{
  "type": "Feature",
  "properties": {
    "iso:country":"US",
    "sg:address":"4054 McKinney Ave",
    "sg:city":"Dallas",
    "sg:classifiers":[
        {
            "category":"Banks & Credit Unions",
            "subcategory":"Bank",
            "type":"Services"
        }
    ],
    "sg:phone":"+1 214 219 2000",
    "sg:postcode":"75204",
    "sg:province":"TX",
    "sg:tags":[
        "personal",
        "short",
        "institution",
        "business"
    ],
    "wof:name":"Production Finance Intl",
    "wof:placetype":"venue"
},
  "geometry": {"coordinates":[-96.792613,32.812825],"type":"Point"}
}