{
  "type": "Feature",
  "properties": {
    "iso:country":"US",
    "sg:address":"220 N 4th St",
    "sg:city":"Kingsville",
    "sg:classifiers":[
        {
            "category":"Education",
            "subcategory":"Library",
            "type":"Public Place"
        }
    ],
    "sg:phone":"+1 361 592 6381",
    "sg:postcode":"78363",
    "sg:province":"TX",
    "wof:name":"Robert J Kleberg Public Lib",
    "wof:placetype":"venue"
},
  "geometry": {"coordinates":[-97.87059000000001,27.518473],"type":"Point"}
}