{
  "type": "Feature",
  "properties": {
    "iso:country":"US",
    "sg:address":"2430 K Ave",
    "sg:city":"Plano",
    "sg:classifiers":[
        {
            "category":"Shopping",
            "subcategory":"Bicycles & Sporting Goods",
            "type":"Retail Goods"
        }
    ],
    "sg:phone":"+1 972 424 1845",
    "sg:postcode":"75074",
    "sg:province":"TX",
    "sg:tags":[
        "medal",
        "plaque",
        "trophies"
    ],
    "wof:name":"Plano Sports Center",
    "wof:placetype":"venue"
},
  "geometry": {"coordinates":[-96.69906,33.030673],"type":"Point"}
}