{
  "type": "Feature",
  "properties": {
    "iso:country":"US",
    "sg:address":"2329 N Fry Rd",
    "sg:city":"Katy",
    "sg:classifiers":[
        {
            "category":"Professional",
            "subcategory":"Accounting & Tax Preparation",
            "type":"Services"
        }
    ],
    "sg:phone":"+1 281 492 8424",
    "sg:postcode":"77449",
    "sg:province":"TX",
    "sg:tags":[
        "accountant",
        "public",
        "certified"
    ],
    "wof:name":"Smith John W",
    "wof:placetype":"venue"
},
  "geometry": {"coordinates":[-95.718982,29.80038],"type":"Point"}
}