{
  "type": "Feature",
  "properties": {
    "iso:country":"US",
    "sg:address":"28723 I- 10 W",
    "sg:city":"Boerne",
    "sg:classifiers":[
        {
            "category":"Personal",
            "subcategory":"Beauty Salon",
            "type":"Services"
        }
    ],
    "sg:phone":"+1 830 755 4341",
    "sg:postcode":"78006",
    "sg:province":"TX",
    "sg:tags":[
        "shop"
    ],
    "wof:name":"Hair Care Studio",
    "wof:placetype":"venue"
},
  "geometry": {"coordinates":[-98.68926999999999,29.740019],"type":"Point"}
}