{
  "type": "Feature",
  "properties": {
    "iso:country":"US",
    "sg:address":"500 W William Cannon Dr",
    "sg:city":"Austin",
    "sg:phone":"+1 512 448 1038",
    "sg:postcode":"78745",
    "sg:province":"TX",
    "sg:website":"http://www.dollartree.com/",
    "wof:name":"Dollar Tree",
    "wof:placetype":"venue"
},
  "geometry": {"coordinates":[-97.785246,30.195901],"type":"Point"}
}