{
  "type": "Feature",
  "properties": {
    "iso:country":"US",
    "sg:address":"1136 E Borgfeld Dr",
    "sg:city":"San Antonio",
    "sg:classifiers":[
        {
            "category":"Retail",
            "subcategory":"Laundry & Dry Cleaning",
            "type":"Services"
        }
    ],
    "sg:phone":"+1 830 980 3302",
    "sg:postcode":"78260",
    "sg:province":"TX",
    "wof:name":"Sunlite Cleaners",
    "wof:placetype":"venue"
},
  "geometry": {"coordinates":[-98.47542199999999,29.713848],"type":"Point"}
}