{
  "type": "Feature",
  "properties": {
    "iso:country":"US",
    "sg:address":"10933 Grissom Ln",
    "sg:city":"Dallas",
    "sg:classifiers":[
        {
            "category":"Retail",
            "subcategory":"Auto Repair",
            "type":"Services"
        }
    ],
    "sg:phone":"+1 972 481 9838",
    "sg:postcode":"75229",
    "sg:province":"TX",
    "sg:tags":[
        "wrecker"
    ],
    "wof:name":"Hollywood Towing",
    "wof:placetype":"venue"
},
  "geometry": {"coordinates":[-96.886976,32.896321],"type":"Point"}
}