{
  "type": "Feature",
  "properties": {
    "iso:country":"US",
    "sg:address":"9207 Coffee St",
    "sg:city":"Houston",
    "sg:classifiers":[
        {
            "category":"Organizations",
            "subcategory":"Religious Organization",
            "type":"Services"
        }
    ],
    "sg:phone":"+1 713 733 2538",
    "sg:postcode":"77033",
    "sg:province":"TX",
    "wof:name":"Fellowship Baptist Church",
    "wof:placetype":"venue"
},
  "geometry": {"coordinates":[-95.352572,29.657242],"type":"Point"}
}