{
  "type": "Feature",
  "properties": {
    "iso:country":"US",
    "sg:address":"3222 Burke Rd",
    "sg:city":"Pasadena",
    "sg:classifiers":[
        {
            "category":"Professional",
            "subcategory":"Accounting & Tax Preparation",
            "type":"Services"
        }
    ],
    "sg:phone":"+1 713 941 2682",
    "sg:postcode":"77504",
    "sg:province":"TX",
    "wof:name":"Sneed Bookkeeping & Tax",
    "wof:placetype":"venue"
},
  "geometry": {"coordinates":[-95.18658600000001,29.658541],"type":"Point"}
}