{
  "type": "Feature",
  "properties": {
    "iso:country":"US",
    "sg:address":"8714 Pagon Cir",
    "sg:city":"Spring",
    "sg:classifiers":[
        {
            "category":"Shopping",
            "subcategory":"Gifts & Souvenirs",
            "type":"Retail Goods"
        }
    ],
    "sg:phone":"+1 281 257 6686",
    "sg:postcode":"77379",
    "sg:province":"TX",
    "wof:name":"Findings of Sherlock",
    "wof:placetype":"venue"
},
  "geometry": {"coordinates":[-95.541387,30.005983],"type":"Point"}
}