{
  "type": "Feature",
  "properties": {
    "iso:country":"US",
    "sg:address":"105 Fay St",
    "sg:city":"Vidor",
    "sg:classifiers":[
        {
            "category":"Real Estate",
            "subcategory":"Real Estate Agent",
            "type":"Services"
        }
    ],
    "sg:phone":"+1 409 783 0400",
    "sg:postcode":"77662",
    "sg:province":"TX",
    "sg:tags":[
        "agency",
        "rental"
    ],
    "wof:name":"River Rat Rentals",
    "wof:placetype":"venue"
},
  "geometry": {"coordinates":[-94.084701,30.169689],"type":"Point"}
}