{
  "type": "Feature",
  "properties": {
    "iso:country":"US",
    "sg:address":"1806 N H St",
    "sg:city":"Midland",
    "sg:classifiers":[
        {
            "category":"Building & Trades",
            "subcategory":"Construction",
            "type":"Services"
        }
    ],
    "sg:phone":"+1 432 570 1644",
    "sg:postcode":"79705",
    "sg:province":"TX",
    "sg:tags":[
        "house"
    ],
    "wof:name":"S&S Remodeling",
    "wof:placetype":"venue"
},
  "geometry": {"coordinates":[-102.096341,32.01422],"type":"Point"}
}