{
  "type": "Feature",
  "properties": {
    "iso:country":"US",
    "sg:address":"3715 Colony Park Dr",
    "sg:city":"Tyler",
    "sg:classifiers":[
        {
            "category":"Professional",
            "subcategory":"Management & Consulting",
            "type":"Services"
        }
    ],
    "sg:phone":"+1 903 526 2525",
    "sg:postcode":"75701",
    "sg:province":"TX",
    "sg:tags":[
        "marketing",
        "program"
    ],
    "wof:name":"CMI Marketing Inc",
    "wof:placetype":"venue"
},
  "geometry": {"coordinates":[-95.295025,32.307065],"type":"Point"}
}