{
  "type": "Feature",
  "properties": {
    "iso:country":"US",
    "sg:address":"2100 S Collins St",
    "sg:city":"Arlington",
    "sg:classifiers":[
        {
            "category":"Retail",
            "subcategory":"Car Wash",
            "type":"Services"
        }
    ],
    "sg:phone":"+1 817 462 8240",
    "sg:postcode":"76010",
    "sg:province":"TX",
    "sg:tags":[
        "carwash"
    ],
    "wof:name":"Pacific Wash LLC",
    "wof:placetype":"venue"
},
  "geometry": {"coordinates":[-97.097651,32.708174],"type":"Point"}
}