{
  "type": "Feature",
  "properties": {
    "iso:country":"US",
    "sg:address":"1009 W 6th",
    "sg:city":"Austin",
    "sg:classifiers":[
        {
            "category":"Shopping",
            "subcategory":"Antiques",
            "type":"Retail Goods"
        },
        {
            "category":"Building & Trades",
            "subcategory":"Construction",
            "type":"Services"
        }
    ],
    "sg:phone":"+1 512 478 9448",
    "sg:postcode":"78703",
    "sg:province":"TX",
    "sg:tags":[
        "interior",
        "design"
    ],
    "sg:website":"www.hemisphereaustin.com",
    "wof:name":"Hemisphere by Whit Hanks",
    "wof:placetype":"venue"
},
  "geometry": {"coordinates":[-97.75470199999999,30.271451],"type":"Point"}
}