{
  "type": "Feature",
  "properties": {
    "iso:country":"US",
    "sg:address":"402 E Wheatland Rd",
    "sg:city":"Dallas",
    "sg:classifiers":[
        {
            "category":"Organizations",
            "subcategory":"Religious Organization",
            "type":"Services"
        }
    ],
    "sg:phone":"+1 972 224 0307",
    "sg:postcode":"75241",
    "sg:province":"TX",
    "sg:tags":[
        "church"
    ],
    "wof:name":"Triumph Missionary Baptist Chr",
    "wof:placetype":"venue"
},
  "geometry": {"coordinates":[-96.81459599999999,32.647643],"type":"Point"}
}