{
  "type": "Feature",
  "properties": {
    "iso:country":"US",
    "sg:address":"3420 Rosefinch Trl",
    "sg:city":"Austin",
    "sg:classifiers":[
        {
            "category":"Professional",
            "subcategory":"Business Services",
            "type":"Services"
        }
    ],
    "sg:phone":"+1 512 347 7555",
    "sg:postcode":"78746",
    "sg:province":"TX",
    "sg:tags":[
        "lecture",
        "bureau",
        "seminar"
    ],
    "wof:name":"Wisdom Tools",
    "wof:placetype":"venue"
},
  "geometry": {"coordinates":[-97.805744,30.274341],"type":"Point"}
}