{
  "type": "Feature",
  "properties": {
    "iso:country":"US",
    "sg:address":"9023 Liptonshire Dr",
    "sg:city":"Dallas",
    "sg:classifiers":[
        {
            "category":"Arts & Performance",
            "subcategory":"Theater",
            "type":"Entertainment"
        }
    ],
    "sg:phone":"+1 214 553 1136",
    "sg:postcode":"75238",
    "sg:province":"TX",
    "sg:tags":[
        "consulting",
        "management",
        "group",
        "s"
    ],
    "wof:name":"Balthrop & Balthrop Inc",
    "wof:placetype":"venue"
},
  "geometry": {"coordinates":[-96.70480999999999,32.870126],"type":"Point"}
}