{
  "type": "Feature",
  "properties": {
    "iso:country":"US",
    "sg:address":"4754 N Cypress Ave",
    "sg:city":"Odessa",
    "sg:classifiers":[
        {
            "category":"Freight",
            "type":"Transportation"
        }
    ],
    "sg:phone":"+1 432 381 2221",
    "sg:postcode":"79764",
    "sg:province":"TX",
    "sg:tags":[
        "operator",
        "local",
        "trucking"
    ],
    "wof:name":"Ross Hotshot & Forklift Svc",
    "wof:placetype":"venue"
},
  "geometry": {"coordinates":[-102.497541,31.867618],"type":"Point"}
}