{
  "type": "Feature",
  "properties": {
    "iso:country":"US",
    "sg:address":"1226 FM 685",
    "sg:city":"Pflugerville",
    "sg:classifiers":[
        {
            "category":"Home & Garden",
            "subcategory":"Home Furnishings",
            "type":"Retail Goods"
        }
    ],
    "sg:phone":"+1 512 989 8192",
    "sg:postcode":"78660",
    "sg:province":"TX",
    "sg:tags":[
        "window",
        "covering"
    ],
    "wof:name":"Ultimate Visions Fashions Inc",
    "wof:placetype":"venue"
},
  "geometry": {"coordinates":[-97.60610800000001,30.449074],"type":"Point"}
}