{
  "type": "Feature",
  "properties": {
    "iso:country":"US",
    "sg:address":"211 Houston St",
    "sg:city":"Richmond",
    "sg:classifiers":[
        {
            "category":"Professional",
            "subcategory":"Lawyer & Legal Services",
            "type":"Services"
        }
    ],
    "sg:phone":"+1 281 341 1771",
    "sg:postcode":"77469",
    "sg:province":"TX",
    "sg:tags":[
        "divorce",
        "attorney",
        "practice",
        "family",
        "law"
    ],
    "wof:name":"Nwanguma Grace N Attorney At Law",
    "wof:placetype":"venue"
},
  "geometry": {"coordinates":[-95.75959400000001,29.581083],"type":"Point"}
}