{
  "type": "Feature",
  "properties": {
    "iso:country":"US",
    "sg:address":"6060 Oak Bay Dr",
    "sg:city":"Houston",
    "sg:classifiers":[
        {
            "category":"Freight",
            "type":"Transportation"
        }
    ],
    "sg:phone":"+1 713 682 2561",
    "sg:postcode":"77091",
    "sg:province":"TX",
    "sg:tags":[
        "operator",
        "local",
        "trucking"
    ],
    "wof:name":"KJ&e Contract Hauling Inc",
    "wof:placetype":"venue"
},
  "geometry": {"coordinates":[-95.46800500000001,29.854545],"type":"Point"}
}