{
  "type": "Feature",
  "properties": {
    "iso:country":"US",
    "sg:address":"901 S Mo-Pac Expy",
    "sg:city":"Austin",
    "sg:classifiers":[
        {
            "category":"Autos & Motor Vehicles",
            "subcategory":"Automobile Sales",
            "type":"Retail Goods"
        }
    ],
    "sg:phone":"+1 512 306 6200",
    "sg:postcode":"78746",
    "sg:province":"TX",
    "sg:tags":[
        "car",
        "dealer"
    ],
    "wof:name":"Auto Save",
    "wof:placetype":"venue"
},
  "geometry": {"coordinates":[-97.783118,30.26624],"type":"Point"}
}