{
  "type": "Feature",
  "properties": {
    "iso:country":"US",
    "sg:address":"2719 N Stanton St",
    "sg:city":"El Paso",
    "sg:classifiers":[
        {
            "category":"Education",
            "subcategory":"Dance Studio",
            "type":"Public Place"
        }
    ],
    "sg:phone":"+1 915 532 2043",
    "sg:postcode":"79902",
    "sg:province":"TX",
    "wof:name":"Shundo Ballroom Dance Studio",
    "wof:placetype":"venue"
},
  "geometry": {"coordinates":[-106.50287299999999,31.778048],"type":"Point"}
}