{
  "type": "Feature",
  "properties": {
    "iso:country":"US",
    "sg:address":"2919 Spring Creek Dr",
    "sg:city":"Spring",
    "sg:classifiers":[
        {
            "category":"Home & Garden",
            "subcategory":"Building Materials",
            "type":"Retail Goods"
        }
    ],
    "sg:phone":"+1 281 651 9018",
    "sg:postcode":"77373",
    "sg:province":"TX",
    "wof:name":"My Paints Horse Breeding & Boa",
    "wof:placetype":"venue"
},
  "geometry": {"coordinates":[-95.391161,30.075106],"type":"Point"}
}