{
  "type": "Feature",
  "properties": {
    "iso:country":"US",
    "sg:address":"907 W 69th St",
    "sg:city":"Odessa",
    "sg:classifiers":[
        {
            "category":"Professional",
            "subcategory":"Art Services",
            "type":"Services"
        },
        {
            "category":"Building & Trades",
            "subcategory":"Electrical",
            "type":"Services"
        }
    ],
    "sg:phone":"+1 432 367 3626",
    "sg:postcode":"79764",
    "sg:province":"TX",
    "sg:tags":[
        "industrial",
        "electrician",
        "electric",
        "consultant",
        "designer",
        "lighting",
        "contractors-commercial"
    ],
    "sg:website":"http://www.electricdoctor.biz",
    "wof:name":"Foreman Electric Service Co Inc",
    "wof:placetype":"venue"
},
  "geometry": {"coordinates":[-102.40626,31.905749],"type":"Point"}
}