{
  "type": "Feature",
  "properties": {
    "iso:country":"US",
    "sg:address":"5510 N Cage Blvd",
    "sg:city":"Pharr",
    "sg:classifiers":[
        {
            "category":"Professional",
            "type":"Services"
        }
    ],
    "sg:phone":"+1 956 781 1111",
    "sg:postcode":"78577",
    "sg:province":"TX",
    "wof:name":"Robert Gstel B Lndmark Bus Ctr",
    "wof:placetype":"venue"
},
  "geometry": {"coordinates":[-98.176401,26.24235],"type":"Point"}
}