{
  "type": "Feature",
  "properties": {
    "iso:country":"US",
    "sg:address":"3202 N Piedras St",
    "sg:city":"El Paso",
    "sg:classifiers":[
        {
            "category":"Shopping",
            "subcategory":"Optical Goods",
            "type":"Retail Goods"
        }
    ],
    "sg:phone":"+1 915 566 4646",
    "sg:postcode":"79930",
    "sg:province":"TX",
    "wof:name":"Optical Co",
    "wof:placetype":"venue"
},
  "geometry": {"coordinates":[-106.46128,31.805915],"type":"Point"}
}