{
  "type": "Feature",
  "properties": {
    "iso:country":"US",
    "sg:address":"11111 Woodmeadow Pkwy",
    "sg:city":"Dallas",
    "sg:classifiers":[
        {
            "category":"Sports & Exercise",
            "subcategory":"Gym",
            "type":"Entertainment"
        }
    ],
    "sg:phone":"+1 972 686 0335",
    "sg:postcode":"75228",
    "sg:province":"TX",
    "sg:tags":[
        "fitness",
        "physical",
        "facility"
    ],
    "wof:name":"Dinamite Dames",
    "wof:placetype":"venue"
},
  "geometry": {"coordinates":[-96.640192,32.846517],"type":"Point"}
}