{
  "type": "Feature",
  "properties": {
    "iso:country":"US",
    "sg:address":"5805 Taylor Draper Cove",
    "sg:city":"Austin",
    "sg:classifiers":[
        {
            "category":"Professional",
            "subcategory":"Computer Services",
            "type":"Services"
        }
    ],
    "sg:phone":"+1 512 826 5871",
    "sg:postcode":"78759",
    "sg:province":"TX",
    "sg:tags":[
        "prepackaged",
        "software"
    ],
    "wof:name":"Evoke Systems Inc",
    "wof:placetype":"venue"
},
  "geometry": {"coordinates":[-97.757412,30.416954],"type":"Point"}
}