{
  "type": "Feature",
  "properties": {
    "iso:country":"US",
    "sg:address":"5002 Saddle Ridge Trl",
    "sg:city":"San Angelo",
    "sg:classifiers":[
        {
            "category":"Building & Trades",
            "subcategory":"Landscaping Services",
            "type":"Services"
        }
    ],
    "sg:phone":"+1 325 947 8227",
    "sg:postcode":"76904",
    "sg:province":"TX",
    "sg:tags":[
        "landscape",
        "contractor"
    ],
    "wof:name":"Deco Curb Of San Angelo",
    "wof:placetype":"venue"
},
  "geometry": {"coordinates":[-100.495175,31.410772],"type":"Point"}
}