{
  "type": "Feature",
  "properties": {
    "iso:country":"US",
    "sg:address":"5901 Kovarik Rd",
    "sg:city":"Wichita Falls",
    "sg:classifiers":[
        {
            "category":"Building & Trades",
            "subcategory":"Plumbing",
            "type":"Services"
        }
    ],
    "sg:phone":"+1 940 692 2381",
    "sg:postcode":"76310",
    "sg:province":"TX",
    "sg:tags":[
        "contractor"
    ],
    "wof:name":"Holcomb Eddie AC Htg & Plbg",
    "wof:placetype":"venue"
},
  "geometry": {"coordinates":[-98.600084,33.887635],"type":"Point"}
}