{
  "type": "Feature",
  "properties": {
    "iso:country":"US",
    "sg:address":"4912 Almond Ave",
    "sg:city":"Dallas",
    "sg:classifiers":[
        {
            "category":"Autos & Motor Vehicles",
            "subcategory":"Auto Supplies",
            "type":"Retail Goods"
        },
        {
            "category":"Retail",
            "subcategory":"Car Wash",
            "type":"Services"
        },
        {
            "category":"Retail",
            "subcategory":"Auto Repair",
            "type":"Services"
        }
    ],
    "sg:phone":"+1 214 637 1168",
    "sg:postcode":"75247",
    "sg:province":"TX",
    "sg:tags":[
        "body",
        "lettering",
        "washing",
        "equipment",
        "truck",
        "cleaning",
        "painting"
    ],
    "sg:website":"http://www.southstarbigrig.com",
    "wof:name":"South Star Truck Wash & Detail Service",
    "wof:placetype":"venue"
},
  "geometry": {"coordinates":[-96.87930799999999,32.806892],"type":"Point"}
}