{
  "type": "Feature",
  "properties": {
    "iso:country":"US",
    "sg:address":"1720 E Pioneer Pkwy",
    "sg:city":"Arlington",
    "sg:classifiers":[
        {
            "category":"Freight",
            "type":"Transportation"
        }
    ],
    "sg:phone":"+1 817 277 4433",
    "sg:postcode":"76010",
    "sg:province":"TX",
    "sg:tags":[
        "special"
    ],
    "wof:name":"U Store Pioneer",
    "wof:placetype":"venue"
},
  "geometry": {"coordinates":[-97.08078,32.709823],"type":"Point"}
}