{
  "type": "Feature",
  "properties": {
    "iso:country":"US",
    "sg:address":"3106 W Cuthbert Ave",
    "sg:city":"Midland",
    "sg:classifiers":[
        {
            "category":"Shopping",
            "subcategory":"Gifts & Souvenirs",
            "type":"Retail Goods"
        }
    ],
    "sg:phone":"+1 432 694 8846",
    "sg:postcode":"79701",
    "sg:province":"TX",
    "sg:tags":[
        "shop"
    ],
    "sg:website":"http://www.hallmark.com",
    "wof:name":"Hallmark Gold Crown",
    "wof:placetype":"venue"
},
  "geometry": {"coordinates":[-102.11647499999999,31.999055],"type":"Point"}
}