{
  "type": "Feature",
  "properties": {
    "iso:country":"US",
    "sg:address":"3501 Helena Ave",
    "sg:city":"Mcallen",
    "sg:classifiers":[
        {
            "category":"Government",
            "subcategory":"Police Station",
            "type":"Public Place"
        }
    ],
    "sg:phone":"+1 956 972 7402",
    "sg:postcode":"78503",
    "sg:province":"TX",
    "sg:tags":[
        "department"
    ],
    "wof:name":"Mc Allen Police Dept",
    "wof:placetype":"venue"
},
  "geometry": {"coordinates":[-98.26597700000001,26.167501],"type":"Point"}
}