{
  "type": "Feature",
  "properties": {
    "iso:country":"US",
    "sg:address":"8711 Wind Stream Dr",
    "sg:city":"Houston",
    "sg:classifiers":[
        {
            "category":"Organizations",
            "subcategory":"Religious Organization",
            "type":"Services"
        }
    ],
    "sg:phone":"+1 713 466 8937",
    "sg:postcode":"77040",
    "sg:province":"TX",
    "wof:name":"Trinity Fncl Svcs",
    "wof:placetype":"venue"
},
  "geometry": {"coordinates":[-95.529518,29.877977],"type":"Point"}
}