{
  "type": "Feature",
  "properties": {
    "iso:country":"US",
    "sg:address":"4919 Shadylane Dr",
    "sg:city":"Midland",
    "sg:classifiers":[
        {
            "category":"Education",
            "subcategory":"School",
            "type":"Public Place"
        }
    ],
    "sg:phone":"+1 432 689 1810",
    "sg:postcode":"79703",
    "sg:province":"TX",
    "wof:name":"Jones Elementary School",
    "wof:placetype":"venue"
},
  "geometry": {"coordinates":[-102.14458500000001,31.981842],"type":"Point"}
}