{
  "type": "Feature",
  "properties": {
    "iso:country":"US",
    "sg:address":"4119 Ramona Ave",
    "sg:city":"Dallas",
    "sg:classifiers":[
        {
            "category":"Organizations",
            "subcategory":"Religious Organization",
            "type":"Services"
        }
    ],
    "sg:phone":"+1 214 372 2150",
    "sg:postcode":"75216",
    "sg:province":"TX",
    "wof:name":"Good Tree Missionary Baptist",
    "wof:placetype":"venue"
},
  "geometry": {"coordinates":[-96.803614,32.694826],"type":"Point"}
}