{
  "type": "Feature",
  "properties": {
    "iso:country":"US",
    "sg:address":"1025 N Stemmons Fwy Ste 700",
    "sg:city":"Dallas",
    "sg:classifiers":[
        {
            "category":"Shopping",
            "subcategory":"Crafts & Fabrics",
            "type":"Retail Goods"
        }
    ],
    "sg:phone":"+1 214 748 5793",
    "sg:postcode":"75207",
    "sg:province":"TX",
    "sg:tags":[
        "store"
    ],
    "sg:website":"www.stroheimandromann.com",
    "wof:name":"Stroheim & Romann",
    "wof:placetype":"venue"
},
  "geometry": {"coordinates":[-96.813711,32.787168],"type":"Point"}
}