{
  "type": "Feature",
  "properties": {
    "iso:country":"US",
    "sg:address":"2100 W Northwest Hwy",
    "sg:city":"Grapevine",
    "sg:classifiers":[
        {
            "category":"Restaurant",
            "type":"Food & Drink"
        }
    ],
    "sg:menulink":"http://www.allmenus.com/tx/northeast-tarrant/65198-cicis-pizza-buffet/menu/",
    "sg:phone":"+1 817 421 9868",
    "sg:postcode":"76051",
    "sg:province":"TX",
    "sg:tags":[
        "american",
        "pizza"
    ],
    "wof:name":"CiCi's Pizza Buffet",
    "wof:placetype":"venue"
},
  "geometry": {"coordinates":[-97.099917,32.943055],"type":"Point"}
}