{
  "type": "Feature",
  "properties": {
    "iso:country":"US",
    "sg:address":"10723 Kenosha Ave",
    "sg:city":"Lubbock",
    "sg:classifiers":[
        {
            "category":"Retail",
            "subcategory":"Auto Repair",
            "type":"Services"
        }
    ],
    "sg:phone":"+1 806 745 0273",
    "sg:postcode":"79423",
    "sg:province":"TX",
    "sg:tags":[
        "general"
    ],
    "wof:name":"Allstar Enterprises",
    "wof:placetype":"venue"
},
  "geometry": {"coordinates":[-101.892079,33.496747],"type":"Point"}
}