{
  "type": "Feature",
  "properties": {
    "iso:country":"US",
    "sg:address":"10805 N Lamar Blvd",
    "sg:city":"Austin",
    "sg:classifiers":[
        {
            "category":"Retail",
            "subcategory":"Auto Repair",
            "type":"Services"
        }
    ],
    "sg:phone":"+1 512 835 4545",
    "sg:postcode":"78753",
    "sg:province":"TX",
    "sg:tags":[
        "repairing",
        "automobile"
    ],
    "sg:website":"www.autosystemsworkshop.com",
    "wof:name":"Autosystems Workshop",
    "wof:placetype":"venue"
},
  "geometry": {"coordinates":[-97.688906,30.377308],"type":"Point"}
}