{
  "type": "Feature",
  "properties": {
    "iso:country":"US",
    "sg:address":"339 W Norwood Ct",
    "sg:city":"San Antonio",
    "sg:classifiers":[
        {
            "category":"Wholesale",
            "subcategory":"Construction Materials",
            "type":"Manufacturing & Wholesale Goods"
        }
    ],
    "sg:phone":"+1 210 824 9957",
    "sg:postcode":"78212",
    "sg:province":"TX",
    "wof:name":"Cardinal Roof Supply",
    "wof:placetype":"venue"
},
  "geometry": {"coordinates":[-98.498643,29.468002],"type":"Point"}
}