{
  "type": "Feature",
  "properties": {
    "iso:country":"US",
    "sg:address":"The Wellness Center 7731 SW Freeway, Ste 201",
    "sg:city":"Houston",
    "sg:classifiers":[
        {
            "category":"Community Center",
            "type":"Public Place"
        }
    ],
    "sg:phone":"+1 866 577 8346",
    "sg:postcode":"77074",
    "sg:province":"TX",
    "sg:tags":[
        "medical"
    ],
    "sg:website":"www.evlt.com/varicose-veins/hous...",
    "wof:name":"The Vein Treatment Center",
    "wof:placetype":"venue"
},
  "geometry": {"coordinates":[-95.522497,29.695571],"type":"Point"}
}