{
  "type": "Feature",
  "properties": {
    "iso:country":"US",
    "sg:address":"105 Streckert Dr",
    "sg:city":"Brownwood",
    "sg:classifiers":[
        {
            "category":"Health Services",
            "subcategory":"Doctor",
            "type":"Services"
        }
    ],
    "sg:phone":"+1 325 643 3300",
    "sg:postcode":"76801",
    "sg:province":"TX",
    "sg:tags":[
        "physician",
        "surgeon"
    ],
    "wof:name":"Heart Of Texas Internal Med",
    "wof:placetype":"venue"
},
  "geometry": {"coordinates":[-98.993166,31.679201],"type":"Point"}
}