{
  "type": "Feature",
  "properties": {
    "iso:country":"US",
    "sg:address":"5848 Hwy 78",
    "sg:city":"Sachse",
    "sg:classifiers":[
        {
            "category":"Fast Food",
            "type":"Food & Drink"
        }
    ],
    "sg:phone":"+1 972 530 6381",
    "sg:postcode":"75048",
    "sg:province":"TX",
    "sg:tags":[
        "burger"
    ],
    "sg:website":"burgerisland6.webs.com/",
    "wof:name":"Burger Island",
    "wof:placetype":"venue"
},
  "geometry": {"coordinates":[-96.595901,32.975883],"type":"Point"}
}