{
  "type": "Feature",
  "properties": {
    "iso:country":"US",
    "sg:address":"1 Briar Oak Cir",
    "sg:city":"Lumberton",
    "sg:classifiers":[
        {
            "category":"Building & Trades",
            "subcategory":"Construction",
            "type":"Services"
        }
    ],
    "sg:phone":"+1 409 755 6945",
    "sg:postcode":"77657",
    "sg:province":"TX",
    "sg:tags":[
        "house"
    ],
    "wof:name":"Awf Builders LLC",
    "wof:placetype":"venue"
},
  "geometry": {"coordinates":[-94.216672,30.29223],"type":"Point"}
}