{
  "type": "Feature",
  "properties": {
    "iso:country":"US",
    "sg:address":"3104 Dawes Dr",
    "sg:city":"Dallas",
    "sg:classifiers":[
        {
            "category":"Insurance",
            "subcategory":"Insurance Agent",
            "type":"Services"
        }
    ],
    "sg:phone":"+1 214 339 6378",
    "sg:postcode":"75211",
    "sg:province":"TX",
    "wof:name":"Manuel Frias Insurance",
    "wof:placetype":"venue"
},
  "geometry": {"coordinates":[-96.872637,32.727079],"type":"Point"}
}