{
  "type": "Feature",
  "properties": {
    "iso:country":"US",
    "sg:address":"111 W Adoue St",
    "sg:city":"Alvin",
    "sg:classifiers":[
        {
            "category":"Farming",
            "subcategory":"Farm",
            "type":"Manufacturing & Wholesale Goods"
        }
    ],
    "sg:phone":"+1 281 585 8340",
    "sg:postcode":"77511",
    "sg:province":"TX",
    "sg:tags":[
        "soybean",
        "grain",
        "cash",
        "crop",
        "general"
    ],
    "wof:name":"Jcm Farms",
    "wof:placetype":"venue"
},
  "geometry": {"coordinates":[-95.244674,29.420204],"type":"Point"}
}