{
  "type": "Feature",
  "properties": {
    "iso:country":"US",
    "sg:address":"1605 N Houston School Rd",
    "sg:city":"Lancaster",
    "sg:classifiers":[
        {
            "category":"Real Estate",
            "subcategory":"Real Estate Agent",
            "type":"Services"
        }
    ],
    "sg:phone":"+1 972 994 9596",
    "sg:postcode":"75134",
    "sg:province":"TX",
    "wof:name":"Primrose Houston One Hsing LP",
    "wof:placetype":"venue"
},
  "geometry": {"coordinates":[-96.805708,32.606922],"type":"Point"}
}