{
  "type": "Feature",
  "properties": {
    "iso:country":"US",
    "sg:address":"1233 N 3rd St",
    "sg:city":"Abilene",
    "sg:classifiers":[
        {
            "category":"Wholesale",
            "subcategory":"Computers",
            "type":"Manufacturing & Wholesale Goods"
        }
    ],
    "sg:phone":"+1 325 677 0775",
    "sg:postcode":"79601",
    "sg:province":"TX",
    "wof:name":"Toner Tiger Inc",
    "wof:placetype":"venue"
},
  "geometry": {"coordinates":[-99.73622,32.451674],"type":"Point"}
}