{
  "type": "Feature",
  "properties": {
    "iso:country":"US",
    "sg:address":"2808 2nd St",
    "sg:city":"Pleasanton",
    "sg:classifiers":[
        {
            "category":"Retail",
            "subcategory":"Auto Repair",
            "type":"Services"
        }
    ],
    "sg:phone":"+1 830 281 8506",
    "sg:postcode":"78064",
    "sg:province":"TX",
    "sg:tags":[
        "repairing",
        "automobile"
    ],
    "wof:name":"Automotive Service & Repair",
    "wof:placetype":"venue"
},
  "geometry": {"coordinates":[-98.479811,28.985124],"type":"Point"}
}