{
  "type": "Feature",
  "properties": {
    "iso:country":"US",
    "sg:address":"4929 Forest Ln",
    "sg:city":"Dallas",
    "sg:classifiers":[
        {
            "category":"Shopping",
            "subcategory":"Computers & Home Electronics",
            "type":"Retail Goods"
        }
    ],
    "sg:phone":"+1 972 668 7700",
    "sg:postcode":"75244",
    "sg:province":"TX",
    "sg:tags":[
        "software"
    ],
    "wof:name":"International Tech",
    "wof:placetype":"venue"
},
  "geometry": {"coordinates":[-96.824341,32.909682],"type":"Point"}
}