{
  "type": "Feature",
  "properties": {
    "iso:country":"US",
    "sg:address":"12221 Merit Dr Ste 1000",
    "sg:city":"Dallas",
    "sg:classifiers":[
        {
            "category":"Professional",
            "subcategory":"Employment Agencies",
            "type":"Services"
        }
    ],
    "sg:phone":"+1 972 881 1313",
    "sg:postcode":"75251",
    "sg:province":"TX",
    "wof:name":"Insource Group the",
    "wof:placetype":"venue"
},
  "geometry": {"coordinates":[-96.772301,32.914001],"type":"Point"}
}