{
  "type": "Feature",
  "properties": {
    "iso:country":"US",
    "sg:address":"499 Flowing Wells Rd",
    "sg:city":"Pottsboro",
    "sg:classifiers":[
        {
            "category":"Building & Trades",
            "subcategory":"Landscaping Services",
            "type":"Services"
        }
    ],
    "sg:phone":"+1 903 786 9728",
    "sg:postcode":"75076",
    "sg:province":"TX",
    "sg:tags":[
        "landscape",
        "contractor"
    ],
    "wof:name":"Aaron's Sprinkler & Lndscpng",
    "wof:placetype":"venue"
},
  "geometry": {"coordinates":[-96.74803799999999,33.7783],"type":"Point"}
}