{
  "type": "Feature",
  "properties": {
    "iso:country":"US",
    "sg:address":"501 E Main St",
    "sg:city":"Arlington",
    "sg:classifiers":[
        {
            "category":"Manufacturing",
            "subcategory":"Glass & Minerals",
            "type":"Manufacturing & Wholesale Goods"
        }
    ],
    "sg:phone":"+1 817 265 0980",
    "sg:postcode":"76010",
    "sg:province":"TX",
    "sg:tags":[
        "concrete",
        "product",
        "mfg"
    ],
    "wof:name":"Pieresearch Inc",
    "wof:placetype":"venue"
},
  "geometry": {"coordinates":[-97.101653,32.73636],"type":"Point"}
}