{
  "type": "Feature",
  "properties": {
    "iso:country":"US",
    "sg:address":"5221 Quail Creek Ct",
    "sg:city":"Keller",
    "sg:classifiers":[
        {
            "category":"Health Services",
            "subcategory":"Doctor",
            "type":"Services"
        }
    ],
    "sg:phone":"+1 817 741 5050",
    "sg:postcode":"76248",
    "sg:province":"TX",
    "wof:name":"Blue Ridge Dental",
    "wof:placetype":"venue"
},
  "geometry": {"coordinates":[-97.267892,32.945274],"type":"Point"}
}