{
  "type": "Feature",
  "properties": {
    "iso:country":"US",
    "sg:address":"1134 US Hwy 290 Bus",
    "sg:city":"Elgin",
    "sg:classifiers":[
        {
            "category":"Restaurant",
            "type":"Food & Drink"
        }
    ],
    "sg:phone":"+1 512 285 5521",
    "sg:postcode":"78621",
    "sg:province":"TX",
    "sg:tags":[
        "eating"
    ],
    "wof:name":"Sonic Drive-In",
    "wof:placetype":"venue"
},
  "geometry": {"coordinates":[-97.37968100000001,30.35517],"type":"Point"}
}