{
  "type": "Feature",
  "properties": {
    "iso:country":"US",
    "sg:address":"314 Pasadena Blvd",
    "sg:city":"Pasadena",
    "sg:classifiers":[
        {
            "category":"Retail",
            "subcategory":"Portrait Studio",
            "type":"Services"
        }
    ],
    "sg:phone":"+1 281 787 7088",
    "sg:postcode":"77506",
    "sg:province":"TX",
    "sg:tags":[
        "photographer"
    ],
    "wof:name":"A Fine Print Photography",
    "wof:placetype":"venue"
},
  "geometry": {"coordinates":[-95.201168,29.707702],"type":"Point"}
}