{
  "type": "Feature",
  "properties": {
    "iso:country":"US",
    "sg:address":"1820 Tom Bolt Dr",
    "sg:city":"El Paso",
    "sg:classifiers":[
        {
            "category":"Retail",
            "subcategory":"Repair Shop",
            "type":"Services"
        }
    ],
    "sg:phone":"+1 915 598 8993",
    "sg:postcode":"79936",
    "sg:province":"TX",
    "wof:name":"Hemisphere Aviation",
    "wof:placetype":"venue"
},
  "geometry": {"coordinates":[-106.31189999999999,31.767988],"type":"Point"}
}