{
  "type": "Feature",
  "properties": {
    "iso:country":"US",
    "sg:address":"6600 Paige Rd",
    "sg:city":"The Colony",
    "sg:classifiers":[
        {
            "category":"Professional",
            "subcategory":"Accounting & Tax Preparation",
            "type":"Services"
        }
    ],
    "sg:phone":"+1 469 384 4300",
    "sg:postcode":"75056",
    "sg:province":"TX",
    "sg:tags":[
        "accountant"
    ],
    "wof:name":"Daniel Saji CPA",
    "wof:placetype":"venue"
},
  "geometry": {"coordinates":[-96.87558,33.092983],"type":"Point"}
}