{
  "type": "Feature",
  "properties": {
    "iso:country":"US",
    "sg:address":"4238 Custer Creek Dr",
    "sg:city":"Missouri City",
    "sg:classifiers":[
        {
            "category":"Shopping",
            "subcategory":"Computers & Home Electronics",
            "type":"Retail Goods"
        }
    ],
    "sg:phone":"+1 281 499 9324",
    "sg:postcode":"77459",
    "sg:province":"TX",
    "wof:name":"Echotech",
    "wof:placetype":"venue"
},
  "geometry": {"coordinates":[-95.568663,29.603962],"type":"Point"}
}