{
  "type": "Feature",
  "properties": {
    "iso:country":"US",
    "sg:address":"113 S Carmack St",
    "sg:city":"Mesquite",
    "sg:classifiers":[
        {
            "category":"Building & Trades",
            "subcategory":"Landscaping Services",
            "type":"Services"
        }
    ],
    "sg:phone":"+1 972 289 3845",
    "sg:postcode":"75149",
    "sg:province":"TX",
    "wof:name":"A&C Lawncare Landscape",
    "wof:placetype":"venue"
},
  "geometry": {"coordinates":[-96.60575300000001,32.766924],"type":"Point"}
}