{
  "type": "Feature",
  "properties": {
    "iso:country":"US",
    "sg:address":"1636 Winchester Way",
    "sg:city":"Bedford",
    "sg:classifiers":[
        {
            "category":"Professional",
            "subcategory":"Computer Services",
            "type":"Services"
        }
    ],
    "sg:phone":"+1 817 267 6423",
    "sg:postcode":"76022",
    "sg:province":"TX",
    "sg:tags":[
        "timber",
        "operation",
        "management",
        "tract",
        "facility"
    ],
    "wof:name":"Tim Barnes Digital Retouch",
    "wof:placetype":"venue"
},
  "geometry": {"coordinates":[-97.14182,32.828324],"type":"Point"}
}