{
  "type": "Feature",
  "properties": {
    "iso:country":"US",
    "sg:address":"4110 Alameda Ave",
    "sg:city":"El Paso",
    "sg:classifiers":[
        {
            "category":"Travel",
            "subcategory":"Hotels & Motels",
            "type":"Entertainment"
        }
    ],
    "sg:phone":"+1 915 533 7595",
    "sg:postcode":"79905",
    "sg:province":"TX",
    "sg:tags":[
        "operation"
    ],
    "wof:name":"Stage Coach Inn Motel",
    "wof:placetype":"venue"
},
  "geometry": {"coordinates":[-106.442684,31.773219],"type":"Point"}
}