{
  "type": "Feature",
  "properties": {
    "iso:country":"US",
    "sg:address":"12959 Jupiter Rd",
    "sg:city":"Dallas",
    "sg:classifiers":[
        {
            "category":"Real Estate",
            "subcategory":"Real Estate Services",
            "type":"Services"
        }
    ],
    "sg:phone":"+1 214 553 9284",
    "sg:postcode":"75238",
    "sg:province":"TX",
    "sg:tags":[
        "management",
        "property"
    ],
    "wof:name":"Andrews-Dillingham Properties",
    "wof:placetype":"venue"
},
  "geometry": {"coordinates":[-96.683333,32.872398],"type":"Point"}
}