{
  "type": "Feature",
  "properties": {
    "iso:country":"US",
    "sg:address":"4520 W 34th St",
    "sg:city":"Houston",
    "sg:classifiers":[
        {
            "category":"Building & Trades",
            "subcategory":"Construction",
            "type":"Services"
        }
    ],
    "sg:phone":"+1 713 683 9096",
    "sg:postcode":"77092",
    "sg:province":"TX",
    "sg:tags":[
        "repairing",
        "remodeling",
        "contractor"
    ],
    "wof:name":"About Face Kitchen & Bath",
    "wof:placetype":"venue"
},
  "geometry": {"coordinates":[-95.457094,29.81951],"type":"Point"}
}