{
  "type": "Feature",
  "properties": {
    "iso:country":"US",
    "sg:address":"7010 Pembrough Ln",
    "sg:city":"Katy",
    "sg:classifiers":[
        {
            "category":"Real Estate",
            "subcategory":"Architect",
            "type":"Services"
        }
    ],
    "sg:phone":"+1 281 395 2329",
    "sg:postcode":"77494",
    "sg:province":"TX",
    "sg:tags":[
        "illustrator",
        "architectural"
    ],
    "wof:name":"Architectural Portraits",
    "wof:placetype":"venue"
},
  "geometry": {"coordinates":[-95.779664,29.703827],"type":"Point"}
}