{
  "type": "Feature",
  "properties": {
    "iso:country":"US",
    "sg:address":"2406 Henderson Dr",
    "sg:city":"Arlington",
    "sg:classifiers":[
        {
            "category":"Social Services",
            "subcategory":"Child Care",
            "type":"Services"
        }
    ],
    "sg:phone":"+1 817 460 5264",
    "sg:postcode":"76010",
    "sg:province":"TX",
    "wof:name":"Ndines Daycare",
    "wof:placetype":"venue"
},
  "geometry": {"coordinates":[-97.068082,32.708585],"type":"Point"}
}