{
  "type": "Feature",
  "properties": {
    "iso:country":"US",
    "sg:address":"3742 Far West Blvd",
    "sg:city":"Austin",
    "sg:classifiers":[
        {
            "category":"Shopping",
            "subcategory":"Gifts & Souvenirs",
            "type":"Retail Goods"
        }
    ],
    "sg:phone":"+1 512 502 9133",
    "sg:postcode":"78731",
    "sg:province":"TX",
    "sg:tags":[
        "shop"
    ],
    "wof:name":"Blizzie's",
    "wof:placetype":"venue"
},
  "geometry": {"coordinates":[-97.76021299999999,30.356806],"type":"Point"}
}