{
  "type": "Feature",
  "properties": {
    "iso:country":"US",
    "sg:address":"9860 Johnson Rd",
    "sg:city":"Montgomery",
    "sg:classifiers":[
        {
            "category":"Wholesale",
            "subcategory":"Machinery & Supplies",
            "type":"Manufacturing & Wholesale Goods"
        }
    ],
    "sg:phone":"+1 936 588 5304",
    "sg:postcode":"77316",
    "sg:province":"TX",
    "sg:tags":[
        "valve"
    ],
    "wof:name":"Crane Valve North America",
    "wof:placetype":"venue"
},
  "geometry": {"coordinates":[-95.61292,30.316896],"type":"Point"}
}