{
  "type": "Feature",
  "properties": {
    "iso:country":"US",
    "sg:address":"1000 Main Street, Suite 2400",
    "sg:city":"Houston",
    "sg:classifiers":[
        {
            "category":"Shopping",
            "subcategory":"Pets & Pet Supplies",
            "type":"Retail Goods"
        }
    ],
    "sg:postcode":"77007",
    "sg:province":"TX",
    "sg:website":"redcollarrescue.petfinder.com",
    "wof:name":"Red Collar Rescue",
    "wof:placetype":"venue"
},
  "geometry": {"coordinates":[-95.365662,29.756846],"type":"Point"}
}