{
  "type": "Feature",
  "properties": {
    "iso:country":"US",
    "sg:address":"5410 North Fwy",
    "sg:city":"Houston",
    "sg:classifiers":[
        {
            "category":"Food & Beverages",
            "subcategory":"Liquor & Beverages",
            "type":"Retail Goods"
        }
    ],
    "sg:phone":"+1 713 694 6404",
    "sg:postcode":"77076",
    "sg:province":"TX",
    "sg:tags":[
        "beer",
        "spirit",
        "wine"
    ],
    "wof:name":"K & B Liquor Store",
    "wof:placetype":"venue"
},
  "geometry": {"coordinates":[-95.392601,29.846001],"type":"Point"}
}