{
  "type": "Feature",
  "properties": {
    "iso:country":"US",
    "sg:address":"272 E Rosewood Ave",
    "sg:city":"San Antonio",
    "sg:classifiers":[
        {
            "category":"Professional",
            "type":"Services"
        }
    ],
    "sg:phone":"+1 210 736 1217",
    "sg:postcode":"78212",
    "sg:province":"TX",
    "wof:name":"Vista Therapy",
    "wof:placetype":"venue"
},
  "geometry": {"coordinates":[-98.49068200000001,29.464995],"type":"Point"}
}