{
  "type": "Feature",
  "properties": {
    "iso:country":"US",
    "sg:address":"5100 Westheimer Rd",
    "sg:city":"Houston",
    "sg:classifiers":[
        {
            "category":"Personal",
            "type":"Services"
        },
        {
            "category":"Shopping",
            "subcategory":"Bridal",
            "type":"Retail Goods"
        }
    ],
    "sg:phone":"+1 713 968 6566",
    "sg:postcode":"77056",
    "sg:province":"TX",
    "sg:tags":[
        "planning",
        "wedding"
    ],
    "wof:name":"Brides by Renee",
    "wof:placetype":"venue"
},
  "geometry": {"coordinates":[-95.464203,29.740801],"type":"Point"}
}