{
  "type": "Feature",
  "properties": {
    "iso:country":"US",
    "sg:address":"340 Garden Oaks Blvd",
    "sg:city":"Houston",
    "sg:classifiers":[
        {
            "category":"Wholesale",
            "subcategory":"Durable Goods & Equipment",
            "type":"Manufacturing & Wholesale Goods"
        },
        {
            "category":"Manufacturing",
            "subcategory":"Building Materials",
            "type":"Manufacturing & Wholesale Goods"
        }
    ],
    "sg:phone":"+1 713 242 9114",
    "sg:postcode":"77018",
    "sg:province":"TX",
    "sg:tags":[
        "filtering",
        "filters-liquid-wholesale",
        "supply"
    ],
    "sg:website":"http://www.greenmarineinc.com",
    "wof:name":"Green Marine & Indus Equip Co",
    "wof:placetype":"venue"
},
  "geometry": {"coordinates":[-95.40512,29.825976],"type":"Point"}
}