{
  "type": "Feature",
  "properties": {
    "iso:country":"US",
    "sg:address":"2803 Ave B",
    "sg:city":"Brownwood",
    "sg:classifiers":[
        {
            "category":"Food & Beverages",
            "subcategory":"Groceries & Convenience Stores",
            "type":"Retail Goods"
        }
    ],
    "sg:phone":"+1 325 646 7645",
    "sg:postcode":"76801",
    "sg:province":"TX",
    "wof:name":"Food Plaza 3",
    "wof:placetype":"venue"
},
  "geometry": {"coordinates":[-98.995611,31.700297],"type":"Point"}
}