{
  "type": "Feature",
  "properties": {
    "iso:country":"US",
    "sg:address":"309 Ashland Ct",
    "sg:city":"Gainesville",
    "sg:classifiers":[
        {
            "category":"Banks & Credit Unions",
            "subcategory":"Bank",
            "type":"Services"
        },
        {
            "category":"Shopping",
            "subcategory":"Used Merchandise",
            "type":"Retail Goods"
        }
    ],
    "sg:phone":"+1 940 665 6568",
    "sg:postcode":"76240",
    "sg:province":"TX",
    "sg:tags":[
        "resale",
        "shop",
        "second",
        "hand"
    ],
    "wof:name":"Brooks Antiques",
    "wof:placetype":"venue"
},
  "geometry": {"coordinates":[-97.11927900000001,33.626906],"type":"Point"}
}