{
  "type": "Feature",
  "properties": {
    "iso:country":"US",
    "sg:address":"13209 Flagstone Ln",
    "sg:city":"Dallas",
    "sg:classifiers":[
        {
            "category":"Bus Station",
            "type":"Transportation"
        }
    ],
    "sg:phone":"+1 972 243 3898",
    "sg:postcode":"75240",
    "sg:province":"TX",
    "sg:tags":[
        "facility"
    ],
    "wof:name":"Central Bus Terminal LLC",
    "wof:placetype":"venue"
},
  "geometry": {"coordinates":[-96.774281,32.92735],"type":"Point"}
}