{
  "type": "Feature",
  "properties": {
    "iso:country":"US",
    "sg:address":"3311 Riverlawn Dr",
    "sg:city":"Kingwood",
    "sg:classifiers":[
        {
            "category":"Professional",
            "subcategory":"Lawyer & Legal Services",
            "type":"Services"
        }
    ],
    "sg:phone":"+1 281 358 8085",
    "sg:postcode":"77339",
    "sg:province":"TX",
    "sg:tags":[
        "attorney",
        "practice"
    ],
    "wof:name":"Hinton Law Firm Pllc",
    "wof:placetype":"venue"
},
  "geometry": {"coordinates":[-95.20588499999999,30.051071],"type":"Point"}
}