{
  "type": "Feature",
  "properties": {
    "iso:country":"US",
    "sg:address":"206 Ash St",
    "sg:city":"Sweetwater",
    "sg:classifiers":[
        {
            "category":"Retail",
            "subcategory":"Auto Repair",
            "type":"Services"
        }
    ],
    "sg:phone":"+1 325 235 0211",
    "sg:postcode":"79556",
    "sg:province":"TX",
    "sg:tags":[
        "repairing",
        "automobile"
    ],
    "wof:name":"Keleman Motorsport",
    "wof:placetype":"venue"
},
  "geometry": {"coordinates":[-100.411053,32.469958],"type":"Point"}
}