{
  "type": "Feature",
  "properties": {
    "iso:country":"US",
    "sg:address":"7140 Navigation Blvd",
    "sg:city":"Houston",
    "sg:classifiers":[
        {
            "category":"Manufacturing",
            "subcategory":"Tools & Machinery",
            "type":"Manufacturing & Wholesale Goods"
        }
    ],
    "sg:phone":"+1 713 928 6288",
    "sg:postcode":"77011",
    "sg:province":"TX",
    "sg:tags":[
        "construction",
        "mfg"
    ],
    "wof:name":"Technico Marine Corp",
    "wof:placetype":"venue"
},
  "geometry": {"coordinates":[-95.29525099999999,29.742644],"type":"Point"}
}