{
  "type": "Feature",
  "properties": {
    "iso:country":"US",
    "sg:address":"251 O Connor Ridge Blvd",
    "sg:city":"Irving",
    "sg:classifiers":[
        {
            "category":"Shopping",
            "subcategory":"Computers & Home Electronics",
            "type":"Retail Goods"
        }
    ],
    "sg:phone":"+1 972 893 7300",
    "sg:postcode":"75038",
    "sg:province":"TX",
    "sg:tags":[
        "software"
    ],
    "wof:name":"Four J's Development",
    "wof:placetype":"venue"
},
  "geometry": {"coordinates":[-96.646,33.194097],"type":"Point"}
}