{
  "type": "Feature",
  "properties": {
    "iso:country":"US",
    "sg:address":"110 Blanco Vis",
    "sg:city":"Blanco",
    "sg:classifiers":[
        {
            "category":"Cinema",
            "subcategory":"Movie Rental",
            "type":"Entertainment"
        }
    ],
    "sg:phone":"+1 830 833 5701",
    "sg:postcode":"78606",
    "sg:province":"TX",
    "sg:tags":[
        "leasing",
        "video",
        "disc",
        "tape"
    ],
    "wof:name":"Video Shak",
    "wof:placetype":"venue"
},
  "geometry": {"coordinates":[-98.415521,30.056805],"type":"Point"}
}