{
  "type": "Feature",
  "properties": {
    "iso:country":"US",
    "sg:address":"1400 Carter Ave",
    "sg:city":"Midland",
    "sg:classifiers":[
        {
            "category":"Personal",
            "subcategory":"Beauty Salon",
            "type":"Services"
        }
    ],
    "sg:phone":"+1 432 570 5362",
    "sg:postcode":"79701",
    "sg:province":"TX",
    "sg:tags":[
        "shop"
    ],
    "wof:name":"Hair Creations",
    "wof:placetype":"venue"
},
  "geometry": {"coordinates":[-102.086562,31.98331],"type":"Point"}
}