{
  "type": "Feature",
  "properties": {
    "iso:country":"US",
    "sg:address":"4228 Myerwood Ln",
    "sg:city":"Dallas",
    "sg:classifiers":[
        {
            "category":"Professional",
            "type":"Services"
        }
    ],
    "sg:phone":"+1 972 991 0705",
    "sg:postcode":"75244",
    "sg:province":"TX",
    "wof:name":"Groom Githens Creative",
    "wof:placetype":"venue"
},
  "geometry": {"coordinates":[-96.83440299999999,32.912987],"type":"Point"}
}