{
  "type": "Feature",
  "properties": {
    "iso:country":"US",
    "sg:address":"545 E John Carpenter Fwy",
    "sg:city":"Irving",
    "sg:classifiers":[
        {
            "category":"Wholesale",
            "subcategory":"Toys & Hobbies",
            "type":"Manufacturing & Wholesale Goods"
        }
    ],
    "sg:phone":"+1 972 444 9700",
    "sg:postcode":"75062",
    "sg:province":"TX",
    "sg:tags":[
        "equipment",
        "mfg",
        "electronic",
        "lessor",
        "gaming"
    ],
    "wof:name":"Bettina Corp",
    "wof:placetype":"venue"
},
  "geometry": {"coordinates":[-96.932942,32.858727],"type":"Point"}
}