{
  "type": "Feature",
  "properties": {
    "iso:country":"US",
    "sg:address":"11330 Louetta Rd",
    "sg:city":"Houston",
    "sg:classifiers":[
        {
            "category":"Place Of Worship",
            "subcategory":"Church",
            "type":"Public Place"
        },
        {
            "category":"Place Of Worship",
            "type":"Public Place"
        }
    ],
    "sg:phone":"+1 281 370 2273",
    "sg:postcode":"77070",
    "sg:province":"TX",
    "sg:tags":[
        "churches-united",
        "methodist"
    ],
    "sg:website":"http://www.lakewoodumc.org",
    "wof:name":"Lakewood United Methodist",
    "wof:placetype":"venue"
},
  "geometry": {"coordinates":[-95.588364,29.99674],"type":"Point"}
}