{
  "type": "Feature",
  "properties": {
    "iso:country":"US",
    "sg:address":"6732 State Hwy 6",
    "sg:city":"Houston",
    "sg:classifiers":[
        {
            "category":"Personal",
            "subcategory":"Beauty Salon",
            "type":"Services"
        }
    ],
    "sg:phone":"+1 281 498 4437",
    "sg:postcode":"77083",
    "sg:province":"TX",
    "sg:tags":[
        "manicuring"
    ],
    "wof:name":"Nail'Cessary",
    "wof:placetype":"venue"
},
  "geometry": {"coordinates":[-95.64404999999999,29.70444],"type":"Point"}
}