{
  "type": "Feature",
  "properties": {
    "iso:country":"US",
    "sg:address":"909 N Kilgore St",
    "sg:city":"Kilgore",
    "sg:classifiers":[
        {
            "category":"Government",
            "subcategory":"Police Station",
            "type":"Public Place"
        }
    ],
    "sg:phone":"+1 903 983 1559",
    "sg:postcode":"75662",
    "sg:province":"TX",
    "sg:tags":[
        "department"
    ],
    "sg:website":"www.kilgorepublicsafety.com",
    "wof:name":"Kilgore Police Dept",
    "wof:placetype":"venue"
},
  "geometry": {"coordinates":[-94.870203,32.390418],"type":"Point"}
}