{
  "type": "Feature",
  "properties": {
    "iso:country":"US",
    "sg:address":"801 Industrial Ave",
    "sg:city":"Copperas Cove",
    "sg:classifiers":[
        {
            "category":"Organizations",
            "subcategory":"Religious Organization",
            "type":"Services"
        }
    ],
    "sg:phone":"+1 254 542 3211",
    "sg:postcode":"76522",
    "sg:province":"TX",
    "sg:tags":[
        "church"
    ],
    "wof:name":"Saint Center",
    "wof:placetype":"venue"
},
  "geometry": {"coordinates":[-97.892861,31.125415],"type":"Point"}
}