{
  "type": "Feature",
  "properties": {
    "iso:country":"US",
    "sg:address":"3585 Washington Blvd",
    "sg:city":"Beaumont",
    "sg:classifiers":[
        {
            "category":"Retail",
            "subcategory":"Auto Repair",
            "type":"Services"
        }
    ],
    "sg:phone":"+1 409 840 2073",
    "sg:postcode":"77705",
    "sg:province":"TX",
    "sg:tags":[
        "repairing",
        "automobile",
        "general"
    ],
    "wof:name":"Jackie's Auto Repair",
    "wof:placetype":"venue"
},
  "geometry": {"coordinates":[-94.12742299999999,30.055708],"type":"Point"}
}