{
  "type": "Feature",
  "properties": {
    "iso:country":"US",
    "sg:address":"3016 Modella Ave",
    "sg:city":"Dallas",
    "sg:classifiers":[
        {
            "category":"Professional",
            "subcategory":"Detective & Security Services",
            "type":"Services"
        }
    ],
    "sg:phone":"+1 972 620 0620",
    "sg:postcode":"75229",
    "sg:province":"TX",
    "sg:tags":[
        "car"
    ],
    "wof:name":"Soules Investigative Services",
    "wof:placetype":"venue"
},
  "geometry": {"coordinates":[-96.87517800000001,32.906728],"type":"Point"}
}