{
  "type": "Feature",
  "properties": {
    "iso:country":"US",
    "sg:address":"4006 S Lamar Blvd Ste 650",
    "sg:city":"Austin",
    "sg:phone":"+1 512 444 4808",
    "sg:postcode":"78704",
    "sg:province":"TX",
    "sg:website":"http://austinbeautystore.com",
    "wof:name":"Beauty Store & Salon",
    "wof:placetype":"venue"
},
  "geometry": {"coordinates":[-97.790695,30.237648],"type":"Point"}
}