{
  "type": "Feature",
  "properties": {
    "iso:country":"US",
    "sg:address":"10802 Legacy Park Dr",
    "sg:city":"Houston",
    "sg:classifiers":[
        {
            "category":"Health Services",
            "subcategory":"Clinic",
            "type":"Services"
        }
    ],
    "sg:phone":"+1 281 477 6055",
    "sg:postcode":"77064",
    "sg:province":"TX",
    "wof:name":"Interim Health Care",
    "wof:placetype":"venue"
},
  "geometry": {"coordinates":[-95.559263,29.921414],"type":"Point"}
}