{
  "type": "Feature",
  "properties": {
    "iso:country":"US",
    "sg:address":"105 Eubanks St",
    "sg:city":"Tom Bean",
    "sg:classifiers":[
        {
            "category":"Education",
            "subcategory":"School",
            "type":"Public Place"
        }
    ],
    "sg:phone":"+1 903 546 6333",
    "sg:postcode":"75489",
    "sg:province":"TX",
    "sg:website":"www.tombean-isd.org",
    "wof:name":"Tom Bean Elementary School",
    "wof:placetype":"venue"
},
  "geometry": {"coordinates":[-96.481252,33.519536],"type":"Point"}
}