{
  "type": "Feature",
  "properties": {
    "iso:country":"US",
    "sg:address":"3903 Eisenhauer Rd",
    "sg:city":"San Antonio",
    "sg:classifiers":[
        {
            "category":"Shopping",
            "type":"Retail Goods"
        }
    ],
    "sg:phone":"+1 210 946 8588",
    "sg:postcode":"78218",
    "sg:province":"TX",
    "sg:tags":[
        "cards",
        "sport",
        "baseball",
        "memorabilia"
    ],
    "wof:name":"Cowboy Fan",
    "wof:placetype":"venue"
},
  "geometry": {"coordinates":[-98.418446,29.496653],"type":"Point"}
}