{
  "type": "Feature",
  "properties": {
    "iso:country":"US",
    "sg:address":"4306 Neely Ave",
    "sg:city":"Midland",
    "sg:classifiers":[
        {
            "category":"Restaurant",
            "type":"Food & Drink"
        }
    ],
    "sg:phone":"+1 432 699 0242",
    "sg:postcode":"79707",
    "sg:province":"TX",
    "sg:tags":[
        "eating"
    ],
    "wof:name":"Oscar's Super Burrito",
    "wof:placetype":"venue"
},
  "geometry": {"coordinates":[-102.139079,32.009096],"type":"Point"}
}