{
  "type": "Feature",
  "properties": {
    "iso:country":"US",
    "sg:address":"2913 Ave C",
    "sg:city":"Bay City",
    "sg:classifiers":[
        {
            "category":"Organizations",
            "subcategory":"Community Association",
            "type":"Services"
        }
    ],
    "sg:phone":"+1 979 245 2768",
    "sg:postcode":"77414",
    "sg:province":"TX",
    "sg:tags":[
        "club"
    ],
    "wof:name":"Sound End Liquor Store",
    "wof:placetype":"venue"
},
  "geometry": {"coordinates":[-95.973252,28.974379],"type":"Point"}
}