{
  "type": "Feature",
  "properties": {
    "iso:country":"US",
    "sg:address":"9080 Teasley Ln",
    "sg:city":"Denton",
    "sg:classifiers":[
        {
            "category":"Utilities",
            "subcategory":"Telephone",
            "type":"Services"
        }
    ],
    "sg:phone":"+1 940 381 9922",
    "sg:postcode":"76210",
    "sg:province":"TX",
    "sg:tags":[
        "systems-wholesale",
        "equipment",
        "system",
        "manufacturer"
    ],
    "wof:name":"Ss8 Networks",
    "wof:placetype":"venue"
},
  "geometry": {"coordinates":[-97.099182,33.13216],"type":"Point"}
}