{
  "type": "Feature",
  "properties": {
    "iso:country":"US",
    "sg:address":"851 Dominion Dr",
    "sg:city":"Katy",
    "sg:classifiers":[
        {
            "category":"Government",
            "subcategory":"Fire Station",
            "type":"Public Place"
        }
    ],
    "sg:phone":"+1 281 492 8080",
    "sg:postcode":"77450",
    "sg:province":"TX",
    "sg:tags":[
        "protection"
    ],
    "wof:name":"West I 10 Fire Dept",
    "wof:placetype":"venue"
},
  "geometry": {"coordinates":[-95.73003,29.771644],"type":"Point"}
}