{
  "type": "Feature",
  "properties": {
    "iso:country":"US",
    "sg:address":"5810 del Bello Ln",
    "sg:city":"Manvel",
    "sg:classifiers":[
        {
            "category":"Retail",
            "subcategory":"Veterinary Services",
            "type":"Services"
        }
    ],
    "sg:phone":"+1 281 489 0235",
    "sg:postcode":"77578",
    "sg:province":"TX",
    "wof:name":"B A Myatt Dvm",
    "wof:placetype":"venue"
},
  "geometry": {"coordinates":[-95.370422,29.501357],"type":"Point"}
}