{
  "type": "Feature",
  "properties": {
    "iso:country":"US",
    "sg:address":"23203 Bayleaf Dr",
    "sg:city":"Spring",
    "sg:classifiers":[
        {
            "category":"Professional",
            "subcategory":"Accounting & Tax Preparation",
            "type":"Services"
        }
    ],
    "sg:phone":"+1 281 353 7034",
    "sg:postcode":"77373",
    "sg:province":"TX",
    "wof:name":"Robles Assoc",
    "wof:placetype":"venue"
},
  "geometry": {"coordinates":[-95.394677,30.046253],"type":"Point"}
}