{
  "type": "Feature",
  "properties": {
    "iso:country":"US",
    "sg:address":"1113 Scenic Loop",
    "sg:city":"Marshall",
    "sg:classifiers":[
        {
            "category":"Retail",
            "subcategory":"Auto Repair",
            "type":"Services"
        }
    ],
    "sg:phone":"+1 903 927 1466",
    "sg:postcode":"75672",
    "sg:province":"TX",
    "sg:tags":[
        "shop",
        "automotive"
    ],
    "wof:name":"Dwayne Johnson",
    "wof:placetype":"venue"
},
  "geometry": {"coordinates":[-94.356819,32.524614],"type":"Point"}
}