{
  "type": "Feature",
  "properties": {
    "iso:country":"US",
    "sg:address":"1525 Fm 766",
    "sg:city":"Cuero",
    "sg:classifiers":[
        {
            "category":"Government",
            "subcategory":"Office",
            "type":"Public Place"
        }
    ],
    "sg:phone":"+1 361 275 2075",
    "sg:postcode":"77954",
    "sg:province":"TX",
    "wof:name":"Stevenson Prison",
    "wof:placetype":"venue"
},
  "geometry": {"coordinates":[-97.30396,29.133185],"type":"Point"}
}