{
  "type": "Feature",
  "properties": {
    "iso:country":"US",
    "sg:address":"3500 Smith Barry Rd",
    "sg:city":"Arlington",
    "sg:classifiers":[
        {
            "category":"Manufacturing",
            "subcategory":"Retail Goods",
            "type":"Manufacturing & Wholesale Goods"
        }
    ],
    "sg:phone":"+1 817 861 6277",
    "sg:postcode":"76013",
    "sg:province":"TX",
    "sg:tags":[
        "product",
        "mfg"
    ],
    "wof:name":"Cfb Industries Inc",
    "wof:placetype":"venue"
},
  "geometry": {"coordinates":[-97.16172299999999,32.713954],"type":"Point"}
}