{
  "type": "Feature",
  "properties": {
    "iso:country":"US",
    "sg:address":"23110 Cinco Ranch Blvd",
    "sg:city":"Katy",
    "sg:classifiers":[
        {
            "category":"Personal",
            "subcategory":"Beauty Salon",
            "type":"Services"
        }
    ],
    "sg:phone":"+1 281 693 4544",
    "sg:postcode":"77494",
    "sg:province":"TX",
    "sg:tags":[
        "shop"
    ],
    "wof:name":"Salon Victoria",
    "wof:placetype":"venue"
},
  "geometry": {"coordinates":[-95.76897599999999,29.743917],"type":"Point"}
}