{
  "type": "Feature",
  "properties": {
    "iso:country":"US",
    "sg:address":"2342 E Southcross Blvd",
    "sg:city":"San Antonio",
    "sg:classifiers":[
        {
            "category":"Banks & Credit Unions",
            "subcategory":"Bank",
            "type":"Services"
        }
    ],
    "sg:phone":"+1 210 534 6300",
    "sg:postcode":"78223",
    "sg:province":"TX",
    "sg:tags":[
        "loan",
        "institution",
        "business"
    ],
    "wof:name":"Citi Financial",
    "wof:placetype":"venue"
},
  "geometry": {"coordinates":[-98.45748,29.375306],"type":"Point"}
}