{
  "type": "Feature",
  "properties": {
    "iso:country":"US",
    "sg:address":"310 S Mill St",
    "sg:city":"Lewisville",
    "sg:classifiers":[
        {
            "category":"Restaurant",
            "type":"Food & Drink"
        }
    ],
    "sg:phone":"+1 972 436 4333",
    "sg:postcode":"75057",
    "sg:province":"TX",
    "sg:tags":[
        "caterer"
    ],
    "wof:name":"Dallas Tortilla & Tamale Fctry",
    "wof:placetype":"venue"
},
  "geometry": {"coordinates":[-96.99369,33.04201],"type":"Point"}
}