{
  "type": "Feature",
  "properties": {
    "iso:country":"US",
    "sg:address":"8030 State Hwy 6",
    "sg:city":"Hitchcock",
    "sg:classifiers":[
        {
            "category":"Shopping",
            "type":"Retail Goods"
        }
    ],
    "sg:phone":"+1 409 978 2181",
    "sg:postcode":"77563",
    "sg:province":"TX",
    "sg:tags":[
        "merchandise"
    ],
    "wof:name":"Home Care Medical Supplies",
    "wof:placetype":"venue"
},
  "geometry": {"coordinates":[-95.01996800000001,29.349592],"type":"Point"}
}