{
  "type": "Feature",
  "properties": {
    "iso:country":"US",
    "sg:address":"3319 Palmetto Trl",
    "sg:city":"Amarillo",
    "sg:classifiers":[
        {
            "category":"Communications",
            "type":"Services"
        }
    ],
    "sg:phone":"+1 806 358 9475",
    "sg:postcode":"79106",
    "sg:province":"TX",
    "sg:tags":[
        "communication"
    ],
    "wof:name":"I T Communications",
    "wof:placetype":"venue"
},
  "geometry": {"coordinates":[-101.907374,35.176482],"type":"Point"}
}