{
  "type": "Feature",
  "properties": {
    "iso:country":"US",
    "sg:address":"2914 Reward Ln",
    "sg:city":"Dallas",
    "sg:classifiers":[
        {
            "category":"Building & Trades",
            "subcategory":"Equipment Rental",
            "type":"Services"
        }
    ],
    "sg:phone":"+1 214 774 0912",
    "sg:postcode":"75220",
    "sg:province":"TX",
    "sg:tags":[
        "camping"
    ],
    "sg:website":"www.livewirespecialevents.com",
    "wof:name":"Live Wire Special Events",
    "wof:placetype":"venue"
},
  "geometry": {"coordinates":[-96.87982700000001,32.874892],"type":"Point"}
}