{
  "type": "Feature",
  "properties": {
    "iso:country":"US",
    "sg:address":"2361 Fabens Rd",
    "sg:city":"Dallas",
    "sg:classifiers":[
        {
            "category":"Autos & Motor Vehicles",
            "subcategory":"Motorcycle Sales",
            "type":"Retail Goods"
        }
    ],
    "sg:phone":"+1 972 406 1933",
    "sg:postcode":"75229",
    "sg:province":"TX",
    "sg:website":"www.southwestsuperbikes.com",
    "wof:name":"Southwest Super Bikes",
    "wof:placetype":"venue"
},
  "geometry": {"coordinates":[-96.898697,32.891499],"type":"Point"}
}