{
  "type": "Feature",
  "properties": {
    "iso:country":"US",
    "sg:address":"616 E 8th St",
    "sg:city":"Mission",
    "sg:classifiers":[
        {
            "category":"Retail",
            "subcategory":"Auto Repair",
            "type":"Services"
        }
    ],
    "sg:phone":"+1 956 581 7905",
    "sg:postcode":"78572",
    "sg:province":"TX",
    "sg:tags":[
        "general"
    ],
    "wof:name":"Cantu Auto Repairs",
    "wof:placetype":"venue"
},
  "geometry": {"coordinates":[-98.319408,26.212484],"type":"Point"}
}