{
  "type": "Feature",
  "properties": {
    "iso:country":"US",
    "sg:address":"1980 Texas Ave",
    "sg:city":"Bridge City",
    "sg:classifiers":[
        {
            "category":"Insurance",
            "subcategory":"Insurance Agent",
            "type":"Services"
        }
    ],
    "sg:phone":"+1 409 738 3288",
    "sg:postcode":"77611",
    "sg:province":"TX",
    "wof:name":"Dodge Donald Insurance",
    "wof:placetype":"venue"
},
  "geometry": {"coordinates":[-93.827431,30.038811],"type":"Point"}
}