{
  "type": "Feature",
  "properties": {
    "iso:country":"US",
    "sg:address":"23516 Majestic Vw",
    "sg:city":"San Antonio",
    "sg:classifiers":[
        {
            "category":"Wholesale",
            "subcategory":"Sporting Goods",
            "type":"Manufacturing & Wholesale Goods"
        }
    ],
    "sg:phone":"+1 210 481 7290",
    "sg:postcode":"78258",
    "sg:province":"TX",
    "wof:name":"Pro Golf of San Antonio",
    "wof:placetype":"venue"
},
  "geometry": {"coordinates":[-98.498615,29.661662],"type":"Point"}
}