{
  "type": "Feature",
  "properties": {
    "iso:country":"US",
    "sg:address":"6088 River Ln",
    "sg:city":"Corpus Christi",
    "sg:classifiers":[
        {
            "category":"Wholesale",
            "subcategory":"Machinery & Supplies",
            "type":"Manufacturing & Wholesale Goods"
        }
    ],
    "sg:phone":"+1 361 241 0460",
    "sg:postcode":"78410",
    "sg:province":"TX",
    "sg:tags":[
        "equipment",
        "industrial"
    ],
    "wof:name":"Diamond Power Wash",
    "wof:placetype":"venue"
},
  "geometry": {"coordinates":[-97.61683499999999,27.8768],"type":"Point"}
}