{
  "type": "Feature",
  "properties": {
    "iso:country":"US",
    "sg:address":"2533 County Line Rd S",
    "sg:city":"Electra",
    "sg:classifiers":[
        {
            "category":"Farming",
            "subcategory":"Livestock Farm",
            "type":"Manufacturing & Wholesale Goods"
        }
    ],
    "sg:phone":"+1 940 495 3773",
    "sg:postcode":"76360",
    "sg:province":"TX",
    "sg:tags":[
        "feeding",
        "ranch"
    ],
    "sg:website":"http://www.philipwhite.net",
    "wof:name":"White Face Horse Barn",
    "wof:placetype":"venue"
},
  "geometry": {"coordinates":[-98.95259900000001,34.032121],"type":"Point"}
}