{
  "type": "Feature",
  "properties": {
    "iso:country":"US",
    "sg:address":"3407 Omega St",
    "sg:city":"Houston",
    "sg:classifiers":[
        {
            "category":"Personal",
            "subcategory":"Beauty Salon",
            "type":"Services"
        }
    ],
    "sg:phone":"+1 713 868 1681",
    "sg:postcode":"77022",
    "sg:province":"TX",
    "sg:tags":[
        "shop"
    ],
    "wof:name":"Poppa Tight Cuts",
    "wof:placetype":"venue"
},
  "geometry": {"coordinates":[-95.385099,29.817293],"type":"Point"}
}