{
  "type": "Feature",
  "properties": {
    "iso:country":"US",
    "sg:address":"1187 Edgebrook Dr",
    "sg:city":"Houston",
    "sg:classifiers":[
        {
            "category":"Food & Beverages",
            "subcategory":"Bakery",
            "type":"Retail Goods"
        }
    ],
    "sg:phone":"+1 713 944 9556",
    "sg:postcode":"77034",
    "sg:province":"TX",
    "sg:tags":[
        "sandwich"
    ],
    "wof:name":"Subway Sandwiches & Salads",
    "wof:placetype":"venue"
},
  "geometry": {"coordinates":[-95.242401,29.6413],"type":"Point"}
}