{
  "type": "Feature",
  "properties": {
    "iso:country":"US",
    "sg:address":"2505 Oak Dr",
    "sg:city":"Bay City",
    "sg:classifiers":[
        {
            "category":"Professional",
            "subcategory":"Accounting & Tax Preparation",
            "type":"Services"
        }
    ],
    "sg:phone":"+1 979 323 7757",
    "sg:postcode":"77414",
    "sg:province":"TX",
    "sg:tags":[
        "bookkeeping",
        "general"
    ],
    "wof:name":"Lester J Wenk Ea",
    "wof:placetype":"venue"
},
  "geometry": {"coordinates":[-95.960431,28.969983],"type":"Point"}
}