{
  "type": "Feature",
  "properties": {
    "iso:country":"US",
    "sg:address":"109 US Hwy 82 E",
    "sg:city":"Annona",
    "sg:classifiers":[
        {
            "category":"Food & Beverages",
            "subcategory":"Groceries & Convenience Stores",
            "type":"Retail Goods"
        }
    ],
    "sg:phone":"+1 903 838 0856",
    "sg:postcode":"75554",
    "sg:province":"TX",
    "wof:name":"One Stop",
    "wof:placetype":"venue"
},
  "geometry": {"coordinates":[-94.782984,33.552405],"type":"Point"}
}