{
  "type": "Feature",
  "properties": {
    "iso:country":"US",
    "sg:address":"3612 N Belt Line Rd",
    "sg:city":"Irving",
    "sg:classifiers":[
        {
            "category":"Food & Beverages",
            "subcategory":"Supermarket",
            "type":"Retail Goods"
        },
        {
            "category":"Shopping",
            "subcategory":"Pharmacy",
            "type":"Retail Goods"
        },
        {
            "category":"Food & Beverages",
            "subcategory":"Groceries & Convenience Stores",
            "type":"Retail Goods"
        }
    ],
    "sg:phone":"+1 972 252 7413",
    "sg:postcode":"75062",
    "sg:province":"TX",
    "sg:tags":[
        "super"
    ],
    "sg:website":"http://www.scottsfoods.com",
    "wof:name":"Kroger",
    "wof:placetype":"venue"
},
  "geometry": {"coordinates":[-96.992051,32.855147],"type":"Point"}
}