{
  "type": "Feature",
  "properties": {
    "iso:country":"US",
    "sg:address":"400 Josephine St",
    "sg:city":"Austin",
    "sg:classifiers":[
        {
            "category":"Organizations",
            "subcategory":"Labor Organization",
            "type":"Services"
        },
        {
            "category":"Building & Trades",
            "subcategory":"Construction",
            "type":"Services"
        }
    ],
    "sg:phone":"+1 512 476 7354",
    "sg:postcode":"78704",
    "sg:province":"TX",
    "sg:tags":[
        "carpenter"
    ],
    "wof:name":"Carpenters Union Local No 1266",
    "wof:placetype":"venue"
},
  "geometry": {"coordinates":[-97.758408,30.26228],"type":"Point"}
}