{
  "type": "Feature",
  "properties": {
    "iso:country":"US",
    "sg:address":"2930 Grants Lake Blvd",
    "sg:city":"Sugar Land",
    "sg:classifiers":[
        {
            "category":"Professional",
            "subcategory":"Business Services",
            "type":"Services"
        }
    ],
    "sg:phone":"+1 281 565 1554",
    "sg:postcode":"77479",
    "sg:province":"TX",
    "wof:name":"Interior Designs By Lucilla",
    "wof:placetype":"venue"
},
  "geometry": {"coordinates":[-95.614625,29.588486],"type":"Point"}
}