{
  "type": "Feature",
  "properties": {
    "iso:country":"US",
    "sg:address":"4035 Young St",
    "sg:city":"Pasadena",
    "sg:classifiers":[
        {
            "category":"Professional",
            "type":"Services"
        }
    ],
    "sg:phone":"+1 281 487 7486",
    "sg:postcode":"77504",
    "sg:province":"TX",
    "wof:name":"Ramos Services",
    "wof:placetype":"venue"
},
  "geometry": {"coordinates":[-95.194157,29.649001],"type":"Point"}
}