{
  "type": "Feature",
  "properties": {
    "iso:country":"US",
    "sg:address":"1425 Robinhood Dr",
    "sg:city":"Brownsville",
    "sg:classifiers":[
        {
            "category":"Retail",
            "subcategory":"Repair Shop",
            "type":"Services"
        }
    ],
    "sg:phone":"+1 956 983 6173",
    "sg:postcode":"78521",
    "sg:province":"TX",
    "sg:tags":[
        "utility"
    ],
    "wof:name":"Southmost Regional Water Auth",
    "wof:placetype":"venue"
},
  "geometry": {"coordinates":[-97.46392299999999,25.925765],"type":"Point"}
}