{
  "type": "Feature",
  "properties": {
    "iso:country":"US",
    "sg:address":"719 Kipling St",
    "sg:city":"Houston",
    "sg:classifiers":[
        {
            "category":"Professional",
            "type":"Services"
        }
    ],
    "sg:phone":"+1 713 524 1417",
    "sg:postcode":"77006",
    "sg:province":"TX",
    "sg:tags":[
        "writer"
    ],
    "wof:name":"Diana Global",
    "wof:placetype":"venue"
},
  "geometry": {"coordinates":[-95.387664,29.740458],"type":"Point"}
}