{
  "type": "Feature",
  "properties": {
    "iso:country":"US",
    "sg:address":"1930 W Hackberry Ave",
    "sg:city":"Mcallen",
    "sg:classifiers":[
        {
            "category":"Autos & Motor Vehicles",
            "subcategory":"Automobile Sales",
            "type":"Retail Goods"
        }
    ],
    "sg:phone":"+1 956 630 5875",
    "sg:postcode":"78501",
    "sg:province":"TX",
    "sg:tags":[
        "used"
    ],
    "wof:name":"Street Wise Auto Sales",
    "wof:placetype":"venue"
},
  "geometry": {"coordinates":[-98.239581,26.212219],"type":"Point"}
}