{
  "type": "Feature",
  "properties": {
    "iso:country":"US",
    "sg:address":"105 E Magnolia St",
    "sg:city":"Falfurrias",
    "sg:classifiers":[
        {
            "category":"Building & Trades",
            "subcategory":"Landscaping Services",
            "type":"Services"
        }
    ],
    "sg:phone":"+1 361 325 2059",
    "sg:postcode":"78355",
    "sg:province":"TX",
    "wof:name":"Michael S Landscaping",
    "wof:placetype":"venue"
},
  "geometry": {"coordinates":[-98.139054,27.237086],"type":"Point"}
}