{
  "type": "Feature",
  "properties": {
    "iso:country":"US",
    "sg:address":"8715 Prairie View Dr",
    "sg:city":"Houston",
    "sg:classifiers":[
        {
            "category":"Banks & Credit Unions",
            "subcategory":"Bank",
            "type":"Services"
        }
    ],
    "sg:phone":"+1 281 999 9997",
    "sg:postcode":"77088",
    "sg:province":"TX",
    "wof:name":"Lincoln City Credit Union",
    "wof:placetype":"venue"
},
  "geometry": {"coordinates":[-95.428398,29.880199],"type":"Point"}
}