{
  "type": "Feature",
  "properties": {
    "iso:country":"US",
    "sg:address":"5151 Fairbanks Dr",
    "sg:city":"El Paso",
    "sg:classifiers":[
        {
            "category":"Utilities",
            "subcategory":"Mobile Phone",
            "type":"Services"
        }
    ],
    "sg:phone":"+1 915 757 3718",
    "sg:postcode":"79924",
    "sg:province":"TX",
    "sg:tags":[
        "telephone",
        "cellular"
    ],
    "wof:name":"Ka-Tec Technology",
    "wof:placetype":"venue"
},
  "geometry": {"coordinates":[-106.42344300000001,31.90305],"type":"Point"}
}