{
  "type": "Feature",
  "properties": {
    "iso:country":"US",
    "sg:address":"11518 Chancellroy Dr",
    "sg:city":"Austin",
    "sg:classifiers":[
        {
            "category":"Insurance",
            "subcategory":"Insurance Agent",
            "type":"Services"
        }
    ],
    "sg:phone":"+1 512 250 1644",
    "sg:postcode":"78759",
    "sg:province":"TX",
    "wof:name":"Robert Wu",
    "wof:placetype":"venue"
},
  "geometry": {"coordinates":[-97.779071,30.430916],"type":"Point"}
}