{
  "type": "Feature",
  "properties": {
    "iso:country":"US",
    "sg:address":"2309 Superior Dr",
    "sg:city":"Arlington",
    "sg:classifiers":[
        {
            "category":"Building & Trades",
            "subcategory":"Construction",
            "type":"Services"
        }
    ],
    "sg:phone":"+1 817 261 0077",
    "sg:postcode":"76013",
    "sg:province":"TX",
    "sg:tags":[
        "repairing",
        "house",
        "remodeling",
        "contractor"
    ],
    "wof:name":"Best Exterior Designs Inc",
    "wof:placetype":"venue"
},
  "geometry": {"coordinates":[-97.149023,32.708004],"type":"Point"}
}