{
  "type": "Feature",
  "properties": {
    "iso:country":"US",
    "sg:address":"7415 Quanah Hill Rd",
    "sg:city":"Weatherford",
    "sg:classifiers":[
        {
            "category":"Farming",
            "subcategory":"Nursery",
            "type":"Manufacturing & Wholesale Goods"
        }
    ],
    "sg:phone":"+1 817 594 3983",
    "sg:postcode":"76087",
    "sg:province":"TX",
    "sg:tags":[
        "ornamental"
    ],
    "wof:name":"Wyler Greenhouses",
    "wof:placetype":"venue"
},
  "geometry": {"coordinates":[-97.950767,32.703393],"type":"Point"}
}