{
  "type": "Feature",
  "properties": {
    "iso:country":"US",
    "sg:address":"3600 Travis St",
    "sg:city":"Houston",
    "sg:classifiers":[
        {
            "category":"Manufacturing",
            "subcategory":"Printing",
            "type":"Manufacturing & Wholesale Goods"
        }
    ],
    "sg:phone":"+1 713 529 4449",
    "sg:postcode":"77002",
    "sg:province":"TX",
    "sg:tags":[
        "newspaper"
    ],
    "wof:name":"Catholic Daily Mgs",
    "wof:placetype":"venue"
},
  "geometry": {"coordinates":[-95.38042,29.739005],"type":"Point"}
}