{
  "type": "Feature",
  "properties": {
    "iso:country":"US",
    "sg:address":"511 Sorenson Trl",
    "sg:city":"Keller",
    "sg:classifiers":[
        {
            "category":"Organizations",
            "subcategory":"Non-profit Organization",
            "type":"Services"
        }
    ],
    "sg:phone":"+1 817 337 0702",
    "sg:postcode":"76248",
    "sg:province":"TX",
    "sg:tags":[
        "social"
    ],
    "wof:name":"Ces Cindys Educational",
    "wof:placetype":"venue"
},
  "geometry": {"coordinates":[-97.19446600000001,32.925942],"type":"Point"}
}