{
  "type": "Feature",
  "properties": {
    "iso:country":"US",
    "sg:address":"6780 Abrams Rd Ste 211",
    "sg:city":"Dallas",
    "sg:classifiers":[
        {
            "category":"Health Services",
            "subcategory":"Doctor",
            "type":"Services"
        }
    ],
    "sg:phone":"+1 214 341 5630",
    "sg:postcode":"75231",
    "sg:province":"TX",
    "wof:name":"Cynthia Dott",
    "wof:placetype":"venue"
},
  "geometry": {"coordinates":[-96.74279799999999,32.867401],"type":"Point"}
}