{
  "type": "Feature",
  "properties": {
    "iso:country":"US",
    "sg:address":"3434 W Illinois Ave",
    "sg:city":"Dallas",
    "sg:phone":"+1 214 333 9505",
    "sg:postcode":"75211",
    "sg:province":"TX",
    "wof:name":"Vanidades Beauty Salon",
    "wof:placetype":"venue"
},
  "geometry": {"coordinates":[-96.87740599999999,32.720291],"type":"Point"}
}