{
  "type": "Feature",
  "properties": {
    "iso:country":"US",
    "sg:address":"5030 Chancellor Row",
    "sg:city":"Corpus Christi",
    "sg:classifiers":[
        {
            "category":"Retail",
            "subcategory":"Auto Repair",
            "type":"Services"
        }
    ],
    "sg:phone":"+1 361 854 0885",
    "sg:postcode":"78416",
    "sg:province":"TX",
    "sg:tags":[
        "body"
    ],
    "wof:name":"Port-A-Trim",
    "wof:placetype":"venue"
},
  "geometry": {"coordinates":[-97.44560199999999,27.745582],"type":"Point"}
}