{
  "type": "Feature",
  "properties": {
    "iso:country":"US",
    "sg:address":"7425 S Hulen St",
    "sg:city":"Fort Worth",
    "sg:classifiers":[
        {
            "category":"Real Estate",
            "subcategory":"Real Estate Operator",
            "type":"Services"
        }
    ],
    "sg:phone":"+1 817 294 1017",
    "sg:postcode":"76133",
    "sg:province":"TX",
    "sg:tags":[
        "building"
    ],
    "wof:name":"Candletree Apartments",
    "wof:placetype":"venue"
},
  "geometry": {"coordinates":[-97.395619,32.638919],"type":"Point"}
}