{
  "type": "Feature",
  "properties": {
    "iso:country":"US",
    "sg:address":"300 E 26th St",
    "sg:city":"Bryan",
    "sg:classifiers":[
        {
            "category":"Government",
            "subcategory":"Office",
            "type":"Public Place"
        }
    ],
    "sg:phone":"+1 979 361 4245",
    "sg:postcode":"77803",
    "sg:province":"TX",
    "sg:tags":[
        "general"
    ],
    "wof:name":"Risk Management",
    "wof:placetype":"venue"
},
  "geometry": {"coordinates":[-96.370076,30.673363],"type":"Point"}
}