{
  "type": "Feature",
  "properties": {
    "iso:country":"US",
    "sg:address":"5832 Live Oak St",
    "sg:city":"Dallas",
    "sg:classifiers":[
        {
            "category":"Education",
            "subcategory":"Special Training",
            "type":"Public Place"
        }
    ],
    "sg:phone":"+1 214 821 5406",
    "sg:postcode":"75214",
    "sg:province":"TX",
    "wof:name":"School Of Metaphysics",
    "wof:placetype":"venue"
},
  "geometry": {"coordinates":[-96.761004,32.812355],"type":"Point"}
}