{
  "type": "Feature",
  "properties": {
    "iso:country":"US",
    "sg:address":"1800 Lakeway Dr Ste 118",
    "sg:city":"Lewisville",
    "sg:classifiers":[
        {
            "category":"Professional",
            "subcategory":"Business Services",
            "type":"Services"
        },
        {
            "category":"Professional",
            "subcategory":"Printing & Photocopies",
            "type":"Services"
        }
    ],
    "sg:phone":"+1 972 459 1493",
    "sg:postcode":"75057",
    "sg:province":"TX",
    "sg:tags":[
        "system",
        "form",
        "printers-business"
    ],
    "sg:website":"http://www.moore.com",
    "wof:name":"R R Donnelley",
    "wof:placetype":"venue"
},
  "geometry": {"coordinates":[-96.97558100000001,33.01748],"type":"Point"}
}