{
  "type": "Feature",
  "properties": {
    "iso:country":"US",
    "sg:address":"13010 W Parmer Ln",
    "sg:city":"Cedar Park",
    "sg:classifiers":[
        {
            "category":"Utilities",
            "subcategory":"Mobile Phone",
            "type":"Services"
        }
    ],
    "sg:phone":"+1 512 260 4010",
    "sg:postcode":"78613",
    "sg:province":"TX",
    "sg:tags":[
        "telephone",
        "cellular"
    ],
    "wof:name":"Arbor Wireless",
    "wof:placetype":"venue"
},
  "geometry": {"coordinates":[-97.781409,30.532228],"type":"Point"}
}