{
  "type": "Feature",
  "properties": {
    "iso:country":"US",
    "sg:address":"501 S Ohio Ave",
    "sg:city":"Mercedes",
    "sg:classifiers":[
        {
            "category":"Health Services",
            "subcategory":"Doctor",
            "type":"Services"
        }
    ],
    "sg:phone":"+1 956 565 2419",
    "sg:postcode":"78570",
    "sg:province":"TX",
    "sg:tags":[
        "dentist"
    ],
    "wof:name":"Mercedes Family Dentistry",
    "wof:placetype":"venue"
},
  "geometry": {"coordinates":[-97.912156,26.146942],"type":"Point"}
}