{
  "type": "Feature",
  "properties": {
    "iso:country":"US",
    "sg:address":"402 W Harrison Ave",
    "sg:city":"Harlingen",
    "sg:classifiers":[
        {
            "category":"Restaurant",
            "type":"Food & Drink"
        }
    ],
    "sg:phone":"+1 956 412 1838",
    "sg:postcode":"78550",
    "sg:province":"TX",
    "wof:name":"Yerberia El Indio",
    "wof:placetype":"venue"
},
  "geometry": {"coordinates":[-97.699983,26.190737],"type":"Point"}
}