{
  "type": "Feature",
  "properties": {
    "iso:country":"US",
    "sg:address":"4120 Martin L King Blvd",
    "sg:city":"Lubbock",
    "sg:classifiers":[
        {
            "category":"Building & Trades",
            "subcategory":"Construction",
            "type":"Services"
        }
    ],
    "sg:phone":"+1 806 744 4298",
    "sg:postcode":"79404",
    "sg:province":"TX",
    "sg:tags":[
        "boring",
        "drilling",
        "contractor"
    ],
    "wof:name":"T & T Drilling Environmental",
    "wof:placetype":"venue"
},
  "geometry": {"coordinates":[-101.818465,33.557106],"type":"Point"}
}