{
  "type": "Feature",
  "properties": {
    "iso:country":"US",
    "sg:address":"5902 Harrisburg Blvd",
    "sg:city":"Houston",
    "sg:classifiers":[
        {
            "category":"Autos & Motor Vehicles",
            "subcategory":"Automobile Sales",
            "type":"Retail Goods"
        }
    ],
    "sg:phone":"+1 713 926 8891",
    "sg:postcode":"77011",
    "sg:province":"TX",
    "sg:tags":[
        "car",
        "used",
        "dealer"
    ],
    "wof:name":"Harrisburg Auto Sales Inc",
    "wof:placetype":"venue"
},
  "geometry": {"coordinates":[-95.31676899999999,29.740049],"type":"Point"}
}