{
  "type": "Feature",
  "properties": {
    "iso:country":"US",
    "sg:address":"8680 Smith Dairy Rd",
    "sg:city":"Salado",
    "sg:classifiers":[
        {
            "category":"Recreation",
            "type":"Entertainment"
        }
    ],
    "sg:phone":"+1 254 947 0891",
    "sg:postcode":"76513",
    "sg:province":"TX",
    "sg:tags":[
        "stable"
    ],
    "wof:name":"K & D Stables",
    "wof:placetype":"venue"
},
  "geometry": {"coordinates":[-97.526932,30.988261],"type":"Point"}
}