{
  "type": "Feature",
  "properties": {
    "iso:country":"US",
    "sg:address":"1302 W Magnolia Ave",
    "sg:city":"Fort Worth",
    "sg:classifiers":[
        {
            "category":"Health Services",
            "subcategory":"Clinic",
            "type":"Services"
        }
    ],
    "sg:phone":"+1 817 335 7700",
    "sg:postcode":"76104",
    "sg:province":"TX",
    "sg:tags":[
        "colonic",
        "irrigation"
    ],
    "wof:name":"Alpha Colonics Ctr",
    "wof:placetype":"venue"
},
  "geometry": {"coordinates":[-97.340253,32.730744],"type":"Point"}
}