{
  "type": "Feature",
  "properties": {
    "iso:country":"US",
    "sg:address":"1127 Aldine Bender Rd",
    "sg:city":"Houston",
    "sg:classifiers":[
        {
            "category":"Education",
            "subcategory":"Kindergarten",
            "type":"Public Place"
        }
    ],
    "sg:phone":"+1 281 449 0654",
    "sg:postcode":"77032",
    "sg:province":"TX",
    "sg:tags":[
        "school",
        "driving"
    ],
    "wof:name":"Bender Enterprises Inc",
    "wof:placetype":"venue"
},
  "geometry": {"coordinates":[-95.37130000000001,29.933399],"type":"Point"}
}