{
  "type": "Feature",
  "properties": {
    "iso:country":"US",
    "sg:address":"7301 N Fm 620",
    "sg:city":"Austin",
    "sg:classifiers":[
        {
            "category":"Coffee & Tea",
            "type":"Food & Drink"
        }
    ],
    "sg:phone":"+1 512 250 3533",
    "sg:postcode":"78726",
    "sg:province":"TX",
    "sg:website":"www.starbucks.com",
    "wof:name":"Starbucks Coffee",
    "wof:placetype":"venue"
},
  "geometry": {"coordinates":[-97.84410800000001,30.399958],"type":"Point"}
}