{
  "type": "Feature",
  "properties": {
    "iso:country":"US",
    "sg:address":"2233 Ridge Rd",
    "sg:city":"Rockwall",
    "sg:classifiers":[
        {
            "category":"Real Estate",
            "subcategory":"Real Estate Agent",
            "type":"Services"
        }
    ],
    "sg:phone":"+1 972 771 0685",
    "sg:postcode":"75032",
    "sg:province":"TX",
    "wof:name":"Lewis Real Estate Investments",
    "wof:placetype":"venue"
},
  "geometry": {"coordinates":[-96.46739100000001,32.900645],"type":"Point"}
}