{
  "type": "Feature",
  "properties": {
    "iso:country":"US",
    "sg:address":"5901 Mcpherson Rd Ste 6C",
    "sg:city":"Laredo",
    "sg:classifiers":[
        {
            "category":"Real Estate",
            "subcategory":"Real Estate Services",
            "type":"Services"
        },
        {
            "category":"Insurance",
            "subcategory":"Title Insurance",
            "type":"Services"
        },
        {
            "category":"Banks & Credit Unions",
            "subcategory":"Financial Services",
            "type":"Services"
        }
    ],
    "sg:phone":"+1 956 791 5810",
    "sg:postcode":"78041",
    "sg:province":"TX",
    "sg:tags":[
        "escrow"
    ],
    "wof:name":"Stewart Title Co",
    "wof:placetype":"venue"
},
  "geometry": {"coordinates":[-99.479912,27.554411],"type":"Point"}
}