{
  "type": "Feature",
  "properties": {
    "iso:country":"US",
    "sg:address":"12322 East Fwy",
    "sg:city":"Houston",
    "sg:classifiers":[
        {
            "category":"Organizations",
            "subcategory":"Religious Organization",
            "type":"Services"
        }
    ],
    "sg:phone":"+1 713 534 1048",
    "sg:postcode":"77015",
    "sg:province":"TX",
    "wof:name":"New Frontier Church.",
    "wof:placetype":"venue"
},
  "geometry": {"coordinates":[-95.218996,29.769852],"type":"Point"}
}