{
  "type": "Feature",
  "properties": {
    "iso:country":"US",
    "sg:address":"10001 S FM 1187",
    "sg:city":"Fort Worth",
    "sg:classifiers":[
        {
            "category":"Retail",
            "subcategory":"Veterinary Services",
            "type":"Services"
        }
    ],
    "sg:phone":"+1 817 443 3927",
    "sg:postcode":"76126",
    "sg:province":"TX",
    "wof:name":"Neil William H Buck Jr",
    "wof:placetype":"venue"
},
  "geometry": {"coordinates":[-97.57135100000001,32.654148],"type":"Point"}
}