{
  "type": "Feature",
  "properties": {
    "iso:country":"US",
    "sg:address":"104 S Main St",
    "sg:city":"Fort Worth",
    "sg:classifiers":[
        {
            "category":"Building & Trades",
            "subcategory":"Cleaning & Sanitation",
            "type":"Services"
        }
    ],
    "sg:phone":"+1 817 336 0034",
    "sg:postcode":"76104",
    "sg:province":"TX",
    "sg:tags":[
        "maintenance"
    ],
    "wof:name":"Work Force",
    "wof:placetype":"venue"
},
  "geometry": {"coordinates":[-97.325935,32.742546],"type":"Point"}
}