{
  "type": "Feature",
  "properties": {
    "iso:country":"US",
    "sg:address":"2305 Ridge Rd",
    "sg:city":"Rockwall",
    "sg:classifiers":[
        {
            "category":"Social Services",
            "subcategory":"Job Training",
            "type":"Services"
        }
    ],
    "sg:phone":"+1 972 772 2320",
    "sg:postcode":"75032",
    "sg:province":"TX",
    "sg:tags":[
        "rehabilitation"
    ],
    "wof:name":"Alvera Rehab Assoc Inc",
    "wof:placetype":"venue"
},
  "geometry": {"coordinates":[-96.468891,32.899072],"type":"Point"}
}