{
  "type": "Feature",
  "properties": {
    "iso:country":"US",
    "sg:address":"405 Cottonwood St",
    "sg:city":"Brenham",
    "sg:classifiers":[
        {
            "category":"Building & Trades",
            "subcategory":"Construction",
            "type":"Services"
        }
    ],
    "sg:phone":"+1 979 836 2043",
    "sg:postcode":"77833",
    "sg:province":"TX",
    "sg:tags":[
        "house",
        "moving"
    ],
    "wof:name":"Yoakum House Moving Inc",
    "wof:placetype":"venue"
},
  "geometry": {"coordinates":[-96.396286,30.171036],"type":"Point"}
}