{
  "type": "Feature",
  "properties": {
    "iso:country":"US",
    "sg:address":"913 Custer Rd",
    "sg:city":"Richardson",
    "sg:classifiers":[
        {
            "category":"Shopping",
            "subcategory":"Hobbies, Toys, & Games",
            "type":"Retail Goods"
        }
    ],
    "sg:phone":"+1 972 234 2971",
    "sg:postcode":"75080",
    "sg:province":"TX",
    "sg:tags":[
        "shop",
        "hobby",
        "model",
        "coin",
        "supply"
    ],
    "wof:name":"Alamo Coins of Texas",
    "wof:placetype":"venue"
},
  "geometry": {"coordinates":[-96.73518300000001,32.959935],"type":"Point"}
}