{
  "type": "Feature",
  "properties": {
    "iso:country":"US",
    "sg:address":"8370 Cripple Creek Dr",
    "sg:city":"Frisco",
    "sg:classifiers":[
        {
            "category":"Professional",
            "type":"Services"
        }
    ],
    "sg:phone":"+1 972 987 5266",
    "sg:postcode":"75034",
    "sg:province":"TX",
    "wof:name":"Wanda McDonald",
    "wof:placetype":"venue"
},
  "geometry": {"coordinates":[-96.811027,33.14343],"type":"Point"}
}