{
  "type": "Feature",
  "properties": {
    "iso:country":"US",
    "sg:address":"3701 Kirby Dr Suite 730",
    "sg:city":"Houston",
    "sg:classifiers":[
        {
            "category":"Shopping",
            "subcategory":"Stationery & Office Supplies",
            "type":"Retail Goods"
        },
        {
            "category":"Wholesale",
            "subcategory":"Computers",
            "type":"Manufacturing & Wholesale Goods"
        }
    ],
    "sg:phone":"+1 713 526 3131",
    "sg:postcode":"77098",
    "sg:province":"TX",
    "sg:tags":[
        "machine",
        "equipment",
        "copy"
    ],
    "sg:website":"http://findxeroxagents.com/copiers-in-houston-texas_617",
    "wof:name":"Office Evolutions, Inc.",
    "wof:placetype":"venue"
},
  "geometry": {"coordinates":[-95.418671,29.733459],"type":"Point"}
}