{
  "type": "Feature",
  "properties": {
    "iso:country":"US",
    "sg:address":"900 Atkins Ave",
    "sg:city":"Devine",
    "sg:classifiers":[
        {
            "category":"Education",
            "subcategory":"School",
            "type":"Public Place"
        }
    ],
    "sg:phone":"+1 830 663 6740",
    "sg:postcode":"78016",
    "sg:province":"TX",
    "wof:name":"Devine Intermediate School",
    "wof:placetype":"venue"
},
  "geometry": {"coordinates":[-98.91483599999999,29.147658],"type":"Point"}
}