{
  "type": "Feature",
  "properties": {
    "iso:country":"US",
    "sg:address":"615 E Moore Ave",
    "sg:city":"Terrell",
    "sg:classifiers":[
        {
            "category":"Manufacturing",
            "subcategory":"Food",
            "type":"Manufacturing & Wholesale Goods"
        }
    ],
    "sg:phone":"+1 972 563 0651",
    "sg:postcode":"75160",
    "sg:province":"TX",
    "sg:tags":[
        "product",
        "mfg"
    ],
    "wof:name":"Mrs Bairds Bakeries Bus Tr",
    "wof:placetype":"venue"
},
  "geometry": {"coordinates":[-96.26852,32.735413],"type":"Point"}
}