{
  "type": "Feature",
  "properties": {
    "iso:country":"US",
    "sg:address":"14045 FM 730 N",
    "sg:city":"Azle",
    "sg:classifiers":[
        {
            "category":"Autos & Motor Vehicles",
            "subcategory":"Boat Sales",
            "type":"Retail Goods"
        }
    ],
    "sg:phone":"+1 817 444 0103",
    "sg:postcode":"76020",
    "sg:province":"TX",
    "sg:tags":[
        "equipment",
        "supply"
    ],
    "wof:name":"Seger Docks & Lifts",
    "wof:placetype":"venue"
},
  "geometry": {"coordinates":[-97.543575,32.982977],"type":"Point"}
}