{
  "type": "Feature",
  "properties": {
    "iso:country":"US",
    "sg:address":"201 N Rivercrest Dr",
    "sg:city":"Fort Worth",
    "sg:classifiers":[
        {
            "category":"Professional",
            "subcategory":"Management & Consulting",
            "type":"Services"
        }
    ],
    "sg:phone":"+1 817 732 4080",
    "sg:postcode":"76107",
    "sg:province":"TX",
    "sg:tags":[
        "engineering",
        "business"
    ],
    "wof:name":"Jary Consulting Services",
    "wof:placetype":"venue"
},
  "geometry": {"coordinates":[-97.37854799999999,32.76023],"type":"Point"}
}