{
  "type": "Feature",
  "properties": {
    "iso:country":"US",
    "sg:address":"401 Rio Concho Dr",
    "sg:city":"San Angelo",
    "sg:classifiers":[
        {
            "category":"Retail",
            "subcategory":"Repair Shop",
            "type":"Services"
        }
    ],
    "sg:phone":"+1 325 653 5271",
    "sg:postcode":"76903",
    "sg:province":"TX",
    "sg:tags":[
        "equipment",
        "industrial"
    ],
    "wof:name":"Thyssenkrupp Elevator",
    "wof:placetype":"venue"
},
  "geometry": {"coordinates":[-100.425515,31.462499],"type":"Point"}
}