{
  "type": "Feature",
  "properties": {
    "iso:country":"US",
    "sg:address":"901 W Duncan Ave",
    "sg:city":"Comanche",
    "sg:classifiers":[
        {
            "category":"Professional",
            "type":"Services"
        }
    ],
    "sg:phone":"+1 325 356 5137",
    "sg:postcode":"76442",
    "sg:province":"TX",
    "wof:name":"Calico Designs",
    "wof:placetype":"venue"
},
  "geometry": {"coordinates":[-98.614082,31.899433],"type":"Point"}
}