{
  "type": "Feature",
  "properties": {
    "iso:country":"US",
    "sg:address":"12304 Burr Ridge Dr",
    "sg:city":"Austin",
    "sg:classifiers":[
        {
            "category":"Professional",
            "subcategory":"Computer Services",
            "type":"Services"
        }
    ],
    "sg:phone":"+1 512 258 2339",
    "sg:postcode":"78729",
    "sg:province":"TX",
    "sg:tags":[
        "consultant",
        "designer"
    ],
    "wof:name":"B & B Enterprises",
    "wof:placetype":"venue"
},
  "geometry": {"coordinates":[-97.780652,30.448457],"type":"Point"}
}