{
  "type": "Feature",
  "properties": {
    "iso:country":"US",
    "sg:address":"2305 Trellis Ln",
    "sg:city":"Plano",
    "sg:classifiers":[
        {
            "category":"Manufacturing",
            "subcategory":"Metals",
            "type":"Manufacturing & Wholesale Goods"
        }
    ],
    "sg:phone":"+1 972 964 3980",
    "sg:postcode":"75075",
    "sg:province":"TX",
    "sg:tags":[
        "metalwork",
        "architectural",
        "mfg"
    ],
    "wof:name":"Signature Stair Parts",
    "wof:placetype":"venue"
},
  "geometry": {"coordinates":[-96.766597,33.030672],"type":"Point"}
}