{
  "type": "Feature",
  "properties": {
    "iso:country":"US",
    "sg:address":"2501 Texas Ave S",
    "sg:city":"College Station",
    "sg:classifiers":[
        {
            "category":"Ice Cream",
            "type":"Food & Drink"
        }
    ],
    "sg:menulink":"http://www.allmenus.com/tx/bryan-college-station/233752-la-paletera/menu/",
    "sg:phone":"+1 979 680 8618",
    "sg:postcode":"77840",
    "sg:province":"TX",
    "sg:tags":[
        "smoothy",
        "juice",
        "american",
        "pizza"
    ],
    "wof:name":"La Paletera",
    "wof:placetype":"venue"
},
  "geometry": {"coordinates":[-96.308995,30.607301],"type":"Point"}
}