{
  "type": "Feature",
  "properties": {
    "iso:country":"US",
    "sg:address":"13041 Valley Forge Cir",
    "sg:city":"Mesquite",
    "sg:classifiers":[
        {
            "category":"Retail",
            "subcategory":"Repair Shop",
            "type":"Services"
        }
    ],
    "sg:phone":"+1 972 226 5781",
    "sg:postcode":"75180",
    "sg:province":"TX",
    "sg:tags":[
        "reupholstery",
        "furniture"
    ],
    "wof:name":"Genes Upholstery",
    "wof:placetype":"venue"
},
  "geometry": {"coordinates":[-96.600702,32.719386],"type":"Point"}
}