{
  "type": "Feature",
  "properties": {
    "iso:country":"US",
    "sg:address":"419 Buffalo Dr",
    "sg:city":"Arlington",
    "sg:classifiers":[
        {
            "category":"Building & Trades",
            "subcategory":"Equipment Rental",
            "type":"Services"
        }
    ],
    "sg:phone":"+1 817 801 7233",
    "sg:postcode":"76013",
    "sg:province":"TX",
    "sg:tags":[
        "rent",
        "amusement",
        "lease"
    ],
    "wof:name":"Space Walk of Mid Cities",
    "wof:placetype":"venue"
},
  "geometry": {"coordinates":[-97.15487400000001,32.731429],"type":"Point"}
}