{
  "type": "Feature",
  "properties": {
    "iso:country":"US",
    "sg:address":"2838 Quail Oak St",
    "sg:city":"San Antonio",
    "sg:classifiers":[
        {
            "category":"Manufacturing",
            "subcategory":"Electronics",
            "type":"Manufacturing & Wholesale Goods"
        }
    ],
    "sg:phone":"+1 210 494 6076",
    "sg:postcode":"78232",
    "sg:province":"TX",
    "sg:tags":[
        "equipment",
        "mfg",
        "home"
    ],
    "wof:name":"Roberts Amplification",
    "wof:placetype":"venue"
},
  "geometry": {"coordinates":[-98.445909,29.592403],"type":"Point"}
}