{
  "type": "Feature",
  "properties": {
    "iso:country":"US",
    "sg:address":"1710 Castlerock Rd",
    "sg:city":"Houston",
    "sg:classifiers":[
        {
            "category":"Professional",
            "subcategory":"Business Services",
            "type":"Services"
        }
    ],
    "sg:phone":"+1 281 583 5333",
    "sg:postcode":"77090",
    "sg:province":"TX",
    "sg:tags":[
        "personal"
    ],
    "wof:name":"Banana Tan",
    "wof:placetype":"venue"
},
  "geometry": {"coordinates":[-95.462789,30.022414],"type":"Point"}
}