{
  "type": "Feature",
  "properties": {
    "iso:country":"US",
    "sg:address":"1701 W Frank Ave",
    "sg:city":"Lufkin",
    "sg:classifiers":[
        {
            "category":"Autos & Motor Vehicles",
            "subcategory":"Auto Supplies",
            "type":"Retail Goods"
        }
    ],
    "sg:phone":"+1 936 699 4010",
    "sg:postcode":"75904",
    "sg:province":"TX",
    "sg:tags":[
        "automobile",
        "parts"
    ],
    "wof:name":"Advance Auto Parts Inc",
    "wof:placetype":"venue"
},
  "geometry": {"coordinates":[-94.75307599999999,31.333813],"type":"Point"}
}