{
  "type": "Feature",
  "properties": {
    "iso:country":"US",
    "sg:address":"205 Hendricks Blvd",
    "sg:city":"Wink",
    "sg:classifiers":[
        {
            "category":"Food & Beverages",
            "subcategory":"Groceries & Convenience Stores",
            "type":"Retail Goods"
        }
    ],
    "sg:phone":"+1 432 527 3684",
    "sg:postcode":"79789",
    "sg:province":"TX",
    "sg:tags":[
        "grocer"
    ],
    "wof:name":"Robertson's Grocery",
    "wof:placetype":"venue"
},
  "geometry": {"coordinates":[-103.159105,31.752548],"type":"Point"}
}