{
  "type": "Feature",
  "properties": {
    "iso:country":"US",
    "sg:address":"1000 Fayette Dr",
    "sg:city":"Euless",
    "sg:classifiers":[
        {
            "category":"Banks & Credit Unions",
            "subcategory":"Financial Services",
            "type":"Services"
        }
    ],
    "sg:phone":"+1 817 283 4279",
    "sg:postcode":"76039",
    "sg:province":"TX",
    "sg:tags":[
        "investor"
    ],
    "wof:name":"KRC Investments LLC",
    "wof:placetype":"venue"
},
  "geometry": {"coordinates":[-97.095412,32.850381],"type":"Point"}
}