{
  "type": "Feature",
  "properties": {
    "iso:country":"US",
    "sg:address":"7186 Redbird Ln W",
    "sg:city":"Burleson",
    "sg:classifiers":[
        {
            "category":"Building & Trades",
            "subcategory":"Construction",
            "type":"Services"
        }
    ],
    "sg:phone":"+1 817 293 4826",
    "sg:postcode":"76028",
    "sg:province":"TX",
    "sg:tags":[
        "contractor"
    ],
    "wof:name":"Trey S Construction Inc",
    "wof:placetype":"venue"
},
  "geometry": {"coordinates":[-97.27504399999999,32.572807],"type":"Point"}
}