{
  "type": "Feature",
  "properties": {
    "iso:country":"US",
    "sg:address":"2804 N Laurent St",
    "sg:city":"Victoria",
    "sg:classifiers":[
        {
            "category":"Shopping",
            "subcategory":"Department Store",
            "type":"Retail Goods"
        }
    ],
    "sg:phone":"+1 361 573 3288",
    "sg:postcode":"77901",
    "sg:province":"TX",
    "sg:website":"www.dunlaps.com",
    "wof:name":"Dunlap's",
    "wof:placetype":"venue"
},
  "geometry": {"coordinates":[-96.992028,28.82005],"type":"Point"}
}