{
  "type": "Feature",
  "properties": {
    "iso:country":"US",
    "sg:address":"3215 Forrester Dr",
    "sg:city":"Pearland",
    "sg:classifiers":[
        {
            "category":"Wholesale",
            "subcategory":"Chemicals & Plastics",
            "type":"Manufacturing & Wholesale Goods"
        }
    ],
    "sg:phone":"+1 281 489 3989",
    "sg:postcode":"77584",
    "sg:province":"TX",
    "wof:name":"Monchem",
    "wof:placetype":"venue"
},
  "geometry": {"coordinates":[-95.354936,29.538185],"type":"Point"}
}