{
  "type": "Feature",
  "properties": {
    "iso:country":"US",
    "sg:address":"104 Barker St",
    "sg:city":"Linden",
    "sg:classifiers":[
        {
            "category":"Utilities",
            "subcategory":"Water",
            "type":"Services"
        }
    ],
    "sg:phone":"+1 903 756 8789",
    "sg:postcode":"75563",
    "sg:province":"TX",
    "sg:tags":[
        "system",
        "supply"
    ],
    "wof:name":"Western Cass Water Supply Co",
    "wof:placetype":"venue"
},
  "geometry": {"coordinates":[-94.363103,33.000139],"type":"Point"}
}