{
  "type": "Feature",
  "properties": {
    "iso:country":"US",
    "sg:address":"115 Kimberly Ln",
    "sg:city":"Kountze",
    "sg:classifiers":[
        {
            "category":"Retail",
            "subcategory":"Auto Repair",
            "type":"Services"
        }
    ],
    "sg:phone":"+1 409 246 1141",
    "sg:postcode":"77625",
    "sg:province":"TX",
    "sg:tags":[
        "machine",
        "automobile",
        "shop"
    ],
    "wof:name":"Ray's Machine Shop",
    "wof:placetype":"venue"
},
  "geometry": {"coordinates":[-94.30100299999999,30.370498],"type":"Point"}
}