{
  "type": "Feature",
  "properties": {
    "iso:country":"US",
    "sg:address":"3000 Smith St",
    "sg:city":"Houston",
    "sg:classifiers":[
        {
            "category":"Professional",
            "subcategory":"Lawyer & Legal Services",
            "type":"Services"
        }
    ],
    "sg:phone":"+1 713 520 1620",
    "sg:postcode":"77006",
    "sg:province":"TX",
    "sg:tags":[
        "criminal",
        "attorney",
        "law",
        "plan"
    ],
    "wof:name":"Scott Ramsey",
    "wof:placetype":"venue"
},
  "geometry": {"coordinates":[-95.37957,29.744881],"type":"Point"}
}