{
  "type": "Feature",
  "properties": {
    "iso:country":"US",
    "sg:address":"5323 Harry Hines Blvd Bldg C",
    "sg:city":"Dallas",
    "sg:classifiers":[
        {
            "category":"Fast Food",
            "type":"Food & Drink"
        }
    ],
    "sg:phone":"+1 214 648 2870",
    "sg:postcode":"75390",
    "sg:province":"TX",
    "sg:tags":[
        "burger"
    ],
    "sg:website":"www.burgerhouse.com/",
    "wof:name":"Burger House",
    "wof:placetype":"venue"
},
  "geometry": {"coordinates":[-96.83841,32.812606],"type":"Point"}
}