{
  "type": "Feature",
  "properties": {
    "iso:country":"US",
    "sg:address":"3003 Williams Dr",
    "sg:city":"Georgetown",
    "sg:classifiers":[
        {
            "category":"Banks & Credit Unions",
            "subcategory":"Bank",
            "type":"Services"
        }
    ],
    "sg:phone":"+1 512 930 4555",
    "sg:postcode":"78628",
    "sg:province":"TX",
    "sg:tags":[
        "state",
        "commercial"
    ],
    "wof:name":"Compass Bank",
    "wof:placetype":"venue"
},
  "geometry": {"coordinates":[-97.69297899999999,30.664258],"type":"Point"}
}