{
  "type": "Feature",
  "properties": {
    "iso:country":"US",
    "sg:address":"1152 Sailfish St",
    "sg:city":"Hitchcock",
    "sg:classifiers":[
        {
            "category":"Insurance",
            "subcategory":"Life Insurance",
            "type":"Services"
        }
    ],
    "sg:phone":"+1 409 935 0303",
    "sg:postcode":"77563",
    "sg:province":"TX",
    "sg:tags":[
        "carrier"
    ],
    "wof:name":"Fentanes & Associates",
    "wof:placetype":"venue"
},
  "geometry": {"coordinates":[-94.937228,29.323077],"type":"Point"}
}