{
  "type": "Feature",
  "properties": {
    "iso:country":"US",
    "sg:address":"20414 Laverton Dr",
    "sg:city":"Katy",
    "sg:classifiers":[
        {
            "category":"Real Estate",
            "subcategory":"Real Estate Agent",
            "type":"Services"
        }
    ],
    "sg:phone":"+1 281 492 2647",
    "sg:postcode":"77450",
    "sg:province":"TX",
    "wof:name":"Houston-KATY Real Estate",
    "wof:placetype":"venue"
},
  "geometry": {"coordinates":[-95.725143,29.779033],"type":"Point"}
}