{
  "type": "Feature",
  "properties": {
    "iso:country":"US",
    "sg:address":"12815 Wire Rd",
    "sg:city":"Leander",
    "sg:classifiers":[
        {
            "category":"Personal",
            "type":"Services"
        }
    ],
    "sg:phone":"+1 512 267 1016",
    "sg:postcode":"78641",
    "sg:province":"TX",
    "sg:tags":[
        "food"
    ],
    "wof:name":"Algae For Life",
    "wof:placetype":"venue"
},
  "geometry": {"coordinates":[-97.871363,30.504756],"type":"Point"}
}