{
  "type": "Feature",
  "properties": {
    "iso:country":"US",
    "sg:address":"109 W Kingsmill Ave",
    "sg:city":"Pampa",
    "sg:classifiers":[
        {
            "category":"Food & Beverages",
            "subcategory":"Specialty",
            "type":"Retail Goods"
        }
    ],
    "sg:phone":"+1 806 665 4883",
    "sg:postcode":"79065",
    "sg:province":"TX",
    "wof:name":"Herbs Etc",
    "wof:placetype":"venue"
},
  "geometry": {"coordinates":[-100.962165,35.536637],"type":"Point"}
}