{
  "type": "Feature",
  "properties": {
    "iso:country":"US",
    "sg:address":"314 W 11th St",
    "sg:city":"Austin",
    "sg:classifiers":[
        {
            "category":"Government",
            "subcategory":"Court House",
            "type":"Public Place"
        }
    ],
    "sg:phone":"+1 512 854 9415",
    "sg:postcode":"78701",
    "sg:province":"TX",
    "sg:tags":[
        "county",
        "counsel"
    ],
    "wof:name":"Travis County Attorney",
    "wof:placetype":"venue"
},
  "geometry": {"coordinates":[-97.744422,30.273736],"type":"Point"}
}