{
  "type": "Feature",
  "properties": {
    "iso:country":"US",
    "sg:address":"512 Flood St",
    "sg:city":"Wichita Falls",
    "sg:classifiers":[
        {
            "category":"Building & Trades",
            "subcategory":"Construction",
            "type":"Services"
        }
    ],
    "sg:phone":"+1 940 761 4427",
    "sg:postcode":"76301",
    "sg:province":"TX",
    "sg:tags":[
        "utility",
        "contractor"
    ],
    "wof:name":"East Wichita Utility Payment",
    "wof:placetype":"venue"
},
  "geometry": {"coordinates":[-98.479129,33.91528],"type":"Point"}
}