{
  "type": "Feature",
  "properties": {
    "iso:country":"US",
    "sg:address":"16235 Olive Glen Dr",
    "sg:city":"Houston",
    "sg:classifiers":[
        {
            "category":"Professional",
            "subcategory":"Management & Consulting",
            "type":"Services"
        }
    ],
    "sg:phone":"+1 713 294 2654",
    "sg:postcode":"77082",
    "sg:province":"TX",
    "sg:tags":[
        "business"
    ],
    "wof:name":"Mj Environmental Consulting",
    "wof:placetype":"venue"
},
  "geometry": {"coordinates":[-95.669771,29.712414],"type":"Point"}
}