{
  "type": "Feature",
  "properties": {
    "iso:country":"US",
    "sg:address":"408 Northville St",
    "sg:city":"Houston",
    "sg:classifiers":[
        {
            "category":"Manufacturing",
            "subcategory":"Metals",
            "type":"Manufacturing & Wholesale Goods"
        },
        {
            "category":"Building & Trades",
            "subcategory":"Plumbing",
            "type":"Services"
        },
        {
            "category":"Building & Trades",
            "subcategory":"Construction",
            "type":"Services"
        }
    ],
    "sg:phone":"+1 281 252 0151",
    "sg:postcode":"77037",
    "sg:province":"TX",
    "sg:tags":[
        "bending",
        "steel",
        "pipe",
        "fabricating",
        "fabricator",
        "welder"
    ],
    "sg:website":"http://www.weweld.com",
    "wof:name":"Precision Welding & Fabrication",
    "wof:placetype":"venue"
},
  "geometry": {"coordinates":[-95.40716,29.909136],"type":"Point"}
}