{
  "type": "Feature",
  "properties": {
    "iso:country":"US",
    "sg:address":"215 N Col Rowe Blvd",
    "sg:city":"Mcallen",
    "sg:classifiers":[
        {
            "category":"Wholesale",
            "subcategory":"Machinery & Supplies",
            "type":"Manufacturing & Wholesale Goods"
        },
        {
            "category":"Retail",
            "subcategory":"Repair Shop",
            "type":"Services"
        }
    ],
    "sg:phone":"+1 956 686 2506",
    "sg:postcode":"78501",
    "sg:province":"TX",
    "sg:tags":[
        "engine"
    ],
    "wof:name":"McAllen Fuel Injection Inc",
    "wof:placetype":"venue"
},
  "geometry": {"coordinates":[-98.220883,26.204297],"type":"Point"}
}