{
  "type": "Feature",
  "properties": {
    "iso:country":"US",
    "sg:address":"7527 Raton St",
    "sg:city":"Houston",
    "sg:classifiers":[
        {
            "category":"Building & Trades",
            "subcategory":"Construction",
            "type":"Services"
        }
    ],
    "sg:phone":"+1 713 682 3939",
    "sg:postcode":"77055",
    "sg:province":"TX",
    "sg:tags":[
        "concrete",
        "cutting",
        "breaking",
        "sawing"
    ],
    "wof:name":"Core-Ect Core Drilling",
    "wof:placetype":"venue"
},
  "geometry": {"coordinates":[-95.479479,29.801132],"type":"Point"}
}