{
  "type": "Feature",
  "properties": {
    "iso:country":"US",
    "sg:address":"3701 W Expressway 83",
    "sg:city":"Mission",
    "sg:classifiers":[
        {
            "category":"Restaurant",
            "type":"Food & Drink"
        }
    ],
    "sg:menulink":"http://www.allmenus.com/tx/mission/177674-jack-in-the-box/menu/",
    "sg:phone":"+1 956 519 7807",
    "sg:postcode":"78572",
    "sg:province":"TX",
    "sg:tags":[
        "burger",
        "american"
    ],
    "wof:name":"Jack in the Box",
    "wof:placetype":"venue"
},
  "geometry": {"coordinates":[-98.358627,26.227359],"type":"Point"}
}