{
  "type": "Feature",
  "properties": {
    "iso:country":"US",
    "sg:address":"2601 S. Stemmons Frwy",
    "sg:city":"Lewisville",
    "sg:classifiers":[
        {
            "category":"Restaurant",
            "type":"Food & Drink"
        }
    ],
    "sg:phone":"+1 214 488 7222",
    "sg:postcode":"75067",
    "sg:province":"TX",
    "sg:tags":[
        "new",
        "american"
    ],
    "sg:website":"www.twinpeaksrestaurant.com",
    "wof:name":"Twin Peaks Restaurant",
    "wof:placetype":"venue"
},
  "geometry": {"coordinates":[-96.96260100000001,33.000999],"type":"Point"}
}