{
  "type": "Feature",
  "properties": {
    "iso:country":"US",
    "sg:address":"105 North Ave",
    "sg:city":"Laredo",
    "sg:classifiers":[
        {
            "category":"Building & Trades",
            "subcategory":"Plumbing",
            "type":"Services"
        }
    ],
    "sg:phone":"+1 956 717 1036",
    "sg:postcode":"78045",
    "sg:province":"TX",
    "sg:tags":[
        "contractor"
    ],
    "wof:name":"Air Laredo",
    "wof:placetype":"venue"
},
  "geometry": {"coordinates":[-99.485682,27.57347],"type":"Point"}
}