{
  "type": "Feature",
  "properties": {
    "iso:country":"US",
    "sg:address":"6735 Main St",
    "sg:city":"Hitchcock",
    "sg:classifiers":[
        {
            "category":"Restaurant",
            "type":"Food & Drink"
        }
    ],
    "sg:phone":"+1 409 986 5054",
    "sg:postcode":"77563",
    "sg:province":"TX",
    "sg:tags":[
        "cafe"
    ],
    "wof:name":"Granny's Kuntry KAFE",
    "wof:placetype":"venue"
},
  "geometry": {"coordinates":[-95.01582999999999,29.349214],"type":"Point"}
}