{
  "type": "Feature",
  "properties": {
    "iso:country":"US",
    "sg:address":"13721 E FM 1097",
    "sg:city":"Willis",
    "sg:classifiers":[
        {
            "category":"Restaurant",
            "type":"Food & Drink"
        },
        {
            "category":"Retail",
            "subcategory":"Auto Repair",
            "type":"Services"
        }
    ],
    "sg:phone":"+1 936 890 6400",
    "sg:postcode":"77318",
    "sg:province":"TX",
    "sg:tags":[
        "body"
    ],
    "wof:name":"Original Italian Pizza",
    "wof:placetype":"venue"
},
  "geometry": {"coordinates":[-95.4478,30.438667],"type":"Point"}
}