{
  "type": "Feature",
  "properties": {
    "iso:country":"US",
    "sg:address":"1526 Fulton St",
    "sg:city":"San Angelo",
    "sg:classifiers":[
        {
            "category":"Professional",
            "subcategory":"Computer Services",
            "type":"Services"
        }
    ],
    "sg:phone":"+1 325 656 2178",
    "sg:postcode":"76905",
    "sg:province":"TX",
    "sg:tags":[
        "related"
    ],
    "wof:name":"A & Systems",
    "wof:placetype":"venue"
},
  "geometry": {"coordinates":[-100.411784,31.442114],"type":"Point"}
}