{
  "type": "Feature",
  "properties": {
    "iso:country":"US",
    "sg:address":"8815 Dyer St",
    "sg:city":"El Paso",
    "sg:classifiers":[
        {
            "category":"Wholesale",
            "subcategory":"Medical Equipment & Supplies",
            "type":"Manufacturing & Wholesale Goods"
        }
    ],
    "sg:phone":"+1 915 751 0737",
    "sg:postcode":"79904",
    "sg:province":"TX",
    "wof:name":"Caprock Medical Supply",
    "wof:placetype":"venue"
},
  "geometry": {"coordinates":[-106.43313000000001,31.862563],"type":"Point"}
}