{
  "type": "Feature",
  "properties": {
    "iso:country":"US",
    "sg:address":"4017 Meadow Lake Ln",
    "sg:city":"Houston",
    "sg:classifiers":[
        {
            "category":"Health Services",
            "subcategory":"Doctor",
            "type":"Services"
        }
    ],
    "sg:phone":"+1 713 623 2132",
    "sg:postcode":"77027",
    "sg:province":"TX",
    "wof:name":"Bean Samuel F MD",
    "wof:placetype":"venue"
},
  "geometry": {"coordinates":[-95.445503,29.746099],"type":"Point"}
}