{
  "type": "Feature",
  "properties": {
    "iso:country":"US",
    "sg:address":"902 Prairie Trl",
    "sg:city":"Austin",
    "sg:classifiers":[
        {
            "category":"Retail",
            "subcategory":"Auto Repair",
            "type":"Services"
        }
    ],
    "sg:phone":"+1 512 836 6191",
    "sg:postcode":"78758",
    "sg:province":"TX",
    "wof:name":"Mike's Auto",
    "wof:placetype":"venue"
},
  "geometry": {"coordinates":[-97.69029999999999,30.379601],"type":"Point"}
}