{
  "type": "Feature",
  "properties": {
    "iso:country":"US",
    "sg:address":"12014 Forestwood Cir",
    "sg:city":"Dallas",
    "sg:classifiers":[
        {
            "category":"Real Estate",
            "subcategory":"Real Estate Agent",
            "type":"Services"
        }
    ],
    "sg:phone":"+1 214 769 4276",
    "sg:postcode":"75244",
    "sg:province":"TX",
    "sg:tags":[
        "investment"
    ],
    "wof:name":"G 2 Capital Corp",
    "wof:placetype":"venue"
},
  "geometry": {"coordinates":[-96.82075,32.912607],"type":"Point"}
}