{
  "type": "Feature",
  "properties": {
    "iso:country":"US",
    "sg:address":"6924 Townbluff Dr",
    "sg:city":"Dallas",
    "sg:classifiers":[
        {
            "category":"Professional",
            "subcategory":"Business Services",
            "type":"Services"
        }
    ],
    "sg:phone":"+1 972 239 4314",
    "sg:postcode":"75248",
    "sg:province":"TX",
    "wof:name":"A J Sam Enterprises Inc",
    "wof:placetype":"venue"
},
  "geometry": {"coordinates":[-96.789451,32.954899],"type":"Point"}
}