{
  "type": "Feature",
  "properties": {
    "iso:country":"US",
    "sg:address":"210 W Anderson St",
    "sg:city":"Brownwood",
    "sg:classifiers":[
        {
            "category":"Manufacturing",
            "subcategory":"Leather Goods",
            "type":"Manufacturing & Wholesale Goods"
        }
    ],
    "sg:phone":"+1 325 646 0141",
    "sg:postcode":"76801",
    "sg:province":"TX",
    "sg:tags":[
        "rubber",
        "footwear",
        "except"
    ],
    "wof:name":"Bear Feet",
    "wof:placetype":"venue"
},
  "geometry": {"coordinates":[-98.983653,31.721274],"type":"Point"}
}