{
  "type": "Feature",
  "properties": {
    "iso:country":"US",
    "sg:address":"8609 NW Plaza Dr Ste 432",
    "sg:city":"Dallas",
    "sg:classifiers":[
        {
            "category":"Professional",
            "subcategory":"Accounting & Tax Preparation",
            "type":"Services"
        }
    ],
    "sg:phone":"+1 214 369 9090",
    "sg:postcode":"75225",
    "sg:province":"TX",
    "sg:tags":[
        "accountant"
    ],
    "wof:name":"Brown Thomas L CPA",
    "wof:placetype":"venue"
},
  "geometry": {"coordinates":[-96.791,32.8624],"type":"Point"}
}