{
  "type": "Feature",
  "properties": {
    "iso:country":"US",
    "sg:address":"3714 Old Settlers Rd",
    "sg:city":"Flower Mound",
    "sg:classifiers":[
        {
            "category":"Building & Trades",
            "subcategory":"Landscaping Services",
            "type":"Services"
        }
    ],
    "sg:phone":"+1 972 242 2777",
    "sg:postcode":"75022",
    "sg:province":"TX",
    "sg:tags":[
        "designer",
        "landscape"
    ],
    "wof:name":"Landscape Development Svc",
    "wof:placetype":"venue"
},
  "geometry": {"coordinates":[-97.079494,33.035589],"type":"Point"}
}