{
  "type": "Feature",
  "properties": {
    "iso:country":"US",
    "sg:address":"5923 Gaston Ave",
    "sg:city":"Dallas",
    "sg:classifiers":[
        {
            "category":"Real Estate",
            "subcategory":"Real Estate Operator",
            "type":"Services"
        }
    ],
    "sg:phone":"+1 214 550 0001",
    "sg:postcode":"75214",
    "sg:province":"TX",
    "sg:tags":[
        "apartment"
    ],
    "sg:website":"www.powerproperties.com",
    "wof:name":"Power Properties Condiminium Sales",
    "wof:placetype":"venue"
},
  "geometry": {"coordinates":[-96.75763499999999,32.810004],"type":"Point"}
}