{
  "type": "Feature",
  "properties": {
    "iso:country":"US",
    "sg:address":"4829 W Lawther Dr",
    "sg:city":"Dallas",
    "sg:classifiers":[
        {
            "category":"Health Services",
            "subcategory":"Clinic",
            "type":"Services"
        }
    ],
    "sg:phone":"+1 214 381 4180",
    "sg:postcode":"75214",
    "sg:province":"TX",
    "sg:tags":[
        "specialty",
        "outpatient"
    ],
    "wof:name":"Rehab Care Group",
    "wof:placetype":"venue"
},
  "geometry": {"coordinates":[-96.729303,32.852209],"type":"Point"}
}