{
  "type": "Feature",
  "properties": {
    "iso:country":"US",
    "sg:address":"1709 Overbrook Ct",
    "sg:city":"Arlington",
    "sg:classifiers":[
        {
            "category":"Building & Trades",
            "subcategory":"Landscaping Services",
            "type":"Services"
        }
    ],
    "sg:phone":"+1 817 468 1635",
    "sg:postcode":"76014",
    "sg:province":"TX",
    "wof:name":"True Lawn-Care & Landscaping",
    "wof:placetype":"venue"
},
  "geometry": {"coordinates":[-97.084665,32.69666],"type":"Point"}
}