{
  "type": "Feature",
  "properties": {
    "iso:country":"US",
    "sg:address":"1300 E Calton Rd",
    "sg:city":"Laredo",
    "sg:classifiers":[
        {
            "category":"Manufacturing",
            "subcategory":"Retail Goods",
            "type":"Manufacturing & Wholesale Goods"
        }
    ],
    "sg:phone":"+1 956 726 4162",
    "sg:postcode":"78041",
    "sg:province":"TX",
    "sg:tags":[
        "product",
        "mfg"
    ],
    "wof:name":"Alma G Marquez",
    "wof:placetype":"venue"
},
  "geometry": {"coordinates":[-99.48038,27.540965],"type":"Point"}
}