{
  "type": "Feature",
  "properties": {
    "iso:country":"US",
    "sg:address":"1410 W California St",
    "sg:city":"Gainesville",
    "sg:classifiers":[
        {
            "category":"Building & Trades",
            "subcategory":"Plumbing",
            "type":"Services"
        }
    ],
    "sg:phone":"+1 940 668 7642",
    "sg:postcode":"76240",
    "sg:province":"TX",
    "sg:tags":[
        "contractor"
    ],
    "wof:name":"Whites Plumbing Inc",
    "wof:placetype":"venue"
},
  "geometry": {"coordinates":[-97.15373700000001,33.62431],"type":"Point"}
}