{
  "type": "Feature",
  "properties": {
    "iso:country":"US",
    "sg:address":"12629 Thistle Down",
    "sg:city":"San Antonio",
    "sg:classifiers":[
        {
            "category":"Retail",
            "subcategory":"Portrait Studio",
            "type":"Services"
        }
    ],
    "sg:phone":"+1 210 599 6855",
    "sg:postcode":"78217",
    "sg:province":"TX",
    "sg:tags":[
        "photo"
    ],
    "wof:name":"Willis Photography",
    "wof:placetype":"venue"
},
  "geometry": {"coordinates":[-98.408434,29.554449],"type":"Point"}
}