{
  "type": "Feature",
  "properties": {
    "iso:country":"US",
    "sg:address":"109 Bebe Ln",
    "sg:city":"Wichita Falls",
    "sg:classifiers":[
        {
            "category":"Organizations",
            "subcategory":"Religious Organization",
            "type":"Services"
        }
    ],
    "sg:phone":"+1 940 767 0096",
    "sg:postcode":"76301",
    "sg:province":"TX",
    "wof:name":"Josephus Ministries",
    "wof:placetype":"venue"
},
  "geometry": {"coordinates":[-98.448933,33.912256],"type":"Point"}
}