{
  "type": "Feature",
  "properties": {
    "iso:country":"US",
    "sg:address":"2401 S Stemmons Fwy",
    "sg:city":"Lewisville",
    "sg:classifiers":[
        {
            "category":"Shopping",
            "type":"Retail Goods"
        }
    ],
    "sg:phone":"+1 972 459 4700",
    "sg:postcode":"75067",
    "sg:province":"TX",
    "sg:tags":[
        "cosmetic",
        "perfume"
    ],
    "wof:name":"Aveda Environmental Lifestyle",
    "wof:placetype":"venue"
},
  "geometry": {"coordinates":[-96.97184799999999,33.006144],"type":"Point"}
}