{
  "type": "Feature",
  "properties": {
    "iso:country":"US",
    "sg:address":"2200 Denton Dr",
    "sg:city":"Austin",
    "sg:classifiers":[
        {
            "category":"Home & Garden",
            "subcategory":"Furniture",
            "type":"Retail Goods"
        }
    ],
    "sg:phone":"+1 512 453 7378",
    "sg:postcode":"78758",
    "sg:province":"TX",
    "wof:name":"Gage Furniture Company",
    "wof:placetype":"venue"
},
  "geometry": {"coordinates":[-97.715232,30.386316],"type":"Point"}
}