{
  "type": "Feature",
  "properties": {
    "iso:country":"US",
    "sg:address":"1720 Sunset Blvd",
    "sg:city":"Houston",
    "sg:classifiers":[
        {
            "category":"Health Services",
            "subcategory":"Clinic",
            "type":"Services"
        }
    ],
    "sg:phone":"+1 713 521 2772",
    "sg:postcode":"77005",
    "sg:province":"TX",
    "sg:tags":[
        "counseling",
        "mental"
    ],
    "wof:name":"Maria Ramos, LCSW",
    "wof:placetype":"venue"
},
  "geometry": {"coordinates":[-95.402322,29.723062],"type":"Point"}
}