{
  "type": "Feature",
  "properties": {
    "iso:country":"US",
    "sg:address":"1916 Bench Mark Dr",
    "sg:city":"Austin",
    "sg:classifiers":[
        {
            "category":"Autos & Motor Vehicles",
            "subcategory":"Automobile Sales",
            "type":"Retail Goods"
        },
        {
            "category":"Retail",
            "subcategory":"Auto Repair",
            "type":"Services"
        }
    ],
    "sg:phone":"+1 512 251 4107",
    "sg:postcode":"78728",
    "sg:province":"TX",
    "sg:tags":[
        "car",
        "used",
        "general",
        "dealer",
        "supply"
    ],
    "sg:website":"www.vol-tech.com",
    "wof:name":"Austin Vol-Tech Services Inc",
    "wof:placetype":"venue"
},
  "geometry": {"coordinates":[-97.682052,30.432819],"type":"Point"}
}