{
  "type": "Feature",
  "properties": {
    "iso:country":"US",
    "sg:address":"418 E Luhn St",
    "sg:city":"Bellville",
    "sg:classifiers":[
        {
            "category":"Professional",
            "subcategory":"Accounting & Tax Preparation",
            "type":"Services"
        }
    ],
    "sg:phone":"+1 979 865 9328",
    "sg:postcode":"77418",
    "sg:province":"TX",
    "sg:tags":[
        "auditing",
        "bookkeeping"
    ],
    "wof:name":"Heflin Tax Service",
    "wof:placetype":"venue"
},
  "geometry": {"coordinates":[-96.25468600000001,29.948143],"type":"Point"}
}