{
  "type": "Feature",
  "properties": {
    "iso:country":"US",
    "sg:address":"1912 W Anderson Ln",
    "sg:city":"Austin",
    "sg:classifiers":[
        {
            "category":"Insurance",
            "subcategory":"Insurance Agent",
            "type":"Services"
        }
    ],
    "sg:phone":"+1 512 451 8878",
    "sg:postcode":"78757",
    "sg:province":"TX",
    "wof:name":"Richard Garrett Insurance",
    "wof:placetype":"venue"
},
  "geometry": {"coordinates":[-97.72997100000001,30.355721],"type":"Point"}
}