{
  "type": "Feature",
  "properties": {
    "iso:country":"US",
    "sg:address":"4218 W Oak St",
    "sg:city":"Palestine",
    "sg:classifiers":[
        {
            "category":"Restaurant",
            "type":"Food & Drink"
        }
    ],
    "sg:phone":"+1 903 723 9594",
    "sg:postcode":"75801",
    "sg:province":"TX",
    "sg:tags":[
        "caterer"
    ],
    "wof:name":"Custom Catering Corp",
    "wof:placetype":"venue"
},
  "geometry": {"coordinates":[-95.673911,31.732119],"type":"Point"}
}