{
  "type": "Feature",
  "properties": {
    "iso:country":"US",
    "sg:address":"6001 Silverleaf Ln",
    "sg:city":"Garland",
    "sg:classifiers":[
        {
            "category":"Banks & Credit Unions",
            "subcategory":"Financial Services",
            "type":"Services"
        }
    ],
    "sg:phone":"+1 972 203 1495",
    "sg:postcode":"75043",
    "sg:province":"TX",
    "sg:tags":[
        "investor"
    ],
    "wof:name":"Hc/JC Investments LLC",
    "wof:placetype":"venue"
},
  "geometry": {"coordinates":[-96.57133899999999,32.843142],"type":"Point"}
}