{
  "type": "Feature",
  "properties": {
    "iso:country":"US",
    "sg:address":"420 State Hwy 110",
    "sg:city":"Whitehouse",
    "sg:classifiers":[
        {
            "category":"Autos & Motor Vehicles",
            "subcategory":"Auto Supplies",
            "type":"Retail Goods"
        }
    ],
    "sg:phone":"+1 903 839 8550",
    "sg:postcode":"75791",
    "sg:province":"TX",
    "sg:tags":[
        "automobile",
        "parts"
    ],
    "wof:name":"NAPA Auto Parts",
    "wof:placetype":"venue"
},
  "geometry": {"coordinates":[-95.225369,32.221761],"type":"Point"}
}