{
  "type": "Feature",
  "properties": {
    "iso:country":"US",
    "sg:address":"17702 Oaksham Ln",
    "sg:city":"Spring",
    "sg:classifiers":[
        {
            "category":"Professional",
            "subcategory":"Engineering",
            "type":"Services"
        }
    ],
    "sg:phone":"+1 281 370 1882",
    "sg:postcode":"77379",
    "sg:province":"TX",
    "wof:name":"Ledikos Inc",
    "wof:placetype":"venue"
},
  "geometry": {"coordinates":[-95.496015,30.022914],"type":"Point"}
}