{
  "type": "Feature",
  "properties": {
    "iso:country":"US",
    "sg:address":"7454 Kent St",
    "sg:city":"Shallowater",
    "sg:classifiers":[
        {
            "category":"Professional",
            "type":"Services"
        }
    ],
    "sg:phone":"+1 806 832 4889",
    "sg:postcode":"79363",
    "sg:province":"TX",
    "wof:name":"Henderson Joya",
    "wof:placetype":"venue"
},
  "geometry": {"coordinates":[-101.979007,33.635898],"type":"Point"}
}