{
  "type": "Feature",
  "properties": {
    "iso:country":"US",
    "sg:address":"601 S San Patricio St",
    "sg:city":"Goliad",
    "sg:classifiers":[
        {
            "category":"Professional",
            "type":"Services"
        }
    ],
    "sg:phone":"+1 361 645 2216",
    "sg:postcode":"77963",
    "sg:province":"TX",
    "sg:tags":[
        "establishment"
    ],
    "wof:name":"Hanover Co",
    "wof:placetype":"venue"
},
  "geometry": {"coordinates":[-97.39789399999999,28.663295],"type":"Point"}
}