{
  "type": "Feature",
  "properties": {
    "iso:country":"US",
    "sg:address":"4405 Avenue A",
    "sg:city":"Austin",
    "sg:classifiers":[
        {
            "category":"Shopping",
            "subcategory":"Jewelry",
            "type":"Retail Goods"
        }
    ],
    "sg:phone":"+1 646 299 3047",
    "sg:postcode":"78751",
    "sg:province":"TX",
    "sg:website":"www.etsy.com/shop.php?user_id=52...",
    "wof:name":"Laura Caslin Handmade Jewelry",
    "wof:placetype":"venue"
},
  "geometry": {"coordinates":[-97.73269999999999,30.309351],"type":"Point"}
}