{
  "type": "Feature",
  "properties": {
    "iso:country":"US",
    "sg:address":"401 State Hwy 21",
    "sg:city":"Caldwell",
    "sg:classifiers":[
        {
            "category":"Travel",
            "subcategory":"Hotels & Motels",
            "type":"Entertainment"
        }
    ],
    "sg:phone":"+1 979 567 3221",
    "sg:postcode":"77836",
    "sg:province":"TX",
    "sg:tags":[
        "operation"
    ],
    "wof:name":"Surrey Inn",
    "wof:placetype":"venue"
},
  "geometry": {"coordinates":[-96.698668,30.533184],"type":"Point"}
}