{
  "type": "Feature",
  "properties": {
    "iso:country":"US",
    "sg:address":"7315 Towerview Ln",
    "sg:city":"Missouri City",
    "sg:classifiers":[
        {
            "category":"Organizations",
            "subcategory":"Religious Organization",
            "type":"Services"
        }
    ],
    "sg:phone":"+1 281 416 2190",
    "sg:postcode":"77489",
    "sg:province":"TX",
    "wof:name":"Bethel Home Care",
    "wof:placetype":"venue"
},
  "geometry": {"coordinates":[-95.496106,29.601287],"type":"Point"}
}