{
  "type": "Feature",
  "properties": {
    "iso:country":"US",
    "sg:address":"617 S 27th St",
    "sg:city":"Mcallen",
    "sg:classifiers":[
        {
            "category":"Recreation",
            "type":"Entertainment"
        }
    ],
    "sg:phone":"+1 956 688 3458",
    "sg:postcode":"78501",
    "sg:province":"TX",
    "sg:tags":[
        "pool",
        "swimming"
    ],
    "wof:name":"Boys Club Municipal Pool",
    "wof:placetype":"venue"
},
  "geometry": {"coordinates":[-98.252424,26.200719],"type":"Point"}
}