{
  "type": "Feature",
  "properties": {
    "iso:country":"US",
    "sg:address":"3825 W Cardinal Dr",
    "sg:city":"Beaumont",
    "sg:classifiers":[
        {
            "category":"Transit Center",
            "subcategory":"Freight",
            "type":"Transportation"
        },
        {
            "category":"Freight",
            "type":"Transportation"
        }
    ],
    "sg:phone":"+1 409 842 0509",
    "sg:postcode":"77705",
    "sg:province":"TX",
    "sg:tags":[
        "trucking",
        "trucking-heavy",
        "hauling",
        "trucking-motor"
    ],
    "wof:name":"Wolfe, Harold",
    "wof:placetype":"venue"
},
  "geometry": {"coordinates":[-94.133415,30.042541],"type":"Point"}
}