{
  "type": "Feature",
  "properties": {
    "iso:country":"US",
    "sg:address":"2005 Mason Street",
    "sg:city":"Houston",
    "sg:classifiers":[
        {
            "category":"Professional",
            "subcategory":"Art Services",
            "type":"Services"
        }
    ],
    "sg:phone":"+1 713 521 1550",
    "sg:postcode":"77006",
    "sg:province":"TX",
    "sg:tags":[
        "photographer"
    ],
    "sg:website":"www.djonesphoto.com",
    "wof:name":"D Jones Photography",
    "wof:placetype":"venue"
},
  "geometry": {"coordinates":[-95.384694,29.750708],"type":"Point"}
}