{
  "type": "Feature",
  "properties": {
    "iso:country":"US",
    "sg:address":"1205 Rio Grande St",
    "sg:city":"Austin",
    "sg:classifiers":[
        {
            "category":"Professional",
            "subcategory":"Lawyer & Legal Services",
            "type":"Services"
        }
    ],
    "sg:phone":"+1 512 476 4473",
    "sg:postcode":"78701",
    "sg:province":"TX",
    "sg:tags":[
        "attorney"
    ],
    "sg:website":"www.mbfc.com",
    "wof:name":"Minton Burton Foster & Collins",
    "wof:placetype":"venue"
},
  "geometry": {"coordinates":[-97.746942,30.276659],"type":"Point"}
}