{
  "type": "Feature",
  "properties": {
    "iso:country":"US",
    "sg:address":"113 Neely Rd",
    "sg:city":"Hewitt",
    "sg:classifiers":[
        {
            "category":"Professional",
            "subcategory":"Management & Consulting",
            "type":"Services"
        }
    ],
    "sg:phone":"+1 254 666 3660",
    "sg:postcode":"76643",
    "sg:province":"TX",
    "sg:tags":[
        "consultant",
        "educational"
    ],
    "wof:name":"A & J Enterprise",
    "wof:placetype":"venue"
},
  "geometry": {"coordinates":[-97.191378,31.455904],"type":"Point"}
}