{
  "type": "Feature",
  "properties": {
    "iso:country":"US",
    "sg:address":"4120 Julie Dr",
    "sg:city":"Amarillo",
    "sg:classifiers":[
        {
            "category":"Retail",
            "subcategory":"Repair Shop",
            "type":"Services"
        }
    ],
    "sg:phone":"+1 806 359 8963",
    "sg:postcode":"79109",
    "sg:province":"TX",
    "wof:name":"Jdw Sales",
    "wof:placetype":"venue"
},
  "geometry": {"coordinates":[-101.876952,35.164882],"type":"Point"}
}