{
  "type": "Feature",
  "properties": {
    "iso:country":"US",
    "sg:address":"11628 Rogue Way",
    "sg:city":"Dallas",
    "sg:classifiers":[
        {
            "category":"Professional",
            "subcategory":"Computer Services",
            "type":"Services"
        }
    ],
    "sg:phone":"+1 214 327 0430",
    "sg:postcode":"75218",
    "sg:province":"TX",
    "sg:tags":[
        "related"
    ],
    "wof:name":"Foresight Computer Systems",
    "wof:placetype":"venue"
},
  "geometry": {"coordinates":[-96.694457,32.854099],"type":"Point"}
}