{
  "type": "Feature",
  "properties": {
    "iso:country":"US",
    "sg:address":"7670 Woodway Dr Ste 344",
    "sg:city":"Houston",
    "sg:classifiers":[
        {
            "category":"Building & Trades",
            "subcategory":"Construction",
            "type":"Services"
        }
    ],
    "sg:phone":"+1 713 266 6500",
    "sg:postcode":"77063",
    "sg:province":"TX",
    "sg:tags":[
        "contractor"
    ],
    "wof:name":"Memorial Builders Inc",
    "wof:placetype":"venue"
},
  "geometry": {"coordinates":[-95.50309799999999,29.7512],"type":"Point"}
}