{
  "type": "Feature",
  "properties": {
    "iso:country":"US",
    "sg:address":"5917 66th St",
    "sg:city":"Lubbock",
    "sg:classifiers":[
        {
            "category":"Organizations",
            "subcategory":"Religious Organization",
            "type":"Services"
        }
    ],
    "sg:phone":"+1 806 794 6655",
    "sg:postcode":"79424",
    "sg:province":"TX",
    "wof:name":"Christian Life Assembly Of God",
    "wof:placetype":"venue"
},
  "geometry": {"coordinates":[-101.943023,33.534165],"type":"Point"}
}