{
  "type": "Feature",
  "properties": {
    "iso:country":"US",
    "sg:address":"800 W Panola St",
    "sg:city":"Carthage",
    "sg:classifiers":[
        {
            "category":"Autos & Motor Vehicles",
            "subcategory":"Auto Supplies",
            "type":"Retail Goods"
        },
        {
            "category":"Wholesale",
            "subcategory":"Electrical",
            "type":"Manufacturing & Wholesale Goods"
        }
    ],
    "sg:phone":"+1 903 693 3226",
    "sg:postcode":"75633",
    "sg:province":"TX",
    "sg:tags":[
        "battery",
        "automobile",
        "part",
        "batteries-storage",
        "accessory"
    ],
    "sg:website":"http://www.autozone.com",
    "wof:name":"AutoZone",
    "wof:placetype":"venue"
},
  "geometry": {"coordinates":[-94.35127300000001,32.157749],"type":"Point"}
}