{
  "type": "Feature",
  "properties": {
    "iso:country":"US",
    "sg:address":"7098 Whispering Wind Dr",
    "sg:city":"Willis",
    "sg:classifiers":[
        {
            "category":"Building & Trades",
            "subcategory":"Construction",
            "type":"Services"
        }
    ],
    "sg:phone":"+1 936 890 1771",
    "sg:postcode":"77318",
    "sg:province":"TX",
    "sg:tags":[
        "house"
    ],
    "wof:name":"Eaton Construction",
    "wof:placetype":"venue"
},
  "geometry": {"coordinates":[-95.570127,30.408049],"type":"Point"}
}