{
  "type": "Feature",
  "properties": {
    "iso:country":"US",
    "sg:address":"65 Towering Pines Dr",
    "sg:city":"Spring",
    "sg:classifiers":[
        {
            "category":"Professional",
            "type":"Services"
        }
    ],
    "sg:phone":"+1 713 817 2537",
    "sg:postcode":"77381",
    "sg:province":"TX",
    "wof:name":"Camexco Inc",
    "wof:placetype":"venue"
},
  "geometry": {"coordinates":[-95.494277,30.173832],"type":"Point"}
}