{
  "type": "Feature",
  "properties": {
    "iso:country":"US",
    "sg:address":"10418 McCormick Ln",
    "sg:city":"El Paso",
    "sg:classifiers":[
        {
            "category":"Health Services",
            "subcategory":"Clinic",
            "type":"Services"
        }
    ],
    "sg:phone":"+1 915 822 9622",
    "sg:postcode":"79924",
    "sg:province":"TX",
    "wof:name":"Body Sugaring Of El Paso",
    "wof:placetype":"venue"
},
  "geometry": {"coordinates":[-106.420064,31.917298],"type":"Point"}
}