{
  "type": "Feature",
  "properties": {
    "iso:country":"US",
    "sg:address":"5103 S Braeswood Blvd",
    "sg:city":"Houston",
    "sg:classifiers":[
        {
            "category":"Food & Beverages",
            "subcategory":"Bakery",
            "type":"Retail Goods"
        }
    ],
    "sg:phone":"+1 713 729 7543",
    "sg:postcode":"77096",
    "sg:province":"TX",
    "wof:name":"Wish Bakery",
    "wof:placetype":"venue"
},
  "geometry": {"coordinates":[-95.467343,29.67816],"type":"Point"}
}