{
  "type": "Feature",
  "properties": {
    "iso:country":"US",
    "sg:address":"201 N Bugle Dr",
    "sg:city":"Fort Worth",
    "sg:classifiers":[
        {
            "category":"Retail",
            "subcategory":"Laundry & Dry Cleaning",
            "type":"Services"
        }
    ],
    "sg:phone":"+1 817 367 0235",
    "sg:postcode":"76108",
    "sg:province":"TX",
    "wof:name":"Westpoint Carpet Cleaning",
    "wof:placetype":"venue"
},
  "geometry": {"coordinates":[-97.497304,32.760816],"type":"Point"}
}