{
  "type": "Feature",
  "properties": {
    "iso:country":"US",
    "sg:address":"800 E William Cannon Drive",
    "sg:city":"Austin",
    "sg:classifiers":[
        {
            "category":"Food & Beverages",
            "subcategory":"Groceries & Convenience Stores",
            "type":"Retail Goods"
        }
    ],
    "sg:phone":"+1 512 441 2829",
    "sg:postcode":"78745",
    "sg:province":"TX",
    "wof:name":"Express Food Mart #8",
    "wof:placetype":"venue"
},
  "geometry": {"coordinates":[-97.77187499999999,30.190971],"type":"Point"}
}