{
  "type": "Feature",
  "properties": {
    "iso:country":"US",
    "sg:address":"3218 E Belknap St",
    "sg:city":"Fort Worth",
    "sg:classifiers":[
        {
            "category":"Social Services",
            "type":"Services"
        }
    ],
    "sg:phone":"+1 817 834 4711",
    "sg:postcode":"76111",
    "sg:province":"TX",
    "sg:tags":[
        "youth",
        "organization",
        "center"
    ],
    "sg:website":"www.fortworthkids.org",
    "wof:name":"Boys & Girls Clubs-Fort Worth",
    "wof:placetype":"venue"
},
  "geometry": {"coordinates":[-97.300669,32.773673],"type":"Point"}
}