{
  "type": "Feature",
  "properties": {
    "iso:country":"US",
    "sg:address":"2991 State Highway 67",
    "sg:city":"Graham",
    "sg:classifiers":[
        {
            "category":"Professional",
            "type":"Services"
        },
        {
            "category":"Food & Beverages",
            "subcategory":"Farmers Market",
            "type":"Retail Goods"
        }
    ],
    "sg:phone":"+1 940 549 4060",
    "sg:postcode":"76450",
    "sg:province":"TX",
    "sg:tags":[
        "operator",
        "field",
        "oil"
    ],
    "wof:name":"Street S B & Co",
    "wof:placetype":"venue"
},
  "geometry": {"coordinates":[-98.649688,33.021249],"type":"Point"}
}