{
  "type": "Feature",
  "properties": {
    "iso:country":"US",
    "sg:address":"2320 FM 2004",
    "sg:city":"Texas City",
    "sg:classifiers":[
        {
            "category":"Travel",
            "subcategory":"Hotels & Motels",
            "type":"Entertainment"
        }
    ],
    "sg:phone":"+1 409 986 6686",
    "sg:postcode":"77591",
    "sg:province":"TX",
    "sg:tags":[
        "operation"
    ],
    "wof:name":"Hampton Inn",
    "wof:placetype":"venue"
},
  "geometry": {"coordinates":[-95.03111699999999,29.407923],"type":"Point"}
}