{
  "type": "Feature",
  "properties": {
    "iso:country":"US",
    "sg:address":"911 S Palestine St",
    "sg:city":"Athens",
    "sg:classifiers":[
        {
            "category":"Personal",
            "subcategory":"Beauty Salon",
            "type":"Services"
        }
    ],
    "sg:phone":"+1 903 677 1411",
    "sg:postcode":"75751",
    "sg:province":"TX",
    "sg:tags":[
        "shop",
        "salons-equipment",
        "supply"
    ],
    "wof:name":"Bel Lajo Beauty Salon & Beauty",
    "wof:placetype":"venue"
},
  "geometry": {"coordinates":[-95.85122200000001,32.187623],"type":"Point"}
}