{
  "type": "Feature",
  "properties": {
    "iso:country":"US",
    "sg:address":"301 Modene St",
    "sg:city":"Seagoville",
    "sg:classifiers":[
        {
            "category":"Shopping",
            "subcategory":"Catalog Store",
            "type":"Retail Goods"
        }
    ],
    "sg:phone":"+1 972 287 3828",
    "sg:postcode":"75159",
    "sg:province":"TX",
    "sg:tags":[
        "mail",
        "house"
    ],
    "wof:name":"Exceptional Home Accents",
    "wof:placetype":"venue"
},
  "geometry": {"coordinates":[-96.57098499999999,32.666083],"type":"Point"}
}