{
  "type": "Feature",
  "properties": {
    "iso:country":"US",
    "sg:address":"833 Adel Dr",
    "sg:city":"Corpus Christi",
    "sg:classifiers":[
        {
            "category":"Organizations",
            "subcategory":"Non-profit Organization",
            "type":"Services"
        }
    ],
    "sg:phone":"+1 361 985 0705",
    "sg:postcode":"78412",
    "sg:province":"TX",
    "sg:tags":[
        "breastfeeding",
        "information",
        "supply"
    ],
    "wof:name":"LA Leche League",
    "wof:placetype":"venue"
},
  "geometry": {"coordinates":[-97.35543699999999,27.71461],"type":"Point"}
}