{
  "type": "Feature",
  "properties": {
    "iso:country":"US",
    "sg:address":"116 Fagan Ln",
    "sg:city":"Texarkana",
    "sg:classifiers":[
        {
            "category":"Organizations",
            "subcategory":"Religious Organization",
            "type":"Services"
        }
    ],
    "sg:phone":"+1 903 671 2915",
    "sg:postcode":"75573",
    "sg:province":"TX",
    "sg:tags":[
        "clergy"
    ],
    "wof:name":"Alvester Hardiman",
    "wof:placetype":"venue"
},
  "geometry": {"coordinates":[-94.24448599999999,33.365387],"type":"Point"}
}