{
  "type": "Feature",
  "properties": {
    "iso:country":"US",
    "sg:address":"6130 Deep South Dr",
    "sg:city":"Katy",
    "sg:classifiers":[
        {
            "category":"Shopping",
            "subcategory":"Crafts & Fabrics",
            "type":"Retail Goods"
        },
        {
            "category":"Professional",
            "subcategory":"Art Services",
            "type":"Services"
        }
    ],
    "sg:phone":"+1 281 813 7251",
    "sg:postcode":"77449",
    "sg:province":"TX",
    "sg:tags":[
        "picture",
        "frame"
    ],
    "wof:name":"Studio 6 Custom Framong",
    "wof:placetype":"venue"
},
  "geometry": {"coordinates":[-95.70071,29.862482],"type":"Point"}
}