{
  "type": "Feature",
  "properties": {
    "iso:country":"US",
    "sg:address":"650 Morelock Ln",
    "sg:city":"Brownwood",
    "sg:classifiers":[
        {
            "category":"Travel",
            "subcategory":"Hotels & Motels",
            "type":"Entertainment"
        }
    ],
    "sg:phone":"+1 325 646 4128",
    "sg:postcode":"76801",
    "sg:province":"TX",
    "sg:tags":[
        "breakfast",
        "accommodation",
        "bed"
    ],
    "wof:name":"Star Of Texas Bed & Breakfast",
    "wof:placetype":"venue"
},
  "geometry": {"coordinates":[-99.007186,31.797443],"type":"Point"}
}