{
  "type": "Feature",
  "properties": {
    "iso:country":"US",
    "sg:address":"1710 Kingwood Dr",
    "sg:city":"Kingwood",
    "sg:classifiers":[
        {
            "category":"Restaurant",
            "type":"Food & Drink"
        }
    ],
    "sg:menulink":"http://www.allmenus.com/tx/houston/193496-taco-bell/menu/",
    "sg:postcode":"77339",
    "sg:province":"TX",
    "sg:tags":[
        "mexican"
    ],
    "wof:name":"Taco Bell",
    "wof:placetype":"venue"
},
  "geometry": {"coordinates":[-95.230701,30.049639],"type":"Point"}
}