{
  "type": "Feature",
  "properties": {
    "iso:country":"US",
    "sg:address":"5342 Circle K Ranch",
    "sg:city":"Kaufman",
    "sg:classifiers":[
        {
            "category":"Farming",
            "subcategory":"Livestock Farm",
            "type":"Manufacturing & Wholesale Goods"
        }
    ],
    "sg:phone":"+1 972 932 7999",
    "sg:postcode":"75142",
    "sg:province":"TX",
    "sg:tags":[
        "ranch"
    ],
    "wof:name":"Circle K Ranch",
    "wof:placetype":"venue"
},
  "geometry": {"coordinates":[-96.146807,32.569157],"type":"Point"}
}