{
  "type": "Feature",
  "properties": {
    "iso:country":"US",
    "sg:address":"3950 Bluebonnet Blvd",
    "sg:city":"Brenham",
    "sg:classifiers":[
        {
            "category":"Real Estate",
            "subcategory":"Developer",
            "type":"Services"
        }
    ],
    "sg:phone":"+1 979 421 7000",
    "sg:postcode":"77833",
    "sg:province":"TX",
    "wof:name":"Country Communities Inc",
    "wof:placetype":"venue"
},
  "geometry": {"coordinates":[-96.299047,30.140943],"type":"Point"}
}