{
  "type": "Feature",
  "properties": {
    "iso:country":"US",
    "sg:address":"212 E Laas St",
    "sg:city":"Weimar",
    "sg:classifiers":[
        {
            "category":"Retail",
            "subcategory":"Veterinary Services",
            "type":"Services"
        }
    ],
    "sg:phone":"+1 979 725 8214",
    "sg:postcode":"78962",
    "sg:province":"TX",
    "wof:name":"Weimar Veterinary Clinic",
    "wof:placetype":"venue"
},
  "geometry": {"coordinates":[-96.777018,29.709078],"type":"Point"}
}