{
  "type": "Feature",
  "properties": {
    "iso:country":"US",
    "sg:address":"811 E Parkerville Rd",
    "sg:city":"De Soto",
    "sg:classifiers":[
        {
            "category":"Organizations",
            "subcategory":"Professional Association",
            "type":"Services"
        }
    ],
    "sg:phone":"+1 972 223 3671",
    "sg:postcode":"75115",
    "sg:province":"TX",
    "sg:tags":[
        "business"
    ],
    "wof:name":"T Wing Construction Inc",
    "wof:placetype":"venue"
},
  "geometry": {"coordinates":[-96.835588,32.575203],"type":"Point"}
}