{
  "type": "Feature",
  "properties": {
    "iso:country":"US",
    "sg:address":"615 S Belt Line Rd",
    "sg:city":"Irving",
    "sg:classifiers":[
        {
            "category":"Food & Beverages",
            "subcategory":"Bakery",
            "type":"Retail Goods"
        }
    ],
    "sg:phone":"+1 972 513 2299",
    "sg:postcode":"75060",
    "sg:province":"TX",
    "wof:name":"Beltline Donuts",
    "wof:placetype":"venue"
},
  "geometry": {"coordinates":[-96.99421100000001,32.808993],"type":"Point"}
}