{
  "type": "Feature",
  "properties": {
    "iso:country":"US",
    "sg:address":"3905 N Medford Dr",
    "sg:city":"Lufkin",
    "sg:classifiers":[
        {
            "category":"Home & Garden",
            "subcategory":"Mobile Homes",
            "type":"Retail Goods"
        }
    ],
    "sg:phone":"+1 936 639 6432",
    "sg:postcode":"75901",
    "sg:province":"TX",
    "wof:name":"Nationwide Manufactured Homes",
    "wof:placetype":"venue"
},
  "geometry": {"coordinates":[-94.70464,31.366248],"type":"Point"}
}