{
  "type": "Feature",
  "properties": {
    "iso:country":"US",
    "sg:address":"1300 E Arapaho Rd",
    "sg:city":"Richardson",
    "sg:classifiers":[
        {
            "category":"Shopping",
            "subcategory":"Computers & Home Electronics",
            "type":"Retail Goods"
        }
    ],
    "sg:phone":"+1 214 575 6900",
    "sg:postcode":"75081",
    "sg:province":"TX",
    "sg:tags":[
        "equipment"
    ],
    "wof:name":"Allied Integrated Services",
    "wof:placetype":"venue"
},
  "geometry": {"coordinates":[-96.701776,32.960583],"type":"Point"}
}