{
  "type": "Feature",
  "properties": {
    "iso:country":"US",
    "sg:address":"1309 W Pipeline Rd",
    "sg:city":"Hurst",
    "sg:classifiers":[
        {
            "category":"Shopping",
            "subcategory":"Computers & Home Electronics",
            "type":"Retail Goods"
        }
    ],
    "sg:phone":"+1 817 589 2221",
    "sg:postcode":"76053",
    "sg:province":"TX",
    "sg:tags":[
        "equipment",
        "electronic",
        "supply"
    ],
    "sg:website":"www.ultimatelectronics.com",
    "wof:name":"Ultimate Electronics",
    "wof:placetype":"venue"
},
  "geometry": {"coordinates":[-97.202844,32.82357],"type":"Point"}
}