{
  "type": "Feature",
  "properties": {
    "iso:country":"US",
    "sg:address":"1301 6th St",
    "sg:city":"Rosenberg",
    "sg:classifiers":[
        {
            "category":"Organizations",
            "subcategory":"Religious Organization",
            "type":"Services"
        }
    ],
    "sg:phone":"+1 281 239 2292",
    "sg:postcode":"77471",
    "sg:province":"TX",
    "wof:name":"Tower of Refuge",
    "wof:placetype":"venue"
},
  "geometry": {"coordinates":[-95.80340700000001,29.554872],"type":"Point"}
}