{
  "type": "Feature",
  "properties": {
    "iso:country":"US",
    "sg:address":"8541 W Bellfort St",
    "sg:city":"Houston",
    "sg:classifiers":[
        {
            "category":"Personal",
            "subcategory":"Beauty Salon",
            "type":"Services"
        }
    ],
    "sg:phone":"+1 713 773 9616",
    "sg:postcode":"77071",
    "sg:province":"TX",
    "sg:tags":[
        "shop",
        "manicuring"
    ],
    "wof:name":"J K Nails",
    "wof:placetype":"venue"
},
  "geometry": {"coordinates":[-95.51390499999999,29.65578],"type":"Point"}
}