{
  "type": "Feature",
  "properties": {
    "iso:country":"US",
    "sg:address":"101 N Highway 67",
    "sg:city":"Cedar Hill",
    "sg:classifiers":[
        {
            "category":"Building & Trades",
            "subcategory":"Locksmith",
            "type":"Services"
        }
    ],
    "sg:phone":"+1 972 293 3553",
    "sg:postcode":"75104",
    "sg:province":"TX",
    "sg:tags":[
        "key"
    ],
    "wof:name":"L O C K S By Le Duff",
    "wof:placetype":"venue"
},
  "geometry": {"coordinates":[-96.947031,32.590021],"type":"Point"}
}