{
  "type": "Feature",
  "properties": {
    "iso:country":"US",
    "sg:address":"610 State Hwy 323",
    "sg:city":"Tyler",
    "sg:classifiers":[
        {
            "category":"Home & Garden",
            "subcategory":"Furniture",
            "type":"Retail Goods"
        }
    ],
    "sg:phone":"+1 903 534 0521",
    "sg:postcode":"75701",
    "sg:province":"TX",
    "wof:name":"Bedroom Expressions",
    "wof:placetype":"venue"
},
  "geometry": {"coordinates":[-95.308711,32.303306],"type":"Point"}
}