{
  "type": "Feature",
  "properties": {
    "iso:country":"US",
    "sg:address":"15014 Redbud Leaf Ln",
    "sg:city":"Cypress",
    "sg:classifiers":[
        {
            "category":"Shopping",
            "subcategory":"Hobbies, Toys, & Games",
            "type":"Retail Goods"
        }
    ],
    "sg:phone":"+1 281 373 0210",
    "sg:postcode":"77433",
    "sg:province":"TX",
    "wof:name":"Bad Boys Diesel Toys",
    "wof:placetype":"venue"
},
  "geometry": {"coordinates":[-95.74558,29.99476],"type":"Point"}
}