{
  "type": "Feature",
  "properties": {
    "iso:country":"US",
    "sg:address":"5005 N State Hwy 34",
    "sg:city":"Kaufman",
    "sg:classifiers":[
        {
            "category":"Manufacturing",
            "subcategory":"Musical Instruments",
            "type":"Manufacturing & Wholesale Goods"
        }
    ],
    "sg:phone":"+1 972 962 6109",
    "sg:postcode":"75142",
    "sg:province":"TX",
    "sg:tags":[
        "mfg"
    ],
    "wof:name":"Skunk Music",
    "wof:placetype":"venue"
},
  "geometry": {"coordinates":[-96.26851600000001,32.633604],"type":"Point"}
}