{
  "type": "Feature",
  "properties": {
    "iso:country":"US",
    "sg:address":"495 Texas Ave",
    "sg:city":"Bridge City",
    "sg:classifiers":[
        {
            "category":"Autos & Motor Vehicles",
            "subcategory":"Automobile Sales",
            "type":"Retail Goods"
        }
    ],
    "sg:phone":"+1 409 960 9060",
    "sg:postcode":"77611",
    "sg:province":"TX",
    "sg:tags":[
        "car",
        "used",
        "dealer"
    ],
    "wof:name":"Cricchio's Cars",
    "wof:placetype":"venue"
},
  "geometry": {"coordinates":[-93.84422000000001,30.022948],"type":"Point"}
}