{
  "type": "Feature",
  "properties": {
    "iso:country":"US",
    "sg:address":"111 S Trinity St",
    "sg:city":"Decatur",
    "sg:classifiers":[
        {
            "category":"Insurance",
            "subcategory":"Insurance Agent",
            "type":"Services"
        }
    ],
    "sg:phone":"+1 940 627 5790",
    "sg:postcode":"76234",
    "sg:province":"TX",
    "wof:name":"Lambert Insurance",
    "wof:placetype":"venue"
},
  "geometry": {"coordinates":[-97.58654,33.23406],"type":"Point"}
}