{
  "type": "Feature",
  "properties": {
    "iso:country":"US",
    "sg:address":"421 Alcorn Ave",
    "sg:city":"Dallas",
    "sg:classifiers":[
        {
            "category":"Personal",
            "subcategory":"Beauty Salon",
            "type":"Services"
        }
    ],
    "sg:phone":"+1 214 391 4190",
    "sg:postcode":"75217",
    "sg:province":"TX",
    "sg:tags":[
        "shop"
    ],
    "wof:name":"Jessicas Hair Salon",
    "wof:placetype":"venue"
},
  "geometry": {"coordinates":[-96.70388199999999,32.719377],"type":"Point"}
}