{
  "type": "Feature",
  "properties": {
    "iso:country":"US",
    "sg:address":"3127 Quakertown Dr",
    "sg:city":"San Antonio",
    "sg:classifiers":[
        {
            "category":"Travel",
            "subcategory":"Campground",
            "type":"Entertainment"
        }
    ],
    "sg:phone":"+1 210 690 8391",
    "sg:postcode":"78230",
    "sg:province":"TX",
    "sg:tags":[
        "trailer"
    ],
    "wof:name":"Buddy Meyer Basketball CA",
    "wof:placetype":"venue"
},
  "geometry": {"coordinates":[-98.54668100000001,29.535801],"type":"Point"}
}