{
  "type": "Feature",
  "properties": {
    "iso:country":"US",
    "sg:address":"5609 SMU Blvd, Suite 102",
    "sg:city":"Dallas",
    "sg:classifiers":[
        {
            "category":"Fast Food",
            "type":"Food & Drink"
        }
    ],
    "sg:phone":"+1 214 570 5999",
    "sg:postcode":"75206",
    "sg:province":"TX",
    "sg:tags":[
        "burger"
    ],
    "sg:website":"www.twistedrootburgerco.com",
    "wof:name":"Twisted Root Burger Co",
    "wof:placetype":"venue"
},
  "geometry": {"coordinates":[-96.77499899999999,32.841933],"type":"Point"}
}