{
  "type": "Feature",
  "properties": {
    "iso:country":"US",
    "sg:address":"1803 Bent Oak Cove",
    "sg:city":"Leander",
    "sg:classifiers":[
        {
            "category":"Professional",
            "subcategory":"Computer Services",
            "type":"Services"
        }
    ],
    "sg:phone":"+1 512 779 6222",
    "sg:postcode":"78641",
    "sg:province":"TX",
    "wof:name":"Compu Doc",
    "wof:placetype":"venue"
},
  "geometry": {"coordinates":[-97.858439,30.551674],"type":"Point"}
}