{
  "type": "Feature",
  "properties": {
    "iso:country":"US",
    "sg:address":"100 N Race St",
    "sg:city":"Fort Worth",
    "sg:classifiers":[
        {
            "category":"Education",
            "subcategory":"Library",
            "type":"Public Place"
        }
    ],
    "sg:phone":"+1 817 551 0726",
    "sg:postcode":"76140",
    "sg:province":"TX",
    "sg:tags":[
        "executive"
    ],
    "wof:name":"Everman Public Library",
    "wof:placetype":"venue"
},
  "geometry": {"coordinates":[-97.287122,32.63201],"type":"Point"}
}