{
  "type": "Feature",
  "properties": {
    "iso:country":"US",
    "sg:address":"2946 Mark Twain Dr",
    "sg:city":"Dallas",
    "sg:classifiers":[
        {
            "category":"Building & Trades",
            "subcategory":"Plumbing",
            "type":"Services"
        }
    ],
    "sg:phone":"+1 972 247 6969",
    "sg:postcode":"75234",
    "sg:province":"TX",
    "sg:tags":[
        "repair",
        "contractor"
    ],
    "wof:name":"Jimmy Price Plumbing",
    "wof:placetype":"venue"
},
  "geometry": {"coordinates":[-96.874477,32.941323],"type":"Point"}
}