{
  "type": "Feature",
  "properties": {
    "iso:country":"US",
    "sg:address":"618 Austin Ave",
    "sg:city":"Waco",
    "sg:classifiers":[
        {
            "category":"Home & Garden",
            "subcategory":"Building Materials",
            "type":"Retail Goods"
        }
    ],
    "sg:phone":"+1 254 757 2484",
    "sg:postcode":"76701",
    "sg:province":"TX",
    "sg:tags":[
        "glass",
        "leaded"
    ],
    "wof:name":"Diana's Glass Works",
    "wof:placetype":"venue"
},
  "geometry": {"coordinates":[-97.133348,31.555339],"type":"Point"}
}