{
  "type": "Feature",
  "properties": {
    "iso:country":"US",
    "sg:address":"1321 S Broadway St",
    "sg:city":"Plainview",
    "sg:phone":"+1 806 296 9693",
    "sg:postcode":"79072",
    "sg:province":"TX",
    "sg:tags":[
        "farm",
        "wheat",
        "grain",
        "cash"
    ],
    "wof:name":"June Houchin",
    "wof:placetype":"venue"
},
  "geometry": {"coordinates":[-101.70261000000001,34.167695],"type":"Point"}
}