{
  "type": "Feature",
  "properties": {
    "iso:country":"US",
    "sg:address":"919 E 32nd St",
    "sg:city":"Austin",
    "sg:classifiers":[
        {
            "category":"Banks & Credit Unions",
            "subcategory":"Investment Brokerage",
            "type":"Services"
        }
    ],
    "sg:phone":"+1 512 397 4070",
    "sg:postcode":"78705",
    "sg:province":"TX",
    "sg:tags":[
        "tape",
        "video",
        "sale",
        "dvds-rental"
    ],
    "wof:name":"Bedside Video",
    "wof:placetype":"venue"
},
  "geometry": {"coordinates":[-97.72672900000001,30.290853],"type":"Point"}
}