{
  "type": "Feature",
  "properties": {
    "iso:country":"US",
    "sg:address":"8695 Mesa Dr",
    "sg:city":"Houston",
    "sg:classifiers":[
        {
            "category":"Personal",
            "subcategory":"Barber",
            "type":"Services"
        }
    ],
    "sg:phone":"+1 713 631 5858",
    "sg:postcode":"77028",
    "sg:province":"TX",
    "sg:tags":[
        "shop"
    ],
    "wof:name":"Phnomena",
    "wof:placetype":"venue"
},
  "geometry": {"coordinates":[-95.26231199999999,29.839796],"type":"Point"}
}