{
  "type": "Feature",
  "properties": {
    "iso:country":"US",
    "sg:address":"8803 Brae Acres Rd",
    "sg:city":"Houston",
    "sg:classifiers":[
        {
            "category":"Professional",
            "subcategory":"Management & Consulting",
            "type":"Services"
        }
    ],
    "sg:phone":"+1 713 778 2870",
    "sg:postcode":"77074",
    "sg:province":"TX",
    "sg:tags":[
        "business"
    ],
    "wof:name":"Southwestern Bell",
    "wof:placetype":"venue"
},
  "geometry": {"coordinates":[-95.52167900000001,29.682697],"type":"Point"}
}