{
  "type": "Feature",
  "properties": {
    "iso:country":"US",
    "sg:address":"2375 Berend Rd",
    "sg:city":"Pilot Point",
    "sg:classifiers":[
        {
            "category":"Farming",
            "subcategory":"Farm",
            "type":"Manufacturing & Wholesale Goods"
        }
    ],
    "sg:phone":"+1 940 686 2224",
    "sg:postcode":"76258",
    "sg:province":"TX",
    "wof:name":"Crenshaw & Doguet Turf Farms",
    "wof:placetype":"venue"
},
  "geometry": {"coordinates":[-96.903104,33.414582],"type":"Point"}
}