{
  "type": "Feature",
  "properties": {
    "iso:country":"US",
    "sg:address":"324 S Morgan St",
    "sg:city":"Granbury",
    "sg:classifiers":[
        {
            "category":"Insurance",
            "subcategory":"Insurance Agent",
            "type":"Services"
        }
    ],
    "sg:phone":"+1 817 279 6509",
    "sg:postcode":"76048",
    "sg:province":"TX",
    "wof:name":"Allstate",
    "wof:placetype":"venue"
},
  "geometry": {"coordinates":[-97.794453,32.440195],"type":"Point"}
}