{
  "type": "Feature",
  "properties": {
    "iso:country":"US",
    "sg:address":"5327 Holly Ave",
    "sg:city":"Pasadena",
    "sg:classifiers":[
        {
            "category":"Building & Trades",
            "subcategory":"Plumbing",
            "type":"Services"
        }
    ],
    "sg:phone":"+1 281 487 8166",
    "sg:postcode":"77503",
    "sg:province":"TX",
    "sg:tags":[
        "contractor"
    ],
    "wof:name":"MB Plumbing Services",
    "wof:placetype":"venue"
},
  "geometry": {"coordinates":[-95.16009,29.668831],"type":"Point"}
}