{
  "type": "Feature",
  "properties": {
    "iso:country":"US",
    "sg:address":"805 Weybridge Ln",
    "sg:city":"Keller",
    "sg:classifiers":[
        {
            "category":"Professional",
            "type":"Services"
        }
    ],
    "sg:phone":"+1 817 247 9604",
    "sg:postcode":"76248",
    "sg:province":"TX",
    "wof:name":"Gerald Borden",
    "wof:placetype":"venue"
},
  "geometry": {"coordinates":[-97.234683,32.959566],"type":"Point"}
}