{
  "type": "Feature",
  "properties": {
    "iso:country":"US",
    "sg:address":"2740 N Grandview Ave",
    "sg:city":"Odessa",
    "sg:classifiers":[
        {
            "category":"Banks & Credit Unions",
            "subcategory":"Bank",
            "type":"Services"
        }
    ],
    "sg:phone":"+1 432 368 9259",
    "sg:postcode":"79762",
    "sg:province":"TX",
    "wof:name":"Western National Bank",
    "wof:placetype":"venue"
},
  "geometry": {"coordinates":[-102.34744600000001,31.876177],"type":"Point"}
}