{
  "type": "Feature",
  "properties": {
    "iso:country":"US",
    "sg:address":"1814 Constantinople St",
    "sg:city":"Castroville",
    "sg:classifiers":[
        {
            "category":"Professional",
            "subcategory":"Management & Consulting",
            "type":"Services"
        },
        {
            "category":"Professional",
            "subcategory":"Advertising",
            "type":"Services"
        }
    ],
    "sg:phone":"+1 830 538 3817",
    "sg:postcode":"78009",
    "sg:province":"TX",
    "sg:tags":[
        "marketing",
        "program",
        "consultant"
    ],
    "wof:name":"Kempf International",
    "wof:placetype":"venue"
},
  "geometry": {"coordinates":[-98.885735,29.355683],"type":"Point"}
}