{
  "type": "Feature",
  "properties": {
    "iso:country":"US",
    "sg:address":"2157 Ave G",
    "sg:city":"Wichita Falls",
    "sg:classifiers":[
        {
            "category":"Professional",
            "type":"Services"
        }
    ],
    "sg:phone":"+1 940 767 0990",
    "sg:postcode":"76309",
    "sg:province":"TX",
    "wof:name":"Suzette Creations",
    "wof:placetype":"venue"
},
  "geometry": {"coordinates":[-98.51835699999999,33.895356],"type":"Point"}
}