{
  "type": "Feature",
  "properties": {
    "iso:country":"US",
    "sg:address":"816 Main St",
    "sg:city":"Lubbock",
    "sg:classifiers":[
        {
            "category":"Professional",
            "subcategory":"Lawyer & Legal Services",
            "type":"Services"
        }
    ],
    "sg:phone":"+1 806 762 6030",
    "sg:postcode":"79401",
    "sg:province":"TX",
    "sg:tags":[
        "attorney"
    ],
    "wof:name":"Steven M Denny",
    "wof:placetype":"venue"
},
  "geometry": {"coordinates":[-101.844249,33.585579],"type":"Point"}
}