{
  "type": "Feature",
  "properties": {
    "iso:country":"US",
    "sg:address":"2502 Buena Vista St",
    "sg:city":"San Antonio",
    "sg:classifiers":[
        {
            "category":"Insurance",
            "subcategory":"Insurance Agent",
            "type":"Services"
        }
    ],
    "sg:phone":"+1 210 434 9713",
    "sg:postcode":"78207",
    "sg:province":"TX",
    "wof:name":"Frances Guerra Insurance Agcy",
    "wof:placetype":"venue"
},
  "geometry": {"coordinates":[-98.527044,29.426999],"type":"Point"}
}