{
  "type": "Feature",
  "properties": {
    "iso:country":"US",
    "sg:address":"1205 Valley View Dr",
    "sg:city":"Arlington",
    "sg:classifiers":[
        {
            "category":"Building & Trades",
            "subcategory":"Construction",
            "type":"Services"
        }
    ],
    "sg:phone":"+1 817 795 3815",
    "sg:postcode":"76010",
    "sg:province":"TX",
    "sg:tags":[
        "hanging",
        "contractor"
    ],
    "wof:name":"JV Painting",
    "wof:placetype":"venue"
},
  "geometry": {"coordinates":[-97.093003,32.726318],"type":"Point"}
}