{
  "type": "Feature",
  "properties": {
    "iso:country":"US",
    "sg:address":"460 Jones St",
    "sg:city":"Lewisville",
    "sg:classifiers":[
        {
            "category":"Building & Trades",
            "subcategory":"Landscaping Services",
            "type":"Services"
        }
    ],
    "sg:phone":"+1 972 446 1472",
    "sg:postcode":"75057",
    "sg:province":"TX",
    "sg:tags":[
        "lawn",
        "care"
    ],
    "wof:name":"Lawn Doctor of Carrollton",
    "wof:placetype":"venue"
},
  "geometry": {"coordinates":[-97.003767,33.063855],"type":"Point"}
}