{
  "type": "Feature",
  "properties": {
    "iso:country":"US",
    "sg:address":"927 Broadway St",
    "sg:city":"Plainview",
    "sg:classifiers":[
        {
            "category":"Professional",
            "subcategory":"Accounting & Tax Preparation",
            "type":"Services"
        }
    ],
    "sg:phone":"+1 806 293 4239",
    "sg:postcode":"79072",
    "sg:province":"TX",
    "wof:name":"Bill Cross CPA",
    "wof:placetype":"venue"
},
  "geometry": {"coordinates":[-101.703165,34.190562],"type":"Point"}
}