{
  "type": "Feature",
  "properties": {
    "iso:country":"US",
    "sg:address":"322 W Cowan Dr",
    "sg:city":"Houston",
    "sg:classifiers":[
        {
            "category":"Health Services",
            "subcategory":"Doctor",
            "type":"Services"
        }
    ],
    "sg:phone":"+1 713 802 2673",
    "sg:postcode":"77007",
    "sg:province":"TX",
    "wof:name":"Garcia Charles A MD",
    "wof:placetype":"venue"
},
  "geometry": {"coordinates":[-95.426132,29.765908],"type":"Point"}
}