{
  "type": "Feature",
  "properties": {
    "iso:country":"US",
    "sg:address":"9512 Indigo Brush Dr",
    "sg:city":"Austin",
    "sg:classifiers":[
        {
            "category":"Professional",
            "type":"Services"
        }
    ],
    "sg:phone":"+1 512 506 8756",
    "sg:postcode":"78726",
    "sg:province":"TX",
    "wof:name":"Briscoe & Broussard Inc",
    "wof:placetype":"venue"
},
  "geometry": {"coordinates":[-97.82590500000001,30.430138],"type":"Point"}
}