{
  "type": "Feature",
  "properties": {
    "iso:country":"US",
    "sg:address":"4512 Old Pond Dr",
    "sg:city":"Plano",
    "sg:classifiers":[
        {
            "category":"Professional",
            "subcategory":"Business Services",
            "type":"Services"
        }
    ],
    "sg:phone":"+1 972 491 2633",
    "sg:postcode":"75024",
    "sg:province":"TX",
    "sg:tags":[
        "merchandise"
    ],
    "wof:name":"Judith Gillespie Interiors",
    "wof:placetype":"venue"
},
  "geometry": {"coordinates":[-96.780638,33.075046],"type":"Point"}
}