{
  "type": "Feature",
  "properties": {
    "iso:country":"US",
    "sg:address":"5307 Bent Tree Dr",
    "sg:city":"Dallas",
    "sg:classifiers":[
        {
            "category":"Arts & Performance",
            "subcategory":"Theater",
            "type":"Entertainment"
        }
    ],
    "sg:phone":"+1 972 931 8443",
    "sg:postcode":"75248",
    "sg:province":"TX",
    "sg:tags":[
        "group"
    ],
    "wof:name":"Cda Entertainment",
    "wof:placetype":"venue"
},
  "geometry": {"coordinates":[-96.812732,32.979146],"type":"Point"}
}