{
  "type": "Feature",
  "properties": {
    "iso:country":"US",
    "sg:address":"2700 Via Fortuna",
    "sg:city":"Austin",
    "sg:classifiers":[
        {
            "category":"Insurance",
            "subcategory":"Insurance Agent",
            "type":"Services"
        }
    ],
    "sg:phone":"+1 512 328 1851",
    "sg:postcode":"78746",
    "sg:province":"TX",
    "sg:tags":[
        "adjuster"
    ],
    "wof:name":"Beneke/Adjusters Intl",
    "wof:placetype":"venue"
},
  "geometry": {"coordinates":[-97.800527,30.255421],"type":"Point"}
}