{
  "type": "Feature",
  "properties": {
    "iso:country":"US",
    "sg:address":"1308 Liesure Ln",
    "sg:city":"De Soto",
    "sg:classifiers":[
        {
            "category":"Freight",
            "type":"Transportation"
        }
    ],
    "sg:phone":"+1 972 780 8072",
    "sg:postcode":"75115",
    "sg:province":"TX",
    "sg:tags":[
        "operator",
        "local",
        "trucking"
    ],
    "wof:name":"D-Best Movers",
    "wof:placetype":"venue"
},
  "geometry": {"coordinates":[-96.89189,32.614602],"type":"Point"}
}