{
  "type": "Feature",
  "properties": {
    "iso:country":"US",
    "sg:address":"18240 Midway Rd",
    "sg:city":"Dallas",
    "sg:classifiers":[
        {
            "category":"Professional",
            "subcategory":"Management & Consulting",
            "type":"Services"
        }
    ],
    "sg:phone":"+1 972 620 1500",
    "sg:postcode":"75287",
    "sg:province":"TX",
    "sg:tags":[
        "administrative",
        "purchasing"
    ],
    "wof:name":"API Purchasing",
    "wof:placetype":"venue"
},
  "geometry": {"coordinates":[-96.843683,32.99811],"type":"Point"}
}