{
  "type": "Feature",
  "properties": {
    "iso:country":"US",
    "sg:address":"125 N Bonnie Brae St",
    "sg:city":"Denton",
    "sg:classifiers":[
        {
            "category":"Food & Beverages",
            "subcategory":"Groceries & Convenience Stores",
            "type":"Retail Goods"
        }
    ],
    "sg:phone":"+1 940 383 3354",
    "sg:postcode":"76201",
    "sg:province":"TX",
    "sg:tags":[
        "station",
        "gasoline"
    ],
    "wof:name":"Nationwide Deli-Quick",
    "wof:placetype":"venue"
},
  "geometry": {"coordinates":[-97.16145400000001,33.215009],"type":"Point"}
}