{
  "type": "Feature",
  "properties": {
    "iso:country":"US",
    "sg:address":"3006 Neyland St",
    "sg:city":"Liberty",
    "sg:classifiers":[
        {
            "category":"Real Estate",
            "subcategory":"Real Estate Operator",
            "type":"Services"
        }
    ],
    "sg:phone":"+1 936 336 6525",
    "sg:postcode":"77575",
    "sg:province":"TX",
    "sg:tags":[
        "apartment"
    ],
    "wof:name":"Oaks Apartments",
    "wof:placetype":"venue"
},
  "geometry": {"coordinates":[-94.782258,30.055435],"type":"Point"}
}