{
  "type": "Feature",
  "properties": {
    "iso:country":"US",
    "sg:address":"741 N 7th St",
    "sg:city":"Albany",
    "sg:classifiers":[
        {
            "category":"Shopping",
            "subcategory":"Jewelry",
            "type":"Retail Goods"
        }
    ],
    "sg:phone":"+1 325 762 2887",
    "sg:postcode":"76430",
    "sg:province":"TX",
    "wof:name":"Heart of West",
    "wof:placetype":"venue"
},
  "geometry": {"coordinates":[-99.296841,32.731615],"type":"Point"}
}