{
  "type": "Feature",
  "properties": {
    "iso:country":"US",
    "sg:address":"501 S Cotton St",
    "sg:city":"El Paso",
    "sg:classifiers":[
        {
            "category":"Shopping",
            "subcategory":"Shoes",
            "type":"Retail Goods"
        }
    ],
    "sg:phone":"+1 915 544 1855",
    "sg:postcode":"79901",
    "sg:province":"TX",
    "sg:tags":[
        "boot"
    ],
    "wof:name":"Attitude Boots",
    "wof:placetype":"venue"
},
  "geometry": {"coordinates":[-106.473669,31.756677],"type":"Point"}
}