{
  "type": "Feature",
  "properties": {
    "iso:country":"US",
    "sg:address":"820 E Mccart St",
    "sg:city":"Krum",
    "sg:classifiers":[
        {
            "category":"Personal",
            "subcategory":"Beauty Salon",
            "type":"Services"
        }
    ],
    "sg:phone":"+1 940 482 6500",
    "sg:postcode":"76249",
    "sg:province":"TX",
    "wof:name":"Double L Salon",
    "wof:placetype":"venue"
},
  "geometry": {"coordinates":[-97.229449,33.258942],"type":"Point"}
}