{
  "type": "Feature",
  "properties": {
    "iso:country":"US",
    "sg:address":"502 E Highland Mall Blvd",
    "sg:city":"Austin",
    "sg:classifiers":[
        {
            "category":"Professional",
            "subcategory":"Business Services",
            "type":"Services"
        }
    ],
    "sg:phone":"+1 512 450 1133",
    "sg:postcode":"78752",
    "sg:province":"TX",
    "sg:tags":[
        "conference",
        "training",
        "center"
    ],
    "wof:name":"Microtek",
    "wof:placetype":"venue"
},
  "geometry": {"coordinates":[-97.710065,30.328197],"type":"Point"}
}