{
  "type": "Feature",
  "properties": {
    "iso:country":"US",
    "sg:address":"2147 Eva Ln",
    "sg:city":"Euless",
    "sg:classifiers":[
        {
            "category":"Real Estate",
            "subcategory":"Real Estate Agent",
            "type":"Services"
        }
    ],
    "sg:phone":"+1 817 571 4327",
    "sg:postcode":"76040",
    "sg:province":"TX",
    "wof:name":"Home Realty Co",
    "wof:placetype":"venue"
},
  "geometry": {"coordinates":[-97.118647,32.826075],"type":"Point"}
}