{
  "type": "Feature",
  "properties": {
    "iso:country":"US",
    "sg:address":"1825 Fortview Rd Ste 105",
    "sg:city":"Austin",
    "sg:classifiers":[
        {
            "category":"Manufacturing",
            "subcategory":"Electronics",
            "type":"Manufacturing & Wholesale Goods"
        }
    ],
    "sg:phone":"+1 512 443 0925",
    "sg:postcode":"78704",
    "sg:province":"TX",
    "sg:tags":[
        "control",
        "regulators-control",
        "panel"
    ],
    "sg:website":"http://www.getransportation.com",
    "wof:name":"General Electric Company",
    "wof:placetype":"venue"
},
  "geometry": {"coordinates":[-97.785892,30.230148],"type":"Point"}
}