{
  "type": "Feature",
  "properties": {
    "iso:country":"US",
    "sg:address":"4036 W Vickery Blvd",
    "sg:city":"Fort Worth",
    "sg:classifiers":[
        {
            "category":"Food & Beverages",
            "subcategory":"Groceries & Convenience Stores",
            "type":"Retail Goods"
        }
    ],
    "sg:phone":"+1 817 737 4740",
    "sg:postcode":"76107",
    "sg:province":"TX",
    "wof:name":"Quick Pick 2",
    "wof:placetype":"venue"
},
  "geometry": {"coordinates":[-97.377047,32.727277],"type":"Point"}
}