{
  "type": "Feature",
  "properties": {
    "iso:country":"US",
    "sg:address":"501 N Main St",
    "sg:city":"Cotulla",
    "sg:classifiers":[
        {
            "category":"Shopping",
            "subcategory":"Jewelry",
            "type":"Retail Goods"
        }
    ],
    "sg:phone":"+1 830 879 3840",
    "sg:postcode":"78014",
    "sg:province":"TX",
    "wof:name":"South By Southwest",
    "wof:placetype":"venue"
},
  "geometry": {"coordinates":[-99.23600999999999,28.44154],"type":"Point"}
}