{
  "type": "Feature",
  "properties": {
    "iso:country":"US",
    "sg:address":"3702 FM 528",
    "sg:city":"Friendswood",
    "sg:classifiers":[
        {
            "category":"Food & Beverages",
            "subcategory":"Groceries & Convenience Stores",
            "type":"Retail Goods"
        }
    ],
    "sg:phone":"+1 281 992 1155",
    "sg:postcode":"77546",
    "sg:province":"TX",
    "wof:name":"Speedy Food Mart",
    "wof:placetype":"venue"
},
  "geometry": {"coordinates":[-95.169546,29.521588],"type":"Point"}
}