{
  "type": "Feature",
  "properties": {
    "iso:country":"US",
    "sg:address":"4801 Frankford Ave",
    "sg:city":"Lubbock",
    "sg:classifiers":[
        {
            "category":"Building & Trades",
            "subcategory":"Equipment Rental",
            "type":"Services"
        }
    ],
    "sg:phone":"+1 806 796 2899",
    "sg:postcode":"79424",
    "sg:province":"TX",
    "sg:tags":[
        "repair",
        "medical"
    ],
    "wof:name":"Mediq-Prn/Lubbock 58",
    "wof:placetype":"venue"
},
  "geometry": {"coordinates":[-101.939734,33.550767],"type":"Point"}
}