{
  "type": "Feature",
  "properties": {
    "iso:country":"US",
    "sg:address":"5240 US Hwy 290",
    "sg:city":"Austin",
    "sg:classifiers":[
        {
            "category":"Professional",
            "type":"Services"
        }
    ],
    "sg:phone":"+1 512 892 2458",
    "sg:postcode":"78735",
    "sg:province":"TX",
    "sg:tags":[
        "establishment"
    ],
    "wof:name":"Integrated Systems",
    "wof:placetype":"venue"
},
  "geometry": {"coordinates":[-97.83220300000001,30.23637],"type":"Point"}
}