{
  "type": "Feature",
  "properties": {
    "iso:country":"US",
    "sg:address":"4862 Willowbend Blvd",
    "sg:city":"Houston",
    "sg:classifiers":[
        {
            "category":"Restaurant",
            "type":"Food & Drink"
        }
    ],
    "sg:phone":"+1 713 721 3228",
    "sg:postcode":"77035",
    "sg:province":"TX",
    "wof:name":"Popeyes Famous Fried Chicken",
    "wof:placetype":"venue"
},
  "geometry": {"coordinates":[-95.462898,29.664499],"type":"Point"}
}