{
  "type": "Feature",
  "properties": {
    "iso:country":"US",
    "sg:address":"107 N 4th St",
    "sg:city":"Uvalde",
    "sg:classifiers":[
        {
            "category":"Retail",
            "subcategory":"Auto Repair",
            "type":"Services"
        }
    ],
    "sg:phone":"+1 830 278 6666",
    "sg:postcode":"78801",
    "sg:province":"TX",
    "sg:tags":[
        "body",
        "automobile",
        "painting",
        "repairing"
    ],
    "wof:name":"Beco's Collision Center & Recovery",
    "wof:placetype":"venue"
},
  "geometry": {"coordinates":[-99.773774,29.214002],"type":"Point"}
}