{
  "type": "Feature",
  "properties": {
    "iso:country":"US",
    "sg:address":"7214 Blanco Rd",
    "sg:city":"San Antonio",
    "sg:classifiers":[
        {
            "category":"Restaurant",
            "type":"Food & Drink"
        }
    ],
    "sg:phone":"+1 210 348 9090",
    "sg:postcode":"78216",
    "sg:province":"TX",
    "sg:tags":[
        "independent",
        "pizzeria"
    ],
    "wof:name":"Goombas Pizzaria Inc",
    "wof:placetype":"venue"
},
  "geometry": {"coordinates":[-98.504997,29.525497],"type":"Point"}
}