{
  "type": "Feature",
  "properties": {
    "iso:country":"US",
    "sg:address":"11614 Stone Bridge Dr",
    "sg:city":"Houston",
    "sg:classifiers":[
        {
            "category":"Professional",
            "type":"Services"
        }
    ],
    "sg:phone":"+1 281 894 2168",
    "sg:postcode":"77064",
    "sg:province":"TX",
    "wof:name":"Jen Joy International",
    "wof:placetype":"venue"
},
  "geometry": {"coordinates":[-95.563419,29.942719],"type":"Point"}
}