{
  "type": "Feature",
  "properties": {
    "iso:country":"US",
    "sg:address":"6105 Grass Hollow",
    "sg:city":"Austin",
    "sg:classifiers":[
        {
            "category":"Home & Garden",
            "subcategory":"Furniture",
            "type":"Retail Goods"
        }
    ],
    "sg:phone":"+1 512 346 3490",
    "sg:postcode":"78750",
    "sg:province":"TX",
    "sg:tags":[
        "cabinet"
    ],
    "wof:name":"Texas Garages",
    "wof:placetype":"venue"
},
  "geometry": {"coordinates":[-97.787632,30.372861],"type":"Point"}
}