{
  "type": "Feature",
  "properties": {
    "iso:country":"US",
    "sg:address":"4847 Twin Valley Dr",
    "sg:city":"Austin",
    "sg:classifiers":[
        {
            "category":"Professional",
            "subcategory":"Lawyer & Legal Services",
            "type":"Services"
        }
    ],
    "sg:phone":"+1 512 560 8661",
    "sg:postcode":"78731",
    "sg:province":"TX",
    "sg:tags":[
        "attorney",
        "practice"
    ],
    "wof:name":"Margie Sampson Lawyer",
    "wof:placetype":"venue"
},
  "geometry": {"coordinates":[-97.782083,30.348055],"type":"Point"}
}