{
  "type": "Feature",
  "properties": {
    "iso:country":"US",
    "sg:address":"2810 Boulanger St",
    "sg:city":"Laredo",
    "sg:classifiers":[
        {
            "category":"Professional",
            "subcategory":"Business Services",
            "type":"Services"
        }
    ],
    "sg:phone":"+1 956 723 6285",
    "sg:postcode":"78043",
    "sg:province":"TX",
    "wof:name":"Garcia Catalina Yanez",
    "wof:placetype":"venue"
},
  "geometry": {"coordinates":[-99.466565,27.486944],"type":"Point"}
}