{
  "type": "Feature",
  "properties": {
    "iso:country":"US",
    "sg:address":"2023 W McDermott Dr",
    "sg:city":"Allen",
    "sg:classifiers":[
        {
            "category":"Retail",
            "subcategory":"Veterinary Services",
            "type":"Services"
        }
    ],
    "sg:phone":"+1 972 390 9273",
    "sg:postcode":"75013",
    "sg:province":"TX",
    "sg:tags":[
        "veterinarian"
    ],
    "wof:name":"Custer Mc Dermott Animal Hosp",
    "wof:placetype":"venue"
},
  "geometry": {"coordinates":[-96.732713,33.100738],"type":"Point"}
}