{
  "type": "Feature",
  "properties": {
    "iso:country":"US",
    "sg:address":"2630 N Josey Ln Ste 114",
    "sg:city":"Carrollton",
    "sg:classifiers":[
        {
            "category":"Health Services",
            "subcategory":"Doctor",
            "type":"Services"
        }
    ],
    "sg:phone":"+1 972 245 4546",
    "sg:postcode":"75007",
    "sg:province":"TX",
    "sg:tags":[
        "surgeon",
        "oral"
    ],
    "sg:website":"www.wulwickdds.com",
    "wof:name":"Wulwick Arthur C DDS",
    "wof:placetype":"venue"
},
  "geometry": {"coordinates":[-96.89070100000001,32.987099],"type":"Point"}
}