{
  "type": "Feature",
  "properties": {
    "iso:country":"US",
    "sg:address":"21430 Park Bend Dr",
    "sg:city":"Katy",
    "sg:classifiers":[
        {
            "category":"Retail",
            "subcategory":"Auto Repair",
            "type":"Services"
        }
    ],
    "sg:phone":"+1 281 578 9754",
    "sg:postcode":"77450",
    "sg:province":"TX",
    "sg:tags":[
        "general"
    ],
    "wof:name":"Williams Auto",
    "wof:placetype":"venue"
},
  "geometry": {"coordinates":[-95.742563,29.764108],"type":"Point"}
}