{
  "type": "Feature",
  "properties": {
    "iso:country":"US",
    "sg:address":"804 W Sabine St",
    "sg:city":"Carthage",
    "sg:classifiers":[
        {
            "category":"Professional",
            "subcategory":"Business Services",
            "type":"Services"
        }
    ],
    "sg:phone":"+1 903 694 4158",
    "sg:postcode":"75633",
    "sg:province":"TX",
    "wof:name":"Sonja Soape",
    "wof:placetype":"venue"
},
  "geometry": {"coordinates":[-94.350365,32.152395],"type":"Point"}
}