{
  "type": "Feature",
  "properties": {
    "iso:country":"US",
    "sg:address":"218 E 6th St",
    "sg:city":"Austin",
    "sg:classifiers":[
        {
            "category":"Bars & Pubs",
            "type":"Food & Drink"
        }
    ],
    "sg:phone":"+1 512 474 6363",
    "sg:postcode":"78701",
    "sg:province":"TX",
    "wof:name":"Bat Bar Austin",
    "wof:placetype":"venue"
},
  "geometry": {"coordinates":[-97.740574,30.267736],"type":"Point"}
}