{
  "type": "Feature",
  "properties": {
    "iso:country":"US",
    "sg:address":"12710 Research Boulevard",
    "sg:city":"Austin",
    "sg:classifiers":[
        {
            "category":"Banks & Credit Unions",
            "subcategory":"Financial Services",
            "type":"Services"
        }
    ],
    "sg:phone":"+1 512 450 1222",
    "sg:postcode":"78759",
    "sg:province":"TX",
    "sg:tags":[
        "broker",
        "mortgage"
    ],
    "wof:name":"Home Trust Company",
    "wof:placetype":"venue"
},
  "geometry": {"coordinates":[-97.766074,30.432068],"type":"Point"}
}