{
  "type": "Feature",
  "properties": {
    "iso:country":"US",
    "sg:address":"1800 S Western St",
    "sg:city":"Amarillo",
    "sg:classifiers":[
        {
            "category":"Organizations",
            "subcategory":"Religious Organization",
            "type":"Services"
        }
    ],
    "sg:phone":"+1 806 355 9829",
    "sg:postcode":"79106",
    "sg:province":"TX",
    "sg:tags":[
        "baptist",
        "church"
    ],
    "wof:name":"Amarillo Suthern Baptists Assn",
    "wof:placetype":"venue"
},
  "geometry": {"coordinates":[-101.884033,35.192831],"type":"Point"}
}