{
  "type": "Feature",
  "properties": {
    "iso:country":"US",
    "sg:address":"2717 Cross St",
    "sg:city":"Laredo",
    "sg:classifiers":[
        {
            "category":"Organizations",
            "subcategory":"Religious Organization",
            "type":"Services"
        }
    ],
    "sg:phone":"+1 956 724 6638",
    "sg:postcode":"78046",
    "sg:province":"TX",
    "sg:tags":[
        "church"
    ],
    "wof:name":"Santo Nino Mission Church",
    "wof:placetype":"venue"
},
  "geometry": {"coordinates":[-99.46752499999999,27.46845],"type":"Point"}
}