{
  "type": "Feature",
  "properties": {
    "iso:country":"US",
    "sg:address":"1106 Main St",
    "sg:city":"Rusk",
    "sg:classifiers":[
        {
            "category":"Banks & Credit Unions",
            "subcategory":"Bank",
            "type":"Services"
        }
    ],
    "sg:phone":"+1 903 683 8899",
    "sg:postcode":"75785",
    "sg:province":"TX",
    "wof:name":"Texas National Bank",
    "wof:placetype":"venue"
},
  "geometry": {"coordinates":[-95.150445,31.802449],"type":"Point"}
}