{
  "type": "Feature",
  "properties": {
    "iso:country":"US",
    "sg:address":"2591 NE 28th St",
    "sg:city":"Fort Worth",
    "sg:classifiers":[
        {
            "category":"Farming",
            "subcategory":"Farm & Veterinary Services",
            "type":"Manufacturing & Wholesale Goods"
        }
    ],
    "sg:phone":"+1 817 831 4696",
    "sg:postcode":"76111",
    "sg:province":"TX",
    "sg:tags":[
        "preparation",
        "soil"
    ],
    "wof:name":"Jowell Corp",
    "wof:placetype":"venue"
},
  "geometry": {"coordinates":[-97.31108999999999,32.795252],"type":"Point"}
}