{
  "type": "Feature",
  "properties": {
    "iso:country":"US",
    "sg:address":"1002 Bandera Rd",
    "sg:city":"San Antonio",
    "sg:classifiers":[
        {
            "category":"Building & Trades",
            "subcategory":"Construction",
            "type":"Services"
        }
    ],
    "sg:phone":"+1 210 433 2843",
    "sg:postcode":"78228",
    "sg:province":"TX",
    "sg:tags":[
        "contractor"
    ],
    "wof:name":"Quality Glass & Glazing Inc",
    "wof:placetype":"venue"
},
  "geometry": {"coordinates":[-98.55907000000001,29.460443],"type":"Point"}
}