{
  "type": "Feature",
  "properties": {
    "iso:country":"US",
    "sg:address":"1519 Stonewall Dr",
    "sg:city":"Longview",
    "sg:classifiers":[
        {
            "category":"Building & Trades",
            "subcategory":"Plumbing",
            "type":"Services"
        }
    ],
    "sg:phone":"+1 903 230 7988",
    "sg:postcode":"75604",
    "sg:province":"TX",
    "sg:tags":[
        "plumber",
        "industrial",
        "contractors-commercial"
    ],
    "wof:name":"East Texas Mr Plumber",
    "wof:placetype":"venue"
},
  "geometry": {"coordinates":[-94.763611,32.516762],"type":"Point"}
}