{
  "type": "Feature",
  "properties": {
    "iso:country":"US",
    "sg:address":"4719 Enchanted Bay Blvd",
    "sg:city":"Arlington",
    "sg:classifiers":[
        {
            "category":"Retail",
            "subcategory":"Auto Repair",
            "type":"Services"
        }
    ],
    "sg:phone":"+1 817 300 3142",
    "sg:postcode":"76016",
    "sg:province":"TX",
    "sg:tags":[
        "automotive"
    ],
    "wof:name":"Kw Quailty Auto Lube",
    "wof:placetype":"venue"
},
  "geometry": {"coordinates":[-97.22775900000001,32.670809],"type":"Point"}
}