{
  "type": "Feature",
  "properties": {
    "iso:country":"US",
    "sg:address":"16901 Davenport Rd",
    "sg:city":"Dallas",
    "sg:classifiers":[
        {
            "category":"Retail",
            "subcategory":"Animal Services",
            "type":"Services"
        }
    ],
    "sg:phone":"+1 214 796 1441",
    "sg:postcode":"75248",
    "sg:province":"TX",
    "sg:tags":[
        "horse",
        "training"
    ],
    "wof:name":"Sundance Stables",
    "wof:placetype":"venue"
},
  "geometry": {"coordinates":[-96.794937,32.979721],"type":"Point"}
}