{
  "type": "Feature",
  "properties": {
    "iso:country":"US",
    "sg:address":"9219 Ridgeland St",
    "sg:city":"San Antonio",
    "sg:classifiers":[
        {
            "category":"Freight",
            "type":"Transportation"
        }
    ],
    "sg:phone":"+1 210 861 5694",
    "sg:postcode":"78250",
    "sg:province":"TX",
    "sg:tags":[
        "local",
        "except",
        "trucking"
    ],
    "wof:name":"Hector Flores Trucking",
    "wof:placetype":"venue"
},
  "geometry": {"coordinates":[-98.67044199999999,29.49326],"type":"Point"}
}