{
  "type": "Feature",
  "properties": {
    "iso:country":"US",
    "sg:address":"8701 Greenville Ave",
    "sg:city":"Dallas",
    "sg:classifiers":[
        {
            "category":"Government",
            "subcategory":"Fire Station",
            "type":"Public Place"
        }
    ],
    "sg:phone":"+1 214 670 0755",
    "sg:postcode":"75243",
    "sg:province":"TX",
    "sg:tags":[
        "protection"
    ],
    "wof:name":"Fire Station 28",
    "wof:placetype":"venue"
},
  "geometry": {"coordinates":[-96.751272,32.896945],"type":"Point"}
}