{
  "type": "Feature",
  "properties": {
    "iso:country":"US",
    "sg:address":"28267 Ruffian Dr",
    "sg:city":"Boerne",
    "sg:classifiers":[
        {
            "category":"Manufacturing",
            "subcategory":"Tools & Machinery",
            "type":"Manufacturing & Wholesale Goods"
        }
    ],
    "sg:phone":"+1 210 695 8242",
    "sg:postcode":"78015",
    "sg:province":"TX",
    "sg:tags":[
        "physician",
        "use",
        "for",
        "oxygen",
        "mfg",
        "hospital",
        "analyzer",
        "an",
        "surgeon"
    ],
    "wof:name":"A-Vox Systems Inc",
    "wof:placetype":"venue"
},
  "geometry": {"coordinates":[-98.628299,29.718903],"type":"Point"}
}