{
  "type": "Feature",
  "properties": {
    "iso:country":"US",
    "sg:address":"3307 Bogota Rd",
    "sg:city":"Athens",
    "sg:classifiers":[
        {
            "category":"Building & Trades",
            "subcategory":"Landscaping Services",
            "type":"Services"
        }
    ],
    "sg:phone":"+1 903 677 5449",
    "sg:postcode":"75751",
    "sg:province":"TX",
    "wof:name":"Davis Lawn Service",
    "wof:placetype":"venue"
},
  "geometry": {"coordinates":[-95.797568,32.209503],"type":"Point"}
}