{
  "type": "Feature",
  "properties": {
    "iso:country":"US",
    "sg:address":"8404 Lenore St",
    "sg:city":"Houston",
    "sg:classifiers":[
        {
            "category":"Professional",
            "type":"Services"
        }
    ],
    "sg:phone":"+1 713 644 8900",
    "sg:postcode":"77017",
    "sg:province":"TX",
    "wof:name":"J Epifanio Vasquez",
    "wof:placetype":"venue"
},
  "geometry": {"coordinates":[-95.255126,29.682599],"type":"Point"}
}