{
  "type": "Feature",
  "properties": {
    "iso:country":"US",
    "sg:address":"205 N 1st St",
    "sg:city":"Roby",
    "sg:classifiers":[
        {
            "category":"Government",
            "subcategory":"Office",
            "type":"Public Place"
        }
    ],
    "sg:phone":"+1 325 776 2271",
    "sg:postcode":"79543",
    "sg:province":"TX",
    "sg:tags":[
        "city"
    ],
    "wof:name":"Roby City Hall",
    "wof:placetype":"venue"
},
  "geometry": {"coordinates":[-100.375893,32.746609],"type":"Point"}
}