{
  "type": "Feature",
  "properties": {
    "iso:country":"US",
    "sg:address":"2225 E Randol Mill Rd",
    "sg:city":"Arlington",
    "sg:classifiers":[
        {
            "category":"Professional",
            "subcategory":"Management & Consulting",
            "type":"Services"
        }
    ],
    "sg:phone":"+1 817 640 0856",
    "sg:postcode":"76011",
    "sg:province":"TX",
    "sg:tags":[
        "import",
        "c",
        "export",
        "provides"
    ],
    "wof:name":"Ibd",
    "wof:placetype":"venue"
},
  "geometry": {"coordinates":[-97.069694,32.748036],"type":"Point"}
}