{
  "type": "Feature",
  "properties": {
    "iso:country":"US",
    "sg:address":"13176 W Lake Houston Pkwy Ste 12",
    "sg:city":"Houston",
    "sg:classifiers":[
        {
            "category":"Health Services",
            "subcategory":"Dentist",
            "type":"Services"
        }
    ],
    "sg:phone":"+1 281 617 1012",
    "sg:postcode":"77044",
    "sg:province":"TX",
    "wof:name":"SUMMERWOOD DENTAL",
    "wof:placetype":"venue"
},
  "geometry": {"coordinates":[-95.17881,29.926904],"type":"Point"}
}