{
  "type": "Feature",
  "properties": {
    "iso:country":"US",
    "sg:address":"2820 Preston Creek",
    "sg:city":"Mesquite",
    "sg:classifiers":[
        {
            "category":"Professional",
            "subcategory":"Employment Agencies",
            "type":"Services"
        }
    ],
    "sg:phone":"+1 972 222 6945",
    "sg:postcode":"75181",
    "sg:province":"TX",
    "sg:tags":[
        "help",
        "supply"
    ],
    "wof:name":"Precision Word & Temp Service",
    "wof:placetype":"venue"
},
  "geometry": {"coordinates":[-96.55675100000001,32.751684],"type":"Point"}
}