{
  "type": "Feature",
  "properties": {
    "iso:country":"US",
    "sg:address":"300 W Ave B",
    "sg:city":"Copperas Cove",
    "sg:classifiers":[
        {
            "category":"Organizations",
            "subcategory":"Religious Organization",
            "type":"Services"
        }
    ],
    "sg:phone":"+1 254 547 3717",
    "sg:postcode":"76522",
    "sg:province":"TX",
    "sg:tags":[
        "church"
    ],
    "sg:website":"www.fbccove.net",
    "wof:name":"First Baptist Church Inc",
    "wof:placetype":"venue"
},
  "geometry": {"coordinates":[-97.905058,31.126756],"type":"Point"}
}