{
  "type": "Feature",
  "properties": {
    "iso:country":"US",
    "sg:address":"401 Co Rd 208",
    "sg:city":"Winters",
    "sg:phone":"+1 325 754 4202",
    "sg:postcode":"79567",
    "sg:province":"TX",
    "sg:tags":[
        "farm",
        "wheat"
    ],
    "wof:name":"Edwin Deike",
    "wof:placetype":"venue"
},
  "geometry": {"coordinates":[-99.903475,31.942788],"type":"Point"}
}