{
  "type": "Feature",
  "properties": {
    "iso:country":"US",
    "sg:address":"8904 la Siesta Ct",
    "sg:city":"Austin",
    "sg:classifiers":[
        {
            "category":"Professional",
            "type":"Services"
        }
    ],
    "sg:phone":"+1 512 394 0822",
    "sg:postcode":"78749",
    "sg:province":"TX",
    "sg:tags":[
        "processing",
        "data"
    ],
    "wof:name":"Cs Stars",
    "wof:placetype":"venue"
},
  "geometry": {"coordinates":[-97.880261,30.211765],"type":"Point"}
}