{
  "type": "Feature",
  "properties": {
    "iso:country":"US",
    "sg:address":"225 Cody Ln",
    "sg:city":"Bastrop",
    "sg:classifiers":[
        {
            "category":"Freight",
            "type":"Transportation"
        }
    ],
    "sg:phone":"+1 512 773 3350",
    "sg:postcode":"78602",
    "sg:province":"TX",
    "sg:tags":[
        "operator",
        "local",
        "trucking"
    ],
    "wof:name":"Ogles Delivery Service",
    "wof:placetype":"venue"
},
  "geometry": {"coordinates":[-97.275015,30.210533],"type":"Point"}
}