{
  "type": "Feature",
  "properties": {
    "iso:country":"US",
    "sg:address":"2420 Jacksboro Hwy",
    "sg:city":"Fort Worth",
    "sg:classifiers":[
        {
            "category":"Shopping",
            "subcategory":"Florist",
            "type":"Retail Goods"
        }
    ],
    "sg:phone":"+1 817 626 5822",
    "sg:postcode":"76114",
    "sg:province":"TX",
    "wof:name":"Bradley Florist",
    "wof:placetype":"venue"
},
  "geometry": {"coordinates":[-97.384069,32.786094],"type":"Point"}
}