{
  "type": "Feature",
  "properties": {
    "iso:country":"US",
    "sg:address":"3001 Magnolia Ln",
    "sg:city":"Bedford",
    "sg:classifiers":[
        {
            "category":"Manufacturing",
            "subcategory":"Tools & Machinery",
            "type":"Manufacturing & Wholesale Goods"
        }
    ],
    "sg:phone":"+1 817 685 0669",
    "sg:postcode":"76021",
    "sg:province":"TX",
    "sg:tags":[
        "industrial",
        "construction",
        "mfg"
    ],
    "wof:name":"Omni Products Inc",
    "wof:placetype":"venue"
},
  "geometry": {"coordinates":[-97.117716,32.860934],"type":"Point"}
}