{
  "type": "Feature",
  "properties": {
    "iso:country":"US",
    "sg:address":"16200 Addison Rd",
    "sg:city":"Addison",
    "sg:classifiers":[
        {
            "category":"Professional",
            "subcategory":"Business Services",
            "type":"Services"
        }
    ],
    "sg:phone":"+1 480 755 1355",
    "sg:postcode":"75001",
    "sg:province":"TX",
    "wof:name":"Hunter Financial Group LLC",
    "wof:placetype":"venue"
},
  "geometry": {"coordinates":[-96.83034000000001,32.973816],"type":"Point"}
}