{
  "type": "Feature",
  "properties": {
    "iso:country":"US",
    "sg:address":"3125 Jacqueline Rd",
    "sg:city":"Wichita Falls",
    "sg:classifiers":[
        {
            "category":"Wholesale",
            "subcategory":"Construction Materials",
            "type":"Manufacturing & Wholesale Goods"
        }
    ],
    "sg:phone":"+1 940 716 9740",
    "sg:postcode":"76306",
    "sg:province":"TX",
    "sg:tags":[
        "sand",
        "gravel"
    ],
    "wof:name":"Bobby Bounds Excavation",
    "wof:placetype":"venue"
},
  "geometry": {"coordinates":[-98.52890600000001,33.924734],"type":"Point"}
}