{
  "type": "Feature",
  "properties": {
    "iso:country":"US",
    "sg:address":"1505 SW Wilshire Blvd",
    "sg:city":"Burleson",
    "sg:classifiers":[
        {
            "category":"Restaurant",
            "type":"Food & Drink"
        }
    ],
    "sg:phone":"+1 817 447 4302",
    "sg:postcode":"76028",
    "sg:province":"TX",
    "wof:name":"Smashburger",
    "wof:placetype":"venue"
},
  "geometry": {"coordinates":[-97.340763,32.528774],"type":"Point"}
}