{
  "type": "Feature",
  "properties": {
    "iso:country":"US",
    "sg:address":"5300 Coke St",
    "sg:city":"Houston",
    "sg:classifiers":[
        {
            "category":"Education",
            "subcategory":"Special Training",
            "type":"Public Place"
        }
    ],
    "sg:phone":"+1 713 671 6856",
    "sg:postcode":"77020",
    "sg:province":"TX",
    "sg:tags":[
        "center"
    ],
    "wof:name":"Kim's Learning Ctr",
    "wof:placetype":"venue"
},
  "geometry": {"coordinates":[-95.32037,29.767853],"type":"Point"}
}