{
  "type": "Feature",
  "properties": {
    "iso:country":"US",
    "sg:address":"16114 Indian Mill Dr",
    "sg:city":"Houston",
    "sg:classifiers":[
        {
            "category":"Freight",
            "type":"Transportation"
        }
    ],
    "sg:phone":"+1 281 589 7608",
    "sg:postcode":"77082",
    "sg:province":"TX",
    "sg:tags":[
        "operator",
        "local",
        "trucking"
    ],
    "wof:name":"Come On Trucking Co",
    "wof:placetype":"venue"
},
  "geometry": {"coordinates":[-95.66701500000001,29.716006],"type":"Point"}
}