{
  "type": "Feature",
  "properties": {
    "iso:country":"US",
    "sg:address":"4444 Walnut Hill Ln",
    "sg:city":"Dallas",
    "sg:classifiers":[
        {
            "category":"Professional",
            "subcategory":"Management & Consulting",
            "type":"Services"
        }
    ],
    "sg:phone":"+1 214 357 2687",
    "sg:postcode":"75229",
    "sg:province":"TX",
    "wof:name":"Hsr Management LLC",
    "wof:placetype":"venue"
},
  "geometry": {"coordinates":[-96.83336199999999,32.880089],"type":"Point"}
}