{
  "type": "Feature",
  "properties": {
    "iso:country":"US",
    "sg:address":"4211 Elgin St",
    "sg:city":"Houston",
    "sg:classifiers":[
        {
            "category":"Travel",
            "subcategory":"Hotels & Motels",
            "type":"Entertainment"
        },
        {
            "category":"Education",
            "subcategory":"University",
            "type":"Public Place"
        }
    ],
    "sg:phone":"+1 713 743 8500",
    "sg:postcode":"77004",
    "sg:province":"TX",
    "sg:tags":[
        "college"
    ],
    "wof:name":"University of Houston",
    "wof:placetype":"venue"
},
  "geometry": {"coordinates":[-95.34066199999999,29.7265],"type":"Point"}
}