{
  "type": "Feature",
  "properties": {
    "iso:country":"US",
    "sg:address":"4324 Lafayette",
    "sg:city":"Bellaire",
    "sg:classifiers":[
        {
            "category":"Professional",
            "subcategory":"Business Services",
            "type":"Services"
        }
    ],
    "sg:phone":"+1 713 667 4069",
    "sg:postcode":"77401",
    "sg:province":"TX",
    "wof:name":"Popular Enterprises Inc",
    "wof:placetype":"venue"
},
  "geometry": {"coordinates":[-95.448825,29.691511],"type":"Point"}
}