{
  "type": "Feature",
  "properties": {
    "iso:country":"US",
    "sg:address":"3526 FM 528",
    "sg:city":"Friendswood",
    "sg:classifiers":[
        {
            "category":"Building & Trades",
            "subcategory":"Pest Control",
            "type":"Services"
        }
    ],
    "sg:phone":"+1 281 332 0604",
    "sg:postcode":"77546",
    "sg:province":"TX",
    "wof:name":"PMR",
    "wof:placetype":"venue"
},
  "geometry": {"coordinates":[-95.167115,29.521812],"type":"Point"}
}