{
  "type": "Feature",
  "properties": {
    "iso:country":"US",
    "sg:address":"207 W 3rd St",
    "sg:city":"Mt Pleasant",
    "sg:classifiers":[
        {
            "category":"Professional",
            "type":"Services"
        }
    ],
    "sg:phone":"+1 903 572 4871",
    "sg:postcode":"75455",
    "sg:province":"TX",
    "wof:name":"J & A Management Svc",
    "wof:placetype":"venue"
},
  "geometry": {"coordinates":[-94.970444,33.15826],"type":"Point"}
}