{
  "type": "Feature",
  "properties": {
    "iso:country":"US",
    "sg:address":"2829 Liberty Dr",
    "sg:city":"Corsicana",
    "sg:classifiers":[
        {
            "category":"Freight",
            "type":"Transportation"
        }
    ],
    "sg:phone":"+1 903 874 5413",
    "sg:postcode":"75110",
    "sg:province":"TX",
    "sg:tags":[
        "waste",
        "management"
    ],
    "wof:name":"Thomas Disposal Service",
    "wof:placetype":"venue"
},
  "geometry": {"coordinates":[-96.521641,32.035516],"type":"Point"}
}