{
  "type": "Feature",
  "properties": {
    "iso:country":"US",
    "sg:address":"1805 de Charles St",
    "sg:city":"Tyler",
    "sg:classifiers":[
        {
            "category":"Manufacturing",
            "subcategory":"Motor Vehicles & Parts",
            "type":"Manufacturing & Wholesale Goods"
        }
    ],
    "sg:phone":"+1 903 597 9558",
    "sg:postcode":"75701",
    "sg:province":"TX",
    "sg:tags":[
        "body",
        "mfg"
    ],
    "wof:name":"M & M Specialties",
    "wof:placetype":"venue"
},
  "geometry": {"coordinates":[-95.280008,32.312943],"type":"Point"}
}