{
  "type": "Feature",
  "properties": {
    "iso:country":"US",
    "sg:address":"10502 Garland Rd",
    "sg:city":"Dallas",
    "sg:classifiers":[
        {
            "category":"Autos & Motor Vehicles",
            "subcategory":"Auto Supplies",
            "type":"Retail Goods"
        }
    ],
    "sg:phone":"+1 214 328 3217",
    "sg:postcode":"75218",
    "sg:province":"TX",
    "sg:tags":[
        "tire"
    ],
    "sg:website":"www.firestonecompleteautocare.com",
    "wof:name":"Firestone Tire & Service Centers",
    "wof:placetype":"venue"
},
  "geometry": {"coordinates":[-96.690399,32.843102],"type":"Point"}
}