{
  "type": "Feature",
  "properties": {
    "iso:country":"US",
    "sg:address":"607 Corsicana Hwy",
    "sg:city":"Hillsboro",
    "sg:classifiers":[
        {
            "category":"Autos & Motor Vehicles",
            "subcategory":"Automobile Sales",
            "type":"Retail Goods"
        }
    ],
    "sg:phone":"+1 254 582 9051",
    "sg:postcode":"76645",
    "sg:province":"TX",
    "sg:tags":[
        "used"
    ],
    "wof:name":"Reid Motor Co",
    "wof:placetype":"venue"
},
  "geometry": {"coordinates":[-97.11968899999999,32.006411],"type":"Point"}
}