{
  "type": "Feature",
  "properties": {
    "iso:country":"US",
    "sg:address":"3192 FM 555",
    "sg:city":"Gilmer",
    "sg:classifiers":[
        {
            "category":"Shopping",
            "subcategory":"Bicycles & Sporting Goods",
            "type":"Retail Goods"
        }
    ],
    "sg:phone":"+1 903 797 6734",
    "sg:postcode":"75645",
    "sg:province":"TX",
    "wof:name":"H&T Gun Shop",
    "wof:placetype":"venue"
},
  "geometry": {"coordinates":[-94.841757,32.770473],"type":"Point"}
}