{
  "type": "Feature",
  "properties": {
    "iso:country":"US",
    "sg:address":"500 E 3rd St",
    "sg:city":"Pecos",
    "sg:phone":"+1 432 445 4069",
    "sg:postcode":"79772",
    "sg:province":"TX",
    "wof:name":"Desert Rental & Sales",
    "wof:placetype":"venue"
},
  "geometry": {"coordinates":[-103.499352,31.42417],"type":"Point"}
}