{
  "type": "Feature",
  "properties": {
    "iso:country":"US",
    "sg:address":"105 Oxford St",
    "sg:city":"Tomball",
    "sg:classifiers":[
        {
            "category":"Real Estate",
            "subcategory":"Architect",
            "type":"Services"
        }
    ],
    "sg:phone":"+1 281 357 8565",
    "sg:postcode":"77375",
    "sg:province":"TX",
    "sg:tags":[
        "architects'",
        "specification",
        "construction",
        "builders'",
        "architectural"
    ],
    "wof:name":"Wheeler's Works",
    "wof:placetype":"venue"
},
  "geometry": {"coordinates":[-95.615216,30.100233],"type":"Point"}
}