{
  "type": "Feature",
  "properties": {
    "iso:country":"US",
    "sg:address":"5562 Gasmer Dr",
    "sg:city":"Houston",
    "sg:classifiers":[
        {
            "category":"Building & Trades",
            "subcategory":"Equipment Rental",
            "type":"Services"
        }
    ],
    "sg:phone":"+1 713 721 3700",
    "sg:postcode":"77035",
    "sg:province":"TX",
    "sg:tags":[
        "party",
        "supply"
    ],
    "wof:name":"Affordable Tents & Events",
    "wof:placetype":"venue"
},
  "geometry": {"coordinates":[-95.481326,29.651069],"type":"Point"}
}