{
  "type": "Feature",
  "properties": {
    "iso:country":"US",
    "sg:address":"3504 Eldorado Trl",
    "sg:city":"Austin",
    "sg:classifiers":[
        {
            "category":"Building & Trades",
            "subcategory":"Plumbing",
            "type":"Services"
        }
    ],
    "sg:phone":"+1 512 476 8379",
    "sg:postcode":"78739",
    "sg:province":"TX",
    "wof:name":"Sides Danny L Plumbing Company",
    "wof:placetype":"venue"
},
  "geometry": {"coordinates":[-97.865906,30.163112],"type":"Point"}
}