{
  "type": "Feature",
  "properties": {
    "iso:country":"US",
    "sg:address":"5320 Baton Rouge Blvd",
    "sg:city":"Frisco",
    "sg:classifiers":[
        {
            "category":"Manufacturing",
            "subcategory":"Rubber & Plastics",
            "type":"Manufacturing & Wholesale Goods"
        }
    ],
    "sg:phone":"+1 972 335 8684",
    "sg:postcode":"75035",
    "sg:province":"TX",
    "sg:tags":[
        "product",
        "fabricated",
        "mfg"
    ],
    "wof:name":"Pioneer National Latex Co",
    "wof:placetype":"venue"
},
  "geometry": {"coordinates":[-96.787277,33.122425],"type":"Point"}
}