{
  "type": "Feature",
  "properties": {
    "iso:country":"US",
    "sg:address":"10007 Sausalito Dr",
    "sg:city":"Austin",
    "sg:classifiers":[
        {
            "category":"Professional",
            "type":"Services"
        }
    ],
    "sg:phone":"+1 512 343 7268",
    "sg:postcode":"78759",
    "sg:province":"TX",
    "wof:name":"Susan Gilliam",
    "wof:placetype":"venue"
},
  "geometry": {"coordinates":[-97.76627000000001,30.406171],"type":"Point"}
}