{
  "type": "Feature",
  "properties": {
    "iso:country":"US",
    "sg:address":"4616 Colleyville Blvd",
    "sg:city":"Colleyville",
    "sg:classifiers":[
        {
            "category":"Professional",
            "subcategory":"Advertising",
            "type":"Services"
        }
    ],
    "sg:phone":"+1 817 833 4910",
    "sg:postcode":"76034",
    "sg:province":"TX",
    "sg:tags":[
        "mailing",
        "shipping"
    ],
    "wof:name":"Elizabeths Mailing Co",
    "wof:placetype":"venue"
},
  "geometry": {"coordinates":[-97.159059,32.878067],"type":"Point"}
}