{
  "type": "Feature",
  "properties": {
    "iso:country":"US",
    "sg:address":"6142 Reamer St",
    "sg:city":"Houston",
    "sg:classifiers":[
        {
            "category":"Wholesale",
            "subcategory":"Vending Machines",
            "type":"Manufacturing & Wholesale Goods"
        }
    ],
    "sg:phone":"+1 281 530 4351",
    "sg:postcode":"77074",
    "sg:province":"TX",
    "sg:tags":[
        "operator"
    ],
    "wof:name":"Daveco Vending",
    "wof:placetype":"venue"
},
  "geometry": {"coordinates":[-95.501845,29.680245],"type":"Point"}
}