{
  "type": "Feature",
  "properties": {
    "iso:country":"US",
    "sg:address":"6405 Steer Trl",
    "sg:city":"Austin",
    "sg:classifiers":[
        {
            "category":"Building & Trades",
            "subcategory":"Construction",
            "type":"Services"
        }
    ],
    "sg:phone":"+1 512 892 8698",
    "sg:postcode":"78749",
    "sg:province":"TX",
    "sg:tags":[
        "house",
        "stonework"
    ],
    "wof:name":"Stewart Stone Inc",
    "wof:placetype":"venue"
},
  "geometry": {"coordinates":[-97.85296700000001,30.230169],"type":"Point"}
}