{
  "type": "Feature",
  "properties": {
    "iso:country":"US",
    "sg:address":"4110 Brownwood Ln",
    "sg:city":"Arlington",
    "sg:classifiers":[
        {
            "category":"Professional",
            "subcategory":"Business Services",
            "type":"Services"
        }
    ],
    "sg:phone":"+1 817 478 7727",
    "sg:postcode":"76017",
    "sg:province":"TX",
    "wof:name":"Gooch Enterprise",
    "wof:placetype":"venue"
},
  "geometry": {"coordinates":[-97.174132,32.656659],"type":"Point"}
}