{
  "type": "Feature",
  "properties": {
    "iso:country":"US",
    "sg:address":"17513 Port Hood Dr",
    "sg:city":"Leander",
    "sg:classifiers":[
        {
            "category":"Building & Trades",
            "subcategory":"Construction",
            "type":"Services"
        }
    ],
    "sg:phone":"+1 512 832 6200",
    "sg:postcode":"78641",
    "sg:province":"TX",
    "sg:tags":[
        "screen",
        "enclosure"
    ],
    "sg:website":"www.austinpatio.com",
    "wof:name":"Austin Patio",
    "wof:placetype":"venue"
},
  "geometry": {"coordinates":[-97.82249,30.545452],"type":"Point"}
}