{
  "type": "Feature",
  "properties": {
    "iso:country":"US",
    "sg:address":"2152 Kazmeier Plz",
    "sg:city":"Bryan",
    "sg:classifiers":[
        {
            "category":"Professional",
            "type":"Services"
        }
    ],
    "sg:phone":"+1 979 268 8058",
    "sg:postcode":"77802",
    "sg:province":"TX",
    "sg:tags":[
        "establishment"
    ],
    "wof:name":"Hipster International",
    "wof:placetype":"venue"
},
  "geometry": {"coordinates":[-96.33259700000001,30.650401],"type":"Point"}
}