{
  "type": "Feature",
  "properties": {
    "iso:country":"US",
    "sg:address":"6425 Boeing Dr",
    "sg:city":"El Paso",
    "sg:classifiers":[
        {
            "category":"Building & Trades",
            "subcategory":"Construction",
            "type":"Services"
        }
    ],
    "sg:phone":"+1 915 633 6677",
    "sg:postcode":"79925",
    "sg:province":"TX",
    "sg:tags":[
        "water",
        "restoration",
        "damage"
    ],
    "wof:name":"Champs Professional Carpet",
    "wof:placetype":"venue"
},
  "geometry": {"coordinates":[-106.401591,31.791818],"type":"Point"}
}