{
  "type": "Feature",
  "properties": {
    "iso:country":"US",
    "sg:address":"1107 Shadow Lakes Blvd",
    "sg:city":"Allen",
    "sg:classifiers":[
        {
            "category":"Professional",
            "type":"Services"
        }
    ],
    "sg:phone":"+1 972 396 7805",
    "sg:postcode":"75002",
    "sg:province":"TX",
    "wof:name":"Russell Boyd",
    "wof:placetype":"venue"
},
  "geometry": {"coordinates":[-96.641088,33.089594],"type":"Point"}
}