{
  "type": "Feature",
  "properties": {
    "iso:country":"US",
    "sg:address":"15448 S Jasper Ave",
    "sg:city":"Odessa",
    "sg:classifiers":[
        {
            "category":"Travel",
            "subcategory":"Hotels & Motels",
            "type":"Entertainment"
        }
    ],
    "sg:phone":"+1 432 580 5880",
    "sg:postcode":"79766",
    "sg:province":"TX",
    "sg:tags":[
        "breakfast",
        "accommodation",
        "bed"
    ],
    "wof:name":"K-Bar Ranch Hunting Lodge",
    "wof:placetype":"venue"
},
  "geometry": {"coordinates":[-102.407886,31.676185],"type":"Point"}
}