{
  "type": "Feature",
  "properties": {
    "iso:country":"US",
    "sg:address":"5410 Boca Raton Dr",
    "sg:city":"Dallas",
    "sg:classifiers":[
        {
            "category":"Real Estate",
            "subcategory":"Real Estate Agent",
            "type":"Services"
        }
    ],
    "sg:phone":"+1 214 692 9359",
    "sg:postcode":"75229",
    "sg:province":"TX",
    "sg:tags":[
        "consultant"
    ],
    "wof:name":"Centex Investments Inc",
    "wof:placetype":"venue"
},
  "geometry": {"coordinates":[-96.816361,32.904475],"type":"Point"}
}