{
  "type": "Feature",
  "properties": {
    "iso:country":"US",
    "sg:address":"803 Tirado St",
    "sg:city":"Austin",
    "sg:classifiers":[
        {
            "category":"Real Estate",
            "subcategory":"Real Estate Operator",
            "type":"Services"
        }
    ],
    "sg:phone":"+1 512 459 3333",
    "sg:postcode":"78752",
    "sg:province":"TX",
    "sg:tags":[
        "apartment"
    ],
    "wof:name":"Highland Village Apartments",
    "wof:placetype":"venue"
},
  "geometry": {"coordinates":[-97.70781599999999,30.322889],"type":"Point"}
}