{
  "type": "Feature",
  "properties": {
    "iso:country":"US",
    "sg:address":"14702 S Post Oak Rd",
    "sg:city":"Houston",
    "sg:classifiers":[
        {
            "category":"Travel",
            "subcategory":"Hotels & Motels",
            "type":"Entertainment"
        }
    ],
    "sg:phone":"+1 713 413 3200",
    "sg:postcode":"77045",
    "sg:province":"TX",
    "wof:name":"Post Oak Inn",
    "wof:placetype":"venue"
},
  "geometry": {"coordinates":[-95.46520200000001,29.613501],"type":"Point"}
}