{
  "type": "Feature",
  "properties": {
    "iso:country":"US",
    "sg:address":"4316 Cedar Springs Rd",
    "sg:city":"Dallas",
    "sg:classifiers":[
        {
            "category":"Building & Trades",
            "subcategory":"Construction",
            "type":"Services"
        }
    ],
    "sg:phone":"+1 214 904 8986",
    "sg:postcode":"75219",
    "sg:province":"TX",
    "sg:tags":[
        "home",
        "new",
        "family",
        "contractor"
    ],
    "wof:name":"Guido Carmen Carl Bldr & Desgr",
    "wof:placetype":"venue"
},
  "geometry": {"coordinates":[-96.815918,32.814817],"type":"Point"}
}