{
  "type": "Feature",
  "properties": {
    "iso:country":"US",
    "sg:address":"500 E Tom Landry St",
    "sg:city":"Mission",
    "sg:classifiers":[
        {
            "category":"Government",
            "subcategory":"Fire Station",
            "type":"Public Place"
        }
    ],
    "sg:phone":"+1 956 580 8705",
    "sg:postcode":"78572",
    "sg:province":"TX",
    "sg:tags":[
        "department"
    ],
    "wof:name":"Mission Fire Dept",
    "wof:placetype":"venue"
},
  "geometry": {"coordinates":[-98.31994,26.215161],"type":"Point"}
}