{
  "type": "Feature",
  "properties": {
    "iso:country":"US",
    "sg:address":"7905 S Ratliff Rd",
    "sg:city":"San Angelo",
    "sg:classifiers":[
        {
            "category":"Wholesale",
            "subcategory":"Farm Supplies",
            "type":"Manufacturing & Wholesale Goods"
        }
    ],
    "sg:phone":"+1 325 651 7280",
    "sg:postcode":"76904",
    "sg:province":"TX",
    "sg:tags":[
        "livestock"
    ],
    "wof:name":"Hudson Livestock Suplmt Inc",
    "wof:placetype":"venue"
},
  "geometry": {"coordinates":[-100.45219899999999,31.363732],"type":"Point"}
}