{
  "type": "Feature",
  "properties": {
    "iso:country":"US",
    "sg:address":"6932 US Hwy 181",
    "sg:city":"Floresville",
    "sg:classifiers":[
        {
            "category":"Home & Garden",
            "subcategory":"Garden Supply",
            "type":"Retail Goods"
        }
    ],
    "sg:phone":"+1 830 216 2401",
    "sg:postcode":"78114",
    "sg:province":"TX",
    "sg:tags":[
        "nurseryman"
    ],
    "wof:name":"Green Thumb Nursery",
    "wof:placetype":"venue"
},
  "geometry": {"coordinates":[-98.2527,29.235307],"type":"Point"}
}