{
  "type": "Feature",
  "properties": {
    "iso:country":"US",
    "sg:address":"5902 Royalton St",
    "sg:city":"Houston",
    "sg:classifiers":[
        {
            "category":"Building & Trades",
            "subcategory":"Construction",
            "type":"Services"
        }
    ],
    "sg:phone":"+1 713 349 0848",
    "sg:postcode":"77081",
    "sg:province":"TX",
    "sg:tags":[
        "contractor"
    ],
    "wof:name":"Houston Cabinets",
    "wof:placetype":"venue"
},
  "geometry": {"coordinates":[-95.472956,29.717662],"type":"Point"}
}