{
  "type": "Feature",
  "properties": {
    "iso:country":"US",
    "sg:address":"6060 Alexis Dr",
    "sg:city":"Dallas",
    "sg:classifiers":[
        {
            "category":"Retail",
            "subcategory":"Car Wash",
            "type":"Services"
        }
    ],
    "sg:phone":"+1 972 960 2896",
    "sg:postcode":"75254",
    "sg:province":"TX",
    "wof:name":"Simoniz Car Wash",
    "wof:placetype":"venue"
},
  "geometry": {"coordinates":[-96.8013,32.949699],"type":"Point"}
}