{
  "type": "Feature",
  "properties": {
    "iso:country":"US",
    "sg:address":"6614 Coachgate Dr",
    "sg:city":"Spring",
    "sg:classifiers":[
        {
            "category":"Building & Trades",
            "subcategory":"Construction",
            "type":"Services"
        }
    ],
    "sg:phone":"+1 281 353 3167",
    "sg:postcode":"77373",
    "sg:province":"TX",
    "sg:tags":[
        "house"
    ],
    "wof:name":"Advance Builders",
    "wof:placetype":"venue"
},
  "geometry": {"coordinates":[-95.329106,30.04159],"type":"Point"}
}