{
  "type": "Feature",
  "properties": {
    "iso:country":"US",
    "sg:address":"6700 Snider Plz",
    "sg:city":"Dallas",
    "sg:classifiers":[
        {
            "category":"Real Estate",
            "subcategory":"Real Estate Agent",
            "type":"Services"
        }
    ],
    "sg:phone":"+1 214 363 0178",
    "sg:postcode":"75205",
    "sg:province":"TX",
    "wof:name":"Plazaco Ltd",
    "wof:placetype":"venue"
},
  "geometry": {"coordinates":[-96.78776999999999,32.848487],"type":"Point"}
}