{
  "type": "Feature",
  "properties": {
    "iso:country":"US",
    "sg:address":"203 Starnes St",
    "sg:city":"Grapevine",
    "sg:classifiers":[
        {
            "category":"Health Services",
            "subcategory":"Chiropractor",
            "type":"Services"
        }
    ],
    "sg:phone":"+1 817 442 9504",
    "sg:postcode":"76051",
    "sg:province":"TX",
    "wof:name":"Neighborhood Chiropractic",
    "wof:placetype":"venue"
},
  "geometry": {"coordinates":[-97.07641599999999,32.942011],"type":"Point"}
}