{
  "type": "Feature",
  "properties": {
    "iso:country":"US",
    "sg:address":"4101 Airport Fwy",
    "sg:city":"Bedford",
    "sg:classifiers":[
        {
            "category":"Wholesale",
            "subcategory":"Machinery & Supplies",
            "type":"Manufacturing & Wholesale Goods"
        }
    ],
    "sg:phone":"+1 817 540 1224",
    "sg:postcode":"76021",
    "sg:province":"TX",
    "sg:tags":[
        "salon",
        "beauty"
    ],
    "wof:name":"Armstrong Mc Call Beauty Supl",
    "wof:placetype":"venue"
},
  "geometry": {"coordinates":[-97.10029299999999,32.838043],"type":"Point"}
}