{
  "type": "Feature",
  "properties": {
    "iso:country":"US",
    "sg:address":"401 W Belknap St",
    "sg:city":"Fort Worth",
    "sg:classifiers":[
        {
            "category":"Government",
            "subcategory":"Court House",
            "type":"Public Place"
        }
    ],
    "sg:phone":"+1 817 884 1400",
    "sg:postcode":"76102",
    "sg:province":"TX",
    "sg:tags":[
        "state",
        "system"
    ],
    "wof:name":"Tarrant Cnty - Cnty At Law Crt",
    "wof:placetype":"venue"
},
  "geometry": {"coordinates":[-97.336383,32.756344],"type":"Point"}
}