{
  "type": "Feature",
  "properties": {
    "iso:country":"US",
    "sg:address":"220 W Veterans Memorial Blvd",
    "sg:city":"Killeen",
    "sg:classifiers":[
        {
            "category":"Manufacturing",
            "subcategory":"Printing",
            "type":"Manufacturing & Wholesale Goods"
        }
    ],
    "sg:phone":"+1 254 680 3345",
    "sg:postcode":"76541",
    "sg:province":"TX",
    "sg:tags":[
        "book"
    ],
    "wof:name":"Mistress of Games LLC",
    "wof:placetype":"venue"
},
  "geometry": {"coordinates":[-97.73332499999999,31.11823],"type":"Point"}
}