{
  "type": "Feature",
  "properties": {
    "iso:country":"US",
    "sg:address":"2417 County Road 316D",
    "sg:city":"Cleburne",
    "sg:classifiers":[
        {
            "category":"Organizations",
            "subcategory":"Religious Organization",
            "type":"Services"
        }
    ],
    "sg:phone":"+1 817 645 6878",
    "sg:postcode":"76031",
    "sg:province":"TX",
    "wof:name":"Cross Ministries",
    "wof:placetype":"venue"
},
  "geometry": {"coordinates":[-97.342929,32.365768],"type":"Point"}
}