{
  "type": "Feature",
  "properties": {
    "iso:country":"US",
    "sg:address":"4005 Diane Dr",
    "sg:city":"Beaumont",
    "sg:classifiers":[
        {
            "category":"Building & Trades",
            "subcategory":"Pest Control",
            "type":"Services"
        }
    ],
    "sg:phone":"+1 409 899 5595",
    "sg:postcode":"77706",
    "sg:province":"TX",
    "wof:name":"Granger's Exterminators",
    "wof:placetype":"venue"
},
  "geometry": {"coordinates":[-94.14389199999999,30.107843],"type":"Point"}
}