{
  "type": "Feature",
  "properties": {
    "iso:country":"US",
    "sg:address":"10022 W Bellfort St",
    "sg:city":"Houston",
    "sg:classifiers":[
        {
            "category":"Home & Garden",
            "subcategory":"Garden Supply",
            "type":"Retail Goods"
        }
    ],
    "sg:phone":"+1 281 561 5771",
    "sg:postcode":"77031",
    "sg:province":"TX",
    "sg:tags":[
        "durable"
    ],
    "wof:name":"Services By Sykes",
    "wof:placetype":"venue"
},
  "geometry": {"coordinates":[-95.555222,29.65279],"type":"Point"}
}