{
  "type": "Feature",
  "properties": {
    "iso:country":"US",
    "sg:address":"14047 Susie Ln",
    "sg:city":"Alvin",
    "sg:classifiers":[
        {
            "category":"Professional",
            "subcategory":"Lawyer & Legal Services",
            "type":"Services"
        }
    ],
    "sg:phone":"+1 281 331 8650",
    "sg:postcode":"77511",
    "sg:province":"TX",
    "sg:tags":[
        "attorney"
    ],
    "wof:name":"James M Bennett Attorney-Law",
    "wof:placetype":"venue"
},
  "geometry": {"coordinates":[-95.316442,29.367632],"type":"Point"}
}