{
  "type": "Feature",
  "properties": {
    "iso:country":"US",
    "sg:address":"419 Co Rd 174",
    "sg:city":"Gainesville",
    "sg:classifiers":[
        {
            "category":"Professional",
            "subcategory":"Accounting & Tax Preparation",
            "type":"Services"
        }
    ],
    "sg:phone":"+1 940 665 3561",
    "sg:postcode":"76240",
    "sg:province":"TX",
    "sg:tags":[
        "accountant"
    ],
    "wof:name":"James M Davis PC",
    "wof:placetype":"venue"
},
  "geometry": {"coordinates":[-97.036911,33.639699],"type":"Point"}
}