{
  "type": "Feature",
  "properties": {
    "iso:country":"US",
    "sg:address":"8570 State Hwy 6",
    "sg:city":"Houston",
    "sg:classifiers":[
        {
            "category":"Personal",
            "subcategory":"Beauty Salon",
            "type":"Services"
        }
    ],
    "sg:phone":"+1 281 855 6605",
    "sg:postcode":"77095",
    "sg:province":"TX",
    "sg:tags":[
        "shop"
    ],
    "wof:name":"Fantastic Sam's",
    "wof:placetype":"venue"
},
  "geometry": {"coordinates":[-95.633071,29.903739],"type":"Point"}
}