{
  "type": "Feature",
  "properties": {
    "iso:country":"US",
    "sg:address":"9535 Forest Ln",
    "sg:city":"Dallas",
    "sg:classifiers":[
        {
            "category":"Health Services",
            "subcategory":"Clinic",
            "type":"Services"
        },
        {
            "category":"Health Services",
            "subcategory":"Health Practitioner",
            "type":"Services"
        }
    ],
    "sg:phone":"+1 972 705 0115",
    "sg:postcode":"75243",
    "sg:province":"TX",
    "sg:tags":[
        "home",
        "care"
    ],
    "wof:name":"Trans Healthcare Inc",
    "wof:placetype":"venue"
},
  "geometry": {"coordinates":[-96.72520299999999,32.909722],"type":"Point"}
}