{
  "type": "Feature",
  "properties": {
    "iso:country":"US",
    "sg:address":"18095 Briarcrest",
    "sg:city":"Flint",
    "sg:classifiers":[
        {
            "category":"Shopping",
            "subcategory":"Clothing, Apparel, & Fashions",
            "type":"Retail Goods"
        }
    ],
    "sg:phone":"+1 903 894 7517",
    "sg:postcode":"75762",
    "sg:province":"TX",
    "wof:name":"Second Act Resale Boutique",
    "wof:placetype":"venue"
},
  "geometry": {"coordinates":[-95.35450299999999,32.221345],"type":"Point"}
}