{
  "type": "Feature",
  "properties": {
    "iso:country":"US",
    "sg:address":"7585 S Broadway Ave",
    "sg:city":"Tyler",
    "sg:classifiers":[
        {
            "category":"Banks & Credit Unions",
            "subcategory":"Bank",
            "type":"Services"
        },
        {
            "category":"Banks & Credit Unions",
            "subcategory":"Financial Services",
            "type":"Services"
        }
    ],
    "sg:phone":"+1 800 734 4667",
    "sg:postcode":"75703",
    "sg:province":"TX",
    "sg:tags":[
        "saving",
        "loan",
        "commercial"
    ],
    "sg:website":"http://www.regionsbank.com",
    "wof:name":"Regions Bank",
    "wof:placetype":"venue"
},
  "geometry": {"coordinates":[-95.306845,32.273503],"type":"Point"}
}