{
  "type": "Feature",
  "properties": {
    "iso:country":"US",
    "sg:address":"5212 Village Ln",
    "sg:city":"Fort Worth",
    "sg:classifiers":[
        {
            "category":"Professional",
            "type":"Services"
        }
    ],
    "sg:phone":"+1 817 531 0603",
    "sg:postcode":"76119",
    "sg:province":"TX",
    "wof:name":"Nina Hogan",
    "wof:placetype":"venue"
},
  "geometry": {"coordinates":[-97.260215,32.683143],"type":"Point"}
}