{
  "type": "Feature",
  "properties": {
    "iso:country":"US",
    "sg:address":"301 N Wesley Dr",
    "sg:city":"League City",
    "sg:classifiers":[
        {
            "category":"Professional",
            "subcategory":"Art Services",
            "type":"Services"
        }
    ],
    "sg:phone":"+1 832 978 5708",
    "sg:postcode":"77573",
    "sg:province":"TX",
    "sg:tags":[
        "graphic",
        "designer"
    ],
    "wof:name":"Burke Creative",
    "wof:placetype":"venue"
},
  "geometry": {"coordinates":[-95.111648,29.506268],"type":"Point"}
}