{
  "type": "Feature",
  "properties": {
    "iso:country":"US",
    "sg:address":"1708 S High St",
    "sg:city":"Longview",
    "sg:classifiers":[
        {
            "category":"Insurance",
            "subcategory":"Insurance Agent",
            "type":"Services"
        }
    ],
    "sg:phone":"+1 903 758 1432",
    "sg:postcode":"75602",
    "sg:province":"TX",
    "wof:name":"State Farm Insurance",
    "wof:placetype":"venue"
},
  "geometry": {"coordinates":[-94.741845,32.471755],"type":"Point"}
}