{
  "type": "Feature",
  "properties": {
    "iso:country":"US",
    "sg:address":"225 Shadow Valley Rd",
    "sg:city":"Whitesboro",
    "sg:classifiers":[
        {
            "category":"Farming",
            "subcategory":"Livestock Farm",
            "type":"Manufacturing & Wholesale Goods"
        }
    ],
    "sg:phone":"+1 903 564 3985",
    "sg:postcode":"76273",
    "sg:province":"TX",
    "wof:name":"Docs Funny Farm",
    "wof:placetype":"venue"
},
  "geometry": {"coordinates":[-96.91101399999999,33.608422],"type":"Point"}
}