{
  "type": "Feature",
  "properties": {
    "iso:country":"US",
    "sg:address":"220 Justin Rd",
    "sg:city":"Plano",
    "sg:classifiers":[
        {
            "category":"Real Estate",
            "subcategory":"Real Estate Agent",
            "type":"Services"
        }
    ],
    "sg:phone":"+1 972 596 6300",
    "sg:postcode":"75094",
    "sg:province":"TX",
    "wof:name":"Titan Marketing International",
    "wof:placetype":"venue"
},
  "geometry": {"coordinates":[-96.63011,33.015159],"type":"Point"}
}