{
  "type": "Feature",
  "properties": {
    "iso:country":"US",
    "sg:address":"1524 E Los Ebanos Blvd",
    "sg:city":"Brownsville",
    "sg:classifiers":[
        {
            "category":"Building & Trades",
            "subcategory":"Construction",
            "type":"Services"
        }
    ],
    "sg:phone":"+1 956 546 3779",
    "sg:postcode":"78520",
    "sg:province":"TX",
    "sg:tags":[
        "residential",
        "general",
        "contractor"
    ],
    "wof:name":"Fitzpatrick Construction Inc",
    "wof:placetype":"venue"
},
  "geometry": {"coordinates":[-97.49971499999999,25.931501],"type":"Point"}
}