{
  "type": "Feature",
  "properties": {
    "iso:country":"US",
    "sg:address":"1501 Post Office St",
    "sg:city":"Galveston",
    "sg:classifiers":[
        {
            "category":"Organizations",
            "subcategory":"Religious Organization",
            "type":"Services"
        }
    ],
    "sg:phone":"+1 409 762 1785",
    "sg:postcode":"77550",
    "sg:province":"TX",
    "sg:tags":[
        "church"
    ],
    "wof:name":"Galveston Friends Church",
    "wof:placetype":"venue"
},
  "geometry": {"coordinates":[-94.785493,29.306618],"type":"Point"}
}