{
  "type": "Feature",
  "properties": {
    "iso:country":"US",
    "sg:address":"500 State Hwy 1604",
    "sg:city":"San Antonio",
    "sg:classifiers":[
        {
            "category":"Professional",
            "subcategory":"Management & Consulting",
            "type":"Services"
        }
    ],
    "sg:phone":"+1 210 545 3663",
    "sg:postcode":"78232",
    "sg:province":"TX",
    "wof:name":"R Hakim Corp",
    "wof:placetype":"venue"
},
  "geometry": {"coordinates":[-98.488384,29.609116],"type":"Point"}
}