{
  "type": "Feature",
  "properties": {
    "iso:country":"US",
    "sg:address":"404 S 2nd St",
    "sg:city":"Canadian",
    "sg:classifiers":[
        {
            "category":"Food & Beverages",
            "subcategory":"Groceries & Convenience Stores",
            "type":"Retail Goods"
        }
    ],
    "sg:phone":"+1 806 323 6141",
    "sg:postcode":"79014",
    "sg:province":"TX",
    "wof:name":"Pay N Save 20",
    "wof:placetype":"venue"
},
  "geometry": {"coordinates":[-100.38746999999999,35.912702],"type":"Point"}
}