{
  "type": "Feature",
  "properties": {
    "iso:country":"US",
    "sg:address":"5001 S Fort Hood St",
    "sg:city":"Killeen",
    "sg:classifiers":[
        {
            "category":"Personal",
            "type":"Services"
        },
        {
            "category":"Professional",
            "subcategory":"Business Services",
            "type":"Services"
        }
    ],
    "sg:phone":"+1 254 634 5200",
    "sg:postcode":"76542",
    "sg:province":"TX",
    "sg:tags":[
        "auction",
        "liquidation",
        "appraisal",
        "estates-sales"
    ],
    "sg:website":"http://www.associatedauctioneertx.com",
    "wof:name":"Fisher John Auctioneer",
    "wof:placetype":"venue"
},
  "geometry": {"coordinates":[-97.75936400000001,31.075765],"type":"Point"}
}