{
  "type": "Feature",
  "properties": {
    "iso:country":"US",
    "sg:address":"129 Bandera Rd",
    "sg:city":"San Antonio",
    "sg:classifiers":[
        {
            "category":"Restaurant",
            "type":"Food & Drink"
        }
    ],
    "sg:menulink":"http://www.allmenus.com/tx/san-antonio/94354-dominos-pizza/menu/",
    "sg:phone":"+1 210 733 3030",
    "sg:postcode":"78228",
    "sg:province":"TX",
    "sg:tags":[
        "american",
        "wing",
        "pizza"
    ],
    "wof:name":"Domino's Pizza",
    "wof:placetype":"venue"
},
  "geometry": {"coordinates":[-98.542351,29.447507],"type":"Point"}
}