{
  "type": "Feature",
  "properties": {
    "iso:country":"US",
    "sg:address":"124 E Leona St",
    "sg:city":"Dilley",
    "sg:classifiers":[
        {
            "category":"Education",
            "subcategory":"School",
            "type":"Public Place"
        }
    ],
    "sg:phone":"+1 830 965 1324",
    "sg:postcode":"78017",
    "sg:province":"TX",
    "wof:name":"Faith Christian Academy",
    "wof:placetype":"venue"
},
  "geometry": {"coordinates":[-99.16914300000001,28.667115],"type":"Point"}
}