{
  "type": "Feature",
  "properties": {
    "iso:country":"US",
    "sg:address":"2805 Palmer Hwy",
    "sg:city":"Texas City",
    "sg:classifiers":[
        {
            "category":"Restaurant",
            "type":"Food & Drink"
        }
    ],
    "sg:menulink":"http://www.allmenus.com/tx/texas-city-league-city/192102-wendys/menu/",
    "sg:phone":"+1 409 945 4663",
    "sg:postcode":"77590",
    "sg:province":"TX",
    "sg:tags":[
        "burger",
        "american",
        "soup"
    ],
    "wof:name":"Wendy's",
    "wof:placetype":"venue"
},
  "geometry": {"coordinates":[-94.93580900000001,29.394964],"type":"Point"}
}