{
  "type": "Feature",
  "properties": {
    "iso:country":"US",
    "sg:address":"13106 Park Manor St",
    "sg:city":"San Antonio",
    "sg:classifiers":[
        {
            "category":"Travel",
            "subcategory":"Travel Agent",
            "type":"Entertainment"
        }
    ],
    "sg:phone":"+1 210 366 0835",
    "sg:postcode":"78230",
    "sg:province":"TX",
    "sg:tags":[
        "agency",
        "bureau"
    ],
    "wof:name":"Cruise & Tour Ctr Inc",
    "wof:placetype":"venue"
},
  "geometry": {"coordinates":[-98.55773499999999,29.562234],"type":"Point"}
}