{
  "type": "Feature",
  "properties": {
    "iso:country":"US",
    "sg:address":"8901 Diana Dr",
    "sg:city":"El Paso",
    "sg:classifiers":[
        {
            "category":"Food & Beverages",
            "subcategory":"Groceries & Convenience Stores",
            "type":"Retail Goods"
        }
    ],
    "sg:phone":"+1 915 757 0818",
    "sg:postcode":"79904",
    "sg:province":"TX",
    "wof:name":"7-Eleven",
    "wof:placetype":"venue"
},
  "geometry": {"coordinates":[-106.423198,31.866062],"type":"Point"}
}