{
  "type": "Feature",
  "properties": {
    "iso:country":"US",
    "sg:address":"905 W Viejo Dr",
    "sg:city":"Friendswood",
    "sg:classifiers":[
        {
            "category":"Shopping",
            "subcategory":"Hobbies, Toys, & Games",
            "type":"Retail Goods"
        }
    ],
    "sg:phone":"+1 281 482 0969",
    "sg:postcode":"77546",
    "sg:province":"TX",
    "wof:name":"Kaididoscope Stained Glass",
    "wof:placetype":"venue"
},
  "geometry": {"coordinates":[-95.172567,29.48657],"type":"Point"}
}