{
  "type": "Feature",
  "properties": {
    "iso:country":"US",
    "sg:address":"6141 Griggs Rd",
    "sg:city":"Houston",
    "sg:classifiers":[
        {
            "category":"Personal",
            "subcategory":"Beauty Salon",
            "type":"Services"
        }
    ],
    "sg:phone":"+1 713 242 6881",
    "sg:postcode":"77023",
    "sg:province":"TX",
    "wof:name":"Lauren's Beauty Salon",
    "wof:placetype":"venue"
},
  "geometry": {"coordinates":[-95.316097,29.702319],"type":"Point"}
}