{
  "type": "Feature",
  "properties": {
    "iso:country":"US",
    "sg:address":"1005 Keiss Dr",
    "sg:city":"Spicewood",
    "sg:classifiers":[
        {
            "category":"Building & Trades",
            "subcategory":"Electrical",
            "type":"Services"
        }
    ],
    "sg:phone":"+1 512 264 8383",
    "sg:postcode":"78669",
    "sg:province":"TX",
    "sg:tags":[
        "electrical",
        "contractor"
    ],
    "wof:name":"Gsd Electric",
    "wof:placetype":"venue"
},
  "geometry": {"coordinates":[-98.055916,30.400508],"type":"Point"}
}