{
  "type": "Feature",
  "properties": {
    "iso:country":"US",
    "sg:address":"14803 Carolina Falls Ln",
    "sg:city":"Cypress",
    "sg:classifiers":[
        {
            "category":"Manufacturing",
            "subcategory":"Printing",
            "type":"Manufacturing & Wholesale Goods"
        }
    ],
    "sg:phone":"+1 281 256 2675",
    "sg:postcode":"77433",
    "sg:province":"TX",
    "sg:tags":[
        "commercial"
    ],
    "wof:name":"Sandees Creations",
    "wof:placetype":"venue"
},
  "geometry": {"coordinates":[-95.730023,29.989354],"type":"Point"}
}