{
  "type": "Feature",
  "properties": {
    "iso:country":"US",
    "sg:address":"113 N 21st St",
    "sg:city":"Temple",
    "sg:classifiers":[
        {
            "category":"Building & Trades",
            "subcategory":"Construction",
            "type":"Services"
        }
    ],
    "sg:phone":"+1 254 770 1818",
    "sg:postcode":"76504",
    "sg:province":"TX",
    "sg:tags":[
        "home",
        "builder"
    ],
    "wof:name":"EDC Homes",
    "wof:placetype":"venue"
},
  "geometry": {"coordinates":[-97.351123,31.101687],"type":"Point"}
}