{
  "type": "Feature",
  "properties": {
    "iso:country":"US",
    "sg:address":"8830 High Haven Dr",
    "sg:city":"Houston",
    "sg:classifiers":[
        {
            "category":"Farming",
            "subcategory":"Livestock Farm",
            "type":"Manufacturing & Wholesale Goods"
        }
    ],
    "sg:phone":"+1 281 561 6112",
    "sg:postcode":"77083",
    "sg:province":"TX",
    "sg:tags":[
        "ranch",
        "feedlot",
        "beef",
        "cattle"
    ],
    "wof:name":"Stillwagon Ranch",
    "wof:placetype":"venue"
},
  "geometry": {"coordinates":[-95.65412000000001,29.682257],"type":"Point"}
}