{
  "type": "Feature",
  "properties": {
    "iso:country":"US",
    "sg:address":"2021 Grainger St",
    "sg:city":"Fort Worth",
    "sg:classifiers":[
        {
            "category":"Professional",
            "type":"Services"
        }
    ],
    "sg:phone":"+1 817 923 0004",
    "sg:postcode":"76110",
    "sg:province":"TX",
    "sg:tags":[
        "establishment"
    ],
    "wof:name":"MAJIC",
    "wof:placetype":"venue"
},
  "geometry": {"coordinates":[-97.33060999999999,32.721448],"type":"Point"}
}