{
  "type": "Feature",
  "properties": {
    "iso:country":"US",
    "sg:address":"2751 Civic Cir",
    "sg:city":"Amarillo",
    "sg:classifiers":[
        {
            "category":"Real Estate",
            "subcategory":"Real Estate Operator",
            "type":"Services"
        }
    ],
    "sg:phone":"+1 806 352 0731",
    "sg:postcode":"79109",
    "sg:province":"TX",
    "sg:tags":[
        "building",
        "nonresidential"
    ],
    "wof:name":"Alt Academy",
    "wof:placetype":"venue"
},
  "geometry": {"coordinates":[-101.867294,35.190618],"type":"Point"}
}