{
  "type": "Feature",
  "properties": {
    "iso:country":"US",
    "sg:address":"2105 S Ervay St",
    "sg:city":"Dallas",
    "sg:classifiers":[
        {
            "category":"Manufacturing",
            "subcategory":"Building Materials",
            "type":"Manufacturing & Wholesale Goods"
        }
    ],
    "sg:phone":"+1 214 421 9900",
    "sg:postcode":"75215",
    "sg:province":"TX",
    "wof:name":"Bechtold Custom Millwork",
    "wof:placetype":"venue"
},
  "geometry": {"coordinates":[-96.784297,32.76791],"type":"Point"}
}