{
  "type": "Feature",
  "properties": {
    "iso:country":"US",
    "sg:address":"4705 Ave H",
    "sg:city":"Rosenberg",
    "sg:classifiers":[
        {
            "category":"Banks & Credit Unions",
            "subcategory":"Bank",
            "type":"Services"
        }
    ],
    "sg:phone":"+1 281 232 7431",
    "sg:postcode":"77471",
    "sg:province":"TX",
    "sg:tags":[
        "financing"
    ],
    "wof:name":"Banner Finance Co",
    "wof:placetype":"venue"
},
  "geometry": {"coordinates":[-95.780546,29.567057],"type":"Point"}
}