{
  "type": "Feature",
  "properties": {
    "iso:country":"US",
    "sg:address":"104 Industrial Blvd",
    "sg:city":"Sugar Land",
    "sg:classifiers":[
        {
            "category":"Organizations",
            "subcategory":"Membership Organization",
            "type":"Services"
        }
    ],
    "sg:phone":"+1 281 313 8222",
    "sg:postcode":"77478",
    "sg:province":"TX",
    "sg:tags":[
        "athletic"
    ],
    "wof:name":"Texas Association-Basketball",
    "wof:placetype":"venue"
},
  "geometry": {"coordinates":[-95.60584900000001,29.626388],"type":"Point"}
}