{
  "type": "Feature",
  "properties": {
    "iso:country":"US",
    "sg:address":"934 Danforth Pl",
    "sg:city":"Arlington",
    "sg:classifiers":[
        {
            "category":"Communications",
            "subcategory":"Television Station",
            "type":"Services"
        }
    ],
    "sg:phone":"+1 817 472 6233",
    "sg:postcode":"76017",
    "sg:province":"TX",
    "wof:name":"Garrett Communications In",
    "wof:placetype":"venue"
},
  "geometry": {"coordinates":[-97.125387,32.649448],"type":"Point"}
}