{
  "type": "Feature",
  "properties": {
    "iso:country":"US",
    "sg:address":"PO Box 233",
    "sg:city":"Houston",
    "sg:classifiers":[
        {
            "category":"Professional",
            "subcategory":"Lawyer & Legal Services",
            "type":"Services"
        }
    ],
    "sg:phone":"+1 713 440 6900",
    "sg:postcode":"77001",
    "sg:province":"TX",
    "sg:website":"www.ursulahall.com",
    "wof:name":"Hall Ursula A Atty",
    "wof:placetype":"venue"
},
  "geometry": {"coordinates":[-95.361397,29.757999],"type":"Point"}
}