{
  "type": "Feature",
  "properties": {
    "iso:country":"US",
    "sg:address":"3203 Crestridge Dr",
    "sg:city":"Dallas",
    "sg:classifiers":[
        {
            "category":"Manufacturing",
            "subcategory":"Paper Products",
            "type":"Manufacturing & Wholesale Goods"
        }
    ],
    "sg:phone":"+1 972 686 1156",
    "sg:postcode":"75228",
    "sg:province":"TX",
    "wof:name":"Polyart-Arjobex America",
    "wof:placetype":"venue"
},
  "geometry": {"coordinates":[-96.660585,32.828721],"type":"Point"}
}