{
  "type": "Feature",
  "properties": {
    "iso:country":"US",
    "sg:address":"6310 Treadwell Blvd",
    "sg:city":"Austin",
    "sg:classifiers":[
        {
            "category":"Recreation",
            "subcategory":"Playground",
            "type":"Entertainment"
        }
    ],
    "sg:postcode":"78757",
    "sg:province":"TX",
    "sg:website":"www.gullettgeckos.org",
    "wof:name":"Gullett Elementary School Playground",
    "wof:placetype":"venue"
},
  "geometry": {"coordinates":[-97.748693,30.343558],"type":"Point"}
}