{
  "type": "Feature",
  "properties": {
    "iso:country":"US",
    "sg:address":"1020 Pecan Crossing Dr",
    "sg:city":"Desoto",
    "sg:classifiers":[
        {
            "category":"Real Estate",
            "subcategory":"Real Estate Services",
            "type":"Services"
        },
        {
            "category":"Real Estate",
            "subcategory":"Real Estate Operator",
            "type":"Services"
        }
    ],
    "sg:phone":"+1 972 224 9291",
    "sg:postcode":"75115",
    "sg:province":"TX",
    "sg:tags":[
        "vacancy",
        "apartment",
        "rental",
        "listing"
    ],
    "wof:name":"Cedar Green Living Center",
    "wof:placetype":"venue"
},
  "geometry": {"coordinates":[-96.827431,32.607159],"type":"Point"}
}