{
  "type": "Feature",
  "properties": {
    "iso:country":"US",
    "sg:address":"725 S Cuyler St",
    "sg:city":"Pampa",
    "sg:classifiers":[
        {
            "category":"Freight",
            "type":"Transportation"
        }
    ],
    "sg:phone":"+1 806 665 0984",
    "sg:postcode":"79065",
    "sg:province":"TX",
    "sg:tags":[
        "hauling",
        "trucking"
    ],
    "wof:name":"Koyote Trucking Co",
    "wof:placetype":"venue"
},
  "geometry": {"coordinates":[-100.956592,35.528855],"type":"Point"}
}