{
  "type": "Feature",
  "properties": {
    "iso:country":"US",
    "sg:address":"1030 E Highway 377",
    "sg:city":"Granbury",
    "sg:classifiers":[
        {
            "category":"Personal",
            "subcategory":"Beauty Salon",
            "type":"Services"
        },
        {
            "category":"Personal",
            "subcategory":"Barber",
            "type":"Services"
        }
    ],
    "sg:phone":"+1 817 579 8300",
    "sg:postcode":"76048",
    "sg:province":"TX",
    "sg:tags":[
        "hair",
        "accessory",
        "stylist",
        "supply"
    ],
    "sg:website":"http://www.greatclips.com/",
    "wof:name":"Great Clips",
    "wof:placetype":"venue"
},
  "geometry": {"coordinates":[-97.775175,32.4348],"type":"Point"}
}