{
  "type": "Feature",
  "properties": {
    "iso:country":"US",
    "sg:address":"108 E Ovilla Rd",
    "sg:city":"Red Oak",
    "sg:classifiers":[
        {
            "category":"Shopping",
            "subcategory":"Tobacco",
            "type":"Retail Goods"
        }
    ],
    "sg:phone":"+1 972 576 2150",
    "sg:postcode":"75154",
    "sg:province":"TX",
    "sg:tags":[
        "shop"
    ],
    "wof:name":"OVILLA TOBACCO",
    "wof:placetype":"venue"
},
  "geometry": {"coordinates":[-96.855919,32.531742],"type":"Point"}
}