{
  "type": "Feature",
  "properties": {
    "iso:country":"US",
    "sg:address":"1928 N Border Ave",
    "sg:city":"Tyler",
    "sg:classifiers":[
        {
            "category":"Professional",
            "type":"Services"
        }
    ],
    "sg:phone":"+1 903 597 2669",
    "sg:postcode":"75702",
    "sg:province":"TX",
    "wof:name":"Wakefield Sounds",
    "wof:placetype":"venue"
},
  "geometry": {"coordinates":[-95.306749,32.36933],"type":"Point"}
}