{
  "type": "Feature",
  "properties": {
    "iso:country":"US",
    "sg:address":"619 S Berry St",
    "sg:city":"Burkburnett",
    "sg:classifiers":[
        {
            "category":"Autos & Motor Vehicles",
            "subcategory":"Auto Supplies",
            "type":"Retail Goods"
        }
    ],
    "sg:phone":"+1 940 569 5615",
    "sg:postcode":"76354",
    "sg:province":"TX",
    "wof:name":"Bradley Tire Service",
    "wof:placetype":"venue"
},
  "geometry": {"coordinates":[-98.560787,34.083907],"type":"Point"}
}