{
  "type": "Feature",
  "properties": {
    "iso:country":"US",
    "sg:address":"508 E 4th St",
    "sg:city":"Lampasas",
    "sg:classifiers":[
        {
            "category":"Shopping",
            "type":"Retail Goods"
        }
    ],
    "sg:phone":"+1 512 556 6997",
    "sg:postcode":"76550",
    "sg:province":"TX",
    "sg:tags":[
        "art",
        "gallery",
        "dealer"
    ],
    "wof:name":"Fourth Street Gallery",
    "wof:placetype":"venue"
},
  "geometry": {"coordinates":[-98.177008,31.065239],"type":"Point"}
}