{
  "type": "Feature",
  "properties": {
    "iso:country":"US",
    "sg:address":"8541 W Bellfort St Ste K",
    "sg:city":"Houston",
    "sg:classifiers":[
        {
            "category":"Food & Beverages",
            "subcategory":"Liquor & Beverages",
            "type":"Retail Goods"
        }
    ],
    "sg:phone":"+1 713 981 5221",
    "sg:postcode":"77071",
    "sg:province":"TX",
    "sg:tags":[
        "beer",
        "spirit",
        "wine"
    ],
    "wof:name":"Kim's Warehouse",
    "wof:placetype":"venue"
},
  "geometry": {"coordinates":[-95.526703,29.6556],"type":"Point"}
}