{
  "type": "Feature",
  "properties": {
    "iso:country":"US",
    "sg:address":"2005 Bayberry Dr",
    "sg:city":"Little Elm",
    "sg:classifiers":[
        {
            "category":"Building & Trades",
            "subcategory":"Construction",
            "type":"Services"
        }
    ],
    "sg:phone":"+1 972 668 0174",
    "sg:postcode":"75068",
    "sg:province":"TX",
    "sg:tags":[
        "contractor"
    ],
    "wof:name":"D & D Solar Screens",
    "wof:placetype":"venue"
},
  "geometry": {"coordinates":[-96.905523,33.173298],"type":"Point"}
}