{
  "type": "Feature",
  "properties": {
    "iso:country":"US",
    "sg:address":"1411 Ebeling Dr",
    "sg:city":"Plainview",
    "sg:classifiers":[
        {
            "category":"Professional",
            "subcategory":"Advertising",
            "type":"Services"
        }
    ],
    "sg:phone":"+1 806 296 9747",
    "sg:postcode":"79072",
    "sg:province":"TX",
    "wof:name":"Wayne Keenum Specialty Advg",
    "wof:placetype":"venue"
},
  "geometry": {"coordinates":[-101.79206600000001,34.199567],"type":"Point"}
}