{
  "type": "Feature",
  "properties": {
    "iso:country":"US",
    "sg:address":"4305 Effie St",
    "sg:city":"Bellaire",
    "sg:classifiers":[
        {
            "category":"Professional",
            "subcategory":"Business Services",
            "type":"Services"
        }
    ],
    "sg:phone":"+1 713 668 3186",
    "sg:postcode":"77401",
    "sg:province":"TX",
    "wof:name":"Brite Star Enterprises",
    "wof:placetype":"venue"
},
  "geometry": {"coordinates":[-95.449184,29.695575],"type":"Point"}
}