{
  "type": "Feature",
  "properties": {
    "iso:country":"US",
    "sg:address":"10730 Barker Cypress Rd",
    "sg:city":"Cypress",
    "sg:classifiers":[
        {
            "category":"Retail",
            "subcategory":"Laundry & Dry Cleaning",
            "type":"Services"
        }
    ],
    "sg:phone":"+1 281 213 3808",
    "sg:postcode":"77433",
    "sg:province":"TX",
    "sg:tags":[
        "power"
    ],
    "wof:name":"KB Master Cleaners",
    "wof:placetype":"venue"
},
  "geometry": {"coordinates":[-95.682861,29.933203],"type":"Point"}
}