{
  "type": "Feature",
  "properties": {
    "iso:country":"US",
    "sg:address":"116 Main St",
    "sg:city":"Sealy",
    "sg:classifiers":[
        {
            "category":"Professional",
            "subcategory":"Business Services",
            "type":"Services"
        }
    ],
    "sg:phone":"+1 979 877 0734",
    "sg:postcode":"77474",
    "sg:province":"TX",
    "wof:name":"Images",
    "wof:placetype":"venue"
},
  "geometry": {"coordinates":[-96.152282,29.782011],"type":"Point"}
}