{
  "type": "Feature",
  "properties": {
    "iso:country":"US",
    "sg:address":"3447 Dalworth St",
    "sg:city":"Arlington",
    "sg:classifiers":[
        {
            "category":"Shopping",
            "type":"Retail Goods"
        }
    ],
    "sg:phone":"+1 817 652 0566",
    "sg:postcode":"76011",
    "sg:province":"TX",
    "sg:tags":[
        "equipment",
        "supply"
    ],
    "wof:name":"CPAPC Restaurant Design/Supply",
    "wof:placetype":"venue"
},
  "geometry": {"coordinates":[-97.050405,32.744604],"type":"Point"}
}