{
  "type": "Feature",
  "properties": {
    "iso:country":"US",
    "sg:address":"6151 Dew Dr",
    "sg:city":"El Paso",
    "sg:classifiers":[
        {
            "category":"Health Services",
            "subcategory":"Health Practitioner",
            "type":"Services"
        }
    ],
    "sg:phone":"+1 915 587 4081",
    "sg:postcode":"79912",
    "sg:province":"TX",
    "sg:tags":[
        "therapist",
        "physical"
    ],
    "wof:name":"El Paso Physcl Therapy Svcs W",
    "wof:placetype":"venue"
},
  "geometry": {"coordinates":[-106.530433,31.832725],"type":"Point"}
}