{
  "type": "Feature",
  "properties": {
    "iso:country":"US",
    "sg:address":"201 N Gibson St",
    "sg:city":"Waxahachie",
    "sg:classifiers":[
        {
            "category":"Personal",
            "type":"Services"
        }
    ],
    "sg:phone":"+1 972 937 6612",
    "sg:postcode":"75165",
    "sg:province":"TX",
    "sg:tags":[
        "therapist",
        "massage"
    ],
    "wof:name":"Sharon Leach Massage",
    "wof:placetype":"venue"
},
  "geometry": {"coordinates":[-96.853669,32.390755],"type":"Point"}
}