{
  "type": "Feature",
  "properties": {
    "iso:country":"US",
    "sg:address":"1112 Gulfton Dr",
    "sg:city":"Pearland",
    "sg:classifiers":[
        {
            "category":"Professional",
            "type":"Services"
        }
    ],
    "sg:phone":"+1 281 996 1873",
    "sg:postcode":"77581",
    "sg:province":"TX",
    "sg:tags":[
        "establishment"
    ],
    "wof:name":"Cherubs-N-Chocolate By Dionee",
    "wof:placetype":"venue"
},
  "geometry": {"coordinates":[-95.224773,29.533159],"type":"Point"}
}