{
  "type": "Feature",
  "properties": {
    "iso:country":"US",
    "sg:address":"1117 12th St",
    "sg:city":"Hartley",
    "sg:classifiers":[
        {
            "category":"Education",
            "subcategory":"School",
            "type":"Public Place"
        }
    ],
    "sg:phone":"+1 806 365 4615",
    "sg:postcode":"79044",
    "sg:province":"TX",
    "wof:name":"Countryside Christian Schl",
    "wof:placetype":"venue"
},
  "geometry": {"coordinates":[-102.404854,35.879875],"type":"Point"}
}