{
  "type": "Feature",
  "properties": {
    "iso:country":"US",
    "sg:address":"1215 Coulter St",
    "sg:city":"Amarillo",
    "sg:classifiers":[
        {
            "category":"Health Services",
            "subcategory":"Doctor",
            "type":"Services"
        }
    ],
    "sg:phone":"+1 806 463 1712",
    "sg:postcode":"79106",
    "sg:province":"TX",
    "sg:tags":[
        "medical"
    ],
    "wof:name":"Amarillo Cardiovasclr & Thorac",
    "wof:placetype":"venue"
},
  "geometry": {"coordinates":[-101.921753,35.196596],"type":"Point"}
}