{
  "type": "Feature",
  "properties": {
    "iso:country":"US",
    "sg:address":"10897 Collier Cemetery Rd",
    "sg:city":"Montgomery",
    "sg:classifiers":[
        {
            "category":"Building & Trades",
            "subcategory":"Plumbing",
            "type":"Services"
        }
    ],
    "sg:phone":"+1 936 447 6337",
    "sg:postcode":"77316",
    "sg:province":"TX",
    "sg:tags":[
        "plumber",
        "industrial",
        "contractors-commercial"
    ],
    "wof:name":"Silverado Plumbing",
    "wof:placetype":"venue"
},
  "geometry": {"coordinates":[-95.64391999999999,30.311124],"type":"Point"}
}