{
  "type": "Feature",
  "properties": {
    "iso:country":"US",
    "sg:address":"4410 Alameda Ave",
    "sg:city":"El Paso",
    "sg:classifiers":[
        {
            "category":"Organizations",
            "subcategory":"Religious Organization",
            "type":"Services"
        }
    ],
    "sg:phone":"+1 915 533 6177",
    "sg:postcode":"79905",
    "sg:province":"TX",
    "sg:tags":[
        "church"
    ],
    "wof:name":"Iglesia Fiel Y Verdadero Inc",
    "wof:placetype":"venue"
},
  "geometry": {"coordinates":[-106.438346,31.771632],"type":"Point"}
}