{
  "type": "Feature",
  "properties": {
    "iso:country":"US",
    "sg:address":"3600 Gus Thomasson Rd",
    "sg:city":"Mesquite",
    "sg:classifiers":[
        {
            "category":"Restaurant",
            "type":"Food & Drink"
        }
    ],
    "sg:phone":"+1 972 613 3651",
    "sg:postcode":"75150",
    "sg:province":"TX",
    "sg:tags":[
        "family"
    ],
    "wof:name":"Donna's Kitchen",
    "wof:placetype":"venue"
},
  "geometry": {"coordinates":[-96.634075,32.808878],"type":"Point"}
}