{
  "type": "Feature",
  "properties": {
    "iso:country":"US",
    "sg:address":"2404 Cedar Springs Rd Suite 500",
    "sg:city":"Dallas",
    "sg:classifiers":[
        {
            "category":"Restaurant",
            "type":"Food & Drink"
        }
    ],
    "sg:phone":"+1 214 855 4999",
    "sg:postcode":"75201",
    "sg:province":"TX",
    "sg:tags":[
        "pizza"
    ],
    "sg:website":"www.coalvines.com",
    "wof:name":"Coal Vines",
    "wof:placetype":"venue"
},
  "geometry": {"coordinates":[-96.80538199999999,32.796558],"type":"Point"}
}