{
  "type": "Feature",
  "properties": {
    "iso:country":"US",
    "sg:address":"2725 Collins Blvd",
    "sg:city":"Garland",
    "sg:classifiers":[
        {
            "category":"Real Estate",
            "subcategory":"Architect",
            "type":"Services"
        }
    ],
    "sg:phone":"+1 972 495 1779",
    "sg:postcode":"75044",
    "sg:province":"TX",
    "sg:tags":[
        "architectural"
    ],
    "wof:name":"B R Architects Inc",
    "wof:placetype":"venue"
},
  "geometry": {"coordinates":[-96.669617,32.969082],"type":"Point"}
}