{
  "type": "Feature",
  "properties": {
    "iso:country":"US",
    "sg:address":"719 Water St",
    "sg:city":"Kerrville",
    "sg:classifiers":[
        {
            "category":"Professional",
            "subcategory":"Lawyer & Legal Services",
            "type":"Services"
        }
    ],
    "sg:phone":"+1 830 895 2924",
    "sg:postcode":"78028",
    "sg:province":"TX",
    "sg:tags":[
        "attorney"
    ],
    "sg:website":"http://www.hartslaw.com",
    "wof:name":"Hart's Law Office",
    "wof:placetype":"venue"
},
  "geometry": {"coordinates":[-99.141469,30.04636],"type":"Point"}
}