{
  "type": "Feature",
  "properties": {
    "iso:country":"US",
    "sg:address":"1420 W Commerce St",
    "sg:city":"San Antonio",
    "sg:classifiers":[
        {
            "category":"Shopping",
            "subcategory":"Bicycles & Sporting Goods",
            "type":"Retail Goods"
        }
    ],
    "sg:phone":"+1 210 225 7589",
    "sg:postcode":"78207",
    "sg:province":"TX",
    "sg:tags":[
        "equipment",
        "hunting",
        "supply"
    ],
    "wof:name":"Buena Vista Distributing",
    "wof:placetype":"venue"
},
  "geometry": {"coordinates":[-98.51081600000001,29.426577],"type":"Point"}
}