{
  "type": "Feature",
  "properties": {
    "iso:country":"US",
    "sg:address":"612 N 3rd St",
    "sg:city":"Texhoma",
    "sg:classifiers":[
        {
            "category":"Organizations",
            "subcategory":"Religious Organization",
            "type":"Services"
        }
    ],
    "sg:phone":"+1 580 423 7147",
    "sg:postcode":"73949",
    "sg:province":"TX",
    "sg:tags":[
        "church"
    ],
    "wof:name":"First Church Of The Nazarene",
    "wof:placetype":"venue"
},
  "geometry": {"coordinates":[-101.784494,36.510252],"type":"Point"}
}