{
  "type": "Feature",
  "properties": {
    "iso:country":"US",
    "sg:address":"2519 College Ave",
    "sg:city":"Snyder",
    "sg:classifiers":[
        {
            "category":"Banks & Credit Unions",
            "subcategory":"Bank",
            "type":"Services"
        }
    ],
    "sg:phone":"+1 325 573 2653",
    "sg:postcode":"79549",
    "sg:province":"TX",
    "sg:tags":[
        "financing"
    ],
    "wof:name":"Sun Loan Co",
    "wof:placetype":"venue"
},
  "geometry": {"coordinates":[-100.918424,32.716995],"type":"Point"}
}