{
  "type": "Feature",
  "properties": {
    "iso:country":"US",
    "sg:address":"998 Holli Ln",
    "sg:city":"Rockwall",
    "sg:classifiers":[
        {
            "category":"Utilities",
            "subcategory":"Electric",
            "type":"Services"
        },
        {
            "category":"Professional",
            "subcategory":"Art Services",
            "type":"Services"
        },
        {
            "category":"Building & Trades",
            "subcategory":"Electrical",
            "type":"Services"
        },
        {
            "category":"Train Station",
            "subcategory":"Light Rail",
            "type":"Transportation"
        }
    ],
    "sg:phone":"+1 972 771 9464",
    "sg:postcode":"75087",
    "sg:province":"TX",
    "sg:tags":[
        "industrial",
        "electrician",
        "consultant",
        "designer",
        "lighting",
        "contractors-commercial",
        "maintenance"
    ],
    "sg:website":"http://www.barneyselectric.com",
    "wof:name":"Barney's Electric",
    "wof:placetype":"venue"
},
  "geometry": {"coordinates":[-96.45764200000001,32.937832],"type":"Point"}
}