{
  "type": "Feature",
  "properties": {
    "iso:country":"US",
    "sg:address":"4133 Gollihar Rd",
    "sg:city":"Corpus Christi",
    "sg:classifiers":[
        {
            "category":"Insurance",
            "subcategory":"Insurance Agent",
            "type":"Services"
        }
    ],
    "sg:phone":"+1 361 854 4500",
    "sg:postcode":"78411",
    "sg:province":"TX",
    "wof:name":"Eddie L Garcia Insurance",
    "wof:placetype":"venue"
},
  "geometry": {"coordinates":[-97.392628,27.731288],"type":"Point"}
}