{
  "type": "Feature",
  "properties": {
    "iso:country":"US",
    "sg:address":"401 W Campbell Rd",
    "sg:city":"Richardson",
    "sg:classifiers":[
        {
            "category":"Health Services",
            "subcategory":"Doctor",
            "type":"Services"
        }
    ],
    "sg:phone":"+1 972 498 8650",
    "sg:postcode":"75080",
    "sg:province":"TX",
    "wof:name":"Dallas Diagnostic Assoc of Richardson",
    "wof:placetype":"venue"
},
  "geometry": {"coordinates":[-96.727898,32.9753],"type":"Point"}
}