{
  "type": "Feature",
  "properties": {
    "iso:country":"US",
    "sg:address":"1516 Morrow St",
    "sg:city":"Austin",
    "sg:classifiers":[
        {
            "category":"Professional",
            "type":"Services"
        }
    ],
    "sg:phone":"+1 512 459 7616",
    "sg:postcode":"78757",
    "sg:province":"TX",
    "sg:tags":[
        "establishment"
    ],
    "wof:name":"Housemission",
    "wof:placetype":"venue"
},
  "geometry": {"coordinates":[-97.72681,30.349141],"type":"Point"}
}