{
  "type": "Feature",
  "properties": {
    "iso:country":"US",
    "sg:address":"920 Rocky Spring Rd",
    "sg:city":"Austin",
    "sg:classifiers":[
        {
            "category":"Shopping",
            "type":"Retail Goods"
        }
    ],
    "sg:phone":"+1 512 837 0956",
    "sg:postcode":"78753",
    "sg:province":"TX",
    "sg:tags":[
        "merchandise"
    ],
    "wof:name":"Christmas Decor",
    "wof:placetype":"venue"
},
  "geometry": {"coordinates":[-97.665505,30.381822],"type":"Point"}
}