{
  "type": "Feature",
  "properties": {
    "iso:country":"US",
    "sg:address":"1302 Gail Borden Pl",
    "sg:city":"El Paso",
    "sg:classifiers":[
        {
            "category":"Manufacturing",
            "subcategory":"Signs",
            "type":"Manufacturing & Wholesale Goods"
        }
    ],
    "sg:phone":"+1 915 591 5771",
    "sg:postcode":"79935",
    "sg:province":"TX",
    "wof:name":"Service Outlet",
    "wof:placetype":"venue"
},
  "geometry": {"coordinates":[-106.324444,31.746352],"type":"Point"}
}