{
  "type": "Feature",
  "properties": {
    "iso:country":"US",
    "sg:address":"4405 Bay Valley Dr",
    "sg:city":"Garland",
    "sg:classifiers":[
        {
            "category":"Building & Trades",
            "subcategory":"Cleaning & Sanitation",
            "type":"Services"
        }
    ],
    "sg:phone":"+1 972 240 0299",
    "sg:postcode":"75043",
    "sg:province":"TX",
    "sg:tags":[
        "janitor",
        "maintenance"
    ],
    "wof:name":"Nitas Neat Cleaning Service",
    "wof:placetype":"venue"
},
  "geometry": {"coordinates":[-96.58703,32.867621],"type":"Point"}
}