{
  "type": "Feature",
  "properties": {
    "iso:country":"US",
    "sg:address":"10713 Pinkney Lane",
    "sg:city":"Austin",
    "sg:classifiers":[
        {
            "category":"Shopping",
            "subcategory":"Jewelry",
            "type":"Retail Goods"
        }
    ],
    "sg:phone":"+1 512 469 9110",
    "sg:postcode":"78739",
    "sg:province":"TX",
    "wof:name":"Engaging Ideas",
    "wof:placetype":"venue"
},
  "geometry": {"coordinates":[-97.888063,30.189449],"type":"Point"}
}