{
  "type": "Feature",
  "properties": {
    "iso:country":"US",
    "sg:address":"3601 Jackson Dr",
    "sg:city":"Mc Kinney",
    "sg:classifiers":[
        {
            "category":"Social Services",
            "subcategory":"Job Training",
            "type":"Services"
        }
    ],
    "sg:phone":"+1 972 549 1609",
    "sg:postcode":"75070",
    "sg:province":"TX",
    "wof:name":"Rhino Seminars",
    "wof:placetype":"venue"
},
  "geometry": {"coordinates":[-96.70045500000001,33.168232],"type":"Point"}
}