{
  "type": "Feature",
  "properties": {
    "iso:country":"US",
    "sg:address":"222 Las Colinas Blvd W",
    "sg:city":"Irving",
    "sg:classifiers":[
        {
            "category":"Professional",
            "subcategory":"Management & Consulting",
            "type":"Services"
        }
    ],
    "sg:phone":"+1 972 401 4107",
    "sg:postcode":"75039",
    "sg:province":"TX",
    "sg:tags":[
        "help",
        "business",
        "supply"
    ],
    "wof:name":"Spherion Corporation",
    "wof:placetype":"venue"
},
  "geometry": {"coordinates":[-96.943473,32.872328],"type":"Point"}
}