{
  "type": "Feature",
  "properties": {
    "iso:country":"US",
    "sg:address":"9507 Silver Falls St",
    "sg:city":"Dallas",
    "sg:classifiers":[
        {
            "category":"Building & Trades",
            "subcategory":"Pest Control",
            "type":"Services"
        }
    ],
    "sg:phone":"+1 214 391 7378",
    "sg:postcode":"75217",
    "sg:province":"TX",
    "wof:name":"Delgado Enterprises Inc",
    "wof:placetype":"venue"
},
  "geometry": {"coordinates":[-96.659013,32.704275],"type":"Point"}
}