{
  "type": "Feature",
  "properties": {
    "iso:country":"US",
    "sg:address":"4830 West Ave",
    "sg:city":"San Antonio",
    "sg:classifiers":[
        {
            "category":"Banks & Credit Unions",
            "subcategory":"Investment Brokerage",
            "type":"Services"
        }
    ],
    "sg:phone":"+1 210 308 1050",
    "sg:postcode":"78213",
    "sg:province":"TX",
    "sg:tags":[
        "advisory"
    ],
    "wof:name":"First Funding Financial",
    "wof:placetype":"venue"
},
  "geometry": {"coordinates":[-98.525869,29.510266],"type":"Point"}
}