{
  "type": "Feature",
  "properties": {
    "iso:country":"US",
    "sg:address":"200 Commerce St NW",
    "sg:city":"Childress",
    "sg:classifiers":[
        {
            "category":"Health Services",
            "subcategory":"Doctor",
            "type":"Services"
        }
    ],
    "sg:phone":"+1 940 937 2200",
    "sg:postcode":"79201",
    "sg:province":"TX",
    "sg:tags":[
        "physician",
        "surgeon"
    ],
    "wof:name":"Clinic For Family Medicine",
    "wof:placetype":"venue"
},
  "geometry": {"coordinates":[-100.206987,34.423961],"type":"Point"}
}