{
  "type": "Feature",
  "properties": {
    "iso:country":"US",
    "sg:address":"1201 Bennett Rd",
    "sg:city":"Alvin",
    "sg:classifiers":[
        {
            "category":"Freight",
            "type":"Transportation"
        }
    ],
    "sg:phone":"+1 281 331 3630",
    "sg:postcode":"77511",
    "sg:province":"TX",
    "sg:tags":[
        "operator",
        "local",
        "trucking"
    ],
    "wof:name":"Joe Deatherage",
    "wof:placetype":"venue"
},
  "geometry": {"coordinates":[-95.27331599999999,29.426381],"type":"Point"}
}