{
  "type": "Feature",
  "properties": {
    "iso:country":"US",
    "sg:address":"2724 S Colfax Cir",
    "sg:city":"Plano",
    "sg:classifiers":[
        {
            "category":"Shopping",
            "subcategory":"Crafts & Fabrics",
            "type":"Retail Goods"
        }
    ],
    "sg:phone":"+1 972 985 9810",
    "sg:postcode":"75075",
    "sg:province":"TX",
    "sg:tags":[
        "sewing"
    ],
    "wof:name":"In Stitches",
    "wof:placetype":"venue"
},
  "geometry": {"coordinates":[-96.74709900000001,33.027872],"type":"Point"}
}