{
  "type": "Feature",
  "properties": {
    "iso:country":"US",
    "sg:address":"7420 Gateway Blvd E",
    "sg:city":"El Paso",
    "sg:classifiers":[
        {
            "category":"Banks & Credit Unions",
            "subcategory":"Bank",
            "type":"Services"
        }
    ],
    "sg:phone":"+1 915 591 9436",
    "sg:postcode":"79915",
    "sg:province":"TX",
    "sg:tags":[
        "financing"
    ],
    "wof:name":"Citi Financial",
    "wof:placetype":"venue"
},
  "geometry": {"coordinates":[-106.365994,31.764929],"type":"Point"}
}