{
  "type": "Feature",
  "properties": {
    "iso:country":"US",
    "sg:address":"6242 Rufe Snow Dr",
    "sg:city":"Fort Worth",
    "sg:classifiers":[
        {
            "category":"Health Services",
            "subcategory":"Doctor",
            "type":"Services"
        }
    ],
    "sg:phone":"+1 817 656 4656",
    "sg:postcode":"76148",
    "sg:province":"TX",
    "sg:tags":[
        "dentist"
    ],
    "wof:name":"Reynolds Dental Clinic",
    "wof:placetype":"venue"
},
  "geometry": {"coordinates":[-97.23792299999999,32.860236],"type":"Point"}
}