{
  "type": "Feature",
  "properties": {
    "iso:country":"US",
    "sg:address":"3144 E Commerce St",
    "sg:city":"San Antonio",
    "sg:classifiers":[
        {
            "category":"Real Estate",
            "subcategory":"Real Estate Operator",
            "type":"Services"
        }
    ],
    "sg:phone":"+1 210 227 8091",
    "sg:postcode":"78220",
    "sg:province":"TX",
    "sg:tags":[
        "apartment"
    ],
    "wof:name":"Center Park Apartments",
    "wof:placetype":"venue"
},
  "geometry": {"coordinates":[-98.43969300000001,29.41978],"type":"Point"}
}