{
  "type": "Feature",
  "properties": {
    "iso:country":"US",
    "sg:address":"1734 Ave D",
    "sg:city":"Abilene",
    "sg:classifiers":[
        {
            "category":"Retail",
            "subcategory":"Portrait Studio",
            "type":"Services"
        }
    ],
    "sg:phone":"+1 325 676 9892",
    "sg:postcode":"79601",
    "sg:province":"TX",
    "sg:tags":[
        "photo"
    ],
    "wof:name":"Kick ME Digital Media",
    "wof:placetype":"venue"
},
  "geometry": {"coordinates":[-99.71456000000001,32.46811],"type":"Point"}
}