{
  "type": "Feature",
  "properties": {
    "iso:country":"US",
    "sg:address":"7111 Martin Luther King Jr Blvd",
    "sg:city":"Houston",
    "sg:classifiers":[
        {
            "category":"Shopping",
            "type":"Retail Goods"
        }
    ],
    "sg:phone":"+1 713 649 1155",
    "sg:postcode":"77033",
    "sg:province":"TX",
    "sg:tags":[
        "cosmetic",
        "perfume"
    ],
    "wof:name":"King Fashions & Gifts",
    "wof:placetype":"venue"
},
  "geometry": {"coordinates":[-95.336332,29.674758],"type":"Point"}
}