{
  "type": "Feature",
  "properties": {
    "iso:country":"US",
    "sg:address":"3635 Dan Morton Dr",
    "sg:city":"Dallas",
    "sg:classifiers":[
        {
            "category":"Organizations",
            "subcategory":"Religious Organization",
            "type":"Services"
        }
    ],
    "sg:phone":"+1 972 780 9621",
    "sg:postcode":"75236",
    "sg:province":"TX",
    "wof:name":"Td Jakes Ministries",
    "wof:placetype":"venue"
},
  "geometry": {"coordinates":[-96.917801,32.700001],"type":"Point"}
}