{
  "type": "Feature",
  "properties": {
    "iso:country":"US",
    "sg:address":"7545 Cherry Park Dr",
    "sg:city":"Houston",
    "sg:classifiers":[
        {
            "category":"Food & Beverages",
            "subcategory":"Groceries & Convenience Stores",
            "type":"Retail Goods"
        }
    ],
    "sg:phone":"+1 281 550 0082",
    "sg:postcode":"77095",
    "sg:province":"TX",
    "wof:name":"Westside",
    "wof:placetype":"venue"
},
  "geometry": {"coordinates":[-95.64069000000001,29.888284],"type":"Point"}
}