{
  "type": "Feature",
  "properties": {
    "iso:country":"US",
    "sg:address":"622 S Oakes St",
    "sg:city":"San Angelo",
    "sg:classifiers":[
        {
            "category":"Government",
            "subcategory":"Office",
            "type":"Public Place"
        }
    ],
    "sg:phone":"+1 325 657 7400",
    "sg:postcode":"76903",
    "sg:province":"TX",
    "wof:name":"Protective & Regulatory Dept",
    "wof:placetype":"venue"
},
  "geometry": {"coordinates":[-100.431583,31.454802],"type":"Point"}
}