{
  "type": "Feature",
  "properties": {
    "iso:country":"US",
    "sg:address":"1101 S Fannin St",
    "sg:city":"Alvarado",
    "sg:classifiers":[
        {
            "category":"Personal",
            "subcategory":"Tanning Parlor",
            "type":"Services"
        }
    ],
    "sg:phone":"+1 817 790 2362",
    "sg:postcode":"76009",
    "sg:province":"TX",
    "sg:tags":[
        "salon"
    ],
    "wof:name":"Sunset Salon & Tanning, Inc.",
    "wof:placetype":"venue"
},
  "geometry": {"coordinates":[-97.20966300000001,32.395771],"type":"Point"}
}