{
  "type": "Feature",
  "properties": {
    "iso:country":"US",
    "sg:address":"2525 Kell Blvd",
    "sg:city":"Wichita Falls",
    "sg:classifiers":[
        {
            "category":"Mining & Drilling",
            "type":"Manufacturing & Wholesale Goods"
        }
    ],
    "sg:phone":"+1 940 761 1085",
    "sg:postcode":"76308",
    "sg:province":"TX",
    "sg:tags":[
        "development",
        "gas",
        "oil",
        "exploration"
    ],
    "sg:website":"www.providenceoil.com",
    "wof:name":"Providence Oil Co",
    "wof:placetype":"venue"
},
  "geometry": {"coordinates":[-98.525464,33.885826],"type":"Point"}
}