{
  "type": "Feature",
  "properties": {
    "iso:country":"US",
    "sg:address":"2527 S Main St",
    "sg:city":"Pearland",
    "sg:classifiers":[
        {
            "category":"Autos & Motor Vehicles",
            "subcategory":"Auto Supplies",
            "type":"Retail Goods"
        }
    ],
    "sg:phone":"+1 281 485 0800",
    "sg:postcode":"77581",
    "sg:province":"TX",
    "sg:tags":[
        "automotive",
        "general",
        "tire",
        "repair"
    ],
    "wof:name":"Pearland Tire & Auto",
    "wof:placetype":"venue"
},
  "geometry": {"coordinates":[-95.285948,29.561285],"type":"Point"}
}