{
  "type": "Feature",
  "properties": {
    "iso:country":"US",
    "sg:address":"2023 Broadway St",
    "sg:city":"Lubbock",
    "sg:classifiers":[
        {
            "category":"Personal",
            "type":"Services"
        }
    ],
    "sg:phone":"+1 806 740 0100",
    "sg:postcode":"79401",
    "sg:province":"TX",
    "sg:tags":[
        "therapist",
        "massage"
    ],
    "sg:website":"www.oceansmassage.com",
    "wof:name":"Oceans Massage Spa",
    "wof:placetype":"venue"
},
  "geometry": {"coordinates":[-101.861564,33.584389],"type":"Point"}
}