{
  "type": "Feature",
  "properties": {
    "iso:country":"US",
    "sg:address":"952 Echo Ln",
    "sg:city":"Houston",
    "sg:classifiers":[
        {
            "category":"Real Estate",
            "subcategory":"Real Estate Services",
            "type":"Services"
        }
    ],
    "sg:phone":"+1 832 358 2200",
    "sg:postcode":"77024",
    "sg:province":"TX",
    "sg:tags":[
        "lawyer",
        "title"
    ],
    "wof:name":"Fidelity National Title",
    "wof:placetype":"venue"
},
  "geometry": {"coordinates":[-95.521202,29.780701],"type":"Point"}
}