{
  "type": "Feature",
  "properties": {
    "iso:country":"US",
    "sg:address":"6448 Embers Rd",
    "sg:city":"Dallas",
    "sg:classifiers":[
        {
            "category":"Shopping",
            "subcategory":"Stationery & Office Supplies",
            "type":"Retail Goods"
        }
    ],
    "sg:phone":"+1 972 733 0078",
    "sg:postcode":"75248",
    "sg:province":"TX",
    "wof:name":"Social Butterfly",
    "wof:placetype":"venue"
},
  "geometry": {"coordinates":[-96.79244300000001,32.972993],"type":"Point"}
}