{
  "type": "Feature",
  "properties": {
    "iso:country":"US",
    "sg:address":"1541 Parkway Ln",
    "sg:city":"Arlington",
    "sg:classifiers":[
        {
            "category":"Real Estate",
            "subcategory":"Real Estate Operator",
            "type":"Services"
        }
    ],
    "sg:phone":"+1 817 265 8861",
    "sg:postcode":"76010",
    "sg:province":"TX",
    "sg:tags":[
        "building",
        "apartment"
    ],
    "wof:name":"Parkway E Twnhome Condominiums",
    "wof:placetype":"venue"
},
  "geometry": {"coordinates":[-97.08581100000001,32.709335],"type":"Point"}
}