{
  "type": "Feature",
  "properties": {
    "iso:country":"US",
    "sg:address":"155 Cedar St",
    "sg:city":"Abilene",
    "sg:classifiers":[
        {
            "category":"Professional",
            "subcategory":"Accounting & Tax Preparation",
            "type":"Services"
        }
    ],
    "sg:phone":"+1 325 676 4936",
    "sg:postcode":"79601",
    "sg:province":"TX",
    "sg:tags":[
        "bookkeeping",
        "general"
    ],
    "wof:name":"De Vries Bookkeeping & Tax",
    "wof:placetype":"venue"
},
  "geometry": {"coordinates":[-99.73539700000001,32.450032],"type":"Point"}
}