{
  "type": "Feature",
  "properties": {
    "iso:country":"US",
    "sg:address":"11111 Kingsley Rd",
    "sg:city":"Dallas",
    "sg:classifiers":[
        {
            "category":"Shopping",
            "subcategory":"Discount & Variety Stores",
            "type":"Retail Goods"
        }
    ],
    "sg:phone":"+1 214 905 5180",
    "sg:postcode":"75238",
    "sg:province":"TX",
    "sg:tags":[
        "merchandise",
        "general"
    ],
    "wof:name":"Femree Enterprises",
    "wof:placetype":"venue"
},
  "geometry": {"coordinates":[-96.68972100000001,32.878754],"type":"Point"}
}