{
  "type": "Feature",
  "properties": {
    "iso:country":"US",
    "sg:address":"543 Ruiz St",
    "sg:city":"San Antonio",
    "sg:classifiers":[
        {
            "category":"Restaurant",
            "type":"Food & Drink"
        }
    ],
    "sg:phone":"+1 210 225 9723",
    "sg:postcode":"78207",
    "sg:province":"TX",
    "sg:tags":[
        "eating"
    ],
    "wof:name":"El Charro Mexican Restaurant",
    "wof:placetype":"venue"
},
  "geometry": {"coordinates":[-98.509175,29.434913],"type":"Point"}
}