{
  "type": "Feature",
  "properties": {
    "iso:country":"US",
    "sg:address":"2904 Tee Anchor Blvd",
    "sg:city":"Amarillo",
    "sg:classifiers":[
        {
            "category":"Government",
            "subcategory":"Office",
            "type":"Public Place"
        }
    ],
    "sg:phone":"+1 806 372 2928",
    "sg:postcode":"79104",
    "sg:province":"TX",
    "sg:tags":[
        "federal",
        "security"
    ],
    "wof:name":"US Defense Investigation Svc",
    "wof:placetype":"venue"
},
  "geometry": {"coordinates":[-101.804564,35.197026],"type":"Point"}
}