{
  "type": "Feature",
  "properties": {
    "iso:country":"US",
    "sg:address":"10814 Green Arbor Dr",
    "sg:city":"Houston",
    "sg:classifiers":[
        {
            "category":"Banks & Credit Unions",
            "subcategory":"Financial Services",
            "type":"Services"
        }
    ],
    "sg:phone":"+1 713 944 2618",
    "sg:postcode":"77089",
    "sg:province":"TX",
    "sg:tags":[
        "management",
        "open",
        "investment"
    ],
    "wof:name":"Oro Management",
    "wof:placetype":"venue"
},
  "geometry": {"coordinates":[-95.22320999999999,29.617827],"type":"Point"}
}