{
  "type": "Feature",
  "properties": {
    "iso:country":"US",
    "sg:address":"301 E Palestine Ave",
    "sg:city":"Palestine",
    "sg:classifiers":[
        {
            "category":"Wholesale",
            "subcategory":"Construction Materials",
            "type":"Manufacturing & Wholesale Goods"
        }
    ],
    "sg:phone":"+1 903 731 9399",
    "sg:postcode":"75801",
    "sg:province":"TX",
    "sg:tags":[
        "timberland",
        "company",
        "timber"
    ],
    "wof:name":"Paul Williams & Assoc",
    "wof:placetype":"venue"
},
  "geometry": {"coordinates":[-95.629593,31.771251],"type":"Point"}
}