{
  "type": "Feature",
  "properties": {
    "iso:country":"US",
    "sg:address":"724 Kingwood Dr",
    "sg:city":"Kingwood",
    "sg:classifiers":[
        {
            "category":"Shopping",
            "subcategory":"Gifts & Souvenirs",
            "type":"Retail Goods"
        }
    ],
    "sg:phone":"+1 281 358 2612",
    "sg:postcode":"77339",
    "sg:province":"TX",
    "sg:tags":[
        "shop",
        "greeting",
        "card"
    ],
    "sg:website":"http://www.hallmark.com",
    "wof:name":"Hallmark Cards & Gifts",
    "wof:placetype":"venue"
},
  "geometry": {"coordinates":[-95.2439,30.050804],"type":"Point"}
}