{
  "type": "Feature",
  "properties": {
    "iso:country":"US",
    "sg:address":"6186 Wilcrest Dr",
    "sg:city":"Houston",
    "sg:classifiers":[
        {
            "category":"Shopping",
            "type":"Retail Goods"
        }
    ],
    "sg:phone":"+1 281 568 7200",
    "sg:postcode":"77072",
    "sg:province":"TX",
    "sg:tags":[
        "equipment",
        "merchandise"
    ],
    "wof:name":"Breathe Moore Easy Medical Sup",
    "wof:placetype":"venue"
},
  "geometry": {"coordinates":[-95.571434,29.712623],"type":"Point"}
}