{
  "type": "Feature",
  "properties": {
    "iso:country":"US",
    "sg:address":"1219 Vista Rd",
    "sg:city":"Pasadena",
    "sg:classifiers":[
        {
            "category":"Freight",
            "type":"Transportation"
        }
    ],
    "sg:phone":"+1 713 686 3003",
    "sg:postcode":"77504",
    "sg:province":"TX",
    "sg:tags":[
        "maritime"
    ],
    "wof:name":"Knight Transport LTD",
    "wof:placetype":"venue"
},
  "geometry": {"coordinates":[-95.19239399999999,29.658993],"type":"Point"}
}