{
  "type": "Feature",
  "properties": {
    "iso:country":"US",
    "sg:address":"2214 S Jupiter Rd",
    "sg:city":"Garland",
    "sg:classifiers":[
        {
            "category":"Wholesale",
            "subcategory":"Medical Equipment & Supplies",
            "type":"Manufacturing & Wholesale Goods"
        }
    ],
    "sg:phone":"+1 972 271 8800",
    "sg:postcode":"75041",
    "sg:province":"TX",
    "wof:name":"JB Medical Equipment",
    "wof:placetype":"venue"
},
  "geometry": {"coordinates":[-96.683066,32.889417],"type":"Point"}
}