{
  "type": "Feature",
  "properties": {
    "iso:country":"US",
    "sg:address":"5213 Streamwood Ln",
    "sg:city":"Plano",
    "sg:classifiers":[
        {
            "category":"Wholesale",
            "subcategory":"Books, Periodicals, & Newspapers",
            "type":"Manufacturing & Wholesale Goods"
        }
    ],
    "sg:phone":"+1 214 280 8140",
    "sg:postcode":"75093",
    "sg:province":"TX",
    "wof:name":"Comicsbymail Co",
    "wof:placetype":"venue"
},
  "geometry": {"coordinates":[-96.80523100000001,33.017755],"type":"Point"}
}