{
  "type": "Feature",
  "properties": {
    "iso:country":"US",
    "sg:address":"21623 Misty Fall Ln",
    "sg:city":"Katy",
    "sg:classifiers":[
        {
            "category":"Building & Trades",
            "subcategory":"Electrical",
            "type":"Services"
        }
    ],
    "sg:phone":"+1 281 642 9867",
    "sg:postcode":"77449",
    "sg:province":"TX",
    "sg:tags":[
        "electrician"
    ],
    "wof:name":"Rp Electric",
    "wof:placetype":"venue"
},
  "geometry": {"coordinates":[-95.75135,29.828664],"type":"Point"}
}