{
  "type": "Feature",
  "properties": {
    "iso:country":"US",
    "sg:address":"5312 Roberta Dr",
    "sg:city":"Fort Worth",
    "sg:classifiers":[
        {
            "category":"Professional",
            "subcategory":"Accounting & Tax Preparation",
            "type":"Services"
        }
    ],
    "sg:phone":"+1 817 281 4471",
    "sg:postcode":"76180",
    "sg:province":"TX",
    "sg:tags":[
        "return"
    ],
    "wof:name":"Rapid Tax Services LLC",
    "wof:placetype":"venue"
},
  "geometry": {"coordinates":[-97.21771099999999,32.846447],"type":"Point"}
}