{
  "type": "Feature",
  "properties": {
    "iso:country":"US",
    "sg:address":"7385 Buggy Hub Trl",
    "sg:city":"Athens",
    "sg:classifiers":[
        {
            "category":"Restaurant",
            "type":"Food & Drink"
        }
    ],
    "sg:phone":"+1 903 677 3323",
    "sg:postcode":"75751",
    "sg:province":"TX",
    "sg:tags":[
        "house",
        "steak",
        "barbecue"
    ],
    "wof:name":"Big O's Bbq",
    "wof:placetype":"venue"
},
  "geometry": {"coordinates":[-95.891082,32.152192],"type":"Point"}
}