{
  "type": "Feature",
  "properties": {
    "iso:country":"US",
    "sg:address":"6013 Wedgwood Dr",
    "sg:city":"Fort Worth",
    "sg:classifiers":[
        {
            "category":"Health Services",
            "subcategory":"Doctor",
            "type":"Services"
        }
    ],
    "sg:phone":"+1 817 292 1442",
    "sg:postcode":"76133",
    "sg:province":"TX",
    "sg:tags":[
        "dentist"
    ],
    "wof:name":"Joseph S Mc Creary DDS",
    "wof:placetype":"venue"
},
  "geometry": {"coordinates":[-97.395762,32.662337],"type":"Point"}
}