{
  "type": "Feature",
  "properties": {
    "iso:country":"US",
    "sg:address":"2201 Fountain View Dr",
    "sg:city":"Houston",
    "sg:classifiers":[
        {
            "category":"Wholesale",
            "subcategory":"Machinery & Supplies",
            "type":"Manufacturing & Wholesale Goods"
        }
    ],
    "sg:phone":"+1 713 266 3251",
    "sg:postcode":"77057",
    "sg:province":"TX",
    "sg:tags":[
        "compressor",
        "product",
        "diesel"
    ],
    "wof:name":"Diesel & Compressor Products",
    "wof:placetype":"venue"
},
  "geometry": {"coordinates":[-95.48535099999999,29.743474],"type":"Point"}
}