{
  "type": "Feature",
  "properties": {
    "iso:country":"US",
    "sg:address":"602 Lindsay St",
    "sg:city":"Gainesville",
    "sg:classifiers":[
        {
            "category":"Retail",
            "subcategory":"Funeral Services",
            "type":"Services"
        }
    ],
    "sg:phone":"+1 940 665 3455",
    "sg:postcode":"76240",
    "sg:province":"TX",
    "sg:tags":[
        "director"
    ],
    "wof:name":"George J Carroll & Son Funeral",
    "wof:placetype":"venue"
},
  "geometry": {"coordinates":[-97.141071,33.619921],"type":"Point"}
}