{
  "type": "Feature",
  "properties": {
    "iso:country":"US",
    "sg:address":"1428 N Irving Heights Dr",
    "sg:city":"Irving",
    "sg:classifiers":[
        {
            "category":"Manufacturing",
            "subcategory":"Food",
            "type":"Manufacturing & Wholesale Goods"
        },
        {
            "category":"Restaurant",
            "type":"Food & Drink"
        }
    ],
    "sg:phone":"+1 972 438 7777",
    "sg:postcode":"75061",
    "sg:province":"TX",
    "sg:tags":[
        "product",
        "mfg"
    ],
    "wof:name":"Capt Nemo's Steak Submarines",
    "wof:placetype":"venue"
},
  "geometry": {"coordinates":[-96.926028,32.829479],"type":"Point"}
}