{
  "type": "Feature",
  "properties": {
    "iso:country":"US",
    "sg:address":"5008 Daisy Ct",
    "sg:city":"Mc Kinney",
    "sg:classifiers":[
        {
            "category":"Home & Garden",
            "subcategory":"Home Furnishings",
            "type":"Retail Goods"
        }
    ],
    "sg:phone":"+1 972 727 9656",
    "sg:postcode":"75070",
    "sg:province":"TX",
    "wof:name":"No Egrets Inc",
    "wof:placetype":"venue"
},
  "geometry": {"coordinates":[-96.681573,33.167323],"type":"Point"}
}