{
  "type": "Feature",
  "properties": {
    "iso:country":"US",
    "sg:address":"330 Liberty Ave",
    "sg:city":"Beaumont",
    "sg:classifiers":[
        {
            "category":"Professional",
            "subcategory":"Lawyer & Legal Services",
            "type":"Services"
        }
    ],
    "sg:phone":"+1 409 833 8936",
    "sg:postcode":"77701",
    "sg:province":"TX",
    "sg:tags":[
        "attorney"
    ],
    "wof:name":"Lewis J Hodge",
    "wof:placetype":"venue"
},
  "geometry": {"coordinates":[-94.10050200000001,30.084375],"type":"Point"}
}