{
  "type": "Feature",
  "properties": {
    "iso:country":"US",
    "sg:address":"12206 Ashley Circle Dr E",
    "sg:city":"Houston",
    "sg:classifiers":[
        {
            "category":"Professional",
            "subcategory":"Management & Consulting",
            "type":"Services"
        }
    ],
    "sg:phone":"+1 713 270 7089",
    "sg:postcode":"77071",
    "sg:province":"TX",
    "sg:tags":[
        "business"
    ],
    "wof:name":"M&M Management & Consulting",
    "wof:placetype":"venue"
},
  "geometry": {"coordinates":[-95.519651,29.644518],"type":"Point"}
}