{
  "type": "Feature",
  "properties": {
    "iso:country":"US",
    "sg:address":"7600 N Capital of Texas Hwy",
    "sg:city":"Austin",
    "sg:classifiers":[
        {
            "category":"Utilities",
            "subcategory":"Mobile Phone",
            "type":"Services"
        }
    ],
    "sg:phone":"+1 512 345 4200",
    "sg:postcode":"78731",
    "sg:province":"TX",
    "sg:tags":[
        "telephone",
        "cellular"
    ],
    "wof:name":"Alereon",
    "wof:placetype":"venue"
},
  "geometry": {"coordinates":[-97.779202,30.377245],"type":"Point"}
}