{
  "type": "Feature",
  "properties": {
    "iso:country":"US",
    "sg:address":"106 E Rusk St",
    "sg:city":"Rockwall",
    "sg:classifiers":[
        {
            "category":"Wholesale",
            "subcategory":"Medical Equipment & Supplies",
            "type":"Manufacturing & Wholesale Goods"
        }
    ],
    "sg:phone":"+1 972 722 3800",
    "sg:postcode":"75087",
    "sg:province":"TX",
    "wof:name":"Palm Tree Medical Products",
    "wof:placetype":"venue"
},
  "geometry": {"coordinates":[-96.459506,32.930984],"type":"Point"}
}