{
  "type": "Feature",
  "properties": {
    "iso:country":"US",
    "sg:address":"820 Adler St",
    "sg:city":"Boerne",
    "sg:classifiers":[
        {
            "category":"Place Of Worship",
            "subcategory":"Church",
            "type":"Public Place"
        },
        {
            "category":"Place Of Worship",
            "type":"Public Place"
        }
    ],
    "sg:phone":"+1 830 249 8448",
    "sg:postcode":"78006",
    "sg:province":"TX",
    "sg:tags":[
        "churches-interdenominational",
        "churches-various",
        "denomination"
    ],
    "wof:name":"Faith Bible Church Of Boerne",
    "wof:placetype":"venue"
},
  "geometry": {"coordinates":[-98.723484,29.80464],"type":"Point"}
}