{
  "type": "Feature",
  "properties": {
    "iso:country":"US",
    "sg:address":"2805 Glen Ridge Ct",
    "sg:city":"Arlington",
    "sg:classifiers":[
        {
            "category":"Freight",
            "type":"Transportation"
        }
    ],
    "sg:phone":"+1 817 467 9967",
    "sg:postcode":"76016",
    "sg:province":"TX",
    "sg:tags":[
        "trucking"
    ],
    "wof:name":"C & L-Trucking",
    "wof:placetype":"venue"
},
  "geometry": {"coordinates":[-97.156831,32.678066],"type":"Point"}
}