{
  "type": "Feature",
  "properties": {
    "iso:country":"US",
    "sg:address":"15538 US Hwy 181",
    "sg:city":"San Antonio",
    "sg:classifiers":[
        {
            "category":"Restaurant",
            "type":"Food & Drink"
        }
    ],
    "sg:phone":"+1 210 635 7002",
    "sg:postcode":"78223",
    "sg:province":"TX",
    "wof:name":"Burger Spot",
    "wof:placetype":"venue"
},
  "geometry": {"coordinates":[-98.305952,29.267522],"type":"Point"}
}