{
  "type": "Feature",
  "properties": {
    "iso:country":"US",
    "sg:address":"3 Concord Dr",
    "sg:city":"Orange",
    "sg:classifiers":[
        {
            "category":"Professional",
            "subcategory":"Business Services",
            "type":"Services"
        }
    ],
    "sg:phone":"+1 409 886 2345",
    "sg:postcode":"77630",
    "sg:province":"TX",
    "wof:name":"Cowling Family Ltd Partnership",
    "wof:placetype":"venue"
},
  "geometry": {"coordinates":[-93.769809,30.101691],"type":"Point"}
}