{
  "type": "Feature",
  "properties": {
    "iso:country":"US",
    "sg:address":"906 E Tyler Ave",
    "sg:city":"Harlingen",
    "sg:classifiers":[
        {
            "category":"Professional",
            "subcategory":"Accounting & Tax Preparation",
            "type":"Services"
        }
    ],
    "sg:phone":"+1 956 412 2621",
    "sg:postcode":"78550",
    "sg:province":"TX",
    "wof:name":"Enrique Ledesma CPA",
    "wof:placetype":"venue"
},
  "geometry": {"coordinates":[-97.685829,26.189568],"type":"Point"}
}