{
  "type": "Feature",
  "properties": {
    "iso:country":"US",
    "sg:address":"11230 Jones Rd W",
    "sg:city":"Houston",
    "sg:classifiers":[
        {
            "category":"Wholesale",
            "subcategory":"Electrical",
            "type":"Manufacturing & Wholesale Goods"
        }
    ],
    "sg:phone":"+1 281 897 9551",
    "sg:postcode":"77065",
    "sg:province":"TX",
    "sg:tags":[
        "alarm",
        "burglar",
        "system"
    ],
    "wof:name":"Armor Alarms",
    "wof:placetype":"venue"
},
  "geometry": {"coordinates":[-95.587615,29.935615],"type":"Point"}
}