{
  "type": "Feature",
  "properties": {
    "iso:country":"US",
    "sg:address":"1801 Avenue E",
    "sg:city":"Del Rio",
    "sg:classifiers":[
        {
            "category":"Retail",
            "subcategory":"Auto Repair",
            "type":"Services"
        }
    ],
    "sg:phone":"+1 830 775 8382",
    "sg:postcode":"78840",
    "sg:province":"TX",
    "sg:tags":[
        "transmission",
        "automotive",
        "general"
    ],
    "wof:name":"Tbs Used Cars",
    "wof:placetype":"venue"
},
  "geometry": {"coordinates":[-100.906035,29.381088],"type":"Point"}
}