{
  "type": "Feature",
  "properties": {
    "iso:country":"US",
    "sg:address":"1703 Northwood Ct",
    "sg:city":"Longview",
    "sg:classifiers":[
        {
            "category":"Professional",
            "subcategory":"Business Services",
            "type":"Services"
        }
    ],
    "sg:phone":"+1 903 297 3090",
    "sg:postcode":"75605",
    "sg:province":"TX",
    "wof:name":"A & J Enterprises",
    "wof:placetype":"venue"
},
  "geometry": {"coordinates":[-94.778181,32.532736],"type":"Point"}
}