{
  "type": "Feature",
  "properties": {
    "iso:country":"US",
    "sg:address":"4501 N Versailles Ave",
    "sg:city":"Dallas",
    "sg:classifiers":[
        {
            "category":"Professional",
            "type":"Services"
        }
    ],
    "sg:phone":"+1 214 559 2303",
    "sg:postcode":"75205",
    "sg:province":"TX",
    "wof:name":"Kevin Magee",
    "wof:placetype":"venue"
},
  "geometry": {"coordinates":[-96.815422,32.831283],"type":"Point"}
}