{
  "type": "Feature",
  "properties": {
    "iso:country":"US",
    "sg:address":"3601 Regent Blvd",
    "sg:city":"Irving",
    "sg:classifiers":[
        {
            "category":"Restaurant",
            "type":"Food & Drink"
        }
    ],
    "sg:phone":"+1 972 915 0001",
    "sg:postcode":"75063",
    "sg:province":"TX",
    "sg:tags":[
        "pizza"
    ],
    "wof:name":"Cavalli Pizza",
    "wof:placetype":"venue"
},
  "geometry": {"coordinates":[-96.995651,32.920658],"type":"Point"}
}