{
  "type": "Feature",
  "properties": {
    "iso:country":"US",
    "sg:address":"408 Jackson St",
    "sg:city":"Farmersville",
    "sg:classifiers":[
        {
            "category":"Recreation",
            "type":"Entertainment"
        }
    ],
    "sg:phone":"+1 972 782 8433",
    "sg:postcode":"75442",
    "sg:province":"TX",
    "wof:name":"Cynthia Cox Massage & Yoga",
    "wof:placetype":"venue"
},
  "geometry": {"coordinates":[-96.35857300000001,33.169072],"type":"Point"}
}