{
  "type": "Feature",
  "properties": {
    "iso:country":"US",
    "sg:address":"901 E Ave K",
    "sg:city":"Grand Prairie",
    "sg:classifiers":[
        {
            "category":"Education",
            "subcategory":"Vocational School",
            "type":"Public Place"
        }
    ],
    "sg:phone":"+1 972 647 1607",
    "sg:postcode":"75050",
    "sg:province":"TX",
    "sg:tags":[
        "reporting"
    ],
    "wof:name":"Arlington Crt Rporting College",
    "wof:placetype":"venue"
},
  "geometry": {"coordinates":[-97.052318,32.771492],"type":"Point"}
}