{
  "type": "Feature",
  "properties": {
    "iso:country":"US",
    "sg:address":"1901 W Commerce St",
    "sg:city":"San Antonio",
    "sg:classifiers":[
        {
            "category":"Restaurant",
            "type":"Food & Drink"
        }
    ],
    "sg:phone":"+1 210 223 1800",
    "sg:postcode":"78207",
    "sg:province":"TX",
    "sg:tags":[
        "eating"
    ],
    "wof:name":"Las Brisas Restaurant 1",
    "wof:placetype":"venue"
},
  "geometry": {"coordinates":[-98.51669099999999,29.427204],"type":"Point"}
}