{
  "type": "Feature",
  "properties": {
    "iso:country":"US",
    "sg:address":"2307 Nuches Ln",
    "sg:city":"Bryan",
    "sg:classifiers":[
        {
            "category":"Retail",
            "subcategory":"Auto Repair",
            "type":"Services"
        }
    ],
    "sg:phone":"+1 979 778 8841",
    "sg:postcode":"77803",
    "sg:province":"TX",
    "sg:tags":[
        "general"
    ],
    "wof:name":"Auto Mechanic On Wheels",
    "wof:placetype":"venue"
},
  "geometry": {"coordinates":[-96.368032,30.701069],"type":"Point"}
}