{
  "type": "Feature",
  "properties": {
    "iso:country":"US",
    "sg:address":"1515 N Town East Blvd Ste 138",
    "sg:city":"Mesquite",
    "sg:classifiers":[
        {
            "category":"Real Estate",
            "subcategory":"Real Estate Services",
            "type":"Services"
        }
    ],
    "sg:phone":"+1 972 241 3711",
    "sg:postcode":"75150",
    "sg:province":"TX",
    "sg:tags":[
        "home",
        "inspector"
    ],
    "wof:name":"AmeriSpec Home Inspection",
    "wof:placetype":"venue"
},
  "geometry": {"coordinates":[-96.618641,32.811017],"type":"Point"}
}