{
  "type": "Feature",
  "properties": {
    "iso:country":"US",
    "sg:address":"209 Investment Loop",
    "sg:city":"Hutto",
    "sg:classifiers":[
        {
            "category":"Transit Center",
            "subcategory":"Freight",
            "type":"Transportation"
        },
        {
            "category":"Freight",
            "type":"Transportation"
        }
    ],
    "sg:phone":"+1 512 846 2675",
    "sg:postcode":"78634",
    "sg:province":"TX",
    "sg:tags":[
        "local",
        "trucking-motor",
        "trucking"
    ],
    "wof:name":"Seventy Nine Inc",
    "wof:placetype":"venue"
},
  "geometry": {"coordinates":[-97.58425699999999,30.537406],"type":"Point"}
}