{
  "type": "Feature",
  "properties": {
    "iso:country":"US",
    "sg:address":"800 Fall Creek Hwy",
    "sg:city":"Granbury",
    "sg:classifiers":[
        {
            "category":"Building & Trades",
            "subcategory":"Construction",
            "type":"Services"
        }
    ],
    "sg:phone":"+1 817 910 2575",
    "sg:postcode":"76049",
    "sg:province":"TX",
    "sg:tags":[
        "house"
    ],
    "wof:name":"Granbury Construction Co Inc",
    "wof:placetype":"venue"
},
  "geometry": {"coordinates":[-97.693303,32.464658],"type":"Point"}
}