{
  "type": "Feature",
  "properties": {
    "iso:country":"US",
    "sg:address":"8101 John T White Rd",
    "sg:city":"Fort Worth",
    "sg:classifiers":[
        {
            "category":"Professional",
            "subcategory":"Advertising",
            "type":"Services"
        }
    ],
    "sg:phone":"+1 817 461 6129",
    "sg:postcode":"76120",
    "sg:province":"TX",
    "sg:tags":[
        "agency"
    ],
    "wof:name":"Dave Fulsons Total Outdoor",
    "wof:placetype":"venue"
},
  "geometry": {"coordinates":[-97.172753,32.764915],"type":"Point"}
}