{
  "type": "Feature",
  "properties": {
    "iso:country":"US",
    "sg:address":"5453 Burnet Rd",
    "sg:city":"Austin",
    "sg:classifiers":[
        {
            "category":"Wholesale",
            "subcategory":"Non-durable Goods",
            "type":"Manufacturing & Wholesale Goods"
        }
    ],
    "sg:phone":"+1 512 633 4578",
    "sg:postcode":"78756",
    "sg:province":"TX",
    "wof:name":"Mexicantera Imports LLC",
    "wof:placetype":"venue"
},
  "geometry": {"coordinates":[-97.739779,30.329603],"type":"Point"}
}