{
  "type": "Feature",
  "properties": {
    "iso:country":"US",
    "sg:address":"407 S Main St",
    "sg:city":"Weatherford",
    "sg:classifiers":[
        {
            "category":"Shopping",
            "subcategory":"Pharmacy",
            "type":"Retail Goods"
        }
    ],
    "sg:phone":"+1 817 613 1318",
    "sg:postcode":"76086",
    "sg:province":"TX",
    "wof:name":"CVS Pharmacy",
    "wof:placetype":"venue"
},
  "geometry": {"coordinates":[-97.797326,32.754605],"type":"Point"}
}