{
  "type": "Feature",
  "properties": {
    "iso:country":"US",
    "sg:address":"11208 West Ave",
    "sg:city":"San Antonio",
    "sg:classifiers":[
        {
            "category":"Real Estate",
            "subcategory":"Real Estate Operator",
            "type":"Services"
        }
    ],
    "sg:phone":"+1 210 735 7333",
    "sg:postcode":"78213",
    "sg:province":"TX",
    "sg:tags":[
        "building",
        "parks"
    ],
    "wof:name":"North Star Prop-Lori El Apt",
    "wof:placetype":"venue"
},
  "geometry": {"coordinates":[-98.512468,29.542743],"type":"Point"}
}