{
  "type": "Feature",
  "properties": {
    "iso:country":"US",
    "sg:address":"5425 Burnet Rd",
    "sg:city":"Austin",
    "sg:classifiers":[
        {
            "category":"Real Estate",
            "subcategory":"Real Estate Agent",
            "type":"Services"
        }
    ],
    "sg:phone":"+1 512 453 6611",
    "sg:postcode":"78756",
    "sg:province":"TX",
    "wof:name":"Nelson Puett & Assoc Realtors",
    "wof:placetype":"venue"
},
  "geometry": {"coordinates":[-97.739811,30.330018],"type":"Point"}
}