{
  "type": "Feature",
  "properties": {
    "iso:country":"US",
    "sg:address":"3213 E Central Texas Expy",
    "sg:city":"Killeen",
    "sg:classifiers":[
        {
            "category":"Restaurant",
            "type":"Food & Drink"
        }
    ],
    "sg:phone":"+1 254 690 7888",
    "sg:postcode":"76543",
    "sg:province":"TX",
    "sg:tags":[
        "delicatessen"
    ],
    "wof:name":"Deli Management Inc",
    "wof:placetype":"venue"
},
  "geometry": {"coordinates":[-97.710577,31.085946],"type":"Point"}
}