{
  "type": "Feature",
  "properties": {
    "iso:country":"US",
    "sg:address":"933 Fm 230",
    "sg:city":"Trinity",
    "sg:classifiers":[
        {
            "category":"Travel",
            "subcategory":"Hotels & Motels",
            "type":"Entertainment"
        },
        {
            "category":"Travel",
            "subcategory":"Bed & Breakfast",
            "type":"Entertainment"
        }
    ],
    "sg:phone":"+1 936 594 3986",
    "sg:postcode":"75862",
    "sg:province":"TX",
    "sg:tags":[
        "inn",
        "lodging"
    ],
    "wof:name":"Whispering Pines Dude Ranch",
    "wof:placetype":"venue"
},
  "geometry": {"coordinates":[-95.417281,30.95827],"type":"Point"}
}