{
  "type": "Feature",
  "properties": {
    "iso:country":"US",
    "sg:address":"5203 Harry Hines Blvd",
    "sg:city":"Dallas",
    "sg:classifiers":[
        {
            "category":"Restaurant",
            "type":"Food & Drink"
        }
    ],
    "sg:phone":"+1 214 879 0355",
    "sg:postcode":"75235",
    "sg:province":"TX",
    "sg:tags":[
        "mexican"
    ],
    "wof:name":"Ufood & Urban Taco",
    "wof:placetype":"venue"
},
  "geometry": {"coordinates":[-96.837834,32.811952],"type":"Point"}
}