{
  "type": "Feature",
  "properties": {
    "iso:country":"US",
    "sg:address":"1700 Sidney Baker St",
    "sg:city":"Kerrville",
    "sg:classifiers":[
        {
            "category":"Utilities",
            "subcategory":"Telephone",
            "type":"Services"
        },
        {
            "category":"Communications",
            "type":"Services"
        }
    ],
    "sg:phone":"+1 830 258 4900",
    "sg:postcode":"78028",
    "sg:province":"TX",
    "sg:tags":[
        "consultant",
        "telecommunication"
    ],
    "wof:name":"Hill Country Telecommunications",
    "wof:placetype":"venue"
},
  "geometry": {"coordinates":[-99.124512,30.06148],"type":"Point"}
}