{
  "type": "Feature",
  "properties": {
    "iso:country":"US",
    "sg:address":"1611 Texoma Pkwy",
    "sg:city":"Sherman",
    "sg:classifiers":[
        {
            "category":"Autos & Motor Vehicles",
            "subcategory":"Motorcycle Sales",
            "type":"Retail Goods"
        }
    ],
    "sg:phone":"+1 903 893 1402",
    "sg:postcode":"75090",
    "sg:province":"TX",
    "sg:tags":[
        "scooter",
        "boat"
    ],
    "wof:name":"Cone's Motorcycle Sales",
    "wof:placetype":"venue"
},
  "geometry": {"coordinates":[-96.608135,33.652458],"type":"Point"}
}