{
  "type": "Feature",
  "properties": {
    "iso:country":"US",
    "sg:address":"4700 Baytree Ave",
    "sg:city":"Denton",
    "sg:classifiers":[
        {
            "category":"Shopping",
            "type":"Retail Goods"
        }
    ],
    "sg:phone":"+1 940 272 0075",
    "sg:postcode":"76208",
    "sg:province":"TX",
    "sg:tags":[
        "merchandise"
    ],
    "wof:name":"Purewater Systems",
    "wof:placetype":"venue"
},
  "geometry": {"coordinates":[-97.06928000000001,33.169008],"type":"Point"}
}