{
  "type": "Feature",
  "properties": {
    "iso:country":"US",
    "sg:address":"16618 Southwest Fwy",
    "sg:city":"Sugar Land",
    "sg:classifiers":[
        {
            "category":"Shopping",
            "subcategory":"Hobbies, Toys, & Games",
            "type":"Retail Goods"
        }
    ],
    "sg:phone":"+1 281 277 8697",
    "sg:postcode":"77479",
    "sg:province":"TX",
    "sg:tags":[
        "clothing",
        "store"
    ],
    "wof:name":"Toys R Us",
    "wof:placetype":"venue"
},
  "geometry": {"coordinates":[-95.631078,29.591184],"type":"Point"}
}