{
  "type": "Feature",
  "properties": {
    "iso:country":"US",
    "sg:address":"4000 Shannon Ln",
    "sg:city":"Dallas",
    "sg:classifiers":[
        {
            "category":"Professional",
            "subcategory":"Business Services",
            "type":"Services"
        }
    ],
    "sg:phone":"+1 214 528 2255",
    "sg:postcode":"75205",
    "sg:province":"TX",
    "sg:tags":[
        "interior",
        "consultant",
        "design",
        "decorator"
    ],
    "wof:name":"Smith & Smith Design Inc",
    "wof:placetype":"venue"
},
  "geometry": {"coordinates":[-96.80327200000001,32.841904],"type":"Point"}
}