{
  "type": "Feature",
  "properties": {
    "iso:country":"US",
    "sg:address":"101 Southwest Pkwy",
    "sg:city":"College Station",
    "sg:classifiers":[
        {
            "category":"Food & Beverages",
            "subcategory":"Groceries & Convenience Stores",
            "type":"Retail Goods"
        }
    ],
    "sg:phone":"+1 979 693 1375",
    "sg:postcode":"77840",
    "sg:province":"TX",
    "wof:name":"Zip'n Stores Inc",
    "wof:placetype":"venue"
},
  "geometry": {"coordinates":[-96.329089,30.592056],"type":"Point"}
}