{
  "type": "Feature",
  "properties": {
    "iso:country":"US",
    "sg:address":"502 Lindsay St",
    "sg:city":"Gainesville",
    "sg:classifiers":[
        {
            "category":"Real Estate",
            "subcategory":"Developer",
            "type":"Services"
        }
    ],
    "sg:phone":"+1 940 668 2728",
    "sg:postcode":"76240",
    "sg:province":"TX",
    "sg:tags":[
        "cemetery"
    ],
    "wof:name":"Center Hill Cemetery Asso",
    "wof:placetype":"venue"
},
  "geometry": {"coordinates":[-97.141068,33.620748],"type":"Point"}
}