{
  "type": "Feature",
  "properties": {
    "iso:country":"US",
    "sg:address":"100 W Pioneer Pkwy",
    "sg:city":"Arlington",
    "sg:classifiers":[
        {
            "category":"Health Services",
            "subcategory":"Doctor",
            "type":"Services"
        }
    ],
    "sg:phone":"+1 817 261 4982",
    "sg:postcode":"76010",
    "sg:province":"TX",
    "sg:tags":[
        "dentist"
    ],
    "wof:name":"Bich-Huong Nguyen Inc",
    "wof:placetype":"venue"
},
  "geometry": {"coordinates":[-97.10923699999999,32.708025],"type":"Point"}
}