{
  "type": "Feature",
  "properties": {
    "iso:country":"US",
    "sg:address":"1502 Mc Gee Ln",
    "sg:city":"Lewisville",
    "sg:classifiers":[
        {
            "category":"Wholesale",
            "subcategory":"Drugs",
            "type":"Manufacturing & Wholesale Goods"
        }
    ],
    "sg:phone":"+1 972 317 7926",
    "sg:postcode":"75077",
    "sg:province":"TX",
    "sg:tags":[
        "shop",
        "beauty"
    ],
    "wof:name":"Nylynn Cosmetics Inc",
    "wof:placetype":"venue"
},
  "geometry": {"coordinates":[-97.027255,33.064167],"type":"Point"}
}