{
  "type": "Feature",
  "properties": {
    "iso:country":"US",
    "sg:address":"4727 Strack Rd",
    "sg:city":"Houston",
    "sg:classifiers":[
        {
            "category":"Retail",
            "subcategory":"Repair Shop",
            "type":"Services"
        }
    ],
    "sg:phone":"+1 281 580 4099",
    "sg:postcode":"77069",
    "sg:province":"TX",
    "sg:tags":[
        "equipment",
        "conditioning",
        "air"
    ],
    "wof:name":"Extreme Air Conditioning Svc",
    "wof:placetype":"venue"
},
  "geometry": {"coordinates":[-95.51506500000001,30.000315],"type":"Point"}
}