{
  "type": "Feature",
  "properties": {
    "iso:country":"US",
    "sg:address":"630 N Americas Ave",
    "sg:city":"El Paso",
    "sg:classifiers":[
        {
            "category":"Insurance",
            "subcategory":"Insurance Agent",
            "type":"Services"
        }
    ],
    "sg:phone":"+1 915 858 1026",
    "sg:postcode":"79907",
    "sg:province":"TX",
    "wof:name":"Farm Bureau Insurance",
    "wof:placetype":"venue"
},
  "geometry": {"coordinates":[-106.307609,31.68252],"type":"Point"}
}