{
  "type": "Feature",
  "properties": {
    "iso:country":"US",
    "sg:address":"702 W Galbraith St",
    "sg:city":"Hebbronville",
    "sg:classifiers":[
        {
            "category":"Retail",
            "subcategory":"Auto Rental",
            "type":"Services"
        },
        {
            "category":"Building & Trades",
            "subcategory":"Equipment Rental",
            "type":"Services"
        }
    ],
    "sg:phone":"+1 361 527 2165",
    "sg:postcode":"78361",
    "sg:province":"TX",
    "sg:tags":[
        "renting",
        "leasing",
        "truck",
        "trailer",
        "yard",
        "store"
    ],
    "sg:website":"http://www.uhaul.com/Locations/Rentals-near-Hebbronville-TX-78361/005458",
    "wof:name":"U-Haul Neighborhood Dealer - Ng4 Storage",
    "wof:placetype":"venue"
},
  "geometry": {"coordinates":[-98.685211,27.307041],"type":"Point"}
}