{
  "type": "Feature",
  "properties": {
    "iso:country":"US",
    "sg:address":"7663 Dowdell Rd",
    "sg:city":"Spring",
    "sg:classifiers":[
        {
            "category":"Home & Garden",
            "subcategory":"Building Materials",
            "type":"Retail Goods"
        },
        {
            "category":"Building & Trades",
            "subcategory":"Construction",
            "type":"Services"
        }
    ],
    "sg:phone":"+1 832 514 4148",
    "sg:postcode":"77389",
    "sg:province":"TX",
    "sg:tags":[
        "insulation",
        "roofing",
        "window",
        "siding",
        "contractor"
    ],
    "sg:website":"http://houston.citysearch.com/profile/external/653772320/spring_tx/roskos_roofing.html?publisher=yellowpages&reference_id=7&placement=ypwebsitemip",
    "wof:name":"Roskos Roofing",
    "wof:placetype":"venue"
},
  "geometry": {"coordinates":[-95.538217,30.101271],"type":"Point"}
}