{
  "type": "Feature",
  "properties": {
    "iso:country":"US",
    "sg:address":"300 Crescent Ct Ste 1500",
    "sg:city":"Dallas",
    "sg:classifiers":[
        {
            "category":"Professional",
            "subcategory":"Lawyer & Legal Services",
            "type":"Services"
        }
    ],
    "sg:phone":"+1 214 978 4000",
    "sg:postcode":"75201",
    "sg:province":"TX",
    "sg:website":"www.mckoolsmith.com",
    "wof:name":"McKool Smith A Professional Corporation",
    "wof:placetype":"venue"
},
  "geometry": {"coordinates":[-96.804298,32.7938],"type":"Point"}
}