{
  "type": "Feature",
  "properties": {
    "iso:country":"US",
    "sg:address":"211 FM 1960 W",
    "sg:city":"Houston",
    "sg:classifiers":[
        {
            "category":"Personal",
            "subcategory":"Beauty Salon",
            "type":"Services"
        }
    ],
    "sg:phone":"+1 281 866 9000",
    "sg:postcode":"77090",
    "sg:province":"TX",
    "wof:name":"Design Secrets",
    "wof:placetype":"venue"
},
  "geometry": {"coordinates":[-95.43144599999999,30.020337],"type":"Point"}
}