{
  "type": "Feature",
  "properties": {
    "iso:country":"US",
    "sg:address":"208 Castleridge Dr",
    "sg:city":"Little Elm",
    "sg:classifiers":[
        {
            "category":"Professional",
            "subcategory":"Computer Services",
            "type":"Services"
        }
    ],
    "sg:phone":"+1 817 800 0042",
    "sg:postcode":"75068",
    "sg:province":"TX",
    "sg:tags":[
        "related"
    ],
    "wof:name":"Pat Cody & Assoc Inc",
    "wof:placetype":"venue"
},
  "geometry": {"coordinates":[-96.91738100000001,33.173024],"type":"Point"}
}