{
  "type": "Feature",
  "properties": {
    "iso:country":"US",
    "sg:address":"65 E Ave K",
    "sg:city":"San Angelo",
    "sg:classifiers":[
        {
            "category":"Wholesale",
            "subcategory":"Electrical",
            "type":"Manufacturing & Wholesale Goods"
        }
    ],
    "sg:phone":"+1 325 653 4255",
    "sg:postcode":"76903",
    "sg:province":"TX",
    "sg:tags":[
        "electric",
        "mfg",
        "rewinding",
        "equipment",
        "motor",
        "armature"
    ],
    "wof:name":"Indeco Industrial Electric Co",
    "wof:placetype":"venue"
},
  "geometry": {"coordinates":[-100.43404700000001,31.445993],"type":"Point"}
}