{
  "type": "Feature",
  "properties": {
    "iso:country":"US",
    "sg:address":"3535 Briarpark Dr",
    "sg:city":"Houston",
    "sg:classifiers":[
        {
            "category":"Freight",
            "type":"Transportation"
        }
    ],
    "sg:phone":"+1 713 952 5101",
    "sg:postcode":"77042",
    "sg:province":"TX",
    "sg:tags":[
        "commercial",
        "storage"
    ],
    "wof:name":"Underground Storage Assoc Inc",
    "wof:placetype":"venue"
},
  "geometry": {"coordinates":[-95.548868,29.726161],"type":"Point"}
}