{
  "type": "Feature",
  "properties": {
    "iso:country":"US",
    "sg:address":"1107 W Laurel St",
    "sg:city":"San Antonio",
    "sg:classifiers":[
        {
            "category":"Manufacturing",
            "subcategory":"Apparel",
            "type":"Manufacturing & Wholesale Goods"
        }
    ],
    "sg:phone":"+1 210 733 3961",
    "sg:postcode":"78201",
    "sg:province":"TX",
    "sg:tags":[
        "outerwear",
        "mfg"
    ],
    "wof:name":"Charles Castro Mfg Co",
    "wof:placetype":"venue"
},
  "geometry": {"coordinates":[-98.50901500000001,29.442552],"type":"Point"}
}