{
  "type": "Feature",
  "properties": {
    "iso:country":"US",
    "sg:address":"6060 Bellaire Blvd Ste D",
    "sg:city":"Houston",
    "sg:classifiers":[
        {
            "category":"Shopping",
            "subcategory":"Mobile Phones",
            "type":"Retail Goods"
        }
    ],
    "sg:phone":"+1 713 667 4444",
    "sg:postcode":"77081",
    "sg:province":"TX",
    "wof:name":"L Fiesta Phone",
    "wof:placetype":"venue"
},
  "geometry": {"coordinates":[-95.488356,29.705715],"type":"Point"}
}