{
  "type": "Feature",
  "properties": {
    "iso:country":"US",
    "sg:address":"4 Aubrey Ct",
    "sg:city":"San Antonio",
    "sg:classifiers":[
        {
            "category":"Building & Trades",
            "subcategory":"Construction",
            "type":"Services"
        }
    ],
    "sg:phone":"+1 210 494 4557",
    "sg:postcode":"78216",
    "sg:province":"TX",
    "sg:tags":[
        "house"
    ],
    "wof:name":"Covenant Decks",
    "wof:placetype":"venue"
},
  "geometry": {"coordinates":[-98.474992,29.555377],"type":"Point"}
}