{
  "type": "Feature",
  "properties": {
    "iso:country":"US",
    "sg:address":"1050 N Westmoreland Rd Ste 308",
    "sg:city":"Dallas",
    "sg:classifiers":[
        {
            "category":"Social Services",
            "subcategory":"Child Care",
            "type":"Services"
        }
    ],
    "sg:phone":"+1 214 467 4601",
    "sg:postcode":"75211",
    "sg:province":"TX",
    "sg:tags":[
        "day"
    ],
    "wof:name":"A Step Ahead Learning Center",
    "wof:placetype":"venue"
},
  "geometry": {"coordinates":[-96.87400100000001,32.756599],"type":"Point"}
}