{
  "type": "Feature",
  "properties": {
    "iso:country":"US",
    "sg:address":"1221 E 6th St",
    "sg:city":"Bonham",
    "sg:classifiers":[
        {
            "category":"Health Services",
            "subcategory":"Hospital",
            "type":"Services"
        },
        {
            "category":"Health Services",
            "subcategory":"Clinic",
            "type":"Services"
        }
    ],
    "sg:phone":"+1 903 583 8583",
    "sg:postcode":"75418",
    "sg:province":"TX",
    "sg:tags":[
        "mental",
        "outpatient",
        "specialty"
    ],
    "wof:name":"Mental Health Mental Retardatn",
    "wof:placetype":"venue"
},
  "geometry": {"coordinates":[-96.16600099999999,33.57915],"type":"Point"}
}