{
  "type": "Feature",
  "properties": {
    "iso:country":"US",
    "sg:address":"2828 Fishtrap Rd",
    "sg:city":"Dallas",
    "sg:classifiers":[
        {
            "category":"Government",
            "subcategory":"Office",
            "type":"Public Place"
        }
    ],
    "sg:phone":"+1 214 670 6340",
    "sg:postcode":"75212",
    "sg:province":"TX",
    "sg:tags":[
        "village"
    ],
    "sg:website":"www.cityhall.com",
    "wof:name":"West Dallas Multipurpose Ctr",
    "wof:placetype":"venue"
},
  "geometry": {"coordinates":[-96.860749,32.778443],"type":"Point"}
}