{
  "type": "Feature",
  "properties": {
    "iso:country":"US",
    "sg:address":"80 Braeswood Sq",
    "sg:city":"Houston",
    "sg:classifiers":[
        {
            "category":"Personal",
            "subcategory":"Beauty Salon",
            "type":"Services"
        },
        {
            "category":"Personal",
            "subcategory":"Hair Removal",
            "type":"Services"
        },
        {
            "category":"Personal",
            "subcategory":"Day Spa",
            "type":"Services"
        }
    ],
    "sg:phone":"+1 713 777 4455",
    "sg:postcode":"77096",
    "sg:province":"TX",
    "sg:tags":[
        "makeup",
        "artist"
    ],
    "sg:website":"www.mysalononline.com/AssuredIma...",
    "wof:name":"Assured Image II",
    "wof:placetype":"venue"
},
  "geometry": {"coordinates":[-95.412843,29.698406],"type":"Point"}
}