{
  "type": "Feature",
  "properties": {
    "iso:country":"US",
    "sg:address":"7000 Regency Square Blvd",
    "sg:city":"Houston",
    "sg:classifiers":[
        {
            "category":"Real Estate",
            "subcategory":"Real Estate Agent",
            "type":"Services"
        }
    ],
    "sg:phone":"+1 713 952 5066",
    "sg:postcode":"77036",
    "sg:province":"TX",
    "wof:name":"Ryland Enterprise Inc",
    "wof:placetype":"venue"
},
  "geometry": {"coordinates":[-95.506827,29.715681],"type":"Point"}
}