{
  "type": "Feature",
  "properties": {
    "iso:country":"US",
    "sg:address":"1041 W Plantation Dr",
    "sg:city":"Clute",
    "sg:classifiers":[
        {
            "category":"Restaurant",
            "type":"Food & Drink"
        }
    ],
    "sg:menulink":"http://www.allmenus.com/tx/brazosport/177348-jack-in-the-box/menu/",
    "sg:phone":"+1 979 265 5190",
    "sg:postcode":"77531",
    "sg:province":"TX",
    "sg:tags":[
        "burger",
        "american"
    ],
    "wof:name":"Jack in the Box",
    "wof:placetype":"venue"
},
  "geometry": {"coordinates":[-95.41865,29.018645],"type":"Point"}
}