{
  "type": "Feature",
  "properties": {
    "iso:country":"US",
    "sg:address":"25190 I- 45",
    "sg:city":"Spring",
    "sg:classifiers":[
        {
            "category":"Shopping",
            "subcategory":"Clothing, Apparel, & Fashions",
            "type":"Retail Goods"
        }
    ],
    "sg:phone":"+1 281 419 4040",
    "sg:postcode":"77386",
    "sg:province":"TX",
    "sg:tags":[
        "tailor"
    ],
    "wof:name":"Kim Tailors",
    "wof:placetype":"venue"
},
  "geometry": {"coordinates":[-95.443111,30.129077],"type":"Point"}
}