{
  "type": "Feature",
  "properties": {
    "iso:country":"US",
    "sg:address":"106 Live Oak Ln",
    "sg:city":"Riesel",
    "sg:classifiers":[
        {
            "category":"Manufacturing",
            "subcategory":"Building Materials",
            "type":"Manufacturing & Wholesale Goods"
        }
    ],
    "sg:phone":"+1 254 896 1144",
    "sg:postcode":"76682",
    "sg:province":"TX",
    "sg:tags":[
        "mfg",
        "wood",
        "kitchen",
        "cabinet"
    ],
    "wof:name":"Keith T Ehlers Co",
    "wof:placetype":"venue"
},
  "geometry": {"coordinates":[-96.909971,31.474615],"type":"Point"}
}