{
  "type": "Feature",
  "properties": {
    "iso:country":"US",
    "sg:address":"3306 54th St",
    "sg:city":"Lubbock",
    "sg:classifiers":[
        {
            "category":"Organizations",
            "subcategory":"Religious Organization",
            "type":"Services"
        }
    ],
    "sg:phone":"+1 806 798 3507",
    "sg:postcode":"79413",
    "sg:province":"TX",
    "sg:tags":[
        "church"
    ],
    "wof:name":"Church Of Jesus Christ Of Lds",
    "wof:placetype":"venue"
},
  "geometry": {"coordinates":[-101.887067,33.545186],"type":"Point"}
}