{
  "type": "Feature",
  "properties": {
    "iso:country":"US",
    "sg:address":"1910 Skillman St",
    "sg:city":"Dallas",
    "sg:classifiers":[
        {
            "category":"Retail",
            "subcategory":"Laundry & Dry Cleaning",
            "type":"Services"
        }
    ],
    "sg:phone":"+1 214 824 6865",
    "sg:postcode":"75206",
    "sg:province":"TX",
    "wof:name":"Rex Cleaners",
    "wof:placetype":"venue"
},
  "geometry": {"coordinates":[-96.761703,32.812901],"type":"Point"}
}