{
  "type": "Feature",
  "properties": {
    "iso:country":"US",
    "sg:address":"3513 Labadie Dr",
    "sg:city":"Fort Worth",
    "sg:classifiers":[
        {
            "category":"Manufacturing",
            "subcategory":"Glass & Minerals",
            "type":"Manufacturing & Wholesale Goods"
        }
    ],
    "sg:phone":"+1 817 590 9598",
    "sg:postcode":"76118",
    "sg:province":"TX",
    "sg:tags":[
        "product",
        "nonmetallic",
        "mfg"
    ],
    "wof:name":"Wright Deran",
    "wof:placetype":"venue"
},
  "geometry": {"coordinates":[-97.21759900000001,32.815502],"type":"Point"}
}