{
  "type": "Feature",
  "properties": {
    "iso:country":"US",
    "sg:address":"9605 S Co Rd 1218",
    "sg:city":"Midland",
    "sg:classifiers":[
        {
            "category":"Autos & Motor Vehicles",
            "subcategory":"Fuel & Gas Station",
            "type":"Retail Goods"
        }
    ],
    "sg:phone":"+1 432 682 2768",
    "sg:postcode":"79706",
    "sg:province":"TX",
    "sg:tags":[
        "gasoline"
    ],
    "wof:name":"Texaco",
    "wof:placetype":"venue"
},
  "geometry": {"coordinates":[-102.085506,31.855206],"type":"Point"}
}