{
  "type": "Feature",
  "properties": {
    "iso:country":"US",
    "sg:address":"2222 Branard St",
    "sg:city":"Houston",
    "sg:classifiers":[
        {
            "category":"Shopping",
            "subcategory":"Gifts & Souvenirs",
            "type":"Retail Goods"
        }
    ],
    "sg:phone":"+1 713 533 0482",
    "sg:postcode":"77098",
    "sg:province":"TX",
    "sg:tags":[
        "shop"
    ],
    "wof:name":"Creative Gifts Of Texas",
    "wof:placetype":"venue"
},
  "geometry": {"coordinates":[-95.416009,29.736999],"type":"Point"}
}