{
  "type": "Feature",
  "properties": {
    "iso:country":"US",
    "sg:address":"406 Grantham Rd",
    "sg:city":"Baytown",
    "sg:classifiers":[
        {
            "category":"Manufacturing",
            "subcategory":"Glass & Minerals",
            "type":"Manufacturing & Wholesale Goods"
        }
    ],
    "sg:phone":"+1 281 422 7598",
    "sg:postcode":"77521",
    "sg:province":"TX",
    "sg:tags":[
        "ready",
        "concrete",
        "mfg"
    ],
    "wof:name":"Daniel Gonzales Make Ready Svc",
    "wof:placetype":"venue"
},
  "geometry": {"coordinates":[-94.969433,29.751091],"type":"Point"}
}