{
  "type": "Feature",
  "properties": {
    "iso:country":"US",
    "sg:address":"1101 Meandering Way",
    "sg:city":"Garland",
    "sg:classifiers":[
        {
            "category":"Freight",
            "type":"Transportation"
        }
    ],
    "sg:phone":"+1 972 530 4224",
    "sg:postcode":"75040",
    "sg:province":"TX",
    "sg:tags":[
        "operator",
        "local",
        "trucking"
    ],
    "wof:name":"Lewis Rw Trucking",
    "wof:placetype":"venue"
},
  "geometry": {"coordinates":[-96.612574,32.931478],"type":"Point"}
}