{
  "type": "Feature",
  "properties": {
    "iso:country":"US",
    "sg:address":"236 E Maddox Ave",
    "sg:city":"Aransas Pass",
    "sg:classifiers":[
        {
            "category":"Organizations",
            "subcategory":"Religious Organization",
            "type":"Services"
        }
    ],
    "sg:phone":"+1 361 758 3611",
    "sg:postcode":"78336",
    "sg:province":"TX",
    "wof:name":"Antioch Baptist Church",
    "wof:placetype":"venue"
},
  "geometry": {"coordinates":[-97.138374,27.909583],"type":"Point"}
}