{
  "type": "Feature",
  "properties": {
    "iso:country":"US",
    "sg:address":"10528 Lakewood Ave",
    "sg:city":"El Paso",
    "sg:classifiers":[
        {
            "category":"Retail",
            "subcategory":"Repair Shop",
            "type":"Services"
        },
        {
            "category":"Building & Trades",
            "subcategory":"Plumbing",
            "type":"Services"
        }
    ],
    "sg:phone":"+1 915 474 9332",
    "sg:postcode":"79925",
    "sg:province":"TX",
    "sg:tags":[
        "boiler",
        "cleaning"
    ],
    "wof:name":"Southwest Industrial Works",
    "wof:placetype":"venue"
},
  "geometry": {"coordinates":[-106.34184500000001,31.758276],"type":"Point"}
}