{
  "type": "Feature",
  "properties": {
    "iso:country":"US",
    "sg:address":"713 S Main St",
    "sg:city":"Quitman",
    "sg:classifiers":[
        {
            "category":"Professional",
            "subcategory":"Engineering",
            "type":"Services"
        },
        {
            "category":"Professional",
            "subcategory":"Computer Services",
            "type":"Services"
        }
    ],
    "sg:phone":"+1 903 763 2424",
    "sg:postcode":"75783",
    "sg:province":"TX",
    "sg:tags":[
        "repair",
        "designer",
        "consultant",
        "integration",
        "system",
        "equipment-service",
        "engineer"
    ],
    "sg:website":"http://www.bulldogcomputer.com",
    "wof:name":"Bulldog Computer",
    "wof:placetype":"venue"
},
  "geometry": {"coordinates":[-95.455443,32.786184],"type":"Point"}
}