{
  "type": "Feature",
  "properties": {
    "iso:country":"US",
    "sg:address":"6142 John Chapman",
    "sg:city":"San Antonio",
    "sg:classifiers":[
        {
            "category":"Restaurant",
            "type":"Food & Drink"
        }
    ],
    "sg:phone":"+1 210 682 7667",
    "sg:postcode":"78240",
    "sg:province":"TX",
    "sg:tags":[
        "eating"
    ],
    "wof:name":"We Get Dinner For You",
    "wof:placetype":"venue"
},
  "geometry": {"coordinates":[-98.601184,29.51031],"type":"Point"}
}