{
  "type": "Feature",
  "properties": {
    "iso:country":"US",
    "sg:address":"219 W Broadway St",
    "sg:city":"Sweetwater",
    "sg:classifiers":[
        {
            "category":"Restaurant",
            "type":"Food & Drink"
        }
    ],
    "sg:phone":"+1 325 235 1125",
    "sg:postcode":"79556",
    "sg:province":"TX",
    "wof:name":"Remember When",
    "wof:placetype":"venue"
},
  "geometry": {"coordinates":[-100.40969800000001,32.46949],"type":"Point"}
}