{
  "type": "Feature",
  "properties": {
    "iso:country":"US",
    "sg:address":"17560 Kuykendahl Rd",
    "sg:city":"Spring",
    "sg:classifiers":[
        {
            "category":"Personal",
            "subcategory":"Beauty Salon",
            "type":"Services"
        }
    ],
    "sg:phone":"+1 281 350 8658",
    "sg:postcode":"77379",
    "sg:province":"TX",
    "sg:tags":[
        "shop"
    ],
    "wof:name":"Hair Gallery",
    "wof:placetype":"venue"
},
  "geometry": {"coordinates":[-95.479884,30.029253],"type":"Point"}
}