{
  "type": "Feature",
  "properties": {
    "iso:country":"US",
    "sg:address":"3402 Lilac St",
    "sg:city":"Pasadena",
    "sg:classifiers":[
        {
            "category":"Wholesale",
            "subcategory":"Auto Parts",
            "type":"Manufacturing & Wholesale Goods"
        }
    ],
    "sg:phone":"+1 281 487 2354",
    "sg:postcode":"77505",
    "sg:province":"TX",
    "sg:tags":[
        "turbochargers"
    ],
    "wof:name":"Cmi-Rotating Svc Ctr Inc",
    "wof:placetype":"venue"
},
  "geometry": {"coordinates":[-95.158737,29.660978],"type":"Point"}
}