{
  "type": "Feature",
  "properties": {
    "iso:country":"US",
    "sg:address":"1220 N Beach St",
    "sg:city":"Fort Worth",
    "sg:classifiers":[
        {
            "category":"Food & Beverages",
            "subcategory":"Groceries & Convenience Stores",
            "type":"Retail Goods"
        }
    ],
    "sg:phone":"+1 817 831 0681",
    "sg:postcode":"76111",
    "sg:province":"TX",
    "wof:name":"Minyard",
    "wof:placetype":"venue"
},
  "geometry": {"coordinates":[-97.290575,32.780111],"type":"Point"}
}