{
  "type": "Feature",
  "properties": {
    "iso:country":"US",
    "sg:address":"7004 Woodale Dr",
    "sg:city":"Fort Worth",
    "sg:classifiers":[
        {
            "category":"Professional",
            "subcategory":"Management & Consulting",
            "type":"Services"
        }
    ],
    "sg:phone":"+1 817 281 2128",
    "sg:postcode":"76148",
    "sg:province":"TX",
    "sg:tags":[
        "business"
    ],
    "wof:name":"Texas Roof Analis & Consulting",
    "wof:placetype":"venue"
},
  "geometry": {"coordinates":[-97.24713199999999,32.872627],"type":"Point"}
}