{
  "type": "Feature",
  "properties": {
    "iso:country":"US",
    "sg:address":"3001 W Irving Blvd",
    "sg:city":"Irving",
    "sg:classifiers":[
        {
            "category":"Shopping",
            "subcategory":"Books",
            "type":"Retail Goods"
        }
    ],
    "sg:phone":"+1 972 986 1026",
    "sg:postcode":"75061",
    "sg:province":"TX",
    "sg:tags":[
        "professional"
    ],
    "wof:name":"Family Christian Stores 189",
    "wof:placetype":"venue"
},
  "geometry": {"coordinates":[-96.988018,32.834212],"type":"Point"}
}