{
  "type": "Feature",
  "properties": {
    "iso:country":"US",
    "sg:address":"506 Border St",
    "sg:city":"Orange",
    "sg:classifiers":[
        {
            "category":"Building & Trades",
            "subcategory":"Construction",
            "type":"Services"
        }
    ],
    "sg:phone":"+1 409 988 0343",
    "sg:postcode":"77630",
    "sg:province":"TX",
    "sg:tags":[
        "contractor"
    ],
    "wof:name":"Shellys Resale",
    "wof:placetype":"venue"
},
  "geometry": {"coordinates":[-93.73708999999999,30.083279],"type":"Point"}
}