{
  "type": "Feature",
  "properties": {
    "iso:country":"US",
    "sg:address":"2100 Buckthorne Pl",
    "sg:city":"Spring",
    "sg:classifiers":[
        {
            "category":"Banks & Credit Unions",
            "subcategory":"Bank",
            "type":"Services"
        }
    ],
    "sg:phone":"+1 281 367 1212",
    "sg:postcode":"77380",
    "sg:province":"TX",
    "sg:tags":[
        "savings",
        "assoc",
        "loan"
    ],
    "wof:name":"Washington Mutual",
    "wof:placetype":"venue"
},
  "geometry": {"coordinates":[-95.47106599999999,30.141368],"type":"Point"}
}