{
  "type": "Feature",
  "properties": {
    "iso:country":"US",
    "sg:address":"1800 W Loop 281",
    "sg:city":"Longview",
    "sg:classifiers":[
        {
            "category":"Real Estate",
            "subcategory":"Architect",
            "type":"Services"
        }
    ],
    "sg:phone":"+1 903 297 5555",
    "sg:postcode":"75604",
    "sg:province":"TX",
    "sg:tags":[
        "architectural"
    ],
    "wof:name":"Potter Jeff Architects",
    "wof:placetype":"venue"
},
  "geometry": {"coordinates":[-94.78352099999999,32.523843],"type":"Point"}
}