{
  "type": "Feature",
  "properties": {
    "iso:country":"US",
    "sg:address":"310 Elmhurst Ave",
    "sg:city":"San Antonio",
    "sg:classifiers":[
        {
            "category":"Shopping",
            "subcategory":"Gifts & Souvenirs",
            "type":"Retail Goods"
        }
    ],
    "sg:phone":"+1 210 824 1176",
    "sg:postcode":"78209",
    "sg:province":"TX",
    "wof:name":"Francille L Radmann",
    "wof:placetype":"venue"
},
  "geometry": {"coordinates":[-98.463143,29.459455],"type":"Point"}
}