{
  "type": "Feature",
  "properties": {
    "iso:country":"US",
    "sg:address":"520 S Adams St",
    "sg:city":"Fredericksburg",
    "sg:classifiers":[
        {
            "category":"Mining & Drilling",
            "type":"Manufacturing & Wholesale Goods"
        }
    ],
    "sg:phone":"+1 830 990 0768",
    "sg:postcode":"78624",
    "sg:province":"TX",
    "sg:tags":[
        "weld",
        "top",
        "metal",
        "base",
        "table",
        "granite"
    ],
    "wof:name":"Granite & Iron Store Inc",
    "wof:placetype":"venue"
},
  "geometry": {"coordinates":[-98.87701300000001,30.270012],"type":"Point"}
}