{
  "type": "Feature",
  "properties": {
    "iso:country":"US",
    "sg:address":"4241 Tanglewood Ln",
    "sg:city":"Odessa",
    "sg:classifiers":[
        {
            "category":"Health Services",
            "subcategory":"Doctor",
            "type":"Services"
        }
    ],
    "sg:phone":"+1 432 552 7788",
    "sg:postcode":"79762",
    "sg:province":"TX",
    "sg:tags":[
        "surgery",
        "eye",
        "clinic"
    ],
    "wof:name":"Laser Ctr For Prmian Basin LLC",
    "wof:placetype":"venue"
},
  "geometry": {"coordinates":[-102.34233500000001,31.89321],"type":"Point"}
}