{
  "type": "Feature",
  "properties": {
    "iso:country":"US",
    "sg:address":"300 E Clay St",
    "sg:city":"West Columbia",
    "sg:classifiers":[
        {
            "category":"Social Services",
            "type":"Services"
        }
    ],
    "sg:phone":"+1 979 345 4121",
    "sg:postcode":"77486",
    "sg:province":"TX",
    "sg:tags":[
        "counseling"
    ],
    "wof:name":"Youth & Family Counseling Svcs",
    "wof:placetype":"venue"
},
  "geometry": {"coordinates":[-95.645827,29.142868],"type":"Point"}
}