{
  "type": "Feature",
  "properties": {
    "iso:country":"US",
    "sg:address":"401 State Hwy 78",
    "sg:city":"Wylie",
    "sg:classifiers":[
        {
            "category":"Banks & Credit Unions",
            "subcategory":"Bank",
            "type":"Services"
        }
    ],
    "sg:phone":"+1 972 442 2319",
    "sg:postcode":"75098",
    "sg:province":"TX",
    "sg:tags":[
        "cashing",
        "check"
    ],
    "wof:name":"ACE Cash Express",
    "wof:placetype":"venue"
},
  "geometry": {"coordinates":[-96.535482,33.014651],"type":"Point"}
}