{
  "type": "Feature",
  "properties": {
    "iso:country":"US",
    "sg:address":"1814 Dolphin Dr",
    "sg:city":"Portland",
    "sg:classifiers":[
        {
            "category":"Local Transit",
            "type":"Transportation"
        }
    ],
    "sg:phone":"+1 361 777 0005",
    "sg:postcode":"78374",
    "sg:province":"TX",
    "sg:tags":[
        "limousine"
    ],
    "wof:name":"Sunset Limousine",
    "wof:placetype":"venue"
},
  "geometry": {"coordinates":[-97.32369799999999,27.893113],"type":"Point"}
}