{
  "type": "Feature",
  "properties": {
    "iso:country":"US",
    "sg:address":"3212 Falls Dr",
    "sg:city":"Dallas",
    "sg:classifiers":[
        {
            "category":"Restaurant",
            "type":"Food & Drink"
        }
    ],
    "sg:phone":"+1 214 331 8000",
    "sg:postcode":"75211",
    "sg:province":"TX",
    "sg:tags":[
        "eating"
    ],
    "wof:name":"Parrilla Tacos",
    "wof:placetype":"venue"
},
  "geometry": {"coordinates":[-96.873043,32.72632],"type":"Point"}
}