{
  "type": "Feature",
  "properties": {
    "iso:country":"US",
    "sg:address":"608 Yaupon St",
    "sg:city":"Lake Jackson",
    "sg:classifiers":[
        {
            "category":"Professional",
            "subcategory":"Management & Consulting",
            "type":"Services"
        }
    ],
    "sg:phone":"+1 979 297 2593",
    "sg:postcode":"77566",
    "sg:province":"TX",
    "sg:tags":[
        "business"
    ],
    "wof:name":"Lafleur Consulting",
    "wof:placetype":"venue"
},
  "geometry": {"coordinates":[-95.43722699999999,29.039641],"type":"Point"}
}