{
  "type": "Feature",
  "properties": {
    "iso:country":"US",
    "sg:address":"1130 S Acme Rd",
    "sg:city":"San Antonio",
    "sg:classifiers":[
        {
            "category":"Building & Trades",
            "subcategory":"Construction",
            "type":"Services"
        }
    ],
    "sg:phone":"+1 210 431 9901",
    "sg:postcode":"78237",
    "sg:province":"TX",
    "sg:tags":[
        "general",
        "contractor"
    ],
    "wof:name":"Rule Construction",
    "wof:placetype":"venue"
},
  "geometry": {"coordinates":[-98.587743,29.409784],"type":"Point"}
}