{
  "type": "Feature",
  "properties": {
    "iso:country":"US",
    "sg:address":"801 Culver St",
    "sg:city":"Commerce",
    "sg:classifiers":[
        {
            "category":"Real Estate",
            "subcategory":"Real Estate Operator",
            "type":"Services"
        }
    ],
    "sg:phone":"+1 903 886 7038",
    "sg:postcode":"75428",
    "sg:province":"TX",
    "sg:tags":[
        "building",
        "apartment"
    ],
    "wof:name":"Quailridge Apartments",
    "wof:placetype":"venue"
},
  "geometry": {"coordinates":[-95.895308,33.236385],"type":"Point"}
}