{
  "type": "Feature",
  "properties": {
    "iso:country":"US",
    "sg:address":"4121 Barnsley Dr",
    "sg:city":"Plano",
    "sg:classifiers":[
        {
            "category":"Professional",
            "subcategory":"Management & Consulting",
            "type":"Services"
        }
    ],
    "sg:phone":"+1 972 612 7899",
    "sg:postcode":"75093",
    "sg:province":"TX",
    "sg:tags":[
        "consultant",
        "resource",
        "human"
    ],
    "wof:name":"M D Beck & Co Inc",
    "wof:placetype":"venue"
},
  "geometry": {"coordinates":[-96.77352999999999,33.039496],"type":"Point"}
}