{
  "type": "Feature",
  "properties": {
    "iso:country":"US",
    "sg:address":"4222 Harvest Hill Rd",
    "sg:city":"Dallas",
    "sg:classifiers":[
        {
            "category":"Professional",
            "type":"Services"
        }
    ],
    "sg:phone":"+1 972 960 2211",
    "sg:postcode":"75244",
    "sg:province":"TX",
    "wof:name":"Slade Sherrod",
    "wof:placetype":"venue"
},
  "geometry": {"coordinates":[-96.83459999999999,32.922279],"type":"Point"}
}