{
  "type": "Feature",
  "properties": {
    "iso:country":"US",
    "sg:address":"8332 Thornhaven Ct",
    "sg:city":"N Richland Hills",
    "sg:classifiers":[
        {
            "category":"Shopping",
            "subcategory":"Used Merchandise",
            "type":"Retail Goods"
        }
    ],
    "sg:phone":"+1 817 281 4028",
    "sg:postcode":"76180",
    "sg:province":"TX",
    "sg:tags":[
        "antique"
    ],
    "wof:name":"Yesteryears",
    "wof:placetype":"venue"
},
  "geometry": {"coordinates":[-97.192927,32.896482],"type":"Point"}
}