{
  "type": "Feature",
  "properties": {
    "iso:country":"US",
    "sg:address":"7500 Viscount Blvd",
    "sg:city":"El Paso",
    "sg:classifiers":[
        {
            "category":"Communications",
            "subcategory":"News Services",
            "type":"Services"
        }
    ],
    "sg:phone":"+1 915 778 5097",
    "sg:postcode":"79925",
    "sg:province":"TX",
    "sg:tags":[
        "syndicate"
    ],
    "wof:name":"F W Dodge",
    "wof:placetype":"venue"
},
  "geometry": {"coordinates":[-106.384727,31.780843],"type":"Point"}
}