{
  "type": "Feature",
  "properties": {
    "iso:country":"US",
    "sg:address":"9830 Harwin Dr",
    "sg:city":"Houston",
    "sg:classifiers":[
        {
            "category":"Shopping",
            "subcategory":"Clothing, Apparel, & Fashions",
            "type":"Retail Goods"
        }
    ],
    "sg:phone":"+1 713 532 3480",
    "sg:postcode":"77036",
    "sg:province":"TX",
    "wof:name":"Klass Fashions",
    "wof:placetype":"venue"
},
  "geometry": {"coordinates":[-95.535304,29.717845],"type":"Point"}
}