{
  "type": "Feature",
  "properties": {
    "iso:country":"US",
    "sg:address":"515 Congress Ave",
    "sg:city":"Austin",
    "sg:classifiers":[
        {
            "category":"Health Services",
            "subcategory":"Hospice",
            "type":"Services"
        }
    ],
    "sg:phone":"+1 512 236 0400",
    "sg:postcode":"78701",
    "sg:province":"TX",
    "wof:name":"Harbor Hospice",
    "wof:placetype":"venue"
},
  "geometry": {"coordinates":[-97.74309599999999,30.267287],"type":"Point"}
}