{
  "type": "Feature",
  "properties": {
    "iso:country":"US",
    "sg:address":"2815 Colquitt St",
    "sg:city":"Houston",
    "sg:classifiers":[
        {
            "category":"Arts & Performance",
            "subcategory":"Art Gallery",
            "type":"Entertainment"
        }
    ],
    "sg:phone":"+1 713 526 9911",
    "sg:postcode":"77098",
    "sg:province":"TX",
    "wof:name":"Moody Gallery Inc",
    "wof:placetype":"venue"
},
  "geometry": {"coordinates":[-95.420998,29.734699],"type":"Point"}
}