{
  "type": "Feature",
  "properties": {
    "iso:country":"US",
    "sg:address":"220 Santa Fe Dr",
    "sg:city":"Weatherford",
    "sg:classifiers":[
        {
            "category":"Shopping",
            "subcategory":"Tobacco",
            "type":"Retail Goods"
        }
    ],
    "sg:phone":"+1 817 599 6971",
    "sg:postcode":"76086",
    "sg:province":"TX",
    "sg:tags":[
        "cigarette",
        "cigar",
        "dealer"
    ],
    "wof:name":"Just Smokes 6",
    "wof:placetype":"venue"
},
  "geometry": {"coordinates":[-97.791954,32.757151],"type":"Point"}
}