{
  "type": "Feature",
  "properties": {
    "iso:country":"US",
    "sg:address":"240 Cargill St",
    "sg:city":"El Paso",
    "sg:classifiers":[
        {
            "category":"Retail",
            "subcategory":"Repair Shop",
            "type":"Services"
        }
    ],
    "sg:phone":"+1 915 778 0321",
    "sg:postcode":"79905",
    "sg:province":"TX",
    "wof:name":"C & F Services",
    "wof:placetype":"venue"
},
  "geometry": {"coordinates":[-106.411706,31.762976],"type":"Point"}
}