{
  "type": "Feature",
  "properties": {
    "iso:country":"US",
    "sg:address":"779 Normandy St Ste 112",
    "sg:city":"Houston",
    "sg:classifiers":[
        {
            "category":"Health Services",
            "subcategory":"Dentist",
            "type":"Services"
        }
    ],
    "sg:phone":"+1 713 453 3733",
    "sg:postcode":"77015",
    "sg:province":"TX",
    "wof:name":"Bravo Dental Clinic",
    "wof:placetype":"venue"
},
  "geometry": {"coordinates":[-95.20517599999999,29.781316],"type":"Point"}
}