{
  "type": "Feature",
  "properties": {
    "iso:country":"US",
    "sg:address":"225 6th St",
    "sg:city":"Cushing",
    "sg:classifiers":[
        {
            "category":"Shopping",
            "subcategory":"Jewelry",
            "type":"Retail Goods"
        }
    ],
    "sg:phone":"+1 936 326 4381",
    "sg:postcode":"75760",
    "sg:province":"TX",
    "sg:tags":[
        "jeweler"
    ],
    "wof:name":"Silver N Stuff",
    "wof:placetype":"venue"
},
  "geometry": {"coordinates":[-94.839257,31.805639],"type":"Point"}
}