{
  "type": "Feature",
  "properties": {
    "iso:country":"US",
    "sg:address":"8835 E Sam Houston Pkwy N",
    "sg:city":"Houston",
    "sg:classifiers":[
        {
            "category":"Restaurant",
            "type":"Food & Drink"
        }
    ],
    "sg:menulink":"http://www.allmenus.com/tx/houston/62846-subway/menu/",
    "sg:phone":"+1 281 436 0600",
    "sg:postcode":"77044",
    "sg:province":"TX",
    "sg:tags":[
        "american",
        "sandwich"
    ],
    "wof:name":"Subway",
    "wof:placetype":"venue"
},
  "geometry": {"coordinates":[-95.187521,29.855376],"type":"Point"}
}