{
  "type": "Feature",
  "properties": {
    "iso:country":"US",
    "sg:address":"113 W Lafayette St",
    "sg:city":"Jefferson",
    "sg:classifiers":[
        {
            "category":"Professional",
            "subcategory":"Accounting & Tax Preparation",
            "type":"Services"
        }
    ],
    "sg:phone":"+1 903 665 2591",
    "sg:postcode":"75657",
    "sg:province":"TX",
    "wof:name":"Parker & Parker C P A",
    "wof:placetype":"venue"
},
  "geometry": {"coordinates":[-94.345079,32.757411],"type":"Point"}
}