{
  "type": "Feature",
  "properties": {
    "iso:country":"US",
    "sg:address":"7703 N Lamar Blvd Ste 123",
    "sg:city":"Austin",
    "sg:classifiers":[
        {
            "category":"Transit Center",
            "subcategory":"Freight",
            "type":"Transportation"
        }
    ],
    "sg:phone":"+1 512 206 4235",
    "sg:postcode":"78752",
    "sg:province":"TX",
    "sg:tags":[
        "container",
        "broker"
    ],
    "wof:name":"Transport Solutions Usa",
    "wof:placetype":"venue"
},
  "geometry": {"coordinates":[-97.714483,30.344439],"type":"Point"}
}