{
  "type": "Feature",
  "properties": {
    "iso:country":"US",
    "sg:address":"8500 Kansas River Dr",
    "sg:city":"Austin",
    "sg:classifiers":[
        {
            "category":"Recreation",
            "type":"Entertainment"
        }
    ],
    "sg:phone":"+1 512 394 1275",
    "sg:postcode":"78745",
    "sg:province":"TX",
    "sg:tags":[
        "camps-recreational"
    ],
    "wof:name":"Gazelles, Gilbert's",
    "wof:placetype":"venue"
},
  "geometry": {"coordinates":[-97.813698,30.18718],"type":"Point"}
}