{
  "type": "Feature",
  "properties": {
    "iso:country":"US",
    "sg:address":"9109 Dyer St",
    "sg:city":"El Paso",
    "sg:classifiers":[
        {
            "category":"Banks & Credit Unions",
            "subcategory":"Bank",
            "type":"Services"
        }
    ],
    "sg:phone":"+1 915 751 6466",
    "sg:postcode":"79924",
    "sg:province":"TX",
    "sg:tags":[
        "loan",
        "real estate"
    ],
    "wof:name":"Wells Fargo Financial Accptnce",
    "wof:placetype":"venue"
},
  "geometry": {"coordinates":[-106.428042,31.870289],"type":"Point"}
}