{
  "type": "Feature",
  "properties": {
    "iso:country":"US",
    "sg:address":"1403 Marian St",
    "sg:city":"Tyler",
    "sg:classifiers":[
        {
            "category":"Shopping",
            "subcategory":"Computers & Home Electronics",
            "type":"Retail Goods"
        }
    ],
    "sg:phone":"+1 903 531 0212",
    "sg:postcode":"75701",
    "sg:province":"TX",
    "sg:tags":[
        "equipment",
        "dealer"
    ],
    "wof:name":"Hancock Computers & Consulting",
    "wof:placetype":"venue"
},
  "geometry": {"coordinates":[-95.286524,32.326948],"type":"Point"}
}