{
  "type": "Feature",
  "properties": {
    "iso:country":"US",
    "sg:address":"1300 S Frazier St",
    "sg:city":"Conroe",
    "sg:classifiers":[
        {
            "category":"Building & Trades",
            "subcategory":"Construction",
            "type":"Services"
        }
    ],
    "sg:phone":"+1 936 441 0800",
    "sg:postcode":"77301",
    "sg:province":"TX",
    "sg:tags":[
        "special",
        "contractor"
    ],
    "wof:name":"Vic Sullivan Enterprises",
    "wof:placetype":"venue"
},
  "geometry": {"coordinates":[-95.45626300000001,30.289717],"type":"Point"}
}