{
  "type": "Feature",
  "properties": {
    "iso:country":"US",
    "sg:address":"1345 Campbell Rd",
    "sg:city":"Houston",
    "sg:classifiers":[
        {
            "category":"Health Services",
            "subcategory":"Dentist",
            "type":"Services"
        }
    ],
    "sg:phone":"+1 713 468 7676",
    "sg:postcode":"77055",
    "sg:province":"TX",
    "wof:name":"Finstad Ricki L DDS Inc",
    "wof:placetype":"venue"
},
  "geometry": {"coordinates":[-95.51406799999999,29.79366],"type":"Point"}
}