{
  "type": "Feature",
  "properties": {
    "iso:country":"US",
    "sg:address":"4302 Ross Ave",
    "sg:city":"Dallas",
    "sg:classifiers":[
        {
            "category":"Utilities",
            "subcategory":"Telephone",
            "type":"Services"
        }
    ],
    "sg:phone":"+1 214 821 1257",
    "sg:postcode":"75204",
    "sg:province":"TX",
    "sg:tags":[
        "telecommunication"
    ],
    "sg:website":"www.877ringagain.com",
    "wof:name":"Ring Again 877",
    "wof:placetype":"venue"
},
  "geometry": {"coordinates":[-96.781198,32.801962],"type":"Point"}
}