{
  "type": "Feature",
  "properties": {
    "iso:country":"US",
    "sg:address":"4811 W Braker Lane",
    "sg:city":"Austin",
    "sg:classifiers":[
        {
            "category":"Restaurant",
            "type":"Food & Drink"
        }
    ],
    "sg:phone":"+1 512 338 6033",
    "sg:postcode":"78759",
    "sg:province":"TX",
    "wof:name":"Taco Bell",
    "wof:placetype":"venue"
},
  "geometry": {"coordinates":[-97.74665400000001,30.400583],"type":"Point"}
}