{
  "type": "Feature",
  "properties": {
    "iso:country":"US",
    "sg:address":"606 N Main St",
    "sg:city":"Highlands",
    "sg:classifiers":[
        {
            "category":"Organizations",
            "subcategory":"Religious Organization",
            "type":"Services"
        }
    ],
    "sg:phone":"+1 281 426 7050",
    "sg:postcode":"77562",
    "sg:province":"TX",
    "wof:name":"Living Word Church",
    "wof:placetype":"venue"
},
  "geometry": {"coordinates":[-95.05755499999999,29.826916],"type":"Point"}
}