{
  "type": "Feature",
  "properties": {
    "iso:country":"US",
    "sg:address":"1240 S Burleson Blvd",
    "sg:city":"Burleson",
    "sg:classifiers":[
        {
            "category":"Home & Garden",
            "subcategory":"Furniture",
            "type":"Retail Goods"
        }
    ],
    "sg:phone":"+1 817 447 6434",
    "sg:postcode":"76028",
    "sg:province":"TX",
    "sg:tags":[
        "store"
    ],
    "sg:website":"www.johntkaraoke.com",
    "wof:name":"John T's Karaoke One Stop",
    "wof:placetype":"venue"
},
  "geometry": {"coordinates":[-97.30678,32.5195],"type":"Point"}
}