{
  "type": "Feature",
  "properties": {
    "iso:country":"US",
    "sg:address":"12862 Northwest Fwy",
    "sg:city":"Houston",
    "sg:classifiers":[
        {
            "category":"Restaurant",
            "type":"Food & Drink"
        }
    ],
    "sg:menulink":"http://www.allmenus.com/tx/houston/50691-dennys/menu/",
    "sg:phone":"+1 713 934 9911",
    "sg:postcode":"77040",
    "sg:province":"TX",
    "sg:tags":[
        "american",
        "diner"
    ],
    "wof:name":"Denny's",
    "wof:placetype":"venue"
},
  "geometry": {"coordinates":[-95.49333799999999,29.84237],"type":"Point"}
}