{
  "type": "Feature",
  "properties": {
    "iso:country":"US",
    "sg:address":"1001 Misty Meadow Dr",
    "sg:city":"Grand Prairie",
    "sg:classifiers":[
        {
            "category":"Organizations",
            "subcategory":"Membership Organization",
            "type":"Services"
        }
    ],
    "sg:phone":"+1 972 564 2351",
    "sg:postcode":"75052",
    "sg:province":"TX",
    "wof:name":"City of Forney Animal Shelter",
    "wof:placetype":"venue"
},
  "geometry": {"coordinates":[-96.989739,32.698026],"type":"Point"}
}