{
  "type": "Feature",
  "properties": {
    "iso:country":"US",
    "sg:address":"303 S Jupiter Rd",
    "sg:city":"Allen",
    "sg:classifiers":[
        {
            "category":"Shopping",
            "subcategory":"Computers & Home Electronics",
            "type":"Retail Goods"
        }
    ],
    "sg:phone":"+1 972 396 2064",
    "sg:postcode":"75002",
    "sg:province":"TX",
    "sg:tags":[
        "software"
    ],
    "sg:website":"www.focus-technologies.com",
    "wof:name":"Focus Technologies",
    "wof:placetype":"venue"
},
  "geometry": {"coordinates":[-96.65971999999999,33.096915],"type":"Point"}
}