{
  "type": "Feature",
  "properties": {
    "iso:country":"US",
    "sg:address":"1500 Wilson Rd",
    "sg:city":"Conroe",
    "sg:classifiers":[
        {
            "category":"Recreation",
            "type":"Entertainment"
        }
    ],
    "sg:phone":"+1 936 539 3547",
    "sg:postcode":"77304",
    "sg:province":"TX",
    "sg:tags":[
        "instructor",
        "gymnastics"
    ],
    "wof:name":"Maximum Athletic Center",
    "wof:placetype":"venue"
},
  "geometry": {"coordinates":[-95.47562499999999,30.325146],"type":"Point"}
}