{
  "type": "Feature",
  "properties": {
    "iso:country":"US",
    "sg:address":"1608 N Glass St",
    "sg:city":"Victoria",
    "sg:classifiers":[
        {
            "category":"Professional",
            "subcategory":"Art Services",
            "type":"Services"
        }
    ],
    "sg:phone":"+1 361 573 4977",
    "sg:postcode":"77901",
    "sg:province":"TX",
    "sg:tags":[
        "commercial",
        "design"
    ],
    "wof:name":"B Creative Marketing Solutions",
    "wof:placetype":"venue"
},
  "geometry": {"coordinates":[-97.005887,28.809852],"type":"Point"}
}