{
  "type": "Feature",
  "properties": {
    "iso:country":"US",
    "sg:address":"2726 Pepper Wood Dr",
    "sg:city":"Sugar Land",
    "sg:classifiers":[
        {
            "category":"Real Estate",
            "subcategory":"Real Estate Agent",
            "type":"Services"
        }
    ],
    "sg:phone":"+1 281 980 9100",
    "sg:postcode":"77479",
    "sg:province":"TX",
    "sg:tags":[
        "personal"
    ],
    "wof:name":"Rozell Realty",
    "wof:placetype":"venue"
},
  "geometry": {"coordinates":[-95.608732,29.586098],"type":"Point"}
}