{
  "type": "Feature",
  "properties": {
    "iso:country":"US",
    "sg:address":"918 Torrance Dr",
    "sg:city":"Garland",
    "sg:classifiers":[
        {
            "category":"Organizations",
            "subcategory":"Community Association",
            "type":"Services"
        }
    ],
    "sg:phone":"+1 972 496 8952",
    "sg:postcode":"75040",
    "sg:province":"TX",
    "wof:name":"Pham Hung PHI",
    "wof:placetype":"venue"
},
  "geometry": {"coordinates":[-96.639785,32.947525],"type":"Point"}
}