{
  "type": "Feature",
  "properties": {
    "iso:country":"US",
    "sg:address":"5336 Alpha Rd",
    "sg:city":"Dallas",
    "sg:classifiers":[
        {
            "category":"Professional",
            "subcategory":"Engineering",
            "type":"Services"
        }
    ],
    "sg:phone":"+1 972 702 0771",
    "sg:postcode":"75240",
    "sg:province":"TX",
    "sg:tags":[
        "engineer"
    ],
    "wof:name":"Kadleck & Associates",
    "wof:placetype":"venue"
},
  "geometry": {"coordinates":[-96.817016,32.932842],"type":"Point"}
}