{
  "type": "Feature",
  "properties": {
    "iso:country":"US",
    "sg:address":"414 Main St",
    "sg:city":"Sugar Land",
    "sg:classifiers":[
        {
            "category":"Organizations",
            "subcategory":"Religious Organization",
            "type":"Services"
        },
        {
            "category":"Social Services",
            "type":"Services"
        }
    ],
    "sg:phone":"+1 281 242 3148",
    "sg:postcode":"77478",
    "sg:province":"TX",
    "sg:tags":[
        "mission"
    ],
    "wof:name":"Basilian Fathers Missions",
    "wof:placetype":"venue"
},
  "geometry": {"coordinates":[-95.633639,29.626022],"type":"Point"}
}