{
  "type": "Feature",
  "properties": {
    "iso:country":"US",
    "sg:address":"201 Ave B",
    "sg:city":"Dalhart",
    "sg:classifiers":[
        {
            "category":"Building & Trades",
            "subcategory":"Cleaning & Sanitation",
            "type":"Services"
        }
    ],
    "sg:phone":"+1 806 244 7668",
    "sg:postcode":"79022",
    "sg:province":"TX",
    "sg:tags":[
        "maintenance"
    ],
    "wof:name":"Cinderfella Chimney Sweep",
    "wof:placetype":"venue"
},
  "geometry": {"coordinates":[-102.49652500000001,36.050748],"type":"Point"}
}