{
  "type": "Feature",
  "properties": {
    "iso:country":"US",
    "sg:address":"11613 N Central Expy Ste 110",
    "sg:city":"Dallas",
    "sg:classifiers":[
        {
            "category":"Personal",
            "subcategory":"Hair Removal",
            "type":"Services"
        },
        {
            "category":"Personal",
            "subcategory":"Nail Salon",
            "type":"Services"
        }
    ],
    "sg:phone":"+1 214 363 8482",
    "sg:postcode":"75243",
    "sg:province":"TX",
    "wof:name":"Royal Nails Boutique",
    "wof:placetype":"venue"
},
  "geometry": {"coordinates":[-96.76936000000001,32.906796],"type":"Point"}
}