{
  "type": "Feature",
  "properties": {
    "iso:country":"US",
    "sg:address":"4516 Reese Creek Rd",
    "sg:city":"Killeen",
    "sg:classifiers":[
        {
            "category":"Manufacturing",
            "subcategory":"Jewelry",
            "type":"Manufacturing & Wholesale Goods"
        },
        {
            "category":"Shopping",
            "subcategory":"Jewelry",
            "type":"Retail Goods"
        },
        {
            "category":"Retail",
            "subcategory":"Repair Shop",
            "type":"Services"
        },
        {
            "category":"Manufacturing",
            "subcategory":"Soap",
            "type":"Manufacturing & Wholesale Goods"
        }
    ],
    "sg:phone":"+1 254 519 1010",
    "sg:postcode":"76549",
    "sg:province":"TX",
    "sg:tags":[
        "manufacturer",
        "watches-wholesale",
        "watch",
        "jewelers-wholesale",
        "clock"
    ],
    "wof:name":"Cove Jewerly",
    "wof:placetype":"venue"
},
  "geometry": {"coordinates":[-97.810913,31.059139],"type":"Point"}
}