{
  "type": "Feature",
  "properties": {
    "iso:country":"US",
    "sg:address":"1906 Elsworthy St",
    "sg:city":"San Antonio",
    "sg:classifiers":[
        {
            "category":"Building & Trades",
            "subcategory":"Landscaping Services",
            "type":"Services"
        }
    ],
    "sg:phone":"+1 210 492 5504",
    "sg:postcode":"78248",
    "sg:province":"TX",
    "wof:name":"Pallsade Lawn & Landscape",
    "wof:placetype":"venue"
},
  "geometry": {"coordinates":[-98.52497700000001,29.56598],"type":"Point"}
}