{
  "type": "Feature",
  "properties": {
    "iso:country":"US",
    "sg:address":"9910 Lazy J Trl",
    "sg:city":"Helotes",
    "sg:classifiers":[
        {
            "category":"Building & Trades",
            "subcategory":"Construction",
            "type":"Services"
        }
    ],
    "sg:phone":"+1 210 695 9018",
    "sg:postcode":"78023",
    "sg:province":"TX",
    "sg:tags":[
        "industrial"
    ],
    "wof:name":"Sescila Construction Co",
    "wof:placetype":"venue"
},
  "geometry": {"coordinates":[-98.676883,29.582927],"type":"Point"}
}