{
  "type": "Feature",
  "properties": {
    "iso:country":"US",
    "sg:address":"4401 Lilac Ln",
    "sg:city":"Victoria",
    "sg:classifiers":[
        {
            "category":"Health Services",
            "subcategory":"Hospital",
            "type":"Services"
        }
    ],
    "sg:phone":"+1 361 578 2849",
    "sg:postcode":"77901",
    "sg:province":"TX",
    "sg:tags":[
        "specialty"
    ],
    "wof:name":"Americn Cncr Scty Texas Dis 20",
    "wof:placetype":"venue"
},
  "geometry": {"coordinates":[-96.99876399999999,28.835492],"type":"Point"}
}