{
  "type": "Feature",
  "properties": {
    "iso:country":"US",
    "sg:address":"11149 Research Blvd",
    "sg:city":"Austin",
    "sg:classifiers":[
        {
            "category":"Wholesale",
            "subcategory":"Computers",
            "type":"Manufacturing & Wholesale Goods"
        },
        {
            "category":"Professional",
            "subcategory":"Computer Services",
            "type":"Services"
        }
    ],
    "sg:phone":"+1 512 306 8225",
    "sg:postcode":"78759",
    "sg:province":"TX",
    "sg:tags":[
        "publisher",
        "designer",
        "consultant",
        "cd-rom",
        "system",
        "equipment",
        "software",
        "developer"
    ],
    "sg:website":"http://www.inferdata.com",
    "wof:name":"Inferdata Corp",
    "wof:placetype":"venue"
},
  "geometry": {"coordinates":[-97.744871,30.406293],"type":"Point"}
}