{
  "type": "Feature",
  "properties": {
    "iso:country":"US",
    "sg:address":"1909 Sabal Palm Dr",
    "sg:city":"Mercedes",
    "sg:classifiers":[
        {
            "category":"Professional",
            "subcategory":"Business Services",
            "type":"Services"
        }
    ],
    "sg:phone":"+1 956 565 5881",
    "sg:postcode":"78570",
    "sg:province":"TX",
    "wof:name":"Ybarras Business Services",
    "wof:placetype":"venue"
},
  "geometry": {"coordinates":[-97.893548,26.161042],"type":"Point"}
}