{
  "type": "Feature",
  "properties": {
    "iso:country":"US",
    "sg:address":"401 S Grant Ave",
    "sg:city":"Odessa",
    "sg:classifiers":[
        {
            "category":"Food & Beverages",
            "subcategory":"Liquor & Beverages",
            "type":"Retail Goods"
        }
    ],
    "sg:phone":"+1 432 332 9376",
    "sg:postcode":"79761",
    "sg:province":"TX",
    "wof:name":"Wyatt's Liquor",
    "wof:placetype":"venue"
},
  "geometry": {"coordinates":[-102.365171,31.842188],"type":"Point"}
}