{
  "type": "Feature",
  "properties": {
    "iso:country":"US",
    "sg:address":"1121 W Mayfield Rd",
    "sg:city":"Arlington",
    "sg:classifiers":[
        {
            "category":"Real Estate",
            "subcategory":"Real Estate Agent",
            "type":"Services"
        }
    ],
    "sg:phone":"+1 817 465 0145",
    "sg:postcode":"76015",
    "sg:province":"TX",
    "wof:name":"Robert's Property Management",
    "wof:placetype":"venue"
},
  "geometry": {"coordinates":[-97.12608899999999,32.691255],"type":"Point"}
}