{
  "type": "Feature",
  "properties": {
    "iso:country":"US",
    "sg:address":"6515 Storage Dr",
    "sg:city":"Amarillo",
    "sg:classifiers":[
        {
            "category":"Wholesale",
            "subcategory":"Hardware",
            "type":"Manufacturing & Wholesale Goods"
        }
    ],
    "sg:phone":"+1 806 467 8499",
    "sg:postcode":"79110",
    "sg:province":"TX",
    "sg:tags":[
        "cutlery"
    ],
    "sg:website":"www.bladez.com",
    "wof:name":"Knife Store",
    "wof:placetype":"venue"
},
  "geometry": {"coordinates":[-101.882001,35.143835],"type":"Point"}
}