{
  "type": "Feature",
  "properties": {
    "iso:country":"US",
    "sg:address":"5011 Slide Rd",
    "sg:city":"Lubbock",
    "sg:classifiers":[
        {
            "category":"Shopping",
            "subcategory":"Clothing, Apparel, & Fashions",
            "type":"Retail Goods"
        }
    ],
    "sg:phone":"+1 806 793 2818",
    "sg:postcode":"79414",
    "sg:province":"TX",
    "sg:tags":[
        "western"
    ],
    "wof:name":"Dollar Western Wear",
    "wof:placetype":"venue"
},
  "geometry": {"coordinates":[-101.922329,33.547932],"type":"Point"}
}