{
  "type": "Feature",
  "properties": {
    "iso:country":"US",
    "sg:address":"415 W Wall St",
    "sg:city":"Midland",
    "sg:classifiers":[
        {
            "category":"Mining & Drilling",
            "type":"Manufacturing & Wholesale Goods"
        }
    ],
    "sg:phone":"+1 432 570 8840",
    "sg:postcode":"79701",
    "sg:province":"TX",
    "sg:tags":[
        "field",
        "oil"
    ],
    "wof:name":"Adobe Oil Field Svc Inc",
    "wof:placetype":"venue"
},
  "geometry": {"coordinates":[-102.079133,31.997333],"type":"Point"}
}