{
  "type": "Feature",
  "properties": {
    "iso:country":"US",
    "sg:address":"1717 Colborne Dr",
    "sg:city":"Mesquite",
    "sg:classifiers":[
        {
            "category":"Shopping",
            "type":"Retail Goods"
        }
    ],
    "sg:phone":"+1 972 288 6594",
    "sg:postcode":"75149",
    "sg:province":"TX",
    "sg:tags":[
        "merchandise"
    ],
    "wof:name":"Harris Jeff Gift Shoppe",
    "wof:placetype":"venue"
},
  "geometry": {"coordinates":[-96.591283,32.745392],"type":"Point"}
}