{
  "type": "Feature",
  "properties": {
    "iso:country":"US",
    "sg:address":"14708 FM 529",
    "sg:city":"Houston",
    "sg:classifiers":[
        {
            "category":"Retail",
            "subcategory":"Laundry & Dry Cleaning",
            "type":"Services"
        }
    ],
    "sg:phone":"+1 281 856 6116",
    "sg:postcode":"77095",
    "sg:province":"TX",
    "sg:tags":[
        "cleaners"
    ],
    "wof:name":"Maha Cleaners",
    "wof:placetype":"venue"
},
  "geometry": {"coordinates":[-95.63457099999999,29.879302],"type":"Point"}
}