{
  "type": "Feature",
  "properties": {
    "iso:country":"US",
    "sg:address":"1241 Moody Ln",
    "sg:city":"Glen Rose",
    "sg:classifiers":[
        {
            "category":"Professional",
            "subcategory":"Management & Consulting",
            "type":"Services"
        }
    ],
    "sg:phone":"+1 254 897 3754",
    "sg:postcode":"76043",
    "sg:province":"TX",
    "wof:name":"RDP Marketing Group",
    "wof:placetype":"venue"
},
  "geometry": {"coordinates":[-97.778628,32.224203],"type":"Point"}
}