{
  "type": "Feature",
  "properties": {
    "iso:country":"US",
    "sg:address":"931 Litsey Rd",
    "sg:city":"Roanoke",
    "sg:classifiers":[
        {
            "category":"Professional",
            "subcategory":"Lawyer & Legal Services",
            "type":"Services"
        }
    ],
    "sg:phone":"+1 817 837 7823",
    "sg:postcode":"76262",
    "sg:province":"TX",
    "sg:tags":[
        "trust",
        "living",
        "planning",
        "probate",
        "estate"
    ],
    "wof:name":"Charity Swdc Classic",
    "wof:placetype":"venue"
},
  "geometry": {"coordinates":[-97.242504,33.008015],"type":"Point"}
}