{
  "type": "Feature",
  "properties": {
    "iso:country":"US",
    "sg:address":"8939 Westheimer Rd",
    "sg:city":"Houston",
    "sg:classifiers":[
        {
            "category":"Shopping",
            "type":"Retail Goods"
        }
    ],
    "sg:phone":"+1 713 334 3535",
    "sg:postcode":"77063",
    "sg:province":"TX",
    "sg:tags":[
        "merchandise"
    ],
    "wof:name":"Voice N View",
    "wof:placetype":"venue"
},
  "geometry": {"coordinates":[-95.52148800000001,29.737253],"type":"Point"}
}