{
  "type": "Feature",
  "properties": {
    "iso:country":"US",
    "sg:address":"4340 N Central Expy",
    "sg:city":"Dallas",
    "sg:classifiers":[
        {
            "category":"Shopping",
            "subcategory":"Music",
            "type":"Retail Goods"
        }
    ],
    "sg:phone":"+1 214 826 3020",
    "sg:postcode":"75206",
    "sg:province":"TX",
    "sg:tags":[
        "video",
        "disc",
        "tape",
        "cassette"
    ],
    "wof:name":"Video Concepts 2000",
    "wof:placetype":"venue"
},
  "geometry": {"coordinates":[-96.788049,32.81717],"type":"Point"}
}