{
  "type": "Feature",
  "properties": {
    "iso:country":"US",
    "sg:address":"330 Sheldon Rd",
    "sg:city":"Channelview",
    "sg:classifiers":[
        {
            "category":"Organizations",
            "subcategory":"Religious Organization",
            "type":"Services"
        }
    ],
    "sg:phone":"+1 281 452 2952",
    "sg:postcode":"77530",
    "sg:province":"TX",
    "sg:tags":[
        "church"
    ],
    "wof:name":"First Assembly Of God",
    "wof:placetype":"venue"
},
  "geometry": {"coordinates":[-95.12445700000001,29.776971],"type":"Point"}
}