{
  "type": "Feature",
  "properties": {
    "iso:country":"US",
    "sg:address":"3801 Toler Rd",
    "sg:city":"Rowlett",
    "sg:classifiers":[
        {
            "category":"Building & Trades",
            "subcategory":"Landscaping Services",
            "type":"Services"
        }
    ],
    "sg:phone":"+1 972 475 0859",
    "sg:postcode":"75089",
    "sg:province":"TX",
    "sg:tags":[
        "landscape",
        "contractor"
    ],
    "wof:name":"Grounds Maintenance Systems",
    "wof:placetype":"venue"
},
  "geometry": {"coordinates":[-96.565219,32.921696],"type":"Point"}
}