{
  "type": "Feature",
  "properties": {
    "iso:country":"US",
    "sg:address":"114 E New York Ave",
    "sg:city":"Hereford",
    "sg:classifiers":[
        {
            "category":"Farming",
            "subcategory":"Farm & Veterinary Services",
            "type":"Manufacturing & Wholesale Goods"
        }
    ],
    "sg:phone":"+1 806 364 3484",
    "sg:postcode":"79045",
    "sg:province":"TX",
    "sg:tags":[
        "seed",
        "grain",
        "cleaning"
    ],
    "wof:name":"Scott Seed Co",
    "wof:placetype":"venue"
},
  "geometry": {"coordinates":[-102.39610399999999,34.813782],"type":"Point"}
}