{
  "type": "Feature",
  "properties": {
    "iso:country":"US",
    "sg:address":"211 S David St",
    "sg:city":"San Angelo",
    "sg:classifiers":[
        {
            "category":"Manufacturing",
            "subcategory":"Tools & Machinery",
            "type":"Manufacturing & Wholesale Goods"
        }
    ],
    "sg:phone":"+1 325 482 8321",
    "sg:postcode":"76903",
    "sg:province":"TX",
    "sg:tags":[
        "computer",
        "electronic",
        "mfg"
    ],
    "wof:name":"Texas Laser",
    "wof:placetype":"venue"
},
  "geometry": {"coordinates":[-100.445108,31.457787],"type":"Point"}
}