{
  "type": "Feature",
  "properties": {
    "iso:country":"US",
    "sg:address":"940 Kirtomy Loop",
    "sg:city":"Pflugerville",
    "sg:classifiers":[
        {
            "category":"Building & Trades",
            "subcategory":"Plumbing",
            "type":"Services"
        }
    ],
    "sg:phone":"+1 512 252 8540",
    "sg:postcode":"78660",
    "sg:province":"TX",
    "sg:tags":[
        "contractor"
    ],
    "wof:name":"Remnant Mechanical Inc",
    "wof:placetype":"venue"
},
  "geometry": {"coordinates":[-97.637382,30.466588],"type":"Point"}
}