{
  "type": "Feature",
  "properties": {
    "iso:country":"US",
    "sg:address":"15928 Midway Rd",
    "sg:city":"Addison",
    "sg:classifiers":[
        {
            "category":"Professional",
            "subcategory":"Employment Agencies",
            "type":"Services"
        }
    ],
    "sg:phone":"+1 972 432 8310",
    "sg:postcode":"75001",
    "sg:province":"TX",
    "sg:website":"www.certified.com",
    "wof:name":"Certified Communications Inc",
    "wof:placetype":"venue"
},
  "geometry": {"coordinates":[-96.84043,32.967225],"type":"Point"}
}