{
  "type": "Feature",
  "properties": {
    "iso:country":"US",
    "sg:address":"9431 Callaghan Rd",
    "sg:city":"San Antonio",
    "sg:classifiers":[
        {
            "category":"Organizations",
            "subcategory":"Community Association",
            "type":"Services"
        }
    ],
    "sg:phone":"+1 210 344 5282",
    "sg:postcode":"78230",
    "sg:province":"TX",
    "wof:name":"Oak Valley Homeowners Asso",
    "wof:placetype":"venue"
},
  "geometry": {"coordinates":[-98.536586,29.527161],"type":"Point"}
}