{
  "type": "Feature",
  "properties": {
    "iso:country":"US",
    "sg:address":"11011 Albury Park Ln",
    "sg:city":"Tomball",
    "sg:classifiers":[
        {
            "category":"Shopping",
            "subcategory":"Bicycles & Sporting Goods",
            "type":"Retail Goods"
        }
    ],
    "sg:phone":"+1 281 351 0554",
    "sg:postcode":"77375",
    "sg:province":"TX",
    "wof:name":"Dixie Arms & Ammo",
    "wof:placetype":"venue"
},
  "geometry": {"coordinates":[-95.58582699999999,30.068714],"type":"Point"}
}