{
  "type": "Feature",
  "properties": {
    "iso:country":"US",
    "sg:address":"12222 Merit Dr",
    "sg:city":"Dallas",
    "sg:classifiers":[
        {
            "category":"Insurance",
            "subcategory":"Life Insurance",
            "type":"Services"
        }
    ],
    "sg:phone":"+1 972 716 8000",
    "sg:postcode":"75251",
    "sg:province":"TX",
    "sg:tags":[
        "carrier"
    ],
    "wof:name":"General American Life Insur Co",
    "wof:placetype":"venue"
},
  "geometry": {"coordinates":[-96.772868,32.918215],"type":"Point"}
}