{
  "type": "Feature",
  "properties": {
    "iso:country":"US",
    "sg:address":"6601 Southwest Fwy",
    "sg:city":"Houston",
    "sg:classifiers":[
        {
            "category":"Autos & Motor Vehicles",
            "subcategory":"Fuel & Gas Station",
            "type":"Retail Goods"
        }
    ],
    "sg:phone":"+1 713 541 6286",
    "sg:postcode":"77074",
    "sg:province":"TX",
    "sg:tags":[
        "grocery",
        "oil"
    ],
    "wof:name":"Hillcroft Shell",
    "wof:placetype":"venue"
},
  "geometry": {"coordinates":[-95.49894399999999,29.715906],"type":"Point"}
}