{
  "type": "Feature",
  "properties": {
    "iso:country":"US",
    "sg:address":"432 Mc Carthy Ave",
    "sg:city":"El Paso",
    "sg:classifiers":[
        {
            "category":"Retail",
            "subcategory":"Portrait Studio",
            "type":"Services"
        }
    ],
    "sg:phone":"+1 915 779 1174",
    "sg:postcode":"79915",
    "sg:province":"TX",
    "sg:tags":[
        "photo"
    ],
    "wof:name":"Lomeli Photos",
    "wof:placetype":"venue"
},
  "geometry": {"coordinates":[-106.37642,31.730888],"type":"Point"}
}