{
  "type": "Feature",
  "properties": {
    "iso:country":"US",
    "sg:address":"3410 Mallard Park",
    "sg:city":"Rowlett",
    "sg:classifiers":[
        {
            "category":"Building & Trades",
            "subcategory":"Construction",
            "type":"Services"
        }
    ],
    "sg:phone":"+1 972 412 2252",
    "sg:postcode":"75088",
    "sg:province":"TX",
    "sg:tags":[
        "floor",
        "laying",
        "contractor"
    ],
    "wof:name":"Park Citys Wood Flooring",
    "wof:placetype":"venue"
},
  "geometry": {"coordinates":[-96.57020799999999,32.876993],"type":"Point"}
}