{
  "type": "Feature",
  "properties": {
    "iso:country":"US",
    "sg:address":"202 Canyon Valley Dr",
    "sg:city":"Richardson",
    "sg:classifiers":[
        {
            "category":"Professional",
            "subcategory":"Computer Services",
            "type":"Services"
        }
    ],
    "sg:phone":"+1 972 705 9403",
    "sg:postcode":"75080",
    "sg:province":"TX",
    "sg:tags":[
        "custom",
        "design",
        "software"
    ],
    "wof:name":"CUC",
    "wof:placetype":"venue"
},
  "geometry": {"coordinates":[-96.714416,32.994168],"type":"Point"}
}