{
  "type": "Feature",
  "properties": {
    "iso:country":"US",
    "sg:address":"1132 Geronimo Dr",
    "sg:city":"El Paso",
    "sg:classifiers":[
        {
            "category":"Shopping",
            "type":"Retail Goods"
        }
    ],
    "sg:phone":"+1 325 872 1962",
    "sg:postcode":"79925",
    "sg:province":"TX",
    "sg:tags":[
        "merchandise"
    ],
    "wof:name":"T & S Corp",
    "wof:placetype":"venue"
},
  "geometry": {"coordinates":[-106.41136400000001,31.785188],"type":"Point"}
}