{
  "type": "Feature",
  "properties": {
    "iso:country":"US",
    "sg:address":"1524 E 10th St",
    "sg:city":"Lubbock",
    "sg:classifiers":[
        {
            "category":"Building & Trades",
            "subcategory":"Cleaning & Sanitation",
            "type":"Services"
        }
    ],
    "sg:phone":"+1 806 778 9357",
    "sg:postcode":"79403",
    "sg:province":"TX",
    "sg:tags":[
        "maintenance"
    ],
    "wof:name":"Johns Cleaning Service",
    "wof:placetype":"venue"
},
  "geometry": {"coordinates":[-101.818648,33.586922],"type":"Point"}
}