{
  "type": "Feature",
  "properties": {
    "iso:country":"US",
    "sg:address":"13881 Southwest Fwy",
    "sg:city":"Sugar Land",
    "sg:classifiers":[
        {
            "category":"Food & Beverages",
            "subcategory":"Specialty",
            "type":"Retail Goods"
        },
        {
            "category":"Food & Beverages",
            "subcategory":"Bakery",
            "type":"Retail Goods"
        }
    ],
    "sg:phone":"+1 281 242 7655",
    "sg:postcode":"77478",
    "sg:province":"TX",
    "sg:tags":[
        "tea",
        "coffee"
    ],
    "wof:name":"T J Cinnamons",
    "wof:placetype":"venue"
},
  "geometry": {"coordinates":[-95.601113,29.621584],"type":"Point"}
}