{
  "type": "Feature",
  "properties": {
    "iso:country":"US",
    "sg:address":"8911 FM 1488",
    "sg:city":"Magnolia",
    "sg:classifiers":[
        {
            "category":"Building & Trades",
            "subcategory":"Construction",
            "type":"Services"
        }
    ],
    "sg:phone":"+1 281 356 8018",
    "sg:postcode":"77354",
    "sg:province":"TX",
    "sg:tags":[
        "residential"
    ],
    "wof:name":"Fretz Construction",
    "wof:placetype":"venue"
},
  "geometry": {"coordinates":[-95.604888,30.221563],"type":"Point"}
}