{
  "type": "Feature",
  "properties": {
    "iso:country":"US",
    "sg:address":"11933 Knickerbocker Rd",
    "sg:city":"San Angelo",
    "sg:classifiers":[
        {
            "category":"Shopping",
            "subcategory":"Gifts & Souvenirs",
            "type":"Retail Goods"
        }
    ],
    "sg:phone":"+1 325 944 1119",
    "sg:postcode":"76904",
    "sg:province":"TX",
    "wof:name":"Specially For You",
    "wof:placetype":"venue"
},
  "geometry": {"coordinates":[-100.584807,31.307322],"type":"Point"}
}