{
  "type": "Feature",
  "properties": {
    "iso:country":"US",
    "sg:address":"11 Center St",
    "sg:city":"Deer Park",
    "sg:classifiers":[
        {
            "category":"Professional",
            "subcategory":"Lawyer & Legal Services",
            "type":"Services"
        }
    ],
    "sg:phone":"+1 281 476 5008",
    "sg:postcode":"77536",
    "sg:province":"TX",
    "wof:name":"Contreras Mitchell Atty",
    "wof:placetype":"venue"
},
  "geometry": {"coordinates":[-95.123802,29.7111],"type":"Point"}
}