{
  "type": "Feature",
  "properties": {
    "iso:country":"US",
    "sg:address":"3017 Commerce St",
    "sg:city":"Dallas",
    "sg:classifiers":[
        {
            "category":"Organizations",
            "subcategory":"Non-profit Organization",
            "type":"Services"
        }
    ],
    "sg:phone":"+1 214 655 6396",
    "sg:postcode":"75226",
    "sg:province":"TX",
    "sg:tags":[
        "service/non-profit",
        "community"
    ],
    "sg:website":"www.soupmobile.com",
    "wof:name":"Soupmobile",
    "wof:placetype":"venue"
},
  "geometry": {"coordinates":[-96.780118,32.783917],"type":"Point"}
}