{
  "type": "Feature",
  "properties": {
    "iso:country":"US",
    "sg:address":"2709 FM 2280",
    "sg:city":"Cleburne",
    "sg:classifiers":[
        {
            "category":"Autos & Motor Vehicles",
            "subcategory":"Automobile Sales",
            "type":"Retail Goods"
        }
    ],
    "sg:phone":"+1 817 558 3878",
    "sg:postcode":"76031",
    "sg:province":"TX",
    "sg:tags":[
        "used"
    ],
    "wof:name":"Jims Autos",
    "wof:placetype":"venue"
},
  "geometry": {"coordinates":[-97.32033800000001,32.417631],"type":"Point"}
}