{
  "type": "Feature",
  "properties": {
    "iso:country":"US",
    "sg:address":"5011 Texoma Pkwy",
    "sg:city":"Sherman",
    "sg:classifiers":[
        {
            "category":"Travel",
            "subcategory":"Travel Agent",
            "type":"Entertainment"
        }
    ],
    "sg:phone":"+1 903 893 6888",
    "sg:postcode":"75090",
    "sg:province":"TX",
    "sg:tags":[
        "agency",
        "bureau"
    ],
    "wof:name":"About Travel",
    "wof:placetype":"venue"
},
  "geometry": {"coordinates":[-96.579229,33.690446],"type":"Point"}
}