{
  "type": "Feature",
  "properties": {
    "iso:country":"US",
    "sg:address":"16535 Southwest Fwy",
    "sg:city":"Sugar Land",
    "sg:classifiers":[
        {
            "category":"Shopping",
            "subcategory":"Clothing, Apparel, & Fashions",
            "type":"Retail Goods"
        }
    ],
    "sg:phone":"+1 281 277 5700",
    "sg:postcode":"77479",
    "sg:province":"TX",
    "wof:name":"Petite Sophisticate",
    "wof:placetype":"venue"
},
  "geometry": {"coordinates":[-95.631574,29.591516],"type":"Point"}
}