{
  "type": "Feature",
  "properties": {
    "iso:country":"US",
    "sg:address":"711 N 8th St",
    "sg:city":"Killeen",
    "sg:classifiers":[
        {
            "category":"Social Services",
            "subcategory":"Child Care",
            "type":"Services"
        }
    ],
    "sg:phone":"+1 254 628 0183",
    "sg:postcode":"76541",
    "sg:province":"TX",
    "wof:name":"Kinderland Learning Ctr",
    "wof:placetype":"venue"
},
  "geometry": {"coordinates":[-97.72537800000001,31.124152],"type":"Point"}
}