{
  "type": "Feature",
  "properties": {
    "iso:country":"US",
    "sg:address":"1313 W Pearl St",
    "sg:city":"Granbury",
    "sg:classifiers":[
        {
            "category":"Professional",
            "subcategory":"Accounting & Tax Preparation",
            "type":"Services"
        }
    ],
    "sg:phone":"+1 817 279 1551",
    "sg:postcode":"76048",
    "sg:province":"TX",
    "wof:name":"Charbonnet and Associates",
    "wof:placetype":"venue"
},
  "geometry": {"coordinates":[-97.802262,32.441421],"type":"Point"}
}