{
  "type": "Feature",
  "properties": {
    "iso:country":"US",
    "sg:address":"2409 E End Blvd S",
    "sg:city":"Marshall",
    "sg:classifiers":[
        {
            "category":"Restaurant",
            "type":"Food & Drink"
        }
    ],
    "sg:phone":"+1 903 935 6421",
    "sg:postcode":"75672",
    "sg:province":"TX",
    "sg:tags":[
        "seafood"
    ],
    "wof:name":"Long John Silver's",
    "wof:placetype":"venue"
},
  "geometry": {"coordinates":[-94.352316,32.524669],"type":"Point"}
}