{
  "type": "Feature",
  "properties": {
    "iso:country":"US",
    "sg:address":"1868 W Kilpatrick St",
    "sg:city":"Cleburne",
    "sg:classifiers":[
        {
            "category":"Building & Trades",
            "subcategory":"Construction",
            "type":"Services"
        }
    ],
    "sg:phone":"+1 817 558 1446",
    "sg:postcode":"76033",
    "sg:province":"TX",
    "sg:tags":[
        "house"
    ],
    "wof:name":"Jkc Construction Inc",
    "wof:placetype":"venue"
},
  "geometry": {"coordinates":[-97.41431300000001,32.360891],"type":"Point"}
}