{
  "type": "Feature",
  "properties": {
    "iso:country":"US",
    "sg:address":"3102 Grape St",
    "sg:city":"Abilene",
    "sg:classifiers":[
        {
            "category":"Food & Beverages",
            "subcategory":"Groceries & Convenience Stores",
            "type":"Retail Goods"
        }
    ],
    "sg:phone":"+1 325 677 4581",
    "sg:postcode":"79601",
    "sg:province":"TX",
    "wof:name":"Skinny's Convenience Stores",
    "wof:placetype":"venue"
},
  "geometry": {"coordinates":[-99.73948,32.488311],"type":"Point"}
}