{
  "type": "Feature",
  "properties": {
    "iso:country":"US",
    "sg:address":"5707 Dolores St",
    "sg:city":"Houston",
    "sg:classifiers":[
        {
            "category":"Manufacturing",
            "subcategory":"Retail Goods",
            "type":"Manufacturing & Wholesale Goods"
        }
    ],
    "sg:phone":"+1 713 782 1038",
    "sg:postcode":"77057",
    "sg:province":"TX",
    "sg:tags":[
        "product",
        "mfg"
    ],
    "wof:name":"J&B CD Rom Distributions",
    "wof:placetype":"venue"
},
  "geometry": {"coordinates":[-95.479697,29.734213],"type":"Point"}
}