{
  "type": "Feature",
  "properties": {
    "iso:country":"US",
    "sg:address":"901 Yellow Jacket Ln",
    "sg:city":"Rockwall",
    "sg:classifiers":[
        {
            "category":"Organizations",
            "subcategory":"Community Association",
            "type":"Services"
        }
    ],
    "sg:phone":"+1 972 772 2004",
    "sg:postcode":"75087",
    "sg:province":"TX",
    "wof:name":"Jacketbackers",
    "wof:placetype":"venue"
},
  "geometry": {"coordinates":[-96.451947,32.912881],"type":"Point"}
}