{
  "type": "Feature",
  "properties": {
    "iso:country":"US",
    "sg:address":"2117 Dunlavy St",
    "sg:city":"Houston",
    "sg:classifiers":[
        {
            "category":"Professional",
            "type":"Services"
        }
    ],
    "sg:phone":"+1 713 522 0477",
    "sg:postcode":"77006",
    "sg:province":"TX",
    "sg:tags":[
        "establishment"
    ],
    "wof:name":"Excel Contactors",
    "wof:placetype":"venue"
},
  "geometry": {"coordinates":[-95.402034,29.746374],"type":"Point"}
}