{
  "type": "Feature",
  "properties": {
    "iso:country":"US",
    "sg:address":"611 Burlington Ave",
    "sg:city":"Spur",
    "sg:classifiers":[
        {
            "category":"Food & Beverages",
            "subcategory":"Groceries & Convenience Stores",
            "type":"Retail Goods"
        }
    ],
    "sg:phone":"+1 806 271 4372",
    "sg:postcode":"79370",
    "sg:province":"TX",
    "wof:name":"Lawrence Brothers Supermarket",
    "wof:placetype":"venue"
},
  "geometry": {"coordinates":[-100.853739,33.479942],"type":"Point"}
}