{
  "type": "Feature",
  "properties": {
    "iso:country":"US",
    "sg:address":"4219 32nd St",
    "sg:city":"Port Arthur",
    "sg:classifiers":[
        {
            "category":"Professional",
            "subcategory":"Accounting & Tax Preparation",
            "type":"Services"
        }
    ],
    "sg:phone":"+1 409 962 1005",
    "sg:postcode":"77642",
    "sg:province":"TX",
    "sg:tags":[
        "return"
    ],
    "wof:name":"Penas Tax Service",
    "wof:placetype":"venue"
},
  "geometry": {"coordinates":[-93.929621,29.923536],"type":"Point"}
}