{
  "type": "Feature",
  "properties": {
    "iso:country":"US",
    "sg:address":"111 Congress Ave",
    "sg:city":"Austin",
    "sg:classifiers":[
        {
            "category":"Professional",
            "subcategory":"Lawyer & Legal Services",
            "type":"Services"
        }
    ],
    "sg:phone":"+1 512 479 9778",
    "sg:postcode":"78701",
    "sg:province":"TX",
    "wof:name":"Elizabeth A Zeck",
    "wof:placetype":"venue"
},
  "geometry": {"coordinates":[-97.744159,30.264199],"type":"Point"}
}