{
  "type": "Feature",
  "properties": {
    "iso:country":"US",
    "sg:address":"9301 Southwest Fwy",
    "sg:city":"Houston",
    "sg:classifiers":[
        {
            "category":"Professional",
            "subcategory":"Lawyer & Legal Services",
            "type":"Services"
        }
    ],
    "sg:phone":"+1 713 270 8500",
    "sg:postcode":"77074",
    "sg:province":"TX",
    "wof:name":"Gardner John L & Associates",
    "wof:placetype":"venue"
},
  "geometry": {"coordinates":[-95.53620100000001,29.6807],"type":"Point"}
}