{
  "type": "Feature",
  "properties": {
    "iso:country":"US",
    "sg:address":"6378 FM 105",
    "sg:city":"Orange",
    "sg:classifiers":[
        {
            "category":"Manufacturing",
            "subcategory":"Chemicals & Compounds",
            "type":"Manufacturing & Wholesale Goods"
        }
    ],
    "sg:phone":"+1 409 670 1717",
    "sg:postcode":"77630",
    "sg:province":"TX",
    "sg:tags":[
        "inorganic",
        "industrial",
        "mfg"
    ],
    "wof:name":"Cat Tech Inc",
    "wof:placetype":"venue"
},
  "geometry": {"coordinates":[-93.781874,30.083197],"type":"Point"}
}