{
  "type": "Feature",
  "properties": {
    "iso:country":"US",
    "sg:address":"751 Bastrop Hwy",
    "sg:city":"Austin",
    "sg:classifiers":[
        {
            "category":"Utilities",
            "subcategory":"Refuse",
            "type":"Services"
        }
    ],
    "sg:phone":"+1 512 258 6670",
    "sg:postcode":"78741",
    "sg:province":"TX",
    "sg:tags":[
        "system"
    ],
    "wof:name":"Austin Liquid Disposal Inc",
    "wof:placetype":"venue"
},
  "geometry": {"coordinates":[-97.683797,30.232741],"type":"Point"}
}