{
  "type": "Feature",
  "properties": {
    "iso:country":"US",
    "sg:address":"26222 Maplewood Dr",
    "sg:city":"Spring",
    "sg:classifiers":[
        {
            "category":"Wholesale",
            "subcategory":"Machinery & Supplies",
            "type":"Manufacturing & Wholesale Goods"
        },
        {
            "category":"Manufacturing",
            "subcategory":"Glass & Minerals",
            "type":"Manufacturing & Wholesale Goods"
        }
    ],
    "sg:phone":"+1 281 359 9318",
    "sg:postcode":"77386",
    "sg:province":"TX",
    "sg:tags":[
        "product",
        "fiber",
        "mfg",
        "fiberglass",
        "representative",
        "fabricator"
    ],
    "wof:name":"Hy Tech Industrial Sales",
    "wof:placetype":"venue"
},
  "geometry": {"coordinates":[-95.44165599999999,30.141606],"type":"Point"}
}