{
  "type": "Feature",
  "properties": {
    "iso:country":"US",
    "sg:address":"7954 Locke Ln",
    "sg:city":"Houston",
    "sg:classifiers":[
        {
            "category":"Wholesale",
            "subcategory":"Electrical",
            "type":"Manufacturing & Wholesale Goods"
        }
    ],
    "sg:phone":"+1 713 664 4477",
    "sg:postcode":"77063",
    "sg:province":"TX",
    "sg:tags":[
        "lighting",
        "fixture"
    ],
    "wof:name":"Builder Lights",
    "wof:placetype":"venue"
},
  "geometry": {"coordinates":[-95.508124,29.739905],"type":"Point"}
}