{
  "type": "Feature",
  "properties": {
    "iso:country":"US",
    "sg:address":"6301 Eppes St",
    "sg:city":"Houston",
    "sg:classifiers":[
        {
            "category":"Manufacturing",
            "subcategory":"Metals",
            "type":"Manufacturing & Wholesale Goods"
        }
    ],
    "sg:phone":"+1 713 644 1983",
    "sg:postcode":"77087",
    "sg:province":"TX",
    "sg:tags":[
        "steel",
        "distributor",
        "mill",
        "warehouse"
    ],
    "wof:name":"U S Alloys Inc",
    "wof:placetype":"venue"
},
  "geometry": {"coordinates":[-95.316101,29.69241],"type":"Point"}
}