{
  "type": "Feature",
  "properties": {
    "iso:country":"US",
    "sg:address":"29202 Ralph Fair Rd",
    "sg:city":"Boerne",
    "sg:classifiers":[
        {
            "category":"Food & Beverages",
            "subcategory":"Groceries & Convenience Stores",
            "type":"Retail Goods"
        }
    ],
    "sg:phone":"+1 830 981 4926",
    "sg:postcode":"78006",
    "sg:province":"TX",
    "sg:tags":[
        "grocer"
    ],
    "wof:name":"Fair Oaks Market",
    "wof:placetype":"venue"
},
  "geometry": {"coordinates":[-98.623217,29.738856],"type":"Point"}
}