{
  "type": "Feature",
  "properties": {
    "iso:country":"US",
    "sg:address":"990 N Main St",
    "sg:city":"Vidor",
    "sg:classifiers":[
        {
            "category":"Banks & Credit Unions",
            "subcategory":"Financial Services",
            "type":"Services"
        }
    ],
    "sg:phone":"+1 409 783 2395",
    "sg:postcode":"77662",
    "sg:province":"TX",
    "sg:tags":[
        "cashing",
        "financing",
        "loan",
        "check",
        "payday"
    ],
    "sg:website":"http://www.advanceamerica.com",
    "wof:name":"Advance America",
    "wof:placetype":"venue"
},
  "geometry": {"coordinates":[-94.016212,30.137091],"type":"Point"}
}