{
  "type": "Feature",
  "properties": {
    "iso:country":"US",
    "sg:address":"2121 Oakdale St",
    "sg:city":"Houston",
    "sg:classifiers":[
        {
            "category":"Health Services",
            "subcategory":"Doctor",
            "type":"Services"
        }
    ],
    "sg:phone":"+1 713 522 2222",
    "sg:postcode":"77004",
    "sg:province":"TX",
    "wof:name":"Jarolimek Lubor MD",
    "wof:placetype":"venue"
},
  "geometry": {"coordinates":[-95.378304,29.721901],"type":"Point"}
}