{
  "type": "Feature",
  "properties": {
    "iso:country":"US",
    "sg:address":"9711 Harrison Ln",
    "sg:city":"Missouri City",
    "sg:classifiers":[
        {
            "category":"Wholesale",
            "subcategory":"Apparel",
            "type":"Manufacturing & Wholesale Goods"
        }
    ],
    "sg:phone":"+1 281 778 9559",
    "sg:postcode":"77459",
    "sg:province":"TX",
    "sg:tags":[
        "clothing"
    ],
    "wof:name":"Storks & More",
    "wof:placetype":"venue"
},
  "geometry": {"coordinates":[-95.52063099999999,29.50448],"type":"Point"}
}