{
  "type": "Feature",
  "properties": {
    "iso:country":"US",
    "sg:address":"1815 Meadow Edge Ln",
    "sg:city":"Spring",
    "sg:classifiers":[
        {
            "category":"Recreation",
            "subcategory":"Marina",
            "type":"Entertainment"
        }
    ],
    "sg:phone":"+1 281 651 7512",
    "sg:postcode":"77388",
    "sg:province":"TX",
    "sg:tags":[
        "operation"
    ],
    "wof:name":"Boat & Rv STORAGE By Rammco",
    "wof:placetype":"venue"
},
  "geometry": {"coordinates":[-95.440862,30.05776],"type":"Point"}
}