{
  "type": "Feature",
  "properties": {
    "iso:country":"US",
    "sg:address":"5603 Waycross Ave",
    "sg:city":"El Paso",
    "sg:classifiers":[
        {
            "category":"Arts & Performance",
            "subcategory":"Theater",
            "type":"Entertainment"
        }
    ],
    "sg:phone":"+1 915 757 1413",
    "sg:postcode":"79924",
    "sg:province":"TX",
    "sg:tags":[
        "live",
        "music"
    ],
    "wof:name":"Midnight Productions",
    "wof:placetype":"venue"
},
  "geometry": {"coordinates":[-106.41017100000001,31.879972],"type":"Point"}
}