{
  "type": "Feature",
  "properties": {
    "iso:country":"US",
    "sg:address":"17330 Marianne Cir",
    "sg:city":"Dallas",
    "sg:classifiers":[
        {
            "category":"Real Estate",
            "subcategory":"Architect",
            "type":"Services"
        }
    ],
    "sg:phone":"+1 214 890 7980",
    "sg:postcode":"75252",
    "sg:province":"TX",
    "wof:name":"Ksng Architects",
    "wof:placetype":"venue"
},
  "geometry": {"coordinates":[-96.79700699999999,32.98685],"type":"Point"}
}