{
  "type": "Feature",
  "properties": {
    "iso:country":"US",
    "sg:address":"6335 Deep Canyon Dr",
    "sg:city":"Katy",
    "sg:classifiers":[
        {
            "category":"Wholesale",
            "subcategory":"Machinery & Supplies",
            "type":"Manufacturing & Wholesale Goods"
        }
    ],
    "sg:phone":"+1 281 829 0827",
    "sg:postcode":"77450",
    "sg:province":"TX",
    "sg:tags":[
        "seismic",
        "drill"
    ],
    "wof:name":"Seismic Drill General Supply",
    "wof:placetype":"venue"
},
  "geometry": {"coordinates":[-95.73033599999999,29.709021],"type":"Point"}
}