{
  "type": "Feature",
  "properties": {
    "iso:country":"US",
    "sg:address":"5101 Gillians Walk",
    "sg:city":"Austin",
    "sg:classifiers":[
        {
            "category":"Building & Trades",
            "subcategory":"Construction",
            "type":"Services"
        }
    ],
    "sg:phone":"+1 512 263 5436",
    "sg:postcode":"78738",
    "sg:province":"TX",
    "sg:tags":[
        "designer",
        "dealer",
        "pool",
        "swimming"
    ],
    "wof:name":"Amazon Poolscapes",
    "wof:placetype":"venue"
},
  "geometry": {"coordinates":[-97.95811399999999,30.29955],"type":"Point"}
}