{
  "type": "Feature",
  "properties": {
    "iso:country":"US",
    "sg:address":"11722 Marsh Ln",
    "sg:city":"Dallas",
    "sg:classifiers":[
        {
            "category":"Personal",
            "subcategory":"Nail Salon",
            "type":"Services"
        }
    ],
    "sg:phone":"+1 214 351 6136",
    "sg:postcode":"75229",
    "sg:province":"TX",
    "wof:name":"Hot Nails",
    "wof:placetype":"venue"
},
  "geometry": {"coordinates":[-96.856003,32.9081],"type":"Point"}
}