{
  "type": "Feature",
  "properties": {
    "iso:country":"US",
    "sg:address":"15809 Avenue C",
    "sg:city":"Channelview",
    "sg:classifiers":[
        {
            "category":"Organizations",
            "subcategory":"Religious Organization",
            "type":"Services"
        }
    ],
    "sg:phone":"+1 281 452 4098",
    "sg:postcode":"77530",
    "sg:province":"TX",
    "sg:website":"www.upci.org",
    "wof:name":"Channelview United Pentecostal Church",
    "wof:placetype":"venue"
},
  "geometry": {"coordinates":[-95.12400100000001,29.7829],"type":"Point"}
}