{
  "type": "Feature",
  "properties": {
    "iso:country":"US",
    "sg:address":"7425 Wellesley Ave",
    "sg:city":"Garland",
    "sg:classifiers":[
        {
            "category":"Professional",
            "subcategory":"Management & Consulting",
            "type":"Services"
        }
    ],
    "sg:phone":"+1 972 414 0402",
    "sg:postcode":"75044",
    "sg:province":"TX",
    "wof:name":"Cz Consulting",
    "wof:placetype":"venue"
},
  "geometry": {"coordinates":[-96.671357,32.983746],"type":"Point"}
}