{
  "type": "Feature",
  "properties": {
    "iso:country":"US",
    "sg:address":"15314 Pebble Peak",
    "sg:city":"San Antonio",
    "sg:classifiers":[
        {
            "category":"Professional",
            "subcategory":"Computer Services",
            "type":"Services"
        }
    ],
    "sg:phone":"+1 210 279 2434",
    "sg:postcode":"78232",
    "sg:province":"TX",
    "wof:name":"A Star Network Solutions",
    "wof:placetype":"venue"
},
  "geometry": {"coordinates":[-98.44220199999999,29.58229],"type":"Point"}
}