{
  "type": "Feature",
  "properties": {
    "iso:country":"US",
    "sg:address":"400 Grant St",
    "sg:city":"Cuero",
    "sg:classifiers":[
        {
            "category":"Organizations",
            "subcategory":"Religious Organization",
            "type":"Services"
        }
    ],
    "sg:phone":"+1 361 275 3348",
    "sg:postcode":"77954",
    "sg:province":"TX",
    "sg:tags":[
        "church"
    ],
    "wof:name":"Mount Bethel Baptist Church",
    "wof:placetype":"venue"
},
  "geometry": {"coordinates":[-97.296707,29.088945],"type":"Point"}
}