{
  "type": "Feature",
  "properties": {
    "iso:country":"US",
    "sg:address":"5043 Barlow Dr",
    "sg:city":"Round Rock",
    "sg:classifiers":[
        {
            "category":"Organizations",
            "subcategory":"Religious Organization",
            "type":"Services"
        }
    ],
    "sg:phone":"+1 512 733 5679",
    "sg:postcode":"78681",
    "sg:province":"TX",
    "wof:name":"Church In Community Fellowship",
    "wof:placetype":"venue"
},
  "geometry": {"coordinates":[-97.727284,30.497533],"type":"Point"}
}