{
  "type": "Feature",
  "properties": {
    "iso:country":"US",
    "sg:address":"1203 W 11th St",
    "sg:city":"Houston",
    "sg:classifiers":[
        {
            "category":"Donuts",
            "subcategory":"None",
            "type":"Food & Drink"
        }
    ],
    "sg:phone":"+1 713 802 1935",
    "sg:postcode":"77008",
    "sg:province":"TX",
    "wof:name":"Bakery Donuts",
    "wof:placetype":"venue"
},
  "geometry": {"coordinates":[-95.408997,29.7904],"type":"Point"}
}