{
  "type": "Feature",
  "properties": {
    "iso:country":"US",
    "sg:address":"4126 S Carrier Pkwy",
    "sg:city":"Grand Prairie",
    "sg:classifiers":[
        {
            "category":"Restaurant",
            "type":"Food & Drink"
        }
    ],
    "sg:menulink":"http://www.allmenus.com/tx/southwest/106919-soup-man/menu/",
    "sg:phone":"+1 972 642 2692",
    "sg:postcode":"75052",
    "sg:province":"TX",
    "sg:tags":[
        "soup",
        "american",
        "salad"
    ],
    "wof:name":"Soup Man",
    "wof:placetype":"venue"
},
  "geometry": {"coordinates":[-97.007677,32.672604],"type":"Point"}
}