{
  "type": "Feature",
  "properties": {
    "iso:country":"US",
    "sg:address":"708 N Alexander Dr",
    "sg:city":"Baytown",
    "sg:classifiers":[
        {
            "category":"Professional",
            "type":"Services"
        }
    ],
    "sg:phone":"+1 281 427 4711",
    "sg:postcode":"77520",
    "sg:province":"TX",
    "sg:tags":[
        "establishment"
    ],
    "wof:name":"Dickens Neal Mtr Co",
    "wof:placetype":"venue"
},
  "geometry": {"coordinates":[-94.956491,29.734214],"type":"Point"}
}