{
  "type": "Feature",
  "properties": {
    "iso:country":"US",
    "sg:address":"10223 Barwood Dr",
    "sg:city":"Houston",
    "sg:classifiers":[
        {
            "category":"Sports & Exercise",
            "subcategory":"Gym",
            "type":"Entertainment"
        }
    ],
    "sg:phone":"+1 713 434 7721",
    "sg:postcode":"77043",
    "sg:province":"TX",
    "sg:tags":[
        "fitness",
        "physical",
        "facility"
    ],
    "wof:name":"Milton D Moore",
    "wof:placetype":"venue"
},
  "geometry": {"coordinates":[-95.553315,29.805672],"type":"Point"}
}