{
  "type": "Feature",
  "properties": {
    "iso:country":"US",
    "sg:address":"2112 Wyoming Ave",
    "sg:city":"El Paso",
    "sg:classifiers":[
        {
            "category":"Retail",
            "subcategory":"Repair Shop",
            "type":"Services"
        }
    ],
    "sg:phone":"+1 915 778 9300",
    "sg:postcode":"79903",
    "sg:province":"TX",
    "wof:name":"Apex Cleaning & Prof Systems",
    "wof:placetype":"venue"
},
  "geometry": {"coordinates":[-106.469154,31.775997],"type":"Point"}
}