{
  "type": "Feature",
  "properties": {
    "iso:country":"US",
    "sg:address":"315 S Main St",
    "sg:city":"Perryton",
    "sg:classifiers":[
        {
            "category":"Professional",
            "subcategory":"Lawyer & Legal Services",
            "type":"Services"
        }
    ],
    "sg:phone":"+1 806 435 6121",
    "sg:postcode":"79070",
    "sg:province":"TX",
    "sg:tags":[
        "attorney"
    ],
    "wof:name":"Scott Law Office",
    "wof:placetype":"venue"
},
  "geometry": {"coordinates":[-100.802627,36.397334],"type":"Point"}
}