{
  "type": "Feature",
  "properties": {
    "iso:country":"US",
    "sg:address":"1207 Green Hill Dr",
    "sg:city":"Arlington",
    "sg:classifiers":[
        {
            "category":"Arena",
            "subcategory":"Sports Club",
            "type":"Entertainment"
        }
    ],
    "sg:phone":"+1 972 880 9144",
    "sg:postcode":"76014",
    "sg:province":"TX",
    "sg:tags":[
        "health"
    ],
    "wof:name":"Level 10 Power & Fitness",
    "wof:placetype":"venue"
},
  "geometry": {"coordinates":[-97.092862,32.686658],"type":"Point"}
}