{
  "type": "Feature",
  "properties": {
    "iso:country":"US",
    "sg:address":"113 Forest Glen Ct",
    "sg:city":"Weatherford",
    "sg:classifiers":[
        {
            "category":"Home & Garden",
            "subcategory":"Home Furnishings",
            "type":"Retail Goods"
        }
    ],
    "sg:phone":"+1 817 341 1362",
    "sg:postcode":"76087",
    "sg:province":"TX",
    "wof:name":"Babes & Bath",
    "wof:placetype":"venue"
},
  "geometry": {"coordinates":[-97.753801,32.72931],"type":"Point"}
}