{
  "type": "Feature",
  "properties": {
    "iso:country":"US",
    "sg:address":"3400 Silverstone Dr",
    "sg:city":"Plano",
    "sg:classifiers":[
        {
            "category":"Shopping",
            "subcategory":"Gifts & Souvenirs",
            "type":"Retail Goods"
        }
    ],
    "sg:phone":"+1 972 867 9508",
    "sg:postcode":"75023",
    "sg:province":"TX",
    "wof:name":"Star Bright Parents Aux",
    "wof:placetype":"venue"
},
  "geometry": {"coordinates":[-96.735913,33.041078],"type":"Point"}
}