{
  "type": "Feature",
  "properties": {
    "iso:country":"US",
    "sg:address":"11767 Katy Fwy",
    "sg:city":"Houston",
    "sg:classifiers":[
        {
            "category":"Banks & Credit Unions",
            "subcategory":"Bank",
            "type":"Services"
        }
    ],
    "sg:phone":"+1 281 752 6800",
    "sg:postcode":"77079",
    "sg:province":"TX",
    "sg:tags":[
        "personal",
        "financing",
        "institution"
    ],
    "wof:name":"Capitol Funding Trust Ltd",
    "wof:placetype":"venue"
},
  "geometry": {"coordinates":[-95.593839,29.784184],"type":"Point"}
}