{
  "type": "Feature",
  "properties": {
    "iso:country":"US",
    "sg:address":"1301 Travis St",
    "sg:city":"Houston",
    "sg:classifiers":[
        {
            "category":"Mining & Drilling",
            "type":"Manufacturing & Wholesale Goods"
        }
    ],
    "sg:phone":"+1 713 658 8080",
    "sg:postcode":"77002",
    "sg:province":"TX",
    "sg:tags":[
        "gas",
        "oil",
        "exploration",
        "production"
    ],
    "wof:name":"Dominion Energy and Mnrl Corp",
    "wof:placetype":"venue"
},
  "geometry": {"coordinates":[-95.36816399999999,29.7545],"type":"Point"}
}