{
  "type": "Feature",
  "properties": {
    "iso:country":"US",
    "sg:address":"3100 Monticello Ave",
    "sg:city":"Dallas",
    "sg:classifiers":[
        {
            "category":"Health Services",
            "subcategory":"Dentist",
            "type":"Services"
        }
    ],
    "sg:phone":"+1 214 528 5500",
    "sg:postcode":"75205",
    "sg:province":"TX",
    "wof:name":"Park Cities Oral & Maxillofacial Surgury PA",
    "wof:placetype":"venue"
},
  "geometry": {"coordinates":[-96.785268,32.826976],"type":"Point"}
}