{
  "type": "Feature",
  "properties": {
    "iso:country":"US",
    "sg:address":"16284 Treasure Cv",
    "sg:city":"Bullard",
    "sg:classifiers":[
        {
            "category":"Professional",
            "subcategory":"Business Services",
            "type":"Services"
        }
    ],
    "sg:phone":"+1 903 825 2998",
    "sg:postcode":"75757",
    "sg:province":"TX",
    "sg:tags":[
        "inspection"
    ],
    "wof:name":"Skillful Inspection Services",
    "wof:placetype":"venue"
},
  "geometry": {"coordinates":[-95.44243,32.142731],"type":"Point"}
}