{
  "type": "Feature",
  "properties": {
    "iso:country":"US",
    "sg:address":"6806 Canon Wren Dr",
    "sg:city":"Austin",
    "sg:classifiers":[
        {
            "category":"Organizations",
            "subcategory":"Membership Organization",
            "type":"Services"
        }
    ],
    "sg:phone":"+1 512 306 1674",
    "sg:postcode":"78746",
    "sg:province":"TX",
    "wof:name":"Texas Chapter Amercn Plg Assoc",
    "wof:placetype":"venue"
},
  "geometry": {"coordinates":[-97.836839,30.302067],"type":"Point"}
}