{
  "type": "Feature",
  "properties": {
    "iso:country":"US",
    "sg:address":"4200 N 19th St",
    "sg:city":"Waco",
    "sg:classifiers":[
        {
            "category":"Professional",
            "type":"Services"
        }
    ],
    "sg:phone":"+1 254 754 6306",
    "sg:postcode":"76708",
    "sg:province":"TX",
    "wof:name":"Texas Paralyzed Veterans",
    "wof:placetype":"venue"
},
  "geometry": {"coordinates":[-97.177043,31.586098],"type":"Point"}
}