{
  "type": "Feature",
  "properties": {
    "iso:country":"US",
    "sg:address":"808 Post St",
    "sg:city":"Houston",
    "sg:classifiers":[
        {
            "category":"Manufacturing",
            "subcategory":"Building Materials",
            "type":"Manufacturing & Wholesale Goods"
        }
    ],
    "sg:phone":"+1 713 691 6676",
    "sg:postcode":"77022",
    "sg:province":"TX",
    "sg:tags":[
        "mfg",
        "wood",
        "kitchen",
        "cabinet"
    ],
    "wof:name":"V & L Cabinets",
    "wof:placetype":"venue"
},
  "geometry": {"coordinates":[-95.361272,29.826444],"type":"Point"}
}