{
  "type": "Feature",
  "properties": {
    "iso:country":"US",
    "sg:address":"1569 Clarksville St",
    "sg:city":"Paris",
    "sg:classifiers":[
        {
            "category":"Organizations",
            "subcategory":"Religious Organization",
            "type":"Services"
        }
    ],
    "sg:phone":"+1 903 784 7337",
    "sg:postcode":"75460",
    "sg:province":"TX",
    "sg:tags":[
        "personal",
        "credit",
        "institution"
    ],
    "wof:name":"City Finance",
    "wof:placetype":"venue"
},
  "geometry": {"coordinates":[-95.539835,33.65784],"type":"Point"}
}