{
  "type": "Feature",
  "properties": {
    "iso:country":"US",
    "sg:address":"14101 N Freeway",
    "sg:city":"Houston",
    "sg:classifiers":[
        {
            "category":"Autos & Motor Vehicles",
            "subcategory":"Automobile Sales",
            "type":"Retail Goods"
        }
    ],
    "sg:phone":"+1 281 872 7200",
    "sg:postcode":"77040",
    "sg:province":"TX",
    "sg:tags":[
        "automotive"
    ],
    "sg:website":"www.demontrondvolvo.com/",
    "wof:name":"Demontrond Volvo",
    "wof:placetype":"venue"
},
  "geometry": {"coordinates":[-95.524804,29.858999],"type":"Point"}
}