{
  "type": "Feature",
  "properties": {
    "iso:country":"US",
    "sg:address":"2864 S 2nd Ave",
    "sg:city":"Mansfield",
    "sg:classifiers":[
        {
            "category":"Shopping",
            "subcategory":"Shoes",
            "type":"Retail Goods"
        }
    ],
    "sg:phone":"+1 682 518 0694",
    "sg:postcode":"76063",
    "sg:province":"TX",
    "wof:name":"All About Boots",
    "wof:placetype":"venue"
},
  "geometry": {"coordinates":[-97.137871,32.528151],"type":"Point"}
}