{
  "type": "Feature",
  "properties": {
    "iso:country":"US",
    "sg:address":"326 N Elm St",
    "sg:city":"Hereford",
    "sg:classifiers":[
        {
            "category":"Organizations",
            "subcategory":"Non-profit Organization",
            "type":"Services"
        }
    ],
    "sg:phone":"+1 806 364 4640",
    "sg:postcode":"79045",
    "sg:province":"TX",
    "sg:tags":[
        "social"
    ],
    "wof:name":"American Fundraising",
    "wof:placetype":"venue"
},
  "geometry": {"coordinates":[-102.416748,34.83235],"type":"Point"}
}