{
  "type": "Feature",
  "properties": {
    "iso:country":"US",
    "sg:address":"16707 Squyres Rd",
    "sg:city":"Spring",
    "sg:classifiers":[
        {
            "category":"Organizations",
            "subcategory":"Religious Organization",
            "type":"Services"
        }
    ],
    "sg:phone":"+1 281 376 2027",
    "sg:postcode":"77379",
    "sg:province":"TX",
    "sg:tags":[
        "baptist",
        "preschool",
        "church"
    ],
    "wof:name":"Fellowship Of Champions",
    "wof:placetype":"venue"
},
  "geometry": {"coordinates":[-95.531729,30.016525],"type":"Point"}
}