{
  "type": "Feature",
  "properties": {
    "iso:country":"US",
    "sg:address":"9523 Antoine Dr Ste F",
    "sg:city":"Houston",
    "sg:classifiers":[
        {
            "category":"Retail",
            "subcategory":"Laundry & Dry Cleaning",
            "type":"Services"
        }
    ],
    "sg:phone":"+1 281 447 8663",
    "sg:postcode":"77086",
    "sg:province":"TX",
    "wof:name":"2000 Cleaners & Alterations",
    "wof:placetype":"venue"
},
  "geometry": {"coordinates":[-95.4804,29.9076],"type":"Point"}
}