{
  "type": "Feature",
  "properties": {
    "iso:country":"US",
    "sg:address":"4938 Easter Dr",
    "sg:city":"Corpus Christi",
    "sg:classifiers":[
        {
            "category":"Professional",
            "subcategory":"Business Services",
            "type":"Services"
        }
    ],
    "sg:phone":"+1 361 854 1298",
    "sg:postcode":"78415",
    "sg:province":"TX",
    "wof:name":"Celestial Recording Studio",
    "wof:placetype":"venue"
},
  "geometry": {"coordinates":[-97.421708,27.735457],"type":"Point"}
}