{
  "type": "Feature",
  "properties": {
    "iso:country":"US",
    "sg:address":"5103 Woodmoor Dr",
    "sg:city":"Austin",
    "sg:classifiers":[
        {
            "category":"Freight",
            "type":"Transportation"
        }
    ],
    "sg:phone":"+1 512 926 0394",
    "sg:postcode":"78721",
    "sg:province":"TX",
    "sg:tags":[
        "operator",
        "distance",
        "long",
        "trucking"
    ],
    "wof:name":"Elliott Trucking",
    "wof:placetype":"venue"
},
  "geometry": {"coordinates":[-97.67572699999999,30.284671],"type":"Point"}
}