{
  "type": "Feature",
  "properties": {
    "iso:country":"US",
    "sg:address":"9805 Fox Chase Cir",
    "sg:city":"Austin",
    "sg:classifiers":[
        {
            "category":"Personal",
            "subcategory":"Beauty Salon",
            "type":"Services"
        }
    ],
    "sg:phone":"+1 512 258 1655",
    "sg:postcode":"78750",
    "sg:province":"TX",
    "sg:tags":[
        "wig",
        "hair",
        "piece"
    ],
    "wof:name":"Us Wig",
    "wof:placetype":"venue"
},
  "geometry": {"coordinates":[-97.80541100000001,30.433255],"type":"Point"}
}