{
  "type": "Feature",
  "properties": {
    "iso:country":"US",
    "sg:address":"900 Main St",
    "sg:city":"Lubbock",
    "sg:classifiers":[
        {
            "category":"Government",
            "subcategory":"Court House",
            "type":"Public Place"
        }
    ],
    "sg:phone":"+1 806 763 3981",
    "sg:postcode":"79401",
    "sg:province":"TX",
    "sg:tags":[
        "state",
        "counsel"
    ],
    "wof:name":"Attorney General",
    "wof:placetype":"venue"
},
  "geometry": {"coordinates":[-101.845641,33.585507],"type":"Point"}
}