{
  "type": "Feature",
  "properties": {
    "iso:country":"US",
    "sg:address":"425 Fry St",
    "sg:city":"Denton",
    "sg:classifiers":[
        {
            "category":"Autos & Motor Vehicles",
            "subcategory":"Automobile Sales",
            "type":"Retail Goods"
        }
    ],
    "sg:phone":"+1 940 387 2148",
    "sg:postcode":"76201",
    "sg:province":"TX",
    "sg:tags":[
        "used"
    ],
    "wof:name":"Motor Ventures",
    "wof:placetype":"venue"
},
  "geometry": {"coordinates":[-97.14649300000001,33.216429],"type":"Point"}
}