{
  "type": "Feature",
  "properties": {
    "iso:country":"US",
    "sg:address":"1443 Fulton Ave",
    "sg:city":"San Antonio",
    "sg:classifiers":[
        {
            "category":"Professional",
            "subcategory":"Business Services",
            "type":"Services"
        }
    ],
    "sg:phone":"+1 210 738 3068",
    "sg:postcode":"78201",
    "sg:province":"TX",
    "sg:tags":[
        "specialist",
        "advertising",
        "promotional"
    ],
    "wof:name":"RC Promotional",
    "wof:placetype":"venue"
},
  "geometry": {"coordinates":[-98.52014800000001,29.461686],"type":"Point"}
}