{
  "type": "Feature",
  "properties": {
    "iso:country":"US",
    "sg:address":"633 W Centerville Rd",
    "sg:city":"Garland",
    "sg:classifiers":[
        {
            "category":"Organizations",
            "subcategory":"Religious Organization",
            "type":"Services"
        }
    ],
    "sg:phone":"+1 972 926 4473",
    "sg:postcode":"75041",
    "sg:province":"TX",
    "sg:tags":[
        "church"
    ],
    "wof:name":"Safe Haven Church",
    "wof:placetype":"venue"
},
  "geometry": {"coordinates":[-96.640703,32.862864],"type":"Point"}
}