{
  "type": "Feature",
  "properties": {
    "iso:country":"US",
    "sg:address":"302 W 11th St",
    "sg:city":"Elgin",
    "sg:classifiers":[
        {
            "category":"Organizations",
            "subcategory":"Religious Organization",
            "type":"Services"
        }
    ],
    "sg:phone":"+1 512 285 9310",
    "sg:postcode":"78621",
    "sg:province":"TX",
    "sg:tags":[
        "church"
    ],
    "wof:name":"Sacred Hearth Catholic Church",
    "wof:placetype":"venue"
},
  "geometry": {"coordinates":[-97.379338,30.352215],"type":"Point"}
}