{
  "type": "Feature",
  "properties": {
    "iso:country":"US",
    "sg:address":"13027 Champions Dr",
    "sg:city":"Houston",
    "sg:classifiers":[
        {
            "category":"Personal",
            "subcategory":"Beauty Salon",
            "type":"Services"
        }
    ],
    "sg:phone":"+1 281 537 5659",
    "sg:postcode":"77069",
    "sg:province":"TX",
    "wof:name":"Diane El Guermai",
    "wof:placetype":"venue"
},
  "geometry": {"coordinates":[-95.525217,29.973246],"type":"Point"}
}