{
  "type": "Feature",
  "properties": {
    "iso:country":"US",
    "sg:address":"2075 Antoine Drive",
    "sg:city":"Houston",
    "sg:classifiers":[
        {
            "category":"Personal",
            "type":"Services"
        }
    ],
    "sg:phone":"+1 281 813 0160",
    "sg:postcode":"77055",
    "sg:province":"TX",
    "sg:tags":[
        "property",
        "maintenance"
    ],
    "sg:website":"http://www.absolutepipeline.com",
    "wof:name":"Absolute Pipeline Maintenance & Consulting",
    "wof:placetype":"venue"
},
  "geometry": {"coordinates":[-95.475442,29.80839],"type":"Point"}
}