{
  "type": "Feature",
  "properties": {
    "iso:country":"US",
    "sg:address":"530 State Hwy 323 NE",
    "sg:city":"Tyler",
    "sg:classifiers":[
        {
            "category":"Wholesale",
            "subcategory":"Auto Parts",
            "type":"Manufacturing & Wholesale Goods"
        }
    ],
    "sg:phone":"+1 903 593 5555",
    "sg:postcode":"75706",
    "sg:province":"TX",
    "wof:name":"TDS",
    "wof:placetype":"venue"
},
  "geometry": {"coordinates":[-95.28869899999999,32.390216],"type":"Point"}
}