{
  "type": "Feature",
  "properties": {
    "iso:country":"US",
    "sg:address":"715 NW River Rd",
    "sg:city":"Martindale",
    "sg:classifiers":[
        {
            "category":"Professional",
            "type":"Services"
        }
    ],
    "sg:phone":"+1 512 357 1498",
    "sg:postcode":"78655",
    "sg:province":"TX",
    "sg:tags":[
        "establishment"
    ],
    "wof:name":"Jam Co",
    "wof:placetype":"venue"
},
  "geometry": {"coordinates":[-97.859139,29.853303],"type":"Point"}
}