{
  "type": "Feature",
  "properties": {
    "iso:country":"US",
    "sg:address":"5240 W 34th St",
    "sg:city":"Houston",
    "sg:classifiers":[
        {
            "category":"Shopping",
            "subcategory":"Computers & Home Electronics",
            "type":"Retail Goods"
        }
    ],
    "sg:phone":"+1 713 682 4661",
    "sg:postcode":"77092",
    "sg:province":"TX",
    "sg:tags":[
        "game",
        "video"
    ],
    "wof:name":"Game Stop Corp",
    "wof:placetype":"venue"
},
  "geometry": {"coordinates":[-95.465757,29.819583],"type":"Point"}
}