{
  "type": "Feature",
  "properties": {
    "iso:country":"US",
    "sg:address":"4117 Creekstone Dr",
    "sg:city":"Plano",
    "sg:classifiers":[
        {
            "category":"Building & Trades",
            "subcategory":"Construction",
            "type":"Services"
        }
    ],
    "sg:phone":"+1 972 612 9932",
    "sg:postcode":"75093",
    "sg:province":"TX",
    "sg:tags":[
        "builder",
        "operative"
    ],
    "wof:name":"American Signature Homes",
    "wof:placetype":"venue"
},
  "geometry": {"coordinates":[-96.77455,33.053276],"type":"Point"}
}