{
  "type": "Feature",
  "properties": {
    "iso:country":"US",
    "sg:address":"1033 N Henderson St",
    "sg:city":"Fort Worth",
    "sg:classifiers":[
        {
            "category":"Autos & Motor Vehicles",
            "subcategory":"Auto Supplies",
            "type":"Retail Goods"
        }
    ],
    "sg:phone":"+1 817 877 1772",
    "sg:postcode":"76107",
    "sg:province":"TX",
    "sg:tags":[
        "equipment",
        "racing",
        "car",
        "automobile"
    ],
    "sg:website":"www.bobbyarchermotorsports.com",
    "wof:name":"Bobby Archer Motor Sports",
    "wof:placetype":"venue"
},
  "geometry": {"coordinates":[-97.350577,32.764683],"type":"Point"}
}