{
  "type": "Feature",
  "properties": {
    "iso:country":"US",
    "sg:address":"5623 Texoma Pkwy",
    "sg:city":"Sherman",
    "sg:classifiers":[
        {
            "category":"Wholesale",
            "subcategory":"Electrical",
            "type":"Manufacturing & Wholesale Goods"
        }
    ],
    "sg:phone":"+1 903 891 3118",
    "sg:postcode":"75090",
    "sg:province":"TX",
    "sg:tags":[
        "control",
        "security",
        "system"
    ],
    "sg:website":"www.gnisec.com",
    "wof:name":"Gnisec Security Cameras",
    "wof:placetype":"venue"
},
  "geometry": {"coordinates":[-96.57610699999999,33.694916],"type":"Point"}
}