{
  "type": "Feature",
  "properties": {
    "iso:country":"US",
    "sg:address":"2727 Fondren Rd # 7A",
    "sg:city":"Houston",
    "sg:classifiers":[
        {
            "category":"Coffee & Tea",
            "type":"Food & Drink"
        }
    ],
    "sg:phone":"+1 713 974 0443",
    "sg:postcode":"77063",
    "sg:province":"TX",
    "sg:website":"www.javacoffee.com",
    "wof:name":"Java Coffee & Tea Co.",
    "wof:placetype":"venue"
},
  "geometry": {"coordinates":[-95.520394,29.736491],"type":"Point"}
}