{
  "type": "Feature",
  "properties": {
    "iso:country":"US",
    "sg:address":"5100 Belt Line Rd Ste 820",
    "sg:city":"Dallas",
    "sg:classifiers":[
        {
            "category":"Shopping",
            "subcategory":"Crafts & Fabrics",
            "type":"Retail Goods"
        }
    ],
    "sg:phone":"+1 972 239 7957",
    "sg:postcode":"75254",
    "sg:province":"TX",
    "sg:tags":[
        "art"
    ],
    "sg:website":"www.kittrellriffkind.com",
    "wof:name":"Kittrell Riffkind Art Glass",
    "wof:placetype":"venue"
},
  "geometry": {"coordinates":[-96.82147000000001,32.953996],"type":"Point"}
}