{
  "type": "Feature",
  "properties": {
    "iso:country":"US",
    "sg:address":"1703 Autumn Woods St",
    "sg:city":"San Antonio",
    "sg:classifiers":[
        {
            "category":"Shopping",
            "subcategory":"Gifts & Souvenirs",
            "type":"Retail Goods"
        }
    ],
    "sg:phone":"+1 210 496 0116",
    "sg:postcode":"78232",
    "sg:province":"TX",
    "wof:name":"Richard W Wechtenhiser",
    "wof:placetype":"venue"
},
  "geometry": {"coordinates":[-98.467634,29.573594],"type":"Point"}
}