{
  "type": "Feature",
  "properties": {
    "iso:country":"US",
    "sg:address":"1019 Yale St",
    "sg:city":"Houston",
    "sg:classifiers":[
        {
            "category":"Wholesale",
            "subcategory":"Construction Materials",
            "type":"Manufacturing & Wholesale Goods"
        }
    ],
    "sg:phone":"+1 713 692 6961",
    "sg:postcode":"77008",
    "sg:province":"TX",
    "sg:tags":[
        "sand",
        "gravel"
    ],
    "wof:name":"Aggregate & Base Materials Inc",
    "wof:placetype":"venue"
},
  "geometry": {"coordinates":[-95.399011,29.788907],"type":"Point"}
}