{
  "type": "Feature",
  "properties": {
    "iso:country":"US",
    "sg:address":"10603 Co Rd 214",
    "sg:city":"Tyler",
    "sg:classifiers":[
        {
            "category":"Shopping",
            "subcategory":"Used Merchandise",
            "type":"Retail Goods"
        }
    ],
    "sg:phone":"+1 903 566 8236",
    "sg:postcode":"75707",
    "sg:province":"TX",
    "wof:name":"Miss Effies Attic",
    "wof:placetype":"venue"
},
  "geometry": {"coordinates":[-95.187439,32.32472],"type":"Point"}
}