{
  "type": "Feature",
  "properties": {
    "iso:country":"US",
    "sg:address":"5410 Bell St",
    "sg:city":"Amarillo",
    "sg:classifiers":[
        {
            "category":"Insurance",
            "subcategory":"Insurance Agent",
            "type":"Services"
        },
        {
            "category":"Insurance",
            "subcategory":"Hazard Insurance",
            "type":"Services"
        },
        {
            "category":"Insurance",
            "subcategory":"Title Insurance",
            "type":"Services"
        },
        {
            "category":"Insurance",
            "subcategory":"Life Insurance",
            "type":"Services"
        }
    ],
    "sg:phone":"+1 806 359 9835",
    "sg:postcode":"79109",
    "sg:province":"TX",
    "sg:tags":[
        "business",
        "auto",
        "commercial",
        "homeowner",
        "motorcycle",
        "renter"
    ],
    "wof:name":"Allstate Insurance Company - David Hahn",
    "wof:placetype":"venue"
},
  "geometry": {"coordinates":[-101.902075,35.150374],"type":"Point"}
}