{
  "type": "Feature",
  "properties": {
    "iso:country":"US",
    "sg:address":"305 W Broadway Ave",
    "sg:city":"Tulia",
    "sg:classifiers":[
        {
            "category":"Shopping",
            "subcategory":"Discount & Variety Stores",
            "type":"Retail Goods"
        }
    ],
    "sg:phone":"+1 361 785 2270",
    "sg:postcode":"79088",
    "sg:province":"TX",
    "wof:name":"Jessica's Variety Shop",
    "wof:placetype":"venue"
},
  "geometry": {"coordinates":[-101.768401,34.5371],"type":"Point"}
}