{
  "type": "Feature",
  "properties": {
    "iso:country":"US",
    "sg:address":"407 Earl St",
    "sg:city":"El Campo",
    "sg:classifiers":[
        {
            "category":"Building & Trades",
            "subcategory":"Construction",
            "type":"Services"
        }
    ],
    "sg:phone":"+1 979 543 1186",
    "sg:postcode":"77437",
    "sg:province":"TX",
    "sg:tags":[
        "contractor"
    ],
    "wof:name":"Herrera Roofing Co",
    "wof:placetype":"venue"
},
  "geometry": {"coordinates":[-96.275989,29.210795],"type":"Point"}
}