{
  "type": "Feature",
  "properties": {
    "iso:country":"US",
    "sg:address":"500 N 1st St",
    "sg:city":"Turkey",
    "sg:phone":"+1 806 423 1482",
    "sg:postcode":"79235",
    "sg:province":"TX",
    "sg:tags":[
        "farm",
        "cotton"
    ],
    "wof:name":"Campbell Bundy",
    "wof:placetype":"venue"
},
  "geometry": {"coordinates":[-101.342815,33.991032],"type":"Point"}
}