{
  "type": "Feature",
  "properties": {
    "iso:country":"US",
    "sg:address":"953 Bonita St",
    "sg:city":"Hitchcock",
    "sg:classifiers":[
        {
            "category":"Professional",
            "type":"Services"
        }
    ],
    "sg:phone":"+1 409 935 8934",
    "sg:postcode":"77563",
    "sg:province":"TX",
    "wof:name":"Gulf Coast Designs",
    "wof:placetype":"venue"
},
  "geometry": {"coordinates":[-94.93810499999999,29.324497],"type":"Point"}
}