{
  "type": "Feature",
  "properties": {
    "iso:country":"US",
    "sg:address":"7541 Rose Ln",
    "sg:city":"Kountze",
    "sg:classifiers":[
        {
            "category":"Organizations",
            "subcategory":"Religious Organization",
            "type":"Services"
        }
    ],
    "sg:phone":"+1 409 246 4844",
    "sg:postcode":"77625",
    "sg:province":"TX",
    "sg:tags":[
        "church"
    ],
    "wof:name":"Friendship Chappel",
    "wof:placetype":"venue"
},
  "geometry": {"coordinates":[-94.41509499999999,30.47803],"type":"Point"}
}