{
  "type": "Feature",
  "properties": {
    "iso:country":"US",
    "sg:address":"500 E 4th St",
    "sg:city":"Austin",
    "sg:classifiers":[
        {
            "category":"Communications",
            "subcategory":"Film & Video Production",
            "type":"Services"
        }
    ],
    "sg:phone":"+1 512 320 0560",
    "sg:postcode":"78701",
    "sg:province":"TX",
    "sg:tags":[
        "audio"
    ],
    "sg:website":"www.ps-av.com",
    "wof:name":"Presentation Services",
    "wof:placetype":"venue"
},
  "geometry": {"coordinates":[-97.73784000000001,30.264626],"type":"Point"}
}