{
  "type": "Feature",
  "properties": {
    "iso:country":"US",
    "sg:address":"7011 McNeil Dr",
    "sg:city":"Austin",
    "sg:classifiers":[
        {
            "category":"Autos & Motor Vehicles",
            "subcategory":"Automobile Sales",
            "type":"Retail Goods"
        },
        {
            "category":"Retail",
            "subcategory":"Auto Repair",
            "type":"Services"
        }
    ],
    "sg:phone":"+1 512 343 3500",
    "sg:postcode":"78729",
    "sg:province":"TX",
    "sg:tags":[
        "car",
        "used",
        "new"
    ],
    "sg:website":"www.bmwofaustin.com",
    "wof:name":"BMW of Austin",
    "wof:placetype":"venue"
},
  "geometry": {"coordinates":[-97.762001,30.436701],"type":"Point"}
}