{
  "type": "Feature",
  "properties": {
    "iso:country":"US",
    "sg:address":"1925 Cedar Springs Rd",
    "sg:city":"Dallas",
    "sg:classifiers":[
        {
            "category":"Restaurant",
            "type":"Food & Drink"
        }
    ],
    "sg:phone":"+1 214 754 0400",
    "sg:postcode":"75201",
    "sg:province":"TX",
    "sg:tags":[
        "management"
    ],
    "wof:name":"Romano Group",
    "wof:placetype":"venue"
},
  "geometry": {"coordinates":[-96.80501099999999,32.789356],"type":"Point"}
}