{
  "type": "Feature",
  "properties": {
    "iso:country":"US",
    "sg:address":"7505 Fannin St Ste 214",
    "sg:city":"Houston",
    "sg:classifiers":[
        {
            "category":"Health Services",
            "subcategory":"Doctor",
            "type":"Services"
        }
    ],
    "sg:phone":"+1 713 797 6453",
    "sg:postcode":"77054",
    "sg:province":"TX",
    "sg:tags":[
        "surgeon",
        "oral"
    ],
    "wof:name":"Deborah Phan, DDS",
    "wof:placetype":"venue"
},
  "geometry": {"coordinates":[-95.401467,29.69239],"type":"Point"}
}