{
  "type": "Feature",
  "properties": {
    "iso:country":"US",
    "sg:address":"5373 Wagon Trl",
    "sg:city":"Robstown",
    "sg:classifiers":[
        {
            "category":"Professional",
            "subcategory":"Business Services",
            "type":"Services"
        }
    ],
    "sg:phone":"+1 361 387 9204",
    "sg:postcode":"78380",
    "sg:province":"TX",
    "sg:tags":[
        "inspection"
    ],
    "wof:name":"N-Spec Quality Svc Inc",
    "wof:placetype":"venue"
},
  "geometry": {"coordinates":[-97.67598599999999,27.863785],"type":"Point"}
}