{
  "type": "Feature",
  "properties": {
    "iso:country":"US",
    "sg:address":"313 E Hutchison St",
    "sg:city":"San Marcos",
    "sg:classifiers":[
        {
            "category":"Professional",
            "subcategory":"Printing & Photocopies",
            "type":"Services"
        }
    ],
    "sg:phone":"+1 512 443 0040",
    "sg:postcode":"78666",
    "sg:province":"TX",
    "sg:tags":[
        "photocopying"
    ],
    "wof:name":"Minuteman Press",
    "wof:placetype":"venue"
},
  "geometry": {"coordinates":[-97.93781199999999,29.884757],"type":"Point"}
}