{
  "type": "Feature",
  "properties": {
    "iso:country":"US",
    "sg:address":"14139 Glasgow Pl",
    "sg:city":"Houston",
    "sg:classifiers":[
        {
            "category":"Professional",
            "subcategory":"Management & Consulting",
            "type":"Services"
        }
    ],
    "sg:phone":"+1 281 493 6878",
    "sg:postcode":"77077",
    "sg:province":"TX",
    "wof:name":"Ip Development Inc",
    "wof:placetype":"venue"
},
  "geometry": {"coordinates":[-95.63499899999999,29.756627],"type":"Point"}
}