{
  "type": "Feature",
  "properties": {
    "iso:country":"US",
    "sg:address":"5288 S Hulen St",
    "sg:city":"Fort Worth",
    "sg:classifiers":[
        {
            "category":"Restaurant",
            "type":"Food & Drink"
        }
    ],
    "sg:menulink":"http://www.allmenus.com/tx/fort-worth/114937-chilis/menu/",
    "sg:phone":"817572119",
    "sg:postcode":"76132",
    "sg:province":"TX",
    "sg:tags":[
        "burger",
        "american",
        "sandwich",
        "tex-mex",
        "soup"
    ],
    "wof:name":"Chili's",
    "wof:placetype":"venue"
},
  "geometry": {"coordinates":[-97.399951,32.67129],"type":"Point"}
}