{
  "type": "Feature",
  "properties": {
    "iso:country":"US",
    "sg:address":"14729 Santa Gertrudis Dr",
    "sg:city":"Corpus Christi",
    "sg:classifiers":[
        {
            "category":"Professional",
            "type":"Services"
        }
    ],
    "sg:phone":"+1 361 387 2587",
    "sg:postcode":"78410",
    "sg:province":"TX",
    "wof:name":"Bw Waters Inc",
    "wof:placetype":"venue"
},
  "geometry": {"coordinates":[-97.656289,27.87176],"type":"Point"}
}