{
  "type": "Feature",
  "properties": {
    "iso:country":"US",
    "sg:address":"6756 Inwood Dr",
    "sg:city":"Fort Worth",
    "sg:classifiers":[
        {
            "category":"Shopping",
            "subcategory":"Used Merchandise",
            "type":"Retail Goods"
        }
    ],
    "sg:phone":"+1 817 605 3084",
    "sg:postcode":"76180",
    "sg:province":"TX",
    "sg:tags":[
        "antique"
    ],
    "wof:name":"Brady & Brady Enterprises",
    "wof:placetype":"venue"
},
  "geometry": {"coordinates":[-97.23582500000001,32.883106],"type":"Point"}
}