{
  "type": "Feature",
  "properties": {
    "iso:country":"US",
    "sg:address":"411 W Jackson St",
    "sg:city":"El Campo",
    "sg:classifiers":[
        {
            "category":"Professional",
            "subcategory":"Lawyer & Legal Services",
            "type":"Services"
        }
    ],
    "sg:phone":"+1 979 543 6822",
    "sg:postcode":"77437",
    "sg:province":"TX",
    "sg:tags":[
        "attorney"
    ],
    "wof:name":"Karen H Meinardus",
    "wof:placetype":"venue"
},
  "geometry": {"coordinates":[-96.27292,29.194662],"type":"Point"}
}