{
  "type": "Feature",
  "properties": {
    "iso:country":"US",
    "sg:address":"806 Mountain Dr",
    "sg:city":"San Marcos",
    "sg:classifiers":[
        {
            "category":"Professional",
            "type":"Services"
        }
    ],
    "sg:phone":"+1 512 396 4122",
    "sg:postcode":"78666",
    "sg:province":"TX",
    "wof:name":"L&L Condo Inc",
    "wof:placetype":"venue"
},
  "geometry": {"coordinates":[-97.98590900000001,29.860452],"type":"Point"}
}