{
  "type": "Feature",
  "properties": {
    "iso:country":"US",
    "sg:address":"3103 S Lamar Blvd",
    "sg:city":"Austin",
    "sg:classifiers":[
        {
            "category":"Retail",
            "subcategory":"Auto Repair",
            "type":"Services"
        }
    ],
    "sg:phone":"+1 512 444 5564",
    "sg:postcode":"78704",
    "sg:province":"TX",
    "sg:tags":[
        "repairing",
        "automobile"
    ],
    "wof:name":"Andy's Auto Electric Plus",
    "wof:placetype":"venue"
},
  "geometry": {"coordinates":[-97.783357,30.242883],"type":"Point"}
}