{
  "type": "Feature",
  "properties": {
    "iso:country":"US",
    "sg:address":"1107 Magnolia Ave",
    "sg:city":"Port Neches",
    "sg:classifiers":[
        {
            "category":"Real Estate",
            "subcategory":"Real Estate Operator",
            "type":"Services"
        }
    ],
    "sg:phone":"+1 409 727 1694",
    "sg:postcode":"77651",
    "sg:province":"TX",
    "sg:tags":[
        "building",
        "apartment",
        "refrigeration"
    ],
    "wof:name":"Concord Apts",
    "wof:placetype":"venue"
},
  "geometry": {"coordinates":[-93.965304,29.981586],"type":"Point"}
}