{
  "type": "Feature",
  "properties": {
    "iso:country":"US",
    "sg:address":"1001 N Dixie Blvd",
    "sg:city":"Odessa",
    "sg:classifiers":[
        {
            "category":"Professional",
            "type":"Services"
        }
    ],
    "sg:phone":"+1 432 337 3106",
    "sg:postcode":"79761",
    "sg:province":"TX",
    "sg:tags":[
        "establishment"
    ],
    "wof:name":"Bailey Group",
    "wof:placetype":"venue"
},
  "geometry": {"coordinates":[-102.360736,31.85877],"type":"Point"}
}