{
  "type": "Feature",
  "properties": {
    "iso:country":"US",
    "sg:address":"8339 Lovett Ave",
    "sg:city":"Dallas",
    "sg:classifiers":[
        {
            "category":"Manufacturing",
            "subcategory":"Metals",
            "type":"Manufacturing & Wholesale Goods"
        }
    ],
    "sg:phone":"+1 214 398 3225",
    "sg:postcode":"75227",
    "sg:province":"TX",
    "sg:tags":[
        "fence"
    ],
    "sg:website":"www.fenceonline.com",
    "wof:name":"Master-Halco",
    "wof:placetype":"venue"
},
  "geometry": {"coordinates":[-96.678769,32.776166],"type":"Point"}
}