{
  "type": "Feature",
  "properties": {
    "iso:country":"US",
    "sg:address":"118 Renfro Valley Dr",
    "sg:city":"Huntsville",
    "sg:classifiers":[
        {
            "category":"Place Of Worship",
            "subcategory":"Church",
            "type":"Public Place"
        },
        {
            "category":"Place Of Worship",
            "type":"Public Place"
        }
    ],
    "sg:phone":"+1 936 294 9649",
    "sg:postcode":"77320",
    "sg:province":"TX",
    "sg:tags":[
        "churches-interdenominational",
        "churches-various",
        "denomination"
    ],
    "wof:name":"Little Bethel Holiness Church",
    "wof:placetype":"venue"
},
  "geometry": {"coordinates":[-95.524597,30.722904],"type":"Point"}
}