{
  "type": "Feature",
  "properties": {
    "iso:country":"US",
    "sg:address":"10979 Co Rd 41",
    "sg:city":"Tyler",
    "sg:classifiers":[
        {
            "category":"Building & Trades",
            "subcategory":"Plumbing",
            "type":"Services"
        }
    ],
    "sg:phone":"+1 903 882 1338",
    "sg:postcode":"75706",
    "sg:province":"TX",
    "sg:tags":[
        "plumbing",
        "contractor"
    ],
    "wof:name":"Boeh Plumbing Company Inc",
    "wof:placetype":"venue"
},
  "geometry": {"coordinates":[-95.346481,32.481558],"type":"Point"}
}