{
  "type": "Feature",
  "properties": {
    "iso:country":"US",
    "sg:address":"16031 Arbor Trl",
    "sg:city":"Buda",
    "sg:classifiers":[
        {
            "category":"Retail",
            "subcategory":"Portrait Studio",
            "type":"Services"
        }
    ],
    "sg:phone":"+1 512 312 1941",
    "sg:postcode":"78610",
    "sg:province":"TX",
    "sg:tags":[
        "photo"
    ],
    "wof:name":"J David Rowley Photography",
    "wof:placetype":"venue"
},
  "geometry": {"coordinates":[-97.91182000000001,30.118022],"type":"Point"}
}