{
  "type": "Feature",
  "properties": {
    "iso:country":"US",
    "sg:address":"15885 Old Hwy 105 W",
    "sg:city":"Montgomery",
    "sg:classifiers":[
        {
            "category":"Food & Beverages",
            "subcategory":"Bakery",
            "type":"Retail Goods"
        }
    ],
    "sg:phone":"+1 936 588 0475",
    "sg:postcode":"77356",
    "sg:province":"TX",
    "sg:tags":[
        "doughnut"
    ],
    "wof:name":"Sparkling Donuts",
    "wof:placetype":"venue"
},
  "geometry": {"coordinates":[-95.792918,30.346169],"type":"Point"}
}