{
  "type": "Feature",
  "properties": {
    "iso:country":"US",
    "sg:address":"806 E 40th St",
    "sg:city":"Lubbock",
    "sg:classifiers":[
        {
            "category":"Freight",
            "type":"Transportation"
        }
    ],
    "sg:phone":"+1 806 762 8947",
    "sg:postcode":"79404",
    "sg:province":"TX",
    "sg:tags":[
        "trucking"
    ],
    "wof:name":"USF Bestway Inc",
    "wof:placetype":"venue"
},
  "geometry": {"coordinates":[-101.828326,33.557754],"type":"Point"}
}