{
  "type": "Feature",
  "properties": {
    "iso:country":"US",
    "sg:address":"1514 Upland Dr",
    "sg:city":"San Antonio",
    "sg:classifiers":[
        {
            "category":"Government",
            "subcategory":"Office",
            "type":"Public Place"
        }
    ],
    "sg:phone":"+1 210 337 6344",
    "sg:postcode":"78219",
    "sg:province":"TX",
    "sg:tags":[
        "national",
        "security"
    ],
    "wof:name":"Domicile",
    "wof:placetype":"venue"
},
  "geometry": {"coordinates":[-98.41502800000001,29.428193],"type":"Point"}
}