{
  "type": "Feature",
  "properties": {
    "iso:country":"US",
    "sg:address":"13497 N Highway 183 Ste 100",
    "sg:city":"Austin",
    "sg:classifiers":[
        {
            "category":"Banks & Credit Unions",
            "subcategory":"Bank",
            "type":"Services"
        }
    ],
    "sg:phone":"+1 512 996 9070",
    "sg:postcode":"78750",
    "sg:province":"TX",
    "sg:website":"www.compassbank.com",
    "wof:name":"BBVA Compass",
    "wof:placetype":"venue"
},
  "geometry": {"coordinates":[-97.789974,30.449388],"type":"Point"}
}