{
  "type": "Feature",
  "properties": {
    "iso:country":"US",
    "sg:address":"4804 Melrose Park Dr",
    "sg:city":"Colleyville",
    "sg:classifiers":[
        {
            "category":"Professional",
            "subcategory":"Business Services",
            "type":"Services"
        }
    ],
    "sg:phone":"+1 817 267 3476",
    "sg:postcode":"76034",
    "sg:province":"TX",
    "sg:tags":[
        "printing",
        "commercial"
    ],
    "wof:name":"Full Stride Sales",
    "wof:placetype":"venue"
},
  "geometry": {"coordinates":[-97.11720800000001,32.87933],"type":"Point"}
}