{
  "type": "Feature",
  "properties": {
    "iso:country":"US",
    "sg:address":"5839 Paisley St",
    "sg:city":"Houston",
    "sg:classifiers":[
        {
            "category":"Professional",
            "subcategory":"Advertising",
            "type":"Services"
        }
    ],
    "sg:phone":"+1 713 721 5288",
    "sg:postcode":"77096",
    "sg:province":"TX",
    "sg:website":"www.jack-stewart.com",
    "wof:name":"JACKSTEWART.COM",
    "wof:placetype":"venue"
},
  "geometry": {"coordinates":[-95.492259,29.674282],"type":"Point"}
}