{
  "type": "Feature",
  "properties": {
    "iso:country":"US",
    "sg:address":"3409 53rd St",
    "sg:city":"Lubbock",
    "sg:classifiers":[
        {
            "category":"Retail",
            "subcategory":"Repair Shop",
            "type":"Services"
        }
    ],
    "sg:phone":"+1 806 778 2313",
    "sg:postcode":"79413",
    "sg:province":"TX",
    "sg:tags":[
        "taxidermist"
    ],
    "wof:name":"All-Star Taxidermists",
    "wof:placetype":"venue"
},
  "geometry": {"coordinates":[-101.88803,33.546039],"type":"Point"}
}