{
  "type": "Feature",
  "properties": {
    "iso:country":"US",
    "sg:address":"1508 50th St",
    "sg:city":"Lubbock",
    "sg:classifiers":[
        {
            "category":"Retail",
            "subcategory":"Repair Shop",
            "type":"Services"
        }
    ],
    "sg:phone":"+1 806 763 5521",
    "sg:postcode":"79412",
    "sg:province":"TX",
    "sg:tags":[
        "body",
        "auto"
    ],
    "wof:name":"Marios Trim Shop",
    "wof:placetype":"venue"
},
  "geometry": {"coordinates":[-101.852394,33.548813],"type":"Point"}
}