{
  "type": "Feature",
  "properties": {
    "iso:country":"US",
    "sg:address":"3123 Green Meadow Dr",
    "sg:city":"San Angelo",
    "sg:classifiers":[
        {
            "category":"Personal",
            "subcategory":"Beauty Salon",
            "type":"Services"
        }
    ],
    "sg:phone":"+1 325 944 3376",
    "sg:postcode":"76904",
    "sg:province":"TX",
    "sg:tags":[
        "treatment",
        "skin"
    ],
    "wof:name":"Bel-Ami Dermatology",
    "wof:placetype":"venue"
},
  "geometry": {"coordinates":[-100.487386,31.419642],"type":"Point"}
}