{
  "type": "Feature",
  "properties": {
    "iso:country":"US",
    "sg:address":"142 Truly Plz",
    "sg:city":"Cleveland",
    "sg:classifiers":[
        {
            "category":"Insurance",
            "subcategory":"Hazard Insurance",
            "type":"Services"
        }
    ],
    "sg:phone":"+1 281 592 1031",
    "sg:postcode":"77327",
    "sg:province":"TX",
    "sg:tags":[
        "commercial",
        "business"
    ],
    "wof:name":"Insurance Services",
    "wof:placetype":"venue"
},
  "geometry": {"coordinates":[-95.096191,30.334185],"type":"Point"}
}