{
  "type": "Feature",
  "properties": {
    "iso:country":"US",
    "sg:address":"2208 Co Rd 436",
    "sg:city":"Yoakum",
    "sg:classifiers":[
        {
            "category":"Building & Trades",
            "subcategory":"Construction",
            "type":"Services"
        }
    ],
    "sg:phone":"+1 361 293 6342",
    "sg:postcode":"77995",
    "sg:province":"TX",
    "sg:tags":[
        "general",
        "contractor"
    ],
    "wof:name":"LTD Construction Co",
    "wof:placetype":"venue"
},
  "geometry": {"coordinates":[-97.03325,29.190888],"type":"Point"}
}