{
  "type": "Feature",
  "properties": {
    "iso:country":"US",
    "sg:address":"3118 E Main St",
    "sg:city":"Grand Prairie",
    "sg:classifiers":[
        {
            "category":"Manufacturing",
            "subcategory":"Building Materials",
            "type":"Manufacturing & Wholesale Goods"
        }
    ],
    "sg:phone":"+1 972 262 0755",
    "sg:postcode":"75050",
    "sg:province":"TX",
    "sg:tags":[
        "molding",
        "mfg",
        "custom",
        "mantle",
        "fireplace",
        "display"
    ],
    "wof:name":"A E S Custom Wood Inc",
    "wof:placetype":"venue"
},
  "geometry": {"coordinates":[-96.95971400000001,32.749473],"type":"Point"}
}