{
  "type": "Feature",
  "properties": {
    "iso:country":"US",
    "sg:address":"2118 Holly Hill Ln",
    "sg:city":"Carrollton",
    "sg:classifiers":[
        {
            "category":"Professional",
            "subcategory":"Management & Consulting",
            "type":"Services"
        }
    ],
    "sg:phone":"+1 972 492 0473",
    "sg:postcode":"75007",
    "sg:province":"TX",
    "sg:tags":[
        "business"
    ],
    "wof:name":"Strategic Global Images Inc",
    "wof:placetype":"venue"
},
  "geometry": {"coordinates":[-96.869738,33.014216],"type":"Point"}
}