{
  "type": "Feature",
  "properties": {
    "iso:country":"US",
    "sg:address":"3306 Sul Ross St",
    "sg:city":"Houston",
    "sg:classifiers":[
        {
            "category":"Health Services",
            "subcategory":"Doctor",
            "type":"Services"
        }
    ],
    "sg:phone":"+1 713 630 0600",
    "sg:postcode":"77098",
    "sg:province":"TX",
    "wof:name":"Cordray & Goodrich Professional Corporation",
    "wof:placetype":"venue"
},
  "geometry": {"coordinates":[-95.426498,29.7376],"type":"Point"}
}