{
  "type": "Feature",
  "properties": {
    "iso:country":"US",
    "sg:address":"9338 Regiment Dr",
    "sg:city":"San Antonio",
    "sg:classifiers":[
        {
            "category":"Insurance",
            "subcategory":"Insurance Agent",
            "type":"Services"
        }
    ],
    "sg:phone":"+1 210 677 0500",
    "sg:postcode":"78240",
    "sg:province":"TX",
    "wof:name":"United Concordia Co Inc",
    "wof:placetype":"venue"
},
  "geometry": {"coordinates":[-98.617841,29.529484],"type":"Point"}
}