{
  "type": "Feature",
  "properties": {
    "iso:country":"US",
    "sg:address":"224 E University Blvd",
    "sg:city":"Odessa",
    "sg:classifiers":[
        {
            "category":"Retail",
            "subcategory":"Self-service Laundry",
            "type":"Services"
        }
    ],
    "sg:phone":"+1 432 332 3415",
    "sg:postcode":"79762",
    "sg:province":"TX",
    "wof:name":"Rub Board",
    "wof:placetype":"venue"
},
  "geometry": {"coordinates":[-102.379418,31.868406],"type":"Point"}
}