{
  "type": "Feature",
  "properties": {
    "iso:country":"US",
    "sg:address":"6001 Gateway Blvd W",
    "sg:city":"El Paso",
    "sg:classifiers":[
        {
            "category":"Shopping",
            "subcategory":"Computers & Home Electronics",
            "type":"Retail Goods"
        }
    ],
    "sg:phone":"+1 915 351 8320",
    "sg:postcode":"79925",
    "sg:province":"TX",
    "sg:tags":[
        "equipment",
        "electronic",
        "supply"
    ],
    "wof:name":"ILM Svc Inc",
    "wof:placetype":"venue"
},
  "geometry": {"coordinates":[-106.41167799999999,31.781898],"type":"Point"}
}