{
  "type": "Feature",
  "properties": {
    "iso:country":"US",
    "sg:address":"1391 Lochspring Dr",
    "sg:city":"Rockwall",
    "sg:classifiers":[
        {
            "category":"Building & Trades",
            "subcategory":"Construction",
            "type":"Services"
        }
    ],
    "sg:phone":"+1 972 772 7450",
    "sg:postcode":"75032",
    "sg:province":"TX",
    "sg:tags":[
        "house"
    ],
    "wof:name":"Centex Homes  Inc",
    "wof:placetype":"venue"
},
  "geometry": {"coordinates":[-96.441333,32.904325],"type":"Point"}
}