{
  "type": "Feature",
  "properties": {
    "iso:country":"US",
    "sg:address":"3141 Irving Blvd",
    "sg:city":"Dallas",
    "sg:classifiers":[
        {
            "category":"Manufacturing",
            "subcategory":"Printing",
            "type":"Manufacturing & Wholesale Goods"
        }
    ],
    "sg:phone":"+1 214 637 6384",
    "sg:postcode":"75247",
    "sg:province":"TX",
    "sg:tags":[
        "commercial"
    ],
    "sg:website":"www.printingetc.net",
    "wof:name":"Printing Etc",
    "wof:placetype":"venue"
},
  "geometry": {"coordinates":[-96.864205,32.807918],"type":"Point"}
}