{
  "type": "Feature",
  "properties": {
    "iso:country":"US",
    "sg:address":"1207 L Ave",
    "sg:city":"Plano",
    "sg:classifiers":[
        {
            "category":"Building & Trades",
            "subcategory":"Construction",
            "type":"Services"
        },
        {
            "category":"Building & Trades",
            "subcategory":"Electrical",
            "type":"Services"
        },
        {
            "category":"Home & Garden",
            "subcategory":"Household Appliances",
            "type":"Retail Goods"
        },
        {
            "category":"Home & Garden",
            "subcategory":"Building Materials",
            "type":"Retail Goods"
        },
        {
            "category":"Professional",
            "subcategory":"Engineering",
            "type":"Services"
        },
        {
            "category":"Building & Trades",
            "subcategory":"Cleaning & Sanitation",
            "type":"Services"
        }
    ],
    "sg:phone":"+1 972 424 4300",
    "sg:postcode":"75074",
    "sg:province":"TX",
    "sg:tags":[
        "systems-repairing",
        "purifying",
        "repair",
        "duct",
        "quality-indoor",
        "system",
        "specialty",
        "equipment",
        "furnaces-heating",
        "furnaces-repairing",
        "pump",
        "insulation",
        "heating",
        "contractor",
        "heat",
        "air conditioning"
    ],
    "sg:website":"http://www.ServiceExpertsDFW.biz",
    "wof:name":"Service Experts DFW",
    "wof:placetype":"venue"
},
  "geometry": {"coordinates":[-96.69776899999999,33.015961],"type":"Point"}
}