{
  "type": "Feature",
  "properties": {
    "iso:country":"US",
    "sg:address":"9212 Flickering Shadow Dr",
    "sg:city":"Dallas",
    "sg:classifiers":[
        {
            "category":"Restaurant",
            "type":"Food & Drink"
        }
    ],
    "sg:phone":"+1 972 664 0415",
    "sg:postcode":"75243",
    "sg:province":"TX",
    "sg:tags":[
        "eating"
    ],
    "wof:name":"Pie In Sky Cafe",
    "wof:placetype":"venue"
},
  "geometry": {"coordinates":[-96.736548,32.920803],"type":"Point"}
}