{
  "type": "Feature",
  "properties": {
    "iso:country":"US",
    "sg:address":"2721 Cherlin Pl",
    "sg:city":"Richardson",
    "sg:classifiers":[
        {
            "category":"Building & Trades",
            "subcategory":"Construction",
            "type":"Services"
        }
    ],
    "sg:phone":"+1 972 690 1207",
    "sg:postcode":"75082",
    "sg:province":"TX",
    "sg:tags":[
        "repairing",
        "remodeling",
        "contractor"
    ],
    "wof:name":"Romex Painting & Remodeling",
    "wof:placetype":"venue"
},
  "geometry": {"coordinates":[-96.672057,32.994156],"type":"Point"}
}