{
  "type": "Feature",
  "properties": {
    "iso:country":"US",
    "sg:address":"203 Forrest South Dr",
    "sg:city":"Whitehouse",
    "sg:classifiers":[
        {
            "category":"Real Estate",
            "subcategory":"Real Estate Agent",
            "type":"Services"
        }
    ],
    "sg:phone":"+1 903 526 3900",
    "sg:postcode":"75791",
    "sg:province":"TX",
    "sg:tags":[
        "appraiser"
    ],
    "wof:name":"Scott Good & Assoc Inc",
    "wof:placetype":"venue"
},
  "geometry": {"coordinates":[-95.21261,32.20745],"type":"Point"}
}