{
  "type": "Feature",
  "properties": {
    "iso:country":"US",
    "sg:address":"6855 Old Spring Branch Rd",
    "sg:city":"Spring Branch",
    "sg:classifiers":[
        {
            "category":"Home & Garden",
            "subcategory":"Home Furnishings",
            "type":"Retail Goods"
        }
    ],
    "sg:phone":"+1 830 885 7622",
    "sg:postcode":"78070",
    "sg:province":"TX",
    "wof:name":"Juscuz Pottery & Artwork",
    "wof:placetype":"venue"
},
  "geometry": {"coordinates":[-98.45723099999999,29.880195],"type":"Point"}
}