{
  "type": "Feature",
  "properties": {
    "iso:country":"US",
    "sg:address":"1910 Silver St",
    "sg:city":"Garland",
    "sg:classifiers":[
        {
            "category":"Wholesale",
            "subcategory":"Medical Equipment & Supplies",
            "type":"Manufacturing & Wholesale Goods"
        }
    ],
    "sg:phone":"+1 972 494 3334",
    "sg:postcode":"75042",
    "sg:province":"TX",
    "sg:tags":[
        "podiatrist",
        "rent"
    ],
    "wof:name":"Medicos",
    "wof:placetype":"venue"
},
  "geometry": {"coordinates":[-96.656761,32.910192],"type":"Point"}
}