{
  "type": "Feature",
  "properties": {
    "iso:country":"US",
    "sg:address":"1515 Mission Hills Ln",
    "sg:city":"Denton",
    "sg:classifiers":[
        {
            "category":"Professional",
            "subcategory":"Accounting & Tax Preparation",
            "type":"Services"
        }
    ],
    "sg:phone":"+1 940 321 6550",
    "sg:postcode":"76210",
    "sg:province":"TX",
    "wof:name":"Naston A Wright CPA",
    "wof:placetype":"venue"
},
  "geometry": {"coordinates":[-97.084732,33.157752],"type":"Point"}
}