{
  "type": "Feature",
  "properties": {
    "iso:country":"US",
    "sg:address":"1317 East St",
    "sg:city":"Graham",
    "sg:classifiers":[
        {
            "category":"Health Services",
            "subcategory":"Doctor",
            "type":"Services"
        }
    ],
    "sg:phone":"+1 940 549 0350",
    "sg:postcode":"76450",
    "sg:province":"TX",
    "wof:name":"Reno",
    "wof:placetype":"venue"
},
  "geometry": {"coordinates":[-98.584305,33.092162],"type":"Point"}
}