{
  "type": "Feature",
  "properties": {
    "iso:country":"US",
    "sg:address":"1500 Pine St",
    "sg:city":"Beaumont",
    "sg:classifiers":[
        {
            "category":"Recreation",
            "subcategory":"Marina",
            "type":"Entertainment"
        }
    ],
    "sg:phone":"+1 409 832 1456",
    "sg:postcode":"77703",
    "sg:province":"TX",
    "wof:name":"Beaumont Yacht Club Inc",
    "wof:placetype":"venue"
},
  "geometry": {"coordinates":[-94.10026000000001,30.095388],"type":"Point"}
}