{
  "type": "Feature",
  "properties": {
    "iso:country":"US",
    "sg:address":"318 N Texas Blvd",
    "sg:city":"Alice",
    "sg:classifiers":[
        {
            "category":"Food & Beverages",
            "subcategory":"Groceries & Convenience Stores",
            "type":"Retail Goods"
        },
        {
            "category":"Autos & Motor Vehicles",
            "subcategory":"Fuel & Gas Station",
            "type":"Retail Goods"
        }
    ],
    "sg:phone":"+1 361 668 0806",
    "sg:postcode":"78332",
    "sg:province":"TX",
    "sg:tags":[
        "station"
    ],
    "wof:name":"Aycock Oil Co Inc",
    "wof:placetype":"venue"
},
  "geometry": {"coordinates":[-98.064678,27.753963],"type":"Point"}
}