{
  "type": "Feature",
  "properties": {
    "iso:country":"US",
    "sg:address":"1901 Preston Rd",
    "sg:city":"Dallas",
    "sg:classifiers":[
        {
            "category":"Shopping",
            "subcategory":"Department Store",
            "type":"Retail Goods"
        }
    ],
    "sg:phone":"+1 972 931 9846",
    "sg:postcode":"75221",
    "sg:province":"TX",
    "wof:name":"Wal-Mart",
    "wof:placetype":"venue"
},
  "geometry": {"coordinates":[-96.7724,32.841999],"type":"Point"}
}