{
  "type": "Feature",
  "properties": {
    "iso:country":"US",
    "sg:address":"915 W Agarita Ave",
    "sg:city":"San Antonio",
    "sg:classifiers":[
        {
            "category":"Health Services",
            "subcategory":"Health Practitioner",
            "type":"Services"
        }
    ],
    "sg:phone":"+1 210 734 5704",
    "sg:postcode":"78201",
    "sg:province":"TX",
    "wof:name":"Muscle Therapy Resource",
    "wof:placetype":"venue"
},
  "geometry": {"coordinates":[-98.50967900000001,29.457777],"type":"Point"}
}