{
  "type": "Feature",
  "properties": {
    "iso:country":"US",
    "sg:address":"1609 Kenning Rd",
    "sg:city":"Crosby",
    "sg:classifiers":[
        {
            "category":"Building & Trades",
            "subcategory":"Construction",
            "type":"Services"
        }
    ],
    "sg:phone":"+1 281 462 8585",
    "sg:postcode":"77532",
    "sg:province":"TX",
    "sg:tags":[
        "general",
        "contractor"
    ],
    "wof:name":"Malibu Constructors Inc",
    "wof:placetype":"venue"
},
  "geometry": {"coordinates":[-95.035985,29.888481],"type":"Point"}
}