{
  "type": "Feature",
  "properties": {
    "iso:country":"US",
    "sg:address":"3800 N Shepherd Dr",
    "sg:city":"Houston",
    "sg:classifiers":[
        {
            "category":"Food & Beverages",
            "subcategory":"Specialty",
            "type":"Retail Goods"
        }
    ],
    "sg:phone":"+1 713 691 4810",
    "sg:postcode":"77018",
    "sg:province":"TX",
    "sg:tags":[
        "health",
        "diet"
    ],
    "wof:name":"HPF Inc",
    "wof:placetype":"venue"
},
  "geometry": {"coordinates":[-95.410506,29.822131],"type":"Point"}
}