{
  "type": "Feature",
  "properties": {
    "iso:country":"US",
    "sg:address":"7303 Alameda Ave",
    "sg:city":"El Paso",
    "sg:classifiers":[
        {
            "category":"Autos & Motor Vehicles",
            "subcategory":"Automobile Sales",
            "type":"Retail Goods"
        }
    ],
    "sg:phone":"+1 915 775 0465",
    "sg:postcode":"79915",
    "sg:province":"TX",
    "sg:tags":[
        "car",
        "dealer"
    ],
    "wof:name":"Q Man Motors",
    "wof:placetype":"venue"
},
  "geometry": {"coordinates":[-106.38091799999999,31.744625],"type":"Point"}
}