{
  "type": "Feature",
  "properties": {
    "iso:country":"US",
    "sg:address":"3232 Parkwood Blvd",
    "sg:city":"Plano",
    "sg:classifiers":[
        {
            "category":"Retail",
            "subcategory":"Veterinary Services",
            "type":"Services"
        }
    ],
    "sg:phone":"+1 972 403 7373",
    "sg:postcode":"75093",
    "sg:province":"TX",
    "wof:name":"Windhaven Veterinary Hospital",
    "wof:placetype":"venue"
},
  "geometry": {"coordinates":[-96.826756,33.044437],"type":"Point"}
}