{
  "type": "Feature",
  "properties": {
    "iso:country":"US",
    "sg:address":"20814 el Suelo Bueno",
    "sg:city":"San Antonio",
    "sg:classifiers":[
        {
            "category":"Professional",
            "type":"Services"
        }
    ],
    "sg:phone":"+1 210 497 4617",
    "sg:postcode":"78258",
    "sg:province":"TX",
    "sg:tags":[
        "establishment"
    ],
    "wof:name":"PPISI",
    "wof:placetype":"venue"
},
  "geometry": {"coordinates":[-98.49264599999999,29.63814],"type":"Point"}
}