{
  "type": "Feature",
  "properties": {
    "iso:country":"US",
    "sg:address":"201 W Alene Dr",
    "sg:city":"Mabank",
    "sg:classifiers":[
        {
            "category":"Shopping",
            "subcategory":"Books",
            "type":"Retail Goods"
        }
    ],
    "sg:phone":"+1 903 887 7775",
    "sg:postcode":"75147",
    "sg:province":"TX",
    "wof:name":"Fruits of Grace Christian Bks",
    "wof:placetype":"venue"
},
  "geometry": {"coordinates":[-96.10868499999999,32.356971],"type":"Point"}
}