{
  "type": "Feature",
  "properties": {
    "iso:country":"US",
    "sg:address":"1412 Daventry Dr",
    "sg:city":"Desoto",
    "sg:classifiers":[
        {
            "category":"Professional",
            "subcategory":"Accounting & Tax Preparation",
            "type":"Services"
        }
    ],
    "sg:phone":"+1 972 296 5164",
    "sg:postcode":"75115",
    "sg:province":"TX",
    "sg:tags":[
        "bookkeeping"
    ],
    "wof:name":"Infinity Accounting Solutions",
    "wof:placetype":"venue"
},
  "geometry": {"coordinates":[-96.89561500000001,32.611859],"type":"Point"}
}