{
  "type": "Feature",
  "properties": {
    "iso:country":"US",
    "sg:address":"195 W Oak St",
    "sg:city":"Stephenville",
    "sg:classifiers":[
        {
            "category":"Building & Trades",
            "subcategory":"Plumbing",
            "type":"Services"
        }
    ],
    "sg:phone":"+1 254 965 4086",
    "sg:postcode":"76401",
    "sg:province":"TX",
    "sg:tags":[
        "plumbing",
        "contractor"
    ],
    "wof:name":"Cross Timbers Plumbing",
    "wof:placetype":"venue"
},
  "geometry": {"coordinates":[-98.209371,32.230005],"type":"Point"}
}