{
  "type": "Feature",
  "properties": {
    "iso:country":"US",
    "sg:address":"1221 Nelson Pl",
    "sg:city":"Burleson",
    "sg:classifiers":[
        {
            "category":"Building & Trades",
            "subcategory":"Electrical",
            "type":"Services"
        }
    ],
    "sg:phone":"+1 817 266 3459",
    "sg:postcode":"76028",
    "sg:province":"TX",
    "sg:tags":[
        "energy"
    ],
    "wof:name":"Borob Energy",
    "wof:placetype":"venue"
},
  "geometry": {"coordinates":[-97.29783399999999,32.590085],"type":"Point"}
}