{
  "type": "Feature",
  "properties": {
    "iso:country":"US",
    "sg:address":"12219 Hoblitzelle Dr",
    "sg:city":"Dallas",
    "sg:classifiers":[
        {
            "category":"Taxi",
            "type":"Transportation"
        }
    ],
    "sg:phone":"+1 972 644 6165",
    "sg:postcode":"75243",
    "sg:province":"TX",
    "sg:tags":[
        "taxicab"
    ],
    "wof:name":"Nega Abebaw Kebede",
    "wof:placetype":"venue"
},
  "geometry": {"coordinates":[-96.758589,32.916456],"type":"Point"}
}