{
  "type": "Feature",
  "properties": {
    "iso:country":"US",
    "sg:address":"10636 Hamlin Dr",
    "sg:city":"Dallas",
    "sg:classifiers":[
        {
            "category":"Building & Trades",
            "subcategory":"Construction",
            "type":"Services"
        }
    ],
    "sg:phone":"+1 214 674 7154",
    "sg:postcode":"75217",
    "sg:province":"TX",
    "sg:tags":[
        "concrete",
        "contractor"
    ],
    "wof:name":"Hernandez Contractors",
    "wof:placetype":"venue"
},
  "geometry": {"coordinates":[-96.640326,32.718168],"type":"Point"}
}