{
  "type": "Feature",
  "properties": {
    "iso:country":"US",
    "sg:address":"3900 Union Rd",
    "sg:city":"Texarkana",
    "sg:classifiers":[
        {
            "category":"Organizations",
            "subcategory":"Religious Organization",
            "type":"Services"
        }
    ],
    "sg:phone":"+1 870 774 6978",
    "sg:postcode":"71854",
    "sg:province":"TX",
    "sg:tags":[
        "church"
    ],
    "wof:name":"Cornerstone Baptist Church",
    "wof:placetype":"venue"
},
  "geometry": {"coordinates":[-94.001988,33.372428],"type":"Point"}
}