{
  "type": "Feature",
  "properties": {
    "iso:country":"US",
    "sg:address":"111 Trinity Ave",
    "sg:city":"Weatherford",
    "sg:classifiers":[
        {
            "category":"Shopping",
            "subcategory":"Pharmacy",
            "type":"Retail Goods"
        }
    ],
    "sg:phone":"+1 817 594 3851",
    "sg:postcode":"76086",
    "sg:province":"TX",
    "wof:name":"Davis City Pharmacy",
    "wof:placetype":"venue"
},
  "geometry": {"coordinates":[-97.797237,32.759644],"type":"Point"}
}