{
  "type": "Feature",
  "properties": {
    "iso:country":"US",
    "sg:address":"5124 N 10th St",
    "sg:city":"Mcallen",
    "sg:classifiers":[
        {
            "category":"Health Services",
            "subcategory":"Doctor",
            "type":"Services"
        }
    ],
    "sg:phone":"+1 956 630 6026",
    "sg:postcode":"78504",
    "sg:province":"TX",
    "wof:name":"Pope Bill D Jr Pdtric Dntstry",
    "wof:placetype":"venue"
},
  "geometry": {"coordinates":[-98.222306,26.248001],"type":"Point"}
}