{
  "type": "Feature",
  "properties": {
    "iso:country":"US",
    "sg:address":"3707 Troup Hwy",
    "sg:city":"Tyler",
    "sg:classifiers":[
        {
            "category":"Shopping",
            "type":"Retail Goods"
        }
    ],
    "sg:phone":"+1 903 561 4459",
    "sg:postcode":"75703",
    "sg:province":"TX",
    "sg:tags":[
        "art",
        "gallery",
        "merchandise",
        "dealer"
    ],
    "wof:name":"Exum's Gallery",
    "wof:placetype":"venue"
},
  "geometry": {"coordinates":[-95.272954,32.309494],"type":"Point"}
}