{
  "type": "Feature",
  "properties": {
    "iso:country":"US",
    "sg:address":"1540 Wagon Wheels Trl",
    "sg:city":"Dallas",
    "sg:classifiers":[
        {
            "category":"Professional",
            "subcategory":"Business Services",
            "type":"Services"
        }
    ],
    "sg:phone":"+1 214 375 3490",
    "sg:postcode":"75241",
    "sg:province":"TX",
    "wof:name":"Awj Enterprises LLC",
    "wof:placetype":"venue"
},
  "geometry": {"coordinates":[-96.79810999999999,32.680286],"type":"Point"}
}