{
  "type": "Feature",
  "properties": {
    "iso:country":"US",
    "sg:address":"904 W 22nd 1/2 St",
    "sg:city":"Austin",
    "sg:classifiers":[
        {
            "category":"Shopping",
            "subcategory":"Used Merchandise",
            "type":"Retail Goods"
        }
    ],
    "sg:phone":"+1 512 474 5005",
    "sg:postcode":"78705",
    "sg:province":"TX",
    "sg:tags":[
        "shop",
        "vintage",
        "consignment",
        "resale"
    ],
    "wof:name":"Vintage",
    "wof:placetype":"venue"
},
  "geometry": {"coordinates":[-97.74646199999999,30.286381],"type":"Point"}
}