{
  "type": "Feature",
  "properties": {
    "iso:country":"US",
    "sg:address":"1434 Goswell Ln",
    "sg:city":"Channelview",
    "sg:classifiers":[
        {
            "category":"Building & Trades",
            "subcategory":"Equipment Rental",
            "type":"Services"
        }
    ],
    "sg:phone":"+1 832 273 5748",
    "sg:postcode":"77530",
    "sg:province":"TX",
    "sg:tags":[
        "yard",
        "leasing",
        "store"
    ],
    "wof:name":"Sky Bounce Moonwalk & Party Rentals",
    "wof:placetype":"venue"
},
  "geometry": {"coordinates":[-95.143951,29.802777],"type":"Point"}
}