{
  "type": "Feature",
  "properties": {
    "iso:country":"US",
    "sg:address":"510 S Mill St",
    "sg:city":"Lewisville",
    "sg:classifiers":[
        {
            "category":"Wholesale",
            "subcategory":"Hardware",
            "type":"Manufacturing & Wholesale Goods"
        }
    ],
    "sg:phone":"+1 972 436 1506",
    "sg:postcode":"75057",
    "sg:province":"TX",
    "sg:tags":[
        "plumbing",
        "fixture",
        "merchandise",
        "supply"
    ],
    "wof:name":"Apex Supply Company",
    "wof:placetype":"venue"
},
  "geometry": {"coordinates":[-96.994041,33.043088],"type":"Point"}
}