{
  "type": "Feature",
  "properties": {
    "iso:country":"US",
    "sg:address":"4023 Oak Lawn Ave",
    "sg:city":"Dallas",
    "sg:classifiers":[
        {
            "category":"Restaurant",
            "type":"Food & Drink"
        },
        {
            "category":"Arts & Performance",
            "subcategory":"Jazz & Blues",
            "type":"Entertainment"
        }
    ],
    "sg:phone":"+1 214 890 1500",
    "sg:postcode":"75219",
    "sg:province":"TX",
    "sg:tags":[
        "seafood",
        "steakhouse"
    ],
    "sg:website":"www.eddiev.com/",
    "wof:name":"Eddie V's Prime Seafood",
    "wof:placetype":"venue"
},
  "geometry": {"coordinates":[-96.802998,32.817976],"type":"Point"}
}