{
  "type": "Feature",
  "properties": {
    "iso:country":"US",
    "sg:address":"1303 Pino Dr",
    "sg:city":"Laguna Vista",
    "sg:classifiers":[
        {
            "category":"Real Estate",
            "subcategory":"Real Estate Operator",
            "type":"Services"
        }
    ],
    "sg:phone":"+1 956 943 2266",
    "sg:postcode":"78578",
    "sg:province":"TX",
    "sg:tags":[
        "apartment"
    ],
    "wof:name":"El Norte Apartments",
    "wof:placetype":"venue"
},
  "geometry": {"coordinates":[-97.30032,26.106284],"type":"Point"}
}