{
  "type": "Feature",
  "properties": {
    "iso:country":"US",
    "sg:address":"1705 Wallace Dr",
    "sg:city":"Carrollton",
    "sg:classifiers":[
        {
            "category":"Home & Garden",
            "subcategory":"Household Appliances",
            "type":"Retail Goods"
        }
    ],
    "sg:phone":"+1 972 446 8888",
    "sg:postcode":"75006",
    "sg:province":"TX",
    "wof:name":"Jarrell Appliance Gallery",
    "wof:placetype":"venue"
},
  "geometry": {"coordinates":[-96.925595,32.940554],"type":"Point"}
}