{
  "type": "Feature",
  "properties": {
    "iso:country":"US",
    "sg:address":"901 Fry St",
    "sg:city":"Marshall",
    "sg:classifiers":[
        {
            "category":"Health Services",
            "subcategory":"Clinic",
            "type":"Services"
        }
    ],
    "sg:phone":"+1 903 938 4278",
    "sg:postcode":"75670",
    "sg:province":"TX",
    "sg:tags":[
        "home",
        "care"
    ],
    "wof:name":"Ajr Home Care Services Inc",
    "wof:placetype":"venue"
},
  "geometry": {"coordinates":[-94.35893,32.535097],"type":"Point"}
}