{
  "type": "Feature",
  "properties": {
    "iso:country":"US",
    "sg:address":"2101 W Rochelle Rd",
    "sg:city":"Irving",
    "sg:classifiers":[
        {
            "category":"Restaurant",
            "type":"Food & Drink"
        }
    ],
    "sg:phone":"+1 972 252 2003",
    "sg:postcode":"75062",
    "sg:province":"TX",
    "sg:tags":[
        "eating"
    ],
    "sg:website":"www.southernrecipes.com",
    "wof:name":"Southern Recipes",
    "wof:placetype":"venue"
},
  "geometry": {"coordinates":[-96.972099,32.842201],"type":"Point"}
}