{
  "type": "Feature",
  "properties": {
    "iso:country":"US",
    "sg:address":"12404 Beverly Villas Ct",
    "sg:city":"Austin",
    "sg:classifiers":[
        {
            "category":"Personal",
            "subcategory":"Beauty Salon",
            "type":"Services"
        }
    ],
    "sg:phone":"+1 512 694 0918",
    "sg:postcode":"78732",
    "sg:province":"TX",
    "wof:name":"Skin Spa",
    "wof:placetype":"venue"
},
  "geometry": {"coordinates":[-97.890592,30.371308],"type":"Point"}
}