{
  "type": "Feature",
  "properties": {
    "iso:country":"US",
    "sg:address":"287 Hidden Lakes Blvd",
    "sg:city":"Gunter",
    "sg:classifiers":[
        {
            "category":"Home & Garden",
            "subcategory":"Building Materials",
            "type":"Retail Goods"
        }
    ],
    "sg:phone":"+1 903 433 2706",
    "sg:postcode":"75058",
    "sg:province":"TX",
    "wof:name":"First Impressions",
    "wof:placetype":"venue"
},
  "geometry": {"coordinates":[-96.70822,33.468532],"type":"Point"}
}