{
  "type": "Feature",
  "properties": {
    "iso:country":"US",
    "sg:address":"1108 8th St",
    "sg:city":"Wellington",
    "sg:classifiers":[
        {
            "category":"Mining & Drilling",
            "type":"Manufacturing & Wholesale Goods"
        }
    ],
    "sg:phone":"+1 806 447 5125",
    "sg:postcode":"79095",
    "sg:province":"TX",
    "sg:tags":[
        "crude",
        "production",
        "gas"
    ],
    "wof:name":"Holten Oil Company",
    "wof:placetype":"venue"
},
  "geometry": {"coordinates":[-100.211901,34.856258],"type":"Point"}
}