{
  "type": "Feature",
  "properties": {
    "iso:country":"US",
    "sg:address":"623 Myrta St Ste E",
    "sg:city":"Kerrville",
    "sg:classifiers":[
        {
            "category":"Personal",
            "subcategory":"Beauty Salon",
            "type":"Services"
        }
    ],
    "sg:phone":"+1 830 896 1620",
    "sg:postcode":"78028",
    "sg:province":"TX",
    "wof:name":"Tamra Hartman",
    "wof:placetype":"venue"
},
  "geometry": {"coordinates":[-99.13507199999999,30.053847],"type":"Point"}
}