{
  "type": "Feature",
  "properties": {
    "iso:country":"US",
    "sg:address":"105 N Katherine St",
    "sg:city":"Crane",
    "sg:classifiers":[
        {
            "category":"Local Transit",
            "type":"Transportation"
        }
    ],
    "sg:phone":"+1 432 558 2094",
    "sg:postcode":"79731",
    "sg:province":"TX",
    "wof:name":"Trax Transportation",
    "wof:placetype":"venue"
},
  "geometry": {"coordinates":[-102.358724,31.401035],"type":"Point"}
}