{
  "type": "Feature",
  "properties": {
    "iso:country":"US",
    "sg:address":"594 Sawdust Rd",
    "sg:city":"Spring",
    "sg:classifiers":[
        {
            "category":"Restaurant",
            "type":"Food & Drink"
        }
    ],
    "sg:phone":"+1 832 620 8621",
    "sg:postcode":"77380",
    "sg:province":"TX",
    "sg:tags":[
        "grill",
        "bar"
    ],
    "wof:name":"Samba Grille",
    "wof:placetype":"venue"
},
  "geometry": {"coordinates":[-95.450907,30.126691],"type":"Point"}
}