{
  "type": "Feature",
  "properties": {
    "iso:country":"US",
    "sg:address":"2135 Bissonnet St",
    "sg:city":"Houston",
    "sg:classifiers":[
        {
            "category":"Professional",
            "type":"Services"
        }
    ],
    "sg:phone":"+1 713 526 4112",
    "sg:postcode":"77005",
    "sg:province":"TX",
    "wof:name":"Medellin Joaquin",
    "wof:placetype":"venue"
},
  "geometry": {"coordinates":[-95.40995599999999,29.725516],"type":"Point"}
}