{
  "type": "Feature",
  "properties": {
    "iso:country":"US",
    "sg:address":"1435 Beall St",
    "sg:city":"Houston",
    "sg:classifiers":[
        {
            "category":"Retail",
            "subcategory":"Event Space",
            "type":"Services"
        },
        {
            "category":"Community Center",
            "subcategory":"Social",
            "type":"Public Place"
        }
    ],
    "sg:phone":"+1 713 869 5767",
    "sg:postcode":"77008",
    "sg:province":"TX",
    "sg:tags":[
        "club",
        "venue"
    ],
    "sg:website":"www.lodge88.org",
    "wof:name":"SPJST Lodge 88",
    "wof:placetype":"venue"
},
  "geometry": {"coordinates":[-95.418502,29.797286],"type":"Point"}
}