{
  "type": "Feature",
  "properties": {
    "iso:country":"US",
    "sg:address":"240 Portland St",
    "sg:city":"Houston",
    "sg:classifiers":[
        {
            "category":"Shopping",
            "subcategory":"Gifts & Souvenirs",
            "type":"Retail Goods"
        },
        {
            "category":"Manufacturing",
            "subcategory":"Printing",
            "type":"Manufacturing & Wholesale Goods"
        }
    ],
    "sg:phone":"+1 713 807 9693",
    "sg:postcode":"77006",
    "sg:province":"TX",
    "sg:tags":[
        "announcement",
        "commercial",
        "invitation"
    ],
    "wof:name":"A 6 Invitations",
    "wof:placetype":"venue"
},
  "geometry": {"coordinates":[-95.38967,29.729789],"type":"Point"}
}