{
  "type": "Feature",
  "properties": {
    "iso:country":"US",
    "sg:address":"1912 N Floyd Rd",
    "sg:city":"Richardson",
    "sg:classifiers":[
        {
            "category":"Restaurant",
            "type":"Food & Drink"
        }
    ],
    "sg:phone":"+1 972 234 8233",
    "sg:postcode":"75080",
    "sg:province":"TX",
    "sg:tags":[
        "eating"
    ],
    "wof:name":"Digital Cafe",
    "wof:placetype":"venue"
},
  "geometry": {"coordinates":[-96.744372,32.976563],"type":"Point"}
}