{
  "type": "Feature",
  "properties": {
    "iso:country":"US",
    "sg:address":"2222 Lansing Switch Rd",
    "sg:city":"Longview",
    "sg:classifiers":[
        {
            "category":"Professional",
            "subcategory":"Business Services",
            "type":"Services"
        }
    ],
    "sg:phone":"+1 903 668 4112",
    "sg:postcode":"75602",
    "sg:province":"TX",
    "wof:name":"Roper Enterprises",
    "wof:placetype":"venue"
},
  "geometry": {"coordinates":[-94.620931,32.465633],"type":"Point"}
}