{
  "type": "Feature",
  "properties": {
    "iso:country":"US",
    "sg:address":"214 Jeffers Rd",
    "sg:city":"Freeport",
    "sg:classifiers":[
        {
            "category":"Building & Trades",
            "subcategory":"Construction",
            "type":"Services"
        }
    ],
    "sg:phone":"+1 979 415 0881",
    "sg:postcode":"77541",
    "sg:province":"TX",
    "sg:tags":[
        "heavy",
        "residential",
        "excavation"
    ],
    "wof:name":"Standard Constructors Inc",
    "wof:placetype":"venue"
},
  "geometry": {"coordinates":[-95.330224,28.990817],"type":"Point"}
}