{
  "type": "Feature",
  "properties": {
    "iso:country":"US",
    "sg:address":"566 Fm 1960 Rd W",
    "sg:city":"Houston",
    "sg:classifiers":[
        {
            "category":"Restaurant",
            "type":"Food & Drink"
        }
    ],
    "sg:menulink":"http://www.allmenus.com/tx/northwest-harris/136865-smoothie-king/menu/",
    "sg:phone":"+1 281 444 3101",
    "sg:postcode":"77090",
    "sg:province":"TX",
    "sg:tags":[
        "smoothy",
        "juice",
        "american"
    ],
    "wof:name":"Smoothie King",
    "wof:placetype":"venue"
},
  "geometry": {"coordinates":[-95.43831900000001,30.018974],"type":"Point"}
}