{
  "type": "Feature",
  "properties": {
    "iso:country":"US",
    "sg:address":"503 Congress Ave",
    "sg:city":"San Antonio",
    "sg:classifiers":[
        {
            "category":"Professional",
            "subcategory":"Business Services",
            "type":"Services"
        }
    ],
    "sg:phone":"+1 210 924 6210",
    "sg:postcode":"78214",
    "sg:province":"TX",
    "wof:name":"Spear Tax Service",
    "wof:placetype":"venue"
},
  "geometry": {"coordinates":[-98.482665,29.36171],"type":"Point"}
}