{
  "type": "Feature",
  "properties": {
    "iso:country":"US",
    "sg:address":"12285 Trautwein Rd",
    "sg:city":"Austin",
    "sg:classifiers":[
        {
            "category":"Building & Trades",
            "subcategory":"Construction",
            "type":"Services"
        }
    ],
    "sg:phone":"+1 512 263 8355",
    "sg:postcode":"78737",
    "sg:province":"TX",
    "sg:tags":[
        "contractor"
    ],
    "wof:name":"Bronwyn LTD",
    "wof:placetype":"venue"
},
  "geometry": {"coordinates":[-98.01419,30.201412],"type":"Point"}
}