{
  "type": "Feature",
  "properties": {
    "iso:country":"US",
    "sg:address":"1001 Fannin St",
    "sg:city":"Houston",
    "sg:classifiers":[
        {
            "category":"Utilities",
            "subcategory":"Fuel Oil & Lpg",
            "type":"Services"
        }
    ],
    "sg:phone":"+1 713 739 0648",
    "sg:postcode":"77002",
    "sg:province":"TX",
    "sg:tags":[
        "dealer"
    ],
    "wof:name":"Northstar Oil and Gas Company",
    "wof:placetype":"venue"
},
  "geometry": {"coordinates":[-95.364639,29.755689],"type":"Point"}
}