{
  "type": "Feature",
  "properties": {
    "iso:country":"US",
    "sg:address":"1507 Egger Ave",
    "sg:city":"Round Rock",
    "sg:classifiers":[
        {
            "category":"Building & Trades",
            "subcategory":"Construction",
            "type":"Services"
        }
    ],
    "sg:phone":"+1 512 388 5392",
    "sg:postcode":"78664",
    "sg:province":"TX",
    "sg:tags":[
        "specializing",
        "contractor",
        "work",
        "laying",
        "floor"
    ],
    "wof:name":"Surfaces & Interiors",
    "wof:placetype":"venue"
},
  "geometry": {"coordinates":[-97.674413,30.523178],"type":"Point"}
}