{
  "type": "Feature",
  "properties": {
    "iso:country":"US",
    "sg:address":"32047 S Wiggins St",
    "sg:city":"Magnolia",
    "sg:classifiers":[
        {
            "category":"Social Services",
            "subcategory":"Child Care",
            "type":"Services"
        }
    ],
    "sg:phone":"+1 281 356 6194",
    "sg:postcode":"77355",
    "sg:province":"TX",
    "sg:tags":[
        "nursery",
        "day"
    ],
    "wof:name":"Kidz 'R' First Day Care",
    "wof:placetype":"venue"
},
  "geometry": {"coordinates":[-95.65606699999999,30.127945],"type":"Point"}
}