{
  "type": "Feature",
  "properties": {
    "iso:country":"US",
    "sg:address":"3905 Greystone Dr",
    "sg:city":"Austin",
    "sg:classifiers":[
        {
            "category":"Professional",
            "type":"Services"
        }
    ],
    "sg:phone":"+1 512 794 0388",
    "sg:postcode":"78731",
    "sg:province":"TX",
    "wof:name":"Mike S Meyer",
    "wof:placetype":"venue"
},
  "geometry": {"coordinates":[-97.761736,30.363103],"type":"Point"}
}