{
  "type": "Feature",
  "properties": {
    "iso:country":"US",
    "sg:address":"1019 Gaye Ln",
    "sg:city":"Arlington",
    "sg:classifiers":[
        {
            "category":"Arts & Performance",
            "subcategory":"Theater",
            "type":"Entertainment"
        }
    ],
    "sg:phone":"+1 817 226 7529",
    "sg:postcode":"76012",
    "sg:province":"TX",
    "sg:tags":[
        "group"
    ],
    "wof:name":"Adventure Caribbean Music",
    "wof:placetype":"venue"
},
  "geometry": {"coordinates":[-97.124624,32.749794],"type":"Point"}
}