{
  "type": "Feature",
  "properties": {
    "iso:country":"US",
    "sg:address":"400 S Main St",
    "sg:city":"Borger",
    "sg:classifiers":[
        {
            "category":"Health Services",
            "subcategory":"Health Practitioner",
            "type":"Services"
        }
    ],
    "sg:phone":"+1 806 273 5299",
    "sg:postcode":"79007",
    "sg:province":"TX",
    "wof:name":"Charlene Rmt Green",
    "wof:placetype":"venue"
},
  "geometry": {"coordinates":[-101.389841,35.663],"type":"Point"}
}