{
  "type": "Feature",
  "properties": {
    "iso:country":"US",
    "sg:address":"2410 E Riverside Drive",
    "sg:city":"Austin",
    "sg:classifiers":[
        {
            "category":"Restaurant",
            "type":"Food & Drink"
        }
    ],
    "sg:phone":"+1 512 851 9464",
    "sg:postcode":"78741",
    "sg:province":"TX",
    "wof:name":"Wingstop",
    "wof:placetype":"venue"
},
  "geometry": {"coordinates":[-97.72487700000001,30.236549],"type":"Point"}
}