{
  "type": "Feature",
  "properties": {
    "iso:country":"US",
    "sg:address":"1750 W Southlake Blvd",
    "sg:city":"Southlake",
    "sg:classifiers":[
        {
            "category":"Building & Trades",
            "subcategory":"Plumbing",
            "type":"Services"
        }
    ],
    "sg:phone":"+1 817 481 7200",
    "sg:postcode":"76092",
    "sg:province":"TX",
    "sg:tags":[
        "contractor"
    ],
    "wof:name":"KIDD Plumbing",
    "wof:placetype":"venue"
},
  "geometry": {"coordinates":[-97.177696,32.941463],"type":"Point"}
}