{
  "type": "Feature",
  "properties": {
    "iso:country":"US",
    "sg:address":"18928 Fortson Ave",
    "sg:city":"Dallas",
    "sg:classifiers":[
        {
            "category":"Arts & Performance",
            "subcategory":"Dance",
            "type":"Entertainment"
        }
    ],
    "sg:phone":"+1 214 228 3008",
    "sg:postcode":"75252",
    "sg:province":"TX",
    "sg:tags":[
        "instruction",
        "dancing"
    ],
    "wof:name":"Dancing Bears Productions",
    "wof:placetype":"venue"
},
  "geometry": {"coordinates":[-96.789372,33.005735],"type":"Point"}
}