{
  "type": "Feature",
  "properties": {
    "iso:country":"US",
    "sg:address":"710 E Broadway St",
    "sg:city":"Lubbock",
    "sg:classifiers":[
        {
            "category":"Restaurant",
            "type":"Food & Drink"
        }
    ],
    "sg:phone":"+1 806 741 1510",
    "sg:postcode":"79403",
    "sg:province":"TX",
    "wof:name":"Burger Boy",
    "wof:placetype":"venue"
},
  "geometry": {"coordinates":[-101.830895,33.58451],"type":"Point"}
}