{
  "type": "Feature",
  "properties": {
    "iso:country":"US",
    "sg:address":"146 Nichols Ln",
    "sg:city":"Bastrop",
    "sg:classifiers":[
        {
            "category":"Wholesale",
            "subcategory":"Apparel",
            "type":"Manufacturing & Wholesale Goods"
        }
    ],
    "sg:phone":"+1 512 581 0440",
    "sg:postcode":"78602",
    "sg:province":"TX",
    "sg:tags":[
        "clothing"
    ],
    "wof:name":"By Claudia",
    "wof:placetype":"venue"
},
  "geometry": {"coordinates":[-97.423126,30.129031],"type":"Point"}
}