{
  "type": "Feature",
  "properties": {
    "iso:country":"US",
    "sg:address":"23910 US Hwy 59",
    "sg:city":"Kingwood",
    "sg:classifiers":[
        {
            "category":"Education",
            "subcategory":"School",
            "type":"Public Place"
        }
    ],
    "sg:phone":"+1 281 358 4223",
    "sg:postcode":"77339",
    "sg:province":"TX",
    "sg:tags":[
        "academic",
        "special"
    ],
    "wof:name":"ECI Keep Pace",
    "wof:placetype":"venue"
},
  "geometry": {"coordinates":[-95.246709,30.067812],"type":"Point"}
}