{
  "type": "Feature",
  "properties": {
    "iso:country":"US",
    "sg:address":"182 Paloma Dr",
    "sg:city":"Canyon Lake",
    "sg:classifiers":[
        {
            "category":"Professional",
            "subcategory":"Business Services",
            "type":"Services"
        }
    ],
    "sg:phone":"+1 830 964 3437",
    "sg:postcode":"78133",
    "sg:province":"TX",
    "sg:tags":[
        "embroidery"
    ],
    "wof:name":"Fun To See T Shirts",
    "wof:placetype":"venue"
},
  "geometry": {"coordinates":[-98.115121,29.853095],"type":"Point"}
}