{
  "type": "Feature",
  "properties": {
    "iso:country":"US",
    "sg:address":"7035 S Central Expy",
    "sg:city":"Dallas",
    "sg:classifiers":[
        {
            "category":"Autos & Motor Vehicles",
            "subcategory":"Automobile Sales",
            "type":"Retail Goods"
        }
    ],
    "sg:phone":"+1 214 371 6223",
    "sg:postcode":"75216",
    "sg:province":"TX",
    "sg:tags":[
        "used",
        "truck"
    ],
    "wof:name":"Nicks B & G Truck Sales",
    "wof:placetype":"venue"
},
  "geometry": {"coordinates":[-96.75852399999999,32.723861],"type":"Point"}
}