{
  "type": "Feature",
  "properties": {
    "iso:country":"US",
    "sg:address":"21032 Dawn Dr",
    "sg:city":"Leander",
    "sg:classifiers":[
        {
            "category":"Building & Trades",
            "subcategory":"Landscaping Services",
            "type":"Services"
        }
    ],
    "sg:phone":"+1 512 267 1617",
    "sg:postcode":"78645",
    "sg:province":"TX",
    "wof:name":"Michael Epps Ldscp Dsign Const",
    "wof:placetype":"venue"
},
  "geometry": {"coordinates":[-97.99221900000001,30.458891],"type":"Point"}
}