{
  "type": "Feature",
  "properties": {
    "iso:country":"US",
    "sg:address":"112 W Church St",
    "sg:city":"Livingston",
    "sg:classifiers":[
        {
            "category":"Shopping",
            "subcategory":"Clothing, Apparel, & Fashions",
            "type":"Retail Goods"
        }
    ],
    "sg:phone":"+1 936 327 9120",
    "sg:postcode":"77351",
    "sg:province":"TX",
    "sg:tags":[
        "shop",
        "bridal",
        "business"
    ],
    "wof:name":"Fina's Creations",
    "wof:placetype":"venue"
},
  "geometry": {"coordinates":[-94.933713,30.711085],"type":"Point"}
}