{
  "type": "Feature",
  "properties": {
    "iso:country":"US",
    "sg:address":"1317 Mesquite Rd",
    "sg:city":"Cedar Park",
    "sg:classifiers":[
        {
            "category":"Professional",
            "subcategory":"Business Services",
            "type":"Services"
        }
    ],
    "sg:phone":"+1 512 401 8140",
    "sg:postcode":"78613",
    "sg:province":"TX",
    "wof:name":"Preyah Group",
    "wof:placetype":"venue"
},
  "geometry": {"coordinates":[-97.828802,30.470173],"type":"Point"}
}