{
  "type": "Feature",
  "properties": {
    "iso:country":"US",
    "sg:address":"9015 Kingswood Pl",
    "sg:city":"Waco",
    "sg:classifiers":[
        {
            "category":"Professional",
            "subcategory":"Management & Consulting",
            "type":"Services"
        }
    ],
    "sg:phone":"+1 254 741 6807",
    "sg:postcode":"76712",
    "sg:province":"TX",
    "sg:tags":[
        "applied",
        "research"
    ],
    "wof:name":"Paul Llich",
    "wof:placetype":"venue"
},
  "geometry": {"coordinates":[-97.23448500000001,31.51262],"type":"Point"}
}