{
  "type": "Feature",
  "properties": {
    "iso:country":"US",
    "sg:address":"4650 FM 1960 W",
    "sg:city":"Houston",
    "sg:classifiers":[
        {
            "category":"Manufacturing",
            "subcategory":"Signs",
            "type":"Manufacturing & Wholesale Goods"
        }
    ],
    "sg:phone":"+1 281 440 7446",
    "sg:postcode":"77069",
    "sg:province":"TX",
    "sg:tags":[
        "specialty",
        "mfg"
    ],
    "wof:name":"Fastsigns",
    "wof:placetype":"venue"
},
  "geometry": {"coordinates":[-95.500693,29.986496],"type":"Point"}
}