{
  "type": "Feature",
  "properties": {
    "iso:country":"US",
    "sg:address":"4000 North Dr",
    "sg:city":"Taylor",
    "sg:classifiers":[
        {
            "category":"Health Services",
            "subcategory":"Clinic",
            "type":"Services"
        }
    ],
    "sg:phone":"+1 512 365 9727",
    "sg:postcode":"76574",
    "sg:province":"TX",
    "sg:tags":[
        "home",
        "care"
    ],
    "wof:name":"Taylor Cmnty Residencial Care",
    "wof:placetype":"venue"
},
  "geometry": {"coordinates":[-97.434425,30.599674],"type":"Point"}
}