{
  "type": "Feature",
  "properties": {
    "iso:country":"US",
    "sg:address":"13802 Research Blvd.",
    "sg:city":"Austin",
    "sg:classifiers":[
        {
            "category":"Sports & Exercise",
            "subcategory":"Gym",
            "type":"Entertainment"
        }
    ],
    "sg:phone":"+1 512 249 6724",
    "sg:postcode":"78750",
    "sg:province":"TX",
    "sg:tags":[
        "trainer"
    ],
    "sg:website":"www.24hourfitness.com",
    "wof:name":"24 Hour Fitness",
    "wof:placetype":"venue"
},
  "geometry": {"coordinates":[-97.795812,30.463245],"type":"Point"}
}