{
  "type": "Feature",
  "properties": {
    "iso:country":"US",
    "sg:address":"1117 Palestine St",
    "sg:city":"Jacksonville",
    "sg:classifiers":[
        {
            "category":"Building & Trades",
            "subcategory":"Electrical",
            "type":"Services"
        }
    ],
    "sg:phone":"+1 903 586 5501",
    "sg:postcode":"75766",
    "sg:province":"TX",
    "sg:tags":[
        "electrical",
        "contractor"
    ],
    "wof:name":"Ross Glynda Photography",
    "wof:placetype":"venue"
},
  "geometry": {"coordinates":[-95.253435,31.954385],"type":"Point"}
}