{
  "type": "Feature",
  "properties": {
    "iso:country":"US",
    "sg:address":"3000 Custer Rd",
    "sg:city":"Plano",
    "sg:classifiers":[
        {
            "category":"Shopping",
            "subcategory":"Clothing, Apparel, & Fashions",
            "type":"Retail Goods"
        }
    ],
    "sg:phone":"+1 972 985 8646",
    "sg:postcode":"75075",
    "sg:province":"TX",
    "sg:tags":[
        "costume"
    ],
    "wof:name":"K C & Co Dancewear",
    "wof:placetype":"venue"
},
  "geometry": {"coordinates":[-96.733265,33.03779],"type":"Point"}
}