{
  "type": "Feature",
  "properties": {
    "iso:country":"US",
    "sg:address":"4615 North Fwy",
    "sg:city":"Houston",
    "sg:classifiers":[
        {
            "category":"Insurance",
            "subcategory":"Health Insurance",
            "type":"Services"
        }
    ],
    "sg:phone":"+1 713 694 6966",
    "sg:postcode":"77022",
    "sg:province":"TX",
    "sg:tags":[
        "market"
    ],
    "wof:name":"Royal Prestige",
    "wof:placetype":"venue"
},
  "geometry": {"coordinates":[-95.38469600000001,29.83285],"type":"Point"}
}