{
  "type": "Feature",
  "properties": {
    "iso:country":"US",
    "sg:address":"8818 Tyler Dr",
    "sg:city":"Lantana",
    "sg:classifiers":[
        {
            "category":"Restaurant",
            "type":"Food & Drink"
        }
    ],
    "sg:phone":"+1 940 725 3195",
    "sg:postcode":"76226",
    "sg:province":"TX",
    "wof:name":"Dough, Rae & Me",
    "wof:placetype":"venue"
},
  "geometry": {"coordinates":[-97.128776,33.099016],"type":"Point"}
}