{
  "type": "Feature",
  "properties": {
    "iso:country":"US",
    "sg:address":"2318 Huber Ave",
    "sg:city":"Borger",
    "sg:classifiers":[
        {
            "category":"Retail",
            "subcategory":"Auto Repair",
            "type":"Services"
        }
    ],
    "sg:phone":"+1 806 273 3082",
    "sg:postcode":"79007",
    "sg:province":"TX",
    "sg:tags":[
        "repairing",
        "automobile"
    ],
    "wof:name":"Specific Auto",
    "wof:placetype":"venue"
},
  "geometry": {"coordinates":[-101.403181,35.641241],"type":"Point"}
}