{
  "type": "Feature",
  "properties": {
    "iso:country":"US",
    "sg:address":"10302 Bent Tree Dr",
    "sg:city":"Rowlett",
    "sg:classifiers":[
        {
            "category":"Professional",
            "subcategory":"Business Services",
            "type":"Services"
        }
    ],
    "sg:phone":"+1 972 412 5529",
    "sg:postcode":"75089",
    "sg:province":"TX",
    "wof:name":"Wilkerson Group",
    "wof:placetype":"venue"
},
  "geometry": {"coordinates":[-96.52670999999999,32.94811],"type":"Point"}
}