{
  "type": "Feature",
  "properties": {
    "iso:country":"US",
    "sg:address":"2018 Meadow Dr",
    "sg:city":"Crowley",
    "sg:classifiers":[
        {
            "category":"Professional",
            "subcategory":"Business Services",
            "type":"Services"
        }
    ],
    "sg:phone":"+1 817 297 3320",
    "sg:postcode":"76036",
    "sg:province":"TX",
    "wof:name":"Stephen A Coffer",
    "wof:placetype":"venue"
},
  "geometry": {"coordinates":[-97.39859199999999,32.536371],"type":"Point"}
}