{
  "type": "Feature",
  "properties": {
    "iso:country":"US",
    "sg:address":"1312 Commercial Ave",
    "sg:city":"Anson",
    "sg:classifiers":[
        {
            "category":"Real Estate",
            "subcategory":"Real Estate Services",
            "type":"Services"
        }
    ],
    "sg:phone":"+1 325 823 3236",
    "sg:postcode":"79501",
    "sg:province":"TX",
    "wof:name":"Fisher-Jones Title Co",
    "wof:placetype":"venue"
},
  "geometry": {"coordinates":[-99.89687600000001,32.754893],"type":"Point"}
}