{
  "type": "Feature",
  "properties": {
    "iso:country":"US",
    "sg:address":"2105 Cross Creek Ct",
    "sg:city":"Arlington",
    "sg:classifiers":[
        {
            "category":"Banks & Credit Unions",
            "subcategory":"Financial Services",
            "type":"Services"
        }
    ],
    "sg:phone":"+1 817 467 6219",
    "sg:postcode":"76017",
    "sg:province":"TX",
    "sg:tags":[
        "investor"
    ],
    "wof:name":"Guion Investments Ltd",
    "wof:placetype":"venue"
},
  "geometry": {"coordinates":[-97.14309299999999,32.667818],"type":"Point"}
}