{
  "type": "Feature",
  "properties": {
    "iso:country":"US",
    "sg:address":"902 7th St",
    "sg:city":"Rosenberg",
    "sg:classifiers":[
        {
            "category":"Home & Garden",
            "subcategory":"Household Appliances",
            "type":"Retail Goods"
        }
    ],
    "sg:phone":"+1 281 342 2394",
    "sg:postcode":"77471",
    "sg:province":"TX",
    "sg:tags":[
        "repair",
        "electrical"
    ],
    "wof:name":"Fort Bend Vac & Sew Mch Repr",
    "wof:placetype":"venue"
},
  "geometry": {"coordinates":[-95.802499,29.559401],"type":"Point"}
}