{
  "type": "Feature",
  "properties": {
    "iso:country":"US",
    "sg:address":"120 Muelhouse St",
    "sg:city":"Belton",
    "sg:classifiers":[
        {
            "category":"Utilities",
            "subcategory":"Water",
            "type":"Services"
        },
        {
            "category":"Retail",
            "subcategory":"Laundry & Dry Cleaning",
            "type":"Services"
        }
    ],
    "sg:phone":"+1 254 933 8989",
    "sg:postcode":"76513",
    "sg:province":"TX",
    "sg:tags":[
        "cleaner",
        "carpet",
        "damage",
        "emergency",
        "rug"
    ],
    "sg:website":"http://www.bellcountyflooring.com",
    "wof:name":"Bell County Carpet Cleaners",
    "wof:placetype":"venue"
},
  "geometry": {"coordinates":[-97.457212,31.055451],"type":"Point"}
}