{
  "type": "Feature",
  "properties": {
    "iso:country":"US",
    "sg:address":"835 Kress St",
    "sg:city":"Houston",
    "sg:classifiers":[
        {
            "category":"Autos & Motor Vehicles",
            "subcategory":"Automobile Sales",
            "type":"Retail Goods"
        }
    ],
    "sg:phone":"+1 713 676 2123",
    "sg:postcode":"77020",
    "sg:province":"TX",
    "sg:tags":[
        "car",
        "used"
    ],
    "sg:website":"www.joesautosales.com",
    "wof:name":"Joe's Auto Sales",
    "wof:placetype":"venue"
},
  "geometry": {"coordinates":[-95.30729700000001,29.773399],"type":"Point"}
}