{
  "type": "Feature",
  "properties": {
    "iso:country":"US",
    "sg:address":"701 Brazos St",
    "sg:city":"Austin",
    "sg:phone":"+1 512 320 9060",
    "sg:postcode":"78701",
    "sg:province":"TX",
    "sg:tags":[
        "product",
        "petroleum"
    ],
    "wof:name":"Engineers Oil & Gas Group",
    "wof:placetype":"venue"
},
  "geometry": {"coordinates":[-97.74078,30.269531],"type":"Point"}
}