{
  "type": "Feature",
  "properties": {
    "iso:country":"US",
    "sg:address":"17803 Frieda Ln",
    "sg:city":"Spring",
    "sg:classifiers":[
        {
            "category":"Building & Trades",
            "subcategory":"Landscaping Services",
            "type":"Services"
        }
    ],
    "sg:phone":"+1 281 257 8601",
    "sg:postcode":"77379",
    "sg:province":"TX",
    "wof:name":"Lawn O Rama",
    "wof:placetype":"venue"
},
  "geometry": {"coordinates":[-95.53914399999999,30.028654],"type":"Point"}
}