{
  "type": "Feature",
  "properties": {
    "iso:country":"US",
    "sg:address":"219 Sandalwood Ln",
    "sg:city":"Levelland",
    "sg:classifiers":[
        {
            "category":"Building & Trades",
            "subcategory":"Plumbing",
            "type":"Services"
        }
    ],
    "sg:phone":"+1 806 894 4617",
    "sg:postcode":"79336",
    "sg:province":"TX",
    "sg:tags":[
        "contractor"
    ],
    "wof:name":"Coastal Climatek Heating",
    "wof:placetype":"venue"
},
  "geometry": {"coordinates":[-102.374606,33.565373],"type":"Point"}
}