{
  "type": "Feature",
  "properties": {
    "iso:country":"US",
    "sg:address":"13005 Cullen Blvd",
    "sg:city":"Houston",
    "sg:classifiers":[
        {
            "category":"Real Estate",
            "subcategory":"Real Estate Agent",
            "type":"Services"
        }
    ],
    "sg:phone":"+1 713 738 3443",
    "sg:postcode":"77047",
    "sg:province":"TX",
    "wof:name":"Evelyn Woods Real Estate Svc",
    "wof:placetype":"venue"
},
  "geometry": {"coordinates":[-95.35534800000001,29.620752],"type":"Point"}
}