{
  "type": "Feature",
  "properties": {
    "iso:country":"US",
    "sg:address":"7300 Brompton St",
    "sg:city":"Houston",
    "sg:classifiers":[
        {
            "category":"Real Estate",
            "subcategory":"Real Estate Agent",
            "type":"Services"
        }
    ],
    "sg:phone":"+1 713 443 6872",
    "sg:postcode":"77025",
    "sg:province":"TX",
    "sg:tags":[
        "inspection"
    ],
    "wof:name":"Entek Inspections",
    "wof:placetype":"venue"
},
  "geometry": {"coordinates":[-95.422988,29.70167],"type":"Point"}
}