{
  "type": "Feature",
  "properties": {
    "iso:country":"US",
    "sg:address":"701 Winship Rd",
    "sg:city":"Pleasanton",
    "sg:classifiers":[
        {
            "category":"Professional",
            "subcategory":"Business Services",
            "type":"Services"
        }
    ],
    "sg:phone":"+1 830 569 4424",
    "sg:postcode":"78064",
    "sg:province":"TX",
    "sg:tags":[
        "or",
        "protection",
        "fire",
        "than",
        "forestry",
        "other",
        "public"
    ],
    "wof:name":"Atascosa Fire Protection",
    "wof:placetype":"venue"
},
  "geometry": {"coordinates":[-98.501436,28.95308],"type":"Point"}
}