{
  "type": "Feature",
  "properties": {
    "iso:country":"US",
    "sg:address":"1719 Basse Rd",
    "sg:city":"San Antonio",
    "sg:classifiers":[
        {
            "category":"Building & Trades",
            "subcategory":"Landscaping Services",
            "type":"Services"
        }
    ],
    "sg:phone":"+1 210 308 7119",
    "sg:postcode":"78213",
    "sg:province":"TX",
    "wof:name":"Express Lawn Service",
    "wof:placetype":"venue"
},
  "geometry": {"coordinates":[-98.512676,29.48878],"type":"Point"}
}