{
  "type": "Feature",
  "properties": {
    "iso:country":"US",
    "sg:address":"17310 Highway 3",
    "sg:city":"Webster",
    "sg:classifiers":[
        {
            "category":"Health Services",
            "subcategory":"Health Practitioner",
            "type":"Services"
        }
    ],
    "sg:phone":"+1 281 332 4452",
    "sg:postcode":"77598",
    "sg:province":"TX",
    "sg:tags":[
        "acupuncture",
        "medicine",
        "alternative"
    ],
    "wof:name":"Acupuncture Pain & Smoking",
    "wof:placetype":"venue"
},
  "geometry": {"coordinates":[-95.122238,29.542127],"type":"Point"}
}