{
  "type": "Feature",
  "properties": {
    "iso:country":"US",
    "sg:address":"459 Eagle Canyon Dr",
    "sg:city":"China Spring",
    "sg:classifiers":[
        {
            "category":"Shopping",
            "subcategory":"Used Merchandise",
            "type":"Retail Goods"
        }
    ],
    "sg:phone":"+1 254 836 4070",
    "sg:postcode":"76633",
    "sg:province":"TX",
    "wof:name":"June Ward Rueter",
    "wof:placetype":"venue"
},
  "geometry": {"coordinates":[-97.2679,31.688551],"type":"Point"}
}