{
  "type": "Feature",
  "properties": {
    "iso:country":"US",
    "sg:address":"3434 FM 2673",
    "sg:city":"Canyon Lake",
    "sg:classifiers":[
        {
            "category":"Real Estate",
            "subcategory":"Real Estate Agent",
            "type":"Services"
        }
    ],
    "sg:phone":"+1 830 964 4000",
    "sg:postcode":"78133",
    "sg:province":"TX",
    "wof:name":"Texas Real Estate",
    "wof:placetype":"venue"
},
  "geometry": {"coordinates":[-98.20303199999999,29.845115],"type":"Point"}
}