{
  "type": "Feature",
  "properties": {
    "iso:country":"US",
    "sg:address":"21018 State Highway 71 W",
    "sg:city":"Spicewood",
    "sg:classifiers":[
        {
            "category":"Professional",
            "subcategory":"Detective & Security Services",
            "type":"Services"
        }
    ],
    "sg:phone":"+1 512 263 7780",
    "sg:postcode":"78669",
    "sg:province":"TX",
    "sg:tags":[
        "information",
        "bureau"
    ],
    "wof:name":"Outback Services Inc.",
    "wof:placetype":"venue"
},
  "geometry": {"coordinates":[-98.062473,30.350526],"type":"Point"}
}