{
  "type": "Feature",
  "properties": {
    "iso:country":"US",
    "sg:address":"614 N Main St",
    "sg:city":"Fort Stockton",
    "sg:classifiers":[
        {
            "category":"Farming",
            "subcategory":"Livestock Farm",
            "type":"Manufacturing & Wholesale Goods"
        }
    ],
    "sg:phone":"+1 432 336 8062",
    "sg:postcode":"79735",
    "sg:province":"TX",
    "sg:tags":[
        "ranch"
    ],
    "wof:name":"Puckett Ranches",
    "wof:placetype":"venue"
},
  "geometry": {"coordinates":[-102.879069,30.890847],"type":"Point"}
}