{
  "type": "Feature",
  "properties": {
    "iso:country":"US",
    "sg:address":"1206 W Wm J Bryan Pkwy",
    "sg:city":"Bryan",
    "sg:classifiers":[
        {
            "category":"Wholesale",
            "subcategory":"Electrical",
            "type":"Manufacturing & Wholesale Goods"
        }
    ],
    "sg:phone":"+1 979 779 8485",
    "sg:postcode":"77803",
    "sg:province":"TX",
    "sg:tags":[
        "equipment"
    ],
    "wof:name":"Motion Industries Inc",
    "wof:placetype":"venue"
},
  "geometry": {"coordinates":[-96.38533099999999,30.676017],"type":"Point"}
}