{
  "type": "Feature",
  "properties": {
    "iso:country":"US",
    "sg:address":"710 W University Ave",
    "sg:city":"Georgetown",
    "sg:classifiers":[
        {
            "category":"Retail",
            "subcategory":"Auto Repair",
            "type":"Services"
        }
    ],
    "sg:phone":"+1 512 863 0868",
    "sg:postcode":"78626",
    "sg:province":"TX",
    "sg:tags":[
        "body"
    ],
    "wof:name":"Bills Body Shop Inc",
    "wof:placetype":"venue"
},
  "geometry": {"coordinates":[-97.682401,30.633116],"type":"Point"}
}