{
  "type": "Feature",
  "properties": {
    "iso:country":"US",
    "sg:address":"8 Sierra Way St",
    "sg:city":"Georgetown",
    "sg:classifiers":[
        {
            "category":"Home & Garden",
            "subcategory":"Home Furnishings",
            "type":"Retail Goods"
        }
    ],
    "sg:phone":"+1 512 930 5850",
    "sg:postcode":"78626",
    "sg:province":"TX",
    "sg:tags":[
        "grill",
        "equipment",
        "barbecue",
        "fireplace",
        "supply"
    ],
    "sg:website":"http://www.georgetownfire-patio.com/",
    "wof:name":"Georgetown Fireplace & Patio",
    "wof:placetype":"venue"
},
  "geometry": {"coordinates":[-97.687523,30.596622],"type":"Point"}
}