{
  "type": "Feature",
  "properties": {
    "iso:country":"US",
    "sg:address":"2515 Piney Woods Dr",
    "sg:city":"Pearland",
    "sg:classifiers":[
        {
            "category":"Real Estate",
            "subcategory":"Real Estate Operator",
            "type":"Services"
        }
    ],
    "sg:phone":"+1 281 648 7235",
    "sg:postcode":"77581",
    "sg:province":"TX",
    "sg:tags":[
        "building",
        "apartment"
    ],
    "wof:name":"Internet Corperate Housing",
    "wof:placetype":"venue"
},
  "geometry": {"coordinates":[-95.225354,29.549779],"type":"Point"}
}