{
  "type": "Feature",
  "properties": {
    "iso:country":"US",
    "sg:address":"5661 Hillcroft St",
    "sg:city":"Houston",
    "sg:classifiers":[
        {
            "category":"Shopping",
            "subcategory":"Clothing, Apparel, & Fashions",
            "type":"Retail Goods"
        }
    ],
    "sg:phone":"+1 713 783 1482",
    "sg:postcode":"77036",
    "sg:province":"TX",
    "wof:name":"Ramesh Lulla",
    "wof:placetype":"venue"
},
  "geometry": {"coordinates":[-95.500969,29.722353],"type":"Point"}
}