{
  "type": "Feature",
  "properties": {
    "iso:country":"US",
    "sg:address":"2225 E Main St",
    "sg:city":"Grand Prairie",
    "sg:classifiers":[
        {
            "category":"Shopping",
            "type":"Retail Goods"
        }
    ],
    "sg:phone":"+1 972 262 2658",
    "sg:postcode":"75050",
    "sg:province":"TX",
    "sg:tags":[
        "trophy",
        "medal",
        "award"
    ],
    "wof:name":"R & M Trophies",
    "wof:placetype":"venue"
},
  "geometry": {"coordinates":[-96.97270899999999,32.749367],"type":"Point"}
}