{
  "type": "Feature",
  "properties": {
    "iso:country":"US",
    "sg:address":"155 McCutcheon Ln",
    "sg:city":"El Paso",
    "sg:classifiers":[
        {
            "category":"Restaurant",
            "type":"Food & Drink"
        }
    ],
    "sg:phone":"+1 915 833 5296",
    "sg:postcode":"79932",
    "sg:province":"TX",
    "sg:tags":[
        "eating"
    ],
    "wof:name":"Go Tout Inc",
    "wof:placetype":"venue"
},
  "geometry": {"coordinates":[-106.58506300000001,31.858852],"type":"Point"}
}