{
  "type": "Feature",
  "properties": {
    "iso:country":"US",
    "sg:address":"300 Harmon Rd",
    "sg:city":"Hurst",
    "sg:classifiers":[
        {
            "category":"Organizations",
            "subcategory":"Religious Organization",
            "type":"Services"
        }
    ],
    "sg:phone":"+1 817 282 4835",
    "sg:postcode":"76053",
    "sg:province":"TX",
    "wof:name":"Grace Covenant Assembly God",
    "wof:placetype":"venue"
},
  "geometry": {"coordinates":[-97.17284100000001,32.816365],"type":"Point"}
}