{
  "type": "Feature",
  "properties": {
    "iso:country":"US",
    "sg:address":"Boulder Dr & Gibbs Williams Rd",
    "sg:city":"Dallas",
    "sg:classifiers":[
        {
            "category":"Education",
            "subcategory":"School",
            "type":"Public Place"
        }
    ],
    "sg:phone":"+1 214 331 7744",
    "sg:postcode":"75201",
    "sg:province":"TX",
    "wof:name":"Dallas Independent School District",
    "wof:placetype":"venue"
},
  "geometry": {"coordinates":[-96.87430000000001,32.698231],"type":"Point"}
}