{
  "type": "Feature",
  "properties": {
    "iso:country":"US",
    "sg:address":"4330 N Grandview Ave # 914",
    "sg:city":"Odessa",
    "sg:classifiers":[
        {
            "category":"Transit Center",
            "subcategory":"Freight",
            "type":"Transportation"
        },
        {
            "category":"Freight",
            "type":"Transportation"
        }
    ],
    "sg:phone":"+1 432 556 7962",
    "sg:postcode":"79762",
    "sg:province":"TX",
    "sg:tags":[
        "trucking-motor",
        "trucking"
    ],
    "wof:name":"Dodd Oil Feild Services",
    "wof:placetype":"venue"
},
  "geometry": {"coordinates":[-102.352996,31.89361],"type":"Point"}
}