{
  "type": "Feature",
  "properties": {
    "iso:country":"US",
    "sg:address":"12222 Merit Drive Suite 120",
    "sg:city":"Dallas",
    "sg:classifiers":[
        {
            "category":"Professional",
            "subcategory":"Business Services",
            "type":"Services"
        }
    ],
    "sg:postcode":"75251",
    "sg:province":"TX",
    "sg:tags":[
        "marketing",
        "socialnetworking",
        "telecommunication",
        "applicationserviceprovider"
    ],
    "sg:website":"http://www.cornerworld.com",
    "wof:name":"CornerWorld",
    "wof:placetype":"venue"
},
  "geometry": {"coordinates":[-96.77287800000001,32.918271],"type":"Point"}
}