{
  "type": "Feature",
  "properties": {
    "iso:country":"US",
    "sg:address":"9700 New Laredo Hwy",
    "sg:city":"San Antonio",
    "sg:classifiers":[
        {
            "category":"Autos & Motor Vehicles",
            "subcategory":"Automobile Sales",
            "type":"Retail Goods"
        }
    ],
    "sg:phone":"+1 210 623 3332",
    "sg:postcode":"78211",
    "sg:province":"TX",
    "sg:tags":[
        "used"
    ],
    "wof:name":"River City Auto Sales",
    "wof:placetype":"venue"
},
  "geometry": {"coordinates":[-98.597545,29.325971],"type":"Point"}
}