{
  "type": "Feature",
  "properties": {
    "iso:country":"US",
    "sg:address":"114 McCarty Ln",
    "sg:city":"La Porte",
    "sg:classifiers":[
        {
            "category":"Wholesale",
            "subcategory":"Machinery & Supplies",
            "type":"Manufacturing & Wholesale Goods"
        },
        {
            "category":"Retail",
            "subcategory":"Repair Shop",
            "type":"Services"
        }
    ],
    "sg:phone":"+1 281 471 1662",
    "sg:postcode":"77571",
    "sg:province":"TX",
    "sg:tags":[
        "machine",
        "tool"
    ],
    "wof:name":"Harold's Machine Tool Repair",
    "wof:placetype":"venue"
},
  "geometry": {"coordinates":[-95.077084,29.688334],"type":"Point"}
}