{
  "type": "Feature",
  "properties": {
    "iso:country":"US",
    "sg:address":"990 Village Square Dr",
    "sg:city":"Tomball",
    "sg:classifiers":[
        {
            "category":"Health Services",
            "subcategory":"Doctor",
            "type":"Services"
        }
    ],
    "sg:phone":"+1 281 351 9806",
    "sg:postcode":"77375",
    "sg:province":"TX",
    "sg:tags":[
        "medical"
    ],
    "wof:name":"Cary Sternick MD",
    "wof:placetype":"venue"
},
  "geometry": {"coordinates":[-95.627348,30.09537],"type":"Point"}
}