{
  "type": "Feature",
  "properties": {
    "iso:country":"US",
    "sg:address":"741 W Ashby Pl",
    "sg:city":"San Antonio",
    "sg:classifiers":[
        {
            "category":"Farming",
            "subcategory":"Farm",
            "type":"Manufacturing & Wholesale Goods"
        }
    ],
    "sg:phone":"+1 210 734 0669",
    "sg:postcode":"78212",
    "sg:province":"TX",
    "sg:tags":[
        "grower",
        "hydroponics"
    ],
    "wof:name":"Casa Verde Garden Supply",
    "wof:placetype":"venue"
},
  "geometry": {"coordinates":[-98.501448,29.449203],"type":"Point"}
}