{
  "type": "Feature",
  "properties": {
    "iso:country":"US",
    "sg:address":"4406 Medical Pkwy",
    "sg:city":"Austin",
    "sg:classifiers":[
        {
            "category":"Personal",
            "subcategory":"Hair Removal",
            "type":"Services"
        },
        {
            "category":"Personal",
            "subcategory":"Skin Care",
            "type":"Services"
        }
    ],
    "sg:phone":"+1 512 698 6769",
    "sg:postcode":"78756",
    "sg:province":"TX",
    "sg:website":"www.blushaustin.com",
    "wof:name":"Blush Skincare by Angie",
    "wof:placetype":"venue"
},
  "geometry": {"coordinates":[-97.74195400000001,30.314171],"type":"Point"}
}