{
  "type": "Feature",
  "properties": {
    "iso:country":"US",
    "sg:address":"10515 SW Fwy Ste E1",
    "sg:city":"Houston",
    "sg:classifiers":[
        {
            "category":"Building & Trades",
            "subcategory":"Plumbing",
            "type":"Services"
        }
    ],
    "sg:phone":"+1 281 240 6868",
    "sg:postcode":"77074",
    "sg:province":"TX",
    "sg:website":"www.arrowplumbing.com",
    "wof:name":"Arrow Plumbing",
    "wof:placetype":"venue"
},
  "geometry": {"coordinates":[-95.55244999999999,29.665256],"type":"Point"}
}