{
  "type": "Feature",
  "properties": {
    "iso:country":"US",
    "sg:address":"1120 E Fannin St",
    "sg:city":"Luling",
    "sg:classifiers":[
        {
            "category":"Utilities",
            "subcategory":"Water",
            "type":"Services"
        }
    ],
    "sg:phone":"+1 830 875 5488",
    "sg:postcode":"78648",
    "sg:province":"TX",
    "sg:tags":[
        "company",
        "sewage"
    ],
    "wof:name":"Luling City Water Dept",
    "wof:placetype":"venue"
},
  "geometry": {"coordinates":[-97.641473,29.681665],"type":"Point"}
}