{
  "type": "Feature",
  "properties": {
    "iso:country":"US",
    "sg:address":"9944 Walnut St",
    "sg:city":"Dallas",
    "sg:classifiers":[
        {
            "category":"Shopping",
            "subcategory":"Shoes",
            "type":"Retail Goods"
        }
    ],
    "sg:phone":"+1 972 690 1347",
    "sg:postcode":"75243",
    "sg:province":"TX",
    "wof:name":"Feet",
    "wof:placetype":"venue"
},
  "geometry": {"coordinates":[-96.71148599999999,32.919326],"type":"Point"}
}