{
  "type": "Feature",
  "properties": {
    "iso:country":"US",
    "sg:address":"301 Singing Quail Trl",
    "sg:city":"Haslet",
    "sg:classifiers":[
        {
            "category":"Shopping",
            "type":"Retail Goods"
        }
    ],
    "sg:phone":"+1 817 903 2541",
    "sg:postcode":"76052",
    "sg:province":"TX",
    "sg:tags":[
        "merchandising"
    ],
    "wof:name":"Zanee Zebra Bowteek",
    "wof:placetype":"venue"
},
  "geometry": {"coordinates":[-97.364054,32.941298],"type":"Point"}
}