{
  "type": "Feature",
  "properties": {
    "iso:country":"US",
    "sg:address":"7820 South Fwy",
    "sg:city":"Fort Worth",
    "sg:classifiers":[
        {
            "category":"Professional",
            "subcategory":"Accounting & Tax Preparation",
            "type":"Services"
        }
    ],
    "sg:phone":"+1 817 975 0303",
    "sg:postcode":"76134",
    "sg:province":"TX",
    "sg:tags":[
        "return",
        "filing"
    ],
    "wof:name":"Quick Account Tax Svc",
    "wof:placetype":"venue"
},
  "geometry": {"coordinates":[-97.322056,32.636846],"type":"Point"}
}