{
  "type": "Feature",
  "properties": {
    "iso:country":"US",
    "sg:address":"410 S Green St",
    "sg:city":"Longview",
    "sg:classifiers":[
        {
            "category":"Education",
            "subcategory":"School",
            "type":"Public Place"
        }
    ],
    "sg:phone":"+1 903 753 1692",
    "sg:postcode":"75601",
    "sg:province":"TX",
    "sg:tags":[
        "a",
        "as",
        "district",
        "operates"
    ],
    "wof:name":"Henry Foster Middle School",
    "wof:placetype":"venue"
},
  "geometry": {"coordinates":[-94.73857,32.489619],"type":"Point"}
}