{
  "type": "Feature",
  "properties": {
    "iso:country":"US",
    "sg:address":"101 N Rufe Snow Dr",
    "sg:city":"Keller",
    "sg:classifiers":[
        {
            "category":"Retail",
            "subcategory":"Photofinishing",
            "type":"Services"
        },
        {
            "category":"Shopping",
            "subcategory":"Pharmacy",
            "type":"Retail Goods"
        }
    ],
    "sg:phone":"+1 817 431 3513",
    "sg:postcode":"76248",
    "sg:province":"TX",
    "sg:tags":[
        "photo",
        "finishing",
        "first",
        "aid",
        "supply"
    ],
    "sg:website":"http://www.cvs.com",
    "wof:name":"CVS/pharmacy",
    "wof:placetype":"venue"
},
  "geometry": {"coordinates":[-97.22920999999999,32.93438],"type":"Point"}
}