{
  "type": "Feature",
  "properties": {
    "iso:country":"US",
    "sg:address":"26 Summithill Pl",
    "sg:city":"Spring",
    "sg:classifiers":[
        {
            "category":"Building & Trades",
            "subcategory":"Landscaping Services",
            "type":"Services"
        }
    ],
    "sg:phone":"+1 281 296 2434",
    "sg:postcode":"77381",
    "sg:province":"TX",
    "sg:tags":[
        "landscape"
    ],
    "wof:name":"Summit Hill Landscape Ser",
    "wof:placetype":"venue"
},
  "geometry": {"coordinates":[-95.520574,30.177724],"type":"Point"}
}