{
  "type": "Feature",
  "properties": {
    "iso:country":"US",
    "sg:address":"5758 N Mesa St",
    "sg:city":"El Paso",
    "sg:classifiers":[
        {
            "category":"Retail",
            "subcategory":"Laundry & Dry Cleaning",
            "type":"Services"
        }
    ],
    "sg:phone":"+1 915 581 6586",
    "sg:postcode":"79912",
    "sg:province":"TX",
    "sg:tags":[
        "garment",
        "alteration",
        "yarn",
        "doe"
    ],
    "wof:name":"Saritas Custom Sewing Inc",
    "wof:placetype":"venue"
},
  "geometry": {"coordinates":[-106.521624,31.82354],"type":"Point"}
}