{
  "type": "Feature",
  "properties": {
    "iso:country":"US",
    "sg:address":"5909 Crystalbrook Dr",
    "sg:city":"Austin",
    "sg:classifiers":[
        {
            "category":"Park",
            "type":"Public Place"
        },
        {
            "category":"Retail",
            "subcategory":"Animal Services",
            "type":"Services"
        }
    ],
    "sg:postcode":"78724",
    "sg:province":"TX",
    "sg:tags":[
        "pet"
    ],
    "sg:website":"www.austinparks.org/apfweb/park....",
    "wof:name":"Northeast District Park, Leash-Free Dog Park",
    "wof:placetype":"venue"
},
  "geometry": {"coordinates":[-97.651867,30.309655],"type":"Point"}
}