{
  "type": "Feature",
  "properties": {
    "iso:country":"US",
    "sg:address":"5107 Emil Ave",
    "sg:city":"Amarillo",
    "sg:classifiers":[
        {
            "category":"Shopping",
            "subcategory":"Hobbies, Toys, & Games",
            "type":"Retail Goods"
        }
    ],
    "sg:phone":"+1 806 352 3767",
    "sg:postcode":"79106",
    "sg:province":"TX",
    "wof:name":"Designer Delights",
    "wof:placetype":"venue"
},
  "geometry": {"coordinates":[-101.894024,35.185914],"type":"Point"}
}