{
  "type": "Feature",
  "properties": {
    "iso:country":"US",
    "sg:address":"17238 Texas Ave",
    "sg:city":"Webster",
    "sg:classifiers":[
        {
            "category":"Shopping",
            "subcategory":"Discount & Variety Stores",
            "type":"Retail Goods"
        }
    ],
    "sg:phone":"+1 281 332 3670",
    "sg:postcode":"77598",
    "sg:province":"TX",
    "sg:tags":[
        "merchandise",
        "general"
    ],
    "wof:name":"Teodora Tello Coronado",
    "wof:placetype":"venue"
},
  "geometry": {"coordinates":[-95.13016,29.539441],"type":"Point"}
}