{
  "type": "Feature",
  "properties": {
    "iso:country":"US",
    "sg:address":"4 Dwain St",
    "sg:city":"Chandler",
    "sg:classifiers":[
        {
            "category":"Building & Trades",
            "subcategory":"Construction",
            "type":"Services"
        }
    ],
    "sg:phone":"+1 903 849 9982",
    "sg:postcode":"75758",
    "sg:province":"TX",
    "sg:tags":[
        "contractor"
    ],
    "wof:name":"Bill Middleton Insulation Equi",
    "wof:placetype":"venue"
},
  "geometry": {"coordinates":[-95.493763,32.223855],"type":"Point"}
}