{
  "type": "Feature",
  "properties": {
    "iso:country":"US",
    "sg:address":"7939 Grandridge Dr",
    "sg:city":"Houston",
    "sg:classifiers":[
        {
            "category":"Freight",
            "type":"Transportation"
        }
    ],
    "sg:phone":"+1 281 459 4432",
    "sg:postcode":"77049",
    "sg:province":"TX",
    "sg:tags":[
        "operator",
        "trucking"
    ],
    "wof:name":"Cesar E Rivera",
    "wof:placetype":"venue"
},
  "geometry": {"coordinates":[-95.18521699999999,29.838153],"type":"Point"}
}