{
  "type": "Feature",
  "properties": {
    "iso:country":"US",
    "sg:address":"5001 Kee Brook Dr",
    "sg:city":"Arlington",
    "sg:classifiers":[
        {
            "category":"Professional",
            "subcategory":"Employment Agencies",
            "type":"Services"
        }
    ],
    "sg:phone":"+1 817 572 2131",
    "sg:postcode":"76017",
    "sg:province":"TX",
    "sg:tags":[
        "help",
        "supply"
    ],
    "wof:name":"Klos & Associates",
    "wof:placetype":"venue"
},
  "geometry": {"coordinates":[-97.185322,32.666126],"type":"Point"}
}