{
  "type": "Feature",
  "properties": {
    "iso:country":"US",
    "sg:address":"4504 Old Yale St",
    "sg:city":"Houston",
    "sg:classifiers":[
        {
            "category":"Organizations",
            "subcategory":"Non-profit Organization",
            "type":"Services"
        }
    ],
    "sg:phone":"+1 713 695 7146",
    "sg:postcode":"77018",
    "sg:province":"TX",
    "sg:tags":[
        "charitable",
        "service/non-profit",
        "community",
        "institution"
    ],
    "wof:name":"Kid Care Food Program",
    "wof:placetype":"venue"
},
  "geometry": {"coordinates":[-95.40270200000001,29.830799],"type":"Point"}
}