{
  "type": "Feature",
  "properties": {
    "iso:country":"US",
    "sg:address":"101 Dawn Dr",
    "sg:city":"Waxahachie",
    "sg:classifiers":[
        {
            "category":"Building & Trades",
            "subcategory":"Construction",
            "type":"Services"
        }
    ],
    "sg:phone":"+1 972 617 8368",
    "sg:postcode":"75165",
    "sg:province":"TX",
    "sg:tags":[
        "house"
    ],
    "wof:name":"Ellis County Fence",
    "wof:placetype":"venue"
},
  "geometry": {"coordinates":[-96.78999399999999,32.479487],"type":"Point"}
}