{
  "type": "Feature",
  "properties": {
    "iso:country":"US",
    "sg:address":"3065 N Josey Ln #62",
    "sg:city":"Carrollton",
    "sg:classifiers":[
        {
            "category":"Shopping",
            "subcategory":"Tobacco",
            "type":"Retail Goods"
        },
        {
            "category":"Food & Beverages",
            "subcategory":"Liquor & Beverages",
            "type":"Retail Goods"
        }
    ],
    "sg:phone":"+1 972 395 0240",
    "sg:postcode":"75007",
    "sg:province":"TX",
    "sg:tags":[
        "shop",
        "beer",
        "spirit",
        "wine"
    ],
    "sg:website":"www.lonestarbeverages.com",
    "wof:name":"Lone Star Beverages",
    "wof:placetype":"venue"
},
  "geometry": {"coordinates":[-96.887518,32.998695],"type":"Point"}
}