{
  "type": "Feature",
  "properties": {
    "iso:country":"US",
    "sg:address":"2003 Windcastle Dr",
    "sg:city":"Mansfield",
    "sg:classifiers":[
        {
            "category":"Communications",
            "subcategory":"Film & Video Production",
            "type":"Services"
        }
    ],
    "sg:phone":"+1 682 518 8683",
    "sg:postcode":"76063",
    "sg:province":"TX",
    "sg:tags":[
        "motion"
    ],
    "wof:name":"Michael Scott Productions",
    "wof:placetype":"venue"
},
  "geometry": {"coordinates":[-97.10954599999999,32.600178],"type":"Point"}
}