{
  "type": "Feature",
  "properties": {
    "iso:country":"US",
    "sg:address":"5072 Creek Ln",
    "sg:city":"College Station",
    "sg:classifiers":[
        {
            "category":"Restaurant",
            "type":"Food & Drink"
        }
    ],
    "sg:phone":"+1 979 690 0514",
    "sg:postcode":"77845",
    "sg:province":"TX",
    "sg:tags":[
        "eating"
    ],
    "wof:name":"Ronnie Akin",
    "wof:placetype":"venue"
},
  "geometry": {"coordinates":[-96.266932,30.477769],"type":"Point"}
}