{
  "type": "Feature",
  "properties": {
    "iso:country":"US",
    "sg:address":"14650 Woodforest Blvd Ste A",
    "sg:city":"Houston",
    "sg:classifiers":[
        {
            "category":"Shopping",
            "subcategory":"Department Store",
            "type":"Retail Goods"
        }
    ],
    "sg:phone":"+1 713 330 8446",
    "sg:postcode":"77015",
    "sg:province":"TX",
    "sg:website":"www.familydollar.com",
    "wof:name":"Family Dollar",
    "wof:placetype":"venue"
},
  "geometry": {"coordinates":[-95.16242800000001,29.790292],"type":"Point"}
}