{
  "type": "Feature",
  "properties": {
    "iso:country":"US",
    "sg:address":"3706 Green Fields Dr",
    "sg:city":"Sugar Land",
    "sg:classifiers":[
        {
            "category":"Health Services",
            "subcategory":"Doctor",
            "type":"Services"
        }
    ],
    "sg:phone":"+1 281 265 0513",
    "sg:postcode":"77479",
    "sg:province":"TX",
    "wof:name":"Armstrong Glen A D D S Inc",
    "wof:placetype":"venue"
},
  "geometry": {"coordinates":[-95.592973,29.57606],"type":"Point"}
}