{
  "type": "Feature",
  "properties": {
    "iso:country":"US",
    "sg:address":"2029 US Hwy 281",
    "sg:city":"Blanco",
    "sg:classifiers":[
        {
            "category":"Retail",
            "subcategory":"Repair Shop",
            "type":"Services"
        }
    ],
    "sg:phone":"+1 830 833 1363",
    "sg:postcode":"78606",
    "sg:province":"TX",
    "wof:name":"Blanco Taxidermy",
    "wof:placetype":"venue"
},
  "geometry": {"coordinates":[-98.41712699999999,30.110129],"type":"Point"}
}