{
  "type": "Feature",
  "properties": {
    "iso:country":"US",
    "sg:address":"119 E 6th St",
    "sg:city":"Rusk",
    "sg:classifiers":[
        {
            "category":"Real Estate",
            "subcategory":"Real Estate Services",
            "type":"Services"
        }
    ],
    "sg:phone":"+1 903 683 5461",
    "sg:postcode":"75785",
    "sg:province":"TX",
    "sg:tags":[
        "company",
        "title"
    ],
    "wof:name":"Southwestern Abstract Co",
    "wof:placetype":"venue"
},
  "geometry": {"coordinates":[-95.149412,31.79601],"type":"Point"}
}