{
  "type": "Feature",
  "properties": {
    "iso:country":"US",
    "sg:address":"2525 Morgan St",
    "sg:city":"Irving",
    "sg:classifiers":[
        {
            "category":"Professional",
            "type":"Services"
        }
    ],
    "sg:phone":"+1 972 255 5900",
    "sg:postcode":"75062",
    "sg:province":"TX",
    "wof:name":"Scyps",
    "wof:placetype":"venue"
},
  "geometry": {"coordinates":[-96.980785,32.846077],"type":"Point"}
}