{
  "type": "Feature",
  "properties": {
    "iso:country":"US",
    "sg:address":"1510 Richey St",
    "sg:city":"Pasadena",
    "sg:classifiers":[
        {
            "category":"Shopping",
            "subcategory":"Clothing, Apparel, & Fashions",
            "type":"Retail Goods"
        },
        {
            "category":"Shopping",
            "subcategory":"Crafts & Fabrics",
            "type":"Retail Goods"
        },
        {
            "category":"Shopping",
            "subcategory":"Party Supplies",
            "type":"Retail Goods"
        },
        {
            "category":"Education",
            "subcategory":"Vocational School",
            "type":"Public Place"
        }
    ],
    "sg:phone":"+1 713 477 8864",
    "sg:postcode":"77502",
    "sg:province":"TX",
    "sg:tags":[
        "cooking",
        "art",
        "costume"
    ],
    "wof:name":"Larry's Art & Craft Supplies",
    "wof:placetype":"venue"
},
  "geometry": {"coordinates":[-95.220299,29.688499],"type":"Point"}
}