{
  "type": "Feature",
  "properties": {
    "iso:country":"US",
    "sg:address":"2119 Oaklawn Dr",
    "sg:city":"La Marque",
    "sg:classifiers":[
        {
            "category":"Wholesale",
            "subcategory":"Non-durable Goods",
            "type":"Manufacturing & Wholesale Goods"
        }
    ],
    "sg:phone":"+1 409 935 2420",
    "sg:postcode":"77568",
    "sg:province":"TX",
    "wof:name":"Jmd Distributing",
    "wof:placetype":"venue"
},
  "geometry": {"coordinates":[-94.973901,29.361383],"type":"Point"}
}