{
  "type": "Feature",
  "properties": {
    "iso:country":"US",
    "sg:address":"100 E Kleberg Ave",
    "sg:city":"Kingsville",
    "sg:classifiers":[
        {
            "category":"Professional",
            "subcategory":"Lawyer & Legal Services",
            "type":"Services"
        }
    ],
    "sg:phone":"+1 361 592 8286",
    "sg:postcode":"78363",
    "sg:province":"TX",
    "wof:name":"David P Luevano Attorney",
    "wof:placetype":"venue"
},
  "geometry": {"coordinates":[-97.86766799999999,27.51665],"type":"Point"}
}