{
  "type": "Feature",
  "properties": {
    "iso:country":"US",
    "sg:address":"400 S Zang Blvd",
    "sg:city":"Dallas",
    "sg:classifiers":[
        {
            "category":"Organizations",
            "subcategory":"Community Association",
            "type":"Services"
        }
    ],
    "sg:phone":"+1 214 948 3722",
    "sg:postcode":"75208",
    "sg:province":"TX",
    "sg:tags":[
        "advocate",
        "conditions",
        "working"
    ],
    "wof:name":"Dallas School ADM Assn",
    "wof:placetype":"venue"
},
  "geometry": {"coordinates":[-96.824637,32.741327],"type":"Point"}
}