{
  "type": "Feature",
  "properties": {
    "iso:country":"US",
    "sg:address":"10719 Gulf Fwy",
    "sg:city":"Houston",
    "sg:classifiers":[
        {
            "category":"Personal",
            "subcategory":"Tattoo Parlor",
            "type":"Services"
        }
    ],
    "sg:phone":"+1 713 944 8282",
    "sg:postcode":"77034",
    "sg:province":"TX",
    "wof:name":"Space City Tattoo 3",
    "wof:placetype":"venue"
},
  "geometry": {"coordinates":[-95.24016399999999,29.638778],"type":"Point"}
}