{
  "type": "Feature",
  "properties": {
    "iso:country":"US",
    "sg:address":"2901 S Padre Island Dr",
    "sg:city":"Corpus Christi",
    "sg:classifiers":[
        {
            "category":"Autos & Motor Vehicles",
            "subcategory":"Auto Supplies",
            "type":"Retail Goods"
        },
        {
            "category":"Wholesale",
            "subcategory":"Auto Parts",
            "type":"Manufacturing & Wholesale Goods"
        }
    ],
    "sg:phone":"+1 361 853 6251",
    "sg:postcode":"78415",
    "sg:province":"TX",
    "sg:tags":[
        "automobile"
    ],
    "wof:name":"Carquest Auto Parts 67",
    "wof:placetype":"venue"
},
  "geometry": {"coordinates":[-97.418279,27.730788],"type":"Point"}
}