{
  "type": "Feature",
  "properties": {
    "iso:country":"US",
    "sg:address":"8407 Wall St",
    "sg:city":"Austin",
    "sg:classifiers":[
        {
            "category":"Government",
            "subcategory":"Office",
            "type":"Public Place"
        }
    ],
    "sg:phone":"+1 512 834 6751",
    "sg:postcode":"78754",
    "sg:province":"TX",
    "sg:website":"www.dshs.state.tx.us",
    "wof:name":"Perfusionists Board-Examiners",
    "wof:placetype":"venue"
},
  "geometry": {"coordinates":[-97.668577,30.344371],"type":"Point"}
}