{
  "type": "Feature",
  "properties": {
    "iso:country":"US",
    "sg:address":"1919 S Shiloh Rd",
    "sg:city":"Garland",
    "sg:classifiers":[
        {
            "category":"Organizations",
            "subcategory":"Religious Organization",
            "type":"Services"
        }
    ],
    "sg:phone":"+1 972 926 9757",
    "sg:postcode":"75041",
    "sg:province":"TX",
    "sg:website":"www.timlee.org",
    "wof:name":"Tim Lee Ministries",
    "wof:placetype":"venue"
},
  "geometry": {"coordinates":[-96.665752,32.895925],"type":"Point"}
}