{
  "type": "Feature",
  "properties": {
    "iso:country":"US",
    "sg:address":"9000 Pagewood Ln",
    "sg:city":"Houston",
    "sg:classifiers":[
        {
            "category":"Retail",
            "subcategory":"Auto Repair",
            "type":"Services"
        }
    ],
    "sg:phone":"+1 713 334 5041",
    "sg:postcode":"77063",
    "sg:province":"TX",
    "wof:name":"Pro Auto Repair",
    "wof:placetype":"venue"
},
  "geometry": {"coordinates":[-95.523003,29.7262],"type":"Point"}
}