{
  "type": "Feature",
  "properties": {
    "iso:country":"US",
    "sg:address":"13311 Purple Sage Rd",
    "sg:city":"Dallas",
    "sg:classifiers":[
        {
            "category":"Health Services",
            "subcategory":"Medical Lab",
            "type":"Services"
        }
    ],
    "sg:phone":"+1 972 233 2050",
    "sg:postcode":"75240",
    "sg:province":"TX",
    "sg:tags":[
        "laboratory"
    ],
    "wof:name":"Richard Ellis",
    "wof:placetype":"venue"
},
  "geometry": {"coordinates":[-96.77810100000001,32.928784],"type":"Point"}
}