{
  "type": "Feature",
  "properties": {
    "iso:country":"US",
    "sg:address":"3309 Dennis St",
    "sg:city":"Houston",
    "sg:classifiers":[
        {
            "category":"Wholesale",
            "subcategory":"Non-durable Goods",
            "type":"Manufacturing & Wholesale Goods"
        }
    ],
    "sg:phone":"+1 713 571 1200",
    "sg:postcode":"77004",
    "sg:province":"TX",
    "wof:name":"Nettra Burks Reliv Distributor",
    "wof:placetype":"venue"
},
  "geometry": {"coordinates":[-95.351859,29.733049],"type":"Point"}
}