{
  "type": "Feature",
  "properties": {
    "iso:country":"US",
    "sg:address":"7333 Dominique Dr",
    "sg:city":"Dallas",
    "sg:classifiers":[
        {
            "category":"Professional",
            "subcategory":"Business Services",
            "type":"Services"
        }
    ],
    "sg:phone":"+1 214 821 5563",
    "sg:postcode":"75214",
    "sg:province":"TX",
    "wof:name":"Catherine Chang Enterprises In",
    "wof:placetype":"venue"
},
  "geometry": {"coordinates":[-96.735484,32.837484],"type":"Point"}
}