{
  "type": "Feature",
  "properties": {
    "iso:country":"US",
    "sg:address":"13626 Reeveston Rd",
    "sg:city":"Houston",
    "sg:classifiers":[
        {
            "category":"Retail",
            "subcategory":"Auto Repair",
            "type":"Services"
        }
    ],
    "sg:phone":"+1 281 219 2313",
    "sg:postcode":"77039",
    "sg:province":"TX",
    "sg:tags":[
        "truck"
    ],
    "wof:name":"Accent Fleet Svc Inc",
    "wof:placetype":"venue"
},
  "geometry": {"coordinates":[-95.367789,29.913682],"type":"Point"}
}