{
  "type": "Feature",
  "properties": {
    "iso:country":"US",
    "sg:address":"8805 Caroline Rd",
    "sg:city":"Corpus Christi",
    "sg:classifiers":[
        {
            "category":"Professional",
            "subcategory":"Lawyer & Legal Services",
            "type":"Services"
        }
    ],
    "sg:phone":"+1 361 241 3245",
    "sg:postcode":"78409",
    "sg:province":"TX",
    "sg:tags":[
        "attorney"
    ],
    "wof:name":"Hector Del Toro",
    "wof:placetype":"venue"
},
  "geometry": {"coordinates":[-97.536101,27.811708],"type":"Point"}
}