{
  "type": "Feature",
  "properties": {
    "iso:country":"US",
    "sg:address":"102 N East St",
    "sg:city":"Uvalde",
    "sg:classifiers":[
        {
            "category":"Insurance",
            "subcategory":"Insurance Agent",
            "type":"Services"
        }
    ],
    "sg:phone":"+1 830 278 6215",
    "sg:postcode":"78801",
    "sg:province":"TX",
    "wof:name":"Thompson Insurance",
    "wof:placetype":"venue"
},
  "geometry": {"coordinates":[-99.785544,29.210537],"type":"Point"}
}