{
  "type": "Feature",
  "properties": {
    "iso:country":"US",
    "sg:address":"2955 Harrison Ave",
    "sg:city":"Beaumont",
    "sg:classifiers":[
        {
            "category":"Health Services",
            "subcategory":"Doctor",
            "type":"Services"
        }
    ],
    "sg:phone":"+1 409 899 5111",
    "sg:postcode":"77702",
    "sg:province":"TX",
    "sg:tags":[
        "medical"
    ],
    "wof:name":"Sultana Munnaver MD Facog",
    "wof:placetype":"venue"
},
  "geometry": {"coordinates":[-94.132257,30.089475],"type":"Point"}
}