{
  "type": "Feature",
  "properties": {
    "iso:country":"US",
    "sg:address":"841 Wood River Rd",
    "sg:city":"Dallas",
    "sg:classifiers":[
        {
            "category":"Professional",
            "type":"Services"
        }
    ],
    "sg:phone":"+1 214 376 3716",
    "sg:postcode":"75232",
    "sg:province":"TX",
    "wof:name":"Glorias Galoria",
    "wof:placetype":"venue"
},
  "geometry": {"coordinates":[-96.838565,32.677389],"type":"Point"}
}