{
  "type": "Feature",
  "properties": {
    "iso:country":"US",
    "sg:address":"3409 Executive Center Dr. Suite 201",
    "sg:city":"Austin",
    "sg:classifiers":[
        {
            "category":"Banks & Credit Unions",
            "subcategory":"Financial Services",
            "type":"Services"
        }
    ],
    "sg:phone":"+1 512 970 6336",
    "sg:postcode":"78731",
    "sg:province":"TX",
    "sg:tags":[
        "broker",
        "mortgage"
    ],
    "sg:website":"www.indusloans.com",
    "wof:name":"Indus Loans",
    "wof:placetype":"venue"
},
  "geometry": {"coordinates":[-97.746994,30.358232],"type":"Point"}
}