{
  "type": "Feature",
  "properties": {
    "iso:country":"US",
    "sg:address":"1515 Ave G",
    "sg:city":"Lubbock",
    "sg:classifiers":[
        {
            "category":"Government",
            "subcategory":"Post Office",
            "type":"Public Place"
        }
    ],
    "sg:phone":"+1 806 762 7823",
    "sg:postcode":"79401",
    "sg:province":"TX",
    "sg:tags":[
        "postal",
        "us"
    ],
    "wof:name":"Address Information Systems",
    "wof:placetype":"venue"
},
  "geometry": {"coordinates":[-101.843115,33.580909],"type":"Point"}
}