{
  "type": "Feature",
  "properties": {
    "iso:country":"US",
    "sg:address":"1765 Old Creek Ct",
    "sg:city":"Brownsville",
    "sg:classifiers":[
        {
            "category":"Professional",
            "subcategory":"Business Services",
            "type":"Services"
        }
    ],
    "sg:phone":"+1 956 544 0601",
    "sg:postcode":"78521",
    "sg:province":"TX",
    "wof:name":"Translation Services",
    "wof:placetype":"venue"
},
  "geometry": {"coordinates":[-97.49196999999999,25.945232],"type":"Point"}
}