{
  "type": "Feature",
  "properties": {
    "iso:country":"US",
    "sg:address":"1500 N Greenville Ave",
    "sg:city":"Richardson",
    "sg:classifiers":[
        {
            "category":"Restaurant",
            "type":"Food & Drink"
        }
    ],
    "sg:phone":"+1 972 889 9702",
    "sg:postcode":"75081",
    "sg:province":"TX",
    "wof:name":"La Cuisine Cafe",
    "wof:placetype":"venue"
},
  "geometry": {"coordinates":[-96.71910099999999,32.9688],"type":"Point"}
}