{
  "type": "Feature",
  "properties": {
    "iso:country":"US",
    "sg:address":"2525 N Jackson Ave",
    "sg:city":"Odessa",
    "sg:classifiers":[
        {
            "category":"Building & Trades",
            "subcategory":"Electrical",
            "type":"Services"
        }
    ],
    "sg:phone":"+1 432 332 1558",
    "sg:postcode":"79761",
    "sg:province":"TX",
    "sg:tags":[
        "electric",
        "contractor"
    ],
    "wof:name":"Brown Electric Co",
    "wof:placetype":"venue"
},
  "geometry": {"coordinates":[-102.37836,31.868327],"type":"Point"}
}