{
  "type": "Feature",
  "properties": {
    "iso:country":"US",
    "sg:address":"217 S Oregon St",
    "sg:city":"El Paso",
    "sg:classifiers":[
        {
            "category":"Shopping",
            "subcategory":"Shoes",
            "type":"Retail Goods"
        }
    ],
    "sg:phone":"+1 915 838 1498",
    "sg:postcode":"79901",
    "sg:province":"TX",
    "sg:tags":[
        "boot"
    ],
    "wof:name":"Juarez Boot Co Inc",
    "wof:placetype":"venue"
},
  "geometry": {"coordinates":[-106.487647,31.756841],"type":"Point"}
}