{
  "type": "Feature",
  "properties": {
    "iso:country":"US",
    "sg:address":"3717 Stone Creek Pkwy",
    "sg:city":"Fort Worth",
    "sg:classifiers":[
        {
            "category":"Banks & Credit Unions",
            "subcategory":"Financial Services",
            "type":"Services"
        }
    ],
    "sg:phone":"+1 817 306 5580",
    "sg:postcode":"76137",
    "sg:province":"TX",
    "sg:tags":[
        "company",
        "holding"
    ],
    "wof:name":"Ql Holdings LLC",
    "wof:placetype":"venue"
},
  "geometry": {"coordinates":[-97.300725,32.858842],"type":"Point"}
}