{
  "type": "Feature",
  "properties": {
    "iso:country":"US",
    "sg:address":"2625 8th Ave",
    "sg:city":"Fort Worth",
    "sg:classifiers":[
        {
            "category":"Professional",
            "subcategory":"Accounting & Tax Preparation",
            "type":"Services"
        }
    ],
    "sg:phone":"+1 817 303 5201",
    "sg:postcode":"76110",
    "sg:province":"TX",
    "sg:tags":[
        "accountant",
        "public",
        "certified"
    ],
    "wof:name":"Kyle E Carrick Cpa PC",
    "wof:placetype":"venue"
},
  "geometry": {"coordinates":[-97.343737,32.711745],"type":"Point"}
}