{
  "type": "Feature",
  "properties": {
    "iso:country":"US",
    "sg:address":"1422 Eldridge Pkwy",
    "sg:city":"Houston",
    "sg:classifiers":[
        {
            "category":"Restaurant",
            "type":"Food & Drink"
        }
    ],
    "sg:menulink":"http://www.allmenus.com/tx/houston/267345-le-mistral/menu/",
    "sg:phone":"+1 832 379 8322",
    "sg:postcode":"77077",
    "sg:province":"TX",
    "sg:tags":[
        "french"
    ],
    "wof:name":"Le Mistral",
    "wof:placetype":"venue"
},
  "geometry": {"coordinates":[-95.62538600000001,29.759657],"type":"Point"}
}