{
  "type": "Feature",
  "properties": {
    "iso:country":"US",
    "sg:address":"6069 Belt Line Rd",
    "sg:city":"Dallas",
    "sg:classifiers":[
        {
            "category":"Professional",
            "subcategory":"Advertising",
            "type":"Services"
        }
    ],
    "sg:phone":"+1 972 661 1696",
    "sg:postcode":"75254",
    "sg:province":"TX",
    "sg:tags":[
        "mail"
    ],
    "wof:name":"Certified Diamond Entrtn",
    "wof:placetype":"venue"
},
  "geometry": {"coordinates":[-96.79905100000001,32.950224],"type":"Point"}
}