{
  "type": "Feature",
  "properties": {
    "iso:country":"US",
    "sg:address":"400 State Hwy 1604",
    "sg:city":"San Antonio",
    "sg:classifiers":[
        {
            "category":"Banks & Credit Unions",
            "subcategory":"Bank",
            "type":"Services"
        }
    ],
    "sg:phone":"+1 210 490 6868",
    "sg:postcode":"78232",
    "sg:province":"TX",
    "wof:name":"Community Home Loan",
    "wof:placetype":"venue"
},
  "geometry": {"coordinates":[-98.48709599999999,29.60932],"type":"Point"}
}