{
  "type": "Feature",
  "properties": {
    "iso:country":"US",
    "sg:address":"338 Bayless Ln",
    "sg:city":"Duncanville",
    "sg:classifiers":[
        {
            "category":"Donuts",
            "subcategory":"None",
            "type":"Food & Drink"
        }
    ],
    "sg:phone":"+1 214 826 9933",
    "sg:postcode":"75116",
    "sg:province":"TX",
    "wof:name":"Donut King",
    "wof:placetype":"venue"
},
  "geometry": {"coordinates":[-96.91269699999999,32.672901],"type":"Point"}
}