{
  "type": "Feature",
  "properties": {
    "iso:country":"US",
    "sg:address":"1507 US Hwy 281",
    "sg:city":"Marble Falls",
    "sg:classifiers":[
        {
            "category":"Wholesale",
            "subcategory":"Farm Supplies",
            "type":"Manufacturing & Wholesale Goods"
        },
        {
            "category":"Shopping",
            "type":"Retail Goods"
        }
    ],
    "sg:phone":"+1 830 798 2642",
    "sg:postcode":"78654",
    "sg:province":"TX",
    "sg:tags":[
        "merchandise"
    ],
    "wof:name":"Tractor Supply 561",
    "wof:placetype":"venue"
},
  "geometry": {"coordinates":[-98.28589599999999,30.525993],"type":"Point"}
}