{
  "type": "Feature",
  "properties": {
    "iso:country":"US",
    "sg:address":"1509 20th Ave N",
    "sg:city":"Texas City",
    "sg:classifiers":[
        {
            "category":"Building & Trades",
            "subcategory":"Plumbing",
            "type":"Services"
        }
    ],
    "sg:phone":"+1 409 948 1181",
    "sg:postcode":"77590",
    "sg:province":"TX",
    "sg:tags":[
        "system",
        "heating",
        "air",
        "conditioning",
        "contractor",
        "condition"
    ],
    "wof:name":"J L Cook & Sons Co",
    "wof:placetype":"venue"
},
  "geometry": {"coordinates":[-94.916693,29.404451],"type":"Point"}
}