{
  "type": "Feature",
  "properties": {
    "iso:country":"US",
    "sg:address":"5101 Bellaire Blvd",
    "sg:city":"Bellaire",
    "sg:classifiers":[
        {
            "category":"Restaurant",
            "type":"Food & Drink"
        }
    ],
    "sg:phone":"+1 713 669 8658",
    "sg:postcode":"77401",
    "sg:province":"TX",
    "sg:tags":[
        "italian"
    ],
    "wof:name":"Auntie Pasto's",
    "wof:placetype":"venue"
},
  "geometry": {"coordinates":[-95.46820099999999,29.7054],"type":"Point"}
}