{
  "type": "Feature",
  "properties": {
    "iso:country":"US",
    "sg:address":"1520 W Irving Blvd",
    "sg:city":"Irving",
    "sg:classifiers":[
        {
            "category":"Freight",
            "type":"Transportation"
        }
    ],
    "sg:phone":"+1 972 254 7318",
    "sg:postcode":"75061",
    "sg:province":"TX",
    "sg:tags":[
        "who",
        "special",
        "general"
    ],
    "wof:name":"Shurgard Storage Centers",
    "wof:placetype":"venue"
},
  "geometry": {"coordinates":[-96.966003,32.820226],"type":"Point"}
}