{
  "type": "Feature",
  "properties": {
    "iso:country":"US",
    "sg:address":"1723 S Center St",
    "sg:city":"Denison",
    "sg:classifiers":[
        {
            "category":"Professional",
            "type":"Services"
        }
    ],
    "sg:phone":"+1 903 463 2204",
    "sg:postcode":"75021",
    "sg:province":"TX",
    "sg:tags":[
        "establishment"
    ],
    "wof:name":"Soccer Denison",
    "wof:placetype":"venue"
},
  "geometry": {"coordinates":[-96.53054899999999,33.736707],"type":"Point"}
}