{
  "type": "Feature",
  "properties": {
    "iso:country":"US",
    "sg:address":"5201 Paris St",
    "sg:city":"Fort Worth",
    "sg:classifiers":[
        {
            "category":"Professional",
            "subcategory":"Business Services",
            "type":"Services"
        }
    ],
    "sg:phone":"+1 817 413 9832",
    "sg:postcode":"76119",
    "sg:province":"TX",
    "wof:name":"SMC Creations",
    "wof:placetype":"venue"
},
  "geometry": {"coordinates":[-97.276582,32.68285],"type":"Point"}
}