{
  "type": "Feature",
  "properties": {
    "iso:country":"US",
    "sg:address":"515 Forester St",
    "sg:city":"Greenville",
    "sg:classifiers":[
        {
            "category":"Autos & Motor Vehicles",
            "subcategory":"Automobile Sales",
            "type":"Retail Goods"
        }
    ],
    "sg:phone":"+1 903 455 3300",
    "sg:postcode":"75401",
    "sg:province":"TX",
    "sg:tags":[
        "car",
        "dealer"
    ],
    "wof:name":"Ace Towing & Transport & Sales",
    "wof:placetype":"venue"
},
  "geometry": {"coordinates":[-96.07310699999999,33.139559],"type":"Point"}
}