{
  "type": "Feature",
  "properties": {
    "iso:country":"US",
    "sg:address":"165 Inwood Vlg",
    "sg:city":"Dallas",
    "sg:classifiers":[
        {
            "category":"Restaurant",
            "type":"Food & Drink"
        }
    ],
    "sg:phone":"+1 214 350 5227",
    "sg:postcode":"75209",
    "sg:province":"TX",
    "sg:tags":[
        "mexican"
    ],
    "wof:name":"Casa Rosa Restaurante",
    "wof:placetype":"venue"
},
  "geometry": {"coordinates":[-96.819,32.8512],"type":"Point"}
}