{
  "type": "Feature",
  "properties": {
    "iso:country":"US",
    "sg:address":"717 Estate Dr",
    "sg:city":"Belton",
    "sg:classifiers":[
        {
            "category":"Shopping",
            "subcategory":"Used Merchandise",
            "type":"Retail Goods"
        }
    ],
    "sg:phone":"+1 254 939 6504",
    "sg:postcode":"76513",
    "sg:province":"TX",
    "sg:tags":[
        "antique",
        "military"
    ],
    "wof:name":"Major Dads Military Antiques",
    "wof:placetype":"venue"
},
  "geometry": {"coordinates":[-97.456726,31.085035],"type":"Point"}
}