{
  "type": "Feature",
  "properties": {
    "iso:country":"US",
    "sg:address":"2708 6th Ave",
    "sg:city":"Fort Worth",
    "sg:classifiers":[
        {
            "category":"Professional",
            "type":"Services"
        }
    ],
    "sg:phone":"+1 817 926 4328",
    "sg:postcode":"76110",
    "sg:province":"TX",
    "wof:name":"Marilee S Haughy",
    "wof:placetype":"venue"
},
  "geometry": {"coordinates":[-97.340351,32.71297],"type":"Point"}
}