{
  "type": "Feature",
  "properties": {
    "iso:country":"US",
    "sg:address":"3631 Grafton Ave",
    "sg:city":"Dallas",
    "sg:classifiers":[
        {
            "category":"Organizations",
            "subcategory":"Religious Organization",
            "type":"Services"
        }
    ],
    "sg:phone":"+1 214 682 2916",
    "sg:postcode":"75211",
    "sg:province":"TX",
    "wof:name":"Trinity One Construction",
    "wof:placetype":"venue"
},
  "geometry": {"coordinates":[-96.881743,32.730276],"type":"Point"}
}