{
  "type": "Feature",
  "properties": {
    "iso:country":"US",
    "sg:address":"2033 Farrington St",
    "sg:city":"Dallas",
    "sg:classifiers":[
        {
            "category":"Shopping",
            "subcategory":"Stationery & Office Supplies",
            "type":"Retail Goods"
        }
    ],
    "sg:phone":"+1 214 749 5766",
    "sg:postcode":"75207",
    "sg:province":"TX",
    "sg:tags":[
        "equipment"
    ],
    "wof:name":"Overman Cheryl",
    "wof:placetype":"venue"
},
  "geometry": {"coordinates":[-96.82899,32.79634],"type":"Point"}
}