{
  "type": "Feature",
  "properties": {
    "iso:country":"US",
    "sg:address":"501 Palm Blvd",
    "sg:city":"Port Isabel",
    "sg:classifiers":[
        {
            "category":"Manufacturing",
            "subcategory":"Retail Goods",
            "type":"Manufacturing & Wholesale Goods"
        },
        {
            "category":"Shopping",
            "subcategory":"Florist",
            "type":"Retail Goods"
        }
    ],
    "sg:phone":"+1 956 943 6967",
    "sg:postcode":"78578",
    "sg:province":"TX",
    "sg:tags":[
        "product",
        "mfg"
    ],
    "wof:name":"Stop & Smell The Roses",
    "wof:placetype":"venue"
},
  "geometry": {"coordinates":[-97.297906,26.095555],"type":"Point"}
}