{
  "type": "Feature",
  "properties": {
    "iso:country":"US",
    "sg:address":"4401 Crawford Dr",
    "sg:city":"Abilene",
    "sg:classifiers":[
        {
            "category":"Wholesale",
            "subcategory":"Medical Equipment & Supplies",
            "type":"Manufacturing & Wholesale Goods"
        }
    ],
    "sg:phone":"+1 325 793 9500",
    "sg:postcode":"79602",
    "sg:province":"TX",
    "sg:tags":[
        "physician",
        "surgeon"
    ],
    "wof:name":"Mediq PRN",
    "wof:placetype":"venue"
},
  "geometry": {"coordinates":[-99.74870199999999,32.400973],"type":"Point"}
}