{
  "type": "Feature",
  "properties": {
    "iso:country":"US",
    "sg:address":"777 N Grove Rd",
    "sg:city":"Richardson",
    "sg:classifiers":[
        {
            "category":"Wholesale",
            "subcategory":"Electrical",
            "type":"Manufacturing & Wholesale Goods"
        },
        {
            "category":"Shopping",
            "subcategory":"Computers & Home Electronics",
            "type":"Retail Goods"
        }
    ],
    "sg:phone":"+1 972 671 1212",
    "sg:postcode":"75081",
    "sg:province":"TX",
    "sg:tags":[
        "equipment",
        "electronic",
        "component",
        "supply"
    ],
    "wof:name":"Promor Electronic Components",
    "wof:placetype":"venue"
},
  "geometry": {"coordinates":[-96.718643,32.958428],"type":"Point"}
}