{
  "type": "Feature",
  "properties": {
    "iso:country":"US",
    "sg:address":"418 Eureka St",
    "sg:city":"Weatherford",
    "sg:classifiers":[
        {
            "category":"Social Services",
            "type":"Services"
        },
        {
            "category":"Personal",
            "type":"Services"
        }
    ],
    "sg:phone":"+1 817 596 8410",
    "sg:postcode":"76086",
    "sg:province":"TX",
    "sg:tags":[
        "family",
        "counselors-licensed",
        "individual",
        "marriage",
        "child",
        "professional",
        "counselor"
    ],
    "wof:name":"Buckner Brandi Ph.D. LPC",
    "wof:placetype":"venue"
},
  "geometry": {"coordinates":[-97.791962,32.750229],"type":"Point"}
}