{
  "type": "Feature",
  "properties": {
    "iso:country":"US",
    "sg:address":"1609 Durham Dr",
    "sg:city":"Houston",
    "sg:classifiers":[
        {
            "category":"Restaurant",
            "type":"Food & Drink"
        }
    ],
    "sg:phone":"+1 713 426 6634",
    "sg:postcode":"77007",
    "sg:province":"TX",
    "sg:tags":[
        "mexican"
    ],
    "sg:website":"www.missionburritos.com",
    "wof:name":"Mission Burrito",
    "wof:placetype":"venue"
},
  "geometry": {"coordinates":[-95.41092,29.775348],"type":"Point"}
}