{
  "type": "Feature",
  "properties": {
    "iso:country":"US",
    "sg:address":"2034 E 20th St",
    "sg:city":"Brownsville",
    "sg:classifiers":[
        {
            "category":"Building & Trades",
            "subcategory":"Pest Control",
            "type":"Services"
        }
    ],
    "sg:phone":"+1 956 546 0536",
    "sg:postcode":"78521",
    "sg:province":"TX",
    "wof:name":"Nyd Nad Pest Control Ser",
    "wof:placetype":"venue"
},
  "geometry": {"coordinates":[-97.47883299999999,25.904234],"type":"Point"}
}