{
  "type": "Feature",
  "properties": {
    "iso:country":"US",
    "sg:address":"2220 San Jacinto Blvd",
    "sg:city":"Denton",
    "sg:classifiers":[
        {
            "category":"Banks & Credit Unions",
            "subcategory":"Financial Services",
            "type":"Services"
        }
    ],
    "sg:phone":"+1 940 387 2211",
    "sg:postcode":"76205",
    "sg:province":"TX",
    "sg:tags":[
        "annuity",
        "insurance"
    ],
    "wof:name":"G Thomas Swenson Ing Financial",
    "wof:placetype":"venue"
},
  "geometry": {"coordinates":[-97.109531,33.192348],"type":"Point"}
}