{
  "type": "Feature",
  "properties": {
    "iso:country":"US",
    "sg:address":"7500 Harrisburg Blvd",
    "sg:city":"Houston",
    "sg:classifiers":[
        {
            "category":"Building & Trades",
            "subcategory":"Locksmith",
            "type":"Services"
        }
    ],
    "sg:phone":"+1 713 924 5988",
    "sg:postcode":"77012",
    "sg:province":"TX",
    "sg:tags":[
        "key"
    ],
    "wof:name":"Enrique's Shop",
    "wof:placetype":"venue"
},
  "geometry": {"coordinates":[-95.29209899999999,29.732401],"type":"Point"}
}