{
  "type": "Feature",
  "properties": {
    "iso:country":"US",
    "sg:address":"3034 Lockcrest St",
    "sg:city":"Houston",
    "sg:classifiers":[
        {
            "category":"Autos & Motor Vehicles",
            "subcategory":"Auto Supplies",
            "type":"Retail Goods"
        }
    ],
    "sg:phone":"+1 713 413 4282",
    "sg:postcode":"77047",
    "sg:province":"TX",
    "sg:tags":[
        "tire"
    ],
    "wof:name":"Cavazos Tire Sales",
    "wof:placetype":"venue"
},
  "geometry": {"coordinates":[-95.379802,29.616651],"type":"Point"}
}