{
  "type": "Feature",
  "properties": {
    "iso:country":"US",
    "sg:address":"12558 Sisco Ln",
    "sg:city":"Bryan",
    "sg:classifiers":[
        {
            "category":"Building & Trades",
            "subcategory":"Landscaping Services",
            "type":"Services"
        }
    ],
    "sg:phone":"+1 979 776 2064",
    "sg:postcode":"77808",
    "sg:province":"TX",
    "sg:tags":[
        "lawn",
        "maintenance"
    ],
    "wof:name":"Lazy Boy Lawn Service",
    "wof:placetype":"venue"
},
  "geometry": {"coordinates":[-96.178847,30.671444],"type":"Point"}
}