{
  "type": "Feature",
  "properties": {
    "iso:country":"US",
    "sg:address":"1226 West Dr",
    "sg:city":"Port Neches",
    "sg:classifiers":[
        {
            "category":"Professional",
            "subcategory":"Business Services",
            "type":"Services"
        }
    ],
    "sg:phone":"+1 409 729 1061",
    "sg:postcode":"77651",
    "sg:province":"TX",
    "wof:name":"Patken Enterprises",
    "wof:placetype":"venue"
},
  "geometry": {"coordinates":[-93.96711500000001,29.9947],"type":"Point"}
}