{
  "type": "Feature",
  "properties": {
    "iso:country":"US",
    "sg:address":"2417 Vail Dr",
    "sg:city":"Mckinney",
    "sg:classifiers":[
        {
            "category":"Building & Trades",
            "subcategory":"Electrical",
            "type":"Services"
        }
    ],
    "sg:phone":"+1 972 569 9042",
    "sg:postcode":"75070",
    "sg:province":"TX",
    "sg:tags":[
        "electrician"
    ],
    "wof:name":"Benge Electric",
    "wof:placetype":"venue"
},
  "geometry": {"coordinates":[-96.658188,33.161152],"type":"Point"}
}