{
  "type": "Feature",
  "properties": {
    "iso:country":"US",
    "sg:address":"12865 Fig Plant Rd",
    "sg:city":"Hamshire",
    "sg:classifiers":[
        {
            "category":"Shopping",
            "type":"Retail Goods"
        }
    ],
    "sg:phone":"+1 409 243 2152",
    "sg:postcode":"77622",
    "sg:province":"TX",
    "sg:tags":[
        "merchandise"
    ],
    "wof:name":"Fabriguze Cabinet Shop",
    "wof:placetype":"venue"
},
  "geometry": {"coordinates":[-94.319512,29.859745],"type":"Point"}
}