{
  "type": "Feature",
  "properties": {
    "iso:country":"US",
    "sg:address":"2303 Highland Heights Ln",
    "sg:city":"Carrollton",
    "sg:classifiers":[
        {
            "category":"Professional",
            "subcategory":"Management & Consulting",
            "type":"Services"
        }
    ],
    "sg:phone":"+1 972 306 3045",
    "sg:postcode":"75007",
    "sg:province":"TX",
    "wof:name":"Lamurian Enterprises",
    "wof:placetype":"venue"
},
  "geometry": {"coordinates":[-96.86501800000001,33.018754],"type":"Point"}
}