{
  "type": "Feature",
  "properties": {
    "iso:country":"US",
    "sg:address":"1003 S Fannin St",
    "sg:city":"Amarillo",
    "sg:classifiers":[
        {
            "category":"Arts & Performance",
            "subcategory":"Theater",
            "type":"Entertainment"
        }
    ],
    "sg:phone":"+1 806 372 9001",
    "sg:postcode":"79102",
    "sg:province":"TX",
    "sg:tags":[
        "group"
    ],
    "wof:name":"Tascosa Band & Orchestra",
    "wof:placetype":"venue"
},
  "geometry": {"coordinates":[-101.859835,35.202476],"type":"Point"}
}