{
  "type": "Feature",
  "properties": {
    "iso:country":"US",
    "sg:address":"801 Pine Tree Rd",
    "sg:city":"Longview",
    "sg:classifiers":[
        {
            "category":"Insurance",
            "subcategory":"Hazard Insurance",
            "type":"Services"
        },
        {
            "category":"Insurance",
            "subcategory":"Insurance Agent",
            "type":"Services"
        },
        {
            "category":"Insurance",
            "subcategory":"Life Insurance",
            "type":"Services"
        }
    ],
    "sg:phone":"+1 903 215 8348",
    "sg:postcode":"75604",
    "sg:province":"TX",
    "sg:tags":[
        "auto"
    ],
    "sg:website":"http://statefarm.mqgroup.com/url.asp?usr=437884",
    "wof:name":"Ingram, Charlene - State Farm Insurance Agent",
    "wof:placetype":"venue"
},
  "geometry": {"coordinates":[-94.797943,32.513901],"type":"Point"}
}