{
  "type": "Feature",
  "properties": {
    "iso:country":"US",
    "sg:address":"4315 Resort Dr",
    "sg:city":"Granbury",
    "sg:classifiers":[
        {
            "category":"Retail",
            "subcategory":"Auto Repair",
            "type":"Services"
        }
    ],
    "sg:phone":"+1 817 579 6113",
    "sg:postcode":"76048",
    "sg:province":"TX",
    "wof:name":"Mike McGarrity Chevrolet",
    "wof:placetype":"venue"
},
  "geometry": {"coordinates":[-97.709868,32.39155],"type":"Point"}
}