{
  "type": "Feature",
  "properties": {
    "iso:country":"US",
    "sg:address":"212 N Broadway St",
    "sg:city":"Brownwood",
    "sg:classifiers":[
        {
            "category":"Museum",
            "type":"Entertainment"
        }
    ],
    "sg:phone":"+1 325 641 1926",
    "sg:postcode":"76801",
    "sg:province":"TX",
    "wof:name":"Brown County Museum Of History",
    "wof:placetype":"venue"
},
  "geometry": {"coordinates":[-98.980632,31.723339],"type":"Point"}
}