{
  "type": "Feature",
  "properties": {
    "iso:country":"US",
    "sg:address":"14855 Skinner Rd",
    "sg:city":"Cypress",
    "sg:classifiers":[
        {
            "category":"Home & Garden",
            "subcategory":"Mobile Homes",
            "type":"Retail Goods"
        }
    ],
    "sg:phone":"+1 281 304 7475",
    "sg:postcode":"77429",
    "sg:province":"TX",
    "wof:name":"Davis Angus Investments",
    "wof:placetype":"venue"
},
  "geometry": {"coordinates":[-95.687625,29.994173],"type":"Point"}
}