{
  "type": "Feature",
  "properties": {
    "iso:country":"US",
    "sg:address":"1026 Jackson Ave",
    "sg:city":"Bacliff",
    "sg:classifiers":[
        {
            "category":"Organizations",
            "subcategory":"Community Association",
            "type":"Services"
        }
    ],
    "sg:phone":"+1 281 339 2606",
    "sg:postcode":"77518",
    "sg:province":"TX",
    "sg:tags":[
        "fraternal"
    ],
    "wof:name":"Fraternal Order Of Eagles",
    "wof:placetype":"venue"
},
  "geometry": {"coordinates":[-94.995355,29.503413],"type":"Point"}
}