{
  "type": "Feature",
  "properties": {
    "iso:country":"US",
    "sg:address":"952 Echo Ln Ste 370",
    "sg:city":"Houston",
    "sg:classifiers":[
        {
            "category":"Autos & Motor Vehicles",
            "subcategory":"Auto Supplies",
            "type":"Retail Goods"
        },
        {
            "category":"Wholesale",
            "subcategory":"Auto Parts",
            "type":"Manufacturing & Wholesale Goods"
        }
    ],
    "sg:phone":"+1 832 242 1818",
    "sg:postcode":"77024",
    "sg:province":"TX",
    "sg:tags":[
        "automobile",
        "rebuilt",
        "rebuilt-wholesale",
        "supplies-used",
        "manufacturer"
    ],
    "wof:name":"Gadi Collections",
    "wof:placetype":"venue"
},
  "geometry": {"coordinates":[-95.521271,29.78192],"type":"Point"}
}