{
  "type": "Feature",
  "properties": {
    "iso:country":"US",
    "sg:address":"2015 Peavy Rd",
    "sg:city":"Dallas",
    "sg:classifiers":[
        {
            "category":"Government",
            "subcategory":"Office",
            "type":"Public Place"
        }
    ],
    "sg:phone":"+1 214 324 5511",
    "sg:postcode":"75228",
    "sg:province":"TX",
    "sg:tags":[
        "federal",
        "human"
    ],
    "wof:name":"H R Auditor",
    "wof:placetype":"venue"
},
  "geometry": {"coordinates":[-96.68393399999999,32.826778],"type":"Point"}
}