{
  "type": "Feature",
  "properties": {
    "iso:country":"US",
    "sg:address":"12349 Metric Blvd",
    "sg:city":"Austin",
    "sg:classifiers":[
        {
            "category":"Education",
            "subcategory":"School",
            "type":"Public Place"
        }
    ],
    "sg:phone":"+1 512 837 7026",
    "sg:postcode":"78758",
    "sg:province":"TX",
    "wof:name":"Twenty First Century Schools",
    "wof:placetype":"venue"
},
  "geometry": {"coordinates":[-97.69674500000001,30.408422],"type":"Point"}
}