{
  "type": "Feature",
  "properties": {
    "iso:country":"US",
    "sg:address":"12363 Waters Park Rd",
    "sg:city":"Austin",
    "sg:classifiers":[
        {
            "category":"Manufacturing",
            "subcategory":"Metals",
            "type":"Manufacturing & Wholesale Goods"
        }
    ],
    "sg:phone":"+1 512 836 4952",
    "sg:postcode":"78759",
    "sg:province":"TX",
    "sg:tags":[
        "concrete",
        "structural",
        "metalwork",
        "reinforcement",
        "mfg"
    ],
    "wof:name":"D L Dennis Company",
    "wof:placetype":"venue"
},
  "geometry": {"coordinates":[-97.708051,30.418076],"type":"Point"}
}