{
  "type": "Feature",
  "properties": {
    "iso:country":"US",
    "sg:address":"101 E Queen Isabella Blvd",
    "sg:city":"Port Isabel",
    "sg:classifiers":[
        {
            "category":"Shopping",
            "subcategory":"Hobbies, Toys, & Games",
            "type":"Retail Goods"
        }
    ],
    "sg:phone":"+1 956 943 5717",
    "sg:postcode":"78578",
    "sg:province":"TX",
    "sg:tags":[
        "supply"
    ],
    "wof:name":"Game Room",
    "wof:placetype":"venue"
},
  "geometry": {"coordinates":[-97.210368,26.075608],"type":"Point"}
}