{
  "type": "Feature",
  "properties": {
    "iso:country":"US",
    "sg:address":"2026 Sawdust Rd",
    "sg:city":"Spring",
    "sg:classifiers":[
        {
            "category":"Building & Trades",
            "subcategory":"Landscaping Services",
            "type":"Services"
        }
    ],
    "sg:phone":"+1 281 292 2747",
    "sg:postcode":"77380",
    "sg:province":"TX",
    "sg:tags":[
        "lawn",
        "maintenance",
        "grounds"
    ],
    "sg:website":"www.woodlandslandscaping.com",
    "wof:name":"Woodlands Landscaping & Mntnc",
    "wof:placetype":"venue"
},
  "geometry": {"coordinates":[-95.471969,30.130323],"type":"Point"}
}