{
  "type": "Feature",
  "properties": {
    "iso:country":"US",
    "sg:address":"7901 Callaghan Rd",
    "sg:city":"San Antonio",
    "sg:classifiers":[
        {
            "category":"Home & Garden",
            "subcategory":"Building Materials",
            "type":"Retail Goods"
        }
    ],
    "sg:phone":"+1 210 979 7990",
    "sg:postcode":"78229",
    "sg:province":"TX",
    "sg:tags":[
        "lumber"
    ],
    "wof:name":"Lowe's",
    "wof:placetype":"venue"
},
  "geometry": {"coordinates":[-98.55316500000001,29.510516],"type":"Point"}
}