{
  "type": "Feature",
  "properties": {
    "iso:country":"US",
    "sg:address":"6441 McCart Ave",
    "sg:city":"Fort Worth",
    "sg:classifiers":[
        {
            "category":"Government",
            "subcategory":"Office",
            "type":"Public Place"
        }
    ],
    "sg:phone":"+1 817 263 7347",
    "sg:postcode":"76133",
    "sg:province":"TX",
    "sg:tags":[
        "force",
        "station",
        "armed",
        "recruiting"
    ],
    "wof:name":"Navy Recruiting Station",
    "wof:placetype":"venue"
},
  "geometry": {"coordinates":[-97.36609300000001,32.651179],"type":"Point"}
}