{
  "type": "Feature",
  "properties": {
    "iso:country":"US",
    "sg:address":"11200 Montana Ave",
    "sg:city":"El Paso",
    "sg:classifiers":[
        {
            "category":"Travel",
            "subcategory":"Campground",
            "type":"Entertainment"
        }
    ],
    "sg:phone":"+1 915 598 7522",
    "sg:postcode":"79936",
    "sg:province":"TX",
    "sg:tags":[
        "trailer"
    ],
    "wof:name":"Arvey Park",
    "wof:placetype":"venue"
},
  "geometry": {"coordinates":[-106.309264,31.800805],"type":"Point"}
}