{
  "type": "Feature",
  "properties": {
    "iso:country":"US",
    "sg:address":"5440 Harvest Hill Rd",
    "sg:city":"Dallas",
    "sg:classifiers":[
        {
            "category":"Real Estate",
            "subcategory":"Real Estate Services",
            "type":"Services"
        }
    ],
    "sg:phone":"+1 972 387 0390",
    "sg:postcode":"75230",
    "sg:province":"TX",
    "sg:tags":[
        "company",
        "title"
    ],
    "wof:name":"American Title Co",
    "wof:placetype":"venue"
},
  "geometry": {"coordinates":[-96.817329,32.921593],"type":"Point"}
}