{
  "type": "Feature",
  "properties": {
    "iso:country":"US",
    "sg:address":"2403 N Washington Ave",
    "sg:city":"Dallas",
    "sg:classifiers":[
        {
            "category":"Restaurant",
            "type":"Food & Drink"
        }
    ],
    "sg:phone":"+1 214 821 4271",
    "sg:postcode":"75204",
    "sg:province":"TX",
    "sg:tags":[
        "eating"
    ],
    "wof:name":"Taste Masters",
    "wof:placetype":"venue"
},
  "geometry": {"coordinates":[-96.791276,32.802393],"type":"Point"}
}