{
  "type": "Feature",
  "properties": {
    "iso:country":"US",
    "sg:address":"803 W Main St",
    "sg:city":"Decatur",
    "sg:classifiers":[
        {
            "category":"Travel",
            "subcategory":"Travel Agent",
            "type":"Entertainment"
        }
    ],
    "sg:phone":"+1 940 627 6600",
    "sg:postcode":"76234",
    "sg:province":"TX",
    "sg:tags":[
        "agency",
        "bureau"
    ],
    "wof:name":"Allwise Travel Inc",
    "wof:placetype":"venue"
},
  "geometry": {"coordinates":[-97.59433799999999,33.23412],"type":"Point"}
}