{
  "type": "Feature",
  "properties": {
    "iso:country":"US",
    "sg:address":"503 N Maple St",
    "sg:city":"Muenster",
    "sg:classifiers":[
        {
            "category":"Health Services",
            "subcategory":"Doctor",
            "type":"Services"
        }
    ],
    "sg:phone":"+1 940 759 2303",
    "sg:postcode":"76252",
    "sg:province":"TX",
    "sg:tags":[
        "dentist"
    ],
    "wof:name":"North Texas Dental Specialists",
    "wof:placetype":"venue"
},
  "geometry": {"coordinates":[-97.379907,33.653507],"type":"Point"}
}