{
  "type": "Feature",
  "properties": {
    "iso:country":"US",
    "sg:address":"1254 S Main St",
    "sg:city":"Lumberton",
    "sg:classifiers":[
        {
            "category":"Shopping",
            "subcategory":"Clothing, Apparel, & Fashions",
            "type":"Retail Goods"
        }
    ],
    "sg:phone":"+1 409 755 6586",
    "sg:postcode":"77657",
    "sg:province":"TX",
    "wof:name":"About Kids",
    "wof:placetype":"venue"
},
  "geometry": {"coordinates":[-94.195654,30.239609],"type":"Point"}
}