{
  "type": "Feature",
  "properties": {
    "iso:country":"US",
    "sg:address":"2956 FM 2673",
    "sg:city":"Canyon Lake",
    "sg:classifiers":[
        {
            "category":"Retail",
            "subcategory":"Repair Shop",
            "type":"Services"
        },
        {
            "category":"Manufacturing",
            "subcategory":"Motor Vehicles & Parts",
            "type":"Manufacturing & Wholesale Goods"
        }
    ],
    "sg:phone":"+1 830 964 4822",
    "sg:postcode":"78133",
    "sg:province":"TX",
    "sg:tags":[
        "scooter",
        "motorcycle",
        "mfg"
    ],
    "sg:website":"www.griffscycleshop.com",
    "wof:name":"Griff's Cycle Shop",
    "wof:placetype":"venue"
},
  "geometry": {"coordinates":[-98.19100899999999,29.842009],"type":"Point"}
}