{
  "type": "Feature",
  "properties": {
    "iso:country":"US",
    "sg:address":"219 W Grand Ave",
    "sg:city":"Yoakum",
    "sg:classifiers":[
        {
            "category":"Autos & Motor Vehicles",
            "subcategory":"Auto Supplies",
            "type":"Retail Goods"
        },
        {
            "category":"Wholesale",
            "subcategory":"Auto Parts",
            "type":"Manufacturing & Wholesale Goods"
        }
    ],
    "sg:phone":"+1 361 293 3642",
    "sg:postcode":"77995",
    "sg:province":"TX",
    "sg:tags":[
        "automobile"
    ],
    "wof:name":"Anders Auto Supplies",
    "wof:placetype":"venue"
},
  "geometry": {"coordinates":[-97.15088299999999,29.289547],"type":"Point"}
}