{
  "type": "Feature",
  "properties": {
    "iso:country":"US",
    "sg:address":"7115 Valburn Dr",
    "sg:city":"Austin",
    "sg:classifiers":[
        {
            "category":"Professional",
            "type":"Services"
        }
    ],
    "sg:phone":"+1 512 345 0516",
    "sg:postcode":"78731",
    "sg:province":"TX",
    "wof:name":"Elbrecht Family Ltd Partnr",
    "wof:placetype":"venue"
},
  "geometry": {"coordinates":[-97.78139299999999,30.370153],"type":"Point"}
}