{
  "type": "Feature",
  "properties": {
    "iso:country":"US",
    "sg:address":"19022 Lakeside Cove",
    "sg:city":"Houston",
    "sg:classifiers":[
        {
            "category":"Banks & Credit Unions",
            "subcategory":"Financial Services",
            "type":"Services"
        }
    ],
    "sg:phone":"+1 281 579 9599",
    "sg:postcode":"77094",
    "sg:province":"TX",
    "sg:tags":[
        "investment",
        "closed"
    ],
    "wof:name":"Brunet Investments Cactus",
    "wof:placetype":"venue"
},
  "geometry": {"coordinates":[-95.700833,29.763723],"type":"Point"}
}