{
  "type": "Feature",
  "properties": {
    "iso:country":"US",
    "sg:address":"604 Heatherglen Dr",
    "sg:city":"Southlake",
    "sg:classifiers":[
        {
            "category":"Professional",
            "type":"Services"
        }
    ],
    "sg:phone":"+1 817 424 0128",
    "sg:postcode":"76092",
    "sg:province":"TX",
    "wof:name":"Dragon Country",
    "wof:placetype":"venue"
},
  "geometry": {"coordinates":[-97.14449399999999,32.934056],"type":"Point"}
}