{
  "type": "Feature",
  "properties": {
    "iso:country":"US",
    "sg:address":"2947 Buckner Blvd",
    "sg:city":"Dallas",
    "sg:classifiers":[
        {
            "category":"Shopping",
            "subcategory":"Shoes",
            "type":"Retail Goods"
        }
    ],
    "sg:phone":"+1 214 381 2030",
    "sg:postcode":"75227",
    "sg:province":"TX",
    "wof:name":"Foot Gear",
    "wof:placetype":"venue"
},
  "geometry": {"coordinates":[-96.682751,32.761915],"type":"Point"}
}