{
  "type": "Feature",
  "properties": {
    "iso:country":"US",
    "sg:address":"2902 Hillcroft St",
    "sg:city":"Houston",
    "sg:classifiers":[
        {
            "category":"Retail",
            "subcategory":"Auto Repair",
            "type":"Services"
        }
    ],
    "sg:phone":"+1 713 782 9111",
    "sg:postcode":"77057",
    "sg:province":"TX",
    "sg:website":"www.nexarmotors.com",
    "wof:name":"NEXAR AUTO REPAIR",
    "wof:placetype":"venue"
},
  "geometry": {"coordinates":[-95.501302,29.734872],"type":"Point"}
}