{
  "type": "Feature",
  "properties": {
    "iso:country":"US",
    "sg:address":"16882 Old Danville Rd",
    "sg:city":"Willis",
    "sg:classifiers":[
        {
            "category":"Building & Trades",
            "subcategory":"Construction",
            "type":"Services"
        }
    ],
    "sg:phone":"+1 936 344 6738",
    "sg:postcode":"77318",
    "sg:province":"TX",
    "sg:tags":[
        "steel"
    ],
    "wof:name":"Draftech",
    "wof:placetype":"venue"
},
  "geometry": {"coordinates":[-95.506743,30.480458],"type":"Point"}
}