{
  "type": "Feature",
  "properties": {
    "iso:country":"US",
    "sg:address":"1342 Squires Rd",
    "sg:city":"Abilene",
    "sg:classifiers":[
        {
            "category":"Education",
            "subcategory":"Special Training",
            "type":"Public Place"
        }
    ],
    "sg:phone":"+1 325 676 2913",
    "sg:postcode":"79602",
    "sg:province":"TX",
    "wof:name":"Jerry E Whitworth",
    "wof:placetype":"venue"
},
  "geometry": {"coordinates":[-99.701784,32.437944],"type":"Point"}
}