{
  "type": "Feature",
  "properties": {
    "iso:country":"US",
    "sg:address":"1211 E 16th St",
    "sg:city":"Plano",
    "sg:classifiers":[
        {
            "category":"Personal",
            "type":"Services"
        },
        {
            "category":"Travel",
            "subcategory":"Hotels & Motels",
            "type":"Entertainment"
        }
    ],
    "sg:phone":"+1 972 424 1889",
    "sg:postcode":"75074",
    "sg:province":"TX",
    "sg:tags":[
        "operation",
        "wedding",
        "chapel"
    ],
    "wof:name":"Carpenter House Inc",
    "wof:placetype":"venue"
},
  "geometry": {"coordinates":[-96.69646400000001,33.021282],"type":"Point"}
}