{
  "type": "Feature",
  "properties": {
    "iso:country":"US",
    "sg:address":"3113 US Hwy 87",
    "sg:city":"Big Spring",
    "sg:classifiers":[
        {
            "category":"Wholesale",
            "subcategory":"Medical Equipment & Supplies",
            "type":"Manufacturing & Wholesale Goods"
        }
    ],
    "sg:phone":"+1 432 263 2266",
    "sg:postcode":"79720",
    "sg:province":"TX",
    "wof:name":"American Medical Equipment",
    "wof:placetype":"venue"
},
  "geometry": {"coordinates":[-101.49914699999999,32.290429],"type":"Point"}
}