{
  "type": "Feature",
  "properties": {
    "iso:country":"US",
    "sg:address":"402 Main St",
    "sg:city":"Houston",
    "sg:classifiers":[
        {
            "category":"Professional",
            "subcategory":"Lawyer & Legal Services",
            "type":"Services"
        }
    ],
    "sg:phone":"+1 281 971 5130",
    "sg:postcode":"77002",
    "sg:province":"TX",
    "sg:tags":[
        "personal",
        "injury"
    ],
    "wof:name":"Personal Injury Attorneys",
    "wof:placetype":"venue"
},
  "geometry": {"coordinates":[-95.361526,29.761588],"type":"Point"}
}