{
  "type": "Feature",
  "properties": {
    "iso:country":"US",
    "sg:address":"1722 N Mays St",
    "sg:city":"Round Rock",
    "sg:classifiers":[
        {
            "category":"Food & Beverages",
            "subcategory":"Liquor & Beverages",
            "type":"Retail Goods"
        }
    ],
    "sg:phone":"+1 512 255 8888",
    "sg:postcode":"78664",
    "sg:province":"TX",
    "sg:tags":[
        "alcoholic"
    ],
    "wof:name":"Reubens Bottle Shops",
    "wof:placetype":"venue"
},
  "geometry": {"coordinates":[-97.68590399999999,30.523683],"type":"Point"}
}