{
  "type": "Feature",
  "properties": {
    "iso:country":"US",
    "sg:address":"3503 Spencer Hwy",
    "sg:city":"Pasadena",
    "sg:classifiers":[
        {
            "category":"Personal",
            "subcategory":"Nail Salon",
            "type":"Services"
        }
    ],
    "sg:phone":"+1 713 944 3388",
    "sg:postcode":"77504",
    "sg:province":"TX",
    "wof:name":"Amy's Nails",
    "wof:placetype":"venue"
},
  "geometry": {"coordinates":[-95.19029999999999,29.665199],"type":"Point"}
}