{
  "type": "Feature",
  "properties": {
    "iso:country":"US",
    "sg:address":"1049 Lakeshore Dr",
    "sg:city":"Spicewood",
    "sg:classifiers":[
        {
            "category":"Building & Trades",
            "subcategory":"Construction",
            "type":"Services"
        }
    ],
    "sg:phone":"+1 512 264 3886",
    "sg:postcode":"78669",
    "sg:province":"TX",
    "sg:tags":[
        "home",
        "builder"
    ],
    "wof:name":"Schatz Builders",
    "wof:placetype":"venue"
},
  "geometry": {"coordinates":[-98.077806,30.440947],"type":"Point"}
}