{
  "type": "Feature",
  "properties": {
    "iso:country":"US",
    "sg:address":"11139 Homestead Rd",
    "sg:city":"Houston",
    "sg:classifiers":[
        {
            "category":"Restaurant",
            "type":"Food & Drink"
        }
    ],
    "sg:phone":"+1 281 442 0519",
    "sg:postcode":"77016",
    "sg:province":"TX",
    "wof:name":"M & H Bar-B-Que",
    "wof:placetype":"venue"
},
  "geometry": {"coordinates":[-95.300679,29.87889],"type":"Point"}
}