{
  "type": "Feature",
  "properties": {
    "iso:country":"US",
    "sg:address":"702 Honeysuckle",
    "sg:city":"White Oak",
    "sg:classifiers":[
        {
            "category":"Home & Garden",
            "subcategory":"Building Materials",
            "type":"Retail Goods"
        }
    ],
    "sg:phone":"+1 903 759 8108",
    "sg:postcode":"75693",
    "sg:province":"TX",
    "sg:tags":[
        "glass",
        "leaded"
    ],
    "wof:name":"Lita Cobb Stained Glass Emprm",
    "wof:placetype":"venue"
},
  "geometry": {"coordinates":[-94.85653499999999,32.523495],"type":"Point"}
}