{
  "type": "Feature",
  "properties": {
    "iso:country":"US",
    "sg:address":"334 S Main St",
    "sg:city":"Irving",
    "sg:classifiers":[
        {
            "category":"Health Services",
            "subcategory":"Doctor",
            "type":"Services"
        }
    ],
    "sg:phone":"+1 972 355 5322",
    "sg:postcode":"75060",
    "sg:province":"TX",
    "sg:tags":[
        "medical"
    ],
    "wof:name":"Keith Mauney & Associates",
    "wof:placetype":"venue"
},
  "geometry": {"coordinates":[-96.946127,32.811017],"type":"Point"}
}