{
  "type": "Feature",
  "properties": {
    "iso:country":"US",
    "sg:address":"4000 Windsor Dr",
    "sg:city":"Flower Mound",
    "sg:classifiers":[
        {
            "category":"Restaurant",
            "type":"Food & Drink"
        }
    ],
    "sg:menulink":"http://www.allmenus.com/tx/lewisville/251264-bridlewood-golf-club/menu/",
    "sg:phone":"+1 972 355 4800",
    "sg:postcode":"75028",
    "sg:province":"TX",
    "sg:tags":[
        "american"
    ],
    "wof:name":"Bridlewood Golf Club",
    "wof:placetype":"venue"
},
  "geometry": {"coordinates":[-97.090405,33.04863],"type":"Point"}
}