{
  "type": "Feature",
  "properties": {
    "iso:country":"US",
    "sg:address":"802 W Johanna St",
    "sg:city":"Austin",
    "sg:classifiers":[
        {
            "category":"Home & Garden",
            "subcategory":"Garden Supply",
            "type":"Retail Goods"
        }
    ],
    "sg:phone":"+1 512 445 2614",
    "sg:postcode":"78704",
    "sg:province":"TX",
    "sg:tags":[
        "equipment",
        "lawn",
        "supplies-wholesale",
        "manufacturer"
    ],
    "wof:name":"They Might Be Monkeys Texas",
    "wof:placetype":"venue"
},
  "geometry": {"coordinates":[-97.75984099999999,30.246499],"type":"Point"}
}