{
  "type": "Feature",
  "properties": {
    "iso:country":"US",
    "sg:address":"462 Beresford St",
    "sg:city":"Houston",
    "sg:classifiers":[
        {
            "category":"Retail",
            "subcategory":"Repair Shop",
            "type":"Services"
        }
    ],
    "sg:phone":"+1 713 453 0251",
    "sg:postcode":"77015",
    "sg:province":"TX",
    "sg:tags":[
        "refrigeration"
    ],
    "wof:name":"Biscamp Refrigeration",
    "wof:placetype":"venue"
},
  "geometry": {"coordinates":[-95.191136,29.790537],"type":"Point"}
}