{
  "type": "Feature",
  "properties": {
    "iso:country":"US",
    "sg:address":"1333 E Belt Line Rd",
    "sg:city":"Coppell",
    "sg:classifiers":[
        {
            "category":"Personal",
            "type":"Services"
        }
    ],
    "sg:phone":"+1 972 284 0514",
    "sg:postcode":"75019",
    "sg:province":"TX",
    "sg:tags":[
        "towing"
    ],
    "wof:name":"Coppell Towing Service & Roadside Assistance",
    "wof:placetype":"venue"
},
  "geometry": {"coordinates":[-96.971293,32.955133],"type":"Point"}
}