{
  "type": "Feature",
  "properties": {
    "iso:country":"US",
    "sg:address":"4144 N Central Expy",
    "sg:city":"Dallas",
    "sg:classifiers":[
        {
            "category":"Insurance",
            "subcategory":"Insurance Agent",
            "type":"Services"
        }
    ],
    "sg:phone":"+1 214 515 9900",
    "sg:postcode":"75204",
    "sg:province":"TX",
    "wof:name":"State Farm Insurance",
    "wof:placetype":"venue"
},
  "geometry": {"coordinates":[-96.789068,32.815438],"type":"Point"}
}