{
  "type": "Feature",
  "properties": {
    "iso:country":"US",
    "sg:address":"408 Avondale St",
    "sg:city":"Houston",
    "sg:classifiers":[
        {
            "category":"Travel",
            "subcategory":"Hotels & Motels",
            "type":"Entertainment"
        }
    ],
    "sg:phone":"+1 713 520 0206",
    "sg:postcode":"77006",
    "sg:province":"TX",
    "sg:tags":[
        "operation"
    ],
    "wof:name":"Montrose Inn",
    "wof:placetype":"venue"
},
  "geometry": {"coordinates":[-95.387157,29.745348],"type":"Point"}
}