{
  "type": "Feature",
  "properties": {
    "iso:country":"US",
    "sg:address":"2207 N Conway Ave",
    "sg:city":"Mission",
    "sg:classifiers":[
        {
            "category":"Freight",
            "type":"Transportation"
        }
    ],
    "sg:phone":"+1 956 585 3412",
    "sg:postcode":"78572",
    "sg:province":"TX",
    "sg:tags":[
        "special",
        "general"
    ],
    "wof:name":"Best Little Warehouse In Texas",
    "wof:placetype":"venue"
},
  "geometry": {"coordinates":[-98.323688,26.227849],"type":"Point"}
}