{
  "type": "Feature",
  "properties": {
    "iso:country":"US",
    "sg:address":"508 Athol St",
    "sg:city":"San Juan",
    "sg:classifiers":[
        {
            "category":"Social Services",
            "subcategory":"Child Care",
            "type":"Services"
        }
    ],
    "sg:phone":"+1 956 781 9927",
    "sg:postcode":"78589",
    "sg:province":"TX",
    "sg:tags":[
        "day"
    ],
    "wof:name":"Lindas Lullaby Land",
    "wof:placetype":"venue"
},
  "geometry": {"coordinates":[-98.16148800000001,26.19763],"type":"Point"}
}