{
  "type": "Feature",
  "properties": {
    "iso:country":"US",
    "sg:address":"3953 Richmond Avenue",
    "sg:city":"Houston",
    "sg:classifiers":[
        {
            "category":"Restaurant",
            "type":"Food & Drink"
        }
    ],
    "sg:phone":"+1 713 599 1119",
    "sg:postcode":"77027",
    "sg:province":"TX",
    "sg:tags":[
        "kosher"
    ],
    "sg:website":"www.aromaclassique.com",
    "wof:name":"Aroma Classique",
    "wof:placetype":"venue"
},
  "geometry": {"coordinates":[-95.439971,29.732583],"type":"Point"}
}