{
  "type": "Feature",
  "properties": {
    "iso:country":"US",
    "sg:address":"1410 Dove Ave",
    "sg:city":"Mcallen",
    "sg:classifiers":[
        {
            "category":"Insurance",
            "subcategory":"Insurance Agent",
            "type":"Services"
        }
    ],
    "sg:phone":"+1 956 688 6226",
    "sg:postcode":"78504",
    "sg:province":"TX",
    "wof:name":"Kathryn F Mc Coy",
    "wof:placetype":"venue"
},
  "geometry": {"coordinates":[-98.226664,26.254516],"type":"Point"}
}