{
  "type": "Feature",
  "properties": {
    "iso:country":"US",
    "sg:address":"3121 Routh St",
    "sg:city":"Dallas",
    "sg:classifiers":[
        {
            "category":"Shopping",
            "subcategory":"Used Merchandise",
            "type":"Retail Goods"
        }
    ],
    "sg:phone":"+1 214 871 0225",
    "sg:postcode":"75201",
    "sg:province":"TX",
    "wof:name":"Adam & Eve Antiques",
    "wof:placetype":"venue"
},
  "geometry": {"coordinates":[-96.80749900000001,32.801285],"type":"Point"}
}