{
  "type": "Feature",
  "properties": {
    "iso:country":"US",
    "sg:address":"4626 Spruce St",
    "sg:city":"Flower Mound",
    "sg:classifiers":[
        {
            "category":"Building & Trades",
            "subcategory":"Construction",
            "type":"Services"
        }
    ],
    "sg:phone":"+1 972 724 0026",
    "sg:postcode":"75028",
    "sg:province":"TX",
    "sg:tags":[
        "concrete",
        "repair"
    ],
    "wof:name":"Gibbys Asphalt & Concrete",
    "wof:placetype":"venue"
},
  "geometry": {"coordinates":[-97.07374,33.048171],"type":"Point"}
}