{
  "type": "Feature",
  "properties": {
    "iso:country":"US",
    "sg:address":"7331 Kirkham Dr",
    "sg:city":"Dallas",
    "sg:classifiers":[
        {
            "category":"Building & Trades",
            "subcategory":"Construction",
            "type":"Services"
        }
    ],
    "sg:phone":"+1 972 380 5559",
    "sg:postcode":"75252",
    "sg:province":"TX",
    "sg:tags":[
        "hanging",
        "contractor"
    ],
    "wof:name":"King Painting LLC",
    "wof:placetype":"venue"
},
  "geometry": {"coordinates":[-96.77851699999999,32.996684],"type":"Point"}
}