{
  "type": "Feature",
  "properties": {
    "iso:country":"US",
    "sg:address":"8206 Debbie Gay Dr",
    "sg:city":"Houston",
    "sg:classifiers":[
        {
            "category":"Freight",
            "type":"Transportation"
        }
    ],
    "sg:phone":"+1 832 955 0500",
    "sg:postcode":"77040",
    "sg:province":"TX",
    "sg:tags":[
        "trucking"
    ],
    "wof:name":"Admiral Truck Svc",
    "wof:placetype":"venue"
},
  "geometry": {"coordinates":[-95.529579,29.891247],"type":"Point"}
}