{
  "type": "Feature",
  "properties": {
    "iso:country":"US",
    "sg:address":"2953 W Main St",
    "sg:city":"Henderson",
    "sg:classifiers":[
        {
            "category":"Place Of Worship",
            "subcategory":"Church",
            "type":"Public Place"
        },
        {
            "category":"Place Of Worship",
            "type":"Public Place"
        },
        {
            "category":"Organizations",
            "subcategory":"Religious Organization",
            "type":"Services"
        }
    ],
    "sg:phone":"+1 903 657 9379",
    "sg:postcode":"75652",
    "sg:province":"TX",
    "sg:tags":[
        "god",
        "god-independent",
        "churches-assemblies",
        "denomination",
        "churches-interdenominational",
        "churches-various"
    ],
    "wof:name":"Calvary Assembly Of God Church",
    "wof:placetype":"venue"
},
  "geometry": {"coordinates":[-94.83574400000001,32.149972],"type":"Point"}
}