{
  "type": "Feature",
  "properties": {
    "iso:country":"US",
    "sg:address":"3318 Malcolm X Blvd",
    "sg:city":"Dallas",
    "sg:classifiers":[
        {
            "category":"Professional",
            "subcategory":"Lawyer & Legal Services",
            "type":"Services"
        }
    ],
    "sg:phone":"+1 214 426 0420",
    "sg:postcode":"75215",
    "sg:province":"TX",
    "sg:tags":[
        "attorney"
    ],
    "wof:name":"David E Youngblood",
    "wof:placetype":"venue"
},
  "geometry": {"coordinates":[-96.7653,32.766524],"type":"Point"}
}