{
  "type": "Feature",
  "properties": {
    "iso:country":"US",
    "sg:address":"2914 Bay Hill Ct",
    "sg:city":"Harlingen",
    "sg:classifiers":[
        {
            "category":"Health Services",
            "subcategory":"Clinic",
            "type":"Services"
        }
    ],
    "sg:phone":"+1 956 428 3051",
    "sg:postcode":"78550",
    "sg:province":"TX",
    "sg:tags":[
        "home"
    ],
    "wof:name":"Rainbow Medical Svc",
    "wof:placetype":"venue"
},
  "geometry": {"coordinates":[-97.657259,26.176599],"type":"Point"}
}