{
  "type": "Feature",
  "properties": {
    "iso:country":"US",
    "sg:address":"2810 Colonial Dr",
    "sg:city":"Nacogdoches",
    "sg:classifiers":[
        {
            "category":"Organizations",
            "subcategory":"Community Association",
            "type":"Services"
        }
    ],
    "sg:phone":"+1 936 564 6838",
    "sg:postcode":"75965",
    "sg:province":"TX",
    "wof:name":"Delta Signa PI Alumni",
    "wof:placetype":"venue"
},
  "geometry": {"coordinates":[-94.63318099999999,31.629346],"type":"Point"}
}