{
  "type": "Feature",
  "properties": {
    "iso:country":"US",
    "sg:address":"110 I- 35 Svc Rd",
    "sg:city":"Round Rock",
    "sg:classifiers":[
        {
            "category":"Personal",
            "type":"Services"
        }
    ],
    "sg:phone":"+1 512 246 8700",
    "sg:postcode":"78681",
    "sg:province":"TX",
    "sg:tags":[
        "control",
        "weight"
    ],
    "wof:name":"Jenny Craig Weight Loss Ctr",
    "wof:placetype":"venue"
},
  "geometry": {"coordinates":[-97.68610200000001,30.508006],"type":"Point"}
}