{
  "type": "Feature",
  "properties": {
    "iso:country":"US",
    "sg:address":"5833 Misted Breeze Dr",
    "sg:city":"Plano",
    "sg:classifiers":[
        {
            "category":"Mining & Drilling",
            "type":"Manufacturing & Wholesale Goods"
        }
    ],
    "sg:phone":"+1 972 398 2118",
    "sg:postcode":"75093",
    "sg:province":"TX",
    "sg:tags":[
        "operator",
        "field",
        "oil"
    ],
    "wof:name":"Stevens, Rick & Associates",
    "wof:placetype":"venue"
},
  "geometry": {"coordinates":[-96.820977,33.05172],"type":"Point"}
}