{
  "type": "Feature",
  "properties": {
    "iso:country":"US",
    "sg:address":"515 Crockett St",
    "sg:city":"Amarillo",
    "sg:classifiers":[
        {
            "category":"Wholesale",
            "subcategory":"Plants",
            "type":"Manufacturing & Wholesale Goods"
        }
    ],
    "sg:phone":"+1 806 372 2301",
    "sg:postcode":"79106",
    "sg:province":"TX",
    "sg:tags":[
        "floral",
        "florist",
        "flower",
        "supply"
    ],
    "wof:name":"J & E Wholesale Floral Company",
    "wof:placetype":"venue"
},
  "geometry": {"coordinates":[-101.856741,35.210377],"type":"Point"}
}