{
  "type": "Feature",
  "properties": {
    "iso:country":"US",
    "sg:address":"8106 Begonia Blvd",
    "sg:city":"Highlands",
    "sg:classifiers":[
        {
            "category":"Home & Garden",
            "subcategory":"Furniture",
            "type":"Retail Goods"
        }
    ],
    "sg:phone":"+1 281 426 8442",
    "sg:postcode":"77562",
    "sg:province":"TX",
    "sg:tags":[
        "store"
    ],
    "wof:name":"J J Furniture",
    "wof:placetype":"venue"
},
  "geometry": {"coordinates":[-95.021444,29.814092],"type":"Point"}
}