{
  "type": "Feature",
  "properties": {
    "iso:country":"US",
    "sg:address":"3503 Elgin St",
    "sg:city":"Houston",
    "sg:classifiers":[
        {
            "category":"Shopping",
            "subcategory":"Books",
            "type":"Retail Goods"
        }
    ],
    "sg:postcode":"77004",
    "sg:province":"TX",
    "sg:website":"www.thecollegestore.com/rho",
    "wof:name":"The College Store",
    "wof:placetype":"venue"
},
  "geometry": {"coordinates":[-95.350346,29.728034],"type":"Point"}
}