{
  "type": "Feature",
  "properties": {
    "iso:country":"US",
    "sg:address":"5900 NE 23rd Ave",
    "sg:city":"Amarillo",
    "sg:classifiers":[
        {
            "category":"Freight",
            "type":"Transportation"
        }
    ],
    "sg:phone":"+1 806 383 9898",
    "sg:postcode":"79107",
    "sg:province":"TX",
    "sg:tags":[
        "operator",
        "trucking"
    ],
    "wof:name":"K Truck Lines Inc",
    "wof:placetype":"venue"
},
  "geometry": {"coordinates":[-101.76787400000001,35.235917],"type":"Point"}
}