{
  "type": "Feature",
  "properties": {
    "iso:country":"US",
    "sg:address":"951 Cincinnati Ave",
    "sg:city":"San Antonio",
    "sg:classifiers":[
        {
            "category":"Food & Beverages",
            "subcategory":"Bakery",
            "type":"Retail Goods"
        }
    ],
    "sg:phone":"+1 210 733 1025",
    "sg:postcode":"78201",
    "sg:province":"TX",
    "wof:name":"Buono Dolce",
    "wof:placetype":"venue"
},
  "geometry": {"coordinates":[-98.52564700000001,29.449705],"type":"Point"}
}