{
  "type": "Feature",
  "properties": {
    "iso:country":"US",
    "sg:address":"1206 E Live Oak St",
    "sg:city":"Austin",
    "sg:classifiers":[
        {
            "category":"Social Services",
            "subcategory":"Job Training",
            "type":"Services"
        }
    ],
    "sg:phone":"+1 512 326 9300",
    "sg:postcode":"78704",
    "sg:province":"TX",
    "sg:tags":[
        "consultant"
    ],
    "wof:name":"Human Excellence",
    "wof:placetype":"venue"
},
  "geometry": {"coordinates":[-97.74363099999999,30.236501],"type":"Point"}
}