{
  "type": "Feature",
  "properties": {
    "iso:country":"US",
    "sg:address":"1710 Co Rd 1320",
    "sg:city":"Morton",
    "sg:classifiers":[
        {
            "category":"Real Estate",
            "subcategory":"Real Estate Operator",
            "type":"Services"
        }
    ],
    "sg:phone":"+1 806 933 4444",
    "sg:postcode":"79320",
    "sg:province":"TX",
    "sg:tags":[
        "property",
        "lessor"
    ],
    "wof:name":"Jo Ann Autry",
    "wof:placetype":"venue"
},
  "geometry": {"coordinates":[-102.747978,33.845699],"type":"Point"}
}