{
  "type": "Feature",
  "properties": {
    "iso:country":"US",
    "sg:address":"11227 Goodnight Ln",
    "sg:city":"Dallas",
    "sg:classifiers":[
        {
            "category":"Manufacturing",
            "subcategory":"Tools & Machinery",
            "type":"Manufacturing & Wholesale Goods"
        }
    ],
    "sg:phone":"+1 972 247 2674",
    "sg:postcode":"75229",
    "sg:province":"TX",
    "sg:tags":[
        "machine",
        "accessory",
        "mfg"
    ],
    "wof:name":"J R Precision Tooling",
    "wof:placetype":"venue"
},
  "geometry": {"coordinates":[-96.901878,32.889709],"type":"Point"}
}