{
  "type": "Feature",
  "properties": {
    "iso:country":"US",
    "sg:address":"10607 Pluchea Cove",
    "sg:city":"Austin",
    "sg:classifiers":[
        {
            "category":"Professional",
            "subcategory":"Business Services",
            "type":"Services"
        }
    ],
    "sg:phone":"+1 512 821 6582",
    "sg:postcode":"78733",
    "sg:province":"TX",
    "wof:name":"Verification Technologies Inc",
    "wof:placetype":"venue"
},
  "geometry": {"coordinates":[-97.899151,30.311269],"type":"Point"}
}