{
  "type": "Feature",
  "properties": {
    "iso:country":"US",
    "sg:address":"2126 McDonald Ln",
    "sg:city":"Mansfield",
    "sg:classifiers":[
        {
            "category":"Building & Trades",
            "subcategory":"Landscaping Services",
            "type":"Services"
        }
    ],
    "sg:phone":"+1 817 477 1124",
    "sg:postcode":"76063",
    "sg:province":"TX",
    "wof:name":"Davids Stump Removal",
    "wof:placetype":"venue"
},
  "geometry": {"coordinates":[-97.17707900000001,32.585359],"type":"Point"}
}