{
  "type": "Feature",
  "properties": {
    "iso:country":"US",
    "sg:address":"517 W Walnut St",
    "sg:city":"Garland",
    "sg:classifiers":[
        {
            "category":"Manufacturing",
            "subcategory":"Tools & Machinery",
            "type":"Manufacturing & Wholesale Goods"
        }
    ],
    "sg:phone":"+1 972 276 5866",
    "sg:postcode":"75040",
    "sg:province":"TX",
    "sg:tags":[
        "machine",
        "shop"
    ],
    "wof:name":"Kimro Products",
    "wof:placetype":"venue"
},
  "geometry": {"coordinates":[-96.636471,32.916485],"type":"Point"}
}