{
  "type": "Feature",
  "properties": {
    "iso:country":"US",
    "sg:address":"3236 Reagan Dr",
    "sg:city":"Fort Worth",
    "sg:classifiers":[
        {
            "category":"Building & Trades",
            "subcategory":"Construction",
            "type":"Services"
        }
    ],
    "sg:phone":"+1 817 946 1735",
    "sg:postcode":"76116",
    "sg:province":"TX",
    "sg:tags":[
        "hanging",
        "contractor"
    ],
    "wof:name":"Rockwell Construction",
    "wof:placetype":"venue"
},
  "geometry": {"coordinates":[-97.447716,32.726464],"type":"Point"}
}