{
  "type": "Feature",
  "properties": {
    "iso:country":"US",
    "sg:address":"3985 Parker Rd",
    "sg:city":"Wylie",
    "sg:classifiers":[
        {
            "category":"Restaurant",
            "type":"Food & Drink"
        }
    ],
    "sg:phone":"+1 972 429 0729",
    "sg:postcode":"75098",
    "sg:province":"TX",
    "sg:tags":[
        "cafe"
    ],
    "wof:name":"Lakeway Breakfast Cafe",
    "wof:placetype":"venue"
},
  "geometry": {"coordinates":[-96.56805900000001,33.051779],"type":"Point"}
}