{
  "type": "Feature",
  "properties": {
    "iso:country":"US",
    "sg:address":"14450 Fm 2100 Rd",
    "sg:city":"Crosby",
    "sg:classifiers":[
        {
            "category":"Utilities",
            "subcategory":"Mobile Phone",
            "type":"Services"
        }
    ],
    "sg:phone":"+1 281 462 7141",
    "sg:postcode":"77532",
    "sg:province":"TX",
    "sg:tags":[
        "telephone",
        "cellular"
    ],
    "wof:name":"Ams Wireless",
    "wof:placetype":"venue"
},
  "geometry": {"coordinates":[-95.063429,29.89616],"type":"Point"}
}