{
  "type": "Feature",
  "properties": {
    "iso:country":"US",
    "sg:address":"310 E Davis St",
    "sg:city":"Conroe",
    "sg:classifiers":[
        {
            "category":"Government",
            "subcategory":"Court House",
            "type":"Public Place"
        }
    ],
    "sg:phone":"+1 936 756 0420",
    "sg:postcode":"77301",
    "sg:province":"TX",
    "sg:tags":[
        "state",
        "counsel"
    ],
    "wof:name":"Criminal Justice Dept",
    "wof:placetype":"venue"
},
  "geometry": {"coordinates":[-95.452814,30.313201],"type":"Point"}
}