{
  "type": "Feature",
  "properties": {
    "iso:country":"US",
    "sg:address":"85 Penn Ave",
    "sg:city":"Victoria",
    "sg:classifiers":[
        {
            "category":"Building & Trades",
            "subcategory":"Construction",
            "type":"Services"
        }
    ],
    "sg:phone":"+1 361 576 2352",
    "sg:postcode":"77904",
    "sg:province":"TX",
    "sg:tags":[
        "house"
    ],
    "wof:name":"Morris Builder",
    "wof:placetype":"venue"
},
  "geometry": {"coordinates":[-97.03234,28.919721],"type":"Point"}
}