{
  "type": "Feature",
  "properties": {
    "iso:country":"US",
    "sg:address":"6626 W 43rd St",
    "sg:city":"Houston",
    "sg:classifiers":[
        {
            "category":"Real Estate",
            "subcategory":"Real Estate Agent",
            "type":"Services"
        }
    ],
    "sg:phone":"+1 713 329 9860",
    "sg:postcode":"77092",
    "sg:province":"TX",
    "wof:name":"Contreras Group",
    "wof:placetype":"venue"
},
  "geometry": {"coordinates":[-95.49032699999999,29.833182],"type":"Point"}
}