{
  "type": "Feature",
  "properties": {
    "iso:country":"US",
    "sg:address":"11645 Angus Rd Ste 2",
    "sg:city":"Austin",
    "sg:classifiers":[
        {
            "category":"Health Services",
            "subcategory":"Chiropractor",
            "type":"Services"
        }
    ],
    "sg:phone":"+1 512 231 8822",
    "sg:postcode":"78759",
    "sg:province":"TX",
    "sg:website":"www.austinchiro.com",
    "wof:name":"Chiropractic Solutions",
    "wof:placetype":"venue"
},
  "geometry": {"coordinates":[-97.74351799999999,30.415184],"type":"Point"}
}