{
  "type": "Feature",
  "properties": {
    "iso:country":"US",
    "sg:address":"7018 Pembrough Ln",
    "sg:city":"Katy",
    "sg:classifiers":[
        {
            "category":"Wholesale",
            "subcategory":"Furniture",
            "type":"Manufacturing & Wholesale Goods"
        }
    ],
    "sg:phone":"+1 281 395 4671",
    "sg:postcode":"77494",
    "sg:province":"TX",
    "wof:name":"Command & Control Environments",
    "wof:placetype":"venue"
},
  "geometry": {"coordinates":[-95.779673,29.703733],"type":"Point"}
}