{
  "type": "Feature",
  "properties": {
    "iso:country":"US",
    "sg:address":"4920 Cullen Blvd",
    "sg:city":"Houston",
    "sg:classifiers":[
        {
            "category":"Professional",
            "subcategory":"Management & Consulting",
            "type":"Services"
        }
    ],
    "sg:phone":"+1 713 523 5006",
    "sg:postcode":"77004",
    "sg:province":"TX",
    "sg:tags":[
        "business"
    ],
    "wof:name":"Monarch Child Development Ctr",
    "wof:placetype":"venue"
},
  "geometry": {"coordinates":[-95.349228,29.716272],"type":"Point"}
}