{
  "type": "Feature",
  "properties": {
    "iso:country":"US",
    "sg:address":"15299 N I- 35",
    "sg:city":"Salado",
    "sg:classifiers":[
        {
            "category":"Social Services",
            "subcategory":"Child Care",
            "type":"Services"
        }
    ],
    "sg:phone":"+1 254 947 1153",
    "sg:postcode":"76537",
    "sg:province":"TX",
    "wof:name":"Kids' Zone Inc",
    "wof:placetype":"venue"
},
  "geometry": {"coordinates":[-97.590588,30.855033],"type":"Point"}
}