{
  "type": "Feature",
  "properties": {
    "iso:country":"US",
    "sg:address":"3325 Fondren Rd",
    "sg:city":"Houston",
    "sg:classifiers":[
        {
            "category":"Retail",
            "subcategory":"Veterinary Services",
            "type":"Services"
        }
    ],
    "sg:phone":"+1 713 781 3424",
    "sg:postcode":"77063",
    "sg:province":"TX",
    "sg:tags":[
        "veterinarian"
    ],
    "wof:name":"Ford Leo DVM",
    "wof:placetype":"venue"
},
  "geometry": {"coordinates":[-95.52040100000001,29.728701],"type":"Point"}
}