{
  "type": "Feature",
  "properties": {
    "iso:country":"US",
    "sg:address":"423 W Dickson Ave",
    "sg:city":"San Antonio",
    "sg:classifiers":[
        {
            "category":"Professional",
            "subcategory":"Business Services",
            "type":"Services"
        }
    ],
    "sg:phone":"+1 210 923 1682",
    "sg:postcode":"78214",
    "sg:province":"TX",
    "wof:name":"Herrera Drafting Svcs",
    "wof:placetype":"venue"
},
  "geometry": {"coordinates":[-98.503415,29.35946],"type":"Point"}
}