{
  "type": "Feature",
  "properties": {
    "iso:country":"US",
    "sg:address":"324 S Main St",
    "sg:city":"Highlands",
    "sg:classifiers":[
        {
            "category":"Wholesale",
            "subcategory":"Auto Parts",
            "type":"Manufacturing & Wholesale Goods"
        }
    ],
    "sg:phone":"+1 281 426 8786",
    "sg:postcode":"77562",
    "sg:province":"TX",
    "sg:tags":[
        "tire"
    ],
    "wof:name":"Luna's Tire Shop",
    "wof:placetype":"venue"
},
  "geometry": {"coordinates":[-95.05729700000001,29.813499],"type":"Point"}
}