{
  "type": "Feature",
  "properties": {
    "iso:country":"US",
    "sg:address":"4687 World Houston Pkwy",
    "sg:city":"Houston",
    "sg:classifiers":[
        {
            "category":"Freight",
            "type":"Transportation"
        }
    ],
    "sg:phone":"+1 281 987 9200",
    "sg:postcode":"77032",
    "sg:province":"TX",
    "sg:website":"www.expeditors.com",
    "wof:name":"Expeditors International",
    "wof:placetype":"venue"
},
  "geometry": {"coordinates":[-95.326424,29.944451],"type":"Point"}
}