{
  "type": "Feature",
  "properties": {
    "iso:country":"US",
    "sg:address":"1607 Brushy View Cove",
    "sg:city":"Austin",
    "sg:classifiers":[
        {
            "category":"Professional",
            "subcategory":"Business Services",
            "type":"Services"
        }
    ],
    "sg:phone":"+1 512 491 5377",
    "sg:postcode":"78754",
    "sg:province":"TX",
    "wof:name":"Facilities Resource Inc",
    "wof:placetype":"venue"
},
  "geometry": {"coordinates":[-97.66337,30.36613],"type":"Point"}
}