{
  "type": "Feature",
  "properties": {
    "iso:country":"US",
    "sg:address":"1401 Drexel Dr",
    "sg:city":"Katy",
    "sg:classifiers":[
        {
            "category":"Personal",
            "subcategory":"Beauty Salon",
            "type":"Services"
        }
    ],
    "sg:phone":"+1 281 391 7985",
    "sg:postcode":"77493",
    "sg:province":"TX",
    "wof:name":"Hair Master Salon",
    "wof:placetype":"venue"
},
  "geometry": {"coordinates":[-95.81652,29.791777],"type":"Point"}
}