{
  "type": "Feature",
  "properties": {
    "iso:country":"US",
    "sg:address":"12215 Ortega St",
    "sg:city":"Dallas",
    "sg:classifiers":[
        {
            "category":"Shopping",
            "subcategory":"Gifts & Souvenirs",
            "type":"Retail Goods"
        }
    ],
    "sg:phone":"+1 972 286 8898",
    "sg:postcode":"75253",
    "sg:province":"TX",
    "wof:name":"Maxwells Custom Frames",
    "wof:placetype":"venue"
},
  "geometry": {"coordinates":[-96.59522200000001,32.698102],"type":"Point"}
}