{
  "type": "Feature",
  "properties": {
    "iso:country":"US",
    "sg:address":"601 Ferris Ave",
    "sg:city":"Waxahachie",
    "sg:classifiers":[
        {
            "category":"Wholesale",
            "subcategory":"Electrical",
            "type":"Manufacturing & Wholesale Goods"
        }
    ],
    "sg:phone":"+1 972 938 1980",
    "sg:postcode":"75165",
    "sg:province":"TX",
    "sg:tags":[
        "radio"
    ],
    "wof:name":"Comtex Communications",
    "wof:placetype":"venue"
},
  "geometry": {"coordinates":[-96.846993,32.393611],"type":"Point"}
}