{
  "type": "Feature",
  "properties": {
    "iso:country":"US",
    "sg:address":"3659 Glen Haven Blvd",
    "sg:city":"Houston",
    "sg:classifiers":[
        {
            "category":"Sports & Exercise",
            "subcategory":"Golf",
            "type":"Entertainment"
        }
    ],
    "sg:phone":"+1 713 432 0064",
    "sg:postcode":"77025",
    "sg:province":"TX",
    "wof:name":"Exceptional Golf",
    "wof:placetype":"venue"
},
  "geometry": {"coordinates":[-95.434196,29.7015],"type":"Point"}
}