{
  "type": "Feature",
  "properties": {
    "iso:country":"US",
    "sg:address":"27207 State Hwy 249",
    "sg:city":"Tomball",
    "sg:classifiers":[
        {
            "category":"Autos & Motor Vehicles",
            "subcategory":"Automobile Sales",
            "type":"Retail Goods"
        }
    ],
    "sg:phone":"+1 281 255 3090",
    "sg:postcode":"77375",
    "sg:province":"TX",
    "sg:tags":[
        "car",
        "used",
        "dealer"
    ],
    "wof:name":"Ham's Trucks Plus Inc",
    "wof:placetype":"venue"
},
  "geometry": {"coordinates":[-95.62536,30.070872],"type":"Point"}
}