{
  "type": "Feature",
  "properties": {
    "iso:country":"US",
    "sg:address":"2229 Forest Hills Rd",
    "sg:city":"Grapevine",
    "sg:classifiers":[
        {
            "category":"Wholesale",
            "subcategory":"Electrical",
            "type":"Manufacturing & Wholesale Goods"
        }
    ],
    "sg:phone":"+1 817 329 5362",
    "sg:postcode":"76051",
    "sg:province":"TX",
    "sg:tags":[
        "electronic"
    ],
    "wof:name":"Creative Video Products",
    "wof:placetype":"venue"
},
  "geometry": {"coordinates":[-97.103134,32.972069],"type":"Point"}
}