{
  "type": "Feature",
  "properties": {
    "iso:country":"US",
    "sg:address":"815 Sarah Anne St",
    "sg:city":"Nacogdoches",
    "sg:classifiers":[
        {
            "category":"Professional",
            "subcategory":"Business Services",
            "type":"Services"
        }
    ],
    "sg:phone":"+1 936 462 1414",
    "sg:postcode":"75965",
    "sg:province":"TX",
    "wof:name":"Mary Adams",
    "wof:placetype":"venue"
},
  "geometry": {"coordinates":[-94.6452,31.639269],"type":"Point"}
}