{
  "type": "Feature",
  "properties": {
    "iso:country":"US",
    "sg:address":"12805 Silver Creek Dr",
    "sg:city":"Austin",
    "sg:classifiers":[
        {
            "category":"Building & Trades",
            "subcategory":"Construction",
            "type":"Services"
        }
    ],
    "sg:phone":"+1 512 244 7552",
    "sg:postcode":"78727",
    "sg:province":"TX",
    "sg:tags":[
        "repairing",
        "remodeling",
        "contractor"
    ],
    "wof:name":"C & C Repair & Remodeling Inc",
    "wof:placetype":"venue"
},
  "geometry": {"coordinates":[-97.713115,30.428989],"type":"Point"}
}