{
  "type": "Feature",
  "properties": {
    "iso:country":"US",
    "sg:address":"2028 Grand Cayman Way",
    "sg:city":"Mesquite",
    "sg:classifiers":[
        {
            "category":"Farming",
            "subcategory":"Nursery",
            "type":"Manufacturing & Wholesale Goods"
        }
    ],
    "sg:phone":"+1 972 289 2389",
    "sg:postcode":"75149",
    "sg:province":"TX",
    "sg:tags":[
        "tree",
        "grower",
        "nursery-wholesale",
        "nurseries-plants"
    ],
    "wof:name":"Donna Holmes Flowers",
    "wof:placetype":"venue"
},
  "geometry": {"coordinates":[-96.570728,32.757631],"type":"Point"}
}