{
  "type": "Feature",
  "properties": {
    "iso:country":"US",
    "sg:address":"1450 State Hwy 146",
    "sg:city":"Dickinson",
    "sg:classifiers":[
        {
            "category":"Utilities",
            "subcategory":"Refuse",
            "type":"Services"
        }
    ],
    "sg:phone":"+1 281 559 2641",
    "sg:postcode":"77539",
    "sg:province":"TX",
    "sg:tags":[
        "system"
    ],
    "wof:name":"K A B Recycling",
    "wof:placetype":"venue"
},
  "geometry": {"coordinates":[-94.978872,29.471094],"type":"Point"}
}