{
  "type": "Feature",
  "properties": {
    "iso:country":"US",
    "sg:address":"6501 E Lancaster Ave",
    "sg:city":"Fort Worth",
    "sg:classifiers":[
        {
            "category":"Real Estate",
            "subcategory":"Real Estate Agent",
            "type":"Services"
        }
    ],
    "sg:phone":"+1 817 451 6660",
    "sg:postcode":"76112",
    "sg:province":"TX",
    "wof:name":"Deborah Williams & Assoc Rlty",
    "wof:placetype":"venue"
},
  "geometry": {"coordinates":[-97.218237,32.732579],"type":"Point"}
}