{
  "type": "Feature",
  "properties": {
    "iso:country":"US",
    "sg:address":"209 E Market St",
    "sg:city":"Sinton",
    "sg:classifiers":[
        {
            "category":"Health Services",
            "subcategory":"Health Practitioner",
            "type":"Services"
        }
    ],
    "sg:phone":"+1 361 364 3533",
    "sg:postcode":"78387",
    "sg:province":"TX",
    "wof:name":"Home Health Care Solutions",
    "wof:placetype":"venue"
},
  "geometry": {"coordinates":[-97.508109,28.037856],"type":"Point"}
}