{
  "type": "Feature",
  "properties": {
    "iso:country":"US",
    "sg:address":"1367 Siesta Dr",
    "sg:city":"Eagle Pass",
    "sg:classifiers":[
        {
            "category":"Retail",
            "subcategory":"Portrait Studio",
            "type":"Services"
        }
    ],
    "sg:phone":"+1 830 773 5497",
    "sg:postcode":"78852",
    "sg:province":"TX",
    "sg:tags":[
        "photo"
    ],
    "wof:name":"Lopez Photo Studio",
    "wof:placetype":"venue"
},
  "geometry": {"coordinates":[-100.493943,28.751633],"type":"Point"}
}