{
  "type": "Feature",
  "properties": {
    "iso:country":"US",
    "sg:address":"6050 Autumn Hills Dr",
    "sg:city":"Fort Worth",
    "sg:classifiers":[
        {
            "category":"Wholesale",
            "subcategory":"Machinery & Supplies",
            "type":"Manufacturing & Wholesale Goods"
        }
    ],
    "sg:phone":"+1 817 516 7037",
    "sg:postcode":"76140",
    "sg:province":"TX",
    "sg:tags":[
        "shop",
        "equipment",
        "establishment",
        "beauty"
    ],
    "wof:name":"Lott Distributing",
    "wof:placetype":"venue"
},
  "geometry": {"coordinates":[-97.257417,32.59005],"type":"Point"}
}