{
  "type": "Feature",
  "properties": {
    "iso:country":"US",
    "sg:address":"11627 Landsdowne Dr",
    "sg:city":"Houston",
    "sg:classifiers":[
        {
            "category":"Travel",
            "subcategory":"Travel Agent",
            "type":"Entertainment"
        }
    ],
    "sg:phone":"+1 713 729 3301",
    "sg:postcode":"77035",
    "sg:province":"TX",
    "sg:tags":[
        "agency"
    ],
    "wof:name":"Ja Travel Services",
    "wof:placetype":"venue"
},
  "geometry": {"coordinates":[-95.48670199999999,29.650737],"type":"Point"}
}