{
  "type": "Feature",
  "properties": {
    "iso:country":"US",
    "sg:address":"1216 E Dulse St",
    "sg:city":"Tyler",
    "sg:classifiers":[
        {
            "category":"Shopping",
            "subcategory":"Used Merchandise",
            "type":"Retail Goods"
        }
    ],
    "sg:phone":"+1 903 597 3439",
    "sg:postcode":"75701",
    "sg:province":"TX",
    "wof:name":"Clipper Ship Antiques",
    "wof:placetype":"venue"
},
  "geometry": {"coordinates":[-95.286394,32.318687],"type":"Point"}
}