{
  "type": "Feature",
  "properties": {
    "iso:country":"US",
    "sg:address":"5006 Ave Q",
    "sg:city":"Galveston",
    "sg:classifiers":[
        {
            "category":"Professional",
            "type":"Services"
        }
    ],
    "sg:phone":"+1 409 744 8888",
    "sg:postcode":"77551",
    "sg:province":"TX",
    "wof:name":"Ktm Electronics",
    "wof:placetype":"venue"
},
  "geometry": {"coordinates":[-94.82074,29.282083],"type":"Point"}
}