{
  "type": "Feature",
  "properties": {
    "iso:country":"US",
    "sg:address":"816 Old Pidcoke Rd",
    "sg:city":"Gatesville",
    "sg:classifiers":[
        {
            "category":"Professional",
            "type":"Services"
        }
    ],
    "sg:phone":"+1 254 865 7736",
    "sg:postcode":"76528",
    "sg:province":"TX",
    "sg:tags":[
        "specialty",
        "mfg"
    ],
    "wof:name":"Patterson Metal Art Works",
    "wof:placetype":"venue"
},
  "geometry": {"coordinates":[-97.779848,31.424029],"type":"Point"}
}