{
  "type": "Feature",
  "properties": {
    "iso:country":"US",
    "sg:address":"500 Ash Ave",
    "sg:city":"Mcallen",
    "sg:classifiers":[
        {
            "category":"Travel",
            "subcategory":"Hotels & Motels",
            "type":"Entertainment"
        }
    ],
    "sg:phone":"+1 956 682 2419",
    "sg:postcode":"78501",
    "sg:province":"TX",
    "wof:name":"Garden Inn East",
    "wof:placetype":"venue"
},
  "geometry": {"coordinates":[-98.222466,26.202438],"type":"Point"}
}