{
  "type": "Feature",
  "properties": {
    "iso:country":"US",
    "sg:address":"633 W Brentwood St",
    "sg:city":"Channelview",
    "sg:classifiers":[
        {
            "category":"Education",
            "subcategory":"Special Training",
            "type":"Public Place"
        }
    ],
    "sg:phone":"+1 281 452 2844",
    "sg:postcode":"77530",
    "sg:province":"TX",
    "wof:name":"Allens Music Express",
    "wof:placetype":"venue"
},
  "geometry": {"coordinates":[-95.145814,29.783867],"type":"Point"}
}