{
  "type": "Feature",
  "properties": {
    "iso:country":"US",
    "sg:address":"4410 Morrison St",
    "sg:city":"Greenville",
    "sg:classifiers":[
        {
            "category":"Wholesale",
            "subcategory":"Stationery",
            "type":"Manufacturing & Wholesale Goods"
        }
    ],
    "sg:phone":"+1 903 454 6413",
    "sg:postcode":"75401",
    "sg:province":"TX",
    "sg:tags":[
        "supply"
    ],
    "wof:name":"Mrs BS Scrapbooking Heart",
    "wof:placetype":"venue"
},
  "geometry": {"coordinates":[-96.129476,33.163102],"type":"Point"}
}