{
  "type": "Feature",
  "properties": {
    "iso:country":"US",
    "sg:address":"9718 Katy Fwy",
    "sg:city":"Houston",
    "sg:classifiers":[
        {
            "category":"Recreation",
            "subcategory":"Dog Park",
            "type":"Entertainment"
        },
        {
            "category":"Farming",
            "subcategory":"Fish & Marine Products",
            "type":"Manufacturing & Wholesale Goods"
        },
        {
            "category":"Shopping",
            "subcategory":"Pets & Pet Supplies",
            "type":"Retail Goods"
        },
        {
            "category":"Museum",
            "subcategory":"Aquarium",
            "type":"Entertainment"
        },
        {
            "category":"Retail",
            "subcategory":"Animal Services",
            "type":"Services"
        }
    ],
    "sg:phone":"+1 713 932 9909",
    "sg:postcode":"77055",
    "sg:province":"TX",
    "sg:tags":[
        "training",
        "food",
        "tropical",
        "grooming",
        "bird",
        "store"
    ],
    "sg:website":"www.petsmart.com",
    "wof:name":"PetSmart",
    "wof:placetype":"venue"
},
  "geometry": {"coordinates":[-95.53264299999999,29.785008],"type":"Point"}
}