{
  "type": "Feature",
  "properties": {
    "iso:country":"US",
    "sg:address":"7510 Tezel Rd",
    "sg:city":"San Antonio",
    "sg:classifiers":[
        {
            "category":"Building & Trades",
            "subcategory":"Construction",
            "type":"Services"
        }
    ],
    "sg:phone":"+1 210 523 1138",
    "sg:postcode":"78250",
    "sg:province":"TX",
    "sg:tags":[
        "carport"
    ],
    "wof:name":"Carports Etc",
    "wof:placetype":"venue"
},
  "geometry": {"coordinates":[-98.662251,29.507899],"type":"Point"}
}