{
  "type": "Feature",
  "properties": {
    "iso:country":"US",
    "sg:address":"814 Hackberry Ct",
    "sg:city":"Brownsville",
    "sg:classifiers":[
        {
            "category":"Travel",
            "subcategory":"Travel Agent",
            "type":"Entertainment"
        }
    ],
    "sg:phone":"+1 956 546 5599",
    "sg:postcode":"78520",
    "sg:province":"TX",
    "sg:tags":[
        "operator",
        "tour"
    ],
    "wof:name":"Birds Galore Inc",
    "wof:placetype":"venue"
},
  "geometry": {"coordinates":[-97.509047,25.928578],"type":"Point"}
}