{
  "type": "Feature",
  "properties": {
    "iso:country":"US",
    "sg:address":"333 Innsdale Dr",
    "sg:city":"Houston",
    "sg:classifiers":[
        {
            "category":"Building & Trades",
            "subcategory":"Construction",
            "type":"Services"
        }
    ],
    "sg:phone":"+1 281 495 5819",
    "sg:postcode":"77076",
    "sg:province":"TX",
    "sg:tags":[
        "hanging",
        "contractor"
    ],
    "wof:name":"Ward Painting Inc",
    "wof:placetype":"venue"
},
  "geometry": {"coordinates":[-95.36829,29.851032],"type":"Point"}
}