{
  "type": "Feature",
  "properties": {
    "iso:country":"US",
    "sg:address":"5944 Zangs Dr",
    "sg:city":"San Antonio",
    "sg:classifiers":[
        {
            "category":"Wholesale",
            "subcategory":"Hardware",
            "type":"Manufacturing & Wholesale Goods"
        }
    ],
    "sg:phone":"+1 210 587 3456",
    "sg:postcode":"78238",
    "sg:province":"TX",
    "sg:tags":[
        "plumbing"
    ],
    "wof:name":"Texson Water Ltd",
    "wof:placetype":"venue"
},
  "geometry": {"coordinates":[-98.603613,29.479271],"type":"Point"}
}