{
  "type": "Feature",
  "properties": {
    "iso:country":"US",
    "sg:address":"255 Elm Lodge Dr",
    "sg:city":"Kingsland",
    "sg:classifiers":[
        {
            "category":"Retail",
            "subcategory":"Repair Shop",
            "type":"Services"
        }
    ],
    "sg:phone":"+1 325 388 3365",
    "sg:postcode":"78639",
    "sg:province":"TX",
    "wof:name":"Lyns Frame Shoppe",
    "wof:placetype":"venue"
},
  "geometry": {"coordinates":[-98.44414999999999,30.669298],"type":"Point"}
}