{
  "type": "Feature",
  "properties": {
    "iso:country":"US",
    "sg:address":"13929 Smith Rd",
    "sg:city":"Humble",
    "sg:classifiers":[
        {
            "category":"Utilities",
            "subcategory":"Refuse",
            "type":"Services"
        },
        {
            "category":"Utilities",
            "subcategory":"Recycling",
            "type":"Services"
        }
    ],
    "sg:phone":"+1 281 441 9055",
    "sg:postcode":"77396",
    "sg:province":"TX",
    "sg:tags":[
        "rubbish",
        "collection",
        "garbage",
        "removal"
    ],
    "wof:name":"Eastex Trash Service",
    "wof:placetype":"venue"
},
  "geometry": {"coordinates":[-95.28742800000001,29.921284],"type":"Point"}
}