{
  "type": "Feature",
  "properties": {
    "iso:country":"US",
    "sg:address":"4109 Kingswick Dr",
    "sg:city":"Arlington",
    "sg:classifiers":[
        {
            "category":"Retail",
            "subcategory":"Auto Repair",
            "type":"Services"
        }
    ],
    "sg:phone":"+1 817 239 4563",
    "sg:postcode":"76016",
    "sg:province":"TX",
    "sg:tags":[
        "automotive"
    ],
    "wof:name":"Slipstream Dynamics",
    "wof:placetype":"venue"
},
  "geometry": {"coordinates":[-97.172988,32.694988],"type":"Point"}
}