{
  "type": "Feature",
  "properties": {
    "iso:country":"US",
    "sg:address":"6727 Churchill Way",
    "sg:city":"Dallas",
    "sg:classifiers":[
        {
            "category":"Real Estate",
            "subcategory":"Developer",
            "type":"Services"
        }
    ],
    "sg:phone":"+1 972 385 1275",
    "sg:postcode":"75230",
    "sg:province":"TX",
    "wof:name":"Downs of Hillcrest",
    "wof:placetype":"venue"
},
  "geometry": {"coordinates":[-96.78927899999999,32.917148],"type":"Point"}
}