{
  "type": "Feature",
  "properties": {
    "iso:country":"US",
    "sg:address":"9290 Woodfair Dr",
    "sg:city":"Houston",
    "sg:classifiers":[
        {
            "category":"Building & Trades",
            "subcategory":"Construction",
            "type":"Services"
        }
    ],
    "sg:phone":"+1 713 773 1153",
    "sg:postcode":"77036",
    "sg:province":"TX",
    "sg:tags":[
        "house"
    ],
    "wof:name":"Villatoros Painting & Remodel",
    "wof:placetype":"venue"
},
  "geometry": {"coordinates":[-95.551884,29.680755],"type":"Point"}
}