{
  "type": "Feature",
  "properties": {
    "iso:country":"US",
    "sg:address":"4031 Saratoga Blvd",
    "sg:city":"Corpus Christi",
    "sg:classifiers":[
        {
            "category":"Restaurant",
            "type":"Food & Drink"
        }
    ],
    "sg:menulink":"http://www.allmenus.com/tx/corpus-christi/202522-mcdonalds/menu/",
    "sg:postcode":"78413",
    "sg:province":"TX",
    "sg:tags":[
        "burger",
        "american"
    ],
    "wof:name":"McDonald's",
    "wof:placetype":"venue"
},
  "geometry": {"coordinates":[-97.411379,27.698889],"type":"Point"}
}