{
  "type": "Feature",
  "properties": {
    "iso:country":"US",
    "sg:address":"1120 Security Dr",
    "sg:city":"Dallas",
    "sg:classifiers":[
        {
            "category":"Freight",
            "type":"Transportation"
        }
    ],
    "sg:phone":"+1 214 630 7227",
    "sg:postcode":"75247",
    "sg:province":"TX",
    "sg:tags":[
        "delivery"
    ],
    "wof:name":"Purnell Furniture Svc",
    "wof:placetype":"venue"
},
  "geometry": {"coordinates":[-96.85565,32.803776],"type":"Point"}
}