{
  "type": "Feature",
  "properties": {
    "iso:country":"US",
    "sg:address":"3701 Apollo Ln",
    "sg:city":"San Angelo",
    "sg:classifiers":[
        {
            "category":"Professional",
            "subcategory":"Computer Services",
            "type":"Services"
        }
    ],
    "sg:phone":"+1 325 651 8628",
    "sg:postcode":"76903",
    "sg:province":"TX",
    "sg:tags":[
        "design",
        "system"
    ],
    "wof:name":"Barton Technology LLC",
    "wof:placetype":"venue"
},
  "geometry": {"coordinates":[-100.438592,31.423747],"type":"Point"}
}