{
  "type": "Feature",
  "properties": {
    "iso:country":"US",
    "sg:address":"418 Lutheran Dr",
    "sg:city":"Pottsboro",
    "sg:classifiers":[
        {
            "category":"Travel",
            "subcategory":"Campground",
            "type":"Entertainment"
        }
    ],
    "sg:phone":"+1 903 786 3148",
    "sg:postcode":"75076",
    "sg:province":"TX",
    "sg:tags":[
        "camp"
    ],
    "wof:name":"All Saints Camp & Conference",
    "wof:placetype":"venue"
},
  "geometry": {"coordinates":[-96.77098100000001,33.809654],"type":"Point"}
}