{
  "type": "Feature",
  "properties": {
    "iso:country":"US",
    "sg:address":"23 Campeche Dr",
    "sg:city":"Galveston",
    "sg:classifiers":[
        {
            "category":"Building & Trades",
            "subcategory":"Construction",
            "type":"Services"
        }
    ],
    "sg:phone":"+1 409 740 3339",
    "sg:postcode":"77554",
    "sg:province":"TX",
    "sg:tags":[
        "house"
    ],
    "wof:name":"Egret Bay Designer Homes",
    "wof:placetype":"venue"
},
  "geometry": {"coordinates":[-94.86838899999999,29.255744],"type":"Point"}
}