{
  "type": "Feature",
  "properties": {
    "iso:country":"US",
    "sg:address":"3730 Kirby Dr Ste 500",
    "sg:city":"Houston",
    "sg:classifiers":[
        {
            "category":"Health Services",
            "subcategory":"Doctor",
            "type":"Services"
        },
        {
            "category":"Health Services",
            "subcategory":"Clinic",
            "type":"Services"
        }
    ],
    "sg:phone":"+1 713 522 4360",
    "sg:postcode":"77098",
    "sg:province":"TX",
    "sg:tags":[
        "psychological",
        "psychologist"
    ],
    "wof:name":"Harris Gerald E Enterprises",
    "wof:placetype":"venue"
},
  "geometry": {"coordinates":[-95.41866899999999,29.733282],"type":"Point"}
}