{
  "type": "Feature",
  "properties": {
    "iso:country":"US",
    "sg:address":"8028 Van Hut Ln",
    "sg:city":"Houston",
    "sg:classifiers":[
        {
            "category":"Manufacturing",
            "subcategory":"Tools & Machinery",
            "type":"Manufacturing & Wholesale Goods"
        }
    ],
    "sg:phone":"+1 281 458 7304",
    "sg:postcode":"77044",
    "sg:province":"TX",
    "sg:tags":[
        "industrial",
        "mfg"
    ],
    "wof:name":"USA Precision Machining",
    "wof:placetype":"venue"
},
  "geometry": {"coordinates":[-95.19829799999999,29.842099],"type":"Point"}
}