{
  "type": "Feature",
  "properties": {
    "iso:country":"US",
    "sg:address":"350 Estes Ranch Rd",
    "sg:city":"Bruceville",
    "sg:classifiers":[
        {
            "category":"Professional",
            "subcategory":"Business Services",
            "type":"Services"
        }
    ],
    "sg:phone":"+1 254 857 8951",
    "sg:postcode":"76630",
    "sg:province":"TX",
    "wof:name":"Cresslinn Group LLC",
    "wof:placetype":"venue"
},
  "geometry": {"coordinates":[-97.23338,31.374085],"type":"Point"}
}