{
  "type": "Feature",
  "properties": {
    "iso:country":"US",
    "sg:address":"275 Halm Dr",
    "sg:city":"New Braunfels",
    "sg:classifiers":[
        {
            "category":"Professional",
            "type":"Services"
        }
    ],
    "sg:phone":"+1 830 223 5117",
    "sg:postcode":"78133",
    "sg:province":"TX",
    "wof:name":"Hunter Advanced Services",
    "wof:placetype":"venue"
},
  "geometry": {"coordinates":[-98.217375,29.922117],"type":"Point"}
}