{
  "type": "Feature",
  "properties": {
    "iso:country":"US",
    "sg:address":"305 Main St",
    "sg:city":"Mt Vernon",
    "sg:classifiers":[
        {
            "category":"Wholesale",
            "subcategory":"Farm Supplies",
            "type":"Manufacturing & Wholesale Goods"
        }
    ],
    "sg:phone":"+1 903 537 4516",
    "sg:postcode":"75457",
    "sg:province":"TX",
    "sg:tags":[
        "feed"
    ],
    "wof:name":"Tri County Feed & Supply",
    "wof:placetype":"venue"
},
  "geometry": {"coordinates":[-95.217336,33.188708],"type":"Point"}
}