{
  "type": "Feature",
  "properties": {
    "iso:country":"US",
    "sg:address":"700 Emerson Ave",
    "sg:city":"Mc Camey",
    "sg:classifiers":[
        {
            "category":"Organizations",
            "subcategory":"Religious Organization",
            "type":"Services"
        }
    ],
    "sg:phone":"+1 432 652 8850",
    "sg:postcode":"79752",
    "sg:province":"TX",
    "sg:tags":[
        "church"
    ],
    "wof:name":"Church Of Christ",
    "wof:placetype":"venue"
},
  "geometry": {"coordinates":[-102.22365499999999,31.131103],"type":"Point"}
}