{
  "type": "Feature",
  "properties": {
    "iso:country":"US",
    "sg:address":"708 W Griffin Pkwy",
    "sg:city":"Mission",
    "sg:classifiers":[
        {
            "category":"Restaurant",
            "type":"Food & Drink"
        }
    ],
    "sg:phone":"+1 956 580 9905",
    "sg:postcode":"78572",
    "sg:province":"TX",
    "sg:tags":[
        "eating"
    ],
    "wof:name":"El Pocito Restaurant No Two",
    "wof:placetype":"venue"
},
  "geometry": {"coordinates":[-98.324523,26.229894],"type":"Point"}
}