{
  "type": "Feature",
  "properties": {
    "iso:country":"US",
    "sg:address":"1411 Evergreen St",
    "sg:city":"Mission",
    "sg:classifiers":[
        {
            "category":"Shopping",
            "subcategory":"Gifts & Souvenirs",
            "type":"Retail Goods"
        }
    ],
    "sg:phone":"+1 956 583 8328",
    "sg:postcode":"78572",
    "sg:province":"TX",
    "wof:name":"Tiffany Dawns Gifts",
    "wof:placetype":"venue"
},
  "geometry": {"coordinates":[-98.309844,26.210581],"type":"Point"}
}