{
  "type": "Feature",
  "properties": {
    "iso:country":"US",
    "sg:address":"202 Maple Valley Rd",
    "sg:city":"Houston",
    "sg:classifiers":[
        {
            "category":"Professional",
            "subcategory":"Management & Consulting",
            "type":"Services"
        }
    ],
    "sg:phone":"+1 713 850 7497",
    "sg:postcode":"77056",
    "sg:province":"TX",
    "sg:tags":[
        "business"
    ],
    "wof:name":"Cz Incorporated",
    "wof:placetype":"venue"
},
  "geometry": {"coordinates":[-95.47541099999999,29.767399],"type":"Point"}
}