{
  "type": "Feature",
  "properties": {
    "iso:country":"US",
    "sg:address":"20809 US Hwy 277",
    "sg:city":"Christoval",
    "sg:classifiers":[
        {
            "category":"Restaurant",
            "type":"Food & Drink"
        }
    ],
    "sg:phone":"+1 325 896 2428",
    "sg:postcode":"76935",
    "sg:province":"TX",
    "sg:tags":[
        "eating"
    ],
    "wof:name":"Country Junction Cafe",
    "wof:placetype":"venue"
},
  "geometry": {"coordinates":[-100.510679,31.174396],"type":"Point"}
}