{
  "type": "Feature",
  "properties": {
    "iso:country":"US",
    "sg:address":"1250 Garth Rd",
    "sg:city":"Baytown",
    "sg:classifiers":[
        {
            "category":"Cinema",
            "subcategory":"Movie Rental",
            "type":"Entertainment"
        }
    ],
    "sg:phone":"+1 281 427 0838",
    "sg:postcode":"77520",
    "sg:province":"TX",
    "sg:tags":[
        "leasing",
        "video",
        "disc",
        "tape"
    ],
    "wof:name":"Hollywood Video",
    "wof:placetype":"venue"
},
  "geometry": {"coordinates":[-94.979032,29.743476],"type":"Point"}
}