{
  "type": "Feature",
  "properties": {
    "iso:country":"US",
    "sg:address":"2261 Shakespeare St",
    "sg:city":"Houston",
    "sg:classifiers":[
        {
            "category":"Banks & Credit Unions",
            "subcategory":"Financial Services",
            "type":"Services"
        }
    ],
    "sg:phone":"+1 713 668 9429",
    "sg:postcode":"77030",
    "sg:province":"TX",
    "sg:tags":[
        "management",
        "investment"
    ],
    "sg:website":"http://www.estragon.net",
    "wof:name":"Estragon",
    "wof:placetype":"venue"
},
  "geometry": {"coordinates":[-95.411412,29.714181],"type":"Point"}
}