{
  "type": "Feature",
  "properties": {
    "iso:country":"US",
    "sg:address":"2000 N Lee Trevino Dr",
    "sg:city":"El Paso",
    "sg:classifiers":[
        {
            "category":"Banks & Credit Unions",
            "subcategory":"Bank",
            "type":"Services"
        }
    ],
    "sg:phone":"+1 915 629 6970",
    "sg:postcode":"79936",
    "sg:province":"TX",
    "sg:tags":[
        "cashing",
        "check"
    ],
    "wof:name":"Quik Cash",
    "wof:placetype":"venue"
},
  "geometry": {"coordinates":[-106.319304,31.77131],"type":"Point"}
}