{
  "type": "Feature",
  "properties": {
    "iso:country":"US",
    "sg:address":"1910 W Braker Ln",
    "sg:city":"Austin",
    "sg:classifiers":[
        {
            "category":"Shopping",
            "subcategory":"Pharmacy",
            "type":"Retail Goods"
        }
    ],
    "sg:phone":"+1 512 835 7531",
    "sg:postcode":"78758",
    "sg:province":"TX",
    "sg:website":"www.walgreens.com",
    "wof:name":"Walgreens",
    "wof:placetype":"venue"
},
  "geometry": {"coordinates":[-97.70524399999999,30.391048],"type":"Point"}
}