{
  "type": "Feature",
  "properties": {
    "iso:country":"US",
    "sg:address":"4205 McEwen Rd",
    "sg:city":"Dallas",
    "sg:classifiers":[
        {
            "category":"Home & Garden",
            "subcategory":"Furniture",
            "type":"Retail Goods"
        }
    ],
    "sg:phone":"+1 972 770 0929",
    "sg:postcode":"75244",
    "sg:province":"TX",
    "sg:tags":[
        "store"
    ],
    "wof:name":"Bassett",
    "wof:placetype":"venue"
},
  "geometry": {"coordinates":[-96.83820299999999,32.929001],"type":"Point"}
}