{
  "type": "Feature",
  "properties": {
    "iso:country":"US",
    "sg:address":"516 Dean Dr",
    "sg:city":"Denison",
    "sg:classifiers":[
        {
            "category":"Building & Trades",
            "subcategory":"Construction",
            "type":"Services"
        }
    ],
    "sg:phone":"+1 903 465 9519",
    "sg:postcode":"75020",
    "sg:province":"TX",
    "sg:tags":[
        "nonresidential",
        "contractor"
    ],
    "wof:name":"H & H Contracting",
    "wof:placetype":"venue"
},
  "geometry": {"coordinates":[-96.56943200000001,33.752451],"type":"Point"}
}