{
  "type": "Feature",
  "properties": {
    "iso:country":"US",
    "sg:address":"4020 Holland Ave",
    "sg:city":"Dallas",
    "sg:classifiers":[
        {
            "category":"Shopping",
            "subcategory":"Catalog Store",
            "type":"Retail Goods"
        }
    ],
    "sg:phone":"+1 214 369 3294",
    "sg:postcode":"75219",
    "sg:province":"TX",
    "sg:tags":[
        "mail",
        "order"
    ],
    "wof:name":"Sweet Trapp",
    "wof:placetype":"venue"
},
  "geometry": {"coordinates":[-96.806856,32.81623],"type":"Point"}
}