{
  "type": "Feature",
  "properties": {
    "iso:country":"US",
    "sg:address":"500 S Main St",
    "sg:city":"Lindale",
    "sg:classifiers":[
        {
            "category":"Cinema",
            "subcategory":"Movie Rental",
            "type":"Entertainment"
        }
    ],
    "sg:phone":"+1 903 882 9231",
    "sg:postcode":"75771",
    "sg:province":"TX",
    "sg:tags":[
        "leasing",
        "video",
        "disc",
        "tape"
    ],
    "wof:name":"Movie House",
    "wof:placetype":"venue"
},
  "geometry": {"coordinates":[-95.408394,32.50943],"type":"Point"}
}