{
  "type": "Feature",
  "properties": {
    "iso:country":"US",
    "sg:address":"122 Sabyan Dr",
    "sg:city":"San Antonio",
    "sg:classifiers":[
        {
            "category":"Wholesale",
            "subcategory":"Machinery & Supplies",
            "type":"Manufacturing & Wholesale Goods"
        }
    ],
    "sg:phone":"+1 210 930 6464",
    "sg:postcode":"78218",
    "sg:province":"TX",
    "sg:tags":[
        "equipment",
        "repair"
    ],
    "wof:name":"All-Tex Equipment",
    "wof:placetype":"venue"
},
  "geometry": {"coordinates":[-98.425549,29.487687],"type":"Point"}
}