{
  "type": "Feature",
  "properties": {
    "iso:country":"US",
    "sg:address":"8314 Spinnaker Cove",
    "sg:city":"Rowlett",
    "sg:classifiers":[
        {
            "category":"Shopping",
            "subcategory":"Gifts & Souvenirs",
            "type":"Retail Goods"
        }
    ],
    "sg:phone":"+1 972 475 3604",
    "sg:postcode":"75089",
    "sg:province":"TX",
    "wof:name":"Gracies Gifts",
    "wof:placetype":"venue"
},
  "geometry": {"coordinates":[-96.522115,32.933254],"type":"Point"}
}