{
  "type": "Feature",
  "properties": {
    "iso:country":"US",
    "sg:address":"5050 Dexham Rd Ste H",
    "sg:city":"Rowlett",
    "sg:classifiers":[
        {
            "category":"Home & Garden",
            "subcategory":"Building Materials",
            "type":"Retail Goods"
        },
        {
            "category":"Building & Trades",
            "subcategory":"Construction",
            "type":"Services"
        },
        {
            "category":"Home & Garden",
            "subcategory":"Furniture",
            "type":"Retail Goods"
        }
    ],
    "sg:phone":"+1 972 414 8983",
    "sg:postcode":"75088",
    "sg:province":"TX",
    "sg:tags":[
        "builder",
        "outdoor",
        "gazebo",
        "patio"
    ],
    "sg:website":"http://www.danielcarport.com",
    "wof:name":"Daniel Carport & Patio Company",
    "wof:placetype":"venue"
},
  "geometry": {"coordinates":[-96.585081,32.904411],"type":"Point"}
}