{
  "type": "Feature",
  "properties": {
    "iso:country":"US",
    "sg:address":"11652 Jollyville Rd",
    "sg:city":"Austin",
    "sg:classifiers":[
        {
            "category":"Real Estate",
            "subcategory":"Real Estate Agent",
            "type":"Services"
        }
    ],
    "sg:phone":"+1 512 636 2323",
    "sg:postcode":"78759",
    "sg:province":"TX",
    "wof:name":"Arboretum Realty",
    "wof:placetype":"venue"
},
  "geometry": {"coordinates":[-97.750939,30.417869],"type":"Point"}
}