{
  "type": "Feature",
  "properties": {
    "iso:country":"US",
    "sg:address":"228 Westheimer Rd",
    "sg:city":"Houston",
    "sg:classifiers":[
        {
            "category":"Professional",
            "subcategory":"Lawyer & Legal Services",
            "type":"Services"
        }
    ],
    "sg:phone":"+1 713 528 7711",
    "sg:postcode":"77006",
    "sg:province":"TX",
    "wof:name":"Marcos & Associates PC",
    "wof:placetype":"venue"
},
  "geometry": {"coordinates":[-95.38351,29.744772],"type":"Point"}
}