{
  "type": "Feature",
  "properties": {
    "iso:country":"US",
    "sg:address":"120 N Washington St",
    "sg:city":"La Grange",
    "sg:classifiers":[
        {
            "category":"Mining & Drilling",
            "type":"Manufacturing & Wholesale Goods"
        }
    ],
    "sg:phone":"+1 979 968 9644",
    "sg:postcode":"78945",
    "sg:province":"TX",
    "sg:tags":[
        "exploration"
    ],
    "wof:name":"Bruce Spindler Office",
    "wof:placetype":"venue"
},
  "geometry": {"coordinates":[-96.87817200000001,29.905809],"type":"Point"}
}