{
  "type": "Feature",
  "properties": {
    "iso:country":"US",
    "sg:address":"1109 Dallas Dr",
    "sg:city":"Denton",
    "sg:classifiers":[
        {
            "category":"Bars & Pubs",
            "type":"Food & Drink"
        }
    ],
    "sg:phone":"+1 940 566 1881",
    "sg:postcode":"76205",
    "sg:province":"TX",
    "sg:tags":[
        "club",
        "night"
    ],
    "wof:name":"Bar Rio",
    "wof:placetype":"venue"
},
  "geometry": {"coordinates":[-97.12124900000001,33.197079],"type":"Point"}
}