{
  "type": "Feature",
  "properties": {
    "iso:country":"US",
    "sg:address":"2613 Rogers Ave",
    "sg:city":"Austin",
    "sg:classifiers":[
        {
            "category":"Social Services",
            "subcategory":"Child Care",
            "type":"Services"
        }
    ],
    "sg:phone":"+1 512 472 9108",
    "sg:postcode":"78722",
    "sg:province":"TX",
    "sg:tags":[
        "day"
    ],
    "sg:website":"www.eackids.org",
    "wof:name":"Extend-A-Care For Kids",
    "wof:placetype":"venue"
},
  "geometry": {"coordinates":[-97.713536,30.282298],"type":"Point"}
}