{
  "type": "Feature",
  "properties": {
    "iso:country":"US",
    "sg:address":"3300 Bingle Rd",
    "sg:city":"Houston",
    "sg:classifiers":[
        {
            "category":"Mining & Drilling",
            "type":"Manufacturing & Wholesale Goods"
        }
    ],
    "sg:phone":"+1 713 895 7575",
    "sg:postcode":"77055",
    "sg:province":"TX",
    "sg:tags":[
        "mud",
        "oil",
        "well",
        "additive"
    ],
    "sg:website":"www.kofg.com",
    "wof:name":"Kelco Oil Field Group",
    "wof:placetype":"venue"
},
  "geometry": {"coordinates":[-95.49494799999999,29.82443],"type":"Point"}
}