{
  "type": "Feature",
  "properties": {
    "iso:country":"US",
    "sg:address":"136 Country Craft Rd",
    "sg:city":"Lufkin",
    "sg:classifiers":[
        {
            "category":"Organizations",
            "subcategory":"Religious Organization",
            "type":"Services"
        }
    ],
    "sg:phone":"+1 936 632 6839",
    "sg:postcode":"75904",
    "sg:province":"TX",
    "sg:tags":[
        "church"
    ],
    "wof:name":"Allen Gin Baptist Church",
    "wof:placetype":"venue"
},
  "geometry": {"coordinates":[-94.75591,31.373075],"type":"Point"}
}