{
  "type": "Feature",
  "properties": {
    "iso:country":"US",
    "sg:address":"18293 Lakeside Dr",
    "sg:city":"Flint",
    "sg:classifiers":[
        {
            "category":"Shopping",
            "type":"Retail Goods"
        }
    ],
    "sg:phone":"+1 903 561 0155",
    "sg:postcode":"75762",
    "sg:province":"TX",
    "sg:tags":[
        "merchandise",
        "general"
    ],
    "wof:name":"Terrys Spa Sales",
    "wof:placetype":"venue"
},
  "geometry": {"coordinates":[-95.456343,32.229852],"type":"Point"}
}