{
  "type": "Feature",
  "properties": {
    "iso:country":"US",
    "sg:address":"8650 Marbach Rd",
    "sg:city":"San Antonio",
    "sg:classifiers":[
        {
            "category":"Autos & Motor Vehicles",
            "subcategory":"Auto Supplies",
            "type":"Retail Goods"
        }
    ],
    "sg:phone":"+1 210 673 9011",
    "sg:postcode":"78227",
    "sg:province":"TX",
    "sg:tags":[
        "automotive",
        "parts",
        "automobile"
    ],
    "wof:name":"Advance Auto Parts Inc",
    "wof:placetype":"venue"
},
  "geometry": {"coordinates":[-98.65773900000001,29.417835],"type":"Point"}
}