{
  "type": "Feature",
  "properties": {
    "iso:country":"US",
    "sg:address":"9114 Jan Glen Ln",
    "sg:city":"Spring",
    "sg:classifiers":[
        {
            "category":"Education",
            "subcategory":"Special Training",
            "type":"Public Place"
        }
    ],
    "sg:phone":"+1 281 257 2230",
    "sg:postcode":"77379",
    "sg:province":"TX",
    "wof:name":"Superior Defensive Driving",
    "wof:placetype":"venue"
},
  "geometry": {"coordinates":[-95.559512,30.023344],"type":"Point"}
}