{
  "type": "Feature",
  "properties": {
    "iso:country":"US",
    "sg:address":"2503 San Gabriel St",
    "sg:city":"Austin",
    "sg:classifiers":[
        {
            "category":"Communications",
            "subcategory":"Film & Video Production",
            "type":"Services"
        }
    ],
    "sg:phone":"+1 512 472 9258",
    "sg:postcode":"78705",
    "sg:province":"TX",
    "sg:tags":[
        "motion"
    ],
    "wof:name":"N3d Productions",
    "wof:placetype":"venue"
},
  "geometry": {"coordinates":[-97.74767300000001,30.289443],"type":"Point"}
}