{
  "type": "Feature",
  "properties": {
    "iso:country":"US",
    "sg:address":"330 Bedford St",
    "sg:city":"Dallas",
    "sg:classifiers":[
        {
            "category":"Professional",
            "type":"Services"
        }
    ],
    "sg:phone":"+1 214 761 9092",
    "sg:postcode":"75212",
    "sg:province":"TX",
    "sg:tags":[
        "establishment"
    ],
    "wof:name":"Dal-Pro Air Systems",
    "wof:placetype":"venue"
},
  "geometry": {"coordinates":[-96.828419,32.77772],"type":"Point"}
}