{
  "type": "Feature",
  "properties": {
    "iso:country":"US",
    "sg:address":"3301 Hamilton Ave",
    "sg:city":"Fort Worth",
    "sg:classifiers":[
        {
            "category":"Health Services",
            "subcategory":"Health Practitioner",
            "type":"Services"
        }
    ],
    "sg:phone":"+1 817 882 9677",
    "sg:postcode":"76107",
    "sg:province":"TX",
    "sg:tags":[
        "home",
        "care"
    ],
    "wof:name":"Accolade Home Care",
    "wof:placetype":"venue"
},
  "geometry": {"coordinates":[-97.36658300000001,32.754832],"type":"Point"}
}