{
  "type": "Feature",
  "properties": {
    "iso:country":"US",
    "sg:address":"14320 Garrett Rd Apt 2",
    "sg:city":"Houston",
    "sg:classifiers":[
        {
            "category":"Organizations",
            "subcategory":"Membership Organization",
            "type":"Services"
        }
    ],
    "sg:phone":"+1 281 456 9350",
    "sg:postcode":"77044",
    "sg:province":"TX",
    "sg:tags":[
        "environmental",
        "ecological",
        "conservation"
    ],
    "sg:website":"http://www.thc.state.tx.us",
    "wof:name":"Sheldon Lake Park",
    "wof:placetype":"venue"
},
  "geometry": {"coordinates":[-95.163849,29.883421],"type":"Point"}
}