{
  "type": "Feature",
  "properties": {
    "iso:country":"US",
    "sg:address":"711 Co Rd 162",
    "sg:city":"Gainesville",
    "sg:classifiers":[
        {
            "category":"Farming",
            "subcategory":"Farm & Veterinary Services",
            "type":"Manufacturing & Wholesale Goods"
        }
    ],
    "sg:phone":"+1 940 665 4952",
    "sg:postcode":"76240",
    "sg:province":"TX",
    "sg:tags":[
        "artificial"
    ],
    "wof:name":"Friedrich Breeding Service",
    "wof:placetype":"venue"
},
  "geometry": {"coordinates":[-97.07991,33.620776],"type":"Point"}
}