{
  "type": "Feature",
  "properties": {
    "iso:country":"US",
    "sg:address":"2631 E Yandell Dr",
    "sg:city":"El Paso",
    "sg:classifiers":[
        {
            "category":"Wholesale",
            "subcategory":"Machinery & Supplies",
            "type":"Manufacturing & Wholesale Goods"
        }
    ],
    "sg:phone":"+1 915 534 7997",
    "sg:postcode":"79903",
    "sg:province":"TX",
    "sg:tags":[
        "commercial",
        "product",
        "laundry"
    ],
    "wof:name":"KS Commercial Ldry Specialists",
    "wof:placetype":"venue"
},
  "geometry": {"coordinates":[-106.46402999999999,31.780583],"type":"Point"}
}