{
  "type": "Feature",
  "properties": {
    "iso:country":"US",
    "sg:address":"815 S Tyler St",
    "sg:city":"Amarillo",
    "sg:classifiers":[
        {
            "category":"Utilities",
            "subcategory":"Telephone",
            "type":"Services"
        }
    ],
    "sg:phone":"+1 806 378 1300",
    "sg:postcode":"79101",
    "sg:province":"AR",
    "sg:tags":[
        "communications"
    ],
    "wof:name":"Southwstern Bell Mssaging Svcs",
    "wof:placetype":"venue"
},
  "geometry": {"coordinates":[-101.83870899999999,35.204809],"type":"Point"}
}