{
  "type": "Feature",
  "properties": {
    "iso:country":"US",
    "sg:address":"6801 Sanger Ave Ste 140",
    "sg:city":"Waco",
    "sg:classifiers":[
        {
            "category":"Social Services",
            "type":"Services"
        },
        {
            "category":"Professional",
            "subcategory":"Accounting & Tax Preparation",
            "type":"Services"
        },
        {
            "category":"Professional",
            "subcategory":"Lawyer & Legal Services",
            "type":"Services"
        }
    ],
    "sg:phone":"+1 254 754 0909",
    "sg:postcode":"76710",
    "sg:province":"TX",
    "sg:tags":[
        "attorney",
        "return",
        "consultant",
        "representative",
        "security",
        "law",
        "bankruptcy"
    ],
    "sg:website":"http://www.bankruptcytaxattorneycpa.com",
    "wof:name":"Olson Joseph D & Associates",
    "wof:placetype":"venue"
},
  "geometry": {"coordinates":[-97.199928,31.519051],"type":"Point"}
}