{
  "type": "Feature",
  "properties": {
    "iso:country":"US",
    "sg:address":"4975 Preston Park Blvd Ste 130",
    "sg:city":"Plano",
    "sg:classifiers":[
        {
            "category":"Professional",
            "subcategory":"Accounting & Tax Preparation",
            "type":"Services"
        }
    ],
    "sg:phone":"+1 972 985 0011",
    "sg:postcode":"75093",
    "sg:province":"TX",
    "sg:tags":[
        "accountant"
    ],
    "wof:name":"Morris CPA & Company I L Lonnie",
    "wof:placetype":"venue"
},
  "geometry": {"coordinates":[-96.7938,33.022999],"type":"Point"}
}