{
  "type": "Feature",
  "properties": {
    "iso:country":"US",
    "sg:address":"2235 Keller Way",
    "sg:city":"Carrollton",
    "sg:classifiers":[
        {
            "category":"Professional",
            "subcategory":"Management & Consulting",
            "type":"Services"
        }
    ],
    "sg:phone":"+1 972 478 7415",
    "sg:postcode":"75006",
    "sg:province":"TX",
    "wof:name":"Ihst Inc",
    "wof:placetype":"venue"
},
  "geometry": {"coordinates":[-96.847403,32.970156],"type":"Point"}
}