{
  "type": "Feature",
  "properties": {
    "iso:country":"US",
    "sg:address":"4120 Slick Rock Chase St",
    "sg:city":"Euless",
    "sg:classifiers":[
        {
            "category":"Wholesale",
            "subcategory":"Stationery",
            "type":"Manufacturing & Wholesale Goods"
        }
    ],
    "sg:phone":"+1 817 868 9246",
    "sg:postcode":"76040",
    "sg:province":"TX",
    "sg:tags":[
        "paper"
    ],
    "wof:name":"Ris Paper Co Inc",
    "wof:placetype":"venue"
},
  "geometry": {"coordinates":[-97.07304499999999,32.823469],"type":"Point"}
}