{
  "type": "Feature",
  "properties": {
    "iso:country":"US",
    "sg:address":"4519 W Lovers Ln",
    "sg:city":"Dallas",
    "sg:classifiers":[
        {
            "category":"Professional",
            "subcategory":"Lawyer & Legal Services",
            "type":"Services"
        }
    ],
    "sg:phone":"+1 214 358 2358",
    "sg:postcode":"75209",
    "sg:province":"TX",
    "sg:tags":[
        "attorney"
    ],
    "wof:name":"Glen A Fitzmartin",
    "wof:placetype":"venue"
},
  "geometry": {"coordinates":[-96.831693,32.851366],"type":"Point"}
}