{
  "type": "Feature",
  "properties": {
    "iso:country":"US",
    "sg:address":"131 N San Antonio St",
    "sg:city":"Port Lavaca",
    "sg:classifiers":[
        {
            "category":"Building & Trades",
            "subcategory":"Construction",
            "type":"Services"
        }
    ],
    "sg:phone":"+1 361 552 4614",
    "sg:postcode":"77979",
    "sg:province":"TX",
    "sg:tags":[
        "house",
        "contractor"
    ],
    "wof:name":"J R G Construction",
    "wof:placetype":"venue"
},
  "geometry": {"coordinates":[-96.62871699999999,28.613702],"type":"Point"}
}