{
  "type": "Feature",
  "properties": {
    "iso:country":"US",
    "sg:address":"550 Stafford Run Rd",
    "sg:city":"Stafford",
    "sg:classifiers":[
        {
            "category":"Professional",
            "subcategory":"Accounting & Tax Preparation",
            "type":"Services"
        }
    ],
    "sg:phone":"+1 281 403 0613",
    "sg:postcode":"77477",
    "sg:province":"TX",
    "wof:name":"Dancys Billing Service",
    "wof:placetype":"venue"
},
  "geometry": {"coordinates":[-95.560619,29.611794],"type":"Point"}
}