{
  "type": "Feature",
  "properties": {
    "iso:country":"US",
    "sg:address":"4113 Andrews Hwy",
    "sg:city":"Odessa",
    "sg:classifiers":[
        {
            "category":"Restaurant",
            "type":"Food & Drink"
        }
    ],
    "sg:phone":"+1 432 368 0350",
    "sg:postcode":"79762",
    "sg:province":"TX",
    "sg:tags":[
        "eating"
    ],
    "wof:name":"KFC",
    "wof:placetype":"venue"
},
  "geometry": {"coordinates":[-102.384427,31.880362],"type":"Point"}
}