{
  "type": "Feature",
  "properties": {
    "iso:country":"US",
    "sg:address":"19803 White Dove Dr",
    "sg:city":"Crosby",
    "sg:classifiers":[
        {
            "category":"Shopping",
            "subcategory":"Bicycles & Sporting Goods",
            "type":"Retail Goods"
        }
    ],
    "sg:phone":"+1 281 324 9040",
    "sg:postcode":"77532",
    "sg:province":"TX",
    "wof:name":"Fire Arms Sales",
    "wof:placetype":"venue"
},
  "geometry": {"coordinates":[-95.12260999999999,29.9665],"type":"Point"}
}