{
  "type": "Feature",
  "properties": {
    "iso:country":"US",
    "sg:address":"1836 S Old Temple Rd",
    "sg:city":"Lorena",
    "sg:classifiers":[
        {
            "category":"Wholesale",
            "subcategory":"Vending Machines",
            "type":"Manufacturing & Wholesale Goods"
        }
    ],
    "sg:phone":"+1 254 857 3222",
    "sg:postcode":"76655",
    "sg:province":"TX",
    "sg:tags":[
        "operator"
    ],
    "wof:name":"Bob Lemley",
    "wof:placetype":"venue"
},
  "geometry": {"coordinates":[-97.206383,31.363956],"type":"Point"}
}