{
  "type": "Feature",
  "properties": {
    "iso:country":"US",
    "sg:address":"5812 Emerson Ct",
    "sg:city":"Arlington",
    "sg:classifiers":[
        {
            "category":"Building & Trades",
            "subcategory":"Plumbing",
            "type":"Services"
        }
    ],
    "sg:phone":"+1 817 457 2233",
    "sg:postcode":"76016",
    "sg:province":"TX",
    "sg:tags":[
        "contractor"
    ],
    "wof:name":"Ls Mechanical Inc",
    "wof:placetype":"venue"
},
  "geometry": {"coordinates":[-97.197284,32.690206],"type":"Point"}
}