{
  "type": "Feature",
  "properties": {
    "iso:country":"US",
    "sg:address":"1790 N Lee Trevino Dr",
    "sg:city":"El Paso",
    "sg:classifiers":[
        {
            "category":"Health Services",
            "subcategory":"Doctor",
            "type":"Services"
        }
    ],
    "sg:phone":"+1 915 533 9040",
    "sg:postcode":"79936",
    "sg:province":"TX",
    "sg:tags":[
        "physician",
        "surgeon"
    ],
    "wof:name":"Radiology Consultants",
    "wof:placetype":"venue"
},
  "geometry": {"coordinates":[-106.318797,31.764541],"type":"Point"}
}