{
  "type": "Feature",
  "properties": {
    "iso:country":"US",
    "sg:address":"402 S Broad St",
    "sg:city":"Lampasas",
    "sg:classifiers":[
        {
            "category":"Professional",
            "subcategory":"Lawyer & Legal Services",
            "type":"Services"
        }
    ],
    "sg:phone":"+1 512 556 8225",
    "sg:postcode":"76550",
    "sg:province":"TX",
    "sg:tags":[
        "attorney"
    ],
    "wof:name":"Sue Zane M Faulkner",
    "wof:placetype":"venue"
},
  "geometry": {"coordinates":[-98.18459900000001,31.063977],"type":"Point"}
}