{
  "type": "Feature",
  "properties": {
    "iso:country":"US",
    "sg:address":"5759 Glenwillow Ct",
    "sg:city":"Fort Worth",
    "sg:classifiers":[
        {
            "category":"Shopping",
            "subcategory":"Computers & Home Electronics",
            "type":"Retail Goods"
        }
    ],
    "sg:phone":"+1 817 346 8629",
    "sg:postcode":"76132",
    "sg:province":"TX",
    "sg:tags":[
        "software"
    ],
    "sg:website":"www.thebusinessgroup.net",
    "wof:name":"Business Group Inc",
    "wof:placetype":"venue"
},
  "geometry": {"coordinates":[-97.39657099999999,32.664925],"type":"Point"}
}