{
  "type": "Feature",
  "properties": {
    "iso:country":"US",
    "sg:address":"7155 FM 1456",
    "sg:city":"Bellville",
    "sg:classifiers":[
        {
            "category":"Real Estate",
            "subcategory":"Developer",
            "type":"Services"
        }
    ],
    "sg:phone":"+1 979 865 2480",
    "sg:postcode":"77418",
    "sg:province":"TX",
    "sg:tags":[
        "cemetery"
    ],
    "wof:name":"Buckhorn Church Cemetery",
    "wof:placetype":"venue"
},
  "geometry": {"coordinates":[-96.21275,30.03467],"type":"Point"}
}