{
  "type": "Feature",
  "properties": {
    "iso:country":"US",
    "sg:address":"3001 S Lamar Blvd Ste 101",
    "sg:city":"Austin",
    "sg:classifiers":[
        {
            "category":"Real Estate",
            "subcategory":"Architect",
            "type":"Services"
        }
    ],
    "sg:phone":"+1 512 282 0906",
    "sg:postcode":"78704",
    "sg:province":"TX",
    "sg:tags":[
        "architects'",
        "specification",
        "builders'",
        "construction",
        "architectural"
    ],
    "wof:name":"Gutierrez, Remberto Architect",
    "wof:placetype":"venue"
},
  "geometry": {"coordinates":[-97.78360000000001,30.242706],"type":"Point"}
}