{
  "type": "Feature",
  "properties": {
    "iso:country":"US",
    "sg:address":"1732 Liberty St",
    "sg:city":"Fort Worth",
    "sg:classifiers":[
        {
            "category":"Organizations",
            "subcategory":"Religious Organization",
            "type":"Services"
        }
    ],
    "sg:phone":"+1 817 536 3558",
    "sg:postcode":"76105",
    "sg:province":"TX",
    "wof:name":"Greater St Mark Church",
    "wof:placetype":"venue"
},
  "geometry": {"coordinates":[-97.244148,32.727539],"type":"Point"}
}