{
  "type": "Feature",
  "properties": {
    "iso:country":"US",
    "sg:address":"5045 Tangle Ln",
    "sg:city":"Houston",
    "sg:classifiers":[
        {
            "category":"Organizations",
            "subcategory":"Community Association",
            "type":"Services"
        }
    ],
    "sg:phone":"+1 713 623 4693",
    "sg:postcode":"77056",
    "sg:province":"TX",
    "wof:name":"Chateau Tngle Ln Hmowners Assn",
    "wof:placetype":"venue"
},
  "geometry": {"coordinates":[-95.466628,29.756841],"type":"Point"}
}