{
  "type": "Feature",
  "properties": {
    "iso:country":"US",
    "sg:address":"1310 Allendale Dr",
    "sg:city":"Lufkin",
    "sg:classifiers":[
        {
            "category":"Retail",
            "subcategory":"Repair Shop",
            "type":"Services"
        }
    ],
    "sg:phone":"+1 936 637 4825",
    "sg:postcode":"75904",
    "sg:province":"TX",
    "sg:tags":[
        "clocks",
        "parts"
    ],
    "wof:name":"Time Healer Clock Repair",
    "wof:placetype":"venue"
},
  "geometry": {"coordinates":[-94.745014,31.320111],"type":"Point"}
}