{
  "type": "Feature",
  "properties": {
    "iso:country":"US",
    "sg:address":"3229 Ayers St",
    "sg:city":"Corpus Christi",
    "sg:classifiers":[
        {
            "category":"Shopping",
            "subcategory":"Discount & Variety Stores",
            "type":"Retail Goods"
        }
    ],
    "sg:phone":"+1 361 887 8184",
    "sg:postcode":"78415",
    "sg:province":"TX",
    "sg:tags":[
        "clothing",
        "uniform"
    ],
    "wof:name":"Corpus Christi Wholesale Mart",
    "wof:placetype":"venue"
},
  "geometry": {"coordinates":[-97.412243,27.760234],"type":"Point"}
}