{
  "type": "Feature",
  "properties": {
    "iso:country":"US",
    "sg:address":"823 Crooked Creek Ln",
    "sg:city":"De Soto",
    "sg:classifiers":[
        {
            "category":"Social Services",
            "subcategory":"Child Care",
            "type":"Services"
        }
    ],
    "sg:phone":"+1 972 274 0398",
    "sg:postcode":"75115",
    "sg:province":"TX",
    "sg:tags":[
        "day"
    ],
    "wof:name":"Adventure Land Daycare and Lea",
    "wof:placetype":"venue"
},
  "geometry": {"coordinates":[-96.837892,32.581826],"type":"Point"}
}