{
  "type": "Feature",
  "properties": {
    "iso:country":"US",
    "sg:address":"14020 FM 2100",
    "sg:city":"Crosby",
    "sg:classifiers":[
        {
            "category":"Recreation",
            "type":"Entertainment"
        }
    ],
    "sg:phone":"+1 281 328 2113",
    "sg:postcode":"77532",
    "sg:province":"TX",
    "sg:tags":[
        "rodeo"
    ],
    "wof:name":"Crosby Fair & Rodeo",
    "wof:placetype":"venue"
},
  "geometry": {"coordinates":[-95.06338700000001,29.889986],"type":"Point"}
}