{
  "type": "Feature",
  "properties": {
    "iso:country":"US",
    "sg:address":"457 S R L Thornton Fwy",
    "sg:city":"Dallas",
    "sg:classifiers":[
        {
            "category":"Professional",
            "subcategory":"Accounting & Tax Preparation",
            "type":"Services"
        }
    ],
    "sg:phone":"+1 214 941 0707",
    "sg:postcode":"75203",
    "sg:province":"TX",
    "sg:tags":[
        "return"
    ],
    "wof:name":"Mora & Associates",
    "wof:placetype":"venue"
},
  "geometry": {"coordinates":[-96.809949,32.75154],"type":"Point"}
}