{
  "type": "Feature",
  "properties": {
    "iso:country":"US",
    "sg:address":"910 Stonewall St",
    "sg:city":"Dallas",
    "sg:classifiers":[
        {
            "category":"Autos & Motor Vehicles",
            "subcategory":"Automobile Sales",
            "type":"Retail Goods"
        }
    ],
    "sg:phone":"+1 214 826 4437",
    "sg:postcode":"75223",
    "sg:province":"TX",
    "sg:tags":[
        "used"
    ],
    "wof:name":"Mata Auto Sales",
    "wof:placetype":"venue"
},
  "geometry": {"coordinates":[-96.762389,32.785034],"type":"Point"}
}