{
  "type": "Feature",
  "properties": {
    "iso:country":"US",
    "sg:address":"16636 N Coit Rd",
    "sg:city":"Dallas",
    "sg:classifiers":[
        {
            "category":"Shopping",
            "subcategory":"Florist",
            "type":"Retail Goods"
        }
    ],
    "sg:phone":"+1 972 247 3133",
    "sg:postcode":"75248",
    "sg:province":"TX",
    "wof:name":"A Plus Flowers",
    "wof:placetype":"venue"
},
  "geometry": {"coordinates":[-96.768259,32.980952],"type":"Point"}
}