{
  "type": "Feature",
  "properties": {
    "iso:country":"US",
    "sg:address":"7225 Crowley Rd",
    "sg:city":"Fort Worth",
    "sg:classifiers":[
        {
            "category":"Shopping",
            "subcategory":"Florist",
            "type":"Retail Goods"
        }
    ],
    "sg:phone":"+1 817 293 9571",
    "sg:postcode":"76134",
    "sg:province":"TX",
    "wof:name":"Flower Garden",
    "wof:placetype":"venue"
},
  "geometry": {"coordinates":[-97.34849199999999,32.639969],"type":"Point"}
}