{
  "type": "Feature",
  "properties": {
    "iso:country":"US",
    "sg:address":"417 Main St",
    "sg:city":"Hereford",
    "sg:classifiers":[
        {
            "category":"Shopping",
            "subcategory":"Clothing, Apparel, & Fashions",
            "type":"Retail Goods"
        }
    ],
    "sg:phone":"+1 806 364 6074",
    "sg:postcode":"79045",
    "sg:province":"TX",
    "sg:tags":[
        "infant",
        "wear"
    ],
    "wof:name":"Kid's Alley",
    "wof:placetype":"venue"
},
  "geometry": {"coordinates":[-102.40058399999999,34.818341],"type":"Point"}
}