{
  "type": "Feature",
  "properties": {
    "iso:country":"US",
    "sg:address":"7000 N MoPac Ste 200",
    "sg:city":"Austin",
    "sg:classifiers":[
        {
            "category":"Education",
            "subcategory":"Special Training",
            "type":"Public Place"
        }
    ],
    "sg:phone":"+1 888 561 7169",
    "sg:postcode":"78731",
    "sg:province":"TX",
    "sg:tags":[
        "school",
        "language"
    ],
    "sg:website":"www.berlitz.us/austin",
    "wof:name":"Berlitz Language Center",
    "wof:placetype":"venue"
},
  "geometry": {"coordinates":[-97.843852,30.216046],"type":"Point"}
}