{
  "type": "Feature",
  "properties": {
    "iso:country":"US",
    "sg:address":"4111 S Cooper St",
    "sg:city":"Arlington",
    "sg:classifiers":[
        {
            "category":"Shopping",
            "subcategory":"Hobbies, Toys, & Games",
            "type":"Retail Goods"
        }
    ],
    "sg:phone":"+1 817 784 0843",
    "sg:postcode":"76015",
    "sg:province":"TX",
    "wof:name":"Toys R Us",
    "wof:placetype":"venue"
},
  "geometry": {"coordinates":[-97.134755,32.679681],"type":"Point"}
}