{
  "type": "Feature",
  "properties": {
    "iso:country":"US",
    "sg:address":"104 E Germania St",
    "sg:city":"Brenham",
    "sg:classifiers":[
        {
            "category":"Retail",
            "subcategory":"Portrait Studio",
            "type":"Services"
        }
    ],
    "sg:phone":"+1 979 836 1885",
    "sg:postcode":"77833",
    "sg:province":"TX",
    "sg:tags":[
        "photographer",
        "aerial"
    ],
    "sg:website":"http://www.stoneysphotography.com",
    "wof:name":"Stoney Lacina Photography",
    "wof:placetype":"venue"
},
  "geometry": {"coordinates":[-96.39612,30.160606],"type":"Point"}
}