{
  "type": "Feature",
  "properties": {
    "iso:country":"US",
    "sg:address":"1750 Range Dr",
    "sg:city":"Mesquite",
    "sg:classifiers":[
        {
            "category":"Wholesale",
            "subcategory":"Medical Equipment & Supplies",
            "type":"Manufacturing & Wholesale Goods"
        }
    ],
    "sg:phone":"+1 972 285 4487",
    "sg:postcode":"75149",
    "sg:province":"TX",
    "sg:tags":[
        "physician",
        "surgeon"
    ],
    "wof:name":"Nation Wide Medical Supplies",
    "wof:placetype":"venue"
},
  "geometry": {"coordinates":[-96.596856,32.787802],"type":"Point"}
}