{
  "type": "Feature",
  "properties": {
    "iso:country":"US",
    "sg:address":"20356 Desert Willow Dr",
    "sg:city":"Katy",
    "sg:classifiers":[
        {
            "category":"Utilities",
            "subcategory":"Water",
            "type":"Services"
        }
    ],
    "sg:phone":"+1 281 828 0899",
    "sg:postcode":"77449",
    "sg:province":"TX",
    "sg:tags":[
        "supply"
    ],
    "wof:name":"Wet Harris County Mud 7",
    "wof:placetype":"venue"
},
  "geometry": {"coordinates":[-95.736125,29.80967],"type":"Point"}
}