{
  "type": "Feature",
  "properties": {
    "iso:country":"US",
    "sg:address":"1141 S 6th St",
    "sg:city":"Abilene",
    "sg:classifiers":[
        {
            "category":"Banks & Credit Unions",
            "subcategory":"Bank",
            "type":"Services"
        }
    ],
    "sg:phone":"+1 325 677 0094",
    "sg:postcode":"79602",
    "sg:province":"TX",
    "sg:tags":[
        "loan",
        "real estate"
    ],
    "wof:name":"Hankins Co",
    "wof:placetype":"venue"
},
  "geometry": {"coordinates":[-99.73630900000001,32.443441],"type":"Point"}
}