{
  "type": "Feature",
  "properties": {
    "iso:country":"US",
    "sg:address":"4503 Oak Club Dr",
    "sg:city":"Arlington",
    "sg:classifiers":[
        {
            "category":"Organizations",
            "subcategory":"Religious Organization",
            "type":"Services"
        }
    ],
    "sg:phone":"+1 817 797 0924",
    "sg:postcode":"76017",
    "sg:province":"TX",
    "sg:tags":[
        "place",
        "worship",
        "church"
    ],
    "wof:name":"Black Church Ministries Instit",
    "wof:placetype":"venue"
},
  "geometry": {"coordinates":[-97.15834599999999,32.672431],"type":"Point"}
}