{
  "type": "Feature",
  "properties": {
    "iso:country":"US",
    "sg:address":"271 E Lamar St",
    "sg:city":"Jasper",
    "sg:classifiers":[
        {
            "category":"Government",
            "subcategory":"Office",
            "type":"Public Place"
        }
    ],
    "sg:phone":"+1 409 384 2677",
    "sg:postcode":"75951",
    "sg:province":"TX",
    "sg:tags":[
        "state",
        "inspection"
    ],
    "wof:name":"Alcoholic Beverage Comm",
    "wof:placetype":"venue"
},
  "geometry": {"coordinates":[-93.998938,30.921759],"type":"Point"}
}