{
  "type": "Feature",
  "properties": {
    "iso:country":"US",
    "sg:address":"7805 Deer Trail Dr",
    "sg:city":"Dallas",
    "sg:classifiers":[
        {
            "category":"Professional",
            "type":"Services"
        }
    ],
    "sg:phone":"+1 214 348 5626",
    "sg:postcode":"75238",
    "sg:province":"TX",
    "wof:name":"Art Editor",
    "wof:placetype":"venue"
},
  "geometry": {"coordinates":[-96.728928,32.866343],"type":"Point"}
}