{
  "type": "Feature",
  "properties": {
    "iso:country":"US",
    "sg:address":"164 Augusta Dr",
    "sg:city":"Wimberley",
    "sg:classifiers":[
        {
            "category":"Professional",
            "subcategory":"Management & Consulting",
            "type":"Services"
        }
    ],
    "sg:phone":"+1 512 842 1613",
    "sg:postcode":"78676",
    "sg:province":"TX",
    "wof:name":"Attendee Management Inc",
    "wof:placetype":"venue"
},
  "geometry": {"coordinates":[-98.118206,30.03394],"type":"Point"}
}