{
  "type": "Feature",
  "properties": {
    "iso:country":"US",
    "sg:address":"8031 Wetherby Ln",
    "sg:city":"Houston",
    "sg:classifiers":[
        {
            "category":"Shopping",
            "subcategory":"Music",
            "type":"Retail Goods"
        }
    ],
    "sg:phone":"+1 713 991 7024",
    "sg:postcode":"77075",
    "sg:province":"TX",
    "wof:name":"Longevity Records Inc",
    "wof:placetype":"venue"
},
  "geometry": {"coordinates":[-95.27627200000001,29.620939],"type":"Point"}
}