{
  "type": "Feature",
  "properties": {
    "iso:country":"US",
    "sg:address":"14152 Ted Williams Rd",
    "sg:city":"Atascosa",
    "sg:classifiers":[
        {
            "category":"Building & Trades",
            "subcategory":"Construction",
            "type":"Services"
        }
    ],
    "sg:phone":"+1 830 709 0909",
    "sg:postcode":"78002",
    "sg:province":"TX",
    "sg:tags":[
        "underground",
        "excavation",
        "work",
        "ne",
        "utility"
    ],
    "wof:name":"Big Tex Contractors Inc",
    "wof:placetype":"venue"
},
  "geometry": {"coordinates":[-98.774283,29.289776],"type":"Point"}
}