{
  "type": "Feature",
  "properties": {
    "iso:country":"US",
    "sg:address":"2501 W Co Rd 114",
    "sg:city":"Midland",
    "sg:classifiers":[
        {
            "category":"Social Services",
            "subcategory":"Adult Care",
            "type":"Services"
        }
    ],
    "sg:phone":"+1 432 683 6292",
    "sg:postcode":"79706",
    "sg:province":"TX",
    "sg:tags":[
        "residential"
    ],
    "wof:name":"Country Acres",
    "wof:placetype":"venue"
},
  "geometry": {"coordinates":[-102.090189,31.963015],"type":"Point"}
}