{
  "type": "Feature",
  "properties": {
    "iso:country":"US",
    "sg:address":"3701 S Lancaster Rd",
    "sg:city":"Dallas",
    "sg:classifiers":[
        {
            "category":"Retail",
            "subcategory":"Car Wash",
            "type":"Services"
        }
    ],
    "sg:phone":"+1 214 375 7701",
    "sg:postcode":"75216",
    "sg:province":"TX",
    "sg:tags":[
        "automobile",
        "detail",
        "clean"
    ],
    "wof:name":"Ms V's Auto Detail",
    "wof:placetype":"venue"
},
  "geometry": {"coordinates":[-96.79827400000001,32.702661],"type":"Point"}
}