{
  "type": "Feature",
  "properties": {
    "iso:country":"US",
    "sg:address":"2481 County Road 224",
    "sg:city":"Florence",
    "sg:classifiers":[
        {
            "category":"Place Of Worship",
            "subcategory":"Church",
            "type":"Public Place"
        },
        {
            "category":"Place Of Worship",
            "type":"Public Place"
        }
    ],
    "sg:phone":"+1 254 793 2738",
    "sg:postcode":"76527",
    "sg:province":"TX",
    "sg:tags":[
        "churches-pentecostal-independent",
        "churches-pentecostal"
    ],
    "wof:name":"William Pentecost",
    "wof:placetype":"venue"
},
  "geometry": {"coordinates":[-97.86591300000001,30.869053],"type":"Point"}
}