{
  "type": "Feature",
  "properties": {
    "iso:country":"US",
    "sg:address":"3026 Sleepy Hollow Dr",
    "sg:city":"Sugar Land",
    "sg:classifiers":[
        {
            "category":"Building & Trades",
            "subcategory":"Construction",
            "type":"Services"
        }
    ],
    "sg:phone":"+1 281 242 6139",
    "sg:postcode":"77479",
    "sg:province":"TX",
    "sg:tags":[
        "house"
    ],
    "wof:name":"JP Savage Construction",
    "wof:placetype":"venue"
},
  "geometry": {"coordinates":[-95.59689899999999,29.578451],"type":"Point"}
}