{
  "type": "Feature",
  "properties": {
    "iso:country":"US",
    "sg:address":"706 N Main St",
    "sg:city":"Andrews",
    "sg:classifiers":[
        {
            "category":"Shopping",
            "subcategory":"Gifts & Souvenirs",
            "type":"Retail Goods"
        }
    ],
    "sg:phone":"+1 432 523 4213",
    "sg:postcode":"79714",
    "sg:province":"TX",
    "sg:tags":[
        "shop"
    ],
    "wof:name":"Something Special Gifts",
    "wof:placetype":"venue"
},
  "geometry": {"coordinates":[-102.54855000000001,32.325327],"type":"Point"}
}