{
  "type": "Feature",
  "properties": {
    "iso:country":"US",
    "sg:address":"5912 San Bernardo Ave",
    "sg:city":"Laredo",
    "sg:classifiers":[
        {
            "category":"Wholesale",
            "subcategory":"Farm Supplies",
            "type":"Manufacturing & Wholesale Goods"
        }
    ],
    "sg:phone":"+1 956 726 2497",
    "sg:postcode":"78041",
    "sg:province":"TX",
    "sg:tags":[
        "feed"
    ],
    "wof:name":"Laredo Ranch Supplies",
    "wof:placetype":"venue"
},
  "geometry": {"coordinates":[-99.504274,27.556219],"type":"Point"}
}