{
  "type": "Feature",
  "properties": {
    "iso:country":"US",
    "sg:address":"2500 E James St",
    "sg:city":"Baytown",
    "sg:classifiers":[
        {
            "category":"Arts & Performance",
            "subcategory":"Theater",
            "type":"Entertainment"
        }
    ],
    "sg:phone":"+1 281 837 0336",
    "sg:postcode":"77520",
    "sg:province":"TX",
    "sg:tags":[
        "group"
    ],
    "wof:name":"Bum Rush Entertainment",
    "wof:placetype":"venue"
},
  "geometry": {"coordinates":[-94.942216,29.727812],"type":"Point"}
}