{
  "type": "Feature",
  "properties": {
    "iso:country":"US",
    "sg:address":"6767 Southwest Fwy",
    "sg:city":"Houston",
    "sg:classifiers":[
        {
            "category":"Recreation",
            "subcategory":"Arcade",
            "type":"Entertainment"
        },
        {
            "category":"Sports & Exercise",
            "subcategory":"Golf",
            "type":"Entertainment"
        }
    ],
    "sg:phone":"+1 713 981 7888",
    "sg:postcode":"77074",
    "sg:province":"TX",
    "sg:tags":[
        "mini"
    ],
    "sg:website":"www.parcfuncenters.com/zshou.aspx",
    "wof:name":"Zuma Fun Center",
    "wof:placetype":"venue"
},
  "geometry": {"coordinates":[-95.501268,29.713098],"type":"Point"}
}