{
  "type": "Feature",
  "properties": {
    "iso:country":"US",
    "sg:address":"3506 Volcanic Ave",
    "sg:city":"El Paso",
    "sg:classifiers":[
        {
            "category":"Organizations",
            "subcategory":"Religious Organization",
            "type":"Services"
        }
    ],
    "sg:phone":"+1 915 755 7409",
    "sg:postcode":"79904",
    "sg:province":"TX",
    "wof:name":"Light of Life Ministries",
    "wof:placetype":"venue"
},
  "geometry": {"coordinates":[-106.452671,31.852163],"type":"Point"}
}