{
  "type": "Feature",
  "properties": {
    "iso:country":"US",
    "sg:address":"9711 Eastwend Dr",
    "sg:city":"Austin",
    "sg:classifiers":[
        {
            "category":"Retail",
            "subcategory":"Auto Repair",
            "type":"Services"
        }
    ],
    "sg:phone":"+1 512 837 9413",
    "sg:postcode":"78753",
    "sg:province":"TX",
    "sg:tags":[
        "automobile",
        "installation",
        "glass"
    ],
    "wof:name":"A Line Auto Glass",
    "wof:placetype":"venue"
},
  "geometry": {"coordinates":[-97.69264,30.364812],"type":"Point"}
}