{
  "type": "Feature",
  "properties": {
    "iso:country":"US",
    "sg:address":"323 N Nelson St",
    "sg:city":"Amarillo",
    "sg:classifiers":[
        {
            "category":"Manufacturing",
            "subcategory":"Tools & Machinery",
            "type":"Manufacturing & Wholesale Goods"
        }
    ],
    "sg:phone":"+1 806 374 0800",
    "sg:postcode":"79107",
    "sg:province":"TX",
    "sg:tags":[
        "mfg",
        "filtration",
        "air"
    ],
    "wof:name":"Filter Max Inc",
    "wof:placetype":"venue"
},
  "geometry": {"coordinates":[-101.806682,35.216133],"type":"Point"}
}