{
  "type": "Feature",
  "properties": {
    "iso:country":"US",
    "sg:address":"6048 Gulfway Dr",
    "sg:city":"Port Arthur",
    "sg:classifiers":[
        {
            "category":"Food & Beverages",
            "subcategory":"Meat & Fish",
            "type":"Retail Goods"
        }
    ],
    "sg:phone":"+1 409 960 7760",
    "sg:postcode":"77642",
    "sg:province":"TX",
    "wof:name":"Lone Star Meat Mkt & Smkhs",
    "wof:placetype":"venue"
},
  "geometry": {"coordinates":[-93.901034,29.930986],"type":"Point"}
}