{
  "type": "Feature",
  "properties": {
    "iso:country":"US",
    "sg:address":"5513 Courtyard Dr",
    "sg:city":"Austin",
    "sg:classifiers":[
        {
            "category":"Health Services",
            "subcategory":"Doctor",
            "type":"Services"
        }
    ],
    "sg:phone":"+1 512 795 8800",
    "sg:postcode":"78731",
    "sg:province":"TX",
    "sg:tags":[
        "medical"
    ],
    "wof:name":"Luis M Suarez MD",
    "wof:placetype":"venue"
},
  "geometry": {"coordinates":[-97.795158,30.352327],"type":"Point"}
}