{
  "type": "Feature",
  "properties": {
    "iso:country":"US",
    "sg:address":"16307 Pradera Dr",
    "sg:city":"Houston",
    "sg:classifiers":[
        {
            "category":"Retail",
            "subcategory":"Repair Shop",
            "type":"Services"
        }
    ],
    "sg:phone":"+1 281 277 6574",
    "sg:postcode":"77083",
    "sg:province":"TX",
    "sg:tags":[
        "welding"
    ],
    "wof:name":"Skc Welding Service",
    "wof:placetype":"venue"
},
  "geometry": {"coordinates":[-95.674283,29.690288],"type":"Point"}
}