{
  "type": "Feature",
  "properties": {
    "iso:country":"US",
    "sg:address":"2350 N Stemmons Fwy",
    "sg:city":"Dallas",
    "sg:classifiers":[
        {
            "category":"Wholesale",
            "subcategory":"Apparel",
            "type":"Manufacturing & Wholesale Goods"
        }
    ],
    "sg:phone":"+1 214 634 9414",
    "sg:postcode":"75207",
    "sg:province":"TX",
    "sg:tags":[
        "clothing"
    ],
    "wof:name":"Bob Denton Apparel Sales",
    "wof:placetype":"venue"
},
  "geometry": {"coordinates":[-96.83231000000001,32.80221],"type":"Point"}
}