{
  "type": "Feature",
  "properties": {
    "iso:country":"US",
    "sg:address":"1208 14th St",
    "sg:city":"Plano",
    "sg:classifiers":[
        {
            "category":"Building & Trades",
            "subcategory":"Plumbing",
            "type":"Services"
        }
    ],
    "sg:phone":"+1 972 424 6274",
    "sg:postcode":"75074",
    "sg:province":"TX",
    "sg:tags":[
        "plumbing",
        "contractor"
    ],
    "wof:name":"Terrell Plumbing Co",
    "wof:placetype":"venue"
},
  "geometry": {"coordinates":[-96.69657100000001,33.01826],"type":"Point"}
}