{
  "type": "Feature",
  "properties": {
    "iso:country":"US",
    "sg:address":"1303 W Durango Blvd",
    "sg:city":"San Antonio",
    "sg:classifiers":[
        {
            "category":"Education",
            "subcategory":"School",
            "type":"Public Place"
        }
    ],
    "sg:phone":"+1 210 227 3383",
    "sg:postcode":"78207",
    "sg:province":"TX",
    "wof:name":"Tafolla Middle School",
    "wof:placetype":"venue"
},
  "geometry": {"coordinates":[-98.512518,29.422584],"type":"Point"}
}