{
  "type": "Feature",
  "properties": {
    "iso:country":"US",
    "sg:address":"404 Avondale Ln",
    "sg:city":"Friendswood",
    "sg:classifiers":[
        {
            "category":"Wholesale",
            "subcategory":"Office Equipment",
            "type":"Manufacturing & Wholesale Goods"
        }
    ],
    "sg:phone":"+1 281 482 9725",
    "sg:postcode":"77546",
    "sg:province":"TX",
    "wof:name":"CPR Paper & Ribbons",
    "wof:placetype":"venue"
},
  "geometry": {"coordinates":[-95.217471,29.532326],"type":"Point"}
}