{
  "type": "Feature",
  "properties": {
    "iso:country":"US",
    "sg:address":"613 Lucero St",
    "sg:city":"Alice",
    "sg:classifiers":[
        {
            "category":"Personal",
            "subcategory":"Beauty Salon",
            "type":"Services"
        }
    ],
    "sg:phone":"+1 361 668 1666",
    "sg:postcode":"78332",
    "sg:province":"TX",
    "sg:tags":[
        "shop"
    ],
    "wof:name":"Scissor KUT Studio Salon",
    "wof:placetype":"venue"
},
  "geometry": {"coordinates":[-98.07092799999999,27.747104],"type":"Point"}
}