{
  "type": "Feature",
  "properties": {
    "iso:country":"US",
    "sg:address":"4916 Wood Creek Dr",
    "sg:city":"Nacogdoches",
    "sg:classifiers":[
        {
            "category":"Building & Trades",
            "subcategory":"Landscaping Services",
            "type":"Services"
        }
    ],
    "sg:phone":"+1 936 559 0478",
    "sg:postcode":"75965",
    "sg:province":"TX",
    "wof:name":"L & L Lawn Maintenance",
    "wof:placetype":"venue"
},
  "geometry": {"coordinates":[-94.661311,31.651321],"type":"Point"}
}