{
  "type": "Feature",
  "properties": {
    "iso:country":"US",
    "sg:address":"7975 Bellfort St",
    "sg:city":"Houston",
    "sg:classifiers":[
        {
            "category":"Retail",
            "subcategory":"Repair Shop",
            "type":"Services"
        },
        {
            "category":"Shopping",
            "subcategory":"Antiques",
            "type":"Retail Goods"
        },
        {
            "category":"Home & Garden",
            "subcategory":"Furniture",
            "type":"Retail Goods"
        }
    ],
    "sg:phone":"+1 713 644 1894",
    "sg:postcode":"77061",
    "sg:province":"TX",
    "sg:tags":[
        "refinish",
        "store"
    ],
    "wof:name":"L & P Furniture Restoration of Houston",
    "wof:placetype":"venue"
},
  "geometry": {"coordinates":[-95.2696,29.6745],"type":"Point"}
}