{
  "type": "Feature",
  "properties": {
    "iso:country":"US",
    "sg:address":"506 Brookwood Dr",
    "sg:city":"Waco",
    "sg:classifiers":[
        {
            "category":"Professional",
            "subcategory":"Art Services",
            "type":"Services"
        }
    ],
    "sg:phone":"+1 254 751 0109",
    "sg:postcode":"76712",
    "sg:province":"TX",
    "sg:tags":[
        "commercial",
        "design"
    ],
    "wof:name":"Wide Open Graphics",
    "wof:placetype":"venue"
},
  "geometry": {"coordinates":[-97.23042700000001,31.500151],"type":"Point"}
}