{
  "type": "Feature",
  "properties": {
    "iso:country":"US",
    "sg:address":"3208 Seymour Rd",
    "sg:city":"Wichita Falls",
    "sg:classifiers":[
        {
            "category":"Social Services",
            "subcategory":"Child Care",
            "type":"Services"
        }
    ],
    "sg:phone":"+1 940 322 6262",
    "sg:postcode":"76309",
    "sg:province":"TX",
    "wof:name":"Seymour Road Day School",
    "wof:placetype":"venue"
},
  "geometry": {"coordinates":[-98.53238899999999,33.89764],"type":"Point"}
}