{
  "type": "Feature",
  "properties": {
    "iso:country":"US",
    "sg:address":"3500 N Terminal Rd",
    "sg:city":"Houston",
    "sg:classifiers":[
        {
            "category":"Shopping",
            "subcategory":"Gifts & Souvenirs",
            "type":"Retail Goods"
        }
    ],
    "sg:phone":"+1 281 821 7700",
    "sg:postcode":"77032",
    "sg:province":"TX",
    "sg:tags":[
        "shop"
    ],
    "sg:website":"www.disneystore.com",
    "wof:name":"Disney Store",
    "wof:placetype":"venue"
},
  "geometry": {"coordinates":[-95.341509,29.987329],"type":"Point"}
}