{
  "type": "Feature",
  "properties": {
    "iso:country":"US",
    "sg:address":"2600 N Ware Rd",
    "sg:city":"Mcallen",
    "sg:classifiers":[
        {
            "category":"Personal",
            "subcategory":"Beauty Salon",
            "type":"Services"
        }
    ],
    "sg:phone":"+1 956 682 9055",
    "sg:postcode":"78501",
    "sg:province":"TX",
    "wof:name":"Hair By Iris",
    "wof:placetype":"venue"
},
  "geometry": {"coordinates":[-98.25743900000001,26.23189],"type":"Point"}
}