{
  "type": "Feature",
  "properties": {
    "iso:country":"US",
    "sg:address":"4856 Co Rd 1126",
    "sg:city":"Cleburne",
    "sg:classifiers":[
        {
            "category":"Professional",
            "subcategory":"Business Services",
            "type":"Services"
        }
    ],
    "sg:phone":"+1 817 558 0583",
    "sg:postcode":"76033",
    "sg:province":"TX",
    "wof:name":"Sports Page Pro Mgmt",
    "wof:placetype":"venue"
},
  "geometry": {"coordinates":[-97.46571299999999,32.414145],"type":"Point"}
}