{
  "type": "Feature",
  "properties": {
    "iso:country":"US",
    "sg:address":"3007 E Hwy 82",
    "sg:city":"Gainesville",
    "sg:classifiers":[
        {
            "category":"Restaurant",
            "type":"Food & Drink"
        }
    ],
    "sg:phone":"+1 940 668 8325",
    "sg:postcode":"76240",
    "sg:province":"TX",
    "sg:tags":[
        "eating"
    ],
    "wof:name":"Trails Inn Restaurant",
    "wof:placetype":"venue"
},
  "geometry": {"coordinates":[-97.109773,33.643791],"type":"Point"}
}