{
  "type": "Feature",
  "properties": {
    "iso:country":"US",
    "sg:address":"350 N Riverside Dr",
    "sg:city":"Fort Worth",
    "sg:classifiers":[
        {
            "category":"Food & Beverages",
            "subcategory":"Groceries & Convenience Stores",
            "type":"Retail Goods"
        }
    ],
    "sg:phone":"+1 817 831 1828",
    "sg:postcode":"76111",
    "sg:province":"TX",
    "wof:name":"Riverside Food Mart",
    "wof:placetype":"venue"
},
  "geometry": {"coordinates":[-97.301647,32.769868],"type":"Point"}
}