{
  "type": "Feature",
  "properties": {
    "iso:country":"US",
    "sg:address":"1002 Gemini St",
    "sg:city":"Houston",
    "sg:classifiers":[
        {
            "category":"Professional",
            "subcategory":"Accounting & Tax Preparation",
            "type":"Services"
        }
    ],
    "sg:phone":"+1 281 488 1854",
    "sg:postcode":"77058",
    "sg:province":"TX",
    "wof:name":"Thomas G Reed CPA",
    "wof:placetype":"venue"
},
  "geometry": {"coordinates":[-95.114526,29.555201],"type":"Point"}
}