{
  "type": "Feature",
  "properties": {
    "iso:country":"US",
    "sg:address":"20439 Ravenwood Dr",
    "sg:city":"Porter",
    "sg:classifiers":[
        {
            "category":"Building & Trades",
            "subcategory":"Construction",
            "type":"Services"
        }
    ],
    "sg:phone":"+1 281 354 2696",
    "sg:postcode":"77365",
    "sg:province":"TX",
    "sg:tags":[
        "wallcoverings-installation",
        "wallpaper",
        "painting",
        "contractor"
    ],
    "wof:name":"Samuel Rodriguez Painting Con",
    "wof:placetype":"venue"
},
  "geometry": {"coordinates":[-95.260471,30.082147],"type":"Point"}
}