{
  "type": "Feature",
  "properties": {
    "iso:country":"US",
    "sg:address":"1110 Eidson Rd",
    "sg:city":"Eagle Pass",
    "sg:classifiers":[
        {
            "category":"Organizations",
            "subcategory":"Religious Organization",
            "type":"Services"
        }
    ],
    "sg:phone":"+1 830 773 5580",
    "sg:postcode":"78852",
    "sg:province":"TX",
    "wof:name":"River of Life Church",
    "wof:placetype":"venue"
},
  "geometry": {"coordinates":[-100.48732200000001,28.692522],"type":"Point"}
}