{
  "type": "Feature",
  "properties": {
    "iso:country":"US",
    "sg:address":"1924 W Oaklawn Rd",
    "sg:city":"Pleasanton",
    "sg:classifiers":[
        {
            "category":"Retail",
            "subcategory":"Animal Services",
            "type":"Services"
        }
    ],
    "sg:phone":"+1 830 281 3644",
    "sg:postcode":"78064",
    "sg:province":"TX",
    "sg:tags":[
        "pet",
        "grooming",
        "washing"
    ],
    "wof:name":"Dog World",
    "wof:placetype":"venue"
},
  "geometry": {"coordinates":[-98.512095,28.940726],"type":"Point"}
}