{
  "type": "Feature",
  "properties": {
    "iso:country":"US",
    "sg:address":"805 Main St",
    "sg:city":"Bandera",
    "sg:classifiers":[
        {
            "category":"Shopping",
            "subcategory":"Discount & Variety Stores",
            "type":"Retail Goods"
        },
        {
            "category":"Shopping",
            "subcategory":"Department Store",
            "type":"Retail Goods"
        }
    ],
    "sg:phone":"+1 830 796 3883",
    "sg:postcode":"78003",
    "sg:province":"TX",
    "sg:tags":[
        "shop"
    ],
    "wof:name":"Family Dollar Stores",
    "wof:placetype":"venue"
},
  "geometry": {"coordinates":[-99.069463,29.723368],"type":"Point"}
}