{
  "type": "Feature",
  "properties": {
    "iso:country":"US",
    "sg:address":"2206 E James St",
    "sg:city":"Baytown",
    "sg:classifiers":[
        {
            "category":"Food & Beverages",
            "subcategory":"Groceries & Convenience Stores",
            "type":"Retail Goods"
        }
    ],
    "sg:phone":"+1 281 422 2901",
    "sg:postcode":"77520",
    "sg:province":"TX",
    "wof:name":"Stop-N-All",
    "wof:placetype":"venue"
},
  "geometry": {"coordinates":[-94.94290100000001,29.728121],"type":"Point"}
}