{
  "type": "Feature",
  "properties": {
    "iso:country":"US",
    "sg:address":"131 Degan Ave Ste 201",
    "sg:city":"Lewisville",
    "sg:classifiers":[
        {
            "category":"Health Services",
            "subcategory":"Doctor",
            "type":"Services"
        },
        {
            "category":"Social Services",
            "type":"Services"
        },
        {
            "category":"Personal",
            "type":"Services"
        }
    ],
    "sg:phone":"+1 972 436 8881",
    "sg:postcode":"75057",
    "sg:province":"TX",
    "sg:tags":[
        "family",
        "counselors-licensed",
        "psychologist",
        "individual",
        "marriage",
        "child",
        "professional",
        "counselor"
    ],
    "wof:name":"Family Wellness Center",
    "wof:placetype":"venue"
},
  "geometry": {"coordinates":[-97.006918,33.046794],"type":"Point"}
}