{
  "type": "Feature",
  "properties": {
    "iso:country":"US",
    "sg:address":"8701 Gateway Blvd W",
    "sg:city":"El Paso",
    "sg:classifiers":[
        {
            "category":"Building & Trades",
            "subcategory":"Construction",
            "type":"Services"
        }
    ],
    "sg:phone":"+1 915 771 7727",
    "sg:postcode":"79935",
    "sg:province":"TX",
    "sg:tags":[
        "house"
    ],
    "wof:name":"U S Builders Inc",
    "wof:placetype":"venue"
},
  "geometry": {"coordinates":[-106.378162,31.772395],"type":"Point"}
}