{
  "type": "Feature",
  "properties": {
    "iso:country":"US",
    "sg:address":"2329 E Hwy 35",
    "sg:city":"Angleton",
    "sg:classifiers":[
        {
            "category":"Retail",
            "subcategory":"Auto Repair",
            "type":"Services"
        }
    ],
    "sg:phone":"+1 979 849 4397",
    "sg:postcode":"77515",
    "sg:province":"TX",
    "sg:tags":[
        "machine",
        "automobile",
        "shop"
    ],
    "wof:name":"Angleton Automotive Machine",
    "wof:placetype":"venue"
},
  "geometry": {"coordinates":[-95.40734500000001,29.186308],"type":"Point"}
}