{
  "type": "Feature",
  "properties": {
    "iso:country":"US",
    "sg:address":"4425 S Mo Pac Expy Ste 600",
    "sg:city":"Austin",
    "sg:classifiers":[
        {
            "category":"Wholesale",
            "subcategory":"Books, Periodicals, & Newspapers",
            "type":"Manufacturing & Wholesale Goods"
        }
    ],
    "sg:phone":"+1 512 891 6100",
    "sg:postcode":"78735",
    "sg:province":"TX",
    "sg:tags":[
        "publisher",
        "book"
    ],
    "wof:name":"Greenleaf Book Group",
    "wof:placetype":"venue"
},
  "geometry": {"coordinates":[-97.81495700000001,30.240142],"type":"Point"}
}