{
  "type": "Feature",
  "properties": {
    "iso:country":"US",
    "sg:address":"713 Sidney Baker St",
    "sg:city":"Kerrville",
    "sg:classifiers":[
        {
            "category":"Shopping",
            "subcategory":"Computers & Home Electronics",
            "type":"Retail Goods"
        }
    ],
    "sg:phone":"+1 830 895 1011",
    "sg:postcode":"78028",
    "sg:province":"TX",
    "sg:tags":[
        "equipment",
        "dealer"
    ],
    "sg:website":"www.mycomputerclinic.com",
    "wof:name":"Computer Clinic",
    "wof:placetype":"venue"
},
  "geometry": {"coordinates":[-99.134298,30.052814],"type":"Point"}
}