{
  "type": "Feature",
  "properties": {
    "iso:country":"US",
    "sg:address":"401 Imperial Dr",
    "sg:city":"Allen",
    "sg:classifiers":[
        {
            "category":"Professional",
            "subcategory":"Accounting & Tax Preparation",
            "type":"Services"
        }
    ],
    "sg:phone":"+1 972 727 4530",
    "sg:postcode":"75013",
    "sg:province":"TX",
    "sg:tags":[
        "accountant"
    ],
    "wof:name":"Dees Fuller & Assoc",
    "wof:placetype":"venue"
},
  "geometry": {"coordinates":[-96.70438300000001,33.097527],"type":"Point"}
}