{
  "type": "Feature",
  "properties": {
    "iso:country":"US",
    "sg:address":"1025 W Airport Fwy",
    "sg:city":"Irving",
    "sg:classifiers":[
        {
            "category":"Food & Beverages",
            "subcategory":"Groceries & Convenience Stores",
            "type":"Retail Goods"
        }
    ],
    "sg:phone":"+1 972 252 9775",
    "sg:postcode":"75062",
    "sg:province":"TX",
    "wof:name":"7-Eleven",
    "wof:placetype":"venue"
},
  "geometry": {"coordinates":[-96.95718100000001,32.837375],"type":"Point"}
}