{
  "type": "Feature",
  "properties": {
    "iso:country":"US",
    "sg:address":"1528 FM 1845 S",
    "sg:city":"Longview",
    "sg:classifiers":[
        {
            "category":"Restaurant",
            "type":"Food & Drink"
        }
    ],
    "sg:phone":"+1 903 753 9219",
    "sg:postcode":"75603",
    "sg:province":"TX",
    "sg:tags":[
        "cafe"
    ],
    "wof:name":"Stockyard's Cafe",
    "wof:placetype":"venue"
},
  "geometry": {"coordinates":[-94.76577,32.470217],"type":"Point"}
}