{
  "type": "Feature",
  "properties": {
    "iso:country":"US",
    "sg:address":"806 S 12th St",
    "sg:city":"Mcallen",
    "sg:classifiers":[
        {
            "category":"Health Services",
            "subcategory":"Doctor",
            "type":"Services"
        }
    ],
    "sg:phone":"+1 956 687 1308",
    "sg:postcode":"78501",
    "sg:province":"TX",
    "sg:tags":[
        "clinic"
    ],
    "wof:name":"Mc Allen Maternity Clinic",
    "wof:placetype":"venue"
},
  "geometry": {"coordinates":[-98.233852,26.194723],"type":"Point"}
}