{
  "type": "Feature",
  "properties": {
    "iso:country":"US",
    "sg:address":"901 Dalworth Dr",
    "sg:city":"Mesquite",
    "sg:classifiers":[
        {
            "category":"Building & Trades",
            "subcategory":"Landscaping Services",
            "type":"Services"
        }
    ],
    "sg:phone":"+1 972 289 3051",
    "sg:postcode":"75149",
    "sg:province":"TX",
    "wof:name":"Pantry Inc",
    "wof:placetype":"venue"
},
  "geometry": {"coordinates":[-96.608538,32.769499],"type":"Point"}
}