{
  "type": "Feature",
  "properties": {
    "iso:country":"US",
    "sg:address":"531 Crockett St",
    "sg:city":"Channelview",
    "sg:classifiers":[
        {
            "category":"Autos & Motor Vehicles",
            "subcategory":"Automobile Sales",
            "type":"Retail Goods"
        }
    ],
    "sg:phone":"+1 281 452 9992",
    "sg:postcode":"77530",
    "sg:province":"TX",
    "sg:tags":[
        "used"
    ],
    "wof:name":"Galaxy Moters Inc",
    "wof:placetype":"venue"
},
  "geometry": {"coordinates":[-95.11600799999999,29.779514],"type":"Point"}
}