{
  "type": "Feature",
  "properties": {
    "iso:country":"US",
    "sg:address":"25700 I- 45",
    "sg:city":"Spring",
    "sg:classifiers":[
        {
            "category":"Banks & Credit Unions",
            "subcategory":"Bank",
            "type":"Services"
        }
    ],
    "sg:phone":"+1 281 298 9600",
    "sg:postcode":"77386",
    "sg:province":"TX",
    "sg:tags":[
        "loan"
    ],
    "wof:name":"Gateway Mortgage Group",
    "wof:placetype":"venue"
},
  "geometry": {"coordinates":[-95.44475300000001,30.136971],"type":"Point"}
}