{
  "type": "Feature",
  "properties": {
    "iso:country":"US",
    "sg:address":"2500 Citywest Blvd # 400",
    "sg:city":"Houston",
    "sg:classifiers":[
        {
            "category":"Utilities",
            "subcategory":"Natural Gas",
            "type":"Services"
        }
    ],
    "sg:phone":"+1 713 784 5634",
    "sg:postcode":"77042",
    "sg:province":"TX",
    "sg:tags":[
        "propane"
    ],
    "wof:name":"Prime Flexible Products, Inc.",
    "wof:placetype":"venue"
},
  "geometry": {"coordinates":[-95.56137099999999,29.739519],"type":"Point"}
}