{
  "type": "Feature",
  "properties": {
    "iso:country":"US",
    "sg:address":"14620 Hempstead Rd",
    "sg:city":"Houston",
    "sg:classifiers":[
        {
            "category":"Wholesale",
            "subcategory":"Machinery & Supplies",
            "type":"Manufacturing & Wholesale Goods"
        },
        {
            "category":"Wholesale",
            "subcategory":"Electrical",
            "type":"Manufacturing & Wholesale Goods"
        }
    ],
    "sg:phone":"+1 713 462 7381",
    "sg:postcode":"77040",
    "sg:province":"TX",
    "sg:tags":[
        "control",
        "equipment",
        "industrial"
    ],
    "wof:name":"Advance Controls & Automation",
    "wof:placetype":"venue"
},
  "geometry": {"coordinates":[-95.54318499999999,29.861054],"type":"Point"}
}