{
  "type": "Feature",
  "properties": {
    "iso:country":"US",
    "sg:address":"7141 Bellfort St",
    "sg:city":"Houston",
    "sg:classifiers":[
        {
            "category":"Professional",
            "subcategory":"Accounting & Tax Preparation",
            "type":"Services"
        }
    ],
    "sg:phone":"+1 713 242 0712",
    "sg:postcode":"77087",
    "sg:province":"TX",
    "sg:tags":[
        "return"
    ],
    "wof:name":"Service Aaa Tax",
    "wof:placetype":"venue"
},
  "geometry": {"coordinates":[-95.30262,29.67128],"type":"Point"}
}