{
  "type": "Feature",
  "properties": {
    "iso:country":"US",
    "sg:address":"6601 Bee Caves Rd",
    "sg:city":"Austin",
    "sg:classifiers":[
        {
            "category":"Real Estate",
            "subcategory":"Architect",
            "type":"Services"
        }
    ],
    "sg:phone":"+1 512 306 9723",
    "sg:postcode":"78746",
    "sg:province":"TX",
    "sg:tags":[
        "architects'",
        "specification",
        "construction",
        "builders'",
        "architectural"
    ],
    "wof:name":"J Ad Interest Inc.",
    "wof:placetype":"venue"
},
  "geometry": {"coordinates":[-97.835964,30.297093],"type":"Point"}
}