{
  "type": "Feature",
  "properties": {
    "iso:country":"US",
    "sg:address":"123 US Hwy 96",
    "sg:city":"Center",
    "sg:classifiers":[
        {
            "category":"Personal",
            "subcategory":"Beauty Salon",
            "type":"Services"
        }
    ],
    "sg:phone":"+1 936 598 2889",
    "sg:postcode":"75935",
    "sg:province":"TX",
    "wof:name":"Finish Line Salon",
    "wof:placetype":"venue"
},
  "geometry": {"coordinates":[-94.187478,31.791834],"type":"Point"}
}