{
  "type": "Feature",
  "properties": {
    "iso:country":"US",
    "sg:address":"85 Carriage Rd",
    "sg:city":"Abilene",
    "sg:classifiers":[
        {
            "category":"Manufacturing",
            "subcategory":"Wood Products",
            "type":"Manufacturing & Wholesale Goods"
        }
    ],
    "sg:phone":"+1 325 695 0378",
    "sg:postcode":"79605",
    "sg:province":"TX",
    "sg:tags":[
        "mfg"
    ],
    "wof:name":"Hardwood Items",
    "wof:placetype":"venue"
},
  "geometry": {"coordinates":[-99.769284,32.409868],"type":"Point"}
}