{
  "type": "Feature",
  "properties": {
    "iso:country":"US",
    "sg:address":"3560 Delaware St",
    "sg:city":"Beaumont",
    "sg:classifiers":[
        {
            "category":"Professional",
            "subcategory":"Accounting & Tax Preparation",
            "type":"Services"
        }
    ],
    "sg:phone":"+1 409 899 1040",
    "sg:postcode":"77706",
    "sg:province":"TX",
    "wof:name":"Edwards Charlotte E",
    "wof:placetype":"venue"
},
  "geometry": {"coordinates":[-94.140557,30.104531],"type":"Point"}
}