{
  "type": "Feature",
  "properties": {
    "iso:country":"US",
    "sg:address":"429 Lake Terrace Dr",
    "sg:city":"Azle",
    "sg:classifiers":[
        {
            "category":"Professional",
            "subcategory":"Art Services",
            "type":"Services"
        }
    ],
    "sg:phone":"+1 817 237 7759",
    "sg:postcode":"76020",
    "sg:province":"TX",
    "sg:tags":[
        "commercial",
        "design"
    ],
    "wof:name":"Skc Design",
    "wof:placetype":"venue"
},
  "geometry": {"coordinates":[-97.514854,32.868045],"type":"Point"}
}