{
  "type": "Feature",
  "properties": {
    "iso:country":"US",
    "sg:address":"5811 Woodcraft",
    "sg:city":"San Antonio",
    "sg:classifiers":[
        {
            "category":"Professional",
            "subcategory":"Business Services",
            "type":"Services"
        }
    ],
    "sg:phone":"+1 210 666 2123",
    "sg:postcode":"78218",
    "sg:province":"TX",
    "wof:name":"Deaf Communication Access",
    "wof:placetype":"venue"
},
  "geometry": {"coordinates":[-98.387125,29.48033],"type":"Point"}
}