{
  "type": "Feature",
  "properties": {
    "iso:country":"US",
    "sg:address":"5200 Bissonnet St",
    "sg:city":"Bellaire",
    "sg:classifiers":[
        {
            "category":"Real Estate",
            "subcategory":"Real Estate Services",
            "type":"Services"
        }
    ],
    "sg:phone":"+1 713 349 9700",
    "sg:postcode":"77401",
    "sg:province":"TX",
    "sg:tags":[
        "management",
        "property"
    ],
    "wof:name":"Coldwell Banker United Realtors",
    "wof:placetype":"venue"
},
  "geometry": {"coordinates":[-95.470596,29.7064],"type":"Point"}
}