{
  "type": "Feature",
  "properties": {
    "iso:country":"US",
    "sg:address":"4400 W Park Row Blvd",
    "sg:city":"Corsicana",
    "sg:classifiers":[
        {
            "category":"Autos & Motor Vehicles",
            "subcategory":"Automobile Sales",
            "type":"Retail Goods"
        }
    ],
    "sg:phone":"+1 903 874 4310",
    "sg:postcode":"75110",
    "sg:province":"TX",
    "sg:tags":[
        "used"
    ],
    "wof:name":"Owen Motor Co",
    "wof:placetype":"venue"
},
  "geometry": {"coordinates":[-96.51030799999999,32.061478],"type":"Point"}
}