{
  "type": "Feature",
  "properties": {
    "iso:country":"US",
    "sg:address":"7442 Reindeer Trl",
    "sg:city":"Leon Valley",
    "sg:classifiers":[
        {
            "category":"Food & Beverages",
            "subcategory":"Specialty",
            "type":"Retail Goods"
        }
    ],
    "sg:phone":"+1 210 521 5282",
    "sg:postcode":"78238",
    "sg:province":"TX",
    "sg:tags":[
        "tea",
        "coffee"
    ],
    "wof:name":"De Coty Coffee Co",
    "wof:placetype":"venue"
},
  "geometry": {"coordinates":[-98.629715,29.500721],"type":"Point"}
}