{
  "type": "Feature",
  "properties": {
    "iso:country":"US",
    "sg:address":"9951 Harwin Dr",
    "sg:city":"Houston",
    "sg:classifiers":[
        {
            "category":"Retail",
            "subcategory":"Storage",
            "type":"Services"
        }
    ],
    "sg:phone":"+1 866 838 2192",
    "sg:postcode":"77036",
    "sg:province":"TX",
    "sg:tags":[
        "self"
    ],
    "sg:website":"www.unclebobs.com/",
    "wof:name":"Uncle Bob's Self Storage",
    "wof:placetype":"venue"
},
  "geometry": {"coordinates":[-95.53667799999999,29.716581],"type":"Point"}
}