{
  "type": "Feature",
  "properties": {
    "iso:country":"US",
    "sg:address":"412 Dallas St",
    "sg:city":"Wichita Falls",
    "sg:classifiers":[
        {
            "category":"Organizations",
            "subcategory":"Religious Organization",
            "type":"Services"
        }
    ],
    "sg:phone":"+1 940 766 0316",
    "sg:postcode":"76301",
    "sg:province":"TX",
    "sg:tags":[
        "church"
    ],
    "wof:name":"St Matthew's Baptist Church",
    "wof:placetype":"venue"
},
  "geometry": {"coordinates":[-98.480887,33.90208],"type":"Point"}
}