{
  "type": "Feature",
  "properties": {
    "iso:country":"US",
    "sg:address":"404 N Rosenstein St",
    "sg:city":"Bells",
    "sg:classifiers":[
        {
            "category":"Building & Trades",
            "subcategory":"Construction",
            "type":"Services"
        }
    ],
    "sg:phone":"+1 903 965 4625",
    "sg:postcode":"75414",
    "sg:province":"TX",
    "sg:tags":[
        "water",
        "well",
        "drilling"
    ],
    "wof:name":"Joe A Witherspoon Water Wells",
    "wof:placetype":"venue"
},
  "geometry": {"coordinates":[-96.411569,33.614493],"type":"Point"}
}