{
  "type": "Feature",
  "properties": {
    "iso:country":"US",
    "sg:address":"1861 Brown Blvd",
    "sg:city":"Arlington",
    "sg:classifiers":[
        {
            "category":"Personal",
            "type":"Services"
        }
    ],
    "sg:phone":"+1 817 226 4999",
    "sg:postcode":"76006",
    "sg:province":"TX",
    "sg:tags":[
        "program",
        "physical",
        "exercise",
        "fitness"
    ],
    "wof:name":"Motivation Fitness Studio",
    "wof:placetype":"venue"
},
  "geometry": {"coordinates":[-97.082554,32.773376],"type":"Point"}
}