{
  "type": "Feature",
  "properties": {
    "iso:country":"US",
    "sg:address":"1625 S Jackson St",
    "sg:city":"Jacksonville",
    "sg:classifiers":[
        {
            "category":"Personal",
            "subcategory":"Beauty Salon",
            "type":"Services"
        }
    ],
    "sg:phone":"+1 903 541 0924",
    "sg:postcode":"75766",
    "sg:province":"TX",
    "sg:tags":[
        "shop"
    ],
    "wof:name":"Chrissy's Creative Cuts",
    "wof:placetype":"venue"
},
  "geometry": {"coordinates":[-95.262541,31.950222],"type":"Point"}
}