{
  "type": "Feature",
  "properties": {
    "iso:country":"US",
    "sg:address":"4028 Lago Viento",
    "sg:city":"Austin",
    "sg:classifiers":[
        {
            "category":"Professional",
            "subcategory":"Computer Services",
            "type":"Services"
        }
    ],
    "sg:phone":"+1 512 423 1532",
    "sg:postcode":"78734",
    "sg:province":"TX",
    "sg:tags":[
        "programing",
        "custom"
    ],
    "wof:name":"Train Artisan",
    "wof:placetype":"venue"
},
  "geometry": {"coordinates":[-97.923489,30.397723],"type":"Point"}
}