{
  "type": "Feature",
  "properties": {
    "iso:country":"US",
    "sg:address":"5424 Basswood Blvd",
    "sg:city":"Fort Worth",
    "sg:classifiers":[
        {
            "category":"Retail",
            "subcategory":"Veterinary Services",
            "type":"Services"
        }
    ],
    "sg:phone":"+1 817 581 1277",
    "sg:postcode":"76137",
    "sg:province":"TX",
    "sg:tags":[
        "veterinarian"
    ],
    "wof:name":"Animal Hospital",
    "wof:placetype":"venue"
},
  "geometry": {"coordinates":[-97.267431,32.874371],"type":"Point"}
}