{
  "type": "Feature",
  "properties": {
    "iso:country":"US",
    "sg:address":"11511 Luna Road",
    "sg:city":"Dallas",
    "sg:classifiers":[
        {
            "category":"Professional",
            "subcategory":"Business Services",
            "type":"Services"
        }
    ],
    "sg:phone":"+1 214 956 4231",
    "sg:postcode":"75234",
    "sg:province":"TX",
    "sg:tags":[
        "food",
        "delivery"
    ],
    "sg:website":"www.macklinscateringco.com",
    "wof:name":"Macklins Catering Company",
    "wof:placetype":"venue"
},
  "geometry": {"coordinates":[-96.919707,32.900399],"type":"Point"}
}