{
  "type": "Feature",
  "properties": {
    "iso:country":"US",
    "sg:address":"4740 Katy Fwy",
    "sg:city":"Houston",
    "sg:classifiers":[
        {
            "category":"Autos & Motor Vehicles",
            "subcategory":"Fuel & Gas Station",
            "type":"Retail Goods"
        }
    ],
    "sg:phone":"+1 713 868 4555",
    "sg:postcode":"77007",
    "sg:province":"TX",
    "wof:name":"Shepherd Shell",
    "wof:placetype":"venue"
},
  "geometry": {"coordinates":[-95.408935,29.77815],"type":"Point"}
}