{
  "type": "Feature",
  "properties": {
    "iso:country":"US",
    "sg:address":"4106 Victoria St",
    "sg:city":"Irving",
    "sg:classifiers":[
        {
            "category":"Manufacturing",
            "subcategory":"Tools & Machinery",
            "type":"Manufacturing & Wholesale Goods"
        }
    ],
    "sg:phone":"+1 972 255 1671",
    "sg:postcode":"75062",
    "sg:province":"TX",
    "sg:tags":[
        "devices",
        "mfg"
    ],
    "wof:name":"RP&m Enterprises",
    "wof:placetype":"venue"
},
  "geometry": {"coordinates":[-97.00600300000001,32.844764],"type":"Point"}
}