{
  "type": "Feature",
  "properties": {
    "iso:country":"US",
    "sg:address":"10355 Canton Field",
    "sg:city":"San Antonio",
    "sg:classifiers":[
        {
            "category":"Shopping",
            "subcategory":"Musical Instruments",
            "type":"Retail Goods"
        }
    ],
    "sg:phone":"+1 210 675 3630",
    "sg:postcode":"78245",
    "sg:province":"TX",
    "wof:name":"Power Harness",
    "wof:placetype":"venue"
},
  "geometry": {"coordinates":[-98.69616499999999,29.392753],"type":"Point"}
}