{
  "type": "Feature",
  "properties": {
    "iso:country":"US",
    "sg:address":"7910 Modesto Dr",
    "sg:city":"Arlington",
    "sg:classifiers":[
        {
            "category":"Building & Trades",
            "subcategory":"Construction",
            "type":"Services"
        }
    ],
    "sg:phone":"+1 682 518 1846",
    "sg:postcode":"76001",
    "sg:province":"TX",
    "sg:tags":[
        "steel",
        "erection",
        "structural"
    ],
    "wof:name":"Sky High Structural Steel",
    "wof:placetype":"venue"
},
  "geometry": {"coordinates":[-97.12326400000001,32.617577],"type":"Point"}
}