{
  "type": "Feature",
  "properties": {
    "iso:country":"US",
    "sg:address":"331 NW Hillery St",
    "sg:city":"Burleson",
    "sg:classifiers":[
        {
            "category":"Insurance",
            "subcategory":"Insurance Agent",
            "type":"Services"
        },
        {
            "category":"Insurance",
            "subcategory":"Hazard Insurance",
            "type":"Services"
        },
        {
            "category":"Insurance",
            "subcategory":"Title Insurance",
            "type":"Services"
        },
        {
            "category":"Insurance",
            "subcategory":"Life Insurance",
            "type":"Services"
        }
    ],
    "sg:phone":"+1 817 447 0719",
    "sg:postcode":"76028",
    "sg:province":"TX",
    "sg:tags":[
        "business",
        "auto",
        "commercial",
        "homeowner",
        "motorcycle",
        "renter"
    ],
    "wof:name":"Allstate Insurance Company - Tim Rial",
    "wof:placetype":"venue"
},
  "geometry": {"coordinates":[-97.325898,32.548755],"type":"Point"}
}