{
  "type": "Feature",
  "properties": {
    "iso:country":"US",
    "sg:address":"2104 Singletree Ave",
    "sg:city":"Austin",
    "sg:classifiers":[
        {
            "category":"Shopping",
            "subcategory":"Hobbies, Toys, & Games",
            "type":"Retail Goods"
        }
    ],
    "sg:phone":"+1 512 339 4790",
    "sg:postcode":"78727",
    "sg:province":"TX",
    "wof:name":"Scrapitydodah",
    "wof:placetype":"venue"
},
  "geometry": {"coordinates":[-97.695055,30.421061],"type":"Point"}
}