{
  "type": "Feature",
  "properties": {
    "iso:country":"US",
    "sg:address":"810 W 11th St",
    "sg:city":"Austin",
    "sg:classifiers":[
        {
            "category":"Organizations",
            "subcategory":"Membership Organization",
            "type":"Services"
        }
    ],
    "sg:phone":"+1 512 474 1454",
    "sg:postcode":"78701",
    "sg:province":"TX",
    "wof:name":"Nasw Texas Chapter",
    "wof:placetype":"venue"
},
  "geometry": {"coordinates":[-97.750381,30.275469],"type":"Point"}
}