{
  "type": "Feature",
  "properties": {
    "iso:country":"US",
    "sg:address":"2151 W Oaklawn Rd",
    "sg:city":"Pleasanton",
    "sg:classifiers":[
        {
            "category":"Health Services",
            "subcategory":"Doctor",
            "type":"Services"
        }
    ],
    "sg:phone":"+1 830 569 3334",
    "sg:postcode":"78064",
    "sg:province":"TX",
    "sg:tags":[
        "physician",
        "surgeon"
    ],
    "wof:name":"Mixon, Ron",
    "wof:placetype":"venue"
},
  "geometry": {"coordinates":[-98.51938699999999,28.935865],"type":"Point"}
}