{
  "type": "Feature",
  "properties": {
    "iso:country":"US",
    "sg:address":"1804 Round Rock Dr",
    "sg:city":"Allen",
    "sg:classifiers":[
        {
            "category":"Banks & Credit Unions",
            "subcategory":"Investment Brokerage",
            "type":"Services"
        }
    ],
    "sg:phone":"+1 972 396 9280",
    "sg:postcode":"75002",
    "sg:province":"TX",
    "sg:tags":[
        "security"
    ],
    "wof:name":"Ekd Investments Inc",
    "wof:placetype":"venue"
},
  "geometry": {"coordinates":[-96.620622,33.094958],"type":"Point"}
}