{
  "type": "Feature",
  "properties": {
    "iso:country":"US",
    "sg:address":"3566 Wilhurt Ave",
    "sg:city":"Dallas",
    "sg:classifiers":[
        {
            "category":"Shopping",
            "subcategory":"Clothing, Apparel, & Fashions",
            "type":"Retail Goods"
        }
    ],
    "sg:phone":"+1 214 371 1560",
    "sg:postcode":"75216",
    "sg:province":"TX",
    "sg:tags":[
        "wig",
        "toupee",
        "hairpiece"
    ],
    "wof:name":"Wigs & Things",
    "wof:placetype":"venue"
},
  "geometry": {"coordinates":[-96.765118,32.71287],"type":"Point"}
}