{
  "type": "Feature",
  "properties": {
    "iso:country":"US",
    "sg:address":"13776 N US Hwy 183",
    "sg:city":"Austin",
    "sg:classifiers":[
        {
            "category":"Sports & Exercise",
            "subcategory":"Gym",
            "type":"Entertainment"
        }
    ],
    "sg:phone":"+1 512 249 6724",
    "sg:postcode":"78750",
    "sg:province":"TX",
    "sg:tags":[
        "club",
        "health",
        "studio",
        "gymnasium"
    ],
    "wof:name":"24 Hour Fitness",
    "wof:placetype":"venue"
},
  "geometry": {"coordinates":[-97.795748,30.464756],"type":"Point"}
}