{
  "type": "Feature",
  "properties": {
    "iso:country":"US",
    "sg:address":"1031 S Walnut Ave",
    "sg:city":"New Braunfels",
    "sg:classifiers":[
        {
            "category":"Restaurant",
            "type":"Food & Drink"
        }
    ],
    "sg:menulink":"http://www.allmenus.com/tx/new-braunfels/179363-chick-fil-a/menu/",
    "sg:phone":"+1 830 620 1200",
    "sg:postcode":"78130",
    "sg:province":"TX",
    "sg:tags":[
        "wrap",
        "soup",
        "american",
        "sandwich",
        "salad"
    ],
    "wof:name":"Chick-fil-A",
    "wof:placetype":"venue"
},
  "geometry": {"coordinates":[-98.12557200000001,29.684694],"type":"Point"}
}