{
  "type": "Feature",
  "properties": {
    "iso:country":"US",
    "sg:address":"2215 Aspen St",
    "sg:city":"Richardson",
    "sg:classifiers":[
        {
            "category":"Manufacturing",
            "subcategory":"Printing",
            "type":"Manufacturing & Wholesale Goods"
        }
    ],
    "sg:phone":"+1 972 699 9044",
    "sg:postcode":"75082",
    "sg:province":"TX",
    "sg:tags":[
        "book"
    ],
    "wof:name":"Mc Graw-Hill Companies Inc",
    "wof:placetype":"venue"
},
  "geometry": {"coordinates":[-96.680042,32.989225],"type":"Point"}
}