{
  "type": "Feature",
  "properties": {
    "iso:country":"US",
    "sg:address":"4203 Ave H",
    "sg:city":"Rosenberg",
    "sg:classifiers":[
        {
            "category":"Personal",
            "subcategory":"Beauty Salon",
            "type":"Services"
        }
    ],
    "sg:phone":"+1 281 232 3409",
    "sg:postcode":"77471",
    "sg:province":"TX",
    "wof:name":"Mane Tamers",
    "wof:placetype":"venue"
},
  "geometry": {"coordinates":[-95.784149,29.563779],"type":"Point"}
}