{
  "type": "Feature",
  "properties": {
    "iso:country":"US",
    "sg:address":"6245 Skylark Ln",
    "sg:city":"Fort Worth",
    "sg:classifiers":[
        {
            "category":"Autos & Motor Vehicles",
            "subcategory":"Motorcycle Sales",
            "type":"Retail Goods"
        }
    ],
    "sg:phone":"+1 817 485 2530",
    "sg:postcode":"76148",
    "sg:province":"TX",
    "wof:name":"Thunder Road Trikes",
    "wof:placetype":"venue"
},
  "geometry": {"coordinates":[-97.242816,32.860272],"type":"Point"}
}