{
  "type": "Feature",
  "properties": {
    "iso:country":"US",
    "sg:address":"6720 del Prado Ave",
    "sg:city":"Fort Worth",
    "sg:classifiers":[
        {
            "category":"Health Services",
            "subcategory":"Doctor",
            "type":"Services"
        }
    ],
    "sg:phone":"+1 817 292 5778",
    "sg:postcode":"76133",
    "sg:province":"TX",
    "sg:tags":[
        "radiological"
    ],
    "wof:name":"Arthur Pawgan MD",
    "wof:placetype":"venue"
},
  "geometry": {"coordinates":[-97.387885,32.647173],"type":"Point"}
}