{
  "type": "Feature",
  "properties": {
    "iso:country":"US",
    "sg:address":"7110 Ash St",
    "sg:city":"Frisco",
    "sg:classifiers":[
        {
            "category":"Organizations",
            "subcategory":"Non-profit Organization",
            "type":"Services"
        }
    ],
    "sg:phone":"+1 972 334 0709",
    "sg:postcode":"75034",
    "sg:province":"TX",
    "sg:tags":[
        "community"
    ],
    "wof:name":"CSJ Group",
    "wof:placetype":"venue"
},
  "geometry": {"coordinates":[-96.823452,33.147428],"type":"Point"}
}