{
  "type": "Feature",
  "properties": {
    "iso:country":"US",
    "sg:address":"2714 E Grant St",
    "sg:city":"Roma",
    "sg:classifiers":[
        {
            "category":"Autos & Motor Vehicles",
            "subcategory":"Auto Supplies",
            "type":"Retail Goods"
        },
        {
            "category":"Wholesale",
            "subcategory":"Electrical",
            "type":"Manufacturing & Wholesale Goods"
        },
        {
            "category":"Wholesale",
            "subcategory":"Auto Parts",
            "type":"Manufacturing & Wholesale Goods"
        }
    ],
    "sg:phone":"+1 956 849 1031",
    "sg:postcode":"78584",
    "sg:province":"TX",
    "sg:tags":[
        "body",
        "battery",
        "automobile",
        "accessory",
        "equipment",
        "truck"
    ],
    "sg:website":"http://www.oreillyauto.com?utm_source=yellowpages&utm_medium=iyp&utm_campaign=2130",
    "wof:name":"O'Reilly Auto Parts",
    "wof:placetype":"venue"
},
  "geometry": {"coordinates":[-98.97543899999999,26.408311],"type":"Point"}
}