{
  "type": "Feature",
  "properties": {
    "iso:country":"US",
    "sg:address":"225 Southwood Oaks",
    "sg:city":"Floresville",
    "sg:classifiers":[
        {
            "category":"Building & Trades",
            "subcategory":"Construction",
            "type":"Services"
        }
    ],
    "sg:phone":"+1 210 275 0377",
    "sg:postcode":"78114",
    "sg:province":"TX",
    "sg:tags":[
        "residential"
    ],
    "wof:name":"Epi & Sons Construction",
    "wof:placetype":"venue"
},
  "geometry": {"coordinates":[-98.22238,29.229535],"type":"Point"}
}