{
  "type": "Feature",
  "properties": {
    "iso:country":"US",
    "sg:address":"1332 US Hwy 80",
    "sg:city":"Longview",
    "sg:classifiers":[
        {
            "category":"Professional",
            "type":"Services"
        }
    ],
    "sg:phone":"+1 903 845 4560",
    "sg:postcode":"75604",
    "sg:province":"TX",
    "wof:name":"Catfish Hut",
    "wof:placetype":"venue"
},
  "geometry": {"coordinates":[-94.7668,32.504215],"type":"Point"}
}