{
  "type": "Feature",
  "properties": {
    "iso:country":"US",
    "sg:address":"703 S Jackson Rd",
    "sg:city":"Pharr",
    "sg:classifiers":[
        {
            "category":"Restaurant",
            "type":"Food & Drink"
        }
    ],
    "sg:menulink":"http://www.allmenus.com/tx/mcallen-pharr/177686-jack-in-the-box/menu/",
    "sg:phone":"+1 956 782 4500",
    "sg:postcode":"78577",
    "sg:province":"TX",
    "sg:tags":[
        "burger",
        "american"
    ],
    "wof:name":"Jack in the Box",
    "wof:placetype":"venue"
},
  "geometry": {"coordinates":[-98.205269,26.191553],"type":"Point"}
}