{
  "type": "Feature",
  "properties": {
    "iso:country":"US",
    "sg:address":"19531 Hardwood Ridge Trl",
    "sg:city":"Cypress",
    "sg:classifiers":[
        {
            "category":"Manufacturing",
            "subcategory":"Pet Food",
            "type":"Manufacturing & Wholesale Goods"
        }
    ],
    "sg:phone":"+1 832 746 6525",
    "sg:postcode":"77429",
    "sg:province":"TX",
    "sg:tags":[
        "hay"
    ],
    "wof:name":"Melissa Yuki Hay",
    "wof:placetype":"venue"
},
  "geometry": {"coordinates":[-95.722307,29.988608],"type":"Point"}
}