{
  "type": "Feature",
  "properties": {
    "iso:country":"US",
    "sg:address":"2626 Bell Rd N",
    "sg:city":"Iowa Park",
    "sg:classifiers":[
        {
            "category":"Farming",
            "subcategory":"Livestock Farm",
            "type":"Manufacturing & Wholesale Goods"
        }
    ],
    "sg:phone":"+1 940 592 5950",
    "sg:postcode":"76367",
    "sg:province":"TX",
    "sg:tags":[
        "beef",
        "feedlot",
        "cattle"
    ],
    "wof:name":"Vier K Milch Farms Inc",
    "wof:placetype":"venue"
},
  "geometry": {"coordinates":[-98.655776,33.989588],"type":"Point"}
}