{
  "type": "Feature",
  "properties": {
    "iso:country":"US",
    "sg:address":"735 E Highland Rd",
    "sg:city":"Red Oak",
    "sg:classifiers":[
        {
            "category":"Retail",
            "subcategory":"Repair Shop",
            "type":"Services"
        }
    ],
    "sg:phone":"+1 972 617 6139",
    "sg:postcode":"75154",
    "sg:province":"TX",
    "sg:tags":[
        "welding"
    ],
    "wof:name":"Scotts Welding",
    "wof:placetype":"venue"
},
  "geometry": {"coordinates":[-96.882531,32.509031],"type":"Point"}
}