{
  "type": "Feature",
  "properties": {
    "iso:country":"US",
    "sg:address":"11438 Chelsea Walk Dr",
    "sg:city":"Houston",
    "sg:classifiers":[
        {
            "category":"Retail",
            "subcategory":"Repair Shop",
            "type":"Services"
        }
    ],
    "sg:phone":"+1 281 580 5759",
    "sg:postcode":"77066",
    "sg:province":"TX",
    "wof:name":"Johnsons On Site Repair",
    "wof:placetype":"venue"
},
  "geometry": {"coordinates":[-95.47737499999999,29.947595],"type":"Point"}
}