{
  "type": "Feature",
  "properties": {
    "iso:country":"US",
    "sg:address":"2231 Neyland Rd",
    "sg:city":"Silsbee",
    "sg:classifiers":[
        {
            "category":"Retail",
            "subcategory":"Auto Repair",
            "type":"Services"
        }
    ],
    "sg:phone":"+1 409 385 6853",
    "sg:postcode":"77656",
    "sg:province":"TX",
    "sg:tags":[
        "automotive"
    ],
    "wof:name":"Alignment Consulting Internati",
    "wof:placetype":"venue"
},
  "geometry": {"coordinates":[-94.20048300000001,30.37762],"type":"Point"}
}