{
  "type": "Feature",
  "properties": {
    "iso:country":"US",
    "sg:address":"1026 Wall Rd",
    "sg:city":"Keller",
    "sg:classifiers":[
        {
            "category":"Building & Trades",
            "subcategory":"Pest Control",
            "type":"Services"
        }
    ],
    "sg:phone":"+1 817 337 4555",
    "sg:postcode":"76248",
    "sg:province":"TX",
    "wof:name":"Chem Care Pest Services",
    "wof:placetype":"venue"
},
  "geometry": {"coordinates":[-97.292913,32.93285],"type":"Point"}
}