{
  "type": "Feature",
  "properties": {
    "iso:country":"US",
    "sg:address":"5300 Coke St",
    "sg:city":"Houston",
    "sg:classifiers":[
        {
            "category":"Real Estate",
            "subcategory":"Real Estate Operator",
            "type":"Services"
        }
    ],
    "sg:phone":"+1 713 672 6614",
    "sg:postcode":"77020",
    "sg:province":"TX",
    "sg:tags":[
        "apartment"
    ],
    "wof:name":"Cleme Manor Apartments",
    "wof:placetype":"venue"
},
  "geometry": {"coordinates":[-95.32037,29.767853],"type":"Point"}
}