{
  "type": "Feature",
  "properties": {
    "iso:country":"US",
    "sg:address":"7908 Londonderry Dr",
    "sg:city":"Fort Worth",
    "sg:classifiers":[
        {
            "category":"Retail",
            "subcategory":"Repair Shop",
            "type":"Services"
        }
    ],
    "sg:phone":"+1 817 485 3895",
    "sg:postcode":"76180",
    "sg:province":"TX",
    "sg:tags":[
        "equipment"
    ],
    "wof:name":"Northeast Business Machines",
    "wof:placetype":"venue"
},
  "geometry": {"coordinates":[-97.222217,32.891837],"type":"Point"}
}