{
  "type": "Feature",
  "properties": {
    "iso:country":"US",
    "sg:address":"111 Walnut St",
    "sg:city":"Mansfield",
    "sg:classifiers":[
        {
            "category":"Building & Trades",
            "subcategory":"Construction",
            "type":"Services"
        }
    ],
    "sg:phone":"+1 817 473 1055",
    "sg:postcode":"76063",
    "sg:province":"TX",
    "sg:tags":[
        "irrigation",
        "lawn",
        "seeding",
        "care"
    ],
    "wof:name":"Turf Masters Irrigation",
    "wof:placetype":"venue"
},
  "geometry": {"coordinates":[-97.14264300000001,32.563708],"type":"Point"}
}