{
  "type": "Feature",
  "properties": {
    "iso:country":"US",
    "sg:address":"2611 Rio Brazos",
    "sg:city":"San Antonio",
    "sg:classifiers":[
        {
            "category":"Organizations",
            "subcategory":"Non-profit Organization",
            "type":"Services"
        }
    ],
    "sg:phone":"+1 210 481 7476",
    "sg:postcode":"78259",
    "sg:province":"TX",
    "sg:tags":[
        "social"
    ],
    "wof:name":"McDermott Land Development LLC",
    "wof:placetype":"venue"
},
  "geometry": {"coordinates":[-98.43907299999999,29.640111],"type":"Point"}
}