{
  "type": "Feature",
  "properties": {
    "iso:country":"US",
    "sg:address":"1821 Roswell Rd",
    "sg:city":"El Paso",
    "sg:classifiers":[
        {
            "category":"Shopping",
            "subcategory":"Computers & Home Electronics",
            "type":"Retail Goods"
        }
    ],
    "sg:phone":"+1 915 680 3218",
    "sg:postcode":"79915",
    "sg:province":"TX",
    "sg:tags":[
        "parts",
        "supply"
    ],
    "wof:name":"Unitech Systems",
    "wof:placetype":"venue"
},
  "geometry": {"coordinates":[-106.371863,31.765516],"type":"Point"}
}