{
  "type": "Feature",
  "properties": {
    "iso:country":"US",
    "sg:address":"307 W Tyler St",
    "sg:city":"Mexia",
    "sg:classifiers":[
        {
            "category":"Retail",
            "subcategory":"Auto Repair",
            "type":"Services"
        }
    ],
    "sg:phone":"+1 254 562 6211",
    "sg:postcode":"76667",
    "sg:province":"TX",
    "sg:tags":[
        "repairing",
        "automobile"
    ],
    "wof:name":"Tyler Street Garage",
    "wof:placetype":"venue"
},
  "geometry": {"coordinates":[-96.487784,31.672551],"type":"Point"}
}