{
  "type": "Feature",
  "properties": {
    "iso:country":"US",
    "sg:address":"6911 Loma Linda St",
    "sg:city":"Palmview",
    "sg:classifiers":[
        {
            "category":"Restaurant",
            "type":"Food & Drink"
        }
    ],
    "sg:phone":"+1 956 240 0525",
    "sg:postcode":"78572",
    "sg:province":"TX",
    "sg:tags":[
        "mexican"
    ],
    "wof:name":"Dora Garcia",
    "wof:placetype":"venue"
},
  "geometry": {"coordinates":[-98.39753,26.245451],"type":"Point"}
}