{
  "type": "Feature",
  "properties": {
    "iso:country":"US",
    "sg:address":"10055 US Hwy 90",
    "sg:city":"Kingsbury",
    "sg:classifiers":[
        {
            "category":"Government",
            "subcategory":"Post Office",
            "type":"Public Place"
        }
    ],
    "sg:phone":"+1 830 639 4601",
    "sg:postcode":"78638",
    "sg:province":"TX",
    "sg:tags":[
        "postal",
        "us"
    ],
    "wof:name":"US Post Office",
    "wof:placetype":"venue"
},
  "geometry": {"coordinates":[-97.82263500000001,29.648981],"type":"Point"}
}