{
  "type": "Feature",
  "properties": {
    "iso:country":"US",
    "sg:address":"630 Gary Ln",
    "sg:city":"El Paso",
    "sg:classifiers":[
        {
            "category":"Building & Trades",
            "subcategory":"Landscaping Services",
            "type":"Services"
        }
    ],
    "sg:phone":"+1 915 581 2676",
    "sg:postcode":"79922",
    "sg:province":"TX",
    "sg:tags":[
        "designer",
        "landscape"
    ],
    "wof:name":"Landscape Architectural Svc",
    "wof:placetype":"venue"
},
  "geometry": {"coordinates":[-106.580248,31.816373],"type":"Point"}
}