{
  "type": "Feature",
  "properties": {
    "iso:country":"US",
    "sg:address":"6718 Cloud Swept Ln",
    "sg:city":"Houston",
    "sg:classifiers":[
        {
            "category":"Arts & Performance",
            "subcategory":"Dance",
            "type":"Entertainment"
        }
    ],
    "sg:phone":"+1 281 999 1050",
    "sg:postcode":"77086",
    "sg:province":"TX",
    "sg:tags":[
        "instruction",
        "dancing"
    ],
    "wof:name":"12 Stepp Dance Co",
    "wof:placetype":"venue"
},
  "geometry": {"coordinates":[-95.48472,29.926502],"type":"Point"}
}