{
  "type": "Feature",
  "properties": {
    "iso:country":"US",
    "sg:address":"440 N Ballard Ave",
    "sg:city":"Wylie",
    "sg:classifiers":[
        {
            "category":"Freight",
            "type":"Transportation"
        }
    ],
    "sg:phone":"+1 972 442 3900",
    "sg:postcode":"75098",
    "sg:province":"TX",
    "sg:tags":[
        "storage"
    ],
    "wof:name":"A A Assured Storage LTD",
    "wof:placetype":"venue"
},
  "geometry": {"coordinates":[-96.538674,33.019462],"type":"Point"}
}