{
  "type": "Feature",
  "properties": {
    "iso:country":"US",
    "sg:address":"3909 Saint Michaels Ct",
    "sg:city":"Sugar Land",
    "sg:classifiers":[
        {
            "category":"Professional",
            "subcategory":"Computer Services",
            "type":"Services"
        }
    ],
    "sg:phone":"+1 281 265 4556",
    "sg:postcode":"77479",
    "sg:province":"TX",
    "sg:tags":[
        "design",
        "system"
    ],
    "wof:name":"The Write Idea",
    "wof:placetype":"venue"
},
  "geometry": {"coordinates":[-95.598645,29.561603],"type":"Point"}
}