{
  "type": "Feature",
  "properties": {
    "iso:country":"US",
    "sg:address":"4843 Waynesboro Dr",
    "sg:city":"Houston",
    "sg:classifiers":[
        {
            "category":"Wholesale",
            "subcategory":"Auto Parts",
            "type":"Manufacturing & Wholesale Goods"
        }
    ],
    "sg:phone":"+1 713 729 8235",
    "sg:postcode":"77035",
    "sg:province":"TX",
    "sg:tags":[
        "mfr",
        "representative",
        "tire"
    ],
    "wof:name":"Frank J Danek",
    "wof:placetype":"venue"
},
  "geometry": {"coordinates":[-95.45861499999999,29.66974],"type":"Point"}
}