{
  "type": "Feature",
  "properties": {
    "iso:country":"US",
    "sg:address":"630 W Main St",
    "sg:city":"Grand Prairie",
    "sg:classifiers":[
        {
            "category":"Freight",
            "type":"Transportation"
        }
    ],
    "sg:phone":"+1 972 262 2813",
    "sg:postcode":"75050",
    "sg:province":"TX",
    "wof:name":"Grand Prairie Medical Trnsprtn",
    "wof:placetype":"venue"
},
  "geometry": {"coordinates":[-97.011735,32.744116],"type":"Point"}
}