{
  "type": "Feature",
  "properties": {
    "iso:country":"US",
    "sg:address":"3404 Springbranch Dr",
    "sg:city":"Richardson",
    "sg:classifiers":[
        {
            "category":"Professional",
            "subcategory":"Engineering",
            "type":"Services"
        }
    ],
    "sg:phone":"+1 972 231 1514",
    "sg:postcode":"75082",
    "sg:province":"TX",
    "sg:tags":[
        "engineer"
    ],
    "wof:name":"PDE Inc",
    "wof:placetype":"venue"
},
  "geometry": {"coordinates":[-96.66001799999999,33.002438],"type":"Point"}
}