{
  "type": "Feature",
  "properties": {
    "iso:country":"US",
    "sg:address":"1500 Oakcliff Rd",
    "sg:city":"Fort Worth",
    "sg:classifiers":[
        {
            "category":"Personal",
            "subcategory":"Beauty Salon",
            "type":"Services"
        }
    ],
    "sg:phone":"+1 817 536 1709",
    "sg:postcode":"76103",
    "sg:province":"TX",
    "wof:name":"Meadowbrook Hair Place",
    "wof:placetype":"venue"
},
  "geometry": {"coordinates":[-97.26446199999999,32.755936],"type":"Point"}
}