{
  "type": "Feature",
  "properties": {
    "iso:country":"US",
    "sg:address":"1100 San Jacinto Ln",
    "sg:city":"Bryan",
    "sg:classifiers":[
        {
            "category":"Food & Beverages",
            "subcategory":"Specialty",
            "type":"Retail Goods"
        },
        {
            "category":"Food & Beverages",
            "subcategory":"Groceries & Convenience Stores",
            "type":"Retail Goods"
        }
    ],
    "sg:phone":"+1 979 822 6141",
    "sg:postcode":"77803",
    "sg:province":"TX",
    "sg:tags":[
        "grocers-specialty"
    ],
    "wof:name":"Ponzio Food Market",
    "wof:placetype":"venue"
},
  "geometry": {"coordinates":[-96.37938699999999,30.684919],"type":"Point"}
}