{
  "type": "Feature",
  "properties": {
    "iso:country":"US",
    "sg:address":"308 Windsor Sq",
    "sg:city":"Alvin",
    "sg:classifiers":[
        {
            "category":"Arena",
            "subcategory":"Sports Club",
            "type":"Entertainment"
        }
    ],
    "sg:phone":"+1 281 585 8008",
    "sg:postcode":"77511",
    "sg:province":"TX",
    "sg:tags":[
        "soccer"
    ],
    "wof:name":"Alvin Youth Soccer Club",
    "wof:placetype":"venue"
},
  "geometry": {"coordinates":[-95.237605,29.395243],"type":"Point"}
}