{
  "type": "Feature",
  "properties": {
    "iso:country":"US",
    "sg:address":"418 Shadywood Rd",
    "sg:city":"Houston",
    "sg:classifiers":[
        {
            "category":"Professional",
            "type":"Services"
        }
    ],
    "sg:phone":"+1 713 783 0307",
    "sg:postcode":"77057",
    "sg:province":"TX",
    "wof:name":"Kaleidoscope Unlimited",
    "wof:placetype":"venue"
},
  "geometry": {"coordinates":[-95.486285,29.764326],"type":"Point"}
}