{
  "type": "Feature",
  "properties": {
    "iso:country":"US",
    "sg:address":"24800 Ford Rd",
    "sg:city":"Porter",
    "sg:classifiers":[
        {
            "category":"Manufacturing",
            "subcategory":"Metals",
            "type":"Manufacturing & Wholesale Goods"
        }
    ],
    "sg:phone":"+1 281 354 3011",
    "sg:postcode":"77365",
    "sg:province":"TX",
    "sg:tags":[
        "fabrication",
        "structural"
    ],
    "wof:name":"Ford Steel LTD",
    "wof:placetype":"venue"
},
  "geometry": {"coordinates":[-95.195761,30.087405],"type":"Point"}
}