{
  "type": "Feature",
  "properties": {
    "iso:country":"US",
    "sg:address":"14934 Cindywood Dr",
    "sg:city":"Houston",
    "sg:classifiers":[
        {
            "category":"Social Services",
            "subcategory":"Child Care",
            "type":"Services"
        }
    ],
    "sg:phone":"+1 281 558 5515",
    "sg:postcode":"77079",
    "sg:province":"TX",
    "sg:tags":[
        "adoption"
    ],
    "sg:website":"http://www.adoptionlady.com",
    "wof:name":"Otte Katherine T/Adoption Consultant",
    "wof:placetype":"venue"
},
  "geometry": {"coordinates":[-95.616958,29.767362],"type":"Point"}
}