{
  "type": "Feature",
  "properties": {
    "iso:country":"US",
    "sg:address":"5912 Hillview Dr",
    "sg:city":"Fort Worth",
    "sg:classifiers":[
        {
            "category":"Building & Trades",
            "subcategory":"Landscaping Services",
            "type":"Services"
        }
    ],
    "sg:phone":"+1 817 427 3018",
    "sg:postcode":"76148",
    "sg:province":"TX",
    "sg:tags":[
        "landscape"
    ],
    "wof:name":"Canyon Crek Landscape",
    "wof:placetype":"venue"
},
  "geometry": {"coordinates":[-97.254468,32.891727],"type":"Point"}
}