{
  "type": "Feature",
  "properties": {
    "iso:country":"US",
    "sg:address":"14770 State Highway 249",
    "sg:city":"Houston",
    "sg:classifiers":[
        {
            "category":"Personal",
            "subcategory":"Day Spa",
            "type":"Services"
        }
    ],
    "sg:phone":"+1 281 880 0909",
    "sg:postcode":"77086",
    "sg:province":"TX",
    "wof:name":"Ocean Blue Spa",
    "wof:placetype":"venue"
},
  "geometry": {"coordinates":[-95.505292,29.928691],"type":"Point"}
}