{
  "type": "Feature",
  "properties": {
    "iso:country":"US",
    "sg:address":"15114 Coral Oak Ct",
    "sg:city":"Houston",
    "sg:classifiers":[
        {
            "category":"Wholesale",
            "subcategory":"Durable Goods & Equipment",
            "type":"Manufacturing & Wholesale Goods"
        }
    ],
    "sg:phone":"+1 281 486 1905",
    "sg:postcode":"77059",
    "sg:province":"TX",
    "wof:name":"Mejia Industrial Supply Compan",
    "wof:placetype":"venue"
},
  "geometry": {"coordinates":[-95.12012,29.585675],"type":"Point"}
}