{
  "type": "Feature",
  "properties": {
    "iso:country":"US",
    "sg:address":"7427 Tower St",
    "sg:city":"Richland Hills",
    "sg:classifiers":[
        {
            "category":"Professional",
            "subcategory":"Advertising",
            "type":"Services"
        }
    ],
    "sg:phone":"+1 817 589 1556",
    "sg:postcode":"76118",
    "sg:province":"TX",
    "sg:tags":[
        "distribution"
    ],
    "wof:name":"Market Distribution Spec",
    "wof:placetype":"venue"
},
  "geometry": {"coordinates":[-97.21921500000001,32.805341],"type":"Point"}
}