{
  "type": "Feature",
  "properties": {
    "iso:country":"US",
    "sg:address":"404 Copano Bay Dr",
    "sg:city":"Bayside",
    "sg:classifiers":[
        {
            "category":"Farming",
            "subcategory":"Fish & Marine Products",
            "type":"Manufacturing & Wholesale Goods"
        }
    ],
    "sg:phone":"+1 361 529 6600",
    "sg:postcode":"78340",
    "sg:province":"TX",
    "sg:tags":[
        "preserves",
        "fishing",
        "hunting"
    ],
    "wof:name":"Fennessey Ranch",
    "wof:placetype":"venue"
},
  "geometry": {"coordinates":[-97.21587599999999,28.088597],"type":"Point"}
}