{
  "type": "Feature",
  "properties": {
    "iso:country":"US",
    "sg:address":"1602 E Martha Ln",
    "sg:city":"Pasadena",
    "sg:classifiers":[
        {
            "category":"Professional",
            "subcategory":"Business Services",
            "type":"Services"
        }
    ],
    "sg:phone":"+1 713 473 1116",
    "sg:postcode":"77502",
    "sg:province":"TX",
    "wof:name":"MJL Enterprises LLC",
    "wof:placetype":"venue"
},
  "geometry": {"coordinates":[-95.185942,29.688803],"type":"Point"}
}