{
  "type": "Feature",
  "properties": {
    "iso:country":"US",
    "sg:address":"9003 San Leandro Dr",
    "sg:city":"Dallas",
    "sg:classifiers":[
        {
            "category":"Arts & Performance",
            "subcategory":"Theater",
            "type":"Entertainment"
        }
    ],
    "sg:phone":"+1 214 321 7384",
    "sg:postcode":"75218",
    "sg:province":"TX",
    "sg:tags":[
        "theatrical"
    ],
    "wof:name":"Mustang Management",
    "wof:placetype":"venue"
},
  "geometry": {"coordinates":[-96.70126500000001,32.821701],"type":"Point"}
}