{
  "type": "Feature",
  "properties": {
    "iso:country":"US",
    "sg:address":"4210 Venado Dr",
    "sg:city":"Austin",
    "sg:classifiers":[
        {
            "category":"Professional",
            "subcategory":"Computer Services",
            "type":"Services"
        }
    ],
    "sg:phone":"+1 512 345 1011",
    "sg:postcode":"78731",
    "sg:province":"TX",
    "sg:tags":[
        "programing",
        "custom"
    ],
    "wof:name":"Landers Computer Systems",
    "wof:placetype":"venue"
},
  "geometry": {"coordinates":[-97.77035600000001,30.362096],"type":"Point"}
}