{
  "type": "Feature",
  "properties": {
    "iso:country":"US",
    "sg:address":"5803 Cary Dr",
    "sg:city":"Austin",
    "sg:classifiers":[
        {
            "category":"Real Estate",
            "subcategory":"Real Estate Agent",
            "type":"Services"
        }
    ],
    "sg:phone":"+1 512 323 5626",
    "sg:postcode":"78757",
    "sg:province":"TX",
    "wof:name":"Westview Properties",
    "wof:placetype":"venue"
},
  "geometry": {"coordinates":[-97.74608499999999,30.338841],"type":"Point"}
}