{
  "type": "Feature",
  "properties": {
    "iso:country":"US",
    "sg:address":"5075 Fairmont Pkwy",
    "sg:city":"Pasadena",
    "sg:classifiers":[
        {
            "category":"Restaurant",
            "type":"Food & Drink"
        }
    ],
    "sg:menulink":"http://www.allmenus.com/tx/pasadena/64523-chuck-e-cheeses/menu/",
    "sg:phone":"+1 281 487 2765",
    "sg:postcode":"77505",
    "sg:province":"TX",
    "sg:tags":[
        "american",
        "pizza"
    ],
    "wof:name":"Chuck E. Cheese's",
    "wof:placetype":"venue"
},
  "geometry": {"coordinates":[-95.166591,29.649866],"type":"Point"}
}