{
  "type": "Feature",
  "properties": {
    "iso:country":"US",
    "sg:address":"750 Landa St",
    "sg:city":"New Braunfels",
    "sg:classifiers":[
        {
            "category":"Health Services",
            "subcategory":"Health Practitioner",
            "type":"Services"
        }
    ],
    "sg:phone":"+1 830 606 3658",
    "sg:postcode":"78130",
    "sg:province":"TX",
    "wof:name":"McKenna Health System",
    "wof:placetype":"venue"
},
  "geometry": {"coordinates":[-98.132784,29.705248],"type":"Point"}
}