{
  "type": "Feature",
  "properties": {
    "iso:country":"US",
    "sg:address":"511 Oakwood Dr",
    "sg:city":"Allen",
    "sg:classifiers":[
        {
            "category":"Manufacturing",
            "subcategory":"Printing",
            "type":"Manufacturing & Wholesale Goods"
        }
    ],
    "sg:phone":"+1 972 359 9311",
    "sg:postcode":"75013",
    "sg:province":"TX",
    "sg:tags":[
        "binding"
    ],
    "wof:name":"Clarke American Checks Inc",
    "wof:placetype":"venue"
},
  "geometry": {"coordinates":[-96.708589,33.092992],"type":"Point"}
}