{
  "type": "Feature",
  "properties": {
    "iso:country":"US",
    "sg:address":"1720 Magnolia St",
    "sg:city":"Beaumont",
    "sg:classifiers":[
        {
            "category":"Wholesale",
            "subcategory":"Vending Machines",
            "type":"Manufacturing & Wholesale Goods"
        }
    ],
    "sg:phone":"+1 409 833 4845",
    "sg:postcode":"77703",
    "sg:province":"TX",
    "sg:tags":[
        "operator"
    ],
    "wof:name":"Lone Star Vending",
    "wof:placetype":"venue"
},
  "geometry": {"coordinates":[-94.104054,30.097419],"type":"Point"}
}