{
  "type": "Feature",
  "properties": {
    "iso:country":"US",
    "sg:address":"203 E Pearl St",
    "sg:city":"Brady",
    "sg:classifiers":[
        {
            "category":"Organizations",
            "subcategory":"Religious Organization",
            "type":"Services"
        }
    ],
    "sg:phone":"+1 325 597 3688",
    "sg:postcode":"76825",
    "sg:province":"TX",
    "sg:tags":[
        "church"
    ],
    "wof:name":"Christian Community Church",
    "wof:placetype":"venue"
},
  "geometry": {"coordinates":[-99.33378399999999,31.143283],"type":"Point"}
}