{
  "type": "Feature",
  "properties": {
    "iso:country":"US",
    "sg:address":"4224 Allencrest Ln",
    "sg:city":"Dallas",
    "sg:classifiers":[
        {
            "category":"Professional",
            "type":"Services"
        }
    ],
    "sg:phone":"+1 972 386 6891",
    "sg:postcode":"75244",
    "sg:province":"TX",
    "wof:name":"Alibates Co",
    "wof:placetype":"venue"
},
  "geometry": {"coordinates":[-96.834309,32.910929],"type":"Point"}
}