{
  "type": "Feature",
  "properties": {
    "iso:country":"US",
    "sg:address":"8281 Mosswood Dr",
    "sg:city":"Woodway",
    "sg:classifiers":[
        {
            "category":"Personal",
            "type":"Services"
        },
        {
            "category":"Professional",
            "subcategory":"Management & Consulting",
            "type":"Services"
        }
    ],
    "sg:phone":"+1 254 399 9971",
    "sg:postcode":"76712",
    "sg:province":"TX",
    "sg:tags":[
        "party",
        "planning"
    ],
    "wof:name":"Party Planners",
    "wof:placetype":"venue"
},
  "geometry": {"coordinates":[-97.221678,31.514863],"type":"Point"}
}