{
  "type": "Feature",
  "properties": {
    "iso:country":"US",
    "sg:address":"15935 Green Meadow Loop",
    "sg:city":"Willis",
    "sg:classifiers":[
        {
            "category":"Professional",
            "subcategory":"Business Services",
            "type":"Services"
        }
    ],
    "sg:phone":"+1 936 890 4980",
    "sg:postcode":"77318",
    "sg:province":"TX",
    "wof:name":"Pro Fab Design",
    "wof:placetype":"venue"
},
  "geometry": {"coordinates":[-95.541965,30.478954],"type":"Point"}
}