{
  "type": "Feature",
  "properties": {
    "iso:country":"US",
    "sg:address":"516 E Houston Ave",
    "sg:city":"Crockett",
    "sg:classifiers":[
        {
            "category":"Professional",
            "subcategory":"Accounting & Tax Preparation",
            "type":"Services"
        }
    ],
    "sg:phone":"+1 936 544 2299",
    "sg:postcode":"75835",
    "sg:province":"TX",
    "wof:name":"Nesmith & Co LLP",
    "wof:placetype":"venue"
},
  "geometry": {"coordinates":[-95.456293,31.318482],"type":"Point"}
}