{
  "type": "Feature",
  "properties": {
    "iso:country":"US",
    "sg:address":"725 Blume Rd #72",
    "sg:city":"Rosenberg",
    "sg:classifiers":[
        {
            "category":"Building & Trades",
            "subcategory":"Construction",
            "type":"Services"
        }
    ],
    "sg:phone":"+1 281 763 9722",
    "sg:postcode":"77471",
    "sg:province":"TX",
    "sg:tags":[
        "contractor"
    ],
    "wof:name":"A&R Contractors",
    "wof:placetype":"venue"
},
  "geometry": {"coordinates":[-95.874771,29.52499],"type":"Point"}
}