{
  "type": "Feature",
  "properties": {
    "iso:country":"US",
    "sg:address":"2306 Lake Austin Blvd",
    "sg:city":"Austin",
    "sg:classifiers":[
        {
            "category":"Health Services",
            "subcategory":"Clinic",
            "type":"Services"
        }
    ],
    "sg:phone":"+1 512 289 9409",
    "sg:postcode":"78703",
    "sg:province":"TX",
    "sg:tags":[
        "counseling",
        "mental"
    ],
    "sg:website":"www.alphacounselingcenterofausti...",
    "wof:name":"Alpha Counseling Center of Austin",
    "wof:placetype":"venue"
},
  "geometry": {"coordinates":[-97.771918,30.278029],"type":"Point"}
}