{
  "type": "Feature",
  "properties": {
    "iso:country":"US",
    "sg:address":"900 Sweetwater Rd",
    "sg:city":"Vidor",
    "sg:classifiers":[
        {
            "category":"Manufacturing",
            "subcategory":"Lumber",
            "type":"Manufacturing & Wholesale Goods"
        }
    ],
    "sg:phone":"+1 409 769 9505",
    "sg:postcode":"77662",
    "sg:province":"TX",
    "sg:tags":[
        "company",
        "logging"
    ],
    "wof:name":"Deep South Logging",
    "wof:placetype":"venue"
},
  "geometry": {"coordinates":[-93.960758,30.161562],"type":"Point"}
}