{
  "type": "Feature",
  "properties": {
    "iso:country":"US",
    "sg:address":"1516 W Green Oaks Blvd",
    "sg:city":"Arlington",
    "sg:classifiers":[
        {
            "category":"Sports & Exercise",
            "subcategory":"Golf",
            "type":"Entertainment"
        }
    ],
    "sg:phone":"+1 817 451 6101",
    "sg:postcode":"76013",
    "sg:province":"TX",
    "sg:tags":[
        "course"
    ],
    "sg:website":"www.arlingtongolf.com",
    "wof:name":"Lake Arlington Golf Course",
    "wof:placetype":"venue"
},
  "geometry": {"coordinates":[-97.18235,32.721256],"type":"Point"}
}