{
  "type": "Feature",
  "properties": {
    "iso:country":"US",
    "sg:address":"615 San Antonio St",
    "sg:city":"Pleasanton",
    "sg:classifiers":[
        {
            "category":"Personal",
            "subcategory":"Beauty Salon",
            "type":"Services"
        }
    ],
    "sg:phone":"+1 830 569 3312",
    "sg:postcode":"78064",
    "sg:province":"TX",
    "sg:tags":[
        "shop"
    ],
    "wof:name":"Gracie's Beauty Salon",
    "wof:placetype":"venue"
},
  "geometry": {"coordinates":[-98.47689699999999,28.973053],"type":"Point"}
}