{
  "type": "Feature",
  "properties": {
    "iso:country":"US",
    "sg:address":"1320 Lakeside Dr",
    "sg:city":"Garland",
    "sg:classifiers":[
        {
            "category":"Personal",
            "type":"Services"
        }
    ],
    "sg:phone":"+1 972 487 1966",
    "sg:postcode":"75040",
    "sg:province":"TX",
    "wof:name":"Bobbys Handyman Service",
    "wof:placetype":"venue"
},
  "geometry": {"coordinates":[-96.645882,32.917948],"type":"Point"}
}