{
  "type": "Feature",
  "properties": {
    "iso:country":"US",
    "sg:address":"312 Nicar St",
    "sg:city":"Houston",
    "sg:classifiers":[
        {
            "category":"Professional",
            "subcategory":"Advertising",
            "type":"Services"
        }
    ],
    "sg:phone":"+1 281 999 1938",
    "sg:postcode":"77037",
    "sg:province":"TX",
    "sg:tags":[
        "agency"
    ],
    "wof:name":"New Vision Advertising",
    "wof:placetype":"venue"
},
  "geometry": {"coordinates":[-95.39590099999999,29.900264],"type":"Point"}
}