{
  "type": "Feature",
  "properties": {
    "iso:country":"US",
    "sg:address":"1918 Montana Trl",
    "sg:city":"Grand Prairie",
    "sg:classifiers":[
        {
            "category":"Building & Trades",
            "subcategory":"Plumbing",
            "type":"Services"
        }
    ],
    "sg:phone":"+1 972 660 7445",
    "sg:postcode":"75052",
    "sg:province":"TX",
    "sg:tags":[
        "contractor"
    ],
    "wof:name":"Eddies Plumbing Service",
    "wof:placetype":"venue"
},
  "geometry": {"coordinates":[-97.03434300000001,32.64728],"type":"Point"}
}