{
  "type": "Feature",
  "properties": {
    "iso:country":"US",
    "sg:address":"2421 Ridgewood St",
    "sg:city":"Irving",
    "sg:classifiers":[
        {
            "category":"Wholesale",
            "subcategory":"Machinery & Supplies",
            "type":"Manufacturing & Wholesale Goods"
        }
    ],
    "sg:phone":"+1 972 258 0156",
    "sg:postcode":"75062",
    "sg:province":"TX",
    "sg:tags":[
        "equipment",
        "industrial"
    ],
    "sg:website":"www.mpakpackaging.com",
    "wof:name":"M Pak",
    "wof:placetype":"venue"
},
  "geometry": {"coordinates":[-96.97854,32.847691],"type":"Point"}
}