{
  "type": "Feature",
  "properties": {
    "iso:country":"US",
    "sg:address":"1317 Northpark Dr Ste 1",
    "sg:city":"Kingwood",
    "sg:classifiers":[
        {
            "category":"Personal",
            "subcategory":"Barber",
            "type":"Services"
        }
    ],
    "sg:phone":"+1 281 354 8249",
    "sg:postcode":"77339",
    "sg:province":"TX",
    "wof:name":"Kingwood Barber Shop",
    "wof:placetype":"venue"
},
  "geometry": {"coordinates":[-95.196575,30.06833],"type":"Point"}
}