{
  "type": "Feature",
  "properties": {
    "iso:country":"US",
    "sg:address":"9720 Hillcroft St",
    "sg:city":"Houston",
    "sg:classifiers":[
        {
            "category":"Restaurant",
            "type":"Food & Drink"
        }
    ],
    "sg:phone":"+1 713 723 8650",
    "sg:postcode":"77096",
    "sg:province":"TX",
    "sg:tags":[
        "bagel",
        "shop",
        "coffee"
    ],
    "sg:website":"www.nybagelhouston.com",
    "wof:name":"New York Coffee Shop",
    "wof:placetype":"venue"
},
  "geometry": {"coordinates":[-95.49369799999999,29.674299],"type":"Point"}
}