{
  "type": "Feature",
  "properties": {
    "iso:country":"US",
    "sg:address":"250 Park Ave",
    "sg:city":"League City",
    "sg:classifiers":[
        {
            "category":"Professional",
            "type":"Services"
        }
    ],
    "sg:phone":"+1 281 280 9908",
    "sg:postcode":"77573",
    "sg:province":"TX",
    "wof:name":"Kiser Service Co",
    "wof:placetype":"venue"
},
  "geometry": {"coordinates":[-95.08930100000001,29.508214],"type":"Point"}
}