{
  "type": "Feature",
  "properties": {
    "iso:country":"US",
    "sg:address":"9414 Twilight Moon Dr",
    "sg:city":"Houston",
    "sg:classifiers":[
        {
            "category":"Recreation",
            "type":"Entertainment"
        }
    ],
    "sg:phone":"+1 281 894 2979",
    "sg:postcode":"77064",
    "sg:province":"TX",
    "sg:tags":[
        "club",
        "membership"
    ],
    "wof:name":"Double R Hunting Club",
    "wof:placetype":"venue"
},
  "geometry": {"coordinates":[-95.564363,29.925332],"type":"Point"}
}