{
  "type": "Feature",
  "properties": {
    "iso:country":"US",
    "sg:address":"303 Camp Craft Rd",
    "sg:city":"Austin",
    "sg:classifiers":[
        {
            "category":"Professional",
            "subcategory":"Engineering",
            "type":"Services"
        }
    ],
    "sg:phone":"+1 512 329 3244",
    "sg:postcode":"78746",
    "sg:province":"TX",
    "sg:tags":[
        "product",
        "software",
        "telecommunication",
        "system"
    ],
    "wof:name":"Austin Info Systems Inc",
    "wof:placetype":"venue"
},
  "geometry": {"coordinates":[-97.81376299999999,30.27865],"type":"Point"}
}