{
  "type": "Feature",
  "properties": {
    "iso:country":"US",
    "sg:address":"7625 W Bellfort St",
    "sg:city":"Houston",
    "sg:classifiers":[
        {
            "category":"Restaurant",
            "type":"Food & Drink"
        }
    ],
    "sg:phone":"+1 713 729 1888",
    "sg:postcode":"77071",
    "sg:province":"TX",
    "wof:name":"Timmy Chan Restaurants No 5",
    "wof:placetype":"venue"
},
  "geometry": {"coordinates":[-95.510696,29.6558],"type":"Point"}
}