{
  "type": "Feature",
  "properties": {
    "iso:country":"US",
    "sg:address":"14026 Sage Bluff",
    "sg:city":"San Antonio",
    "sg:classifiers":[
        {
            "category":"Professional",
            "subcategory":"Management & Consulting",
            "type":"Services"
        }
    ],
    "sg:phone":"+1 210 402 3939",
    "sg:postcode":"78216",
    "sg:province":"TX",
    "wof:name":"Dr Andre A Kulisz LLC",
    "wof:placetype":"venue"
},
  "geometry": {"coordinates":[-98.49647,29.568318],"type":"Point"}
}