{
  "type": "Feature",
  "properties": {
    "iso:country":"US",
    "sg:address":"2503 McCue Rd",
    "sg:city":"Houston",
    "sg:classifiers":[
        {
            "category":"Real Estate",
            "subcategory":"Real Estate Operator",
            "type":"Services"
        }
    ],
    "sg:phone":"+1 713 961 5654",
    "sg:postcode":"77056",
    "sg:province":"TX",
    "sg:tags":[
        "building",
        "apartment"
    ],
    "wof:name":"Country Squire Apartments",
    "wof:placetype":"venue"
},
  "geometry": {"coordinates":[-95.46415399999999,29.742893],"type":"Point"}
}