{
  "type": "Feature",
  "properties": {
    "iso:country":"US",
    "sg:address":"2330 Austin Hwy",
    "sg:city":"San Antonio",
    "sg:classifiers":[
        {
            "category":"Professional",
            "type":"Services"
        }
    ],
    "sg:phone":"+1 210 599 2547",
    "sg:postcode":"78218",
    "sg:province":"TX",
    "sg:tags":[
        "establishment"
    ],
    "wof:name":"T G 103",
    "wof:placetype":"venue"
},
  "geometry": {"coordinates":[-98.41624,29.5038],"type":"Point"}
}