{
  "type": "Feature",
  "properties": {
    "iso:country":"US",
    "sg:address":"4604 Sidereal Dr",
    "sg:city":"Austin",
    "sg:classifiers":[
        {
            "category":"Insurance",
            "subcategory":"Hazard Insurance",
            "type":"Services"
        }
    ],
    "sg:phone":"+1 512 837 5348",
    "sg:postcode":"78727",
    "sg:province":"TX",
    "wof:name":"Michael Phillips",
    "wof:placetype":"venue"
},
  "geometry": {"coordinates":[-97.721857,30.427918],"type":"Point"}
}