{
  "type": "Feature",
  "properties": {
    "iso:country":"US",
    "sg:address":"4301 Crane St",
    "sg:city":"Houston",
    "sg:classifiers":[
        {
            "category":"Travel",
            "subcategory":"Hotels & Motels",
            "type":"Entertainment"
        }
    ],
    "sg:phone":"+1 713 675 3104",
    "sg:postcode":"77026",
    "sg:province":"TX",
    "sg:tags":[
        "operation"
    ],
    "wof:name":"Alfron Motel",
    "wof:placetype":"venue"
},
  "geometry": {"coordinates":[-95.326897,29.797001],"type":"Point"}
}