{
  "type": "Feature",
  "properties": {
    "iso:country":"US",
    "sg:address":"6702 Irvington Blvd",
    "sg:city":"Houston",
    "sg:classifiers":[
        {
            "category":"Government",
            "subcategory":"Fire Station",
            "type":"Public Place"
        }
    ],
    "sg:phone":"+1 713 694 2536",
    "sg:postcode":"77022",
    "sg:province":"TX",
    "sg:tags":[
        "protection"
    ],
    "wof:name":"Fire Dept-Station 30",
    "wof:placetype":"venue"
},
  "geometry": {"coordinates":[-95.361087,29.819618],"type":"Point"}
}