{
  "type": "Feature",
  "properties": {
    "iso:country":"US",
    "sg:address":"13531 Hughes Pl",
    "sg:city":"Dallas",
    "sg:classifiers":[
        {
            "category":"Organizations",
            "subcategory":"Membership Organization",
            "type":"Services"
        }
    ],
    "sg:phone":"+1 972 239 1450",
    "sg:postcode":"75240",
    "sg:province":"TX",
    "wof:name":"Jeffrey A Carter Foundation",
    "wof:placetype":"venue"
},
  "geometry": {"coordinates":[-96.797532,32.932108],"type":"Point"}
}