{
  "type": "Feature",
  "properties": {
    "iso:country":"US",
    "sg:address":"17610 Majestic Forest Dr",
    "sg:city":"Spring",
    "sg:classifiers":[
        {
            "category":"Building & Trades",
            "subcategory":"Construction",
            "type":"Services"
        }
    ],
    "sg:phone":"+1 281 376 5230",
    "sg:postcode":"77379",
    "sg:province":"TX",
    "sg:tags":[
        "home",
        "remodeling",
        "contractor"
    ],
    "wof:name":"Morris House",
    "wof:placetype":"venue"
},
  "geometry": {"coordinates":[-95.518486,30.036725],"type":"Point"}
}