{
  "type": "Feature",
  "properties": {
    "iso:country":"US",
    "sg:address":"915 N Elmendorf St",
    "sg:city":"San Antonio",
    "sg:classifiers":[
        {
            "category":"Organizations",
            "subcategory":"Religious Organization",
            "type":"Services"
        }
    ],
    "sg:phone":"+1 210 434 2279",
    "sg:postcode":"78207",
    "sg:province":"TX",
    "wof:name":"Palestine Baptist Church",
    "wof:placetype":"venue"
},
  "geometry": {"coordinates":[-98.528195,29.43752],"type":"Point"}
}