{
  "type": "Feature",
  "properties": {
    "iso:country":"US",
    "sg:address":"825 Ave H E",
    "sg:city":"Arlington",
    "sg:classifiers":[
        {
            "category":"Wholesale",
            "subcategory":"Machinery & Supplies",
            "type":"Manufacturing & Wholesale Goods"
        },
        {
            "category":"Wholesale",
            "subcategory":"Auto Parts",
            "type":"Manufacturing & Wholesale Goods"
        }
    ],
    "sg:phone":"+1 817 633 1844",
    "sg:postcode":"76011",
    "sg:province":"TX",
    "sg:tags":[
        "tool"
    ],
    "sg:website":"www.nestorsales.com",
    "wof:name":"Ace Tool Co",
    "wof:placetype":"venue"
},
  "geometry": {"coordinates":[-97.053541,32.762144],"type":"Point"}
}