{
  "type": "Feature",
  "properties": {
    "iso:country":"US",
    "sg:address":"1019 16th St",
    "sg:city":"Galveston",
    "sg:classifiers":[
        {
            "category":"Organizations",
            "subcategory":"Religious Organization",
            "type":"Services"
        }
    ],
    "sg:phone":"+1 409 762 4313",
    "sg:postcode":"77550",
    "sg:province":"TX",
    "wof:name":"First Apstlic Pntcostal Church",
    "wof:placetype":"venue"
},
  "geometry": {"coordinates":[-94.78390899999999,29.301794],"type":"Point"}
}