{
  "type": "Feature",
  "properties": {
    "iso:country":"US",
    "sg:address":"1503 E Vickery Blvd",
    "sg:city":"Fort Worth",
    "sg:classifiers":[
        {
            "category":"Shopping",
            "subcategory":"Used Merchandise",
            "type":"Retail Goods"
        }
    ],
    "sg:phone":"+1 817 535 9120",
    "sg:postcode":"76104",
    "sg:province":"TX",
    "sg:tags":[
        "furniture"
    ],
    "wof:name":"Bennie & Flo's Bargain House",
    "wof:placetype":"venue"
},
  "geometry": {"coordinates":[-97.30660399999999,32.739258],"type":"Point"}
}