{
  "type": "Feature",
  "properties": {
    "iso:country":"US",
    "sg:address":"9766 Whithorn Dr",
    "sg:city":"Houston",
    "sg:classifiers":[
        {
            "category":"Professional",
            "subcategory":"Advertising",
            "type":"Services"
        }
    ],
    "sg:phone":"+1 832 444 7675",
    "sg:postcode":"77095",
    "sg:province":"TX",
    "sg:tags":[
        "marketing",
        "consulting",
        "technology",
        "internet"
    ],
    "wof:name":"Bevers & Co",
    "wof:placetype":"venue"
},
  "geometry": {"coordinates":[-95.64801900000001,29.92608],"type":"Point"}
}