{
  "type": "Feature",
  "properties": {
    "iso:country":"US",
    "sg:address":"2300 Palmetto Dr",
    "sg:city":"Mission",
    "sg:phone":"+1 956 583 3943",
    "sg:postcode":"78574",
    "sg:province":"TX",
    "wof:name":"Northwest Puppies",
    "wof:placetype":"venue"
},
  "geometry": {"coordinates":[-98.31343099999999,26.228239],"type":"Point"}
}