{
  "type": "Feature",
  "properties": {
    "iso:country":"US",
    "sg:address":"420 N Hall St",
    "sg:city":"Fairfield",
    "sg:classifiers":[
        {
            "category":"Wholesale",
            "subcategory":"Machinery & Supplies",
            "type":"Manufacturing & Wholesale Goods"
        }
    ],
    "sg:phone":"+1 903 389 3166",
    "sg:postcode":"75840",
    "sg:province":"TX",
    "sg:tags":[
        "equipment",
        "industrial"
    ],
    "wof:name":"Larrys Welding Supplies",
    "wof:placetype":"venue"
},
  "geometry": {"coordinates":[-96.15870200000001,31.729988],"type":"Point"}
}