{
  "type": "Feature",
  "properties": {
    "iso:country":"US",
    "sg:address":"1501 US Hwy 281",
    "sg:city":"Marble Falls",
    "sg:classifiers":[
        {
            "category":"Sports & Exercise",
            "subcategory":"Bowling",
            "type":"Entertainment"
        }
    ],
    "sg:phone":"+1 830 693 4386",
    "sg:postcode":"78654",
    "sg:province":"TX",
    "sg:tags":[
        "center"
    ],
    "wof:name":"Rockhopper's Family Fun Ctr",
    "wof:placetype":"venue"
},
  "geometry": {"coordinates":[-98.285889,30.526007],"type":"Point"}
}