{
  "type": "Feature",
  "properties": {
    "iso:country":"US",
    "sg:address":"607 University Dr E",
    "sg:city":"College Station",
    "sg:classifiers":[
        {
            "category":"Personal",
            "subcategory":"Beauty Salon",
            "type":"Services"
        }
    ],
    "sg:phone":"+1 979 846 8822",
    "sg:postcode":"77840",
    "sg:province":"TX",
    "sg:tags":[
        "hair"
    ],
    "wof:name":"T G F Precision Haircutters",
    "wof:placetype":"venue"
},
  "geometry": {"coordinates":[-96.329945,30.632332],"type":"Point"}
}