{
  "type": "Feature",
  "properties": {
    "iso:country":"US",
    "sg:address":"1511 Hidden Hill Cir",
    "sg:city":"Kingwood",
    "sg:classifiers":[
        {
            "category":"Banks & Credit Unions",
            "subcategory":"Investment Brokerage",
            "type":"Services"
        }
    ],
    "sg:phone":"+1 281 358 3624",
    "sg:postcode":"77339",
    "sg:province":"TX",
    "sg:tags":[
        "advisory"
    ],
    "wof:name":"Rba Investments",
    "wof:placetype":"venue"
},
  "geometry": {"coordinates":[-95.23344899999999,30.027217],"type":"Point"}
}