{
  "type": "Feature",
  "properties": {
    "iso:country":"US",
    "sg:address":"714 Van Zandt St",
    "sg:city":"San Angelo",
    "sg:classifiers":[
        {
            "category":"Manufacturing",
            "subcategory":"Glass & Minerals",
            "type":"Manufacturing & Wholesale Goods"
        }
    ],
    "sg:phone":"+1 325 651 6542",
    "sg:postcode":"76905",
    "sg:province":"TX",
    "sg:tags":[
        "ready",
        "concrete",
        "mfg"
    ],
    "wof:name":"Dry & Ready",
    "wof:placetype":"venue"
},
  "geometry": {"coordinates":[-100.40466600000001,31.451509],"type":"Point"}
}