{
  "type": "Feature",
  "properties": {
    "iso:country":"US",
    "sg:address":"5012 Mosson Rd",
    "sg:city":"Fort Worth",
    "sg:classifiers":[
        {
            "category":"Local Transit",
            "type":"Transportation"
        }
    ],
    "sg:phone":"+1 817 572 6808",
    "sg:postcode":"76119",
    "sg:province":"TX",
    "sg:tags":[
        "shuttle"
    ],
    "wof:name":"VIP Charters",
    "wof:placetype":"venue"
},
  "geometry": {"coordinates":[-97.244533,32.675294],"type":"Point"}
}