{
  "type": "Feature",
  "properties": {
    "iso:country":"US",
    "sg:address":"1302 S Cypress St",
    "sg:city":"Brady",
    "sg:classifiers":[
        {
            "category":"Social Services",
            "subcategory":"Child Care",
            "type":"Services"
        }
    ],
    "sg:phone":"+1 325 597 7986",
    "sg:postcode":"76825",
    "sg:province":"TX",
    "sg:tags":[
        "day"
    ],
    "wof:name":"Child Ride Moon Walk",
    "wof:placetype":"venue"
},
  "geometry": {"coordinates":[-99.33939599999999,31.125235],"type":"Point"}
}