{
  "type": "Feature",
  "properties": {
    "iso:country":"US",
    "sg:address":"3317 Northland Drive",
    "sg:city":"Austin",
    "sg:classifiers":[
        {
            "category":"Coffee & Tea",
            "type":"Food & Drink"
        }
    ],
    "sg:phone":"+1 512 458 5574",
    "sg:postcode":"78731",
    "sg:province":"TX",
    "sg:website":"www.starbucks.com",
    "wof:name":"Starbucks Coffee",
    "wof:placetype":"venue"
},
  "geometry": {"coordinates":[-97.758684,30.335825],"type":"Point"}
}