{
  "type": "Feature",
  "properties": {
    "iso:country":"US",
    "sg:address":"606 Woodlake Dr",
    "sg:city":"Mc Queeney",
    "sg:classifiers":[
        {
            "category":"Professional",
            "subcategory":"Business Services",
            "type":"Services"
        }
    ],
    "sg:phone":"+1 830 557 6809",
    "sg:postcode":"78123",
    "sg:province":"TX",
    "wof:name":"Woodlake Partners Management I",
    "wof:placetype":"venue"
},
  "geometry": {"coordinates":[-98.033619,29.620969],"type":"Point"}
}