{
  "type": "Feature",
  "properties": {
    "iso:country":"US",
    "sg:address":"510 N I Rd",
    "sg:city":"San Juan",
    "sg:classifiers":[
        {
            "category":"Food & Beverages",
            "subcategory":"Groceries & Convenience Stores",
            "type":"Retail Goods"
        }
    ],
    "sg:phone":"+1 956 702 4111",
    "sg:postcode":"78589",
    "sg:province":"TX",
    "wof:name":"Kold Spot",
    "wof:placetype":"venue"
},
  "geometry": {"coordinates":[-98.16672199999999,26.197027],"type":"Point"}
}