{
  "type": "Feature",
  "properties": {
    "iso:country":"US",
    "sg:address":"410 Holy Cross Dr",
    "sg:city":"San Antonio",
    "sg:classifiers":[
        {
            "category":"Recreation",
            "type":"Entertainment"
        }
    ],
    "sg:phone":"+1 210 432 1155",
    "sg:postcode":"78228",
    "sg:province":"TX",
    "wof:name":"El Conquistador Party House",
    "wof:placetype":"venue"
},
  "geometry": {"coordinates":[-98.57202599999999,29.449589],"type":"Point"}
}