{
  "type": "Feature",
  "properties": {
    "iso:country":"US",
    "sg:address":"1305 Alta Vista Ave",
    "sg:city":"Austin",
    "sg:classifiers":[
        {
            "category":"Professional",
            "type":"Services"
        }
    ],
    "sg:phone":"+1 512 441 1695",
    "sg:postcode":"78704",
    "sg:province":"TX",
    "wof:name":"Tracey Baudoin",
    "wof:placetype":"venue"
},
  "geometry": {"coordinates":[-97.74145900000001,30.247034],"type":"Point"}
}