{
  "type": "Feature",
  "properties": {
    "iso:country":"US",
    "sg:address":"3245 Townsend Dr",
    "sg:city":"Fort Worth",
    "sg:classifiers":[
        {
            "category":"Building & Trades",
            "subcategory":"Landscaping Services",
            "type":"Services"
        }
    ],
    "sg:phone":"+1 817 926 2190",
    "sg:postcode":"76110",
    "sg:province":"TX",
    "wof:name":"Cut Tree Service Landscaping",
    "wof:placetype":"venue"
},
  "geometry": {"coordinates":[-97.349181,32.703142],"type":"Point"}
}