{
  "type": "Feature",
  "properties": {
    "iso:country":"US",
    "sg:address":"116 N Polk St",
    "sg:city":"Jefferson",
    "sg:classifiers":[
        {
            "category":"Professional",
            "subcategory":"Advertising",
            "type":"Services"
        }
    ],
    "sg:phone":"+1 903 789 3414",
    "sg:postcode":"75657",
    "sg:province":"TX",
    "sg:tags":[
        "mi"
    ],
    "wof:name":"Imhof Art Gallery",
    "wof:placetype":"venue"
},
  "geometry": {"coordinates":[-94.344499,32.757123],"type":"Point"}
}