{
  "type": "Feature",
  "properties": {
    "iso:country":"US",
    "sg:address":"4333 N Josey Ln",
    "sg:city":"Carrollton",
    "sg:classifiers":[
        {
            "category":"Health Services",
            "subcategory":"Doctor",
            "type":"Services"
        }
    ],
    "sg:phone":"+1 972 394 4500",
    "sg:postcode":"75010",
    "sg:province":"TX",
    "sg:tags":[
        "medical"
    ],
    "wof:name":"Goldberg Kenneth A MD PA",
    "wof:placetype":"venue"
},
  "geometry": {"coordinates":[-96.884542,33.028132],"type":"Point"}
}