{
  "type": "Feature",
  "properties": {
    "iso:country":"US",
    "sg:address":"1011 E Ennis Ave",
    "sg:city":"Ennis",
    "sg:classifiers":[
        {
            "category":"Banks & Credit Unions",
            "subcategory":"Bank",
            "type":"Services"
        }
    ],
    "sg:phone":"+1 972 875 1458",
    "sg:postcode":"75119",
    "sg:province":"TX",
    "sg:tags":[
        "cashing",
        "check"
    ],
    "wof:name":"Advance America",
    "wof:placetype":"venue"
},
  "geometry": {"coordinates":[-96.616863,32.333173],"type":"Point"}
}