{
  "type": "Feature",
  "properties": {
    "iso:country":"US",
    "sg:address":"1518 Marshall St",
    "sg:city":"Houston",
    "sg:classifiers":[
        {
            "category":"Professional",
            "type":"Services"
        }
    ],
    "sg:phone":"+1 713 522 3778",
    "sg:postcode":"77006",
    "sg:province":"TX",
    "wof:name":"Rab Services Inc",
    "wof:placetype":"venue"
},
  "geometry": {"coordinates":[-95.399035,29.739617],"type":"Point"}
}