{
  "type": "Feature",
  "properties": {
    "iso:country":"US",
    "sg:address":"1515 Bissonnet St",
    "sg:city":"Houston",
    "sg:classifiers":[
        {
            "category":"Education",
            "subcategory":"University",
            "type":"Public Place"
        }
    ],
    "sg:phone":"+1 713 348 4723",
    "sg:postcode":"77005",
    "sg:province":"TX",
    "sg:tags":[
        "college"
    ],
    "sg:website":"campushousing.rice.edu/graduate/",
    "wof:name":"Rice Graduate Apartments",
    "wof:placetype":"venue"
},
  "geometry": {"coordinates":[-95.398359,29.725551],"type":"Point"}
}