{
  "type": "Feature",
  "properties": {
    "iso:country":"US",
    "sg:address":"375 Fletcher Rd",
    "sg:city":"Lumberton",
    "sg:classifiers":[
        {
            "category":"Retail",
            "subcategory":"Repair Shop",
            "type":"Services"
        }
    ],
    "sg:phone":"+1 409 755 1585",
    "sg:postcode":"77657",
    "sg:province":"TX",
    "sg:tags":[
        "bathtub",
        "sink",
        "refinishing"
    ],
    "wof:name":"Cox Coating",
    "wof:placetype":"venue"
},
  "geometry": {"coordinates":[-94.195002,30.268303],"type":"Point"}
}