{
  "type": "Feature",
  "properties": {
    "iso:country":"US",
    "sg:address":"1110 State Hwy 16",
    "sg:city":"Graham",
    "sg:classifiers":[
        {
            "category":"Sports & Exercise",
            "subcategory":"Gym",
            "type":"Entertainment"
        }
    ],
    "sg:phone":"+1 940 549 5898",
    "sg:postcode":"76450",
    "sg:province":"TX",
    "sg:tags":[
        "fitness",
        "woman",
        "physical",
        "for",
        "facility"
    ],
    "wof:name":"Curves For Women",
    "wof:placetype":"venue"
},
  "geometry": {"coordinates":[-98.589696,33.095201],"type":"Point"}
}