{
  "type": "Feature",
  "properties": {
    "iso:country":"US",
    "sg:address":"5746 Vickery Blvd",
    "sg:city":"Dallas",
    "sg:classifiers":[
        {
            "category":"Arts & Performance",
            "subcategory":"Theater",
            "type":"Entertainment"
        }
    ],
    "sg:phone":"+1 214 824 1648",
    "sg:postcode":"75206",
    "sg:province":"TX",
    "sg:tags":[
        "group"
    ],
    "wof:name":"Merlin Magical One",
    "wof:placetype":"venue"
},
  "geometry": {"coordinates":[-96.76883100000001,32.822858],"type":"Point"}
}