{
  "type": "Feature",
  "properties": {
    "iso:country":"US",
    "sg:address":"106 S Front St",
    "sg:city":"Kyle",
    "sg:classifiers":[
        {
            "category":"Government",
            "subcategory":"Office",
            "type":"Public Place"
        }
    ],
    "sg:phone":"+1 512 268 1270",
    "sg:postcode":"78640",
    "sg:province":"TX",
    "sg:tags":[
        "county",
        "program",
        "health"
    ],
    "wof:name":"Health Dept",
    "wof:placetype":"venue"
},
  "geometry": {"coordinates":[-97.875445,29.9885],"type":"Point"}
}