{
  "type": "Feature",
  "properties": {
    "iso:country":"US",
    "sg:address":"8002 US Hwy 277",
    "sg:city":"Abilene",
    "sg:classifiers":[
        {
            "category":"Shopping",
            "type":"Retail Goods"
        }
    ],
    "sg:phone":"+1 325 673 8881",
    "sg:postcode":"79601",
    "sg:province":"TX",
    "sg:tags":[
        "monument"
    ],
    "wof:name":"Clemmer Monument Works",
    "wof:placetype":"venue"
},
  "geometry": {"coordinates":[-99.77291200000001,32.545141],"type":"Point"}
}