{
  "type": "Feature",
  "properties": {
    "iso:country":"US",
    "sg:address":"1307 Castroville Rd",
    "sg:city":"San Antonio",
    "sg:classifiers":[
        {
            "category":"Shopping",
            "subcategory":"Clothing, Apparel, & Fashions",
            "type":"Retail Goods"
        }
    ],
    "sg:phone":"+1 210 433 9134",
    "sg:postcode":"78237",
    "sg:province":"TX",
    "sg:tags":[
        "shop",
        "bridal"
    ],
    "wof:name":"Rebecca's Boutique",
    "wof:placetype":"venue"
},
  "geometry": {"coordinates":[-98.559167,29.415499],"type":"Point"}
}