{
  "type": "Feature",
  "properties": {
    "iso:country":"US",
    "sg:address":"3440 Bell St Ste 302",
    "sg:city":"Amarillo",
    "sg:classifiers":[
        {
            "category":"Banks & Credit Unions",
            "subcategory":"Investment Brokerage",
            "type":"Services"
        },
        {
            "category":"Banks & Credit Unions",
            "subcategory":"Bank",
            "type":"Services"
        },
        {
            "category":"Banks & Credit Unions",
            "subcategory":"Financial Services",
            "type":"Services"
        }
    ],
    "sg:phone":"+1 806 553 4354",
    "sg:postcode":"79109",
    "sg:province":"TX",
    "sg:tags":[
        "advisory",
        "mutual",
        "retirement",
        "annuity",
        "broker",
        "fund",
        "planning",
        "plan",
        "consultant",
        "security",
        "bond",
        "insurance",
        "stock"
    ],
    "sg:website":"http://amarillo.citysearch.com/profile/external/604311022/amarillo_tx/edward_jones_taylor_graves.html?publisher=yellowpages&reference_id=1&placement=ypwebsitemip",
    "wof:name":"Edward Jones - TAYLOR GRAVES",
    "wof:placetype":"venue"
},
  "geometry": {"coordinates":[-101.902304,35.175554],"type":"Point"}
}