{
  "type": "Feature",
  "properties": {
    "iso:country":"US",
    "sg:address":"1167 Patricia",
    "sg:city":"San Antonio",
    "sg:classifiers":[
        {
            "category":"Autos & Motor Vehicles",
            "subcategory":"Fuel & Gas Station",
            "type":"Retail Goods"
        }
    ],
    "sg:phone":"+1 210 342 5240",
    "sg:postcode":"78213",
    "sg:province":"TX",
    "sg:tags":[
        "station",
        "gasoline"
    ],
    "wof:name":"Texaco",
    "wof:placetype":"venue"
},
  "geometry": {"coordinates":[-98.51261100000001,29.545139],"type":"Point"}
}