{
  "type": "Feature",
  "properties": {
    "iso:country":"US",
    "sg:address":"2411 S Henderson Blvd",
    "sg:city":"Kilgore",
    "sg:classifiers":[
        {
            "category":"Food & Beverages",
            "subcategory":"Groceries & Convenience Stores",
            "type":"Retail Goods"
        }
    ],
    "sg:phone":"+1 903 983 2776",
    "sg:postcode":"75662",
    "sg:province":"TX",
    "wof:name":"Clayton's Mini Mart South",
    "wof:placetype":"venue"
},
  "geometry": {"coordinates":[-94.86941299999999,32.367513],"type":"Point"}
}