{
  "type": "Feature",
  "properties": {
    "iso:country":"US",
    "sg:address":"2815 Chenault St",
    "sg:city":"Fort Worth",
    "sg:classifiers":[
        {
            "category":"Organizations",
            "subcategory":"Religious Organization",
            "type":"Services"
        }
    ],
    "sg:phone":"+1 817 834 6011",
    "sg:postcode":"76111",
    "sg:province":"TX",
    "sg:tags":[
        "church"
    ],
    "wof:name":"Pentecostal Church Of God",
    "wof:placetype":"venue"
},
  "geometry": {"coordinates":[-97.305393,32.764345],"type":"Point"}
}