{
  "type": "Feature",
  "properties": {
    "iso:country":"US",
    "sg:address":"2905 Country Place Ct",
    "sg:city":"Carrollton",
    "sg:classifiers":[
        {
            "category":"Banks & Credit Unions",
            "subcategory":"Investment Brokerage",
            "type":"Services"
        }
    ],
    "sg:phone":"+1 972 417 2690",
    "sg:postcode":"75006",
    "sg:province":"TX",
    "wof:name":"Parkhill Associates",
    "wof:placetype":"venue"
},
  "geometry": {"coordinates":[-96.854513,32.959397],"type":"Point"}
}