{
  "type": "Feature",
  "properties": {
    "iso:country":"US",
    "sg:address":"1175 FM 2673",
    "sg:city":"Canyon Lake",
    "sg:classifiers":[
        {
            "category":"Insurance",
            "subcategory":"Insurance Agent",
            "type":"Services"
        }
    ],
    "sg:phone":"+1 830 964 4049",
    "sg:postcode":"78133",
    "sg:province":"TX",
    "wof:name":"Miller & Miller Insurance",
    "wof:placetype":"venue"
},
  "geometry": {"coordinates":[-98.171222,29.850038],"type":"Point"}
}