{
  "type": "Feature",
  "properties": {
    "iso:country":"US",
    "sg:address":"3900 Kenneth Ave",
    "sg:city":"Beaumont",
    "sg:classifiers":[
        {
            "category":"Shopping",
            "subcategory":"Gifts & Souvenirs",
            "type":"Retail Goods"
        }
    ],
    "sg:phone":"+1 409 835 7263",
    "sg:postcode":"77705",
    "sg:province":"TX",
    "sg:tags":[
        "shop"
    ],
    "wof:name":"Good Time",
    "wof:placetype":"venue"
},
  "geometry": {"coordinates":[-94.08933500000001,30.048116],"type":"Point"}
}