{
  "type": "Feature",
  "properties": {
    "iso:country":"US",
    "sg:address":"419 E Sam Rayburn Dr",
    "sg:city":"Bonham",
    "sg:classifiers":[
        {
            "category":"Wholesale",
            "subcategory":"Farm Supplies",
            "type":"Manufacturing & Wholesale Goods"
        }
    ],
    "sg:phone":"+1 903 583 7416",
    "sg:postcode":"75418",
    "sg:province":"TX",
    "sg:tags":[
        "hardware"
    ],
    "wof:name":"Orschelin Farm and Home 88",
    "wof:placetype":"venue"
},
  "geometry": {"coordinates":[-96.175462,33.577039],"type":"Point"}
}