{
  "type": "Feature",
  "properties": {
    "iso:country":"US",
    "sg:address":"4303 Rivercrest Dr",
    "sg:city":"Wichita Falls",
    "sg:classifiers":[
        {
            "category":"Shopping",
            "type":"Retail Goods"
        }
    ],
    "sg:phone":"+1 940 692 9064",
    "sg:postcode":"76309",
    "sg:province":"TX",
    "sg:tags":[
        "candle"
    ],
    "wof:name":"Southwest Candles",
    "wof:placetype":"venue"
},
  "geometry": {"coordinates":[-98.554748,33.891795],"type":"Point"}
}