{
  "type": "Feature",
  "properties": {
    "iso:country":"US",
    "sg:address":"13114 Maxwell Rd",
    "sg:city":"Cypress",
    "sg:classifiers":[
        {
            "category":"Building & Trades",
            "subcategory":"Construction",
            "type":"Services"
        }
    ],
    "sg:phone":"+1 281 304 5345",
    "sg:postcode":"77429",
    "sg:province":"TX",
    "sg:tags":[
        "masonry",
        "contractor"
    ],
    "wof:name":"Labrozzi Custom Masonry",
    "wof:placetype":"venue"
},
  "geometry": {"coordinates":[-95.62342,29.97067],"type":"Point"}
}