{
  "type": "Feature",
  "properties": {
    "iso:country":"US",
    "sg:address":"2602 Ave M",
    "sg:city":"Hondo",
    "sg:classifiers":[
        {
            "category":"Professional",
            "subcategory":"Management & Consulting",
            "type":"Services"
        }
    ],
    "sg:phone":"+1 830 741 2003",
    "sg:postcode":"78861",
    "sg:province":"TX",
    "wof:name":"Larry Winkler",
    "wof:placetype":"venue"
},
  "geometry": {"coordinates":[-99.142022,29.341422],"type":"Point"}
}