{
  "type": "Feature",
  "properties": {
    "iso:country":"US",
    "sg:address":"120 E Kaufman St",
    "sg:city":"Paris",
    "sg:classifiers":[
        {
            "category":"Social Services",
            "type":"Services"
        }
    ],
    "sg:phone":"+1 903 785 3563",
    "sg:postcode":"75460",
    "sg:province":"TX",
    "sg:tags":[
        "organization",
        "welfare"
    ],
    "wof:name":"King's Daughters",
    "wof:placetype":"venue"
},
  "geometry": {"coordinates":[-95.55521299999999,33.659833],"type":"Point"}
}