{
  "type": "Feature",
  "properties": {
    "iso:country":"US",
    "sg:address":"4408 Andert Rd",
    "sg:city":"Bryan",
    "sg:classifiers":[
        {
            "category":"Shopping",
            "subcategory":"Hobbies, Toys, & Games",
            "type":"Retail Goods"
        }
    ],
    "sg:phone":"+1 979 589 2855",
    "sg:postcode":"77808",
    "sg:province":"TX",
    "wof:name":"Which Crafts",
    "wof:placetype":"venue"
},
  "geometry": {"coordinates":[-96.299317,30.7437],"type":"Point"}
}