{
  "type": "Feature",
  "properties": {
    "iso:country":"US",
    "sg:address":"120 Sundance Pkwy",
    "sg:city":"Round Rock",
    "sg:classifiers":[
        {
            "category":"Home & Garden",
            "subcategory":"Building Materials",
            "type":"Retail Goods"
        }
    ],
    "sg:phone":"+1 512 600 0011",
    "sg:postcode":"78681",
    "sg:province":"TX",
    "wof:name":"Lowes",
    "wof:placetype":"venue"
},
  "geometry": {"coordinates":[-97.67917199999999,30.483575],"type":"Point"}
}