{
  "type": "Feature",
  "properties": {
    "iso:country":"US",
    "sg:address":"3924 Menn St",
    "sg:city":"Fort Worth",
    "sg:classifiers":[
        {
            "category":"Building & Trades",
            "subcategory":"Construction",
            "type":"Services"
        }
    ],
    "sg:phone":"+1 817 401 5638",
    "sg:postcode":"76117",
    "sg:province":"TX",
    "sg:tags":[
        "house"
    ],
    "wof:name":"CND Construction",
    "wof:placetype":"venue"
},
  "geometry": {"coordinates":[-97.28855799999999,32.805396],"type":"Point"}
}