{
  "type": "Feature",
  "properties": {
    "iso:country":"US",
    "sg:address":"2940 Piper Rd",
    "sg:city":"Pearland",
    "sg:classifiers":[
        {
            "category":"Real Estate",
            "subcategory":"Real Estate Agent",
            "type":"Services"
        }
    ],
    "sg:phone":"+1 281 997 1805",
    "sg:postcode":"77584",
    "sg:province":"TX",
    "wof:name":"Davids Rental Properties",
    "wof:placetype":"venue"
},
  "geometry": {"coordinates":[-95.328382,29.559135],"type":"Point"}
}