{
  "type": "Feature",
  "properties": {
    "iso:country":"US",
    "sg:address":"1317 Middleton Dr",
    "sg:city":"Cedar Hill",
    "sg:classifiers":[
        {
            "category":"Home & Garden",
            "subcategory":"Furniture",
            "type":"Retail Goods"
        }
    ],
    "sg:phone":"+1 972 291 0004",
    "sg:postcode":"75104",
    "sg:province":"TX",
    "wof:name":"A&P Furniture & Transport",
    "wof:placetype":"venue"
},
  "geometry": {"coordinates":[-96.954779,32.614157],"type":"Point"}
}