{
  "type": "Feature",
  "properties": {
    "iso:country":"US",
    "sg:address":"5307 Mockingbird Ln",
    "sg:city":"Dallas",
    "sg:classifiers":[
        {
            "category":"Real Estate",
            "subcategory":"Real Estate Agent",
            "type":"Services"
        }
    ],
    "sg:phone":"+1 214 414 5620",
    "sg:postcode":"75206",
    "sg:province":"TX",
    "wof:name":"Corner Real Estate Services",
    "wof:placetype":"venue"
},
  "geometry": {"coordinates":[-96.77866299999999,32.836585],"type":"Point"}
}