{
  "type": "Feature",
  "properties": {
    "iso:country":"US",
    "sg:address":"100 Briar Patch Cove",
    "sg:city":"Georgetown",
    "sg:classifiers":[
        {
            "category":"Professional",
            "type":"Services"
        }
    ],
    "sg:phone":"+1 512 864 7890",
    "sg:postcode":"78628",
    "sg:province":"TX",
    "wof:name":"Judge Muse",
    "wof:placetype":"venue"
},
  "geometry": {"coordinates":[-97.725937,30.706566],"type":"Point"}
}