{
  "type": "Feature",
  "properties": {
    "iso:country":"US",
    "sg:address":"2516 Avenue H",
    "sg:city":"Rosenberg",
    "sg:classifiers":[
        {
            "category":"Food & Beverages",
            "subcategory":"Groceries & Convenience Stores",
            "type":"Retail Goods"
        }
    ],
    "sg:phone":"+1 281 341 5011",
    "sg:postcode":"77471",
    "sg:province":"TX",
    "wof:name":"Budget Chopper",
    "wof:placetype":"venue"
},
  "geometry": {"coordinates":[-95.801148,29.558403],"type":"Point"}
}