{
  "type": "Feature",
  "properties": {
    "iso:country":"US",
    "sg:address":"4340 N Central Expy # 920",
    "sg:city":"Dallas",
    "sg:classifiers":[
        {
            "category":"Manufacturing",
            "subcategory":"Metals",
            "type":"Manufacturing & Wholesale Goods"
        },
        {
            "category":"Manufacturing",
            "subcategory":"Jewelry",
            "type":"Manufacturing & Wholesale Goods"
        }
    ],
    "sg:phone":"+1 214 522 8300",
    "sg:postcode":"75206",
    "sg:province":"TX",
    "sg:tags":[
        "stone",
        "manufacturer",
        "metals-precious",
        "jewelers-wholesale",
        "jewels-imitation"
    ],
    "wof:name":"Southwest Jewel Trade",
    "wof:placetype":"venue"
},
  "geometry": {"coordinates":[-96.78766400000001,32.818162],"type":"Point"}
}