{
  "type": "Feature",
  "properties": {
    "iso:country":"US",
    "sg:address":"3699 McKinney Ave",
    "sg:city":"Dallas",
    "sg:classifiers":[
        {
            "category":"Cinema",
            "subcategory":"Movie Theater",
            "type":"Entertainment"
        }
    ],
    "sg:phone":"+1 214 520 0025",
    "sg:postcode":"75204",
    "sg:province":"TX",
    "wof:name":"Magnolia Theater",
    "wof:placetype":"venue"
},
  "geometry": {"coordinates":[-96.797642,32.806948],"type":"Point"}
}