{
  "type": "Feature",
  "properties": {
    "iso:country":"US",
    "sg:address":"1107 Cowboys Pkwy",
    "sg:city":"Irving",
    "sg:classifiers":[
        {
            "category":"Manufacturing",
            "subcategory":"Tools & Machinery",
            "type":"Manufacturing & Wholesale Goods"
        }
    ],
    "sg:phone":"+1 972 402 8426",
    "sg:postcode":"75063",
    "sg:province":"TX",
    "sg:tags":[
        "machine",
        "mfg"
    ],
    "wof:name":"Amada America Inc",
    "wof:placetype":"venue"
},
  "geometry": {"coordinates":[-96.962648,32.939866],"type":"Point"}
}