{
  "type": "Feature",
  "properties": {
    "iso:country":"US",
    "sg:address":"12014 Chatam Ln",
    "sg:city":"Houston",
    "sg:classifiers":[
        {
            "category":"Wholesale",
            "subcategory":"Machinery & Supplies",
            "type":"Manufacturing & Wholesale Goods"
        }
    ],
    "sg:phone":"+1 713 782 2586",
    "sg:postcode":"77024",
    "sg:province":"TX",
    "sg:tags":[
        "oil",
        "refining"
    ],
    "wof:name":"Sercel Incorporated",
    "wof:placetype":"venue"
},
  "geometry": {"coordinates":[-95.539097,29.761266],"type":"Point"}
}