{
  "type": "Feature",
  "properties": {
    "iso:country":"US",
    "sg:address":"910 Egyptian Dr",
    "sg:city":"Corpus Christi",
    "sg:classifiers":[
        {
            "category":"Professional",
            "subcategory":"Engineering",
            "type":"Services"
        }
    ],
    "sg:phone":"+1 361 993 6721",
    "sg:postcode":"78412",
    "sg:province":"TX",
    "sg:tags":[
        "engineer"
    ],
    "wof:name":"Home For Assisted Living",
    "wof:placetype":"venue"
},
  "geometry": {"coordinates":[-97.347447,27.708203],"type":"Point"}
}