{
  "type": "Feature",
  "properties": {
    "iso:country":"US",
    "sg:address":"1844 W Division St",
    "sg:city":"Arlington",
    "sg:classifiers":[
        {
            "category":"Wholesale",
            "subcategory":"Apparel",
            "type":"Manufacturing & Wholesale Goods"
        }
    ],
    "sg:phone":"+1 817 274 7547",
    "sg:postcode":"76012",
    "sg:province":"TX",
    "sg:tags":[
        "contractor",
        "woman",
        "clothing",
        "mfg"
    ],
    "wof:name":"Zanne Holmes Design",
    "wof:placetype":"venue"
},
  "geometry": {"coordinates":[-97.136994,32.735822],"type":"Point"}
}