{
  "type": "Feature",
  "properties": {
    "iso:country":"US",
    "sg:address":"3733 Shell St",
    "sg:city":"El Paso",
    "sg:classifiers":[
        {
            "category":"Home & Garden",
            "subcategory":"Building Materials",
            "type":"Retail Goods"
        }
    ],
    "sg:phone":"+1 915 779 0500",
    "sg:postcode":"79925",
    "sg:province":"TX",
    "sg:tags":[
        "type",
        "door"
    ],
    "wof:name":"El Paso Door Co",
    "wof:placetype":"venue"
},
  "geometry": {"coordinates":[-106.362573,31.796414],"type":"Point"}
}