{
  "type": "Feature",
  "properties": {
    "iso:country":"US",
    "sg:address":"4502 Lilac Ln",
    "sg:city":"Victoria",
    "sg:classifiers":[
        {
            "category":"Professional",
            "type":"Services"
        }
    ],
    "sg:phone":"+1 361 788 4570",
    "sg:postcode":"77901",
    "sg:province":"TX",
    "sg:tags":[
        "establishment"
    ],
    "wof:name":"Gingerbread Cottage",
    "wof:placetype":"venue"
},
  "geometry": {"coordinates":[-96.998615,28.834577],"type":"Point"}
}