{
  "type": "Feature",
  "properties": {
    "iso:country":"US",
    "sg:address":"1002 Camden St",
    "sg:city":"San Antonio",
    "sg:classifiers":[
        {
            "category":"Banks & Credit Unions",
            "subcategory":"Bank",
            "type":"Services"
        }
    ],
    "sg:phone":"+1 210 226 3751",
    "sg:postcode":"78215",
    "sg:province":"TX",
    "wof:name":"Local 500 IBEW Credit Union",
    "wof:placetype":"venue"
},
  "geometry": {"coordinates":[-98.484486,29.438953],"type":"Point"}
}