{
  "type": "Feature",
  "properties": {
    "iso:country":"US",
    "sg:address":"13827 Woodchester Dr",
    "sg:city":"Sugar Land",
    "sg:classifiers":[
        {
            "category":"Wholesale",
            "subcategory":"Auto Parts",
            "type":"Manufacturing & Wholesale Goods"
        }
    ],
    "sg:phone":"+1 281 242 1596",
    "sg:postcode":"77478",
    "sg:province":"TX",
    "sg:tags":[
        "equipment",
        "machinery"
    ],
    "wof:name":"L & D Procurement Specialists",
    "wof:placetype":"venue"
},
  "geometry": {"coordinates":[-95.628056,29.641694],"type":"Point"}
}