{
  "type": "Feature",
  "properties": {
    "iso:country":"US",
    "sg:address":"460 State Hwy 36",
    "sg:city":"Cameron",
    "sg:classifiers":[
        {
            "category":"Shopping",
            "subcategory":"Clothing, Apparel, & Fashions",
            "type":"Retail Goods"
        }
    ],
    "sg:phone":"+1 254 697 4814",
    "sg:postcode":"76520",
    "sg:province":"TX",
    "sg:tags":[
        "navy",
        "army"
    ],
    "wof:name":"Little River Crafts & Army Sur",
    "wof:placetype":"venue"
},
  "geometry": {"coordinates":[-96.978538,30.853724],"type":"Point"}
}