{
  "type": "Feature",
  "properties": {
    "iso:country":"US",
    "sg:address":"2207 Clear Creek Rd",
    "sg:city":"Killeen",
    "sg:classifiers":[
        {
            "category":"Health Services",
            "subcategory":"Hospital",
            "type":"Services"
        }
    ],
    "sg:phone":"+1 254 526 5353",
    "sg:postcode":"76549",
    "sg:province":"TX",
    "sg:tags":[
        "treatment",
        "cancer",
        "center"
    ],
    "wof:name":"Killeen Cancer Clinic",
    "wof:placetype":"venue"
},
  "geometry": {"coordinates":[-97.798354,31.116534],"type":"Point"}
}