{
  "type": "Feature",
  "properties": {
    "iso:country":"US",
    "sg:address":"8011 Blankenship Dr",
    "sg:city":"Houston",
    "sg:classifiers":[
        {
            "category":"Wholesale",
            "subcategory":"Machinery & Supplies",
            "type":"Manufacturing & Wholesale Goods"
        }
    ],
    "sg:phone":"+1 713 681 5115",
    "sg:postcode":"77055",
    "sg:province":"TX",
    "sg:tags":[
        "equipment",
        "oil",
        "well"
    ],
    "wof:name":"Wilson Valve Specialties",
    "wof:placetype":"venue"
},
  "geometry": {"coordinates":[-95.492743,29.819843],"type":"Point"}
}