{
  "type": "Feature",
  "properties": {
    "iso:country":"US",
    "sg:address":"102 Decker Ct",
    "sg:city":"Irving",
    "sg:classifiers":[
        {
            "category":"Wholesale",
            "subcategory":"Durable Goods & Equipment",
            "type":"Manufacturing & Wholesale Goods"
        },
        {
            "category":"Wholesale",
            "subcategory":"Electrical",
            "type":"Manufacturing & Wholesale Goods"
        }
    ],
    "sg:phone":"+1 972 871 0104",
    "sg:postcode":"75062",
    "sg:province":"TX",
    "sg:tags":[
        "product",
        "wire",
        "for",
        "cable",
        "mfg",
        "representative",
        "manufacturer"
    ],
    "wof:name":"Power Tech Electrical Sales",
    "wof:placetype":"venue"
},
  "geometry": {"coordinates":[-96.947272,32.864596],"type":"Point"}
}