{
  "type": "Feature",
  "properties": {
    "iso:country":"US",
    "sg:address":"220 Foremost Dr",
    "sg:city":"Austin",
    "sg:classifiers":[
        {
            "category":"Organizations",
            "subcategory":"Religious Organization",
            "type":"Services"
        }
    ],
    "sg:phone":"+1 512 282 0604",
    "sg:postcode":"78745",
    "sg:province":"TX",
    "sg:website":"www.churchinaustin.com",
    "wof:name":"Church In Austin",
    "wof:placetype":"venue"
},
  "geometry": {"coordinates":[-97.779751,30.179239],"type":"Point"}
}