{
  "type": "Feature",
  "properties": {
    "iso:country":"US",
    "sg:address":"6301 Glenhollow Ct",
    "sg:city":"Dallas",
    "sg:classifiers":[
        {
            "category":"Building & Trades",
            "subcategory":"Pest Control",
            "type":"Services"
        }
    ],
    "sg:phone":"+1 972 248 3373",
    "sg:postcode":"75248",
    "sg:province":"TX",
    "wof:name":"Texas Mosquito Control",
    "wof:placetype":"venue"
},
  "geometry": {"coordinates":[-96.79879800000001,32.973801],"type":"Point"}
}