{
  "type": "Feature",
  "properties": {
    "iso:country":"US",
    "sg:address":"1506 Lubbock Rd",
    "sg:city":"Brownfield",
    "sg:classifiers":[
        {
            "category":"Banks & Credit Unions",
            "subcategory":"Financial Services",
            "type":"Services"
        }
    ],
    "sg:phone":"+1 806 637 3557",
    "sg:postcode":"79316",
    "sg:province":"TX",
    "sg:tags":[
        "company",
        "holding"
    ],
    "wof:name":"Hphp Inc",
    "wof:placetype":"venue"
},
  "geometry": {"coordinates":[-102.273984,33.195586],"type":"Point"}
}