{
  "type": "Feature",
  "properties": {
    "iso:country":"US",
    "sg:address":"670 Washington Blvd",
    "sg:city":"Beaumont",
    "sg:classifiers":[
        {
            "category":"Food & Beverages",
            "subcategory":"Groceries & Convenience Stores",
            "type":"Retail Goods"
        }
    ],
    "sg:phone":"+1 409 838 6184",
    "sg:postcode":"77705",
    "sg:province":"TX",
    "wof:name":"P & J Food Store",
    "wof:placetype":"venue"
},
  "geometry": {"coordinates":[-94.088487,30.058336],"type":"Point"}
}