{
  "type": "Feature",
  "properties": {
    "iso:country":"US",
    "sg:address":"4118 Northvale Dr",
    "sg:city":"Houston",
    "sg:classifiers":[
        {
            "category":"Professional",
            "type":"Services"
        }
    ],
    "sg:phone":"+1 281 895 0551",
    "sg:postcode":"77014",
    "sg:province":"TX",
    "wof:name":"Safe Place Youth Center",
    "wof:placetype":"venue"
},
  "geometry": {"coordinates":[-95.483864,29.983967],"type":"Point"}
}