{
  "type": "Feature",
  "properties": {
    "iso:country":"US",
    "sg:address":"2116 56th St",
    "sg:city":"Lubbock",
    "sg:classifiers":[
        {
            "category":"Local Transit",
            "type":"Transportation"
        }
    ],
    "sg:phone":"+1 806 741 0190",
    "sg:postcode":"79412",
    "sg:province":"TX",
    "sg:tags":[
        "public"
    ],
    "wof:name":"NTS Transportation Service",
    "wof:placetype":"venue"
},
  "geometry": {"coordinates":[-101.863499,33.543376],"type":"Point"}
}