{
  "type": "Feature",
  "properties": {
    "iso:country":"US",
    "sg:address":"424 E Main St",
    "sg:city":"Lewisville",
    "sg:classifiers":[
        {
            "category":"Shopping",
            "subcategory":"Used Merchandise",
            "type":"Retail Goods"
        },
        {
            "category":"Retail",
            "subcategory":"Repair Shop",
            "type":"Services"
        }
    ],
    "sg:phone":"+1 972 221 1908",
    "sg:postcode":"75057",
    "sg:province":"TX",
    "sg:tags":[
        "refinishing",
        "furniture"
    ],
    "wof:name":"Accent Antiques & Refinishing",
    "wof:placetype":"venue"
},
  "geometry": {"coordinates":[-96.99013600000001,33.046254],"type":"Point"}
}