{
  "type": "Feature",
  "properties": {
    "iso:country":"US",
    "sg:address":"550 Westcott St",
    "sg:city":"Houston",
    "sg:classifiers":[
        {
            "category":"Real Estate",
            "subcategory":"Real Estate Operator",
            "type":"Services"
        }
    ],
    "sg:phone":"+1 713 880 1818",
    "sg:postcode":"77007",
    "sg:province":"TX",
    "sg:tags":[
        "building",
        "automobile",
        "nonresidential",
        "parking"
    ],
    "wof:name":"Westcott Central Office Bldg",
    "wof:placetype":"venue"
},
  "geometry": {"coordinates":[-95.42167999999999,29.766982],"type":"Point"}
}