{
  "type": "Feature",
  "properties": {
    "iso:country":"US",
    "sg:address":"10770 Barely Ln",
    "sg:city":"Houston",
    "sg:classifiers":[
        {
            "category":"Personal",
            "type":"Services"
        }
    ],
    "sg:phone":"+1 281 477 0143",
    "sg:postcode":"77070",
    "sg:province":"TX",
    "sg:tags":[
        "credit",
        "debt",
        "counseling"
    ],
    "wof:name":"Clearlake Credit Svc",
    "wof:placetype":"venue"
},
  "geometry": {"coordinates":[-95.583975,29.940523],"type":"Point"}
}