{
  "type": "Feature",
  "properties": {
    "iso:country":"US",
    "sg:address":"12211 Waldemar Dr",
    "sg:city":"Houston",
    "sg:classifiers":[
        {
            "category":"Professional",
            "subcategory":"Art Services",
            "type":"Services"
        }
    ],
    "sg:phone":"+1 281 531 0260",
    "sg:postcode":"77077",
    "sg:province":"TX",
    "sg:tags":[
        "photography",
        "commercial"
    ],
    "wof:name":"Gary Fountain Photography",
    "wof:placetype":"venue"
},
  "geometry": {"coordinates":[-95.597948,29.744873],"type":"Point"}
}