{
  "type": "Feature",
  "properties": {
    "iso:country":"US",
    "sg:address":"417 S 11th St",
    "sg:city":"Abilene",
    "sg:classifiers":[
        {
            "category":"Building & Trades",
            "subcategory":"Construction",
            "type":"Services"
        }
    ],
    "sg:phone":"+1 325 676 5627",
    "sg:postcode":"79602",
    "sg:province":"TX",
    "sg:tags":[
        "painter"
    ],
    "wof:name":"Ross Painting Co",
    "wof:placetype":"venue"
},
  "geometry": {"coordinates":[-99.728463,32.43695],"type":"Point"}
}