{
  "type": "Feature",
  "properties": {
    "iso:country":"US",
    "sg:address":"3207 State Hwy 43 E",
    "sg:city":"Henderson",
    "sg:classifiers":[
        {
            "category":"Building & Trades",
            "subcategory":"Construction",
            "type":"Services"
        }
    ],
    "sg:phone":"+1 903 657 4688",
    "sg:postcode":"75652",
    "sg:province":"TX",
    "sg:tags":[
        "housing"
    ],
    "wof:name":"Custom One Construction",
    "wof:placetype":"venue"
},
  "geometry": {"coordinates":[-94.737612,32.201625],"type":"Point"}
}