{
  "type": "Feature",
  "properties": {
    "iso:country":"US",
    "sg:address":"4601 S Loop 289",
    "sg:city":"Lubbock",
    "sg:classifiers":[
        {
            "category":"Health Services",
            "subcategory":"Doctor",
            "type":"Services"
        }
    ],
    "sg:phone":"+1 806 792 7200",
    "sg:postcode":"79424",
    "sg:province":"TX",
    "sg:tags":[
        "medical"
    ],
    "wof:name":"Ico Robert",
    "wof:placetype":"venue"
},
  "geometry": {"coordinates":[-101.913332,33.532339],"type":"Point"}
}