{
  "type": "Feature",
  "properties": {
    "iso:country":"US",
    "sg:address":"100 Independence Pl",
    "sg:city":"Tyler",
    "sg:classifiers":[
        {
            "category":"Professional",
            "subcategory":"Management & Consulting",
            "type":"Services"
        }
    ],
    "sg:phone":"+1 903 561 6811",
    "sg:postcode":"75703",
    "sg:province":"TX",
    "wof:name":"Managed By Simons D Real Esta",
    "wof:placetype":"venue"
},
  "geometry": {"coordinates":[-95.30074399999999,32.298825],"type":"Point"}
}