{
  "type": "Feature",
  "properties": {
    "iso:country":"US",
    "sg:address":"1317 Wood St",
    "sg:city":"Big Spring",
    "sg:classifiers":[
        {
            "category":"Building & Trades",
            "subcategory":"Construction",
            "type":"Services"
        }
    ],
    "sg:phone":"+1 432 267 5714",
    "sg:postcode":"79720",
    "sg:province":"TX",
    "sg:tags":[
        "concrete",
        "contractor"
    ],
    "wof:name":"Marquez Fence Co",
    "wof:placetype":"venue"
},
  "geometry": {"coordinates":[-101.45712899999999,32.249043],"type":"Point"}
}