{
  "type": "Feature",
  "properties": {
    "iso:country":"US",
    "sg:address":"1422 Main St",
    "sg:city":"Southlake",
    "sg:classifiers":[
        {
            "category":"Health Services",
            "subcategory":"Doctor",
            "type":"Services"
        }
    ],
    "sg:phone":"+1 817 416 9980",
    "sg:postcode":"76092",
    "sg:province":"TX",
    "sg:tags":[
        "physician",
        "reconstructive",
        "surgeons",
        "cosmetic",
        "plastic",
        "surgery",
        "surgeon"
    ],
    "sg:website":"http://www.drkasden.us",
    "wof:name":"Scott E. Kasden M.D.",
    "wof:placetype":"venue"
},
  "geometry": {"coordinates":[-97.13017000000001,32.94257],"type":"Point"}
}