{
  "type": "Feature",
  "properties": {
    "iso:country":"US",
    "sg:address":"2606 E Houston St",
    "sg:city":"San Antonio",
    "sg:classifiers":[
        {
            "category":"Health Services",
            "subcategory":"Doctor",
            "type":"Services"
        }
    ],
    "sg:phone":"+1 210 227 0962",
    "sg:postcode":"78202",
    "sg:province":"TX",
    "sg:tags":[
        "dentist"
    ],
    "wof:name":"Eastside Christian Dental Clnc",
    "wof:placetype":"venue"
},
  "geometry": {"coordinates":[-98.45003800000001,29.42501],"type":"Point"}
}