{
  "type": "Feature",
  "properties": {
    "iso:country":"US",
    "sg:address":"2701 Bellefontaine St",
    "sg:city":"Houston",
    "sg:classifiers":[
        {
            "category":"Social Services",
            "subcategory":"Child Care",
            "type":"Services"
        }
    ],
    "sg:phone":"+1 713 663 7557",
    "sg:postcode":"77025",
    "sg:province":"TX",
    "wof:name":"Van Nguyen Tran",
    "wof:placetype":"venue"
},
  "geometry": {"coordinates":[-95.421549,29.702969],"type":"Point"}
}