{
  "type": "Feature",
  "properties": {
    "iso:country":"US",
    "sg:address":"4008 Tulane Dr",
    "sg:city":"Amarillo",
    "sg:classifiers":[
        {
            "category":"Health Services",
            "subcategory":"Clinic",
            "type":"Services"
        }
    ],
    "sg:phone":"+1 806 358 9984",
    "sg:postcode":"79109",
    "sg:province":"TX",
    "sg:tags":[
        "home",
        "care"
    ],
    "wof:name":"Tulane Group Home",
    "wof:placetype":"venue"
},
  "geometry": {"coordinates":[-101.881987,35.165909],"type":"Point"}
}