{
  "type": "Feature",
  "properties": {
    "iso:country":"US",
    "sg:address":"6101 Honeytree Dr",
    "sg:city":"Arlington",
    "sg:classifiers":[
        {
            "category":"Professional",
            "subcategory":"Business Services",
            "type":"Services"
        }
    ],
    "sg:phone":"+1 817 457 9350",
    "sg:postcode":"76016",
    "sg:province":"TX",
    "wof:name":"Arcadia Enterprises",
    "wof:placetype":"venue"
},
  "geometry": {"coordinates":[-97.201854,32.6926],"type":"Point"}
}