{
  "type": "Feature",
  "properties": {
    "iso:country":"US",
    "sg:address":"5002 US Hwy 277 S",
    "sg:city":"Abilene",
    "sg:classifiers":[
        {
            "category":"Insurance",
            "subcategory":"Insurance Agent",
            "type":"Services"
        }
    ],
    "sg:phone":"+1 325 698 4916",
    "sg:postcode":"79605",
    "sg:province":"TX",
    "wof:name":"Bailey Group",
    "wof:placetype":"venue"
},
  "geometry": {"coordinates":[-99.78711699999999,32.425654],"type":"Point"}
}