{
  "type": "Feature",
  "properties": {
    "iso:country":"US",
    "sg:address":"9700 Richmond Ave",
    "sg:city":"Houston",
    "sg:classifiers":[
        {
            "category":"Professional",
            "subcategory":"Accounting & Tax Preparation",
            "type":"Services"
        }
    ],
    "sg:phone":"+1 832 419 7576",
    "sg:postcode":"77042",
    "sg:province":"TX",
    "sg:tags":[
        "accountant",
        "public",
        "certified"
    ],
    "wof:name":"Pathak Devesh",
    "wof:placetype":"venue"
},
  "geometry": {"coordinates":[-95.54045000000001,29.727681],"type":"Point"}
}