{
  "type": "Feature",
  "properties": {
    "iso:country":"US",
    "sg:address":"210 S Adams St",
    "sg:city":"Fredericksburg",
    "sg:classifiers":[
        {
            "category":"Shopping",
            "subcategory":"Gifts & Souvenirs",
            "type":"Retail Goods"
        }
    ],
    "sg:phone":"+1 830 997 9527",
    "sg:postcode":"78624",
    "sg:province":"TX",
    "sg:tags":[
        "apparel",
        "pet",
        "supply"
    ],
    "wof:name":"Peachworks LLC",
    "wof:placetype":"venue"
},
  "geometry": {"coordinates":[-98.873458,30.273947],"type":"Point"}
}