{
  "type": "Feature",
  "properties": {
    "iso:country":"US",
    "sg:address":"2525 W Anderson Ln",
    "sg:city":"Austin",
    "sg:classifiers":[
        {
            "category":"Real Estate",
            "subcategory":"Real Estate Services",
            "type":"Services"
        },
        {
            "category":"Insurance",
            "subcategory":"Title Insurance",
            "type":"Services"
        },
        {
            "category":"Banks & Credit Unions",
            "subcategory":"Financial Services",
            "type":"Services"
        }
    ],
    "sg:phone":"+1 512 401 8541",
    "sg:postcode":"78757",
    "sg:province":"TX",
    "sg:tags":[
        "escrow"
    ],
    "wof:name":"Towne & Country Title",
    "wof:placetype":"venue"
},
  "geometry": {"coordinates":[-97.73378,30.357481],"type":"Point"}
}