{
  "type": "Feature",
  "properties": {
    "iso:country":"US",
    "sg:address":"5501 N Lamar Boulevard",
    "sg:city":"Austin",
    "sg:classifiers":[
        {
            "category":"Real Estate",
            "subcategory":"Real Estate Services",
            "type":"Services"
        },
        {
            "category":"Banks & Credit Unions",
            "subcategory":"Financial Services",
            "type":"Services"
        }
    ],
    "sg:phone":"+1 512 494 0424",
    "sg:postcode":"78751",
    "sg:province":"TX",
    "sg:tags":[
        "financing",
        "loan",
        "mortgage",
        "broker"
    ],
    "sg:website":"http://www.alliedmtgcapital.com",
    "wof:name":"Allied Mortgage Capital Corporation-Branch",
    "wof:placetype":"venue"
},
  "geometry": {"coordinates":[-97.72834899999999,30.322918],"type":"Point"}
}