{
  "type": "Feature",
  "properties": {
    "iso:country":"US",
    "sg:address":"10603 Prospect Hill Dr",
    "sg:city":"Houston",
    "sg:classifiers":[
        {
            "category":"Shopping",
            "subcategory":"Clothing, Apparel, & Fashions",
            "type":"Retail Goods"
        }
    ],
    "sg:phone":"+1 281 970 4388",
    "sg:postcode":"77064",
    "sg:province":"TX",
    "wof:name":"Rae Rae",
    "wof:placetype":"venue"
},
  "geometry": {"coordinates":[-95.57670899999999,29.914911],"type":"Point"}
}