{
  "type": "Feature",
  "properties": {
    "iso:country":"US",
    "sg:address":"15888 Champion Forest Dr",
    "sg:city":"Spring",
    "sg:classifiers":[
        {
            "category":"Autos & Motor Vehicles",
            "subcategory":"Auto Supplies",
            "type":"Retail Goods"
        }
    ],
    "sg:phone":"+1 281 251 2183",
    "sg:postcode":"77379",
    "sg:province":"TX",
    "sg:tags":[
        "tire"
    ],
    "wof:name":"Goodyear Auto Svc Ctr",
    "wof:placetype":"venue"
},
  "geometry": {"coordinates":[-95.53361,30.005212],"type":"Point"}
}