{
  "type": "Feature",
  "properties": {
    "iso:country":"US",
    "sg:address":"4800 E 42nd St",
    "sg:city":"Odessa",
    "sg:classifiers":[
        {
            "category":"Professional",
            "subcategory":"Advertising",
            "type":"Services"
        }
    ],
    "sg:phone":"+1 432 550 7339",
    "sg:postcode":"79762",
    "sg:province":"TX",
    "sg:tags":[
        "counselor"
    ],
    "wof:name":"Hunt Advertising",
    "wof:placetype":"venue"
},
  "geometry": {"coordinates":[-102.334064,31.893496],"type":"Point"}
}