{
  "type": "Feature",
  "properties": {
    "iso:country":"US",
    "sg:address":"6400 Fannin St Ste 2290",
    "sg:city":"Houston",
    "sg:classifiers":[
        {
            "category":"Health Services",
            "subcategory":"Doctor",
            "type":"Services"
        }
    ],
    "sg:phone":"+1 713 795 5155",
    "sg:postcode":"77030",
    "sg:province":"TX",
    "wof:name":"Lung & Asthma Clinic",
    "wof:placetype":"venue"
},
  "geometry": {"coordinates":[-95.39664500000001,29.715423],"type":"Point"}
}