{
  "type": "Feature",
  "properties": {
    "iso:country":"US",
    "sg:address":"1600 Smith St Ste 3895",
    "sg:city":"Houston",
    "sg:classifiers":[
        {
            "category":"Banks & Credit Unions",
            "subcategory":"Bank",
            "type":"Services"
        }
    ],
    "sg:phone":"+1 713 750 0575",
    "sg:postcode":"77002",
    "sg:province":"TX",
    "wof:name":"Chevron Credit Union",
    "wof:placetype":"venue"
},
  "geometry": {"coordinates":[-95.372069,29.754607],"type":"Point"}
}