{
  "type": "Feature",
  "properties": {
    "iso:country":"US",
    "sg:address":"2540 King Arthur Blvd",
    "sg:city":"Lewisville",
    "sg:classifiers":[
        {
            "category":"Shopping",
            "subcategory":"Party Supplies",
            "type":"Retail Goods"
        },
        {
            "category":"Shopping",
            "subcategory":"Gifts & Souvenirs",
            "type":"Retail Goods"
        },
        {
            "category":"Personal",
            "type":"Services"
        },
        {
            "category":"Shopping",
            "subcategory":"Florist",
            "type":"Retail Goods"
        }
    ],
    "sg:phone":"+1 469 549 1404",
    "sg:postcode":"75056",
    "sg:province":"TX",
    "sg:tags":[
        "shop",
        "delivery",
        "balloon",
        "balloons-retail",
        "decorator"
    ],
    "sg:website":"http://www.celebrateitballoons.com",
    "wof:name":"Celebrate It! Balloons & Gifts",
    "wof:placetype":"venue"
},
  "geometry": {"coordinates":[-96.899066,33.035242],"type":"Point"}
}