{
  "type": "Feature",
  "properties": {
    "iso:country":"US",
    "sg:address":"9522 Lexham Dr",
    "sg:city":"Houston",
    "sg:classifiers":[
        {
            "category":"Professional",
            "subcategory":"Business Services",
            "type":"Services"
        }
    ],
    "sg:phone":"+1 281 561 6910",
    "sg:postcode":"77083",
    "sg:province":"TX",
    "wof:name":"Humera Khan",
    "wof:placetype":"venue"
},
  "geometry": {"coordinates":[-95.639573,29.675218],"type":"Point"}
}