{
  "type": "Feature",
  "properties": {
    "iso:country":"US",
    "sg:address":"6902 State Highway 70",
    "sg:city":"Sweetwater",
    "sg:classifiers":[
        {
            "category":"Building & Trades",
            "subcategory":"Construction",
            "type":"Services"
        }
    ],
    "sg:phone":"+1 325 236 9217",
    "sg:postcode":"79556",
    "sg:province":"TX",
    "sg:tags":[
        "consultant",
        "management"
    ],
    "wof:name":"Sweetwater Wind 2",
    "wof:placetype":"venue"
},
  "geometry": {"coordinates":[-100.352064,32.344625],"type":"Point"}
}