{
  "type": "Feature",
  "properties": {
    "iso:country":"US",
    "sg:address":"450 N Sam Houston Pkwy E",
    "sg:city":"Houston",
    "sg:classifiers":[
        {
            "category":"Professional",
            "subcategory":"Computer Services",
            "type":"Services"
        }
    ],
    "sg:phone":"+1 281 931 5202",
    "sg:postcode":"77060",
    "sg:province":"TX",
    "sg:tags":[
        "repair"
    ],
    "wof:name":"Custom Business Solutions",
    "wof:placetype":"venue"
},
  "geometry": {"coordinates":[-95.395302,29.938499],"type":"Point"}
}