{
  "type": "Feature",
  "properties": {
    "iso:country":"US",
    "sg:address":"11508 FM 2860",
    "sg:city":"Kaufman",
    "sg:classifiers":[
        {
            "category":"Shopping",
            "subcategory":"Hobbies, Toys, & Games",
            "type":"Retail Goods"
        }
    ],
    "sg:phone":"+1 972 932 6786",
    "sg:postcode":"75142",
    "sg:province":"TX",
    "sg:tags":[
        "equipment",
        "ceramic",
        "supply"
    ],
    "wof:name":"Gail Marven Ceramics",
    "wof:placetype":"venue"
},
  "geometry": {"coordinates":[-96.278802,32.494469],"type":"Point"}
}