{
  "type": "Feature",
  "properties": {
    "iso:country":"US",
    "sg:address":"2250 Jackson Cir",
    "sg:city":"Carrollton",
    "sg:classifiers":[
        {
            "category":"Professional",
            "subcategory":"Accounting & Tax Preparation",
            "type":"Services"
        }
    ],
    "sg:phone":"+1 972 245 9700",
    "sg:postcode":"75006",
    "sg:province":"TX",
    "sg:tags":[
        "return",
        "filing"
    ],
    "wof:name":"Affordable Tax Svc",
    "wof:placetype":"venue"
},
  "geometry": {"coordinates":[-96.895456,32.975776],"type":"Point"}
}