{
  "type": "Feature",
  "properties": {
    "iso:country":"US",
    "sg:address":"21227 Park Run Dr",
    "sg:city":"Katy",
    "sg:classifiers":[
        {
            "category":"Professional",
            "type":"Services"
        }
    ],
    "sg:phone":"+1 281 578 6871",
    "sg:postcode":"77450",
    "sg:province":"TX",
    "wof:name":"Zhaoling Y LI Co",
    "wof:placetype":"venue"
},
  "geometry": {"coordinates":[-95.735411,29.760328],"type":"Point"}
}