{
  "type": "Feature",
  "properties": {
    "iso:country":"US",
    "sg:address":"2505 Texas Dr",
    "sg:city":"Irving",
    "sg:classifiers":[
        {
            "category":"Real Estate",
            "subcategory":"Surveying",
            "type":"Services"
        }
    ],
    "sg:phone":"+1 972 255 1501",
    "sg:postcode":"75062",
    "sg:province":"TX",
    "sg:tags":[
        "surveyor"
    ],
    "wof:name":"Dewey & Assoc",
    "wof:placetype":"venue"
},
  "geometry": {"coordinates":[-96.97113899999999,32.837711],"type":"Point"}
}