{
  "type": "Feature",
  "properties": {
    "iso:country":"US",
    "sg:address":"2500 W Loop Fwy",
    "sg:city":"Houston",
    "sg:classifiers":[
        {
            "category":"Banks & Credit Unions",
            "subcategory":"Bank",
            "type":"Services"
        }
    ],
    "sg:phone":"+1 713 355 1808",
    "sg:postcode":"77027",
    "sg:province":"TX",
    "sg:tags":[
        "depository",
        "banking",
        "escrow"
    ],
    "wof:name":"Commercial Escrow Company",
    "wof:placetype":"venue"
},
  "geometry": {"coordinates":[-95.457286,29.746351],"type":"Point"}
}