{
  "type": "Feature",
  "properties": {
    "iso:country":"US",
    "sg:address":"444 E Mansfield Hwy",
    "sg:city":"Kennedale",
    "sg:phone":"+1 817 249 6333",
    "sg:postcode":"76060",
    "sg:province":"TX",
    "sg:tags":[
        "equipment",
        "station"
    ],
    "wof:name":"W Two Plus Inc",
    "wof:placetype":"venue"
},
  "geometry": {"coordinates":[-97.21658600000001,32.642012],"type":"Point"}
}