{
  "type": "Feature",
  "properties": {
    "iso:country":"US",
    "sg:address":"1234 S Broadway St",
    "sg:city":"Sulphur Springs",
    "sg:classifiers":[
        {
            "category":"Restaurant",
            "type":"Food & Drink"
        }
    ],
    "sg:phone":"+1 903 885 7922",
    "sg:postcode":"75482",
    "sg:province":"TX",
    "wof:name":"A & W Family Restaurant",
    "wof:placetype":"venue"
},
  "geometry": {"coordinates":[-95.59625,33.11803],"type":"Point"}
}