{
  "type": "Feature",
  "properties": {
    "iso:country":"US",
    "sg:address":"6214 Lacoste Love Ct",
    "sg:city":"Spring",
    "sg:classifiers":[
        {
            "category":"Banks & Credit Unions",
            "subcategory":"Investment Brokerage",
            "type":"Services"
        }
    ],
    "sg:phone":"+1 281 251 3638",
    "sg:postcode":"77379",
    "sg:province":"TX",
    "sg:tags":[
        "security"
    ],
    "wof:name":"Steel Family Partnership",
    "wof:placetype":"venue"
},
  "geometry": {"coordinates":[-95.50493400000001,30.019371],"type":"Point"}
}