{
  "type": "Feature",
  "properties": {
    "iso:country":"US",
    "sg:address":"21831 Fm 359 Rd",
    "sg:city":"Hempstead",
    "sg:classifiers":[
        {
            "category":"Shopping",
            "subcategory":"Jewelry",
            "type":"Retail Goods"
        }
    ],
    "sg:phone":"+1 979 826 8571",
    "sg:postcode":"77445",
    "sg:province":"TX",
    "sg:tags":[
        "precious",
        "semi-precious",
        "stone"
    ],
    "wof:name":"Tudi Of Houston",
    "wof:placetype":"venue"
},
  "geometry": {"coordinates":[-96.04335,30.08952],"type":"Point"}
}