{
  "type": "Feature",
  "properties": {
    "iso:country":"US",
    "sg:address":"6106 Royal Breeze",
    "sg:city":"San Antonio",
    "sg:classifiers":[
        {
            "category":"Shopping",
            "type":"Retail Goods"
        }
    ],
    "sg:phone":"+1 210 653 4971",
    "sg:postcode":"78239",
    "sg:province":"TX",
    "sg:tags":[
        "merchandise"
    ],
    "wof:name":"Buddy Davidson",
    "wof:placetype":"venue"
},
  "geometry": {"coordinates":[-98.365883,29.5353],"type":"Point"}
}