{
  "type": "Feature",
  "properties": {
    "iso:country":"US",
    "sg:address":"606 N McColl Rd",
    "sg:city":"Mcallen",
    "sg:classifiers":[
        {
            "category":"Organizations",
            "subcategory":"Non-profit Organization",
            "type":"Services"
        }
    ],
    "sg:phone":"+1 956 683 7678",
    "sg:postcode":"78501",
    "sg:province":"TX",
    "wof:name":"Medication Assistance Prgm",
    "wof:placetype":"venue"
},
  "geometry": {"coordinates":[-98.211476,26.208483],"type":"Point"}
}