{
  "type": "Feature",
  "properties": {
    "iso:country":"US",
    "sg:address":"4920 Canberra Ln",
    "sg:city":"Arlington",
    "sg:classifiers":[
        {
            "category":"Restaurant",
            "type":"Food & Drink"
        }
    ],
    "sg:phone":"+1 817 516 8561",
    "sg:postcode":"76017",
    "sg:province":"TX",
    "sg:tags":[
        "eating"
    ],
    "wof:name":"Tweeds Personal Chef Service",
    "wof:placetype":"venue"
},
  "geometry": {"coordinates":[-97.198662,32.666332],"type":"Point"}
}