{
  "type": "Feature",
  "properties": {
    "iso:country":"US",
    "sg:address":"4309 N 10th St",
    "sg:city":"Mcallen",
    "sg:classifiers":[
        {
            "category":"Health Services",
            "subcategory":"Doctor",
            "type":"Services"
        }
    ],
    "sg:phone":"+1 956 992 8815",
    "sg:postcode":"78504",
    "sg:province":"TX",
    "sg:tags":[
        "physician",
        "surgeon"
    ],
    "wof:name":"Doctors On Call",
    "wof:placetype":"venue"
},
  "geometry": {"coordinates":[-98.223485,26.241934],"type":"Point"}
}