{
  "type": "Feature",
  "properties": {
    "iso:country":"US",
    "sg:address":"4930 Belt Line Rd",
    "sg:city":"Dallas",
    "sg:classifiers":[
        {
            "category":"Personal",
            "subcategory":"Beauty Salon",
            "type":"Services"
        }
    ],
    "sg:phone":"+1 972 308 8438",
    "sg:postcode":"75254",
    "sg:province":"TX",
    "sg:tags":[
        "shop"
    ],
    "wof:name":"Image Hair Studio",
    "wof:placetype":"venue"
},
  "geometry": {"coordinates":[-96.82520599999999,32.953947],"type":"Point"}
}