{
  "type": "Feature",
  "properties": {
    "iso:country":"US",
    "sg:address":"225 Oak Creek Cir",
    "sg:city":"Mc Gregor",
    "sg:classifiers":[
        {
            "category":"Professional",
            "type":"Services"
        }
    ],
    "sg:phone":"+1 254 848 5486",
    "sg:postcode":"76657",
    "sg:province":"TX",
    "wof:name":"Brisco Darlins",
    "wof:placetype":"venue"
},
  "geometry": {"coordinates":[-97.313625,31.474659],"type":"Point"}
}