{
  "type": "Feature",
  "properties": {
    "iso:country":"US",
    "sg:address":"3705 Trice Ave",
    "sg:city":"Waco",
    "sg:classifiers":[
        {
            "category":"Shopping",
            "subcategory":"Books",
            "type":"Retail Goods"
        }
    ],
    "sg:phone":"+1 254 754 0962",
    "sg:postcode":"76707",
    "sg:province":"TX",
    "wof:name":"Gladys Book Store",
    "wof:placetype":"venue"
},
  "geometry": {"coordinates":[-97.18119,31.547266],"type":"Point"}
}