{
  "type": "Feature",
  "properties": {
    "iso:country":"US",
    "sg:address":"7827 Olusta Dr",
    "sg:city":"Dallas",
    "sg:classifiers":[
        {
            "category":"Organizations",
            "subcategory":"Religious Organization",
            "type":"Services"
        }
    ],
    "sg:phone":"+1 214 391 2057",
    "sg:postcode":"75217",
    "sg:province":"TX",
    "wof:name":"Jesus H Sias",
    "wof:placetype":"venue"
},
  "geometry": {"coordinates":[-96.687423,32.711146],"type":"Point"}
}