{
  "type": "Feature",
  "properties": {
    "iso:country":"US",
    "sg:address":"1125 Terrace Trl",
    "sg:city":"Hurst",
    "sg:classifiers":[
        {
            "category":"Shopping",
            "subcategory":"Used Merchandise",
            "type":"Retail Goods"
        }
    ],
    "sg:phone":"+1 817 282 1093",
    "sg:postcode":"76053",
    "sg:province":"TX",
    "wof:name":"Kathleens Collections",
    "wof:placetype":"venue"
},
  "geometry": {"coordinates":[-97.181603,32.829931],"type":"Point"}
}