{
  "type": "Feature",
  "properties": {
    "iso:country":"US",
    "sg:address":"215 Emberson Chapel Rd",
    "sg:city":"Pilot Point",
    "sg:classifiers":[
        {
            "category":"Home & Garden",
            "subcategory":"Furniture",
            "type":"Retail Goods"
        }
    ],
    "sg:phone":"+1 940 686 5820",
    "sg:postcode":"76258",
    "sg:province":"TX",
    "sg:tags":[
        "cabinet"
    ],
    "wof:name":"Danny & Sons",
    "wof:placetype":"venue"
},
  "geometry": {"coordinates":[-96.91985099999999,33.437601],"type":"Point"}
}