{
  "type": "Feature",
  "properties": {
    "iso:country":"US",
    "sg:address":"10463 Royal Andrews Dr",
    "sg:city":"Conroe",
    "sg:classifiers":[
        {
            "category":"Real Estate",
            "subcategory":"Real Estate Agent",
            "type":"Services"
        }
    ],
    "sg:phone":"+1 936 890 2925",
    "sg:postcode":"77303",
    "sg:province":"TX",
    "sg:tags":[
        "inspection"
    ],
    "wof:name":"Texas Professional Inspections",
    "wof:placetype":"venue"
},
  "geometry": {"coordinates":[-95.409059,30.421018],"type":"Point"}
}