{
  "type": "Feature",
  "properties": {
    "iso:country":"US",
    "sg:address":"2211 Richmond Ave",
    "sg:city":"Houston",
    "sg:classifiers":[
        {
            "category":"Professional",
            "subcategory":"Management & Consulting",
            "type":"Services"
        },
        {
            "category":"Social Services",
            "type":"Services"
        }
    ],
    "sg:phone":"+1 713 526 4666",
    "sg:postcode":"77098",
    "sg:province":"TX",
    "sg:tags":[
        "stress"
    ],
    "wof:name":"Escape 3",
    "wof:placetype":"venue"
},
  "geometry": {"coordinates":[-95.414897,29.734112],"type":"Point"}
}