{
  "type": "Feature",
  "properties": {
    "iso:country":"US",
    "sg:address":"6513 Wildwood Dr",
    "sg:city":"Mc Kinney",
    "sg:classifiers":[
        {
            "category":"Wholesale",
            "subcategory":"Furniture",
            "type":"Manufacturing & Wholesale Goods"
        }
    ],
    "sg:phone":"+1 972 562 4418",
    "sg:postcode":"75070",
    "sg:province":"TX",
    "wof:name":"Don White & Associates",
    "wof:placetype":"venue"
},
  "geometry": {"coordinates":[-96.70217100000001,33.189003],"type":"Point"}
}