{
  "type": "Feature",
  "properties": {
    "iso:country":"US",
    "sg:address":"2909 Cole Ave",
    "sg:city":"Dallas",
    "sg:classifiers":[
        {
            "category":"Professional",
            "subcategory":"Management & Consulting",
            "type":"Services"
        }
    ],
    "sg:phone":"+1 214 880 1717",
    "sg:postcode":"75204",
    "sg:province":"TX",
    "sg:tags":[
        "marketing",
        "consultant"
    ],
    "wof:name":"Mc Donald Marketing",
    "wof:placetype":"venue"
},
  "geometry": {"coordinates":[-96.802173,32.80238],"type":"Point"}
}