{
  "type": "Feature",
  "properties": {
    "iso:country":"US",
    "sg:address":"105 Oakwood St",
    "sg:city":"Sonora",
    "sg:classifiers":[
        {
            "category":"Organizations",
            "subcategory":"Religious Organization",
            "type":"Services"
        }
    ],
    "sg:phone":"+1 325 387 5190",
    "sg:postcode":"76950",
    "sg:province":"TX",
    "wof:name":"St Anns Parish Hall",
    "wof:placetype":"venue"
},
  "geometry": {"coordinates":[-100.63260699999999,30.563896],"type":"Point"}
}