{
  "type": "Feature",
  "properties": {
    "iso:country":"US",
    "sg:address":"821 Gunter St",
    "sg:city":"Austin",
    "sg:classifiers":[
        {
            "category":"Organizations",
            "subcategory":"Non-profit Organization",
            "type":"Services"
        },
        {
            "category":"Social Services",
            "type":"Services"
        }
    ],
    "sg:phone":"+1 512 385 5571",
    "sg:postcode":"78702",
    "sg:province":"TX",
    "sg:tags":[
        "human"
    ],
    "sg:website":"www.casamarianella.org",
    "wof:name":"Casa Marianella Inc",
    "wof:placetype":"venue"
},
  "geometry": {"coordinates":[-97.701626,30.258963],"type":"Point"}
}