{
  "type": "Feature",
  "properties": {
    "iso:country":"US",
    "sg:address":"3206 Mercer St",
    "sg:city":"Houston",
    "sg:classifiers":[
        {
            "category":"Personal",
            "subcategory":"Beauty Salon",
            "type":"Services"
        }
    ],
    "sg:phone":"+1 713 621 1102",
    "sg:postcode":"77027",
    "sg:province":"TX",
    "sg:tags":[
        "shop"
    ],
    "wof:name":"Sebastien Gerletti Salon",
    "wof:placetype":"venue"
},
  "geometry": {"coordinates":[-95.43221699999999,29.737451],"type":"Point"}
}