{
  "type": "Feature",
  "properties": {
    "iso:country":"US",
    "sg:address":"1316 Rocky Creek Dr",
    "sg:city":"Pflugerville",
    "sg:classifiers":[
        {
            "category":"Social Services",
            "subcategory":"Child Care",
            "type":"Services"
        }
    ],
    "sg:phone":"+1 512 251 8952",
    "sg:postcode":"78660",
    "sg:province":"TX",
    "sg:tags":[
        "day"
    ],
    "wof:name":"Pappa Bears",
    "wof:placetype":"venue"
},
  "geometry": {"coordinates":[-97.614537,30.455673],"type":"Point"}
}