{
  "type": "Feature",
  "properties": {
    "iso:country":"US",
    "sg:address":"13100 Wild Turkey Dr",
    "sg:city":"Manchaca",
    "sg:classifiers":[
        {
            "category":"Professional",
            "type":"Services"
        }
    ],
    "sg:phone":"+1 512 385 5137",
    "sg:postcode":"78652",
    "sg:province":"TX",
    "wof:name":"Jean Sena",
    "wof:placetype":"venue"
},
  "geometry": {"coordinates":[-97.820851,30.117708],"type":"Point"}
}