{
  "type": "Feature",
  "properties": {
    "iso:country":"US",
    "sg:address":"5708 Marilyn Dr",
    "sg:city":"Austin",
    "sg:classifiers":[
        {
            "category":"Personal",
            "subcategory":"Beauty Salon",
            "type":"Services"
        }
    ],
    "sg:phone":"+1 512 302 1169",
    "sg:postcode":"78757",
    "sg:province":"TX",
    "sg:tags":[
        "shop"
    ],
    "wof:name":"Shannas",
    "wof:placetype":"venue"
},
  "geometry": {"coordinates":[-97.752718,30.338055],"type":"Point"}
}