{
  "type": "Feature",
  "properties": {
    "iso:country":"US",
    "sg:address":"9635 Millridge Dr",
    "sg:city":"Dallas",
    "sg:classifiers":[
        {
            "category":"Communications",
            "subcategory":"Film & Video Production",
            "type":"Services"
        }
    ],
    "sg:phone":"+1 214 349 2797",
    "sg:postcode":"75243",
    "sg:province":"TX",
    "sg:tags":[
        "post"
    ],
    "wof:name":"Newsvideo",
    "wof:placetype":"venue"
},
  "geometry": {"coordinates":[-96.72985199999999,32.904596],"type":"Point"}
}