{
  "type": "Feature",
  "properties": {
    "iso:country":"US",
    "sg:address":"2220 Aldine Mail Rd",
    "sg:city":"Houston",
    "sg:classifiers":[
        {
            "category":"Autos & Motor Vehicles",
            "subcategory":"Auto Supplies",
            "type":"Retail Goods"
        }
    ],
    "sg:phone":"+1 281 590 9334",
    "sg:postcode":"77039",
    "sg:province":"TX",
    "sg:tags":[
        "tire"
    ],
    "wof:name":"Aldine Tires",
    "wof:placetype":"venue"
},
  "geometry": {"coordinates":[-95.351161,29.902205],"type":"Point"}
}