{
  "type": "Feature",
  "properties": {
    "iso:country":"US",
    "sg:address":"3905 Holliday Rd",
    "sg:city":"Dallas",
    "sg:classifiers":[
        {
            "category":"Building & Trades",
            "subcategory":"Construction",
            "type":"Services"
        }
    ],
    "sg:phone":"+1 214 333 2770",
    "sg:postcode":"75224",
    "sg:province":"TX",
    "sg:tags":[
        "house",
        "contractor"
    ],
    "wof:name":"Lee Construction & Remodeling",
    "wof:placetype":"venue"
},
  "geometry": {"coordinates":[-96.85630500000001,32.695321],"type":"Point"}
}