{
  "type": "Feature",
  "properties": {
    "iso:country":"US",
    "sg:address":"921 Proton Rd",
    "sg:city":"San Antonio",
    "sg:classifiers":[
        {
            "category":"Professional",
            "subcategory":"Lawyer & Legal Services",
            "type":"Services"
        }
    ],
    "sg:phone":"+1 210 227 2726",
    "sg:postcode":"78258",
    "sg:province":"TX",
    "sg:tags":[
        "attorney"
    ],
    "wof:name":"R David Fritsche",
    "wof:placetype":"venue"
},
  "geometry": {"coordinates":[-98.479924,29.612214],"type":"Point"}
}