{
  "type": "Feature",
  "properties": {
    "iso:country":"US",
    "sg:address":"768 Lincoln Sq",
    "sg:city":"Arlington",
    "sg:classifiers":[
        {
            "category":"Education",
            "subcategory":"Vocational School",
            "type":"Public Place"
        }
    ],
    "sg:phone":"+1 817 226 1900",
    "sg:postcode":"76011",
    "sg:province":"TX",
    "sg:tags":[
        "training",
        "computer",
        "software"
    ],
    "wof:name":"CCI Training Center Inc",
    "wof:placetype":"venue"
},
  "geometry": {"coordinates":[-97.099694,32.756761],"type":"Point"}
}