{
  "type": "Feature",
  "properties": {
    "iso:country":"US",
    "sg:address":"472 County Road 4010",
    "sg:city":"Dayton",
    "sg:classifiers":[
        {
            "category":"Professional",
            "subcategory":"Art Services",
            "type":"Services"
        }
    ],
    "sg:phone":"+1 281 385 5408",
    "sg:postcode":"77535",
    "sg:province":"TX",
    "sg:tags":[
        "taxidermist"
    ],
    "wof:name":"Wild Things Taxidermy",
    "wof:placetype":"venue"
},
  "geometry": {"coordinates":[-94.8117,29.896068],"type":"Point"}
}