{
  "type": "Feature",
  "properties": {
    "iso:country":"US",
    "sg:address":"1902 Country Club Dr Ste 150",
    "sg:city":"Carrollton",
    "sg:classifiers":[
        {
            "category":"Health Services",
            "subcategory":"Doctor",
            "type":"Services"
        }
    ],
    "sg:phone":"+1 972 416 4272",
    "sg:postcode":"75006",
    "sg:province":"TX",
    "sg:tags":[
        "surgeon",
        "oral"
    ],
    "wof:name":"Medearis Charles R DDS",
    "wof:placetype":"venue"
},
  "geometry": {"coordinates":[-96.88870199999999,32.960899],"type":"Point"}
}