{
  "type": "Feature",
  "properties": {
    "iso:country":"US",
    "sg:address":"4506 US Hwy 80",
    "sg:city":"Grand Saline",
    "sg:classifiers":[
        {
            "category":"Shopping",
            "subcategory":"Discount & Variety Stores",
            "type":"Retail Goods"
        }
    ],
    "sg:phone":"+1 903 962 3285",
    "sg:postcode":"75140",
    "sg:province":"TX",
    "sg:tags":[
        "merchandise",
        "general"
    ],
    "wof:name":"East End Fireworks",
    "wof:placetype":"venue"
},
  "geometry": {"coordinates":[-95.66696899999999,32.674083],"type":"Point"}
}