{
  "type": "Feature",
  "properties": {
    "iso:country":"US",
    "sg:address":"5614 State Hwy 6",
    "sg:city":"Houston",
    "sg:classifiers":[
        {
            "category":"Retail",
            "subcategory":"Car Wash",
            "type":"Services"
        }
    ],
    "sg:phone":"+1 281 855 6992",
    "sg:postcode":"77084",
    "sg:province":"TX",
    "sg:tags":[
        "carwash"
    ],
    "wof:name":"Bear Creek Car Wash",
    "wof:placetype":"venue"
},
  "geometry": {"coordinates":[-95.645122,29.857877],"type":"Point"}
}