{
  "type": "Feature",
  "properties": {
    "iso:country":"US",
    "sg:address":"4550 Post Oak Place Dr",
    "sg:city":"Houston",
    "sg:classifiers":[
        {
            "category":"Professional",
            "subcategory":"Lawyer & Legal Services",
            "type":"Services"
        }
    ],
    "sg:phone":"+1 713 961 0256",
    "sg:postcode":"77027",
    "sg:province":"TX",
    "wof:name":"Trusch Norma L Attorney At Law",
    "wof:placetype":"venue"
},
  "geometry": {"coordinates":[-95.450357,29.750339],"type":"Point"}
}