{
  "type": "Feature",
  "properties": {
    "iso:country":"US",
    "sg:address":"1010 W 34th Ave",
    "sg:city":"Amarillo",
    "sg:classifiers":[
        {
            "category":"Retail",
            "subcategory":"Repair Shop",
            "type":"Services"
        }
    ],
    "sg:phone":"+1 806 372 5093",
    "sg:postcode":"79109",
    "sg:province":"TX",
    "sg:tags":[
        "lock",
        "locksmith"
    ],
    "wof:name":"Banks Mobile Locksmith Svc",
    "wof:placetype":"venue"
},
  "geometry": {"coordinates":[-101.848995,35.178388],"type":"Point"}
}