{
  "type": "Feature",
  "properties": {
    "iso:country":"US",
    "sg:address":"4723 Aftonshire Dr",
    "sg:city":"Houston",
    "sg:classifiers":[
        {
            "category":"Social Services",
            "type":"Services"
        }
    ],
    "sg:phone":"+1 713 871 9994",
    "sg:postcode":"77027",
    "sg:province":"TX",
    "wof:name":"Emotions Anonymous of Houston",
    "wof:placetype":"venue"
},
  "geometry": {"coordinates":[-95.457419,29.736235],"type":"Point"}
}