{
  "type": "Feature",
  "properties": {
    "iso:country":"US",
    "sg:address":"310 W Jefferson St",
    "sg:city":"Waxahachie",
    "sg:classifiers":[
        {
            "category":"Professional",
            "subcategory":"Management & Consulting",
            "type":"Services"
        }
    ],
    "sg:phone":"+1 972 923 2950",
    "sg:postcode":"75165",
    "sg:province":"TX",
    "sg:tags":[
        "consultant",
        "training"
    ],
    "sg:website":"www.skillscommunity.com",
    "wof:name":"Skillsnet Corp",
    "wof:placetype":"venue"
},
  "geometry": {"coordinates":[-96.850239,32.385367],"type":"Point"}
}