{
  "type": "Feature",
  "properties": {
    "iso:country":"US",
    "sg:address":"1201 Barbara Jordan Blvd",
    "sg:city":"Austin",
    "sg:classifiers":[
        {
            "category":"Home & Garden",
            "subcategory":"Household Appliances",
            "type":"Retail Goods"
        },
        {
            "category":"Home & Garden",
            "subcategory":"Furniture",
            "type":"Retail Goods"
        }
    ],
    "sg:phone":"+1 512 476 1601",
    "sg:postcode":"78723",
    "sg:province":"TX",
    "sg:tags":[
        "renting",
        "leasing",
        "dryers-rental",
        "washer",
        "rental",
        "lease"
    ],
    "wof:name":"Flexi Compras",
    "wof:placetype":"venue"
},
  "geometry": {"coordinates":[-97.70931299999999,30.306742],"type":"Point"}
}