{
  "type": "Feature",
  "properties": {
    "iso:country":"US",
    "sg:address":"2615 Woods Estates Dr",
    "sg:city":"Kingwood",
    "sg:classifiers":[
        {
            "category":"Organizations",
            "subcategory":"Professional Association",
            "type":"Services"
        }
    ],
    "sg:phone":"+1 281 358 3699",
    "sg:postcode":"77339",
    "sg:province":"TX",
    "wof:name":"Kings Forest Community Assn",
    "wof:placetype":"venue"
},
  "geometry": {"coordinates":[-95.200951,30.048242],"type":"Point"}
}