{
  "type": "Feature",
  "properties": {
    "iso:country":"US",
    "sg:address":"7700 Heathrow Dr",
    "sg:city":"Plano",
    "sg:classifiers":[
        {
            "category":"Manufacturing",
            "subcategory":"Printing",
            "type":"Manufacturing & Wholesale Goods"
        }
    ],
    "sg:phone":"+1 972 618 5301",
    "sg:postcode":"75025",
    "sg:province":"TX",
    "sg:tags":[
        "commercial"
    ],
    "wof:name":"Maureens Weddings & Affairs",
    "wof:placetype":"venue"
},
  "geometry": {"coordinates":[-96.73739399999999,33.083045],"type":"Point"}
}