{
  "type": "Feature",
  "properties": {
    "iso:country":"US",
    "sg:address":"23502 Crooked Creek Ct",
    "sg:city":"Hockley",
    "sg:classifiers":[
        {
            "category":"Professional",
            "subcategory":"Computer Services",
            "type":"Services"
        }
    ],
    "sg:phone":"+1 281 259 5335",
    "sg:postcode":"77447",
    "sg:province":"TX",
    "sg:tags":[
        "information",
        "system",
        "related"
    ],
    "wof:name":"Merit Information Systems LLC",
    "wof:placetype":"venue"
},
  "geometry": {"coordinates":[-95.77743599999999,30.113249],"type":"Point"}
}