{
  "type": "Feature",
  "properties": {
    "iso:country":"US",
    "sg:address":"15919 Cumbria Dr",
    "sg:city":"Spring",
    "sg:classifiers":[
        {
            "category":"Professional",
            "subcategory":"Engineering",
            "type":"Services"
        }
    ],
    "sg:phone":"+1 281 586 2285",
    "sg:postcode":"77379",
    "sg:province":"TX",
    "wof:name":"Farrell Enterprises Inc",
    "wof:placetype":"venue"
},
  "geometry": {"coordinates":[-95.54185200000001,29.997859],"type":"Point"}
}