{
  "type": "Feature",
  "properties": {
    "iso:country":"US",
    "sg:address":"15549 Woodforest Blvd",
    "sg:city":"Channelview",
    "sg:classifiers":[
        {
            "category":"Shopping",
            "subcategory":"Books",
            "type":"Retail Goods"
        }
    ],
    "sg:phone":"+1 281 457 6737",
    "sg:postcode":"77530",
    "sg:province":"TX",
    "wof:name":"Andys Books & Nooks",
    "wof:placetype":"venue"
},
  "geometry": {"coordinates":[-95.130167,29.789179],"type":"Point"}
}