{
  "type": "Feature",
  "properties": {
    "iso:country":"US",
    "sg:address":"2328 Fannin St",
    "sg:city":"Houston",
    "sg:classifiers":[
        {
            "category":"Professional",
            "subcategory":"Accounting & Tax Preparation",
            "type":"Services"
        }
    ],
    "sg:phone":"+1 713 652 5900",
    "sg:postcode":"77002",
    "sg:province":"TX",
    "sg:tags":[
        "accountant"
    ],
    "wof:name":"Ronald Castro CPA",
    "wof:placetype":"venue"
},
  "geometry": {"coordinates":[-95.372203,29.746282],"type":"Point"}
}