{
  "type": "Feature",
  "properties": {
    "iso:country":"US",
    "sg:address":"1102 N Smith Ave",
    "sg:city":"Hebbronville",
    "sg:classifiers":[
        {
            "category":"Food & Beverages",
            "subcategory":"Meat & Fish",
            "type":"Retail Goods"
        }
    ],
    "sg:phone":"+1 361 527 2170",
    "sg:postcode":"78361",
    "sg:province":"TX",
    "wof:name":"Morales Quality Meats",
    "wof:placetype":"venue"
},
  "geometry": {"coordinates":[-98.67757400000001,27.317507],"type":"Point"}
}