{
  "type": "Feature",
  "properties": {
    "iso:country":"US",
    "sg:address":"1602 Casperson Dr",
    "sg:city":"Houston",
    "sg:classifiers":[
        {
            "category":"Building & Trades",
            "subcategory":"Landscaping Services",
            "type":"Services"
        }
    ],
    "sg:phone":"+1 713 330 8717",
    "sg:postcode":"77029",
    "sg:province":"TX",
    "sg:tags":[
        "landscape",
        "contractor"
    ],
    "wof:name":"Eden Lawn Svc",
    "wof:placetype":"venue"
},
  "geometry": {"coordinates":[-95.22924999999999,29.762642],"type":"Point"}
}