{
  "type": "Feature",
  "properties": {
    "iso:country":"US",
    "sg:address":"1104 Campbell Ave",
    "sg:city":"Jourdanton",
    "sg:classifiers":[
        {
            "category":"Government",
            "subcategory":"Office",
            "type":"Public Place"
        }
    ],
    "sg:phone":"+1 830 769 2787",
    "sg:postcode":"78026",
    "sg:province":"TX",
    "wof:name":"Atascosa County Program Office",
    "wof:placetype":"venue"
},
  "geometry": {"coordinates":[-98.544759,28.917975],"type":"Point"}
}