{
  "type": "Feature",
  "properties": {
    "iso:country":"US",
    "sg:address":"5200 Dallas Ave",
    "sg:city":"Fort Worth",
    "sg:classifiers":[
        {
            "category":"Building & Trades",
            "subcategory":"Construction",
            "type":"Services"
        }
    ],
    "sg:phone":"+1 817 239 8773",
    "sg:postcode":"76112",
    "sg:province":"TX",
    "sg:tags":[
        "house",
        "industrial",
        "co"
    ],
    "wof:name":"Dayco General Contractors",
    "wof:placetype":"venue"
},
  "geometry": {"coordinates":[-97.242915,32.73785],"type":"Point"}
}