{
  "type": "Feature",
  "properties": {
    "iso:country":"US",
    "sg:address":"18334 Ella Blvd",
    "sg:city":"Spring",
    "sg:classifiers":[
        {
            "category":"Building & Trades",
            "subcategory":"Construction",
            "type":"Services"
        }
    ],
    "sg:phone":"+1 281 353 1512",
    "sg:postcode":"77388",
    "sg:province":"TX",
    "sg:tags":[
        "general",
        "contractor"
    ],
    "wof:name":"Chemical Distribution",
    "wof:placetype":"venue"
},
  "geometry": {"coordinates":[-95.466071,30.03754],"type":"Point"}
}