{
  "type": "Feature",
  "properties": {
    "iso:country":"US",
    "sg:address":"4818 Orchid Ln",
    "sg:city":"Corpus Christi",
    "sg:classifiers":[
        {
            "category":"Banks & Credit Unions",
            "subcategory":"Investment Brokerage",
            "type":"Services"
        }
    ],
    "sg:phone":"+1 361 854 0128",
    "sg:postcode":"78416",
    "sg:province":"TX",
    "sg:tags":[
        "advisory"
    ],
    "wof:name":"Equity Financial Services",
    "wof:placetype":"venue"
},
  "geometry": {"coordinates":[-97.431088,27.742035],"type":"Point"}
}