{
  "type": "Feature",
  "properties": {
    "iso:country":"US",
    "sg:address":"5714 Bellaire Blvd",
    "sg:city":"Houston",
    "sg:classifiers":[
        {
            "category":"Banks & Credit Unions",
            "subcategory":"Bank",
            "type":"Services"
        }
    ],
    "sg:phone":"+1 713 218 0429",
    "sg:postcode":"77081",
    "sg:province":"TX",
    "sg:tags":[
        "money",
        "order"
    ],
    "wof:name":"IXE Dollar Express",
    "wof:placetype":"venue"
},
  "geometry": {"coordinates":[-95.48062899999999,29.70567],"type":"Point"}
}