{
  "type": "Feature",
  "properties": {
    "iso:country":"US",
    "sg:address":"551 E 15th St",
    "sg:city":"Plano",
    "sg:classifiers":[
        {
            "category":"Banks & Credit Unions",
            "subcategory":"Bank",
            "type":"Services"
        }
    ],
    "sg:phone":"+1 972 423 3592",
    "sg:postcode":"75074",
    "sg:province":"TX",
    "sg:tags":[
        "state",
        "savings"
    ],
    "wof:name":"Central/15th Financial Center",
    "wof:placetype":"venue"
},
  "geometry": {"coordinates":[-96.707956,33.019847],"type":"Point"}
}