{
  "type": "Feature",
  "properties": {
    "iso:country":"US",
    "sg:address":"108 Pullman Pl",
    "sg:city":"Wylie",
    "sg:classifiers":[
        {
            "category":"Shopping",
            "subcategory":"Clothing, Apparel, & Fashions",
            "type":"Retail Goods"
        }
    ],
    "sg:phone":"+1 972 442 0137",
    "sg:postcode":"75098",
    "sg:province":"TX",
    "sg:tags":[
        "family"
    ],
    "wof:name":"Chic Boutique",
    "wof:placetype":"venue"
},
  "geometry": {"coordinates":[-96.549936,33.015644],"type":"Point"}
}