{
  "type": "Feature",
  "properties": {
    "iso:country":"US",
    "sg:address":"3606 Thompson St",
    "sg:city":"Austin",
    "sg:classifiers":[
        {
            "category":"Personal",
            "subcategory":"Beauty Salon",
            "type":"Services"
        }
    ],
    "sg:phone":"+1 512 301 6429",
    "sg:postcode":"78702",
    "sg:province":"TX",
    "sg:tags":[
        "shop"
    ],
    "wof:name":"JS Hair Salon",
    "wof:placetype":"venue"
},
  "geometry": {"coordinates":[-97.696884,30.265748],"type":"Point"}
}