{
  "type": "Feature",
  "properties": {
    "iso:country":"US",
    "sg:address":"6889 Hightower Dr",
    "sg:city":"Fort Worth",
    "sg:classifiers":[
        {
            "category":"Real Estate",
            "subcategory":"Real Estate Operator",
            "type":"Services"
        }
    ],
    "sg:phone":"+1 817 498 3313",
    "sg:postcode":"76180",
    "sg:province":"TX",
    "sg:tags":[
        "building",
        "apartment"
    ],
    "wof:name":"Haverhill Apartments",
    "wof:placetype":"venue"
},
  "geometry": {"coordinates":[-97.23272799999999,32.874941],"type":"Point"}
}