{
  "type": "Feature",
  "properties": {
    "iso:country":"US",
    "sg:address":"13375 Galicia",
    "sg:city":"Universal City",
    "sg:classifiers":[
        {
            "category":"Professional",
            "subcategory":"Computer Services",
            "type":"Services"
        }
    ],
    "sg:phone":"+1 210 798 4289",
    "sg:postcode":"78148",
    "sg:province":"TX",
    "wof:name":"Computer Toolz",
    "wof:placetype":"venue"
},
  "geometry": {"coordinates":[-98.317939,29.561359],"type":"Point"}
}