{
  "type": "Feature",
  "properties": {
    "iso:country":"US",
    "sg:address":"22622 Aldine Westfield Rd",
    "sg:city":"Spring",
    "sg:classifiers":[
        {
            "category":"Shopping",
            "subcategory":"Beauty & Cosmetics",
            "type":"Retail Goods"
        }
    ],
    "sg:phone":"+1 281 350 3324",
    "sg:postcode":"77373",
    "sg:province":"TX",
    "sg:tags":[
        "ac",
        "merchandise"
    ],
    "wof:name":"Merle Norman Cosmetics",
    "wof:placetype":"venue"
},
  "geometry": {"coordinates":[-95.384124,30.04387],"type":"Point"}
}