{
  "type": "Feature",
  "properties": {
    "iso:country":"US",
    "sg:address":"511 Placid Lake Ln",
    "sg:city":"Magnolia",
    "sg:classifiers":[
        {
            "category":"Retail",
            "subcategory":"Auto Repair",
            "type":"Services"
        }
    ],
    "sg:phone":"+1 281 252 6350",
    "sg:postcode":"77354",
    "sg:province":"TX",
    "sg:tags":[
        "automotive"
    ],
    "wof:name":"Greenes Wrecker",
    "wof:placetype":"venue"
},
  "geometry": {"coordinates":[-95.742045,30.222441],"type":"Point"}
}