{
  "type": "Feature",
  "properties": {
    "iso:country":"US",
    "sg:address":"334 W Hidalgo Ave",
    "sg:city":"Raymondville",
    "sg:classifiers":[
        {
            "category":"Professional",
            "subcategory":"Printing & Photocopies",
            "type":"Services"
        }
    ],
    "sg:phone":"+1 956 689 2679",
    "sg:postcode":"78580",
    "sg:province":"TX",
    "sg:tags":[
        "photocopying"
    ],
    "wof:name":"Copy Pros",
    "wof:placetype":"venue"
},
  "geometry": {"coordinates":[-97.784976,26.481955],"type":"Point"}
}