{
  "type": "Feature",
  "properties": {
    "iso:country":"US",
    "sg:address":"539 Briarcliff Dr",
    "sg:city":"Garland",
    "sg:classifiers":[
        {
            "category":"Travel",
            "subcategory":"Travel Agent",
            "type":"Entertainment"
        }
    ],
    "sg:phone":"+1 972 681 2588",
    "sg:postcode":"75043",
    "sg:province":"TX",
    "sg:tags":[
        "agency",
        "bureau"
    ],
    "wof:name":"GMK Enterprises",
    "wof:placetype":"venue"
},
  "geometry": {"coordinates":[-96.61054799999999,32.840973],"type":"Point"}
}