{
  "type": "Feature",
  "properties": {
    "iso:country":"US",
    "sg:address":"2323 Bryan St",
    "sg:city":"Dallas",
    "sg:classifiers":[
        {
            "category":"Utilities",
            "subcategory":"Telephone",
            "type":"Services"
        }
    ],
    "sg:phone":"+1 214 969 7269",
    "sg:postcode":"75201",
    "sg:province":"TX",
    "sg:tags":[
        "communications"
    ],
    "wof:name":"Qwest",
    "wof:placetype":"venue"
},
  "geometry": {"coordinates":[-96.793783,32.787117],"type":"Point"}
}