{
  "type": "Feature",
  "properties": {
    "iso:country":"US",
    "sg:address":"703 FM 523",
    "sg:city":"Freeport",
    "sg:classifiers":[
        {
            "category":"Freight",
            "type":"Transportation"
        }
    ],
    "sg:phone":"+1 979 239 1419",
    "sg:postcode":"77541",
    "sg:province":"TX",
    "sg:tags":[
        "courier"
    ],
    "wof:name":"Velocity Express",
    "wof:placetype":"venue"
},
  "geometry": {"coordinates":[-95.34486,28.974183],"type":"Point"}
}