{
  "type": "Feature",
  "properties": {
    "iso:country":"US",
    "sg:address":"8626 Tesoro Dr",
    "sg:city":"San Antonio",
    "sg:classifiers":[
        {
            "category":"Professional",
            "type":"Services"
        }
    ],
    "sg:phone":"+1 210 804 5400",
    "sg:postcode":"78217",
    "sg:province":"TX",
    "wof:name":"Alamo Screening & Investi",
    "wof:placetype":"venue"
},
  "geometry": {"coordinates":[-98.454401,29.51823],"type":"Point"}
}