{
  "type": "Feature",
  "properties": {
    "iso:country":"US",
    "sg:address":"3124 Sherwood Way",
    "sg:city":"San Angelo",
    "sg:classifiers":[
        {
            "category":"Real Estate",
            "subcategory":"Real Estate Agent",
            "type":"Services"
        }
    ],
    "sg:phone":"+1 325 944 1630",
    "sg:postcode":"76901",
    "sg:province":"TX",
    "wof:name":"Bob Ingram Real Estate",
    "wof:placetype":"venue"
},
  "geometry": {"coordinates":[-100.47863700000001,31.446051],"type":"Point"}
}