{
  "type": "Feature",
  "properties": {
    "iso:country":"US",
    "sg:address":"220 Oak Hill Dr",
    "sg:city":"Kerrville",
    "sg:classifiers":[
        {
            "category":"Professional",
            "type":"Services"
        }
    ],
    "sg:phone":"+1 830 257 1529",
    "sg:postcode":"78028",
    "sg:province":"TX",
    "sg:tags":[
        "art",
        "fine",
        "gallery",
        "artist"
    ],
    "wof:name":"Chance, Earlayne",
    "wof:placetype":"venue"
},
  "geometry": {"coordinates":[-99.17471,30.072982],"type":"Point"}
}