{
  "type": "Feature",
  "properties": {
    "iso:country":"US",
    "sg:address":"12416 Swallow Ct",
    "sg:city":"Mesquite",
    "sg:classifiers":[
        {
            "category":"Professional",
            "subcategory":"Management & Consulting",
            "type":"Services"
        }
    ],
    "sg:phone":"+1 972 286 5756",
    "sg:postcode":"75180",
    "sg:province":"TX",
    "sg:tags":[
        "business"
    ],
    "wof:name":"J J Santos",
    "wof:placetype":"venue"
},
  "geometry": {"coordinates":[-96.61229400000001,32.704249],"type":"Point"}
}