{
  "type": "Feature",
  "properties": {
    "iso:country":"US",
    "sg:address":"3525 Shore Dr",
    "sg:city":"Corpus Christi",
    "sg:classifiers":[
        {
            "category":"Retail",
            "subcategory":"Repair Shop",
            "type":"Services"
        }
    ],
    "sg:phone":"+1 361 937 3131",
    "sg:postcode":"78418",
    "sg:province":"TX",
    "sg:tags":[
        "water",
        "equipment",
        "softening"
    ],
    "wof:name":"R S Svc Co",
    "wof:placetype":"venue"
},
  "geometry": {"coordinates":[-97.293717,27.622311],"type":"Point"}
}