{
  "type": "Feature",
  "properties": {
    "iso:country":"US",
    "sg:address":"2837 Miller Ranch Rd",
    "sg:city":"Pearland",
    "sg:classifiers":[
        {
            "category":"Wholesale",
            "subcategory":"Painting Supplies",
            "type":"Manufacturing & Wholesale Goods"
        }
    ],
    "sg:phone":"+1 281 436 0026",
    "sg:postcode":"77584",
    "sg:province":"TX",
    "wof:name":"P P G Architectural Finishes",
    "wof:placetype":"venue"
},
  "geometry": {"coordinates":[-95.373085,29.556277],"type":"Point"}
}