{
  "type": "Feature",
  "properties": {
    "iso:country":"US",
    "sg:address":"432 Atkinson Dr",
    "sg:city":"Lufkin",
    "sg:phone":"+1 936 634 2038",
    "sg:postcode":"75901",
    "sg:province":"TX",
    "sg:tags":[
        "equipment",
        "commercial"
    ],
    "wof:name":"Quality Restaurant Supply",
    "wof:placetype":"venue"
},
  "geometry": {"coordinates":[-94.721537,31.345344],"type":"Point"}
}