{
  "type": "Feature",
  "properties": {
    "iso:country":"US",
    "sg:address":"616 S Grant Ave",
    "sg:city":"Odessa",
    "sg:classifiers":[
        {
            "category":"Professional",
            "subcategory":"Accounting & Tax Preparation",
            "type":"Services"
        }
    ],
    "sg:phone":"+1 432 332 0008",
    "sg:postcode":"79761",
    "sg:province":"TX",
    "wof:name":"Belindas Income Tax",
    "wof:placetype":"venue"
},
  "geometry": {"coordinates":[-102.363803,31.840216],"type":"Point"}
}