{
  "type": "Feature",
  "properties": {
    "iso:country":"US",
    "sg:address":"1501 S 1st St",
    "sg:city":"Austin",
    "sg:classifiers":[
        {
            "category":"Restaurant",
            "type":"Food & Drink"
        }
    ],
    "sg:phone":"+1 512 255 5023",
    "sg:postcode":"78704",
    "sg:province":"TX",
    "wof:name":"High Time Tea Bar & Brain Gym",
    "wof:placetype":"venue"
},
  "geometry": {"coordinates":[-97.755116,30.249515],"type":"Point"}
}