{
  "type": "Feature",
  "properties": {
    "iso:country":"US",
    "sg:address":"208 E Central Ave Suite 107",
    "sg:city":"Belton",
    "sg:classifiers":[
        {
            "category":"Professional",
            "subcategory":"Lawyer & Legal Services",
            "type":"Services"
        }
    ],
    "sg:phone":"+1 254 634 2587",
    "sg:postcode":"76513",
    "sg:province":"TX",
    "sg:tags":[
        "attorney"
    ],
    "wof:name":"Ed Brown Law Firm",
    "wof:placetype":"venue"
},
  "geometry": {"coordinates":[-97.462878,31.056175],"type":"Point"}
}