{
  "type": "Feature",
  "properties": {
    "iso:country":"US",
    "sg:address":"2700 Forest Ln",
    "sg:city":"Dallas",
    "sg:classifiers":[
        {
            "category":"Home & Garden",
            "subcategory":"Carpets & Floor Coverings",
            "type":"Retail Goods"
        }
    ],
    "sg:phone":"+1 972 406 8881",
    "sg:postcode":"75234",
    "sg:province":"TX",
    "sg:tags":[
        "flooring"
    ],
    "wof:name":"Tuscan Floors Distributor",
    "wof:placetype":"venue"
},
  "geometry": {"coordinates":[-96.886582,32.909052],"type":"Point"}
}