{
  "type": "Feature",
  "properties": {
    "iso:country":"US",
    "sg:address":"2112 8th St",
    "sg:city":"Bay City",
    "sg:classifiers":[
        {
            "category":"Organizations",
            "subcategory":"Religious Organization",
            "type":"Services"
        }
    ],
    "sg:phone":"+1 979 323 8579",
    "sg:postcode":"77414",
    "sg:province":"TX",
    "sg:tags":[
        "church"
    ],
    "wof:name":"Bay City Church Of God",
    "wof:placetype":"venue"
},
  "geometry": {"coordinates":[-95.964172,28.984152],"type":"Point"}
}