{
  "type": "Feature",
  "properties": {
    "iso:country":"US",
    "sg:address":"700 S Fleishel Ave",
    "sg:city":"Tyler",
    "sg:classifiers":[
        {
            "category":"Food & Beverages",
            "subcategory":"Groceries & Convenience Stores",
            "type":"Retail Goods"
        }
    ],
    "sg:phone":"+1 903 592 2524",
    "sg:postcode":"75701",
    "sg:province":"TX",
    "wof:name":"Easy Stop",
    "wof:placetype":"venue"
},
  "geometry": {"coordinates":[-95.28876200000001,32.341516],"type":"Point"}
}