{
  "type": "Feature",
  "properties": {
    "iso:country":"US",
    "sg:address":"103 Old Hwy 90 Lp",
    "sg:city":"Schulenburg",
    "sg:classifiers":[
        {
            "category":"Social Services",
            "subcategory":"Child Care",
            "type":"Services"
        }
    ],
    "sg:phone":"+1 979 743 3826",
    "sg:postcode":"78956",
    "sg:province":"TX",
    "wof:name":"Kid's Klubhouse",
    "wof:placetype":"venue"
},
  "geometry": {"coordinates":[-96.921274,29.681886],"type":"Point"}
}