{
  "type": "Feature",
  "properties": {
    "iso:country":"US",
    "sg:address":"613 Everhart Rd",
    "sg:city":"Corpus Christi",
    "sg:classifiers":[
        {
            "category":"Shopping",
            "subcategory":"Clothing, Apparel, & Fashions",
            "type":"Retail Goods"
        }
    ],
    "sg:phone":"+1 361 993 7722",
    "sg:postcode":"78411",
    "sg:province":"TX",
    "wof:name":"Lamp Ladies Inc",
    "wof:placetype":"venue"
},
  "geometry": {"coordinates":[-97.374791,27.7297],"type":"Point"}
}