{
  "type": "Feature",
  "properties": {
    "iso:country":"US",
    "sg:address":"8311 Spencer Hwy",
    "sg:city":"Deer Park",
    "sg:classifiers":[
        {
            "category":"Shopping",
            "subcategory":"Discount & Variety Stores",
            "type":"Retail Goods"
        }
    ],
    "sg:phone":"+1 281 542 9141",
    "sg:postcode":"77536",
    "sg:province":"TX",
    "wof:name":"Dollar General",
    "wof:placetype":"venue"
},
  "geometry": {"coordinates":[-95.112032,29.663976],"type":"Point"}
}