{
  "type": "Feature",
  "properties": {
    "iso:country":"US",
    "sg:address":"402 S Main St",
    "sg:city":"Henderson",
    "sg:classifiers":[
        {
            "category":"Organizations",
            "subcategory":"Religious Organization",
            "type":"Services"
        }
    ],
    "sg:phone":"+1 903 657 1408",
    "sg:postcode":"75654",
    "sg:province":"TX",
    "wof:name":"South Main",
    "wof:placetype":"venue"
},
  "geometry": {"coordinates":[-94.799598,32.150194],"type":"Point"}
}