{
  "type": "Feature",
  "properties": {
    "iso:country":"US",
    "sg:address":"506 E Hayes St",
    "sg:city":"Savoy",
    "sg:classifiers":[
        {
            "category":"Home & Garden",
            "subcategory":"Building Materials",
            "type":"Retail Goods"
        },
        {
            "category":"Building & Trades",
            "subcategory":"Construction",
            "type":"Services"
        },
        {
            "category":"Military Area",
            "subcategory":"Armory",
            "type":"Public Place"
        }
    ],
    "sg:phone":"+1 903 965 4251",
    "sg:postcode":"75479",
    "sg:province":"TX",
    "sg:tags":[
        "repair",
        "fence",
        "altering",
        "contractor",
        "remodeling",
        "fence-sales"
    ],
    "wof:name":"John Kinman Fences",
    "wof:placetype":"venue"
},
  "geometry": {"coordinates":[-96.362661,33.598401],"type":"Point"}
}