{
  "type": "Feature",
  "properties": {
    "iso:country":"US",
    "sg:address":"1319 Mission St",
    "sg:city":"Duncanville",
    "sg:classifiers":[
        {
            "category":"Building & Trades",
            "subcategory":"Construction",
            "type":"Services"
        }
    ],
    "sg:phone":"+1 972 296 7946",
    "sg:postcode":"75137",
    "sg:province":"TX",
    "sg:tags":[
        "coping",
        "plastering",
        "tiling",
        "pool",
        "swimming"
    ],
    "wof:name":"Riviera Pools",
    "wof:placetype":"venue"
},
  "geometry": {"coordinates":[-96.92117399999999,32.639295],"type":"Point"}
}