{
  "type": "Feature",
  "properties": {
    "iso:country":"US",
    "sg:address":"303 Walnut St",
    "sg:city":"Duncanville",
    "sg:classifiers":[
        {
            "category":"Fast Food",
            "type":"Food & Drink"
        },
        {
            "category":"Restaurant",
            "type":"Food & Drink"
        }
    ],
    "sg:phone":"+1 972 283 4294",
    "sg:postcode":"75116",
    "sg:province":"TX",
    "sg:tags":[
        "american",
        "hot",
        "hamburger",
        "dog"
    ],
    "sg:website":"http://www.jackinthebox.com",
    "wof:name":"Jack in the Box",
    "wof:placetype":"venue"
},
  "geometry": {"coordinates":[-96.910083,32.65388],"type":"Point"}
}