{
  "type": "Feature",
  "properties": {
    "iso:country":"US",
    "sg:address":"4221 S Padre Island Dr",
    "sg:city":"Austin",
    "sg:classifiers":[
        {
            "category":"Restaurant",
            "type":"Food & Drink"
        }
    ],
    "sg:phone":"+1 361 814 6283",
    "sg:postcode":"78741",
    "sg:province":"TX",
    "wof:name":"Outback Steak House",
    "wof:placetype":"venue"
},
  "geometry": {"coordinates":[-97.72020000000001,30.2332],"type":"Point"}
}