{
  "type": "Feature",
  "properties": {
    "iso:country":"US",
    "sg:address":"421 W Valley Dr",
    "sg:city":"Iowa Park",
    "sg:classifiers":[
        {
            "category":"Building & Trades",
            "subcategory":"Electrical",
            "type":"Services"
        }
    ],
    "sg:phone":"+1 940 592 2994",
    "sg:postcode":"76367",
    "sg:province":"TX",
    "sg:tags":[
        "electrical",
        "contractor"
    ],
    "wof:name":"Clarence Hill Electrical",
    "wof:placetype":"venue"
},
  "geometry": {"coordinates":[-98.67061200000001,33.93671],"type":"Point"}
}