{
  "type": "Feature",
  "properties": {
    "iso:country":"US",
    "sg:address":"1105 Santa Maria Ave",
    "sg:city":"Laredo",
    "sg:classifiers":[
        {
            "category":"Retail",
            "subcategory":"Car Wash",
            "type":"Services"
        }
    ],
    "sg:phone":"+1 956 728 9090",
    "sg:postcode":"78040",
    "sg:province":"TX",
    "sg:tags":[
        "polishing",
        "washing"
    ],
    "wof:name":"Ronald Mc Duck's Inc",
    "wof:placetype":"venue"
},
  "geometry": {"coordinates":[-99.51026400000001,27.509851],"type":"Point"}
}