{
  "type": "Feature",
  "properties": {
    "iso:country":"US",
    "sg:address":"87 Autumn Branch Dr",
    "sg:city":"Spring",
    "sg:classifiers":[
        {
            "category":"Autos & Motor Vehicles",
            "subcategory":"Motorcycle Sales",
            "type":"Retail Goods"
        }
    ],
    "sg:phone":"+1 281 362 0989",
    "sg:postcode":"77382",
    "sg:province":"TX",
    "wof:name":"South Paw Cycles Inc",
    "wof:placetype":"venue"
},
  "geometry": {"coordinates":[-95.52294500000001,30.216194],"type":"Point"}
}