{
  "type": "Feature",
  "properties": {
    "iso:country":"US",
    "sg:address":"4016 Rowlett Rd",
    "sg:city":"Rowlett",
    "sg:classifiers":[
        {
            "category":"Real Estate",
            "subcategory":"Real Estate Services",
            "type":"Services"
        }
    ],
    "sg:phone":"+1 972 463 5277",
    "sg:postcode":"75088",
    "sg:province":"TX",
    "sg:tags":[
        "management",
        "property"
    ],
    "wof:name":"Metro Property Management",
    "wof:placetype":"venue"
},
  "geometry": {"coordinates":[-96.569298,32.8969],"type":"Point"}
}