{
  "type": "Feature",
  "properties": {
    "iso:country":"US",
    "sg:address":"3234 Blackchamp Rd",
    "sg:city":"Midlothian",
    "sg:classifiers":[
        {
            "category":"Building & Trades",
            "subcategory":"Plumbing",
            "type":"Services"
        }
    ],
    "sg:phone":"+1 972 923 9607",
    "sg:postcode":"76065",
    "sg:province":"TX",
    "sg:tags":[
        "plumber",
        "industrial",
        "contractors-commercial"
    ],
    "wof:name":"Ellis County Plumbing",
    "wof:placetype":"venue"
},
  "geometry": {"coordinates":[-96.899359,32.442211],"type":"Point"}
}