{
  "type": "Feature",
  "properties": {
    "iso:country":"US",
    "sg:address":"3113 S 31st St",
    "sg:city":"Temple",
    "sg:classifiers":[
        {
            "category":"Ice Cream",
            "type":"Food & Drink"
        }
    ],
    "sg:menulink":"http://www.allmenus.com/tx/temple/162543-dairy-queen/menu/",
    "sg:phone":"+1 254 774 8740",
    "sg:postcode":"76502",
    "sg:province":"TX",
    "sg:tags":[
        "burger",
        "american"
    ],
    "wof:name":"Dairy Queen",
    "wof:placetype":"venue"
},
  "geometry": {"coordinates":[-97.369339,31.06982],"type":"Point"}
}