{
  "type": "Feature",
  "properties": {
    "iso:country":"US",
    "sg:address":"402 Cedar St",
    "sg:city":"Abilene",
    "sg:classifiers":[
        {
            "category":"Professional",
            "subcategory":"Accounting & Tax Preparation",
            "type":"Services"
        }
    ],
    "sg:phone":"+1 325 676 1300",
    "sg:postcode":"79601",
    "sg:province":"TX",
    "sg:tags":[
        "accountant"
    ],
    "wof:name":"Brandon Polk CPA",
    "wof:placetype":"venue"
},
  "geometry": {"coordinates":[-99.73520000000001,32.45374],"type":"Point"}
}