{
  "type": "Feature",
  "properties": {
    "iso:country":"US",
    "sg:address":"1706 Hunter Rd",
    "sg:city":"New Braunfels",
    "sg:classifiers":[
        {
            "category":"Shopping",
            "subcategory":"Used Merchandise",
            "type":"Retail Goods"
        }
    ],
    "sg:phone":"+1 830 620 9602",
    "sg:postcode":"78130",
    "sg:province":"TX",
    "sg:tags":[
        "antique"
    ],
    "wof:name":"Cactus Jack's Antiques Etc",
    "wof:placetype":"venue"
},
  "geometry": {"coordinates":[-98.101893,29.740959],"type":"Point"}
}