{
  "type": "Feature",
  "properties": {
    "iso:country":"US",
    "sg:address":"302 E Queen Isabella Blvd",
    "sg:city":"Port Isabel",
    "sg:classifiers":[
        {
            "category":"Banks & Credit Unions",
            "subcategory":"Bank",
            "type":"Services"
        }
    ],
    "sg:phone":"+1 956 943 7300",
    "sg:postcode":"78578",
    "sg:province":"TX",
    "sg:tags":[
        "broker",
        "mortgage"
    ],
    "wof:name":"Rivera Margaret Mrtg Co LLC",
    "wof:placetype":"venue"
},
  "geometry": {"coordinates":[-97.207426,26.076956],"type":"Point"}
}