{
  "type": "Feature",
  "properties": {
    "iso:country":"US",
    "sg:address":"18 Thomas Ln",
    "sg:city":"Huffman",
    "sg:classifiers":[
        {
            "category":"Education",
            "subcategory":"Vocational School",
            "type":"Public Place"
        }
    ],
    "sg:phone":"+1 281 360 6923",
    "sg:postcode":"77336",
    "sg:province":"TX",
    "wof:name":"Whiz Kids On Computers",
    "wof:placetype":"venue"
},
  "geometry": {"coordinates":[-95.124415,30.125329],"type":"Point"}
}