{
  "type": "Feature",
  "properties": {
    "iso:country":"US",
    "sg:address":"10721 Plano Rd Ste 100",
    "sg:city":"Dallas",
    "sg:classifiers":[
        {
            "category":"Real Estate",
            "subcategory":"Architect",
            "type":"Services"
        }
    ],
    "sg:phone":"+1 214 341 6395",
    "sg:postcode":"75238",
    "sg:province":"TX",
    "wof:name":"Roper Dan A Architech",
    "wof:placetype":"venue"
},
  "geometry": {"coordinates":[-96.70059999999999,32.894798],"type":"Point"}
}