{
  "type": "Feature",
  "properties": {
    "iso:country":"US",
    "sg:address":"770 Roosevelt St",
    "sg:city":"New Braunfels",
    "sg:classifiers":[
        {
            "category":"Manufacturing",
            "subcategory":"Toys & Sporting Goods",
            "type":"Manufacturing & Wholesale Goods"
        }
    ],
    "sg:phone":"+1 830 609 0939",
    "sg:postcode":"78130",
    "sg:province":"TX",
    "sg:tags":[
        "mfg"
    ],
    "wof:name":"Main Street Enterprises",
    "wof:placetype":"venue"
},
  "geometry": {"coordinates":[-98.125136,29.693337],"type":"Point"}
}