{
  "type": "Feature",
  "properties": {
    "iso:country":"US",
    "sg:address":"3103 Harrisburg Blvd",
    "sg:city":"Houston",
    "sg:classifiers":[
        {
            "category":"Building & Trades",
            "subcategory":"Cleaning & Sanitation",
            "type":"Services"
        }
    ],
    "sg:phone":"+1 713 759 1765",
    "sg:postcode":"77003",
    "sg:province":"TX",
    "sg:tags":[
        "maintenance"
    ],
    "wof:name":"EPM Svc",
    "wof:placetype":"venue"
},
  "geometry": {"coordinates":[-95.343738,29.749889],"type":"Point"}
}