{
  "type": "Feature",
  "properties": {
    "iso:country":"US",
    "sg:address":"1844 Rosemeade Pkwy",
    "sg:city":"Carrollton",
    "sg:classifiers":[
        {
            "category":"Professional",
            "subcategory":"Computer Services",
            "type":"Services"
        }
    ],
    "sg:phone":"+1 972 492 5315",
    "sg:postcode":"75007",
    "sg:province":"TX",
    "sg:tags":[
        "repair"
    ],
    "wof:name":"Click PSI Inc",
    "wof:placetype":"venue"
},
  "geometry": {"coordinates":[-96.88710500000001,33.011769],"type":"Point"}
}