{
  "type": "Feature",
  "properties": {
    "iso:country":"US",
    "sg:address":"2300 Highland Village Rd",
    "sg:city":"Lewisville",
    "sg:classifiers":[
        {
            "category":"Building & Trades",
            "subcategory":"Construction",
            "type":"Services"
        }
    ],
    "sg:phone":"+1 972 966 2872",
    "sg:postcode":"75077",
    "sg:province":"TX",
    "sg:tags":[
        "concrete",
        "contractor"
    ],
    "wof:name":"Sharp Curbing Inc",
    "wof:placetype":"venue"
},
  "geometry": {"coordinates":[-97.057585,33.072181],"type":"Point"}
}