{
  "type": "Feature",
  "properties": {
    "iso:country":"US",
    "sg:address":"459 Wayside Dr",
    "sg:city":"San Antonio",
    "sg:classifiers":[
        {
            "category":"Communications",
            "subcategory":"Film & Video Production",
            "type":"Services"
        }
    ],
    "sg:phone":"+1 210 349 4923",
    "sg:postcode":"78213",
    "sg:province":"TX",
    "sg:tags":[
        "taping"
    ],
    "wof:name":"Zamarripa Video Svc",
    "wof:placetype":"venue"
},
  "geometry": {"coordinates":[-98.537745,29.502233],"type":"Point"}
}