{
  "type": "Feature",
  "properties": {
    "iso:country":"US",
    "sg:address":"6444 Highway 6 N",
    "sg:city":"Houston",
    "sg:classifiers":[
        {
            "category":"Home & Garden",
            "subcategory":"Household Appliances",
            "type":"Retail Goods"
        },
        {
            "category":"Retail",
            "subcategory":"Repair Shop",
            "type":"Services"
        }
    ],
    "sg:phone":"+1 281 463 9340",
    "sg:postcode":"77084",
    "sg:province":"TX",
    "sg:tags":[
        "equipment",
        "cleaners-repair",
        "system",
        "cleaners-household-dealers",
        "vacuum"
    ],
    "wof:name":"Cypress Vacuum Shop",
    "wof:placetype":"venue"
},
  "geometry": {"coordinates":[-95.64527200000001,29.873179],"type":"Point"}
}