{
  "type": "Feature",
  "properties": {
    "iso:country":"US",
    "sg:address":"608 Raintree Cir",
    "sg:city":"Coppell",
    "sg:classifiers":[
        {
            "category":"Shopping",
            "subcategory":"Gifts & Souvenirs",
            "type":"Retail Goods"
        }
    ],
    "sg:phone":"+1 972 745 7378",
    "sg:postcode":"75019",
    "sg:province":"TX",
    "wof:name":"Connie Lynn Engholm",
    "wof:placetype":"venue"
},
  "geometry": {"coordinates":[-96.97033999999999,32.983571],"type":"Point"}
}