{
  "type": "Feature",
  "properties": {
    "iso:country":"US",
    "sg:address":"1001 S 10th St",
    "sg:city":"Mcallen",
    "sg:classifiers":[
        {
            "category":"Personal",
            "type":"Services"
        }
    ],
    "sg:phone":"+1 956 687 7721",
    "sg:postcode":"78501",
    "sg:province":"TX",
    "sg:tags":[
        "wear",
        "formal"
    ],
    "wof:name":"Al's Formal Wear",
    "wof:placetype":"venue"
},
  "geometry": {"coordinates":[-98.23168800000001,26.193458],"type":"Point"}
}