{
  "type": "Feature",
  "properties": {
    "iso:country":"US",
    "sg:address":"1230 State Hwy 159",
    "sg:city":"Bellville",
    "sg:classifiers":[
        {
            "category":"Personal",
            "type":"Services"
        },
        {
            "category":"Personal",
            "subcategory":"Beauty Salon",
            "type":"Services"
        }
    ],
    "sg:phone":"+1 979 865 5113",
    "sg:postcode":"77418",
    "sg:province":"TX",
    "sg:tags":[
        "shop",
        "electrologist"
    ],
    "wof:name":"Wild Hair",
    "wof:placetype":"venue"
},
  "geometry": {"coordinates":[-96.26954600000001,29.95746],"type":"Point"}
}