{
  "type": "Feature",
  "properties": {
    "iso:country":"US",
    "sg:address":"408 Camaron Woods",
    "sg:city":"Schertz",
    "sg:classifiers":[
        {
            "category":"Banks & Credit Unions",
            "subcategory":"Bank",
            "type":"Services"
        }
    ],
    "sg:phone":"+1 210 945 0076",
    "sg:postcode":"78154",
    "sg:province":"TX",
    "sg:tags":[
        "loan",
        "real estate"
    ],
    "wof:name":"Military Mortgage",
    "wof:placetype":"venue"
},
  "geometry": {"coordinates":[-98.27897400000001,29.579359],"type":"Point"}
}