{
  "type": "Feature",
  "properties": {
    "iso:country":"US",
    "sg:address":"201 S",
    "sg:city":"Lampasas",
    "sg:classifiers":[
        {
            "category":"Food & Beverages",
            "subcategory":"Liquor & Beverages",
            "type":"Retail Goods"
        }
    ],
    "sg:phone":"+1 512 556 4555",
    "sg:postcode":"76550",
    "sg:province":"TX",
    "sg:tags":[
        "beer",
        "spirit",
        "wine"
    ],
    "wof:name":"Bottle Shop On Key Av",
    "wof:placetype":"venue"
},
  "geometry": {"coordinates":[-97.55263100000001,30.339871],"type":"Point"}
}