{
  "type": "Feature",
  "properties": {
    "iso:country":"US",
    "sg:address":"1811 Pont la Salle Ln",
    "sg:city":"Pasadena",
    "sg:classifiers":[
        {
            "category":"Shopping",
            "subcategory":"Music",
            "type":"Retail Goods"
        }
    ],
    "sg:phone":"+1 832 654 0015",
    "sg:postcode":"77503",
    "sg:province":"TX",
    "sg:tags":[
        "video"
    ],
    "wof:name":"Jesse Video & Music",
    "wof:placetype":"venue"
},
  "geometry": {"coordinates":[-95.170027,29.685506],"type":"Point"}
}