{
  "type": "Feature",
  "properties": {
    "iso:country":"US",
    "sg:address":"434 Lanier Rd",
    "sg:city":"Seagoville",
    "sg:classifiers":[
        {
            "category":"Shopping",
            "subcategory":"Catalog Store",
            "type":"Retail Goods"
        }
    ],
    "sg:phone":"+1 972 476 9939",
    "sg:postcode":"75159",
    "sg:province":"TX",
    "sg:tags":[
        "mail",
        "house"
    ],
    "wof:name":"Open Attic Inc",
    "wof:placetype":"venue"
},
  "geometry": {"coordinates":[-96.506941,32.568393],"type":"Point"}
}