{
  "type": "Feature",
  "properties": {
    "iso:country":"US",
    "sg:address":"3701 Royalcrest Dr",
    "sg:city":"Fort Worth",
    "sg:classifiers":[
        {
            "category":"Organizations",
            "subcategory":"Religious Organization",
            "type":"Services"
        }
    ],
    "sg:phone":"+1 817 561 6348",
    "sg:postcode":"76140",
    "sg:province":"TX",
    "wof:name":"Jesus V Flores",
    "wof:placetype":"venue"
},
  "geometry": {"coordinates":[-97.266122,32.639925],"type":"Point"}
}