{
  "type": "Feature",
  "properties": {
    "iso:country":"US",
    "sg:address":"11209 N Lamar Blvd",
    "sg:city":"Austin",
    "sg:classifiers":[
        {
            "category":"Food & Beverages",
            "subcategory":"Groceries & Convenience Stores",
            "type":"Retail Goods"
        }
    ],
    "sg:phone":"+1 512 834 9142",
    "sg:postcode":"78753",
    "sg:province":"TX",
    "wof:name":"Antonine Grocery",
    "wof:placetype":"venue"
},
  "geometry": {"coordinates":[-97.6871,30.380443],"type":"Point"}
}