{
  "type": "Feature",
  "properties": {
    "iso:country":"US",
    "sg:address":"4606 Bridgeport Dr",
    "sg:city":"Garland",
    "sg:classifiers":[
        {
            "category":"Professional",
            "subcategory":"Business Services",
            "type":"Services"
        }
    ],
    "sg:phone":"+1 972 226 6535",
    "sg:postcode":"75043",
    "sg:province":"TX",
    "sg:tags":[
        "sales",
        "estate"
    ],
    "wof:name":"M & M Estate Liquidators",
    "wof:placetype":"venue"
},
  "geometry": {"coordinates":[-96.56195200000001,32.849497],"type":"Point"}
}