{
  "type": "Feature",
  "properties": {
    "iso:country":"US",
    "sg:address":"3361 Boyington Dr Ste 180",
    "sg:city":"Carrollton",
    "sg:classifiers":[
        {
            "category":"Banks & Credit Unions",
            "subcategory":"Financial Services",
            "type":"Services"
        }
    ],
    "sg:phone":"+1 972 726 7776",
    "sg:postcode":"75006",
    "sg:province":"TX",
    "sg:tags":[
        "card-merchant",
        "card"
    ],
    "wof:name":"Standard Payments",
    "wof:placetype":"venue"
},
  "geometry": {"coordinates":[-96.83923,32.965039],"type":"Point"}
}