{
  "type": "Feature",
  "properties": {
    "iso:country":"US",
    "sg:address":"3708 S Sugar Rd",
    "sg:city":"Edinburg",
    "sg:classifiers":[
        {
            "category":"Restaurant",
            "type":"Food & Drink"
        }
    ],
    "sg:phone":"+1 956 287 2873",
    "sg:postcode":"78539",
    "sg:province":"TX",
    "wof:name":"Taqueria LA Casita",
    "wof:placetype":"venue"
},
  "geometry": {"coordinates":[-98.184225,26.265814],"type":"Point"}
}