{
  "type": "Feature",
  "properties": {
    "iso:country":"US",
    "sg:address":"6004 Tasajillo Trl",
    "sg:city":"Austin",
    "sg:classifiers":[
        {
            "category":"Professional",
            "subcategory":"Business Services",
            "type":"Services"
        }
    ],
    "sg:phone":"+1 512 301 0496",
    "sg:postcode":"78739",
    "sg:province":"TX",
    "sg:tags":[
        "arbitration"
    ],
    "wof:name":"Carol A Buls Mediator",
    "wof:placetype":"venue"
},
  "geometry": {"coordinates":[-97.883893,30.195111],"type":"Point"}
}