{
  "type": "Feature",
  "properties": {
    "iso:country":"US",
    "sg:address":"1905 W 15th St",
    "sg:city":"Plano",
    "sg:classifiers":[
        {
            "category":"Personal",
            "subcategory":"Beauty Salon",
            "type":"Services"
        }
    ],
    "sg:phone":"+1 972 578 1140",
    "sg:postcode":"75075",
    "sg:province":"TX",
    "sg:tags":[
        "shop"
    ],
    "wof:name":"Classic Cuts",
    "wof:placetype":"venue"
},
  "geometry": {"coordinates":[-96.728561,33.019607],"type":"Point"}
}