{
  "type": "Feature",
  "properties": {
    "iso:country":"US",
    "sg:address":"2502 N 1st St",
    "sg:city":"Abilene",
    "sg:classifiers":[
        {
            "category":"Food & Beverages",
            "subcategory":"Liquor & Beverages",
            "type":"Retail Goods"
        }
    ],
    "sg:phone":"+1 325 677 2971",
    "sg:postcode":"79603",
    "sg:province":"TX",
    "sg:tags":[
        "alcoholic"
    ],
    "wof:name":"Big Country Liquor",
    "wof:placetype":"venue"
},
  "geometry": {"coordinates":[-99.753806,32.450728],"type":"Point"}
}