{
  "type": "Feature",
  "properties": {
    "iso:country":"US",
    "sg:address":"6220 Jefferson Blvd",
    "sg:city":"Groves",
    "sg:classifiers":[
        {
            "category":"Personal",
            "subcategory":"Beauty Salon",
            "type":"Services"
        }
    ],
    "sg:phone":"+1 409 962 5576",
    "sg:postcode":"77619",
    "sg:province":"TX",
    "sg:tags":[
        "shop"
    ],
    "wof:name":"Visions Of Summer",
    "wof:placetype":"venue"
},
  "geometry": {"coordinates":[-93.92091499999999,29.949886],"type":"Point"}
}