{
  "type": "Feature",
  "properties": {
    "iso:country":"US",
    "sg:address":"500 Main St",
    "sg:city":"Fort Worth",
    "sg:classifiers":[
        {
            "category":"Professional",
            "subcategory":"Lawyer & Legal Services",
            "type":"Services"
        }
    ],
    "sg:phone":"+1 817 877 3666",
    "sg:postcode":"76102",
    "sg:province":"TX",
    "sg:tags":[
        "attorney"
    ],
    "sg:website":"www.murphymahon.com",
    "wof:name":"Murphy Mahon Keffler & Farrier",
    "wof:placetype":"venue"
},
  "geometry": {"coordinates":[-97.33072300000001,32.753897],"type":"Point"}
}