{
  "type": "Feature",
  "properties": {
    "iso:country":"US",
    "sg:address":"208 Briarglen Dr",
    "sg:city":"Cedar Hill",
    "sg:classifiers":[
        {
            "category":"Professional",
            "subcategory":"Computer Services",
            "type":"Services"
        }
    ],
    "sg:phone":"+1 214 680 3094",
    "sg:postcode":"75104",
    "sg:province":"TX",
    "sg:tags":[
        "related"
    ],
    "wof:name":"Edmouse Co",
    "wof:placetype":"venue"
},
  "geometry": {"coordinates":[-96.94438,32.570051],"type":"Point"}
}