{
  "type": "Feature",
  "properties": {
    "iso:country":"US",
    "sg:address":"2600 S Good Latimer Expy",
    "sg:city":"Dallas",
    "sg:classifiers":[
        {
            "category":"Shopping",
            "subcategory":"Crafts & Fabrics",
            "type":"Retail Goods"
        },
        {
            "category":"Wholesale",
            "subcategory":"Home Furnishings",
            "type":"Manufacturing & Wholesale Goods"
        }
    ],
    "sg:phone":"+1 972 288 2144",
    "sg:postcode":"75215",
    "sg:province":"TX",
    "sg:tags":[
        "fabrics-wholesale",
        "upholstery",
        "manufacturer"
    ],
    "wof:name":"Oakes Distributing Co",
    "wof:placetype":"venue"
},
  "geometry": {"coordinates":[-96.776222,32.769409],"type":"Point"}
}