{
  "type": "Feature",
  "properties": {
    "iso:country":"US",
    "sg:address":"2100 N Greenville Ave Ste 100",
    "sg:city":"Richardson",
    "sg:phone":"+1 888 352 0065",
    "sg:postcode":"75082",
    "sg:province":"TX",
    "sg:website":"http://dallas.citysearch.com/profile/external/603556882/richardson_tx/pole_iticians_fitness_studio.html?publisher=yellowpages&reference_id=1&placement=ypwebsitemip",
    "wof:name":"Pole'iticians Fitness Studio",
    "wof:placetype":"venue"
},
  "geometry": {"coordinates":[-96.709763,32.977859],"type":"Point"}
}