{
  "type": "Feature",
  "properties": {
    "iso:country":"US",
    "sg:address":"3636 Bee Caves Rd",
    "sg:city":"Austin",
    "sg:classifiers":[
        {
            "category":"Government",
            "subcategory":"Fire Station",
            "type":"Public Place"
        }
    ],
    "sg:phone":"+1 512 327 2780",
    "sg:postcode":"78746",
    "sg:province":"TX",
    "sg:tags":[
        "department"
    ],
    "wof:name":"Westlake Fire Dept",
    "wof:placetype":"venue"
},
  "geometry": {"coordinates":[-97.80728000000001,30.280004],"type":"Point"}
}