{
  "type": "Feature",
  "properties": {
    "iso:country":"US",
    "sg:address":"20034 Shady Dr",
    "sg:city":"Chandler",
    "sg:classifiers":[
        {
            "category":"Utilities",
            "subcategory":"Telephone",
            "type":"Services"
        }
    ],
    "sg:phone":"+1 903 849 3097",
    "sg:postcode":"75758",
    "sg:province":"TX",
    "sg:tags":[
        "communications"
    ],
    "wof:name":"Telephone Systems",
    "wof:placetype":"venue"
},
  "geometry": {"coordinates":[-95.51612,32.193836],"type":"Point"}
}