{
  "type": "Feature",
  "properties": {
    "iso:country":"US",
    "sg:address":"3900 Cedar Springs Rd",
    "sg:city":"Dallas",
    "sg:classifiers":[
        {
            "category":"Shopping",
            "subcategory":"Gifts & Souvenirs",
            "type":"Retail Goods"
        }
    ],
    "sg:phone":"+1 214 522 6886",
    "sg:postcode":"75219",
    "sg:province":"TX",
    "sg:tags":[
        "shop",
        "jewelry"
    ],
    "sg:website":"www.nuvodallas.com/",
    "wof:name":"Nuvo",
    "wof:placetype":"venue"
},
  "geometry": {"coordinates":[-96.80999799999999,32.8102],"type":"Point"}
}