{
  "type": "Feature",
  "properties": {
    "iso:country":"US",
    "sg:address":"1229 W 7th Ave",
    "sg:city":"Corsicana",
    "sg:classifiers":[
        {
            "category":"Banks & Credit Unions",
            "subcategory":"Bank",
            "type":"Services"
        }
    ],
    "sg:phone":"+1 903 874 5300",
    "sg:postcode":"75110",
    "sg:province":"TX",
    "sg:tags":[
        "cashing",
        "check"
    ],
    "wof:name":"PDQ Cash",
    "wof:placetype":"venue"
},
  "geometry": {"coordinates":[-96.473984,32.086283],"type":"Point"}
}