{
  "type": "Feature",
  "properties": {
    "iso:country":"US",
    "sg:address":"7602 Leather Market St",
    "sg:city":"Houston",
    "sg:classifiers":[
        {
            "category":"Social Services",
            "subcategory":"Child Care",
            "type":"Services"
        }
    ],
    "sg:phone":"+1 713 856 8116",
    "sg:postcode":"77064",
    "sg:province":"TX",
    "sg:tags":[
        "day"
    ],
    "wof:name":"Scooter Sblngs Chrstn Chldcare",
    "wof:placetype":"venue"
},
  "geometry": {"coordinates":[-95.509687,29.902051],"type":"Point"}
}