{
  "type": "Feature",
  "properties": {
    "iso:country":"US",
    "sg:address":"6624 Watauga Rd",
    "sg:city":"Watauga",
    "sg:classifiers":[
        {
            "category":"Banks & Credit Unions",
            "subcategory":"Bank",
            "type":"Services"
        },
        {
            "category":"Banks & Credit Unions",
            "subcategory":"Financial Services",
            "type":"Services"
        }
    ],
    "sg:phone":"+1 817 788 7650",
    "sg:postcode":"76148",
    "sg:province":"TX",
    "sg:tags":[
        "saving",
        "loan",
        "commercial"
    ],
    "sg:website":"https://www.chase.com/",
    "wof:name":"Chase",
    "wof:placetype":"venue"
},
  "geometry": {"coordinates":[-97.240686,32.860423],"type":"Point"}
}