{
  "type": "Feature",
  "properties": {
    "iso:country":"US",
    "sg:address":"13900 N I-35",
    "sg:city":"Austin",
    "sg:classifiers":[
        {
            "category":"Arts & Performance",
            "subcategory":"Arts Center",
            "type":"Entertainment"
        },
        {
            "category":"Social Services",
            "subcategory":"Child Care",
            "type":"Services"
        },
        {
            "category":"Sports & Exercise",
            "subcategory":"Playing Field",
            "type":"Entertainment"
        }
    ],
    "sg:phone":"+1 512 251 2439",
    "sg:postcode":"78728",
    "sg:province":"TX",
    "sg:tags":[
        "performing",
        "instruction",
        "day",
        "fitness"
    ],
    "sg:website":"www.capgym.com/",
    "wof:name":"Capital Gymnastics",
    "wof:placetype":"venue"
},
  "geometry": {"coordinates":[-97.67213099999999,30.427896],"type":"Point"}
}