{
  "type": "Feature",
  "properties": {
    "iso:country":"US",
    "sg:address":"200 S Grants Ln",
    "sg:city":"Fort Worth",
    "sg:classifiers":[
        {
            "category":"Professional",
            "type":"Services"
        }
    ],
    "sg:phone":"+1 817 367 3868",
    "sg:postcode":"76108",
    "sg:province":"TX",
    "wof:name":"G & J Custom Millwork",
    "wof:placetype":"venue"
},
  "geometry": {"coordinates":[-97.44604099999999,32.758189],"type":"Point"}
}