{
  "type": "Feature",
  "properties": {
    "iso:country":"US",
    "sg:address":"411 S High St",
    "sg:city":"Longview",
    "sg:classifiers":[
        {
            "category":"Wholesale",
            "subcategory":"Office Equipment",
            "type":"Manufacturing & Wholesale Goods"
        },
        {
            "category":"Shopping",
            "subcategory":"Computers & Home Electronics",
            "type":"Retail Goods"
        },
        {
            "category":"Government",
            "subcategory":"Post Office",
            "type":"Public Place"
        }
    ],
    "sg:phone":"+1 903 758 7500",
    "sg:postcode":"75601",
    "sg:province":"TX",
    "sg:tags":[
        "scanning",
        "printer",
        "supply",
        "list",
        "mailing",
        "plotting"
    ],
    "wof:name":"Country Mailer",
    "wof:placetype":"venue"
},
  "geometry": {"coordinates":[-94.744086,32.490189],"type":"Point"}
}