{
  "type": "Feature",
  "properties": {
    "iso:country":"US",
    "sg:address":"200 N Ballard St",
    "sg:city":"Pampa",
    "sg:classifiers":[
        {
            "category":"Social Services",
            "type":"Services"
        }
    ],
    "sg:phone":"+1 806 669 1001",
    "sg:postcode":"79065",
    "sg:province":"TX",
    "sg:tags":[
        "organization",
        "welfare"
    ],
    "wof:name":"United Way",
    "wof:placetype":"venue"
},
  "geometry": {"coordinates":[-100.961583,35.538236],"type":"Point"}
}