{
  "type": "Feature",
  "properties": {
    "iso:country":"US",
    "sg:address":"5504 N Lakeside Hills Ct",
    "sg:city":"Granbury",
    "sg:classifiers":[
        {
            "category":"Wholesale",
            "subcategory":"Fruits & Vegetables",
            "type":"Manufacturing & Wholesale Goods"
        }
    ],
    "sg:phone":"+1 817 573 7554",
    "sg:postcode":"76048",
    "sg:province":"TX",
    "wof:name":"Anawan Inc",
    "wof:placetype":"venue"
},
  "geometry": {"coordinates":[-97.72944099999999,32.397124],"type":"Point"}
}