{
  "type": "Feature",
  "properties": {
    "iso:country":"US",
    "sg:address":"3421 Chihuahua Ave",
    "sg:city":"Dallas",
    "sg:classifiers":[
        {
            "category":"Organizations",
            "subcategory":"Religious Organization",
            "type":"Services"
        }
    ],
    "sg:phone":"+1 214 742 3825",
    "sg:postcode":"75212",
    "sg:province":"TX",
    "wof:name":"Greater Mt Hebron Miss Baptist",
    "wof:placetype":"venue"
},
  "geometry": {"coordinates":[-96.845685,32.784743],"type":"Point"}
}