{
  "type": "Feature",
  "properties": {
    "iso:country":"US",
    "sg:address":"4414 Julian St",
    "sg:city":"Houston",
    "sg:classifiers":[
        {
            "category":"Shopping",
            "subcategory":"Discount & Variety Stores",
            "type":"Retail Goods"
        }
    ],
    "sg:phone":"+1 713 301 0591",
    "sg:postcode":"77009",
    "sg:province":"TX",
    "sg:tags":[
        "merchandise",
        "general"
    ],
    "wof:name":"Alejandra M Gutierrez Retail",
    "wof:placetype":"venue"
},
  "geometry": {"coordinates":[-95.382206,29.796927],"type":"Point"}
}