{
  "type": "Feature",
  "properties": {
    "iso:country":"US",
    "sg:address":"1111 S Saint Marys St",
    "sg:city":"San Antonio",
    "sg:classifiers":[
        {
            "category":"Shopping",
            "subcategory":"Music",
            "type":"Retail Goods"
        }
    ],
    "sg:phone":"+1 210 212 9373",
    "sg:postcode":"78210",
    "sg:province":"TX",
    "wof:name":"Planet of Tapes",
    "wof:placetype":"venue"
},
  "geometry": {"coordinates":[-98.48817699999999,29.411409],"type":"Point"}
}