{
  "type": "Feature",
  "properties": {
    "iso:country":"US",
    "sg:address":"10006 Neuens Rd",
    "sg:city":"Houston",
    "sg:classifiers":[
        {
            "category":"Shopping",
            "subcategory":"Computers & Home Electronics",
            "type":"Retail Goods"
        }
    ],
    "sg:phone":"+1 713 465 4985",
    "sg:postcode":"77080",
    "sg:province":"TX",
    "sg:tags":[
        "equipment",
        "dealer"
    ],
    "wof:name":"Computers Alink",
    "wof:placetype":"venue"
},
  "geometry": {"coordinates":[-95.54508,29.806082],"type":"Point"}
}