{
  "type": "Feature",
  "properties": {
    "iso:country":"US",
    "sg:address":"8650 S Braeswood Blvd",
    "sg:city":"Houston",
    "sg:classifiers":[
        {
            "category":"Communications",
            "type":"Services"
        }
    ],
    "sg:phone":"+1 713 777 0108",
    "sg:postcode":"77031",
    "sg:province":"TX",
    "sg:tags":[
        "equipment",
        "paging",
        "signaling"
    ],
    "wof:name":"Apollo Gold & Pagers",
    "wof:placetype":"venue"
},
  "geometry": {"coordinates":[-95.529499,29.671402],"type":"Point"}
}