{
  "type": "Feature",
  "properties": {
    "iso:country":"US",
    "sg:address":"16301 County Line Rd",
    "sg:city":"Elgin",
    "sg:classifiers":[
        {
            "category":"Professional",
            "subcategory":"Detective & Security Services",
            "type":"Services"
        }
    ],
    "sg:phone":"+1 512 285 3503",
    "sg:postcode":"78621",
    "sg:province":"TX",
    "sg:tags":[
        "information",
        "bureau"
    ],
    "wof:name":"Soil And Groundwater Services, Inc.",
    "wof:placetype":"venue"
},
  "geometry": {"coordinates":[-97.38226299999999,30.39946],"type":"Point"}
}