{
  "type": "Feature",
  "properties": {
    "iso:country":"US",
    "sg:address":"1775 N Loop 336 E Suite 10",
    "sg:city":"Conroe",
    "sg:classifiers":[
        {
            "category":"Utilities",
            "subcategory":"Water",
            "type":"Services"
        }
    ],
    "sg:phone":"+1 936 788 2100",
    "sg:postcode":"77301",
    "sg:province":"TX",
    "sg:tags":[
        "equipment",
        "conditioning",
        "softening"
    ],
    "sg:website":"http://www.csswater.com",
    "wof:name":"Clear Solution Services",
    "wof:placetype":"venue"
},
  "geometry": {"coordinates":[-95.42012800000001,30.337442],"type":"Point"}
}