{
  "type": "Feature",
  "properties": {
    "iso:country":"US",
    "sg:address":"5415 Winding Ridge Dr",
    "sg:city":"Spring",
    "sg:classifiers":[
        {
            "category":"Real Estate",
            "subcategory":"Real Estate Agent",
            "type":"Services"
        }
    ],
    "sg:phone":"+1 281 379 2219",
    "sg:postcode":"77379",
    "sg:province":"TX",
    "wof:name":"Steve & Elyse Ernst",
    "wof:placetype":"venue"
},
  "geometry": {"coordinates":[-95.504312,30.037698],"type":"Point"}
}