{
  "type": "Feature",
  "properties": {
    "iso:country":"US",
    "sg:address":"112 East St",
    "sg:city":"Hutto",
    "sg:classifiers":[
        {
            "category":"Personal",
            "subcategory":"Nail Salon",
            "type":"Services"
        }
    ],
    "sg:phone":"+1 512 846 2292",
    "sg:postcode":"78634",
    "sg:province":"TX",
    "wof:name":"Rose Nails",
    "wof:placetype":"venue"
},
  "geometry": {"coordinates":[-97.547057,30.543102],"type":"Point"}
}