{
  "type": "Feature",
  "properties": {
    "iso:country":"US",
    "sg:address":"1925 Dallas Pkwy",
    "sg:city":"Plano",
    "sg:classifiers":[
        {
            "category":"Autos & Motor Vehicles",
            "subcategory":"Fuel & Gas Station",
            "type":"Retail Goods"
        }
    ],
    "sg:phone":"+1 972 250 2822",
    "sg:postcode":"75093",
    "sg:province":"TX",
    "sg:tags":[
        "oil"
    ],
    "wof:name":"Park Chevron",
    "wof:placetype":"venue"
},
  "geometry": {"coordinates":[-96.82965799999999,33.02775],"type":"Point"}
}