{
  "type": "Feature",
  "properties": {
    "iso:country":"US",
    "sg:address":"2424 Texoma Pkwy",
    "sg:city":"Sherman",
    "sg:classifiers":[
        {
            "category":"Building & Trades",
            "subcategory":"Construction",
            "type":"Services"
        }
    ],
    "sg:phone":"+1 903 819 0174",
    "sg:postcode":"75090",
    "sg:province":"TX",
    "sg:tags":[
        "house"
    ],
    "wof:name":"Tip Top Construction",
    "wof:placetype":"venue"
},
  "geometry": {"coordinates":[-96.596655,33.665108],"type":"Point"}
}