{
  "type": "Feature",
  "properties": {
    "iso:country":"US",
    "sg:address":"13150 Bissonnet St",
    "sg:city":"Houston",
    "sg:classifiers":[
        {
            "category":"Shopping",
            "subcategory":"Gifts & Souvenirs",
            "type":"Retail Goods"
        }
    ],
    "sg:phone":"+1 281 568 1415",
    "sg:postcode":"77099",
    "sg:province":"TX",
    "sg:tags":[
        "shop"
    ],
    "wof:name":"Bami Merchandise Unlimited",
    "wof:placetype":"venue"
},
  "geometry": {"coordinates":[-95.61411099999999,29.681205],"type":"Point"}
}