{
  "type": "Feature",
  "properties": {
    "iso:country":"US",
    "sg:address":"7104 Dallas Dr",
    "sg:city":"Austin",
    "sg:classifiers":[
        {
            "category":"Professional",
            "type":"Services"
        }
    ],
    "sg:phone":"+1 512 331 8482",
    "sg:postcode":"78729",
    "sg:province":"TX",
    "wof:name":"Michael S Perkins",
    "wof:placetype":"venue"
},
  "geometry": {"coordinates":[-97.75139299999999,30.447202],"type":"Point"}
}