{
  "type": "Feature",
  "properties": {
    "iso:country":"US",
    "sg:address":"6405 25th St",
    "sg:city":"Lubbock",
    "sg:classifiers":[
        {
            "category":"Building & Trades",
            "subcategory":"Construction",
            "type":"Services"
        }
    ],
    "sg:phone":"+1 806 785 8782",
    "sg:postcode":"79407",
    "sg:province":"TX",
    "sg:tags":[
        "contractor"
    ],
    "wof:name":"All Around Fence",
    "wof:placetype":"venue"
},
  "geometry": {"coordinates":[-101.957052,33.571485],"type":"Point"}
}