{
  "type": "Feature",
  "properties": {
    "iso:country":"US",
    "sg:address":"607 Westford St",
    "sg:city":"Houston",
    "sg:classifiers":[
        {
            "category":"Building & Trades",
            "subcategory":"Cleaning & Sanitation",
            "type":"Services"
        }
    ],
    "sg:phone":"+1 713 691 0681",
    "sg:postcode":"77022",
    "sg:province":"TX",
    "sg:tags":[
        "maintenance"
    ],
    "wof:name":"Dave Hughes Yard Maintenance",
    "wof:placetype":"venue"
},
  "geometry": {"coordinates":[-95.361341,29.824186],"type":"Point"}
}