{
  "type": "Feature",
  "properties": {
    "iso:country":"US",
    "sg:address":"2301 N Millbend Dr",
    "sg:city":"Spring",
    "sg:classifiers":[
        {
            "category":"Food & Beverages",
            "subcategory":"Liquor & Beverages",
            "type":"Retail Goods"
        }
    ],
    "sg:phone":"+1 281 364 6278",
    "sg:postcode":"77380",
    "sg:province":"TX",
    "sg:tags":[
        "alcoholic"
    ],
    "wof:name":"Beverage Operations Inc",
    "wof:placetype":"venue"
},
  "geometry": {"coordinates":[-95.47377299999999,30.148653],"type":"Point"}
}