{
  "type": "Feature",
  "properties": {
    "iso:country":"US",
    "sg:address":"400 N Timberland Dr",
    "sg:city":"Lufkin",
    "sg:classifiers":[
        {
            "category":"Shopping",
            "subcategory":"Department Store",
            "type":"Retail Goods"
        }
    ],
    "sg:phone":"+1 936 634 0382",
    "sg:postcode":"75901",
    "sg:province":"TX",
    "sg:website":"www.samsclub.com",
    "wof:name":"Sam's Club",
    "wof:placetype":"venue"
},
  "geometry": {"coordinates":[-94.71802599999999,31.341849],"type":"Point"}
}