{
  "type": "Feature",
  "properties": {
    "iso:country":"US",
    "sg:address":"151 Loop 64",
    "sg:city":"Dripping Springs",
    "sg:classifiers":[
        {
            "category":"Real Estate",
            "subcategory":"Real Estate Agent",
            "type":"Services"
        }
    ],
    "sg:phone":"+1 512 894 0039",
    "sg:postcode":"78620",
    "sg:province":"TX",
    "sg:tags":[
        "investment"
    ],
    "wof:name":"Carter Investments",
    "wof:placetype":"venue"
},
  "geometry": {"coordinates":[-98.08911000000001,30.192714],"type":"Point"}
}