{
  "type": "Feature",
  "properties": {
    "iso:country":"US",
    "sg:address":"1213 Juanita St",
    "sg:city":"Mesquite",
    "sg:classifiers":[
        {
            "category":"Retail",
            "subcategory":"Repair Shop",
            "type":"Services"
        }
    ],
    "sg:phone":"+1 972 289 5764",
    "sg:postcode":"75149",
    "sg:province":"TX",
    "wof:name":"Apex Appliance",
    "wof:placetype":"venue"
},
  "geometry": {"coordinates":[-96.620375,32.785321],"type":"Point"}
}