{
  "type": "Feature",
  "properties": {
    "iso:country":"US",
    "sg:address":"11571 FM 1294",
    "sg:city":"Shallowater",
    "sg:phone":"+1 806 873 3442",
    "sg:postcode":"79363",
    "sg:province":"TX",
    "sg:tags":[
        "wheat",
        "beef",
        "farm",
        "cattle",
        "feedlot",
        "cotton"
    ],
    "wof:name":"Donald Pair",
    "wof:placetype":"venue"
},
  "geometry": {"coordinates":[-102.073882,33.693873],"type":"Point"}
}