{
  "type": "Feature",
  "properties": {
    "iso:country":"US",
    "sg:address":"5925 Forest Ln",
    "sg:city":"Dallas",
    "sg:classifiers":[
        {
            "category":"Insurance",
            "subcategory":"Insurance Agent",
            "type":"Services"
        }
    ],
    "sg:phone":"+1 972 490 5682",
    "sg:postcode":"75230",
    "sg:province":"TX",
    "wof:name":"Farmers Insurance Group",
    "wof:placetype":"venue"
},
  "geometry": {"coordinates":[-96.80473000000001,32.909613],"type":"Point"}
}