{
  "type": "Feature",
  "properties": {
    "iso:country":"US",
    "sg:address":"1507 Charleston Cove",
    "sg:city":"Mesquite",
    "sg:classifiers":[
        {
            "category":"Shopping",
            "subcategory":"Catalog Store",
            "type":"Retail Goods"
        }
    ],
    "sg:phone":"+1 972 289 8182",
    "sg:postcode":"75149",
    "sg:province":"TX",
    "sg:tags":[
        "mail",
        "photography",
        "commercial",
        "house"
    ],
    "wof:name":"Kayco Tools Company",
    "wof:placetype":"venue"
},
  "geometry": {"coordinates":[-96.579561,32.763851],"type":"Point"}
}