{
  "type": "Feature",
  "properties": {
    "iso:country":"US",
    "sg:address":"1102 Wilbarger St",
    "sg:city":"Vernon",
    "sg:classifiers":[
        {
            "category":"Shopping",
            "subcategory":"Gifts & Souvenirs",
            "type":"Retail Goods"
        }
    ],
    "sg:phone":"+1 940 552 6604",
    "sg:postcode":"76384",
    "sg:province":"TX",
    "wof:name":"Lucilles Gift & Hobby Sh",
    "wof:placetype":"venue"
},
  "geometry": {"coordinates":[-99.277654,34.152892],"type":"Point"}
}