{
  "type": "Feature",
  "properties": {
    "iso:country":"US",
    "sg:address":"2300 Dillard St",
    "sg:city":"Fort Worth",
    "sg:classifiers":[
        {
            "category":"Education",
            "subcategory":"School",
            "type":"Public Place"
        }
    ],
    "sg:phone":"+1 817 531 6265",
    "sg:postcode":"76105",
    "sg:province":"TX",
    "sg:tags":[
        "elementary"
    ],
    "wof:name":"Maud I Logan Elementary School",
    "wof:placetype":"venue"
},
  "geometry": {"coordinates":[-97.242885,32.722796],"type":"Point"}
}