{
  "type": "Feature",
  "properties": {
    "iso:country":"US",
    "sg:address":"9805 Tellerson Ave",
    "sg:city":"Dallas",
    "sg:classifiers":[
        {
            "category":"Social Services",
            "subcategory":"Child Care",
            "type":"Services"
        }
    ],
    "sg:phone":"+1 214 327 1500",
    "sg:postcode":"75228",
    "sg:province":"TX",
    "sg:tags":[
        "day"
    ],
    "wof:name":"Oates Crossing",
    "wof:placetype":"venue"
},
  "geometry": {"coordinates":[-96.67457,32.822413],"type":"Point"}
}