{
  "type": "Feature",
  "properties": {
    "iso:country":"US",
    "sg:address":"6620 Harry Hines Blvd",
    "sg:city":"Dallas",
    "sg:classifiers":[
        {
            "category":"Professional",
            "type":"Services"
        }
    ],
    "sg:phone":"+1 214 366 3441",
    "sg:postcode":"75235",
    "sg:province":"TX",
    "wof:name":"Tob Ltd",
    "wof:placetype":"venue"
},
  "geometry": {"coordinates":[-96.851581,32.823231],"type":"Point"}
}