{
  "type": "Feature",
  "properties": {
    "iso:country":"US",
    "sg:address":"4011 Irving Blvd",
    "sg:city":"Dallas",
    "sg:classifiers":[
        {
            "category":"Retail",
            "subcategory":"Auto Repair",
            "type":"Services"
        }
    ],
    "sg:phone":"+1 214 630 6789",
    "sg:postcode":"75247",
    "sg:province":"TX",
    "sg:tags":[
        "body"
    ],
    "wof:name":"Jam Enterprises",
    "wof:placetype":"venue"
},
  "geometry": {"coordinates":[-96.88412700000001,32.808166],"type":"Point"}
}