{
  "type": "Feature",
  "properties": {
    "iso:country":"US",
    "sg:address":"1442 Gentle Bend Dr",
    "sg:city":"Missouri City",
    "sg:classifiers":[
        {
            "category":"Banks & Credit Unions",
            "subcategory":"Bank",
            "type":"Services"
        }
    ],
    "sg:phone":"+1 281 437 1071",
    "sg:postcode":"77489",
    "sg:province":"TX",
    "sg:tags":[
        "personal",
        "institution"
    ],
    "wof:name":"World Wide Credit Management",
    "wof:placetype":"venue"
},
  "geometry": {"coordinates":[-95.523867,29.593783],"type":"Point"}
}