{
  "type": "Feature",
  "properties": {
    "iso:country":"US",
    "sg:address":"3620 Woodchase Dr",
    "sg:city":"Houston",
    "sg:classifiers":[
        {
            "category":"Personal",
            "subcategory":"Beauty Salon",
            "type":"Services"
        }
    ],
    "sg:phone":"+1 713 780 0061",
    "sg:postcode":"77042",
    "sg:province":"TX",
    "wof:name":"Incredible Cuts",
    "wof:placetype":"venue"
},
  "geometry": {"coordinates":[-95.545692,29.724099],"type":"Point"}
}