{
  "type": "Feature",
  "properties": {
    "iso:country":"US",
    "sg:address":"10203 Plano Rd",
    "sg:city":"Dallas",
    "sg:classifiers":[
        {
            "category":"Professional",
            "type":"Services"
        }
    ],
    "sg:phone":"+1 214 348 6171",
    "sg:postcode":"75238",
    "sg:province":"TX",
    "sg:tags":[
        "establishment"
    ],
    "wof:name":"Coatings Alliance",
    "wof:placetype":"venue"
},
  "geometry": {"coordinates":[-96.700535,32.887561],"type":"Point"}
}