{
  "type": "Feature",
  "properties": {
    "iso:country":"US",
    "sg:address":"4314 Green Tree Ct",
    "sg:city":"Pasadena",
    "sg:classifiers":[
        {
            "category":"Professional",
            "subcategory":"Business Services",
            "type":"Services"
        }
    ],
    "sg:phone":"+1 832 860 8281",
    "sg:postcode":"77505",
    "sg:province":"TX",
    "wof:name":"Neatocreato Designs",
    "wof:placetype":"venue"
},
  "geometry": {"coordinates":[-95.12233000000001,29.643863],"type":"Point"}
}