{
  "type": "Feature",
  "properties": {
    "iso:country":"US",
    "sg:address":"1820 N Main St",
    "sg:city":"Houston",
    "sg:classifiers":[
        {
            "category":"Food & Beverages",
            "subcategory":"Groceries & Convenience Stores",
            "type":"Retail Goods"
        }
    ],
    "sg:phone":"+1 713 227 0814",
    "sg:postcode":"77009",
    "sg:province":"TX",
    "wof:name":"Super Mercado El Guaro",
    "wof:placetype":"venue"
},
  "geometry": {"coordinates":[-95.361397,29.775801],"type":"Point"}
}