{
  "type": "Feature",
  "properties": {
    "iso:country":"US",
    "sg:address":"2323 Lutcher Dr",
    "sg:city":"Orange",
    "sg:classifiers":[
        {
            "category":"Autos & Motor Vehicles",
            "subcategory":"Fuel & Gas Station",
            "type":"Retail Goods"
        }
    ],
    "sg:phone":"+1 409 883 4820",
    "sg:postcode":"77630",
    "sg:province":"TX",
    "sg:tags":[
        "station",
        "gasoline"
    ],
    "wof:name":"Chevron Mini Mart",
    "wof:placetype":"venue"
},
  "geometry": {"coordinates":[-93.74881999999999,30.120431],"type":"Point"}
}