{
  "type": "Feature",
  "properties": {
    "iso:country":"US",
    "sg:address":"22106 State Highway 71 W",
    "sg:city":"Spicewood",
    "sg:classifiers":[
        {
            "category":"Personal",
            "subcategory":"Beauty Salon",
            "type":"Services"
        }
    ],
    "sg:phone":"+1 512 264 2112",
    "sg:postcode":"78669",
    "sg:province":"TX",
    "sg:tags":[
        "hair",
        "stylist"
    ],
    "wof:name":"Hair By Hopie",
    "wof:placetype":"venue"
},
  "geometry": {"coordinates":[-98.07252099999999,30.367891],"type":"Point"}
}