{
  "type": "Feature",
  "properties": {
    "iso:country":"US",
    "sg:address":"855 Uvalde Rd Ste E",
    "sg:city":"Houston",
    "sg:classifiers":[
        {
            "category":"Health Services",
            "subcategory":"Chiropractor",
            "type":"Services"
        }
    ],
    "sg:phone":"+1 713 455 0323",
    "sg:postcode":"77015",
    "sg:province":"TX",
    "wof:name":"Hardin Shirley Dr DC",
    "wof:placetype":"venue"
},
  "geometry": {"coordinates":[-95.18665900000001,29.780799],"type":"Point"}
}