{
  "type": "Feature",
  "properties": {
    "iso:country":"US",
    "sg:address":"4925 Parkside Way",
    "sg:city":"Fort Worth",
    "sg:classifiers":[
        {
            "category":"Professional",
            "subcategory":"Research",
            "type":"Services"
        }
    ],
    "sg:phone":"+1 817 788 2105",
    "sg:postcode":"76137",
    "sg:province":"TX",
    "sg:tags":[
        "environmental",
        "ecological"
    ],
    "wof:name":"Aicklen Environmental Svc",
    "wof:placetype":"venue"
},
  "geometry": {"coordinates":[-97.27910199999999,32.875551],"type":"Point"}
}