{
  "type": "Feature",
  "properties": {
    "iso:country":"US",
    "sg:address":"630 Solo St",
    "sg:city":"San Antonio",
    "sg:classifiers":[
        {
            "category":"Building & Trades",
            "subcategory":"Construction",
            "type":"Services"
        }
    ],
    "sg:phone":"+1 210 481 3824",
    "sg:postcode":"78260",
    "sg:province":"TX",
    "sg:tags":[
        "water",
        "well",
        "drilling"
    ],
    "wof:name":"Bomax Industries Inc",
    "wof:placetype":"venue"
},
  "geometry": {"coordinates":[-98.50297399999999,29.685398],"type":"Point"}
}