{
  "type": "Feature",
  "properties": {
    "iso:country":"US",
    "sg:address":"22437 Fossil Path",
    "sg:city":"San Antonio",
    "sg:classifiers":[
        {
            "category":"Professional",
            "type":"Services"
        }
    ],
    "sg:phone":"+1 210 497 8644",
    "sg:postcode":"78261",
    "sg:province":"TX",
    "wof:name":"Jenny M Oconnor",
    "wof:placetype":"venue"
},
  "geometry": {"coordinates":[-98.417857,29.650089],"type":"Point"}
}