{
  "type": "Feature",
  "properties": {
    "iso:country":"US",
    "sg:address":"4810 East Fwy",
    "sg:city":"Baytown",
    "sg:classifiers":[
        {
            "category":"Shopping",
            "subcategory":"Clothing, Apparel, & Fashions",
            "type":"Retail Goods"
        }
    ],
    "sg:phone":"+1 281 421 1293",
    "sg:postcode":"77521",
    "sg:province":"TX",
    "sg:tags":[
        "shop",
        "bridal"
    ],
    "wof:name":"Brides Mart",
    "wof:placetype":"venue"
},
  "geometry": {"coordinates":[-94.98762600000001,29.803498],"type":"Point"}
}