{
  "type": "Feature",
  "properties": {
    "iso:country":"US",
    "sg:address":"319 E Austin St",
    "sg:city":"Troy",
    "sg:classifiers":[
        {
            "category":"Restaurant",
            "type":"Food & Drink"
        }
    ],
    "sg:phone":"+1 254 938 2185",
    "sg:postcode":"76579",
    "sg:province":"TX",
    "sg:tags":[
        "eating"
    ],
    "wof:name":"Tooters Bar B Que",
    "wof:placetype":"venue"
},
  "geometry": {"coordinates":[-97.300821,31.20043],"type":"Point"}
}