{
  "type": "Feature",
  "properties": {
    "iso:country":"US",
    "sg:address":"12823 Nyack Dr",
    "sg:city":"Houston",
    "sg:classifiers":[
        {
            "category":"Building & Trades",
            "subcategory":"Cleaning & Sanitation",
            "type":"Services"
        }
    ],
    "sg:phone":"+1 713 961 4403",
    "sg:postcode":"77089",
    "sg:province":"TX",
    "sg:tags":[
        "janitorial"
    ],
    "wof:name":"Ruben Vasquez",
    "wof:placetype":"venue"
},
  "geometry": {"coordinates":[-95.196855,29.593375],"type":"Point"}
}