{
  "type": "Feature",
  "properties": {
    "iso:country":"US",
    "sg:address":"202 W Twohig Ave",
    "sg:city":"San Angelo",
    "sg:classifiers":[
        {
            "category":"Professional",
            "subcategory":"Lawyer & Legal Services",
            "type":"Services"
        }
    ],
    "sg:phone":"+1 325 658 8993",
    "sg:postcode":"76903",
    "sg:province":"TX",
    "wof:name":"Layne R Turner Attorney",
    "wof:placetype":"venue"
},
  "geometry": {"coordinates":[-100.43997,31.46014],"type":"Point"}
}