{
  "type": "Feature",
  "properties": {
    "iso:country":"US",
    "sg:address":"5515 Ballenton Ln",
    "sg:city":"Austin",
    "sg:classifiers":[
        {
            "category":"Professional",
            "subcategory":"Management & Consulting",
            "type":"Services"
        }
    ],
    "sg:phone":"+1 512 301 6067",
    "sg:postcode":"78739",
    "sg:province":"TX",
    "sg:tags":[
        "business"
    ],
    "wof:name":"Celebrity Systems Consulting L",
    "wof:placetype":"venue"
},
  "geometry": {"coordinates":[-97.877729,30.192377],"type":"Point"}
}