{
  "type": "Feature",
  "properties": {
    "iso:country":"US",
    "sg:address":"620 Robin Ln",
    "sg:city":"Argyle",
    "sg:classifiers":[
        {
            "category":"Shopping",
            "subcategory":"Used Merchandise",
            "type":"Retail Goods"
        }
    ],
    "sg:phone":"+1 940 240 3156",
    "sg:postcode":"76226",
    "sg:province":"TX",
    "wof:name":"Robins Nest Antiques",
    "wof:placetype":"venue"
},
  "geometry": {"coordinates":[-97.200119,33.097233],"type":"Point"}
}