{
  "type": "Feature",
  "properties": {
    "iso:country":"US",
    "sg:address":"1001 Ayers St",
    "sg:city":"Corpus Christi",
    "sg:classifiers":[
        {
            "category":"Health Services",
            "subcategory":"Health Practitioner",
            "type":"Services"
        }
    ],
    "sg:phone":"+1 361 882 9010",
    "sg:postcode":"78404",
    "sg:province":"TX",
    "wof:name":"Sharon L Rogers PHD Inc",
    "wof:placetype":"venue"
},
  "geometry": {"coordinates":[-97.40016799999999,27.773733],"type":"Point"}
}