{
  "type": "Feature",
  "properties": {
    "iso:country":"US",
    "sg:address":"1115 State Hwy 80",
    "sg:city":"San Marcos",
    "sg:classifiers":[
        {
            "category":"Real Estate",
            "subcategory":"Surveying",
            "type":"Services"
        }
    ],
    "sg:phone":"+1 512 396 2270",
    "sg:postcode":"78666",
    "sg:province":"TX",
    "sg:tags":[
        "surveyor"
    ],
    "sg:website":"www.byrnsurvey.com",
    "wof:name":"Byrn & Assoc Inc",
    "wof:placetype":"venue"
},
  "geometry": {"coordinates":[-97.91425599999999,29.881226],"type":"Point"}
}