{
  "type": "Feature",
  "properties": {
    "iso:country":"US",
    "sg:address":"9819 Morningfield",
    "sg:city":"San Antonio",
    "sg:classifiers":[
        {
            "category":"Professional",
            "subcategory":"Management & Consulting",
            "type":"Services"
        }
    ],
    "sg:phone":"+1 210 639 4746",
    "sg:postcode":"78250",
    "sg:province":"TX",
    "wof:name":"Texas Logistics Solutions",
    "wof:placetype":"venue"
},
  "geometry": {"coordinates":[-98.68408100000001,29.515416],"type":"Point"}
}