{
  "type": "Feature",
  "properties": {
    "iso:country":"US",
    "sg:address":"1100 Callaghan Rd",
    "sg:city":"San Antonio",
    "sg:classifiers":[
        {
            "category":"Real Estate",
            "subcategory":"Real Estate Agent",
            "type":"Services"
        }
    ],
    "sg:phone":"+1 210 431 7330",
    "sg:postcode":"78228",
    "sg:province":"TX",
    "wof:name":"I Buy Houses",
    "wof:placetype":"venue"
},
  "geometry": {"coordinates":[-98.602695,29.441902],"type":"Point"}
}