{
  "type": "Feature",
  "properties": {
    "iso:country":"US",
    "sg:address":"101 W Adkins St",
    "sg:city":"Seagoville",
    "sg:classifiers":[
        {
            "category":"Professional",
            "subcategory":"Credit Reporting & Collection",
            "type":"Services"
        }
    ],
    "sg:phone":"+1 972 287 9283",
    "sg:postcode":"75159",
    "sg:province":"TX",
    "sg:tags":[
        "agency"
    ],
    "wof:name":"Maxam Recovery Svc",
    "wof:placetype":"venue"
},
  "geometry": {"coordinates":[-96.55301799999999,32.649043],"type":"Point"}
}