{
  "type": "Feature",
  "properties": {
    "iso:country":"US",
    "sg:address":"17390 Preston Road Suite 245",
    "sg:city":"Dallas",
    "sg:classifiers":[
        {
            "category":"Personal",
            "subcategory":"Beauty Salon",
            "type":"Services"
        }
    ],
    "sg:phone":"+1 972 991 4431",
    "sg:postcode":"75252",
    "sg:province":"TX",
    "sg:tags":[
        "spa"
    ],
    "sg:website":"www.salonjo-li.com",
    "wof:name":"Salon Jo-Li",
    "wof:placetype":"venue"
},
  "geometry": {"coordinates":[-96.80308100000001,32.987183],"type":"Point"}
}