{
  "type": "Feature",
  "properties": {
    "iso:country":"US",
    "sg:address":"8356 Sterling St",
    "sg:city":"Irving",
    "sg:classifiers":[
        {
            "category":"Health Services",
            "subcategory":"Medical Lab",
            "type":"Services"
        }
    ],
    "sg:phone":"+1 972 929 1100",
    "sg:postcode":"75063",
    "sg:province":"TX",
    "sg:tags":[
        "laboratory"
    ],
    "wof:name":"Draeger Safety Diagnostics Inc",
    "wof:placetype":"venue"
},
  "geometry": {"coordinates":[-97.012891,32.921514],"type":"Point"}
}