{
  "type": "Feature",
  "properties": {
    "iso:country":"US",
    "sg:address":"4922 Luella Ave",
    "sg:city":"Deer Park",
    "sg:classifiers":[
        {
            "category":"Professional",
            "subcategory":"Engineering",
            "type":"Services"
        }
    ],
    "sg:phone":"+1 281 479 5135",
    "sg:postcode":"77536",
    "sg:province":"TX",
    "wof:name":"Texas Coastal Surveying",
    "wof:placetype":"venue"
},
  "geometry": {"coordinates":[-95.113086,29.665227],"type":"Point"}
}