{
  "type": "Feature",
  "properties": {
    "iso:country":"US",
    "sg:address":"6800 Bleker St",
    "sg:city":"Houston",
    "sg:classifiers":[
        {
            "category":"Social Services",
            "subcategory":"Adult Care",
            "type":"Services"
        }
    ],
    "sg:phone":"+1 713 631 9100",
    "sg:postcode":"77016",
    "sg:province":"TX",
    "sg:tags":[
        "home",
        "residential"
    ],
    "wof:name":"Nixon Assisted Living - Hstn",
    "wof:placetype":"venue"
},
  "geometry": {"coordinates":[-95.33426,29.821278],"type":"Point"}
}