{
  "type": "Feature",
  "properties": {
    "iso:country":"US",
    "sg:address":"602 Everest St",
    "sg:city":"San Antonio",
    "sg:classifiers":[
        {
            "category":"Building & Trades",
            "subcategory":"Construction",
            "type":"Services"
        }
    ],
    "sg:phone":"+1 210 828 2739",
    "sg:postcode":"78209",
    "sg:province":"TX",
    "sg:tags":[
        "house",
        "contractor",
        "construct",
        "roofing"
    ],
    "wof:name":"River City Roofing & Rmdlg",
    "wof:placetype":"venue"
},
  "geometry": {"coordinates":[-98.47080200000001,29.509408],"type":"Point"}
}