{
  "type": "Feature",
  "properties": {
    "iso:country":"US",
    "sg:address":"406 W State Hwy 302",
    "sg:city":"Kermit",
    "sg:classifiers":[
        {
            "category":"Food & Beverages",
            "subcategory":"Liquor & Beverages",
            "type":"Retail Goods"
        }
    ],
    "sg:phone":"+1 432 586 9282",
    "sg:postcode":"79745",
    "sg:province":"TX",
    "wof:name":"Jimmy's Liquor",
    "wof:placetype":"venue"
},
  "geometry": {"coordinates":[-103.093633,31.845626],"type":"Point"}
}