{
  "type": "Feature",
  "properties": {
    "iso:country":"US",
    "sg:address":"1754 Co Rd 4698",
    "sg:city":"Boyd",
    "sg:classifiers":[
        {
            "category":"Building & Trades",
            "subcategory":"Plumbing",
            "type":"Services"
        }
    ],
    "sg:phone":"+1 940 433 2534",
    "sg:postcode":"76023",
    "sg:province":"TX",
    "sg:tags":[
        "plumbing",
        "contractor"
    ],
    "wof:name":"Coplen Plumbing",
    "wof:placetype":"venue"
},
  "geometry": {"coordinates":[-97.63328199999999,33.05623],"type":"Point"}
}