{
  "type": "Feature",
  "properties": {
    "iso:country":"US",
    "sg:address":"1835 Co Rd 319",
    "sg:city":"Terrell",
    "sg:classifiers":[
        {
            "category":"Building & Trades",
            "subcategory":"Construction",
            "type":"Services"
        }
    ],
    "sg:phone":"+1 972 563 3366",
    "sg:postcode":"75161",
    "sg:province":"TX",
    "wof:name":"Stone Solutions",
    "wof:placetype":"venue"
},
  "geometry": {"coordinates":[-96.236372,32.754855],"type":"Point"}
}