{
  "type": "Feature",
  "properties": {
    "iso:country":"US",
    "sg:address":"202 N 5th St",
    "sg:city":"Robstown",
    "sg:classifiers":[
        {
            "category":"Retail",
            "subcategory":"Auto Repair",
            "type":"Services"
        }
    ],
    "sg:phone":"+1 361 387 5438",
    "sg:postcode":"78380",
    "sg:province":"TX",
    "sg:tags":[
        "repairing",
        "automobile"
    ],
    "wof:name":"Hernandez Auto Svc",
    "wof:placetype":"venue"
},
  "geometry": {"coordinates":[-97.663273,27.790367],"type":"Point"}
}