{
  "type": "Feature",
  "properties": {
    "iso:country":"US",
    "sg:address":"1901 Ben Ficklin Rd",
    "sg:city":"San Angelo",
    "sg:classifiers":[
        {
            "category":"Personal",
            "subcategory":"Beauty Salon",
            "type":"Services"
        }
    ],
    "sg:phone":"+1 325 655 8434",
    "sg:postcode":"76903",
    "sg:province":"TX",
    "wof:name":"Nancy's Hair & Nail Salon",
    "wof:placetype":"venue"
},
  "geometry": {"coordinates":[-100.440253,31.440648],"type":"Point"}
}