{
  "type": "Feature",
  "properties": {
    "iso:country":"US",
    "sg:address":"3228 Industrial Dr",
    "sg:city":"Wichita Falls",
    "sg:classifiers":[
        {
            "category":"Professional",
            "subcategory":"Business Services",
            "type":"Services"
        }
    ],
    "sg:phone":"+1 940 723 1744",
    "sg:postcode":"76306",
    "sg:province":"TX",
    "wof:name":"Kids Korner Gift Shoppes",
    "wof:placetype":"venue"
},
  "geometry": {"coordinates":[-98.53475899999999,33.928767],"type":"Point"}
}