{
  "type": "Feature",
  "properties": {
    "iso:country":"US",
    "sg:address":"1139 Industrial Dr E",
    "sg:city":"Sulphur Springs",
    "sg:classifiers":[
        {
            "category":"Organizations",
            "subcategory":"Religious Organization",
            "type":"Services"
        }
    ],
    "sg:phone":"+1 903 885 2868",
    "sg:postcode":"75482",
    "sg:province":"TX",
    "sg:tags":[
        "church"
    ],
    "sg:website":"www.rehobothonline.org",
    "wof:name":"Rehoboth Baptist Assocation",
    "wof:placetype":"venue"
},
  "geometry": {"coordinates":[-95.57682800000001,33.132021],"type":"Point"}
}