{
  "type": "Feature",
  "properties": {
    "iso:country":"US",
    "sg:address":"3015 NW 30th St",
    "sg:city":"Fort Worth",
    "sg:classifiers":[
        {
            "category":"Retail",
            "subcategory":"Auto Repair",
            "type":"Services"
        }
    ],
    "sg:phone":"+1 817 988 5344",
    "sg:postcode":"76106",
    "sg:province":"TX",
    "sg:tags":[
        "general"
    ],
    "wof:name":"Amvo Automotive",
    "wof:placetype":"venue"
},
  "geometry": {"coordinates":[-97.379559,32.805909],"type":"Point"}
}