{
  "type": "Feature",
  "properties": {
    "iso:country":"US",
    "sg:address":"5939 Harry Hines Blvd Ste 845",
    "sg:city":"Dallas",
    "sg:classifiers":[
        {
            "category":"Health Services",
            "subcategory":"Doctor",
            "type":"Services"
        }
    ],
    "sg:phone":"+1 214 389 7806",
    "sg:postcode":"75235",
    "sg:province":"TX",
    "wof:name":"Valerie Laurel Liao MD",
    "wof:placetype":"venue"
},
  "geometry": {"coordinates":[-96.844956,32.817793],"type":"Point"}
}