{
  "type": "Feature",
  "properties": {
    "iso:country":"US",
    "sg:address":"2210 Clark Ave",
    "sg:city":"San Antonio",
    "sg:classifiers":[
        {
            "category":"Personal",
            "subcategory":"Beauty Salon",
            "type":"Services"
        }
    ],
    "sg:phone":"+1 210 333 4810",
    "sg:postcode":"78210",
    "sg:province":"TX",
    "wof:name":"Cutting Edge Hair Design",
    "wof:placetype":"venue"
},
  "geometry": {"coordinates":[-98.448255,29.391723],"type":"Point"}
}