{
  "type": "Feature",
  "properties": {
    "iso:country":"US",
    "sg:address":"4005 Brookside Dr",
    "sg:city":"Bedford",
    "sg:classifiers":[
        {
            "category":"Wholesale",
            "subcategory":"Vending Machines",
            "type":"Manufacturing & Wholesale Goods"
        }
    ],
    "sg:phone":"+1 817 283 6956",
    "sg:postcode":"76021",
    "sg:province":"TX",
    "sg:tags":[
        "operator"
    ],
    "wof:name":"Ridway Vending",
    "wof:placetype":"venue"
},
  "geometry": {"coordinates":[-97.134097,32.866066],"type":"Point"}
}