{
  "type": "Feature",
  "properties": {
    "iso:country":"US",
    "sg:address":"2230 Chapel Downs Dr",
    "sg:city":"Arlington",
    "sg:classifiers":[
        {
            "category":"Professional",
            "subcategory":"Management & Consulting",
            "type":"Services"
        }
    ],
    "sg:phone":"+1 817 417 7372",
    "sg:postcode":"76017",
    "sg:province":"TX",
    "wof:name":"Mg Business Services",
    "wof:placetype":"venue"
},
  "geometry": {"coordinates":[-97.144458,32.649924],"type":"Point"}
}