{
  "type": "Feature",
  "properties": {
    "iso:country":"US",
    "sg:address":"4985 Morris Ave",
    "sg:city":"Addison",
    "sg:classifiers":[
        {
            "category":"Real Estate",
            "subcategory":"Architect",
            "type":"Services"
        }
    ],
    "sg:phone":"+1 972 788 4141",
    "sg:postcode":"75001",
    "sg:province":"TX",
    "wof:name":"Archimatrix",
    "wof:placetype":"venue"
},
  "geometry": {"coordinates":[-96.824057,32.962792],"type":"Point"}
}