{
  "type": "Feature",
  "properties": {
    "iso:country":"US",
    "sg:address":"611 Fabrication St",
    "sg:city":"Dallas",
    "sg:classifiers":[
        {
            "category":"Wholesale",
            "subcategory":"Non-durable Goods",
            "type":"Manufacturing & Wholesale Goods"
        }
    ],
    "sg:phone":"+1 214 747 6251",
    "sg:postcode":"75212",
    "sg:province":"TX",
    "wof:name":"Town Planner",
    "wof:placetype":"venue"
},
  "geometry": {"coordinates":[-96.834475,32.776261],"type":"Point"}
}