{
  "type": "Feature",
  "properties": {
    "iso:country":"US",
    "sg:address":"1127 Judson Rd Ste 233",
    "sg:city":"Longview",
    "sg:classifiers":[
        {
            "category":"Professional",
            "subcategory":"Accounting & Tax Preparation",
            "type":"Services"
        }
    ],
    "sg:phone":"+1 903 758 0648",
    "sg:postcode":"75601",
    "sg:province":"TX",
    "sg:tags":[
        "bookkeeping",
        "return",
        "accountants-certified",
        "preparation-business",
        "public"
    ],
    "sg:website":"http://www.henrypeters.com",
    "wof:name":"Henry & Peters, P.C.",
    "wof:placetype":"venue"
},
  "geometry": {"coordinates":[-94.73822,32.509518],"type":"Point"}
}