{
  "type": "Feature",
  "properties": {
    "iso:country":"US",
    "sg:address":"1107 E Central Ave",
    "sg:city":"Comanche",
    "sg:classifiers":[
        {
            "category":"Restaurant",
            "type":"Food & Drink"
        }
    ],
    "sg:phone":"+1 325 356 3454",
    "sg:postcode":"76442",
    "sg:province":"TX",
    "sg:tags":[
        "eating"
    ],
    "wof:name":"Ejs Barbeque",
    "wof:placetype":"venue"
},
  "geometry": {"coordinates":[-98.591218,31.897789],"type":"Point"}
}