{
  "type": "Feature",
  "properties": {
    "iso:country":"US",
    "sg:address":"2951 Marina Bay Dr",
    "sg:city":"League City",
    "sg:classifiers":[
        {
            "category":"Professional",
            "subcategory":"Engineering",
            "type":"Services"
        }
    ],
    "sg:phone":"+1 281 535 0681",
    "sg:postcode":"77573",
    "sg:province":"TX",
    "wof:name":"Intl Trbmchnery Consulting Svc",
    "wof:placetype":"venue"
},
  "geometry": {"coordinates":[-95.064081,29.539925],"type":"Point"}
}