{
  "type": "Feature",
  "properties": {
    "iso:country":"US",
    "sg:address":"2105 Ranch Rd 620 N",
    "sg:city":"Austin",
    "sg:classifiers":[
        {
            "category":"Building & Trades",
            "subcategory":"Construction",
            "type":"Services"
        }
    ],
    "sg:phone":"+1 512 266 1626",
    "sg:postcode":"78734",
    "sg:province":"TX",
    "sg:tags":[
        "concrete",
        "contractor"
    ],
    "wof:name":"Anchor Concrete Inc",
    "wof:placetype":"venue"
},
  "geometry": {"coordinates":[-97.943432,30.381675],"type":"Point"}
}