{
  "type": "Feature",
  "properties": {
    "iso:country":"US",
    "sg:address":"1302 Byers Ln",
    "sg:city":"Austin",
    "sg:classifiers":[
        {
            "category":"Building & Trades",
            "subcategory":"Construction",
            "type":"Services"
        }
    ],
    "sg:phone":"+1 512 833 5330",
    "sg:postcode":"78753",
    "sg:province":"TX",
    "sg:tags":[
        "nonresidential"
    ],
    "wof:name":"Dial A Painter",
    "wof:placetype":"venue"
},
  "geometry": {"coordinates":[-97.66063800000001,30.378362],"type":"Point"}
}