{
  "type": "Feature",
  "properties": {
    "iso:country":"US",
    "sg:address":"10120 Synott Rd",
    "sg:city":"Sugar Land",
    "sg:classifiers":[
        {
            "category":"Professional",
            "subcategory":"Business Services",
            "type":"Services"
        }
    ],
    "sg:phone":"+1 281 495 0666",
    "sg:postcode":"77478",
    "sg:province":"TX",
    "wof:name":"Houston Mechanical Inspectors",
    "wof:placetype":"venue"
},
  "geometry": {"coordinates":[-95.61731,29.667412],"type":"Point"}
}