{
  "type": "Feature",
  "properties": {
    "iso:country":"US",
    "sg:address":"4000 State Hwy 78",
    "sg:city":"Wylie",
    "sg:classifiers":[
        {
            "category":"Professional",
            "subcategory":"Business Services",
            "type":"Services"
        }
    ],
    "sg:phone":"+1 972 429 1254",
    "sg:postcode":"75098",
    "sg:province":"TX",
    "sg:tags":[
        "pool",
        "swimming"
    ],
    "wof:name":"Sterling Pool Svc Inc",
    "wof:placetype":"venue"
},
  "geometry": {"coordinates":[-96.488416,33.025882],"type":"Point"}
}