{
  "type": "Feature",
  "properties": {
    "iso:country":"US",
    "sg:address":"7526 N I- 20",
    "sg:city":"Sweetwater",
    "sg:classifiers":[
        {
            "category":"Government",
            "subcategory":"Office",
            "type":"Public Place"
        }
    ],
    "sg:phone":"+1 325 235 8637",
    "sg:postcode":"79556",
    "sg:province":"TX",
    "sg:tags":[
        "state",
        "program"
    ],
    "wof:name":"Transportation Dept",
    "wof:placetype":"venue"
},
  "geometry": {"coordinates":[-100.386301,32.459999],"type":"Point"}
}