{
  "type": "Feature",
  "properties": {
    "iso:country":"US",
    "sg:address":"1106 Claire Ave",
    "sg:city":"Austin",
    "sg:classifiers":[
        {
            "category":"Retail",
            "subcategory":"Portrait Studio",
            "type":"Services"
        }
    ],
    "sg:phone":"+1 512 474 2676",
    "sg:postcode":"78703",
    "sg:province":"TX",
    "sg:tags":[
        "photo"
    ],
    "wof:name":"Stan Kearl Photographer",
    "wof:placetype":"venue"
},
  "geometry": {"coordinates":[-97.75045,30.295666],"type":"Point"}
}