{
  "type": "Feature",
  "properties": {
    "iso:country":"US",
    "sg:address":"1764 Shiloh Church Rd",
    "sg:city":"Crawford",
    "sg:phone":"+1 254 848 4179",
    "sg:postcode":"76638",
    "sg:province":"TX",
    "sg:tags":[
        "farm",
        "product",
        "grain",
        "corn",
        "cash"
    ],
    "wof:name":"Helen Michalewicz",
    "wof:placetype":"venue"
},
  "geometry": {"coordinates":[-97.365876,31.569988],"type":"Point"}
}