{
  "type": "Feature",
  "properties": {
    "iso:country":"US",
    "sg:address":"10003 Kirkwren Dr",
    "sg:city":"Houston",
    "sg:classifiers":[
        {
            "category":"Building & Trades",
            "subcategory":"Construction",
            "type":"Services"
        }
    ],
    "sg:phone":"+1 281 484 5379",
    "sg:postcode":"77089",
    "sg:province":"TX",
    "sg:tags":[
        "contractor"
    ],
    "wof:name":"Seabes Roofing & Construction",
    "wof:placetype":"venue"
},
  "geometry": {"coordinates":[-95.24484,29.598181],"type":"Point"}
}