{
  "type": "Feature",
  "properties": {
    "iso:country":"US",
    "sg:address":"6111 W Amarillo Blvd",
    "sg:city":"Amarillo",
    "sg:classifiers":[
        {
            "category":"Health Services",
            "subcategory":"Doctor",
            "type":"Services"
        }
    ],
    "sg:phone":"+1 806 463 5903",
    "sg:postcode":"79106",
    "sg:province":"TX",
    "sg:tags":[
        "medical"
    ],
    "wof:name":"Cesar Luiz G Md PA",
    "wof:placetype":"venue"
},
  "geometry": {"coordinates":[-101.908152,35.200732],"type":"Point"}
}