{
  "type": "Feature",
  "properties": {
    "iso:country":"US",
    "sg:address":"127 Turtle Creek Blvd",
    "sg:city":"Dallas",
    "sg:classifiers":[
        {
            "category":"Personal",
            "subcategory":"Beauty Salon",
            "type":"Services"
        }
    ],
    "sg:phone":"+1 214 521 4933",
    "sg:postcode":"75207",
    "sg:province":"TX",
    "sg:tags":[
        "shop"
    ],
    "wof:name":"Tom Slate",
    "wof:placetype":"venue"
},
  "geometry": {"coordinates":[-96.826966,32.793416],"type":"Point"}
}