{
  "type": "Feature",
  "properties": {
    "iso:country":"US",
    "sg:address":"4695 Southmost Rd",
    "sg:city":"Brownsville",
    "sg:classifiers":[
        {
            "category":"Shopping",
            "subcategory":"Florist",
            "type":"Retail Goods"
        }
    ],
    "sg:phone":"+1 956 544 6078",
    "sg:postcode":"78521",
    "sg:province":"TX",
    "wof:name":"El Paraiso Flower Shop",
    "wof:placetype":"venue"
},
  "geometry": {"coordinates":[-97.448618,25.895491],"type":"Point"}
}