{
  "type": "Feature",
  "properties": {
    "iso:country":"US",
    "sg:address":"421 S Seguin Ave",
    "sg:city":"New Braunfels",
    "sg:classifiers":[
        {
            "category":"Social Services",
            "type":"Services"
        }
    ],
    "sg:phone":"+1 830 620 7760",
    "sg:postcode":"78130",
    "sg:province":"TX",
    "sg:tags":[
        "organization",
        "welfare"
    ],
    "wof:name":"United Way",
    "wof:placetype":"venue"
},
  "geometry": {"coordinates":[-98.119546,29.69963],"type":"Point"}
}