{
  "type": "Feature",
  "properties": {
    "iso:country":"US",
    "sg:address":"1111 E Tyler St",
    "sg:city":"Athens",
    "sg:classifiers":[
        {
            "category":"Shopping",
            "subcategory":"Shoes",
            "type":"Retail Goods"
        }
    ],
    "sg:phone":"+1 903 677 1199",
    "sg:postcode":"75751",
    "sg:province":"TX",
    "sg:tags":[
        "shoe",
        "store"
    ],
    "wof:name":"Payless Shoesource",
    "wof:placetype":"venue"
},
  "geometry": {"coordinates":[-95.834548,32.205907],"type":"Point"}
}