{
  "type": "Feature",
  "properties": {
    "iso:country":"US",
    "sg:address":"237 S Cedar Ridge Dr",
    "sg:city":"Duncanville",
    "sg:classifiers":[
        {
            "category":"Shopping",
            "type":"Retail Goods"
        }
    ],
    "sg:phone":"+1 972 572 0277",
    "sg:postcode":"75116",
    "sg:province":"TX",
    "sg:tags":[
        "picture",
        "frame"
    ],
    "wof:name":"Frames & Things",
    "wof:placetype":"venue"
},
  "geometry": {"coordinates":[-96.92562100000001,32.647551],"type":"Point"}
}