{
  "type": "Feature",
  "properties": {
    "iso:country":"US",
    "sg:address":"1909 Crockett St",
    "sg:city":"Amarillo",
    "sg:classifiers":[
        {
            "category":"Wholesale",
            "subcategory":"Non-durable Goods",
            "type":"Manufacturing & Wholesale Goods"
        }
    ],
    "sg:phone":"+1 806 570 1434",
    "sg:postcode":"79109",
    "sg:province":"TX",
    "sg:tags":[
        "merchandise-wholesale"
    ],
    "wof:name":"M & B Trading",
    "wof:placetype":"venue"
},
  "geometry": {"coordinates":[-101.85788700000001,35.194542],"type":"Point"}
}