{
  "type": "Feature",
  "properties": {
    "iso:country":"US",
    "sg:address":"1213 Forest Park Dr",
    "sg:city":"Weatherford",
    "sg:classifiers":[
        {
            "category":"Professional",
            "subcategory":"Management & Consulting",
            "type":"Services"
        }
    ],
    "sg:phone":"+1 817 921 2966",
    "sg:postcode":"76087",
    "sg:province":"TX",
    "sg:tags":[
        "business"
    ],
    "wof:name":"Hers Raters of Texas LLC",
    "wof:placetype":"venue"
},
  "geometry": {"coordinates":[-97.68069800000001,32.762426],"type":"Point"}
}