{
  "type": "Feature",
  "properties": {
    "iso:country":"US",
    "sg:address":"1302 N Chadbourne St",
    "sg:city":"San Angelo",
    "sg:classifiers":[
        {
            "category":"Restaurant",
            "type":"Food & Drink"
        }
    ],
    "sg:phone":"+1 325 653 7765",
    "sg:postcode":"76903",
    "sg:province":"TX",
    "wof:name":"Corner Stop",
    "wof:placetype":"venue"
},
  "geometry": {"coordinates":[-100.444659,31.474686],"type":"Point"}
}