{
  "type": "Feature",
  "properties": {
    "iso:country":"US",
    "sg:address":"1700 Gulf Blvd",
    "sg:city":"S Padre Island",
    "sg:classifiers":[
        {
            "category":"Real Estate",
            "subcategory":"Real Estate Agent",
            "type":"Services"
        },
        {
            "category":"Real Estate",
            "subcategory":"Real Estate Operator",
            "type":"Services"
        }
    ],
    "sg:phone":"+1 956 761 1193",
    "sg:postcode":"78597",
    "sg:province":"TX",
    "sg:tags":[
        "condominium"
    ],
    "sg:website":"www.marisol-spi.com",
    "wof:name":"Marisol Apartments",
    "wof:placetype":"venue"
},
  "geometry": {"coordinates":[-97.16388499999999,26.096205],"type":"Point"}
}