{
  "type": "Feature",
  "properties": {
    "iso:country":"US",
    "sg:address":"3761 Brownlea Rd",
    "sg:city":"Silsbee",
    "sg:classifiers":[
        {
            "category":"Wholesale",
            "subcategory":"Jewelry",
            "type":"Manufacturing & Wholesale Goods"
        }
    ],
    "sg:phone":"+1 409 385 5057",
    "sg:postcode":"77656",
    "sg:province":"TX",
    "sg:tags":[
        "stone",
        "precious"
    ],
    "wof:name":"Timeless Treasures",
    "wof:placetype":"venue"
},
  "geometry": {"coordinates":[-94.18841500000001,30.418975],"type":"Point"}
}