{
  "type": "Feature",
  "properties": {
    "iso:country":"US",
    "sg:address":"1125 Wildflower Ln",
    "sg:city":"Mesquite",
    "sg:classifiers":[
        {
            "category":"Personal",
            "subcategory":"Beauty Salon",
            "type":"Services"
        }
    ],
    "sg:phone":"+1 972 216 7939",
    "sg:postcode":"75149",
    "sg:province":"TX",
    "sg:tags":[
        "shop"
    ],
    "wof:name":"Mary Anns Arts & Crafts",
    "wof:placetype":"venue"
},
  "geometry": {"coordinates":[-96.58324399999999,32.77861],"type":"Point"}
}