{
  "type": "Feature",
  "properties": {
    "iso:country":"US",
    "sg:address":"2305 Windchime Dr",
    "sg:city":"Grand Prairie",
    "sg:classifiers":[
        {
            "category":"Real Estate",
            "subcategory":"Real Estate Agent",
            "type":"Services"
        }
    ],
    "sg:phone":"+1 972 264 0145",
    "sg:postcode":"75051",
    "sg:province":"TX",
    "wof:name":"Jarvis Co",
    "wof:placetype":"venue"
},
  "geometry": {"coordinates":[-96.992362,32.712705],"type":"Point"}
}