{
  "type": "Feature",
  "properties": {
    "iso:country":"US",
    "sg:address":"1332 Laramie Pl",
    "sg:city":"Lewisville",
    "sg:classifiers":[
        {
            "category":"Professional",
            "subcategory":"Computer Services",
            "type":"Services"
        }
    ],
    "sg:phone":"+1 972 436 5101",
    "sg:postcode":"75077",
    "sg:province":"TX",
    "sg:tags":[
        "information",
        "retrieval"
    ],
    "wof:name":"Denick Internet Services",
    "wof:placetype":"venue"
},
  "geometry": {"coordinates":[-97.026826,33.052013],"type":"Point"}
}