{
  "type": "Feature",
  "properties": {
    "iso:country":"US",
    "sg:address":"617 E Irving Blvd",
    "sg:city":"Irving",
    "sg:classifiers":[
        {
            "category":"Restaurant",
            "type":"Food & Drink"
        }
    ],
    "sg:phone":"+1 972 554 1895",
    "sg:postcode":"75060",
    "sg:province":"TX",
    "wof:name":"Antojitos Salvadorenos",
    "wof:placetype":"venue"
},
  "geometry": {"coordinates":[-96.939003,32.813801],"type":"Point"}
}