{
  "type": "Feature",
  "properties": {
    "iso:country":"US",
    "sg:address":"3100 McKenzie Ave",
    "sg:city":"Waco",
    "sg:classifiers":[
        {
            "category":"Building & Trades",
            "subcategory":"Construction",
            "type":"Services"
        }
    ],
    "sg:phone":"+1 254 776 5578",
    "sg:postcode":"76708",
    "sg:province":"TX",
    "sg:tags":[
        "contractor"
    ],
    "wof:name":"National Insulation of Waco",
    "wof:placetype":"venue"
},
  "geometry": {"coordinates":[-97.18100099999999,31.562548],"type":"Point"}
}