{
  "type": "Feature",
  "properties": {
    "iso:country":"US",
    "sg:address":"6246 Richmond Ave",
    "sg:city":"Dallas",
    "sg:classifiers":[
        {
            "category":"Building & Trades",
            "subcategory":"Landscaping Services",
            "type":"Services"
        }
    ],
    "sg:phone":"+1 214 828 0879",
    "sg:postcode":"75214",
    "sg:province":"TX",
    "wof:name":"Green Visions",
    "wof:placetype":"venue"
},
  "geometry": {"coordinates":[-96.756523,32.816109],"type":"Point"}
}