{
  "type": "Feature",
  "properties": {
    "iso:country":"US",
    "sg:address":"7934 Triple Crown Dr",
    "sg:city":"Houston",
    "sg:classifiers":[
        {
            "category":"Professional",
            "subcategory":"Management & Consulting",
            "type":"Services"
        }
    ],
    "sg:phone":"+1 713 728 1934",
    "sg:postcode":"77071",
    "sg:province":"TX",
    "wof:name":"Transformative Technologies",
    "wof:placetype":"venue"
},
  "geometry": {"coordinates":[-95.51746199999999,29.644066],"type":"Point"}
}