{
  "type": "Feature",
  "properties": {
    "iso:country":"US",
    "sg:address":"18761 Bandera Rd",
    "sg:city":"Helotes",
    "sg:classifiers":[
        {
            "category":"Building & Trades",
            "subcategory":"Construction",
            "type":"Services"
        }
    ],
    "sg:phone":"+1 210 695 3588",
    "sg:postcode":"78023",
    "sg:province":"TX",
    "sg:tags":[
        "water",
        "well",
        "drilling"
    ],
    "wof:name":"Weaverling & Son Inc",
    "wof:placetype":"venue"
},
  "geometry": {"coordinates":[-98.749622,29.615851],"type":"Point"}
}