{
  "type": "Feature",
  "properties": {
    "iso:country":"US",
    "sg:address":"4048 Mehalia Dr",
    "sg:city":"Dallas",
    "sg:classifiers":[
        {
            "category":"Building & Trades",
            "subcategory":"Cleaning & Sanitation",
            "type":"Services"
        }
    ],
    "sg:phone":"+1 972 225 6157",
    "sg:postcode":"75241",
    "sg:province":"TX",
    "sg:tags":[
        "maintenance"
    ],
    "wof:name":"EMK Industrial Maintenance Svc",
    "wof:placetype":"venue"
},
  "geometry": {"coordinates":[-96.754566,32.672625],"type":"Point"}
}