{
  "type": "Feature",
  "properties": {
    "iso:country":"US",
    "sg:address":"5021 Alps Dr",
    "sg:city":"El Paso",
    "sg:classifiers":[
        {
            "category":"Professional",
            "subcategory":"Business Services",
            "type":"Services"
        }
    ],
    "sg:phone":"+1 915 755 0325",
    "sg:postcode":"79904",
    "sg:province":"TX",
    "wof:name":"Melvin E Matthews",
    "wof:placetype":"venue"
},
  "geometry": {"coordinates":[-106.41907399999999,31.866255],"type":"Point"}
}