{
  "type": "Feature",
  "properties": {
    "iso:country":"US",
    "sg:address":"9703 Santa Clara Dr",
    "sg:city":"Fort Worth",
    "sg:classifiers":[
        {
            "category":"Restaurant",
            "type":"Food & Drink"
        }
    ],
    "sg:phone":"+1 817 244 4805",
    "sg:postcode":"76116",
    "sg:province":"TX",
    "sg:tags":[
        "eating"
    ],
    "wof:name":"Speedway Kitchen",
    "wof:placetype":"venue"
},
  "geometry": {"coordinates":[-97.4953,32.728223],"type":"Point"}
}