{
  "type": "Feature",
  "properties": {
    "iso:country":"US",
    "sg:address":"23 Manor Ln",
    "sg:city":"Allen",
    "sg:classifiers":[
        {
            "category":"Professional",
            "subcategory":"Computer Services",
            "type":"Services"
        }
    ],
    "sg:phone":"+1 972 727 1545",
    "sg:postcode":"75002",
    "sg:province":"TX",
    "sg:tags":[
        "related"
    ],
    "wof:name":"Cenkron",
    "wof:placetype":"venue"
},
  "geometry": {"coordinates":[-96.576205,33.097293],"type":"Point"}
}