{
  "type": "Feature",
  "properties": {
    "iso:country":"US",
    "sg:address":"8603 Broadway St",
    "sg:city":"Pearland",
    "sg:classifiers":[
        {
            "category":"Health Services",
            "subcategory":"Doctor",
            "type":"Services"
        }
    ],
    "sg:phone":"+1 281 485 7740",
    "sg:postcode":"77584",
    "sg:province":"TX",
    "sg:tags":[
        "physician",
        "surgeon"
    ],
    "wof:name":"Baylor Orthopedic Surg Prlnd",
    "wof:placetype":"venue"
},
  "geometry": {"coordinates":[-95.35218999999999,29.559029],"type":"Point"}
}