{
  "type": "Feature",
  "properties": {
    "iso:country":"US",
    "sg:address":"13261 Murphy Rd",
    "sg:city":"Stafford",
    "sg:classifiers":[
        {
            "category":"Building & Trades",
            "subcategory":"Construction",
            "type":"Services"
        },
        {
            "category":"Retail",
            "subcategory":"Auto Repair",
            "type":"Services"
        }
    ],
    "sg:phone":"+1 281 499 3806",
    "sg:postcode":"77477",
    "sg:province":"TX",
    "sg:tags":[
        "glass",
        "coating",
        "tinting",
        "contractor"
    ],
    "wof:name":"All Out Offroad",
    "wof:placetype":"venue"
},
  "geometry": {"coordinates":[-95.56484,29.629921],"type":"Point"}
}