{
  "type": "Feature",
  "properties": {
    "iso:country":"US",
    "sg:address":"13918 Hempstead Rd",
    "sg:city":"Houston",
    "sg:classifiers":[
        {
            "category":"Restaurant",
            "type":"Food & Drink"
        }
    ],
    "sg:phone":"+1 713 460 3287",
    "sg:postcode":"77040",
    "sg:province":"TX",
    "sg:tags":[
        "eating"
    ],
    "wof:name":"Eats Mesquite Grill",
    "wof:placetype":"venue"
},
  "geometry": {"coordinates":[-95.52845000000001,29.850591],"type":"Point"}
}