{
  "type": "Feature",
  "properties": {
    "iso:country":"US",
    "sg:address":"716 Beechwood Dr",
    "sg:city":"De Soto",
    "sg:classifiers":[
        {
            "category":"Wholesale",
            "subcategory":"Drugs",
            "type":"Manufacturing & Wholesale Goods"
        }
    ],
    "sg:phone":"+1 972 223 0772",
    "sg:postcode":"75115",
    "sg:province":"TX",
    "wof:name":"Lajoyce M Meeks",
    "wof:placetype":"venue"
},
  "geometry": {"coordinates":[-96.843215,32.582285],"type":"Point"}
}