{
  "type": "Feature",
  "properties": {
    "iso:country":"US",
    "sg:address":"503 Jernigan St",
    "sg:city":"Bells",
    "sg:classifiers":[
        {
            "category":"Shopping",
            "subcategory":"Hobbies, Toys, & Games",
            "type":"Retail Goods"
        }
    ],
    "sg:phone":"+1 903 965 0266",
    "sg:postcode":"75414",
    "sg:province":"TX",
    "wof:name":"Judith A Morris",
    "wof:placetype":"venue"
},
  "geometry": {"coordinates":[-96.406541,33.604849],"type":"Point"}
}