{
  "type": "Feature",
  "properties": {
    "iso:country":"US",
    "sg:address":"1413 Tremont St",
    "sg:city":"Galveston",
    "sg:classifiers":[
        {
            "category":"Retail",
            "subcategory":"Repair Shop",
            "type":"Services"
        }
    ],
    "sg:phone":"+1 409 621 4652",
    "sg:postcode":"77550",
    "sg:province":"TX",
    "wof:name":"Rose Ann Hall Designs",
    "wof:placetype":"venue"
},
  "geometry": {"coordinates":[-94.79081499999999,29.296594],"type":"Point"}
}