{
  "type": "Feature",
  "properties": {
    "iso:country":"US",
    "sg:address":"2440 S Collins St",
    "sg:city":"Arlington",
    "sg:classifiers":[
        {
            "category":"Restaurant",
            "type":"Food & Drink"
        }
    ],
    "sg:phone":"+1 817 801 0050",
    "sg:postcode":"76014",
    "sg:province":"TX",
    "sg:tags":[
        "eating"
    ],
    "wof:name":"Sunset Cafe",
    "wof:placetype":"venue"
},
  "geometry": {"coordinates":[-97.097763,32.705463],"type":"Point"}
}