{
  "type": "Feature",
  "properties": {
    "iso:country":"US",
    "sg:address":"124 Lyman Dr",
    "sg:city":"San Antonio",
    "sg:classifiers":[
        {
            "category":"Professional",
            "type":"Services"
        }
    ],
    "sg:phone":"+1 210 414 0507",
    "sg:postcode":"78209",
    "sg:province":"TX",
    "wof:name":"Debra S Runyan",
    "wof:placetype":"venue"
},
  "geometry": {"coordinates":[-98.438936,29.478631],"type":"Point"}
}