{
  "type": "Feature",
  "properties": {
    "iso:country":"US",
    "sg:address":"13617 Inwood Rd",
    "sg:city":"Dallas",
    "sg:classifiers":[
        {
            "category":"Professional",
            "subcategory":"Advertising",
            "type":"Services"
        }
    ],
    "sg:phone":"+1 972 726 8830",
    "sg:postcode":"75244",
    "sg:province":"TX",
    "sg:tags":[
        "counselor"
    ],
    "sg:website":"www.regalipromotions.com",
    "wof:name":"Regali Inc",
    "wof:placetype":"venue"
},
  "geometry": {"coordinates":[-96.823359,32.933781],"type":"Point"}
}