{
  "type": "Feature",
  "properties": {
    "iso:country":"US",
    "sg:address":"11107 Wurzbach Rd",
    "sg:city":"San Antonio",
    "sg:classifiers":[
        {
            "category":"Professional",
            "subcategory":"Detective & Security Services",
            "type":"Services"
        }
    ],
    "sg:phone":"+1 210 690 6955",
    "sg:postcode":"78230",
    "sg:province":"TX",
    "sg:tags":[
        "car",
        "electronic"
    ],
    "wof:name":"Ais Investigations Inc",
    "wof:placetype":"venue"
},
  "geometry": {"coordinates":[-98.551664,29.541234],"type":"Point"}
}