{
  "type": "Feature",
  "properties": {
    "iso:country":"US",
    "sg:address":"6101 Harrogate Dr",
    "sg:city":"Austin",
    "sg:classifiers":[
        {
            "category":"Professional",
            "subcategory":"Research",
            "type":"Services"
        }
    ],
    "sg:phone":"+1 512 331 1594",
    "sg:postcode":"78759",
    "sg:province":"TX",
    "sg:tags":[
        "consultant",
        "signal"
    ],
    "wof:name":"Qian Shie",
    "wof:placetype":"venue"
},
  "geometry": {"coordinates":[-97.759523,30.416912],"type":"Point"}
}