{
  "type": "Feature",
  "properties": {
    "iso:country":"US",
    "sg:address":"2127 Petunia St",
    "sg:city":"Dallas",
    "sg:classifiers":[
        {
            "category":"Professional",
            "type":"Services"
        }
    ],
    "sg:phone":"+1 214 327 3697",
    "sg:postcode":"75228",
    "sg:province":"TX",
    "wof:name":"McRae Echeck Recovery Inc",
    "wof:placetype":"venue"
},
  "geometry": {"coordinates":[-96.67831099999999,32.805117],"type":"Point"}
}