{
  "type": "Feature",
  "properties": {
    "iso:country":"US",
    "sg:address":"455 Stephen F Austin Dr",
    "sg:city":"Conroe",
    "sg:classifiers":[
        {
            "category":"Professional",
            "subcategory":"Management & Consulting",
            "type":"Services"
        }
    ],
    "sg:phone":"+1 936 321 8601",
    "sg:postcode":"77302",
    "sg:province":"TX",
    "sg:tags":[
        "consultant"
    ],
    "wof:name":"Howard's Consulting Svc",
    "wof:placetype":"venue"
},
  "geometry": {"coordinates":[-95.437361,30.262347],"type":"Point"}
}