{
  "type": "Feature",
  "properties": {
    "iso:country":"US",
    "sg:address":"414 Bostwick St",
    "sg:city":"Nacogdoches",
    "sg:classifiers":[
        {
            "category":"Communications",
            "subcategory":"Film & Video Production",
            "type":"Services"
        }
    ],
    "sg:phone":"+1 936 569 8895",
    "sg:postcode":"75965",
    "sg:province":"TX",
    "sg:tags":[
        "motion",
        "picture"
    ],
    "wof:name":"Soundhaus Music Productions",
    "wof:placetype":"venue"
},
  "geometry": {"coordinates":[-94.64924999999999,31.640304],"type":"Point"}
}