{
  "type": "Feature",
  "properties": {
    "iso:country":"US",
    "sg:address":"104 E Plum St",
    "sg:city":"Sonora",
    "sg:classifiers":[
        {
            "category":"Retail",
            "subcategory":"Auto Repair",
            "type":"Services"
        }
    ],
    "sg:phone":"+1 325 387 2492",
    "sg:postcode":"76950",
    "sg:province":"TX",
    "sg:tags":[
        "wrecker"
    ],
    "wof:name":"Blacks Wrecker & Auto Service",
    "wof:placetype":"venue"
},
  "geometry": {"coordinates":[-100.644868,30.570281],"type":"Point"}
}