{
  "type": "Feature",
  "properties": {
    "iso:country":"US",
    "sg:address":"14 Lake Mist Ct",
    "sg:city":"Sugar Land",
    "sg:classifiers":[
        {
            "category":"Building & Trades",
            "subcategory":"Equipment Rental",
            "type":"Services"
        }
    ],
    "sg:phone":"+1 281 277 7100",
    "sg:postcode":"77479",
    "sg:province":"TX",
    "sg:tags":[
        "loan",
        "broker",
        "business"
    ],
    "wof:name":"National Funding LLC",
    "wof:placetype":"venue"
},
  "geometry": {"coordinates":[-95.675453,29.59385],"type":"Point"}
}