{
  "type": "Feature",
  "properties": {
    "iso:country":"US",
    "sg:address":"10919 Hickory Tree Ct",
    "sg:city":"Houston",
    "sg:classifiers":[
        {
            "category":"Shopping",
            "type":"Retail Goods"
        }
    ],
    "sg:phone":"+1 281 469 4182",
    "sg:postcode":"77065",
    "sg:province":"TX",
    "sg:tags":[
        "merchandise"
    ],
    "wof:name":"Thu N Phan",
    "wof:placetype":"venue"
},
  "geometry": {"coordinates":[-95.611616,29.926987],"type":"Point"}
}