{
  "type": "Feature",
  "properties": {
    "iso:country":"US",
    "sg:address":"4064 E Loop 820 S",
    "sg:city":"Fort Worth",
    "sg:classifiers":[
        {
            "category":"Wholesale",
            "subcategory":"Construction Materials",
            "type":"Manufacturing & Wholesale Goods"
        }
    ],
    "sg:phone":"+1 817 654 1555",
    "sg:postcode":"76119",
    "sg:province":"TX",
    "sg:tags":[
        "fence"
    ],
    "wof:name":"Corral Fence Inc",
    "wof:placetype":"venue"
},
  "geometry": {"coordinates":[-97.23321900000001,32.705779],"type":"Point"}
}