{
  "type": "Feature",
  "properties": {
    "iso:country":"US",
    "sg:address":"1725 1st St",
    "sg:city":"Palacios",
    "sg:classifiers":[
        {
            "category":"Retail",
            "subcategory":"Auto Repair",
            "type":"Services"
        }
    ],
    "sg:phone":"+1 361 972 2203",
    "sg:postcode":"77465",
    "sg:province":"TX",
    "sg:tags":[
        "body",
        "automobile",
        "painting"
    ],
    "wof:name":"J & S Paint Body Shop Wrecker",
    "wof:placetype":"venue"
},
  "geometry": {"coordinates":[-96.210325,28.719808],"type":"Point"}
}