{
  "type": "Feature",
  "properties": {
    "iso:country":"US",
    "sg:address":"7134 Bayou Forest Dr",
    "sg:city":"Houston",
    "sg:classifiers":[
        {
            "category":"Shopping",
            "subcategory":"Used Merchandise",
            "type":"Retail Goods"
        }
    ],
    "sg:phone":"+1 713 385 8778",
    "sg:postcode":"77088",
    "sg:province":"TX",
    "wof:name":"Larrys Wholesale Antiques",
    "wof:placetype":"venue"
},
  "geometry": {"coordinates":[-95.481482,29.873914],"type":"Point"}
}