{
  "type": "Feature",
  "properties": {
    "iso:country":"US",
    "sg:address":"550 The Meadows Pkwy",
    "sg:city":"De Soto",
    "sg:classifiers":[
        {
            "category":"Building & Trades",
            "subcategory":"Construction",
            "type":"Services"
        }
    ],
    "sg:phone":"+1 972 230 3424",
    "sg:postcode":"75115",
    "sg:province":"TX",
    "sg:tags":[
        "contractor"
    ],
    "wof:name":"H&H General Contractors",
    "wof:placetype":"venue"
},
  "geometry": {"coordinates":[-96.84062900000001,32.597294],"type":"Point"}
}