{
  "type": "Feature",
  "properties": {
    "iso:country":"US",
    "sg:address":"830 S Beckham Ave",
    "sg:city":"Tyler",
    "sg:classifiers":[
        {
            "category":"Organizations",
            "subcategory":"Membership Organization",
            "type":"Services"
        }
    ],
    "sg:phone":"+1 903 597 7652",
    "sg:postcode":"75701",
    "sg:province":"TX",
    "wof:name":"Vaughn Foundation & Interest",
    "wof:placetype":"venue"
},
  "geometry": {"coordinates":[-95.29227299999999,32.340722],"type":"Point"}
}