{
  "type": "Feature",
  "properties": {
    "iso:country":"US",
    "sg:address":"521 S 1st St",
    "sg:city":"Muleshoe",
    "sg:classifiers":[
        {
            "category":"Place Of Worship",
            "subcategory":"Church",
            "type":"Public Place"
        },
        {
            "category":"Place Of Worship",
            "type":"Public Place"
        },
        {
            "category":"Organizations",
            "subcategory":"Religious Organization",
            "type":"Services"
        }
    ],
    "sg:phone":"+1 806 272 3017",
    "sg:postcode":"79347",
    "sg:province":"TX",
    "sg:tags":[
        "god",
        "god-independent",
        "churches-assemblies"
    ],
    "wof:name":"First Assembly Of God Church",
    "wof:placetype":"venue"
},
  "geometry": {"coordinates":[-102.72329499999999,34.226966],"type":"Point"}
}