{
  "type": "Feature",
  "properties": {
    "iso:country":"US",
    "sg:address":"13135 Champions Dr # 102",
    "sg:city":"Houston",
    "sg:classifiers":[
        {
            "category":"Personal",
            "subcategory":"Massage",
            "type":"Services"
        },
        {
            "category":"Health Services",
            "subcategory":"Clinic",
            "type":"Services"
        },
        {
            "category":"Health Services",
            "subcategory":"Health Practitioner",
            "type":"Services"
        }
    ],
    "sg:phone":"+1 281 440 1397",
    "sg:postcode":"77069",
    "sg:province":"TX",
    "sg:tags":[
        "therapist",
        "therapy",
        "physical"
    ],
    "wof:name":"The Center For Healthy Muscles",
    "wof:placetype":"venue"
},
  "geometry": {"coordinates":[-95.526416,29.974886],"type":"Point"}
}