{
  "type": "Feature",
  "properties": {
    "iso:country":"US",
    "sg:address":"15739 Lee Rd",
    "sg:city":"Humble",
    "sg:classifiers":[
        {
            "category":"Autos & Motor Vehicles",
            "subcategory":"Auto Supplies",
            "type":"Retail Goods"
        }
    ],
    "sg:phone":"+1 281 442 2595",
    "sg:postcode":"77396",
    "sg:province":"TX",
    "wof:name":"Mike Donald Used Cars",
    "wof:placetype":"venue"
},
  "geometry": {"coordinates":[-95.303969,29.949123],"type":"Point"}
}