{
  "type": "Feature",
  "properties": {
    "iso:country":"US",
    "sg:address":"129 Beach St",
    "sg:city":"Hereford",
    "sg:classifiers":[
        {
            "category":"Arts & Performance",
            "subcategory":"Arts Center",
            "type":"Entertainment"
        },
        {
            "category":"Building & Trades",
            "subcategory":"Construction",
            "type":"Services"
        }
    ],
    "sg:phone":"+1 866 486 0213",
    "sg:postcode":"79045",
    "sg:province":"TX",
    "sg:tags":[
        "plastering",
        "drywall",
        "contractor",
        "decorating",
        "hand",
        "painting"
    ],
    "wof:name":"H.I.T.P Paint Services",
    "wof:placetype":"venue"
},
  "geometry": {"coordinates":[-102.41349099999999,34.82329],"type":"Point"}
}