{
  "type": "Feature",
  "properties": {
    "iso:country":"US",
    "sg:address":"1736 Rock Prairie Rd",
    "sg:city":"College Station",
    "sg:classifiers":[
        {
            "category":"Personal",
            "subcategory":"Beauty Salon",
            "type":"Services"
        }
    ],
    "sg:phone":"+1 979 693 6424",
    "sg:postcode":"77845",
    "sg:province":"TX",
    "sg:tags":[
        "manicuring"
    ],
    "wof:name":"Pretty Nails",
    "wof:placetype":"venue"
},
  "geometry": {"coordinates":[-96.29092799999999,30.582556],"type":"Point"}
}