{
  "type": "Feature",
  "properties": {
    "iso:country":"US",
    "sg:address":"4316 Beverly Dr",
    "sg:city":"Waco",
    "sg:classifiers":[
        {
            "category":"Building & Trades",
            "subcategory":"Construction",
            "type":"Services"
        }
    ],
    "sg:phone":"+1 254 717 8682",
    "sg:postcode":"76711",
    "sg:province":"TX",
    "sg:tags":[
        "house"
    ],
    "wof:name":"Star Construction",
    "wof:placetype":"venue"
},
  "geometry": {"coordinates":[-97.160585,31.51751],"type":"Point"}
}