{
  "type": "Feature",
  "properties": {
    "iso:country":"US",
    "sg:address":"6910 Forest Glen Dr",
    "sg:city":"Dallas",
    "sg:classifiers":[
        {
            "category":"Professional",
            "type":"Services"
        }
    ],
    "sg:phone":"+1 972 239 6762",
    "sg:postcode":"75230",
    "sg:province":"TX",
    "sg:tags":[
        "establishment"
    ],
    "wof:name":"Sharif & Munir Lane Park Ests",
    "wof:placetype":"venue"
},
  "geometry": {"coordinates":[-96.784485,32.913282],"type":"Point"}
}