{
  "type": "Feature",
  "properties": {
    "iso:country":"US",
    "sg:address":"400 Harborside Dr",
    "sg:city":"Galveston",
    "sg:classifiers":[
        {
            "category":"Health Services",
            "subcategory":"Doctor",
            "type":"Services"
        }
    ],
    "sg:phone":"+1 409 772 6283",
    "sg:postcode":"77550",
    "sg:province":"TX",
    "sg:tags":[
        "medical"
    ],
    "wof:name":"General Pediatrics",
    "wof:placetype":"venue"
},
  "geometry": {"coordinates":[-94.77426199999999,29.313969],"type":"Point"}
}