{
  "type": "Feature",
  "properties": {
    "iso:country":"US",
    "sg:address":"1343 Columbia Dr",
    "sg:city":"Richardson",
    "sg:classifiers":[
        {
            "category":"Shopping",
            "subcategory":"Computers & Home Electronics",
            "type":"Retail Goods"
        }
    ],
    "sg:phone":"+1 972 437 0090",
    "sg:postcode":"75081",
    "sg:province":"TX",
    "sg:tags":[
        "equipment",
        "electronic",
        "supply"
    ],
    "wof:name":"Century Electronics",
    "wof:placetype":"venue"
},
  "geometry": {"coordinates":[-96.701189,32.955725],"type":"Point"}
}