{
  "type": "Feature",
  "properties": {
    "iso:country":"US",
    "sg:address":"3633 Eisenhower Rd",
    "sg:city":"Odessa",
    "sg:classifiers":[
        {
            "category":"Retail",
            "subcategory":"Veterinary Services",
            "type":"Services"
        }
    ],
    "sg:phone":"+1 432 363 0182",
    "sg:postcode":"79762",
    "sg:province":"TX",
    "sg:tags":[
        "animal"
    ],
    "wof:name":"All Things Canine",
    "wof:placetype":"venue"
},
  "geometry": {"coordinates":[-102.37350000000001,31.881197],"type":"Point"}
}