{
  "type": "Feature",
  "properties": {
    "iso:country":"US",
    "sg:address":"3470 S Watson Rd",
    "sg:city":"Arlington",
    "sg:classifiers":[
        {
            "category":"Organizations",
            "subcategory":"Non-profit Organization",
            "type":"Services"
        }
    ],
    "sg:phone":"+1 817 557 4977",
    "sg:postcode":"76014",
    "sg:province":"TX",
    "sg:tags":[
        "fund",
        "counselor",
        "raising"
    ],
    "wof:name":"Scholastic Book Fairs",
    "wof:placetype":"venue"
},
  "geometry": {"coordinates":[-97.063118,32.691393],"type":"Point"}
}