{
  "type": "Feature",
  "properties": {
    "iso:country":"US",
    "sg:address":"26913 Katy Fwy",
    "sg:city":"Katy",
    "sg:classifiers":[
        {
            "category":"Utilities",
            "subcategory":"Electric",
            "type":"Services"
        },
        {
            "category":"Manufacturing",
            "subcategory":"Electronics",
            "type":"Manufacturing & Wholesale Goods"
        },
        {
            "category":"Building & Trades",
            "subcategory":"Electrical",
            "type":"Services"
        }
    ],
    "sg:phone":"+1 281 392 7115",
    "sg:postcode":"77494",
    "sg:province":"TX",
    "sg:tags":[
        "industrial",
        "electrician",
        "contractors-commercial",
        "equipment-testing"
    ],
    "wof:name":"Parmley Electric Co",
    "wof:placetype":"venue"
},
  "geometry": {"coordinates":[-95.870113,29.77703],"type":"Point"}
}