{
  "type": "Feature",
  "properties": {
    "iso:country":"US",
    "sg:address":"905 E Tyler St",
    "sg:city":"Brownsville",
    "sg:classifiers":[
        {
            "category":"Utilities",
            "subcategory":"Electric",
            "type":"Services"
        },
        {
            "category":"Manufacturing",
            "subcategory":"Motor Vehicles & Parts",
            "type":"Manufacturing & Wholesale Goods"
        }
    ],
    "sg:phone":"+1 956 546 4523",
    "sg:postcode":"78520",
    "sg:province":"TX",
    "sg:tags":[
        "equipment-repair"
    ],
    "wof:name":"Imperial Electric",
    "wof:placetype":"venue"
},
  "geometry": {"coordinates":[-97.49395800000001,25.908573],"type":"Point"}
}