{
  "type": "Feature",
  "properties": {
    "iso:country":"US",
    "sg:address":"2757 Rayford Rd",
    "sg:city":"Spring",
    "sg:classifiers":[
        {
            "category":"Personal",
            "subcategory":"Beauty Salon",
            "type":"Services"
        },
        {
            "category":"Personal",
            "subcategory":"Skin Care",
            "type":"Services"
        }
    ],
    "sg:phone":"+1 281 298 3607",
    "sg:postcode":"77386",
    "sg:province":"TX",
    "wof:name":"SK Salon",
    "wof:placetype":"venue"
},
  "geometry": {"coordinates":[-95.399539,30.120937],"type":"Point"}
}