{
  "type": "Feature",
  "properties": {
    "iso:country":"US",
    "sg:address":"3817 US Highway 80 E",
    "sg:city":"Mesquite",
    "sg:classifiers":[
        {
            "category":"Travel",
            "subcategory":"Hotels & Motels",
            "type":"Entertainment"
        }
    ],
    "sg:phone":"+1 972 681 0044",
    "sg:postcode":"75150",
    "sg:province":"TX",
    "wof:name":"Deluxe Inn",
    "wof:placetype":"venue"
},
  "geometry": {"coordinates":[-96.65630299999999,32.7939],"type":"Point"}
}