{
  "type": "Feature",
  "properties": {
    "iso:country":"US",
    "sg:address":"611 E Main St",
    "sg:city":"La Porte",
    "sg:classifiers":[
        {
            "category":"Marine",
            "type":"Transportation"
        }
    ],
    "sg:phone":"+1 281 471 5100",
    "sg:postcode":"77571",
    "sg:province":"TX",
    "sg:tags":[
        "water",
        "transport",
        "boat"
    ],
    "wof:name":"Zemanek Marine Services Inc",
    "wof:placetype":"venue"
},
  "geometry": {"coordinates":[-95.01455199999999,29.667829],"type":"Point"}
}