{
  "type": "Feature",
  "properties": {
    "iso:country":"US",
    "sg:address":"2023 S Bridge St Space 2",
    "sg:city":"Brady",
    "sg:classifiers":[
        {
            "category":"Fast Food",
            "type":"Food & Drink"
        },
        {
            "category":"Restaurant",
            "type":"Food & Drink"
        },
        {
            "category":"Food & Beverages",
            "subcategory":"Groceries & Convenience Stores",
            "type":"Retail Goods"
        }
    ],
    "sg:phone":"+1 325 597 8055",
    "sg:postcode":"76825",
    "sg:province":"TX",
    "sg:tags":[
        "shop",
        "american",
        "sandwich",
        "take"
    ],
    "sg:website":"http://www.subway.com",
    "wof:name":"Subway",
    "wof:placetype":"venue"
},
  "geometry": {"coordinates":[-99.335644,31.118486],"type":"Point"}
}