{
  "type": "Feature",
  "properties": {
    "iso:country":"US",
    "sg:address":"630 S Naquin Rd",
    "sg:city":"Orange",
    "sg:classifiers":[
        {
            "category":"Restaurant",
            "type":"Food & Drink"
        }
    ],
    "sg:phone":"+1 409 745 0216",
    "sg:postcode":"77630",
    "sg:province":"TX",
    "sg:tags":[
        "cajun",
        "creole"
    ],
    "wof:name":"Cajun Eatery, Inc",
    "wof:placetype":"venue"
},
  "geometry": {"coordinates":[-93.8443,30.117128],"type":"Point"}
}