{
  "type": "Feature",
  "properties": {
    "iso:country":"US",
    "sg:address":"120 Tawakoni Dr.",
    "sg:city":"Emory",
    "sg:classifiers":[
        {
            "category":"Real Estate",
            "subcategory":"Real Estate Services",
            "type":"Services"
        },
        {
            "category":"Real Estate",
            "subcategory":"Real Estate Agent",
            "type":"Services"
        }
    ],
    "sg:phone":"+1 903 850 0329",
    "sg:postcode":"75440",
    "sg:province":"TX",
    "sg:tags":[
        "consultant"
    ],
    "sg:website":"http://www.lakeforkatoz.com",
    "wof:name":"Emory Homes - Ed Cada",
    "wof:placetype":"venue"
},
  "geometry": {"coordinates":[-95.771473,32.877238],"type":"Point"}
}