{
  "type": "Feature",
  "properties": {
    "iso:country":"US",
    "sg:address":"7301 Trinity Blvd",
    "sg:city":"Fort Worth",
    "sg:classifiers":[
        {
            "category":"Food & Beverages",
            "subcategory":"Meat & Fish",
            "type":"Retail Goods"
        }
    ],
    "sg:phone":"+1 817 595 4794",
    "sg:postcode":"76118",
    "sg:province":"TX",
    "sg:tags":[
        "grocery",
        "general"
    ],
    "wof:name":"MBM",
    "wof:placetype":"venue"
},
  "geometry": {"coordinates":[-97.217097,32.797982],"type":"Point"}
}