{
  "type": "Feature",
  "properties": {
    "iso:country":"US",
    "sg:address":"1113 Grant St",
    "sg:city":"Laredo",
    "sg:classifiers":[
        {
            "category":"Wholesale",
            "subcategory":"Apparel",
            "type":"Manufacturing & Wholesale Goods"
        }
    ],
    "sg:phone":"+1 956 753 9351",
    "sg:postcode":"78040",
    "sg:province":"TX",
    "sg:tags":[
        "footwear"
    ],
    "wof:name":"Amigo Shoes Inc",
    "wof:placetype":"venue"
},
  "geometry": {"coordinates":[-99.50743300000001,27.502764],"type":"Point"}
}