{
  "type": "Feature",
  "properties": {
    "iso:country":"US",
    "sg:address":"5341 FM 349 S",
    "sg:city":"Longview",
    "sg:classifiers":[
        {
            "category":"Retail",
            "subcategory":"Repair Shop",
            "type":"Services"
        }
    ],
    "sg:phone":"+1 903 753 3397",
    "sg:postcode":"75603",
    "sg:province":"TX",
    "sg:tags":[
        "refrigerating"
    ],
    "wof:name":"Keith's Commercial Refrig",
    "wof:placetype":"venue"
},
  "geometry": {"coordinates":[-94.689853,32.394838],"type":"Point"}
}