{
  "type": "Feature",
  "properties": {
    "iso:country":"US",
    "sg:address":"1821 E Main St",
    "sg:city":"Grand Prairie",
    "sg:classifiers":[
        {
            "category":"Autos & Motor Vehicles",
            "subcategory":"Automobile Sales",
            "type":"Retail Goods"
        }
    ],
    "sg:phone":"+1 972 282 9300",
    "sg:postcode":"75050",
    "sg:province":"TX",
    "sg:tags":[
        "car",
        "dealer"
    ],
    "wof:name":"Es Auto Sales",
    "wof:placetype":"venue"
},
  "geometry": {"coordinates":[-96.980397,32.748234],"type":"Point"}
}