{
  "type": "Feature",
  "properties": {
    "iso:country":"US",
    "sg:address":"1234 Richland Hills Dr",
    "sg:city":"San Antonio",
    "sg:classifiers":[
        {
            "category":"Professional",
            "type":"Services"
        }
    ],
    "sg:phone":"+1 210 256 2323",
    "sg:postcode":"78251",
    "sg:province":"TX",
    "wof:name":"Maya Personal Services",
    "wof:placetype":"venue"
},
  "geometry": {"coordinates":[-98.661663,29.44773],"type":"Point"}
}