{
  "type": "Feature",
  "properties": {
    "iso:country":"US",
    "sg:address":"8700 Brodie Ln",
    "sg:city":"Austin",
    "sg:classifiers":[
        {
            "category":"Professional",
            "subcategory":"Business Services",
            "type":"Services"
        }
    ],
    "sg:phone":"+1 512 291 4531",
    "sg:postcode":"78745",
    "sg:province":"TX",
    "sg:tags":[
        "process",
        "server"
    ],
    "wof:name":"United Process Svc",
    "wof:placetype":"venue"
},
  "geometry": {"coordinates":[-97.840627,30.198563],"type":"Point"}
}