{
  "type": "Feature",
  "properties": {
    "iso:country":"US",
    "sg:address":"522 Hampshire St",
    "sg:city":"Longview",
    "sg:classifiers":[
        {
            "category":"Shopping",
            "type":"Retail Goods"
        }
    ],
    "sg:phone":"+1 903 757 4072",
    "sg:postcode":"75605",
    "sg:province":"TX",
    "sg:tags":[
        "merchandise"
    ],
    "wof:name":"Troop 201 Alumni Foundati",
    "wof:placetype":"venue"
},
  "geometry": {"coordinates":[-94.755106,32.533731],"type":"Point"}
}