{
  "type": "Feature",
  "properties": {
    "iso:country":"US",
    "sg:address":"105 E Virginia St",
    "sg:city":"Mc Kinney",
    "sg:classifiers":[
        {
            "category":"Shopping",
            "subcategory":"Gifts & Souvenirs",
            "type":"Retail Goods"
        },
        {
            "category":"Shopping",
            "subcategory":"Clothing, Apparel, & Fashions",
            "type":"Retail Goods"
        }
    ],
    "sg:phone":"+1 972 542 0429",
    "sg:postcode":"75069",
    "sg:province":"TX",
    "sg:tags":[
        "shop"
    ],
    "wof:name":"Little Red Hen The",
    "wof:placetype":"venue"
},
  "geometry": {"coordinates":[-96.61584000000001,33.198042],"type":"Point"}
}