{
  "type": "Feature",
  "properties": {
    "iso:country":"US",
    "sg:address":"2819 Fontana Dr",
    "sg:city":"Houston",
    "sg:classifiers":[
        {
            "category":"Professional",
            "type":"Services"
        }
    ],
    "sg:phone":"+1 713 907 3699",
    "sg:postcode":"77043",
    "sg:province":"TX",
    "wof:name":"Dp Diabetic Products",
    "wof:placetype":"venue"
},
  "geometry": {"coordinates":[-95.55303000000001,29.824176],"type":"Point"}
}