{
  "type": "Feature",
  "properties": {
    "iso:country":"US",
    "sg:address":"551 Co Rd Ff",
    "sg:city":"Wilson",
    "sg:phone":"+1 806 996 5482",
    "sg:postcode":"79373",
    "sg:province":"TX",
    "sg:tags":[
        "farm",
        "cotton"
    ],
    "wof:name":"Breiger Farms",
    "wof:placetype":"venue"
},
  "geometry": {"coordinates":[-101.618673,33.338225],"type":"Point"}
}