{
  "type": "Feature",
  "properties": {
    "iso:country":"US",
    "sg:address":"2 Camden Ct",
    "sg:city":"Sugar Land",
    "sg:classifiers":[
        {
            "category":"Professional",
            "subcategory":"Business Services",
            "type":"Services"
        }
    ],
    "sg:phone":"+1 281 265 8945",
    "sg:postcode":"77479",
    "sg:province":"TX",
    "wof:name":"Ipec Solutions LLC",
    "wof:placetype":"venue"
},
  "geometry": {"coordinates":[-95.62667999999999,29.561995],"type":"Point"}
}