{
  "type": "Feature",
  "properties": {
    "iso:country":"US",
    "sg:address":"2801 Hancock Dr",
    "sg:city":"Austin",
    "sg:classifiers":[
        {
            "category":"Landmark",
            "subcategory":"Monument",
            "type":"Public Place"
        }
    ],
    "sg:phone":"+1 512 454 3589",
    "sg:postcode":"78731",
    "sg:province":"TX",
    "wof:name":"Monument Company",
    "wof:placetype":"venue"
},
  "geometry": {"coordinates":[-97.749138,30.3276],"type":"Point"}
}