{
  "type": "Feature",
  "properties": {
    "iso:country":"US",
    "sg:address":"1005 W Davis St",
    "sg:city":"Dallas",
    "sg:classifiers":[
        {
            "category":"Shopping",
            "subcategory":"Used Merchandise",
            "type":"Retail Goods"
        }
    ],
    "sg:phone":"+1 214 948 3400",
    "sg:postcode":"75208",
    "sg:province":"TX",
    "wof:name":"Beckies Est Liquidation Servic",
    "wof:placetype":"venue"
},
  "geometry": {"coordinates":[-96.84030199999999,32.749555],"type":"Point"}
}