{
  "type": "Feature",
  "properties": {
    "iso:country":"US",
    "sg:address":"101 Munger St",
    "sg:city":"Pasadena",
    "sg:classifiers":[
        {
            "category":"Professional",
            "subcategory":"Computer Services",
            "type":"Services"
        }
    ],
    "sg:phone":"+1 713 477 4195",
    "sg:postcode":"77506",
    "sg:province":"TX",
    "sg:tags":[
        "repair"
    ],
    "wof:name":"Digital Graphic Svc Inc",
    "wof:placetype":"venue"
},
  "geometry": {"coordinates":[-95.21059700000001,29.71142],"type":"Point"}
}