{
  "type": "Feature",
  "properties": {
    "iso:country":"US",
    "sg:address":"4734 Hidden Springs Dr",
    "sg:city":"Houston",
    "sg:classifiers":[
        {
            "category":"Professional",
            "type":"Services"
        }
    ],
    "sg:phone":"+1 281 855 4195",
    "sg:postcode":"77084",
    "sg:province":"TX",
    "wof:name":"Lynn D Taylor Inc",
    "wof:placetype":"venue"
},
  "geometry": {"coordinates":[-95.631574,29.842299],"type":"Point"}
}