{
  "type": "Feature",
  "properties": {
    "iso:country":"US",
    "sg:address":"6700 Denton Dr",
    "sg:city":"Dallas",
    "sg:classifiers":[
        {
            "category":"Manufacturing",
            "subcategory":"Printing",
            "type":"Manufacturing & Wholesale Goods"
        }
    ],
    "sg:phone":"+1 214 904 2100",
    "sg:postcode":"75235",
    "sg:province":"TX",
    "sg:tags":[
        "printer"
    ],
    "sg:website":"www.wpcnet.com",
    "wof:name":"Williamson Printing Corp",
    "wof:placetype":"venue"
},
  "geometry": {"coordinates":[-96.844669,32.832915],"type":"Point"}
}