{
  "type": "Feature",
  "properties": {
    "iso:country":"US",
    "sg:address":"2216 S Eastern St",
    "sg:city":"Amarillo",
    "sg:classifiers":[
        {
            "category":"Freight",
            "type":"Transportation"
        }
    ],
    "sg:phone":"+1 806 331 0039",
    "sg:postcode":"79118",
    "sg:province":"TX",
    "sg:tags":[
        "marina",
        "operation",
        "ware",
        "special",
        "general"
    ],
    "wof:name":"Amarillo Boat & Rv Storage",
    "wof:placetype":"venue"
},
  "geometry": {"coordinates":[-101.77778000000001,35.189987],"type":"Point"}
}