{
  "type": "Feature",
  "properties": {
    "iso:country":"US",
    "sg:address":"2601 S Hampton Rd",
    "sg:city":"Dallas",
    "sg:classifiers":[
        {
            "category":"Shopping",
            "subcategory":"Jewelry",
            "type":"Retail Goods"
        },
        {
            "category":"Shopping",
            "subcategory":"Pawn Shop",
            "type":"Retail Goods"
        }
    ],
    "sg:phone":"+1 877 382 2323",
    "sg:postcode":"75233",
    "sg:province":"TX",
    "sg:website":"www.speedycashgold.com/?k=21#cid...",
    "wof:name":"Speedy Cash Gold",
    "wof:placetype":"venue"
},
  "geometry": {"coordinates":[-96.857294,32.720057],"type":"Point"}
}