{
  "type": "Feature",
  "properties": {
    "iso:country":"US",
    "sg:address":"6805 Main St",
    "sg:city":"Lewisville",
    "sg:classifiers":[
        {
            "category":"Health Services",
            "subcategory":"Chiropractor",
            "type":"Services"
        }
    ],
    "sg:phone":"+1 972 625 6700",
    "sg:postcode":"75056",
    "sg:province":"TX",
    "wof:name":"Chicoine Chiropractic Clinic",
    "wof:placetype":"venue"
},
  "geometry": {"coordinates":[-96.892724,33.096614],"type":"Point"}
}