{
  "type": "Feature",
  "properties": {
    "iso:country":"US",
    "sg:address":"1501 W Main St",
    "sg:city":"Rio Grande City",
    "sg:classifiers":[
        {
            "category":"Home & Garden",
            "subcategory":"Carpets & Floor Coverings",
            "type":"Retail Goods"
        }
    ],
    "sg:phone":"+1 956 487 6600",
    "sg:postcode":"78582",
    "sg:province":"TX",
    "wof:name":"Wallys Carpets",
    "wof:placetype":"venue"
},
  "geometry": {"coordinates":[-98.836392,26.37859],"type":"Point"}
}