{
  "type": "Feature",
  "properties": {
    "iso:country":"US",
    "sg:address":"15541 El Estado Dr",
    "sg:city":"Dallas",
    "sg:classifiers":[
        {
            "category":"Freight",
            "type":"Transportation"
        }
    ],
    "sg:phone":"+1 214 503 2600",
    "sg:postcode":"75248",
    "sg:province":"TX",
    "sg:tags":[
        "broker",
        "trucking"
    ],
    "wof:name":"Sears Lagistics",
    "wof:placetype":"venue"
},
  "geometry": {"coordinates":[-96.771587,32.960469],"type":"Point"}
}