{
  "type": "Feature",
  "properties": {
    "iso:country":"US",
    "sg:address":"905 San Gabriel Ranch Rd",
    "sg:city":"Liberty Hill",
    "sg:classifiers":[
        {
            "category":"Retail",
            "subcategory":"Portrait Studio",
            "type":"Services"
        }
    ],
    "sg:phone":"+1 512 515 0919",
    "sg:postcode":"78642",
    "sg:province":"TX",
    "sg:tags":[
        "photo"
    ],
    "wof:name":"Sandees Photography",
    "wof:placetype":"venue"
},
  "geometry": {"coordinates":[-97.91076700000001,30.710526],"type":"Point"}
}