{
  "type": "Feature",
  "properties": {
    "iso:country":"US",
    "sg:address":"2108 Calais Way",
    "sg:city":"Arlington",
    "sg:classifiers":[
        {
            "category":"Real Estate",
            "subcategory":"Real Estate Operator",
            "type":"Services"
        }
    ],
    "sg:phone":"+1 817 649 9149",
    "sg:postcode":"76006",
    "sg:province":"TX",
    "sg:tags":[
        "apartment"
    ],
    "wof:name":"Springfield At Ballpark Way",
    "wof:placetype":"venue"
},
  "geometry": {"coordinates":[-97.07236,32.765736],"type":"Point"}
}