{
  "type": "Feature",
  "properties": {
    "iso:country":"US",
    "sg:address":"212 S Oak St",
    "sg:city":"Kermit",
    "sg:classifiers":[
        {
            "category":"Education",
            "subcategory":"Special Training",
            "type":"Public Place"
        }
    ],
    "sg:phone":"+1 432 586 2236",
    "sg:postcode":"79745",
    "sg:province":"TX",
    "sg:tags":[
        "center"
    ],
    "wof:name":"Silly Bug Learning Ctr",
    "wof:placetype":"venue"
},
  "geometry": {"coordinates":[-103.09394899999999,31.856373],"type":"Point"}
}