{
  "type": "Feature",
  "properties": {
    "iso:country":"US",
    "sg:address":"18861 Harbor Side Blvd",
    "sg:city":"Montgomery",
    "sg:classifiers":[
        {
            "category":"Building & Trades",
            "subcategory":"Construction",
            "type":"Services"
        }
    ],
    "sg:phone":"+1 936 582 1595",
    "sg:postcode":"77356",
    "sg:province":"TX",
    "sg:tags":[
        "home",
        "builder"
    ],
    "wof:name":"Barnett & Co Custom Homes",
    "wof:placetype":"venue"
},
  "geometry": {"coordinates":[-95.65489599999999,30.398069],"type":"Point"}
}