{
  "type": "Feature",
  "properties": {
    "iso:country":"US",
    "sg:address":"1823 W Gulf Bank Rd",
    "sg:city":"Houston",
    "sg:classifiers":[
        {
            "category":"Building & Trades",
            "subcategory":"Construction",
            "type":"Services"
        }
    ],
    "sg:phone":"+1 281 445 2591",
    "sg:postcode":"77088",
    "sg:province":"TX",
    "sg:tags":[
        "contractor"
    ],
    "wof:name":"Johnson Gutter Service",
    "wof:placetype":"venue"
},
  "geometry": {"coordinates":[-95.431104,29.886194],"type":"Point"}
}