{
  "type": "Feature",
  "properties": {
    "iso:country":"US",
    "sg:address":"1106 N Texas Blvd",
    "sg:city":"Alice",
    "sg:classifiers":[
        {
            "category":"Food & Beverages",
            "subcategory":"Groceries & Convenience Stores",
            "type":"Retail Goods"
        }
    ],
    "sg:phone":"+1 361 661 0700",
    "sg:postcode":"78332",
    "sg:province":"TX",
    "wof:name":"Yu Mis",
    "wof:placetype":"venue"
},
  "geometry": {"coordinates":[-98.06471999999999,27.760707],"type":"Point"}
}