{
  "type": "Feature",
  "properties": {
    "iso:country":"US",
    "sg:address":"10526 Cayuga Dr",
    "sg:city":"Dallas",
    "sg:classifiers":[
        {
            "category":"Home & Garden",
            "subcategory":"Carpets & Floor Coverings",
            "type":"Retail Goods"
        }
    ],
    "sg:phone":"+1 214 328 2144",
    "sg:postcode":"75228",
    "sg:province":"TX",
    "wof:name":"RC Carpet Services",
    "wof:placetype":"venue"
},
  "geometry": {"coordinates":[-96.685884,32.837616],"type":"Point"}
}