{
  "type": "Feature",
  "properties": {
    "iso:country":"US",
    "sg:address":"4114 Stone Haven Dr",
    "sg:city":"Garland",
    "sg:classifiers":[
        {
            "category":"Shopping",
            "subcategory":"Clothing, Apparel, & Fashions",
            "type":"Retail Goods"
        }
    ],
    "sg:phone":"+1 214 703 6676",
    "sg:postcode":"75043",
    "sg:province":"TX",
    "sg:tags":[
        "apparel",
        "women's"
    ],
    "wof:name":"Lulu S Fashions",
    "wof:placetype":"venue"
},
  "geometry": {"coordinates":[-96.569293,32.864227],"type":"Point"}
}