{
  "type": "Feature",
  "properties": {
    "iso:country":"US",
    "sg:address":"1701 Bauerle Ave",
    "sg:city":"Austin",
    "sg:classifiers":[
        {
            "category":"Professional",
            "subcategory":"Management & Consulting",
            "type":"Services"
        }
    ],
    "sg:phone":"+1 512 440 0309",
    "sg:postcode":"78704",
    "sg:province":"TX",
    "sg:tags":[
        "consultant",
        "training"
    ],
    "wof:name":"Quantum Leadership Solution",
    "wof:placetype":"venue"
},
  "geometry": {"coordinates":[-97.77007,30.251803],"type":"Point"}
}