{
  "type": "Feature",
  "properties": {
    "iso:country":"US",
    "sg:address":"450 Cypress Ridge Rd",
    "sg:city":"Mc Queeney",
    "sg:classifiers":[
        {
            "category":"Professional",
            "subcategory":"Management & Consulting",
            "type":"Services"
        }
    ],
    "sg:phone":"+1 830 560 1770",
    "sg:postcode":"78123",
    "sg:province":"TX",
    "sg:tags":[
        "business"
    ],
    "wof:name":"Stanley Spurkosky Consulting",
    "wof:placetype":"venue"
},
  "geometry": {"coordinates":[-98.031685,29.585508],"type":"Point"}
}