{
  "type": "Feature",
  "properties": {
    "iso:country":"US",
    "sg:address":"31843 Edgewater Dr",
    "sg:city":"Magnolia",
    "sg:classifiers":[
        {
            "category":"Wholesale",
            "subcategory":"Non-durable Goods",
            "type":"Manufacturing & Wholesale Goods"
        }
    ],
    "sg:phone":"+1 281 356 3502",
    "sg:postcode":"77354",
    "sg:province":"TX",
    "wof:name":"Texas Outdoor Products",
    "wof:placetype":"venue"
},
  "geometry": {"coordinates":[-95.64164599999999,30.208032],"type":"Point"}
}