{
  "type": "Feature",
  "properties": {
    "iso:country":"US",
    "sg:address":"19514 Turtle Creek Ln",
    "sg:city":"Magnolia",
    "sg:classifiers":[
        {
            "category":"Building & Trades",
            "subcategory":"Construction",
            "type":"Services"
        }
    ],
    "sg:phone":"+1 281 259 8699",
    "sg:postcode":"77355",
    "sg:province":"TX",
    "sg:tags":[
        "residential"
    ],
    "wof:name":"Hoot General Construction",
    "wof:placetype":"venue"
},
  "geometry": {"coordinates":[-95.743357,30.119816],"type":"Point"}
}