{
  "type": "Feature",
  "properties": {
    "iso:country":"US",
    "sg:address":"616 W Main",
    "sg:city":"Tomball",
    "sg:classifiers":[
        {
            "category":"Education",
            "subcategory":"Dance Studio",
            "type":"Public Place"
        }
    ],
    "sg:phone":"+1 281 255 6222",
    "sg:postcode":"77375",
    "sg:province":"TX",
    "sg:tags":[
        "instruction",
        "dancing"
    ],
    "wof:name":"Ballet Conservatory",
    "wof:placetype":"venue"
},
  "geometry": {"coordinates":[-95.619511,30.095759],"type":"Point"}
}