{
  "type": "Feature",
  "properties": {
    "iso:country":"US",
    "sg:address":"1622 S Western St",
    "sg:city":"Amarillo",
    "sg:classifiers":[
        {
            "category":"Building & Trades",
            "subcategory":"Construction",
            "type":"Services"
        }
    ],
    "sg:phone":"+1 806 356 9104",
    "sg:postcode":"79106",
    "sg:province":"TX",
    "sg:tags":[
        "contractor"
    ],
    "wof:name":"A T R Roofing",
    "wof:placetype":"venue"
},
  "geometry": {"coordinates":[-101.884102,35.197371],"type":"Point"}
}