{
  "type": "Feature",
  "properties": {
    "iso:country":"US",
    "sg:address":"5608 Zelma Dr",
    "sg:city":"Houston",
    "sg:classifiers":[
        {
            "category":"Communications",
            "type":"Services"
        }
    ],
    "sg:phone":"+1 713 294 9070",
    "sg:postcode":"77076",
    "sg:province":"TX",
    "sg:tags":[
        "application",
        "internet",
        "specialized",
        "solution",
        "database"
    ],
    "wof:name":"Houstons Internet DOT Com",
    "wof:placetype":"venue"
},
  "geometry": {"coordinates":[-95.38644499999999,29.850174],"type":"Point"}
}