{
  "type": "Feature",
  "properties": {
    "iso:country":"US",
    "sg:address":"819 Augusta St",
    "sg:city":"San Antonio",
    "sg:classifiers":[
        {
            "category":"Restaurant",
            "type":"Food & Drink"
        }
    ],
    "sg:menulink":"http://www.allmenus.com/tx/san-antonio/14416-the-bright-shawl/menu/",
    "sg:phone":"+1 210 225 6366",
    "sg:postcode":"78215",
    "sg:province":"TX",
    "sg:tags":[
        "american"
    ],
    "wof:name":"The Bright Shawl",
    "wof:placetype":"venue"
},
  "geometry": {"coordinates":[-98.487787,29.434523],"type":"Point"}
}