{
  "type": "Feature",
  "properties": {
    "iso:country":"US",
    "sg:address":"7766 US Hwy 287",
    "sg:city":"Childress",
    "sg:classifiers":[
        {
            "category":"Autos & Motor Vehicles",
            "subcategory":"Automobile Sales",
            "type":"Retail Goods"
        }
    ],
    "sg:phone":"+1 940 937 3935",
    "sg:postcode":"79201",
    "sg:province":"TX",
    "sg:tags":[
        "used"
    ],
    "wof:name":"Smittys Auto Sales",
    "wof:placetype":"venue"
},
  "geometry": {"coordinates":[-100.246246,34.441034],"type":"Point"}
}