{
  "type": "Feature",
  "properties": {
    "iso:country":"US",
    "sg:address":"5005 N FM 1417",
    "sg:city":"Sherman",
    "sg:classifiers":[
        {
            "category":"Retail",
            "subcategory":"Veterinary Services",
            "type":"Services"
        }
    ],
    "sg:phone":"+1 903 868 9434",
    "sg:postcode":"75092",
    "sg:province":"TX",
    "wof:name":"Texoma Veterinary Hospital",
    "wof:placetype":"venue"
},
  "geometry": {"coordinates":[-96.64926199999999,33.691424],"type":"Point"}
}