{
  "type": "Feature",
  "properties": {
    "iso:country":"US",
    "sg:address":"502 Marsha St",
    "sg:city":"Keller",
    "sg:classifiers":[
        {
            "category":"Social Services",
            "subcategory":"Child Care",
            "type":"Services"
        }
    ],
    "sg:phone":"+1 817 431 6185",
    "sg:postcode":"76248",
    "sg:province":"TX",
    "wof:name":"Teresa Ann Smith",
    "wof:placetype":"venue"
},
  "geometry": {"coordinates":[-97.245154,32.936604],"type":"Point"}
}