{
  "type": "Feature",
  "properties": {
    "iso:country":"US",
    "sg:address":"508 16th St",
    "sg:city":"Canyon",
    "sg:classifiers":[
        {
            "category":"Professional",
            "subcategory":"Management & Consulting",
            "type":"Services"
        }
    ],
    "sg:phone":"+1 806 655 1081",
    "sg:postcode":"79015",
    "sg:province":"TX",
    "wof:name":"Aramark",
    "wof:placetype":"venue"
},
  "geometry": {"coordinates":[-101.92764699999999,34.978758],"type":"Point"}
}