{
  "type": "Feature",
  "properties": {
    "iso:country":"US",
    "sg:address":"4950 W Illinois Ave",
    "sg:city":"Dallas",
    "sg:classifiers":[
        {
            "category":"Shopping",
            "subcategory":"Bicycles & Sporting Goods",
            "type":"Retail Goods"
        }
    ],
    "sg:phone":"+1 214 330 8071",
    "sg:postcode":"75211",
    "sg:province":"TX",
    "wof:name":"Azteca Sports",
    "wof:placetype":"venue"
},
  "geometry": {"coordinates":[-96.907856,32.720254],"type":"Point"}
}