{
  "type": "Feature",
  "properties": {
    "iso:country":"US",
    "sg:address":"2708 Sunset Strip",
    "sg:city":"Greenville",
    "sg:classifiers":[
        {
            "category":"Professional",
            "type":"Services"
        }
    ],
    "sg:phone":"+1 903 450 1169",
    "sg:postcode":"75402",
    "sg:province":"TX",
    "wof:name":"L Otis James Jr",
    "wof:placetype":"venue"
},
  "geometry": {"coordinates":[-96.108769,33.08157],"type":"Point"}
}