{
  "type": "Feature",
  "properties": {
    "iso:country":"US",
    "sg:address":"6905 Hawaii Ln",
    "sg:city":"Arlington",
    "sg:classifiers":[
        {
            "category":"Professional",
            "subcategory":"Computer Services",
            "type":"Services"
        }
    ],
    "sg:phone":"+1 817 561 2289",
    "sg:postcode":"76016",
    "sg:province":"TX",
    "sg:tags":[
        "related"
    ],
    "wof:name":"Engineering & Computer Svcs",
    "wof:placetype":"venue"
},
  "geometry": {"coordinates":[-97.216652,32.673263],"type":"Point"}
}