{
  "type": "Feature",
  "properties": {
    "iso:country":"US",
    "sg:address":"1825 W Walnut Hill Ln",
    "sg:city":"Irving",
    "sg:classifiers":[
        {
            "category":"Insurance",
            "subcategory":"Insurance Agent",
            "type":"Services"
        }
    ],
    "sg:phone":"+1 972 331 2636",
    "sg:postcode":"75038",
    "sg:province":"TX",
    "wof:name":"Clement Washington Insurance A",
    "wof:placetype":"venue"
},
  "geometry": {"coordinates":[-96.970996,32.872319],"type":"Point"}
}