{
  "type": "Feature",
  "properties": {
    "iso:country":"US",
    "sg:address":"1103 Woodbridge Ave",
    "sg:city":"Pearland",
    "sg:classifiers":[
        {
            "category":"Insurance",
            "subcategory":"Hazard Insurance",
            "type":"Services"
        }
    ],
    "sg:phone":"+1 713 436 9539",
    "sg:postcode":"77584",
    "sg:province":"TX",
    "sg:tags":[
        "carrier"
    ],
    "wof:name":"CNA Benefits",
    "wof:placetype":"venue"
},
  "geometry": {"coordinates":[-95.377523,29.571245],"type":"Point"}
}