{
  "type": "Feature",
  "properties": {
    "iso:country":"US",
    "sg:address":"12511 North Fwy",
    "sg:city":"Houston",
    "sg:classifiers":[
        {
            "category":"Manufacturing",
            "subcategory":"Rubber & Plastics",
            "type":"Manufacturing & Wholesale Goods"
        }
    ],
    "sg:phone":"+1 281 873 7446",
    "sg:postcode":"77060",
    "sg:province":"TX",
    "sg:tags":[
        "product",
        "mfg"
    ],
    "wof:name":"American Plastic Fabricators",
    "wof:placetype":"venue"
},
  "geometry": {"coordinates":[-95.417731,29.949706],"type":"Point"}
}