{
  "type": "Feature",
  "properties": {
    "iso:country":"US",
    "sg:address":"805 Harris Ave",
    "sg:city":"Kemah",
    "sg:classifiers":[
        {
            "category":"Travel",
            "subcategory":"Hotels & Motels",
            "type":"Entertainment"
        }
    ],
    "sg:phone":"+1 281 334 0003",
    "sg:postcode":"77565",
    "sg:province":"TX",
    "wof:name":"Holiday Inn Kemah",
    "wof:placetype":"venue"
},
  "geometry": {"coordinates":[-95.01915,29.54149],"type":"Point"}
}