{
  "type": "Feature",
  "properties": {
    "iso:country":"US",
    "sg:address":"404 E Commerce St",
    "sg:city":"Brady",
    "sg:classifiers":[
        {
            "category":"Personal",
            "subcategory":"Beauty Salon",
            "type":"Services"
        }
    ],
    "sg:phone":"+1 325 597 5122",
    "sg:postcode":"76825",
    "sg:province":"TX",
    "sg:tags":[
        "shop"
    ],
    "wof:name":"Hair Store",
    "wof:placetype":"venue"
},
  "geometry": {"coordinates":[-99.33229300000001,31.134673],"type":"Point"}
}