{
  "type": "Feature",
  "properties": {
    "iso:country":"US",
    "sg:address":"112 S Commercial Ave",
    "sg:city":"Coleman",
    "sg:classifiers":[
        {
            "category":"Real Estate",
            "subcategory":"Real Estate Agent",
            "type":"Services"
        }
    ],
    "sg:phone":"+1 325 625 4111",
    "sg:postcode":"76834",
    "sg:province":"TX",
    "sg:tags":[
        "brokerage",
        "sale"
    ],
    "wof:name":"Century 21",
    "wof:placetype":"venue"
},
  "geometry": {"coordinates":[-99.423058,31.830869],"type":"Point"}
}