{
  "type": "Feature",
  "properties": {
    "iso:country":"US",
    "sg:address":"1032 Ave G",
    "sg:city":"Ralls",
    "sg:classifiers":[
        {
            "category":"Farming",
            "subcategory":"Farm & Veterinary Services",
            "type":"Manufacturing & Wholesale Goods"
        }
    ],
    "sg:phone":"+1 806 649 7438",
    "sg:postcode":"79357",
    "sg:province":"TX",
    "sg:tags":[
        "aerial",
        "applicator",
        "cotton"
    ],
    "wof:name":"Laminack Cot Frm & Flying Svc",
    "wof:placetype":"venue"
},
  "geometry": {"coordinates":[-101.385375,33.68157],"type":"Point"}
}