{
  "type": "Feature",
  "properties": {
    "iso:country":"US",
    "sg:address":"130 N Central Expy",
    "sg:city":"Mc Kinney",
    "sg:classifiers":[
        {
            "category":"Health Services",
            "subcategory":"Health Practitioner",
            "type":"Services"
        }
    ],
    "sg:phone":"+1 972 548 5348",
    "sg:postcode":"75070",
    "sg:province":"TX",
    "wof:name":"Physical Rhbltation Ctr McKinn",
    "wof:placetype":"venue"
},
  "geometry": {"coordinates":[-96.63933,33.199355],"type":"Point"}
}