{
  "type": "Feature",
  "properties": {
    "iso:country":"US",
    "sg:address":"12209 Tomball Pkwy",
    "sg:city":"Houston",
    "sg:classifiers":[
        {
            "category":"Autos & Motor Vehicles",
            "subcategory":"Automobile Sales",
            "type":"Retail Goods"
        }
    ],
    "sg:phone":"+1 281 820 2926",
    "sg:postcode":"77086",
    "sg:province":"TX",
    "sg:tags":[
        "repair",
        "used",
        "general"
    ],
    "wof:name":"N&S Motors",
    "wof:placetype":"venue"
},
  "geometry": {"coordinates":[-95.47458899999999,29.907807],"type":"Point"}
}