{
  "type": "Feature",
  "properties": {
    "iso:country":"US",
    "sg:address":"1451 Woodhollow Dr",
    "sg:city":"Houston",
    "sg:classifiers":[
        {
            "category":"Professional",
            "subcategory":"Management & Consulting",
            "type":"Services"
        }
    ],
    "sg:phone":"+1 615 771 9989",
    "sg:postcode":"77057",
    "sg:province":"TX",
    "wof:name":"Intelometry Inc",
    "wof:placetype":"venue"
},
  "geometry": {"coordinates":[-95.497404,29.751159],"type":"Point"}
}