{
  "type": "Feature",
  "properties": {
    "iso:country":"US",
    "sg:address":"7017 Mills Branch Cir",
    "sg:city":"Plano",
    "sg:classifiers":[
        {
            "category":"Professional",
            "subcategory":"Business Services",
            "type":"Services"
        }
    ],
    "sg:phone":"+1 214 616 5231",
    "sg:postcode":"75024",
    "sg:province":"TX",
    "wof:name":"Inspiring Designs Inc",
    "wof:placetype":"venue"
},
  "geometry": {"coordinates":[-96.85326499999999,33.067835],"type":"Point"}
}