{
  "type": "Feature",
  "properties": {
    "iso:country":"US",
    "sg:address":"16714 Doverwood Way",
    "sg:city":"Houston",
    "sg:classifiers":[
        {
            "category":"Shopping",
            "subcategory":"Pets & Pet Supplies",
            "type":"Retail Goods"
        }
    ],
    "sg:phone":"+1 713 488 8560",
    "sg:postcode":"77058",
    "sg:province":"TX",
    "sg:tags":[
        "furnishing",
        "dog",
        "store",
        "cat"
    ],
    "wof:name":"Lake Clear Pets",
    "wof:placetype":"venue"
},
  "geometry": {"coordinates":[-95.109099,29.562662],"type":"Point"}
}