{
  "type": "Feature",
  "properties": {
    "iso:country":"US",
    "sg:address":"225 Helen Dr",
    "sg:city":"Deer Park",
    "sg:classifiers":[
        {
            "category":"Farming",
            "subcategory":"Livestock Farm",
            "type":"Manufacturing & Wholesale Goods"
        }
    ],
    "sg:phone":"+1 281 479 2250",
    "sg:postcode":"77536",
    "sg:province":"TX",
    "sg:tags":[
        "specialty",
        "animal"
    ],
    "wof:name":"3 P Show Animals",
    "wof:placetype":"venue"
},
  "geometry": {"coordinates":[-95.12116899999999,29.699497],"type":"Point"}
}