{
  "type": "Feature",
  "properties": {
    "iso:country":"US",
    "sg:address":"1767 Co Rd 3799",
    "sg:city":"Quinlan",
    "sg:classifiers":[
        {
            "category":"Organizations",
            "subcategory":"Religious Organization",
            "type":"Services"
        }
    ],
    "sg:phone":"+1 903 356 0800",
    "sg:postcode":"75474",
    "sg:province":"TX",
    "wof:name":"Calvary Baptist Church",
    "wof:placetype":"venue"
},
  "geometry": {"coordinates":[-96.083816,32.868464],"type":"Point"}
}