{
  "type": "Feature",
  "properties": {
    "iso:country":"US",
    "sg:address":"11322 Brass Hammer Ct",
    "sg:city":"Houston",
    "sg:classifiers":[
        {
            "category":"Restaurant",
            "type":"Food & Drink"
        }
    ],
    "sg:phone":"+1 281 894 8682",
    "sg:postcode":"77065",
    "sg:province":"TX",
    "sg:tags":[
        "eating"
    ],
    "wof:name":"Chucho Crazy Chicken",
    "wof:placetype":"venue"
},
  "geometry": {"coordinates":[-95.589066,29.917141],"type":"Point"}
}