{
  "type": "Feature",
  "properties": {
    "iso:country":"US",
    "sg:address":"13301 Tichester Ct",
    "sg:city":"Austin",
    "sg:classifiers":[
        {
            "category":"Building & Trades",
            "subcategory":"Construction",
            "type":"Services"
        }
    ],
    "sg:phone":"+1 512 331 6130",
    "sg:postcode":"78729",
    "sg:province":"TX",
    "sg:tags":[
        "house"
    ],
    "wof:name":"Phoenix Medical Construction",
    "wof:placetype":"venue"
},
  "geometry": {"coordinates":[-97.77403700000001,30.463856],"type":"Point"}
}