{
  "type": "Feature",
  "properties": {
    "iso:country":"US",
    "sg:address":"17330 Spring Cypress Rd",
    "sg:city":"Cypress",
    "sg:classifiers":[
        {
            "category":"Restaurant",
            "type":"Food & Drink"
        }
    ],
    "sg:phone":"+1 281 256 7388",
    "sg:postcode":"77429",
    "sg:province":"TX",
    "wof:name":"Choon Bai Chinese Cafe",
    "wof:placetype":"venue"
},
  "geometry": {"coordinates":[-95.68948,29.972744],"type":"Point"}
}