{
  "type": "Feature",
  "properties": {
    "iso:country":"US",
    "sg:address":"313 Little Lake Rd",
    "sg:city":"Hutto",
    "sg:classifiers":[
        {
            "category":"Professional",
            "subcategory":"Art Services",
            "type":"Services"
        }
    ],
    "sg:phone":"+1 512 759 2633",
    "sg:postcode":"78634",
    "sg:province":"TX",
    "sg:tags":[
        "designer",
        "display",
        "producer"
    ],
    "wof:name":"Dana Dillon Design",
    "wof:placetype":"venue"
},
  "geometry": {"coordinates":[-97.57310099999999,30.507184],"type":"Point"}
}