{
  "type": "Feature",
  "properties": {
    "iso:country":"US",
    "sg:address":"114 NE 4th St",
    "sg:city":"Grand Prairie",
    "sg:classifiers":[
        {
            "category":"Real Estate",
            "subcategory":"Real Estate Agent",
            "type":"Services"
        }
    ],
    "sg:phone":"+1 972 263 6935",
    "sg:postcode":"75050",
    "sg:province":"TX",
    "sg:tags":[
        "appraiser"
    ],
    "wof:name":"Tommy Garrett & Assoc",
    "wof:placetype":"venue"
},
  "geometry": {"coordinates":[-96.99985100000001,32.746759],"type":"Point"}
}