{
  "type": "Feature",
  "properties": {
    "iso:country":"US",
    "sg:address":"3555 Knickerbocker Rd",
    "sg:city":"San Angelo",
    "sg:classifiers":[
        {
            "category":"Health Services",
            "subcategory":"Doctor",
            "type":"Services"
        }
    ],
    "sg:phone":"+1 325 224 5181",
    "sg:postcode":"76904",
    "sg:province":"TX",
    "sg:tags":[
        "physician",
        "surgeon"
    ],
    "wof:name":"Barbara Montague MD",
    "wof:placetype":"venue"
},
  "geometry": {"coordinates":[-100.470288,31.420037],"type":"Point"}
}