{
  "type": "Feature",
  "properties": {
    "iso:country":"US",
    "sg:address":"213 N Val Verde Cir",
    "sg:city":"Keene",
    "sg:classifiers":[
        {
            "category":"Real Estate",
            "subcategory":"Real Estate Operator",
            "type":"Services"
        }
    ],
    "sg:phone":"+1 817 641 2682",
    "sg:postcode":"76059",
    "sg:province":"TX",
    "sg:tags":[
        "apartment"
    ],
    "wof:name":"Sherwood Arms Apartments",
    "wof:placetype":"venue"
},
  "geometry": {"coordinates":[-97.328823,32.395264],"type":"Point"}
}