{
  "type": "Feature",
  "properties": {
    "iso:country":"US",
    "sg:address":"9627 Arborhill Dr",
    "sg:city":"Dallas",
    "sg:classifiers":[
        {
            "category":"Social Services",
            "subcategory":"Child Care",
            "type":"Services"
        }
    ],
    "sg:phone":"+1 214 341 0988",
    "sg:postcode":"75243",
    "sg:province":"TX",
    "sg:tags":[
        "day"
    ],
    "wof:name":"Rex L Day",
    "wof:placetype":"venue"
},
  "geometry": {"coordinates":[-96.729319,32.906425],"type":"Point"}
}