{
  "type": "Feature",
  "properties": {
    "iso:country":"US",
    "sg:address":"204 Boca Chica Blvd",
    "sg:city":"Brownsville",
    "sg:classifiers":[
        {
            "category":"Social Services",
            "subcategory":"Child Care",
            "type":"Services"
        }
    ],
    "sg:phone":"+1 956 542 7576",
    "sg:postcode":"78520",
    "sg:province":"TX",
    "sg:tags":[
        "day"
    ],
    "wof:name":"Montessori School",
    "wof:placetype":"venue"
},
  "geometry": {"coordinates":[-97.517444,25.926372],"type":"Point"}
}