{
  "type": "Feature",
  "properties": {
    "iso:country":"US",
    "sg:address":"3724 Jefferson Street",
    "sg:city":"Austin",
    "sg:classifiers":[
        {
            "category":"Health Services",
            "subcategory":"Health Practitioner",
            "type":"Services"
        }
    ],
    "sg:phone":"+1 512 453 6778",
    "sg:postcode":"78731",
    "sg:province":"TX",
    "sg:tags":[
        "therapy",
        "physical"
    ],
    "wof:name":"Woodfin Shelia Speech Patholgst",
    "wof:placetype":"venue"
},
  "geometry": {"coordinates":[-97.750924,30.308855],"type":"Point"}
}