{
  "type": "Feature",
  "properties": {
    "iso:country":"US",
    "sg:address":"29 Edge Rock Dr",
    "sg:city":"Del Valle",
    "sg:classifiers":[
        {
            "category":"Building & Trades",
            "subcategory":"Construction",
            "type":"Services"
        }
    ],
    "sg:phone":"+1 512 247 2855",
    "sg:postcode":"78617",
    "sg:province":"TX",
    "sg:tags":[
        "nonresidential"
    ],
    "wof:name":"R&J Construction",
    "wof:placetype":"venue"
},
  "geometry": {"coordinates":[-97.56744399999999,30.131012],"type":"Point"}
}