{
  "type": "Feature",
  "properties": {
    "iso:country":"US",
    "sg:address":"184 Quitman St",
    "sg:city":"Emory",
    "sg:classifiers":[
        {
            "category":"Personal",
            "subcategory":"Barber",
            "type":"Services"
        }
    ],
    "sg:phone":"+1 903 473 1441",
    "sg:postcode":"75440",
    "sg:province":"TX",
    "sg:tags":[
        "shop"
    ],
    "wof:name":"Dale's Barber Shop",
    "wof:placetype":"venue"
},
  "geometry": {"coordinates":[-95.76603900000001,32.874692],"type":"Point"}
}