{
  "type": "Feature",
  "properties": {
    "iso:country":"US",
    "sg:address":"5131 Mallow St",
    "sg:city":"Houston",
    "sg:classifiers":[
        {
            "category":"Travel",
            "subcategory":"Hotels & Motels",
            "type":"Entertainment"
        }
    ],
    "sg:phone":"+1 713 731 1735",
    "sg:postcode":"77033",
    "sg:province":"TX",
    "sg:tags":[
        "operation"
    ],
    "wof:name":"Hideaway Motel",
    "wof:placetype":"venue"
},
  "geometry": {"coordinates":[-95.34890300000001,29.659784],"type":"Point"}
}