{
  "type": "Feature",
  "properties": {
    "iso:country":"US",
    "sg:address":"2181 W Green Oaks Blvd",
    "sg:city":"Arlington",
    "sg:classifiers":[
        {
            "category":"Personal",
            "subcategory":"Beauty Salon",
            "type":"Services"
        }
    ],
    "sg:phone":"+1 817 451 4348",
    "sg:postcode":"76013",
    "sg:province":"TX",
    "sg:tags":[
        "shop"
    ],
    "wof:name":"Serenity Spa & Salon",
    "wof:placetype":"venue"
},
  "geometry": {"coordinates":[-97.190645,32.709084],"type":"Point"}
}