{
  "type": "Feature",
  "properties": {
    "iso:country":"US",
    "sg:address":"1806 Center St",
    "sg:city":"Houston",
    "sg:classifiers":[
        {
            "category":"Shopping",
            "subcategory":"Computers & Home Electronics",
            "type":"Retail Goods"
        }
    ],
    "sg:phone":"+1 281 476 4841",
    "sg:postcode":"77007",
    "sg:province":"TX",
    "sg:tags":[
        "equipment",
        "dealer"
    ],
    "wof:name":"D P Micro",
    "wof:placetype":"venue"
},
  "geometry": {"coordinates":[-95.375896,29.768486],"type":"Point"}
}