{
  "type": "Feature",
  "properties": {
    "iso:country":"US",
    "sg:address":"1026 Red Bird Mall",
    "sg:city":"Duncanville",
    "sg:classifiers":[
        {
            "category":"Insurance",
            "subcategory":"Health Insurance",
            "type":"Services"
        }
    ],
    "sg:phone":"+1 972 709 1302",
    "sg:postcode":"75116",
    "sg:province":"TX",
    "sg:tags":[
        "market"
    ],
    "wof:name":"General Nutrition Centers",
    "wof:placetype":"venue"
},
  "geometry": {"coordinates":[-96.91330000000001,32.6618],"type":"Point"}
}