{
  "type": "Feature",
  "properties": {
    "iso:country":"US",
    "sg:address":"1500 Bluebonnet Trl",
    "sg:city":"Arlington",
    "sg:classifiers":[
        {
            "category":"Professional",
            "subcategory":"Computer Services",
            "type":"Services"
        }
    ],
    "sg:phone":"+1 817 469 7146",
    "sg:postcode":"76013",
    "sg:province":"TX",
    "sg:tags":[
        "datum"
    ],
    "wof:name":"Priscilla Rogers Consultants",
    "wof:placetype":"venue"
},
  "geometry": {"coordinates":[-97.131957,32.713051],"type":"Point"}
}