{
  "type": "Feature",
  "properties": {
    "iso:country":"US",
    "sg:address":"519 Ridge St",
    "sg:city":"Houston",
    "sg:classifiers":[
        {
            "category":"Arts & Performance",
            "subcategory":"Theater",
            "type":"Entertainment"
        }
    ],
    "sg:phone":"+1 281 300 1042",
    "sg:postcode":"77009",
    "sg:province":"TX",
    "sg:tags":[
        "band",
        "orchestra"
    ],
    "wof:name":"Cindy Scott Jazz Combo",
    "wof:placetype":"venue"
},
  "geometry": {"coordinates":[-95.377127,29.783086],"type":"Point"}
}