{
  "type": "Feature",
  "properties": {
    "iso:country":"US",
    "sg:address":"3755 S Capital of Texas Hwy",
    "sg:city":"Austin",
    "sg:classifiers":[
        {
            "category":"Professional",
            "subcategory":"Management & Consulting",
            "type":"Services"
        }
    ],
    "sg:phone":"+1 512 707 5120",
    "sg:postcode":"78704",
    "sg:province":"TX",
    "sg:tags":[
        "marketing",
        "consultant"
    ],
    "wof:name":"Strider Marketing",
    "wof:placetype":"venue"
},
  "geometry": {"coordinates":[-97.801141,30.242843],"type":"Point"}
}