{
  "type": "Feature",
  "properties": {
    "iso:country":"US",
    "sg:address":"304 S Timberland Dr",
    "sg:city":"Lufkin",
    "sg:classifiers":[
        {
            "category":"Autos & Motor Vehicles",
            "subcategory":"Automobile Sales",
            "type":"Retail Goods"
        },
        {
            "category":"Autos & Motor Vehicles",
            "subcategory":"Auto Supplies",
            "type":"Retail Goods"
        }
    ],
    "sg:phone":"+1 936 634 9222",
    "sg:postcode":"75901",
    "sg:province":"TX",
    "sg:tags":[
        "car",
        "used",
        "dealer"
    ],
    "wof:name":"Champion Auto Inc",
    "wof:placetype":"venue"
},
  "geometry": {"coordinates":[-94.72011999999999,31.33348],"type":"Point"}
}