{
  "type": "Feature",
  "properties": {
    "iso:country":"US",
    "sg:address":"1517 Warwick Rd",
    "sg:city":"Houston",
    "sg:classifiers":[
        {
            "category":"Building & Trades",
            "subcategory":"Landscaping Services",
            "type":"Services"
        }
    ],
    "sg:phone":"+1 832 452 7797",
    "sg:postcode":"77093",
    "sg:province":"TX",
    "sg:tags":[
        "landscape"
    ],
    "wof:name":"J & E Landscaping",
    "wof:placetype":"venue"
},
  "geometry": {"coordinates":[-95.359787,29.878846],"type":"Point"}
}