{
  "type": "Feature",
  "properties": {
    "iso:country":"US",
    "sg:address":"107 Bruton Terrace Ctr",
    "sg:city":"Dallas",
    "sg:classifiers":[
        {
            "category":"Personal",
            "subcategory":"Nail Salon",
            "type":"Services"
        }
    ],
    "sg:phone":"+1 214 275 6824",
    "sg:postcode":"75227",
    "sg:province":"TX",
    "wof:name":"P L Nail Salon",
    "wof:placetype":"venue"
},
  "geometry": {"coordinates":[-96.670303,32.7537],"type":"Point"}
}