{
  "type": "Feature",
  "properties": {
    "iso:country":"US",
    "sg:address":"3901 Wallingford Dr",
    "sg:city":"Garland",
    "sg:classifiers":[
        {
            "category":"Building & Trades",
            "subcategory":"Construction",
            "type":"Services"
        }
    ],
    "sg:phone":"+1 972 303 1880",
    "sg:postcode":"75043",
    "sg:province":"TX",
    "sg:tags":[
        "house"
    ],
    "wof:name":"Centex",
    "wof:placetype":"venue"
},
  "geometry": {"coordinates":[-96.57230199999999,32.858891],"type":"Point"}
}