{
  "type": "Feature",
  "properties": {
    "iso:country":"US",
    "sg:address":"1441 Farm St",
    "sg:city":"Bastrop",
    "sg:classifiers":[
        {
            "category":"Restaurant",
            "type":"Food & Drink"
        }
    ],
    "sg:phone":"+1 512 321 3626",
    "sg:postcode":"78602",
    "sg:province":"TX",
    "sg:tags":[
        "eating"
    ],
    "wof:name":"Goobers Bbq",
    "wof:placetype":"venue"
},
  "geometry": {"coordinates":[-97.312578,30.112807],"type":"Point"}
}