{
  "type": "Feature",
  "properties": {
    "iso:country":"US",
    "sg:address":"66 Daughtrey Ave",
    "sg:city":"Waco",
    "sg:classifiers":[
        {
            "category":"Professional",
            "subcategory":"Employment Agencies",
            "type":"Services"
        }
    ],
    "sg:phone":"+1 254 753 6551",
    "sg:postcode":"76706",
    "sg:province":"TX",
    "wof:name":"Brazos Jobs",
    "wof:placetype":"venue"
},
  "geometry": {"coordinates":[-97.107584,31.547963],"type":"Point"}
}