{
  "type": "Feature",
  "properties": {
    "iso:country":"US",
    "sg:address":"19331 Shiloh Creek Ln",
    "sg:city":"Katy",
    "sg:classifiers":[
        {
            "category":"Communications",
            "subcategory":"Film & Video Production",
            "type":"Services"
        }
    ],
    "sg:phone":"+1 281 345 2163",
    "sg:postcode":"77449",
    "sg:province":"TX",
    "sg:tags":[
        "motion"
    ],
    "wof:name":"On Q Video Productions",
    "wof:placetype":"venue"
},
  "geometry": {"coordinates":[-95.70820000000001,29.867572],"type":"Point"}
}