{
  "type": "Feature",
  "properties": {
    "iso:country":"US",
    "sg:address":"1712 11th St",
    "sg:city":"Wichita Falls",
    "sg:classifiers":[
        {
            "category":"Health Services",
            "subcategory":"Doctor",
            "type":"Services"
        }
    ],
    "sg:phone":"+1 940 723 2499",
    "sg:postcode":"76301",
    "sg:province":"TX",
    "sg:tags":[
        "physician",
        "surgeon"
    ],
    "wof:name":"Texoma Outpatient Surgery Ctr",
    "wof:placetype":"venue"
},
  "geometry": {"coordinates":[-98.505726,33.901404],"type":"Point"}
}