{
  "type": "Feature",
  "properties": {
    "iso:country":"US",
    "sg:address":"13924 Watson Rd",
    "sg:city":"Von Ormy",
    "sg:classifiers":[
        {
            "category":"Freight",
            "type":"Transportation"
        }
    ],
    "sg:phone":"+1 210 623 7389",
    "sg:postcode":"78073",
    "sg:province":"TX",
    "sg:tags":[
        "operator",
        "local",
        "trucking"
    ],
    "wof:name":"R Ramirez Trucking Inc",
    "wof:placetype":"venue"
},
  "geometry": {"coordinates":[-98.596017,29.285695],"type":"Point"}
}