{
  "type": "Feature",
  "properties": {
    "iso:country":"US",
    "sg:address":"5813 Preston Rd",
    "sg:city":"Plano",
    "sg:classifiers":[
        {
            "category":"Personal",
            "subcategory":"Beauty Salon",
            "type":"Services"
        }
    ],
    "sg:phone":"+1 469 467 9978",
    "sg:postcode":"75093",
    "sg:province":"TX",
    "sg:tags":[
        "manicuring"
    ],
    "wof:name":"Maile Nails",
    "wof:placetype":"venue"
},
  "geometry": {"coordinates":[-96.795035,33.055195],"type":"Point"}
}