{
  "type": "Feature",
  "properties": {
    "iso:country":"US",
    "sg:address":"5794 Bingle Rd",
    "sg:city":"Houston",
    "sg:classifiers":[
        {
            "category":"Shopping",
            "subcategory":"Mobile Phones",
            "type":"Retail Goods"
        }
    ],
    "sg:phone":"+1 713 957 3866",
    "sg:postcode":"77092",
    "sg:province":"TX",
    "wof:name":"Cricket",
    "wof:placetype":"venue"
},
  "geometry": {"coordinates":[-95.488659,29.850434],"type":"Point"}
}