{
  "type": "Feature",
  "properties": {
    "iso:country":"US",
    "sg:address":"1902 Common St",
    "sg:city":"New Braunfels",
    "sg:classifiers":[
        {
            "category":"Real Estate",
            "subcategory":"Real Estate Agent",
            "type":"Services"
        }
    ],
    "sg:phone":"+1 830 632 8300",
    "sg:postcode":"78130",
    "sg:province":"TX",
    "sg:tags":[
        "management"
    ],
    "wof:name":"Procomm",
    "wof:placetype":"venue"
},
  "geometry": {"coordinates":[-98.097486,29.732052],"type":"Point"}
}