{
  "type": "Feature",
  "properties": {
    "iso:country":"US",
    "sg:address":"2413 Sheilah Dr",
    "sg:city":"Mesquite",
    "sg:classifiers":[
        {
            "category":"Professional",
            "subcategory":"Detective & Security Services",
            "type":"Services"
        }
    ],
    "sg:phone":"+1 972 437 3745",
    "sg:postcode":"75180",
    "sg:province":"TX",
    "sg:tags":[
        "system"
    ],
    "wof:name":"Parker Alarm Systems Inc",
    "wof:placetype":"venue"
},
  "geometry": {"coordinates":[-96.626482,32.734333],"type":"Point"}
}