{
  "type": "Feature",
  "properties": {
    "iso:country":"US",
    "sg:address":"2631 W Mulberry Ave",
    "sg:city":"San Antonio",
    "sg:classifiers":[
        {
            "category":"Building & Trades",
            "subcategory":"Construction",
            "type":"Services"
        }
    ],
    "sg:phone":"+1 210 734 7607",
    "sg:postcode":"78228",
    "sg:province":"TX",
    "sg:tags":[
        "concrete",
        "work"
    ],
    "wof:name":"Lopez Construction Company",
    "wof:placetype":"venue"
},
  "geometry": {"coordinates":[-98.548778,29.458329],"type":"Point"}
}