{
  "type": "Feature",
  "properties": {
    "iso:country":"US",
    "sg:address":"2609 Rockview Dr",
    "sg:city":"Waco",
    "sg:classifiers":[
        {
            "category":"Professional",
            "subcategory":"Management & Consulting",
            "type":"Services"
        }
    ],
    "sg:phone":"+1 254 776 6559",
    "sg:postcode":"76710",
    "sg:province":"TX",
    "sg:tags":[
        "retail",
        "direct",
        "sales"
    ],
    "wof:name":"Linda B Easter",
    "wof:placetype":"venue"
},
  "geometry": {"coordinates":[-97.212247,31.542542],"type":"Point"}
}