{
  "type": "Feature",
  "properties": {
    "iso:country":"US",
    "sg:address":"8001 N Mesa St Ste G",
    "sg:city":"El Paso",
    "sg:classifiers":[
        {
            "category":"Restaurant",
            "type":"Food & Drink"
        }
    ],
    "sg:phone":"+1 915 581 5565",
    "sg:postcode":"79932",
    "sg:province":"TX",
    "sg:tags":[
        "mexican"
    ],
    "wof:name":"Ay Caramba",
    "wof:placetype":"venue"
},
  "geometry": {"coordinates":[-106.576296,31.840334],"type":"Point"}
}