{
  "type": "Feature",
  "properties": {
    "iso:country":"US",
    "sg:address":"7522 Green Lawn Dr",
    "sg:city":"Houston",
    "sg:classifiers":[
        {
            "category":"Professional",
            "subcategory":"Management & Consulting",
            "type":"Services"
        }
    ],
    "sg:phone":"+1 281 847 3653",
    "sg:postcode":"77088",
    "sg:province":"TX",
    "sg:tags":[
        "retail",
        "direct",
        "sales"
    ],
    "wof:name":"CJS Creative Distinction",
    "wof:placetype":"venue"
},
  "geometry": {"coordinates":[-95.47971699999999,29.875983],"type":"Point"}
}