{
  "type": "Feature",
  "properties": {
    "iso:country":"US",
    "sg:address":"5834 Mapleshade Ln",
    "sg:city":"Dallas",
    "sg:classifiers":[
        {
            "category":"Shopping",
            "subcategory":"Discount & Variety Stores",
            "type":"Retail Goods"
        }
    ],
    "sg:phone":"+1 972 931 1154",
    "sg:postcode":"75252",
    "sg:province":"TX",
    "sg:tags":[
        "merchandise",
        "general"
    ],
    "wof:name":"Music Stands & Benches",
    "wof:placetype":"venue"
},
  "geometry": {"coordinates":[-96.806459,33.00599],"type":"Point"}
}