{
  "type": "Feature",
  "properties": {
    "iso:country":"US",
    "sg:address":"1319 S Houston Rd",
    "sg:city":"Pasadena",
    "sg:classifiers":[
        {
            "category":"Home & Garden",
            "subcategory":"Building Materials",
            "type":"Retail Goods"
        }
    ],
    "sg:phone":"+1 713 477 2338",
    "sg:postcode":"77502",
    "sg:province":"TX",
    "sg:tags":[
        "door"
    ],
    "wof:name":"Doors Unlimited",
    "wof:placetype":"venue"
},
  "geometry": {"coordinates":[-95.221535,29.690157],"type":"Point"}
}