{
  "type": "Feature",
  "properties": {
    "iso:country":"US",
    "sg:address":"1217 Main St",
    "sg:city":"Dallas",
    "sg:classifiers":[
        {
            "category":"Recreation",
            "subcategory":"Dance Hall",
            "type":"Entertainment"
        }
    ],
    "sg:postcode":"75202",
    "sg:province":"TX",
    "sg:tags":[
        "club"
    ],
    "sg:website":"www.buddha9dallas.com",
    "wof:name":"Buddha 9",
    "wof:placetype":"venue"
},
  "geometry": {"coordinates":[-96.801215,32.78046],"type":"Point"}
}