{
  "type": "Feature",
  "properties": {
    "iso:country":"US",
    "sg:address":"101 Wimberley Sq",
    "sg:city":"Wimberley",
    "sg:classifiers":[
        {
            "category":"Shopping",
            "subcategory":"Bicycles & Sporting Goods",
            "type":"Retail Goods"
        }
    ],
    "sg:phone":"+1 512 847 0200",
    "sg:postcode":"78676",
    "sg:province":"TX",
    "sg:tags":[
        "equipment",
        "golf",
        "supply"
    ],
    "wof:name":"Golf 4U",
    "wof:placetype":"venue"
},
  "geometry": {"coordinates":[-98.09611099999999,29.996367],"type":"Point"}
}