{
  "type": "Feature",
  "properties": {
    "iso:country":"US",
    "sg:address":"8788 Hammerly Blvd",
    "sg:city":"Houston",
    "sg:classifiers":[
        {
            "category":"Retail",
            "subcategory":"Self-service Laundry",
            "type":"Services"
        }
    ],
    "sg:phone":"+1 713 465 8611",
    "sg:postcode":"77080",
    "sg:province":"TX",
    "sg:tags":[
        "coin"
    ],
    "wof:name":"Washateria Texas Cleaners",
    "wof:placetype":"venue"
},
  "geometry": {"coordinates":[-95.509548,29.811073],"type":"Point"}
}