{
  "type": "Feature",
  "properties": {
    "iso:country":"US",
    "sg:address":"402 E Market St",
    "sg:city":"Sinton",
    "sg:classifiers":[
        {
            "category":"Manufacturing",
            "subcategory":"Metals",
            "type":"Manufacturing & Wholesale Goods"
        }
    ],
    "sg:phone":"+1 361 287 3623",
    "sg:postcode":"78387",
    "sg:province":"TX",
    "sg:tags":[
        "gates"
    ],
    "wof:name":"Brown Enterprises",
    "wof:placetype":"venue"
},
  "geometry": {"coordinates":[-97.50680199999999,28.037693],"type":"Point"}
}