{
  "type": "Feature",
  "properties": {
    "iso:country":"US",
    "sg:address":"7320 Ashcroft Dr",
    "sg:city":"Houston",
    "sg:classifiers":[
        {
            "category":"Building & Trades",
            "subcategory":"Construction",
            "type":"Services"
        }
    ],
    "sg:phone":"+1 713 771 7320",
    "sg:postcode":"77081",
    "sg:province":"TX",
    "sg:tags":[
        "contractor"
    ],
    "wof:name":"J R De Lay Builder Inc",
    "wof:placetype":"venue"
},
  "geometry": {"coordinates":[-95.490883,29.699644],"type":"Point"}
}