{
  "type": "Feature",
  "properties": {
    "iso:country":"US",
    "sg:address":"424 Peterson Dr",
    "sg:city":"Kerrville",
    "sg:classifiers":[
        {
            "category":"Building & Trades",
            "subcategory":"Construction",
            "type":"Services"
        }
    ],
    "sg:phone":"+1 830 377 9017",
    "sg:postcode":"78028",
    "sg:province":"TX",
    "sg:tags":[
        "painting",
        "contractor"
    ],
    "wof:name":"AJ's Painting",
    "wof:placetype":"venue"
},
  "geometry": {"coordinates":[-99.128383,30.064882],"type":"Point"}
}