{
  "type": "Feature",
  "properties": {
    "iso:country":"US",
    "sg:address":"5053 Fieldwood Dr",
    "sg:city":"Houston",
    "sg:classifiers":[
        {
            "category":"Professional",
            "subcategory":"Lawyer & Legal Services",
            "type":"Services"
        }
    ],
    "sg:phone":"+1 713 224 3981",
    "sg:postcode":"77056",
    "sg:province":"TX",
    "wof:name":"Vecchio John F Atty",
    "wof:placetype":"venue"
},
  "geometry": {"coordinates":[-95.463898,29.752701],"type":"Point"}
}