{
  "type": "Feature",
  "properties": {
    "iso:country":"US",
    "sg:address":"142 Howell St",
    "sg:city":"Dallas",
    "sg:classifiers":[
        {
            "category":"Home & Garden",
            "subcategory":"Home Furnishings",
            "type":"Retail Goods"
        }
    ],
    "sg:phone":"+1 214 237 0299",
    "sg:postcode":"75207",
    "sg:province":"TX",
    "sg:tags":[
        "lighting",
        "iron",
        "fixture",
        "wrought",
        "bronze"
    ],
    "wof:name":"Solara Lighting LLC",
    "wof:placetype":"venue"
},
  "geometry": {"coordinates":[-96.819838,32.787304],"type":"Point"}
}