{
  "type": "Feature",
  "properties": {
    "iso:country":"US",
    "sg:address":"1392 Gifford Rd",
    "sg:city":"Angleton",
    "sg:classifiers":[
        {
            "category":"Real Estate",
            "subcategory":"Real Estate Operator",
            "type":"Services"
        }
    ],
    "sg:phone":"+1 979 849 0726",
    "sg:postcode":"77515",
    "sg:province":"TX",
    "sg:tags":[
        "mobile",
        "home",
        "site"
    ],
    "wof:name":"Possims Corn Hollow",
    "wof:placetype":"venue"
},
  "geometry": {"coordinates":[-95.418302,29.140201],"type":"Point"}
}