{
  "type": "Feature",
  "properties": {
    "iso:country":"US",
    "sg:address":"12130 Harry Hines Blvd",
    "sg:city":"Dallas",
    "sg:classifiers":[
        {
            "category":"Autos & Motor Vehicles",
            "subcategory":"Auto Supplies",
            "type":"Retail Goods"
        },
        {
            "category":"Retail",
            "subcategory":"Auto Repair",
            "type":"Services"
        }
    ],
    "sg:phone":"+1 972 484 3595",
    "sg:postcode":"75234",
    "sg:province":"TX",
    "sg:tags":[
        "body",
        "automobile",
        "truck",
        "painting",
        "repairing"
    ],
    "wof:name":"L & R Auto",
    "wof:placetype":"venue"
},
  "geometry": {"coordinates":[-96.8965,32.914181],"type":"Point"}
}