{
  "type": "Feature",
  "properties": {
    "iso:country":"US",
    "sg:address":"3001 W Spring Creek Pkwy",
    "sg:city":"Plano",
    "sg:classifiers":[
        {
            "category":"Food & Beverages",
            "subcategory":"Groceries & Convenience Stores",
            "type":"Retail Goods"
        }
    ],
    "sg:phone":"+1 972 618 7001",
    "sg:postcode":"75023",
    "sg:province":"TX",
    "wof:name":"Stop N Go",
    "wof:placetype":"venue"
},
  "geometry": {"coordinates":[-96.75306999999999,33.057452],"type":"Point"}
}