{
  "type": "Feature",
  "properties": {
    "iso:country":"US",
    "sg:address":"7115 Cottonwood Cir",
    "sg:city":"Garland",
    "sg:classifiers":[
        {
            "category":"Communications",
            "type":"Services"
        }
    ],
    "sg:phone":"+1 972 495 8346",
    "sg:postcode":"75048",
    "sg:province":"TX",
    "sg:tags":[
        "communication"
    ],
    "wof:name":"Xpress Communications",
    "wof:placetype":"venue"
},
  "geometry": {"coordinates":[-96.603291,32.984012],"type":"Point"}
}