{
  "type": "Feature",
  "properties": {
    "iso:country":"US",
    "sg:address":"20 E Greenway Plz",
    "sg:city":"Houston",
    "sg:classifiers":[
        {
            "category":"Health Services",
            "subcategory":"Clinic",
            "type":"Services"
        }
    ],
    "sg:phone":"+1 713 592 8140",
    "sg:postcode":"77046",
    "sg:province":"TX",
    "wof:name":"Center For Innovation In Hlth",
    "wof:placetype":"venue"
},
  "geometry": {"coordinates":[-95.43170000000001,29.733237],"type":"Point"}
}