{
  "type": "Feature",
  "properties": {
    "iso:country":"US",
    "sg:address":"407 N Clear Creek Dr",
    "sg:city":"Friendswood",
    "sg:classifiers":[
        {
            "category":"Real Estate",
            "subcategory":"Developer",
            "type":"Services"
        }
    ],
    "sg:phone":"+1 281 482 7868",
    "sg:postcode":"77546",
    "sg:province":"TX",
    "wof:name":"Forest Friendswood Subdivision",
    "wof:placetype":"venue"
},
  "geometry": {"coordinates":[-95.182688,29.510915],"type":"Point"}
}