{
  "type": "Feature",
  "properties": {
    "iso:country":"US",
    "sg:address":"183 N Cedar Park",
    "sg:city":"Austin",
    "sg:classifiers":[
        {
            "category":"Shopping",
            "subcategory":"Pets & Pet Supplies",
            "type":"Retail Goods"
        }
    ],
    "sg:phone":"+1 512 331 6742",
    "sg:postcode":"78729",
    "sg:province":"TX",
    "sg:tags":[
        "store"
    ],
    "wof:name":"Pet Connection Superstore",
    "wof:placetype":"venue"
},
  "geometry": {"coordinates":[-97.762604,30.4506],"type":"Point"}
}