{
  "type": "Feature",
  "properties": {
    "iso:country":"US",
    "sg:address":"401 N 37th St",
    "sg:city":"Orange",
    "sg:classifiers":[
        {
            "category":"Organizations",
            "subcategory":"Religious Organization",
            "type":"Services"
        }
    ],
    "sg:phone":"+1 409 886 7276",
    "sg:postcode":"77630",
    "sg:province":"TX",
    "sg:tags":[
        "place",
        "worship",
        "church"
    ],
    "sg:website":"http://www.orangewesley.org",
    "wof:name":"Wesley United Methodist Church",
    "wof:placetype":"venue"
},
  "geometry": {"coordinates":[-93.77723899999999,30.093607],"type":"Point"}
}