{
  "type": "Feature",
  "properties": {
    "iso:country":"US",
    "sg:address":"1120 N 3rd St",
    "sg:city":"Longview",
    "sg:classifiers":[
        {
            "category":"Wholesale",
            "subcategory":"Office Equipment",
            "type":"Manufacturing & Wholesale Goods"
        },
        {
            "category":"Professional",
            "subcategory":"Printing & Photocopies",
            "type":"Services"
        },
        {
            "category":"Shopping",
            "subcategory":"Computers & Home Electronics",
            "type":"Retail Goods"
        }
    ],
    "sg:phone":"+1 903 758 2081",
    "sg:postcode":"75601",
    "sg:province":"TX",
    "sg:tags":[
        "lithographer",
        "scanning",
        "printer",
        "plotting",
        "supply"
    ],
    "wof:name":"Longview Print Shop",
    "wof:placetype":"venue"
},
  "geometry": {"coordinates":[-94.732218,32.507747],"type":"Point"}
}