{
  "type": "Feature",
  "properties": {
    "iso:country":"US",
    "sg:address":"107 State Hwy 110",
    "sg:city":"Whitehouse",
    "sg:classifiers":[
        {
            "category":"Banks & Credit Unions",
            "subcategory":"Bank",
            "type":"Services"
        }
    ],
    "sg:phone":"+1 903 839 7283",
    "sg:postcode":"75791",
    "sg:province":"TX",
    "sg:tags":[
        "savings",
        "loan",
        "association"
    ],
    "wof:name":"First Federal Bank Of Texas",
    "wof:placetype":"venue"
},
  "geometry": {"coordinates":[-95.226057,32.226248],"type":"Point"}
}