{
  "type": "Feature",
  "properties": {
    "iso:country":"US",
    "sg:address":"3120 Santa Maria Ave",
    "sg:city":"Laredo",
    "sg:classifiers":[
        {
            "category":"Restaurant",
            "type":"Food & Drink"
        }
    ],
    "sg:phone":"+1 956 791 9699",
    "sg:postcode":"78040",
    "sg:province":"TX",
    "wof:name":"Las Coquetas Drive Thru",
    "wof:placetype":"venue"
},
  "geometry": {"coordinates":[-99.510142,27.528021],"type":"Point"}
}