{
  "type": "Feature",
  "properties": {
    "iso:country":"US",
    "sg:address":"11308 S Pipeline Rd",
    "sg:city":"Euless",
    "sg:classifiers":[
        {
            "category":"Wholesale",
            "subcategory":"Machinery & Supplies",
            "type":"Manufacturing & Wholesale Goods"
        }
    ],
    "sg:phone":"+1 817 267 3988",
    "sg:postcode":"76040",
    "sg:province":"TX",
    "sg:tags":[
        "equipment",
        "construction",
        "rent"
    ],
    "wof:name":"Builders Equipment & Tool Co",
    "wof:placetype":"venue"
},
  "geometry": {"coordinates":[-97.12507100000001,32.814592],"type":"Point"}
}