{
  "type": "Feature",
  "properties": {
    "iso:country":"US",
    "sg:address":"428 Kirkwood Dr",
    "sg:city":"Dallas",
    "sg:classifiers":[
        {
            "category":"Professional",
            "type":"Services"
        }
    ],
    "sg:phone":"+1 214 328 2078",
    "sg:postcode":"75218",
    "sg:province":"TX",
    "wof:name":"Rose A Melgoza",
    "wof:placetype":"venue"
},
  "geometry": {"coordinates":[-96.71006800000001,32.853956],"type":"Point"}
}