{
  "type": "Feature",
  "properties": {
    "iso:country":"US",
    "sg:address":"7443 Airport Fwy",
    "sg:city":"Fort Worth",
    "sg:classifiers":[
        {
            "category":"Wholesale",
            "subcategory":"Stationery",
            "type":"Manufacturing & Wholesale Goods"
        }
    ],
    "sg:phone":"+1 817 595 2121",
    "sg:postcode":"76118",
    "sg:province":"TX",
    "sg:tags":[
        "product",
        "graphic",
        "paper",
        "design",
        "offset",
        "printer"
    ],
    "wof:name":"Fasclampitt Paper Company",
    "wof:placetype":"venue"
},
  "geometry": {"coordinates":[-97.21678799999999,32.803584],"type":"Point"}
}