{
  "type": "Feature",
  "properties": {
    "iso:country":"US",
    "sg:address":"8749 Garden Ridge Dr",
    "sg:city":"San Antonio",
    "sg:classifiers":[
        {
            "category":"Manufacturing",
            "subcategory":"Motor Vehicles & Parts",
            "type":"Manufacturing & Wholesale Goods"
        }
    ],
    "sg:phone":"+1 210 651 9797",
    "sg:postcode":"78266",
    "sg:province":"TX",
    "sg:tags":[
        "automobile",
        "supply"
    ],
    "sg:website":"www.fuelinjection.com",
    "wof:name":"Daco Parts Corp",
    "wof:placetype":"venue"
},
  "geometry": {"coordinates":[-98.312507,29.624351],"type":"Point"}
}