{
  "type": "Feature",
  "properties": {
    "iso:country":"US",
    "sg:address":"117 W Ennis Ave",
    "sg:city":"Ennis",
    "sg:classifiers":[
        {
            "category":"Donuts",
            "subcategory":"None",
            "type":"Food & Drink"
        }
    ],
    "sg:phone":"+1 972 875 6137",
    "sg:postcode":"75119",
    "sg:province":"TX",
    "sg:tags":[
        "shop"
    ],
    "wof:name":"Heavenly Donuts",
    "wof:placetype":"venue"
},
  "geometry": {"coordinates":[-96.627315,32.327706],"type":"Point"}
}