{
  "type": "Feature",
  "properties": {
    "iso:country":"US",
    "sg:address":"1250 Butternut St",
    "sg:city":"Abilene",
    "sg:classifiers":[
        {
            "category":"Building & Trades",
            "subcategory":"Cleaning & Sanitation",
            "type":"Services"
        }
    ],
    "sg:phone":"+1 325 692 0017",
    "sg:postcode":"79602",
    "sg:province":"TX",
    "sg:tags":[
        "janitor"
    ],
    "wof:name":"Briercroft Inc Air Duct Clnng",
    "wof:placetype":"venue"
},
  "geometry": {"coordinates":[-99.738649,32.434702],"type":"Point"}
}