{
  "type": "Feature",
  "properties": {
    "iso:country":"US",
    "sg:address":"3114 Terrell Rd",
    "sg:city":"Greenville",
    "sg:classifiers":[
        {
            "category":"Organizations",
            "subcategory":"Religious Organization",
            "type":"Services"
        }
    ],
    "sg:phone":"+1 903 455 9741",
    "sg:postcode":"75402",
    "sg:province":"TX",
    "sg:tags":[
        "church"
    ],
    "wof:name":"Kingdom Hall Jehovahs Witness",
    "wof:placetype":"venue"
},
  "geometry": {"coordinates":[-96.11318300000001,33.106385],"type":"Point"}
}