{
  "type": "Feature",
  "properties": {
    "iso:country":"US",
    "sg:address":"2620 State St",
    "sg:city":"Dallas",
    "sg:classifiers":[
        {
            "category":"Professional",
            "subcategory":"Lawyer & Legal Services",
            "type":"Services"
        }
    ],
    "sg:phone":"+1 214 871 9590",
    "sg:postcode":"75204",
    "sg:province":"TX",
    "sg:tags":[
        "divorce",
        "law",
        "family"
    ],
    "wof:name":"McKnight Mary D Atty",
    "wof:placetype":"venue"
},
  "geometry": {"coordinates":[-96.799797,32.7957],"type":"Point"}
}