{
  "type": "Feature",
  "properties": {
    "iso:country":"US",
    "sg:address":"500 Baybrook Mall",
    "sg:city":"Friendswood",
    "sg:classifiers":[
        {
            "category":"Restaurant",
            "type":"Food & Drink"
        }
    ],
    "sg:phone":"+1 281 488 8803",
    "sg:postcode":"77546",
    "sg:province":"TX",
    "sg:tags":[
        "steak"
    ],
    "wof:name":"Great Steak & Potato Co",
    "wof:placetype":"venue"
},
  "geometry": {"coordinates":[-95.151539,29.543784],"type":"Point"}
}