{
  "type": "Feature",
  "properties": {
    "iso:country":"US",
    "sg:address":"3008 Kemp Blvd",
    "sg:city":"Wichita Falls",
    "sg:classifiers":[
        {
            "category":"Home & Garden",
            "subcategory":"Household Appliances",
            "type":"Retail Goods"
        }
    ],
    "sg:phone":"+1 940 691 1112",
    "sg:postcode":"76308",
    "sg:province":"TX",
    "sg:tags":[
        "stereo",
        "furniture"
    ],
    "wof:name":"Hamilton-Bryan",
    "wof:placetype":"venue"
},
  "geometry": {"coordinates":[-98.528791,33.882233],"type":"Point"}
}