{
  "type": "Feature",
  "properties": {
    "iso:country":"US",
    "sg:address":"17440 Dallas Pkwy",
    "sg:city":"Dallas",
    "sg:classifiers":[
        {
            "category":"Professional",
            "subcategory":"Computer Services",
            "type":"Services"
        }
    ],
    "sg:phone":"+1 972 931 2383",
    "sg:postcode":"75287",
    "sg:province":"TX",
    "sg:tags":[
        "programing",
        "custom"
    ],
    "wof:name":"CRS Inc",
    "wof:placetype":"venue"
},
  "geometry": {"coordinates":[-96.828064,32.988264],"type":"Point"}
}