{
  "type": "Feature",
  "properties": {
    "iso:country":"US",
    "sg:address":"1827 Strand St",
    "sg:city":"Galveston",
    "sg:classifiers":[
        {
            "category":"Organizations",
            "subcategory":"Labor Organization",
            "type":"Services"
        }
    ],
    "sg:phone":"+1 409 762 2341",
    "sg:postcode":"77550",
    "sg:province":"TX",
    "wof:name":"ILA South Atlantic & Gulf",
    "wof:placetype":"venue"
},
  "geometry": {"coordinates":[-94.78952099999999,29.308367],"type":"Point"}
}