{
  "type": "Feature",
  "properties": {
    "iso:country":"US",
    "sg:address":"181 US Hwy 96",
    "sg:city":"Center",
    "sg:classifiers":[
        {
            "category":"Restaurant",
            "type":"Food & Drink"
        }
    ],
    "sg:phone":"+1 936 598 2082",
    "sg:postcode":"75935",
    "sg:province":"TX",
    "wof:name":"Raceway Food Mart",
    "wof:placetype":"venue"
},
  "geometry": {"coordinates":[-94.186553,31.791298],"type":"Point"}
}