{
  "type": "Feature",
  "properties": {
    "iso:country":"US",
    "sg:address":"301 N Muskingum Ave",
    "sg:city":"Odessa",
    "sg:classifiers":[
        {
            "category":"Health Services",
            "subcategory":"Doctor",
            "type":"Services"
        }
    ],
    "sg:phone":"+1 432 580 9292",
    "sg:postcode":"79761",
    "sg:province":"TX",
    "sg:tags":[
        "physician",
        "surgeon"
    ],
    "wof:name":"Healthy Heart Ctr",
    "wof:placetype":"venue"
},
  "geometry": {"coordinates":[-102.363615,31.850216],"type":"Point"}
}