{
  "type": "Feature",
  "properties": {
    "iso:country":"US",
    "sg:address":"13109 Fall Manor Dr",
    "sg:city":"Dallas",
    "sg:classifiers":[
        {
            "category":"Professional",
            "subcategory":"Employment Agencies",
            "type":"Services"
        }
    ],
    "sg:phone":"+1 972 690 1110",
    "sg:postcode":"75243",
    "sg:province":"TX",
    "sg:tags":[
        "teachers'"
    ],
    "wof:name":"Four You Harmony",
    "wof:placetype":"venue"
},
  "geometry": {"coordinates":[-96.713154,32.926608],"type":"Point"}
}