{
  "type": "Feature",
  "properties": {
    "iso:country":"US",
    "sg:address":"240 Circleview Dr S",
    "sg:city":"Hurst",
    "sg:classifiers":[
        {
            "category":"Building & Trades",
            "subcategory":"Electrical",
            "type":"Services"
        }
    ],
    "sg:phone":"+1 817 268 0096",
    "sg:postcode":"76054",
    "sg:province":"TX",
    "sg:tags":[
        "electrical",
        "contractor"
    ],
    "wof:name":"Billy F Holcombe Jr",
    "wof:placetype":"venue"
},
  "geometry": {"coordinates":[-97.169603,32.842866],"type":"Point"}
}