{
  "type": "Feature",
  "properties": {
    "iso:country":"US",
    "sg:address":"15722 Whitewater Ln",
    "sg:city":"Houston",
    "sg:classifiers":[
        {
            "category":"Banks & Credit Unions",
            "subcategory":"Financial Services",
            "type":"Services"
        }
    ],
    "sg:phone":"+1 281 493 3929",
    "sg:postcode":"77079",
    "sg:province":"TX",
    "sg:tags":[
        "investment",
        "closed"
    ],
    "wof:name":"Robert R Heath",
    "wof:placetype":"venue"
},
  "geometry": {"coordinates":[-95.63316399999999,29.781945],"type":"Point"}
}