{
  "type": "Feature",
  "properties": {
    "iso:country":"US",
    "sg:address":"6015 N Shepherd Dr",
    "sg:city":"Houston",
    "sg:classifiers":[
        {
            "category":"Wholesale",
            "subcategory":"Auto Parts",
            "type":"Manufacturing & Wholesale Goods"
        }
    ],
    "sg:phone":"+1 713 695 6336",
    "sg:postcode":"77091",
    "sg:province":"TX",
    "sg:tags":[
        "engine"
    ],
    "wof:name":"Japanese Motors",
    "wof:placetype":"venue"
},
  "geometry": {"coordinates":[-95.412565,29.85465],"type":"Point"}
}