{
  "type": "Feature",
  "properties": {
    "iso:country":"US",
    "sg:address":"911 Allendale Dr",
    "sg:city":"Lufkin",
    "sg:classifiers":[
        {
            "category":"Health Services",
            "subcategory":"Hospital",
            "type":"Services"
        }
    ],
    "sg:phone":"+1 936 634 1315",
    "sg:postcode":"75904",
    "sg:province":"TX",
    "sg:tags":[
        "mental"
    ],
    "wof:name":"NAMI Lufkin",
    "wof:placetype":"venue"
},
  "geometry": {"coordinates":[-94.74689100000001,31.325473],"type":"Point"}
}