{
  "type": "Feature",
  "properties": {
    "iso:country":"US",
    "sg:address":"4508 Trowbridge Dr",
    "sg:city":"Arlington",
    "sg:classifiers":[
        {
            "category":"Building & Trades",
            "subcategory":"Construction",
            "type":"Services"
        }
    ],
    "sg:phone":"+1 817 654 9539",
    "sg:postcode":"76013",
    "sg:province":"TX",
    "sg:tags":[
        "residential"
    ],
    "wof:name":"Pearce Construction",
    "wof:placetype":"venue"
},
  "geometry": {"coordinates":[-97.180482,32.70736],"type":"Point"}
}