{
  "type": "Feature",
  "properties": {
    "iso:country":"US",
    "sg:address":"1709 S Montgomery St",
    "sg:city":"Sherman",
    "sg:classifiers":[
        {
            "category":"Food & Beverages",
            "subcategory":"Groceries & Convenience Stores",
            "type":"Retail Goods"
        }
    ],
    "sg:phone":"+1 903 892 3672",
    "sg:postcode":"75090",
    "sg:province":"TX",
    "sg:tags":[
        "business"
    ],
    "wof:name":"Texoma Indoor Flea Market",
    "wof:placetype":"venue"
},
  "geometry": {"coordinates":[-96.60118799999999,33.618464],"type":"Point"}
}