{
  "type": "Feature",
  "properties": {
    "iso:country":"US",
    "sg:address":"5188 State Hwy 1604",
    "sg:city":"San Antonio",
    "sg:classifiers":[
        {
            "category":"Retail",
            "subcategory":"Auto Rental",
            "type":"Services"
        }
    ],
    "sg:phone":"+1 210 479 6931",
    "sg:postcode":"78249",
    "sg:province":"TX",
    "sg:tags":[
        "renting",
        "leasing",
        "trailer"
    ],
    "wof:name":"U-Haul Co",
    "wof:placetype":"venue"
},
  "geometry": {"coordinates":[-98.587514,29.591934],"type":"Point"}
}