{
  "type": "Feature",
  "properties": {
    "iso:country":"US",
    "sg:address":"622 N Barnett Ave",
    "sg:city":"Dallas",
    "sg:classifiers":[
        {
            "category":"Organizations",
            "subcategory":"Religious Organization",
            "type":"Services"
        }
    ],
    "sg:phone":"+1 214 339 0365",
    "sg:postcode":"75211",
    "sg:province":"TX",
    "wof:name":"Jesus J Pina",
    "wof:placetype":"venue"
},
  "geometry": {"coordinates":[-96.87128800000001,32.751217],"type":"Point"}
}