{
  "type": "Feature",
  "properties": {
    "iso:country":"US",
    "sg:address":"4383 Kenneth Ave",
    "sg:city":"Beaumont",
    "sg:classifiers":[
        {
            "category":"Banks & Credit Unions",
            "subcategory":"Financial Services",
            "type":"Services"
        }
    ],
    "sg:phone":"+1 409 658 3245",
    "sg:postcode":"77705",
    "sg:province":"TX",
    "sg:tags":[
        "investor"
    ],
    "wof:name":"Michaels Home Investments",
    "wof:placetype":"venue"
},
  "geometry": {"coordinates":[-94.089304,30.045187],"type":"Point"}
}