{
  "type": "Feature",
  "properties": {
    "iso:country":"US",
    "sg:address":"1110 S Presa St",
    "sg:city":"San Antonio",
    "sg:classifiers":[
        {
            "category":"Food & Beverages",
            "subcategory":"Groceries & Convenience Stores",
            "type":"Retail Goods"
        }
    ],
    "sg:phone":"+1 210 532 7830",
    "sg:postcode":"78210",
    "sg:province":"TX",
    "wof:name":"Pik Nik Foods",
    "wof:placetype":"venue"
},
  "geometry": {"coordinates":[-98.486221,29.409117],"type":"Point"}
}