{
  "type": "Feature",
  "properties": {
    "iso:country":"US",
    "sg:address":"7250 W Greens Rd",
    "sg:city":"Houston",
    "sg:classifiers":[
        {
            "category":"Organizations",
            "subcategory":"Religious Organization",
            "type":"Services"
        }
    ],
    "sg:phone":"+1 832 237 6575",
    "sg:postcode":"77064",
    "sg:province":"TX",
    "wof:name":"His Witness Ministries",
    "wof:placetype":"venue"
},
  "geometry": {"coordinates":[-95.53523300000001,29.955015],"type":"Point"}
}