{
  "type": "Feature",
  "properties": {
    "iso:country":"US",
    "sg:address":"250 S Stemmons Fwy",
    "sg:city":"Lewisville",
    "sg:classifiers":[
        {
            "category":"Banks & Credit Unions",
            "subcategory":"Bank",
            "type":"Services"
        }
    ],
    "sg:phone":"+1 972 219 2620",
    "sg:postcode":"75067",
    "sg:province":"TX",
    "sg:tags":[
        "loan"
    ],
    "wof:name":"American Home Mortgage",
    "wof:placetype":"venue"
},
  "geometry": {"coordinates":[-97.007413,33.044817],"type":"Point"}
}