{
  "type": "Feature",
  "properties": {
    "iso:country":"US",
    "sg:address":"3201 W Pioneer Pkwy",
    "sg:city":"Pantego",
    "sg:classifiers":[
        {
            "category":"Restaurant",
            "type":"Food & Drink"
        }
    ],
    "sg:phone":"+1 817 633 2560",
    "sg:postcode":"76013",
    "sg:province":"TX",
    "sg:tags":[
        "sandwich"
    ],
    "wof:name":"Texas B",
    "wof:placetype":"venue"
},
  "geometry": {"coordinates":[-97.158098,32.71065],"type":"Point"}
}