{
  "type": "Feature",
  "properties": {
    "iso:country":"US",
    "sg:address":"4248 Cactus Dr",
    "sg:city":"Argyle",
    "sg:classifiers":[
        {
            "category":"Transit Center",
            "subcategory":"Freight",
            "type":"Transportation"
        }
    ],
    "sg:phone":"+1 940 594 4042",
    "sg:postcode":"76226",
    "sg:province":"TX",
    "sg:tags":[
        "trucking-light",
        "hauling"
    ],
    "wof:name":"Kw's Hauling",
    "wof:placetype":"venue"
},
  "geometry": {"coordinates":[-97.197756,33.082247],"type":"Point"}
}