{
  "type": "Feature",
  "properties": {
    "iso:country":"US",
    "sg:address":"5505 Cavalry Post Dr",
    "sg:city":"Arlington",
    "sg:classifiers":[
        {
            "category":"Shopping",
            "subcategory":"Bicycles & Sporting Goods",
            "type":"Retail Goods"
        }
    ],
    "sg:phone":"+1 817 557 5551",
    "sg:postcode":"76017",
    "sg:province":"TX",
    "sg:tags":[
        "bicycles-repair"
    ],
    "wof:name":"R & R Bicycle Repair",
    "wof:placetype":"venue"
},
  "geometry": {"coordinates":[-97.13961,32.657078],"type":"Point"}
}