{
  "type": "Feature",
  "properties": {
    "iso:country":"US",
    "sg:address":"808 N 5th St",
    "sg:city":"Alpine",
    "sg:classifiers":[
        {
            "category":"Government",
            "subcategory":"Police Station",
            "type":"Public Place"
        }
    ],
    "sg:phone":"+1 432 837 3494",
    "sg:postcode":"79830",
    "sg:province":"TX",
    "sg:tags":[
        "state"
    ],
    "wof:name":"Public Safety Narcotic Dept",
    "wof:placetype":"venue"
},
  "geometry": {"coordinates":[-103.664136,30.364505],"type":"Point"}
}