{
  "type": "Feature",
  "properties": {
    "iso:country":"US",
    "sg:address":"407 International Pkwy",
    "sg:city":"Arlington",
    "sg:classifiers":[
        {
            "category":"Home & Garden",
            "subcategory":"Furniture",
            "type":"Retail Goods"
        }
    ],
    "sg:phone":"+1 817 276 2532",
    "sg:postcode":"76011",
    "sg:province":"TX",
    "sg:tags":[
        "store"
    ],
    "wof:name":"Canales Furniture",
    "wof:placetype":"venue"
},
  "geometry": {"coordinates":[-97.07353999999999,32.744597],"type":"Point"}
}