{
  "type": "Feature",
  "properties": {
    "iso:country":"US",
    "sg:address":"12914 Meehan Dr",
    "sg:city":"Austin",
    "sg:classifiers":[
        {
            "category":"Restaurant",
            "type":"Food & Drink"
        }
    ],
    "sg:phone":"+1 512 302 5433",
    "sg:postcode":"78727",
    "sg:province":"TX",
    "wof:name":"888 Vietnamese Restaurant",
    "wof:placetype":"venue"
},
  "geometry": {"coordinates":[-97.686341,30.419326],"type":"Point"}
}