{
  "type": "Feature",
  "properties": {
    "iso:country":"US",
    "sg:address":"1919 State Hwy 6",
    "sg:city":"Houston",
    "sg:classifiers":[
        {
            "category":"Autos & Motor Vehicles",
            "subcategory":"Automobile Sales",
            "type":"Retail Goods"
        }
    ],
    "sg:phone":"+1 281 597 9600",
    "sg:postcode":"77077",
    "sg:province":"TX",
    "sg:tags":[
        "car",
        "dealer"
    ],
    "wof:name":"Allstar Motors",
    "wof:placetype":"venue"
},
  "geometry": {"coordinates":[-95.644509,29.750408],"type":"Point"}
}