{
  "type": "Feature",
  "properties": {
    "iso:country":"US",
    "sg:address":"1121 State Hwy 87",
    "sg:city":"Crystal Beach",
    "sg:classifiers":[
        {
            "category":"Food & Beverages",
            "subcategory":"Groceries & Convenience Stores",
            "type":"Retail Goods"
        }
    ],
    "sg:phone":"+1 409 684 6816",
    "sg:postcode":"77650",
    "sg:province":"TX",
    "sg:tags":[
        "grocer"
    ],
    "wof:name":"South Shore Grocery",
    "wof:placetype":"venue"
},
  "geometry": {"coordinates":[-94.667841,29.441191],"type":"Point"}
}