{
  "type": "Feature",
  "properties": {
    "iso:country":"US",
    "sg:address":"1109 Knotty Oaks Dr",
    "sg:city":"Waco",
    "sg:classifiers":[
        {
            "category":"Professional",
            "subcategory":"Business Services",
            "type":"Services"
        }
    ],
    "sg:phone":"+1 254 757 3636",
    "sg:postcode":"76712",
    "sg:province":"TX",
    "wof:name":"A Affordable Bail Bonds",
    "wof:placetype":"venue"
},
  "geometry": {"coordinates":[-97.225694,31.513324],"type":"Point"}
}