{
  "type": "Feature",
  "properties": {
    "iso:country":"US",
    "sg:address":"4503 Magnolia Ln",
    "sg:city":"Sugar Land",
    "sg:classifiers":[
        {
            "category":"Professional",
            "type":"Services"
        }
    ],
    "sg:phone":"+1 281 980 8789",
    "sg:postcode":"77478",
    "sg:province":"TX",
    "wof:name":"Dragon Network Corp",
    "wof:placetype":"venue"
},
  "geometry": {"coordinates":[-95.583123,29.585198],"type":"Point"}
}