{
  "type": "Feature",
  "properties": {
    "iso:country":"US",
    "sg:address":"1605 Ave K",
    "sg:city":"Hondo",
    "sg:classifiers":[
        {
            "category":"Communications",
            "subcategory":"Radio Station",
            "type":"Services"
        }
    ],
    "sg:phone":"+1 830 741 5296",
    "sg:postcode":"78861",
    "sg:province":"TX",
    "sg:tags":[
        "company",
        "broadcasting"
    ],
    "wof:name":"KCWM",
    "wof:placetype":"venue"
},
  "geometry": {"coordinates":[-99.14066699999999,29.350261],"type":"Point"}
}