{
  "type": "Feature",
  "properties": {
    "iso:country":"US",
    "sg:address":"104 SW 6th Ave",
    "sg:city":"Amarillo",
    "sg:classifiers":[
        {
            "category":"Insurance",
            "subcategory":"Health Insurance",
            "type":"Services"
        },
        {
            "category":"Organizations",
            "subcategory":"Non-profit Organization",
            "type":"Services"
        }
    ],
    "sg:phone":"+1 806 374 5783",
    "sg:postcode":"79101",
    "sg:province":"TX",
    "sg:tags":[
        "fund",
        "raising",
        "maintenance"
    ],
    "sg:website":"http://www.marchofdimes.com",
    "wof:name":"March of Dimes Birth Defects Foundation-Golden Spread Chapter",
    "wof:placetype":"venue"
},
  "geometry": {"coordinates":[-101.83704,35.207664],"type":"Point"}
}