{
  "type": "Feature",
  "properties": {
    "iso:country":"US",
    "sg:address":"3045 Lackland Rd",
    "sg:city":"Fort Worth",
    "sg:classifiers":[
        {
            "category":"Professional",
            "subcategory":"Lawyer & Legal Services",
            "type":"Services"
        }
    ],
    "sg:phone":"+1 817 336 7711",
    "sg:postcode":"76116",
    "sg:province":"TX",
    "sg:tags":[
        "attorney"
    ],
    "wof:name":"Murphy Moore & Griffith",
    "wof:placetype":"venue"
},
  "geometry": {"coordinates":[-97.434556,32.730664],"type":"Point"}
}