{
  "type": "Feature",
  "properties": {
    "iso:country":"US",
    "sg:address":"5623 Evers Rd",
    "sg:city":"San Antonio",
    "sg:classifiers":[
        {
            "category":"Personal",
            "subcategory":"Beauty Salon",
            "type":"Services"
        }
    ],
    "sg:phone":"+1 210 521 4850",
    "sg:postcode":"78238",
    "sg:province":"TX",
    "sg:tags":[
        "shop"
    ],
    "wof:name":"D Jorges",
    "wof:placetype":"venue"
},
  "geometry": {"coordinates":[-98.59759099999999,29.488618],"type":"Point"}
}