{
  "type": "Feature",
  "properties": {
    "iso:country":"US",
    "sg:address":"7919 Montglen St",
    "sg:city":"Houston",
    "sg:classifiers":[
        {
            "category":"Professional",
            "type":"Services"
        }
    ],
    "sg:phone":"+1 713 644 0387",
    "sg:postcode":"77061",
    "sg:province":"TX",
    "wof:name":"Crown Warehouse Serv",
    "wof:placetype":"venue"
},
  "geometry": {"coordinates":[-95.274129,29.674207],"type":"Point"}
}