{
  "type": "Feature",
  "properties": {
    "iso:country":"US",
    "sg:address":"6321 Wallingford Dr",
    "sg:city":"Fort Worth",
    "sg:classifiers":[
        {
            "category":"Shopping",
            "subcategory":"Jewelry",
            "type":"Retail Goods"
        }
    ],
    "sg:phone":"+1 817 370 1633",
    "sg:postcode":"76133",
    "sg:province":"TX",
    "sg:tags":[
        "designer"
    ],
    "wof:name":"Maureen Beneze Modern Jewelry",
    "wof:placetype":"venue"
},
  "geometry": {"coordinates":[-97.389019,32.652844],"type":"Point"}
}