{
  "type": "Feature",
  "properties": {
    "iso:country":"US",
    "sg:address":"6607 Parkridge Dr",
    "sg:city":"Garland",
    "sg:classifiers":[
        {
            "category":"Professional",
            "subcategory":"Management & Consulting",
            "type":"Services"
        }
    ],
    "sg:phone":"+1 972 530 8105",
    "sg:postcode":"75048",
    "sg:province":"TX",
    "wof:name":"T Sol Management",
    "wof:placetype":"venue"
},
  "geometry": {"coordinates":[-96.58096,32.981196],"type":"Point"}
}