{
  "type": "Feature",
  "properties": {
    "iso:country":"US",
    "sg:address":"1055 E Tyler St",
    "sg:city":"Brownsville",
    "sg:classifiers":[
        {
            "category":"Professional",
            "subcategory":"Detective & Security Services",
            "type":"Services"
        }
    ],
    "sg:phone":"+1 956 574 9633",
    "sg:postcode":"78520",
    "sg:province":"TX",
    "sg:tags":[
        "car"
    ],
    "wof:name":"Professonal SEC Investigations",
    "wof:placetype":"venue"
},
  "geometry": {"coordinates":[-97.492476,25.907311],"type":"Point"}
}