{
  "type": "Feature",
  "properties": {
    "iso:country":"US",
    "sg:address":"1137 E Elizabeth St",
    "sg:city":"Brownsville",
    "sg:classifiers":[
        {
            "category":"Shopping",
            "subcategory":"Discount & Variety Stores",
            "type":"Retail Goods"
        }
    ],
    "sg:phone":"+1 956 544 7862",
    "sg:postcode":"78520",
    "sg:province":"TX",
    "sg:tags":[
        "merchandise",
        "general"
    ],
    "wof:name":"ABC Cash & Carry Inc",
    "wof:placetype":"venue"
},
  "geometry": {"coordinates":[-97.498357,25.901382],"type":"Point"}
}