{
  "type": "Feature",
  "properties": {
    "iso:country":"US",
    "sg:address":"5411 E Grand Ave",
    "sg:city":"Dallas",
    "sg:classifiers":[
        {
            "category":"Home & Garden",
            "subcategory":"Carpets & Floor Coverings",
            "type":"Retail Goods"
        }
    ],
    "sg:phone":"+1 214 370 5095",
    "sg:postcode":"75223",
    "sg:province":"TX",
    "sg:tags":[
        "mattress"
    ],
    "wof:name":"Matress Warehouse and Furniture Number 2",
    "wof:placetype":"venue"
},
  "geometry": {"coordinates":[-96.748802,32.792599],"type":"Point"}
}