{
  "type": "Feature",
  "properties": {
    "iso:country":"US",
    "sg:address":"2104 Crockett Rd",
    "sg:city":"Palestine",
    "sg:classifiers":[
        {
            "category":"Restaurant",
            "type":"Food & Drink"
        }
    ],
    "sg:menulink":"http://www.allmenus.com/tx/palestine/193546-taco-bell/menu/",
    "sg:postcode":"75801",
    "sg:province":"TX",
    "sg:tags":[
        "mexican"
    ],
    "wof:name":"Taco Bell",
    "wof:placetype":"venue"
},
  "geometry": {"coordinates":[-95.606883,31.735591],"type":"Point"}
}