{
  "type": "Feature",
  "properties": {
    "iso:country":"US",
    "sg:address":"201 Cloud Peak Cove",
    "sg:city":"Round Rock",
    "sg:classifiers":[
        {
            "category":"Professional",
            "type":"Services"
        }
    ],
    "sg:phone":"+1 512 246 2595",
    "sg:postcode":"78681",
    "sg:province":"TX",
    "wof:name":"Sun Peak Cove Inc",
    "wof:placetype":"venue"
},
  "geometry": {"coordinates":[-97.71832000000001,30.51586],"type":"Point"}
}