{
  "type": "Feature",
  "properties": {
    "iso:country":"US",
    "sg:address":"2000 Murphy Dr",
    "sg:city":"Bedford",
    "sg:classifiers":[
        {
            "category":"Food & Beverages",
            "subcategory":"Groceries & Convenience Stores",
            "type":"Retail Goods"
        }
    ],
    "sg:phone":"+1 817 354 6830",
    "sg:postcode":"76021",
    "sg:province":"TX",
    "wof:name":"Murphy Mart",
    "wof:placetype":"venue"
},
  "geometry": {"coordinates":[-97.12343799999999,32.843331],"type":"Point"}
}