{
  "type": "Feature",
  "properties": {
    "iso:country":"US",
    "sg:address":"14110 Business Ave",
    "sg:city":"Laredo",
    "sg:classifiers":[
        {
            "category":"Professional",
            "subcategory":"Business Services",
            "type":"Services"
        }
    ],
    "sg:phone":"+1 956 791 8080",
    "sg:postcode":"78045",
    "sg:province":"TX",
    "wof:name":"Jireh Customs Services Co LLC",
    "wof:placetype":"venue"
},
  "geometry": {"coordinates":[-99.53364000000001,27.615921],"type":"Point"}
}