{
  "type": "Feature",
  "properties": {
    "iso:country":"US",
    "sg:address":"5866 S Staples St",
    "sg:city":"Corpus Christi",
    "sg:classifiers":[
        {
            "category":"Real Estate",
            "subcategory":"Real Estate Agent",
            "type":"Services"
        }
    ],
    "sg:phone":"+1 361 993 0184",
    "sg:postcode":"78413",
    "sg:province":"TX",
    "sg:tags":[
        "management"
    ],
    "wof:name":"Capital Management Co",
    "wof:placetype":"venue"
},
  "geometry": {"coordinates":[-97.377713,27.69522],"type":"Point"}
}