{
  "type": "Feature",
  "properties": {
    "iso:country":"US",
    "sg:address":"160 E Spring Valley Rd",
    "sg:city":"Richardson",
    "sg:classifiers":[
        {
            "category":"Restaurant",
            "type":"Food & Drink"
        }
    ],
    "sg:phone":"+1 972 235 7942",
    "sg:postcode":"75081",
    "sg:province":"TX",
    "sg:tags":[
        "eating"
    ],
    "wof:name":"Taco Bell",
    "wof:placetype":"venue"
},
  "geometry": {"coordinates":[-96.736289,32.939988],"type":"Point"}
}