{
  "type": "Feature",
  "properties": {
    "iso:country":"US",
    "sg:address":"822 E King Ave",
    "sg:city":"Kingsville",
    "sg:classifiers":[
        {
            "category":"Shopping",
            "subcategory":"Hobbies, Toys, & Games",
            "type":"Retail Goods"
        }
    ],
    "sg:phone":"+1 361 595 7785",
    "sg:postcode":"78363",
    "sg:province":"TX",
    "wof:name":"Hobby House",
    "wof:placetype":"venue"
},
  "geometry": {"coordinates":[-97.857906,27.515771],"type":"Point"}
}