{
  "type": "Feature",
  "properties": {
    "iso:country":"US",
    "sg:address":"2305 Colorado Blvd",
    "sg:city":"Denton",
    "sg:classifiers":[
        {
            "category":"Shopping",
            "subcategory":"Music",
            "type":"Retail Goods"
        }
    ],
    "sg:phone":"+1 940 565 1764",
    "sg:postcode":"76205",
    "sg:province":"TX",
    "sg:tags":[
        "book",
        "video"
    ],
    "wof:name":"Hastings Books 9684",
    "wof:placetype":"venue"
},
  "geometry": {"coordinates":[-97.10610699999999,33.193749],"type":"Point"}
}