{
  "type": "Feature",
  "properties": {
    "iso:country":"US",
    "sg:address":"940 N Belt Line Rd",
    "sg:city":"Irving",
    "sg:classifiers":[
        {
            "category":"Building & Trades",
            "subcategory":"Plumbing",
            "type":"Services"
        },
        {
            "category":"Building & Trades",
            "subcategory":"Construction",
            "type":"Services"
        },
        {
            "category":"Building & Trades",
            "subcategory":"Electrical",
            "type":"Services"
        }
    ],
    "sg:phone":"+1 972 986 4006",
    "sg:postcode":"75061",
    "sg:province":"TX",
    "sg:tags":[
        "repair",
        "plumber",
        "electrician",
        "specialty",
        "system",
        "heating",
        "contractor",
        "air conditioning"
    ],
    "sg:website":"http://www.henrysserviceall.com",
    "wof:name":"Henry's Service All",
    "wof:placetype":"venue"
},
  "geometry": {"coordinates":[-96.993697,32.8238],"type":"Point"}
}