{
  "type": "Feature",
  "properties": {
    "iso:country":"US",
    "sg:address":"1128 N Main St",
    "sg:city":"Cleburne",
    "sg:classifiers":[
        {
            "category":"Retail",
            "subcategory":"Auto Repair",
            "type":"Services"
        }
    ],
    "sg:phone":"+1 817 689 1490",
    "sg:postcode":"76033",
    "sg:province":"TX",
    "sg:tags":[
        "body",
        "painting",
        "repairing",
        "automobile"
    ],
    "wof:name":"Ivan's Paint And Body",
    "wof:placetype":"venue"
},
  "geometry": {"coordinates":[-97.38713799999999,32.39677],"type":"Point"}
}