{
  "type": "Feature",
  "properties": {
    "iso:country":"US",
    "sg:address":"1501 N Neches St",
    "sg:city":"Coleman",
    "sg:classifiers":[
        {
            "category":"Food & Beverages",
            "subcategory":"Groceries & Convenience Stores",
            "type":"Retail Goods"
        }
    ],
    "sg:phone":"+1 325 625 3416",
    "sg:postcode":"76834",
    "sg:province":"TX",
    "sg:tags":[
        "station",
        "gasoline"
    ],
    "wof:name":"Allsups",
    "wof:placetype":"venue"
},
  "geometry": {"coordinates":[-99.427171,31.8445],"type":"Point"}
}