{
  "type": "Feature",
  "properties": {
    "iso:country":"US",
    "sg:address":"1020 W End St",
    "sg:city":"Terrell",
    "sg:classifiers":[
        {
            "category":"Organizations",
            "subcategory":"Religious Organization",
            "type":"Services"
        }
    ],
    "sg:phone":"+1 972 563 3109",
    "sg:postcode":"75160",
    "sg:province":"TX",
    "sg:tags":[
        "church"
    ],
    "wof:name":"Mount Calvary Baptist Church",
    "wof:placetype":"venue"
},
  "geometry": {"coordinates":[-96.30014799999999,32.736468],"type":"Point"}
}