{
  "type": "Feature",
  "properties": {
    "iso:country":"US",
    "sg:address":"13106 Chrisman Rd",
    "sg:city":"Houston",
    "sg:classifiers":[
        {
            "category":"Organizations",
            "subcategory":"Community Association",
            "type":"Services"
        }
    ],
    "sg:phone":"+1 281 442 4105",
    "sg:postcode":"77039",
    "sg:province":"TX",
    "sg:tags":[
        "fraternal"
    ],
    "wof:name":"Masonic Lodge",
    "wof:placetype":"venue"
},
  "geometry": {"coordinates":[-95.363373,29.902447],"type":"Point"}
}