{
  "type": "Feature",
  "properties": {
    "iso:country":"US",
    "sg:address":"3145 Tudor Ln",
    "sg:city":"Irving",
    "sg:classifiers":[
        {
            "category":"Social Services",
            "subcategory":"Child Care",
            "type":"Services"
        }
    ],
    "sg:phone":"+1 214 441 3463",
    "sg:postcode":"75060",
    "sg:province":"TX",
    "wof:name":"Aunties Day Care",
    "wof:placetype":"venue"
},
  "geometry": {"coordinates":[-96.98927500000001,32.813719],"type":"Point"}
}