{
  "type": "Feature",
  "properties": {
    "iso:country":"US",
    "sg:address":"8299 Small Block Rd",
    "sg:city":"Roanoke",
    "sg:classifiers":[
        {
            "category":"Building & Trades",
            "subcategory":"Construction",
            "type":"Services"
        }
    ],
    "sg:phone":"+1 817 464 0030",
    "sg:postcode":"76262",
    "sg:province":"TX",
    "sg:tags":[
        "company"
    ],
    "wof:name":"N E Construction",
    "wof:placetype":"venue"
},
  "geometry": {"coordinates":[-97.27515200000001,33.022298],"type":"Point"}
}