{
  "type": "Feature",
  "properties": {
    "iso:country":"US",
    "sg:address":"13650 T I Blvd",
    "sg:city":"Dallas",
    "sg:classifiers":[
        {
            "category":"Building & Trades",
            "subcategory":"Construction",
            "type":"Services"
        }
    ],
    "sg:phone":"+1 214 575 8840",
    "sg:postcode":"75243",
    "sg:province":"TX",
    "sg:tags":[
        "roofing",
        "contractor"
    ],
    "wof:name":"Prosource Roofing LTD",
    "wof:placetype":"venue"
},
  "geometry": {"coordinates":[-96.74832600000001,32.934042],"type":"Point"}
}