{
  "type": "Feature",
  "properties": {
    "iso:country":"US",
    "sg:address":"1320 Greenway Dr",
    "sg:city":"Irving",
    "sg:classifiers":[
        {
            "category":"Professional",
            "type":"Services"
        }
    ],
    "sg:phone":"+1 214 441 1347",
    "sg:postcode":"75038",
    "sg:province":"TX",
    "sg:tags":[
        "establishment"
    ],
    "wof:name":"First Manhattan",
    "wof:placetype":"venue"
},
  "geometry": {"coordinates":[-96.968943,32.889663],"type":"Point"}
}