{
  "type": "Feature",
  "properties": {
    "iso:country":"US",
    "sg:address":"1500 Convention Center Dr",
    "sg:city":"Arlington",
    "sg:classifiers":[
        {
            "category":"Retail",
            "subcategory":"Laundry & Dry Cleaning",
            "type":"Services"
        },
        {
            "category":"Personal",
            "type":"Services"
        }
    ],
    "sg:phone":"+1 817 274 6696",
    "sg:postcode":"76011",
    "sg:province":"TX",
    "sg:tags":[
        "valet"
    ],
    "wof:name":"City Nights Valet Inc",
    "wof:placetype":"venue"
},
  "geometry": {"coordinates":[-97.080152,32.75773],"type":"Point"}
}