{
  "type": "Feature",
  "properties": {
    "iso:country":"US",
    "sg:address":"1454 Halsey Way",
    "sg:city":"Carrollton",
    "sg:classifiers":[
        {
            "category":"Manufacturing",
            "subcategory":"Tools & Machinery",
            "type":"Manufacturing & Wholesale Goods"
        }
    ],
    "sg:phone":"+1 972 242 3232",
    "sg:postcode":"75007",
    "sg:province":"TX",
    "sg:tags":[
        "surgical",
        "industrial",
        "electrical",
        "apparatus",
        "mfg"
    ],
    "wof:name":"Thermotek Inc",
    "wof:placetype":"venue"
},
  "geometry": {"coordinates":[-96.922543,32.987837],"type":"Point"}
}