{
  "type": "Feature",
  "properties": {
    "iso:country":"US",
    "sg:address":"17415 Club Hill Ct",
    "sg:city":"Dallas",
    "sg:classifiers":[
        {
            "category":"Wholesale",
            "subcategory":"Electrical",
            "type":"Manufacturing & Wholesale Goods"
        }
    ],
    "sg:phone":"+1 972 250 2500",
    "sg:postcode":"75248",
    "sg:province":"TX",
    "sg:tags":[
        "equipment",
        "electric",
        "supply"
    ],
    "wof:name":"Breaker Supply Inc",
    "wof:placetype":"venue"
},
  "geometry": {"coordinates":[-96.815437,32.985649],"type":"Point"}
}