{
  "type": "Feature",
  "properties": {
    "iso:country":"US",
    "sg:address":"14415 Stagecoach Rd",
    "sg:city":"Magnolia",
    "sg:classifiers":[
        {
            "category":"Building & Trades",
            "subcategory":"Landscaping Services",
            "type":"Services"
        }
    ],
    "sg:phone":"+1 281 356 5296",
    "sg:postcode":"77355",
    "sg:province":"TX",
    "wof:name":"Extra Touch Landscaping",
    "wof:placetype":"venue"
},
  "geometry": {"coordinates":[-95.694345,30.138503],"type":"Point"}
}