{
  "type": "Feature",
  "properties": {
    "iso:country":"US",
    "sg:address":"236 Northwest Dr",
    "sg:city":"Hereford",
    "sg:classifiers":[
        {
            "category":"Professional",
            "type":"Services"
        }
    ],
    "sg:phone":"+1 806 364 4404",
    "sg:postcode":"79045",
    "sg:province":"TX",
    "wof:name":"Wartes Reality",
    "wof:placetype":"venue"
},
  "geometry": {"coordinates":[-102.411304,34.82831],"type":"Point"}
}