{
  "type": "Feature",
  "properties": {
    "iso:country":"US",
    "sg:address":"201 San Jacinto Ct",
    "sg:city":"Waxahachie",
    "sg:classifiers":[
        {
            "category":"Wholesale",
            "subcategory":"Construction Materials",
            "type":"Manufacturing & Wholesale Goods"
        },
        {
            "category":"Manufacturing",
            "subcategory":"Metals",
            "type":"Manufacturing & Wholesale Goods"
        }
    ],
    "sg:phone":"+1 972 938 9771",
    "sg:postcode":"75165",
    "sg:province":"TX",
    "sg:tags":[
        "weather",
        "stripping",
        "mfg"
    ],
    "wof:name":"Odom David Weather Strip Co",
    "wof:placetype":"venue"
},
  "geometry": {"coordinates":[-96.84520999999999,32.416143],"type":"Point"}
}