{
  "type": "Feature",
  "properties": {
    "iso:country":"US",
    "sg:address":"301 N Seaman St",
    "sg:city":"Eastland",
    "sg:classifiers":[
        {
            "category":"Wholesale",
            "subcategory":"Farm Supplies",
            "type":"Manufacturing & Wholesale Goods"
        }
    ],
    "sg:phone":"+1 254 629 2173",
    "sg:postcode":"76448",
    "sg:province":"TX",
    "wof:name":"Eastland Farm & Ranch Inc",
    "wof:placetype":"venue"
},
  "geometry": {"coordinates":[-98.81811500000001,32.404789],"type":"Point"}
}