{
  "type": "Feature",
  "properties": {
    "iso:country":"US",
    "sg:address":"11907 N Garden St",
    "sg:city":"Houston",
    "sg:classifiers":[
        {
            "category":"Retail",
            "subcategory":"Repair Shop",
            "type":"Services"
        }
    ],
    "sg:phone":"+1 713 995 9797",
    "sg:postcode":"77071",
    "sg:province":"TX",
    "sg:tags":[
        "equipment",
        "blasting",
        "blast",
        "cleaning"
    ],
    "wof:name":"Texla Parts & Equipment Inc",
    "wof:placetype":"venue"
},
  "geometry": {"coordinates":[-95.52233,29.632156],"type":"Point"}
}