{
  "type": "Feature",
  "properties": {
    "iso:country":"US",
    "sg:address":"4500 Jimmy Doolittle Dr",
    "sg:city":"Addison",
    "sg:classifiers":[
        {
            "category":"Wholesale",
            "subcategory":"Machinery & Supplies",
            "type":"Manufacturing & Wholesale Goods"
        }
    ],
    "sg:phone":"+1 972 248 3520",
    "sg:postcode":"75001",
    "sg:province":"TX",
    "sg:tags":[
        "equipment",
        "transportation"
    ],
    "wof:name":"Turbin Aircraft Services Inc",
    "wof:placetype":"venue"
},
  "geometry": {"coordinates":[-96.832809,32.967746],"type":"Point"}
}