{
  "type": "Feature",
  "properties": {
    "iso:country":"US",
    "sg:address":"16753 Donwick Dr",
    "sg:city":"Conroe",
    "sg:classifiers":[
        {
            "category":"Professional",
            "type":"Services"
        }
    ],
    "sg:phone":"+1 936 321 9644",
    "sg:postcode":"77385",
    "sg:province":"TX",
    "sg:tags":[
        "establishment"
    ],
    "wof:name":"Elkins & Williams",
    "wof:placetype":"venue"
},
  "geometry": {"coordinates":[-95.441568,30.212263],"type":"Point"}
}