{
  "type": "Feature",
  "properties": {
    "iso:country":"US",
    "sg:address":"104 Lamplighter Ct",
    "sg:city":"Azle",
    "sg:classifiers":[
        {
            "category":"Organizations",
            "subcategory":"Community Association",
            "type":"Services"
        }
    ],
    "sg:phone":"+1 817 237 0385",
    "sg:postcode":"76020",
    "sg:province":"TX",
    "sg:tags":[
        "fraternal"
    ],
    "wof:name":"Texas Community Alternatives",
    "wof:placetype":"venue"
},
  "geometry": {"coordinates":[-97.516413,32.868048],"type":"Point"}
}