{
  "type": "Feature",
  "properties": {
    "iso:country":"US",
    "sg:address":"9321 Meldrum Ln",
    "sg:city":"Houston",
    "sg:classifiers":[
        {
            "category":"Building & Trades",
            "subcategory":"Construction",
            "type":"Services"
        }
    ],
    "sg:phone":"+1 713 947 8177",
    "sg:postcode":"77075",
    "sg:province":"TX",
    "sg:tags":[
        "contractor"
    ],
    "wof:name":"South Texas Projects",
    "wof:placetype":"venue"
},
  "geometry": {"coordinates":[-95.25035,29.634675],"type":"Point"}
}