{
  "type": "Feature",
  "properties": {
    "iso:country":"US",
    "sg:address":"2201 E Lamar Blvd",
    "sg:city":"Arlington",
    "sg:classifiers":[
        {
            "category":"Professional",
            "subcategory":"Lawyer & Legal Services",
            "type":"Services"
        }
    ],
    "sg:phone":"+1 817 640 6401",
    "sg:postcode":"76006",
    "sg:province":"TX",
    "sg:tags":[
        "attorney"
    ],
    "wof:name":"James C Ash Jr",
    "wof:placetype":"venue"
},
  "geometry": {"coordinates":[-97.071046,32.761547],"type":"Point"}
}