{
  "type": "Feature",
  "properties": {
    "iso:country":"US",
    "sg:address":"1618 Fairway Vista Dr",
    "sg:city":"Denton",
    "sg:classifiers":[
        {
            "category":"Building & Trades",
            "subcategory":"Construction",
            "type":"Services"
        }
    ],
    "sg:phone":"+1 940 498 9171",
    "sg:postcode":"76210",
    "sg:province":"TX",
    "sg:tags":[
        "house"
    ],
    "wof:name":"Plantation Homes",
    "wof:placetype":"venue"
},
  "geometry": {"coordinates":[-97.085306,33.150167],"type":"Point"}
}