{
  "type": "Feature",
  "properties": {
    "iso:country":"US",
    "sg:address":"1011 Becker St",
    "sg:city":"Channelview",
    "sg:classifiers":[
        {
            "category":"Building & Trades",
            "subcategory":"Landscaping Services",
            "type":"Services"
        }
    ],
    "sg:phone":"+1 281 452 5468",
    "sg:postcode":"77530",
    "sg:province":"TX",
    "wof:name":"Tornado Express Lawns",
    "wof:placetype":"venue"
},
  "geometry": {"coordinates":[-95.116507,29.793857],"type":"Point"}
}