{
  "type": "Feature",
  "properties": {
    "iso:country":"US",
    "sg:address":"1303 S Midland Dr",
    "sg:city":"Midland",
    "sg:classifiers":[
        {
            "category":"Retail",
            "subcategory":"Auto Repair",
            "type":"Services"
        }
    ],
    "sg:phone":"+1 432 262 5896",
    "sg:postcode":"79703",
    "sg:province":"TX",
    "sg:tags":[
        "body",
        "automobile",
        "painting"
    ],
    "wof:name":"Midland Body Works",
    "wof:placetype":"venue"
},
  "geometry": {"coordinates":[-102.127083,31.96911],"type":"Point"}
}