{
  "type": "Feature",
  "properties": {
    "iso:country":"US",
    "sg:address":"5706 W 45th Ave",
    "sg:city":"Amarillo",
    "sg:classifiers":[
        {
            "category":"Professional",
            "subcategory":"Computer Services",
            "type":"Services"
        }
    ],
    "sg:phone":"+1 806 350 7811",
    "sg:postcode":"79109",
    "sg:province":"TX",
    "sg:tags":[
        "consultant",
        "designer",
        "datum",
        "system"
    ],
    "wof:name":"Technique Data System Inc",
    "wof:placetype":"venue"
},
  "geometry": {"coordinates":[-101.902173,35.161576],"type":"Point"}
}