{
  "type": "Feature",
  "properties": {
    "iso:country":"US",
    "sg:address":"1310 N Texas Blvd",
    "sg:city":"Weslaco",
    "sg:classifiers":[
        {
            "category":"Banks & Credit Unions",
            "subcategory":"Bank",
            "type":"Services"
        }
    ],
    "sg:phone":"+1 956 973 9500",
    "sg:postcode":"78596",
    "sg:province":"TX",
    "wof:name":"International Bank Of Comm",
    "wof:placetype":"venue"
},
  "geometry": {"coordinates":[-97.990936,26.174862],"type":"Point"}
}