{
  "type": "Feature",
  "properties": {
    "iso:country":"US",
    "sg:address":"200 Mill Branch Ln",
    "sg:city":"Lancaster",
    "sg:classifiers":[
        {
            "category":"Manufacturing",
            "subcategory":"Wood Products",
            "type":"Manufacturing & Wholesale Goods"
        }
    ],
    "sg:phone":"+1 972 227 2741",
    "sg:postcode":"75146",
    "sg:province":"TX",
    "sg:tags":[
        "mfg"
    ],
    "wof:name":"Arthur K Ransom",
    "wof:placetype":"venue"
},
  "geometry": {"coordinates":[-96.79062,32.585219],"type":"Point"}
}