{
  "type": "Feature",
  "properties": {
    "iso:country":"US",
    "sg:address":"1627 Market Center Blvd",
    "sg:city":"Dallas",
    "sg:classifiers":[
        {
            "category":"Shopping",
            "subcategory":"Bicycles & Sporting Goods",
            "type":"Retail Goods"
        }
    ],
    "sg:phone":"+1 214 748 8451",
    "sg:postcode":"75207",
    "sg:province":"TX",
    "wof:name":"Tamj Leather Goods",
    "wof:placetype":"venue"
},
  "geometry": {"coordinates":[-96.822283,32.792932],"type":"Point"}
}