{
  "type": "Feature",
  "properties": {
    "iso:country":"US",
    "sg:address":"3603 Ross Ave",
    "sg:city":"Dallas",
    "sg:classifiers":[
        {
            "category":"Professional",
            "subcategory":"Advertising",
            "type":"Services"
        }
    ],
    "sg:phone":"+1 972 380 9111",
    "sg:postcode":"75204",
    "sg:province":"TX",
    "sg:tags":[
        "billboard"
    ],
    "wof:name":"Billboard Services Inc",
    "wof:placetype":"venue"
},
  "geometry": {"coordinates":[-96.78792300000001,32.79646],"type":"Point"}
}