{
  "type": "Feature",
  "properties": {
    "iso:country":"US",
    "sg:address":"2509 80th St",
    "sg:city":"Lubbock",
    "sg:classifiers":[
        {
            "category":"Real Estate",
            "subcategory":"Real Estate Agent",
            "type":"Services"
        }
    ],
    "sg:phone":"+1 806 785 2422",
    "sg:postcode":"79423",
    "sg:province":"TX",
    "wof:name":"Green Real Estate & Investment",
    "wof:placetype":"venue"
},
  "geometry": {"coordinates":[-101.87266099999999,33.521488],"type":"Point"}
}