{
  "type": "Feature",
  "properties": {
    "iso:country":"US",
    "sg:address":"5360 N Macarthur Blvd",
    "sg:city":"Irving",
    "sg:classifiers":[
        {
            "category":"Restaurant",
            "type":"Food & Drink"
        }
    ],
    "sg:menulink":"http://www.allmenus.com/tx/southwest/193484-taco-bell/menu/",
    "sg:postcode":"75038",
    "sg:province":"TX",
    "sg:tags":[
        "mexican"
    ],
    "wof:name":"Taco Bell",
    "wof:placetype":"venue"
},
  "geometry": {"coordinates":[-96.96346699999999,32.8829],"type":"Point"}
}