{
  "type": "Feature",
  "properties": {
    "iso:country":"US",
    "sg:address":"200 N Dairy Ashford Rd",
    "sg:city":"Houston",
    "sg:classifiers":[
        {
            "category":"Organizations",
            "subcategory":"Professional Association",
            "type":"Services"
        }
    ],
    "sg:phone":"+1 281 679 8040",
    "sg:postcode":"77079",
    "sg:province":"TX",
    "sg:tags":[
        "business",
        "offshore",
        "for"
    ],
    "wof:name":"Offshore Energy Center",
    "wof:placetype":"venue"
},
  "geometry": {"coordinates":[-95.60650699999999,29.785286],"type":"Point"}
}