{
  "type": "Feature",
  "properties": {
    "iso:country":"US",
    "sg:address":"16422 Farnell Ct",
    "sg:city":"Spring",
    "sg:classifiers":[
        {
            "category":"Manufacturing",
            "subcategory":"Printing",
            "type":"Manufacturing & Wholesale Goods"
        }
    ],
    "sg:phone":"+1 832 717 4848",
    "sg:postcode":"77379",
    "sg:province":"TX",
    "sg:tags":[
        "publisher"
    ],
    "wof:name":"City Publications Of Houston",
    "wof:placetype":"venue"
},
  "geometry": {"coordinates":[-95.534043,30.007726],"type":"Point"}
}