{
  "type": "Feature",
  "properties": {
    "iso:country":"US",
    "sg:address":"531 Waldo Rd",
    "sg:city":"Mc Gregor",
    "sg:phone":"+1 254 486 2457",
    "sg:postcode":"76657",
    "sg:province":"TX",
    "sg:tags":[
        "farm",
        "wheat",
        "corn",
        "grain",
        "cash"
    ],
    "wof:name":"Gregg Westerfeld Farm",
    "wof:placetype":"venue"
},
  "geometry": {"coordinates":[-97.51231,31.485011],"type":"Point"}
}