{
  "type": "Feature",
  "properties": {
    "iso:country":"US",
    "sg:address":"1048 Hot Wells Blvd",
    "sg:city":"San Antonio",
    "sg:classifiers":[
        {
            "category":"Autos & Motor Vehicles",
            "subcategory":"Auto Supplies",
            "type":"Retail Goods"
        }
    ],
    "sg:phone":"+1 210 337 0718",
    "sg:postcode":"78223",
    "sg:province":"TX",
    "sg:tags":[
        "tire"
    ],
    "wof:name":"Simon's Tire Shop",
    "wof:placetype":"venue"
},
  "geometry": {"coordinates":[-98.444608,29.368632],"type":"Point"}
}