{
  "type": "Feature",
  "properties": {
    "iso:country":"US",
    "sg:address":"5501 Columbia Ave",
    "sg:city":"Dallas",
    "sg:classifiers":[
        {
            "category":"Arts & Performance",
            "subcategory":"Arts Center",
            "type":"Entertainment"
        },
        {
            "category":"Community Center",
            "type":"Public Place"
        },
        {
            "category":"Museum",
            "type":"Entertainment"
        }
    ],
    "sg:phone":"+1 214 824 4251",
    "sg:postcode":"75214",
    "sg:province":"TX",
    "sg:tags":[
        "information",
        "reading",
        "christian",
        "room",
        "science"
    ],
    "wof:name":"5501 Columbia Art Center",
    "wof:placetype":"venue"
},
  "geometry": {"coordinates":[-96.757668,32.800072],"type":"Point"}
}