{
  "type": "Feature",
  "properties": {
    "iso:country":"US",
    "sg:address":"4113 Arborcrest Dr",
    "sg:city":"Mesquite",
    "sg:classifiers":[
        {
            "category":"Shopping",
            "subcategory":"Used Merchandise",
            "type":"Retail Goods"
        }
    ],
    "sg:phone":"+1 972 557 0331",
    "sg:postcode":"75180",
    "sg:province":"TX",
    "wof:name":"Ruth Whatley",
    "wof:placetype":"venue"
},
  "geometry": {"coordinates":[-96.59545,32.716604],"type":"Point"}
}