{
  "type": "Feature",
  "properties": {
    "iso:country":"US",
    "sg:address":"1924 E Henderson St",
    "sg:city":"Cleburne",
    "sg:classifiers":[
        {
            "category":"Building & Trades",
            "subcategory":"Construction",
            "type":"Services"
        }
    ],
    "sg:phone":"+1 817 641 7383",
    "sg:postcode":"76031",
    "sg:province":"TX",
    "sg:tags":[
        "mobile",
        "home",
        "nonresidential"
    ],
    "wof:name":"Pioneer Mobile Homes",
    "wof:placetype":"venue"
},
  "geometry": {"coordinates":[-97.353711,32.366893],"type":"Point"}
}