{
  "type": "Feature",
  "properties": {
    "iso:country":"US",
    "sg:address":"1603 W Broadway St",
    "sg:city":"Sweetwater",
    "sg:classifiers":[
        {
            "category":"Professional",
            "subcategory":"Business Services",
            "type":"Services"
        }
    ],
    "sg:phone":"+1 325 236 6377",
    "sg:postcode":"79556",
    "sg:province":"TX",
    "sg:tags":[
        "auctioneer"
    ],
    "wof:name":"Sweetwater Cattle Auction Inc",
    "wof:placetype":"venue"
},
  "geometry": {"coordinates":[-100.431077,32.460365],"type":"Point"}
}