{
  "type": "Feature",
  "properties": {
    "iso:country":"US",
    "sg:address":"411 S 1st St W",
    "sg:city":"Clyde",
    "sg:classifiers":[
        {
            "category":"Shopping",
            "subcategory":"Used Merchandise",
            "type":"Retail Goods"
        }
    ],
    "sg:phone":"+1 325 893 2743",
    "sg:postcode":"79510",
    "sg:province":"TX",
    "wof:name":"Goodwill Retail",
    "wof:placetype":"venue"
},
  "geometry": {"coordinates":[-99.502961,32.406833],"type":"Point"}
}