{
  "type": "Feature",
  "properties": {
    "iso:country":"US",
    "sg:address":"2628 Austin Ave",
    "sg:city":"Mcallen",
    "sg:classifiers":[
        {
            "category":"Professional",
            "subcategory":"Detective & Security Services",
            "type":"Services"
        }
    ],
    "sg:phone":"+1 956 630 1533",
    "sg:postcode":"78501",
    "sg:province":"TX",
    "sg:tags":[
        "information",
        "bureau"
    ],
    "wof:name":"Ftf Services",
    "wof:placetype":"venue"
},
  "geometry": {"coordinates":[-98.250175,26.205726],"type":"Point"}
}