{
  "type": "Feature",
  "properties": {
    "iso:country":"US",
    "sg:address":"1304 E Rio Grande St",
    "sg:city":"Victoria",
    "sg:classifiers":[
        {
            "category":"Insurance",
            "subcategory":"Insurance Agent",
            "type":"Services"
        }
    ],
    "sg:phone":"+1 361 573 4567",
    "sg:postcode":"77901",
    "sg:province":"TX",
    "wof:name":"Burgman John",
    "wof:placetype":"venue"
},
  "geometry": {"coordinates":[-96.988865,28.806441],"type":"Point"}
}