{
  "type": "Feature",
  "properties": {
    "iso:country":"US",
    "sg:address":"8701 S Gessner Dr",
    "sg:city":"Houston",
    "sg:classifiers":[
        {
            "category":"Government",
            "subcategory":"Office",
            "type":"Public Place"
        }
    ],
    "sg:phone":"+1 713 773 6500",
    "sg:postcode":"77074",
    "sg:province":"TX",
    "sg:tags":[
        "federal",
        "program",
        "adm"
    ],
    "wof:name":"US Small Business Adm",
    "wof:placetype":"venue"
},
  "geometry": {"coordinates":[-95.528507,29.685299],"type":"Point"}
}