{
  "type": "Feature",
  "properties": {
    "iso:country":"US",
    "sg:address":"3304 Kimberly Ln",
    "sg:city":"Grand Prairie",
    "sg:classifiers":[
        {
            "category":"Personal",
            "type":"Services"
        }
    ],
    "sg:phone":"+1 972 602 0867",
    "sg:postcode":"75052",
    "sg:province":"TX",
    "wof:name":"Creative Anonited Images",
    "wof:placetype":"venue"
},
  "geometry": {"coordinates":[-97.04903,32.687571],"type":"Point"}
}