{
  "type": "Feature",
  "properties": {
    "iso:country":"US",
    "sg:address":"1506 W Buckingham Rd",
    "sg:city":"Garland",
    "sg:classifiers":[
        {
            "category":"Restaurant",
            "type":"Food & Drink"
        }
    ],
    "sg:menulink":"http://www.allmenus.com/tx/northeast/157178-whataburger/menu/",
    "sg:phone":"+1 972 276 6900",
    "sg:postcode":"75042",
    "sg:province":"TX",
    "sg:tags":[
        "burger",
        "american"
    ],
    "wof:name":"Whataburger",
    "wof:placetype":"venue"
},
  "geometry": {"coordinates":[-96.64994,32.930601],"type":"Point"}
}