{
  "type": "Feature",
  "properties": {
    "iso:country":"US",
    "sg:address":"7801 Main St",
    "sg:city":"Houston",
    "sg:classifiers":[
        {
            "category":"Shopping",
            "subcategory":"Crafts & Fabrics",
            "type":"Retail Goods"
        }
    ],
    "sg:phone":"+1 713 395 7308",
    "sg:postcode":"77030",
    "sg:province":"TX",
    "sg:tags":[
        "art",
        "supply"
    ],
    "wof:name":"Garden Ridge",
    "wof:placetype":"venue"
},
  "geometry": {"coordinates":[-95.41332199999999,29.69577],"type":"Point"}
}