{
  "type": "Feature",
  "properties": {
    "iso:country":"US",
    "sg:address":"408 W 8th St",
    "sg:city":"Cisco",
    "sg:classifiers":[
        {
            "category":"Education",
            "subcategory":"Special Training",
            "type":"Public Place"
        }
    ],
    "sg:phone":"+1 254 442 4099",
    "sg:postcode":"76437",
    "sg:province":"TX",
    "sg:tags":[
        "instruction",
        "music"
    ],
    "wof:name":"Susan Piano Wester & Voice Stu",
    "wof:placetype":"venue"
},
  "geometry": {"coordinates":[-98.982231,32.38683],"type":"Point"}
}