{
  "type": "Feature",
  "properties": {
    "iso:country":"US",
    "sg:address":"3560 Wosley Dr",
    "sg:city":"Fort Worth",
    "sg:classifiers":[
        {
            "category":"Food & Beverages",
            "subcategory":"Specialty",
            "type":"Retail Goods"
        }
    ],
    "sg:phone":"+1 817 263 5737",
    "sg:postcode":"76133",
    "sg:province":"TX",
    "sg:tags":[
        "health",
        "diet"
    ],
    "wof:name":"Positive Effects",
    "wof:placetype":"venue"
},
  "geometry": {"coordinates":[-97.371377,32.666342],"type":"Point"}
}