{
  "type": "Feature",
  "properties": {
    "iso:country":"US",
    "sg:address":"5627 Dyer St",
    "sg:city":"Dallas",
    "sg:classifiers":[
        {
            "category":"Restaurant",
            "type":"Food & Drink"
        }
    ],
    "sg:phone":"+1 214 265 1338",
    "sg:postcode":"75206",
    "sg:province":"TX",
    "wof:name":"Green Elephant",
    "wof:placetype":"venue"
},
  "geometry": {"coordinates":[-96.77144699999999,32.843266],"type":"Point"}
}