{
  "type": "Feature",
  "properties": {
    "iso:country":"US",
    "sg:address":"3319 Elmridge St",
    "sg:city":"Houston",
    "sg:classifiers":[
        {
            "category":"Shopping",
            "subcategory":"Used Merchandise",
            "type":"Retail Goods"
        }
    ],
    "sg:phone":"+1 713 664 4447",
    "sg:postcode":"77025",
    "sg:province":"TX",
    "wof:name":"Hebert Antiques & Collectibles",
    "wof:placetype":"venue"
},
  "geometry": {"coordinates":[-95.428895,29.683967],"type":"Point"}
}