{
  "type": "Feature",
  "properties": {
    "iso:country":"US",
    "sg:address":"5345 William D Tate Ave",
    "sg:city":"Grapevine",
    "sg:classifiers":[
        {
            "category":"Restaurant",
            "type":"Food & Drink"
        }
    ],
    "sg:menulink":"http://www.allmenus.com/tx/northeast-tarrant/202066-mcdonalds/menu/",
    "sg:postcode":"76051",
    "sg:province":"TX",
    "sg:tags":[
        "burger",
        "american"
    ],
    "wof:name":"McDonald's",
    "wof:placetype":"venue"
},
  "geometry": {"coordinates":[-97.098653,32.882225],"type":"Point"}
}