{
  "type": "Feature",
  "properties": {
    "iso:country":"US",
    "sg:address":"705 N Greenwood St",
    "sg:city":"Houston",
    "sg:classifiers":[
        {
            "category":"Freight",
            "type":"Transportation"
        }
    ],
    "sg:phone":"+1 713 923 2585",
    "sg:postcode":"77011",
    "sg:province":"TX",
    "sg:tags":[
        "cargo",
        "handler",
        "marine"
    ],
    "wof:name":"General Stevedores Inc",
    "wof:placetype":"venue"
},
  "geometry": {"coordinates":[-95.31037499999999,29.752077],"type":"Point"}
}