{
  "type": "Feature",
  "properties": {
    "iso:country":"US",
    "sg:address":"3701 Ave G",
    "sg:city":"Galveston",
    "sg:classifiers":[
        {
            "category":"Bars & Pubs",
            "type":"Food & Drink"
        }
    ],
    "sg:phone":"+1 409 763 9653",
    "sg:postcode":"77550",
    "sg:province":"TX",
    "sg:tags":[
        "drinking"
    ],
    "wof:name":"Kimbrows Lounge",
    "wof:placetype":"venue"
},
  "geometry": {"coordinates":[-94.81014999999999,29.298278],"type":"Point"}
}