{
  "type": "Feature",
  "properties": {
    "iso:country":"US",
    "sg:address":"1224 Taperwicke Dr",
    "sg:city":"Dallas",
    "sg:classifiers":[
        {
            "category":"Shopping",
            "subcategory":"Clothing, Apparel, & Fashions",
            "type":"Retail Goods"
        }
    ],
    "sg:phone":"+1 972 224 1563",
    "sg:postcode":"75232",
    "sg:province":"TX",
    "wof:name":"Precious Stones & Etc",
    "wof:placetype":"venue"
},
  "geometry": {"coordinates":[-96.84542399999999,32.651785],"type":"Point"}
}