{
  "type": "Feature",
  "properties": {
    "iso:country":"US",
    "sg:address":"PO Box 8560",
    "sg:city":"Houston",
    "sg:classifiers":[
        {
            "category":"Professional",
            "subcategory":"Business Services",
            "type":"Services"
        }
    ],
    "sg:phone":"+1 713 880 3123",
    "sg:postcode":"77249",
    "sg:province":"TX",
    "sg:tags":[
        "delivery",
        "courier"
    ],
    "wof:name":"G L Transport Services",
    "wof:placetype":"venue"
},
  "geometry": {"coordinates":[-95.3797,29.803801],"type":"Point"}
}