{
  "type": "Feature",
  "properties": {
    "iso:country":"US",
    "sg:address":"16715 Huffmeister Rd",
    "sg:city":"Cypress",
    "sg:classifiers":[
        {
            "category":"Building & Trades",
            "subcategory":"Construction",
            "type":"Services"
        }
    ],
    "sg:phone":"+1 281 373 5927",
    "sg:postcode":"77429",
    "sg:province":"TX",
    "sg:tags":[
        "excavation",
        "builder",
        "operative",
        "contractor"
    ],
    "wof:name":"Greg Spedale Service Co",
    "wof:placetype":"venue"
},
  "geometry": {"coordinates":[-95.67357,29.994041],"type":"Point"}
}