{
  "type": "Feature",
  "properties": {
    "iso:country":"US",
    "sg:address":"1516 Ridgeview St",
    "sg:city":"Mesquite",
    "sg:classifiers":[
        {
            "category":"Professional",
            "subcategory":"Engineering",
            "type":"Services"
        }
    ],
    "sg:phone":"+1 972 288 6168",
    "sg:postcode":"75149",
    "sg:province":"TX",
    "sg:tags":[
        "engineer"
    ],
    "wof:name":"Mallow Associates Inc",
    "wof:placetype":"venue"
},
  "geometry": {"coordinates":[-96.61379700000001,32.788215],"type":"Point"}
}