{
  "type": "Feature",
  "properties": {
    "iso:country":"US",
    "sg:address":"2406 Ellis St",
    "sg:city":"Dallas",
    "sg:classifiers":[
        {
            "category":"Health Services",
            "subcategory":"Clinic",
            "type":"Services"
        }
    ],
    "sg:phone":"+1 214 468 8467",
    "sg:postcode":"75204",
    "sg:province":"TX",
    "wof:name":"Trinity Health Care Mgmt Svc",
    "wof:placetype":"venue"
},
  "geometry": {"coordinates":[-96.796897,32.799693],"type":"Point"}
}