{
  "type": "Feature",
  "properties": {
    "iso:country":"US",
    "sg:address":"1443 Aldine Bender Rd",
    "sg:city":"Houston",
    "sg:classifiers":[
        {
            "category":"Autos & Motor Vehicles",
            "subcategory":"Auto Supplies",
            "type":"Retail Goods"
        }
    ],
    "sg:phone":"+1 281 540 3278",
    "sg:postcode":"77032",
    "sg:province":"TX",
    "sg:tags":[
        "car",
        "equipment",
        "parts",
        "automobile",
        "performance",
        "racing"
    ],
    "sg:website":"www.conleyracing.com",
    "wof:name":"Conley's Performance Plus",
    "wof:placetype":"venue"
},
  "geometry": {"coordinates":[-95.368258,29.933092],"type":"Point"}
}