{
  "type": "Feature",
  "properties": {
    "iso:country":"US",
    "sg:address":"8241 Slippery Creek St",
    "sg:city":"Red Oak",
    "sg:classifiers":[
        {
            "category":"Building & Trades",
            "subcategory":"Plumbing",
            "type":"Services"
        }
    ],
    "sg:phone":"+1 972 296 9043",
    "sg:postcode":"75154",
    "sg:province":"TX",
    "sg:tags":[
        "plumbing",
        "contractor"
    ],
    "wof:name":"J Carroll Plumbing Contractors",
    "wof:placetype":"venue"
},
  "geometry": {"coordinates":[-96.89044800000001,32.510771],"type":"Point"}
}