{
  "type": "Feature",
  "properties": {
    "iso:country":"US",
    "sg:address":"4325 N Josey Ln",
    "sg:city":"Carrollton",
    "sg:classifiers":[
        {
            "category":"Health Services",
            "subcategory":"Doctor",
            "type":"Services"
        }
    ],
    "sg:phone":"+1 972 395 7131",
    "sg:postcode":"75010",
    "sg:province":"TX",
    "sg:tags":[
        "optometrist",
        "surgeon",
        "physician"
    ],
    "wof:name":"Lee Eye Surgery Clinic",
    "wof:placetype":"venue"
},
  "geometry": {"coordinates":[-96.884697,33.027699],"type":"Point"}
}