{
  "type": "Feature",
  "properties": {
    "iso:country":"US",
    "sg:address":"2808 Rolling Hills Dr",
    "sg:city":"Sherman",
    "sg:classifiers":[
        {
            "category":"Home & Garden",
            "subcategory":"Building Materials",
            "type":"Retail Goods"
        }
    ],
    "sg:phone":"+1 903 893 3781",
    "sg:postcode":"75092",
    "sg:province":"TX",
    "sg:tags":[
        "screen",
        "window"
    ],
    "wof:name":"J & L Metalcraft",
    "wof:placetype":"venue"
},
  "geometry": {"coordinates":[-96.65416,33.595554],"type":"Point"}
}