{
  "type": "Feature",
  "properties": {
    "iso:country":"US",
    "sg:address":"7120 Campbell Rd",
    "sg:city":"Dallas",
    "sg:classifiers":[
        {
            "category":"Shopping",
            "subcategory":"Optical Goods",
            "type":"Retail Goods"
        }
    ],
    "sg:phone":"+1 972 931 0394",
    "sg:postcode":"75248",
    "sg:province":"TX",
    "sg:tags":[
        "mfg",
        "ophthalmic"
    ],
    "wof:name":"Campbell Opticians Inc",
    "wof:placetype":"venue"
},
  "geometry": {"coordinates":[-96.784693,32.979069],"type":"Point"}
}