{
  "type": "Feature",
  "properties": {
    "iso:country":"US",
    "sg:address":"3200 Harris Park Ave",
    "sg:city":"Austin",
    "sg:classifiers":[
        {
            "category":"Real Estate",
            "subcategory":"Architect",
            "type":"Services"
        }
    ],
    "sg:phone":"+1 512 469 2900",
    "sg:postcode":"78705",
    "sg:province":"TX",
    "sg:tags":[
        "architects'",
        "specification",
        "builders'",
        "construction",
        "architectural"
    ],
    "wof:name":"Chris Greer Architect",
    "wof:placetype":"venue"
},
  "geometry": {"coordinates":[-97.731056,30.29295],"type":"Point"}
}