{
  "type": "Feature",
  "properties": {
    "iso:country":"US",
    "sg:address":"122 N Valley View Dr",
    "sg:city":"Kerrville",
    "sg:classifiers":[
        {
            "category":"Organizations",
            "subcategory":"Religious Organization",
            "type":"Services"
        }
    ],
    "sg:phone":"+1 830 257 4348",
    "sg:postcode":"78028",
    "sg:province":"TX",
    "sg:tags":[
        "church"
    ],
    "wof:name":"Southern Oaks Baptist Church",
    "wof:placetype":"venue"
},
  "geometry": {"coordinates":[-99.15145,30.02576],"type":"Point"}
}