{
  "type": "Feature",
  "properties": {
    "iso:country":"US",
    "sg:address":"219 Co Rd 467",
    "sg:city":"Muenster",
    "sg:classifiers":[
        {
            "category":"Farming",
            "subcategory":"Dairy Farm",
            "type":"Manufacturing & Wholesale Goods"
        }
    ],
    "sg:phone":"+1 940 759 4930",
    "sg:postcode":"76252",
    "sg:province":"TX",
    "sg:tags":[
        "beef",
        "feedlot",
        "cattle"
    ],
    "wof:name":"Paul Bayer",
    "wof:placetype":"venue"
},
  "geometry": {"coordinates":[-97.39625100000001,33.676962],"type":"Point"}
}