{
  "type": "Feature",
  "properties": {
    "iso:country":"US",
    "sg:address":"2832 Texas Ave",
    "sg:city":"Bridge City",
    "sg:classifiers":[
        {
            "category":"Retail",
            "subcategory":"Veterinary Services",
            "type":"Services"
        }
    ],
    "sg:phone":"+1 409 735 9155",
    "sg:postcode":"77611",
    "sg:province":"TX",
    "sg:tags":[
        "clinic"
    ],
    "wof:name":"Bridge City Animal Hospital",
    "wof:placetype":"venue"
},
  "geometry": {"coordinates":[-93.82404200000001,30.04207],"type":"Point"}
}