{
  "type": "Feature",
  "properties": {
    "iso:country":"US",
    "sg:address":"4130 Byron St",
    "sg:city":"Houston",
    "sg:classifiers":[
        {
            "category":"Park",
            "type":"Public Place"
        },
        {
            "category":"Recreation",
            "subcategory":"Playground",
            "type":"Entertainment"
        },
        {
            "category":"Sports & Exercise",
            "subcategory":"Swimming Pool",
            "type":"Entertainment"
        }
    ],
    "sg:phone":"+1 713 662 5383",
    "sg:postcode":"77006",
    "sg:province":"TX",
    "sg:website":"www.westu.org",
    "wof:name":"Colonial Park",
    "wof:placetype":"venue"
},
  "geometry": {"coordinates":[-95.44384100000001,29.712441],"type":"Point"}
}