{
  "type": "Feature",
  "properties": {
    "iso:country":"US",
    "sg:address":"2663 Myrtle Springs Ave",
    "sg:city":"Dallas",
    "sg:classifiers":[
        {
            "category":"Wholesale",
            "subcategory":"Auto Parts",
            "type":"Manufacturing & Wholesale Goods"
        }
    ],
    "sg:phone":"+1 214 350 6671",
    "sg:postcode":"75220",
    "sg:province":"TX",
    "sg:tags":[
        "equipment",
        "truck"
    ],
    "sg:website":"www.cepimixers.com",
    "wof:name":"Construction Equipment Parts",
    "wof:placetype":"venue"
},
  "geometry": {"coordinates":[-96.88675600000001,32.868539],"type":"Point"}
}