{
  "type": "Feature",
  "properties": {
    "iso:country":"US",
    "sg:address":"4845 Briar Creek Dr",
    "sg:city":"Flower Mound",
    "sg:classifiers":[
        {
            "category":"Organizations",
            "subcategory":"Religious Organization",
            "type":"Services"
        }
    ],
    "sg:phone":"+1 972 355 1809",
    "sg:postcode":"75028",
    "sg:province":"TX",
    "sg:tags":[
        "church"
    ],
    "sg:website":"www.dfwbahai.org",
    "wof:name":"Flower Mound Baha'i Faith Chr",
    "wof:placetype":"venue"
},
  "geometry": {"coordinates":[-97.067459,33.051076],"type":"Point"}
}