{
  "type": "Feature",
  "properties": {
    "iso:country":"US",
    "sg:address":"1509 Woodvine Dr",
    "sg:city":"Houston",
    "sg:classifiers":[
        {
            "category":"Utilities",
            "subcategory":"Electric",
            "type":"Services"
        },
        {
            "category":"Home & Garden",
            "subcategory":"Building Materials",
            "type":"Retail Goods"
        },
        {
            "category":"Building & Trades",
            "subcategory":"Construction",
            "type":"Services"
        }
    ],
    "sg:phone":"+1 713 682 8199",
    "sg:postcode":"77055",
    "sg:province":"TX",
    "sg:tags":[
        "system",
        "specialty",
        "energy",
        "heating",
        "equipment",
        "systems-manufacturers",
        "solar",
        "distributor",
        "contractor",
        "systems-dealers",
        "air conditioning"
    ],
    "wof:name":"Efficient Energy Systems",
    "wof:placetype":"venue"
},
  "geometry": {"coordinates":[-95.478579,29.796441],"type":"Point"}
}