{
  "type": "Feature",
  "properties": {
    "iso:country":"US",
    "sg:address":"1103 Esters Rd",
    "sg:city":"Irving",
    "sg:classifiers":[
        {
            "category":"Professional",
            "subcategory":"Management & Consulting",
            "type":"Services"
        }
    ],
    "sg:phone":"+1 469 499 5442",
    "sg:postcode":"75061",
    "sg:province":"TX",
    "sg:tags":[
        "business"
    ],
    "wof:name":"Dynasty Consulting Group",
    "wof:placetype":"venue"
},
  "geometry": {"coordinates":[-97.010834,32.823942],"type":"Point"}
}