{
  "type": "Feature",
  "properties": {
    "iso:country":"US",
    "sg:address":"330 Sunset St",
    "sg:city":"Denton",
    "sg:classifiers":[
        {
            "category":"Shopping",
            "subcategory":"Clothing, Apparel, & Fashions",
            "type":"Retail Goods"
        }
    ],
    "sg:phone":"+1 940 387 9915",
    "sg:postcode":"76201",
    "sg:province":"TX",
    "sg:tags":[
        "wear"
    ],
    "wof:name":"Small Fry Inc",
    "wof:placetype":"venue"
},
  "geometry": {"coordinates":[-97.13692899999999,33.229639],"type":"Point"}
}