{
  "type": "Feature",
  "properties": {
    "iso:country":"US",
    "sg:address":"1250 S Capital of Texas Hwy",
    "sg:city":"Austin",
    "sg:classifiers":[
        {
            "category":"Professional",
            "subcategory":"Lawyer & Legal Services",
            "type":"Services"
        }
    ],
    "sg:phone":"+1 512 329 2199",
    "sg:postcode":"78746",
    "sg:province":"TX",
    "wof:name":"Rowley John",
    "wof:placetype":"venue"
},
  "geometry": {"coordinates":[-97.820801,30.278999],"type":"Point"}
}