{
  "type": "Feature",
  "properties": {
    "iso:country":"US",
    "sg:address":"3202 Banksfield Ct",
    "sg:city":"Katy",
    "sg:classifiers":[
        {
            "category":"Travel",
            "subcategory":"Travel Agent",
            "type":"Entertainment"
        }
    ],
    "sg:phone":"+1 281 392 6262",
    "sg:postcode":"77494",
    "sg:province":"TX",
    "sg:tags":[
        "agency",
        "services-commercial"
    ],
    "wof:name":"Travelcorp International",
    "wof:placetype":"venue"
},
  "geometry": {"coordinates":[-95.78744,29.736157],"type":"Point"}
}