{
  "type": "Feature",
  "properties": {
    "iso:country":"US",
    "sg:address":"689 Bob White Rd",
    "sg:city":"Victoria",
    "sg:classifiers":[
        {
            "category":"Professional",
            "subcategory":"Testing Lab",
            "type":"Services"
        }
    ],
    "sg:phone":"+1 361 578 7700",
    "sg:postcode":"77905",
    "sg:province":"TX",
    "sg:tags":[
        "calibration"
    ],
    "wof:name":"Victoria Mechanical Svc Inc",
    "wof:placetype":"venue"
},
  "geometry": {"coordinates":[-97.09418599999999,28.777455],"type":"Point"}
}