{
  "type": "Feature",
  "properties": {
    "iso:country":"US",
    "sg:address":"1914 Howard Ln",
    "sg:city":"Austin",
    "sg:classifiers":[
        {
            "category":"Shopping",
            "type":"Retail Goods"
        }
    ],
    "sg:phone":"+1 512 670 3647",
    "sg:postcode":"78728",
    "sg:province":"TX",
    "sg:tags":[
        "pet",
        "food",
        "merchandise",
        "supply"
    ],
    "wof:name":"Pauls Pet Food Delivery Ex",
    "wof:placetype":"venue"
},
  "geometry": {"coordinates":[-97.683899,30.430483],"type":"Point"}
}