{
  "type": "Feature",
  "properties": {
    "iso:country":"US",
    "sg:address":"15210 Hillside Park Way",
    "sg:city":"Cypress",
    "sg:classifiers":[
        {
            "category":"Manufacturing",
            "subcategory":"Tools & Machinery",
            "type":"Manufacturing & Wholesale Goods"
        }
    ],
    "sg:phone":"+1 281 373 5920",
    "sg:postcode":"77433",
    "sg:province":"TX",
    "sg:tags":[
        "control",
        "mfg"
    ],
    "wof:name":"Valve Actuator Service",
    "wof:placetype":"venue"
},
  "geometry": {"coordinates":[-95.73681500000001,29.995622],"type":"Point"}
}