{
  "type": "Feature",
  "properties": {
    "iso:country":"US",
    "sg:address":"2354 Joe Field Rd",
    "sg:city":"Dallas",
    "sg:classifiers":[
        {
            "category":"Building & Trades",
            "subcategory":"Equipment Rental",
            "type":"Services"
        }
    ],
    "sg:phone":"+1 214 357 2525",
    "sg:postcode":"75229",
    "sg:province":"TX",
    "sg:tags":[
        "yard"
    ],
    "wof:name":"Arrow Lift Rentals",
    "wof:placetype":"venue"
},
  "geometry": {"coordinates":[-96.898681,32.892855],"type":"Point"}
}