{
  "type": "Feature",
  "properties": {
    "iso:country":"US",
    "sg:address":"2113 Wells Branch Pkwy Ste 700",
    "sg:city":"Austin",
    "sg:classifiers":[
        {
            "category":"Food & Beverages",
            "subcategory":"Liquor & Beverages",
            "type":"Retail Goods"
        }
    ],
    "sg:phone":"+1 512 990 7401",
    "sg:postcode":"78728",
    "sg:province":"TX",
    "sg:tags":[
        "beer",
        "spirit",
        "wine"
    ],
    "wof:name":"Tejas Liquor",
    "wof:placetype":"venue"
},
  "geometry": {"coordinates":[-97.68400800000001,30.435961],"type":"Point"}
}