{
  "type": "Feature",
  "properties": {
    "iso:country":"US",
    "sg:address":"1910 Tucumcari Dr",
    "sg:city":"Houston",
    "sg:classifiers":[
        {
            "category":"Shopping",
            "subcategory":"Gifts & Souvenirs",
            "type":"Retail Goods"
        }
    ],
    "sg:phone":"+1 281 444 0896",
    "sg:postcode":"77090",
    "sg:province":"TX",
    "wof:name":"Baskets Beyond Belief",
    "wof:placetype":"venue"
},
  "geometry": {"coordinates":[-95.464625,30.018608],"type":"Point"}
}