{
  "type": "Feature",
  "properties": {
    "iso:country":"US",
    "sg:address":"715 Dallas Dr",
    "sg:city":"Denton",
    "sg:classifiers":[
        {
            "category":"Retail",
            "subcategory":"Auto Repair",
            "type":"Services"
        }
    ],
    "sg:phone":"+1 940 387 5066",
    "sg:postcode":"76205",
    "sg:province":"TX",
    "sg:tags":[
        "shop",
        "automotive",
        "wrecker",
        "towing"
    ],
    "wof:name":"Joe Akers Wrecker Service",
    "wof:placetype":"venue"
},
  "geometry": {"coordinates":[-97.125404,33.200362],"type":"Point"}
}