{
  "type": "Feature",
  "properties": {
    "iso:country":"US",
    "sg:address":"2509 Country Pl",
    "sg:city":"Carrollton",
    "sg:classifiers":[
        {
            "category":"Personal",
            "type":"Services"
        }
    ],
    "sg:phone":"+1 972 416 4226",
    "sg:postcode":"75006",
    "sg:province":"TX",
    "wof:name":"Cate N Cats Creative Concepts",
    "wof:placetype":"venue"
},
  "geometry": {"coordinates":[-96.85987299999999,32.960453],"type":"Point"}
}