{
  "type": "Feature",
  "properties": {
    "iso:country":"US",
    "sg:address":"1400 E New Boston Rd",
    "sg:city":"Nash",
    "sg:classifiers":[
        {
            "category":"Real Estate",
            "subcategory":"Real Estate Operator",
            "type":"Services"
        }
    ],
    "sg:phone":"+1 903 838 4157",
    "sg:postcode":"75569",
    "sg:province":"TX",
    "sg:tags":[
        "apartment"
    ],
    "wof:name":"Brad Durgett",
    "wof:placetype":"venue"
},
  "geometry": {"coordinates":[-94.110471,33.443138],"type":"Point"}
}