{
  "type": "Feature",
  "properties": {
    "iso:country":"US",
    "sg:address":"700 12th St",
    "sg:city":"Bay City",
    "sg:classifiers":[
        {
            "category":"Health Services",
            "subcategory":"Hospital",
            "type":"Services"
        }
    ],
    "sg:phone":"+1 979 245 7800",
    "sg:postcode":"77414",
    "sg:province":"TX",
    "sg:tags":[
        "skilled",
        "nursing",
        "facility"
    ],
    "wof:name":"Matagorda Healthcare Center",
    "wof:placetype":"venue"
},
  "geometry": {"coordinates":[-95.979788,28.987976],"type":"Point"}
}