{
  "type": "Feature",
  "properties": {
    "iso:country":"US",
    "sg:address":"120 West St",
    "sg:city":"Yoakum",
    "sg:classifiers":[
        {
            "category":"Manufacturing",
            "subcategory":"Glass & Minerals",
            "type":"Manufacturing & Wholesale Goods"
        }
    ],
    "sg:phone":"+1 361 293 3601",
    "sg:postcode":"77995",
    "sg:province":"TX",
    "sg:tags":[
        "cut",
        "mfg"
    ],
    "wof:name":"Southern Memorial Monuments",
    "wof:placetype":"venue"
},
  "geometry": {"coordinates":[-97.151734,29.285007],"type":"Point"}
}