{
  "type": "Feature",
  "properties": {
    "iso:country":"US",
    "sg:address":"7801 N Capital of Texas Hwy",
    "sg:city":"Austin",
    "sg:classifiers":[
        {
            "category":"Building & Trades",
            "subcategory":"Construction",
            "type":"Services"
        }
    ],
    "sg:phone":"+1 512 241 7100",
    "sg:postcode":"78731",
    "sg:province":"TX",
    "sg:tags":[
        "home",
        "builder"
    ],
    "wof:name":"Drees Co",
    "wof:placetype":"venue"
},
  "geometry": {"coordinates":[-97.781122,30.375665],"type":"Point"}
}