{
  "type": "Feature",
  "properties": {
    "iso:country":"US",
    "sg:address":"933 Mobley Rd",
    "sg:city":"Cedar Hill",
    "sg:classifiers":[
        {
            "category":"Professional",
            "subcategory":"Computer Services",
            "type":"Services"
        }
    ],
    "sg:phone":"+1 972 293 2572",
    "sg:postcode":"75104",
    "sg:province":"TX",
    "sg:tags":[
        "programing",
        "custom"
    ],
    "wof:name":"Shope Associates Inc",
    "wof:placetype":"venue"
},
  "geometry": {"coordinates":[-96.97933999999999,32.601445],"type":"Point"}
}