{
  "type": "Feature",
  "properties": {
    "iso:country":"US",
    "sg:address":"16015 Craighurst Dr",
    "sg:city":"Houston",
    "sg:classifiers":[
        {
            "category":"Professional",
            "subcategory":"Computer Services",
            "type":"Services"
        }
    ],
    "sg:phone":"+1 281 488 7016",
    "sg:postcode":"77059",
    "sg:province":"TX",
    "sg:tags":[
        "consulting"
    ],
    "wof:name":"Alma Information Systems",
    "wof:placetype":"venue"
},
  "geometry": {"coordinates":[-95.112841,29.587052],"type":"Point"}
}