{
  "type": "Feature",
  "properties": {
    "iso:country":"US",
    "sg:address":"3611 Maplewood Ave",
    "sg:city":"Wichita Falls",
    "sg:classifiers":[
        {
            "category":"Real Estate",
            "subcategory":"Real Estate Operator",
            "type":"Services"
        }
    ],
    "sg:phone":"+1 940 692 8021",
    "sg:postcode":"76308",
    "sg:province":"TX",
    "sg:tags":[
        "apartment"
    ],
    "wof:name":"Park Place Apartments",
    "wof:placetype":"venue"
},
  "geometry": {"coordinates":[-98.528524,33.870762],"type":"Point"}
}