{
  "type": "Feature",
  "properties": {
    "iso:country":"US",
    "sg:address":"4201 S Congress Avenue",
    "sg:city":"Austin",
    "sg:classifiers":[
        {
            "category":"Real Estate",
            "subcategory":"Real Estate Services",
            "type":"Services"
        }
    ],
    "sg:phone":"+1 512 444 6501",
    "sg:postcode":"78745",
    "sg:province":"TX",
    "sg:tags":[
        "management",
        "property"
    ],
    "wof:name":"Action Industries of Austin",
    "wof:placetype":"venue"
},
  "geometry": {"coordinates":[-97.764899,30.221335],"type":"Point"}
}