{
  "type": "Feature",
  "properties": {
    "iso:country":"US",
    "sg:address":"109 Magnolia St",
    "sg:city":"League City",
    "sg:classifiers":[
        {
            "category":"Restaurant",
            "type":"Food & Drink"
        }
    ],
    "sg:phone":"+1 281 332 3222",
    "sg:postcode":"77573",
    "sg:province":"TX",
    "sg:tags":[
        "eating"
    ],
    "wof:name":"Churchs Chicken",
    "wof:placetype":"venue"
},
  "geometry": {"coordinates":[-95.094824,29.507612],"type":"Point"}
}