{
  "type": "Feature",
  "properties": {
    "iso:country":"US",
    "sg:address":"204 Kintail Dr",
    "sg:city":"Spicewood",
    "sg:classifiers":[
        {
            "category":"Professional",
            "subcategory":"Management & Consulting",
            "type":"Services"
        }
    ],
    "sg:phone":"+1 512 264 0108",
    "sg:postcode":"78669",
    "sg:province":"TX",
    "sg:tags":[
        "consultant",
        "business"
    ],
    "wof:name":"Falcon Management Co",
    "wof:placetype":"venue"
},
  "geometry": {"coordinates":[-98.041456,30.405422],"type":"Point"}
}