{
  "type": "Feature",
  "properties": {
    "iso:country":"US",
    "sg:address":"512 Canyon Lake Dr",
    "sg:city":"Aledo",
    "sg:classifiers":[
        {
            "category":"Building & Trades",
            "subcategory":"Plumbing",
            "type":"Services"
        }
    ],
    "sg:phone":"+1 817 441 1298",
    "sg:postcode":"76008",
    "sg:province":"TX",
    "sg:tags":[
        "conditioning",
        "air",
        "system",
        "contractor"
    ],
    "wof:name":"Stallons A/C",
    "wof:placetype":"venue"
},
  "geometry": {"coordinates":[-97.666162,32.679791],"type":"Point"}
}