{
  "type": "Feature",
  "properties": {
    "iso:country":"US",
    "sg:address":"1803 Mesquite Ct",
    "sg:city":"Southlake",
    "sg:classifiers":[
        {
            "category":"Professional",
            "subcategory":"Business Services",
            "type":"Services"
        }
    ],
    "sg:phone":"+1 817 251 9388",
    "sg:postcode":"76092",
    "sg:province":"TX",
    "wof:name":"Kopp Enterprises Inc",
    "wof:placetype":"venue"
},
  "geometry": {"coordinates":[-97.18406899999999,32.945321],"type":"Point"}
}