{
  "type": "Feature",
  "properties": {
    "iso:country":"US",
    "sg:address":"3010 TX-30 W",
    "sg:city":"Huntsville",
    "sg:classifiers":[
        {
            "category":"Restaurant",
            "type":"Food & Drink"
        }
    ],
    "sg:menulink":"http://www.allmenus.com/tx/huntsville/93974-pizza-hut/menu/",
    "sg:phone":"+1 936 294 9191",
    "sg:postcode":"77320",
    "sg:province":"TX",
    "sg:tags":[
        "american",
        "pizza"
    ],
    "wof:name":"Pizza Hut",
    "wof:placetype":"venue"
},
  "geometry": {"coordinates":[-95.573082,30.718392],"type":"Point"}
}