{
  "type": "Feature",
  "properties": {
    "iso:country":"US",
    "sg:address":"2821 New Boston Rd",
    "sg:city":"Texarkana",
    "sg:classifiers":[
        {
            "category":"Wholesale",
            "subcategory":"Stationery",
            "type":"Manufacturing & Wholesale Goods"
        }
    ],
    "sg:phone":"+1 903 831 4700",
    "sg:postcode":"75501",
    "sg:province":"TX",
    "sg:tags":[
        "school",
        "supply"
    ],
    "wof:name":"Sav-Ondiscount Office Supls",
    "wof:placetype":"venue"
},
  "geometry": {"coordinates":[-94.080214,33.436074],"type":"Point"}
}