{
  "type": "Feature",
  "properties": {
    "iso:country":"US",
    "sg:address":"2611 Eisenhauer Rd",
    "sg:city":"San Antonio",
    "sg:classifiers":[
        {
            "category":"Shopping",
            "subcategory":"Clothing, Apparel, & Fashions",
            "type":"Retail Goods"
        }
    ],
    "sg:phone":"+1 210 822 7176",
    "sg:postcode":"78209",
    "sg:province":"TX",
    "sg:tags":[
        "designer"
    ],
    "wof:name":"Focus On Fashion",
    "wof:placetype":"venue"
},
  "geometry": {"coordinates":[-98.45170400000001,29.495817],"type":"Point"}
}