{
  "type": "Feature",
  "properties": {
    "iso:country":"US",
    "sg:address":"5301 Belt Line Rd # 106",
    "sg:city":"Dallas",
    "sg:classifiers":[
        {
            "category":"Shopping",
            "subcategory":"Pets & Pet Supplies",
            "type":"Retail Goods"
        }
    ],
    "sg:phone":"+1 972 788 0460",
    "sg:postcode":"75254",
    "sg:province":"TX",
    "sg:tags":[
        "store"
    ],
    "sg:website":"www.petco.com",
    "wof:name":"Petco",
    "wof:placetype":"venue"
},
  "geometry": {"coordinates":[-96.816806,32.954139],"type":"Point"}
}