{
  "type": "Feature",
  "properties": {
    "iso:country":"US",
    "sg:address":"3517 Longmorn Ln",
    "sg:city":"Longview",
    "sg:classifiers":[
        {
            "category":"Farming",
            "subcategory":"Livestock Farm",
            "type":"Manufacturing & Wholesale Goods"
        }
    ],
    "sg:phone":"+1 903 291 0063",
    "sg:postcode":"75604",
    "sg:province":"TX",
    "sg:tags":[
        "ranch"
    ],
    "wof:name":"Mark Lawyer",
    "wof:placetype":"venue"
},
  "geometry": {"coordinates":[-94.800021,32.547182],"type":"Point"}
}