{
  "type": "Feature",
  "properties": {
    "iso:country":"US",
    "sg:address":"2024 Centimeter Cir",
    "sg:city":"Austin",
    "sg:classifiers":[
        {
            "category":"Wholesale",
            "subcategory":"Meat",
            "type":"Manufacturing & Wholesale Goods"
        }
    ],
    "sg:phone":"+1 512 973 8550",
    "sg:postcode":"78758",
    "sg:province":"TX",
    "wof:name":"Martin Preferred Foods",
    "wof:placetype":"venue"
},
  "geometry": {"coordinates":[-97.71448599999999,30.381619],"type":"Point"}
}