{
  "type": "Feature",
  "properties": {
    "iso:country":"US",
    "sg:address":"801 4th St",
    "sg:city":"Rosenberg",
    "sg:classifiers":[
        {
            "category":"Restaurant",
            "type":"Food & Drink"
        }
    ],
    "sg:phone":"+1 281 342 6550",
    "sg:postcode":"77471",
    "sg:province":"TX",
    "wof:name":"Leon Taqueria",
    "wof:placetype":"venue"
},
  "geometry": {"coordinates":[-95.80568700000001,29.56041],"type":"Point"}
}