{
  "type": "Feature",
  "properties": {
    "iso:country":"US",
    "sg:address":"14719 US Hwy 290",
    "sg:city":"Manor",
    "sg:classifiers":[
        {
            "category":"Wholesale",
            "subcategory":"Machinery & Supplies",
            "type":"Manufacturing & Wholesale Goods"
        },
        {
            "category":"Manufacturing",
            "subcategory":"Tools & Machinery",
            "type":"Manufacturing & Wholesale Goods"
        }
    ],
    "sg:phone":"+1 512 272 5537",
    "sg:postcode":"78653",
    "sg:province":"TX",
    "sg:tags":[
        "equipment",
        "material",
        "handling",
        "mfg"
    ],
    "wof:name":"Air Bearing Central Inc",
    "wof:placetype":"venue"
},
  "geometry": {"coordinates":[-97.478623,30.351008],"type":"Point"}
}