{
  "type": "Feature",
  "properties": {
    "iso:country":"US",
    "sg:address":"707 S Cedar St",
    "sg:city":"Pecos",
    "sg:classifiers":[
        {
            "category":"Restaurant",
            "type":"Food & Drink"
        }
    ],
    "sg:phone":"+1 432 445 9889",
    "sg:postcode":"79772",
    "sg:province":"TX",
    "sg:tags":[
        "asian",
        "chinese",
        "pan"
    ],
    "wof:name":"The China Bowl",
    "wof:placetype":"venue"
},
  "geometry": {"coordinates":[-103.49251099999999,31.42193],"type":"Point"}
}