{
  "type": "Feature",
  "properties": {
    "iso:country":"US",
    "sg:address":"7213 McNeil Drive",
    "sg:city":"Austin",
    "sg:classifiers":[
        {
            "category":"Personal",
            "subcategory":"Day Spa",
            "type":"Services"
        },
        {
            "category":"Home & Garden",
            "subcategory":"Building Materials",
            "type":"Retail Goods"
        },
        {
            "category":"Military Area",
            "subcategory":"Armory",
            "type":"Public Place"
        },
        {
            "category":"Manufacturing",
            "subcategory":"Metals",
            "type":"Manufacturing & Wholesale Goods"
        },
        {
            "category":"Manufacturing",
            "subcategory":"Building Materials",
            "type":"Manufacturing & Wholesale Goods"
        },
        {
            "category":"Building & Trades",
            "subcategory":"Construction",
            "type":"Services"
        }
    ],
    "sg:phone":"+1 512 258 5000",
    "sg:postcode":"78729",
    "sg:province":"TX",
    "sg:tags":[
        "repair",
        "fence",
        "deck",
        "ornamental",
        "builder",
        "cover",
        "contractor",
        "hot",
        "vinyl",
        "iron",
        "gate",
        "tub",
        "accessory",
        "work-supplies",
        "enclosure",
        "patio",
        "fence-sales"
    ],
    "sg:website":"www.austexfenceanddeck.com",
    "wof:name":"Austex Fence & Deck",
    "wof:placetype":"venue"
},
  "geometry": {"coordinates":[-97.765664,30.435525],"type":"Point"}
}