{
  "type": "Feature",
  "properties": {
    "iso:country":"US",
    "sg:address":"2901 S Capital of Texas Hwy",
    "sg:city":"Austin",
    "sg:classifiers":[
        {
            "category":"Professional",
            "type":"Services"
        }
    ],
    "sg:phone":"+1 512 327 7515",
    "sg:postcode":"78746",
    "sg:province":"TX",
    "sg:tags":[
        "establishment"
    ],
    "wof:name":"Topkapi",
    "wof:placetype":"venue"
},
  "geometry": {"coordinates":[-97.80790399999999,30.252976],"type":"Point"}
}