{
  "type": "Feature",
  "properties": {
    "iso:country":"US",
    "sg:address":"22008 Woodway Dr",
    "sg:city":"Waco",
    "sg:classifiers":[
        {
            "category":"Building & Trades",
            "subcategory":"Construction",
            "type":"Services"
        }
    ],
    "sg:phone":"+1 254 772 2737",
    "sg:postcode":"76712",
    "sg:province":"TX",
    "sg:tags":[
        "general",
        "contractor"
    ],
    "sg:website":"www.pci-gc.com",
    "wof:name":"Pearson Construction Co",
    "wof:placetype":"venue"
},
  "geometry": {"coordinates":[-97.267769,31.485947],"type":"Point"}
}