{
  "type": "Feature",
  "properties": {
    "iso:country":"US",
    "sg:address":"4264 Westlake Dr",
    "sg:city":"Austin",
    "sg:classifiers":[
        {
            "category":"Real Estate",
            "subcategory":"Real Estate Agent",
            "type":"Services"
        }
    ],
    "sg:phone":"+1 512 327 0771",
    "sg:postcode":"78746",
    "sg:province":"TX",
    "wof:name":"Bee Cave Oaks Development Inc",
    "wof:placetype":"venue"
},
  "geometry": {"coordinates":[-97.80521,30.334761],"type":"Point"}
}