{
  "type": "Feature",
  "properties": {
    "iso:country":"US",
    "sg:address":"1100 Eidson Rd",
    "sg:city":"Eagle Pass",
    "sg:classifiers":[
        {
            "category":"Government",
            "subcategory":"Office",
            "type":"Public Place"
        }
    ],
    "sg:phone":"+1 830 773 9408",
    "sg:postcode":"78852",
    "sg:province":"TX",
    "sg:tags":[
        "village"
    ],
    "wof:name":"Eagle Pass City Landfill",
    "wof:placetype":"venue"
},
  "geometry": {"coordinates":[-100.48727,28.692724],"type":"Point"}
}