{
  "type": "Feature",
  "properties": {
    "iso:country":"US",
    "sg:address":"1605 Ivory St",
    "sg:city":"Edinburg",
    "sg:classifiers":[
        {
            "category":"Place Of Worship",
            "type":"Public Place"
        }
    ],
    "sg:phone":"+1 956 205 6179",
    "sg:postcode":"78541",
    "sg:province":"TX",
    "sg:tags":[
        "church"
    ],
    "wof:name":"Juan De Dios Garza",
    "wof:placetype":"venue"
},
  "geometry": {"coordinates":[-98.21447000000001,26.342169],"type":"Point"}
}