{
  "type": "Feature",
  "properties": {
    "iso:country":"US",
    "sg:address":"8801 Ravenswood Rd",
    "sg:city":"Granbury",
    "sg:classifiers":[
        {
            "category":"Professional",
            "subcategory":"Business Services",
            "type":"Services"
        }
    ],
    "sg:phone":"+1 817 279 8064",
    "sg:postcode":"76049",
    "sg:province":"TX",
    "wof:name":"Dos Cuellar Enterprises Inc",
    "wof:placetype":"venue"
},
  "geometry": {"coordinates":[-97.618452,32.351569],"type":"Point"}
}