{
  "type": "Feature",
  "properties": {
    "iso:country":"US",
    "sg:address":"1223 Bonnie Brae St",
    "sg:city":"Houston",
    "sg:classifiers":[
        {
            "category":"Mining & Drilling",
            "type":"Manufacturing & Wholesale Goods"
        }
    ],
    "sg:phone":"+1 713 785 3794",
    "sg:postcode":"77006",
    "sg:province":"TX",
    "sg:tags":[
        "crude",
        "production",
        "gas"
    ],
    "wof:name":"O W S Energy Inc",
    "wof:placetype":"venue"
},
  "geometry": {"coordinates":[-95.39456300000001,29.733503],"type":"Point"}
}