{
  "type": "Feature",
  "properties": {
    "iso:country":"US",
    "sg:address":"3 Spring Creek Rd",
    "sg:city":"Victoria",
    "sg:classifiers":[
        {
            "category":"Building & Trades",
            "subcategory":"Construction",
            "type":"Services"
        }
    ],
    "sg:phone":"+1 361 573 1879",
    "sg:postcode":"77904",
    "sg:province":"TX",
    "sg:tags":[
        "house"
    ],
    "wof:name":"Scheumack Homes",
    "wof:placetype":"venue"
},
  "geometry": {"coordinates":[-97.004971,28.850019],"type":"Point"}
}