{
  "type": "Feature",
  "properties": {
    "iso:country":"US",
    "sg:address":"2315 Rock Creek Rd",
    "sg:city":"Crowley",
    "sg:classifiers":[
        {
            "category":"Freight",
            "type":"Transportation"
        }
    ],
    "sg:phone":"+1 817 297 6547",
    "sg:postcode":"76028",
    "sg:province":"TX",
    "sg:tags":[
        "local",
        "except",
        "trucking"
    ],
    "wof:name":"Dlf Trucking",
    "wof:placetype":"venue"
},
  "geometry": {"coordinates":[-97.407568,32.539749],"type":"Point"}
}