{
  "type": "Feature",
  "properties": {
    "iso:country":"US",
    "sg:address":"13158 Humphrey Dr",
    "sg:city":"Austin",
    "sg:classifiers":[
        {
            "category":"Real Estate",
            "subcategory":"Architect",
            "type":"Services"
        }
    ],
    "sg:phone":"+1 512 250 8890",
    "sg:postcode":"78729",
    "sg:province":"TX",
    "sg:tags":[
        "provides",
        "architectural"
    ],
    "wof:name":"Haakman Consulting",
    "wof:placetype":"venue"
},
  "geometry": {"coordinates":[-97.761195,30.44969],"type":"Point"}
}