{
  "type": "Feature",
  "properties": {
    "iso:country":"US",
    "sg:address":"4001 Sam Houston Pkwy",
    "sg:city":"Houston",
    "sg:classifiers":[
        {
            "category":"Health Services",
            "subcategory":"Medical Lab",
            "type":"Services"
        }
    ],
    "sg:phone":"+1 713 996 0900",
    "sg:postcode":"77015",
    "sg:province":"TX",
    "sg:tags":[
        "laboratory"
    ],
    "wof:name":"Integrated Diagnostic Ctr",
    "wof:placetype":"venue"
},
  "geometry": {"coordinates":[-95.14726,29.76338],"type":"Point"}
}