{
  "type": "Feature",
  "properties": {
    "iso:country":"US",
    "sg:address":"747 W Wheatland Rd",
    "sg:city":"Duncanville",
    "sg:classifiers":[
        {
            "category":"Retail",
            "subcategory":"Laundry & Dry Cleaning",
            "type":"Services"
        }
    ],
    "sg:phone":"+1 972 296 1515",
    "sg:postcode":"75116",
    "sg:province":"TX",
    "sg:tags":[
        "drycleaning",
        "plant"
    ],
    "wof:name":"Ken Staggs Cleaners & Laundry",
    "wof:placetype":"venue"
},
  "geometry": {"coordinates":[-96.92337000000001,32.647553],"type":"Point"}
}