{
  "type": "Feature",
  "properties": {
    "iso:country":"US",
    "sg:address":"2200 Main St",
    "sg:city":"Junction",
    "sg:classifiers":[
        {
            "category":"Real Estate",
            "subcategory":"Real Estate Services",
            "type":"Services"
        },
        {
            "category":"Real Estate",
            "subcategory":"Real Estate Agent",
            "type":"Services"
        }
    ],
    "sg:phone":"+1 325 446 8642",
    "sg:postcode":"76849",
    "sg:province":"TX",
    "sg:tags":[
        "buyer",
        "broker"
    ],
    "wof:name":"Riverside Realty",
    "wof:placetype":"venue"
},
  "geometry": {"coordinates":[-99.778244,30.494886],"type":"Point"}
}