{
  "type": "Feature",
  "properties": {
    "iso:country":"US",
    "sg:address":"6435 McCart Ave",
    "sg:city":"Fort Worth",
    "sg:classifiers":[
        {
            "category":"Personal",
            "subcategory":"Beauty Salon",
            "type":"Services"
        }
    ],
    "sg:phone":"+1 817 370 8770",
    "sg:postcode":"76133",
    "sg:province":"TX",
    "wof:name":"Suave Salon",
    "wof:placetype":"venue"
},
  "geometry": {"coordinates":[-97.366225,32.65102],"type":"Point"}
}