{
  "type": "Feature",
  "properties": {
    "iso:country":"US",
    "sg:address":"3845 Main St",
    "sg:city":"Rowlett",
    "sg:classifiers":[
        {
            "category":"Building & Trades",
            "subcategory":"Plumbing",
            "type":"Services"
        }
    ],
    "sg:phone":"+1 972 412 0947",
    "sg:postcode":"75088",
    "sg:province":"TX",
    "sg:tags":[
        "air",
        "heating",
        "conditioning",
        "contractor"
    ],
    "wof:name":"Alps Air Conditioning & Htg Co",
    "wof:placetype":"venue"
},
  "geometry": {"coordinates":[-96.56789000000001,32.902967],"type":"Point"}
}