{
  "type": "Feature",
  "properties": {
    "iso:country":"US",
    "sg:address":"1605 Grandview W",
    "sg:city":"Wichita Falls",
    "sg:classifiers":[
        {
            "category":"Personal",
            "subcategory":"Barber",
            "type":"Services"
        }
    ],
    "sg:phone":"+1 940 855 2359",
    "sg:postcode":"76306",
    "sg:province":"TX",
    "sg:tags":[
        "shop",
        "photo",
        "studio",
        "portrait"
    ],
    "wof:name":"In His Image",
    "wof:placetype":"venue"
},
  "geometry": {"coordinates":[-98.552019,33.944215],"type":"Point"}
}