{
  "type": "Feature",
  "properties": {
    "iso:country":"US",
    "sg:address":"9315 Stella Link Rd",
    "sg:city":"Houston",
    "sg:classifiers":[
        {
            "category":"Professional",
            "subcategory":"Employment Agencies",
            "type":"Services"
        }
    ],
    "sg:phone":"+1 713 218 6555",
    "sg:postcode":"77025",
    "sg:province":"TX",
    "wof:name":"Houston Works",
    "wof:placetype":"venue"
},
  "geometry": {"coordinates":[-95.439864,29.681579],"type":"Point"}
}