{
  "type": "Feature",
  "properties": {
    "iso:country":"US",
    "sg:address":"808 SW Green Oaks Blvd",
    "sg:city":"Arlington",
    "sg:classifiers":[
        {
            "category":"Shopping",
            "subcategory":"Jewelry",
            "type":"Retail Goods"
        }
    ],
    "sg:phone":"+1 817 845 9335",
    "sg:postcode":"76017",
    "sg:province":"TX",
    "wof:name":"M&N Investments",
    "wof:placetype":"venue"
},
  "geometry": {"coordinates":[-97.118787,32.659401],"type":"Point"}
}