{
  "type": "Feature",
  "properties": {
    "iso:country":"US",
    "sg:address":"4834 Yorktown Blvd",
    "sg:city":"Corpus Christi",
    "sg:classifiers":[
        {
            "category":"Health Services",
            "subcategory":"Nursing And Care Facility",
            "type":"Services"
        },
        {
            "category":"Social Services",
            "subcategory":"Adult Care",
            "type":"Services"
        }
    ],
    "sg:phone":"+1 361 991 3252",
    "sg:postcode":"78413",
    "sg:province":"TX",
    "sg:tags":[
        "home",
        "intermediate",
        "residential"
    ],
    "wof:name":"Villa Of Corpus Christi South",
    "wof:placetype":"venue"
},
  "geometry": {"coordinates":[-97.40802499999999,27.672472],"type":"Point"}
}