{
  "type": "Feature",
  "properties": {
    "iso:country":"US",
    "sg:address":"12045 15th St",
    "sg:city":"Santa Fe",
    "sg:classifiers":[
        {
            "category":"Organizations",
            "subcategory":"Non-profit Organization",
            "type":"Services"
        }
    ],
    "sg:phone":"+1 409 925 2848",
    "sg:postcode":"77510",
    "sg:province":"TX",
    "sg:tags":[
        "information",
        "alcoholism",
        "treatment"
    ],
    "wof:name":"Alcoholics Anonymous",
    "wof:placetype":"venue"
},
  "geometry": {"coordinates":[-95.082947,29.371667],"type":"Point"}
}