{
  "type": "Feature",
  "properties": {
    "iso:country":"US",
    "sg:address":"2400 Ave P",
    "sg:city":"Hondo",
    "sg:classifiers":[
        {
            "category":"Organizations",
            "subcategory":"Religious Organization",
            "type":"Services"
        }
    ],
    "sg:phone":"+1 830 741 2272",
    "sg:postcode":"78861",
    "sg:province":"TX",
    "sg:tags":[
        "church"
    ],
    "wof:name":"First Baptist Church Of Hondo",
    "wof:placetype":"venue"
},
  "geometry": {"coordinates":[-99.144761,29.343346],"type":"Point"}
}