{
  "type": "Feature",
  "properties": {
    "iso:country":"US",
    "sg:address":"206 S Central Ave",
    "sg:city":"Petrolia",
    "sg:classifiers":[
        {
            "category":"Wholesale",
            "subcategory":"Electrical",
            "type":"Manufacturing & Wholesale Goods"
        }
    ],
    "sg:phone":"+1 940 524 3363",
    "sg:postcode":"76377",
    "sg:province":"TX",
    "sg:tags":[
        "electric",
        "motor"
    ],
    "wof:name":"Wemsco Electric Motor Svc",
    "wof:placetype":"venue"
},
  "geometry": {"coordinates":[-98.23160300000001,34.012308],"type":"Point"}
}