{
  "type": "Feature",
  "properties": {
    "iso:country":"US",
    "sg:address":"1710 Country Club Dr",
    "sg:city":"Mansfield",
    "sg:classifiers":[
        {
            "category":"Professional",
            "subcategory":"Lawyer & Legal Services",
            "type":"Services"
        }
    ],
    "sg:phone":"+1 817 348 6723",
    "sg:postcode":"76063",
    "sg:province":"TX",
    "sg:tags":[
        "attorney"
    ],
    "wof:name":"Ed Winfrey Attorney At Law",
    "wof:placetype":"venue"
},
  "geometry": {"coordinates":[-97.109219,32.593467],"type":"Point"}
}