{
  "type": "Feature",
  "properties": {
    "iso:country":"US",
    "sg:address":"17641 Stuebner Airline Rd",
    "sg:city":"Spring",
    "sg:classifiers":[
        {
            "category":"Sports & Exercise",
            "subcategory":"Gym",
            "type":"Entertainment"
        }
    ],
    "sg:phone":"+1 832 717 4000",
    "sg:postcode":"77379",
    "sg:province":"TX",
    "sg:tags":[
        "club",
        "health",
        "studio",
        "gymnasium"
    ],
    "wof:name":"Amazon Fitness & Wellness Ctr",
    "wof:placetype":"venue"
},
  "geometry": {"coordinates":[-95.53213599999999,30.029618],"type":"Point"}
}