{
  "type": "Feature",
  "properties": {
    "iso:country":"US",
    "sg:address":"7085 Southwest Fwy",
    "sg:city":"Houston",
    "sg:classifiers":[
        {
            "category":"Utilities",
            "subcategory":"Mobile Phone",
            "type":"Services"
        }
    ],
    "sg:phone":"+1 713 272 6493",
    "sg:postcode":"77074",
    "sg:province":"TX",
    "sg:tags":[
        "telephone",
        "cellular"
    ],
    "sg:website":"http://www.cellularsales.com",
    "wof:name":"Cellular Sales",
    "wof:placetype":"venue"
},
  "geometry": {"coordinates":[-95.509675,29.706959],"type":"Point"}
}