{
  "type": "Feature",
  "properties": {
    "iso:country":"US",
    "sg:address":"3729 Marks Pl",
    "sg:city":"Fort Worth",
    "sg:classifiers":[
        {
            "category":"Professional",
            "subcategory":"Computer Services",
            "type":"Services"
        }
    ],
    "sg:phone":"+1 817 737 8612",
    "sg:postcode":"76116",
    "sg:province":"TX",
    "sg:tags":[
        "datum"
    ],
    "wof:name":"Paperwork",
    "wof:placetype":"venue"
},
  "geometry": {"coordinates":[-97.439404,32.715083],"type":"Point"}
}