{
  "type": "Feature",
  "properties": {
    "iso:country":"US",
    "sg:address":"2331 S Brahma Blvd",
    "sg:city":"Kingsville",
    "sg:classifiers":[
        {
            "category":"Social Services",
            "type":"Services"
        }
    ],
    "sg:phone":"+1 361 592 8330",
    "sg:postcode":"78363",
    "sg:province":"TX",
    "wof:name":"Eagles Flight Eductl Program",
    "wof:placetype":"venue"
},
  "geometry": {"coordinates":[-97.85594399999999,27.494839],"type":"Point"}
}