{
  "type": "Feature",
  "properties": {
    "iso:country":"US",
    "sg:address":"1329 Bluebird Ln",
    "sg:city":"Midlothian",
    "sg:classifiers":[
        {
            "category":"Shopping",
            "subcategory":"Gifts & Souvenirs",
            "type":"Retail Goods"
        }
    ],
    "sg:phone":"+1 972 775 8033",
    "sg:postcode":"76065",
    "sg:province":"TX",
    "wof:name":"A Little Bit of Heaven",
    "wof:placetype":"venue"
},
  "geometry": {"coordinates":[-96.94966100000001,32.497442],"type":"Point"}
}