{
  "type": "Feature",
  "properties": {
    "iso:country":"US",
    "sg:address":"15905 Wood Dr",
    "sg:city":"Channelview",
    "sg:classifiers":[
        {
            "category":"Freight",
            "type":"Transportation"
        }
    ],
    "sg:phone":"+1 281 864 9267",
    "sg:postcode":"77530",
    "sg:province":"TX",
    "sg:tags":[
        "dry",
        "bulk",
        "trucking"
    ],
    "sg:website":"www.ergon.com",
    "wof:name":"Ergon Trucking Inc",
    "wof:placetype":"venue"
},
  "geometry": {"coordinates":[-95.12426000000001,29.806844],"type":"Point"}
}