{
  "type": "Feature",
  "properties": {
    "iso:country":"US",
    "sg:address":"1501 W Pioneer Dr",
    "sg:city":"Irving",
    "sg:classifiers":[
        {
            "category":"Retail",
            "subcategory":"Auto Repair",
            "type":"Services"
        }
    ],
    "sg:phone":"+1 972 259 3004",
    "sg:postcode":"75061",
    "sg:province":"TX",
    "wof:name":"Pena Auto Repair",
    "wof:placetype":"venue"
},
  "geometry": {"coordinates":[-96.964996,32.822399],"type":"Point"}
}