{
  "type": "Feature",
  "properties": {
    "iso:country":"US",
    "sg:address":"5515 Singleton Blvd",
    "sg:city":"Dallas",
    "sg:classifiers":[
        {
            "category":"Autos & Motor Vehicles",
            "subcategory":"Automobile Sales",
            "type":"Retail Goods"
        }
    ],
    "sg:phone":"+1 214 630 2127",
    "sg:postcode":"75212",
    "sg:province":"TX",
    "sg:tags":[
        "car",
        "used"
    ],
    "wof:name":"Gary's Used Cars Inc",
    "wof:placetype":"venue"
},
  "geometry": {"coordinates":[-96.91120100000001,32.7785],"type":"Point"}
}