{
  "type": "Feature",
  "properties": {
    "iso:country":"US",
    "sg:address":"4921 Tulip Ln",
    "sg:city":"Fort Worth",
    "sg:classifiers":[
        {
            "category":"Communications",
            "subcategory":"Film & Video Production",
            "type":"Services"
        }
    ],
    "sg:phone":"+1 817 281 2567",
    "sg:postcode":"76137",
    "sg:province":"TX",
    "sg:tags":[
        "motion"
    ],
    "wof:name":"Mountain Peak Productions",
    "wof:placetype":"venue"
},
  "geometry": {"coordinates":[-97.27689700000001,32.862469],"type":"Point"}
}