{
  "type": "Feature",
  "properties": {
    "iso:country":"US",
    "sg:address":"501 Elm St",
    "sg:city":"Graham",
    "sg:classifiers":[
        {
            "category":"Shopping",
            "subcategory":"Jewelry",
            "type":"Retail Goods"
        }
    ],
    "sg:phone":"+1 940 549 3335",
    "sg:postcode":"76450",
    "sg:province":"TX",
    "sg:tags":[
        "jeweler"
    ],
    "wof:name":"Everette's Jewelers",
    "wof:placetype":"venue"
},
  "geometry": {"coordinates":[-98.58954900000001,33.10705],"type":"Point"}
}