{
  "type": "Feature",
  "properties": {
    "iso:country":"US",
    "sg:address":"2419 Amber Springs Dr",
    "sg:city":"Katy",
    "sg:classifiers":[
        {
            "category":"Professional",
            "subcategory":"Computer Services",
            "type":"Services"
        }
    ],
    "sg:phone":"+1 281 492 8490",
    "sg:postcode":"77450",
    "sg:province":"TX",
    "sg:tags":[
        "datum"
    ],
    "wof:name":"Lyntonweb",
    "wof:placetype":"venue"
},
  "geometry": {"coordinates":[-95.730085,29.747578],"type":"Point"}
}