{
  "type": "Feature",
  "properties": {
    "iso:country":"US",
    "sg:address":"76 Co Rd 430",
    "sg:city":"Dayton",
    "sg:classifiers":[
        {
            "category":"Restaurant",
            "type":"Food & Drink"
        }
    ],
    "sg:phone":"+1 936 257 9391",
    "sg:postcode":"77535",
    "sg:province":"TX",
    "sg:tags":[
        "caterer"
    ],
    "wof:name":"Bryan's Crawfish",
    "wof:placetype":"venue"
},
  "geometry": {"coordinates":[-94.83636799999999,29.931586],"type":"Point"}
}