{
  "type": "Feature",
  "properties": {
    "iso:country":"US",
    "sg:address":"1430 S Elm St",
    "sg:city":"Carrollton",
    "sg:classifiers":[
        {
            "category":"Shopping",
            "type":"Retail Goods"
        }
    ],
    "sg:phone":"+1 972 245 1836",
    "sg:postcode":"75006",
    "sg:province":"TX",
    "sg:tags":[
        "automobile",
        "used",
        "merchandise"
    ],
    "wof:name":"B & T Motors",
    "wof:placetype":"venue"
},
  "geometry": {"coordinates":[-96.906418,32.948825],"type":"Point"}
}