{
  "type": "Feature",
  "properties": {
    "iso:country":"US",
    "sg:address":"9806 Wallisville Rd",
    "sg:city":"Houston",
    "sg:classifiers":[
        {
            "category":"Freight",
            "type":"Transportation"
        }
    ],
    "sg:phone":"+1 713 674 0705",
    "sg:postcode":"77013",
    "sg:province":"TX",
    "wof:name":"Carolina National Trnsprtn",
    "wof:placetype":"venue"
},
  "geometry": {"coordinates":[-95.25876599999999,29.792551],"type":"Point"}
}