{
  "type": "Feature",
  "properties": {
    "iso:country":"US",
    "sg:address":"5013 Katy Fwy",
    "sg:city":"Houston",
    "sg:classifiers":[
        {
            "category":"Health Services",
            "subcategory":"Doctor",
            "type":"Services"
        }
    ],
    "sg:phone":"+1 713 864 8313",
    "sg:postcode":"77007",
    "sg:province":"TX",
    "sg:tags":[
        "surgeon",
        "oral"
    ],
    "wof:name":"Wong Michael A DDS",
    "wof:placetype":"venue"
},
  "geometry": {"coordinates":[-95.413399,29.776899],"type":"Point"}
}