{
  "type": "Feature",
  "properties": {
    "iso:country":"US",
    "sg:address":"1000 Meyer St",
    "sg:city":"Sealy",
    "sg:classifiers":[
        {
            "category":"Insurance",
            "subcategory":"Insurance Agent",
            "type":"Services"
        }
    ],
    "sg:phone":"+1 979 885 7497",
    "sg:postcode":"77474",
    "sg:province":"TX",
    "wof:name":"State Farm Insurance",
    "wof:placetype":"venue"
},
  "geometry": {"coordinates":[-96.1561,29.775647],"type":"Point"}
}