{
  "type": "Feature",
  "properties": {
    "iso:country":"US",
    "sg:address":"318 W Clark St",
    "sg:city":"Pharr",
    "sg:classifiers":[
        {
            "category":"Manufacturing",
            "subcategory":"Apparel",
            "type":"Manufacturing & Wholesale Goods"
        }
    ],
    "sg:phone":"+1 956 782 0805",
    "sg:postcode":"78577",
    "sg:province":"TX",
    "wof:name":"Perfect Stitch",
    "wof:placetype":"venue"
},
  "geometry": {"coordinates":[-98.187713,26.197071],"type":"Point"}
}