{
  "type": "Feature",
  "properties": {
    "iso:country":"US",
    "sg:address":"3611 Springbrook St",
    "sg:city":"Dallas",
    "sg:classifiers":[
        {
            "category":"Mining & Drilling",
            "type":"Manufacturing & Wholesale Goods"
        }
    ],
    "sg:phone":"+1 214 827 2120",
    "sg:postcode":"75205",
    "sg:province":"TX",
    "sg:tags":[
        "crude",
        "production",
        "gas"
    ],
    "wof:name":"Kasle Energy Inc",
    "wof:placetype":"venue"
},
  "geometry": {"coordinates":[-96.79727099999999,32.819614],"type":"Point"}
}