{
  "type": "Feature",
  "properties": {
    "iso:country":"US",
    "sg:address":"4902 Bonny Dr",
    "sg:city":"Wichita Falls",
    "sg:classifiers":[
        {
            "category":"Retail",
            "subcategory":"Repair Shop",
            "type":"Services"
        }
    ],
    "sg:phone":"+1 940 322 6579",
    "sg:postcode":"76302",
    "sg:province":"TX",
    "wof:name":"Cleaning By Sheri",
    "wof:placetype":"venue"
},
  "geometry": {"coordinates":[-98.483104,33.854765],"type":"Point"}
}