{
  "type": "Feature",
  "properties": {
    "iso:country":"US",
    "sg:address":"224 Sagecrest Dr",
    "sg:city":"San Antonio",
    "sg:classifiers":[
        {
            "category":"Professional",
            "subcategory":"Business Services",
            "type":"Services"
        }
    ],
    "sg:phone":"+1 210 496 1205",
    "sg:postcode":"78232",
    "sg:province":"TX",
    "wof:name":"Shop With Ease",
    "wof:placetype":"venue"
},
  "geometry": {"coordinates":[-98.478954,29.605102],"type":"Point"}
}