{
  "type": "Feature",
  "properties": {
    "iso:country":"US",
    "sg:address":"3102 Oak Lawn Ave Ste 700",
    "sg:city":"Dallas",
    "sg:classifiers":[
        {
            "category":"Building & Trades",
            "subcategory":"Construction",
            "type":"Services"
        }
    ],
    "sg:phone":"+1 214 560 2288",
    "sg:postcode":"75219",
    "sg:province":"TX",
    "sg:tags":[
        "interior",
        "design"
    ],
    "wof:name":"Morgan Adrienne Interior Design",
    "wof:placetype":"venue"
},
  "geometry": {"coordinates":[-96.80847199999999,32.809035],"type":"Point"}
}