{
  "type": "Feature",
  "properties": {
    "iso:country":"US",
    "sg:address":"1441 N Main St",
    "sg:city":"Fort Worth",
    "sg:classifiers":[
        {
            "category":"Autos & Motor Vehicles",
            "subcategory":"Auto Supplies",
            "type":"Retail Goods"
        }
    ],
    "sg:phone":"+1 817 626 2051",
    "sg:postcode":"76106",
    "sg:province":"TX",
    "sg:tags":[
        "tire"
    ],
    "wof:name":"Garcia Tire Co",
    "wof:placetype":"venue"
},
  "geometry": {"coordinates":[-97.347562,32.778894],"type":"Point"}
}