{
  "type": "Feature",
  "properties": {
    "iso:country":"US",
    "sg:address":"2835 W Brooklyn Ave",
    "sg:city":"Dallas",
    "sg:classifiers":[
        {
            "category":"Building & Trades",
            "subcategory":"Construction",
            "type":"Services"
        }
    ],
    "sg:phone":"+1 214 339 9411",
    "sg:postcode":"75211",
    "sg:province":"TX",
    "sg:tags":[
        "painter"
    ],
    "wof:name":"R L Richards Painting",
    "wof:placetype":"venue"
},
  "geometry": {"coordinates":[-96.868083,32.739248],"type":"Point"}
}