{
  "type": "Feature",
  "properties": {
    "iso:country":"US",
    "sg:address":"428 N Timberlane Rd",
    "sg:city":"Lone Star",
    "sg:classifiers":[
        {
            "category":"Professional",
            "type":"Services"
        }
    ],
    "sg:phone":"+1 903 656 3289",
    "sg:postcode":"75668",
    "sg:province":"TX",
    "wof:name":"Horace L Irwin",
    "wof:placetype":"venue"
},
  "geometry": {"coordinates":[-94.714685,32.95663],"type":"Point"}
}