{
  "type": "Feature",
  "properties": {
    "iso:country":"US",
    "sg:address":"905 29th St N",
    "sg:city":"Texas City",
    "sg:classifiers":[
        {
            "category":"Personal",
            "subcategory":"Barber",
            "type":"Services"
        }
    ],
    "sg:phone":"+1 409 945 8813",
    "sg:postcode":"77590",
    "sg:province":"TX",
    "sg:tags":[
        "shop"
    ],
    "wof:name":"Doyles Hair Shop",
    "wof:placetype":"venue"
},
  "geometry": {"coordinates":[-94.93730600000001,29.393451],"type":"Point"}
}