{
  "type": "Feature",
  "properties": {
    "iso:country":"US",
    "sg:address":"7801 Brandi Ln",
    "sg:city":"N Richland Hills",
    "sg:classifiers":[
        {
            "category":"Professional",
            "subcategory":"Business Services",
            "type":"Services"
        }
    ],
    "sg:phone":"+1 817 656 1979",
    "sg:postcode":"76180",
    "sg:province":"TX",
    "sg:tags":[
        "embroidery"
    ],
    "wof:name":"Northeast Sports & Embroidery",
    "wof:placetype":"venue"
},
  "geometry": {"coordinates":[-97.212475,32.865093],"type":"Point"}
}