{
  "type": "Feature",
  "properties": {
    "iso:country":"US",
    "sg:address":"3244 Hwy 67",
    "sg:city":"Mesquite",
    "sg:classifiers":[
        {
            "category":"Insurance",
            "subcategory":"Insurance Agent",
            "type":"Services"
        },
        {
            "category":"Shopping",
            "subcategory":"Computers & Home Electronics",
            "type":"Retail Goods"
        }
    ],
    "sg:phone":"+1 972 270 3133",
    "sg:postcode":"75150",
    "sg:province":"TX",
    "sg:tags":[
        "software"
    ],
    "wof:name":"Insurance Software Specialists",
    "wof:placetype":"venue"
},
  "geometry": {"coordinates":[-96.64839499999999,32.81275],"type":"Point"}
}