{
  "type": "Feature",
  "properties": {
    "iso:country":"US",
    "sg:address":"212 Vintage Ln",
    "sg:city":"Laredo",
    "sg:classifiers":[
        {
            "category":"Health Services",
            "subcategory":"Doctor",
            "type":"Services"
        }
    ],
    "sg:phone":"+1 956 725 4222",
    "sg:postcode":"78041",
    "sg:province":"TX",
    "wof:name":"Villanueva Graciela Dra",
    "wof:placetype":"venue"
},
  "geometry": {"coordinates":[-99.492874,27.560021],"type":"Point"}
}