{
  "type": "Feature",
  "properties": {
    "iso:country":"US",
    "sg:address":"6716 Bridge St",
    "sg:city":"Fort Worth",
    "sg:classifiers":[
        {
            "category":"Building & Trades",
            "subcategory":"Construction",
            "type":"Services"
        }
    ],
    "sg:phone":"+1 817 446 5597",
    "sg:postcode":"76112",
    "sg:province":"TX",
    "sg:tags":[
        "contractor"
    ],
    "wof:name":"Landmark General Contractors",
    "wof:placetype":"venue"
},
  "geometry": {"coordinates":[-97.217145,32.765274],"type":"Point"}
}