{
  "type": "Feature",
  "properties": {
    "iso:country":"US",
    "sg:address":"3003 Swiss Ave",
    "sg:city":"Dallas",
    "sg:classifiers":[
        {
            "category":"Organizations",
            "subcategory":"Non-profit Organization",
            "type":"Services"
        }
    ],
    "sg:phone":"+1 214 826 9431",
    "sg:postcode":"75204",
    "sg:province":"TX",
    "sg:tags":[
        "service/non-profit",
        "community"
    ],
    "wof:name":"Meadows Foundation Inc",
    "wof:placetype":"venue"
},
  "geometry": {"coordinates":[-96.785048,32.789232],"type":"Point"}
}