{
  "type": "Feature",
  "properties": {
    "iso:country":"US",
    "sg:address":"16250 Hammon St",
    "sg:city":"Amarillo",
    "sg:classifiers":[
        {
            "category":"Real Estate",
            "subcategory":"Real Estate Operator",
            "type":"Services"
        }
    ],
    "sg:phone":"+1 806 655 3261",
    "sg:postcode":"79118",
    "sg:province":"TX",
    "sg:tags":[
        "mobile",
        "home",
        "community"
    ],
    "wof:name":"Rockwell Acres Mobile Home Prk",
    "wof:placetype":"venue"
},
  "geometry": {"coordinates":[-101.91367099999999,35.043751],"type":"Point"}
}