{
  "type": "Feature",
  "properties": {
    "iso:country":"US",
    "sg:address":"2498 W Upshur Ave",
    "sg:city":"Gladewater",
    "sg:classifiers":[
        {
            "category":"Professional",
            "type":"Services"
        }
    ],
    "sg:phone":"+1 903 844 8254",
    "sg:postcode":"75647",
    "sg:province":"TX",
    "sg:tags":[
        "establishment"
    ],
    "wof:name":"Jp Pct 3 Upshur County",
    "wof:placetype":"venue"
},
  "geometry": {"coordinates":[-94.961854,32.542741],"type":"Point"}
}