{
  "type": "Feature",
  "properties": {
    "iso:country":"US",
    "sg:address":"1104 Van Horn Dr",
    "sg:city":"College Station",
    "sg:classifiers":[
        {
            "category":"Professional",
            "type":"Services"
        }
    ],
    "sg:phone":"+1 979 412 2178",
    "sg:postcode":"77845",
    "sg:province":"TX",
    "wof:name":"Electronics Etc",
    "wof:placetype":"venue"
},
  "geometry": {"coordinates":[-96.30289,30.588561],"type":"Point"}
}