{
  "type": "Feature",
  "properties": {
    "iso:country":"US",
    "sg:address":"1560 FM 971",
    "sg:city":"Georgetown",
    "sg:classifiers":[
        {
            "category":"Education",
            "subcategory":"School",
            "type":"Public Place"
        }
    ],
    "sg:phone":"+1 512 943 5150",
    "sg:postcode":"78626",
    "sg:province":"TX",
    "wof:name":"Charles Forbes Middle School",
    "wof:placetype":"venue"
},
  "geometry": {"coordinates":[-97.651116,30.663612],"type":"Point"}
}