{
  "type": "Feature",
  "properties": {
    "iso:country":"US",
    "sg:address":"310 Secor St",
    "sg:city":"Midland",
    "sg:classifiers":[
        {
            "category":"Personal",
            "subcategory":"Beauty Salon",
            "type":"Services"
        }
    ],
    "sg:phone":"+1 432 570 8892",
    "sg:postcode":"79701",
    "sg:province":"TX",
    "wof:name":"All About You",
    "wof:placetype":"venue"
},
  "geometry": {"coordinates":[-102.10274099999999,31.995977],"type":"Point"}
}