{
  "type": "Feature",
  "properties": {
    "iso:country":"US",
    "sg:address":"11708 Hempstead Rd",
    "sg:city":"Houston",
    "sg:classifiers":[
        {
            "category":"Restaurant",
            "type":"Food & Drink"
        }
    ],
    "sg:phone":"+1 713 957 1320",
    "sg:postcode":"77092",
    "sg:province":"TX",
    "sg:tags":[
        "eating"
    ],
    "wof:name":"Angie's Country Kitchen",
    "wof:placetype":"venue"
},
  "geometry": {"coordinates":[-95.483498,29.8186],"type":"Point"}
}