{
  "type": "Feature",
  "properties": {
    "iso:country":"US",
    "sg:address":"924 E 16th St",
    "sg:city":"Odessa",
    "sg:classifiers":[
        {
            "category":"Retail",
            "subcategory":"Repair Shop",
            "type":"Services"
        }
    ],
    "sg:phone":"+1 432 333 5156",
    "sg:postcode":"79761",
    "sg:province":"TX",
    "wof:name":"Daniels Appliances",
    "wof:placetype":"venue"
},
  "geometry": {"coordinates":[-102.36519199999999,31.864042],"type":"Point"}
}