{
  "type": "Feature",
  "properties": {
    "iso:country":"US",
    "sg:address":"5330 Bent Tree Forest Dr",
    "sg:city":"Dallas",
    "sg:classifiers":[
        {
            "category":"Professional",
            "subcategory":"Computer Services",
            "type":"Services"
        }
    ],
    "sg:phone":"+1 972 239 8038",
    "sg:postcode":"75248",
    "sg:province":"TX",
    "sg:tags":[
        "design",
        "system"
    ],
    "wof:name":"Dolcini J & Assoc",
    "wof:placetype":"venue"
},
  "geometry": {"coordinates":[-96.81708,32.965034],"type":"Point"}
}