{
  "type": "Feature",
  "properties": {
    "iso:country":"US",
    "sg:address":"15 2nd St N",
    "sg:city":"Texas City",
    "sg:classifiers":[
        {
            "category":"Professional",
            "subcategory":"Business Services",
            "type":"Services"
        }
    ],
    "sg:phone":"+1 409 965 9800",
    "sg:postcode":"77590",
    "sg:province":"TX",
    "wof:name":"Fan Man Production",
    "wof:placetype":"venue"
},
  "geometry": {"coordinates":[-94.896556,29.384432],"type":"Point"}
}