{
  "type": "Feature",
  "properties": {
    "iso:country":"US",
    "sg:address":"4901 Keller Springs Rd",
    "sg:city":"Addison",
    "sg:classifiers":[
        {
            "category":"Manufacturing",
            "subcategory":"Printing",
            "type":"Manufacturing & Wholesale Goods"
        }
    ],
    "sg:phone":"+1 972 931 3400",
    "sg:postcode":"75001",
    "sg:province":"TX",
    "sg:tags":[
        "lithographic",
        "printer",
        "commercial"
    ],
    "wof:name":"Prime Printing and Promotions",
    "wof:placetype":"venue"
},
  "geometry": {"coordinates":[-96.82583700000001,32.968624],"type":"Point"}
}