{
  "type": "Feature",
  "properties": {
    "iso:country":"US",
    "sg:address":"120 Fowlkes St",
    "sg:city":"Sealy",
    "sg:classifiers":[
        {
            "category":"Social Services",
            "subcategory":"Child Care",
            "type":"Services"
        }
    ],
    "sg:phone":"+1 979 885 3724",
    "sg:postcode":"77474",
    "sg:province":"TX",
    "wof:name":"Rece's House Of Angels",
    "wof:placetype":"venue"
},
  "geometry": {"coordinates":[-96.156589,29.782057],"type":"Point"}
}