{
  "type": "Feature",
  "properties": {
    "iso:country":"US",
    "sg:address":"8200 Neely Dr",
    "sg:city":"Austin",
    "sg:classifiers":[
        {
            "category":"Professional",
            "subcategory":"Secretarial Services",
            "type":"Services"
        }
    ],
    "sg:phone":"+1 512 502 0220",
    "sg:postcode":"78759",
    "sg:province":"TX",
    "sg:tags":[
        "reporting"
    ],
    "wof:name":"McMillan Reporting",
    "wof:placetype":"venue"
},
  "geometry": {"coordinates":[-97.757791,30.377644],"type":"Point"}
}