{
  "type": "Feature",
  "properties": {
    "iso:country":"US",
    "sg:address":"1304 San Antonio St",
    "sg:city":"Austin",
    "sg:classifiers":[
        {
            "category":"Insurance",
            "subcategory":"Insurance Agent",
            "type":"Services"
        }
    ],
    "sg:phone":"+1 512 478 7798",
    "sg:postcode":"78701",
    "sg:province":"TX",
    "wof:name":"Southwestern Life Insurance",
    "wof:placetype":"venue"
},
  "geometry": {"coordinates":[-97.744523,30.27724],"type":"Point"}
}