{
  "type": "Feature",
  "properties": {
    "iso:country":"US",
    "sg:address":"4359 Greco Dr",
    "sg:city":"San Antonio",
    "sg:classifiers":[
        {
            "category":"Social Services",
            "subcategory":"Child Care",
            "type":"Services"
        }
    ],
    "sg:phone":"+1 210 333 2128",
    "sg:postcode":"78222",
    "sg:province":"TX",
    "sg:tags":[
        "day"
    ],
    "wof:name":"Pecan Valley Child Care Center",
    "wof:placetype":"venue"
},
  "geometry": {"coordinates":[-98.408125,29.380588],"type":"Point"}
}