{
  "type": "Feature",
  "properties": {
    "iso:country":"US",
    "sg:address":"202 W Oleander St",
    "sg:city":"S Padre Island",
    "sg:classifiers":[
        {
            "category":"Real Estate",
            "subcategory":"Real Estate Operator",
            "type":"Services"
        }
    ],
    "sg:phone":"+1 956 761 2409",
    "sg:postcode":"78597",
    "sg:province":"TX",
    "sg:tags":[
        "apartment"
    ],
    "wof:name":"Tropic Breeze Apartments",
    "wof:placetype":"venue"
},
  "geometry": {"coordinates":[-97.17075199999999,26.113898],"type":"Point"}
}