{
  "type": "Feature",
  "properties": {
    "iso:country":"US",
    "sg:address":"4209 Versailles Ave",
    "sg:city":"Dallas",
    "sg:classifiers":[
        {
            "category":"Professional",
            "subcategory":"Business Services",
            "type":"Services"
        }
    ],
    "sg:phone":"+1 214 526 7639",
    "sg:postcode":"75205",
    "sg:province":"TX",
    "wof:name":"Rcb Partners LLC",
    "wof:placetype":"venue"
},
  "geometry": {"coordinates":[-96.806766,32.831122],"type":"Point"}
}