{
  "type": "Feature",
  "properties": {
    "iso:country":"US",
    "sg:address":"1211 Muirfield Pl",
    "sg:city":"Houston",
    "sg:classifiers":[
        {
            "category":"Food & Beverages",
            "subcategory":"Cheese",
            "type":"Retail Goods"
        }
    ],
    "sg:phone":"+1 713 688 9549",
    "sg:postcode":"77055",
    "sg:province":"TX",
    "wof:name":"Cacique Cheese Company Of Texas, Inc.",
    "wof:placetype":"venue"
},
  "geometry": {"coordinates":[-95.469953,29.791153],"type":"Point"}
}