{
  "type": "Feature",
  "properties": {
    "iso:country":"US",
    "sg:address":"6704 S Broadway Ave",
    "sg:city":"Tyler",
    "sg:classifiers":[
        {
            "category":"Restaurant",
            "type":"Food & Drink"
        }
    ],
    "sg:phone":"+1 903 581 7433",
    "sg:postcode":"75703",
    "sg:province":"TX",
    "sg:tags":[
        "eating"
    ],
    "wof:name":"Papacita's Mexican Restaurant",
    "wof:placetype":"venue"
},
  "geometry": {"coordinates":[-95.30662599999999,32.275351],"type":"Point"}
}