{
  "type": "Feature",
  "properties": {
    "iso:country":"US",
    "sg:address":"1500 Springbrook St",
    "sg:city":"Corinth",
    "sg:classifiers":[
        {
            "category":"Building & Trades",
            "subcategory":"Construction",
            "type":"Services"
        }
    ],
    "sg:phone":"+1 940 594 4804",
    "sg:postcode":"76210",
    "sg:province":"TX",
    "sg:tags":[
        "contractor",
        "fence-sales"
    ],
    "wof:name":"Henry & Son",
    "wof:placetype":"venue"
},
  "geometry": {"coordinates":[-97.073837,33.155472],"type":"Point"}
}