{
  "type": "Feature",
  "properties": {
    "iso:country":"US",
    "sg:address":"2000 Highway 157 N",
    "sg:city":"Mansfield",
    "sg:classifiers":[
        {
            "category":"Personal",
            "type":"Services"
        },
        {
            "category":"Arena",
            "subcategory":"Sports Club",
            "type":"Entertainment"
        }
    ],
    "sg:phone":"+1 682 518 8607",
    "sg:postcode":"76063",
    "sg:province":"TX",
    "sg:tags":[
        "trainer",
        "consultant",
        "physical",
        "health",
        "fitness"
    ],
    "wof:name":"First Spa & Nail",
    "wof:placetype":"venue"
},
  "geometry": {"coordinates":[-97.14444,32.602904],"type":"Point"}
}