{
  "type": "Feature",
  "properties": {
    "iso:country":"US",
    "sg:address":"123 S Main St",
    "sg:city":"Perryton",
    "sg:classifiers":[
        {
            "category":"Shopping",
            "subcategory":"Stationery & Office Supplies",
            "type":"Retail Goods"
        }
    ],
    "sg:phone":"+1 806 435 4812",
    "sg:postcode":"79070",
    "sg:province":"TX",
    "sg:tags":[
        "rubber",
        "stamp",
        "plastic"
    ],
    "wof:name":"Perryton Office Supply",
    "wof:placetype":"venue"
},
  "geometry": {"coordinates":[-100.802626,36.399344],"type":"Point"}
}