{
  "type": "Feature",
  "properties": {
    "iso:country":"US",
    "sg:address":"2737 Meadowbrook Dr",
    "sg:city":"Fort Worth",
    "sg:classifiers":[
        {
            "category":"Government",
            "subcategory":"Fire Station",
            "type":"Public Place"
        }
    ],
    "sg:phone":"+1 817 392 6805",
    "sg:postcode":"76103",
    "sg:province":"TX",
    "sg:tags":[
        "protection"
    ],
    "wof:name":"Fire Dept",
    "wof:placetype":"venue"
},
  "geometry": {"coordinates":[-97.28622300000001,32.743809],"type":"Point"}
}