{
  "type": "Feature",
  "properties": {
    "iso:country":"US",
    "sg:address":"13706 N Highway 183 Ste 109",
    "sg:city":"Austin",
    "sg:classifiers":[
        {
            "category":"Professional",
            "subcategory":"Business Services",
            "type":"Services"
        },
        {
            "category":"Organizations",
            "subcategory":"Professional Association",
            "type":"Services"
        }
    ],
    "sg:phone":"+1 512 320 0616",
    "sg:postcode":"78750",
    "sg:province":"TX",
    "sg:tags":[
        "referral",
        "contractor"
    ],
    "wof:name":"Tacca",
    "wof:placetype":"venue"
},
  "geometry": {"coordinates":[-97.792821,30.456631],"type":"Point"}
}