{
  "type": "Feature",
  "properties": {
    "iso:country":"US",
    "sg:address":"3406 Haven Oaks Dr",
    "sg:city":"Houston",
    "sg:classifiers":[
        {
            "category":"Insurance",
            "subcategory":"Insurance Agent",
            "type":"Services"
        }
    ],
    "sg:phone":"+1 281 444 9190",
    "sg:postcode":"77068",
    "sg:province":"TX",
    "wof:name":"Liberty Multiline Insurance",
    "wof:placetype":"venue"
},
  "geometry": {"coordinates":[-95.48866599999999,30.007299],"type":"Point"}
}