{
  "type": "Feature",
  "properties": {
    "iso:country":"US",
    "sg:address":"12070 Beaumont Hwy",
    "sg:city":"Houston",
    "sg:classifiers":[
        {
            "category":"Utilities",
            "subcategory":"Electric",
            "type":"Services"
        }
    ],
    "sg:phone":"+1 713 945 8555",
    "sg:postcode":"77049",
    "sg:province":"TX",
    "sg:tags":[
        "plant",
        "power"
    ],
    "wof:name":"Greens Bayou Power Plant",
    "wof:placetype":"venue"
},
  "geometry": {"coordinates":[-95.22026200000001,29.828227],"type":"Point"}
}