{
  "type": "Feature",
  "properties": {
    "iso:country":"US",
    "sg:address":"613 Quitman St",
    "sg:city":"Pittsburg",
    "sg:classifiers":[
        {
            "category":"Education",
            "subcategory":"Library",
            "type":"Public Place"
        }
    ],
    "sg:phone":"+1 903 856 3302",
    "sg:postcode":"75686",
    "sg:province":"TX",
    "wof:name":"Pittsburg-Camp County Library",
    "wof:placetype":"venue"
},
  "geometry": {"coordinates":[-94.977327,33.000476],"type":"Point"}
}