{
  "type": "Feature",
  "properties": {
    "iso:country":"US",
    "sg:address":"700 Stonecrest Rd",
    "sg:city":"Argyle",
    "sg:classifiers":[
        {
            "category":"Retail",
            "subcategory":"Laundry & Dry Cleaning",
            "type":"Services"
        }
    ],
    "sg:phone":"+1 940 464 0199",
    "sg:postcode":"76226",
    "sg:province":"TX",
    "sg:tags":[
        "drycleaning",
        "plant"
    ],
    "wof:name":"Cinch Cleaners",
    "wof:placetype":"venue"
},
  "geometry": {"coordinates":[-97.19443800000001,33.096648],"type":"Point"}
}