{
  "type": "Feature",
  "properties": {
    "iso:country":"US",
    "sg:address":"6465 East Mockingbird Ln Ste 316",
    "sg:city":"Dallas",
    "sg:classifiers":[
        {
            "category":"Bars & Pubs",
            "subcategory":"Sports Bar",
            "type":"Food & Drink"
        }
    ],
    "sg:phone":"+1 214 826 0110",
    "sg:postcode":"75214",
    "sg:province":"TX",
    "sg:website":"www.1stand10dallas.com",
    "wof:name":"Lakewood's 1st & 10",
    "wof:placetype":"venue"
},
  "geometry": {"coordinates":[-96.75130799999999,32.837506],"type":"Point"}
}