{
  "type": "Feature",
  "properties": {
    "iso:country":"US",
    "sg:address":"1042 S Gordon St",
    "sg:city":"Alvin",
    "sg:classifiers":[
        {
            "category":"Autos & Motor Vehicles",
            "subcategory":"Auto Supplies",
            "type":"Retail Goods"
        }
    ],
    "sg:phone":"+1 281 585 8184",
    "sg:postcode":"77511",
    "sg:province":"TX",
    "sg:tags":[
        "automobile",
        "parts"
    ],
    "wof:name":"O'Reilly Auto Parts",
    "wof:placetype":"venue"
},
  "geometry": {"coordinates":[-95.24389600000001,29.415739],"type":"Point"}
}