{
  "type": "Feature",
  "properties": {
    "iso:country":"US",
    "sg:address":"2000 Delwood Ct",
    "sg:city":"Austin",
    "sg:classifiers":[
        {
            "category":"Shopping",
            "type":"Retail Goods"
        }
    ],
    "sg:phone":"+1 512 926 1611",
    "sg:postcode":"78723",
    "sg:province":"TX",
    "sg:tags":[
        "merchandise"
    ],
    "wof:name":"Barfield Aquarium Maintenance",
    "wof:placetype":"venue"
},
  "geometry": {"coordinates":[-97.688841,30.308037],"type":"Point"}
}