{
  "type": "Feature",
  "properties": {
    "iso:country":"US",
    "sg:address":"7411 Hines Pl",
    "sg:city":"Dallas",
    "sg:classifiers":[
        {
            "category":"Wholesale",
            "subcategory":"Apparel",
            "type":"Manufacturing & Wholesale Goods"
        }
    ],
    "sg:phone":"+1 214 631 1826",
    "sg:postcode":"75235",
    "sg:province":"TX",
    "sg:tags":[
        "piece"
    ],
    "wof:name":"Harris Stanley Textiles",
    "wof:placetype":"venue"
},
  "geometry": {"coordinates":[-96.85923699999999,32.829624],"type":"Point"}
}