{
  "type": "Feature",
  "properties": {
    "iso:country":"US",
    "sg:address":"608 Cliff St",
    "sg:city":"Quitman",
    "sg:classifiers":[
        {
            "category":"Building & Trades",
            "subcategory":"Plumbing",
            "type":"Services"
        }
    ],
    "sg:phone":"+1 903 763 0002",
    "sg:postcode":"75783",
    "sg:province":"TX",
    "sg:tags":[
        "contractor"
    ],
    "wof:name":"Edward Shelman",
    "wof:placetype":"venue"
},
  "geometry": {"coordinates":[-95.445384,32.804955],"type":"Point"}
}