{
  "type": "Feature",
  "properties": {
    "iso:country":"US",
    "sg:address":"7350 Teaswood Dr",
    "sg:city":"Conroe",
    "sg:classifiers":[
        {
            "category":"Professional",
            "subcategory":"Business Services",
            "type":"Services"
        }
    ],
    "sg:phone":"+1 936 441 0813",
    "sg:postcode":"77304",
    "sg:province":"TX",
    "sg:tags":[
        "environmental",
        "ecological",
        "product"
    ],
    "wof:name":"Environmental Improvement",
    "wof:placetype":"venue"
},
  "geometry": {"coordinates":[-95.510643,30.360091],"type":"Point"}
}