{
  "type": "Feature",
  "properties": {
    "iso:country":"US",
    "sg:address":"16126 Lakeview Dr",
    "sg:city":"Houston",
    "sg:classifiers":[
        {
            "category":"Professional",
            "type":"Services"
        }
    ],
    "sg:phone":"+1 713 466 4654",
    "sg:postcode":"77040",
    "sg:province":"TX",
    "wof:name":"Lk & SA Inc",
    "wof:placetype":"venue"
},
  "geometry": {"coordinates":[-95.564142,29.884276],"type":"Point"}
}