{
  "type": "Feature",
  "properties": {
    "iso:country":"US",
    "sg:address":"12919 Susanna Ln",
    "sg:city":"Houston",
    "sg:classifiers":[
        {
            "category":"Professional",
            "subcategory":"Computer Services",
            "type":"Services"
        }
    ],
    "sg:phone":"+1 281 561 7783",
    "sg:postcode":"77072",
    "sg:province":"TX",
    "wof:name":"Greenkomp",
    "wof:placetype":"venue"
},
  "geometry": {"coordinates":[-95.610786,29.697742],"type":"Point"}
}