{
  "type": "Feature",
  "properties": {
    "iso:country":"US",
    "sg:address":"1814 S Western St",
    "sg:city":"Amarillo",
    "sg:classifiers":[
        {
            "category":"Shopping",
            "type":"Retail Goods"
        }
    ],
    "sg:phone":"+1 806 372 4049",
    "sg:postcode":"79106",
    "sg:province":"TX",
    "sg:tags":[
        "repair",
        "photocopier",
        "facsimile",
        "rent",
        "mach",
        "lease"
    ],
    "wof:name":"Remco Copyco",
    "wof:placetype":"venue"
},
  "geometry": {"coordinates":[-101.884108,35.192901],"type":"Point"}
}