{
  "type": "Feature",
  "properties": {
    "iso:country":"US",
    "sg:address":"200 Sequoia",
    "sg:city":"San Antonio",
    "sg:classifiers":[
        {
            "category":"Professional",
            "subcategory":"Business Services",
            "type":"Services"
        }
    ],
    "sg:phone":"+1 210 494 3743",
    "sg:postcode":"78232",
    "sg:province":"TX",
    "wof:name":"Ruth W Childre",
    "wof:placetype":"venue"
},
  "geometry": {"coordinates":[-98.487082,29.59591],"type":"Point"}
}