{
  "type": "Feature",
  "properties": {
    "iso:country":"US",
    "sg:address":"6501 Old Brock Rd",
    "sg:city":"Weatherford",
    "sg:classifiers":[
        {
            "category":"Building & Trades",
            "subcategory":"Construction",
            "type":"Services"
        }
    ],
    "sg:phone":"+1 817 594 6702",
    "sg:postcode":"76087",
    "sg:province":"TX",
    "sg:tags":[
        "contractor"
    ],
    "wof:name":"Lowell Ranspot Construction",
    "wof:placetype":"venue"
},
  "geometry": {"coordinates":[-97.89513700000001,32.698525],"type":"Point"}
}