{
  "type": "Feature",
  "properties": {
    "iso:country":"US",
    "sg:address":"1950 N Washington Ave",
    "sg:city":"Dallas",
    "sg:classifiers":[
        {
            "category":"Organizations",
            "subcategory":"Religious Organization",
            "type":"Services"
        }
    ],
    "sg:phone":"+1 214 824 6801",
    "sg:postcode":"75204",
    "sg:province":"TX",
    "wof:name":"Central Dallas Church",
    "wof:placetype":"venue"
},
  "geometry": {"coordinates":[-96.788229,32.799826],"type":"Point"}
}