{
  "type": "Feature",
  "properties": {
    "iso:country":"US",
    "sg:address":"1420 Dallas Ave",
    "sg:city":"Mcallen",
    "sg:classifiers":[
        {
            "category":"Banks & Credit Unions",
            "subcategory":"Bank",
            "type":"Services"
        }
    ],
    "sg:phone":"+1 956 668 1410",
    "sg:postcode":"78501",
    "sg:province":"TX",
    "sg:tags":[
        "personal"
    ],
    "wof:name":"Worth Finance Corp",
    "wof:placetype":"venue"
},
  "geometry": {"coordinates":[-98.235924,26.200686],"type":"Point"}
}