{
  "type": "Feature",
  "properties": {
    "iso:country":"US",
    "sg:address":"524 W Lamar St",
    "sg:city":"Sherman",
    "sg:classifiers":[
        {
            "category":"Restaurant",
            "type":"Food & Drink"
        }
    ],
    "sg:phone":"+1 903 893 6095",
    "sg:postcode":"75090",
    "sg:province":"TX",
    "wof:name":"Dairy Queen",
    "wof:placetype":"venue"
},
  "geometry": {"coordinates":[-96.61373,33.634589],"type":"Point"}
}