{
  "type": "Feature",
  "properties": {
    "iso:country":"US",
    "sg:address":"5120 Tolar Hwy",
    "sg:city":"Tolar",
    "sg:classifiers":[
        {
            "category":"Farming",
            "subcategory":"Livestock Farm",
            "type":"Manufacturing & Wholesale Goods"
        }
    ],
    "sg:phone":"+1 254 835 4779",
    "sg:postcode":"76476",
    "sg:province":"TX",
    "sg:tags":[
        "beef",
        "feedlot",
        "cattle"
    ],
    "wof:name":"4w Angus Ranch",
    "wof:placetype":"venue"
},
  "geometry": {"coordinates":[-97.96754799999999,32.422901],"type":"Point"}
}