{
  "type": "Feature",
  "properties": {
    "iso:country":"US",
    "sg:address":"4444 Westgrove Dr",
    "sg:city":"Addison",
    "sg:classifiers":[
        {
            "category":"Autos & Motor Vehicles",
            "subcategory":"Automobile Sales",
            "type":"Retail Goods"
        }
    ],
    "sg:phone":"+1 972 732 9555",
    "sg:postcode":"75001",
    "sg:province":"TX",
    "wof:name":"Legacy Avaitaion Inc",
    "wof:placetype":"venue"
},
  "geometry": {"coordinates":[-96.833392,32.97575],"type":"Point"}
}