{
  "type": "Feature",
  "properties": {
    "iso:country":"US",
    "sg:address":"5828 E Berry St",
    "sg:city":"Fort Worth",
    "sg:classifiers":[
        {
            "category":"Wholesale",
            "subcategory":"Machinery & Supplies",
            "type":"Manufacturing & Wholesale Goods"
        }
    ],
    "sg:phone":"+1 817 496 6001",
    "sg:postcode":"76119",
    "sg:province":"TX",
    "sg:tags":[
        "equipment",
        "veterinarian"
    ],
    "wof:name":"Frontier Veterinary Supply Inc",
    "wof:placetype":"venue"
},
  "geometry": {"coordinates":[-97.22842199999999,32.707382],"type":"Point"}
}