{
  "type": "Feature",
  "properties": {
    "iso:country":"US",
    "sg:address":"17610 Northwest Fwy",
    "sg:city":"Houston",
    "sg:classifiers":[
        {
            "category":"Manufacturing",
            "subcategory":"Toys & Sporting Goods",
            "type":"Manufacturing & Wholesale Goods"
        }
    ],
    "sg:phone":"+1 713 466 6044",
    "sg:postcode":"77065",
    "sg:province":"TX",
    "sg:tags":[
        "equipment",
        "playground",
        "mfg"
    ],
    "wof:name":"Outdoor Equipment Co",
    "wof:placetype":"venue"
},
  "geometry": {"coordinates":[-95.584463,29.89066],"type":"Point"}
}