{
  "type": "Feature",
  "properties": {
    "iso:country":"US",
    "sg:address":"25250 Borough Park Dr",
    "sg:city":"The Woodlands",
    "sg:classifiers":[
        {
            "category":"Insurance",
            "subcategory":"Insurance Agent",
            "type":"Services"
        }
    ],
    "sg:phone":"+1 281 364 8300",
    "sg:postcode":"77380",
    "sg:province":"TX",
    "wof:name":"Diversified Insurance",
    "wof:placetype":"venue"
},
  "geometry": {"coordinates":[-95.44626700000001,30.128544],"type":"Point"}
}