{
  "type": "Feature",
  "properties": {
    "iso:country":"US",
    "sg:address":"900 W Osr",
    "sg:city":"Caldwell",
    "sg:classifiers":[
        {
            "category":"Transit Center",
            "subcategory":"Freight",
            "type":"Transportation"
        },
        {
            "category":"Freight",
            "type":"Transportation"
        }
    ],
    "sg:phone":"+1 979 567 1986",
    "sg:postcode":"77836",
    "sg:province":"TX",
    "sg:tags":[
        "local",
        "trucking-motor",
        "trucking"
    ],
    "wof:name":"C Town Trucking",
    "wof:placetype":"venue"
},
  "geometry": {"coordinates":[-96.706413,30.53091],"type":"Point"}
}