{
  "type": "Feature",
  "properties": {
    "iso:country":"US",
    "sg:address":"518 Goodson Loop",
    "sg:city":"Pinehurst",
    "sg:classifiers":[
        {
            "category":"Home & Garden",
            "subcategory":"Home Furnishings",
            "type":"Retail Goods"
        },
        {
            "category":"Building & Trades",
            "subcategory":"Construction",
            "type":"Services"
        }
    ],
    "sg:phone":"+1 281 252 0849",
    "sg:postcode":"77362",
    "sg:province":"TX",
    "sg:tags":[
        "contractor",
        "mirror"
    ],
    "wof:name":"D J's Glass & Mirror",
    "wof:placetype":"venue"
},
  "geometry": {"coordinates":[-95.685591,30.163731],"type":"Point"}
}