{
  "type": "Feature",
  "properties": {
    "iso:country":"US",
    "sg:address":"11255 Garland Rd Ste 1130",
    "sg:city":"Dallas",
    "sg:classifiers":[
        {
            "category":"Health Services",
            "subcategory":"Optometrist",
            "type":"Services"
        }
    ],
    "sg:phone":"+1 214 575 7668",
    "sg:postcode":"75218",
    "sg:province":"TX",
    "sg:website":"www.mekasfamilyeyecare.com",
    "wof:name":"MEKAS FAMILY EYE CARE",
    "wof:placetype":"venue"
},
  "geometry": {"coordinates":[-96.68456999999999,32.848392],"type":"Point"}
}