{
  "type": "Feature",
  "properties": {
    "iso:country":"US",
    "sg:address":"4655 Techniplex Dr",
    "sg:city":"Stafford",
    "sg:classifiers":[
        {
            "category":"Manufacturing",
            "subcategory":"Printing",
            "type":"Manufacturing & Wholesale Goods"
        },
        {
            "category":"Professional",
            "subcategory":"Business Services",
            "type":"Services"
        },
        {
            "category":"Wholesale",
            "subcategory":"Books, Periodicals, & Newspapers",
            "type":"Manufacturing & Wholesale Goods"
        }
    ],
    "sg:phone":"+1 281 690 4242",
    "sg:postcode":"77477",
    "sg:province":"TX",
    "sg:tags":[
        "consultant",
        "magazines-distributors",
        "publishing",
        "representative",
        "publisher"
    ],
    "wof:name":"Fort Bend Focus",
    "wof:placetype":"venue"
},
  "geometry": {"coordinates":[-95.583738,29.633871],"type":"Point"}
}