{
  "type": "Feature",
  "properties": {
    "iso:country":"US",
    "sg:address":"707 Hollybrook Dr",
    "sg:city":"Longview",
    "sg:classifiers":[
        {
            "category":"Health Services",
            "subcategory":"Doctor",
            "type":"Services"
        }
    ],
    "sg:phone":"+1 903 553 9300",
    "sg:postcode":"75605",
    "sg:province":"TX",
    "sg:tags":[
        "physician",
        "medical",
        "surgeon"
    ],
    "wof:name":"Kellous A Price MD",
    "wof:placetype":"venue"
},
  "geometry": {"coordinates":[-94.731926,32.532134],"type":"Point"}
}