{
  "type": "Feature",
  "properties": {
    "iso:country":"US",
    "sg:address":"401 W 15th St",
    "sg:city":"Austin",
    "sg:classifiers":[
        {
            "category":"Organizations",
            "subcategory":"Professional Association",
            "type":"Services"
        }
    ],
    "sg:phone":"+1 512 370 1506",
    "sg:postcode":"78701",
    "sg:province":"TX",
    "sg:website":"www.txpeds.org",
    "wof:name":"Texas Pediatric Society",
    "wof:placetype":"venue"
},
  "geometry": {"coordinates":[-97.74403700000001,30.27826],"type":"Point"}
}