{
  "type": "Feature",
  "properties": {
    "iso:country":"US",
    "sg:address":"2208 W Park Row Dr # 100",
    "sg:city":"Pantego",
    "sg:classifiers":[
        {
            "category":"Education",
            "subcategory":"College",
            "type":"Public Place"
        }
    ],
    "sg:phone":"+1 817 277 6341",
    "sg:postcode":"76013",
    "sg:province":"TX",
    "sg:tags":[
        "school",
        "beauty"
    ],
    "sg:website":"http://www.ogleschool.com",
    "wof:name":"Ogle Beauty Supply",
    "wof:placetype":"venue"
},
  "geometry": {"coordinates":[-97.142448,32.72131],"type":"Point"}
}