{
  "type": "Feature",
  "properties": {
    "iso:country":"US",
    "sg:address":"7680 Joe Newton St",
    "sg:city":"San Antonio",
    "sg:classifiers":[
        {
            "category":"Organizations",
            "subcategory":"Religious Organization",
            "type":"Services"
        }
    ],
    "sg:phone":"+1 210 521 3377",
    "sg:postcode":"78251",
    "sg:province":"TX",
    "wof:name":"Pilgrim Center of Hope Inc",
    "wof:placetype":"venue"
},
  "geometry": {"coordinates":[-98.639225,29.462587],"type":"Point"}
}