{
  "type": "Feature",
  "properties": {
    "iso:country":"US",
    "sg:address":"15631 Fern Basin Dr",
    "sg:city":"Houston",
    "sg:classifiers":[
        {
            "category":"Professional",
            "type":"Services"
        }
    ],
    "sg:phone":"+1 281 859 3451",
    "sg:postcode":"77084",
    "sg:province":"TX",
    "wof:name":"Lynne S Walker",
    "wof:placetype":"venue"
},
  "geometry": {"coordinates":[-95.63508899999999,29.852615],"type":"Point"}
}