{
  "type": "Feature",
  "properties": {
    "iso:country":"US",
    "sg:address":"900 W Gibson St",
    "sg:city":"Jasper",
    "sg:classifiers":[
        {
            "category":"Travel",
            "subcategory":"Hotels & Motels",
            "type":"Entertainment"
        }
    ],
    "sg:phone":"+1 409 384 3424",
    "sg:postcode":"75951",
    "sg:province":"TX",
    "wof:name":"Budget Inn",
    "wof:placetype":"venue"
},
  "geometry": {"coordinates":[-94.016266,30.905113],"type":"Point"}
}