{
  "type": "Feature",
  "properties": {
    "iso:country":"US",
    "sg:address":"9426 Magnolia Ridge Dr",
    "sg:city":"Houston",
    "sg:classifiers":[
        {
            "category":"Professional",
            "subcategory":"Business Services",
            "type":"Services"
        }
    ],
    "sg:phone":"+1 281 655 8530",
    "sg:postcode":"77070",
    "sg:province":"TX",
    "wof:name":"Haleylynn Enterprise",
    "wof:placetype":"venue"
},
  "geometry": {"coordinates":[-95.566214,30.008034],"type":"Point"}
}