{
  "type": "Feature",
  "properties": {
    "iso:country":"US",
    "sg:address":"3470 Fannin St",
    "sg:city":"Beaumont",
    "sg:classifiers":[
        {
            "category":"Professional",
            "type":"Services"
        }
    ],
    "sg:phone":"+1 409 832 9018",
    "sg:postcode":"77701",
    "sg:province":"TX",
    "sg:tags":[
        "establishment"
    ],
    "wof:name":"Abortion Acceptable Assoc",
    "wof:placetype":"venue"
},
  "geometry": {"coordinates":[-94.125533,30.072105],"type":"Point"}
}