{
  "type": "Feature",
  "properties": {
    "iso:country":"US",
    "sg:address":"211 W Welder St",
    "sg:city":"Sinton",
    "sg:classifiers":[
        {
            "category":"Building & Trades",
            "subcategory":"Construction",
            "type":"Services"
        }
    ],
    "sg:phone":"+1 361 364 1569",
    "sg:postcode":"78387",
    "sg:province":"TX",
    "sg:tags":[
        "road",
        "contractor"
    ],
    "wof:name":"J Carroll Weaver Inc",
    "wof:placetype":"venue"
},
  "geometry": {"coordinates":[-97.511906,28.041173],"type":"Point"}
}