{
  "type": "Feature",
  "properties": {
    "iso:country":"US",
    "sg:address":"1721 S Avondale St",
    "sg:city":"Amarillo",
    "sg:classifiers":[
        {
            "category":"Communications",
            "subcategory":"Radio Station",
            "type":"Services"
        }
    ],
    "sg:phone":"+1 806 353 4448",
    "sg:postcode":"79106",
    "sg:province":"TX",
    "sg:tags":[
        "company",
        "broadcasting"
    ],
    "wof:name":"KDJW",
    "wof:placetype":"venue"
},
  "geometry": {"coordinates":[-101.89325700000001,35.195162],"type":"Point"}
}