{
  "type": "Feature",
  "properties": {
    "iso:country":"US",
    "sg:address":"3928 Kingwood Dr",
    "sg:city":"Humble",
    "sg:classifiers":[
        {
            "category":"Professional",
            "subcategory":"Research",
            "type":"Services"
        }
    ],
    "sg:phone":"+1 281 358 7171",
    "sg:postcode":"77339",
    "sg:province":"TX",
    "sg:tags":[
        "laboratory"
    ],
    "wof:name":"Aqua Analytical Lab Svc Inc",
    "wof:placetype":"venue"
},
  "geometry": {"coordinates":[-95.186295,30.049108],"type":"Point"}
}