{
  "type": "Feature",
  "properties": {
    "iso:country":"US",
    "sg:address":"616 Lakebridge Dr",
    "sg:city":"Lake Dallas",
    "sg:classifiers":[
        {
            "category":"Building & Trades",
            "subcategory":"Cleaning & Sanitation",
            "type":"Services"
        }
    ],
    "sg:phone":"+1 940 498 0717",
    "sg:postcode":"75065",
    "sg:province":"TX",
    "sg:tags":[
        "maintenance"
    ],
    "wof:name":"Personal Touch Housekeeping",
    "wof:placetype":"venue"
},
  "geometry": {"coordinates":[-97.017646,33.116923],"type":"Point"}
}