{
  "type": "Feature",
  "properties": {
    "iso:country":"US",
    "sg:address":"54 Haverhill Way",
    "sg:city":"San Antonio",
    "sg:classifiers":[
        {
            "category":"Real Estate",
            "subcategory":"Real Estate Agent",
            "type":"Services"
        }
    ],
    "sg:phone":"+1 210 832 8575",
    "sg:postcode":"78209",
    "sg:province":"TX",
    "wof:name":"Realty Asset Advisors Inc",
    "wof:placetype":"venue"
},
  "geometry": {"coordinates":[-98.47047600000001,29.493459],"type":"Point"}
}