{
  "type": "Feature",
  "properties": {
    "iso:country":"US",
    "sg:address":"6021 State Hwy 75",
    "sg:city":"Huntsville",
    "sg:classifiers":[
        {
            "category":"Home & Garden",
            "subcategory":"Building Materials",
            "type":"Retail Goods"
        }
    ],
    "sg:phone":"+1 936 295 4200",
    "sg:postcode":"77340",
    "sg:province":"TX",
    "sg:website":"www.mccoys.com",
    "wof:name":"Mc Coy's Building Supply Ctr",
    "wof:placetype":"venue"
},
  "geometry": {"coordinates":[-95.531659,30.695656],"type":"Point"}
}