{
  "type": "Feature",
  "properties": {
    "iso:country":"US",
    "sg:address":"3416 E Commerce St",
    "sg:city":"San Antonio",
    "sg:classifiers":[
        {
            "category":"Wholesale",
            "subcategory":"Auto Parts",
            "type":"Manufacturing & Wholesale Goods"
        }
    ],
    "sg:phone":"+1 210 224 7661",
    "sg:postcode":"78220",
    "sg:province":"TX",
    "sg:tags":[
        "tire"
    ],
    "wof:name":"C D Tire Shop",
    "wof:placetype":"venue"
},
  "geometry": {"coordinates":[-98.43234099999999,29.421545],"type":"Point"}
}