{
  "type": "Feature",
  "properties": {
    "iso:country":"US",
    "sg:address":"109 N Oregon St",
    "sg:city":"El Paso",
    "sg:classifiers":[
        {
            "category":"Professional",
            "subcategory":"Lawyer & Legal Services",
            "type":"Services"
        }
    ],
    "sg:phone":"+1 915 532 4328",
    "sg:postcode":"79901",
    "sg:province":"TX",
    "sg:tags":[
        "attorney"
    ],
    "wof:name":"Texas Rural Legal Aid Inc",
    "wof:placetype":"venue"
},
  "geometry": {"coordinates":[-106.488017,31.758298],"type":"Point"}
}