{
  "type": "Feature",
  "properties": {
    "iso:country":"US",
    "sg:address":"4771 US Hwy 67",
    "sg:city":"Midlothian",
    "sg:classifiers":[
        {
            "category":"Wholesale",
            "subcategory":"Motor Vehicles",
            "type":"Manufacturing & Wholesale Goods"
        }
    ],
    "sg:phone":"+1 972 775 8400",
    "sg:postcode":"76065",
    "sg:province":"TX",
    "sg:tags":[
        "trailer"
    ],
    "wof:name":"Eagle Trailers",
    "wof:placetype":"venue"
},
  "geometry": {"coordinates":[-96.975842,32.534372],"type":"Point"}
}