{
  "type": "Feature",
  "properties": {
    "iso:country":"US",
    "sg:address":"1 Riverway Ste 2055",
    "sg:city":"Houston",
    "sg:classifiers":[
        {
            "category":"Professional",
            "subcategory":"Lawyer & Legal Services",
            "type":"Services"
        }
    ],
    "sg:phone":"+1 800 284 5983",
    "sg:postcode":"77056",
    "sg:province":"TX",
    "sg:website":"www.houston-injury.com",
    "wof:name":"The Doan Law Firm PC",
    "wof:placetype":"venue"
},
  "geometry": {"coordinates":[-95.462503,29.76067],"type":"Point"}
}