{
  "type": "Feature",
  "properties": {
    "iso:country":"US",
    "sg:address":"4680 Glenn Curtiss Dr",
    "sg:city":"Addison",
    "sg:classifiers":[
        {
            "category":"Airport",
            "type":"Transportation"
        }
    ],
    "sg:phone":"+1 972 818 6300",
    "sg:postcode":"75001",
    "sg:province":"TX",
    "sg:tags":[
        "aircraft",
        "maintenance"
    ],
    "wof:name":"JSF",
    "wof:placetype":"venue"
},
  "geometry": {"coordinates":[-96.831566,32.970065],"type":"Point"}
}