{
  "type": "Feature",
  "properties": {
    "iso:country":"US",
    "sg:address":"13211 Jones Rd",
    "sg:city":"Houston",
    "sg:classifiers":[
        {
            "category":"Professional",
            "subcategory":"Accounting & Tax Preparation",
            "type":"Services"
        },
        {
            "category":"Professional",
            "subcategory":"Management & Consulting",
            "type":"Services"
        },
        {
            "category":"Banks & Credit Unions",
            "subcategory":"Financial Services",
            "type":"Services"
        }
    ],
    "sg:phone":"+1 281 894 0499",
    "sg:postcode":"77070",
    "sg:province":"TX",
    "sg:tags":[
        "financing",
        "return",
        "billing",
        "preparation-business",
        "taxes-consultants",
        "consultant",
        "planning",
        "representative",
        "bookkeeping"
    ],
    "wof:name":"Heritage Plus Tax & Bookkeeping",
    "wof:placetype":"venue"
},
  "geometry": {"coordinates":[-95.585279,29.963366],"type":"Point"}
}