{
  "type": "Feature",
  "properties": {
    "iso:country":"US",
    "sg:address":"111 W Spring Valley Rd",
    "sg:city":"Richardson",
    "sg:classifiers":[
        {
            "category":"Professional",
            "subcategory":"Business Services",
            "type":"Services"
        }
    ],
    "sg:phone":"+1 972 690 7227",
    "sg:postcode":"75081",
    "sg:province":"TX",
    "sg:tags":[
        "information",
        "referral"
    ],
    "wof:name":"Info Experts",
    "wof:placetype":"venue"
},
  "geometry": {"coordinates":[-96.73960599999999,32.93987],"type":"Point"}
}