{
  "type": "Feature",
  "properties": {
    "iso:country":"US",
    "sg:address":"9917 Nocturne Cove",
    "sg:city":"Austin",
    "sg:classifiers":[
        {
            "category":"Travel",
            "subcategory":"Travel Agent",
            "type":"Entertainment"
        }
    ],
    "sg:phone":"+1 512 219 8708",
    "sg:postcode":"78750",
    "sg:province":"TX",
    "sg:tags":[
        "information",
        "tourist"
    ],
    "wof:name":"Map Austin",
    "wof:placetype":"venue"
},
  "geometry": {"coordinates":[-97.80131900000001,30.443982],"type":"Point"}
}