{
  "type": "Feature",
  "properties": {
    "iso:country":"US",
    "sg:address":"109 E Main St",
    "sg:city":"Olney",
    "sg:classifiers":[
        {
            "category":"Professional",
            "subcategory":"Accounting & Tax Preparation",
            "type":"Services"
        }
    ],
    "sg:phone":"+1 940 564 2071",
    "sg:postcode":"76374",
    "sg:province":"TX",
    "wof:name":"B&M Business Services",
    "wof:placetype":"venue"
},
  "geometry": {"coordinates":[-98.753972,33.370696],"type":"Point"}
}