{
  "type": "Feature",
  "properties": {
    "iso:country":"US",
    "sg:address":"23214 Thelma Ln",
    "sg:city":"New Caney",
    "sg:classifiers":[
        {
            "category":"Retail",
            "subcategory":"Auto Repair",
            "type":"Services"
        }
    ],
    "sg:phone":"+1 281 399 8271",
    "sg:postcode":"77357",
    "sg:province":"TX",
    "sg:tags":[
        "machine",
        "automotive",
        "tool",
        "mfg"
    ],
    "wof:name":"Smith Machine Works",
    "wof:placetype":"venue"
},
  "geometry": {"coordinates":[-95.209053,30.134887],"type":"Point"}
}