{
  "type": "Feature",
  "properties": {
    "iso:country":"US",
    "sg:address":"4314 N Central Expy",
    "sg:city":"Dallas",
    "sg:classifiers":[
        {
            "category":"Professional",
            "subcategory":"Lawyer & Legal Services",
            "type":"Services"
        }
    ],
    "sg:phone":"+1 214 741 6713",
    "sg:postcode":"75206",
    "sg:province":"TX",
    "wof:name":"Callejo Adelfa B Atty",
    "wof:placetype":"venue"
},
  "geometry": {"coordinates":[-96.78800200000001,32.817299],"type":"Point"}
}