{
  "type": "Feature",
  "properties": {
    "iso:country":"US",
    "sg:address":"2721 Wilbarger St",
    "sg:city":"Vernon",
    "sg:classifiers":[
        {
            "category":"Shopping",
            "type":"Retail Goods"
        },
        {
            "category":"Health Services",
            "subcategory":"Clinic",
            "type":"Services"
        }
    ],
    "sg:phone":"+1 940 553 1300",
    "sg:postcode":"76384",
    "sg:province":"TX",
    "sg:tags":[
        "home",
        "merchandise"
    ],
    "wof:name":"Specialty Nurses Home Care",
    "wof:placetype":"venue"
},
  "geometry": {"coordinates":[-99.29465500000001,34.152555],"type":"Point"}
}