{
  "type": "Feature",
  "properties": {
    "iso:country":"US",
    "sg:address":"8622 Starcrest Dr",
    "sg:city":"San Antonio",
    "sg:classifiers":[
        {
            "category":"Social Services",
            "subcategory":"Adult Care",
            "type":"Services"
        }
    ],
    "sg:phone":"+1 210 655 1011",
    "sg:postcode":"78217",
    "sg:province":"TX",
    "sg:tags":[
        "residential"
    ],
    "wof:name":"Towne Oaks Residence",
    "wof:placetype":"venue"
},
  "geometry": {"coordinates":[-98.422763,29.51842],"type":"Point"}
}