{
  "type": "Feature",
  "properties": {
    "iso:country":"US",
    "sg:address":"2750 Blanchette St",
    "sg:city":"Beaumont",
    "sg:classifiers":[
        {
            "category":"Retail",
            "subcategory":"Auto Repair",
            "type":"Services"
        }
    ],
    "sg:phone":"+1 409 835 7192",
    "sg:postcode":"77701",
    "sg:province":"TX",
    "sg:tags":[
        "carwash",
        "general"
    ],
    "wof:name":"Eddies Auto Beauty Center",
    "wof:placetype":"venue"
},
  "geometry": {"coordinates":[-94.114017,30.063891],"type":"Point"}
}