{
  "type": "Feature",
  "properties": {
    "iso:country":"US",
    "sg:address":"101 Diamond Trl",
    "sg:city":"Georgetown",
    "sg:classifiers":[
        {
            "category":"Professional",
            "subcategory":"Employment Agencies",
            "type":"Services"
        }
    ],
    "sg:phone":"+1 512 869 2020",
    "sg:postcode":"78633",
    "sg:province":"TX",
    "sg:tags":[
        "help",
        "supply"
    ],
    "wof:name":"Currey Air Charter Inc",
    "wof:placetype":"venue"
},
  "geometry": {"coordinates":[-97.760707,30.701057],"type":"Point"}
}