{
  "type": "Feature",
  "properties": {
    "iso:country":"US",
    "sg:address":"2822 State St",
    "sg:city":"Dallas",
    "sg:classifiers":[
        {
            "category":"Building & Trades",
            "subcategory":"Construction",
            "type":"Services"
        }
    ],
    "sg:phone":"+1 214 526 4900",
    "sg:postcode":"75204",
    "sg:province":"TX",
    "sg:tags":[
        "home",
        "builder"
    ],
    "wof:name":"Perry Homes Dallas Intown",
    "wof:placetype":"venue"
},
  "geometry": {"coordinates":[-96.79852700000001,32.796713],"type":"Point"}
}