{
  "type": "Feature",
  "properties": {
    "iso:country":"US",
    "sg:address":"1219 Colorado Ln",
    "sg:city":"Arlington",
    "sg:classifiers":[
        {
            "category":"Retail",
            "subcategory":"Auto Repair",
            "type":"Services"
        }
    ],
    "sg:phone":"+1 817 226 9200",
    "sg:postcode":"76015",
    "sg:province":"TX",
    "sg:tags":[
        "automobile",
        "lubrication",
        "automotive"
    ],
    "wof:name":"Oil Extreme Mobile Pit Stop",
    "wof:placetype":"venue"
},
  "geometry": {"coordinates":[-97.12592100000001,32.702188],"type":"Point"}
}