{
  "type": "Feature",
  "properties": {
    "iso:country":"US",
    "sg:address":"3304 Buckle Ln",
    "sg:city":"Plano",
    "sg:classifiers":[
        {
            "category":"Food & Beverages",
            "subcategory":"Candy",
            "type":"Retail Goods"
        }
    ],
    "sg:phone":"+1 972 867 6219",
    "sg:postcode":"75023",
    "sg:province":"TX",
    "wof:name":"Candy Bouquet",
    "wof:placetype":"venue"
},
  "geometry": {"coordinates":[-96.75881200000001,33.044981],"type":"Point"}
}