{
  "type": "Feature",
  "properties": {
    "iso:country":"US",
    "sg:address":"3105 Stanolind Ave",
    "sg:city":"Midland",
    "sg:classifiers":[
        {
            "category":"Professional",
            "subcategory":"Business Services",
            "type":"Services"
        }
    ],
    "sg:phone":"+1 432 689 2140",
    "sg:postcode":"79705",
    "sg:province":"TX",
    "wof:name":"Jean K Lawrence",
    "wof:placetype":"venue"
},
  "geometry": {"coordinates":[-102.118337,32.012222],"type":"Point"}
}