{
  "type": "Feature",
  "properties": {
    "iso:country":"US",
    "sg:address":"6219 Congress Ave S",
    "sg:city":"Austin",
    "sg:classifiers":[
        {
            "category":"Autos & Motor Vehicles",
            "subcategory":"Automobile Sales",
            "type":"Retail Goods"
        }
    ],
    "sg:phone":"+1 512 447 1865",
    "sg:postcode":"78745",
    "sg:province":"TX",
    "sg:tags":[
        "car",
        "dealer"
    ],
    "wof:name":"Black Jack Motors",
    "wof:placetype":"venue"
},
  "geometry": {"coordinates":[-97.776523,30.198628],"type":"Point"}
}