{
  "type": "Feature",
  "properties": {
    "iso:country":"US",
    "sg:address":"4150 N Shepherd Dr",
    "sg:city":"Houston",
    "sg:classifiers":[
        {
            "category":"Shopping",
            "subcategory":"Pharmacy",
            "type":"Retail Goods"
        }
    ],
    "sg:phone":"+1 713 884 4040",
    "sg:postcode":"77018",
    "sg:province":"TX",
    "sg:tags":[
        "drugstore"
    ],
    "sg:website":"www.cvs.com",
    "wof:name":"CVS pharmacy",
    "wof:placetype":"venue"
},
  "geometry": {"coordinates":[-95.410387,29.825182],"type":"Point"}
}