{
  "type": "Feature",
  "properties": {
    "iso:country":"US",
    "sg:address":"1916 Seley Ave",
    "sg:city":"Waco",
    "sg:classifiers":[
        {
            "category":"Social Services",
            "subcategory":"Adult Care",
            "type":"Services"
        }
    ],
    "sg:phone":"+1 254 799 6291",
    "sg:postcode":"76704",
    "sg:province":"TX",
    "sg:tags":[
        "retardation",
        "home",
        "dev",
        "disabled"
    ],
    "wof:name":"Pecan Ridge Living Ctr",
    "wof:placetype":"venue"
},
  "geometry": {"coordinates":[-97.115146,31.586523],"type":"Point"}
}