{
  "type": "Feature",
  "properties": {
    "iso:country":"US",
    "sg:address":"3403 W Pioneer Dr",
    "sg:city":"Irving",
    "sg:classifiers":[
        {
            "category":"Restaurant",
            "type":"Food & Drink"
        }
    ],
    "sg:phone":"+1 972 790 5551",
    "sg:postcode":"75061",
    "sg:province":"TX",
    "wof:name":"Texas Snow Bullets",
    "wof:placetype":"venue"
},
  "geometry": {"coordinates":[-96.993756,32.828627],"type":"Point"}
}