{
  "type": "Feature",
  "properties": {
    "iso:country":"US",
    "sg:address":"4110 Highway 6 N",
    "sg:city":"Houston",
    "sg:classifiers":[
        {
            "category":"Manufacturing",
            "subcategory":"Rubber & Plastics",
            "type":"Manufacturing & Wholesale Goods"
        },
        {
            "category":"Autos & Motor Vehicles",
            "subcategory":"Auto Supplies",
            "type":"Retail Goods"
        },
        {
            "category":"Retail",
            "subcategory":"Auto Repair",
            "type":"Services"
        }
    ],
    "sg:phone":"+1 281 463 2700",
    "sg:postcode":"77084",
    "sg:province":"TX",
    "sg:tags":[
        "tires-wholesale",
        "tire",
        "retread",
        "recap",
        "manufacturer"
    ],
    "sg:website":"http://www.coopertire.com/html/",
    "wof:name":"Southwest Tire Shop #2",
    "wof:placetype":"venue"
},
  "geometry": {"coordinates":[-95.64563800000001,29.832384],"type":"Point"}
}