{
  "type": "Feature",
  "properties": {
    "iso:country":"US",
    "sg:address":"12004 Commonwealth Way",
    "sg:city":"Austin",
    "sg:classifiers":[
        {
            "category":"Home & Garden",
            "subcategory":"Building Materials",
            "type":"Retail Goods"
        }
    ],
    "sg:phone":"+1 512 335 6273",
    "sg:postcode":"78759",
    "sg:province":"TX",
    "sg:tags":[
        "door"
    ],
    "wof:name":"Gary's Overhead Door",
    "wof:placetype":"venue"
},
  "geometry": {"coordinates":[-97.766914,30.430734],"type":"Point"}
}