{
  "type": "Feature",
  "properties": {
    "iso:country":"US",
    "sg:address":"431 Eldridge Rd",
    "sg:city":"Sugar Land",
    "sg:classifiers":[
        {
            "category":"Social Services",
            "type":"Services"
        }
    ],
    "sg:phone":"+1 281 242 5385",
    "sg:postcode":"77478",
    "sg:province":"TX",
    "sg:tags":[
        "program",
        "outreach"
    ],
    "wof:name":"Family Outreach East Fort Bend",
    "wof:placetype":"venue"
},
  "geometry": {"coordinates":[-95.618719,29.629328],"type":"Point"}
}