{
  "type": "Feature",
  "properties": {
    "iso:country":"US",
    "sg:address":"1802 Beaver Bend Rd",
    "sg:city":"Houston",
    "sg:classifiers":[
        {
            "category":"Wholesale",
            "subcategory":"Plants",
            "type":"Manufacturing & Wholesale Goods"
        }
    ],
    "sg:phone":"+1 281 847 2320",
    "sg:postcode":"77088",
    "sg:province":"TX",
    "sg:tags":[
        "supply"
    ],
    "wof:name":"Sierra Grande Plants",
    "wof:placetype":"venue"
},
  "geometry": {"coordinates":[-95.428617,29.892735],"type":"Point"}
}