{
  "type": "Feature",
  "properties": {
    "iso:country":"US",
    "sg:address":"1201 W Belt Line Rd",
    "sg:city":"Richardson",
    "sg:classifiers":[
        {
            "category":"Education",
            "subcategory":"School",
            "type":"Public Place"
        }
    ],
    "sg:phone":"+1 972 238 1183",
    "sg:postcode":"75080",
    "sg:province":"TX",
    "wof:name":"Richardson Adventist School",
    "wof:placetype":"venue"
},
  "geometry": {"coordinates":[-96.75720200000001,32.951],"type":"Point"}
}