{
  "type": "Feature",
  "properties": {
    "iso:country":"US",
    "sg:address":"740 Slaughter St",
    "sg:city":"Vidor",
    "sg:classifiers":[
        {
            "category":"Building & Trades",
            "subcategory":"Construction",
            "type":"Services"
        }
    ],
    "sg:phone":"+1 409 783 2885",
    "sg:postcode":"77662",
    "sg:province":"TX",
    "sg:tags":[
        "water",
        "well",
        "drilling"
    ],
    "wof:name":"Golden Triangle Water Wells",
    "wof:placetype":"venue"
},
  "geometry": {"coordinates":[-94.027371,30.12681],"type":"Point"}
}