{
  "type": "Feature",
  "properties": {
    "iso:country":"US",
    "sg:address":"210 N Big Spring St",
    "sg:city":"Midland",
    "sg:classifiers":[
        {
            "category":"Professional",
            "subcategory":"Management & Consulting",
            "type":"Services"
        }
    ],
    "sg:phone":"+1 432 683 4001",
    "sg:postcode":"79701",
    "sg:province":"TX",
    "wof:name":"Pentec Pension",
    "wof:placetype":"venue"
},
  "geometry": {"coordinates":[-102.078039,31.999419],"type":"Point"}
}