{
  "type": "Feature",
  "properties": {
    "iso:country":"US",
    "sg:address":"5710 E R L Thornton Fwy",
    "sg:city":"Dallas",
    "sg:classifiers":[
        {
            "category":"Organizations",
            "subcategory":"Religious Organization",
            "type":"Services"
        }
    ],
    "sg:phone":"+1 214 828 4588",
    "sg:postcode":"75223",
    "sg:province":"TX",
    "wof:name":"Methodisms Bread Basket",
    "wof:placetype":"venue"
},
  "geometry": {"coordinates":[-96.74297799999999,32.791272],"type":"Point"}
}