{
  "type": "Feature",
  "properties": {
    "iso:country":"US",
    "sg:address":"11921 Bissonnet St",
    "sg:city":"Houston",
    "sg:classifiers":[
        {
            "category":"Professional",
            "subcategory":"Business Services",
            "type":"Services"
        }
    ],
    "sg:phone":"+1 281 495 3343",
    "sg:postcode":"77099",
    "sg:province":"TX",
    "wof:name":"Kirkwood Dental Associates",
    "wof:placetype":"venue"
},
  "geometry": {"coordinates":[-95.588357,29.675209],"type":"Point"}
}