{
  "type": "Feature",
  "properties": {
    "iso:country":"US",
    "sg:address":"1812 Ave Mexico",
    "sg:city":"Laredo",
    "sg:classifiers":[
        {
            "category":"Arts & Performance",
            "subcategory":"Theater",
            "type":"Entertainment"
        }
    ],
    "sg:phone":"+1 956 725 2752",
    "sg:postcode":"78046",
    "sg:province":"TX",
    "sg:tags":[
        "group"
    ],
    "wof:name":"E&H Promotions",
    "wof:placetype":"venue"
},
  "geometry": {"coordinates":[-99.451995,27.479504],"type":"Point"}
}