{
  "type": "Feature",
  "properties": {
    "iso:country":"US",
    "sg:address":"2112 San Antonio St",
    "sg:city":"San Angelo",
    "sg:classifiers":[
        {
            "category":"Home & Garden",
            "subcategory":"Building Materials",
            "type":"Retail Goods"
        }
    ],
    "sg:phone":"+1 325 949 7723",
    "sg:postcode":"76901",
    "sg:province":"TX",
    "sg:tags":[
        "shutter"
    ],
    "wof:name":"Cameron Custom Shutters",
    "wof:placetype":"venue"
},
  "geometry": {"coordinates":[-100.466679,31.455061],"type":"Point"}
}