{
  "type": "Feature",
  "properties": {
    "iso:country":"US",
    "sg:address":"6614 San Pedro Ave",
    "sg:city":"San Antonio",
    "sg:classifiers":[
        {
            "category":"Food & Beverages",
            "subcategory":"Groceries & Convenience Stores",
            "type":"Retail Goods"
        }
    ],
    "sg:phone":"+1 210 822 3202",
    "sg:postcode":"78216",
    "sg:province":"TX",
    "wof:name":"E Z Mart Stores",
    "wof:placetype":"venue"
},
  "geometry": {"coordinates":[-98.49918599999999,29.500047],"type":"Point"}
}