{
  "type": "Feature",
  "properties": {
    "iso:country":"US",
    "sg:address":"2540 N Galloway Ave",
    "sg:city":"Mesquite",
    "sg:classifiers":[
        {
            "category":"Health Services",
            "subcategory":"Health Practitioner",
            "type":"Services"
        }
    ],
    "sg:phone":"+1 972 613 3440",
    "sg:postcode":"75150",
    "sg:province":"TX",
    "wof:name":"Texas Hand Rhblttion Occptonal",
    "wof:placetype":"venue"
},
  "geometry": {"coordinates":[-96.611442,32.799591],"type":"Point"}
}