{
  "type": "Feature",
  "properties": {
    "iso:country":"US",
    "sg:address":"4101 Beltline Rd",
    "sg:city":"Addison",
    "sg:classifiers":[
        {
            "category":"Restaurant",
            "type":"Food & Drink"
        }
    ],
    "sg:phone":"+1 972 789 9206",
    "sg:postcode":"75001",
    "sg:province":"TX",
    "sg:tags":[
        "indian"
    ],
    "sg:website":"www.indianflavors.net/",
    "wof:name":"Flavors Indian Restaurant",
    "wof:placetype":"venue"
},
  "geometry": {"coordinates":[-96.869416,32.952601],"type":"Point"}
}