{
  "type": "Feature",
  "properties": {
    "iso:country":"US",
    "sg:address":"2814 Main St Ste 201",
    "sg:city":"Dallas",
    "sg:classifiers":[
        {
            "category":"Retail",
            "subcategory":"Event Space",
            "type":"Services"
        }
    ],
    "sg:phone":"+1 214 334 4481",
    "sg:postcode":"75226",
    "sg:province":"TX",
    "sg:tags":[
        "venue"
    ],
    "sg:website":"www.thisisspace.com/",
    "wof:name":"Space Studio",
    "wof:placetype":"venue"
},
  "geometry": {"coordinates":[-96.782791,32.783968],"type":"Point"}
}