{
  "type": "Feature",
  "properties": {
    "iso:country":"US",
    "sg:address":"5601 Bandera Rd",
    "sg:city":"San Antonio",
    "sg:classifiers":[
        {
            "category":"Personal",
            "subcategory":"Beauty Salon",
            "type":"Services"
        }
    ],
    "sg:phone":"+1 210 682 3715",
    "sg:postcode":"78238",
    "sg:province":"TX",
    "sg:tags":[
        "shop",
        "manicuring"
    ],
    "wof:name":"Vicky Nails",
    "wof:placetype":"venue"
},
  "geometry": {"coordinates":[-98.595017,29.480707],"type":"Point"}
}