{
  "type": "Feature",
  "properties": {
    "iso:country":"US",
    "sg:address":"6609 Blanco Rd",
    "sg:city":"San Antonio",
    "sg:classifiers":[
        {
            "category":"Personal",
            "type":"Services"
        }
    ],
    "sg:phone":"+1 210 979 9788",
    "sg:postcode":"78216",
    "sg:province":"TX",
    "sg:tags":[
        "cosmetic"
    ],
    "wof:name":"Simple Beautiful Perm Cosmetic",
    "wof:placetype":"venue"
},
  "geometry": {"coordinates":[-98.50674600000001,29.520197],"type":"Point"}
}