{
  "type": "Feature",
  "properties": {
    "iso:country":"US",
    "sg:address":"9001 Scotland Well Cv",
    "sg:city":"Austin",
    "sg:classifiers":[
        {
            "category":"Professional",
            "subcategory":"Accounting & Tax Preparation",
            "type":"Services"
        }
    ],
    "sg:phone":"+1 512 250 1115",
    "sg:postcode":"78750",
    "sg:province":"TX",
    "sg:tags":[
        "bookkeeping",
        "return",
        "preparation-business",
        "billing"
    ],
    "wof:name":"Patricia C Steele",
    "wof:placetype":"venue"
},
  "geometry": {"coordinates":[-97.796318,30.42481],"type":"Point"}
}