{
  "type": "Feature",
  "properties": {
    "iso:country":"US",
    "sg:address":"547 E Jefferson Blvd",
    "sg:city":"Dallas",
    "sg:classifiers":[
        {
            "category":"Education",
            "subcategory":"Special Training",
            "type":"Public Place"
        },
        {
            "category":"Education",
            "subcategory":"School",
            "type":"Public Place"
        }
    ],
    "sg:phone":"+1 214 941 2081",
    "sg:postcode":"75203",
    "sg:province":"TX",
    "sg:tags":[
        "educational"
    ],
    "sg:website":"http://www.ngsmigrant.com",
    "wof:name":"The School Of Liberal Arts & Science",
    "wof:placetype":"venue"
},
  "geometry": {"coordinates":[-96.816507,32.746945],"type":"Point"}
}