{
  "type": "Feature",
  "properties": {
    "iso:country":"US",
    "sg:address":"1826 Chestnut Spring",
    "sg:city":"Bulverde",
    "sg:classifiers":[
        {
            "category":"Wholesale",
            "subcategory":"Electrical",
            "type":"Manufacturing & Wholesale Goods"
        }
    ],
    "sg:phone":"+1 830 438 3986",
    "sg:postcode":"78163",
    "sg:province":"TX",
    "sg:tags":[
        "equipment"
    ],
    "wof:name":"Westinghouse Lighting Corp",
    "wof:placetype":"venue"
},
  "geometry": {"coordinates":[-98.458794,29.785881],"type":"Point"}
}