{
  "type": "Feature",
  "properties": {
    "iso:country":"US",
    "sg:address":"5126 Las Campanas St",
    "sg:city":"San Antonio",
    "sg:classifiers":[
        {
            "category":"Health Services",
            "subcategory":"Health Practitioner",
            "type":"Services"
        }
    ],
    "sg:phone":"+1 210 654 9155",
    "sg:postcode":"78233",
    "sg:province":"TX",
    "sg:tags":[
        "hypnotist"
    ],
    "wof:name":"Cheryl Cain",
    "wof:placetype":"venue"
},
  "geometry": {"coordinates":[-98.387697,29.555547],"type":"Point"}
}