{
  "type": "Feature",
  "properties": {
    "iso:country":"US",
    "sg:address":"500 Winburn Ave",
    "sg:city":"Schertz",
    "sg:classifiers":[
        {
            "category":"Building & Trades",
            "subcategory":"Construction",
            "type":"Services"
        }
    ],
    "sg:phone":"+1 210 945 9035",
    "sg:postcode":"78154",
    "sg:province":"TX",
    "sg:tags":[
        "home",
        "builder",
        "general",
        "contractor"
    ],
    "wof:name":"Stonecrafter Homes & Imprvmts",
    "wof:placetype":"venue"
},
  "geometry": {"coordinates":[-98.271109,29.556853],"type":"Point"}
}