{
  "type": "Feature",
  "properties": {
    "iso:country":"US",
    "sg:address":"5605 Dana Dr",
    "sg:city":"Fort Worth",
    "sg:classifiers":[
        {
            "category":"Utilities",
            "subcategory":"Telephone",
            "type":"Services"
        }
    ],
    "sg:phone":"+1 817 834 1788",
    "sg:postcode":"76117",
    "sg:province":"TX",
    "sg:tags":[
        "communications"
    ],
    "wof:name":"Miles A Dowdy",
    "wof:placetype":"venue"
},
  "geometry": {"coordinates":[-97.260845,32.807341],"type":"Point"}
}