{
  "type": "Feature",
  "properties": {
    "iso:country":"US",
    "sg:address":"1424 Phillips St",
    "sg:city":"Cleburne",
    "sg:classifiers":[
        {
            "category":"Building & Trades",
            "subcategory":"Electrical",
            "type":"Services"
        }
    ],
    "sg:phone":"+1 817 641 8914",
    "sg:postcode":"76033",
    "sg:province":"TX",
    "sg:tags":[
        "electrical",
        "electric",
        "contractor"
    ],
    "wof:name":"Patterson Electric",
    "wof:placetype":"venue"
},
  "geometry": {"coordinates":[-97.412154,32.356488],"type":"Point"}
}