{
  "type": "Feature",
  "properties": {
    "iso:country":"US",
    "sg:address":"103 FM 1183",
    "sg:city":"Ennis",
    "sg:classifiers":[
        {
            "category":"Personal",
            "subcategory":"Beauty Salon",
            "type":"Services"
        }
    ],
    "sg:phone":"+1 972 875 8833",
    "sg:postcode":"75119",
    "sg:province":"TX",
    "sg:tags":[
        "shop"
    ],
    "wof:name":"Split Endz",
    "wof:placetype":"venue"
},
  "geometry": {"coordinates":[-96.626605,32.327015],"type":"Point"}
}