{
  "type": "Feature",
  "properties": {
    "iso:country":"US",
    "sg:address":"105 E Pecan St",
    "sg:city":"San Saba",
    "sg:classifiers":[
        {
            "category":"Home & Garden",
            "subcategory":"Building Materials",
            "type":"Retail Goods"
        }
    ],
    "sg:phone":"+1 325 372 5279",
    "sg:postcode":"76877",
    "sg:province":"TX",
    "sg:tags":[
        "glass",
        "leaded"
    ],
    "wof:name":"Upper Room",
    "wof:placetype":"venue"
},
  "geometry": {"coordinates":[-98.720116,31.197575],"type":"Point"}
}