{
  "type": "Feature",
  "properties": {
    "iso:country":"US",
    "sg:address":"7573 Bent Oak Ln",
    "sg:city":"Tyler",
    "sg:classifiers":[
        {
            "category":"Autos & Motor Vehicles",
            "subcategory":"Automobile Sales",
            "type":"Retail Goods"
        }
    ],
    "sg:phone":"+1 903 535 9951",
    "sg:postcode":"75708",
    "sg:province":"TX",
    "sg:tags":[
        "new",
        "car"
    ],
    "wof:name":"East Texas Auto Sales",
    "wof:placetype":"venue"
},
  "geometry": {"coordinates":[-95.251141,32.394776],"type":"Point"}
}