{
  "type": "Feature",
  "properties": {
    "iso:country":"US",
    "sg:address":"3000 23rd St",
    "sg:city":"Snyder",
    "sg:classifiers":[
        {
            "category":"Shopping",
            "subcategory":"Gifts & Souvenirs",
            "type":"Retail Goods"
        }
    ],
    "sg:phone":"+1 325 573 5938",
    "sg:postcode":"79549",
    "sg:province":"TX",
    "wof:name":"Sues Zoo",
    "wof:placetype":"venue"
},
  "geometry": {"coordinates":[-100.931456,32.719249],"type":"Point"}
}