{
  "type": "Feature",
  "properties": {
    "iso:country":"US",
    "sg:address":"21929 Katy Fwy",
    "sg:city":"Katy",
    "sg:classifiers":[
        {
            "category":"Shopping",
            "subcategory":"Beauty & Cosmetics",
            "type":"Retail Goods"
        }
    ],
    "sg:phone":"+1 281 392 3301",
    "sg:postcode":"77450",
    "sg:province":"TX",
    "sg:tags":[
        "merchandise"
    ],
    "wof:name":"Merle Norman Cosmetics",
    "wof:placetype":"venue"
},
  "geometry": {"coordinates":[-95.752539,29.783177],"type":"Point"}
}