{
  "type": "Feature",
  "properties": {
    "iso:country":"US",
    "sg:address":"10607 Co Rd 149",
    "sg:city":"Flint",
    "sg:classifiers":[
        {
            "category":"Building & Trades",
            "subcategory":"Landscaping Services",
            "type":"Services"
        }
    ],
    "sg:phone":"+1 903 894 3965",
    "sg:postcode":"75762",
    "sg:province":"TX",
    "wof:name":"J&J Tree Service",
    "wof:placetype":"venue"
},
  "geometry": {"coordinates":[-95.345365,32.18954],"type":"Point"}
}