{
  "type": "Feature",
  "properties": {
    "iso:country":"US",
    "sg:address":"951 N Walnut Creek Dr",
    "sg:city":"Mansfield",
    "sg:classifiers":[
        {
            "category":"Insurance",
            "subcategory":"Insurance Agent",
            "type":"Services"
        }
    ],
    "sg:phone":"+1 817 473 1138",
    "sg:postcode":"76063",
    "sg:province":"TX",
    "wof:name":"John Key Insurance Agent",
    "wof:placetype":"venue"
},
  "geometry": {"coordinates":[-97.132502,32.579516],"type":"Point"}
}