{
  "type": "Feature",
  "properties": {
    "iso:country":"US",
    "sg:address":"8902 Gauguin Dr",
    "sg:city":"Houston",
    "sg:classifiers":[
        {
            "category":"Building & Trades",
            "subcategory":"Plumbing",
            "type":"Services"
        }
    ],
    "sg:phone":"+1 713 466 9005",
    "sg:postcode":"77088",
    "sg:province":"TX",
    "sg:tags":[
        "contractor"
    ],
    "wof:name":"Dwf Plumbing Services & Repair",
    "wof:placetype":"venue"
},
  "geometry": {"coordinates":[-95.491986,29.873082],"type":"Point"}
}