{
  "type": "Feature",
  "properties": {
    "iso:country":"US",
    "sg:address":"3522 S Alameda St",
    "sg:city":"Corpus Christi",
    "sg:classifiers":[
        {
            "category":"Wholesale",
            "subcategory":"Medical Equipment & Supplies",
            "type":"Manufacturing & Wholesale Goods"
        }
    ],
    "sg:phone":"+1 361 884 9393",
    "sg:postcode":"78411",
    "sg:province":"TX",
    "sg:tags":[
        "physician",
        "surgeon"
    ],
    "wof:name":"Respiratory Solutions Inc",
    "wof:placetype":"venue"
},
  "geometry": {"coordinates":[-97.38448699999999,27.748711],"type":"Point"}
}