{
  "type": "Feature",
  "properties": {
    "iso:country":"US",
    "sg:address":"4225 Canoas Dr",
    "sg:city":"Austin",
    "sg:classifiers":[
        {
            "category":"Professional",
            "subcategory":"Detective & Security Services",
            "type":"Services"
        }
    ],
    "sg:phone":"+1 512 494 4549",
    "sg:postcode":"78730",
    "sg:province":"TX",
    "sg:tags":[
        "information",
        "bureau"
    ],
    "wof:name":"Community Medication Assisted Treatment",
    "wof:placetype":"venue"
},
  "geometry": {"coordinates":[-97.85732899999999,30.367252],"type":"Point"}
}