{
  "type": "Feature",
  "properties": {
    "iso:country":"US",
    "sg:address":"903 Felder St",
    "sg:city":"Navasota",
    "sg:classifiers":[
        {
            "category":"Shopping",
            "subcategory":"Hobbies, Toys, & Games",
            "type":"Retail Goods"
        }
    ],
    "sg:phone":"+1 936 825 7268",
    "sg:postcode":"77868",
    "sg:province":"TX",
    "wof:name":"Navasota Miniture Armory",
    "wof:placetype":"venue"
},
  "geometry": {"coordinates":[-96.083558,30.394596],"type":"Point"}
}