{
  "type": "Feature",
  "properties": {
    "iso:country":"US",
    "sg:address":"473 Cranbrook Dr",
    "sg:city":"Waco",
    "sg:classifiers":[
        {
            "category":"Insurance",
            "subcategory":"Insurance Agent",
            "type":"Services"
        }
    ],
    "sg:phone":"+1 254 741 9350",
    "sg:postcode":"76712",
    "sg:province":"TX",
    "wof:name":"Susan Burt Insurance",
    "wof:placetype":"venue"
},
  "geometry": {"coordinates":[-97.203678,31.511287],"type":"Point"}
}