{
  "type": "Feature",
  "properties": {
    "iso:country":"US",
    "sg:address":"533 US Hwy 83",
    "sg:city":"Uvalde",
    "sg:classifiers":[
        {
            "category":"Professional",
            "type":"Services"
        }
    ],
    "sg:phone":"+1 830 591 1399",
    "sg:postcode":"78801",
    "sg:province":"TX",
    "sg:tags":[
        "establishment"
    ],
    "wof:name":"Dirt Werks",
    "wof:placetype":"venue"
},
  "geometry": {"coordinates":[-99.787808,29.194257],"type":"Point"}
}