{
  "type": "Feature",
  "properties": {
    "iso:country":"US",
    "sg:address":"4204 S Fannin St",
    "sg:city":"Amarillo",
    "sg:classifiers":[
        {
            "category":"Professional",
            "subcategory":"Business Services",
            "type":"Services"
        }
    ],
    "sg:phone":"+1 806 353 9231",
    "sg:postcode":"79110",
    "sg:province":"TX",
    "wof:name":"Baker Home Instpections",
    "wof:placetype":"venue"
},
  "geometry": {"coordinates":[-101.860733,35.167554],"type":"Point"}
}