{
  "type": "Feature",
  "properties": {
    "iso:country":"US",
    "sg:address":"3509 Elgin St",
    "sg:city":"Houston",
    "sg:classifiers":[
        {
            "category":"Food & Beverages",
            "subcategory":"Groceries & Convenience Stores",
            "type":"Retail Goods"
        }
    ],
    "sg:phone":"+1 713 571 2222",
    "sg:postcode":"77004",
    "sg:province":"TX",
    "sg:tags":[
        "shop",
        "sandwich"
    ],
    "sg:website":"http://www.grabbajavacafe.com",
    "wof:name":"Grabba Java",
    "wof:placetype":"venue"
},
  "geometry": {"coordinates":[-95.350117,29.727977],"type":"Point"}
}