{
  "type": "Feature",
  "properties": {
    "iso:country":"US",
    "sg:address":"12902 6th St",
    "sg:city":"Alta Loma",
    "sg:classifiers":[
        {
            "category":"Organizations",
            "subcategory":"Religious Organization",
            "type":"Services"
        }
    ],
    "sg:phone":"+1 409 925 3411",
    "sg:postcode":"77510",
    "sg:province":"TX",
    "sg:tags":[
        "church"
    ],
    "sg:website":"www.santafebaptistchurch.org",
    "wof:name":"Santa Fe Baptist Church",
    "wof:placetype":"venue"
},
  "geometry": {"coordinates":[-95.096294,29.384451],"type":"Point"}
}