{
  "type": "Feature",
  "properties": {
    "iso:country":"US",
    "sg:address":"3801 Bellaire Blvd",
    "sg:city":"Houston",
    "sg:classifiers":[
        {
            "category":"Restaurant",
            "type":"Food & Drink"
        }
    ],
    "sg:phone":"+1 713 665 3900",
    "sg:postcode":"77025",
    "sg:province":"TX",
    "sg:tags":[
        "tex-mex"
    ],
    "wof:name":"Terlingua Border Cafe",
    "wof:placetype":"venue"
},
  "geometry": {"coordinates":[-95.43819999999999,29.705426],"type":"Point"}
}