{
  "type": "Feature",
  "properties": {
    "iso:country":"US",
    "sg:address":"710 Northgate Rd",
    "sg:city":"Victoria",
    "sg:classifiers":[
        {
            "category":"Professional",
            "subcategory":"Engineering",
            "type":"Services"
        },
        {
            "category":"Home & Garden",
            "subcategory":"Building Materials",
            "type":"Retail Goods"
        },
        {
            "category":"Building & Trades",
            "subcategory":"Construction",
            "type":"Services"
        }
    ],
    "sg:phone":"+1 361 576 1212",
    "sg:postcode":"77904",
    "sg:province":"TX",
    "sg:tags":[
        "repair",
        "system",
        "specialty",
        "heating",
        "equipment",
        "contractor",
        "air conditioning"
    ],
    "sg:website":"http://www.airtechsairconditioning.net/",
    "wof:name":"Air Techs Air Conditioning Co",
    "wof:placetype":"venue"
},
  "geometry": {"coordinates":[-97.002663,28.8813],"type":"Point"}
}