{
  "type": "Feature",
  "properties": {
    "iso:country":"US",
    "sg:address":"2107 E Hwy 377",
    "sg:city":"Granbury",
    "sg:classifiers":[
        {
            "category":"Home & Garden",
            "subcategory":"Furniture",
            "type":"Retail Goods"
        }
    ],
    "sg:phone":"+1 817 573 4578",
    "sg:postcode":"76049",
    "sg:province":"TX",
    "wof:name":"Lake Country Furniture",
    "wof:placetype":"venue"
},
  "geometry": {"coordinates":[-97.75135899999999,32.443655],"type":"Point"}
}