{
  "type": "Feature",
  "properties": {
    "iso:country":"US",
    "sg:address":"720 Bayland Ave",
    "sg:city":"Houston",
    "sg:classifiers":[
        {
            "category":"Professional",
            "subcategory":"Lawyer & Legal Services",
            "type":"Services"
        }
    ],
    "sg:phone":"+1 713 861 0782",
    "sg:postcode":"77009",
    "sg:province":"TX",
    "wof:name":"Rowland Roy",
    "wof:placetype":"venue"
},
  "geometry": {"coordinates":[-95.3805,29.78664],"type":"Point"}
}