{
  "type": "Feature",
  "properties": {
    "iso:country":"US",
    "sg:address":"12901 Dakota Ln",
    "sg:city":"Austin",
    "sg:classifiers":[
        {
            "category":"Recreation",
            "type":"Entertainment"
        }
    ],
    "sg:phone":"+1 512 335 4190",
    "sg:postcode":"78729",
    "sg:province":"TX",
    "sg:tags":[
        "diving",
        "instruction"
    ],
    "wof:name":"Austin Divers Training Ctr",
    "wof:placetype":"venue"
},
  "geometry": {"coordinates":[-97.75413399999999,30.442845],"type":"Point"}
}