{
  "type": "Feature",
  "properties": {
    "iso:country":"US",
    "sg:address":"8529 Birmingham Dr",
    "sg:city":"Austin",
    "sg:classifiers":[
        {
            "category":"Professional",
            "subcategory":"Detective & Security Services",
            "type":"Services"
        }
    ],
    "sg:phone":"+1 512 554 8111",
    "sg:postcode":"78748",
    "sg:province":"TX",
    "sg:tags":[
        "information",
        "bureau"
    ],
    "wof:name":"Quick's Wireless Services",
    "wof:placetype":"venue"
},
  "geometry": {"coordinates":[-97.80528200000001,30.182121],"type":"Point"}
}