{
  "type": "Feature",
  "properties": {
    "iso:country":"US",
    "sg:address":"11515 Warbler Ledge",
    "sg:city":"Austin",
    "sg:classifiers":[
        {
            "category":"Shopping",
            "subcategory":"Discount & Variety Stores",
            "type":"Retail Goods"
        },
        {
            "category":"Wholesale",
            "subcategory":"Groceries",
            "type":"Manufacturing & Wholesale Goods"
        }
    ],
    "sg:phone":"+1 512 358 9593",
    "sg:postcode":"78734",
    "sg:province":"TX",
    "sg:tags":[
        "post",
        "trading",
        "association"
    ],
    "wof:name":"Serengeti Trading Company LLC",
    "wof:placetype":"venue"
},
  "geometry": {"coordinates":[-97.93053,30.285841],"type":"Point"}
}