{
  "type": "Feature",
  "properties": {
    "iso:country":"US",
    "sg:address":"6575 E Northwest Hwy",
    "sg:city":"Dallas",
    "sg:classifiers":[
        {
            "category":"Autos & Motor Vehicles",
            "subcategory":"Auto Supplies",
            "type":"Retail Goods"
        }
    ],
    "sg:phone":"+1 214 692 1044",
    "sg:postcode":"75231",
    "sg:province":"TX",
    "sg:tags":[
        "wheel",
        "cover"
    ],
    "wof:name":"D J's Wheel World",
    "wof:placetype":"venue"
},
  "geometry": {"coordinates":[-96.74779700000001,32.856465],"type":"Point"}
}