{
  "type": "Feature",
  "properties": {
    "iso:country":"US",
    "sg:address":"213 W Hudgins St",
    "sg:city":"Grapevine",
    "sg:classifiers":[
        {
            "category":"Professional",
            "subcategory":"Lawyer & Legal Services",
            "type":"Services"
        }
    ],
    "sg:phone":"+1 817 424 4210",
    "sg:postcode":"76051",
    "sg:province":"TX",
    "sg:tags":[
        "attorney"
    ],
    "wof:name":"Delila Ledwith Law Offices",
    "wof:placetype":"venue"
},
  "geometry": {"coordinates":[-97.07923099999999,32.934302],"type":"Point"}
}