{
  "type": "Feature",
  "properties": {
    "iso:country":"US",
    "sg:address":"11733 Marsh Ln",
    "sg:city":"Dallas",
    "sg:classifiers":[
        {
            "category":"Retail",
            "subcategory":"Repair Shop",
            "type":"Services"
        }
    ],
    "sg:phone":"+1 972 416 2888",
    "sg:postcode":"75229",
    "sg:province":"TX",
    "sg:tags":[
        "repairing",
        "picture",
        "frame"
    ],
    "wof:name":"Forest Framer",
    "wof:placetype":"venue"
},
  "geometry": {"coordinates":[-96.85625,32.908834],"type":"Point"}
}