{
  "type": "Feature",
  "properties": {
    "iso:country":"US",
    "sg:address":"4707 W Walnut St",
    "sg:city":"Pearland",
    "sg:classifiers":[
        {
            "category":"Retail",
            "subcategory":"Auto Repair",
            "type":"Services"
        }
    ],
    "sg:phone":"+1 281 485 0041",
    "sg:postcode":"77581",
    "sg:province":"TX",
    "sg:tags":[
        "repairing",
        "automobile"
    ],
    "wof:name":"Elliott's Automotive",
    "wof:placetype":"venue"
},
  "geometry": {"coordinates":[-95.295185,29.559871],"type":"Point"}
}