{
  "type": "Feature",
  "properties": {
    "iso:country":"US",
    "sg:address":"10601 N Lamar Boulevard",
    "sg:city":"Austin",
    "sg:classifiers":[
        {
            "category":"Professional",
            "subcategory":"Computer Services",
            "type":"Services"
        }
    ],
    "sg:phone":"+1 512 834 2222",
    "sg:postcode":"78753",
    "sg:province":"TX",
    "sg:tags":[
        "stereo",
        "installation"
    ],
    "wof:name":"Discount Car Stereo",
    "wof:placetype":"venue"
},
  "geometry": {"coordinates":[-97.690157,30.375485],"type":"Point"}
}