{
  "type": "Feature",
  "properties": {
    "iso:country":"US",
    "sg:address":"9206 Woodleigh Dr",
    "sg:city":"Houston",
    "sg:classifiers":[
        {
            "category":"Organizations",
            "subcategory":"Membership Organization",
            "type":"Services"
        }
    ],
    "sg:phone":"+1 281 530 7691",
    "sg:postcode":"77083",
    "sg:province":"TX",
    "wof:name":"Providence Community Assn",
    "wof:placetype":"venue"
},
  "geometry": {"coordinates":[-95.64533900000001,29.680417],"type":"Point"}
}