{
  "type": "Feature",
  "properties": {
    "iso:country":"US",
    "sg:address":"101 N Mockingbird Ln",
    "sg:city":"Keene",
    "sg:classifiers":[
        {
            "category":"Government",
            "subcategory":"Office",
            "type":"Public Place"
        }
    ],
    "sg:phone":"+1 817 641 7831",
    "sg:postcode":"76059",
    "sg:province":"TX",
    "sg:tags":[
        "township",
        "government-city",
        "village"
    ],
    "wof:name":"City of Keene",
    "wof:placetype":"venue"
},
  "geometry": {"coordinates":[-97.328613,32.39624],"type":"Point"}
}