{
  "type": "Feature",
  "properties": {
    "iso:country":"US",
    "sg:address":"340 Mechanic St",
    "sg:city":"Tomball",
    "sg:classifiers":[
        {
            "category":"Mining & Drilling",
            "type":"Manufacturing & Wholesale Goods"
        }
    ],
    "sg:phone":"+1 281 290 7335",
    "sg:postcode":"77375",
    "sg:province":"TX",
    "sg:tags":[
        "field",
        "oil"
    ],
    "wof:name":"Gallco Services, Inc.",
    "wof:placetype":"venue"
},
  "geometry": {"coordinates":[-95.609618,30.097917],"type":"Point"}
}