{
  "type": "Feature",
  "properties": {
    "iso:country":"US",
    "sg:address":"205 Fordyce St",
    "sg:city":"Barry",
    "sg:classifiers":[
        {
            "category":"Professional",
            "subcategory":"Advertising",
            "type":"Services"
        }
    ],
    "sg:phone":"+1 903 695 1145",
    "sg:postcode":"75102",
    "sg:province":"TX",
    "sg:tags":[
        "promotion",
        "sale"
    ],
    "wof:name":"Schipper Promotional",
    "wof:placetype":"venue"
},
  "geometry": {"coordinates":[-96.636392,32.100384],"type":"Point"}
}