{
  "type": "Feature",
  "properties": {
    "iso:country":"US",
    "sg:address":"202 N Elm St",
    "sg:city":"Malone",
    "sg:classifiers":[
        {
            "category":"Food & Beverages",
            "subcategory":"Groceries & Convenience Stores",
            "type":"Retail Goods"
        }
    ],
    "sg:phone":"+1 254 533 2472",
    "sg:postcode":"76660",
    "sg:province":"TX",
    "sg:tags":[
        "grocer"
    ],
    "wof:name":"Corner Store",
    "wof:placetype":"venue"
},
  "geometry": {"coordinates":[-96.892926,31.916946],"type":"Point"}
}