{
  "type": "Feature",
  "properties": {
    "iso:country":"US",
    "sg:address":"415 Paso Real",
    "sg:city":"San Benito",
    "sg:classifiers":[
        {
            "category":"Restaurant",
            "type":"Food & Drink"
        }
    ],
    "sg:phone":"+1 956 399 7671",
    "sg:postcode":"78586",
    "sg:province":"TX",
    "wof:name":"Mi Rancho Steak House",
    "wof:placetype":"venue"
},
  "geometry": {"coordinates":[-97.657341,26.161301],"type":"Point"}
}