{
  "type": "Feature",
  "properties": {
    "iso:country":"US",
    "sg:address":"901 S 10th St",
    "sg:city":"Mcallen",
    "sg:classifiers":[
        {
            "category":"Shopping",
            "subcategory":"Discount & Variety Stores",
            "type":"Retail Goods"
        }
    ],
    "sg:phone":"+1 956 994 8544",
    "sg:postcode":"78501",
    "sg:province":"TX",
    "sg:tags":[
        "merchandise",
        "general"
    ],
    "wof:name":"Ninety Cents Plus",
    "wof:placetype":"venue"
},
  "geometry": {"coordinates":[-98.231337,26.195192],"type":"Point"}
}