{
  "type": "Feature",
  "properties": {
    "iso:country":"US",
    "sg:address":"9777 W Gulf Bank Rd",
    "sg:city":"Houston",
    "sg:classifiers":[
        {
            "category":"Manufacturing",
            "subcategory":"Tools & Machinery",
            "type":"Manufacturing & Wholesale Goods"
        }
    ],
    "sg:phone":"+1 713 896 3600",
    "sg:postcode":"77040",
    "sg:province":"TX",
    "sg:tags":[
        "oil",
        "gas"
    ],
    "sg:website":"www.hycalog.com",
    "wof:name":"Hycalog",
    "wof:placetype":"venue"
},
  "geometry": {"coordinates":[-95.54451899999999,29.87789],"type":"Point"}
}