{
  "type": "Feature",
  "properties": {
    "iso:country":"US",
    "sg:address":"3005 Gordon St",
    "sg:city":"Vernon",
    "sg:classifiers":[
        {
            "category":"Restaurant",
            "type":"Food & Drink"
        }
    ],
    "sg:phone":"+1 940 552 9012",
    "sg:postcode":"76384",
    "sg:province":"TX",
    "wof:name":"Mr Jim's Pizza",
    "wof:placetype":"venue"
},
  "geometry": {"coordinates":[-99.296476,34.14411],"type":"Point"}
}