{
  "type": "Feature",
  "properties": {
    "iso:country":"US",
    "sg:address":"3168 State Hwy 16",
    "sg:city":"Fredericksburg",
    "sg:classifiers":[
        {
            "category":"Manufacturing",
            "subcategory":"Metals",
            "type":"Manufacturing & Wholesale Goods"
        }
    ],
    "sg:phone":"+1 830 997 9391",
    "sg:postcode":"78624",
    "sg:province":"TX",
    "sg:tags":[
        "small",
        "screw",
        "machine",
        "parts",
        "mfg"
    ],
    "wof:name":"Kager Industries",
    "wof:placetype":"venue"
},
  "geometry": {"coordinates":[-98.821568,30.304116],"type":"Point"}
}