{
  "type": "Feature",
  "properties": {
    "iso:country":"US",
    "sg:address":"21820 SE H K Dodgen Loop",
    "sg:city":"Temple",
    "sg:classifiers":[
        {
            "category":"Wholesale",
            "subcategory":"Farm Supplies",
            "type":"Manufacturing & Wholesale Goods"
        },
        {
            "category":"Wholesale",
            "subcategory":"Machinery & Supplies",
            "type":"Manufacturing & Wholesale Goods"
        }
    ],
    "sg:phone":"+1 254 773 5817",
    "sg:postcode":"76504",
    "sg:province":"TX",
    "sg:tags":[
        "baling",
        "equipment"
    ],
    "wof:name":"Farm Equipment Service Inc",
    "wof:placetype":"venue"
},
  "geometry": {"coordinates":[-97.335565,31.059568],"type":"Point"}
}