{
  "type": "Feature",
  "properties": {
    "iso:country":"US",
    "sg:address":"6140 Blue Spruce Cir",
    "sg:city":"Fort Worth",
    "sg:classifiers":[
        {
            "category":"Shopping",
            "subcategory":"Stationery & Office Supplies",
            "type":"Retail Goods"
        }
    ],
    "sg:phone":"+1 817 281 0614",
    "sg:postcode":"76137",
    "sg:province":"TX",
    "wof:name":"Watkins Enterprises",
    "wof:placetype":"venue"
},
  "geometry": {"coordinates":[-97.27859100000001,32.859576],"type":"Point"}
}