{
  "type": "Feature",
  "properties": {
    "iso:country":"US",
    "sg:address":"8842 Welles Edge Dr",
    "sg:city":"San Antonio",
    "sg:classifiers":[
        {
            "category":"Wholesale",
            "subcategory":"Plants",
            "type":"Manufacturing & Wholesale Goods"
        }
    ],
    "sg:phone":"+1 210 696 9842",
    "sg:postcode":"78240",
    "sg:province":"TX",
    "sg:tags":[
        "nursery",
        "tree"
    ],
    "wof:name":"Quality Trees",
    "wof:placetype":"venue"
},
  "geometry": {"coordinates":[-98.608644,29.527413],"type":"Point"}
}