{
  "type": "Feature",
  "properties": {
    "iso:country":"US",
    "sg:address":"1901 Glen Allen St",
    "sg:city":"Austin",
    "sg:classifiers":[
        {
            "category":"Professional",
            "type":"Services"
        }
    ],
    "sg:phone":"+1 512 444 4697",
    "sg:postcode":"78704",
    "sg:province":"TX",
    "wof:name":"Heather Farnsworth (nar)",
    "wof:placetype":"venue"
},
  "geometry": {"coordinates":[-97.780896,30.240909],"type":"Point"}
}