{
  "type": "Feature",
  "properties": {
    "iso:country":"US",
    "sg:address":"710 Rand Rd",
    "sg:city":"Kaufman",
    "sg:classifiers":[
        {
            "category":"Real Estate",
            "subcategory":"Real Estate Operator",
            "type":"Services"
        }
    ],
    "sg:phone":"+1 972 962 2253",
    "sg:postcode":"75142",
    "sg:province":"TX",
    "sg:tags":[
        "mobile",
        "home",
        "site",
        "community"
    ],
    "wof:name":"Village Mobile Home Park",
    "wof:placetype":"venue"
},
  "geometry": {"coordinates":[-96.30358099999999,32.585853],"type":"Point"}
}