{
  "type": "Feature",
  "properties": {
    "iso:country":"US",
    "sg:address":"400 S Harvey St",
    "sg:city":"Borger",
    "sg:classifiers":[
        {
            "category":"Retail",
            "subcategory":"Auto Repair",
            "type":"Services"
        }
    ],
    "sg:phone":"+1 806 274 4761",
    "sg:postcode":"79007",
    "sg:province":"TX",
    "sg:tags":[
        "body",
        "glass",
        "replacement"
    ],
    "wof:name":"B&L Body Shop Inc",
    "wof:placetype":"venue"
},
  "geometry": {"coordinates":[-101.387868,35.662974],"type":"Point"}
}