{
  "type": "Feature",
  "properties": {
    "iso:country":"US",
    "sg:address":"3440 Williams Rd",
    "sg:city":"Fort Worth",
    "sg:classifiers":[
        {
            "category":"Professional",
            "type":"Services"
        }
    ],
    "sg:phone":"+1 817 560 7144",
    "sg:postcode":"76116",
    "sg:province":"TX",
    "wof:name":"National Sports Network",
    "wof:placetype":"venue"
},
  "geometry": {"coordinates":[-97.451453,32.721249],"type":"Point"}
}