{
  "type": "Feature",
  "properties": {
    "iso:country":"US",
    "sg:address":"2202 N Beckley Ave",
    "sg:city":"Dallas",
    "sg:classifiers":[
        {
            "category":"Home & Garden",
            "subcategory":"Home Furnishings",
            "type":"Retail Goods"
        },
        {
            "category":"Commercial Area",
            "type":"Public Place"
        },
        {
            "category":"Manufacturing",
            "subcategory":"Glass & Minerals",
            "type":"Manufacturing & Wholesale Goods"
        },
        {
            "category":"Manufacturing",
            "subcategory":"Building Materials",
            "type":"Manufacturing & Wholesale Goods"
        }
    ],
    "sg:phone":"+1 214 747 4875",
    "sg:postcode":"75208",
    "sg:province":"TX",
    "sg:tags":[
        "plate",
        "door",
        "repair",
        "top",
        "glass-auto",
        "shower",
        "window",
        "mirror",
        "front",
        "replacement",
        "enclosure",
        "store",
        "furniture"
    ],
    "sg:website":"http://www.ocmginc.com",
    "wof:name":"Oak Cliff Mirror & Glass",
    "wof:placetype":"venue"
},
  "geometry": {"coordinates":[-96.822838,32.770031],"type":"Point"}
}