{
  "type": "Feature",
  "properties": {
    "iso:country":"US",
    "sg:address":"1712 Rio Grande St",
    "sg:city":"Austin",
    "sg:classifiers":[
        {
            "category":"Professional",
            "subcategory":"Management & Consulting",
            "type":"Services"
        }
    ],
    "sg:phone":"+1 512 476 0891",
    "sg:postcode":"78701",
    "sg:province":"TX",
    "sg:tags":[
        "commercial",
        "business",
        "physical"
    ],
    "wof:name":"S W C A Environmental Cons",
    "wof:placetype":"venue"
},
  "geometry": {"coordinates":[-97.745341,30.281465],"type":"Point"}
}