{
  "type": "Feature",
  "properties": {
    "iso:country":"US",
    "sg:address":"220 S Cedar Ridge Dr",
    "sg:city":"Duncanville",
    "sg:classifiers":[
        {
            "category":"Banks & Credit Unions",
            "subcategory":"Bank",
            "type":"Services"
        }
    ],
    "sg:phone":"+1 972 283 7150",
    "sg:postcode":"75116",
    "sg:province":"TX",
    "wof:name":"Bank of America",
    "wof:placetype":"venue"
},
  "geometry": {"coordinates":[-96.925697,32.649399],"type":"Point"}
}