{
  "type": "Feature",
  "properties": {
    "iso:country":"US",
    "sg:address":"4601 Buffalo Gap Rd B3",
    "sg:city":"Abilene",
    "sg:classifiers":[
        {
            "category":"Organizations",
            "subcategory":"Community Association",
            "type":"Services"
        }
    ],
    "sg:phone":"+1 325 692 6250",
    "sg:postcode":"79606",
    "sg:province":"TX",
    "wof:name":"Randolph Gilreath & Association Inc",
    "wof:placetype":"venue"
},
  "geometry": {"coordinates":[-99.762693,32.394169],"type":"Point"}
}