{
  "type": "Feature",
  "properties": {
    "iso:country":"US",
    "sg:address":"9548 Deer Trail Dr",
    "sg:city":"Houston",
    "sg:classifiers":[
        {
            "category":"Organizations",
            "subcategory":"Religious Organization",
            "type":"Services"
        }
    ],
    "sg:phone":"+1 281 445 5748",
    "sg:postcode":"77038",
    "sg:province":"TX",
    "sg:tags":[
        "monastery",
        "convent"
    ],
    "wof:name":"Missionary Carmelite Sisters",
    "wof:placetype":"venue"
},
  "geometry": {"coordinates":[-95.42273,29.904384],"type":"Point"}
}