{
  "type": "Feature",
  "properties": {
    "iso:country":"US",
    "sg:address":"2450 Lakeshore Dr",
    "sg:city":"Grapevine",
    "sg:classifiers":[
        {
            "category":"Professional",
            "type":"Services"
        }
    ],
    "sg:phone":"+1 817 488 7390",
    "sg:postcode":"76051",
    "sg:province":"TX",
    "wof:name":"Mitchell 330000599419 Marion",
    "wof:placetype":"venue"
},
  "geometry": {"coordinates":[-97.10486899999999,32.977285],"type":"Point"}
}