{
  "type": "Feature",
  "properties": {
    "iso:country":"US",
    "sg:address":"7231 Alexander Dr",
    "sg:city":"Dallas",
    "sg:classifiers":[
        {
            "category":"Real Estate",
            "subcategory":"Architect",
            "type":"Services"
        }
    ],
    "sg:phone":"+1 214 827 2550",
    "sg:postcode":"75214",
    "sg:province":"TX",
    "sg:tags":[
        "architectural"
    ],
    "wof:name":"Thomas Krahenbuhl Architect",
    "wof:placetype":"venue"
},
  "geometry": {"coordinates":[-96.735069,32.829531],"type":"Point"}
}