{
  "type": "Feature",
  "properties": {
    "iso:country":"US",
    "sg:address":"841 N Belt Line Rd",
    "sg:city":"Irving",
    "sg:classifiers":[
        {
            "category":"Manufacturing",
            "subcategory":"Food",
            "type":"Manufacturing & Wholesale Goods"
        },
        {
            "category":"Wholesale",
            "subcategory":"Groceries",
            "type":"Manufacturing & Wholesale Goods"
        }
    ],
    "sg:phone":"+1 972 986 9794",
    "sg:postcode":"75061",
    "sg:province":"TX",
    "sg:tags":[
        "preparation",
        "product",
        "mfg"
    ],
    "wof:name":"Inchon Food Company",
    "wof:placetype":"venue"
},
  "geometry": {"coordinates":[-96.99393999999999,32.823828],"type":"Point"}
}