{
  "type": "Feature",
  "properties": {
    "iso:country":"US",
    "sg:address":"3930 Bee Caves Rd",
    "sg:city":"Austin",
    "sg:classifiers":[
        {
            "category":"Real Estate",
            "subcategory":"Architect",
            "type":"Services"
        },
        {
            "category":"Building & Trades",
            "subcategory":"Landscaping Services",
            "type":"Services"
        }
    ],
    "sg:phone":"+1 512 327 3388",
    "sg:postcode":"78746",
    "sg:province":"TX",
    "sg:tags":[
        "designer",
        "architectural",
        "landscape"
    ],
    "wof:name":"Russ Bragg Landscape Architect",
    "wof:placetype":"venue"
},
  "geometry": {"coordinates":[-97.80988000000001,30.282519],"type":"Point"}
}