{
  "type": "Feature",
  "properties": {
    "iso:country":"US",
    "sg:address":"2101 FM 1424",
    "sg:city":"Tulia",
    "sg:classifiers":[
        {
            "category":"Farming",
            "subcategory":"Livestock Farm",
            "type":"Manufacturing & Wholesale Goods"
        }
    ],
    "sg:phone":"+1 806 627 4223",
    "sg:postcode":"79088",
    "sg:province":"TX",
    "sg:tags":[
        "ranch",
        "cattle",
        "beef",
        "long",
        "trucking"
    ],
    "wof:name":"Blackwell Trucking",
    "wof:placetype":"venue"
},
  "geometry": {"coordinates":[-101.92044300000001,34.614041],"type":"Point"}
}