{
  "type": "Feature",
  "properties": {
    "iso:country":"US",
    "sg:address":"3525 N 1st St",
    "sg:city":"Abilene",
    "sg:classifiers":[
        {
            "category":"Banks & Credit Unions",
            "subcategory":"Bank",
            "type":"Services"
        }
    ],
    "sg:phone":"+1 325 676 1071",
    "sg:postcode":"79603",
    "sg:province":"TX",
    "sg:tags":[
        "loan"
    ],
    "wof:name":"Sun Loan Co",
    "wof:placetype":"venue"
},
  "geometry": {"coordinates":[-99.768467,32.452065],"type":"Point"}
}