{
  "type": "Feature",
  "properties": {
    "iso:country":"US",
    "sg:address":"3210 Stone Rd",
    "sg:city":"Kilgore",
    "sg:classifiers":[
        {
            "category":"Health Services",
            "subcategory":"Doctor",
            "type":"Services"
        }
    ],
    "sg:phone":"+1 903 984 8556",
    "sg:postcode":"75662",
    "sg:province":"TX",
    "wof:name":"Landry D Duane DDS Inc",
    "wof:placetype":"venue"
},
  "geometry": {"coordinates":[-94.842417,32.38216],"type":"Point"}
}