{
  "type": "Feature",
  "properties": {
    "iso:country":"US",
    "sg:address":"1901 Sunrise Rd",
    "sg:city":"Round Rock",
    "sg:classifiers":[
        {
            "category":"Education",
            "subcategory":"School",
            "type":"Public Place"
        }
    ],
    "sg:phone":"+1 512 464 5000",
    "sg:postcode":"78664",
    "sg:province":"TX",
    "wof:name":"Stony Point 9th Grade Center",
    "wof:placetype":"venue"
},
  "geometry": {"coordinates":[-97.667913,30.531314],"type":"Point"}
}