{
  "type": "Feature",
  "properties": {
    "iso:country":"US",
    "sg:address":"11111 N Central Expy",
    "sg:city":"Dallas",
    "sg:classifiers":[
        {
            "category":"Retail",
            "subcategory":"Laundry & Dry Cleaning",
            "type":"Services"
        }
    ],
    "sg:phone":"+1 214 696 1133",
    "sg:postcode":"75243",
    "sg:province":"TX",
    "sg:tags":[
        "cleaners"
    ],
    "wof:name":"Town & Country Cleaners",
    "wof:placetype":"venue"
},
  "geometry": {"coordinates":[-96.769531,32.899066],"type":"Point"}
}