{
  "type": "Feature",
  "properties": {
    "iso:country":"US",
    "sg:address":"7917 Magna St",
    "sg:city":"Houston",
    "sg:classifiers":[
        {
            "category":"Shopping",
            "subcategory":"Gifts & Souvenirs",
            "type":"Retail Goods"
        }
    ],
    "sg:phone":"+1 713 692 7680",
    "sg:postcode":"77093",
    "sg:province":"TX",
    "wof:name":"AJS Gifts",
    "wof:placetype":"venue"
},
  "geometry": {"coordinates":[-95.33123399999999,29.832318],"type":"Point"}
}