{
  "type": "Feature",
  "properties": {
    "iso:country":"US",
    "sg:address":"9630 Westheimer Rd",
    "sg:city":"Houston",
    "sg:classifiers":[
        {
            "category":"Sports & Exercise",
            "subcategory":"Gym",
            "type":"Entertainment"
        }
    ],
    "sg:phone":"+1 713 952 8400",
    "sg:postcode":"77063",
    "sg:province":"TX",
    "sg:tags":[
        "club",
        "health",
        "studio",
        "gymnasium"
    ],
    "wof:name":"Ladies Workout Express",
    "wof:placetype":"venue"
},
  "geometry": {"coordinates":[-95.53725300000001,29.737223],"type":"Point"}
}