{
  "type": "Feature",
  "properties": {
    "iso:country":"US",
    "sg:address":"4031 N Macarthur Blvd",
    "sg:city":"Irving",
    "sg:classifiers":[
        {
            "category":"Personal",
            "type":"Services"
        }
    ],
    "sg:phone":"+1 972 332 2697",
    "sg:postcode":"75038",
    "sg:province":"TX",
    "sg:tags":[
        "mover"
    ],
    "sg:website":"movers.gaudie.org/Mover/Texas/Ir...",
    "wof:name":"Gaudie Movers",
    "wof:placetype":"venue"
},
  "geometry": {"coordinates":[-96.95929599999999,32.860223],"type":"Point"}
}