{
  "type": "Feature",
  "properties": {
    "iso:country":"US",
    "sg:address":"3115 W Arkansas Ln",
    "sg:city":"Arlington",
    "sg:classifiers":[
        {
            "category":"Manufacturing",
            "subcategory":"Glass & Minerals",
            "type":"Manufacturing & Wholesale Goods"
        },
        {
            "category":"Manufacturing",
            "subcategory":"Signs",
            "type":"Manufacturing & Wholesale Goods"
        }
    ],
    "sg:phone":"+1 817 860 1876",
    "sg:postcode":"76016",
    "sg:province":"TX",
    "sg:tags":[
        "decoration",
        "glassware",
        "specialty",
        "mfg"
    ],
    "wof:name":"Avant Sign & Design Inc",
    "wof:placetype":"venue"
},
  "geometry": {"coordinates":[-97.15707,32.706872],"type":"Point"}
}