{
  "type": "Feature",
  "properties": {
    "iso:country":"US",
    "sg:address":"9100 Wurzbach Rd",
    "sg:city":"San Antonio",
    "sg:classifiers":[
        {
            "category":"Retail",
            "subcategory":"Veterinary Services",
            "type":"Services"
        }
    ],
    "sg:phone":"+1 210 614 5145",
    "sg:postcode":"78240",
    "sg:province":"TX",
    "sg:tags":[
        "clinic"
    ],
    "wof:name":"Turtle Creek Animal Hospital",
    "wof:placetype":"venue"
},
  "geometry": {"coordinates":[-98.567503,29.525568],"type":"Point"}
}