{
  "type": "Feature",
  "properties": {
    "iso:country":"US",
    "sg:address":"400 W 15th St",
    "sg:city":"Austin",
    "sg:classifiers":[
        {
            "category":"Professional",
            "subcategory":"Lawyer & Legal Services",
            "type":"Services"
        }
    ],
    "sg:phone":"+1 512 472 0404",
    "sg:postcode":"78701",
    "sg:province":"TX",
    "sg:tags":[
        "planning",
        "estate"
    ],
    "wof:name":"Leonard B Gabbay PC",
    "wof:placetype":"venue"
},
  "geometry": {"coordinates":[-97.74403700000001,30.27826],"type":"Point"}
}