{
  "type": "Feature",
  "properties": {
    "iso:country":"US",
    "sg:address":"5512 S Willow Dr",
    "sg:city":"Houston",
    "sg:classifiers":[
        {
            "category":"Building & Trades",
            "subcategory":"Pest Control",
            "type":"Services"
        }
    ],
    "sg:phone":"+1 713 522 3331",
    "sg:postcode":"77035",
    "sg:province":"TX",
    "wof:name":"VP Exterminators",
    "wof:placetype":"venue"
},
  "geometry": {"coordinates":[-95.47477000000001,29.652859],"type":"Point"}
}