{
  "type": "Feature",
  "properties": {
    "iso:country":"US",
    "sg:address":"1551 Corporate Dr",
    "sg:city":"Irving",
    "sg:classifiers":[
        {
            "category":"Travel",
            "subcategory":"Travel Agent",
            "type":"Entertainment"
        }
    ],
    "sg:phone":"+1 972 580 1881",
    "sg:postcode":"75038",
    "sg:province":"TX",
    "sg:tags":[
        "agency"
    ],
    "wof:name":"Carlson Wagonlit Travel",
    "wof:placetype":"venue"
},
  "geometry": {"coordinates":[-96.978419,32.888323],"type":"Point"}
}