{
  "type": "Feature",
  "properties": {
    "iso:country":"US",
    "sg:address":"6313 Burnet Rd",
    "sg:city":"Austin",
    "sg:classifiers":[
        {
            "category":"Autos & Motor Vehicles",
            "subcategory":"Auto Supplies",
            "type":"Retail Goods"
        }
    ],
    "sg:phone":"+1 512 452 9394",
    "sg:postcode":"78757",
    "sg:province":"TX",
    "sg:tags":[
        "automobile",
        "part",
        "repair"
    ],
    "sg:website":"www.autozone.com",
    "wof:name":"Autozone",
    "wof:placetype":"venue"
},
  "geometry": {"coordinates":[-97.738769,30.338223],"type":"Point"}
}