{
  "type": "Feature",
  "properties": {
    "iso:country":"US",
    "sg:address":"3920 Cedar Springs Rd",
    "sg:city":"Dallas",
    "sg:classifiers":[
        {
            "category":"Shopping",
            "subcategory":"Clothing, Apparel, & Fashions",
            "type":"Retail Goods"
        }
    ],
    "sg:phone":"+1 214 528 9600",
    "sg:postcode":"75219",
    "sg:province":"TX",
    "sg:tags":[
        "sportswear"
    ],
    "sg:website":"http://www.unionjack.com",
    "wof:name":"Union Jack",
    "wof:placetype":"venue"
},
  "geometry": {"coordinates":[-96.810205,32.810213],"type":"Point"}
}