{
  "type": "Feature",
  "properties": {
    "iso:country":"US",
    "sg:address":"1100 Gumwood Ave",
    "sg:city":"Mcallen",
    "sg:classifiers":[
        {
            "category":"Education",
            "subcategory":"School",
            "type":"Public Place"
        }
    ],
    "sg:phone":"+1 956 686 3651",
    "sg:postcode":"78501",
    "sg:province":"TX",
    "sg:tags":[
        "organization",
        "religious"
    ],
    "wof:name":"Our Lady Of Sorrows School",
    "wof:placetype":"venue"
},
  "geometry": {"coordinates":[-98.231179,26.209996],"type":"Point"}
}