{
  "type": "Feature",
  "properties": {
    "iso:country":"US",
    "sg:address":"19905 Angel Bay Dr",
    "sg:city":"Spicewood",
    "sg:classifiers":[
        {
            "category":"Professional",
            "subcategory":"Management & Consulting",
            "type":"Services"
        }
    ],
    "sg:phone":"+1 512 264 8026",
    "sg:postcode":"78669",
    "sg:province":"TX",
    "sg:tags":[
        "business"
    ],
    "wof:name":"Regulatory Interlinx Inc",
    "wof:placetype":"venue"
},
  "geometry": {"coordinates":[-98.009147,30.400638],"type":"Point"}
}