{
  "type": "Feature",
  "properties": {
    "iso:country":"US",
    "sg:address":"1300 Green Oaks Rd",
    "sg:city":"Fort Worth",
    "sg:classifiers":[
        {
            "category":"Shopping",
            "type":"Retail Goods"
        }
    ],
    "sg:phone":"+1 817 763 8387",
    "sg:postcode":"76116",
    "sg:province":"TX",
    "sg:tags":[
        "veterinary",
        "merchandise"
    ],
    "wof:name":"Banfield The Pet Hospital",
    "wof:placetype":"venue"
},
  "geometry": {"coordinates":[-97.433789,32.749203],"type":"Point"}
}