{
  "type": "Feature",
  "properties": {
    "iso:country":"US",
    "sg:address":"14914 Carla Ct",
    "sg:city":"Conroe",
    "sg:classifiers":[
        {
            "category":"Wholesale",
            "subcategory":"Machinery & Supplies",
            "type":"Manufacturing & Wholesale Goods"
        }
    ],
    "sg:phone":"+1 281 429 7874",
    "sg:postcode":"77302",
    "sg:province":"TX",
    "sg:tags":[
        "equipment",
        "industrial"
    ],
    "wof:name":"Marcos Valdez Co",
    "wof:placetype":"venue"
},
  "geometry": {"coordinates":[-95.348671,30.190588],"type":"Point"}
}