{
  "type": "Feature",
  "properties": {
    "iso:country":"US",
    "sg:address":"630 112th St",
    "sg:city":"Arlington",
    "sg:phone":"+1 817 469 1090",
    "sg:postcode":"76011",
    "sg:province":"TX",
    "wof:name":"Mbr Guaranteed Foundation",
    "wof:placetype":"venue"
},
  "geometry": {"coordinates":[-97.047732,32.749747],"type":"Point"}
}