{
  "type": "Feature",
  "properties": {
    "iso:country":"US",
    "sg:address":"460 S Belt Line Rd",
    "sg:city":"Irving",
    "sg:classifiers":[
        {
            "category":"Freight",
            "type":"Transportation"
        }
    ],
    "sg:phone":"+1 972 514 6059",
    "sg:postcode":"75060",
    "sg:province":"TX",
    "sg:tags":[
        "operator",
        "local",
        "trucking"
    ],
    "wof:name":"All Snax",
    "wof:placetype":"venue"
},
  "geometry": {"coordinates":[-96.993965,32.809676],"type":"Point"}
}