{
  "type": "Feature",
  "properties": {
    "iso:country":"US",
    "sg:address":"2863 Everett Dr",
    "sg:city":"La Marque",
    "sg:classifiers":[
        {
            "category":"Shopping",
            "subcategory":"Gifts & Souvenirs",
            "type":"Retail Goods"
        }
    ],
    "sg:phone":"+1 409 938 8864",
    "sg:postcode":"77546",
    "sg:province":"TX",
    "sg:tags":[
        "announcement",
        "wedding",
        "invitation"
    ],
    "wof:name":"Allstar Printing",
    "wof:placetype":"venue"
},
  "geometry": {"coordinates":[-95.22327199999999,29.472353],"type":"Point"}
}