{
  "type": "Feature",
  "properties": {
    "iso:country":"US",
    "sg:address":"2606 Irving Blvd",
    "sg:city":"Dallas",
    "sg:classifiers":[
        {
            "category":"Home & Garden",
            "subcategory":"Furniture",
            "type":"Retail Goods"
        }
    ],
    "sg:phone":"+1 214 905 1100",
    "sg:postcode":"75207",
    "sg:province":"TX",
    "sg:tags":[
        "store"
    ],
    "sg:website":"www.jetfurniture.com",
    "wof:name":"Jet Furniture",
    "wof:placetype":"venue"
},
  "geometry": {"coordinates":[-96.842281,32.80123],"type":"Point"}
}