{
  "type": "Feature",
  "properties": {
    "iso:country":"US",
    "sg:address":"120 N Sugar Rd",
    "sg:city":"Pharr",
    "sg:classifiers":[
        {
            "category":"Shopping",
            "subcategory":"Clothing, Apparel, & Fashions",
            "type":"Retail Goods"
        }
    ],
    "sg:phone":"+1 956 787 1510",
    "sg:postcode":"78577",
    "sg:province":"TX",
    "sg:tags":[
        "work",
        "uniform",
        "uniforms-accessories",
        "clothes"
    ],
    "wof:name":"Second Look",
    "wof:placetype":"venue"
},
  "geometry": {"coordinates":[-98.19567600000001,26.19782],"type":"Point"}
}