{
  "type": "Feature",
  "properties": {
    "iso:country":"US",
    "sg:address":"501 E Nolana Ave",
    "sg:city":"Mcallen",
    "sg:classifiers":[
        {
            "category":"Restaurant",
            "type":"Food & Drink"
        }
    ],
    "sg:menulink":"http://www.allmenus.com/tx/mcallen-pharr/115065-chilis/menu/",
    "sg:phone":"+1 956 668 0326",
    "sg:postcode":"78504",
    "sg:province":"TX",
    "sg:tags":[
        "burger",
        "american",
        "sandwich",
        "tex-mex",
        "soup"
    ],
    "wof:name":"Chili's",
    "wof:placetype":"venue"
},
  "geometry": {"coordinates":[-98.20907699999999,26.237688],"type":"Point"}
}