{
  "type": "Feature",
  "properties": {
    "iso:country":"US",
    "sg:address":"118 Oak Hollow St",
    "sg:city":"Conroe",
    "sg:classifiers":[
        {
            "category":"Food & Beverages",
            "subcategory":"Groceries & Convenience Stores",
            "type":"Retail Goods"
        }
    ],
    "sg:phone":"+1 936 539 6434",
    "sg:postcode":"77301",
    "sg:province":"TX",
    "sg:tags":[
        "notion"
    ],
    "wof:name":"C J S Kuntry Threads",
    "wof:placetype":"venue"
},
  "geometry": {"coordinates":[-95.466015,30.319737],"type":"Point"}
}