{
  "type": "Feature",
  "properties": {
    "iso:country":"US",
    "sg:address":"524 S Alabama Dr",
    "sg:city":"Celina",
    "sg:classifiers":[
        {
            "category":"Manufacturing",
            "subcategory":"Jewelry",
            "type":"Manufacturing & Wholesale Goods"
        }
    ],
    "sg:phone":"+1 972 382 2428",
    "sg:postcode":"75009",
    "sg:province":"TX",
    "sg:tags":[
        "costume",
        "mfg"
    ],
    "wof:name":"Kelly B Sherwood",
    "wof:placetype":"venue"
},
  "geometry": {"coordinates":[-96.79367499999999,33.319683],"type":"Point"}
}