{
  "type": "Feature",
  "properties": {
    "iso:country":"US",
    "sg:address":"113 N Wilson St",
    "sg:city":"Burleson",
    "sg:classifiers":[
        {
            "category":"Personal",
            "subcategory":"Beauty Salon",
            "type":"Services"
        }
    ],
    "sg:phone":"+1 817 295 4434",
    "sg:postcode":"76028",
    "sg:province":"TX",
    "sg:tags":[
        "shop"
    ],
    "wof:name":"Talkin Scssors Hair Nail Dsign",
    "wof:placetype":"venue"
},
  "geometry": {"coordinates":[-97.322222,32.543551],"type":"Point"}
}