{
  "type": "Feature",
  "properties": {
    "iso:country":"US",
    "sg:address":"7015 Snider Plz",
    "sg:city":"Dallas",
    "sg:classifiers":[
        {
            "category":"Shopping",
            "subcategory":"Bicycles & Sporting Goods",
            "type":"Retail Goods"
        },
        {
            "category":"Sports & Exercise",
            "subcategory":"Bicycle Rental",
            "type":"Entertainment"
        },
        {
            "category":"Parking",
            "subcategory":"Bicycle",
            "type":"Transportation"
        }
    ],
    "sg:phone":"+1 214 363 2025",
    "sg:postcode":"75205",
    "sg:province":"TX",
    "sg:tags":[
        "shop",
        "system",
        "bicycles-repair",
        "bike",
        "security",
        "rack",
        "bicycles-renting"
    ],
    "sg:website":"www.bicyclesplustx.net/",
    "wof:name":"Bicycles Plus",
    "wof:placetype":"venue"
},
  "geometry": {"coordinates":[-96.787903,32.850399],"type":"Point"}
}