{
  "type": "Feature",
  "properties": {
    "iso:country":"US",
    "sg:address":"925 W Stenger St",
    "sg:city":"San Benito",
    "sg:classifiers":[
        {
            "category":"Government",
            "subcategory":"Office",
            "type":"Public Place"
        }
    ],
    "sg:phone":"+1 956 361 3890",
    "sg:postcode":"78586",
    "sg:province":"TX",
    "sg:tags":[
        "village"
    ],
    "wof:name":"San Benito City Shop",
    "wof:placetype":"venue"
},
  "geometry": {"coordinates":[-97.63670500000001,26.137561],"type":"Point"}
}