{
  "type": "Feature",
  "properties": {
    "iso:country":"US",
    "sg:address":"5400 Mimosa Ln",
    "sg:city":"Richmond",
    "sg:classifiers":[
        {
            "category":"Banks & Credit Unions",
            "subcategory":"Bank",
            "type":"Services"
        }
    ],
    "sg:phone":"+1 281 341 0001",
    "sg:postcode":"77469",
    "sg:province":"TX",
    "sg:tags":[
        "financial"
    ],
    "wof:name":"C & K Investments",
    "wof:placetype":"venue"
},
  "geometry": {"coordinates":[-95.791562,29.637085],"type":"Point"}
}