{
  "type": "Feature",
  "properties": {
    "iso:country":"US",
    "sg:address":"1323 N Lee Trevino Dr",
    "sg:city":"El Paso",
    "sg:classifiers":[
        {
            "category":"Real Estate",
            "subcategory":"Real Estate Operator",
            "type":"Services"
        }
    ],
    "sg:phone":"+1 915 593 6674",
    "sg:postcode":"79936",
    "sg:province":"TX",
    "sg:tags":[
        "mall",
        "shopping",
        "center"
    ],
    "wof:name":"Trevino Mall Office",
    "wof:placetype":"venue"
},
  "geometry": {"coordinates":[-106.32292200000001,31.741898],"type":"Point"}
}