{
  "type": "Feature",
  "properties": {
    "iso:country":"US",
    "sg:address":"5820 Trailridge Dr",
    "sg:city":"Austin",
    "sg:classifiers":[
        {
            "category":"Professional",
            "subcategory":"Art Services",
            "type":"Services"
        }
    ],
    "sg:phone":"+1 512 453 4737",
    "sg:postcode":"78731",
    "sg:province":"TX",
    "sg:tags":[
        "commercial",
        "design",
        "business"
    ],
    "wof:name":"Kitchens For Cooks",
    "wof:placetype":"venue"
},
  "geometry": {"coordinates":[-97.75848499999999,30.342365],"type":"Point"}
}