{
  "type": "Feature",
  "properties": {
    "iso:country":"US",
    "sg:address":"3101 W Normandale St",
    "sg:city":"Fort Worth",
    "sg:classifiers":[
        {
            "category":"Real Estate",
            "subcategory":"Real Estate Operator",
            "type":"Services"
        }
    ],
    "sg:phone":"+1 817 244 6154",
    "sg:postcode":"76116",
    "sg:province":"TX",
    "sg:tags":[
        "building",
        "apartment"
    ],
    "wof:name":"Hills Apartments",
    "wof:placetype":"venue"
},
  "geometry": {"coordinates":[-97.47829299999999,32.727494],"type":"Point"}
}