{
  "type": "Feature",
  "properties": {
    "iso:country":"US",
    "sg:address":"701 N Post Oak Rd Ste 204",
    "sg:city":"Houston",
    "sg:classifiers":[
        {
            "category":"Building & Trades",
            "subcategory":"Construction",
            "type":"Services"
        }
    ],
    "sg:phone":"+1 713 683 9994",
    "sg:postcode":"77024",
    "sg:province":"TX",
    "sg:tags":[
        "contractor"
    ],
    "wof:name":"Vallone & Co Custom Homes",
    "wof:placetype":"venue"
},
  "geometry": {"coordinates":[-95.456802,29.7796],"type":"Point"}
}