{
  "type": "Feature",
  "properties": {
    "iso:country":"US",
    "sg:address":"3099 Rockwell Ave",
    "sg:city":"Beaumont",
    "sg:classifiers":[
        {
            "category":"Retail",
            "subcategory":"Repair Shop",
            "type":"Services"
        }
    ],
    "sg:phone":"+1 409 832 4470",
    "sg:postcode":"77701",
    "sg:province":"TX",
    "wof:name":"Sullivans Furniture Repair",
    "wof:placetype":"venue"
},
  "geometry": {"coordinates":[-94.1178,30.056825],"type":"Point"}
}