{
  "type": "Feature",
  "properties": {
    "iso:country":"US",
    "sg:address":"3228 E 5th St",
    "sg:city":"Austin",
    "sg:classifiers":[
        {
            "category":"Retail",
            "subcategory":"Auto Repair",
            "type":"Services"
        }
    ],
    "sg:phone":"+1 512 389 2460",
    "sg:postcode":"78702",
    "sg:province":"TX",
    "sg:tags":[
        "general"
    ],
    "wof:name":"Elite Auto Works",
    "wof:placetype":"venue"
},
  "geometry": {"coordinates":[-97.70602100000001,30.254975],"type":"Point"}
}