{
  "type": "Feature",
  "properties": {
    "iso:country":"US",
    "sg:address":"8024 Beechwood Dr",
    "sg:city":"Fort Worth",
    "sg:classifiers":[
        {
            "category":"Professional",
            "subcategory":"Secretarial Services",
            "type":"Services"
        }
    ],
    "sg:phone":"+1 817 560 0275",
    "sg:postcode":"76116",
    "sg:province":"TX",
    "sg:tags":[
        "reporting"
    ],
    "wof:name":"Sues Scoping Service",
    "wof:placetype":"venue"
},
  "geometry": {"coordinates":[-97.455084,32.712608],"type":"Point"}
}