{
  "type": "Feature",
  "properties": {
    "iso:country":"US",
    "sg:address":"4236 Ridgecrest Dr",
    "sg:city":"El Paso",
    "sg:classifiers":[
        {
            "category":"Building & Trades",
            "subcategory":"Landscaping Services",
            "type":"Services"
        }
    ],
    "sg:phone":"+1 915 533 2342",
    "sg:postcode":"79902",
    "sg:province":"TX",
    "wof:name":"Pearson Tree Place",
    "wof:placetype":"venue"
},
  "geometry": {"coordinates":[-106.508612,31.799491],"type":"Point"}
}