{
  "type": "Feature",
  "properties": {
    "iso:country":"US",
    "sg:address":"801 Texas Ave",
    "sg:city":"Lubbock",
    "sg:classifiers":[
        {
            "category":"Government",
            "subcategory":"Office",
            "type":"Public Place"
        }
    ],
    "sg:phone":"+1 806 712 2000",
    "sg:postcode":"79401",
    "sg:province":"TX",
    "sg:tags":[
        "village"
    ],
    "wof:name":"Citibus",
    "wof:placetype":"venue"
},
  "geometry": {"coordinates":[-101.845645,33.587385],"type":"Point"}
}