{
  "type": "Feature",
  "properties": {
    "iso:country":"US",
    "sg:address":"4420 Fieldglen Ct",
    "sg:city":"League City",
    "sg:classifiers":[
        {
            "category":"Wholesale",
            "subcategory":"Non-durable Goods",
            "type":"Manufacturing & Wholesale Goods"
        }
    ],
    "sg:phone":"+1 281 332 7323",
    "sg:postcode":"77573",
    "sg:province":"TX",
    "sg:tags":[
        "advertising"
    ],
    "wof:name":"Jackson Co",
    "wof:placetype":"venue"
},
  "geometry": {"coordinates":[-95.138598,29.492975],"type":"Point"}
}