{
  "type": "Feature",
  "properties": {
    "iso:country":"US",
    "sg:address":"400 Durham Dr",
    "sg:city":"Arlington",
    "sg:classifiers":[
        {
            "category":"Arts & Performance",
            "subcategory":"Dance",
            "type":"Entertainment"
        }
    ],
    "sg:phone":"+1 817 468 1771",
    "sg:postcode":"76014",
    "sg:province":"TX",
    "sg:tags":[
        "instruction",
        "dancing"
    ],
    "wof:name":"Arlington Dance Academy",
    "wof:placetype":"venue"
},
  "geometry": {"coordinates":[-97.10681200000001,32.699471],"type":"Point"}
}