{
  "type": "Feature",
  "properties": {
    "iso:country":"US",
    "sg:address":"4514 Travis St Ste 101",
    "sg:city":"Dallas",
    "sg:classifiers":[
        {
            "category":"Bars & Pubs",
            "subcategory":"Wine Bar",
            "type":"Food & Drink"
        }
    ],
    "sg:phone":"+1 214 528 9463",
    "sg:postcode":"75205",
    "sg:province":"TX",
    "sg:website":"www.chateauwinemarket.com/bodega...",
    "wof:name":"Bodega Wine Bar",
    "wof:placetype":"venue"
},
  "geometry": {"coordinates":[-96.79053999999999,32.822368],"type":"Point"}
}