{
  "type": "Feature",
  "properties": {
    "iso:country":"US",
    "sg:address":"4606 Purlane",
    "sg:city":"San Antonio",
    "sg:classifiers":[
        {
            "category":"Building & Trades",
            "subcategory":"Landscaping Services",
            "type":"Services"
        }
    ],
    "sg:phone":"+1 210 404 2984",
    "sg:postcode":"78247",
    "sg:province":"TX",
    "wof:name":"Alamo Tree Landscape & Lawn",
    "wof:placetype":"venue"
},
  "geometry": {"coordinates":[-98.40223899999999,29.584514],"type":"Point"}
}