{
  "type": "Feature",
  "properties": {
    "iso:country":"US",
    "sg:address":"600 N Shady Shores Dr",
    "sg:city":"Lake Dallas",
    "sg:classifiers":[
        {
            "category":"Organizations",
            "subcategory":"Religious Organization",
            "type":"Services"
        }
    ],
    "sg:phone":"+1 940 321 6020",
    "sg:postcode":"75065",
    "sg:province":"TX",
    "sg:tags":[
        "house",
        "retreat"
    ],
    "wof:name":"Montsrrate Jesuite Retreat Hse",
    "wof:placetype":"venue"
},
  "geometry": {"coordinates":[-97.02988999999999,33.13395],"type":"Point"}
}