{
  "type": "Feature",
  "properties": {
    "iso:country":"US",
    "sg:address":"3030 Tanglewood Park W",
    "sg:city":"Fort Worth",
    "sg:classifiers":[
        {
            "category":"Education",
            "subcategory":"Dance Studio",
            "type":"Public Place"
        }
    ],
    "sg:phone":"+1 817 926 9686",
    "sg:postcode":"76109",
    "sg:province":"TX",
    "wof:name":"Encore Prfrmg Arts Showcase",
    "wof:placetype":"venue"
},
  "geometry": {"coordinates":[-97.38635499999999,32.708038],"type":"Point"}
}