{
  "type": "Feature",
  "properties": {
    "iso:country":"US",
    "sg:address":"1409 E Denman Ave",
    "sg:city":"Lufkin",
    "sg:classifiers":[
        {
            "category":"Home & Garden",
            "subcategory":"Home Furnishings",
            "type":"Retail Goods"
        }
    ],
    "sg:phone":"+1 936 639 5826",
    "sg:postcode":"75901",
    "sg:province":"TX",
    "sg:tags":[
        "equipment",
        "fireplace"
    ],
    "wof:name":"Hunt Stone & Fireplace",
    "wof:placetype":"venue"
},
  "geometry": {"coordinates":[-94.708307,31.323525],"type":"Point"}
}