{
  "type": "Feature",
  "properties": {
    "iso:country":"US",
    "sg:address":"8730 Overhill Ln",
    "sg:city":"Beaumont",
    "sg:classifiers":[
        {
            "category":"Building & Trades",
            "subcategory":"Construction",
            "type":"Services"
        }
    ],
    "sg:phone":"+1 409 860 3481",
    "sg:postcode":"77707",
    "sg:province":"TX",
    "sg:tags":[
        "wallpaper"
    ],
    "wof:name":"Gallet's Painting",
    "wof:placetype":"venue"
},
  "geometry": {"coordinates":[-94.191104,30.073721],"type":"Point"}
}