{
  "type": "Feature",
  "properties": {
    "iso:country":"US",
    "sg:address":"6206 State Hwy 6",
    "sg:city":"Houston",
    "sg:classifiers":[
        {
            "category":"Social Services",
            "subcategory":"Child Care",
            "type":"Services"
        }
    ],
    "sg:phone":"+1 281 561 5830",
    "sg:postcode":"77083",
    "sg:province":"TX",
    "sg:tags":[
        "center"
    ],
    "wof:name":"Alois Love N Care",
    "wof:placetype":"venue"
},
  "geometry": {"coordinates":[-95.64410100000001,29.710752],"type":"Point"}
}