{
  "type": "Feature",
  "properties": {
    "iso:country":"US",
    "sg:address":"7647 Park Place Blvd",
    "sg:city":"Houston",
    "sg:classifiers":[
        {
            "category":"Shopping",
            "subcategory":"Computers & Home Electronics",
            "type":"Retail Goods"
        }
    ],
    "sg:phone":"+1 713 847 9238",
    "sg:postcode":"77087",
    "sg:province":"TX",
    "wof:name":"Patricia Vobarrubias",
    "wof:placetype":"venue"
},
  "geometry": {"coordinates":[-95.287499,29.685418],"type":"Point"}
}