{
  "type": "Feature",
  "properties": {
    "iso:country":"US",
    "sg:address":"8445 Hughes Cir",
    "sg:city":"El Paso",
    "sg:classifiers":[
        {
            "category":"Professional",
            "subcategory":"Computer Services",
            "type":"Services"
        }
    ],
    "sg:phone":"+1 915 859 8045",
    "sg:postcode":"79907",
    "sg:province":"TX",
    "wof:name":"Network Tech",
    "wof:placetype":"venue"
},
  "geometry": {"coordinates":[-106.34249800000001,31.710938],"type":"Point"}
}