{
  "type": "Feature",
  "properties": {
    "iso:country":"US",
    "sg:address":"304 E Mockingbird Ln",
    "sg:city":"Victoria",
    "sg:classifiers":[
        {
            "category":"Autos & Motor Vehicles",
            "subcategory":"Automobile Sales",
            "type":"Retail Goods"
        }
    ],
    "sg:phone":"+1 361 570 9977",
    "sg:postcode":"77904",
    "sg:province":"TX",
    "sg:tags":[
        "dealers-used",
        "car",
        "used",
        "cars-wholesale"
    ],
    "wof:name":"Parker Motor Co",
    "wof:placetype":"venue"
},
  "geometry": {"coordinates":[-97.00371699999999,28.83527],"type":"Point"}
}