{
  "type": "Feature",
  "properties": {
    "iso:country":"US",
    "sg:address":"5414 Cedar Springs Rd",
    "sg:city":"Dallas",
    "sg:classifiers":[
        {
            "category":"Insurance",
            "subcategory":"Insurance Agent",
            "type":"Services"
        }
    ],
    "sg:phone":"+1 214 522 4038",
    "sg:postcode":"75235",
    "sg:province":"TX",
    "wof:name":"Adriana's Insurance",
    "wof:placetype":"venue"
},
  "geometry": {"coordinates":[-96.828586,32.823711],"type":"Point"}
}