{
  "type": "Feature",
  "properties": {
    "iso:country":"US",
    "sg:address":"9440 Weichold",
    "sg:city":"Converse",
    "sg:classifiers":[
        {
            "category":"Real Estate",
            "subcategory":"Real Estate Operator",
            "type":"Services"
        }
    ],
    "sg:phone":"+1 210 658 8122",
    "sg:postcode":"78109",
    "sg:province":"TX",
    "sg:tags":[
        "apartment"
    ],
    "wof:name":"American Towers Corp.",
    "wof:placetype":"venue"
},
  "geometry": {"coordinates":[-98.300552,29.467508],"type":"Point"}
}