{
  "type": "Feature",
  "properties": {
    "iso:country":"US",
    "sg:address":"9090 Skillman St",
    "sg:city":"Dallas",
    "sg:classifiers":[
        {
            "category":"Real Estate",
            "subcategory":"Real Estate Services",
            "type":"Services"
        },
        {
            "category":"Real Estate",
            "subcategory":"Real Estate Agent",
            "type":"Services"
        }
    ],
    "sg:phone":"+1 214 272 2330",
    "sg:postcode":"75243",
    "sg:province":"TX",
    "sg:website":"www.ezbuyforeclosured.com",
    "wof:name":"Dallas Buy Foreclosures",
    "wof:placetype":"venue"
},
  "geometry": {"coordinates":[-96.721745,32.896579],"type":"Point"}
}