{
  "type": "Feature",
  "properties": {
    "iso:country":"US",
    "sg:address":"205 M L King Dr",
    "sg:city":"Commerce",
    "sg:classifiers":[
        {
            "category":"Organizations",
            "subcategory":"Religious Organization",
            "type":"Services"
        }
    ],
    "sg:phone":"+1 903 886 6781",
    "sg:postcode":"75428",
    "sg:province":"TX",
    "sg:tags":[
        "church"
    ],
    "wof:name":"Griffith Chapel Methodist",
    "wof:placetype":"venue"
},
  "geometry": {"coordinates":[-95.892752,33.251457],"type":"Point"}
}