{
  "type": "Feature",
  "properties": {
    "iso:country":"US",
    "sg:address":"11150 Beamer Rd",
    "sg:city":"Houston",
    "sg:classifiers":[
        {
            "category":"Building & Trades",
            "subcategory":"Construction",
            "type":"Services"
        }
    ],
    "sg:phone":"+1 281 476 0824",
    "sg:postcode":"77089",
    "sg:province":"TX",
    "sg:tags":[
        "contractor"
    ],
    "wof:name":"Kallimarmaro",
    "wof:placetype":"venue"
},
  "geometry": {"coordinates":[-95.22795499999999,29.60979],"type":"Point"}
}