{
  "type": "Feature",
  "properties": {
    "iso:country":"US",
    "sg:address":"13421 Woodforest Blvd",
    "sg:city":"Houston",
    "sg:classifiers":[
        {
            "category":"Personal",
            "subcategory":"Beauty Salon",
            "type":"Services"
        }
    ],
    "sg:phone":"+1 713 455 1444",
    "sg:postcode":"77015",
    "sg:province":"TX",
    "sg:tags":[
        "shop"
    ],
    "wof:name":"Mane Street-The Salon",
    "wof:placetype":"venue"
},
  "geometry": {"coordinates":[-95.18678800000001,29.791891],"type":"Point"}
}