{
  "type": "Feature",
  "properties": {
    "iso:country":"US",
    "sg:address":"3829 Call Field Rd",
    "sg:city":"Wichita Falls",
    "sg:classifiers":[
        {
            "category":"Shopping",
            "type":"Retail Goods"
        }
    ],
    "sg:phone":"+1 940 691 4888",
    "sg:postcode":"76308",
    "sg:province":"TX",
    "sg:tags":[
        "merchandise"
    ],
    "wof:name":"Outback Pools & Spas",
    "wof:placetype":"venue"
},
  "geometry": {"coordinates":[-98.542075,33.871266],"type":"Point"}
}