{
  "type": "Feature",
  "properties": {
    "iso:country":"US",
    "sg:address":"4003 Cloudy Ridge Rd",
    "sg:city":"Austin",
    "sg:classifiers":[
        {
            "category":"Professional",
            "subcategory":"Art Services",
            "type":"Services"
        }
    ],
    "sg:phone":"+1 512 266 1391",
    "sg:postcode":"78734",
    "sg:province":"TX",
    "sg:tags":[
        "photography",
        "photographers-commercial",
        "commercial"
    ],
    "wof:name":"R Greg Hursley Inc",
    "wof:placetype":"venue"
},
  "geometry": {"coordinates":[-97.91536600000001,30.392694],"type":"Point"}
}