{
  "type": "Feature",
  "properties": {
    "iso:country":"US",
    "sg:address":"3616 Statler Dr",
    "sg:city":"Mesquite",
    "sg:classifiers":[
        {
            "category":"Arts & Performance",
            "subcategory":"Theater",
            "type":"Entertainment"
        }
    ],
    "sg:phone":"+1 972 279 3068",
    "sg:postcode":"75150",
    "sg:province":"TX",
    "sg:tags":[
        "group"
    ],
    "wof:name":"King Pins",
    "wof:placetype":"venue"
},
  "geometry": {"coordinates":[-96.656493,32.817185],"type":"Point"}
}