{
  "type": "Feature",
  "properties": {
    "iso:country":"US",
    "sg:address":"510 Bering Dr",
    "sg:city":"Houston",
    "sg:classifiers":[
        {
            "category":"Professional",
            "subcategory":"Business Services",
            "type":"Services"
        },
        {
            "category":"Real Estate",
            "subcategory":"Real Estate Operator",
            "type":"Services"
        }
    ],
    "sg:phone":"+1 713 968 7500",
    "sg:postcode":"77057",
    "sg:province":"TX",
    "sg:tags":[
        "building",
        "paging",
        "answering",
        "nonresidential"
    ],
    "wof:name":"Businessuites LLC",
    "wof:placetype":"venue"
},
  "geometry": {"coordinates":[-95.478545,29.765154],"type":"Point"}
}