{
  "type": "Feature",
  "properties": {
    "iso:country":"US",
    "sg:address":"3322 Spring Ave",
    "sg:city":"Dallas",
    "sg:classifiers":[
        {
            "category":"Banks & Credit Unions",
            "subcategory":"Investment Brokerage",
            "type":"Services"
        }
    ],
    "sg:phone":"+1 214 426 0555",
    "sg:postcode":"75215",
    "sg:province":"TX",
    "wof:name":"Tenancy-In-Common Investments",
    "wof:placetype":"venue"
},
  "geometry": {"coordinates":[-96.75332899999999,32.764425],"type":"Point"}
}