{
  "type": "Feature",
  "properties": {
    "iso:country":"US",
    "sg:address":"17124 East Fwy",
    "sg:city":"Channelview",
    "sg:classifiers":[
        {
            "category":"Retail",
            "subcategory":"Auto Repair",
            "type":"Services"
        }
    ],
    "sg:phone":"+1 281 452 4230",
    "sg:postcode":"77530",
    "sg:province":"TX",
    "sg:tags":[
        "automotive"
    ],
    "wof:name":"Roberson Diesel Road Service",
    "wof:placetype":"venue"
},
  "geometry": {"coordinates":[-95.090253,29.790038],"type":"Point"}
}