{
  "type": "Feature",
  "properties": {
    "iso:country":"US",
    "sg:address":"1602 W Louisiana Ave",
    "sg:city":"Midland",
    "sg:classifiers":[
        {
            "category":"Communications",
            "subcategory":"Film & Video Production",
            "type":"Services"
        }
    ],
    "sg:phone":"+1 432 682 0050",
    "sg:postcode":"79701",
    "sg:province":"TX",
    "sg:tags":[
        "taping"
    ],
    "wof:name":"Newcomer Videography",
    "wof:placetype":"venue"
},
  "geometry": {"coordinates":[-102.095006,32.00075],"type":"Point"}
}