{
  "type": "Feature",
  "properties": {
    "iso:country":"US",
    "sg:address":"5921 Piper Ln",
    "sg:city":"College Station",
    "sg:classifiers":[
        {
            "category":"Building & Trades",
            "subcategory":"Construction",
            "type":"Services"
        }
    ],
    "sg:phone":"+1 979 846 3198",
    "sg:postcode":"77845",
    "sg:province":"TX",
    "sg:tags":[
        "carpentry",
        "contractor"
    ],
    "wof:name":"Andr Construction",
    "wof:placetype":"venue"
},
  "geometry": {"coordinates":[-96.40312400000001,30.592557],"type":"Point"}
}