{
  "type": "Feature",
  "properties": {
    "iso:country":"US",
    "sg:address":"260 N Main St",
    "sg:city":"Grapevine",
    "sg:classifiers":[
        {
            "category":"Banks & Credit Unions",
            "subcategory":"Investment Brokerage",
            "type":"Services"
        }
    ],
    "sg:phone":"+1 817 442 0470",
    "sg:postcode":"76051",
    "sg:province":"TX",
    "sg:tags":[
        "security"
    ],
    "wof:name":"Edward Jones 26340",
    "wof:placetype":"venue"
},
  "geometry": {"coordinates":[-97.077675,32.942645],"type":"Point"}
}