{
  "type": "Feature",
  "properties": {
    "iso:country":"US",
    "sg:address":"17619 E State Hwy 29",
    "sg:city":"Buchanan Dam",
    "sg:classifiers":[
        {
            "category":"Shopping",
            "subcategory":"Clothing, Apparel, & Fashions",
            "type":"Retail Goods"
        }
    ],
    "sg:phone":"+1 512 793 5213",
    "sg:postcode":"78609",
    "sg:province":"TX",
    "wof:name":"Fashion Finders Inc",
    "wof:placetype":"venue"
},
  "geometry": {"coordinates":[-98.417598,30.742496],"type":"Point"}
}