{
  "type": "Feature",
  "properties": {
    "iso:country":"US",
    "sg:address":"2602 Calico Ct",
    "sg:city":"College Station",
    "sg:classifiers":[
        {
            "category":"Wholesale",
            "subcategory":"Stationery",
            "type":"Manufacturing & Wholesale Goods"
        }
    ],
    "sg:phone":"+1 979 693 1284",
    "sg:postcode":"77845",
    "sg:province":"TX",
    "sg:tags":[
        "business",
        "form"
    ],
    "wof:name":"Sunbelt Business Graphics",
    "wof:placetype":"venue"
},
  "geometry": {"coordinates":[-96.287828,30.621239],"type":"Point"}
}