{
  "type": "Feature",
  "properties": {
    "iso:country":"US",
    "sg:address":"7280 Boone Rd",
    "sg:city":"Houston",
    "sg:classifiers":[
        {
            "category":"Wholesale",
            "subcategory":"Auto Parts",
            "type":"Manufacturing & Wholesale Goods"
        }
    ],
    "sg:phone":"+1 281 568 9900",
    "sg:postcode":"77072",
    "sg:province":"TX",
    "sg:tags":[
        "supply"
    ],
    "wof:name":"Ryens Transmission Parts",
    "wof:placetype":"venue"
},
  "geometry": {"coordinates":[-95.575394,29.699692],"type":"Point"}
}