{
  "type": "Feature",
  "properties": {
    "iso:country":"US",
    "sg:address":"7925 Airline Dr",
    "sg:city":"Houston",
    "sg:classifiers":[
        {
            "category":"Personal",
            "subcategory":"Beauty Salon",
            "type":"Services"
        }
    ],
    "sg:phone":"+1 281 442 5988",
    "sg:postcode":"77037",
    "sg:province":"TX",
    "sg:tags":[
        "shop"
    ],
    "wof:name":"Hair Solutions",
    "wof:placetype":"venue"
},
  "geometry": {"coordinates":[-95.38716599999999,29.876573],"type":"Point"}
}