{
  "type": "Feature",
  "properties": {
    "iso:country":"US",
    "sg:address":"7831 Barberton Dr",
    "sg:city":"Houston",
    "sg:classifiers":[
        {
            "category":"Building & Trades",
            "subcategory":"Construction",
            "type":"Services"
        }
    ],
    "sg:phone":"+1 713 771 5158",
    "sg:postcode":"77036",
    "sg:province":"TX",
    "sg:tags":[
        "wallpaper"
    ],
    "wof:name":"Action Wallcovering",
    "wof:placetype":"venue"
},
  "geometry": {"coordinates":[-95.52590499999999,29.694202],"type":"Point"}
}