{
  "type": "Feature",
  "properties": {
    "iso:country":"US",
    "sg:address":"230 Haggin St",
    "sg:city":"San Antonio",
    "sg:classifiers":[
        {
            "category":"Shopping",
            "subcategory":"Jewelry",
            "type":"Retail Goods"
        }
    ],
    "sg:phone":"+1 210 532 5079",
    "sg:postcode":"78210",
    "sg:province":"TX",
    "wof:name":"Maria Delcarmen",
    "wof:placetype":"venue"
},
  "geometry": {"coordinates":[-98.470116,29.388814],"type":"Point"}
}