{
  "type": "Feature",
  "properties": {
    "iso:country":"US",
    "sg:address":"12400 S Gessner Dr",
    "sg:city":"Houston",
    "sg:classifiers":[
        {
            "category":"Food & Beverages",
            "subcategory":"Groceries & Convenience Stores",
            "type":"Retail Goods"
        }
    ],
    "sg:phone":"+1 713 541 9305",
    "sg:postcode":"77071",
    "sg:province":"TX",
    "wof:name":"Bradley Food Store",
    "wof:placetype":"venue"
},
  "geometry": {"coordinates":[-95.528801,29.6395],"type":"Point"}
}