{
  "type": "Feature",
  "properties": {
    "iso:country":"US",
    "sg:address":"1120 Ave G",
    "sg:city":"Bay City",
    "sg:classifiers":[
        {
            "category":"Health Services",
            "subcategory":"Doctor",
            "type":"Services"
        }
    ],
    "sg:phone":"+1 979 245 5721",
    "sg:postcode":"77414",
    "sg:province":"TX",
    "sg:tags":[
        "clinic"
    ],
    "wof:name":"Medical Arts Clinic",
    "wof:placetype":"venue"
},
  "geometry": {"coordinates":[-95.969246,28.993203],"type":"Point"}
}