{
  "type": "Feature",
  "properties": {
    "iso:country":"US",
    "sg:address":"3723 US Hwy 69",
    "sg:city":"Lufkin",
    "sg:classifiers":[
        {
            "category":"Shopping",
            "subcategory":"Gifts & Souvenirs",
            "type":"Retail Goods"
        }
    ],
    "sg:phone":"+1 936 634 0134",
    "sg:postcode":"75901",
    "sg:province":"TX",
    "wof:name":"Pjs Gift Shop",
    "wof:placetype":"venue"
},
  "geometry": {"coordinates":[-94.704572,31.3663],"type":"Point"}
}