{
  "type": "Feature",
  "properties": {
    "iso:country":"US",
    "sg:address":"1151 Mineral Springs Rd",
    "sg:city":"Arlington",
    "sg:classifiers":[
        {
            "category":"Wholesale",
            "subcategory":"Electrical",
            "type":"Manufacturing & Wholesale Goods"
        }
    ],
    "sg:phone":"+1 817 466 0044",
    "sg:postcode":"76001",
    "sg:province":"TX",
    "sg:tags":[
        "control"
    ],
    "wof:name":"Green Light Controls",
    "wof:placetype":"venue"
},
  "geometry": {"coordinates":[-97.126823,32.644973],"type":"Point"}
}