{
  "type": "Feature",
  "properties": {
    "iso:country":"US",
    "sg:address":"816 W King Ave",
    "sg:city":"Kingsville",
    "sg:classifiers":[
        {
            "category":"Restaurant",
            "type":"Food & Drink"
        }
    ],
    "sg:phone":"+1 361 592 7817",
    "sg:postcode":"78363",
    "sg:province":"TX",
    "sg:tags":[
        "drinking",
        "eating"
    ],
    "wof:name":"Pizza Parlor",
    "wof:placetype":"venue"
},
  "geometry": {"coordinates":[-97.87896499999999,27.515517],"type":"Point"}
}