{
  "type": "Feature",
  "properties": {
    "iso:country":"US",
    "sg:address":"301 Industrial Dr",
    "sg:city":"Forney",
    "sg:phone":"+1 972 564 5554",
    "sg:postcode":"75126",
    "sg:province":"TX",
    "sg:tags":[
        "equipment",
        "commercial"
    ],
    "wof:name":"Dfw Foodshow",
    "wof:placetype":"venue"
},
  "geometry": {"coordinates":[-96.456137,32.751709],"type":"Point"}
}