{
  "type": "Feature",
  "properties": {
    "iso:country":"US",
    "sg:address":"1407 Victory Ln",
    "sg:city":"Alvin",
    "sg:classifiers":[
        {
            "category":"Retail",
            "subcategory":"Auto Repair",
            "type":"Services"
        }
    ],
    "sg:phone":"+1 281 221 9136",
    "sg:postcode":"77511",
    "sg:province":"TX",
    "sg:tags":[
        "repairing",
        "automobile"
    ],
    "wof:name":"At Auto Performance",
    "wof:placetype":"venue"
},
  "geometry": {"coordinates":[-95.23436100000001,29.452159],"type":"Point"}
}