{
  "type": "Feature",
  "properties": {
    "iso:country":"US",
    "sg:address":"1800 South St",
    "sg:city":"Nacogdoches",
    "sg:classifiers":[
        {
            "category":"Personal",
            "subcategory":"Beauty Salon",
            "type":"Services"
        }
    ],
    "sg:phone":"+1 936 564 0551",
    "sg:postcode":"75964",
    "sg:province":"TX",
    "sg:tags":[
        "shop"
    ],
    "wof:name":"Anel's Hair Salon",
    "wof:placetype":"venue"
},
  "geometry": {"coordinates":[-94.665971,31.589568],"type":"Point"}
}