{
  "type": "Feature",
  "properties": {
    "iso:country":"US",
    "sg:address":"610 N Austin Ave",
    "sg:city":"Georgetown",
    "sg:classifiers":[
        {
            "category":"Banks & Credit Unions",
            "subcategory":"Bank",
            "type":"Services"
        }
    ],
    "sg:phone":"+1 512 863 4572",
    "sg:postcode":"78626",
    "sg:province":"TX",
    "sg:tags":[
        "personal",
        "institution"
    ],
    "wof:name":"Bank Of America",
    "wof:placetype":"venue"
},
  "geometry": {"coordinates":[-97.67828799999999,30.646493],"type":"Point"}
}