{
  "type": "Feature",
  "properties": {
    "iso:country":"US",
    "sg:address":"3409 Alstein Ln",
    "sg:city":"Plano",
    "sg:classifiers":[
        {
            "category":"Real Estate",
            "subcategory":"Real Estate Agent",
            "type":"Services"
        }
    ],
    "sg:phone":"+1 469 467 7583",
    "sg:postcode":"75093",
    "sg:province":"TX",
    "sg:tags":[
        "management"
    ],
    "wof:name":"Metric Property Management",
    "wof:placetype":"venue"
},
  "geometry": {"coordinates":[-96.784076,33.045548],"type":"Point"}
}