{
  "type": "Feature",
  "properties": {
    "iso:country":"US",
    "sg:address":"7974 Bethel Rd",
    "sg:city":"Weatherford",
    "sg:classifiers":[
        {
            "category":"Coffee & Tea",
            "type":"Food & Drink"
        },
        {
            "category":"Restaurant",
            "type":"Food & Drink"
        }
    ],
    "sg:phone":"+1 817 598 1222",
    "sg:postcode":"76087",
    "sg:province":"TX",
    "sg:tags":[
        "seafood",
        "espresso"
    ],
    "wof:name":"Tin Top Blues Cafe",
    "wof:placetype":"venue"
},
  "geometry": {"coordinates":[-97.813311,32.597803],"type":"Point"}
}