{
  "type": "Feature",
  "properties": {
    "iso:country":"US",
    "sg:address":"2680 Nova Dr",
    "sg:city":"Dallas",
    "sg:classifiers":[
        {
            "category":"Manufacturing",
            "subcategory":"Food",
            "type":"Manufacturing & Wholesale Goods"
        }
    ],
    "sg:phone":"+1 972 869 1111",
    "sg:postcode":"75229",
    "sg:province":"TX",
    "sg:tags":[
        "macaroni",
        "noodle",
        "spaghetti"
    ],
    "wof:name":"Tommaso's Fresh Pasta",
    "wof:placetype":"venue"
},
  "geometry": {"coordinates":[-96.88914,32.905544],"type":"Point"}
}