{
  "type": "Feature",
  "properties": {
    "iso:country":"US",
    "sg:address":"210 Ravenhead Dr",
    "sg:city":"Houston",
    "sg:classifiers":[
        {
            "category":"Building & Trades",
            "subcategory":"Landscaping Services",
            "type":"Services"
        }
    ],
    "sg:phone":"+1 713 910 1770",
    "sg:postcode":"77034",
    "sg:province":"TX",
    "wof:name":"Southern Select Lawn & Ldscp",
    "wof:placetype":"venue"
},
  "geometry": {"coordinates":[-95.211381,29.64776],"type":"Point"}
}