{
  "type": "Feature",
  "properties": {
    "iso:country":"US",
    "sg:address":"336 Lombardy Ave",
    "sg:city":"El Paso",
    "sg:classifiers":[
        {
            "category":"Manufacturing",
            "subcategory":"Metals",
            "type":"Manufacturing & Wholesale Goods"
        }
    ],
    "sg:phone":"+1 915 584 0836",
    "sg:postcode":"79922",
    "sg:province":"TX",
    "wof:name":"Cougar Enterprises",
    "wof:placetype":"venue"
},
  "geometry": {"coordinates":[-106.583561,31.836373],"type":"Point"}
}