{
  "type": "Feature",
  "properties": {
    "iso:country":"US",
    "sg:address":"3827 Buckner Blvd",
    "sg:city":"Dallas",
    "sg:classifiers":[
        {
            "category":"Professional",
            "subcategory":"Management & Consulting",
            "type":"Services"
        }
    ],
    "sg:phone":"+1 214 946 5464",
    "sg:postcode":"75227",
    "sg:province":"TX",
    "sg:tags":[
        "consultant",
        "business"
    ],
    "wof:name":"Southwest Bahavioral Systems",
    "wof:placetype":"venue"
},
  "geometry": {"coordinates":[-96.682767,32.770957],"type":"Point"}
}