{
  "type": "Feature",
  "properties": {
    "iso:country":"US",
    "sg:address":"11850 Jones Rd",
    "sg:city":"Houston",
    "sg:classifiers":[
        {
            "category":"Wholesale",
            "subcategory":"Metals & Minerals",
            "type":"Manufacturing & Wholesale Goods"
        }
    ],
    "sg:phone":"+1 281 894 4014",
    "sg:postcode":"77070",
    "sg:province":"TX",
    "sg:tags":[
        "steel",
        "warehouse"
    ],
    "wof:name":"Connor Patrick Steel Co",
    "wof:placetype":"venue"
},
  "geometry": {"coordinates":[-95.584721,29.945983],"type":"Point"}
}