{
  "type": "Feature",
  "properties": {
    "iso:country":"US",
    "sg:address":"2707 Welborn Ct",
    "sg:city":"Missouri City",
    "sg:classifiers":[
        {
            "category":"Shopping",
            "subcategory":"Computers & Home Electronics",
            "type":"Retail Goods"
        }
    ],
    "sg:phone":"+1 281 835 0637",
    "sg:postcode":"77459",
    "sg:province":"TX",
    "wof:name":"PC Tech Nirvana",
    "wof:placetype":"venue"
},
  "geometry": {"coordinates":[-95.51452500000001,29.546378],"type":"Point"}
}