{
  "type": "Feature",
  "properties": {
    "iso:country":"US",
    "sg:address":"8201 Old Gay Hill Rd",
    "sg:city":"Brenham",
    "sg:classifiers":[
        {
            "category":"Organizations",
            "subcategory":"Religious Organization",
            "type":"Services"
        }
    ],
    "sg:phone":"+1 979 836 2003",
    "sg:postcode":"77833",
    "sg:province":"TX",
    "sg:tags":[
        "church"
    ],
    "wof:name":"St Peters Lutheran Church",
    "wof:placetype":"venue"
},
  "geometry": {"coordinates":[-96.46794199999999,30.258505],"type":"Point"}
}