{
  "type": "Feature",
  "properties": {
    "iso:country":"US",
    "sg:address":"3133 Marquita Dr",
    "sg:city":"Fort Worth",
    "sg:classifiers":[
        {
            "category":"Real Estate",
            "subcategory":"Developer",
            "type":"Services"
        }
    ],
    "sg:phone":"+1 817 244 5119",
    "sg:postcode":"76116",
    "sg:province":"TX",
    "sg:tags":[
        "association"
    ],
    "wof:name":"Spring Creek Cemetary Assn Inc",
    "wof:placetype":"venue"
},
  "geometry": {"coordinates":[-97.443506,32.727057],"type":"Point"}
}