{
  "type": "Feature",
  "properties": {
    "iso:country":"US",
    "sg:address":"310 la Feria Rd",
    "sg:city":"Brownsville",
    "sg:classifiers":[
        {
            "category":"Shopping",
            "type":"Retail Goods"
        }
    ],
    "sg:phone":"+1 956 542 7080",
    "sg:postcode":"78520",
    "sg:province":"TX",
    "sg:tags":[
        "merchandise"
    ],
    "wof:name":"Escamillas Shop",
    "wof:placetype":"venue"
},
  "geometry": {"coordinates":[-97.518789,25.950566],"type":"Point"}
}