{
  "type": "Feature",
  "properties": {
    "iso:country":"US",
    "sg:address":"4880 W Panther Creek Dr",
    "sg:city":"Spring",
    "sg:classifiers":[
        {
            "category":"Banks & Credit Unions",
            "subcategory":"Bank",
            "type":"Services"
        }
    ],
    "sg:phone":"+1 281 362 2400",
    "sg:postcode":"77381",
    "sg:province":"TX",
    "sg:tags":[
        "commercial"
    ],
    "wof:name":"Wells Fargo",
    "wof:placetype":"venue"
},
  "geometry": {"coordinates":[-95.502144,30.166565],"type":"Point"}
}