{
  "type": "Feature",
  "properties": {
    "iso:country":"US",
    "sg:address":"363 W Main St",
    "sg:city":"Lewisville",
    "sg:classifiers":[
        {
            "category":"Health Services",
            "subcategory":"Chiropractor",
            "type":"Services"
        }
    ],
    "sg:phone":"+1 972 436 0409",
    "sg:postcode":"75057",
    "sg:province":"TX",
    "wof:name":"Mcalister Family Chiropractic",
    "wof:placetype":"venue"
},
  "geometry": {"coordinates":[-97.00103900000001,33.046385],"type":"Point"}
}