{
  "type": "Feature",
  "properties": {
    "iso:country":"US",
    "sg:address":"510 Industrial Blvd",
    "sg:city":"Sugar Land",
    "sg:classifiers":[
        {
            "category":"Wholesale",
            "subcategory":"Metals & Minerals",
            "type":"Manufacturing & Wholesale Goods"
        }
    ],
    "sg:phone":"+1 281 240 6031",
    "sg:postcode":"77478",
    "sg:province":"TX",
    "sg:tags":[
        "center"
    ],
    "wof:name":"International Alloys",
    "wof:placetype":"venue"
},
  "geometry": {"coordinates":[-95.605925,29.633513],"type":"Point"}
}