{
  "type": "Feature",
  "properties": {
    "iso:country":"US",
    "sg:address":"11601 Marina View Dr",
    "sg:city":"Montgomery",
    "sg:classifiers":[
        {
            "category":"Building & Trades",
            "subcategory":"Electrical",
            "type":"Services"
        }
    ],
    "sg:phone":"+1 936 448 1132",
    "sg:postcode":"77356",
    "sg:province":"TX",
    "sg:tags":[
        "electrical",
        "contractor"
    ],
    "wof:name":"Ne Electric",
    "wof:placetype":"venue"
},
  "geometry": {"coordinates":[-95.606481,30.40202],"type":"Point"}
}