{
  "type": "Feature",
  "properties": {
    "iso:country":"US",
    "sg:address":"1606 Peavy Rd",
    "sg:city":"Dallas",
    "sg:classifiers":[
        {
            "category":"Wholesale",
            "subcategory":"Office Equipment",
            "type":"Manufacturing & Wholesale Goods"
        }
    ],
    "sg:phone":"+1 214 321 1116",
    "sg:postcode":"75228",
    "sg:province":"TX",
    "wof:name":"Kearbyco",
    "wof:placetype":"venue"
},
  "geometry": {"coordinates":[-96.690056,32.832945],"type":"Point"}
}