{
  "type": "Feature",
  "properties": {
    "iso:country":"US",
    "sg:address":"411 Hurst St",
    "sg:city":"Center",
    "sg:classifiers":[
        {
            "category":"Building & Trades",
            "subcategory":"Cleaning & Sanitation",
            "type":"Services"
        }
    ],
    "sg:phone":"+1 936 598 3582",
    "sg:postcode":"75935",
    "sg:province":"TX",
    "sg:tags":[
        "janitor"
    ],
    "wof:name":"Deep East Texas Janitorial",
    "wof:placetype":"venue"
},
  "geometry": {"coordinates":[-94.19850099999999,31.817147],"type":"Point"}
}