{
  "type": "Feature",
  "properties": {
    "iso:country":"US",
    "sg:address":"1209 W Texas Ave",
    "sg:city":"Midland",
    "sg:classifiers":[
        {
            "category":"Professional",
            "subcategory":"Lawyer & Legal Services",
            "type":"Services"
        }
    ],
    "sg:phone":"+1 432 682 7800",
    "sg:postcode":"79701",
    "sg:province":"TX",
    "sg:tags":[
        "attorney",
        "plan"
    ],
    "sg:website":"http://www.williamslawpc.com",
    "wof:name":"Williams Law Firm PC",
    "wof:placetype":"venue"
},
  "geometry": {"coordinates":[-102.087219,31.997258],"type":"Point"}
}