{
  "type": "Feature",
  "properties": {
    "iso:country":"US",
    "sg:address":"3013 Fountain View Dr",
    "sg:city":"Houston",
    "sg:classifiers":[
        {
            "category":"Real Estate",
            "subcategory":"Real Estate Agent",
            "type":"Services"
        }
    ],
    "sg:phone":"+1 713 782 0524",
    "sg:postcode":"77057",
    "sg:province":"TX",
    "wof:name":"Chain Property Management",
    "wof:placetype":"venue"
},
  "geometry": {"coordinates":[-95.48416400000001,29.733203],"type":"Point"}
}