{
  "type": "Feature",
  "properties": {
    "iso:country":"US",
    "sg:address":"320 Jim Wright Fwy N",
    "sg:city":"Fort Worth",
    "sg:classifiers":[
        {
            "category":"Banks & Credit Unions",
            "subcategory":"Investment Brokerage",
            "type":"Services"
        }
    ],
    "sg:phone":"+1 817 560 8259",
    "sg:postcode":"76108",
    "sg:province":"TX",
    "sg:tags":[
        "advisory",
        "financial"
    ],
    "wof:name":"Gaetano's Financial Svc",
    "wof:placetype":"venue"
},
  "geometry": {"coordinates":[-97.476156,32.76402],"type":"Point"}
}