{
  "type": "Feature",
  "properties": {
    "iso:country":"US",
    "sg:address":"4001 S Lamar Boulevard",
    "sg:city":"Austin",
    "sg:classifiers":[
        {
            "category":"Shopping",
            "subcategory":"Crafts & Fabrics",
            "type":"Retail Goods"
        }
    ],
    "sg:phone":"+1 512 442 3446",
    "sg:postcode":"78704",
    "sg:province":"TX",
    "sg:tags":[
        "store"
    ],
    "wof:name":"Hancock Fabrics",
    "wof:placetype":"venue"
},
  "geometry": {"coordinates":[-97.792407,30.236284],"type":"Point"}
}