{
  "type": "Feature",
  "properties": {
    "iso:country":"US",
    "sg:address":"4600 W Park Blvd",
    "sg:city":"Plano",
    "sg:classifiers":[
        {
            "category":"Health Services",
            "subcategory":"Clinic",
            "type":"Services"
        }
    ],
    "sg:phone":"+1 972 398 0261",
    "sg:postcode":"75093",
    "sg:province":"TX",
    "sg:tags":[
        "specialty",
        "outpatient"
    ],
    "wof:name":"HealthSouth",
    "wof:placetype":"venue"
},
  "geometry": {"coordinates":[-96.788403,33.026918],"type":"Point"}
}