{
  "type": "Feature",
  "properties": {
    "iso:country":"US",
    "sg:address":"1220 Co Rd 25",
    "sg:city":"Lamesa",
    "sg:phone":"+1 806 780 6220",
    "sg:postcode":"79331",
    "sg:province":"TX",
    "sg:tags":[
        "farm",
        "cotton"
    ],
    "wof:name":"JW Stafford Farms",
    "wof:placetype":"venue"
},
  "geometry": {"coordinates":[-101.906094,32.644802],"type":"Point"}
}