{
  "type": "Feature",
  "properties": {
    "iso:country":"US",
    "sg:address":"8517 Darlina Dr",
    "sg:city":"El Paso",
    "sg:classifiers":[
        {
            "category":"Professional",
            "subcategory":"Engineering",
            "type":"Services"
        }
    ],
    "sg:phone":"+1 915 779 6587",
    "sg:postcode":"79925",
    "sg:province":"TX",
    "wof:name":"Barrett Refrigeration Co",
    "wof:placetype":"venue"
},
  "geometry": {"coordinates":[-106.372818,31.778931],"type":"Point"}
}