{
  "type": "Feature",
  "properties": {
    "iso:country":"US",
    "sg:address":"1508 1st St",
    "sg:city":"Bayside",
    "sg:classifiers":[
        {
            "category":"Banks & Credit Unions",
            "subcategory":"Investment Brokerage",
            "type":"Services"
        }
    ],
    "sg:phone":"+1 361 547 0441",
    "sg:postcode":"78340",
    "sg:province":"TX",
    "sg:tags":[
        "security"
    ],
    "wof:name":"Edward Jones 22204",
    "wof:placetype":"venue"
},
  "geometry": {"coordinates":[-97.193916,28.109553],"type":"Point"}
}