{
  "type": "Feature",
  "properties": {
    "iso:country":"US",
    "sg:address":"1080 Crown Dr",
    "sg:city":"Bulverde",
    "sg:classifiers":[
        {
            "category":"Building & Trades",
            "subcategory":"Cleaning & Sanitation",
            "type":"Services"
        }
    ],
    "sg:phone":"+1 830 438 3381",
    "sg:postcode":"78163",
    "sg:province":"TX",
    "sg:tags":[
        "maintenance"
    ],
    "wof:name":"Oak Hills Window Cleaning",
    "wof:placetype":"venue"
},
  "geometry": {"coordinates":[-98.461484,29.791068],"type":"Point"}
}