{
  "type": "Feature",
  "properties": {
    "iso:country":"US",
    "sg:address":"12200 Ark Rd",
    "sg:city":"Frisco",
    "sg:classifiers":[
        {
            "category":"Professional",
            "subcategory":"Management & Consulting",
            "type":"Services"
        }
    ],
    "sg:phone":"+1 972 987 6514",
    "sg:postcode":"75035",
    "sg:province":"TX",
    "sg:tags":[
        "business"
    ],
    "wof:name":"Veritas Consulting Group",
    "wof:placetype":"venue"
},
  "geometry": {"coordinates":[-96.77258500000001,33.1469],"type":"Point"}
}