{
  "type": "Feature",
  "properties": {
    "iso:country":"US",
    "sg:address":"13807 Laurel Hollow",
    "sg:city":"San Antonio",
    "sg:classifiers":[
        {
            "category":"Organizations",
            "subcategory":"Religious Organization",
            "type":"Services"
        }
    ],
    "sg:phone":"+1 210 490 2121",
    "sg:postcode":"78232",
    "sg:province":"TX",
    "wof:name":"Armenian Church San Antonio",
    "wof:placetype":"venue"
},
  "geometry": {"coordinates":[-98.46241000000001,29.57259],"type":"Point"}
}