{
  "type": "Feature",
  "properties": {
    "iso:country":"US",
    "sg:address":"805 Avenue B",
    "sg:city":"Katy",
    "sg:classifiers":[
        {
            "category":"Retail",
            "subcategory":"Laundry & Dry Cleaning",
            "type":"Services"
        },
        {
            "category":"Retail",
            "subcategory":"Repair Shop",
            "type":"Services"
        },
        {
            "category":"Building & Trades",
            "subcategory":"Construction",
            "type":"Services"
        },
        {
            "category":"Manufacturing",
            "subcategory":"Building Materials",
            "type":"Manufacturing & Wholesale Goods"
        },
        {
            "category":"Home & Garden",
            "subcategory":"Carpets & Floor Coverings",
            "type":"Retail Goods"
        }
    ],
    "sg:phone":"+1 281 391 8035",
    "sg:postcode":"77493",
    "sg:province":"TX",
    "sg:tags":[
        "cleaner",
        "materials-wholesale",
        "rug",
        "tile-contractors",
        "manufacturer"
    ],
    "wof:name":"Brookshire Carpet",
    "wof:placetype":"venue"
},
  "geometry": {"coordinates":[-95.822205,29.786434],"type":"Point"}
}