{
  "type": "Feature",
  "properties": {
    "iso:country":"US",
    "sg:address":"102 W Hiram St",
    "sg:city":"Atlanta",
    "sg:classifiers":[
        {
            "category":"Professional",
            "subcategory":"Business Services",
            "type":"Services"
        }
    ],
    "sg:phone":"+1 903 799 5426",
    "sg:postcode":"75551",
    "sg:province":"TX",
    "sg:tags":[
        "embroidery"
    ],
    "wof:name":"Sassy Stitches",
    "wof:placetype":"venue"
},
  "geometry": {"coordinates":[-94.167197,33.115622],"type":"Point"}
}