{
  "type": "Feature",
  "properties": {
    "iso:country":"US",
    "sg:address":"2108 Green Oaks Rd",
    "sg:city":"Fort Worth",
    "sg:classifiers":[
        {
            "category":"Shopping",
            "subcategory":"Clothing, Apparel, & Fashions",
            "type":"Retail Goods"
        }
    ],
    "sg:phone":"+1 817 569 8800",
    "sg:postcode":"76116",
    "sg:province":"TX",
    "sg:tags":[
        "family"
    ],
    "wof:name":"Banana Republic",
    "wof:placetype":"venue"
},
  "geometry": {"coordinates":[-97.43425000000001,32.735934],"type":"Point"}
}