{
  "type": "Feature",
  "properties": {
    "iso:country":"US",
    "sg:address":"7345 Crestway Dr",
    "sg:city":"San Antonio",
    "sg:classifiers":[
        {
            "category":"Freight",
            "type":"Transportation"
        }
    ],
    "sg:phone":"+1 210 657 2400",
    "sg:postcode":"78239",
    "sg:province":"TX",
    "sg:tags":[
        "commercial",
        "storage"
    ],
    "wof:name":"AAA Storage",
    "wof:placetype":"venue"
},
  "geometry": {"coordinates":[-98.34432,29.522023],"type":"Point"}
}