{
  "type": "Feature",
  "properties": {
    "iso:country":"US",
    "sg:address":"11410 Jollyville Road",
    "sg:city":"Austin",
    "sg:classifiers":[
        {
            "category":"Health Services",
            "subcategory":"Optometrist",
            "type":"Services"
        }
    ],
    "sg:phone":"+1 512 343 0406",
    "sg:postcode":"78759",
    "sg:province":"TX",
    "wof:name":"Shepard & Shepard Optometrists",
    "wof:placetype":"venue"
},
  "geometry": {"coordinates":[-97.74787999999999,30.411345],"type":"Point"}
}