{
  "type": "Feature",
  "properties": {
    "iso:country":"US",
    "sg:address":"101 W Dannelly St",
    "sg:city":"Hebbronville",
    "sg:classifiers":[
        {
            "category":"Professional",
            "subcategory":"Accounting & Tax Preparation",
            "type":"Services"
        }
    ],
    "sg:phone":"+1 361 527 4657",
    "sg:postcode":"78361",
    "sg:province":"TX",
    "sg:tags":[
        "return",
        "filing"
    ],
    "wof:name":"Arnolodo Gonzalez Tax Svc",
    "wof:placetype":"venue"
},
  "geometry": {"coordinates":[-98.678546,27.30085],"type":"Point"}
}