{
  "type": "Feature",
  "properties": {
    "iso:country":"US",
    "sg:address":"12800 Preston Rd",
    "sg:city":"Dallas",
    "sg:classifiers":[
        {
            "category":"Health Services",
            "subcategory":"Doctor",
            "type":"Services"
        }
    ],
    "sg:phone":"+1 972 490 7979",
    "sg:postcode":"75230",
    "sg:province":"TX",
    "sg:tags":[
        "physician",
        "surgeon"
    ],
    "wof:name":"Advanced Orthopedics",
    "wof:placetype":"venue"
},
  "geometry": {"coordinates":[-96.803569,32.924228],"type":"Point"}
}