{
  "type": "Feature",
  "properties": {
    "iso:country":"US",
    "sg:address":"15219 Stuebner Airline Rd",
    "sg:city":"Houston",
    "sg:classifiers":[
        {
            "category":"Recreation",
            "subcategory":"Arcade",
            "type":"Entertainment"
        }
    ],
    "sg:phone":"+1 832 484 8199",
    "sg:postcode":"77069",
    "sg:province":"TX",
    "sg:tags":[
        "casino"
    ],
    "wof:name":"Casino Adventures",
    "wof:placetype":"venue"
},
  "geometry": {"coordinates":[-95.508099,30.001114],"type":"Point"}
}