{
  "type": "Feature",
  "properties": {
    "iso:country":"US",
    "sg:address":"213 Wilshire Dr",
    "sg:city":"Coppell",
    "sg:classifiers":[
        {
            "category":"Professional",
            "subcategory":"Computer Services",
            "type":"Services"
        }
    ],
    "sg:phone":"+1 972 471 0315",
    "sg:postcode":"75019",
    "sg:province":"TX",
    "sg:tags":[
        "related"
    ],
    "wof:name":"My Computer Guy",
    "wof:placetype":"venue"
},
  "geometry": {"coordinates":[-96.94651399999999,32.963132],"type":"Point"}
}