{
  "type": "Feature",
  "properties": {
    "iso:country":"US",
    "sg:address":"7240 Cliffbrook Dr",
    "sg:city":"Dallas",
    "sg:classifiers":[
        {
            "category":"Wholesale",
            "subcategory":"Machinery & Supplies",
            "type":"Manufacturing & Wholesale Goods"
        }
    ],
    "sg:phone":"+1 972 239 9112",
    "sg:postcode":"75254",
    "sg:province":"TX",
    "sg:tags":[
        "equipment",
        "material",
        "handling"
    ],
    "wof:name":"Indoff Inc",
    "wof:placetype":"venue"
},
  "geometry": {"coordinates":[-96.778954,32.945581],"type":"Point"}
}