{
  "type": "Feature",
  "properties": {
    "iso:country":"US",
    "sg:address":"1204 San Antonio St",
    "sg:city":"Austin",
    "sg:classifiers":[
        {
            "category":"Organizations",
            "subcategory":"Membership Organization",
            "type":"Services"
        }
    ],
    "sg:phone":"+1 512 472 0102",
    "sg:postcode":"78701",
    "sg:province":"TX",
    "sg:tags":[
        "historical"
    ],
    "wof:name":"Preservation Texas Inc",
    "wof:placetype":"venue"
},
  "geometry": {"coordinates":[-97.744861,30.276278],"type":"Point"}
}