{
  "type": "Feature",
  "properties": {
    "iso:country":"US",
    "sg:address":"600 Scott Ave",
    "sg:city":"Wichita Falls",
    "sg:classifiers":[
        {
            "category":"Government",
            "subcategory":"Office",
            "type":"Public Place"
        }
    ],
    "sg:phone":"+1 940 723 0153",
    "sg:postcode":"76301",
    "sg:province":"TX",
    "sg:tags":[
        "county",
        "resource"
    ],
    "wof:name":"Wichita County Human Svc",
    "wof:placetype":"venue"
},
  "geometry": {"coordinates":[-98.492879,33.912878],"type":"Point"}
}