{
  "type": "Feature",
  "properties": {
    "iso:country":"US",
    "sg:address":"21009 Fawn Ridge Dr",
    "sg:city":"Leander",
    "sg:classifiers":[
        {
            "category":"Professional",
            "subcategory":"Business Services",
            "type":"Services"
        }
    ],
    "sg:phone":"+1 512 267 1820",
    "sg:postcode":"78645",
    "sg:province":"TX",
    "wof:name":"Js Dunn Partners Ltd",
    "wof:placetype":"venue"
},
  "geometry": {"coordinates":[-97.98473300000001,30.464258],"type":"Point"}
}