{
  "type": "Feature",
  "properties": {
    "iso:country":"US",
    "sg:address":"6255 Lamar Rd",
    "sg:city":"Reno",
    "sg:classifiers":[
        {
            "category":"Autos & Motor Vehicles",
            "subcategory":"Automobile Sales",
            "type":"Retail Goods"
        }
    ],
    "sg:phone":"+1 903 783 9297",
    "sg:postcode":"75462",
    "sg:province":"TX",
    "sg:tags":[
        "new",
        "car"
    ],
    "wof:name":"Wheels Unlimited Auto Sales",
    "wof:placetype":"venue"
},
  "geometry": {"coordinates":[-95.469114,33.6633],"type":"Point"}
}