{
  "type": "Feature",
  "properties": {
    "iso:country":"US",
    "sg:address":"1416 Industrial Dr",
    "sg:city":"Royse City",
    "sg:classifiers":[
        {
            "category":"Manufacturing",
            "subcategory":"Aerospace",
            "type":"Manufacturing & Wholesale Goods"
        }
    ],
    "sg:phone":"+1 972 635 9400",
    "sg:postcode":"75189",
    "sg:province":"TX",
    "sg:tags":[
        "metal"
    ],
    "wof:name":"C and M Trading Inc",
    "wof:placetype":"venue"
},
  "geometry": {"coordinates":[-96.303625,32.983489],"type":"Point"}
}