{
  "type": "Feature",
  "properties": {
    "iso:country":"US",
    "sg:address":"2615 Western Trails Blvd",
    "sg:city":"Austin",
    "sg:classifiers":[
        {
            "category":"Real Estate",
            "subcategory":"Real Estate Agent",
            "type":"Services"
        }
    ],
    "sg:phone":"+1 512 892 3511",
    "sg:postcode":"78745",
    "sg:province":"TX",
    "wof:name":"Robinson Co Realtors",
    "wof:placetype":"venue"
},
  "geometry": {"coordinates":[-97.801214,30.228984],"type":"Point"}
}