{
  "type": "Feature",
  "properties": {
    "iso:country":"US",
    "sg:address":"21548 Quail Run Rd",
    "sg:city":"Chandler",
    "sg:classifiers":[
        {
            "category":"Freight",
            "type":"Transportation"
        }
    ],
    "sg:phone":"+1 903 849 5971",
    "sg:postcode":"75758",
    "sg:province":"TX",
    "sg:tags":[
        "moving"
    ],
    "wof:name":"CNT Movers",
    "wof:placetype":"venue"
},
  "geometry": {"coordinates":[-95.494654,32.238119],"type":"Point"}
}