{
  "type": "Feature",
  "properties": {
    "iso:country":"US",
    "sg:address":"918 Bailey St",
    "sg:city":"Houston",
    "sg:classifiers":[
        {
            "category":"Shopping",
            "type":"Retail Goods"
        }
    ],
    "sg:phone":"+1 713 271 2737",
    "sg:postcode":"77019",
    "sg:province":"TX",
    "sg:tags":[
        "telephone",
        "cellular"
    ],
    "wof:name":"Southern Cellular",
    "wof:placetype":"venue"
},
  "geometry": {"coordinates":[-95.38215700000001,29.757927],"type":"Point"}
}