{
  "type": "Feature",
  "properties": {
    "iso:country":"US",
    "sg:address":"9201 Homestead Rd",
    "sg:city":"Houston",
    "sg:classifiers":[
        {
            "category":"Food & Beverages",
            "subcategory":"Groceries & Convenience Stores",
            "type":"Retail Goods"
        }
    ],
    "sg:phone":"+1 713 491 0813",
    "sg:postcode":"77016",
    "sg:province":"TX",
    "wof:name":"King M Foodmart",
    "wof:placetype":"venue"
},
  "geometry": {"coordinates":[-95.302308,29.845027],"type":"Point"}
}