{
  "type": "Feature",
  "properties": {
    "iso:country":"US",
    "sg:address":"3420 14th St",
    "sg:city":"Plano",
    "sg:classifiers":[
        {
            "category":"Freight",
            "type":"Transportation"
        }
    ],
    "sg:phone":"+1 972 881 1625",
    "sg:postcode":"75074",
    "sg:province":"TX",
    "sg:tags":[
        "storage",
        "commercial",
        "general"
    ],
    "wof:name":"Plano Storage Station",
    "wof:placetype":"venue"
},
  "geometry": {"coordinates":[-96.671396,33.015019],"type":"Point"}
}