{
  "type": "Feature",
  "properties": {
    "iso:country":"US",
    "sg:address":"15705 Long Vista Dr",
    "sg:city":"Austin",
    "sg:classifiers":[
        {
            "category":"Professional",
            "subcategory":"Engineering",
            "type":"Services"
        },
        {
            "category":"Manufacturing",
            "subcategory":"Aerospace",
            "type":"Manufacturing & Wholesale Goods"
        }
    ],
    "sg:phone":"+1 512 498 0300",
    "sg:postcode":"78728",
    "sg:province":"TX",
    "sg:tags":[
        "aeronautical",
        "industry",
        "engineer"
    ],
    "wof:name":"E G & G Technical Services",
    "wof:placetype":"venue"
},
  "geometry": {"coordinates":[-97.67197899999999,30.455781],"type":"Point"}
}