{
  "type": "Feature",
  "properties": {
    "iso:country":"US",
    "sg:address":"300 W Pioneer Pkwy",
    "sg:city":"Arlington",
    "sg:classifiers":[
        {
            "category":"Real Estate",
            "subcategory":"Real Estate Operator",
            "type":"Services"
        }
    ],
    "sg:phone":"+1 817 275 6572",
    "sg:postcode":"76010",
    "sg:province":"TX",
    "sg:tags":[
        "building",
        "apartment"
    ],
    "wof:name":"English Village Townhomes",
    "wof:placetype":"venue"
},
  "geometry": {"coordinates":[-97.11234399999999,32.708067],"type":"Point"}
}