{
  "type": "Feature",
  "properties": {
    "iso:country":"US",
    "sg:address":"101 S MacArthur Blvd",
    "sg:city":"Irving",
    "sg:classifiers":[
        {
            "category":"Autos & Motor Vehicles",
            "subcategory":"Fuel & Gas Station",
            "type":"Retail Goods"
        },
        {
            "category":"Food & Beverages",
            "subcategory":"Groceries & Convenience Stores",
            "type":"Retail Goods"
        }
    ],
    "sg:phone":"+1 972 254 0121",
    "sg:postcode":"75060",
    "sg:province":"TX",
    "wof:name":"Valero",
    "wof:placetype":"venue"
},
  "geometry": {"coordinates":[-96.960143,32.814581],"type":"Point"}
}