{
  "type": "Feature",
  "properties": {
    "iso:country":"US",
    "sg:address":"4435 Frontier Trl",
    "sg:city":"Austin",
    "sg:classifiers":[
        {
            "category":"Retail",
            "subcategory":"Funeral Services",
            "type":"Services"
        }
    ],
    "sg:phone":"+1 512 443 1366",
    "sg:postcode":"78745",
    "sg:province":"TX",
    "sg:tags":[
        "cemetery",
        "plan"
    ],
    "wof:name":"Harrell Funeral Home",
    "wof:placetype":"venue"
},
  "geometry": {"coordinates":[-97.79499800000001,30.2316],"type":"Point"}
}