{
  "type": "Feature",
  "properties": {
    "iso:country":"US",
    "sg:address":"1913 N 38th St",
    "sg:city":"Killeen",
    "sg:classifiers":[
        {
            "category":"Professional",
            "subcategory":"Business Services",
            "type":"Services"
        }
    ],
    "sg:phone":"+1 254 526 8299",
    "sg:postcode":"76543",
    "sg:province":"TX",
    "wof:name":"Godfrey Zuma",
    "wof:placetype":"venue"
},
  "geometry": {"coordinates":[-97.695454,31.128186],"type":"Point"}
}