{
  "type": "Feature",
  "properties": {
    "iso:country":"US",
    "sg:address":"538 Main St",
    "sg:city":"Liberty",
    "sg:classifiers":[
        {
            "category":"Health Services",
            "subcategory":"Clinic",
            "type":"Services"
        }
    ],
    "sg:phone":"+1 936 334 1114",
    "sg:postcode":"77575",
    "sg:province":"TX",
    "sg:tags":[
        "home",
        "care"
    ],
    "wof:name":"Interlink Home Health Services",
    "wof:placetype":"venue"
},
  "geometry": {"coordinates":[-94.795813,30.060498],"type":"Point"}
}