{
  "type": "Feature",
  "properties": {
    "iso:country":"US",
    "sg:address":"8744 Buckskin Dr",
    "sg:city":"Boerne",
    "sg:classifiers":[
        {
            "category":"Professional",
            "subcategory":"Business Services",
            "type":"Services"
        }
    ],
    "sg:phone":"+1 210 698 0505",
    "sg:postcode":"78006",
    "sg:province":"TX",
    "wof:name":"Kabanek Family Partnership",
    "wof:placetype":"venue"
},
  "geometry": {"coordinates":[-98.653451,29.695999],"type":"Point"}
}