{
  "type": "Feature",
  "properties": {
    "iso:country":"US",
    "sg:address":"1703 Chelsey Ln",
    "sg:city":"Richardson",
    "sg:classifiers":[
        {
            "category":"Shopping",
            "subcategory":"Clothing, Apparel, & Fashions",
            "type":"Retail Goods"
        },
        {
            "category":"Shopping",
            "subcategory":"Crafts & Fabrics",
            "type":"Retail Goods"
        }
    ],
    "sg:phone":"+1 972 669 8432",
    "sg:postcode":"75082",
    "sg:province":"TX",
    "sg:tags":[
        "shop",
        "shirts-custom",
        "made"
    ],
    "wof:name":"Klee Shirts Inc",
    "wof:placetype":"venue"
},
  "geometry": {"coordinates":[-96.693865,32.979462],"type":"Point"}
}