{
  "type": "Feature",
  "properties": {
    "iso:country":"US",
    "sg:address":"811 N Eastside Dr",
    "sg:city":"Wichita Falls",
    "sg:classifiers":[
        {
            "category":"Food & Beverages",
            "subcategory":"Groceries & Convenience Stores",
            "type":"Retail Goods"
        }
    ],
    "sg:phone":"+1 940 322 4756",
    "sg:postcode":"76306",
    "sg:province":"TX",
    "wof:name":"Bluebonnet Grocery",
    "wof:placetype":"venue"
},
  "geometry": {"coordinates":[-98.497806,33.927313],"type":"Point"}
}