{
  "type": "Feature",
  "properties": {
    "iso:country":"US",
    "sg:address":"5419 Bissonnet St",
    "sg:city":"Houston",
    "sg:classifiers":[
        {
            "category":"Organizations",
            "subcategory":"Religious Organization",
            "type":"Services"
        }
    ],
    "sg:phone":"+1 713 633 7544",
    "sg:postcode":"77081",
    "sg:province":"TX",
    "wof:name":"First Baptist Church Trinity",
    "wof:placetype":"venue"
},
  "geometry": {"coordinates":[-95.474272,29.704324],"type":"Point"}
}