{
  "type": "Feature",
  "properties": {
    "iso:country":"US",
    "sg:address":"1601 W Grand Ave",
    "sg:city":"Marshall",
    "sg:classifiers":[
        {
            "category":"Food & Beverages",
            "subcategory":"Groceries & Convenience Stores",
            "type":"Retail Goods"
        }
    ],
    "sg:phone":"+1 903 935 2569",
    "sg:postcode":"75670",
    "sg:province":"TX",
    "sg:tags":[
        "station",
        "gasoline"
    ],
    "wof:name":"Short Stop 5",
    "wof:placetype":"venue"
},
  "geometry": {"coordinates":[-94.38301800000001,32.548389],"type":"Point"}
}