{
  "type": "Feature",
  "properties": {
    "iso:country":"US",
    "sg:address":"5717 14th St",
    "sg:city":"Lubbock",
    "sg:classifiers":[
        {
            "category":"Professional",
            "type":"Services"
        }
    ],
    "sg:phone":"+1 806 797 1522",
    "sg:postcode":"79416",
    "sg:province":"TX",
    "wof:name":"Caprock Chapter American",
    "wof:placetype":"venue"
},
  "geometry": {"coordinates":[-101.93579099999999,33.584505],"type":"Point"}
}