{
  "type": "Feature",
  "properties": {
    "iso:country":"US",
    "sg:address":"317 Gentry St",
    "sg:city":"Spring",
    "sg:classifiers":[
        {
            "category":"Restaurant",
            "type":"Food & Drink"
        }
    ],
    "sg:phone":"+1 281 288 1117",
    "sg:postcode":"77373",
    "sg:province":"TX",
    "sg:tags":[
        "eating"
    ],
    "wof:name":"Log House Eatery",
    "wof:placetype":"venue"
},
  "geometry": {"coordinates":[-95.41983999999999,30.078619],"type":"Point"}
}