{
  "type": "Feature",
  "properties": {
    "iso:country":"US",
    "sg:address":"3206 Cole Ct",
    "sg:city":"Rosenberg",
    "sg:classifiers":[
        {
            "category":"Retail",
            "subcategory":"Portrait Studio",
            "type":"Services"
        }
    ],
    "sg:phone":"+1 281 342 4859",
    "sg:postcode":"77471",
    "sg:province":"TX",
    "sg:tags":[
        "photo"
    ],
    "wof:name":"Jerry Dame Photography",
    "wof:placetype":"venue"
},
  "geometry": {"coordinates":[-95.828214,29.501861],"type":"Point"}
}