{
  "type": "Feature",
  "properties": {
    "iso:country":"US",
    "sg:address":"1446 Pennygent Ln",
    "sg:city":"Channelview",
    "sg:classifiers":[
        {
            "category":"Professional",
            "subcategory":"Management & Consulting",
            "type":"Services"
        }
    ],
    "sg:phone":"+1 281 452 6615",
    "sg:postcode":"77530",
    "sg:province":"TX",
    "sg:tags":[
        "business"
    ],
    "wof:name":"Maria Delrosario Montanez",
    "wof:placetype":"venue"
},
  "geometry": {"coordinates":[-95.15209400000001,29.802648],"type":"Point"}
}