{
  "type": "Feature",
  "properties": {
    "iso:country":"US",
    "sg:address":"206 Spring",
    "sg:city":"Center",
    "sg:classifiers":[
        {
            "category":"Professional",
            "subcategory":"Business Services",
            "type":"Services"
        }
    ],
    "sg:phone":"+1 936 598 8247",
    "sg:postcode":"75935",
    "sg:province":"TX",
    "wof:name":"CB Harvill Enterprises Inc",
    "wof:placetype":"venue"
},
  "geometry": {"coordinates":[-94.178353,31.792177],"type":"Point"}
}