{
  "type": "Feature",
  "properties": {
    "iso:country":"US",
    "sg:address":"3002 S Zarzamora",
    "sg:city":"San Antonio",
    "sg:classifiers":[
        {
            "category":"Food & Beverages",
            "subcategory":"Groceries & Convenience Stores",
            "type":"Retail Goods"
        }
    ],
    "sg:phone":"+1 210 927 4040",
    "sg:postcode":"78225",
    "sg:province":"TX",
    "wof:name":"Tetco Stores Inc",
    "wof:placetype":"venue"
},
  "geometry": {"coordinates":[-98.532121,29.393711],"type":"Point"}
}