{
  "type": "Feature",
  "properties": {
    "iso:country":"US",
    "sg:address":"1712 S Mcdonald St",
    "sg:city":"Mckinney",
    "sg:classifiers":[
        {
            "category":"Utilities",
            "subcategory":"Fuel Oil & Lpg",
            "type":"Services"
        },
        {
            "category":"Utilities",
            "subcategory":"Natural Gas",
            "type":"Services"
        }
    ],
    "sg:phone":"+1 972 562 3371",
    "sg:postcode":"75069",
    "sg:province":"TX",
    "sg:tags":[
        "propane",
        "bulk",
        "petroleum-bottled",
        "gas-liquefied"
    ],
    "sg:website":"http://www.ferrellgas.com",
    "wof:name":"Ferrellgas",
    "wof:placetype":"venue"
},
  "geometry": {"coordinates":[-96.619338,33.178002],"type":"Point"}
}