{
  "type": "Feature",
  "properties": {
    "iso:country":"US",
    "sg:address":"9416 Overlake Dr",
    "sg:city":"Dallas",
    "sg:classifiers":[
        {
            "category":"Freight",
            "type":"Transportation"
        }
    ],
    "sg:phone":"+1 214 902 0525",
    "sg:postcode":"75220",
    "sg:province":"TX",
    "sg:tags":[
        "local",
        "except",
        "trucking"
    ],
    "wof:name":"R & B Trucking",
    "wof:placetype":"venue"
},
  "geometry": {"coordinates":[-96.867898,32.856784],"type":"Point"}
}