{
  "type": "Feature",
  "properties": {
    "iso:country":"US",
    "sg:address":"13202 Turkey Roost Dr",
    "sg:city":"Manchaca",
    "sg:classifiers":[
        {
            "category":"Building & Trades",
            "subcategory":"Construction",
            "type":"Services"
        }
    ],
    "sg:phone":"+1 512 282 1778",
    "sg:postcode":"78652",
    "sg:province":"TX",
    "sg:tags":[
        "carpentry",
        "contractor"
    ],
    "wof:name":"To The T Custom Interiors Inc",
    "wof:placetype":"venue"
},
  "geometry": {"coordinates":[-97.877531,30.145613],"type":"Point"}
}