{
  "type": "Feature",
  "properties": {
    "iso:country":"US",
    "sg:address":"439 Sheldon Rd",
    "sg:city":"Channelview",
    "sg:classifiers":[
        {
            "category":"Restaurant",
            "type":"Food & Drink"
        }
    ],
    "sg:phone":"+1 281 452 0001",
    "sg:postcode":"77530",
    "sg:province":"TX",
    "sg:tags":[
        "pizza",
        "italian"
    ],
    "wof:name":"Pizza Hut",
    "wof:placetype":"venue"
},
  "geometry": {"coordinates":[-95.124717,29.778962],"type":"Point"}
}