{
  "type": "Feature",
  "properties": {
    "iso:country":"US",
    "sg:address":"314 W Bowie St",
    "sg:city":"Beeville",
    "sg:classifiers":[
        {
            "category":"Building & Trades",
            "subcategory":"Plumbing",
            "type":"Services"
        }
    ],
    "sg:phone":"+1 361 358 1826",
    "sg:postcode":"78102",
    "sg:province":"TX",
    "sg:tags":[
        "conditioning",
        "air",
        "system",
        "contractor"
    ],
    "wof:name":"Hickey Air Conditioning & Htg",
    "wof:placetype":"venue"
},
  "geometry": {"coordinates":[-97.75093099999999,28.401976],"type":"Point"}
}