{
  "type": "Feature",
  "properties": {
    "iso:country":"US",
    "sg:address":"3915 Roadrunner",
    "sg:city":"Ropesville",
    "sg:classifiers":[
        {
            "category":"Professional",
            "type":"Services"
        }
    ],
    "sg:phone":"+1 806 562 2027",
    "sg:postcode":"79358",
    "sg:province":"TX",
    "wof:name":"ARC Inc",
    "wof:placetype":"venue"
},
  "geometry": {"coordinates":[-102.227469,33.44649],"type":"Point"}
}