{
  "type": "Feature",
  "properties": {
    "iso:country":"US",
    "sg:address":"550 N Denton Tap Rd",
    "sg:city":"Coppell",
    "sg:classifiers":[
        {
            "category":"Real Estate",
            "subcategory":"Real Estate Services",
            "type":"Services"
        }
    ],
    "sg:phone":"+1 972 316 2020",
    "sg:postcode":"75019",
    "sg:province":"TX",
    "sg:website":"www.championsschool.com",
    "wof:name":"Champion School of Real Estate",
    "wof:placetype":"venue"
},
  "geometry": {"coordinates":[-96.992744,32.982643],"type":"Point"}
}