{
  "type": "Feature",
  "properties": {
    "iso:country":"US",
    "sg:address":"7089 N Lakeview Rd",
    "sg:city":"Salado",
    "sg:classifiers":[
        {
            "category":"Retail",
            "subcategory":"Auto Repair",
            "type":"Services"
        }
    ],
    "sg:phone":"+1 254 947 5504",
    "sg:postcode":"76571",
    "sg:province":"TX",
    "sg:tags":[
        "glass",
        "replacement"
    ],
    "wof:name":"Ricks Windshield Repair",
    "wof:placetype":"venue"
},
  "geometry": {"coordinates":[-97.574664,30.997814],"type":"Point"}
}