{
  "type": "Feature",
  "properties": {
    "iso:country":"US",
    "sg:address":"11155 Dennis Rd",
    "sg:city":"Dallas",
    "sg:classifiers":[
        {
            "category":"Retail",
            "subcategory":"Auto Repair",
            "type":"Services"
        }
    ],
    "sg:phone":"+1 972 241 1901",
    "sg:postcode":"75229",
    "sg:province":"TX",
    "wof:name":"Dennis Road Automotive",
    "wof:placetype":"venue"
},
  "geometry": {"coordinates":[-96.881401,32.900398],"type":"Point"}
}