{
  "type": "Feature",
  "properties": {
    "iso:country":"US",
    "sg:address":"7670 FM 2164",
    "sg:city":"Sanger",
    "sg:classifiers":[
        {
            "category":"Organizations",
            "subcategory":"Religious Organization",
            "type":"Services"
        }
    ],
    "sg:phone":"+1 940 458 3274",
    "sg:postcode":"76266",
    "sg:province":"TX",
    "wof:name":"Gribble Springs Baptist Church",
    "wof:placetype":"venue"
},
  "geometry": {"coordinates":[-97.1249,33.32548],"type":"Point"}
}