{
  "type": "Feature",
  "properties": {
    "iso:country":"US",
    "sg:address":"1950 E Main St",
    "sg:city":"Grand Prairie",
    "sg:classifiers":[
        {
            "category":"Manufacturing",
            "subcategory":"Metals",
            "type":"Manufacturing & Wholesale Goods"
        }
    ],
    "sg:phone":"+1 972 263 1566",
    "sg:postcode":"75050",
    "sg:province":"TX",
    "sg:tags":[
        "conversion",
        "mfg",
        "automobile",
        "recreational",
        "sea",
        "vehicle"
    ],
    "wof:name":"Metal Specialties Mfg Co",
    "wof:placetype":"venue"
},
  "geometry": {"coordinates":[-96.97748799999999,32.748908],"type":"Point"}
}