{
  "type": "Feature",
  "properties": {
    "iso:country":"US",
    "sg:address":"4309 W Baker Rd",
    "sg:city":"Baytown",
    "sg:classifiers":[
        {
            "category":"Ice Cream",
            "type":"Food & Drink"
        }
    ],
    "sg:menulink":"http://www.allmenus.com/tx/baytown/162093-dairy-queen/menu/",
    "sg:phone":"+1 281 424 1451",
    "sg:postcode":"77521",
    "sg:province":"TX",
    "sg:tags":[
        "burger",
        "american"
    ],
    "wof:name":"Dairy Queen",
    "wof:placetype":"venue"
},
  "geometry": {"coordinates":[-95.011821,29.770336],"type":"Point"}
}