{
  "type": "Feature",
  "properties": {
    "iso:country":"US",
    "sg:address":"16631 Kuykendahl Rd",
    "sg:city":"Houston",
    "sg:classifiers":[
        {
            "category":"Building & Trades",
            "subcategory":"Plumbing",
            "type":"Services"
        }
    ],
    "sg:phone":"+1 281 440 8980",
    "sg:postcode":"77068",
    "sg:province":"TX",
    "sg:tags":[
        "conditioning",
        "contractor",
        "system",
        "air"
    ],
    "wof:name":"Air North Air Conditioning Svc",
    "wof:placetype":"venue"
},
  "geometry": {"coordinates":[-95.47235000000001,30.018866],"type":"Point"}
}