{
  "type": "Feature",
  "properties": {
    "iso:country":"US",
    "sg:address":"3839 Dry Creek Dr Apt 121",
    "sg:city":"Austin",
    "sg:classifiers":[
        {
            "category":"Shopping",
            "subcategory":"Pets & Pet Supplies",
            "type":"Retail Goods"
        },
        {
            "category":"Retail",
            "subcategory":"Animal Services",
            "type":"Services"
        }
    ],
    "sg:phone":"+1 512 407 9279",
    "sg:postcode":"78731",
    "sg:province":"TX",
    "sg:tags":[
        "grooming",
        "dog",
        "cat"
    ],
    "wof:name":"Something Different By Ma",
    "wof:placetype":"venue"
},
  "geometry": {"coordinates":[-97.764599,30.343415],"type":"Point"}
}