{
  "type": "Feature",
  "properties": {
    "iso:country":"US",
    "sg:address":"1306 W Wallace St",
    "sg:city":"San Saba",
    "sg:classifiers":[
        {
            "category":"Restaurant",
            "type":"Food & Drink"
        }
    ],
    "sg:phone":"+1 325 372 6519",
    "sg:postcode":"76877",
    "sg:province":"TX",
    "sg:tags":[
        "eating"
    ],
    "wof:name":"Town & Country",
    "wof:placetype":"venue"
},
  "geometry": {"coordinates":[-98.731489,31.195776],"type":"Point"}
}