{
  "type": "Feature",
  "properties": {
    "iso:country":"US",
    "sg:address":"1981 E Mulberry St",
    "sg:city":"Angleton",
    "sg:classifiers":[
        {
            "category":"Professional",
            "type":"Services"
        }
    ],
    "sg:phone":"+1 979 849 0009",
    "sg:postcode":"77515",
    "sg:province":"TX",
    "sg:tags":[
        "establishment"
    ],
    "wof:name":"J & D Treasures",
    "wof:placetype":"venue"
},
  "geometry": {"coordinates":[-95.413445,29.176857],"type":"Point"}
}