{
  "type": "Feature",
  "properties": {
    "iso:country":"US",
    "sg:address":"2574 South Loop W",
    "sg:city":"Houston",
    "sg:classifiers":[
        {
            "category":"Home & Garden",
            "subcategory":"Furniture",
            "type":"Retail Goods"
        }
    ],
    "sg:phone":"+1 713 665 6867",
    "sg:postcode":"77054",
    "sg:province":"TX",
    "sg:tags":[
        "store"
    ],
    "wof:name":"Astro Furniture",
    "wof:placetype":"venue"
},
  "geometry": {"coordinates":[-95.416901,29.678301],"type":"Point"}
}