{
  "type": "Feature",
  "properties": {
    "iso:country":"US",
    "sg:address":"6202 Decker Dr",
    "sg:city":"Baytown",
    "sg:classifiers":[
        {
            "category":"Home & Garden",
            "subcategory":"Mobile Homes",
            "type":"Retail Goods"
        }
    ],
    "sg:phone":"+1 281 424 3668",
    "sg:postcode":"77520",
    "sg:province":"TX",
    "wof:name":"Americas Acceptance MBL Homes",
    "wof:placetype":"venue"
},
  "geometry": {"coordinates":[-95.03201900000001,29.782706],"type":"Point"}
}