{
  "type": "Feature",
  "properties": {
    "iso:country":"US",
    "sg:address":"13442 Klamath Falls Dr",
    "sg:city":"Houston",
    "sg:classifiers":[
        {
            "category":"Professional",
            "type":"Services"
        }
    ],
    "sg:phone":"+1 713 466 3429",
    "sg:postcode":"77041",
    "sg:province":"TX",
    "wof:name":"PA PA Earls Fetchum Catchum",
    "wof:placetype":"venue"
},
  "geometry": {"coordinates":[-95.612264,29.85836],"type":"Point"}
}