{
  "type": "Feature",
  "properties": {
    "iso:country":"US",
    "sg:address":"2680 Nova Dr",
    "sg:city":"Dallas",
    "sg:phone":"+1 972 401 1885",
    "sg:postcode":"75229",
    "sg:province":"TX",
    "sg:tags":[
        "equipment",
        "commercial"
    ],
    "wof:name":"SES Marketeers",
    "wof:placetype":"venue"
},
  "geometry": {"coordinates":[-96.88914,32.905544],"type":"Point"}
}