{
  "type": "Feature",
  "properties": {
    "iso:country":"US",
    "sg:address":"2219 Pittman St",
    "sg:city":"Dallas",
    "sg:classifiers":[
        {
            "category":"Retail",
            "subcategory":"Auto Repair",
            "type":"Services"
        }
    ],
    "sg:phone":"+1 214 752 0215",
    "sg:postcode":"75208",
    "sg:province":"TX",
    "sg:tags":[
        "body",
        "automobile",
        "painting"
    ],
    "wof:name":"Uzi's Body Shop",
    "wof:placetype":"venue"
},
  "geometry": {"coordinates":[-96.831582,32.771772],"type":"Point"}
}