{
  "type": "Feature",
  "properties": {
    "iso:country":"US",
    "sg:address":"2721 Nall St",
    "sg:city":"Port Neches",
    "sg:classifiers":[
        {
            "category":"Social Services",
            "type":"Services"
        }
    ],
    "sg:phone":"+1 409 727 8979",
    "sg:postcode":"77651",
    "sg:province":"TX",
    "sg:tags":[
        "counseling"
    ],
    "wof:name":"Starr Thurber Lpc Lmft",
    "wof:placetype":"venue"
},
  "geometry": {"coordinates":[-93.969809,29.972396],"type":"Point"}
}