{
  "type": "Feature",
  "properties": {
    "iso:country":"US",
    "sg:address":"13300 Violet St",
    "sg:city":"Euless",
    "sg:classifiers":[
        {
            "category":"Wholesale",
            "subcategory":"Metals & Minerals",
            "type":"Manufacturing & Wholesale Goods"
        }
    ],
    "sg:phone":"+1 817 868 9702",
    "sg:postcode":"76040",
    "sg:province":"TX",
    "sg:tags":[
        "distribution",
        "fasteners-industrial"
    ],
    "wof:name":"Commodity Resources Inc",
    "wof:placetype":"venue"
},
  "geometry": {"coordinates":[-97.077862,32.819248],"type":"Point"}
}