{
  "type": "Feature",
  "properties": {
    "iso:country":"US",
    "sg:address":"8560 Freeland St",
    "sg:city":"Houston",
    "sg:classifiers":[
        {
            "category":"Wholesale",
            "subcategory":"Machinery & Supplies",
            "type":"Manufacturing & Wholesale Goods"
        }
    ],
    "sg:phone":"+1 713 943 8763",
    "sg:postcode":"77075",
    "sg:province":"TX",
    "sg:tags":[
        "fitting",
        "valve"
    ],
    "wof:name":"H L Albright Co Inc",
    "wof:placetype":"venue"
},
  "geometry": {"coordinates":[-95.262595,29.638899],"type":"Point"}
}