{
  "type": "Feature",
  "properties": {
    "iso:country":"US",
    "sg:address":"3009 Saulsbury Dr",
    "sg:city":"Temple",
    "sg:classifiers":[
        {
            "category":"Government",
            "subcategory":"Court House",
            "type":"Public Place"
        }
    ],
    "sg:phone":"+1 254 778 1841",
    "sg:postcode":"76504",
    "sg:province":"TX",
    "sg:tags":[
        "state",
        "counsel"
    ],
    "wof:name":"Attorney General",
    "wof:placetype":"venue"
},
  "geometry": {"coordinates":[-97.37119800000001,31.11171],"type":"Point"}
}