{
  "type": "Feature",
  "properties": {
    "iso:country":"US",
    "sg:address":"4403 Emerald Dr",
    "sg:city":"Carrollton",
    "sg:classifiers":[
        {
            "category":"Shopping",
            "subcategory":"Gifts & Souvenirs",
            "type":"Retail Goods"
        }
    ],
    "sg:phone":"+1 972 394 1502",
    "sg:postcode":"75010",
    "sg:province":"TX",
    "wof:name":"JP Decorating Designs & Gifts",
    "wof:placetype":"venue"
},
  "geometry": {"coordinates":[-96.879187,33.035158],"type":"Point"}
}