{
  "type": "Feature",
  "properties": {
    "iso:country":"US",
    "sg:address":"9759 Forest Ln",
    "sg:city":"Dallas",
    "sg:classifiers":[
        {
            "category":"Organizations",
            "subcategory":"Religious Organization",
            "type":"Services"
        }
    ],
    "sg:phone":"+1 972 808 9300",
    "sg:postcode":"75243",
    "sg:province":"TX",
    "sg:tags":[
        "church"
    ],
    "wof:name":"Dallas Overcomers Church",
    "wof:placetype":"venue"
},
  "geometry": {"coordinates":[-96.71930399999999,32.90964],"type":"Point"}
}