{
  "type": "Feature",
  "properties": {
    "iso:country":"US",
    "sg:address":"22706 August Leaf Dr",
    "sg:city":"Tomball",
    "sg:classifiers":[
        {
            "category":"Insurance",
            "subcategory":"Insurance Agent",
            "type":"Services"
        }
    ],
    "sg:phone":"+1 281 376 8089",
    "sg:postcode":"77375",
    "sg:province":"TX",
    "wof:name":"Box Insurance Services",
    "wof:placetype":"venue"
},
  "geometry": {"coordinates":[-95.551858,30.096262],"type":"Point"}
}