{
  "type": "Feature",
  "properties": {
    "iso:country":"US",
    "sg:address":"3637 N Buckner Blvd",
    "sg:city":"Dallas",
    "sg:classifiers":[
        {
            "category":"Banks & Credit Unions",
            "subcategory":"Bank",
            "type":"Services"
        }
    ],
    "sg:phone":"+1 214 328 2736",
    "sg:postcode":"75228",
    "sg:province":"TX",
    "wof:name":"Homebank",
    "wof:placetype":"venue"
},
  "geometry": {"coordinates":[-96.68270099999999,32.801899],"type":"Point"}
}