{
  "type": "Feature",
  "properties": {
    "iso:country":"US",
    "sg:address":"3012 Quail Ln",
    "sg:city":"Arlington",
    "sg:classifiers":[
        {
            "category":"Real Estate",
            "subcategory":"Real Estate Agent",
            "type":"Services"
        }
    ],
    "sg:phone":"+1 817 654 2001",
    "sg:postcode":"76016",
    "sg:province":"TX",
    "sg:tags":[
        "business"
    ],
    "wof:name":"Cline Home Inspection Svc",
    "wof:placetype":"venue"
},
  "geometry": {"coordinates":[-97.19411100000001,32.695789],"type":"Point"}
}