{
  "type": "Feature",
  "properties": {
    "iso:country":"US",
    "sg:address":"7018 Alameda Ave",
    "sg:city":"El Paso",
    "sg:classifiers":[
        {
            "category":"Retail",
            "subcategory":"Laundry & Dry Cleaning",
            "type":"Services"
        }
    ],
    "sg:phone":"+1 915 778 2027",
    "sg:postcode":"79915",
    "sg:province":"TX",
    "wof:name":"Express Cleaners",
    "wof:placetype":"venue"
},
  "geometry": {"coordinates":[-106.397921,31.758266],"type":"Point"}
}