{
  "type": "Feature",
  "properties": {
    "iso:country":"US",
    "sg:address":"1646 N Jefferson St",
    "sg:city":"La Grange",
    "sg:classifiers":[
        {
            "category":"Government",
            "subcategory":"Office",
            "type":"Public Place"
        }
    ],
    "sg:phone":"+1 979 968 2612",
    "sg:postcode":"78945",
    "sg:province":"TX",
    "sg:tags":[
        "state"
    ],
    "wof:name":"Texas Parks & Wildlife",
    "wof:placetype":"venue"
},
  "geometry": {"coordinates":[-96.881118,29.922966],"type":"Point"}
}