{
  "type": "Feature",
  "properties": {
    "iso:country":"US",
    "sg:address":"1903 Jefferson St",
    "sg:city":"Laredo",
    "sg:classifiers":[
        {
            "category":"Building & Trades",
            "subcategory":"Construction",
            "type":"Services"
        }
    ],
    "sg:phone":"+1 956 722 7377",
    "sg:postcode":"78040",
    "sg:province":"TX",
    "sg:tags":[
        "logistics",
        "industrial"
    ],
    "wof:name":"Southern Logistics",
    "wof:placetype":"venue"
},
  "geometry": {"coordinates":[-99.51499699999999,27.523572],"type":"Point"}
}