{
  "type": "Feature",
  "properties": {
    "iso:country":"US",
    "sg:address":"1024 E Irving Blvd",
    "sg:city":"Irving",
    "sg:classifiers":[
        {
            "category":"Autos & Motor Vehicles",
            "subcategory":"Auto Supplies",
            "type":"Retail Goods"
        },
        {
            "category":"Retail",
            "subcategory":"Auto Repair",
            "type":"Services"
        }
    ],
    "sg:phone":"+1 972 438 7725",
    "sg:postcode":"75060",
    "sg:province":"TX",
    "sg:tags":[
        "tire"
    ],
    "wof:name":"Womble Tire & Auto Inc",
    "wof:placetype":"venue"
},
  "geometry": {"coordinates":[-96.933403,32.810902],"type":"Point"}
}