{
  "type": "Feature",
  "properties": {
    "iso:country":"US",
    "sg:address":"105 O Neill St",
    "sg:city":"Alvord",
    "sg:classifiers":[
        {
            "category":"Government",
            "subcategory":"Post Office",
            "type":"Public Place"
        }
    ],
    "sg:phone":"+1 940 427 2111",
    "sg:postcode":"76225",
    "sg:province":"TX",
    "sg:tags":[
        "postal",
        "us"
    ],
    "wof:name":"US Post Office",
    "wof:placetype":"venue"
},
  "geometry": {"coordinates":[-96.96657999999999,33.390229],"type":"Point"}
}