{
  "type": "Feature",
  "properties": {
    "iso:country":"US",
    "sg:address":"1150 State Hwy 1604",
    "sg:city":"San Antonio",
    "sg:classifiers":[
        {
            "category":"Autos & Motor Vehicles",
            "subcategory":"Automobile Sales",
            "type":"Retail Goods"
        }
    ],
    "sg:phone":"+1 210 732 6004",
    "sg:postcode":"78248",
    "sg:province":"TX",
    "sg:tags":[
        "used"
    ],
    "wof:name":"Texas Cars",
    "wof:placetype":"venue"
},
  "geometry": {"coordinates":[-98.51264999999999,29.608587],"type":"Point"}
}