{
  "type": "Feature",
  "properties": {
    "iso:country":"US",
    "sg:address":"3421 FM 1960 W",
    "sg:city":"Houston",
    "sg:classifiers":[
        {
            "category":"Retail",
            "subcategory":"Auto Repair",
            "type":"Services"
        }
    ],
    "sg:phone":"+1 281 233 0111",
    "sg:postcode":"77068",
    "sg:province":"TX",
    "sg:tags":[
        "general"
    ],
    "wof:name":"Bimmer Workshop",
    "wof:placetype":"venue"
},
  "geometry": {"coordinates":[-95.477277,29.999476],"type":"Point"}
}