{
  "type": "Feature",
  "properties": {
    "iso:country":"US",
    "sg:address":"12506 D Bar Dr",
    "sg:city":"Santa Fe",
    "sg:classifiers":[
        {
            "category":"Home & Garden",
            "subcategory":"Home Furnishings",
            "type":"Retail Goods"
        }
    ],
    "sg:phone":"+1 409 925 8982",
    "sg:postcode":"77510",
    "sg:province":"TX",
    "wof:name":"Donnas Scents Appeal",
    "wof:placetype":"venue"
},
  "geometry": {"coordinates":[-95.09094399999999,29.379259],"type":"Point"}
}