{
  "type": "Feature",
  "properties": {
    "iso:country":"US",
    "sg:address":"2812 N Lee Trevino Dr",
    "sg:city":"El Paso",
    "sg:classifiers":[
        {
            "category":"Social Services",
            "subcategory":"Child Care",
            "type":"Services"
        }
    ],
    "sg:phone":"+1 915 592 2306",
    "sg:postcode":"79936",
    "sg:province":"TX",
    "wof:name":"Teacher's Apple Daycare",
    "wof:placetype":"venue"
},
  "geometry": {"coordinates":[-106.322987,31.780768],"type":"Point"}
}