{
  "type": "Feature",
  "properties": {
    "iso:country":"US",
    "sg:address":"3433 S 20th St",
    "sg:city":"Abilene",
    "sg:classifiers":[
        {
            "category":"Professional",
            "subcategory":"Research",
            "type":"Services"
        }
    ],
    "sg:phone":"+1 325 692 7764",
    "sg:postcode":"79605",
    "sg:province":"TX",
    "sg:tags":[
        "environmental",
        "ecological"
    ],
    "wof:name":"West Texas Hydro Kleen",
    "wof:placetype":"venue"
},
  "geometry": {"coordinates":[-99.767931,32.424369],"type":"Point"}
}