{
  "type": "Feature",
  "properties": {
    "iso:country":"US",
    "sg:address":"4537 Lancelot Dr",
    "sg:city":"Plano",
    "sg:classifiers":[
        {
            "category":"Professional",
            "subcategory":"Computer Services",
            "type":"Services"
        }
    ],
    "sg:phone":"+1 972 208 0111",
    "sg:postcode":"75024",
    "sg:province":"TX",
    "sg:tags":[
        "prepackaged",
        "software"
    ],
    "wof:name":"Great Sthwest Intractive Group",
    "wof:placetype":"venue"
},
  "geometry": {"coordinates":[-96.78219900000001,33.076814],"type":"Point"}
}