{
  "type": "Feature",
  "properties": {
    "iso:country":"US",
    "sg:address":"1250 Texas Pkwy",
    "sg:city":"Stafford",
    "sg:classifiers":[
        {
            "category":"Retail",
            "subcategory":"Auto Repair",
            "type":"Services"
        }
    ],
    "sg:phone":"+1 281 261 0926",
    "sg:postcode":"77477",
    "sg:province":"TX",
    "sg:tags":[
        "general",
        "supply"
    ],
    "wof:name":"Berchers Tire & Service Center",
    "wof:placetype":"venue"
},
  "geometry": {"coordinates":[-95.527371,29.609014],"type":"Point"}
}