{
  "type": "Feature",
  "properties": {
    "iso:country":"US",
    "sg:address":"415 Westheimer",
    "sg:city":"Houston",
    "sg:classifiers":[
        {
            "category":"Restaurant",
            "type":"Food & Drink"
        }
    ],
    "sg:phone":"+1 713 527 0609",
    "sg:postcode":"77006",
    "sg:province":"TX",
    "sg:tags":[
        "italian"
    ],
    "sg:website":"www.sorrentohouston.com",
    "wof:name":"Sorrento Ristorante Italiano",
    "wof:placetype":"venue"
},
  "geometry": {"coordinates":[-95.386223,29.744556],"type":"Point"}
}