{
  "type": "Feature",
  "properties": {
    "iso:country":"US",
    "sg:address":"610 W Gibson St",
    "sg:city":"Jasper",
    "sg:classifiers":[
        {
            "category":"Fast Food",
            "type":"Food & Drink"
        },
        {
            "category":"Restaurant",
            "type":"Food & Drink"
        }
    ],
    "sg:phone":"+1 409 381 8219",
    "sg:postcode":"75951",
    "sg:province":"TX",
    "sg:tags":[
        "hot",
        "hamburger",
        "dog"
    ],
    "wof:name":"Novrozsky's Hamburgers",
    "wof:placetype":"venue"
},
  "geometry": {"coordinates":[-93.99284400000001,30.912315],"type":"Point"}
}