{
  "type": "Feature",
  "properties": {
    "iso:country":"US",
    "sg:address":"4078 W Hwy 199",
    "sg:city":"Springtown",
    "sg:classifiers":[
        {
            "category":"Manufacturing",
            "subcategory":"Motor Vehicles & Parts",
            "type":"Manufacturing & Wholesale Goods"
        }
    ],
    "sg:phone":"+1 817 220 5535",
    "sg:postcode":"76082",
    "sg:province":"TX",
    "sg:tags":[
        "trailer"
    ],
    "sg:website":"www.deerskinmfg.com",
    "wof:name":"Deerskin Manufacturing",
    "wof:placetype":"venue"
},
  "geometry": {"coordinates":[-97.749309,32.979616],"type":"Point"}
}