{
  "type": "Feature",
  "properties": {
    "iso:country":"US",
    "sg:address":"10123 Pebble Park Ln",
    "sg:city":"Houston",
    "sg:classifiers":[
        {
            "category":"Building & Trades",
            "subcategory":"Cleaning & Sanitation",
            "type":"Services"
        }
    ],
    "sg:phone":"+1 713 995 0723",
    "sg:postcode":"77036",
    "sg:province":"TX",
    "sg:tags":[
        "maintenance"
    ],
    "wof:name":"Aguila Cleaning Services",
    "wof:placetype":"venue"
},
  "geometry": {"coordinates":[-95.556246,29.68419],"type":"Point"}
}