{
  "type": "Feature",
  "properties": {
    "iso:country":"US",
    "sg:address":"3700 S Shaver St Exd",
    "sg:city":"South Houston",
    "sg:classifiers":[
        {
            "category":"Food & Beverages",
            "subcategory":"Liquor & Beverages",
            "type":"Retail Goods"
        }
    ],
    "sg:phone":"+1 713 944 7845",
    "sg:postcode":"77587",
    "sg:province":"TX",
    "sg:tags":[
        "drink",
        "ice",
        "also",
        "beer",
        "soft",
        "wine"
    ],
    "wof:name":"Beverage King",
    "wof:placetype":"venue"
},
  "geometry": {"coordinates":[-95.20809199999999,29.653647],"type":"Point"}
}