{
  "type": "Feature",
  "properties": {
    "iso:country":"US",
    "sg:address":"2005 Cortlandt St",
    "sg:city":"Houston",
    "sg:classifiers":[
        {
            "category":"Professional",
            "subcategory":"Computer Services",
            "type":"Services"
        }
    ],
    "sg:phone":"+1 713 426 3157",
    "sg:postcode":"77008",
    "sg:province":"TX",
    "sg:tags":[
        "consultant",
        "designer"
    ],
    "wof:name":"MPRO It Consulting",
    "wof:placetype":"venue"
},
  "geometry": {"coordinates":[-95.39567,29.806012],"type":"Point"}
}