{
  "type": "Feature",
  "properties": {
    "iso:country":"US",
    "sg:address":"3201 West Ave",
    "sg:city":"San Antonio",
    "sg:classifiers":[
        {
            "category":"Autos & Motor Vehicles",
            "subcategory":"Auto Supplies",
            "type":"Retail Goods"
        }
    ],
    "sg:phone":"+1 210 340 4069",
    "sg:postcode":"78213",
    "sg:province":"TX",
    "sg:tags":[
        "battery"
    ],
    "wof:name":"M-Tronics",
    "wof:placetype":"venue"
},
  "geometry": {"coordinates":[-98.526054,29.490742],"type":"Point"}
}