{
  "type": "Feature",
  "properties": {
    "iso:country":"US",
    "sg:address":"1001 Texas Blvd",
    "sg:city":"Texarkana",
    "sg:classifiers":[
        {
            "category":"Insurance",
            "subcategory":"Insurance Agent",
            "type":"Services"
        }
    ],
    "sg:phone":"+1 903 793 7789",
    "sg:postcode":"75501",
    "sg:province":"TX",
    "wof:name":"Ronald Rudd",
    "wof:placetype":"venue"
},
  "geometry": {"coordinates":[-94.050146,33.428739],"type":"Point"}
}