{
  "type": "Feature",
  "properties": {
    "iso:country":"US",
    "sg:address":"3201 Forest Hill Cir",
    "sg:city":"Fort Worth",
    "sg:classifiers":[
        {
            "category":"Restaurant",
            "type":"Food & Drink"
        }
    ],
    "sg:menulink":"http://www.allmenus.com/tx/fort-worth/94514-dominos-pizza/menu/",
    "sg:phone":"+1 817 355 8888",
    "sg:postcode":"76140",
    "sg:province":"TX",
    "sg:tags":[
        "american",
        "wing",
        "pizza"
    ],
    "wof:name":"Domino's Pizza",
    "wof:placetype":"venue"
},
  "geometry": {"coordinates":[-97.274818,32.658642],"type":"Point"}
}