{
  "type": "Feature",
  "properties": {
    "iso:country":"US",
    "sg:address":"4305 Briarbend Dr",
    "sg:city":"Houston",
    "sg:classifiers":[
        {
            "category":"Sports & Exercise",
            "subcategory":"Sports Center",
            "type":"Entertainment"
        }
    ],
    "sg:phone":"+1 713 729 9802",
    "sg:postcode":"77035",
    "sg:province":"TX",
    "sg:tags":[
        "manager",
        "promoter"
    ],
    "wof:name":"Red Shift Racing",
    "wof:placetype":"venue"
},
  "geometry": {"coordinates":[-95.44897400000001,29.66183],"type":"Point"}
}