{
  "type": "Feature",
  "properties": {
    "iso:country":"US",
    "sg:address":"27831 Commercial Park Ln",
    "sg:city":"Tomball",
    "sg:classifiers":[
        {
            "category":"Retail",
            "subcategory":"Repair Shop",
            "type":"Services"
        }
    ],
    "sg:phone":"+1 281 516 7505",
    "sg:postcode":"77375",
    "sg:province":"TX",
    "wof:name":"Services In Advance Biomedical",
    "wof:placetype":"venue"
},
  "geometry": {"coordinates":[-95.619992,30.077676],"type":"Point"}
}