{
  "type": "Feature",
  "properties": {
    "iso:country":"US",
    "sg:address":"4718 Edison St",
    "sg:city":"Houston",
    "sg:classifiers":[
        {
            "category":"Professional",
            "subcategory":"Lawyer & Legal Services",
            "type":"Services"
        }
    ],
    "sg:phone":"+1 713 652 3900",
    "sg:postcode":"77009",
    "sg:province":"TX",
    "sg:website":"www.ricardorodriguez.com",
    "wof:name":"Ricardo Rodriguez",
    "wof:placetype":"venue"
},
  "geometry": {"coordinates":[-95.36269,29.803097],"type":"Point"}
}