{
  "type": "Feature",
  "properties": {
    "iso:country":"US",
    "sg:address":"1213 West Loop North",
    "sg:city":"Houston",
    "sg:classifiers":[
        {
            "category":"Professional",
            "subcategory":"Art Services",
            "type":"Services"
        },
        {
            "category":"Shopping",
            "subcategory":"Bridal",
            "type":"Retail Goods"
        }
    ],
    "sg:phone":"+1 713 688 7700",
    "sg:postcode":"77092",
    "sg:province":"TX",
    "sg:tags":[
        "photographer"
    ],
    "sg:website":"www.amphotographyvideo.com",
    "wof:name":"A.M. Photography",
    "wof:placetype":"venue"
},
  "geometry": {"coordinates":[-95.454373,29.789853],"type":"Point"}
}