{
  "type": "Feature",
  "properties": {
    "iso:country":"US",
    "sg:address":"105 N Main St",
    "sg:city":"Midland",
    "sg:classifiers":[
        {
            "category":"Museum",
            "type":"Entertainment"
        }
    ],
    "sg:phone":"+1 432 682 6234",
    "sg:postcode":"79701",
    "sg:province":"TX",
    "sg:tags":[
        "gallery"
    ],
    "wof:name":"Midland Center",
    "wof:placetype":"venue"
},
  "geometry": {"coordinates":[-102.07447500000001,31.998516],"type":"Point"}
}