{
  "type": "Feature",
  "properties": {
    "iso:country":"US",
    "sg:address":"3440 Bell St",
    "sg:city":"Amarillo",
    "sg:classifiers":[
        {
            "category":"Health Services",
            "subcategory":"Chiropractor",
            "type":"Services"
        }
    ],
    "sg:phone":"+1 806 358 9666",
    "sg:postcode":"79109",
    "sg:province":"TX",
    "sg:tags":[
        "chiropractic"
    ],
    "wof:name":"Todd J Gray",
    "wof:placetype":"venue"
},
  "geometry": {"coordinates":[-101.902304,35.175554],"type":"Point"}
}