{
  "type": "Feature",
  "properties": {
    "iso:country":"US",
    "sg:address":"1300 7th St",
    "sg:city":"Bay City",
    "sg:classifiers":[
        {
            "category":"Communications",
            "type":"Services"
        }
    ],
    "sg:phone":"+1 979 323 7911",
    "sg:postcode":"77414",
    "sg:province":"TX",
    "sg:tags":[
        "communication"
    ],
    "wof:name":"Gulf Coast E M S Emrgncy Line",
    "wof:placetype":"venue"
},
  "geometry": {"coordinates":[-95.97365499999999,28.982896],"type":"Point"}
}