{
  "type": "Feature",
  "properties": {
    "iso:country":"US",
    "sg:address":"809 Tower Dr",
    "sg:city":"Odessa",
    "sg:classifiers":[
        {
            "category":"Shopping",
            "type":"Retail Goods"
        }
    ],
    "sg:phone":"+1 800 316 3168",
    "sg:postcode":"79761",
    "sg:province":"TX",
    "sg:tags":[
        "medical",
        "apparatus",
        "supply"
    ],
    "wof:name":"Major Medical Supply Inc",
    "wof:placetype":"venue"
},
  "geometry": {"coordinates":[-102.342142,31.862161],"type":"Point"}
}