{
  "type": "Feature",
  "properties": {
    "iso:country":"US",
    "sg:address":"108 N Blackwell St",
    "sg:city":"Pasadena",
    "sg:classifiers":[
        {
            "category":"Communications",
            "type":"Services"
        }
    ],
    "sg:phone":"+1 713 920 2590",
    "sg:postcode":"77506",
    "sg:province":"TX",
    "sg:tags":[
        "communication"
    ],
    "wof:name":"NM Communications",
    "wof:placetype":"venue"
},
  "geometry": {"coordinates":[-95.22357700000001,29.714101],"type":"Point"}
}