{
  "type": "Feature",
  "properties": {
    "iso:country":"US",
    "sg:address":"3750 N Main St",
    "sg:city":"Fort Worth",
    "sg:classifiers":[
        {
            "category":"Wholesale",
            "subcategory":"Scrap",
            "type":"Manufacturing & Wholesale Goods"
        }
    ],
    "sg:phone":"+1 817 625 4366",
    "sg:postcode":"76106",
    "sg:province":"TX",
    "sg:tags":[
        "metal"
    ],
    "wof:name":"American Recycling",
    "wof:placetype":"venue"
},
  "geometry": {"coordinates":[-97.35136199999999,32.812155],"type":"Point"}
}