{
  "type": "Feature",
  "properties": {
    "iso:country":"US",
    "sg:address":"13008 Spring Oak Dr",
    "sg:city":"Mesquite",
    "sg:classifiers":[
        {
            "category":"Shopping",
            "subcategory":"Mobile Phones",
            "type":"Retail Goods"
        }
    ],
    "sg:phone":"+1 972 913 8955",
    "sg:postcode":"75180",
    "sg:province":"TX",
    "wof:name":"MetroPCS",
    "wof:placetype":"venue"
},
  "geometry": {"coordinates":[-96.60472799999999,32.712012],"type":"Point"}
}