{
  "type": "Feature",
  "properties": {
    "iso:country":"US",
    "sg:address":"171 Parkhouse St",
    "sg:city":"Dallas",
    "sg:classifiers":[
        {
            "category":"Professional",
            "subcategory":"Business Services",
            "type":"Services"
        }
    ],
    "sg:phone":"+1 214 749 5745",
    "sg:postcode":"75207",
    "sg:province":"TX",
    "wof:name":"Lloyds Empower Lion",
    "wof:placetype":"venue"
},
  "geometry": {"coordinates":[-96.816911,32.784609],"type":"Point"}
}