{
  "type": "Feature",
  "properties": {
    "iso:country":"US",
    "sg:address":"506 E Purnell Rd",
    "sg:city":"Lewisville",
    "sg:phone":"+1 972 436 1100",
    "sg:postcode":"75057",
    "sg:province":"TX",
    "sg:website":"http://american-cycleco.com",
    "wof:name":"American Cycle Company",
    "wof:placetype":"venue"
},
  "geometry": {"coordinates":[-96.988596,33.042],"type":"Point"}
}