{
  "type": "Feature",
  "properties": {
    "iso:country":"US",
    "sg:address":"1416 Houston St",
    "sg:city":"Laredo",
    "sg:classifiers":[
        {
            "category":"Wholesale",
            "subcategory":"Electrical",
            "type":"Manufacturing & Wholesale Goods"
        }
    ],
    "sg:phone":"+1 956 727 1784",
    "sg:postcode":"78040",
    "sg:province":"TX",
    "sg:tags":[
        "alarm",
        "burglar",
        "system"
    ],
    "wof:name":"Best Alarm Co",
    "wof:placetype":"venue"
},
  "geometry": {"coordinates":[-99.510234,27.507224],"type":"Point"}
}