{
  "type": "Feature",
  "properties": {
    "iso:country":"US",
    "sg:address":"11011 Brooklet Dr Ste 320",
    "sg:city":"Houston",
    "sg:classifiers":[
        {
            "category":"Building & Trades",
            "subcategory":"Construction",
            "type":"Services"
        }
    ],
    "sg:phone":"+1 832 328 1385",
    "sg:postcode":"77099",
    "sg:province":"TX",
    "sg:tags":[
        "contractor"
    ],
    "sg:website":"www.dmacconstruction.net",
    "wof:name":"Dmac Construction",
    "wof:placetype":"venue"
},
  "geometry": {"coordinates":[-95.56289700000001,29.660999],"type":"Point"}
}