{
  "type": "Feature",
  "properties": {
    "iso:country":"US",
    "sg:address":"325 E Wood Ave",
    "sg:city":"Raymondville",
    "sg:classifiers":[
        {
            "category":"Retail",
            "subcategory":"Laundry & Dry Cleaning",
            "type":"Services"
        }
    ],
    "sg:phone":"+1 956 689 4065",
    "sg:postcode":"78580",
    "sg:province":"TX",
    "wof:name":"Diaper Place",
    "wof:placetype":"venue"
},
  "geometry": {"coordinates":[-97.77891200000001,26.474534],"type":"Point"}
}