{
  "type": "Feature",
  "properties": {
    "iso:country":"US",
    "sg:address":"9000 W Bellfort St",
    "sg:city":"Houston",
    "sg:classifiers":[
        {
            "category":"Wholesale",
            "subcategory":"Medical Equipment & Supplies",
            "type":"Manufacturing & Wholesale Goods"
        }
    ],
    "sg:phone":"+1 713 779 8201",
    "sg:postcode":"77031",
    "sg:province":"TX",
    "wof:name":"Kingstof Medical Equipmen",
    "wof:placetype":"venue"
},
  "geometry": {"coordinates":[-95.534814,29.656391],"type":"Point"}
}