{
  "type": "Feature",
  "properties": {
    "iso:country":"US",
    "sg:address":"204 W San Antonio St",
    "sg:city":"New Braunfels",
    "sg:classifiers":[
        {
            "category":"Professional",
            "subcategory":"Management & Consulting",
            "type":"Services"
        }
    ],
    "sg:phone":"+1 830 609 4242",
    "sg:postcode":"78130",
    "sg:province":"TX",
    "sg:tags":[
        "association"
    ],
    "wof:name":"Greater New Braunfels HBA",
    "wof:placetype":"venue"
},
  "geometry": {"coordinates":[-98.123091,29.704511],"type":"Point"}
}