{
  "type": "Feature",
  "properties": {
    "iso:country":"US",
    "sg:address":"3715 Cypress Key Dr",
    "sg:city":"Spring",
    "sg:classifiers":[
        {
            "category":"Building & Trades",
            "subcategory":"Construction",
            "type":"Services"
        }
    ],
    "sg:phone":"+1 281 651 9926",
    "sg:postcode":"77388",
    "sg:province":"TX",
    "sg:tags":[
        "home",
        "builder",
        "operative",
        "family"
    ],
    "wof:name":"Cypesswood Glen Estates",
    "wof:placetype":"venue"
},
  "geometry": {"coordinates":[-95.475936,30.059162],"type":"Point"}
}