{
  "type": "Feature",
  "properties": {
    "iso:country":"US",
    "sg:address":"2115 W 10th St",
    "sg:city":"Austin",
    "sg:classifiers":[
        {
            "category":"Professional",
            "type":"Services"
        }
    ],
    "sg:phone":"+1 512 320 8667",
    "sg:postcode":"78703",
    "sg:province":"TX",
    "wof:name":"MO of Milc",
    "wof:placetype":"venue"
},
  "geometry": {"coordinates":[-97.769227,30.282838],"type":"Point"}
}