{
  "type": "Feature",
  "properties": {
    "iso:country":"US",
    "sg:address":"303 S Ave G",
    "sg:city":"Haskell",
    "sg:classifiers":[
        {
            "category":"Farming",
            "subcategory":"Farm",
            "type":"Manufacturing & Wholesale Goods"
        }
    ],
    "sg:phone":"+1 940 864 3039",
    "sg:postcode":"79521",
    "sg:province":"TX",
    "sg:tags":[
        "crop",
        "general"
    ],
    "wof:name":"David Miller",
    "wof:placetype":"venue"
},
  "geometry": {"coordinates":[-99.73638800000001,33.154509],"type":"Point"}
}