{
  "type": "Feature",
  "properties": {
    "iso:country":"US",
    "sg:address":"2120 Evergreen St",
    "sg:city":"Garland",
    "sg:classifiers":[
        {
            "category":"Shopping",
            "subcategory":"Clothing, Apparel, & Fashions",
            "type":"Retail Goods"
        }
    ],
    "sg:phone":"+1 972 926 5933",
    "sg:postcode":"75041",
    "sg:province":"TX",
    "wof:name":"Ladies Night Out Lno",
    "wof:placetype":"venue"
},
  "geometry": {"coordinates":[-96.639475,32.889725],"type":"Point"}
}