{
  "type": "Feature",
  "properties": {
    "iso:country":"US",
    "sg:address":"4 S Plaza St",
    "sg:city":"Ladonia",
    "sg:classifiers":[
        {
            "category":"Real Estate",
            "subcategory":"Real Estate Agent",
            "type":"Services"
        }
    ],
    "sg:phone":"+1 903 367 7652",
    "sg:postcode":"75449",
    "sg:province":"TX",
    "wof:name":"Leon Hurse Real Estate",
    "wof:placetype":"venue"
},
  "geometry": {"coordinates":[-95.946713,33.425201],"type":"Point"}
}