{
  "type": "Feature",
  "properties": {
    "iso:country":"US",
    "sg:address":"472 Wicker Way",
    "sg:city":"Burleson",
    "sg:classifiers":[
        {
            "category":"Building & Trades",
            "subcategory":"Construction",
            "type":"Services"
        }
    ],
    "sg:phone":"+1 817 295 6268",
    "sg:postcode":"76028",
    "sg:province":"TX",
    "sg:tags":[
        "painter"
    ],
    "wof:name":"Corona Construction",
    "wof:placetype":"venue"
},
  "geometry": {"coordinates":[-97.36145399999999,32.498165],"type":"Point"}
}