{
  "type": "Feature",
  "properties": {
    "iso:country":"US",
    "sg:address":"2425 W Park Row Dr",
    "sg:city":"Pantego",
    "sg:classifiers":[
        {
            "category":"Travel",
            "subcategory":"Travel Agent",
            "type":"Entertainment"
        }
    ],
    "sg:phone":"+1 817 469 1414",
    "sg:postcode":"76013",
    "sg:province":"TX",
    "sg:tags":[
        "agency",
        "bureau"
    ],
    "sg:website":"www.allports.com",
    "wof:name":"All Port Travel",
    "wof:placetype":"venue"
},
  "geometry": {"coordinates":[-97.14691999999999,32.721404],"type":"Point"}
}