{
  "type": "Feature",
  "properties": {
    "iso:country":"US",
    "sg:address":"12591 Blanchard Rd",
    "sg:city":"Atascosa",
    "sg:classifiers":[
        {
            "category":"Building & Trades",
            "subcategory":"Cleaning & Sanitation",
            "type":"Services"
        }
    ],
    "sg:phone":"+1 210 622 9546",
    "sg:postcode":"78002",
    "sg:province":"TX",
    "sg:tags":[
        "janitor"
    ],
    "wof:name":"Texas Enterprises",
    "wof:placetype":"venue"
},
  "geometry": {"coordinates":[-98.703378,29.298096],"type":"Point"}
}