{
  "type": "Feature",
  "properties": {
    "iso:country":"US",
    "sg:address":"341 W Tyler Ave",
    "sg:city":"Longview",
    "sg:classifiers":[
        {
            "category":"Autos & Motor Vehicles",
            "subcategory":"Automobile Sales",
            "type":"Retail Goods"
        }
    ],
    "sg:phone":"+1 903 758 1452",
    "sg:postcode":"75601",
    "sg:province":"TX",
    "sg:tags":[
        "car",
        "dealer"
    ],
    "wof:name":"Allied Auto & Van Rental",
    "wof:placetype":"venue"
},
  "geometry": {"coordinates":[-94.74708099999999,32.498774],"type":"Point"}
}