{
  "type": "Feature",
  "properties": {
    "iso:country":"US",
    "sg:address":"3204 New Boston Rd",
    "sg:city":"Texarkana",
    "sg:classifiers":[
        {
            "category":"Building & Trades",
            "subcategory":"Electrical",
            "type":"Services"
        },
        {
            "category":"Wholesale",
            "subcategory":"Electrical",
            "type":"Manufacturing & Wholesale Goods"
        }
    ],
    "sg:phone":"+1 903 838 7896",
    "sg:postcode":"75501",
    "sg:province":"TX",
    "sg:tags":[
        "sound",
        "equipment",
        "integrated",
        "system",
        "contractor"
    ],
    "sg:website":"www.regionalsound.com",
    "wof:name":"Regional Sound & Communication",
    "wof:placetype":"venue"
},
  "geometry": {"coordinates":[-94.08527599999999,33.438562],"type":"Point"}
}