{
  "type": "Feature",
  "properties": {
    "iso:country":"US",
    "sg:address":"5840 E Loop 820 S",
    "sg:city":"Fort Worth",
    "sg:classifiers":[
        {
            "category":"Shopping",
            "subcategory":"Clothing, Apparel, & Fashions",
            "type":"Retail Goods"
        }
    ],
    "sg:phone":"+1 817 731 7218",
    "sg:postcode":"76119",
    "sg:province":"TX",
    "wof:name":"Bridesmart",
    "wof:placetype":"venue"
},
  "geometry": {"coordinates":[-97.241146,32.67437],"type":"Point"}
}