{
  "type": "Feature",
  "properties": {
    "iso:country":"US",
    "sg:address":"11093 Northwest Fwy",
    "sg:city":"Houston",
    "sg:classifiers":[
        {
            "category":"Professional",
            "subcategory":"Employment Agencies",
            "type":"Services"
        }
    ],
    "sg:phone":"+1 713 476 9930",
    "sg:postcode":"77092",
    "sg:province":"TX",
    "wof:name":"Mangum Staffing",
    "wof:placetype":"venue"
},
  "geometry": {"coordinates":[-95.483996,29.833489],"type":"Point"}
}