{
  "type": "Feature",
  "properties": {
    "iso:country":"US",
    "sg:address":"1110 E Oak St",
    "sg:city":"Wylie",
    "sg:classifiers":[
        {
            "category":"Communications",
            "type":"Services"
        }
    ],
    "sg:phone":"+1 972 672 1698",
    "sg:postcode":"75098",
    "sg:province":"TX",
    "sg:tags":[
        "communication",
        "telephone"
    ],
    "wof:name":"Teague Communications & Co",
    "wof:placetype":"venue"
},
  "geometry": {"coordinates":[-96.516198,33.01389],"type":"Point"}
}