{
  "type": "Feature",
  "properties": {
    "iso:country":"US",
    "sg:address":"3830 State Hwy 44",
    "sg:city":"Alice",
    "sg:classifiers":[
        {
            "category":"Freight",
            "type":"Transportation"
        }
    ],
    "sg:phone":"+1 361 668 9407",
    "sg:postcode":"78332",
    "sg:province":"TX",
    "sg:tags":[
        "special"
    ],
    "wof:name":"Fourty Four Storage Building",
    "wof:placetype":"venue"
},
  "geometry": {"coordinates":[-98.150429,27.75101],"type":"Point"}
}