{
  "type": "Feature",
  "properties": {
    "iso:country":"US",
    "sg:address":"7603 Park Place Blvd",
    "sg:city":"Houston",
    "sg:classifiers":[
        {
            "category":"Retail",
            "subcategory":"Auto Repair",
            "type":"Services"
        }
    ],
    "sg:phone":"+1 713 649 4411",
    "sg:postcode":"77087",
    "sg:province":"TX",
    "sg:website":"www.mobil.com",
    "wof:name":"Mobil Auto Service",
    "wof:placetype":"venue"
},
  "geometry": {"coordinates":[-95.289216,29.685438],"type":"Point"}
}