{
  "type": "Feature",
  "properties": {
    "iso:country":"US",
    "sg:address":"112 S Masters Dr",
    "sg:city":"Dallas",
    "sg:classifiers":[
        {
            "category":"Building & Trades",
            "subcategory":"Construction",
            "type":"Services"
        }
    ],
    "sg:phone":"+1 972 913 1005",
    "sg:postcode":"75217",
    "sg:province":"TX",
    "sg:tags":[
        "site",
        "clean"
    ],
    "wof:name":"Swift Cleaning Svc",
    "wof:placetype":"venue"
},
  "geometry": {"coordinates":[-96.64838,32.710085],"type":"Point"}
}