{
  "type": "Feature",
  "properties": {
    "iso:country":"US",
    "sg:address":"2905 N Conway Ave",
    "sg:city":"Mission",
    "sg:classifiers":[
        {
            "category":"Professional",
            "type":"Services"
        }
    ],
    "sg:phone":"+1 956 581 4135",
    "sg:postcode":"78574",
    "sg:province":"TX",
    "wof:name":"Wagon City Recreation Board In",
    "wof:placetype":"venue"
},
  "geometry": {"coordinates":[-98.32180700000001,26.238426],"type":"Point"}
}