{
  "type": "Feature",
  "properties": {
    "iso:country":"US",
    "sg:address":"3201 Pinehurst Dr",
    "sg:city":"Plano",
    "sg:classifiers":[
        {
            "category":"Professional",
            "subcategory":"Computer Services",
            "type":"Services"
        }
    ],
    "sg:phone":"+1 972 596 1879",
    "sg:postcode":"75075",
    "sg:province":"TX",
    "sg:tags":[
        "programming"
    ],
    "wof:name":"John A Sparks & Michelle Benum",
    "wof:placetype":"venue"
},
  "geometry": {"coordinates":[-96.755016,33.035618],"type":"Point"}
}