{
  "type": "Feature",
  "properties": {
    "iso:country":"US",
    "sg:address":"121 League St",
    "sg:city":"League City",
    "sg:classifiers":[
        {
            "category":"Wholesale",
            "subcategory":"Machinery & Supplies",
            "type":"Manufacturing & Wholesale Goods"
        }
    ],
    "sg:phone":"+1 281 316 9988",
    "sg:postcode":"77573",
    "sg:province":"TX",
    "sg:tags":[
        "equipment",
        "hydraulic"
    ],
    "wof:name":"League City Hydraulic Hose",
    "wof:placetype":"venue"
},
  "geometry": {"coordinates":[-95.09800799999999,29.508226],"type":"Point"}
}