{
  "type": "Feature",
  "properties": {
    "iso:country":"US",
    "sg:address":"1011 Village Square Dr",
    "sg:city":"Tomball",
    "sg:classifiers":[
        {
            "category":"Wholesale",
            "subcategory":"Vending Machines",
            "type":"Manufacturing & Wholesale Goods"
        }
    ],
    "sg:phone":"+1 281 290 8571",
    "sg:postcode":"77375",
    "sg:province":"TX",
    "sg:tags":[
        "operator"
    ],
    "wof:name":"VI Bell Sales",
    "wof:placetype":"venue"
},
  "geometry": {"coordinates":[-95.627827,30.0953],"type":"Point"}
}