{
  "type": "Feature",
  "properties": {
    "iso:country":"US",
    "sg:address":"617 W Kearney St Ste 205",
    "sg:city":"Mesquite",
    "sg:classifiers":[
        {
            "category":"Shopping",
            "subcategory":"Bicycles & Sporting Goods",
            "type":"Retail Goods"
        }
    ],
    "sg:phone":"+1 214 351 4500",
    "sg:postcode":"75149",
    "sg:province":"TX",
    "wof:name":"Feminine Protection",
    "wof:placetype":"venue"
},
  "geometry": {"coordinates":[-96.60520200000001,32.770901],"type":"Point"}
}