{
  "type": "Feature",
  "properties": {
    "iso:country":"US",
    "sg:address":"3835 Mambrino Hwy",
    "sg:city":"Granbury",
    "sg:classifiers":[
        {
            "category":"Education",
            "subcategory":"School",
            "type":"Public Place"
        }
    ],
    "sg:phone":"+1 817 408 4900",
    "sg:postcode":"76048",
    "sg:province":"TX",
    "sg:tags":[
        "elementary"
    ],
    "sg:website":"http://www.granbury.k12.tx.us",
    "wof:name":"Manbrino School",
    "wof:placetype":"venue"
},
  "geometry": {"coordinates":[-97.713886,32.380287],"type":"Point"}
}