{
  "type": "Feature",
  "properties": {
    "iso:country":"US",
    "sg:address":"2814 International Blvd",
    "sg:city":"Brownsville",
    "sg:classifiers":[
        {
            "category":"Food & Beverages",
            "subcategory":"Groceries & Convenience Stores",
            "type":"Retail Goods"
        }
    ],
    "sg:phone":"+1 956 542 8695",
    "sg:postcode":"78521",
    "sg:province":"TX",
    "sg:tags":[
        "grocer"
    ],
    "wof:name":"Lopez Super Markets",
    "wof:placetype":"venue"
},
  "geometry": {"coordinates":[-97.477794,25.908625],"type":"Point"}
}