{
  "type": "Feature",
  "properties": {
    "iso:country":"US",
    "sg:address":"8243 Squires Place Dr",
    "sg:city":"Houston",
    "sg:classifiers":[
        {
            "category":"Professional",
            "type":"Services"
        }
    ],
    "sg:phone":"+1 281 277 3239",
    "sg:postcode":"77083",
    "sg:province":"TX",
    "wof:name":"Beyond Bathing",
    "wof:placetype":"venue"
},
  "geometry": {"coordinates":[-95.677396,29.685841],"type":"Point"}
}