{
  "type": "Feature",
  "properties": {
    "iso:country":"US",
    "sg:address":"8250 W Little York Rd",
    "sg:city":"Houston",
    "sg:classifiers":[
        {
            "category":"Retail",
            "subcategory":"Auto Repair",
            "type":"Services"
        }
    ],
    "sg:phone":"+1 713 466 0303",
    "sg:postcode":"77040",
    "sg:province":"TX",
    "sg:tags":[
        "body",
        "shop"
    ],
    "wof:name":"Sterling Auto Body Centers West Little York",
    "wof:placetype":"venue"
},
  "geometry": {"coordinates":[-95.519402,29.865601],"type":"Point"}
}