{
  "type": "Feature",
  "properties": {
    "iso:country":"US",
    "sg:address":"125 Turner St",
    "sg:city":"Waco",
    "sg:classifiers":[
        {
            "category":"Organizations",
            "subcategory":"Religious Organization",
            "type":"Services"
        }
    ],
    "sg:phone":"+1 254 752 1822",
    "sg:postcode":"76704",
    "sg:province":"TX",
    "sg:tags":[
        "place",
        "worship",
        "church"
    ],
    "wof:name":"Wesley United Methodist Church",
    "wof:placetype":"venue"
},
  "geometry": {"coordinates":[-97.123177,31.56815],"type":"Point"}
}