{
  "type": "Feature",
  "properties": {
    "iso:country":"US",
    "sg:address":"917 N Hampton Rd",
    "sg:city":"Dallas",
    "sg:classifiers":[
        {
            "category":"Food & Beverages",
            "subcategory":"Bakery",
            "type":"Retail Goods"
        }
    ],
    "sg:phone":"+1 972 223 1114",
    "sg:postcode":"75208",
    "sg:province":"TX",
    "sg:tags":[
        "sandwich"
    ],
    "wof:name":"Subway Sandwiches & Salads",
    "wof:placetype":"venue"
},
  "geometry": {"coordinates":[-96.856796,32.7556],"type":"Point"}
}