{
  "type": "Feature",
  "properties": {
    "iso:country":"US",
    "sg:address":"4835 Lyndon B Johnson Fwy",
    "sg:city":"Dallas",
    "sg:classifiers":[
        {
            "category":"Professional",
            "subcategory":"Lawyer & Legal Services",
            "type":"Services"
        }
    ],
    "sg:phone":"+1 972 387 0007",
    "sg:postcode":"75244",
    "sg:province":"TX",
    "wof:name":"Jackson Thomas P Atty",
    "wof:placetype":"venue"
},
  "geometry": {"coordinates":[-96.824349,32.927397],"type":"Point"}
}