{
  "type": "Feature",
  "properties": {
    "iso:country":"US",
    "sg:address":"181 Lexington Dr",
    "sg:city":"Austin",
    "sg:classifiers":[
        {
            "category":"Professional",
            "type":"Services"
        }
    ],
    "sg:phone":"+1 512 466 8982",
    "sg:postcode":"78737",
    "sg:province":"TX",
    "sg:tags":[
        "field",
        "oil"
    ],
    "wof:name":"Tfh Interests, Inc",
    "wof:placetype":"venue"
},
  "geometry": {"coordinates":[-97.984932,30.199325],"type":"Point"}
}