{
  "type": "Feature",
  "properties": {
    "iso:country":"US",
    "sg:address":"2710 Civic Cir",
    "sg:city":"Amarillo",
    "sg:classifiers":[
        {
            "category":"Personal",
            "subcategory":"Beauty Salon",
            "type":"Services"
        }
    ],
    "sg:phone":"+1 806 358 7740",
    "sg:postcode":"79109",
    "sg:province":"TX",
    "sg:tags":[
        "shop"
    ],
    "wof:name":"A Little Off The Top",
    "wof:placetype":"venue"
},
  "geometry": {"coordinates":[-101.868044,35.191131],"type":"Point"}
}