{
  "type": "Feature",
  "properties": {
    "iso:country":"US",
    "sg:address":"2109 N Grandview Ave",
    "sg:city":"Odessa",
    "sg:classifiers":[
        {
            "category":"Organizations",
            "subcategory":"Religious Organization",
            "type":"Services"
        }
    ],
    "sg:phone":"+1 432 366 2300",
    "sg:postcode":"79761",
    "sg:province":"TX",
    "sg:tags":[
        "church"
    ],
    "wof:name":"Church Of God Grandview",
    "wof:placetype":"venue"
},
  "geometry": {"coordinates":[-102.34592000000001,31.870757],"type":"Point"}
}