{
  "type": "Feature",
  "properties": {
    "iso:country":"US",
    "sg:address":"1037 Pyramid Dr",
    "sg:city":"Garland",
    "sg:classifiers":[
        {
            "category":"Professional",
            "type":"Services"
        }
    ],
    "sg:phone":"+1 972 414 0964",
    "sg:postcode":"75040",
    "sg:province":"TX",
    "wof:name":"U Name It Monogramming & More",
    "wof:placetype":"venue"
},
  "geometry": {"coordinates":[-96.61946399999999,32.934429],"type":"Point"}
}