{
  "type": "Feature",
  "properties": {
    "iso:country":"US",
    "sg:address":"6230 Cornell Dr",
    "sg:city":"Corpus Christi",
    "sg:classifiers":[
        {
            "category":"Building & Trades",
            "subcategory":"Landscaping Services",
            "type":"Services"
        }
    ],
    "sg:phone":"+1 361 960 7433",
    "sg:postcode":"78414",
    "sg:province":"TX",
    "wof:name":"Bay Area Lawn Maintenance",
    "wof:placetype":"venue"
},
  "geometry": {"coordinates":[-97.379344,27.66956],"type":"Point"}
}