{
  "type": "Feature",
  "properties": {
    "iso:country":"US",
    "sg:address":"2321 91st St",
    "sg:city":"Lubbock",
    "sg:classifiers":[
        {
            "category":"Autos & Motor Vehicles",
            "subcategory":"Automobile Sales",
            "type":"Retail Goods"
        }
    ],
    "sg:phone":"+1 806 792 9355",
    "sg:postcode":"79423",
    "sg:province":"TX",
    "sg:tags":[
        "used"
    ],
    "wof:name":"Kerr Motors",
    "wof:placetype":"venue"
},
  "geometry": {"coordinates":[-101.86611600000001,33.511939],"type":"Point"}
}