{
  "type": "Feature",
  "properties": {
    "iso:country":"US",
    "sg:address":"511 Joyner Cir",
    "sg:city":"Killeen",
    "sg:classifiers":[
        {
            "category":"Building & Trades",
            "subcategory":"Construction",
            "type":"Services"
        }
    ],
    "sg:phone":"+1 254 554 2327",
    "sg:postcode":"76541",
    "sg:province":"TX",
    "sg:tags":[
        "contractor",
        "mason"
    ],
    "wof:name":"Mexicano Masonry",
    "wof:placetype":"venue"
},
  "geometry": {"coordinates":[-97.73705200000001,31.11612],"type":"Point"}
}