{
  "type": "Feature",
  "properties": {
    "iso:country":"US",
    "sg:address":"6402 S Padre Island Dr",
    "sg:city":"Corpus Christi",
    "sg:classifiers":[
        {
            "category":"Professional",
            "type":"Services"
        }
    ],
    "sg:phone":"+1 361 980 1042",
    "sg:postcode":"78412",
    "sg:province":"TX",
    "sg:tags":[
        "establishment"
    ],
    "wof:name":"Q Ban 1 Inc",
    "wof:placetype":"venue"
},
  "geometry": {"coordinates":[-97.35381700000001,27.699987],"type":"Point"}
}