{
  "type": "Feature",
  "properties": {
    "iso:country":"US",
    "sg:address":"14958 Doria Dr",
    "sg:city":"Austin",
    "sg:classifiers":[
        {
            "category":"Professional",
            "subcategory":"Business Services",
            "type":"Services"
        }
    ],
    "sg:phone":"+1 512 246 1206",
    "sg:postcode":"78728",
    "sg:province":"TX",
    "wof:name":"Asa Financial Services",
    "wof:placetype":"venue"
},
  "geometry": {"coordinates":[-97.68131700000001,30.449016],"type":"Point"}
}