{
  "type": "Feature",
  "properties": {
    "iso:country":"US",
    "sg:address":"8327 Quail Hills Dr",
    "sg:city":"Missouri City",
    "sg:classifiers":[
        {
            "category":"Organizations",
            "subcategory":"Religious Organization",
            "type":"Services"
        }
    ],
    "sg:phone":"+1 281 438 8582",
    "sg:postcode":"77489",
    "sg:province":"TX",
    "sg:tags":[
        "church"
    ],
    "wof:name":"Holy Of Holies Deliverance Chr",
    "wof:placetype":"venue"
},
  "geometry": {"coordinates":[-95.51253800000001,29.589507],"type":"Point"}
}