{
  "type": "Feature",
  "properties": {
    "iso:country":"US",
    "sg:address":"1313 Kemp Blvd",
    "sg:city":"Wichita Falls",
    "sg:classifiers":[
        {
            "category":"Retail",
            "subcategory":"Animal Services",
            "type":"Services"
        }
    ],
    "sg:phone":"+1 940 767 7998",
    "sg:postcode":"76309",
    "sg:province":"TX",
    "sg:tags":[
        "pet",
        "grooming",
        "washing"
    ],
    "wof:name":"Pampered Pets Grooming Salon",
    "wof:placetype":"venue"
},
  "geometry": {"coordinates":[-98.520886,33.900669],"type":"Point"}
}