{
  "type": "Feature",
  "properties": {
    "iso:country":"US",
    "sg:address":"3755 N Josey Ln",
    "sg:city":"Carrollton",
    "sg:classifiers":[
        {
            "category":"Government",
            "subcategory":"Post Office",
            "type":"Public Place"
        }
    ],
    "sg:phone":"+1 972 939 0306",
    "sg:postcode":"75007",
    "sg:province":"TX",
    "wof:name":"US Post Office",
    "wof:placetype":"venue"
},
  "geometry": {"coordinates":[-96.886989,33.009219],"type":"Point"}
}