{
  "type": "Feature",
  "properties": {
    "iso:country":"US",
    "sg:address":"3722 Candlecreek Ct",
    "sg:city":"San Antonio",
    "sg:classifiers":[
        {
            "category":"Home & Garden",
            "subcategory":"Home Furnishings",
            "type":"Retail Goods"
        }
    ],
    "sg:phone":"+1 210 661 6327",
    "sg:postcode":"78244",
    "sg:province":"TX",
    "wof:name":"Jorge Lira",
    "wof:placetype":"venue"
},
  "geometry": {"coordinates":[-98.36448900000001,29.457889],"type":"Point"}
}