{
  "type": "Feature",
  "properties": {
    "iso:country":"US",
    "sg:address":"16218 Amberwood Rd",
    "sg:city":"Dallas",
    "sg:classifiers":[
        {
            "category":"Shopping",
            "subcategory":"Florist",
            "type":"Retail Goods"
        }
    ],
    "sg:phone":"+1 972 381 0217",
    "sg:postcode":"75248",
    "sg:province":"TX",
    "wof:name":"Floral Illusions",
    "wof:placetype":"venue"
},
  "geometry": {"coordinates":[-96.79569600000001,32.97227],"type":"Point"}
}