{
  "type": "Feature",
  "properties": {
    "iso:country":"US",
    "sg:address":"1810 Laredo St",
    "sg:city":"Laredo",
    "sg:classifiers":[
        {
            "category":"Professional",
            "subcategory":"Business Services",
            "type":"Services"
        }
    ],
    "sg:phone":"+1 956 286 9396",
    "sg:postcode":"78043",
    "sg:province":"TX",
    "wof:name":"All Design Fabrics",
    "wof:placetype":"venue"
},
  "geometry": {"coordinates":[-99.477361,27.507563],"type":"Point"}
}