{
  "type": "Feature",
  "properties": {
    "iso:country":"US",
    "sg:address":"1310 Boyles St",
    "sg:city":"Houston",
    "sg:classifiers":[
        {
            "category":"Building & Trades",
            "subcategory":"Construction",
            "type":"Services"
        }
    ],
    "sg:phone":"+1 713 675 7521",
    "sg:postcode":"77020",
    "sg:province":"TX",
    "sg:tags":[
        "painter"
    ],
    "wof:name":"Te-Ko Contractors Inc",
    "wof:placetype":"venue"
},
  "geometry": {"coordinates":[-95.29879800000001,29.7679],"type":"Point"}
}