{
  "type": "Feature",
  "properties": {
    "iso:country":"US",
    "sg:address":"4100 S Staples St",
    "sg:city":"Corpus Christi",
    "sg:classifiers":[
        {
            "category":"Shopping",
            "subcategory":"Clothing, Apparel, & Fashions",
            "type":"Retail Goods"
        }
    ],
    "sg:phone":"+1 361 852 7791",
    "sg:postcode":"78411",
    "sg:province":"TX",
    "sg:tags":[
        "shop",
        "bridal"
    ],
    "wof:name":"Bridal Boutique & After 5",
    "wof:placetype":"venue"
},
  "geometry": {"coordinates":[-97.377999,27.724743],"type":"Point"}
}