{
  "type": "Feature",
  "properties": {
    "iso:country":"US",
    "sg:address":"9400 White Settlement Rd",
    "sg:city":"Fort Worth",
    "sg:classifiers":[
        {
            "category":"Food & Beverages",
            "subcategory":"Groceries & Convenience Stores",
            "type":"Retail Goods"
        },
        {
            "category":"Autos & Motor Vehicles",
            "subcategory":"Fuel & Gas Station",
            "type":"Retail Goods"
        }
    ],
    "sg:phone":"+1 817 246 2946",
    "sg:postcode":"76108",
    "sg:province":"TX",
    "sg:tags":[
        "station",
        "gasoline",
        "oil"
    ],
    "wof:name":"Diamond Shamrock",
    "wof:placetype":"venue"
},
  "geometry": {"coordinates":[-97.48029,32.760951],"type":"Point"}
}