{
  "type": "Feature",
  "properties": {
    "iso:country":"US",
    "sg:address":"2030 Quarry St",
    "sg:city":"Dallas",
    "sg:classifiers":[
        {
            "category":"Autos & Motor Vehicles",
            "subcategory":"Automobile Sales",
            "type":"Retail Goods"
        }
    ],
    "sg:phone":"+1 214 637 2279",
    "sg:postcode":"75212",
    "sg:province":"TX",
    "sg:tags":[
        "car",
        "dealer"
    ],
    "wof:name":"T & T Auto Sales",
    "wof:placetype":"venue"
},
  "geometry": {"coordinates":[-96.917039,32.769689],"type":"Point"}
}