{
  "type": "Feature",
  "properties": {
    "iso:country":"US",
    "sg:address":"8703 Serenade Ln",
    "sg:city":"Houston",
    "sg:classifiers":[
        {
            "category":"Professional",
            "type":"Services"
        }
    ],
    "sg:phone":"+1 832 467 2000",
    "sg:postcode":"77040",
    "sg:province":"TX",
    "sg:tags":[
        "establishment"
    ],
    "wof:name":"Glasteel",
    "wof:placetype":"venue"
},
  "geometry": {"coordinates":[-95.52877100000001,29.887394],"type":"Point"}
}