{
  "type": "Feature",
  "properties": {
    "iso:country":"US",
    "sg:address":"17455 Spring Cypress Rd",
    "sg:city":"Cypress",
    "sg:classifiers":[
        {
            "category":"Food & Beverages",
            "subcategory":"Groceries & Convenience Stores",
            "type":"Retail Goods"
        }
    ],
    "sg:phone":"+1 281 304 0859",
    "sg:postcode":"77429",
    "sg:province":"TX",
    "sg:tags":[
        "grocer"
    ],
    "wof:name":"Kroger",
    "wof:placetype":"venue"
},
  "geometry": {"coordinates":[-95.69098099999999,29.972545],"type":"Point"}
}