{
  "type": "Feature",
  "properties": {
    "iso:country":"US",
    "sg:address":"13331 Preston Rd",
    "sg:city":"Dallas",
    "sg:classifiers":[
        {
            "category":"Shopping",
            "subcategory":"Clothing, Apparel, & Fashions",
            "type":"Retail Goods"
        }
    ],
    "sg:phone":"+1 972 763 0943",
    "sg:postcode":"75240",
    "sg:province":"TX",
    "sg:tags":[
        "accessory",
        "clothing",
        "women's"
    ],
    "sg:website":"www.ashleystewart.com",
    "wof:name":"Ashley Stewart",
    "wof:placetype":"venue"
},
  "geometry": {"coordinates":[-96.803774,32.93111],"type":"Point"}
}