{
  "type": "Feature",
  "properties": {
    "iso:country":"US",
    "sg:address":"2300 W Michigan Ave",
    "sg:city":"Midland",
    "sg:classifiers":[
        {
            "category":"Health Services",
            "subcategory":"Doctor",
            "type":"Services"
        }
    ],
    "sg:phone":"+1 432 570 6291",
    "sg:postcode":"79701",
    "sg:province":"TX",
    "sg:tags":[
        "medical"
    ],
    "wof:name":"Institute of Pain MGT Inc",
    "wof:placetype":"venue"
},
  "geometry": {"coordinates":[-102.10298899999999,31.997421],"type":"Point"}
}