{
  "type": "Feature",
  "properties": {
    "iso:country":"US",
    "sg:address":"7705 Callbram Ln",
    "sg:city":"Austin",
    "sg:classifiers":[
        {
            "category":"Building & Trades",
            "subcategory":"Construction",
            "type":"Services"
        }
    ],
    "sg:phone":"+1 512 288 6523",
    "sg:postcode":"78736",
    "sg:province":"TX",
    "sg:tags":[
        "air",
        "heating",
        "conditioning/hvac"
    ],
    "wof:name":"Able Heating & Air Conditioning",
    "wof:placetype":"venue"
},
  "geometry": {"coordinates":[-97.89252,30.232532],"type":"Point"}
}