{
  "type": "Feature",
  "properties": {
    "iso:country":"US",
    "sg:address":"1309 W Harris Ave",
    "sg:city":"Pasadena",
    "sg:classifiers":[
        {
            "category":"Retail",
            "subcategory":"Auto Repair",
            "type":"Services"
        }
    ],
    "sg:phone":"+1 713 472 3863",
    "sg:postcode":"77506",
    "sg:province":"TX",
    "sg:tags":[
        "repairing",
        "automobile"
    ],
    "wof:name":"Galindo's Auto Svc",
    "wof:placetype":"venue"
},
  "geometry": {"coordinates":[-95.22795000000001,29.697836],"type":"Point"}
}