{
  "type": "Feature",
  "properties": {
    "iso:country":"US",
    "sg:address":"905 Ashland Blvd Apt B",
    "sg:city":"Channelview",
    "sg:classifiers":[
        {
            "category":"Real Estate",
            "subcategory":"Real Estate Operator",
            "type":"Services"
        }
    ],
    "sg:phone":"+1 281 452 1981",
    "sg:postcode":"77530",
    "sg:province":"TX",
    "sg:tags":[
        "apartment"
    ],
    "wof:name":"Casa De Grande Apartments",
    "wof:placetype":"venue"
},
  "geometry": {"coordinates":[-95.135201,29.7911],"type":"Point"}
}