{
  "type": "Feature",
  "properties": {
    "iso:country":"US",
    "sg:address":"615 N Main St",
    "sg:city":"Euless",
    "sg:classifiers":[
        {
            "category":"Professional",
            "type":"Services"
        },
        {
            "category":"Retail",
            "subcategory":"Auto Rental",
            "type":"Services"
        },
        {
            "category":"Travel",
            "subcategory":"Travel Agent",
            "type":"Entertainment"
        },
        {
            "category":"Airport",
            "type":"Transportation"
        }
    ],
    "sg:phone":"+1 214 810 5994",
    "sg:postcode":"76039",
    "sg:province":"TX",
    "sg:tags":[
        "consultant",
        "limousine"
    ],
    "sg:website":"http://www.yext.com/p/superpages/godfather-limousine-euless-texas.html",
    "wof:name":"Godfather Limousine",
    "wof:placetype":"venue"
},
  "geometry": {"coordinates":[-97.082527,32.854044],"type":"Point"}
}