{
  "type": "Feature",
  "properties": {
    "iso:country":"US",
    "sg:address":"1704 N Jefferson St",
    "sg:city":"La Grange",
    "sg:classifiers":[
        {
            "category":"Professional",
            "subcategory":"Business Services",
            "type":"Services"
        }
    ],
    "sg:phone":"+1 979 968 9191",
    "sg:postcode":"78945",
    "sg:province":"TX",
    "wof:name":"Fast Action Bail Bonds",
    "wof:placetype":"venue"
},
  "geometry": {"coordinates":[-96.88101,29.926724],"type":"Point"}
}