{
  "type": "Feature",
  "properties": {
    "iso:country":"US",
    "sg:address":"2326 W Walnut St",
    "sg:city":"Garland",
    "sg:classifiers":[
        {
            "category":"Personal",
            "subcategory":"Beauty Salon",
            "type":"Services"
        }
    ],
    "sg:phone":"+1 972 276 6732",
    "sg:postcode":"75042",
    "sg:province":"TX",
    "sg:tags":[
        "shop"
    ],
    "wof:name":"Marlenes Beauty Salon & Cutter",
    "wof:placetype":"venue"
},
  "geometry": {"coordinates":[-96.662875,32.916271],"type":"Point"}
}