{
  "type": "Feature",
  "properties": {
    "iso:country":"US",
    "sg:address":"705 Main St",
    "sg:city":"Sulphur Springs",
    "sg:classifiers":[
        {
            "category":"Ice Cream",
            "type":"Food & Drink"
        }
    ],
    "sg:menulink":"http://www.allmenus.com/tx/sulphur-springs/162536-dairy-queen/menu/",
    "sg:phone":"+1 903 885 3640",
    "sg:postcode":"75482",
    "sg:province":"TX",
    "sg:tags":[
        "burger",
        "american"
    ],
    "wof:name":"Dairy Queen",
    "wof:placetype":"venue"
},
  "geometry": {"coordinates":[-95.609284,33.135532],"type":"Point"}
}