{
  "type": "Feature",
  "properties": {
    "iso:country":"US",
    "sg:address":"511 W 7th St",
    "sg:city":"Littlefield",
    "sg:classifiers":[
        {
            "category":"Social Services",
            "subcategory":"Child Care",
            "type":"Services"
        }
    ],
    "sg:phone":"+1 806 385 5265",
    "sg:postcode":"79339",
    "sg:province":"TX",
    "sg:tags":[
        "kindergarten",
        "academic",
        "school"
    ],
    "wof:name":"Shapes Little Steps Head Start",
    "wof:placetype":"venue"
},
  "geometry": {"coordinates":[-102.334746,33.920228],"type":"Point"}
}