{
  "type": "Feature",
  "properties": {
    "iso:country":"US",
    "sg:address":"14008 Lago Grande Dr",
    "sg:city":"El Paso",
    "sg:classifiers":[
        {
            "category":"Retail",
            "subcategory":"Laundry & Dry Cleaning",
            "type":"Services"
        }
    ],
    "sg:phone":"+1 915 852 9779",
    "sg:postcode":"79928",
    "sg:province":"TX",
    "sg:tags":[
        "cleaners",
        "rug",
        "carpet"
    ],
    "wof:name":"Horizon Steam Clean",
    "wof:placetype":"venue"
},
  "geometry": {"coordinates":[-106.195195,31.683666],"type":"Point"}
}