{
  "type": "Feature",
  "properties": {
    "iso:country":"US",
    "sg:address":"200 S Spring Creek Dr",
    "sg:city":"Richardson",
    "sg:classifiers":[
        {
            "category":"Restaurant",
            "type":"Food & Drink"
        }
    ],
    "sg:phone":"+1 972 386 5311",
    "sg:postcode":"75081",
    "sg:province":"TX",
    "sg:tags":[
        "eating"
    ],
    "wof:name":"Grill Doctor",
    "wof:placetype":"venue"
},
  "geometry": {"coordinates":[-96.68782899999999,32.942828],"type":"Point"}
}