{
  "type": "Feature",
  "properties": {
    "iso:country":"US",
    "sg:address":"9710 S Mason Rd",
    "sg:city":"Richmond",
    "sg:classifiers":[
        {
            "category":"Banks & Credit Unions",
            "subcategory":"Bank",
            "type":"Services"
        }
    ],
    "sg:phone":"+1 281 232 3003",
    "sg:postcode":"77407",
    "sg:province":"TX",
    "sg:tags":[
        "saving",
        "commercial"
    ],
    "wof:name":"Valuebank Texas",
    "wof:placetype":"venue"
},
  "geometry": {"coordinates":[-95.742867,29.70306],"type":"Point"}
}