{
  "type": "Feature",
  "properties": {
    "iso:country":"US",
    "sg:address":"2509 Fm 1960 Rd E Ste A",
    "sg:city":"Houston",
    "sg:classifiers":[
        {
            "category":"Manufacturing",
            "subcategory":"Tools & Machinery",
            "type":"Manufacturing & Wholesale Goods"
        }
    ],
    "sg:phone":"+1 281 682 0877",
    "sg:postcode":"77073",
    "sg:province":"TX",
    "sg:tags":[
        "springs-wholesale",
        "manufacturer"
    ],
    "wof:name":"Las Salsitas By Spring Taquetia",
    "wof:placetype":"venue"
},
  "geometry": {"coordinates":[-95.38940700000001,30.022826],"type":"Point"}
}