{
  "type": "Feature",
  "properties": {
    "iso:country":"US",
    "sg:address":"283 N Willis St",
    "sg:city":"Abilene",
    "sg:classifiers":[
        {
            "category":"Freight",
            "type":"Transportation"
        }
    ],
    "sg:phone":"+1 325 677 3428",
    "sg:postcode":"79603",
    "sg:province":"TX",
    "sg:tags":[
        "commercial",
        "storage"
    ],
    "wof:name":"Abilene Self-Storage",
    "wof:placetype":"venue"
},
  "geometry": {"coordinates":[-99.763831,32.451939],"type":"Point"}
}