{
  "type": "Feature",
  "properties": {
    "iso:country":"US",
    "sg:address":"2700 W Grauwyler Rd",
    "sg:city":"Irving",
    "sg:classifiers":[
        {
            "category":"Real Estate",
            "subcategory":"Real Estate Operator",
            "type":"Services"
        }
    ],
    "sg:phone":"+1 972 986 5944",
    "sg:postcode":"75061",
    "sg:province":"TX",
    "sg:tags":[
        "building",
        "apartment"
    ],
    "wof:name":"Executive Apartments",
    "wof:placetype":"venue"
},
  "geometry": {"coordinates":[-96.981634,32.828945],"type":"Point"}
}