{
  "type": "Feature",
  "properties": {
    "iso:country":"US",
    "sg:address":"4505 E Veterans Memorial Blvd",
    "sg:city":"Killeen",
    "sg:classifiers":[
        {
            "category":"Organizations",
            "subcategory":"Community Association",
            "type":"Services"
        }
    ],
    "sg:phone":"+1 254 690 0002",
    "sg:postcode":"76543",
    "sg:province":"TX",
    "sg:tags":[
        "club"
    ],
    "wof:name":"Club Fusion",
    "wof:placetype":"venue"
},
  "geometry": {"coordinates":[-97.693347,31.097932],"type":"Point"}
}