{
  "type": "Feature",
  "properties": {
    "iso:country":"US",
    "sg:address":"2021 Texas Ave S",
    "sg:city":"Bryan",
    "sg:classifiers":[
        {
            "category":"Professional",
            "subcategory":"Advertising",
            "type":"Services"
        }
    ],
    "sg:phone":"+1 979 779 6245",
    "sg:postcode":"77802",
    "sg:province":"TX",
    "sg:tags":[
        "mailing",
        "shipping"
    ],
    "wof:name":"De Lucia Mail Svc",
    "wof:placetype":"venue"
},
  "geometry": {"coordinates":[-96.360702,30.650187],"type":"Point"}
}