{
  "type": "Feature",
  "properties": {
    "iso:country":"US",
    "sg:address":"1434 S Clack St",
    "sg:city":"Abilene",
    "sg:classifiers":[
        {
            "category":"Autos & Motor Vehicles",
            "subcategory":"Automobile Sales",
            "type":"Retail Goods"
        }
    ],
    "sg:phone":"+1 325 437 2874",
    "sg:postcode":"79605",
    "sg:province":"TX",
    "sg:tags":[
        "car",
        "dealer"
    ],
    "wof:name":"Abilene Auto Mall",
    "wof:placetype":"venue"
},
  "geometry": {"coordinates":[-99.787594,32.431963],"type":"Point"}
}