{
  "type": "Feature",
  "properties": {
    "iso:country":"US",
    "sg:address":"9804 Beck Cir",
    "sg:city":"Austin",
    "sg:classifiers":[
        {
            "category":"Retail",
            "subcategory":"Auto Repair",
            "type":"Services"
        }
    ],
    "sg:phone":"+1 512 339 9239",
    "sg:postcode":"78758",
    "sg:province":"TX",
    "sg:tags":[
        "repairing",
        "automobile",
        "general"
    ],
    "wof:name":"Japanese Auto Tech Inc",
    "wof:placetype":"venue"
},
  "geometry": {"coordinates":[-97.71461600000001,30.375001],"type":"Point"}
}