{
  "type": "Feature",
  "properties": {
    "iso:country":"US",
    "sg:address":"3301 101st St",
    "sg:city":"Lubbock",
    "sg:classifiers":[
        {
            "category":"Health Services",
            "subcategory":"Clinic",
            "type":"Services"
        },
        {
            "category":"Health Services",
            "subcategory":"Health Practitioner",
            "type":"Services"
        }
    ],
    "sg:phone":"+1 806 794 1240",
    "sg:postcode":"79423",
    "sg:province":"TX",
    "sg:tags":[
        "psychologist",
        "specialty",
        "outpatient"
    ],
    "wof:name":"Shirley Willis PHD",
    "wof:placetype":"venue"
},
  "geometry": {"coordinates":[-101.887638,33.502313],"type":"Point"}
}