{
  "type": "Feature",
  "properties": {
    "iso:country":"US",
    "sg:address":"904 Wooded Creek Ln",
    "sg:city":"Mc Kinney",
    "sg:classifiers":[
        {
            "category":"Professional",
            "subcategory":"Computer Services",
            "type":"Services"
        }
    ],
    "sg:phone":"+1 214 952 9177",
    "sg:postcode":"75071",
    "sg:province":"TX",
    "sg:tags":[
        "consulting",
        "technology"
    ],
    "wof:name":"12 Feet Inc",
    "wof:placetype":"venue"
},
  "geometry": {"coordinates":[-96.654425,33.205494],"type":"Point"}
}