{
  "type": "Feature",
  "properties": {
    "iso:country":"US",
    "sg:address":"1213 W Waco Dr",
    "sg:city":"Waco",
    "sg:classifiers":[
        {
            "category":"Retail",
            "subcategory":"Auto Repair",
            "type":"Services"
        }
    ],
    "sg:phone":"+1 254 235 1812",
    "sg:postcode":"76707",
    "sg:province":"TX",
    "sg:tags":[
        "repairing",
        "automobile"
    ],
    "wof:name":"Pop's & Son",
    "wof:placetype":"venue"
},
  "geometry": {"coordinates":[-97.143201,31.554456],"type":"Point"}
}