{
  "type": "Feature",
  "properties": {
    "iso:country":"US",
    "sg:address":"4760 Beechnut St",
    "sg:city":"Houston",
    "sg:classifiers":[
        {
            "category":"Professional",
            "type":"Services"
        }
    ],
    "sg:phone":"+1 713 222 2020",
    "sg:postcode":"77096",
    "sg:province":"TX",
    "sg:tags":[
        "establishment"
    ],
    "wof:name":"Advantage Eye Care",
    "wof:placetype":"venue"
},
  "geometry": {"coordinates":[-95.461197,29.689288],"type":"Point"}
}