{
  "type": "Feature",
  "properties": {
    "iso:country":"US",
    "sg:address":"5118 I- 30",
    "sg:city":"Greenville",
    "sg:classifiers":[
        {
            "category":"Travel",
            "subcategory":"Hotels & Motels",
            "type":"Entertainment"
        }
    ],
    "sg:phone":"+1 903 454 9200",
    "sg:postcode":"75402",
    "sg:province":"TX",
    "wof:name":"Royal Inns",
    "wof:placetype":"venue"
},
  "geometry": {"coordinates":[-96.097264,33.11919],"type":"Point"}
}