{
  "type": "Feature",
  "properties": {
    "iso:country":"US",
    "sg:address":"11 Laguna Rd",
    "sg:city":"Montgomery",
    "sg:classifiers":[
        {
            "category":"Professional",
            "subcategory":"Business Services",
            "type":"Services"
        }
    ],
    "sg:phone":"+1 936 582 6058",
    "sg:postcode":"77356",
    "sg:province":"TX",
    "wof:name":"Staging Designs of Texas",
    "wof:placetype":"venue"
},
  "geometry": {"coordinates":[-95.643428,30.400367],"type":"Point"}
}