{
  "type": "Feature",
  "properties": {
    "iso:country":"US",
    "sg:address":"7800 Washington Ave",
    "sg:city":"Houston",
    "sg:classifiers":[
        {
            "category":"Manufacturing",
            "subcategory":"Signs",
            "type":"Manufacturing & Wholesale Goods"
        },
        {
            "category":"Manufacturing",
            "subcategory":"Paper Products",
            "type":"Manufacturing & Wholesale Goods"
        }
    ],
    "sg:phone":"+1 713 869 5900",
    "sg:postcode":"77007",
    "sg:province":"TX",
    "sg:tags":[
        "designer",
        "producer",
        "mfg",
        "spec",
        "converted",
        "display"
    ],
    "sg:website":"www.brianthomasdisplay.com",
    "wof:name":"Brian Thomas Display & Packg",
    "wof:placetype":"venue"
},
  "geometry": {"coordinates":[-95.43370899999999,29.78054],"type":"Point"}
}