{
  "type": "Feature",
  "properties": {
    "iso:country":"US",
    "sg:address":"131 N General McMullen Dr",
    "sg:city":"San Antonio",
    "sg:classifiers":[
        {
            "category":"Autos & Motor Vehicles",
            "subcategory":"Auto Supplies",
            "type":"Retail Goods"
        }
    ],
    "sg:phone":"+1 210 431 7100",
    "sg:postcode":"78237",
    "sg:province":"TX",
    "sg:tags":[
        "automobile",
        "parts"
    ],
    "sg:website":"www.advanceautoparts.com",
    "wof:name":"Advance Auto Parts Inc",
    "wof:placetype":"venue"
},
  "geometry": {"coordinates":[-98.553878,29.432375],"type":"Point"}
}