{
  "type": "Feature",
  "properties": {
    "iso:country":"US",
    "sg:address":"903 W US Hwy 83",
    "sg:city":"Pharr",
    "sg:classifiers":[
        {
            "category":"Shopping",
            "subcategory":"Clothing, Apparel, & Fashions",
            "type":"Retail Goods"
        }
    ],
    "sg:phone":"+1 956 781 9150",
    "sg:postcode":"78577",
    "sg:province":"TX",
    "sg:tags":[
        "dance"
    ],
    "wof:name":"Dance Etc",
    "wof:placetype":"venue"
},
  "geometry": {"coordinates":[-98.19780799999999,26.202945],"type":"Point"}
}