{
  "type": "Feature",
  "properties": {
    "iso:country":"US",
    "sg:address":"4433 Airline Dr",
    "sg:city":"Houston",
    "sg:classifiers":[
        {
            "category":"Wholesale",
            "subcategory":"Electrical",
            "type":"Manufacturing & Wholesale Goods"
        }
    ],
    "sg:phone":"+1 713 691 6521",
    "sg:postcode":"77022",
    "sg:province":"TX",
    "sg:tags":[
        "equipment",
        "electric",
        "supply"
    ],
    "sg:website":"www.dealerselectrical.com",
    "wof:name":"Dealers Electrical Supply",
    "wof:placetype":"venue"
},
  "geometry": {"coordinates":[-95.384485,29.830448],"type":"Point"}
}