{
  "type": "Feature",
  "properties": {
    "iso:country":"US",
    "sg:address":"12802 New Cypress Dr",
    "sg:city":"Cypress",
    "sg:classifiers":[
        {
            "category":"Freight",
            "type":"Transportation"
        }
    ],
    "sg:phone":"+1 281 830 2156",
    "sg:postcode":"77429",
    "sg:province":"TX",
    "sg:tags":[
        "operator",
        "trucking"
    ],
    "wof:name":"Far & Near Auto Transport Svc",
    "wof:placetype":"venue"
},
  "geometry": {"coordinates":[-95.639877,29.962187],"type":"Point"}
}