{
  "type": "Feature",
  "properties": {
    "iso:country":"US",
    "sg:address":"3020 Ramona Dr",
    "sg:city":"Fort Worth",
    "sg:classifiers":[
        {
            "category":"Retail",
            "subcategory":"Auto Repair",
            "type":"Services"
        }
    ],
    "sg:phone":"+1 817 244 8200",
    "sg:postcode":"76116",
    "sg:province":"TX",
    "sg:tags":[
        "transmission"
    ],
    "wof:name":"Bright's Transmission Svc",
    "wof:placetype":"venue"
},
  "geometry": {"coordinates":[-97.444975,32.728961],"type":"Point"}
}