{
  "type": "Feature",
  "properties": {
    "iso:country":"US",
    "sg:address":"420 S Main St",
    "sg:city":"Highlands",
    "sg:classifiers":[
        {
            "category":"Banks & Credit Unions",
            "subcategory":"Bank",
            "type":"Services"
        }
    ],
    "sg:phone":"+1 281 426 5690",
    "sg:postcode":"77562",
    "sg:province":"TX",
    "sg:website":"www.woodforest.com",
    "wof:name":"Woodforest National Bank",
    "wof:placetype":"venue"
},
  "geometry": {"coordinates":[-95.05729700000001,29.8123],"type":"Point"}
}