{
  "type": "Feature",
  "properties": {
    "iso:country":"US",
    "sg:address":"12805 Boheme Dr",
    "sg:city":"Houston",
    "sg:classifiers":[
        {
            "category":"Recreation",
            "type":"Entertainment"
        }
    ],
    "sg:phone":"+1 713 461 0017",
    "sg:postcode":"77024",
    "sg:province":"TX",
    "sg:tags":[
        "club",
        "membership"
    ],
    "wof:name":"Memorial Bend Club",
    "wof:placetype":"venue"
},
  "geometry": {"coordinates":[-95.561453,29.767459],"type":"Point"}
}