{
  "type": "Feature",
  "properties": {
    "iso:country":"US",
    "sg:address":"5600 Kemah Ct",
    "sg:city":"Granbury",
    "sg:classifiers":[
        {
            "category":"Building & Trades",
            "subcategory":"Landscaping Services",
            "type":"Services"
        }
    ],
    "sg:phone":"+1 817 326 0221",
    "sg:postcode":"76049",
    "sg:province":"TX",
    "wof:name":"Clints Superior Lawn",
    "wof:placetype":"venue"
},
  "geometry": {"coordinates":[-97.69019299999999,32.450261],"type":"Point"}
}