{
  "type": "Feature",
  "properties": {
    "iso:country":"US",
    "sg:address":"14214 Marsh Ln",
    "sg:city":"Addison",
    "sg:classifiers":[
        {
            "category":"Health Services",
            "subcategory":"Podiatrist",
            "type":"Services"
        }
    ],
    "sg:phone":"+1 972 241 3338",
    "sg:postcode":"75001",
    "sg:province":"TX",
    "wof:name":"Brookhaven Foot Clinic",
    "wof:placetype":"venue"
},
  "geometry": {"coordinates":[-96.855699,32.937913],"type":"Point"}
}