{
  "type": "Feature",
  "properties": {
    "iso:country":"US",
    "sg:address":"500 S el Paso St",
    "sg:city":"El Paso",
    "sg:classifiers":[
        {
            "category":"Shopping",
            "subcategory":"Shoes",
            "type":"Retail Goods"
        }
    ],
    "sg:phone":"+1 325 532 7323",
    "sg:postcode":"79901",
    "sg:province":"TX",
    "wof:name":"Payless Shoe Source",
    "wof:placetype":"venue"
},
  "geometry": {"coordinates":[-106.48762000000001,31.753406],"type":"Point"}
}