{
  "type": "Feature",
  "properties": {
    "iso:country":"US",
    "sg:address":"7900 Churchill Way",
    "sg:city":"Dallas",
    "sg:classifiers":[
        {
            "category":"Professional",
            "subcategory":"Management & Consulting",
            "type":"Services"
        }
    ],
    "sg:phone":"+1 214 924 7210",
    "sg:postcode":"75251",
    "sg:province":"TX",
    "sg:tags":[
        "business"
    ],
    "wof:name":"Digital Instance LLC",
    "wof:placetype":"venue"
},
  "geometry": {"coordinates":[-96.772251,32.918418],"type":"Point"}
}