{
  "type": "Feature",
  "properties": {
    "iso:country":"US",
    "sg:address":"318 Moore Dr",
    "sg:city":"Abilene",
    "sg:classifiers":[
        {
            "category":"Building & Trades",
            "subcategory":"Construction",
            "type":"Services"
        }
    ],
    "sg:phone":"+1 325 672 3784",
    "sg:postcode":"79605",
    "sg:province":"TX",
    "sg:tags":[
        "house"
    ],
    "wof:name":"J&J Improvements",
    "wof:placetype":"venue"
},
  "geometry": {"coordinates":[-99.771907,32.447753],"type":"Point"}
}