{
  "type": "Feature",
  "properties": {
    "iso:country":"US",
    "sg:address":"117 N Wasson Dr",
    "sg:city":"Gail",
    "sg:classifiers":[
        {
            "category":"Government",
            "subcategory":"Court House",
            "type":"Public Place"
        }
    ],
    "sg:phone":"+1 806 756 4391",
    "sg:postcode":"79720",
    "sg:province":"TX",
    "sg:tags":[
        "county"
    ],
    "wof:name":"Borden County Judge's Ofc",
    "wof:placetype":"venue"
},
  "geometry": {"coordinates":[-101.505033,32.262483],"type":"Point"}
}