{
  "type": "Feature",
  "properties": {
    "iso:country":"US",
    "sg:address":"7700 Gulf Fwy",
    "sg:city":"Houston",
    "sg:classifiers":[
        {
            "category":"Wholesale",
            "subcategory":"Electrical",
            "type":"Manufacturing & Wholesale Goods"
        }
    ],
    "sg:phone":"+1 713 943 1205",
    "sg:postcode":"77017",
    "sg:province":"TX",
    "sg:tags":[
        "alarm",
        "burglar",
        "system"
    ],
    "wof:name":"Alarm Processing Corp",
    "wof:placetype":"venue"
},
  "geometry": {"coordinates":[-95.254035,29.65693],"type":"Point"}
}