{
  "type": "Feature",
  "properties": {
    "iso:country":"US",
    "sg:address":"4010 Bluebonnet Dr",
    "sg:city":"Houston",
    "sg:classifiers":[
        {
            "category":"Shopping",
            "subcategory":"Hobbies, Toys, & Games",
            "type":"Retail Goods"
        }
    ],
    "sg:phone":"+1 713 796 0900",
    "sg:postcode":"77053",
    "sg:province":"TX",
    "sg:tags":[
        "toy",
        "store"
    ],
    "sg:website":"www.teambabyentertainment.com",
    "wof:name":"Team Baby Entertainment",
    "wof:placetype":"venue"
},
  "geometry": {"coordinates":[-95.437991,29.588197],"type":"Point"}
}