{
  "type": "Feature",
  "properties": {
    "iso:country":"US",
    "sg:address":"4800 NE Stallings Dr",
    "sg:city":"Nacogdoches",
    "sg:classifiers":[
        {
            "category":"Health Services",
            "subcategory":"Doctor",
            "type":"Services"
        }
    ],
    "sg:phone":"+1 936 564 6197",
    "sg:postcode":"75965",
    "sg:province":"TX",
    "sg:tags":[
        "house",
        "medical",
        "mail"
    ],
    "wof:name":"F Barry Roberts MD",
    "wof:placetype":"venue"
},
  "geometry": {"coordinates":[-94.65344399999999,31.652077],"type":"Point"}
}