{
  "type": "Feature",
  "properties": {
    "iso:country":"US",
    "sg:address":"3414 W Rochelle Rd",
    "sg:city":"Irving",
    "sg:classifiers":[
        {
            "category":"Restaurant",
            "type":"Food & Drink"
        }
    ],
    "sg:phone":"+1 972 255 9988",
    "sg:postcode":"75062",
    "sg:province":"TX",
    "sg:tags":[
        "delivery"
    ],
    "wof:name":"Lite Wok",
    "wof:placetype":"venue"
},
  "geometry": {"coordinates":[-96.99305200000001,32.847415],"type":"Point"}
}