{
  "type": "Feature",
  "properties": {
    "iso:country":"US",
    "sg:address":"6918 Corporate Dr Ste A9",
    "sg:city":"Houston",
    "sg:classifiers":[
        {
            "category":"Banks & Credit Unions",
            "subcategory":"Financial Services",
            "type":"Services"
        }
    ],
    "sg:phone":"+1 713 270 8804",
    "sg:postcode":"77036",
    "sg:province":"TX",
    "sg:tags":[
        "broker",
        "mortgage"
    ],
    "wof:name":"Texas Corporate Mortgage",
    "wof:placetype":"venue"
},
  "geometry": {"coordinates":[-95.55212,29.702965],"type":"Point"}
}