{
  "type": "Feature",
  "properties": {
    "iso:country":"US",
    "sg:address":"2241 Ashley Park Dr",
    "sg:city":"Plano",
    "sg:classifiers":[
        {
            "category":"Retail",
            "subcategory":"Animal Services",
            "type":"Services"
        }
    ],
    "sg:phone":"+1 972 423 2221",
    "sg:postcode":"75074",
    "sg:province":"TX",
    "sg:tags":[
        "pet",
        "boarding",
        "sitting"
    ],
    "wof:name":"My Pets Preference Inc",
    "wof:placetype":"venue"
},
  "geometry": {"coordinates":[-96.696454,33.029637],"type":"Point"}
}