{
  "type": "Feature",
  "properties": {
    "iso:country":"US",
    "sg:address":"401 E Market St",
    "sg:city":"Sinton",
    "sg:classifiers":[
        {
            "category":"Shopping",
            "type":"Retail Goods"
        }
    ],
    "sg:phone":"+1 361 364 5300",
    "sg:postcode":"78387",
    "sg:province":"TX",
    "sg:tags":[
        "merchandise"
    ],
    "wof:name":"Janota Services",
    "wof:placetype":"venue"
},
  "geometry": {"coordinates":[-97.506818,28.037768],"type":"Point"}
}