{
  "type": "Feature",
  "properties": {
    "iso:country":"US",
    "sg:address":"10655 Richmond Ave",
    "sg:city":"Houston",
    "sg:classifiers":[
        {
            "category":"Manufacturing",
            "subcategory":"Chemicals & Compounds",
            "type":"Manufacturing & Wholesale Goods"
        }
    ],
    "sg:phone":"+1 713 975 5802",
    "sg:postcode":"77042",
    "sg:province":"TX",
    "sg:tags":[
        "carbon",
        "black",
        "mfg"
    ],
    "wof:name":"Research & Lab",
    "wof:placetype":"venue"
},
  "geometry": {"coordinates":[-95.563219,29.72771],"type":"Point"}
}