{
  "type": "Feature",
  "properties": {
    "iso:country":"US",
    "sg:address":"4480 Blalock Rd",
    "sg:city":"Houston",
    "sg:classifiers":[
        {
            "category":"Health Services",
            "subcategory":"Clinic",
            "type":"Services"
        }
    ],
    "sg:phone":"+1 281 597 0056",
    "sg:postcode":"77041",
    "sg:province":"TX",
    "sg:tags":[
        "home"
    ],
    "wof:name":"Immaculate Home Health Inc",
    "wof:placetype":"venue"
},
  "geometry": {"coordinates":[-95.523944,29.83743],"type":"Point"}
}