{
  "type": "Feature",
  "properties": {
    "iso:country":"US",
    "sg:address":"4302 Delhi St",
    "sg:city":"Houston",
    "sg:classifiers":[
        {
            "category":"Social Services",
            "subcategory":"Child Care",
            "type":"Services"
        }
    ],
    "sg:phone":"+1 713 695 6071",
    "sg:postcode":"77022",
    "sg:province":"TX",
    "sg:tags":[
        "day"
    ],
    "wof:name":"P & M Child Care Center",
    "wof:placetype":"venue"
},
  "geometry": {"coordinates":[-95.387377,29.828578],"type":"Point"}
}