{
  "type": "Feature",
  "properties": {
    "iso:country":"US",
    "sg:address":"1129 Co Rd 3336",
    "sg:city":"Bridgeport",
    "sg:classifiers":[
        {
            "category":"Wholesale",
            "subcategory":"Vending Machines",
            "type":"Manufacturing & Wholesale Goods"
        }
    ],
    "sg:phone":"+1 940 683 6459",
    "sg:postcode":"76426",
    "sg:province":"TX",
    "sg:tags":[
        "operator"
    ],
    "wof:name":"S&S Vending",
    "wof:placetype":"venue"
},
  "geometry": {"coordinates":[-97.75672900000001,33.17264],"type":"Point"}
}