{
  "type": "Feature",
  "properties": {
    "iso:country":"US",
    "sg:address":"4521 Clovis Rd",
    "sg:city":"Lubbock",
    "sg:classifiers":[
        {
            "category":"Wholesale",
            "subcategory":"Machinery & Supplies",
            "type":"Manufacturing & Wholesale Goods"
        }
    ],
    "sg:phone":"+1 806 765 5490",
    "sg:postcode":"79416",
    "sg:province":"TX",
    "sg:tags":[
        "equipment",
        "irrigation",
        "system"
    ],
    "wof:name":"South Plains Valley Irrigation",
    "wof:placetype":"venue"
},
  "geometry": {"coordinates":[-101.92796800000001,33.635429],"type":"Point"}
}