{
  "type": "Feature",
  "properties": {
    "iso:country":"US",
    "sg:address":"27110 Paula Ln",
    "sg:city":"Conroe",
    "sg:classifiers":[
        {
            "category":"Professional",
            "subcategory":"Business Services",
            "type":"Services"
        }
    ],
    "sg:phone":"+1 281 367 4182",
    "sg:postcode":"77385",
    "sg:province":"TX",
    "wof:name":"Clinton Butts Bjb Service",
    "wof:placetype":"venue"
},
  "geometry": {"coordinates":[-95.447288,30.160742],"type":"Point"}
}