{
  "type": "Feature",
  "properties": {
    "iso:country":"US",
    "sg:address":"349 E Nannette Dr",
    "sg:city":"Pharr",
    "sg:classifiers":[
        {
            "category":"Restaurant",
            "type":"Food & Drink"
        }
    ],
    "sg:phone":"+1 956 702 6866",
    "sg:postcode":"78577",
    "sg:province":"TX",
    "sg:tags":[
        "eating"
    ],
    "wof:name":"Pizza Now",
    "wof:placetype":"venue"
},
  "geometry": {"coordinates":[-98.191579,26.122021],"type":"Point"}
}