{
  "type": "Feature",
  "properties": {
    "iso:country":"US",
    "sg:address":"307 Oak Creek Ct",
    "sg:city":"League City",
    "sg:classifiers":[
        {
            "category":"Organizations",
            "subcategory":"Religious Organization",
            "type":"Services"
        }
    ],
    "sg:phone":"+1 281 316 9402",
    "sg:postcode":"77573",
    "sg:province":"TX",
    "wof:name":"Randy Caldwell Minstries Inc",
    "wof:placetype":"venue"
},
  "geometry": {"coordinates":[-95.151988,29.494007],"type":"Point"}
}