{
  "type": "Feature",
  "properties": {
    "iso:country":"US",
    "sg:address":"687 Co Rd 300",
    "sg:city":"Abilene",
    "sg:classifiers":[
        {
            "category":"Farming",
            "subcategory":"Dairy Farm",
            "type":"Manufacturing & Wholesale Goods"
        }
    ],
    "sg:phone":"+1 325 692 3268",
    "sg:postcode":"79603",
    "sg:province":"TX",
    "wof:name":"Hohhertz Dairies",
    "wof:placetype":"venue"
},
  "geometry": {"coordinates":[-99.933271,32.393534],"type":"Point"}
}