{
  "type": "Feature",
  "properties": {
    "iso:country":"US",
    "sg:address":"1017 Shady Oaks Dr",
    "sg:city":"Denton",
    "sg:classifiers":[
        {
            "category":"Building & Trades",
            "subcategory":"Electrical",
            "type":"Services"
        }
    ],
    "sg:phone":"+1 940 387 2665",
    "sg:postcode":"76205",
    "sg:province":"TX",
    "sg:tags":[
        "electrical"
    ],
    "wof:name":"Concept Communication",
    "wof:placetype":"venue"
},
  "geometry": {"coordinates":[-97.120779,33.200331],"type":"Point"}
}