{
  "type": "Feature",
  "properties": {
    "iso:country":"US",
    "sg:address":"9978 Monroe Dr",
    "sg:city":"Dallas",
    "sg:classifiers":[
        {
            "category":"Freight",
            "type":"Transportation"
        }
    ],
    "sg:phone":"+1 214 351 9000",
    "sg:postcode":"75220",
    "sg:province":"TX",
    "sg:tags":[
        "arrangement",
        "courier",
        "air"
    ],
    "wof:name":"Air Concepts",
    "wof:placetype":"venue"
},
  "geometry": {"coordinates":[-96.87803,32.877933],"type":"Point"}
}