{
  "type": "Feature",
  "properties": {
    "iso:country":"US",
    "sg:address":"202 N Main St",
    "sg:city":"Andrews",
    "sg:classifiers":[
        {
            "category":"Professional",
            "subcategory":"Lawyer & Legal Services",
            "type":"Services"
        }
    ],
    "sg:phone":"+1 432 523 2889",
    "sg:postcode":"79714",
    "sg:province":"TX",
    "sg:tags":[
        "attorney"
    ],
    "wof:name":"J Timothy Mason",
    "wof:placetype":"venue"
},
  "geometry": {"coordinates":[-102.546914,32.320127],"type":"Point"}
}