{
  "type": "Feature",
  "properties": {
    "iso:country":"US",
    "sg:address":"2115 Canton St",
    "sg:city":"Dallas",
    "sg:classifiers":[
        {
            "category":"Personal",
            "subcategory":"Adult",
            "type":"Services"
        }
    ],
    "sg:phone":"+1 972 744 0400",
    "sg:postcode":"75201",
    "sg:province":"TX",
    "sg:tags":[
        "escort"
    ],
    "wof:name":"Amber Lynn's Escort",
    "wof:placetype":"venue"
},
  "geometry": {"coordinates":[-96.790072,32.780106],"type":"Point"}
}