{
  "type": "Feature",
  "properties": {
    "iso:country":"US",
    "sg:address":"4528 Waring St",
    "sg:city":"Houston",
    "sg:classifiers":[
        {
            "category":"Real Estate",
            "subcategory":"Real Estate Agent",
            "type":"Services"
        }
    ],
    "sg:phone":"+1 713 626 7624",
    "sg:postcode":"77027",
    "sg:province":"TX",
    "wof:name":"Est of Ike J Maenza & Est",
    "wof:placetype":"venue"
},
  "geometry": {"coordinates":[-95.45305500000001,29.734722],"type":"Point"}
}