{
  "type": "Feature",
  "properties": {
    "iso:country":"US",
    "sg:address":"3010 S Lamar Blvd",
    "sg:city":"Austin",
    "sg:classifiers":[
        {
            "category":"Shopping",
            "subcategory":"Bicycles & Sporting Goods",
            "type":"Retail Goods"
        }
    ],
    "sg:phone":"+1 512 916 0952",
    "sg:postcode":"78704",
    "sg:province":"TX",
    "wof:name":"Sports Unlimited",
    "wof:placetype":"venue"
},
  "geometry": {"coordinates":[-97.783489,30.242967],"type":"Point"}
}