{
  "type": "Feature",
  "properties": {
    "iso:country":"US",
    "sg:address":"1013 N 13th St",
    "sg:city":"Lamesa",
    "sg:classifiers":[
        {
            "category":"Professional",
            "subcategory":"Advertising",
            "type":"Services"
        }
    ],
    "sg:phone":"+1 806 872 5540",
    "sg:postcode":"79331",
    "sg:province":"TX",
    "sg:tags":[
        "graphic",
        "design"
    ],
    "wof:name":"Duron Matlock Design",
    "wof:placetype":"venue"
},
  "geometry": {"coordinates":[-101.96233700000001,32.742949],"type":"Point"}
}