{
  "type": "Feature",
  "properties": {
    "iso:country":"US",
    "sg:address":"2616 Flameleaf Dr",
    "sg:city":"Grapevine",
    "sg:classifiers":[
        {
            "category":"Shopping",
            "subcategory":"Clothing, Apparel, & Fashions",
            "type":"Retail Goods"
        }
    ],
    "sg:phone":"+1 817 424 0083",
    "sg:postcode":"76051",
    "sg:province":"TX",
    "sg:tags":[
        "wear"
    ],
    "wof:name":"Lilligrace LLC",
    "wof:placetype":"venue"
},
  "geometry": {"coordinates":[-97.10331100000001,32.899746],"type":"Point"}
}