{
  "type": "Feature",
  "properties": {
    "iso:country":"US",
    "sg:address":"2830 Webb Chapel Exn",
    "sg:city":"Dallas",
    "sg:classifiers":[
        {
            "category":"Professional",
            "subcategory":"Management & Consulting",
            "type":"Services"
        }
    ],
    "sg:phone":"+1 214 350 7347",
    "sg:postcode":"75220",
    "sg:province":"TX",
    "sg:tags":[
        "business"
    ],
    "wof:name":"Centro Communications",
    "wof:placetype":"venue"
},
  "geometry": {"coordinates":[-96.86992499999999,32.857225],"type":"Point"}
}