{
  "type": "Feature",
  "properties": {
    "iso:country":"US",
    "sg:address":"7715 Susan Elaine St",
    "sg:city":"San Antonio",
    "sg:classifiers":[
        {
            "category":"Building & Trades",
            "subcategory":"Construction",
            "type":"Services"
        }
    ],
    "sg:phone":"+1 210 681 6870",
    "sg:postcode":"78240",
    "sg:province":"TX",
    "sg:tags":[
        "carpentry",
        "contractor"
    ],
    "wof:name":"Premier Staging Inc",
    "wof:placetype":"venue"
},
  "geometry": {"coordinates":[-98.640061,29.529842],"type":"Point"}
}