{
  "type": "Feature",
  "properties": {
    "iso:country":"US",
    "sg:address":"202 S Maple St",
    "sg:city":"Van",
    "sg:classifiers":[
        {
            "category":"Personal",
            "subcategory":"Beauty Salon",
            "type":"Services"
        }
    ],
    "sg:phone":"+1 903 963 4247",
    "sg:postcode":"75790",
    "sg:province":"TX",
    "wof:name":"Christy's",
    "wof:placetype":"venue"
},
  "geometry": {"coordinates":[-95.637727,32.519775],"type":"Point"}
}