{
  "type": "Feature",
  "properties": {
    "iso:country":"US",
    "sg:address":"11315 Sunfish Ln",
    "sg:city":"Houston",
    "sg:classifiers":[
        {
            "category":"Real Estate",
            "subcategory":"Real Estate Agent",
            "type":"Services"
        }
    ],
    "sg:phone":"+1 281 440 3559",
    "sg:postcode":"77067",
    "sg:province":"TX",
    "sg:tags":[
        "investment"
    ],
    "wof:name":"E B Properties & Assoc",
    "wof:placetype":"venue"
},
  "geometry": {"coordinates":[-95.463673,29.94672],"type":"Point"}
}