{
  "type": "Feature",
  "properties": {
    "iso:country":"US",
    "sg:address":"2011 Shadow Bend Dr",
    "sg:city":"Houston",
    "sg:classifiers":[
        {
            "category":"Professional",
            "subcategory":"Management & Consulting",
            "type":"Services"
        }
    ],
    "sg:phone":"+1 713 464 1153",
    "sg:postcode":"77043",
    "sg:province":"TX",
    "wof:name":"Welch Consulting",
    "wof:placetype":"venue"
},
  "geometry": {"coordinates":[-95.556848,29.808865],"type":"Point"}
}