{
  "type": "Feature",
  "properties": {
    "iso:country":"US",
    "sg:address":"2001 Fisk Ave",
    "sg:city":"Brownwood",
    "sg:classifiers":[
        {
            "category":"Building & Trades",
            "subcategory":"Construction",
            "type":"Services"
        }
    ],
    "sg:phone":"+1 325 646 9581",
    "sg:postcode":"76801",
    "sg:province":"TX",
    "sg:tags":[
        "roofing",
        "sheet",
        "metal",
        "contractor"
    ],
    "wof:name":"Lydick-Hoks Roofg of Brownwood",
    "wof:placetype":"venue"
},
  "geometry": {"coordinates":[-98.99224599999999,31.70933],"type":"Point"}
}