{
  "type": "Feature",
  "properties": {
    "iso:country":"US",
    "sg:address":"9025 Homestead Rd",
    "sg:city":"Houston",
    "sg:classifiers":[
        {
            "category":"Home & Garden",
            "subcategory":"Furniture",
            "type":"Retail Goods"
        }
    ],
    "sg:phone":"+1 713 633 1831",
    "sg:postcode":"77016",
    "sg:province":"TX",
    "sg:tags":[
        "repair"
    ],
    "wof:name":"Markay Furniture Center Inc",
    "wof:placetype":"venue"
},
  "geometry": {"coordinates":[-95.302183,29.843179],"type":"Point"}
}