{
  "type": "Feature",
  "properties": {
    "iso:country":"US",
    "sg:address":"3100 Breton Dr",
    "sg:city":"Plano",
    "sg:classifiers":[
        {
            "category":"Professional",
            "subcategory":"Employment Agencies",
            "type":"Services"
        }
    ],
    "sg:phone":"+1 972 943 5714",
    "sg:postcode":"75025",
    "sg:province":"TX",
    "sg:tags":[
        "permanent",
        "temp",
        "staffing"
    ],
    "wof:name":"Kaycee Group",
    "wof:placetype":"venue"
},
  "geometry": {"coordinates":[-96.75096499999999,33.076675],"type":"Point"}
}