{
  "type": "Feature",
  "properties": {
    "iso:country":"US",
    "sg:address":"1526 Avenue A",
    "sg:city":"Katy",
    "sg:classifiers":[
        {
            "category":"Building & Trades",
            "subcategory":"Landscaping Services",
            "type":"Services"
        }
    ],
    "sg:phone":"+1 281 391 6867",
    "sg:postcode":"77493",
    "sg:province":"TX",
    "sg:tags":[
        "lawn"
    ],
    "wof:name":"Calderon Landscaping & Lawncar",
    "wof:placetype":"venue"
},
  "geometry": {"coordinates":[-95.82101400000001,29.793864],"type":"Point"}
}