{
  "type": "Feature",
  "properties": {
    "iso:country":"US",
    "sg:address":"1523 E Expy 83",
    "sg:city":"Mission",
    "sg:classifiers":[
        {
            "category":"Professional",
            "type":"Services"
        }
    ],
    "sg:phone":"+1 956 583 1631",
    "sg:postcode":"78572",
    "sg:province":"TX",
    "wof:name":"Bpi Granite",
    "wof:placetype":"venue"
},
  "geometry": {"coordinates":[-98.30328,26.19823],"type":"Point"}
}