{
  "type": "Feature",
  "properties": {
    "iso:country":"US",
    "sg:address":"900 Senter Rd",
    "sg:city":"Irving",
    "sg:classifiers":[
        {
            "category":"Sports & Exercise",
            "subcategory":"Sports Center",
            "type":"Entertainment"
        }
    ],
    "sg:phone":"+1 972 721 2641",
    "sg:postcode":"75060",
    "sg:province":"TX",
    "sg:tags":[
        "amateur",
        "team"
    ],
    "sg:website":"www.ci.irving.tx.us",
    "wof:name":"City of Irving",
    "wof:placetype":"venue"
},
  "geometry": {"coordinates":[-96.94676200000001,32.804728],"type":"Point"}
}