{
  "type": "Feature",
  "properties": {
    "iso:country":"US",
    "sg:address":"945 Robinson St",
    "sg:city":"Kermit",
    "sg:classifiers":[
        {
            "category":"Personal",
            "subcategory":"Beauty Salon",
            "type":"Services"
        }
    ],
    "sg:phone":"+1 432 586 6853",
    "sg:postcode":"79745",
    "sg:province":"TX",
    "sg:tags":[
        "shop"
    ],
    "wof:name":"Beauty Walk",
    "wof:placetype":"venue"
},
  "geometry": {"coordinates":[-103.09349899999999,31.845701],"type":"Point"}
}