{
  "type": "Feature",
  "properties": {
    "iso:country":"US",
    "sg:address":"1827 W Louisiana St",
    "sg:city":"Mc Kinney",
    "sg:classifiers":[
        {
            "category":"Professional",
            "type":"Services"
        }
    ],
    "sg:phone":"+1 972 529 2233",
    "sg:postcode":"75069",
    "sg:province":"TX",
    "sg:tags":[
        "establishment"
    ],
    "wof:name":"Hammerle Finley",
    "wof:placetype":"venue"
},
  "geometry": {"coordinates":[-96.630109,33.197172],"type":"Point"}
}