{
  "type": "Feature",
  "properties": {
    "iso:country":"US",
    "sg:address":"2508 Wild Rose Ct",
    "sg:city":"Arlington",
    "sg:classifiers":[
        {
            "category":"Social Services",
            "type":"Services"
        },
        {
            "category":"Professional",
            "subcategory":"Employment Agencies",
            "type":"Services"
        }
    ],
    "sg:phone":"+1 817 633 3531",
    "sg:postcode":"76006",
    "sg:province":"TX",
    "sg:tags":[
        "workers'",
        "placement",
        "volunteer"
    ],
    "wof:name":"Matt Mckee Foundation",
    "wof:placetype":"venue"
},
  "geometry": {"coordinates":[-97.06751300000001,32.777882],"type":"Point"}
}