{
  "type": "Feature",
  "properties": {
    "iso:country":"US",
    "sg:address":"3711 Briarpark Dr Ste 400",
    "sg:city":"Houston",
    "sg:classifiers":[
        {
            "category":"Shopping",
            "subcategory":"Stationery & Office Supplies",
            "type":"Retail Goods"
        }
    ],
    "sg:phone":"+1 713 977 7271",
    "sg:postcode":"77042",
    "sg:province":"TX",
    "sg:tags":[
        "equipment"
    ],
    "wof:name":"Staples",
    "wof:placetype":"venue"
},
  "geometry": {"coordinates":[-95.548672,29.723823],"type":"Point"}
}