{
  "type": "Feature",
  "properties": {
    "iso:country":"US",
    "sg:address":"2400 Lakeside Blvd",
    "sg:city":"Richardson",
    "sg:classifiers":[
        {
            "category":"Health Services",
            "subcategory":"Doctor",
            "type":"Services"
        }
    ],
    "sg:phone":"+1 972 644 9595",
    "sg:postcode":"75082",
    "sg:province":"TX",
    "sg:tags":[
        "dentist"
    ],
    "wof:name":"G Brooks Haney DDS",
    "wof:placetype":"venue"
},
  "geometry": {"coordinates":[-96.71117,32.981536],"type":"Point"}
}