{
  "type": "Feature",
  "properties": {
    "iso:country":"US",
    "sg:address":"302 Lincoln Park Dr",
    "sg:city":"Cleburne",
    "sg:classifiers":[
        {
            "category":"Social Services",
            "type":"Services"
        }
    ],
    "sg:phone":"+1 817 558 6564",
    "sg:postcode":"76033",
    "sg:province":"TX",
    "wof:name":"Alvarado Meadows Rehab",
    "wof:placetype":"venue"
},
  "geometry": {"coordinates":[-97.410375,32.344056],"type":"Point"}
}