{
  "type": "Feature",
  "properties": {
    "iso:country":"US",
    "sg:address":"101 Southwestern Blvd",
    "sg:city":"Sugar Land",
    "sg:classifiers":[
        {
            "category":"Banks & Credit Unions",
            "subcategory":"Bank",
            "type":"Services"
        }
    ],
    "sg:phone":"+1 281 242 3488",
    "sg:postcode":"77478",
    "sg:province":"TX",
    "sg:tags":[
        "mortgage"
    ],
    "wof:name":"Homeowers Mortgage Inc",
    "wof:placetype":"venue"
},
  "geometry": {"coordinates":[-95.597617,29.622866],"type":"Point"}
}