{
  "type": "Feature",
  "properties": {
    "iso:country":"US",
    "sg:address":"1910 N Coit Rd",
    "sg:city":"Richardson",
    "sg:classifiers":[
        {
            "category":"Restaurant",
            "type":"Food & Drink"
        }
    ],
    "sg:phone":"+1 972 231 8858",
    "sg:postcode":"75080",
    "sg:province":"TX",
    "wof:name":"Tong's House Of Richardson",
    "wof:placetype":"venue"
},
  "geometry": {"coordinates":[-96.768297,32.976179],"type":"Point"}
}