{
  "type": "Feature",
  "properties": {
    "iso:country":"US",
    "sg:address":"1418 Miami Dr",
    "sg:city":"Corpus Christi",
    "sg:classifiers":[
        {
            "category":"Communications",
            "subcategory":"Radio Station",
            "type":"Services"
        }
    ],
    "sg:phone":"+1 361 857 2598",
    "sg:postcode":"78415",
    "sg:province":"TX",
    "sg:tags":[
        "company",
        "broadcasting"
    ],
    "wof:name":"Cobra Broadcasting & Prdctn",
    "wof:placetype":"venue"
},
  "geometry": {"coordinates":[-97.403395,27.750073],"type":"Point"}
}