{
  "type": "Feature",
  "properties": {
    "iso:country":"US",
    "sg:address":"10874 Leslie Rd",
    "sg:city":"Helotes",
    "sg:classifiers":[
        {
            "category":"Wholesale",
            "subcategory":"Auto Parts",
            "type":"Manufacturing & Wholesale Goods"
        }
    ],
    "sg:phone":"+1 210 372 9546",
    "sg:postcode":"78023",
    "sg:province":"TX",
    "sg:tags":[
        "truck",
        "accessory"
    ],
    "sg:website":"www.xtcoffroad.com",
    "wof:name":"XTC Xtreme Truck Ctr",
    "wof:placetype":"venue"
},
  "geometry": {"coordinates":[-98.68372100000001,29.543225],"type":"Point"}
}