{
  "type": "Feature",
  "properties": {
    "iso:country":"US",
    "sg:address":"8681 N Highway 77",
    "sg:city":"Lexington",
    "sg:classifiers":[
        {
            "category":"Banks & Credit Unions",
            "subcategory":"Bank",
            "type":"Services"
        }
    ],
    "sg:phone":"+1 979 773 2227",
    "sg:postcode":"78947",
    "sg:province":"TX",
    "sg:website":"www.roundtopstatebank.com",
    "wof:name":"Round Top State Bank",
    "wof:placetype":"venue"
},
  "geometry": {"coordinates":[-97.566064,30.410935],"type":"Point"}
}