{
  "type": "Feature",
  "properties": {
    "iso:country":"US",
    "sg:address":"204 US Hwy 87",
    "sg:city":"Seagraves",
    "sg:classifiers":[
        {
            "category":"Wholesale",
            "subcategory":"Farm Supplies",
            "type":"Manufacturing & Wholesale Goods"
        }
    ],
    "sg:phone":"+1 806 387 2135",
    "sg:postcode":"79331",
    "sg:province":"TX",
    "sg:tags":[
        "peanut",
        "product"
    ],
    "wof:name":"J & V Peanut Co",
    "wof:placetype":"venue"
},
  "geometry": {"coordinates":[-101.949681,32.734706],"type":"Point"}
}