{
  "type": "Feature",
  "properties": {
    "iso:country":"US",
    "sg:address":"13276 N US Hwy 183",
    "sg:city":"Austin",
    "sg:classifiers":[
        {
            "category":"Professional",
            "subcategory":"Management & Consulting",
            "type":"Services"
        }
    ],
    "sg:phone":"+1 512 258 7347",
    "sg:postcode":"78750",
    "sg:province":"TX",
    "sg:tags":[
        "consultant",
        "planning"
    ],
    "wof:name":"Duncan Associates",
    "wof:placetype":"venue"
},
  "geometry": {"coordinates":[-97.78580700000001,30.443315],"type":"Point"}
}