{
  "type": "Feature",
  "properties": {
    "iso:country":"US",
    "sg:address":"201 E Angelina St",
    "sg:city":"Palestine",
    "sg:classifiers":[
        {
            "category":"Restaurant",
            "type":"Food & Drink"
        }
    ],
    "sg:phone":"+1 903 729 3600",
    "sg:postcode":"75801",
    "sg:province":"TX",
    "wof:name":"The Redlands Restaurant",
    "wof:placetype":"venue"
},
  "geometry": {"coordinates":[-95.628372,31.754641],"type":"Point"}
}