{
  "type": "Feature",
  "properties": {
    "iso:country":"US",
    "sg:address":"1501 Monarch Oaks St",
    "sg:city":"Houston",
    "sg:classifiers":[
        {
            "category":"Shopping",
            "type":"Retail Goods"
        }
    ],
    "sg:phone":"+1 713 467 8213",
    "sg:postcode":"77055",
    "sg:province":"TX",
    "sg:tags":[
        "telephone",
        "cellular"
    ],
    "wof:name":"Mary Jane Beisert Inc",
    "wof:placetype":"venue"
},
  "geometry": {"coordinates":[-95.490055,29.796852],"type":"Point"}
}