{
  "type": "Feature",
  "properties": {
    "iso:country":"US",
    "sg:address":"5115 NE 28th St",
    "sg:city":"Fort Worth",
    "sg:classifiers":[
        {
            "category":"Restaurant",
            "type":"Food & Drink"
        }
    ],
    "sg:phone":"+1 817 222 0882",
    "sg:postcode":"76117",
    "sg:province":"TX",
    "wof:name":"Dixie House Cafe",
    "wof:placetype":"venue"
},
  "geometry": {"coordinates":[-97.272701,32.794971],"type":"Point"}
}