{
  "type": "Feature",
  "properties": {
    "iso:country":"US",
    "sg:address":"40302 Donna Ana Rd",
    "sg:city":"Magnolia",
    "sg:classifiers":[
        {
            "category":"Freight",
            "type":"Transportation"
        }
    ],
    "sg:phone":"+1 281 356 7243",
    "sg:postcode":"77354",
    "sg:province":"TX",
    "wof:name":"Bob Transport Inc",
    "wof:placetype":"venue"
},
  "geometry": {"coordinates":[-95.603799,30.235472],"type":"Point"}
}