{
  "type": "Feature",
  "properties": {
    "iso:country":"US",
    "sg:address":"1406 N Main St",
    "sg:city":"Cleburne",
    "sg:classifiers":[
        {
            "category":"Retail",
            "subcategory":"Auto Repair",
            "type":"Services"
        }
    ],
    "sg:phone":"+1 817 556 3837",
    "sg:postcode":"76033",
    "sg:province":"TX",
    "sg:tags":[
        "body",
        "automobile",
        "top",
        "upholstery"
    ],
    "wof:name":"Gwen's Auto Upholstery",
    "wof:placetype":"venue"
},
  "geometry": {"coordinates":[-97.39459100000001,32.366525],"type":"Point"}
}