{
  "type": "Feature",
  "properties": {
    "iso:country":"US",
    "sg:address":"10140 Suez Dr",
    "sg:city":"El Paso",
    "sg:classifiers":[
        {
            "category":"Manufacturing",
            "subcategory":"Signs",
            "type":"Manufacturing & Wholesale Goods"
        }
    ],
    "sg:phone":"+1 915 526 3215",
    "sg:postcode":"79925",
    "sg:province":"TX",
    "sg:tags":[
        "animation",
        "mechanism"
    ],
    "wof:name":"Kindegraph",
    "wof:placetype":"venue"
},
  "geometry": {"coordinates":[-106.34750200000001,31.779574],"type":"Point"}
}