{
  "type": "Feature",
  "properties": {
    "iso:country":"US",
    "sg:address":"3916 Valley Ridge Dr",
    "sg:city":"Granbury",
    "sg:classifiers":[
        {
            "category":"Food & Beverages",
            "subcategory":"Groceries & Convenience Stores",
            "type":"Retail Goods"
        }
    ],
    "sg:phone":"+1 817 279 7100",
    "sg:postcode":"76048",
    "sg:province":"TX",
    "wof:name":"Oak Trail Shores General Store",
    "wof:placetype":"venue"
},
  "geometry": {"coordinates":[-97.82380999999999,32.486571],"type":"Point"}
}