{
  "type": "Feature",
  "properties": {
    "iso:country":"US",
    "sg:address":"325 Clayton St",
    "sg:city":"Grand Prairie",
    "sg:classifiers":[
        {
            "category":"Building & Trades",
            "subcategory":"Plumbing",
            "type":"Services"
        }
    ],
    "sg:phone":"+1 972 754 1255",
    "sg:postcode":"75052",
    "sg:province":"TX",
    "sg:tags":[
        "heating",
        "solar",
        "system"
    ],
    "wof:name":"Heritage Solar Screens",
    "wof:placetype":"venue"
},
  "geometry": {"coordinates":[-97.00589100000001,32.665677],"type":"Point"}
}