{
  "type": "Feature",
  "properties": {
    "iso:country":"US",
    "sg:address":"507 S Polk St",
    "sg:city":"Dallas",
    "sg:classifiers":[
        {
            "category":"Insurance",
            "subcategory":"Insurance Agent",
            "type":"Services"
        }
    ],
    "sg:phone":"+1 214 946 5400",
    "sg:postcode":"75208",
    "sg:province":"TX",
    "wof:name":"Greater Texas Insurance",
    "wof:placetype":"venue"
},
  "geometry": {"coordinates":[-96.839522,32.740235],"type":"Point"}
}