{
  "type": "Feature",
  "properties": {
    "iso:country":"US",
    "sg:address":"2814 Cottonwood Dr",
    "sg:city":"Katy",
    "sg:classifiers":[
        {
            "category":"Professional",
            "type":"Services"
        }
    ],
    "sg:phone":"+1 281 391 2583",
    "sg:postcode":"77493",
    "sg:province":"TX",
    "sg:tags":[
        "establishment"
    ],
    "wof:name":"Beverly Edberg & Assoc",
    "wof:placetype":"venue"
},
  "geometry": {"coordinates":[-95.831098,29.813258],"type":"Point"}
}