{
  "type": "Feature",
  "properties": {
    "iso:country":"US",
    "sg:address":"5312 Criswell Ln",
    "sg:city":"El Paso",
    "sg:classifiers":[
        {
            "category":"Health Services",
            "subcategory":"Clinic",
            "type":"Services"
        }
    ],
    "sg:phone":"+1 915 587 0074",
    "sg:postcode":"79932",
    "sg:province":"TX",
    "sg:tags":[
        "home",
        "care"
    ],
    "wof:name":"R&H Home Care Inc",
    "wof:placetype":"venue"
},
  "geometry": {"coordinates":[-106.61426400000001,31.853288],"type":"Point"}
}