{
  "type": "Feature",
  "properties": {
    "iso:country":"US",
    "sg:address":"6923 Tallahasse Dr",
    "sg:city":"San Antonio",
    "sg:classifiers":[
        {
            "category":"Building & Trades",
            "subcategory":"Plumbing",
            "type":"Services"
        }
    ],
    "sg:phone":"+1 210 655 4896",
    "sg:postcode":"78227",
    "sg:province":"TX",
    "sg:tags":[
        "plumbing",
        "repair",
        "air",
        "heating",
        "conditioning"
    ],
    "wof:name":"AC Masters",
    "wof:placetype":"venue"
},
  "geometry": {"coordinates":[-98.62767700000001,29.407287],"type":"Point"}
}