{
  "type": "Feature",
  "properties": {
    "iso:country":"US",
    "sg:address":"16948 Highway 3",
    "sg:city":"Webster",
    "sg:classifiers":[
        {
            "category":"Shopping",
            "subcategory":"Clothing, Apparel, & Fashions",
            "type":"Retail Goods"
        },
        {
            "category":"Shopping",
            "subcategory":"Baby Store",
            "type":"Retail Goods"
        }
    ],
    "sg:phone":"+1 281 338 4441",
    "sg:postcode":"77598",
    "sg:province":"TX",
    "sg:tags":[
        "children's",
        "infant",
        "clothing",
        "wear"
    ],
    "wof:name":"La T Da",
    "wof:placetype":"venue"
},
  "geometry": {"coordinates":[-95.127004,29.547198],"type":"Point"}
}