{
  "type": "Feature",
  "properties": {
    "iso:country":"US",
    "sg:address":"2315 Mechanic St",
    "sg:city":"Galveston",
    "sg:classifiers":[
        {
            "category":"Bars & Pubs",
            "type":"Food & Drink"
        }
    ],
    "sg:phone":"+1 409 765 5914",
    "sg:postcode":"77550",
    "sg:province":"TX",
    "sg:tags":[
        "drinking"
    ],
    "wof:name":"Fitzpatricks Pub",
    "wof:placetype":"venue"
},
  "geometry": {"coordinates":[-94.795064,29.305955],"type":"Point"}
}