{
  "type": "Feature",
  "properties": {
    "iso:country":"US",
    "sg:address":"522 S Patrick St",
    "sg:city":"Dublin",
    "sg:classifiers":[
        {
            "category":"Manufacturing",
            "subcategory":"Printing",
            "type":"Manufacturing & Wholesale Goods"
        }
    ],
    "sg:phone":"+1 254 445 4560",
    "sg:postcode":"76446",
    "sg:province":"TX",
    "sg:tags":[
        "newspaper"
    ],
    "wof:name":"Dairy Trader",
    "wof:placetype":"venue"
},
  "geometry": {"coordinates":[-98.34417999999999,32.080179],"type":"Point"}
}