{
  "type": "Feature",
  "properties": {
    "iso:country":"US",
    "sg:address":"4331 Glenhaven Blvd",
    "sg:city":"Dallas",
    "sg:classifiers":[
        {
            "category":"Building & Trades",
            "subcategory":"Plumbing",
            "type":"Services"
        }
    ],
    "sg:phone":"+1 214 339 7396",
    "sg:postcode":"75211",
    "sg:province":"TX",
    "wof:name":"Nix Johnny Plumbing",
    "wof:placetype":"venue"
},
  "geometry": {"coordinates":[-96.891296,32.729099],"type":"Point"}
}