{
  "type": "Feature",
  "properties": {
    "iso:country":"US",
    "sg:address":"4010 Long Champ Dr",
    "sg:city":"Austin",
    "sg:classifiers":[
        {
            "category":"Professional",
            "subcategory":"Business Services",
            "type":"Services"
        }
    ],
    "sg:phone":"+1 512 306 1058",
    "sg:postcode":"78746",
    "sg:province":"TX",
    "sg:tags":[
        "consultant",
        "coach"
    ],
    "wof:name":"S Matherly Consultant",
    "wof:placetype":"venue"
},
  "geometry": {"coordinates":[-97.801491,30.338011],"type":"Point"}
}