{
  "type": "Feature",
  "properties": {
    "iso:country":"US",
    "sg:address":"803 Vinton Ave",
    "sg:city":"Canutillo",
    "sg:classifiers":[
        {
            "category":"Building & Trades",
            "subcategory":"Plumbing",
            "type":"Services"
        }
    ],
    "sg:phone":"+1 915 877 5115",
    "sg:postcode":"79835",
    "sg:province":"TX",
    "sg:tags":[
        "contractor"
    ],
    "wof:name":"Hambricks Heating & Cooling",
    "wof:placetype":"venue"
},
  "geometry": {"coordinates":[-106.59078,31.917655],"type":"Point"}
}