{
  "type": "Feature",
  "properties": {
    "iso:country":"US",
    "sg:address":"8947 Aspen Place Dr",
    "sg:city":"Houston",
    "sg:classifiers":[
        {
            "category":"Professional",
            "type":"Services"
        }
    ],
    "sg:phone":"+1 713 921 0141",
    "sg:postcode":"77071",
    "sg:province":"TX",
    "wof:name":"Matalino Studios",
    "wof:placetype":"venue"
},
  "geometry": {"coordinates":[-95.532067,29.648562],"type":"Point"}
}