{
  "type": "Feature",
  "properties": {
    "iso:country":"US",
    "sg:address":"12047 Islamorada Dr",
    "sg:city":"Houston",
    "sg:classifiers":[
        {
            "category":"Professional",
            "subcategory":"Art Services",
            "type":"Services"
        }
    ],
    "sg:phone":"+1 281 458 3560",
    "sg:postcode":"77044",
    "sg:province":"TX",
    "sg:tags":[
        "commercial",
        "design"
    ],
    "wof:name":"R&R Graphic Designs",
    "wof:placetype":"venue"
},
  "geometry": {"coordinates":[-95.22036799999999,29.859368],"type":"Point"}
}