{
  "type": "Feature",
  "properties": {
    "iso:country":"US",
    "sg:address":"1534 Kennebeck Pl",
    "sg:city":"Houston",
    "sg:classifiers":[
        {
            "category":"Real Estate",
            "subcategory":"Real Estate Operator",
            "type":"Services"
        }
    ],
    "sg:phone":"+1 281 497 3052",
    "sg:postcode":"77077",
    "sg:province":"TX",
    "sg:tags":[
        "building",
        "nonresidential"
    ],
    "wof:name":"Hall Computer Training",
    "wof:placetype":"venue"
},
  "geometry": {"coordinates":[-95.629684,29.757857],"type":"Point"}
}