{
  "type": "Feature",
  "properties": {
    "iso:country":"US",
    "sg:address":"114 E Parker Rd",
    "sg:city":"Houston",
    "sg:classifiers":[
        {
            "category":"Professional",
            "type":"Services"
        }
    ],
    "sg:phone":"+1 713 699 4749",
    "sg:postcode":"77076",
    "sg:province":"TX",
    "sg:tags":[
        "establishment"
    ],
    "wof:name":"Construmex",
    "wof:placetype":"venue"
},
  "geometry": {"coordinates":[-95.396591,29.859556],"type":"Point"}
}