{
  "type": "Feature",
  "properties": {
    "iso:country":"US",
    "sg:address":"21026 Park Brush Ln",
    "sg:city":"Katy",
    "sg:classifiers":[
        {
            "category":"Manufacturing",
            "subcategory":"Retail Goods",
            "type":"Manufacturing & Wholesale Goods"
        }
    ],
    "sg:phone":"+1 281 492 2766",
    "sg:postcode":"77450",
    "sg:province":"TX",
    "sg:tags":[
        "product",
        "mfg"
    ],
    "wof:name":"Ford Designs",
    "wof:placetype":"venue"
},
  "geometry": {"coordinates":[-95.73714099999999,29.770471],"type":"Point"}
}