{
  "type": "Feature",
  "properties": {
    "iso:country":"US",
    "sg:address":"303 S Tyler St",
    "sg:city":"Beeville",
    "sg:classifiers":[
        {
            "category":"Organizations",
            "subcategory":"Religious Organization",
            "type":"Services"
        }
    ],
    "sg:phone":"+1 361 362 4868",
    "sg:postcode":"78102",
    "sg:province":"TX",
    "wof:name":"Maranatha Church Of God",
    "wof:placetype":"venue"
},
  "geometry": {"coordinates":[-97.74200399999999,28.402562],"type":"Point"}
}