{
  "type": "Feature",
  "properties": {
    "iso:country":"US",
    "sg:address":"1430 Bradley Ln Ste 102",
    "sg:city":"Carrollton",
    "sg:classifiers":[
        {
            "category":"Cinema",
            "subcategory":"Movie Rental",
            "type":"Entertainment"
        }
    ],
    "sg:phone":"+1 972 245 6088",
    "sg:postcode":"75007",
    "sg:province":"TX",
    "sg:tags":[
        "game",
        "video"
    ],
    "wof:name":"Ingram Entertainment Inc",
    "wof:placetype":"venue"
},
  "geometry": {"coordinates":[-96.921997,32.9911],"type":"Point"}
}