{
  "type": "Feature",
  "properties": {
    "iso:country":"US",
    "sg:address":"607 N Main St",
    "sg:city":"Aubrey",
    "sg:classifiers":[
        {
            "category":"Building & Trades",
            "subcategory":"Construction",
            "type":"Services"
        }
    ],
    "sg:phone":"+1 940 365 9422",
    "sg:postcode":"76227",
    "sg:province":"TX",
    "sg:tags":[
        "house"
    ],
    "wof:name":"Robert Taylor Construction",
    "wof:placetype":"venue"
},
  "geometry": {"coordinates":[-96.986282,33.30922],"type":"Point"}
}