{
  "type": "Feature",
  "properties": {
    "iso:country":"US",
    "sg:address":"409 S Georgia St",
    "sg:city":"Amarillo",
    "sg:classifiers":[
        {
            "category":"Retail",
            "subcategory":"Auto Repair",
            "type":"Services"
        }
    ],
    "sg:phone":"+1 806 376 9440",
    "sg:postcode":"79106",
    "sg:province":"TX",
    "sg:tags":[
        "repairing",
        "shop",
        "general",
        "automotive",
        "automobile"
    ],
    "wof:name":"Dallas Haner Automotive Repair",
    "wof:placetype":"venue"
},
  "geometry": {"coordinates":[-101.866274,35.212656],"type":"Point"}
}