{
  "type": "Feature",
  "properties": {
    "iso:country":"US",
    "sg:address":"800 W Coke Rd",
    "sg:city":"Winnsboro",
    "sg:classifiers":[
        {
            "category":"Manufacturing",
            "subcategory":"Printing",
            "type":"Manufacturing & Wholesale Goods"
        }
    ],
    "sg:phone":"+1 903 342 0022",
    "sg:postcode":"75494",
    "sg:province":"TX",
    "sg:tags":[
        "book"
    ],
    "wof:name":"New Ventures Publishing Group",
    "wof:placetype":"venue"
},
  "geometry": {"coordinates":[-95.306798,32.94744],"type":"Point"}
}