{
  "type": "Feature",
  "properties": {
    "iso:country":"US",
    "sg:address":"715 N Main St",
    "sg:city":"Bremond",
    "sg:classifiers":[
        {
            "category":"Organizations",
            "subcategory":"Religious Organization",
            "type":"Services"
        }
    ],
    "sg:phone":"+1 254 746 7789",
    "sg:postcode":"76629",
    "sg:province":"TX",
    "sg:tags":[
        "church"
    ],
    "wof:name":"St Mary's Rectory",
    "wof:placetype":"venue"
},
  "geometry": {"coordinates":[-96.673114,31.171165],"type":"Point"}
}