{
  "type": "Feature",
  "properties": {
    "iso:country":"US",
    "sg:address":"14860 Montfort Drive Suite 210",
    "sg:city":"Dallas",
    "sg:classifiers":[
        {
            "category":"Professional",
            "subcategory":"Computer Services",
            "type":"Services"
        }
    ],
    "sg:phone":"+1 214 722 3040",
    "sg:postcode":"75254 ",
    "sg:province":"TX",
    "sg:website":"http://www.chinacrescent.com",
    "wof:name":"China Crescent",
    "wof:placetype":"venue"
},
  "geometry": {"coordinates":[-96.81827699999999,32.950804],"type":"Point"}
}