{
  "type": "Feature",
  "properties": {
    "iso:country":"US",
    "sg:address":"200 N Matthews St",
    "sg:city":"Bowie",
    "sg:classifiers":[
        {
            "category":"Food & Beverages",
            "subcategory":"Groceries & Convenience Stores",
            "type":"Retail Goods"
        }
    ],
    "sg:phone":"+1 940 872 1104",
    "sg:postcode":"76230",
    "sg:province":"TX",
    "sg:tags":[
        "independent"
    ],
    "wof:name":"Quickway",
    "wof:placetype":"venue"
},
  "geometry": {"coordinates":[-97.85300599999999,33.562606],"type":"Point"}
}