{
  "type": "Feature",
  "properties": {
    "iso:country":"US",
    "sg:address":"3209 Red Oak Ln",
    "sg:city":"Bedford",
    "sg:classifiers":[
        {
            "category":"Professional",
            "type":"Services"
        }
    ],
    "sg:phone":"+1 817 283 1359",
    "sg:postcode":"76021",
    "sg:province":"TX",
    "wof:name":"Texas Bounce Inc",
    "wof:placetype":"venue"
},
  "geometry": {"coordinates":[-97.12113100000001,32.858311],"type":"Point"}
}