{
  "type": "Feature",
  "properties": {
    "iso:country":"US",
    "sg:address":"273 Raintree Dr",
    "sg:city":"Lewisville",
    "sg:classifiers":[
        {
            "category":"Professional",
            "subcategory":"Business Services",
            "type":"Services"
        }
    ],
    "sg:phone":"+1 972 317 2399",
    "sg:postcode":"75077",
    "sg:province":"TX",
    "wof:name":"Great American Scrapbook Co",
    "wof:placetype":"venue"
},
  "geometry": {"coordinates":[-97.037442,33.090484],"type":"Point"}
}