{
  "type": "Feature",
  "properties": {
    "iso:country":"US",
    "sg:address":"207 E School House Rd",
    "sg:city":"Paradise",
    "sg:classifiers":[
        {
            "category":"Building & Trades",
            "subcategory":"Construction",
            "type":"Services"
        }
    ],
    "sg:phone":"+1 940 969 2373",
    "sg:postcode":"76073",
    "sg:province":"TX",
    "sg:tags":[
        "hanging",
        "contractor"
    ],
    "wof:name":"Paradise Painting",
    "wof:placetype":"venue"
},
  "geometry": {"coordinates":[-97.68578100000001,33.148049],"type":"Point"}
}