{
  "type": "Feature",
  "properties": {
    "iso:country":"US",
    "sg:address":"19782 Old Hwy 105 W",
    "sg:city":"Montgomery",
    "sg:classifiers":[
        {
            "category":"Health Services",
            "subcategory":"Doctor",
            "type":"Services"
        }
    ],
    "sg:phone":"+1 936 448 4114",
    "sg:postcode":"77356",
    "sg:province":"TX",
    "sg:tags":[
        "physician",
        "surgeon"
    ],
    "wof:name":"Physicians Specialty Ctr",
    "wof:placetype":"venue"
},
  "geometry": {"coordinates":[-95.79345600000001,30.345241],"type":"Point"}
}