{
  "type": "Feature",
  "properties": {
    "iso:country":"US",
    "sg:address":"5151 S Foster Rd",
    "sg:city":"San Antonio",
    "sg:classifiers":[
        {
            "category":"Building & Trades",
            "subcategory":"Construction",
            "type":"Services"
        }
    ],
    "sg:phone":"+1 210 648 7667",
    "sg:postcode":"78222",
    "sg:province":"TX",
    "sg:tags":[
        "mobile",
        "home"
    ],
    "wof:name":"My 3 Sons Mobile Home Svc",
    "wof:placetype":"venue"
},
  "geometry": {"coordinates":[-98.360905,29.376562],"type":"Point"}
}