{
  "type": "Feature",
  "properties": {
    "iso:country":"US",
    "sg:address":"2008 W 3rd St",
    "sg:city":"Monahans",
    "sg:classifiers":[
        {
            "category":"Retail",
            "subcategory":"Repair Shop",
            "type":"Services"
        }
    ],
    "sg:phone":"+1 432 943 5232",
    "sg:postcode":"79756",
    "sg:province":"TX",
    "wof:name":"Aztec PC Repair",
    "wof:placetype":"venue"
},
  "geometry": {"coordinates":[-102.91577100000001,31.585584],"type":"Point"}
}