{
  "type": "Feature",
  "properties": {
    "iso:country":"US",
    "sg:address":"3702 Altamesa Blvd",
    "sg:city":"Fort Worth",
    "sg:classifiers":[
        {
            "category":"Restaurant",
            "type":"Food & Drink"
        }
    ],
    "sg:phone":"+1 817 263 1700",
    "sg:postcode":"76133",
    "sg:province":"TX",
    "sg:tags":[
        "eating"
    ],
    "wof:name":"E & C Wok",
    "wof:placetype":"venue"
},
  "geometry": {"coordinates":[-97.374765,32.650385],"type":"Point"}
}