{
  "type": "Feature",
  "properties": {
    "iso:country":"US",
    "sg:address":"3829 Sunnyview Ln",
    "sg:city":"Flower Mound",
    "sg:classifiers":[
        {
            "category":"Professional",
            "subcategory":"Computer Services",
            "type":"Services"
        }
    ],
    "sg:phone":"+1 817 430 4665",
    "sg:postcode":"75022",
    "sg:province":"TX",
    "sg:tags":[
        "internet"
    ],
    "wof:name":"Unwired DFW Inc",
    "wof:placetype":"venue"
},
  "geometry": {"coordinates":[-97.15317400000001,33.033677],"type":"Point"}
}