{
  "type": "Feature",
  "properties": {
    "iso:country":"US",
    "sg:address":"7 Ironwood Rd",
    "sg:city":"San Antonio",
    "sg:classifiers":[
        {
            "category":"Professional",
            "subcategory":"Management & Consulting",
            "type":"Services"
        }
    ],
    "sg:phone":"+1 210 930 5252",
    "sg:postcode":"78212",
    "sg:province":"TX",
    "sg:tags":[
        "automobile",
        "consultant"
    ],
    "wof:name":"Power Automotive Consulting",
    "wof:placetype":"venue"
},
  "geometry": {"coordinates":[-98.477369,29.468952],"type":"Point"}
}