{
  "type": "Feature",
  "properties": {
    "iso:country":"US",
    "sg:address":"12824 Veterans Memorial Dr",
    "sg:city":"Houston",
    "sg:classifiers":[
        {
            "category":"Cinema",
            "subcategory":"Movie Rental",
            "type":"Entertainment"
        }
    ],
    "sg:phone":"+1 281 537 5996",
    "sg:postcode":"77014",
    "sg:province":"TX",
    "sg:tags":[
        "leasing",
        "video",
        "disc",
        "tape"
    ],
    "wof:name":"Loa Video",
    "wof:placetype":"venue"
},
  "geometry": {"coordinates":[-95.487193,29.972915],"type":"Point"}
}