{
  "type": "Feature",
  "properties": {
    "iso:country":"US",
    "sg:address":"1535 Bosher Dr",
    "sg:city":"Cedar Hill",
    "sg:classifiers":[
        {
            "category":"Social Services",
            "subcategory":"Child Care",
            "type":"Services"
        },
        {
            "category":"Education",
            "subcategory":"Special Training",
            "type":"Public Place"
        }
    ],
    "sg:phone":"+1 972 299 0537",
    "sg:postcode":"75104",
    "sg:province":"TX",
    "sg:tags":[
        "center",
        "day"
    ],
    "wof:name":"Good Day Learning & Developmen",
    "wof:placetype":"venue"
},
  "geometry": {"coordinates":[-96.937203,32.61809],"type":"Point"}
}