{
  "type": "Feature",
  "properties": {
    "iso:country":"US",
    "sg:address":"17 Plaza Cir",
    "sg:city":"Texarkana",
    "sg:classifiers":[
        {
            "category":"Personal",
            "subcategory":"Beauty Salon",
            "type":"Services"
        },
        {
            "category":"Personal",
            "subcategory":"Barber",
            "type":"Services"
        }
    ],
    "sg:phone":"+1 903 792 7786",
    "sg:postcode":"75503",
    "sg:province":"TX",
    "sg:tags":[
        "hair",
        "stylist"
    ],
    "wof:name":"Brute Barber Shop",
    "wof:placetype":"venue"
},
  "geometry": {"coordinates":[-94.070953,33.469958],"type":"Point"}
}