{
  "type": "Feature",
  "properties": {
    "iso:country":"US",
    "sg:address":"3948 Legacy Dr",
    "sg:city":"Plano",
    "sg:classifiers":[
        {
            "category":"Personal",
            "subcategory":"Beauty Salon",
            "type":"Services"
        }
    ],
    "sg:phone":"+1 972 943 0732",
    "sg:postcode":"75023",
    "sg:province":"TX",
    "sg:tags":[
        "shop"
    ],
    "wof:name":"Styling Hutch",
    "wof:placetype":"venue"
},
  "geometry": {"coordinates":[-96.77198799999999,33.071651],"type":"Point"}
}