{
  "type": "Feature",
  "properties": {
    "iso:country":"US",
    "sg:address":"1533 el Monte Blvd",
    "sg:city":"San Antonio",
    "sg:classifiers":[
        {
            "category":"Professional",
            "subcategory":"Business Services",
            "type":"Services"
        }
    ],
    "sg:phone":"+1 210 525 1274",
    "sg:postcode":"78201",
    "sg:province":"TX",
    "sg:tags":[
        "dry",
        "good",
        "hauling"
    ],
    "wof:name":"Cargo Express",
    "wof:placetype":"venue"
},
  "geometry": {"coordinates":[-98.520291,29.485035],"type":"Point"}
}