{
  "type": "Feature",
  "properties": {
    "iso:country":"US",
    "sg:address":"716 W Yandell Dr",
    "sg:city":"El Paso",
    "sg:classifiers":[
        {
            "category":"Real Estate",
            "subcategory":"Real Estate Operator",
            "type":"Services"
        }
    ],
    "sg:phone":"+1 915 542 0177",
    "sg:postcode":"79902",
    "sg:province":"TX",
    "sg:tags":[
        "building",
        "apartment"
    ],
    "wof:name":"Laespana Apts",
    "wof:placetype":"venue"
},
  "geometry": {"coordinates":[-106.49746399999999,31.763331],"type":"Point"}
}