{
  "type": "Feature",
  "properties": {
    "iso:country":"US",
    "sg:address":"11 Greenway Plz Ste 1515",
    "sg:city":"Houston",
    "sg:classifiers":[
        {
            "category":"Building & Trades",
            "subcategory":"Construction",
            "type":"Services"
        }
    ],
    "sg:phone":"+1 713 686 7764",
    "sg:postcode":"77046",
    "sg:province":"TX",
    "sg:tags":[
        "consultant"
    ],
    "wof:name":"P2mg",
    "wof:placetype":"venue"
},
  "geometry": {"coordinates":[-95.432068,29.732825],"type":"Point"}
}