{
  "type": "Feature",
  "properties": {
    "iso:country":"US",
    "sg:address":"16222 Koester St",
    "sg:city":"Houston",
    "sg:classifiers":[
        {
            "category":"Travel",
            "subcategory":"Travel Agent",
            "type":"Entertainment"
        }
    ],
    "sg:phone":"+1 713 466 1884",
    "sg:postcode":"77040",
    "sg:province":"TX",
    "sg:tags":[
        "agency"
    ],
    "wof:name":"Metcalf Cruises",
    "wof:placetype":"venue"
},
  "geometry": {"coordinates":[-95.56713499999999,29.893216],"type":"Point"}
}