{
  "type": "Feature",
  "properties": {
    "iso:country":"US",
    "sg:address":"747 US Hwy 259",
    "sg:city":"Kilgore",
    "sg:classifiers":[
        {
            "category":"Food & Beverages",
            "subcategory":"Groceries & Convenience Stores",
            "type":"Retail Goods"
        }
    ],
    "sg:phone":"+1 903 983 2576",
    "sg:postcode":"75662",
    "sg:province":"TX",
    "wof:name":"Brookshire Food 008",
    "wof:placetype":"venue"
},
  "geometry": {"coordinates":[-94.86826600000001,32.386429],"type":"Point"}
}