{
  "type": "Feature",
  "properties": {
    "iso:country":"US",
    "sg:address":"1111 Pinewood Ln",
    "sg:city":"Seabrook",
    "sg:classifiers":[
        {
            "category":"Professional",
            "subcategory":"Management & Consulting",
            "type":"Services"
        }
    ],
    "sg:phone":"+1 281 326 4672",
    "sg:postcode":"77586",
    "sg:province":"TX",
    "sg:tags":[
        "business"
    ],
    "wof:name":"Wiersig Services",
    "wof:placetype":"venue"
},
  "geometry": {"coordinates":[-95.057436,29.580607],"type":"Point"}
}