{
  "type": "Feature",
  "properties": {
    "iso:country":"US",
    "sg:address":"3564 Far W Blvd",
    "sg:city":"Austin",
    "sg:classifiers":[
        {
            "category":"Autos & Motor Vehicles",
            "subcategory":"Auto Supplies",
            "type":"Retail Goods"
        },
        {
            "category":"Retail",
            "subcategory":"Auto Repair",
            "type":"Services"
        }
    ],
    "sg:phone":"+1 512 345 6600",
    "sg:postcode":"78731",
    "sg:province":"TX",
    "sg:tags":[
        "tire"
    ],
    "sg:website":"www.lambstire.com/",
    "wof:name":"Lamb's Tire & Automotive",
    "wof:placetype":"venue"
},
  "geometry": {"coordinates":[-97.753984,30.354264],"type":"Point"}
}