{
  "type": "Feature",
  "properties": {
    "iso:country":"US",
    "sg:address":"15111 Preston Rd Ste 107",
    "sg:city":"Dallas",
    "sg:classifiers":[
        {
            "category":"Professional",
            "subcategory":"Lawyer & Legal Services",
            "type":"Services"
        },
        {
            "category":"Professional",
            "subcategory":"Printing & Photocopies",
            "type":"Services"
        }
    ],
    "sg:phone":"+1 972 239 3233",
    "sg:postcode":"75248",
    "sg:province":"TX",
    "sg:tags":[
        "notary"
    ],
    "wof:name":"Eagle Postal Centers",
    "wof:placetype":"venue"
},
  "geometry": {"coordinates":[-96.804497,32.954498],"type":"Point"}
}