{
  "type": "Feature",
  "properties": {
    "iso:country":"US",
    "sg:address":"3333 Bering Dr",
    "sg:city":"Houston",
    "sg:classifiers":[
        {
            "category":"Education",
            "subcategory":"School",
            "type":"Public Place"
        }
    ],
    "sg:phone":"+1 972 231 7040",
    "sg:postcode":"77057",
    "sg:province":"TX",
    "wof:name":"Saber Academy",
    "wof:placetype":"venue"
},
  "geometry": {"coordinates":[-95.48020200000001,29.73],"type":"Point"}
}