{
  "type": "Feature",
  "properties": {
    "iso:country":"US",
    "sg:address":"2304 S Congress Ave",
    "sg:city":"Austin",
    "sg:classifiers":[
        {
            "category":"Restaurant",
            "type":"Food & Drink"
        }
    ],
    "sg:phone":"+1 512 445 9727",
    "sg:postcode":"78704",
    "sg:province":"TX",
    "sg:tags":[
        "indian"
    ],
    "sg:website":"www.newindia.us",
    "wof:name":"New India Cuisine",
    "wof:placetype":"venue"
},
  "geometry": {"coordinates":[-97.75321,30.239881],"type":"Point"}
}