{
  "type": "Feature",
  "properties": {
    "iso:country":"US",
    "sg:address":"3410 Crest Elm Dr",
    "sg:city":"Corpus Christi",
    "sg:classifiers":[
        {
            "category":"Building & Trades",
            "subcategory":"Construction",
            "type":"Services"
        }
    ],
    "sg:phone":"+1 361 852 8753",
    "sg:postcode":"78415",
    "sg:province":"TX",
    "sg:tags":[
        "house"
    ],
    "wof:name":"JRS Renovations",
    "wof:placetype":"venue"
},
  "geometry": {"coordinates":[-97.41580500000001,27.715633],"type":"Point"}
}