{
  "type": "Feature",
  "properties": {
    "iso:country":"US",
    "sg:address":"8414 Ledford Ln",
    "sg:city":"Converse",
    "sg:classifiers":[
        {
            "category":"Restaurant",
            "type":"Food & Drink"
        }
    ],
    "sg:phone":"+1 210 566 2171",
    "sg:postcode":"78109",
    "sg:province":"TX",
    "sg:tags":[
        "eating"
    ],
    "wof:name":"Lettys Catering Inc",
    "wof:placetype":"venue"
},
  "geometry": {"coordinates":[-98.314139,29.507309],"type":"Point"}
}