{
  "type": "Feature",
  "properties": {
    "iso:country":"US",
    "sg:address":"13310 Verbena Ln",
    "sg:city":"Houston",
    "sg:classifiers":[
        {
            "category":"Professional",
            "subcategory":"Business Services",
            "type":"Services"
        }
    ],
    "sg:phone":"+1 281 498 6045",
    "sg:postcode":"77083",
    "sg:province":"TX",
    "wof:name":"Charles Lindsay Drafting Inc",
    "wof:placetype":"venue"
},
  "geometry": {"coordinates":[-95.618893,29.707525],"type":"Point"}
}