{
  "type": "Feature",
  "properties": {
    "iso:country":"US",
    "sg:address":"102 W American Blvd",
    "sg:city":"Muleshoe",
    "sg:classifiers":[
        {
            "category":"Professional",
            "type":"Services"
        }
    ],
    "sg:phone":"+1 806 272 5278",
    "sg:postcode":"79347",
    "sg:province":"TX",
    "sg:tags":[
        "establishment"
    ],
    "wof:name":"Ince Fina No 21",
    "wof:placetype":"venue"
},
  "geometry": {"coordinates":[-102.724841,34.226935],"type":"Point"}
}