{
  "type": "Feature",
  "properties": {
    "iso:country":"US",
    "sg:address":"7514 Bairnsdale Ln",
    "sg:city":"Houston",
    "sg:classifiers":[
        {
            "category":"Professional",
            "subcategory":"Business Services",
            "type":"Services"
        }
    ],
    "sg:phone":"+1 281 955 1013",
    "sg:postcode":"77070",
    "sg:province":"TX",
    "wof:name":"B&R Design LLC",
    "wof:placetype":"venue"
},
  "geometry": {"coordinates":[-95.54798,29.980401],"type":"Point"}
}