{
  "type": "Feature",
  "properties": {
    "iso:country":"US",
    "sg:address":"3913 Todd Ln Ste 301",
    "sg:city":"Austin",
    "sg:classifiers":[
        {
            "category":"Personal",
            "type":"Services"
        }
    ],
    "sg:phone":"+1 512 892 4000",
    "sg:postcode":"78744",
    "sg:province":"TX",
    "sg:tags":[
        "mover"
    ],
    "sg:website":"www.alohaaustin.com",
    "wof:name":"Aloha Moving",
    "wof:placetype":"venue"
},
  "geometry": {"coordinates":[-97.736225,30.213329],"type":"Point"}
}