{
  "type": "Feature",
  "properties": {
    "iso:country":"US",
    "sg:address":"7203 Lenora St",
    "sg:city":"Austin",
    "sg:classifiers":[
        {
            "category":"Shopping",
            "subcategory":"Books",
            "type":"Retail Goods"
        }
    ],
    "sg:phone":"+1 512 444 2543",
    "sg:postcode":"78745",
    "sg:province":"TX",
    "sg:tags":[
        "dealer"
    ],
    "wof:name":"Crazy Horse Book Co",
    "wof:placetype":"venue"
},
  "geometry": {"coordinates":[-97.796358,30.193627],"type":"Point"}
}