{
  "type": "Feature",
  "properties": {
    "iso:country":"US",
    "sg:address":"2304 Pheasant Trl",
    "sg:city":"Arlington",
    "sg:classifiers":[
        {
            "category":"Retail",
            "subcategory":"Laundry & Dry Cleaning",
            "type":"Services"
        }
    ],
    "sg:phone":"+1 817 469 8689",
    "sg:postcode":"76016",
    "sg:province":"TX",
    "sg:tags":[
        "cleaners"
    ],
    "wof:name":"Y Pay More Cleaners",
    "wof:placetype":"venue"
},
  "geometry": {"coordinates":[-97.182772,32.705234],"type":"Point"}
}