{
  "type": "Feature",
  "properties": {
    "iso:country":"US",
    "sg:address":"608 W 12th St Ste A",
    "sg:city":"Austin",
    "sg:classifiers":[
        {
            "category":"Professional",
            "subcategory":"Lawyer & Legal Services",
            "type":"Services"
        }
    ],
    "sg:phone":"+1 512 472 7893",
    "sg:postcode":"78701",
    "sg:province":"TX",
    "wof:name":"Alberts William H Atty",
    "wof:placetype":"venue"
},
  "geometry": {"coordinates":[-97.74630000000001,30.2756],"type":"Point"}
}