{
  "type": "Feature",
  "properties": {
    "iso:country":"US",
    "sg:address":"201 S 1st St",
    "sg:city":"Temple",
    "sg:classifiers":[
        {
            "category":"Personal",
            "subcategory":"Barber",
            "type":"Services"
        }
    ],
    "sg:phone":"+1 254 778 9730",
    "sg:postcode":"76501",
    "sg:province":"TX",
    "sg:tags":[
        "shop"
    ],
    "wof:name":"Gandy's Barber Shop",
    "wof:placetype":"venue"
},
  "geometry": {"coordinates":[-97.342979,31.09479],"type":"Point"}
}