{
  "type": "Feature",
  "properties": {
    "iso:country":"US",
    "sg:address":"8415 Mahogany Ct",
    "sg:city":"Laredo",
    "sg:classifiers":[
        {
            "category":"Banks & Credit Unions",
            "subcategory":"Bank",
            "type":"Services"
        }
    ],
    "sg:phone":"+1 956 726 8828",
    "sg:postcode":"78045",
    "sg:province":"TX",
    "sg:tags":[
        "institution",
        "business"
    ],
    "wof:name":"A R L Mall Investments Ltd",
    "wof:placetype":"venue"
},
  "geometry": {"coordinates":[-99.47512,27.583751],"type":"Point"}
}