{
  "type": "Feature",
  "properties": {
    "iso:country":"US",
    "sg:address":"8757 Autobahn Dr",
    "sg:city":"Dallas",
    "sg:classifiers":[
        {
            "category":"Health Services",
            "subcategory":"Hospital",
            "type":"Services"
        }
    ],
    "sg:phone":"+1 214 820 2885",
    "sg:postcode":"75237",
    "sg:province":"TX",
    "sg:tags":[
        "general"
    ],
    "wof:name":"Distribution",
    "wof:placetype":"venue"
},
  "geometry": {"coordinates":[-96.862223,32.642128],"type":"Point"}
}