{
  "type": "Feature",
  "properties": {
    "iso:country":"US",
    "sg:address":"137 S Main St",
    "sg:city":"Paris",
    "sg:classifiers":[
        {
            "category":"Banks & Credit Unions",
            "subcategory":"Bank",
            "type":"Services"
        }
    ],
    "sg:phone":"+1 903 785 6436",
    "sg:postcode":"75460",
    "sg:province":"TX",
    "sg:tags":[
        "personal",
        "institution"
    ],
    "wof:name":"T & B Rentals",
    "wof:placetype":"venue"
},
  "geometry": {"coordinates":[-95.55620999999999,33.66039],"type":"Point"}
}