{
  "type": "Feature",
  "properties": {
    "iso:country":"US",
    "sg:address":"920 Circle Dr",
    "sg:city":"Nederland",
    "sg:classifiers":[
        {
            "category":"Home & Garden",
            "subcategory":"Home Furnishings",
            "type":"Retail Goods"
        }
    ],
    "sg:phone":"+1 409 727 7478",
    "sg:postcode":"77627",
    "sg:province":"TX",
    "wof:name":"E Z N Ramps",
    "wof:placetype":"venue"
},
  "geometry": {"coordinates":[-94.01151400000001,29.964112],"type":"Point"}
}