{
  "type": "Feature",
  "properties": {
    "iso:country":"US",
    "sg:address":"1715 Sawdust Rd",
    "sg:city":"Spring",
    "sg:classifiers":[
        {
            "category":"Retail",
            "subcategory":"Repair Shop",
            "type":"Services"
        }
    ],
    "sg:phone":"+1 281 362 1311",
    "sg:postcode":"77380",
    "sg:province":"TX",
    "sg:tags":[
        "machine",
        "fax",
        "copy",
        "sale"
    ],
    "wof:name":"Copy World",
    "wof:placetype":"venue"
},
  "geometry": {"coordinates":[-95.47063300000001,30.126172],"type":"Point"}
}