{
  "type": "Feature",
  "properties": {
    "iso:country":"US",
    "sg:address":"8220 N Hwy 146",
    "sg:city":"Baytown",
    "sg:classifiers":[
        {
            "category":"Food & Beverages",
            "subcategory":"Fruits & Vegetables",
            "type":"Retail Goods"
        }
    ],
    "sg:phone":"+1 281 383 1300",
    "sg:postcode":"77521",
    "sg:province":"TX",
    "wof:name":"Bluebonnet Farms Ltd",
    "wof:placetype":"venue"
},
  "geometry": {"coordinates":[-94.90137799999999,29.813658],"type":"Point"}
}