{
  "type": "Feature",
  "properties": {
    "iso:country":"US",
    "sg:address":"6009 Richmond Ave Ste 222",
    "sg:city":"Houston",
    "sg:classifiers":[
        {
            "category":"Autos & Motor Vehicles",
            "subcategory":"Automobile Sales",
            "type":"Retail Goods"
        }
    ],
    "sg:phone":"+1 713 667 5466",
    "sg:postcode":"77057",
    "sg:province":"TX",
    "sg:tags":[
        "limo"
    ],
    "wof:name":"Aloha Limousine & Valet Parking Services",
    "wof:placetype":"venue"
},
  "geometry": {"coordinates":[-95.48490099999999,29.7314],"type":"Point"}
}