{
  "type": "Feature",
  "properties": {
    "iso:country":"US",
    "sg:address":"10466 Terrace Rd",
    "sg:city":"Sanger",
    "sg:classifiers":[
        {
            "category":"Home & Garden",
            "subcategory":"Household Appliances",
            "type":"Retail Goods"
        },
        {
            "category":"Building & Trades",
            "subcategory":"Construction",
            "type":"Services"
        }
    ],
    "sg:phone":"+1 940 458 9391",
    "sg:postcode":"76266",
    "sg:province":"TX",
    "sg:tags":[
        "major",
        "system",
        "appliances-small",
        "specialty",
        "heating",
        "contractor",
        "air conditioning"
    ],
    "wof:name":"Norman's Heat & Air Inc",
    "wof:placetype":"venue"
},
  "geometry": {"coordinates":[-97.121752,33.360541],"type":"Point"}
}