{
  "type": "Feature",
  "properties": {
    "iso:country":"US",
    "sg:address":"283 N Wills St",
    "sg:city":"Wills Point",
    "sg:classifiers":[
        {
            "category":"Building & Trades",
            "subcategory":"Plumbing",
            "type":"Services"
        }
    ],
    "sg:phone":"+1 903 873 8524",
    "sg:postcode":"75169",
    "sg:province":"TX",
    "sg:tags":[
        "heating",
        "contractor"
    ],
    "wof:name":"All Around Air CONDITIONING",
    "wof:placetype":"venue"
},
  "geometry": {"coordinates":[-96.01128,32.709583],"type":"Point"}
}