{
  "type": "Feature",
  "properties": {
    "iso:country":"US",
    "sg:address":"4425 Jefferson Ave",
    "sg:city":"Texarkana",
    "sg:classifiers":[
        {
            "category":"Shopping",
            "type":"Retail Goods"
        }
    ],
    "sg:phone":"+1 870 773 6270",
    "sg:postcode":"71854",
    "sg:province":"TX",
    "sg:tags":[
        "hearing",
        "equipment",
        "supply",
        "merchandise",
        "impaired"
    ],
    "wof:name":"J & L Hearing Center",
    "wof:placetype":"venue"
},
  "geometry": {"coordinates":[-94.029095,33.465992],"type":"Point"}
}