{
  "type": "Feature",
  "properties": {
    "iso:country":"US",
    "sg:address":"4414 Cedar Springs Rd",
    "sg:city":"Dallas",
    "sg:classifiers":[
        {
            "category":"Wholesale",
            "subcategory":"Computers",
            "type":"Manufacturing & Wholesale Goods"
        }
    ],
    "sg:phone":"+1 214 522 4195",
    "sg:postcode":"75219",
    "sg:province":"TX",
    "wof:name":"Proact",
    "wof:placetype":"venue"
},
  "geometry": {"coordinates":[-96.816299,32.815102],"type":"Point"}
}