{
  "type": "Feature",
  "properties": {
    "iso:country":"US",
    "sg:address":"800 Buttercup Ln",
    "sg:city":"Arlington",
    "sg:classifiers":[
        {
            "category":"Building & Trades",
            "subcategory":"Construction",
            "type":"Services"
        }
    ],
    "sg:phone":"+1 817 467 3164",
    "sg:postcode":"76002",
    "sg:province":"TX",
    "sg:tags":[
        "house"
    ],
    "wof:name":"Ellis Construction",
    "wof:placetype":"venue"
},
  "geometry": {"coordinates":[-97.09958399999999,32.635899],"type":"Point"}
}