{
  "type": "Feature",
  "properties": {
    "iso:country":"US",
    "sg:address":"7729 Knickerbocker Rd",
    "sg:city":"San Angelo",
    "sg:classifiers":[
        {
            "category":"Mining & Drilling",
            "type":"Manufacturing & Wholesale Goods"
        }
    ],
    "sg:phone":"+1 325 234 4893",
    "sg:postcode":"76904",
    "sg:province":"TX",
    "sg:tags":[
        "oil"
    ],
    "wof:name":"Maddox Drilling Services LLC",
    "wof:placetype":"venue"
},
  "geometry": {"coordinates":[-100.494285,31.371729],"type":"Point"}
}