{
  "type": "Feature",
  "properties": {
    "iso:country":"US",
    "sg:address":"157 Oak Fields Dr",
    "sg:city":"Floresville",
    "sg:classifiers":[
        {
            "category":"Shopping",
            "subcategory":"Jewelry",
            "type":"Retail Goods"
        }
    ],
    "sg:phone":"+1 830 393 1910",
    "sg:postcode":"78114",
    "sg:province":"TX",
    "wof:name":"Casteels",
    "wof:placetype":"venue"
},
  "geometry": {"coordinates":[-98.21134499999999,29.235158],"type":"Point"}
}