{
  "type": "Feature",
  "properties": {
    "iso:country":"US",
    "sg:address":"4431 Griggs Rd",
    "sg:city":"Houston",
    "sg:classifiers":[
        {
            "category":"Banks & Credit Unions",
            "subcategory":"Bank",
            "type":"Services"
        }
    ],
    "sg:phone":"+1 713 741 6700",
    "sg:postcode":"77021",
    "sg:province":"TX",
    "sg:tags":[
        "loan"
    ],
    "wof:name":"Custom Loans Inc",
    "wof:placetype":"venue"
},
  "geometry": {"coordinates":[-95.349553,29.702163],"type":"Point"}
}