{
  "type": "Feature",
  "properties": {
    "iso:country":"US",
    "sg:address":"1011 S University Parks Dr",
    "sg:city":"Waco",
    "sg:classifiers":[
        {
            "category":"Shopping",
            "subcategory":"Hobbies, Toys, & Games",
            "type":"Retail Goods"
        },
        {
            "category":"Shopping",
            "subcategory":"Gifts & Souvenirs",
            "type":"Retail Goods"
        }
    ],
    "sg:phone":"+1 254 754 3350",
    "sg:postcode":"76706",
    "sg:province":"TX",
    "sg:tags":[
        "shop"
    ],
    "wof:name":"Harts n Crafts",
    "wof:placetype":"venue"
},
  "geometry": {"coordinates":[-97.119235,31.552521],"type":"Point"}
}