{
  "type": "Feature",
  "properties": {
    "iso:country":"US",
    "sg:address":"380 Uvalde Rd",
    "sg:city":"Houston",
    "sg:classifiers":[
        {
            "category":"Restaurant",
            "type":"Food & Drink"
        }
    ],
    "sg:phone":"+1 713 453 1011",
    "sg:postcode":"77015",
    "sg:province":"TX",
    "sg:tags":[
        "seafood"
    ],
    "wof:name":"Long John Silvers",
    "wof:placetype":"venue"
},
  "geometry": {"coordinates":[-95.187028,29.792305],"type":"Point"}
}