{
  "type": "Feature",
  "properties": {
    "iso:country":"US",
    "sg:address":"6890 Harrisburg Blvd",
    "sg:city":"Houston",
    "sg:classifiers":[
        {
            "category":"Restaurant",
            "type":"Food & Drink"
        }
    ],
    "sg:phone":"+1 713 921 4100",
    "sg:postcode":"77011",
    "sg:province":"TX",
    "sg:tags":[
        "mexican"
    ],
    "wof:name":"Mambo Parrilla",
    "wof:placetype":"venue"
},
  "geometry": {"coordinates":[-95.30439800000001,29.7363],"type":"Point"}
}