{
  "type": "Feature",
  "properties": {
    "iso:country":"US",
    "sg:address":"10700 Richmond Ave Ste 223",
    "sg:city":"Houston",
    "sg:classifiers":[
        {
            "category":"Personal",
            "type":"Services"
        }
    ],
    "sg:phone":"+1 281 708 5858",
    "sg:postcode":"77042",
    "sg:province":"TX",
    "sg:tags":[
        "sewing",
        "alteration"
    ],
    "sg:website":"www.imparali.com",
    "wof:name":"Imparali Custom Tailors",
    "wof:placetype":"venue"
},
  "geometry": {"coordinates":[-95.564607,29.728612],"type":"Point"}
}