{
  "type": "Feature",
  "properties": {
    "iso:country":"US",
    "sg:address":"9850 Drysdale Ln",
    "sg:city":"Houston",
    "sg:classifiers":[
        {
            "category":"Education",
            "subcategory":"Music School",
            "type":"Public Place"
        }
    ],
    "sg:phone":"+1 713 690 2200",
    "sg:postcode":"77041",
    "sg:province":"TX",
    "sg:tags":[
        "instrument",
        "teacher",
        "musical"
    ],
    "wof:name":"Home Dialysis",
    "wof:placetype":"venue"
},
  "geometry": {"coordinates":[-95.535937,29.852326],"type":"Point"}
}