{
  "type": "Feature",
  "properties": {
    "iso:country":"US",
    "sg:address":"5520 N McColl Rd",
    "sg:city":"Mcallen",
    "sg:classifiers":[
        {
            "category":"Professional",
            "subcategory":"Lawyer & Legal Services",
            "type":"Services"
        }
    ],
    "sg:phone":"+1 956 664 8330",
    "sg:postcode":"78504",
    "sg:province":"TX",
    "wof:name":"Mercier Eugene X Law Offices",
    "wof:placetype":"venue"
},
  "geometry": {"coordinates":[-98.20441599999999,26.24986],"type":"Point"}
}