{
  "type": "Feature",
  "properties": {
    "iso:country":"US",
    "sg:address":"600 Congress Ave Ste 2400",
    "sg:city":"Austin",
    "sg:classifiers":[
        {
            "category":"Professional",
            "subcategory":"Lawyer & Legal Services",
            "type":"Services"
        },
        {
            "category":"Banks & Credit Unions",
            "subcategory":"Financial Services",
            "type":"Services"
        }
    ],
    "sg:phone":"+1 512 474 5201",
    "sg:postcode":"78701",
    "sg:province":"TX",
    "sg:tags":[
        "attorney",
        "law",
        "business",
        "bankruptcy"
    ],
    "wof:name":"Mendez, Anna - Giarratani Shafeeqa Watkins",
    "wof:placetype":"venue"
},
  "geometry": {"coordinates":[-97.742828,30.268049],"type":"Point"}
}