{
  "type": "Feature",
  "properties": {
    "iso:country":"US",
    "sg:address":"1244 Tanner Dr",
    "sg:city":"Lewisville",
    "sg:classifiers":[
        {
            "category":"Autos & Motor Vehicles",
            "subcategory":"Automobile Sales",
            "type":"Retail Goods"
        }
    ],
    "sg:phone":"+1 972 434 5424",
    "sg:postcode":"75077",
    "sg:province":"TX",
    "sg:tags":[
        "machine",
        "repair",
        "tool",
        "rebuild"
    ],
    "wof:name":"Tektool International, Inc.",
    "wof:placetype":"venue"
},
  "geometry": {"coordinates":[-97.023967,33.063583],"type":"Point"}
}