{
  "type": "Feature",
  "properties": {
    "iso:country":"US",
    "sg:address":"2614 NW Stallings Dr",
    "sg:city":"Nacogdoches",
    "sg:classifiers":[
        {
            "category":"Government",
            "subcategory":"Office",
            "type":"Public Place"
        }
    ],
    "sg:phone":"+1 936 569 6695",
    "sg:postcode":"75964",
    "sg:province":"TX",
    "sg:tags":[
        "state",
        "resource"
    ],
    "sg:website":"www.hhsc.state.tx.us",
    "wof:name":"Human Service Dept-Food Stamps",
    "wof:placetype":"venue"
},
  "geometry": {"coordinates":[-94.68375399999999,31.627267],"type":"Point"}
}