{
  "type": "Feature",
  "properties": {
    "iso:country":"US",
    "sg:address":"6810 Krause Dr",
    "sg:city":"Missouri City",
    "sg:classifiers":[
        {
            "category":"Building & Trades",
            "subcategory":"Landscaping Services",
            "type":"Services"
        }
    ],
    "sg:phone":"+1 281 438 8082",
    "sg:postcode":"77489",
    "sg:province":"TX",
    "wof:name":"AJS Landscaping & Lawncare",
    "wof:placetype":"venue"
},
  "geometry": {"coordinates":[-95.486226,29.59478],"type":"Point"}
}