{
  "type": "Feature",
  "properties": {
    "iso:country":"US",
    "sg:address":"735 N Westmoreland Rd",
    "sg:city":"Dallas",
    "sg:classifiers":[
        {
            "category":"Shopping",
            "subcategory":"Gifts & Souvenirs",
            "type":"Retail Goods"
        }
    ],
    "sg:phone":"+1 972 270 0974",
    "sg:postcode":"75211",
    "sg:province":"TX",
    "sg:tags":[
        "shop",
        "novelty"
    ],
    "wof:name":"Rocios Decorations",
    "wof:placetype":"venue"
},
  "geometry": {"coordinates":[-96.874106,32.750163],"type":"Point"}
}