{
  "type": "Feature",
  "properties": {
    "iso:country":"US",
    "sg:address":"2222 Ella Blvd",
    "sg:city":"Houston",
    "sg:classifiers":[
        {
            "category":"Restaurant",
            "type":"Food & Drink"
        }
    ],
    "sg:menulink":"http://www.allmenus.com/tx/houston/271085-della-carts-catering/menu/",
    "sg:phone":"+1 713 937 8039",
    "sg:postcode":"77008",
    "sg:province":"TX",
    "sg:tags":[
        "american"
    ],
    "wof:name":"Della Carts Catering",
    "wof:placetype":"venue"
},
  "geometry": {"coordinates":[-95.428862,29.806154],"type":"Point"}
}