{
  "type": "Feature",
  "properties": {
    "iso:country":"US",
    "sg:address":"1125 Baker St",
    "sg:city":"Fort Worth",
    "sg:classifiers":[
        {
            "category":"Organizations",
            "subcategory":"Religious Organization",
            "type":"Services"
        }
    ],
    "sg:phone":"+1 817 921 5351",
    "sg:postcode":"76104",
    "sg:province":"TX",
    "wof:name":"City Of Refuge Church",
    "wof:placetype":"venue"
},
  "geometry": {"coordinates":[-97.31430899999999,32.708757],"type":"Point"}
}