{
  "type": "Feature",
  "properties": {
    "iso:country":"US",
    "sg:address":"300 Monroe St",
    "sg:city":"Kountze",
    "sg:classifiers":[
        {
            "category":"Professional",
            "subcategory":"Lawyer & Legal Services",
            "type":"Services"
        }
    ],
    "sg:phone":"+1 409 246 3818",
    "sg:postcode":"77625",
    "sg:province":"TX",
    "sg:tags":[
        "plan"
    ],
    "wof:name":"Britton E Plunk",
    "wof:placetype":"venue"
},
  "geometry": {"coordinates":[-94.317429,30.368408],"type":"Point"}
}