{
  "type": "Feature",
  "properties": {
    "iso:country":"US",
    "sg:address":"17421 Jackson Pines Dr",
    "sg:city":"Houston",
    "sg:classifiers":[
        {
            "category":"Professional",
            "type":"Services"
        }
    ],
    "sg:phone":"+1 281 440 1681",
    "sg:postcode":"77090",
    "sg:province":"TX",
    "wof:name":"Bruce Cockrell Tr",
    "wof:placetype":"venue"
},
  "geometry": {"coordinates":[-95.46789099999999,30.01462],"type":"Point"}
}