{
  "type": "Feature",
  "properties": {
    "iso:country":"US",
    "sg:address":"907 N 4th St",
    "sg:city":"Longview",
    "sg:classifiers":[
        {
            "category":"Professional",
            "type":"Services"
        }
    ],
    "sg:phone":"+1 903 758 3374",
    "sg:postcode":"75601",
    "sg:province":"TX",
    "sg:tags":[
        "establishment"
    ],
    "wof:name":"Kitchen Business",
    "wof:placetype":"venue"
},
  "geometry": {"coordinates":[-94.731134,32.506827],"type":"Point"}
}