{
  "type": "Feature",
  "properties": {
    "iso:country":"US",
    "sg:address":"3200 Southwest Fwy",
    "sg:city":"Houston",
    "sg:classifiers":[
        {
            "category":"Professional",
            "type":"Services"
        }
    ],
    "sg:phone":"+1 713 357 2800",
    "sg:postcode":"77027",
    "sg:province":"TX",
    "sg:tags":[
        "retail",
        "provider"
    ],
    "wof:name":"Startex Power",
    "wof:placetype":"venue"
},
  "geometry": {"coordinates":[-95.428192,29.730271],"type":"Point"}
}