{
  "type": "Feature",
  "properties": {
    "iso:country":"US",
    "sg:address":"1719 N Arkansas Ave",
    "sg:city":"Laredo",
    "sg:classifiers":[
        {
            "category":"Wholesale",
            "subcategory":"Scrap",
            "type":"Manufacturing & Wholesale Goods"
        }
    ],
    "sg:phone":"+1 956 727 1404",
    "sg:postcode":"78040",
    "sg:province":"TX",
    "sg:tags":[
        "rag"
    ],
    "wof:name":"Best Way Rags & Wipers",
    "wof:placetype":"venue"
},
  "geometry": {"coordinates":[-99.468006,27.512971],"type":"Point"}
}