{
  "type": "Feature",
  "properties": {
    "iso:country":"US",
    "sg:address":"7111 Phillips St",
    "sg:city":"Houston",
    "sg:classifiers":[
        {
            "category":"Building & Trades",
            "subcategory":"Plumbing",
            "type":"Services"
        }
    ],
    "sg:phone":"+1 281 447 2753",
    "sg:postcode":"77088",
    "sg:province":"TX",
    "sg:tags":[
        "contractor"
    ],
    "wof:name":"Climate Clothing Co",
    "wof:placetype":"venue"
},
  "geometry": {"coordinates":[-95.437973,29.866271],"type":"Point"}
}