{
  "type": "Feature",
  "properties": {
    "iso:country":"US",
    "sg:address":"100 FM 462",
    "sg:city":"Moore",
    "sg:classifiers":[
        {
            "category":"Food & Beverages",
            "subcategory":"Groceries & Convenience Stores",
            "type":"Retail Goods"
        }
    ],
    "sg:phone":"+1 830 665 6323",
    "sg:postcode":"78061",
    "sg:province":"TX",
    "sg:tags":[
        "grill"
    ],
    "wof:name":"Southwest Convenient Str Grill",
    "wof:placetype":"venue"
},
  "geometry": {"coordinates":[-99.003444,29.059817],"type":"Point"}
}