{
  "type": "Feature",
  "properties": {
    "iso:country":"US",
    "sg:address":"8950 N Central Expy",
    "sg:city":"Dallas",
    "sg:classifiers":[
        {
            "category":"Professional",
            "subcategory":"Computer Services",
            "type":"Services"
        }
    ],
    "sg:phone":"+1 214 369 4774",
    "sg:postcode":"75231",
    "sg:province":"TX",
    "sg:tags":[
        "internet"
    ],
    "wof:name":"Happy Computer",
    "wof:placetype":"venue"
},
  "geometry": {"coordinates":[-96.76973,32.871682],"type":"Point"}
}