{
  "type": "Feature",
  "properties": {
    "iso:country":"US",
    "sg:address":"5435 Merrimac Ave",
    "sg:city":"Dallas",
    "sg:classifiers":[
        {
            "category":"Professional",
            "subcategory":"Advertising",
            "type":"Services"
        }
    ],
    "sg:phone":"+1 214 824 2605",
    "sg:postcode":"75206",
    "sg:province":"TX",
    "sg:tags":[
        "agency"
    ],
    "wof:name":"Slate Blank Advertising",
    "wof:placetype":"venue"
},
  "geometry": {"coordinates":[-96.77549,32.827432],"type":"Point"}
}