{
  "type": "Feature",
  "properties": {
    "iso:country":"US",
    "sg:address":"100 E Hubbard St",
    "sg:city":"Lindale",
    "sg:classifiers":[
        {
            "category":"Shopping",
            "subcategory":"Used Merchandise",
            "type":"Retail Goods"
        }
    ],
    "sg:phone":"+1 903 882 1127",
    "sg:postcode":"75771",
    "sg:province":"TX",
    "sg:tags":[
        "antique"
    ],
    "wof:name":"Made In The Shade",
    "wof:placetype":"venue"
},
  "geometry": {"coordinates":[-95.408238,32.515887],"type":"Point"}
}