{
  "type": "Feature",
  "properties": {
    "iso:country":"US",
    "sg:address":"1000 E Bowman Rd",
    "sg:city":"Round Rock",
    "sg:classifiers":[
        {
            "category":"Social Services",
            "subcategory":"Child Care",
            "type":"Services"
        }
    ],
    "sg:phone":"+1 512 244 0390",
    "sg:postcode":"78664",
    "sg:province":"TX",
    "sg:tags":[
        "day"
    ],
    "wof:name":"Nanny & Papas Center",
    "wof:placetype":"venue"
},
  "geometry": {"coordinates":[-97.66959799999999,30.529822],"type":"Point"}
}