{
  "type": "Feature",
  "properties": {
    "iso:country":"US",
    "sg:address":"14501 Westheimer Rd",
    "sg:city":"Houston",
    "sg:classifiers":[
        {
            "category":"Restaurant",
            "type":"Food & Drink"
        }
    ],
    "sg:menulink":"http://www.allmenus.com/tx/houston/217923-burger-king/menu/",
    "sg:phone":"+1 281 558 3304",
    "sg:postcode":"77077",
    "sg:province":"TX",
    "sg:tags":[
        "american"
    ],
    "wof:name":"Burger King",
    "wof:placetype":"venue"
},
  "geometry": {"coordinates":[-95.64265399999999,29.735018],"type":"Point"}
}