{
  "type": "Feature",
  "properties": {
    "iso:country":"US",
    "sg:address":"2103 Ernestine St",
    "sg:city":"Houston",
    "sg:classifiers":[
        {
            "category":"Freight",
            "type":"Transportation"
        }
    ],
    "sg:phone":"+1 713 924 3483",
    "sg:postcode":"77023",
    "sg:province":"TX",
    "sg:tags":[
        "operator",
        "local",
        "trucking"
    ],
    "wof:name":"Exel Direct Inc",
    "wof:placetype":"venue"
},
  "geometry": {"coordinates":[-95.33657599999999,29.72863],"type":"Point"}
}