{
  "type": "Feature",
  "properties": {
    "iso:country":"US",
    "sg:address":"24426 Saddlebrook Cir",
    "sg:city":"Katy",
    "sg:classifiers":[
        {
            "category":"Building & Trades",
            "subcategory":"Electrical",
            "type":"Services"
        }
    ],
    "sg:phone":"+1 281 693 7032",
    "sg:postcode":"77494",
    "sg:province":"TX",
    "sg:tags":[
        "electric",
        "contractor"
    ],
    "wof:name":"Paul Brandt",
    "wof:placetype":"venue"
},
  "geometry": {"coordinates":[-95.785292,29.755936],"type":"Point"}
}