{
  "type": "Feature",
  "properties": {
    "iso:country":"US",
    "sg:address":"2707 Pinewood Ter",
    "sg:city":"Austin",
    "sg:classifiers":[
        {
            "category":"Professional",
            "subcategory":"Computer Services",
            "type":"Services"
        }
    ],
    "sg:phone":"+1 512 458 9675",
    "sg:postcode":"78757",
    "sg:province":"TX",
    "sg:tags":[
        "programing",
        "custom"
    ],
    "wof:name":"Rockhowardcom",
    "wof:placetype":"venue"
},
  "geometry": {"coordinates":[-97.737832,30.350134],"type":"Point"}
}