{
  "type": "Feature",
  "properties": {
    "iso:country":"US",
    "sg:address":"5118 Denton Dr",
    "sg:city":"Dallas",
    "sg:classifiers":[
        {
            "category":"Shopping",
            "subcategory":"Computers & Home Electronics",
            "type":"Retail Goods"
        }
    ],
    "sg:phone":"+1 214 337 8279",
    "sg:postcode":"75235",
    "sg:province":"TX",
    "sg:tags":[
        "repair",
        "antenna"
    ],
    "wof:name":"Satellite City Inc",
    "wof:placetype":"venue"
},
  "geometry": {"coordinates":[-96.827426,32.818044],"type":"Point"}
}