{
  "type": "Feature",
  "properties": {
    "iso:country":"US",
    "sg:address":"4421 Titanic Ave",
    "sg:city":"El Paso",
    "sg:classifiers":[
        {
            "category":"Building & Trades",
            "subcategory":"Cleaning & Sanitation",
            "type":"Services"
        }
    ],
    "sg:phone":"+1 915 751 3780",
    "sg:postcode":"79904",
    "sg:province":"TX",
    "sg:tags":[
        "janitor"
    ],
    "sg:website":"www.maintenanceunlimited.com",
    "wof:name":"Maintenance Unlimited",
    "wof:placetype":"venue"
},
  "geometry": {"coordinates":[-106.43367000000001,31.853512],"type":"Point"}
}