{
  "type": "Feature",
  "properties": {
    "iso:country":"US",
    "sg:address":"1 E Sauz St",
    "sg:city":"Rio Grande City",
    "sg:classifiers":[
        {
            "category":"Freight",
            "type":"Transportation"
        }
    ],
    "sg:phone":"+1 956 487 7424",
    "sg:postcode":"78582",
    "sg:province":"TX",
    "sg:tags":[
        "warehouse",
        "public"
    ],
    "wof:name":"ECTSA Intl",
    "wof:placetype":"venue"
},
  "geometry": {"coordinates":[-98.77836600000001,26.359873],"type":"Point"}
}