{
  "type": "Feature",
  "properties": {
    "iso:country":"US",
    "sg:address":"200 S Kansas St",
    "sg:city":"El Paso",
    "sg:classifiers":[
        {
            "category":"Government",
            "subcategory":"Office",
            "type":"Public Place"
        }
    ],
    "sg:phone":"+1 915 546 8102",
    "sg:postcode":"79901",
    "sg:province":"TX",
    "wof:name":"El Paso County Jury Summons",
    "wof:placetype":"venue"
},
  "geometry": {"coordinates":[-106.484313,31.756974],"type":"Point"}
}