{
  "type": "Feature",
  "properties": {
    "iso:country":"US",
    "sg:address":"10823 Kirkwell Dr",
    "sg:city":"Houston",
    "sg:classifiers":[
        {
            "category":"Shopping",
            "type":"Retail Goods"
        }
    ],
    "sg:phone":"+1 281 481 8639",
    "sg:postcode":"77089",
    "sg:province":"TX",
    "sg:tags":[
        "equipment",
        "purifying",
        "cleaning",
        "merchandise",
        "air"
    ],
    "wof:name":"Richard A Reed",
    "wof:placetype":"venue"
},
  "geometry": {"coordinates":[-95.23020699999999,29.596695],"type":"Point"}
}