{
  "type": "Feature",
  "properties": {
    "iso:country":"US",
    "sg:address":"2438 W Anderson Ln",
    "sg:city":"Austin",
    "sg:classifiers":[
        {
            "category":"Home & Garden",
            "subcategory":"Furniture",
            "type":"Retail Goods"
        }
    ],
    "sg:phone":"+1 512 452 0559",
    "sg:postcode":"78757",
    "sg:province":"TX",
    "wof:name":"Brown Stores & Svc Corp",
    "wof:placetype":"venue"
},
  "geometry": {"coordinates":[-97.734702,30.358016],"type":"Point"}
}