{
  "type": "Feature",
  "properties": {
    "iso:country":"US",
    "sg:address":"5522 Beaver Lodge Dr",
    "sg:city":"Humble",
    "sg:classifiers":[
        {
            "category":"Professional",
            "type":"Services"
        }
    ],
    "sg:phone":"+1 281 361 6365",
    "sg:postcode":"77345",
    "sg:province":"TX",
    "wof:name":"Branton Estate LLC",
    "wof:placetype":"venue"
},
  "geometry": {"coordinates":[-95.16068,30.049923],"type":"Point"}
}