{
  "type": "Feature",
  "properties": {
    "iso:country":"US",
    "sg:address":"11394 James Watt Dr",
    "sg:city":"El Paso",
    "sg:classifiers":[
        {
            "category":"Professional",
            "type":"Services"
        }
    ],
    "sg:phone":"+1 915 590 7545",
    "sg:postcode":"79936",
    "sg:province":"TX",
    "sg:tags":[
        "establishment"
    ],
    "wof:name":"MBH Precision",
    "wof:placetype":"venue"
},
  "geometry": {"coordinates":[-106.320087,31.74472],"type":"Point"}
}