{
  "type": "Feature",
  "properties": {
    "iso:country":"US",
    "sg:address":"10330 Strait Ln",
    "sg:city":"Dallas",
    "sg:classifiers":[
        {
            "category":"Real Estate",
            "subcategory":"Developer",
            "type":"Services"
        }
    ],
    "sg:phone":"+1 214 369 3763",
    "sg:postcode":"75229",
    "sg:province":"TX",
    "wof:name":"Corona Construction Company",
    "wof:placetype":"venue"
},
  "geometry": {"coordinates":[-96.824699,32.88471],"type":"Point"}
}