{
  "type": "Feature",
  "properties": {
    "iso:country":"US",
    "sg:address":"814 Highland Village Rd",
    "sg:city":"Lewisville",
    "sg:classifiers":[
        {
            "category":"Personal",
            "type":"Services"
        }
    ],
    "sg:phone":"+1 972 317 9133",
    "sg:postcode":"75077",
    "sg:province":"TX",
    "sg:tags":[
        "miscellaneous"
    ],
    "wof:name":"J & J Casinos",
    "wof:placetype":"venue"
},
  "geometry": {"coordinates":[-97.046741,33.093627],"type":"Point"}
}