{
  "type": "Feature",
  "properties": {
    "iso:country":"US",
    "sg:address":"1004 E Hebron Pkwy",
    "sg:city":"Carrollton",
    "sg:classifiers":[
        {
            "category":"Ice Cream",
            "type":"Food & Drink"
        }
    ],
    "sg:phone":"+1 214 731 8250",
    "sg:postcode":"75010",
    "sg:province":"TX",
    "sg:tags":[
        "frozen",
        "yogurt"
    ],
    "sg:website":"www.shakesfrozencustard.com/",
    "wof:name":"Shake's Frozen Custard",
    "wof:placetype":"venue"
},
  "geometry": {"coordinates":[-96.91502199999999,33.020822],"type":"Point"}
}