{
  "type": "Feature",
  "properties": {
    "iso:country":"US",
    "sg:address":"11500 N Stemmons Fwy Ste 172",
    "sg:city":"Dallas",
    "sg:classifiers":[
        {
            "category":"Personal",
            "type":"Services"
        }
    ],
    "sg:phone":"+1 972 484 6035",
    "sg:postcode":"75229",
    "sg:province":"TX",
    "sg:tags":[
        "mover"
    ],
    "sg:website":"www.progressivemoving.com",
    "wof:name":"Progressive Moving Company",
    "wof:placetype":"venue"
},
  "geometry": {"coordinates":[-96.896761,32.90426],"type":"Point"}
}