{
  "type": "Feature",
  "properties": {
    "iso:country":"US",
    "sg:address":"1351 SW Wilshire Blvd Suite 102",
    "sg:city":"Burleson",
    "sg:classifiers":[
        {
            "category":"Banks & Credit Unions",
            "subcategory":"Investment Brokerage",
            "type":"Services"
        },
        {
            "category":"Banks & Credit Unions",
            "subcategory":"Bank",
            "type":"Services"
        },
        {
            "category":"Banks & Credit Unions",
            "subcategory":"Financial Services",
            "type":"Services"
        }
    ],
    "sg:phone":"+1 888 657 3865",
    "sg:postcode":"76028",
    "sg:province":"TX",
    "sg:tags":[
        "advisory",
        "mutual",
        "retirement",
        "annuity",
        "broker",
        "fund",
        "planning",
        "plan",
        "consultant",
        "security",
        "bond",
        "insurance",
        "stock"
    ],
    "sg:website":"http://fortworth.citysearch.com/profile/external/611963930/burleson_tx/edward_jones_tris_r_fitzgibbon.html?publisher=yellowpages&reference_id=1&placement=ypwebsitemip",
    "wof:name":"Edward Jones - TRIS R FITZGIBBON",
    "wof:placetype":"venue"
},
  "geometry": {"coordinates":[-97.340763,32.528774],"type":"Point"}
}