{
  "type": "Feature",
  "properties": {
    "iso:country":"US",
    "sg:address":"1418 Beech Ave",
    "sg:city":"Mcallen",
    "sg:classifiers":[
        {
            "category":"Professional",
            "subcategory":"Lawyer & Legal Services",
            "type":"Services"
        }
    ],
    "sg:phone":"+1 956 687 2920",
    "sg:postcode":"78501",
    "sg:province":"TX",
    "wof:name":"Richard O Habermann Attorney",
    "wof:placetype":"venue"
},
  "geometry": {"coordinates":[-98.23500900000001,26.205744],"type":"Point"}
}