{
  "type": "Feature",
  "properties": {
    "iso:country":"US",
    "sg:address":"107 Paleface Point Dr",
    "sg:city":"Spicewood",
    "sg:classifiers":[
        {
            "category":"Professional",
            "subcategory":"Management & Consulting",
            "type":"Services"
        }
    ],
    "sg:phone":"+1 512 264 0848",
    "sg:postcode":"78669",
    "sg:province":"TX",
    "sg:tags":[
        "business"
    ],
    "wof:name":"Patterson Consulting",
    "wof:placetype":"venue"
},
  "geometry": {"coordinates":[-98.09482800000001,30.432674],"type":"Point"}
}