{
  "type": "Feature",
  "properties": {
    "iso:country":"US",
    "sg:address":"630 Broadway St",
    "sg:city":"Plainview",
    "sg:classifiers":[
        {
            "category":"Retail",
            "subcategory":"Auto Repair",
            "type":"Services"
        }
    ],
    "sg:phone":"+1 806 293 8933",
    "sg:postcode":"79072",
    "sg:province":"TX",
    "sg:tags":[
        "body",
        "automobile",
        "painting"
    ],
    "wof:name":"Body Shop",
    "wof:placetype":"venue"
},
  "geometry": {"coordinates":[-101.702957,34.186587],"type":"Point"}
}