{
  "type": "Feature",
  "properties": {
    "iso:country":"US",
    "sg:address":"11621 N D St",
    "sg:city":"La Porte",
    "sg:classifiers":[
        {
            "category":"Travel",
            "subcategory":"Campground",
            "type":"Entertainment"
        }
    ],
    "sg:phone":"+1 281 471 3598",
    "sg:postcode":"77571",
    "sg:province":"TX",
    "sg:tags":[
        "camp"
    ],
    "wof:name":"Spec Some Action Adventure",
    "wof:placetype":"venue"
},
  "geometry": {"coordinates":[-95.053546,29.669984],"type":"Point"}
}