{
  "type": "Feature",
  "properties": {
    "iso:country":"US",
    "sg:address":"Deep Tissue Spa 816 W 12th St",
    "sg:city":"Austin",
    "sg:classifiers":[
        {
            "category":"Personal",
            "subcategory":"Massage",
            "type":"Services"
        }
    ],
    "sg:phone":"+1 512 658 8448",
    "sg:postcode":"78701",
    "sg:province":"TX",
    "wof:name":"Julie K. O'Leary, LMT",
    "wof:placetype":"venue"
},
  "geometry": {"coordinates":[-97.748439,30.276128],"type":"Point"}
}