{
  "type": "Feature",
  "properties": {
    "iso:country":"US",
    "sg:address":"7402 Burkridge Dr",
    "sg:city":"Houston",
    "sg:classifiers":[
        {
            "category":"Wholesale",
            "subcategory":"Vending Machines",
            "type":"Manufacturing & Wholesale Goods"
        }
    ],
    "sg:phone":"+1 713 849 5700",
    "sg:postcode":"77041",
    "sg:province":"TX",
    "sg:tags":[
        "operated",
        "phonograph"
    ],
    "wof:name":"ABC Music Co",
    "wof:placetype":"venue"
},
  "geometry": {"coordinates":[-95.608591,29.885166],"type":"Point"}
}