{
  "type": "Feature",
  "properties": {
    "iso:country":"US",
    "sg:address":"3402 Hazel St",
    "sg:city":"Texarkana",
    "sg:classifiers":[
        {
            "category":"Professional",
            "type":"Services"
        }
    ],
    "sg:phone":"+1 903 792 5105",
    "sg:postcode":"75503",
    "sg:province":"TX",
    "sg:tags":[
        "establishment"
    ],
    "wof:name":"Res",
    "wof:placetype":"venue"
},
  "geometry": {"coordinates":[-94.045404,33.45035],"type":"Point"}
}