{
  "type": "Feature",
  "properties": {
    "iso:country":"US",
    "sg:address":"1327 W Pipeline Rd",
    "sg:city":"Hurst",
    "sg:classifiers":[
        {
            "category":"Shopping",
            "subcategory":"Music",
            "type":"Retail Goods"
        },
        {
            "category":"Cinema",
            "subcategory":"Movie Rental",
            "type":"Entertainment"
        }
    ],
    "sg:phone":"+1 817 595 4065",
    "sg:postcode":"76053",
    "sg:province":"TX",
    "sg:tags":[
        "leasing",
        "previously",
        "disc",
        "tape",
        "video",
        "viewed"
    ],
    "wof:name":"Movie Trading Company",
    "wof:placetype":"venue"
},
  "geometry": {"coordinates":[-97.202533,32.82359],"type":"Point"}
}