{
  "type": "Feature",
  "properties": {
    "iso:country":"US",
    "sg:address":"2542 Garden Rd",
    "sg:city":"Pearland",
    "sg:classifiers":[
        {
            "category":"Professional",
            "type":"Services"
        }
    ],
    "sg:phone":"+1 281 412 4264",
    "sg:postcode":"77581",
    "sg:province":"TX",
    "wof:name":"A&J Sweeper Service",
    "wof:placetype":"venue"
},
  "geometry": {"coordinates":[-95.32103600000001,29.574715],"type":"Point"}
}