{
  "type": "Feature",
  "properties": {
    "iso:country":"US",
    "sg:address":"6105 Coffee Port Rd",
    "sg:city":"Brownsville",
    "sg:classifiers":[
        {
            "category":"Restaurant",
            "type":"Food & Drink"
        }
    ],
    "sg:phone":"+1 956 831 2508",
    "sg:postcode":"78521",
    "sg:province":"TX",
    "wof:name":"Whataburger",
    "wof:placetype":"venue"
},
  "geometry": {"coordinates":[-97.43568999999999,25.93883],"type":"Point"}
}