{
  "type": "Feature",
  "properties": {
    "iso:country":"US",
    "sg:address":"44 Blue Heron Dr",
    "sg:city":"Rockport",
    "sg:classifiers":[
        {
            "category":"Professional",
            "type":"Services"
        }
    ],
    "sg:phone":"+1 361 729 0215",
    "sg:postcode":"78382",
    "sg:province":"TX",
    "wof:name":"Five Grand Corp",
    "wof:placetype":"venue"
},
  "geometry": {"coordinates":[-97.030175,28.033339],"type":"Point"}
}