{
  "type": "Feature",
  "properties": {
    "iso:country":"US",
    "sg:address":"903 N Loop 336 W Ste C",
    "sg:city":"Conroe",
    "sg:classifiers":[
        {
            "category":"Personal",
            "subcategory":"Massage",
            "type":"Services"
        },
        {
            "category":"Health Services",
            "subcategory":"Clinic",
            "type":"Services"
        },
        {
            "category":"Health Services",
            "subcategory":"Health Practitioner",
            "type":"Services"
        },
        {
            "category":"Health Services",
            "subcategory":"Chiropractor",
            "type":"Services"
        }
    ],
    "sg:phone":"+1 936 788 6565",
    "sg:postcode":"77301",
    "sg:province":"TX",
    "sg:tags":[
        "chiropractic",
        "acupuncture",
        "therapist",
        "therapy",
        "medicine",
        "alternative",
        "physical"
    ],
    "wof:name":"Miller Chiropractic Center",
    "wof:placetype":"venue"
},
  "geometry": {"coordinates":[-95.46888,30.335733],"type":"Point"}
}