{
  "type": "Feature",
  "properties": {
    "iso:country":"US",
    "sg:address":"4806 91st St",
    "sg:city":"Lubbock",
    "sg:classifiers":[
        {
            "category":"Real Estate",
            "subcategory":"Real Estate Operator",
            "type":"Services"
        }
    ],
    "sg:phone":"+1 806 798 0211",
    "sg:postcode":"79424",
    "sg:province":"TX",
    "sg:tags":[
        "apartment"
    ],
    "wof:name":"Lubbock South Plains Apartments, Ltd",
    "wof:placetype":"venue"
},
  "geometry": {"coordinates":[-101.914062,33.511041],"type":"Point"}
}