{
  "type": "Feature",
  "properties": {
    "iso:country":"US",
    "sg:address":"1220 Richelieu Ln",
    "sg:city":"Houston",
    "sg:classifiers":[
        {
            "category":"Building & Trades",
            "subcategory":"Construction",
            "type":"Services"
        }
    ],
    "sg:phone":"+1 713 688 2501",
    "sg:postcode":"77018",
    "sg:province":"TX",
    "sg:tags":[
        "contractor"
    ],
    "wof:name":"Tabco Wtrprfing Rstoration Inc",
    "wof:placetype":"venue"
},
  "geometry": {"coordinates":[-95.435011,29.835248],"type":"Point"}
}