{
  "type": "Feature",
  "properties": {
    "iso:country":"US",
    "sg:address":"1507 Saddlecreek Dr",
    "sg:city":"Houston",
    "sg:classifiers":[
        {
            "category":"Professional",
            "subcategory":"Business Services",
            "type":"Services"
        }
    ],
    "sg:phone":"+1 281 444 1223",
    "sg:postcode":"77090",
    "sg:province":"TX",
    "wof:name":"Ann Epperson Interiors",
    "wof:placetype":"venue"
},
  "geometry": {"coordinates":[-95.456039,30.019197],"type":"Point"}
}