{
  "type": "Feature",
  "properties": {
    "iso:country":"US",
    "sg:address":"9502 Meadowheath Dr",
    "sg:city":"Austin",
    "sg:classifiers":[
        {
            "category":"Retail",
            "subcategory":"Repair Shop",
            "type":"Services"
        }
    ],
    "sg:phone":"+1 512 219 6650",
    "sg:postcode":"78729",
    "sg:province":"TX",
    "sg:tags":[
        "radio",
        "lab"
    ],
    "wof:name":"Austin Radio Labs",
    "wof:placetype":"venue"
},
  "geometry": {"coordinates":[-97.781414,30.461236],"type":"Point"}
}