{
  "type": "Feature",
  "properties": {
    "iso:country":"US",
    "sg:address":"2400 Dallas Pkwy",
    "sg:city":"Plano",
    "sg:classifiers":[
        {
            "category":"Professional",
            "subcategory":"Computer Services",
            "type":"Services"
        }
    ],
    "sg:phone":"+1 972 801 4200",
    "sg:postcode":"75093",
    "sg:province":"TX",
    "sg:tags":[
        "consulting",
        "management",
        "related"
    ],
    "wof:name":"Fuego Inc",
    "wof:placetype":"venue"
},
  "geometry": {"coordinates":[-96.82869599999999,33.031384],"type":"Point"}
}