{
  "type": "Feature",
  "properties": {
    "iso:country":"US",
    "sg:address":"1209 Eastman St",
    "sg:city":"Pasadena",
    "sg:classifiers":[
        {
            "category":"Building & Trades",
            "subcategory":"Construction",
            "type":"Services"
        }
    ],
    "sg:phone":"+1 713 472 4441",
    "sg:postcode":"77506",
    "sg:province":"TX",
    "sg:tags":[
        "house"
    ],
    "wof:name":"Ganz Construction",
    "wof:placetype":"venue"
},
  "geometry": {"coordinates":[-95.214641,29.690929],"type":"Point"}
}