{
  "type": "Feature",
  "properties": {
    "iso:country":"US",
    "sg:address":"507 W Orange St",
    "sg:city":"Angleton",
    "sg:classifiers":[
        {
            "category":"Retail",
            "subcategory":"Funeral Services",
            "type":"Services"
        }
    ],
    "sg:phone":"+1 979 849 6379",
    "sg:postcode":"77515",
    "sg:province":"TX",
    "sg:tags":[
        "director"
    ],
    "wof:name":"Gardner's Funeral Home",
    "wof:placetype":"venue"
},
  "geometry": {"coordinates":[-95.436983,29.162915],"type":"Point"}
}