{
  "type": "Feature",
  "properties": {
    "iso:country":"US",
    "sg:address":"11845 E Northwest Hwy",
    "sg:city":"Dallas",
    "sg:classifiers":[
        {
            "category":"Restaurant",
            "type":"Food & Drink"
        }
    ],
    "sg:phone":"+1 214 341 2288",
    "sg:postcode":"75218",
    "sg:province":"TX",
    "sg:website":"www.goldencorral.net",
    "wof:name":"Golden Corral Buffet & Grill",
    "wof:placetype":"venue"
},
  "geometry": {"coordinates":[-96.677357,32.864145],"type":"Point"}
}