{
  "type": "Feature",
  "properties": {
    "iso:country":"US",
    "sg:address":"550 Brooklyn Ave",
    "sg:city":"San Antonio",
    "sg:classifiers":[
        {
            "category":"Real Estate",
            "subcategory":"Real Estate Operator",
            "type":"Services"
        }
    ],
    "sg:phone":"+1 210 226 2247",
    "sg:postcode":"78215",
    "sg:province":"TX",
    "sg:tags":[
        "apartment"
    ],
    "wof:name":"Rex Apartments",
    "wof:placetype":"venue"
},
  "geometry": {"coordinates":[-98.48526,29.433592],"type":"Point"}
}