{
  "type": "Feature",
  "properties": {
    "iso:country":"US",
    "sg:address":"11451 FM 775",
    "sg:city":"La Vernia",
    "sg:classifiers":[
        {
            "category":"Personal",
            "type":"Services"
        }
    ],
    "sg:phone":"+1 830 914 4354",
    "sg:postcode":"78121",
    "sg:province":"TX",
    "wof:name":"Tanning Barn",
    "wof:placetype":"venue"
},
  "geometry": {"coordinates":[-98.109274,29.431703],"type":"Point"}
}