{
  "type": "Feature",
  "properties": {
    "iso:country":"US",
    "sg:address":"5656 Weber Rd",
    "sg:city":"Corpus Christi",
    "sg:classifiers":[
        {
            "category":"Insurance",
            "subcategory":"Insurance Agent",
            "type":"Services"
        }
    ],
    "sg:phone":"+1 361 993 5959",
    "sg:postcode":"78411",
    "sg:province":"TX",
    "wof:name":"Fred Loya Insurance",
    "wof:placetype":"venue"
},
  "geometry": {"coordinates":[-97.40419199999999,27.712581],"type":"Point"}
}