{
  "type": "Feature",
  "properties": {
    "iso:country":"US",
    "sg:address":"1005 W Ralph Hall Pkwy 211",
    "sg:city":"Rockwall",
    "sg:classifiers":[
        {
            "category":"Health Services",
            "subcategory":"Doctor",
            "type":"Services"
        }
    ],
    "sg:phone":"+1 972 771 3322",
    "sg:postcode":"75032",
    "sg:province":"TX",
    "sg:tags":[
        "physician",
        "oncology",
        "surgeons",
        "surgeon",
        "gynecologic"
    ],
    "wof:name":"Us Oncology Holdings, Inc.",
    "wof:placetype":"venue"
},
  "geometry": {"coordinates":[-96.470741,32.886252],"type":"Point"}
}