{
  "type": "Feature",
  "properties": {
    "iso:country":"US",
    "sg:address":"807 Lodge Ln",
    "sg:city":"Richmond",
    "sg:classifiers":[
        {
            "category":"Real Estate",
            "subcategory":"Real Estate Services",
            "type":"Services"
        },
        {
            "category":"Real Estate",
            "subcategory":"Real Estate Agent",
            "type":"Services"
        }
    ],
    "sg:phone":"+1 281 342 6361",
    "sg:postcode":"77406",
    "sg:province":"TX",
    "sg:tags":[
        "buyer",
        "broker"
    ],
    "wof:name":"Stanton Realty",
    "wof:placetype":"venue"
},
  "geometry": {"coordinates":[-95.72541099999999,29.607056],"type":"Point"}
}