{
  "type": "Feature",
  "properties": {
    "iso:country":"US",
    "sg:address":"1101 W Ball St",
    "sg:city":"Weatherford",
    "sg:classifiers":[
        {
            "category":"Organizations",
            "subcategory":"Religious Organization",
            "type":"Services"
        }
    ],
    "sg:phone":"+1 817 599 0406",
    "sg:postcode":"76086",
    "sg:province":"TX",
    "wof:name":"Community Baptist Church",
    "wof:placetype":"venue"
},
  "geometry": {"coordinates":[-97.813182,32.764319],"type":"Point"}
}