{
  "type": "Feature",
  "properties": {
    "iso:country":"US",
    "sg:address":"4730 Widerop Ln",
    "sg:city":"Friendswood",
    "sg:classifiers":[
        {
            "category":"Professional",
            "subcategory":"Art Services",
            "type":"Services"
        }
    ],
    "sg:phone":"+1 281 235 3790",
    "sg:postcode":"77546",
    "sg:province":"TX",
    "sg:tags":[
        "designer",
        "display",
        "producer"
    ],
    "wof:name":"Open Door Concepts",
    "wof:placetype":"venue"
},
  "geometry": {"coordinates":[-95.176683,29.540057],"type":"Point"}
}