{
  "type": "Feature",
  "properties": {
    "iso:country":"US",
    "sg:address":"215 Rock Prairie Rd",
    "sg:city":"College Station",
    "sg:classifiers":[
        {
            "category":"Building & Trades",
            "subcategory":"Construction",
            "type":"Services"
        }
    ],
    "sg:phone":"+1 979 776 0007",
    "sg:postcode":"77845",
    "sg:province":"TX",
    "sg:tags":[
        "home",
        "builder"
    ],
    "wof:name":"David Price Homebuilders Inc",
    "wof:placetype":"venue"
},
  "geometry": {"coordinates":[-96.30833800000001,30.573209],"type":"Point"}
}