{
  "type": "Feature",
  "properties": {
    "iso:country":"US",
    "sg:address":"6908 Cameron Rd",
    "sg:city":"Austin",
    "sg:classifiers":[
        {
            "category":"Autos & Motor Vehicles",
            "subcategory":"Auto Supplies",
            "type":"Retail Goods"
        }
    ],
    "sg:phone":"+1 512 451 5559",
    "sg:postcode":"78752",
    "sg:province":"TX",
    "wof:name":"Frontier Tire & Service",
    "wof:placetype":"venue"
},
  "geometry": {"coordinates":[-97.693164,30.324868],"type":"Point"}
}