{
  "type": "Feature",
  "properties": {
    "iso:country":"US",
    "sg:address":"22125 Brierwood Dr",
    "sg:city":"Frankston",
    "sg:classifiers":[
        {
            "category":"Manufacturing",
            "subcategory":"Signs",
            "type":"Manufacturing & Wholesale Goods"
        }
    ],
    "sg:phone":"+1 903 876 2704",
    "sg:postcode":"75763",
    "sg:province":"TX",
    "wof:name":"Uncle Joe's Graphics",
    "wof:placetype":"venue"
},
  "geometry": {"coordinates":[-95.49217899999999,32.14692],"type":"Point"}
}