{
  "type": "Feature",
  "properties": {
    "iso:country":"US",
    "sg:address":"16315 Stuebner Airline Rd",
    "sg:city":"Spring",
    "sg:classifiers":[
        {
            "category":"Wholesale",
            "subcategory":"Auto Parts",
            "type":"Manufacturing & Wholesale Goods"
        }
    ],
    "sg:phone":"+1 281 370 9148",
    "sg:postcode":"77379",
    "sg:province":"TX",
    "sg:tags":[
        "used"
    ],
    "wof:name":"Gulf Coast Axles & Cv Joints",
    "wof:placetype":"venue"
},
  "geometry": {"coordinates":[-95.51924699999999,30.016618],"type":"Point"}
}