{
  "type": "Feature",
  "properties": {
    "iso:country":"US",
    "sg:address":"5614 Royalton St",
    "sg:city":"Houston",
    "sg:classifiers":[
        {
            "category":"Home & Garden",
            "subcategory":"Building Materials",
            "type":"Retail Goods"
        }
    ],
    "sg:phone":"+1 713 661 3641",
    "sg:postcode":"77081",
    "sg:province":"TX",
    "sg:tags":[
        "fixture",
        "display"
    ],
    "sg:website":"www.architecturaldesigncab.com",
    "wof:name":"Architectural Design Cab Works",
    "wof:placetype":"venue"
},
  "geometry": {"coordinates":[-95.472363,29.721057],"type":"Point"}
}