{
  "type": "Feature",
  "properties": {
    "iso:country":"US",
    "sg:address":"118 W Bowie St",
    "sg:city":"Luling",
    "sg:classifiers":[
        {
            "category":"Education",
            "subcategory":"School",
            "type":"Public Place"
        }
    ],
    "sg:phone":"+1 830 875 2223",
    "sg:postcode":"78648",
    "sg:province":"TX",
    "sg:website":"www.luling.txed.net",
    "wof:name":"Luling Primary School",
    "wof:placetype":"venue"
},
  "geometry": {"coordinates":[-97.65720899999999,29.679549],"type":"Point"}
}