{
  "type": "Feature",
  "properties": {
    "iso:country":"US",
    "sg:address":"6900 Alexandria Ct",
    "sg:city":"Fort Worth",
    "sg:classifiers":[
        {
            "category":"Building & Trades",
            "subcategory":"Landscaping Services",
            "type":"Services"
        }
    ],
    "sg:phone":"+1 817 263 9091",
    "sg:postcode":"76133",
    "sg:province":"TX",
    "wof:name":"Mow Better",
    "wof:placetype":"venue"
},
  "geometry": {"coordinates":[-97.37137199999999,32.642041],"type":"Point"}
}