{
  "type": "Feature",
  "properties": {
    "iso:country":"US",
    "sg:address":"1703 West Gray",
    "sg:city":"Houston",
    "sg:classifiers":[
        {
            "category":"Shopping",
            "subcategory":"Pets & Pet Supplies",
            "type":"Retail Goods"
        }
    ],
    "sg:phone":"+1 713 522 0100",
    "sg:postcode":"77019",
    "sg:province":"TX",
    "sg:tags":[
        "groomers"
    ],
    "sg:website":"www.chateaugrooming.com",
    "wof:name":"Chateau Grooming Parlor",
    "wof:placetype":"venue"
},
  "geometry": {"coordinates":[-95.40104700000001,29.75316],"type":"Point"}
}