{
  "type": "Feature",
  "properties": {
    "iso:country":"US",
    "sg:address":"8526 Oakwood Dr",
    "sg:city":"Magnolia",
    "sg:classifiers":[
        {
            "category":"Wholesale",
            "subcategory":"Toys & Hobbies",
            "type":"Manufacturing & Wholesale Goods"
        }
    ],
    "sg:phone":"+1 281 356 7750",
    "sg:postcode":"77354",
    "sg:province":"TX",
    "sg:tags":[
        "wholesaler"
    ],
    "wof:name":"Standard Fitting Intl",
    "wof:placetype":"venue"
},
  "geometry": {"coordinates":[-95.59282,30.153055],"type":"Point"}
}