{
  "type": "Feature",
  "properties": {
    "iso:country":"US",
    "sg:address":"5710 S General Bruce Dr",
    "sg:city":"Temple",
    "sg:classifiers":[
        {
            "category":"Retail",
            "subcategory":"Auto Repair",
            "type":"Services"
        }
    ],
    "sg:phone":"+1 254 773 6668",
    "sg:postcode":"76502",
    "sg:province":"TX",
    "sg:tags":[
        "body",
        "automobile",
        "painting"
    ],
    "wof:name":"B & G Collision Center",
    "wof:placetype":"venue"
},
  "geometry": {"coordinates":[-97.413561,31.079917],"type":"Point"}
}