{
  "type": "Feature",
  "properties": {
    "iso:country":"US",
    "sg:address":"1340 W Walnut Hill Ln",
    "sg:city":"Irving",
    "sg:classifiers":[
        {
            "category":"Professional",
            "type":"Services"
        }
    ],
    "sg:phone":"+1 972 373 9300",
    "sg:postcode":"75038",
    "sg:province":"TX",
    "wof:name":"GCI GMBH",
    "wof:placetype":"venue"
},
  "geometry": {"coordinates":[-96.97247400000001,32.884891],"type":"Point"}
}