{
  "type": "Feature",
  "properties": {
    "iso:country":"US",
    "sg:address":"6363 Woodway Dr",
    "sg:city":"Houston",
    "sg:classifiers":[
        {
            "category":"Banks & Credit Unions",
            "subcategory":"Investment Brokerage",
            "type":"Services"
        }
    ],
    "sg:phone":"+1 713 260 3931",
    "sg:postcode":"77057",
    "sg:province":"TX",
    "sg:tags":[
        "commodity",
        "contract"
    ],
    "wof:name":"Mc Vean Trdg & Investments LLC",
    "wof:placetype":"venue"
},
  "geometry": {"coordinates":[-95.49775,29.755648],"type":"Point"}
}