{
  "type": "Feature",
  "properties": {
    "iso:country":"US",
    "sg:address":"3410 Lakeview Pkwy",
    "sg:city":"Rowlett",
    "sg:classifiers":[
        {
            "category":"Health Services",
            "subcategory":"Optometrist",
            "type":"Services"
        }
    ],
    "sg:phone":"+1 972 412 7490",
    "sg:postcode":"75088",
    "sg:province":"TX",
    "wof:name":"Rowlett Family Eyecare",
    "wof:placetype":"venue"
},
  "geometry": {"coordinates":[-96.57067499999999,32.907512],"type":"Point"}
}