{
  "type": "Feature",
  "properties": {
    "iso:country":"US",
    "sg:address":"8502 Coppersky",
    "sg:city":"Converse",
    "sg:classifiers":[
        {
            "category":"Wholesale",
            "subcategory":"Machinery & Supplies",
            "type":"Manufacturing & Wholesale Goods"
        }
    ],
    "sg:phone":"+1 210 566 6650",
    "sg:postcode":"78109",
    "sg:province":"TX",
    "sg:tags":[
        "fire",
        "department",
        "equipment"
    ],
    "sg:website":"www.buckeyef.com",
    "wof:name":"Buckeye Fire Equipment Co",
    "wof:placetype":"venue"
},
  "geometry": {"coordinates":[-98.293618,29.508775],"type":"Point"}
}