{
  "type": "Feature",
  "properties": {
    "iso:country":"US",
    "sg:address":"1646 E Cesar Chavez St",
    "sg:city":"Austin",
    "sg:classifiers":[
        {
            "category":"Shopping",
            "subcategory":"Discount & Variety Stores",
            "type":"Retail Goods"
        }
    ],
    "sg:phone":"+1 512 320 0289",
    "sg:postcode":"78702",
    "sg:province":"TX",
    "wof:name":"1405 Dolex Dollar Express",
    "wof:placetype":"venue"
},
  "geometry": {"coordinates":[-97.72743199999999,30.258223],"type":"Point"}
}