{
  "type": "Feature",
  "properties": {
    "iso:country":"US",
    "sg:address":"2924 Main St",
    "sg:city":"Dallas",
    "sg:classifiers":[
        {
            "category":"Shopping",
            "subcategory":"Clothing, Apparel, & Fashions",
            "type":"Retail Goods"
        }
    ],
    "sg:phone":"+1 214 651 8323",
    "sg:postcode":"75226",
    "sg:province":"TX",
    "wof:name":"Subjugate",
    "wof:placetype":"venue"
},
  "geometry": {"coordinates":[-96.780912,32.784492],"type":"Point"}
}