{
  "type": "Feature",
  "properties": {
    "iso:country":"US",
    "sg:address":"5757 Woodway Dr",
    "sg:city":"Houston",
    "sg:classifiers":[
        {
            "category":"Professional",
            "subcategory":"Management & Consulting",
            "type":"Services"
        }
    ],
    "sg:phone":"+1 713 781 8100",
    "sg:postcode":"77057",
    "sg:province":"TX",
    "sg:tags":[
        "business"
    ],
    "wof:name":"Harris Dmjm Inc",
    "wof:placetype":"venue"
},
  "geometry": {"coordinates":[-95.479046,29.763495],"type":"Point"}
}