{
  "type": "Feature",
  "properties": {
    "iso:country":"US",
    "sg:address":"802 W 41st St",
    "sg:city":"Houston",
    "sg:classifiers":[
        {
            "category":"Building & Trades",
            "subcategory":"Landscaping Services",
            "type":"Services"
        }
    ],
    "sg:phone":"+1 713 222 8733",
    "sg:postcode":"77018",
    "sg:province":"TX",
    "sg:tags":[
        "tree"
    ],
    "wof:name":"Abc Tree Service",
    "wof:placetype":"venue"
},
  "geometry": {"coordinates":[-95.415087,29.824174],"type":"Point"}
}