{
  "type": "Feature",
  "properties": {
    "iso:country":"US",
    "sg:address":"3022 Robinson Rd",
    "sg:city":"Missouri City",
    "sg:classifiers":[
        {
            "category":"Professional",
            "subcategory":"Management & Consulting",
            "type":"Services"
        }
    ],
    "sg:phone":"+1 281 416 8935",
    "sg:postcode":"77459",
    "sg:province":"TX",
    "sg:tags":[
        "business"
    ],
    "wof:name":"Kinney Consulting Services",
    "wof:placetype":"venue"
},
  "geometry": {"coordinates":[-95.54939400000001,29.573777],"type":"Point"}
}