{
  "type": "Feature",
  "properties": {
    "iso:country":"US",
    "sg:address":"5511 W Amarillo Blvd",
    "sg:city":"Amarillo",
    "sg:classifiers":[
        {
            "category":"Organizations",
            "subcategory":"Religious Organization",
            "type":"Services"
        }
    ],
    "sg:phone":"+1 806 353 1488",
    "sg:postcode":"79106",
    "sg:province":"TX",
    "sg:tags":[
        "church"
    ],
    "sg:website":"www.calvarychapel.com",
    "wof:name":"Grace Community Church",
    "wof:placetype":"venue"
},
  "geometry": {"coordinates":[-101.900032,35.216433],"type":"Point"}
}