{
  "type": "Feature",
  "properties": {
    "iso:country":"US",
    "sg:address":"6244 Westwind Dr",
    "sg:city":"El Paso",
    "sg:classifiers":[
        {
            "category":"Health Services",
            "subcategory":"Nursing And Care Facility",
            "type":"Services"
        }
    ],
    "sg:phone":"+1 915 833 4393",
    "sg:postcode":"79912",
    "sg:province":"TX",
    "wof:name":"Daisy Care Foster Home",
    "wof:placetype":"venue"
},
  "geometry": {"coordinates":[-106.526573,31.838371],"type":"Point"}
}