{
  "type": "Feature",
  "properties": {
    "iso:country":"US",
    "sg:address":"2140 Calder Ave",
    "sg:city":"Beaumont",
    "sg:classifiers":[
        {
            "category":"Professional",
            "type":"Services"
        }
    ],
    "sg:phone":"+1 409 813 2206",
    "sg:postcode":"77701",
    "sg:province":"TX",
    "wof:name":"Texas Treatment Services",
    "wof:placetype":"venue"
},
  "geometry": {"coordinates":[-94.117588,30.085918],"type":"Point"}
}