{
  "type": "Feature",
  "properties": {
    "iso:country":"US",
    "sg:address":"4748 Algiers St",
    "sg:city":"Dallas",
    "sg:classifiers":[
        {
            "category":"Communications",
            "subcategory":"Film & Video Production",
            "type":"Services"
        },
        {
            "category":"Building & Trades",
            "subcategory":"Equipment Rental",
            "type":"Services"
        }
    ],
    "sg:phone":"+1 214 630 7228",
    "sg:postcode":"75207",
    "sg:province":"TX",
    "sg:tags":[
        "picture",
        "tv",
        "motion",
        "player",
        "rent",
        "recorder"
    ],
    "sg:website":"www.electriclight.com",
    "wof:name":"E L & P",
    "wof:placetype":"venue"
},
  "geometry": {"coordinates":[-96.848206,32.803252],"type":"Point"}
}