{
  "type": "Feature",
  "properties": {
    "iso:country":"US",
    "sg:address":"2644 E Trinity Mills Rd",
    "sg:city":"Carrollton",
    "sg:classifiers":[
        {
            "category":"Education",
            "subcategory":"Preschool",
            "type":"Public Place"
        },
        {
            "category":"Education",
            "subcategory":"School",
            "type":"Public Place"
        }
    ],
    "sg:phone":"+1 972 416 5437",
    "sg:postcode":"75006",
    "sg:province":"TX",
    "sg:tags":[
        "elementary"
    ],
    "sg:website":"www.covenantchurch.org",
    "wof:name":"American Heritage Academy",
    "wof:placetype":"venue"
},
  "geometry": {"coordinates":[-96.86019899999999,32.986099],"type":"Point"}
}