{
  "type": "Feature",
  "properties": {
    "iso:country":"US",
    "sg:address":"313 Bluebonnet Cir",
    "sg:city":"Mc Gregor",
    "sg:classifiers":[
        {
            "category":"Professional",
            "type":"Services"
        }
    ],
    "sg:phone":"+1 254 848 5699",
    "sg:postcode":"76657",
    "sg:province":"TX",
    "wof:name":"Cainburrharr",
    "wof:placetype":"venue"
},
  "geometry": {"coordinates":[-97.312038,31.475668],"type":"Point"}
}