{
  "type": "Feature",
  "properties": {
    "iso:country":"US",
    "sg:address":"100 Pecan Dr",
    "sg:city":"Aledo",
    "sg:classifiers":[
        {
            "category":"Place Of Worship",
            "subcategory":"Church",
            "type":"Public Place"
        },
        {
            "category":"Place Of Worship",
            "type":"Public Place"
        }
    ],
    "sg:phone":"+1 817 441 8329",
    "sg:postcode":"76008",
    "sg:province":"TX",
    "sg:tags":[
        "churches-methodist"
    ],
    "sg:website":"http://www.aledoumc.org",
    "wof:name":"Central Texas Conference United Methodist Church",
    "wof:placetype":"venue"
},
  "geometry": {"coordinates":[-97.600235,32.695461],"type":"Point"}
}