{
  "type": "Feature",
  "properties": {
    "iso:country":"US",
    "sg:address":"117 E Main St",
    "sg:city":"Royse City",
    "sg:classifiers":[
        {
            "category":"Personal",
            "subcategory":"Beauty Salon",
            "type":"Services"
        }
    ],
    "sg:phone":"+1 972 635 2226",
    "sg:postcode":"75189",
    "sg:province":"TX",
    "wof:name":"Rumors Nail Salon",
    "wof:placetype":"venue"
},
  "geometry": {"coordinates":[-96.33142100000001,32.975338],"type":"Point"}
}