{
  "type": "Feature",
  "properties": {
    "iso:country":"US",
    "sg:address":"824 Office Park Cir",
    "sg:city":"Lewisville",
    "sg:classifiers":[
        {
            "category":"Utilities",
            "subcategory":"Telephone",
            "type":"Services"
        }
    ],
    "sg:phone":"+1 972 353 3393",
    "sg:postcode":"75057",
    "sg:province":"TX",
    "sg:tags":[
        "communications"
    ],
    "wof:name":"TXI",
    "wof:placetype":"venue"
},
  "geometry": {"coordinates":[-96.99782999999999,33.052153],"type":"Point"}
}