{
  "type": "Feature",
  "properties": {
    "iso:country":"US",
    "sg:address":"4025 Preston Rd",
    "sg:city":"Plano",
    "sg:classifiers":[
        {
            "category":"Restaurant",
            "type":"Food & Drink"
        }
    ],
    "sg:phone":"+1 972 781 1406",
    "sg:postcode":"75093",
    "sg:province":"TX",
    "sg:tags":[
        "eating"
    ],
    "wof:name":"Cold Stone Creamery",
    "wof:placetype":"venue"
},
  "geometry": {"coordinates":[-96.79451899999999,33.052745],"type":"Point"}
}