{
  "type": "Feature",
  "properties": {
    "iso:country":"US",
    "sg:address":"3200 Padre Blvd",
    "sg:city":"S Padre Island",
    "sg:classifiers":[
        {
            "category":"Professional",
            "subcategory":"Lawyer & Legal Services",
            "type":"Services"
        }
    ],
    "sg:phone":"+1 956 761 4575",
    "sg:postcode":"78597",
    "sg:province":"TX",
    "sg:tags":[
        "attorney"
    ],
    "wof:name":"Pilot House",
    "wof:placetype":"venue"
},
  "geometry": {"coordinates":[-97.16875899999999,26.108214],"type":"Point"}
}