{
  "type": "Feature",
  "properties": {
    "iso:country":"US",
    "sg:address":"9130 Jollyville Rd",
    "sg:city":"Austin",
    "sg:classifiers":[
        {
            "category":"Wholesale",
            "subcategory":"Durable Goods & Equipment",
            "type":"Manufacturing & Wholesale Goods"
        }
    ],
    "sg:phone":"+1 512 454 1111",
    "sg:postcode":"78759",
    "sg:province":"TX",
    "sg:tags":[
        "representative",
        "manufacturer"
    ],
    "wof:name":"Kruvand Associates",
    "wof:placetype":"venue"
},
  "geometry": {"coordinates":[-97.74159400000001,30.380305],"type":"Point"}
}