{
  "type": "Feature",
  "properties": {
    "iso:country":"US",
    "sg:address":"3506 21st St",
    "sg:city":"Lubbock",
    "sg:classifiers":[
        {
            "category":"Health Services",
            "subcategory":"Clinic",
            "type":"Services"
        }
    ],
    "sg:phone":"+1 806 792 9877",
    "sg:postcode":"79410",
    "sg:province":"TX",
    "sg:tags":[
        "physician",
        "surgeon",
        "bureau",
        "information"
    ],
    "wof:name":"Parkinson Disease APDA",
    "wof:placetype":"venue"
},
  "geometry": {"coordinates":[-101.89199499999999,33.576014],"type":"Point"}
}