{
  "type": "Feature",
  "properties": {
    "iso:country":"US",
    "sg:address":"4434 Frontier Trl",
    "sg:city":"Austin",
    "sg:phone":"+1 512 892 9038",
    "sg:postcode":"78745",
    "sg:province":"TX",
    "wof:name":"Central Texas Veterinary Specialty Hospital",
    "wof:placetype":"venue"
},
  "geometry": {"coordinates":[-97.795469,30.231231],"type":"Point"}
}