{
  "type": "Feature",
  "properties": {
    "iso:country":"US",
    "sg:address":"4910 E Saunders St",
    "sg:city":"Laredo",
    "sg:classifiers":[
        {
            "category":"Wholesale",
            "subcategory":"Durable Goods & Equipment",
            "type":"Manufacturing & Wholesale Goods"
        },
        {
            "category":"Wholesale",
            "subcategory":"Non-durable Goods",
            "type":"Manufacturing & Wholesale Goods"
        }
    ],
    "sg:phone":"+1 956 726 1373",
    "sg:postcode":"78041",
    "sg:province":"TX",
    "sg:tags":[
        "importer"
    ],
    "wof:name":"Gomez Imports",
    "wof:placetype":"venue"
},
  "geometry": {"coordinates":[-99.44842,27.528496],"type":"Point"}
}