{
  "type": "Feature",
  "properties": {
    "iso:country":"US",
    "sg:address":"8609 Old Oak Dr",
    "sg:city":"Irving",
    "sg:classifiers":[
        {
            "category":"Professional",
            "subcategory":"Management & Consulting",
            "type":"Services"
        }
    ],
    "sg:phone":"+1 214 995 5516",
    "sg:postcode":"75063",
    "sg:province":"TX",
    "sg:tags":[
        "asset",
        "point"
    ],
    "wof:name":"USA",
    "wof:placetype":"venue"
},
  "geometry": {"coordinates":[-96.948532,32.922443],"type":"Point"}
}