{
  "type": "Feature",
  "properties": {
    "iso:country":"US",
    "sg:address":"14101 Northwest Fwy",
    "sg:city":"Houston",
    "sg:classifiers":[
        {
            "category":"Autos & Motor Vehicles",
            "subcategory":"Fuel & Gas Station",
            "type":"Retail Goods"
        }
    ],
    "sg:phone":"+1 713 462 0102",
    "sg:postcode":"77040",
    "sg:province":"TX",
    "wof:name":"Exxon Company U S A Complete Auto Repar Twng Srvce",
    "wof:placetype":"venue"
},
  "geometry": {"coordinates":[-95.526398,29.860001],"type":"Point"}
}