{
  "type": "Feature",
  "properties": {
    "iso:country":"US",
    "sg:address":"5201 Harbor Town Dr",
    "sg:city":"Dallas",
    "sg:classifiers":[
        {
            "category":"Manufacturing",
            "subcategory":"Tools & Machinery",
            "type":"Manufacturing & Wholesale Goods"
        }
    ],
    "sg:phone":"+1 972 733 4396",
    "sg:postcode":"75287",
    "sg:province":"TX",
    "sg:tags":[
        "analytical",
        "instrument",
        "mfg"
    ],
    "wof:name":"V Foster Deryl Inc",
    "wof:placetype":"venue"
},
  "geometry": {"coordinates":[-96.824057,32.987505],"type":"Point"}
}