{
  "type": "Feature",
  "properties": {
    "iso:country":"US",
    "sg:address":"500 Sara Dr",
    "sg:city":"Round Rock",
    "sg:classifiers":[
        {
            "category":"Professional",
            "subcategory":"Management & Consulting",
            "type":"Services"
        }
    ],
    "sg:phone":"+1 512 587 1006",
    "sg:postcode":"78664",
    "sg:province":"TX",
    "sg:tags":[
        "marketing",
        "writing",
        "communications"
    ],
    "wof:name":"Infomasons",
    "wof:placetype":"venue"
},
  "geometry": {"coordinates":[-97.676536,30.525875],"type":"Point"}
}