{
  "type": "Feature",
  "properties": {
    "iso:country":"US",
    "sg:address":"2591 NE 28th St",
    "sg:city":"Fort Worth",
    "sg:classifiers":[
        {
            "category":"Freight",
            "type":"Transportation"
        }
    ],
    "sg:phone":"+1 817 759 0200",
    "sg:postcode":"76111",
    "sg:province":"TX",
    "sg:tags":[
        "operator",
        "trucking"
    ],
    "wof:name":"Asco Venture Transport",
    "wof:placetype":"venue"
},
  "geometry": {"coordinates":[-97.31108999999999,32.795252],"type":"Point"}
}