{
  "type": "Feature",
  "properties": {
    "iso:country":"US",
    "sg:address":"600 N Crockett St",
    "sg:city":"Sherman",
    "sg:classifiers":[
        {
            "category":"Health Services",
            "subcategory":"Clinic",
            "type":"Services"
        }
    ],
    "sg:phone":"+1 903 868 1339",
    "sg:postcode":"75090",
    "sg:province":"TX",
    "sg:tags":[
        "home"
    ],
    "wof:name":"Heavensent Caregivers",
    "wof:placetype":"venue"
},
  "geometry": {"coordinates":[-96.61204600000001,33.641262],"type":"Point"}
}