{
  "type": "Feature",
  "properties": {
    "iso:country":"US",
    "sg:address":"201 Laurence Dr",
    "sg:city":"Rockwall",
    "sg:classifiers":[
        {
            "category":"Real Estate",
            "subcategory":"Real Estate Agent",
            "type":"Services"
        }
    ],
    "sg:phone":"+1 972 722 6400",
    "sg:postcode":"75032",
    "sg:province":"TX",
    "wof:name":"Diamond Realtors",
    "wof:placetype":"venue"
},
  "geometry": {"coordinates":[-96.470277,32.840522],"type":"Point"}
}