{
  "type": "Feature",
  "properties": {
    "iso:country":"US",
    "sg:address":"119 W Highland Dr",
    "sg:city":"Boerne",
    "sg:classifiers":[
        {
            "category":"Professional",
            "type":"Services"
        }
    ],
    "sg:phone":"+1 830 249 1853",
    "sg:postcode":"78006",
    "sg:province":"TX",
    "wof:name":"Creative Images",
    "wof:placetype":"venue"
},
  "geometry": {"coordinates":[-98.730093,29.784368],"type":"Point"}
}