{
  "type": "Feature",
  "properties": {
    "iso:country":"US",
    "sg:address":"1310 Eagle Lakes Dr",
    "sg:city":"Friendswood",
    "sg:classifiers":[
        {
            "category":"Professional",
            "subcategory":"Business Services",
            "type":"Services"
        }
    ],
    "sg:phone":"+1 281 996 9137",
    "sg:postcode":"77546",
    "sg:province":"TX",
    "wof:name":"Randy Barr",
    "wof:placetype":"venue"
},
  "geometry": {"coordinates":[-95.195795,29.491034],"type":"Point"}
}