{
  "type": "Feature",
  "properties": {
    "iso:country":"US",
    "sg:address":"2261 Brookhollow Plaza Dr",
    "sg:city":"Arlington",
    "sg:classifiers":[
        {
            "category":"Banks & Credit Unions",
            "subcategory":"Investment Brokerage",
            "type":"Services"
        }
    ],
    "sg:phone":"+1 817 608 0600",
    "sg:postcode":"76006",
    "sg:province":"TX",
    "sg:tags":[
        "advisory",
        "financial"
    ],
    "wof:name":"Primerica Financial Svc",
    "wof:placetype":"venue"
},
  "geometry": {"coordinates":[-97.069937,32.763439],"type":"Point"}
}