{
  "type": "Feature",
  "properties": {
    "iso:country":"US",
    "sg:address":"3122 N 1st St",
    "sg:city":"Abilene",
    "sg:classifiers":[
        {
            "category":"Shopping",
            "type":"Retail Goods"
        },
        {
            "category":"Building & Trades",
            "subcategory":"Equipment Rental",
            "type":"Services"
        }
    ],
    "sg:phone":"+1 325 672 3030",
    "sg:postcode":"79603",
    "sg:province":"TX",
    "sg:tags":[
        "health",
        "medical",
        "care",
        "m",
        "home"
    ],
    "wof:name":"Express Medical Supply Ltd",
    "wof:placetype":"venue"
},
  "geometry": {"coordinates":[-99.760248,32.451243],"type":"Point"}
}