{
  "type": "Feature",
  "properties": {
    "iso:country":"US",
    "sg:address":"317 Adams",
    "sg:city":"Seguin",
    "sg:classifiers":[
        {
            "category":"Building & Trades",
            "subcategory":"Construction",
            "type":"Services"
        }
    ],
    "sg:phone":"+1 830 379 8353",
    "sg:postcode":"78155",
    "sg:province":"TX",
    "sg:tags":[
        "home",
        "improvement"
    ],
    "wof:name":"Pape Mobile Home Repair & Svc",
    "wof:placetype":"venue"
},
  "geometry": {"coordinates":[-97.967726,29.563133],"type":"Point"}
}