{
  "type": "Feature",
  "properties": {
    "iso:country":"US",
    "sg:address":"1750 Viceroy Dr",
    "sg:city":"Dallas",
    "sg:classifiers":[
        {
            "category":"Education",
            "subcategory":"School",
            "type":"Public Place"
        }
    ],
    "sg:phone":"+1 214 276 0352",
    "sg:postcode":"75235",
    "sg:province":"TX",
    "wof:name":"Uplift Education",
    "wof:placetype":"venue"
},
  "geometry": {"coordinates":[-96.868706,32.8361],"type":"Point"}
}