{
  "type": "Feature",
  "properties": {
    "iso:country":"US",
    "sg:address":"1320 Homer Smith Rd",
    "sg:city":"Whitewright",
    "sg:classifiers":[
        {
            "category":"Manufacturing",
            "subcategory":"Food",
            "type":"Manufacturing & Wholesale Goods"
        }
    ],
    "sg:phone":"+1 903 546 4861",
    "sg:postcode":"75491",
    "sg:province":"TX",
    "sg:tags":[
        "preparation",
        "mfg"
    ],
    "wof:name":"CB Enterprises",
    "wof:placetype":"venue"
},
  "geometry": {"coordinates":[-96.497846,33.483226],"type":"Point"}
}