{
  "type": "Feature",
  "properties": {
    "iso:country":"US",
    "sg:address":"1010 Amelia St",
    "sg:city":"Beaumont",
    "sg:classifiers":[
        {
            "category":"Bars & Pubs",
            "type":"Food & Drink"
        }
    ],
    "sg:phone":"+1 409 866 9057",
    "sg:postcode":"77707",
    "sg:province":"TX",
    "sg:tags":[
        "drinking"
    ],
    "wof:name":"Lindas Lounge",
    "wof:placetype":"venue"
},
  "geometry": {"coordinates":[-94.18316299999999,30.06506],"type":"Point"}
}