{
  "type": "Feature",
  "properties": {
    "iso:country":"US",
    "sg:address":"8080 Pat Booker Rd",
    "sg:city":"San Antonio",
    "sg:classifiers":[
        {
            "category":"Personal",
            "subcategory":"Beauty Salon",
            "type":"Services"
        }
    ],
    "sg:phone":"+1 210 654 7400",
    "sg:postcode":"78233",
    "sg:province":"TX",
    "sg:tags":[
        "shop"
    ],
    "wof:name":"Blondes Brunettes and Red",
    "wof:placetype":"venue"
},
  "geometry": {"coordinates":[-98.332352,29.562603],"type":"Point"}
}