{
  "type": "Feature",
  "properties": {
    "iso:country":"US",
    "sg:address":"4919 Homer St",
    "sg:city":"Dallas",
    "sg:classifiers":[
        {
            "category":"Shopping",
            "subcategory":"Used Merchandise",
            "type":"Retail Goods"
        }
    ],
    "sg:phone":"+1 214 824 5558",
    "sg:postcode":"75206",
    "sg:province":"TX",
    "sg:tags":[
        "antique"
    ],
    "wof:name":"Nancy's Antiques",
    "wof:placetype":"venue"
},
  "geometry": {"coordinates":[-96.784997,32.815427],"type":"Point"}
}