{
  "type": "Feature",
  "properties": {
    "iso:country":"US",
    "sg:address":"218 E Virginia St",
    "sg:city":"Mc Kinney",
    "sg:classifiers":[
        {
            "category":"Professional",
            "type":"Services"
        }
    ],
    "sg:phone":"+1 972 542 3958",
    "sg:postcode":"75069",
    "sg:province":"TX",
    "sg:tags":[
        "establishment"
    ],
    "wof:name":"Duncan Enterprises",
    "wof:placetype":"venue"
},
  "geometry": {"coordinates":[-96.61477499999999,33.197897],"type":"Point"}
}