{
  "type": "Feature",
  "properties": {
    "iso:country":"US",
    "sg:address":"2302 Garden City Hwy",
    "sg:city":"Midland",
    "sg:classifiers":[
        {
            "category":"Building & Trades",
            "subcategory":"Plumbing",
            "type":"Services"
        }
    ],
    "sg:phone":"+1 432 570 8105",
    "sg:postcode":"79701",
    "sg:province":"TX",
    "sg:tags":[
        "plumbing",
        "contractor"
    ],
    "wof:name":"Alpine Mechanical",
    "wof:placetype":"venue"
},
  "geometry": {"coordinates":[-102.04652900000001,31.984892],"type":"Point"}
}