{
  "type": "Feature",
  "properties": {
    "iso:country":"US",
    "sg:address":"1314 Oahu Dr",
    "sg:city":"Galveston",
    "sg:classifiers":[
        {
            "category":"Shopping",
            "type":"Retail Goods"
        }
    ],
    "sg:phone":"+1 409 908 0598",
    "sg:postcode":"77554",
    "sg:province":"TX",
    "sg:tags":[
        "merchandise"
    ],
    "wof:name":"Faye M Garrett",
    "wof:placetype":"venue"
},
  "geometry": {"coordinates":[-94.91654200000001,29.293267],"type":"Point"}
}