{
  "type": "Feature",
  "properties": {
    "iso:country":"US",
    "sg:address":"3014 Del Monte Dr",
    "sg:city":"Houston",
    "sg:classifiers":[
        {
            "category":"Health Services",
            "subcategory":"Doctor",
            "type":"Services"
        }
    ],
    "sg:phone":"+1 713 528 3285",
    "sg:postcode":"77019",
    "sg:province":"TX",
    "wof:name":"Cooley Denton A MD",
    "wof:placetype":"venue"
},
  "geometry": {"coordinates":[-95.420799,29.750601],"type":"Point"}
}