{
  "type": "Feature",
  "properties": {
    "iso:country":"US",
    "sg:address":"6347 Oberlin Ct",
    "sg:city":"Tyler",
    "sg:classifiers":[
        {
            "category":"Personal",
            "subcategory":"Beauty Salon",
            "type":"Services"
        }
    ],
    "sg:phone":"+1 903 581 7339",
    "sg:postcode":"75703",
    "sg:province":"TX",
    "wof:name":"Tyler's Best Spa",
    "wof:placetype":"venue"
},
  "geometry": {"coordinates":[-95.292952,32.265429],"type":"Point"}
}