{
  "type": "Feature",
  "properties": {
    "iso:country":"US",
    "sg:address":"15301 Spectrum Dr Ste 510",
    "sg:city":"Addison",
    "sg:classifiers":[
        {
            "category":"Banks & Credit Unions",
            "subcategory":"Financial Services",
            "type":"Services"
        }
    ],
    "sg:phone":"+1 972 991 1221",
    "sg:postcode":"75001",
    "sg:province":"TX",
    "sg:tags":[
        "broker",
        "mortgage"
    ],
    "wof:name":"Barkwood Mortgage",
    "wof:placetype":"venue"
},
  "geometry": {"coordinates":[-96.824943,32.957792],"type":"Point"}
}