{
  "type": "Feature",
  "properties": {
    "iso:country":"US",
    "sg:address":"1224 Chelsea St",
    "sg:city":"Grapevine",
    "sg:classifiers":[
        {
            "category":"Building & Trades",
            "subcategory":"Construction",
            "type":"Services"
        }
    ],
    "sg:phone":"+1 817 488 1533",
    "sg:postcode":"76051",
    "sg:province":"TX",
    "wof:name":"American Buildings Co",
    "wof:placetype":"venue"
},
  "geometry": {"coordinates":[-97.08813000000001,32.937404],"type":"Point"}
}