{
  "type": "Feature",
  "properties": {
    "iso:country":"US",
    "sg:address":"801 E Plano Pkwy",
    "sg:city":"Plano",
    "sg:classifiers":[
        {
            "category":"Professional",
            "subcategory":"Computer Services",
            "type":"Services"
        }
    ],
    "sg:phone":"+1 972 943 0837",
    "sg:postcode":"75074",
    "sg:province":"TX",
    "sg:tags":[
        "design",
        "integration",
        "system"
    ],
    "wof:name":"Premier Consultancy Services",
    "wof:placetype":"venue"
},
  "geometry": {"coordinates":[-96.702063,33.007404],"type":"Point"}
}