{
  "type": "Feature",
  "properties": {
    "iso:country":"US",
    "sg:address":"3740 N Josey Ln",
    "sg:city":"Carrollton",
    "sg:classifiers":[
        {
            "category":"Wholesale",
            "subcategory":"Computers",
            "type":"Manufacturing & Wholesale Goods"
        }
    ],
    "sg:phone":"+1 972 939 2675",
    "sg:postcode":"75007",
    "sg:province":"TX",
    "sg:website":"www.menmicro.com",
    "wof:name":"Men Micro Inc",
    "wof:placetype":"venue"
},
  "geometry": {"coordinates":[-96.886872,33.011697],"type":"Point"}
}