{
  "type": "Feature",
  "properties": {
    "iso:country":"US",
    "sg:address":"101 Bluebonnet Dr",
    "sg:city":"Winters",
    "sg:classifiers":[
        {
            "category":"Real Estate",
            "subcategory":"Real Estate Operator",
            "type":"Services"
        }
    ],
    "sg:phone":"+1 325 754 3331",
    "sg:postcode":"79567",
    "sg:province":"TX",
    "sg:tags":[
        "apartment"
    ],
    "wof:name":"Ventures Housing Finance,",
    "wof:placetype":"venue"
},
  "geometry": {"coordinates":[-99.962681,31.976183],"type":"Point"}
}