{
  "type": "Feature",
  "properties": {
    "iso:country":"US",
    "sg:address":"4559 5th St",
    "sg:city":"Brookshire",
    "sg:classifiers":[
        {
            "category":"Home & Garden",
            "subcategory":"Furniture",
            "type":"Retail Goods"
        }
    ],
    "sg:phone":"+1 281 375 7962",
    "sg:postcode":"77423",
    "sg:province":"TX",
    "sg:tags":[
        "top",
        "counter"
    ],
    "wof:name":"Marble & Granite Creations",
    "wof:placetype":"venue"
},
  "geometry": {"coordinates":[-95.96176199999999,29.785081],"type":"Point"}
}