{
  "type": "Feature",
  "properties": {
    "iso:country":"US",
    "sg:address":"1717 Main St",
    "sg:city":"Dallas",
    "sg:classifiers":[
        {
            "category":"Insurance",
            "subcategory":"Hazard Insurance",
            "type":"Services"
        }
    ],
    "sg:phone":"+1 972 263 2042",
    "sg:postcode":"75201",
    "sg:province":"TX",
    "sg:tags":[
        "carrier"
    ],
    "wof:name":"Shumway & Assoc Inc",
    "wof:placetype":"venue"
},
  "geometry": {"coordinates":[-96.795799,32.781431],"type":"Point"}
}