{
  "type": "Feature",
  "properties": {
    "iso:country":"US",
    "sg:address":"15603 E State Hwy 29",
    "sg:city":"Buchanan Dam",
    "sg:classifiers":[
        {
            "category":"Bars & Pubs",
            "type":"Food & Drink"
        }
    ],
    "sg:phone":"+1 512 793 6267",
    "sg:postcode":"78609",
    "sg:province":"TX",
    "sg:tags":[
        "club",
        "night"
    ],
    "wof:name":"Ranch",
    "wof:placetype":"venue"
},
  "geometry": {"coordinates":[-98.46096900000001,30.733752],"type":"Point"}
}