{
  "type": "Feature",
  "properties": {
    "iso:country":"US",
    "sg:address":"959 E Collins Blvd",
    "sg:city":"Richardson",
    "sg:classifiers":[
        {
            "category":"Shopping",
            "subcategory":"Optical Goods",
            "type":"Retail Goods"
        }
    ],
    "sg:phone":"+1 469 916 1674",
    "sg:postcode":"75081",
    "sg:province":"TX",
    "wof:name":"Arcube Optical Mfg L",
    "wof:placetype":"venue"
},
  "geometry": {"coordinates":[-96.711743,32.968042],"type":"Point"}
}