{
  "type": "Feature",
  "properties": {
    "iso:country":"US",
    "sg:address":"216 Sequoya St",
    "sg:city":"Buda",
    "sg:classifiers":[
        {
            "category":"Manufacturing",
            "subcategory":"Metals",
            "type":"Manufacturing & Wholesale Goods"
        }
    ],
    "sg:phone":"+1 512 312 0011",
    "sg:postcode":"78610",
    "sg:province":"TX",
    "sg:tags":[
        "metalwork",
        "architectural",
        "mfg"
    ],
    "wof:name":"Metal Crafts By Ronnie",
    "wof:placetype":"venue"
},
  "geometry": {"coordinates":[-97.837311,30.077391],"type":"Point"}
}