{
  "type": "Feature",
  "properties": {
    "iso:country":"US",
    "sg:address":"108 W 45th Street Apt 101",
    "sg:city":"Austin",
    "sg:classifiers":[
        {
            "category":"Real Estate",
            "subcategory":"Real Estate Operator",
            "type":"Services"
        }
    ],
    "sg:phone":"+1 512 452 1419",
    "sg:postcode":"78751",
    "sg:province":"TX",
    "sg:tags":[
        "apartment"
    ],
    "sg:website":"www.108place.com",
    "wof:name":"108 Place Apartments",
    "wof:placetype":"venue"
},
  "geometry": {"coordinates":[-97.72845100000001,30.308735],"type":"Point"}
}