{
  "type": "Feature",
  "properties": {
    "iso:country":"US",
    "sg:address":"1709 SE 14th Ave",
    "sg:city":"Mineral Wells",
    "sg:classifiers":[
        {
            "category":"Personal",
            "subcategory":"Beauty Salon",
            "type":"Services"
        }
    ],
    "sg:phone":"+1 940 325 6921",
    "sg:postcode":"76067",
    "sg:province":"TX",
    "sg:tags":[
        "shop"
    ],
    "wof:name":"Delores Beauty Salon",
    "wof:placetype":"venue"
},
  "geometry": {"coordinates":[-98.10003399999999,32.796397],"type":"Point"}
}