{
  "type": "Feature",
  "properties": {
    "iso:country":"US",
    "sg:address":"307 Locust St",
    "sg:city":"Sweetwater",
    "sg:classifiers":[
        {
            "category":"Professional",
            "subcategory":"Lawyer & Legal Services",
            "type":"Services"
        }
    ],
    "sg:phone":"+1 325 236 6864",
    "sg:postcode":"79556",
    "sg:province":"TX",
    "sg:tags":[
        "attorney"
    ],
    "sg:website":"www.conardlaw.com",
    "wof:name":"Frank Conard Law Firm",
    "wof:placetype":"venue"
},
  "geometry": {"coordinates":[-100.408551,32.472333],"type":"Point"}
}