{
  "type": "Feature",
  "properties": {
    "iso:country":"US",
    "sg:address":"10600 Gulf Fwy",
    "sg:city":"Houston",
    "sg:classifiers":[
        {
            "category":"Restaurant",
            "type":"Food & Drink"
        }
    ],
    "sg:phone":"+1 713 944 8980",
    "sg:postcode":"77034",
    "sg:province":"TX",
    "wof:name":"James Coney Island",
    "wof:placetype":"venue"
},
  "geometry": {"coordinates":[-95.242401,29.6394],"type":"Point"}
}