{
  "type": "Feature",
  "properties": {
    "iso:country":"US",
    "sg:address":"6911 Canyon Way Dr",
    "sg:city":"Houston",
    "sg:classifiers":[
        {
            "category":"Shopping",
            "type":"Retail Goods"
        }
    ],
    "sg:phone":"+1 281 272 1385",
    "sg:postcode":"77086",
    "sg:province":"TX",
    "sg:tags":[
        "merchandise"
    ],
    "wof:name":"Candles & More",
    "wof:placetype":"venue"
},
  "geometry": {"coordinates":[-95.487872,29.93338],"type":"Point"}
}