{
  "type": "Feature",
  "properties": {
    "iso:country":"US",
    "sg:address":"800 Spring St",
    "sg:city":"Del Rio",
    "sg:classifiers":[
        {
            "category":"Recreation",
            "type":"Entertainment"
        }
    ],
    "sg:phone":"+1 830 774 8786",
    "sg:postcode":"78840",
    "sg:province":"TX",
    "sg:tags":[
        "parks"
    ],
    "wof:name":"Roosevelt Baseball Park",
    "wof:placetype":"venue"
},
  "geometry": {"coordinates":[-100.88961500000001,29.365389],"type":"Point"}
}