{
  "type": "Feature",
  "properties": {
    "iso:country":"US",
    "sg:address":"143 Cricket Hollow Ln",
    "sg:city":"Smithville",
    "sg:classifiers":[
        {
            "category":"Wholesale",
            "subcategory":"Hardware",
            "type":"Manufacturing & Wholesale Goods"
        }
    ],
    "sg:phone":"+1 512 237 3143",
    "sg:postcode":"78957",
    "sg:province":"TX",
    "sg:tags":[
        "plumbing"
    ],
    "wof:name":"Johnsons Waste Water Systems",
    "wof:placetype":"venue"
},
  "geometry": {"coordinates":[-97.115223,30.109245],"type":"Point"}
}