{
  "type": "Feature",
  "properties": {
    "iso:country":"US",
    "sg:address":"5815 Blazing Star Rd",
    "sg:city":"Frisco",
    "sg:classifiers":[
        {
            "category":"Wholesale",
            "subcategory":"Groceries",
            "type":"Manufacturing & Wholesale Goods"
        }
    ],
    "sg:phone":"+1 972 625 0772",
    "sg:postcode":"75034",
    "sg:province":"TX",
    "sg:tags":[
        "general"
    ],
    "wof:name":"General Mills",
    "wof:placetype":"venue"
},
  "geometry": {"coordinates":[-96.87651700000001,33.124621],"type":"Point"}
}