{
  "type": "Feature",
  "properties": {
    "iso:country":"US",
    "sg:address":"1327 Drury Ln",
    "sg:city":"San Antonio",
    "sg:classifiers":[
        {
            "category":"Retail",
            "subcategory":"Auto Repair",
            "type":"Services"
        }
    ],
    "sg:phone":"+1 210 927 2621",
    "sg:postcode":"78221",
    "sg:province":"TX",
    "sg:tags":[
        "automotive"
    ],
    "wof:name":"Bubies Wrecker Service",
    "wof:placetype":"venue"
},
  "geometry": {"coordinates":[-98.52617499999999,29.347676],"type":"Point"}
}