{
  "type": "Feature",
  "properties": {
    "iso:country":"US",
    "sg:address":"1225 Scott Dr",
    "sg:city":"Hurst",
    "sg:classifiers":[
        {
            "category":"Professional",
            "type":"Services"
        }
    ],
    "sg:phone":"+1 817 284 3631",
    "sg:postcode":"76053",
    "sg:province":"TX",
    "wof:name":"Avalon Electronics Co",
    "wof:placetype":"venue"
},
  "geometry": {"coordinates":[-97.188371,32.833207],"type":"Point"}
}