{
  "type": "Feature",
  "properties": {
    "iso:country":"US",
    "sg:address":"1006 Coral Pl",
    "sg:city":"Corpus Christi",
    "sg:classifiers":[
        {
            "category":"Restaurant",
            "type":"Food & Drink"
        }
    ],
    "sg:phone":"+1 361 857 0057",
    "sg:postcode":"78411",
    "sg:province":"TX",
    "sg:tags":[
        "heating"
    ],
    "wof:name":"TW Bull Co",
    "wof:placetype":"venue"
},
  "geometry": {"coordinates":[-97.38252199999999,27.731696],"type":"Point"}
}