{
  "type": "Feature",
  "properties": {
    "iso:country":"US",
    "sg:address":"12862 State Hwy 155",
    "sg:city":"Tyler",
    "sg:classifiers":[
        {
            "category":"Retail",
            "subcategory":"Laundry & Dry Cleaning",
            "type":"Services"
        },
        {
            "category":"Shopping",
            "subcategory":"Clothing, Apparel, & Fashions",
            "type":"Retail Goods"
        }
    ],
    "sg:phone":"+1 903 561 1431",
    "sg:postcode":"75703",
    "sg:province":"TX",
    "sg:tags":[
        "alteration"
    ],
    "wof:name":"P B Alterations",
    "wof:placetype":"venue"
},
  "geometry": {"coordinates":[-95.347543,32.294931],"type":"Point"}
}