{
  "type": "Feature",
  "properties": {
    "iso:country":"US",
    "sg:address":"1210 Sherman St",
    "sg:city":"San Antonio",
    "sg:classifiers":[
        {
            "category":"Wholesale",
            "subcategory":"Fruits & Vegetables",
            "type":"Manufacturing & Wholesale Goods"
        }
    ],
    "sg:phone":"+1 210 224 3432",
    "sg:postcode":"78202",
    "sg:province":"TX",
    "wof:name":"Pacific Fruit Express",
    "wof:placetype":"venue"
},
  "geometry": {"coordinates":[-98.459587,29.433967],"type":"Point"}
}