{
  "type": "Feature",
  "properties": {
    "iso:country":"US",
    "sg:address":"400 Round Rock Ave",
    "sg:city":"Round Rock",
    "sg:classifiers":[
        {
            "category":"Restaurant",
            "type":"Food & Drink"
        }
    ],
    "sg:menulink":"http://www.allmenus.com/tx/georgetown-round-rock/229105-golden-chick/menu/",
    "sg:phone":"+1 512 255 0950",
    "sg:postcode":"78664",
    "sg:province":"TX",
    "sg:tags":[
        "american"
    ],
    "wof:name":"Golden Chick",
    "wof:placetype":"venue"
},
  "geometry": {"coordinates":[-97.68233499999999,30.509242],"type":"Point"}
}