{
  "type": "Feature",
  "properties": {
    "iso:country":"US",
    "sg:address":"1213 RM 620 N",
    "sg:city":"Austin",
    "sg:classifiers":[
        {
            "category":"Professional",
            "type":"Services"
        }
    ],
    "sg:phone":"+1 512 480 0019",
    "sg:postcode":"78734",
    "sg:province":"TX",
    "sg:tags":[
        "establishment"
    ],
    "wof:name":"Rio Development",
    "wof:placetype":"venue"
},
  "geometry": {"coordinates":[-97.94672300000001,30.375001],"type":"Point"}
}