{
  "type": "Feature",
  "properties": {
    "iso:country":"US",
    "sg:address":"2209 S 9th St",
    "sg:city":"Waco",
    "sg:classifiers":[
        {
            "category":"Shopping",
            "subcategory":"Computers & Home Electronics",
            "type":"Retail Goods"
        }
    ],
    "sg:phone":"+1 254 754 3878",
    "sg:postcode":"76706",
    "sg:province":"TX",
    "wof:name":"Antonio Car Audio",
    "wof:placetype":"venue"
},
  "geometry": {"coordinates":[-97.115557,31.536706],"type":"Point"}
}