{
  "type": "Feature",
  "properties": {
    "iso:country":"US",
    "sg:address":"5729 Savoy Dr",
    "sg:city":"Houston",
    "sg:classifiers":[
        {
            "category":"Wholesale",
            "subcategory":"Construction Materials",
            "type":"Manufacturing & Wholesale Goods"
        }
    ],
    "sg:phone":"+1 713 952 0002",
    "sg:postcode":"77036",
    "sg:province":"TX",
    "sg:tags":[
        "windows",
        "door"
    ],
    "wof:name":"The Window Center",
    "wof:placetype":"venue"
},
  "geometry": {"coordinates":[-95.50596,29.719178],"type":"Point"}
}