{
  "type": "Feature",
  "properties": {
    "iso:country":"US",
    "sg:address":"1515 N Town East Blvd Ste 188",
    "sg:city":"Mesquite",
    "sg:classifiers":[
        {
            "category":"Shopping",
            "subcategory":"Clothing, Apparel, & Fashions",
            "type":"Retail Goods"
        }
    ],
    "sg:phone":"+1 888 852 6357",
    "sg:postcode":"75150",
    "sg:province":"TX",
    "sg:tags":[
        "clothing",
        "men's",
        "sale",
        "wear",
        "rental",
        "store",
        "formal"
    ],
    "sg:website":"http://dallas.citysearch.com/profile/external/9567931/mesquite_tx/men_s_wearhouse.html?publisher=yellowpages&reference_id=1&placement=ypwebsitemip",
    "wof:name":"Men's Wearhouse",
    "wof:placetype":"venue"
},
  "geometry": {"coordinates":[-96.618347,32.81089],"type":"Point"}
}