{
  "type": "Feature",
  "properties": {
    "iso:country":"US",
    "sg:address":"1800 Quail Hollow Rd",
    "sg:city":"Cleburne",
    "sg:classifiers":[
        {
            "category":"Building & Trades",
            "subcategory":"Landscaping Services",
            "type":"Services"
        }
    ],
    "sg:phone":"+1 817 556 9001",
    "sg:postcode":"76033",
    "sg:province":"TX",
    "sg:tags":[
        "landscape",
        "contractor"
    ],
    "wof:name":"Border Magic-N Central Texas",
    "wof:placetype":"venue"
},
  "geometry": {"coordinates":[-97.422797,32.326358],"type":"Point"}
}