{
  "type": "Feature",
  "properties": {
    "iso:country":"US",
    "sg:address":"4223 Martin L King Blvd",
    "sg:city":"Lubbock",
    "sg:classifiers":[
        {
            "category":"Freight",
            "type":"Transportation"
        }
    ],
    "sg:phone":"+1 806 762 8674",
    "sg:postcode":"79404",
    "sg:province":"TX",
    "sg:tags":[
        "trucking"
    ],
    "wof:name":"Fed Ex Freight East",
    "wof:placetype":"venue"
},
  "geometry": {"coordinates":[-101.818318,33.554382],"type":"Point"}
}