{
  "type": "Feature",
  "properties": {
    "iso:country":"US",
    "sg:address":"1603 Cooper Dr",
    "sg:city":"Irving",
    "sg:classifiers":[
        {
            "category":"Autos & Motor Vehicles",
            "subcategory":"Automobile Sales",
            "type":"Retail Goods"
        }
    ],
    "sg:phone":"+1 972 438 1900",
    "sg:postcode":"75061",
    "sg:province":"TX",
    "sg:tags":[
        "limo"
    ],
    "wof:name":"Panache Limousine Inc",
    "wof:placetype":"venue"
},
  "geometry": {"coordinates":[-96.924733,32.830712],"type":"Point"}
}