{
  "type": "Feature",
  "properties": {
    "iso:country":"US",
    "sg:address":"2331 Commercial Ave",
    "sg:city":"Anson",
    "sg:classifiers":[
        {
            "category":"Shopping",
            "subcategory":"Discount & Variety Stores",
            "type":"Retail Goods"
        }
    ],
    "sg:phone":"+1 325 823 4985",
    "sg:postcode":"79501",
    "sg:province":"TX",
    "wof:name":"Dollar General",
    "wof:placetype":"venue"
},
  "geometry": {"coordinates":[-99.896771,32.745316],"type":"Point"}
}