{
  "type": "Feature",
  "properties": {
    "iso:country":"US",
    "sg:address":"301 E McLain St",
    "sg:city":"Seymour",
    "sg:classifiers":[
        {
            "category":"Real Estate",
            "subcategory":"Real Estate Agent",
            "type":"Services"
        }
    ],
    "sg:phone":"+1 940 888 3135",
    "sg:postcode":"76380",
    "sg:province":"TX",
    "wof:name":"Success Realty",
    "wof:placetype":"venue"
},
  "geometry": {"coordinates":[-99.259028,33.588015],"type":"Point"}
}