{
  "type": "Feature",
  "properties": {
    "iso:country":"US",
    "sg:address":"9235 Katy Fwy",
    "sg:city":"Houston",
    "sg:classifiers":[
        {
            "category":"Banks & Credit Unions",
            "subcategory":"Investment Brokerage",
            "type":"Services"
        }
    ],
    "sg:phone":"+1 713 465 4295",
    "sg:postcode":"77024",
    "sg:province":"TX",
    "sg:tags":[
        "security"
    ],
    "wof:name":"Wolfe & Hurst Bond Broker Inc",
    "wof:placetype":"venue"
},
  "geometry": {"coordinates":[-95.51831,29.783676],"type":"Point"}
}