{
  "type": "Feature",
  "properties": {
    "iso:country":"US",
    "sg:address":"3621 Raider Dr",
    "sg:city":"Hurst",
    "sg:classifiers":[
        {
            "category":"Building & Trades",
            "subcategory":"Landscaping Services",
            "type":"Services"
        }
    ],
    "sg:phone":"+1 817 858 0805",
    "sg:postcode":"76053",
    "sg:province":"TX",
    "wof:name":"Modular Watergardens LLC",
    "wof:placetype":"venue"
},
  "geometry": {"coordinates":[-97.1348,32.812876],"type":"Point"}
}