{
  "type": "Feature",
  "properties": {
    "iso:country":"US",
    "sg:address":"5418 Schertz Rd",
    "sg:city":"San Antonio",
    "sg:classifiers":[
        {
            "category":"Retail",
            "subcategory":"Laundry & Dry Cleaning",
            "type":"Services"
        }
    ],
    "sg:phone":"+1 210 545 0605",
    "sg:postcode":"78233",
    "sg:province":"TX",
    "wof:name":"Steam King Inc",
    "wof:placetype":"venue"
},
  "geometry": {"coordinates":[-98.38261900000001,29.541702],"type":"Point"}
}