{
  "type": "Feature",
  "properties": {
    "iso:country":"US",
    "sg:address":"511 N 2nd St",
    "sg:city":"Midlothian",
    "sg:classifiers":[
        {
            "category":"Professional",
            "subcategory":"Management & Consulting",
            "type":"Services"
        }
    ],
    "sg:phone":"+1 972 723 1284",
    "sg:postcode":"76065",
    "sg:province":"TX",
    "sg:tags":[
        "retail",
        "direct",
        "sales"
    ],
    "wof:name":"Home Interiors & Gifts",
    "wof:placetype":"venue"
},
  "geometry": {"coordinates":[-97.00109399999999,32.488045],"type":"Point"}
}