{
  "type": "Feature",
  "properties": {
    "iso:country":"US",
    "sg:address":"1501 US Hwy 67",
    "sg:city":"Midlothian",
    "sg:classifiers":[
        {
            "category":"Insurance",
            "subcategory":"Insurance Agent",
            "type":"Services"
        }
    ],
    "sg:phone":"+1 972 723 9080",
    "sg:postcode":"76065",
    "sg:province":"TX",
    "wof:name":"Jeffery Honeycutt Insurance",
    "wof:placetype":"venue"
},
  "geometry": {"coordinates":[-96.98777800000001,32.501196],"type":"Point"}
}