{
  "type": "Feature",
  "properties": {
    "iso:country":"US",
    "sg:address":"6604 Anglin Dr",
    "sg:city":"Fort Worth",
    "sg:classifiers":[
        {
            "category":"Manufacturing",
            "subcategory":"Furniture",
            "type":"Manufacturing & Wholesale Goods"
        }
    ],
    "sg:phone":"+1 817 534 8146",
    "sg:postcode":"76119",
    "sg:province":"TX",
    "sg:tags":[
        "wood",
        "mfg"
    ],
    "wof:name":"Tim Platt",
    "wof:placetype":"venue"
},
  "geometry": {"coordinates":[-97.251588,32.662035],"type":"Point"}
}