{
  "type": "Feature",
  "properties": {
    "iso:country":"US",
    "sg:address":"305 N Main St",
    "sg:city":"Taylor",
    "sg:classifiers":[
        {
            "category":"Shopping",
            "type":"Retail Goods"
        }
    ],
    "sg:phone":"+1 512 352 3402",
    "sg:postcode":"76574",
    "sg:province":"TX",
    "sg:tags":[
        "cards",
        "sport",
        "baseball",
        "memorabilia"
    ],
    "wof:name":"Fun Cards",
    "wof:placetype":"venue"
},
  "geometry": {"coordinates":[-97.409768,30.570592],"type":"Point"}
}