{
  "type": "Feature",
  "properties": {
    "iso:country":"US",
    "sg:address":"401 W Woodard St",
    "sg:city":"Denison",
    "sg:classifiers":[
        {
            "category":"Retail",
            "subcategory":"Funeral Services",
            "type":"Services"
        }
    ],
    "sg:phone":"+1 903 465 2323",
    "sg:postcode":"75020",
    "sg:province":"TX",
    "sg:tags":[
        "director"
    ],
    "wof:name":"Bratcher Funeral Home",
    "wof:placetype":"venue"
},
  "geometry": {"coordinates":[-96.541479,33.756482],"type":"Point"}
}