{
  "type": "Feature",
  "properties": {
    "iso:country":"US",
    "sg:address":"7726 Colony Point Ct",
    "sg:city":"Houston",
    "sg:classifiers":[
        {
            "category":"Professional",
            "type":"Services"
        }
    ],
    "sg:phone":"+1 281 858 8089",
    "sg:postcode":"77095",
    "sg:province":"TX",
    "wof:name":"Laura G",
    "wof:placetype":"venue"
},
  "geometry": {"coordinates":[-95.672161,29.891153],"type":"Point"}
}