{
  "type": "Feature",
  "properties": {
    "iso:country":"US",
    "sg:address":"625 Church St",
    "sg:city":"Fairfield",
    "sg:classifiers":[
        {
            "category":"Retail",
            "subcategory":"Animal Services",
            "type":"Services"
        }
    ],
    "sg:phone":"+1 903 389 5586",
    "sg:postcode":"75840",
    "sg:province":"TX",
    "wof:name":"Robert Jackson",
    "wof:placetype":"venue"
},
  "geometry": {"coordinates":[-96.16745400000001,31.706136],"type":"Point"}
}