{
  "type": "Feature",
  "properties": {
    "iso:country":"US",
    "sg:address":"1816 Clarence St",
    "sg:city":"Dallas",
    "sg:classifiers":[
        {
            "category":"Professional",
            "subcategory":"Art Services",
            "type":"Services"
        }
    ],
    "sg:phone":"+1 214 428 4510",
    "sg:postcode":"75215",
    "sg:province":"TX",
    "sg:tags":[
        "photography",
        "commercial"
    ],
    "wof:name":"Seth A Smith Photographer",
    "wof:placetype":"venue"
},
  "geometry": {"coordinates":[-96.780028,32.766932],"type":"Point"}
}