{
  "type": "Feature",
  "properties": {
    "iso:country":"US",
    "sg:address":"2 Wake Robin Ct",
    "sg:city":"Spring",
    "sg:classifiers":[
        {
            "category":"Professional",
            "type":"Services"
        }
    ],
    "sg:phone":"+1 281 292 8688",
    "sg:postcode":"77380",
    "sg:province":"TX",
    "wof:name":"Douglas G Dellmore Inc",
    "wof:placetype":"venue"
},
  "geometry": {"coordinates":[-95.45530599999999,30.145524],"type":"Point"}
}