{
  "type": "Feature",
  "properties": {
    "iso:country":"US",
    "sg:address":"223 Old Tyler Rd",
    "sg:city":"Nacogdoches",
    "sg:classifiers":[
        {
            "category":"Wholesale",
            "subcategory":"Hardware",
            "type":"Manufacturing & Wholesale Goods"
        }
    ],
    "sg:phone":"+1 936 560 1852",
    "sg:postcode":"75961",
    "sg:province":"TX",
    "sg:tags":[
        "plumbing",
        "fixture",
        "supply"
    ],
    "wof:name":"Morrison Supply Co",
    "wof:placetype":"venue"
},
  "geometry": {"coordinates":[-94.659097,31.606735],"type":"Point"}
}