{
  "type": "Feature",
  "properties": {
    "iso:country":"US",
    "sg:address":"7303 19th St",
    "sg:city":"Lubbock",
    "sg:classifiers":[
        {
            "category":"Retail",
            "subcategory":"Repair Shop",
            "type":"Services"
        }
    ],
    "sg:phone":"+1 806 792 6495",
    "sg:postcode":"79407",
    "sg:province":"TX",
    "sg:tags":[
        "appliance"
    ],
    "wof:name":"Doctor Appliance",
    "wof:placetype":"venue"
},
  "geometry": {"coordinates":[-101.975936,33.577688],"type":"Point"}
}