{
  "type": "Feature",
  "properties": {
    "iso:country":"US",
    "sg:address":"2703 SW Military Dr",
    "sg:city":"San Antonio",
    "sg:classifiers":[
        {
            "category":"Banks & Credit Unions",
            "subcategory":"Bank",
            "type":"Services"
        }
    ],
    "sg:phone":"+1 210 220 4011",
    "sg:postcode":"78224",
    "sg:province":"TX",
    "wof:name":"Frost National Bank",
    "wof:placetype":"venue"
},
  "geometry": {"coordinates":[-98.541422,29.356707],"type":"Point"}
}