{
  "type": "Feature",
  "properties": {
    "iso:country":"US",
    "sg:address":"2801 Technology Dr",
    "sg:city":"Plano",
    "sg:classifiers":[
        {
            "category":"Shopping",
            "subcategory":"Department Store",
            "type":"Retail Goods"
        }
    ],
    "sg:phone":"+1 972 578 1782",
    "sg:postcode":"75074",
    "sg:province":"TX",
    "wof:name":"Mervyn's",
    "wof:placetype":"venue"
},
  "geometry": {"coordinates":[-96.67624499999999,33.012579],"type":"Point"}
}