{
  "type": "Feature",
  "properties": {
    "iso:country":"US",
    "sg:address":"2114 W 6th St",
    "sg:city":"Weslaco",
    "sg:classifiers":[
        {
            "category":"Real Estate",
            "subcategory":"Real Estate Agent",
            "type":"Services"
        }
    ],
    "sg:phone":"+1 956 968 8317",
    "sg:postcode":"78596",
    "sg:province":"TX",
    "wof:name":"Walker Realty",
    "wof:placetype":"venue"
},
  "geometry": {"coordinates":[-98.00779799999999,26.155144],"type":"Point"}
}