{
  "type": "Feature",
  "properties": {
    "iso:country":"US",
    "sg:address":"2609 N Grandview Ave",
    "sg:city":"Odessa",
    "sg:classifiers":[
        {
            "category":"Personal",
            "subcategory":"Beauty Salon",
            "type":"Services"
        }
    ],
    "sg:phone":"+1 432 272 5013",
    "sg:postcode":"79761",
    "sg:province":"TX",
    "sg:tags":[
        "shop"
    ],
    "wof:name":"Shannon Sullivan",
    "wof:placetype":"venue"
},
  "geometry": {"coordinates":[-102.347353,31.87548],"type":"Point"}
}