{
  "type": "Feature",
  "properties": {
    "iso:country":"US",
    "sg:address":"10703 Oak View Dr",
    "sg:city":"Austin",
    "sg:classifiers":[
        {
            "category":"Professional",
            "subcategory":"Accounting & Tax Preparation",
            "type":"Services"
        }
    ],
    "sg:phone":"+1 512 835 7369",
    "sg:postcode":"78759",
    "sg:province":"TX",
    "sg:tags":[
        "accountant"
    ],
    "wof:name":"Travis B Fuller",
    "wof:placetype":"venue"
},
  "geometry": {"coordinates":[-97.77261900000001,30.420204],"type":"Point"}
}