{
  "type": "Feature",
  "properties": {
    "iso:country":"US",
    "sg:address":"801 S Greenville Ave",
    "sg:city":"Allen",
    "sg:classifiers":[
        {
            "category":"Restaurant",
            "type":"Food & Drink"
        }
    ],
    "sg:phone":"+1 214 383 4789",
    "sg:postcode":"75002",
    "sg:province":"TX",
    "sg:tags":[
        "mexican"
    ],
    "wof:name":"El Grande Burrito",
    "wof:placetype":"venue"
},
  "geometry": {"coordinates":[-96.671043,33.08746],"type":"Point"}
}