{
  "type": "Feature",
  "properties": {
    "iso:country":"US",
    "sg:address":"6250 State Hwy 151",
    "sg:city":"San Antonio",
    "sg:classifiers":[
        {
            "category":"Building & Trades",
            "subcategory":"Construction",
            "type":"Services"
        }
    ],
    "sg:phone":"+1 210 599 7777",
    "sg:postcode":"78227",
    "sg:province":"TX",
    "wof:name":"Capital Excavation Company",
    "wof:placetype":"venue"
},
  "geometry": {"coordinates":[-98.61870500000001,29.433809],"type":"Point"}
}