{
  "type": "Feature",
  "properties": {
    "iso:country":"US",
    "sg:address":"1400 S Sherman St",
    "sg:city":"Richardson",
    "sg:classifiers":[
        {
            "category":"Professional",
            "subcategory":"Employment Agencies",
            "type":"Services"
        }
    ],
    "sg:phone":"+1 972 231 5117",
    "sg:postcode":"75081",
    "sg:province":"TX",
    "wof:name":"E D M Inc",
    "wof:placetype":"venue"
},
  "geometry": {"coordinates":[-96.745597,32.934016],"type":"Point"}
}