{
  "type": "Feature",
  "properties": {
    "iso:country":"US",
    "sg:address":"1608 Abbey Ln",
    "sg:city":"Cedar Park",
    "sg:classifiers":[
        {
            "category":"Wholesale",
            "subcategory":"Apparel",
            "type":"Manufacturing & Wholesale Goods"
        }
    ],
    "sg:phone":"+1 512 259 6705",
    "sg:postcode":"78613",
    "sg:province":"TX",
    "sg:tags":[
        "clothing"
    ],
    "wof:name":"Dallo Distributors",
    "wof:placetype":"venue"
},
  "geometry": {"coordinates":[-97.85626999999999,30.52233],"type":"Point"}
}