{
  "type": "Feature",
  "properties": {
    "iso:country":"US",
    "sg:address":"4509 Avenue A",
    "sg:city":"Austin",
    "sg:classifiers":[
        {
            "category":"Real Estate",
            "subcategory":"Real Estate Services",
            "type":"Services"
        }
    ],
    "sg:phone":"+1 512 784 9674",
    "sg:postcode":"78751",
    "sg:province":"TX",
    "sg:website":"www.ethreeproperties.com/",
    "wof:name":"Patty Sylvana - E3 Properties",
    "wof:placetype":"venue"
},
  "geometry": {"coordinates":[-97.731419,30.31101],"type":"Point"}
}