{
  "type": "Feature",
  "properties": {
    "iso:country":"US",
    "sg:address":"8903 Ave P",
    "sg:city":"Lubbock",
    "sg:classifiers":[
        {
            "category":"Building & Trades",
            "subcategory":"Construction",
            "type":"Services"
        }
    ],
    "sg:phone":"+1 806 748 4141",
    "sg:postcode":"79423",
    "sg:province":"TX",
    "sg:tags":[
        "insulation",
        "heat",
        "contractor"
    ],
    "wof:name":"Gale Insulation",
    "wof:placetype":"venue"
},
  "geometry": {"coordinates":[-101.852982,33.513251],"type":"Point"}
}