{
  "type": "Feature",
  "properties": {
    "iso:country":"US",
    "sg:address":"18226 Nassau Bay Dr",
    "sg:city":"Houston",
    "sg:classifiers":[
        {
            "category":"Recreation",
            "type":"Entertainment"
        }
    ],
    "sg:phone":"+1 281 335 1552",
    "sg:postcode":"77058",
    "sg:province":"TX",
    "sg:tags":[
        "club",
        "membership"
    ],
    "wof:name":"Football Little League In",
    "wof:placetype":"venue"
},
  "geometry": {"coordinates":[-95.09779,29.54232],"type":"Point"}
}