{
  "type": "Feature",
  "properties": {
    "iso:country":"US",
    "sg:address":"8050 North Fwy",
    "sg:city":"Houston",
    "sg:classifiers":[
        {
            "category":"Retail",
            "subcategory":"Auto Repair",
            "type":"Services"
        }
    ],
    "sg:phone":"+1 281 931 9693",
    "sg:postcode":"77037",
    "sg:province":"TX",
    "sg:tags":[
        "wrecker"
    ],
    "wof:name":"Kingston's Wrecker Svc",
    "wof:placetype":"venue"
},
  "geometry": {"coordinates":[-95.411523,29.876035],"type":"Point"}
}