{
  "type": "Feature",
  "properties": {
    "iso:country":"US",
    "sg:address":"7023 Cullen Blvd",
    "sg:city":"Houston",
    "sg:classifiers":[
        {
            "category":"Home & Garden",
            "subcategory":"Hardware",
            "type":"Retail Goods"
        }
    ],
    "sg:phone":"+1 713 748 0003",
    "sg:postcode":"77021",
    "sg:province":"TX",
    "sg:tags":[
        "store"
    ],
    "wof:name":"Snaps Hardware",
    "wof:placetype":"venue"
},
  "geometry": {"coordinates":[-95.354401,29.6868],"type":"Point"}
}