{
  "type": "Feature",
  "properties": {
    "iso:country":"US",
    "sg:address":"317 E Main St",
    "sg:city":"Bellville",
    "sg:classifiers":[
        {
            "category":"Shopping",
            "subcategory":"Bicycles & Sporting Goods",
            "type":"Retail Goods"
        },
        {
            "category":"Shopping",
            "subcategory":"Clothing, Apparel, & Fashions",
            "type":"Retail Goods"
        }
    ],
    "sg:phone":"+1 979 865 1458",
    "sg:postcode":"77418",
    "sg:province":"TX",
    "sg:tags":[
        "western",
        "wear"
    ],
    "sg:website":"www.rockingbcowboysupply.com",
    "wof:name":"Rockiing B Cowboy Supply Inc",
    "wof:placetype":"venue"
},
  "geometry": {"coordinates":[-96.255026,29.949378],"type":"Point"}
}