{
  "type": "Feature",
  "properties": {
    "iso:country":"US",
    "sg:address":"2607 S Houston St",
    "sg:city":"Amarillo",
    "sg:classifiers":[
        {
            "category":"Building & Trades",
            "subcategory":"Pest Control",
            "type":"Services"
        }
    ],
    "sg:phone":"+1 806 379 9868",
    "sg:postcode":"79103",
    "sg:province":"TX",
    "wof:name":"L & H Pest Control",
    "wof:placetype":"venue"
},
  "geometry": {"coordinates":[-101.824274,35.185067],"type":"Point"}
}