{
  "type": "Feature",
  "properties": {
    "iso:country":"US",
    "sg:address":"12025 North Fwy",
    "sg:city":"Houston",
    "sg:classifiers":[
        {
            "category":"Shopping",
            "type":"Retail Goods"
        }
    ],
    "sg:phone":"+1 281 877 0680",
    "sg:postcode":"77060",
    "sg:province":"TX",
    "sg:tags":[
        "cellular",
        "merchandise",
        "telephone"
    ],
    "wof:name":"Mobile Star Networks",
    "wof:placetype":"venue"
},
  "geometry": {"coordinates":[-95.41602399999999,29.944798],"type":"Point"}
}