{
  "type": "Feature",
  "properties": {
    "iso:country":"US",
    "sg:address":"2121 W Parmer Ln",
    "sg:city":"Austin",
    "sg:classifiers":[
        {
            "category":"Personal",
            "subcategory":"Beauty Salon",
            "type":"Services"
        }
    ],
    "sg:phone":"+1 512 977 9944",
    "sg:postcode":"78727",
    "sg:province":"TX",
    "wof:name":"Hair Studio",
    "wof:placetype":"venue"
},
  "geometry": {"coordinates":[-97.697908,30.416634],"type":"Point"}
}