{
  "type": "Feature",
  "properties": {
    "iso:country":"US",
    "sg:address":"702 S Nebraska Ave",
    "sg:city":"San Juan",
    "sg:classifiers":[
        {
            "category":"Manufacturing",
            "subcategory":"Printing",
            "type":"Manufacturing & Wholesale Goods"
        }
    ],
    "sg:phone":"+1 956 702 2044",
    "sg:postcode":"78589",
    "sg:province":"TX",
    "sg:tags":[
        "printer"
    ],
    "wof:name":"Express Printing",
    "wof:placetype":"venue"
},
  "geometry": {"coordinates":[-98.156098,26.186571],"type":"Point"}
}