{
  "type": "Feature",
  "properties": {
    "iso:country":"US",
    "sg:address":"19116 Timberland Blvd",
    "sg:city":"Porter",
    "sg:classifiers":[
        {
            "category":"Building & Trades",
            "subcategory":"Electrical",
            "type":"Services"
        },
        {
            "category":"Wholesale",
            "subcategory":"Electrical",
            "type":"Manufacturing & Wholesale Goods"
        }
    ],
    "sg:phone":"+1 713 694 7857",
    "sg:postcode":"77365",
    "sg:province":"TX",
    "sg:tags":[
        "alarm",
        "burglar",
        "system",
        "contractor"
    ],
    "wof:name":"Willis Charles Alarms",
    "wof:placetype":"venue"
},
  "geometry": {"coordinates":[-95.27318200000001,30.133755],"type":"Point"}
}