{
  "type": "Feature",
  "properties": {
    "iso:country":"US",
    "sg:address":"3272 State Hwy 154",
    "sg:city":"Marshall",
    "sg:classifiers":[
        {
            "category":"Building & Trades",
            "subcategory":"Construction",
            "type":"Services"
        }
    ],
    "sg:phone":"+1 903 923 0885",
    "sg:postcode":"75670",
    "sg:province":"TX",
    "sg:tags":[
        "general",
        "contractor"
    ],
    "wof:name":"Greenhead Construction Co",
    "wof:placetype":"venue"
},
  "geometry": {"coordinates":[-94.400037,32.560274],"type":"Point"}
}