{
  "type": "Feature",
  "properties": {
    "iso:country":"US",
    "sg:address":"909 Haven Way",
    "sg:city":"Brownsville",
    "sg:classifiers":[
        {
            "category":"Building & Trades",
            "subcategory":"Landscaping Services",
            "type":"Services"
        }
    ],
    "sg:phone":"+1 956 831 2997",
    "sg:postcode":"78521",
    "sg:province":"TX",
    "wof:name":"Ramirez Lawn & Tree Servi",
    "wof:placetype":"venue"
},
  "geometry": {"coordinates":[-97.38675600000001,25.926616],"type":"Point"}
}