{
  "type": "Feature",
  "properties": {
    "iso:country":"US",
    "sg:address":"916 Maple St",
    "sg:city":"Bonham",
    "sg:classifiers":[
        {
            "category":"Organizations",
            "subcategory":"Religious Organization",
            "type":"Services"
        }
    ],
    "sg:phone":"+1 903 583 7734",
    "sg:postcode":"75418",
    "sg:province":"TX",
    "sg:tags":[
        "church"
    ],
    "wof:name":"St Elizabeth Catholic Church",
    "wof:placetype":"venue"
},
  "geometry": {"coordinates":[-96.182267,33.582605],"type":"Point"}
}