{
  "type": "Feature",
  "properties": {
    "iso:country":"US",
    "sg:address":"865 W Miller Rd",
    "sg:city":"Garland",
    "sg:classifiers":[
        {
            "category":"Shopping",
            "subcategory":"Discount & Variety Stores",
            "type":"Retail Goods"
        }
    ],
    "sg:phone":"+1 972 926 0786",
    "sg:postcode":"75041",
    "sg:province":"TX",
    "sg:tags":[
        "merchandise",
        "general"
    ],
    "wof:name":"Dollar Bazaar",
    "wof:placetype":"venue"
},
  "geometry": {"coordinates":[-96.64309,32.894531],"type":"Point"}
}