{
  "type": "Feature",
  "properties": {
    "iso:country":"US",
    "sg:address":"7210 Bluefield Dr",
    "sg:city":"Dallas",
    "sg:classifiers":[
        {
            "category":"Shopping",
            "subcategory":"Computers & Home Electronics",
            "type":"Retail Goods"
        }
    ],
    "sg:phone":"+1 972 233 5769",
    "sg:postcode":"75248",
    "sg:province":"TX",
    "wof:name":"Expert Broadcast Electronics",
    "wof:placetype":"venue"
},
  "geometry": {"coordinates":[-96.781685,32.972077],"type":"Point"}
}