{
  "type": "Feature",
  "properties": {
    "iso:country":"US",
    "sg:address":"4200 N Frazier St",
    "sg:city":"Conroe",
    "sg:classifiers":[
        {
            "category":"Wholesale",
            "subcategory":"Hardware",
            "type":"Manufacturing & Wholesale Goods"
        },
        {
            "category":"Manufacturing",
            "subcategory":"Wood Products",
            "type":"Manufacturing & Wholesale Goods"
        }
    ],
    "sg:phone":"+1 936 856 2981",
    "sg:postcode":"77303",
    "sg:province":"TX",
    "sg:tags":[
        "broom",
        "mop",
        "handle",
        "mfg"
    ],
    "wof:name":"Owens Handle Company Inc",
    "wof:placetype":"venue"
},
  "geometry": {"coordinates":[-95.477548,30.368361],"type":"Point"}
}