{
  "type": "Feature",
  "properties": {
    "iso:country":"US",
    "sg:address":"3314 Knox St",
    "sg:city":"Dallas",
    "sg:classifiers":[
        {
            "category":"Restaurant",
            "type":"Food & Drink"
        }
    ],
    "sg:phone":"+1 214 526 3600",
    "sg:postcode":"75205",
    "sg:province":"TX",
    "sg:tags":[
        "eating"
    ],
    "wof:name":"Talenti",
    "wof:placetype":"venue"
},
  "geometry": {"coordinates":[-96.791032,32.824095],"type":"Point"}
}