{
  "type": "Feature",
  "properties": {
    "iso:country":"US",
    "sg:address":"11515 Chimney Rock Rd",
    "sg:city":"Houston",
    "sg:classifiers":[
        {
            "category":"Health Services",
            "subcategory":"Doctor",
            "type":"Services"
        }
    ],
    "sg:phone":"+1 713 728 3117",
    "sg:postcode":"77035",
    "sg:province":"TX",
    "sg:tags":[
        "podiatrist"
    ],
    "wof:name":"Wolf David S DPM",
    "wof:placetype":"venue"
},
  "geometry": {"coordinates":[-95.476997,29.656401],"type":"Point"}
}