{
  "type": "Feature",
  "properties": {
    "iso:country":"US",
    "sg:address":"13101 Preston Road Suite 220",
    "sg:city":"Dallas",
    "sg:classifiers":[
        {
            "category":"Real Estate",
            "subcategory":"Real Estate Services",
            "type":"Services"
        }
    ],
    "sg:phone":"+1 214 244 1244",
    "sg:postcode":"75240",
    "sg:province":"TX",
    "wof:name":"Forbes Shipper, LLC",
    "wof:placetype":"venue"
},
  "geometry": {"coordinates":[-96.806259,32.927695],"type":"Point"}
}