{
  "type": "Feature",
  "properties": {
    "iso:country":"US",
    "sg:address":"220 N Eastwood St",
    "sg:city":"Houston",
    "sg:classifiers":[
        {
            "category":"Building & Trades",
            "subcategory":"Construction",
            "type":"Services"
        }
    ],
    "sg:phone":"+1 713 923 4704",
    "sg:postcode":"77011",
    "sg:province":"TX",
    "sg:tags":[
        "contractor"
    ],
    "wof:name":"J T Tile",
    "wof:placetype":"venue"
},
  "geometry": {"coordinates":[-95.32808799999999,29.750575],"type":"Point"}
}