{
  "type": "Feature",
  "properties": {
    "iso:country":"US",
    "sg:address":"2414 Sweetgum Ct",
    "sg:city":"Rowlett",
    "sg:classifiers":[
        {
            "category":"Food & Beverages",
            "subcategory":"Groceries & Convenience Stores",
            "type":"Retail Goods"
        }
    ],
    "sg:phone":"+1 972 412 7746",
    "sg:postcode":"75089",
    "sg:province":"TX",
    "wof:name":"Unica Properties",
    "wof:placetype":"venue"
},
  "geometry": {"coordinates":[-96.58169700000001,32.926559],"type":"Point"}
}