{
  "type": "Feature",
  "properties": {
    "iso:country":"US",
    "sg:address":"3802 21st St",
    "sg:city":"Lubbock",
    "sg:classifiers":[
        {
            "category":"Health Services",
            "subcategory":"Doctor",
            "type":"Services"
        }
    ],
    "sg:phone":"+1 806 795 6417",
    "sg:postcode":"79410",
    "sg:province":"TX",
    "sg:tags":[
        "physician",
        "surgeon"
    ],
    "wof:name":"John C Dickey MD",
    "wof:placetype":"venue"
},
  "geometry": {"coordinates":[-101.897513,33.576008],"type":"Point"}
}