{
  "type": "Feature",
  "properties": {
    "iso:country":"US",
    "sg:address":"18250 Marsh Ln 515",
    "sg:city":"Dallas",
    "sg:classifiers":[
        {
            "category":"Shopping",
            "subcategory":"Clothing, Apparel, & Fashions",
            "type":"Retail Goods"
        }
    ],
    "sg:phone":"+1 512 351 0973",
    "sg:postcode":"75287",
    "sg:province":"TX",
    "sg:tags":[
        "t-shirt",
        "made",
        "vintage",
        "period",
        "shirts-custom",
        "clothing-collectible"
    ],
    "sg:website":"http://CARDGARMENTS.COM",
    "wof:name":"CAD GARMENTS",
    "wof:placetype":"venue"
},
  "geometry": {"coordinates":[-96.85553299999999,32.999217],"type":"Point"}
}