{
  "type": "Feature",
  "properties": {
    "iso:country":"US",
    "sg:address":"10448 Gulfdale St",
    "sg:city":"San Antonio",
    "sg:classifiers":[
        {
            "category":"Wholesale",
            "subcategory":"Machinery & Supplies",
            "type":"Manufacturing & Wholesale Goods"
        }
    ],
    "sg:phone":"+1 210 365 5606",
    "sg:postcode":"78216",
    "sg:province":"TX",
    "sg:tags":[
        "printer",
        "cartridge"
    ],
    "wof:name":"San Antonio Print Supply",
    "wof:placetype":"venue"
},
  "geometry": {"coordinates":[-98.490923,29.538144],"type":"Point"}
}