{
  "type": "Feature",
  "properties": {
    "iso:country":"US",
    "sg:address":"1508 Falcon Dr",
    "sg:city":"Desoto",
    "sg:classifiers":[
        {
            "category":"Wholesale",
            "subcategory":"Machinery & Supplies",
            "type":"Manufacturing & Wholesale Goods"
        }
    ],
    "sg:phone":"+1 972 228 2157",
    "sg:postcode":"75115",
    "sg:province":"TX",
    "sg:tags":[
        "packaging",
        "equipment",
        "strapping",
        "shipping"
    ],
    "sg:website":"www.dalwrap.com",
    "wof:name":"Dallas Strapping Company",
    "wof:placetype":"venue"
},
  "geometry": {"coordinates":[-96.851806,32.622369],"type":"Point"}
}