{
  "type": "Feature",
  "properties": {
    "iso:country":"US",
    "sg:address":"12315 Shadow Vista Dr",
    "sg:city":"Houston",
    "sg:classifiers":[
        {
            "category":"Professional",
            "type":"Services"
        }
    ],
    "sg:phone":"+1 281 497 5261",
    "sg:postcode":"77082",
    "sg:province":"TX",
    "wof:name":"Geofix-It Consulting",
    "wof:placetype":"venue"
},
  "geometry": {"coordinates":[-95.597703,29.723051],"type":"Point"}
}