{
  "type": "Feature",
  "properties": {
    "iso:country":"US",
    "sg:address":"36 Quintana Dr",
    "sg:city":"Galveston",
    "sg:classifiers":[
        {
            "category":"Professional",
            "type":"Services"
        }
    ],
    "sg:phone":"+1 409 741 0758",
    "sg:postcode":"77554",
    "sg:province":"TX",
    "wof:name":"Healthevolution L L C",
    "wof:placetype":"venue"
},
  "geometry": {"coordinates":[-94.872235,29.251165],"type":"Point"}
}