{
  "type": "Feature",
  "properties": {
    "iso:country":"US",
    "sg:address":"400 S Houston St",
    "sg:city":"Dallas",
    "sg:classifiers":[
        {
            "category":"Professional",
            "subcategory":"Lawyer & Legal Services",
            "type":"Services"
        },
        {
            "category":"Professional",
            "subcategory":"Business Services",
            "type":"Services"
        }
    ],
    "sg:phone":"+1 214 651 7111",
    "sg:postcode":"75202",
    "sg:province":"TX",
    "sg:tags":[
        "process",
        "server"
    ],
    "wof:name":"Lawyer's Civil Process Inc",
    "wof:placetype":"venue"
},
  "geometry": {"coordinates":[-96.80693100000001,32.775798],"type":"Point"}
}