{
  "type": "Feature",
  "properties": {
    "iso:country":"US",
    "sg:address":"7387 Co Rd 244",
    "sg:city":"Clyde",
    "sg:classifiers":[
        {
            "category":"Farming",
            "subcategory":"Livestock Farm",
            "type":"Manufacturing & Wholesale Goods"
        }
    ],
    "sg:phone":"+1 325 893 5383",
    "sg:postcode":"79510",
    "sg:province":"TX",
    "sg:tags":[
        "beef",
        "feedlot",
        "cattle"
    ],
    "wof:name":"Billy J Tarrant Farm",
    "wof:placetype":"venue"
},
  "geometry": {"coordinates":[-99.522666,32.341409],"type":"Point"}
}