{
  "type": "Feature",
  "properties": {
    "iso:country":"US",
    "sg:address":"18310 Rittenhouse Park Ct",
    "sg:city":"Spring",
    "sg:classifiers":[
        {
            "category":"Professional",
            "subcategory":"Computer Services",
            "type":"Services"
        }
    ],
    "sg:phone":"+1 281 655 0197",
    "sg:postcode":"77379",
    "sg:province":"TX",
    "sg:tags":[
        "design",
        "integrated",
        "system"
    ],
    "wof:name":"Messaging Solutions LLC",
    "wof:placetype":"venue"
},
  "geometry": {"coordinates":[-95.501232,30.03433],"type":"Point"}
}