{
  "type": "Feature",
  "properties": {
    "iso:country":"US",
    "sg:address":"1004 Padre Blvd",
    "sg:city":"South Padre Island",
    "sg:classifiers":[
        {
            "category":"Food & Beverages",
            "subcategory":"Liquor & Beverages",
            "type":"Retail Goods"
        }
    ],
    "sg:phone":"+1 956 761 4007",
    "sg:postcode":"78597",
    "sg:province":"TX",
    "sg:tags":[
        "alcoholic"
    ],
    "wof:name":"Bens Liquor Fine Wine & Tob",
    "wof:placetype":"venue"
},
  "geometry": {"coordinates":[-97.16526500000001,26.093668],"type":"Point"}
}