{
  "type": "Feature",
  "properties": {
    "iso:country":"US",
    "sg:address":"4021 Co Rd 177",
    "sg:city":"Anna",
    "sg:classifiers":[
        {
            "category":"Shopping",
            "subcategory":"Bicycles & Sporting Goods",
            "type":"Retail Goods"
        }
    ],
    "sg:phone":"+1 972 924 2370",
    "sg:postcode":"75409",
    "sg:province":"TX",
    "wof:name":"Rcs Unlimited",
    "wof:placetype":"venue"
},
  "geometry": {"coordinates":[-96.651234,33.384982],"type":"Point"}
}