{
  "type": "Feature",
  "properties": {
    "iso:country":"US",
    "sg:address":"1010 N Belt Line Rd Ste 101",
    "sg:city":"Mesquite",
    "sg:classifiers":[
        {
            "category":"Health Services",
            "subcategory":"Doctor",
            "type":"Services"
        }
    ],
    "sg:phone":"+1 972 288 4429",
    "sg:postcode":"75149",
    "sg:province":"TX",
    "sg:tags":[
        "orthopedist"
    ],
    "sg:website":"www.mesquiteorthopedicclinic.com",
    "wof:name":"Mesquite Orthopedic Clinic",
    "wof:placetype":"venue"
},
  "geometry": {"coordinates":[-96.59880099999999,32.775299],"type":"Point"}
}