{
  "type": "Feature",
  "properties": {
    "iso:country":"US",
    "sg:address":"6440 Tarascas Dr",
    "sg:city":"El Paso",
    "sg:classifiers":[
        {
            "category":"Recreation",
            "type":"Entertainment"
        }
    ],
    "sg:phone":"+1 915 584 4850",
    "sg:postcode":"79912",
    "sg:province":"TX",
    "wof:name":"Citys Originals",
    "wof:placetype":"venue"
},
  "geometry": {"coordinates":[-106.53402800000001,31.849458],"type":"Point"}
}