{
  "type": "Feature",
  "properties": {
    "iso:country":"US",
    "sg:address":"1001 S Wheeler St",
    "sg:city":"Jasper",
    "sg:classifiers":[
        {
            "category":"Professional",
            "type":"Services"
        }
    ],
    "sg:phone":"+1 409 698 9980",
    "sg:postcode":"75951",
    "sg:province":"TX",
    "wof:name":"Ginger Jar",
    "wof:placetype":"venue"
},
  "geometry": {"coordinates":[-93.995861,30.91168],"type":"Point"}
}