{
  "type": "Feature",
  "properties": {
    "iso:country":"US",
    "sg:address":"6836 Bee Caves Rd Ste 270",
    "sg:city":"Austin",
    "sg:classifiers":[
        {
            "category":"Professional",
            "type":"Services"
        },
        {
            "category":"Professional",
            "subcategory":"Art Services",
            "type":"Services"
        }
    ],
    "sg:phone":"+1 512 707 9641",
    "sg:postcode":"78746",
    "sg:province":"TX",
    "sg:tags":[
        "photographer"
    ],
    "sg:website":"www.austinimagery.com",
    "wof:name":"Austin Imagery Wedding & Portrait Photography",
    "wof:placetype":"venue"
},
  "geometry": {"coordinates":[-97.838402,30.300371],"type":"Point"}
}