{
  "type": "Feature",
  "properties": {
    "iso:country":"US",
    "sg:address":"1805 Pearl St",
    "sg:city":"Carrollton",
    "sg:classifiers":[
        {
            "category":"Education",
            "subcategory":"School",
            "type":"Public Place"
        }
    ],
    "sg:phone":"+1 972 323 6101",
    "sg:postcode":"75006",
    "sg:province":"TX",
    "wof:name":"Carrollton Elementary School",
    "wof:placetype":"venue"
},
  "geometry": {"coordinates":[-96.890407,32.956172],"type":"Point"}
}