{
  "type": "Feature",
  "properties": {
    "iso:country":"US",
    "sg:address":"207 Lane Dr",
    "sg:city":"Rosenberg",
    "sg:classifiers":[
        {
            "category":"Banks & Credit Unions",
            "subcategory":"Investment Brokerage",
            "type":"Services"
        }
    ],
    "sg:phone":"+1 281 342 5328",
    "sg:postcode":"77471",
    "sg:province":"TX",
    "sg:tags":[
        "security"
    ],
    "wof:name":"Automated Physical Security",
    "wof:placetype":"venue"
},
  "geometry": {"coordinates":[-95.77358,29.572874],"type":"Point"}
}