{
  "type": "Feature",
  "properties": {
    "iso:country":"US",
    "sg:address":"5309 Thornwood Cir",
    "sg:city":"Dickinson",
    "sg:classifiers":[
        {
            "category":"Professional",
            "subcategory":"Computer Services",
            "type":"Services"
        }
    ],
    "sg:phone":"+1 281 337 1822",
    "sg:postcode":"77539",
    "sg:province":"TX",
    "sg:tags":[
        "datum"
    ],
    "wof:name":"Sea Holm Consultant Svc",
    "wof:placetype":"venue"
},
  "geometry": {"coordinates":[-95.027061,29.469152],"type":"Point"}
}