{
  "type": "Feature",
  "properties": {
    "iso:country":"US",
    "sg:address":"1024 Indiana Ave",
    "sg:city":"Wichita Falls",
    "sg:classifiers":[
        {
            "category":"Home & Garden",
            "subcategory":"Furniture",
            "type":"Retail Goods"
        }
    ],
    "sg:phone":"+1 940 723 7396",
    "sg:postcode":"76301",
    "sg:province":"TX",
    "sg:tags":[
        "equipment"
    ],
    "wof:name":"Budget Furniture",
    "wof:placetype":"venue"
},
  "geometry": {"coordinates":[-98.488736,33.909832],"type":"Point"}
}