{
  "type": "Feature",
  "properties": {
    "iso:country":"US",
    "sg:address":"20131 US Hwy 59",
    "sg:city":"Humble",
    "sg:classifiers":[
        {
            "category":"Shopping",
            "subcategory":"Clothing, Apparel, & Fashions",
            "type":"Retail Goods"
        }
    ],
    "sg:phone":"+1 281 446 0286",
    "sg:postcode":"77338",
    "sg:province":"TX",
    "sg:tags":[
        "family"
    ],
    "wof:name":"Palais Royal",
    "wof:placetype":"venue"
},
  "geometry": {"coordinates":[-95.26742,30.007204],"type":"Point"}
}