{
  "type": "Feature",
  "properties": {
    "iso:country":"US",
    "sg:address":"5515 Strack Rd",
    "sg:city":"Houston",
    "sg:classifiers":[
        {
            "category":"Sports & Exercise",
            "subcategory":"Swimming Pool",
            "type":"Entertainment"
        }
    ],
    "sg:phone":"+1 281 397 7920",
    "sg:postcode":"77069",
    "sg:province":"TX",
    "sg:tags":[
        "pools-public"
    ],
    "wof:name":"Oaks of Huntwick Pool",
    "wof:placetype":"venue"
},
  "geometry": {"coordinates":[-95.524303,29.995335],"type":"Point"}
}