{
  "type": "Feature",
  "properties": {
    "iso:country":"US",
    "sg:address":"9030 Viscount Row",
    "sg:city":"Dallas",
    "sg:classifiers":[
        {
            "category":"Manufacturing",
            "subcategory":"Metals",
            "type":"Manufacturing & Wholesale Goods"
        }
    ],
    "sg:phone":"+1 214 358 5039",
    "sg:postcode":"75247",
    "sg:province":"TX",
    "sg:tags":[
        "production",
        "grinding"
    ],
    "sg:website":"www.retcotool.com",
    "wof:name":"Retco Tool Co",
    "wof:placetype":"venue"
},
  "geometry": {"coordinates":[-96.894887,32.81523],"type":"Point"}
}