{
  "type": "Feature",
  "properties": {
    "iso:country":"US",
    "sg:address":"412 W Post Office St",
    "sg:city":"Weimar",
    "sg:classifiers":[
        {
            "category":"Organizations",
            "subcategory":"Religious Organization",
            "type":"Services"
        }
    ],
    "sg:phone":"+1 979 725 6558",
    "sg:postcode":"78962",
    "sg:province":"TX",
    "sg:tags":[
        "clergy"
    ],
    "wof:name":"Mt Arie Baptist Parsonage",
    "wof:placetype":"venue"
},
  "geometry": {"coordinates":[-96.78548499999999,29.704018],"type":"Point"}
}