{
  "type": "Feature",
  "properties": {
    "iso:country":"US",
    "sg:address":"2012 Vista Trl",
    "sg:city":"Roanoke",
    "sg:classifiers":[
        {
            "category":"Professional",
            "subcategory":"Management & Consulting",
            "type":"Services"
        }
    ],
    "sg:phone":"+1 817 431 9039",
    "sg:postcode":"76262",
    "sg:province":"TX",
    "sg:tags":[
        "business"
    ],
    "wof:name":"In Springfield Consulting",
    "wof:placetype":"venue"
},
  "geometry": {"coordinates":[-97.20258200000001,32.952506],"type":"Point"}
}