{
  "type": "Feature",
  "properties": {
    "iso:country":"US",
    "sg:address":"1905 Wheless Ln",
    "sg:city":"Austin",
    "sg:classifiers":[
        {
            "category":"Shopping",
            "subcategory":"Books",
            "type":"Retail Goods"
        }
    ],
    "sg:phone":"+1 512 928 2117",
    "sg:postcode":"78723",
    "sg:province":"TX",
    "sg:tags":[
        "dealer"
    ],
    "wof:name":"Casa De Alabanza",
    "wof:placetype":"venue"
},
  "geometry": {"coordinates":[-97.688423,30.314151],"type":"Point"}
}