{
  "type": "Feature",
  "properties": {
    "iso:country":"US",
    "sg:address":"15920 FM 2964",
    "sg:city":"Whitehouse",
    "sg:classifiers":[
        {
            "category":"Building & Trades",
            "subcategory":"Cleaning & Sanitation",
            "type":"Services"
        }
    ],
    "sg:phone":"+1 903 839 2554",
    "sg:postcode":"75707",
    "sg:province":"TX",
    "sg:tags":[
        "janitor"
    ],
    "wof:name":"B'Clean",
    "wof:placetype":"venue"
},
  "geometry": {"coordinates":[-95.24994,32.250006],"type":"Point"}
}