{
  "type": "Feature",
  "properties": {
    "iso:country":"US",
    "sg:address":"22203 State Hwy 16",
    "sg:city":"Von Ormy",
    "sg:classifiers":[
        {
            "category":"Manufacturing",
            "subcategory":"Tools & Machinery",
            "type":"Manufacturing & Wholesale Goods"
        }
    ],
    "sg:phone":"+1 210 624 3432",
    "sg:postcode":"78073",
    "sg:province":"TX",
    "sg:tags":[
        "machine",
        "mfg"
    ],
    "wof:name":"Dale Wise Enterprises",
    "wof:placetype":"venue"
},
  "geometry": {"coordinates":[-98.585249,29.190725],"type":"Point"}
}