{
  "type": "Feature",
  "properties": {
    "iso:country":"US",
    "sg:address":"5601 Brodie Ln",
    "sg:city":"Austin",
    "sg:classifiers":[
        {
            "category":"Bakery",
            "type":"Food & Drink"
        }
    ],
    "sg:menulink":"http://www.allmenus.com/tx/austin/106823-marie-callenders/menu/",
    "sg:phone":"+1 512 899 1000",
    "sg:postcode":"78745",
    "sg:province":"TX",
    "sg:tags":[
        "american",
        "pastry"
    ],
    "wof:name":"Marie Callender's",
    "wof:placetype":"venue"
},
  "geometry": {"coordinates":[-97.82151,30.226863],"type":"Point"}
}