{
  "type": "Feature",
  "properties": {
    "iso:country":"US",
    "sg:address":"11111 W Hardy Rd",
    "sg:city":"Houston",
    "sg:classifiers":[
        {
            "category":"Food & Beverages",
            "subcategory":"Groceries & Convenience Stores",
            "type":"Retail Goods"
        }
    ],
    "sg:phone":"+1 713 699 2168",
    "sg:postcode":"77076",
    "sg:province":"TX",
    "sg:website":"www.featherpetro.com",
    "wof:name":"Stop N Save",
    "wof:placetype":"venue"
},
  "geometry": {"coordinates":[-95.364304,29.8645],"type":"Point"}
}