{
  "type": "Feature",
  "properties": {
    "iso:country":"US",
    "sg:address":"326 S 16th St",
    "sg:city":"La Porte",
    "sg:classifiers":[
        {
            "category":"Freight",
            "type":"Transportation"
        }
    ],
    "sg:phone":"+1 281 842 7040",
    "sg:postcode":"77571",
    "sg:province":"TX",
    "wof:name":"Bennett International Group",
    "wof:placetype":"venue"
},
  "geometry": {"coordinates":[-95.035966,29.662269],"type":"Point"}
}