{
  "type": "Feature",
  "properties": {
    "iso:country":"US",
    "sg:address":"10403 Stone Falls Ln",
    "sg:city":"Frisco",
    "sg:classifiers":[
        {
            "category":"Professional",
            "type":"Services"
        }
    ],
    "sg:phone":"+1 972 712 1560",
    "sg:postcode":"75035",
    "sg:province":"TX",
    "wof:name":"Creating Concepts",
    "wof:placetype":"venue"
},
  "geometry": {"coordinates":[-96.791572,33.139375],"type":"Point"}
}