{
  "type": "Feature",
  "properties": {
    "iso:country":"US",
    "sg:address":"801 E Denman Ave",
    "sg:city":"Lufkin",
    "sg:classifiers":[
        {
            "category":"Insurance",
            "subcategory":"Insurance Agent",
            "type":"Services"
        }
    ],
    "sg:phone":"+1 936 639 9851",
    "sg:postcode":"75901",
    "sg:province":"TX",
    "wof:name":"Mary Shanklin Insurance Agency",
    "wof:placetype":"venue"
},
  "geometry": {"coordinates":[-94.719881,31.32902],"type":"Point"}
}