{
  "type": "Feature",
  "properties": {
    "iso:country":"US",
    "sg:address":"2000 Montana Ave",
    "sg:city":"El Paso",
    "sg:classifiers":[
        {
            "category":"Restaurant",
            "type":"Food & Drink"
        }
    ],
    "sg:phone":"+1 915 533 0155",
    "sg:postcode":"79903",
    "sg:province":"TX",
    "sg:tags":[
        "eating"
    ],
    "wof:name":"Amigos Restaurant",
    "wof:placetype":"venue"
},
  "geometry": {"coordinates":[-106.471548,31.776832],"type":"Point"}
}