{
  "type": "Feature",
  "properties": {
    "iso:country":"US",
    "sg:address":"508 Pierce St",
    "sg:city":"Lindale",
    "sg:classifiers":[
        {
            "category":"Health Services",
            "subcategory":"Nursing And Care Facility",
            "type":"Services"
        }
    ],
    "sg:phone":"+1 903 882 6169",
    "sg:postcode":"75771",
    "sg:province":"TX",
    "sg:tags":[
        "home",
        "convalescent"
    ],
    "wof:name":"Colonial Nursing Center",
    "wof:placetype":"venue"
},
  "geometry": {"coordinates":[-95.40417600000001,32.510522],"type":"Point"}
}