{
  "type": "Feature",
  "properties": {
    "iso:country":"US",
    "sg:address":"400 Josephine St",
    "sg:city":"Austin",
    "sg:classifiers":[
        {
            "category":"Food Court",
            "type":"Food & Drink"
        },
        {
            "category":"Restaurant",
            "type":"Food & Drink"
        }
    ],
    "sg:phone":"+1 512 552 9034",
    "sg:postcode":"78704",
    "sg:province":"TX",
    "sg:tags":[
        "style",
        "family",
        "dessert",
        "french",
        "lunch",
        "stand",
        "brunch",
        "creperies",
        "breakfast"
    ],
    "sg:website":"www.fliphappycrepes.com",
    "wof:name":"Flip Happy Crepes",
    "wof:placetype":"venue"
},
  "geometry": {"coordinates":[-97.75863699999999,30.262318],"type":"Point"}
}