{
  "type": "Feature",
  "properties": {
    "iso:country":"US",
    "sg:address":"6612 Glade Dr",
    "sg:city":"Arlington",
    "sg:classifiers":[
        {
            "category":"Recreation",
            "type":"Entertainment"
        }
    ],
    "sg:phone":"+1 817 457 2285",
    "sg:postcode":"76001",
    "sg:province":"TX",
    "wof:name":"Colleen Dillon",
    "wof:placetype":"venue"
},
  "geometry": {"coordinates":[-97.14627,32.635859],"type":"Point"}
}