{
  "type": "Feature",
  "properties": {
    "iso:country":"US",
    "sg:address":"3010 Trawood Dr",
    "sg:city":"El Paso",
    "sg:classifiers":[
        {
            "category":"Professional",
            "subcategory":"Management & Consulting",
            "type":"Services"
        }
    ],
    "sg:phone":"+1 915 855 7505",
    "sg:postcode":"79936",
    "sg:province":"TX",
    "sg:tags":[
        "retail",
        "direct",
        "sales"
    ],
    "wof:name":"Water Express No 12",
    "wof:placetype":"venue"
},
  "geometry": {"coordinates":[-106.299184,31.765333],"type":"Point"}
}