{
  "type": "Feature",
  "properties": {
    "iso:country":"US",
    "sg:address":"565 FM 3040",
    "sg:city":"Lewisville",
    "sg:classifiers":[
        {
            "category":"Shopping",
            "subcategory":"Clothing, Apparel, & Fashions",
            "type":"Retail Goods"
        }
    ],
    "sg:phone":"+1 972 315 2554",
    "sg:postcode":"75067",
    "sg:province":"TX",
    "wof:name":"The Casual Male Big Tall 9500",
    "wof:placetype":"venue"
},
  "geometry": {"coordinates":[-96.974059,33.00524],"type":"Point"}
}