{
  "type": "Feature",
  "properties": {
    "iso:country":"US",
    "sg:address":"1839 SE Parkway St",
    "sg:city":"Azle",
    "sg:classifiers":[
        {
            "category":"Home & Garden",
            "subcategory":"Garden Supply",
            "type":"Retail Goods"
        }
    ],
    "sg:phone":"+1 817 238 9190",
    "sg:postcode":"76020",
    "sg:province":"TX",
    "sg:tags":[
        "repair"
    ],
    "wof:name":"Ricks Lawnmower Shop",
    "wof:placetype":"venue"
},
  "geometry": {"coordinates":[-97.519926,32.860975],"type":"Point"}
}