{
  "type": "Feature",
  "properties": {
    "iso:country":"US",
    "sg:address":"9631 Garden Path",
    "sg:city":"San Antonio",
    "sg:classifiers":[
        {
            "category":"Shopping",
            "subcategory":"Jewelry",
            "type":"Retail Goods"
        }
    ],
    "sg:phone":"+1 210 520 2409",
    "sg:postcode":"78254",
    "sg:province":"TX",
    "wof:name":"Normas Trinkets & Treasures",
    "wof:placetype":"venue"
},
  "geometry": {"coordinates":[-98.67468100000001,29.539816],"type":"Point"}
}