{
  "type": "Feature",
  "properties": {
    "iso:country":"US",
    "sg:address":"100 N Main St",
    "sg:city":"Lindale",
    "sg:classifiers":[
        {
            "category":"Mining & Drilling",
            "type":"Manufacturing & Wholesale Goods"
        }
    ],
    "sg:phone":"+1 903 882 8153",
    "sg:postcode":"75771",
    "sg:province":"TX",
    "sg:tags":[
        "oil",
        "gas",
        "producer"
    ],
    "wof:name":"Jerry KIDD Oil",
    "wof:placetype":"venue"
},
  "geometry": {"coordinates":[-95.40976000000001,32.516228],"type":"Point"}
}