{
  "type": "Feature",
  "properties": {
    "iso:country":"US",
    "sg:address":"7520 Lake Bonham Dr",
    "sg:city":"Bonham",
    "sg:classifiers":[
        {
            "category":"Recreation",
            "type":"Entertainment"
        }
    ],
    "sg:phone":"+1 903 583 8001",
    "sg:postcode":"75418",
    "sg:province":"TX",
    "sg:tags":[
        "concessionaire"
    ],
    "wof:name":"Lake Bonham Concession",
    "wof:placetype":"venue"
},
  "geometry": {"coordinates":[-96.137534,33.64421],"type":"Point"}
}