{
  "type": "Feature",
  "properties": {
    "iso:country":"US",
    "sg:address":"1850 Park Springs Blvd",
    "sg:city":"Arlington",
    "sg:classifiers":[
        {
            "category":"Retail",
            "subcategory":"Auto Repair",
            "type":"Services"
        }
    ],
    "sg:phone":"+1 817 303 5445",
    "sg:postcode":"76013",
    "sg:province":"TX",
    "sg:tags":[
        "repairing",
        "automobile",
        "general"
    ],
    "wof:name":"Don's Total Car Care",
    "wof:placetype":"venue"
},
  "geometry": {"coordinates":[-97.169096,32.715388],"type":"Point"}
}