{
  "type": "Feature",
  "properties": {
    "iso:country":"US",
    "sg:address":"905 E Goliad Ave",
    "sg:city":"Crockett",
    "sg:classifiers":[
        {
            "category":"Real Estate",
            "subcategory":"Real Estate Operator",
            "type":"Services"
        }
    ],
    "sg:phone":"+1 936 544 5083",
    "sg:postcode":"75835",
    "sg:province":"TX",
    "sg:tags":[
        "building",
        "apartment"
    ],
    "wof:name":"Butler House Apartments",
    "wof:placetype":"venue"
},
  "geometry": {"coordinates":[-95.45161899999999,31.317639],"type":"Point"}
}