{
  "type": "Feature",
  "properties": {
    "iso:country":"US",
    "sg:address":"4823 Rittiman Rd",
    "sg:city":"San Antonio",
    "sg:classifiers":[
        {
            "category":"Building & Trades",
            "subcategory":"Construction",
            "type":"Services"
        }
    ],
    "sg:phone":"+1 210 590 7569",
    "sg:postcode":"78218",
    "sg:province":"TX",
    "sg:tags":[
        "contractor"
    ],
    "wof:name":"Marble & Tile Service",
    "wof:placetype":"venue"
},
  "geometry": {"coordinates":[-98.393919,29.484143],"type":"Point"}
}