{
  "type": "Feature",
  "properties": {
    "iso:country":"US",
    "sg:address":"3213 Bond St",
    "sg:city":"Pasadena",
    "sg:classifiers":[
        {
            "category":"Shopping",
            "subcategory":"Hobbies, Toys, & Games",
            "type":"Retail Goods"
        }
    ],
    "sg:phone":"+1 713 477 1060",
    "sg:postcode":"77503",
    "sg:province":"TX",
    "sg:tags":[
        "shop"
    ],
    "wof:name":"Guerrero Reynaldo",
    "wof:placetype":"venue"
},
  "geometry": {"coordinates":[-95.163894,29.710862],"type":"Point"}
}