{
  "type": "Feature",
  "properties": {
    "iso:country":"US",
    "sg:address":"7631 Cook Rd",
    "sg:city":"Houston",
    "sg:classifiers":[
        {
            "category":"Personal",
            "subcategory":"Beauty Salon",
            "type":"Services"
        }
    ],
    "sg:phone":"+1 281 564 5000",
    "sg:postcode":"77072",
    "sg:province":"TX",
    "sg:tags":[
        "shop"
    ],
    "wof:name":"A Touch Of Elegance Hair Std",
    "wof:placetype":"venue"
},
  "geometry": {"coordinates":[-95.596012,29.695404],"type":"Point"}
}