{
  "type": "Feature",
  "properties": {
    "iso:country":"US",
    "sg:address":"3109 Glen Ora St",
    "sg:city":"Austin",
    "sg:classifiers":[
        {
            "category":"Health Services",
            "subcategory":"Doctor",
            "type":"Services"
        }
    ],
    "sg:phone":"+1 512 442 9677",
    "sg:postcode":"78704",
    "sg:province":"TX",
    "sg:tags":[
        "medical"
    ],
    "wof:name":"Mark G Shafer PHD",
    "wof:placetype":"venue"
},
  "geometry": {"coordinates":[-97.780832,30.240467],"type":"Point"}
}