{
  "type": "Feature",
  "properties": {
    "iso:country":"US",
    "sg:address":"602 Pena Dr",
    "sg:city":"Laredo",
    "sg:classifiers":[
        {
            "category":"Social Services",
            "subcategory":"Child Care",
            "type":"Services"
        }
    ],
    "sg:phone":"+1 956 712 9950",
    "sg:postcode":"78046",
    "sg:province":"TX",
    "sg:tags":[
        "day"
    ],
    "wof:name":"Golden Apple II",
    "wof:placetype":"venue"
},
  "geometry": {"coordinates":[-99.476281,27.364312],"type":"Point"}
}