{
  "type": "Feature",
  "properties": {
    "iso:country":"US",
    "sg:address":"205 Old Hewitt Rd",
    "sg:city":"Waco",
    "sg:classifiers":[
        {
            "category":"Banks & Credit Unions",
            "subcategory":"Bank",
            "type":"Services"
        }
    ],
    "sg:phone":"+1 254 772 6905",
    "sg:postcode":"76712",
    "sg:province":"TX",
    "sg:tags":[
        "loan",
        "real estate"
    ],
    "wof:name":"Texas Land Bank",
    "wof:placetype":"venue"
},
  "geometry": {"coordinates":[-97.21189,31.498626],"type":"Point"}
}