{
  "type": "Feature",
  "properties": {
    "iso:country":"US",
    "sg:address":"1615 Market Center Blvd",
    "sg:city":"Dallas",
    "sg:classifiers":[
        {
            "category":"Bars & Pubs",
            "type":"Food & Drink"
        }
    ],
    "sg:phone":"+1 214 745 9209",
    "sg:postcode":"75207",
    "sg:province":"TX",
    "sg:tags":[
        "lounge",
        "nightlife",
        "cocktail"
    ],
    "wof:name":"Joe's Lounge",
    "wof:placetype":"venue"
},
  "geometry": {"coordinates":[-96.822304,32.7929],"type":"Point"}
}