{
  "type": "Feature",
  "properties": {
    "iso:country":"US",
    "sg:address":"2525 Barge Ln",
    "sg:city":"Dallas",
    "sg:classifiers":[
        {
            "category":"Building & Trades",
            "subcategory":"Construction",
            "type":"Services"
        }
    ],
    "sg:phone":"+1 972 298 5566",
    "sg:postcode":"75212",
    "sg:province":"TX",
    "sg:tags":[
        "commercial",
        "contractor"
    ],
    "wof:name":"Texas Tunnel Technologies",
    "wof:placetype":"venue"
},
  "geometry": {"coordinates":[-96.92074599999999,32.778412],"type":"Point"}
}