{
  "type": "Feature",
  "properties": {
    "iso:country":"US",
    "sg:address":"9107 Mesa Dr",
    "sg:city":"Houston",
    "sg:classifiers":[
        {
            "category":"Retail",
            "subcategory":"Auto Repair",
            "type":"Services"
        }
    ],
    "sg:phone":"+1 713 633 0004",
    "sg:postcode":"77028",
    "sg:province":"TX",
    "sg:tags":[
        "truck"
    ],
    "wof:name":"Nab Truck & Auto Svc",
    "wof:placetype":"venue"
},
  "geometry": {"coordinates":[-95.26237,29.844032],"type":"Point"}
}