{
  "type": "Feature",
  "properties": {
    "iso:country":"US",
    "sg:address":"2615 Jacksboro Hwy",
    "sg:city":"River Oaks",
    "sg:classifiers":[
        {
            "category":"Professional",
            "type":"Services"
        }
    ],
    "sg:phone":"+1 817 624 0501",
    "sg:postcode":"76114",
    "sg:province":"TX",
    "sg:tags":[
        "establishment"
    ],
    "wof:name":"LA Fiesta Ballroom",
    "wof:placetype":"venue"
},
  "geometry": {"coordinates":[-97.38741899999999,32.788761],"type":"Point"}
}