{
  "type": "Feature",
  "properties": {
    "iso:country":"US",
    "sg:address":"2030 South St",
    "sg:city":"Beaumont",
    "sg:classifiers":[
        {
            "category":"Retail",
            "subcategory":"Auto Repair",
            "type":"Services"
        }
    ],
    "sg:phone":"+1 409 833 3901",
    "sg:postcode":"77701",
    "sg:province":"TX",
    "sg:tags":[
        "general"
    ],
    "wof:name":"Bob Jessie",
    "wof:placetype":"venue"
},
  "geometry": {"coordinates":[-94.116321,30.082006],"type":"Point"}
}