{
  "type": "Feature",
  "properties": {
    "iso:country":"US",
    "sg:address":"1006 N Front St",
    "sg:city":"Stanton",
    "sg:classifiers":[
        {
            "category":"Restaurant",
            "type":"Food & Drink"
        }
    ],
    "sg:phone":"+1 432 607 2222",
    "sg:postcode":"79782",
    "sg:province":"TX",
    "wof:name":"Taco King",
    "wof:placetype":"venue"
},
  "geometry": {"coordinates":[-101.779918,32.132682],"type":"Point"}
}