{
  "type": "Feature",
  "properties": {
    "iso:country":"US",
    "sg:address":"3260 E Euless Blvd",
    "sg:city":"Euless",
    "sg:classifiers":[
        {
            "category":"Food & Beverages",
            "subcategory":"Groceries & Convenience Stores",
            "type":"Retail Goods"
        }
    ],
    "sg:phone":"+1 817 358 9800",
    "sg:postcode":"76040",
    "sg:province":"TX",
    "sg:tags":[
        "product"
    ],
    "wof:name":"Chez Marie Exotic Food Intl",
    "wof:placetype":"venue"
},
  "geometry": {"coordinates":[-97.135273,32.816206],"type":"Point"}
}