{
  "type": "Feature",
  "properties": {
    "iso:country":"US",
    "sg:address":"113 Page St",
    "sg:city":"Longview",
    "sg:classifiers":[
        {
            "category":"Professional",
            "type":"Services"
        }
    ],
    "sg:phone":"+1 903 759 3161",
    "sg:postcode":"75604",
    "sg:province":"TX",
    "wof:name":"Daughters of Republic of",
    "wof:placetype":"venue"
},
  "geometry": {"coordinates":[-94.80372199999999,32.506419],"type":"Point"}
}