{
  "type": "Feature",
  "properties": {
    "iso:country":"US",
    "sg:address":"777 E Austin St",
    "sg:city":"Nacogdoches",
    "sg:classifiers":[
        {
            "category":"Banks & Credit Unions",
            "subcategory":"Investment Brokerage",
            "type":"Services"
        },
        {
            "category":"Banks & Credit Unions",
            "subcategory":"Bank",
            "type":"Services"
        },
        {
            "category":"Banks & Credit Unions",
            "subcategory":"Financial Services",
            "type":"Services"
        }
    ],
    "sg:phone":"+1 877 828 6508",
    "sg:postcode":"75965",
    "sg:province":"TX",
    "sg:tags":[
        "advisory",
        "mutual",
        "retirement",
        "annuity",
        "broker",
        "fund",
        "planning",
        "plan",
        "consultant",
        "security",
        "bond",
        "insurance",
        "stock"
    ],
    "sg:website":"http://edwardjones.com",
    "wof:name":"Edward Jones - GARY L RUSSELL",
    "wof:placetype":"venue"
},
  "geometry": {"coordinates":[-94.64130400000001,31.631951],"type":"Point"}
}