{
  "type": "Feature",
  "properties": {
    "iso:country":"US",
    "sg:address":"5870 State Hwy 6",
    "sg:city":"Houston",
    "sg:classifiers":[
        {
            "category":"Professional",
            "subcategory":"Computer Services",
            "type":"Services"
        },
        {
            "category":"Shopping",
            "subcategory":"Computers & Home Electronics",
            "type":"Retail Goods"
        }
    ],
    "sg:phone":"+1 281 858 8555",
    "sg:postcode":"77084",
    "sg:province":"TX",
    "sg:tags":[
        "county",
        "hardware",
        "software",
        "for",
        "government"
    ],
    "sg:website":"www.us-lgs.com",
    "wof:name":"Local Government Solutions",
    "wof:placetype":"venue"
},
  "geometry": {"coordinates":[-95.645186,29.861242],"type":"Point"}
}