{
  "type": "Feature",
  "properties": {
    "iso:country":"US",
    "sg:address":"801 W Division St",
    "sg:city":"Orange",
    "sg:classifiers":[
        {
            "category":"Government",
            "subcategory":"Court House",
            "type":"Public Place"
        }
    ],
    "sg:phone":"+1 409 883 6764",
    "sg:postcode":"77630",
    "sg:province":"TX",
    "sg:tags":[
        "county",
        "counsel"
    ],
    "wof:name":"County Attorney",
    "wof:placetype":"venue"
},
  "geometry": {"coordinates":[-93.736648,30.090134],"type":"Point"}
}