{
  "type": "Feature",
  "properties": {
    "iso:country":"US",
    "sg:address":"2841 Paso del Robles",
    "sg:city":"San Marcos",
    "sg:classifiers":[
        {
            "category":"Manufacturing",
            "subcategory":"Printing",
            "type":"Manufacturing & Wholesale Goods"
        }
    ],
    "sg:phone":"+1 512 396 6182",
    "sg:postcode":"78666",
    "sg:province":"TX",
    "sg:tags":[
        "book"
    ],
    "wof:name":"Design Concepts For History",
    "wof:placetype":"venue"
},
  "geometry": {"coordinates":[-98.000569,29.870048],"type":"Point"}
}