{
  "type": "Feature",
  "properties": {
    "iso:country":"US",
    "sg:address":"2511 E Hubbard St",
    "sg:city":"Mineral Wells",
    "sg:classifiers":[
        {
            "category":"Shopping",
            "subcategory":"Computers & Home Electronics",
            "type":"Retail Goods"
        }
    ],
    "sg:phone":"+1 940 328 6008",
    "sg:postcode":"76067",
    "sg:province":"TX",
    "wof:name":"Ace Computers",
    "wof:placetype":"venue"
},
  "geometry": {"coordinates":[-98.091956,32.809232],"type":"Point"}
}