{
  "type": "Feature",
  "properties": {
    "iso:country":"US",
    "sg:address":"6169 Cloudy Sky Dr",
    "sg:city":"El Paso",
    "sg:classifiers":[
        {
            "category":"Manufacturing",
            "subcategory":"Metals",
            "type":"Manufacturing & Wholesale Goods"
        }
    ],
    "sg:phone":"+1 915 329 1554",
    "sg:postcode":"79932",
    "sg:province":"TX",
    "sg:tags":[
        "repair",
        "fabrication",
        "aluminum",
        "stainless"
    ],
    "wof:name":"Dynamic Metals",
    "wof:placetype":"venue"
},
  "geometry": {"coordinates":[-106.582891,31.878554],"type":"Point"}
}