{
  "type": "Feature",
  "properties": {
    "iso:country":"US",
    "sg:address":"15815 Sylvan Lake Dr",
    "sg:city":"Houston",
    "sg:classifiers":[
        {
            "category":"Organizations",
            "subcategory":"Labor Organization",
            "type":"Services"
        }
    ],
    "sg:phone":"+1 281 218 7424",
    "sg:postcode":"77062",
    "sg:province":"TX",
    "wof:name":"Clear Lake Holdings Lc",
    "wof:placetype":"venue"
},
  "geometry": {"coordinates":[-95.11375,29.584342],"type":"Point"}
}