{
  "type": "Feature",
  "properties": {
    "iso:country":"US",
    "sg:address":"3385 N 3rd St",
    "sg:city":"Abilene",
    "sg:classifiers":[
        {
            "category":"Education",
            "subcategory":"Special Training",
            "type":"Public Place"
        }
    ],
    "sg:phone":"+1 325 673 3400",
    "sg:postcode":"79603",
    "sg:province":"TX",
    "sg:tags":[
        "self",
        "motivational",
        "improvement"
    ],
    "wof:name":"Living Well Ctr",
    "wof:placetype":"venue"
},
  "geometry": {"coordinates":[-99.76298,32.452941],"type":"Point"}
}