{
  "type": "Feature",
  "properties": {
    "iso:country":"US",
    "sg:address":"2300 Bell St",
    "sg:city":"Amarillo",
    "sg:classifiers":[
        {
            "category":"Wholesale",
            "subcategory":"Machinery & Supplies",
            "type":"Manufacturing & Wholesale Goods"
        },
        {
            "category":"Shopping",
            "subcategory":"Beauty & Cosmetics",
            "type":"Retail Goods"
        }
    ],
    "sg:phone":"+1 806 353 3525",
    "sg:postcode":"79106",
    "sg:province":"TX",
    "sg:tags":[
        "salon",
        "establishment",
        "merchandise"
    ],
    "wof:name":"Sally Beauty Supply 219",
    "wof:placetype":"venue"
},
  "geometry": {"coordinates":[-101.902349,35.187598],"type":"Point"}
}