{
  "type": "Feature",
  "properties": {
    "iso:country":"US",
    "sg:address":"699 N Pecan St",
    "sg:city":"Nash",
    "sg:classifiers":[
        {
            "category":"Building & Trades",
            "subcategory":"Electrical",
            "type":"Services"
        }
    ],
    "sg:phone":"+1 903 838 6892",
    "sg:postcode":"75569",
    "sg:province":"TX",
    "sg:tags":[
        "electric",
        "industrial",
        "contractors-commercial",
        "contractor"
    ],
    "wof:name":"Industrial Power Systems",
    "wof:placetype":"venue"
},
  "geometry": {"coordinates":[-94.12262,33.451191],"type":"Point"}
}