{
  "type": "Feature",
  "properties": {
    "iso:country":"US",
    "sg:address":"201 S Mineola St",
    "sg:city":"Midland",
    "sg:classifiers":[
        {
            "category":"Retail",
            "subcategory":"Auto Repair",
            "type":"Services"
        }
    ],
    "sg:phone":"+1 432 683 5113",
    "sg:postcode":"79701",
    "sg:province":"TX",
    "sg:tags":[
        "body",
        "automobile",
        "painting"
    ],
    "wof:name":"West Texas Collison Ctr",
    "wof:placetype":"venue"
},
  "geometry": {"coordinates":[-102.066947,31.995571],"type":"Point"}
}