{
  "type": "Feature",
  "properties": {
    "iso:country":"US",
    "sg:address":"3743 Erie St",
    "sg:city":"Houston",
    "sg:classifiers":[
        {
            "category":"Personal",
            "type":"Services"
        },
        {
            "category":"Recreation",
            "type":"Entertainment"
        }
    ],
    "sg:phone":"+1 713 643 9373",
    "sg:postcode":"77017",
    "sg:province":"TX",
    "sg:tags":[
        "psychic",
        "medium"
    ],
    "wof:name":"Alana's Psychic Readings",
    "wof:placetype":"venue"
},
  "geometry": {"coordinates":[-95.278902,29.688122],"type":"Point"}
}