{
  "type": "Feature",
  "properties": {
    "iso:country":"US",
    "sg:address":"8815 Industrial Dr",
    "sg:city":"Pearland",
    "sg:classifiers":[
        {
            "category":"Manufacturing",
            "subcategory":"Chemicals & Compounds",
            "type":"Manufacturing & Wholesale Goods"
        }
    ],
    "sg:phone":"+1 281 993 9991",
    "sg:postcode":"77584",
    "sg:province":"TX",
    "sg:tags":[
        "explosive",
        "mfg"
    ],
    "wof:name":"Owen Oil Tools",
    "wof:placetype":"venue"
},
  "geometry": {"coordinates":[-95.26519399999999,29.528999],"type":"Point"}
}