{
  "type": "Feature",
  "properties": {
    "iso:country":"US",
    "sg:address":"12501 W Hwy 71",
    "sg:city":"Austin",
    "sg:classifiers":[
        {
            "category":"Home & Garden",
            "subcategory":"Furniture",
            "type":"Retail Goods"
        }
    ],
    "sg:phone":"+1 512 263 1111",
    "sg:postcode":"78738",
    "sg:province":"TX",
    "sg:tags":[
        "swimming",
        "pool",
        "patio",
        "supply"
    ],
    "wof:name":"Patio Haus",
    "wof:placetype":"venue"
},
  "geometry": {"coordinates":[-97.93997299999999,30.306635],"type":"Point"}
}