{
  "type": "Feature",
  "properties": {
    "iso:country":"US",
    "sg:address":"2909 Thomas Ave",
    "sg:city":"Dallas",
    "sg:classifiers":[
        {
            "category":"Communications",
            "subcategory":"Film & Video Production",
            "type":"Services"
        }
    ],
    "sg:phone":"+1 214 468 8989",
    "sg:postcode":"75204",
    "sg:province":"TX",
    "sg:tags":[
        "motion",
        "picture",
        "studio",
        "producer"
    ],
    "wof:name":"Arrival Pictures",
    "wof:placetype":"venue"
},
  "geometry": {"coordinates":[-96.79619099999999,32.797371],"type":"Point"}
}