{
  "type": "Feature",
  "properties": {
    "iso:country":"US",
    "sg:address":"2804 Main St",
    "sg:city":"Dallas",
    "sg:classifiers":[
        {
            "category":"Personal",
            "subcategory":"Adult",
            "type":"Services"
        }
    ],
    "sg:phone":"+1 214 443 9868",
    "sg:postcode":"75226",
    "sg:province":"TX",
    "sg:tags":[
        "escort"
    ],
    "wof:name":"Dominating Ladies",
    "wof:placetype":"venue"
},
  "geometry": {"coordinates":[-96.782259,32.784261],"type":"Point"}
}