{
  "type": "Feature",
  "properties": {
    "iso:country":"US",
    "sg:address":"2000 Hwy 21 E",
    "sg:city":"Bryan",
    "sg:classifiers":[
        {
            "category":"Food & Beverages",
            "subcategory":"Groceries & Convenience Stores",
            "type":"Retail Goods"
        }
    ],
    "sg:phone":"+1 979 778 0120",
    "sg:postcode":"77803",
    "sg:province":"TX",
    "sg:tags":[
        "grocer"
    ],
    "wof:name":"Appletree Markets Inc",
    "wof:placetype":"venue"
},
  "geometry": {"coordinates":[-96.37067399999999,30.689352],"type":"Point"}
}