{
  "type": "Feature",
  "properties": {
    "iso:country":"US",
    "sg:address":"611 Mountain Crest Dr",
    "sg:city":"Wimberley",
    "sg:classifiers":[
        {
            "category":"Professional",
            "subcategory":"Business Services",
            "type":"Services"
        }
    ],
    "sg:phone":"+1 512 847 0242",
    "sg:postcode":"78676",
    "sg:province":"TX",
    "wof:name":"Watercolor Design",
    "wof:placetype":"venue"
},
  "geometry": {"coordinates":[-98.10323200000001,30.035296],"type":"Point"}
}