{
  "type": "Feature",
  "properties": {
    "iso:country":"US",
    "sg:address":"106 Pogue Ave",
    "sg:city":"Eastland",
    "sg:classifiers":[
        {
            "category":"Building & Trades",
            "subcategory":"Plumbing",
            "type":"Services"
        }
    ],
    "sg:phone":"+1 254 629 2251",
    "sg:postcode":"76448",
    "sg:province":"TX",
    "sg:tags":[
        "system",
        "heating",
        "contractor",
        "air conditioning"
    ],
    "sg:website":"www.jjair.net",
    "wof:name":"J & J Air Conditioning",
    "wof:placetype":"venue"
},
  "geometry": {"coordinates":[-98.797881,32.401618],"type":"Point"}
}