{
  "type": "Feature",
  "properties": {
    "iso:country":"US",
    "sg:address":"619 Mercury Ave",
    "sg:city":"Duncanville",
    "sg:classifiers":[
        {
            "category":"Building & Trades",
            "subcategory":"Construction",
            "type":"Services"
        }
    ],
    "sg:phone":"+1 972 283 8195",
    "sg:postcode":"75137",
    "sg:province":"TX",
    "sg:tags":[
        "contractor"
    ],
    "wof:name":"Affordable Fencing Dunn Right",
    "wof:placetype":"venue"
},
  "geometry": {"coordinates":[-96.922348,32.645081],"type":"Point"}
}