{
  "type": "Feature",
  "properties": {
    "iso:country":"US",
    "sg:address":"7777 Southwest Fwy",
    "sg:city":"Houston",
    "sg:classifiers":[
        {
            "category":"Health Services",
            "subcategory":"Doctor",
            "type":"Services"
        }
    ],
    "sg:phone":"+1 713 776 8888",
    "sg:postcode":"77074",
    "sg:province":"TX",
    "sg:tags":[
        "physician"
    ],
    "wof:name":"Memorial Neurology Consultants",
    "wof:placetype":"venue"
},
  "geometry": {"coordinates":[-95.52403,29.694089],"type":"Point"}
}