{
  "type": "Feature",
  "properties": {
    "iso:country":"US",
    "sg:address":"997 Junction Hwy",
    "sg:city":"Kerrville",
    "sg:classifiers":[
        {
            "category":"Ice Cream",
            "type":"Food & Drink"
        }
    ],
    "sg:menulink":"http://www.allmenus.com/tx/kerrville/162332-dairy-queen/menu/",
    "sg:phone":"+1 210 896 3737",
    "sg:postcode":"78028",
    "sg:province":"TX",
    "sg:tags":[
        "burger",
        "american"
    ],
    "wof:name":"Dairy Queen",
    "wof:placetype":"venue"
},
  "geometry": {"coordinates":[-99.162125,30.057814],"type":"Point"}
}