{
  "type": "Feature",
  "properties": {
    "iso:country":"US",
    "sg:address":"2439 Swiss Ave",
    "sg:city":"Dallas",
    "sg:classifiers":[
        {
            "category":"Freight",
            "type":"Transportation"
        }
    ],
    "sg:phone":"+1 214 515 0505",
    "sg:postcode":"75204",
    "sg:province":"TX",
    "sg:tags":[
        "warehouse",
        "commercial",
        "mover",
        "storage",
        "public"
    ],
    "sg:website":"publicstorage.com",
    "wof:name":"Public Storage",
    "wof:placetype":"venue"
},
  "geometry": {"coordinates":[-96.7901,32.7855],"type":"Point"}
}