{
  "type": "Feature",
  "properties": {
    "iso:country":"US",
    "sg:address":"7140 Jay Ln",
    "sg:city":"Azle",
    "sg:classifiers":[
        {
            "category":"Professional",
            "type":"Services"
        }
    ],
    "sg:phone":"+1 817 270 8226",
    "sg:postcode":"76020",
    "sg:province":"TX",
    "wof:name":"Auvenshine Etc",
    "wof:placetype":"venue"
},
  "geometry": {"coordinates":[-97.519094,32.973748],"type":"Point"}
}