{
  "type": "Feature",
  "properties": {
    "iso:country":"US",
    "sg:address":"9201 Mid Cities Blvd",
    "sg:city":"Fort Worth",
    "sg:classifiers":[
        {
            "category":"Building & Trades",
            "subcategory":"Construction",
            "type":"Services"
        }
    ],
    "sg:phone":"+1 817 656 5274",
    "sg:postcode":"76180",
    "sg:province":"TX",
    "sg:tags":[
        "home",
        "improvement"
    ],
    "wof:name":"Home Depot",
    "wof:placetype":"venue"
},
  "geometry": {"coordinates":[-97.18803200000001,32.861883],"type":"Point"}
}