{
  "type": "Feature",
  "properties": {
    "iso:country":"US",
    "sg:address":"6038 Sundance Ln",
    "sg:city":"San Antonio",
    "sg:classifiers":[
        {
            "category":"Bars & Pubs",
            "type":"Food & Drink"
        }
    ],
    "sg:phone":"+1 210 684 1125",
    "sg:postcode":"78238",
    "sg:province":"TX",
    "sg:tags":[
        "drinking",
        "furniture"
    ],
    "wof:name":"Relco",
    "wof:placetype":"venue"
},
  "geometry": {"coordinates":[-98.605419,29.475773],"type":"Point"}
}