{
  "type": "Feature",
  "properties": {
    "iso:country":"US",
    "sg:address":"3410 FM 1960 W",
    "sg:city":"Houston",
    "sg:classifiers":[
        {
            "category":"Retail",
            "subcategory":"Funeral Services",
            "type":"Services"
        }
    ],
    "sg:phone":"+1 281 397 0800",
    "sg:postcode":"77068",
    "sg:province":"TX",
    "wof:name":"SCI",
    "wof:placetype":"venue"
},
  "geometry": {"coordinates":[-95.477244,29.999497],"type":"Point"}
}