{
  "type": "Feature",
  "properties": {
    "iso:country":"US",
    "sg:address":"4332 Betty St",
    "sg:city":"Bellaire",
    "sg:classifiers":[
        {
            "category":"Professional",
            "subcategory":"Accounting & Tax Preparation",
            "type":"Services"
        }
    ],
    "sg:phone":"+1 713 664 6831",
    "sg:postcode":"77401",
    "sg:province":"TX",
    "sg:tags":[
        "consultant",
        "return"
    ],
    "wof:name":"Associated Tax Appraisers",
    "wof:placetype":"venue"
},
  "geometry": {"coordinates":[-95.448824,29.699929],"type":"Point"}
}