{
  "type": "Feature",
  "properties": {
    "iso:country":"US",
    "sg:address":"3148 Twisted Vine Ln",
    "sg:city":"Grand Prairie",
    "sg:classifiers":[
        {
            "category":"Professional",
            "subcategory":"Business Services",
            "type":"Services"
        }
    ],
    "sg:phone":"+1 972 741 8472",
    "sg:postcode":"75052",
    "sg:province":"TX",
    "wof:name":"World Websites Group",
    "wof:placetype":"venue"
},
  "geometry": {"coordinates":[-97.03926199999999,32.694314],"type":"Point"}
}