{
  "type": "Feature",
  "properties": {
    "iso:country":"US",
    "sg:address":"5930 Lyndon B Johnson Fwy Ste 437",
    "sg:city":"Dallas",
    "sg:classifiers":[
        {
            "category":"Personal",
            "type":"Services"
        },
        {
            "category":"Sports & Exercise",
            "subcategory":"Gym",
            "type":"Entertainment"
        },
        {
            "category":"Health Services",
            "subcategory":"Health Practitioner",
            "type":"Services"
        }
    ],
    "sg:phone":"+1 214 289 7215",
    "sg:postcode":"75240",
    "sg:province":"TX",
    "sg:tags":[
        "trainer",
        "control",
        "weight",
        "consultant",
        "dietitian",
        "program",
        "fitness",
        "nutritionist",
        "physical"
    ],
    "wof:name":"Roger E. Adams, Ph.D.",
    "wof:placetype":"venue"
},
  "geometry": {"coordinates":[-96.804672,32.925129],"type":"Point"}
}