{
  "type": "Feature",
  "properties": {
    "iso:country":"US",
    "sg:address":"509 E Newport Ln",
    "sg:city":"Mcallen",
    "sg:classifiers":[
        {
            "category":"Retail",
            "subcategory":"Portrait Studio",
            "type":"Services"
        }
    ],
    "sg:phone":"+1 956 687 4009",
    "sg:postcode":"78501",
    "sg:province":"TX",
    "sg:tags":[
        "photo"
    ],
    "wof:name":"J M Castellano Photography",
    "wof:placetype":"venue"
},
  "geometry": {"coordinates":[-98.21633300000001,26.189698],"type":"Point"}
}