{
  "type": "Feature",
  "properties": {
    "iso:country":"US",
    "sg:address":"614 Beaver Pl",
    "sg:city":"Greenville",
    "sg:classifiers":[
        {
            "category":"Wholesale",
            "subcategory":"Home Furnishings",
            "type":"Manufacturing & Wholesale Goods"
        }
    ],
    "sg:phone":"+1 903 455 8522",
    "sg:postcode":"75402",
    "sg:province":"TX",
    "sg:tags":[
        "curtain",
        "drapery"
    ],
    "wof:name":"Scotties Workroom",
    "wof:placetype":"venue"
},
  "geometry": {"coordinates":[-96.09117500000001,33.117399],"type":"Point"}
}