{
  "type": "Feature",
  "properties": {
    "iso:country":"US",
    "sg:address":"2010 SW H K Dodgen Loop",
    "sg:city":"Temple",
    "sg:classifiers":[
        {
            "category":"Communications",
            "subcategory":"Radio Station",
            "type":"Services"
        }
    ],
    "sg:phone":"+1 254 791 5251",
    "sg:postcode":"76504",
    "sg:province":"TX",
    "sg:tags":[
        "company",
        "broadcasting"
    ],
    "wof:name":"KVLT",
    "wof:placetype":"venue"
},
  "geometry": {"coordinates":[-97.376136,31.075774],"type":"Point"}
}