{
  "type": "Feature",
  "properties": {
    "iso:country":"US",
    "sg:address":"1340 Royal Oak Dr",
    "sg:city":"De Soto",
    "sg:classifiers":[
        {
            "category":"Social Services",
            "subcategory":"Job Training",
            "type":"Services"
        }
    ],
    "sg:phone":"+1 972 228 1864",
    "sg:postcode":"75115",
    "sg:province":"TX",
    "sg:tags":[
        "work"
    ],
    "wof:name":"J-Malak and Associates",
    "wof:placetype":"venue"
},
  "geometry": {"coordinates":[-96.838341,32.615174],"type":"Point"}
}