{
  "type": "Feature",
  "properties": {
    "iso:country":"US",
    "sg:address":"2350 County Road 202",
    "sg:city":"Burnet",
    "sg:classifiers":[
        {
            "category":"Manufacturing",
            "subcategory":"Wood Products",
            "type":"Manufacturing & Wholesale Goods"
        }
    ],
    "sg:phone":"+1 512 784 2512",
    "sg:postcode":"78611",
    "sg:province":"TX",
    "sg:tags":[
        "woodenware"
    ],
    "wof:name":"Custom Pins & More",
    "wof:placetype":"venue"
},
  "geometry": {"coordinates":[-98.15293800000001,30.875312],"type":"Point"}
}