{
  "type": "Feature",
  "properties": {
    "iso:country":"US",
    "sg:address":"13014 Thatcher Dr",
    "sg:city":"Houston",
    "sg:classifiers":[
        {
            "category":"Real Estate",
            "subcategory":"Developer",
            "type":"Services"
        }
    ],
    "sg:phone":"+1 281 558 9697",
    "sg:postcode":"77077",
    "sg:province":"TX",
    "wof:name":"Appaloosa Land Co Inc",
    "wof:placetype":"venue"
},
  "geometry": {"coordinates":[-95.618751,29.738364],"type":"Point"}
}