{
  "type": "Feature",
  "properties": {
    "iso:country":"US",
    "sg:address":"1215 Corona Dr",
    "sg:city":"Austin",
    "sg:classifiers":[
        {
            "category":"Coffee & Tea",
            "type":"Food & Drink"
        }
    ],
    "sg:phone":"+1 512 524 0014",
    "sg:postcode":"78723",
    "sg:province":"TX",
    "sg:website":"www.coronacafeaustin.com",
    "wof:name":"Corona Cafe",
    "wof:placetype":"venue"
},
  "geometry": {"coordinates":[-97.70479400000001,30.312378],"type":"Point"}
}