{
  "type": "Feature",
  "properties": {
    "iso:country":"US",
    "sg:address":"7959 Broadway",
    "sg:city":"San Antonio",
    "sg:classifiers":[
        {
            "category":"Sports & Exercise",
            "subcategory":"Gym",
            "type":"Entertainment"
        }
    ],
    "sg:phone":"+1 210 826 9080",
    "sg:postcode":"78209",
    "sg:province":"TX",
    "sg:tags":[
        "fitness",
        "physical",
        "facility"
    ],
    "wof:name":"Continuum Center For Mindful M",
    "wof:placetype":"venue"
},
  "geometry": {"coordinates":[-98.466284,29.506161],"type":"Point"}
}