{
  "type": "Feature",
  "properties": {
    "iso:country":"US",
    "sg:address":"12700 Hillcrest Rd Ste 145",
    "sg:city":"Dallas",
    "sg:classifiers":[
        {
            "category":"Professional",
            "subcategory":"Accounting & Tax Preparation",
            "type":"Services"
        }
    ],
    "sg:phone":"+1 972 661 0283",
    "sg:postcode":"75230",
    "sg:province":"TX",
    "sg:tags":[
        "accountant"
    ],
    "wof:name":"Messina Ronald B CPA",
    "wof:placetype":"venue"
},
  "geometry": {"coordinates":[-96.78620100000001,32.9212],"type":"Point"}
}