{
  "type": "Feature",
  "properties": {
    "iso:country":"US",
    "sg:address":"8909 Hinman St",
    "sg:city":"Houston",
    "sg:classifiers":[
        {
            "category":"Retail",
            "subcategory":"Storage",
            "type":"Services"
        }
    ],
    "sg:phone":"+1 713 649 5423",
    "sg:postcode":"77061",
    "sg:province":"TX",
    "sg:tags":[
        "household",
        "commercial"
    ],
    "sg:website":"http://www.texassstorage.com",
    "wof:name":"Texas Self Storage Hobby Airport",
    "wof:placetype":"venue"
},
  "geometry": {"coordinates":[-95.26753600000001,29.658199],"type":"Point"}
}