{
  "type": "Feature",
  "properties": {
    "iso:country":"US",
    "sg:address":"801 S Columbia Dr",
    "sg:city":"West Columbia",
    "sg:classifiers":[
        {
            "category":"Professional",
            "subcategory":"Lawyer & Legal Services",
            "type":"Services"
        }
    ],
    "sg:phone":"+1 979 345 5012",
    "sg:postcode":"77486",
    "sg:province":"TX",
    "sg:tags":[
        "attorney"
    ],
    "wof:name":"Laura R Cole",
    "wof:placetype":"venue"
},
  "geometry": {"coordinates":[-95.652907,29.137579],"type":"Point"}
}