{
  "type": "Feature",
  "properties": {
    "iso:country":"US",
    "sg:address":"1148 Pat Booker Rd",
    "sg:city":"Universal City",
    "sg:classifiers":[
        {
            "category":"Home & Garden",
            "subcategory":"Garden Supply",
            "type":"Retail Goods"
        }
    ],
    "sg:phone":"+1 210 658 3171",
    "sg:postcode":"78148",
    "sg:province":"TX",
    "sg:tags":[
        "nurseryman"
    ],
    "wof:name":"Calloway's Nursery Inc",
    "wof:placetype":"venue"
},
  "geometry": {"coordinates":[-98.298659,29.550726],"type":"Point"}
}