{
  "type": "Feature",
  "properties": {
    "iso:country":"US",
    "sg:address":"1326 Peacham Ct",
    "sg:city":"Fresno",
    "sg:classifiers":[
        {
            "category":"Professional",
            "type":"Services"
        }
    ],
    "sg:phone":"+1 281 431 8357",
    "sg:postcode":"77545",
    "sg:province":"TX",
    "sg:tags":[
        "establishment"
    ],
    "wof:name":"Chelsea's Bedroom Design",
    "wof:placetype":"venue"
},
  "geometry": {"coordinates":[-95.470935,29.522285],"type":"Point"}
}