{
  "type": "Feature",
  "properties": {
    "iso:country":"US",
    "sg:address":"822 Main St",
    "sg:city":"Houston",
    "sg:classifiers":[
        {
            "category":"Building & Trades",
            "subcategory":"Construction",
            "type":"Services"
        },
        {
            "category":"Home & Garden",
            "subcategory":"Furniture",
            "type":"Retail Goods"
        }
    ],
    "sg:phone":"+1 479 394 2566",
    "sg:postcode":"77002",
    "sg:province":"TX",
    "sg:tags":[
        "interior",
        "design",
        "store"
    ],
    "wof:name":"Kathy's Home Decor & Furnishings",
    "wof:placetype":"venue"
},
  "geometry": {"coordinates":[-95.364057,29.75841],"type":"Point"}
}