{
  "type": "Feature",
  "properties": {
    "iso:country":"US",
    "sg:address":"3258 E Plantation Dr",
    "sg:city":"La Porte",
    "sg:classifiers":[
        {
            "category":"Professional",
            "type":"Services"
        }
    ],
    "sg:phone":"+1 281 930 1968",
    "sg:postcode":"77571",
    "sg:province":"TX",
    "sg:tags":[
        "establishment"
    ],
    "wof:name":"C & W Classics",
    "wof:placetype":"venue"
},
  "geometry": {"coordinates":[-95.098866,29.661461],"type":"Point"}
}