{
  "type": "Feature",
  "properties": {
    "iso:country":"US",
    "sg:address":"1003 S Garfield St",
    "sg:city":"Midland",
    "sg:classifiers":[
        {
            "category":"Building & Trades",
            "subcategory":"Construction",
            "type":"Services"
        }
    ],
    "sg:phone":"+1 432 685 3733",
    "sg:postcode":"79701",
    "sg:province":"TX",
    "sg:tags":[
        "home",
        "builder"
    ],
    "wof:name":"Midland Gallery Homes LLC",
    "wof:placetype":"venue"
},
  "geometry": {"coordinates":[-102.09237,31.983507],"type":"Point"}
}