{
  "type": "Feature",
  "properties": {
    "iso:country":"US",
    "sg:address":"6906 Glenview Ln",
    "sg:city":"Colleyville",
    "sg:classifiers":[
        {
            "category":"Professional",
            "subcategory":"Business Services",
            "type":"Services"
        }
    ],
    "sg:phone":"+1 817 251 1864",
    "sg:postcode":"76034",
    "sg:province":"TX",
    "sg:tags":[
        "telemarketing"
    ],
    "wof:name":"Sitel",
    "wof:placetype":"venue"
},
  "geometry": {"coordinates":[-97.132035,32.90899],"type":"Point"}
}