{
  "type": "Feature",
  "properties": {
    "iso:country":"US",
    "sg:address":"308 Dunaway Ct",
    "sg:city":"Euless",
    "sg:classifiers":[
        {
            "category":"Organizations",
            "subcategory":"Religious Organization",
            "type":"Services"
        }
    ],
    "sg:phone":"+1 817 685 6597",
    "sg:postcode":"76040",
    "sg:province":"TX",
    "wof:name":"Faith & Philanthropy Institute",
    "wof:placetype":"venue"
},
  "geometry": {"coordinates":[-97.078,32.828443],"type":"Point"}
}