{
  "type": "Feature",
  "properties": {
    "iso:country":"US",
    "sg:address":"2719 Mier St",
    "sg:city":"Laredo",
    "sg:classifiers":[
        {
            "category":"Restaurant",
            "type":"Food & Drink"
        }
    ],
    "sg:phone":"+1 956 722 4918",
    "sg:postcode":"78043",
    "sg:province":"TX",
    "wof:name":"Hilda's Snack Bar & Party Supl",
    "wof:placetype":"venue"
},
  "geometry": {"coordinates":[-99.46818,27.510147],"type":"Point"}
}