{
  "type": "Feature",
  "properties": {
    "iso:country":"US",
    "sg:address":"3509 Cleveland St",
    "sg:city":"Dallas",
    "sg:classifiers":[
        {
            "category":"Real Estate",
            "subcategory":"Real Estate Agent",
            "type":"Services"
        }
    ],
    "sg:phone":"+1 214 762 5416",
    "sg:postcode":"75215",
    "sg:province":"TX",
    "wof:name":"Hummbee Real Estate Investments",
    "wof:placetype":"venue"
},
  "geometry": {"coordinates":[-96.77572000000001,32.756708],"type":"Point"}
}