{
  "type": "Feature",
  "properties": {
    "iso:country":"US",
    "sg:address":"200 W Walker St",
    "sg:city":"Breckenridge",
    "sg:classifiers":[
        {
            "category":"Government",
            "subcategory":"Court House",
            "type":"Public Place"
        }
    ],
    "sg:phone":"+1 254 559 3151",
    "sg:postcode":"76424",
    "sg:province":"TX",
    "sg:tags":[
        "county",
        "counsel",
        "system",
        "state"
    ],
    "wof:name":"Stephens County District Court",
    "wof:placetype":"venue"
},
  "geometry": {"coordinates":[-98.90507599999999,32.755423],"type":"Point"}
}