{
  "type": "Feature",
  "properties": {
    "iso:country":"US",
    "sg:address":"9424 State Hwy 154",
    "sg:city":"Big Sandy",
    "sg:classifiers":[
        {
            "category":"Building & Trades",
            "subcategory":"Construction",
            "type":"Services"
        }
    ],
    "sg:phone":"+1 903 725 5341",
    "sg:postcode":"75755",
    "sg:province":"TX",
    "sg:tags":[
        "contractor"
    ],
    "wof:name":"Buchanan Roofing",
    "wof:placetype":"venue"
},
  "geometry": {"coordinates":[-95.102694,32.753347],"type":"Point"}
}