{
  "type": "Feature",
  "properties": {
    "iso:country":"US",
    "sg:address":"2979 FM 2108",
    "sg:city":"Lufkin",
    "sg:classifiers":[
        {
            "category":"Food & Beverages",
            "subcategory":"Groceries & Convenience Stores",
            "type":"Retail Goods"
        },
        {
            "category":"Autos & Motor Vehicles",
            "subcategory":"Fuel & Gas Station",
            "type":"Retail Goods"
        }
    ],
    "sg:phone":"+1 936 634 2070",
    "sg:postcode":"75941",
    "sg:province":"TX",
    "sg:tags":[
        "station",
        "gasoline"
    ],
    "wof:name":"Fairview Mini Mart",
    "wof:placetype":"venue"
},
  "geometry": {"coordinates":[-94.721419,31.254553],"type":"Point"}
}