{
  "type": "Feature",
  "properties": {
    "iso:country":"US",
    "sg:address":"6608 Camelot Rd",
    "sg:city":"Fort Worth",
    "sg:classifiers":[
        {
            "category":"Organizations",
            "subcategory":"Non-profit Organization",
            "type":"Services"
        }
    ],
    "sg:phone":"+1 817 293 3499",
    "sg:postcode":"76134",
    "sg:province":"TX",
    "sg:tags":[
        "social"
    ],
    "wof:name":"National Property Management",
    "wof:placetype":"venue"
},
  "geometry": {"coordinates":[-97.340276,32.64969],"type":"Point"}
}