{
  "type": "Feature",
  "properties": {
    "iso:country":"US",
    "sg:address":"12640 E Northwest Hwy",
    "sg:city":"Dallas",
    "sg:classifiers":[
        {
            "category":"Building & Trades",
            "subcategory":"Construction",
            "type":"Services"
        }
    ],
    "sg:phone":"+1 972 686 7733",
    "sg:postcode":"75228",
    "sg:province":"TX",
    "sg:tags":[
        "residential",
        "remodeling"
    ],
    "wof:name":"American Tornado Master",
    "wof:placetype":"venue"
},
  "geometry": {"coordinates":[-96.662499,32.863955],"type":"Point"}
}