{
  "type": "Feature",
  "properties": {
    "iso:country":"US",
    "sg:address":"201 E 24th St",
    "sg:city":"Big Spring",
    "sg:classifiers":[
        {
            "category":"Organizations",
            "subcategory":"Religious Organization",
            "type":"Services"
        }
    ],
    "sg:phone":"+1 432 267 6543",
    "sg:postcode":"79720",
    "sg:province":"TX",
    "wof:name":"Primitive Baptist Church",
    "wof:placetype":"venue"
},
  "geometry": {"coordinates":[-101.466129,32.232348],"type":"Point"}
}