{
  "type": "Feature",
  "properties": {
    "iso:country":"US",
    "sg:address":"401 E Parker Ave",
    "sg:city":"Midland",
    "sg:classifiers":[
        {
            "category":"Education",
            "subcategory":"School",
            "type":"Public Place"
        }
    ],
    "sg:phone":"+1 432 689 1430",
    "sg:postcode":"79701",
    "sg:province":"TX",
    "wof:name":"Crockett Elementary School",
    "wof:placetype":"venue"
},
  "geometry": {"coordinates":[-102.071686,32.013252],"type":"Point"}
}