{
  "type": "Feature",
  "properties": {
    "iso:country":"US",
    "sg:address":"4436 Sherylwood Dr",
    "sg:city":"Port Arthur",
    "sg:classifiers":[
        {
            "category":"Building & Trades",
            "subcategory":"Construction",
            "type":"Services"
        }
    ],
    "sg:phone":"+1 409 727 4068",
    "sg:postcode":"77642",
    "sg:province":"TX",
    "sg:tags":[
        "home",
        "builder"
    ],
    "wof:name":"Heartfelt Homes Inc",
    "wof:placetype":"venue"
},
  "geometry": {"coordinates":[-93.962515,29.950693],"type":"Point"}
}