{
  "type": "Feature",
  "properties": {
    "iso:country":"US",
    "sg:address":"3135 Executive Dr",
    "sg:city":"San Angelo",
    "sg:classifiers":[
        {
            "category":"Organizations",
            "subcategory":"Professional Association",
            "type":"Services"
        }
    ],
    "sg:phone":"+1 325 223 2345",
    "sg:postcode":"76904",
    "sg:province":"TX",
    "wof:name":"American Heart Assn Regl Ofc",
    "wof:placetype":"venue"
},
  "geometry": {"coordinates":[-100.46279800000001,31.423141],"type":"Point"}
}