{
  "type": "Feature",
  "properties": {
    "iso:country":"US",
    "sg:address":"12311 Willow Bend Dr",
    "sg:city":"Austin",
    "sg:classifiers":[
        {
            "category":"Arts & Performance",
            "subcategory":"Theater",
            "type":"Entertainment"
        }
    ],
    "sg:phone":"+1 512 837 7858",
    "sg:postcode":"78758",
    "sg:province":"TX",
    "sg:tags":[
        "musician"
    ],
    "wof:name":"Time Warp",
    "wof:placetype":"venue"
},
  "geometry": {"coordinates":[-97.68039,30.408215],"type":"Point"}
}