{
  "type": "Feature",
  "properties": {
    "iso:country":"US",
    "sg:address":"4811 Ethel St",
    "sg:city":"Pearland",
    "sg:classifiers":[
        {
            "category":"Building & Trades",
            "subcategory":"Construction",
            "type":"Services"
        }
    ],
    "sg:phone":"+1 281 460 4849",
    "sg:postcode":"77584",
    "sg:province":"TX",
    "sg:tags":[
        "wallcoverings-installation",
        "wallpaper",
        "painting",
        "contractor"
    ],
    "wof:name":"Peacock Painting",
    "wof:placetype":"venue"
},
  "geometry": {"coordinates":[-95.34191199999999,29.53987],"type":"Point"}
}