{
  "type": "Feature",
  "properties": {
    "iso:country":"US",
    "sg:address":"10111 Elm Knoll Trl",
    "sg:city":"Houston",
    "sg:classifiers":[
        {
            "category":"Manufacturing",
            "subcategory":"Metals",
            "type":"Manufacturing & Wholesale Goods"
        }
    ],
    "sg:phone":"+1 281 821 7887",
    "sg:postcode":"77064",
    "sg:province":"TX",
    "sg:tags":[
        "mfg",
        "metalwork",
        "structural"
    ],
    "wof:name":"World Wide Fabricators Inc",
    "wof:placetype":"venue"
},
  "geometry": {"coordinates":[-95.57737400000001,29.921257],"type":"Point"}
}