{
  "type": "Feature",
  "properties": {
    "iso:country":"US",
    "sg:address":"17737 Co Rd 15",
    "sg:city":"Tyler",
    "sg:classifiers":[
        {
            "category":"Manufacturing",
            "subcategory":"Metals",
            "type":"Manufacturing & Wholesale Goods"
        }
    ],
    "sg:phone":"+1 903 839 7508",
    "sg:postcode":"75703",
    "sg:province":"TX",
    "sg:tags":[
        "shop",
        "novelty",
        "specialty",
        "gift",
        "mfg"
    ],
    "wof:name":"Jennings Fabrications & Creat",
    "wof:placetype":"venue"
},
  "geometry": {"coordinates":[-95.28742099999999,32.223126],"type":"Point"}
}