{
  "type": "Feature",
  "properties": {
    "iso:country":"US",
    "sg:address":"206 S Stewart Rd",
    "sg:city":"Mission",
    "sg:classifiers":[
        {
            "category":"Real Estate",
            "subcategory":"Real Estate Operator",
            "type":"Services"
        }
    ],
    "sg:phone":"+1 956 585 6594",
    "sg:postcode":"78572",
    "sg:province":"TX",
    "sg:tags":[
        "site"
    ],
    "wof:name":"W & I Resorts",
    "wof:placetype":"venue"
},
  "geometry": {"coordinates":[-98.303934,26.200614],"type":"Point"}
}