{
  "type": "Feature",
  "properties": {
    "iso:country":"US",
    "sg:address":"2040 N Redbud Blvd Ste 120",
    "sg:city":"Mckinney",
    "sg:phone":"+1 214 544 9556",
    "sg:postcode":"75069",
    "sg:province":"TX",
    "sg:website":"http://www.sfodallas.com",
    "wof:name":"Surplus Floors Outlet",
    "wof:placetype":"venue"
},
  "geometry": {"coordinates":[-96.62836900000001,33.2206],"type":"Point"}
}