{
  "type": "Feature",
  "properties": {
    "iso:country":"US",
    "sg:address":"3327 S Ewing Ave",
    "sg:city":"Dallas",
    "sg:classifiers":[
        {
            "category":"Freight",
            "type":"Transportation"
        }
    ],
    "sg:phone":"+1 214 375 7512",
    "sg:postcode":"75216",
    "sg:province":"TX",
    "sg:tags":[
        "operator",
        "trucking"
    ],
    "wof:name":"Billy Thurman Trucking LLC",
    "wof:placetype":"venue"
},
  "geometry": {"coordinates":[-96.81093199999999,32.703391],"type":"Point"}
}