{
  "type": "Feature",
  "properties": {
    "iso:country":"US",
    "sg:address":"840 Nantucket Dr",
    "sg:city":"Beaumont",
    "sg:classifiers":[
        {
            "category":"Banks & Credit Unions",
            "subcategory":"Financial Services",
            "type":"Services"
        }
    ],
    "sg:phone":"+1 409 860 4409",
    "sg:postcode":"77706",
    "sg:province":"TX",
    "sg:tags":[
        "trust",
        "management"
    ],
    "wof:name":"Salim Family Investments",
    "wof:placetype":"venue"
},
  "geometry": {"coordinates":[-94.182211,30.081804],"type":"Point"}
}