{
  "type": "Feature",
  "properties": {
    "iso:country":"US",
    "sg:address":"1710 Ripple Creek Ct",
    "sg:city":"Missouri City",
    "sg:classifiers":[
        {
            "category":"Professional",
            "type":"Services"
        }
    ],
    "sg:phone":"+1 281 261 2333",
    "sg:postcode":"77489",
    "sg:province":"TX",
    "wof:name":"Kenneth Allen",
    "wof:placetype":"venue"
},
  "geometry": {"coordinates":[-95.533145,29.601139],"type":"Point"}
}