{
  "type": "Feature",
  "properties": {
    "iso:country":"US",
    "sg:address":"124 W Davis St",
    "sg:city":"Conroe",
    "sg:classifiers":[
        {
            "category":"Professional",
            "type":"Services"
        }
    ],
    "sg:phone":"+1 936 539 3661",
    "sg:postcode":"77301",
    "sg:province":"TX",
    "sg:tags":[
        "establishment"
    ],
    "wof:name":"Grogan Mineral Co Inc",
    "wof:placetype":"venue"
},
  "geometry": {"coordinates":[-95.45623500000001,30.312236],"type":"Point"}
}