{
  "type": "Feature",
  "properties": {
    "iso:country":"US",
    "sg:address":"18209 Egret Bay Blvd",
    "sg:city":"Houston",
    "sg:classifiers":[
        {
            "category":"Shopping",
            "subcategory":"Clothing, Apparel, & Fashions",
            "type":"Retail Goods"
        }
    ],
    "sg:phone":"+1 281 335 7946",
    "sg:postcode":"77058",
    "sg:province":"TX",
    "wof:name":"Wet Spot Swimwear",
    "wof:placetype":"venue"
},
  "geometry": {"coordinates":[-95.099653,29.539786],"type":"Point"}
}