{
  "type": "Feature",
  "properties": {
    "iso:country":"US",
    "sg:address":"1807 Dory Ln",
    "sg:city":"Irving",
    "sg:classifiers":[
        {
            "category":"Building & Trades",
            "subcategory":"Cleaning & Sanitation",
            "type":"Services"
        }
    ],
    "sg:phone":"+1 972 445 0578",
    "sg:postcode":"75061",
    "sg:province":"TX",
    "sg:tags":[
        "maintenance"
    ],
    "wof:name":"Homestyle Maid Service",
    "wof:placetype":"venue"
},
  "geometry": {"coordinates":[-96.93137,32.83496],"type":"Point"}
}