{
  "type": "Feature",
  "properties": {
    "iso:country":"US",
    "sg:address":"2354 E Northwest Pkwy",
    "sg:city":"Southlake",
    "sg:classifiers":[
        {
            "category":"Building & Trades",
            "subcategory":"Plumbing",
            "type":"Services"
        }
    ],
    "sg:phone":"+1 817 912 0750",
    "sg:postcode":"76092",
    "sg:province":"TX",
    "sg:tags":[
        "product",
        "management",
        "energy",
        "system"
    ],
    "wof:name":"Strategic Energy",
    "wof:placetype":"venue"
},
  "geometry": {"coordinates":[-97.11376300000001,32.943648],"type":"Point"}
}