{
  "type": "Feature",
  "properties": {
    "iso:country":"US",
    "sg:address":"3719 Leopard St",
    "sg:city":"Corpus Christi",
    "sg:classifiers":[
        {
            "category":"Shopping",
            "subcategory":"Discount & Variety Stores",
            "type":"Retail Goods"
        },
        {
            "category":"Shopping",
            "subcategory":"Department Store",
            "type":"Retail Goods"
        }
    ],
    "sg:phone":"+1 361 888 8573",
    "sg:postcode":"78408",
    "sg:province":"TX",
    "sg:tags":[
        "shop"
    ],
    "wof:name":"Family Dollar Stores",
    "wof:placetype":"venue"
},
  "geometry": {"coordinates":[-97.432872,27.797034],"type":"Point"}
}