{
  "type": "Feature",
  "properties": {
    "iso:country":"US",
    "sg:address":"1222 Edris Dr",
    "sg:city":"San Antonio",
    "sg:classifiers":[
        {
            "category":"Wholesale",
            "subcategory":"Machinery & Supplies",
            "type":"Manufacturing & Wholesale Goods"
        }
    ],
    "sg:phone":"+1 210 927 7961",
    "sg:postcode":"78224",
    "sg:province":"TX",
    "sg:tags":[
        "equipment",
        "hydraulic"
    ],
    "wof:name":"J C Hydraulics",
    "wof:placetype":"venue"
},
  "geometry": {"coordinates":[-98.52517,29.328987],"type":"Point"}
}