{
  "type": "Feature",
  "properties": {
    "iso:country":"US",
    "sg:address":"Office 595 Orleans St. Ste. 410 Church Services 701 Main Street Beaumont Civic Center",
    "sg:city":"Beaumont",
    "sg:classifiers":[
        {
            "category":"Place Of Worship",
            "subcategory":"Church",
            "type":"Public Place"
        },
        {
            "category":"Place Of Worship",
            "type":"Public Place"
        },
        {
            "category":"Building & Trades",
            "subcategory":"Pest Control",
            "type":"Services"
        }
    ],
    "sg:phone":"+1 409 833 7771",
    "sg:postcode":"77701",
    "sg:province":"TX",
    "sg:tags":[
        "churches-holiness",
        "gospel",
        "churches-unity",
        "churches-full",
        "churches-non-denominational"
    ],
    "sg:website":"http://www.togodbethegloryministries.ws",
    "wof:name":"To GOD be the GLORY Ministries",
    "wof:placetype":"venue"
},
  "geometry": {"coordinates":[-94.095917,30.08247],"type":"Point"}
}