{
  "type": "Feature",
  "properties": {
    "iso:country":"US",
    "sg:address":"727 E Main St",
    "sg:city":"Uvalde",
    "sg:classifiers":[
        {
            "category":"Banks & Credit Unions",
            "subcategory":"Bank",
            "type":"Services"
        }
    ],
    "sg:phone":"+1 830 278 1147",
    "sg:postcode":"78801",
    "sg:province":"TX",
    "wof:name":"National American Bank",
    "wof:placetype":"venue"
},
  "geometry": {"coordinates":[-99.773951,29.213525],"type":"Point"}
}