{
  "type": "Feature",
  "properties": {
    "iso:country":"US",
    "sg:address":"800 N Shoreline Blvd",
    "sg:city":"Corpus Christi",
    "sg:classifiers":[
        {
            "category":"Professional",
            "type":"Services"
        },
        {
            "category":"Mining & Drilling",
            "type":"Manufacturing & Wholesale Goods"
        }
    ],
    "sg:phone":"+1 361 884 2443",
    "sg:postcode":"78401",
    "sg:province":"TX",
    "sg:tags":[
        "consultant",
        "exploration",
        "geological"
    ],
    "wof:name":"Suemaur Exploration Inc",
    "wof:placetype":"venue"
},
  "geometry": {"coordinates":[-97.39156800000001,27.799605],"type":"Point"}
}