{
  "type": "Feature",
  "properties": {
    "iso:country":"US",
    "sg:address":"1235b Clear Lake City Blvd",
    "sg:city":"Houston",
    "sg:classifiers":[
        {
            "category":"Restaurant",
            "type":"Food & Drink"
        }
    ],
    "sg:menulink":"http://www.allmenus.com/tx/houston/62683-subway/menu/",
    "sg:phone":"+1 281 461 6162",
    "sg:postcode":"77062",
    "sg:province":"TX",
    "sg:tags":[
        "american",
        "sandwich"
    ],
    "wof:name":"Subway",
    "wof:placetype":"venue"
},
  "geometry": {"coordinates":[-95.154257,29.582136],"type":"Point"}
}