{
  "type": "Feature",
  "properties": {
    "iso:country":"US",
    "sg:address":"731 Sherman St",
    "sg:city":"Richardson",
    "sg:classifiers":[
        {
            "category":"Shopping",
            "type":"Retail Goods"
        }
    ],
    "sg:phone":"+1 972 231 4426",
    "sg:postcode":"75081",
    "sg:province":"TX",
    "sg:tags":[
        "stone",
        "s",
        "merchandise",
        "mfg"
    ],
    "wof:name":"A Trophy Company",
    "wof:placetype":"venue"
},
  "geometry": {"coordinates":[-96.739626,32.941745],"type":"Point"}
}