{
  "type": "Feature",
  "properties": {
    "iso:country":"US",
    "sg:address":"9316 Windy Crest Dr",
    "sg:city":"Dallas",
    "sg:classifiers":[
        {
            "category":"Professional",
            "type":"Services"
        }
    ],
    "sg:phone":"+1 214 341 7230",
    "sg:postcode":"75243",
    "sg:province":"TX",
    "sg:tags":[
        "lecturer"
    ],
    "wof:name":"Steven N Blair",
    "wof:placetype":"venue"
},
  "geometry": {"coordinates":[-96.74005099999999,32.907132],"type":"Point"}
}