{
  "type": "Feature",
  "properties": {
    "iso:country":"US",
    "sg:address":"810 W Arapaho Rd",
    "sg:city":"Richardson",
    "sg:classifiers":[
        {
            "category":"Health Services",
            "subcategory":"Doctor",
            "type":"Services"
        }
    ],
    "sg:phone":"+1 972 238 9999",
    "sg:postcode":"75080",
    "sg:province":"TX",
    "sg:tags":[
        "dentist"
    ],
    "wof:name":"Complete Dental Care Pa",
    "wof:placetype":"venue"
},
  "geometry": {"coordinates":[-96.74857900000001,32.962928],"type":"Point"}
}