{
  "type": "Feature",
  "properties": {
    "iso:country":"US",
    "sg:address":"913 N Riggins St",
    "sg:city":"Anna",
    "sg:classifiers":[
        {
            "category":"Building & Trades",
            "subcategory":"Construction",
            "type":"Services"
        }
    ],
    "sg:phone":"+1 972 924 2115",
    "sg:postcode":"75409",
    "sg:province":"TX",
    "sg:tags":[
        "repairing",
        "nonresidential",
        "remodeling",
        "contractor"
    ],
    "wof:name":"General Home Repair & Imrvmnt",
    "wof:placetype":"venue"
},
  "geometry": {"coordinates":[-96.548633,33.358094],"type":"Point"}
}