{
  "type": "Feature",
  "properties": {
    "iso:country":"US",
    "sg:address":"2422 N Van Buren St",
    "sg:city":"San Angelo",
    "sg:classifiers":[
        {
            "category":"Utilities",
            "subcategory":"Telephone",
            "type":"Services"
        }
    ],
    "sg:phone":"+1 325 224 4197",
    "sg:postcode":"76901",
    "sg:province":"TX",
    "sg:tags":[
        "repair",
        "maintain",
        "telecommunication"
    ],
    "wof:name":"R and D Services",
    "wof:placetype":"venue"
},
  "geometry": {"coordinates":[-100.473083,31.475644],"type":"Point"}
}