{
  "type": "Feature",
  "properties": {
    "iso:country":"US",
    "sg:address":"8215 Agora Pkwy",
    "sg:city":"Selma",
    "sg:classifiers":[
        {
            "category":"Home & Garden",
            "subcategory":"Furniture",
            "type":"Retail Goods"
        },
        {
            "category":"Home & Garden",
            "subcategory":"Home Furnishings",
            "type":"Retail Goods"
        },
        {
            "category":"Home & Garden",
            "subcategory":"Carpets & Floor Coverings",
            "type":"Retail Goods"
        }
    ],
    "sg:phone":"+1 210 853 5685",
    "sg:postcode":"78154",
    "sg:province":"TX",
    "sg:tags":[
        "bedroom",
        "set",
        "store",
        "bed",
        "mattress"
    ],
    "sg:website":"http://www.mattressfirm.com/stores/texas/live_oak/forum_clearance_center.aspx?utm_source=yellowpages&utm_medium=link&utm_content=Forum%20Clearance%20Center&utm_campaign=Store%20Pages",
    "wof:name":"Mattress Firm",
    "wof:placetype":"venue"
},
  "geometry": {"coordinates":[-98.329521,29.5691],"type":"Point"}
}