{
  "type": "Feature",
  "properties": {
    "iso:country":"US",
    "sg:address":"5900 W Slaughter Ln",
    "sg:city":"Austin",
    "sg:phone":"+1 512 301 6143",
    "sg:postcode":"78749",
    "sg:province":"TX",
    "wof:name":"Nuevo Leon Restaurant",
    "wof:placetype":"venue"
},
  "geometry": {"coordinates":[-97.878349,30.200701],"type":"Point"}
}