{
  "type": "Feature",
  "properties": {
    "iso:country":"US",
    "sg:address":"10909 Sabo Rd",
    "sg:city":"Houston",
    "sg:classifiers":[
        {
            "category":"Health Services",
            "subcategory":"Clinic",
            "type":"Services"
        }
    ],
    "sg:phone":"+1 281 922 7085",
    "sg:postcode":"77089",
    "sg:province":"TX",
    "sg:tags":[
        "home",
        "care"
    ],
    "wof:name":"Bayou City Home Health Care In",
    "wof:placetype":"venue"
},
  "geometry": {"coordinates":[-95.222599,29.611459],"type":"Point"}
}