{
  "type": "Feature",
  "properties": {
    "iso:country":"US",
    "sg:address":"2100 N Stemmons Fwy",
    "sg:city":"Dallas",
    "sg:classifiers":[
        {
            "category":"Wholesale",
            "subcategory":"Durable Goods & Equipment",
            "type":"Manufacturing & Wholesale Goods"
        }
    ],
    "sg:phone":"+1 214 742 4862",
    "sg:postcode":"75207",
    "sg:province":"TX",
    "sg:tags":[
        "representative",
        "manufacturer"
    ],
    "wof:name":"Milson & Louis Gifts",
    "wof:placetype":"venue"
},
  "geometry": {"coordinates":[-96.82739599999999,32.802121],"type":"Point"}
}