{
  "type": "Feature",
  "properties": {
    "iso:country":"US",
    "sg:address":"6055 Hearne Rd",
    "sg:city":"Bryan",
    "sg:classifiers":[
        {
            "category":"Building & Trades",
            "subcategory":"Construction",
            "type":"Services"
        }
    ],
    "sg:phone":"+1 979 218 4467",
    "sg:postcode":"77808",
    "sg:province":"TX",
    "sg:tags":[
        "house"
    ],
    "wof:name":"OQuinn Construction",
    "wof:placetype":"venue"
},
  "geometry": {"coordinates":[-96.22123999999999,30.786085],"type":"Point"}
}