{
  "type": "Feature",
  "properties": {
    "iso:country":"US",
    "sg:address":"833 N Ware Rd",
    "sg:city":"Mcallen",
    "sg:classifiers":[
        {
            "category":"Real Estate",
            "subcategory":"Real Estate Services",
            "type":"Services"
        },
        {
            "category":"Real Estate",
            "subcategory":"Real Estate Agent",
            "type":"Services"
        }
    ],
    "sg:phone":"+1 956 668 7528",
    "sg:postcode":"78501",
    "sg:province":"TX",
    "sg:tags":[
        "buyer",
        "management",
        "broker"
    ],
    "wof:name":"Select Properties",
    "wof:placetype":"venue"
},
  "geometry": {"coordinates":[-98.26032499999999,26.215128],"type":"Point"}
}