{
  "type": "Feature",
  "properties": {
    "iso:country":"US",
    "sg:address":"2400 Bowie Dr",
    "sg:city":"Corsicana",
    "sg:classifiers":[
        {
            "category":"Education",
            "subcategory":"School",
            "type":"Public Place"
        }
    ],
    "sg:phone":"+1 903 874 1124",
    "sg:postcode":"75110",
    "sg:province":"TX",
    "wof:name":"William Tyndale Christian Aca",
    "wof:placetype":"venue"
},
  "geometry": {"coordinates":[-96.494145,32.112796],"type":"Point"}
}