{
  "type": "Feature",
  "properties": {
    "iso:country":"US",
    "sg:address":"7880 Alpha Rd",
    "sg:city":"Dallas",
    "sg:classifiers":[
        {
            "category":"Travel",
            "subcategory":"Hotels & Motels",
            "type":"Entertainment"
        },
        {
            "category":"Retail",
            "subcategory":"Event Space",
            "type":"Services"
        }
    ],
    "sg:phone":"+1 972 391 0000",
    "sg:postcode":"75240",
    "sg:province":"TX",
    "sg:tags":[
        "facility",
        "venue",
        "hall",
        "reception",
        "lodging",
        "corporate",
        "banquet"
    ],
    "sg:website":"www.staybridge.com",
    "wof:name":"Staybridge Suites Dallas - Near The Galleria",
    "wof:placetype":"venue"
},
  "geometry": {"coordinates":[-96.771063,32.927125],"type":"Point"}
}