{
  "type": "Feature",
  "properties": {
    "iso:country":"US",
    "sg:address":"130 Ridgewood Cove",
    "sg:city":"Georgetown",
    "sg:classifiers":[
        {
            "category":"Professional",
            "subcategory":"Engineering",
            "type":"Services"
        }
    ],
    "sg:phone":"+1 512 864 9092",
    "sg:postcode":"78628",
    "sg:province":"TX",
    "wof:name":"Donald Devano",
    "wof:placetype":"venue"
},
  "geometry": {"coordinates":[-97.767427,30.723774],"type":"Point"}
}