{
  "type": "Feature",
  "properties": {
    "iso:country":"US",
    "sg:address":"10208 Ranch Rd 620 N",
    "sg:city":"Austin",
    "sg:classifiers":[
        {
            "category":"Professional",
            "subcategory":"Advertising",
            "type":"Services"
        }
    ],
    "sg:phone":"+1 512 336 8121",
    "sg:postcode":"78726",
    "sg:province":"TX",
    "sg:tags":[
        "mail"
    ],
    "wof:name":"Direct Mailers Discount Outlet",
    "wof:placetype":"venue"
},
  "geometry": {"coordinates":[-97.83769700000001,30.438136],"type":"Point"}
}