{
  "type": "Feature",
  "properties": {
    "iso:country":"US",
    "sg:address":"27222 Robinson Rd",
    "sg:city":"Conroe",
    "sg:classifiers":[
        {
            "category":"Home & Garden",
            "subcategory":"Garden Supply",
            "type":"Retail Goods"
        }
    ],
    "sg:phone":"+1 281 367 0985",
    "sg:postcode":"77385",
    "sg:province":"TX",
    "wof:name":"MBK Designs",
    "wof:placetype":"venue"
},
  "geometry": {"coordinates":[-95.443921,30.157098],"type":"Point"}
}