{
  "type": "Feature",
  "properties": {
    "iso:country":"US",
    "sg:address":"1114 Babbling Brook Dr",
    "sg:city":"Lewisville",
    "sg:classifiers":[
        {
            "category":"Professional",
            "type":"Services"
        }
    ],
    "sg:phone":"+1 972 315 2994",
    "sg:postcode":"75067",
    "sg:province":"TX",
    "wof:name":"Metroplex Fryer Services LLC",
    "wof:placetype":"venue"
},
  "geometry": {"coordinates":[-97.02148699999999,33.016641],"type":"Point"}
}