{
  "type": "Feature",
  "properties": {
    "iso:country":"US",
    "sg:address":"476 W Cameron Ave",
    "sg:city":"Rockdale",
    "sg:classifiers":[
        {
            "category":"Autos & Motor Vehicles",
            "subcategory":"Automobile Sales",
            "type":"Retail Goods"
        }
    ],
    "sg:phone":"+1 512 446 5841",
    "sg:postcode":"76567",
    "sg:province":"TX",
    "sg:tags":[
        "car",
        "dealer"
    ],
    "sg:website":"www.millerstarnes.com",
    "wof:name":"Miller-Starnes Chevrolet Buick",
    "wof:placetype":"venue"
},
  "geometry": {"coordinates":[-97.005674,30.653695],"type":"Point"}
}