{
  "type": "Feature",
  "properties": {
    "iso:country":"US",
    "sg:address":"2302 Clower St",
    "sg:city":"San Antonio",
    "sg:classifiers":[
        {
            "category":"Building & Trades",
            "subcategory":"Electrical",
            "type":"Services"
        }
    ],
    "sg:phone":"+1 210 734 9951",
    "sg:postcode":"78201",
    "sg:province":"TX",
    "sg:tags":[
        "electrical",
        "contractor"
    ],
    "wof:name":"Premise Cabling",
    "wof:placetype":"venue"
},
  "geometry": {"coordinates":[-98.53346000000001,29.477684],"type":"Point"}
}