{
  "type": "Feature",
  "properties": {
    "iso:country":"US",
    "sg:address":"5211 Main St",
    "sg:city":"Sheridan",
    "sg:classifiers":[
        {
            "category":"Recreation",
            "subcategory":"Amusement Park",
            "type":"Entertainment"
        }
    ],
    "sg:phone":"+1 979 234 7718",
    "sg:postcode":"77426",
    "sg:province":"TX",
    "sg:website":"www.splashway.org",
    "wof:name":"Splashway Water Park-Sheridan",
    "wof:placetype":"venue"
},
  "geometry": {"coordinates":[-96.257182,30.141044],"type":"Point"}
}