{
  "type": "Feature",
  "properties": {
    "iso:country":"US",
    "sg:address":"1905 Culebra Rd",
    "sg:city":"San Antonio",
    "sg:classifiers":[
        {
            "category":"Food & Beverages",
            "subcategory":"Groceries & Convenience Stores",
            "type":"Retail Goods"
        }
    ],
    "sg:phone":"+1 210 736 5625",
    "sg:postcode":"78201",
    "sg:province":"TX",
    "wof:name":"Express Lane Grocery",
    "wof:placetype":"venue"
},
  "geometry": {"coordinates":[-98.539095,29.446602],"type":"Point"}
}