{
  "type": "Feature",
  "properties": {
    "iso:country":"US",
    "sg:address":"6422 Sewanee St",
    "sg:city":"Houston",
    "sg:classifiers":[
        {
            "category":"Professional",
            "subcategory":"Management & Consulting",
            "type":"Services"
        }
    ],
    "sg:phone":"+1 713 838 0907",
    "sg:postcode":"77005",
    "sg:province":"TX",
    "wof:name":"Oldgroup Consulting",
    "wof:placetype":"venue"
},
  "geometry": {"coordinates":[-95.43107000000001,29.711354],"type":"Point"}
}