{
  "type": "Feature",
  "properties": {
    "iso:country":"US",
    "sg:address":"2416 E 29th St",
    "sg:city":"Mission",
    "sg:classifiers":[
        {
            "category":"Shopping",
            "type":"Retail Goods"
        }
    ],
    "sg:phone":"+1 956 583 2529",
    "sg:postcode":"78574",
    "sg:province":"TX",
    "sg:tags":[
        "cosmetic",
        "perfume"
    ],
    "wof:name":"Mary Kay Cosmetics",
    "wof:placetype":"venue"
},
  "geometry": {"coordinates":[-98.28112299999999,26.234329],"type":"Point"}
}