{
  "type": "Feature",
  "properties": {
    "iso:country":"US",
    "sg:address":"5100 E Interstate 20 Svc Rd",
    "sg:city":"Aledo",
    "sg:classifiers":[
        {
            "category":"Food & Beverages",
            "subcategory":"Groceries & Convenience Stores",
            "type":"Retail Goods"
        }
    ],
    "sg:phone":"+1 817 441 2333",
    "sg:postcode":"76008",
    "sg:province":"TX",
    "wof:name":"Mr C Food Store",
    "wof:placetype":"venue"
},
  "geometry": {"coordinates":[-97.60894999999999,32.729385],"type":"Point"}
}