{
  "type": "Feature",
  "properties": {
    "iso:country":"US",
    "sg:address":"810 N Llano St",
    "sg:city":"Fredericksburg",
    "sg:classifiers":[
        {
            "category":"Shopping",
            "type":"Retail Goods"
        }
    ],
    "sg:phone":"+1 830 990 8925",
    "sg:postcode":"78624",
    "sg:province":"TX",
    "sg:tags":[
        "miscellaneous",
        "store"
    ],
    "wof:name":"Prescott's Orthotics",
    "wof:placetype":"venue"
},
  "geometry": {"coordinates":[-98.86374000000001,30.281157],"type":"Point"}
}