{
  "type": "Feature",
  "properties": {
    "iso:country":"US",
    "sg:address":"4406 80th St",
    "sg:city":"Lubbock",
    "sg:classifiers":[
        {
            "category":"Personal",
            "type":"Services"
        }
    ],
    "sg:phone":"+1 806 796 1873",
    "sg:postcode":"79424",
    "sg:province":"TX",
    "wof:name":"Therapeutic Massage Thera",
    "wof:placetype":"venue"
},
  "geometry": {"coordinates":[-101.905587,33.521393],"type":"Point"}
}