{
  "type": "Feature",
  "properties": {
    "iso:country":"US",
    "sg:address":"18430 Security Rd",
    "sg:city":"Houston",
    "sg:classifiers":[
        {
            "category":"Professional",
            "type":"Services"
        }
    ],
    "sg:phone":"+1 281 209 2400",
    "sg:postcode":"77032",
    "sg:province":"TX",
    "sg:tags":[
        "establishment"
    ],
    "wof:name":"Africa 2000 Cargo",
    "wof:placetype":"venue"
},
  "geometry": {"coordinates":[-95.347246,29.98076],"type":"Point"}
}