{
  "type": "Feature",
  "properties": {
    "iso:country":"US",
    "sg:address":"2003 Legend Grove Ct",
    "sg:city":"Houston",
    "sg:classifiers":[
        {
            "category":"Professional",
            "subcategory":"Accounting & Tax Preparation",
            "type":"Services"
        }
    ],
    "sg:phone":"+1 281 480 9160",
    "sg:postcode":"77062",
    "sg:province":"TX",
    "wof:name":"A W E Francis CPA",
    "wof:placetype":"venue"
},
  "geometry": {"coordinates":[-95.143871,29.589782],"type":"Point"}
}