{
  "type": "Feature",
  "properties": {
    "iso:country":"US",
    "sg:address":"2104 Ellingham Dr",
    "sg:city":"Wichita Falls",
    "sg:classifiers":[
        {
            "category":"Professional",
            "subcategory":"Management & Consulting",
            "type":"Services"
        }
    ],
    "sg:phone":"+1 940 767 7717",
    "sg:postcode":"76308",
    "sg:province":"TX",
    "sg:tags":[
        "eating"
    ],
    "wof:name":"Subway",
    "wof:placetype":"venue"
},
  "geometry": {"coordinates":[-98.514867,33.882291],"type":"Point"}
}