{
  "type": "Feature",
  "properties": {
    "iso:country":"US",
    "sg:address":"701 Timbercreek Dr",
    "sg:city":"Hurst",
    "sg:classifiers":[
        {
            "category":"Shopping",
            "subcategory":"Gifts & Souvenirs",
            "type":"Retail Goods"
        }
    ],
    "sg:phone":"+1 817 280 0476",
    "sg:postcode":"76053",
    "sg:province":"TX",
    "wof:name":"Petals Galore",
    "wof:placetype":"venue"
},
  "geometry": {"coordinates":[-97.15842499999999,32.813693],"type":"Point"}
}