{
  "type": "Feature",
  "properties": {
    "iso:country":"US",
    "sg:address":"717 Taylor Dr",
    "sg:city":"Plano",
    "sg:classifiers":[
        {
            "category":"Professional",
            "type":"Services"
        }
    ],
    "sg:phone":"+1 469 467 4000",
    "sg:postcode":"75074",
    "sg:province":"TX",
    "sg:tags":[
        "establishment"
    ],
    "wof:name":"Tech Plan",
    "wof:placetype":"venue"
},
  "geometry": {"coordinates":[-96.703221,33.009043],"type":"Point"}
}