{
  "type": "Feature",
  "properties": {
    "iso:country":"US",
    "sg:address":"1015 Mill Crossing Pl",
    "sg:city":"Arlington",
    "sg:classifiers":[
        {
            "category":"Professional",
            "subcategory":"Computer Services",
            "type":"Services"
        }
    ],
    "sg:phone":"+1 817 875 7880",
    "sg:postcode":"76006",
    "sg:province":"TX",
    "sg:tags":[
        "datum"
    ],
    "wof:name":"Web Favorite Inc",
    "wof:placetype":"venue"
},
  "geometry": {"coordinates":[-97.093717,32.780404],"type":"Point"}
}