{
  "type": "Feature",
  "properties": {
    "iso:country":"US",
    "sg:address":"14100 Montfort Dr",
    "sg:city":"Dallas",
    "sg:classifiers":[
        {
            "category":"Banks & Credit Unions",
            "subcategory":"Investment Brokerage",
            "type":"Services"
        }
    ],
    "sg:phone":"+1 972 233 7575",
    "sg:postcode":"75254",
    "sg:province":"TX",
    "wof:name":"GE Capital Corp",
    "wof:placetype":"venue"
},
  "geometry": {"coordinates":[-96.814031,32.939541],"type":"Point"}
}