{
  "type": "Feature",
  "properties": {
    "iso:country":"US",
    "sg:address":"7715 Hertfordshire Dr",
    "sg:city":"Spring",
    "sg:classifiers":[
        {
            "category":"Professional",
            "type":"Services"
        }
    ],
    "sg:phone":"+1 281 376 7959",
    "sg:postcode":"77379",
    "sg:province":"TX",
    "wof:name":"Jallco L L C",
    "wof:placetype":"venue"
},
  "geometry": {"coordinates":[-95.53593600000001,30.027967],"type":"Point"}
}