{
  "type": "Feature",
  "properties": {
    "iso:country":"US",
    "sg:address":"802 W Liveoak St",
    "sg:city":"Coleman",
    "sg:classifiers":[
        {
            "category":"Transit Center",
            "subcategory":"Freight",
            "type":"Transportation"
        },
        {
            "category":"Freight",
            "type":"Transportation"
        }
    ],
    "sg:phone":"+1 325 625 5531",
    "sg:postcode":"76834",
    "sg:province":"TX",
    "sg:tags":[
        "local",
        "trucking-motor",
        "trucking"
    ],
    "wof:name":"Cct Trucking",
    "wof:placetype":"venue"
},
  "geometry": {"coordinates":[-99.430886,31.830998],"type":"Point"}
}