{
  "type": "Feature",
  "properties": {
    "iso:country":"US",
    "sg:address":"2231 Mockingbird Dr",
    "sg:city":"Round Rock",
    "sg:classifiers":[
        {
            "category":"Manufacturing",
            "subcategory":"Retail Goods",
            "type":"Manufacturing & Wholesale Goods"
        }
    ],
    "sg:phone":"+1 512 388 9751",
    "sg:postcode":"78681",
    "sg:province":"TX",
    "sg:tags":[
        "product",
        "mfg"
    ],
    "wof:name":"Northland Industries Inc",
    "wof:placetype":"venue"
},
  "geometry": {"coordinates":[-97.709481,30.516451],"type":"Point"}
}