{
  "type": "Feature",
  "properties": {
    "iso:country":"US",
    "sg:address":"6965 Bandera Rd",
    "sg:city":"San Antonio",
    "sg:classifiers":[
        {
            "category":"Restaurant",
            "type":"Food & Drink"
        }
    ],
    "sg:menulink":"http://www.allmenus.com/tx/san-antonio/67638-peter-pipers-pizza/menu/",
    "sg:phone":"+1 210 543 7118",
    "sg:postcode":"78238",
    "sg:province":"TX",
    "sg:tags":[
        "american",
        "pizza"
    ],
    "wof:name":"Peter Pipers Pizza",
    "wof:placetype":"venue"
},
  "geometry": {"coordinates":[-98.623665,29.499145],"type":"Point"}
}