{
  "type": "Feature",
  "properties": {
    "iso:country":"US",
    "sg:address":"4908 Fairvent St",
    "sg:city":"Pasadena",
    "sg:classifiers":[
        {
            "category":"Building & Trades",
            "subcategory":"Landscaping Services",
            "type":"Services"
        }
    ],
    "sg:phone":"+1 281 991 7236",
    "sg:postcode":"77505",
    "sg:province":"TX",
    "sg:tags":[
        "landscape",
        "contractor"
    ],
    "wof:name":"Antonio's Landscaping",
    "wof:placetype":"venue"
},
  "geometry": {"coordinates":[-95.167558,29.648303],"type":"Point"}
}