{
  "type": "Feature",
  "properties": {
    "iso:country":"US",
    "sg:address":"3205 W Davis St Suite A-170",
    "sg:city":"Conroe",
    "sg:classifiers":[
        {
            "category":"Banks & Credit Unions",
            "subcategory":"Investment Brokerage",
            "type":"Services"
        },
        {
            "category":"Banks & Credit Unions",
            "subcategory":"Bank",
            "type":"Services"
        },
        {
            "category":"Banks & Credit Unions",
            "subcategory":"Financial Services",
            "type":"Services"
        }
    ],
    "sg:phone":"+1 936 647 3902",
    "sg:postcode":"77304",
    "sg:province":"TX",
    "sg:tags":[
        "advisory",
        "mutual",
        "retirement",
        "annuity",
        "broker",
        "fund",
        "planning",
        "plan",
        "consultant",
        "security",
        "bond",
        "insurance",
        "stock"
    ],
    "sg:website":"http://houston.citysearch.com/profile/external/602568863/conroe_tx/edward_jones_melinda_mcgowan.html?publisher=yellowpages&reference_id=1&placement=ypwebsitemip",
    "wof:name":"Edward Jones - MELINDA MCGOWAN",
    "wof:placetype":"venue"
},
  "geometry": {"coordinates":[-95.517212,30.336816],"type":"Point"}
}