{
  "type": "Feature",
  "properties": {
    "iso:country":"US",
    "sg:address":"2837 Ladybird Ln",
    "sg:city":"Dallas",
    "sg:classifiers":[
        {
            "category":"Home & Garden",
            "subcategory":"Carpets & Floor Coverings",
            "type":"Retail Goods"
        }
    ],
    "sg:phone":"+1 214 956 7711",
    "sg:postcode":"75220",
    "sg:province":"TX",
    "wof:name":"Graciano Commercial Carpet",
    "wof:placetype":"venue"
},
  "geometry": {"coordinates":[-96.878885,32.879402],"type":"Point"}
}