{
  "type": "Feature",
  "properties": {
    "iso:country":"US",
    "sg:address":"401 Coke Ave",
    "sg:city":"Hillsboro",
    "sg:classifiers":[
        {
            "category":"Health Services",
            "subcategory":"Optometrist",
            "type":"Services"
        }
    ],
    "sg:phone":"+1 254 582 9772",
    "sg:postcode":"76645",
    "sg:province":"TX",
    "wof:name":"Johnston Eye Care",
    "wof:placetype":"venue"
},
  "geometry": {"coordinates":[-97.09872,32.007652],"type":"Point"}
}