{
  "type": "Feature",
  "properties": {
    "iso:country":"US",
    "sg:address":"3626 N Hall St",
    "sg:city":"Dallas",
    "sg:classifiers":[
        {
            "category":"Health Services",
            "subcategory":"Clinic",
            "type":"Services"
        }
    ],
    "sg:phone":"+1 214 821 5703",
    "sg:postcode":"75219",
    "sg:province":"TX",
    "sg:tags":[
        "colonic",
        "irrigation"
    ],
    "wof:name":"Genesis",
    "wof:placetype":"venue"
},
  "geometry": {"coordinates":[-96.805774,32.808713],"type":"Point"}
}