{
  "type": "Feature",
  "properties": {
    "iso:country":"US",
    "sg:address":"1225 Hughmont Dr",
    "sg:city":"Pflugerville",
    "sg:classifiers":[
        {
            "category":"Building & Trades",
            "subcategory":"Plumbing",
            "type":"Services"
        }
    ],
    "sg:phone":"+1 512 251 9437",
    "sg:postcode":"78660",
    "sg:province":"TX",
    "sg:tags":[
        "contractor"
    ],
    "wof:name":"4a Plumber",
    "wof:placetype":"venue"
},
  "geometry": {"coordinates":[-97.631563,30.459615],"type":"Point"}
}