{
  "type": "Feature",
  "properties": {
    "iso:country":"US",
    "sg:address":"4438 Centerview Dr",
    "sg:city":"San Antonio",
    "sg:classifiers":[
        {
            "category":"Social Services",
            "subcategory":"Job Training",
            "type":"Services"
        }
    ],
    "sg:phone":"+1 210 733 5566",
    "sg:postcode":"78228",
    "sg:province":"TX",
    "wof:name":"Cascade Rhblitation Counseling",
    "wof:placetype":"venue"
},
  "geometry": {"coordinates":[-98.570061,29.487774],"type":"Point"}
}