{
  "type": "Feature",
  "properties": {
    "iso:country":"US",
    "sg:address":"4420 State Hwy 6",
    "sg:city":"Houston",
    "sg:classifiers":[
        {
            "category":"Retail",
            "subcategory":"Auto Repair",
            "type":"Services"
        }
    ],
    "sg:phone":"+1 281 550 8784",
    "sg:postcode":"77084",
    "sg:province":"TX",
    "sg:tags":[
        "tire"
    ],
    "wof:name":"Clay Road Hwy 6 Tire & Auto",
    "wof:placetype":"venue"
},
  "geometry": {"coordinates":[-95.645619,29.838366],"type":"Point"}
}