{
  "type": "Feature",
  "properties": {
    "iso:country":"US",
    "sg:address":"1518 Austin Hwy",
    "sg:city":"San Antonio",
    "sg:classifiers":[
        {
            "category":"Real Estate",
            "subcategory":"Real Estate Agent",
            "type":"Services"
        }
    ],
    "sg:phone":"+1 210 828 5544",
    "sg:postcode":"78218",
    "sg:province":"TX",
    "wof:name":"Stevens Group",
    "wof:placetype":"venue"
},
  "geometry": {"coordinates":[-98.43136,29.494694],"type":"Point"}
}