{
  "type": "Feature",
  "properties": {
    "iso:country":"US",
    "sg:address":"101 W Randol Mill Rd",
    "sg:city":"Arlington",
    "sg:classifiers":[
        {
            "category":"Banks & Credit Unions",
            "subcategory":"Investment Brokerage",
            "type":"Services"
        }
    ],
    "sg:phone":"+1 817 794 0001",
    "sg:postcode":"76011",
    "sg:province":"TX",
    "sg:tags":[
        "advisory",
        "financial"
    ],
    "sg:website":"www.fsbfin.com",
    "wof:name":"FSB Financial",
    "wof:placetype":"venue"
},
  "geometry": {"coordinates":[-97.109059,32.750059],"type":"Point"}
}