{
  "type": "Feature",
  "properties": {
    "iso:country":"US",
    "sg:address":"11834 Harry Hines Blvd",
    "sg:city":"Dallas",
    "sg:classifiers":[
        {
            "category":"Shopping",
            "subcategory":"Mobile Phones",
            "type":"Retail Goods"
        }
    ],
    "sg:phone":"+1 972 241 0800",
    "sg:postcode":"75234",
    "sg:province":"TX",
    "wof:name":"Wireless Universe Inc",
    "wof:placetype":"venue"
},
  "geometry": {"coordinates":[-96.89589700000001,32.9105],"type":"Point"}
}