{
  "type": "Feature",
  "properties": {
    "iso:country":"US",
    "sg:address":"1408 W 15th Ave",
    "sg:city":"Amarillo",
    "sg:classifiers":[
        {
            "category":"Retail",
            "subcategory":"Repair Shop",
            "type":"Services"
        }
    ],
    "sg:phone":"+1 806 374 8961",
    "sg:postcode":"79102",
    "sg:province":"TX",
    "wof:name":"San Jacinto Upholstery Co",
    "wof:placetype":"venue"
},
  "geometry": {"coordinates":[-101.854021,35.199671],"type":"Point"}
}