{
  "type": "Feature",
  "properties": {
    "iso:country":"US",
    "sg:address":"3607 Old Spanish Trl",
    "sg:city":"Houston",
    "sg:classifiers":[
        {
            "category":"Restaurant",
            "type":"Food & Drink"
        }
    ],
    "sg:phone":"+1 713 747 3800",
    "sg:postcode":"77021",
    "sg:province":"TX",
    "sg:tags":[
        "pizza"
    ],
    "sg:website":"www.dominos.com",
    "wof:name":"Domino's Pizza",
    "wof:placetype":"venue"
},
  "geometry": {"coordinates":[-95.36369999999999,29.702276],"type":"Point"}
}