{
  "type": "Feature",
  "properties": {
    "iso:country":"US",
    "sg:address":"9217 Mallory St",
    "sg:city":"Houston",
    "sg:classifiers":[
        {
            "category":"Organizations",
            "subcategory":"Religious Organization",
            "type":"Services"
        }
    ],
    "sg:phone":"+1 713 731 9845",
    "sg:postcode":"77051",
    "sg:province":"TX",
    "wof:name":"Triumph Temple Church Inc",
    "wof:placetype":"venue"
},
  "geometry": {"coordinates":[-95.370791,29.656725],"type":"Point"}
}