{
  "type": "Feature",
  "properties": {
    "iso:country":"US",
    "sg:address":"311 W Nakoma Dr",
    "sg:city":"San Antonio",
    "sg:classifiers":[
        {
            "category":"Building & Trades",
            "subcategory":"Construction",
            "type":"Services"
        }
    ],
    "sg:phone":"+1 210 377 1586",
    "sg:postcode":"78216",
    "sg:province":"TX",
    "sg:tags":[
        "general",
        "nonresidential",
        "contractor"
    ],
    "wof:name":"Baron-Long Construction Ltd",
    "wof:placetype":"venue"
},
  "geometry": {"coordinates":[-98.498608,29.553146],"type":"Point"}
}