{
  "type": "Feature",
  "properties": {
    "iso:country":"US",
    "sg:address":"3609 Lindhaven Dr",
    "sg:city":"Pearland",
    "sg:classifiers":[
        {
            "category":"Professional",
            "type":"Services"
        }
    ],
    "sg:phone":"+1 281 692 9901",
    "sg:postcode":"77584",
    "sg:province":"TX",
    "wof:name":"Glenn Garrison",
    "wof:placetype":"venue"
},
  "geometry": {"coordinates":[-95.30435799999999,29.541683],"type":"Point"}
}