{
  "type": "Feature",
  "properties": {
    "iso:country":"US",
    "sg:address":"5869 Sugar Hill Dr",
    "sg:city":"Houston",
    "sg:classifiers":[
        {
            "category":"Professional",
            "subcategory":"Business Services",
            "type":"Services"
        }
    ],
    "sg:phone":"+1 713 782 6468",
    "sg:postcode":"77057",
    "sg:province":"TX",
    "sg:tags":[
        "interior",
        "consultant",
        "designer",
        "design",
        "decorator"
    ],
    "wof:name":"K Rouse Interiors Inc",
    "wof:placetype":"venue"
},
  "geometry": {"coordinates":[-95.484629,29.756659],"type":"Point"}
}