{
  "type": "Feature",
  "properties": {
    "iso:country":"US",
    "sg:address":"11997 Main St",
    "sg:city":"Houston",
    "sg:classifiers":[
        {
            "category":"Food & Beverages",
            "subcategory":"Groceries & Convenience Stores",
            "type":"Retail Goods"
        }
    ],
    "sg:phone":"+1 713 721 3197",
    "sg:postcode":"77035",
    "sg:province":"TX",
    "wof:name":"Eagle Food Mart 3",
    "wof:placetype":"venue"
},
  "geometry": {"coordinates":[-95.446297,29.653299],"type":"Point"}
}