{
  "type": "Feature",
  "properties": {
    "iso:country":"US",
    "sg:address":"10740 N Central Expy Ste 100",
    "sg:city":"Dallas",
    "sg:classifiers":[
        {
            "category":"Health Services",
            "subcategory":"Doctor",
            "type":"Services"
        }
    ],
    "sg:phone":"+1 214 361 6700",
    "sg:postcode":"75231",
    "sg:province":"TX",
    "wof:name":"Jost Bradley F Md",
    "wof:placetype":"venue"
},
  "geometry": {"coordinates":[-96.76816100000001,32.894473],"type":"Point"}
}