{
  "type": "Feature",
  "properties": {
    "iso:country":"US",
    "sg:address":"411 N Akard St",
    "sg:city":"Dallas",
    "sg:classifiers":[
        {
            "category":"Banks & Credit Unions",
            "subcategory":"Bank",
            "type":"Services"
        }
    ],
    "sg:phone":"+1 214 871 7974",
    "sg:postcode":"75201",
    "sg:province":"TX",
    "wof:name":"Wells Fargo",
    "wof:placetype":"venue"
},
  "geometry": {"coordinates":[-96.80038500000001,32.783069],"type":"Point"}
}