{
  "type": "Feature",
  "properties": {
    "iso:country":"US",
    "sg:address":"25 Highland Park Vlg",
    "sg:city":"Dallas",
    "sg:classifiers":[
        {
            "category":"Professional",
            "subcategory":"Lawyer & Legal Services",
            "type":"Services"
        }
    ],
    "sg:phone":"+1 214 691 0290",
    "sg:postcode":"75205",
    "sg:province":"TX",
    "wof:name":"Augusta Realty Corp The",
    "wof:placetype":"venue"
},
  "geometry": {"coordinates":[-96.806325,32.835913],"type":"Point"}
}