{
  "type": "Feature",
  "properties": {
    "iso:country":"US",
    "sg:address":"15835 Foothill Farms Loop",
    "sg:city":"Pflugerville",
    "sg:classifiers":[
        {
            "category":"Manufacturing",
            "subcategory":"Furniture",
            "type":"Manufacturing & Wholesale Goods"
        }
    ],
    "sg:phone":"+1 512 293 8380",
    "sg:postcode":"78660",
    "sg:province":"TX",
    "sg:tags":[
        "household",
        "metal",
        "mfg"
    ],
    "wof:name":"Alpine Metal Works",
    "wof:placetype":"venue"
},
  "geometry": {"coordinates":[-97.653813,30.450319],"type":"Point"}
}