{
  "type": "Feature",
  "properties": {
    "iso:country":"US",
    "sg:address":"1902 Cliff Maus Dr",
    "sg:city":"Corpus Christi",
    "sg:classifiers":[
        {
            "category":"Organizations",
            "subcategory":"Religious Organization",
            "type":"Services"
        }
    ],
    "sg:phone":"+1 361 855 9311",
    "sg:postcode":"78416",
    "sg:province":"TX",
    "sg:tags":[
        "church"
    ],
    "wof:name":"West Haven Baptist Church",
    "wof:placetype":"venue"
},
  "geometry": {"coordinates":[-97.454201,27.750864],"type":"Point"}
}