{
  "type": "Feature",
  "properties": {
    "iso:country":"US",
    "sg:address":"3726 Scott St",
    "sg:city":"Houston",
    "sg:classifiers":[
        {
            "category":"Donuts",
            "subcategory":"None",
            "type":"Food & Drink"
        }
    ],
    "sg:phone":"+1 713 748 7076",
    "sg:postcode":"77004",
    "sg:province":"TX",
    "wof:name":"University Shipley DO-Nuts",
    "wof:placetype":"venue"
},
  "geometry": {"coordinates":[-95.35169999999999,29.7222],"type":"Point"}
}