{
  "type": "Feature",
  "properties": {
    "iso:country":"US",
    "sg:address":"4507 Bissonnet St",
    "sg:city":"Bellaire",
    "sg:classifiers":[
        {
            "category":"Retail",
            "subcategory":"Laundry & Dry Cleaning",
            "type":"Services"
        },
        {
            "category":"Personal",
            "subcategory":"Shoe Repair & Shine",
            "type":"Services"
        }
    ],
    "sg:phone":"+1 713 667 9054",
    "sg:postcode":"77401",
    "sg:province":"TX",
    "sg:tags":[
        "cleaner"
    ],
    "wof:name":"Exclusive Cleaners & Shoe Repair",
    "wof:placetype":"venue"
},
  "geometry": {"coordinates":[-95.452003,29.715599],"type":"Point"}
}