{
  "type": "Feature",
  "properties": {
    "iso:country":"US",
    "sg:address":"11928 McAuliffe Dr",
    "sg:city":"El Paso",
    "sg:classifiers":[
        {
            "category":"Health Services",
            "subcategory":"Nursing And Care Facility",
            "type":"Services"
        }
    ],
    "sg:phone":"+1 915 857 7303",
    "sg:postcode":"79936",
    "sg:province":"TX",
    "wof:name":"Reynaud Elderly Foster Care",
    "wof:placetype":"venue"
},
  "geometry": {"coordinates":[-106.280394,31.756761],"type":"Point"}
}