{
  "type": "Feature",
  "properties": {
    "iso:country":"US",
    "sg:address":"6405 Stillwater Ln",
    "sg:city":"Plano",
    "sg:classifiers":[
        {
            "category":"Building & Trades",
            "subcategory":"Construction",
            "type":"Services"
        }
    ],
    "sg:phone":"+1 972 668 0321",
    "sg:postcode":"75024",
    "sg:province":"TX",
    "sg:tags":[
        "home",
        "builder"
    ],
    "wof:name":"Kings Ridge Grand Homes",
    "wof:placetype":"venue"
},
  "geometry": {"coordinates":[-96.852175,33.061024],"type":"Point"}
}