{
  "type": "Feature",
  "properties": {
    "iso:country":"US",
    "sg:address":"33 N Western St",
    "sg:city":"Amarillo",
    "sg:classifiers":[
        {
            "category":"Personal",
            "subcategory":"Beauty Salon",
            "type":"Services"
        }
    ],
    "sg:phone":"+1 806 355 8101",
    "sg:postcode":"79106",
    "sg:province":"TX",
    "wof:name":"Carousel Salon",
    "wof:placetype":"venue"
},
  "geometry": {"coordinates":[-101.884136,35.217227],"type":"Point"}
}