{
  "type": "Feature",
  "properties": {
    "iso:country":"US",
    "sg:address":"1929 Prospect St",
    "sg:city":"Houston",
    "sg:classifiers":[
        {
            "category":"Building & Trades",
            "subcategory":"Landscaping Services",
            "type":"Services"
        }
    ],
    "sg:phone":"+1 713 838 0565",
    "sg:postcode":"77004",
    "sg:province":"TX",
    "sg:tags":[
        "landscape",
        "contractor"
    ],
    "wof:name":"Deal Landscapes",
    "wof:placetype":"venue"
},
  "geometry": {"coordinates":[-95.379293,29.721825],"type":"Point"}
}