{
  "type": "Feature",
  "properties": {
    "iso:country":"US",
    "sg:address":"13085 West Rd Ste 500",
    "sg:city":"Houston",
    "sg:classifiers":[
        {
            "category":"Home & Garden",
            "subcategory":"Household Appliances",
            "type":"Retail Goods"
        },
        {
            "category":"Professional",
            "subcategory":"Detective & Security Services",
            "type":"Services"
        },
        {
            "category":"Manufacturing",
            "subcategory":"Aerospace",
            "type":"Manufacturing & Wholesale Goods"
        }
    ],
    "sg:phone":"+1 832 912 2600",
    "sg:postcode":"77041",
    "sg:province":"TX",
    "sg:tags":[
        "control",
        "industry",
        "monitoring",
        "thermostat",
        "system"
    ],
    "sg:website":"http://www51.honeywell.com",
    "wof:name":"Honeywell",
    "wof:placetype":"venue"
},
  "geometry": {"coordinates":[-95.602191,29.897973],"type":"Point"}
}