{
  "type": "Feature",
  "properties": {
    "iso:country":"US",
    "sg:address":"4272 Kellway Cir",
    "sg:city":"Addison",
    "sg:classifiers":[
        {
            "category":"Shopping",
            "subcategory":"Clothing, Apparel, & Fashions",
            "type":"Retail Goods"
        }
    ],
    "sg:phone":"+1 469 533 6377",
    "sg:postcode":"75001",
    "sg:province":"TX",
    "sg:tags":[
        "item"
    ],
    "wof:name":"Leslies Closet Inc",
    "wof:placetype":"venue"
},
  "geometry": {"coordinates":[-96.84197899999999,32.970567],"type":"Point"}
}