{
  "type": "Feature",
  "properties": {
    "iso:country":"US",
    "sg:address":"502 US Hwy 90 Alt",
    "sg:city":"Richmond",
    "sg:classifiers":[
        {
            "category":"Retail",
            "subcategory":"Veterinary Services",
            "type":"Services"
        }
    ],
    "sg:phone":"+1 281 342 3431",
    "sg:postcode":"77469",
    "sg:province":"TX",
    "sg:tags":[
        "hospital",
        "veterinarian",
        "animal"
    ],
    "wof:name":"Richmond Animal Hospital Inc",
    "wof:placetype":"venue"
},
  "geometry": {"coordinates":[-95.762298,29.581872],"type":"Point"}
}