{
  "type": "Feature",
  "properties": {
    "iso:country":"US",
    "sg:address":"113 E Rosedale St",
    "sg:city":"Fort Worth",
    "sg:classifiers":[
        {
            "category":"Professional",
            "subcategory":"Lawyer & Legal Services",
            "type":"Services"
        }
    ],
    "sg:phone":"+1 817 332 1519",
    "sg:postcode":"76104",
    "sg:province":"TX",
    "sg:tags":[
        "attorney"
    ],
    "wof:name":"Steven G King Law Office",
    "wof:placetype":"venue"
},
  "geometry": {"coordinates":[-97.32514999999999,32.733133],"type":"Point"}
}