{
  "type": "Feature",
  "properties": {
    "iso:country":"US",
    "sg:address":"17218 Bamwood Dr",
    "sg:city":"Houston",
    "sg:classifiers":[
        {
            "category":"Autos & Motor Vehicles",
            "subcategory":"Automobile Sales",
            "type":"Retail Goods"
        }
    ],
    "sg:phone":"+1 281 587 0449",
    "sg:postcode":"77090",
    "sg:province":"TX",
    "sg:tags":[
        "classic"
    ],
    "wof:name":"Classic Mustang Of Houston",
    "wof:placetype":"venue"
},
  "geometry": {"coordinates":[-95.44949,30.014971],"type":"Point"}
}