{
  "type": "Feature",
  "properties": {
    "iso:country":"US",
    "sg:address":"2126 W 3rd St",
    "sg:city":"Pecos",
    "sg:classifiers":[
        {
            "category":"Manufacturing",
            "subcategory":"Tools & Machinery",
            "type":"Manufacturing & Wholesale Goods"
        }
    ],
    "sg:phone":"+1 432 445 4001",
    "sg:postcode":"79772",
    "sg:province":"TX",
    "sg:tags":[
        "machine",
        "shop"
    ],
    "wof:name":"P H Machine Shop",
    "wof:placetype":"venue"
},
  "geometry": {"coordinates":[-103.518089,31.417607],"type":"Point"}
}