{
  "type": "Feature",
  "properties": {
    "iso:country":"US",
    "sg:address":"7103 Castleview Ln",
    "sg:city":"Missouri City",
    "sg:classifiers":[
        {
            "category":"Social Services",
            "type":"Services"
        }
    ],
    "sg:phone":"+1 281 437 6157",
    "sg:postcode":"77489",
    "sg:province":"TX",
    "wof:name":"Just For My Empowerment ME",
    "wof:placetype":"venue"
},
  "geometry": {"coordinates":[-95.492464,29.600481],"type":"Point"}
}