{
  "type": "Feature",
  "properties": {
    "iso:country":"US",
    "sg:address":"4805 Bellmead Dr",
    "sg:city":"Waco",
    "sg:classifiers":[
        {
            "category":"Wholesale",
            "subcategory":"Toys & Hobbies",
            "type":"Manufacturing & Wholesale Goods"
        }
    ],
    "sg:phone":"+1 254 799 3740",
    "sg:postcode":"76705",
    "sg:province":"TX",
    "wof:name":"S & W Fireworks Stand",
    "wof:placetype":"venue"
},
  "geometry": {"coordinates":[-97.07013999999999,31.608884],"type":"Point"}
}