{
  "type": "Feature",
  "properties": {
    "iso:country":"US",
    "sg:address":"625 E 52nd St",
    "sg:city":"Odessa",
    "sg:classifiers":[
        {
            "category":"Social Services",
            "subcategory":"Child Care",
            "type":"Services"
        }
    ],
    "sg:phone":"+1 432 362 1600",
    "sg:postcode":"79762",
    "sg:province":"TX",
    "sg:tags":[
        "day"
    ],
    "wof:name":"Kids & Cares Learning Center",
    "wof:placetype":"venue"
},
  "geometry": {"coordinates":[-102.378506,31.894985],"type":"Point"}
}