{
  "type": "Feature",
  "properties": {
    "iso:country":"US",
    "sg:address":"1601 S 14th St",
    "sg:city":"Abilene",
    "sg:classifiers":[
        {
            "category":"Real Estate",
            "subcategory":"Real Estate Operator",
            "type":"Services"
        }
    ],
    "sg:phone":"+1 325 690 0123",
    "sg:postcode":"79602",
    "sg:province":"TX",
    "sg:tags":[
        "apartment"
    ],
    "sg:website":"www.werentabilene.com",
    "wof:name":"Quadrangle Apartments",
    "wof:placetype":"venue"
},
  "geometry": {"coordinates":[-99.74157700000001,32.432014],"type":"Point"}
}