{
  "type": "Feature",
  "properties": {
    "iso:country":"US",
    "sg:address":"919 N Carroll Blvd",
    "sg:city":"Denton",
    "sg:classifiers":[
        {
            "category":"Real Estate",
            "subcategory":"Real Estate Agent",
            "type":"Services"
        }
    ],
    "sg:phone":"+1 940 566 2730",
    "sg:postcode":"76201",
    "sg:province":"TX",
    "sg:website":"www.ntrealtor.com",
    "wof:name":"Barbara Russell Realtors Inc",
    "wof:placetype":"venue"
},
  "geometry": {"coordinates":[-97.13717699999999,33.223824],"type":"Point"}
}