{
  "type": "Feature",
  "properties": {
    "iso:country":"US",
    "sg:address":"4122 Lakeshore Forest Dr",
    "sg:city":"Missouri City",
    "sg:classifiers":[
        {
            "category":"Mining & Drilling",
            "type":"Manufacturing & Wholesale Goods"
        }
    ],
    "sg:phone":"+1 281 835 0161",
    "sg:postcode":"77459",
    "sg:province":"TX",
    "sg:tags":[
        "field"
    ],
    "wof:name":"Cambridge Geosciences Ltd Co",
    "wof:placetype":"venue"
},
  "geometry": {"coordinates":[-95.53133699999999,29.556019],"type":"Point"}
}