{
  "type": "Feature",
  "properties": {
    "iso:country":"US",
    "sg:address":"227 New Laredo Hwy",
    "sg:city":"San Antonio",
    "sg:classifiers":[
        {
            "category":"Home & Garden",
            "subcategory":"Building Materials",
            "type":"Retail Goods"
        }
    ],
    "sg:phone":"+1 210 924 5131",
    "sg:postcode":"78211",
    "sg:province":"TX",
    "wof:name":"Mgafg LLC",
    "wof:placetype":"venue"
},
  "geometry": {"coordinates":[-98.538657,29.372263],"type":"Point"}
}