{
  "type": "Feature",
  "properties": {
    "iso:country":"US",
    "sg:address":"318 E Richey Rd",
    "sg:city":"Houston",
    "sg:classifiers":[
        {
            "category":"Building & Trades",
            "subcategory":"Construction",
            "type":"Services"
        }
    ],
    "sg:phone":"+1 281 440 8557",
    "sg:postcode":"77073",
    "sg:province":"TX",
    "sg:tags":[
        "control",
        "erosion"
    ],
    "wof:name":"Erosion Control Inc",
    "wof:placetype":"venue"
},
  "geometry": {"coordinates":[-95.421588,29.998162],"type":"Point"}
}