{
  "type": "Feature",
  "properties": {
    "iso:country":"US",
    "sg:address":"11415 Burgoyne Dr",
    "sg:city":"Houston",
    "sg:classifiers":[
        {
            "category":"Shopping",
            "subcategory":"Bicycles & Sporting Goods",
            "type":"Retail Goods"
        }
    ],
    "sg:phone":"+1 281 493 5986",
    "sg:postcode":"77077",
    "sg:province":"TX",
    "wof:name":"River Rat Supply",
    "wof:placetype":"venue"
},
  "geometry": {"coordinates":[-95.577753,29.741979],"type":"Point"}
}