{
  "type": "Feature",
  "properties": {
    "iso:country":"US",
    "sg:address":"2407 E Griffin Pkwy",
    "sg:city":"Mission",
    "sg:classifiers":[
        {
            "category":"Health Services",
            "subcategory":"Dentist",
            "type":"Services"
        }
    ],
    "sg:phone":"+1 956 581 2773",
    "sg:postcode":"78572",
    "sg:province":"TX",
    "sg:tags":[
        "product",
        "whitening",
        "teeth"
    ],
    "wof:name":"Brann, Timothy W",
    "wof:placetype":"venue"
},
  "geometry": {"coordinates":[-98.283451,26.22414],"type":"Point"}
}