{
  "type": "Feature",
  "properties": {
    "iso:country":"US",
    "sg:address":"1009 S Big Spring St",
    "sg:city":"Midland",
    "sg:classifiers":[
        {
            "category":"Autos & Motor Vehicles",
            "subcategory":"Automobile Sales",
            "type":"Retail Goods"
        }
    ],
    "sg:phone":"+1 432 694 8952",
    "sg:postcode":"79701",
    "sg:province":"TX",
    "sg:tags":[
        "used"
    ],
    "wof:name":"Erickas New & Used Merchandis",
    "wof:placetype":"venue"
},
  "geometry": {"coordinates":[-102.077685,31.987071],"type":"Point"}
}