{
  "type": "Feature",
  "properties": {
    "iso:country":"US",
    "sg:address":"1022 Wirt Rd",
    "sg:city":"Houston",
    "sg:classifiers":[
        {
            "category":"Shopping",
            "subcategory":"Stationery & Office Supplies",
            "type":"Retail Goods"
        }
    ],
    "sg:phone":"+1 713 957 4700",
    "sg:postcode":"77055",
    "sg:province":"TX",
    "sg:tags":[
        "printing",
        "offset",
        "furniture"
    ],
    "wof:name":"Office Effects Inc",
    "wof:placetype":"venue"
},
  "geometry": {"coordinates":[-95.48477,29.785925],"type":"Point"}
}