{
  "type": "Feature",
  "properties": {
    "iso:country":"US",
    "sg:address":"4815 50th St",
    "sg:city":"Lubbock",
    "sg:classifiers":[
        {
            "category":"Shopping",
            "subcategory":"Used Merchandise",
            "type":"Retail Goods"
        },
        {
            "category":"Shopping",
            "subcategory":"Clothing, Apparel, & Fashions",
            "type":"Retail Goods"
        }
    ],
    "sg:phone":"+1 806 788 1555",
    "sg:postcode":"79414",
    "sg:province":"TX",
    "sg:tags":[
        "infant",
        "wear"
    ],
    "wof:name":"Once Upon A Child",
    "wof:placetype":"venue"
},
  "geometry": {"coordinates":[-101.917813,33.548678],"type":"Point"}
}