{
  "type": "Feature",
  "properties": {
    "iso:country":"US",
    "sg:address":"8713 Golden Pond Dr",
    "sg:city":"Rowlett",
    "sg:classifiers":[
        {
            "category":"Building & Trades",
            "subcategory":"Construction",
            "type":"Services"
        }
    ],
    "sg:phone":"+1 972 475 9700",
    "sg:postcode":"75089",
    "sg:province":"TX",
    "sg:tags":[
        "contractor"
    ],
    "wof:name":"Todd Wilson Marble & Tile",
    "wof:placetype":"venue"
},
  "geometry": {"coordinates":[-96.51699600000001,32.923151],"type":"Point"}
}