{
  "type": "Feature",
  "properties": {
    "iso:country":"US",
    "sg:address":"2109 San Pedro Ave",
    "sg:city":"San Antonio",
    "sg:classifiers":[
        {
            "category":"Professional",
            "subcategory":"Accounting & Tax Preparation",
            "type":"Services"
        }
    ],
    "sg:phone":"+1 210 733 6619",
    "sg:postcode":"78212",
    "sg:province":"TX",
    "sg:tags":[
        "accountant"
    ],
    "wof:name":"Enrique S Gonzalez CPA",
    "wof:placetype":"venue"
},
  "geometry": {"coordinates":[-98.499371,29.454746],"type":"Point"}
}