{
  "type": "Feature",
  "properties": {
    "iso:country":"US",
    "sg:address":"600 W Cotton St",
    "sg:city":"Longview",
    "sg:classifiers":[
        {
            "category":"Autos & Motor Vehicles",
            "subcategory":"Automobile Sales",
            "type":"Retail Goods"
        }
    ],
    "sg:phone":"+1 903 553 1476",
    "sg:postcode":"75604",
    "sg:province":"TX",
    "sg:tags":[
        "dealers-used",
        "car",
        "used",
        "cars-wholesale"
    ],
    "wof:name":"Certified Used Cars",
    "wof:placetype":"venue"
},
  "geometry": {"coordinates":[-94.75160200000001,32.496101],"type":"Point"}
}