{
  "type": "Feature",
  "properties": {
    "iso:country":"US",
    "sg:address":"4607 Glennwood Dr",
    "sg:city":"Killeen",
    "sg:classifiers":[
        {
            "category":"Arts & Performance",
            "subcategory":"Theater",
            "type":"Entertainment"
        }
    ],
    "sg:phone":"+1 254 690 7849",
    "sg:postcode":"76542",
    "sg:province":"TX",
    "sg:tags":[
        "group"
    ],
    "wof:name":"U Can Sing Karaoke",
    "wof:placetype":"venue"
},
  "geometry": {"coordinates":[-97.70129300000001,31.067058],"type":"Point"}
}