{
  "type": "Feature",
  "properties": {
    "iso:country":"US",
    "sg:address":"3822 Greenshadow Dr",
    "sg:city":"Pasadena",
    "sg:classifiers":[
        {
            "category":"Organizations",
            "subcategory":"Religious Organization",
            "type":"Services"
        }
    ],
    "sg:phone":"+1 713 477 8986",
    "sg:postcode":"77503",
    "sg:province":"TX",
    "sg:tags":[
        "church"
    ],
    "sg:website":"www.calvarychapelag.org",
    "wof:name":"Calvary Chapel Assembly Of God",
    "wof:placetype":"venue"
},
  "geometry": {"coordinates":[-95.15358999999999,29.70169],"type":"Point"}
}