{
  "type": "Feature",
  "properties": {
    "iso:country":"US",
    "sg:address":"150 S Main St",
    "sg:city":"Farmersville",
    "sg:classifiers":[
        {
            "category":"Building & Trades",
            "subcategory":"Plumbing",
            "type":"Services"
        }
    ],
    "sg:phone":"+1 972 754 5040",
    "sg:postcode":"75442",
    "sg:province":"TX",
    "sg:tags":[
        "plumber",
        "contractor"
    ],
    "wof:name":"Tri-County Plumbing",
    "wof:placetype":"venue"
},
  "geometry": {"coordinates":[-96.36000900000001,33.162244],"type":"Point"}
}