{
  "type": "Feature",
  "properties": {
    "iso:country":"US",
    "sg:address":"616 W Arkansas Ave",
    "sg:city":"Vivian",
    "sg:classifiers":[
        {
            "category":"Insurance",
            "subcategory":"Insurance Agent",
            "type":"Services"
        }
    ],
    "sg:phone":"+1 318 375 2405",
    "sg:postcode":"71082",
    "sg:province":"TX",
    "wof:name":"Richard Rein",
    "wof:placetype":"venue"
},
  "geometry": {"coordinates":[-93.992408,32.873206],"type":"Point"}
}