{
  "type": "Feature",
  "properties": {
    "iso:country":"US",
    "sg:address":"611 W 11th St",
    "sg:city":"Weslaco",
    "sg:classifiers":[
        {
            "category":"Organizations",
            "subcategory":"Community Association",
            "type":"Services"
        }
    ],
    "sg:phone":"+1 956 968 3876",
    "sg:postcode":"78596",
    "sg:province":"TX",
    "wof:name":"Lions International Weslaco",
    "wof:placetype":"venue"
},
  "geometry": {"coordinates":[-97.996686,26.148867],"type":"Point"}
}