{
  "type": "Feature",
  "properties": {
    "iso:country":"US",
    "sg:address":"2933 Prince Hall Sq",
    "sg:city":"Dallas",
    "sg:classifiers":[
        {
            "category":"Social Services",
            "subcategory":"Child Care",
            "type":"Services"
        }
    ],
    "sg:phone":"+1 214 372 2701",
    "sg:postcode":"75216",
    "sg:province":"TX",
    "wof:name":"Mekia's Day Care",
    "wof:placetype":"venue"
},
  "geometry": {"coordinates":[-96.77210599999999,32.695977],"type":"Point"}
}