{
  "type": "Feature",
  "properties": {
    "iso:country":"US",
    "sg:address":"114 S Broadway St",
    "sg:city":"Mcallen",
    "sg:classifiers":[
        {
            "category":"Shopping",
            "type":"Retail Goods"
        }
    ],
    "sg:phone":"+1 956 618 2378",
    "sg:postcode":"78501",
    "sg:province":"TX",
    "sg:tags":[
        "equipment",
        "merchandise"
    ],
    "wof:name":"Best Medical Supply",
    "wof:placetype":"venue"
},
  "geometry": {"coordinates":[-98.23365800000001,26.20238],"type":"Point"}
}