{
  "type": "Feature",
  "properties": {
    "iso:country":"US",
    "sg:address":"3512 Ransom Cir",
    "sg:city":"Denison",
    "sg:classifiers":[
        {
            "category":"Banks & Credit Unions",
            "subcategory":"Financial Services",
            "type":"Services"
        }
    ],
    "sg:phone":"+1 903 465 9284",
    "sg:postcode":"75020",
    "sg:province":"TX",
    "sg:tags":[
        "company",
        "holding"
    ],
    "wof:name":"B&S Holdings Inc",
    "wof:placetype":"venue"
},
  "geometry": {"coordinates":[-96.59045500000001,33.753887],"type":"Point"}
}