{
  "type": "Feature",
  "properties": {
    "iso:country":"US",
    "sg:address":"2707 Fairway Dr",
    "sg:city":"Orange",
    "sg:classifiers":[
        {
            "category":"Professional",
            "subcategory":"Detective & Security Services",
            "type":"Services"
        }
    ],
    "sg:phone":"+1 409 670 5841",
    "sg:postcode":"77630",
    "sg:province":"TX",
    "sg:tags":[
        "information",
        "bureau"
    ],
    "wof:name":"Time Makers Errand Service",
    "wof:placetype":"venue"
},
  "geometry": {"coordinates":[-93.75513599999999,30.115654],"type":"Point"}
}