{
  "type": "Feature",
  "properties": {
    "iso:country":"US",
    "sg:address":"15477 US Hwy 290",
    "sg:city":"Burton",
    "sg:classifiers":[
        {
            "category":"Retail",
            "subcategory":"Repair Shop",
            "type":"Services"
        }
    ],
    "sg:phone":"+1 979 289 4634",
    "sg:postcode":"77835",
    "sg:province":"TX",
    "sg:tags":[
        "welding"
    ],
    "wof:name":"Brad's Custom Welding",
    "wof:placetype":"venue"
},
  "geometry": {"coordinates":[-96.612088,30.166305],"type":"Point"}
}