{
  "type": "Feature",
  "properties": {
    "iso:country":"US",
    "sg:address":"2325 Crestlake Dr",
    "sg:city":"Rockwall",
    "sg:classifiers":[
        {
            "category":"Retail",
            "subcategory":"Auto Repair",
            "type":"Services"
        }
    ],
    "sg:phone":"+1 972 289 6229",
    "sg:postcode":"75087",
    "sg:province":"TX",
    "sg:tags":[
        "automotive",
        "general"
    ],
    "wof:name":"Computech",
    "wof:placetype":"venue"
},
  "geometry": {"coordinates":[-96.48319499999999,32.945554],"type":"Point"}
}