{
  "type": "Feature",
  "properties": {
    "iso:country":"US",
    "sg:address":"3903 Eisenhauer Rd",
    "sg:city":"San Antonio",
    "sg:classifiers":[
        {
            "category":"Retail",
            "subcategory":"Laundry & Dry Cleaning",
            "type":"Services"
        }
    ],
    "sg:phone":"+1 210 653 5100",
    "sg:postcode":"78218",
    "sg:province":"TX",
    "sg:tags":[
        "rug"
    ],
    "wof:name":"Rug Palace",
    "wof:placetype":"venue"
},
  "geometry": {"coordinates":[-98.418446,29.496653],"type":"Point"}
}