{
  "type": "Feature",
  "properties": {
    "iso:country":"US",
    "sg:address":"934 S Park St",
    "sg:city":"Uvalde",
    "sg:classifiers":[
        {
            "category":"Retail",
            "subcategory":"Repair Shop",
            "type":"Services"
        }
    ],
    "sg:phone":"+1 830 278 1378",
    "sg:postcode":"78801",
    "sg:province":"TX",
    "sg:tags":[
        "pump"
    ],
    "wof:name":"C W Drilling Co",
    "wof:placetype":"venue"
},
  "geometry": {"coordinates":[-99.78330699999999,29.194592],"type":"Point"}
}