{
  "type": "Feature",
  "properties": {
    "iso:country":"US",
    "sg:address":"505 McCarty St",
    "sg:city":"Yoakum",
    "sg:classifiers":[
        {
            "category":"Health Services",
            "subcategory":"Nursing And Care Facility",
            "type":"Services"
        }
    ],
    "sg:phone":"+1 361 293 5268",
    "sg:postcode":"77995",
    "sg:province":"TX",
    "sg:tags":[
        "ill",
        "provides",
        "for",
        "terminally"
    ],
    "wof:name":"Hospice Texas Yoakum",
    "wof:placetype":"venue"
},
  "geometry": {"coordinates":[-97.153839,29.29035],"type":"Point"}
}