{
  "type": "Feature",
  "properties": {
    "iso:country":"US",
    "sg:address":"206 S Main St",
    "sg:city":"Burnet",
    "sg:classifiers":[
        {
            "category":"Shopping",
            "subcategory":"Used Merchandise",
            "type":"Retail Goods"
        }
    ],
    "sg:phone":"+1 512 756 7783",
    "sg:postcode":"78611",
    "sg:province":"TX",
    "sg:tags":[
        "antique"
    ],
    "wof:name":"Burnet Antique Mall",
    "wof:placetype":"venue"
},
  "geometry": {"coordinates":[-98.22756699999999,30.757307],"type":"Point"}
}