{
  "type": "Feature",
  "properties": {
    "iso:country":"US",
    "sg:address":"900 Hickey Ct",
    "sg:city":"Granbury",
    "sg:classifiers":[
        {
            "category":"Restaurant",
            "type":"Food & Drink"
        }
    ],
    "sg:phone":"+1 817 279 1753",
    "sg:postcode":"76049",
    "sg:province":"TX",
    "sg:tags":[
        "eating"
    ],
    "wof:name":"R&M Enterprises",
    "wof:placetype":"venue"
},
  "geometry": {"coordinates":[-97.76347699999999,32.536133],"type":"Point"}
}