{
  "type": "Feature",
  "properties": {
    "iso:country":"US",
    "sg:address":"500 Elm St",
    "sg:city":"Dallas",
    "sg:classifiers":[
        {
            "category":"Professional",
            "subcategory":"Research",
            "type":"Services"
        },
        {
            "category":"Education",
            "subcategory":"Library",
            "type":"Public Place"
        },
        {
            "category":"Professional",
            "subcategory":"Business Services",
            "type":"Services"
        }
    ],
    "sg:phone":"+1 214 741 2424",
    "sg:postcode":"75202",
    "sg:province":"TX",
    "sg:tags":[
        "consultant",
        "coach"
    ],
    "wof:name":"North Texas Research Group",
    "wof:placetype":"venue"
},
  "geometry": {"coordinates":[-96.80806699999999,32.779549],"type":"Point"}
}