{
  "type": "Feature",
  "properties": {
    "iso:country":"US",
    "sg:address":"1815 Broadway St",
    "sg:city":"Rockport",
    "sg:classifiers":[
        {
            "category":"Autos & Motor Vehicles",
            "subcategory":"Boat Sales",
            "type":"Retail Goods"
        }
    ],
    "sg:phone":"+1 361 729 3486",
    "sg:postcode":"78382",
    "sg:province":"TX",
    "sg:tags":[
        "business"
    ],
    "wof:name":"Sailing Unlimited",
    "wof:placetype":"venue"
},
  "geometry": {"coordinates":[-97.03404399999999,28.047196],"type":"Point"}
}