{
  "type": "Feature",
  "properties": {
    "iso:country":"US",
    "sg:address":"855 NE Alsbury Blvd Ste 600",
    "sg:city":"Burleson",
    "sg:classifiers":[
        {
            "category":"Professional",
            "subcategory":"Lawyer & Legal Services",
            "type":"Services"
        }
    ],
    "sg:phone":"+1 817 426 1313",
    "sg:postcode":"76028",
    "sg:province":"TX",
    "wof:name":"Attorney Offices Of Walker & Walker",
    "wof:placetype":"venue"
},
  "geometry": {"coordinates":[-97.32121100000001,32.563228],"type":"Point"}
}