{
  "type": "Feature",
  "properties": {
    "iso:country":"US",
    "sg:address":"1003 W Sam Rayburn Dr",
    "sg:city":"Bonham",
    "sg:classifiers":[
        {
            "category":"Autos & Motor Vehicles",
            "subcategory":"Auto Supplies",
            "type":"Retail Goods"
        }
    ],
    "sg:phone":"+1 903 583 9069",
    "sg:postcode":"75418",
    "sg:province":"TX",
    "sg:tags":[
        "tire"
    ],
    "wof:name":"D & D Tire Shop",
    "wof:placetype":"venue"
},
  "geometry": {"coordinates":[-96.191278,33.577165],"type":"Point"}
}