{
  "type": "Feature",
  "properties": {
    "iso:country":"US",
    "sg:address":"414 N General McMullen Dr",
    "sg:city":"San Antonio",
    "sg:classifiers":[
        {
            "category":"Professional",
            "subcategory":"Management & Consulting",
            "type":"Services"
        }
    ],
    "sg:phone":"+1 210 432 6333",
    "sg:postcode":"78237",
    "sg:province":"TX",
    "sg:tags":[
        "consultant",
        "training"
    ],
    "wof:name":"Advanced Medical Training",
    "wof:placetype":"venue"
},
  "geometry": {"coordinates":[-98.553212,29.436766],"type":"Point"}
}