{
  "type": "Feature",
  "properties": {
    "iso:country":"US",
    "sg:address":"8737 Bluffcreek Ln",
    "sg:city":"Plano",
    "sg:classifiers":[
        {
            "category":"Banks & Credit Unions",
            "subcategory":"Bank",
            "type":"Services"
        }
    ],
    "sg:phone":"+1 214 618 6162",
    "sg:postcode":"75024",
    "sg:province":"TX",
    "sg:tags":[
        "loan",
        "real estate"
    ],
    "wof:name":"Prosper Financial Group Inc",
    "wof:placetype":"venue"
},
  "geometry": {"coordinates":[-96.78351000000001,33.097952],"type":"Point"}
}