{
  "type": "Feature",
  "properties": {
    "iso:country":"US",
    "sg:address":"10777 Southwest Fwy",
    "sg:city":"Houston",
    "sg:classifiers":[
        {
            "category":"Banks & Credit Unions",
            "subcategory":"Bank",
            "type":"Services"
        }
    ],
    "sg:phone":"+1 713 988 5615",
    "sg:postcode":"77074",
    "sg:province":"TX",
    "sg:website":"www.pplmotorhomes.com",
    "wof:name":"First State Premium",
    "wof:placetype":"venue"
},
  "geometry": {"coordinates":[-95.553692,29.663366],"type":"Point"}
}