{
  "type": "Feature",
  "properties": {
    "iso:country":"US",
    "sg:address":"2431 W Mistletoe Ave",
    "sg:city":"San Antonio",
    "sg:classifiers":[
        {
            "category":"Retail",
            "subcategory":"Laundry & Dry Cleaning",
            "type":"Services"
        }
    ],
    "sg:phone":"+1 210 421 4810",
    "sg:postcode":"78228",
    "sg:province":"TX",
    "sg:tags":[
        "cleaners",
        "rug",
        "carpet"
    ],
    "wof:name":"S & S Carpet Cleaning Svc",
    "wof:placetype":"venue"
},
  "geometry": {"coordinates":[-98.540648,29.45654],"type":"Point"}
}