{
  "type": "Feature",
  "properties": {
    "iso:country":"US",
    "sg:address":"28528 Palm Blvd",
    "sg:city":"Harlingen",
    "sg:classifiers":[
        {
            "category":"Health Services",
            "subcategory":"Doctor",
            "type":"Services"
        }
    ],
    "sg:phone":"+1 956 618 7100",
    "sg:postcode":"78552",
    "sg:province":"TX",
    "sg:tags":[
        "physician",
        "surgeon"
    ],
    "wof:name":"Robert L Hatcher MD",
    "wof:placetype":"venue"
},
  "geometry": {"coordinates":[-97.74016,26.146603],"type":"Point"}
}