{
  "type": "Feature",
  "properties": {
    "iso:country":"US",
    "sg:address":"417 Ivan Dr",
    "sg:city":"Lewisville",
    "sg:classifiers":[
        {
            "category":"Autos & Motor Vehicles",
            "subcategory":"Boat Sales",
            "type":"Retail Goods"
        }
    ],
    "sg:phone":"+1 469 549 0673",
    "sg:postcode":"75067",
    "sg:province":"TX",
    "sg:tags":[
        "dealer",
        "sales"
    ],
    "wof:name":"Dallas Boat Show Inc",
    "wof:placetype":"venue"
},
  "geometry": {"coordinates":[-97.00035699999999,33.021584],"type":"Point"}
}