{
  "type": "Feature",
  "properties": {
    "iso:country":"US",
    "sg:address":"101 Pepper Bush St",
    "sg:city":"Shavano Park",
    "sg:classifiers":[
        {
            "category":"Utilities",
            "subcategory":"Telephone",
            "type":"Services"
        }
    ],
    "sg:phone":"+1 210 354 1111",
    "sg:postcode":"78231",
    "sg:province":"TX",
    "sg:tags":[
        "telecommunication"
    ],
    "wof:name":"Global Telecommunications Inc",
    "wof:placetype":"venue"
},
  "geometry": {"coordinates":[-98.556753,29.578006],"type":"Point"}
}