{
  "type": "Feature",
  "properties": {
    "iso:country":"US",
    "sg:address":"17275 Addison Rd",
    "sg:city":"Addison",
    "sg:classifiers":[
        {
            "category":"Real Estate",
            "subcategory":"Real Estate Agent",
            "type":"Services"
        }
    ],
    "sg:phone":"+1 972 931 2112",
    "sg:postcode":"75001",
    "sg:province":"TX",
    "wof:name":"Conrow Company",
    "wof:placetype":"venue"
},
  "geometry": {"coordinates":[-96.830404,32.979507],"type":"Point"}
}