{
  "type": "Feature",
  "properties": {
    "iso:country":"US",
    "sg:address":"1819 E Park Row Dr",
    "sg:city":"Arlington",
    "sg:classifiers":[
        {
            "category":"Retail",
            "subcategory":"Car Wash",
            "type":"Services"
        }
    ],
    "sg:phone":"+1 214 662 5958",
    "sg:postcode":"76010",
    "sg:province":"TX",
    "sg:tags":[
        "carwash"
    ],
    "wof:name":"Lewis Kwik Kar Wash",
    "wof:placetype":"venue"
},
  "geometry": {"coordinates":[-97.08137499999999,32.720913],"type":"Point"}
}