{
  "type": "Feature",
  "properties": {
    "iso:country":"US",
    "sg:address":"12065 Starcrest Dr",
    "sg:city":"San Antonio",
    "sg:classifiers":[
        {
            "category":"Building & Trades",
            "subcategory":"Construction",
            "type":"Services"
        }
    ],
    "sg:phone":"+1 210 494 1006",
    "sg:postcode":"78247",
    "sg:province":"TX",
    "sg:tags":[
        "house",
        "construct",
        "contractor"
    ],
    "wof:name":"Continuous Rain Gutters",
    "wof:placetype":"venue"
},
  "geometry": {"coordinates":[-98.467322,29.552054],"type":"Point"}
}