{
  "type": "Feature",
  "properties": {
    "iso:country":"US",
    "sg:address":"907 S Carroll Ave",
    "sg:city":"Dallas",
    "sg:classifiers":[
        {
            "category":"Organizations",
            "subcategory":"Community Association",
            "type":"Services"
        }
    ],
    "sg:phone":"+1 214 821 2182",
    "sg:postcode":"75223",
    "sg:province":"TX",
    "sg:tags":[
        "club"
    ],
    "wof:name":"Mario's Nite Club",
    "wof:placetype":"venue"
},
  "geometry": {"coordinates":[-96.761821,32.786545],"type":"Point"}
}