{
  "type": "Feature",
  "properties": {
    "iso:country":"US",
    "sg:address":"617 N Eastwood St",
    "sg:city":"Houston",
    "sg:classifiers":[
        {
            "category":"Retail",
            "subcategory":"Auto Repair",
            "type":"Services"
        }
    ],
    "sg:phone":"+1 713 923 2064",
    "sg:postcode":"77011",
    "sg:province":"TX",
    "wof:name":"Ortega Paul Services",
    "wof:placetype":"venue"
},
  "geometry": {"coordinates":[-95.32550000000001,29.7542],"type":"Point"}
}