{
  "type": "Feature",
  "properties": {
    "iso:country":"US",
    "sg:address":"3311 S Co Rd 1206",
    "sg:city":"Midland",
    "sg:classifiers":[
        {
            "category":"Retail",
            "subcategory":"Animal Services",
            "type":"Services"
        }
    ],
    "sg:phone":"+1 432 694 0008",
    "sg:postcode":"79706",
    "sg:province":"TX",
    "sg:tags":[
        "cat",
        "dog",
        "kennel"
    ],
    "wof:name":"Winnermaker Kennels",
    "wof:placetype":"venue"
},
  "geometry": {"coordinates":[-102.093816,31.950852],"type":"Point"}
}