{
  "type": "Feature",
  "properties": {
    "iso:country":"US",
    "sg:address":"11940 Manchaca Rd Ste 104 #111",
    "sg:city":"Austin",
    "sg:classifiers":[
        {
            "category":"Personal",
            "type":"Services"
        }
    ],
    "sg:phone":"+1 512 743 2560",
    "sg:postcode":"78748",
    "sg:province":"TX",
    "sg:tags":[
        "local"
    ],
    "sg:website":"www.scientificinstrumentationser...",
    "wof:name":"Scientific Instrumentation Services",
    "wof:placetype":"venue"
},
  "geometry": {"coordinates":[-97.835551,30.145613],"type":"Point"}
}