{
  "type": "Feature",
  "properties": {
    "iso:country":"US",
    "sg:address":"1401 Cll del Norte",
    "sg:city":"Laredo",
    "sg:classifiers":[
        {
            "category":"Real Estate",
            "subcategory":"Real Estate Agent",
            "type":"Services"
        }
    ],
    "sg:phone":"+1 956 753 3030",
    "sg:postcode":"78041",
    "sg:province":"TX",
    "wof:name":"Del Realty",
    "wof:placetype":"venue"
},
  "geometry": {"coordinates":[-99.48235699999999,27.450636],"type":"Point"}
}