{
  "type": "Feature",
  "properties": {
    "iso:country":"US",
    "sg:address":"501 S East St",
    "sg:city":"Weimar",
    "sg:classifiers":[
        {
            "category":"Building & Trades",
            "subcategory":"Equipment Rental",
            "type":"Services"
        },
        {
            "category":"Retail",
            "subcategory":"Storage",
            "type":"Services"
        }
    ],
    "sg:phone":"+1 979 725 9545",
    "sg:postcode":"78962",
    "sg:province":"TX",
    "sg:tags":[
        "commercial",
        "household",
        "yard",
        "store",
        "leasing"
    ],
    "wof:name":"Southwest Rail Industries, Inc.",
    "wof:placetype":"venue"
},
  "geometry": {"coordinates":[-96.77507799999999,29.6984],"type":"Point"}
}