{
  "type": "Feature",
  "properties": {
    "iso:country":"US",
    "sg:address":"10524 US Hwy 80",
    "sg:city":"Forney",
    "sg:classifiers":[
        {
            "category":"Shopping",
            "subcategory":"Used Merchandise",
            "type":"Retail Goods"
        }
    ],
    "sg:phone":"+1 972 564 4433",
    "sg:postcode":"75126",
    "sg:province":"TX",
    "wof:name":"Wholesale Antiques",
    "wof:placetype":"venue"
},
  "geometry": {"coordinates":[-96.436667,32.741383],"type":"Point"}
}