{
  "type": "Feature",
  "properties": {
    "iso:country":"US",
    "sg:address":"10860 Switzer Ave Suite 103",
    "sg:city":"Dallas",
    "sg:classifiers":[
        {
            "category":"Home & Garden",
            "subcategory":"Household Appliances",
            "type":"Retail Goods"
        },
        {
            "category":"Building & Trades",
            "subcategory":"Construction",
            "type":"Services"
        }
    ],
    "sg:phone":"+1 214 342 2665",
    "sg:postcode":"75238",
    "sg:province":"TX",
    "sg:tags":[
        "system",
        "specialty",
        "heat",
        "contractor",
        "pump",
        "heating",
        "ventilating",
        "air conditioning"
    ],
    "sg:website":"http://dallas.citysearch.com/profile/external/47564586/dallas_tx/empire_mechanical_heating_ac_inc_.html?publisher=yellowpages&reference_id=1&placement=ypwebsitemip",
    "wof:name":"Empire Mechanical Heating & AC, Inc.",
    "wof:placetype":"venue"
},
  "geometry": {"coordinates":[-96.704559,32.895859],"type":"Point"}
}