{
  "type": "Feature",
  "properties": {
    "iso:country":"US",
    "sg:address":"500 E 4th St",
    "sg:city":"Austin",
    "sg:classifiers":[
        {
            "category":"Restaurant",
            "type":"Food & Drink"
        }
    ],
    "sg:phone":"+1 512 493 4901",
    "sg:postcode":"78701",
    "sg:province":"TX",
    "sg:tags":[
        "eating"
    ],
    "wof:name":"Liberty Tavern",
    "wof:placetype":"venue"
},
  "geometry": {"coordinates":[-97.73784000000001,30.264626],"type":"Point"}
}