{
  "type": "Feature",
  "properties": {
    "iso:country":"US",
    "sg:address":"5116 Alba Rd",
    "sg:city":"Houston",
    "sg:classifiers":[
        {
            "category":"Real Estate",
            "subcategory":"Real Estate Operator",
            "type":"Services"
        }
    ],
    "sg:phone":"+1 713 688 2353",
    "sg:postcode":"77018",
    "sg:province":"TX",
    "sg:tags":[
        "apartment"
    ],
    "wof:name":"Candlelight Garden Apartments",
    "wof:placetype":"venue"
},
  "geometry": {"coordinates":[-95.420283,29.841011],"type":"Point"}
}