{
  "type": "Feature",
  "properties": {
    "iso:country":"US",
    "sg:address":"960 Early Blvd",
    "sg:city":"Early",
    "sg:classifiers":[
        {
            "category":"Government",
            "subcategory":"Office",
            "type":"Public Place"
        }
    ],
    "sg:phone":"+1 325 643 5451",
    "sg:postcode":"76802",
    "sg:province":"TX",
    "sg:tags":[
        "township",
        "government-city",
        "village"
    ],
    "wof:name":"Fire Department",
    "wof:placetype":"venue"
},
  "geometry": {"coordinates":[-98.903423,31.75967],"type":"Point"}
}