{
  "type": "Feature",
  "properties": {
    "iso:country":"US",
    "sg:address":"9020 N Capital of Texas Hwy",
    "sg:city":"Austin",
    "sg:classifiers":[
        {
            "category":"Restaurant",
            "type":"Food & Drink"
        }
    ],
    "sg:phone":"+1 512 340 9989",
    "sg:postcode":"78759",
    "sg:province":"TX",
    "sg:tags":[
        "eating",
        "caterer"
    ],
    "wof:name":"Lizzard Rock Cafe",
    "wof:placetype":"venue"
},
  "geometry": {"coordinates":[-97.756998,30.388222],"type":"Point"}
}