{
  "type": "Feature",
  "properties": {
    "iso:country":"US",
    "sg:address":"2525 National Dr",
    "sg:city":"Garland",
    "sg:classifiers":[
        {
            "category":"Building & Trades",
            "subcategory":"Cleaning & Sanitation",
            "type":"Services"
        }
    ],
    "sg:phone":"+1 972 278 2664",
    "sg:postcode":"75041",
    "sg:province":"TX",
    "sg:tags":[
        "ventilating",
        "system"
    ],
    "sg:website":"www.filter-1.com",
    "wof:name":"Clean Air Consultants",
    "wof:placetype":"venue"
},
  "geometry": {"coordinates":[-96.671539,32.885794],"type":"Point"}
}