{
  "type": "Feature",
  "properties": {
    "iso:country":"US",
    "sg:address":"4438 Griggs Rd",
    "sg:city":"Houston",
    "sg:classifiers":[
        {
            "category":"Wholesale",
            "subcategory":"Electrical",
            "type":"Manufacturing & Wholesale Goods"
        }
    ],
    "sg:phone":"+1 713 741 7020",
    "sg:postcode":"77021",
    "sg:province":"TX",
    "sg:tags":[
        "radio"
    ],
    "wof:name":"Aero Pagers 2000",
    "wof:placetype":"venue"
},
  "geometry": {"coordinates":[-95.34868400000001,29.701736],"type":"Point"}
}