{
  "type": "Feature",
  "properties": {
    "iso:country":"US",
    "sg:address":"2110 Crystal River Dr",
    "sg:city":"Humble",
    "sg:classifiers":[
        {
            "category":"Professional",
            "subcategory":"Management & Consulting",
            "type":"Services"
        }
    ],
    "sg:phone":"+1 281 361 0939",
    "sg:postcode":"77345",
    "sg:province":"TX",
    "wof:name":"Cimarron Energy Marketing",
    "wof:placetype":"venue"
},
  "geometry": {"coordinates":[-95.170129,30.046976],"type":"Point"}
}