{
  "type": "Feature",
  "properties": {
    "iso:country":"US",
    "sg:address":"333 Water St",
    "sg:city":"Kerrville",
    "sg:classifiers":[
        {
            "category":"Real Estate",
            "subcategory":"Real Estate Operator",
            "type":"Services"
        }
    ],
    "sg:phone":"+1 830 257 8220",
    "sg:postcode":"78028",
    "sg:province":"TX",
    "sg:tags":[
        "apartment"
    ],
    "wof:name":"River Oaks Apartments",
    "wof:placetype":"venue"
},
  "geometry": {"coordinates":[-99.145464,30.050013],"type":"Point"}
}