{
  "type": "Feature",
  "properties": {
    "iso:country":"US",
    "sg:address":"121 W Debbie Ln",
    "sg:city":"Mansfield",
    "sg:phone":"+1 682 518 6916",
    "sg:postcode":"76063",
    "sg:province":"TX",
    "wof:name":"Fancy Nails & Spa",
    "wof:placetype":"venue"
},
  "geometry": {"coordinates":[-97.144981,32.592467],"type":"Point"}
}