{
  "type": "Feature",
  "properties": {
    "iso:country":"US",
    "sg:address":"3100 Timmons Ln",
    "sg:city":"Houston",
    "sg:classifiers":[
        {
            "category":"Health Services",
            "subcategory":"Doctor",
            "type":"Services"
        }
    ],
    "sg:phone":"+1 713 529 3867",
    "sg:postcode":"77027",
    "sg:province":"TX",
    "wof:name":"Patel Nimisha Md",
    "wof:placetype":"venue"
},
  "geometry": {"coordinates":[-95.436711,29.736698],"type":"Point"}
}