{
  "type": "Feature",
  "properties": {
    "iso:country":"US",
    "sg:address":"8600 Woodway Dr",
    "sg:city":"Houston",
    "sg:classifiers":[
        {
            "category":"Real Estate",
            "subcategory":"Real Estate Operator",
            "type":"Services"
        }
    ],
    "sg:phone":"+1 713 780 1720",
    "sg:postcode":"77063",
    "sg:province":"TX",
    "sg:tags":[
        "apartment"
    ],
    "wof:name":"Creekside Apartments",
    "wof:placetype":"venue"
},
  "geometry": {"coordinates":[-95.517555,29.741173],"type":"Point"}
}