{
  "type": "Feature",
  "properties": {
    "iso:country":"US",
    "sg:address":"7900 Gulf Fwy",
    "sg:city":"Houston",
    "sg:classifiers":[
        {
            "category":"Shopping",
            "subcategory":"Florist",
            "type":"Retail Goods"
        }
    ],
    "sg:phone":"+1 713 644 1691",
    "sg:postcode":"77017",
    "sg:province":"TX",
    "wof:name":"Discount Flowers",
    "wof:placetype":"venue"
},
  "geometry": {"coordinates":[-95.276802,29.684299],"type":"Point"}
}