{
  "type": "Feature",
  "properties": {
    "iso:country":"US",
    "sg:address":"128 S Brooks St",
    "sg:city":"Brazoria",
    "sg:classifiers":[
        {
            "category":"Retail",
            "subcategory":"Auto Repair",
            "type":"Services"
        }
    ],
    "sg:phone":"+1 979 798 9124",
    "sg:postcode":"77422",
    "sg:province":"TX",
    "sg:tags":[
        "repairing",
        "automobile"
    ],
    "wof:name":"A Mobile Car Care",
    "wof:placetype":"venue"
},
  "geometry": {"coordinates":[-95.569991,29.045693],"type":"Point"}
}