{
  "type": "Feature",
  "properties": {
    "iso:country":"US",
    "sg:address":"2216 Westlake Dr",
    "sg:city":"Austin",
    "sg:classifiers":[
        {
            "category":"Professional",
            "type":"Services"
        }
    ],
    "sg:phone":"+1 512 347 0954",
    "sg:postcode":"78746",
    "sg:province":"TX",
    "wof:name":"Webtrans L L C",
    "wof:placetype":"venue"
},
  "geometry": {"coordinates":[-97.784918,30.302904],"type":"Point"}
}