{
  "type": "Feature",
  "properties": {
    "iso:country":"US",
    "sg:address":"117 S Commercial St",
    "sg:city":"Aransas Pass",
    "sg:classifiers":[
        {
            "category":"Food & Beverages",
            "subcategory":"Liquor & Beverages",
            "type":"Retail Goods"
        }
    ],
    "sg:phone":"+1 361 758 7678",
    "sg:postcode":"78336",
    "sg:province":"TX",
    "wof:name":"Homeport Liquor",
    "wof:placetype":"venue"
},
  "geometry": {"coordinates":[-97.144338,27.904932],"type":"Point"}
}