{
  "type": "Feature",
  "properties": {
    "iso:country":"US",
    "sg:address":"100 W Walnut St",
    "sg:city":"Taylor",
    "sg:classifiers":[
        {
            "category":"Food & Beverages",
            "subcategory":"Groceries & Convenience Stores",
            "type":"Retail Goods"
        }
    ],
    "sg:phone":"+1 512 352 7708",
    "sg:postcode":"76574",
    "sg:province":"TX",
    "wof:name":"Bien Grocery",
    "wof:placetype":"venue"
},
  "geometry": {"coordinates":[-97.40904999999999,30.564711],"type":"Point"}
}