{
  "type": "Feature",
  "properties": {
    "iso:country":"US",
    "sg:address":"100 E 6th St",
    "sg:city":"Pecos",
    "sg:classifiers":[
        {
            "category":"Banks & Credit Unions",
            "subcategory":"Bank",
            "type":"Services"
        }
    ],
    "sg:phone":"+1 432 445 9444",
    "sg:postcode":"79772",
    "sg:province":"TX",
    "sg:website":"www.wtnb.com",
    "wof:name":"West Texas National Bank",
    "wof:placetype":"venue"
},
  "geometry": {"coordinates":[-103.492987,31.422984],"type":"Point"}
}