{
  "type": "Feature",
  "properties": {
    "iso:country":"US",
    "sg:address":"730 S Main St",
    "sg:city":"Jacksboro",
    "sg:classifiers":[
        {
            "category":"Government",
            "subcategory":"Office",
            "type":"Public Place"
        }
    ],
    "sg:phone":"+1 940 567 6611",
    "sg:postcode":"76458",
    "sg:province":"TX",
    "sg:tags":[
        "state",
        "program"
    ],
    "wof:name":"Transportation Dept Mntnc",
    "wof:placetype":"venue"
},
  "geometry": {"coordinates":[-98.145073,33.195521],"type":"Point"}
}