{
  "type": "Feature",
  "properties": {
    "iso:country":"US",
    "sg:address":"107 W Chestnut St",
    "sg:city":"Throckmorton",
    "sg:classifiers":[
        {
            "category":"Insurance",
            "subcategory":"Insurance Agent",
            "type":"Services"
        }
    ],
    "sg:phone":"+1 940 849 2201",
    "sg:postcode":"76483",
    "sg:province":"TX",
    "wof:name":"Liles Boyd Insurance",
    "wof:placetype":"venue"
},
  "geometry": {"coordinates":[-99.177492,33.178588],"type":"Point"}
}