{
  "type": "Feature",
  "properties": {
    "iso:country":"US",
    "sg:address":"230 W Colorado St",
    "sg:city":"La Grange",
    "sg:classifiers":[
        {
            "category":"Personal",
            "subcategory":"Beauty Salon",
            "type":"Services"
        }
    ],
    "sg:phone":"+1 979 968 8184",
    "sg:postcode":"78945",
    "sg:province":"TX",
    "sg:tags":[
        "shop"
    ],
    "wof:name":"Trends Salon & Day Spa",
    "wof:placetype":"venue"
},
  "geometry": {"coordinates":[-96.878659,29.90585],"type":"Point"}
}