{
  "type": "Feature",
  "properties": {
    "iso:country":"US",
    "sg:address":"4402 Burnet Rd",
    "sg:city":"Austin",
    "sg:classifiers":[
        {
            "category":"Health Services",
            "subcategory":"Clinic",
            "type":"Services"
        }
    ],
    "sg:phone":"+1 512 480 8788",
    "sg:postcode":"78756",
    "sg:province":"TX",
    "sg:tags":[
        "counseling",
        "mental"
    ],
    "wof:name":"Jack Morrison Lmsw Acp",
    "wof:placetype":"venue"
},
  "geometry": {"coordinates":[-97.74189800000001,30.314699],"type":"Point"}
}