{
  "type": "Feature",
  "properties": {
    "iso:country":"US",
    "sg:address":"800 Bering Dr Ste 227",
    "sg:city":"Houston",
    "sg:classifiers":[
        {
            "category":"Professional",
            "subcategory":"Lawyer & Legal Services",
            "type":"Services"
        }
    ],
    "sg:phone":"+1 713 780 9414",
    "sg:postcode":"77057",
    "sg:province":"TX",
    "wof:name":"Cantrell Don R Atty At Law",
    "wof:placetype":"venue"
},
  "geometry": {"coordinates":[-95.479698,29.7582],"type":"Point"}
}