{
  "type": "Feature",
  "properties": {
    "iso:country":"US",
    "sg:address":"2440 Texas Pkwy Ste 340",
    "sg:city":"Missouri City",
    "sg:classifiers":[
        {
            "category":"Sports & Exercise",
            "subcategory":"Gym",
            "type":"Entertainment"
        }
    ],
    "sg:phone":"+1 281 261 8111",
    "sg:postcode":"77489",
    "sg:province":"TX",
    "sg:tags":[
        "trainer"
    ],
    "wof:name":"Caring Health Services",
    "wof:placetype":"venue"
},
  "geometry": {"coordinates":[-95.526757,29.592533],"type":"Point"}
}