{
  "type": "Feature",
  "properties": {
    "iso:country":"US",
    "sg:address":"526 N Roosevelt St",
    "sg:city":"Pearsall",
    "sg:classifiers":[
        {
            "category":"Wholesale",
            "subcategory":"Groceries",
            "type":"Manufacturing & Wholesale Goods"
        }
    ],
    "sg:phone":"+1 830 334 4430",
    "sg:postcode":"78061",
    "sg:province":"TX",
    "sg:tags":[
        "honey"
    ],
    "wof:name":"Youngblood's Honey",
    "wof:placetype":"venue"
},
  "geometry": {"coordinates":[-99.08202799999999,28.894208],"type":"Point"}
}