{
  "type": "Feature",
  "properties": {
    "iso:country":"US",
    "sg:address":"1845 la Mancha St",
    "sg:city":"Brownsville",
    "sg:classifiers":[
        {
            "category":"Building & Trades",
            "subcategory":"Construction",
            "type":"Services"
        }
    ],
    "sg:phone":"+1 956 542 5549",
    "sg:postcode":"78521",
    "sg:province":"TX",
    "sg:tags":[
        "contractor",
        "paving",
        "asphalt",
        "sealcoating"
    ],
    "wof:name":"Arrow Construction",
    "wof:placetype":"venue"
},
  "geometry": {"coordinates":[-97.48861100000001,25.947209],"type":"Point"}
}