{
  "type": "Feature",
  "properties": {
    "iso:country":"US",
    "sg:address":"11527 Jones Rd",
    "sg:city":"Houston",
    "sg:classifiers":[
        {
            "category":"Autos & Motor Vehicles",
            "subcategory":"Automobile Sales",
            "type":"Retail Goods"
        }
    ],
    "sg:phone":"+1 281 477 0411",
    "sg:postcode":"77070",
    "sg:province":"TX",
    "sg:tags":[
        "car",
        "dealer"
    ],
    "wof:name":"Globe Auto Sales",
    "wof:placetype":"venue"
},
  "geometry": {"coordinates":[-95.584791,29.941446],"type":"Point"}
}