{
  "type": "Feature",
  "properties": {
    "iso:country":"US",
    "sg:address":"2591 E Pioneer Dr",
    "sg:city":"Irving",
    "sg:classifiers":[
        {
            "category":"Real Estate",
            "subcategory":"Real Estate Agent",
            "type":"Services"
        }
    ],
    "sg:phone":"+1 972 554 8555",
    "sg:postcode":"75061",
    "sg:province":"TX",
    "wof:name":"Loop 12 Distribution Ctr",
    "wof:placetype":"venue"
},
  "geometry": {"coordinates":[-96.91181400000001,32.818456],"type":"Point"}
}