{
  "type": "Feature",
  "properties": {
    "iso:country":"US",
    "sg:address":"118 Broadway St",
    "sg:city":"Austin",
    "sg:classifiers":[
        {
            "category":"Social Services",
            "type":"Services"
        }
    ],
    "sg:phone":"+1 512 477 2229",
    "sg:postcode":"78702",
    "sg:province":"TX",
    "sg:tags":[
        "agency",
        "adoption"
    ],
    "wof:name":"Adoption Angels Inc",
    "wof:placetype":"venue"
},
  "geometry": {"coordinates":[-97.71153099999999,30.253424],"type":"Point"}
}