{
  "type": "Feature",
  "properties": {
    "iso:country":"US",
    "sg:address":"3215 Steck Ave",
    "sg:city":"Austin",
    "sg:classifiers":[
        {
            "category":"Real Estate",
            "subcategory":"Developer",
            "type":"Services"
        }
    ],
    "sg:phone":"+1 512 467 8030",
    "sg:postcode":"78757",
    "sg:province":"TX",
    "wof:name":"Spanos The Corp",
    "wof:placetype":"venue"
},
  "geometry": {"coordinates":[-97.73645999999999,30.365263],"type":"Point"}
}