{
  "type": "Feature",
  "properties": {
    "iso:country":"US",
    "sg:address":"13505 Oregon Flat Trl",
    "sg:city":"Austin",
    "sg:classifiers":[
        {
            "category":"Professional",
            "subcategory":"Business Services",
            "type":"Services"
        }
    ],
    "sg:phone":"+1 512 670 0189",
    "sg:postcode":"78727",
    "sg:province":"TX",
    "wof:name":"Country Road U S",
    "wof:placetype":"venue"
},
  "geometry": {"coordinates":[-97.682061,30.426687],"type":"Point"}
}