{
  "type": "Feature",
  "properties": {
    "iso:country":"US",
    "sg:address":"7212 W Highway 71",
    "sg:city":"Austin",
    "sg:classifiers":[
        {
            "category":"Personal",
            "type":"Services"
        }
    ],
    "sg:phone":"+1 512 288 0909",
    "sg:postcode":"78735",
    "sg:province":"TX",
    "sg:tags":[
        "mover"
    ],
    "wof:name":"Oak Hill Center Storage",
    "wof:placetype":"venue"
},
  "geometry": {"coordinates":[-97.846478,30.246507],"type":"Point"}
}