{
  "type": "Feature",
  "properties": {
    "iso:country":"US",
    "sg:address":"3303 Central Expy",
    "sg:city":"Plano",
    "sg:classifiers":[
        {
            "category":"Shopping",
            "type":"Retail Goods"
        }
    ],
    "sg:phone":"+1 972 423 3300",
    "sg:postcode":"75023",
    "sg:province":"TX",
    "sg:tags":[
        "paper",
        "merchandise"
    ],
    "wof:name":"Boxes To Go",
    "wof:placetype":"venue"
},
  "geometry": {"coordinates":[-96.70394899999999,33.039318],"type":"Point"}
}