{
  "type": "Feature",
  "properties": {
    "iso:country":"US",
    "sg:address":"12475 State Hwy 123",
    "sg:city":"Seguin",
    "sg:classifiers":[
        {
            "category":"Retail",
            "subcategory":"Auto Repair",
            "type":"Services"
        }
    ],
    "sg:phone":"+1 830 379 6980",
    "sg:postcode":"78155",
    "sg:province":"TX",
    "sg:tags":[
        "general"
    ],
    "wof:name":"H & H Auto Service",
    "wof:placetype":"venue"
},
  "geometry": {"coordinates":[-97.947107,29.767604],"type":"Point"}
}