{
  "type": "Feature",
  "properties": {
    "iso:country":"US",
    "sg:address":"6710 Chelsea Wood",
    "sg:city":"San Antonio",
    "sg:classifiers":[
        {
            "category":"Professional",
            "type":"Services"
        }
    ],
    "sg:phone":"+1 210 654 8155",
    "sg:postcode":"78239",
    "sg:province":"TX",
    "wof:name":"Dora T Penalver",
    "wof:placetype":"venue"
},
  "geometry": {"coordinates":[-98.351161,29.526049],"type":"Point"}
}