{
  "type": "Feature",
  "properties": {
    "iso:country":"US",
    "sg:address":"858 Cactus Ridge Rd",
    "sg:city":"Fredericksburg",
    "sg:classifiers":[
        {
            "category":"Retail",
            "subcategory":"Storage",
            "type":"Services"
        }
    ],
    "sg:phone":"+1 830 990 1140",
    "sg:postcode":"78624",
    "sg:province":"TX",
    "sg:tags":[
        "self",
        "commercial",
        "household"
    ],
    "wof:name":"A B C Self Storage",
    "wof:placetype":"venue"
},
  "geometry": {"coordinates":[-99.027475,30.278002],"type":"Point"}
}