{
  "type": "Feature",
  "properties": {
    "iso:country":"US",
    "sg:address":"1237 Canyon Shores",
    "sg:city":"New Braunfels",
    "sg:classifiers":[
        {
            "category":"Organizations",
            "subcategory":"Community Association",
            "type":"Services"
        }
    ],
    "sg:phone":"+1 830 935 4745",
    "sg:postcode":"78133",
    "sg:province":"TX",
    "wof:name":"Canyon Lk Shres Prperty Owners",
    "wof:placetype":"venue"
},
  "geometry": {"coordinates":[-98.28806400000001,29.926177],"type":"Point"}
}