{
  "type": "Feature",
  "properties": {
    "iso:country":"US",
    "sg:address":"425 Lovera Blvd",
    "sg:city":"San Antonio",
    "sg:classifiers":[
        {
            "category":"Retail",
            "subcategory":"Repair Shop",
            "type":"Services"
        }
    ],
    "sg:phone":"+1 210 736 3332",
    "sg:postcode":"78212",
    "sg:province":"TX",
    "sg:tags":[
        "electrical"
    ],
    "wof:name":"Mr Fix It Appliance Repair",
    "wof:placetype":"venue"
},
  "geometry": {"coordinates":[-98.502365,29.484302],"type":"Point"}
}