{
  "type": "Feature",
  "properties": {
    "iso:country":"US",
    "sg:address":"5504 71st St",
    "sg:city":"Lubbock",
    "sg:classifiers":[
        {
            "category":"Professional",
            "subcategory":"Research",
            "type":"Services"
        }
    ],
    "sg:phone":"+1 806 783 8770",
    "sg:postcode":"79424",
    "sg:province":"TX",
    "wof:name":"Microchem Soulutions",
    "wof:placetype":"venue"
},
  "geometry": {"coordinates":[-101.93533499999999,33.529155],"type":"Point"}
}