{
  "type": "Feature",
  "properties": {
    "iso:country":"US",
    "sg:address":"301 State Hwy 243",
    "sg:city":"Canton",
    "sg:classifiers":[
        {
            "category":"Banks & Credit Unions",
            "subcategory":"Bank",
            "type":"Services"
        }
    ],
    "sg:phone":"+1 903 567 3302",
    "sg:postcode":"75103",
    "sg:province":"TX",
    "sg:tags":[
        "personal",
        "institution"
    ],
    "wof:name":"Advance America",
    "wof:placetype":"venue"
},
  "geometry": {"coordinates":[-95.85737899999999,32.545301],"type":"Point"}
}