{
  "type": "Feature",
  "properties": {
    "iso:country":"US",
    "sg:address":"16610 Colony Terrace Dr",
    "sg:city":"Sugar Land",
    "sg:classifiers":[
        {
            "category":"Professional",
            "subcategory":"Accounting & Tax Preparation",
            "type":"Services"
        }
    ],
    "sg:phone":"+1 281 265 6954",
    "sg:postcode":"77479",
    "sg:province":"TX",
    "wof:name":"H Parikh CPA",
    "wof:placetype":"venue"
},
  "geometry": {"coordinates":[-95.622184,29.58504],"type":"Point"}
}