{
  "type": "Feature",
  "properties": {
    "iso:country":"US",
    "sg:address":"225 Quail Trail Ln",
    "sg:city":"Arlington",
    "sg:classifiers":[
        {
            "category":"Shopping",
            "subcategory":"Clothing, Apparel, & Fashions",
            "type":"Retail Goods"
        }
    ],
    "sg:phone":"+1 214 415 0507",
    "sg:postcode":"76002",
    "sg:province":"TX",
    "sg:tags":[
        "shoes"
    ],
    "wof:name":"Mr T Fashion",
    "wof:placetype":"venue"
},
  "geometry": {"coordinates":[-97.111558,32.627976],"type":"Point"}
}