{
  "type": "Feature",
  "properties": {
    "iso:country":"US",
    "sg:address":"7111 Westbrair Dr",
    "sg:city":"San Antonio",
    "sg:classifiers":[
        {
            "category":"Building & Trades",
            "subcategory":"Construction",
            "type":"Services"
        }
    ],
    "sg:phone":"+1 210 645 1081",
    "sg:postcode":"78227",
    "sg:province":"TX",
    "sg:tags":[
        "contractor"
    ],
    "wof:name":"A A Stucco",
    "wof:placetype":"venue"
},
  "geometry": {"coordinates":[-98.631793,29.409904],"type":"Point"}
}