{
  "type": "Feature",
  "properties": {
    "iso:country":"US",
    "sg:address":"4115 Druid Hills Dr",
    "sg:city":"Dallas",
    "sg:classifiers":[
        {
            "category":"Real Estate",
            "subcategory":"Real Estate Agent",
            "type":"Services"
        }
    ],
    "sg:phone":"+1 214 339 1700",
    "sg:postcode":"75224",
    "sg:province":"TX",
    "wof:name":"Phillips Commercial",
    "wof:placetype":"venue"
},
  "geometry": {"coordinates":[-96.85373199999999,32.691811],"type":"Point"}
}