{
  "type": "Feature",
  "properties": {
    "iso:country":"US",
    "sg:address":"9620 Lynbrook Dr",
    "sg:city":"Dallas",
    "sg:classifiers":[
        {
            "category":"Education",
            "subcategory":"School",
            "type":"Public Place"
        }
    ],
    "sg:phone":"+1 214 503 9020",
    "sg:postcode":"75238",
    "sg:province":"TX",
    "wof:name":"Anne Porter Kelly",
    "wof:placetype":"venue"
},
  "geometry": {"coordinates":[-96.70375799999999,32.877621],"type":"Point"}
}