{
  "type": "Feature",
  "properties": {
    "iso:country":"US",
    "sg:address":"900 Arizona Ave",
    "sg:city":"El Paso",
    "sg:classifiers":[
        {
            "category":"Organizations",
            "subcategory":"Community Association",
            "type":"Services"
        }
    ],
    "sg:phone":"+1 915 313 9466",
    "sg:postcode":"79902",
    "sg:province":"TX",
    "wof:name":"Christian Women's Job Corp",
    "wof:placetype":"venue"
},
  "geometry": {"coordinates":[-106.486125,31.769728],"type":"Point"}
}