{
  "type": "Feature",
  "properties": {
    "iso:country":"US",
    "sg:address":"619 W Palestine Ave",
    "sg:city":"Elkhart",
    "sg:classifiers":[
        {
            "category":"Restaurant",
            "type":"Food & Drink"
        }
    ],
    "sg:phone":"+1 903 764 2031",
    "sg:postcode":"75801",
    "sg:province":"TX",
    "sg:tags":[
        "eating"
    ],
    "wof:name":"Lts Diner",
    "wof:placetype":"venue"
},
  "geometry": {"coordinates":[-95.63900599999999,31.7699],"type":"Point"}
}