{
  "type": "Feature",
  "properties": {
    "iso:country":"US",
    "sg:address":"603 N 9th St",
    "sg:city":"Midlothian",
    "sg:classifiers":[
        {
            "category":"Organizations",
            "subcategory":"Religious Organization",
            "type":"Services"
        }
    ],
    "sg:phone":"+1 972 723 2154",
    "sg:postcode":"76065",
    "sg:province":"TX",
    "wof:name":"Mount Pleasant Baptist",
    "wof:placetype":"venue"
},
  "geometry": {"coordinates":[-96.993544,32.488422],"type":"Point"}
}