{
  "type": "Feature",
  "properties": {
    "iso:country":"US",
    "sg:address":"101 S Main St",
    "sg:city":"Balmorhea",
    "sg:classifiers":[
        {
            "category":"Education",
            "subcategory":"Library",
            "type":"Public Place"
        }
    ],
    "sg:phone":"+1 432 375 2522",
    "sg:postcode":"79701",
    "sg:province":"TX",
    "wof:name":"Balmorhea Public Library",
    "wof:placetype":"venue"
},
  "geometry": {"coordinates":[-102.07434000000001,31.996468],"type":"Point"}
}