{
  "type": "Feature",
  "properties": {
    "iso:country":"US",
    "sg:address":"2013 Fountainview Dr",
    "sg:city":"Euless",
    "sg:classifiers":[
        {
            "category":"Real Estate",
            "subcategory":"Real Estate Agent",
            "type":"Services"
        }
    ],
    "sg:phone":"+1 817 545 6982",
    "sg:postcode":"76039",
    "sg:province":"TX",
    "wof:name":"G&J Executives",
    "wof:placetype":"venue"
},
  "geometry": {"coordinates":[-97.080901,32.864642],"type":"Point"}
}