{
  "type": "Feature",
  "properties": {
    "iso:country":"US",
    "sg:address":"1306 Crestwood Ct",
    "sg:city":"Allen",
    "sg:classifiers":[
        {
            "category":"Education",
            "subcategory":"Special Training",
            "type":"Public Place"
        }
    ],
    "sg:phone":"+1 972 359 1118",
    "sg:postcode":"75002",
    "sg:province":"TX",
    "sg:tags":[
        "program"
    ],
    "wof:name":"Challenge NEB Interest Inc",
    "wof:placetype":"venue"
},
  "geometry": {"coordinates":[-96.639065,33.103136],"type":"Point"}
}