{
  "type": "Feature",
  "properties": {
    "iso:country":"US",
    "sg:address":"1511 Early Blvd",
    "sg:city":"Early",
    "sg:classifiers":[
        {
            "category":"Travel",
            "subcategory":"Campground",
            "type":"Entertainment"
        }
    ],
    "sg:phone":"+1 325 643 5965",
    "sg:postcode":"76802",
    "sg:province":"TX",
    "sg:tags":[
        "mobile",
        "home",
        "park"
    ],
    "wof:name":"Travelers N Park & Campground",
    "wof:placetype":"venue"
},
  "geometry": {"coordinates":[-98.922432,31.751221],"type":"Point"}
}