{
  "type": "Feature",
  "properties": {
    "iso:country":"US",
    "sg:address":"4914 Crestwood Dr",
    "sg:city":"Cibolo",
    "sg:classifiers":[
        {
            "category":"Shopping",
            "subcategory":"Gifts & Souvenirs",
            "type":"Retail Goods"
        }
    ],
    "sg:phone":"+1 830 627 2811",
    "sg:postcode":"78108",
    "sg:province":"TX",
    "sg:tags":[
        "basket",
        "parcel"
    ],
    "wof:name":"From The Heart Of Texas",
    "wof:placetype":"venue"
},
  "geometry": {"coordinates":[-98.22738099999999,29.619955],"type":"Point"}
}