{
  "type": "Feature",
  "properties": {
    "iso:country":"US",
    "sg:address":"9614 Enstone Cir",
    "sg:city":"Spring",
    "sg:classifiers":[
        {
            "category":"Professional",
            "subcategory":"Management & Consulting",
            "type":"Services"
        }
    ],
    "sg:phone":"+1 330 283 4563",
    "sg:postcode":"77379",
    "sg:province":"TX",
    "sg:tags":[
        "quality",
        "productivity"
    ],
    "wof:name":"Eagle Force Inc",
    "wof:placetype":"venue"
},
  "geometry": {"coordinates":[-95.54986100000001,29.999195],"type":"Point"}
}