{
  "type": "Feature",
  "properties": {
    "iso:country":"US",
    "sg:address":"1717 W 22nd St",
    "sg:city":"Houston",
    "sg:classifiers":[
        {
            "category":"Building & Trades",
            "subcategory":"Construction",
            "type":"Services"
        }
    ],
    "sg:phone":"+1 713 802 1700",
    "sg:postcode":"77008",
    "sg:province":"TX",
    "sg:tags":[
        "house"
    ],
    "wof:name":"Caspian Enterprises",
    "wof:placetype":"venue"
},
  "geometry": {"coordinates":[-95.43129999999999,29.805698],"type":"Point"}
}