{
  "type": "Feature",
  "properties": {
    "iso:country":"US",
    "sg:address":"2005 W Gray St Ste C",
    "sg:city":"Houston",
    "sg:classifiers":[
        {
            "category":"Bakery",
            "type":"Food & Drink"
        }
    ],
    "sg:phone":"+1 713 520 6174",
    "sg:postcode":"77019",
    "sg:province":"TX",
    "sg:website":"www.epicure-cafe.com",
    "wof:name":"Epicure Bakery",
    "wof:placetype":"venue"
},
  "geometry": {"coordinates":[-95.408948,29.752646],"type":"Point"}
}