{
  "type": "Feature",
  "properties": {
    "iso:country":"US",
    "sg:address":"131 Glenwood Dr",
    "sg:city":"Murphy",
    "sg:classifiers":[
        {
            "category":"Professional",
            "subcategory":"Detective & Security Services",
            "type":"Services"
        }
    ],
    "sg:phone":"+1 214 793 9734",
    "sg:postcode":"75094",
    "sg:province":"TX",
    "sg:tags":[
        "information",
        "bureau"
    ],
    "wof:name":"Dem Services",
    "wof:placetype":"venue"
},
  "geometry": {"coordinates":[-96.61242900000001,33.005739],"type":"Point"}
}