{
  "type": "Feature",
  "properties": {
    "iso:country":"US",
    "sg:address":"5001 Spring Valley Rd Ste 400E",
    "sg:city":"Dallas",
    "sg:classifiers":[
        {
            "category":"Banks & Credit Unions",
            "subcategory":"Bank",
            "type":"Services"
        }
    ],
    "sg:phone":"+1 972 383 1235",
    "sg:postcode":"75244",
    "sg:province":"TX",
    "sg:website":"www.stressfreemoney.biz/",
    "wof:name":"Stressfreemoney",
    "wof:placetype":"venue"
},
  "geometry": {"coordinates":[-96.82413,32.93964],"type":"Point"}
}