{
  "type": "Feature",
  "properties": {
    "iso:country":"US",
    "sg:address":"11500 Eastex Fwy",
    "sg:city":"Houston",
    "sg:classifiers":[
        {
            "category":"Wholesale",
            "subcategory":"Machinery & Supplies",
            "type":"Manufacturing & Wholesale Goods"
        }
    ],
    "sg:phone":"+1 281 449 9166",
    "sg:postcode":"77093",
    "sg:province":"TX",
    "sg:tags":[
        "equipment",
        "parts",
        "tractor"
    ],
    "wof:name":"A & M Machinery",
    "wof:placetype":"venue"
},
  "geometry": {"coordinates":[-95.32092900000001,29.886999],"type":"Point"}
}