{
  "type": "Feature",
  "properties": {
    "iso:country":"US",
    "sg:address":"2207 Allen St",
    "sg:city":"Dallas",
    "sg:classifiers":[
        {
            "category":"Restaurant",
            "type":"Food & Drink"
        }
    ],
    "sg:phone":"+1 214 720 0323",
    "sg:postcode":"75204",
    "sg:province":"TX",
    "sg:tags":[
        "french"
    ],
    "sg:website":"www.watels.com",
    "wof:name":"Watel's Restaurant",
    "wof:placetype":"venue"
},
  "geometry": {"coordinates":[-96.796402,32.795799],"type":"Point"}
}