{
  "type": "Feature",
  "properties": {
    "iso:country":"US",
    "sg:address":"304 Bennett Dr",
    "sg:city":"Dumas",
    "sg:phone":"+1 806 935 3718",
    "sg:postcode":"79029",
    "sg:province":"TX",
    "sg:tags":[
        "farm",
        "corn",
        "wheat"
    ],
    "wof:name":"Gearhart Farms",
    "wof:placetype":"venue"
},
  "geometry": {"coordinates":[-101.95650500000001,35.863022],"type":"Point"}
}