{
  "type": "Feature",
  "properties": {
    "iso:country":"US",
    "sg:address":"10834 Warwana Rd",
    "sg:city":"Houston",
    "sg:classifiers":[
        {
            "category":"Building & Trades",
            "subcategory":"Plumbing",
            "type":"Services"
        }
    ],
    "sg:phone":"+1 281 496 2455",
    "sg:postcode":"77043",
    "sg:province":"TX",
    "sg:tags":[
        "contractor"
    ],
    "wof:name":"Worlds Greatest Plumber",
    "wof:placetype":"venue"
},
  "geometry": {"coordinates":[-95.56712,29.80097],"type":"Point"}
}