{
  "type": "Feature",
  "properties": {
    "iso:country":"US",
    "sg:address":"1017 Long Prairie Rd",
    "sg:city":"Flower Mound",
    "sg:classifiers":[
        {
            "category":"Professional",
            "subcategory":"Management & Consulting",
            "type":"Services"
        }
    ],
    "sg:phone":"+1 972 899 2150",
    "sg:postcode":"75022",
    "sg:province":"TX",
    "sg:tags":[
        "construction"
    ],
    "wof:name":"Development Red Rock",
    "wof:placetype":"venue"
},
  "geometry": {"coordinates":[-97.068242,32.999393],"type":"Point"}
}