{
  "type": "Feature",
  "properties": {
    "iso:country":"US",
    "sg:address":"2601 Logan St",
    "sg:city":"Dallas",
    "sg:classifiers":[
        {
            "category":"Freight",
            "type":"Transportation"
        }
    ],
    "sg:phone":"+1 214 426 7982",
    "sg:postcode":"75215",
    "sg:province":"TX",
    "sg:tags":[
        "operator",
        "local",
        "trucking"
    ],
    "wof:name":"Oncor Energy Delivery",
    "wof:placetype":"venue"
},
  "geometry": {"coordinates":[-96.77592300000001,32.77225],"type":"Point"}
}