{
  "type": "Feature",
  "properties": {
    "iso:country":"US",
    "sg:address":"16302 Shadybank Dr",
    "sg:city":"Dallas",
    "sg:classifiers":[
        {
            "category":"Professional",
            "subcategory":"Management & Consulting",
            "type":"Services"
        }
    ],
    "sg:phone":"+1 972 931 9200",
    "sg:postcode":"75248",
    "sg:province":"TX",
    "sg:tags":[
        "business"
    ],
    "wof:name":"Dodson and Associates",
    "wof:placetype":"venue"
},
  "geometry": {"coordinates":[-96.79469899999999,32.969932],"type":"Point"}
}