{
  "type": "Feature",
  "properties": {
    "iso:country":"US",
    "sg:address":"617 N Tom Green Ave",
    "sg:city":"Odessa",
    "sg:classifiers":[
        {
            "category":"Health Services",
            "subcategory":"Doctor",
            "type":"Services"
        }
    ],
    "sg:phone":"+1 432 580 7277",
    "sg:postcode":"79761",
    "sg:province":"TX",
    "sg:tags":[
        "physician",
        "surgeon"
    ],
    "wof:name":"Westwood Medical Ctr",
    "wof:placetype":"venue"
},
  "geometry": {"coordinates":[-102.36654799999999,31.852177],"type":"Point"}
}