{
  "type": "Feature",
  "properties": {
    "iso:country":"US",
    "sg:address":"4621 Highgrove Dr",
    "sg:city":"Fort Worth",
    "sg:classifiers":[
        {
            "category":"Professional",
            "type":"Services"
        }
    ],
    "sg:phone":"+1 817 294 2316",
    "sg:postcode":"76132",
    "sg:province":"TX",
    "sg:tags":[
        "arts",
        "artist"
    ],
    "wof:name":"Lone Wolf Art",
    "wof:placetype":"venue"
},
  "geometry": {"coordinates":[-97.395116,32.671048],"type":"Point"}
}