{
  "type": "Feature",
  "properties": {
    "iso:country":"US",
    "sg:address":"4320 Noyes Rd",
    "sg:city":"Von Ormy",
    "sg:classifiers":[
        {
            "category":"Building & Trades",
            "subcategory":"Electrical",
            "type":"Services"
        }
    ],
    "sg:phone":"+1 210 624 2474",
    "sg:postcode":"78073",
    "sg:province":"TX",
    "sg:tags":[
        "electric",
        "contractor"
    ],
    "wof:name":"Estess Electric & Machine Co",
    "wof:placetype":"venue"
},
  "geometry": {"coordinates":[-98.585837,29.249076],"type":"Point"}
}