{
  "type": "Feature",
  "properties": {
    "iso:country":"US",
    "sg:address":"9330 Lyndon B Johnson Fwy",
    "sg:city":"Dallas",
    "sg:classifiers":[
        {
            "category":"Professional",
            "subcategory":"Lawyer & Legal Services",
            "type":"Services"
        }
    ],
    "sg:phone":"+1 214 523 9660",
    "sg:postcode":"75243",
    "sg:province":"TX",
    "sg:tags":[
        "attorney"
    ],
    "wof:name":"Barry L Reno Attorney",
    "wof:placetype":"venue"
},
  "geometry": {"coordinates":[-96.73576,32.910847],"type":"Point"}
}