{
  "type": "Feature",
  "properties": {
    "iso:country":"US",
    "sg:address":"1414 S Loop W Ste 200",
    "sg:city":"Houston",
    "sg:classifiers":[
        {
            "category":"Health Services",
            "subcategory":"Doctor",
            "type":"Services"
        }
    ],
    "sg:phone":"+1 713 797 6106",
    "sg:postcode":"77054",
    "sg:province":"TX",
    "wof:name":"US Healthworks",
    "wof:placetype":"venue"
},
  "geometry": {"coordinates":[-95.397744,29.68047],"type":"Point"}
}