{
  "type": "Feature",
  "properties": {
    "iso:country":"US",
    "sg:address":"1810 Coulter St",
    "sg:city":"Amarillo",
    "sg:classifiers":[
        {
            "category":"Health Services",
            "subcategory":"Doctor",
            "type":"Services"
        }
    ],
    "sg:phone":"+1 806 358 8731",
    "sg:postcode":"79106",
    "sg:province":"TX",
    "sg:tags":[
        "medical"
    ],
    "wof:name":"Mary Ann Piskun MD",
    "wof:placetype":"venue"
},
  "geometry": {"coordinates":[-101.921329,35.193696],"type":"Point"}
}