{
  "type": "Feature",
  "properties": {
    "iso:country":"US",
    "sg:address":"7529 Orange Valley Dr",
    "sg:city":"N Richland Hills",
    "sg:classifiers":[
        {
            "category":"Shopping",
            "subcategory":"Computers & Home Electronics",
            "type":"Retail Goods"
        }
    ],
    "sg:phone":"+1 817 485 7178",
    "sg:postcode":"76180",
    "sg:province":"TX",
    "sg:tags":[
        "equipment",
        "electronic",
        "supply"
    ],
    "wof:name":"PBH Home Theater",
    "wof:placetype":"venue"
},
  "geometry": {"coordinates":[-97.22381799999999,32.883782],"type":"Point"}
}