{
  "type": "Feature",
  "properties": {
    "iso:country":"US",
    "sg:address":"9026 Klondike St",
    "sg:city":"Houston",
    "sg:classifiers":[
        {
            "category":"Bus Charters",
            "type":"Transportation"
        }
    ],
    "sg:phone":"+1 713 943 3201",
    "sg:postcode":"77075",
    "sg:province":"TX",
    "wof:name":"Martinez School Bus Service",
    "wof:placetype":"venue"
},
  "geometry": {"coordinates":[-95.253135,29.635826],"type":"Point"}
}