{
  "type": "Feature",
  "properties": {
    "iso:country":"US",
    "sg:address":"11300 Wilcrest Green Dr",
    "sg:city":"Houston",
    "sg:classifiers":[
        {
            "category":"Organizations",
            "subcategory":"Religious Organization",
            "type":"Services"
        }
    ],
    "sg:phone":"+1 713 954 9422",
    "sg:postcode":"77042",
    "sg:province":"TX",
    "sg:tags":[
        "church"
    ],
    "sg:website":"www.westhoustonchristian.com",
    "wof:name":"Jack Pidgeon Ministries",
    "wof:placetype":"venue"
},
  "geometry": {"coordinates":[-95.569912,29.724481],"type":"Point"}
}