{
  "type": "Feature",
  "properties": {
    "iso:country":"US",
    "sg:address":"805 Clear View Ct",
    "sg:city":"Burleson",
    "sg:classifiers":[
        {
            "category":"Retail",
            "subcategory":"Auto Repair",
            "type":"Services"
        }
    ],
    "sg:phone":"+1 817 447 1948",
    "sg:postcode":"76028",
    "sg:province":"TX",
    "sg:tags":[
        "body"
    ],
    "wof:name":"Mark Parks",
    "wof:placetype":"venue"
},
  "geometry": {"coordinates":[-97.29568,32.528848],"type":"Point"}
}