{
  "type": "Feature",
  "properties": {
    "iso:country":"US",
    "sg:address":"4519 San Bernardo Ave",
    "sg:city":"Laredo",
    "sg:classifiers":[
        {
            "category":"Insurance",
            "subcategory":"Insurance Agent",
            "type":"Services"
        }
    ],
    "sg:phone":"+1 956 724 9083",
    "sg:postcode":"78041",
    "sg:province":"TX",
    "wof:name":"New York Life",
    "wof:placetype":"venue"
},
  "geometry": {"coordinates":[-99.504248,27.540328],"type":"Point"}
}