{
  "type": "Feature",
  "properties": {
    "iso:country":"US",
    "sg:address":"201 E Scott Ave",
    "sg:city":"Wichita Falls",
    "sg:classifiers":[
        {
            "category":"Retail",
            "subcategory":"Auto Repair",
            "type":"Services"
        }
    ],
    "sg:phone":"+1 940 766 2831",
    "sg:postcode":"76301",
    "sg:province":"TX",
    "sg:tags":[
        "body"
    ],
    "wof:name":"Stewarts Automotive",
    "wof:placetype":"venue"
},
  "geometry": {"coordinates":[-98.484526,33.903079],"type":"Point"}
}