{
  "type": "Feature",
  "properties": {
    "iso:country":"US",
    "sg:address":"4235 S Alameda St",
    "sg:city":"Corpus Christi",
    "sg:classifiers":[
        {
            "category":"Shopping",
            "subcategory":"Florist",
            "type":"Retail Goods"
        }
    ],
    "sg:phone":"+1 361 853 3416",
    "sg:postcode":"78412",
    "sg:province":"TX",
    "wof:name":"Marsdens Flowers",
    "wof:placetype":"venue"
},
  "geometry": {"coordinates":[-97.372641,27.730859],"type":"Point"}
}