{
  "type": "Feature",
  "properties": {
    "iso:country":"US",
    "sg:address":"1308 Common St",
    "sg:city":"New Braunfels",
    "sg:classifiers":[
        {
            "category":"Shopping",
            "subcategory":"Optical Goods",
            "type":"Retail Goods"
        }
    ],
    "sg:phone":"+1 830 624 9099",
    "sg:postcode":"78130",
    "sg:province":"TX",
    "sg:tags":[
        "optician"
    ],
    "wof:name":"Spare Pair",
    "wof:placetype":"venue"
},
  "geometry": {"coordinates":[-98.100793,29.722151],"type":"Point"}
}