{
  "type": "Feature",
  "properties": {
    "iso:country":"US",
    "sg:address":"516 N Conway Ave",
    "sg:city":"Mission",
    "sg:classifiers":[
        {
            "category":"Recreation",
            "subcategory":"Arcade",
            "type":"Entertainment"
        }
    ],
    "sg:phone":"+1 956 585 6032",
    "sg:postcode":"78572",
    "sg:province":"TX",
    "sg:tags":[
        "device",
        "operator",
        "machine",
        "vending",
        "amusement"
    ],
    "wof:name":"J and J Music",
    "wof:placetype":"venue"
},
  "geometry": {"coordinates":[-98.326334,26.211337],"type":"Point"}
}