{
  "type": "Feature",
  "properties": {
    "iso:country":"US",
    "sg:address":"2900 North Fwy",
    "sg:city":"Houston",
    "sg:classifiers":[
        {
            "category":"Autos & Motor Vehicles",
            "subcategory":"Automobile Sales",
            "type":"Retail Goods"
        }
    ],
    "sg:phone":"+1 713 697 5494",
    "sg:postcode":"77009",
    "sg:province":"TX",
    "sg:tags":[
        "limo"
    ],
    "wof:name":"Pristine Limousine",
    "wof:placetype":"venue"
},
  "geometry": {"coordinates":[-95.371385,29.801497],"type":"Point"}
}