{
  "type": "Feature",
  "properties": {
    "iso:country":"US",
    "sg:address":"9616 N Lamar Blvd Ste 183",
    "sg:city":"Austin",
    "sg:classifiers":[
        {
            "category":"Shopping",
            "subcategory":"Mobile Phones",
            "type":"Retail Goods"
        }
    ],
    "sg:phone":"+1 512 814 3099",
    "sg:postcode":"78753",
    "sg:province":"TX",
    "wof:name":"ZZ Wireless Cellular and More",
    "wof:placetype":"venue"
},
  "geometry": {"coordinates":[-97.695577,30.3659],"type":"Point"}
}