{
  "type": "Feature",
  "properties": {
    "iso:country":"US",
    "sg:address":"6710 Loyola Ln",
    "sg:city":"Austin",
    "sg:classifiers":[
        {
            "category":"Building & Trades",
            "subcategory":"Electrical",
            "type":"Services"
        }
    ],
    "sg:phone":"+1 512 926 7036",
    "sg:postcode":"78724",
    "sg:province":"TX",
    "sg:tags":[
        "booth",
        "equipment",
        "telephone",
        "pay"
    ],
    "wof:name":"Us Telecoin Corp",
    "wof:placetype":"venue"
},
  "geometry": {"coordinates":[-97.64604300000001,30.299333],"type":"Point"}
}