{
  "type": "Feature",
  "properties": {
    "iso:country":"US",
    "sg:address":"2321 114th St",
    "sg:city":"Lubbock",
    "sg:classifiers":[
        {
            "category":"Building & Trades",
            "subcategory":"Construction",
            "type":"Services"
        }
    ],
    "sg:phone":"+1 806 748 8330",
    "sg:postcode":"79423",
    "sg:province":"TX",
    "sg:tags":[
        "contractor"
    ],
    "wof:name":"Charles Terry Construction",
    "wof:placetype":"venue"
},
  "geometry": {"coordinates":[-101.867722,33.490716],"type":"Point"}
}