{
  "type": "Feature",
  "properties": {
    "iso:country":"US",
    "sg:address":"355 State Hwy 75",
    "sg:city":"Willis",
    "sg:classifiers":[
        {
            "category":"Organizations",
            "subcategory":"Community Association",
            "type":"Services"
        }
    ],
    "sg:phone":"+1 936 344 2167",
    "sg:postcode":"77378",
    "sg:province":"TX",
    "sg:tags":[
        "fraternal"
    ],
    "wof:name":"Knights Of Columbus",
    "wof:placetype":"venue"
},
  "geometry": {"coordinates":[-95.480582,30.426306],"type":"Point"}
}