{
  "type": "Feature",
  "properties": {
    "iso:country":"US",
    "sg:address":"1624 N Lee Trevino Dr",
    "sg:city":"El Paso",
    "sg:classifiers":[
        {
            "category":"Health Services",
            "subcategory":"Health Practitioner",
            "type":"Services"
        },
        {
            "category":"Professional",
            "subcategory":"Employment Agencies",
            "type":"Services"
        }
    ],
    "sg:phone":"+1 915 629 8000",
    "sg:postcode":"79936",
    "sg:province":"TX",
    "sg:tags":[
        "nurse",
        "registry",
        "staffing"
    ],
    "sg:website":"www.southwestnursestaffing.com",
    "wof:name":"Southwest Nurse Staffing",
    "wof:placetype":"venue"
},
  "geometry": {"coordinates":[-106.318738,31.7584],"type":"Point"}
}