{
  "type": "Feature",
  "properties": {
    "iso:country":"US",
    "sg:address":"3620 S I- 35 E",
    "sg:city":"Denton",
    "sg:classifiers":[
        {
            "category":"Restaurant",
            "type":"Food & Drink"
        }
    ],
    "sg:phone":"+1 940 891 0443",
    "sg:postcode":"76210",
    "sg:province":"TX",
    "sg:tags":[
        "eating"
    ],
    "wof:name":"Briar Inn Cafe",
    "wof:placetype":"venue"
},
  "geometry": {"coordinates":[-97.091413,33.173861],"type":"Point"}
}