{
  "type": "Feature",
  "properties": {
    "iso:country":"US",
    "sg:address":"5034 Ocotillo St",
    "sg:city":"El Paso",
    "sg:classifiers":[
        {
            "category":"Professional",
            "subcategory":"Lawyer & Legal Services",
            "type":"Services"
        }
    ],
    "sg:phone":"+1 915 584 1258",
    "sg:postcode":"79932",
    "sg:province":"TX",
    "sg:tags":[
        "attorney"
    ],
    "wof:name":"Leo B Garcia",
    "wof:placetype":"venue"
},
  "geometry": {"coordinates":[-106.582154,31.842723],"type":"Point"}
}