{
  "type": "Feature",
  "properties": {
    "iso:country":"US",
    "sg:address":"1606 S Texas Ave",
    "sg:city":"Bryan",
    "sg:classifiers":[
        {
            "category":"Autos & Motor Vehicles",
            "subcategory":"Auto Supplies",
            "type":"Retail Goods"
        },
        {
            "category":"Retail",
            "subcategory":"Car Wash",
            "type":"Services"
        },
        {
            "category":"Retail",
            "subcategory":"Auto Repair",
            "type":"Services"
        }
    ],
    "sg:phone":"+1 979 361 3368",
    "sg:postcode":"77802",
    "sg:province":"TX",
    "sg:tags":[
        "body",
        "automobile",
        "truck",
        "painting",
        "repairing"
    ],
    "wof:name":"Dent Magic",
    "wof:placetype":"venue"
},
  "geometry": {"coordinates":[-96.365937,30.655224],"type":"Point"}
}