{
  "type": "Feature",
  "properties": {
    "iso:country":"US",
    "sg:address":"2607 Capistrano Ct N",
    "sg:city":"Arlington",
    "sg:classifiers":[
        {
            "category":"Manufacturing",
            "subcategory":"Apparel",
            "type":"Manufacturing & Wholesale Goods"
        }
    ],
    "sg:phone":"+1 817 265 0084",
    "sg:postcode":"76015",
    "sg:province":"TX",
    "sg:tags":[
        "sewing",
        "contractor"
    ],
    "wof:name":"C A Opare Custom Sewing",
    "wof:placetype":"venue"
},
  "geometry": {"coordinates":[-97.14782200000001,32.701301],"type":"Point"}
}