{
  "type": "Feature",
  "properties": {
    "iso:country":"US",
    "sg:address":"1014 N Main St",
    "sg:city":"Weatherford",
    "sg:classifiers":[
        {
            "category":"Food & Beverages",
            "subcategory":"Groceries & Convenience Stores",
            "type":"Retail Goods"
        }
    ],
    "sg:phone":"+1 817 594 0523",
    "sg:postcode":"76086",
    "sg:province":"TX",
    "wof:name":"Big Pantry Food & Travel Store",
    "wof:placetype":"venue"
},
  "geometry": {"coordinates":[-97.79713700000001,32.770906],"type":"Point"}
}