{
  "type": "Feature",
  "properties": {
    "iso:country":"US",
    "sg:address":"7848 Jarvis Way",
    "sg:city":"Fort Worth",
    "sg:classifiers":[
        {
            "category":"Shopping",
            "type":"Retail Goods"
        }
    ],
    "sg:phone":"+1 817 238 1229",
    "sg:postcode":"76135",
    "sg:province":"TX",
    "sg:tags":[
        "feed",
        "store"
    ],
    "wof:name":"Turkey Mountain General Store",
    "wof:placetype":"venue"
},
  "geometry": {"coordinates":[-97.45905999999999,32.817842],"type":"Point"}
}