{
  "type": "Feature",
  "properties": {
    "iso:country":"US",
    "sg:address":"16009 Congo Ln",
    "sg:city":"Houston",
    "sg:classifiers":[
        {
            "category":"Professional",
            "subcategory":"Management & Consulting",
            "type":"Services"
        }
    ],
    "sg:phone":"+1 713 937 6186",
    "sg:postcode":"77040",
    "sg:province":"TX",
    "sg:tags":[
        "consultant",
        "business"
    ],
    "sg:website":"www.awardsites.com",
    "wof:name":"Focus Associates",
    "wof:placetype":"venue"
},
  "geometry": {"coordinates":[-95.562026,29.883371],"type":"Point"}
}