{
  "type": "Feature",
  "properties": {
    "iso:country":"US",
    "sg:address":"1322 N Texas Ave",
    "sg:city":"Bryan",
    "sg:classifiers":[
        {
            "category":"Professional",
            "subcategory":"Business Services",
            "type":"Services"
        }
    ],
    "sg:phone":"+1 979 779 3162",
    "sg:postcode":"77803",
    "sg:province":"TX",
    "wof:name":"Dodlex Dollars Express Inc",
    "wof:placetype":"venue"
},
  "geometry": {"coordinates":[-96.371296,30.687769],"type":"Point"}
}