{
  "type": "Feature",
  "properties": {
    "iso:country":"US",
    "sg:address":"1939 Strickland Dr",
    "sg:city":"Orange",
    "sg:classifiers":[
        {
            "category":"Banks & Credit Unions",
            "subcategory":"Bank",
            "type":"Services"
        },
        {
            "category":"Banks & Credit Unions",
            "subcategory":"Financial Services",
            "type":"Services"
        }
    ],
    "sg:phone":"+1 409 988 1300",
    "sg:postcode":"77630",
    "sg:province":"TX",
    "sg:tags":[
        "loan"
    ],
    "sg:website":"http://www.sabinefcu.org",
    "wof:name":"Sabine Federal Credit Union",
    "wof:placetype":"venue"
},
  "geometry": {"coordinates":[-93.77625399999999,30.108442],"type":"Point"}
}