{
  "type": "Feature",
  "properties": {
    "iso:country":"US",
    "sg:address":"2011 Ploverville Ln",
    "sg:city":"Austin",
    "sg:classifiers":[
        {
            "category":"Professional",
            "type":"Services"
        }
    ],
    "sg:phone":"+1 512 619 6769",
    "sg:postcode":"78728",
    "sg:province":"TX",
    "sg:tags":[
        "field",
        "reader"
    ],
    "wof:name":"Lorna Mae Hermosura",
    "wof:placetype":"venue"
},
  "geometry": {"coordinates":[-97.67644199999999,30.443527],"type":"Point"}
}