{
  "type": "Feature",
  "properties": {
    "iso:country":"US",
    "sg:address":"11722 Whisper Dew St",
    "sg:city":"San Antonio",
    "sg:classifiers":[
        {
            "category":"Professional",
            "subcategory":"Engineering",
            "type":"Services"
        },
        {
            "category":"Professional",
            "subcategory":"Management & Consulting",
            "type":"Services"
        }
    ],
    "sg:phone":"+1 210 492 6931",
    "sg:postcode":"78230",
    "sg:province":"TX",
    "sg:tags":[
        "consultant",
        "business"
    ],
    "wof:name":"Knapp Associates",
    "wof:placetype":"venue"
},
  "geometry": {"coordinates":[-98.543356,29.548436],"type":"Point"}
}