{
  "type": "Feature",
  "properties": {
    "iso:country":"US",
    "sg:address":"327 Quail Haven Rd",
    "sg:city":"China Spring",
    "sg:classifiers":[
        {
            "category":"Shopping",
            "type":"Retail Goods"
        }
    ],
    "sg:phone":"+1 254 836 4056",
    "sg:postcode":"76633",
    "sg:province":"TX",
    "sg:tags":[
        "merchandise"
    ],
    "wof:name":"Beals Exotic Birds",
    "wof:placetype":"venue"
},
  "geometry": {"coordinates":[-97.28703,31.678185],"type":"Point"}
}