{
  "type": "Feature",
  "properties": {
    "iso:country":"US",
    "sg:address":"1950 US Hwy 80",
    "sg:city":"Abilene",
    "sg:classifiers":[
        {
            "category":"Mining & Drilling",
            "type":"Manufacturing & Wholesale Goods"
        }
    ],
    "sg:phone":"+1 325 673 1151",
    "sg:postcode":"79601",
    "sg:province":"TX",
    "sg:tags":[
        "operator",
        "oil"
    ],
    "wof:name":"K W Well Svc",
    "wof:placetype":"venue"
},
  "geometry": {"coordinates":[-99.69278199999999,32.447458],"type":"Point"}
}