{
  "type": "Feature",
  "properties": {
    "iso:country":"US",
    "sg:address":"2544 Gus Thomasson Rd",
    "sg:city":"Dallas",
    "sg:classifiers":[
        {
            "category":"Ice Cream",
            "type":"Food & Drink"
        }
    ],
    "sg:phone":"+1 214 954 7279",
    "sg:postcode":"75228",
    "sg:province":"TX",
    "sg:tags":[
        "frozen",
        "yogurt"
    ],
    "wof:name":"17 Degrees Frozen Yogurt",
    "wof:placetype":"venue"
},
  "geometry": {"coordinates":[-96.67214199999999,32.834739],"type":"Point"}
}