{
  "type": "Feature",
  "properties": {
    "iso:country":"US",
    "sg:address":"2630 Northaven Rd",
    "sg:city":"Dallas",
    "sg:classifiers":[
        {
            "category":"Professional",
            "subcategory":"Testing Lab",
            "type":"Services"
        },
        {
            "category":"Professional",
            "subcategory":"Engineering",
            "type":"Services"
        }
    ],
    "sg:phone":"+1 972 488 3500",
    "sg:postcode":"75229",
    "sg:province":"TX",
    "sg:tags":[
        "laboratory"
    ],
    "wof:name":"Geoscience Engineering & Tstg",
    "wof:placetype":"venue"
},
  "geometry": {"coordinates":[-96.890164,32.903778],"type":"Point"}
}