{
  "type": "Feature",
  "properties": {
    "iso:country":"US",
    "sg:address":"4310 Buena Vista St",
    "sg:city":"Dallas",
    "sg:classifiers":[
        {
            "category":"Mining & Drilling",
            "type":"Manufacturing & Wholesale Goods"
        }
    ],
    "sg:phone":"+1 214 692 0072",
    "sg:postcode":"75205",
    "sg:province":"TX",
    "sg:tags":[
        "development",
        "gas",
        "oil",
        "exploration"
    ],
    "wof:name":"Alpine Exploration",
    "wof:placetype":"venue"
},
  "geometry": {"coordinates":[-96.793007,32.820669],"type":"Point"}
}