{
  "type": "Feature",
  "properties": {
    "iso:country":"US",
    "sg:address":"11911 Martin Luther King Jr Blvd",
    "sg:city":"Houston",
    "sg:classifiers":[
        {
            "category":"Building & Trades",
            "subcategory":"Cleaning & Sanitation",
            "type":"Services"
        }
    ],
    "sg:phone":"+1 713 738 5697",
    "sg:postcode":"77048",
    "sg:province":"TX",
    "sg:tags":[
        "janitor"
    ],
    "wof:name":"B S Cleaning Svc",
    "wof:placetype":"venue"
},
  "geometry": {"coordinates":[-95.339359,29.631078],"type":"Point"}
}