{
  "type": "Feature",
  "properties": {
    "iso:country":"US",
    "sg:address":"12127 Highway 36",
    "sg:city":"Bellville",
    "sg:classifiers":[
        {
            "category":"Manufacturing",
            "subcategory":"Food",
            "type":"Manufacturing & Wholesale Goods"
        },
        {
            "category":"Wholesale",
            "subcategory":"Groceries",
            "type":"Manufacturing & Wholesale Goods"
        },
        {
            "category":"Food & Beverages",
            "subcategory":"Groceries & Convenience Stores",
            "type":"Retail Goods"
        }
    ],
    "sg:phone":"+1 979 865 9701",
    "sg:postcode":"77418",
    "sg:province":"TX",
    "sg:tags":[
        "product",
        "processing",
        "products-wholesale",
        "chip",
        "potato"
    ],
    "sg:website":"http://www.fritolay.com",
    "wof:name":"Frito Lay Incorporated",
    "wof:placetype":"venue"
},
  "geometry": {"coordinates":[-96.343194,30.0674],"type":"Point"}
}