{
  "type": "Feature",
  "properties": {
    "iso:country":"US",
    "sg:address":"305 NE Loop 820",
    "sg:city":"Hurst",
    "sg:classifiers":[
        {
            "category":"Wholesale",
            "subcategory":"Motor Vehicles",
            "type":"Manufacturing & Wholesale Goods"
        }
    ],
    "sg:phone":"+1 817 590 4675",
    "sg:postcode":"76053",
    "sg:province":"TX",
    "sg:tags":[
        "auction",
        "automobile"
    ],
    "wof:name":"National Automotive Info Bur",
    "wof:placetype":"venue"
},
  "geometry": {"coordinates":[-97.20737800000001,32.815348],"type":"Point"}
}