{
  "type": "Feature",
  "properties": {
    "iso:country":"US",
    "sg:address":"707 N Super St",
    "sg:city":"Houston",
    "sg:classifiers":[
        {
            "category":"Building & Trades",
            "subcategory":"Construction",
            "type":"Services"
        }
    ],
    "sg:phone":"+1 713 923 6934",
    "sg:postcode":"77011",
    "sg:province":"TX",
    "sg:tags":[
        "contractor"
    ],
    "wof:name":"A L Tile and Marble",
    "wof:placetype":"venue"
},
  "geometry": {"coordinates":[-95.324634,29.754095],"type":"Point"}
}