{
  "type": "Feature",
  "properties": {
    "iso:country":"US",
    "sg:address":"13246 Murphy Rd Ste 400",
    "sg:city":"Stafford",
    "sg:classifiers":[
        {
            "category":"Shopping",
            "subcategory":"Stationery & Office Supplies",
            "type":"Retail Goods"
        }
    ],
    "sg:phone":"+1 281 499 6900",
    "sg:postcode":"77477",
    "sg:province":"TX",
    "sg:tags":[
        "equipment"
    ],
    "sg:website":"www.camperisofficefurniture.net",
    "wof:name":"CAMPERI'S OFFICE FURNITURE",
    "wof:placetype":"venue"
},
  "geometry": {"coordinates":[-95.565101,29.63044],"type":"Point"}
}