{
  "type": "Feature",
  "properties": {
    "iso:country":"US",
    "sg:address":"3801 Herschel Ave",
    "sg:city":"Dallas",
    "sg:classifiers":[
        {
            "category":"Education",
            "subcategory":"School",
            "type":"Public Place"
        }
    ],
    "sg:phone":"+1 972 502 1200",
    "sg:postcode":"75219",
    "sg:province":"TX",
    "sg:website":"www.dallasisd.org",
    "wof:name":"Schools",
    "wof:placetype":"venue"
},
  "geometry": {"coordinates":[-96.809837,32.820293],"type":"Point"}
}