{
  "type": "Feature",
  "properties": {
    "iso:country":"US",
    "sg:address":"788 State Hwy 7",
    "sg:city":"Center",
    "sg:classifiers":[
        {
            "category":"Shopping",
            "subcategory":"Florist",
            "type":"Retail Goods"
        }
    ],
    "sg:phone":"+1 936 598 9949",
    "sg:postcode":"75935",
    "sg:province":"TX",
    "wof:name":"Hughes Florist",
    "wof:placetype":"venue"
},
  "geometry": {"coordinates":[-94.18611799999999,31.788057],"type":"Point"}
}