{
  "type": "Feature",
  "properties": {
    "iso:country":"US",
    "sg:address":"718 Card Dr",
    "sg:city":"Lufkin",
    "sg:classifiers":[
        {
            "category":"Personal",
            "subcategory":"Beauty Salon",
            "type":"Services"
        }
    ],
    "sg:phone":"+1 936 634 3122",
    "sg:postcode":"75901",
    "sg:province":"TX",
    "sg:tags":[
        "shop"
    ],
    "wof:name":"J Pauls Salon",
    "wof:placetype":"venue"
},
  "geometry": {"coordinates":[-94.712476,31.318261],"type":"Point"}
}