{
  "type": "Feature",
  "properties": {
    "iso:country":"US",
    "sg:address":"1203 Fairchild Dr",
    "sg:city":"Diboll",
    "sg:classifiers":[
        {
            "category":"Freight",
            "type":"Transportation"
        }
    ],
    "sg:phone":"+1 936 829 2253",
    "sg:postcode":"75941",
    "sg:province":"TX",
    "sg:tags":[
        "operator",
        "local",
        "trucking"
    ],
    "wof:name":"Nathan W Pullin Trucking",
    "wof:placetype":"venue"
},
  "geometry": {"coordinates":[-94.74140199999999,31.234181],"type":"Point"}
}