{
  "type": "Feature",
  "properties": {
    "iso:country":"US",
    "sg:address":"905 Magdalene Dr",
    "sg:city":"Houston",
    "sg:classifiers":[
        {
            "category":"Real Estate",
            "subcategory":"Real Estate Agent",
            "type":"Services"
        }
    ],
    "sg:phone":"+1 713 932 9969",
    "sg:postcode":"77024",
    "sg:province":"TX",
    "sg:tags":[
        "development",
        "company",
        "appraiser",
        "general"
    ],
    "wof:name":"Kurtin Real Estate & Dev Inc",
    "wof:placetype":"venue"
},
  "geometry": {"coordinates":[-95.528173,29.779477],"type":"Point"}
}