{
  "type": "Feature",
  "properties": {
    "iso:country":"US",
    "sg:address":"2221 W Houston Ave",
    "sg:city":"Mcallen",
    "sg:classifiers":[
        {
            "category":"Wholesale",
            "subcategory":"Auto Parts",
            "type":"Manufacturing & Wholesale Goods"
        }
    ],
    "sg:phone":"+1 956 682 8359",
    "sg:postcode":"78501",
    "sg:province":"TX",
    "sg:tags":[
        "supply"
    ],
    "wof:name":"Valley Auto Parts",
    "wof:placetype":"venue"
},
  "geometry": {"coordinates":[-98.246016,26.198056],"type":"Point"}
}