{
  "type": "Feature",
  "properties": {
    "iso:country":"US",
    "sg:address":"899 Tahuaya Dr",
    "sg:city":"Belton",
    "sg:classifiers":[
        {
            "category":"Cinema",
            "subcategory":"Movie Rental",
            "type":"Entertainment"
        }
    ],
    "sg:phone":"+1 254 947 0093",
    "sg:postcode":"76513",
    "sg:province":"TX",
    "sg:tags":[
        "video",
        "tape"
    ],
    "wof:name":"Last Drive In Picture Show Th",
    "wof:placetype":"venue"
},
  "geometry": {"coordinates":[-97.50080199999999,30.998844],"type":"Point"}
}