{
  "type": "Feature",
  "properties": {
    "iso:country":"US",
    "sg:address":"2803 Winding Oak Trl",
    "sg:city":"Garland",
    "sg:classifiers":[
        {
            "category":"Wholesale",
            "subcategory":"Metals & Minerals",
            "type":"Manufacturing & Wholesale Goods"
        }
    ],
    "sg:phone":"+1 972 496 0180",
    "sg:postcode":"75044",
    "sg:province":"TX",
    "sg:tags":[
        "center"
    ],
    "wof:name":"Debmet Inc",
    "wof:placetype":"venue"
},
  "geometry": {"coordinates":[-96.67142,32.932551],"type":"Point"}
}