{
  "type": "Feature",
  "properties": {
    "iso:country":"US",
    "sg:address":"809 East St",
    "sg:city":"Texarkana",
    "sg:classifiers":[
        {
            "category":"Wholesale",
            "subcategory":"Tobacco Products",
            "type":"Manufacturing & Wholesale Goods"
        }
    ],
    "sg:phone":"+1 870 773 1860",
    "sg:postcode":"71854",
    "sg:province":"TX",
    "sg:tags":[
        "cigarette",
        "cigar",
        "dealer"
    ],
    "wof:name":"Tobacco Station USA",
    "wof:placetype":"venue"
},
  "geometry": {"coordinates":[-94.03027400000001,33.412784],"type":"Point"}
}