{
  "type": "Feature",
  "properties": {
    "iso:country":"US",
    "sg:address":"3000 Phoenix Dr",
    "sg:city":"Fort Worth",
    "sg:classifiers":[
        {
            "category":"Shopping",
            "type":"Retail Goods"
        }
    ],
    "sg:phone":"+1 817 244 4135",
    "sg:postcode":"76116",
    "sg:province":"TX",
    "sg:tags":[
        "merchandise"
    ],
    "wof:name":"Candle Delight",
    "wof:placetype":"venue"
},
  "geometry": {"coordinates":[-97.458249,32.729461],"type":"Point"}
}