{
  "type": "Feature",
  "properties": {
    "iso:country":"US",
    "sg:address":"120 Woodway Ln",
    "sg:city":"San Antonio",
    "sg:classifiers":[
        {
            "category":"Professional",
            "subcategory":"Computer Services",
            "type":"Services"
        }
    ],
    "sg:phone":"+1 210 885 8167",
    "sg:postcode":"78209",
    "sg:province":"TX",
    "sg:tags":[
        "consultant",
        "designer"
    ],
    "sg:website":"www.farrimond.org",
    "wof:name":"Farrimond Technologies",
    "wof:placetype":"venue"
},
  "geometry": {"coordinates":[-98.473056,29.487167],"type":"Point"}
}