{
  "type": "Feature",
  "properties": {
    "iso:country":"US",
    "sg:address":"9816 Memorial Blvd # 206",
    "sg:city":"Humble",
    "sg:classifiers":[
        {
            "category":"Health Services",
            "subcategory":"Doctor",
            "type":"Services"
        },
        {
            "category":"Health Services",
            "subcategory":"Clinic",
            "type":"Services"
        },
        {
            "category":"Community Center",
            "type":"Public Place"
        }
    ],
    "sg:phone":"+1 281 446 8114",
    "sg:postcode":"77338",
    "sg:province":"TX",
    "sg:tags":[
        "physician",
        "stomach",
        "gastroenterology",
        "medical",
        "surgeons",
        "surgeon",
        "intestines"
    ],
    "wof:name":"Digestive Disease Consultants",
    "wof:placetype":"venue"
},
  "geometry": {"coordinates":[-95.274998,29.994317],"type":"Point"}
}