{
  "type": "Feature",
  "properties": {
    "iso:country":"US",
    "sg:address":"139 Mulberry St",
    "sg:city":"Lake Jackson",
    "sg:classifiers":[
        {
            "category":"Building & Trades",
            "subcategory":"Landscaping Services",
            "type":"Services"
        }
    ],
    "sg:phone":"+1 979 297 7762",
    "sg:postcode":"77566",
    "sg:province":"TX",
    "wof:name":"Chamblees Mowing Service",
    "wof:placetype":"venue"
},
  "geometry": {"coordinates":[-95.424066,29.033122],"type":"Point"}
}