{
  "type": "Feature",
  "properties": {
    "iso:country":"US",
    "sg:address":"153 Hilldale Dr",
    "sg:city":"Nederland",
    "sg:classifiers":[
        {
            "category":"Building & Trades",
            "subcategory":"Construction",
            "type":"Services"
        }
    ],
    "sg:phone":"+1 409 727 7599",
    "sg:postcode":"77627",
    "sg:province":"TX",
    "sg:tags":[
        "nonresidential"
    ],
    "wof:name":"Hall Construction",
    "wof:placetype":"venue"
},
  "geometry": {"coordinates":[-93.994033,29.953682],"type":"Point"}
}