{
  "type": "Feature",
  "properties": {
    "iso:country":"US",
    "sg:address":"1248 Austin Hwy",
    "sg:city":"San Antonio",
    "sg:classifiers":[
        {
            "category":"Recreation",
            "type":"Entertainment"
        }
    ],
    "sg:phone":"+1 210 805 8885",
    "sg:postcode":"78209",
    "sg:province":"TX",
    "wof:name":"Summer Palace",
    "wof:placetype":"venue"
},
  "geometry": {"coordinates":[-98.44214599999999,29.489787],"type":"Point"}
}