{
  "type": "Feature",
  "properties": {
    "iso:country":"US",
    "sg:address":"10909 Sanden Dr",
    "sg:city":"Dallas",
    "sg:classifiers":[
        {
            "category":"Freight",
            "type":"Transportation"
        }
    ],
    "sg:phone":"+1 214 221 0132",
    "sg:postcode":"75238",
    "sg:province":"TX",
    "sg:tags":[
        "trucking"
    ],
    "wof:name":"Dupre Transport LLC",
    "wof:placetype":"venue"
},
  "geometry": {"coordinates":[-96.694008,32.89866],"type":"Point"}
}