{
  "type": "Feature",
  "properties": {
    "iso:country":"US",
    "sg:address":"15555 Vickery Dr",
    "sg:city":"Houston",
    "sg:classifiers":[
        {
            "category":"Wholesale",
            "subcategory":"Machinery & Supplies",
            "type":"Manufacturing & Wholesale Goods"
        }
    ],
    "sg:phone":"+1 281 590 1431",
    "sg:postcode":"77032",
    "sg:province":"TX",
    "sg:tags":[
        "engine",
        "aircraft",
        "parts"
    ],
    "wof:name":"Arnoni Aviation Limited",
    "wof:placetype":"venue"
},
  "geometry": {"coordinates":[-95.315755,29.94188],"type":"Point"}
}