{
  "type": "Feature",
  "properties": {
    "iso:country":"US",
    "sg:address":"3915 Spring Ave",
    "sg:city":"Dallas",
    "sg:classifiers":[
        {
            "category":"Freight",
            "type":"Transportation"
        }
    ],
    "sg:phone":"+1 214 421 7992",
    "sg:postcode":"75210",
    "sg:province":"TX",
    "wof:name":"Jabez Transport Inc",
    "wof:placetype":"venue"
},
  "geometry": {"coordinates":[-96.747848,32.769873],"type":"Point"}
}