{
  "type": "Feature",
  "properties": {
    "iso:country":"US",
    "sg:address":"402 S Main St",
    "sg:city":"Mcallen",
    "sg:classifiers":[
        {
            "category":"Shopping",
            "subcategory":"Jewelry",
            "type":"Retail Goods"
        }
    ],
    "sg:phone":"+1 956 971 1670",
    "sg:postcode":"78501",
    "sg:province":"TX",
    "sg:tags":[
        "jeweler"
    ],
    "wof:name":"Italian Gold Imports",
    "wof:placetype":"venue"
},
  "geometry": {"coordinates":[-98.23528399999999,26.199575],"type":"Point"}
}