{
  "type": "Feature",
  "properties": {
    "iso:country":"US",
    "sg:address":"2923 6th Ave",
    "sg:city":"Amarillo",
    "sg:classifiers":[
        {
            "category":"Shopping",
            "subcategory":"Luggage & Leather Goods",
            "type":"Retail Goods"
        }
    ],
    "sg:phone":"+1 806 373 6132",
    "sg:postcode":"79106",
    "sg:province":"TX",
    "wof:name":"Gran Fe Custom Leather",
    "wof:placetype":"venue"
},
  "geometry": {"coordinates":[-101.86963,35.211225],"type":"Point"}
}