{
  "type": "Feature",
  "properties": {
    "iso:country":"US",
    "sg:address":"1700 Rebecca Ln",
    "sg:city":"Conroe",
    "sg:classifiers":[
        {
            "category":"Retail",
            "subcategory":"Repair Shop",
            "type":"Services"
        }
    ],
    "sg:phone":"+1 936 760 1126",
    "sg:postcode":"77301",
    "sg:province":"TX",
    "wof:name":"J Alan Furniture Refinishing",
    "wof:placetype":"venue"
},
  "geometry": {"coordinates":[-95.426817,30.311331],"type":"Point"}
}