{
  "type": "Feature",
  "properties": {
    "iso:country":"US",
    "sg:address":"3022 FM 2802",
    "sg:city":"Orange",
    "sg:classifiers":[
        {
            "category":"Shopping",
            "subcategory":"Gifts & Souvenirs",
            "type":"Retail Goods"
        }
    ],
    "sg:phone":"+1 409 745 5405",
    "sg:postcode":"77632",
    "sg:province":"TX",
    "sg:tags":[
        "novelty",
        "wear",
        "child"
    ],
    "wof:name":"Kracker Jack Kids",
    "wof:placetype":"venue"
},
  "geometry": {"coordinates":[-93.881822,30.220765],"type":"Point"}
}