{
  "type": "Feature",
  "properties": {
    "iso:country":"US",
    "sg:address":"2908 Story Rd W",
    "sg:city":"Irving",
    "sg:classifiers":[
        {
            "category":"Professional",
            "subcategory":"Business Services",
            "type":"Services"
        }
    ],
    "sg:phone":"+1 972 647 2629",
    "sg:postcode":"75038",
    "sg:province":"TX",
    "sg:tags":[
        "water",
        "treatment"
    ],
    "wof:name":"Novatek",
    "wof:placetype":"venue"
},
  "geometry": {"coordinates":[-96.982947,32.871251],"type":"Point"}
}