{
  "type": "Feature",
  "properties": {
    "iso:country":"US",
    "sg:address":"1813 Todville Rd",
    "sg:city":"Seabrook",
    "sg:classifiers":[
        {
            "category":"Recreation",
            "type":"Entertainment"
        }
    ],
    "sg:phone":"+1 281 291 9733",
    "sg:postcode":"77586",
    "sg:province":"TX",
    "wof:name":"Fishing Unlimited Inc",
    "wof:placetype":"venue"
},
  "geometry": {"coordinates":[-95.014973,29.563747],"type":"Point"}
}