{
  "type": "Feature",
  "properties": {
    "iso:country":"US",
    "sg:address":"6105 Crimson Dr",
    "sg:city":"Mc Kinney",
    "sg:classifiers":[
        {
            "category":"Professional",
            "subcategory":"Lawyer & Legal Services",
            "type":"Services"
        }
    ],
    "sg:phone":"+1 972 529 1054",
    "sg:postcode":"75070",
    "sg:province":"TX",
    "wof:name":"Bankhead Barefoot",
    "wof:placetype":"venue"
},
  "geometry": {"coordinates":[-96.698156,33.193201],"type":"Point"}
}