{
  "type": "Feature",
  "properties": {
    "iso:country":"US",
    "sg:address":"1430 N Woods St",
    "sg:city":"Sherman",
    "sg:classifiers":[
        {
            "category":"Building & Trades",
            "subcategory":"Construction",
            "type":"Services"
        }
    ],
    "sg:phone":"+1 903 814 0715",
    "sg:postcode":"75092",
    "sg:province":"TX",
    "sg:tags":[
        "industrial",
        "contractors-commercial",
        "contractor"
    ],
    "wof:name":"Superior Construction",
    "wof:placetype":"venue"
},
  "geometry": {"coordinates":[-96.61876599999999,33.648274],"type":"Point"}
}