{
  "type": "Feature",
  "properties": {
    "iso:country":"US",
    "sg:address":"3409 Central Expy",
    "sg:city":"Plano",
    "sg:classifiers":[
        {
            "category":"Banks & Credit Unions",
            "subcategory":"Bank",
            "type":"Services"
        }
    ],
    "sg:phone":"+1 972 422 9810",
    "sg:postcode":"75023",
    "sg:province":"TX",
    "sg:tags":[
        "state",
        "commercial"
    ],
    "wof:name":"First American Bank Ssb",
    "wof:placetype":"venue"
},
  "geometry": {"coordinates":[-96.700123,33.046623],"type":"Point"}
}