{
  "type": "Feature",
  "properties": {
    "iso:country":"US",
    "sg:address":"16933 Garrett Rd",
    "sg:city":"Harlingen",
    "sg:classifiers":[
        {
            "category":"Manufacturing",
            "subcategory":"Metals",
            "type":"Manufacturing & Wholesale Goods"
        }
    ],
    "sg:phone":"+1 956 421 3936",
    "sg:postcode":"78552",
    "sg:province":"TX",
    "sg:tags":[
        "steel"
    ],
    "wof:name":"Mattei Inc Metal Works",
    "wof:placetype":"venue"
},
  "geometry": {"coordinates":[-97.751954,26.170864],"type":"Point"}
}