{
  "type": "Feature",
  "properties": {
    "iso:country":"US",
    "sg:address":"2211 Midwestern Pkwy",
    "sg:city":"Wichita Falls",
    "sg:classifiers":[
        {
            "category":"Health Services",
            "subcategory":"Doctor",
            "type":"Services"
        }
    ],
    "sg:phone":"+1 940 696 2323",
    "sg:postcode":"76308",
    "sg:province":"TX",
    "sg:tags":[
        "physician",
        "surgeon",
        "allergy",
        "center"
    ],
    "wof:name":"Allergy Center PA",
    "wof:placetype":"venue"
},
  "geometry": {"coordinates":[-98.513803,33.871389],"type":"Point"}
}