{
  "type": "Feature",
  "properties": {
    "iso:country":"US",
    "sg:address":"3212 Lakehurst Dr",
    "sg:city":"Mesquite",
    "sg:classifiers":[
        {
            "category":"Retail",
            "subcategory":"Auto Repair",
            "type":"Services"
        }
    ],
    "sg:phone":"+1 972 222 5773",
    "sg:postcode":"75181",
    "sg:province":"TX",
    "sg:tags":[
        "automotive"
    ],
    "wof:name":"Edomen Inc",
    "wof:placetype":"venue"
},
  "geometry": {"coordinates":[-96.549302,32.753924],"type":"Point"}
}