{
  "type": "Feature",
  "properties": {
    "iso:country":"US",
    "sg:address":"1402 Azle Hwy",
    "sg:city":"Weatherford",
    "sg:classifiers":[
        {
            "category":"Building & Trades",
            "subcategory":"Construction",
            "type":"Services"
        }
    ],
    "sg:phone":"+1 817 781 1606",
    "sg:postcode":"76085",
    "sg:province":"TX",
    "sg:tags":[
        "clearing",
        "land",
        "leveling"
    ],
    "wof:name":"M M Construction & Excavation",
    "wof:placetype":"venue"
},
  "geometry": {"coordinates":[-97.731754,32.781433],"type":"Point"}
}