{
  "type": "Feature",
  "properties": {
    "iso:country":"US",
    "sg:address":"5700 Tapadera Trace Ln",
    "sg:city":"Austin",
    "sg:classifiers":[
        {
            "category":"Professional",
            "subcategory":"Business Services",
            "type":"Services"
        }
    ],
    "sg:phone":"+1 512 250 0700",
    "sg:postcode":"78727",
    "sg:province":"TX",
    "wof:name":"Thall Design",
    "wof:placetype":"venue"
},
  "geometry": {"coordinates":[-97.742738,30.430504],"type":"Point"}
}