{
  "type": "Feature",
  "properties": {
    "iso:country":"US",
    "sg:address":"121 Atlantic St",
    "sg:city":"Corpus Christi",
    "sg:classifiers":[
        {
            "category":"Health Services",
            "subcategory":"Doctor",
            "type":"Services"
        }
    ],
    "sg:phone":"+1 361 883 9091",
    "sg:postcode":"78404",
    "sg:province":"TX",
    "sg:tags":[
        "medical"
    ],
    "wof:name":"Christopher P Comstock MD",
    "wof:placetype":"venue"
},
  "geometry": {"coordinates":[-97.39241699999999,27.771479],"type":"Point"}
}