{
  "type": "Feature",
  "properties": {
    "iso:country":"US",
    "sg:address":"5469 N Macarthur Blvd",
    "sg:city":"Irving",
    "sg:classifiers":[
        {
            "category":"Restaurant",
            "type":"Food & Drink"
        }
    ],
    "sg:phone":"+1 972 518 1962",
    "sg:postcode":"75038",
    "sg:province":"TX",
    "sg:tags":[
        "sandwich"
    ],
    "wof:name":"Roly Poly",
    "wof:placetype":"venue"
},
  "geometry": {"coordinates":[-96.96419899999999,32.884887],"type":"Point"}
}