{
  "type": "Feature",
  "properties": {
    "iso:country":"US",
    "sg:address":"2700 7th St",
    "sg:city":"Bay City",
    "sg:classifiers":[
        {
            "category":"Utilities",
            "subcategory":"Mobile Phone",
            "type":"Services"
        }
    ],
    "sg:phone":"+1 979 244 3535",
    "sg:postcode":"77414",
    "sg:province":"TX",
    "sg:tags":[
        "telephone",
        "cellular"
    ],
    "wof:name":"Cellular Connection",
    "wof:placetype":"venue"
},
  "geometry": {"coordinates":[-95.956987,28.983373],"type":"Point"}
}