{
  "type": "Feature",
  "properties": {
    "iso:country":"US",
    "sg:address":"1928 Johanna Dr",
    "sg:city":"Houston",
    "sg:classifiers":[
        {
            "category":"Building & Trades",
            "subcategory":"Construction",
            "type":"Services"
        }
    ],
    "sg:phone":"+1 713 683 1931",
    "sg:postcode":"77055",
    "sg:province":"TX",
    "sg:tags":[
        "house"
    ],
    "wof:name":"Topique Construction",
    "wof:placetype":"venue"
},
  "geometry": {"coordinates":[-95.482766,29.804193],"type":"Point"}
}