{
  "type": "Feature",
  "properties": {
    "iso:country":"US",
    "sg:address":"675 Hembry St",
    "sg:city":"Lewisville",
    "sg:classifiers":[
        {
            "category":"Retail",
            "subcategory":"Repair Shop",
            "type":"Services"
        }
    ],
    "sg:phone":"+1 972 420 1396",
    "sg:postcode":"75057",
    "sg:province":"TX",
    "sg:tags":[
        "reupholstery",
        "furniture"
    ],
    "sg:website":"www.lone.ws",
    "wof:name":"Lone Star Custom Upholstery",
    "wof:placetype":"venue"
},
  "geometry": {"coordinates":[-96.99189800000001,33.039799],"type":"Point"}
}