{
  "type": "Feature",
  "properties": {
    "iso:country":"US",
    "sg:address":"2560 Tarpley Rd",
    "sg:city":"Carrollton",
    "sg:classifiers":[
        {
            "category":"Shopping",
            "subcategory":"Jewelry",
            "type":"Retail Goods"
        }
    ],
    "sg:phone":"+1 972 416 6000",
    "sg:postcode":"75006",
    "sg:province":"TX",
    "wof:name":"Pacific Northern Inc",
    "wof:placetype":"venue"
},
  "geometry": {"coordinates":[-96.851438,32.985153],"type":"Point"}
}