{
  "type": "Feature",
  "properties": {
    "iso:country":"US",
    "sg:address":"14005 McNeil Rd",
    "sg:city":"Austin",
    "sg:classifiers":[
        {
            "category":"Government",
            "subcategory":"Post Office",
            "type":"Public Place"
        }
    ],
    "sg:phone":"+1 512 255 8330",
    "sg:postcode":"78728",
    "sg:province":"TX",
    "wof:name":"US Post Office",
    "wof:placetype":"venue"
},
  "geometry": {"coordinates":[-97.72050900000001,30.455605],"type":"Point"}
}