{
  "type": "Feature",
  "properties": {
    "iso:country":"US",
    "sg:address":"318 N Main St",
    "sg:city":"Shamrock",
    "sg:classifiers":[
        {
            "category":"Travel",
            "subcategory":"Campground",
            "type":"Entertainment"
        }
    ],
    "sg:phone":"+1 806 256 3719",
    "sg:postcode":"79079",
    "sg:province":"TX",
    "wof:name":"West Forty Camp Area",
    "wof:placetype":"venue"
},
  "geometry": {"coordinates":[-100.24906300000001,35.217366],"type":"Point"}
}