{
  "type": "Feature",
  "properties": {
    "iso:country":"US",
    "sg:address":"574 Youngblood Rd",
    "sg:city":"Robinson",
    "sg:classifiers":[
        {
            "category":"Building & Trades",
            "subcategory":"Construction",
            "type":"Services"
        }
    ],
    "sg:phone":"+1 254 662 5571",
    "sg:postcode":"76706",
    "sg:province":"TX",
    "sg:tags":[
        "roofing",
        "contractor"
    ],
    "wof:name":"Johnson Roofing",
    "wof:placetype":"venue"
},
  "geometry": {"coordinates":[-97.105396,31.447713],"type":"Point"}
}