{
  "type": "Feature",
  "properties": {
    "iso:country":"US",
    "sg:address":"2530 Tarpley Rd",
    "sg:city":"Carrollton",
    "sg:classifiers":[
        {
            "category":"Health Services",
            "subcategory":"Health Practitioner",
            "type":"Services"
        }
    ],
    "sg:phone":"+1 214 483 2200",
    "sg:postcode":"75006",
    "sg:province":"TX",
    "sg:tags":[
        "therapy",
        "physical"
    ],
    "wof:name":"Abra Therapeutics",
    "wof:placetype":"venue"
},
  "geometry": {"coordinates":[-96.851456,32.983688],"type":"Point"}
}