{
  "type": "Feature",
  "properties": {
    "iso:country":"US",
    "sg:address":"9515 N Lamar Blvd",
    "sg:city":"Austin",
    "sg:phone":"+1 512 453 6616",
    "sg:postcode":"78753",
    "sg:province":"TX",
    "wof:name":"Desperados",
    "wof:placetype":"venue"
},
  "geometry": {"coordinates":[-97.69600699999999,30.36488],"type":"Point"}
}