{
  "type": "Feature",
  "properties": {
    "iso:country":"US",
    "sg:address":"11608 Sweetshade Ln",
    "sg:city":"Austin",
    "sg:classifiers":[
        {
            "category":"Wholesale",
            "subcategory":"Painting Supplies",
            "type":"Manufacturing & Wholesale Goods"
        },
        {
            "category":"Manufacturing",
            "subcategory":"Chemicals & Compounds",
            "type":"Manufacturing & Wholesale Goods"
        },
        {
            "category":"Manufacturing",
            "subcategory":"Building Materials",
            "type":"Manufacturing & Wholesale Goods"
        }
    ],
    "sg:phone":"+1 512 480 8466",
    "sg:postcode":"78759",
    "sg:province":"TX",
    "sg:tags":[
        "paint-wholesale",
        "equipment",
        "manufacturer",
        "painter",
        "paint"
    ],
    "sg:website":"http://www.clementspaint.com",
    "wof:name":"Clement's Paint",
    "wof:placetype":"venue"
},
  "geometry": {"coordinates":[-97.770768,30.426887],"type":"Point"}
}