{
  "type": "Feature",
  "properties": {
    "iso:country":"US",
    "sg:address":"4257 I- 35 N",
    "sg:city":"Waco",
    "sg:classifiers":[
        {
            "category":"Travel",
            "subcategory":"Hotels & Motels",
            "type":"Entertainment"
        }
    ],
    "sg:phone":"+1 254 412 2535",
    "sg:postcode":"76705",
    "sg:province":"TX",
    "wof:name":"Fairfield Inn & Suites North",
    "wof:placetype":"venue"
},
  "geometry": {"coordinates":[-97.10627100000001,31.606626],"type":"Point"}
}