{
  "type": "Feature",
  "properties": {
    "iso:country":"US",
    "sg:address":"104 Bal Harbor Ln",
    "sg:city":"Bullard",
    "sg:classifiers":[
        {
            "category":"Professional",
            "subcategory":"Business Services",
            "type":"Services"
        }
    ],
    "sg:phone":"+1 903 574 1556",
    "sg:postcode":"75757",
    "sg:province":"TX",
    "wof:name":"Rainbow Pool Services",
    "wof:placetype":"venue"
},
  "geometry": {"coordinates":[-95.444503,32.159354],"type":"Point"}
}