{
  "type": "Feature",
  "properties": {
    "iso:country":"US",
    "sg:address":"507 US Hwy 77",
    "sg:city":"Waxahachie",
    "sg:classifiers":[
        {
            "category":"Shopping",
            "subcategory":"Jewelry",
            "type":"Retail Goods"
        }
    ],
    "sg:phone":"+1 972 923 0015",
    "sg:postcode":"75165",
    "sg:province":"TX",
    "sg:tags":[
        "jeweler"
    ],
    "wof:name":"Simply Diva's",
    "wof:placetype":"venue"
},
  "geometry": {"coordinates":[-96.841666,32.412881],"type":"Point"}
}