{
  "type": "Feature",
  "properties": {
    "iso:country":"US",
    "sg:address":"95 W 2nd St",
    "sg:city":"Big Lake",
    "sg:classifiers":[
        {
            "category":"Professional",
            "subcategory":"Management & Consulting",
            "type":"Services"
        }
    ],
    "sg:phone":"+1 325 884 5772",
    "sg:postcode":"76932",
    "sg:province":"TX",
    "sg:tags":[
        "food",
        "facility"
    ],
    "wof:name":"Big Lake Anchor Svc",
    "wof:placetype":"venue"
},
  "geometry": {"coordinates":[-101.46545,31.191564],"type":"Point"}
}