{
  "type": "Feature",
  "properties": {
    "iso:country":"US",
    "sg:address":"153 Diamond Dr",
    "sg:city":"Killeen",
    "sg:classifiers":[
        {
            "category":"Retail",
            "subcategory":"Auto Repair",
            "type":"Services"
        }
    ],
    "sg:phone":"+1 254 554 6490",
    "sg:postcode":"76542",
    "sg:province":"TX",
    "sg:tags":[
        "repairing",
        "automobile"
    ],
    "wof:name":"J T Automotive Inc",
    "wof:placetype":"venue"
},
  "geometry": {"coordinates":[-97.742473,30.990232],"type":"Point"}
}