{
  "type": "Feature",
  "properties": {
    "iso:country":"US",
    "sg:address":"5204 Doe Valley Ln",
    "sg:city":"Austin",
    "sg:classifiers":[
        {
            "category":"Shopping",
            "subcategory":"Gifts & Souvenirs",
            "type":"Retail Goods"
        }
    ],
    "sg:phone":"+1 512 345 3873",
    "sg:postcode":"78759",
    "sg:province":"TX",
    "sg:tags":[
        "basket"
    ],
    "wof:name":"All Occasions Gift Baskets",
    "wof:placetype":"venue"
},
  "geometry": {"coordinates":[-97.760002,30.392269],"type":"Point"}
}