{
  "type": "Feature",
  "properties": {
    "iso:country":"US",
    "sg:address":"140 N Cotton St",
    "sg:city":"El Paso",
    "sg:classifiers":[
        {
            "category":"Professional",
            "subcategory":"Management & Consulting",
            "type":"Services"
        }
    ],
    "sg:phone":"+1 915 534 9160",
    "sg:postcode":"79901",
    "sg:province":"TX",
    "sg:tags":[
        "environmental"
    ],
    "wof:name":"Cfr Environmental Services",
    "wof:placetype":"venue"
},
  "geometry": {"coordinates":[-106.47357599999999,31.765386],"type":"Point"}
}