{
  "type": "Feature",
  "properties": {
    "iso:country":"US",
    "sg:address":"200 S 16th St",
    "sg:city":"Mcallen",
    "sg:classifiers":[
        {
            "category":"Personal",
            "subcategory":"Beauty Salon",
            "type":"Services"
        }
    ],
    "sg:phone":"+1 956 683 1669",
    "sg:postcode":"78501",
    "sg:province":"TX",
    "wof:name":"Angela Beauty Salon",
    "wof:placetype":"venue"
},
  "geometry": {"coordinates":[-98.23710699999999,26.201753],"type":"Point"}
}