{
  "type": "Feature",
  "properties": {
    "iso:country":"US",
    "sg:address":"12600 Silver Spr",
    "sg:city":"Austin",
    "sg:classifiers":[
        {
            "category":"Professional",
            "subcategory":"Management & Consulting",
            "type":"Services"
        }
    ],
    "sg:phone":"+1 512 627 8700",
    "sg:postcode":"78727",
    "sg:province":"TX",
    "sg:tags":[
        "business"
    ],
    "wof:name":"Jci World Corporation",
    "wof:placetype":"venue"
},
  "geometry": {"coordinates":[-97.699349,30.417484],"type":"Point"}
}