{
  "type": "Feature",
  "properties": {
    "iso:country":"US",
    "sg:address":"3724 Race St",
    "sg:city":"Dallas",
    "sg:classifiers":[
        {
            "category":"Wholesale",
            "subcategory":"Machinery & Supplies",
            "type":"Manufacturing & Wholesale Goods"
        }
    ],
    "sg:phone":"+1 214 826 2610",
    "sg:postcode":"75246",
    "sg:province":"TX",
    "sg:tags":[
        "water",
        "head",
        "sprinkler",
        "mfg"
    ],
    "wof:name":"Riggs Irrigation Supply",
    "wof:placetype":"venue"
},
  "geometry": {"coordinates":[-96.77589399999999,32.786664],"type":"Point"}
}