{
  "type": "Feature",
  "properties": {
    "iso:country":"US",
    "sg:address":"8215 Joliet Ave",
    "sg:city":"Lubbock",
    "sg:classifiers":[
        {
            "category":"Organizations",
            "subcategory":"Religious Organization",
            "type":"Services"
        }
    ],
    "sg:phone":"+1 806 796 2060",
    "sg:postcode":"79423",
    "sg:province":"TX",
    "sg:tags":[
        "church"
    ],
    "wof:name":"Daybreak Community Svc",
    "wof:placetype":"venue"
},
  "geometry": {"coordinates":[-101.890708,33.51806],"type":"Point"}
}