{
  "type": "Feature",
  "properties": {
    "iso:country":"US",
    "sg:address":"120 E San Patricio Ave",
    "sg:city":"Mathis",
    "sg:classifiers":[
        {
            "category":"Insurance",
            "subcategory":"Insurance Agent",
            "type":"Services"
        }
    ],
    "sg:phone":"+1 361 247 3228",
    "sg:postcode":"78368",
    "sg:province":"TX",
    "wof:name":"Keetch & Assoc Insurance",
    "wof:placetype":"venue"
},
  "geometry": {"coordinates":[-97.827849,28.093858],"type":"Point"}
}