{
  "type": "Feature",
  "properties": {
    "iso:country":"US",
    "sg:address":"2601 Starks Ave",
    "sg:city":"Dallas",
    "sg:classifiers":[
        {
            "category":"Organizations",
            "subcategory":"Religious Organization",
            "type":"Services"
        }
    ],
    "sg:phone":"+1 214 421 2623",
    "sg:postcode":"75215",
    "sg:province":"TX",
    "sg:tags":[
        "church"
    ],
    "wof:name":"New Galilee Baptist Church",
    "wof:placetype":"venue"
},
  "geometry": {"coordinates":[-96.748369,32.749936],"type":"Point"}
}