{
  "type": "Feature",
  "properties": {
    "iso:country":"US",
    "sg:address":"103 N 7th St",
    "sg:city":"Corsicana",
    "sg:classifiers":[
        {
            "category":"Wholesale",
            "subcategory":"Hardware",
            "type":"Manufacturing & Wholesale Goods"
        }
    ],
    "sg:phone":"+1 903 874 3743",
    "sg:postcode":"75110",
    "sg:province":"TX",
    "sg:tags":[
        "plumbing",
        "fixture",
        "supply"
    ],
    "wof:name":"Corsicana Winnelson Co",
    "wof:placetype":"venue"
},
  "geometry": {"coordinates":[-96.46078,32.096183],"type":"Point"}
}