{
  "type": "Feature",
  "properties": {
    "iso:country":"US",
    "sg:address":"1329 Rusk Dr",
    "sg:city":"Richardson",
    "sg:classifiers":[
        {
            "category":"Travel",
            "subcategory":"Travel Agent",
            "type":"Entertainment"
        }
    ],
    "sg:phone":"+1 972 234 4301",
    "sg:postcode":"75081",
    "sg:province":"TX",
    "sg:tags":[
        "agency"
    ],
    "wof:name":"Dannis & Dannis Inc",
    "wof:placetype":"venue"
},
  "geometry": {"coordinates":[-96.70150599999999,32.939677],"type":"Point"}
}