{
  "type": "Feature",
  "properties": {
    "iso:country":"US",
    "sg:address":"1807 Gallagher St",
    "sg:city":"Dallas",
    "sg:classifiers":[
        {
            "category":"Professional",
            "type":"Services"
        }
    ],
    "sg:phone":"+1 214 744 0952",
    "sg:postcode":"75212",
    "sg:province":"TX",
    "wof:name":"Vicki Snyder",
    "wof:placetype":"venue"
},
  "geometry": {"coordinates":[-96.85017499999999,32.784866],"type":"Point"}
}