{
  "type": "Feature",
  "properties": {
    "iso:country":"US",
    "sg:address":"1615 Rutherford Ln",
    "sg:city":"Austin",
    "sg:classifiers":[
        {
            "category":"Recreation",
            "type":"Entertainment"
        }
    ],
    "sg:phone":"+1 512 997 7275",
    "sg:postcode":"78754",
    "sg:province":"TX",
    "sg:tags":[
        "skateboard",
        "parks",
        "rink"
    ],
    "wof:name":"Motive Skate Shop",
    "wof:placetype":"venue"
},
  "geometry": {"coordinates":[-97.683032,30.337253],"type":"Point"}
}