{
  "type": "Feature",
  "properties": {
    "iso:country":"US",
    "sg:address":"3201 Chimneyrock Dr",
    "sg:city":"Plano",
    "sg:classifiers":[
        {
            "category":"Professional",
            "subcategory":"Employment Agencies",
            "type":"Services"
        }
    ],
    "sg:phone":"+1 972 519 0863",
    "sg:postcode":"75023",
    "sg:province":"TX",
    "sg:tags":[
        "consultant",
        "search",
        "executive"
    ],
    "wof:name":"United Search Assoc",
    "wof:placetype":"venue"
},
  "geometry": {"coordinates":[-96.752793,33.050407],"type":"Point"}
}