{
  "type": "Feature",
  "properties": {
    "iso:country":"US",
    "sg:address":"319 N Ballard St",
    "sg:city":"Pampa",
    "sg:classifiers":[
        {
            "category":"Manufacturing",
            "subcategory":"Printing",
            "type":"Manufacturing & Wholesale Goods"
        }
    ],
    "sg:phone":"+1 806 669 7941",
    "sg:postcode":"79065",
    "sg:province":"TX",
    "sg:tags":[
        "commercial"
    ],
    "wof:name":"Texas Printing Co",
    "wof:placetype":"venue"
},
  "geometry": {"coordinates":[-100.962188,35.538957],"type":"Point"}
}