{
  "type": "Feature",
  "properties": {
    "iso:country":"US",
    "sg:address":"10313 Noel Dr",
    "sg:city":"Frisco",
    "sg:classifiers":[
        {
            "category":"Home & Garden",
            "subcategory":"Building Materials",
            "type":"Retail Goods"
        }
    ],
    "sg:phone":"+1 469 853 0113",
    "sg:postcode":"75035",
    "sg:province":"TX",
    "sg:tags":[
        "door"
    ],
    "wof:name":"Your Choice Garage Door Svc",
    "wof:placetype":"venue"
},
  "geometry": {"coordinates":[-96.790002,33.119201],"type":"Point"}
}