{
  "type": "Feature",
  "properties": {
    "iso:country":"US",
    "sg:address":"800 N Rooney St",
    "sg:city":"Fort Stockton",
    "sg:classifiers":[
        {
            "category":"Retail",
            "subcategory":"Auto Repair",
            "type":"Services"
        }
    ],
    "sg:phone":"+1 432 336 3632",
    "sg:postcode":"79735",
    "sg:province":"TX",
    "sg:tags":[
        "repairing",
        "automobile",
        "general"
    ],
    "wof:name":"Rainwater Motor Co Inc",
    "wof:placetype":"venue"
},
  "geometry": {"coordinates":[-102.876918,30.89303],"type":"Point"}
}