{
  "type": "Feature",
  "properties": {
    "iso:country":"US",
    "sg:address":"2801 Princeton Pl",
    "sg:city":"Plano",
    "sg:classifiers":[
        {
            "category":"Professional",
            "subcategory":"Business Services",
            "type":"Services"
        }
    ],
    "sg:phone":"+1 972 985 8813",
    "sg:postcode":"75075",
    "sg:province":"TX",
    "wof:name":"Behjat Interiors",
    "wof:placetype":"venue"
},
  "geometry": {"coordinates":[-96.749686,33.010613],"type":"Point"}
}