{
  "type": "Feature",
  "properties": {
    "iso:country":"US",
    "sg:address":"2913 Canton St",
    "sg:city":"Dallas",
    "sg:classifiers":[
        {
            "category":"Professional",
            "subcategory":"Art Services",
            "type":"Services"
        }
    ],
    "sg:phone":"+1 214 939 9194",
    "sg:postcode":"75226",
    "sg:province":"TX",
    "sg:tags":[
        "agency",
        "commercial",
        "advertising",
        "graphics"
    ],
    "wof:name":"Squires & Company",
    "wof:placetype":"venue"
},
  "geometry": {"coordinates":[-96.780299,32.782836],"type":"Point"}
}