{
  "type": "Feature",
  "properties": {
    "iso:country":"US",
    "sg:address":"227 Brazos St",
    "sg:city":"Garland",
    "sg:classifiers":[
        {
            "category":"Professional",
            "type":"Services"
        }
    ],
    "sg:phone":"+1 972 271 4171",
    "sg:postcode":"75041",
    "sg:province":"TX",
    "sg:tags":[
        "establishment"
    ],
    "wof:name":"KBW Systems",
    "wof:placetype":"venue"
},
  "geometry": {"coordinates":[-96.628632,32.877004],"type":"Point"}
}