{
  "type": "Feature",
  "properties": {
    "iso:country":"US",
    "sg:address":"5520 Lyndon B Johnson Fwy",
    "sg:city":"Dallas",
    "sg:classifiers":[
        {
            "category":"Professional",
            "subcategory":"Research",
            "type":"Services"
        }
    ],
    "sg:phone":"+1 972 404 4001",
    "sg:postcode":"75240",
    "sg:province":"TX",
    "sg:tags":[
        "organization",
        "noncommercial"
    ],
    "wof:name":"George & Fay Young Foundation",
    "wof:placetype":"venue"
},
  "geometry": {"coordinates":[-96.816131,32.925481],"type":"Point"}
}