{
  "type": "Feature",
  "properties": {
    "iso:country":"US",
    "sg:address":"10403 Cullen Blvd",
    "sg:city":"Houston",
    "sg:classifiers":[
        {
            "category":"Food & Beverages",
            "subcategory":"Groceries & Convenience Stores",
            "type":"Retail Goods"
        }
    ],
    "sg:phone":"+1 713 734 2096",
    "sg:postcode":"77047",
    "sg:province":"TX",
    "wof:name":"New Standard Food Market",
    "wof:placetype":"venue"
},
  "geometry": {"coordinates":[-95.355904,29.6462],"type":"Point"}
}