{
  "type": "Feature",
  "properties": {
    "iso:country":"US",
    "sg:address":"223 E Dicker Dr",
    "sg:city":"Pharr",
    "sg:classifiers":[
        {
            "category":"Restaurant",
            "type":"Food & Drink"
        }
    ],
    "sg:phone":"+1 956 781 0859",
    "sg:postcode":"78577",
    "sg:province":"TX",
    "wof:name":"Hiucho's Restaurant",
    "wof:placetype":"venue"
},
  "geometry": {"coordinates":[-98.189813,26.122488],"type":"Point"}
}