{
  "type": "Feature",
  "properties": {
    "iso:country":"US",
    "sg:address":"2950 Springer Rd",
    "sg:city":"Midlothian",
    "sg:classifiers":[
        {
            "category":"Building & Trades",
            "subcategory":"Landscaping Services",
            "type":"Services"
        }
    ],
    "sg:phone":"+1 972 723 1313",
    "sg:postcode":"76065",
    "sg:province":"TX",
    "wof:name":"Texas Lawns & Landscapes Inc",
    "wof:placetype":"venue"
},
  "geometry": {"coordinates":[-96.908694,32.513283],"type":"Point"}
}