{
  "type": "Feature",
  "properties": {
    "iso:country":"US",
    "sg:address":"3617 Kim Dr",
    "sg:city":"Irving",
    "sg:classifiers":[
        {
            "category":"Utilities",
            "subcategory":"Water",
            "type":"Services"
        }
    ],
    "sg:phone":"+1 972 871 8500",
    "sg:postcode":"75061",
    "sg:province":"TX",
    "sg:tags":[
        "dealer"
    ],
    "wof:name":"Munsterman Chance",
    "wof:placetype":"venue"
},
  "geometry": {"coordinates":[-96.99478000000001,32.820368],"type":"Point"}
}