{
  "type": "Feature",
  "properties": {
    "iso:country":"US",
    "sg:address":"1019 12th St",
    "sg:city":"Huntsville",
    "sg:classifiers":[
        {
            "category":"Professional",
            "subcategory":"Management & Consulting",
            "type":"Services"
        }
    ],
    "sg:phone":"+1 936 293 1451",
    "sg:postcode":"77340",
    "sg:province":"TX",
    "sg:tags":[
        "consultant"
    ],
    "wof:name":"Cleveland Consulting",
    "wof:placetype":"venue"
},
  "geometry": {"coordinates":[-95.550184,30.722901],"type":"Point"}
}