{
  "type": "Feature",
  "properties": {
    "iso:country":"US",
    "sg:address":"7135 W Tidwell Rd Ste 117",
    "sg:city":"Houston",
    "sg:classifiers":[
        {
            "category":"Professional",
            "subcategory":"Employment Agencies",
            "type":"Services"
        }
    ],
    "sg:phone":"+1 713 869 9900",
    "sg:postcode":"77092",
    "sg:province":"TX",
    "wof:name":"Instatech Corp",
    "wof:placetype":"venue"
},
  "geometry": {"coordinates":[-95.49717,29.850532],"type":"Point"}
}