{
  "type": "Feature",
  "properties": {
    "iso:country":"US",
    "sg:address":"700 W Mulberry St",
    "sg:city":"Angleton",
    "sg:classifiers":[
        {
            "category":"Professional",
            "type":"Services"
        }
    ],
    "sg:phone":"+1 281 581 2330",
    "sg:postcode":"77515",
    "sg:province":"TX",
    "sg:tags":[
        "establishment"
    ],
    "wof:name":"D & H Farm Equipment",
    "wof:placetype":"venue"
},
  "geometry": {"coordinates":[-95.44074999999999,29.163954],"type":"Point"}
}