{
  "type": "Feature",
  "properties": {
    "iso:country":"US",
    "sg:address":"10735 W Little York Rd",
    "sg:city":"Houston",
    "sg:classifiers":[
        {
            "category":"Manufacturing",
            "subcategory":"Retail Goods",
            "type":"Manufacturing & Wholesale Goods"
        }
    ],
    "sg:phone":"+1 713 983 6070",
    "sg:postcode":"77041",
    "sg:province":"TX",
    "sg:tags":[
        "assembly",
        "fabricating"
    ],
    "sg:website":"www.cvlogistics.com",
    "wof:name":"C V Logistics Inc",
    "wof:placetype":"venue"
},
  "geometry": {"coordinates":[-95.565596,29.867171],"type":"Point"}
}