{
  "type": "Feature",
  "properties": {
    "iso:country":"US",
    "sg:address":"5501 Jacksboro Hwy",
    "sg:city":"Fort Worth",
    "sg:classifiers":[
        {
            "category":"Shopping",
            "subcategory":"Tobacco",
            "type":"Retail Goods"
        }
    ],
    "sg:phone":"+1 817 624 1676",
    "sg:postcode":"76114",
    "sg:province":"TX",
    "sg:tags":[
        "product"
    ],
    "wof:name":"Smoke Rings",
    "wof:placetype":"venue"
},
  "geometry": {"coordinates":[-97.405366,32.798964],"type":"Point"}
}