{
  "type": "Feature",
  "properties": {
    "iso:country":"US",
    "sg:address":"5602 I- 37",
    "sg:city":"Corpus Christi",
    "sg:classifiers":[
        {
            "category":"Professional",
            "subcategory":"Business Services",
            "type":"Services"
        }
    ],
    "sg:phone":"+1 361 289 1138",
    "sg:postcode":"78407",
    "sg:province":"TX",
    "sg:tags":[
        "inspection"
    ],
    "wof:name":"All Tech Inspection",
    "wof:placetype":"venue"
},
  "geometry": {"coordinates":[-97.46363100000001,27.804636],"type":"Point"}
}