{
  "type": "Feature",
  "properties": {
    "iso:country":"US",
    "sg:address":"714 Profit Dr",
    "sg:city":"Garland",
    "sg:classifiers":[
        {
            "category":"Home & Garden",
            "subcategory":"Building Materials",
            "type":"Retail Goods"
        },
        {
            "category":"Building & Trades",
            "subcategory":"Construction",
            "type":"Services"
        }
    ],
    "sg:phone":"+1 972 276 6672",
    "sg:postcode":"75040",
    "sg:province":"TX",
    "sg:tags":[
        "plate",
        "window",
        "contractor",
        "glass",
        "nonresidential"
    ],
    "wof:name":"A-1 Glass",
    "wof:placetype":"venue"
},
  "geometry": {"coordinates":[-96.630717,32.918898],"type":"Point"}
}