{
  "type": "Feature",
  "properties": {
    "iso:country":"US",
    "sg:address":"8852 Colberg Dr",
    "sg:city":"Austin",
    "sg:classifiers":[
        {
            "category":"Wholesale",
            "subcategory":"Non-durable Goods",
            "type":"Manufacturing & Wholesale Goods"
        }
    ],
    "sg:phone":"+1 512 990 3311",
    "sg:postcode":"78749",
    "sg:province":"TX",
    "wof:name":"Esscentials",
    "wof:placetype":"venue"
},
  "geometry": {"coordinates":[-97.887685,30.215945],"type":"Point"}
}