{
  "type": "Feature",
  "properties": {
    "iso:country":"US",
    "sg:address":"1402 Mineral Wells Hwy",
    "sg:city":"Weatherford",
    "sg:classifiers":[
        {
            "category":"Retail",
            "subcategory":"Auto Repair",
            "type":"Services"
        }
    ],
    "sg:phone":"+1 817 594 7158",
    "sg:postcode":"76086",
    "sg:province":"TX",
    "sg:tags":[
        "general"
    ],
    "wof:name":"Birdwell Lube & Automotive",
    "wof:placetype":"venue"
},
  "geometry": {"coordinates":[-97.820123,32.759611],"type":"Point"}
}