{
  "type": "Feature",
  "properties": {
    "iso:country":"US",
    "sg:address":"16002 Kitzman Rd",
    "sg:city":"Cypress",
    "sg:classifiers":[
        {
            "category":"Building & Trades",
            "subcategory":"Construction",
            "type":"Services"
        }
    ],
    "sg:phone":"+1 281 351 5344",
    "sg:postcode":"77429",
    "sg:province":"TX",
    "sg:tags":[
        "control",
        "corrosion"
    ],
    "wof:name":"Kennedy Coating Inspection Svc",
    "wof:placetype":"venue"
},
  "geometry": {"coordinates":[-95.65967499999999,30.038118],"type":"Point"}
}