{
  "type": "Feature",
  "properties": {
    "iso:country":"US",
    "sg:address":"13851 Brannon Field Ln",
    "sg:city":"Houston",
    "sg:classifiers":[
        {
            "category":"Professional",
            "subcategory":"Computer Services",
            "type":"Services"
        }
    ],
    "sg:phone":"+1 281 970 4704",
    "sg:postcode":"77041",
    "sg:province":"TX",
    "sg:tags":[
        "related"
    ],
    "wof:name":"Amsden Enterprises",
    "wof:placetype":"venue"
},
  "geometry": {"coordinates":[-95.619184,29.895383],"type":"Point"}
}