{
  "type": "Feature",
  "properties": {
    "iso:country":"US",
    "sg:address":"4621 Montrose Blvd Suite B240",
    "sg:city":"Houston",
    "sg:classifiers":[
        {
            "category":"Professional",
            "subcategory":"Computer Services",
            "type":"Services"
        }
    ],
    "sg:phone":"+1 713 370 6420",
    "sg:postcode":"77006",
    "sg:province":"TX",
    "sg:tags":[
        "apps",
        "iphone-app",
        "mobile-app",
        "android",
        "android-app",
        "smartphone"
    ],
    "sg:website":"http://www.stratopy.com",
    "wof:name":"Stratopy",
    "wof:placetype":"venue"
},
  "geometry": {"coordinates":[-95.390997,29.73072],"type":"Point"}
}