{
  "type": "Feature",
  "properties": {
    "iso:country":"US",
    "sg:address":"14455 River Rd",
    "sg:city":"New Braunfels",
    "sg:classifiers":[
        {
            "category":"Retail",
            "subcategory":"Animal Services",
            "type":"Services"
        }
    ],
    "sg:phone":"+1 830 964 3647",
    "sg:postcode":"78132",
    "sg:province":"TX",
    "wof:name":"Doggone Grooming",
    "wof:placetype":"venue"
},
  "geometry": {"coordinates":[-98.17364600000001,29.847985],"type":"Point"}
}