{
  "type": "Feature",
  "properties": {
    "iso:country":"US",
    "sg:address":"10214 Sagegate Dr",
    "sg:city":"Houston",
    "sg:classifiers":[
        {
            "category":"Building & Trades",
            "subcategory":"Landscaping Services",
            "type":"Services"
        }
    ],
    "sg:phone":"+1 281 484 0067",
    "sg:postcode":"77089",
    "sg:province":"TX",
    "sg:tags":[
        "landscape"
    ],
    "wof:name":"A&K Tractor Works",
    "wof:placetype":"venue"
},
  "geometry": {"coordinates":[-95.226268,29.579422],"type":"Point"}
}