{
  "type": "Feature",
  "properties": {
    "iso:country":"US",
    "sg:address":"11660 Westheimer Rd",
    "sg:city":"Houston",
    "sg:classifiers":[
        {
            "category":"Shopping",
            "subcategory":"Computers & Home Electronics",
            "type":"Retail Goods"
        }
    ],
    "sg:phone":"+1 281 531 5893",
    "sg:postcode":"77077",
    "sg:province":"TX",
    "sg:tags":[
        "game",
        "video"
    ],
    "wof:name":"EB Games",
    "wof:placetype":"venue"
},
  "geometry": {"coordinates":[-95.583445,29.736548],"type":"Point"}
}