{
  "type": "Feature",
  "properties": {
    "iso:country":"US",
    "sg:address":"2368 Autumn Mist Ct",
    "sg:city":"League City",
    "sg:classifiers":[
        {
            "category":"Health Services",
            "subcategory":"Doctor",
            "type":"Services"
        }
    ],
    "sg:phone":"+1 281 538 0764",
    "sg:postcode":"77573",
    "sg:province":"TX",
    "sg:tags":[
        "medical"
    ],
    "wof:name":"Michael S Sieling MD PA",
    "wof:placetype":"venue"
},
  "geometry": {"coordinates":[-95.071341,29.537816],"type":"Point"}
}