{
  "type": "Feature",
  "properties": {
    "iso:country":"US",
    "sg:address":"705 W Commerce St",
    "sg:city":"Brownwood",
    "sg:classifiers":[
        {
            "category":"Shopping",
            "subcategory":"Used Merchandise",
            "type":"Retail Goods"
        }
    ],
    "sg:phone":"+1 325 641 0335",
    "sg:postcode":"76801",
    "sg:province":"TX",
    "wof:name":"Ricochet Oldies & Antiques",
    "wof:placetype":"venue"
},
  "geometry": {"coordinates":[-98.992468,31.729761],"type":"Point"}
}