{
  "type": "Feature",
  "properties": {
    "iso:country":"US",
    "sg:address":"28317 FM 2978",
    "sg:city":"Magnolia",
    "sg:classifiers":[
        {
            "category":"Wholesale",
            "subcategory":"Non-durable Goods",
            "type":"Manufacturing & Wholesale Goods"
        }
    ],
    "sg:phone":"+1 281 252 5441",
    "sg:postcode":"77354",
    "sg:province":"TX",
    "sg:tags":[
        "adhesive",
        "industrial",
        "mfg",
        "rep",
        "system",
        "packaging",
        "ink"
    ],
    "wof:name":"R & R Packaging Systems Inc",
    "wof:placetype":"venue"
},
  "geometry": {"coordinates":[-95.599537,30.171698],"type":"Point"}
}