{
  "type": "Feature",
  "properties": {
    "iso:country":"US",
    "sg:address":"1018 Sir Lancelot Cir",
    "sg:city":"Lewisville",
    "sg:classifiers":[
        {
            "category":"Banks & Credit Unions",
            "subcategory":"Bank",
            "type":"Services"
        }
    ],
    "sg:phone":"+1 972 899 0026",
    "sg:postcode":"75010",
    "sg:province":"TX",
    "sg:tags":[
        "loan",
        "real estate"
    ],
    "wof:name":"Oak Tree Mortgage",
    "wof:placetype":"venue"
},
  "geometry": {"coordinates":[-96.88767900000001,33.033968],"type":"Point"}
}