{
  "type": "Feature",
  "properties": {
    "iso:country":"US",
    "sg:address":"526 Saint Paul St",
    "sg:city":"Gonzales",
    "sg:classifiers":[
        {
            "category":"Wholesale",
            "subcategory":"Hardware",
            "type":"Manufacturing & Wholesale Goods"
        },
        {
            "category":"Home & Garden",
            "subcategory":"Garden Supply",
            "type":"Retail Goods"
        },
        {
            "category":"Retail",
            "subcategory":"Repair Shop",
            "type":"Services"
        }
    ],
    "sg:phone":"+1 830 672 6415",
    "sg:postcode":"78629",
    "sg:province":"TX",
    "sg:tags":[
        "renting",
        "lawn",
        "outdoor",
        "power",
        "landscaping",
        "equipment-sales",
        "equipment",
        "saw"
    ],
    "sg:website":"http://www.stihlusa.com/",
    "wof:name":"A-Line Auto Parts",
    "wof:placetype":"venue"
},
  "geometry": {"coordinates":[-97.45169199999999,29.502112],"type":"Point"}
}