{
  "type": "Feature",
  "properties": {
    "iso:country":"US",
    "sg:address":"6050 Hudnall Rd",
    "sg:city":"Orange",
    "sg:classifiers":[
        {
            "category":"Farming",
            "subcategory":"Farm",
            "type":"Manufacturing & Wholesale Goods"
        }
    ],
    "sg:phone":"+1 409 746 9331",
    "sg:postcode":"77632",
    "sg:province":"TX",
    "wof:name":"James D Sears",
    "wof:placetype":"venue"
},
  "geometry": {"coordinates":[-93.796001,30.20727],"type":"Point"}
}