{
  "type": "Feature",
  "properties": {
    "iso:country":"US",
    "sg:address":"5324 Gaston Ave",
    "sg:city":"Dallas",
    "sg:classifiers":[
        {
            "category":"Professional",
            "subcategory":"Management & Consulting",
            "type":"Services"
        }
    ],
    "sg:phone":"+1 214 219 1902",
    "sg:postcode":"75214",
    "sg:province":"TX",
    "sg:tags":[
        "business"
    ],
    "wof:name":"Gawel Drue",
    "wof:placetype":"venue"
},
  "geometry": {"coordinates":[-96.765168,32.803365],"type":"Point"}
}