{
  "type": "Feature",
  "properties": {
    "iso:country":"US",
    "sg:address":"2817 Wheeling Ave",
    "sg:city":"El Paso",
    "sg:classifiers":[
        {
            "category":"Manufacturing",
            "subcategory":"Printing",
            "type":"Manufacturing & Wholesale Goods"
        }
    ],
    "sg:phone":"+1 915 566 6588",
    "sg:postcode":"79930",
    "sg:province":"TX",
    "sg:tags":[
        "periodical"
    ],
    "wof:name":"Rock On Magazine",
    "wof:placetype":"venue"
},
  "geometry": {"coordinates":[-106.461484,31.792102],"type":"Point"}
}