{
  "type": "Feature",
  "properties": {
    "iso:country":"US",
    "sg:address":"6110 Desert Sun St",
    "sg:city":"San Antonio",
    "sg:classifiers":[
        {
            "category":"Arts & Performance",
            "subcategory":"Theater",
            "type":"Entertainment"
        }
    ],
    "sg:phone":"+1 210 509 6197",
    "sg:postcode":"78238",
    "sg:province":"TX",
    "sg:tags":[
        "group"
    ],
    "wof:name":"Gmg Enterprises",
    "wof:placetype":"venue"
},
  "geometry": {"coordinates":[-98.60872500000001,29.495463],"type":"Point"}
}