{
  "type": "Feature",
  "properties": {
    "iso:country":"US",
    "sg:address":"3159 S Garland Ave",
    "sg:city":"Garland",
    "sg:classifiers":[
        {
            "category":"Health Services",
            "subcategory":"Optometrist",
            "type":"Services"
        }
    ],
    "sg:phone":"+1 972 840 1776",
    "sg:postcode":"75041",
    "sg:province":"TX",
    "wof:name":"Elliot Jerry Dr Optmtrst",
    "wof:placetype":"venue"
},
  "geometry": {"coordinates":[-96.66130099999999,32.877499],"type":"Point"}
}