{
  "type": "Feature",
  "properties": {
    "iso:country":"US",
    "sg:address":"1621 Ringgold St",
    "sg:city":"Brownsville",
    "sg:classifiers":[
        {
            "category":"Building & Trades",
            "subcategory":"Construction",
            "type":"Services"
        }
    ],
    "sg:phone":"+1 956 546 3593",
    "sg:postcode":"78520",
    "sg:province":"TX",
    "sg:tags":[
        "contractor",
        "fence-sales"
    ],
    "wof:name":"Palm Valley Fence",
    "wof:placetype":"venue"
},
  "geometry": {"coordinates":[-97.486594,25.905446],"type":"Point"}
}