{
  "type": "Feature",
  "properties": {
    "iso:country":"US",
    "sg:address":"1309 Main St",
    "sg:city":"Dallas",
    "sg:classifiers":[
        {
            "category":"Real Estate",
            "subcategory":"Real Estate Services",
            "type":"Services"
        }
    ],
    "sg:phone":"+1 214 741 1309",
    "sg:postcode":"75202",
    "sg:province":"TX",
    "sg:tags":[
        "management",
        "property"
    ],
    "sg:website":"www.trigonmanagement.com",
    "wof:name":"Trigon Management",
    "wof:placetype":"venue"
},
  "geometry": {"coordinates":[-96.80089700000001,32.780407],"type":"Point"}
}