{
  "type": "Feature",
  "properties": {
    "iso:country":"US",
    "sg:address":"9009 Mountain Ridge Dr Ste 240",
    "sg:city":"Austin",
    "sg:classifiers":[
        {
            "category":"Utilities",
            "subcategory":"Electric",
            "type":"Services"
        },
        {
            "category":"Bus Station",
            "type":"Transportation"
        }
    ],
    "sg:phone":"+1 512 418 9924",
    "sg:postcode":"78759",
    "sg:province":"TX",
    "sg:tags":[
        "systems-uninterruptible",
        "electronic",
        "power",
        "supply"
    ],
    "wof:name":"Astec America Inc.",
    "wof:placetype":"venue"
},
  "geometry": {"coordinates":[-97.75391999999999,30.38664],"type":"Point"}
}