{
  "type": "Feature",
  "properties": {
    "iso:country":"US",
    "sg:address":"3644 State Hwy 6",
    "sg:city":"Sugar Land",
    "sg:classifiers":[
        {
            "category":"Professional",
            "subcategory":"Business Services",
            "type":"Services"
        }
    ],
    "sg:phone":"+1 281 242 3336",
    "sg:postcode":"77478",
    "sg:province":"TX",
    "sg:tags":[
        "interior",
        "designer",
        "commercial",
        "christmas",
        "decorator"
    ],
    "wof:name":"Design Source",
    "wof:placetype":"venue"
},
  "geometry": {"coordinates":[-95.59804,29.589471],"type":"Point"}
}