{
  "type": "Feature",
  "properties": {
    "iso:country":"US",
    "sg:address":"9206 Quail Meadow Dr",
    "sg:city":"Austin",
    "sg:classifiers":[
        {
            "category":"Building & Trades",
            "subcategory":"Landscaping Services",
            "type":"Services"
        }
    ],
    "sg:phone":"+1 512 339 7262",
    "sg:postcode":"78758",
    "sg:province":"TX",
    "wof:name":"Bill Gusman Lawn Service",
    "wof:placetype":"venue"
},
  "geometry": {"coordinates":[-97.70836199999999,30.368014],"type":"Point"}
}