{
  "type": "Feature",
  "properties": {
    "iso:country":"US",
    "sg:address":"3730 N Josey Ln Ste 122",
    "sg:city":"Carrollton",
    "sg:classifiers":[
        {
            "category":"Health Services",
            "subcategory":"Doctor",
            "type":"Services"
        },
        {
            "category":"Health Services",
            "subcategory":"Chiropractor",
            "type":"Services"
        }
    ],
    "sg:phone":"+1 972 416 2000",
    "sg:postcode":"75007",
    "sg:province":"TX",
    "sg:tags":[
        "medicine",
        "sport"
    ],
    "sg:website":"www.manfrechiro.com",
    "wof:name":"Manfre Chiropractic Office",
    "wof:placetype":"venue"
},
  "geometry": {"coordinates":[-96.88690800000001,33.01337],"type":"Point"}
}