{
  "type": "Feature",
  "properties": {
    "iso:country":"US",
    "sg:address":"105 Argyle",
    "sg:city":"Marshall",
    "sg:classifiers":[
        {
            "category":"Health Services",
            "subcategory":"Doctor",
            "type":"Services"
        }
    ],
    "sg:phone":"+1 903 927 1500",
    "sg:postcode":"75670",
    "sg:province":"TX",
    "wof:name":"Mark Neel DDS",
    "wof:placetype":"venue"
},
  "geometry": {"coordinates":[-94.368596,32.537969],"type":"Point"}
}