{
  "type": "Feature",
  "properties": {
    "iso:country":"US",
    "sg:address":"2621 Woodlawn Dr",
    "sg:city":"San Angelo",
    "sg:classifiers":[
        {
            "category":"Building & Trades",
            "subcategory":"Cleaning & Sanitation",
            "type":"Services"
        }
    ],
    "sg:phone":"+1 325 944 0321",
    "sg:postcode":"76901",
    "sg:province":"TX",
    "sg:tags":[
        "janitor"
    ],
    "wof:name":"Tidy Team Cleaning Svc",
    "wof:placetype":"venue"
},
  "geometry": {"coordinates":[-100.47756,31.46213],"type":"Point"}
}