{
  "type": "Feature",
  "properties": {
    "iso:country":"US",
    "sg:address":"6907 Winterberry Dr",
    "sg:city":"Austin",
    "sg:classifiers":[
        {
            "category":"Real Estate",
            "subcategory":"Developer",
            "type":"Services"
        }
    ],
    "sg:phone":"+1 512 345 5363",
    "sg:postcode":"78750",
    "sg:province":"TX",
    "wof:name":"Smith Sage Development Inc",
    "wof:placetype":"venue"
},
  "geometry": {"coordinates":[-97.79807099999999,30.3752],"type":"Point"}
}