{
  "type": "Feature",
  "properties": {
    "iso:country":"US",
    "sg:address":"806 E 3rd St",
    "sg:city":"Big Spring",
    "sg:classifiers":[
        {
            "category":"Restaurant",
            "type":"Food & Drink"
        }
    ],
    "sg:phone":"+1 432 264 0674",
    "sg:postcode":"79720",
    "sg:province":"TX",
    "sg:tags":[
        "eating"
    ],
    "wof:name":"LL Concession",
    "wof:placetype":"venue"
},
  "geometry": {"coordinates":[-101.467951,32.255964],"type":"Point"}
}