{
  "type": "Feature",
  "properties": {
    "iso:country":"US",
    "sg:address":"7001 Westwind Dr",
    "sg:city":"El Paso",
    "sg:classifiers":[
        {
            "category":"Social Services",
            "type":"Services"
        }
    ],
    "sg:phone":"+1 915 833 8719",
    "sg:postcode":"79912",
    "sg:province":"TX",
    "sg:tags":[
        "counselor",
        "marriage",
        "family"
    ],
    "wof:name":"Alma Altamirano LPC",
    "wof:placetype":"venue"
},
  "geometry": {"coordinates":[-106.54188600000001,31.853347],"type":"Point"}
}