{
  "type": "Feature",
  "properties": {
    "iso:country":"US",
    "sg:address":"407 E 6th St",
    "sg:city":"Austin",
    "sg:classifiers":[
        {
            "category":"Professional",
            "subcategory":"Business Services",
            "type":"Services"
        }
    ],
    "sg:phone":"+1 512 236 0140",
    "sg:postcode":"78701",
    "sg:province":"TX",
    "sg:tags":[
        "recording",
        "studio"
    ],
    "wof:name":"Suitcase Studios",
    "wof:placetype":"venue"
},
  "geometry": {"coordinates":[-97.738247,30.266782],"type":"Point"}
}