{
  "type": "Feature",
  "properties": {
    "iso:country":"US",
    "sg:address":"2905 Milam St",
    "sg:city":"Houston",
    "sg:classifiers":[
        {
            "category":"Health Services",
            "subcategory":"Doctor",
            "type":"Services"
        }
    ],
    "sg:phone":"+1 713 529 5659",
    "sg:postcode":"77006",
    "sg:province":"TX",
    "sg:tags":[
        "physician",
        "surgeon"
    ],
    "wof:name":"Phung Nguyen MD",
    "wof:placetype":"venue"
},
  "geometry": {"coordinates":[-95.377403,29.744301],"type":"Point"}
}