{
  "type": "Feature",
  "properties": {
    "iso:country":"US",
    "sg:address":"2429 N Fry Rd",
    "sg:city":"Katy",
    "sg:classifiers":[
        {
            "category":"Personal",
            "subcategory":"Beauty Salon",
            "type":"Services"
        }
    ],
    "sg:phone":"+1 281 578 2228",
    "sg:postcode":"77449",
    "sg:province":"TX",
    "sg:tags":[
        "hair"
    ],
    "wof:name":"Sophisti Cuts",
    "wof:placetype":"venue"
},
  "geometry": {"coordinates":[-95.71935000000001,29.802367],"type":"Point"}
}