{
  "type": "Feature",
  "properties": {
    "iso:country":"US",
    "sg:address":"6209 S Fawnlake Dr",
    "sg:city":"Katy",
    "sg:classifiers":[
        {
            "category":"Wholesale",
            "subcategory":"Machinery & Supplies",
            "type":"Manufacturing & Wholesale Goods"
        }
    ],
    "sg:phone":"+1 281 347 0033",
    "sg:postcode":"77493",
    "sg:province":"TX",
    "sg:tags":[
        "industrial"
    ],
    "wof:name":"Autoclave Engineers",
    "wof:placetype":"venue"
},
  "geometry": {"coordinates":[-95.828776,29.805948],"type":"Point"}
}