{
  "type": "Feature",
  "properties": {
    "iso:country":"US",
    "sg:address":"8310 Woodward St",
    "sg:city":"Houston",
    "sg:classifiers":[
        {
            "category":"Food & Beverages",
            "subcategory":"Liquor & Beverages",
            "type":"Retail Goods"
        }
    ],
    "sg:phone":"+1 713 731 1283",
    "sg:postcode":"77051",
    "sg:province":"TX",
    "sg:tags":[
        "alcoholic"
    ],
    "wof:name":"Leroy Ruffin",
    "wof:placetype":"venue"
},
  "geometry": {"coordinates":[-95.373679,29.670779],"type":"Point"}
}