{
  "type": "Feature",
  "properties": {
    "iso:country":"US",
    "sg:address":"3602 W Waco Dr",
    "sg:city":"Waco",
    "sg:classifiers":[
        {
            "category":"Building & Trades",
            "subcategory":"Construction",
            "type":"Services"
        }
    ],
    "sg:phone":"+1 254 752 0170",
    "sg:postcode":"76710",
    "sg:province":"TX",
    "sg:tags":[
        "contractor"
    ],
    "wof:name":"Fitch Drywall",
    "wof:placetype":"venue"
},
  "geometry": {"coordinates":[-97.164557,31.533596],"type":"Point"}
}