{
  "type": "Feature",
  "properties": {
    "iso:country":"US",
    "sg:address":"4161 Beechwood Ln",
    "sg:city":"Dallas",
    "sg:classifiers":[
        {
            "category":"Professional",
            "type":"Services"
        }
    ],
    "sg:phone":"+1 214 358 5516",
    "sg:postcode":"75220",
    "sg:province":"TX",
    "wof:name":"Supportworks Inc",
    "wof:placetype":"venue"
},
  "geometry": {"coordinates":[-96.840887,32.876238],"type":"Point"}
}