{
  "type": "Feature",
  "properties": {
    "iso:country":"US",
    "sg:address":"106 S 5th St",
    "sg:city":"Vega",
    "sg:classifiers":[
        {
            "category":"Home & Garden",
            "subcategory":"Garden Supply",
            "type":"Retail Goods"
        }
    ],
    "sg:phone":"+1 806 267 2379",
    "sg:postcode":"79092",
    "sg:province":"TX",
    "sg:tags":[
        "bulb",
        "seed"
    ],
    "sg:website":"www.richardsonseeds.com",
    "wof:name":"Richardson Seeds Inc",
    "wof:placetype":"venue"
},
  "geometry": {"coordinates":[-102.42212000000001,35.246505],"type":"Point"}
}