{
  "type": "Feature",
  "properties": {
    "iso:country":"US",
    "sg:address":"317 N Cedar St",
    "sg:city":"Pecos",
    "sg:classifiers":[
        {
            "category":"Retail",
            "subcategory":"Auto Repair",
            "type":"Services"
        }
    ],
    "sg:phone":"+1 432 445 2520",
    "sg:postcode":"79772",
    "sg:province":"TX",
    "sg:tags":[
        "general"
    ],
    "wof:name":"Jesse & Sons Auto Repair",
    "wof:placetype":"venue"
},
  "geometry": {"coordinates":[-103.49719,31.431732],"type":"Point"}
}