{
  "type": "Feature",
  "properties": {
    "iso:country":"US",
    "sg:address":"10703 Plano Rd",
    "sg:city":"Dallas",
    "sg:classifiers":[
        {
            "category":"Home & Garden",
            "subcategory":"Building Materials",
            "type":"Retail Goods"
        },
        {
            "category":"Building & Trades",
            "subcategory":"Construction",
            "type":"Services"
        }
    ],
    "sg:phone":"+1 469 364 9900",
    "sg:postcode":"75238",
    "sg:province":"TX",
    "sg:tags":[
        "repairing",
        "siding",
        "work",
        "remodeling",
        "contractor"
    ],
    "wof:name":"Procraft Liquid Siding",
    "wof:placetype":"venue"
},
  "geometry": {"coordinates":[-96.700746,32.896901],"type":"Point"}
}