{
  "type": "Feature",
  "properties": {
    "iso:country":"US",
    "sg:address":"149 E Travis St",
    "sg:city":"La Grange",
    "sg:classifiers":[
        {
            "category":"Professional",
            "subcategory":"Research",
            "type":"Services"
        }
    ],
    "sg:phone":"+1 979 968 2673",
    "sg:postcode":"78945",
    "sg:province":"TX",
    "sg:tags":[
        "environmental",
        "ecological"
    ],
    "wof:name":"Fahrenthold & Assoc",
    "wof:placetype":"venue"
},
  "geometry": {"coordinates":[-96.876108,29.905933],"type":"Point"}
}