{
  "type": "Feature",
  "properties": {
    "iso:country":"US",
    "sg:address":"908 E Court St",
    "sg:city":"Seguin",
    "sg:classifiers":[
        {
            "category":"Health Services",
            "subcategory":"Doctor",
            "type":"Services"
        }
    ],
    "sg:phone":"+1 830 303 5996",
    "sg:postcode":"78155",
    "sg:province":"TX",
    "sg:tags":[
        "physician",
        "surgeon"
    ],
    "wof:name":"Heart & Vascular Inst Of Texas",
    "wof:placetype":"venue"
},
  "geometry": {"coordinates":[-97.952646,29.569118],"type":"Point"}
}