{
  "type": "Feature",
  "properties": {
    "iso:country":"US",
    "sg:address":"733 W Davis St",
    "sg:city":"Conroe",
    "sg:classifiers":[
        {
            "category":"Shopping",
            "subcategory":"Discount & Variety Stores",
            "type":"Retail Goods"
        }
    ],
    "sg:phone":"+1 936 539 5214",
    "sg:postcode":"77301",
    "sg:province":"TX",
    "wof:name":"Dollar General",
    "wof:placetype":"venue"
},
  "geometry": {"coordinates":[-95.46334,30.312157],"type":"Point"}
}