{
  "type": "Feature",
  "properties": {
    "iso:country":"US",
    "sg:address":"204 Baxter St",
    "sg:city":"San Augustine",
    "sg:classifiers":[
        {
            "category":"Manufacturing",
            "subcategory":"Lumber",
            "type":"Manufacturing & Wholesale Goods"
        }
    ],
    "sg:phone":"+1 936 275 5990",
    "sg:postcode":"75972",
    "sg:province":"TX",
    "sg:tags":[
        "forestry",
        "forester"
    ],
    "wof:name":"Ladner Forestry Consulting Svc",
    "wof:placetype":"venue"
},
  "geometry": {"coordinates":[-94.10254999999999,31.518088],"type":"Point"}
}