{
  "type": "Feature",
  "properties": {
    "iso:country":"US",
    "sg:address":"2901 N Velasco St",
    "sg:city":"Angleton",
    "sg:classifiers":[
        {
            "category":"Deli",
            "type":"Food & Drink"
        }
    ],
    "sg:menulink":"http://www.allmenus.com/tx/angleton-rosharon/126727-blimpie-subs--sandwiches/menu/",
    "sg:phone":"+1 979 849 1554",
    "sg:postcode":"77515",
    "sg:province":"TX",
    "sg:tags":[
        "wrap",
        "american",
        "sandwich"
    ],
    "wof:name":"Blimpie Subs & Sandwiches",
    "wof:placetype":"venue"
},
  "geometry": {"coordinates":[-95.434421,29.194165],"type":"Point"}
}