{
  "type": "Feature",
  "properties": {
    "iso:country":"US",
    "sg:address":"4202 Yellowstone Dr",
    "sg:city":"Pasadena",
    "sg:classifiers":[
        {
            "category":"Organizations",
            "subcategory":"Religious Organization",
            "type":"Services"
        }
    ],
    "sg:phone":"+1 281 991 8479",
    "sg:postcode":"77504",
    "sg:province":"TX",
    "sg:tags":[
        "church"
    ],
    "wof:name":"Church Of Jesus Christ Of Lds",
    "wof:placetype":"venue"
},
  "geometry": {"coordinates":[-95.178538,29.64415],"type":"Point"}
}