{
  "type": "Feature",
  "properties": {
    "iso:country":"US",
    "sg:address":"3119 Lilly Street",
    "sg:city":"Pasadena",
    "sg:classifiers":[
        {
            "category":"Home & Garden",
            "subcategory":"Garden Supply",
            "type":"Retail Goods"
        }
    ],
    "sg:phone":"+1 281 991 6841",
    "sg:postcode":"77505",
    "sg:province":"TX",
    "sg:tags":[
        "nursery",
        "gardening"
    ],
    "sg:website":"www.clownalleyorchids.com",
    "wof:name":"Clown Alley Orchids",
    "wof:placetype":"venue"
},
  "geometry": {"coordinates":[-95.166462,29.663701],"type":"Point"}
}