{
  "type": "Feature",
  "properties": {
    "iso:country":"US",
    "sg:address":"1213 N Carrier Pkwy",
    "sg:city":"Grand Prairie",
    "sg:classifiers":[
        {
            "category":"Wholesale",
            "subcategory":"Motor Vehicles",
            "type":"Manufacturing & Wholesale Goods"
        }
    ],
    "sg:phone":"+1 972 606 0677",
    "sg:postcode":"75050",
    "sg:province":"TX",
    "sg:tags":[
        "automobile",
        "truck",
        "broker"
    ],
    "wof:name":"Harte-Hanks Transportation Svc",
    "wof:placetype":"venue"
},
  "geometry": {"coordinates":[-97.019998,32.758147],"type":"Point"}
}