{
  "type": "Feature",
  "properties": {
    "iso:country":"US",
    "sg:address":"1050 Edgebrook Dr",
    "sg:city":"Houston",
    "sg:classifiers":[
        {
            "category":"Utilities",
            "subcategory":"Telephone",
            "type":"Services"
        }
    ],
    "sg:phone":"+1 281 221 6988",
    "sg:postcode":"77034",
    "sg:province":"TX",
    "sg:tags":[
        "communication",
        "radio",
        "except"
    ],
    "wof:name":"Think E-Biz",
    "wof:placetype":"venue"
},
  "geometry": {"coordinates":[-95.238906,29.643236],"type":"Point"}
}