{
  "type": "Feature",
  "properties": {
    "iso:country":"US",
    "sg:address":"3625 N Hall St",
    "sg:city":"Dallas",
    "sg:classifiers":[
        {
            "category":"Professional",
            "subcategory":"Computer Services",
            "type":"Services"
        }
    ],
    "sg:phone":"+1 214 263 8450",
    "sg:postcode":"75219",
    "sg:province":"TX",
    "sg:tags":[
        "consulting",
        "management",
        "related"
    ],
    "wof:name":"Computer Dynamics",
    "wof:placetype":"venue"
},
  "geometry": {"coordinates":[-96.805426,32.808334],"type":"Point"}
}