{
  "type": "Feature",
  "properties": {
    "iso:country":"US",
    "sg:address":"6260 Goliad Ave",
    "sg:city":"Dallas",
    "sg:classifiers":[
        {
            "category":"Restaurant",
            "type":"Food & Drink"
        }
    ],
    "sg:phone":"+1 214 827 3527",
    "sg:postcode":"75214",
    "sg:province":"TX",
    "sg:tags":[
        "eating"
    ],
    "wof:name":"Isamare Beverage Inc",
    "wof:placetype":"venue"
},
  "geometry": {"coordinates":[-96.75736499999999,32.818085],"type":"Point"}
}