{
  "type": "Feature",
  "properties": {
    "iso:country":"US",
    "sg:address":"1418 Cedar Post Ln",
    "sg:city":"Houston",
    "sg:classifiers":[
        {
            "category":"Building & Trades",
            "subcategory":"Construction",
            "type":"Services"
        }
    ],
    "sg:phone":"+1 713 984 8834",
    "sg:postcode":"77055",
    "sg:province":"TX",
    "sg:tags":[
        "repairing",
        "general",
        "remodeling",
        "contractor"
    ],
    "wof:name":"Craftsmanship By John Inc",
    "wof:placetype":"venue"
},
  "geometry": {"coordinates":[-95.524379,29.794834],"type":"Point"}
}