{
  "type": "Feature",
  "properties": {
    "iso:country":"US",
    "sg:address":"3226 Commander Dr",
    "sg:city":"Carrollton",
    "sg:classifiers":[
        {
            "category":"Professional",
            "subcategory":"Management & Consulting",
            "type":"Services"
        },
        {
            "category":"Professional",
            "subcategory":"Testing Lab",
            "type":"Services"
        },
        {
            "category":"Professional",
            "subcategory":"Engineering",
            "type":"Services"
        }
    ],
    "sg:phone":"+1 972 931 7127",
    "sg:postcode":"75006",
    "sg:province":"TX",
    "sg:tags":[
        "laboratory",
        "consultant",
        "ecological",
        "engineer",
        "environmental"
    ],
    "sg:website":"http://www.metcoenv.com",
    "wof:name":"Metco Environmental",
    "wof:placetype":"venue"
},
  "geometry": {"coordinates":[-96.849296,32.977063],"type":"Point"}
}