{
  "type": "Feature",
  "properties": {
    "iso:country":"US",
    "sg:address":"2704 Washington St",
    "sg:city":"Greenville",
    "sg:classifiers":[
        {
            "category":"Professional",
            "subcategory":"Lawyer & Legal Services",
            "type":"Services"
        }
    ],
    "sg:phone":"+1 903 454 2600",
    "sg:postcode":"75401",
    "sg:province":"TX",
    "sg:tags":[
        "attorney"
    ],
    "wof:name":"Timothy Linden Law Office",
    "wof:placetype":"venue"
},
  "geometry": {"coordinates":[-96.108166,33.139161],"type":"Point"}
}