{
  "type": "Feature",
  "properties": {
    "iso:country":"US",
    "sg:address":"180 McCutcheon Ln",
    "sg:city":"El Paso",
    "sg:classifiers":[
        {
            "category":"Retail",
            "subcategory":"Repair Shop",
            "type":"Services"
        }
    ],
    "sg:phone":"+1 915 581 5850",
    "sg:postcode":"79932",
    "sg:province":"TX",
    "sg:tags":[
        "door"
    ],
    "wof:name":"Door Repair Co",
    "wof:placetype":"venue"
},
  "geometry": {"coordinates":[-106.585565,31.85824],"type":"Point"}
}