{
  "type": "Feature",
  "properties": {
    "iso:country":"US",
    "sg:address":"110 Flying Scot St",
    "sg:city":"Austin",
    "sg:classifiers":[
        {
            "category":"Professional",
            "subcategory":"Management & Consulting",
            "type":"Services"
        }
    ],
    "sg:phone":"+1 512 261 4446",
    "sg:postcode":"78734",
    "sg:province":"TX",
    "sg:tags":[
        "roofing"
    ],
    "wof:name":"Chatagnier Kent J Cons In Rfin",
    "wof:placetype":"venue"
},
  "geometry": {"coordinates":[-97.993284,30.357439],"type":"Point"}
}