{
  "type": "Feature",
  "properties": {
    "iso:country":"US",
    "sg:address":"3701 Stoney Creek Rd",
    "sg:city":"Fort Worth",
    "sg:classifiers":[
        {
            "category":"Wholesale",
            "subcategory":"Apparel",
            "type":"Manufacturing & Wholesale Goods"
        }
    ],
    "sg:phone":"+1 817 737 6477",
    "sg:postcode":"76116",
    "sg:province":"TX",
    "sg:tags":[
        "mfg",
        "household",
        "mail",
        "retail",
        "order",
        "clothes"
    ],
    "wof:name":"Earth Friendly Goods",
    "wof:placetype":"venue"
},
  "geometry": {"coordinates":[-97.434139,32.696495],"type":"Point"}
}