{
  "type": "Feature",
  "properties": {
    "iso:country":"US",
    "sg:address":"8807 Emmott Rd",
    "sg:city":"Houston",
    "sg:classifiers":[
        {
            "category":"Wholesale",
            "subcategory":"Machinery & Supplies",
            "type":"Manufacturing & Wholesale Goods"
        }
    ],
    "sg:phone":"+1 713 466 6269",
    "sg:postcode":"77040",
    "sg:province":"TX",
    "sg:tags":[
        "water",
        "company-utility",
        "cleaning"
    ],
    "wof:name":"C R S Power Flow",
    "wof:placetype":"venue"
},
  "geometry": {"coordinates":[-95.531654,29.873849],"type":"Point"}
}