{
  "type": "Feature",
  "properties": {
    "iso:country":"US",
    "sg:address":"5012 W Park Dr",
    "sg:city":"Austin",
    "sg:classifiers":[
        {
            "category":"Professional",
            "type":"Services"
        }
    ],
    "sg:phone":"+1 512 467 2200",
    "sg:postcode":"78731",
    "sg:province":"TX",
    "sg:tags":[
        "establishment"
    ],
    "wof:name":"Gozers United",
    "wof:placetype":"venue"
},
  "geometry": {"coordinates":[-97.75306500000001,30.329257],"type":"Point"}
}