{
  "type": "Feature",
  "properties": {
    "iso:country":"US",
    "sg:address":"1813 Mustang St",
    "sg:city":"Amarillo",
    "sg:classifiers":[
        {
            "category":"Freight",
            "type":"Transportation"
        }
    ],
    "sg:phone":"+1 806 352 0203",
    "sg:postcode":"79102",
    "sg:province":"TX",
    "sg:tags":[
        "operator",
        "trucking"
    ],
    "wof:name":"K & S Transport",
    "wof:placetype":"venue"
},
  "geometry": {"coordinates":[-101.881663,35.195924],"type":"Point"}
}