{
  "type": "Feature",
  "properties": {
    "iso:country":"US",
    "sg:address":"1434 Kingsley Dr",
    "sg:city":"Allen",
    "sg:classifiers":[
        {
            "category":"Professional",
            "type":"Services"
        }
    ],
    "sg:phone":"+1 972 359 7014",
    "sg:postcode":"75013",
    "sg:province":"TX",
    "wof:name":"Skillbase Inc",
    "wof:placetype":"venue"
},
  "geometry": {"coordinates":[-96.704854,33.124865],"type":"Point"}
}