{
  "type": "Feature",
  "properties": {
    "iso:country":"US",
    "sg:address":"5010 Grove West Blvd",
    "sg:city":"Stafford",
    "sg:classifiers":[
        {
            "category":"Wholesale",
            "subcategory":"Vending Machines",
            "type":"Manufacturing & Wholesale Goods"
        }
    ],
    "sg:phone":"+1 281 242 1790",
    "sg:postcode":"77477",
    "sg:province":"TX",
    "wof:name":"Cook Enterprise",
    "wof:placetype":"venue"
},
  "geometry": {"coordinates":[-95.59147299999999,29.644815],"type":"Point"}
}