{
  "type": "Feature",
  "properties": {
    "iso:country":"US",
    "sg:address":"3404 Wayside Ave",
    "sg:city":"Fort Worth",
    "sg:classifiers":[
        {
            "category":"Banks & Credit Unions",
            "subcategory":"Investment Brokerage",
            "type":"Services"
        }
    ],
    "sg:phone":"+1 817 926 8746",
    "sg:postcode":"76110",
    "sg:province":"TX",
    "sg:tags":[
        "advisory"
    ],
    "wof:name":"Stone Financial",
    "wof:placetype":"venue"
},
  "geometry": {"coordinates":[-97.351392,32.699089],"type":"Point"}
}