{
  "type": "Feature",
  "properties": {
    "iso:country":"US",
    "sg:address":"3554 FM 346 E",
    "sg:city":"Tyler",
    "sg:classifiers":[
        {
            "category":"Building & Trades",
            "subcategory":"Plumbing",
            "type":"Services"
        }
    ],
    "sg:phone":"+1 903 581 1352",
    "sg:postcode":"75703",
    "sg:province":"TX",
    "sg:tags":[
        "contractor"
    ],
    "wof:name":"Gil Air Tech",
    "wof:placetype":"venue"
},
  "geometry": {"coordinates":[-95.28523800000001,32.215738],"type":"Point"}
}