{
  "type": "Feature",
  "properties": {
    "iso:country":"US",
    "sg:address":"911 N Bryan Ave",
    "sg:city":"Bryan",
    "sg:classifiers":[
        {
            "category":"Restaurant",
            "type":"Food & Drink"
        }
    ],
    "sg:phone":"+1 979 775 8054",
    "sg:postcode":"77803",
    "sg:province":"TX",
    "sg:tags":[
        "mexican"
    ],
    "wof:name":"Taqueria El Tio",
    "wof:placetype":"venue"
},
  "geometry": {"coordinates":[-96.373024,30.681142],"type":"Point"}
}