{
  "type": "Feature",
  "properties": {
    "iso:country":"US",
    "sg:address":"508 Crockett St",
    "sg:city":"Amarillo",
    "sg:classifiers":[
        {
            "category":"Building & Trades",
            "subcategory":"Electrical",
            "type":"Services"
        }
    ],
    "sg:phone":"+1 806 373 0452",
    "sg:postcode":"79106",
    "sg:province":"TX",
    "sg:tags":[
        "electric",
        "contractor"
    ],
    "wof:name":"H L Price & Sons Electrical",
    "wof:placetype":"venue"
},
  "geometry": {"coordinates":[-101.8569,35.210334],"type":"Point"}
}