{
  "type": "Feature",
  "properties": {
    "iso:country":"US",
    "sg:address":"5224 Saunders Rd",
    "sg:city":"Fort Worth",
    "sg:classifiers":[
        {
            "category":"Building & Trades",
            "subcategory":"Construction",
            "type":"Services"
        }
    ],
    "sg:phone":"+1 817 563 5564",
    "sg:postcode":"76119",
    "sg:province":"TX",
    "sg:tags":[
        "house",
        "foundation",
        "contractor",
        "leveling",
        "repair"
    ],
    "sg:website":"www.pjfr.com",
    "wof:name":"Power Jack Foundation Repair",
    "wof:placetype":"venue"
},
  "geometry": {"coordinates":[-97.241377,32.676541],"type":"Point"}
}