{
  "type": "Feature",
  "properties": {
    "iso:country":"US",
    "sg:address":"2422 FM 1294",
    "sg:city":"Lubbock",
    "sg:classifiers":[
        {
            "category":"Professional",
            "type":"Services"
        }
    ],
    "sg:phone":"+1 806 746 5881",
    "sg:postcode":"79403",
    "sg:province":"TX",
    "sg:tags":[
        "establishment"
    ],
    "wof:name":"Farmers Depot",
    "wof:placetype":"venue"
},
  "geometry": {"coordinates":[-101.862683,33.693794],"type":"Point"}
}