{
  "type": "Feature",
  "properties": {
    "iso:country":"US",
    "sg:address":"197 Willowcreek Cir",
    "sg:city":"Allen",
    "sg:classifiers":[
        {
            "category":"Professional",
            "type":"Services"
        }
    ],
    "sg:phone":"+1 972 359 2839",
    "sg:postcode":"75002",
    "sg:province":"TX",
    "sg:tags":[
        "establishment"
    ],
    "wof:name":"Output Technology Corp",
    "wof:placetype":"venue"
},
  "geometry": {"coordinates":[-96.67198399999999,33.094826],"type":"Point"}
}