{
  "type": "Feature",
  "properties": {
    "iso:country":"US",
    "sg:address":"1521 N Custer Rd Suite 2800",
    "sg:city":"Mckinney",
    "sg:classifiers":[
        {
            "category":"Fast Food",
            "type":"Food & Drink"
        },
        {
            "category":"Restaurant",
            "type":"Food & Drink"
        },
        {
            "category":"Food & Beverages",
            "subcategory":"Groceries & Convenience Stores",
            "type":"Retail Goods"
        }
    ],
    "sg:phone":"+1 972 540 6510",
    "sg:postcode":"75071",
    "sg:province":"TX",
    "sg:tags":[
        "shop",
        "american",
        "sandwich",
        "take"
    ],
    "sg:website":"http://www.subway.com",
    "wof:name":"Subway",
    "wof:placetype":"venue"
},
  "geometry": {"coordinates":[-96.73282500000001,33.215986],"type":"Point"}
}