{
  "type": "Feature",
  "properties": {
    "iso:country":"US",
    "sg:address":"11301 Jacksboro Hwy",
    "sg:city":"Fort Worth",
    "sg:classifiers":[
        {
            "category":"Building & Trades",
            "subcategory":"Equipment Rental",
            "type":"Services"
        }
    ],
    "sg:phone":"+1 817 626 0240",
    "sg:postcode":"76135",
    "sg:province":"TX",
    "sg:tags":[
        "leasing"
    ],
    "wof:name":"Cottonwood Creek Inc",
    "wof:placetype":"venue"
},
  "geometry": {"coordinates":[-97.50485500000001,32.850873],"type":"Point"}
}