{
  "type": "Feature",
  "properties": {
    "iso:country":"US",
    "sg:address":"10309 Perrin Beitel Rd",
    "sg:city":"San Antonio",
    "sg:classifiers":[
        {
            "category":"Shopping",
            "subcategory":"Used Merchandise",
            "type":"Retail Goods"
        }
    ],
    "sg:phone":"+1 210 637 0838",
    "sg:postcode":"78217",
    "sg:province":"TX",
    "sg:tags":[
        "pawnbroker"
    ],
    "wof:name":"Money Mart Pawn & Jewelry",
    "wof:placetype":"venue"
},
  "geometry": {"coordinates":[-98.411118,29.534219],"type":"Point"}
}