{
  "type": "Feature",
  "properties": {
    "iso:country":"US",
    "sg:address":"119 Broken Bough Ln",
    "sg:city":"San Antonio",
    "sg:classifiers":[
        {
            "category":"Professional",
            "subcategory":"Business Services",
            "type":"Services"
        }
    ],
    "sg:phone":"+1 210 492 9266",
    "sg:postcode":"78231",
    "sg:province":"TX",
    "wof:name":"Psencik Family Partners L",
    "wof:placetype":"venue"
},
  "geometry": {"coordinates":[-98.56037600000001,29.586383],"type":"Point"}
}