{
  "type": "Feature",
  "properties": {
    "iso:country":"US",
    "sg:address":"5210 Canal St",
    "sg:city":"Houston",
    "sg:classifiers":[
        {
            "category":"Manufacturing",
            "subcategory":"Tools & Machinery",
            "type":"Manufacturing & Wholesale Goods"
        }
    ],
    "sg:phone":"+1 713 921 2154",
    "sg:postcode":"77011",
    "sg:province":"TX",
    "sg:tags":[
        "mfg",
        "pattern",
        "model",
        "industrial",
        "custom"
    ],
    "wof:name":"Houston Pattern Works Inc",
    "wof:placetype":"venue"
},
  "geometry": {"coordinates":[-95.321573,29.74629],"type":"Point"}
}