{
  "type": "Feature",
  "properties": {
    "iso:country":"US",
    "sg:address":"2601 S Main St",
    "sg:city":"Mcallen",
    "sg:classifiers":[
        {
            "category":"Airline",
            "type":"Transportation"
        }
    ],
    "sg:phone":"+1 800 238 5355",
    "sg:postcode":"78503",
    "sg:province":"TX",
    "sg:tags":[
        "courier",
        "air"
    ],
    "wof:name":"Federal Express Corporation",
    "wof:placetype":"venue"
},
  "geometry": {"coordinates":[-98.238209,26.18179],"type":"Point"}
}