{
  "type": "Feature",
  "properties": {
    "iso:country":"US",
    "sg:address":"210 Clay St",
    "sg:city":"Nocona",
    "sg:classifiers":[
        {
            "category":"Manufacturing",
            "subcategory":"Buildings",
            "type":"Manufacturing & Wholesale Goods"
        },
        {
            "category":"Building & Trades",
            "subcategory":"Construction",
            "type":"Services"
        }
    ],
    "sg:phone":"+1 940 825 3858",
    "sg:postcode":"76255",
    "sg:province":"TX",
    "sg:tags":[
        "home",
        "builder",
        "contractor"
    ],
    "sg:website":"http://www.mchomes.com",
    "wof:name":"M C Homes",
    "wof:placetype":"venue"
},
  "geometry": {"coordinates":[-97.727199,33.788688],"type":"Point"}
}