{
  "type": "Feature",
  "properties": {
    "iso:country":"US",
    "sg:address":"215 Hudson St",
    "sg:city":"Newark",
    "sg:classifiers":[
        {
            "category":"Shopping",
            "type":"Retail Goods"
        }
    ],
    "sg:phone":"+1 817 489 2113",
    "sg:postcode":"76071",
    "sg:province":"TX",
    "sg:tags":[
        "merchandise"
    ],
    "wof:name":"Charlotte E Chapman",
    "wof:placetype":"venue"
},
  "geometry": {"coordinates":[-97.482733,33.001815],"type":"Point"}
}