{
  "type": "Feature",
  "properties": {
    "iso:country":"US",
    "sg:address":"2426 Guadalupe St.",
    "sg:city":"Austin",
    "sg:classifiers":[
        {
            "category":"Restaurant",
            "type":"Food & Drink"
        }
    ],
    "sg:phone":"+1 512 472 6356",
    "sg:postcode":"78705",
    "sg:province":"TX",
    "sg:tags":[
        "pizza"
    ],
    "sg:website":"www.mellowmushroom.com",
    "wof:name":"The Mellow Mushroom",
    "wof:placetype":"venue"
},
  "geometry": {"coordinates":[-97.741699,30.288601],"type":"Point"}
}