{
  "type": "Feature",
  "properties": {
    "iso:country":"US",
    "sg:address":"2095 Eastman Ave",
    "sg:city":"New Braunfels",
    "sg:classifiers":[
        {
            "category":"Shopping",
            "type":"Retail Goods"
        }
    ],
    "sg:phone":"+1 830 625 3822",
    "sg:postcode":"78130",
    "sg:province":"TX",
    "sg:tags":[
        "merchandise"
    ],
    "wof:name":"Dorseys General Store",
    "wof:placetype":"venue"
},
  "geometry": {"coordinates":[-98.137286,29.682348],"type":"Point"}
}