{
  "type": "Feature",
  "properties": {
    "iso:country":"US",
    "sg:address":"10807 Perrin Beitel Rd",
    "sg:city":"San Antonio",
    "sg:classifiers":[
        {
            "category":"Insurance",
            "subcategory":"Insurance Agent",
            "type":"Services"
        }
    ],
    "sg:phone":"+1 210 655 2311",
    "sg:postcode":"78217",
    "sg:province":"TX",
    "wof:name":"Joe White Agency",
    "wof:placetype":"venue"
},
  "geometry": {"coordinates":[-98.411047,29.538892],"type":"Point"}
}