{
  "type": "Feature",
  "properties": {
    "iso:country":"US",
    "sg:address":"5623 Shoal Creek Blvd",
    "sg:city":"Austin",
    "sg:classifiers":[
        {
            "category":"Building & Trades",
            "subcategory":"Construction",
            "type":"Services"
        }
    ],
    "sg:phone":"+1 512 243 7745",
    "sg:postcode":"78756",
    "sg:province":"TX",
    "sg:tags":[
        "maker",
        "cabinet"
    ],
    "wof:name":"Austin Cabinet Connection",
    "wof:placetype":"venue"
},
  "geometry": {"coordinates":[-97.748431,30.332981],"type":"Point"}
}