{
  "type": "Feature",
  "properties": {
    "iso:country":"US",
    "sg:address":"1001 Oakridge Ct",
    "sg:city":"Kennedale",
    "sg:classifiers":[
        {
            "category":"Freight",
            "type":"Transportation"
        }
    ],
    "sg:phone":"+1 817 483 0693",
    "sg:postcode":"76060",
    "sg:province":"TX",
    "sg:tags":[
        "operator",
        "mail",
        "trucking",
        "local",
        "house"
    ],
    "wof:name":"Ray Birch Co",
    "wof:placetype":"venue"
},
  "geometry": {"coordinates":[-97.21248199999999,32.656109],"type":"Point"}
}