{
  "type": "Feature",
  "properties": {
    "iso:country":"US",
    "sg:address":"5425 22nd St",
    "sg:city":"Lubbock",
    "sg:classifiers":[
        {
            "category":"Shopping",
            "subcategory":"Bicycles & Sporting Goods",
            "type":"Retail Goods"
        }
    ],
    "sg:phone":"+1 806 792 6326",
    "sg:postcode":"79407",
    "sg:province":"TX",
    "wof:name":"Ghost Riders Bicycles",
    "wof:placetype":"venue"
},
  "geometry": {"coordinates":[-101.930482,33.574411],"type":"Point"}
}