{
  "type": "Feature",
  "properties": {
    "iso:country":"US",
    "sg:address":"1102 NW 7th St",
    "sg:city":"Grand Prairie",
    "sg:classifiers":[
        {
            "category":"Organizations",
            "subcategory":"Religious Organization",
            "type":"Services"
        },
        {
            "category":"Social Services",
            "type":"Services"
        }
    ],
    "sg:phone":"+1 972 264 3771",
    "sg:postcode":"75050",
    "sg:province":"TX",
    "sg:tags":[
        "church"
    ],
    "wof:name":"Community Service Center",
    "wof:placetype":"venue"
},
  "geometry": {"coordinates":[-97.01227400000001,32.758158],"type":"Point"}
}