{
  "type": "Feature",
  "properties": {
    "iso:country":"US",
    "sg:address":"1335 N Belt Line Rd",
    "sg:city":"Irving",
    "sg:classifiers":[
        {
            "category":"Professional",
            "type":"Services"
        }
    ],
    "sg:phone":"+1 972 790 4648",
    "sg:postcode":"75061",
    "sg:province":"TX",
    "wof:name":"VMJ General Svc",
    "wof:placetype":"venue"
},
  "geometry": {"coordinates":[-96.99387299999999,32.826372],"type":"Point"}
}