{
  "type": "Feature",
  "properties": {
    "iso:country":"US",
    "sg:address":"10028 Algiers Rd",
    "sg:city":"Houston",
    "sg:classifiers":[
        {
            "category":"Organizations",
            "subcategory":"Religious Organization",
            "type":"Services"
        }
    ],
    "sg:phone":"+1 713 939 1959",
    "sg:postcode":"77041",
    "sg:province":"TX",
    "wof:name":"Carverdale Cmnty Fllwship Cgic",
    "wof:placetype":"venue"
},
  "geometry": {"coordinates":[-95.54216099999999,29.84546],"type":"Point"}
}