{
  "type": "Feature",
  "properties": {
    "iso:country":"US",
    "sg:address":"111 E Irving Blvd",
    "sg:city":"Irving",
    "sg:classifiers":[
        {
            "category":"Wholesale",
            "subcategory":"Non-durable Goods",
            "type":"Manufacturing & Wholesale Goods"
        }
    ],
    "sg:phone":"+1 972 251 1880",
    "sg:postcode":"75060",
    "sg:province":"TX",
    "sg:tags":[
        "calendar"
    ],
    "wof:name":"DBR Publishing",
    "wof:placetype":"venue"
},
  "geometry": {"coordinates":[-96.945014,32.813905],"type":"Point"}
}