{
  "type": "Feature",
  "properties": {
    "iso:country":"US",
    "sg:address":"3304 Communications Pkwy",
    "sg:city":"Plano",
    "sg:classifiers":[
        {
            "category":"Personal",
            "type":"Services"
        }
    ],
    "sg:phone":"+1 972 473 2644",
    "sg:postcode":"75093",
    "sg:province":"TX",
    "sg:tags":[
        "consultant",
        "image"
    ],
    "wof:name":"Preview Health Imaging",
    "wof:placetype":"venue"
},
  "geometry": {"coordinates":[-96.83286699999999,33.045387],"type":"Point"}
}