{
  "type": "Feature",
  "properties": {
    "iso:country":"US",
    "sg:address":"4022 Lyndhurst Pl",
    "sg:city":"Sugar Land",
    "sg:classifiers":[
        {
            "category":"Professional",
            "subcategory":"Computer Services",
            "type":"Services"
        }
    ],
    "sg:phone":"+1 281 989 8600",
    "sg:postcode":"77479",
    "sg:province":"TX",
    "sg:tags":[
        "programing",
        "custom"
    ],
    "wof:name":"Mustmedia LLC",
    "wof:placetype":"venue"
},
  "geometry": {"coordinates":[-95.627747,29.575552],"type":"Point"}
}