{
  "type": "Feature",
  "properties": {
    "iso:country":"US",
    "sg:address":"2813 Rio Grande St",
    "sg:city":"Austin",
    "sg:classifiers":[
        {
            "category":"Professional",
            "subcategory":"Computer Services",
            "type":"Services"
        }
    ],
    "sg:phone":"+1 512 472 4521",
    "sg:postcode":"78705",
    "sg:province":"TX",
    "sg:tags":[
        "agency",
        "datum",
        "advertising"
    ],
    "wof:name":"Fishtank Design and Marketing",
    "wof:placetype":"venue"
},
  "geometry": {"coordinates":[-97.74400900000001,30.293945],"type":"Point"}
}