{
  "type": "Feature",
  "properties": {
    "iso:country":"US",
    "sg:address":"1821 Trowbridge St",
    "sg:city":"Garland",
    "sg:classifiers":[
        {
            "category":"Professional",
            "subcategory":"Business Services",
            "type":"Services"
        }
    ],
    "sg:phone":"+1 972 495 0896",
    "sg:postcode":"75044",
    "sg:province":"TX",
    "sg:tags":[
        "good"
    ],
    "wof:name":"Pool Plaza",
    "wof:placetype":"venue"
},
  "geometry": {"coordinates":[-96.65425999999999,32.936548],"type":"Point"}
}