{
  "type": "Feature",
  "properties": {
    "iso:country":"US",
    "sg:address":"1630 Millview Pl",
    "sg:city":"Carrollton",
    "sg:classifiers":[
        {
            "category":"Professional",
            "subcategory":"Business Services",
            "type":"Services"
        }
    ],
    "sg:phone":"+1 972 245 6112",
    "sg:postcode":"75006",
    "sg:province":"TX",
    "sg:tags":[
        "technical",
        "preparation",
        "manual"
    ],
    "wof:name":"Moreau Services Inc",
    "wof:placetype":"venue"
},
  "geometry": {"coordinates":[-96.896181,32.983492],"type":"Point"}
}