{
  "type": "Feature",
  "properties": {
    "iso:country":"US",
    "sg:address":"3173 W Holcombe Blvd",
    "sg:city":"Houston",
    "sg:classifiers":[
        {
            "category":"Restaurant",
            "type":"Food & Drink"
        },
        {
            "category":"Food & Beverages",
            "subcategory":"Bakery",
            "type":"Retail Goods"
        }
    ],
    "sg:phone":"+1 713 664 9272",
    "sg:postcode":"77025",
    "sg:province":"TX",
    "sg:tags":[
        "greek",
        "sandwich",
        "mediterranean"
    ],
    "sg:website":"yapakitchen.samsbiz.com",
    "wof:name":"Yapa Kitchen Fresh Takeaway",
    "wof:placetype":"venue"
},
  "geometry": {"coordinates":[-95.42710099999999,29.7059],"type":"Point"}
}