{
  "type": "Feature",
  "properties": {
    "iso:country":"US",
    "sg:address":"41 Timberidge",
    "sg:city":"Rowlett",
    "sg:classifiers":[
        {
            "category":"Building & Trades",
            "subcategory":"Construction",
            "type":"Services"
        }
    ],
    "sg:phone":"+1 972 475 2470",
    "sg:postcode":"75089",
    "sg:province":"TX",
    "sg:tags":[
        "house"
    ],
    "wof:name":"B&R Remodeling",
    "wof:placetype":"venue"
},
  "geometry": {"coordinates":[-96.537499,32.92772],"type":"Point"}
}