{
  "type": "Feature",
  "properties": {
    "iso:country":"US",
    "sg:address":"2002 S Zapata Hwy",
    "sg:city":"Laredo",
    "sg:classifiers":[
        {
            "category":"Food & Beverages",
            "subcategory":"Groceries & Convenience Stores",
            "type":"Retail Goods"
        }
    ],
    "sg:phone":"+1 956 791 4109",
    "sg:postcode":"78046",
    "sg:province":"TX",
    "wof:name":"Arguindegui Oil Co II Ltd",
    "wof:placetype":"venue"
},
  "geometry": {"coordinates":[-99.473973,27.478637],"type":"Point"}
}