{
  "type": "Feature",
  "properties": {
    "iso:country":"US",
    "sg:address":"1716 Sam Houston Pkwy",
    "sg:city":"Houston",
    "sg:classifiers":[
        {
            "category":"Professional",
            "subcategory":"Management & Consulting",
            "type":"Services"
        }
    ],
    "sg:phone":"+1 713 467 3394",
    "sg:postcode":"77060",
    "sg:province":"TX",
    "wof:name":"CCC Corporate Services Inc",
    "wof:placetype":"venue"
},
  "geometry": {"coordinates":[-95.36041400000001,29.938575],"type":"Point"}
}