{
  "type": "Feature",
  "properties": {
    "iso:country":"US",
    "sg:address":"2719 Aspen Rd",
    "sg:city":"Rosenberg",
    "sg:classifiers":[
        {
            "category":"Manufacturing",
            "subcategory":"Furniture",
            "type":"Manufacturing & Wholesale Goods"
        },
        {
            "category":"Professional",
            "subcategory":"Management & Consulting",
            "type":"Services"
        }
    ],
    "sg:phone":"+1 281 238 4724",
    "sg:postcode":"77471",
    "sg:province":"TX",
    "sg:tags":[
        "sales",
        "retail",
        "wood",
        "direct",
        "mfg"
    ],
    "wof:name":"William Christen",
    "wof:placetype":"venue"
},
  "geometry": {"coordinates":[-95.818602,29.501369],"type":"Point"}
}