{
  "type": "Feature",
  "properties": {
    "iso:country":"US",
    "sg:address":"740 Robin Ln",
    "sg:city":"Coppell",
    "sg:classifiers":[
        {
            "category":"Wholesale",
            "subcategory":"Chemicals & Plastics",
            "type":"Manufacturing & Wholesale Goods"
        }
    ],
    "sg:phone":"+1 972 304 1480",
    "sg:postcode":"75019",
    "sg:province":"TX",
    "wof:name":"Kommerling USA Inc",
    "wof:placetype":"venue"
},
  "geometry": {"coordinates":[-96.971518,32.966287],"type":"Point"}
}