{
  "type": "Feature",
  "properties": {
    "iso:country":"US",
    "sg:address":"1317 University Ave",
    "sg:city":"Lubbock",
    "sg:classifiers":[
        {
            "category":"Personal",
            "type":"Services"
        }
    ],
    "sg:phone":"+1 806 762 1263",
    "sg:postcode":"79401",
    "sg:province":"TX",
    "wof:name":"Tomken Investments",
    "wof:placetype":"venue"
},
  "geometry": {"coordinates":[-101.87056,33.582732],"type":"Point"}
}