{
  "type": "Feature",
  "properties": {
    "iso:country":"US",
    "sg:address":"1010 Behman St",
    "sg:city":"Corpus Christi",
    "sg:classifiers":[
        {
            "category":"Real Estate",
            "subcategory":"Real Estate Operator",
            "type":"Services"
        }
    ],
    "sg:phone":"+1 361 937 4451",
    "sg:postcode":"78418",
    "sg:province":"TX",
    "sg:tags":[
        "building",
        "apartment"
    ],
    "wof:name":"Aztec Manor Apartments",
    "wof:placetype":"venue"
},
  "geometry": {"coordinates":[-97.292158,27.675641],"type":"Point"}
}