{
  "type": "Feature",
  "properties": {
    "iso:country":"US",
    "sg:address":"4800 Gilmer Rd",
    "sg:city":"Longview",
    "sg:classifiers":[
        {
            "category":"Manufacturing",
            "subcategory":"Paper Products",
            "type":"Manufacturing & Wholesale Goods"
        }
    ],
    "sg:phone":"+1 903 297 4991",
    "sg:postcode":"75605",
    "sg:province":"TX",
    "sg:tags":[
        "die",
        "mfg",
        "business",
        "pack"
    ],
    "wof:name":"ITW Angleboard",
    "wof:placetype":"venue"
},
  "geometry": {"coordinates":[-94.80492099999999,32.566959],"type":"Point"}
}