{
  "type": "Feature",
  "properties": {
    "iso:country":"US",
    "sg:address":"5321 S Loop 289",
    "sg:city":"Lubbock",
    "sg:classifiers":[
        {
            "category":"Professional",
            "type":"Services"
        }
    ],
    "sg:phone":"+1 806 795 7905",
    "sg:postcode":"79424",
    "sg:province":"TX",
    "wof:name":"Early Bird Mobile Services",
    "wof:placetype":"venue"
},
  "geometry": {"coordinates":[-101.929209,33.536578],"type":"Point"}
}