{
  "type": "Feature",
  "properties": {
    "iso:country":"US",
    "sg:address":"1021 W Main St",
    "sg:city":"League City",
    "sg:classifiers":[
        {
            "category":"Food & Beverages",
            "subcategory":"Groceries & Convenience Stores",
            "type":"Retail Goods"
        }
    ],
    "sg:phone":"+1 281 338 0078",
    "sg:postcode":"77573",
    "sg:province":"TX",
    "sg:tags":[
        "pump",
        "gas"
    ],
    "wof:name":"Angel Brothers Enterprises",
    "wof:placetype":"venue"
},
  "geometry": {"coordinates":[-95.104282,29.505485],"type":"Point"}
}