{
  "type": "Feature",
  "properties": {
    "iso:country":"US",
    "sg:address":"5090 Richmond Ave Ste 238",
    "sg:city":"Houston",
    "sg:classifiers":[
        {
            "category":"Wholesale",
            "subcategory":"Home Furnishings",
            "type":"Manufacturing & Wholesale Goods"
        }
    ],
    "sg:phone":"+1 713 594 9943",
    "sg:postcode":"77056",
    "sg:province":"TX",
    "sg:tags":[
        "blind",
        "shade"
    ],
    "sg:website":"www.budgetblinds.com/SWHouston/?...",
    "wof:name":"Budget Blinds",
    "wof:placetype":"venue"
},
  "geometry": {"coordinates":[-95.465356,29.731714],"type":"Point"}
}