{
  "type": "Feature",
  "properties": {
    "iso:country":"US",
    "sg:address":"12826 Ashford Knoll Dr",
    "sg:city":"Houston",
    "sg:classifiers":[
        {
            "category":"Home & Garden",
            "subcategory":"Furniture",
            "type":"Retail Goods"
        }
    ],
    "sg:phone":"+1 832 755 4353",
    "sg:postcode":"77082",
    "sg:province":"TX",
    "wof:name":"Sleep Studies",
    "wof:placetype":"venue"
},
  "geometry": {"coordinates":[-95.61185999999999,29.733035],"type":"Point"}
}