{
  "type": "Feature",
  "properties": {
    "iso:country":"US",
    "sg:address":"2218 Dennis Rd",
    "sg:city":"Weatherford",
    "sg:classifiers":[
        {
            "category":"Freight",
            "type":"Transportation"
        }
    ],
    "sg:phone":"+1 817 613 1228",
    "sg:postcode":"76087",
    "sg:province":"TX",
    "sg:tags":[
        "operator",
        "local",
        "trucking"
    ],
    "wof:name":"Lone Star Escort",
    "wof:placetype":"venue"
},
  "geometry": {"coordinates":[-97.87984899999999,32.696178],"type":"Point"}
}