{
  "type": "Feature",
  "properties": {
    "iso:country":"US",
    "sg:address":"203 Seagraves Rd",
    "sg:city":"Brownfield",
    "sg:classifiers":[
        {
            "category":"Building & Trades",
            "subcategory":"Landscaping Services",
            "type":"Services"
        }
    ],
    "sg:phone":"+1 806 637 9334",
    "sg:postcode":"79316",
    "sg:province":"TX",
    "sg:tags":[
        "spraying",
        "lawn"
    ],
    "wof:name":"Greenlight Lawn & Pest Inc",
    "wof:placetype":"venue"
},
  "geometry": {"coordinates":[-102.277405,33.172251],"type":"Point"}
}