{
  "type": "Feature",
  "properties": {
    "iso:country":"US",
    "sg:address":"212 W Main St",
    "sg:city":"Pecan Gap",
    "sg:classifiers":[
        {
            "category":"Autos & Motor Vehicles",
            "subcategory":"Automobile Sales",
            "type":"Retail Goods"
        }
    ],
    "sg:phone":"+1 903 359 6408",
    "sg:postcode":"75469",
    "sg:province":"TX",
    "sg:tags":[
        "car",
        "dealer"
    ],
    "wof:name":"W D Cheney's Car Sales",
    "wof:placetype":"venue"
},
  "geometry": {"coordinates":[-95.854153,33.437866],"type":"Point"}
}