{
  "type": "Feature",
  "properties": {
    "iso:country":"US",
    "sg:address":"591 E Highway St",
    "sg:city":"Fredericksburg",
    "sg:classifiers":[
        {
            "category":"Real Estate",
            "subcategory":"Real Estate Operator",
            "type":"Services"
        }
    ],
    "sg:phone":"+1 830 997 6803",
    "sg:postcode":"78624",
    "sg:province":"TX",
    "sg:tags":[
        "building",
        "apartment"
    ],
    "wof:name":"Fredercksburg Snior Apartments",
    "wof:placetype":"venue"
},
  "geometry": {"coordinates":[-98.86574899999999,30.261873],"type":"Point"}
}