{
  "type": "Feature",
  "properties": {
    "iso:country":"US",
    "sg:address":"1103 E Ennis Ave",
    "sg:city":"Ennis",
    "sg:classifiers":[
        {
            "category":"Banks & Credit Unions",
            "subcategory":"Bank",
            "type":"Services"
        }
    ],
    "sg:phone":"+1 972 875 1704",
    "sg:postcode":"75119",
    "sg:province":"TX",
    "sg:tags":[
        "depository",
        "banking"
    ],
    "wof:name":"Mr Payroll",
    "wof:placetype":"venue"
},
  "geometry": {"coordinates":[-96.616005,32.334085],"type":"Point"}
}