{
  "type": "Feature",
  "properties": {
    "iso:country":"US",
    "sg:address":"689 Punjab Dr",
    "sg:city":"El Paso",
    "sg:classifiers":[
        {
            "category":"Shopping",
            "subcategory":"Used Merchandise",
            "type":"Retail Goods"
        }
    ],
    "sg:phone":"+1 915 858 6848",
    "sg:postcode":"79927",
    "sg:province":"TX",
    "wof:name":"Carmen Palacios",
    "wof:placetype":"venue"
},
  "geometry": {"coordinates":[-106.276492,31.666961],"type":"Point"}
}