{
  "type": "Feature",
  "properties": {
    "iso:country":"US",
    "sg:address":"102 Andrews Hwy",
    "sg:city":"Midland",
    "sg:classifiers":[
        {
            "category":"Personal",
            "subcategory":"Tattoo Parlor",
            "type":"Services"
        },
        {
            "category":"Personal",
            "subcategory":"Piercing",
            "type":"Services"
        }
    ],
    "sg:phone":"+1 432 520 4241",
    "sg:postcode":"79701",
    "sg:province":"TX",
    "sg:tags":[
        "body"
    ],
    "sg:website":"http://www.uprock.com",
    "wof:name":"Uprock",
    "wof:placetype":"venue"
},
  "geometry": {"coordinates":[-102.098709,31.993504],"type":"Point"}
}