{
  "type": "Feature",
  "properties": {
    "iso:country":"US",
    "sg:address":"2059 Arbor Creek Dr",
    "sg:city":"Carrollton",
    "sg:classifiers":[
        {
            "category":"Professional",
            "type":"Services"
        }
    ],
    "sg:phone":"+1 972 236 8400",
    "sg:postcode":"75010",
    "sg:province":"TX",
    "wof:name":"T Bar Service Co",
    "wof:placetype":"venue"
},
  "geometry": {"coordinates":[-96.875742,33.033914],"type":"Point"}
}