{
  "type": "Feature",
  "properties": {
    "iso:country":"US",
    "sg:address":"2200 Cockrell Ave",
    "sg:city":"Dallas",
    "sg:classifiers":[
        {
            "category":"Manufacturing",
            "subcategory":"Wood Products",
            "type":"Manufacturing & Wholesale Goods"
        }
    ],
    "sg:phone":"+1 214 428 6045",
    "sg:postcode":"75215",
    "sg:province":"TX",
    "sg:tags":[
        "picture",
        "frame",
        "merchandise",
        "mfg"
    ],
    "wof:name":"All About Art Inc",
    "wof:placetype":"venue"
},
  "geometry": {"coordinates":[-96.787571,32.762555],"type":"Point"}
}