{
  "type": "Feature",
  "properties": {
    "iso:country":"US",
    "sg:address":"838 Cortlandt St",
    "sg:city":"Houston",
    "sg:classifiers":[
        {
            "category":"Professional",
            "subcategory":"Art Services",
            "type":"Services"
        }
    ],
    "sg:phone":"+1 713 864 7450",
    "sg:postcode":"77007",
    "sg:province":"TX",
    "sg:tags":[
        "photography",
        "commercial"
    ],
    "wof:name":"John Henry Childs Photography",
    "wof:placetype":"venue"
},
  "geometry": {"coordinates":[-95.395156,29.786329],"type":"Point"}
}