{
  "type": "Feature",
  "properties": {
    "iso:country":"US",
    "sg:address":"2925 Keller Springs Rd",
    "sg:city":"Carrollton",
    "sg:classifiers":[
        {
            "category":"Real Estate",
            "subcategory":"Real Estate Operator",
            "type":"Services"
        }
    ],
    "sg:phone":"+1 972 418 6259",
    "sg:postcode":"75006",
    "sg:province":"TX",
    "sg:tags":[
        "apartment"
    ],
    "wof:name":"Spicewood Crossing Apartments",
    "wof:placetype":"venue"
},
  "geometry": {"coordinates":[-96.853528,32.971316],"type":"Point"}
}