{
  "type": "Feature",
  "properties": {
    "iso:country":"US",
    "sg:address":"13909 Skyview Dr",
    "sg:city":"Sugar Land",
    "sg:classifiers":[
        {
            "category":"Health Services",
            "subcategory":"Nursing And Care Facility",
            "type":"Services"
        }
    ],
    "sg:phone":"+1 281 491 7440",
    "sg:postcode":"77478",
    "sg:province":"TX",
    "sg:tags":[
        "adult"
    ],
    "wof:name":"A Country Place Rsdndl Care Hm",
    "wof:placetype":"venue"
},
  "geometry": {"coordinates":[-95.630453,29.65261],"type":"Point"}
}