{
  "type": "Feature",
  "properties": {
    "iso:country":"US",
    "sg:address":"4040 State Hwy 6 S",
    "sg:city":"College Station",
    "sg:classifiers":[
        {
            "category":"Shopping",
            "subcategory":"Bicycles & Sporting Goods",
            "type":"Retail Goods"
        }
    ],
    "sg:phone":"+1 979 690 9888",
    "sg:postcode":"77845",
    "sg:province":"TX",
    "sg:tags":[
        "equipment",
        "playground"
    ],
    "wof:name":"Rainbow Play Systems",
    "wof:placetype":"venue"
},
  "geometry": {"coordinates":[-96.283992,30.581961],"type":"Point"}
}