{
  "type": "Feature",
  "properties": {
    "iso:country":"US",
    "sg:address":"234 Sunset Ridge Dr",
    "sg:city":"League City",
    "sg:classifiers":[
        {
            "category":"Manufacturing",
            "subcategory":"Soap",
            "type":"Manufacturing & Wholesale Goods"
        }
    ],
    "sg:phone":"+1 281 507 7306",
    "sg:postcode":"77573",
    "sg:province":"TX",
    "sg:tags":[
        "detergent"
    ],
    "wof:name":"Chem Services",
    "wof:placetype":"venue"
},
  "geometry": {"coordinates":[-95.041613,29.538666],"type":"Point"}
}