{
  "type": "Feature",
  "properties": {
    "iso:country":"US",
    "sg:address":"1230 Northwest Hwy",
    "sg:city":"Garland",
    "sg:classifiers":[
        {
            "category":"Professional",
            "subcategory":"Computer Services",
            "type":"Services"
        }
    ],
    "sg:phone":"+1 972 877 3873",
    "sg:postcode":"75041",
    "sg:province":"TX",
    "sg:tags":[
        "consulting"
    ],
    "wof:name":"Apollo Cabling Services Inc",
    "wof:placetype":"venue"
},
  "geometry": {"coordinates":[-96.644065,32.86229],"type":"Point"}
}