{
  "type": "Feature",
  "properties": {
    "iso:country":"US",
    "sg:address":"511 N Central Expy",
    "sg:city":"Mc Kinney",
    "sg:classifiers":[
        {
            "category":"Home & Garden",
            "subcategory":"Building Materials",
            "type":"Retail Goods"
        }
    ],
    "sg:phone":"+1 469 952 5180",
    "sg:postcode":"75070",
    "sg:province":"TX",
    "sg:tags":[
        "glass",
        "window",
        "plate"
    ],
    "wof:name":"Smokin Glass Works",
    "wof:placetype":"venue"
},
  "geometry": {"coordinates":[-96.639293,33.2004],"type":"Point"}
}