{
  "type": "Feature",
  "properties": {
    "iso:country":"US",
    "sg:address":"7676 Hillmont St",
    "sg:city":"Houston",
    "sg:classifiers":[
        {
            "category":"Professional",
            "subcategory":"Accounting & Tax Preparation",
            "type":"Services"
        }
    ],
    "sg:phone":"+1 713 461 6646",
    "sg:postcode":"77040",
    "sg:province":"TX",
    "sg:tags":[
        "billing"
    ],
    "wof:name":"Network Professional Billing",
    "wof:placetype":"venue"
},
  "geometry": {"coordinates":[-95.50558700000001,29.843719],"type":"Point"}
}