{
  "type": "Feature",
  "properties": {
    "iso:country":"US",
    "sg:address":"1006 Magoffin Ave",
    "sg:city":"El Paso",
    "sg:classifiers":[
        {
            "category":"Professional",
            "subcategory":"Lawyer & Legal Services",
            "type":"Services"
        }
    ],
    "sg:phone":"+1 915 544 1088",
    "sg:postcode":"79901",
    "sg:province":"TX",
    "sg:tags":[
        "attorney",
        "practice",
        "general"
    ],
    "wof:name":"Law Office of Charles McDonald",
    "wof:placetype":"venue"
},
  "geometry": {"coordinates":[-106.47872,31.761881],"type":"Point"}
}