{
  "type": "Feature",
  "properties": {
    "iso:country":"US",
    "sg:address":"1700 E 6th St",
    "sg:city":"Weslaco",
    "sg:classifiers":[
        {
            "category":"Freight",
            "type":"Transportation"
        }
    ],
    "sg:phone":"+1 956 968 8723",
    "sg:postcode":"78596",
    "sg:province":"TX",
    "sg:tags":[
        "special"
    ],
    "wof:name":"Dakm",
    "wof:placetype":"venue"
},
  "geometry": {"coordinates":[-97.972441,26.155583],"type":"Point"}
}