{
  "type": "Feature",
  "properties": {
    "iso:country":"US",
    "sg:address":"404 Van Dyck Dr",
    "sg:city":"Temple",
    "sg:classifiers":[
        {
            "category":"Autos & Motor Vehicles",
            "subcategory":"Fuel & Gas Station",
            "type":"Retail Goods"
        }
    ],
    "sg:phone":"+1 254 778 0207",
    "sg:postcode":"76504",
    "sg:province":"TX",
    "sg:tags":[
        "oil"
    ],
    "wof:name":"Diamond Shamrock",
    "wof:placetype":"venue"
},
  "geometry": {"coordinates":[-97.36805,31.108935],"type":"Point"}
}