{
  "type": "Feature",
  "properties": {
    "iso:country":"US",
    "sg:address":"441 US Hwy 80 E",
    "sg:city":"Mesquite",
    "sg:classifiers":[
        {
            "category":"Building & Trades",
            "subcategory":"Construction",
            "type":"Services"
        }
    ],
    "sg:phone":"+1 972 203 1700",
    "sg:postcode":"75149",
    "sg:province":"TX",
    "sg:tags":[
        "utility",
        "contractor"
    ],
    "wof:name":"Gar-Tex Construction Co",
    "wof:placetype":"venue"
},
  "geometry": {"coordinates":[-96.600481,32.790935],"type":"Point"}
}