{
  "type": "Feature",
  "properties": {
    "iso:country":"US",
    "sg:address":"2514 82nd St",
    "sg:city":"Lubbock",
    "sg:classifiers":[
        {
            "category":"Real Estate",
            "subcategory":"Real Estate Services",
            "type":"Services"
        },
        {
            "category":"Real Estate",
            "subcategory":"Real Estate Agent",
            "type":"Services"
        }
    ],
    "sg:phone":"+1 806 748 8100",
    "sg:postcode":"79423",
    "sg:province":"TX",
    "sg:tags":[
        "management"
    ],
    "wof:name":"Medical Capital Recovery Inc",
    "wof:placetype":"venue"
},
  "geometry": {"coordinates":[-101.87206399999999,33.519774],"type":"Point"}
}