{
  "type": "Feature",
  "properties": {
    "iso:country":"US",
    "sg:address":"3901 Shoal Creek Blvd",
    "sg:city":"Austin",
    "sg:classifiers":[
        {
            "category":"Organizations",
            "subcategory":"Religious Organization",
            "type":"Services"
        }
    ],
    "sg:phone":"+1 512 454 6806",
    "sg:postcode":"78756",
    "sg:province":"TX",
    "sg:tags":[
        "jewish"
    ],
    "wof:name":"Temple Beth Israel",
    "wof:placetype":"venue"
},
  "geometry": {"coordinates":[-97.74748700000001,30.307228],"type":"Point"}
}