{
  "type": "Feature",
  "properties": {
    "iso:country":"US",
    "sg:address":"1201 Payton Gin Rd",
    "sg:city":"Austin",
    "sg:classifiers":[
        {
            "category":"Education",
            "subcategory":"School",
            "type":"Public Place"
        }
    ],
    "sg:phone":"+1 512 414 2514",
    "sg:postcode":"78758",
    "sg:province":"TX",
    "sg:tags":[
        "high"
    ],
    "sg:website":"http://www.austin.isd.tenet.edu",
    "wof:name":"Lanier High School",
    "wof:placetype":"venue"
},
  "geometry": {"coordinates":[-97.709228,30.361815],"type":"Point"}
}