{
  "type": "Feature",
  "properties": {
    "iso:country":"US",
    "sg:address":"2440 Presidential Pkwy",
    "sg:city":"Midlothian",
    "sg:classifiers":[
        {
            "category":"Restaurant",
            "type":"Food & Drink"
        }
    ],
    "sg:menulink":"http://www.allmenus.com/tx/midlothian/157346-whataburger/menu/",
    "sg:phone":"+1 972 775 2480",
    "sg:postcode":"76065",
    "sg:province":"TX",
    "sg:tags":[
        "burger",
        "american"
    ],
    "wof:name":"Whataburger",
    "wof:placetype":"venue"
},
  "geometry": {"coordinates":[-96.937099,32.457163],"type":"Point"}
}