{
  "type": "Feature",
  "properties": {
    "iso:country":"US",
    "sg:address":"3906 Waldo St",
    "sg:city":"Houston",
    "sg:classifiers":[
        {
            "category":"Building & Trades",
            "subcategory":"Construction",
            "type":"Services"
        }
    ],
    "sg:phone":"+1 713 334 1808",
    "sg:postcode":"77063",
    "sg:province":"TX",
    "sg:tags":[
        "woodworker"
    ],
    "wof:name":"Legacy Custom Woodwork",
    "wof:placetype":"venue"
},
  "geometry": {"coordinates":[-95.527541,29.722627],"type":"Point"}
}