{
  "type": "Feature",
  "properties": {
    "iso:country":"US",
    "sg:address":"6210 Stable Point Dr",
    "sg:city":"San Antonio",
    "sg:classifiers":[
        {
            "category":"Professional",
            "subcategory":"Management & Consulting",
            "type":"Services"
        }
    ],
    "sg:phone":"+1 210 348 6212",
    "sg:postcode":"78249",
    "sg:province":"TX",
    "sg:tags":[
        "business"
    ],
    "wof:name":"Tri Lin Integrated Servic",
    "wof:placetype":"venue"
},
  "geometry": {"coordinates":[-98.610254,29.561955],"type":"Point"}
}