{
  "type": "Feature",
  "properties": {
    "iso:country":"US",
    "sg:address":"507 W Lake St",
    "sg:city":"Jefferson",
    "sg:classifiers":[
        {
            "category":"Professional",
            "subcategory":"Management & Consulting",
            "type":"Services"
        }
    ],
    "sg:phone":"+1 903 665 2135",
    "sg:postcode":"75657",
    "sg:province":"TX",
    "sg:tags":[
        "business"
    ],
    "wof:name":"Creative Memories Consultant",
    "wof:placetype":"venue"
},
  "geometry": {"coordinates":[-94.347165,32.753143],"type":"Point"}
}