{
  "type": "Feature",
  "properties": {
    "iso:country":"US",
    "sg:address":"218 N Camp St",
    "sg:city":"Seguin",
    "sg:classifiers":[
        {
            "category":"Insurance",
            "subcategory":"Insurance Agent",
            "type":"Services"
        }
    ],
    "sg:phone":"+1 830 303 0365",
    "sg:postcode":"78155",
    "sg:province":"TX",
    "wof:name":"Alvin B Duffey Insurance and F",
    "wof:placetype":"venue"
},
  "geometry": {"coordinates":[-97.965563,29.570013],"type":"Point"}
}