{
  "type": "Feature",
  "properties": {
    "iso:country":"US",
    "sg:address":"2208 Dallas Pkwy Ste 310",
    "sg:city":"Plano",
    "sg:classifiers":[
        {
            "category":"Shopping",
            "subcategory":"Mobile Phones",
            "type":"Retail Goods"
        }
    ],
    "sg:phone":"+1 972 403 3277",
    "sg:postcode":"75093",
    "sg:province":"TX",
    "wof:name":"Verizon Wireless",
    "wof:placetype":"venue"
},
  "geometry": {"coordinates":[-96.828796,33.030499],"type":"Point"}
}