{
  "type": "Feature",
  "properties": {
    "iso:country":"US",
    "sg:address":"7613 Westheimer Rd",
    "sg:city":"Houston",
    "sg:classifiers":[
        {
            "category":"Manufacturing",
            "subcategory":"Tools & Machinery",
            "type":"Manufacturing & Wholesale Goods"
        }
    ],
    "sg:phone":"+1 713 334 0199",
    "sg:postcode":"77063",
    "sg:province":"TX",
    "sg:tags":[
        "mfg",
        "cleaners",
        "household",
        "appliance",
        "vacuum",
        "home"
    ],
    "wof:name":"Hoover Company The",
    "wof:placetype":"venue"
},
  "geometry": {"coordinates":[-95.50278,29.737444],"type":"Point"}
}