{
  "type": "Feature",
  "properties": {
    "iso:country":"US",
    "sg:address":"10325 Denton Dr Ste C",
    "sg:city":"Dallas",
    "sg:classifiers":[
        {
            "category":"Autos & Motor Vehicles",
            "subcategory":"Automobile Sales",
            "type":"Retail Goods"
        }
    ],
    "sg:phone":"+1 214 489 3369",
    "sg:postcode":"75220",
    "sg:province":"TX",
    "sg:tags":[
        "new",
        "car"
    ],
    "wof:name":"Only Import Auto Sales",
    "wof:placetype":"venue"
},
  "geometry": {"coordinates":[-96.87893800000001,32.863612],"type":"Point"}
}