{
  "type": "Feature",
  "properties": {
    "iso:country":"US",
    "sg:address":"1114 Center Ave",
    "sg:city":"Brownwood",
    "sg:classifiers":[
        {
            "category":"Organizations",
            "subcategory":"Non-profit Organization",
            "type":"Services"
        }
    ],
    "sg:phone":"+1 325 641 0533",
    "sg:postcode":"76801",
    "sg:province":"TX",
    "wof:name":"Keep Brownswood Beautiful",
    "wof:placetype":"venue"
},
  "geometry": {"coordinates":[-98.98657,31.716549],"type":"Point"}
}