{
  "type": "Feature",
  "properties": {
    "iso:country":"US",
    "sg:address":"3009 Miller Pl",
    "sg:city":"Mesquite",
    "sg:classifiers":[
        {
            "category":"Professional",
            "type":"Services"
        }
    ],
    "sg:phone":"+1 972 681 3907",
    "sg:postcode":"75150",
    "sg:province":"TX",
    "wof:name":"Domingo Telly Llamas",
    "wof:placetype":"venue"
},
  "geometry": {"coordinates":[-96.64354400000001,32.806838],"type":"Point"}
}