{
  "type": "Feature",
  "properties": {
    "iso:country":"US",
    "sg:address":"10609 Ames Ln",
    "sg:city":"Austin",
    "sg:classifiers":[
        {
            "category":"Professional",
            "type":"Services"
        }
    ],
    "sg:phone":"+1 512 301 5115",
    "sg:postcode":"78739",
    "sg:province":"TX",
    "wof:name":"Georgia P Zunker",
    "wof:placetype":"venue"
},
  "geometry": {"coordinates":[-97.890523,30.193687],"type":"Point"}
}