{
  "type": "Feature",
  "properties": {
    "iso:country":"US",
    "sg:address":"8322 Dunlap St",
    "sg:city":"Houston",
    "sg:classifiers":[
        {
            "category":"Building & Trades",
            "subcategory":"Construction",
            "type":"Services"
        }
    ],
    "sg:phone":"+1 713 270 5661",
    "sg:postcode":"77074",
    "sg:province":"TX",
    "sg:tags":[
        "concrete",
        "contractor"
    ],
    "wof:name":"Area Foundation Repair",
    "wof:placetype":"venue"
},
  "geometry": {"coordinates":[-95.49444699999999,29.688561],"type":"Point"}
}