{
  "type": "Feature",
  "properties": {
    "iso:country":"US",
    "sg:address":"4523 Rodeo Ln",
    "sg:city":"Laredo",
    "sg:classifiers":[
        {
            "category":"Shopping",
            "subcategory":"Used Merchandise",
            "type":"Retail Goods"
        }
    ],
    "sg:phone":"+1 956 727 3381",
    "sg:postcode":"78046",
    "sg:province":"TX",
    "wof:name":"E Garcia Anselma",
    "wof:placetype":"venue"
},
  "geometry": {"coordinates":[-99.469049,27.450817],"type":"Point"}
}