{
  "type": "Feature",
  "properties": {
    "iso:country":"US",
    "sg:address":"14940 Webb Chapel Rd",
    "sg:city":"Dallas",
    "sg:classifiers":[
        {
            "category":"Donuts",
            "subcategory":"None",
            "type":"Food & Drink"
        }
    ],
    "sg:phone":"+1 972 243 2194",
    "sg:postcode":"75234",
    "sg:province":"TX",
    "wof:name":"Country Style Donuts",
    "wof:placetype":"venue"
},
  "geometry": {"coordinates":[-96.870543,32.953013],"type":"Point"}
}