{
  "type": "Feature",
  "properties": {
    "iso:country":"US",
    "sg:address":"505 E 3rd St",
    "sg:city":"Lampasas",
    "sg:classifiers":[
        {
            "category":"Health Services",
            "subcategory":"Clinic",
            "type":"Services"
        },
        {
            "category":"Health Services",
            "subcategory":"Nursing And Care Facility",
            "type":"Services"
        },
        {
            "category":"Health Services",
            "subcategory":"Health Practitioner",
            "type":"Services"
        }
    ],
    "sg:phone":"+1 512 556 8295",
    "sg:postcode":"76550",
    "sg:province":"TX",
    "sg:tags":[
        "home",
        "medical",
        "eldercare-home"
    ],
    "wof:name":"Hill Country Health Services Inc.",
    "wof:placetype":"venue"
},
  "geometry": {"coordinates":[-98.178212,31.065913],"type":"Point"}
}