{
  "type": "Feature",
  "properties": {
    "iso:country":"US",
    "sg:address":"605 E Virginia St",
    "sg:city":"Mc Kinney",
    "sg:classifiers":[
        {
            "category":"Building & Trades",
            "subcategory":"Landscaping Services",
            "type":"Services"
        }
    ],
    "sg:phone":"+1 972 562 7600",
    "sg:postcode":"75069",
    "sg:province":"TX",
    "sg:tags":[
        "landscape",
        "contractor"
    ],
    "wof:name":"J & J Landscape & Irrigation",
    "wof:placetype":"venue"
},
  "geometry": {"coordinates":[-96.609353,33.198056],"type":"Point"}
}