{
  "type": "Feature",
  "properties": {
    "iso:country":"US",
    "sg:address":"4071 Beechwood Ln",
    "sg:city":"Dallas",
    "sg:classifiers":[
        {
            "category":"Professional",
            "subcategory":"Business Services",
            "type":"Services"
        }
    ],
    "sg:phone":"+1 214 956 7030",
    "sg:postcode":"75220",
    "sg:province":"TX",
    "wof:name":"Enterprises L Pendergraft",
    "wof:placetype":"venue"
},
  "geometry": {"coordinates":[-96.844841,32.876259],"type":"Point"}
}