{
  "type": "Feature",
  "properties": {
    "iso:country":"US",
    "sg:address":"1623 E Waco Ave",
    "sg:city":"Dallas",
    "sg:classifiers":[
        {
            "category":"Shopping",
            "subcategory":"Clothing, Apparel, & Fashions",
            "type":"Retail Goods"
        }
    ],
    "sg:phone":"+1 214 941 3060",
    "sg:postcode":"75216",
    "sg:province":"TX",
    "wof:name":"Geminis Gifts & Jewelry",
    "wof:placetype":"venue"
},
  "geometry": {"coordinates":[-96.799817,32.737771],"type":"Point"}
}