{
  "type": "Feature",
  "properties": {
    "iso:country":"US",
    "sg:address":"107 Bud Dr",
    "sg:city":"Waco",
    "sg:classifiers":[
        {
            "category":"Wholesale",
            "subcategory":"Toys & Hobbies",
            "type":"Manufacturing & Wholesale Goods"
        }
    ],
    "sg:phone":"+1 254 867 8367",
    "sg:postcode":"76705",
    "sg:province":"TX",
    "sg:tags":[
        "firework"
    ],
    "wof:name":"American Fireworks",
    "wof:placetype":"venue"
},
  "geometry": {"coordinates":[-97.09977600000001,31.612373],"type":"Point"}
}