{
  "type": "Feature",
  "properties": {
    "iso:country":"US",
    "sg:address":"311 Randy Lee Ln",
    "sg:city":"Mc Kinney",
    "sg:classifiers":[
        {
            "category":"Health Services",
            "subcategory":"Doctor",
            "type":"Services"
        }
    ],
    "sg:phone":"+1 972 548 7675",
    "sg:postcode":"75071",
    "sg:province":"TX",
    "wof:name":"William M Smith",
    "wof:placetype":"venue"
},
  "geometry": {"coordinates":[-96.643653,33.203449],"type":"Point"}
}