{
  "type": "Feature",
  "properties": {
    "iso:country":"US",
    "sg:address":"11106 Broken Sky Dr",
    "sg:city":"Houston",
    "sg:classifiers":[
        {
            "category":"Wholesale",
            "subcategory":"Vending Machines",
            "type":"Manufacturing & Wholesale Goods"
        }
    ],
    "sg:phone":"+1 281 469 0281",
    "sg:postcode":"77064",
    "sg:province":"TX",
    "sg:tags":[
        "operator"
    ],
    "wof:name":"Hartline Vending",
    "wof:placetype":"venue"
},
  "geometry": {"coordinates":[-95.56909899999999,29.930467],"type":"Point"}
}