{
  "type": "Feature",
  "properties": {
    "iso:country":"US",
    "sg:address":"6101 Callaghan Rd",
    "sg:city":"San Antonio",
    "sg:classifiers":[
        {
            "category":"Food & Beverages",
            "subcategory":"Specialty",
            "type":"Retail Goods"
        }
    ],
    "sg:phone":"+1 210 684 4561",
    "sg:postcode":"78228",
    "sg:province":"TX",
    "wof:name":"La Familia Hlth Snacks & More",
    "wof:placetype":"venue"
},
  "geometry": {"coordinates":[-98.57663100000001,29.487102],"type":"Point"}
}