{
  "type": "Feature",
  "properties": {
    "iso:country":"US",
    "sg:address":"1805 Ave Q",
    "sg:city":"Huntsville",
    "sg:classifiers":[
        {
            "category":"Education",
            "subcategory":"Dance Studio",
            "type":"Public Place"
        }
    ],
    "sg:phone":"+1 936 295 5514",
    "sg:postcode":"77340",
    "sg:province":"TX",
    "wof:name":"Faye Burns Dance Studio",
    "wof:placetype":"venue"
},
  "geometry": {"coordinates":[-95.559209,30.715025],"type":"Point"}
}