{
  "type": "Feature",
  "properties": {
    "iso:country":"US",
    "sg:address":"8204 Co Rd 285",
    "sg:city":"Anna",
    "sg:classifiers":[
        {
            "category":"Wholesale",
            "subcategory":"Durable Goods & Equipment",
            "type":"Manufacturing & Wholesale Goods"
        }
    ],
    "sg:phone":"+1 972 924 3414",
    "sg:postcode":"75409",
    "sg:province":"TX",
    "wof:name":"Wilkins Co",
    "wof:placetype":"venue"
},
  "geometry": {"coordinates":[-96.627152,33.337395],"type":"Point"}
}