{
  "type": "Feature",
  "properties": {
    "iso:country":"US",
    "sg:address":"12500 Normandy Crossing Dr",
    "sg:city":"Houston",
    "sg:classifiers":[
        {
            "category":"Education",
            "subcategory":"School",
            "type":"Public Place"
        }
    ],
    "sg:phone":"+1 832 386 1600",
    "sg:postcode":"77015",
    "sg:province":"TX",
    "sg:tags":[
        "high",
        "middle",
        "elementary"
    ],
    "wof:name":"Schools",
    "wof:placetype":"venue"
},
  "geometry": {"coordinates":[-95.208101,29.781032],"type":"Point"}
}