{
  "type": "Feature",
  "properties": {
    "iso:country":"US",
    "sg:address":"7719 Homestead Rd",
    "sg:city":"Houston",
    "sg:classifiers":[
        {
            "category":"Restaurant",
            "type":"Food & Drink"
        }
    ],
    "sg:phone":"+1 713 635 7380",
    "sg:postcode":"77028",
    "sg:province":"TX",
    "sg:tags":[
        "cajun/creole"
    ],
    "wof:name":"J.W.'s Original Cajun Boudin Hut",
    "wof:placetype":"venue"
},
  "geometry": {"coordinates":[-95.30210099999999,29.8325],"type":"Point"}
}