{
  "type": "Feature",
  "properties": {
    "iso:country":"US",
    "sg:address":"113 Industrial Blvd",
    "sg:city":"Austin",
    "sg:classifiers":[
        {
            "category":"Building & Trades",
            "subcategory":"Landscaping Services",
            "type":"Services"
        }
    ],
    "sg:phone":"+1 512 442 2204",
    "sg:postcode":"78745",
    "sg:province":"TX",
    "wof:name":"Total Landscape",
    "wof:placetype":"venue"
},
  "geometry": {"coordinates":[-97.762407,30.218783],"type":"Point"}
}