{
  "type": "Feature",
  "properties": {
    "iso:country":"US",
    "sg:address":"1043 N Pacific St",
    "sg:city":"Mineola",
    "sg:classifiers":[
        {
            "category":"Personal",
            "subcategory":"Beauty Salon",
            "type":"Services"
        }
    ],
    "sg:phone":"+1 903 569 6760",
    "sg:postcode":"75773",
    "sg:province":"TX",
    "sg:tags":[
        "manicuring"
    ],
    "wof:name":"Super Nails",
    "wof:placetype":"venue"
},
  "geometry": {"coordinates":[-95.485399,32.672452],"type":"Point"}
}