{
  "type": "Feature",
  "properties": {
    "iso:country":"US",
    "sg:address":"420 W Bandera Rd",
    "sg:city":"Boerne",
    "sg:classifiers":[
        {
            "category":"Restaurant",
            "type":"Food & Drink"
        }
    ],
    "sg:phone":"+1 830 249 2990",
    "sg:postcode":"78006",
    "sg:province":"TX",
    "sg:tags":[
        "eating"
    ],
    "wof:name":"China Town Cafe",
    "wof:placetype":"venue"
},
  "geometry": {"coordinates":[-98.736053,29.780529],"type":"Point"}
}