{
  "type": "Feature",
  "properties": {
    "iso:country":"US",
    "sg:address":"420 S Bliss Ave",
    "sg:city":"Dumas",
    "sg:classifiers":[
        {
            "category":"Organizations",
            "subcategory":"Religious Organization",
            "type":"Services"
        }
    ],
    "sg:phone":"+1 806 935 5604",
    "sg:postcode":"79029",
    "sg:province":"TX",
    "sg:tags":[
        "church"
    ],
    "sg:website":"www.fbcdumas.org",
    "wof:name":"First Baptist Church",
    "wof:placetype":"venue"
},
  "geometry": {"coordinates":[-101.971914,35.861806],"type":"Point"}
}