{
  "type": "Feature",
  "properties": {
    "iso:country":"US",
    "sg:address":"602 Morgan Blvd",
    "sg:city":"Harlingen",
    "sg:classifiers":[
        {
            "category":"Social Services",
            "subcategory":"Child Care",
            "type":"Services"
        }
    ],
    "sg:phone":"+1 956 425 6330",
    "sg:postcode":"78550",
    "sg:province":"TX",
    "wof:name":"St Paul Lutheran Early Ctr",
    "wof:placetype":"venue"
},
  "geometry": {"coordinates":[-97.67864299999999,26.199697],"type":"Point"}
}