{
  "type": "Feature",
  "properties": {
    "iso:country":"US",
    "sg:address":"25 Highland Park Village",
    "sg:city":"Dallas",
    "sg:classifiers":[
        {
            "category":"Wholesale",
            "subcategory":"Apparel",
            "type":"Manufacturing & Wholesale Goods"
        },
        {
            "category":"Shopping",
            "subcategory":"Clothing, Apparel, & Fashions",
            "type":"Retail Goods"
        }
    ],
    "sg:phone":"+1 214 668 9255",
    "sg:postcode":"75205",
    "sg:province":"TX",
    "sg:tags":[
        "athletic",
        "corporate",
        "sportswear"
    ],
    "wof:name":"Calf Creek Enterprises",
    "wof:placetype":"venue"
},
  "geometry": {"coordinates":[-96.806248,32.836194],"type":"Point"}
}