{
  "type": "Feature",
  "properties": {
    "iso:country":"US",
    "sg:address":"134 N 8th St",
    "sg:city":"Midlothian",
    "sg:classifiers":[
        {
            "category":"Banks & Credit Unions",
            "subcategory":"Bank",
            "type":"Services"
        }
    ],
    "sg:phone":"+1 972 723 6025",
    "sg:postcode":"76065",
    "sg:province":"TX",
    "sg:tags":[
        "mortgage"
    ],
    "wof:name":"Home Loan Corp",
    "wof:placetype":"venue"
},
  "geometry": {"coordinates":[-96.994433,32.482903],"type":"Point"}
}