{
  "type": "Feature",
  "properties": {
    "iso:country":"US",
    "sg:address":"9540 Richmond, Suite C",
    "sg:city":"Houston",
    "sg:classifiers":[
        {
            "category":"Restaurant",
            "type":"Food & Drink"
        }
    ],
    "sg:phone":"+1 713 783 7755",
    "sg:postcode":"77063",
    "sg:province":"TX",
    "sg:tags":[
        "vietnamese"
    ],
    "wof:name":"Pier Cafe",
    "wof:placetype":"venue"
},
  "geometry": {"coordinates":[-95.534188,29.729104],"type":"Point"}
}