{
  "type": "Feature",
  "properties": {
    "iso:country":"US",
    "sg:address":"333 Clay St Ste 4850",
    "sg:city":"Houston",
    "sg:classifiers":[
        {
            "category":"Professional",
            "subcategory":"Employment Agencies",
            "type":"Services"
        }
    ],
    "sg:phone":"+1 713 658 1855",
    "sg:postcode":"77002",
    "sg:province":"TX",
    "wof:name":"Officeteam",
    "wof:placetype":"venue"
},
  "geometry": {"coordinates":[-95.372704,29.7582],"type":"Point"}
}