{
  "type": "Feature",
  "properties": {
    "iso:country":"US",
    "sg:address":"616 W Duranta Ave",
    "sg:city":"Alamo",
    "sg:classifiers":[
        {
            "category":"Organizations",
            "subcategory":"Religious Organization",
            "type":"Services"
        }
    ],
    "sg:phone":"+1 956 783 2480",
    "sg:postcode":"78516",
    "sg:province":"TX",
    "sg:tags":[
        "church"
    ],
    "wof:name":"El Buen Pastor",
    "wof:placetype":"venue"
},
  "geometry": {"coordinates":[-98.113041,26.187627],"type":"Point"}
}