{
  "type": "Feature",
  "properties": {
    "iso:country":"US",
    "sg:address":"8625 Old Hwy 87",
    "sg:city":"Orange",
    "sg:classifiers":[
        {
            "category":"Retail",
            "subcategory":"Auto Rental",
            "type":"Services"
        }
    ],
    "sg:phone":"+1 409 746 9269",
    "sg:postcode":"77630",
    "sg:province":"TX",
    "sg:tags":[
        "renting",
        "truck",
        "leasing"
    ],
    "wof:name":"U-Haul Co",
    "wof:placetype":"venue"
},
  "geometry": {"coordinates":[-93.754954,30.185654],"type":"Point"}
}