{
  "type": "Feature",
  "properties": {
    "iso:country":"US",
    "sg:address":"6640 Waterbury Dr",
    "sg:city":"Frisco",
    "sg:classifiers":[
        {
            "category":"Professional",
            "type":"Services"
        }
    ],
    "sg:phone":"+1 972 712 4399",
    "sg:postcode":"75035",
    "sg:province":"TX",
    "wof:name":"Sankyo Pharma",
    "wof:placetype":"venue"
},
  "geometry": {"coordinates":[-96.78236099999999,33.133324],"type":"Point"}
}