{
  "type": "Feature",
  "properties": {
    "iso:country":"US",
    "sg:address":"8200 Bagby Dr",
    "sg:city":"Austin",
    "sg:classifiers":[
        {
            "category":"Freight",
            "type":"Transportation"
        }
    ],
    "sg:phone":"+1 512 926 8531",
    "sg:postcode":"78724",
    "sg:province":"TX",
    "sg:tags":[
        "mover",
        "trucking"
    ],
    "sg:website":"www.abf.com",
    "wof:name":"Abf Freight System",
    "wof:placetype":"venue"
},
  "geometry": {"coordinates":[-97.631928,30.289542],"type":"Point"}
}