{
  "type": "Feature",
  "properties": {
    "iso:country":"US",
    "sg:address":"4502 Walzem Rd",
    "sg:city":"San Antonio",
    "sg:classifiers":[
        {
            "category":"Home & Garden",
            "subcategory":"Household Appliances",
            "type":"Retail Goods"
        }
    ],
    "sg:phone":"+1 210 590 2044",
    "sg:postcode":"78218",
    "sg:province":"TX",
    "sg:tags":[
        "cleaners",
        "vacuum"
    ],
    "wof:name":"Kirby Co",
    "wof:placetype":"venue"
},
  "geometry": {"coordinates":[-98.40302200000001,29.510231],"type":"Point"}
}