{
  "type": "Feature",
  "properties": {
    "iso:country":"US",
    "sg:address":"1985 State Hwy 79",
    "sg:city":"Wichita Falls",
    "sg:classifiers":[
        {
            "category":"Building & Trades",
            "subcategory":"Construction",
            "type":"Services"
        }
    ],
    "sg:phone":"+1 940 766 4128",
    "sg:postcode":"76305",
    "sg:province":"TX",
    "sg:tags":[
        "house"
    ],
    "wof:name":"Hanson Home Improvements",
    "wof:placetype":"venue"
},
  "geometry": {"coordinates":[-98.43606,33.905861],"type":"Point"}
}