{
  "type": "Feature",
  "properties": {
    "iso:country":"US",
    "sg:address":"5221 Gates Dr",
    "sg:city":"Lewisville",
    "sg:classifiers":[
        {
            "category":"Manufacturing",
            "subcategory":"Tools & Machinery",
            "type":"Manufacturing & Wholesale Goods"
        }
    ],
    "sg:phone":"+1 972 977 5495",
    "sg:postcode":"75056",
    "sg:province":"TX",
    "sg:tags":[
        "lamp",
        "electric",
        "mfg"
    ],
    "wof:name":"Barllani",
    "wof:placetype":"venue"
},
  "geometry": {"coordinates":[-96.877289,33.095181],"type":"Point"}
}