{
  "type": "Feature",
  "properties": {
    "iso:country":"US",
    "sg:address":"719 Sawdust Rd",
    "sg:city":"Spring",
    "sg:classifiers":[
        {
            "category":"Insurance",
            "subcategory":"Insurance Agent",
            "type":"Services"
        }
    ],
    "sg:phone":"+1 281 367 3424",
    "sg:postcode":"77380",
    "sg:province":"TX",
    "wof:name":"Anico",
    "wof:placetype":"venue"
},
  "geometry": {"coordinates":[-95.456928,30.126695],"type":"Point"}
}