{
  "type": "Feature",
  "properties": {
    "iso:country":"US",
    "sg:address":"4125 N 31st St",
    "sg:city":"Waco",
    "sg:classifiers":[
        {
            "category":"Professional",
            "type":"Services"
        },
        {
            "category":"Professional",
            "subcategory":"Business Services",
            "type":"Services"
        }
    ],
    "sg:phone":"+1 254 752 8005",
    "sg:postcode":"76708",
    "sg:province":"TX",
    "sg:tags":[
        "communications",
        "telephone"
    ],
    "wof:name":"J & J Communications",
    "wof:placetype":"venue"
},
  "geometry": {"coordinates":[-97.187372,31.576539],"type":"Point"}
}