{
  "type": "Feature",
  "properties": {
    "iso:country":"US",
    "sg:address":"3219 Canyon Links Dr",
    "sg:city":"Katy",
    "sg:classifiers":[
        {
            "category":"Professional",
            "subcategory":"Business Services",
            "type":"Services"
        }
    ],
    "sg:phone":"+1 281 599 9818",
    "sg:postcode":"77450",
    "sg:province":"TX",
    "wof:name":"Seidel Group LLC",
    "wof:placetype":"venue"
},
  "geometry": {"coordinates":[-95.746279,29.736504],"type":"Point"}
}