{
  "type": "Feature",
  "properties": {
    "iso:country":"US",
    "sg:address":"2008 Riverview St",
    "sg:city":"Austin",
    "sg:classifiers":[
        {
            "category":"Home & Garden",
            "subcategory":"Garden Supply",
            "type":"Retail Goods"
        }
    ],
    "sg:phone":"+1 512 212 1294",
    "sg:postcode":"78702",
    "sg:province":"TX",
    "sg:tags":[
        "nursery",
        "gardening"
    ],
    "sg:website":"www.MINIM.IS",
    "wof:name":"MINIMIS",
    "wof:placetype":"venue"
},
  "geometry": {"coordinates":[-97.72500599999999,30.251167],"type":"Point"}
}