{
  "type": "Feature",
  "properties": {
    "iso:country":"US",
    "sg:address":"15455 Dallas Pkwy 6th floor",
    "sg:city":"Addison",
    "sg:classifiers":[
        {
            "category":"Transit Center",
            "subcategory":"Passenger",
            "type":"Transportation"
        }
    ],
    "sg:phone":"+1 972 764 3563",
    "sg:postcode":"75001",
    "sg:province":"TX",
    "sg:website":"jetoptionsjetcharter.com",
    "wof:name":"JetOptions Private Jet Charter",
    "wof:placetype":"venue"
},
  "geometry": {"coordinates":[-96.821533,32.960169],"type":"Point"}
}