{
  "type": "Feature",
  "properties": {
    "iso:country":"US",
    "sg:address":"275 Wigington Ln",
    "sg:city":"Inez",
    "sg:classifiers":[
        {
            "category":"Professional",
            "subcategory":"Business Services",
            "type":"Services"
        }
    ],
    "sg:phone":"+1 361 575 0209",
    "sg:postcode":"77968",
    "sg:province":"TX",
    "wof:name":"Impact Promotions of Victoria",
    "wof:placetype":"venue"
},
  "geometry": {"coordinates":[-96.894183,28.908363],"type":"Point"}
}