{
  "type": "Feature",
  "properties": {
    "iso:country":"US",
    "sg:address":"3301 Sandy Ln",
    "sg:city":"Mcallen",
    "sg:classifiers":[
        {
            "category":"Professional",
            "subcategory":"Business Services",
            "type":"Services"
        }
    ],
    "sg:phone":"+1 956 631 5220",
    "sg:postcode":"78503",
    "sg:province":"TX",
    "wof:name":"Big Horn Ranch LLC",
    "wof:placetype":"venue"
},
  "geometry": {"coordinates":[-98.223834,26.168398],"type":"Point"}
}