{
  "type": "Feature",
  "properties": {
    "iso:country":"US",
    "sg:address":"516 Fritz Swanson Rd",
    "sg:city":"Kilgore",
    "sg:classifiers":[
        {
            "category":"Organizations",
            "subcategory":"Religious Organization",
            "type":"Services"
        }
    ],
    "sg:phone":"+1 903 984 2381",
    "sg:postcode":"75662",
    "sg:province":"TX",
    "sg:tags":[
        "church"
    ],
    "wof:name":"First Pentecostal Church",
    "wof:placetype":"venue"
},
  "geometry": {"coordinates":[-94.87885900000001,32.394565],"type":"Point"}
}