{
  "type": "Feature",
  "properties": {
    "iso:country":"US",
    "sg:address":"400 Callaghan St",
    "sg:city":"Laredo",
    "sg:classifiers":[
        {
            "category":"Education",
            "subcategory":"School",
            "type":"Public Place"
        }
    ],
    "sg:phone":"+1 956 722 3915",
    "sg:postcode":"78040",
    "sg:province":"TX",
    "sg:tags":[
        "organization",
        "religious"
    ],
    "wof:name":"Our Lady of Guadalupe School",
    "wof:placetype":"venue"
},
  "geometry": {"coordinates":[-99.50067900000001,27.514256],"type":"Point"}
}