{
  "type": "Feature",
  "properties": {
    "iso:country":"US",
    "sg:address":"9331 Highmeadow Dr",
    "sg:city":"Houston",
    "sg:classifiers":[
        {
            "category":"Shopping",
            "subcategory":"Jewelry",
            "type":"Retail Goods"
        }
    ],
    "sg:phone":"+1 713 953 1005",
    "sg:postcode":"77063",
    "sg:province":"TX",
    "sg:tags":[
        "jeweler"
    ],
    "wof:name":"Autumn L Davidson Jeweler",
    "wof:placetype":"venue"
},
  "geometry": {"coordinates":[-95.530914,29.734092],"type":"Point"}
}