{
  "type": "Feature",
  "properties": {
    "iso:country":"US",
    "sg:address":"305 9th St",
    "sg:city":"Terrell",
    "sg:classifiers":[
        {
            "category":"Food & Beverages",
            "subcategory":"Groceries & Convenience Stores",
            "type":"Retail Goods"
        }
    ],
    "sg:phone":"+1 972 563 5298",
    "sg:postcode":"75160",
    "sg:province":"TX",
    "wof:name":"Billy K Convenience Store",
    "wof:placetype":"venue"
},
  "geometry": {"coordinates":[-96.29075400000001,32.744213],"type":"Point"}
}