{
  "type": "Feature",
  "properties": {
    "iso:country":"US",
    "sg:address":"502 S 1st St",
    "sg:city":"Temple",
    "sg:classifiers":[
        {
            "category":"Wholesale",
            "subcategory":"Machinery & Supplies",
            "type":"Manufacturing & Wholesale Goods"
        }
    ],
    "sg:phone":"+1 254 770 1600",
    "sg:postcode":"76504",
    "sg:province":"TX",
    "sg:tags":[
        "carpet",
        "cleaning",
        "rug"
    ],
    "wof:name":"Biotech Analytical & Testing",
    "wof:placetype":"venue"
},
  "geometry": {"coordinates":[-97.344539,31.09102],"type":"Point"}
}