{
  "type": "Feature",
  "properties": {
    "iso:country":"US",
    "sg:address":"5629 Starlight Dr",
    "sg:city":"Fort Worth",
    "sg:classifiers":[
        {
            "category":"Professional",
            "type":"Services"
        }
    ],
    "sg:phone":"+1 817 281 2157",
    "sg:postcode":"76117",
    "sg:province":"TX",
    "wof:name":"Parrot Head Racing",
    "wof:placetype":"venue"
},
  "geometry": {"coordinates":[-97.25912,32.832034],"type":"Point"}
}