{
  "type": "Feature",
  "properties": {
    "iso:country":"US",
    "sg:address":"300 E 2nd St",
    "sg:city":"Monahans",
    "sg:classifiers":[
        {
            "category":"Professional",
            "subcategory":"Lawyer & Legal Services",
            "type":"Services"
        }
    ],
    "sg:phone":"+1 432 943 4590",
    "sg:postcode":"79756",
    "sg:province":"TX",
    "wof:name":"Upchurch Hal Atty At Law PC",
    "wof:placetype":"venue"
},
  "geometry": {"coordinates":[-102.889484,31.594488],"type":"Point"}
}