{
  "type": "Feature",
  "properties": {
    "iso:country":"US",
    "sg:address":"206 Hwy 332 W",
    "sg:city":"Lake Jackson",
    "sg:classifiers":[
        {
            "category":"Professional",
            "subcategory":"Lawyer & Legal Services",
            "type":"Services"
        }
    ],
    "sg:phone":"+1 979 480 9992",
    "sg:postcode":"77566",
    "sg:province":"TX",
    "sg:tags":[
        "attorney"
    ],
    "wof:name":"Brannan Law Office",
    "wof:placetype":"venue"
},
  "geometry": {"coordinates":[-95.466785,29.048389],"type":"Point"}
}