{
  "type": "Feature",
  "properties": {
    "iso:country":"US",
    "sg:address":"202 Pasadena Blvd",
    "sg:city":"Pasadena",
    "sg:classifiers":[
        {
            "category":"Autos & Motor Vehicles",
            "subcategory":"Auto Supplies",
            "type":"Retail Goods"
        }
    ],
    "sg:phone":"+1 713 473 5543",
    "sg:postcode":"77506",
    "sg:province":"TX",
    "sg:tags":[
        "automobile",
        "parts"
    ],
    "sg:website":"www.akela74sf.com",
    "wof:name":"Meineke Car Care Ctr",
    "wof:placetype":"venue"
},
  "geometry": {"coordinates":[-95.201308,29.710282],"type":"Point"}
}