{
  "type": "Feature",
  "properties": {
    "iso:country":"US",
    "sg:address":"217 Main St",
    "sg:city":"Garland",
    "sg:classifiers":[
        {
            "category":"Professional",
            "subcategory":"Engineering",
            "type":"Services"
        }
    ],
    "sg:phone":"+1 972 264 2780",
    "sg:postcode":"75040",
    "sg:province":"TX",
    "sg:tags":[
        "engineer"
    ],
    "wof:name":"Hudson Group",
    "wof:placetype":"venue"
},
  "geometry": {"coordinates":[-96.633782,32.912736],"type":"Point"}
}