{
  "type": "Feature",
  "properties": {
    "iso:country":"US",
    "sg:address":"6650 9th Ave",
    "sg:city":"Port Arthur",
    "sg:classifiers":[
        {
            "category":"Shopping",
            "subcategory":"Pharmacy",
            "type":"Retail Goods"
        }
    ],
    "sg:phone":"+1 409 960 6800",
    "sg:postcode":"77642",
    "sg:province":"TX",
    "wof:name":"Emergency Rx Resource",
    "wof:placetype":"venue"
},
  "geometry": {"coordinates":[-93.963915,29.938801],"type":"Point"}
}