{
  "type": "Feature",
  "properties": {
    "iso:country":"US",
    "sg:address":"5420 Gulfton St",
    "sg:city":"Houston",
    "sg:classifiers":[
        {
            "category":"Building & Trades",
            "subcategory":"Plumbing",
            "type":"Services"
        }
    ],
    "sg:phone":"+1 713 669 0099",
    "sg:postcode":"77081",
    "sg:province":"TX",
    "sg:tags":[
        "specializing",
        "co",
        "heating",
        "contractor",
        "ventilation",
        "air"
    ],
    "wof:name":"Schaffer Mechanical Inc",
    "wof:placetype":"venue"
},
  "geometry": {"coordinates":[-95.474093,29.716613],"type":"Point"}
}