{
  "type": "Feature",
  "properties": {
    "iso:country":"US",
    "sg:address":"721 Telephone Rd",
    "sg:city":"Houston",
    "sg:classifiers":[
        {
            "category":"Personal",
            "subcategory":"Barber",
            "type":"Services"
        }
    ],
    "sg:phone":"+1 713 924 5112",
    "sg:postcode":"77023",
    "sg:province":"TX",
    "sg:tags":[
        "shop"
    ],
    "wof:name":"Peluqueria Acapulco No 4",
    "wof:placetype":"venue"
},
  "geometry": {"coordinates":[-95.330399,29.734699],"type":"Point"}
}