{
  "type": "Feature",
  "properties": {
    "iso:country":"US",
    "sg:address":"7451 Dogwood Park",
    "sg:city":"Richland Hills",
    "sg:classifiers":[
        {
            "category":"Building & Trades",
            "subcategory":"Plumbing",
            "type":"Services"
        }
    ],
    "sg:phone":"+1 817 595 4809",
    "sg:postcode":"76118",
    "sg:province":"TX",
    "sg:tags":[
        "conditioning",
        "air",
        "system",
        "contractor"
    ],
    "wof:name":"Janitrol Distributors",
    "wof:placetype":"venue"
},
  "geometry": {"coordinates":[-97.21973699999999,32.804013],"type":"Point"}
}