{
  "type": "Feature",
  "properties": {
    "iso:country":"US",
    "sg:address":"3875 E Whitestone Blvd",
    "sg:city":"Cedar Park",
    "sg:classifiers":[
        {
            "category":"Home & Garden",
            "subcategory":"Garden Supply",
            "type":"Retail Goods"
        }
    ],
    "sg:phone":"+1 512 259 7430",
    "sg:postcode":"78613",
    "sg:province":"TX",
    "sg:tags":[
        "mulch"
    ],
    "sg:website":"www.austinwoodrecycling.com",
    "wof:name":"Austin Wood Recycling",
    "wof:placetype":"venue"
},
  "geometry": {"coordinates":[-97.772086,30.540426],"type":"Point"}
}