{
  "type": "Feature",
  "properties": {
    "iso:country":"US",
    "sg:address":"3001 Kemp Blvd",
    "sg:city":"Wichita Falls",
    "sg:classifiers":[
        {
            "category":"Professional",
            "subcategory":"Computer Services",
            "type":"Services"
        }
    ],
    "sg:phone":"+1 940 761 9794",
    "sg:postcode":"76308",
    "sg:province":"TX",
    "sg:website":"www.computerage.net",
    "wof:name":"Computerage Business Svc",
    "wof:placetype":"venue"
},
  "geometry": {"coordinates":[-98.528323,33.884269],"type":"Point"}
}