{
  "type": "Feature",
  "properties": {
    "iso:country":"US",
    "sg:address":"440 Tall Timbers St",
    "sg:city":"Lumberton",
    "sg:classifiers":[
        {
            "category":"Personal",
            "subcategory":"Beauty Salon",
            "type":"Services"
        }
    ],
    "sg:phone":"+1 409 755 3021",
    "sg:postcode":"77657",
    "sg:province":"TX",
    "sg:tags":[
        "shop"
    ],
    "wof:name":"Rhondas Nail Boutique",
    "wof:placetype":"venue"
},
  "geometry": {"coordinates":[-94.198504,30.260681],"type":"Point"}
}