{
  "type": "Feature",
  "properties": {
    "iso:country":"US",
    "sg:address":"1930 N 1st St",
    "sg:city":"Abilene",
    "sg:classifiers":[
        {
            "category":"Shopping",
            "subcategory":"Stationery & Office Supplies",
            "type":"Retail Goods"
        }
    ],
    "sg:phone":"+1 325 672 3982",
    "sg:postcode":"79603",
    "sg:province":"TX",
    "sg:tags":[
        "equipment",
        "filing",
        "system"
    ],
    "wof:name":"Barnhill Office Systems",
    "wof:placetype":"venue"
},
  "geometry": {"coordinates":[-99.745636,32.45022],"type":"Point"}
}