{
  "type": "Feature",
  "properties": {
    "iso:country":"US",
    "sg:address":"4430 Folsom Dr",
    "sg:city":"Beaumont",
    "sg:classifiers":[
        {
            "category":"Real Estate",
            "subcategory":"Architect",
            "type":"Services"
        }
    ],
    "sg:phone":"+1 409 892 4098",
    "sg:postcode":"77706",
    "sg:province":"TX",
    "sg:tags":[
        "architectural"
    ],
    "wof:name":"Gordy & Huffhines",
    "wof:placetype":"venue"
},
  "geometry": {"coordinates":[-94.153791,30.115098],"type":"Point"}
}