{
  "type": "Feature",
  "properties": {
    "iso:country":"US",
    "sg:address":"817 N Main St",
    "sg:city":"Gladewater",
    "sg:classifiers":[
        {
            "category":"Insurance",
            "subcategory":"Hazard Insurance",
            "type":"Services"
        }
    ],
    "sg:phone":"+1 903 845 2477",
    "sg:postcode":"75647",
    "sg:province":"TX",
    "sg:tags":[
        "commercial",
        "business"
    ],
    "sg:website":"http://statefarm.com",
    "wof:name":"Wells Harold R Ins",
    "wof:placetype":"venue"
},
  "geometry": {"coordinates":[-94.940583,32.540297],"type":"Point"}
}