{
  "type": "Feature",
  "properties": {
    "iso:country":"US",
    "sg:address":"230 W Elmview Pl",
    "sg:city":"San Antonio",
    "sg:classifiers":[
        {
            "category":"Manufacturing",
            "subcategory":"Printing",
            "type":"Manufacturing & Wholesale Goods"
        }
    ],
    "sg:phone":"+1 210 828 1839",
    "sg:postcode":"78209",
    "sg:province":"TX",
    "sg:tags":[
        "periodical"
    ],
    "wof:name":"Scene In SA Magazine",
    "wof:placetype":"venue"
},
  "geometry": {"coordinates":[-98.46942300000001,29.492869],"type":"Point"}
}