{
  "type": "Feature",
  "properties": {
    "iso:country":"US",
    "sg:address":"2200 W North Loop Blvd",
    "sg:city":"Austin",
    "sg:classifiers":[
        {
            "category":"Professional",
            "subcategory":"Secretarial Services",
            "type":"Services"
        }
    ],
    "sg:phone":"+1 512 451 6965",
    "sg:postcode":"78756",
    "sg:province":"TX",
    "sg:tags":[
        "reporting"
    ],
    "wof:name":"Lorco",
    "wof:placetype":"venue"
},
  "geometry": {"coordinates":[-97.742684,30.325491],"type":"Point"}
}