{
  "type": "Feature",
  "properties": {
    "iso:country":"US",
    "sg:address":"1201 Rd To Six Flags E",
    "sg:city":"Arlington",
    "sg:classifiers":[
        {
            "category":"Banks & Credit Unions",
            "subcategory":"Bank",
            "type":"Services"
        }
    ],
    "sg:phone":"+1 817 274 7240",
    "sg:postcode":"76011",
    "sg:province":"TX",
    "sg:tags":[
        "investment",
        "broker"
    ],
    "wof:name":"Dominion Financial Services",
    "wof:placetype":"venue"
},
  "geometry": {"coordinates":[-97.08866,32.755566],"type":"Point"}
}