{
  "type": "Feature",
  "properties": {
    "iso:country":"US",
    "sg:address":"8420 Hammerly Blvd",
    "sg:city":"Houston",
    "sg:classifiers":[
        {
            "category":"Autos & Motor Vehicles",
            "subcategory":"Automobile Sales",
            "type":"Retail Goods"
        }
    ],
    "sg:phone":"+1 713 461 7137",
    "sg:postcode":"77055",
    "sg:province":"TX",
    "sg:tags":[
        "car",
        "dealer"
    ],
    "wof:name":"Hammerly Auto",
    "wof:placetype":"venue"
},
  "geometry": {"coordinates":[-95.49789199999999,29.811063],"type":"Point"}
}