{
  "type": "Feature",
  "properties": {
    "iso:country":"US",
    "sg:address":"22766 Cypresswood Dr",
    "sg:city":"Spring",
    "sg:classifiers":[
        {
            "category":"Recreation",
            "type":"Entertainment"
        }
    ],
    "sg:phone":"+1 281 443 1015",
    "sg:postcode":"77373",
    "sg:province":"TX",
    "wof:name":"Martial Arts",
    "wof:placetype":"venue"
},
  "geometry": {"coordinates":[-95.345777,30.043981],"type":"Point"}
}