{
  "type": "Feature",
  "properties": {
    "iso:country":"US",
    "sg:address":"11525 Todd St",
    "sg:city":"Houston",
    "sg:classifiers":[
        {
            "category":"Arts & Performance",
            "subcategory":"Art Gallery",
            "type":"Entertainment"
        }
    ],
    "sg:phone":"+1 713 316 9800",
    "sg:postcode":"77055",
    "sg:province":"TX",
    "sg:website":"www.hadaedu.org",
    "wof:name":"Houston Academy Of Dramatic Arts",
    "wof:placetype":"venue"
},
  "geometry": {"coordinates":[-95.48088300000001,29.815818],"type":"Point"}
}