{
  "type": "Feature",
  "properties": {
    "iso:country":"US",
    "sg:address":"8714 Clearbrook Trl",
    "sg:city":"Austin",
    "sg:classifiers":[
        {
            "category":"Professional",
            "subcategory":"Computer Services",
            "type":"Services"
        }
    ],
    "sg:phone":"+1 512 415 9256",
    "sg:postcode":"78729",
    "sg:province":"TX",
    "wof:name":"Tech Services",
    "wof:placetype":"venue"
},
  "geometry": {"coordinates":[-97.772745,30.455818],"type":"Point"}
}