{
  "type": "Feature",
  "properties": {
    "iso:country":"US",
    "sg:address":"707 Chukar Dr",
    "sg:city":"Victoria",
    "sg:classifiers":[
        {
            "category":"Professional",
            "subcategory":"Research",
            "type":"Services"
        }
    ],
    "sg:phone":"+1 361 573 3555",
    "sg:postcode":"77905",
    "sg:province":"TX",
    "sg:tags":[
        "robotics",
        "electronics",
        "industrial"
    ],
    "wof:name":"Cain Company",
    "wof:placetype":"venue"
},
  "geometry": {"coordinates":[-97.08550099999999,28.779556],"type":"Point"}
}