{
  "type": "Feature",
  "properties": {
    "iso:country":"US",
    "sg:address":"12141 Richmond Ave",
    "sg:city":"Houston",
    "sg:classifiers":[
        {
            "category":"Health Services",
            "subcategory":"Medical Lab",
            "type":"Services"
        }
    ],
    "sg:phone":"+1 281 589 0736",
    "sg:postcode":"77082",
    "sg:province":"TX",
    "sg:tags":[
        "laboratory"
    ],
    "wof:name":"American Medical Labs Inc",
    "wof:placetype":"venue"
},
  "geometry": {"coordinates":[-95.59614500000001,29.729957],"type":"Point"}
}