{
  "type": "Feature",
  "properties": {
    "iso:country":"US",
    "sg:address":"1958 el Dorado Blvd",
    "sg:city":"Houston",
    "sg:classifiers":[
        {
            "category":"Personal",
            "subcategory":"Beauty Salon",
            "type":"Services"
        }
    ],
    "sg:phone":"+1 281 486 2085",
    "sg:postcode":"77062",
    "sg:province":"TX",
    "sg:tags":[
        "shop"
    ],
    "wof:name":"Supercuts",
    "wof:placetype":"venue"
},
  "geometry": {"coordinates":[-95.121556,29.578135],"type":"Point"}
}