{
  "type": "Feature",
  "properties": {
    "iso:country":"US",
    "sg:address":"5875 E State Hwy 21",
    "sg:city":"Bryan",
    "sg:classifiers":[
        {
            "category":"Wholesale",
            "subcategory":"Hardware",
            "type":"Manufacturing & Wholesale Goods"
        }
    ],
    "sg:phone":"+1 979 778 8088",
    "sg:postcode":"77808",
    "sg:province":"TX",
    "sg:tags":[
        "fastener"
    ],
    "wof:name":"Mack Bolt & Steel",
    "wof:placetype":"venue"
},
  "geometry": {"coordinates":[-96.345467,30.711261],"type":"Point"}
}