{
  "type": "Feature",
  "properties": {
    "iso:country":"US",
    "sg:address":"945 McKinney St",
    "sg:city":"Houston",
    "sg:classifiers":[
        {
            "category":"Home & Garden",
            "subcategory":"Hardware",
            "type":"Retail Goods"
        },
        {
            "category":"Home & Garden",
            "subcategory":"Building Materials",
            "type":"Retail Goods"
        },
        {
            "category":"Professional",
            "subcategory":"Printing & Photocopies",
            "type":"Services"
        },
        {
            "category":"Building & Trades",
            "subcategory":"Construction",
            "type":"Services"
        }
    ],
    "sg:phone":"+1 281 324 0067",
    "sg:postcode":"77002",
    "sg:province":"TX",
    "sg:tags":[
        "door",
        "handyman",
        "contractor",
        "garage",
        "opener",
        "door-overhead",
        "type",
        "store"
    ],
    "sg:website":"http://local.ingenio.com/Listings/Details.aspx?NUM=a%3a10260300%3a13%3a4859924%3a14%3a0%3a7",
    "wof:name":"Houston Garage Door Repair",
    "wof:placetype":"venue"
},
  "geometry": {"coordinates":[-95.36534899999999,29.75735],"type":"Point"}
}