{
  "type": "Feature",
  "properties": {
    "iso:country":"US",
    "sg:address":"1903 Central Dr Suite 104",
    "sg:city":"Bedford",
    "sg:classifiers":[
        {
            "category":"Banks & Credit Unions",
            "subcategory":"Investment Brokerage",
            "type":"Services"
        },
        {
            "category":"Banks & Credit Unions",
            "subcategory":"Bank",
            "type":"Services"
        },
        {
            "category":"Banks & Credit Unions",
            "subcategory":"Financial Services",
            "type":"Services"
        }
    ],
    "sg:phone":"+1 817 684 7407",
    "sg:postcode":"76021",
    "sg:province":"TX",
    "sg:tags":[
        "advisory",
        "mutual",
        "retirement",
        "annuity",
        "broker",
        "fund",
        "planning",
        "plan",
        "consultant",
        "security",
        "bond",
        "insurance",
        "stock"
    ],
    "sg:website":"http://fortworth.citysearch.com/profile/external/604326432/bedford_tx/edward_jones_dave_dudziak.html?publisher=yellowpages&reference_id=1&placement=ypwebsitemip",
    "wof:name":"Edward Jones - DAVE DUDZIAK",
    "wof:placetype":"venue"
},
  "geometry": {"coordinates":[-97.133522,32.83814],"type":"Point"}
}