{
  "type": "Feature",
  "properties": {
    "iso:country":"US",
    "sg:address":"12295 Rojas Dr",
    "sg:city":"El Paso",
    "sg:classifiers":[
        {
            "category":"Building & Trades",
            "subcategory":"Construction",
            "type":"Services"
        },
        {
            "category":"Shopping",
            "subcategory":"Computers & Home Electronics",
            "type":"Retail Goods"
        }
    ],
    "sg:phone":"+1 915 859 0455",
    "sg:postcode":"79928",
    "sg:province":"TX",
    "sg:tags":[
        "equipment",
        "satellite",
        "installation",
        "system",
        "maintenance"
    ],
    "wof:name":"Dish Network",
    "wof:placetype":"venue"
},
  "geometry": {"coordinates":[-106.278959,31.703708],"type":"Point"}
}