{
  "type": "Feature",
  "properties": {
    "iso:country":"US",
    "sg:address":"1600 Porter Rd",
    "sg:city":"Conroe",
    "sg:classifiers":[
        {
            "category":"Real Estate",
            "subcategory":"Developer",
            "type":"Services"
        }
    ],
    "sg:phone":"+1 936 756 2126",
    "sg:postcode":"77301",
    "sg:province":"TX",
    "sg:tags":[
        "cemetery"
    ],
    "wof:name":"Conroe Memorial Cemetery",
    "wof:placetype":"venue"
},
  "geometry": {"coordinates":[-95.431252,30.300868],"type":"Point"}
}