{
  "type": "Feature",
  "properties": {
    "iso:country":"US",
    "sg:address":"1213 Colony St",
    "sg:city":"Flower Mound",
    "sg:classifiers":[
        {
            "category":"Professional",
            "subcategory":"Art Services",
            "type":"Services"
        }
    ],
    "sg:phone":"+1 972 691 5921",
    "sg:postcode":"75028",
    "sg:province":"TX",
    "sg:tags":[
        "artist"
    ],
    "wof:name":"Vincent Studio",
    "wof:placetype":"venue"
},
  "geometry": {"coordinates":[-97.047843,33.058887],"type":"Point"}
}