{
  "type": "Feature",
  "properties": {
    "iso:country":"US",
    "sg:address":"1610 S Bonham St",
    "sg:city":"Amarillo",
    "sg:classifiers":[
        {
            "category":"Insurance",
            "subcategory":"Insurance Agent",
            "type":"Services"
        }
    ],
    "sg:phone":"+1 806 374 2007",
    "sg:postcode":"79102",
    "sg:province":"TX",
    "wof:name":"New York Life Insurance Co",
    "wof:placetype":"venue"
},
  "geometry": {"coordinates":[-101.858974,35.1958],"type":"Point"}
}