{
  "type": "Feature",
  "properties": {
    "iso:country":"US",
    "sg:address":"2104 N Frazier St",
    "sg:city":"Conroe",
    "sg:classifiers":[
        {
            "category":"Personal",
            "subcategory":"Beauty Salon",
            "type":"Services"
        }
    ],
    "sg:phone":"+1 936 441 9494",
    "sg:postcode":"77301",
    "sg:province":"TX",
    "sg:tags":[
        "shop"
    ],
    "wof:name":"Nail Spa",
    "wof:placetype":"venue"
},
  "geometry": {"coordinates":[-95.467292,30.335122],"type":"Point"}
}