{
  "type": "Feature",
  "properties": {
    "iso:country":"US",
    "sg:address":"12941 North Fwy",
    "sg:city":"Houston",
    "sg:classifiers":[
        {
            "category":"Mining & Drilling",
            "type":"Manufacturing & Wholesale Goods"
        }
    ],
    "sg:phone":"+1 281 872 9700",
    "sg:postcode":"77037",
    "sg:province":"TX",
    "sg:tags":[
        "development",
        "gas",
        "oil",
        "exploration"
    ],
    "wof:name":"Cornerstone Energy",
    "wof:placetype":"venue"
},
  "geometry": {"coordinates":[-95.418627,29.955672],"type":"Point"}
}