{
  "type": "Feature",
  "properties": {
    "iso:country":"US",
    "sg:address":"819 E Tidwell Rd",
    "sg:city":"Houston",
    "sg:classifiers":[
        {
            "category":"Shopping",
            "subcategory":"Used Merchandise",
            "type":"Retail Goods"
        }
    ],
    "sg:phone":"+1 713 699 1400",
    "sg:postcode":"77022",
    "sg:province":"TX",
    "sg:tags":[
        "shop",
        "pawn"
    ],
    "wof:name":"Diamond Pawn Systems-Airline",
    "wof:placetype":"venue"
},
  "geometry": {"coordinates":[-95.38471800000001,29.845613],"type":"Point"}
}