{
  "type": "Feature",
  "properties": {
    "iso:country":"US",
    "sg:address":"12111 Audelia Rd",
    "sg:city":"Dallas",
    "sg:classifiers":[
        {
            "category":"Communications",
            "subcategory":"Film & Video Production",
            "type":"Services"
        }
    ],
    "sg:phone":"+1 972 437 4417",
    "sg:postcode":"75243",
    "sg:province":"TX",
    "sg:tags":[
        "motion"
    ],
    "wof:name":"Profit",
    "wof:placetype":"venue"
},
  "geometry": {"coordinates":[-96.71808,32.912885],"type":"Point"}
}