{
  "type": "Feature",
  "properties": {
    "iso:country":"US",
    "sg:address":"4225 Willow Bend Ln",
    "sg:city":"Port Arthur",
    "sg:classifiers":[
        {
            "category":"Organizations",
            "subcategory":"Membership Organization",
            "type":"Services"
        }
    ],
    "sg:phone":"+1 409 727 1213",
    "sg:postcode":"77642",
    "sg:province":"TX",
    "wof:name":"Social Order of Beauceant",
    "wof:placetype":"venue"
},
  "geometry": {"coordinates":[-93.979749,29.958313],"type":"Point"}
}