{
  "type": "Feature",
  "properties": {
    "iso:country":"US",
    "sg:address":"304 N 8th St",
    "sg:city":"Skidmore",
    "sg:classifiers":[
        {
            "category":"Restaurant",
            "type":"Food & Drink"
        }
    ],
    "sg:phone":"+1 361 287 3847",
    "sg:postcode":"78389",
    "sg:province":"TX",
    "wof:name":"Chisholm Trail Cafe",
    "wof:placetype":"venue"
},
  "geometry": {"coordinates":[-97.68633699999999,28.256899],"type":"Point"}
}