{
  "type": "Feature",
  "properties": {
    "iso:country":"US",
    "sg:address":"317 Lyndsie Dr",
    "sg:city":"Coppell",
    "sg:classifiers":[
        {
            "category":"Professional",
            "type":"Services"
        }
    ],
    "sg:phone":"+1 972 459 6699",
    "sg:postcode":"75019",
    "sg:province":"TX",
    "wof:name":"Cyber It Gurus LLC",
    "wof:placetype":"venue"
},
  "geometry": {"coordinates":[-96.984036,32.984149],"type":"Point"}
}