{
  "type": "Feature",
  "properties": {
    "iso:country":"US",
    "sg:address":"4200 Bluffridge Dr",
    "sg:city":"Austin",
    "sg:classifiers":[
        {
            "category":"Professional",
            "subcategory":"Management & Consulting",
            "type":"Services"
        }
    ],
    "sg:phone":"+1 512 231 9699",
    "sg:postcode":"78759",
    "sg:province":"TX",
    "sg:tags":[
        "consultant",
        "educational"
    ],
    "wof:name":"Suzanne Duncan",
    "wof:placetype":"venue"
},
  "geometry": {"coordinates":[-97.74949100000001,30.386598],"type":"Point"}
}