{
  "type": "Feature",
  "properties": {
    "iso:country":"US",
    "sg:address":"1811 W Frank Ave",
    "sg:city":"Lufkin",
    "sg:classifiers":[
        {
            "category":"Personal",
            "subcategory":"Tanning Parlor",
            "type":"Services"
        }
    ],
    "sg:phone":"+1 936 699 4060",
    "sg:postcode":"75904",
    "sg:province":"TX",
    "sg:tags":[
        "salon"
    ],
    "wof:name":"Sun-Daze Tanning Salon",
    "wof:placetype":"venue"
},
  "geometry": {"coordinates":[-94.754991,31.333421],"type":"Point"}
}