{
  "type": "Feature",
  "properties": {
    "iso:country":"US",
    "sg:address":"9100 Southwest Fwy",
    "sg:city":"Houston",
    "sg:classifiers":[
        {
            "category":"Health Services",
            "subcategory":"Clinic",
            "type":"Services"
        }
    ],
    "sg:phone":"+1 713 779 6300",
    "sg:postcode":"77074",
    "sg:province":"TX",
    "sg:tags":[
        "counseling",
        "mental"
    ],
    "wof:name":"Matson James Acsw Lmsw-Acp",
    "wof:placetype":"venue"
},
  "geometry": {"coordinates":[-95.533501,29.684999],"type":"Point"}
}