{
  "type": "Feature",
  "properties": {
    "iso:country":"US",
    "sg:address":"6202 Shotwell St",
    "sg:city":"Houston",
    "sg:classifiers":[
        {
            "category":"Shopping",
            "subcategory":"Music",
            "type":"Retail Goods"
        }
    ],
    "sg:phone":"+1 713 491 8400",
    "sg:postcode":"77028",
    "sg:province":"TX",
    "sg:tags":[
        "contractor"
    ],
    "wof:name":"Rokk Steady Records",
    "wof:placetype":"venue"
},
  "geometry": {"coordinates":[-95.312307,29.816827],"type":"Point"}
}