{
  "type": "Feature",
  "properties": {
    "iso:country":"US",
    "sg:address":"1218 Baylor St",
    "sg:city":"Austin",
    "sg:classifiers":[
        {
            "category":"Wholesale",
            "subcategory":"Non-durable Goods",
            "type":"Manufacturing & Wholesale Goods"
        }
    ],
    "sg:phone":"+1 512 479 6578",
    "sg:postcode":"78703",
    "sg:province":"TX",
    "sg:tags":[
        "merchandise-wholesale"
    ],
    "wof:name":"Mokrane Trading",
    "wof:placetype":"venue"
},
  "geometry": {"coordinates":[-97.752287,30.277437],"type":"Point"}
}