{
  "type": "Feature",
  "properties": {
    "iso:country":"US",
    "sg:address":"311 Andrews Hwy",
    "sg:city":"Midland",
    "sg:classifiers":[
        {
            "category":"Professional",
            "subcategory":"Business Services",
            "type":"Services"
        }
    ],
    "sg:phone":"+1 432 687 3042",
    "sg:postcode":"79701",
    "sg:province":"TX",
    "sg:tags":[
        "interior",
        "consultant",
        "design",
        "decorator"
    ],
    "wof:name":"Van Stavern Interiors Inc",
    "wof:placetype":"venue"
},
  "geometry": {"coordinates":[-102.10153,31.996214],"type":"Point"}
}