{
  "type": "Feature",
  "properties": {
    "iso:country":"US",
    "sg:address":"2510 40th Ave N",
    "sg:city":"Texas City",
    "sg:classifiers":[
        {
            "category":"Retail",
            "subcategory":"Repair Shop",
            "type":"Services"
        }
    ],
    "sg:phone":"+1 409 948 0794",
    "sg:postcode":"77590",
    "sg:province":"TX",
    "sg:tags":[
        "refrigeration"
    ],
    "wof:name":"J Clark Air",
    "wof:placetype":"venue"
},
  "geometry": {"coordinates":[-94.93218299999999,29.419236],"type":"Point"}
}