{
  "type": "Feature",
  "properties": {
    "iso:country":"US",
    "sg:address":"20030 Cook Rd",
    "sg:city":"Tomball",
    "sg:classifiers":[
        {
            "category":"Freight",
            "type":"Transportation"
        }
    ],
    "sg:phone":"+1 281 351 8590",
    "sg:postcode":"77377",
    "sg:province":"TX",
    "sg:tags":[
        "general"
    ],
    "wof:name":"Rosehill Mini Storage",
    "wof:placetype":"venue"
},
  "geometry": {"coordinates":[-95.749166,30.058339],"type":"Point"}
}