{
  "type": "Feature",
  "properties": {
    "iso:country":"US",
    "sg:address":"304 Main St",
    "sg:city":"Smithville",
    "sg:classifiers":[
        {
            "category":"Insurance",
            "subcategory":"Insurance Agent",
            "type":"Services"
        }
    ],
    "sg:phone":"+1 512 237 2439",
    "sg:postcode":"78957",
    "sg:province":"TX",
    "wof:name":"American Casualty",
    "wof:placetype":"venue"
},
  "geometry": {"coordinates":[-97.159042,30.009253],"type":"Point"}
}