{
  "type": "Feature",
  "properties": {
    "iso:country":"US",
    "sg:address":"1 Chisholm Trl",
    "sg:city":"Round Rock",
    "sg:classifiers":[
        {
            "category":"Health Services",
            "subcategory":"Hospital",
            "type":"Services"
        }
    ],
    "sg:phone":"+1 512 246 8045",
    "sg:postcode":"78681",
    "sg:province":"TX",
    "sg:tags":[
        "mental"
    ],
    "wof:name":"Integrated Mental Health Svc",
    "wof:placetype":"venue"
},
  "geometry": {"coordinates":[-97.68944999999999,30.513077],"type":"Point"}
}