{
  "type": "Feature",
  "properties": {
    "iso:country":"US",
    "sg:address":"20333 Southwest Fwy",
    "sg:city":"Sugar Land",
    "sg:classifiers":[
        {
            "category":"Banks & Credit Unions",
            "subcategory":"Financial Services",
            "type":"Services"
        }
    ],
    "sg:phone":"+1 281 343 1700",
    "sg:postcode":"77479",
    "sg:province":"TX",
    "sg:tags":[
        "investment",
        "closed"
    ],
    "wof:name":"Sifco LLC",
    "wof:placetype":"venue"
},
  "geometry": {"coordinates":[-95.64954,29.580217],"type":"Point"}
}