{
  "type": "Feature",
  "properties": {
    "iso:country":"US",
    "sg:address":"616 Clay St",
    "sg:city":"Kerrville",
    "sg:classifiers":[
        {
            "category":"Social Services",
            "subcategory":"Adult Care",
            "type":"Services"
        }
    ],
    "sg:phone":"+1 830 792 3900",
    "sg:postcode":"78028",
    "sg:province":"TX",
    "sg:tags":[
        "rehabilitation",
        "center"
    ],
    "wof:name":"Counseling Center",
    "wof:placetype":"venue"
},
  "geometry": {"coordinates":[-99.138243,30.051526],"type":"Point"}
}