{
  "type": "Feature",
  "properties": {
    "iso:country":"US",
    "sg:address":"106 N Blackburn St",
    "sg:city":"Brady",
    "sg:classifiers":[
        {
            "category":"Banks & Credit Unions",
            "subcategory":"Investment Brokerage",
            "type":"Services"
        },
        {
            "category":"Insurance",
            "subcategory":"Hazard Insurance",
            "type":"Services"
        }
    ],
    "sg:phone":"+1 325 597 2275",
    "sg:postcode":"76825",
    "sg:province":"TX",
    "sg:tags":[
        "commercial",
        "agent",
        "business",
        "resume"
    ],
    "wof:name":"Mcanelly Insurance Agency",
    "wof:placetype":"venue"
},
  "geometry": {"coordinates":[-99.334082,31.134734],"type":"Point"}
}