{
  "type": "Feature",
  "properties": {
    "iso:country":"US",
    "sg:address":"905 Halsell Ave",
    "sg:city":"Bridgeport",
    "sg:classifiers":[
        {
            "category":"Professional",
            "type":"Services"
        }
    ],
    "sg:phone":"+1 940 683 4471",
    "sg:postcode":"76426",
    "sg:province":"TX",
    "wof:name":"Lone Star Flip N Cheer In",
    "wof:placetype":"venue"
},
  "geometry": {"coordinates":[-97.765975,33.210516],"type":"Point"}
}