{
  "type": "Feature",
  "properties": {
    "iso:country":"US",
    "sg:address":"401 E Kilpatrick St",
    "sg:city":"Mineola",
    "sg:classifiers":[
        {
            "category":"Shopping",
            "subcategory":"Gifts & Souvenirs",
            "type":"Retail Goods"
        }
    ],
    "sg:phone":"+1 903 569 0892",
    "sg:postcode":"75773",
    "sg:province":"TX",
    "wof:name":"Petite Affairs",
    "wof:placetype":"venue"
},
  "geometry": {"coordinates":[-95.485562,32.663784],"type":"Point"}
}