{
  "type": "Feature",
  "properties": {
    "iso:country":"US",
    "sg:address":"825 John Ben Shepperd Pkwy",
    "sg:city":"Odessa",
    "sg:classifiers":[
        {
            "category":"Professional",
            "subcategory":"Accounting & Tax Preparation",
            "type":"Services"
        }
    ],
    "sg:phone":"+1 432 580 3535",
    "sg:postcode":"79761",
    "sg:province":"TX",
    "sg:tags":[
        "billing"
    ],
    "wof:name":"Script Source Inc",
    "wof:placetype":"venue"
},
  "geometry": {"coordinates":[-102.321834,31.869736],"type":"Point"}
}