{
  "type": "Feature",
  "properties": {
    "iso:country":"US",
    "sg:address":"111 Meadow View Ln",
    "sg:city":"Kerrville",
    "sg:classifiers":[
        {
            "category":"Building & Trades",
            "subcategory":"Plumbing",
            "type":"Services"
        }
    ],
    "sg:phone":"+1 830 895 4000",
    "sg:postcode":"78028",
    "sg:province":"TX",
    "sg:tags":[
        "conditioning",
        "air",
        "system",
        "contractor"
    ],
    "wof:name":"Albert's Air Conditioning Htg",
    "wof:placetype":"venue"
},
  "geometry": {"coordinates":[-99.12516100000001,30.023674],"type":"Point"}
}