{
  "type": "Feature",
  "properties": {
    "iso:country":"US",
    "sg:address":"4907 Silver Frost Dr",
    "sg:city":"Houston",
    "sg:classifiers":[
        {
            "category":"Professional",
            "type":"Services"
        }
    ],
    "sg:phone":"+1 281 440 4429",
    "sg:postcode":"77066",
    "sg:province":"TX",
    "wof:name":"Lisa ONeal",
    "wof:placetype":"venue"
},
  "geometry": {"coordinates":[-95.49158799999999,29.951514],"type":"Point"}
}