{
  "type": "Feature",
  "properties": {
    "iso:country":"US",
    "sg:address":"1806 Richey St",
    "sg:city":"Pasadena",
    "sg:classifiers":[
        {
            "category":"Autos & Motor Vehicles",
            "subcategory":"Automobile Sales",
            "type":"Retail Goods"
        }
    ],
    "sg:phone":"+1 713 472 7636",
    "sg:postcode":"77502",
    "sg:province":"TX",
    "sg:tags":[
        "car",
        "used"
    ],
    "wof:name":"Gone Fishin Auto Sales",
    "wof:placetype":"venue"
},
  "geometry": {"coordinates":[-95.223106,29.685141],"type":"Point"}
}