{
  "type": "Feature",
  "properties": {
    "iso:country":"US",
    "sg:address":"1720 Liberty St",
    "sg:city":"Bonham",
    "sg:classifiers":[
        {
            "category":"Restaurant",
            "type":"Food & Drink"
        }
    ],
    "sg:phone":"+1 903 583 3770",
    "sg:postcode":"75418",
    "sg:province":"TX",
    "wof:name":"Subway Sandwiches & Salads",
    "wof:placetype":"venue"
},
  "geometry": {"coordinates":[-96.181765,33.592233],"type":"Point"}
}