{
  "type": "Feature",
  "properties": {
    "iso:country":"US",
    "sg:address":"331 N Washington St",
    "sg:city":"Beeville",
    "sg:classifiers":[
        {
            "category":"Social Services",
            "subcategory":"Job Training",
            "type":"Services"
        }
    ],
    "sg:phone":"+1 361 358 8248",
    "sg:postcode":"78102",
    "sg:province":"TX",
    "sg:tags":[
        "agency",
        "rehabilitation",
        "vocational"
    ],
    "wof:name":"Beeville Center",
    "wof:placetype":"venue"
},
  "geometry": {"coordinates":[-97.750743,28.404274],"type":"Point"}
}