{
  "type": "Feature",
  "properties": {
    "iso:country":"US",
    "sg:address":"755 Land-O-Lakes Dr",
    "sg:city":"Brownsville",
    "sg:classifiers":[
        {
            "category":"Professional",
            "subcategory":"Engineering",
            "type":"Services"
        }
    ],
    "sg:phone":"+1 956 541 3658",
    "sg:postcode":"78521",
    "sg:province":"TX",
    "sg:tags":[
        "engineer"
    ],
    "wof:name":"Holdar Engineering Co",
    "wof:placetype":"venue"
},
  "geometry": {"coordinates":[-97.46521300000001,25.931581],"type":"Point"}
}