{
  "type": "Feature",
  "properties": {
    "iso:country":"US",
    "sg:address":"3427 E State Hwy 158",
    "sg:city":"Midland",
    "sg:classifiers":[
        {
            "category":"Mining & Drilling",
            "type":"Manufacturing & Wholesale Goods"
        }
    ],
    "sg:phone":"+1 432 682 7742",
    "sg:postcode":"79706",
    "sg:province":"TX",
    "sg:tags":[
        "field",
        "oil"
    ],
    "wof:name":"Don-Nan Pump & Supply Co",
    "wof:placetype":"venue"
},
  "geometry": {"coordinates":[-102.007329,31.97411],"type":"Point"}
}