{
  "type": "Feature",
  "properties": {
    "iso:country":"US",
    "sg:address":"9606 Mesa Dr",
    "sg:city":"Houston",
    "sg:classifiers":[
        {
            "category":"Restaurant",
            "type":"Food & Drink"
        }
    ],
    "sg:phone":"+1 713 631 3962",
    "sg:postcode":"77078",
    "sg:province":"TX",
    "wof:name":"Lacy's Cafeteria & Restaurant",
    "wof:placetype":"venue"
},
  "geometry": {"coordinates":[-95.262199,29.8515],"type":"Point"}
}