{
  "type": "Feature",
  "properties": {
    "iso:country":"US",
    "sg:address":"406 S Santa Fe Trl",
    "sg:city":"Duncanville",
    "sg:classifiers":[
        {
            "category":"Building & Trades",
            "subcategory":"Construction",
            "type":"Services"
        }
    ],
    "sg:phone":"+1 972 572 7663",
    "sg:postcode":"75116",
    "sg:province":"TX",
    "sg:tags":[
        "general",
        "contractor"
    ],
    "wof:name":"Premier Roofing Solutions",
    "wof:placetype":"venue"
},
  "geometry": {"coordinates":[-96.912729,32.647968],"type":"Point"}
}