{
  "type": "Feature",
  "properties": {
    "iso:country":"US",
    "sg:address":"7304 Durado Dr",
    "sg:city":"Fort Worth",
    "sg:classifiers":[
        {
            "category":"Professional",
            "subcategory":"Management & Consulting",
            "type":"Services"
        }
    ],
    "sg:phone":"+1 817 236 3443",
    "sg:postcode":"76179",
    "sg:province":"TX",
    "wof:name":"Sweeney Associates",
    "wof:placetype":"venue"
},
  "geometry": {"coordinates":[-97.432784,32.877782],"type":"Point"}
}