{
  "type": "Feature",
  "properties": {
    "iso:country":"US",
    "sg:address":"8515 Greenville Ave",
    "sg:city":"Dallas",
    "sg:classifiers":[
        {
            "category":"Professional",
            "subcategory":"Art Services",
            "type":"Services"
        }
    ],
    "sg:phone":"+1 214 348 6811",
    "sg:postcode":"75243",
    "sg:province":"TX",
    "sg:tags":[
        "artist"
    ],
    "wof:name":"Joe Ing & Friends Inc",
    "wof:placetype":"venue"
},
  "geometry": {"coordinates":[-96.75289100000001,32.894531],"type":"Point"}
}