{
  "type": "Feature",
  "properties": {
    "iso:country":"US",
    "sg:address":"412 E Main St",
    "sg:city":"Gatesville",
    "sg:classifiers":[
        {
            "category":"Building & Trades",
            "subcategory":"Plumbing",
            "type":"Services"
        }
    ],
    "sg:phone":"+1 254 865 2950",
    "sg:postcode":"76528",
    "sg:province":"TX",
    "sg:tags":[
        "contractor"
    ],
    "wof:name":"Genes Heating & AC",
    "wof:placetype":"venue"
},
  "geometry": {"coordinates":[-97.752467,31.434935],"type":"Point"}
}