{
  "type": "Feature",
  "properties": {
    "iso:country":"US",
    "sg:address":"309 San Felipe St",
    "sg:city":"Edinburg",
    "sg:classifiers":[
        {
            "category":"Professional",
            "subcategory":"Management & Consulting",
            "type":"Services"
        }
    ],
    "sg:phone":"+1 956 380 4014",
    "sg:postcode":"78539",
    "sg:province":"TX",
    "sg:tags":[
        "business"
    ],
    "wof:name":"Reyes Consulting",
    "wof:placetype":"venue"
},
  "geometry": {"coordinates":[-98.20920599999999,26.311405],"type":"Point"}
}