{
  "type": "Feature",
  "properties": {
    "iso:country":"US",
    "sg:address":"7178 Fm 2450",
    "sg:city":"Sanger",
    "sg:classifiers":[
        {
            "category":"Food & Beverages",
            "subcategory":"Groceries & Convenience Stores",
            "type":"Retail Goods"
        }
    ],
    "sg:phone":"+1 940 482 6850",
    "sg:postcode":"76266",
    "sg:province":"TX",
    "wof:name":"Lori's Quick",
    "wof:placetype":"venue"
},
  "geometry": {"coordinates":[-97.237295,33.314598],"type":"Point"}
}