{
  "type": "Feature",
  "properties": {
    "iso:country":"US",
    "sg:address":"9327 Sotherloch Lake Dr.",
    "sg:city":"Spring",
    "sg:classifiers":[
        {
            "category":"Professional",
            "subcategory":"Management & Consulting",
            "type":"Services"
        }
    ],
    "sg:phone":"+1 713 504 5287",
    "sg:postcode":"77379",
    "sg:province":"TX",
    "sg:tags":[
        "marketing",
        "consultant"
    ],
    "sg:website":"http://www.virtualmarketingspecialists.com",
    "wof:name":"Virtual Marketing Specialists",
    "wof:placetype":"venue"
},
  "geometry": {"coordinates":[-95.568237,30.031191],"type":"Point"}
}