{
  "type": "Feature",
  "properties": {
    "iso:country":"US",
    "sg:address":"729 Exposition Ave",
    "sg:city":"Dallas",
    "sg:classifiers":[
        {
            "category":"Manufacturing",
            "subcategory":"Food",
            "type":"Manufacturing & Wholesale Goods"
        }
    ],
    "sg:phone":"+1 214 824 2060",
    "sg:postcode":"75226",
    "sg:province":"TX",
    "sg:tags":[
        "extract",
        "syrup",
        "flavoring"
    ],
    "wof:name":"Bert Concessions Inc",
    "wof:placetype":"venue"
},
  "geometry": {"coordinates":[-96.769462,32.782935],"type":"Point"}
}