{
  "type": "Feature",
  "properties": {
    "iso:country":"US",
    "sg:address":"15831 Brook Forest Dr",
    "sg:city":"Houston",
    "sg:classifiers":[
        {
            "category":"Professional",
            "subcategory":"Management & Consulting",
            "type":"Services"
        }
    ],
    "sg:phone":"+1 281 480 2214",
    "sg:postcode":"77059",
    "sg:province":"TX",
    "sg:tags":[
        "business"
    ],
    "wof:name":"Doug Cooke Consulting",
    "wof:placetype":"venue"
},
  "geometry": {"coordinates":[-95.116663,29.584962],"type":"Point"}
}