{
  "type": "Feature",
  "properties": {
    "iso:country":"US",
    "sg:address":"1301 Paula Pl",
    "sg:city":"Brownfield",
    "sg:phone":"+1 806 637 8901",
    "sg:postcode":"79316",
    "sg:province":"TX",
    "sg:tags":[
        "farm",
        "field",
        "crop",
        "cotton"
    ],
    "wof:name":"M & D Farms Inc",
    "wof:placetype":"venue"
},
  "geometry": {"coordinates":[-102.253214,33.166574],"type":"Point"}
}