{
  "type": "Feature",
  "properties": {
    "iso:country":"US",
    "sg:address":"5712 Southwest Fwy",
    "sg:city":"Houston",
    "sg:classifiers":[
        {
            "category":"Retail",
            "subcategory":"Auto Repair",
            "type":"Services"
        }
    ],
    "sg:phone":"+1 713 789 0000",
    "sg:postcode":"77057",
    "sg:province":"TX",
    "wof:name":"Team Autoplex",
    "wof:placetype":"venue"
},
  "geometry": {"coordinates":[-95.47875000000001,29.726404],"type":"Point"}
}