{
  "type": "Feature",
  "properties": {
    "iso:country":"US",
    "sg:address":"14602 Old Humble Rd",
    "sg:city":"Humble",
    "sg:classifiers":[
        {
            "category":"Wholesale",
            "subcategory":"Auto Parts",
            "type":"Manufacturing & Wholesale Goods"
        }
    ],
    "sg:phone":"+1 281 441 2166",
    "sg:postcode":"77396",
    "sg:province":"TX",
    "sg:tags":[
        "automobile",
        "rebuilt"
    ],
    "wof:name":"Latino Auto Salvage",
    "wof:placetype":"venue"
},
  "geometry": {"coordinates":[-95.290727,29.933463],"type":"Point"}
}