{
  "type": "Feature",
  "properties": {
    "iso:country":"US",
    "sg:address":"7502 Greenville Ave",
    "sg:city":"Dallas",
    "sg:classifiers":[
        {
            "category":"Manufacturing",
            "subcategory":"Printing",
            "type":"Manufacturing & Wholesale Goods"
        }
    ],
    "sg:phone":"+1 214 890 4050",
    "sg:postcode":"75231",
    "sg:province":"TX",
    "sg:tags":[
        "publisher"
    ],
    "wof:name":"Durban House Publishing Inc",
    "wof:placetype":"venue"
},
  "geometry": {"coordinates":[-96.758375,32.885596],"type":"Point"}
}