{
  "type": "Feature",
  "properties": {
    "iso:country":"US",
    "sg:address":"66 N Wright St",
    "sg:city":"Alice",
    "sg:classifiers":[
        {
            "category":"Manufacturing",
            "subcategory":"Printing",
            "type":"Manufacturing & Wholesale Goods"
        }
    ],
    "sg:phone":"+1 361 664 4386",
    "sg:postcode":"78332",
    "sg:province":"TX",
    "sg:tags":[
        "printer",
        "commercial",
        "offset"
    ],
    "wof:name":"Accurate Printing Co Inc",
    "wof:placetype":"venue"
},
  "geometry": {"coordinates":[-98.074354,27.750469],"type":"Point"}
}