{
  "type": "Feature",
  "properties": {
    "iso:country":"US",
    "sg:address":"8111 Preston Rd",
    "sg:city":"Dallas",
    "sg:classifiers":[
        {
            "category":"Professional",
            "subcategory":"Accounting & Tax Preparation",
            "type":"Services"
        }
    ],
    "sg:phone":"+1 214 346 9646",
    "sg:postcode":"75225",
    "sg:province":"TX",
    "sg:tags":[
        "accountant"
    ],
    "wof:name":"Blackburn May & Co",
    "wof:placetype":"venue"
},
  "geometry": {"coordinates":[-96.804143,32.861225],"type":"Point"}
}