{
  "type": "Feature",
  "properties": {
    "iso:country":"US",
    "sg:address":"1125 Apache Dr",
    "sg:city":"Carrollton",
    "sg:classifiers":[
        {
            "category":"Building & Trades",
            "subcategory":"Construction",
            "type":"Services"
        }
    ],
    "sg:phone":"+1 972 492 8947",
    "sg:postcode":"75043",
    "sg:province":"TX",
    "sg:tags":[
        "home",
        "builder"
    ],
    "wof:name":"Legacy Homes",
    "wof:placetype":"venue"
},
  "geometry": {"coordinates":[-96.607277,32.866029],"type":"Point"}
}