{
  "type": "Feature",
  "properties": {
    "iso:country":"US",
    "sg:address":"1 Lazy Ln",
    "sg:city":"Bay City",
    "sg:classifiers":[
        {
            "category":"Building & Trades",
            "subcategory":"Plumbing",
            "type":"Services"
        }
    ],
    "sg:phone":"+1 979 245 6981",
    "sg:postcode":"77414",
    "sg:province":"TX",
    "sg:tags":[
        "machine",
        "refrigeration",
        "ice",
        "contractor"
    ],
    "wof:name":"Sullivan Air Conditioning",
    "wof:placetype":"venue"
},
  "geometry": {"coordinates":[-95.960089,28.968757],"type":"Point"}
}