{
  "type": "Feature",
  "properties": {
    "iso:country":"US",
    "sg:address":"3505 Missoula St",
    "sg:city":"Irving",
    "sg:classifiers":[
        {
            "category":"Professional",
            "subcategory":"Management & Consulting",
            "type":"Services"
        }
    ],
    "sg:phone":"+1 972 659 0584",
    "sg:postcode":"75062",
    "sg:province":"TX",
    "sg:tags":[
        "business"
    ],
    "wof:name":"Kd Consulting",
    "wof:placetype":"venue"
},
  "geometry": {"coordinates":[-96.99888199999999,32.854537],"type":"Point"}
}