{
  "type": "Feature",
  "properties": {
    "iso:country":"US",
    "sg:address":"107 W Sanford St",
    "sg:city":"Arlington",
    "sg:classifiers":[
        {
            "category":"Freight",
            "type":"Transportation"
        }
    ],
    "sg:phone":"+1 817 275 5610",
    "sg:postcode":"76011",
    "sg:province":"TX",
    "sg:tags":[
        "trucking"
    ],
    "wof:name":"Truck One Trucking",
    "wof:placetype":"venue"
},
  "geometry": {"coordinates":[-97.10808299999999,32.742878],"type":"Point"}
}