{
  "type": "Feature",
  "properties": {
    "iso:country":"US",
    "sg:address":"1500 N Houston St",
    "sg:city":"Livingston",
    "sg:classifiers":[
        {
            "category":"Real Estate",
            "subcategory":"Real Estate Operator",
            "type":"Services"
        }
    ],
    "sg:phone":"+1 936 327 3153",
    "sg:postcode":"77351",
    "sg:province":"TX",
    "sg:tags":[
        "apartment"
    ],
    "wof:name":"Timber Apartments",
    "wof:placetype":"venue"
},
  "geometry": {"coordinates":[-94.931124,30.720245],"type":"Point"}
}