{
  "type": "Feature",
  "properties": {
    "iso:country":"US",
    "sg:address":"800 Conrad Hilton Blvd",
    "sg:city":"Cisco",
    "sg:classifiers":[
        {
            "category":"Shopping",
            "subcategory":"Department Store",
            "type":"Retail Goods"
        }
    ],
    "sg:phone":"+1 254 442 1626",
    "sg:postcode":"76437",
    "sg:province":"TX",
    "sg:tags":[
        "shop"
    ],
    "wof:name":"Kathy's Thrift Town",
    "wof:placetype":"venue"
},
  "geometry": {"coordinates":[-98.979322,32.388123],"type":"Point"}
}