{
  "type": "Feature",
  "properties": {
    "iso:country":"US",
    "sg:address":"4623 Binz-Engleman Rd",
    "sg:city":"San Antonio",
    "sg:classifiers":[
        {
            "category":"Retail",
            "subcategory":"Veterinary Services",
            "type":"Services"
        }
    ],
    "sg:phone":"+1 210 661 6717",
    "sg:postcode":"78219",
    "sg:province":"TX",
    "wof:name":"Kirby Animal Hospital",
    "wof:placetype":"venue"
},
  "geometry": {"coordinates":[-98.40092300000001,29.458898],"type":"Point"}
}