{
  "type": "Feature",
  "properties": {
    "iso:country":"US",
    "sg:address":"202 Travis St",
    "sg:city":"Houston",
    "sg:classifiers":[
        {
            "category":"Freight",
            "type":"Transportation"
        }
    ],
    "sg:phone":"+1 713 671 9181",
    "sg:postcode":"77002",
    "sg:province":"TX",
    "sg:tags":[
        "consultant"
    ],
    "wof:name":"AMX Logistics",
    "wof:placetype":"venue"
},
  "geometry": {"coordinates":[-95.361655,29.762839],"type":"Point"}
}