{
  "type": "Feature",
  "properties": {
    "iso:country":"US",
    "sg:address":"13500 Tomball Pkwy",
    "sg:city":"Houston",
    "sg:classifiers":[
        {
            "category":"Insurance",
            "subcategory":"Insurance Agent",
            "type":"Services"
        }
    ],
    "sg:phone":"+1 281 999 9930",
    "sg:postcode":"77086",
    "sg:province":"TX",
    "wof:name":"Intrepid Marketing Group",
    "wof:placetype":"venue"
},
  "geometry": {"coordinates":[-95.492555,29.919203],"type":"Point"}
}