{
  "type": "Feature",
  "properties": {
    "iso:country":"US",
    "sg:address":"6500 Sands Point Dr",
    "sg:city":"Houston",
    "sg:classifiers":[
        {
            "category":"Wholesale",
            "subcategory":"Hardware",
            "type":"Manufacturing & Wholesale Goods"
        },
        {
            "category":"Insurance",
            "subcategory":"Insurance Agent",
            "type":"Services"
        }
    ],
    "sg:phone":"+1 713 271 2005",
    "sg:postcode":"77074",
    "sg:province":"TX",
    "sg:tags":[
        "plumbing",
        "adjuster"
    ],
    "wof:name":"Frye Claims Consultation & ADM",
    "wof:placetype":"venue"
},
  "geometry": {"coordinates":[-95.49695199999999,29.711453],"type":"Point"}
}