{
  "type": "Feature",
  "properties": {
    "iso:country":"US",
    "sg:address":"15819 Lenclaire Dr",
    "sg:city":"Houston",
    "sg:classifiers":[
        {
            "category":"Home & Garden",
            "subcategory":"Building Materials",
            "type":"Retail Goods"
        }
    ],
    "sg:phone":"+1 281 438 4148",
    "sg:postcode":"77053",
    "sg:province":"TX",
    "sg:tags":[
        "repair"
    ],
    "wof:name":"Dock and Sons Garage Door Svc",
    "wof:placetype":"venue"
},
  "geometry": {"coordinates":[-95.470282,29.596788],"type":"Point"}
}