{
  "type": "Feature",
  "properties": {
    "iso:country":"US",
    "sg:address":"2617 Thomas Ave",
    "sg:city":"Dallas",
    "sg:classifiers":[
        {
            "category":"Health Services",
            "subcategory":"Dentist",
            "type":"Services"
        }
    ],
    "sg:phone":"+1 214 979 3278",
    "sg:postcode":"75204",
    "sg:province":"TX",
    "sg:website":"www.aspendentalhouse.com",
    "wof:name":"Whitfield Mark DDS",
    "wof:placetype":"venue"
},
  "geometry": {"coordinates":[-96.799633,32.794731],"type":"Point"}
}