{
  "type": "Feature",
  "properties": {
    "iso:country":"US",
    "sg:address":"1355 Westgreen Blvd",
    "sg:city":"Katy",
    "sg:classifiers":[
        {
            "category":"Wholesale",
            "subcategory":"Non-durable Goods",
            "type":"Manufacturing & Wholesale Goods"
        }
    ],
    "sg:phone":"+1 281 578 5543",
    "sg:postcode":"77450",
    "sg:province":"TX",
    "wof:name":"Lil Braves Trading Post",
    "wof:placetype":"venue"
},
  "geometry": {"coordinates":[-95.73481099999999,29.764933],"type":"Point"}
}