{
  "type": "Feature",
  "properties": {
    "iso:country":"US",
    "sg:address":"3406 74th St",
    "sg:city":"Lubbock",
    "sg:classifiers":[
        {
            "category":"Retail",
            "subcategory":"Portrait Studio",
            "type":"Services"
        }
    ],
    "sg:phone":"+1 806 798 1572",
    "sg:postcode":"79423",
    "sg:province":"TX",
    "sg:tags":[
        "photo"
    ],
    "wof:name":"Mark McCall Photography",
    "wof:placetype":"venue"
},
  "geometry": {"coordinates":[-101.88986800000001,33.526615],"type":"Point"}
}