{
  "type": "Feature",
  "properties": {
    "iso:country":"US",
    "sg:address":"601 N Glenville Dr",
    "sg:city":"Richardson",
    "sg:classifiers":[
        {
            "category":"Building & Trades",
            "subcategory":"Pest Control",
            "type":"Services"
        }
    ],
    "sg:phone":"+1 214 349 6009",
    "sg:postcode":"75081",
    "sg:province":"TX",
    "sg:tags":[
        "spraying"
    ],
    "sg:website":"www.centex.com",
    "wof:name":"Hometeam",
    "wof:placetype":"venue"
},
  "geometry": {"coordinates":[-96.705344,32.95755],"type":"Point"}
}