{
  "type": "Feature",
  "properties": {
    "iso:country":"US",
    "sg:address":"2808 Milam St",
    "sg:city":"Houston",
    "sg:classifiers":[
        {
            "category":"Banks & Credit Unions",
            "subcategory":"Bank",
            "type":"Services"
        }
    ],
    "sg:phone":"+1 713 630 3200",
    "sg:postcode":"77006",
    "sg:province":"TX",
    "sg:tags":[
        "national",
        "commercial"
    ],
    "wof:name":"Metrobank N A",
    "wof:placetype":"venue"
},
  "geometry": {"coordinates":[-95.377326,29.744654],"type":"Point"}
}