{
  "type": "Feature",
  "properties": {
    "iso:country":"US",
    "sg:address":"1763 Upland Dr",
    "sg:city":"Houston",
    "sg:classifiers":[
        {
            "category":"Shopping",
            "subcategory":"Clothing, Apparel, & Fashions",
            "type":"Retail Goods"
        },
        {
            "category":"Shopping",
            "subcategory":"Bicycles & Sporting Goods",
            "type":"Retail Goods"
        }
    ],
    "sg:phone":"+1 713 365 0595",
    "sg:postcode":"77043",
    "sg:province":"TX",
    "sg:tags":[
        "apparel",
        "racing",
        "sportswear",
        "merchandise"
    ],
    "wof:name":"The Pride Of Texas All Stars",
    "wof:placetype":"venue"
},
  "geometry": {"coordinates":[-95.576646,29.798313],"type":"Point"}
}