{
  "type": "Feature",
  "properties": {
    "iso:country":"US",
    "sg:address":"4027 Co Rd 156",
    "sg:city":"Alvin",
    "sg:classifiers":[
        {
            "category":"Building & Trades",
            "subcategory":"Construction",
            "type":"Services"
        }
    ],
    "sg:phone":"+1 281 331 2232",
    "sg:postcode":"77511",
    "sg:province":"TX",
    "sg:tags":[
        "contracting",
        "utility",
        "contractor"
    ],
    "wof:name":"Vintage Contracting Inc",
    "wof:placetype":"venue"
},
  "geometry": {"coordinates":[-95.221058,29.383442],"type":"Point"}
}