{
  "type": "Feature",
  "properties": {
    "iso:country":"US",
    "sg:address":"2423 E Griffin Pkwy",
    "sg:city":"Mission",
    "sg:classifiers":[
        {
            "category":"Insurance",
            "subcategory":"Insurance Agent",
            "type":"Services"
        }
    ],
    "sg:phone":"+1 956 581 6203",
    "sg:postcode":"78572",
    "sg:province":"TX",
    "sg:tags":[
        "building",
        "operator",
        "nonresidential"
    ],
    "wof:name":"Metro Office Complex",
    "wof:placetype":"venue"
},
  "geometry": {"coordinates":[-98.28230000000001,26.224069],"type":"Point"}
}