{
  "type": "Feature",
  "properties": {
    "iso:country":"US",
    "sg:address":"2106 Hawk Ln",
    "sg:city":"Amarillo",
    "sg:classifiers":[
        {
            "category":"Wholesale",
            "subcategory":"Non-durable Goods",
            "type":"Manufacturing & Wholesale Goods"
        }
    ],
    "sg:phone":"+1 806 352 7565",
    "sg:postcode":"79118",
    "sg:province":"TX",
    "wof:name":"Applause",
    "wof:placetype":"venue"
},
  "geometry": {"coordinates":[-101.813242,35.159503],"type":"Point"}
}