{
  "type": "Feature",
  "properties": {
    "iso:country":"US",
    "sg:address":"380 Campbell Acres Rd",
    "sg:city":"Cleveland",
    "sg:classifiers":[
        {
            "category":"Freight",
            "type":"Transportation"
        }
    ],
    "sg:phone":"+1 281 593 1410",
    "sg:postcode":"77328",
    "sg:province":"TX",
    "sg:tags":[
        "operator",
        "local",
        "trucking"
    ],
    "wof:name":"C & M Carriers Inc",
    "wof:placetype":"venue"
},
  "geometry": {"coordinates":[-95.09527199999999,30.388596],"type":"Point"}
}