{
  "type": "Feature",
  "properties": {
    "iso:country":"US",
    "sg:address":"910 S Grant Ave",
    "sg:city":"Odessa",
    "sg:classifiers":[
        {
            "category":"Social Services",
            "type":"Services"
        }
    ],
    "sg:phone":"+1 432 335 9622",
    "sg:postcode":"79761",
    "sg:province":"TX",
    "sg:tags":[
        "organization",
        "welfare"
    ],
    "wof:name":"YMCA Southside Day Care",
    "wof:placetype":"venue"
},
  "geometry": {"coordinates":[-102.361817,31.837435],"type":"Point"}
}