{
  "type": "Feature",
  "properties": {
    "iso:country":"US",
    "sg:address":"2414 W 12th St",
    "sg:city":"Austin",
    "sg:classifiers":[
        {
            "category":"Organizations",
            "subcategory":"Religious Organization",
            "type":"Services"
        }
    ],
    "sg:phone":"+1 512 480 9080",
    "sg:postcode":"78703",
    "sg:province":"TX",
    "wof:name":"Mesa Community",
    "wof:placetype":"venue"
},
  "geometry": {"coordinates":[-97.77084000000001,30.286063],"type":"Point"}
}