{
  "type": "Feature",
  "properties": {
    "iso:country":"US",
    "sg:address":"1124 S Buffalo St",
    "sg:city":"Canton",
    "sg:classifiers":[
        {
            "category":"Personal",
            "subcategory":"Beauty Salon",
            "type":"Services"
        }
    ],
    "sg:phone":"+1 903 567 2046",
    "sg:postcode":"75103",
    "sg:province":"TX",
    "wof:name":"Jane's Beauty Shop",
    "wof:placetype":"venue"
},
  "geometry": {"coordinates":[-95.866637,32.545533],"type":"Point"}
}