{
  "type": "Feature",
  "properties": {
    "iso:country":"US",
    "sg:address":"7180 Bandera Rd",
    "sg:city":"San Antonio",
    "sg:classifiers":[
        {
            "category":"Health Services",
            "subcategory":"Clinic",
            "type":"Services"
        }
    ],
    "sg:phone":"+1 210 682 1300",
    "sg:postcode":"78238",
    "sg:province":"TX",
    "sg:tags":[
        "dialysis"
    ],
    "wof:name":"Bandera Dialysis Facility",
    "wof:placetype":"venue"
},
  "geometry": {"coordinates":[-98.626824,29.503837],"type":"Point"}
}