{
  "type": "Feature",
  "properties": {
    "iso:country":"US",
    "sg:address":"2931 Ferndale St",
    "sg:city":"Houston",
    "sg:classifiers":[
        {
            "category":"Home & Garden",
            "subcategory":"Home Furnishings",
            "type":"Retail Goods"
        }
    ],
    "sg:phone":"+1 866 920 8226",
    "sg:postcode":"77098",
    "sg:province":"TX",
    "sg:tags":[
        "decor"
    ],
    "sg:website":"www.christmasrocks.us",
    "wof:name":"Christmas Rocks!",
    "wof:placetype":"venue"
},
  "geometry": {"coordinates":[-95.421885,29.739585],"type":"Point"}
}