{
  "type": "Feature",
  "properties": {
    "iso:country":"US",
    "sg:address":"7940 Flagstone St",
    "sg:city":"Frisco",
    "sg:classifiers":[
        {
            "category":"Professional",
            "subcategory":"Computer Services",
            "type":"Services"
        }
    ],
    "sg:phone":"+1 972 712 3258",
    "sg:postcode":"75034",
    "sg:province":"TX",
    "sg:tags":[
        "programing",
        "custom"
    ],
    "wof:name":"Plettware",
    "wof:placetype":"venue"
},
  "geometry": {"coordinates":[-96.807816,33.141562],"type":"Point"}
}