{
  "type": "Feature",
  "properties": {
    "iso:country":"US",
    "sg:address":"1906 Cannonwood Lane",
    "sg:city":"Austin",
    "sg:classifiers":[
        {
            "category":"Wholesale",
            "subcategory":"Stationery",
            "type":"Manufacturing & Wholesale Goods"
        }
    ],
    "sg:phone":"+1 512 416 7165",
    "sg:postcode":"78745",
    "sg:province":"TX",
    "sg:tags":[
        "card"
    ],
    "wof:name":"Exqusite Papers",
    "wof:placetype":"venue"
},
  "geometry": {"coordinates":[-97.801119,30.209591],"type":"Point"}
}