{
  "type": "Feature",
  "properties": {
    "iso:country":"US",
    "sg:address":"203 N Plaza Ave",
    "sg:city":"Big Lake",
    "sg:classifiers":[
        {
            "category":"Government",
            "subcategory":"Office",
            "type":"Public Place"
        }
    ],
    "sg:phone":"+1 325 884 2511",
    "sg:postcode":"76932",
    "sg:province":"TX",
    "sg:tags":[
        "village"
    ],
    "wof:name":"Big Lake City Office",
    "wof:placetype":"venue"
},
  "geometry": {"coordinates":[-101.46072599999999,31.192504],"type":"Point"}
}