{
  "type": "Feature",
  "properties": {
    "iso:country":"US",
    "sg:address":"4701 Sunshine Pkwy",
    "sg:city":"Midland",
    "sg:classifiers":[
        {
            "category":"Professional",
            "type":"Services"
        }
    ],
    "sg:phone":"+1 432 520 0140",
    "sg:postcode":"79707",
    "sg:province":"TX",
    "sg:tags":[
        "establishment"
    ],
    "wof:name":"EDOC Technologies",
    "wof:placetype":"venue"
},
  "geometry": {"coordinates":[-102.145286,32.007278],"type":"Point"}
}