{
  "type": "Feature",
  "properties": {
    "iso:country":"US",
    "sg:address":"2133 Butternut St",
    "sg:city":"Abilene",
    "sg:classifiers":[
        {
            "category":"Professional",
            "subcategory":"Business Services",
            "type":"Services"
        }
    ],
    "sg:phone":"+1 325 677 3555",
    "sg:postcode":"79602",
    "sg:province":"TX",
    "sg:tags":[
        "auctioneer"
    ],
    "wof:name":"C M Co Auctions",
    "wof:placetype":"venue"
},
  "geometry": {"coordinates":[-99.738578,32.422424],"type":"Point"}
}