{
  "type": "Feature",
  "properties": {
    "iso:country":"US",
    "sg:address":"1301 Murray Ave",
    "sg:city":"Rockdale",
    "sg:classifiers":[
        {
            "category":"Organizations",
            "subcategory":"Religious Organization",
            "type":"Services"
        }
    ],
    "sg:phone":"+1 512 446 2179",
    "sg:postcode":"76567",
    "sg:province":"TX",
    "sg:tags":[
        "church"
    ],
    "wof:name":"Church Of Christ",
    "wof:placetype":"venue"
},
  "geometry": {"coordinates":[-97.01804799999999,30.653544],"type":"Point"}
}