{
  "type": "Feature",
  "properties": {
    "iso:country":"US",
    "sg:address":"23994 Majestic Forest",
    "sg:city":"New Caney",
    "sg:classifiers":[
        {
            "category":"Shopping",
            "type":"Retail Goods"
        }
    ],
    "sg:phone":"+1 281 689 3360",
    "sg:postcode":"77357",
    "sg:province":"TX",
    "sg:tags":[
        "merchandise"
    ],
    "wof:name":"Larry G Myers",
    "wof:placetype":"venue"
},
  "geometry": {"coordinates":[-95.22158399999999,30.197423],"type":"Point"}
}