{
  "type": "Feature",
  "properties": {
    "iso:country":"US",
    "sg:address":"4438 Dowlen Rd",
    "sg:city":"Beaumont",
    "sg:classifiers":[
        {
            "category":"Professional",
            "type":"Services"
        }
    ],
    "sg:phone":"+1 409 892 5044",
    "sg:postcode":"77706",
    "sg:province":"TX",
    "sg:tags":[
        "establishment"
    ],
    "wof:name":"Silk Road",
    "wof:placetype":"venue"
},
  "geometry": {"coordinates":[-94.161827,30.121743],"type":"Point"}
}