{
  "type": "Feature",
  "properties": {
    "iso:country":"US",
    "sg:address":"2304 Serenity Ln",
    "sg:city":"Rockwall",
    "sg:classifiers":[
        {
            "category":"Home & Garden",
            "subcategory":"Furniture",
            "type":"Retail Goods"
        }
    ],
    "sg:phone":"+1 972 771 1430",
    "sg:postcode":"75032",
    "sg:province":"TX",
    "sg:tags":[
        "store"
    ],
    "wof:name":"Ginger S Collection",
    "wof:placetype":"venue"
},
  "geometry": {"coordinates":[-96.47183699999999,32.871941],"type":"Point"}
}