{
  "type": "Feature",
  "properties": {
    "iso:country":"US",
    "sg:address":"4100 Cat Hollow Dr",
    "sg:city":"Austin",
    "sg:classifiers":[
        {
            "category":"Banks & Credit Unions",
            "subcategory":"Investment Brokerage",
            "type":"Services"
        }
    ],
    "sg:phone":"+1 512 345 2000",
    "sg:postcode":"78731",
    "sg:province":"TX",
    "sg:tags":[
        "advisory"
    ],
    "wof:name":"Professional Planning Service",
    "wof:placetype":"venue"
},
  "geometry": {"coordinates":[-97.767208,30.362683],"type":"Point"}
}