{
  "type": "Feature",
  "properties": {
    "iso:country":"US",
    "sg:address":"2261 Brookhollow Plaza Dr",
    "sg:city":"Arlington",
    "sg:classifiers":[
        {
            "category":"Real Estate",
            "subcategory":"Real Estate Agent",
            "type":"Services"
        }
    ],
    "sg:phone":"+1 817 608 0075",
    "sg:postcode":"76006",
    "sg:province":"TX",
    "sg:tags":[
        "management"
    ],
    "wof:name":"Cantex Management Corporation",
    "wof:placetype":"venue"
},
  "geometry": {"coordinates":[-97.069937,32.763439],"type":"Point"}
}