{
  "type": "Feature",
  "properties": {
    "iso:country":"US",
    "sg:address":"448 Matterhorn St",
    "sg:city":"Cedar Hill",
    "sg:classifiers":[
        {
            "category":"Shopping",
            "subcategory":"Gifts & Souvenirs",
            "type":"Retail Goods"
        }
    ],
    "sg:phone":"+1 972 293 0008",
    "sg:postcode":"75104",
    "sg:province":"TX",
    "sg:tags":[
        "basket",
        "parcel"
    ],
    "wof:name":"King Karen R Gift Baskets Etc",
    "wof:placetype":"venue"
},
  "geometry": {"coordinates":[-96.939798,32.582287],"type":"Point"}
}