{
  "type": "Feature",
  "properties": {
    "iso:country":"US",
    "sg:address":"1601 Blue Bonnet St",
    "sg:city":"Vidor",
    "sg:classifiers":[
        {
            "category":"Retail",
            "subcategory":"Repair Shop",
            "type":"Services"
        }
    ],
    "sg:phone":"+1 409 769 7847",
    "sg:postcode":"77662",
    "sg:province":"TX",
    "sg:tags":[
        "mobile",
        "home"
    ],
    "wof:name":"Roys Mobile Home Service",
    "wof:placetype":"venue"
},
  "geometry": {"coordinates":[-93.986305,30.115181],"type":"Point"}
}