{
  "type": "Feature",
  "properties": {
    "iso:country":"US",
    "sg:address":"6701 Alameda Ave",
    "sg:city":"El Paso",
    "sg:classifiers":[
        {
            "category":"Retail",
            "subcategory":"Repair Shop",
            "type":"Services"
        }
    ],
    "sg:phone":"+1 915 772 6624",
    "sg:postcode":"79905",
    "sg:province":"TX",
    "wof:name":"Bueno Video",
    "wof:placetype":"venue"
},
  "geometry": {"coordinates":[-106.404747,31.764035],"type":"Point"}
}