{
  "type": "Feature",
  "properties": {
    "iso:country":"US",
    "sg:address":"10401 Greenbough Dr",
    "sg:city":"Stafford",
    "sg:classifiers":[
        {
            "category":"Wholesale",
            "subcategory":"Machinery & Supplies",
            "type":"Manufacturing & Wholesale Goods"
        }
    ],
    "sg:phone":"+1 281 403 2870",
    "sg:postcode":"77477",
    "sg:province":"TX",
    "sg:tags":[
        "equipment",
        "welding"
    ],
    "wof:name":"WOKA North America",
    "wof:placetype":"venue"
},
  "geometry": {"coordinates":[-95.56186599999999,29.620959],"type":"Point"}
}