{
  "type": "Feature",
  "properties": {
    "iso:country":"US",
    "sg:address":"3228 E Euless Blvd",
    "sg:city":"Euless",
    "sg:classifiers":[
        {
            "category":"Manufacturing",
            "subcategory":"Printing",
            "type":"Manufacturing & Wholesale Goods"
        }
    ],
    "sg:phone":"+1 817 571 9966",
    "sg:postcode":"76040",
    "sg:province":"TX",
    "sg:tags":[
        "printer"
    ],
    "wof:name":"Trans Continental Cc 3",
    "wof:placetype":"venue"
},
  "geometry": {"coordinates":[-97.135633,32.816055],"type":"Point"}
}