{
  "type": "Feature",
  "properties": {
    "iso:country":"US",
    "sg:address":"131 Clubhouse Dr",
    "sg:city":"Austin",
    "sg:classifiers":[
        {
            "category":"Farming",
            "subcategory":"Farm",
            "type":"Manufacturing & Wholesale Goods"
        }
    ],
    "sg:phone":"+1 512 261 1806",
    "sg:postcode":"78734",
    "sg:province":"TX",
    "sg:tags":[
        "crop",
        "general"
    ],
    "wof:name":"Bella Verdi Farms LLC",
    "wof:placetype":"venue"
},
  "geometry": {"coordinates":[-97.966589,30.364297],"type":"Point"}
}