{
  "type": "Feature",
  "properties": {
    "iso:country":"US",
    "sg:address":"702 N Grand Ave",
    "sg:city":"Gainesville",
    "sg:classifiers":[
        {
            "category":"Personal",
            "subcategory":"Beauty Salon",
            "type":"Services"
        }
    ],
    "sg:phone":"+1 940 580 3535",
    "sg:postcode":"76240",
    "sg:province":"TX",
    "sg:tags":[
        "hair",
        "stylist"
    ],
    "wof:name":"Hair After",
    "wof:placetype":"venue"
},
  "geometry": {"coordinates":[-97.133399,33.630564],"type":"Point"}
}