{
  "type": "Feature",
  "properties": {
    "iso:country":"US",
    "sg:address":"8607 Ferris Dr",
    "sg:city":"Houston",
    "sg:classifiers":[
        {
            "category":"Manufacturing",
            "subcategory":"Paper Products",
            "type":"Manufacturing & Wholesale Goods"
        }
    ],
    "sg:phone":"+1 713 666 7614",
    "sg:postcode":"77096",
    "sg:province":"TX",
    "sg:tags":[
        "adhesive",
        "mfg",
        "coating",
        "high",
        "performance",
        "distributes"
    ],
    "wof:name":"Tetra Chemical Inc",
    "wof:placetype":"venue"
},
  "geometry": {"coordinates":[-95.47218100000001,29.68634],"type":"Point"}
}