{
  "type": "Feature",
  "properties": {
    "iso:country":"US",
    "sg:address":"1101 Charlotte St",
    "sg:city":"Austin",
    "sg:classifiers":[
        {
            "category":"Professional",
            "subcategory":"Computer Services",
            "type":"Services"
        }
    ],
    "sg:phone":"+1 512 657 5700",
    "sg:postcode":"78703",
    "sg:province":"TX",
    "sg:tags":[
        "repair"
    ],
    "wof:name":"Machanic",
    "wof:placetype":"venue"
},
  "geometry": {"coordinates":[-97.76093299999999,30.281148],"type":"Point"}
}