{
  "type": "Feature",
  "properties": {
    "iso:country":"US",
    "sg:address":"1713 Lilley Ave",
    "sg:city":"Cleveland",
    "sg:classifiers":[
        {
            "category":"Building & Trades",
            "subcategory":"Construction",
            "type":"Services"
        }
    ],
    "sg:phone":"+1 281 592 1009",
    "sg:postcode":"77327",
    "sg:province":"TX",
    "sg:tags":[
        "general",
        "contractor"
    ],
    "wof:name":"D C Construction",
    "wof:placetype":"venue"
},
  "geometry": {"coordinates":[-95.07533599999999,30.358722],"type":"Point"}
}