{
  "type": "Feature",
  "properties": {
    "iso:country":"US",
    "sg:address":"1603 Cartwright Rd",
    "sg:city":"Missouri City",
    "sg:classifiers":[
        {
            "category":"Shopping",
            "subcategory":"Jewelry",
            "type":"Retail Goods"
        }
    ],
    "sg:phone":"+1 281 835 0433",
    "sg:postcode":"77489",
    "sg:province":"TX",
    "wof:name":"Jewelryrama",
    "wof:placetype":"venue"
},
  "geometry": {"coordinates":[-95.526202,29.583482],"type":"Point"}
}