{
  "type": "Feature",
  "properties": {
    "iso:country":"US",
    "sg:address":"6401 Gateway Blvd W",
    "sg:city":"El Paso",
    "sg:classifiers":[
        {
            "category":"Restaurant",
            "type":"Food & Drink"
        }
    ],
    "sg:phone":"+1 915 772 5767",
    "sg:postcode":"79925",
    "sg:province":"TX",
    "sg:tags":[
        "parlor",
        "ice",
        "cream"
    ],
    "wof:name":"TCBY",
    "wof:placetype":"venue"
},
  "geometry": {"coordinates":[-106.40052900000001,31.78243],"type":"Point"}
}