{
  "type": "Feature",
  "properties": {
    "iso:country":"US",
    "sg:address":"2626 Wolflin Ave",
    "sg:city":"Amarillo",
    "sg:classifiers":[
        {
            "category":"Health Services",
            "subcategory":"Clinic",
            "type":"Services"
        }
    ],
    "sg:phone":"+1 806 351 0296",
    "sg:postcode":"79109",
    "sg:province":"TX",
    "wof:name":"Pam's Gentle Touch",
    "wof:placetype":"venue"
},
  "geometry": {"coordinates":[-101.86418999999999,35.19289],"type":"Point"}
}