{
  "type": "Feature",
  "properties": {
    "iso:country":"US",
    "sg:address":"301 W Sam Rayburn Dr",
    "sg:city":"Bonham",
    "sg:classifiers":[
        {
            "category":"Shopping",
            "subcategory":"Florist",
            "type":"Retail Goods"
        }
    ],
    "sg:phone":"+1 903 583 3725",
    "sg:postcode":"75418",
    "sg:province":"TX",
    "wof:name":"Judys Garden Shed",
    "wof:placetype":"venue"
},
  "geometry": {"coordinates":[-96.182587,33.577141],"type":"Point"}
}