{
  "type": "Feature",
  "properties": {
    "iso:country":"US",
    "sg:address":"703 Throckmorton St",
    "sg:city":"Rockwall",
    "sg:classifiers":[
        {
            "category":"Shopping",
            "subcategory":"Music",
            "type":"Retail Goods"
        }
    ],
    "sg:phone":"+1 972 771 3710",
    "sg:postcode":"75087",
    "sg:province":"TX",
    "wof:name":"Blaz Em Up Records & Ent",
    "wof:placetype":"venue"
},
  "geometry": {"coordinates":[-96.459456,32.924354],"type":"Point"}
}