{
  "type": "Feature",
  "properties": {
    "iso:country":"US",
    "sg:address":"1840 N Lee Trevino Dr",
    "sg:city":"El Paso",
    "sg:classifiers":[
        {
            "category":"Shopping",
            "subcategory":"Clothing, Apparel, & Fashions",
            "type":"Retail Goods"
        }
    ],
    "sg:phone":"+1 915 629 7191",
    "sg:postcode":"79936",
    "sg:province":"TX",
    "sg:tags":[
        "sportswear"
    ],
    "wof:name":"Sport Xplosion",
    "wof:placetype":"venue"
},
  "geometry": {"coordinates":[-106.31890300000001,31.767667],"type":"Point"}
}