{
  "type": "Feature",
  "properties": {
    "iso:country":"US",
    "sg:address":"7681 Cambridge St",
    "sg:city":"Houston",
    "sg:classifiers":[
        {
            "category":"Building & Trades",
            "subcategory":"Equipment Rental",
            "type":"Services"
        }
    ],
    "sg:phone":"+1 713 796 2241",
    "sg:postcode":"77054",
    "sg:province":"TX",
    "wof:name":"Texas Health Technologies",
    "wof:placetype":"venue"
},
  "geometry": {"coordinates":[-95.392064,29.694052],"type":"Point"}
}