{
  "type": "Feature",
  "properties": {
    "iso:country":"US",
    "sg:address":"2325 Co Rd 90",
    "sg:city":"Pearland",
    "sg:classifiers":[
        {
            "category":"Social Services",
            "subcategory":"Child Care",
            "type":"Services"
        }
    ],
    "sg:phone":"+1 281 485 8667",
    "sg:postcode":"77584",
    "sg:province":"TX",
    "sg:tags":[
        "day"
    ],
    "wof:name":"Children's World Learning Ctr",
    "wof:placetype":"venue"
},
  "geometry": {"coordinates":[-95.367278,29.554569],"type":"Point"}
}