{
  "type": "Feature",
  "properties": {
    "iso:country":"US",
    "sg:address":"19001 Mirror Lake Dr",
    "sg:city":"Spring",
    "sg:classifiers":[
        {
            "category":"Utilities",
            "subcategory":"Electric",
            "type":"Services"
        }
    ],
    "sg:phone":"+1 281 350 5601",
    "sg:postcode":"77388",
    "sg:province":"TX",
    "sg:tags":[
        "company"
    ],
    "wof:name":"Klein Public Utility District",
    "wof:placetype":"venue"
},
  "geometry": {"coordinates":[-95.461322,30.040937],"type":"Point"}
}