{
  "type": "Feature",
  "properties": {
    "iso:country":"US",
    "sg:address":"150 S Denton Tap Rd Ste 116",
    "sg:city":"Coppell",
    "sg:classifiers":[
        {
            "category":"Health Services",
            "subcategory":"Doctor",
            "type":"Services"
        }
    ],
    "sg:phone":"+1 972 304 0091",
    "sg:postcode":"75019",
    "sg:province":"TX",
    "wof:name":"Ulanoski Pamela MD",
    "wof:placetype":"venue"
},
  "geometry": {"coordinates":[-96.99328,32.965714],"type":"Point"}
}