{
  "type": "Feature",
  "properties": {
    "iso:country":"US",
    "sg:address":"1305 W Main St",
    "sg:city":"Atlanta",
    "sg:classifiers":[
        {
            "category":"Insurance",
            "subcategory":"Insurance Agent",
            "type":"Services"
        }
    ],
    "sg:phone":"+1 903 799 6341",
    "sg:postcode":"75551",
    "sg:province":"TX",
    "wof:name":"Jeff Hobbs Insurance",
    "wof:placetype":"venue"
},
  "geometry": {"coordinates":[-94.183634,33.110922],"type":"Point"}
}