{
  "type": "Feature",
  "properties": {
    "iso:country":"US",
    "sg:address":"2306 Line Ave",
    "sg:city":"Amarillo",
    "sg:classifiers":[
        {
            "category":"Professional",
            "subcategory":"Accounting & Tax Preparation",
            "type":"Services"
        }
    ],
    "sg:phone":"+1 806 373 7163",
    "sg:postcode":"79106",
    "sg:province":"TX",
    "sg:tags":[
        "accountant"
    ],
    "wof:name":"John Gressett CPA",
    "wof:placetype":"venue"
},
  "geometry": {"coordinates":[-101.86327,35.208172],"type":"Point"}
}