{
  "type": "Feature",
  "properties": {
    "iso:country":"US",
    "sg:address":"7808 Southwestern Blvd",
    "sg:city":"Dallas",
    "sg:classifiers":[
        {
            "category":"Building & Trades",
            "subcategory":"Construction",
            "type":"Services"
        }
    ],
    "sg:phone":"+1 214 750 7676",
    "sg:postcode":"75225",
    "sg:province":"TX",
    "sg:tags":[
        "roofing",
        "contractor"
    ],
    "wof:name":"Rent-A-Handyman Inc",
    "wof:placetype":"venue"
},
  "geometry": {"coordinates":[-96.77083500000001,32.857017],"type":"Point"}
}