{
  "type": "Feature",
  "properties": {
    "iso:country":"US",
    "sg:address":"7305 Lea Pl",
    "sg:city":"Fort Worth",
    "sg:classifiers":[
        {
            "category":"Shopping",
            "subcategory":"Clothing, Apparel, & Fashions",
            "type":"Retail Goods"
        }
    ],
    "sg:phone":"+1 817 568 0219",
    "sg:postcode":"76140",
    "sg:province":"TX",
    "wof:name":"Qrazi KURL & Klothing",
    "wof:placetype":"venue"
},
  "geometry": {"coordinates":[-97.27994200000001,32.647505],"type":"Point"}
}