{
  "type": "Feature",
  "properties": {
    "iso:country":"US",
    "sg:address":"1205 Esther Blvd",
    "sg:city":"Bryan",
    "sg:classifiers":[
        {
            "category":"Shopping",
            "subcategory":"Gifts & Souvenirs",
            "type":"Retail Goods"
        }
    ],
    "sg:phone":"+1 979 775 1953",
    "sg:postcode":"77802",
    "sg:province":"TX",
    "wof:name":"Balloons By Ruth",
    "wof:placetype":"venue"
},
  "geometry": {"coordinates":[-96.353207,30.65613],"type":"Point"}
}