{
  "type": "Feature",
  "properties": {
    "iso:country":"US",
    "sg:address":"11103 Mills Rd",
    "sg:city":"Cypress",
    "sg:classifiers":[
        {
            "category":"Social Services",
            "subcategory":"Child Care",
            "type":"Services"
        }
    ],
    "sg:phone":"+1 281 469 9616",
    "sg:postcode":"77429",
    "sg:province":"TX",
    "sg:tags":[
        "day"
    ],
    "wof:name":"Montessori Child Dev Ctr Inc",
    "wof:placetype":"venue"
},
  "geometry": {"coordinates":[-95.585464,29.961084],"type":"Point"}
}