{
  "type": "Feature",
  "properties": {
    "iso:country":"US",
    "sg:address":"98 Windmill Rd",
    "sg:city":"San Antonio",
    "sg:classifiers":[
        {
            "category":"Professional",
            "subcategory":"Business Services",
            "type":"Services"
        }
    ],
    "sg:phone":"+1 210 492 1117",
    "sg:postcode":"78231",
    "sg:province":"TX",
    "wof:name":"Fh Mahan Enterprises Inc",
    "wof:placetype":"venue"
},
  "geometry": {"coordinates":[-98.55014,29.584391],"type":"Point"}
}