{
  "type": "Feature",
  "properties": {
    "iso:country":"US",
    "sg:address":"2006 Whitefeather Trl",
    "sg:city":"Crosby",
    "sg:classifiers":[
        {
            "category":"Manufacturing",
            "subcategory":"Furniture",
            "type":"Manufacturing & Wholesale Goods"
        }
    ],
    "sg:phone":"+1 281 324 9394",
    "sg:postcode":"77532",
    "sg:province":"TX",
    "sg:tags":[
        "household",
        "mfg"
    ],
    "wof:name":"Raccoon Golf Harmony Millwork",
    "wof:placetype":"venue"
},
  "geometry": {"coordinates":[-95.11704400000001,29.979356],"type":"Point"}
}