{
  "type": "Feature",
  "properties": {
    "iso:country":"US",
    "sg:address":"1601 N Travis St",
    "sg:city":"Sherman",
    "sg:classifiers":[
        {
            "category":"Professional",
            "subcategory":"Accounting & Tax Preparation",
            "type":"Services"
        }
    ],
    "sg:phone":"+1 903 893 7428",
    "sg:postcode":"75092",
    "sg:province":"TX",
    "sg:tags":[
        "accountant"
    ],
    "wof:name":"Snyder & Grisham LLP",
    "wof:placetype":"venue"
},
  "geometry": {"coordinates":[-96.61429699999999,33.652574],"type":"Point"}
}