{
  "type": "Feature",
  "properties": {
    "iso:country":"US",
    "sg:address":"100 Cactus Dr",
    "sg:city":"Robstown",
    "sg:classifiers":[
        {
            "category":"Personal",
            "type":"Services"
        }
    ],
    "sg:phone":"+1 361 767 4958",
    "sg:postcode":"78380",
    "sg:province":"TX",
    "sg:tags":[
        "therapist",
        "massage"
    ],
    "wof:name":"Wellness Massage Therapy",
    "wof:placetype":"venue"
},
  "geometry": {"coordinates":[-97.663687,27.808622],"type":"Point"}
}