{
  "type": "Feature",
  "properties": {
    "iso:country":"US",
    "sg:address":"402 W Grand Pkwy S",
    "sg:city":"Katy",
    "sg:classifiers":[
        {
            "category":"Restaurant",
            "type":"Food & Drink"
        }
    ],
    "sg:menulink":"http://www.allmenus.com/tx/houston/139532-quiznos-sub/menu/",
    "sg:phone":"+1 281 693 2349",
    "sg:postcode":"77494",
    "sg:province":"TX",
    "sg:tags":[
        "wrap",
        "american",
        "sandwich"
    ],
    "wof:name":"Quiznos Sub",
    "wof:placetype":"venue"
},
  "geometry": {"coordinates":[-95.77781899999999,29.780611],"type":"Point"}
}