{
  "type": "Feature",
  "properties": {
    "iso:country":"US",
    "sg:address":"5408 San Bernardo Ave",
    "sg:city":"Laredo",
    "sg:classifiers":[
        {
            "category":"Shopping",
            "subcategory":"Stationery & Office Supplies",
            "type":"Retail Goods"
        }
    ],
    "sg:phone":"+1 956 791 0251",
    "sg:postcode":"78041",
    "sg:province":"TX",
    "wof:name":"Office Max",
    "wof:placetype":"venue"
},
  "geometry": {"coordinates":[-99.504323,27.551575],"type":"Point"}
}