{
  "type": "Feature",
  "properties": {
    "iso:country":"US",
    "sg:address":"110 SE 1st St",
    "sg:city":"Morton",
    "sg:classifiers":[
        {
            "category":"Retail",
            "subcategory":"Auto Repair",
            "type":"Services"
        }
    ],
    "sg:phone":"+1 806 266 5741",
    "sg:postcode":"79346",
    "sg:province":"TX",
    "sg:tags":[
        "repairing",
        "automobile",
        "general"
    ],
    "wof:name":"Jay's Garage & Machine Shop",
    "wof:placetype":"venue"
},
  "geometry": {"coordinates":[-102.75811299999999,33.725097],"type":"Point"}
}