{
  "type": "Feature",
  "properties": {
    "iso:country":"US",
    "sg:address":"606 Stonehenge Dr",
    "sg:city":"Grand Prairie",
    "sg:classifiers":[
        {
            "category":"Professional",
            "subcategory":"Advertising",
            "type":"Services"
        }
    ],
    "sg:phone":"+1 972 504 8007",
    "sg:postcode":"75052",
    "sg:province":"TX",
    "sg:tags":[
        "agency"
    ],
    "wof:name":"Eye Candy",
    "wof:placetype":"venue"
},
  "geometry": {"coordinates":[-97.011501,32.699148],"type":"Point"}
}