{
  "type": "Feature",
  "properties": {
    "iso:country":"US",
    "sg:address":"2314 N Main St",
    "sg:city":"Belton",
    "sg:classifiers":[
        {
            "category":"Building & Trades",
            "subcategory":"Construction",
            "type":"Services"
        }
    ],
    "sg:phone":"+1 254 939 6550",
    "sg:postcode":"76513",
    "sg:province":"TX",
    "sg:tags":[
        "house"
    ],
    "wof:name":"Central Texas Designs",
    "wof:placetype":"venue"
},
  "geometry": {"coordinates":[-97.45732099999999,31.078395],"type":"Point"}
}