{
  "type": "Feature",
  "properties": {
    "iso:country":"US",
    "sg:address":"3699 McKinney Ave",
    "sg:city":"Dallas",
    "sg:classifiers":[
        {
            "category":"Professional",
            "type":"Services"
        }
    ],
    "sg:phone":"+1 214 559 2455",
    "sg:postcode":"75204",
    "sg:province":"TX",
    "sg:tags":[
        "arts",
        "artist"
    ],
    "wof:name":"Nieto Fine Art",
    "wof:placetype":"venue"
},
  "geometry": {"coordinates":[-96.797642,32.806948],"type":"Point"}
}