{
  "type": "Feature",
  "properties": {
    "iso:country":"US",
    "sg:address":"101 N Donald St",
    "sg:city":"Seymour",
    "sg:classifiers":[
        {
            "category":"Wholesale",
            "subcategory":"Home Furnishings",
            "type":"Manufacturing & Wholesale Goods"
        }
    ],
    "sg:phone":"+1 940 888 2748",
    "sg:postcode":"76380",
    "sg:province":"TX",
    "wof:name":"Charles Malone",
    "wof:placetype":"venue"
},
  "geometry": {"coordinates":[-99.26649500000001,33.588975],"type":"Point"}
}