{
  "type": "Feature",
  "properties": {
    "iso:country":"US",
    "sg:address":"112 Detroit Ave",
    "sg:city":"Levelland",
    "sg:classifiers":[
        {
            "category":"Professional",
            "type":"Services"
        }
    ],
    "sg:phone":"+1 806 894 4874",
    "sg:postcode":"79336",
    "sg:province":"TX",
    "wof:name":"Camp Bluegrass Inc",
    "wof:placetype":"venue"
},
  "geometry": {"coordinates":[-102.35687,33.586376],"type":"Point"}
}