{
  "type": "Feature",
  "properties": {
    "iso:country":"US",
    "sg:address":"420 McCaleb Rd",
    "sg:city":"Montgomery",
    "sg:classifiers":[
        {
            "category":"Freight",
            "type":"Transportation"
        },
        {
            "category":"Recreation",
            "subcategory":"Marina",
            "type":"Entertainment"
        }
    ],
    "sg:phone":"+1 936 588 4582",
    "sg:postcode":"77316",
    "sg:province":"TX",
    "sg:tags":[
        "storage",
        "boat",
        "general"
    ],
    "wof:name":"Stor More Storage",
    "wof:placetype":"venue"
},
  "geometry": {"coordinates":[-95.58315,30.352635],"type":"Point"}
}