{
  "type": "Feature",
  "properties": {
    "iso:country":"US",
    "sg:address":"3234 Modella Ave",
    "sg:city":"Dallas",
    "sg:classifiers":[
        {
            "category":"Wholesale",
            "subcategory":"Drugs",
            "type":"Manufacturing & Wholesale Goods"
        }
    ],
    "sg:phone":"+1 972 241 4398",
    "sg:postcode":"75229",
    "sg:province":"TX",
    "wof:name":"Marilou Felarca",
    "wof:placetype":"venue"
},
  "geometry": {"coordinates":[-96.868664,32.906622],"type":"Point"}
}