{
  "type": "Feature",
  "properties": {
    "iso:country":"US",
    "sg:address":"8802 Harry Hines Blvd",
    "sg:city":"Dallas",
    "sg:classifiers":[
        {
            "category":"Organizations",
            "subcategory":"Professional Association",
            "type":"Services"
        },
        {
            "category":"Organizations",
            "subcategory":"Community Association",
            "type":"Services"
        }
    ],
    "sg:phone":"+1 214 351 2500",
    "sg:postcode":"75235",
    "sg:province":"TX",
    "sg:tags":[
        "charitable"
    ],
    "sg:website":"www.ucpdallas.org",
    "wof:name":"United Cerebral Palsy Metro Da",
    "wof:placetype":"venue"
},
  "geometry": {"coordinates":[-96.868393,32.839856],"type":"Point"}
}