{
  "type": "Feature",
  "properties": {
    "iso:country":"US",
    "sg:address":"1220 Holt Ave",
    "sg:city":"De Soto",
    "sg:classifiers":[
        {
            "category":"Building & Trades",
            "subcategory":"Construction",
            "type":"Services"
        }
    ],
    "sg:phone":"+1 972 224 8812",
    "sg:postcode":"75115",
    "sg:province":"TX",
    "sg:tags":[
        "house"
    ],
    "wof:name":"Willis Construction",
    "wof:placetype":"venue"
},
  "geometry": {"coordinates":[-96.85633,32.612141],"type":"Point"}
}