{
  "type": "Feature",
  "properties": {
    "iso:country":"US",
    "sg:address":"26343 Anderson Rd",
    "sg:city":"Magnolia",
    "sg:classifiers":[
        {
            "category":"Manufacturing",
            "subcategory":"Tools & Machinery",
            "type":"Manufacturing & Wholesale Goods"
        },
        {
            "category":"Industrial Area",
            "type":"Public Place"
        }
    ],
    "sg:phone":"+1 281 259 1114",
    "sg:postcode":"77354",
    "sg:province":"TX",
    "sg:tags":[
        "repair",
        "equipment-repairing",
        "machinery-rebuild"
    ],
    "wof:name":"Gulf Coast Centrifuge",
    "wof:placetype":"venue"
},
  "geometry": {"coordinates":[-95.635406,30.153432],"type":"Point"}
}