{
  "type": "Feature",
  "properties": {
    "iso:country":"US",
    "sg:address":"310 US Hwy 59S Bus",
    "sg:city":"El Campo",
    "sg:classifiers":[
        {
            "category":"Travel",
            "subcategory":"Hotels & Motels",
            "type":"Entertainment"
        }
    ],
    "sg:phone":"+1 979 543 1666",
    "sg:postcode":"77437",
    "sg:province":"TX",
    "wof:name":"Shoney's Inn",
    "wof:placetype":"venue"
},
  "geometry": {"coordinates":[-96.266852,29.198513],"type":"Point"}
}