{
  "type": "Feature",
  "properties": {
    "iso:country":"US",
    "sg:address":"1120 N Beach St",
    "sg:city":"Fort Worth",
    "sg:classifiers":[
        {
            "category":"Food & Beverages",
            "subcategory":"Liquor & Beverages",
            "type":"Retail Goods"
        }
    ],
    "sg:phone":"+1 817 831 3577",
    "sg:postcode":"76111",
    "sg:province":"TX",
    "sg:tags":[
        "alcoholic"
    ],
    "wof:name":"Fort Worth Discount Liquor",
    "wof:placetype":"venue"
},
  "geometry": {"coordinates":[-97.288765,32.776288],"type":"Point"}
}