{
  "type": "Feature",
  "properties": {
    "iso:country":"US",
    "sg:address":"2891 Hunter Rd",
    "sg:city":"New Braunfels",
    "sg:classifiers":[
        {
            "category":"Wholesale",
            "subcategory":"Farm Supplies",
            "type":"Manufacturing & Wholesale Goods"
        }
    ],
    "sg:phone":"+1 830 625 2289",
    "sg:postcode":"78132",
    "sg:province":"TX",
    "sg:tags":[
        "feed",
        "liquid"
    ],
    "wof:name":"Koepp Liquid Feed Service",
    "wof:placetype":"venue"
},
  "geometry": {"coordinates":[-98.092561,29.753221],"type":"Point"}
}