{
  "type": "Feature",
  "properties": {
    "iso:country":"US",
    "sg:address":"11423 S Meadow Joy Dr",
    "sg:city":"Houston",
    "sg:classifiers":[
        {
            "category":"Home & Garden",
            "subcategory":"Furniture",
            "type":"Retail Goods"
        }
    ],
    "sg:phone":"+1 281 484 4314",
    "sg:postcode":"77089",
    "sg:province":"TX",
    "wof:name":"Virginia G Flores",
    "wof:placetype":"venue"
},
  "geometry": {"coordinates":[-95.204881,29.590511],"type":"Point"}
}