{
  "type": "Feature",
  "properties": {
    "iso:country":"US",
    "sg:address":"3100 Wilcrest Dr",
    "sg:city":"Houston",
    "sg:classifiers":[
        {
            "category":"Mining & Drilling",
            "type":"Manufacturing & Wholesale Goods"
        }
    ],
    "sg:phone":"+1 713 953 7718",
    "sg:postcode":"77042",
    "sg:province":"TX",
    "sg:tags":[
        "development",
        "gas",
        "oil",
        "exploration"
    ],
    "wof:name":"DMS Oil Co",
    "wof:placetype":"venue"
},
  "geometry": {"coordinates":[-95.571749,29.730316],"type":"Point"}
}