{
  "type": "Feature",
  "properties": {
    "iso:country":"US",
    "sg:address":"120 W Oak St",
    "sg:city":"Palestine",
    "sg:classifiers":[
        {
            "category":"Restaurant",
            "type":"Food & Drink"
        }
    ],
    "sg:phone":"+1 903 729 4410",
    "sg:postcode":"75801",
    "sg:province":"TX",
    "sg:tags":[
        "eating"
    ],
    "wof:name":"Old Magnolia Mercantile",
    "wof:placetype":"venue"
},
  "geometry": {"coordinates":[-95.63228700000001,31.76254],"type":"Point"}
}