{
  "type": "Feature",
  "properties": {
    "iso:country":"US",
    "sg:address":"500 Dallas St",
    "sg:city":"Plainview",
    "sg:phone":"+1 806 293 8363",
    "sg:postcode":"79072",
    "sg:province":"TX",
    "sg:website":"http://www.countywidetitleco.com",
    "wof:name":"Countywide Title Co",
    "wof:placetype":"venue"
},
  "geometry": {"coordinates":[-101.740494,34.183996],"type":"Point"}
}