{
  "type": "Feature",
  "properties": {
    "iso:country":"US",
    "sg:address":"541 S Texas Blvd",
    "sg:city":"Weslaco",
    "sg:classifiers":[
        {
            "category":"Banks & Credit Unions",
            "subcategory":"Bank",
            "type":"Services"
        }
    ],
    "sg:phone":"+1 956 973 2818",
    "sg:postcode":"78596",
    "sg:province":"TX",
    "sg:tags":[
        "institution",
        "business"
    ],
    "wof:name":"Aztec Finance Company",
    "wof:placetype":"venue"
},
  "geometry": {"coordinates":[-97.990549,26.1564],"type":"Point"}
}