{
  "type": "Feature",
  "properties": {
    "iso:country":"US",
    "sg:address":"1401 N 13th St",
    "sg:city":"Ballinger",
    "sg:classifiers":[
        {
            "category":"Restaurant",
            "type":"Food & Drink"
        }
    ],
    "sg:phone":"+1 325 365 4272",
    "sg:postcode":"76821",
    "sg:province":"TX",
    "sg:tags":[
        "mexican"
    ],
    "wof:name":"Don Pablos Burritos",
    "wof:placetype":"venue"
},
  "geometry": {"coordinates":[-99.96670899999999,31.743295],"type":"Point"}
}