{
  "type": "Feature",
  "properties": {
    "iso:country":"US",
    "sg:address":"1102 Explorer St",
    "sg:city":"Duncanville",
    "sg:classifiers":[
        {
            "category":"Manufacturing",
            "subcategory":"Printing",
            "type":"Manufacturing & Wholesale Goods"
        }
    ],
    "sg:phone":"+1 972 780 0776",
    "sg:postcode":"75137",
    "sg:province":"TX",
    "sg:tags":[
        "printer"
    ],
    "wof:name":"Vision Printing",
    "wof:placetype":"venue"
},
  "geometry": {"coordinates":[-96.92265,32.640032],"type":"Point"}
}