{
  "type": "Feature",
  "properties": {
    "iso:country":"US",
    "sg:address":"1415 N 18th St",
    "sg:city":"Memphis",
    "sg:classifiers":[
        {
            "category":"Health Services",
            "subcategory":"Nursing And Care Facility",
            "type":"Services"
        }
    ],
    "sg:phone":"+1 806 259 3566",
    "sg:postcode":"79245",
    "sg:province":"TX",
    "sg:tags":[
        "home",
        "convalescent"
    ],
    "wof:name":"Memphis Convalescent Ctr",
    "wof:placetype":"venue"
},
  "geometry": {"coordinates":[-100.55211,34.736491],"type":"Point"}
}