{
  "type": "Feature",
  "properties": {
    "iso:country":"US",
    "sg:address":"724 State Hwy 46",
    "sg:city":"New Braunfels",
    "sg:classifiers":[
        {
            "category":"Personal",
            "type":"Services"
        }
    ],
    "sg:phone":"+1 830 629 2150",
    "sg:postcode":"78130",
    "sg:province":"TX",
    "sg:tags":[
        "therapist",
        "massage"
    ],
    "wof:name":"Massage & Trigger Point Thrpy",
    "wof:placetype":"venue"
},
  "geometry": {"coordinates":[-98.068955,29.687999],"type":"Point"}
}