{
  "type": "Feature",
  "properties": {
    "iso:country":"US",
    "sg:address":"110 S Main St",
    "sg:city":"Winters",
    "sg:classifiers":[
        {
            "category":"Government",
            "subcategory":"Office",
            "type":"Public Place"
        }
    ],
    "sg:phone":"+1 325 754 5469",
    "sg:postcode":"79567",
    "sg:province":"TX",
    "sg:tags":[
        "program",
        "administrative"
    ],
    "wof:name":"Human Services Texas Dept of",
    "wof:placetype":"venue"
},
  "geometry": {"coordinates":[-99.962735,31.957599],"type":"Point"}
}