{
  "type": "Feature",
  "properties": {
    "iso:country":"US",
    "sg:address":"1400 Allston St",
    "sg:city":"Houston",
    "sg:classifiers":[
        {
            "category":"Restaurant",
            "type":"Food & Drink"
        }
    ],
    "sg:phone":"+1 713 880 2166",
    "sg:postcode":"77008",
    "sg:province":"TX",
    "sg:tags":[
        "new",
        "american"
    ],
    "sg:website":"www.houseintheheights.com",
    "wof:name":"House In the Heights",
    "wof:placetype":"venue"
},
  "geometry": {"coordinates":[-95.40010100000001,29.796499],"type":"Point"}
}