{
  "type": "Feature",
  "properties": {
    "iso:country":"US",
    "sg:address":"5103 Old Jacksboro Hwy",
    "sg:city":"Wichita Falls",
    "sg:classifiers":[
        {
            "category":"Retail",
            "subcategory":"Auto Repair",
            "type":"Services"
        },
        {
            "category":"Wholesale",
            "subcategory":"Auto Parts",
            "type":"Manufacturing & Wholesale Goods"
        }
    ],
    "sg:phone":"+1 940 766 5252",
    "sg:postcode":"76302",
    "sg:province":"TX",
    "sg:tags":[
        "repairing",
        "automobile",
        "transmission"
    ],
    "wof:name":"Master Tech Automotive",
    "wof:placetype":"venue"
},
  "geometry": {"coordinates":[-98.494456,33.85367],"type":"Point"}
}