{
  "type": "Feature",
  "properties": {
    "iso:country":"US",
    "sg:address":"200 N Loraine St",
    "sg:city":"Midland",
    "sg:classifiers":[
        {
            "category":"Professional",
            "type":"Services"
        }
    ],
    "sg:phone":"+1 432 682 7327",
    "sg:postcode":"79701",
    "sg:province":"TX",
    "sg:tags":[
        "geophysicist"
    ],
    "sg:website":"www.rallyexploration.com",
    "wof:name":"Rally Exploration Inc",
    "wof:placetype":"venue"
},
  "geometry": {"coordinates":[-102.07566,31.999575],"type":"Point"}
}