{
  "type": "Feature",
  "properties": {
    "iso:country":"US",
    "sg:address":"11914 Cedarcliff Dr",
    "sg:city":"Houston",
    "sg:classifiers":[
        {
            "category":"Building & Trades",
            "subcategory":"Construction",
            "type":"Services"
        }
    ],
    "sg:phone":"+1 281 955 1915",
    "sg:postcode":"77070",
    "sg:province":"TX",
    "sg:tags":[
        "concrete",
        "contractor"
    ],
    "wof:name":"Arrow Concrete Services",
    "wof:placetype":"venue"
},
  "geometry": {"coordinates":[-95.570847,29.947381],"type":"Point"}
}