{
  "type": "Feature",
  "properties": {
    "iso:country":"US",
    "sg:address":"4102 S Staples St",
    "sg:city":"Corpus Christi",
    "sg:classifiers":[
        {
            "category":"Banks & Credit Unions",
            "subcategory":"Bank",
            "type":"Services"
        }
    ],
    "sg:phone":"+1 361 814 2935",
    "sg:postcode":"78411",
    "sg:province":"TX",
    "wof:name":"Prosperity Bank",
    "wof:placetype":"venue"
},
  "geometry": {"coordinates":[-97.377955,27.724816],"type":"Point"}
}