{
  "type": "Feature",
  "properties": {
    "iso:country":"US",
    "sg:address":"2002 Judson Rd",
    "sg:city":"Longview",
    "sg:classifiers":[
        {
            "category":"Shopping",
            "subcategory":"Clothing, Apparel, & Fashions",
            "type":"Retail Goods"
        }
    ],
    "sg:phone":"+1 903 753 6106",
    "sg:postcode":"75605",
    "sg:province":"TX",
    "wof:name":"Stella T's",
    "wof:placetype":"venue"
},
  "geometry": {"coordinates":[-94.744463,32.536175],"type":"Point"}
}