{
  "type": "Feature",
  "properties": {
    "iso:country":"US",
    "sg:address":"3520 Grapevine Mills Pkwy",
    "sg:city":"Grapevine",
    "sg:classifiers":[
        {
            "category":"Building & Trades",
            "subcategory":"Construction",
            "type":"Services"
        },
        {
            "category":"Home & Garden",
            "subcategory":"Carpets & Floor Coverings",
            "type":"Retail Goods"
        }
    ],
    "sg:phone":"+1 469 549 0230",
    "sg:postcode":"76051",
    "sg:province":"TX",
    "sg:tags":[
        "contractor",
        "flooring",
        "tile-contractors"
    ],
    "wof:name":"All American Flooring",
    "wof:placetype":"venue"
},
  "geometry": {"coordinates":[-97.036615,32.976366],"type":"Point"}
}