{
  "type": "Feature",
  "properties": {
    "iso:country":"US",
    "sg:address":"515 S Fry Rd",
    "sg:city":"Katy",
    "sg:classifiers":[
        {
            "category":"Travel",
            "subcategory":"Bed & Breakfast",
            "type":"Entertainment"
        }
    ],
    "sg:phone":"+1 713 688 1555",
    "sg:postcode":"77450",
    "sg:province":"TX",
    "sg:tags":[
        "corporate",
        "lodging"
    ],
    "sg:website":"www.corpapts.com",
    "wof:name":"Corporate Apartments-America",
    "wof:placetype":"venue"
},
  "geometry": {"coordinates":[-95.718891,29.780946],"type":"Point"}
}