{
  "type": "Feature",
  "properties": {
    "iso:country":"US",
    "sg:address":"2110 Wyoming Ave",
    "sg:city":"El Paso",
    "sg:classifiers":[
        {
            "category":"Building & Trades",
            "subcategory":"Cleaning & Sanitation",
            "type":"Services"
        }
    ],
    "sg:phone":"+1 915 533 9797",
    "sg:postcode":"79903",
    "sg:province":"TX",
    "sg:tags":[
        "janitorial"
    ],
    "wof:name":"Professional Janitorial Svc",
    "wof:placetype":"venue"
},
  "geometry": {"coordinates":[-106.469133,31.776013],"type":"Point"}
}