{
  "type": "Feature",
  "properties": {
    "iso:country":"US",
    "sg:address":"26 FM 289",
    "sg:city":"Comfort",
    "sg:classifiers":[
        {
            "category":"Bus Charters",
            "type":"Transportation"
        }
    ],
    "sg:phone":"+1 830 995 4900",
    "sg:postcode":"78013",
    "sg:province":"TX",
    "sg:tags":[
        "rental"
    ],
    "sg:website":"www.roadhousecoach.com",
    "wof:name":"Roadhouse Transportation Inc",
    "wof:placetype":"venue"
},
  "geometry": {"coordinates":[-98.88878099999999,29.957854],"type":"Point"}
}