{
  "type": "Feature",
  "properties": {
    "iso:country":"US",
    "sg:address":"902 W 14th St",
    "sg:city":"San Angelo",
    "sg:classifiers":[
        {
            "category":"Retail",
            "subcategory":"Auto Repair",
            "type":"Services"
        }
    ],
    "sg:phone":"+1 325 653 1393",
    "sg:postcode":"76903",
    "sg:province":"TX",
    "sg:tags":[
        "automotive",
        "general"
    ],
    "wof:name":"Rays Service Center",
    "wof:placetype":"venue"
},
  "geometry": {"coordinates":[-100.457267,31.466592],"type":"Point"}
}