{
  "type": "Feature",
  "properties": {
    "iso:country":"US",
    "sg:address":"14 Aberdeen Crossing Pl",
    "sg:city":"Spring",
    "sg:classifiers":[
        {
            "category":"Professional",
            "subcategory":"Business Services",
            "type":"Services"
        }
    ],
    "sg:phone":"+1 281 296 2014",
    "sg:postcode":"77381",
    "sg:province":"TX",
    "wof:name":"Lisa Gunther Interiors",
    "wof:placetype":"venue"
},
  "geometry": {"coordinates":[-95.52150899999999,30.182086],"type":"Point"}
}