{
  "type": "Feature",
  "properties": {
    "iso:country":"US",
    "sg:address":"4002 Corder St",
    "sg:city":"Houston",
    "sg:classifiers":[
        {
            "category":"Real Estate",
            "subcategory":"Real Estate Operator",
            "type":"Services"
        }
    ],
    "sg:phone":"+1 713 741 4075",
    "sg:postcode":"77021",
    "sg:province":"TX",
    "sg:tags":[
        "building",
        "apartment"
    ],
    "wof:name":"Missionary Village Apartments",
    "wof:placetype":"venue"
},
  "geometry": {"coordinates":[-95.36161800000001,29.685121],"type":"Point"}
}