{
  "type": "Feature",
  "properties": {
    "iso:country":"US",
    "sg:address":"6203 N Capital of Texas Hwy",
    "sg:city":"Austin",
    "sg:classifiers":[
        {
            "category":"Personal",
            "subcategory":"Beauty Salon",
            "type":"Services"
        }
    ],
    "sg:phone":"+1 512 338 8188",
    "sg:postcode":"78731",
    "sg:province":"TX",
    "sg:tags":[
        "nail",
        "manicuring"
    ],
    "wof:name":"Le Pro Nails",
    "wof:placetype":"venue"
},
  "geometry": {"coordinates":[-97.79007900000001,30.364015],"type":"Point"}
}