{
  "type": "Feature",
  "properties": {
    "iso:country":"US",
    "sg:address":"2078 Pine Park Blvd",
    "sg:city":"Orange",
    "sg:classifiers":[
        {
            "category":"Insurance",
            "subcategory":"Hazard Insurance",
            "type":"Services"
        }
    ],
    "sg:phone":"+1 409 746 2627",
    "sg:postcode":"77632",
    "sg:province":"TX",
    "wof:name":"Albert Hebert Jr",
    "wof:placetype":"venue"
},
  "geometry": {"coordinates":[-93.769845,30.234735],"type":"Point"}
}