{
  "type": "Feature",
  "properties": {
    "iso:country":"US",
    "sg:address":"3623 Cortez Dr",
    "sg:city":"Dallas",
    "sg:classifiers":[
        {
            "category":"Building & Trades",
            "subcategory":"Locksmith",
            "type":"Services"
        }
    ],
    "sg:phone":"+1 214 330 5625",
    "sg:postcode":"75220",
    "sg:province":"TX",
    "sg:tags":[
        "lock"
    ],
    "wof:name":"A Locksmith In Dallas",
    "wof:placetype":"venue"
},
  "geometry": {"coordinates":[-96.858003,32.866393],"type":"Point"}
}