{
  "type": "Feature",
  "properties": {
    "iso:country":"US",
    "sg:address":"310 E Main St Ste 104",
    "sg:city":"Richardson",
    "sg:classifiers":[
        {
            "category":"Health Services",
            "subcategory":"Health Practitioner",
            "type":"Services"
        }
    ],
    "sg:phone":"+1 972 234 3168",
    "sg:postcode":"75081",
    "sg:province":"TX",
    "sg:tags":[
        "acupuncture"
    ],
    "wof:name":"May Acupuncture",
    "wof:placetype":"venue"
},
  "geometry": {"coordinates":[-96.72959899999999,32.948299],"type":"Point"}
}