{
  "type": "Feature",
  "properties": {
    "iso:country":"US",
    "sg:address":"151 E Castlewood Dr",
    "sg:city":"Marble Falls",
    "sg:classifiers":[
        {
            "category":"Shopping",
            "type":"Retail Goods"
        }
    ],
    "sg:phone":"+1 830 598 8792",
    "sg:postcode":"78654",
    "sg:province":"TX",
    "sg:tags":[
        "picture",
        "art",
        "framing"
    ],
    "wof:name":"Framers Workshop & Gallery",
    "wof:placetype":"venue"
},
  "geometry": {"coordinates":[-98.381456,30.594048],"type":"Point"}
}