{
  "type": "Feature",
  "properties": {
    "iso:country":"US",
    "sg:address":"609 Parkhaven Dr",
    "sg:city":"Mesquite",
    "sg:classifiers":[
        {
            "category":"Social Services",
            "subcategory":"Child Care",
            "type":"Services"
        }
    ],
    "sg:phone":"+1 972 288 8322",
    "sg:postcode":"75149",
    "sg:province":"TX",
    "sg:tags":[
        "center",
        "day"
    ],
    "wof:name":"Peppermint First School Inc",
    "wof:placetype":"venue"
},
  "geometry": {"coordinates":[-96.606798,32.759882],"type":"Point"}
}