{
  "type": "Feature",
  "properties": {
    "iso:country":"US",
    "sg:address":"3620 Hollywood St",
    "sg:city":"Beaumont",
    "sg:classifiers":[
        {
            "category":"Autos & Motor Vehicles",
            "subcategory":"Automobile Sales",
            "type":"Retail Goods"
        }
    ],
    "sg:phone":"+1 409 832 4640",
    "sg:postcode":"77701",
    "sg:province":"TX",
    "sg:tags":[
        "car",
        "dealer"
    ],
    "wof:name":"Beaumont Auto Co",
    "wof:placetype":"venue"
},
  "geometry": {"coordinates":[-94.130774,30.07451],"type":"Point"}
}