{
  "type": "Feature",
  "properties": {
    "iso:country":"US",
    "sg:address":"9386 Lyndon B Johnson Fwy",
    "sg:city":"Dallas",
    "sg:classifiers":[
        {
            "category":"Travel",
            "subcategory":"Hotels & Motels",
            "type":"Entertainment"
        }
    ],
    "sg:phone":"+1 972 690 1220",
    "sg:postcode":"75243",
    "sg:province":"TX",
    "sg:tags":[
        "corporate",
        "lodging"
    ],
    "sg:website":"http://www.howardjohnson.com",
    "wof:name":"Howard Johnson",
    "wof:placetype":"venue"
},
  "geometry": {"coordinates":[-96.736097,32.911129],"type":"Point"}
}