{
  "type": "Feature",
  "properties": {
    "iso:country":"US",
    "sg:address":"401 E Brown St",
    "sg:city":"Pampa",
    "sg:classifiers":[
        {
            "category":"Travel",
            "subcategory":"Hotels & Motels",
            "type":"Entertainment"
        },
        {
            "category":"Education",
            "subcategory":"College",
            "type":"Public Place"
        },
        {
            "category":"Professional",
            "subcategory":"Employment Agencies",
            "type":"Services"
        },
        {
            "category":"Organizations",
            "subcategory":"Membership Organization",
            "type":"Services"
        }
    ],
    "sg:phone":"+1 806 665 4661",
    "sg:postcode":"79065",
    "sg:province":"TX",
    "sg:tags":[
        "housing",
        "employer",
        "student",
        "lodging",
        "corporate",
        "fraternal"
    ],
    "sg:website":"http://www.mooseintl.org",
    "wof:name":"Moose Lodge Hall",
    "wof:placetype":"venue"
},
  "geometry": {"coordinates":[-100.955406,35.533749],"type":"Point"}
}