{
  "type": "Feature",
  "properties": {
    "iso:country":"US",
    "sg:address":"4906 Borchers Dr",
    "sg:city":"San Antonio",
    "sg:classifiers":[
        {
            "category":"Building & Trades",
            "subcategory":"Construction",
            "type":"Services"
        }
    ],
    "sg:phone":"+1 210 666 8799",
    "sg:postcode":"78219",
    "sg:province":"TX",
    "sg:tags":[
        "repair",
        "contractor"
    ],
    "wof:name":"Budget Resurfacing",
    "wof:placetype":"venue"
},
  "geometry": {"coordinates":[-98.388085,29.453815],"type":"Point"}
}