{
  "type": "Feature",
  "properties": {
    "iso:country":"US",
    "sg:address":"188 Squirrel Ridge",
    "sg:city":"Wylie",
    "sg:classifiers":[
        {
            "category":"Building & Trades",
            "subcategory":"Construction",
            "type":"Services"
        }
    ],
    "sg:phone":"+1 972 429 2176",
    "sg:postcode":"75098",
    "sg:province":"TX",
    "sg:tags":[
        "house"
    ],
    "wof:name":"Sharp Custom Homes LLC",
    "wof:placetype":"venue"
},
  "geometry": {"coordinates":[-96.49804,32.990877],"type":"Point"}
}