{
  "type": "Feature",
  "properties": {
    "iso:country":"US",
    "sg:address":"2012 Shady Glen Trl",
    "sg:city":"Princeton",
    "sg:classifiers":[
        {
            "category":"Building & Trades",
            "subcategory":"Construction",
            "type":"Services"
        },
        {
            "category":"Home & Garden",
            "subcategory":"Carpets & Floor Coverings",
            "type":"Retail Goods"
        }
    ],
    "sg:phone":"+1 972 736 3535",
    "sg:postcode":"75407",
    "sg:province":"TX",
    "sg:tags":[
        "roofing",
        "structure",
        "roof",
        "contractor"
    ],
    "sg:website":"http://www.360roofingco.com",
    "wof:name":"360 Roofing Co",
    "wof:placetype":"venue"
},
  "geometry": {"coordinates":[-96.528091,33.18562],"type":"Point"}
}