{
  "type": "Feature",
  "properties": {
    "iso:country":"US",
    "sg:address":"2611 Aldama St",
    "sg:city":"Laredo",
    "sg:classifiers":[
        {
            "category":"Professional",
            "type":"Services"
        }
    ],
    "sg:phone":"+1 956 723 6710",
    "sg:postcode":"78043",
    "sg:province":"TX",
    "wof:name":"Diamond Back Services",
    "wof:placetype":"venue"
},
  "geometry": {"coordinates":[-99.469227,27.500991],"type":"Point"}
}