{
  "type": "Feature",
  "properties": {
    "iso:country":"US",
    "sg:address":"910 S Mo-Pac Expy",
    "sg:city":"Austin",
    "sg:classifiers":[
        {
            "category":"Wholesale",
            "subcategory":"Machinery & Supplies",
            "type":"Manufacturing & Wholesale Goods"
        }
    ],
    "sg:phone":"+1 512 306 2500",
    "sg:postcode":"78746",
    "sg:province":"TX",
    "sg:tags":[
        "equipment",
        "pump",
        "mechanical",
        "pumping",
        "mfg"
    ],
    "wof:name":"Babtex Inc",
    "wof:placetype":"venue"
},
  "geometry": {"coordinates":[-97.78304799999999,30.266271],"type":"Point"}
}