{
  "type": "Feature",
  "properties": {
    "iso:country":"US",
    "sg:address":"11101 Airport Blvd",
    "sg:city":"Amarillo",
    "sg:classifiers":[
        {
            "category":"Government",
            "subcategory":"Office",
            "type":"Public Place"
        }
    ],
    "sg:phone":"+1 806 335 2929",
    "sg:postcode":"79111",
    "sg:province":"TX",
    "sg:tags":[
        "security",
        "homeland"
    ],
    "sg:website":"http://www.cap-ttcs.org",
    "wof:name":"Amarillo Squadron",
    "wof:placetype":"venue"
},
  "geometry": {"coordinates":[-101.699499,35.216985],"type":"Point"}
}