{
  "type": "Feature",
  "properties": {
    "iso:country":"US",
    "sg:address":"110 Ringer Pl",
    "sg:city":"China Spring",
    "sg:classifiers":[
        {
            "category":"Professional",
            "type":"Services"
        }
    ],
    "sg:phone":"+1 254 836 9372",
    "sg:postcode":"76633",
    "sg:province":"TX",
    "wof:name":"R&R Controls",
    "wof:placetype":"venue"
},
  "geometry": {"coordinates":[-97.291518,31.693673],"type":"Point"}
}