{
  "type": "Feature",
  "properties": {
    "iso:country":"US",
    "sg:address":"125 N Beaton St",
    "sg:city":"Corsicana",
    "sg:classifiers":[
        {
            "category":"Shopping",
            "subcategory":"Pharmacy",
            "type":"Retail Goods"
        }
    ],
    "sg:phone":"+1 903 874 5891",
    "sg:postcode":"75110",
    "sg:province":"TX",
    "wof:name":"Dee's Place",
    "wof:placetype":"venue"
},
  "geometry": {"coordinates":[-96.46402,32.094325],"type":"Point"}
}