{
  "type": "Feature",
  "properties": {
    "iso:country":"US",
    "sg:address":"9873 Co Rd 3613",
    "sg:city":"Murchison",
    "sg:classifiers":[
        {
            "category":"Professional",
            "subcategory":"Credit Reporting & Collection",
            "type":"Services"
        }
    ],
    "sg:phone":"+1 903 852 6409",
    "sg:postcode":"75756",
    "sg:province":"TX",
    "wof:name":"Debt Counseling Works",
    "wof:placetype":"venue"
},
  "geometry": {"coordinates":[-95.66486500000001,32.27265],"type":"Point"}
}