{
  "type": "Feature",
  "properties": {
    "iso:country":"US",
    "sg:address":"206 E Harris Ave",
    "sg:city":"San Angelo",
    "sg:classifiers":[
        {
            "category":"Professional",
            "type":"Services"
        }
    ],
    "sg:phone":"+1 325 658 6825",
    "sg:postcode":"76903",
    "sg:province":"TX",
    "wof:name":"Scci Hospital",
    "wof:placetype":"venue"
},
  "geometry": {"coordinates":[-100.43220100000001,31.465463],"type":"Point"}
}