{
  "type": "Feature",
  "properties": {
    "iso:country":"US",
    "sg:address":"11550 Fuqua St",
    "sg:city":"Houston",
    "sg:classifiers":[
        {
            "category":"Professional",
            "subcategory":"Lawyer & Legal Services",
            "type":"Services"
        }
    ],
    "sg:phone":"+1 281 484 9300",
    "sg:postcode":"77034",
    "sg:province":"TX",
    "sg:tags":[
        "attorney"
    ],
    "wof:name":"James P Brady",
    "wof:placetype":"venue"
},
  "geometry": {"coordinates":[-95.213956,29.617625],"type":"Point"}
}