{
  "type": "Feature",
  "properties": {
    "iso:country":"US",
    "sg:address":"5300 Memorial Dr",
    "sg:city":"Houston",
    "sg:classifiers":[
        {
            "category":"Mining & Drilling",
            "type":"Manufacturing & Wholesale Goods"
        }
    ],
    "sg:phone":"+1 713 880 2683",
    "sg:postcode":"77007",
    "sg:province":"TX",
    "sg:tags":[
        "development",
        "gas",
        "oil",
        "exploration"
    ],
    "wof:name":"Global-Texneft",
    "wof:placetype":"venue"
},
  "geometry": {"coordinates":[-95.41620899999999,29.761481],"type":"Point"}
}