{
  "type": "Feature",
  "properties": {
    "iso:country":"US",
    "sg:address":"417 E TX-199",
    "sg:city":"Springtown",
    "sg:classifiers":[
        {
            "category":"Restaurant",
            "type":"Food & Drink"
        }
    ],
    "sg:menulink":"http://www.allmenus.com/tx/springtown/74434-mr-jims-pizza/menu/",
    "sg:phone":"+1 817 523 2255",
    "sg:postcode":"76082",
    "sg:province":"TX",
    "sg:tags":[
        "american",
        "pizza"
    ],
    "wof:name":"Mr. Jim's Pizza",
    "wof:placetype":"venue"
},
  "geometry": {"coordinates":[-97.687721,32.964124],"type":"Point"}
}