{
  "type": "Feature",
  "properties": {
    "iso:country":"US",
    "sg:address":"1500 Dragon St",
    "sg:city":"Dallas",
    "sg:classifiers":[
        {
            "category":"Wholesale",
            "subcategory":"Plants",
            "type":"Manufacturing & Wholesale Goods"
        },
        {
            "category":"Shopping",
            "type":"Retail Goods"
        }
    ],
    "sg:phone":"+1 214 747 3350",
    "sg:postcode":"75207",
    "sg:province":"TX",
    "sg:tags":[
        "flower",
        "tree",
        "merchandise",
        "artificial",
        "supply"
    ],
    "wof:name":"Jim Bagwell Associates Inc",
    "wof:placetype":"venue"
},
  "geometry": {"coordinates":[-96.819185,32.790731],"type":"Point"}
}