{
  "type": "Feature",
  "properties": {
    "iso:country":"US",
    "sg:address":"1091 N Main St",
    "sg:city":"Vidor",
    "sg:classifiers":[
        {
            "category":"Government",
            "subcategory":"Office",
            "type":"Public Place"
        }
    ],
    "sg:phone":"+1 409 769 1631",
    "sg:postcode":"77662",
    "sg:province":"TX",
    "sg:tags":[
        "human"
    ],
    "wof:name":"Human Services Texas Dept of",
    "wof:placetype":"venue"
},
  "geometry": {"coordinates":[-94.016006,30.138881],"type":"Point"}
}