{
  "type": "Feature",
  "properties": {
    "iso:country":"US",
    "sg:address":"5204 Pine Valley Loop",
    "sg:city":"Smithville",
    "sg:classifiers":[
        {
            "category":"Manufacturing",
            "subcategory":"Glass & Minerals",
            "type":"Manufacturing & Wholesale Goods"
        }
    ],
    "sg:phone":"+1 512 360 5155",
    "sg:postcode":"78957",
    "sg:province":"TX",
    "sg:tags":[
        "product",
        "nonmetallic",
        "mfg"
    ],
    "wof:name":"Dubose Designs",
    "wof:placetype":"venue"
},
  "geometry": {"coordinates":[-97.31851399999999,29.951162],"type":"Point"}
}