{
  "type": "Feature",
  "properties": {
    "iso:country":"US",
    "sg:address":"2105 Ashwood Ln",
    "sg:city":"Carrollton",
    "sg:classifiers":[
        {
            "category":"Building & Trades",
            "subcategory":"Cleaning & Sanitation",
            "type":"Services"
        }
    ],
    "sg:phone":"+1 972 434 1497",
    "sg:postcode":"75006",
    "sg:province":"TX",
    "sg:tags":[
        "maintenance"
    ],
    "wof:name":"TNT Janitorial",
    "wof:placetype":"venue"
},
  "geometry": {"coordinates":[-96.906688,32.974563],"type":"Point"}
}