{
  "type": "Feature",
  "properties": {
    "iso:country":"US",
    "sg:address":"8021 FM 78",
    "sg:city":"San Antonio",
    "sg:classifiers":[
        {
            "category":"Retail",
            "subcategory":"Laundry & Dry Cleaning",
            "type":"Services"
        }
    ],
    "sg:phone":"+1 210 661 0217",
    "sg:postcode":"78244",
    "sg:province":"TX",
    "sg:tags":[
        "cleaners"
    ],
    "wof:name":"Snow White Cleaners & Tailors",
    "wof:placetype":"venue"
},
  "geometry": {"coordinates":[-98.32593,29.495661],"type":"Point"}
}