{
  "type": "Feature",
  "properties": {
    "iso:country":"US",
    "sg:address":"3535 Munger Ave",
    "sg:city":"Dallas",
    "sg:classifiers":[
        {
            "category":"Real Estate",
            "subcategory":"Real Estate Operator",
            "type":"Services"
        }
    ],
    "sg:phone":"+1 214 826 0415",
    "sg:postcode":"75204",
    "sg:province":"TX",
    "sg:tags":[
        "townhouses"
    ],
    "wof:name":"Carroll & Monarch",
    "wof:placetype":"venue"
},
  "geometry": {"coordinates":[-96.789389,32.798212],"type":"Point"}
}