{
  "type": "Feature",
  "properties": {
    "iso:country":"US",
    "sg:address":"701 W Broadway St",
    "sg:city":"Fritch",
    "sg:classifiers":[
        {
            "category":"Restaurant",
            "type":"Food & Drink"
        }
    ],
    "sg:phone":"+1 806 857 5434",
    "sg:postcode":"79036",
    "sg:province":"TX",
    "wof:name":"Ol Hickory's Smokehouse",
    "wof:placetype":"venue"
},
  "geometry": {"coordinates":[-101.605175,35.638434],"type":"Point"}
}