{
  "type": "Feature",
  "properties": {
    "iso:country":"US",
    "sg:address":"912 Citrus St",
    "sg:city":"San Juan",
    "sg:classifiers":[
        {
            "category":"Personal",
            "subcategory":"Beauty Salon",
            "type":"Services"
        }
    ],
    "sg:phone":"+1 956 783 0908",
    "sg:postcode":"78589",
    "sg:province":"TX",
    "wof:name":"Ofri's Beauty Salon",
    "wof:placetype":"venue"
},
  "geometry": {"coordinates":[-98.16520199999999,26.1991],"type":"Point"}
}