{
  "type": "Feature",
  "properties": {
    "iso:country":"US",
    "sg:address":"3010 Clearview Dr",
    "sg:city":"Midlothian",
    "sg:classifiers":[
        {
            "category":"Building & Trades",
            "subcategory":"Landscaping Services",
            "type":"Services"
        }
    ],
    "sg:phone":"+1 972 709 7546",
    "sg:postcode":"76065",
    "sg:province":"TX",
    "wof:name":"Classic Lawn Care",
    "wof:placetype":"venue"
},
  "geometry": {"coordinates":[-97.007666,32.452251],"type":"Point"}
}