{
  "type": "Feature",
  "properties": {
    "iso:country":"US",
    "sg:address":"4001 S Osage St",
    "sg:city":"Amarillo",
    "sg:classifiers":[
        {
            "category":"Government",
            "subcategory":"Office",
            "type":"Public Place"
        }
    ],
    "sg:phone":"+1 806 359 1556",
    "sg:postcode":"79118",
    "sg:province":"TX",
    "sg:tags":[
        "village"
    ],
    "wof:name":"Amarillo Industrial Waste",
    "wof:placetype":"venue"
},
  "geometry": {"coordinates":[-101.813074,35.169696],"type":"Point"}
}