{
  "type": "Feature",
  "properties": {
    "iso:country":"US",
    "sg:address":"500 Main St",
    "sg:city":"Brownwood",
    "sg:classifiers":[
        {
            "category":"Banks & Credit Unions",
            "subcategory":"Investment Brokerage",
            "type":"Services"
        },
        {
            "category":"Banks & Credit Unions",
            "subcategory":"Bank",
            "type":"Services"
        },
        {
            "category":"Banks & Credit Unions",
            "subcategory":"Financial Services",
            "type":"Services"
        }
    ],
    "sg:phone":"+1 888 583 5257",
    "sg:postcode":"76801",
    "sg:province":"TX",
    "sg:tags":[
        "advisory",
        "mutual",
        "retirement",
        "annuity",
        "broker",
        "fund",
        "planning",
        "plan",
        "consultant",
        "security",
        "bond",
        "insurance",
        "stock"
    ],
    "sg:website":"http://national.citysearch.com/profile/external/38528221/brownwood_tx/edward_jones_pierre_osbourn.html?publisher=yellowpages&reference_id=1&placement=ypwebsitemip",
    "wof:name":"Edward Jones - PIERRE OSBOURN",
    "wof:placetype":"venue"
},
  "geometry": {"coordinates":[-98.98436,31.72072],"type":"Point"}
}