{
  "type": "Feature",
  "properties": {
    "iso:country":"US",
    "sg:address":"1555 N Main St",
    "sg:city":"Paris",
    "sg:classifiers":[
        {
            "category":"Home & Garden",
            "subcategory":"Carpets & Floor Coverings",
            "type":"Retail Goods"
        }
    ],
    "sg:phone":"+1 903 784 5989",
    "sg:postcode":"75460",
    "sg:province":"TX",
    "wof:name":"Triangle Carpet & Rug",
    "wof:placetype":"venue"
},
  "geometry": {"coordinates":[-95.55589000000001,33.676048],"type":"Point"}
}