{
  "type": "Feature",
  "properties": {
    "iso:country":"US",
    "sg:address":"219 Cullen Ave",
    "sg:city":"El Paso",
    "sg:classifiers":[
        {
            "category":"Freight",
            "type":"Transportation"
        }
    ],
    "sg:phone":"+1 915 779 0897",
    "sg:postcode":"79915",
    "sg:province":"TX",
    "wof:name":"San Luis Transportation",
    "wof:placetype":"venue"
},
  "geometry": {"coordinates":[-106.370943,31.729978],"type":"Point"}
}