{
  "type": "Feature",
  "properties": {
    "iso:country":"US",
    "sg:address":"2502 Coastal Oak Dr",
    "sg:city":"Houston",
    "sg:classifiers":[
        {
            "category":"Building & Trades",
            "subcategory":"Landscaping Services",
            "type":"Services"
        }
    ],
    "sg:phone":"+1 281 326 5296",
    "sg:postcode":"77059",
    "sg:province":"TX",
    "sg:tags":[
        "contractor"
    ],
    "wof:name":"Grass Hopper Landscape & Cnstr",
    "wof:placetype":"venue"
},
  "geometry": {"coordinates":[-95.11842900000001,29.587428],"type":"Point"}
}