{
  "type": "Feature",
  "properties": {
    "iso:country":"US",
    "sg:address":"3202 Edgecreek Dr",
    "sg:city":"Houston",
    "sg:classifiers":[
        {
            "category":"Restaurant",
            "type":"Food & Drink"
        }
    ],
    "sg:phone":"+1 281 587 1271",
    "sg:postcode":"77066",
    "sg:province":"TX",
    "sg:tags":[
        "eating"
    ],
    "wof:name":"Thai Truong",
    "wof:placetype":"venue"
},
  "geometry": {"coordinates":[-95.46719899999999,29.94034],"type":"Point"}
}