{
  "type": "Feature",
  "properties": {
    "iso:country":"US",
    "sg:address":"16704 Tomcat Dr",
    "sg:city":"Round Rock",
    "sg:classifiers":[
        {
            "category":"Wholesale",
            "subcategory":"Chemicals & Plastics",
            "type":"Manufacturing & Wholesale Goods"
        }
    ],
    "sg:phone":"+1 512 694 1646",
    "sg:postcode":"78681",
    "sg:province":"TX",
    "wof:name":"Simon Enterprises",
    "wof:placetype":"venue"
},
  "geometry": {"coordinates":[-97.735264,30.505718],"type":"Point"}
}