{
  "type": "Feature",
  "properties": {
    "iso:country":"US",
    "sg:address":"124 S Ridgeway Dr",
    "sg:city":"Cleburne",
    "sg:classifiers":[
        {
            "category":"Shopping",
            "subcategory":"Gifts & Souvenirs",
            "type":"Retail Goods"
        }
    ],
    "sg:phone":"+1 817 645 7171",
    "sg:postcode":"76033",
    "sg:province":"TX",
    "sg:tags":[
        "shop"
    ],
    "wof:name":"Corner Shop",
    "wof:placetype":"venue"
},
  "geometry": {"coordinates":[-97.408288,32.340054],"type":"Point"}
}