{
  "type": "Feature",
  "properties": {
    "iso:country":"US",
    "sg:address":"11066 Pecan Park Blvd Ste 109",
    "sg:city":"Cedar Park",
    "sg:classifiers":[
        {
            "category":"Shopping",
            "subcategory":"Clothing, Apparel, & Fashions",
            "type":"Retail Goods"
        }
    ],
    "sg:phone":"+1 512 331 7329",
    "sg:postcode":"78613",
    "sg:province":"TX",
    "sg:tags":[
        "accessory",
        "clothing",
        "women's"
    ],
    "sg:website":"lanebryant.charmingshoppes.com",
    "wof:name":"Lane Bryant",
    "wof:placetype":"venue"
},
  "geometry": {"coordinates":[-97.80203,30.470028],"type":"Point"}
}