{
  "type": "Feature",
  "properties": {
    "iso:country":"US",
    "sg:address":"1101 Heritage Pkwy",
    "sg:city":"Mansfield",
    "sg:classifiers":[
        {
            "category":"Autos & Motor Vehicles",
            "subcategory":"Recreational Vehicle Sales",
            "type":"Retail Goods"
        }
    ],
    "sg:phone":"+1 817 453 5402",
    "sg:postcode":"76063",
    "sg:province":"TX",
    "sg:tags":[
        "parts",
        "trailer"
    ],
    "wof:name":"Interstate Trailers",
    "wof:placetype":"venue"
},
  "geometry": {"coordinates":[-97.12459200000001,32.552138],"type":"Point"}
}