{
  "type": "Feature",
  "properties": {
    "iso:country":"US",
    "sg:address":"1212 N Velasco St",
    "sg:city":"Angleton",
    "sg:classifiers":[
        {
            "category":"Government",
            "subcategory":"Office",
            "type":"Public Place"
        }
    ],
    "sg:phone":"+1 979 849 8521",
    "sg:postcode":"77515",
    "sg:province":"TX",
    "sg:tags":[
        "state",
        "resource"
    ],
    "wof:name":"Vocational Rehabilitation Div",
    "wof:placetype":"venue"
},
  "geometry": {"coordinates":[-95.433199,29.186938],"type":"Point"}
}