{
  "type": "Feature",
  "properties": {
    "iso:country":"US",
    "sg:address":"214 SW 26th Ave",
    "sg:city":"Mineral Wells",
    "sg:classifiers":[
        {
            "category":"Health Services",
            "subcategory":"Doctor",
            "type":"Services"
        }
    ],
    "sg:phone":"+1 940 325 7064",
    "sg:postcode":"76067",
    "sg:province":"TX",
    "sg:tags":[
        "physician",
        "surgeon"
    ],
    "wof:name":"Mathis Adams MD",
    "wof:placetype":"venue"
},
  "geometry": {"coordinates":[-98.146787,32.800663],"type":"Point"}
}