{
  "type": "Feature",
  "properties": {
    "iso:country":"US",
    "sg:address":"4500 University Drive Campus Recreation and Wellness Center",
    "sg:city":"Houston",
    "sg:classifiers":[
        {
            "category":"Juice Bar",
            "subcategory":"None",
            "type":"Food & Drink"
        }
    ],
    "sg:phone":"+1 713 743 1688",
    "sg:postcode":"77005",
    "sg:province":"TX",
    "sg:tags":[
        "smoothy"
    ],
    "sg:website":"www.smoothieking.com/",
    "wof:name":"Smoothie King",
    "wof:placetype":"venue"
},
  "geometry": {"coordinates":[-95.446887,29.71456],"type":"Point"}
}