{
  "type": "Feature",
  "properties": {
    "iso:country":"US",
    "sg:address":"1806 Crescent Oak Dr",
    "sg:city":"Missouri City",
    "sg:classifiers":[
        {
            "category":"Building & Trades",
            "subcategory":"Construction",
            "type":"Services"
        }
    ],
    "sg:phone":"+1 281 416 8283",
    "sg:postcode":"77459",
    "sg:province":"TX",
    "sg:tags":[
        "excavation",
        "contractor"
    ],
    "wof:name":"ABC Backhoe Services Inc",
    "wof:placetype":"venue"
},
  "geometry": {"coordinates":[-95.523492,29.556447],"type":"Point"}
}