{
  "type": "Feature",
  "properties": {
    "iso:country":"US",
    "sg:address":"640 Ivy Ln",
    "sg:city":"San Antonio",
    "sg:classifiers":[
        {
            "category":"Banks & Credit Unions",
            "subcategory":"Financial Services",
            "type":"Services"
        }
    ],
    "sg:phone":"+1 210 822 2870",
    "sg:postcode":"78209",
    "sg:province":"TX",
    "sg:tags":[
        "personal",
        "ranch",
        "investment",
        "cattle"
    ],
    "wof:name":"Heritage Ranch",
    "wof:placetype":"venue"
},
  "geometry": {"coordinates":[-98.444919,29.479567],"type":"Point"}
}