{
  "type": "Feature",
  "properties": {
    "iso:country":"US",
    "sg:address":"15255 Mason Rd",
    "sg:city":"Cypress",
    "sg:classifiers":[
        {
            "category":"Social Services",
            "subcategory":"Child Care",
            "type":"Services"
        }
    ],
    "sg:phone":"+1 281 256 2811",
    "sg:postcode":"77433",
    "sg:province":"TX",
    "sg:tags":[
        "day"
    ],
    "wof:name":"La Petite Academy 791",
    "wof:placetype":"venue"
},
  "geometry": {"coordinates":[-95.73784999999999,29.996137],"type":"Point"}
}