{
  "type": "Feature",
  "properties": {
    "iso:country":"US",
    "sg:address":"5515 S Loop Fwy",
    "sg:city":"Houston",
    "sg:classifiers":[
        {
            "category":"Shopping",
            "subcategory":"Jewelry",
            "type":"Retail Goods"
        }
    ],
    "sg:phone":"+1 713 734 6800",
    "sg:postcode":"77033",
    "sg:province":"TX",
    "sg:tags":[
        "jeweler"
    ],
    "wof:name":"Naaz Jewelry & Fashion",
    "wof:placetype":"venue"
},
  "geometry": {"coordinates":[-95.336135,29.686727],"type":"Point"}
}