{
  "type": "Feature",
  "properties": {
    "iso:country":"US",
    "sg:address":"226 W Phillips Ct",
    "sg:city":"Grand Prairie",
    "sg:classifiers":[
        {
            "category":"Building & Trades",
            "subcategory":"Landscaping Services",
            "type":"Services"
        }
    ],
    "sg:phone":"+1 972 262 5968",
    "sg:postcode":"75051",
    "sg:province":"TX",
    "wof:name":"Gonzalez Landscaping",
    "wof:placetype":"venue"
},
  "geometry": {"coordinates":[-97.007065,32.724405],"type":"Point"}
}