{
  "type": "Feature",
  "properties": {
    "iso:country":"US",
    "sg:address":"3835 San Jacinto St",
    "sg:city":"Dallas",
    "sg:classifiers":[
        {
            "category":"Community Center",
            "type":"Public Place"
        }
    ],
    "sg:phone":"+1 214 821 9700",
    "sg:postcode":"75204",
    "sg:province":"TX",
    "sg:tags":[
        "medical"
    ],
    "wof:name":"Alpha Clinical Research",
    "wof:placetype":"venue"
},
  "geometry": {"coordinates":[-96.784969,32.797612],"type":"Point"}
}