{
  "type": "Feature",
  "properties": {
    "iso:country":"US",
    "sg:address":"711 Lynne Cir",
    "sg:city":"Orange",
    "sg:classifiers":[
        {
            "category":"Professional",
            "subcategory":"Business Services",
            "type":"Services"
        }
    ],
    "sg:phone":"+1 409 735 2929",
    "sg:postcode":"77630",
    "sg:province":"TX",
    "wof:name":"H&L Enterprises",
    "wof:placetype":"venue"
},
  "geometry": {"coordinates":[-93.907419,30.066352],"type":"Point"}
}