{
  "type": "Feature",
  "properties": {
    "iso:country":"US",
    "sg:address":"34 Arien Ct",
    "sg:city":"Brownsville",
    "sg:classifiers":[
        {
            "category":"Real Estate",
            "subcategory":"Real Estate Agent",
            "type":"Services"
        }
    ],
    "sg:phone":"+1 956 546 6863",
    "sg:postcode":"78521",
    "sg:province":"TX",
    "wof:name":"A N C O Properties Corporation",
    "wof:placetype":"venue"
},
  "geometry": {"coordinates":[-97.496745,25.944574],"type":"Point"}
}