{
  "type": "Feature",
  "properties": {
    "iso:country":"US",
    "sg:address":"610 Green Meadows Ln",
    "sg:city":"Red Oak",
    "sg:classifiers":[
        {
            "category":"Manufacturing",
            "subcategory":"Textiles",
            "type":"Manufacturing & Wholesale Goods"
        }
    ],
    "sg:phone":"+1 972 217 7445",
    "sg:postcode":"75154",
    "sg:province":"TX",
    "sg:tags":[
        "plant",
        "silk",
        "finishing",
        "fiber"
    ],
    "wof:name":"H&P Dupriest Partners Ltd",
    "wof:placetype":"venue"
},
  "geometry": {"coordinates":[-96.90028700000001,32.540715],"type":"Point"}
}