{
  "type": "Feature",
  "properties": {
    "iso:country":"US",
    "sg:address":"4803 Oldfort Hill Dr",
    "sg:city":"Austin",
    "sg:classifiers":[
        {
            "category":"Social Services",
            "type":"Services"
        }
    ],
    "sg:phone":"+1 512 926 4511",
    "sg:postcode":"78723",
    "sg:province":"TX",
    "sg:tags":[
        "consultant",
        "security",
        "representative"
    ],
    "wof:name":"Action Pr",
    "wof:placetype":"venue"
},
  "geometry": {"coordinates":[-97.675145,30.28667],"type":"Point"}
}