{
  "type": "Feature",
  "properties": {
    "iso:country":"US",
    "sg:address":"934 E Adams St",
    "sg:city":"Brownsville",
    "sg:classifiers":[
        {
            "category":"Retail",
            "subcategory":"Laundry & Dry Cleaning",
            "type":"Services"
        }
    ],
    "sg:phone":"+1 956 546 6121",
    "sg:postcode":"78520",
    "sg:province":"TX",
    "sg:tags":[
        "garment",
        "drycleaning",
        "plant",
        "agent",
        "cleaners"
    ],
    "wof:name":"Saenz Cleaners Inc",
    "wof:placetype":"venue"
},
  "geometry": {"coordinates":[-97.498431,25.903812],"type":"Point"}
}