{
  "type": "Feature",
  "properties": {
    "iso:country":"US",
    "sg:address":"2725 Aspen Ct E",
    "sg:city":"Plano",
    "sg:classifiers":[
        {
            "category":"Organizations",
            "subcategory":"Religious Organization",
            "type":"Services"
        }
    ],
    "sg:phone":"+1 972 964 1771",
    "sg:postcode":"75075",
    "sg:province":"TX",
    "wof:name":"Mundo De Fe",
    "wof:placetype":"venue"
},
  "geometry": {"coordinates":[-96.747466,33.02342],"type":"Point"}
}