{
  "type": "Feature",
  "properties": {
    "iso:country":"US",
    "sg:address":"1031 Andrews Hwy",
    "sg:city":"Midland",
    "sg:classifiers":[
        {
            "category":"Retail",
            "subcategory":"Repair Shop",
            "type":"Services"
        },
        {
            "category":"Mining & Drilling",
            "type":"Manufacturing & Wholesale Goods"
        }
    ],
    "sg:phone":"+1 432 520 9722",
    "sg:postcode":"79701",
    "sg:province":"TX",
    "sg:tags":[
        "industrial",
        "equipment",
        "mfg",
        "specialty",
        "field",
        "oil",
        "machinery"
    ],
    "wof:name":"Automated Well Control Systems",
    "wof:placetype":"venue"
},
  "geometry": {"coordinates":[-102.113793,32.000656],"type":"Point"}
}