{
  "type": "Feature",
  "properties": {
    "iso:country":"US",
    "sg:address":"3314 S Congress Avenue",
    "sg:city":"Austin",
    "sg:classifiers":[
        {
            "category":"Professional",
            "subcategory":"Lawyer & Legal Services",
            "type":"Services"
        }
    ],
    "sg:phone":"+1 512 447 0335",
    "sg:postcode":"78704",
    "sg:province":"TX",
    "sg:tags":[
        "notary"
    ],
    "wof:name":"Capitol Rubber Stamp Service",
    "wof:placetype":"venue"
},
  "geometry": {"coordinates":[-97.76004,30.230193],"type":"Point"}
}