{
  "type": "Feature",
  "properties": {
    "iso:country":"US",
    "sg:address":"8930 Wurzbach Rd",
    "sg:city":"San Antonio",
    "sg:classifiers":[
        {
            "category":"Retail",
            "subcategory":"Repair Shop",
            "type":"Services"
        }
    ],
    "sg:phone":"+1 210 673 0233",
    "sg:postcode":"78240",
    "sg:province":"TX",
    "sg:tags":[
        "plumbing",
        "drain",
        "cleaning",
        "sewer"
    ],
    "wof:name":"Eagle Drain Svc",
    "wof:placetype":"venue"
},
  "geometry": {"coordinates":[-98.566475,29.526758],"type":"Point"}
}