{
  "type": "Feature",
  "properties": {
    "iso:country":"US",
    "sg:address":"8401 Sovereign Row",
    "sg:city":"Dallas",
    "sg:classifiers":[
        {
            "category":"Manufacturing",
            "subcategory":"Pet Food",
            "type":"Manufacturing & Wholesale Goods"
        }
    ],
    "sg:phone":"+1 214 630 4511",
    "sg:postcode":"75247",
    "sg:province":"TX",
    "sg:tags":[
        "flour",
        "prepared",
        "dough",
        "mix"
    ],
    "sg:website":"www.cainfood.com",
    "wof:name":"Cain Food Industries Inc",
    "wof:placetype":"venue"
},
  "geometry": {"coordinates":[-96.88581000000001,32.819763],"type":"Point"}
}