{
  "type": "Feature",
  "properties": {
    "iso:country":"US",
    "sg:address":"13403 Huffmeister Rd",
    "sg:city":"Cypress",
    "sg:classifiers":[
        {
            "category":"Wholesale",
            "subcategory":"Machinery & Supplies",
            "type":"Manufacturing & Wholesale Goods"
        }
    ],
    "sg:phone":"+1 281 256 1616",
    "sg:postcode":"77429",
    "sg:province":"TX",
    "sg:tags":[
        "field",
        "oil"
    ],
    "wof:name":"Atlas Oil Field Supply Co",
    "wof:placetype":"venue"
},
  "geometry": {"coordinates":[-95.63160000000001,29.962557],"type":"Point"}
}