{
  "type": "Feature",
  "properties": {
    "iso:country":"US",
    "sg:address":"506 Pat Booker Rd",
    "sg:city":"Universal City",
    "sg:classifiers":[
        {
            "category":"Retail",
            "subcategory":"Repair Shop",
            "type":"Services"
        },
        {
            "category":"Building & Trades",
            "subcategory":"Equipment Rental",
            "type":"Services"
        }
    ],
    "sg:phone":"+1 210 659 1453",
    "sg:postcode":"78148",
    "sg:province":"TX",
    "sg:tags":[
        "video"
    ],
    "wof:name":"Speedy's TV Repair",
    "wof:placetype":"venue"
},
  "geometry": {"coordinates":[-98.290414,29.547648],"type":"Point"}
}