{
  "type": "Feature",
  "properties": {
    "iso:country":"US",
    "sg:address":"333 S Saint Augustine Dr",
    "sg:city":"Dallas",
    "sg:classifiers":[
        {
            "category":"Personal",
            "subcategory":"Beauty Salon",
            "type":"Services"
        }
    ],
    "sg:phone":"+1 214 398 3335",
    "sg:postcode":"75217",
    "sg:province":"TX",
    "sg:tags":[
        "manicuring"
    ],
    "wof:name":"Top Nails",
    "wof:placetype":"venue"
},
  "geometry": {"coordinates":[-96.657117,32.706612],"type":"Point"}
}