{
  "type": "Feature",
  "properties": {
    "iso:country":"US",
    "sg:address":"153 Loy St",
    "sg:city":"Burleson",
    "sg:classifiers":[
        {
            "category":"Bus Station",
            "type":"Transportation"
        }
    ],
    "sg:phone":"+1 817 447 2130",
    "sg:postcode":"76028",
    "sg:province":"TX",
    "sg:tags":[
        "charter",
        "facility"
    ],
    "wof:name":"Genes Bus Leasing & Repair",
    "wof:placetype":"venue"
},
  "geometry": {"coordinates":[-97.308013,32.541888],"type":"Point"}
}