{
  "type": "Feature",
  "properties": {
    "iso:country":"US",
    "sg:address":"703 E US Hwy 83",
    "sg:city":"Weslaco",
    "sg:classifiers":[
        {
            "category":"Food & Beverages",
            "subcategory":"Groceries & Convenience Stores",
            "type":"Retail Goods"
        }
    ],
    "sg:phone":"+1 956 968 3822",
    "sg:postcode":"78596",
    "sg:province":"TX",
    "wof:name":"Corner Stop 2",
    "wof:placetype":"venue"
},
  "geometry": {"coordinates":[-97.982581,26.157946],"type":"Point"}
}