{
  "type": "Feature",
  "properties": {
    "iso:country":"US",
    "sg:address":"7433 Leopard St",
    "sg:city":"Corpus Christi",
    "sg:classifiers":[
        {
            "category":"Organizations",
            "subcategory":"Non-profit Organization",
            "type":"Services"
        }
    ],
    "sg:phone":"+1 361 289 5856",
    "sg:postcode":"78409",
    "sg:province":"TX",
    "sg:website":"www.csccb.org",
    "wof:name":"Contractors Safety Council",
    "wof:placetype":"venue"
},
  "geometry": {"coordinates":[-97.505838,27.808495],"type":"Point"}
}