{
  "type": "Feature",
  "properties": {
    "iso:country":"US",
    "sg:address":"6353 Richmond Ave",
    "sg:city":"Houston",
    "sg:classifiers":[
        {
            "category":"Restaurant",
            "type":"Food & Drink"
        }
    ],
    "sg:phone":"+1 713 953 9448",
    "sg:postcode":"77057",
    "sg:province":"TX",
    "sg:tags":[
        "eating"
    ],
    "wof:name":"Copeland/Bubba King",
    "wof:placetype":"venue"
},
  "geometry": {"coordinates":[-95.496633,29.73166],"type":"Point"}
}