{
  "type": "Feature",
  "properties": {
    "iso:country":"US",
    "sg:address":"1200 Cedar Bayou Rd",
    "sg:city":"Baytown",
    "sg:classifiers":[
        {
            "category":"Building & Trades",
            "subcategory":"Plumbing",
            "type":"Services"
        }
    ],
    "sg:phone":"+1 713 649 1267",
    "sg:postcode":"77520",
    "sg:province":"TX",
    "sg:tags":[
        "plumbing",
        "conditioning",
        "air",
        "heating",
        "contractor"
    ],
    "wof:name":"Derryberrys LP",
    "wof:placetype":"venue"
},
  "geometry": {"coordinates":[-94.950315,29.74982],"type":"Point"}
}