{
  "type": "Feature",
  "properties": {
    "iso:country":"US",
    "sg:address":"23 Ripple Rush Ct",
    "sg:city":"Spring",
    "sg:classifiers":[
        {
            "category":"Professional",
            "subcategory":"Management & Consulting",
            "type":"Services"
        }
    ],
    "sg:phone":"+1 281 296 9583",
    "sg:postcode":"77381",
    "sg:province":"TX",
    "wof:name":"Kilonow",
    "wof:placetype":"venue"
},
  "geometry": {"coordinates":[-95.495653,30.163057],"type":"Point"}
}