{
  "type": "Feature",
  "properties": {
    "iso:country":"US",
    "sg:address":"2118 34th St",
    "sg:city":"Lubbock",
    "sg:classifiers":[
        {
            "category":"Professional",
            "subcategory":"Accounting & Tax Preparation",
            "type":"Services"
        }
    ],
    "sg:phone":"+1 806 763 8733",
    "sg:postcode":"79411",
    "sg:province":"TX",
    "wof:name":"Hansen John J",
    "wof:placetype":"venue"
},
  "geometry": {"coordinates":[-101.862916,33.563356],"type":"Point"}
}