{
  "type": "Feature",
  "properties": {
    "iso:country":"US",
    "sg:address":"11601 Katy Fwy",
    "sg:city":"Houston",
    "sg:classifiers":[
        {
            "category":"Building & Trades",
            "subcategory":"Construction",
            "type":"Services"
        }
    ],
    "sg:phone":"+1 281 496 0121",
    "sg:postcode":"77079",
    "sg:province":"TX",
    "sg:tags":[
        "repairing",
        "remodeling",
        "contractor"
    ],
    "wof:name":"Capital Plus Remodelers Inc",
    "wof:placetype":"venue"
},
  "geometry": {"coordinates":[-95.588188,29.78415],"type":"Point"}
}