{
  "type": "Feature",
  "properties": {
    "iso:country":"US",
    "sg:address":"7015 Gillis Johnson St",
    "sg:city":"Fort Worth",
    "sg:classifiers":[
        {
            "category":"Professional",
            "type":"Services"
        }
    ],
    "sg:phone":"+1 817 237 4224",
    "sg:postcode":"76179",
    "sg:province":"TX",
    "wof:name":"Hbr Services LLC",
    "wof:placetype":"venue"
},
  "geometry": {"coordinates":[-97.412824,32.862804],"type":"Point"}
}