{
  "type": "Feature",
  "properties": {
    "iso:country":"US",
    "sg:address":"1112 N Industrial Blvd",
    "sg:city":"Dallas",
    "sg:classifiers":[
        {
            "category":"Professional",
            "type":"Services"
        }
    ],
    "sg:phone":"+1 214 744 1244",
    "sg:postcode":"75207",
    "sg:province":"TX",
    "sg:tags":[
        "establishment"
    ],
    "wof:name":"Back Bar",
    "wof:placetype":"venue"
},
  "geometry": {"coordinates":[-96.818646,32.787966],"type":"Point"}
}