{
  "type": "Feature",
  "properties": {
    "iso:country":"US",
    "sg:address":"1101 W Webb St",
    "sg:city":"Brownfield",
    "sg:classifiers":[
        {
            "category":"Real Estate",
            "subcategory":"Real Estate Operator",
            "type":"Services"
        }
    ],
    "sg:phone":"+1 806 637 2227",
    "sg:postcode":"79316",
    "sg:province":"TX",
    "sg:tags":[
        "mobile",
        "home",
        "site"
    ],
    "wof:name":"Careyville Mobile Home Village",
    "wof:placetype":"venue"
},
  "geometry": {"coordinates":[-102.28882400000001,33.166553],"type":"Point"}
}