{
  "type": "Feature",
  "properties": {
    "iso:country":"US",
    "sg:address":"1304 Summit Ave",
    "sg:city":"Plano",
    "sg:classifiers":[
        {
            "category":"Building & Trades",
            "subcategory":"Landscaping Services",
            "type":"Services"
        }
    ],
    "sg:phone":"+1 972 578 9558",
    "sg:postcode":"75074",
    "sg:province":"TX",
    "wof:name":"Tru Green-Chemlawn",
    "wof:placetype":"venue"
},
  "geometry": {"coordinates":[-96.697023,33.009395],"type":"Point"}
}