{
  "type": "Feature",
  "properties": {
    "iso:country":"US",
    "sg:address":"819 Warwick Rd",
    "sg:city":"El Paso",
    "sg:classifiers":[
        {
            "category":"Building & Trades",
            "subcategory":"Pest Control",
            "type":"Services"
        }
    ],
    "sg:phone":"+1 915 872 1998",
    "sg:postcode":"79907",
    "sg:province":"TX",
    "wof:name":"Jade Pest Control",
    "wof:placetype":"venue"
},
  "geometry": {"coordinates":[-106.311446,31.701192],"type":"Point"}
}