{
  "type": "Feature",
  "properties": {
    "iso:country":"US",
    "sg:address":"5337 Fulwell Dr",
    "sg:city":"Corpus Christi",
    "sg:classifiers":[
        {
            "category":"Professional",
            "type":"Services"
        }
    ],
    "sg:phone":"+1 361 991 1337",
    "sg:postcode":"78413",
    "sg:province":"TX",
    "sg:tags":[
        "establishment"
    ],
    "wof:name":"Liz's Lockbox",
    "wof:placetype":"venue"
},
  "geometry": {"coordinates":[-97.38416100000001,27.698646],"type":"Point"}
}