{
  "type": "Feature",
  "properties": {
    "iso:country":"US",
    "sg:address":"3839 Bee Caves Rd",
    "sg:city":"Austin",
    "sg:classifiers":[
        {
            "category":"Banks & Credit Unions",
            "subcategory":"Bank",
            "type":"Services"
        }
    ],
    "sg:phone":"+1 512 637 9900",
    "sg:postcode":"78746",
    "sg:province":"TX",
    "sg:tags":[
        "loan",
        "mortgage",
        "real estate"
    ],
    "sg:website":"www.lonestarloan.com",
    "wof:name":"Milestone Mortgage Corp",
    "wof:placetype":"venue"
},
  "geometry": {"coordinates":[-97.808205,30.280836],"type":"Point"}
}