{
  "type": "Feature",
  "properties": {
    "iso:country":"US",
    "sg:address":"10425 Okanella St",
    "sg:city":"Houston",
    "sg:classifiers":[
        {
            "category":"Freight",
            "type":"Transportation"
        }
    ],
    "sg:phone":"+1 713 896 0819",
    "sg:postcode":"77041",
    "sg:province":"TX",
    "sg:tags":[
        "record"
    ],
    "wof:name":"Fugro C & M Storage",
    "wof:placetype":"venue"
},
  "geometry": {"coordinates":[-95.55417799999999,29.858986],"type":"Point"}
}