{
  "type": "Feature",
  "properties": {
    "iso:country":"US",
    "sg:address":"915 N University Dr",
    "sg:city":"Nacogdoches",
    "sg:classifiers":[
        {
            "category":"Autos & Motor Vehicles",
            "subcategory":"Auto Supplies",
            "type":"Retail Goods"
        }
    ],
    "sg:phone":"+1 936 462 9527",
    "sg:postcode":"75961",
    "sg:province":"TX",
    "wof:name":"Advance Auto Parts",
    "wof:placetype":"venue"
},
  "geometry": {"coordinates":[-94.63930499999999,31.616733],"type":"Point"}
}