{
  "type": "Feature",
  "properties": {
    "iso:country":"US",
    "sg:address":"1514 2nd St",
    "sg:city":"Pleasanton",
    "sg:classifiers":[
        {
            "category":"Professional",
            "subcategory":"Management & Consulting",
            "type":"Services"
        }
    ],
    "sg:phone":"+1 830 569 6063",
    "sg:postcode":"78064",
    "sg:province":"TX",
    "sg:tags":[
        "consultant",
        "energy",
        "conservation"
    ],
    "wof:name":"Sedco Resources",
    "wof:placetype":"venue"
},
  "geometry": {"coordinates":[-98.47882,28.973808],"type":"Point"}
}