{
  "type": "Feature",
  "properties": {
    "iso:country":"US",
    "sg:address":"3026 Grand Ave",
    "sg:city":"Dallas",
    "sg:classifiers":[
        {
            "category":"Food & Beverages",
            "subcategory":"Groceries & Convenience Stores",
            "type":"Retail Goods"
        }
    ],
    "sg:phone":"+1 214 421 7423",
    "sg:postcode":"75215",
    "sg:province":"TX",
    "sg:tags":[
        "grocer",
        "meat"
    ],
    "wof:name":"Grand City Groc",
    "wof:placetype":"venue"
},
  "geometry": {"coordinates":[-96.768303,32.774502],"type":"Point"}
}