{
  "type": "Feature",
  "properties": {
    "iso:country":"US",
    "sg:address":"7333 E Highway 290",
    "sg:city":"Austin",
    "sg:classifiers":[
        {
            "category":"Professional",
            "subcategory":"Computer Services",
            "type":"Services"
        }
    ],
    "sg:phone":"+1 512 926 0600",
    "sg:postcode":"78723",
    "sg:province":"TX",
    "sg:tags":[
        "systems-consultants",
        "designer",
        "data"
    ],
    "wof:name":"Accutax Solutions",
    "wof:placetype":"venue"
},
  "geometry": {"coordinates":[-97.67903,30.323304],"type":"Point"}
}