{
  "type": "Feature",
  "properties": {
    "iso:country":"US",
    "sg:address":"1106 S Lamar Blvd",
    "sg:city":"Austin",
    "sg:classifiers":[
        {
            "category":"Shopping",
            "subcategory":"Musical Instruments",
            "type":"Retail Goods"
        }
    ],
    "sg:phone":"+1 512 707 8780",
    "sg:postcode":"78704",
    "sg:province":"TX",
    "wof:name":"Custom Shop Guitar & Bass",
    "wof:placetype":"venue"
},
  "geometry": {"coordinates":[-97.761853,30.255451],"type":"Point"}
}