{
  "type": "Feature",
  "properties": {
    "iso:country":"US",
    "sg:address":"2417 Sabine St",
    "sg:city":"Houston",
    "sg:classifiers":[
        {
            "category":"Building & Trades",
            "subcategory":"Construction",
            "type":"Services"
        }
    ],
    "sg:phone":"+1 713 864 4818",
    "sg:postcode":"77007",
    "sg:province":"TX",
    "sg:tags":[
        "painter"
    ],
    "wof:name":"Esmeralda T Painting Co",
    "wof:placetype":"venue"
},
  "geometry": {"coordinates":[-95.37624099999999,29.778447],"type":"Point"}
}