{
  "type": "Feature",
  "properties": {
    "iso:country":"US",
    "sg:address":"12423 Whittington Dr",
    "sg:city":"Houston",
    "sg:classifiers":[
        {
            "category":"Retail",
            "subcategory":"Animal Services",
            "type":"Services"
        }
    ],
    "sg:phone":"+1 281 759 5200",
    "sg:postcode":"77077",
    "sg:province":"TX",
    "sg:tags":[
        "pet",
        "grooming",
        "washing"
    ],
    "wof:name":"Groomers On The Go",
    "wof:placetype":"venue"
},
  "geometry": {"coordinates":[-95.599609,29.747404],"type":"Point"}
}