{
  "type": "Feature",
  "properties": {
    "iso:country":"US",
    "sg:address":"10535 Boyer Boulevard",
    "sg:city":"Austin",
    "sg:classifiers":[
        {
            "category":"Real Estate",
            "subcategory":"Real Estate Services",
            "type":"Services"
        }
    ],
    "sg:phone":"+1 512 836 7118",
    "sg:postcode":"78758",
    "sg:province":"TX",
    "sg:tags":[
        "management",
        "property"
    ],
    "wof:name":"Hill Partners Management Company",
    "wof:placetype":"venue"
},
  "geometry": {"coordinates":[-97.71110899999999,30.383597],"type":"Point"}
}