{
  "type": "Feature",
  "properties": {
    "iso:country":"US",
    "sg:address":"5710 N Carter Ave",
    "sg:city":"Odessa",
    "sg:classifiers":[
        {
            "category":"Professional",
            "subcategory":"Detective & Security Services",
            "type":"Services"
        }
    ],
    "sg:phone":"+1 432 924 5117",
    "sg:postcode":"79764",
    "sg:province":"TX",
    "sg:tags":[
        "information",
        "bureau"
    ],
    "wof:name":"Jackson Small Engine Service",
    "wof:placetype":"venue"
},
  "geometry": {"coordinates":[-102.53008800000001,31.86437],"type":"Point"}
}