{
  "type": "Feature",
  "properties": {
    "iso:country":"US",
    "sg:address":"3319 Prudence Dr",
    "sg:city":"Houston",
    "sg:classifiers":[
        {
            "category":"Retail",
            "subcategory":"Repair Shop",
            "type":"Services"
        }
    ],
    "sg:phone":"+1 713 433 0858",
    "sg:postcode":"77045",
    "sg:province":"TX",
    "sg:tags":[
        "refrigeration"
    ],
    "wof:name":"Air-Tone Heating & Air Conditi",
    "wof:placetype":"venue"
},
  "geometry": {"coordinates":[-95.42625200000001,29.624757],"type":"Point"}
}