{
  "type": "Feature",
  "properties": {
    "iso:country":"US",
    "sg:address":"321 Iron Horse Dr",
    "sg:city":"Hutto",
    "sg:classifiers":[
        {
            "category":"Autos & Motor Vehicles",
            "subcategory":"Automobile Sales",
            "type":"Retail Goods"
        }
    ],
    "sg:phone":"+1 512 255 4556",
    "sg:postcode":"78634",
    "sg:province":"TX",
    "sg:tags":[
        "used"
    ],
    "wof:name":"Classic Street LLC",
    "wof:placetype":"venue"
},
  "geometry": {"coordinates":[-97.59572900000001,30.53705],"type":"Point"}
}