{
  "type": "Feature",
  "properties": {
    "iso:country":"US",
    "sg:address":"2173 Turkey Rd",
    "sg:city":"Gladewater",
    "sg:classifiers":[
        {
            "category":"Manufacturing",
            "subcategory":"Buildings",
            "type":"Manufacturing & Wholesale Goods"
        },
        {
            "category":"Building & Trades",
            "subcategory":"Construction",
            "type":"Services"
        }
    ],
    "sg:phone":"+1 903 759 4955",
    "sg:postcode":"75647",
    "sg:province":"TX",
    "sg:tags":[
        "excavation",
        "home",
        "builder",
        "contractor",
        "grading"
    ],
    "sg:website":"http://www.trendsetterconstruction.com",
    "wof:name":"Trendsetter Construction Inc.",
    "wof:placetype":"venue"
},
  "geometry": {"coordinates":[-94.873001,32.573225],"type":"Point"}
}