{
  "type": "Feature",
  "properties": {
    "iso:country":"US",
    "sg:address":"1011 E Connell St",
    "sg:city":"Breckenridge",
    "sg:classifiers":[
        {
            "category":"Professional",
            "subcategory":"Management & Consulting",
            "type":"Services"
        }
    ],
    "sg:phone":"+1 254 559 6219",
    "sg:postcode":"76424",
    "sg:province":"TX",
    "sg:tags":[
        "business"
    ],
    "wof:name":"Cole Energy Management",
    "wof:placetype":"venue"
},
  "geometry": {"coordinates":[-98.88966000000001,32.759077],"type":"Point"}
}