{
  "type": "Feature",
  "properties": {
    "iso:country":"US",
    "sg:address":"1613 Fredericksburg Rd",
    "sg:city":"San Antonio",
    "sg:classifiers":[
        {
            "category":"Shopping",
            "subcategory":"Gifts & Souvenirs",
            "type":"Retail Goods"
        }
    ],
    "sg:phone":"+1 210 736 2090",
    "sg:postcode":"78201",
    "sg:province":"TX",
    "sg:tags":[
        "shop"
    ],
    "wof:name":"Betty's Gift Shop",
    "wof:placetype":"venue"
},
  "geometry": {"coordinates":[-98.521653,29.45996],"type":"Point"}
}