{
  "type": "Feature",
  "properties": {
    "iso:country":"US",
    "sg:address":"2312 Merle St",
    "sg:city":"Pasadena",
    "sg:classifiers":[
        {
            "category":"Insurance",
            "subcategory":"Insurance Agent",
            "type":"Services"
        }
    ],
    "sg:phone":"+1 713 534 9342",
    "sg:postcode":"77502",
    "sg:province":"TX",
    "wof:name":"Mike Massingill Insurance",
    "wof:placetype":"venue"
},
  "geometry": {"coordinates":[-95.20423099999999,29.676871],"type":"Point"}
}