{
  "type": "Feature",
  "properties": {
    "iso:country":"US",
    "sg:address":"810 Brooks Ave",
    "sg:city":"Rosenberg",
    "sg:classifiers":[
        {
            "category":"Real Estate",
            "subcategory":"Real Estate Operator",
            "type":"Services"
        }
    ],
    "sg:phone":"+1 281 342 4384",
    "sg:postcode":"77471",
    "sg:province":"TX",
    "sg:tags":[
        "apartment"
    ],
    "wof:name":"Brookmore Hollow Apartments",
    "wof:placetype":"venue"
},
  "geometry": {"coordinates":[-95.814702,29.543234],"type":"Point"}
}