{
  "type": "Feature",
  "properties": {
    "iso:country":"US",
    "sg:address":"1401 Jupiter Rd",
    "sg:city":"Plano",
    "sg:classifiers":[
        {
            "category":"Shopping",
            "subcategory":"Books",
            "type":"Retail Goods"
        }
    ],
    "sg:phone":"+1 469 241 1973",
    "sg:postcode":"75074",
    "sg:province":"TX",
    "sg:tags":[
        "dealer"
    ],
    "wof:name":"LA Puerta Libreria Biblica",
    "wof:placetype":"venue"
},
  "geometry": {"coordinates":[-96.682536,33.018667],"type":"Point"}
}