{
  "type": "Feature",
  "properties": {
    "iso:country":"US",
    "sg:address":"15108 Lee Rd",
    "sg:city":"Humble",
    "sg:classifiers":[
        {
            "category":"Shopping",
            "subcategory":"Computers & Home Electronics",
            "type":"Retail Goods"
        }
    ],
    "sg:phone":"+1 281 441 1139",
    "sg:postcode":"77396",
    "sg:province":"TX",
    "wof:name":"Communications X Tra",
    "wof:placetype":"venue"
},
  "geometry": {"coordinates":[-95.303347,29.937831],"type":"Point"}
}