{
  "type": "Feature",
  "properties": {
    "iso:country":"US",
    "sg:address":"1822 S FM 51",
    "sg:city":"Decatur",
    "sg:classifiers":[
        {
            "category":"Banks & Credit Unions",
            "subcategory":"Investment Brokerage",
            "type":"Services"
        }
    ],
    "sg:phone":"+1 940 627 1620",
    "sg:postcode":"76234",
    "sg:province":"TX",
    "sg:tags":[
        "stock",
        "bond"
    ],
    "wof:name":"Edward Jones Co",
    "wof:placetype":"venue"
},
  "geometry": {"coordinates":[-97.59626900000001,33.218644],"type":"Point"}
}