{
  "type": "Feature",
  "properties": {
    "iso:country":"US",
    "sg:address":"913 N Mill St",
    "sg:city":"Lewisville",
    "sg:classifiers":[
        {
            "category":"Insurance",
            "subcategory":"Insurance Agent",
            "type":"Services"
        }
    ],
    "sg:phone":"+1 972 436 1955",
    "sg:postcode":"75057",
    "sg:province":"TX",
    "sg:tags":[
        "company"
    ],
    "wof:name":"Allen & Hughes Insurance Inc",
    "wof:placetype":"venue"
},
  "geometry": {"coordinates":[-97.000688,33.057286],"type":"Point"}
}