{
  "type": "Feature",
  "properties": {
    "iso:country":"US",
    "sg:address":"1506 Rosalie St",
    "sg:city":"Houston",
    "sg:classifiers":[
        {
            "category":"Professional",
            "subcategory":"Research",
            "type":"Services"
        }
    ],
    "sg:phone":"+1 713 528 3107",
    "sg:postcode":"77004",
    "sg:province":"TX",
    "sg:tags":[
        "information",
        "technology",
        "scientific"
    ],
    "wof:name":"Smrc",
    "wof:placetype":"venue"
},
  "geometry": {"coordinates":[-95.37150200000001,29.739101],"type":"Point"}
}