{
  "type": "Feature",
  "properties": {
    "iso:country":"US",
    "sg:address":"2825 I- 10 Svc Rd",
    "sg:city":"Beaumont",
    "sg:classifiers":[
        {
            "category":"Professional",
            "subcategory":"Advertising",
            "type":"Services"
        }
    ],
    "sg:phone":"+1 409 924 9500",
    "sg:postcode":"77702",
    "sg:province":"TX",
    "sg:tags":[
        "representative"
    ],
    "wof:name":"Tcim Services Inc",
    "wof:placetype":"venue"
},
  "geometry": {"coordinates":[-94.131197,30.095549],"type":"Point"}
}