{
  "type": "Feature",
  "properties": {
    "iso:country":"US",
    "sg:address":"1223 N Front St",
    "sg:city":"Mathis",
    "sg:classifiers":[
        {
            "category":"Organizations",
            "subcategory":"Community Association",
            "type":"Services"
        }
    ],
    "sg:phone":"+1 361 547 0177",
    "sg:postcode":"78368",
    "sg:province":"TX",
    "wof:name":"Kiwanis International Inc",
    "wof:placetype":"venue"
},
  "geometry": {"coordinates":[-97.82165500000001,28.101495],"type":"Point"}
}