{
  "type": "Feature",
  "properties": {
    "iso:country":"US",
    "sg:address":"424 N Center St",
    "sg:city":"Longview",
    "sg:classifiers":[
        {
            "category":"Insurance",
            "subcategory":"Hazard Insurance",
            "type":"Services"
        }
    ],
    "sg:phone":"+1 903 758 1751",
    "sg:postcode":"75601",
    "sg:province":"TX",
    "sg:tags":[
        "bond"
    ],
    "wof:name":"ABC Bail Bonds",
    "wof:placetype":"venue"
},
  "geometry": {"coordinates":[-94.738451,32.499813],"type":"Point"}
}