{
  "type": "Feature",
  "properties": {
    "iso:country":"US",
    "sg:address":"117 Eileen Dr",
    "sg:city":"Pleasanton",
    "sg:classifiers":[
        {
            "category":"Building & Trades",
            "subcategory":"Construction",
            "type":"Services"
        }
    ],
    "sg:phone":"+1 830 569 4996",
    "sg:postcode":"78064",
    "sg:province":"TX",
    "sg:tags":[
        "industrial",
        "contractors-commercial",
        "contractor"
    ],
    "wof:name":"Monica L Urban",
    "wof:placetype":"venue"
},
  "geometry": {"coordinates":[-98.514976,28.959898],"type":"Point"}
}