{
  "type": "Feature",
  "properties": {
    "iso:country":"US",
    "sg:address":"8350 N Central Expy",
    "sg:city":"Dallas",
    "sg:classifiers":[
        {
            "category":"Professional",
            "subcategory":"Management & Consulting",
            "type":"Services"
        }
    ],
    "sg:phone":"+1 469 232 3800",
    "sg:postcode":"75206",
    "sg:province":"TX",
    "sg:tags":[
        "consultant",
        "business"
    ],
    "sg:website":"www.haygroup.com",
    "wof:name":"Hay Management Consultants",
    "wof:placetype":"venue"
},
  "geometry": {"coordinates":[-96.77185,32.850455],"type":"Point"}
}