{
  "type": "Feature",
  "properties": {
    "iso:country":"US",
    "sg:address":"2405 S Carrier Pkwy",
    "sg:city":"Grand Prairie",
    "sg:classifiers":[
        {
            "category":"Retail",
            "subcategory":"Veterinary Services",
            "type":"Services"
        }
    ],
    "sg:phone":"+1 972 262 1581",
    "sg:postcode":"75051",
    "sg:province":"TX",
    "sg:tags":[
        "hospital",
        "animal"
    ],
    "sg:website":"www.carrieranimalhospital.com",
    "wof:name":"Carrier Animal Hospital",
    "wof:placetype":"venue"
},
  "geometry": {"coordinates":[-97.01530700000001,32.712022],"type":"Point"}
}