{
  "type": "Feature",
  "properties": {
    "iso:country":"US",
    "sg:address":"10323 Lake Creek Pkwy",
    "sg:city":"Austin",
    "sg:classifiers":[
        {
            "category":"Professional",
            "subcategory":"Employment Agencies",
            "type":"Services"
        }
    ],
    "sg:phone":"+1 512 257 3600",
    "sg:postcode":"78750",
    "sg:province":"TX",
    "wof:name":"Multi-World LLC",
    "wof:placetype":"venue"
},
  "geometry": {"coordinates":[-97.79548,30.460643],"type":"Point"}
}