{
  "type": "Feature",
  "properties": {
    "iso:country":"US",
    "sg:address":"11150 Research Blvd",
    "sg:city":"Austin",
    "sg:classifiers":[
        {
            "category":"Arts & Performance",
            "subcategory":"Theater",
            "type":"Entertainment"
        }
    ],
    "sg:phone":"+1 512 349 7198",
    "sg:postcode":"78759",
    "sg:province":"TX",
    "sg:tags":[
        "dance",
        "company"
    ],
    "wof:name":"Third Coast Jazz",
    "wof:placetype":"venue"
},
  "geometry": {"coordinates":[-97.745942,30.405083],"type":"Point"}
}