{
  "type": "Feature",
  "properties": {
    "iso:country":"US",
    "sg:address":"1502 W Coral Reef Ln",
    "sg:city":"Wylie",
    "sg:classifiers":[
        {
            "category":"Building & Trades",
            "subcategory":"Construction",
            "type":"Services"
        }
    ],
    "sg:phone":"+1 214 763 5463",
    "sg:postcode":"75098",
    "sg:province":"TX",
    "sg:tags":[
        "hanging",
        "contractor"
    ],
    "wof:name":"Solis Armando",
    "wof:placetype":"venue"
},
  "geometry": {"coordinates":[-96.567903,33.041341],"type":"Point"}
}