{
  "type": "Feature",
  "properties": {
    "iso:country":"US",
    "sg:address":"515 S 1st St",
    "sg:city":"Lufkin",
    "sg:classifiers":[
        {
            "category":"Professional",
            "subcategory":"Lawyer & Legal Services",
            "type":"Services"
        }
    ],
    "sg:phone":"+1 936 637 4800",
    "sg:postcode":"75901",
    "sg:province":"TX",
    "wof:name":"Cox Jrlynn Jackee Atty At Law",
    "wof:placetype":"venue"
},
  "geometry": {"coordinates":[-94.73025199999999,31.335102],"type":"Point"}
}