{
  "type": "Feature",
  "properties": {
    "iso:country":"US",
    "sg:address":"4717 S Lamar St",
    "sg:city":"Dallas",
    "sg:classifiers":[
        {
            "category":"Wholesale",
            "subcategory":"Scrap",
            "type":"Manufacturing & Wholesale Goods"
        }
    ],
    "sg:phone":"+1 214 426 6566",
    "sg:postcode":"75215",
    "sg:province":"TX",
    "sg:tags":[
        "recycling",
        "center"
    ],
    "wof:name":"Okon Metals Inc",
    "wof:placetype":"venue"
},
  "geometry": {"coordinates":[-96.763268,32.746908],"type":"Point"}
}