{
  "type": "Feature",
  "properties": {
    "iso:country":"US",
    "sg:address":"202 S Ave S",
    "sg:city":"Lamesa",
    "sg:classifiers":[
        {
            "category":"Sports & Exercise",
            "subcategory":"Golf",
            "type":"Entertainment"
        }
    ],
    "sg:phone":"+1 806 872 8100",
    "sg:postcode":"79331",
    "sg:province":"TX",
    "sg:tags":[
        "course"
    ],
    "wof:name":"Plains Fairways",
    "wof:placetype":"venue"
},
  "geometry": {"coordinates":[-101.972506,32.727769],"type":"Point"}
}