{
  "type": "Feature",
  "properties": {
    "iso:country":"US",
    "sg:address":"1918 W Ave H",
    "sg:city":"Temple",
    "sg:classifiers":[
        {
            "category":"Shopping",
            "subcategory":"Clothing, Apparel, & Fashions",
            "type":"Retail Goods"
        }
    ],
    "sg:phone":"+1 254 791 5437",
    "sg:postcode":"76504",
    "sg:province":"TX",
    "wof:name":"Wizard Of Goz",
    "wof:placetype":"venue"
},
  "geometry": {"coordinates":[-97.365478,31.094781],"type":"Point"}
}