{
  "type": "Feature",
  "properties": {
    "iso:country":"US",
    "sg:address":"5112 Ave H",
    "sg:city":"Rosenberg",
    "sg:classifiers":[
        {
            "category":"Sports & Exercise",
            "subcategory":"Gym",
            "type":"Entertainment"
        }
    ],
    "sg:phone":"+1 281 239 3517",
    "sg:postcode":"77471",
    "sg:province":"TX",
    "sg:tags":[
        "facility",
        "club",
        "gymnasium",
        "health",
        "fitness",
        "studio",
        "physical"
    ],
    "wof:name":"Curves For Women 85",
    "wof:placetype":"venue"
},
  "geometry": {"coordinates":[-95.77381099999999,29.573476],"type":"Point"}
}