{
  "type": "Feature",
  "properties": {
    "iso:country":"US",
    "sg:address":"11246 Concho St",
    "sg:city":"Houston",
    "sg:classifiers":[
        {
            "category":"Building & Trades",
            "subcategory":"Construction",
            "type":"Services"
        }
    ],
    "sg:phone":"+1 281 933 1025",
    "sg:postcode":"77072",
    "sg:province":"TX",
    "sg:tags":[
        "concrete",
        "contractor"
    ],
    "wof:name":"Slab Cor Construction",
    "wof:placetype":"venue"
},
  "geometry": {"coordinates":[-95.577313,29.690473],"type":"Point"}
}