{
  "type": "Feature",
  "properties": {
    "iso:country":"US",
    "sg:address":"620 Knollwood Dr",
    "sg:city":"Rockwall",
    "sg:classifiers":[
        {
            "category":"Health Services",
            "subcategory":"Health Practitioner",
            "type":"Services"
        }
    ],
    "sg:phone":"+1 972 771 8713",
    "sg:postcode":"75087",
    "sg:province":"TX",
    "wof:name":"Creative Cancer Concepts Inc",
    "wof:placetype":"venue"
},
  "geometry": {"coordinates":[-96.478987,32.93609],"type":"Point"}
}