{
  "type": "Feature",
  "properties": {
    "iso:country":"US",
    "sg:address":"13000 Josey Ln Suite 105",
    "sg:city":"Dallas",
    "sg:classifiers":[
        {
            "category":"Personal",
            "type":"Services"
        },
        {
            "category":"Building & Trades",
            "subcategory":"Cleaning & Sanitation",
            "type":"Services"
        }
    ],
    "sg:phone":"+1 972 484 2663",
    "sg:postcode":"75234",
    "sg:province":"TX",
    "sg:tags":[
        "house",
        "butlers'",
        "maids'"
    ],
    "sg:website":"http://www.maids.com/?source=yellowpages.com",
    "wof:name":"The Maids Home Services",
    "wof:placetype":"venue"
},
  "geometry": {"coordinates":[-96.88157099999999,32.922656],"type":"Point"}
}