{
  "type": "Feature",
  "properties": {
    "iso:country":"US",
    "sg:address":"104 Gallery Cir",
    "sg:city":"San Antonio",
    "sg:classifiers":[
        {
            "category":"Health Services",
            "subcategory":"Doctor",
            "type":"Services"
        }
    ],
    "sg:phone":"+1 210 499 0033",
    "sg:postcode":"78258",
    "sg:province":"TX",
    "sg:tags":[
        "medical"
    ],
    "wof:name":"Adrianne D Vaughn MD Alamo",
    "wof:placetype":"venue"
},
  "geometry": {"coordinates":[-98.491771,29.6152],"type":"Point"}
}