{
  "type": "Feature",
  "properties": {
    "iso:country":"US",
    "sg:address":"1571 Franklin Rd",
    "sg:city":"Eddy",
    "sg:classifiers":[
        {
            "category":"Building & Trades",
            "subcategory":"Electrical",
            "type":"Services"
        }
    ],
    "sg:phone":"+1 254 859 5358",
    "sg:postcode":"76524",
    "sg:province":"TX",
    "sg:tags":[
        "electric",
        "contractor"
    ],
    "wof:name":"Wallace Electric Inc",
    "wof:placetype":"venue"
},
  "geometry": {"coordinates":[-97.276025,31.283788],"type":"Point"}
}