{
  "type": "Feature",
  "properties": {
    "iso:country":"US",
    "sg:address":"200 S Sunny Ln",
    "sg:city":"Linden",
    "sg:classifiers":[
        {
            "category":"Real Estate",
            "subcategory":"Real Estate Operator",
            "type":"Services"
        }
    ],
    "sg:phone":"+1 903 756 7765",
    "sg:postcode":"75563",
    "sg:province":"TX",
    "sg:tags":[
        "apartment"
    ],
    "wof:name":"MJS Management Inc",
    "wof:placetype":"venue"
},
  "geometry": {"coordinates":[-94.35947,33.011617],"type":"Point"}
}