{
  "type": "Feature",
  "properties": {
    "iso:country":"US",
    "sg:address":"212 S Houston St",
    "sg:city":"Hillsboro",
    "sg:classifiers":[
        {
            "category":"Retail",
            "subcategory":"Repair Shop",
            "type":"Services"
        }
    ],
    "sg:phone":"+1 254 582 9621",
    "sg:postcode":"76645",
    "sg:province":"TX",
    "wof:name":"Grounds Locksmith",
    "wof:placetype":"venue"
},
  "geometry": {"coordinates":[-97.135451,32.0097],"type":"Point"}
}