{
  "type": "Feature",
  "properties": {
    "iso:country":"US",
    "sg:address":"703 15th St",
    "sg:city":"Olton",
    "sg:classifiers":[
        {
            "category":"Wholesale",
            "subcategory":"Farm Supplies",
            "type":"Manufacturing & Wholesale Goods"
        }
    ],
    "sg:phone":"+1 806 285 3076",
    "sg:postcode":"79064",
    "sg:province":"TX",
    "sg:tags":[
        "bulb",
        "seed"
    ],
    "wof:name":"Texas Best Bean & Seed",
    "wof:placetype":"venue"
},
  "geometry": {"coordinates":[-102.13758300000001,34.173917],"type":"Point"}
}