{
  "type": "Feature",
  "properties": {
    "iso:country":"US",
    "sg:address":"234 W Rochelle Rd",
    "sg:city":"Irving",
    "sg:classifiers":[
        {
            "category":"Banks & Credit Unions",
            "subcategory":"Investment Brokerage",
            "type":"Services"
        }
    ],
    "sg:phone":"+1 972 252 0805",
    "sg:postcode":"75062",
    "sg:province":"TX",
    "sg:tags":[
        "management"
    ],
    "wof:name":"K Sabzwari Investments Inc",
    "wof:placetype":"venue"
},
  "geometry": {"coordinates":[-96.949736,32.844346],"type":"Point"}
}