{
  "type": "Feature",
  "properties": {
    "iso:country":"US",
    "sg:address":"1706 Strawberry Rd",
    "sg:city":"Pasadena",
    "sg:classifiers":[
        {
            "category":"Home & Garden",
            "subcategory":"Building Materials",
            "type":"Retail Goods"
        }
    ],
    "sg:phone":"+1 713 472 5590",
    "sg:postcode":"77502",
    "sg:province":"TX",
    "wof:name":"Five Star Products Inc",
    "wof:placetype":"venue"
},
  "geometry": {"coordinates":[-95.19326599999999,29.686193],"type":"Point"}
}