{
  "type": "Feature",
  "properties": {
    "iso:country":"US",
    "sg:address":"13405 Granada St",
    "sg:city":"Houston",
    "sg:classifiers":[
        {
            "category":"Professional",
            "subcategory":"Detective & Security Services",
            "type":"Services"
        }
    ],
    "sg:phone":"+1 713 453 2525",
    "sg:postcode":"77015",
    "sg:province":"TX",
    "sg:tags":[
        "investigator"
    ],
    "wof:name":"Baker Street Intl",
    "wof:placetype":"venue"
},
  "geometry": {"coordinates":[-95.18391099999999,29.788144],"type":"Point"}
}