{
  "type": "Feature",
  "properties": {
    "iso:country":"US",
    "sg:address":"609 E Main St",
    "sg:city":"Gatesville",
    "sg:classifiers":[
        {
            "category":"Professional",
            "subcategory":"Lawyer & Legal Services",
            "type":"Services"
        }
    ],
    "sg:phone":"+1 254 248 1650",
    "sg:postcode":"76528",
    "sg:province":"TX",
    "sg:tags":[
        "attorney"
    ],
    "wof:name":"Gately Sandy Law Office",
    "wof:placetype":"venue"
},
  "geometry": {"coordinates":[-97.75052100000001,31.435002],"type":"Point"}
}