{
  "type": "Feature",
  "properties": {
    "iso:country":"US",
    "sg:address":"12755 FM 1346",
    "sg:city":"Saint Hedwig",
    "sg:classifiers":[
        {
            "category":"Manufacturing",
            "subcategory":"Building Materials",
            "type":"Manufacturing & Wholesale Goods"
        }
    ],
    "sg:phone":"+1 210 667 1034",
    "sg:postcode":"78152",
    "sg:province":"TX",
    "sg:tags":[
        "mfg",
        "wood",
        "kitchen",
        "cabinet"
    ],
    "wof:name":"Pats Cabinet Shop",
    "wof:placetype":"venue"
},
  "geometry": {"coordinates":[-98.231917,29.426369],"type":"Point"}
}