{
  "type": "Feature",
  "properties": {
    "iso:country":"US",
    "sg:address":"7347 Bonita St",
    "sg:city":"Houston",
    "sg:classifiers":[
        {
            "category":"Social Services",
            "type":"Services"
        }
    ],
    "sg:phone":"+1 713 635 5470",
    "sg:postcode":"77016",
    "sg:province":"TX",
    "wof:name":"Bonita Street House Of Hope",
    "wof:placetype":"venue"
},
  "geometry": {"coordinates":[-95.32376499999999,29.822201],"type":"Point"}
}