{
  "type": "Feature",
  "properties": {
    "iso:country":"US",
    "sg:address":"5960 W Parker Rd",
    "sg:city":"Plano",
    "sg:classifiers":[
        {
            "category":"Personal",
            "subcategory":"Beauty Salon",
            "type":"Services"
        }
    ],
    "sg:phone":"+1 972 473 2720",
    "sg:postcode":"75093",
    "sg:province":"TX",
    "wof:name":"Style America",
    "wof:placetype":"venue"
},
  "geometry": {"coordinates":[-96.827029,33.045229],"type":"Point"}
}