{
  "type": "Feature",
  "properties": {
    "iso:country":"US",
    "sg:address":"1335 Santa Fe St",
    "sg:city":"Corpus Christi",
    "sg:classifiers":[
        {
            "category":"Shopping",
            "subcategory":"Pharmacy",
            "type":"Retail Goods"
        }
    ],
    "sg:phone":"+1 361 887 5066",
    "sg:postcode":"78404",
    "sg:province":"TX",
    "wof:name":"Clinical Nuclear Svc Inc",
    "wof:placetype":"venue"
},
  "geometry": {"coordinates":[-97.39727600000001,27.777631],"type":"Point"}
}