{
  "type": "Feature",
  "properties": {
    "iso:country":"US",
    "sg:address":"3633 SW Moody St",
    "sg:city":"Victoria",
    "sg:classifiers":[
        {
            "category":"Food & Beverages",
            "subcategory":"Groceries & Convenience Stores",
            "type":"Retail Goods"
        }
    ],
    "sg:phone":"+1 361 573 0128",
    "sg:postcode":"77905",
    "sg:province":"TX",
    "sg:tags":[
        "gasoline"
    ],
    "wof:name":"Oak Hill Food Store",
    "wof:placetype":"venue"
},
  "geometry": {"coordinates":[-97.045022,28.783374],"type":"Point"}
}