{
  "type": "Feature",
  "properties": {
    "iso:country":"US",
    "sg:address":"2202 Bon Aire Ave",
    "sg:city":"Victoria",
    "sg:classifiers":[
        {
            "category":"Shopping",
            "type":"Retail Goods"
        }
    ],
    "sg:phone":"+1 361 576 4043",
    "sg:postcode":"77901",
    "sg:province":"TX",
    "sg:tags":[
        "merchandise"
    ],
    "wof:name":"Mikes Pro Shop Victoria Co",
    "wof:placetype":"venue"
},
  "geometry": {"coordinates":[-96.982902,28.819513],"type":"Point"}
}