{
  "type": "Feature",
  "properties": {
    "iso:country":"US",
    "sg:address":"4200 Westheimer Ste 102",
    "sg:city":"Houston",
    "sg:classifiers":[
        {
            "category":"Home & Garden",
            "subcategory":"Building Materials",
            "type":"Retail Goods"
        },
        {
            "category":"Building & Trades",
            "subcategory":"Construction",
            "type":"Services"
        }
    ],
    "sg:phone":"+1 713 627 8970",
    "sg:postcode":"77027",
    "sg:province":"TX",
    "sg:tags":[
        "interior",
        "design",
        "supply"
    ],
    "sg:website":"www.cabinetsanddesigns.net/",
    "wof:name":"Cabinets & Designs Inc",
    "wof:placetype":"venue"
},
  "geometry": {"coordinates":[-95.44998,29.741613],"type":"Point"}
}