{
  "type": "Feature",
  "properties": {
    "iso:country":"US",
    "sg:address":"2605 Independence Rd",
    "sg:city":"Colleyville",
    "sg:classifiers":[
        {
            "category":"Professional",
            "subcategory":"Management & Consulting",
            "type":"Services"
        }
    ],
    "sg:phone":"+1 817 251 0968",
    "sg:postcode":"76034",
    "sg:province":"TX",
    "wof:name":"Richardson & Assoc",
    "wof:placetype":"venue"
},
  "geometry": {"coordinates":[-97.128287,32.901998],"type":"Point"}
}