{
  "type": "Feature",
  "properties": {
    "iso:country":"US",
    "sg:address":"933 E Nasa Pkwy",
    "sg:city":"Houston",
    "sg:classifiers":[
        {
            "category":"Shopping",
            "subcategory":"Discount & Variety Stores",
            "type":"Retail Goods"
        }
    ],
    "sg:phone":"+1 281 486 4999",
    "sg:postcode":"77058",
    "sg:province":"TX",
    "sg:tags":[
        "merchandise"
    ],
    "wof:name":"Always 99c Store",
    "wof:placetype":"venue"
},
  "geometry": {"coordinates":[-95.107574,29.545474],"type":"Point"}
}