{
  "type": "Feature",
  "properties": {
    "iso:country":"US",
    "sg:address":"1302 E Oak Ave",
    "sg:city":"Midland",
    "sg:classifiers":[
        {
            "category":"Shopping",
            "subcategory":"Gifts & Souvenirs",
            "type":"Retail Goods"
        }
    ],
    "sg:phone":"+1 432 684 8568",
    "sg:postcode":"79705",
    "sg:province":"TX",
    "wof:name":"San Miguel Mexican Imports",
    "wof:placetype":"venue"
},
  "geometry": {"coordinates":[-102.066907,32.025711],"type":"Point"}
}