{
  "type": "Feature",
  "properties": {
    "iso:country":"US",
    "sg:address":"4161 Hallmont Dr",
    "sg:city":"Grapevine",
    "sg:classifiers":[
        {
            "category":"Professional",
            "type":"Services"
        }
    ],
    "sg:phone":"+1 817 684 1361",
    "sg:postcode":"76051",
    "sg:province":"TX",
    "wof:name":"Smarttime",
    "wof:placetype":"venue"
},
  "geometry": {"coordinates":[-97.112943,32.892677],"type":"Point"}
}