{
  "type": "Feature",
  "properties": {
    "iso:country":"US",
    "sg:address":"819 Orange Ave",
    "sg:city":"Farmersville",
    "sg:classifiers":[
        {
            "category":"Freight",
            "type":"Transportation"
        }
    ],
    "sg:phone":"+1 972 782 8370",
    "sg:postcode":"75442",
    "sg:province":"TX",
    "sg:tags":[
        "commercial",
        "storage"
    ],
    "wof:name":"Orange Street Storage",
    "wof:placetype":"venue"
},
  "geometry": {"coordinates":[-96.358313,33.154072],"type":"Point"}
}