{
  "type": "Feature",
  "properties": {
    "iso:country":"US",
    "sg:address":"9500 S I-H 35 South Park Meadows",
    "sg:city":"Austin",
    "sg:classifiers":[
        {
            "category":"Restaurant",
            "type":"Food & Drink"
        }
    ],
    "sg:phone":"+1 512 292 1658",
    "sg:postcode":"78748",
    "sg:province":"TX",
    "sg:tags":[
        "italian"
    ],
    "wof:name":"Johnny Carino's",
    "wof:placetype":"venue"
},
  "geometry": {"coordinates":[-97.789131,30.162178],"type":"Point"}
}