{
  "type": "Feature",
  "properties": {
    "iso:country":"US",
    "sg:address":"105 E Maxan St",
    "sg:city":"Port Isabel",
    "sg:classifiers":[
        {
            "category":"Sports & Exercise",
            "subcategory":"Gym",
            "type":"Entertainment"
        }
    ],
    "sg:phone":"+1 956 943 2221",
    "sg:postcode":"78578",
    "sg:province":"TX",
    "sg:tags":[
        "club",
        "health",
        "studio",
        "gymnasium"
    ],
    "wof:name":"Curves For Women",
    "wof:placetype":"venue"
},
  "geometry": {"coordinates":[-97.209868,26.076621],"type":"Point"}
}