{
  "type": "Feature",
  "properties": {
    "iso:country":"US",
    "sg:address":"1180 Appling Rd",
    "sg:city":"Kingsbury",
    "sg:classifiers":[
        {
            "category":"Professional",
            "subcategory":"Management & Consulting",
            "type":"Services"
        }
    ],
    "sg:phone":"+1 830 875 6888",
    "sg:postcode":"78638",
    "sg:province":"TX",
    "sg:tags":[
        "consultant",
        "medium"
    ],
    "wof:name":"Murphy Media Group",
    "wof:placetype":"venue"
},
  "geometry": {"coordinates":[-97.75926200000001,29.643983],"type":"Point"}
}