{
  "type": "Feature",
  "properties": {
    "iso:country":"US",
    "sg:address":"8802 Highway 183",
    "sg:city":"Cisco",
    "sg:classifiers":[
        {
            "category":"Farming",
            "subcategory":"Dairy Farm",
            "type":"Manufacturing & Wholesale Goods"
        }
    ],
    "sg:phone":"+1 254 442 1930",
    "sg:postcode":"76437",
    "sg:province":"TX",
    "wof:name":"Marvin Reich",
    "wof:placetype":"venue"
},
  "geometry": {"coordinates":[-98.957683,32.30805],"type":"Point"}
}