{
  "type": "Feature",
  "properties": {
    "iso:country":"US",
    "sg:address":"524 N Locust St",
    "sg:city":"Denton",
    "sg:classifiers":[
        {
            "category":"Professional",
            "type":"Services"
        }
    ],
    "sg:phone":"+1 940 898 1923",
    "sg:postcode":"76201",
    "sg:province":"TX",
    "sg:tags":[
        "establishment"
    ],
    "wof:name":"Kneaded Touch & Co",
    "wof:placetype":"venue"
},
  "geometry": {"coordinates":[-97.1323,33.218436],"type":"Point"}
}