{
  "type": "Feature",
  "properties": {
    "iso:country":"US",
    "sg:address":"236 S Bonner Ave",
    "sg:city":"Tyler",
    "sg:classifiers":[
        {
            "category":"Professional",
            "type":"Services"
        }
    ],
    "sg:phone":"+1 903 526 2848",
    "sg:postcode":"75702",
    "sg:province":"TX",
    "wof:name":"La Caribenea",
    "wof:placetype":"venue"
},
  "geometry": {"coordinates":[-95.30553999999999,32.346671],"type":"Point"}
}