{
  "type": "Feature",
  "properties": {
    "iso:country":"US",
    "sg:address":"4419 N Main St",
    "sg:city":"Houston",
    "sg:classifiers":[
        {
            "category":"Education",
            "subcategory":"Special Training",
            "type":"Public Place"
        }
    ],
    "sg:phone":"+1 713 869 1205",
    "sg:postcode":"77009",
    "sg:province":"TX",
    "sg:tags":[
        "school",
        "language"
    ],
    "wof:name":"AAMA",
    "wof:placetype":"venue"
},
  "geometry": {"coordinates":[-95.379119,29.795163],"type":"Point"}
}