{
  "type": "Feature",
  "properties": {
    "iso:country":"US",
    "sg:address":"2967 Bingle Rd",
    "sg:city":"Houston",
    "sg:classifiers":[
        {
            "category":"Retail",
            "subcategory":"Auto Rental",
            "type":"Services"
        }
    ],
    "sg:phone":"+1 713 647 9550",
    "sg:postcode":"77055",
    "sg:province":"TX",
    "sg:tags":[
        "passenger",
        "car"
    ],
    "wof:name":"Enterprise Rent-A-Car",
    "wof:placetype":"venue"
},
  "geometry": {"coordinates":[-95.498887,29.820285],"type":"Point"}
}