{
  "type": "Feature",
  "properties": {
    "iso:country":"US",
    "sg:address":"351 E Amber St",
    "sg:city":"San Antonio",
    "sg:classifiers":[
        {
            "category":"Education",
            "subcategory":"School",
            "type":"Public Place"
        }
    ],
    "sg:phone":"+1 210 432 8630",
    "sg:postcode":"78221",
    "sg:province":"TX",
    "wof:name":"School of Leadership",
    "wof:placetype":"venue"
},
  "geometry": {"coordinates":[-98.495436,29.344782],"type":"Point"}
}