{
  "type": "Feature",
  "properties": {
    "iso:country":"US",
    "sg:address":"1500 Primrose Dr",
    "sg:city":"Waco",
    "sg:classifiers":[
        {
            "category":"Wholesale",
            "subcategory":"Plants",
            "type":"Manufacturing & Wholesale Goods"
        }
    ],
    "sg:phone":"+1 254 752 3351",
    "sg:postcode":"76706",
    "sg:province":"TX",
    "sg:tags":[
        "florist",
        "flower",
        "supply"
    ],
    "wof:name":"Wolfe Wholesale Florist Inc",
    "wof:placetype":"venue"
},
  "geometry": {"coordinates":[-97.117795,31.532311],"type":"Point"}
}