{
  "type": "Feature",
  "properties": {
    "iso:country":"US",
    "sg:address":"2815 Sam Houston Pkwy",
    "sg:city":"Houston",
    "sg:classifiers":[
        {
            "category":"Building & Trades",
            "subcategory":"Equipment Rental",
            "type":"Services"
        }
    ],
    "sg:phone":"+1 281 372 5635",
    "sg:postcode":"77032",
    "sg:province":"TX",
    "sg:tags":[
        "leasing"
    ],
    "wof:name":"Hertz",
    "wof:placetype":"venue"
},
  "geometry": {"coordinates":[-95.345326,29.939529],"type":"Point"}
}