{
  "type": "Feature",
  "properties": {
    "iso:country":"US",
    "sg:address":"613 Tampico St",
    "sg:city":"Mission",
    "sg:classifiers":[
        {
            "category":"Restaurant",
            "type":"Food & Drink"
        }
    ],
    "sg:phone":"+1 956 580 2294",
    "sg:postcode":"78572",
    "sg:province":"TX",
    "sg:tags":[
        "mexican"
    ],
    "wof:name":"Jose I Garcia",
    "wof:placetype":"venue"
},
  "geometry": {"coordinates":[-98.38721099999999,26.229885],"type":"Point"}
}