{
  "type": "Feature",
  "properties": {
    "iso:country":"US",
    "sg:address":"450 Lantana St",
    "sg:city":"Corpus Christi",
    "sg:classifiers":[
        {
            "category":"Professional",
            "subcategory":"Testing Lab",
            "type":"Services"
        }
    ],
    "sg:phone":"+1 361 289 5457",
    "sg:postcode":"78408",
    "sg:province":"TX",
    "sg:tags":[
        "core",
        "oil",
        "well",
        "analysis"
    ],
    "wof:name":"Core Lab Petroleum Svc",
    "wof:placetype":"venue"
},
  "geometry": {"coordinates":[-97.470173,27.793142],"type":"Point"}
}