{
  "type": "Feature",
  "properties": {
    "iso:country":"US",
    "sg:address":"14204 Vandever St",
    "sg:city":"Austin",
    "sg:classifiers":[
        {
            "category":"Wholesale",
            "subcategory":"Jewelry",
            "type":"Manufacturing & Wholesale Goods"
        },
        {
            "category":"Shopping",
            "subcategory":"Crafts & Fabrics",
            "type":"Retail Goods"
        }
    ],
    "sg:phone":"+1 512 669 8862",
    "sg:postcode":"78725",
    "sg:province":"TX",
    "sg:tags":[
        "bead",
        "beads-wholesale",
        "manufacturer"
    ],
    "wof:name":"Susans-Beads",
    "wof:placetype":"venue"
},
  "geometry": {"coordinates":[-97.587216,30.242837],"type":"Point"}
}