{
  "type": "Feature",
  "properties": {
    "iso:country":"US",
    "sg:address":"2526 S Adams St",
    "sg:city":"Fort Worth",
    "sg:classifiers":[
        {
            "category":"Professional",
            "subcategory":"Management & Consulting",
            "type":"Services"
        }
    ],
    "sg:phone":"+1 817 926 2366",
    "sg:postcode":"76110",
    "sg:province":"TX",
    "wof:name":"Historic Design Development",
    "wof:placetype":"venue"
},
  "geometry": {"coordinates":[-97.336759,32.715751],"type":"Point"}
}