{
  "type": "Feature",
  "properties": {
    "iso:country":"US",
    "sg:address":"1310 Ranch Rd 620 S",
    "sg:city":"Lakeway",
    "sg:classifiers":[
        {
            "category":"Utilities",
            "subcategory":"Natural Gas",
            "type":"Services"
        }
    ],
    "sg:phone":"+1 512 263 1892",
    "sg:postcode":"78734",
    "sg:province":"TX",
    "sg:tags":[
        "producer"
    ],
    "wof:name":"Bayou Bend Petroleum Corp",
    "wof:placetype":"venue"
},
  "geometry": {"coordinates":[-97.96316899999999,30.351303],"type":"Point"}
}