{
  "type": "Feature",
  "properties": {
    "iso:country":"US",
    "sg:address":"4810 Fountainhead Dr",
    "sg:city":"Houston",
    "sg:classifiers":[
        {
            "category":"Professional",
            "subcategory":"Employment Agencies",
            "type":"Services"
        }
    ],
    "sg:phone":"+1 281 444 3325",
    "sg:postcode":"77066",
    "sg:province":"TX",
    "sg:tags":[
        "opportunity"
    ],
    "sg:website":"www.ideal-staffing.com",
    "wof:name":"Ideal Staffing Svc",
    "wof:placetype":"venue"
},
  "geometry": {"coordinates":[-95.498824,29.981218],"type":"Point"}
}