{
  "type": "Feature",
  "properties": {
    "iso:country":"US",
    "sg:address":"1366 Broad Valley Ct",
    "sg:city":"Burleson",
    "sg:classifiers":[
        {
            "category":"Professional",
            "type":"Services"
        }
    ],
    "sg:phone":"+1 817 295 6168",
    "sg:postcode":"76028",
    "sg:province":"TX",
    "wof:name":"Elroy Rivas",
    "wof:placetype":"venue"
},
  "geometry": {"coordinates":[-97.33074000000001,32.515692],"type":"Point"}
}