{
  "type": "Feature",
  "properties": {
    "iso:country":"US",
    "sg:address":"3126 S Flores St",
    "sg:city":"San Antonio",
    "sg:classifiers":[
        {
            "category":"Organizations",
            "subcategory":"Religious Organization",
            "type":"Services"
        }
    ],
    "sg:phone":"+1 210 923 3206",
    "sg:postcode":"78204",
    "sg:province":"TX",
    "sg:tags":[
        "church"
    ],
    "wof:name":"Safe Harbor Church",
    "wof:placetype":"venue"
},
  "geometry": {"coordinates":[-98.503998,29.392985],"type":"Point"}
}