{
  "type": "Feature",
  "properties": {
    "iso:country":"US",
    "sg:address":"1013 E 15th St",
    "sg:city":"Plano",
    "sg:classifiers":[
        {
            "category":"Professional",
            "type":"Services"
        }
    ],
    "sg:phone":"+1 972 312 1808",
    "sg:postcode":"75074",
    "sg:province":"TX",
    "sg:tags":[
        "establishment"
    ],
    "wof:name":"Michael Holter Creative",
    "wof:placetype":"venue"
},
  "geometry": {"coordinates":[-96.699226,33.019698],"type":"Point"}
}