{
  "type": "Feature",
  "properties": {
    "iso:country":"US",
    "sg:address":"6202 Vickijohn Dr",
    "sg:city":"Houston",
    "sg:classifiers":[
        {
            "category":"Manufacturing",
            "subcategory":"Metals",
            "type":"Manufacturing & Wholesale Goods"
        }
    ],
    "sg:phone":"+1 713 771 2454",
    "sg:postcode":"77096",
    "sg:province":"TX",
    "sg:tags":[
        "mfg"
    ],
    "wof:name":"American Rollflex Corp",
    "wof:placetype":"venue"
},
  "geometry": {"coordinates":[-95.49829800000001,29.662375],"type":"Point"}
}