{
  "type": "Feature",
  "properties": {
    "iso:country":"US",
    "sg:address":"1207 Stonegate St",
    "sg:city":"Alice",
    "sg:classifiers":[
        {
            "category":"Professional",
            "type":"Services"
        }
    ],
    "sg:phone":"+1 361 668 0217",
    "sg:postcode":"78332",
    "sg:province":"TX",
    "wof:name":"Ramirez Danielll",
    "wof:placetype":"venue"
},
  "geometry": {"coordinates":[-98.058913,27.740037],"type":"Point"}
}