{
  "type": "Feature",
  "properties": {
    "iso:country":"US",
    "sg:address":"719 N Kentucky St",
    "sg:city":"Mc Kinney",
    "sg:classifiers":[
        {
            "category":"Retail",
            "subcategory":"Repair Shop",
            "type":"Services"
        }
    ],
    "sg:phone":"+1 972 562 5551",
    "sg:postcode":"75069",
    "sg:province":"TX",
    "sg:tags":[
        "restoration",
        "furniture"
    ],
    "wof:name":"Affordable Antiques",
    "wof:placetype":"venue"
},
  "geometry": {"coordinates":[-96.61601899999999,33.204713],"type":"Point"}
}