{
  "type": "Feature",
  "properties": {
    "iso:country":"US",
    "sg:address":"11110 Metric Blvd Ste B",
    "sg:city":"Austin",
    "sg:classifiers":[
        {
            "category":"Retail",
            "subcategory":"Repair Shop",
            "type":"Services"
        }
    ],
    "sg:phone":"+1 512 719 4041",
    "sg:postcode":"78758",
    "sg:province":"TX",
    "sg:tags":[
        "tool",
        "electric"
    ],
    "sg:website":"http://www.simco.com",
    "wof:name":"Simco Electronics",
    "wof:placetype":"venue"
},
  "geometry": {"coordinates":[-97.709771,30.39005],"type":"Point"}
}