{
  "type": "Feature",
  "properties": {
    "iso:country":"US",
    "sg:address":"7844 Abbot Dr",
    "sg:city":"Fort Worth",
    "sg:classifiers":[
        {
            "category":"Wholesale",
            "subcategory":"Computers",
            "type":"Manufacturing & Wholesale Goods"
        }
    ],
    "sg:phone":"+1 817 246 6436",
    "sg:postcode":"76108",
    "sg:province":"TX",
    "wof:name":"Calvery Computing & More",
    "wof:placetype":"venue"
},
  "geometry": {"coordinates":[-97.450495,32.74643],"type":"Point"}
}