{
  "type": "Feature",
  "properties": {
    "iso:country":"US",
    "sg:address":"3715 Little York Rd",
    "sg:city":"Houston",
    "sg:classifiers":[
        {
            "category":"Restaurant",
            "type":"Food & Drink"
        }
    ],
    "sg:phone":"+1 281 449 5466",
    "sg:postcode":"77093",
    "sg:province":"TX",
    "sg:website":"www.burgerking.com",
    "wof:name":"Burger King",
    "wof:placetype":"venue"
},
  "geometry": {"coordinates":[-95.331299,29.870701],"type":"Point"}
}