{
  "type": "Feature",
  "properties": {
    "iso:country":"US",
    "sg:address":"5011 Alabama St",
    "sg:city":"El Paso",
    "sg:classifiers":[
        {
            "category":"Social Services",
            "subcategory":"Child Care",
            "type":"Services"
        }
    ],
    "sg:phone":"+1 915 566 7755",
    "sg:postcode":"79930",
    "sg:province":"TX",
    "sg:tags":[
        "day"
    ],
    "wof:name":"Bellas Day Care & Learning Ctr",
    "wof:placetype":"venue"
},
  "geometry": {"coordinates":[-106.465726,31.821797],"type":"Point"}
}