{
  "type": "Feature",
  "properties": {
    "iso:country":"US",
    "sg:address":"16306 Longneck Dr",
    "sg:city":"Magnolia",
    "sg:classifiers":[
        {
            "category":"Personal",
            "subcategory":"Beauty Salon",
            "type":"Services"
        }
    ],
    "sg:phone":"+1 281 259 0235",
    "sg:postcode":"77355",
    "sg:province":"TX",
    "sg:tags":[
        "shop"
    ],
    "wof:name":"Baycliff It/Is Lists Inc",
    "wof:placetype":"venue"
},
  "geometry": {"coordinates":[-95.729609,30.12483],"type":"Point"}
}