{
  "type": "Feature",
  "properties": {
    "iso:country":"US",
    "sg:address":"3725 Colony Dr",
    "sg:city":"San Antonio",
    "sg:classifiers":[
        {
            "category":"Shopping",
            "type":"Retail Goods"
        }
    ],
    "sg:phone":"+1 210 696 1511",
    "sg:postcode":"78230",
    "sg:province":"TX",
    "sg:tags":[
        "animal",
        "supply"
    ],
    "wof:name":"PETCO",
    "wof:placetype":"venue"
},
  "geometry": {"coordinates":[-98.55904700000001,29.531256],"type":"Point"}
}