{
  "type": "Feature",
  "properties": {
    "iso:country":"US",
    "sg:address":"3113 S Sam Rayburn Fwy",
    "sg:city":"Sherman",
    "sg:classifiers":[
        {
            "category":"Food & Beverages",
            "subcategory":"Groceries & Convenience Stores",
            "type":"Retail Goods"
        }
    ],
    "sg:phone":"+1 903 892 8279",
    "sg:postcode":"75090",
    "sg:province":"TX",
    "wof:name":"Aleman Food Mart",
    "wof:placetype":"venue"
},
  "geometry": {"coordinates":[-96.60883699999999,33.609605],"type":"Point"}
}