{
  "type": "Feature",
  "properties": {
    "iso:country":"US",
    "sg:address":"601 N Tom Green Ave",
    "sg:city":"Odessa",
    "sg:classifiers":[
        {
            "category":"Health Services",
            "subcategory":"Doctor",
            "type":"Services"
        }
    ],
    "sg:phone":"+1 432 334 7888",
    "sg:postcode":"79761",
    "sg:province":"TX",
    "sg:tags":[
        "physician",
        "surgeon"
    ],
    "wof:name":"Women's Center-Permian Basin",
    "wof:placetype":"venue"
},
  "geometry": {"coordinates":[-102.36657099999999,31.852361],"type":"Point"}
}