{
  "type": "Feature",
  "properties": {
    "iso:country":"US",
    "sg:address":"2106 Old Sattler Rd",
    "sg:city":"Canyon Lake",
    "sg:classifiers":[
        {
            "category":"Food & Beverages",
            "subcategory":"Groceries & Convenience Stores",
            "type":"Retail Goods"
        }
    ],
    "sg:phone":"+1 830 899 4699",
    "sg:postcode":"78133",
    "sg:province":"TX",
    "sg:tags":[
        "grocer"
    ],
    "wof:name":"Tiger Stop",
    "wof:placetype":"venue"
},
  "geometry": {"coordinates":[-98.263178,29.843396],"type":"Point"}
}