{
  "type": "Feature",
  "properties": {
    "iso:country":"US",
    "sg:address":"2409 Sir Guy Dr",
    "sg:city":"Grand Prairie",
    "sg:classifiers":[
        {
            "category":"Building & Trades",
            "subcategory":"Equipment Rental",
            "type":"Services"
        }
    ],
    "sg:phone":"+1 972 641 2824",
    "sg:postcode":"75050",
    "sg:province":"TX",
    "wof:name":"Potter Rentals",
    "wof:placetype":"venue"
},
  "geometry": {"coordinates":[-97.039604,32.774969],"type":"Point"}
}