{
  "type": "Feature",
  "properties": {
    "iso:country":"US",
    "sg:address":"609 Hilltop Ct",
    "sg:city":"Kennedale",
    "sg:classifiers":[
        {
            "category":"Professional",
            "subcategory":"Management & Consulting",
            "type":"Services"
        }
    ],
    "sg:phone":"+1 817 483 7574",
    "sg:postcode":"76060",
    "sg:province":"TX",
    "sg:tags":[
        "consultant"
    ],
    "sg:website":"www.prochemist.com",
    "wof:name":"Mcafee Consulting",
    "wof:placetype":"venue"
},
  "geometry": {"coordinates":[-97.217501,32.650562],"type":"Point"}
}