{
  "type": "Feature",
  "properties": {
    "iso:country":"US",
    "sg:address":"9826 Canoga Ln",
    "sg:city":"Houston",
    "sg:classifiers":[
        {
            "category":"Wholesale",
            "subcategory":"Toys & Hobbies",
            "type":"Manufacturing & Wholesale Goods"
        }
    ],
    "sg:phone":"+1 713 827 9092",
    "sg:postcode":"77080",
    "sg:province":"TX",
    "sg:tags":[
        "educational"
    ],
    "wof:name":"Gil-Mor Inc",
    "wof:placetype":"venue"
},
  "geometry": {"coordinates":[-95.538093,29.808313],"type":"Point"}
}