{
  "type": "Feature",
  "properties": {
    "iso:country":"US",
    "sg:address":"201 N Center St",
    "sg:city":"Arlington",
    "sg:classifiers":[
        {
            "category":"Autos & Motor Vehicles",
            "subcategory":"Automobile Sales",
            "type":"Retail Goods"
        }
    ],
    "sg:phone":"+1 817 861 1020",
    "sg:postcode":"76011",
    "sg:province":"TX",
    "sg:tags":[
        "car",
        "used",
        "dealer"
    ],
    "wof:name":"R C Used Cars",
    "wof:placetype":"venue"
},
  "geometry": {"coordinates":[-97.10694599999999,32.739049],"type":"Point"}
}