{
  "type": "Feature",
  "properties": {
    "iso:country":"US",
    "sg:address":"1750 Range Dr",
    "sg:city":"Mesquite",
    "sg:classifiers":[
        {
            "category":"Building & Trades",
            "subcategory":"Construction",
            "type":"Services"
        }
    ],
    "sg:phone":"+1 972 285 2600",
    "sg:postcode":"75149",
    "sg:province":"TX",
    "sg:tags":[
        "home",
        "builder"
    ],
    "wof:name":"Woodstone Homes",
    "wof:placetype":"venue"
},
  "geometry": {"coordinates":[-96.596856,32.787802],"type":"Point"}
}