{
  "type": "Feature",
  "properties": {
    "iso:country":"US",
    "sg:address":"3500 Mccall Ln",
    "sg:city":"Austin",
    "sg:classifiers":[
        {
            "category":"Real Estate",
            "subcategory":"Surveying",
            "type":"Services"
        }
    ],
    "sg:phone":"+1 512 476 4456",
    "sg:postcode":"78744",
    "sg:province":"TX",
    "sg:tags":[
        "planning",
        "land"
    ],
    "wof:name":"Thrower Design",
    "wof:placetype":"venue"
},
  "geometry": {"coordinates":[-97.68814500000001,30.20112],"type":"Point"}
}