{
  "type": "Feature",
  "properties": {
    "iso:country":"US",
    "sg:address":"2060 Space Park Dr",
    "sg:city":"Houston",
    "sg:classifiers":[
        {
            "category":"Health Services",
            "subcategory":"Doctor",
            "type":"Services"
        }
    ],
    "sg:phone":"+1 281 333 1703",
    "sg:postcode":"77058",
    "sg:province":"TX",
    "sg:tags":[
        "medical"
    ],
    "wof:name":"Oggero Kelly S M D F A C S",
    "wof:placetype":"venue"
},
  "geometry": {"coordinates":[-95.086567,29.548426],"type":"Point"}
}