{
  "type": "Feature",
  "properties": {
    "iso:country":"US",
    "sg:address":"13129 Veterans Memorial Dr",
    "sg:city":"Houston",
    "sg:classifiers":[
        {
            "category":"Personal",
            "subcategory":"Beauty Salon",
            "type":"Services"
        }
    ],
    "sg:phone":"+1 281 440 3447",
    "sg:postcode":"77014",
    "sg:province":"TX",
    "sg:tags":[
        "shop"
    ],
    "wof:name":"Another Level Of Style",
    "wof:placetype":"venue"
},
  "geometry": {"coordinates":[-95.49096,29.977893],"type":"Point"}
}