{
  "type": "Feature",
  "properties": {
    "iso:country":"US",
    "sg:address":"514 Broad Leaf Ln",
    "sg:city":"Mc Kinney",
    "sg:classifiers":[
        {
            "category":"Insurance",
            "subcategory":"Insurance Agent",
            "type":"Services"
        }
    ],
    "sg:phone":"+1 972 547 9755",
    "sg:postcode":"75070",
    "sg:province":"TX",
    "wof:name":"CIC Insurance Svc",
    "wof:placetype":"venue"
},
  "geometry": {"coordinates":[-96.683947,33.191116],"type":"Point"}
}