{
  "type": "Feature",
  "properties": {
    "iso:country":"US",
    "sg:address":"9001 Ranch Rd 620 N",
    "sg:city":"Austin",
    "sg:classifiers":[
        {
            "category":"Social Services",
            "subcategory":"Child Care",
            "type":"Services"
        }
    ],
    "sg:phone":"+1 512 258 4495",
    "sg:postcode":"78726",
    "sg:province":"TX",
    "sg:tags":[
        "day"
    ],
    "wof:name":"Canyon Creek Preschool Inc",
    "wof:placetype":"venue"
},
  "geometry": {"coordinates":[-97.849947,30.411728],"type":"Point"}
}