{
  "type": "Feature",
  "properties": {
    "iso:country":"US",
    "sg:address":"2308 Miguel Ln",
    "sg:city":"Arlington",
    "sg:classifiers":[
        {
            "category":"Local Transit",
            "type":"Transportation"
        }
    ],
    "sg:phone":"+1 817 451 9786",
    "sg:postcode":"76016",
    "sg:province":"TX",
    "sg:tags":[
        "passenger"
    ],
    "wof:name":"Special K Limousine",
    "wof:placetype":"venue"
},
  "geometry": {"coordinates":[-97.193934,32.707107],"type":"Point"}
}