{
  "type": "Feature",
  "properties": {
    "iso:country":"US",
    "sg:address":"1658 Redwood St",
    "sg:city":"Seguin",
    "sg:classifiers":[
        {
            "category":"Retail",
            "subcategory":"Repair Shop",
            "type":"Services"
        }
    ],
    "sg:phone":"+1 830 303 2188",
    "sg:postcode":"78155",
    "sg:province":"TX",
    "sg:tags":[
        "welding"
    ],
    "wof:name":"Dreamcatcher Wldg Fabrication",
    "wof:placetype":"venue"
},
  "geometry": {"coordinates":[-97.931994,29.567965],"type":"Point"}
}