{
  "type": "Feature",
  "properties": {
    "iso:country":"US",
    "sg:address":"2030 Glade Rd",
    "sg:city":"Grapevine",
    "sg:classifiers":[
        {
            "category":"Food & Beverages",
            "subcategory":"Candy",
            "type":"Retail Goods"
        },
        {
            "category":"Shopping",
            "subcategory":"Florist",
            "type":"Retail Goods"
        }
    ],
    "sg:phone":"+1 817 410 1212",
    "sg:postcode":"76051",
    "sg:province":"TX",
    "sg:tags":[
        "cookie",
        "arrangement"
    ],
    "wof:name":"Candy Bouquet",
    "wof:placetype":"venue"
},
  "geometry": {"coordinates":[-97.095242,32.881155],"type":"Point"}
}