{
  "type": "Feature",
  "properties": {
    "iso:country":"US",
    "sg:address":"2318 Brookney St",
    "sg:city":"Pearland",
    "sg:classifiers":[
        {
            "category":"Building & Trades",
            "subcategory":"Landscaping Services",
            "type":"Services"
        }
    ],
    "sg:phone":"+1 281 997 1489",
    "sg:postcode":"77584",
    "sg:province":"TX",
    "wof:name":"Johnson Tractor Service",
    "wof:placetype":"venue"
},
  "geometry": {"coordinates":[-95.36116199999999,29.56913],"type":"Point"}
}