{
  "type": "Feature",
  "properties": {
    "iso:country":"US",
    "sg:address":"14065 Aston St",
    "sg:city":"Houston",
    "sg:classifiers":[
        {
            "category":"Manufacturing",
            "subcategory":"Petroleum Products",
            "type":"Manufacturing & Wholesale Goods"
        }
    ],
    "sg:phone":"+1 713 690 1711",
    "sg:postcode":"77040",
    "sg:province":"TX",
    "sg:tags":[
        "contract"
    ],
    "wof:name":"Turner Hitec Industries",
    "wof:placetype":"venue"
},
  "geometry": {"coordinates":[-95.529214,29.852341],"type":"Point"}
}