{
  "type": "Feature",
  "properties": {
    "iso:country":"US",
    "sg:address":"816 Congress Ave",
    "sg:city":"Austin",
    "sg:classifiers":[
        {
            "category":"Professional",
            "subcategory":"Lawyer & Legal Services",
            "type":"Services"
        }
    ],
    "sg:phone":"+1 512 473 3644",
    "sg:postcode":"78701",
    "sg:province":"TX",
    "wof:name":"Joe Daly",
    "wof:placetype":"venue"
},
  "geometry": {"coordinates":[-97.741878,30.27072],"type":"Point"}
}