{
  "type": "Feature",
  "properties": {
    "iso:country":"US",
    "sg:address":"2520 Little John Ln",
    "sg:city":"Groves",
    "sg:classifiers":[
        {
            "category":"Building & Trades",
            "subcategory":"Cleaning & Sanitation",
            "type":"Services"
        }
    ],
    "sg:phone":"+1 409 963 1656",
    "sg:postcode":"77619",
    "sg:province":"TX",
    "sg:tags":[
        "maintenance"
    ],
    "wof:name":"United Home Maintenance",
    "wof:placetype":"venue"
},
  "geometry": {"coordinates":[-93.899799,29.943267],"type":"Point"}
}