{
  "type": "Feature",
  "properties": {
    "iso:country":"US",
    "sg:address":"220 US Hwy 87",
    "sg:city":"Tulia",
    "sg:classifiers":[
        {
            "category":"Professional",
            "type":"Services"
        }
    ],
    "sg:phone":"+1 806 995 4815",
    "sg:postcode":"79088",
    "sg:province":"TX",
    "wof:name":"Bill's Fina Svc",
    "wof:placetype":"venue"
},
  "geometry": {"coordinates":[-101.77633400000001,34.539591],"type":"Point"}
}