{
  "type": "Feature",
  "properties": {
    "iso:country":"US",
    "sg:address":"990 Foster Rd",
    "sg:city":"Pleasanton",
    "sg:classifiers":[
        {
            "category":"Farming",
            "subcategory":"Farm",
            "type":"Manufacturing & Wholesale Goods"
        }
    ],
    "sg:phone":"+1 830 569 4354",
    "sg:postcode":"78064",
    "sg:province":"TX",
    "sg:tags":[
        "crop",
        "general"
    ],
    "wof:name":"Eugene Martinez",
    "wof:placetype":"venue"
},
  "geometry": {"coordinates":[-98.38696,29.020358],"type":"Point"}
}