{
  "type": "Feature",
  "properties": {
    "iso:country":"US",
    "sg:address":"1736 N Mays St",
    "sg:city":"Round Rock",
    "sg:classifiers":[
        {
            "category":"Banks & Credit Unions",
            "subcategory":"Bank",
            "type":"Services"
        }
    ],
    "sg:phone":"+1 512 733 9617",
    "sg:postcode":"78664",
    "sg:province":"TX",
    "sg:tags":[
        "loan"
    ],
    "wof:name":"Sun Loan Co",
    "wof:placetype":"venue"
},
  "geometry": {"coordinates":[-97.685851,30.523553],"type":"Point"}
}