{
  "type": "Feature",
  "properties": {
    "iso:country":"US",
    "sg:address":"9541 Church St",
    "sg:city":"Needville",
    "sg:classifiers":[
        {
            "category":"Building & Trades",
            "subcategory":"Construction",
            "type":"Services"
        }
    ],
    "sg:phone":"+1 979 793 3613",
    "sg:postcode":"77461",
    "sg:province":"TX",
    "sg:tags":[
        "utility",
        "paving",
        "site"
    ],
    "wof:name":"Cadle Construction",
    "wof:placetype":"venue"
},
  "geometry": {"coordinates":[-95.83305799999999,29.392624],"type":"Point"}
}