{
  "type": "Feature",
  "properties": {
    "iso:country":"US",
    "sg:address":"1504 S Kaufman St",
    "sg:city":"Ennis",
    "sg:classifiers":[
        {
            "category":"Manufacturing",
            "subcategory":"Rubber & Plastics",
            "type":"Manufacturing & Wholesale Goods"
        }
    ],
    "sg:phone":"+1 972 875 6555",
    "sg:postcode":"75119",
    "sg:province":"TX",
    "sg:tags":[
        "spa",
        "hot",
        "tub"
    ],
    "wof:name":"Koral Industries Inc",
    "wof:placetype":"venue"
},
  "geometry": {"coordinates":[-96.61526499999999,32.318638],"type":"Point"}
}