{
  "type": "Feature",
  "properties": {
    "iso:country":"US",
    "sg:address":"1165 Peavy Rd",
    "sg:city":"Dallas",
    "sg:classifiers":[
        {
            "category":"Home & Garden",
            "subcategory":"Furniture",
            "type":"Retail Goods"
        }
    ],
    "sg:phone":"+1 214 660 9557",
    "sg:postcode":"75218",
    "sg:province":"TX",
    "sg:tags":[
        "store"
    ],
    "wof:name":"Garcia Discount Furniture",
    "wof:placetype":"venue"
},
  "geometry": {"coordinates":[-96.69732399999999,32.83931],"type":"Point"}
}