{
  "type": "Feature",
  "properties": {
    "iso:country":"US",
    "sg:address":"10719 Plano Rd",
    "sg:city":"Dallas",
    "sg:classifiers":[
        {
            "category":"Manufacturing",
            "subcategory":"Apparel",
            "type":"Manufacturing & Wholesale Goods"
        }
    ],
    "sg:phone":"+1 214 503 1500",
    "sg:postcode":"75238",
    "sg:province":"TX",
    "wof:name":"Boyce McLeon Usa Inc",
    "wof:placetype":"venue"
},
  "geometry": {"coordinates":[-96.700745,32.896579],"type":"Point"}
}