{
  "type": "Feature",
  "properties": {
    "iso:country":"US",
    "sg:address":"825 Quince Ave",
    "sg:city":"Mcallen",
    "sg:classifiers":[
        {
            "category":"Professional",
            "subcategory":"Lawyer & Legal Services",
            "type":"Services"
        }
    ],
    "sg:phone":"+1 956 687 8233",
    "sg:postcode":"78501",
    "sg:province":"TX",
    "sg:tags":[
        "attorney"
    ],
    "wof:name":"Servando Gonzales Law Office",
    "wof:placetype":"venue"
},
  "geometry": {"coordinates":[-98.226134,26.218662],"type":"Point"}
}