{
  "type": "Feature",
  "properties": {
    "iso:country":"US",
    "sg:address":"235 W Rochelle Rd",
    "sg:city":"Irving",
    "sg:classifiers":[
        {
            "category":"Personal",
            "subcategory":"Beauty Salon",
            "type":"Services"
        }
    ],
    "sg:phone":"+1 972 255 8586",
    "sg:postcode":"75062",
    "sg:province":"TX",
    "wof:name":"Anita's Family Hair Style",
    "wof:placetype":"venue"
},
  "geometry": {"coordinates":[-96.949736,32.844346],"type":"Point"}
}