{
  "type": "Feature",
  "properties": {
    "iso:country":"US",
    "sg:address":"2217 N 10th St",
    "sg:city":"Mcallen",
    "sg:classifiers":[
        {
            "category":"Insurance",
            "subcategory":"Insurance Agent",
            "type":"Services"
        }
    ],
    "sg:phone":"+1 956 687 1779",
    "sg:postcode":"78501",
    "sg:province":"TX",
    "wof:name":"Palm City Insurance Co",
    "wof:placetype":"venue"
},
  "geometry": {"coordinates":[-98.226563,26.223983],"type":"Point"}
}