{
  "type": "Feature",
  "properties": {
    "iso:country":"US",
    "sg:address":"2510 S Oklahoma Ave",
    "sg:city":"Weslaco",
    "sg:classifiers":[
        {
            "category":"Shopping",
            "subcategory":"Used Merchandise",
            "type":"Retail Goods"
        }
    ],
    "sg:phone":"+1 956 968 8692",
    "sg:postcode":"78596",
    "sg:province":"TX",
    "wof:name":"Marys Second Hand Store",
    "wof:placetype":"venue"
},
  "geometry": {"coordinates":[-97.994714,26.13161],"type":"Point"}
}