{
  "type": "Feature",
  "properties": {
    "iso:country":"US",
    "sg:address":"2401 N Arkansas Ave",
    "sg:city":"Laredo",
    "sg:classifiers":[
        {
            "category":"Autos & Motor Vehicles",
            "subcategory":"Automobile Sales",
            "type":"Retail Goods"
        }
    ],
    "sg:phone":"+1 956 712 0364",
    "sg:postcode":"78043",
    "sg:province":"TX",
    "sg:tags":[
        "car",
        "used",
        "dealer"
    ],
    "wof:name":"Deanda Auto Sales",
    "wof:placetype":"venue"
},
  "geometry": {"coordinates":[-99.46799900000001,27.518582],"type":"Point"}
}