{
  "type": "Feature",
  "properties": {
    "iso:country":"US",
    "sg:address":"108 Oak Shadows",
    "sg:city":"Lufkin",
    "sg:classifiers":[
        {
            "category":"Real Estate",
            "subcategory":"Real Estate Agent",
            "type":"Services"
        }
    ],
    "sg:phone":"+1 936 632 4749",
    "sg:postcode":"75901",
    "sg:province":"TX",
    "wof:name":"Brandenburg Real Estate",
    "wof:placetype":"venue"
},
  "geometry": {"coordinates":[-94.70283000000001,31.299489],"type":"Point"}
}