{
  "type": "Feature",
  "properties": {
    "iso:country":"US",
    "sg:address":"6201 Valleyview St",
    "sg:city":"Leander",
    "sg:classifiers":[
        {
            "category":"Insurance",
            "subcategory":"Life Insurance",
            "type":"Services"
        }
    ],
    "sg:phone":"+1 512 267 2233",
    "sg:postcode":"78645",
    "sg:province":"TX",
    "sg:tags":[
        "annuity",
        "health"
    ],
    "wof:name":"Aid Assoc For Lutherans",
    "wof:placetype":"venue"
},
  "geometry": {"coordinates":[-97.990578,30.458614],"type":"Point"}
}