{
  "type": "Feature",
  "properties": {
    "iso:country":"US",
    "sg:address":"4513 Keota Dr",
    "sg:city":"Austin",
    "sg:classifiers":[
        {
            "category":"Health Services",
            "subcategory":"Chiropractor",
            "type":"Services"
        }
    ],
    "sg:phone":"+1 512 328 2639",
    "sg:postcode":"78749",
    "sg:province":"TX",
    "wof:name":"Mackin Chiropractic Clinic",
    "wof:placetype":"venue"
},
  "geometry": {"coordinates":[-97.852059,30.206579],"type":"Point"}
}