{
  "type": "Feature",
  "properties": {
    "iso:country":"US",
    "sg:address":"2034 Christian Rd",
    "sg:city":"Ennis",
    "sg:classifiers":[
        {
            "category":"Professional",
            "subcategory":"Business Services",
            "type":"Services"
        }
    ],
    "sg:phone":"+1 972 878 9917",
    "sg:postcode":"75119",
    "sg:province":"TX",
    "wof:name":"Ja Bingham Enterprises Inc",
    "wof:placetype":"venue"
},
  "geometry": {"coordinates":[-96.616201,32.366541],"type":"Point"}
}