{
  "type": "Feature",
  "properties": {
    "iso:country":"US",
    "sg:address":"4305 Bryant Irvin Rd",
    "sg:city":"Fort Worth",
    "sg:classifiers":[
        {
            "category":"Building & Trades",
            "subcategory":"Equipment Rental",
            "type":"Services"
        }
    ],
    "sg:phone":"+1 817 738 7368",
    "sg:postcode":"76132",
    "sg:province":"TX",
    "sg:tags":[
        "heavy",
        "construction"
    ],
    "wof:name":"Nationsrent Inc",
    "wof:placetype":"venue"
},
  "geometry": {"coordinates":[-97.41346900000001,32.717955],"type":"Point"}
}