{
  "type": "Feature",
  "properties": {
    "iso:country":"US",
    "sg:address":"1001 Bluebonnet Ln",
    "sg:city":"Austin",
    "sg:classifiers":[
        {
            "category":"Building & Trades",
            "subcategory":"Construction",
            "type":"Services"
        }
    ],
    "sg:phone":"+1 512 291 5701",
    "sg:postcode":"78704",
    "sg:province":"TX",
    "sg:tags":[
        "contractor"
    ],
    "wof:name":"Cllp Inc",
    "wof:placetype":"venue"
},
  "geometry": {"coordinates":[-97.769266,30.259899],"type":"Point"}
}