{
  "type": "Feature",
  "properties": {
    "iso:country":"US",
    "sg:address":"6202 Iguana Cir",
    "sg:city":"Austin",
    "sg:classifiers":[
        {
            "category":"Building & Trades",
            "subcategory":"Construction",
            "type":"Services"
        }
    ],
    "sg:phone":"+1 512 288 5824",
    "sg:postcode":"78735",
    "sg:province":"TX",
    "sg:tags":[
        "house"
    ],
    "wof:name":"Howard Nettles Const Co",
    "wof:placetype":"venue"
},
  "geometry": {"coordinates":[-97.87949500000001,30.24506],"type":"Point"}
}