{
  "type": "Feature",
  "properties": {
    "iso:country":"US",
    "sg:address":"719 Meadow Ln",
    "sg:city":"Bryan",
    "sg:classifiers":[
        {
            "category":"Professional",
            "subcategory":"Engineering",
            "type":"Services"
        }
    ],
    "sg:phone":"+1 979 260 1574",
    "sg:postcode":"77802",
    "sg:province":"TX",
    "wof:name":"Jamieson Associates",
    "wof:placetype":"venue"
},
  "geometry": {"coordinates":[-96.35065899999999,30.641219],"type":"Point"}
}