{
  "type": "Feature",
  "properties": {
    "iso:country":"US",
    "sg:address":"7399 N Central Expy",
    "sg:city":"Plano",
    "sg:classifiers":[
        {
            "category":"Restaurant",
            "type":"Food & Drink"
        }
    ],
    "sg:menulink":"http://www.allmenus.com/tx/plano/42630-luna-de-noche/menu/",
    "sg:phone":"+1 214 389 9520",
    "sg:postcode":"75025",
    "sg:province":"TX",
    "sg:tags":[
        "mexican"
    ],
    "wof:name":"Luna De Noche",
    "wof:placetype":"venue"
},
  "geometry": {"coordinates":[-96.686747,33.075306],"type":"Point"}
}