{
  "type": "Feature",
  "properties": {
    "iso:country":"US",
    "sg:address":"2610 Parana Dr",
    "sg:city":"Houston",
    "sg:classifiers":[
        {
            "category":"Shopping",
            "subcategory":"Used Merchandise",
            "type":"Retail Goods"
        }
    ],
    "sg:phone":"+1 713 996 9415",
    "sg:postcode":"77080",
    "sg:province":"TX",
    "wof:name":"I&M Antique Maps Prints Etc",
    "wof:placetype":"venue"
},
  "geometry": {"coordinates":[-95.53506899999999,29.820112],"type":"Point"}
}