{
  "type": "Feature",
  "properties": {
    "iso:country":"US",
    "sg:address":"10264 Co Rd 37",
    "sg:city":"Sinton",
    "sg:classifiers":[
        {
            "category":"Wholesale",
            "subcategory":"Sporting Goods",
            "type":"Manufacturing & Wholesale Goods"
        }
    ],
    "sg:phone":"+1 361 364 5455",
    "sg:postcode":"78387",
    "sg:province":"TX",
    "wof:name":"Johnsons Upholstery Shop",
    "wof:placetype":"venue"
},
  "geometry": {"coordinates":[-97.57282600000001,28.088505],"type":"Point"}
}