{
  "type": "Feature",
  "properties": {
    "iso:country":"US",
    "sg:address":"1304 Shards Ct",
    "sg:city":"Denton",
    "sg:classifiers":[
        {
            "category":"Shopping",
            "subcategory":"Jewelry",
            "type":"Retail Goods"
        }
    ],
    "sg:phone":"+1 903 564 6991",
    "sg:postcode":"76210",
    "sg:province":"TX",
    "wof:name":"Jewelry Box",
    "wof:placetype":"venue"
},
  "geometry": {"coordinates":[-97.09074699999999,33.135878],"type":"Point"}
}