{
  "type": "Feature",
  "properties": {
    "iso:country":"US",
    "sg:address":"6601 Cypresswood Dr",
    "sg:city":"Spring",
    "sg:classifiers":[
        {
            "category":"Wholesale",
            "subcategory":"Electrical",
            "type":"Manufacturing & Wholesale Goods"
        }
    ],
    "sg:phone":"+1 713 539 9424",
    "sg:postcode":"77379",
    "sg:province":"TX",
    "sg:tags":[
        "equipment",
        "telecommunication"
    ],
    "wof:name":"RC Telecom Sales LLC",
    "wof:placetype":"venue"
},
  "geometry": {"coordinates":[-95.505504,30.016114],"type":"Point"}
}