{
  "type": "Feature",
  "properties": {
    "iso:country":"US",
    "sg:address":"2906 Deep Valley Trl",
    "sg:city":"Plano",
    "sg:classifiers":[
        {
            "category":"Home & Garden",
            "subcategory":"Home Furnishings",
            "type":"Retail Goods"
        }
    ],
    "sg:phone":"+1 972 530 3343",
    "sg:postcode":"75075",
    "sg:province":"TX",
    "sg:tags":[
        "quilting"
    ],
    "wof:name":"Stephanie's Quilt Making",
    "wof:placetype":"venue"
},
  "geometry": {"coordinates":[-96.744984,33.037551],"type":"Point"}
}