{
  "type": "Feature",
  "properties": {
    "iso:country":"US",
    "sg:address":"2 W Plaza St",
    "sg:city":"Ladonia",
    "sg:classifiers":[
        {
            "category":"Real Estate",
            "subcategory":"Real Estate Agent",
            "type":"Services"
        }
    ],
    "sg:phone":"+1 903 367 7317",
    "sg:postcode":"75449",
    "sg:province":"TX",
    "wof:name":"Clang Realty",
    "wof:placetype":"venue"
},
  "geometry": {"coordinates":[-95.94729599999999,33.426238],"type":"Point"}
}