{
  "type": "Feature",
  "properties": {
    "iso:country":"US",
    "sg:address":"10612 Hempstead Rd Ste D",
    "sg:city":"Houston",
    "sg:classifiers":[
        {
            "category":"Manufacturing",
            "subcategory":"Tools & Machinery",
            "type":"Manufacturing & Wholesale Goods"
        },
        {
            "category":"Manufacturing",
            "subcategory":"Electronics",
            "type":"Manufacturing & Wholesale Goods"
        },
        {
            "category":"Shopping",
            "subcategory":"Computers & Home Electronics",
            "type":"Retail Goods"
        }
    ],
    "sg:phone":"+1 713 682 4747",
    "sg:postcode":"77092",
    "sg:province":"TX",
    "sg:tags":[
        "electric",
        "consumer",
        "equipment-testing",
        "equipment",
        "supplies-wholesale",
        "manufacturer"
    ],
    "sg:website":"http://www.dongriffin.com",
    "wof:name":"Don Griffin",
    "wof:placetype":"venue"
},
  "geometry": {"coordinates":[-95.46941099999999,29.808257],"type":"Point"}
}