{
  "type": "Feature",
  "properties": {
    "iso:country":"US",
    "sg:address":"3316 Blue Jay Ln",
    "sg:city":"Austin",
    "sg:classifiers":[
        {
            "category":"Building & Trades",
            "subcategory":"Landscaping Services",
            "type":"Services"
        }
    ],
    "sg:phone":"+1 512 322 0662",
    "sg:postcode":"78732",
    "sg:province":"TX",
    "wof:name":"Treetamers",
    "wof:placetype":"venue"
},
  "geometry": {"coordinates":[-97.91132399999999,30.386205],"type":"Point"}
}