{
  "type": "Feature",
  "properties": {
    "iso:country":"US",
    "sg:address":"140 Old Hwy 90 E",
    "sg:city":"Vidor",
    "sg:classifiers":[
        {
            "category":"Retail",
            "subcategory":"Auto Repair",
            "type":"Services"
        }
    ],
    "sg:phone":"+1 409 769 8448",
    "sg:postcode":"77662",
    "sg:province":"TX",
    "sg:tags":[
        "automobile",
        "inspection"
    ],
    "wof:name":"Herb's State Inspection Sta",
    "wof:placetype":"venue"
},
  "geometry": {"coordinates":[-94.011842,30.124809],"type":"Point"}
}