{
  "type": "Feature",
  "properties": {
    "iso:country":"US",
    "sg:address":"12200 Gulf Fwy",
    "sg:city":"Houston",
    "sg:classifiers":[
        {
            "category":"Home & Garden",
            "subcategory":"Home Furnishings",
            "type":"Retail Goods"
        }
    ],
    "sg:phone":"+1 713 946 8085",
    "sg:postcode":"77034",
    "sg:province":"TX",
    "sg:tags":[
        "linen",
        "house"
    ],
    "wof:name":"Anna's Linens",
    "wof:placetype":"venue"
},
  "geometry": {"coordinates":[-95.22247299999999,29.621476],"type":"Point"}
}