{
  "type": "Feature",
  "properties": {
    "iso:country":"US",
    "sg:address":"5925 Forest Ln",
    "sg:city":"Dallas",
    "sg:classifiers":[
        {
            "category":"Banks & Credit Unions",
            "subcategory":"Investment Brokerage",
            "type":"Services"
        }
    ],
    "sg:phone":"+1 972 503 1217",
    "sg:postcode":"75230",
    "sg:province":"TX",
    "sg:tags":[
        "security"
    ],
    "wof:name":"Edward Jones Co",
    "wof:placetype":"venue"
},
  "geometry": {"coordinates":[-96.80473000000001,32.909613],"type":"Point"}
}