{
  "type": "Feature",
  "properties": {
    "iso:country":"US",
    "sg:address":"401 E Hillside Rd",
    "sg:city":"Laredo",
    "sg:classifiers":[
        {
            "category":"Professional",
            "subcategory":"Lawyer & Legal Services",
            "type":"Services"
        }
    ],
    "sg:phone":"+1 956 791 6634",
    "sg:postcode":"78041",
    "sg:province":"TX",
    "sg:tags":[
        "attorney",
        "criminal",
        "family",
        "divorce",
        "damage",
        "accident",
        "property",
        "law"
    ],
    "wof:name":"Mario, Castillo Jr",
    "wof:placetype":"venue"
},
  "geometry": {"coordinates":[-99.491348,27.546129],"type":"Point"}
}