{
  "type": "Feature",
  "properties": {
    "iso:country":"US",
    "sg:address":"1855 Cheyenne Dr",
    "sg:city":"Carrollton",
    "sg:classifiers":[
        {
            "category":"Personal",
            "subcategory":"Beauty Salon",
            "type":"Services"
        }
    ],
    "sg:phone":"+1 972 492 2187",
    "sg:postcode":"75010",
    "sg:province":"TX",
    "sg:tags":[
        "shop"
    ],
    "wof:name":"Hair Haven",
    "wof:placetype":"venue"
},
  "geometry": {"coordinates":[-96.885262,33.02957],"type":"Point"}
}