{
  "type": "Feature",
  "properties": {
    "iso:country":"US",
    "sg:address":"332 Somerset Rd",
    "sg:city":"San Antonio",
    "sg:classifiers":[
        {
            "category":"Bars & Pubs",
            "type":"Food & Drink"
        }
    ],
    "sg:phone":"+1 210 922 8199",
    "sg:postcode":"78211",
    "sg:province":"TX",
    "sg:tags":[
        "club",
        "drinking",
        "night"
    ],
    "wof:name":"LA Cita Nite Club",
    "wof:placetype":"venue"
},
  "geometry": {"coordinates":[-98.536905,29.371392],"type":"Point"}
}