{
  "type": "Feature",
  "properties": {
    "iso:country":"US",
    "sg:address":"1911 E University Dr",
    "sg:city":"Edinburg",
    "sg:classifiers":[
        {
            "category":"Restaurant",
            "type":"Food & Drink"
        }
    ],
    "sg:phone":"+1 956 289 1165",
    "sg:postcode":"78539",
    "sg:province":"TX",
    "sg:tags":[
        "eating"
    ],
    "wof:name":"Victor's Chicken",
    "wof:placetype":"venue"
},
  "geometry": {"coordinates":[-98.142415,26.298595],"type":"Point"}
}