{
  "type": "Feature",
  "properties": {
    "iso:country":"US",
    "sg:address":"208 S Brazos St",
    "sg:city":"Whitney",
    "sg:classifiers":[
        {
            "category":"Building & Trades",
            "subcategory":"Construction",
            "type":"Services"
        }
    ],
    "sg:phone":"+1 254 694 3036",
    "sg:postcode":"76692",
    "sg:province":"TX",
    "sg:tags":[
        "home",
        "builder"
    ],
    "wof:name":"Syn Con Construction",
    "wof:placetype":"venue"
},
  "geometry": {"coordinates":[-97.320787,31.946431],"type":"Point"}
}