{
  "type": "Feature",
  "properties": {
    "iso:country":"US",
    "sg:address":"130 Vintage Park Blvd",
    "sg:city":"Houston",
    "sg:classifiers":[
        {
            "category":"Restaurant",
            "type":"Food & Drink"
        }
    ],
    "sg:phone":"+1 281 826 0166",
    "sg:postcode":"77070",
    "sg:province":"TX",
    "sg:tags":[
        "vegetarian",
        "health"
    ],
    "wof:name":"Salata",
    "wof:placetype":"venue"
},
  "geometry": {"coordinates":[-95.574387,29.995819],"type":"Point"}
}