{
  "type": "Feature",
  "properties": {
    "iso:country":"US",
    "sg:address":"5208 Ragan Dr",
    "sg:city":"Lewisville",
    "sg:classifiers":[
        {
            "category":"Building & Trades",
            "subcategory":"Cleaning & Sanitation",
            "type":"Services"
        }
    ],
    "sg:phone":"+1 972 624 0821",
    "sg:postcode":"75056",
    "sg:province":"TX",
    "sg:tags":[
        "window",
        "maintenance"
    ],
    "wof:name":"Clearview Windows",
    "wof:placetype":"venue"
},
  "geometry": {"coordinates":[-96.880599,33.102956],"type":"Point"}
}