{
  "type": "Feature",
  "properties": {
    "iso:country":"US",
    "sg:address":"307 Woodlands Ln",
    "sg:city":"Victoria",
    "sg:classifiers":[
        {
            "category":"Professional",
            "subcategory":"Business Services",
            "type":"Services"
        }
    ],
    "sg:phone":"+1 361 572 0521",
    "sg:postcode":"77904",
    "sg:province":"TX",
    "wof:name":"Chandna Corp",
    "wof:placetype":"venue"
},
  "geometry": {"coordinates":[-97.010677,28.856773],"type":"Point"}
}