{
  "type": "Feature",
  "properties": {
    "iso:country":"US",
    "sg:address":"1003 N High St",
    "sg:city":"Longview",
    "sg:classifiers":[
        {
            "category":"Banks & Credit Unions",
            "subcategory":"Investment Brokerage",
            "type":"Services"
        },
        {
            "category":"Insurance",
            "subcategory":"Hazard Insurance",
            "type":"Services"
        },
        {
            "category":"Banks & Credit Unions",
            "subcategory":"Financial Services",
            "type":"Services"
        }
    ],
    "sg:phone":"+1 903 758 0148",
    "sg:postcode":"75601",
    "sg:province":"TX",
    "sg:tags":[
        "annuity",
        "retirement",
        "commercial",
        "plan",
        "business"
    ],
    "wof:name":"Brokerage Center",
    "wof:placetype":"venue"
},
  "geometry": {"coordinates":[-94.740419,32.505372],"type":"Point"}
}