{
  "type": "Feature",
  "properties": {
    "iso:country":"US",
    "sg:address":"2829 Chimney Rock Rd",
    "sg:city":"Houston",
    "sg:classifiers":[
        {
            "category":"Banks & Credit Unions",
            "subcategory":"Bank",
            "type":"Services"
        }
    ],
    "sg:phone":"+1 713 789 7879",
    "sg:postcode":"77056",
    "sg:province":"TX",
    "sg:website":"www.capitalone.com",
    "wof:name":"CapitalOne",
    "wof:placetype":"venue"
},
  "geometry": {"coordinates":[-95.476302,29.736324],"type":"Point"}
}