{
  "type": "Feature",
  "properties": {
    "iso:country":"US",
    "sg:address":"17407 Kenton Crossing Ln",
    "sg:city":"Richmond",
    "sg:classifiers":[
        {
            "category":"Shopping",
            "subcategory":"Clothing, Apparel, & Fashions",
            "type":"Retail Goods"
        }
    ],
    "sg:phone":"+1 281 277 2374",
    "sg:postcode":"77469",
    "sg:province":"TX",
    "sg:tags":[
        "wear"
    ],
    "wof:name":"Joycees Kidz",
    "wof:placetype":"venue"
},
  "geometry": {"coordinates":[-95.691821,29.705288],"type":"Point"}
}