{
  "type": "Feature",
  "properties": {
    "iso:country":"US",
    "sg:address":"7315 Wood Bluff Blvd",
    "sg:city":"Houston",
    "sg:classifiers":[
        {
            "category":"Professional",
            "type":"Services"
        }
    ],
    "sg:phone":"+1 713 896 1986",
    "sg:postcode":"77040",
    "sg:province":"TX",
    "wof:name":"Oleander Designs",
    "wof:placetype":"venue"
},
  "geometry": {"coordinates":[-95.51823400000001,29.878515],"type":"Point"}
}