{
  "type": "Feature",
  "properties": {
    "iso:country":"US",
    "sg:address":"3698 S Fm 113",
    "sg:city":"Millsap",
    "sg:classifiers":[
        {
            "category":"Structure",
            "subcategory":"Office Building",
            "type":"Public Place"
        }
    ],
    "sg:phone":"+1 940 682 4241",
    "sg:postcode":"76066",
    "sg:province":"TX",
    "sg:tags":[
        "park"
    ],
    "wof:name":"Joe Young Grocery",
    "wof:placetype":"venue"
},
  "geometry": {"coordinates":[-98.005887,32.727646],"type":"Point"}
}