{
  "type": "Feature",
  "properties": {
    "iso:country":"US",
    "sg:address":"2702 Telephone Rd",
    "sg:city":"Houston",
    "sg:classifiers":[
        {
            "category":"Building & Trades",
            "subcategory":"Construction",
            "type":"Services"
        },
        {
            "category":"Home & Garden",
            "subcategory":"Carpets & Floor Coverings",
            "type":"Retail Goods"
        }
    ],
    "sg:phone":"+1 713 923 5422",
    "sg:postcode":"77023",
    "sg:province":"TX",
    "sg:tags":[
        "interior",
        "design",
        "mattress"
    ],
    "wof:name":"Reyna Home Furnishing",
    "wof:placetype":"venue"
},
  "geometry": {"coordinates":[-95.31999999999999,29.7167],"type":"Point"}
}