{
  "type": "Feature",
  "properties": {
    "iso:country":"US",
    "sg:address":"1022 Navarro St",
    "sg:city":"San Antonio",
    "sg:classifiers":[
        {
            "category":"Travel",
            "subcategory":"Travel Agent",
            "type":"Entertainment"
        }
    ],
    "sg:phone":"+1 210 277 1138",
    "sg:postcode":"78205",
    "sg:province":"TX",
    "sg:tags":[
        "agency",
        "bureau"
    ],
    "wof:name":"Seven Seasons Travel",
    "wof:placetype":"venue"
},
  "geometry": {"coordinates":[-98.49027599999999,29.430874],"type":"Point"}
}