{
  "type": "Feature",
  "properties": {
    "iso:country":"US",
    "sg:address":"5716 Trinity Ln",
    "sg:city":"Fort Worth",
    "sg:classifiers":[
        {
            "category":"Professional",
            "type":"Services"
        }
    ],
    "sg:phone":"+1 817 605 0157",
    "sg:postcode":"76137",
    "sg:province":"TX",
    "wof:name":"Bowman Gregory L Etux Mel",
    "wof:placetype":"venue"
},
  "geometry": {"coordinates":[-97.278251,32.851668],"type":"Point"}
}