{
  "type": "Feature",
  "properties": {
    "iso:country":"US",
    "sg:address":"2510 Bitters Rd",
    "sg:city":"San Antonio",
    "sg:classifiers":[
        {
            "category":"Freight",
            "type":"Transportation"
        }
    ],
    "sg:phone":"+1 210 828 0404",
    "sg:postcode":"78217",
    "sg:province":"TX",
    "sg:tags":[
        "special"
    ],
    "wof:name":"Kotzebue Storage Facility",
    "wof:placetype":"venue"
},
  "geometry": {"coordinates":[-98.45092099999999,29.534661],"type":"Point"}
}