{
  "type": "Feature",
  "properties": {
    "iso:country":"US",
    "sg:address":"14102 Woodville Gardens Dr",
    "sg:city":"Houston",
    "sg:classifiers":[
        {
            "category":"Wholesale",
            "subcategory":"Non-durable Goods",
            "type":"Manufacturing & Wholesale Goods"
        }
    ],
    "sg:phone":"+1 281 556 6050",
    "sg:postcode":"77077",
    "sg:province":"TX",
    "wof:name":"Promotional Innovations",
    "wof:placetype":"venue"
},
  "geometry": {"coordinates":[-95.63722,29.761666],"type":"Point"}
}