{
  "type": "Feature",
  "properties": {
    "iso:country":"US",
    "sg:address":"4710 Nolan St",
    "sg:city":"Fort Worth",
    "sg:classifiers":[
        {
            "category":"Professional",
            "type":"Services"
        }
    ],
    "sg:phone":"+1 817 535 3818",
    "sg:postcode":"76119",
    "sg:province":"TX",
    "wof:name":"Funky Town Players",
    "wof:placetype":"venue"
},
  "geometry": {"coordinates":[-97.27582200000001,32.692445],"type":"Point"}
}