{
  "type": "Feature",
  "properties": {
    "iso:country":"US",
    "sg:address":"515 N 2nd St",
    "sg:city":"Killeen",
    "sg:classifiers":[
        {
            "category":"Insurance",
            "subcategory":"Hazard Insurance",
            "type":"Services"
        }
    ],
    "sg:phone":"+1 254 628 7064",
    "sg:postcode":"76541",
    "sg:province":"TX",
    "sg:tags":[
        "bond"
    ],
    "wof:name":"Aaardvark Bail Bond Svc",
    "wof:placetype":"venue"
},
  "geometry": {"coordinates":[-97.72947499999999,31.123208],"type":"Point"}
}