{
  "type": "Feature",
  "properties": {
    "iso:country":"US",
    "sg:address":"120 Main St",
    "sg:city":"Italy",
    "sg:classifiers":[
        {
            "category":"Shopping",
            "subcategory":"Bicycles & Sporting Goods",
            "type":"Retail Goods"
        }
    ],
    "sg:phone":"+1 972 483 6285",
    "sg:postcode":"76651",
    "sg:province":"TX",
    "wof:name":"Anglea Turf Concepts Inc",
    "wof:placetype":"venue"
},
  "geometry": {"coordinates":[-96.886591,32.183879],"type":"Point"}
}