{
  "type": "Feature",
  "properties": {
    "iso:country":"US",
    "sg:address":"1611 Mockingbird Ln",
    "sg:city":"Tyler",
    "sg:classifiers":[
        {
            "category":"Professional",
            "subcategory":"Accounting & Tax Preparation",
            "type":"Services"
        }
    ],
    "sg:phone":"+1 903 593 8233",
    "sg:postcode":"75701",
    "sg:province":"TX",
    "sg:tags":[
        "return",
        "filing"
    ],
    "wof:name":"Tax Centers Of America",
    "wof:placetype":"venue"
},
  "geometry": {"coordinates":[-95.32038,32.335806],"type":"Point"}
}