{
  "type": "Feature",
  "properties": {
    "iso:country":"US",
    "sg:address":"417 S 17th St",
    "sg:city":"Mcallen",
    "sg:classifiers":[
        {
            "category":"Professional",
            "subcategory":"Business Services",
            "type":"Services"
        }
    ],
    "sg:phone":"+1 956 630 3284",
    "sg:postcode":"78501",
    "sg:province":"TX",
    "sg:tags":[
        "notary",
        "public"
    ],
    "wof:name":"Salinas, Jose Notary Public",
    "wof:placetype":"venue"
},
  "geometry": {"coordinates":[-98.23837,26.200804],"type":"Point"}
}