{
  "type": "Feature",
  "properties": {
    "iso:country":"US",
    "sg:address":"16801 Feather Craft Ln",
    "sg:city":"Houston",
    "sg:phone":"+1 281 486 2232",
    "sg:postcode":"77058",
    "sg:province":"TX",
    "sg:website":"http://www.fredechevrolet.com",
    "wof:name":"Norman Frede Chevrolet Co",
    "wof:placetype":"venue"
},
  "geometry": {"coordinates":[-95.12230700000001,29.550819],"type":"Point"}
}