{
  "type": "Feature",
  "properties": {
    "iso:country":"US",
    "sg:address":"1307 Petunia Ln",
    "sg:city":"Pflugerville",
    "sg:classifiers":[
        {
            "category":"Personal",
            "subcategory":"Barber",
            "type":"Services"
        }
    ],
    "sg:phone":"+1 512 989 1675",
    "sg:postcode":"78660",
    "sg:province":"TX",
    "sg:tags":[
        "shop"
    ],
    "wof:name":"Buckhorn Barber Shop",
    "wof:placetype":"venue"
},
  "geometry": {"coordinates":[-97.608711,30.436604],"type":"Point"}
}