{
  "type": "Feature",
  "properties": {
    "iso:country":"US",
    "sg:address":"1810 N Glenwood Blvd",
    "sg:city":"Tyler",
    "sg:classifiers":[
        {
            "category":"Manufacturing",
            "subcategory":"Printing",
            "type":"Manufacturing & Wholesale Goods"
        }
    ],
    "sg:phone":"+1 903 595 2141",
    "sg:postcode":"75702",
    "sg:province":"TX",
    "sg:tags":[
        "book"
    ],
    "wof:name":"Cartwrights Home Office",
    "wof:placetype":"venue"
},
  "geometry": {"coordinates":[-95.31904900000001,32.369115],"type":"Point"}
}