{
  "type": "Feature",
  "properties": {
    "iso:country":"US",
    "sg:address":"10515 Bellaire Blvd Ste H",
    "sg:city":"Houston",
    "sg:classifiers":[
        {
            "category":"Professional",
            "subcategory":"Lawyer & Legal Services",
            "type":"Services"
        }
    ],
    "sg:phone":"+1 713 524 1975",
    "sg:postcode":"77072",
    "sg:province":"TX",
    "wof:name":"Fenton Dal Atty",
    "wof:placetype":"venue"
},
  "geometry": {"coordinates":[-95.565697,29.704],"type":"Point"}
}