{
  "type": "Feature",
  "properties": {
    "iso:country":"US",
    "sg:address":"162 J L Dr",
    "sg:city":"Valley View",
    "sg:classifiers":[
        {
            "category":"Shopping",
            "subcategory":"Used Merchandise",
            "type":"Retail Goods"
        }
    ],
    "sg:phone":"+1 940 726 3322",
    "sg:postcode":"76272",
    "sg:province":"TX",
    "wof:name":"Kathy Mc Cormick",
    "wof:placetype":"venue"
},
  "geometry": {"coordinates":[-97.185334,33.436382],"type":"Point"}
}