{
  "type": "Feature",
  "properties": {
    "iso:country":"US",
    "sg:address":"9409 China Spring Rd",
    "sg:city":"Waco",
    "sg:classifiers":[
        {
            "category":"Retail",
            "subcategory":"Auto Rental",
            "type":"Services"
        }
    ],
    "sg:phone":"+1 254 752 6294",
    "sg:postcode":"76708",
    "sg:province":"TX",
    "sg:tags":[
        "trailer",
        "utility"
    ],
    "wof:name":"U-Haul",
    "wof:placetype":"venue"
},
  "geometry": {"coordinates":[-97.215954,31.623279],"type":"Point"}
}