{
  "type": "Feature",
  "properties": {
    "iso:country":"US",
    "sg:address":"208 Lampwick Cir",
    "sg:city":"College Station",
    "sg:classifiers":[
        {
            "category":"Real Estate",
            "subcategory":"Real Estate Agent",
            "type":"Services"
        }
    ],
    "sg:phone":"+1 979 846 2014",
    "sg:postcode":"77840",
    "sg:province":"TX",
    "wof:name":"Aim Properties",
    "wof:placetype":"venue"
},
  "geometry": {"coordinates":[-96.33171900000001,30.636325],"type":"Point"}
}