{
  "type": "Feature",
  "properties": {
    "iso:country":"US",
    "sg:address":"301 Brushy Creek Trl",
    "sg:city":"Coppell",
    "sg:classifiers":[
        {
            "category":"Professional",
            "type":"Services"
        }
    ],
    "sg:phone":"+1 972 679 9793",
    "sg:postcode":"75019",
    "sg:province":"TX",
    "wof:name":"Secola Inc",
    "wof:placetype":"venue"
},
  "geometry": {"coordinates":[-96.990425,32.977325],"type":"Point"}
}