{
  "type": "Feature",
  "properties": {
    "iso:country":"US",
    "sg:address":"6803 Cornelia Ln",
    "sg:city":"Dallas",
    "sg:classifiers":[
        {
            "category":"Real Estate",
            "subcategory":"Real Estate Agent",
            "type":"Services"
        }
    ],
    "sg:phone":"+1 214 823 5796",
    "sg:postcode":"75214",
    "sg:province":"TX",
    "wof:name":"Strattin Properties",
    "wof:placetype":"venue"
},
  "geometry": {"coordinates":[-96.74047,32.828316],"type":"Point"}
}