{
  "type": "Feature",
  "properties": {
    "iso:country":"US",
    "sg:address":"2200 E Park Row Dr",
    "sg:city":"Arlington",
    "sg:classifiers":[
        {
            "category":"Organizations",
            "subcategory":"Religious Organization",
            "type":"Services"
        }
    ],
    "sg:phone":"+1 817 274 8231",
    "sg:postcode":"76010",
    "sg:province":"TX",
    "wof:name":"Hillcrest Park Baptist Church",
    "wof:placetype":"venue"
},
  "geometry": {"coordinates":[-97.069311,32.720824],"type":"Point"}
}