{
  "type": "Feature",
  "properties": {
    "iso:country":"US",
    "sg:address":"6095 Glenmont Dr",
    "sg:city":"Houston",
    "sg:classifiers":[
        {
            "category":"Shopping",
            "subcategory":"Mobile Phones",
            "type":"Retail Goods"
        }
    ],
    "sg:phone":"+1 713 662 0304",
    "sg:postcode":"77081",
    "sg:province":"TX",
    "wof:name":"Priceless Cellular & Gift Store",
    "wof:placetype":"venue"
},
  "geometry": {"coordinates":[-95.488885,29.719865],"type":"Point"}
}