{
  "type": "Feature",
  "properties": {
    "iso:country":"US",
    "sg:address":"6201 Middle Fiskville Rd",
    "sg:city":"Austin",
    "sg:classifiers":[
        {
            "category":"Building & Trades",
            "subcategory":"Construction",
            "type":"Services"
        }
    ],
    "sg:phone":"+1 512 218 0601",
    "sg:postcode":"78752",
    "sg:province":"TX",
    "sg:tags":[
        "waterproofing",
        "contractor"
    ],
    "wof:name":"Citadel Restoration Svc",
    "wof:placetype":"venue"
},
  "geometry": {"coordinates":[-97.708422,30.326221],"type":"Point"}
}