{
  "type": "Feature",
  "properties": {
    "iso:country":"US",
    "sg:address":"4718 Robertson Rd",
    "sg:city":"Richmond",
    "sg:classifiers":[
        {
            "category":"Building & Trades",
            "subcategory":"Construction",
            "type":"Services"
        }
    ],
    "sg:phone":"+1 281 344 9822",
    "sg:postcode":"77469",
    "sg:province":"TX",
    "sg:tags":[
        "contractor"
    ],
    "wof:name":"Dew Contracting Co",
    "wof:placetype":"venue"
},
  "geometry": {"coordinates":[-95.787288,29.642602],"type":"Point"}
}