{
  "type": "Feature",
  "properties": {
    "iso:country":"US",
    "sg:address":"4716 Foster School Rd",
    "sg:city":"Needville",
    "sg:classifiers":[
        {
            "category":"Professional",
            "type":"Services"
        }
    ],
    "sg:phone":"+1 979 793 3768",
    "sg:postcode":"77461",
    "sg:province":"TX",
    "wof:name":"Robert E Kolkmeier",
    "wof:placetype":"venue"
},
  "geometry": {"coordinates":[-95.86107699999999,29.458442],"type":"Point"}
}