{
  "type": "Feature",
  "properties": {
    "iso:country":"US",
    "sg:address":"123 Caldwell St",
    "sg:city":"Baytown",
    "sg:classifiers":[
        {
            "category":"Professional",
            "subcategory":"Business Services",
            "type":"Services"
        }
    ],
    "sg:phone":"+1 281 424 7290",
    "sg:postcode":"77520",
    "sg:province":"TX",
    "wof:name":"Smalling Enterprise",
    "wof:placetype":"venue"
},
  "geometry": {"coordinates":[-95.03770799999999,29.777492],"type":"Point"}
}