{
  "type": "Feature",
  "properties": {
    "iso:country":"US",
    "sg:address":"2609 Eastland Ave",
    "sg:city":"Greenville",
    "sg:classifiers":[
        {
            "category":"Banks & Credit Unions",
            "subcategory":"Investment Brokerage",
            "type":"Services"
        }
    ],
    "sg:phone":"+1 903 455 8686",
    "sg:postcode":"75402",
    "sg:province":"TX",
    "wof:name":"Linsco Private Ledger",
    "wof:placetype":"venue"
},
  "geometry": {"coordinates":[-96.109467,33.111216],"type":"Point"}
}