{
  "type": "Feature",
  "properties": {
    "iso:country":"US",
    "sg:address":"4751 State Hwy 6",
    "sg:city":"Missouri City",
    "sg:classifiers":[
        {
            "category":"Restaurant",
            "type":"Food & Drink"
        }
    ],
    "sg:phone":"+1 281 499 2386",
    "sg:postcode":"77459",
    "sg:province":"TX",
    "sg:tags":[
        "eating"
    ],
    "wof:name":"Kenshin Sushi",
    "wof:placetype":"venue"
},
  "geometry": {"coordinates":[-95.58031200000001,29.578865],"type":"Point"}
}