{
  "type": "Feature",
  "properties": {
    "iso:country":"US",
    "sg:address":"6010 75th Pl",
    "sg:city":"Lubbock",
    "sg:classifiers":[
        {
            "category":"Structure",
            "subcategory":"Office Building",
            "type":"Public Place"
        }
    ],
    "sg:phone":"+1 806 745 6412",
    "sg:postcode":"79424",
    "sg:province":"TX",
    "sg:tags":[
        "park"
    ],
    "wof:name":"Siwel Properties",
    "wof:placetype":"venue"
},
  "geometry": {"coordinates":[-101.94715600000001,33.524329],"type":"Point"}
}