{
  "type": "Feature",
  "properties": {
    "iso:country":"US",
    "sg:address":"506 Forrest Dr",
    "sg:city":"Dumas",
    "sg:classifiers":[
        {
            "category":"Professional",
            "subcategory":"Business Services",
            "type":"Services"
        }
    ],
    "sg:phone":"+1 806 935 6721",
    "sg:postcode":"79029",
    "sg:province":"TX",
    "sg:tags":[
        "holding"
    ],
    "wof:name":"Ub Holdings",
    "wof:placetype":"venue"
},
  "geometry": {"coordinates":[-101.95632999999999,35.874117],"type":"Point"}
}