{
  "type": "Feature",
  "properties": {
    "iso:country":"US",
    "sg:address":"875 Wildwood Ln",
    "sg:city":"Southlake",
    "sg:classifiers":[
        {
            "category":"Restaurant",
            "type":"Food & Drink"
        }
    ],
    "sg:phone":"+1 817 488 1555",
    "sg:postcode":"76092",
    "sg:province":"TX",
    "wof:name":"DJR Restaurants",
    "wof:placetype":"venue"
},
  "geometry": {"coordinates":[-97.13797700000001,32.950935],"type":"Point"}
}