{
  "type": "Feature",
  "properties": {
    "iso:country":"US",
    "sg:address":"406 40th St",
    "sg:city":"Lubbock",
    "sg:classifiers":[
        {
            "category":"Shopping",
            "subcategory":"Gifts & Souvenirs",
            "type":"Retail Goods"
        }
    ],
    "sg:phone":"+1 806 740 0876",
    "sg:postcode":"79404",
    "sg:province":"TX",
    "wof:name":"Carrie McDonald",
    "wof:placetype":"venue"
},
  "geometry": {"coordinates":[-101.83891199999999,33.5579],"type":"Point"}
}