{
  "type": "Feature",
  "properties": {
    "iso:country":"US",
    "sg:address":"117 Early Blvd",
    "sg:city":"Brownwood",
    "sg:classifiers":[
        {
            "category":"Personal",
            "subcategory":"Tanning Parlor",
            "type":"Services"
        }
    ],
    "sg:phone":"+1 325 643 5301",
    "sg:postcode":"76802",
    "sg:province":"TX",
    "sg:tags":[
        "salon"
    ],
    "wof:name":"Sun Kissed Tan",
    "wof:placetype":"venue"
},
  "geometry": {"coordinates":[-98.970555,31.732303],"type":"Point"}
}