{
  "type": "Feature",
  "properties": {
    "iso:country":"US",
    "sg:address":"4544 Post Oak Place Dr # 204",
    "sg:city":"Houston",
    "sg:classifiers":[
        {
            "category":"Social Services",
            "type":"Services"
        },
        {
            "category":"Personal",
            "type":"Services"
        }
    ],
    "sg:phone":"+1 713 621 7001",
    "sg:postcode":"77027",
    "sg:province":"TX",
    "sg:tags":[
        "family",
        "counselors-licensed",
        "individual",
        "marriage",
        "child",
        "professional",
        "counselor"
    ],
    "wof:name":"Kathleen A Senior Phd",
    "wof:placetype":"venue"
},
  "geometry": {"coordinates":[-95.451064,29.750267],"type":"Point"}
}