{
  "type": "Feature",
  "properties": {
    "iso:country":"US",
    "sg:address":"2437 Abrameit Rd",
    "sg:city":"Goliad",
    "sg:classifiers":[
        {
            "category":"Farming",
            "subcategory":"Livestock Farm",
            "type":"Manufacturing & Wholesale Goods"
        },
        {
            "category":"Farming",
            "subcategory":"Farm & Veterinary Services",
            "type":"Manufacturing & Wholesale Goods"
        }
    ],
    "sg:phone":"+1 361 645 8022",
    "sg:postcode":"77963",
    "sg:province":"TX",
    "sg:tags":[
        "breeder"
    ],
    "wof:name":"Leroy Schneider",
    "wof:placetype":"venue"
},
  "geometry": {"coordinates":[-97.22887900000001,28.773334],"type":"Point"}
}