{
  "type": "Feature",
  "properties": {
    "iso:country":"US",
    "sg:address":"2016 Main St",
    "sg:city":"Houston",
    "sg:classifiers":[
        {
            "category":"Arts & Performance",
            "subcategory":"Music",
            "type":"Entertainment"
        },
        {
            "category":"Bars & Pubs",
            "subcategory":"Gay Bar",
            "type":"Food & Drink"
        },
        {
            "category":"Recreation",
            "subcategory":"Dance Hall",
            "type":"Entertainment"
        }
    ],
    "sg:phone":"+1 713 751 3101",
    "sg:postcode":"77002",
    "sg:province":"TX",
    "sg:tags":[
        "club",
        "venue"
    ],
    "sg:website":"leavetheboyfriendathome.com/",
    "wof:name":"Mainstage",
    "wof:placetype":"venue"
},
  "geometry": {"coordinates":[-95.37181099999999,29.749105],"type":"Point"}
}