{
  "type": "Feature",
  "properties": {
    "iso:country":"US",
    "sg:address":"1639 Dawson St",
    "sg:city":"San Antonio",
    "sg:classifiers":[
        {
            "category":"Organizations",
            "subcategory":"Religious Organization",
            "type":"Services"
        }
    ],
    "sg:phone":"+1 210 226 4075",
    "sg:postcode":"78202",
    "sg:province":"TX",
    "sg:tags":[
        "church"
    ],
    "wof:name":"Isrealite Baptist Church",
    "wof:placetype":"venue"
},
  "geometry": {"coordinates":[-98.45823,29.42643],"type":"Point"}
}