{
  "type": "Feature",
  "properties": {
    "iso:country":"US",
    "sg:address":"201 S 28th St",
    "sg:city":"Killeen",
    "sg:classifiers":[
        {
            "category":"Government",
            "subcategory":"Fire Station",
            "type":"Public Place"
        }
    ],
    "sg:phone":"+1 254 501 7676",
    "sg:postcode":"76541",
    "sg:province":"TX",
    "sg:tags":[
        "protection"
    ],
    "wof:name":"Fire Department",
    "wof:placetype":"venue"
},
  "geometry": {"coordinates":[-97.718602,31.112519],"type":"Point"}
}