{
  "type": "Feature",
  "properties": {
    "iso:country":"US",
    "sg:address":"193 W San Antonio St",
    "sg:city":"New Braunfels",
    "sg:classifiers":[
        {
            "category":"Health Services",
            "subcategory":"Nursing And Care Facility",
            "type":"Services"
        }
    ],
    "sg:phone":"+1 830 624 1044",
    "sg:postcode":"78130",
    "sg:province":"TX",
    "sg:tags":[
        "living",
        "assisted"
    ],
    "wof:name":"Alzcare LLC",
    "wof:placetype":"venue"
},
  "geometry": {"coordinates":[-98.124194,29.703468],"type":"Point"}
}