{
  "type": "Feature",
  "properties": {
    "iso:country":"US",
    "sg:address":"10111 Emerald Oaks Dr",
    "sg:city":"Houston",
    "sg:classifiers":[
        {
            "category":"Building & Trades",
            "subcategory":"Construction",
            "type":"Services"
        }
    ],
    "sg:phone":"+1 832 607 1500",
    "sg:postcode":"77070",
    "sg:province":"TX",
    "sg:tags":[
        "house"
    ],
    "wof:name":"Conejo Contruction",
    "wof:placetype":"venue"
},
  "geometry": {"coordinates":[-95.571838,29.944757],"type":"Point"}
}