{
  "type": "Feature",
  "properties": {
    "iso:country":"US",
    "sg:address":"6911 Frankford Rd",
    "sg:city":"Dallas",
    "sg:classifiers":[
        {
            "category":"Food & Beverages",
            "subcategory":"Bakery",
            "type":"Retail Goods"
        }
    ],
    "sg:phone":"+1 972 964 3451",
    "sg:postcode":"75252",
    "sg:province":"TX",
    "sg:tags":[
        "bagel"
    ],
    "wof:name":"Bennys Bagels",
    "wof:placetype":"venue"
},
  "geometry": {"coordinates":[-96.783153,32.997873],"type":"Point"}
}