{
  "type": "Feature",
  "properties": {
    "iso:country":"US",
    "sg:address":"12801 N Central Expy",
    "sg:city":"Dallas",
    "sg:classifiers":[
        {
            "category":"Insurance",
            "subcategory":"Insurance Agent",
            "type":"Services"
        }
    ],
    "sg:phone":"+1 972 458 1701",
    "sg:postcode":"75243",
    "sg:province":"TX",
    "sg:tags":[
        "claim",
        "account",
        "management",
        "electronic",
        "processing"
    ],
    "wof:name":"American Medical Finance Inc",
    "wof:placetype":"venue"
},
  "geometry": {"coordinates":[-96.76426499999999,32.923718],"type":"Point"}
}