{
  "type": "Feature",
  "properties": {
    "iso:country":"US",
    "sg:address":"4922 Locust St",
    "sg:city":"Bellaire",
    "sg:classifiers":[
        {
            "category":"Personal",
            "subcategory":"Beauty Salon",
            "type":"Services"
        }
    ],
    "sg:phone":"+1 713 838 1999",
    "sg:postcode":"77401",
    "sg:province":"TX",
    "wof:name":"Kitsa's Hair Studio",
    "wof:placetype":"venue"
},
  "geometry": {"coordinates":[-95.466594,29.708911],"type":"Point"}
}