{
  "type": "Feature",
  "properties": {
    "iso:country":"US",
    "sg:address":"3610 Hirschfield Rd",
    "sg:city":"Spring",
    "sg:classifiers":[
        {
            "category":"Food & Beverages",
            "subcategory":"Specialty",
            "type":"Retail Goods"
        }
    ],
    "sg:phone":"+1 281 353 8965",
    "sg:postcode":"77373",
    "sg:province":"TX",
    "wof:name":"Watkins Products Distributor",
    "wof:placetype":"venue"
},
  "geometry": {"coordinates":[-95.377568,30.044861],"type":"Point"}
}