{
  "type": "Feature",
  "properties": {
    "iso:country":"US",
    "sg:address":"3631 Maplewood Ave",
    "sg:city":"Wichita Falls",
    "sg:classifiers":[
        {
            "category":"Health Services",
            "subcategory":"Optometrist",
            "type":"Services"
        }
    ],
    "sg:phone":"+1 940 696 0296",
    "sg:postcode":"76308",
    "sg:province":"TX",
    "wof:name":"Maplewood Eye Care Ctr",
    "wof:placetype":"venue"
},
  "geometry": {"coordinates":[-98.52861300000001,33.871051],"type":"Point"}
}