{
  "type": "Feature",
  "properties": {
    "iso:country":"US",
    "sg:address":"1438 W Water St",
    "sg:city":"Weatherford",
    "sg:classifiers":[
        {
            "category":"Health Services",
            "subcategory":"Chiropractor",
            "type":"Services"
        }
    ],
    "sg:phone":"+1 817 596 0002",
    "sg:postcode":"76086",
    "sg:province":"TX",
    "wof:name":"Burrows Chiropractic Clinic",
    "wof:placetype":"venue"
},
  "geometry": {"coordinates":[-97.82123900000001,32.763482],"type":"Point"}
}