{
  "type": "Feature",
  "properties": {
    "iso:country":"US",
    "sg:address":"20619 Aldine Westfield Rd",
    "sg:city":"Humble",
    "sg:classifiers":[
        {
            "category":"Personal",
            "subcategory":"Beauty Salon",
            "type":"Services"
        }
    ],
    "sg:phone":"+1 281 443 1373",
    "sg:postcode":"77338",
    "sg:province":"TX",
    "sg:tags":[
        "shop"
    ],
    "wof:name":"D & M Beauty Salon",
    "wof:placetype":"venue"
},
  "geometry": {"coordinates":[-95.377154,30.0146],"type":"Point"}
}