{
  "type": "Feature",
  "properties": {
    "iso:country":"US",
    "sg:address":"403 S Elm St",
    "sg:city":"Brady",
    "sg:classifiers":[
        {
            "category":"Restaurant",
            "type":"Food & Drink"
        }
    ],
    "sg:phone":"+1 325 597 5050",
    "sg:postcode":"76825",
    "sg:province":"TX",
    "sg:tags":[
        "eating"
    ],
    "sg:website":"http://www.texmexrestaurant.com",
    "wof:name":"Tex Mex Restaurant",
    "wof:placetype":"venue"
},
  "geometry": {"coordinates":[-99.333229,31.132236],"type":"Point"}
}