{
  "type": "Feature",
  "properties": {
    "iso:country":"US",
    "sg:address":"2502 Rich Oak Dr",
    "sg:city":"Garland",
    "sg:classifiers":[
        {
            "category":"Professional",
            "subcategory":"Management & Consulting",
            "type":"Services"
        }
    ],
    "sg:phone":"+1 972 898 5100",
    "sg:postcode":"75044",
    "sg:province":"TX",
    "sg:tags":[
        "business"
    ],
    "wof:name":"Team Telesoft Inc",
    "wof:placetype":"venue"
},
  "geometry": {"coordinates":[-96.665282,32.936141],"type":"Point"}
}