{
  "type": "Feature",
  "properties": {
    "iso:country":"US",
    "sg:address":"706 Sharon Dr",
    "sg:city":"Corpus Christi",
    "sg:classifiers":[
        {
            "category":"Retail",
            "subcategory":"Auto Repair",
            "type":"Services"
        }
    ],
    "sg:phone":"+1 361 980 8338",
    "sg:postcode":"78412",
    "sg:province":"TX",
    "sg:tags":[
        "body",
        "glass",
        "replacement"
    ],
    "wof:name":"First Class Glass",
    "wof:placetype":"venue"
},
  "geometry": {"coordinates":[-97.372789,27.721745],"type":"Point"}
}