{
  "type": "Feature",
  "properties": {
    "iso:country":"US",
    "sg:address":"300 S C M Allen Pkwy",
    "sg:city":"San Marcos",
    "sg:classifiers":[
        {
            "category":"Organizations",
            "subcategory":"Non-profit Organization",
            "type":"Services"
        }
    ],
    "sg:phone":"+1 512 878 1961",
    "sg:postcode":"78666",
    "sg:province":"TX",
    "wof:name":"Tx Hima",
    "wof:placetype":"venue"
},
  "geometry": {"coordinates":[-97.93521800000001,29.877159],"type":"Point"}
}