{
  "type": "Feature",
  "properties": {
    "iso:country":"US",
    "sg:address":"4506 Highway 6",
    "sg:city":"Sugar Land",
    "sg:classifiers":[
        {
            "category":"Restaurant",
            "type":"Food & Drink"
        }
    ],
    "sg:menulink":"http://www.allmenus.com/tx/sugar-land/73351-doubledaves-pizza-works/menu/",
    "sg:phone":"+1 281 980 3283",
    "sg:postcode":"77478",
    "sg:province":"TX",
    "sg:tags":[
        "american",
        "pizza"
    ],
    "wof:name":"DoubleDave's Pizza Works",
    "wof:placetype":"venue"
},
  "geometry": {"coordinates":[-95.58575500000001,29.582423],"type":"Point"}
}