{
  "type": "Feature",
  "properties": {
    "iso:country":"US",
    "sg:address":"1201 Barbara Jordan Blvd",
    "sg:city":"Austin",
    "sg:classifiers":[
        {
            "category":"Health Services",
            "subcategory":"Dentist",
            "type":"Services"
        }
    ],
    "sg:phone":"+1 512 474 7575",
    "sg:postcode":"78723",
    "sg:province":"TX",
    "sg:tags":[
        "pediatric"
    ],
    "wof:name":"Central Texas Pediatric Dentistry",
    "wof:placetype":"venue"
},
  "geometry": {"coordinates":[-97.71104800000001,30.307277],"type":"Point"}
}