{
  "type": "Feature",
  "properties": {
    "iso:country":"US",
    "sg:address":"717 Barren Springs Dr",
    "sg:city":"Houston",
    "sg:classifiers":[
        {
            "category":"Retail",
            "subcategory":"Car Wash",
            "type":"Services"
        }
    ],
    "sg:phone":"+1 281 873 8973",
    "sg:postcode":"77090",
    "sg:province":"TX",
    "sg:tags":[
        "polishing",
        "washing"
    ],
    "wof:name":"George Car Wash",
    "wof:placetype":"venue"
},
  "geometry": {"coordinates":[-95.434234,29.989748],"type":"Point"}
}