{
  "type": "Feature",
  "properties": {
    "iso:country":"US",
    "sg:address":"1813 E Main St",
    "sg:city":"League City",
    "sg:classifiers":[
        {
            "category":"Food & Beverages",
            "subcategory":"Groceries & Convenience Stores",
            "type":"Retail Goods"
        }
    ],
    "sg:phone":"+1 281 316 9755",
    "sg:postcode":"77573",
    "sg:province":"TX",
    "wof:name":"Little Chief Minute Market",
    "wof:placetype":"venue"
},
  "geometry": {"coordinates":[-95.0788,29.520051],"type":"Point"}
}