{
  "type": "Feature",
  "properties": {
    "iso:country":"US",
    "sg:address":"5007 Fulton St",
    "sg:city":"Houston",
    "sg:classifiers":[
        {
            "category":"Autos & Motor Vehicles",
            "subcategory":"Auto Supplies",
            "type":"Retail Goods"
        }
    ],
    "sg:phone":"+1 281 888 7891",
    "sg:postcode":"77009",
    "sg:province":"TX",
    "sg:tags":[
        "tire"
    ],
    "wof:name":"One Stop Tire And Rims",
    "wof:placetype":"venue"
},
  "geometry": {"coordinates":[-95.369004,29.80544],"type":"Point"}
}