{
  "type": "Feature",
  "properties": {
    "iso:country":"US",
    "sg:address":"15230 Chaseridge Dr",
    "sg:city":"Missouri City",
    "sg:classifiers":[
        {
            "category":"Professional",
            "subcategory":"Management & Consulting",
            "type":"Services"
        }
    ],
    "sg:phone":"+1 281 438 9504",
    "sg:postcode":"77489",
    "sg:province":"TX",
    "sg:tags":[
        "consultant",
        "resource",
        "human"
    ],
    "wof:name":"H R Techniques",
    "wof:placetype":"venue"
},
  "geometry": {"coordinates":[-95.504136,29.604928],"type":"Point"}
}