{
  "type": "Feature",
  "properties": {
    "iso:country":"US",
    "sg:address":"238 W Rowson St",
    "sg:city":"San Benito",
    "sg:classifiers":[
        {
            "category":"Home & Garden",
            "subcategory":"Building Materials",
            "type":"Retail Goods"
        },
        {
            "category":"Building & Trades",
            "subcategory":"Construction",
            "type":"Services"
        }
    ],
    "sg:phone":"+1 956 399 2421",
    "sg:postcode":"78586",
    "sg:province":"TX",
    "sg:tags":[
        "house",
        "lumber",
        "ma"
    ],
    "wof:name":"Montalvo's Lumber Co",
    "wof:placetype":"venue"
},
  "geometry": {"coordinates":[-97.633349,26.132888],"type":"Point"}
}