{
  "type": "Feature",
  "properties": {
    "iso:country":"US",
    "sg:address":"12175 Network Blvd",
    "sg:city":"San Antonio",
    "sg:classifiers":[
        {
            "category":"Organizations",
            "subcategory":"Religious Organization",
            "type":"Services"
        }
    ],
    "sg:phone":"+1 210 561 9673",
    "sg:postcode":"78249",
    "sg:province":"TX",
    "wof:name":"Upwords Ministries",
    "wof:placetype":"venue"
},
  "geometry": {"coordinates":[-98.58914799999999,29.548833],"type":"Point"}
}