{
  "type": "Feature",
  "properties": {
    "iso:country":"US",
    "sg:address":"9364 Forest Hills Blvd",
    "sg:city":"Dallas",
    "sg:classifiers":[
        {
            "category":"Professional",
            "type":"Services"
        }
    ],
    "sg:phone":"+1 214 328 5802",
    "sg:postcode":"75218",
    "sg:province":"TX",
    "wof:name":"Oceans & Earth Research F",
    "wof:placetype":"venue"
},
  "geometry": {"coordinates":[-96.701966,32.830679],"type":"Point"}
}