{
  "type": "Feature",
  "properties": {
    "iso:country":"US",
    "sg:address":"6807 One Oak Rd",
    "sg:city":"Austin",
    "sg:classifiers":[
        {
            "category":"Professional",
            "subcategory":"Engineering",
            "type":"Services"
        }
    ],
    "sg:phone":"+1 512 892 1035",
    "sg:postcode":"78749",
    "sg:province":"TX",
    "wof:name":"Welsch Engineering Inc",
    "wof:placetype":"venue"
},
  "geometry": {"coordinates":[-97.84555899999999,30.222941],"type":"Point"}
}