{
  "type": "Feature",
  "properties": {
    "iso:country":"US",
    "sg:address":"1088 McCaleb Rd",
    "sg:city":"Montgomery",
    "sg:classifiers":[
        {
            "category":"Retail",
            "subcategory":"Auto Repair",
            "type":"Services"
        }
    ],
    "sg:phone":"+1 936 588 4255",
    "sg:postcode":"77316",
    "sg:province":"TX",
    "sg:tags":[
        "general"
    ],
    "wof:name":"Montgomery County Truck Svc",
    "wof:placetype":"venue"
},
  "geometry": {"coordinates":[-95.583361,30.348051],"type":"Point"}
}