{
  "type": "Feature",
  "properties": {
    "iso:country":"US",
    "sg:address":"1202 Hidden Ridge",
    "sg:city":"Irving",
    "sg:classifiers":[
        {
            "category":"Shopping",
            "subcategory":"Gifts & Souvenirs",
            "type":"Retail Goods"
        }
    ],
    "sg:phone":"+1 972 507 3840",
    "sg:postcode":"75038",
    "sg:province":"TX",
    "wof:name":"Trust Cards",
    "wof:placetype":"venue"
},
  "geometry": {"coordinates":[-96.96844400000001,32.879209],"type":"Point"}
}