{
  "type": "Feature",
  "properties": {
    "iso:country":"US",
    "sg:address":"1123 W Davis St",
    "sg:city":"Dallas",
    "sg:classifiers":[
        {
            "category":"Restaurant",
            "type":"Food & Drink"
        }
    ],
    "sg:phone":"+1 214 946 4711",
    "sg:postcode":"75208",
    "sg:province":"TX",
    "sg:tags":[
        "southern",
        "eating"
    ],
    "sg:website":"www.normascafe.com",
    "wof:name":"Norma's Cafe",
    "wof:placetype":"venue"
},
  "geometry": {"coordinates":[-96.841194,32.749718],"type":"Point"}
}