{
  "type": "Feature",
  "properties": {
    "iso:country":"US",
    "sg:address":"1302 Temple Sq",
    "sg:city":"San Antonio",
    "sg:classifiers":[
        {
            "category":"Building & Trades",
            "subcategory":"Construction",
            "type":"Services"
        }
    ],
    "sg:phone":"+1 210 670 8286",
    "sg:postcode":"78245",
    "sg:province":"TX",
    "sg:tags":[
        "carpentry",
        "contractor"
    ],
    "wof:name":"Denmeli Cabinet Shop",
    "wof:placetype":"venue"
},
  "geometry": {"coordinates":[-98.680029,29.42354],"type":"Point"}
}