{
  "type": "Feature",
  "properties": {
    "iso:country":"US",
    "sg:address":"13350 Floyd Cir",
    "sg:city":"Dallas",
    "sg:classifiers":[
        {
            "category":"Health Services",
            "subcategory":"Doctor",
            "type":"Services"
        }
    ],
    "sg:phone":"+1 972 671 9504",
    "sg:postcode":"75243",
    "sg:province":"TX",
    "sg:tags":[
        "clinic"
    ],
    "wof:name":"Baylor Occupation & Family",
    "wof:placetype":"venue"
},
  "geometry": {"coordinates":[-96.748046,32.93093],"type":"Point"}
}