{
  "type": "Feature",
  "properties": {
    "iso:country":"US",
    "sg:address":"3020 Legacy Dr",
    "sg:city":"Plano",
    "sg:classifiers":[
        {
            "category":"Freight",
            "type":"Transportation"
        }
    ],
    "sg:phone":"+1 972 489 1337",
    "sg:postcode":"75023",
    "sg:province":"TX",
    "sg:tags":[
        "sea",
        "foreign"
    ],
    "wof:name":"Pacific Links International",
    "wof:placetype":"venue"
},
  "geometry": {"coordinates":[-96.75106100000001,33.07168],"type":"Point"}
}