{
  "type": "Feature",
  "properties": {
    "iso:country":"US",
    "sg:address":"4109 Logan St",
    "sg:city":"Irving",
    "sg:classifiers":[
        {
            "category":"Freight",
            "type":"Transportation"
        }
    ],
    "sg:phone":"+1 972 570 5913",
    "sg:postcode":"75062",
    "sg:province":"TX",
    "wof:name":"Fitts Transportation",
    "wof:placetype":"venue"
},
  "geometry": {"coordinates":[-97.007328,32.853655],"type":"Point"}
}