{
  "type": "Feature",
  "properties": {
    "iso:country":"US",
    "sg:address":"610 Mission Trl",
    "sg:city":"Wimberley",
    "sg:classifiers":[
        {
            "category":"Building & Trades",
            "subcategory":"Construction",
            "type":"Services"
        }
    ],
    "sg:phone":"+1 512 847 8325",
    "sg:postcode":"78676",
    "sg:province":"TX",
    "sg:tags":[
        "residential",
        "contractor",
        "general"
    ],
    "sg:website":"www.strobelconstruction.com",
    "wof:name":"Strobel Construction Inc",
    "wof:placetype":"venue"
},
  "geometry": {"coordinates":[-98.065442,29.954815],"type":"Point"}
}