{
  "type": "Feature",
  "properties": {
    "iso:country":"US",
    "sg:address":"6532 Lyndon B Johnson Fwy Ste 100 - 102",
    "sg:city":"Dallas",
    "sg:classifiers":[
        {
            "category":"Personal",
            "subcategory":"Beauty Salon",
            "type":"Services"
        },
        {
            "category":"Personal",
            "subcategory":"Hair Removal",
            "type":"Services"
        }
    ],
    "sg:phone":"+1 214 529 3538",
    "sg:postcode":"75240",
    "sg:province":"TX",
    "sg:tags":[
        "cosmetologist",
        "weaving",
        "stylist"
    ],
    "sg:website":"http://www.ahseeksalondallas.com",
    "wof:name":"Ahseek Salon",
    "wof:placetype":"venue"
},
  "geometry": {"coordinates":[-96.793424,32.924492],"type":"Point"}
}