{
  "type": "Feature",
  "properties": {
    "iso:country":"US",
    "sg:address":"23623 Colonial Pkwy",
    "sg:city":"Katy",
    "sg:classifiers":[
        {
            "category":"Freight",
            "type":"Transportation"
        }
    ],
    "sg:phone":"+1 281 347 5700",
    "sg:postcode":"77493",
    "sg:province":"TX",
    "sg:tags":[
        "distribution",
        "center"
    ],
    "wof:name":"Albertsons Dist Ctr 8295",
    "wof:placetype":"venue"
},
  "geometry": {"coordinates":[-95.777519,29.793918],"type":"Point"}
}