{
  "type": "Feature",
  "properties": {
    "iso:country":"US",
    "sg:address":"10102 Morgan Meadow Ln",
    "sg:city":"Dallas",
    "sg:classifiers":[
        {
            "category":"Manufacturing",
            "subcategory":"Printing",
            "type":"Manufacturing & Wholesale Goods"
        }
    ],
    "sg:phone":"+1 972 699 0815",
    "sg:postcode":"75243",
    "sg:province":"TX",
    "sg:tags":[
        "book"
    ],
    "wof:name":"Morgan Meadow Enterprises",
    "wof:placetype":"venue"
},
  "geometry": {"coordinates":[-96.70907,32.921293],"type":"Point"}
}