{
  "type": "Feature",
  "properties": {
    "iso:country":"US",
    "sg:address":"2901 Linda Dr",
    "sg:city":"Pearland",
    "sg:classifiers":[
        {
            "category":"Professional",
            "subcategory":"Computer Services",
            "type":"Services"
        }
    ],
    "sg:phone":"+1 281 485 0410",
    "sg:postcode":"77584",
    "sg:province":"TX",
    "sg:tags":[
        "design",
        "system"
    ],
    "wof:name":"Technology Dynamics",
    "wof:placetype":"venue"
},
  "geometry": {"coordinates":[-95.29644500000001,29.552967],"type":"Point"}
}