{
  "type": "Feature",
  "properties": {
    "iso:country":"US",
    "sg:address":"102 Williams St",
    "sg:city":"Copperas Cove",
    "sg:classifiers":[
        {
            "category":"Freight",
            "type":"Transportation"
        }
    ],
    "sg:phone":"+1 254 547 7504",
    "sg:postcode":"76522",
    "sg:province":"TX",
    "sg:tags":[
        "operator",
        "local",
        "trucking"
    ],
    "wof:name":"John P Jones Trucking LLC",
    "wof:placetype":"venue"
},
  "geometry": {"coordinates":[-97.879755,31.119373],"type":"Point"}
}