{
  "type": "Feature",
  "properties": {
    "iso:country":"US",
    "sg:address":"117 7th St",
    "sg:city":"Rosenberg",
    "sg:classifiers":[
        {
            "category":"Professional",
            "subcategory":"Employment Agencies",
            "type":"Services"
        }
    ],
    "sg:phone":"+1 281 344 0279",
    "sg:postcode":"77471",
    "sg:province":"TX",
    "wof:name":"Workforce Commission",
    "wof:placetype":"venue"
},
  "geometry": {"coordinates":[-95.80254499999999,29.567158],"type":"Point"}
}