{
  "type": "Feature",
  "properties": {
    "iso:country":"US",
    "sg:address":"423 S Main St",
    "sg:city":"Mc Gregor",
    "sg:classifiers":[
        {
            "category":"Real Estate",
            "subcategory":"Real Estate Agent",
            "type":"Services"
        }
    ],
    "sg:phone":"+1 254 840 2824",
    "sg:postcode":"76657",
    "sg:province":"TX",
    "sg:website":"www.psrealtors.com",
    "wof:name":"Paschall Skipper & Assoc",
    "wof:placetype":"venue"
},
  "geometry": {"coordinates":[-97.405627,31.438457],"type":"Point"}
}