{
  "type": "Feature",
  "properties": {
    "iso:country":"US",
    "sg:address":"900 S Palestine St",
    "sg:city":"Athens",
    "sg:classifiers":[
        {
            "category":"Taxi",
            "type":"Transportation"
        }
    ],
    "sg:phone":"+1 903 675 4016",
    "sg:postcode":"75751",
    "sg:province":"TX",
    "wof:name":"Roc Yel Inc",
    "wof:placetype":"venue"
},
  "geometry": {"coordinates":[-95.85140199999999,32.188053],"type":"Point"}
}