{
  "type": "Feature",
  "properties": {
    "iso:country":"US",
    "sg:address":"402 Tradesmens Park Dr",
    "sg:city":"Hutto",
    "sg:classifiers":[
        {
            "category":"Manufacturing",
            "subcategory":"Electronics",
            "type":"Manufacturing & Wholesale Goods"
        }
    ],
    "sg:phone":"+1 512 759 2009",
    "sg:postcode":"78634",
    "sg:province":"TX",
    "sg:tags":[
        "repair",
        "devices",
        "mfg"
    ],
    "wof:name":"E P T",
    "wof:placetype":"venue"
},
  "geometry": {"coordinates":[-97.59272199999999,30.541643],"type":"Point"}
}