{
  "type": "Feature",
  "properties": {
    "iso:country":"US",
    "sg:address":"1430 S Main St",
    "sg:city":"Lindale",
    "sg:classifiers":[
        {
            "category":"Wholesale",
            "subcategory":"Electrical",
            "type":"Manufacturing & Wholesale Goods"
        }
    ],
    "sg:phone":"+1 903 881 9227",
    "sg:postcode":"75771",
    "sg:province":"TX",
    "sg:tags":[
        "equipment"
    ],
    "wof:name":"Edison Security",
    "wof:placetype":"venue"
},
  "geometry": {"coordinates":[-95.40611199999999,32.50127],"type":"Point"}
}