{
  "type": "Feature",
  "properties": {
    "iso:country":"US",
    "sg:address":"301 N Thompson St",
    "sg:city":"Conroe",
    "sg:classifiers":[
        {
            "category":"Government",
            "subcategory":"Office",
            "type":"Public Place"
        }
    ],
    "sg:phone":"+1 936 539 7828",
    "sg:postcode":"77301",
    "sg:province":"TX",
    "sg:tags":[
        "executive"
    ],
    "wof:name":"Montgomery Cnty Dst Attys Off",
    "wof:placetype":"venue"
},
  "geometry": {"coordinates":[-95.458119,30.312174],"type":"Point"}
}