{
  "type": "Feature",
  "properties": {
    "iso:country":"US",
    "sg:address":"7212 Red Hawk Ct",
    "sg:city":"Fort Worth",
    "sg:classifiers":[
        {
            "category":"Health Services",
            "subcategory":"Doctor",
            "type":"Services"
        }
    ],
    "sg:phone":"+1 817 294 9200",
    "sg:postcode":"76132",
    "sg:province":"TX",
    "sg:tags":[
        "dentist"
    ],
    "wof:name":"City View Orthodontics",
    "wof:placetype":"venue"
},
  "geometry": {"coordinates":[-97.419713,32.653511],"type":"Point"}
}