{
  "type": "Feature",
  "properties": {
    "iso:country":"US",
    "sg:address":"4053 Desert Mountain Dr",
    "sg:city":"Plano",
    "sg:classifiers":[
        {
            "category":"Building & Trades",
            "subcategory":"Construction",
            "type":"Services"
        }
    ],
    "sg:phone":"+1 972 985 8336",
    "sg:postcode":"75093",
    "sg:province":"TX",
    "sg:tags":[
        "contractor"
    ],
    "wof:name":"J Ruan Company",
    "wof:placetype":"venue"
},
  "geometry": {"coordinates":[-96.792146,33.052802],"type":"Point"}
}