{
  "type": "Feature",
  "properties": {
    "iso:country":"US",
    "sg:address":"5250 Gulfton Ste 4-G",
    "sg:city":"Houston",
    "sg:classifiers":[
        {
            "category":"Coffee & Tea",
            "type":"Food & Drink"
        }
    ],
    "sg:phone":"+1 713 523 5282",
    "sg:postcode":"77081",
    "sg:province":"TX",
    "sg:website":"www.javapura.com",
    "wof:name":"Java Pura Coffee Roasters",
    "wof:placetype":"venue"
},
  "geometry": {"coordinates":[-95.471602,29.716878],"type":"Point"}
}