{
  "type": "Feature",
  "properties": {
    "iso:country":"US",
    "sg:address":"3016 Whitehall Ln",
    "sg:city":"Wichita Falls",
    "sg:classifiers":[
        {
            "category":"Building & Trades",
            "subcategory":"Plumbing",
            "type":"Services"
        }
    ],
    "sg:phone":"+1 940 691 2285",
    "sg:postcode":"76309",
    "sg:province":"TX",
    "sg:tags":[
        "mechanical",
        "contractor"
    ],
    "wof:name":"R & R Mechanical Co",
    "wof:placetype":"venue"
},
  "geometry": {"coordinates":[-98.555852,33.880025],"type":"Point"}
}