{
  "type": "Feature",
  "properties": {
    "iso:country":"US",
    "sg:address":"18014 Memorial Estates Dr",
    "sg:city":"Spring",
    "sg:classifiers":[
        {
            "category":"Professional",
            "subcategory":"Management & Consulting",
            "type":"Services"
        }
    ],
    "sg:phone":"+1 281 320 2266",
    "sg:postcode":"77379",
    "sg:province":"TX",
    "wof:name":"Temple-Brown Development",
    "wof:placetype":"venue"
},
  "geometry": {"coordinates":[-95.54507700000001,30.030499],"type":"Point"}
}