{
  "type": "Feature",
  "properties": {
    "iso:country":"US",
    "sg:address":"5120 Broadway",
    "sg:city":"San Antonio",
    "sg:classifiers":[
        {
            "category":"Real Estate",
            "subcategory":"Real Estate Agent",
            "type":"Services"
        }
    ],
    "sg:phone":"+1 210 822 8757",
    "sg:postcode":"78209",
    "sg:province":"TX",
    "sg:tags":[
        "appraisal"
    ],
    "wof:name":"Hodges Brad & Associates",
    "wof:placetype":"venue"
},
  "geometry": {"coordinates":[-98.462661,29.473846],"type":"Point"}
}