{
  "type": "Feature",
  "properties": {
    "iso:country":"US",
    "sg:address":"106 N Grace St",
    "sg:city":"Crockett",
    "sg:classifiers":[
        {
            "category":"Health Services",
            "subcategory":"Clinic",
            "type":"Services"
        }
    ],
    "sg:phone":"+1 936 544 7202",
    "sg:postcode":"75835",
    "sg:province":"TX",
    "sg:tags":[
        "home"
    ],
    "wof:name":"Aftercare Visiting Nurse Svc",
    "wof:placetype":"venue"
},
  "geometry": {"coordinates":[-95.44578,31.322131],"type":"Point"}
}