{
  "type": "Feature",
  "properties": {
    "iso:country":"US",
    "sg:address":"2701 N Central Expy",
    "sg:city":"Plano",
    "sg:classifiers":[
        {
            "category":"Autos & Motor Vehicles",
            "subcategory":"Automobile Sales",
            "type":"Retail Goods"
        }
    ],
    "sg:phone":"+1 972 578 7511",
    "sg:postcode":"75075",
    "sg:province":"TX",
    "sg:tags":[
        "new",
        "used",
        "car"
    ],
    "sg:website":"http://www.metroplexcadillacdealers.com/",
    "wof:name":"Crest Cadillac",
    "wof:placetype":"venue"
},
  "geometry": {"coordinates":[-96.70649899999999,33.034499],"type":"Point"}
}