{
  "type": "Feature",
  "properties": {
    "iso:country":"US",
    "sg:address":"415 W Hubbard St",
    "sg:city":"Mineral Wells",
    "sg:classifiers":[
        {
            "category":"Personal",
            "subcategory":"Beauty Salon",
            "type":"Services"
        }
    ],
    "sg:phone":"+1 940 325 2069",
    "sg:postcode":"76067",
    "sg:province":"TX",
    "sg:tags":[
        "shop"
    ],
    "wof:name":"Roylynn's Hair Barn",
    "wof:placetype":"venue"
},
  "geometry": {"coordinates":[-98.116225,32.809134],"type":"Point"}
}