{
  "type": "Feature",
  "properties": {
    "iso:country":"US",
    "sg:address":"1705 Guadalupe Street",
    "sg:city":"Austin",
    "sg:classifiers":[
        {
            "category":"Organizations",
            "subcategory":"Non-profit Organization",
            "type":"Services"
        }
    ],
    "sg:phone":"+1 512 480 9291",
    "sg:postcode":"78701",
    "sg:province":"TX",
    "sg:tags":[
        "service/non-profit",
        "community"
    ],
    "wof:name":"Reel Women",
    "wof:placetype":"venue"
},
  "geometry": {"coordinates":[-97.74227,30.280225],"type":"Point"}
}