{
  "type": "Feature",
  "properties": {
    "iso:country":"US",
    "sg:address":"5809 Crestwood Dr",
    "sg:city":"Corpus Christi",
    "sg:classifiers":[
        {
            "category":"Retail",
            "subcategory":"Repair Shop",
            "type":"Services"
        }
    ],
    "sg:phone":"+1 361 882 8327",
    "sg:postcode":"78415",
    "sg:province":"TX",
    "sg:tags":[
        "refrigeration"
    ],
    "wof:name":"Vollmer Air Conditioning",
    "wof:placetype":"venue"
},
  "geometry": {"coordinates":[-97.418167,27.716473],"type":"Point"}
}