{
  "type": "Feature",
  "properties": {
    "iso:country":"US",
    "sg:address":"13636 Hempstead Rd",
    "sg:city":"Houston",
    "sg:classifiers":[
        {
            "category":"Wholesale",
            "subcategory":"Machinery & Supplies",
            "type":"Manufacturing & Wholesale Goods"
        }
    ],
    "sg:phone":"+1 713 462 8027",
    "sg:postcode":"77040",
    "sg:province":"TX",
    "sg:tags":[
        "equipment",
        "welding"
    ],
    "sg:website":"www.airgas.com",
    "wof:name":"Airgas Southwest",
    "wof:placetype":"venue"
},
  "geometry": {"coordinates":[-95.523293,29.846912],"type":"Point"}
}