{
  "type": "Feature",
  "properties": {
    "iso:country":"US",
    "sg:address":"4260 Justin Rd",
    "sg:city":"Lewisville",
    "sg:classifiers":[
        {
            "category":"Home & Garden",
            "subcategory":"Home Furnishings",
            "type":"Retail Goods"
        }
    ],
    "sg:phone":"+1 972 724 1443",
    "sg:postcode":"75077",
    "sg:province":"TX",
    "sg:tags":[
        "commerce"
    ],
    "wof:name":"Forever In Season I L P",
    "wof:placetype":"venue"
},
  "geometry": {"coordinates":[-97.08165099999999,33.07234],"type":"Point"}
}