{
  "type": "Feature",
  "properties": {
    "iso:country":"US",
    "sg:address":"1845 Troup Hwy",
    "sg:city":"Tyler",
    "sg:classifiers":[
        {
            "category":"Building & Trades",
            "subcategory":"Construction",
            "type":"Services"
        }
    ],
    "sg:phone":"+1 903 597 3982",
    "sg:postcode":"75701",
    "sg:province":"TX",
    "sg:tags":[
        "nonresidential"
    ],
    "wof:name":"Card Warehouse",
    "wof:placetype":"venue"
},
  "geometry": {"coordinates":[-95.27810100000001,32.317017],"type":"Point"}
}