{
  "type": "Feature",
  "properties": {
    "iso:country":"US",
    "sg:address":"1771 Wildfire Ln",
    "sg:city":"Frisco",
    "sg:classifiers":[
        {
            "category":"Professional",
            "subcategory":"Lawyer & Legal Services",
            "type":"Services"
        }
    ],
    "sg:phone":"+1 972 377 7392",
    "sg:postcode":"75034",
    "sg:province":"TX",
    "wof:name":"Funnell Kvin J Attorney At Law",
    "wof:placetype":"venue"
},
  "geometry": {"coordinates":[-96.877399,33.159007],"type":"Point"}
}