{
  "type": "Feature",
  "properties": {
    "iso:country":"US",
    "sg:address":"3530 Dry Creek Dr",
    "sg:city":"Pasadena",
    "sg:classifiers":[
        {
            "category":"Manufacturing",
            "subcategory":"Jewelry",
            "type":"Manufacturing & Wholesale Goods"
        }
    ],
    "sg:phone":"+1 281 998 8125",
    "sg:postcode":"77505",
    "sg:province":"TX",
    "sg:tags":[
        "costume",
        "mfg"
    ],
    "wof:name":"Silvia Garza",
    "wof:placetype":"venue"
},
  "geometry": {"coordinates":[-95.138856,29.657505],"type":"Point"}
}