{
  "type": "Feature",
  "properties": {
    "iso:country":"US",
    "sg:address":"1226 Idaho Ave",
    "sg:city":"Dallas",
    "sg:classifiers":[
        {
            "category":"Manufacturing",
            "subcategory":"Signs",
            "type":"Manufacturing & Wholesale Goods"
        }
    ],
    "sg:phone":"+1 214 943 1782",
    "sg:postcode":"75216",
    "sg:province":"TX",
    "sg:tags":[
        "specialty",
        "mfg"
    ],
    "wof:name":"Swift, Frances Show Cards & Charts",
    "wof:placetype":"venue"
},
  "geometry": {"coordinates":[-96.812912,32.733778],"type":"Point"}
}