{
  "type": "Feature",
  "properties": {
    "iso:country":"US",
    "sg:address":"9751 Katy Fwy",
    "sg:city":"Houston",
    "sg:classifiers":[
        {
            "category":"Restaurant",
            "type":"Food & Drink"
        }
    ],
    "sg:phone":"+1 713 827 8329",
    "sg:postcode":"77024",
    "sg:province":"TX",
    "sg:tags":[
        "japanese"
    ],
    "wof:name":"Kobe Japanese Restaurant",
    "wof:placetype":"venue"
},
  "geometry": {"coordinates":[-95.533997,29.783701],"type":"Point"}
}