{
  "type": "Feature",
  "properties": {
    "iso:country":"US",
    "sg:address":"4614 Briarbend Dr",
    "sg:city":"Houston",
    "sg:classifiers":[
        {
            "category":"Arts & Performance",
            "subcategory":"Theater",
            "type":"Entertainment"
        }
    ],
    "sg:phone":"+1 713 661 6804",
    "sg:postcode":"77035",
    "sg:province":"TX",
    "sg:tags":[
        "group"
    ],
    "wof:name":"Accent Chamber Music",
    "wof:placetype":"venue"
},
  "geometry": {"coordinates":[-95.454306,29.661857],"type":"Point"}
}