{
  "type": "Feature",
  "properties": {
    "iso:country":"US",
    "sg:address":"3550 Lamar Ave",
    "sg:city":"Paris",
    "sg:classifiers":[
        {
            "category":"Shopping",
            "subcategory":"Department Store",
            "type":"Retail Goods"
        }
    ],
    "sg:phone":"+1 903 737 8928",
    "sg:postcode":"75460",
    "sg:province":"TX",
    "sg:tags":[
        "shop"
    ],
    "wof:name":"Dollar General",
    "wof:placetype":"venue"
},
  "geometry": {"coordinates":[-95.510097,33.661409],"type":"Point"}
}