{
  "type": "Feature",
  "properties": {
    "iso:country":"US",
    "sg:address":"11652 Jollyville Rd",
    "sg:city":"Austin",
    "sg:classifiers":[
        {
            "category":"Banks & Credit Unions",
            "subcategory":"Bank",
            "type":"Services"
        }
    ],
    "sg:phone":"+1 512 219 7746",
    "sg:postcode":"78759",
    "sg:province":"TX",
    "sg:tags":[
        "loan",
        "broker",
        "real estate"
    ],
    "sg:website":"http://www.aomaustin.com",
    "wof:name":"Advantage One Mortgage",
    "wof:placetype":"venue"
},
  "geometry": {"coordinates":[-97.75136000000001,30.418453],"type":"Point"}
}