{
  "type": "Feature",
  "properties": {
    "iso:country":"US",
    "sg:address":"42 Candle Pine Pl",
    "sg:city":"Spring",
    "sg:classifiers":[
        {
            "category":"Professional",
            "subcategory":"Business Services",
            "type":"Services"
        }
    ],
    "sg:phone":"+1 936 321 5952",
    "sg:postcode":"77381",
    "sg:province":"TX",
    "wof:name":"Ali Harvey Custom Win Fashions",
    "wof:placetype":"venue"
},
  "geometry": {"coordinates":[-95.52848299999999,30.203121],"type":"Point"}
}