{
  "type": "Feature",
  "properties": {
    "iso:country":"US",
    "sg:address":"8350 Phelan Blvd",
    "sg:city":"Beaumont",
    "sg:classifiers":[
        {
            "category":"Restaurant",
            "type":"Food & Drink"
        }
    ],
    "sg:phone":"+1 409 866 7746",
    "sg:postcode":"77706",
    "sg:province":"TX",
    "sg:tags":[
        "pizza"
    ],
    "wof:name":"Pizza Time",
    "wof:placetype":"venue"
},
  "geometry": {"coordinates":[-94.189549,30.076668],"type":"Point"}
}