{
  "type": "Feature",
  "properties": {
    "iso:country":"US",
    "sg:address":"116 S 7th St",
    "sg:city":"Ballinger",
    "sg:classifiers":[
        {
            "category":"Professional",
            "subcategory":"Accounting & Tax Preparation",
            "type":"Services"
        }
    ],
    "sg:phone":"+1 325 365 5458",
    "sg:postcode":"76821",
    "sg:province":"TX",
    "sg:tags":[
        "return",
        "filing"
    ],
    "wof:name":"H & R Block Tax Svc",
    "wof:placetype":"venue"
},
  "geometry": {"coordinates":[-99.947248,31.737964],"type":"Point"}
}