{
  "type": "Feature",
  "properties": {
    "iso:country":"US",
    "sg:address":"8750 N Central Expy",
    "sg:city":"Dallas",
    "sg:classifiers":[
        {
            "category":"Banks & Credit Unions",
            "subcategory":"Investment Brokerage",
            "type":"Services"
        },
        {
            "category":"Banks & Credit Unions",
            "subcategory":"Financial Services",
            "type":"Services"
        }
    ],
    "sg:phone":"+1 214 265 0820",
    "sg:postcode":"75231",
    "sg:province":"TX",
    "sg:tags":[
        "investing",
        "broker",
        "mortgage"
    ],
    "sg:website":"www.statestreetmortgage.com",
    "wof:name":"State Street Mortgage",
    "wof:placetype":"venue"
},
  "geometry": {"coordinates":[-96.769566,32.869166],"type":"Point"}
}