{
  "type": "Feature",
  "properties": {
    "iso:country":"US",
    "sg:address":"1370 N Millbend Dr",
    "sg:city":"Spring",
    "sg:classifiers":[
        {
            "category":"Organizations",
            "subcategory":"Religious Organization",
            "type":"Services"
        }
    ],
    "sg:phone":"+1 281 298 9901",
    "sg:postcode":"77380",
    "sg:province":"TX",
    "wof:name":"Lord of Life Lutheran Church",
    "wof:placetype":"venue"
},
  "geometry": {"coordinates":[-95.45536,30.152119],"type":"Point"}
}