{
  "type": "Feature",
  "properties": {
    "iso:country":"US",
    "sg:address":"1351 Hailey St",
    "sg:city":"Sweetwater",
    "sg:classifiers":[
        {
            "category":"Retail",
            "subcategory":"Laundry & Dry Cleaning",
            "type":"Services"
        }
    ],
    "sg:phone":"+1 325 236 9800",
    "sg:postcode":"79556",
    "sg:province":"TX",
    "sg:tags":[
        "cleaners",
        "rug",
        "carpet"
    ],
    "wof:name":"Power Clean Carpet Care",
    "wof:placetype":"venue"
},
  "geometry": {"coordinates":[-100.401258,32.481947],"type":"Point"}
}