{
  "type": "Feature",
  "properties": {
    "iso:country":"US",
    "sg:address":"222 W Main St",
    "sg:city":"Denison",
    "sg:classifiers":[
        {
            "category":"Real Estate",
            "subcategory":"Surveying",
            "type":"Services"
        }
    ],
    "sg:phone":"+1 903 463 6191",
    "sg:postcode":"75020",
    "sg:province":"TX",
    "sg:tags":[
        "surveyor"
    ],
    "wof:name":"Helvey & Assoc Surveying Inc",
    "wof:placetype":"venue"
},
  "geometry": {"coordinates":[-96.538118,33.755317],"type":"Point"}
}