{
  "type": "Feature",
  "properties": {
    "iso:country":"US",
    "sg:address":"13616 Neutron Rd",
    "sg:city":"Dallas",
    "sg:classifiers":[
        {
            "category":"Shopping",
            "subcategory":"Computers & Home Electronics",
            "type":"Retail Goods"
        }
    ],
    "sg:phone":"+1 972 458 0501",
    "sg:postcode":"75244",
    "sg:province":"TX",
    "sg:website":"www.accentav.com",
    "wof:name":"Accent Audio Video Inc",
    "wof:placetype":"venue"
},
  "geometry": {"coordinates":[-96.834801,32.933498],"type":"Point"}
}