{
  "type": "Feature",
  "properties": {
    "iso:country":"US",
    "sg:address":"1101 N Industrial Blvd",
    "sg:city":"Round Rock",
    "sg:classifiers":[
        {
            "category":"Wholesale",
            "subcategory":"Machinery & Supplies",
            "type":"Manufacturing & Wholesale Goods"
        }
    ],
    "sg:phone":"+1 512 733 6610",
    "sg:postcode":"78681",
    "sg:province":"TX",
    "sg:tags":[
        "equipment",
        "industrial"
    ],
    "wof:name":"Above All Components",
    "wof:placetype":"venue"
},
  "geometry": {"coordinates":[-97.693315,30.521986],"type":"Point"}
}