{
  "type": "Feature",
  "properties": {
    "iso:country":"US",
    "sg:address":"146 Triangle Acres Ln",
    "sg:city":"Cedar Creek",
    "sg:classifiers":[
        {
            "category":"Freight",
            "type":"Transportation"
        }
    ],
    "sg:phone":"+1 512 303 9837",
    "sg:postcode":"78612",
    "sg:province":"TX",
    "sg:tags":[
        "operator",
        "local",
        "trucking"
    ],
    "wof:name":"JG Trucking",
    "wof:placetype":"venue"
},
  "geometry": {"coordinates":[-97.489885,30.143251],"type":"Point"}
}