{
  "type": "Feature",
  "properties": {
    "iso:country":"US",
    "sg:address":"2719 Ave H",
    "sg:city":"Rosenberg",
    "sg:classifiers":[
        {
            "category":"Home & Garden",
            "subcategory":"Building Materials",
            "type":"Retail Goods"
        }
    ],
    "sg:phone":"+1 281 232 6416",
    "sg:postcode":"77471",
    "sg:province":"TX",
    "sg:tags":[
        "glass",
        "window",
        "plate"
    ],
    "sg:website":"www.rayglass.com",
    "wof:name":"Ray Glass Co",
    "wof:placetype":"venue"
},
  "geometry": {"coordinates":[-95.797337,29.558515],"type":"Point"}
}