{
  "type": "Feature",
  "properties": {
    "iso:country":"US",
    "sg:address":"1220 Corporate Dr W",
    "sg:city":"Arlington",
    "sg:classifiers":[
        {
            "category":"Professional",
            "subcategory":"Printing & Photocopies",
            "type":"Services"
        }
    ],
    "sg:phone":"+1 817 695 1077",
    "sg:postcode":"76006",
    "sg:province":"TX",
    "sg:tags":[
        "photocopying",
        "blueprinting"
    ],
    "sg:website":"www.reprofw.com",
    "wof:name":"Reprographics of Arlington",
    "wof:placetype":"venue"
},
  "geometry": {"coordinates":[-97.067953,32.768254],"type":"Point"}
}