{
  "type": "Feature",
  "properties": {
    "iso:country":"US",
    "sg:address":"926 Miramar Pl",
    "sg:city":"Corpus Christi",
    "sg:classifiers":[
        {
            "category":"Personal",
            "subcategory":"Barber",
            "type":"Services"
        }
    ],
    "sg:phone":"+1 361 852 3291",
    "sg:postcode":"78411",
    "sg:province":"TX",
    "sg:tags":[
        "shop"
    ],
    "wof:name":"Adrians Beauty Salon",
    "wof:placetype":"venue"
},
  "geometry": {"coordinates":[-97.37890400000001,27.732617],"type":"Point"}
}