{
  "type": "Feature",
  "properties": {
    "iso:country":"US",
    "sg:address":"144 E Little York Rd",
    "sg:city":"Houston",
    "sg:classifiers":[
        {
            "category":"Personal",
            "subcategory":"Beauty Salon",
            "type":"Services"
        }
    ],
    "sg:phone":"+1 713 694 6700",
    "sg:postcode":"77076",
    "sg:province":"TX",
    "sg:tags":[
        "treatment",
        "skin"
    ],
    "wof:name":"Nora's Beauty Salon",
    "wof:placetype":"venue"
},
  "geometry": {"coordinates":[-95.39841800000001,29.869827],"type":"Point"}
}