{
  "type": "Feature",
  "properties": {
    "iso:country":"US",
    "sg:address":"321 Mesa Grande Dr",
    "sg:city":"Fort Worth",
    "sg:classifiers":[
        {
            "category":"Retail",
            "subcategory":"Repair Shop",
            "type":"Services"
        },
        {
            "category":"Building & Trades",
            "subcategory":"Plumbing",
            "type":"Services"
        }
    ],
    "sg:phone":"+1 817 448 9310",
    "sg:postcode":"76108",
    "sg:province":"TX",
    "sg:tags":[
        "equipment",
        "air",
        "refrigeration",
        "conditioning",
        "contractor"
    ],
    "wof:name":"Freed Air Conditioning",
    "wof:placetype":"venue"
},
  "geometry": {"coordinates":[-97.58080699999999,32.800618],"type":"Point"}
}