{
  "type": "Feature",
  "properties": {
    "iso:country":"US",
    "sg:address":"1141 Uptown Park Blvd Ste 4",
    "sg:city":"Houston",
    "sg:classifiers":[
        {
            "category":"Shopping",
            "subcategory":"Tobacco",
            "type":"Retail Goods"
        }
    ],
    "sg:phone":"+1 713 840 7612",
    "sg:postcode":"77056",
    "sg:province":"TX",
    "sg:tags":[
        "shop"
    ],
    "wof:name":"Cigar Vault",
    "wof:placetype":"venue"
},
  "geometry": {"coordinates":[-95.45760300000001,29.755699],"type":"Point"}
}