{
  "type": "Feature",
  "properties": {
    "iso:country":"US",
    "sg:address":"1114 Roberts St",
    "sg:city":"Bowie",
    "sg:phone":"+1 940 872 4711",
    "sg:postcode":"76230",
    "sg:province":"TX",
    "sg:tags":[
        "fixture",
        "store"
    ],
    "wof:name":"Chichi Designs",
    "wof:placetype":"venue"
},
  "geometry": {"coordinates":[-97.847523,33.569599],"type":"Point"}
}