{
  "type": "Feature",
  "properties": {
    "iso:country":"US",
    "sg:address":"106 S Green St",
    "sg:city":"Caldwell",
    "sg:classifiers":[
        {
            "category":"Autos & Motor Vehicles",
            "subcategory":"Auto Supplies",
            "type":"Retail Goods"
        }
    ],
    "sg:phone":"+1 979 567 6375",
    "sg:postcode":"77836",
    "sg:province":"TX",
    "sg:tags":[
        "tire"
    ],
    "wof:name":"Mitchell's Tire Svc",
    "wof:placetype":"venue"
},
  "geometry": {"coordinates":[-96.69079600000001,30.534886],"type":"Point"}
}