{
  "type": "Feature",
  "properties": {
    "iso:country":"US",
    "sg:address":"7826 Meadowpark Dr",
    "sg:city":"Dallas",
    "sg:classifiers":[
        {
            "category":"Professional",
            "type":"Services"
        }
    ],
    "sg:phone":"+1 214 363 9384",
    "sg:postcode":"75230",
    "sg:province":"TX",
    "sg:tags":[
        "establishment"
    ],
    "wof:name":"Mark Trew Co",
    "wof:placetype":"venue"
},
  "geometry": {"coordinates":[-96.770678,32.885322],"type":"Point"}
}