{
  "type": "Feature",
  "properties": {
    "iso:country":"US",
    "sg:address":"117 Bess St",
    "sg:city":"New Braunfels",
    "sg:classifiers":[
        {
            "category":"Food & Beverages",
            "subcategory":"Liquor & Beverages",
            "type":"Retail Goods"
        }
    ],
    "sg:phone":"+1 830 625 3568",
    "sg:postcode":"78130",
    "sg:province":"TX",
    "wof:name":"K & B Liquors",
    "wof:placetype":"venue"
},
  "geometry": {"coordinates":[-98.05000200000001,29.653908],"type":"Point"}
}