{
  "type": "Feature",
  "properties": {
    "iso:country":"US",
    "sg:address":"2404 Tarpley Rd",
    "sg:city":"Carrollton",
    "sg:classifiers":[
        {
            "category":"Building & Trades",
            "subcategory":"Construction",
            "type":"Services"
        }
    ],
    "sg:phone":"+1 972 416 1518",
    "sg:postcode":"75006",
    "sg:province":"TX",
    "sg:tags":[
        "concrete",
        "contractor"
    ],
    "wof:name":"Ramer Concrete Inc",
    "wof:placetype":"venue"
},
  "geometry": {"coordinates":[-96.85132299999999,32.974086],"type":"Point"}
}