{
  "type": "Feature",
  "properties": {
    "iso:country":"US",
    "sg:address":"2725 Harlanwood Dr",
    "sg:city":"Fort Worth",
    "sg:classifiers":[
        {
            "category":"Banks & Credit Unions",
            "subcategory":"Financial Services",
            "type":"Services"
        }
    ],
    "sg:phone":"+1 817 926 2689",
    "sg:postcode":"76109",
    "sg:province":"TX",
    "sg:tags":[
        "trust",
        "management"
    ],
    "wof:name":"Mattye Carter Family Trust",
    "wof:placetype":"venue"
},
  "geometry": {"coordinates":[-97.374088,32.710385],"type":"Point"}
}