{
  "type": "Feature",
  "properties": {
    "iso:country":"US",
    "sg:address":"111 Deerhorn Ct",
    "sg:city":"Austin",
    "sg:classifiers":[
        {
            "category":"Professional",
            "subcategory":"Computer Services",
            "type":"Services"
        }
    ],
    "sg:phone":"+1 512 261 8756",
    "sg:postcode":"78734",
    "sg:province":"TX",
    "sg:tags":[
        "datum"
    ],
    "wof:name":"Linear City",
    "wof:placetype":"venue"
},
  "geometry": {"coordinates":[-97.980231,30.366646],"type":"Point"}
}