{
  "type": "Feature",
  "properties": {
    "iso:country":"US",
    "sg:address":"822 Poinsettia Dr",
    "sg:city":"Lancaster",
    "sg:classifiers":[
        {
            "category":"Travel",
            "subcategory":"Travel Agent",
            "type":"Entertainment"
        }
    ],
    "sg:phone":"+1 972 218 7515",
    "sg:postcode":"75146",
    "sg:province":"TX",
    "sg:tags":[
        "agency"
    ],
    "wof:name":"Global One Travel",
    "wof:placetype":"venue"
},
  "geometry": {"coordinates":[-96.769498,32.597114],"type":"Point"}
}