{
  "type": "Feature",
  "properties": {
    "iso:country":"US",
    "sg:address":"322 Pinehurst Blvd",
    "sg:city":"San Antonio",
    "sg:classifiers":[
        {
            "category":"Shopping",
            "subcategory":"Clothing, Apparel, & Fashions",
            "type":"Retail Goods"
        }
    ],
    "sg:phone":"+1 210 924 5373",
    "sg:postcode":"78221",
    "sg:province":"TX",
    "wof:name":"Donovan Imports",
    "wof:placetype":"venue"
},
  "geometry": {"coordinates":[-98.49949599999999,29.32698],"type":"Point"}
}