{
  "type": "Feature",
  "properties": {
    "iso:country":"US",
    "sg:address":"11311 N Central Expy",
    "sg:city":"Dallas",
    "sg:classifiers":[
        {
            "category":"Wholesale",
            "subcategory":"Medical Equipment & Supplies",
            "type":"Manufacturing & Wholesale Goods"
        }
    ],
    "sg:phone":"+1 214 373 3774",
    "sg:postcode":"75243",
    "sg:province":"TX",
    "sg:tags":[
        "optical"
    ],
    "wof:name":"Wise Contact US Optical Corp",
    "wof:placetype":"venue"
},
  "geometry": {"coordinates":[-96.769521,32.901991],"type":"Point"}
}