{
  "type": "Feature",
  "properties": {
    "iso:country":"US",
    "sg:address":"2703 Fondren Dr",
    "sg:city":"Dallas",
    "sg:classifiers":[
        {
            "category":"Building & Trades",
            "subcategory":"Electrical",
            "type":"Services"
        }
    ],
    "sg:phone":"+1 214 373 4607",
    "sg:postcode":"75206",
    "sg:province":"TX",
    "sg:tags":[
        "electrician"
    ],
    "sg:website":"www.parkcitieselectrical.com",
    "wof:name":"Park Cities Electrical Co",
    "wof:placetype":"venue"
},
  "geometry": {"coordinates":[-96.775398,32.8447],"type":"Point"}
}