{
  "type": "Feature",
  "properties": {
    "iso:country":"US",
    "sg:address":"2542 Long Reach Dr",
    "sg:city":"Sugar Land",
    "sg:classifiers":[
        {
            "category":"Food & Beverages",
            "subcategory":"Groceries & Convenience Stores",
            "type":"Retail Goods"
        }
    ],
    "sg:phone":"+1 713 271 3779",
    "sg:postcode":"77478",
    "sg:province":"TX",
    "wof:name":"New Thrifty Food Mart",
    "wof:placetype":"venue"
},
  "geometry": {"coordinates":[-95.60985700000001,29.597159],"type":"Point"}
}