{
  "type": "Feature",
  "properties": {
    "iso:country":"US",
    "sg:address":"4452 Overton Crest St",
    "sg:city":"Fort Worth",
    "sg:classifiers":[
        {
            "category":"Professional",
            "type":"Services"
        }
    ],
    "sg:phone":"+1 817 921 3133",
    "sg:postcode":"76109",
    "sg:province":"TX",
    "wof:name":"Harley/Maddisson LLC",
    "wof:placetype":"venue"
},
  "geometry": {"coordinates":[-97.38820200000001,32.699493],"type":"Point"}
}