{
  "type": "Feature",
  "properties": {
    "iso:country":"US",
    "sg:address":"1106 Vance Jackson Rd",
    "sg:city":"San Antonio",
    "sg:classifiers":[
        {
            "category":"Restaurant",
            "type":"Food & Drink"
        }
    ],
    "sg:phone":"+1 210 732 3315",
    "sg:postcode":"78201",
    "sg:province":"TX",
    "wof:name":"Taqueria Guadalajara",
    "wof:placetype":"venue"
},
  "geometry": {"coordinates":[-98.534864,29.483709],"type":"Point"}
}