{
  "type": "Feature",
  "properties": {
    "iso:country":"US",
    "sg:address":"4715 Titanic Ave",
    "sg:city":"El Paso",
    "sg:classifiers":[
        {
            "category":"Building & Trades",
            "subcategory":"Construction",
            "type":"Services"
        }
    ],
    "sg:phone":"+1 915 755 1410",
    "sg:postcode":"79904",
    "sg:province":"TX",
    "sg:tags":[
        "roofing",
        "contractor"
    ],
    "wof:name":"Big G Roofing",
    "wof:placetype":"venue"
},
  "geometry": {"coordinates":[-106.430564,31.853569],"type":"Point"}
}