{
  "type": "Feature",
  "properties": {
    "iso:country":"US",
    "sg:address":"613 Sheldon Rd",
    "sg:city":"Channelview",
    "sg:classifiers":[
        {
            "category":"Restaurant",
            "type":"Food & Drink"
        }
    ],
    "sg:menulink":"http://www.allmenus.com/tx/houston/203798-sonic/menu/",
    "sg:phone":"+1 281 452 0013",
    "sg:postcode":"77530",
    "sg:province":"TX",
    "sg:tags":[
        "burger",
        "american"
    ],
    "wof:name":"Sonic",
    "wof:placetype":"venue"
},
  "geometry": {"coordinates":[-95.124994,29.784131],"type":"Point"}
}