{
  "type": "Feature",
  "properties": {
    "iso:country":"US",
    "sg:address":"3720 Whitehall Dr",
    "sg:city":"Dallas",
    "sg:classifiers":[
        {
            "category":"Professional",
            "subcategory":"Management & Consulting",
            "type":"Services"
        }
    ],
    "sg:phone":"+1 214 352 6547",
    "sg:postcode":"75229",
    "sg:province":"TX",
    "sg:tags":[
        "construction"
    ],
    "wof:name":"Richard N Whittle & Associates",
    "wof:placetype":"venue"
},
  "geometry": {"coordinates":[-96.85211700000001,32.901145],"type":"Point"}
}