{
  "type": "Feature",
  "properties": {
    "iso:country":"US",
    "sg:address":"1311 Marydale Dr",
    "sg:city":"Arlington",
    "sg:classifiers":[
        {
            "category":"Professional",
            "subcategory":"Business Services",
            "type":"Services"
        }
    ],
    "sg:phone":"+1 817 265 4416",
    "sg:postcode":"76013",
    "sg:province":"TX",
    "sg:tags":[
        "production",
        "music",
        "publishing"
    ],
    "wof:name":"Mark Harrell Music Productions",
    "wof:placetype":"venue"
},
  "geometry": {"coordinates":[-97.12738899999999,32.718481],"type":"Point"}
}