{
  "type": "Feature",
  "properties": {
    "iso:country":"US",
    "sg:address":"1418 Preston St",
    "sg:city":"Houston",
    "sg:classifiers":[
        {
            "category":"Deli",
            "type":"Food & Drink"
        },
        {
            "category":"Food & Beverages",
            "subcategory":"Bakery",
            "type":"Retail Goods"
        }
    ],
    "sg:phone":"+1 713 222 7010",
    "sg:postcode":"77002",
    "sg:province":"TX",
    "sg:tags":[
        "sandwich"
    ],
    "wof:name":"Joe's Deli",
    "wof:placetype":"venue"
},
  "geometry": {"coordinates":[-95.357793,29.759207],"type":"Point"}
}