{
  "type": "Feature",
  "properties": {
    "iso:country":"US",
    "sg:address":"5708 Southwest Fwy",
    "sg:city":"Houston",
    "sg:classifiers":[
        {
            "category":"Building & Trades",
            "subcategory":"Equipment Rental",
            "type":"Services"
        }
    ],
    "sg:phone":"+1 713 783 2162",
    "sg:postcode":"77057",
    "sg:province":"TX",
    "sg:tags":[
        "leasing"
    ],
    "wof:name":"Nations Leasing",
    "wof:placetype":"venue"
},
  "geometry": {"coordinates":[-95.47689,29.726283],"type":"Point"}
}