{
  "type": "Feature",
  "properties": {
    "iso:country":"US",
    "sg:address":"2116 Cedar Cir",
    "sg:city":"Carrollton",
    "sg:classifiers":[
        {
            "category":"Shopping",
            "subcategory":"Gifts & Souvenirs",
            "type":"Retail Goods"
        }
    ],
    "sg:phone":"+1 972 416 8973",
    "sg:postcode":"75006",
    "sg:province":"TX",
    "wof:name":"Gifts Worc",
    "wof:placetype":"venue"
},
  "geometry": {"coordinates":[-96.876464,32.979026],"type":"Point"}
}