{
  "type": "Feature",
  "properties": {
    "iso:country":"US",
    "sg:address":"14230 Memorial Dr",
    "sg:city":"Houston",
    "sg:classifiers":[
        {
            "category":"Education",
            "subcategory":"School",
            "type":"Public Place"
        }
    ],
    "sg:phone":"+1 713 497 2855",
    "sg:postcode":"77079",
    "sg:province":"TX",
    "wof:name":"Meadow Wood Elementary School",
    "wof:placetype":"venue"
},
  "geometry": {"coordinates":[-95.59538499999999,29.770139],"type":"Point"}
}