{
  "type": "Feature",
  "properties": {
    "iso:country":"US",
    "sg:address":"3520 Solis",
    "sg:city":"Laredo",
    "sg:classifiers":[
        {
            "category":"Professional",
            "type":"Services"
        }
    ],
    "sg:phone":"+1 956 791 9103",
    "sg:postcode":"78046",
    "sg:province":"TX",
    "wof:name":"Pedro Torres",
    "wof:placetype":"venue"
},
  "geometry": {"coordinates":[-99.49724999999999,27.333868],"type":"Point"}
}