{
  "type": "Feature",
  "properties": {
    "iso:country":"US",
    "sg:address":"2221 Pittner Ln",
    "sg:city":"Plano",
    "sg:classifiers":[
        {
            "category":"Restaurant",
            "type":"Food & Drink"
        }
    ],
    "sg:phone":"+1 972 491 7262",
    "sg:postcode":"75025",
    "sg:province":"TX",
    "sg:tags":[
        "eating"
    ],
    "wof:name":"Sandman Restaurant Company Inc",
    "wof:placetype":"venue"
},
  "geometry": {"coordinates":[-96.738411,33.081393],"type":"Point"}
}