{
  "type": "Feature",
  "properties": {
    "iso:country":"US",
    "sg:address":"305 Scrub Oak",
    "sg:city":"Ingram",
    "sg:classifiers":[
        {
            "category":"Farming",
            "subcategory":"Livestock Farm",
            "type":"Manufacturing & Wholesale Goods"
        }
    ],
    "sg:phone":"+1 830 367 2812",
    "sg:postcode":"78025",
    "sg:province":"TX",
    "sg:tags":[
        "ranch",
        "animal",
        "general"
    ],
    "wof:name":"Paso Creek Ranch Inc",
    "wof:placetype":"venue"
},
  "geometry": {"coordinates":[-99.25721,30.074508],"type":"Point"}
}