{
  "type": "Feature",
  "properties": {
    "iso:country":"US",
    "sg:address":"7011 Harwin Dr",
    "sg:city":"Houston",
    "sg:classifiers":[
        {
            "category":"Travel",
            "subcategory":"Travel Agent",
            "type":"Entertainment"
        }
    ],
    "sg:phone":"+1 713 784 5300",
    "sg:postcode":"77036",
    "sg:province":"TX",
    "sg:tags":[
        "agency",
        "bureau"
    ],
    "wof:name":"Apex Travel",
    "wof:placetype":"venue"
},
  "geometry": {"coordinates":[-95.50633000000001,29.718102],"type":"Point"}
}