{
  "type": "Feature",
  "properties": {
    "iso:country":"US",
    "sg:address":"609 S Guadalupe St",
    "sg:city":"Seguin",
    "sg:classifiers":[
        {
            "category":"Organizations",
            "subcategory":"Religious Organization",
            "type":"Services"
        }
    ],
    "sg:phone":"+1 830 379 4242",
    "sg:postcode":"78155",
    "sg:province":"TX",
    "sg:tags":[
        "church"
    ],
    "wof:name":"Second Baptist Church",
    "wof:placetype":"venue"
},
  "geometry": {"coordinates":[-97.969403,29.565014],"type":"Point"}
}