{
  "type": "Feature",
  "properties": {
    "iso:country":"US",
    "sg:address":"9404 Apple Way",
    "sg:city":"Irving",
    "sg:classifiers":[
        {
            "category":"Professional",
            "subcategory":"Management & Consulting",
            "type":"Services"
        }
    ],
    "sg:phone":"+1 214 505 1845",
    "sg:postcode":"75063",
    "sg:province":"TX",
    "sg:tags":[
        "consultant"
    ],
    "wof:name":"Wilson Consulting Svc",
    "wof:placetype":"venue"
},
  "geometry": {"coordinates":[-96.95931,32.934063],"type":"Point"}
}