{
  "type": "Feature",
  "properties": {
    "iso:country":"US",
    "sg:address":"14210 Cypress Green Dr",
    "sg:city":"Cypress",
    "sg:classifiers":[
        {
            "category":"Home & Garden",
            "subcategory":"Home Furnishings",
            "type":"Retail Goods"
        }
    ],
    "sg:phone":"+1 281 379 2045",
    "sg:postcode":"77429",
    "sg:province":"TX",
    "sg:tags":[
        "temporary",
        "for",
        "lodging"
    ],
    "wof:name":"H&H Home Services",
    "wof:placetype":"venue"
},
  "geometry": {"coordinates":[-95.635199,30.00052],"type":"Point"}
}