{
  "type": "Feature",
  "properties": {
    "iso:country":"US",
    "sg:address":"5536 Bus Park",
    "sg:city":"San Antonio",
    "sg:classifiers":[
        {
            "category":"Professional",
            "type":"Services"
        }
    ],
    "sg:phone":"+1 210 666 2778",
    "sg:postcode":"78218",
    "sg:province":"TX",
    "sg:tags":[
        "establishment"
    ],
    "wof:name":"Monoflex Coatings",
    "wof:placetype":"venue"
},
  "geometry": {"coordinates":[-98.393399,29.477349],"type":"Point"}
}