{
  "type": "Feature",
  "properties": {
    "iso:country":"US",
    "sg:address":"912 S 2nd St",
    "sg:city":"Canadian",
    "sg:classifiers":[
        {
            "category":"Home & Garden",
            "subcategory":"Building Materials",
            "type":"Retail Goods"
        }
    ],
    "sg:phone":"+1 806 323 8016",
    "sg:postcode":"79014",
    "sg:province":"TX",
    "sg:tags":[
        "glass",
        "window",
        "plate"
    ],
    "wof:name":"Canadian Glass & Sign Co",
    "wof:placetype":"venue"
},
  "geometry": {"coordinates":[-100.390677,35.905679],"type":"Point"}
}