{
  "type": "Feature",
  "properties": {
    "iso:country":"US",
    "sg:address":"3317 Finley Rd",
    "sg:city":"Irving",
    "sg:classifiers":[
        {
            "category":"Professional",
            "subcategory":"Accounting & Tax Preparation",
            "type":"Services"
        }
    ],
    "sg:phone":"+1 972 413 1170",
    "sg:postcode":"75062",
    "sg:province":"TX",
    "sg:tags":[
        "return",
        "filing"
    ],
    "wof:name":"AFOT Intl",
    "wof:placetype":"venue"
},
  "geometry": {"coordinates":[-96.991877,32.850949],"type":"Point"}
}