{
  "type": "Feature",
  "properties": {
    "iso:country":"US",
    "sg:address":"6905 Grapevine Hwy",
    "sg:city":"N Richland Hills",
    "sg:classifiers":[
        {
            "category":"Shopping",
            "subcategory":"Jewelry",
            "type":"Retail Goods"
        }
    ],
    "sg:phone":"+1 817 590 2133",
    "sg:postcode":"76180",
    "sg:province":"TX",
    "sg:tags":[
        "clocks"
    ],
    "wof:name":"Annie's Clocks Knives & Gifts",
    "wof:placetype":"venue"
},
  "geometry": {"coordinates":[-97.233491,32.819647],"type":"Point"}
}