{
  "type": "Feature",
  "properties": {
    "iso:country":"US",
    "sg:address":"901 Prachyl Rd",
    "sg:city":"Weatherford",
    "sg:classifiers":[
        {
            "category":"Home & Garden",
            "subcategory":"Carpets & Floor Coverings",
            "type":"Retail Goods"
        }
    ],
    "sg:phone":"+1 817 594 8289",
    "sg:postcode":"76087",
    "sg:province":"TX",
    "sg:tags":[
        "dealer",
        "rug"
    ],
    "wof:name":"B & G Carpets Inc",
    "wof:placetype":"venue"
},
  "geometry": {"coordinates":[-97.77130099999999,32.6003],"type":"Point"}
}