{
  "type": "Feature",
  "properties": {
    "iso:country":"US",
    "sg:address":"3505 S Dairy Ashford St",
    "sg:city":"Houston",
    "sg:classifiers":[
        {
            "category":"Building & Trades",
            "subcategory":"Equipment Rental",
            "type":"Services"
        }
    ],
    "sg:phone":"+1 281 679 0877",
    "sg:postcode":"77082",
    "sg:province":"TX",
    "sg:tags":[
        "engaged",
        "medical",
        "leasing",
        "or"
    ],
    "wof:name":"Pulmonary Home Care",
    "wof:placetype":"venue"
},
  "geometry": {"coordinates":[-95.604784,29.723745],"type":"Point"}
}