{
  "type": "Feature",
  "properties": {
    "iso:country":"US",
    "sg:address":"410 Pierce St",
    "sg:city":"Houston",
    "sg:classifiers":[
        {
            "category":"Professional",
            "subcategory":"Computer Services",
            "type":"Services"
        }
    ],
    "sg:phone":"+1 713 461 9200",
    "sg:postcode":"77002",
    "sg:province":"TX",
    "sg:tags":[
        "consultant",
        "designer",
        "datum",
        "system"
    ],
    "wof:name":"Distributed Network Svc",
    "wof:placetype":"venue"
},
  "geometry": {"coordinates":[-95.37525599999999,29.752063],"type":"Point"}
}