{
  "type": "Feature",
  "properties": {
    "iso:country":"US",
    "sg:address":"579 N Valley Mills Dr",
    "sg:city":"Waco",
    "sg:classifiers":[
        {
            "category":"Professional",
            "subcategory":"Research",
            "type":"Services"
        },
        {
            "category":"Professional",
            "subcategory":"Management & Consulting",
            "type":"Services"
        }
    ],
    "sg:phone":"+1 254 772 8303",
    "sg:postcode":"76710",
    "sg:province":"TX",
    "sg:tags":[
        "environmental",
        "ecological",
        "business"
    ],
    "wof:name":"Burcham Environmental Services",
    "wof:placetype":"venue"
},
  "geometry": {"coordinates":[-97.171857,31.528836],"type":"Point"}
}