{
  "type": "Feature",
  "properties": {
    "iso:country":"US",
    "sg:address":"6720 Gray Wolf Dr",
    "sg:city":"Plano",
    "sg:classifiers":[
        {
            "category":"Social Services",
            "subcategory":"Job Training",
            "type":"Services"
        }
    ],
    "sg:phone":"+1 469 384 9986",
    "sg:postcode":"75024",
    "sg:province":"TX",
    "sg:tags":[
        "technical",
        "consulting"
    ],
    "wof:name":"Apis Training & Seminars US",
    "wof:placetype":"venue"
},
  "geometry": {"coordinates":[-96.833415,33.064527],"type":"Point"}
}