{
  "type": "Feature",
  "properties": {
    "iso:country":"US",
    "sg:address":"15527 Pine Valley Trl",
    "sg:city":"Cypress",
    "sg:classifiers":[
        {
            "category":"Professional",
            "subcategory":"Business Services",
            "type":"Services"
        }
    ],
    "sg:phone":"+1 281 370 1560",
    "sg:postcode":"77433",
    "sg:province":"TX",
    "sg:tags":[
        "inspection"
    ],
    "wof:name":"J D Real Estate Inspections",
    "wof:placetype":"venue"
},
  "geometry": {"coordinates":[-95.757042,30.001878],"type":"Point"}
}