{
  "type": "Feature",
  "properties": {
    "iso:country":"US",
    "sg:address":"2418 N Krenek Rd",
    "sg:city":"Crosby",
    "sg:classifiers":[
        {
            "category":"Professional",
            "subcategory":"Business Services",
            "type":"Services"
        }
    ],
    "sg:phone":"+1 281 462 2730",
    "sg:postcode":"77532",
    "sg:province":"TX",
    "sg:tags":[
        "record",
        "document"
    ],
    "wof:name":"Allstate Documents",
    "wof:placetype":"venue"
},
  "geometry": {"coordinates":[-95.02758900000001,29.901666],"type":"Point"}
}