{
  "type": "Feature",
  "properties": {
    "iso:country":"US",
    "sg:address":"2005 Island Manor Ln",
    "sg:city":"League City",
    "sg:classifiers":[
        {
            "category":"Professional",
            "type":"Services"
        }
    ],
    "sg:phone":"+1 281 332 5825",
    "sg:postcode":"77573",
    "sg:province":"TX",
    "wof:name":"Artwear By Gilley",
    "wof:placetype":"venue"
},
  "geometry": {"coordinates":[-95.118261,29.48167],"type":"Point"}
}