{
  "type": "Feature",
  "properties": {
    "iso:country":"US",
    "sg:address":"2817 Bering Dr",
    "sg:city":"Houston",
    "sg:classifiers":[
        {
            "category":"Professional",
            "subcategory":"Advertising",
            "type":"Services"
        }
    ],
    "sg:phone":"+1 713 974 5265",
    "sg:postcode":"77057",
    "sg:province":"TX",
    "sg:tags":[
        "h",
        "agency",
        "public",
        "relations"
    ],
    "wof:name":"N R Richards & Assoc",
    "wof:placetype":"venue"
},
  "geometry": {"coordinates":[-95.480377,29.735635],"type":"Point"}
}