{
  "type": "Feature",
  "properties": {
    "iso:country":"US",
    "sg:address":"2822 Guthrie Rd",
    "sg:city":"Garland",
    "sg:classifiers":[
        {
            "category":"Real Estate",
            "subcategory":"Real Estate Services",
            "type":"Services"
        },
        {
            "category":"Real Estate",
            "subcategory":"Real Estate Operator",
            "type":"Services"
        }
    ],
    "sg:phone":"+1 972 226 0374",
    "sg:postcode":"75043",
    "sg:province":"TX",
    "sg:tags":[
        "vacancy",
        "apartment",
        "rental",
        "listing"
    ],
    "sg:website":"http://www.myapartmenthome.com",
    "wof:name":"Valley Creek Apartments",
    "wof:placetype":"venue"
},
  "geometry": {"coordinates":[-96.58618,32.835577],"type":"Point"}
}