{
  "type": "Feature",
  "properties": {
    "iso:country":"US",
    "sg:address":"5201 Bartlett Dr",
    "sg:city":"Lewisville",
    "sg:classifiers":[
        {
            "category":"Building & Trades",
            "subcategory":"Landscaping Services",
            "type":"Services"
        }
    ],
    "sg:phone":"+1 972 624 0474",
    "sg:postcode":"75056",
    "sg:province":"TX",
    "wof:name":"Picture Perfect Lawn Care",
    "wof:placetype":"venue"
},
  "geometry": {"coordinates":[-96.88265,33.086149],"type":"Point"}
}