{
  "type": "Feature",
  "properties": {
    "iso:country":"US",
    "sg:address":"408 E Browning St",
    "sg:city":"Calvert",
    "sg:classifiers":[
        {
            "category":"Shopping",
            "subcategory":"Crafts & Fabrics",
            "type":"Retail Goods"
        }
    ],
    "sg:phone":"+1 979 364 2831",
    "sg:postcode":"77837",
    "sg:province":"TX",
    "sg:tags":[
        "shop"
    ],
    "wof:name":"Mimi's Little Wonders",
    "wof:placetype":"venue"
},
  "geometry": {"coordinates":[-96.67494000000001,30.984114],"type":"Point"}
}