{
  "type": "Feature",
  "properties": {
    "iso:country":"US",
    "sg:address":"601 S 1st St",
    "sg:city":"Lamesa",
    "sg:classifiers":[
        {
            "category":"Government",
            "subcategory":"Office",
            "type":"Public Place"
        }
    ],
    "sg:phone":"+1 806 872 4379",
    "sg:postcode":"79331",
    "sg:province":"TX",
    "sg:tags":[
        "city",
        "program",
        "adm"
    ],
    "wof:name":"Lemesa Economic Development",
    "wof:placetype":"venue"
},
  "geometry": {"coordinates":[-101.95392200000001,32.731645],"type":"Point"}
}