{
  "type": "Feature",
  "properties": {
    "iso:country":"US",
    "sg:address":"6121 Park Ln",
    "sg:city":"Dallas",
    "sg:classifiers":[
        {
            "category":"Shopping",
            "subcategory":"Jewelry",
            "type":"Retail Goods"
        }
    ],
    "sg:phone":"+1 469 366 0120",
    "sg:postcode":"75225",
    "sg:province":"TX",
    "wof:name":"Agatha Paris",
    "wof:placetype":"venue"
},
  "geometry": {"coordinates":[-96.80187100000001,32.87351],"type":"Point"}
}