{
  "type": "Feature",
  "properties": {
    "iso:country":"US",
    "sg:address":"6810 W Military Dr",
    "sg:city":"San Antonio",
    "sg:classifiers":[
        {
            "category":"Banks & Credit Unions",
            "subcategory":"Bank",
            "type":"Services"
        }
    ],
    "sg:phone":"+1 210 645 3700",
    "sg:postcode":"78227",
    "sg:province":"TX",
    "sg:tags":[
        "company",
        "holding"
    ],
    "wof:name":"Intercntnental Bnk Shares Corp",
    "wof:placetype":"venue"
},
  "geometry": {"coordinates":[-98.62917299999999,29.405509],"type":"Point"}
}