{
  "type": "Feature",
  "properties": {
    "iso:country":"US",
    "sg:address":"4100 Fairbanks Ct",
    "sg:city":"Irving",
    "sg:classifiers":[
        {
            "category":"Wholesale",
            "subcategory":"Vending Machines",
            "type":"Manufacturing & Wholesale Goods"
        }
    ],
    "sg:phone":"+1 972 252 6823",
    "sg:postcode":"75062",
    "sg:province":"TX",
    "sg:tags":[
        "operator"
    ],
    "wof:name":"Annies Arcades",
    "wof:placetype":"venue"
},
  "geometry": {"coordinates":[-97.003917,32.852134],"type":"Point"}
}