{
  "type": "Feature",
  "properties": {
    "iso:country":"US",
    "sg:address":"561 Hanover Dr",
    "sg:city":"Allen",
    "sg:classifiers":[
        {
            "category":"Freight",
            "type":"Transportation"
        }
    ],
    "sg:phone":"+1 972 390 2026",
    "sg:postcode":"75002",
    "sg:province":"TX",
    "sg:tags":[
        "operator",
        "local",
        "trucking"
    ],
    "wof:name":"Bruce Wallesch & Sons Trucking",
    "wof:placetype":"venue"
},
  "geometry": {"coordinates":[-96.66906400000001,33.07858],"type":"Point"}
}