{
  "type": "Feature",
  "properties": {
    "iso:country":"US",
    "sg:address":"814 W Terrell Ave",
    "sg:city":"Fort Worth",
    "sg:classifiers":[
        {
            "category":"Professional",
            "subcategory":"Engineering",
            "type":"Services"
        }
    ],
    "sg:phone":"+1 817 924 0796",
    "sg:postcode":"76104",
    "sg:province":"TX",
    "sg:tags":[
        "engineer"
    ],
    "wof:name":"Engineering Analysts Inc",
    "wof:placetype":"venue"
},
  "geometry": {"coordinates":[-97.333934,32.735602],"type":"Point"}
}