{
  "type": "Feature",
  "properties": {
    "iso:country":"US",
    "sg:address":"7918 State Hwy 6",
    "sg:city":"Hitchcock",
    "sg:classifiers":[
        {
            "category":"Retail",
            "subcategory":"Auto Repair",
            "type":"Services"
        }
    ],
    "sg:phone":"+1 409 316 0567",
    "sg:postcode":"77563",
    "sg:province":"TX",
    "sg:tags":[
        "repairing",
        "automobile"
    ],
    "wof:name":"Hitchcock Car & Truck Repair",
    "wof:placetype":"venue"
},
  "geometry": {"coordinates":[-95.018531,29.349153],"type":"Point"}
}