{
  "type": "Feature",
  "properties": {
    "iso:country":"US",
    "sg:address":"2133 Wheaton Dr",
    "sg:city":"Richardson",
    "sg:classifiers":[
        {
            "category":"Organizations",
            "subcategory":"Membership Organization",
            "type":"Services"
        }
    ],
    "sg:phone":"+1 972 680 1532",
    "sg:postcode":"75081",
    "sg:province":"TX",
    "sg:tags":[
        "club",
        "private"
    ],
    "wof:name":"Texas Northern Model Railroad",
    "wof:placetype":"venue"
},
  "geometry": {"coordinates":[-96.685271,32.964619],"type":"Point"}
}