{
  "type": "Feature",
  "properties": {
    "iso:country":"US",
    "sg:address":"3217 Independence Pkwy",
    "sg:city":"Plano",
    "sg:classifiers":[
        {
            "category":"Restaurant",
            "type":"Food & Drink"
        }
    ],
    "sg:menulink":"http://www.allmenus.com/tx/plano/44022-chopsticks/menu/",
    "sg:phone":"+1 972 985 7656",
    "sg:postcode":"75075",
    "sg:province":"TX",
    "sg:tags":[
        "asian",
        "chinese"
    ],
    "wof:name":"Chopsticks",
    "wof:placetype":"venue"
},
  "geometry": {"coordinates":[-96.753399,33.040013],"type":"Point"}
}