{
  "type": "Feature",
  "properties": {
    "iso:country":"US",
    "sg:address":"1012 Study Ln",
    "sg:city":"Carrollton",
    "sg:classifiers":[
        {
            "category":"Education",
            "subcategory":"School",
            "type":"Public Place"
        }
    ],
    "sg:phone":"+1 972 446 9206",
    "sg:postcode":"75006",
    "sg:province":"TX",
    "wof:name":"R E Good Elementary",
    "wof:placetype":"venue"
},
  "geometry": {"coordinates":[-96.907562,32.970013],"type":"Point"}
}