{
  "type": "Feature",
  "properties": {
    "iso:country":"US",
    "sg:address":"3809 Trailwood Ln",
    "sg:city":"Fort Worth",
    "sg:classifiers":[
        {
            "category":"Shopping",
            "type":"Retail Goods"
        }
    ],
    "sg:phone":"+1 817 924 2021",
    "sg:postcode":"76109",
    "sg:province":"TX",
    "sg:tags":[
        "merchandise"
    ],
    "wof:name":"Lokko Rokko LLC",
    "wof:placetype":"venue"
},
  "geometry": {"coordinates":[-97.376597,32.707281],"type":"Point"}
}