{
  "type": "Feature",
  "properties": {
    "iso:country":"US",
    "sg:address":"333 N Goat Ridge Rd",
    "sg:city":"Pipe Creek",
    "sg:classifiers":[
        {
            "category":"Food & Beverages",
            "subcategory":"Groceries & Convenience Stores",
            "type":"Retail Goods"
        }
    ],
    "sg:phone":"+1 830 535 6288",
    "sg:postcode":"78063",
    "sg:province":"TX",
    "wof:name":"Hawks Country Store",
    "wof:placetype":"venue"
},
  "geometry": {"coordinates":[-98.958654,29.785363],"type":"Point"}
}