{
  "type": "Feature",
  "properties": {
    "iso:country":"US",
    "sg:address":"6910 Renwick Dr Ste B",
    "sg:city":"Houston",
    "sg:classifiers":[
        {
            "category":"Retail",
            "subcategory":"Repair Shop",
            "type":"Services"
        }
    ],
    "sg:phone":"+1 713 349 0171",
    "sg:postcode":"77081",
    "sg:province":"TX",
    "sg:tags":[
        "upholsterer"
    ],
    "wof:name":"London Upholstery",
    "wof:placetype":"venue"
},
  "geometry": {"coordinates":[-95.48471000000001,29.704499],"type":"Point"}
}