{
  "type": "Feature",
  "properties": {
    "iso:country":"US",
    "sg:address":"6210 S Broadway Ave",
    "sg:city":"Tyler",
    "sg:classifiers":[
        {
            "category":"Food & Beverages",
            "subcategory":"Groceries & Convenience Stores",
            "type":"Retail Goods"
        }
    ],
    "sg:phone":"+1 903 581 0806",
    "sg:postcode":"75703",
    "sg:province":"TX",
    "wof:name":"Kidd Brothers 5",
    "wof:placetype":"venue"
},
  "geometry": {"coordinates":[-95.30450500000001,32.285103],"type":"Point"}
}