{
  "type": "Feature",
  "properties": {
    "iso:country":"US",
    "sg:address":"3400 Elm St",
    "sg:city":"Dallas",
    "sg:classifiers":[
        {
            "category":"Retail",
            "subcategory":"Auto Repair",
            "type":"Services"
        }
    ],
    "sg:phone":"+1 214 573 8740",
    "sg:postcode":"75226",
    "sg:province":"TX",
    "sg:tags":[
        "repairing",
        "automobile"
    ],
    "wof:name":"Personal Care Automotive",
    "wof:placetype":"venue"
},
  "geometry": {"coordinates":[-96.77553899999999,32.786316],"type":"Point"}
}