{
  "type": "Feature",
  "properties": {
    "iso:country":"US",
    "sg:address":"2502 5th Ave S",
    "sg:city":"Texas City",
    "sg:classifiers":[
        {
            "category":"Manufacturing",
            "subcategory":"Chemicals & Compounds",
            "type":"Manufacturing & Wholesale Goods"
        }
    ],
    "sg:phone":"+1 409 943 2478",
    "sg:postcode":"77590",
    "sg:province":"TX",
    "wof:name":"V P North America",
    "wof:placetype":"venue"
},
  "geometry": {"coordinates":[-94.933802,29.379266],"type":"Point"}
}