{
  "type": "Feature",
  "properties": {
    "iso:country":"US",
    "sg:address":"12502 Seattle Slew Dr",
    "sg:city":"Houston",
    "sg:classifiers":[
        {
            "category":"Freight",
            "type":"Transportation"
        }
    ],
    "sg:phone":"+1 281 890 9130",
    "sg:postcode":"77065",
    "sg:province":"TX",
    "sg:tags":[
        "general"
    ],
    "wof:name":"Ssi Storage Management Inc",
    "wof:placetype":"venue"
},
  "geometry": {"coordinates":[-95.590474,29.903608],"type":"Point"}
}