{
  "type": "Feature",
  "properties": {
    "iso:country":"US",
    "sg:address":"233 Belvidere St",
    "sg:city":"El Paso",
    "sg:classifiers":[
        {
            "category":"Arena",
            "subcategory":"Sports Club",
            "type":"Entertainment"
        }
    ],
    "sg:phone":"+1 915 581 2409",
    "sg:postcode":"79912",
    "sg:province":"TX",
    "wof:name":"Penta Continental Boxing",
    "wof:placetype":"venue"
},
  "geometry": {"coordinates":[-106.557951,31.840865],"type":"Point"}
}