{
  "type": "Feature",
  "properties": {
    "iso:country":"US",
    "sg:address":"4321 W 45th Ave",
    "sg:city":"Amarillo",
    "sg:classifiers":[
        {
            "category":"Arena",
            "subcategory":"Sports Club",
            "type":"Entertainment"
        }
    ],
    "sg:phone":"+1 806 353 4640",
    "sg:postcode":"79109",
    "sg:province":"TX",
    "sg:tags":[
        "educational",
        "administrative"
    ],
    "wof:name":"Tawa",
    "wof:placetype":"venue"
},
  "geometry": {"coordinates":[-101.888958,35.161615],"type":"Point"}
}