{
  "type": "Feature",
  "properties": {
    "iso:country":"US",
    "sg:address":"1725 Jay Ell Dr",
    "sg:city":"Richardson",
    "sg:classifiers":[
        {
            "category":"Manufacturing",
            "subcategory":"Tools & Machinery",
            "type":"Manufacturing & Wholesale Goods"
        }
    ],
    "sg:phone":"+1 972 235 1923",
    "sg:postcode":"75081",
    "sg:province":"TX",
    "sg:tags":[
        "industrial",
        "mfg"
    ],
    "wof:name":"Turnamatic Machine Inc",
    "wof:placetype":"venue"
},
  "geometry": {"coordinates":[-96.714288,32.970222],"type":"Point"}
}