{
  "type": "Feature",
  "properties": {
    "iso:country":"US",
    "sg:address":"2009 Dover Dr",
    "sg:city":"Rowlett",
    "sg:classifiers":[
        {
            "category":"Banks & Credit Unions",
            "subcategory":"Bank",
            "type":"Services"
        }
    ],
    "sg:phone":"+1 214 777 4020",
    "sg:postcode":"75088",
    "sg:province":"TX",
    "sg:tags":[
        "national",
        "commercial"
    ],
    "wof:name":"Wells Fargo",
    "wof:placetype":"venue"
},
  "geometry": {"coordinates":[-96.575053,32.880729],"type":"Point"}
}