{
  "type": "Feature",
  "properties": {
    "iso:country":"US",
    "sg:address":"12514 Riva Ridge Ln",
    "sg:city":"Houston",
    "sg:classifiers":[
        {
            "category":"Shopping",
            "subcategory":"Gifts & Souvenirs",
            "type":"Retail Goods"
        }
    ],
    "sg:phone":"+1 713 723 0069",
    "sg:postcode":"77071",
    "sg:province":"TX",
    "wof:name":"Just Because Greetings",
    "wof:placetype":"venue"
},
  "geometry": {"coordinates":[-95.51609500000001,29.64109],"type":"Point"}
}