{
  "type": "Feature",
  "properties": {
    "iso:country":"US",
    "sg:address":"109 S Story Rd",
    "sg:city":"Irving",
    "sg:classifiers":[
        {
            "category":"Shopping",
            "type":"Retail Goods"
        }
    ],
    "sg:phone":"+1 972 871 2866",
    "sg:postcode":"75060",
    "sg:province":"TX",
    "sg:tags":[
        "cosmetic",
        "perfume"
    ],
    "wof:name":"Avon Training Ctr",
    "wof:placetype":"venue"
},
  "geometry": {"coordinates":[-96.976572,32.813722],"type":"Point"}
}