{
  "type": "Feature",
  "properties": {
    "iso:country":"US",
    "sg:address":"9600 S Interstate 35",
    "sg:city":"Austin",
    "sg:classifiers":[
        {
            "category":"Shopping",
            "subcategory":"Jewelry",
            "type":"Retail Goods"
        }
    ],
    "sg:phone":"+1 512 233 4200",
    "sg:postcode":"78748",
    "sg:province":"TX",
    "wof:name":"Hanna D's Southpark",
    "wof:placetype":"venue"
},
  "geometry": {"coordinates":[-97.755785,30.209392],"type":"Point"}
}