{
  "type": "Feature",
  "properties": {
    "iso:country":"US",
    "sg:address":"212 N Columbia Dr",
    "sg:city":"West Columbia",
    "sg:classifiers":[
        {
            "category":"Personal",
            "subcategory":"Beauty Salon",
            "type":"Services"
        }
    ],
    "sg:phone":"+1 979 345 6505",
    "sg:postcode":"77486",
    "sg:province":"TX",
    "wof:name":"Cooky's A Place For Great Hair",
    "wof:placetype":"venue"
},
  "geometry": {"coordinates":[-95.660107,29.150629],"type":"Point"}
}