{
  "type": "Feature",
  "properties": {
    "iso:country":"US",
    "sg:address":"4525 Club Estate Pl",
    "sg:city":"Mesquite",
    "sg:classifiers":[
        {
            "category":"Travel",
            "subcategory":"Travel Agent",
            "type":"Entertainment"
        }
    ],
    "sg:phone":"+1 972 270 1779",
    "sg:postcode":"75150",
    "sg:province":"TX",
    "sg:tags":[
        "agency",
        "bureau"
    ],
    "wof:name":"Have Keys Will Travel",
    "wof:placetype":"venue"
},
  "geometry": {"coordinates":[-96.634491,32.832878],"type":"Point"}
}