{
  "type": "Feature",
  "properties": {
    "iso:country":"US",
    "sg:address":"6401 Woodway Dr Ste 179",
    "sg:city":"Houston",
    "sg:classifiers":[
        {
            "category":"Retail",
            "subcategory":"Laundry & Dry Cleaning",
            "type":"Services"
        }
    ],
    "sg:phone":"+1 713 266 1096",
    "sg:postcode":"77057",
    "sg:province":"TX",
    "wof:name":"Twin Oaks Cleaners & Laundry",
    "wof:placetype":"venue"
},
  "geometry": {"coordinates":[-95.497902,29.7556],"type":"Point"}
}