{
  "type": "Feature",
  "properties": {
    "iso:country":"US",
    "sg:address":"5017 W Highway 290",
    "sg:city":"Austin",
    "sg:classifiers":[
        {
            "category":"Restaurant",
            "type":"Food & Drink"
        }
    ],
    "sg:phone":"+1 512 892 8780",
    "sg:postcode":"78735",
    "sg:province":"TX",
    "wof:name":"McDonald's",
    "wof:placetype":"venue"
},
  "geometry": {"coordinates":[-97.821819,30.236909],"type":"Point"}
}