{
  "type": "Feature",
  "properties": {
    "iso:country":"US",
    "sg:address":"6434 Phelan Blvd",
    "sg:city":"Beaumont",
    "sg:classifiers":[
        {
            "category":"Ice Cream",
            "type":"Food & Drink"
        }
    ],
    "sg:menulink":"http://www.allmenus.com/tx/beaumont/209351-tcby/menu/",
    "sg:phone":"+1 409 866 4545",
    "sg:postcode":"77706",
    "sg:province":"TX",
    "sg:tags":[
        "smoothy",
        "juice",
        "american"
    ],
    "wof:name":"TCBY",
    "wof:placetype":"venue"
},
  "geometry": {"coordinates":[-94.164135,30.080151],"type":"Point"}
}