{
  "type": "Feature",
  "properties": {
    "iso:country":"US",
    "sg:address":"5427 N Macarthur Blvd",
    "sg:city":"Irving",
    "sg:classifiers":[
        {
            "category":"Restaurant",
            "type":"Food & Drink"
        }
    ],
    "sg:menulink":"http://www.allmenus.com/tx/southwest/39305-currys/menu/",
    "sg:phone":"+1 972 518 0188",
    "sg:postcode":"75038",
    "sg:province":"TX",
    "sg:tags":[
        "indian",
        "asian"
    ],
    "wof:name":"Curry's",
    "wof:placetype":"venue"
},
  "geometry": {"coordinates":[-96.964657,32.884388],"type":"Point"}
}