{
  "type": "Feature",
  "properties": {
    "iso:country":"US",
    "sg:address":"2407 Daybreak Dr",
    "sg:city":"Dallas",
    "sg:classifiers":[
        {
            "category":"Freight",
            "type":"Transportation"
        }
    ],
    "sg:phone":"+1 972 307 0686",
    "sg:postcode":"75287",
    "sg:province":"TX",
    "sg:tags":[
        "terminal",
        "truck",
        "facility"
    ],
    "wof:name":"Jimmy F Ligon",
    "wof:placetype":"venue"
},
  "geometry": {"coordinates":[-96.87206399999999,32.991495],"type":"Point"}
}