{
  "type": "Feature",
  "properties": {
    "iso:country":"US",
    "sg:address":"4615 Bagpipe Ln",
    "sg:city":"Houston",
    "sg:classifiers":[
        {
            "category":"Shopping",
            "subcategory":"Music",
            "type":"Retail Goods"
        }
    ],
    "sg:phone":"+1 281 856 0094",
    "sg:postcode":"77084",
    "sg:province":"TX",
    "wof:name":"God Squad Records",
    "wof:placetype":"venue"
},
  "geometry": {"coordinates":[-95.649079,29.842874],"type":"Point"}
}