{
  "type": "Feature",
  "properties": {
    "iso:country":"US",
    "sg:address":"1808 Kipling Dr",
    "sg:city":"Flower Mound",
    "sg:classifiers":[
        {
            "category":"Wholesale",
            "subcategory":"Non-durable Goods",
            "type":"Manufacturing & Wholesale Goods"
        }
    ],
    "sg:phone":"+1 972 539 2107",
    "sg:postcode":"75022",
    "sg:province":"TX",
    "wof:name":"M & Js Trading LLC",
    "wof:placetype":"venue"
},
  "geometry": {"coordinates":[-97.081028,33.009406],"type":"Point"}
}