{
  "type": "Feature",
  "properties": {
    "iso:country":"US",
    "sg:address":"4600 Seton Center Pkwy",
    "sg:city":"Austin",
    "sg:classifiers":[
        {
            "category":"Retail",
            "subcategory":"Portrait Studio",
            "type":"Services"
        }
    ],
    "sg:phone":"+1 512 349 9175",
    "sg:postcode":"78759",
    "sg:province":"TX",
    "sg:tags":[
        "photo"
    ],
    "wof:name":"Leslie Pierce Photography",
    "wof:placetype":"venue"
},
  "geometry": {"coordinates":[-97.742313,30.400911],"type":"Point"}
}