{
  "type": "Feature",
  "properties": {
    "iso:country":"US",
    "sg:address":"157 S Graham St",
    "sg:city":"Stephenville",
    "sg:classifiers":[
        {
            "category":"Professional",
            "subcategory":"Lawyer & Legal Services",
            "type":"Services"
        }
    ],
    "sg:phone":"+1 877 804 3373",
    "sg:postcode":"76401",
    "sg:province":"TX",
    "sg:tags":[
        "attorney",
        "practice"
    ],
    "sg:website":"http://www.lewellenlaw.com",
    "wof:name":"Lewellen Law",
    "wof:placetype":"venue"
},
  "geometry": {"coordinates":[-98.20192299999999,32.220275],"type":"Point"}
}