{
  "type": "Feature",
  "properties": {
    "iso:country":"US",
    "sg:address":"3813 Darrell Ln",
    "sg:city":"Tyler",
    "sg:classifiers":[
        {
            "category":"Building & Trades",
            "subcategory":"Construction",
            "type":"Services"
        }
    ],
    "sg:phone":"+1 903 597 2132",
    "sg:postcode":"75701",
    "sg:province":"TX",
    "sg:tags":[
        "hanging",
        "contractor"
    ],
    "wof:name":"Do-All Roofing & Painting",
    "wof:placetype":"venue"
},
  "geometry": {"coordinates":[-95.31666800000001,32.306767],"type":"Point"}
}