{
  "type": "Feature",
  "properties": {
    "iso:country":"US",
    "sg:address":"1139 Basse Rd",
    "sg:city":"San Antonio",
    "sg:classifiers":[
        {
            "category":"Retail",
            "subcategory":"Auto Repair",
            "type":"Services"
        }
    ],
    "sg:phone":"+1 210 785 9929",
    "sg:postcode":"78212",
    "sg:province":"TX",
    "sg:tags":[
        "body",
        "automobile",
        "painting"
    ],
    "wof:name":"Collision Master",
    "wof:placetype":"venue"
},
  "geometry": {"coordinates":[-98.50213100000001,29.488232],"type":"Point"}
}