{
  "type": "Feature",
  "properties": {
    "iso:country":"US",
    "sg:address":"1516 N Sylvania Ave",
    "sg:city":"Fort Worth",
    "sg:classifiers":[
        {
            "category":"Organizations",
            "subcategory":"Religious Organization",
            "type":"Services"
        }
    ],
    "sg:phone":"+1 817 834 6290",
    "sg:postcode":"76111",
    "sg:province":"TX",
    "sg:tags":[
        "church"
    ],
    "wof:name":"Iglesia Cristiana Camino Depaz",
    "wof:placetype":"venue"
},
  "geometry": {"coordinates":[-97.308577,32.783007],"type":"Point"}
}