{
  "type": "Feature",
  "properties": {
    "iso:country":"US",
    "sg:address":"6114 Dusty Trl",
    "sg:city":"San Antonio",
    "sg:classifiers":[
        {
            "category":"Professional",
            "subcategory":"Computer Services",
            "type":"Services"
        }
    ],
    "sg:phone":"+1 210 416 1642",
    "sg:postcode":"78249",
    "sg:province":"TX",
    "sg:tags":[
        "hardware",
        "peripheral",
        "adaptive",
        "for",
        "software"
    ],
    "wof:name":"Vision Technology Resources",
    "wof:placetype":"venue"
},
  "geometry": {"coordinates":[-98.607821,29.564232],"type":"Point"}
}