{
  "type": "Feature",
  "properties": {
    "iso:country":"US",
    "sg:address":"10 Business Dr",
    "sg:city":"Brownsville",
    "sg:classifiers":[
        {
            "category":"Building & Trades",
            "subcategory":"Construction",
            "type":"Services"
        }
    ],
    "sg:phone":"+1 956 541 1309",
    "sg:postcode":"78521",
    "sg:province":"TX",
    "sg:tags":[
        "designer",
        "dealer",
        "pool",
        "swimming"
    ],
    "sg:website":"www.berrypool.com",
    "wof:name":"Berry Pool & Supply",
    "wof:placetype":"venue"
},
  "geometry": {"coordinates":[-97.471598,25.92457],"type":"Point"}
}