{
  "type": "Feature",
  "properties": {
    "iso:country":"US",
    "sg:address":"2813 Aberdeen Dr",
    "sg:city":"Flower Mound",
    "sg:classifiers":[
        {
            "category":"Wholesale",
            "subcategory":"Farm Supplies",
            "type":"Manufacturing & Wholesale Goods"
        }
    ],
    "sg:phone":"+1 972 724 0120",
    "sg:postcode":"75022",
    "sg:province":"TX",
    "wof:name":"Ecnerwal International",
    "wof:placetype":"venue"
},
  "geometry": {"coordinates":[-97.07493599999999,33.001377],"type":"Point"}
}