{
  "type": "Feature",
  "properties": {
    "iso:country":"US",
    "sg:address":"2510 S Belt Line Rd",
    "sg:city":"Grand Prairie",
    "sg:classifiers":[
        {
            "category":"Personal",
            "subcategory":"Beauty Salon",
            "type":"Services"
        }
    ],
    "sg:phone":"+1 972 264 3323",
    "sg:postcode":"75052",
    "sg:province":"TX",
    "wof:name":"Rumors Hair Studio",
    "wof:placetype":"venue"
},
  "geometry": {"coordinates":[-96.994106,32.707232],"type":"Point"}
}