{
  "type": "Feature",
  "properties": {
    "iso:country":"US",
    "sg:address":"1917 American Dr",
    "sg:city":"Leander",
    "sg:classifiers":[
        {
            "category":"Wholesale",
            "subcategory":"Sporting Goods",
            "type":"Manufacturing & Wholesale Goods"
        }
    ],
    "sg:phone":"+1 512 267 2002",
    "sg:postcode":"78645",
    "sg:province":"TX",
    "sg:tags":[
        "s"
    ],
    "wof:name":"Precision Watercraft Rental",
    "wof:placetype":"venue"
},
  "geometry": {"coordinates":[-98.015496,30.418004],"type":"Point"}
}