{
  "type": "Feature",
  "properties": {
    "iso:country":"US",
    "sg:address":"201 Vernon Ave",
    "sg:city":"Lubbock",
    "sg:classifiers":[
        {
            "category":"Education",
            "subcategory":"School",
            "type":"Public Place"
        }
    ],
    "sg:phone":"+1 806 766 1766",
    "sg:postcode":"79415",
    "sg:province":"TX",
    "wof:name":"Jackson Elementary School",
    "wof:placetype":"venue"
},
  "geometry": {"coordinates":[-101.865154,33.59511],"type":"Point"}
}