{
  "type": "Feature",
  "properties": {
    "iso:country":"US",
    "sg:address":"2627 S Cooper St",
    "sg:city":"Arlington",
    "sg:classifiers":[
        {
            "category":"Building & Trades",
            "subcategory":"Construction",
            "type":"Services"
        }
    ],
    "sg:phone":"+1 817 792 3292",
    "sg:postcode":"76015",
    "sg:province":"TX",
    "sg:tags":[
        "concrete",
        "contractor",
        "carpentry"
    ],
    "wof:name":"Oldcastle Architectural W Inc",
    "wof:placetype":"venue"
},
  "geometry": {"coordinates":[-97.122164,32.699985],"type":"Point"}
}