{
  "type": "Feature",
  "properties": {
    "iso:country":"US",
    "sg:address":"5016 Miller Ave",
    "sg:city":"Dallas",
    "sg:classifiers":[
        {
            "category":"Home & Garden",
            "subcategory":"Garden Supply",
            "type":"Retail Goods"
        }
    ],
    "sg:phone":"+1 214 824 7277",
    "sg:postcode":"75206",
    "sg:province":"TX",
    "wof:name":"Sticks and Stones Garden Mkt",
    "wof:placetype":"venue"
},
  "geometry": {"coordinates":[-96.782517,32.821185],"type":"Point"}
}