{
  "type": "Feature",
  "properties": {
    "iso:country":"US",
    "sg:address":"13251 Stable Rd",
    "sg:city":"El Paso",
    "sg:classifiers":[
        {
            "category":"Organizations",
            "subcategory":"Religious Organization",
            "type":"Services"
        }
    ],
    "sg:phone":"+1 915 849 9023",
    "sg:postcode":"79938",
    "sg:province":"TX",
    "wof:name":"Templo Crstano Pdroso Guerroro",
    "wof:placetype":"venue"
},
  "geometry": {"coordinates":[-106.230616,31.820748],"type":"Point"}
}