{
  "type": "Feature",
  "properties": {
    "iso:country":"US",
    "sg:address":"1705 Pebble Run Dr",
    "sg:city":"Allen",
    "sg:classifiers":[
        {
            "category":"Professional",
            "subcategory":"Computer Services",
            "type":"Services"
        }
    ],
    "sg:phone":"+1 972 727 6871",
    "sg:postcode":"75002",
    "sg:province":"TX",
    "sg:tags":[
        "related"
    ],
    "wof:name":"Jjp Consulting",
    "wof:placetype":"venue"
},
  "geometry": {"coordinates":[-96.63349599999999,33.127124],"type":"Point"}
}