{
  "type": "Feature",
  "properties": {
    "iso:country":"US",
    "sg:address":"604 Havencrest Dr",
    "sg:city":"Desoto",
    "sg:classifiers":[
        {
            "category":"Education",
            "subcategory":"Special Training",
            "type":"Public Place"
        }
    ],
    "sg:phone":"+1 972 230 2201",
    "sg:postcode":"75115",
    "sg:province":"TX",
    "sg:tags":[
        "educational"
    ],
    "wof:name":"Educational Diagnostics",
    "wof:placetype":"venue"
},
  "geometry": {"coordinates":[-96.840284,32.599765],"type":"Point"}
}