{
  "type": "Feature",
  "properties": {
    "iso:country":"US",
    "sg:address":"2303 Edison Dr",
    "sg:city":"San Antonio",
    "sg:classifiers":[
        {
            "category":"Real Estate",
            "subcategory":"Real Estate Agent",
            "type":"Services"
        }
    ],
    "sg:phone":"+1 210 732 9102",
    "sg:postcode":"78201",
    "sg:province":"TX",
    "wof:name":"Crown Properties",
    "wof:placetype":"venue"
},
  "geometry": {"coordinates":[-98.534145,29.472641],"type":"Point"}
}