{
  "type": "Feature",
  "properties": {
    "iso:country":"US",
    "sg:address":"3121 Rosedale St",
    "sg:city":"Houston",
    "sg:classifiers":[
        {
            "category":"Wholesale",
            "subcategory":"Apparel",
            "type":"Manufacturing & Wholesale Goods"
        }
    ],
    "sg:phone":"+1 713 526 3265",
    "sg:postcode":"77004",
    "sg:province":"TX",
    "sg:tags":[
        "footwear"
    ],
    "wof:name":"Fes Emporium",
    "wof:placetype":"venue"
},
  "geometry": {"coordinates":[-95.368793,29.72008],"type":"Point"}
}