{
  "type": "Feature",
  "properties": {
    "iso:country":"US",
    "sg:address":"15102 Jones Maltsberger Rd",
    "sg:city":"San Antonio",
    "sg:classifiers":[
        {
            "category":"Insurance",
            "subcategory":"Insurance Agent",
            "type":"Services"
        }
    ],
    "sg:phone":"+1 210 496 1963",
    "sg:postcode":"78247",
    "sg:province":"TX",
    "wof:name":"Rayner Insurance Services",
    "wof:placetype":"venue"
},
  "geometry": {"coordinates":[-98.43966899999999,29.580234],"type":"Point"}
}