{
  "type": "Feature",
  "properties": {
    "iso:country":"US",
    "sg:address":"4513 Foxfire Way",
    "sg:city":"Fort Worth",
    "sg:classifiers":[
        {
            "category":"Professional",
            "subcategory":"Business Services",
            "type":"Services"
        }
    ],
    "sg:phone":"+1 817 346 9030",
    "sg:postcode":"76133",
    "sg:province":"TX",
    "wof:name":"Grays Auction",
    "wof:placetype":"venue"
},
  "geometry": {"coordinates":[-97.39037,32.64439],"type":"Point"}
}