{
  "type": "Feature",
  "properties": {
    "iso:country":"US",
    "sg:address":"146 Guadalupe St",
    "sg:city":"San Antonio",
    "sg:classifiers":[
        {
            "category":"Wholesale",
            "subcategory":"Furniture",
            "type":"Manufacturing & Wholesale Goods"
        }
    ],
    "sg:phone":"+1 210 226 1092",
    "sg:postcode":"78204",
    "sg:province":"TX",
    "wof:name":"J D L Custom Office Furniture",
    "wof:placetype":"venue"
},
  "geometry": {"coordinates":[-98.500924,29.416723],"type":"Point"}
}