{
  "type": "Feature",
  "properties": {
    "iso:country":"US",
    "sg:address":"2810 N O Connor Rd",
    "sg:city":"Irving",
    "sg:classifiers":[
        {
            "category":"Food & Beverages",
            "subcategory":"Groceries & Convenience Stores",
            "type":"Retail Goods"
        }
    ],
    "sg:phone":"+1 972 570 8612",
    "sg:postcode":"75062",
    "sg:province":"TX",
    "sg:tags":[
        "grocer"
    ],
    "wof:name":"Bharat Bazar",
    "wof:placetype":"venue"
},
  "geometry": {"coordinates":[-96.951122,32.844698],"type":"Point"}
}