{
  "type": "Feature",
  "properties": {
    "iso:country":"US",
    "sg:address":"607 Parsons St",
    "sg:city":"San Angelo",
    "sg:classifiers":[
        {
            "category":"Real Estate",
            "subcategory":"Real Estate Operator",
            "type":"Services"
        }
    ],
    "sg:phone":"+1 325 659 4567",
    "sg:postcode":"76903",
    "sg:province":"TX",
    "sg:tags":[
        "building",
        "apartment"
    ],
    "wof:name":"Appletree Apartments",
    "wof:placetype":"venue"
},
  "geometry": {"coordinates":[-100.42349,31.454915],"type":"Point"}
}