{
  "type": "Feature",
  "properties": {
    "iso:country":"US",
    "sg:address":"1221 W Ben White Blvd",
    "sg:city":"Austin",
    "sg:classifiers":[
        {
            "category":"Health Services",
            "subcategory":"Doctor",
            "type":"Services"
        },
        {
            "category":"Social Services",
            "type":"Services"
        },
        {
            "category":"Personal",
            "type":"Services"
        },
        {
            "category":"Health Services",
            "subcategory":"Health Practitioner",
            "type":"Services"
        }
    ],
    "sg:phone":"+1 512 842 2223",
    "sg:postcode":"78704",
    "sg:province":"TX",
    "sg:tags":[
        "family",
        "psychotherapist",
        "psychologist",
        "individual",
        "marriage",
        "child",
        "counseling",
        "counselor"
    ],
    "sg:website":"http://www.catherine-ford.com",
    "wof:name":"Ford, Catherine M. PhD",
    "wof:placetype":"venue"
},
  "geometry": {"coordinates":[-97.77904100000001,30.227408],"type":"Point"}
}