{
  "type": "Feature",
  "properties": {
    "iso:country":"US",
    "sg:address":"1101 Alma St",
    "sg:city":"Tomball",
    "sg:classifiers":[
        {
            "category":"Health Services",
            "subcategory":"Doctor",
            "type":"Services"
        },
        {
            "category":"Health Services",
            "subcategory":"Clinic",
            "type":"Services"
        }
    ],
    "sg:phone":"+1 281 290 0018",
    "sg:postcode":"77375",
    "sg:province":"TX",
    "sg:tags":[
        "physician",
        "family",
        "practice",
        "surgeons",
        "medicine",
        "surgeon"
    ],
    "wof:name":"Tomball Primary Care Pa",
    "wof:placetype":"venue"
},
  "geometry": {"coordinates":[-95.626312,30.090469],"type":"Point"}
}