{
  "type": "Feature",
  "properties": {
    "iso:country":"US",
    "sg:address":"2403 Rigsby Ave",
    "sg:city":"San Antonio",
    "sg:classifiers":[
        {
            "category":"Organizations",
            "subcategory":"Religious Organization",
            "type":"Services"
        }
    ],
    "sg:phone":"+1 210 337 7250",
    "sg:postcode":"78222",
    "sg:province":"TX",
    "wof:name":"True Light Baptist Church",
    "wof:placetype":"venue"
},
  "geometry": {"coordinates":[-98.420709,29.39944],"type":"Point"}
}