{
  "type": "Feature",
  "properties": {
    "iso:country":"US",
    "sg:address":"5715 Will Clayton, #2837",
    "sg:city":"Humble",
    "sg:classifiers":[
        {
            "category":"Professional",
            "subcategory":"Computer Services",
            "type":"Services"
        }
    ],
    "sg:phone":"+1 877 353 7297",
    "sg:postcode":"77338",
    "sg:province":"TX",
    "sg:tags":[
        "utilites-software"
    ],
    "sg:website":"http://www.spotmau.com",
    "wof:name":"Spotmau Corporation",
    "wof:placetype":"venue"
},
  "geometry": {"coordinates":[-95.304777,29.984638],"type":"Point"}
}