{
  "type": "Feature",
  "properties": {
    "iso:country":"US",
    "sg:address":"1401 N 13th St",
    "sg:city":"Ballinger",
    "sg:classifiers":[
        {
            "category":"Government",
            "subcategory":"Office",
            "type":"Public Place"
        }
    ],
    "sg:phone":"+1 325 365 2629",
    "sg:postcode":"76821",
    "sg:province":"TX",
    "sg:tags":[
        "housing",
        "program"
    ],
    "wof:name":"Ballinger Housing Authority",
    "wof:placetype":"venue"
},
  "geometry": {"coordinates":[-99.96670899999999,31.743295],"type":"Point"}
}