{
  "type": "Feature",
  "properties": {
    "iso:country":"US",
    "sg:address":"2909 Cole Ave Suite 120",
    "sg:city":"Dallas",
    "sg:classifiers":[
        {
            "category":"Education",
            "subcategory":"Special Training",
            "type":"Public Place"
        },
        {
            "category":"Communications",
            "type":"Services"
        }
    ],
    "sg:phone":"+1 214 871 2909",
    "sg:postcode":"75204",
    "sg:province":"TX",
    "sg:tags":[
        "translator",
        "interpreter",
        "school",
        "language"
    ],
    "sg:website":"http://oneworldlanguage.com",
    "wof:name":"OneWorld Language Solutions",
    "wof:placetype":"venue"
},
  "geometry": {"coordinates":[-96.802393,32.801874],"type":"Point"}
}