{
  "type": "Feature",
  "properties": {
    "iso:country":"US",
    "sg:address":"125 Avant Garde Dr",
    "sg:city":"Victoria",
    "sg:classifiers":[
        {
            "category":"Professional",
            "type":"Services"
        }
    ],
    "sg:phone":"+1 361 576 0421",
    "sg:postcode":"77901",
    "sg:province":"TX",
    "wof:name":"Eccentricities",
    "wof:placetype":"venue"
},
  "geometry": {"coordinates":[-96.98379799999999,28.836091],"type":"Point"}
}