{
  "type": "Feature",
  "properties": {
    "iso:country":"US",
    "sg:address":"14996 Northwest Fwy",
    "sg:city":"Houston",
    "sg:classifiers":[
        {
            "category":"Travel",
            "subcategory":"Hotels & Motels",
            "type":"Entertainment"
        }
    ],
    "sg:phone":"+1 713 939 9955",
    "sg:postcode":"77040",
    "sg:province":"TX",
    "sg:website":"www.preetbanquethalls.com",
    "wof:name":"Hotel Preet",
    "wof:placetype":"venue"
},
  "geometry": {"coordinates":[-95.54871199999999,29.871019],"type":"Point"}
}