{
  "type": "Feature",
  "properties": {
    "iso:country":"US",
    "sg:address":"327 Krajca Rd",
    "sg:city":"Ennis",
    "sg:classifiers":[
        {
            "category":"Professional",
            "type":"Services"
        }
    ],
    "sg:phone":"+1 972 646 5119",
    "sg:postcode":"75119",
    "sg:province":"TX",
    "wof:name":"Susan Hamm",
    "wof:placetype":"venue"
},
  "geometry": {"coordinates":[-96.68423300000001,32.248681],"type":"Point"}
}