{
  "type": "Feature",
  "properties": {
    "iso:country":"US",
    "sg:address":"7118 Blackberry Dr",
    "sg:city":"Arlington",
    "sg:classifiers":[
        {
            "category":"Building & Trades",
            "subcategory":"Construction",
            "type":"Services"
        }
    ],
    "sg:phone":"+1 817 561 1750",
    "sg:postcode":"76016",
    "sg:province":"TX",
    "sg:tags":[
        "roofing",
        "contractor"
    ],
    "wof:name":"Apex Roofing",
    "wof:placetype":"venue"
},
  "geometry": {"coordinates":[-97.217792,32.676513],"type":"Point"}
}