{
  "type": "Feature",
  "properties": {
    "iso:country":"US",
    "sg:address":"1208 N Copia St",
    "sg:city":"El Paso",
    "sg:classifiers":[
        {
            "category":"Autos & Motor Vehicles",
            "subcategory":"Auto Supplies",
            "type":"Retail Goods"
        }
    ],
    "sg:phone":"+1 915 565 2997",
    "sg:postcode":"79903",
    "sg:province":"TX",
    "sg:tags":[
        "station",
        "gasoline"
    ],
    "wof:name":"Campos Garage",
    "wof:placetype":"venue"
},
  "geometry": {"coordinates":[-106.45139399999999,31.787064],"type":"Point"}
}