{
  "type": "Feature",
  "properties": {
    "iso:country":"US",
    "sg:address":"325 Wenrick Dr",
    "sg:city":"Roanoke",
    "sg:classifiers":[
        {
            "category":"Professional",
            "subcategory":"Computer Services",
            "type":"Services"
        }
    ],
    "sg:phone":"+1 817 308 9953",
    "sg:postcode":"76262",
    "sg:province":"TX",
    "sg:tags":[
        "consulting"
    ],
    "wof:name":"Combay Inc",
    "wof:placetype":"venue"
},
  "geometry": {"coordinates":[-97.212321,33.016967],"type":"Point"}
}