{
  "type": "Feature",
  "properties": {
    "iso:country":"US",
    "sg:address":"1315 Hyde Park Blvd",
    "sg:city":"Houston",
    "sg:classifiers":[
        {
            "category":"Government",
            "subcategory":"Post Office",
            "type":"Public Place"
        }
    ],
    "sg:phone":"+1 713 522 3897",
    "sg:postcode":"77006",
    "sg:province":"TX",
    "sg:tags":[
        "postal",
        "us"
    ],
    "wof:name":"Fairview Station",
    "wof:placetype":"venue"
},
  "geometry": {"coordinates":[-95.394137,29.747221],"type":"Point"}
}