{
  "type": "Feature",
  "properties": {
    "iso:country":"US",
    "sg:address":"803 S Ross Ave",
    "sg:city":"Mexia",
    "sg:classifiers":[
        {
            "category":"Education",
            "subcategory":"School",
            "type":"Public Place"
        }
    ],
    "sg:phone":"+1 254 562 5050",
    "sg:postcode":"76667",
    "sg:province":"TX",
    "wof:name":"Living Word Academy",
    "wof:placetype":"venue"
},
  "geometry": {"coordinates":[-96.47283,31.674571],"type":"Point"}
}