{
  "type": "Feature",
  "properties": {
    "iso:country":"US",
    "sg:address":"4641 Lasater Rd",
    "sg:city":"Mesquite",
    "sg:classifiers":[
        {
            "category":"Professional",
            "type":"Services"
        }
    ],
    "sg:phone":"+1 972 849 2673",
    "sg:postcode":"75181",
    "sg:province":"TX",
    "wof:name":"Morhar Inc",
    "wof:placetype":"venue"
},
  "geometry": {"coordinates":[-96.580895,32.708556],"type":"Point"}
}