{
  "type": "Feature",
  "properties": {
    "iso:country":"US",
    "sg:address":"1544 Sawdust Rd",
    "sg:city":"Spring",
    "sg:classifiers":[
        {
            "category":"Manufacturing",
            "subcategory":"Metals",
            "type":"Manufacturing & Wholesale Goods"
        }
    ],
    "sg:phone":"+1 281 292 7868",
    "sg:postcode":"77380",
    "sg:province":"TX",
    "wof:name":"Bakertron",
    "wof:placetype":"venue"
},
  "geometry": {"coordinates":[-95.46709199999999,30.126339],"type":"Point"}
}