{
  "type": "Feature",
  "properties": {
    "iso:country":"US",
    "sg:address":"4603 Ave Florencia",
    "sg:city":"Brownsville",
    "sg:classifiers":[
        {
            "category":"Retail",
            "subcategory":"Auto Repair",
            "type":"Services"
        },
        {
            "category":"Wholesale",
            "subcategory":"Fruits & Vegetables",
            "type":"Manufacturing & Wholesale Goods"
        }
    ],
    "sg:phone":"+1 956 504 6307",
    "sg:postcode":"78526",
    "sg:province":"TX",
    "sg:tags":[
        "repairing",
        "automobile"
    ],
    "wof:name":"Auto Service Guvaz",
    "wof:placetype":"venue"
},
  "geometry": {"coordinates":[-97.482632,25.972986],"type":"Point"}
}