{
  "type": "Feature",
  "properties": {
    "iso:country":"US",
    "sg:address":"6020 Hidden Sunrise Dr",
    "sg:city":"San Antonio",
    "sg:classifiers":[
        {
            "category":"Building & Trades",
            "subcategory":"Construction",
            "type":"Services"
        }
    ],
    "sg:phone":"+1 210 661 7593",
    "sg:postcode":"78244",
    "sg:province":"TX",
    "sg:tags":[
        "contractor"
    ],
    "wof:name":"Pow Pressure Cleaning",
    "wof:placetype":"venue"
},
  "geometry": {"coordinates":[-98.364999,29.464116],"type":"Point"}
}