{
  "type": "Feature",
  "properties": {
    "iso:country":"US",
    "sg:address":"4400 W Co Rd 116",
    "sg:city":"Midland",
    "sg:classifiers":[
        {
            "category":"Building & Trades",
            "subcategory":"Plumbing",
            "type":"Services"
        }
    ],
    "sg:phone":"+1 432 520 5294",
    "sg:postcode":"79706",
    "sg:province":"TX",
    "sg:tags":[
        "plumbing",
        "contractor"
    ],
    "wof:name":"Atlantis Plumbing & AC",
    "wof:placetype":"venue"
},
  "geometry": {"coordinates":[-102.121146,31.951957],"type":"Point"}
}