{
  "type": "Feature",
  "properties": {
    "iso:country":"US",
    "sg:address":"16835 Deer Creek Dr",
    "sg:city":"Spring",
    "sg:classifiers":[
        {
            "category":"Utilities",
            "subcategory":"Mobile Phone",
            "type":"Services"
        }
    ],
    "sg:phone":"+1 281 374 8605",
    "sg:postcode":"77379",
    "sg:province":"TX",
    "sg:tags":[
        "communication",
        "telephone",
        "cellular",
        "radiotelephone"
    ],
    "wof:name":"Nextel Partners Inc",
    "wof:placetype":"venue"
},
  "geometry": {"coordinates":[-95.52199299999999,30.022883],"type":"Point"}
}