{
  "type": "Feature",
  "properties": {
    "iso:country":"US",
    "sg:address":"2500 Judson Rd",
    "sg:city":"Longview",
    "sg:classifiers":[
        {
            "category":"Professional",
            "subcategory":"Lawyer & Legal Services",
            "type":"Services"
        }
    ],
    "sg:phone":"+1 903 236 4411",
    "sg:postcode":"75605",
    "sg:province":"TX",
    "sg:tags":[
        "attorney"
    ],
    "wof:name":"Jon K Hudgens Law Office",
    "wof:placetype":"venue"
},
  "geometry": {"coordinates":[-94.745408,32.539321],"type":"Point"}
}