{
  "type": "Feature",
  "properties": {
    "iso:country":"US",
    "sg:address":"75 N Crossed Birch Pl",
    "sg:city":"Spring",
    "sg:classifiers":[
        {
            "category":"Wholesale",
            "subcategory":"Non-durable Goods",
            "type":"Manufacturing & Wholesale Goods"
        }
    ],
    "sg:phone":"+1 281 321 5213",
    "sg:postcode":"77381",
    "sg:province":"TX",
    "wof:name":"Russell Distributions",
    "wof:placetype":"venue"
},
  "geometry": {"coordinates":[-95.50925599999999,30.198251],"type":"Point"}
}