{
  "type": "Feature",
  "properties": {
    "iso:country":"US",
    "sg:address":"618 Chestnut Dr",
    "sg:city":"Grand Prairie",
    "sg:classifiers":[
        {
            "category":"Professional",
            "type":"Services"
        }
    ],
    "sg:phone":"+1 972 262 0216",
    "sg:postcode":"75052",
    "sg:province":"TX",
    "wof:name":"Kitchen Bernadine",
    "wof:placetype":"venue"
},
  "geometry": {"coordinates":[-97.001428,32.68473],"type":"Point"}
}