{
  "type": "Feature",
  "properties": {
    "iso:country":"US",
    "sg:address":"103 January Ln",
    "sg:city":"Lufkin",
    "sg:classifiers":[
        {
            "category":"Arts & Performance",
            "subcategory":"Art Gallery",
            "type":"Entertainment"
        }
    ],
    "sg:phone":"+1 936 632 3618",
    "sg:postcode":"75904",
    "sg:province":"TX",
    "sg:tags":[
        "fine",
        "artist"
    ],
    "wof:name":"Ann Reyes Phifer",
    "wof:placetype":"venue"
},
  "geometry": {"coordinates":[-94.764207,31.323697],"type":"Point"}
}