{
  "type": "Feature",
  "properties": {
    "iso:country":"US",
    "sg:address":"1712 W Dallas St",
    "sg:city":"Houston",
    "sg:classifiers":[
        {
            "category":"Autos & Motor Vehicles",
            "subcategory":"Auto Supplies",
            "type":"Retail Goods"
        },
        {
            "category":"Retail",
            "subcategory":"Auto Repair",
            "type":"Services"
        }
    ],
    "sg:phone":"+1 713 658 1754",
    "sg:postcode":"77019",
    "sg:province":"TX",
    "sg:tags":[
        "body",
        "shop",
        "tire"
    ],
    "wof:name":"Aquilina Tire & Supply",
    "wof:placetype":"venue"
},
  "geometry": {"coordinates":[-95.3843,29.757799],"type":"Point"}
}