{
  "type": "Feature",
  "properties": {
    "iso:country":"US",
    "sg:address":"112 E New St",
    "sg:city":"Eastland",
    "sg:classifiers":[
        {
            "category":"Wholesale",
            "subcategory":"Groceries",
            "type":"Manufacturing & Wholesale Goods"
        }
    ],
    "sg:phone":"+1 254 629 8738",
    "sg:postcode":"76448",
    "sg:province":"TX",
    "sg:tags":[
        "confectionery"
    ],
    "wof:name":"Frito-Lay",
    "wof:placetype":"venue"
},
  "geometry": {"coordinates":[-98.818018,32.387448],"type":"Point"}
}