{
  "type": "Feature",
  "properties": {
    "iso:country":"US",
    "sg:address":"6611 Pino Real Dr",
    "sg:city":"El Paso",
    "sg:classifiers":[
        {
            "category":"Real Estate",
            "subcategory":"Real Estate Agent",
            "type":"Services"
        }
    ],
    "sg:phone":"+1 915 533 9292",
    "sg:postcode":"79912",
    "sg:province":"TX",
    "wof:name":"J W Fitzgerald Realtors Inc",
    "wof:placetype":"venue"
},
  "geometry": {"coordinates":[-106.53795,31.844806],"type":"Point"}
}