{
  "type": "Feature",
  "properties": {
    "iso:country":"US",
    "sg:address":"2615 Market St",
    "sg:city":"Baytown",
    "sg:classifiers":[
        {
            "category":"Place Of Worship",
            "type":"Public Place"
        }
    ],
    "sg:phone":"+1 281 428 2302",
    "sg:postcode":"77520",
    "sg:province":"TX",
    "sg:tags":[
        "church"
    ],
    "wof:name":"Iglesia Metodista Unida",
    "wof:placetype":"venue"
},
  "geometry": {"coordinates":[-94.99912,29.72726],"type":"Point"}
}