{
  "type": "Feature",
  "properties": {
    "iso:country":"US",
    "sg:address":"1318 W 20th St",
    "sg:city":"Odessa",
    "sg:classifiers":[
        {
            "category":"Professional",
            "subcategory":"Accounting & Tax Preparation",
            "type":"Services"
        }
    ],
    "sg:phone":"+1 432 333 4348",
    "sg:postcode":"79763",
    "sg:province":"TX",
    "sg:tags":[
        "return"
    ],
    "wof:name":"Fierro Tax Svc",
    "wof:placetype":"venue"
},
  "geometry": {"coordinates":[-102.396145,31.856101],"type":"Point"}
}