{
  "type": "Feature",
  "properties": {
    "iso:country":"US",
    "sg:address":"16375 Jacintoport Blvd",
    "sg:city":"Houston",
    "sg:classifiers":[
        {
            "category":"Professional",
            "type":"Services"
        }
    ],
    "sg:phone":"+1 281 452 3123",
    "sg:postcode":"77015",
    "sg:province":"TX",
    "sg:tags":[
        "establishment"
    ],
    "wof:name":"Houston Jacinto Port Blvd",
    "wof:placetype":"venue"
},
  "geometry": {"coordinates":[-95.11560799999999,29.747796],"type":"Point"}
}