{
  "type": "Feature",
  "properties": {
    "iso:country":"US",
    "sg:address":"404 S Main St",
    "sg:city":"Perryton",
    "sg:classifiers":[
        {
            "category":"Shopping",
            "subcategory":"Gifts & Souvenirs",
            "type":"Retail Goods"
        }
    ],
    "sg:phone":"+1 806 435 4126",
    "sg:postcode":"79070",
    "sg:province":"TX",
    "sg:tags":[
        "shop"
    ],
    "wof:name":"Charlotte & Co",
    "wof:placetype":"venue"
},
  "geometry": {"coordinates":[-100.802753,36.396399],"type":"Point"}
}