{
  "type": "Feature",
  "properties": {
    "iso:country":"US",
    "sg:address":"851 Old Alice Rd",
    "sg:city":"Brownsville",
    "sg:classifiers":[
        {
            "category":"Social Services",
            "subcategory":"Job Training",
            "type":"Services"
        }
    ],
    "sg:phone":"+1 956 546 3141",
    "sg:postcode":"78520",
    "sg:province":"TX",
    "sg:tags":[
        "rehab",
        "government"
    ],
    "wof:name":"Texas Workforce Commission",
    "wof:placetype":"venue"
},
  "geometry": {"coordinates":[-97.49846100000001,25.932319],"type":"Point"}
}