{
  "type": "Feature",
  "properties": {
    "iso:country":"US",
    "sg:address":"4009 Benoit Dr",
    "sg:city":"Plano",
    "sg:classifiers":[
        {
            "category":"Professional",
            "subcategory":"Engineering",
            "type":"Services"
        }
    ],
    "sg:phone":"+1 972 712 8101",
    "sg:postcode":"75024",
    "sg:province":"TX",
    "wof:name":"Quantum Business Solution",
    "wof:placetype":"venue"
},
  "geometry": {"coordinates":[-96.77262,33.086689],"type":"Point"}
}