{
  "type": "Feature",
  "properties": {
    "iso:country":"US",
    "sg:address":"12115 State Hwy 107",
    "sg:city":"Adkins",
    "sg:classifiers":[
        {
            "category":"Freight",
            "type":"Transportation"
        }
    ],
    "sg:phone":"+1 361 649 2447",
    "sg:postcode":"78101",
    "sg:province":"TX",
    "sg:tags":[
        "operator",
        "trucking"
    ],
    "wof:name":"Jerry Huggins Trnsp Svcs",
    "wof:placetype":"venue"
},
  "geometry": {"coordinates":[-98.24510100000001,29.367209],"type":"Point"}
}