{
  "type": "Feature",
  "properties": {
    "iso:country":"US",
    "sg:address":"6418 Laura Koppe Rd",
    "sg:city":"Houston",
    "sg:classifiers":[
        {
            "category":"Health Services",
            "subcategory":"Doctor",
            "type":"Services"
        }
    ],
    "sg:phone":"+1 713 633 7360",
    "sg:postcode":"77016",
    "sg:province":"TX",
    "sg:tags":[
        "dentist"
    ],
    "wof:name":"Glasper Voris W Inc",
    "wof:placetype":"venue"
},
  "geometry": {"coordinates":[-95.305397,29.840599],"type":"Point"}
}