{
  "type": "Feature",
  "properties": {
    "iso:country":"US",
    "sg:address":"1215 San Francisco St",
    "sg:city":"San Antonio",
    "sg:classifiers":[
        {
            "category":"Building & Trades",
            "subcategory":"Plumbing",
            "type":"Services"
        }
    ],
    "sg:phone":"+1 210 735 9235",
    "sg:postcode":"78201",
    "sg:province":"TX",
    "sg:tags":[
        "control",
        "c",
        "system",
        "heating",
        "ventilation",
        "conditioning",
        "air"
    ],
    "wof:name":"GILLETTE MECHANICAL",
    "wof:placetype":"venue"
},
  "geometry": {"coordinates":[-98.513803,29.468781],"type":"Point"}
}