{
  "type": "Feature",
  "properties": {
    "iso:country":"US",
    "sg:address":"15602 Sandtrap Dr",
    "sg:city":"Waller",
    "sg:classifiers":[
        {
            "category":"Personal",
            "subcategory":"Beauty Salon",
            "type":"Services"
        }
    ],
    "sg:phone":"+1 936 372 3809",
    "sg:postcode":"77484",
    "sg:province":"TX",
    "wof:name":"Envision Salon",
    "wof:placetype":"venue"
},
  "geometry": {"coordinates":[-95.93341100000001,29.999969],"type":"Point"}
}