{
  "type": "Feature",
  "properties": {
    "iso:country":"US",
    "sg:address":"2833 Fox Glen Dr",
    "sg:city":"Mesquite",
    "sg:classifiers":[
        {
            "category":"Home & Garden",
            "subcategory":"Hardware",
            "type":"Retail Goods"
        }
    ],
    "sg:phone":"+1 972 682 0717",
    "sg:postcode":"75150",
    "sg:province":"TX",
    "wof:name":"Matco Tools",
    "wof:placetype":"venue"
},
  "geometry": {"coordinates":[-96.614576,32.803961],"type":"Point"}
}