{
  "type": "Feature",
  "properties": {
    "iso:country":"US",
    "sg:address":"1635 W Division St",
    "sg:city":"Arlington",
    "sg:classifiers":[
        {
            "category":"Health Services",
            "subcategory":"Clinic",
            "type":"Services"
        }
    ],
    "sg:phone":"+1 817 274 4159",
    "sg:postcode":"76012",
    "sg:province":"TX",
    "sg:tags":[
        "physician",
        "surgeon"
    ],
    "wof:name":"Accent Family Healthcare",
    "wof:placetype":"venue"
},
  "geometry": {"coordinates":[-97.1323,32.736273],"type":"Point"}
}