{
  "type": "Feature",
  "properties": {
    "iso:country":"US",
    "sg:address":"2222 Westerland Dr",
    "sg:city":"Houston",
    "sg:classifiers":[
        {
            "category":"Real Estate",
            "subcategory":"Architect",
            "type":"Services"
        },
        {
            "category":"Professional",
            "subcategory":"Art Services",
            "type":"Services"
        }
    ],
    "sg:phone":"+1 713 785 2800",
    "sg:postcode":"77063",
    "sg:province":"TX",
    "sg:tags":[
        "arts",
        "graphic",
        "illustrator",
        "advertising",
        "architectural"
    ],
    "sg:website":"www.buildersgraphics.com",
    "wof:name":"Builders Graphics Inc",
    "wof:placetype":"venue"
},
  "geometry": {"coordinates":[-95.531486,29.74118],"type":"Point"}
}