{
  "type": "Feature",
  "properties": {
    "iso:country":"US",
    "sg:address":"10480 Chinaberry Dr",
    "sg:city":"El Paso",
    "sg:classifiers":[
        {
            "category":"Shopping",
            "subcategory":"Clothing, Apparel, & Fashions",
            "type":"Retail Goods"
        }
    ],
    "sg:phone":"+1 915 592 0949",
    "sg:postcode":"79925",
    "sg:province":"TX",
    "sg:tags":[
        "family"
    ],
    "wof:name":"Crj Ortega",
    "wof:placetype":"venue"
},
  "geometry": {"coordinates":[-106.344818,31.76223],"type":"Point"}
}