{
  "type": "Feature",
  "properties": {
    "iso:country":"US",
    "sg:address":"210 SE 24th Ave",
    "sg:city":"Perryton",
    "sg:classifiers":[
        {
            "category":"Restaurant",
            "type":"Food & Drink"
        }
    ],
    "sg:phone":"+1 806 435 4863",
    "sg:postcode":"79070",
    "sg:province":"TX",
    "sg:tags":[
        "barbecue",
        "style",
        "family"
    ],
    "wof:name":"The Smoke House Restaurant",
    "wof:placetype":"venue"
},
  "geometry": {"coordinates":[-100.801703,36.37697],"type":"Point"}
}