{
  "type": "Feature",
  "properties": {
    "iso:country":"US",
    "sg:address":"313 Lane Dr",
    "sg:city":"Rosenberg",
    "sg:classifiers":[
        {
            "category":"Real Estate",
            "subcategory":"Real Estate Operator",
            "type":"Services"
        }
    ],
    "sg:phone":"+1 281 342 2423",
    "sg:postcode":"77471",
    "sg:province":"TX",
    "sg:tags":[
        "building",
        "apartment"
    ],
    "wof:name":"Fort Bend Voa Elderly",
    "wof:placetype":"venue"
},
  "geometry": {"coordinates":[-95.77354699999999,29.571147],"type":"Point"}
}