{
  "type": "Feature",
  "properties": {
    "iso:country":"US",
    "sg:address":"21688 Co Rd 181",
    "sg:city":"Bullard",
    "sg:classifiers":[
        {
            "category":"Building & Trades",
            "subcategory":"Construction",
            "type":"Services"
        }
    ],
    "sg:phone":"+1 903 894 6055",
    "sg:postcode":"75757",
    "sg:province":"TX",
    "sg:tags":[
        "house"
    ],
    "wof:name":"Wilson Homes LLC",
    "wof:placetype":"venue"
},
  "geometry": {"coordinates":[-95.37076,32.164633],"type":"Point"}
}