{
  "type": "Feature",
  "properties": {
    "iso:country":"US",
    "sg:address":"8911 Capitol Dr",
    "sg:city":"Austin",
    "sg:classifiers":[
        {
            "category":"Insurance",
            "subcategory":"Insurance Agent",
            "type":"Services"
        }
    ],
    "sg:phone":"+1 512 794 1324",
    "sg:postcode":"78753",
    "sg:province":"TX",
    "wof:name":"Aetna Investment Services Inc",
    "wof:placetype":"venue"
},
  "geometry": {"coordinates":[-97.694519,30.355261],"type":"Point"}
}