{
  "type": "Feature",
  "properties": {
    "iso:country":"US",
    "sg:address":"2700 4th St",
    "sg:city":"Brownwood",
    "sg:classifiers":[
        {
            "category":"Freight",
            "type":"Transportation"
        }
    ],
    "sg:phone":"+1 325 646 9911",
    "sg:postcode":"76801",
    "sg:province":"TX",
    "sg:tags":[
        "commercial",
        "storage"
    ],
    "wof:name":"Southside Storage",
    "wof:placetype":"venue"
},
  "geometry": {"coordinates":[-98.973118,31.692432],"type":"Point"}
}