{
  "type": "Feature",
  "properties": {
    "iso:country":"US",
    "sg:address":"910 29th St",
    "sg:city":"Hondo",
    "sg:classifiers":[
        {
            "category":"Manufacturing",
            "subcategory":"Tools & Machinery",
            "type":"Manufacturing & Wholesale Goods"
        }
    ],
    "sg:phone":"+1 830 426 2160",
    "sg:postcode":"78861",
    "sg:province":"TX",
    "sg:tags":[
        "electrical",
        "mfg"
    ],
    "wof:name":"Four N Electric",
    "wof:placetype":"venue"
},
  "geometry": {"coordinates":[-99.137677,29.338673],"type":"Point"}
}