{
  "type": "Feature",
  "properties": {
    "iso:country":"US",
    "sg:address":"2132 Kessler Ct",
    "sg:city":"Dallas",
    "sg:classifiers":[
        {
            "category":"Shopping",
            "type":"Retail Goods"
        }
    ],
    "sg:phone":"+1 214 941 7248",
    "sg:postcode":"75208",
    "sg:province":"TX",
    "sg:tags":[
        "merchandise"
    ],
    "wof:name":"Dots Shop",
    "wof:placetype":"venue"
},
  "geometry": {"coordinates":[-96.842895,32.763108],"type":"Point"}
}