{
  "type": "Feature",
  "properties": {
    "iso:country":"US",
    "sg:address":"1001 S Main St",
    "sg:city":"Georgetown",
    "sg:classifiers":[
        {
            "category":"Social Services",
            "subcategory":"Child Care",
            "type":"Services"
        }
    ],
    "sg:phone":"+1 512 869 4505",
    "sg:postcode":"78626",
    "sg:province":"TX",
    "wof:name":"Main Street Children Ctr",
    "wof:placetype":"venue"
},
  "geometry": {"coordinates":[-97.67699399999999,30.634912],"type":"Point"}
}