{
  "type": "Feature",
  "properties": {
    "iso:country":"US",
    "sg:address":"4112 W University Blvd",
    "sg:city":"Odessa",
    "sg:classifiers":[
        {
            "category":"Retail",
            "subcategory":"Auto Repair",
            "type":"Services"
        }
    ],
    "sg:phone":"+1 432 381 5501",
    "sg:postcode":"79764",
    "sg:province":"TX",
    "sg:tags":[
        "general"
    ],
    "wof:name":"Skelton Auto & Diesel Repair",
    "wof:placetype":"venue"
},
  "geometry": {"coordinates":[-102.430573,31.857335],"type":"Point"}
}