{
  "type": "Feature",
  "properties": {
    "iso:country":"US",
    "sg:address":"2918 Brown Trl",
    "sg:city":"Bedford",
    "sg:classifiers":[
        {
            "category":"Food & Beverages",
            "subcategory":"Bakery",
            "type":"Retail Goods"
        }
    ],
    "sg:phone":"+1 817 485 4292",
    "sg:postcode":"76021",
    "sg:province":"TX",
    "sg:tags":[
        "product",
        "mfg"
    ],
    "wof:name":"First Donut",
    "wof:placetype":"venue"
},
  "geometry": {"coordinates":[-97.160061,32.851652],"type":"Point"}
}