{
  "type": "Feature",
  "properties": {
    "iso:country":"US",
    "sg:address":"1901 Co Rd 105",
    "sg:city":"Hutto",
    "sg:classifiers":[
        {
            "category":"Building & Trades",
            "subcategory":"Construction",
            "type":"Services"
        }
    ],
    "sg:phone":"+1 512 930 3099",
    "sg:postcode":"78634",
    "sg:province":"TX",
    "sg:tags":[
        "house",
        "builder",
        "operative"
    ],
    "wof:name":"Robert J Klepzig Builder",
    "wof:placetype":"venue"
},
  "geometry": {"coordinates":[-97.596492,30.612742],"type":"Point"}
}