{
  "type": "Feature",
  "properties": {
    "iso:country":"US",
    "sg:address":"8617 Mesa Dr",
    "sg:city":"Houston",
    "sg:classifiers":[
        {
            "category":"Restaurant",
            "type":"Food & Drink"
        }
    ],
    "sg:phone":"+1 713 635 1665",
    "sg:postcode":"77028",
    "sg:province":"TX",
    "sg:tags":[
        "eating",
        "fast"
    ],
    "wof:name":"Le's Fast Food",
    "wof:placetype":"venue"
},
  "geometry": {"coordinates":[-95.262398,29.839899],"type":"Point"}
}