{
  "type": "Feature",
  "properties": {
    "iso:country":"US",
    "sg:address":"517 E 6th St",
    "sg:city":"Austin",
    "sg:classifiers":[
        {
            "category":"Bars & Pubs",
            "type":"Food & Drink"
        },
        {
            "category":"Restaurant",
            "type":"Food & Drink"
        }
    ],
    "sg:menulink":"http://www.allmenus.com/tx/austin/14628-casino-el-camino/menu/",
    "sg:phone":"+1 512 469 9330",
    "sg:postcode":"78701",
    "sg:province":"TX",
    "sg:tags":[
        "american"
    ],
    "wof:name":"Casino El Camino",
    "wof:placetype":"venue"
},
  "geometry": {"coordinates":[-97.738007,30.266721],"type":"Point"}
}