{
  "type": "Feature",
  "properties": {
    "iso:country":"US",
    "sg:address":"6424 Industrial Park Blvd",
    "sg:city":"Fort Worth",
    "sg:classifiers":[
        {
            "category":"Real Estate",
            "subcategory":"Real Estate Operator",
            "type":"Services"
        }
    ],
    "sg:phone":"+1 817 656 2272",
    "sg:postcode":"76180",
    "sg:province":"TX",
    "sg:tags":[
        "apartment"
    ],
    "wof:name":"Hilltop Apartments",
    "wof:placetype":"venue"
},
  "geometry": {"coordinates":[-97.24709900000001,32.845287],"type":"Point"}
}