{
  "type": "Feature",
  "properties": {
    "iso:country":"US",
    "sg:address":"1305 FM 359",
    "sg:city":"Richmond",
    "sg:classifiers":[
        {
            "category":"Retail",
            "subcategory":"Laundry & Dry Cleaning",
            "type":"Services"
        }
    ],
    "sg:phone":"+1 281 238 9370",
    "sg:postcode":"77469",
    "sg:province":"TX",
    "sg:tags":[
        "repair",
        "shoe",
        "laundering",
        "cleaners"
    ],
    "wof:name":"Holiday Cleaners",
    "wof:placetype":"venue"
},
  "geometry": {"coordinates":[-95.743329,29.61532],"type":"Point"}
}