{
  "type": "Feature",
  "properties": {
    "iso:country":"US",
    "sg:address":"407 N Cedar Ridge Dr",
    "sg:city":"Duncanville",
    "sg:classifiers":[
        {
            "category":"Professional",
            "subcategory":"Lawyer & Legal Services",
            "type":"Services"
        }
    ],
    "sg:phone":"+1 972 780 8186",
    "sg:postcode":"75116",
    "sg:province":"TX",
    "wof:name":"Jackson Ray Atty At Law",
    "wof:placetype":"venue"
},
  "geometry": {"coordinates":[-96.925797,32.654999],"type":"Point"}
}