{
  "type": "Feature",
  "properties": {
    "iso:country":"US",
    "sg:address":"3310 E Southcross Blvd",
    "sg:city":"San Antonio",
    "sg:classifiers":[
        {
            "category":"Health Services",
            "subcategory":"Optometrist",
            "type":"Services"
        }
    ],
    "sg:phone":"+1 210 534 8863",
    "sg:postcode":"78223",
    "sg:province":"TX",
    "wof:name":"Beverly K Wiatrek OD",
    "wof:placetype":"venue"
},
  "geometry": {"coordinates":[-98.43285299999999,29.377564],"type":"Point"}
}