{
  "type": "Feature",
  "properties": {
    "iso:country":"US",
    "sg:address":"3420 Thornton Dr",
    "sg:city":"Amarillo",
    "sg:classifiers":[
        {
            "category":"Health Services",
            "subcategory":"Dentist",
            "type":"Services"
        }
    ],
    "sg:phone":"+1 806 353 3593",
    "sg:postcode":"79109",
    "sg:province":"TX",
    "sg:tags":[
        "dentists-orthodontists"
    ],
    "sg:website":"http://www.harwellortho.com",
    "wof:name":"Harwell & Harwell Orthodontics",
    "wof:placetype":"venue"
},
  "geometry": {"coordinates":[-101.91861,35.176151],"type":"Point"}
}