{
  "type": "Feature",
  "properties": {
    "iso:country":"US",
    "sg:address":"5415 Bandera Rd",
    "sg:city":"San Antonio",
    "sg:classifiers":[
        {
            "category":"Home & Garden",
            "subcategory":"Building Materials",
            "type":"Retail Goods"
        },
        {
            "category":"Wholesale",
            "subcategory":"Electrical",
            "type":"Manufacturing & Wholesale Goods"
        }
    ],
    "sg:phone":"+1 210 523 1422",
    "sg:postcode":"78238",
    "sg:province":"TX",
    "sg:tags":[
        "equipment",
        "parts",
        "electric",
        "supply"
    ],
    "wof:name":"Quality Distributing Company",
    "wof:placetype":"venue"
},
  "geometry": {"coordinates":[-98.591944,29.47972],"type":"Point"}
}