{
  "type": "Feature",
  "properties": {
    "iso:country":"US",
    "sg:address":"6860 Twin Hills Ave",
    "sg:city":"Dallas",
    "sg:classifiers":[
        {
            "category":"Shopping",
            "subcategory":"Pharmacy",
            "type":"Retail Goods"
        }
    ],
    "sg:phone":"+1 214 368 3050",
    "sg:postcode":"75231",
    "sg:province":"TX",
    "wof:name":"CVS Pharmacy",
    "wof:placetype":"venue"
},
  "geometry": {"coordinates":[-96.764595,32.871454],"type":"Point"}
}