{
  "type": "Feature",
  "properties": {
    "iso:country":"US",
    "sg:address":"7122 Wood Hollow Dr",
    "sg:city":"Austin",
    "sg:classifiers":[
        {
            "category":"Manufacturing",
            "subcategory":"Motor Vehicles & Parts",
            "type":"Manufacturing & Wholesale Goods"
        }
    ],
    "sg:phone":"+1 512 346 8570",
    "sg:postcode":"78731",
    "sg:province":"TX",
    "sg:tags":[
        "mfg",
        "trimming"
    ],
    "wof:name":"Christine P Ziober",
    "wof:placetype":"venue"
},
  "geometry": {"coordinates":[-97.751513,30.356185],"type":"Point"}
}