{
  "type": "Feature",
  "properties": {
    "iso:country":"US",
    "sg:address":"6404 Airline Dr",
    "sg:city":"Houston",
    "sg:classifiers":[
        {
            "category":"Restaurant",
            "type":"Food & Drink"
        }
    ],
    "sg:phone":"+1 713 699 9555",
    "sg:postcode":"77076",
    "sg:province":"TX",
    "sg:tags":[
        "eating"
    ],
    "wof:name":"Boogie Burger",
    "wof:placetype":"venue"
},
  "geometry": {"coordinates":[-95.384642,29.860103],"type":"Point"}
}