{
  "type": "Feature",
  "properties": {
    "iso:country":"US",
    "sg:address":"1874 Courtside Place Dr",
    "sg:city":"Missouri City",
    "sg:classifiers":[
        {
            "category":"Shopping",
            "subcategory":"Music",
            "type":"Retail Goods"
        }
    ],
    "sg:phone":"+1 281 261 7454",
    "sg:postcode":"77489",
    "sg:province":"TX",
    "wof:name":"Vital Entertainment Zone Ve2",
    "wof:placetype":"venue"
},
  "geometry": {"coordinates":[-95.530945,29.595284],"type":"Point"}
}