{
  "type": "Feature",
  "properties": {
    "iso:country":"US",
    "sg:address":"108 State Hwy 31 E",
    "sg:city":"Kilgore",
    "sg:classifiers":[
        {
            "category":"Retail",
            "subcategory":"Auto Repair",
            "type":"Services"
        }
    ],
    "sg:phone":"+1 903 984 4927",
    "sg:postcode":"75662",
    "sg:province":"TX",
    "sg:tags":[
        "body",
        "automobile",
        "painting"
    ],
    "wof:name":"Jake's Paint & Body Shop",
    "wof:placetype":"venue"
},
  "geometry": {"coordinates":[-94.87975900000001,32.396594],"type":"Point"}
}