{
  "type": "Feature",
  "properties": {
    "iso:country":"US",
    "sg:address":"612 13th St",
    "sg:city":"Bridgeport",
    "sg:classifiers":[
        {
            "category":"Retail",
            "subcategory":"Repair Shop",
            "type":"Services"
        }
    ],
    "sg:phone":"+1 940 683 5210",
    "sg:postcode":"76426",
    "sg:province":"TX",
    "wof:name":"American Industrial Components",
    "wof:placetype":"venue"
},
  "geometry": {"coordinates":[-97.754497,33.204316],"type":"Point"}
}