{
  "type": "Feature",
  "properties": {
    "iso:country":"US",
    "sg:address":"5057 Ridgecrest Dr",
    "sg:city":"Lewisville",
    "sg:classifiers":[
        {
            "category":"Banks & Credit Unions",
            "subcategory":"Financial Services",
            "type":"Services"
        }
    ],
    "sg:phone":"+1 972 625 6579",
    "sg:postcode":"75056",
    "sg:province":"TX",
    "sg:tags":[
        "trust",
        "management"
    ],
    "wof:name":"Pereira Family Trust",
    "wof:placetype":"venue"
},
  "geometry": {"coordinates":[-96.895785,33.083175],"type":"Point"}
}