{
  "type": "Feature",
  "properties": {
    "iso:country":"US",
    "sg:address":"288 Lakecreek Dr",
    "sg:city":"New Braunfels",
    "sg:classifiers":[
        {
            "category":"Building & Trades",
            "subcategory":"Construction",
            "type":"Services"
        }
    ],
    "sg:phone":"+1 830 624 8911",
    "sg:postcode":"78130",
    "sg:province":"TX",
    "sg:tags":[
        "contractor"
    ],
    "wof:name":"Harder Tile & Marble",
    "wof:placetype":"venue"
},
  "geometry": {"coordinates":[-98.05683500000001,29.622894],"type":"Point"}
}