{
  "type": "Feature",
  "properties": {
    "iso:country":"US",
    "sg:address":"8705 Hansom Cab Cir",
    "sg:city":"Temple",
    "sg:classifiers":[
        {
            "category":"Building & Trades",
            "subcategory":"Construction",
            "type":"Services"
        }
    ],
    "sg:phone":"+1 254 780 3409",
    "sg:postcode":"76502",
    "sg:province":"TX",
    "sg:tags":[
        "home",
        "builder"
    ],
    "wof:name":"Pilkington Homes At Carriage",
    "wof:placetype":"venue"
},
  "geometry": {"coordinates":[-97.44407,31.098422],"type":"Point"}
}