{
  "type": "Feature",
  "properties": {
    "iso:country":"US",
    "sg:address":"2313 Lake Austin Blvd",
    "sg:city":"Austin",
    "sg:classifiers":[
        {
            "category":"Professional",
            "subcategory":"Business Services",
            "type":"Services"
        }
    ],
    "sg:phone":"+1 512 236 0500",
    "sg:postcode":"78703",
    "sg:province":"TX",
    "sg:tags":[
        "agency",
        "talent"
    ],
    "sg:website":"http://www.colliertalent.com",
    "wof:name":"Collier Talent Agency",
    "wof:placetype":"venue"
},
  "geometry": {"coordinates":[-97.77187000000001,30.277686],"type":"Point"}
}