{
  "type": "Feature",
  "properties": {
    "iso:country":"US",
    "sg:address":"6723 Stewart Rd",
    "sg:city":"Galveston",
    "sg:classifiers":[
        {
            "category":"Personal",
            "subcategory":"Beauty Salon",
            "type":"Services"
        }
    ],
    "sg:phone":"+1 409 741 1912",
    "sg:postcode":"77551",
    "sg:province":"TX",
    "sg:tags":[
        "manicuring"
    ],
    "wof:name":"Magic Touch Nail Salon",
    "wof:placetype":"venue"
},
  "geometry": {"coordinates":[-94.837349,29.272867],"type":"Point"}
}