{
  "type": "Feature",
  "properties": {
    "iso:country":"US",
    "sg:address":"20041 Fiddlers Green Rd",
    "sg:city":"Frisco",
    "sg:classifiers":[
        {
            "category":"Professional",
            "subcategory":"Business Services",
            "type":"Services"
        }
    ],
    "sg:phone":"+1 972 294 7707",
    "sg:postcode":"75034",
    "sg:province":"TX",
    "wof:name":"Wright Designs",
    "wof:placetype":"venue"
},
  "geometry": {"coordinates":[-96.934574,33.141918],"type":"Point"}
}