{
  "type": "Feature",
  "properties": {
    "iso:country":"US",
    "sg:address":"1041 W 4th St",
    "sg:city":"Baird",
    "sg:classifiers":[
        {
            "category":"Farming",
            "subcategory":"Livestock Farm",
            "type":"Manufacturing & Wholesale Goods"
        }
    ],
    "sg:phone":"+1 325 854 1065",
    "sg:postcode":"79504",
    "sg:province":"TX",
    "sg:tags":[
        "beef",
        "feedlot",
        "cattle"
    ],
    "wof:name":"Diller & Diller Inc",
    "wof:placetype":"venue"
},
  "geometry": {"coordinates":[-99.406064,32.39526],"type":"Point"}
}