{
  "type": "Feature",
  "properties": {
    "iso:country":"US",
    "sg:address":"4254 Director Dr",
    "sg:city":"San Antonio",
    "sg:classifiers":[
        {
            "category":"Professional",
            "type":"Services"
        }
    ],
    "sg:phone":"+1 210 333 3335",
    "sg:postcode":"78219",
    "sg:province":"TX",
    "wof:name":"Texwin Co",
    "wof:placetype":"venue"
},
  "geometry": {"coordinates":[-98.41441399999999,29.43897],"type":"Point"}
}