{
  "type": "Feature",
  "properties": {
    "iso:country":"US",
    "sg:address":"4804 Pony Chase",
    "sg:city":"Austin",
    "sg:classifiers":[
        {
            "category":"Manufacturing",
            "subcategory":"Tools & Machinery",
            "type":"Manufacturing & Wholesale Goods"
        }
    ],
    "sg:phone":"+1 512 258 5617",
    "sg:postcode":"78727",
    "sg:province":"TX",
    "sg:tags":[
        "equipment",
        "household",
        "cooking",
        "eating",
        "mfg"
    ],
    "wof:name":"Menu Cookbook Co",
    "wof:placetype":"venue"
},
  "geometry": {"coordinates":[-97.73200300000001,30.42186],"type":"Point"}
}