{
  "type": "Feature",
  "properties": {
    "iso:country":"US",
    "sg:address":"2404 S Grand Blvd",
    "sg:city":"Pearland",
    "sg:classifiers":[
        {
            "category":"Wholesale",
            "subcategory":"Auto Parts",
            "type":"Manufacturing & Wholesale Goods"
        }
    ],
    "sg:phone":"+1 281 485 8828",
    "sg:postcode":"77581",
    "sg:province":"TX",
    "sg:tags":[
        "distributor",
        "automotive",
        "supply"
    ],
    "wof:name":"Elite Automotive Marketing",
    "wof:placetype":"venue"
},
  "geometry": {"coordinates":[-95.28389199999999,29.563611],"type":"Point"}
}