{
  "type": "Feature",
  "properties": {
    "iso:country":"US",
    "sg:address":"909 W California St",
    "sg:city":"Floydada",
    "sg:phone":"+1 806 983 2967",
    "sg:postcode":"79235",
    "sg:province":"TX",
    "sg:tags":[
        "farm",
        "cotton"
    ],
    "wof:name":"S and J Farms",
    "wof:placetype":"venue"
},
  "geometry": {"coordinates":[-101.34954,33.984211],"type":"Point"}
}