{
  "type": "Feature",
  "properties": {
    "iso:country":"US",
    "sg:address":"3504 Swiss Ave",
    "sg:city":"Dallas",
    "sg:classifiers":[
        {
            "category":"Health Services",
            "subcategory":"Doctor",
            "type":"Services"
        }
    ],
    "sg:phone":"+1 214 823 2684",
    "sg:postcode":"75204",
    "sg:province":"TX",
    "wof:name":"Millard Mark W MD",
    "wof:placetype":"venue"
},
  "geometry": {"coordinates":[-96.781998,32.791698],"type":"Point"}
}