{
  "type": "Feature",
  "properties": {
    "iso:country":"US",
    "sg:address":"3003 Lake Shore Dr",
    "sg:city":"Edinburg",
    "sg:classifiers":[
        {
            "category":"Real Estate",
            "subcategory":"Real Estate Agent",
            "type":"Services"
        }
    ],
    "sg:phone":"+1 956 383 5037",
    "sg:postcode":"78539",
    "sg:province":"TX",
    "wof:name":"RPM Services",
    "wof:placetype":"venue"
},
  "geometry": {"coordinates":[-98.204097,26.27958],"type":"Point"}
}