{
  "type": "Feature",
  "properties": {
    "iso:country":"US",
    "sg:address":"1550 N Durham Dr",
    "sg:city":"Houston",
    "sg:classifiers":[
        {
            "category":"Autos & Motor Vehicles",
            "subcategory":"Automobile Sales",
            "type":"Retail Goods"
        }
    ],
    "sg:phone":"+1 713 864 6328",
    "sg:postcode":"77008",
    "sg:province":"TX",
    "sg:tags":[
        "used"
    ],
    "wof:name":"Michael Hall",
    "wof:placetype":"venue"
},
  "geometry": {"coordinates":[-95.411599,29.798764],"type":"Point"}
}