{
  "type": "Feature",
  "properties": {
    "iso:country":"US",
    "sg:address":"321 N Merrifield Rd",
    "sg:city":"Dallas",
    "sg:classifiers":[
        {
            "category":"Freight",
            "type":"Transportation"
        }
    ],
    "sg:phone":"+1 972 263 7361",
    "sg:postcode":"75211",
    "sg:province":"TX",
    "sg:tags":[
        "operator",
        "trucking"
    ],
    "wof:name":"Anderson Trucking Service Inc",
    "wof:placetype":"venue"
},
  "geometry": {"coordinates":[-96.922636,32.749534],"type":"Point"}
}