{
  "type": "Feature",
  "properties": {
    "iso:country":"US",
    "sg:address":"515 SW 24th St",
    "sg:city":"San Antonio",
    "sg:classifiers":[
        {
            "category":"Organizations",
            "subcategory":"Religious Organization",
            "type":"Services"
        }
    ],
    "sg:phone":"+1 210 433 7553",
    "sg:postcode":"78207",
    "sg:province":"TX",
    "wof:name":"Ollu Convent",
    "wof:placetype":"venue"
},
  "geometry": {"coordinates":[-98.543199,29.424768],"type":"Point"}
}