{
  "type": "Feature",
  "properties": {
    "iso:country":"US",
    "sg:address":"23110 I- 45",
    "sg:city":"Spring",
    "sg:classifiers":[
        {
            "category":"Autos & Motor Vehicles",
            "subcategory":"Automobile Sales",
            "type":"Retail Goods"
        }
    ],
    "sg:phone":"+1 281 350 8889",
    "sg:postcode":"77373",
    "sg:province":"TX",
    "wof:name":"Crossway Auto Center Inc",
    "wof:placetype":"venue"
},
  "geometry": {"coordinates":[-95.43683900000001,30.1101],"type":"Point"}
}