{
  "type": "Feature",
  "properties": {
    "iso:country":"US",
    "sg:address":"2704 Fort Blvd",
    "sg:city":"El Paso",
    "sg:classifiers":[
        {
            "category":"Shopping",
            "subcategory":"Clothing, Apparel, & Fashions",
            "type":"Retail Goods"
        }
    ],
    "sg:phone":"+1 915 566 3661",
    "sg:postcode":"79930",
    "sg:province":"TX",
    "wof:name":"E Sanchez Retailer",
    "wof:placetype":"venue"
},
  "geometry": {"coordinates":[-106.46292800000001,31.805864],"type":"Point"}
}