{
  "type": "Feature",
  "properties": {
    "iso:country":"US",
    "sg:address":"3709 Eastledge Dr",
    "sg:city":"Austin",
    "sg:classifiers":[
        {
            "category":"Farming",
            "subcategory":"Livestock Farm",
            "type":"Manufacturing & Wholesale Goods"
        }
    ],
    "sg:phone":"+1 512 452 0978",
    "sg:postcode":"78731",
    "sg:province":"TX",
    "sg:tags":[
        "animal",
        "general"
    ],
    "wof:name":"9k Ranch LLC",
    "wof:placetype":"venue"
},
  "geometry": {"coordinates":[-97.768321,30.318958],"type":"Point"}
}