{
  "type": "Feature",
  "properties": {
    "iso:country":"US",
    "sg:address":"4112 Harlanwood Dr",
    "sg:city":"Fort Worth",
    "sg:classifiers":[
        {
            "category":"Professional",
            "subcategory":"Advertising",
            "type":"Services"
        }
    ],
    "sg:phone":"+1 817 926 3883",
    "sg:postcode":"76109",
    "sg:province":"TX",
    "wof:name":"Wadley Co",
    "wof:placetype":"venue"
},
  "geometry": {"coordinates":[-97.38108,32.706137],"type":"Point"}
}