{
  "type": "Feature",
  "properties": {
    "iso:country":"US",
    "sg:address":"3028 S 1st St",
    "sg:city":"Garland",
    "sg:classifiers":[
        {
            "category":"Restaurant",
            "type":"Food & Drink"
        }
    ],
    "sg:phone":"+1 972 278 9499",
    "sg:postcode":"75041",
    "sg:province":"TX",
    "wof:name":"Church's Fried Chicken",
    "wof:placetype":"venue"
},
  "geometry": {"coordinates":[-96.63099699999999,32.879902],"type":"Point"}
}