{
  "type": "Feature",
  "properties": {
    "iso:country":"US",
    "sg:address":"850 N Dorothy Dr",
    "sg:city":"Richardson",
    "sg:classifiers":[
        {
            "category":"Communications",
            "type":"Services"
        },
        {
            "category":"Professional",
            "subcategory":"Management & Consulting",
            "type":"Services"
        }
    ],
    "sg:phone":"+1 972 788 5400",
    "sg:postcode":"75081",
    "sg:province":"TX",
    "sg:tags":[
        "wireless",
        "carrier",
        "telecommunication"
    ],
    "wof:name":"Oncom Wireless",
    "wof:placetype":"venue"
},
  "geometry": {"coordinates":[-96.722461,32.959138],"type":"Point"}
}