{
  "type": "Feature",
  "properties": {
    "iso:country":"US",
    "sg:address":"1121 Green River Trl",
    "sg:city":"Cleburne",
    "sg:classifiers":[
        {
            "category":"Building & Trades",
            "subcategory":"Pest Control",
            "type":"Services"
        }
    ],
    "sg:phone":"+1 817 517 6010",
    "sg:postcode":"76033",
    "sg:province":"TX",
    "sg:tags":[
        "spraying"
    ],
    "wof:name":"Abby's Pest & Termite",
    "wof:placetype":"venue"
},
  "geometry": {"coordinates":[-97.401194,32.333054],"type":"Point"}
}