{
  "type": "Feature",
  "properties": {
    "iso:country":"US",
    "sg:address":"447 Maryland St",
    "sg:city":"Marlin",
    "sg:classifiers":[
        {
            "category":"Utilities",
            "subcategory":"Cable",
            "type":"Services"
        }
    ],
    "sg:phone":"+1 254 883 5837",
    "sg:postcode":"76661",
    "sg:province":"TX",
    "sg:tags":[
        "television"
    ],
    "wof:name":"Satellites In Motion",
    "wof:placetype":"venue"
},
  "geometry": {"coordinates":[-96.90437300000001,31.316631],"type":"Point"}
}