{
  "type": "Feature",
  "properties": {
    "iso:country":"US",
    "sg:address":"1501 E Bustamante St",
    "sg:city":"Laredo",
    "sg:classifiers":[
        {
            "category":"Shopping",
            "subcategory":"Pharmacy",
            "type":"Retail Goods"
        }
    ],
    "sg:phone":"+1 956 791 1991",
    "sg:postcode":"78041",
    "sg:province":"TX",
    "wof:name":"Med Center Pharmacy",
    "wof:placetype":"venue"
},
  "geometry": {"coordinates":[-99.48029099999999,27.534195],"type":"Point"}
}