{
  "type": "Feature",
  "properties": {
    "iso:country":"US",
    "sg:address":"201 Oak Dr S",
    "sg:city":"Lake Jackson",
    "sg:classifiers":[
        {
            "category":"Health Services",
            "subcategory":"Doctor",
            "type":"Services"
        }
    ],
    "sg:phone":"+1 979 299 0012",
    "sg:postcode":"77566",
    "sg:province":"TX",
    "sg:tags":[
        "medical"
    ],
    "wof:name":"Patel Nilesh J MD",
    "wof:placetype":"venue"
},
  "geometry": {"coordinates":[-95.45371,29.031834],"type":"Point"}
}