{
  "type": "Feature",
  "properties": {
    "iso:country":"US",
    "sg:address":"2713 Pineneedle Ln",
    "sg:city":"Pearland",
    "sg:classifiers":[
        {
            "category":"Farming",
            "subcategory":"Farm & Veterinary Services",
            "type":"Manufacturing & Wholesale Goods"
        }
    ],
    "sg:phone":"+1 281 485 3501",
    "sg:postcode":"77581",
    "sg:province":"TX",
    "sg:tags":[
        "crop"
    ],
    "wof:name":"Wickers Work",
    "wof:placetype":"venue"
},
  "geometry": {"coordinates":[-95.23774299999999,29.556196],"type":"Point"}
}