{
  "type": "Feature",
  "properties": {
    "iso:country":"US",
    "sg:address":"1525 Crystal Farms Rd",
    "sg:city":"Tatum",
    "sg:classifiers":[
        {
            "category":"Building & Trades",
            "subcategory":"Construction",
            "type":"Services"
        }
    ],
    "sg:phone":"+1 903 947 6245",
    "sg:postcode":"75691",
    "sg:province":"TX",
    "sg:tags":[
        "home",
        "maintenance",
        "repair"
    ],
    "wof:name":"Larry B Woods",
    "wof:placetype":"venue"
},
  "geometry": {"coordinates":[-94.52794299999999,32.327532],"type":"Point"}
}