{
  "type": "Feature",
  "properties": {
    "iso:country":"US",
    "sg:address":"7608 S Cage Blvd",
    "sg:city":"Pharr",
    "sg:classifiers":[
        {
            "category":"Shopping",
            "subcategory":"Discount & Variety Stores",
            "type":"Retail Goods"
        }
    ],
    "sg:phone":"+1 956 283 1325",
    "sg:postcode":"78577",
    "sg:province":"TX",
    "wof:name":"Dollar General",
    "wof:placetype":"venue"
},
  "geometry": {"coordinates":[-98.196096,26.123148],"type":"Point"}
}