{
  "type": "Feature",
  "properties": {
    "iso:country":"US",
    "sg:address":"12516 Sun Terrace Ave",
    "sg:city":"El Paso",
    "sg:classifiers":[
        {
            "category":"Professional",
            "type":"Services"
        }
    ],
    "sg:phone":"+1 915 849 8011",
    "sg:postcode":"79938",
    "sg:province":"TX",
    "sg:tags":[
        "establishment"
    ],
    "wof:name":"R H O Logistics",
    "wof:placetype":"venue"
},
  "geometry": {"coordinates":[-106.255937,31.762711],"type":"Point"}
}