{
  "type": "Feature",
  "properties": {
    "iso:country":"US",
    "sg:address":"2202 Morse St",
    "sg:city":"Houston",
    "sg:classifiers":[
        {
            "category":"Professional",
            "subcategory":"Management & Consulting",
            "type":"Services"
        }
    ],
    "sg:phone":"+1 713 522 2690",
    "sg:postcode":"77019",
    "sg:province":"TX",
    "sg:tags":[
        "consultant"
    ],
    "sg:website":"http://www.rlgcommunity.com",
    "wof:name":"Reed Larkey Group Inc",
    "wof:placetype":"venue"
},
  "geometry": {"coordinates":[-95.405484,29.746177],"type":"Point"}
}