{
  "type": "Feature",
  "properties": {
    "iso:country":"US",
    "sg:address":"416 N Cage Blvd",
    "sg:city":"Pharr",
    "sg:classifiers":[
        {
            "category":"Wholesale",
            "subcategory":"Plants",
            "type":"Manufacturing & Wholesale Goods"
        }
    ],
    "sg:phone":"+1 956 787 3192",
    "sg:postcode":"78577",
    "sg:province":"TX",
    "sg:tags":[
        "nursery",
        "tree",
        "supply"
    ],
    "wof:name":"Robert's Import & Nursery",
    "wof:placetype":"venue"
},
  "geometry": {"coordinates":[-98.18322000000001,26.199223],"type":"Point"}
}