{
  "type": "Feature",
  "properties": {
    "iso:country":"US",
    "sg:address":"1820 Swan St",
    "sg:city":"Longview",
    "sg:classifiers":[
        {
            "category":"Building & Trades",
            "subcategory":"Construction",
            "type":"Services"
        }
    ],
    "sg:phone":"+1 903 759 2880",
    "sg:postcode":"75604",
    "sg:province":"TX",
    "sg:tags":[
        "home",
        "builder"
    ],
    "wof:name":"Mission Home FBC",
    "wof:placetype":"venue"
},
  "geometry": {"coordinates":[-94.79992,32.528132],"type":"Point"}
}