{
  "type": "Feature",
  "properties": {
    "iso:country":"US",
    "sg:address":"701 E Marshall Ave",
    "sg:city":"Longview",
    "sg:classifiers":[
        {
            "category":"Health Services",
            "subcategory":"Doctor",
            "type":"Services"
        }
    ],
    "sg:phone":"+1 903 236 4115",
    "sg:postcode":"75601",
    "sg:province":"TX",
    "sg:tags":[
        "physician",
        "surgeon"
    ],
    "wof:name":"East Texas Neurosurgical Assoc",
    "wof:placetype":"venue"
},
  "geometry": {"coordinates":[-94.730181,32.501982],"type":"Point"}
}