{
  "type": "Feature",
  "properties": {
    "iso:country":"US",
    "sg:address":"11368 Emerald St",
    "sg:city":"Dallas",
    "sg:classifiers":[
        {
            "category":"Restaurant",
            "type":"Food & Drink"
        }
    ],
    "sg:phone":"+1 469 522 1050",
    "sg:postcode":"75229",
    "sg:province":"TX",
    "wof:name":"Hurky's Bbq Express",
    "wof:placetype":"venue"
},
  "geometry": {"coordinates":[-96.89937,32.895336],"type":"Point"}
}