{
  "type": "Feature",
  "properties": {
    "iso:country":"US",
    "sg:address":"106 4th",
    "sg:city":"Ingram",
    "sg:classifiers":[
        {
            "category":"Building & Trades",
            "subcategory":"Construction",
            "type":"Services"
        }
    ],
    "sg:phone":"+1 830 367 4411",
    "sg:postcode":"78025",
    "sg:province":"TX",
    "sg:tags":[
        "general",
        "contractor"
    ],
    "wof:name":"Wallworks Construction",
    "wof:placetype":"venue"
},
  "geometry": {"coordinates":[-99.23572900000001,30.080016],"type":"Point"}
}