{
  "type": "Feature",
  "properties": {
    "iso:country":"US",
    "sg:address":"6466 State Hwy 19 S",
    "sg:city":"Athens",
    "sg:classifiers":[
        {
            "category":"Building & Trades",
            "subcategory":"Construction",
            "type":"Services"
        }
    ],
    "sg:phone":"+1 903 670 3001",
    "sg:postcode":"75751",
    "sg:province":"TX",
    "wof:name":"Oncor Pipeline Services",
    "wof:placetype":"venue"
},
  "geometry": {"coordinates":[-95.852142,32.230665],"type":"Point"}
}