{
  "type": "Feature",
  "properties": {
    "iso:country":"US",
    "sg:address":"915 E Schunior St",
    "sg:city":"Edinburg",
    "sg:classifiers":[
        {
            "category":"Retail",
            "subcategory":"Auto Repair",
            "type":"Services"
        }
    ],
    "sg:phone":"+1 956 383 8941",
    "sg:postcode":"78541",
    "sg:province":"TX",
    "sg:tags":[
        "transmission"
    ],
    "wof:name":"Johnny's Auto Svc",
    "wof:placetype":"venue"
},
  "geometry": {"coordinates":[-98.15142299999999,26.30705],"type":"Point"}
}