{
  "type": "Feature",
  "properties": {
    "iso:country":"US",
    "sg:address":"11427 North Fwy",
    "sg:city":"Houston",
    "sg:classifiers":[
        {
            "category":"Cinema",
            "subcategory":"Movie Rental",
            "type":"Entertainment"
        }
    ],
    "sg:phone":"+1 832 598 2434",
    "sg:postcode":"77060",
    "sg:province":"TX",
    "sg:tags":[
        "game",
        "video"
    ],
    "wof:name":"North Freeway Video",
    "wof:placetype":"venue"
},
  "geometry": {"coordinates":[-95.412548,29.932542],"type":"Point"}
}