{
  "type": "Feature",
  "properties": {
    "iso:country":"US",
    "sg:address":"785 Creekwood St",
    "sg:city":"Vidor",
    "sg:classifiers":[
        {
            "category":"Professional",
            "subcategory":"Business Services",
            "type":"Services"
        }
    ],
    "sg:phone":"+1 409 745 4079",
    "sg:postcode":"77662",
    "sg:province":"TX",
    "wof:name":"Intergrity Automotive",
    "wof:placetype":"venue"
},
  "geometry": {"coordinates":[-93.927449,30.170954],"type":"Point"}
}