{
  "type": "Feature",
  "properties": {
    "iso:country":"US",
    "sg:address":"16350 Benton City Rd",
    "sg:city":"Von Ormy",
    "sg:classifiers":[
        {
            "category":"Shopping",
            "subcategory":"Gifts & Souvenirs",
            "type":"Retail Goods"
        }
    ],
    "sg:phone":"+1 210 622 9022",
    "sg:postcode":"78073",
    "sg:province":"TX",
    "wof:name":"E Rose Gifts",
    "wof:placetype":"venue"
},
  "geometry": {"coordinates":[-98.65705,29.261227],"type":"Point"}
}