{
  "type": "Feature",
  "properties": {
    "iso:country":"US",
    "sg:address":"16631 Red Gully Dr",
    "sg:city":"Sugar Land",
    "sg:classifiers":[
        {
            "category":"Professional",
            "type":"Services"
        }
    ],
    "sg:phone":"+1 281 277 1628",
    "sg:postcode":"77478",
    "sg:province":"TX",
    "wof:name":"Mums Word",
    "wof:placetype":"venue"
},
  "geometry": {"coordinates":[-95.671452,29.64075],"type":"Point"}
}