{
  "type": "Feature",
  "properties": {
    "iso:country":"US",
    "sg:address":"401 S Pine St",
    "sg:city":"Kermit",
    "sg:classifiers":[
        {
            "category":"Government",
            "subcategory":"Office",
            "type":"Public Place"
        }
    ],
    "sg:phone":"+1 432 586 9679",
    "sg:postcode":"79745",
    "sg:province":"TX",
    "sg:tags":[
        "state",
        "program"
    ],
    "wof:name":"Protective & Regulatory Svc",
    "wof:placetype":"venue"
},
  "geometry": {"coordinates":[-103.09518300000001,31.853966],"type":"Point"}
}