{
  "type": "Feature",
  "properties": {
    "iso:country":"US",
    "sg:address":"5411 Pine St",
    "sg:city":"Bellaire",
    "sg:classifiers":[
        {
            "category":"Building & Trades",
            "subcategory":"Construction",
            "type":"Services"
        }
    ],
    "sg:phone":"+1 713 682 8240",
    "sg:postcode":"77401",
    "sg:province":"TX",
    "sg:tags":[
        "house"
    ],
    "wof:name":"Kino Studio Inc",
    "wof:placetype":"venue"
},
  "geometry": {"coordinates":[-95.48410800000001,29.694564],"type":"Point"}
}