{
  "type": "Feature",
  "properties": {
    "iso:country":"US",
    "sg:address":"605 Ranch Rd 1431",
    "sg:city":"Kingsland",
    "sg:classifiers":[
        {
            "category":"Shopping",
            "subcategory":"Clothing, Apparel, & Fashions",
            "type":"Retail Goods"
        }
    ],
    "sg:phone":"+1 325 388 8668",
    "sg:postcode":"78639",
    "sg:province":"TX",
    "sg:tags":[
        "wear"
    ],
    "wof:name":"Lil Toots Exchange",
    "wof:placetype":"venue"
},
  "geometry": {"coordinates":[-98.435298,30.659674],"type":"Point"}
}