{
  "type": "Feature",
  "properties": {
    "iso:country":"US",
    "sg:address":"5235 de Zavala Rd",
    "sg:city":"San Antonio",
    "sg:classifiers":[
        {
            "category":"Restaurant",
            "type":"Food & Drink"
        }
    ],
    "sg:phone":"+1 210 696 1659",
    "sg:postcode":"78249",
    "sg:province":"TX",
    "sg:tags":[
        "eating"
    ],
    "wof:name":"Stagg Partnership",
    "wof:placetype":"venue"
},
  "geometry": {"coordinates":[-98.586511,29.564744],"type":"Point"}
}