{
  "type": "Feature",
  "properties": {
    "iso:country":"US",
    "sg:address":"7637 Parkview Cir",
    "sg:city":"Austin",
    "sg:classifiers":[
        {
            "category":"Professional",
            "subcategory":"Business Services",
            "type":"Services"
        }
    ],
    "sg:phone":"+1 512 345 9767",
    "sg:postcode":"78731",
    "sg:province":"TX",
    "sg:tags":[
        "patent",
        "agent"
    ],
    "wof:name":"Innoventions Venture Corp",
    "wof:placetype":"venue"
},
  "geometry": {"coordinates":[-97.773669,30.370066],"type":"Point"}
}