{
  "type": "Feature",
  "properties": {
    "iso:country":"US",
    "sg:address":"8531 Sunny Ridge Dr",
    "sg:city":"Houston",
    "sg:classifiers":[
        {
            "category":"Manufacturing",
            "subcategory":"Apparel",
            "type":"Manufacturing & Wholesale Goods"
        }
    ],
    "sg:phone":"+1 281 856 7949",
    "sg:postcode":"77095",
    "sg:province":"TX",
    "wof:name":"Beevers Joli",
    "wof:placetype":"venue"
},
  "geometry": {"coordinates":[-95.641814,29.907188],"type":"Point"}
}