{
  "type": "Feature",
  "properties": {
    "iso:country":"US",
    "sg:address":"4128 Sunmeadows St",
    "sg:city":"Plano",
    "sg:classifiers":[
        {
            "category":"Professional",
            "subcategory":"Computer Services",
            "type":"Services"
        }
    ],
    "sg:phone":"+1 972 208 7355",
    "sg:postcode":"75024",
    "sg:province":"TX",
    "sg:tags":[
        "implementation",
        "software"
    ],
    "wof:name":"Ensoft Consulting Inc",
    "wof:placetype":"venue"
},
  "geometry": {"coordinates":[-96.77516900000001,33.076747],"type":"Point"}
}