{
  "type": "Feature",
  "properties": {
    "iso:country":"US",
    "sg:address":"4523 E Belknap St",
    "sg:city":"Fort Worth",
    "sg:classifiers":[
        {
            "category":"Retail",
            "subcategory":"Auto Repair",
            "type":"Services"
        }
    ],
    "sg:phone":"+1 817 834 2296",
    "sg:postcode":"76117",
    "sg:province":"TX",
    "sg:tags":[
        "transmission"
    ],
    "wof:name":"Transpec Transmission Specs",
    "wof:placetype":"venue"
},
  "geometry": {"coordinates":[-97.279492,32.7891],"type":"Point"}
}