{
  "type": "Feature",
  "properties": {
    "iso:country":"US",
    "sg:address":"4000 Kelley St",
    "sg:city":"Houston",
    "sg:classifiers":[
        {
            "category":"Education",
            "subcategory":"School",
            "type":"Public Place"
        }
    ],
    "sg:phone":"+1 713 636 6000",
    "sg:postcode":"77026",
    "sg:province":"TX",
    "sg:tags":[
        "high",
        "middle",
        "elementary"
    ],
    "wof:name":"Houston Independent School District",
    "wof:placetype":"venue"
},
  "geometry": {"coordinates":[-95.331726,29.813082],"type":"Point"}
}