{
  "type": "Feature",
  "properties": {
    "iso:country":"US",
    "sg:address":"300 Ligustrum St",
    "sg:city":"Lake Jackson",
    "sg:classifiers":[
        {
            "category":"Education",
            "subcategory":"School",
            "type":"Public Place"
        }
    ],
    "sg:phone":"+1 979 730 7165",
    "sg:postcode":"77566",
    "sg:province":"TX",
    "wof:name":"Beutel Elementary School",
    "wof:placetype":"venue"
},
  "geometry": {"coordinates":[-95.430328,29.034451],"type":"Point"}
}