{
  "type": "Feature",
  "properties": {
    "iso:country":"US",
    "sg:address":"12655 Crossroads Park Dr",
    "sg:city":"Houston",
    "sg:classifiers":[
        {
            "category":"Insurance",
            "subcategory":"Insurance Agent",
            "type":"Services"
        }
    ],
    "sg:phone":"+1 281 807 7412",
    "sg:postcode":"77065",
    "sg:province":"TX",
    "sg:tags":[
        "processing"
    ],
    "wof:name":"Associated Claims Svc",
    "wof:placetype":"venue"
},
  "geometry": {"coordinates":[-95.61338600000001,29.913409],"type":"Point"}
}