{
  "type": "Feature",
  "properties": {
    "iso:country":"US",
    "sg:address":"8127 Mesa Dr",
    "sg:city":"Austin",
    "sg:classifiers":[
        {
            "category":"Banks & Credit Unions",
            "subcategory":"Investment Brokerage",
            "type":"Services"
        }
    ],
    "sg:phone":"+1 512 241 0049",
    "sg:postcode":"78759",
    "sg:province":"TX",
    "sg:tags":[
        "security"
    ],
    "wof:name":"Edward Jones Co",
    "wof:placetype":"venue"
},
  "geometry": {"coordinates":[-97.75560299999999,30.373952],"type":"Point"}
}