{
  "type": "Feature",
  "properties": {
    "iso:country":"US",
    "sg:address":"1817 N Fork Rd",
    "sg:city":"Fort Worth",
    "sg:classifiers":[
        {
            "category":"Professional",
            "type":"Services"
        }
    ],
    "sg:phone":"+1 817 236 8327",
    "sg:postcode":"76179",
    "sg:province":"TX",
    "wof:name":"Turbine Works LLC",
    "wof:placetype":"venue"
},
  "geometry": {"coordinates":[-97.404791,32.893898],"type":"Point"}
}