{
  "type": "Feature",
  "properties": {
    "iso:country":"US",
    "sg:address":"110 Hwy 332 W",
    "sg:city":"Lake Jackson",
    "sg:classifiers":[
        {
            "category":"Shopping",
            "subcategory":"Books",
            "type":"Retail Goods"
        },
        {
            "category":"Cinema",
            "subcategory":"Movie Rental",
            "type":"Entertainment"
        }
    ],
    "sg:phone":"+1 979 297 5932",
    "sg:postcode":"77566",
    "sg:province":"TX",
    "sg:tags":[
        "leasing",
        "video",
        "disc",
        "tape"
    ],
    "wof:name":"Hastings Book Music & Video",
    "wof:placetype":"venue"
},
  "geometry": {"coordinates":[-95.46361400000001,29.048686],"type":"Point"}
}