{
  "type": "Feature",
  "properties": {
    "iso:country":"US",
    "sg:address":"15238 Highsprings Dr",
    "sg:city":"Houston",
    "sg:classifiers":[
        {
            "category":"Professional",
            "subcategory":"Lawyer & Legal Services",
            "type":"Services"
        }
    ],
    "sg:phone":"+1 281 583 1024",
    "sg:postcode":"77068",
    "sg:province":"TX",
    "sg:tags":[
        "attorney"
    ],
    "wof:name":"Kenneth L Nash Law Offices",
    "wof:placetype":"venue"
},
  "geometry": {"coordinates":[-95.49402000000001,30.002408],"type":"Point"}
}