{
  "type": "Feature",
  "properties": {
    "iso:country":"US",
    "sg:address":"5916 Falcon Ave",
    "sg:city":"El Paso",
    "sg:classifiers":[
        {
            "category":"Personal",
            "type":"Services"
        }
    ],
    "sg:phone":"+1 915 449 5382",
    "sg:postcode":"79924",
    "sg:province":"TX",
    "sg:tags":[
        "information",
        "system",
        "consultant"
    ],
    "wof:name":"Aic Corporation",
    "wof:placetype":"venue"
},
  "geometry": {"coordinates":[-106.400639,31.881073],"type":"Point"}
}