{
  "type": "Feature",
  "properties": {
    "iso:country":"US",
    "sg:address":"833 E Arapaho Rd",
    "sg:city":"Richardson",
    "sg:classifiers":[
        {
            "category":"Professional",
            "subcategory":"Accounting & Tax Preparation",
            "type":"Services"
        }
    ],
    "sg:phone":"+1 972 690 6023",
    "sg:postcode":"75081",
    "sg:province":"TX",
    "sg:tags":[
        "accountant"
    ],
    "wof:name":"Stock James Acct",
    "wof:placetype":"venue"
},
  "geometry": {"coordinates":[-96.713303,32.9608],"type":"Point"}
}