{
  "type": "Feature",
  "properties": {
    "iso:country":"US",
    "sg:address":"700 S Zarzamora",
    "sg:city":"San Antonio",
    "sg:classifiers":[
        {
            "category":"Social Services",
            "type":"Services"
        }
    ],
    "sg:phone":"+1 210 207 7190",
    "sg:postcode":"78207",
    "sg:province":"TX",
    "sg:tags":[
        "government"
    ],
    "wof:name":"San Antonio Youth Svc Div",
    "wof:placetype":"venue"
},
  "geometry": {"coordinates":[-98.52788099999999,29.420789],"type":"Point"}
}