{
  "type": "Feature",
  "properties": {
    "iso:country":"US",
    "sg:address":"10411 Raritan Dr",
    "sg:city":"Houston",
    "sg:phone":"+1 713 465 0054",
    "sg:postcode":"77043",
    "sg:province":"TX",
    "sg:tags":[
        "visual",
        "planning",
        "display",
        "store"
    ],
    "wof:name":"Clark-Horton Co Inc",
    "wof:placetype":"venue"
},
  "geometry": {"coordinates":[-95.556172,29.803383],"type":"Point"}
}