{
  "type": "Feature",
  "properties": {
    "iso:country":"US",
    "sg:address":"1124 N Zarzamora",
    "sg:city":"San Antonio",
    "sg:classifiers":[
        {
            "category":"Food & Beverages",
            "subcategory":"Groceries & Convenience Stores",
            "type":"Retail Goods"
        }
    ],
    "sg:phone":"+1 210 738 3255",
    "sg:postcode":"78207",
    "sg:province":"TX",
    "sg:tags":[
        "grocer"
    ],
    "wof:name":"Grandma's Ice & Grocery",
    "wof:placetype":"venue"
},
  "geometry": {"coordinates":[-98.525527,29.439842],"type":"Point"}
}