{
  "type": "Feature",
  "properties": {
    "iso:country":"US",
    "sg:address":"5028 Park Ln",
    "sg:city":"Dallas",
    "sg:classifiers":[
        {
            "category":"Retail",
            "subcategory":"Car Wash",
            "type":"Services"
        }
    ],
    "sg:phone":"+1 972 407 9648",
    "sg:postcode":"75220",
    "sg:province":"TX",
    "wof:name":"Car Spa Inc",
    "wof:placetype":"venue"
},
  "geometry": {"coordinates":[-96.821701,32.8741],"type":"Point"}
}