{
  "type": "Feature",
  "properties": {
    "iso:country":"US",
    "sg:address":"2703 Tidewater Dr",
    "sg:city":"Houston",
    "sg:classifiers":[
        {
            "category":"Real Estate",
            "subcategory":"Real Estate Services",
            "type":"Services"
        }
    ],
    "sg:phone":"+1 713 434 2130",
    "sg:postcode":"77045",
    "sg:province":"TX",
    "sg:tags":[
        "home",
        "inspector"
    ],
    "wof:name":"Apartmate of Houston",
    "wof:placetype":"venue"
},
  "geometry": {"coordinates":[-95.415199,29.632401],"type":"Point"}
}