{
  "type": "Feature",
  "properties": {
    "iso:country":"US",
    "sg:address":"7101 W Hwy 71",
    "sg:city":"Austin",
    "sg:classifiers":[
        {
            "category":"Food & Beverages",
            "subcategory":"Liquor & Beverages",
            "type":"Retail Goods"
        }
    ],
    "sg:phone":"+1 512 288 4590",
    "sg:postcode":"78735",
    "sg:province":"TX",
    "sg:tags":[
        "store"
    ],
    "wof:name":"Steve's Liquor & Fine Wines",
    "wof:placetype":"venue"
},
  "geometry": {"coordinates":[-97.876546,30.235048],"type":"Point"}
}