{
  "type": "Feature",
  "properties": {
    "iso:country":"US",
    "sg:address":"1140 Robin Rd",
    "sg:city":"El Paso",
    "sg:classifiers":[
        {
            "category":"Retail",
            "subcategory":"Repair Shop",
            "type":"Services"
        }
    ],
    "sg:phone":"+1 915 858 3212",
    "sg:postcode":"79927",
    "sg:province":"TX",
    "sg:tags":[
        "refrigeration",
        "gen",
        "tire"
    ],
    "wof:name":"El Paso Trailer Refrigeration",
    "wof:placetype":"venue"
},
  "geometry": {"coordinates":[-106.245608,31.661488],"type":"Point"}
}