{
  "type": "Feature",
  "properties": {
    "iso:country":"US",
    "sg:address":"321 N Broadway St",
    "sg:city":"Joshua",
    "sg:classifiers":[
        {
            "category":"Shopping",
            "subcategory":"Department Store",
            "type":"Retail Goods"
        }
    ],
    "sg:phone":"+1 817 645 9399",
    "sg:postcode":"76058",
    "sg:province":"TX",
    "sg:website":"www.dollargeneral.com",
    "wof:name":"Dollar General Store",
    "wof:placetype":"venue"
},
  "geometry": {"coordinates":[-97.384697,32.464001],"type":"Point"}
}