{
  "type": "Feature",
  "properties": {
    "iso:country":"US",
    "sg:address":"3909 Dover St",
    "sg:city":"Houston",
    "sg:classifiers":[
        {
            "category":"Manufacturing",
            "subcategory":"Printing",
            "type":"Manufacturing & Wholesale Goods"
        }
    ],
    "sg:phone":"+1 713 643 1636",
    "sg:postcode":"77087",
    "sg:province":"TX",
    "sg:tags":[
        "lithographic",
        "commercial"
    ],
    "wof:name":"Quality Prep and Printing Inc",
    "wof:placetype":"venue"
},
  "geometry": {"coordinates":[-95.28018899999999,29.684421],"type":"Point"}
}