{
  "type": "Feature",
  "properties": {
    "iso:country":"US",
    "sg:address":"515 S Archie St",
    "sg:city":"Vidor",
    "sg:classifiers":[
        {
            "category":"Health Services",
            "subcategory":"Doctor",
            "type":"Services"
        }
    ],
    "sg:phone":"+1 409 769 2295",
    "sg:postcode":"77662",
    "sg:province":"TX",
    "sg:tags":[
        "physician",
        "surgeon"
    ],
    "wof:name":"Sei Chang Oh MD",
    "wof:placetype":"venue"
},
  "geometry": {"coordinates":[-94.01629800000001,30.128918],"type":"Point"}
}