{
  "type": "Feature",
  "properties": {
    "iso:country":"US",
    "sg:address":"5115 Montana Ave",
    "sg:city":"El Paso",
    "sg:classifiers":[
        {
            "category":"Home & Garden",
            "subcategory":"Furniture",
            "type":"Retail Goods"
        }
    ],
    "sg:phone":"+1 915 562 6666",
    "sg:postcode":"79903",
    "sg:province":"TX",
    "sg:tags":[
        "juvenile",
        "nursery"
    ],
    "wof:name":"Tiny Tot Shop Inc",
    "wof:placetype":"venue"
},
  "geometry": {"coordinates":[-106.42748400000001,31.783789],"type":"Point"}
}