{
  "type": "Feature",
  "properties": {
    "iso:country":"US",
    "sg:address":"701 Hall St",
    "sg:city":"Cedar Hill",
    "sg:classifiers":[
        {
            "category":"Building & Trades",
            "subcategory":"Electrical",
            "type":"Services"
        }
    ],
    "sg:phone":"+1 972 291 7153",
    "sg:postcode":"75104",
    "sg:province":"TX",
    "sg:tags":[
        "electrician",
        "electric",
        "contractor"
    ],
    "wof:name":"Dean Electric Inc",
    "wof:placetype":"venue"
},
  "geometry": {"coordinates":[-96.966904,32.577099],"type":"Point"}
}