{
  "type": "Feature",
  "properties": {
    "iso:country":"US",
    "sg:address":"109 S Corinth St",
    "sg:city":"Dallas",
    "sg:classifiers":[
        {
            "category":"Autos & Motor Vehicles",
            "subcategory":"Automobile Sales",
            "type":"Retail Goods"
        }
    ],
    "sg:phone":"+1 214 941 8070",
    "sg:postcode":"75203",
    "sg:province":"TX",
    "sg:tags":[
        "car",
        "dealer"
    ],
    "wof:name":"Auto City Of America",
    "wof:placetype":"venue"
},
  "geometry": {"coordinates":[-96.799558,32.747715],"type":"Point"}
}