{
  "type": "Feature",
  "properties": {
    "iso:country":"US",
    "sg:address":"8623 Fm 1960 Bypass Rd W",
    "sg:city":"Humble",
    "sg:classifiers":[
        {
            "category":"Autos & Motor Vehicles",
            "subcategory":"Automobile Sales",
            "type":"Retail Goods"
        },
        {
            "category":"Autos & Motor Vehicles",
            "subcategory":"Auto Supplies",
            "type":"Retail Goods"
        },
        {
            "category":"Shopping",
            "subcategory":"Discount & Variety Stores",
            "type":"Retail Goods"
        }
    ],
    "sg:phone":"+1 281 905 1330",
    "sg:postcode":"77338",
    "sg:province":"TX",
    "sg:tags":[
        "surplus",
        "part",
        "supplies-used",
        "rebuilt",
        "salvage",
        "merchandise"
    ],
    "sg:website":"http://www.bigalssalvage.com",
    "wof:name":"Texas #1 Auto Buyers",
    "wof:placetype":"venue"
},
  "geometry": {"coordinates":[-95.295078,30.004949],"type":"Point"}
}