{
  "type": "Feature",
  "properties": {
    "iso:country":"US",
    "sg:address":"610 Old Boerne Rd",
    "sg:city":"Bulverde",
    "sg:classifiers":[
        {
            "category":"Building & Trades",
            "subcategory":"Pest Control",
            "type":"Services"
        }
    ],
    "sg:phone":"+1 830 980 4011",
    "sg:postcode":"78163",
    "sg:province":"TX",
    "wof:name":"Sterling Inspections Inc",
    "wof:placetype":"venue"
},
  "geometry": {"coordinates":[-98.442413,29.795845],"type":"Point"}
}