{
  "type": "Feature",
  "properties": {
    "iso:country":"US",
    "sg:address":"6130 Northwood Rd",
    "sg:city":"Dallas",
    "sg:classifiers":[
        {
            "category":"Wholesale",
            "subcategory":"Medical Equipment & Supplies",
            "type":"Manufacturing & Wholesale Goods"
        }
    ],
    "sg:phone":"+1 214 369 0216",
    "sg:postcode":"75225",
    "sg:province":"TX",
    "wof:name":"Webco Medical Products",
    "wof:placetype":"venue"
},
  "geometry": {"coordinates":[-96.797932,32.869456],"type":"Point"}
}