{
  "type": "Feature",
  "properties": {
    "iso:country":"US",
    "sg:address":"383 E Hidalgo Ave",
    "sg:city":"Raymondville",
    "sg:classifiers":[
        {
            "category":"Restaurant",
            "type":"Food & Drink"
        }
    ],
    "sg:phone":"+1 956 689 3435",
    "sg:postcode":"78580",
    "sg:province":"TX",
    "sg:tags":[
        "mexican"
    ],
    "wof:name":"Mi Pueblito Restaurant",
    "wof:placetype":"venue"
},
  "geometry": {"coordinates":[-97.77910300000001,26.481919],"type":"Point"}
}