{
  "type": "Feature",
  "properties": {
    "iso:country":"US",
    "sg:address":"700 Harwood Rd",
    "sg:city":"Bedford",
    "sg:classifiers":[
        {
            "category":"Organizations",
            "subcategory":"Religious Organization",
            "type":"Services"
        }
    ],
    "sg:phone":"+1 817 267 3329",
    "sg:postcode":"76021",
    "sg:province":"TX",
    "wof:name":"Ismailia Cultural Center",
    "wof:placetype":"venue"
},
  "geometry": {"coordinates":[-97.158891,32.853141],"type":"Point"}
}