{
  "type": "Feature",
  "properties": {
    "iso:country":"US",
    "sg:address":"709 W Page Ave",
    "sg:city":"Dallas",
    "sg:classifiers":[
        {
            "category":"Building & Trades",
            "subcategory":"Construction",
            "type":"Services"
        }
    ],
    "sg:phone":"+1 214 941 1284",
    "sg:postcode":"75208",
    "sg:province":"TX",
    "sg:tags":[
        "contractor"
    ],
    "wof:name":"Jesus Munguia Masonry",
    "wof:placetype":"venue"
},
  "geometry": {"coordinates":[-96.83566,32.740263],"type":"Point"}
}