{
  "type": "Feature",
  "properties": {
    "iso:country":"US",
    "sg:address":"838 Veracruz Dr",
    "sg:city":"Rosenberg",
    "sg:classifiers":[
        {
            "category":"Building & Trades",
            "subcategory":"Construction",
            "type":"Services"
        }
    ],
    "sg:phone":"+1 281 342 5719",
    "sg:postcode":"77471",
    "sg:province":"TX",
    "sg:tags":[
        "contractor"
    ],
    "wof:name":"Ryder Painting & Roofing",
    "wof:placetype":"venue"
},
  "geometry": {"coordinates":[-95.829272,29.547791],"type":"Point"}
}