{
  "type": "Feature",
  "properties": {
    "iso:country":"US",
    "sg:address":"14720 Co Rd 485",
    "sg:city":"Nevada",
    "sg:classifiers":[
        {
            "category":"Autos & Motor Vehicles",
            "subcategory":"Automobile Sales",
            "type":"Retail Goods"
        }
    ],
    "sg:phone":"+1 972 772 3817",
    "sg:postcode":"75173",
    "sg:province":"TX",
    "wof:name":"Olds Jeff",
    "wof:placetype":"venue"
},
  "geometry": {"coordinates":[-96.45459200000001,33.004593],"type":"Point"}
}