{
  "type": "Feature",
  "properties": {
    "iso:country":"US",
    "sg:address":"4900 S Lancaster Rd",
    "sg:city":"Dallas",
    "sg:classifiers":[
        {
            "category":"Military Area",
            "type":"Public Place"
        },
        {
            "category":"Professional",
            "subcategory":"Engineering",
            "type":"Services"
        },
        {
            "category":"Government",
            "subcategory":"Office",
            "type":"Public Place"
        }
    ],
    "sg:phone":"+1 214 371 3109",
    "sg:postcode":"75216",
    "sg:province":"TX",
    "sg:tags":[
        "consulting",
        "force",
        "recruiting",
        "state",
        "government-united",
        "armed",
        "engineer"
    ],
    "wof:name":"US Army Reserve",
    "wof:placetype":"venue"
},
  "geometry": {"coordinates":[-96.79057,32.688464],"type":"Point"}
}