{
  "type": "Feature",
  "properties": {
    "iso:country":"US",
    "sg:address":"907 N Muskingum Ave",
    "sg:city":"Odessa",
    "sg:classifiers":[
        {
            "category":"Manufacturing",
            "subcategory":"Tools & Machinery",
            "type":"Manufacturing & Wholesale Goods"
        }
    ],
    "sg:phone":"+1 432 332 3201",
    "sg:postcode":"79761",
    "sg:province":"TX",
    "sg:tags":[
        "machine",
        "shop"
    ],
    "wof:name":"Odessa Manufacture & Sales",
    "wof:placetype":"venue"
},
  "geometry": {"coordinates":[-102.36751,31.855566],"type":"Point"}
}