{
  "type": "Feature",
  "properties": {
    "iso:country":"US",
    "sg:address":"14805 Thunderhead Rd",
    "sg:city":"Austin",
    "sg:classifiers":[
        {
            "category":"Home & Garden",
            "subcategory":"Garden Supply",
            "type":"Retail Goods"
        }
    ],
    "sg:phone":"+1 512 266 3063",
    "sg:postcode":"78734",
    "sg:province":"TX",
    "sg:tags":[
        "merchandise"
    ],
    "wof:name":"Plant Connection",
    "wof:placetype":"venue"
},
  "geometry": {"coordinates":[-97.934894,30.373179],"type":"Point"}
}