{
  "type": "Feature",
  "properties": {
    "iso:country":"US",
    "sg:address":"333 Gross Rd",
    "sg:city":"Mesquite",
    "sg:classifiers":[
        {
            "category":"Autos & Motor Vehicles",
            "subcategory":"Boat Sales",
            "type":"Retail Goods"
        }
    ],
    "sg:phone":"+1 972 289 7867",
    "sg:postcode":"75149",
    "sg:province":"TX",
    "sg:tags":[
        "repair",
        "dealer"
    ],
    "wof:name":"West Boats Inc",
    "wof:placetype":"venue"
},
  "geometry": {"coordinates":[-96.613399,32.771609],"type":"Point"}
}