{
  "type": "Feature",
  "properties": {
    "iso:country":"US",
    "sg:address":"834 SW Military Dr",
    "sg:city":"San Antonio",
    "sg:classifiers":[
        {
            "category":"Health Services",
            "subcategory":"Doctor",
            "type":"Services"
        }
    ],
    "sg:phone":"+1 210 928 3573",
    "sg:postcode":"78221",
    "sg:province":"TX",
    "sg:tags":[
        "dentist"
    ],
    "wof:name":"Greg Lerner DDS",
    "wof:placetype":"venue"
},
  "geometry": {"coordinates":[-98.505657,29.356614],"type":"Point"}
}