{
  "type": "Feature",
  "properties": {
    "iso:country":"US",
    "sg:address":"5950 Salcon Cliff Dr",
    "sg:city":"Austin",
    "sg:classifiers":[
        {
            "category":"Real Estate",
            "subcategory":"Real Estate Services",
            "type":"Services"
        },
        {
            "category":"Real Estate",
            "subcategory":"Surveying",
            "type":"Services"
        }
    ],
    "sg:phone":"+1 512 288 0344",
    "sg:postcode":"78749",
    "sg:province":"TX",
    "sg:tags":[
        "industrial",
        "appraisers-commercial",
        "appraiser"
    ],
    "wof:name":"Southwest Valuation",
    "wof:placetype":"venue"
},
  "geometry": {"coordinates":[-97.875844,30.205358],"type":"Point"}
}