{
  "type": "Feature",
  "properties": {
    "iso:country":"US",
    "sg:address":"2013 S Washington St",
    "sg:city":"Kaufman",
    "sg:classifiers":[
        {
            "category":"Autos & Motor Vehicles",
            "subcategory":"Auto Supplies",
            "type":"Retail Goods"
        }
    ],
    "sg:phone":"+1 972 932 0130",
    "sg:postcode":"75142",
    "sg:province":"TX",
    "sg:tags":[
        "automobile",
        "parts"
    ],
    "wof:name":"Autozone",
    "wof:placetype":"venue"
},
  "geometry": {"coordinates":[-96.30900200000001,32.576296],"type":"Point"}
}