{
  "type": "Feature",
  "properties": {
    "iso:country":"US",
    "sg:address":"1901 N Central Expy",
    "sg:city":"Richardson",
    "sg:classifiers":[
        {
            "category":"Insurance",
            "subcategory":"Insurance Agent",
            "type":"Services"
        }
    ],
    "sg:phone":"+1 972 889 1247",
    "sg:postcode":"75080",
    "sg:province":"TX",
    "wof:name":"Mc Casland Financial Svc",
    "wof:placetype":"venue"
},
  "geometry": {"coordinates":[-96.71660300000001,32.975366],"type":"Point"}
}