{
  "type": "Feature",
  "properties": {
    "iso:country":"US",
    "sg:address":"700 N Harwood St",
    "sg:city":"Dallas",
    "sg:classifiers":[
        {
            "category":"Sports & Exercise",
            "subcategory":"Gym",
            "type":"Entertainment"
        }
    ],
    "sg:phone":"+1 214 220 2423",
    "sg:postcode":"75201",
    "sg:province":"TX",
    "sg:tags":[
        "club",
        "studio",
        "health",
        "gymnasium"
    ],
    "sg:website":"www.24hourfitness.com",
    "wof:name":"24 Hour Fitness",
    "wof:placetype":"venue"
},
  "geometry": {"coordinates":[-96.79756500000001,32.785524],"type":"Point"}
}