{
  "type": "Feature",
  "properties": {
    "iso:country":"US",
    "sg:address":"4328 Briar Creek Ln",
    "sg:city":"Dallas",
    "sg:classifiers":[
        {
            "category":"Real Estate",
            "subcategory":"Real Estate Agent",
            "type":"Services"
        }
    ],
    "sg:phone":"+1 214 824 3388",
    "sg:postcode":"75214",
    "sg:province":"TX",
    "sg:website":"www.donwilliams.com",
    "wof:name":"Don Williams Co Realtors",
    "wof:placetype":"venue"
},
  "geometry": {"coordinates":[-96.748763,32.839638],"type":"Point"}
}