{
  "type": "Feature",
  "properties": {
    "iso:country":"US",
    "sg:address":"2012 Lake Air Dr",
    "sg:city":"Waco",
    "sg:classifiers":[
        {
            "category":"Health Services",
            "subcategory":"Doctor",
            "type":"Services"
        }
    ],
    "sg:phone":"+1 254 751 7100",
    "sg:postcode":"76710",
    "sg:province":"TX",
    "wof:name":"Theodore J Lawson DDS",
    "wof:placetype":"venue"
},
  "geometry": {"coordinates":[-97.19380700000001,31.544819],"type":"Point"}
}