{
  "type": "Feature",
  "properties": {
    "iso:country":"US",
    "sg:address":"837 Moffett Springs Rd",
    "sg:city":"Huntsville",
    "sg:classifiers":[
        {
            "category":"Professional",
            "subcategory":"Management & Consulting",
            "type":"Services"
        }
    ],
    "sg:phone":"+1 936 435 9914",
    "sg:postcode":"77320",
    "sg:province":"TX",
    "sg:tags":[
        "business"
    ],
    "wof:name":"Tk Services",
    "wof:placetype":"venue"
},
  "geometry": {"coordinates":[-95.60062600000001,30.749749],"type":"Point"}
}