{
  "type": "Feature",
  "properties": {
    "iso:country":"US",
    "sg:address":"131 Ewing Pl",
    "sg:city":"San Antonio",
    "sg:classifiers":[
        {
            "category":"Retail",
            "subcategory":"Repair Shop",
            "type":"Services"
        }
    ],
    "sg:phone":"+1 210 738 2350",
    "sg:postcode":"78201",
    "sg:province":"TX",
    "sg:tags":[
        "welding"
    ],
    "wof:name":"Rodriguez Welding Service",
    "wof:placetype":"venue"
},
  "geometry": {"coordinates":[-98.545023,29.475532],"type":"Point"}
}