{
  "type": "Feature",
  "properties": {
    "iso:country":"US",
    "sg:address":"8208 Stony Creek Dr",
    "sg:city":"Dallas",
    "sg:classifiers":[
        {
            "category":"Real Estate",
            "subcategory":"Real Estate Services",
            "type":"Services"
        }
    ],
    "sg:phone":"+1 214 660 3155",
    "sg:postcode":"75228",
    "sg:province":"TX",
    "sg:tags":[
        "apartment",
        "rental",
        "finder"
    ],
    "wof:name":"The Mill At Stonycreek",
    "wof:placetype":"venue"
},
  "geometry": {"coordinates":[-96.708505,32.802526],"type":"Point"}
}