{
  "type": "Feature",
  "properties": {
    "iso:country":"US",
    "sg:address":"100 Sandau Rd",
    "sg:city":"San Antonio",
    "sg:classifiers":[
        {
            "category":"Wholesale",
            "subcategory":"Office Equipment",
            "type":"Manufacturing & Wholesale Goods"
        }
    ],
    "sg:phone":"+1 210 377 3655",
    "sg:postcode":"78216",
    "sg:province":"TX",
    "sg:tags":[
        "machine",
        "duplicating",
        "copying"
    ],
    "sg:website":"www.lanier.com",
    "wof:name":"Lanier Worldwide Inc",
    "wof:placetype":"venue"
},
  "geometry": {"coordinates":[-98.49065,29.541466],"type":"Point"}
}