{
  "type": "Feature",
  "properties": {
    "iso:country":"US",
    "sg:address":"213 Leonard Dr",
    "sg:city":"Longview",
    "sg:classifiers":[
        {
            "category":"Professional",
            "subcategory":"Business Services",
            "type":"Services"
        }
    ],
    "sg:phone":"+1 903 758 7338",
    "sg:postcode":"75602",
    "sg:province":"TX",
    "wof:name":"Joint Heirs Recording",
    "wof:placetype":"venue"
},
  "geometry": {"coordinates":[-94.736991,32.468387],"type":"Point"}
}