{
  "type": "Feature",
  "properties": {
    "iso:country":"US",
    "sg:address":"121 E San Augustine St",
    "sg:city":"Deer Park",
    "sg:classifiers":[
        {
            "category":"Professional",
            "subcategory":"Accounting & Tax Preparation",
            "type":"Services"
        }
    ],
    "sg:phone":"+1 281 479 5765",
    "sg:postcode":"77536",
    "sg:province":"TX",
    "sg:tags":[
        "bookkeeping",
        "general"
    ],
    "wof:name":"Diamond Consultants",
    "wof:placetype":"venue"
},
  "geometry": {"coordinates":[-95.120144,29.689665],"type":"Point"}
}