{
  "type": "Feature",
  "properties": {
    "iso:country":"US",
    "sg:address":"4366 Thousand Oaks Dr",
    "sg:city":"San Antonio",
    "sg:classifiers":[
        {
            "category":"Education",
            "subcategory":"Special Training",
            "type":"Public Place"
        }
    ],
    "sg:phone":"+1 210 654 3029",
    "sg:postcode":"78217",
    "sg:province":"TX",
    "sg:tags":[
        "instruction",
        "driving"
    ],
    "wof:name":"That's The Ticket Defensive",
    "wof:placetype":"venue"
},
  "geometry": {"coordinates":[-98.409092,29.551663],"type":"Point"}
}