{
  "type": "Feature",
  "properties": {
    "iso:country":"US",
    "sg:address":"2500 Strawberry Rd",
    "sg:city":"Pasadena",
    "sg:classifiers":[
        {
            "category":"Professional",
            "subcategory":"Computer Services",
            "type":"Services"
        }
    ],
    "sg:phone":"+1 713 477 0559",
    "sg:postcode":"77502",
    "sg:province":"TX",
    "sg:tags":[
        "design",
        "system"
    ],
    "wof:name":"Mtz Cad Service",
    "wof:placetype":"venue"
},
  "geometry": {"coordinates":[-95.193005,29.6744],"type":"Point"}
}