{
  "type": "Feature",
  "properties": {
    "iso:country":"US",
    "sg:address":"6110 Greenville Ave",
    "sg:city":"Dallas",
    "sg:classifiers":[
        {
            "category":"Manufacturing",
            "subcategory":"Signs",
            "type":"Manufacturing & Wholesale Goods"
        }
    ],
    "sg:phone":"+1 214 987 4467",
    "sg:postcode":"75206",
    "sg:province":"TX",
    "wof:name":"Sign-A-Rama",
    "wof:placetype":"venue"
},
  "geometry": {"coordinates":[-96.767933,32.859953],"type":"Point"}
}