{
  "type": "Feature",
  "properties": {
    "iso:country":"US",
    "sg:address":"2121 N Collins St",
    "sg:city":"Arlington",
    "sg:classifiers":[
        {
            "category":"Utilities",
            "subcategory":"Mobile Phone",
            "type":"Services"
        }
    ],
    "sg:phone":"+1 817 274 2800",
    "sg:postcode":"76011",
    "sg:province":"TX",
    "sg:tags":[
        "telephone",
        "cellular"
    ],
    "wof:name":"Wireless Point 11",
    "wof:placetype":"venue"
},
  "geometry": {"coordinates":[-97.096942,32.768736],"type":"Point"}
}