{
  "type": "Feature",
  "properties": {
    "iso:country":"US",
    "sg:address":"5000 Quorum Dr",
    "sg:city":"Dallas",
    "sg:classifiers":[
        {
            "category":"Personal",
            "subcategory":"Beauty Salon",
            "type":"Services"
        }
    ],
    "sg:phone":"+1 972 239 1449",
    "sg:postcode":"75254",
    "sg:province":"TX",
    "sg:tags":[
        "treatment",
        "skin"
    ],
    "wof:name":"Euro Products Intl Inc",
    "wof:placetype":"venue"
},
  "geometry": {"coordinates":[-96.825504,32.948383],"type":"Point"}
}