{
  "type": "Feature",
  "properties": {
    "iso:country":"US",
    "sg:address":"2122 Hidden Creek Dr",
    "sg:city":"Humble",
    "sg:classifiers":[
        {
            "category":"Professional",
            "subcategory":"Computer Services",
            "type":"Services"
        }
    ],
    "sg:phone":"+1 281 358 8722",
    "sg:postcode":"77339",
    "sg:province":"TX",
    "sg:tags":[
        "consultant",
        "designer"
    ],
    "wof:name":"Nexsystems",
    "wof:placetype":"venue"
},
  "geometry": {"coordinates":[-95.22089800000001,30.049912],"type":"Point"}
}