{
  "type": "Feature",
  "properties": {
    "iso:country":"US",
    "sg:address":"547 Brown Trl",
    "sg:city":"Hurst",
    "sg:classifiers":[
        {
            "category":"Food & Beverages",
            "subcategory":"Groceries & Convenience Stores",
            "type":"Retail Goods"
        }
    ],
    "sg:phone":"+1 817 285 8807",
    "sg:postcode":"76053",
    "sg:province":"TX",
    "wof:name":"Allamah Inc",
    "wof:placetype":"venue"
},
  "geometry": {"coordinates":[-97.164614,32.818976],"type":"Point"}
}