{
  "type": "Feature",
  "properties": {
    "iso:country":"US",
    "sg:address":"4211 Todd Ln",
    "sg:city":"Austin",
    "sg:classifiers":[
        {
            "category":"Retail",
            "subcategory":"Repair Shop",
            "type":"Services"
        },
        {
            "category":"Retail",
            "subcategory":"Auto Repair",
            "type":"Services"
        }
    ],
    "sg:phone":"+1 512 444 3971",
    "sg:postcode":"78744",
    "sg:province":"TX",
    "sg:tags":[
        "automobile",
        "top",
        "upholstery"
    ],
    "wof:name":"Ben's Upholstery",
    "wof:placetype":"venue"
},
  "geometry": {"coordinates":[-97.738984,30.20933],"type":"Point"}
}