{
  "type": "Feature",
  "properties": {
    "iso:country":"US",
    "sg:address":"210 Arnold Ave",
    "sg:city":"Arlington",
    "sg:classifiers":[
        {
            "category":"Wholesale",
            "subcategory":"Machinery & Supplies",
            "type":"Manufacturing & Wholesale Goods"
        }
    ],
    "sg:phone":"+1 817 461 5419",
    "sg:postcode":"76010",
    "sg:province":"TX",
    "sg:tags":[
        "equipment",
        "irrigation",
        "system"
    ],
    "wof:name":"L & J Lawn Sprinkler Mntnc",
    "wof:placetype":"venue"
},
  "geometry": {"coordinates":[-97.094041,32.734125],"type":"Point"}
}