{
  "type": "Feature",
  "properties": {
    "iso:country":"US",
    "sg:address":"1018 Saunders St",
    "sg:city":"Waller",
    "sg:classifiers":[
        {
            "category":"Shopping",
            "subcategory":"Department Store",
            "type":"Retail Goods"
        },
        {
            "category":"Shopping",
            "subcategory":"Discount & Variety Stores",
            "type":"Retail Goods"
        }
    ],
    "sg:phone":"+1 936 372 3116",
    "sg:postcode":"77484",
    "sg:province":"TX",
    "wof:name":"D & M Dollar Store",
    "wof:placetype":"venue"
},
  "geometry": {"coordinates":[-95.924053,30.059595],"type":"Point"}
}