{
  "type": "Feature",
  "properties": {
    "iso:country":"US",
    "sg:address":"32219 Willow Creek Park",
    "sg:city":"Conroe",
    "sg:classifiers":[
        {
            "category":"Wholesale",
            "subcategory":"Hardware",
            "type":"Manufacturing & Wholesale Goods"
        }
    ],
    "sg:phone":"+1 281 419 8563",
    "sg:postcode":"77385",
    "sg:province":"TX",
    "sg:tags":[
        "hardware-wholesale",
        "manufacturer"
    ],
    "wof:name":"Lee Walton Bradley",
    "wof:placetype":"venue"
},
  "geometry": {"coordinates":[-95.406738,30.151402],"type":"Point"}
}