{
  "type": "Feature",
  "properties": {
    "iso:country":"US",
    "sg:address":"6730 Cullen Blvd",
    "sg:city":"Houston",
    "sg:classifiers":[
        {
            "category":"Retail",
            "subcategory":"Portrait Studio",
            "type":"Services"
        }
    ],
    "sg:phone":"+1 713 748 6000",
    "sg:postcode":"77021",
    "sg:province":"TX",
    "sg:tags":[
        "photographer"
    ],
    "wof:name":"All Occasions Photography",
    "wof:placetype":"venue"
},
  "geometry": {"coordinates":[-95.353448,29.690047],"type":"Point"}
}