{
  "type": "Feature",
  "properties": {
    "iso:country":"US",
    "sg:address":"2851 W Euless Blvd Ste 200",
    "sg:city":"Euless",
    "sg:classifiers":[
        {
            "category":"Home & Garden",
            "subcategory":"Building Materials",
            "type":"Retail Goods"
        },
        {
            "category":"Home & Garden",
            "subcategory":"Home Furnishings",
            "type":"Retail Goods"
        },
        {
            "category":"Professional",
            "subcategory":"Art Services",
            "type":"Services"
        },
        {
            "category":"Manufacturing",
            "subcategory":"Signs",
            "type":"Manufacturing & Wholesale Goods"
        }
    ],
    "sg:phone":"+1 817 318 7800",
    "sg:postcode":"76040",
    "sg:province":"TX",
    "sg:tags":[
        "graphic",
        "signs-erectors",
        "fixture",
        "designer",
        "lighting",
        "awning",
        "canopy",
        "hanger"
    ],
    "wof:name":"Signs Up",
    "wof:placetype":"venue"
},
  "geometry": {"coordinates":[-97.132609,32.817036],"type":"Point"}
}