{
  "type": "Feature",
  "properties": {
    "iso:country":"US",
    "sg:address":"9100 Westminster Glen Ave",
    "sg:city":"Austin",
    "sg:classifiers":[
        {
            "category":"Autos & Motor Vehicles",
            "subcategory":"Auto Supplies",
            "type":"Retail Goods"
        }
    ],
    "sg:phone":"+1 512 576 0631",
    "sg:postcode":"78730",
    "sg:province":"TX",
    "wof:name":"Greenlight Solutions Ltd Co",
    "wof:placetype":"venue"
},
  "geometry": {"coordinates":[-97.83855699999999,30.365239],"type":"Point"}
}