{
  "type": "Feature",
  "properties": {
    "iso:country":"US",
    "sg:address":"18700 Weiss Ln",
    "sg:city":"Pflugerville",
    "sg:classifiers":[
        {
            "category":"Social Services",
            "subcategory":"Child Care",
            "type":"Services"
        }
    ],
    "sg:phone":"+1 512 251 4321",
    "sg:postcode":"78660",
    "sg:province":"TX",
    "wof:name":"Kinder Haus Childcare Inc",
    "wof:placetype":"venue"
},
  "geometry": {"coordinates":[-97.560292,30.449073],"type":"Point"}
}