{
  "type": "Feature",
  "properties": {
    "iso:country":"US",
    "sg:address":"4 Llano Dr",
    "sg:city":"Roanoke",
    "sg:classifiers":[
        {
            "category":"Organizations",
            "subcategory":"Religious Organization",
            "type":"Services"
        }
    ],
    "sg:phone":"+1 682 831 9896",
    "sg:postcode":"76262",
    "sg:province":"TX",
    "sg:tags":[
        "church"
    ],
    "wof:name":"Highland Church",
    "wof:placetype":"venue"
},
  "geometry": {"coordinates":[-97.20734,33.00058],"type":"Point"}
}