{
  "type": "Feature",
  "properties": {
    "iso:country":"US",
    "sg:address":"7815 Arapaho Rd",
    "sg:city":"Dallas",
    "sg:classifiers":[
        {
            "category":"Organizations",
            "subcategory":"Religious Organization",
            "type":"Services"
        }
    ],
    "sg:phone":"+1 972 661 0526",
    "sg:postcode":"75248",
    "sg:province":"TX",
    "wof:name":"Fellowship Bible Church",
    "wof:placetype":"venue"
},
  "geometry": {"coordinates":[-96.773189,32.962138],"type":"Point"}
}