{
  "type": "Feature",
  "properties": {
    "iso:country":"US",
    "sg:address":"2512 S State Hwy 36",
    "sg:city":"Gatesville",
    "sg:classifiers":[
        {
            "category":"Personal",
            "subcategory":"Beauty Salon",
            "type":"Services"
        }
    ],
    "sg:phone":"+1 254 865 5514",
    "sg:postcode":"76528",
    "sg:province":"TX",
    "wof:name":"Cinderella Beauty Shop",
    "wof:placetype":"venue"
},
  "geometry": {"coordinates":[-97.72754999999999,31.430829],"type":"Point"}
}