{
  "type": "Feature",
  "properties": {
    "iso:country":"US",
    "sg:address":"1006 E 1st",
    "sg:city":"Hughes Springs",
    "sg:classifiers":[
        {
            "category":"Restaurant",
            "type":"Food & Drink"
        }
    ],
    "sg:menulink":"http://www.allmenus.com/tx/hughes-springs-avinger/204114-sonic/menu/",
    "sg:phone":"+1 903 639 1551",
    "sg:postcode":"75656",
    "sg:province":"TX",
    "sg:tags":[
        "burger",
        "american"
    ],
    "wof:name":"Sonic",
    "wof:placetype":"venue"
},
  "geometry": {"coordinates":[-94.61923400000001,32.998337],"type":"Point"}
}