{
  "type": "Feature",
  "properties": {
    "iso:country":"US",
    "sg:address":"2523 Fairway Park Dr",
    "sg:city":"Houston",
    "sg:classifiers":[
        {
            "category":"Wholesale",
            "subcategory":"Furniture",
            "type":"Manufacturing & Wholesale Goods"
        }
    ],
    "sg:phone":"+1 713 688 3373",
    "sg:postcode":"77092",
    "sg:province":"TX",
    "sg:tags":[
        "furniture-wholesale",
        "manufacturer"
    ],
    "wof:name":"Supreme Bar Supply",
    "wof:placetype":"venue"
},
  "geometry": {"coordinates":[-95.467506,29.812288],"type":"Point"}
}