{
  "type": "Feature",
  "properties": {
    "iso:country":"US",
    "sg:address":"16110 Brimfield Dr",
    "sg:city":"Houston",
    "sg:classifiers":[
        {
            "category":"Restaurant",
            "type":"Food & Drink"
        }
    ],
    "sg:phone":"+1 281 752 8872",
    "sg:postcode":"77082",
    "sg:province":"TX",
    "sg:tags":[
        "eating"
    ],
    "wof:name":"Donnellys Catering",
    "wof:placetype":"venue"
},
  "geometry": {"coordinates":[-95.66909,29.720741],"type":"Point"}
}