{
  "type": "Feature",
  "properties": {
    "iso:country":"US",
    "sg:address":"1523 Chilton Ln",
    "sg:city":"Katy",
    "sg:classifiers":[
        {
            "category":"Real Estate",
            "subcategory":"Real Estate Agent",
            "type":"Services"
        }
    ],
    "sg:phone":"+1 281 398 9844",
    "sg:postcode":"77493",
    "sg:province":"TX",
    "wof:name":"KATY Property Management",
    "wof:placetype":"venue"
},
  "geometry": {"coordinates":[-95.81476600000001,29.79494],"type":"Point"}
}