{
  "type": "Feature",
  "properties": {
    "iso:country":"US",
    "sg:address":"812 Washington St",
    "sg:city":"South Houston",
    "sg:classifiers":[
        {
            "category":"Building & Trades",
            "subcategory":"Construction",
            "type":"Services"
        }
    ],
    "sg:phone":"+1 713 947 6784",
    "sg:postcode":"77587",
    "sg:province":"TX",
    "sg:tags":[
        "contractor"
    ],
    "wof:name":"Garcia Roofing & Insulation",
    "wof:placetype":"venue"
},
  "geometry": {"coordinates":[-95.238535,29.658171],"type":"Point"}
}