{
  "type": "Feature",
  "properties": {
    "iso:country":"US",
    "sg:address":"6810 Arrow Way",
    "sg:city":"San Antonio",
    "sg:classifiers":[
        {
            "category":"Professional",
            "subcategory":"Management & Consulting",
            "type":"Services"
        }
    ],
    "sg:phone":"+1 210 698 6401",
    "sg:postcode":"78256",
    "sg:province":"TX",
    "sg:tags":[
        "business"
    ],
    "wof:name":"Cheline Inc",
    "wof:placetype":"venue"
},
  "geometry": {"coordinates":[-98.616753,29.609502],"type":"Point"}
}