{
  "type": "Feature",
  "properties": {
    "iso:country":"US",
    "sg:address":"328 Dobbs Ave",
    "sg:city":"Odessa",
    "sg:classifiers":[
        {
            "category":"Organizations",
            "subcategory":"Community Association",
            "type":"Services"
        }
    ],
    "sg:phone":"+1 432 337 9229",
    "sg:postcode":"79761",
    "sg:province":"TX",
    "sg:tags":[
        "eating"
    ],
    "wof:name":"Ector Lions Club & Bingo Hall",
    "wof:placetype":"venue"
},
  "geometry": {"coordinates":[-102.343903,31.849611],"type":"Point"}
}