{
  "type": "Feature",
  "properties": {
    "iso:country":"US",
    "sg:address":"637 W Jefferson Blvd",
    "sg:city":"Dallas",
    "sg:classifiers":[
        {
            "category":"Banks & Credit Unions",
            "subcategory":"Bank",
            "type":"Services"
        }
    ],
    "sg:phone":"+1 972 237 0514",
    "sg:postcode":"75208",
    "sg:province":"TX",
    "sg:tags":[
        "depository",
        "banking",
        "library",
        "research"
    ],
    "wof:name":"Atmex Multi Services Metr",
    "wof:placetype":"venue"
},
  "geometry": {"coordinates":[-96.83281100000001,32.74316],"type":"Point"}
}