{
  "type": "Feature",
  "properties": {
    "iso:country":"US",
    "sg:address":"6463 Buchanan Rd",
    "sg:city":"Texarkana",
    "sg:classifiers":[
        {
            "category":"Building & Trades",
            "subcategory":"Construction",
            "type":"Services"
        }
    ],
    "sg:phone":"+1 903 792 7512",
    "sg:postcode":"75501",
    "sg:province":"TX",
    "sg:tags":[
        "wallcoverings-installation",
        "wallpaper",
        "painting",
        "contractor"
    ],
    "wof:name":"Jesses Painting Co",
    "wof:placetype":"venue"
},
  "geometry": {"coordinates":[-94.06357300000001,33.336641],"type":"Point"}
}