{
  "type": "Feature",
  "properties": {
    "iso:country":"US",
    "sg:address":"1820 Poggenpohl St",
    "sg:city":"Laredo",
    "sg:classifiers":[
        {
            "category":"Freight",
            "type":"Transportation"
        }
    ],
    "sg:phone":"+1 956 724 6968",
    "sg:postcode":"78040",
    "sg:province":"TX",
    "wof:name":"Luis AE Gonzalez Hijos Frwdng",
    "wof:placetype":"venue"
},
  "geometry": {"coordinates":[-99.513891,27.520093],"type":"Point"}
}