{
  "type": "Feature",
  "properties": {
    "iso:country":"US",
    "sg:address":"4141 S Braeswood Blvd",
    "sg:city":"Houston",
    "sg:classifiers":[
        {
            "category":"Health Services",
            "subcategory":"Nursing And Care Facility",
            "type":"Services"
        }
    ],
    "sg:phone":"+1 713 666 2651",
    "sg:postcode":"77025",
    "sg:province":"TX",
    "sg:tags":[
        "home",
        "convalescent",
        "retirement"
    ],
    "sg:website":"http://www.houstonretirement.org",
    "wof:name":"Bayou Manor",
    "wof:placetype":"venue"
},
  "geometry": {"coordinates":[-95.445156,29.687222],"type":"Point"}
}