{
  "type": "Feature",
  "properties": {
    "iso:country":"US",
    "sg:address":"8097 Antoine Dr",
    "sg:city":"Houston",
    "sg:classifiers":[
        {
            "category":"Shopping",
            "subcategory":"Clothing, Apparel, & Fashions",
            "type":"Retail Goods"
        }
    ],
    "sg:phone":"+1 281 448 3339",
    "sg:postcode":"77088",
    "sg:province":"TX",
    "sg:tags":[
        "alteration"
    ],
    "wof:name":"Ann Tailors",
    "wof:placetype":"venue"
},
  "geometry": {"coordinates":[-95.47404400000001,29.885102],"type":"Point"}
}