{
  "type": "Feature",
  "properties": {
    "iso:country":"US",
    "sg:address":"7102 Morrow Ct",
    "sg:city":"Sugar Land",
    "sg:classifiers":[
        {
            "category":"Professional",
            "subcategory":"Computer Services",
            "type":"Services"
        }
    ],
    "sg:phone":"+1 832 489 8278",
    "sg:postcode":"77479",
    "sg:province":"TX",
    "sg:tags":[
        "related"
    ],
    "wof:name":"Softcover Inc",
    "wof:placetype":"venue"
},
  "geometry": {"coordinates":[-95.665538,29.587753],"type":"Point"}
}