{
  "type": "Feature",
  "properties": {
    "iso:country":"US",
    "sg:address":"609 Amistad Dr",
    "sg:city":"Laredo",
    "sg:classifiers":[
        {
            "category":"Retail",
            "subcategory":"Auto Repair",
            "type":"Services"
        }
    ],
    "sg:phone":"+1 956 795 0101",
    "sg:postcode":"78041",
    "sg:province":"TX",
    "sg:tags":[
        "body",
        "automobile",
        "painting"
    ],
    "wof:name":"MAACO Auto Painting & Bodywork",
    "wof:placetype":"venue"
},
  "geometry": {"coordinates":[-99.481544,27.553857],"type":"Point"}
}