{
  "type": "Feature",
  "properties": {
    "iso:country":"US",
    "sg:address":"7501 Folkstone Dr",
    "sg:city":"Fort Worth",
    "sg:classifiers":[
        {
            "category":"Social Services",
            "subcategory":"Child Care",
            "type":"Services"
        }
    ],
    "sg:phone":"+1 817 483 1590",
    "sg:postcode":"76140",
    "sg:province":"TX",
    "wof:name":"Perry Celestine",
    "wof:placetype":"venue"
},
  "geometry": {"coordinates":[-97.266682,32.649431],"type":"Point"}
}