{
  "type": "Feature",
  "properties": {
    "iso:country":"US",
    "sg:address":"1407 15th Pl",
    "sg:city":"Plano",
    "sg:classifiers":[
        {
            "category":"Building & Trades",
            "subcategory":"Landscaping Services",
            "type":"Services"
        }
    ],
    "sg:phone":"+1 972 881 8268",
    "sg:postcode":"75074",
    "sg:province":"TX",
    "sg:tags":[
        "landscape"
    ],
    "wof:name":"Chicos Landscaping",
    "wof:placetype":"venue"
},
  "geometry": {"coordinates":[-96.693573,33.020773],"type":"Point"}
}