{
  "type": "Feature",
  "properties": {
    "iso:country":"US",
    "sg:address":"3424 Eddy St",
    "sg:city":"Amarillo",
    "sg:classifiers":[
        {
            "category":"Professional",
            "type":"Services"
        }
    ],
    "sg:phone":"+1 806 352 9389",
    "sg:postcode":"79109",
    "sg:province":"TX",
    "wof:name":"Brady Tree Service",
    "wof:placetype":"venue"
},
  "geometry": {"coordinates":[-101.886312,35.174111],"type":"Point"}
}