{
  "type": "Feature",
  "properties": {
    "iso:country":"US",
    "sg:address":"101 W Church St",
    "sg:city":"Livingston",
    "sg:classifiers":[
        {
            "category":"Government",
            "subcategory":"Court House",
            "type":"Public Place"
        }
    ],
    "sg:phone":"+1 936 327 6814",
    "sg:postcode":"77351",
    "sg:province":"TX",
    "sg:tags":[
        "legal"
    ],
    "wof:name":"Government County",
    "wof:placetype":"venue"
},
  "geometry": {"coordinates":[-94.93386,30.71101],"type":"Point"}
}