{
  "type": "Feature",
  "properties": {
    "iso:country":"US",
    "sg:address":"5005 E Ben White Blvd",
    "sg:city":"Austin",
    "sg:classifiers":[
        {
            "category":"Home & Garden",
            "subcategory":"Building Materials",
            "type":"Retail Goods"
        }
    ],
    "sg:phone":"+1 512 385 6166",
    "sg:postcode":"78741",
    "sg:province":"TX",
    "sg:tags":[
        "lumber"
    ],
    "wof:name":"Ace Contractors Supply",
    "wof:placetype":"venue"
},
  "geometry": {"coordinates":[-97.72394300000001,30.213663],"type":"Point"}
}