{
  "type": "Feature",
  "properties": {
    "iso:country":"US",
    "sg:address":"3301 S Sage Ct",
    "sg:city":"Bedford",
    "sg:classifiers":[
        {
            "category":"Professional",
            "subcategory":"Business Services",
            "type":"Services"
        }
    ],
    "sg:phone":"+1 877 734 2484",
    "sg:postcode":"76021",
    "sg:province":"TX",
    "wof:name":"Promatix Promotional Products",
    "wof:placetype":"venue"
},
  "geometry": {"coordinates":[-97.13117800000001,32.857822],"type":"Point"}
}