{
  "type": "Feature",
  "properties": {
    "iso:country":"US",
    "sg:address":"1200 Ross Ave",
    "sg:city":"Dallas",
    "sg:classifiers":[
        {
            "category":"Professional",
            "subcategory":"Lawyer & Legal Services",
            "type":"Services"
        }
    ],
    "sg:phone":"+1 214 754 0909",
    "sg:postcode":"75202",
    "sg:province":"TX",
    "wof:name":"Anderson Michael Hal Atty",
    "wof:placetype":"venue"
},
  "geometry": {"coordinates":[-96.80390199999999,32.783001],"type":"Point"}
}