{
  "type": "Feature",
  "properties": {
    "iso:country":"US",
    "sg:address":"14203 FM 1314",
    "sg:city":"Conroe",
    "sg:classifiers":[
        {
            "category":"Food & Beverages",
            "subcategory":"Bakery",
            "type":"Retail Goods"
        }
    ],
    "sg:phone":"+1 936 446 1028",
    "sg:postcode":"77302",
    "sg:province":"TX",
    "wof:name":"Linda S Brown",
    "wof:placetype":"venue"
},
  "geometry": {"coordinates":[-95.39115700000001,30.249095],"type":"Point"}
}