{
  "type": "Feature",
  "properties": {
    "iso:country":"US",
    "sg:address":"361 Hill Rd",
    "sg:city":"Kerrville",
    "sg:classifiers":[
        {
            "category":"Professional",
            "type":"Services"
        }
    ],
    "sg:phone":"+1 830 257 9073",
    "sg:postcode":"78003",
    "sg:province":"TX",
    "wof:name":"Osborne Services & Prison",
    "wof:placetype":"venue"
},
  "geometry": {"coordinates":[-99.184082,29.767298],"type":"Point"}
}