{
  "type": "Feature",
  "properties": {
    "iso:country":"US",
    "sg:address":"5910 de Milo Dr",
    "sg:city":"Houston",
    "sg:classifiers":[
        {
            "category":"Professional",
            "type":"Services"
        }
    ],
    "sg:phone":"+1 713 686 7294",
    "sg:postcode":"77092",
    "sg:province":"TX",
    "wof:name":"Robert S Simpson Co",
    "wof:placetype":"venue"
},
  "geometry": {"coordinates":[-95.475399,29.833899],"type":"Point"}
}