{
  "type": "Feature",
  "properties": {
    "iso:country":"US",
    "sg:address":"2112 University Club Dr",
    "sg:city":"Austin",
    "sg:classifiers":[
        {
            "category":"Building & Trades",
            "subcategory":"Construction",
            "type":"Services"
        }
    ],
    "sg:phone":"+1 512 266 6769",
    "sg:postcode":"78732",
    "sg:province":"TX",
    "sg:tags":[
        "contractor"
    ],
    "wof:name":"Dress Custom Homes Lp",
    "wof:placetype":"venue"
},
  "geometry": {"coordinates":[-97.893069,30.355195],"type":"Point"}
}