{
  "type": "Feature",
  "properties": {
    "iso:country":"US",
    "sg:address":"7913 Rendon Bloodworth Rd",
    "sg:city":"Mansfield",
    "sg:classifiers":[
        {
            "category":"Retail",
            "subcategory":"Auto Repair",
            "type":"Services"
        }
    ],
    "sg:phone":"+1 817 477 3790",
    "sg:postcode":"76063",
    "sg:province":"TX",
    "sg:tags":[
        "repairing",
        "body",
        "automotive",
        "automobile"
    ],
    "wof:name":"Jordan's Automotive",
    "wof:placetype":"venue"
},
  "geometry": {"coordinates":[-97.21914099999999,32.576352],"type":"Point"}
}