{
  "type": "Feature",
  "properties": {
    "iso:country":"US",
    "sg:address":"450 Oxford Dr",
    "sg:city":"Gordonville",
    "sg:classifiers":[
        {
            "category":"Freight",
            "type":"Transportation"
        }
    ],
    "sg:phone":"+1 903 523 0056",
    "sg:postcode":"76245",
    "sg:province":"TX",
    "sg:tags":[
        "dock"
    ],
    "wof:name":"Texoma Custom Dock",
    "wof:placetype":"venue"
},
  "geometry": {"coordinates":[-96.825999,33.855852],"type":"Point"}
}