{
  "type": "Feature",
  "properties": {
    "iso:country":"US",
    "sg:address":"450 Gears Rd",
    "sg:city":"Houston",
    "sg:classifiers":[
        {
            "category":"Insurance",
            "subcategory":"Insurance Agent",
            "type":"Services"
        }
    ],
    "sg:phone":"+1 713 874 9600",
    "sg:postcode":"77067",
    "sg:province":"TX",
    "wof:name":"Hartford",
    "wof:placetype":"venue"
},
  "geometry": {"coordinates":[-95.41921499999999,29.945403],"type":"Point"}
}