{
  "type": "Feature",
  "properties": {
    "iso:country":"US",
    "sg:address":"306 Brooks St",
    "sg:city":"Sugar Land",
    "sg:classifiers":[
        {
            "category":"Insurance",
            "subcategory":"Insurance Agent",
            "type":"Services"
        }
    ],
    "sg:phone":"+1 281 242 3755",
    "sg:postcode":"77478",
    "sg:province":"TX",
    "wof:name":"Eric Brand Insurance",
    "wof:placetype":"venue"
},
  "geometry": {"coordinates":[-95.63515200000001,29.616813],"type":"Point"}
}