{
  "type": "Feature",
  "properties": {
    "iso:country":"US",
    "sg:address":"2264 S Ww White Rd",
    "sg:city":"San Antonio",
    "sg:classifiers":[
        {
            "category":"Food & Beverages",
            "subcategory":"Groceries & Convenience Stores",
            "type":"Retail Goods"
        }
    ],
    "sg:phone":"+1 210 333 6665",
    "sg:postcode":"78222",
    "sg:province":"TX",
    "wof:name":"Speedy Stop",
    "wof:placetype":"venue"
},
  "geometry": {"coordinates":[-98.404573,29.391603],"type":"Point"}
}