{
  "type": "Feature",
  "properties": {
    "iso:country":"US",
    "sg:address":"3501 Lebanon Ave",
    "sg:city":"El Paso",
    "sg:classifiers":[
        {
            "category":"Wholesale",
            "subcategory":"Meat",
            "type":"Manufacturing & Wholesale Goods"
        }
    ],
    "sg:phone":"+1 915 577 0779",
    "sg:postcode":"79930",
    "sg:province":"TX",
    "wof:name":"Paisano Foods Corp",
    "wof:placetype":"venue"
},
  "geometry": {"coordinates":[-106.450841,31.79396],"type":"Point"}
}