{
  "type": "Feature",
  "properties": {
    "iso:country":"US",
    "sg:address":"4334 Shady Pine Dr",
    "sg:city":"Spring",
    "sg:classifiers":[
        {
            "category":"Wholesale",
            "subcategory":"Machinery & Supplies",
            "type":"Manufacturing & Wholesale Goods"
        }
    ],
    "sg:phone":"+1 281 651 9557",
    "sg:postcode":"77388",
    "sg:province":"TX",
    "sg:tags":[
        "equipment",
        "rep",
        "material",
        "handling",
        "mfg"
    ],
    "wof:name":"C Morse & Associates Inc",
    "wof:placetype":"venue"
},
  "geometry": {"coordinates":[-95.478009,30.028427],"type":"Point"}
}