{
  "type": "Feature",
  "properties": {
    "iso:country":"US",
    "sg:address":"418 S Ervay St",
    "sg:city":"Dallas",
    "sg:classifiers":[
        {
            "category":"Restaurant",
            "type":"Food & Drink"
        }
    ],
    "sg:phone":"+1 214 742 2114",
    "sg:postcode":"75201",
    "sg:province":"TX",
    "wof:name":"Deluxe Diner",
    "wof:placetype":"venue"
},
  "geometry": {"coordinates":[-96.7967,32.778801],"type":"Point"}
}