{
  "type": "Feature",
  "properties": {
    "iso:country":"US",
    "sg:address":"901 Kck Way",
    "sg:city":"Cedar Hill",
    "sg:classifiers":[
        {
            "category":"Education",
            "subcategory":"Special Training",
            "type":"Public Place"
        },
        {
            "category":"Professional",
            "subcategory":"Employment Agencies",
            "type":"Services"
        }
    ],
    "sg:phone":"+1 469 272 3434",
    "sg:postcode":"75104",
    "sg:province":"TX",
    "sg:tags":[
        "school",
        "instruction",
        "help",
        "driving",
        "supply"
    ],
    "wof:name":"C R England Inc",
    "wof:placetype":"venue"
},
  "geometry": {"coordinates":[-96.962097,32.568901],"type":"Point"}
}