{
  "type": "Feature",
  "properties": {
    "iso:country":"US",
    "sg:address":"1550 Aldine Bender Rd",
    "sg:city":"Houston",
    "sg:classifiers":[
        {
            "category":"Food & Beverages",
            "subcategory":"Bakery",
            "type":"Retail Goods"
        }
    ],
    "sg:phone":"+1 281 590 5060",
    "sg:postcode":"77032",
    "sg:province":"TX",
    "sg:tags":[
        "sandwich"
    ],
    "sg:website":"www.sandwichesexpress.com",
    "wof:name":"Sandwiches Express",
    "wof:placetype":"venue"
},
  "geometry": {"coordinates":[-95.3638,29.932301],"type":"Point"}
}