{
  "type": "Feature",
  "properties": {
    "iso:country":"US",
    "sg:address":"5412 E Martin Luther King Jr Blvd",
    "sg:city":"Austin",
    "sg:classifiers":[
        {
            "category":"Social Services",
            "subcategory":"Child Care",
            "type":"Services"
        }
    ],
    "sg:phone":"+1 512 929 3311",
    "sg:postcode":"78721",
    "sg:province":"TX",
    "sg:tags":[
        "day"
    ],
    "wof:name":"French Hall Academy",
    "wof:placetype":"venue"
},
  "geometry": {"coordinates":[-97.672802,30.286854],"type":"Point"}
}