{
  "type": "Feature",
  "properties": {
    "iso:country":"US",
    "sg:address":"10205 Vaquero Trl",
    "sg:city":"Austin",
    "sg:classifiers":[
        {
            "category":"Manufacturing",
            "subcategory":"Petroleum Products",
            "type":"Manufacturing & Wholesale Goods"
        }
    ],
    "sg:phone":"+1 512 336 2895",
    "sg:postcode":"78759",
    "sg:province":"TX",
    "sg:tags":[
        "contract"
    ],
    "wof:name":"Colejen Industries",
    "wof:placetype":"venue"
},
  "geometry": {"coordinates":[-97.78969499999999,30.418586],"type":"Point"}
}