{
  "type": "Feature",
  "properties": {
    "iso:country":"US",
    "sg:address":"507 W 17th St",
    "sg:city":"Austin",
    "sg:classifiers":[
        {
            "category":"Transit Center",
            "subcategory":"Freight",
            "type":"Transportation"
        },
        {
            "category":"Freight",
            "type":"Transportation"
        },
        {
            "category":"Professional",
            "subcategory":"Business Services",
            "type":"Services"
        },
        {
            "category":"Taxi",
            "type":"Transportation"
        },
        {
            "category":"Government",
            "subcategory":"Post Office",
            "type":"Public Place"
        }
    ],
    "sg:phone":"+1 512 473 2904",
    "sg:postcode":"78701",
    "sg:province":"TX",
    "sg:tags":[
        "trucking-motor",
        "courier",
        "trucking",
        "delivery",
        "messenger",
        "local"
    ],
    "wof:name":"Datamovers Delivery Service",
    "wof:placetype":"venue"
},
  "geometry": {"coordinates":[-97.743444,30.280048],"type":"Point"}
}