{
  "type": "Feature",
  "properties": {
    "iso:country":"US",
    "sg:address":"1002 Steves Ave",
    "sg:city":"San Antonio",
    "sg:classifiers":[
        {
            "category":"Food & Beverages",
            "subcategory":"Liquor & Beverages",
            "type":"Retail Goods"
        }
    ],
    "sg:phone":"+1 210 534 1831",
    "sg:postcode":"78210",
    "sg:province":"TX",
    "sg:tags":[
        "coin",
        "laundry",
        "alcoholic"
    ],
    "wof:name":"Ellis HI Ball",
    "wof:placetype":"venue"
},
  "geometry": {"coordinates":[-98.47727999999999,29.391154],"type":"Point"}
}