{
  "type": "Feature",
  "properties": {
    "iso:country":"US",
    "sg:address":"1608 Handley Dr",
    "sg:city":"Fort Worth",
    "sg:classifiers":[
        {
            "category":"Restaurant",
            "type":"Food & Drink"
        }
    ],
    "sg:phone":"+1 817 451 8046",
    "sg:postcode":"76112",
    "sg:province":"TX",
    "sg:tags":[
        "eating"
    ],
    "wof:name":"Taco Bueno 3030",
    "wof:placetype":"venue"
},
  "geometry": {"coordinates":[-97.214127,32.756814],"type":"Point"}
}