{
  "type": "Feature",
  "properties": {
    "iso:country":"US",
    "sg:address":"1070 Madewell Rd",
    "sg:city":"Paris",
    "sg:classifiers":[
        {
            "category":"Building & Trades",
            "subcategory":"Electrical",
            "type":"Services"
        }
    ],
    "sg:phone":"+1 903 982 5211",
    "sg:postcode":"75462",
    "sg:province":"TX",
    "sg:tags":[
        "repair",
        "electrical",
        "contractor"
    ],
    "wof:name":"Joe Bybee Telephone Service",
    "wof:placetype":"venue"
},
  "geometry": {"coordinates":[-95.418216,33.66361],"type":"Point"}
}