{
  "type": "Feature",
  "properties": {
    "iso:country":"US",
    "sg:address":"8623 Martin Luther King Jr Blvd",
    "sg:city":"Houston",
    "sg:classifiers":[
        {
            "category":"Personal",
            "subcategory":"Beauty Salon",
            "type":"Services"
        }
    ],
    "sg:phone":"+1 713 731 8048",
    "sg:postcode":"77033",
    "sg:province":"TX",
    "sg:tags":[
        "shop"
    ],
    "wof:name":"Pro Nails",
    "wof:placetype":"venue"
},
  "geometry": {"coordinates":[-95.33650299999999,29.657913],"type":"Point"}
}