{
  "type": "Feature",
  "properties": {
    "iso:country":"US",
    "sg:address":"PO Box 2136",
    "sg:city":"Austin",
    "sg:classifiers":[
        {
            "category":"Professional",
            "subcategory":"Computer Services",
            "type":"Services"
        }
    ],
    "sg:phone":"+1 866 387 7363",
    "sg:postcode":"78768-2136",
    "sg:province":"TX",
    "sg:tags":[
        "prepaid",
        "prepaid-debit",
        "visa",
        "mastercard",
        "reloadable",
        "debit-cards"
    ],
    "sg:website":"http://netspend.com",
    "wof:name":"NetSpend",
    "wof:placetype":"venue"
},
  "geometry": {"coordinates":[-97.771258,30.326374],"type":"Point"}
}