{
  "type": "Feature",
  "properties": {
    "iso:country":"US",
    "sg:address":"402 Heights Blvd",
    "sg:city":"Houston",
    "sg:classifiers":[
        {
            "category":"Sports & Exercise",
            "subcategory":"Golf",
            "type":"Entertainment"
        }
    ],
    "sg:phone":"+1 713 522 4547",
    "sg:postcode":"77007",
    "sg:province":"TX",
    "wof:name":"Bsl Golf Corp",
    "wof:placetype":"venue"
},
  "geometry": {"coordinates":[-95.39720199999999,29.778],"type":"Point"}
}