{
  "type": "Feature",
  "properties": {
    "iso:country":"US",
    "sg:address":"2517 Edward Ln",
    "sg:city":"Laredo",
    "sg:classifiers":[
        {
            "category":"Freight",
            "type":"Transportation"
        }
    ],
    "sg:phone":"+1 956 725 8237",
    "sg:postcode":"78046",
    "sg:province":"TX",
    "sg:tags":[
        "operator",
        "local",
        "trucking"
    ],
    "wof:name":"Conrado Valina Jr",
    "wof:placetype":"venue"
},
  "geometry": {"coordinates":[-99.472039,27.450589],"type":"Point"}
}