{
  "type": "Feature",
  "properties": {
    "iso:country":"US",
    "sg:address":"4715 Widerop Ln",
    "sg:city":"Friendswood",
    "sg:classifiers":[
        {
            "category":"Professional",
            "type":"Services"
        }
    ],
    "sg:phone":"+1 281 992 3717",
    "sg:postcode":"77546",
    "sg:province":"TX",
    "wof:name":"Pierrettes",
    "wof:placetype":"venue"
},
  "geometry": {"coordinates":[-95.17853599999999,29.538348],"type":"Point"}
}