{
  "type": "Feature",
  "properties": {
    "iso:country":"US",
    "sg:address":"5701 Kayview Dr",
    "sg:city":"Austin",
    "sg:classifiers":[
        {
            "category":"Personal",
            "type":"Services"
        }
    ],
    "sg:phone":"+1 512 288 3916",
    "sg:postcode":"78749",
    "sg:province":"TX",
    "sg:tags":[
        "bureau"
    ],
    "wof:name":"Kathryn's Concierge Inc",
    "wof:placetype":"venue"
},
  "geometry": {"coordinates":[-97.863741,30.218819],"type":"Point"}
}