{
  "type": "Feature",
  "properties": {
    "iso:country":"US",
    "sg:address":"1005 Buckingham Ct",
    "sg:city":"Friendswood",
    "sg:classifiers":[
        {
            "category":"Real Estate",
            "subcategory":"Real Estate Agent",
            "type":"Services"
        }
    ],
    "sg:phone":"+1 281 993 0282",
    "sg:postcode":"77546",
    "sg:province":"TX",
    "wof:name":"Chigger Creek Management LLC",
    "wof:placetype":"venue"
},
  "geometry": {"coordinates":[-95.19987999999999,29.505903],"type":"Point"}
}