{
  "type": "Feature",
  "properties": {
    "iso:country":"US",
    "sg:address":"19002 Dallas Pkwy",
    "sg:city":"Dallas",
    "sg:classifiers":[
        {
            "category":"Freight",
            "type":"Transportation"
        }
    ],
    "sg:phone":"+1 972 735 8943",
    "sg:postcode":"75287",
    "sg:province":"TX",
    "sg:tags":[
        "mover"
    ],
    "wof:name":"A Personal Touch Movers",
    "wof:placetype":"venue"
},
  "geometry": {"coordinates":[-96.828399,33.012831],"type":"Point"}
}