{
  "type": "Feature",
  "properties": {
    "iso:country":"US",
    "sg:address":"1000 McKinley St",
    "sg:city":"Benbrook",
    "sg:classifiers":[
        {
            "category":"Social Services",
            "subcategory":"Job Training",
            "type":"Services"
        }
    ],
    "sg:phone":"+1 817 249 0022",
    "sg:postcode":"76126",
    "sg:province":"TX",
    "sg:tags":[
        "rehabilitation"
    ],
    "wof:name":"Benbrook Nursing & Rehab",
    "wof:placetype":"venue"
},
  "geometry": {"coordinates":[-97.46589,32.675429],"type":"Point"}
}