{
  "type": "Feature",
  "properties": {
    "iso:country":"US",
    "sg:address":"1813 Fuller St",
    "sg:city":"Greenville",
    "sg:classifiers":[
        {
            "category":"Insurance",
            "subcategory":"Hazard Insurance",
            "type":"Services"
        }
    ],
    "sg:phone":"+1 903 455 7155",
    "sg:postcode":"75401",
    "sg:province":"TX",
    "sg:tags":[
        "bond"
    ],
    "wof:name":"Sherry's Good Bail Bonds",
    "wof:placetype":"venue"
},
  "geometry": {"coordinates":[-96.110382,33.144683],"type":"Point"}
}