{
  "type": "Feature",
  "properties": {
    "iso:country":"US",
    "sg:address":"12514 Sableleaf Dr",
    "sg:city":"Cypress",
    "sg:classifiers":[
        {
            "category":"Wholesale",
            "subcategory":"Machinery & Supplies",
            "type":"Manufacturing & Wholesale Goods"
        }
    ],
    "sg:phone":"+1 281 890 8039",
    "sg:postcode":"77429",
    "sg:province":"TX",
    "sg:tags":[
        "equipment",
        "industrial"
    ],
    "wof:name":"Tcb Enterprises",
    "wof:placetype":"venue"
},
  "geometry": {"coordinates":[-95.59764,29.956699],"type":"Point"}
}