{
  "type": "Feature",
  "properties": {
    "iso:country":"US",
    "sg:address":"109 W Sabine St",
    "sg:city":"Carthage",
    "sg:classifiers":[
        {
            "category":"Shopping",
            "subcategory":"Florist",
            "type":"Retail Goods"
        }
    ],
    "sg:phone":"+1 903 693 5768",
    "sg:postcode":"75633",
    "sg:province":"TX",
    "wof:name":"Violet Shop",
    "wof:placetype":"venue"
},
  "geometry": {"coordinates":[-94.338571,32.156502],"type":"Point"}
}