{
  "type": "Feature",
  "properties": {
    "iso:country":"US",
    "sg:address":"200 N Loraine St",
    "sg:city":"Midland",
    "sg:classifiers":[
        {
            "category":"Banks & Credit Unions",
            "subcategory":"Bank",
            "type":"Services"
        }
    ],
    "sg:phone":"+1 432 570 6100",
    "sg:postcode":"79701",
    "sg:province":"TX",
    "sg:website":"www.ssbank.com",
    "wof:name":"Security State Bank",
    "wof:placetype":"venue"
},
  "geometry": {"coordinates":[-102.07566,31.999575],"type":"Point"}
}