{
  "type": "Feature",
  "properties": {
    "iso:country":"US",
    "sg:address":"400 Black St",
    "sg:city":"Schulenburg",
    "sg:classifiers":[
        {
            "category":"Education",
            "subcategory":"School",
            "type":"Public Place"
        }
    ],
    "sg:phone":"+1 979 743 3080",
    "sg:postcode":"78956",
    "sg:province":"TX",
    "wof:name":"St Rose School",
    "wof:placetype":"venue"
},
  "geometry": {"coordinates":[-96.90320699999999,29.675897],"type":"Point"}
}