{
  "type": "Feature",
  "properties": {
    "iso:country":"US",
    "sg:address":"5127 Ave U",
    "sg:city":"Galveston",
    "sg:classifiers":[
        {
            "category":"Organizations",
            "subcategory":"Religious Organization",
            "type":"Services"
        }
    ],
    "sg:phone":"+1 409 744 6510",
    "sg:postcode":"77551",
    "sg:province":"TX",
    "wof:name":"Westminster Presbt Church",
    "wof:placetype":"venue"
},
  "geometry": {"coordinates":[-94.819275,29.274737],"type":"Point"}
}