{
  "type": "Feature",
  "properties": {
    "iso:country":"US",
    "sg:address":"14654 Spring Cypress Rd",
    "sg:city":"Cypress",
    "sg:classifiers":[
        {
            "category":"Recreation",
            "type":"Entertainment"
        }
    ],
    "sg:phone":"+1 281 376 2372",
    "sg:postcode":"77429",
    "sg:province":"TX",
    "sg:tags":[
        "instruction",
        "swimming"
    ],
    "sg:website":"www.fleetswimming.com",
    "wof:name":"Cy-Fair Swim Club",
    "wof:placetype":"venue"
},
  "geometry": {"coordinates":[-95.64249100000001,29.998112],"type":"Point"}
}