{
  "type": "Feature",
  "properties": {
    "iso:country":"US",
    "sg:address":"8920 Lambright Rd",
    "sg:city":"Houston",
    "sg:classifiers":[
        {
            "category":"Professional",
            "subcategory":"Business Services",
            "type":"Services"
        }
    ],
    "sg:phone":"+1 713 991 3811",
    "sg:postcode":"77075",
    "sg:province":"TX",
    "wof:name":"Berlanga Enterprises",
    "wof:placetype":"venue"
},
  "geometry": {"coordinates":[-95.261876,29.622864],"type":"Point"}
}