{
  "type": "Feature",
  "properties": {
    "iso:country":"US",
    "sg:address":"420 E Royall Blvd",
    "sg:city":"Malakoff",
    "sg:classifiers":[
        {
            "category":"Real Estate",
            "subcategory":"Real Estate Services",
            "type":"Services"
        },
        {
            "category":"Real Estate",
            "subcategory":"Real Estate Agent",
            "type":"Services"
        }
    ],
    "sg:phone":"+1 903 489 1300",
    "sg:postcode":"75148",
    "sg:province":"TX",
    "sg:tags":[
        "buyer",
        "broker"
    ],
    "sg:website":"http://www.mcateerealty.net",
    "wof:name":"Mc Atee Realty Inc",
    "wof:placetype":"venue"
},
  "geometry": {"coordinates":[-96.006895,32.172211],"type":"Point"}
}