{
  "type": "Feature",
  "properties": {
    "iso:country":"US",
    "sg:address":"315 E Oakdale Rd",
    "sg:city":"Irving",
    "sg:classifiers":[
        {
            "category":"Building & Trades",
            "subcategory":"Construction",
            "type":"Services"
        }
    ],
    "sg:phone":"+1 972 253 7183",
    "sg:postcode":"75060",
    "sg:province":"TX",
    "sg:tags":[
        "excavation",
        "contractor"
    ],
    "wof:name":"Potts Grading",
    "wof:placetype":"venue"
},
  "geometry": {"coordinates":[-96.943864,32.793993],"type":"Point"}
}