{
  "type": "Feature",
  "properties": {
    "iso:country":"US",
    "sg:address":"3167 FM 2727",
    "sg:city":"Kaufman",
    "sg:classifiers":[
        {
            "category":"Autos & Motor Vehicles",
            "subcategory":"Automobile Sales",
            "type":"Retail Goods"
        }
    ],
    "sg:phone":"+1 972 962 8925",
    "sg:postcode":"75142",
    "sg:province":"TX",
    "sg:tags":[
        "car",
        "dealer"
    ],
    "wof:name":"Gillespie Motors",
    "wof:placetype":"venue"
},
  "geometry": {"coordinates":[-96.251446,32.603915],"type":"Point"}
}