{
  "type": "Feature",
  "properties": {
    "iso:country":"US",
    "sg:address":"303 E Crockett St",
    "sg:city":"Cleveland",
    "sg:classifiers":[
        {
            "category":"Retail",
            "subcategory":"Funeral Services",
            "type":"Services"
        }
    ],
    "sg:phone":"+1 281 592 2641",
    "sg:postcode":"77327",
    "sg:province":"TX",
    "sg:tags":[
        "director"
    ],
    "wof:name":"Pace-Stancil Funeral Home",
    "wof:placetype":"venue"
},
  "geometry": {"coordinates":[-95.085369,30.3424],"type":"Point"}
}