{
  "type": "Feature",
  "properties": {
    "iso:country":"US",
    "sg:address":"3406 Marshall St",
    "sg:city":"Vernon",
    "sg:classifiers":[
        {
            "category":"Shopping",
            "subcategory":"Gifts & Souvenirs",
            "type":"Retail Goods"
        }
    ],
    "sg:phone":"+1 940 552 7009",
    "sg:postcode":"76384",
    "sg:province":"TX",
    "sg:tags":[
        "shop"
    ],
    "wof:name":"Classic Gifts",
    "wof:placetype":"venue"
},
  "geometry": {"coordinates":[-99.30141399999999,34.151665],"type":"Point"}
}