{
  "type": "Feature",
  "properties": {
    "iso:country":"US",
    "sg:address":"1 N Milton St",
    "sg:city":"San Angelo",
    "sg:classifiers":[
        {
            "category":"Social Services",
            "type":"Services"
        }
    ],
    "sg:phone":"+1 325 486 0704",
    "sg:postcode":"76901",
    "sg:province":"TX",
    "sg:tags":[
        "counselor",
        "marriage",
        "family"
    ],
    "wof:name":"Live Oak Counseling",
    "wof:placetype":"venue"
},
  "geometry": {"coordinates":[-100.461023,31.455434],"type":"Point"}
}