{
  "type": "Feature",
  "properties": {
    "iso:country":"US",
    "sg:address":"414 Executive Center Blvd",
    "sg:city":"El Paso",
    "sg:classifiers":[
        {
            "category":"Professional",
            "subcategory":"Management & Consulting",
            "type":"Services"
        }
    ],
    "sg:phone":"+1 915 351 1900",
    "sg:postcode":"79902",
    "sg:province":"TX",
    "sg:tags":[
        "engineering"
    ],
    "wof:name":"Construction Management",
    "wof:placetype":"venue"
},
  "geometry": {"coordinates":[-106.513435,31.795305],"type":"Point"}
}