{
  "type": "Feature",
  "properties": {
    "iso:country":"US",
    "sg:address":"1125 Lawrence St",
    "sg:city":"Houston",
    "sg:classifiers":[
        {
            "category":"Education",
            "subcategory":"School",
            "type":"Public Place"
        }
    ],
    "sg:phone":"+1 713 868 9797",
    "sg:postcode":"77008",
    "sg:province":"TX",
    "wof:name":"Heights Charter School",
    "wof:placetype":"venue"
},
  "geometry": {"coordinates":[-95.40720399999999,29.791201],"type":"Point"}
}