{
  "type": "Feature",
  "properties": {
    "iso:country":"US",
    "sg:address":"3803 Redbud Dr W",
    "sg:city":"La Porte",
    "sg:classifiers":[
        {
            "category":"Professional",
            "type":"Services"
        }
    ],
    "sg:phone":"+1 281 471 4816",
    "sg:postcode":"77571",
    "sg:province":"TX",
    "wof:name":"Basket Kreations By There",
    "wof:placetype":"venue"
},
  "geometry": {"coordinates":[-95.061007,29.65493],"type":"Point"}
}