{
  "type": "Feature",
  "properties": {
    "iso:country":"US",
    "sg:address":"111 N Marsalis Ave",
    "sg:city":"Dallas",
    "sg:classifiers":[
        {
            "category":"Travel",
            "subcategory":"Travel Agent",
            "type":"Entertainment"
        }
    ],
    "sg:phone":"+1 214 942 9980",
    "sg:postcode":"75203",
    "sg:province":"TX",
    "sg:tags":[
        "tour",
        "promoter"
    ],
    "wof:name":"Gto Tours",
    "wof:placetype":"venue"
},
  "geometry": {"coordinates":[-96.815804,32.749001],"type":"Point"}
}