{
  "type": "Feature",
  "properties": {
    "iso:country":"US",
    "sg:address":"5318 Matney Ln",
    "sg:city":"Tyler",
    "sg:classifiers":[
        {
            "category":"Shopping",
            "subcategory":"Shoes",
            "type":"Retail Goods"
        }
    ],
    "sg:phone":"+1 903 566 9491",
    "sg:postcode":"75707",
    "sg:province":"TX",
    "wof:name":"Gonzales Zapaterias",
    "wof:placetype":"venue"
},
  "geometry": {"coordinates":[-95.199611,32.341479],"type":"Point"}
}