{
  "type": "Feature",
  "properties": {
    "iso:country":"US",
    "sg:address":"1325 Rose Ln",
    "sg:city":"Salado",
    "sg:classifiers":[
        {
            "category":"Professional",
            "subcategory":"Business Services",
            "type":"Services"
        }
    ],
    "sg:phone":"+1 254 947 8199",
    "sg:postcode":"76571",
    "sg:province":"TX",
    "sg:tags":[
        "broker"
    ],
    "wof:name":"Veracity Ventures",
    "wof:placetype":"venue"
},
  "geometry": {"coordinates":[-97.516617,30.963638],"type":"Point"}
}