{
  "type": "Feature",
  "properties": {
    "iso:country":"US",
    "sg:address":"21206 Northwest Fwy",
    "sg:city":"Cypress",
    "sg:classifiers":[
        {
            "category":"Home & Garden",
            "subcategory":"Mobile Homes",
            "type":"Retail Goods"
        }
    ],
    "sg:phone":"+1 281 970 1300",
    "sg:postcode":"77429",
    "sg:province":"TX",
    "wof:name":"Factory Homes Of America",
    "wof:placetype":"venue"
},
  "geometry": {"coordinates":[-95.635656,29.926747],"type":"Point"}
}