{
  "type": "Feature",
  "properties": {
    "iso:country":"US",
    "sg:address":"2508 E Riverside Dr",
    "sg:city":"Austin",
    "sg:classifiers":[
        {
            "category":"Professional",
            "type":"Services"
        }
    ],
    "sg:phone":"+1 512 292 6989",
    "sg:postcode":"78741",
    "sg:province":"TX",
    "wof:name":"Aguirres Roasted Corn &",
    "wof:placetype":"venue"
},
  "geometry": {"coordinates":[-97.725934,30.238883],"type":"Point"}
}