{
  "type": "Feature",
  "properties": {
    "iso:country":"US",
    "sg:address":"1518 W 3rd St",
    "sg:city":"Pecos",
    "sg:classifiers":[
        {
            "category":"Retail",
            "subcategory":"Repair Shop",
            "type":"Services"
        }
    ],
    "sg:phone":"+1 432 445 9844",
    "sg:postcode":"79772",
    "sg:province":"TX",
    "sg:tags":[
        "upholsterer"
    ],
    "wof:name":"J & J Upholstery",
    "wof:placetype":"venue"
},
  "geometry": {"coordinates":[-103.509272,31.420653],"type":"Point"}
}