{
  "type": "Feature",
  "properties": {
    "iso:country":"US",
    "sg:address":"505 E Travis St",
    "sg:city":"Marshall",
    "sg:classifiers":[
        {
            "category":"Cinema",
            "subcategory":"Movie Rental",
            "type":"Entertainment"
        }
    ],
    "sg:phone":"+1 903 934 9100",
    "sg:postcode":"75670",
    "sg:province":"TX",
    "sg:tags":[
        "video",
        "tape"
    ],
    "wof:name":"American Video Graphics LP",
    "wof:placetype":"venue"
},
  "geometry": {"coordinates":[-94.363202,32.541683],"type":"Point"}
}