{
  "type": "Feature",
  "properties": {
    "iso:country":"US",
    "sg:address":"10136 Cromwell Dr",
    "sg:city":"Dallas",
    "sg:classifiers":[
        {
            "category":"Retail",
            "subcategory":"Repair Shop",
            "type":"Services"
        }
    ],
    "sg:phone":"+1 214 350 5250",
    "sg:postcode":"75229",
    "sg:province":"TX",
    "sg:tags":[
        "antique"
    ],
    "sg:website":"www.chattelfurniturerepair.com",
    "wof:name":"Chattel Furniture Repair",
    "wof:placetype":"venue"
},
  "geometry": {"coordinates":[-96.86190000000001,32.884701],"type":"Point"}
}