{
  "type": "Feature",
  "properties": {
    "iso:country":"US",
    "sg:address":"2111 North St",
    "sg:city":"Nacogdoches",
    "sg:classifiers":[
        {
            "category":"Wholesale",
            "subcategory":"Electrical",
            "type":"Manufacturing & Wholesale Goods"
        }
    ],
    "sg:phone":"+1 936 462 1160",
    "sg:postcode":"75965",
    "sg:province":"TX",
    "sg:tags":[
        "radio"
    ],
    "wof:name":"Hawk Electronics",
    "wof:placetype":"venue"
},
  "geometry": {"coordinates":[-94.652412,31.623703],"type":"Point"}
}