{
  "type": "Feature",
  "properties": {
    "iso:country":"US",
    "sg:address":"3107 McCann Rd",
    "sg:city":"Longview",
    "sg:classifiers":[
        {
            "category":"Insurance",
            "subcategory":"Insurance Agent",
            "type":"Services"
        }
    ],
    "sg:phone":"+1 903 753 8934",
    "sg:postcode":"75605",
    "sg:province":"TX",
    "wof:name":"State Farm Insurance",
    "wof:placetype":"venue"
},
  "geometry": {"coordinates":[-94.75334700000001,32.534507],"type":"Point"}
}