{
  "type": "Feature",
  "properties": {
    "iso:country":"US",
    "sg:address":"3904 Fountain Ter",
    "sg:city":"Amarillo",
    "sg:classifiers":[
        {
            "category":"Manufacturing",
            "subcategory":"Glass & Minerals",
            "type":"Manufacturing & Wholesale Goods"
        }
    ],
    "sg:phone":"+1 806 337 1637",
    "sg:postcode":"79106",
    "sg:province":"TX",
    "sg:tags":[
        "mfg"
    ],
    "wof:name":"Jazzy Glazz",
    "wof:placetype":"venue"
},
  "geometry": {"coordinates":[-101.882672,35.205463],"type":"Point"}
}