{
  "type": "Feature",
  "properties": {
    "iso:country":"US",
    "sg:address":"417 State Hwy 100",
    "sg:city":"Port Isabel",
    "sg:classifiers":[
        {
            "category":"Shopping",
            "subcategory":"Florist",
            "type":"Retail Goods"
        }
    ],
    "sg:phone":"+1 956 943 4344",
    "sg:postcode":"78578",
    "sg:province":"TX",
    "wof:name":"Bridgeview Flowers & Gifts",
    "wof:placetype":"venue"
},
  "geometry": {"coordinates":[-97.20759,26.077469],"type":"Point"}
}