{
  "type": "Feature",
  "properties": {
    "iso:country":"US",
    "sg:address":"903 W 21st St",
    "sg:city":"Odessa",
    "sg:classifiers":[
        {
            "category":"Professional",
            "subcategory":"Art Services",
            "type":"Services"
        }
    ],
    "sg:phone":"+1 432 335 7998",
    "sg:postcode":"79763",
    "sg:province":"TX",
    "sg:tags":[
        "commercial",
        "design"
    ],
    "wof:name":"Jagged Edge-Original Mosa",
    "wof:placetype":"venue"
},
  "geometry": {"coordinates":[-102.39011000000001,31.858245],"type":"Point"}
}