{
  "type": "Feature",
  "properties": {
    "iso:country":"US",
    "sg:address":"5305 Jensen Dr",
    "sg:city":"Houston",
    "sg:classifiers":[
        {
            "category":"Professional",
            "subcategory":"Research",
            "type":"Services"
        }
    ],
    "sg:phone":"+1 713 796 2616",
    "sg:postcode":"77026",
    "sg:province":"TX",
    "sg:tags":[
        "refinery",
        "instrument",
        "for",
        "lab"
    ],
    "wof:name":"Lab Solutions Inc",
    "wof:placetype":"venue"
},
  "geometry": {"coordinates":[-95.342401,29.809228],"type":"Point"}
}