{
  "type": "Feature",
  "properties": {
    "iso:country":"US",
    "sg:address":"1001 Janeil Ln",
    "sg:city":"De Soto",
    "sg:classifiers":[
        {
            "category":"Shopping",
            "subcategory":"Catalog Store",
            "type":"Retail Goods"
        }
    ],
    "sg:phone":"+1 972 230 8724",
    "sg:postcode":"75115",
    "sg:province":"TX",
    "sg:tags":[
        "house",
        "mail"
    ],
    "wof:name":"Patricia R Chaney",
    "wof:placetype":"venue"
},
  "geometry": {"coordinates":[-96.82652400000001,32.573144],"type":"Point"}
}