{
  "type": "Feature",
  "properties": {
    "iso:country":"US",
    "sg:address":"4834 Beechnut St",
    "sg:city":"Houston",
    "sg:classifiers":[
        {
            "category":"Professional",
            "subcategory":"Accounting & Tax Preparation",
            "type":"Services"
        }
    ],
    "sg:phone":"+1 713 664 7719",
    "sg:postcode":"77096",
    "sg:province":"TX",
    "sg:tags":[
        "return",
        "filing"
    ],
    "wof:name":"H & R Block Tax Svc",
    "wof:placetype":"venue"
},
  "geometry": {"coordinates":[-95.462475,29.689259],"type":"Point"}
}