{
  "type": "Feature",
  "properties": {
    "iso:country":"US",
    "sg:address":"6035 Mount Olive Rd",
    "sg:city":"Adkins",
    "sg:classifiers":[
        {
            "category":"Real Estate",
            "subcategory":"Real Estate Operator",
            "type":"Services"
        }
    ],
    "sg:phone":"+1 210 589 4863",
    "sg:postcode":"78101",
    "sg:province":"TX",
    "sg:tags":[
        "apartment"
    ],
    "wof:name":"Sarah Carolanne Davila",
    "wof:placetype":"venue"
},
  "geometry": {"coordinates":[-98.252546,29.36471],"type":"Point"}
}