{
  "type": "Feature",
  "properties": {
    "iso:country":"US",
    "sg:address":"11325 Pegasus St Suite 265E",
    "sg:city":"Dallas",
    "sg:classifiers":[
        {
            "category":"Professional",
            "subcategory":"Lawyer & Legal Services",
            "type":"Services"
        }
    ],
    "sg:phone":"+1 214 265 1199",
    "sg:postcode":"75225",
    "sg:province":"TX",
    "sg:tags":[
        "attorney",
        "plan"
    ],
    "wof:name":"Hunter Kalinke & Boyd",
    "wof:placetype":"venue"
},
  "geometry": {"coordinates":[-96.685891,32.87477],"type":"Point"}
}