{
  "type": "Feature",
  "properties": {
    "iso:country":"US",
    "sg:address":"3920 Alma Dr",
    "sg:city":"Plano",
    "sg:classifiers":[
        {
            "category":"Health Services",
            "subcategory":"Hospital",
            "type":"Services"
        }
    ],
    "sg:phone":"+1 972 422 5939",
    "sg:postcode":"75023",
    "sg:province":"TX",
    "sg:tags":[
        "mental"
    ],
    "wof:name":"Lifepath Systems",
    "wof:placetype":"venue"
},
  "geometry": {"coordinates":[-96.709924,33.048729],"type":"Point"}
}