{
  "type": "Feature",
  "properties": {
    "iso:country":"US",
    "sg:address":"104 N Gentle Dr",
    "sg:city":"Richardson",
    "sg:classifiers":[
        {
            "category":"Freight",
            "type":"Transportation"
        }
    ],
    "sg:phone":"+1 972 235 6427",
    "sg:postcode":"75080",
    "sg:province":"TX",
    "sg:tags":[
        "operator",
        "local",
        "trucking"
    ],
    "wof:name":"Davis Trucking",
    "wof:placetype":"venue"
},
  "geometry": {"coordinates":[-96.74857900000001,32.950954],"type":"Point"}
}