{
  "type": "Feature",
  "properties": {
    "iso:country":"US",
    "sg:address":"2211 Harlandale Ave",
    "sg:city":"Dallas",
    "sg:classifiers":[
        {
            "category":"Professional",
            "type":"Services"
        }
    ],
    "sg:phone":"+1 214 374 6967",
    "sg:postcode":"75216",
    "sg:province":"TX",
    "sg:tags":[
        "establishment"
    ],
    "wof:name":"Faithdeliverance Missionary",
    "wof:placetype":"venue"
},
  "geometry": {"coordinates":[-96.80977,32.72046],"type":"Point"}
}