{
  "type": "Feature",
  "properties": {
    "iso:country":"US",
    "sg:address":"1707 Clubview Dr",
    "sg:city":"Amarillo",
    "sg:classifiers":[
        {
            "category":"Wholesale",
            "subcategory":"Durable Goods & Equipment",
            "type":"Manufacturing & Wholesale Goods"
        }
    ],
    "sg:phone":"+1 806 354 2424",
    "sg:postcode":"79124",
    "sg:province":"TX",
    "sg:tags":[
        "importer"
    ],
    "wof:name":"Coury's Mediterranean Imports",
    "wof:placetype":"venue"
},
  "geometry": {"coordinates":[-101.895527,35.234405],"type":"Point"}
}