{
  "type": "Feature",
  "properties": {
    "iso:country":"US",
    "sg:address":"2995 Blue Bell Ln",
    "sg:city":"Brenham",
    "sg:classifiers":[
        {
            "category":"Shopping",
            "subcategory":"Jewelry",
            "type":"Retail Goods"
        }
    ],
    "sg:phone":"+1 979 830 7288",
    "sg:postcode":"77833",
    "sg:province":"TX",
    "wof:name":"Lauras Jewelry",
    "wof:placetype":"venue"
},
  "geometry": {"coordinates":[-96.304295,30.154058],"type":"Point"}
}