{
  "type": "Feature",
  "properties": {
    "iso:country":"US",
    "sg:address":"9030 Directors Row",
    "sg:city":"Dallas",
    "sg:classifiers":[
        {
            "category":"Wholesale",
            "subcategory":"Chemicals & Plastics",
            "type":"Manufacturing & Wholesale Goods"
        }
    ],
    "sg:phone":"+1 214 630 8657",
    "sg:postcode":"75247",
    "sg:province":"TX",
    "wof:name":"Sunbelt Materials & Supply",
    "wof:placetype":"venue"
},
  "geometry": {"coordinates":[-96.88923699999999,32.81726],"type":"Point"}
}