{
  "type": "Feature",
  "properties": {
    "iso:country":"US",
    "sg:address":"1401 E 8th St",
    "sg:city":"Weslaco",
    "sg:classifiers":[
        {
            "category":"Health Services",
            "subcategory":"Doctor",
            "type":"Services"
        },
        {
            "category":"Health Services",
            "subcategory":"Hospital",
            "type":"Services"
        }
    ],
    "sg:phone":"+1 956 969 5112",
    "sg:postcode":"78596",
    "sg:province":"TX",
    "sg:tags":[
        "consultant",
        "medical",
        "practice",
        "nursing",
        "home"
    ],
    "wof:name":"Knapp Medical Center Foundation, Inc.",
    "wof:placetype":"venue"
},
  "geometry": {"coordinates":[-97.976418,26.15197],"type":"Point"}
}