{
  "type": "Feature",
  "properties": {
    "iso:country":"US",
    "sg:address":"1155 N Center",
    "sg:city":"San Antonio",
    "sg:classifiers":[
        {
            "category":"Wholesale",
            "subcategory":"Fruits & Vegetables",
            "type":"Manufacturing & Wholesale Goods"
        }
    ],
    "sg:phone":"+1 210 472 3820",
    "sg:postcode":"78202",
    "sg:province":"TX",
    "wof:name":"First Produce LTD",
    "wof:placetype":"venue"
},
  "geometry": {"coordinates":[-98.463272,29.422167],"type":"Point"}
}