{
  "type": "Feature",
  "properties": {
    "iso:country":"US",
    "sg:address":"6408 Walebridge Ln",
    "sg:city":"Austin",
    "sg:classifiers":[
        {
            "category":"Social Services",
            "type":"Services"
        }
    ],
    "sg:phone":"+1 512 748 6851",
    "sg:postcode":"78739",
    "sg:province":"TX",
    "wof:name":"Focus Cnseling Assn Ministries",
    "wof:placetype":"venue"
},
  "geometry": {"coordinates":[-97.894209,30.191236],"type":"Point"}
}