{
  "type": "Feature",
  "properties": {
    "iso:country":"US",
    "sg:address":"1111 E College St",
    "sg:city":"Seguin",
    "sg:classifiers":[
        {
            "category":"Building & Trades",
            "subcategory":"Construction",
            "type":"Services"
        }
    ],
    "sg:phone":"+1 830 303 3998",
    "sg:postcode":"78155",
    "sg:province":"TX",
    "sg:tags":[
        "general",
        "contractor"
    ],
    "wof:name":"Bud Bailey Construction",
    "wof:placetype":"venue"
},
  "geometry": {"coordinates":[-97.949277,29.574654],"type":"Point"}
}