{
  "type": "Feature",
  "properties": {
    "iso:country":"US",
    "sg:address":"105 Co Rd 499",
    "sg:city":"Harlingen",
    "sg:classifiers":[
        {
            "category":"Social Services",
            "subcategory":"Adult Care",
            "type":"Services"
        }
    ],
    "sg:phone":"+1 956 425 7035",
    "sg:postcode":"78550",
    "sg:province":"TX",
    "sg:tags":[
        "residential"
    ],
    "wof:name":"Villa of Harlingen",
    "wof:placetype":"venue"
},
  "geometry": {"coordinates":[-97.663194,26.191047],"type":"Point"}
}