{
  "type": "Feature",
  "properties": {
    "iso:country":"US",
    "sg:address":"2513 Lindberg Ave",
    "sg:city":"Mcallen",
    "sg:classifiers":[
        {
            "category":"Retail",
            "subcategory":"Repair Shop",
            "type":"Services"
        }
    ],
    "sg:phone":"+1 956 631 5361",
    "sg:postcode":"78501",
    "sg:province":"TX",
    "wof:name":"Valdez Isaias",
    "wof:placetype":"venue"
},
  "geometry": {"coordinates":[-98.251075,26.195458],"type":"Point"}
}