{
  "type": "Feature",
  "properties": {
    "iso:country":"US",
    "sg:address":"1202 E del Mar Blvd",
    "sg:city":"Laredo",
    "sg:classifiers":[
        {
            "category":"Retail",
            "subcategory":"Portrait Studio",
            "type":"Services"
        }
    ],
    "sg:phone":"+1 956 725 0602",
    "sg:postcode":"78041",
    "sg:province":"TX",
    "sg:tags":[
        "photo"
    ],
    "wof:name":"Avalon Studios",
    "wof:placetype":"venue"
},
  "geometry": {"coordinates":[-99.47314,27.574215],"type":"Point"}
}