{
  "type": "Feature",
  "properties": {
    "iso:country":"US",
    "sg:address":"1037 Texas Ave S",
    "sg:city":"College Station",
    "sg:classifiers":[
        {
            "category":"Restaurant",
            "type":"Food & Drink"
        }
    ],
    "sg:menulink":"http://www.allmenus.com/tx/bryan-college-station/291947-fontana-italian-restaurant/menu/",
    "sg:phone":"+1 979 693 9000",
    "sg:postcode":"77840",
    "sg:province":"TX",
    "sg:tags":[
        "italian"
    ],
    "wof:name":"Fontana Italian Restaurant",
    "wof:placetype":"venue"
},
  "geometry": {"coordinates":[-96.327878,30.622271],"type":"Point"}
}