{
  "type": "Feature",
  "properties": {
    "iso:country":"US",
    "sg:address":"8400 Gaylord Pkwy",
    "sg:city":"Frisco",
    "sg:classifiers":[
        {
            "category":"Real Estate",
            "subcategory":"Real Estate Operator",
            "type":"Services"
        }
    ],
    "sg:phone":"+1 972 668 2986",
    "sg:postcode":"75034",
    "sg:province":"TX",
    "sg:tags":[
        "building",
        "nonresidential"
    ],
    "wof:name":"Centre At Preston Ridge",
    "wof:placetype":"venue"
},
  "geometry": {"coordinates":[-96.81362900000001,33.102216],"type":"Point"}
}