{
  "type": "Feature",
  "properties": {
    "iso:country":"US",
    "sg:address":"3811 S Cooper St",
    "sg:city":"Arlington",
    "sg:classifiers":[
        {
            "category":"Manufacturing",
            "subcategory":"Printing",
            "type":"Manufacturing & Wholesale Goods"
        }
    ],
    "sg:phone":"+1 817 419 9157",
    "sg:postcode":"76015",
    "sg:province":"TX",
    "sg:tags":[
        "screen"
    ],
    "wof:name":"Family Touch",
    "wof:placetype":"venue"
},
  "geometry": {"coordinates":[-97.13327099999999,32.682767],"type":"Point"}
}