{
  "type": "Feature",
  "properties": {
    "iso:country":"US",
    "sg:address":"308 E Edgewood Dr",
    "sg:city":"Friendswood",
    "sg:classifiers":[
        {
            "category":"Health Services",
            "subcategory":"Clinic",
            "type":"Services"
        },
        {
            "category":"Health Services",
            "subcategory":"Chiropractor",
            "type":"Services"
        }
    ],
    "sg:phone":"+1 281 992 4495",
    "sg:postcode":"77546",
    "sg:province":"TX",
    "sg:tags":[
        "chiropractic"
    ],
    "wof:name":"Redding Chiropractic",
    "wof:placetype":"venue"
},
  "geometry": {"coordinates":[-95.20238000000001,29.536923],"type":"Point"}
}