{
  "type": "Feature",
  "properties": {
    "iso:country":"US",
    "sg:address":"9718 Hillcroft St",
    "sg:city":"Houston",
    "sg:classifiers":[
        {
            "category":"Shopping",
            "type":"Retail Goods"
        }
    ],
    "sg:phone":"+1 713 728 3111",
    "sg:postcode":"77096",
    "sg:province":"TX",
    "sg:tags":[
        "shop",
        "gift",
        "memorabilia",
        "baseball",
        "sport",
        "card"
    ],
    "sg:website":"http://www.hltt.com",
    "wof:name":"Hlt & T Sports Distributing Company",
    "wof:placetype":"venue"
},
  "geometry": {"coordinates":[-95.493689,29.674855],"type":"Point"}
}