{
  "type": "Feature",
  "properties": {
    "iso:country":"US",
    "sg:address":"2170 Buckthorne Pl",
    "sg:city":"The Woodlands",
    "sg:classifiers":[
        {
            "category":"Professional",
            "subcategory":"Management & Consulting",
            "type":"Services"
        }
    ],
    "sg:phone":"+1 281 363 1640",
    "sg:postcode":"77380",
    "sg:province":"TX",
    "sg:tags":[
        "consultant",
        "training"
    ],
    "wof:name":"Interfaith Training & Emplymnt",
    "wof:placetype":"venue"
},
  "geometry": {"coordinates":[-95.471028,30.141272],"type":"Point"}
}