{
  "type": "Feature",
  "properties": {
    "iso:country":"US",
    "sg:address":"6405 Ellen Cir",
    "sg:city":"Texarkana",
    "sg:classifiers":[
        {
            "category":"Building & Trades",
            "subcategory":"Construction",
            "type":"Services"
        }
    ],
    "sg:phone":"+1 903 831 6619",
    "sg:postcode":"75503",
    "sg:province":"TX",
    "sg:tags":[
        "house"
    ],
    "wof:name":"Hollingsworth Remodeling",
    "wof:placetype":"venue"
},
  "geometry": {"coordinates":[-94.10768,33.485973],"type":"Point"}
}