{
  "type": "Feature",
  "properties": {
    "iso:country":"US",
    "sg:address":"315 Garraty Rd",
    "sg:city":"San Antonio",
    "sg:classifiers":[
        {
            "category":"Home & Garden",
            "subcategory":"Home Furnishings",
            "type":"Retail Goods"
        },
        {
            "category":"Wholesale",
            "subcategory":"Home Furnishings",
            "type":"Manufacturing & Wholesale Goods"
        }
    ],
    "sg:phone":"+1 210 822 5824",
    "sg:postcode":"78209",
    "sg:province":"TX",
    "sg:tags":[
        "window",
        "covering"
    ],
    "wof:name":"Frans Decor & Window Covering",
    "wof:placetype":"venue"
},
  "geometry": {"coordinates":[-98.45860500000001,29.475016],"type":"Point"}
}