{
  "type": "Feature",
  "properties": {
    "iso:country":"US",
    "sg:address":"6317 Bee Caves Rd. Suite 220",
    "sg:city":"Austin",
    "sg:classifiers":[
        {
            "category":"Personal",
            "subcategory":"Beauty Salon",
            "type":"Services"
        }
    ],
    "sg:phone":"+1 512 330 0984",
    "sg:postcode":"78746",
    "sg:province":"TX",
    "sg:tags":[
        "hair"
    ],
    "sg:website":"www.thehillssalon.com/",
    "wof:name":"The Hills Salon & Spa",
    "wof:placetype":"venue"
},
  "geometry": {"coordinates":[-97.83334000000001,30.296719],"type":"Point"}
}