{
  "type": "Feature",
  "properties": {
    "iso:country":"US",
    "sg:address":"139 Zubicek Rd",
    "sg:city":"Cat Spring",
    "sg:classifiers":[
        {
            "category":"Professional",
            "subcategory":"Business Services",
            "type":"Services"
        }
    ],
    "sg:phone":"+1 979 865 8293",
    "sg:postcode":"78933",
    "sg:province":"TX",
    "wof:name":"Cdr Enterprises",
    "wof:placetype":"venue"
},
  "geometry": {"coordinates":[-96.328369,29.84163],"type":"Point"}
}