{
  "type": "Feature",
  "properties": {
    "iso:country":"US",
    "sg:address":"4397 Calder Ave",
    "sg:city":"Beaumont",
    "sg:classifiers":[
        {
            "category":"Wholesale",
            "subcategory":"Office Equipment",
            "type":"Manufacturing & Wholesale Goods"
        }
    ],
    "sg:phone":"+1 409 899 1575",
    "sg:postcode":"77706",
    "sg:province":"TX",
    "sg:tags":[
        "machine",
        "duplicating",
        "copying"
    ],
    "wof:name":"Laser Recon",
    "wof:placetype":"venue"
},
  "geometry": {"coordinates":[-94.148203,30.086086],"type":"Point"}
}