{
  "type": "Feature",
  "properties": {
    "iso:country":"US",
    "sg:address":"312 E 2nd St",
    "sg:city":"Alice",
    "sg:classifiers":[
        {
            "category":"Health Services",
            "subcategory":"Doctor",
            "type":"Services"
        }
    ],
    "sg:phone":"+1 361 664 5535",
    "sg:postcode":"78332",
    "sg:province":"TX",
    "sg:tags":[
        "physician",
        "surgeon"
    ],
    "wof:name":"Mauricio B Teixeira Associated",
    "wof:placetype":"venue"
},
  "geometry": {"coordinates":[-98.074325,27.752032],"type":"Point"}
}