{
  "type": "Feature",
  "properties": {
    "iso:country":"US",
    "sg:address":"627 Space Way Dr",
    "sg:city":"Duncanville",
    "sg:classifiers":[
        {
            "category":"Manufacturing",
            "subcategory":"Tools & Machinery",
            "type":"Manufacturing & Wholesale Goods"
        }
    ],
    "sg:phone":"+1 972 296 3860",
    "sg:postcode":"75137",
    "sg:province":"TX",
    "sg:tags":[
        "machine",
        "shop"
    ],
    "wof:name":"Wesco Manufacturing Inc",
    "wof:placetype":"venue"
},
  "geometry": {"coordinates":[-96.921598,32.645095],"type":"Point"}
}