{
  "type": "Feature",
  "properties": {
    "iso:country":"US",
    "sg:address":"1886 Schwab Rd",
    "sg:city":"Marion",
    "sg:classifiers":[
        {
            "category":"Professional",
            "type":"Services"
        }
    ],
    "sg:phone":"+1 830 914 4947",
    "sg:postcode":"78124",
    "sg:province":"TX",
    "wof:name":"Edward Wohlfahrt",
    "wof:placetype":"venue"
},
  "geometry": {"coordinates":[-98.097111,29.55132],"type":"Point"}
}