{
  "type": "Feature",
  "properties": {
    "iso:country":"US",
    "sg:address":"411 Simmons St",
    "sg:city":"Denton",
    "sg:classifiers":[
        {
            "category":"Organizations",
            "subcategory":"Religious Organization",
            "type":"Services"
        }
    ],
    "sg:phone":"+1 940 387 5622",
    "sg:postcode":"76205",
    "sg:province":"TX",
    "wof:name":"Church of Christ",
    "wof:placetype":"venue"
},
  "geometry": {"coordinates":[-97.129451,33.204329],"type":"Point"}
}