{
  "type": "Feature",
  "properties": {
    "iso:country":"US",
    "sg:address":"7630 N Beach St",
    "sg:city":"Fort Worth",
    "sg:classifiers":[
        {
            "category":"Retail",
            "subcategory":"Laundry & Dry Cleaning",
            "type":"Services"
        }
    ],
    "sg:phone":"+1 817 498 9400",
    "sg:postcode":"76137",
    "sg:province":"TX",
    "sg:tags":[
        "drycleaning",
        "plant"
    ],
    "wof:name":"My Cleaners",
    "wof:placetype":"venue"
},
  "geometry": {"coordinates":[-97.28977399999999,32.877851],"type":"Point"}
}