{
  "type": "Feature",
  "properties": {
    "iso:country":"US",
    "sg:address":"5821 Aton Ave",
    "sg:city":"Fort Worth",
    "sg:classifiers":[
        {
            "category":"Real Estate",
            "subcategory":"Real Estate Operator",
            "type":"Services"
        }
    ],
    "sg:phone":"+1 817 732 6024",
    "sg:postcode":"76114",
    "sg:province":"TX",
    "sg:tags":[
        "building",
        "nonresidential"
    ],
    "wof:name":"Infinity Properties",
    "wof:placetype":"venue"
},
  "geometry": {"coordinates":[-97.41370999999999,32.753688],"type":"Point"}
}