{
  "type": "Feature",
  "properties": {
    "iso:country":"US",
    "sg:address":"7433 1/2 Navigation Blvd",
    "sg:city":"Houston",
    "sg:classifiers":[
        {
            "category":"Bars & Pubs",
            "subcategory":"Sports Bar",
            "type":"Food & Drink"
        }
    ],
    "sg:phone":"+1 713 928 6575",
    "sg:postcode":"77011",
    "sg:province":"TX",
    "wof:name":"Shorty's Sportsbar",
    "wof:placetype":"venue"
},
  "geometry": {"coordinates":[-95.290093,29.741241],"type":"Point"}
}