{
  "type": "Feature",
  "properties": {
    "iso:country":"US",
    "sg:address":"6323 Lodge St",
    "sg:city":"Houston",
    "sg:classifiers":[
        {
            "category":"Professional",
            "subcategory":"Computer Services",
            "type":"Services"
        }
    ],
    "sg:phone":"+1 713 680 8217",
    "sg:postcode":"77092",
    "sg:province":"TX",
    "sg:tags":[
        "repair"
    ],
    "sg:website":"www.teebaud.com",
    "wof:name":"Normco",
    "wof:placetype":"venue"
},
  "geometry": {"coordinates":[-95.48256600000001,29.830339],"type":"Point"}
}