{
  "type": "Feature",
  "properties": {
    "iso:country":"US",
    "sg:address":"1028 E 16th St",
    "sg:city":"Brownsville",
    "sg:classifiers":[
        {
            "category":"Building & Trades",
            "subcategory":"Pest Control",
            "type":"Services"
        }
    ],
    "sg:phone":"+1 956 542 3270",
    "sg:postcode":"78520",
    "sg:province":"TX",
    "wof:name":"ABC Insect Control",
    "wof:placetype":"venue"
},
  "geometry": {"coordinates":[-97.49097999999999,25.901616],"type":"Point"}
}