{
  "type": "Feature",
  "properties": {
    "iso:country":"US",
    "sg:address":"3125 Jarvis Dr",
    "sg:city":"El Paso",
    "sg:classifiers":[
        {
            "category":"Professional",
            "subcategory":"Business Services",
            "type":"Services"
        }
    ],
    "sg:phone":"+1 915 541 6527",
    "sg:postcode":"79935",
    "sg:province":"TX",
    "wof:name":"Mrq Liquidators",
    "wof:placetype":"venue"
},
  "geometry": {"coordinates":[-106.329621,31.785739],"type":"Point"}
}