{
  "type": "Feature",
  "properties": {
    "iso:country":"US",
    "sg:address":"712 N Frost St",
    "sg:city":"Pampa",
    "sg:classifiers":[
        {
            "category":"Building & Trades",
            "subcategory":"Landscaping Services",
            "type":"Services"
        }
    ],
    "sg:phone":"+1 806 669 6605",
    "sg:postcode":"79065",
    "sg:province":"TX",
    "sg:tags":[
        "lawn",
        "maintenance",
        "grounds"
    ],
    "wof:name":"Milton's Professional Lawn Cr",
    "wof:placetype":"venue"
},
  "geometry": {"coordinates":[-100.967491,35.541725],"type":"Point"}
}