{
  "type": "Feature",
  "properties": {
    "iso:country":"US",
    "sg:address":"107 W Stassney Ln",
    "sg:city":"Austin",
    "sg:phone":"+1 512 388 5091",
    "sg:postcode":"78745",
    "sg:province":"TX",
    "sg:tags":[
        "equipment",
        "supply"
    ],
    "wof:name":"Austin Beverage",
    "wof:placetype":"venue"
},
  "geometry": {"coordinates":[-97.77728399999999,30.206112],"type":"Point"}
}