{
  "type": "Feature",
  "properties": {
    "iso:country":"US",
    "sg:address":"517 Co Rd 305D",
    "sg:city":"Carthage",
    "sg:classifiers":[
        {
            "category":"Real Estate",
            "subcategory":"Real Estate Operator",
            "type":"Services"
        }
    ],
    "sg:phone":"+1 903 693 3673",
    "sg:postcode":"75654",
    "sg:province":"TX",
    "sg:tags":[
        "property",
        "lessor"
    ],
    "wof:name":"Bills Tire & Brakes",
    "wof:placetype":"venue"
},
  "geometry": {"coordinates":[-94.77688499999999,32.121238],"type":"Point"}
}