{
  "type": "Feature",
  "properties": {
    "iso:country":"US",
    "sg:address":"5800 Corporate Dr Ste C1",
    "sg:city":"Houston",
    "sg:classifiers":[
        {
            "category":"Real Estate",
            "subcategory":"Real Estate Services",
            "type":"Services"
        }
    ],
    "sg:phone":"+1 713 270 3222",
    "sg:postcode":"77036",
    "sg:province":"TX",
    "sg:tags":[
        "management",
        "property"
    ],
    "wof:name":"Unicorp Property Management",
    "wof:placetype":"venue"
},
  "geometry": {"coordinates":[-95.551598,29.7166],"type":"Point"}
}