{
  "type": "Feature",
  "properties": {
    "iso:country":"US",
    "sg:address":"9601 White Rock Trl",
    "sg:city":"Dallas",
    "sg:classifiers":[
        {
            "category":"Manufacturing",
            "subcategory":"Metals",
            "type":"Manufacturing & Wholesale Goods"
        }
    ],
    "sg:phone":"+1 214 348 9814",
    "sg:postcode":"75238",
    "sg:province":"TX",
    "sg:tags":[
        "mfg",
        "fabrication",
        "custom"
    ],
    "wof:name":"La Fer and Associates Inc",
    "wof:placetype":"venue"
},
  "geometry": {"coordinates":[-96.72918199999999,32.876531],"type":"Point"}
}