{
  "type": "Feature",
  "properties": {
    "iso:country":"US",
    "sg:address":"171 Medicine Rock",
    "sg:city":"Universal City",
    "sg:classifiers":[
        {
            "category":"Professional",
            "subcategory":"Accounting & Tax Preparation",
            "type":"Services"
        }
    ],
    "sg:phone":"+1 210 659 6272",
    "sg:postcode":"78148",
    "sg:province":"TX",
    "sg:tags":[
        "payroll"
    ],
    "wof:name":"Payroll Processing Svc",
    "wof:placetype":"venue"
},
  "geometry": {"coordinates":[-98.32167099999999,29.536871],"type":"Point"}
}