{
  "type": "Feature",
  "properties": {
    "iso:country":"US",
    "sg:address":"4038 Boone Rd",
    "sg:city":"Houston",
    "sg:classifiers":[
        {
            "category":"Shopping",
            "subcategory":"Computers & Home Electronics",
            "type":"Retail Goods"
        }
    ],
    "sg:phone":"+1 281 564 2004",
    "sg:postcode":"77072",
    "sg:province":"TX",
    "wof:name":"Boom Boom Care Stereo",
    "wof:placetype":"venue"
},
  "geometry": {"coordinates":[-95.575676,29.71598],"type":"Point"}
}