{
  "type": "Feature",
  "properties": {
    "iso:country":"US",
    "sg:address":"408 Bayou Dr",
    "sg:city":"Bay City",
    "sg:classifiers":[
        {
            "category":"Retail",
            "subcategory":"Repair Shop",
            "type":"Services"
        }
    ],
    "sg:phone":"+1 979 245 5440",
    "sg:postcode":"77414",
    "sg:province":"TX",
    "wof:name":"Bayou Bike Works",
    "wof:placetype":"venue"
},
  "geometry": {"coordinates":[-95.928359,28.996958],"type":"Point"}
}