{
  "type": "Feature",
  "properties": {
    "iso:country":"US",
    "sg:address":"207 W Coombs St",
    "sg:city":"Alvin",
    "sg:classifiers":[
        {
            "category":"Shopping",
            "subcategory":"Discount & Variety Stores",
            "type":"Retail Goods"
        }
    ],
    "sg:phone":"+1 281 331 7210",
    "sg:postcode":"77511",
    "sg:province":"TX",
    "wof:name":"Dollar General",
    "wof:placetype":"venue"
},
  "geometry": {"coordinates":[-95.245424,29.417648],"type":"Point"}
}