{
  "type": "Feature",
  "properties": {
    "iso:country":"US",
    "sg:address":"128 Presa Pl",
    "sg:city":"El Paso",
    "sg:classifiers":[
        {
            "category":"Education",
            "subcategory":"School",
            "type":"Public Place"
        }
    ],
    "sg:phone":"+1 915 859 9686",
    "sg:postcode":"79907",
    "sg:province":"TX",
    "sg:tags":[
        "elementary"
    ],
    "wof:name":"Presa Elementary School",
    "wof:placetype":"venue"
},
  "geometry": {"coordinates":[-106.31940899999999,31.689436],"type":"Point"}
}