{
  "type": "Feature",
  "properties": {
    "iso:country":"US",
    "sg:address":"6001 Rampart St",
    "sg:city":"Houston",
    "sg:classifiers":[
        {
            "category":"Professional",
            "type":"Services"
        }
    ],
    "sg:phone":"+1 713 661 3862",
    "sg:postcode":"77081",
    "sg:province":"TX",
    "wof:name":"Jose A Orellana",
    "wof:placetype":"venue"
},
  "geometry": {"coordinates":[-95.488929,29.714637],"type":"Point"}
}