{
  "type": "Feature",
  "properties": {
    "iso:country":"US",
    "sg:address":"230 Oaks St",
    "sg:city":"Whitney",
    "sg:classifiers":[
        {
            "category":"Insurance",
            "subcategory":"Hazard Insurance",
            "type":"Services"
        },
        {
            "category":"Insurance",
            "subcategory":"Insurance Agent",
            "type":"Services"
        }
    ],
    "sg:phone":"+1 254 694 1549",
    "sg:postcode":"76661",
    "sg:province":"TX",
    "sg:tags":[
        "carrier"
    ],
    "wof:name":"Henderson Insurance Agency",
    "wof:placetype":"venue"
},
  "geometry": {"coordinates":[-96.894408,31.308264],"type":"Point"}
}