{
  "type": "Feature",
  "properties": {
    "iso:country":"US",
    "sg:address":"8323 Southwest Fwy",
    "sg:city":"Houston",
    "sg:classifiers":[
        {
            "category":"Professional",
            "subcategory":"Accounting & Tax Preparation",
            "type":"Services"
        }
    ],
    "sg:phone":"+1 713 776 9800",
    "sg:postcode":"77074",
    "sg:province":"TX",
    "sg:tags":[
        "accountant"
    ],
    "wof:name":"Werner Richard S PC",
    "wof:placetype":"venue"
},
  "geometry": {"coordinates":[-95.52673900000001,29.68798],"type":"Point"}
}