{
  "type": "Feature",
  "properties": {
    "iso:country":"US",
    "sg:address":"264 Stewart St",
    "sg:city":"Jasper",
    "sg:classifiers":[
        {
            "category":"Building & Trades",
            "subcategory":"Construction",
            "type":"Services"
        }
    ],
    "sg:phone":"+1 409 384 2239",
    "sg:postcode":"75951",
    "sg:province":"TX",
    "sg:tags":[
        "concrete",
        "contractor"
    ],
    "wof:name":"Economy Concrete Contractor",
    "wof:placetype":"venue"
},
  "geometry": {"coordinates":[-93.990674,30.931682],"type":"Point"}
}