{
  "type": "Feature",
  "properties": {
    "iso:country":"US",
    "sg:address":"1400 State Loop 288",
    "sg:city":"Denton",
    "sg:classifiers":[
        {
            "category":"Restaurant",
            "type":"Food & Drink"
        }
    ],
    "sg:phone":"+1 940 383 8838",
    "sg:postcode":"76205",
    "sg:province":"TX",
    "wof:name":"Rice Boxx",
    "wof:placetype":"venue"
},
  "geometry": {"coordinates":[-97.093627,33.194637],"type":"Point"}
}