{
  "type": "Feature",
  "properties": {
    "iso:country":"US",
    "sg:address":"1210 Sharon Rd",
    "sg:city":"Belton",
    "sg:classifiers":[
        {
            "category":"Home & Garden",
            "subcategory":"Building Materials",
            "type":"Retail Goods"
        },
        {
            "category":"Building & Trades",
            "subcategory":"Construction",
            "type":"Services"
        }
    ],
    "sg:phone":"+1 254 493 4932",
    "sg:postcode":"76513",
    "sg:province":"TX",
    "sg:tags":[
        "concrete",
        "staining",
        "contractor"
    ],
    "wof:name":"J4 Concrete",
    "wof:placetype":"venue"
},
  "geometry": {"coordinates":[-97.45564299999999,31.042118],"type":"Point"}
}