{
  "type": "Feature",
  "properties": {
    "iso:country":"US",
    "sg:address":"2726 Moss Ct",
    "sg:city":"Seabrook",
    "sg:classifiers":[
        {
            "category":"Building & Trades",
            "subcategory":"Construction",
            "type":"Services"
        }
    ],
    "sg:phone":"+1 281 532 9600",
    "sg:postcode":"77586",
    "sg:province":"TX",
    "sg:tags":[
        "special",
        "contractor"
    ],
    "wof:name":"Texas Thermospray Inc",
    "wof:placetype":"venue"
},
  "geometry": {"coordinates":[-95.03409000000001,29.57446],"type":"Point"}
}