{
  "type": "Feature",
  "properties": {
    "iso:country":"US",
    "sg:address":"5122 Meadow Crst",
    "sg:city":"La Porte",
    "sg:classifiers":[
        {
            "category":"Banks & Credit Unions",
            "subcategory":"Investment Brokerage",
            "type":"Services"
        }
    ],
    "sg:phone":"+1 281 470 7830",
    "sg:postcode":"77571",
    "sg:province":"TX",
    "sg:tags":[
        "security"
    ],
    "wof:name":"International Alloys",
    "wof:placetype":"venue"
},
  "geometry": {"coordinates":[-95.07481,29.665957],"type":"Point"}
}