{
  "type": "Feature",
  "properties": {
    "iso:country":"US",
    "sg:address":"26 Woodland Ln",
    "sg:city":"Round Rock",
    "sg:classifiers":[
        {
            "category":"Professional",
            "type":"Services"
        }
    ],
    "sg:phone":"+1 512 255 5497",
    "sg:postcode":"78664",
    "sg:province":"TX",
    "wof:name":"Huggins L L C",
    "wof:placetype":"venue"
},
  "geometry": {"coordinates":[-97.609582,30.524645],"type":"Point"}
}