{
  "type": "Feature",
  "properties": {
    "iso:country":"US",
    "sg:address":"3809 N 1st St",
    "sg:city":"Mcallen",
    "sg:classifiers":[
        {
            "category":"Professional",
            "type":"Services"
        }
    ],
    "sg:phone":"+1 956 687 6180",
    "sg:postcode":"78501",
    "sg:province":"TX",
    "wof:name":"Casa Jung",
    "wof:placetype":"venue"
},
  "geometry": {"coordinates":[-98.212636,26.236697],"type":"Point"}
}