{
  "type": "Feature",
  "properties": {
    "iso:country":"US",
    "sg:address":"4709 59th St",
    "sg:city":"Lubbock",
    "sg:classifiers":[
        {
            "category":"Freight",
            "type":"Transportation"
        }
    ],
    "sg:phone":"+1 806 785 2740",
    "sg:postcode":"79414",
    "sg:province":"TX",
    "sg:tags":[
        "forwarding"
    ],
    "wof:name":"K & K Air Express",
    "wof:placetype":"venue"
},
  "geometry": {"coordinates":[-101.91359300000001,33.540488],"type":"Point"}
}