{
  "type": "Feature",
  "properties": {
    "iso:country":"US",
    "sg:address":"411 Industrial Dr",
    "sg:city":"Richardson",
    "sg:classifiers":[
        {
            "category":"Building & Trades",
            "subcategory":"Construction",
            "type":"Services"
        }
    ],
    "sg:phone":"+1 972 437 0909",
    "sg:postcode":"75081",
    "sg:province":"TX",
    "sg:tags":[
        "roofing",
        "contractor"
    ],
    "sg:website":"www.classicconstruction.com",
    "wof:name":"Classic Construction & Rstrtn",
    "wof:placetype":"venue"
},
  "geometry": {"coordinates":[-96.712112,32.953724],"type":"Point"}
}