{
  "type": "Feature",
  "properties": {
    "iso:country":"US",
    "sg:address":"319 State Hwy 27",
    "sg:city":"Ingram",
    "sg:classifiers":[
        {
            "category":"Shopping",
            "subcategory":"Computers & Home Electronics",
            "type":"Retail Goods"
        }
    ],
    "sg:phone":"+1 830 367 4646",
    "sg:postcode":"78025",
    "sg:province":"TX",
    "sg:tags":[
        "equipment",
        "dealer"
    ],
    "wof:name":"Advance Systems",
    "wof:placetype":"venue"
},
  "geometry": {"coordinates":[-99.240495,30.077399],"type":"Point"}
}