{
  "type": "Feature",
  "properties": {
    "iso:country":"US",
    "sg:address":"3637 W Alabama St Ste 130",
    "sg:city":"Houston",
    "sg:classifiers":[
        {
            "category":"Shopping",
            "subcategory":"Bridal",
            "type":"Retail Goods"
        }
    ],
    "sg:phone":"+1 713 963 8213",
    "sg:postcode":"77027",
    "sg:province":"TX",
    "wof:name":"Beautiful U Bridal Veil & Accessories",
    "wof:placetype":"venue"
},
  "geometry": {"coordinates":[-95.436093,29.737804],"type":"Point"}
}