{
  "type": "Feature",
  "properties": {
    "iso:country":"US",
    "sg:address":"3520 Brightstone Ct",
    "sg:city":"Flower Mound",
    "sg:classifiers":[
        {
            "category":"Building & Trades",
            "subcategory":"Construction",
            "type":"Services"
        }
    ],
    "sg:phone":"+1 972 539 5523",
    "sg:postcode":"75022",
    "sg:province":"TX",
    "sg:tags":[
        "house"
    ],
    "wof:name":"Builders In American Metroplex",
    "wof:placetype":"venue"
},
  "geometry": {"coordinates":[-97.074184,33.032891],"type":"Point"}
}