{
  "type": "Feature",
  "properties": {
    "iso:country":"US",
    "sg:address":"1428 Wooded Acres Dr",
    "sg:city":"Waco",
    "sg:classifiers":[
        {
            "category":"Shopping",
            "subcategory":"Clothing, Apparel, & Fashions",
            "type":"Retail Goods"
        }
    ],
    "sg:phone":"+1 254 399 8844",
    "sg:postcode":"76710",
    "sg:province":"TX",
    "sg:tags":[
        "apparel",
        "women's"
    ],
    "sg:website":"http://www.dots.com",
    "wof:name":"Dots 573",
    "wof:placetype":"venue"
},
  "geometry": {"coordinates":[-97.189137,31.532423],"type":"Point"}
}