{
  "type": "Feature",
  "properties": {
    "iso:country":"US",
    "sg:address":"20634 Harvest Hill Ln",
    "sg:city":"Houston",
    "sg:classifiers":[
        {
            "category":"Shopping",
            "subcategory":"Gifts & Souvenirs",
            "type":"Retail Goods"
        }
    ],
    "sg:phone":"+1 281 821 7308",
    "sg:postcode":"77073",
    "sg:province":"TX",
    "wof:name":"William Kendall Paul",
    "wof:placetype":"venue"
},
  "geometry": {"coordinates":[-95.38146500000001,30.011443],"type":"Point"}
}