{
  "type": "Feature",
  "properties": {
    "iso:country":"US",
    "sg:address":"11927 Kingslake Forest Dr",
    "sg:city":"Houston",
    "sg:classifiers":[
        {
            "category":"Social Services",
            "subcategory":"Child Care",
            "type":"Services"
        }
    ],
    "sg:phone":"+1 281 458 7199",
    "sg:postcode":"77044",
    "sg:province":"TX",
    "sg:tags":[
        "day"
    ],
    "wof:name":"Pampered Lttle Peoples Daycare",
    "wof:placetype":"venue"
},
  "geometry": {"coordinates":[-95.22096000000001,29.892213],"type":"Point"}
}