{
  "type": "Feature",
  "properties": {
    "iso:country":"US",
    "sg:address":"1725 Parkside Cir",
    "sg:city":"Round Rock",
    "sg:classifiers":[
        {
            "category":"Museum",
            "type":"Entertainment"
        }
    ],
    "sg:phone":"+1 512 244 1195",
    "sg:postcode":"78664",
    "sg:province":"TX",
    "sg:tags":[
        "gallery"
    ],
    "wof:name":"From My House To Your House",
    "wof:placetype":"venue"
},
  "geometry": {"coordinates":[-97.661506,30.501984],"type":"Point"}
}