{
  "type": "Feature",
  "properties": {
    "iso:country":"US",
    "sg:address":"300 Ward Rd",
    "sg:city":"Midlothian",
    "sg:classifiers":[
        {
            "category":"Manufacturing",
            "subcategory":"Metals",
            "type":"Manufacturing & Wholesale Goods"
        }
    ],
    "sg:phone":"+1 972 723 1438",
    "sg:postcode":"76065",
    "sg:province":"TX",
    "sg:tags":[
        "product",
        "primary",
        "mfg"
    ],
    "wof:name":"Heckett Multiserv",
    "wof:placetype":"venue"
},
  "geometry": {"coordinates":[-97.028379,32.463114],"type":"Point"}
}