{
  "type": "Feature",
  "properties": {
    "iso:country":"US",
    "sg:address":"2711 S Buckner Blvd",
    "sg:city":"Dallas",
    "sg:classifiers":[
        {
            "category":"Retail",
            "subcategory":"Auto Repair",
            "type":"Services"
        }
    ],
    "sg:phone":"+1 214 388 8203",
    "sg:postcode":"75227",
    "sg:province":"TX",
    "sg:website":"www.precisiontune.com",
    "wof:name":"Precision Tune Auto Care",
    "wof:placetype":"venue"
},
  "geometry": {"coordinates":[-96.682999,32.757702],"type":"Point"}
}