{
  "type": "Feature",
  "properties": {
    "iso:country":"US",
    "sg:address":"2210 State Hwy 34",
    "sg:city":"Greenville",
    "sg:classifiers":[
        {
            "category":"Personal",
            "subcategory":"Beauty Salon",
            "type":"Services"
        }
    ],
    "sg:phone":"+1 903 455 7979",
    "sg:postcode":"75401",
    "sg:province":"TX",
    "sg:tags":[
        "shop"
    ],
    "wof:name":"Hair Hut",
    "wof:placetype":"venue"
},
  "geometry": {"coordinates":[-96.101725,33.197335],"type":"Point"}
}