{
  "type": "Feature",
  "properties": {
    "iso:country":"US",
    "sg:address":"263 Cypresswood Dr",
    "sg:city":"Spring",
    "sg:classifiers":[
        {
            "category":"Food & Beverages",
            "subcategory":"Bakery",
            "type":"Retail Goods"
        }
    ],
    "sg:phone":"+1 281 350 3111",
    "sg:postcode":"77388",
    "sg:province":"TX",
    "wof:name":"Bakery Dounuts",
    "wof:placetype":"venue"
},
  "geometry": {"coordinates":[-95.436494,30.051115],"type":"Point"}
}