{
  "type": "Feature",
  "properties": {
    "iso:country":"US",
    "sg:address":"10709 Leafwood Ln",
    "sg:city":"Austin",
    "sg:classifiers":[
        {
            "category":"Retail",
            "subcategory":"Self-service Laundry",
            "type":"Services"
        }
    ],
    "sg:phone":"+1 512 249 7047",
    "sg:postcode":"78750",
    "sg:province":"TX",
    "sg:tags":[
        "coin"
    ],
    "wof:name":"Gold Coin Store",
    "wof:placetype":"venue"
},
  "geometry": {"coordinates":[-97.796463,30.429973],"type":"Point"}
}