{
  "type": "Feature",
  "properties": {
    "iso:country":"US",
    "sg:address":"11854 Airline Dr",
    "sg:city":"Houston",
    "sg:classifiers":[
        {
            "category":"Shopping",
            "subcategory":"Pawn Shop",
            "type":"Retail Goods"
        }
    ],
    "sg:phone":"+1 281 999 5626",
    "sg:postcode":"77037",
    "sg:province":"TX",
    "sg:website":"www.ezpawn.com",
    "wof:name":"Ez Pawn",
    "wof:placetype":"venue"
},
  "geometry": {"coordinates":[-95.409401,29.9279],"type":"Point"}
}