{
  "type": "Feature",
  "properties": {
    "iso:country":"US",
    "sg:address":"6007 Deepwood Dr",
    "sg:city":"Houston",
    "sg:classifiers":[
        {
            "category":"Organizations",
            "subcategory":"Religious Organization",
            "type":"Services"
        }
    ],
    "sg:phone":"+1 713 645 8665",
    "sg:postcode":"77023",
    "sg:province":"TX",
    "wof:name":"Reconciliation Church Inc",
    "wof:placetype":"venue"
},
  "geometry": {"coordinates":[-95.323418,29.7005],"type":"Point"}
}