{
  "type": "Feature",
  "properties": {
    "iso:country":"US",
    "sg:address":"100 E Corsicana St",
    "sg:city":"Athens",
    "sg:classifiers":[
        {
            "category":"Utilities",
            "subcategory":"Telephone",
            "type":"Services"
        }
    ],
    "sg:phone":"+1 903 675 0403",
    "sg:postcode":"75751",
    "sg:province":"TX",
    "sg:tags":[
        "tel"
    ],
    "wof:name":"Sprint",
    "wof:placetype":"venue"
},
  "geometry": {"coordinates":[-95.853758,32.204358],"type":"Point"}
}