{
  "type": "Feature",
  "properties": {
    "iso:country":"US",
    "sg:address":"15720 Park Row Ste 200",
    "sg:city":"Houston",
    "sg:classifiers":[
        {
            "category":"Communications",
            "type":"Services"
        },
        {
            "category":"Shopping",
            "subcategory":"Computers & Home Electronics",
            "type":"Retail Goods"
        }
    ],
    "sg:phone":"+1 281 647 0040",
    "sg:postcode":"77084",
    "sg:province":"TX",
    "sg:tags":[
        "sound",
        "television",
        "system",
        "equipment",
        "radio",
        "store"
    ],
    "wof:name":"Sound Perfection",
    "wof:placetype":"venue"
},
  "geometry": {"coordinates":[-95.659137,29.789231],"type":"Point"}
}