{
  "type": "Feature",
  "properties": {
    "iso:country":"US",
    "sg:address":"1102 W 6th St",
    "sg:city":"Austin",
    "sg:classifiers":[
        {
            "category":"Banks & Credit Unions",
            "subcategory":"Investment Brokerage",
            "type":"Services"
        }
    ],
    "sg:phone":"+1 512 481 1956",
    "sg:postcode":"78703",
    "sg:province":"TX",
    "sg:tags":[
        "advisory",
        "financial"
    ],
    "wof:name":"Treaty Oak Capital Mgmt",
    "wof:placetype":"venue"
},
  "geometry": {"coordinates":[-97.755287,30.272135],"type":"Point"}
}