{
  "type": "Feature",
  "properties": {
    "iso:country":"US",
    "sg:address":"6616 Gold Dust Trl",
    "sg:city":"Dallas",
    "sg:classifiers":[
        {
            "category":"Wholesale",
            "subcategory":"Jewelry",
            "type":"Manufacturing & Wholesale Goods"
        }
    ],
    "sg:phone":"+1 972 387 8080",
    "sg:postcode":"75252",
    "sg:province":"TX",
    "sg:tags":[
        "stone"
    ],
    "wof:name":"Euro-Africa Diamonds",
    "wof:placetype":"venue"
},
  "geometry": {"coordinates":[-96.78467999999999,32.991844],"type":"Point"}
}