{
  "type": "Feature",
  "properties": {
    "iso:country":"US",
    "sg:address":"214 Davis St N",
    "sg:city":"Sulphur Springs",
    "sg:classifiers":[
        {
            "category":"Professional",
            "subcategory":"Accounting & Tax Preparation",
            "type":"Services"
        }
    ],
    "sg:phone":"+1 903 885 7571",
    "sg:postcode":"75482",
    "sg:province":"TX",
    "sg:tags":[
        "accountant"
    ],
    "wof:name":"Bawcum & Preuss",
    "wof:placetype":"venue"
},
  "geometry": {"coordinates":[-95.60278700000001,33.139028],"type":"Point"}
}