{
  "type": "Feature",
  "properties": {
    "iso:country":"US",
    "sg:address":"4305 N Vine St",
    "sg:city":"Victoria",
    "sg:classifiers":[
        {
            "category":"Wholesale",
            "subcategory":"Hardware",
            "type":"Manufacturing & Wholesale Goods"
        }
    ],
    "sg:phone":"+1 361 572 3191",
    "sg:postcode":"77901",
    "sg:province":"TX",
    "sg:tags":[
        "plumbing",
        "fixture",
        "supply"
    ],
    "wof:name":"City Plumbing Supply Co",
    "wof:placetype":"venue"
},
  "geometry": {"coordinates":[-97.00961700000001,28.828255],"type":"Point"}
}