{
  "type": "Feature",
  "properties": {
    "iso:country":"US",
    "sg:address":"1021 Ridgecrest Dr",
    "sg:city":"Mc Kinney",
    "sg:classifiers":[
        {
            "category":"Utilities",
            "subcategory":"Telephone",
            "type":"Services"
        }
    ],
    "sg:phone":"+1 972 562 0066",
    "sg:postcode":"75069",
    "sg:province":"TX",
    "sg:tags":[
        "host",
        "internet"
    ],
    "wof:name":"Hutchins Industry",
    "wof:placetype":"venue"
},
  "geometry": {"coordinates":[-96.63212900000001,33.178638],"type":"Point"}
}