{
  "type": "Feature",
  "properties": {
    "iso:country":"US",
    "sg:address":"2050 Sabine Pass Ave",
    "sg:city":"Beaumont",
    "sg:classifiers":[
        {
            "category":"Wholesale",
            "subcategory":"Metals & Minerals",
            "type":"Manufacturing & Wholesale Goods"
        }
    ],
    "sg:phone":"+1 409 832 4526",
    "sg:postcode":"77701",
    "sg:province":"TX",
    "sg:tags":[
        "center"
    ],
    "wof:name":"Manchester Sling Co",
    "wof:placetype":"venue"
},
  "geometry": {"coordinates":[-94.091408,30.067896],"type":"Point"}
}