{
  "type": "Feature",
  "properties": {
    "iso:country":"US",
    "sg:address":"9830 Sageroyal Ln",
    "sg:city":"Houston",
    "sg:classifiers":[
        {
            "category":"Manufacturing",
            "subcategory":"Apparel",
            "type":"Manufacturing & Wholesale Goods"
        }
    ],
    "sg:phone":"+1 281 485 2919",
    "sg:postcode":"77089",
    "sg:province":"TX",
    "sg:tags":[
        "sewing",
        "contractor"
    ],
    "wof:name":"Linda's Creations",
    "wof:placetype":"venue"
},
  "geometry": {"coordinates":[-95.238339,29.581412],"type":"Point"}
}