{
  "type": "Feature",
  "properties": {
    "iso:country":"US",
    "sg:address":"3606 John Stockbauer Dr",
    "sg:city":"Victoria",
    "sg:classifiers":[
        {
            "category":"Insurance",
            "subcategory":"Insurance Agent",
            "type":"Services"
        }
    ],
    "sg:phone":"+1 361 575 5268",
    "sg:postcode":"77904",
    "sg:province":"TX",
    "wof:name":"Homer Brown Insurance",
    "wof:placetype":"venue"
},
  "geometry": {"coordinates":[-96.94757199999999,28.818453],"type":"Point"}
}