{
  "type": "Feature",
  "properties": {
    "iso:country":"US",
    "sg:address":"2429 E Main St",
    "sg:city":"Gatesville",
    "sg:classifiers":[
        {
            "category":"Shopping",
            "subcategory":"Used Merchandise",
            "type":"Retail Goods"
        }
    ],
    "sg:phone":"+1 254 865 6553",
    "sg:postcode":"76528",
    "sg:province":"TX",
    "wof:name":"Heart Texas Goodwill Inds",
    "wof:placetype":"venue"
},
  "geometry": {"coordinates":[-97.729347,31.434861],"type":"Point"}
}