{
  "type": "Feature",
  "properties": {
    "iso:country":"US",
    "sg:address":"6720 Ridgetop Rd",
    "sg:city":"Fort Worth",
    "sg:classifiers":[
        {
            "category":"Insurance",
            "subcategory":"Insurance Agent",
            "type":"Services"
        }
    ],
    "sg:phone":"+1 817 577 0364",
    "sg:postcode":"76180",
    "sg:province":"TX",
    "wof:name":"McHenry & Associates",
    "wof:placetype":"venue"
},
  "geometry": {"coordinates":[-97.23406799999999,32.878364],"type":"Point"}
}