{
  "type": "Feature",
  "properties": {
    "iso:country":"US",
    "sg:address":"1708 Hwy 365",
    "sg:city":"Port Arthur",
    "sg:classifiers":[
        {
            "category":"Personal",
            "subcategory":"Beauty Salon",
            "type":"Services"
        }
    ],
    "sg:phone":"+1 409 721 6569",
    "sg:postcode":"77640",
    "sg:province":"TX",
    "sg:tags":[
        "shop"
    ],
    "wof:name":"Nancys Nails",
    "wof:placetype":"venue"
},
  "geometry": {"coordinates":[-93.999993,29.93978],"type":"Point"}
}