{
  "type": "Feature",
  "properties": {
    "iso:country":"US",
    "sg:address":"980 University Dr E",
    "sg:city":"College Station",
    "sg:classifiers":[
        {
            "category":"Restaurant",
            "type":"Food & Drink"
        }
    ],
    "sg:menulink":"http://www.allmenus.com/tx/bryan-college-station/292834-bodega-coast-/menu/",
    "sg:phone":"+1 976 268 8101",
    "sg:postcode":"77840",
    "sg:province":"TX",
    "sg:tags":[
        "american"
    ],
    "wof:name":"Bodega Coast",
    "wof:placetype":"venue"
},
  "geometry": {"coordinates":[-96.32306699999999,30.635162],"type":"Point"}
}