{
  "type": "Feature",
  "properties": {
    "iso:country":"US",
    "sg:address":"2000 E 24th St",
    "sg:city":"Texarkana",
    "sg:classifiers":[
        {
            "category":"Real Estate",
            "subcategory":"Real Estate Operator",
            "type":"Services"
        }
    ],
    "sg:phone":"+1 870 773 1219",
    "sg:postcode":"71854",
    "sg:province":"TX",
    "sg:tags":[
        "apartment"
    ],
    "wof:name":"Shangri-LA Apartments",
    "wof:placetype":"venue"
},
  "geometry": {"coordinates":[-94.022023,33.445294],"type":"Point"}
}