{
  "type": "Feature",
  "properties": {
    "iso:country":"US",
    "sg:address":"216 Bluebird Ct",
    "sg:city":"Mc Queeney",
    "sg:classifiers":[
        {
            "category":"Professional",
            "type":"Services"
        }
    ],
    "sg:phone":"+1 830 557 6618",
    "sg:postcode":"78123",
    "sg:province":"TX",
    "wof:name":"Cv Property Services",
    "wof:placetype":"venue"
},
  "geometry": {"coordinates":[-98.03094400000001,29.619866],"type":"Point"}
}