{
  "type": "Feature",
  "properties": {
    "iso:country":"US",
    "sg:address":"1801 27th St",
    "sg:city":"Snyder",
    "sg:classifiers":[
        {
            "category":"Building & Trades",
            "subcategory":"Equipment Rental",
            "type":"Services"
        }
    ],
    "sg:phone":"+1 325 573 2231",
    "sg:postcode":"79549",
    "sg:province":"TX",
    "sg:tags":[
        "yard"
    ],
    "wof:name":"U-Haul Co",
    "wof:placetype":"venue"
},
  "geometry": {"coordinates":[-100.918397,32.7151],"type":"Point"}
}