{
  "type": "Feature",
  "properties": {
    "iso:country":"US",
    "sg:address":"3111 College Ave",
    "sg:city":"Snyder",
    "sg:classifiers":[
        {
            "category":"Retail",
            "subcategory":"Laundry & Dry Cleaning",
            "type":"Services"
        }
    ],
    "sg:phone":"+1 325 573 7376",
    "sg:postcode":"79549",
    "sg:province":"TX",
    "sg:tags":[
        "cleaner",
        "plant",
        "drycleaning"
    ],
    "wof:name":"Lone Star Cleaners",
    "wof:placetype":"venue"
},
  "geometry": {"coordinates":[-100.918941,32.710313],"type":"Point"}
}