{
  "type": "Feature",
  "properties": {
    "iso:country":"US",
    "sg:address":"2400 E Van Buren St",
    "sg:city":"Brownsville",
    "sg:classifiers":[
        {
            "category":"Education",
            "subcategory":"School",
            "type":"Public Place"
        }
    ],
    "sg:phone":"+1 956 982 2700",
    "sg:postcode":"78520",
    "sg:province":"TX",
    "wof:name":"Longoria Elementary School",
    "wof:placetype":"venue"
},
  "geometry": {"coordinates":[-97.48245900000001,25.896558],"type":"Point"}
}