{
  "type": "Feature",
  "properties": {
    "iso:country":"US",
    "sg:address":"269 Frosty Hollow Rd",
    "sg:city":"Denison",
    "sg:classifiers":[
        {
            "category":"Wholesale",
            "subcategory":"Hardware",
            "type":"Manufacturing & Wholesale Goods"
        }
    ],
    "sg:phone":"+1 903 465 3541",
    "sg:postcode":"75021",
    "sg:province":"TX",
    "sg:tags":[
        "refrigerating"
    ],
    "wof:name":"Arnold's Refrigeration & AC",
    "wof:placetype":"venue"
},
  "geometry": {"coordinates":[-96.50732499999999,33.721083],"type":"Point"}
}