{
  "type": "Feature",
  "properties": {
    "iso:country":"US",
    "sg:address":"2030 10th St",
    "sg:city":"Port Neches",
    "sg:classifiers":[
        {
            "category":"Building & Trades",
            "subcategory":"Cleaning & Sanitation",
            "type":"Services"
        }
    ],
    "sg:phone":"+1 409 729 4601",
    "sg:postcode":"77651",
    "sg:province":"TX",
    "wof:name":"Lynn's Office Cleaning",
    "wof:placetype":"venue"
},
  "geometry": {"coordinates":[-93.966024,29.985298],"type":"Point"}
}