{
  "type": "Feature",
  "properties": {
    "iso:country":"US",
    "sg:address":"10200 Sausalito Dr",
    "sg:city":"Austin",
    "sg:classifiers":[
        {
            "category":"Professional",
            "subcategory":"Lawyer & Legal Services",
            "type":"Services"
        }
    ],
    "sg:phone":"+1 512 343 1958",
    "sg:postcode":"78759",
    "sg:province":"TX",
    "wof:name":"Ruesink Charles",
    "wof:placetype":"venue"
},
  "geometry": {"coordinates":[-97.763912,30.408174],"type":"Point"}
}