{
  "type": "Feature",
  "properties": {
    "iso:country":"US",
    "sg:address":"17424 Woods Dr",
    "sg:city":"New Caney",
    "sg:classifiers":[
        {
            "category":"Building & Trades",
            "subcategory":"Construction",
            "type":"Services"
        }
    ],
    "sg:phone":"+1 281 948 2492",
    "sg:postcode":"77357",
    "sg:province":"TX",
    "sg:tags":[
        "sandblasting",
        "contractor"
    ],
    "wof:name":"Eric Johnson Sandblasting",
    "wof:placetype":"venue"
},
  "geometry": {"coordinates":[-95.26524499999999,30.194981],"type":"Point"}
}