{
  "type": "Feature",
  "properties": {
    "iso:country":"US",
    "sg:address":"3303 Glenview Ave",
    "sg:city":"Austin",
    "sg:classifiers":[
        {
            "category":"Shopping",
            "subcategory":"Used Merchandise",
            "type":"Retail Goods"
        }
    ],
    "sg:phone":"+1 512 472 7366",
    "sg:postcode":"78703",
    "sg:province":"TX",
    "sg:tags":[
        "antique"
    ],
    "wof:name":"Antiques By Grace Homan",
    "wof:placetype":"venue"
},
  "geometry": {"coordinates":[-97.75188,30.306209],"type":"Point"}
}