{
  "type": "Feature",
  "properties": {
    "iso:country":"US",
    "sg:address":"6500 N Belt Line Rd",
    "sg:city":"Irving",
    "sg:classifiers":[
        {
            "category":"Banks & Credit Unions",
            "subcategory":"Investment Brokerage",
            "type":"Services"
        }
    ],
    "sg:phone":"+1 972 999 4570",
    "sg:postcode":"75063",
    "sg:province":"TX",
    "wof:name":"Wellington Associates Inc",
    "wof:placetype":"venue"
},
  "geometry": {"coordinates":[-96.991259,32.901772],"type":"Point"}
}