{
  "type": "Feature",
  "properties": {
    "iso:country":"US",
    "sg:address":"314 S Elm St",
    "sg:city":"Denton",
    "sg:classifiers":[
        {
            "category":"Shopping",
            "subcategory":"Musical Instruments",
            "type":"Retail Goods"
        }
    ],
    "sg:phone":"+1 940 382 7124",
    "sg:postcode":"76201",
    "sg:province":"TX",
    "sg:tags":[
        "music",
        "dealer"
    ],
    "sg:website":"www.penders.com",
    "wof:name":"Pender's Music Store",
    "wof:placetype":"venue"
},
  "geometry": {"coordinates":[-97.133787,33.212383],"type":"Point"}
}