{
  "type": "Feature",
  "properties": {
    "iso:country":"US",
    "sg:address":"5112 Steadmont Dr",
    "sg:city":"Houston",
    "sg:classifiers":[
        {
            "category":"Home & Garden",
            "subcategory":"Garden Supply",
            "type":"Retail Goods"
        }
    ],
    "sg:phone":"+1 713 462 0007",
    "sg:postcode":"77040",
    "sg:province":"TX",
    "sg:tags":[
        "nursery",
        "gardening",
        "sprinkler"
    ],
    "wof:name":"AMC Industries Inc",
    "wof:placetype":"venue"
},
  "geometry": {"coordinates":[-95.509598,29.8396],"type":"Point"}
}