{
  "type": "Feature",
  "properties": {
    "iso:country":"US",
    "sg:address":"3304 E Broadway St",
    "sg:city":"Sweetwater",
    "sg:classifiers":[
        {
            "category":"Organizations",
            "subcategory":"Religious Organization",
            "type":"Services"
        }
    ],
    "sg:phone":"+1 325 235 4750",
    "sg:postcode":"79556",
    "sg:province":"TX",
    "sg:tags":[
        "church"
    ],
    "wof:name":"Rhema Valley Church",
    "wof:placetype":"venue"
},
  "geometry": {"coordinates":[-100.370366,32.484268],"type":"Point"}
}