{
  "type": "Feature",
  "properties": {
    "iso:country":"US",
    "sg:address":"5085 FM 84",
    "sg:city":"Denison",
    "sg:classifiers":[
        {
            "category":"Building & Trades",
            "subcategory":"Construction",
            "type":"Services"
        }
    ],
    "sg:phone":"+1 903 821 9016",
    "sg:postcode":"75020",
    "sg:province":"TX",
    "sg:tags":[
        "waterproofing",
        "contractor"
    ],
    "wof:name":"All Seasons Contracting",
    "wof:placetype":"venue"
},
  "geometry": {"coordinates":[-96.59911,33.78561],"type":"Point"}
}