{
  "type": "Feature",
  "properties": {
    "iso:country":"US",
    "sg:address":"935 Eldridge Rd",
    "sg:city":"Sugar Land",
    "sg:classifiers":[
        {
            "category":"Professional",
            "subcategory":"Management & Consulting",
            "type":"Services"
        }
    ],
    "sg:phone":"+1 281 242 2621",
    "sg:postcode":"77478",
    "sg:province":"TX",
    "sg:tags":[
        "energy"
    ],
    "wof:name":"Granite Energy Management Lc",
    "wof:placetype":"venue"
},
  "geometry": {"coordinates":[-95.61875999999999,29.631412],"type":"Point"}
}