{
  "type": "Feature",
  "properties": {
    "iso:country":"US",
    "sg:address":"1625 8th Ave",
    "sg:city":"Fort Worth",
    "sg:classifiers":[
        {
            "category":"Restaurant",
            "type":"Food & Drink"
        }
    ],
    "sg:phone":"+1 817 927 8541",
    "sg:postcode":"76104",
    "sg:province":"TX",
    "sg:tags":[
        "eating"
    ],
    "wof:name":"Mexican Inn Cafes",
    "wof:placetype":"venue"
},
  "geometry": {"coordinates":[-97.343605,32.727568],"type":"Point"}
}