{
  "type": "Feature",
  "properties": {
    "iso:country":"US",
    "sg:address":"2100 Peach Blossom St",
    "sg:city":"San Antonio",
    "sg:classifiers":[
        {
            "category":"Professional",
            "subcategory":"Business Services",
            "type":"Services"
        }
    ],
    "sg:phone":"+1 210 495 6395",
    "sg:postcode":"78247",
    "sg:province":"TX",
    "wof:name":"Perpetual Solutions",
    "wof:placetype":"venue"
},
  "geometry": {"coordinates":[-98.459345,29.550535],"type":"Point"}
}