{
  "type": "Feature",
  "properties": {
    "iso:country":"US",
    "sg:address":"812 Robin Ct",
    "sg:city":"Springtown",
    "sg:classifiers":[
        {
            "category":"Wholesale",
            "subcategory":"Non-durable Goods",
            "type":"Manufacturing & Wholesale Goods"
        }
    ],
    "sg:phone":"+1 817 523 4570",
    "sg:postcode":"76082",
    "sg:province":"TX",
    "wof:name":"Infinity Distributing",
    "wof:placetype":"venue"
},
  "geometry": {"coordinates":[-97.688957,32.975409],"type":"Point"}
}