{
  "type": "Feature",
  "properties": {
    "iso:country":"US",
    "sg:address":"1826 Portsmouth St",
    "sg:city":"Houston",
    "sg:classifiers":[
        {
            "category":"Arts & Performance",
            "subcategory":"Theater",
            "type":"Entertainment"
        }
    ],
    "sg:phone":"+1 713 526 7889",
    "sg:postcode":"77098",
    "sg:province":"TX",
    "sg:tags":[
        "group"
    ],
    "wof:name":"Tidy Cottage Music",
    "wof:placetype":"venue"
},
  "geometry": {"coordinates":[-95.406375,29.733532],"type":"Point"}
}