{
  "type": "Feature",
  "properties": {
    "iso:country":"US",
    "sg:address":"9950 Chemical Rd",
    "sg:city":"Pasadena",
    "sg:classifiers":[
        {
            "category":"Professional",
            "subcategory":"Management & Consulting",
            "type":"Services"
        },
        {
            "category":"Building & Trades",
            "subcategory":"Cleaning & Sanitation",
            "type":"Services"
        },
        {
            "category":"Professional",
            "subcategory":"Engineering",
            "type":"Services"
        }
    ],
    "sg:phone":"+1 281 474 2576",
    "sg:postcode":"77507",
    "sg:province":"TX",
    "sg:tags":[
        "control",
        "consultant",
        "hazardous",
        "material",
        "removal",
        "environmental",
        "ecological",
        "engineer"
    ],
    "wof:name":"Effective Environmental",
    "wof:placetype":"venue"
},
  "geometry": {"coordinates":[-95.05492700000001,29.616931],"type":"Point"}
}