{
  "type": "Feature",
  "properties": {
    "iso:country":"US",
    "sg:address":"5712 Willow Wood Ln",
    "sg:city":"Dallas",
    "sg:classifiers":[
        {
            "category":"Professional",
            "subcategory":"Business Services",
            "type":"Services"
        }
    ],
    "sg:phone":"+1 972 248 4004",
    "sg:postcode":"75252",
    "sg:province":"TX",
    "wof:name":"Bond Booth Enterprises LLC",
    "wof:placetype":"venue"
},
  "geometry": {"coordinates":[-96.81110099999999,33.011481],"type":"Point"}
}