{
  "type": "Feature",
  "properties": {
    "iso:country":"US",
    "sg:address":"1306 W Crawford St",
    "sg:city":"Denison",
    "sg:classifiers":[
        {
            "category":"Shopping",
            "subcategory":"Used Merchandise",
            "type":"Retail Goods"
        }
    ],
    "sg:phone":"+1 903 464 9431",
    "sg:postcode":"75020",
    "sg:province":"TX",
    "wof:name":"Trojan Antiques & Crafts",
    "wof:placetype":"venue"
},
  "geometry": {"coordinates":[-96.555488,33.753973],"type":"Point"}
}