{
  "type": "Feature",
  "properties": {
    "iso:country":"US",
    "sg:address":"716 S Getty St",
    "sg:city":"Uvalde",
    "sg:classifiers":[
        {
            "category":"Retail",
            "subcategory":"Repair Shop",
            "type":"Services"
        }
    ],
    "sg:phone":"+1 830 278 9581",
    "sg:postcode":"78801",
    "sg:province":"TX",
    "sg:tags":[
        "scale"
    ],
    "wof:name":"A-1 Scale Svc Inc",
    "wof:placetype":"venue"
},
  "geometry": {"coordinates":[-99.78204599999999,29.199833],"type":"Point"}
}