{
  "type": "Feature",
  "properties": {
    "iso:country":"US",
    "sg:address":"20153 FM 2920",
    "sg:city":"Tomball",
    "sg:classifiers":[
        {
            "category":"Home & Garden",
            "subcategory":"Garden Supply",
            "type":"Retail Goods"
        }
    ],
    "sg:phone":"+1 281 351 7130",
    "sg:postcode":"77377",
    "sg:province":"TX",
    "sg:tags":[
        "nurseryman"
    ],
    "wof:name":"High Meadow Tree Farm",
    "wof:placetype":"venue"
},
  "geometry": {"coordinates":[-95.738399,30.079977],"type":"Point"}
}