{
  "type": "Feature",
  "properties": {
    "iso:country":"US",
    "sg:address":"610 E Industrial Ave",
    "sg:city":"Midland",
    "sg:classifiers":[
        {
            "category":"Bars & Pubs",
            "type":"Food & Drink"
        }
    ],
    "sg:phone":"+1 432 620 8191",
    "sg:postcode":"79701",
    "sg:province":"TX",
    "sg:tags":[
        "drinking"
    ],
    "wof:name":"Zacs Club Jamaica",
    "wof:placetype":"venue"
},
  "geometry": {"coordinates":[-102.06685400000001,31.998906],"type":"Point"}
}