{
  "type": "Feature",
  "properties": {
    "iso:country":"US",
    "sg:address":"1000 S Kreymer Ln",
    "sg:city":"Wylie",
    "sg:classifiers":[
        {
            "category":"Real Estate",
            "subcategory":"Real Estate Agent",
            "type":"Services"
        }
    ],
    "sg:phone":"+1 972 442 6438",
    "sg:postcode":"75098",
    "sg:province":"TX",
    "wof:name":"Brent Cowan & Associates Inc",
    "wof:placetype":"venue"
},
  "geometry": {"coordinates":[-96.51034300000001,33.005553],"type":"Point"}
}