{
  "type": "Feature",
  "properties": {
    "iso:country":"US",
    "sg:address":"314 Dogie Trl",
    "sg:city":"Little Elm",
    "sg:classifiers":[
        {
            "category":"Building & Trades",
            "subcategory":"Construction",
            "type":"Services"
        }
    ],
    "sg:phone":"+1 972 802 5790",
    "sg:postcode":"75068",
    "sg:province":"TX",
    "sg:tags":[
        "residential"
    ],
    "wof:name":"Sparks Art",
    "wof:placetype":"venue"
},
  "geometry": {"coordinates":[-97.007723,33.180547],"type":"Point"}
}