{
  "type": "Feature",
  "properties": {
    "iso:country":"US",
    "sg:address":"1245 S Cannon St",
    "sg:city":"Sour Lake",
    "sg:classifiers":[
        {
            "category":"Building & Trades",
            "subcategory":"Construction",
            "type":"Services"
        }
    ],
    "sg:phone":"+1 409 287 2721",
    "sg:postcode":"77659",
    "sg:province":"TX",
    "sg:tags":[
        "roofing",
        "contractor"
    ],
    "wof:name":"Gray Roofing Co",
    "wof:placetype":"venue"
},
  "geometry": {"coordinates":[-94.40023100000001,30.128738],"type":"Point"}
}