{
  "type": "Feature",
  "properties": {
    "iso:country":"US",
    "sg:address":"705 Cedar Bayou Rd",
    "sg:city":"Baytown",
    "sg:classifiers":[
        {
            "category":"Wholesale",
            "subcategory":"Hardware",
            "type":"Manufacturing & Wholesale Goods"
        }
    ],
    "sg:phone":"+1 281 427 8295",
    "sg:postcode":"77520",
    "sg:province":"TX",
    "sg:tags":[
        "conditioning",
        "system"
    ],
    "wof:name":"ACR Supply Inc",
    "wof:placetype":"venue"
},
  "geometry": {"coordinates":[-94.95597600000001,29.748761],"type":"Point"}
}