{
  "type": "Feature",
  "properties": {
    "iso:country":"US",
    "sg:address":"231 W Fm 117",
    "sg:city":"Dilley",
    "sg:classifiers":[
        {
            "category":"Education",
            "subcategory":"Library",
            "type":"Public Place"
        }
    ],
    "sg:phone":"+1 830 965 1951",
    "sg:postcode":"78017",
    "sg:province":"TX",
    "wof:name":"Department Of City Of Dilley",
    "wof:placetype":"venue"
},
  "geometry": {"coordinates":[-99.170086,28.673979],"type":"Point"}
}