{
  "type": "Feature",
  "properties": {
    "iso:country":"US",
    "sg:address":"1928 N Conway Ave",
    "sg:city":"Mission",
    "sg:classifiers":[
        {
            "category":"Shopping",
            "subcategory":"Tobacco",
            "type":"Retail Goods"
        }
    ],
    "sg:phone":"+1 956 581 6665",
    "sg:postcode":"78572",
    "sg:province":"TX",
    "sg:tags":[
        "cigarette",
        "cigar"
    ],
    "wof:name":"The Peace Pipe",
    "wof:placetype":"venue"
},
  "geometry": {"coordinates":[-98.32409699999999,26.225468],"type":"Point"}
}