{
  "type": "Feature",
  "properties": {
    "iso:country":"US",
    "sg:address":"349 Co Rd 487",
    "sg:city":"Stephenville",
    "sg:classifiers":[
        {
            "category":"Building & Trades",
            "subcategory":"Construction",
            "type":"Services"
        }
    ],
    "sg:phone":"+1 254 965 5941",
    "sg:postcode":"76444",
    "sg:province":"TX",
    "sg:tags":[
        "house"
    ],
    "wof:name":"Faron Danley",
    "wof:placetype":"venue"
},
  "geometry": {"coordinates":[-98.548596,32.144135],"type":"Point"}
}