{
  "type": "Feature",
  "properties": {
    "iso:country":"US",
    "sg:address":"2911 E Division St",
    "sg:city":"Arlington",
    "sg:classifiers":[
        {
            "category":"Shopping",
            "subcategory":"Beauty & Cosmetics",
            "type":"Retail Goods"
        }
    ],
    "sg:phone":"+1 817 649 2010",
    "sg:postcode":"76011",
    "sg:province":"TX",
    "sg:tags":[
        "merchandise"
    ],
    "wof:name":"Avon",
    "wof:placetype":"venue"
},
  "geometry": {"coordinates":[-97.057286,32.74189],"type":"Point"}
}