{
  "type": "Feature",
  "properties": {
    "iso:country":"US",
    "sg:address":"2701 Saturn Rd",
    "sg:city":"Garland",
    "sg:classifiers":[
        {
            "category":"Organizations",
            "subcategory":"Religious Organization",
            "type":"Services"
        }
    ],
    "sg:phone":"+1 972 530 8782",
    "sg:postcode":"75041",
    "sg:province":"TX",
    "sg:tags":[
        "church"
    ],
    "wof:name":"Church Of Jesus Christ Of Lds",
    "wof:placetype":"venue"
},
  "geometry": {"coordinates":[-96.64828199999999,32.886552],"type":"Point"}
}