{
  "type": "Feature",
  "properties": {
    "iso:country":"US",
    "sg:address":"953 SW 34th St",
    "sg:city":"San Antonio",
    "sg:classifiers":[
        {
            "category":"Professional",
            "subcategory":"Detective & Security Services",
            "type":"Services"
        }
    ],
    "sg:phone":"+1 210 431 3255",
    "sg:postcode":"78237",
    "sg:province":"TX",
    "sg:tags":[
        "guard",
        "patrol"
    ],
    "wof:name":"Texas Private Security/Patrol",
    "wof:placetype":"venue"
},
  "geometry": {"coordinates":[-98.569771,29.413033],"type":"Point"}
}