{
  "type": "Feature",
  "properties": {
    "iso:country":"US",
    "sg:address":"1595 N Central Expy",
    "sg:city":"Richardson",
    "sg:classifiers":[
        {
            "category":"Recreation",
            "type":"Entertainment"
        }
    ],
    "sg:phone":"+1 972 235 7436",
    "sg:postcode":"75080",
    "sg:province":"TX",
    "sg:tags":[
        "club",
        "membership"
    ],
    "wof:name":"Phenomenon Private Club Inc",
    "wof:placetype":"venue"
},
  "geometry": {"coordinates":[-96.721161,32.96818],"type":"Point"}
}