{
  "type": "Feature",
  "properties": {
    "iso:country":"US",
    "sg:address":"18201 Viscount Rd",
    "sg:city":"Houston",
    "sg:classifiers":[
        {
            "category":"Freight",
            "type":"Transportation"
        }
    ],
    "sg:phone":"+1 281 443 7447",
    "sg:postcode":"77032",
    "sg:province":"TX",
    "sg:tags":[
        "company",
        "holding"
    ],
    "wof:name":"Gateway Logistics Group Inc",
    "wof:placetype":"venue"
},
  "geometry": {"coordinates":[-95.346069,29.981043],"type":"Point"}
}