{
  "type": "Feature",
  "properties": {
    "iso:country":"US",
    "sg:address":"1305 W Airport Fwy",
    "sg:city":"Euless",
    "sg:classifiers":[
        {
            "category":"Health Services",
            "subcategory":"Doctor",
            "type":"Services"
        }
    ],
    "sg:phone":"+1 817 545 0662",
    "sg:postcode":"76040",
    "sg:province":"TX",
    "sg:tags":[
        "physician",
        "surgeon"
    ],
    "wof:name":"Senior Health Ctr Of Bedford",
    "wof:placetype":"venue"
},
  "geometry": {"coordinates":[-97.10162800000001,32.837213],"type":"Point"}
}