{
  "type": "Feature",
  "properties": {
    "iso:country":"US",
    "sg:address":"6132 Walla Ave",
    "sg:city":"Fort Worth",
    "sg:classifiers":[
        {
            "category":"Building & Trades",
            "subcategory":"Construction",
            "type":"Services"
        }
    ],
    "sg:phone":"+1 817 292 9461",
    "sg:postcode":"76133",
    "sg:province":"TX",
    "sg:tags":[
        "house"
    ],
    "wof:name":"Jim Varnell Custom Homes",
    "wof:placetype":"venue"
},
  "geometry": {"coordinates":[-97.391632,32.657744],"type":"Point"}
}