{
  "type": "Feature",
  "properties": {
    "iso:country":"US",
    "sg:address":"2400 Ave F",
    "sg:city":"Del Rio",
    "sg:classifiers":[
        {
            "category":"Bars & Pubs",
            "type":"Food & Drink"
        }
    ],
    "sg:phone":"+1 830 778 1745",
    "sg:postcode":"78840",
    "sg:province":"TX",
    "sg:tags":[
        "club",
        "night"
    ],
    "wof:name":"Denim & Diamonds",
    "wof:placetype":"venue"
},
  "geometry": {"coordinates":[-100.905173,29.393718],"type":"Point"}
}