{
  "type": "Feature",
  "properties": {
    "iso:country":"US",
    "sg:address":"5502 Burnham Dr",
    "sg:city":"Corpus Christi",
    "sg:classifiers":[
        {
            "category":"Shopping",
            "type":"Retail Goods"
        }
    ],
    "sg:phone":"+1 361 906 1552",
    "sg:postcode":"78413",
    "sg:province":"TX",
    "sg:tags":[
        "janitorial",
        "supply"
    ],
    "wof:name":"Supply Line Usa Inc",
    "wof:placetype":"venue"
},
  "geometry": {"coordinates":[-97.379411,27.696894],"type":"Point"}
}