{
  "type": "Feature",
  "properties": {
    "iso:country":"US",
    "sg:address":"15321 Vantage Pkwy E",
    "sg:city":"Houston",
    "sg:classifiers":[
        {
            "category":"Travel",
            "subcategory":"Hotels & Motels",
            "type":"Entertainment"
        }
    ],
    "sg:phone":"+1 281 442 4444",
    "sg:postcode":"77032",
    "sg:province":"TX",
    "wof:name":"Quality Suites",
    "wof:placetype":"venue"
},
  "geometry": {"coordinates":[-95.3629,29.9417],"type":"Point"}
}