{
  "type": "Feature",
  "properties": {
    "iso:country":"US",
    "sg:address":"11209 Bellaire Blvd",
    "sg:city":"Houston",
    "sg:classifiers":[
        {
            "category":"Shopping",
            "type":"Retail Goods"
        }
    ],
    "sg:phone":"+1 281 530 6870",
    "sg:postcode":"77072",
    "sg:province":"TX",
    "sg:tags":[
        "merchandise"
    ],
    "wof:name":"C-Kret Eyeware",
    "wof:placetype":"venue"
},
  "geometry": {"coordinates":[-95.578014,29.703746],"type":"Point"}
}