{
  "type": "Feature",
  "properties": {
    "iso:country":"US",
    "sg:address":"2331 Gus Thomasson Rd",
    "sg:city":"Dallas",
    "sg:classifiers":[
        {
            "category":"Organizations",
            "subcategory":"Religious Organization",
            "type":"Services"
        }
    ],
    "sg:phone":"+1 214 320 8858",
    "sg:postcode":"75228",
    "sg:province":"TX",
    "wof:name":"Texas Christian Endeavor Inc",
    "wof:placetype":"venue"
},
  "geometry": {"coordinates":[-96.676102,32.834599],"type":"Point"}
}