{
  "type": "Feature",
  "properties": {
    "iso:country":"US",
    "sg:address":"835 Tower Dr",
    "sg:city":"Odessa",
    "sg:classifiers":[
        {
            "category":"Professional",
            "subcategory":"Accounting & Tax Preparation",
            "type":"Services"
        }
    ],
    "sg:phone":"+1 432 580 4663",
    "sg:postcode":"79761",
    "sg:province":"TX",
    "sg:tags":[
        "return"
    ],
    "wof:name":"Susan Goode",
    "wof:placetype":"venue"
},
  "geometry": {"coordinates":[-102.342412,31.863946],"type":"Point"}
}