{
  "type": "Feature",
  "properties": {
    "iso:country":"US",
    "sg:address":"205 W Washington St",
    "sg:city":"Anthony",
    "sg:classifiers":[
        {
            "category":"Personal",
            "subcategory":"Beauty Salon",
            "type":"Services"
        }
    ],
    "sg:phone":"+1 915 886 2411",
    "sg:postcode":"79821",
    "sg:province":"TX",
    "sg:tags":[
        "shop"
    ],
    "wof:name":"Sure Elganances",
    "wof:placetype":"venue"
},
  "geometry": {"coordinates":[-106.608146,32.000087],"type":"Point"}
}