{
  "type": "Feature",
  "properties": {
    "iso:country":"US",
    "sg:address":"5416 Glen Ridge Dr",
    "sg:city":"San Antonio",
    "sg:classifiers":[
        {
            "category":"Personal",
            "subcategory":"Beauty Salon",
            "type":"Services"
        }
    ],
    "sg:phone":"+1 210 684 3427",
    "sg:postcode":"78229",
    "sg:province":"TX",
    "sg:tags":[
        "shop"
    ],
    "wof:name":"Artistic Hair Salon",
    "wof:placetype":"venue"
},
  "geometry": {"coordinates":[-98.594128,29.486135],"type":"Point"}
}