{
  "type": "Feature",
  "properties": {
    "iso:country":"US",
    "sg:address":"2445 Gateway Dr",
    "sg:city":"Irving",
    "sg:classifiers":[
        {
            "category":"Health Services",
            "subcategory":"Medical Lab",
            "type":"Services"
        }
    ],
    "sg:phone":"+1 214 821 1770",
    "sg:postcode":"75063",
    "sg:province":"TX",
    "sg:tags":[
        "laboratory"
    ],
    "wof:name":"Dhs Management Services Inc",
    "wof:placetype":"venue"
},
  "geometry": {"coordinates":[-96.984731,32.893257],"type":"Point"}
}