{
  "type": "Feature",
  "properties": {
    "iso:country":"US",
    "sg:address":"5697 Westcreek Dr",
    "sg:city":"Fort Worth",
    "sg:classifiers":[
        {
            "category":"Shopping",
            "subcategory":"Bicycles & Sporting Goods",
            "type":"Retail Goods"
        }
    ],
    "sg:phone":"+1 817 294 4372",
    "sg:postcode":"76133",
    "sg:province":"TX",
    "sg:tags":[
        "gun",
        "gunsmith"
    ],
    "wof:name":"Firearms Unlimited",
    "wof:placetype":"venue"
},
  "geometry": {"coordinates":[-97.361817,32.663772],"type":"Point"}
}