{
  "type": "Feature",
  "properties": {
    "iso:country":"US",
    "sg:address":"4709 Lucky Ln",
    "sg:city":"Dallas",
    "sg:classifiers":[
        {
            "category":"Travel",
            "subcategory":"Hotels & Motels",
            "type":"Entertainment"
        }
    ],
    "sg:phone":"+1 214 678 0466",
    "sg:postcode":"75247",
    "sg:province":"TX",
    "wof:name":"Relax Inn",
    "wof:placetype":"venue"
},
  "geometry": {"coordinates":[-96.874397,32.803799],"type":"Point"}
}