{
  "type": "Feature",
  "properties": {
    "iso:country":"US",
    "sg:address":"253 Memorial City Way",
    "sg:city":"Houston",
    "sg:classifiers":[
        {
            "category":"Shopping",
            "subcategory":"Shoes",
            "type":"Retail Goods"
        }
    ],
    "sg:phone":"+1 713 461 3925",
    "sg:postcode":"77024",
    "sg:province":"TX",
    "wof:name":"Lady Foot Locker",
    "wof:placetype":"venue"
},
  "geometry": {"coordinates":[-95.535985,29.778895],"type":"Point"}
}