{
  "type": "Feature",
  "properties": {
    "iso:country":"US",
    "sg:address":"4657 Old Pond Dr",
    "sg:city":"Plano",
    "sg:classifiers":[
        {
            "category":"Professional",
            "subcategory":"Business Services",
            "type":"Services"
        }
    ],
    "sg:phone":"+1 972 801 9922",
    "sg:postcode":"75024",
    "sg:province":"TX",
    "wof:name":"Kolbe & Assoc",
    "wof:placetype":"venue"
},
  "geometry": {"coordinates":[-96.788338,33.075114],"type":"Point"}
}