{
  "type": "Feature",
  "properties": {
    "iso:country":"US",
    "sg:address":"504 W Coffin St",
    "sg:city":"Denison",
    "sg:classifiers":[
        {
            "category":"Building & Trades",
            "subcategory":"Electrical",
            "type":"Services"
        }
    ],
    "sg:phone":"+1 903 465 8087",
    "sg:postcode":"75020",
    "sg:province":"TX",
    "sg:tags":[
        "general",
        "electrical",
        "contractor"
    ],
    "wof:name":"Luke Horn Electric",
    "wof:placetype":"venue"
},
  "geometry": {"coordinates":[-96.544104,33.73218],"type":"Point"}
}