{
  "type": "Feature",
  "properties": {
    "iso:country":"US",
    "sg:address":"101 W Mill Ave",
    "sg:city":"Comanche",
    "sg:classifiers":[
        {
            "category":"Health Services",
            "subcategory":"Doctor",
            "type":"Services"
        }
    ],
    "sg:phone":"+1 325 356 7537",
    "sg:postcode":"76442",
    "sg:province":"TX",
    "sg:tags":[
        "physician",
        "surgeon",
        "medical"
    ],
    "wof:name":"Comanche Family Medical Clinic",
    "wof:placetype":"venue"
},
  "geometry": {"coordinates":[-98.60502700000001,31.895539],"type":"Point"}
}