{
  "type": "Feature",
  "properties": {
    "iso:country":"US",
    "sg:address":"112 N Peters St",
    "sg:city":"Daingerfield",
    "sg:classifiers":[
        {
            "category":"Shopping",
            "subcategory":"Pharmacy",
            "type":"Retail Goods"
        }
    ],
    "sg:phone":"+1 903 645 2785",
    "sg:postcode":"75638",
    "sg:province":"TX",
    "wof:name":"Medcare Plus Pharmacy",
    "wof:placetype":"venue"
},
  "geometry": {"coordinates":[-94.723927,33.03254],"type":"Point"}
}