{
  "type": "Feature",
  "properties": {
    "iso:country":"US",
    "sg:address":"1004 Benedict St",
    "sg:city":"Caldwell",
    "sg:classifiers":[
        {
            "category":"Shopping",
            "type":"Retail Goods"
        }
    ],
    "sg:phone":"+1 979 567 0506",
    "sg:postcode":"77836",
    "sg:province":"TX",
    "sg:tags":[
        "merchandise"
    ],
    "wof:name":"Person Merchandise",
    "wof:placetype":"venue"
},
  "geometry": {"coordinates":[-96.71298899999999,30.524257],"type":"Point"}
}