{
  "type": "Feature",
  "properties": {
    "iso:country":"US",
    "sg:address":"206 S Main St",
    "sg:city":"Henderson",
    "sg:classifiers":[
        {
            "category":"Real Estate",
            "subcategory":"Real Estate Agent",
            "type":"Services"
        }
    ],
    "sg:phone":"+1 903 657 7574",
    "sg:postcode":"75654",
    "sg:province":"TX",
    "sg:tags":[
        "realtor"
    ],
    "wof:name":"Rusk County Realty",
    "wof:placetype":"venue"
},
  "geometry": {"coordinates":[-94.79962399999999,32.151748],"type":"Point"}
}