{
  "type": "Feature",
  "properties": {
    "iso:country":"US",
    "sg:address":"133 S 9th St",
    "sg:city":"Slaton",
    "sg:classifiers":[
        {
            "category":"Retail",
            "subcategory":"Repair Shop",
            "type":"Services"
        }
    ],
    "sg:phone":"+1 806 828 5060",
    "sg:postcode":"79364",
    "sg:province":"TX",
    "sg:tags":[
        "merchandise"
    ],
    "wof:name":"Absolutely Wireless",
    "wof:placetype":"venue"
},
  "geometry": {"coordinates":[-101.644102,33.437428],"type":"Point"}
}