{
  "type": "Feature",
  "properties": {
    "iso:country":"US",
    "sg:address":"3417 73rd St",
    "sg:city":"Lubbock",
    "sg:classifiers":[
        {
            "category":"Professional",
            "subcategory":"Computer Services",
            "type":"Services"
        }
    ],
    "sg:phone":"+1 806 740 1414",
    "sg:postcode":"79423",
    "sg:province":"TX",
    "sg:tags":[
        "related"
    ],
    "wof:name":"Network Lubbock Inc",
    "wof:placetype":"venue"
},
  "geometry": {"coordinates":[-101.889268,33.52746],"type":"Point"}
}