{
  "type": "Feature",
  "properties": {
    "iso:country":"US",
    "sg:address":"13118 Schroeder Rd",
    "sg:city":"Houston",
    "sg:classifiers":[
        {
            "category":"Freight",
            "type":"Transportation"
        }
    ],
    "sg:phone":"+1 281 955 9718",
    "sg:postcode":"77070",
    "sg:province":"TX",
    "sg:tags":[
        "special"
    ],
    "wof:name":"Prestonwood Rv Boat Storage",
    "wof:placetype":"venue"
},
  "geometry": {"coordinates":[-95.55627699999999,29.97361],"type":"Point"}
}