{
  "type": "Feature",
  "properties": {
    "iso:country":"US",
    "sg:address":"2237 Cottonwood Ln",
    "sg:city":"Bedford",
    "sg:classifiers":[
        {
            "category":"Food & Beverages",
            "subcategory":"Groceries & Convenience Stores",
            "type":"Retail Goods"
        }
    ],
    "sg:phone":"+1 817 354 9159",
    "sg:postcode":"76021",
    "sg:province":"TX",
    "wof:name":"ATL Services LLC",
    "wof:placetype":"venue"
},
  "geometry": {"coordinates":[-97.104613,32.846002],"type":"Point"}
}