{
  "type": "Feature",
  "properties": {
    "iso:country":"US",
    "sg:address":"8522 Coppersky",
    "sg:city":"Converse",
    "sg:classifiers":[
        {
            "category":"Banks & Credit Unions",
            "subcategory":"Bank",
            "type":"Services"
        },
        {
            "category":"Shopping",
            "subcategory":"Used Merchandise",
            "type":"Retail Goods"
        }
    ],
    "sg:phone":"+1 210 566 8778",
    "sg:postcode":"78109",
    "sg:province":"TX",
    "sg:tags":[
        "resale",
        "shop",
        "second",
        "hand"
    ],
    "wof:name":"Jimmie J Bankston",
    "wof:placetype":"venue"
},
  "geometry": {"coordinates":[-98.29375400000001,29.508839],"type":"Point"}
}