{
  "type": "Feature",
  "properties": {
    "iso:country":"US",
    "sg:address":"12707 Pleasant Grove Rd",
    "sg:city":"Cypress",
    "sg:classifiers":[
        {
            "category":"Shopping",
            "subcategory":"Books",
            "type":"Retail Goods"
        }
    ],
    "sg:phone":"+1 281 373 0998",
    "sg:postcode":"77429",
    "sg:province":"TX",
    "wof:name":"Jahjep Books",
    "wof:placetype":"venue"
},
  "geometry": {"coordinates":[-95.64597000000001,29.959028],"type":"Point"}
}