{
  "type": "Feature",
  "properties": {
    "iso:country":"US",
    "sg:address":"9639 Hillcroft Ste 841",
    "sg:city":"Houston",
    "sg:classifiers":[
        {
            "category":"Professional",
            "subcategory":"Accounting & Tax Preparation",
            "type":"Services"
        },
        {
            "category":"Banks & Credit Unions",
            "subcategory":"Financial Services",
            "type":"Services"
        }
    ],
    "sg:phone":"+1 713 721 3321",
    "sg:postcode":"77096",
    "sg:province":"TX",
    "sg:tags":[
        "accountant",
        "advising"
    ],
    "wof:name":"Michael Plaks",
    "wof:placetype":"venue"
},
  "geometry": {"coordinates":[-95.49361,29.676393],"type":"Point"}
}