{
  "type": "Feature",
  "properties": {
    "iso:country":"US",
    "sg:address":"137 Currency Dr",
    "sg:city":"Del Rio",
    "sg:classifiers":[
        {
            "category":"Autos & Motor Vehicles",
            "subcategory":"Auto Supplies",
            "type":"Retail Goods"
        }
    ],
    "sg:phone":"+1 830 298 0143",
    "sg:postcode":"78840",
    "sg:province":"TX",
    "sg:tags":[
        "tire"
    ],
    "wof:name":"Sanchez Tire Shop",
    "wof:placetype":"venue"
},
  "geometry": {"coordinates":[-100.841679,29.370184],"type":"Point"}
}