{
  "type": "Feature",
  "properties": {
    "iso:country":"US",
    "sg:address":"2025 Midway Rd Ste C",
    "sg:city":"Carrollton",
    "sg:classifiers":[
        {
            "category":"Shopping",
            "subcategory":"Stationery & Office Supplies",
            "type":"Retail Goods"
        },
        {
            "category":"Wholesale",
            "subcategory":"Office Equipment",
            "type":"Manufacturing & Wholesale Goods"
        },
        {
            "category":"Shopping",
            "subcategory":"Computers & Home Electronics",
            "type":"Retail Goods"
        }
    ],
    "sg:phone":"+1 972 387 2583",
    "sg:postcode":"75006",
    "sg:province":"TX",
    "sg:tags":[
        "typewriter",
        "furniture"
    ],
    "wof:name":"ReGenesis",
    "wof:placetype":"venue"
},
  "geometry": {"coordinates":[-96.83869300000001,32.96285],"type":"Point"}
}