{
  "type": "Feature",
  "properties": {
    "iso:country":"US",
    "sg:address":"112 N Acacia Park Cir",
    "sg:city":"Spring",
    "sg:classifiers":[
        {
            "category":"Insurance",
            "subcategory":"Insurance Agent",
            "type":"Services"
        }
    ],
    "sg:phone":"+1 281 292 2464",
    "sg:postcode":"77382",
    "sg:province":"TX",
    "wof:name":"Schmitz Insurance Agency",
    "wof:placetype":"venue"
},
  "geometry": {"coordinates":[-95.530528,30.218907],"type":"Point"}
}