{
  "type": "Feature",
  "properties": {
    "iso:country":"US",
    "sg:address":"3710 Stanford St",
    "sg:city":"Houston",
    "sg:classifiers":[
        {
            "category":"Personal",
            "subcategory":"Beauty Salon",
            "type":"Services"
        }
    ],
    "sg:phone":"+1 713 683 1511",
    "sg:postcode":"77006",
    "sg:province":"TX",
    "sg:tags":[
        "shop"
    ],
    "wof:name":"Axis Hair Design",
    "wof:placetype":"venue"
},
  "geometry": {"coordinates":[-95.38896099999999,29.738882],"type":"Point"}
}