{
  "type": "Feature",
  "properties": {
    "iso:country":"US",
    "sg:address":"9713 Kennemer Dr",
    "sg:city":"Plano",
    "sg:classifiers":[
        {
            "category":"Building & Trades",
            "subcategory":"Landscaping Services",
            "type":"Services"
        }
    ],
    "sg:phone":"+1 972 359 7993",
    "sg:postcode":"75025",
    "sg:province":"TX",
    "wof:name":"North Side Lawn & Landscape",
    "wof:placetype":"venue"
},
  "geometry": {"coordinates":[-96.740251,33.109524],"type":"Point"}
}