{
  "type": "Feature",
  "properties": {
    "iso:country":"US",
    "sg:address":"3202 Worthington Dr",
    "sg:city":"Pearland",
    "sg:classifiers":[
        {
            "category":"Shopping",
            "subcategory":"Computers & Home Electronics",
            "type":"Retail Goods"
        }
    ],
    "sg:phone":"+1 713 436 6040",
    "sg:postcode":"77584",
    "sg:province":"TX",
    "sg:tags":[
        "software"
    ],
    "wof:name":"Rib Software",
    "wof:placetype":"venue"
},
  "geometry": {"coordinates":[-95.37191300000001,29.57133],"type":"Point"}
}