{
  "type": "Feature",
  "properties": {
    "iso:country":"US",
    "sg:address":"1019 N Ejido Ave",
    "sg:city":"Laredo",
    "sg:classifiers":[
        {
            "category":"Food & Beverages",
            "subcategory":"Groceries & Convenience Stores",
            "type":"Retail Goods"
        }
    ],
    "sg:phone":"+1 956 725 7984",
    "sg:postcode":"78043",
    "sg:province":"TX",
    "sg:tags":[
        "grocer"
    ],
    "wof:name":"Mancillas Grocery",
    "wof:placetype":"venue"
},
  "geometry": {"coordinates":[-99.462841,27.505468],"type":"Point"}
}