{
  "type": "Feature",
  "properties": {
    "iso:country":"US",
    "sg:address":"4725 Colleyville Blvd",
    "sg:city":"Colleyville",
    "sg:classifiers":[
        {
            "category":"Restaurant",
            "type":"Food & Drink"
        }
    ],
    "sg:menulink":"http://www.allmenus.com/tx/northeast-tarrant/166382-arbys/menu/",
    "sg:phone":"+1 817 281 5673",
    "sg:postcode":"76034",
    "sg:province":"TX",
    "sg:tags":[
        "burger",
        "american"
    ],
    "wof:name":"Arby's",
    "wof:placetype":"venue"
},
  "geometry": {"coordinates":[-97.156621,32.879498],"type":"Point"}
}