{
  "type": "Feature",
  "properties": {
    "iso:country":"US",
    "sg:address":"3119 30th St",
    "sg:city":"Lubbock",
    "sg:classifiers":[
        {
            "category":"Professional",
            "type":"Services"
        }
    ],
    "sg:phone":"+1 806 793 8372",
    "sg:postcode":"79410",
    "sg:province":"TX",
    "wof:name":"Fiddle Wicks",
    "wof:placetype":"venue"
},
  "geometry": {"coordinates":[-101.88309700000001,33.56686],"type":"Point"}
}