{
  "type": "Feature",
  "properties": {
    "iso:country":"US",
    "sg:address":"3519 Huggins Way St",
    "sg:city":"Pearland",
    "sg:classifiers":[
        {
            "category":"Professional",
            "subcategory":"Computer Services",
            "type":"Services"
        }
    ],
    "sg:phone":"+1 281 997 2960",
    "sg:postcode":"77584",
    "sg:province":"TX",
    "sg:tags":[
        "consulting",
        "software"
    ],
    "wof:name":"Object Edge",
    "wof:placetype":"venue"
},
  "geometry": {"coordinates":[-95.36317200000001,29.55006],"type":"Point"}
}