{
  "type": "Feature",
  "properties": {
    "iso:country":"US",
    "sg:address":"319 E Eldora Rd",
    "sg:city":"Pharr",
    "sg:classifiers":[
        {
            "category":"Building & Trades",
            "subcategory":"Plumbing",
            "type":"Services"
        }
    ],
    "sg:phone":"+1 956 787 0165",
    "sg:postcode":"78577",
    "sg:province":"TX",
    "sg:tags":[
        "plumbing",
        "contractor"
    ],
    "wof:name":"Roy's Plumbing-Plus",
    "wof:placetype":"venue"
},
  "geometry": {"coordinates":[-98.17663899999999,26.22578],"type":"Point"}
}