{
  "type": "Feature",
  "properties": {
    "iso:country":"US",
    "sg:address":"5350 S Staples St",
    "sg:city":"Corpus Christi",
    "sg:classifiers":[
        {
            "category":"Professional",
            "subcategory":"Lawyer & Legal Services",
            "type":"Services"
        }
    ],
    "sg:phone":"+1 361 992 8999",
    "sg:postcode":"78411",
    "sg:province":"TX",
    "wof:name":"Abraham Moss",
    "wof:placetype":"venue"
},
  "geometry": {"coordinates":[-97.37236900000001,27.70374],"type":"Point"}
}