{
  "type": "Feature",
  "properties": {
    "iso:country":"US",
    "sg:address":"119 Burnet Dr",
    "sg:city":"Baytown",
    "sg:classifiers":[
        {
            "category":"Personal",
            "subcategory":"Beauty Salon",
            "type":"Services"
        }
    ],
    "sg:phone":"+1 281 424 7321",
    "sg:postcode":"77520",
    "sg:province":"TX",
    "sg:tags":[
        "shop"
    ],
    "wof:name":"Aesthetics Skin Care Clinic",
    "wof:placetype":"venue"
},
  "geometry": {"coordinates":[-95.03570499999999,29.769491],"type":"Point"}
}