{
  "type": "Feature",
  "properties": {
    "iso:country":"US",
    "sg:address":"4038 Starbridge Pointe Ln",
    "sg:city":"Katy",
    "sg:classifiers":[
        {
            "category":"Restaurant",
            "type":"Food & Drink"
        }
    ],
    "sg:phone":"+1 281 829 0779",
    "sg:postcode":"77449",
    "sg:province":"TX",
    "sg:tags":[
        "eating"
    ],
    "wof:name":"H&L Catering Service",
    "wof:placetype":"venue"
},
  "geometry": {"coordinates":[-95.749692,29.830169],"type":"Point"}
}