{
  "type": "Feature",
  "properties": {
    "iso:country":"US",
    "sg:address":"1018 Victorian Ct",
    "sg:city":"Seabrook",
    "sg:classifiers":[
        {
            "category":"Wholesale",
            "subcategory":"Auto Parts",
            "type":"Manufacturing & Wholesale Goods"
        }
    ],
    "sg:phone":"+1 713 875 7818",
    "sg:postcode":"77586",
    "sg:province":"TX",
    "sg:tags":[
        "automobile"
    ],
    "wof:name":"Aero-Colours Inc",
    "wof:placetype":"venue"
},
  "geometry": {"coordinates":[-95.011865,29.578854],"type":"Point"}
}