{
  "type": "Feature",
  "properties": {
    "iso:country":"US",
    "sg:address":"3707 W Camp Wisdom Rd",
    "sg:city":"Dallas",
    "sg:classifiers":[
        {
            "category":"Shopping",
            "subcategory":"Clothing, Apparel, & Fashions",
            "type":"Retail Goods"
        }
    ],
    "sg:phone":"+1 972 613 3000",
    "sg:postcode":"75237",
    "sg:province":"TX",
    "sg:tags":[
        "boy",
        "store"
    ],
    "wof:name":"N T A Menswear",
    "wof:placetype":"venue"
},
  "geometry": {"coordinates":[-96.879006,32.662115],"type":"Point"}
}