{
  "type": "Feature",
  "properties": {
    "iso:country":"US",
    "sg:address":"3638 Co Rd 341",
    "sg:city":"Mc Kinney",
    "sg:classifiers":[
        {
            "category":"Building & Trades",
            "subcategory":"Construction",
            "type":"Services"
        }
    ],
    "sg:phone":"+1 214 215 0792",
    "sg:postcode":"75071",
    "sg:province":"TX",
    "sg:tags":[
        "house"
    ],
    "wof:name":"Grimaldo Construction LLC",
    "wof:placetype":"venue"
},
  "geometry": {"coordinates":[-96.54990599999999,33.249958],"type":"Point"}
}