{
  "type": "Feature",
  "properties": {
    "iso:country":"US",
    "sg:address":"3513 Lockwood Dr Ste C",
    "sg:city":"Houston",
    "sg:classifiers":[
        {
            "category":"Shopping",
            "subcategory":"Bicycles & Sporting Goods",
            "type":"Retail Goods"
        }
    ],
    "sg:phone":"+1 713 673 2577",
    "sg:postcode":"77026",
    "sg:province":"TX",
    "wof:name":"Buck Terrell Athletics",
    "wof:placetype":"venue"
},
  "geometry": {"coordinates":[-95.316101,29.791201],"type":"Point"}
}