{
  "type": "Feature",
  "properties": {
    "iso:country":"US",
    "sg:address":"7500 Callaghan Rd",
    "sg:city":"San Antonio",
    "sg:classifiers":[
        {
            "category":"Professional",
            "subcategory":"Business Services",
            "type":"Services"
        }
    ],
    "sg:phone":"+1 210 348 7562",
    "sg:postcode":"78229",
    "sg:province":"TX",
    "wof:name":"Medical Media Group",
    "wof:placetype":"venue"
},
  "geometry": {"coordinates":[-98.558374,29.504952],"type":"Point"}
}