{
  "type": "Feature",
  "properties": {
    "iso:country":"US",
    "sg:address":"1505 Kesser Dr",
    "sg:city":"Plano",
    "sg:classifiers":[
        {
            "category":"Banks & Credit Unions",
            "subcategory":"Bank",
            "type":"Services"
        }
    ],
    "sg:phone":"+1 972 517 4094",
    "sg:postcode":"75025",
    "sg:province":"TX",
    "sg:tags":[
        "mortgage"
    ],
    "wof:name":"Unstoppable Dreams Marketing",
    "wof:placetype":"venue"
},
  "geometry": {"coordinates":[-96.719899,33.082158],"type":"Point"}
}