{
  "type": "Feature",
  "properties": {
    "iso:country":"US",
    "sg:address":"2142 Cordoba Dr",
    "sg:city":"Carrollton",
    "sg:classifiers":[
        {
            "category":"Shopping",
            "subcategory":"Clothing, Apparel, & Fashions",
            "type":"Retail Goods"
        }
    ],
    "sg:phone":"+1 972 242 7615",
    "sg:postcode":"75006",
    "sg:province":"TX",
    "wof:name":"Wear Original Wonders",
    "wof:placetype":"venue"
},
  "geometry": {"coordinates":[-96.88121700000001,32.97871],"type":"Point"}
}