{
  "type": "Feature",
  "properties": {
    "iso:country":"US",
    "sg:address":"12924 W Hwy 80 E",
    "sg:city":"Odessa",
    "sg:classifiers":[
        {
            "category":"Building & Trades",
            "subcategory":"Construction",
            "type":"Services"
        }
    ],
    "sg:phone":"+1 432 563 1852",
    "sg:postcode":"79765",
    "sg:province":"TX",
    "sg:tags":[
        "fence",
        "contractor"
    ],
    "wof:name":"Abbott Supply Fence Div",
    "wof:placetype":"venue"
},
  "geometry": {"coordinates":[-102.253444,31.903881],"type":"Point"}
}