{
  "type": "Feature",
  "properties": {
    "iso:country":"US",
    "sg:address":"404 Ohio Ave",
    "sg:city":"Graham",
    "sg:classifiers":[
        {
            "category":"Retail",
            "subcategory":"Repair Shop",
            "type":"Services"
        }
    ],
    "sg:phone":"+1 940 549 2959",
    "sg:postcode":"76450",
    "sg:province":"TX",
    "sg:tags":[
        "welding"
    ],
    "wof:name":"Burgess Welding",
    "wof:placetype":"venue"
},
  "geometry": {"coordinates":[-98.57275199999999,33.108851],"type":"Point"}
}