{
  "type": "Feature",
  "properties": {
    "iso:country":"US",
    "sg:address":"1701 Brittmoore Rd",
    "sg:city":"Houston",
    "sg:classifiers":[
        {
            "category":"Building & Trades",
            "subcategory":"Construction",
            "type":"Services"
        }
    ],
    "sg:phone":"+1 713 682 8811",
    "sg:postcode":"77043",
    "sg:province":"TX",
    "sg:tags":[
        "exterior"
    ],
    "wof:name":"Shahmoradi & Associates Inc",
    "wof:placetype":"venue"
},
  "geometry": {"coordinates":[-95.56993799999999,29.805548],"type":"Point"}
}