{
  "type": "Feature",
  "properties": {
    "iso:country":"US",
    "sg:address":"804 Avenue F NW",
    "sg:city":"Childress",
    "sg:classifiers":[
        {
            "category":"Wholesale",
            "subcategory":"Hardware",
            "type":"Manufacturing & Wholesale Goods"
        },
        {
            "category":"Home & Garden",
            "subcategory":"Garden Supply",
            "type":"Retail Goods"
        },
        {
            "category":"Retail",
            "subcategory":"Repair Shop",
            "type":"Services"
        }
    ],
    "sg:phone":"+1 940 937 2002",
    "sg:postcode":"79201",
    "sg:province":"TX",
    "sg:tags":[
        "renting",
        "lawn",
        "outdoor",
        "power",
        "landscaping",
        "equipment-sales",
        "equipment",
        "saw"
    ],
    "sg:website":"http://www.stihldealer.net/default-dealer-040025.aspx",
    "wof:name":"Lott Sales Company",
    "wof:placetype":"venue"
},
  "geometry": {"coordinates":[-100.212228,34.429338],"type":"Point"}
}