{
  "type": "Feature",
  "properties": {
    "iso:country":"US",
    "sg:address":"4105 Wilbarger St",
    "sg:city":"Vernon",
    "sg:classifiers":[
        {
            "category":"Insurance",
            "subcategory":"Insurance Agent",
            "type":"Services"
        }
    ],
    "sg:phone":"+1 940 552 0500",
    "sg:postcode":"76384",
    "sg:province":"TX",
    "wof:name":"Allstate Insurance",
    "wof:placetype":"venue"
},
  "geometry": {"coordinates":[-99.310913,34.15223],"type":"Point"}
}