{
  "type": "Feature",
  "properties": {
    "iso:country":"US",
    "sg:address":"807 N 8th St",
    "sg:city":"Alpine",
    "sg:classifiers":[
        {
            "category":"Manufacturing",
            "subcategory":"Metals",
            "type":"Manufacturing & Wholesale Goods"
        }
    ],
    "sg:phone":"+1 432 238 8435",
    "sg:postcode":"79830",
    "sg:province":"TX",
    "sg:tags":[
        "sheet",
        "fabrication"
    ],
    "wof:name":"7m Fabrication",
    "wof:placetype":"venue"
},
  "geometry": {"coordinates":[-103.66713300000001,30.363142],"type":"Point"}
}