{
  "type": "Feature",
  "properties": {
    "iso:country":"US",
    "sg:address":"3751 Tanacross Dr",
    "sg:city":"Fort Worth",
    "sg:classifiers":[
        {
            "category":"Travel",
            "subcategory":"Hotels & Motels",
            "type":"Entertainment"
        }
    ],
    "sg:phone":"+1 817 222 2333",
    "sg:postcode":"76137",
    "sg:province":"TX",
    "sg:tags":[
        "operation"
    ],
    "wof:name":"Comfort Suites North",
    "wof:placetype":"venue"
},
  "geometry": {"coordinates":[-97.292198,32.836974],"type":"Point"}
}