{
  "type": "Feature",
  "properties": {
    "iso:country":"US",
    "sg:address":"306 19th St NW",
    "sg:city":"Childress",
    "sg:classifiers":[
        {
            "category":"Freight",
            "type":"Transportation"
        }
    ],
    "sg:phone":"+1 940 937 8621",
    "sg:postcode":"79201",
    "sg:province":"TX",
    "sg:tags":[
        "commercial",
        "storage"
    ],
    "wof:name":"ACI Storage Units",
    "wof:placetype":"venue"
},
  "geometry": {"coordinates":[-100.226232,34.431162],"type":"Point"}
}