{
  "type": "Feature",
  "properties": {
    "iso:country":"US",
    "sg:address":"505 Willowcrest Dr",
    "sg:city":"Garland",
    "sg:classifiers":[
        {
            "category":"Professional",
            "subcategory":"Lawyer & Legal Services",
            "type":"Services"
        }
    ],
    "sg:phone":"+1 972 495 6094",
    "sg:postcode":"75040",
    "sg:province":"TX",
    "sg:tags":[
        "plan"
    ],
    "wof:name":"Keith Brown Law Office",
    "wof:placetype":"venue"
},
  "geometry": {"coordinates":[-96.63555100000001,32.945114],"type":"Point"}
}