{
  "type": "Feature",
  "properties": {
    "iso:country":"US",
    "sg:address":"2208 Lee St",
    "sg:city":"Waco",
    "sg:classifiers":[
        {
            "category":"Social Services",
            "subcategory":"Child Care",
            "type":"Services"
        }
    ],
    "sg:phone":"+1 254 759 0292",
    "sg:postcode":"76711",
    "sg:province":"TX",
    "wof:name":"Z Bear Evening Childcare",
    "wof:placetype":"venue"
},
  "geometry": {"coordinates":[-97.142117,31.513379],"type":"Point"}
}