{
  "type": "Feature",
  "properties": {
    "iso:country":"US",
    "sg:address":"2518 NW Stallings Dr",
    "sg:city":"Nacogdoches",
    "sg:classifiers":[
        {
            "category":"Autos & Motor Vehicles",
            "subcategory":"Motorcycle Sales",
            "type":"Retail Goods"
        }
    ],
    "sg:phone":"+1 936 715 0100",
    "sg:postcode":"75964",
    "sg:province":"TX",
    "sg:tags":[
        "scooter",
        "parts"
    ],
    "wof:name":"Texas Thunder Harely Davidson",
    "wof:placetype":"venue"
},
  "geometry": {"coordinates":[-94.68375399999999,31.627267],"type":"Point"}
}