{
  "type": "Feature",
  "properties": {
    "iso:country":"US",
    "sg:address":"2305 Benbrook Dr",
    "sg:city":"Carrollton",
    "sg:classifiers":[
        {
            "category":"Building & Trades",
            "subcategory":"Construction",
            "type":"Services"
        }
    ],
    "sg:phone":"+1 972 245 6211",
    "sg:postcode":"75007",
    "sg:province":"TX",
    "sg:tags":[
        "tile",
        "dealer"
    ],
    "wof:name":"Francisco Garcia Tile",
    "wof:placetype":"venue"
},
  "geometry": {"coordinates":[-96.875428,32.988702],"type":"Point"}
}