{
  "type": "Feature",
  "properties": {
    "iso:country":"US",
    "sg:address":"1505 Hill Rd",
    "sg:city":"Houston",
    "sg:classifiers":[
        {
            "category":"Manufacturing",
            "subcategory":"Rubber & Plastics",
            "type":"Manufacturing & Wholesale Goods"
        }
    ],
    "sg:phone":"+1 281 449 0189",
    "sg:postcode":"77039",
    "sg:province":"TX",
    "sg:tags":[
        "product",
        "extrusion",
        "mfg"
    ],
    "wof:name":"Bilden Plastics Inc",
    "wof:placetype":"venue"
},
  "geometry": {"coordinates":[-95.367614,29.895764],"type":"Point"}
}