{
  "type": "Feature",
  "properties": {
    "iso:country":"US",
    "sg:address":"404 E Cedar St",
    "sg:city":"Denver City",
    "sg:classifiers":[
        {
            "category":"Retail",
            "subcategory":"Laundry & Dry Cleaning",
            "type":"Services"
        }
    ],
    "sg:phone":"+1 806 592 8023",
    "sg:postcode":"79323",
    "sg:province":"TX",
    "wof:name":"Shermans Carpet Care",
    "wof:placetype":"venue"
},
  "geometry": {"coordinates":[-102.826077,32.962192],"type":"Point"}
}