{
  "type": "Feature",
  "properties": {
    "iso:country":"US",
    "sg:address":"2506 Seven Hills Dr",
    "sg:city":"Grand Prairie",
    "sg:classifiers":[
        {
            "category":"Building & Trades",
            "subcategory":"Construction",
            "type":"Services"
        }
    ],
    "sg:phone":"+1 972 602 9000",
    "sg:postcode":"75052",
    "sg:province":"TX",
    "sg:tags":[
        "painter"
    ],
    "wof:name":"Advanced Painting & Drywall",
    "wof:placetype":"venue"
},
  "geometry": {"coordinates":[-97.039963,32.683441],"type":"Point"}
}