{
  "type": "Feature",
  "properties": {
    "iso:country":"US",
    "sg:address":"3228 S Flores St",
    "sg:city":"San Antonio",
    "sg:classifiers":[
        {
            "category":"Restaurant",
            "type":"Food & Drink"
        }
    ],
    "sg:phone":"+1 210 532 1231",
    "sg:postcode":"78204",
    "sg:province":"TX",
    "sg:tags":[
        "drinking",
        "eating"
    ],
    "wof:name":"Blue Moon Cafe",
    "wof:placetype":"venue"
},
  "geometry": {"coordinates":[-98.50389800000001,29.391761],"type":"Point"}
}