{
  "type": "Feature",
  "properties": {
    "iso:country":"US",
    "sg:address":"436 Hillview Dr",
    "sg:city":"Hurst",
    "sg:classifiers":[
        {
            "category":"Professional",
            "subcategory":"Management & Consulting",
            "type":"Services"
        }
    ],
    "sg:phone":"+1 817 282 9106",
    "sg:postcode":"76054",
    "sg:province":"TX",
    "sg:tags":[
        "consultant",
        "business"
    ],
    "wof:name":"Strategic Action",
    "wof:placetype":"venue"
},
  "geometry": {"coordinates":[-97.176666,32.843773],"type":"Point"}
}