{
  "type": "Feature",
  "properties": {
    "iso:country":"US",
    "sg:address":"1564 Los Ebanos Dr",
    "sg:city":"Laredo",
    "sg:classifiers":[
        {
            "category":"Food & Beverages",
            "subcategory":"Groceries & Convenience Stores",
            "type":"Retail Goods"
        }
    ],
    "sg:phone":"+1 956 542 5062",
    "sg:postcode":"78041",
    "sg:province":"TX",
    "wof:name":"Circle K",
    "wof:placetype":"venue"
},
  "geometry": {"coordinates":[-99.474526,27.550362],"type":"Point"}
}