{
  "type": "Feature",
  "properties": {
    "iso:country":"US",
    "sg:address":"408 Coleman St",
    "sg:city":"Marlin",
    "sg:classifiers":[
        {
            "category":"Personal",
            "subcategory":"Beauty Salon",
            "type":"Services"
        }
    ],
    "sg:phone":"+1 254 883 2341",
    "sg:postcode":"76661",
    "sg:province":"TX",
    "sg:tags":[
        "shop"
    ],
    "wof:name":"Jo Anna's Creative Styling",
    "wof:placetype":"venue"
},
  "geometry": {"coordinates":[-96.89224400000001,31.307391],"type":"Point"}
}