{
  "type": "Feature",
  "properties": {
    "iso:country":"US",
    "sg:address":"2339 Pollex Ave",
    "sg:city":"Corpus Christi",
    "sg:classifiers":[
        {
            "category":"Farming",
            "subcategory":"Farm & Veterinary Services",
            "type":"Manufacturing & Wholesale Goods"
        }
    ],
    "sg:phone":"+1 361 885 0225",
    "sg:postcode":"78415",
    "sg:province":"TX",
    "sg:tags":[
        "preparation",
        "soil"
    ],
    "wof:name":"Mafsama",
    "wof:placetype":"venue"
},
  "geometry": {"coordinates":[-97.44371700000001,27.71184],"type":"Point"}
}