{
  "type": "Feature",
  "properties": {
    "iso:country":"US",
    "sg:address":"24319 Broken Bow Ln",
    "sg:city":"Hockley",
    "sg:classifiers":[
        {
            "category":"Building & Trades",
            "subcategory":"Equipment Rental",
            "type":"Services"
        }
    ],
    "sg:phone":"+1 281 989 5962",
    "sg:postcode":"77447",
    "sg:province":"TX",
    "sg:tags":[
        "yard",
        "leasing",
        "store"
    ],
    "wof:name":"Armsrtong Moonwalk Rentals",
    "wof:placetype":"venue"
},
  "geometry": {"coordinates":[-95.804501,30.023946],"type":"Point"}
}