{
  "type": "Feature",
  "properties": {
    "iso:country":"US",
    "sg:address":"302 E Dallas St",
    "sg:city":"Canton",
    "sg:classifiers":[
        {
            "category":"Autos & Motor Vehicles",
            "subcategory":"Fuel & Gas Station",
            "type":"Retail Goods"
        }
    ],
    "sg:phone":"+1 903 567 2203",
    "sg:postcode":"75103",
    "sg:province":"TX",
    "sg:tags":[
        "station",
        "gasoline"
    ],
    "wof:name":"Mobil",
    "wof:placetype":"venue"
},
  "geometry": {"coordinates":[-95.861966,32.556457],"type":"Point"}
}