{
  "type": "Feature",
  "properties": {
    "iso:country":"US",
    "sg:address":"101 Garrapata Ln",
    "sg:city":"San Antonio",
    "sg:classifiers":[
        {
            "category":"Banks & Credit Unions",
            "subcategory":"Financial Services",
            "type":"Services"
        }
    ],
    "sg:phone":"+1 210 490 6894",
    "sg:postcode":"78232",
    "sg:province":"TX",
    "sg:tags":[
        "investor"
    ],
    "wof:name":"Kaltex Investors Inc",
    "wof:placetype":"venue"
},
  "geometry": {"coordinates":[-98.49270799999999,29.602145],"type":"Point"}
}