{
  "type": "Feature",
  "properties": {
    "iso:country":"US",
    "sg:address":"685 6th St",
    "sg:city":"Sour Lake",
    "sg:classifiers":[
        {
            "category":"Retail",
            "subcategory":"Repair Shop",
            "type":"Services"
        }
    ],
    "sg:phone":"+1 409 287 3401",
    "sg:postcode":"77640",
    "sg:province":"TX",
    "sg:tags":[
        "repairing",
        "equipment",
        "electric"
    ],
    "wof:name":"Radley Electric Inc",
    "wof:placetype":"venue"
},
  "geometry": {"coordinates":[-93.93588099999999,29.873745],"type":"Point"}
}