{
  "type": "Feature",
  "properties": {
    "iso:country":"US",
    "sg:address":"4545 Kingwood Dr Apt 1724",
    "sg:city":"Kingwood",
    "sg:classifiers":[
        {
            "category":"Restaurant",
            "type":"Food & Drink"
        }
    ],
    "sg:phone":"+1 281 446 5115",
    "sg:postcode":"77345",
    "sg:province":"TX",
    "sg:tags":[
        "mexican"
    ],
    "wof:name":"Aristides Garcia",
    "wof:placetype":"venue"
},
  "geometry": {"coordinates":[-95.182363,30.050817],"type":"Point"}
}