{
  "type": "Feature",
  "properties": {
    "iso:country":"US",
    "sg:address":"5407 N McColl Rd",
    "sg:city":"Mcallen",
    "sg:classifiers":[
        {
            "category":"Banks & Credit Unions",
            "subcategory":"Investment Brokerage",
            "type":"Services"
        }
    ],
    "sg:phone":"+1 956 668 0701",
    "sg:postcode":"78504",
    "sg:province":"TX",
    "sg:tags":[
        "consultant",
        "planning",
        "financial"
    ],
    "wof:name":"American Express Financial Adv",
    "wof:placetype":"venue"
},
  "geometry": {"coordinates":[-98.204723,26.248856],"type":"Point"}
}