{
  "type": "Feature",
  "properties": {
    "iso:country":"US",
    "sg:address":"6690 Doniphan Dr",
    "sg:city":"Canutillo",
    "sg:classifiers":[
        {
            "category":"Retail",
            "subcategory":"Auto Repair",
            "type":"Services"
        }
    ],
    "sg:phone":"+1 915 877 1519",
    "sg:postcode":"79835",
    "sg:province":"TX",
    "sg:tags":[
        "repairing",
        "shop",
        "automobile",
        "automotive"
    ],
    "wof:name":"Leo's Automotive",
    "wof:placetype":"venue"
},
  "geometry": {"coordinates":[-106.59899900000001,31.9002],"type":"Point"}
}