{
  "type": "Feature",
  "properties": {
    "iso:country":"US",
    "sg:address":"1901 Hall Ave",
    "sg:city":"Littlefield",
    "sg:classifiers":[
        {
            "category":"Autos & Motor Vehicles",
            "subcategory":"Fuel & Gas Station",
            "type":"Retail Goods"
        }
    ],
    "sg:phone":"+1 806 385 6333",
    "sg:postcode":"79339",
    "sg:province":"TX",
    "sg:tags":[
        "grocery",
        "station",
        "gasoline"
    ],
    "wof:name":"Fast Stop 3",
    "wof:placetype":"venue"
},
  "geometry": {"coordinates":[-102.327164,33.907298],"type":"Point"}
}