{
  "type": "Feature",
  "properties": {
    "iso:country":"US",
    "sg:address":"125 Industrial Dr",
    "sg:city":"Brownsville",
    "sg:classifiers":[
        {
            "category":"Wholesale",
            "subcategory":"Hardware",
            "type":"Manufacturing & Wholesale Goods"
        }
    ],
    "sg:phone":"+1 956 546 4292",
    "sg:postcode":"78521",
    "sg:province":"TX",
    "sg:tags":[
        "nut",
        "bolt"
    ],
    "sg:website":"www.sabersteelgroup.com",
    "wof:name":"Saber Steel Group",
    "wof:placetype":"venue"
},
  "geometry": {"coordinates":[-97.472104,25.919672],"type":"Point"}
}