{
  "type": "Feature",
  "properties": {
    "iso:country":"US",
    "sg:address":"1035 Dairy Ashford St",
    "sg:city":"Houston",
    "sg:classifiers":[
        {
            "category":"Travel",
            "subcategory":"Travel Agent",
            "type":"Entertainment"
        }
    ],
    "sg:phone":"+1 281 497 1668",
    "sg:postcode":"77079",
    "sg:province":"TX",
    "sg:tags":[
        "agency",
        "bureau"
    ],
    "sg:website":"www.viaadvantage.com",
    "wof:name":"American Express Advantage Trv",
    "wof:placetype":"venue"
},
  "geometry": {"coordinates":[-95.606466,29.77875],"type":"Point"}
}