{
  "type": "Feature",
  "properties": {
    "iso:country":"US",
    "sg:address":"14881 Quorum Dr",
    "sg:city":"Dallas",
    "sg:classifiers":[
        {
            "category":"Real Estate",
            "subcategory":"Real Estate Agent",
            "type":"Services"
        },
        {
            "category":"Professional",
            "subcategory":"Research",
            "type":"Services"
        }
    ],
    "sg:phone":"+1 972 701 9200",
    "sg:postcode":"75254",
    "sg:province":"TX",
    "sg:tags":[
        "consultant",
        "commercial",
        "nonphysical"
    ],
    "wof:name":"American Metro Study Corp",
    "wof:placetype":"venue"
},
  "geometry": {"coordinates":[-96.823866,32.948819],"type":"Point"}
}