{
  "type": "Feature",
  "properties": {
    "iso:country":"US",
    "sg:address":"6220 Mora Ln",
    "sg:city":"Nacogdoches",
    "sg:classifiers":[
        {
            "category":"Building & Trades",
            "subcategory":"Construction",
            "type":"Services"
        }
    ],
    "sg:phone":"+1 936 564 6290",
    "sg:postcode":"75965",
    "sg:province":"TX",
    "wof:name":"Danny Mora Metal Buildings",
    "wof:placetype":"venue"
},
  "geometry": {"coordinates":[-94.615312,31.699502],"type":"Point"}
}