{
  "type": "Feature",
  "properties": {
    "iso:country":"US",
    "sg:address":"1214 Cherokee Dr",
    "sg:city":"Richardson",
    "sg:classifiers":[
        {
            "category":"Manufacturing",
            "subcategory":"Musical Instruments",
            "type":"Manufacturing & Wholesale Goods"
        }
    ],
    "sg:phone":"+1 972 690 6844",
    "sg:postcode":"75080",
    "sg:province":"TX",
    "sg:tags":[
        "instruments-industrial-repairing"
    ],
    "wof:name":"Electro Mechanical Services",
    "wof:placetype":"venue"
},
  "geometry": {"coordinates":[-96.759433,32.962891],"type":"Point"}
}