{
  "type": "Feature",
  "properties": {
    "iso:country":"US",
    "sg:address":"3308 Clawson Rd",
    "sg:city":"Austin",
    "sg:classifiers":[
        {
            "category":"Health Services",
            "subcategory":"Clinic",
            "type":"Services"
        },
        {
            "category":"Professional",
            "subcategory":"Research",
            "type":"Services"
        },
        {
            "category":"Science Facility",
            "type":"Public Place"
        }
    ],
    "sg:phone":"+1 512 693 2545",
    "sg:postcode":"78704",
    "sg:province":"TX",
    "sg:tags":[
        "development",
        "educational",
        "laboratories-research",
        "physicist"
    ],
    "wof:name":"Austin Research Associates",
    "wof:placetype":"venue"
},
  "geometry": {"coordinates":[-97.77828,30.236927],"type":"Point"}
}