{
  "type": "Feature",
  "properties": {
    "iso:country":"US",
    "sg:address":"8518 Westview Dr",
    "sg:city":"Houston",
    "sg:classifiers":[
        {
            "category":"Professional",
            "subcategory":"Business Services",
            "type":"Services"
        }
    ],
    "sg:phone":"+1 713 461 3575",
    "sg:postcode":"77055",
    "sg:province":"TX",
    "wof:name":"Kln Properties",
    "wof:placetype":"venue"
},
  "geometry": {"coordinates":[-95.500457,29.793823],"type":"Point"}
}