{
  "type": "Feature",
  "properties": {
    "iso:country":"US",
    "sg:address":"2207 N 23rd St",
    "sg:city":"Mcallen",
    "sg:classifiers":[
        {
            "category":"Professional",
            "subcategory":"Computer Services",
            "type":"Services"
        }
    ],
    "sg:phone":"+1 956 664 0190",
    "sg:postcode":"78501",
    "sg:province":"TX",
    "sg:tags":[
        "internet"
    ],
    "wof:name":"DCCI-Vt",
    "wof:placetype":"venue"
},
  "geometry": {"coordinates":[-98.241665,26.227673],"type":"Point"}
}