{
  "type": "Feature",
  "properties": {
    "iso:country":"US",
    "sg:address":"1623 S Fry Rd",
    "sg:city":"Katy",
    "sg:classifiers":[
        {
            "category":"Health Services",
            "subcategory":"Doctor",
            "type":"Services"
        }
    ],
    "sg:phone":"+1 281 398 9711",
    "sg:postcode":"77450",
    "sg:province":"TX",
    "sg:tags":[
        "physician",
        "surgeon"
    ],
    "wof:name":"Neuro I",
    "wof:placetype":"venue"
},
  "geometry": {"coordinates":[-95.716067,29.764887],"type":"Point"}
}