{
  "type": "Feature",
  "properties": {
    "iso:country":"US",
    "sg:address":"3051 S Hwy 123 Byp",
    "sg:city":"Seguin",
    "sg:classifiers":[
        {
            "category":"Autos & Motor Vehicles",
            "subcategory":"Fuel & Gas Station",
            "type":"Retail Goods"
        }
    ],
    "sg:phone":"+1 830 372 2270",
    "sg:postcode":"78155",
    "sg:province":"TX",
    "sg:tags":[
        "oil"
    ],
    "wof:name":"Pic & Pac Convenience Stores",
    "wof:placetype":"venue"
},
  "geometry": {"coordinates":[-97.94931699999999,29.551041],"type":"Point"}
}