{
  "type": "Feature",
  "properties": {
    "iso:country":"US",
    "sg:address":"9810 Forest Ln",
    "sg:city":"Dallas",
    "sg:classifiers":[
        {
            "category":"Food & Beverages",
            "subcategory":"Ethnic Foods",
            "type":"Retail Goods"
        }
    ],
    "sg:phone":"+1 214 340 3035",
    "sg:postcode":"75243",
    "sg:province":"TX",
    "sg:tags":[
        "soul"
    ],
    "sg:website":"bigmamaschickenandwaffles.com/",
    "wof:name":"Big Mama's Chicken & Waffles",
    "wof:placetype":"venue"
},
  "geometry": {"coordinates":[-96.717465,32.909438],"type":"Point"}
}