{
  "type": "Feature",
  "properties": {
    "iso:country":"US",
    "sg:address":"413 S Mesa St",
    "sg:city":"El Paso",
    "sg:classifiers":[
        {
            "category":"Food & Beverages",
            "subcategory":"Specialty",
            "type":"Retail Goods"
        }
    ],
    "sg:phone":"+1 915 838 8614",
    "sg:postcode":"79901",
    "sg:province":"TX",
    "sg:tags":[
        "herb"
    ],
    "wof:name":"San Mira Natural",
    "wof:placetype":"venue"
},
  "geometry": {"coordinates":[-106.485921,31.754834],"type":"Point"}
}