{
  "type": "Feature",
  "properties": {
    "iso:country":"US",
    "sg:address":"10000 Wallisville Rd",
    "sg:city":"Houston",
    "sg:classifiers":[
        {
            "category":"Wholesale",
            "subcategory":"Machinery & Supplies",
            "type":"Manufacturing & Wholesale Goods"
        }
    ],
    "sg:phone":"+1 713 675 7989",
    "sg:postcode":"77013",
    "sg:province":"TX",
    "sg:tags":[
        "equipment",
        "distributes",
        "parts",
        "repair"
    ],
    "wof:name":"Martec International",
    "wof:placetype":"venue"
},
  "geometry": {"coordinates":[-95.254239,29.793516],"type":"Point"}
}