{
  "type": "Feature",
  "properties": {
    "iso:country":"US",
    "sg:address":"5085 W Park Blvd Ste 150",
    "sg:city":"Plano",
    "sg:classifiers":[
        {
            "category":"Banks & Credit Unions",
            "subcategory":"Financial Services",
            "type":"Services"
        }
    ],
    "sg:phone":"+1 469 298 1200",
    "sg:postcode":"75093",
    "sg:province":"TX",
    "sg:website":"www.collectmoneynow.com",
    "wof:name":"Haller, Harlan & Taylor",
    "wof:placetype":"venue"
},
  "geometry": {"coordinates":[-96.8001,33.027678],"type":"Point"}
}