{
  "type": "Feature",
  "properties": {
    "iso:country":"US",
    "sg:address":"3601 S Ravinia Dr",
    "sg:city":"Dallas",
    "sg:classifiers":[
        {
            "category":"Organizations",
            "subcategory":"Religious Organization",
            "type":"Services"
        }
    ],
    "sg:phone":"+1 214 337 7277",
    "sg:postcode":"75233",
    "sg:province":"TX",
    "sg:tags":[
        "church"
    ],
    "wof:name":"Southwood United Methodist Chr",
    "wof:placetype":"venue"
},
  "geometry": {"coordinates":[-96.870255,32.69911],"type":"Point"}
}