{
  "type": "Feature",
  "properties": {
    "iso:country":"US",
    "sg:address":"2915 Patzcuaro Dr",
    "sg:city":"Eagle Pass",
    "sg:classifiers":[
        {
            "category":"Insurance",
            "subcategory":"Insurance Agent",
            "type":"Services"
        }
    ],
    "sg:phone":"+1 830 758 1266",
    "sg:postcode":"78852",
    "sg:province":"TX",
    "wof:name":"Mission Life",
    "wof:placetype":"venue"
},
  "geometry": {"coordinates":[-100.468222,28.708038],"type":"Point"}
}