{
  "type": "Feature",
  "properties": {
    "iso:country":"US",
    "sg:address":"2911 E Division St Ste 41",
    "sg:city":"Arlington",
    "sg:classifiers":[
        {
            "category":"Arena",
            "subcategory":"Sports Club",
            "type":"Entertainment"
        }
    ],
    "sg:phone":"+1 817 300 8524",
    "sg:postcode":"76011",
    "sg:province":"TX",
    "sg:tags":[
        "martial art",
        "instruction"
    ],
    "wof:name":"Nguyen's Int Marshall Arts",
    "wof:placetype":"venue"
},
  "geometry": {"coordinates":[-97.056152,32.741483],"type":"Point"}
}