{
  "type": "Feature",
  "properties": {
    "iso:country":"US",
    "sg:address":"11078 State Hwy 123",
    "sg:city":"Falls City",
    "sg:classifiers":[
        {
            "category":"Autos & Motor Vehicles",
            "subcategory":"Automobile Sales",
            "type":"Retail Goods"
        }
    ],
    "sg:phone":"+1 830 745 2064",
    "sg:postcode":"78113",
    "sg:province":"TX",
    "wof:name":"Beam Trailer Sales",
    "wof:placetype":"venue"
},
  "geometry": {"coordinates":[-97.938564,29.089125],"type":"Point"}
}