{
  "type": "Feature",
  "properties": {
    "iso:country":"US",
    "sg:address":"521 E Davis St",
    "sg:city":"Luling",
    "sg:classifiers":[
        {
            "category":"Personal",
            "subcategory":"Beauty Salon",
            "type":"Services"
        }
    ],
    "sg:phone":"+1 830 875 5522",
    "sg:postcode":"78648",
    "sg:province":"TX",
    "sg:tags":[
        "shop"
    ],
    "wof:name":"Dynamic Designs",
    "wof:placetype":"venue"
},
  "geometry": {"coordinates":[-97.639554,29.680037],"type":"Point"}
}