{
  "type": "Feature",
  "properties": {
    "iso:country":"US",
    "sg:address":"400 San Felipe Rd",
    "sg:city":"Sealy",
    "sg:classifiers":[
        {
            "category":"Organizations",
            "subcategory":"Religious Organization",
            "type":"Services"
        }
    ],
    "sg:phone":"+1 979 885 2419",
    "sg:postcode":"77474",
    "sg:province":"TX",
    "sg:tags":[
        "church"
    ],
    "wof:name":"St Paul AME Church",
    "wof:placetype":"venue"
},
  "geometry": {"coordinates":[-96.15093,29.78434],"type":"Point"}
}