{
  "type": "Feature",
  "properties": {
    "iso:country":"US",
    "sg:address":"2100 Live Oak Dr",
    "sg:city":"Garland",
    "sg:classifiers":[
        {
            "category":"Building & Trades",
            "subcategory":"Locksmith",
            "type":"Services"
        }
    ],
    "sg:phone":"+1 214 416 0421",
    "sg:postcode":"75040",
    "sg:province":"TX",
    "sg:tags":[
        "key"
    ],
    "wof:name":"ALL DAY ALL NIGHT EMERGENCY A LOCKSMIT",
    "wof:placetype":"venue"
},
  "geometry": {"coordinates":[-96.602756,32.933621],"type":"Point"}
}