{
  "type": "Feature",
  "properties": {
    "iso:country":"US",
    "sg:address":"445 W Travis St",
    "sg:city":"La Grange",
    "sg:classifiers":[
        {
            "category":"Manufacturing",
            "subcategory":"Glass & Minerals",
            "type":"Manufacturing & Wholesale Goods"
        }
    ],
    "sg:phone":"+1 979 968 3149",
    "sg:postcode":"78945",
    "sg:province":"TX",
    "sg:tags":[
        "monument"
    ],
    "sg:website":"www.lwstolzmemorialsinc.com",
    "wof:name":"L W Stolz Memorials Inc",
    "wof:placetype":"venue"
},
  "geometry": {"coordinates":[-96.88018,29.903662],"type":"Point"}
}