{
  "type": "Feature",
  "properties": {
    "iso:country":"US",
    "sg:address":"1127 Elder St",
    "sg:city":"Houston",
    "sg:classifiers":[
        {
            "category":"Retail",
            "subcategory":"Laundry & Dry Cleaning",
            "type":"Services"
        }
    ],
    "sg:phone":"+1 281 759 5220",
    "sg:postcode":"77007",
    "sg:province":"TX",
    "sg:tags":[
        "drycleaning",
        "plant"
    ],
    "wof:name":"Enclave Cleaners",
    "wof:placetype":"venue"
},
  "geometry": {"coordinates":[-95.367491,29.76906],"type":"Point"}
}