{
  "type": "Feature",
  "properties": {
    "iso:country":"US",
    "sg:address":"408 Lockwood St",
    "sg:city":"Fort Worth",
    "sg:classifiers":[
        {
            "category":"Professional",
            "subcategory":"Business Services",
            "type":"Services"
        }
    ],
    "sg:phone":"+1 817 246 2636",
    "sg:postcode":"76108",
    "sg:province":"TX",
    "wof:name":"Fredricka C Blizzard",
    "wof:placetype":"venue"
},
  "geometry": {"coordinates":[-97.466318,32.764906],"type":"Point"}
}