{
  "type": "Feature",
  "properties": {
    "iso:country":"US",
    "sg:address":"2634 Yorktown St",
    "sg:city":"Houston",
    "sg:classifiers":[
        {
            "category":"Professional",
            "subcategory":"Business Services",
            "type":"Services"
        }
    ],
    "sg:phone":"+1 713 572 2736",
    "sg:postcode":"77056",
    "sg:province":"TX",
    "wof:name":"Saved By Bib",
    "wof:placetype":"venue"
},
  "geometry": {"coordinates":[-95.470691,29.740448],"type":"Point"}
}