{
  "type": "Feature",
  "properties": {
    "iso:country":"US",
    "sg:address":"617 Dorsey Dr",
    "sg:city":"El Paso",
    "sg:classifiers":[
        {
            "category":"Professional",
            "type":"Services"
        }
    ],
    "sg:phone":"+1 915 833 4350",
    "sg:postcode":"79912",
    "sg:province":"TX",
    "wof:name":"Luis Caro Inc",
    "wof:placetype":"venue"
},
  "geometry": {"coordinates":[-106.56107799999999,31.852203],"type":"Point"}
}