{
  "type": "Feature",
  "properties": {
    "iso:country":"US",
    "sg:address":"3512 Texas Blvd",
    "sg:city":"Texarkana",
    "sg:classifiers":[
        {
            "category":"Professional",
            "subcategory":"Lawyer & Legal Services",
            "type":"Services"
        }
    ],
    "sg:phone":"+1 903 791 9300",
    "sg:postcode":"75503",
    "sg:province":"TX",
    "sg:tags":[
        "attorney"
    ],
    "wof:name":"Greer Mc Casland Miller LLP",
    "wof:placetype":"venue"
},
  "geometry": {"coordinates":[-94.052903,33.451474],"type":"Point"}
}