{
  "type": "Feature",
  "properties": {
    "iso:country":"US",
    "sg:address":"317 Sioux St",
    "sg:city":"Keller",
    "sg:classifiers":[
        {
            "category":"Organizations",
            "subcategory":"Religious Organization",
            "type":"Services"
        }
    ],
    "sg:phone":"+1 817 431 3610",
    "sg:postcode":"76248",
    "sg:province":"TX",
    "wof:name":"Household of Faith",
    "wof:placetype":"venue"
},
  "geometry": {"coordinates":[-97.23957,32.927547],"type":"Point"}
}