{
  "type": "Feature",
  "properties": {
    "iso:country":"US",
    "sg:address":"2852 U S Highway 190 W",
    "sg:city":"Livingston",
    "sg:classifiers":[
        {
            "category":"Wholesale",
            "subcategory":"Farm Supplies",
            "type":"Manufacturing & Wholesale Goods"
        },
        {
            "category":"Home & Garden",
            "subcategory":"Garden Supply",
            "type":"Retail Goods"
        },
        {
            "category":"Autos & Motor Vehicles",
            "subcategory":"Auto Supplies",
            "type":"Retail Goods"
        },
        {
            "category":"Wholesale",
            "subcategory":"Machinery & Supplies",
            "type":"Manufacturing & Wholesale Goods"
        },
        {
            "category":"Autos & Motor Vehicles",
            "subcategory":"Automobile Sales",
            "type":"Retail Goods"
        }
    ],
    "sg:phone":"+1 936 967 4094",
    "sg:postcode":"77351",
    "sg:province":"TX",
    "sg:tags":[
        "lawn",
        "tractor-repair",
        "mower",
        "equipment",
        "tractor",
        "baling",
        "trailer",
        "transport"
    ],
    "sg:website":"http://www.tractorpackage.com",
    "wof:name":"Peters Tractor & Equipment Company",
    "wof:placetype":"venue"
},
  "geometry": {"coordinates":[-94.97421900000001,30.728747],"type":"Point"}
}