{
  "type": "Feature",
  "properties": {
    "iso:country":"US",
    "sg:address":"201 W Nasa Rd 1",
    "sg:city":"Webster",
    "sg:classifiers":[
        {
            "category":"Social Services",
            "subcategory":"Child Care",
            "type":"Services"
        }
    ],
    "sg:phone":"+1 281 332 2821",
    "sg:postcode":"77598",
    "sg:province":"TX",
    "sg:tags":[
        "organization",
        "religious",
        "day"
    ],
    "wof:name":"The Children School",
    "wof:placetype":"venue"
},
  "geometry": {"coordinates":[-95.119941,29.536306],"type":"Point"}
}