{
  "type": "Feature",
  "properties": {
    "iso:country":"US",
    "sg:address":"788 S Mill St",
    "sg:city":"Lewisville",
    "sg:classifiers":[
        {
            "category":"Retail",
            "subcategory":"Laundry & Dry Cleaning",
            "type":"Services"
        }
    ],
    "sg:phone":"+1 972 436 1600",
    "sg:postcode":"75057",
    "sg:province":"TX",
    "sg:tags":[
        "laundries-self",
        "operated",
        "washer",
        "dryer",
        "coin"
    ],
    "wof:name":"Star Wash Coin Laundry",
    "wof:placetype":"venue"
},
  "geometry": {"coordinates":[-96.99281499999999,33.039136],"type":"Point"}
}