{
  "type": "Feature",
  "properties": {
    "iso:country":"US",
    "sg:address":"101 Hensley Ln",
    "sg:city":"Wylie",
    "sg:classifiers":[
        {
            "category":"Education",
            "subcategory":"School",
            "type":"Public Place"
        }
    ],
    "sg:phone":"+1 972 941 9072",
    "sg:postcode":"75098",
    "sg:province":"TX",
    "sg:tags":[
        "k-",
        "private"
    ],
    "wof:name":"Cooper Jr High",
    "wof:placetype":"venue"
},
  "geometry": {"coordinates":[-96.578323,32.999691],"type":"Point"}
}