{
  "type": "Feature",
  "properties": {
    "iso:country":"US",
    "sg:address":"8009 US Hwy 87",
    "sg:city":"San Angelo",
    "sg:classifiers":[
        {
            "category":"Real Estate",
            "subcategory":"Developer",
            "type":"Services"
        }
    ],
    "sg:phone":"+1 325 481 3131",
    "sg:postcode":"76901",
    "sg:province":"TX",
    "sg:tags":[
        "cemetery"
    ],
    "wof:name":"Pioneer Memorial Park",
    "wof:placetype":"venue"
},
  "geometry": {"coordinates":[-100.537644,31.557069],"type":"Point"}
}