{
  "type": "Feature",
  "properties": {
    "iso:country":"US",
    "sg:address":"12017 Shirestone Ln",
    "sg:city":"Dallas",
    "sg:classifiers":[
        {
            "category":"Professional",
            "subcategory":"Lawyer & Legal Services",
            "type":"Services"
        }
    ],
    "sg:phone":"+1 214 712 4430",
    "sg:postcode":"75244",
    "sg:province":"TX",
    "wof:name":"Stephen L Baskind PC",
    "wof:placetype":"venue"
},
  "geometry": {"coordinates":[-96.822329,32.912847],"type":"Point"}
}