{
  "type": "Feature",
  "properties": {
    "iso:country":"US",
    "sg:address":"11023 Moonlit Park",
    "sg:city":"San Antonio",
    "sg:classifiers":[
        {
            "category":"Shopping",
            "subcategory":"Catalog Store",
            "type":"Retail Goods"
        }
    ],
    "sg:phone":"+1 210 696 3488",
    "sg:postcode":"78249",
    "sg:province":"TX",
    "sg:tags":[
        "mail",
        "house"
    ],
    "wof:name":"Surplus Supply",
    "wof:placetype":"venue"
},
  "geometry": {"coordinates":[-98.635694,29.550352],"type":"Point"}
}