{
  "type": "Feature",
  "properties": {
    "iso:country":"US",
    "sg:address":"921 7th St",
    "sg:city":"Wichita Falls",
    "sg:classifiers":[
        {
            "category":"Professional",
            "subcategory":"Lawyer & Legal Services",
            "type":"Services"
        }
    ],
    "sg:phone":"+1 940 322 4455",
    "sg:postcode":"76301",
    "sg:province":"TX",
    "sg:tags":[
        "attorney"
    ],
    "wof:name":"Charlye O Farris",
    "wof:placetype":"venue"
},
  "geometry": {"coordinates":[-98.494877,33.911699],"type":"Point"}
}