{
  "type": "Feature",
  "properties": {
    "iso:country":"US",
    "sg:address":"9100 Southwest Fwy",
    "sg:city":"Houston",
    "sg:classifiers":[
        {
            "category":"Real Estate",
            "subcategory":"Real Estate Agent",
            "type":"Services"
        }
    ],
    "sg:phone":"+1 713 541 2010",
    "sg:postcode":"77074",
    "sg:province":"TX",
    "wof:name":"Homelink Realty",
    "wof:placetype":"venue"
},
  "geometry": {"coordinates":[-95.534329,29.683871],"type":"Point"}
}