{
  "type": "Feature",
  "properties": {
    "iso:country":"US",
    "sg:address":"26036 Highway 290",
    "sg:city":"Cypress",
    "sg:classifiers":[
        {
            "category":"Restaurant",
            "type":"Food & Drink"
        }
    ],
    "sg:menulink":"http://www.allmenus.com/tx/northwest-harris/43097-new-york-pizzeria/menu/",
    "sg:phone":"+1 281 256 7111",
    "sg:postcode":"77429",
    "sg:province":"TX",
    "sg:tags":[
        "american",
        "pizza"
    ],
    "wof:name":"New York Pizzeria",
    "wof:placetype":"venue"
},
  "geometry": {"coordinates":[-95.695419,29.972831],"type":"Point"}
}