{
  "type": "Feature",
  "properties": {
    "iso:country":"US",
    "sg:address":"213 NE 32nd St",
    "sg:city":"Grand Prairie",
    "sg:classifiers":[
        {
            "category":"Shopping",
            "subcategory":"Clothing, Apparel, & Fashions",
            "type":"Retail Goods"
        }
    ],
    "sg:phone":"+1 972 266 0450",
    "sg:postcode":"75050",
    "sg:province":"TX",
    "wof:name":"Paula Godinez",
    "wof:placetype":"venue"
},
  "geometry": {"coordinates":[-96.957505,32.751727],"type":"Point"}
}