{
  "type": "Feature",
  "properties": {
    "iso:country":"US",
    "sg:address":"6060 Hooton St",
    "sg:city":"Houston",
    "sg:classifiers":[
        {
            "category":"Travel",
            "subcategory":"Hotels & Motels",
            "type":"Entertainment"
        }
    ],
    "sg:phone":"+1 713 777 9955",
    "sg:postcode":"77081",
    "sg:province":"TX",
    "wof:name":"Waloon Properties",
    "wof:placetype":"venue"
},
  "geometry": {"coordinates":[-95.495329,29.717068],"type":"Point"}
}