{
  "type": "Feature",
  "properties": {
    "iso:country":"US",
    "sg:address":"10210 Sand Pass Ln",
    "sg:city":"Houston",
    "sg:classifiers":[
        {
            "category":"Building & Trades",
            "subcategory":"Electrical",
            "type":"Services"
        }
    ],
    "sg:phone":"+1 281 970 3737",
    "sg:postcode":"77064",
    "sg:province":"TX",
    "sg:tags":[
        "electrical",
        "contractor"
    ],
    "wof:name":"Cabling Design & Installation",
    "wof:placetype":"venue"
},
  "geometry": {"coordinates":[-95.57143600000001,29.915601],"type":"Point"}
}