{
  "type": "Feature",
  "properties": {
    "iso:country":"US",
    "sg:address":"207 N Kirby St",
    "sg:city":"Garland",
    "sg:classifiers":[
        {
            "category":"Professional",
            "type":"Services"
        }
    ],
    "sg:phone":"+1 972 485 0116",
    "sg:postcode":"75042",
    "sg:province":"TX",
    "wof:name":"Absolute Stainless",
    "wof:placetype":"venue"
},
  "geometry": {"coordinates":[-96.676917,32.914919],"type":"Point"}
}