{
  "type": "Feature",
  "properties": {
    "iso:country":"US",
    "sg:address":"4401 Coit Rd",
    "sg:city":"Frisco",
    "sg:classifiers":[
        {
            "category":"Health Services",
            "subcategory":"Doctor",
            "type":"Services"
        }
    ],
    "sg:phone":"+1 972 335 9075",
    "sg:postcode":"75035",
    "sg:province":"TX",
    "sg:tags":[
        "physician",
        "surgeon"
    ],
    "wof:name":"Dallas Pulmonary Assoc",
    "wof:placetype":"venue"
},
  "geometry": {"coordinates":[-96.76828,33.113345],"type":"Point"}
}