{
  "type": "Feature",
  "properties": {
    "iso:country":"US",
    "sg:address":"1807 Tierra Mesa",
    "sg:city":"San Antonio",
    "sg:classifiers":[
        {
            "category":"Professional",
            "subcategory":"Business Services",
            "type":"Services"
        }
    ],
    "sg:phone":"+1 210 648 6470",
    "sg:postcode":"78263",
    "sg:province":"TX",
    "wof:name":"White Pat Unique Creations By",
    "wof:placetype":"venue"
},
  "geometry": {"coordinates":[-98.34692800000001,29.403767],"type":"Point"}
}