{
  "type": "Feature",
  "properties": {
    "iso:country":"US",
    "sg:address":"625 S Oak St",
    "sg:city":"Pearsall",
    "sg:classifiers":[
        {
            "category":"Restaurant",
            "type":"Food & Drink"
        }
    ],
    "sg:phone":"+1 830 334 2203",
    "sg:postcode":"78061",
    "sg:province":"TX",
    "wof:name":"Mc Donald's",
    "wof:placetype":"venue"
},
  "geometry": {"coordinates":[-99.096654,28.887192],"type":"Point"}
}