{
  "type": "Feature",
  "properties": {
    "iso:country":"US",
    "sg:address":"3106 E 2nd St",
    "sg:city":"Austin",
    "sg:classifiers":[
        {
            "category":"Organizations",
            "subcategory":"Religious Organization",
            "type":"Services"
        }
    ],
    "sg:phone":"+1 512 477 1647",
    "sg:postcode":"78702",
    "sg:province":"TX",
    "sg:tags":[
        "church"
    ],
    "sg:website":"www.eastsidecoc.com",
    "wof:name":"East Side Church of Christ",
    "wof:placetype":"venue"
},
  "geometry": {"coordinates":[-97.709006,30.25262],"type":"Point"}
}