{
  "type": "Feature",
  "properties": {
    "iso:country":"US",
    "sg:address":"3631 Deerbrook Ct",
    "sg:city":"Pearland",
    "sg:classifiers":[
        {
            "category":"Professional",
            "subcategory":"Art Services",
            "type":"Services"
        }
    ],
    "sg:phone":"+1 832 722 3925",
    "sg:postcode":"77584",
    "sg:province":"TX",
    "sg:tags":[
        "photography",
        "commercial"
    ],
    "wof:name":"Buildsmart",
    "wof:placetype":"venue"
},
  "geometry": {"coordinates":[-95.358802,29.531793],"type":"Point"}
}