{
  "type": "Feature",
  "properties": {
    "iso:country":"US",
    "sg:address":"502 E Kuhn St",
    "sg:city":"Edinburg",
    "sg:classifiers":[
        {
            "category":"Organizations",
            "subcategory":"Religious Organization",
            "type":"Services"
        }
    ],
    "sg:phone":"+1 956 383 6870",
    "sg:postcode":"78541",
    "sg:province":"TX",
    "sg:tags":[
        "monastery",
        "convent"
    ],
    "wof:name":"Sacred Heart Convent",
    "wof:placetype":"venue"
},
  "geometry": {"coordinates":[-98.156548,26.302599],"type":"Point"}
}