{
  "type": "Feature",
  "properties": {
    "iso:country":"US",
    "sg:address":"302 N 3rd St",
    "sg:city":"Mabank",
    "sg:classifiers":[
        {
            "category":"Health Services",
            "subcategory":"Chiropractor",
            "type":"Services"
        }
    ],
    "sg:phone":"+1 903 887 4440",
    "sg:postcode":"75147",
    "sg:province":"TX",
    "sg:tags":[
        "chiropractic"
    ],
    "wof:name":"Chiropractic Health Care",
    "wof:placetype":"venue"
},
  "geometry": {"coordinates":[-96.100427,32.368148],"type":"Point"}
}