{
  "type": "Feature",
  "properties": {
    "iso:country":"US",
    "sg:address":"4301 W Davis St",
    "sg:city":"Conroe",
    "sg:classifiers":[
        {
            "category":"Wholesale",
            "subcategory":"Auto Parts",
            "type":"Manufacturing & Wholesale Goods"
        }
    ],
    "sg:phone":"+1 936 788 1000",
    "sg:postcode":"77304",
    "sg:province":"TX",
    "sg:tags":[
        "mfg",
        "motor",
        "vehicle"
    ],
    "wof:name":"Porous Media Corporation",
    "wof:placetype":"venue"
},
  "geometry": {"coordinates":[-95.493686,30.324534],"type":"Point"}
}