{
  "type": "Feature",
  "properties": {
    "iso:country":"US",
    "sg:address":"5255 Commercial Dr",
    "sg:city":"Brownsville",
    "sg:classifiers":[
        {
            "category":"Building & Trades",
            "subcategory":"Electrical",
            "type":"Services"
        }
    ],
    "sg:phone":"+1 956 831 7801",
    "sg:postcode":"78521",
    "sg:province":"TX",
    "sg:tags":[
        "electric",
        "contractor"
    ],
    "wof:name":"Metro Electric Inc",
    "wof:placetype":"venue"
},
  "geometry": {"coordinates":[-97.43657399999999,25.944904],"type":"Point"}
}