{
  "type": "Feature",
  "properties": {
    "iso:country":"US",
    "sg:address":"1407 W Walker St",
    "sg:city":"Breckenridge",
    "sg:classifiers":[
        {
            "category":"Shopping",
            "subcategory":"Florist",
            "type":"Retail Goods"
        }
    ],
    "sg:phone":"+1 254 559 1546",
    "sg:postcode":"76424",
    "sg:province":"TX",
    "wof:name":"Sage In Bloom Inc",
    "wof:placetype":"venue"
},
  "geometry": {"coordinates":[-98.921076,32.755292],"type":"Point"}
}