{
  "type": "Feature",
  "properties": {
    "iso:country":"US",
    "sg:address":"5402 Farmer St",
    "sg:city":"Houston",
    "sg:classifiers":[
        {
            "category":"Home & Garden",
            "subcategory":"Furniture",
            "type":"Retail Goods"
        }
    ],
    "sg:phone":"+1 281 893 7130",
    "sg:postcode":"77020",
    "sg:province":"TX",
    "wof:name":"Chair King Furniture",
    "wof:placetype":"venue"
},
  "geometry": {"coordinates":[-95.31647700000001,29.775627],"type":"Point"}
}