{
  "type": "Feature",
  "properties": {
    "iso:country":"US",
    "sg:address":"14930 S Baylan St",
    "sg:city":"Santa Fe",
    "sg:classifiers":[
        {
            "category":"Wholesale",
            "subcategory":"Vending Machines",
            "type":"Manufacturing & Wholesale Goods"
        }
    ],
    "sg:phone":"+1 409 925 5589",
    "sg:postcode":"77517",
    "sg:province":"TX",
    "sg:tags":[
        "operator"
    ],
    "wof:name":"V&S Enterprise",
    "wof:placetype":"venue"
},
  "geometry": {"coordinates":[-95.131771,29.363517],"type":"Point"}
}