{
  "type": "Feature",
  "properties": {
    "iso:country":"US",
    "sg:address":"26 Eton Green Cir",
    "sg:city":"San Antonio",
    "sg:classifiers":[
        {
            "category":"Professional",
            "type":"Services"
        }
    ],
    "sg:phone":"+1 210 698 0376",
    "sg:postcode":"78257",
    "sg:province":"TX",
    "wof:name":"Caminero Inc",
    "wof:placetype":"venue"
},
  "geometry": {"coordinates":[-98.611012,29.641641],"type":"Point"}
}