{
  "type": "Feature",
  "properties": {
    "iso:country":"US",
    "sg:address":"4000 Co Rd 511",
    "sg:city":"Brownsville",
    "sg:classifiers":[
        {
            "category":"Health Services",
            "subcategory":"Doctor",
            "type":"Services"
        }
    ],
    "sg:phone":"+1 956 831 8338",
    "sg:postcode":"78526",
    "sg:province":"TX",
    "sg:tags":[
        "clinic",
        "medical"
    ],
    "wof:name":"Su Clinica Familiar Inc",
    "wof:placetype":"venue"
},
  "geometry": {"coordinates":[-97.454871,25.991113],"type":"Point"}
}