{
  "type": "Feature",
  "properties": {
    "iso:country":"US",
    "sg:address":"2926 Silver Cedar Trl",
    "sg:city":"Katy",
    "sg:classifiers":[
        {
            "category":"Restaurant",
            "type":"Food & Drink"
        }
    ],
    "sg:phone":"+1 281 599 0230",
    "sg:postcode":"77449",
    "sg:province":"TX",
    "sg:tags":[
        "eating"
    ],
    "wof:name":"Ice Happens",
    "wof:placetype":"venue"
},
  "geometry": {"coordinates":[-95.729506,29.810753],"type":"Point"}
}