{
  "type": "Feature",
  "properties": {
    "iso:country":"US",
    "sg:address":"401 NE 31st St",
    "sg:city":"Grand Prairie",
    "sg:classifiers":[
        {
            "category":"Organizations",
            "subcategory":"Religious Organization",
            "type":"Services"
        }
    ],
    "sg:phone":"+1 972 262 6122",
    "sg:postcode":"75050",
    "sg:province":"TX",
    "sg:tags":[
        "church"
    ],
    "wof:name":"Bowles Memorial Baptist Church",
    "wof:placetype":"venue"
},
  "geometry": {"coordinates":[-96.95846899999999,32.756265],"type":"Point"}
}