{
  "type": "Feature",
  "properties": {
    "iso:country":"US",
    "sg:address":"5011 N McColl Rd",
    "sg:city":"Mcallen",
    "sg:classifiers":[
        {
            "category":"Banks & Credit Unions",
            "subcategory":"Bank",
            "type":"Services"
        }
    ],
    "sg:phone":"+1 956 631 7648",
    "sg:postcode":"78504",
    "sg:province":"TX",
    "sg:tags":[
        "mortgage",
        "loan",
        "broker",
        "real estate"
    ],
    "wof:name":"First Valley Mortgage Brokers",
    "wof:placetype":"venue"
},
  "geometry": {"coordinates":[-98.204806,26.248384],"type":"Point"}
}