{
  "type": "Feature",
  "properties": {
    "iso:country":"US",
    "sg:address":"2131 Richey St",
    "sg:city":"Pasadena",
    "sg:classifiers":[
        {
            "category":"Shopping",
            "subcategory":"Pawn Shop",
            "type":"Retail Goods"
        }
    ],
    "sg:phone":"+1 713 534 7296",
    "sg:postcode":"77502",
    "sg:province":"TX",
    "wof:name":"Circle Pawn Dot Com Inc",
    "wof:placetype":"venue"
},
  "geometry": {"coordinates":[-95.22682500000001,29.681313],"type":"Point"}
}