{
  "type": "Feature",
  "properties": {
    "iso:country":"US",
    "sg:address":"6803 US Hwy 277",
    "sg:city":"Abilene",
    "sg:classifiers":[
        {
            "category":"Manufacturing",
            "subcategory":"Watercraft",
            "type":"Manufacturing & Wholesale Goods"
        }
    ],
    "sg:phone":"+1 325 676 7777",
    "sg:postcode":"79601",
    "sg:province":"TX",
    "sg:tags":[
        "boat",
        "mfg"
    ],
    "wof:name":"Tige Boats Incorporated",
    "wof:placetype":"venue"
},
  "geometry": {"coordinates":[-99.756136,32.525076],"type":"Point"}
}