{
  "type": "Feature",
  "properties": {
    "iso:country":"US",
    "sg:address":"726 Connally St",
    "sg:city":"Sulphur Springs",
    "sg:classifiers":[
        {
            "category":"Shopping",
            "subcategory":"Used Merchandise",
            "type":"Retail Goods"
        }
    ],
    "sg:phone":"+1 903 439 4623",
    "sg:postcode":"75482",
    "sg:province":"TX",
    "wof:name":"Plaza Antiques",
    "wof:placetype":"venue"
},
  "geometry": {"coordinates":[-95.610652,33.138206],"type":"Point"}
}