{
  "type": "Feature",
  "properties": {
    "iso:country":"US",
    "sg:address":"917 W Ferguson Ave",
    "sg:city":"Pharr",
    "sg:classifiers":[
        {
            "category":"Bars & Pubs",
            "type":"Food & Drink"
        }
    ],
    "sg:phone":"+1 956 781 0730",
    "sg:postcode":"78577",
    "sg:province":"TX",
    "sg:tags":[
        "club",
        "drinking",
        "night"
    ],
    "wof:name":"Doc's Billiards",
    "wof:placetype":"venue"
},
  "geometry": {"coordinates":[-98.19482000000001,26.213367],"type":"Point"}
}