{
  "type": "Feature",
  "properties": {
    "iso:country":"US",
    "sg:address":"6 Butterfield Trail Blvd",
    "sg:city":"El Paso",
    "sg:classifiers":[
        {
            "category":"Manufacturing",
            "subcategory":"Metals",
            "type":"Manufacturing & Wholesale Goods"
        }
    ],
    "sg:phone":"+1 915 592 8948",
    "sg:postcode":"79906",
    "sg:province":"TX",
    "sg:tags":[
        "nonferrous",
        "mfg"
    ],
    "wof:name":"Motorola",
    "wof:placetype":"venue"
},
  "geometry": {"coordinates":[-106.401062,31.812641],"type":"Point"}
}