{
  "type": "Feature",
  "properties": {
    "iso:country":"US",
    "sg:address":"301 N Greenville Ave",
    "sg:city":"Allen",
    "sg:classifiers":[
        {
            "category":"Real Estate",
            "subcategory":"Real Estate Services",
            "type":"Services"
        },
        {
            "category":"Real Estate",
            "subcategory":"Real Estate Operator",
            "type":"Services"
        }
    ],
    "sg:phone":"+1 972 727 8412",
    "sg:postcode":"75002",
    "sg:province":"TX",
    "sg:tags":[
        "vacancy",
        "apartment",
        "rental",
        "listing"
    ],
    "wof:name":"Cottonwood Creek Apts Inc",
    "wof:placetype":"venue"
},
  "geometry": {"coordinates":[-96.65979,33.103527],"type":"Point"}
}