{
  "type": "Feature",
  "properties": {
    "iso:country":"US",
    "sg:address":"2237 S Cooper St",
    "sg:city":"Arlington",
    "sg:classifiers":[
        {
            "category":"Personal",
            "type":"Services"
        }
    ],
    "sg:phone":"+1 817 275 1710",
    "sg:postcode":"76013",
    "sg:province":"TX",
    "wof:name":"Joes Bodacious Body Art & Pie",
    "wof:placetype":"venue"
},
  "geometry": {"coordinates":[-97.116477,32.707684],"type":"Point"}
}