{
  "type": "Feature",
  "properties": {
    "iso:country":"US",
    "sg:address":"721 Hood St",
    "sg:city":"Waco",
    "sg:classifiers":[
        {
            "category":"Retail",
            "subcategory":"Auto Repair",
            "type":"Services"
        }
    ],
    "sg:phone":"+1 254 753 7772",
    "sg:postcode":"76704",
    "sg:province":"TX",
    "sg:tags":[
        "general"
    ],
    "wof:name":"James Garage",
    "wof:placetype":"venue"
},
  "geometry": {"coordinates":[-97.128753,31.572957],"type":"Point"}
}