{
  "type": "Feature",
  "properties": {
    "iso:country":"US",
    "sg:address":"439 N Garland Ave",
    "sg:city":"Garland",
    "sg:classifiers":[
        {
            "category":"Bakery",
            "type":"Food & Drink"
        }
    ],
    "sg:phone":"+1 972 272 2601",
    "sg:postcode":"75040",
    "sg:province":"TX",
    "wof:name":"Mrs Baird's Thrift Store",
    "wof:placetype":"venue"
},
  "geometry": {"coordinates":[-96.648399,32.9161],"type":"Point"}
}