{
  "type": "Feature",
  "properties": {
    "iso:country":"US",
    "sg:address":"3329 Indian St",
    "sg:city":"Vernon",
    "sg:classifiers":[
        {
            "category":"Building & Trades",
            "subcategory":"Construction",
            "type":"Services"
        }
    ],
    "sg:phone":"+1 940 553 3712",
    "sg:postcode":"76384",
    "sg:province":"TX",
    "sg:tags":[
        "paving",
        "contractor"
    ],
    "wof:name":"MAC Paving Inc",
    "wof:placetype":"venue"
},
  "geometry": {"coordinates":[-99.299813,34.145554],"type":"Point"}
}