{
  "type": "Feature",
  "properties": {
    "iso:country":"US",
    "sg:address":"7046 Callaghan Rd",
    "sg:city":"San Antonio",
    "sg:classifiers":[
        {
            "category":"Professional",
            "subcategory":"Business Services",
            "type":"Services"
        }
    ],
    "sg:phone":"+1 210 366 9397",
    "sg:postcode":"78229",
    "sg:province":"TX",
    "sg:tags":[
        "trade",
        "fair",
        "show"
    ],
    "wof:name":"Taste Of Mexico Inc",
    "wof:placetype":"venue"
},
  "geometry": {"coordinates":[-98.56530100000001,29.498027],"type":"Point"}
}