{
  "type": "Feature",
  "properties": {
    "iso:country":"US",
    "sg:address":"6505 Huckleberry Cove",
    "sg:city":"Austin",
    "sg:classifiers":[
        {
            "category":"Professional",
            "subcategory":"Engineering",
            "type":"Services"
        }
    ],
    "sg:phone":"+1 512 328 0205",
    "sg:postcode":"78746",
    "sg:province":"TX",
    "wof:name":"Frequency Engineering",
    "wof:placetype":"venue"
},
  "geometry": {"coordinates":[-97.844178,30.281104],"type":"Point"}
}