{
  "type": "Feature",
  "properties": {
    "iso:country":"US",
    "sg:address":"5001 Village Cir",
    "sg:city":"Dallas",
    "sg:classifiers":[
        {
            "category":"Insurance",
            "subcategory":"Insurance Agent",
            "type":"Services"
        }
    ],
    "sg:phone":"+1 972 386 5555",
    "sg:postcode":"75248",
    "sg:province":"TX",
    "sg:tags":[
        "consultant"
    ],
    "wof:name":"Employee Benefits Specialist",
    "wof:placetype":"venue"
},
  "geometry": {"coordinates":[-96.822631,32.977266],"type":"Point"}
}