{
  "type": "Feature",
  "properties": {
    "iso:country":"US",
    "sg:address":"24830 Butterwick Dr",
    "sg:city":"Spring",
    "sg:classifiers":[
        {
            "category":"Building & Trades",
            "subcategory":"Construction",
            "type":"Services"
        }
    ],
    "sg:phone":"+1 832 567 7725",
    "sg:postcode":"77389",
    "sg:province":"TX",
    "sg:tags":[
        "new",
        "home"
    ],
    "wof:name":"Papmor Inc",
    "wof:placetype":"venue"
},
  "geometry": {"coordinates":[-95.549285,30.121966],"type":"Point"}
}