{
  "type": "Feature",
  "properties": {
    "iso:country":"US",
    "sg:address":"1716 Tidwell Ln",
    "sg:city":"Houston",
    "sg:classifiers":[
        {
            "category":"Recreation",
            "type":"Entertainment"
        }
    ],
    "sg:phone":"+1 713 695 3078",
    "sg:postcode":"77093",
    "sg:province":"TX",
    "wof:name":"Manantial Billiards",
    "wof:placetype":"venue"
},
  "geometry": {"coordinates":[-95.358502,29.847852],"type":"Point"}
}