{
  "type": "Feature",
  "properties": {
    "iso:country":"US",
    "sg:address":"18111 Preston Rd",
    "sg:city":"Dallas",
    "sg:classifiers":[
        {
            "category":"Real Estate",
            "subcategory":"Real Estate Agent",
            "type":"Services"
        }
    ],
    "sg:phone":"+1 214 373 4800",
    "sg:postcode":"75252",
    "sg:province":"TX",
    "wof:name":"Ryan Family Ltd Partnership",
    "wof:placetype":"venue"
},
  "geometry": {"coordinates":[-96.79692799999999,32.999963],"type":"Point"}
}