{
  "type": "Feature",
  "properties": {
    "iso:country":"US",
    "sg:address":"103 E Pioneer Dr",
    "sg:city":"Irving",
    "sg:classifiers":[
        {
            "category":"Communications",
            "subcategory":"Radio Station",
            "type":"Services"
        },
        {
            "category":"Recreation",
            "type":"Entertainment"
        },
        {
            "category":"Communications",
            "type":"Services"
        },
        {
            "category":"Shopping",
            "subcategory":"Computers & Home Electronics",
            "type":"Retail Goods"
        }
    ],
    "sg:phone":"+1 972 579 9954",
    "sg:postcode":"75061",
    "sg:province":"TX",
    "sg:tags":[
        "sound",
        "television",
        "band",
        "system",
        "equipment",
        "radios-citizens",
        "store"
    ],
    "wof:name":"Central Communications & Electronics Inc",
    "wof:placetype":"venue"
},
  "geometry": {"coordinates":[-96.946253,32.818062],"type":"Point"}
}