{
  "type": "Feature",
  "properties": {
    "iso:country":"US",
    "sg:address":"3880 Irving Mall",
    "sg:city":"Irving",
    "sg:classifiers":[
        {
            "category":"Shopping",
            "subcategory":"Jewelry",
            "type":"Retail Goods"
        }
    ],
    "sg:phone":"+1 972 953 0319",
    "sg:postcode":"75062",
    "sg:province":"TX",
    "wof:name":"Rice Your World",
    "wof:placetype":"venue"
},
  "geometry": {"coordinates":[-96.99360299999999,32.840767],"type":"Point"}
}