{
  "type": "Feature",
  "properties": {
    "iso:country":"US",
    "sg:address":"7111 Harwin Dr",
    "sg:city":"Houston",
    "sg:classifiers":[
        {
            "category":"Health Services",
            "subcategory":"Doctor",
            "type":"Services"
        }
    ],
    "sg:phone":"+1 713 339 1476",
    "sg:postcode":"77036",
    "sg:province":"TX",
    "sg:tags":[
        "medical"
    ],
    "wof:name":"Sharpstown Medical Clinic",
    "wof:placetype":"venue"
},
  "geometry": {"coordinates":[-95.50909299999999,29.717903],"type":"Point"}
}