{
  "type": "Feature",
  "properties": {
    "iso:country":"US",
    "sg:address":"35 Lyreleaf Pl",
    "sg:city":"Spring",
    "sg:classifiers":[
        {
            "category":"Building & Trades",
            "subcategory":"Plumbing",
            "type":"Services"
        }
    ],
    "sg:phone":"+1 281 292 4982",
    "sg:postcode":"77382",
    "sg:province":"TX",
    "sg:tags":[
        "contractor"
    ],
    "wof:name":"EZ Sprinkler & Landscape Co",
    "wof:placetype":"venue"
},
  "geometry": {"coordinates":[-95.544669,30.214849],"type":"Point"}
}