{
  "type": "Feature",
  "properties": {
    "iso:country":"US",
    "sg:address":"N642 3249 Forest Ln",
    "sg:city":"Garland",
    "sg:classifiers":[
        {
            "category":"Food & Beverages",
            "subcategory":"Groceries & Convenience Stores",
            "type":"Retail Goods"
        }
    ],
    "sg:phone":"+1 972 276 7054",
    "sg:postcode":"75042",
    "sg:province":"TX",
    "wof:name":"Stop N Go Markets Of Texas Inc",
    "wof:placetype":"venue"
},
  "geometry": {"coordinates":[-96.67841799999999,32.909319],"type":"Point"}
}