{
  "type": "Feature",
  "properties": {
    "iso:country":"US",
    "sg:address":"2826 E Illinois Ave",
    "sg:city":"Dallas",
    "sg:classifiers":[
        {
            "category":"Health Services",
            "subcategory":"Doctor",
            "type":"Services"
        }
    ],
    "sg:phone":"+1 214 372 4621",
    "sg:postcode":"75216",
    "sg:province":"TX",
    "sg:tags":[
        "podiatrist"
    ],
    "wof:name":"Clark Ben Jr Podiatrst",
    "wof:placetype":"venue"
},
  "geometry": {"coordinates":[-96.7799,32.716499],"type":"Point"}
}