{
  "type": "Feature",
  "properties": {
    "iso:country":"US",
    "sg:address":"6535 Tioga Cir",
    "sg:city":"Dallas",
    "sg:classifiers":[
        {
            "category":"Shopping",
            "subcategory":"Florist",
            "type":"Retail Goods"
        }
    ],
    "sg:phone":"+1 972 225 9582",
    "sg:postcode":"75241",
    "sg:province":"TX",
    "wof:name":"Petals of Sentiment",
    "wof:placetype":"venue"
},
  "geometry": {"coordinates":[-96.761729,32.661585],"type":"Point"}
}