{
  "type": "Feature",
  "properties": {
    "iso:country":"US",
    "sg:address":"5831 100th St",
    "sg:city":"Lubbock",
    "sg:classifiers":[
        {
            "category":"Building & Trades",
            "subcategory":"Construction",
            "type":"Services"
        }
    ],
    "sg:phone":"+1 806 748 5574",
    "sg:postcode":"79424",
    "sg:province":"TX",
    "sg:tags":[
        "home",
        "builder"
    ],
    "wof:name":"David Rogers Homes",
    "wof:placetype":"venue"
},
  "geometry": {"coordinates":[-101.94108900000001,33.502941],"type":"Point"}
}