{
  "type": "Feature",
  "properties": {
    "iso:country":"US",
    "sg:address":"215 W Camp Wisdom Rd Ste 8",
    "sg:city":"Duncanville",
    "sg:classifiers":[
        {
            "category":"Shopping",
            "subcategory":"Crafts & Fabrics",
            "type":"Retail Goods"
        }
    ],
    "sg:phone":"+1 972 283 9007",
    "sg:postcode":"75116",
    "sg:province":"TX",
    "sg:tags":[
        "art"
    ],
    "wof:name":"Knick Knacks Craft & Antique Mall",
    "wof:placetype":"venue"
},
  "geometry": {"coordinates":[-96.91330000000001,32.6618],"type":"Point"}
}