{
  "type": "Feature",
  "properties": {
    "iso:country":"US",
    "sg:address":"2306 Green Meadow Dr",
    "sg:city":"Carrollton",
    "sg:classifiers":[
        {
            "category":"Professional",
            "subcategory":"Business Services",
            "type":"Services"
        }
    ],
    "sg:phone":"+1 972 245 6191",
    "sg:postcode":"75006",
    "sg:province":"TX",
    "wof:name":"Gardner Technology Solutions",
    "wof:placetype":"venue"
},
  "geometry": {"coordinates":[-96.895853,32.980203],"type":"Point"}
}