{
  "type": "Feature",
  "properties": {
    "iso:country":"US",
    "sg:address":"8118 Park Place Blvd",
    "sg:city":"Houston",
    "sg:classifiers":[
        {
            "category":"Banks & Credit Unions",
            "subcategory":"Bank",
            "type":"Services"
        }
    ],
    "sg:phone":"+1 713 649 4663",
    "sg:postcode":"77017",
    "sg:province":"TX",
    "sg:tags":[
        "loan",
        "real estate"
    ],
    "wof:name":"Mortgages Direct",
    "wof:placetype":"venue"
},
  "geometry": {"coordinates":[-95.276596,29.686017],"type":"Point"}
}