{
  "type": "Feature",
  "properties": {
    "iso:country":"US",
    "sg:address":"1510 Randolph St",
    "sg:city":"Carrollton",
    "sg:classifiers":[
        {
            "category":"Wholesale",
            "subcategory":"Electrical",
            "type":"Manufacturing & Wholesale Goods"
        }
    ],
    "sg:phone":"+1 972 245 2149",
    "sg:postcode":"75006",
    "sg:province":"TX",
    "sg:tags":[
        "alarm",
        "burglar",
        "system"
    ],
    "wof:name":"Diversified Alarm Systems",
    "wof:placetype":"venue"
},
  "geometry": {"coordinates":[-96.899311,32.94497],"type":"Point"}
}