{
  "type": "Feature",
  "properties": {
    "iso:country":"US",
    "sg:address":"2401 Belle Plain St",
    "sg:city":"Brownwood",
    "sg:classifiers":[
        {
            "category":"Building & Trades",
            "subcategory":"Construction",
            "type":"Services"
        },
        {
            "category":"Retail",
            "subcategory":"Auto Repair",
            "type":"Services"
        }
    ],
    "sg:phone":"+1 325 646 8696",
    "sg:postcode":"76801",
    "sg:province":"TX",
    "sg:tags":[
        "shop",
        "backhoe",
        "trenching",
        "automotive",
        "contractor",
        "underground"
    ],
    "wof:name":"Brown County Backhoe Service",
    "wof:placetype":"venue"
},
  "geometry": {"coordinates":[-98.99993600000001,31.740443],"type":"Point"}
}