{
  "type": "Feature",
  "properties": {
    "iso:country":"US",
    "sg:address":"11209 Metric Blvd",
    "sg:city":"Austin",
    "sg:classifiers":[
        {
            "category":"Government",
            "subcategory":"Office",
            "type":"Public Place"
        }
    ],
    "sg:phone":"+1 512 338 6506",
    "sg:postcode":"78758",
    "sg:province":"TX",
    "sg:tags":[
        "state",
        "program",
        "health"
    ],
    "wof:name":"Health Dept",
    "wof:placetype":"venue"
},
  "geometry": {"coordinates":[-97.70975799999999,30.389511],"type":"Point"}
}