{
  "type": "Feature",
  "properties": {
    "iso:country":"US",
    "sg:address":"600 Newland Dr",
    "sg:city":"Waco",
    "sg:classifiers":[
        {
            "category":"Building & Trades",
            "subcategory":"Plumbing",
            "type":"Services"
        }
    ],
    "sg:phone":"+1 254 662 5800",
    "sg:postcode":"76706",
    "sg:province":"TX",
    "sg:tags":[
        "contractor"
    ],
    "wof:name":"Extreme Plumbing",
    "wof:placetype":"venue"
},
  "geometry": {"coordinates":[-97.101786,31.4994],"type":"Point"}
}