{
  "type": "Feature",
  "properties": {
    "iso:country":"US",
    "sg:address":"1722 Elizabeth Ave",
    "sg:city":"Wichita Falls",
    "sg:classifiers":[
        {
            "category":"Real Estate",
            "subcategory":"Real Estate Operator",
            "type":"Services"
        }
    ],
    "sg:phone":"+1 940 322 9947",
    "sg:postcode":"76301",
    "sg:province":"TX",
    "sg:tags":[
        "building",
        "nonresidential"
    ],
    "wof:name":"Smith Properties",
    "wof:placetype":"venue"
},
  "geometry": {"coordinates":[-98.505578,33.899155],"type":"Point"}
}