{
  "type": "Feature",
  "properties": {
    "iso:country":"US",
    "sg:address":"465 Texla Rd",
    "sg:city":"Vidor",
    "sg:classifiers":[
        {
            "category":"Banks & Credit Unions",
            "subcategory":"Financial Services",
            "type":"Services"
        }
    ],
    "sg:phone":"+1 409 786 3606",
    "sg:postcode":"77662",
    "sg:province":"TX",
    "sg:tags":[
        "company",
        "holding"
    ],
    "wof:name":"Texla Road Enterprises LLC",
    "wof:placetype":"venue"
},
  "geometry": {"coordinates":[-93.99725599999999,30.234816],"type":"Point"}
}