{
  "type": "Feature",
  "properties": {
    "iso:country":"US",
    "sg:address":"404 W Bridge St",
    "sg:city":"Granbury",
    "sg:classifiers":[
        {
            "category":"Travel",
            "subcategory":"Hotels & Motels",
            "type":"Entertainment"
        }
    ],
    "sg:phone":"+1 817 579 7673",
    "sg:postcode":"76048",
    "sg:province":"TX",
    "sg:tags":[
        "operation"
    ],
    "wof:name":"Victorian Rose Bed & Breakfast",
    "wof:placetype":"venue"
},
  "geometry": {"coordinates":[-97.791999,32.44332],"type":"Point"}
}