{
  "type": "Feature",
  "properties": {
    "iso:country":"US",
    "sg:address":"11406 Rustic Rock Dr",
    "sg:city":"Austin",
    "sg:classifiers":[
        {
            "category":"Professional",
            "subcategory":"Management & Consulting",
            "type":"Services"
        }
    ],
    "sg:phone":"+1 512 249 9509",
    "sg:postcode":"78750",
    "sg:province":"TX",
    "sg:tags":[
        "consultant",
        "business"
    ],
    "wof:name":"Keith Bannon",
    "wof:placetype":"venue"
},
  "geometry": {"coordinates":[-97.78147300000001,30.430578],"type":"Point"}
}