{
  "type": "Feature",
  "properties": {
    "iso:country":"US",
    "sg:address":"1748 Central Blvd",
    "sg:city":"Brownsville",
    "sg:classifiers":[
        {
            "category":"Wholesale",
            "subcategory":"Sporting Goods",
            "type":"Manufacturing & Wholesale Goods"
        }
    ],
    "sg:phone":"+1 956 541 3344",
    "sg:postcode":"78520",
    "sg:province":"TX",
    "sg:tags":[
        "equipment",
        "pool",
        "swimming"
    ],
    "wof:name":"Clear Pool Co",
    "wof:placetype":"venue"
},
  "geometry": {"coordinates":[-97.510938,25.929519],"type":"Point"}
}