{
  "type": "Feature",
  "properties": {
    "iso:country":"US",
    "sg:address":"308 S Walters",
    "sg:city":"San Antonio",
    "sg:classifiers":[
        {
            "category":"Real Estate",
            "subcategory":"Real Estate Agent",
            "type":"Services"
        }
    ],
    "sg:phone":"+1 210 226 7030",
    "sg:postcode":"78203",
    "sg:province":"TX",
    "wof:name":"Heritage Group Realtors",
    "wof:placetype":"venue"
},
  "geometry": {"coordinates":[-98.452203,29.416805],"type":"Point"}
}