{
  "type": "Feature",
  "properties": {
    "iso:country":"US",
    "sg:address":"10055 Grogans Mill Rd",
    "sg:city":"Spring",
    "sg:classifiers":[
        {
            "category":"Banks & Credit Unions",
            "subcategory":"Bank",
            "type":"Services"
        }
    ],
    "sg:phone":"+1 281 419 2514",
    "sg:postcode":"77380",
    "sg:province":"TX",
    "sg:tags":[
        "federal"
    ],
    "wof:name":"Riverland Credit Union",
    "wof:placetype":"venue"
},
  "geometry": {"coordinates":[-95.47050400000001,30.159316],"type":"Point"}
}