{
  "type": "Feature",
  "properties": {
    "iso:country":"US",
    "sg:address":"2822 Goddard Pl",
    "sg:city":"Midland",
    "sg:classifiers":[
        {
            "category":"Professional",
            "subcategory":"Detective & Security Services",
            "type":"Services"
        }
    ],
    "sg:phone":"+1 432 699 4199",
    "sg:postcode":"79705",
    "sg:province":"TX",
    "sg:tags":[
        "car"
    ],
    "wof:name":"Ronnie H Benton Investigator",
    "wof:placetype":"venue"
},
  "geometry": {"coordinates":[-102.122151,32.030135],"type":"Point"}
}