{
  "type": "Feature",
  "properties": {
    "iso:country":"US",
    "sg:address":"22914 Walderford Dr",
    "sg:city":"Katy",
    "sg:classifiers":[
        {
            "category":"Building & Trades",
            "subcategory":"Construction",
            "type":"Services"
        }
    ],
    "sg:phone":"+1 281 392 4629",
    "sg:postcode":"77450",
    "sg:province":"TX",
    "sg:tags":[
        "house"
    ],
    "wof:name":"Space City Construction Nor",
    "wof:placetype":"venue"
},
  "geometry": {"coordinates":[-95.769215,29.782419],"type":"Point"}
}