{
  "type": "Feature",
  "properties": {
    "iso:country":"US",
    "sg:address":"3018 Guadalupe St",
    "sg:city":"San Antonio",
    "sg:classifiers":[
        {
            "category":"Restaurant",
            "type":"Food & Drink"
        }
    ],
    "sg:phone":"+1 210 436 4651",
    "sg:postcode":"78207",
    "sg:province":"TX",
    "sg:tags":[
        "eating"
    ],
    "wof:name":"LA Fuente Mexican Restaurant",
    "wof:placetype":"venue"
},
  "geometry": {"coordinates":[-98.534679,29.420142],"type":"Point"}
}