{
  "type": "Feature",
  "properties": {
    "iso:country":"US",
    "sg:address":"7670 Woodway Dr",
    "sg:city":"Houston",
    "sg:classifiers":[
        {
            "category":"Travel",
            "subcategory":"Travel Agent",
            "type":"Entertainment"
        }
    ],
    "sg:phone":"+1 713 781 1191",
    "sg:postcode":"77063",
    "sg:province":"TX",
    "sg:tags":[
        "agency",
        "bureau"
    ],
    "wof:name":"ADP Travel",
    "wof:placetype":"venue"
},
  "geometry": {"coordinates":[-95.50287400000001,29.752429],"type":"Point"}
}