{
  "type": "Feature",
  "properties": {
    "iso:country":"US",
    "sg:address":"515 N Sam Houston Pkwy E # 622",
    "sg:city":"Houston",
    "sg:classifiers":[
        {
            "category":"Insurance",
            "subcategory":"Insurance Agent",
            "type":"Services"
        },
        {
            "category":"Insurance",
            "subcategory":"Hazard Insurance",
            "type":"Services"
        }
    ],
    "sg:phone":"+1 281 847 8422",
    "sg:postcode":"77060",
    "sg:province":"TX",
    "sg:tags":[
        "consultant",
        "analyst"
    ],
    "wof:name":"First Financial Administrators Inc",
    "wof:placetype":"venue"
},
  "geometry": {"coordinates":[-95.39220299999999,29.938959],"type":"Point"}
}