{
  "type": "Feature",
  "properties": {
    "iso:country":"US",
    "sg:address":"1808 N Cage Blvd",
    "sg:city":"Pharr",
    "sg:classifiers":[
        {
            "category":"Food & Beverages",
            "subcategory":"Groceries & Convenience Stores",
            "type":"Retail Goods"
        }
    ],
    "sg:phone":"+1 956 702 2110",
    "sg:postcode":"78577",
    "sg:province":"TX",
    "wof:name":"Suby's Food Mart",
    "wof:placetype":"venue"
},
  "geometry": {"coordinates":[-98.181494,26.210677],"type":"Point"}
}