{
  "type": "Feature",
  "properties": {
    "iso:country":"US",
    "sg:address":"20519 Rhodes Rd",
    "sg:city":"Spring",
    "sg:classifiers":[
        {
            "category":"Wholesale",
            "subcategory":"Plants",
            "type":"Manufacturing & Wholesale Goods"
        }
    ],
    "sg:phone":"+1 281 350 0840",
    "sg:postcode":"77388",
    "sg:province":"TX",
    "sg:tags":[
        "nursery",
        "tree",
        "stock"
    ],
    "wof:name":"Morning Star Greenhouses Inc",
    "wof:placetype":"venue"
},
  "geometry": {"coordinates":[-95.49690099999999,30.06553],"type":"Point"}
}