{
  "type": "Feature",
  "properties": {
    "iso:country":"US",
    "sg:address":"712 S Saginaw Blvd",
    "sg:city":"Fort Worth",
    "sg:classifiers":[
        {
            "category":"Personal",
            "subcategory":"Barber",
            "type":"Services"
        }
    ],
    "sg:phone":"+1 817 232 8811",
    "sg:postcode":"76179",
    "sg:province":"TX",
    "sg:tags":[
        "shop"
    ],
    "wof:name":"Saginaw Barber Shop",
    "wof:placetype":"venue"
},
  "geometry": {"coordinates":[-97.360822,32.853033],"type":"Point"}
}