{
  "type": "Feature",
  "properties": {
    "iso:country":"US",
    "sg:address":"2600 Longhorn Blvd",
    "sg:city":"Austin",
    "sg:classifiers":[
        {
            "category":"Home & Garden",
            "subcategory":"Building Materials",
            "type":"Retail Goods"
        }
    ],
    "sg:phone":"+1 512 339 6699",
    "sg:postcode":"78758",
    "sg:province":"TX",
    "wof:name":"Jones-Blair Paint & Dctg Ctr",
    "wof:placetype":"venue"
},
  "geometry": {"coordinates":[-97.726472,30.380788],"type":"Point"}
}