{
  "type": "Feature",
  "properties": {
    "iso:country":"US",
    "sg:address":"1214 Chesterton Dr",
    "sg:city":"Richardson",
    "sg:classifiers":[
        {
            "category":"Professional",
            "subcategory":"Business Services",
            "type":"Services"
        }
    ],
    "sg:phone":"+1 972 231 5432",
    "sg:postcode":"75080",
    "sg:province":"TX",
    "wof:name":"Surgical Technologies Inc",
    "wof:placetype":"venue"
},
  "geometry": {"coordinates":[-96.76311,32.975224],"type":"Point"}
}