{
  "type": "Feature",
  "properties": {
    "iso:country":"US",
    "sg:address":"12222 J Rendon Rd",
    "sg:city":"Burleson",
    "sg:classifiers":[
        {
            "category":"Food & Beverages",
            "subcategory":"Bakery",
            "type":"Retail Goods"
        }
    ],
    "sg:phone":"+1 817 483 6555",
    "sg:postcode":"76028",
    "sg:province":"TX",
    "wof:name":"Pate Donuts",
    "wof:placetype":"venue"
},
  "geometry": {"coordinates":[-97.252651,32.579663],"type":"Point"}
}