{
  "type": "Feature",
  "properties": {
    "iso:country":"US",
    "sg:address":"1620 Hunter Dr",
    "sg:city":"El Paso",
    "sg:classifiers":[
        {
            "category":"Professional",
            "type":"Services"
        }
    ],
    "sg:phone":"+1 915 594 9899",
    "sg:postcode":"79915",
    "sg:province":"TX",
    "sg:tags":[
        "establishment"
    ],
    "wof:name":"Heartland Payment Systems",
    "wof:placetype":"venue"
},
  "geometry": {"coordinates":[-106.365261,31.761598],"type":"Point"}
}