{
  "type": "Feature",
  "properties": {
    "iso:country":"US",
    "sg:address":"1001 Rockledge Dr",
    "sg:city":"Garland",
    "sg:classifiers":[
        {
            "category":"Wholesale",
            "subcategory":"Electrical",
            "type":"Manufacturing & Wholesale Goods"
        }
    ],
    "sg:phone":"+1 972 270 0892",
    "sg:postcode":"75043",
    "sg:province":"TX",
    "sg:tags":[
        "electronic"
    ],
    "wof:name":"Ashley O & Associates",
    "wof:placetype":"venue"
},
  "geometry": {"coordinates":[-96.640171,32.851957],"type":"Point"}
}