{
  "type": "Feature",
  "properties": {
    "iso:country":"US",
    "sg:address":"5411 Leeway Dr",
    "sg:city":"Dallas",
    "sg:classifiers":[
        {
            "category":"Professional",
            "subcategory":"Business Services",
            "type":"Services"
        }
    ],
    "sg:phone":"+1 972 283 2066",
    "sg:postcode":"75236",
    "sg:province":"TX",
    "sg:tags":[
        "interior",
        "consultant",
        "design",
        "decorator"
    ],
    "wof:name":"Trinkets Interior Decor Spec",
    "wof:placetype":"venue"
},
  "geometry": {"coordinates":[-96.930758,32.679236],"type":"Point"}
}