{
  "type": "Feature",
  "properties": {
    "iso:country":"US",
    "sg:address":"5204 Fallworth Ct",
    "sg:city":"Fort Worth",
    "sg:classifiers":[
        {
            "category":"Shopping",
            "type":"Retail Goods"
        },
        {
            "category":"Shopping",
            "subcategory":"Gifts & Souvenirs",
            "type":"Retail Goods"
        }
    ],
    "sg:phone":"+1 817 858 1191",
    "sg:postcode":"76133",
    "sg:province":"TX",
    "sg:tags":[
        "product",
        "wood"
    ],
    "wof:name":"Ceramic Gifts Wood Designs",
    "wof:placetype":"venue"
},
  "geometry": {"coordinates":[-97.405396,32.645939],"type":"Point"}
}