{
  "type": "Feature",
  "properties": {
    "iso:country":"US",
    "sg:address":"708 Frontage Rd",
    "sg:city":"Idalou",
    "sg:classifiers":[
        {
            "category":"Food & Beverages",
            "subcategory":"Groceries & Convenience Stores",
            "type":"Retail Goods"
        }
    ],
    "sg:phone":"+1 806 892 3924",
    "sg:postcode":"79329",
    "sg:province":"TX",
    "wof:name":"Rip Griffins",
    "wof:placetype":"venue"
},
  "geometry": {"coordinates":[-101.69027199999999,33.663914],"type":"Point"}
}