{
  "type": "Feature",
  "properties": {
    "iso:country":"US",
    "sg:address":"1605 Mistletoe Ln",
    "sg:city":"Arlington",
    "sg:classifiers":[
        {
            "category":"Food & Beverages",
            "subcategory":"Specialty",
            "type":"Retail Goods"
        }
    ],
    "sg:phone":"+1 817 861 0077",
    "sg:postcode":"76013",
    "sg:province":"TX",
    "wof:name":"Advanced Herbal Products",
    "wof:placetype":"venue"
},
  "geometry": {"coordinates":[-97.15549799999999,32.720291],"type":"Point"}
}