{
  "type": "Feature",
  "properties": {
    "iso:country":"US",
    "sg:address":"1220 Fm 1092 Rd",
    "sg:city":"Missouri City",
    "sg:classifiers":[
        {
            "category":"Education",
            "subcategory":"Preschool",
            "type":"Public Place"
        },
        {
            "category":"Education",
            "subcategory":"School",
            "type":"Public Place"
        }
    ],
    "sg:phone":"+1 281 499 2581",
    "sg:postcode":"77459",
    "sg:province":"TX",
    "sg:tags":[
        "elementary"
    ],
    "wof:name":"First Methodist Day School",
    "wof:placetype":"venue"
},
  "geometry": {"coordinates":[-95.564352,29.601664],"type":"Point"}
}