{
  "type": "Feature",
  "properties": {
    "iso:country":"US",
    "sg:address":"3105 Ira E Woods Ave",
    "sg:city":"Grapevine",
    "sg:classifiers":[
        {
            "category":"Sports & Exercise",
            "subcategory":"Gym",
            "type":"Entertainment"
        }
    ],
    "sg:phone":"+1 817 329 2274",
    "sg:postcode":"76051",
    "sg:province":"TX",
    "sg:tags":[
        "personal",
        "fitness",
        "physical",
        "facility"
    ],
    "wof:name":"Better Bodies Texas",
    "wof:placetype":"venue"
},
  "geometry": {"coordinates":[-97.11906999999999,32.919131],"type":"Point"}
}