{
  "type": "Feature",
  "properties": {
    "iso:country":"US",
    "sg:address":"5927 FM 3233",
    "sg:city":"La Grange",
    "sg:classifiers":[
        {
            "category":"Building & Trades",
            "subcategory":"Construction",
            "type":"Services"
        }
    ],
    "sg:phone":"+1 979 247 4583",
    "sg:postcode":"78945",
    "sg:province":"TX",
    "sg:tags":[
        "contractor"
    ],
    "wof:name":"Kana Bros House Leveling & Mvg",
    "wof:placetype":"venue"
},
  "geometry": {"coordinates":[-96.85541000000001,29.84075],"type":"Point"}
}