{
  "type": "Feature",
  "properties": {
    "iso:country":"US",
    "sg:address":"7575 McCart Ave",
    "sg:city":"Fort Worth",
    "sg:classifiers":[
        {
            "category":"Retail",
            "subcategory":"Laundry & Dry Cleaning",
            "type":"Services"
        }
    ],
    "sg:phone":"+1 817 361 9240",
    "sg:postcode":"76123",
    "sg:province":"TX",
    "sg:tags":[
        "drycleaning",
        "plant"
    ],
    "wof:name":"Super Dry Clean City",
    "wof:placetype":"venue"
},
  "geometry": {"coordinates":[-97.369844,32.632627],"type":"Point"}
}