{
  "type": "Feature",
  "properties": {
    "iso:country":"US",
    "sg:address":"905 Ave T",
    "sg:city":"Grand Prairie",
    "sg:classifiers":[
        {
            "category":"Manufacturing",
            "subcategory":"Chemicals & Compounds",
            "type":"Manufacturing & Wholesale Goods"
        }
    ],
    "sg:phone":"+1 972 623 5680",
    "sg:postcode":"75050",
    "sg:province":"TX",
    "sg:tags":[
        "product",
        "mfg"
    ],
    "wof:name":"Kwal-Howells Inc",
    "wof:placetype":"venue"
},
  "geometry": {"coordinates":[-97.04664099999999,32.790292],"type":"Point"}
}