{
  "type": "Feature",
  "properties": {
    "iso:country":"US",
    "sg:address":"1108 Park Dr",
    "sg:city":"Denison",
    "sg:classifiers":[
        {
            "category":"Professional",
            "type":"Services"
        }
    ],
    "sg:phone":"+1 903 465 6013",
    "sg:postcode":"75020",
    "sg:province":"TX",
    "wof:name":"James R Rice",
    "wof:placetype":"venue"
},
  "geometry": {"coordinates":[-96.576148,33.768088],"type":"Point"}
}