{
  "type": "Feature",
  "properties": {
    "iso:country":"US",
    "sg:address":"705 8th St",
    "sg:city":"Wichita Falls",
    "sg:classifiers":[
        {
            "category":"Professional",
            "type":"Services"
        }
    ],
    "sg:phone":"+1 940 322 5085",
    "sg:postcode":"76301",
    "sg:province":"TX",
    "sg:tags":[
        "establishment"
    ],
    "wof:name":"Adacom Marketing",
    "wof:placetype":"venue"
},
  "geometry": {"coordinates":[-98.492001,33.911873],"type":"Point"}
}