{
  "type": "Feature",
  "properties": {
    "iso:country":"US",
    "sg:address":"517 SW 48th Ave",
    "sg:city":"Amarillo",
    "sg:classifiers":[
        {
            "category":"Real Estate",
            "subcategory":"Real Estate Services",
            "type":"Services"
        },
        {
            "category":"Real Estate",
            "subcategory":"Real Estate Agent",
            "type":"Services"
        }
    ],
    "sg:phone":"+1 806 331 6353",
    "sg:postcode":"79110",
    "sg:province":"TX",
    "sg:tags":[
        "buyer",
        "management",
        "broker"
    ],
    "wof:name":"Cpi Properties",
    "wof:placetype":"venue"
},
  "geometry": {"coordinates":[-101.845555,35.160575],"type":"Point"}
}