{
  "type": "Feature",
  "properties": {
    "iso:country":"US",
    "sg:address":"415 Center St",
    "sg:city":"Beaumont",
    "sg:classifiers":[
        {
            "category":"Professional",
            "subcategory":"Engineering",
            "type":"Services"
        }
    ],
    "sg:phone":"+1 409 833 2407",
    "sg:postcode":"77701",
    "sg:province":"TX",
    "sg:tags":[
        "engineer"
    ],
    "wof:name":"Beaumont Engineering Co",
    "wof:placetype":"venue"
},
  "geometry": {"coordinates":[-94.107282,30.085887],"type":"Point"}
}