{
  "type": "Feature",
  "properties": {
    "iso:country":"US",
    "sg:address":"1404 Arlington St",
    "sg:city":"Houston",
    "sg:classifiers":[
        {
            "category":"Professional",
            "subcategory":"Lawyer & Legal Services",
            "type":"Services"
        }
    ],
    "sg:phone":"+1 713 224 3300",
    "sg:postcode":"77008",
    "sg:province":"TX",
    "wof:name":"Magner Robert J Atty",
    "wof:placetype":"venue"
},
  "geometry": {"coordinates":[-95.394203,29.796499],"type":"Point"}
}