{
  "type": "Feature",
  "properties": {
    "iso:country":"US",
    "sg:address":"5000 E Cesar Chavez St",
    "sg:city":"Austin",
    "sg:classifiers":[
        {
            "category":"Building & Trades",
            "subcategory":"Electrical",
            "type":"Services"
        }
    ],
    "sg:phone":"+1 512 386 7700",
    "sg:postcode":"78702",
    "sg:province":"TX",
    "sg:tags":[
        "electric",
        "contractor"
    ],
    "wof:name":"Maldonado's Electrical Rbldrs",
    "wof:placetype":"venue"
},
  "geometry": {"coordinates":[-97.698572,30.251389],"type":"Point"}
}