{
  "type": "Feature",
  "properties": {
    "iso:country":"US",
    "sg:address":"4646 Corona Dr",
    "sg:city":"Corpus Christi",
    "sg:classifiers":[
        {
            "category":"Health Services",
            "subcategory":"Chiropractor",
            "type":"Services"
        }
    ],
    "sg:phone":"+1 361 225 2077",
    "sg:postcode":"78411",
    "sg:province":"TX",
    "wof:name":"Adame Chropractic Wellness Ctr",
    "wof:placetype":"venue"
},
  "geometry": {"coordinates":[-97.389088,27.713844],"type":"Point"}
}