{
  "type": "Feature",
  "properties": {
    "iso:country":"US",
    "sg:address":"1325 Pennsylvania Ave",
    "sg:city":"Fort Worth",
    "sg:classifiers":[
        {
            "category":"Health Services",
            "subcategory":"Doctor",
            "type":"Services"
        }
    ],
    "sg:phone":"+1 817 335 4240",
    "sg:postcode":"76104",
    "sg:province":"TX",
    "sg:tags":[
        "physician",
        "surgeon"
    ],
    "wof:name":"Urology Associates",
    "wof:placetype":"venue"
},
  "geometry": {"coordinates":[-97.340057,32.73841],"type":"Point"}
}