{
  "type": "Feature",
  "properties": {
    "iso:country":"US",
    "sg:address":"501 Minter St",
    "sg:city":"Uvalde",
    "sg:classifiers":[
        {
            "category":"Professional",
            "type":"Services"
        }
    ],
    "sg:phone":"+1 830 278 8783",
    "sg:postcode":"78801",
    "sg:province":"TX",
    "wof:name":"Uvaldeans Against Lawsuit",
    "wof:placetype":"venue"
},
  "geometry": {"coordinates":[-99.79912299999999,29.220989],"type":"Point"}
}