{
  "type": "Feature",
  "properties": {
    "iso:country":"US",
    "sg:address":"2102 Brooks St",
    "sg:city":"Houston",
    "sg:classifiers":[
        {
            "category":"Professional",
            "subcategory":"Computer Services",
            "type":"Services"
        }
    ],
    "sg:phone":"+1 713 523 9310",
    "sg:postcode":"77026",
    "sg:province":"TX",
    "sg:tags":[
        "design",
        "system",
        "related"
    ],
    "wof:name":"Anitel Technologies Inc",
    "wof:placetype":"venue"
},
  "geometry": {"coordinates":[-95.34748999999999,29.775495],"type":"Point"}
}