{
  "type": "Feature",
  "properties": {
    "iso:country":"US",
    "sg:address":"12621 B Research Blvd",
    "sg:city":"Austin",
    "sg:classifiers":[
        {
            "category":"Autos & Motor Vehicles",
            "subcategory":"Automobile Sales",
            "type":"Retail Goods"
        }
    ],
    "sg:phone":"+1 512 331 1355",
    "sg:postcode":"78759",
    "sg:province":"TX",
    "sg:tags":[
        "automotive"
    ],
    "sg:website":"www.crescentengines.com",
    "wof:name":"Crescent Automotive",
    "wof:placetype":"venue"
},
  "geometry": {"coordinates":[-97.763577,30.432016],"type":"Point"}
}