{
  "type": "Feature",
  "properties": {
    "iso:country":"US",
    "sg:address":"13241 Meadow Creek Ln",
    "sg:city":"Conroe",
    "sg:classifiers":[
        {
            "category":"Place Of Worship",
            "type":"Public Place"
        }
    ],
    "sg:phone":"+1 936 441 0436",
    "sg:postcode":"77302",
    "sg:province":"TX",
    "sg:tags":[
        "church"
    ],
    "wof:name":"English Fellowship Church",
    "wof:placetype":"venue"
},
  "geometry": {"coordinates":[-95.44305900000001,30.264724],"type":"Point"}
}