{
  "type": "Feature",
  "properties": {
    "iso:country":"US",
    "sg:address":"706 Farmer St",
    "sg:city":"Lufkin",
    "sg:classifiers":[
        {
            "category":"Place Of Worship",
            "subcategory":"Church",
            "type":"Public Place"
        },
        {
            "category":"Place Of Worship",
            "type":"Public Place"
        }
    ],
    "sg:phone":"+1 936 875 2491",
    "sg:postcode":"75904",
    "sg:province":"TX",
    "sg:tags":[
        "churches-baptist-general",
        "churches-baptist"
    ],
    "wof:name":"Bethlehem Methodist Parsonage",
    "wof:placetype":"venue"
},
  "geometry": {"coordinates":[-94.728426,31.420191],"type":"Point"}
}