{
  "type": "Feature",
  "properties": {
    "iso:country":"US",
    "sg:address":"1009 Westcrest",
    "sg:city":"Floresville",
    "sg:classifiers":[
        {
            "category":"Building & Trades",
            "subcategory":"Construction",
            "type":"Services"
        }
    ],
    "sg:phone":"+1 210 475 0228",
    "sg:postcode":"78114",
    "sg:province":"TX",
    "sg:tags":[
        "contractor"
    ],
    "wof:name":"Metro General Contracting",
    "wof:placetype":"venue"
},
  "geometry": {"coordinates":[-98.17377,29.149034],"type":"Point"}
}