{
  "type": "Feature",
  "properties": {
    "iso:country":"US",
    "sg:address":"6670 Radley Dr",
    "sg:city":"Spring",
    "sg:classifiers":[
        {
            "category":"Food & Beverages",
            "subcategory":"Groceries & Convenience Stores",
            "type":"Retail Goods"
        }
    ],
    "sg:phone":"+1 281 251 1902",
    "sg:postcode":"77379",
    "sg:province":"TX",
    "wof:name":"Gourmet Pantry",
    "wof:placetype":"venue"
},
  "geometry": {"coordinates":[-95.512248,30.018769],"type":"Point"}
}