{
  "type": "Feature",
  "properties": {
    "iso:country":"US",
    "sg:address":"4324 Arcady Ave",
    "sg:city":"Dallas",
    "sg:classifiers":[
        {
            "category":"Shopping",
            "subcategory":"Clothing, Apparel, & Fashions",
            "type":"Retail Goods"
        }
    ],
    "sg:phone":"+1 214 219 5700",
    "sg:postcode":"75205",
    "sg:province":"TX",
    "sg:tags":[
        "designer"
    ],
    "wof:name":"Pickens Design",
    "wof:placetype":"venue"
},
  "geometry": {"coordinates":[-96.80790399999999,32.82812],"type":"Point"}
}