{
  "type": "Feature",
  "properties": {
    "iso:country":"US",
    "sg:address":"7002 Foxport Ln",
    "sg:city":"Humble",
    "sg:classifiers":[
        {
            "category":"Building & Trades",
            "subcategory":"Plumbing",
            "type":"Services"
        }
    ],
    "sg:phone":"+1 281 446 8390",
    "sg:postcode":"77338",
    "sg:province":"TX",
    "sg:tags":[
        "contractor"
    ],
    "wof:name":"Bc Air",
    "wof:placetype":"venue"
},
  "geometry": {"coordinates":[-95.317083,30.01736],"type":"Point"}
}