{
  "type": "Feature",
  "properties": {
    "iso:country":"US",
    "sg:address":"139 E Hopkins St",
    "sg:city":"San Marcos",
    "sg:classifiers":[
        {
            "category":"Building & Trades",
            "subcategory":"Construction",
            "type":"Services"
        }
    ],
    "sg:phone":"+1 512 396 2474",
    "sg:postcode":"78666",
    "sg:province":"TX",
    "sg:tags":[
        "concrete",
        "contractor"
    ],
    "wof:name":"Wilkerson Concrete",
    "wof:placetype":"venue"
},
  "geometry": {"coordinates":[-97.94057599999999,29.883208],"type":"Point"}
}