{
  "type": "Feature",
  "properties": {
    "iso:country":"US",
    "sg:address":"3313 S University Dr",
    "sg:city":"Fort Worth",
    "sg:classifiers":[
        {
            "category":"Shopping",
            "subcategory":"Florist",
            "type":"Retail Goods"
        }
    ],
    "sg:phone":"+1 817 882 9700",
    "sg:postcode":"76109",
    "sg:province":"TX",
    "wof:name":"Thistles & Tumbleweed",
    "wof:placetype":"venue"
},
  "geometry": {"coordinates":[-97.360461,32.699779],"type":"Point"}
}