{
  "type": "Feature",
  "properties": {
    "iso:country":"US",
    "sg:address":"2421 N Main St",
    "sg:city":"Belton",
    "sg:classifiers":[
        {
            "category":"Professional",
            "subcategory":"Advertising",
            "type":"Services"
        }
    ],
    "sg:phone":"+1 254 933 8300",
    "sg:postcode":"76513",
    "sg:province":"TX",
    "sg:tags":[
        "mailing",
        "shipping"
    ],
    "wof:name":"Mail Store",
    "wof:placetype":"venue"
},
  "geometry": {"coordinates":[-97.457324,31.078952],"type":"Point"}
}