{
  "type": "Feature",
  "properties": {
    "iso:country":"US",
    "sg:address":"902 SW Military Dr",
    "sg:city":"San Antonio",
    "sg:classifiers":[
        {
            "category":"Shopping",
            "subcategory":"Gifts & Souvenirs",
            "type":"Retail Goods"
        }
    ],
    "sg:phone":"+1 210 924 6056",
    "sg:postcode":"78221",
    "sg:province":"TX",
    "sg:tags":[
        "party",
        "supply"
    ],
    "wof:name":"Party Mart",
    "wof:placetype":"venue"
},
  "geometry": {"coordinates":[-98.50738200000001,29.356604],"type":"Point"}
}