{
  "type": "Feature",
  "properties": {
    "iso:country":"US",
    "sg:address":"1106 N Hwy 360",
    "sg:city":"Grand Prairie",
    "sg:classifiers":[
        {
            "category":"Freight",
            "type":"Transportation"
        }
    ],
    "sg:phone":"+1 972 641 9977",
    "sg:postcode":"75050",
    "sg:province":"TX",
    "sg:tags":[
        "mover"
    ],
    "wof:name":"All Day Fire Fighter Moving",
    "wof:placetype":"venue"
},
  "geometry": {"coordinates":[-97.062602,32.767195],"type":"Point"}
}