{
  "type": "Feature",
  "properties": {
    "iso:country":"US",
    "sg:address":"31164 Co Rd 106",
    "sg:city":"Rio Hondo",
    "sg:classifiers":[
        {
            "category":"Food & Beverages",
            "subcategory":"Groceries & Convenience Stores",
            "type":"Retail Goods"
        }
    ],
    "sg:phone":"+1 956 361 2169",
    "sg:postcode":"78583",
    "sg:province":"TX",
    "wof:name":"J & M Grocery",
    "wof:placetype":"venue"
},
  "geometry": {"coordinates":[-97.521603,26.224981],"type":"Point"}
}