{
  "type": "Feature",
  "properties": {
    "iso:country":"US",
    "sg:address":"12909 Jupiter Rd",
    "sg:city":"Dallas",
    "sg:classifiers":[
        {
            "category":"Food & Beverages",
            "subcategory":"Groceries & Convenience Stores",
            "type":"Retail Goods"
        }
    ],
    "sg:phone":"+1 214 343 3541",
    "sg:postcode":"75238",
    "sg:province":"TX",
    "wof:name":"US One Stop",
    "wof:placetype":"venue"
},
  "geometry": {"coordinates":[-96.683296,32.8731],"type":"Point"}
}