{
  "type": "Feature",
  "properties": {
    "iso:country":"US",
    "sg:address":"1931 Humble Place Dr",
    "sg:city":"Humble",
    "sg:classifiers":[
        {
            "category":"Manufacturing",
            "subcategory":"Lumber",
            "type":"Manufacturing & Wholesale Goods"
        }
    ],
    "sg:phone":"+1 281 540 8858",
    "sg:postcode":"77338",
    "sg:province":"TX",
    "sg:tags":[
        "forester"
    ],
    "wof:name":"Forest Resources",
    "wof:placetype":"venue"
},
  "geometry": {"coordinates":[-95.24596099999999,29.996791],"type":"Point"}
}