{
  "type": "Feature",
  "properties": {
    "iso:country":"US",
    "sg:address":"1703 Creekway Dr",
    "sg:city":"Lewisville",
    "sg:classifiers":[
        {
            "category":"Wholesale",
            "subcategory":"Stationery",
            "type":"Manufacturing & Wholesale Goods"
        }
    ],
    "sg:phone":"+1 972 219 3865",
    "sg:postcode":"75067",
    "sg:province":"TX",
    "sg:tags":[
        "supply"
    ],
    "wof:name":"Bear A Bull Forms",
    "wof:placetype":"venue"
},
  "geometry": {"coordinates":[-97.03144500000001,33.024525],"type":"Point"}
}