{
  "type": "Feature",
  "properties": {
    "iso:country":"US",
    "sg:address":"2121 Sam Houston Pkwy",
    "sg:city":"Houston",
    "sg:classifiers":[
        {
            "category":"Shopping",
            "subcategory":"Discount & Variety Stores",
            "type":"Retail Goods"
        }
    ],
    "sg:phone":"+1 713 468 2608",
    "sg:postcode":"77060",
    "sg:province":"TX",
    "sg:tags":[
        "merchandise",
        "general"
    ],
    "wof:name":"Junk General Store",
    "wof:placetype":"venue"
},
  "geometry": {"coordinates":[-95.35428,29.938618],"type":"Point"}
}