{
  "type": "Feature",
  "properties": {
    "iso:country":"US",
    "sg:address":"4220 S Flores St",
    "sg:city":"San Antonio",
    "sg:classifiers":[
        {
            "category":"Wholesale",
            "subcategory":"Machinery & Supplies",
            "type":"Manufacturing & Wholesale Goods"
        }
    ],
    "sg:phone":"+1 210 534 1411",
    "sg:postcode":"78214",
    "sg:province":"TX",
    "sg:tags":[
        "equipment",
        "establishment",
        "business"
    ],
    "wof:name":"Bexar Fire & Safety Eqp Co",
    "wof:placetype":"venue"
},
  "geometry": {"coordinates":[-98.50198899999999,29.382994],"type":"Point"}
}