{
  "type": "Feature",
  "properties": {
    "iso:country":"US",
    "sg:address":"805 E Jackson St",
    "sg:city":"El Campo",
    "sg:classifiers":[
        {
            "category":"Restaurant",
            "type":"Food & Drink"
        }
    ],
    "sg:menulink":"http://www.allmenus.com/tx/el-campo/14935-los-cucos/menu/",
    "sg:phone":"+1 979 578 0612",
    "sg:postcode":"77437",
    "sg:province":"TX",
    "sg:tags":[
        "american",
        "mexican",
        "tex-mex"
    ],
    "wof:name":"Los Cucos",
    "wof:placetype":"venue"
},
  "geometry": {"coordinates":[-96.262142,29.201513],"type":"Point"}
}