{
  "type": "Feature",
  "properties": {
    "iso:country":"US",
    "sg:address":"8230 Galler Rd",
    "sg:city":"Richmond",
    "sg:classifiers":[
        {
            "category":"Professional",
            "subcategory":"Business Services",
            "type":"Services"
        }
    ],
    "sg:phone":"+1 979 793 6522",
    "sg:postcode":"77469",
    "sg:province":"TX",
    "wof:name":"Hdt Real Estate Inspection",
    "wof:placetype":"venue"
},
  "geometry": {"coordinates":[-95.79159799999999,29.461241],"type":"Point"}
}