{
  "type": "Feature",
  "properties": {
    "iso:country":"US",
    "sg:address":"1865 Little York Rd",
    "sg:city":"Houston",
    "sg:classifiers":[
        {
            "category":"Retail",
            "subcategory":"Repair Shop",
            "type":"Services"
        }
    ],
    "sg:phone":"+1 832 200 3894",
    "sg:postcode":"77093",
    "sg:province":"TX",
    "sg:tags":[
        "lock",
        "locksmith"
    ],
    "wof:name":"007 Locksmith",
    "wof:placetype":"venue"
},
  "geometry": {"coordinates":[-95.354097,29.871005],"type":"Point"}
}