{
  "type": "Feature",
  "properties": {
    "iso:country":"US",
    "sg:address":"1324 N Nursery Rd",
    "sg:city":"Irving",
    "sg:classifiers":[
        {
            "category":"Freight",
            "type":"Transportation"
        }
    ],
    "sg:phone":"+1 972 438 3608",
    "sg:postcode":"75061",
    "sg:province":"TX",
    "sg:tags":[
        "hauling",
        "trucking"
    ],
    "wof:name":"Rodgers Trucking",
    "wof:placetype":"venue"
},
  "geometry": {"coordinates":[-96.93536899999999,32.82747],"type":"Point"}
}