{
  "type": "Feature",
  "properties": {
    "iso:country":"US",
    "sg:address":"8022 Yacht Club Dr",
    "sg:city":"Rowlett",
    "sg:classifiers":[
        {
            "category":"Building & Trades",
            "subcategory":"Equipment Rental",
            "type":"Services"
        }
    ],
    "sg:phone":"+1 972 475 8563",
    "sg:postcode":"75089",
    "sg:province":"TX",
    "sg:tags":[
        "industrial",
        "scale"
    ],
    "wof:name":"Advanced Scale Technology",
    "wof:placetype":"venue"
},
  "geometry": {"coordinates":[-96.519199,32.932082],"type":"Point"}
}