{
  "type": "Feature",
  "properties": {
    "iso:country":"US",
    "sg:address":"3930 Beaver St",
    "sg:city":"Vernon",
    "sg:classifiers":[
        {
            "category":"Mining & Drilling",
            "type":"Manufacturing & Wholesale Goods"
        }
    ],
    "sg:phone":"+1 940 552 6644",
    "sg:postcode":"76384",
    "sg:province":"TX",
    "sg:tags":[
        "report",
        "field",
        "oil"
    ],
    "wof:name":"Oil & Gas Reporting Service",
    "wof:placetype":"venue"
},
  "geometry": {"coordinates":[-99.303977,34.141434],"type":"Point"}
}