{
  "type": "Feature",
  "properties": {
    "iso:country":"US",
    "sg:address":"1904 N Wells St",
    "sg:city":"Pampa",
    "sg:classifiers":[
        {
            "category":"Personal",
            "type":"Services"
        }
    ],
    "sg:phone":"+1 806 665 2024",
    "sg:postcode":"79065",
    "sg:province":"TX",
    "sg:tags":[
        "dressmaker"
    ],
    "wof:name":"Barbara's Creations",
    "wof:placetype":"venue"
},
  "geometry": {"coordinates":[-100.97710499999999,35.555849],"type":"Point"}
}