{
  "type": "Feature",
  "properties": {
    "iso:country":"US",
    "sg:address":"3000 Altamesa Blvd",
    "sg:city":"Fort Worth",
    "sg:classifiers":[
        {
            "category":"Professional",
            "subcategory":"Computer Services",
            "type":"Services"
        }
    ],
    "sg:phone":"+1 817 263 8100",
    "sg:postcode":"76133",
    "sg:province":"TX",
    "sg:tags":[
        "development",
        "consulting",
        "technology",
        "training"
    ],
    "wof:name":"Savoy River LLC",
    "wof:placetype":"venue"
},
  "geometry": {"coordinates":[-97.360573,32.648942],"type":"Point"}
}