{
  "type": "Feature",
  "properties": {
    "iso:country":"US",
    "sg:address":"2320 NW Loop 286",
    "sg:city":"Paris",
    "sg:classifiers":[
        {
            "category":"Manufacturing",
            "subcategory":"Retail Goods",
            "type":"Manufacturing & Wholesale Goods"
        }
    ],
    "sg:phone":"+1 903 784 8183",
    "sg:postcode":"75460",
    "sg:province":"TX",
    "sg:tags":[
        "product",
        "mfg"
    ],
    "wof:name":"Paris Industries",
    "wof:placetype":"venue"
},
  "geometry": {"coordinates":[-95.581508,33.680572],"type":"Point"}
}