{
  "type": "Feature",
  "properties": {
    "iso:country":"US",
    "sg:address":"306 S Broadway St",
    "sg:city":"Mcallen",
    "sg:classifiers":[
        {
            "category":"Shopping",
            "type":"Retail Goods"
        }
    ],
    "sg:phone":"+1 956 631 1931",
    "sg:postcode":"78501",
    "sg:province":"TX",
    "sg:tags":[
        "coin",
        "dealer",
        "supply"
    ],
    "wof:name":"Broadway Coins",
    "wof:placetype":"venue"
},
  "geometry": {"coordinates":[-98.23400599999999,26.200393],"type":"Point"}
}