{
  "type": "Feature",
  "properties": {
    "iso:country":"US",
    "sg:address":"7301 FM 853",
    "sg:city":"San Angelo",
    "sg:classifiers":[
        {
            "category":"Manufacturing",
            "subcategory":"Metals",
            "type":"Manufacturing & Wholesale Goods"
        }
    ],
    "sg:phone":"+1 325 949 9331",
    "sg:postcode":"76901",
    "sg:province":"TX",
    "sg:tags":[
        "steel",
        "stainless",
        "al",
        "custom",
        "carbon",
        "fabrication"
    ],
    "wof:name":"A M A Manufacturing Company",
    "wof:placetype":"venue"
},
  "geometry": {"coordinates":[-100.539084,31.444474],"type":"Point"}
}