{
  "type": "Feature",
  "properties": {
    "iso:country":"US",
    "sg:address":"2510 Jester Ln",
    "sg:city":"Stafford",
    "sg:classifiers":[
        {
            "category":"Building & Trades",
            "subcategory":"Landscaping Services",
            "type":"Services"
        }
    ],
    "sg:phone":"+1 281 261 7370",
    "sg:postcode":"77477",
    "sg:province":"TX",
    "sg:tags":[
        "landscape"
    ],
    "wof:name":"J&J Landscaping",
    "wof:placetype":"venue"
},
  "geometry": {"coordinates":[-95.553302,29.611754],"type":"Point"}
}