{
  "type": "Feature",
  "properties": {
    "iso:country":"US",
    "sg:address":"2404 State Line Ave",
    "sg:city":"Texarkana",
    "sg:classifiers":[
        {
            "category":"Food & Beverages",
            "subcategory":"Groceries & Convenience Stores",
            "type":"Retail Goods"
        }
    ],
    "sg:phone":"+1 870 779 7778",
    "sg:postcode":"75501",
    "sg:province":"TX",
    "sg:tags":[
        "retailer"
    ],
    "wof:name":"Speed X",
    "wof:placetype":"venue"
},
  "geometry": {"coordinates":[-94.043207,33.399679],"type":"Point"}
}