{
  "type": "Feature",
  "properties": {
    "iso:country":"US",
    "sg:address":"901 Fisher Rd",
    "sg:city":"Longview",
    "sg:classifiers":[
        {
            "category":"Manufacturing",
            "subcategory":"Motor Vehicles & Parts",
            "type":"Manufacturing & Wholesale Goods"
        }
    ],
    "sg:phone":"+1 903 759 9451",
    "sg:postcode":"75604",
    "sg:province":"TX",
    "sg:tags":[
        "trailer"
    ],
    "sg:website":"www.fleetwood.com",
    "wof:name":"Fleetwood Travel Trailers Inc",
    "wof:placetype":"venue"
},
  "geometry": {"coordinates":[-94.818364,32.50839],"type":"Point"}
}