{
  "type": "Feature",
  "properties": {
    "iso:country":"US",
    "sg:address":"2004 Hardy Cir",
    "sg:city":"Austin",
    "sg:classifiers":[
        {
            "category":"Professional",
            "subcategory":"Business Services",
            "type":"Services"
        }
    ],
    "sg:phone":"+1 512 257 9172",
    "sg:postcode":"78757",
    "sg:province":"TX",
    "sg:tags":[
        "holding"
    ],
    "wof:name":"Ja-Kat Holdings",
    "wof:placetype":"venue"
},
  "geometry": {"coordinates":[-97.73241299999999,30.346875],"type":"Point"}
}