{
  "type": "Feature",
  "properties": {
    "iso:country":"US",
    "sg:address":"900 County Ln",
    "sg:city":"Burnet",
    "sg:classifiers":[
        {
            "category":"Professional",
            "subcategory":"Lawyer & Legal Services",
            "type":"Services"
        }
    ],
    "sg:phone":"+1 512 715 8600",
    "sg:postcode":"78611",
    "sg:province":"TX",
    "wof:name":"Southwestern Corrections",
    "wof:placetype":"venue"
},
  "geometry": {"coordinates":[-97.55506699999999,30.347481],"type":"Point"}
}