{
  "type": "Feature",
  "properties": {
    "iso:country":"US",
    "sg:address":"403 S Bonner St",
    "sg:city":"Jacksonville",
    "sg:classifiers":[
        {
            "category":"Shopping",
            "subcategory":"Crafts & Fabrics",
            "type":"Retail Goods"
        }
    ],
    "sg:phone":"+1 903 589 7397",
    "sg:postcode":"75766",
    "sg:province":"TX",
    "sg:tags":[
        "sewing"
    ],
    "wof:name":"Sew Be It",
    "wof:placetype":"venue"
},
  "geometry": {"coordinates":[-95.273993,31.961017],"type":"Point"}
}