{
  "type": "Feature",
  "properties": {
    "iso:country":"US",
    "sg:address":"1250 E Copeland Rd",
    "sg:city":"Arlington",
    "sg:classifiers":[
        {
            "category":"Real Estate",
            "subcategory":"Real Estate Agent",
            "type":"Services"
        }
    ],
    "sg:phone":"+1 817 543 0335",
    "sg:postcode":"76011",
    "sg:province":"TX",
    "wof:name":"Fobare Commercial Inc",
    "wof:placetype":"venue"
},
  "geometry": {"coordinates":[-97.09032999999999,32.759042],"type":"Point"}
}