{
  "type": "Feature",
  "properties": {
    "iso:country":"US",
    "sg:address":"1324 Kings Hwy",
    "sg:city":"Fort Worth",
    "sg:classifiers":[
        {
            "category":"Education",
            "subcategory":"School",
            "type":"Public Place"
        }
    ],
    "sg:phone":"+1 817 838 1550",
    "sg:postcode":"76117",
    "sg:province":"TX",
    "sg:tags":[
        "association"
    ],
    "wof:name":"Natha Howell Elementary School",
    "wof:placetype":"venue"
},
  "geometry": {"coordinates":[-97.287361,32.781267],"type":"Point"}
}