{
  "type": "Feature",
  "properties": {
    "iso:country":"US",
    "sg:address":"132 N Main St",
    "sg:city":"Grand Saline",
    "sg:classifiers":[
        {
            "category":"Personal",
            "type":"Services"
        }
    ],
    "sg:phone":"+1 903 962 5233",
    "sg:postcode":"75140",
    "sg:province":"TX",
    "wof:name":"Triple R Tan",
    "wof:placetype":"venue"
},
  "geometry": {"coordinates":[-95.70955499999999,32.673216],"type":"Point"}
}