{
  "type": "Feature",
  "properties": {
    "iso:country":"US",
    "sg:address":"6215 Ridgemont St",
    "sg:city":"Houston",
    "sg:classifiers":[
        {
            "category":"Manufacturing",
            "subcategory":"Tools & Machinery",
            "type":"Manufacturing & Wholesale Goods"
        }
    ],
    "sg:phone":"+1 713 641 1022",
    "sg:postcode":"77087",
    "sg:province":"TX",
    "sg:tags":[
        "industrial",
        "mfg"
    ],
    "wof:name":"MTZ Machine Shop",
    "wof:placetype":"venue"
},
  "geometry": {"coordinates":[-95.317711,29.691261],"type":"Point"}
}