{
  "type": "Feature",
  "properties": {
    "iso:country":"US",
    "sg:address":"9048 Long Point Rd",
    "sg:city":"Houston",
    "sg:classifiers":[
        {
            "category":"Retail",
            "subcategory":"Auto Repair",
            "type":"Services"
        }
    ],
    "sg:phone":"+1 713 467 7356",
    "sg:postcode":"77055",
    "sg:province":"TX",
    "sg:tags":[
        "body",
        "automobile",
        "painting"
    ],
    "wof:name":"Info Repair Ctr",
    "wof:placetype":"venue"
},
  "geometry": {"coordinates":[-95.51241,29.800485],"type":"Point"}
}