{
  "type": "Feature",
  "properties": {
    "iso:country":"US",
    "sg:address":"5118 Santa Fe Dr",
    "sg:city":"Lubbock",
    "sg:classifiers":[
        {
            "category":"Home & Garden",
            "subcategory":"Home Furnishings",
            "type":"Retail Goods"
        }
    ],
    "sg:phone":"+1 806 797 9780",
    "sg:postcode":"79407",
    "sg:province":"TX",
    "sg:tags":[
        "upholstery",
        "fabric"
    ],
    "wof:name":"Edge's Upholstery",
    "wof:placetype":"venue"
},
  "geometry": {"coordinates":[-101.920086,33.566013],"type":"Point"}
}