{
  "type": "Feature",
  "properties": {
    "iso:country":"US",
    "sg:address":"4017 Clay Ave",
    "sg:city":"Fort Worth",
    "sg:classifiers":[
        {
            "category":"Manufacturing",
            "subcategory":"Furniture",
            "type":"Manufacturing & Wholesale Goods"
        },
        {
            "category":"Building & Trades",
            "subcategory":"Construction",
            "type":"Services"
        }
    ],
    "sg:phone":"+1 817 656 0206",
    "sg:postcode":"76117",
    "sg:province":"TX",
    "sg:tags":[
        "cabinet",
        "wood",
        "maker",
        "mfg"
    ],
    "wof:name":"Ron's Custom Cabinets",
    "wof:placetype":"venue"
},
  "geometry": {"coordinates":[-97.28208100000001,32.829227],"type":"Point"}
}