{
  "type": "Feature",
  "properties": {
    "iso:country":"US",
    "sg:address":"452 FM 306",
    "sg:city":"New Braunfels",
    "sg:classifiers":[
        {
            "category":"Freight",
            "type":"Transportation"
        }
    ],
    "sg:phone":"+1 830 625 2872",
    "sg:postcode":"78130",
    "sg:province":"TX",
    "sg:tags":[
        "commercial",
        "storage",
        "special"
    ],
    "wof:name":"U S A Mini Storage",
    "wof:placetype":"venue"
},
  "geometry": {"coordinates":[-98.085718,29.7355],"type":"Point"}
}