{
  "type": "Feature",
  "properties": {
    "iso:country":"US",
    "sg:address":"6625 FM 3396",
    "sg:city":"Kemp",
    "sg:classifiers":[
        {
            "category":"Retail",
            "subcategory":"Repair Shop",
            "type":"Services"
        }
    ],
    "sg:phone":"+1 903 498 5760",
    "sg:postcode":"75143",
    "sg:province":"TX",
    "sg:tags":[
        "electrical"
    ],
    "wof:name":"Siguma Enterprises",
    "wof:placetype":"venue"
},
  "geometry": {"coordinates":[-96.317438,32.363616],"type":"Point"}
}