{
  "type": "Feature",
  "properties": {
    "iso:country":"US",
    "sg:address":"275 Commerce St",
    "sg:city":"Southlake",
    "sg:classifiers":[
        {
            "category":"Wholesale",
            "subcategory":"Plants",
            "type":"Manufacturing & Wholesale Goods"
        }
    ],
    "sg:phone":"+1 817 481 6130",
    "sg:postcode":"76092",
    "sg:province":"TX",
    "sg:tags":[
        "flower"
    ],
    "wof:name":"Silk Market",
    "wof:placetype":"venue"
},
  "geometry": {"coordinates":[-97.104764,32.93603],"type":"Point"}
}