{
  "type": "Feature",
  "properties": {
    "iso:country":"US",
    "sg:address":"1406 Three Points Rd",
    "sg:city":"Pflugerville",
    "sg:classifiers":[
        {
            "category":"Professional",
            "subcategory":"Engineering",
            "type":"Services"
        }
    ],
    "sg:phone":"+1 512 251 4279",
    "sg:postcode":"78660",
    "sg:province":"TX",
    "sg:tags":[
        "consulting",
        "engineer"
    ],
    "sg:website":"www.ephainc.com",
    "wof:name":"E P Hamilton & Associates",
    "wof:placetype":"venue"
},
  "geometry": {"coordinates":[-97.662115,30.451673],"type":"Point"}
}