{
  "type": "Feature",
  "properties": {
    "iso:country":"US",
    "sg:address":"5 Duncannon Ct",
    "sg:city":"Dallas",
    "sg:classifiers":[
        {
            "category":"Real Estate",
            "subcategory":"Real Estate Agent",
            "type":"Services"
        }
    ],
    "sg:phone":"+1 214 691 3693",
    "sg:postcode":"75225",
    "sg:province":"TX",
    "wof:name":"Kas Properties",
    "wof:placetype":"venue"
},
  "geometry": {"coordinates":[-96.776624,32.878619],"type":"Point"}
}