{
  "type": "Feature",
  "properties": {
    "iso:country":"US",
    "sg:address":"619 Inspiration Dr",
    "sg:city":"San Antonio",
    "sg:classifiers":[
        {
            "category":"Professional",
            "type":"Services"
        }
    ],
    "sg:phone":"+1 210 436 1939",
    "sg:postcode":"78228",
    "sg:province":"TX",
    "wof:name":"Murray Rf Co Inc",
    "wof:placetype":"venue"
},
  "geometry": {"coordinates":[-98.576733,29.482793],"type":"Point"}
}