{
  "type": "Feature",
  "properties": {
    "iso:country":"US",
    "sg:address":"10190 Old Katy Rd",
    "sg:city":"Houston",
    "sg:classifiers":[
        {
            "category":"Banks & Credit Unions",
            "subcategory":"Bank",
            "type":"Services"
        }
    ],
    "sg:phone":"+1 713 465 4095",
    "sg:postcode":"77043",
    "sg:province":"TX",
    "sg:tags":[
        "loan",
        "real estate"
    ],
    "wof:name":"First Quantum Funding",
    "wof:placetype":"venue"
},
  "geometry": {"coordinates":[-95.548878,29.785036],"type":"Point"}
}