{
  "type": "Feature",
  "properties": {
    "iso:country":"US",
    "sg:address":"3207 Mercer St",
    "sg:city":"Houston",
    "sg:classifiers":[
        {
            "category":"Professional",
            "subcategory":"Business Services",
            "type":"Services"
        }
    ],
    "sg:phone":"+1 713 864 9933",
    "sg:postcode":"77027",
    "sg:province":"TX",
    "wof:name":"Sanders Tom Mediator",
    "wof:placetype":"venue"
},
  "geometry": {"coordinates":[-95.432067,29.737454],"type":"Point"}
}