{
  "type": "Feature",
  "properties": {
    "iso:country":"US",
    "sg:address":"780 S Macarthur Blvd",
    "sg:city":"Coppell",
    "sg:classifiers":[
        {
            "category":"Restaurant",
            "type":"Food & Drink"
        }
    ],
    "sg:phone":"+1 972 304 1060",
    "sg:postcode":"75019",
    "sg:province":"TX",
    "sg:tags":[
        "eating"
    ],
    "wof:name":"Little Caesars",
    "wof:placetype":"venue"
},
  "geometry": {"coordinates":[-96.957577,32.954932],"type":"Point"}
}