{
  "type": "Feature",
  "properties": {
    "iso:country":"US",
    "sg:address":"2732 Gaston Ave",
    "sg:city":"Dallas",
    "sg:classifiers":[
        {
            "category":"Professional",
            "subcategory":"Research",
            "type":"Services"
        }
    ],
    "sg:phone":"+1 214 752 7554",
    "sg:postcode":"75226",
    "sg:province":"TX",
    "sg:tags":[
        "organization",
        "noncommercial"
    ],
    "wof:name":"Soul Stirrers Institute",
    "wof:placetype":"venue"
},
  "geometry": {"coordinates":[-96.786447,32.786331],"type":"Point"}
}