{
  "type": "Feature",
  "properties": {
    "iso:country":"US",
    "sg:address":"1910 Danbury Dr",
    "sg:city":"Garland",
    "sg:classifiers":[
        {
            "category":"Building & Trades",
            "subcategory":"Equipment Rental",
            "type":"Services"
        }
    ],
    "sg:phone":"+1 972 271 7363",
    "sg:postcode":"75040",
    "sg:province":"TX",
    "wof:name":"P&B Fiesta Rental",
    "wof:placetype":"venue"
},
  "geometry": {"coordinates":[-96.61939,32.89543],"type":"Point"}
}