{
  "type": "Feature",
  "properties": {
    "iso:country":"US",
    "sg:address":"602 Redwood Dr",
    "sg:city":"Grand Prairie",
    "sg:classifiers":[
        {
            "category":"Manufacturing",
            "subcategory":"Furniture",
            "type":"Manufacturing & Wholesale Goods"
        }
    ],
    "sg:phone":"+1 972 262 1408",
    "sg:postcode":"75052",
    "sg:province":"TX",
    "sg:tags":[
        "household",
        "wood",
        "mfg"
    ],
    "wof:name":"Daddy Did It",
    "wof:placetype":"venue"
},
  "geometry": {"coordinates":[-97.000799,32.686403],"type":"Point"}
}