{
  "type": "Feature",
  "properties": {
    "iso:country":"US",
    "sg:address":"1630 E Main St",
    "sg:city":"Grand Prairie",
    "sg:classifiers":[
        {
            "category":"Professional",
            "subcategory":"Business Services",
            "type":"Services"
        }
    ],
    "sg:phone":"+1 972 266 0366",
    "sg:postcode":"75050",
    "sg:province":"TX",
    "wof:name":"Dolex Dollar Express",
    "wof:placetype":"venue"
},
  "geometry": {"coordinates":[-96.982687,32.748034],"type":"Point"}
}