{
  "type": "Feature",
  "properties": {
    "iso:country":"US",
    "sg:address":"2810 Mayfield Rd",
    "sg:city":"Grand Prairie",
    "sg:classifiers":[
        {
            "category":"Home & Garden",
            "subcategory":"Furniture",
            "type":"Retail Goods"
        }
    ],
    "sg:phone":"+1 972 647 2255",
    "sg:postcode":"75052",
    "sg:province":"TX",
    "wof:name":"Rooms To Sell",
    "wof:placetype":"venue"
},
  "geometry": {"coordinates":[-97.053783,32.691455],"type":"Point"}
}