{
  "type": "Feature",
  "properties": {
    "iso:country":"US",
    "sg:address":"4309 Irving Ave",
    "sg:city":"Dallas",
    "sg:classifiers":[
        {
            "category":"Professional",
            "subcategory":"Detective & Security Services",
            "type":"Services"
        }
    ],
    "sg:phone":"+1 214 522 2850",
    "sg:postcode":"75219",
    "sg:province":"TX",
    "sg:tags":[
        "system"
    ],
    "wof:name":"Sonitrol of Dallas Inc",
    "wof:placetype":"venue"
},
  "geometry": {"coordinates":[-96.799004,32.816301],"type":"Point"}
}