{
  "type": "Feature",
  "properties": {
    "iso:country":"US",
    "sg:address":"16015 Winchmore Hill Dr",
    "sg:city":"Spring",
    "sg:classifiers":[
        {
            "category":"Shopping",
            "subcategory":"Discount & Variety Stores",
            "type":"Retail Goods"
        }
    ],
    "sg:phone":"+1 281 370 4696",
    "sg:postcode":"77379",
    "sg:province":"TX",
    "wof:name":"Battarbee Racing Inc",
    "wof:placetype":"venue"
},
  "geometry": {"coordinates":[-95.53828799999999,30.004981],"type":"Point"}
}