{
  "type": "Feature",
  "properties": {
    "iso:country":"US",
    "sg:address":"635 W Campbell Rd",
    "sg:city":"Richardson",
    "sg:classifiers":[
        {
            "category":"Retail",
            "subcategory":"Portrait Studio",
            "type":"Services"
        }
    ],
    "sg:phone":"+1 972 238 9900",
    "sg:postcode":"75080",
    "sg:province":"TX",
    "sg:tags":[
        "photo"
    ],
    "wof:name":"Bovis Studio",
    "wof:placetype":"venue"
},
  "geometry": {"coordinates":[-96.741241,32.977996],"type":"Point"}
}