{
  "type": "Feature",
  "properties": {
    "iso:country":"US",
    "sg:address":"2321 Southwest Fwy",
    "sg:city":"Houston",
    "sg:classifiers":[
        {
            "category":"Health Services",
            "subcategory":"Doctor",
            "type":"Services"
        }
    ],
    "sg:phone":"+1 713 533 1250",
    "sg:postcode":"77098",
    "sg:province":"TX",
    "wof:name":"United Neurology",
    "wof:placetype":"venue"
},
  "geometry": {"coordinates":[-95.414267,29.730189],"type":"Point"}
}