{
  "type": "Feature",
  "properties": {
    "iso:country":"US",
    "sg:address":"506 Frankie St",
    "sg:city":"Wharton",
    "sg:classifiers":[
        {
            "category":"Shopping",
            "subcategory":"Jewelry",
            "type":"Retail Goods"
        }
    ],
    "sg:phone":"+1 979 532 8205",
    "sg:postcode":"77488",
    "sg:province":"TX",
    "sg:tags":[
        "repair"
    ],
    "wof:name":"Jaceks Design",
    "wof:placetype":"venue"
},
  "geometry": {"coordinates":[-96.088959,29.327353],"type":"Point"}
}