{
  "type": "Feature",
  "properties": {
    "iso:country":"US",
    "sg:address":"5342 Canyon Dr",
    "sg:city":"Amarillo",
    "sg:classifiers":[
        {
            "category":"Arts & Performance",
            "subcategory":"Theater",
            "type":"Entertainment"
        }
    ],
    "sg:phone":"+1 806 356 6487",
    "sg:postcode":"79109",
    "sg:province":"TX",
    "sg:tags":[
        "live",
        "music"
    ],
    "wof:name":"Karaoke Of Amarillo",
    "wof:placetype":"venue"
},
  "geometry": {"coordinates":[-101.884371,35.15032],"type":"Point"}
}