{
  "type": "Feature",
  "properties": {
    "iso:country":"US",
    "sg:address":"275 Circle Dr",
    "sg:city":"Bridge City",
    "sg:classifiers":[
        {
            "category":"Professional",
            "subcategory":"Detective & Security Services",
            "type":"Services"
        }
    ],
    "sg:phone":"+1 409 697 4999",
    "sg:postcode":"77611",
    "sg:province":"TX",
    "sg:tags":[
        "car",
        "investigator"
    ],
    "wof:name":"Bacom Investigation Service",
    "wof:placetype":"venue"
},
  "geometry": {"coordinates":[-93.836296,30.023914],"type":"Point"}
}