{
  "type": "Feature",
  "properties": {
    "iso:country":"US",
    "sg:address":"813 Forest Ave",
    "sg:city":"Tyler",
    "sg:classifiers":[
        {
            "category":"Mining & Drilling",
            "type":"Manufacturing & Wholesale Goods"
        }
    ],
    "sg:phone":"+1 903 593 3828",
    "sg:postcode":"75702",
    "sg:province":"TX",
    "sg:tags":[
        "exploration"
    ],
    "wof:name":"First Texas Hunter Inc",
    "wof:placetype":"venue"
},
  "geometry": {"coordinates":[-95.326009,32.358935],"type":"Point"}
}