{
  "type": "Feature",
  "properties": {
    "iso:country":"US",
    "sg:address":"2755 Valwood Pkwy",
    "sg:city":"Dallas",
    "sg:classifiers":[
        {
            "category":"Manufacturing",
            "subcategory":"Retail Goods",
            "type":"Manufacturing & Wholesale Goods"
        }
    ],
    "sg:phone":"+1 972 620 0270",
    "sg:postcode":"75234",
    "sg:province":"TX",
    "sg:tags":[
        "product",
        "mfg"
    ],
    "wof:name":"Dawn Beaver Mfg",
    "wof:placetype":"venue"
},
  "geometry": {"coordinates":[-96.88672800000001,32.938389],"type":"Point"}
}