{
  "type": "Feature",
  "properties": {
    "iso:country":"US",
    "sg:address":"4404 E Oltorf Street Apt 7202",
    "sg:city":"Austin",
    "sg:classifiers":[
        {
            "category":"Real Estate",
            "subcategory":"Real Estate Operator",
            "type":"Services"
        }
    ],
    "sg:phone":"+1 512 912 7661",
    "sg:postcode":"78741",
    "sg:province":"TX",
    "sg:tags":[
        "apartment"
    ],
    "wof:name":"University Canyon Apartments Austin",
    "wof:placetype":"venue"
},
  "geometry": {"coordinates":[-97.72662099999999,30.22696],"type":"Point"}
}