{
  "type": "Feature",
  "properties": {
    "iso:country":"US",
    "sg:address":"2657 Warfield St",
    "sg:city":"Fort Worth",
    "sg:classifiers":[
        {
            "category":"Recreation",
            "subcategory":"Arcade",
            "type":"Entertainment"
        }
    ],
    "sg:phone":"+1 817 626 5411",
    "sg:postcode":"76106",
    "sg:province":"TX",
    "sg:tags":[
        "operated",
        "game",
        "coin",
        "amusement"
    ],
    "wof:name":"Quality Vending",
    "wof:placetype":"venue"
},
  "geometry": {"coordinates":[-97.323564,32.792764],"type":"Point"}
}