{
  "type": "Feature",
  "properties": {
    "iso:country":"US",
    "sg:address":"5200 Keller Springs Rd",
    "sg:city":"Dallas",
    "sg:classifiers":[
        {
            "category":"Professional",
            "type":"Services"
        }
    ],
    "sg:phone":"+1 972 662 6464",
    "sg:postcode":"75248",
    "sg:province":"TX",
    "wof:name":"Rpbackus Interests",
    "wof:placetype":"venue"
},
  "geometry": {"coordinates":[-96.814606,32.968426],"type":"Point"}
}