{
  "type": "Feature",
  "properties": {
    "iso:country":"US",
    "sg:address":"6616 Stichter Ave",
    "sg:city":"Dallas",
    "sg:classifiers":[
        {
            "category":"Personal",
            "type":"Services"
        }
    ],
    "sg:phone":"+1 214 265 9024",
    "sg:postcode":"75230",
    "sg:province":"TX",
    "sg:tags":[
        "miscellaneous"
    ],
    "wof:name":"Tanna LLC",
    "wof:placetype":"venue"
},
  "geometry": {"coordinates":[-96.791785,32.880998],"type":"Point"}
}