{
  "type": "Feature",
  "properties": {
    "iso:country":"US",
    "sg:address":"418 S Main St",
    "sg:city":"Highlands",
    "sg:classifiers":[
        {
            "category":"Retail",
            "subcategory":"Auto Repair",
            "type":"Services"
        }
    ],
    "sg:phone":"+1 281 426 5774",
    "sg:postcode":"77562",
    "sg:province":"TX",
    "sg:tags":[
        "antique",
        "rebuilding",
        "race",
        "car",
        "vintage"
    ],
    "wof:name":"Sheldon Design",
    "wof:placetype":"venue"
},
  "geometry": {"coordinates":[-95.056927,29.810579],"type":"Point"}
}