{
  "type": "Feature",
  "properties": {
    "iso:country":"US",
    "sg:address":"911 W 1st Ave",
    "sg:city":"Amarillo",
    "sg:classifiers":[
        {
            "category":"Organizations",
            "subcategory":"Religious Organization",
            "type":"Services"
        }
    ],
    "sg:phone":"+1 806 376 7116",
    "sg:postcode":"79106",
    "sg:province":"TX",
    "sg:tags":[
        "clergy"
    ],
    "wof:name":"Elgie Crow",
    "wof:placetype":"venue"
},
  "geometry": {"coordinates":[-101.847269,35.214122],"type":"Point"}
}