{
  "type": "Feature",
  "properties": {
    "iso:country":"US",
    "sg:address":"909 State Hwy 323",
    "sg:city":"Tyler",
    "sg:classifiers":[
        {
            "category":"Wholesale",
            "subcategory":"Jewelry",
            "type":"Manufacturing & Wholesale Goods"
        }
    ],
    "sg:phone":"+1 903 531 9696",
    "sg:postcode":"75701",
    "sg:province":"TX",
    "sg:tags":[
        "jeweler"
    ],
    "wof:name":"Edward Comer",
    "wof:placetype":"venue"
},
  "geometry": {"coordinates":[-95.311042,32.303738],"type":"Point"}
}