{
  "type": "Feature",
  "properties": {
    "iso:country":"US",
    "sg:address":"11363 Veterans Memorial Dr",
    "sg:city":"Houston",
    "sg:classifiers":[
        {
            "category":"Personal",
            "subcategory":"Beauty Salon",
            "type":"Services"
        }
    ],
    "sg:phone":"+1 281 895 6188",
    "sg:postcode":"77067",
    "sg:province":"TX",
    "sg:tags":[
        "shop"
    ],
    "wof:name":"Uptown Beauty Mart",
    "wof:placetype":"venue"
},
  "geometry": {"coordinates":[-95.46700300000001,29.946472],"type":"Point"}
}