{
  "type": "Feature",
  "properties": {
    "iso:country":"US",
    "sg:address":"3205 Buffalo Springs Trl",
    "sg:city":"Georgetown",
    "sg:classifiers":[
        {
            "category":"Building & Trades",
            "subcategory":"Construction",
            "type":"Services"
        }
    ],
    "sg:phone":"+1 512 470 2242",
    "sg:postcode":"78628",
    "sg:province":"TX",
    "sg:tags":[
        "contractor"
    ],
    "wof:name":"Plan B Painting & Drywall",
    "wof:placetype":"venue"
},
  "geometry": {"coordinates":[-97.69072199999999,30.668293],"type":"Point"}
}