{
  "type": "Feature",
  "properties": {
    "iso:country":"US",
    "sg:address":"4338 Haven Glen Dr",
    "sg:city":"Humble",
    "sg:classifiers":[
        {
            "category":"Utilities",
            "subcategory":"Telephone",
            "type":"Services"
        }
    ],
    "sg:phone":"+1 281 358 7677",
    "sg:postcode":"77339",
    "sg:province":"TX",
    "sg:tags":[
        "communications",
        "computer",
        "related"
    ],
    "wof:name":"Robert M Tyler",
    "wof:placetype":"venue"
},
  "geometry": {"coordinates":[-95.20608,30.067651],"type":"Point"}
}