{
  "type": "Feature",
  "properties": {
    "iso:country":"US",
    "sg:address":"630 S Saint Marys St",
    "sg:city":"Falfurrias",
    "sg:classifiers":[
        {
            "category":"Restaurant",
            "type":"Food & Drink"
        }
    ],
    "sg:phone":"+1 361 325 3888",
    "sg:postcode":"78355",
    "sg:province":"TX",
    "sg:tags":[
        "eating"
    ],
    "sg:website":"http://www.dairyqueen.com",
    "wof:name":"Dairy Queen",
    "wof:placetype":"venue"
},
  "geometry": {"coordinates":[-98.144935,27.221473],"type":"Point"}
}