{
  "type": "Feature",
  "properties": {
    "iso:country":"US",
    "sg:address":"1901 S 24th Ave",
    "sg:city":"Edinburg",
    "sg:classifiers":[
        {
            "category":"Health Services",
            "subcategory":"Clinic",
            "type":"Services"
        }
    ],
    "sg:phone":"+1 956 383 0121",
    "sg:postcode":"78539",
    "sg:province":"TX",
    "sg:tags":[
        "outpatient",
        "mental"
    ],
    "wof:name":"Tropical TX Ctr Mental Hlth",
    "wof:placetype":"venue"
},
  "geometry": {"coordinates":[-98.15013399999999,26.283327],"type":"Point"}
}