{
  "type": "Feature",
  "properties": {
    "iso:country":"US",
    "sg:address":"2150 del Rio Blvd",
    "sg:city":"Eagle Pass",
    "sg:classifiers":[
        {
            "category":"Restaurant",
            "type":"Food & Drink"
        }
    ],
    "sg:phone":"+1 830 773 2100",
    "sg:postcode":"78852",
    "sg:province":"TX",
    "sg:tags":[
        "eating"
    ],
    "wof:name":"Guvas Steak & Grill",
    "wof:placetype":"venue"
},
  "geometry": {"coordinates":[-100.495698,28.733205],"type":"Point"}
}