{
  "type": "Feature",
  "properties": {
    "iso:country":"US",
    "sg:address":"151 Melody Ln",
    "sg:city":"Kingsland",
    "sg:classifiers":[
        {
            "category":"Travel",
            "subcategory":"Hotels & Motels",
            "type":"Entertainment"
        }
    ],
    "sg:phone":"+1 325 388 4343",
    "sg:postcode":"78629",
    "sg:province":"TX",
    "sg:tags":[
        "resort"
    ],
    "sg:website":"www.longhornresort.com",
    "wof:name":"Longhorn Resort",
    "wof:placetype":"venue"
},
  "geometry": {"coordinates":[-97.431338,29.504806],"type":"Point"}
}