{
  "type": "Feature",
  "properties": {
    "iso:country":"US",
    "sg:address":"5426 29th St",
    "sg:city":"Lubbock",
    "sg:classifiers":[
        {
            "category":"Real Estate",
            "subcategory":"Real Estate Operator",
            "type":"Services"
        }
    ],
    "sg:phone":"+1 806 799 2268",
    "sg:postcode":"79407",
    "sg:province":"TX",
    "sg:tags":[
        "property",
        "lessor"
    ],
    "wof:name":"Bell W Don Farms Inc",
    "wof:placetype":"venue"
},
  "geometry": {"coordinates":[-101.930193,33.567821],"type":"Point"}
}