{
  "type": "Feature",
  "properties": {
    "iso:country":"US",
    "sg:address":"4918 Holly Rd",
    "sg:city":"Corpus Christi",
    "sg:classifiers":[
        {
            "category":"Banks & Credit Unions",
            "subcategory":"Investment Brokerage",
            "type":"Services"
        }
    ],
    "sg:phone":"+1 361 906 2866",
    "sg:postcode":"78411",
    "sg:province":"TX",
    "sg:tags":[
        "advisory",
        "financial"
    ],
    "wof:name":"Brann Financial",
    "wof:placetype":"venue"
},
  "geometry": {"coordinates":[-97.389578,27.705172],"type":"Point"}
}