{
  "type": "Feature",
  "properties": {
    "iso:country":"US",
    "sg:address":"5426 Gessner Dr",
    "sg:city":"Houston",
    "sg:classifiers":[
        {
            "category":"Manufacturing",
            "subcategory":"Printing",
            "type":"Manufacturing & Wholesale Goods"
        }
    ],
    "sg:phone":"+1 713 462 8500",
    "sg:postcode":"77041",
    "sg:province":"TX",
    "sg:tags":[
        "printer"
    ],
    "wof:name":"Image Masters",
    "wof:placetype":"venue"
},
  "geometry": {"coordinates":[-95.54501,29.846262],"type":"Point"}
}