{
  "type": "Feature",
  "properties": {
    "iso:country":"US",
    "sg:address":"1515 Cumberland Rd",
    "sg:city":"Tyler",
    "sg:classifiers":[
        {
            "category":"Structure",
            "subcategory":"Warehouse",
            "type":"Public Place"
        },
        {
            "category":"Retail",
            "subcategory":"Storage",
            "type":"Services"
        }
    ],
    "sg:phone":"+1 903 581 5721",
    "sg:postcode":"75703",
    "sg:province":"TX",
    "sg:tags":[
        "self",
        "warehouses-public-commercial"
    ],
    "wof:name":"Ivor Mckwown",
    "wof:placetype":"venue"
},
  "geometry": {"coordinates":[-95.28458999999999,32.253028],"type":"Point"}
}