{
  "type": "Feature",
  "properties": {
    "iso:country":"US",
    "sg:address":"642 S Padre Island Dr",
    "sg:city":"Corpus Christi",
    "sg:classifiers":[
        {
            "category":"Autos & Motor Vehicles",
            "subcategory":"Motorcycle Sales",
            "type":"Retail Goods"
        }
    ],
    "sg:phone":"+1 361 855 7907",
    "sg:postcode":"78416",
    "sg:province":"TX",
    "wof:name":"Cycledelic Custom Motor Cycles",
    "wof:placetype":"venue"
},
  "geometry": {"coordinates":[-97.45806399999999,27.754744],"type":"Point"}
}