{
  "type": "Feature",
  "properties": {
    "iso:country":"US",
    "sg:address":"4106 Goodfellow Dr",
    "sg:city":"Dallas",
    "sg:classifiers":[
        {
            "category":"Insurance",
            "subcategory":"Insurance Agent",
            "type":"Services"
        }
    ],
    "sg:phone":"+1 214 351 5415",
    "sg:postcode":"75229",
    "sg:province":"TX",
    "wof:name":"Stephen S Williams",
    "wof:placetype":"venue"
},
  "geometry": {"coordinates":[-96.840678,32.908818],"type":"Point"}
}