{
  "type": "Feature",
  "properties": {
    "iso:country":"US",
    "sg:address":"508 Jewett St",
    "sg:city":"Houston",
    "sg:classifiers":[
        {
            "category":"Shopping",
            "type":"Retail Goods"
        }
    ],
    "sg:phone":"+1 713 426 2322",
    "sg:postcode":"77009",
    "sg:province":"TX",
    "sg:tags":[
        "ice"
    ],
    "wof:name":"Airtran Ice Machine",
    "wof:placetype":"venue"
},
  "geometry": {"coordinates":[-95.37294300000001,29.799149],"type":"Point"}
}