{
  "type": "Feature",
  "properties": {
    "iso:country":"US",
    "sg:address":"6040 Co Rd 77",
    "sg:city":"Taft",
    "sg:phone":"+1 361 528 3635",
    "sg:postcode":"78390",
    "sg:province":"TX",
    "sg:tags":[
        "farm",
        "cotton"
    ],
    "wof:name":"K Rothlisberge",
    "wof:placetype":"venue"
},
  "geometry": {"coordinates":[-97.36137600000001,27.975693],"type":"Point"}
}