{
  "type": "Feature",
  "properties": {
    "iso:country":"US",
    "sg:address":"1001 McKinney St",
    "sg:city":"Houston",
    "sg:classifiers":[
        {
            "category":"Mining & Drilling",
            "type":"Manufacturing & Wholesale Goods"
        }
    ],
    "sg:phone":"+1 713 651 9100",
    "sg:postcode":"77002",
    "sg:province":"TX",
    "sg:tags":[
        "exploration"
    ],
    "wof:name":"Sp Hartzell Inc",
    "wof:placetype":"venue"
},
  "geometry": {"coordinates":[-95.36405000000001,29.75643],"type":"Point"}
}