{
  "type": "Feature",
  "properties": {
    "iso:country":"US",
    "sg:address":"16115 Forecastle St",
    "sg:city":"Crosby",
    "sg:classifiers":[
        {
            "category":"Shopping",
            "subcategory":"Computers & Home Electronics",
            "type":"Retail Goods"
        }
    ],
    "sg:phone":"+1 281 328 1427",
    "sg:postcode":"77532",
    "sg:province":"TX",
    "sg:tags":[
        "automobile",
        "stereo",
        "radio",
        "system"
    ],
    "wof:name":"Never Satisfied Car Audio",
    "wof:placetype":"venue"
},
  "geometry": {"coordinates":[-95.078377,29.91493],"type":"Point"}
}