{
  "type": "Feature",
  "properties": {
    "iso:country":"US",
    "sg:address":"3400 S Collins St",
    "sg:city":"Arlington",
    "sg:classifiers":[
        {
            "category":"Food & Beverages",
            "subcategory":"Groceries & Convenience Stores",
            "type":"Retail Goods"
        }
    ],
    "sg:phone":"+1 817 465 8219",
    "sg:postcode":"76014",
    "sg:province":"TX",
    "wof:name":"7-Eleven",
    "wof:placetype":"venue"
},
  "geometry": {"coordinates":[-97.09647,32.688249],"type":"Point"}
}