{
  "type": "Feature",
  "properties": {
    "iso:country":"US",
    "sg:address":"4047 Naco Perrin Blvd",
    "sg:city":"San Antonio",
    "sg:classifiers":[
        {
            "category":"Building & Trades",
            "subcategory":"Construction",
            "type":"Services"
        }
    ],
    "sg:phone":"+1 210 444 1100",
    "sg:postcode":"78217",
    "sg:province":"TX",
    "sg:tags":[
        "general",
        "contractor"
    ],
    "wof:name":"Hispanic Contractors",
    "wof:placetype":"venue"
},
  "geometry": {"coordinates":[-98.416827,29.543438],"type":"Point"}
}