{
  "type": "Feature",
  "properties": {
    "iso:country":"US",
    "sg:address":"2215 S Congress Ave",
    "sg:city":"Austin",
    "sg:classifiers":[
        {
            "category":"Retail",
            "subcategory":"Laundry & Dry Cleaning",
            "type":"Services"
        }
    ],
    "sg:phone":"+1 512 491 9191",
    "sg:postcode":"78704",
    "sg:province":"TX",
    "wof:name":"Jack Brown Alterations",
    "wof:placetype":"venue"
},
  "geometry": {"coordinates":[-97.752701,30.2404],"type":"Point"}
}