{
  "type": "Feature",
  "properties": {
    "iso:country":"US",
    "sg:address":"11406 Metric Blvd",
    "sg:city":"Austin",
    "sg:classifiers":[
        {
            "category":"Professional",
            "subcategory":"Business Services",
            "type":"Services"
        },
        {
            "category":"Manufacturing",
            "subcategory":"Paper Products",
            "type":"Manufacturing & Wholesale Goods"
        },
        {
            "category":"Real Estate",
            "subcategory":"Architect",
            "type":"Services"
        }
    ],
    "sg:phone":"+1 877 747 7570",
    "sg:postcode":"78758",
    "sg:province":"TX",
    "sg:tags":[
        "shredding-paper",
        "document",
        "destruction",
        "record"
    ],
    "sg:website":"http://solutions.ironmountain.com/Papershred",
    "wof:name":"Iron Mountain",
    "wof:placetype":"venue"
},
  "geometry": {"coordinates":[-97.707762,30.393249],"type":"Point"}
}