{
  "type": "Feature",
  "properties": {
    "iso:country":"US",
    "sg:address":"2200 North Loop W",
    "sg:city":"Houston",
    "sg:classifiers":[
        {
            "category":"Professional",
            "subcategory":"Lawyer & Legal Services",
            "type":"Services"
        }
    ],
    "sg:phone":"+1 713 682 4210",
    "sg:postcode":"77018",
    "sg:province":"TX",
    "wof:name":"The Law Office of Candace B Demary",
    "wof:placetype":"venue"
},
  "geometry": {"coordinates":[-95.439812,29.810006],"type":"Point"}
}