{
  "type": "Feature",
  "properties": {
    "iso:country":"US",
    "sg:address":"2211 S Hackberry St",
    "sg:city":"San Antonio",
    "sg:classifiers":[
        {
            "category":"Travel",
            "subcategory":"Campground",
            "type":"Entertainment"
        }
    ],
    "sg:phone":"+1 210 534 4615",
    "sg:postcode":"78210",
    "sg:province":"TX",
    "sg:tags":[
        "child",
        "camp",
        "day",
        "care"
    ],
    "wof:name":"Kid Kamp Day Care Center",
    "wof:placetype":"venue"
},
  "geometry": {"coordinates":[-98.473557,29.395245],"type":"Point"}
}