{
  "type": "Feature",
  "properties": {
    "iso:country":"US",
    "sg:address":"6511 State Hwy 19 S",
    "sg:city":"Athens",
    "sg:classifiers":[
        {
            "category":"Retail",
            "subcategory":"Auto Repair",
            "type":"Services"
        }
    ],
    "sg:phone":"+1 903 675 3639",
    "sg:postcode":"75751",
    "sg:province":"TX",
    "sg:tags":[
        "general"
    ],
    "wof:name":"Fulton Tire & Auto Service",
    "wof:placetype":"venue"
},
  "geometry": {"coordinates":[-95.852143,32.230485],"type":"Point"}
}