{
  "type": "Feature",
  "properties": {
    "iso:country":"US",
    "sg:address":"1336 Malone St",
    "sg:city":"Houston",
    "sg:classifiers":[
        {
            "category":"Professional",
            "subcategory":"Business Services",
            "type":"Services"
        }
    ],
    "sg:phone":"+1 713 868 0084",
    "sg:postcode":"77007",
    "sg:province":"TX",
    "wof:name":"M Mitchell Interiors Inc",
    "wof:placetype":"venue"
},
  "geometry": {"coordinates":[-95.41928799999999,29.773717],"type":"Point"}
}