{
  "type": "Feature",
  "properties": {
    "iso:country":"US",
    "sg:address":"19435 Haude Rd",
    "sg:city":"Spring",
    "sg:classifiers":[
        {
            "category":"Manufacturing",
            "subcategory":"Printing",
            "type":"Manufacturing & Wholesale Goods"
        }
    ],
    "sg:phone":"+1 281 353 7252",
    "sg:postcode":"77388",
    "sg:province":"TX",
    "sg:tags":[
        "business",
        "form",
        "system"
    ],
    "wof:name":"CSM Business Svc",
    "wof:placetype":"venue"
},
  "geometry": {"coordinates":[-95.456959,30.048726],"type":"Point"}
}