{
  "type": "Feature",
  "properties": {
    "iso:country":"US",
    "sg:address":"608 W Monroe St Ste B",
    "sg:city":"Austin",
    "sg:classifiers":[
        {
            "category":"Professional",
            "type":"Services"
        }
    ],
    "sg:phone":"+1 512 448 3005",
    "sg:postcode":"78704",
    "sg:province":"TX",
    "sg:tags":[
        "processing",
        "data"
    ],
    "wof:name":"N G H Enterprises L L C",
    "wof:placetype":"venue"
},
  "geometry": {"coordinates":[-97.756212,30.249789],"type":"Point"}
}