{
  "type": "Feature",
  "properties": {
    "iso:country":"US",
    "sg:address":"228 Martha St",
    "sg:city":"Euless",
    "sg:classifiers":[
        {
            "category":"Personal",
            "subcategory":"Beauty Salon",
            "type":"Services"
        }
    ],
    "sg:phone":"+1 817 545 6300",
    "sg:postcode":"76040",
    "sg:province":"TX",
    "sg:tags":[
        "hair",
        "shop",
        "stylist"
    ],
    "wof:name":"Nuevo Look Beauty Salon",
    "wof:placetype":"venue"
},
  "geometry": {"coordinates":[-97.086249,32.835308],"type":"Point"}
}