{
  "type": "Feature",
  "properties": {
    "iso:country":"US",
    "sg:address":"2101 5th Ave",
    "sg:city":"Port Arthur",
    "sg:classifiers":[
        {
            "category":"Manufacturing",
            "subcategory":"Metals",
            "type":"Manufacturing & Wholesale Goods"
        }
    ],
    "sg:phone":"+1 409 985 5231",
    "sg:postcode":"77642",
    "sg:province":"TX",
    "sg:tags":[
        "steel"
    ],
    "wof:name":"Pat Tank",
    "wof:placetype":"venue"
},
  "geometry": {"coordinates":[-93.92986999999999,29.907024],"type":"Point"}
}