{
  "type": "Feature",
  "properties": {
    "iso:country":"US",
    "sg:address":"1704 Military Pkwy",
    "sg:city":"Mesquite",
    "sg:classifiers":[
        {
            "category":"Restaurant",
            "type":"Food & Drink"
        }
    ],
    "sg:phone":"+1 972 285 1300",
    "sg:postcode":"75149",
    "sg:province":"TX",
    "sg:tags":[
        "eating"
    ],
    "wof:name":"Catfish Station",
    "wof:placetype":"venue"
},
  "geometry": {"coordinates":[-96.624132,32.767741],"type":"Point"}
}