{
  "type": "Feature",
  "properties": {
    "iso:country":"US",
    "sg:address":"3824 Harlanwood Dr",
    "sg:city":"Fort Worth",
    "sg:classifiers":[
        {
            "category":"Real Estate",
            "subcategory":"Real Estate Operator",
            "type":"Services"
        }
    ],
    "sg:phone":"+1 817 921 4400",
    "sg:postcode":"76109",
    "sg:province":"TX",
    "sg:tags":[
        "building",
        "nonresidential"
    ],
    "wof:name":"Mdd Property Company Ltd",
    "wof:placetype":"venue"
},
  "geometry": {"coordinates":[-97.376165,32.706653],"type":"Point"}
}