{
  "type": "Feature",
  "properties": {
    "iso:country":"US",
    "sg:address":"6950 W Sam Houston Pkwy N",
    "sg:city":"Houston",
    "sg:classifiers":[
        {
            "category":"Manufacturing",
            "subcategory":"Metals",
            "type":"Manufacturing & Wholesale Goods"
        },
        {
            "category":"Manufacturing",
            "subcategory":"Building Materials",
            "type":"Manufacturing & Wholesale Goods"
        }
    ],
    "sg:phone":"+1 713 937 0600",
    "sg:postcode":"77041",
    "sg:province":"TX",
    "sg:tags":[
        "tubing",
        "pipe-wholesale",
        "manufacturer"
    ],
    "wof:name":"Act Fabrication, Inc.",
    "wof:placetype":"venue"
},
  "geometry": {"coordinates":[-95.563626,29.87312],"type":"Point"}
}