{
  "type": "Feature",
  "properties": {
    "iso:country":"US",
    "sg:address":"4311 N 28th Ln",
    "sg:city":"Mcallen",
    "sg:classifiers":[
        {
            "category":"Building & Trades",
            "subcategory":"Construction",
            "type":"Services"
        }
    ],
    "sg:phone":"+1 956 686 1524",
    "sg:postcode":"78504",
    "sg:province":"TX",
    "sg:tags":[
        "residential"
    ],
    "wof:name":"Northstar Homes",
    "wof:placetype":"venue"
},
  "geometry": {"coordinates":[-98.24618100000001,26.247011],"type":"Point"}
}