{
  "type": "Feature",
  "properties": {
    "iso:country":"US",
    "sg:address":"6750 W Loop Fwy",
    "sg:city":"Bellaire",
    "sg:classifiers":[
        {
            "category":"Real Estate",
            "subcategory":"Real Estate Agent",
            "type":"Services"
        }
    ],
    "sg:phone":"+1 713 661 3008",
    "sg:postcode":"77401",
    "sg:province":"TX",
    "wof:name":"Avalon Media",
    "wof:placetype":"venue"
},
  "geometry": {"coordinates":[-95.4598,29.705779],"type":"Point"}
}