{
  "type": "Feature",
  "properties": {
    "iso:country":"US",
    "sg:address":"1201 Barbara Jordan Blvd #51",
    "sg:city":"Austin",
    "sg:classifiers":[
        {
            "category":"Personal",
            "subcategory":"Nail Salon",
            "type":"Services"
        }
    ],
    "sg:phone":"+1 512 474 0888",
    "sg:postcode":"78723",
    "sg:province":"TX",
    "wof:name":"Great Nails",
    "wof:placetype":"venue"
},
  "geometry": {"coordinates":[-97.708454,30.305818],"type":"Point"}
}