{
  "type": "Feature",
  "properties": {
    "iso:country":"US",
    "sg:address":"4313 Silverthorne Dr",
    "sg:city":"Mesquite",
    "sg:classifiers":[
        {
            "category":"Shopping",
            "subcategory":"Party Supplies",
            "type":"Retail Goods"
        }
    ],
    "sg:phone":"+1 972 557 7970",
    "sg:postcode":"75180",
    "sg:province":"TX",
    "sg:tags":[
        "rental"
    ],
    "wof:name":"Bouncers Unlimited",
    "wof:placetype":"venue"
},
  "geometry": {"coordinates":[-96.593231,32.713239],"type":"Point"}
}