{
  "type": "Feature",
  "properties": {
    "iso:country":"US",
    "sg:address":"10565 S Fm 157",
    "sg:city":"Venus",
    "sg:classifiers":[
        {
            "category":"Home & Garden",
            "subcategory":"Building Materials",
            "type":"Retail Goods"
        },
        {
            "category":"Building & Trades",
            "subcategory":"Construction",
            "type":"Services"
        }
    ],
    "sg:phone":"+1 972 296 5377",
    "sg:postcode":"76084",
    "sg:province":"TX",
    "sg:tags":[
        "door",
        "altering",
        "contractor",
        "garage",
        "opener",
        "remodeling"
    ],
    "wof:name":"Arlington Garage Doors",
    "wof:placetype":"venue"
},
  "geometry": {"coordinates":[-97.04881899999999,32.352479],"type":"Point"}
}