{
  "type": "Feature",
  "properties": {
    "iso:country":"US",
    "sg:address":"305 N Corpus Christi St",
    "sg:city":"Rio Grande City",
    "sg:classifiers":[
        {
            "category":"Building & Trades",
            "subcategory":"Plumbing",
            "type":"Services"
        }
    ],
    "sg:phone":"+1 956 716 6411",
    "sg:postcode":"78582",
    "sg:province":"TX",
    "sg:tags":[
        "conditioning",
        "air",
        "system",
        "contractor"
    ],
    "wof:name":"Colair Inc",
    "wof:placetype":"venue"
},
  "geometry": {"coordinates":[-98.818596,26.381166],"type":"Point"}
}