{
  "type": "Feature",
  "properties": {
    "iso:country":"US",
    "sg:address":"1604 W US Hwy 380",
    "sg:city":"Decatur",
    "sg:classifiers":[
        {
            "category":"Government",
            "subcategory":"Office",
            "type":"Public Place"
        }
    ],
    "sg:phone":"+1 940 627 3531",
    "sg:postcode":"76234",
    "sg:province":"TX",
    "sg:tags":[
        "development",
        "rural"
    ],
    "wof:name":"Rural Development",
    "wof:placetype":"venue"
},
  "geometry": {"coordinates":[-97.609109,33.234422],"type":"Point"}
}