{
  "type": "Feature",
  "properties": {
    "iso:country":"US",
    "sg:address":"301 W Columbus St",
    "sg:city":"West",
    "sg:classifiers":[
        {
            "category":"Government",
            "subcategory":"Post Office",
            "type":"Public Place"
        }
    ],
    "sg:phone":"+1 254 826 5731",
    "sg:postcode":"76691",
    "sg:province":"TX",
    "sg:tags":[
        "postal",
        "us"
    ],
    "wof:name":"US Post Office",
    "wof:placetype":"venue"
},
  "geometry": {"coordinates":[-97.093673,31.803894],"type":"Point"}
}