{
  "type": "Feature",
  "properties": {
    "iso:country":"US",
    "sg:address":"25211 Grogans Mill Rd",
    "sg:city":"Spring",
    "sg:classifiers":[
        {
            "category":"Professional",
            "subcategory":"Lawyer & Legal Services",
            "type":"Services"
        }
    ],
    "sg:phone":"+1 281 367 5955",
    "sg:postcode":"77380",
    "sg:province":"TX",
    "sg:tags":[
        "attorney"
    ],
    "sg:website":"www.stirman.com",
    "wof:name":"Stirman Kennedy & Hird PC",
    "wof:placetype":"venue"
},
  "geometry": {"coordinates":[-95.45715,30.128972],"type":"Point"}
}