{
  "type": "Feature",
  "properties": {
    "iso:country":"US",
    "sg:address":"3206 Reid Dr",
    "sg:city":"Corpus Christi",
    "sg:classifiers":[
        {
            "category":"Real Estate",
            "subcategory":"Architect",
            "type":"Services"
        }
    ],
    "sg:phone":"+1 361 854 0151",
    "sg:postcode":"78404",
    "sg:province":"TX",
    "sg:tags":[
        "architectural"
    ],
    "wof:name":"Custom Plan Service",
    "wof:placetype":"venue"
},
  "geometry": {"coordinates":[-97.391637,27.755717],"type":"Point"}
}