{
  "type": "Feature",
  "properties": {
    "iso:country":"US",
    "sg:address":"7206 Thurston St",
    "sg:city":"Dallas",
    "sg:classifiers":[
        {
            "category":"Building & Trades",
            "subcategory":"Construction",
            "type":"Services"
        }
    ],
    "sg:phone":"+1 214 357 1366",
    "sg:postcode":"75235",
    "sg:province":"TX",
    "sg:tags":[
        "contractor"
    ],
    "wof:name":"Rodriquez Home Repair",
    "wof:placetype":"venue"
},
  "geometry": {"coordinates":[-96.849053,32.831966],"type":"Point"}
}