{
  "type": "Feature",
  "properties": {
    "iso:country":"US",
    "sg:address":"7811 S Cooper St",
    "sg:city":"Arlington",
    "sg:classifiers":[
        {
            "category":"Personal",
            "subcategory":"Beauty Salon",
            "type":"Services"
        }
    ],
    "sg:phone":"+1 817 465 9555",
    "sg:postcode":"76001",
    "sg:province":"TX",
    "sg:tags":[
        "shop"
    ],
    "wof:name":"Nature Nails",
    "wof:placetype":"venue"
},
  "geometry": {"coordinates":[-97.138313,32.618222],"type":"Point"}
}