{
  "type": "Feature",
  "properties": {
    "iso:country":"US",
    "sg:address":"4542 Bronze Way",
    "sg:city":"Dallas",
    "sg:classifiers":[
        {
            "category":"Communications",
            "subcategory":"Film & Video Production",
            "type":"Services"
        }
    ],
    "sg:phone":"+1 214 339 7032",
    "sg:postcode":"75236",
    "sg:province":"TX",
    "sg:tags":[
        "distribution",
        "power"
    ],
    "wof:name":"GE",
    "wof:placetype":"venue"
},
  "geometry": {"coordinates":[-96.896278,32.687177],"type":"Point"}
}