{
  "type": "Feature",
  "properties": {
    "iso:country":"US",
    "sg:address":"602 Titus St Ste 140",
    "sg:city":"Gilmer",
    "sg:classifiers":[
        {
            "category":"Health Services",
            "subcategory":"Doctor",
            "type":"Services"
        }
    ],
    "sg:phone":"+1 903 841 7300",
    "sg:postcode":"75644",
    "sg:province":"TX",
    "sg:tags":[
        "medicine",
        "physician",
        "practice",
        "surgeons",
        "family"
    ],
    "wof:name":"E T M C Physicians Clinics",
    "wof:placetype":"venue"
},
  "geometry": {"coordinates":[-94.944412,32.733753],"type":"Point"}
}