{
  "type": "Feature",
  "properties": {
    "iso:country":"US",
    "sg:address":"7227 Preston Rd",
    "sg:city":"Frisco",
    "sg:classifiers":[
        {
            "category":"Health Services",
            "subcategory":"Doctor",
            "type":"Services"
        }
    ],
    "sg:phone":"+1 972 377 7878",
    "sg:postcode":"75034",
    "sg:province":"TX",
    "sg:tags":[
        "clinic"
    ],
    "wof:name":"Primacare Medical Ctr",
    "wof:placetype":"venue"
},
  "geometry": {"coordinates":[-96.80479099999999,33.140717],"type":"Point"}
}