{
  "type": "Feature",
  "properties": {
    "iso:country":"US",
    "sg:address":"10207 N Central Expwy",
    "sg:city":"Dallas",
    "sg:classifiers":[
        {
            "category":"Restaurant",
            "type":"Food & Drink"
        }
    ],
    "sg:phone":"+1 214 739 3436",
    "sg:postcode":"75231",
    "sg:province":"TX",
    "sg:tags":[
        "thai",
        "asian",
        "pan"
    ],
    "sg:website":"www.bangkokthaicuisinedallas.com",
    "wof:name":"Bangkok Thai Cuisine",
    "wof:placetype":"venue"
},
  "geometry": {"coordinates":[-96.770481,32.885607],"type":"Point"}
}