{
  "type": "Feature",
  "properties": {
    "iso:country":"US",
    "sg:address":"2829 Hiawatha Trl",
    "sg:city":"Fort Worth",
    "sg:classifiers":[
        {
            "category":"Building & Trades",
            "subcategory":"Construction",
            "type":"Services"
        }
    ],
    "sg:phone":"+1 817 237 6847",
    "sg:postcode":"76135",
    "sg:province":"TX",
    "sg:tags":[
        "repairing",
        "remodeling",
        "contractor"
    ],
    "wof:name":"Gilbreath Tile Co",
    "wof:placetype":"venue"
},
  "geometry": {"coordinates":[-97.451095,32.799032],"type":"Point"}
}