{
  "type": "Feature",
  "properties": {
    "iso:country":"US",
    "sg:address":"1338 E Parkerville Rd",
    "sg:city":"Desoto",
    "sg:classifiers":[
        {
            "category":"Professional",
            "subcategory":"Secretarial Services",
            "type":"Services"
        }
    ],
    "sg:phone":"+1 972 230 1880",
    "sg:postcode":"75115",
    "sg:province":"TX",
    "sg:tags":[
        "resume"
    ],
    "wof:name":"Resume Writing & Career Cnslng",
    "wof:placetype":"venue"
},
  "geometry": {"coordinates":[-96.827387,32.575204],"type":"Point"}
}