{
  "type": "Feature",
  "properties": {
    "iso:country":"US",
    "sg:address":"1908 Park Ave",
    "sg:city":"Victoria",
    "sg:classifiers":[
        {
            "category":"Building & Trades",
            "subcategory":"Landscaping Services",
            "type":"Services"
        }
    ],
    "sg:phone":"+1 361 572 3652",
    "sg:postcode":"77901",
    "sg:province":"TX",
    "wof:name":"Richard Alexander Lind",
    "wof:placetype":"venue"
},
  "geometry": {"coordinates":[-96.984405,28.81607],"type":"Point"}
}