{
  "type": "Feature",
  "properties": {
    "iso:country":"US",
    "sg:address":"122 N 77 Sunshine Strip",
    "sg:city":"Harlingen",
    "sg:classifiers":[
        {
            "category":"Personal",
            "subcategory":"Beauty Salon",
            "type":"Services"
        },
        {
            "category":"Personal",
            "subcategory":"Barber",
            "type":"Services"
        }
    ],
    "sg:phone":"+1 956 423 6523",
    "sg:postcode":"78550",
    "sg:province":"TX",
    "sg:tags":[
        "hair",
        "stylist"
    ],
    "wof:name":"Minnie's Hair Designs",
    "wof:placetype":"venue"
},
  "geometry": {"coordinates":[-97.67997,26.192988],"type":"Point"}
}