{
  "type": "Feature",
  "properties": {
    "iso:country":"US",
    "sg:address":"2609 43rd St",
    "sg:city":"Lubbock",
    "sg:classifiers":[
        {
            "category":"Building & Trades",
            "subcategory":"Construction",
            "type":"Services"
        }
    ],
    "sg:phone":"+1 806 780 4970",
    "sg:postcode":"79413",
    "sg:province":"TX",
    "sg:tags":[
        "house"
    ],
    "wof:name":"L&M Remodeling & Maintenance",
    "wof:placetype":"venue"
},
  "geometry": {"coordinates":[-101.874617,33.555034],"type":"Point"}
}