{
  "type": "Feature",
  "properties": {
    "iso:country":"US",
    "sg:address":"509 State School Rd",
    "sg:city":"Gatesville",
    "sg:classifiers":[
        {
            "category":"Shopping",
            "subcategory":"Used Merchandise",
            "type":"Retail Goods"
        }
    ],
    "sg:phone":"+1 254 865 9600",
    "sg:postcode":"76528",
    "sg:province":"TX",
    "wof:name":"R & R Ventures",
    "wof:placetype":"venue"
},
  "geometry": {"coordinates":[-97.743791,31.458362],"type":"Point"}
}