{
  "type": "Feature",
  "properties": {
    "iso:country":"US",
    "sg:address":"4814 Mc Dermed Dr",
    "sg:city":"Houston",
    "sg:classifiers":[
        {
            "category":"Professional",
            "subcategory":"Employment Agencies",
            "type":"Services"
        }
    ],
    "sg:phone":"+1 713 816 9793",
    "sg:postcode":"77035",
    "sg:province":"TX",
    "sg:tags":[
        "help",
        "supply"
    ],
    "wof:name":"Premier Maid Service",
    "wof:placetype":"venue"
},
  "geometry": {"coordinates":[-95.460196,29.669031],"type":"Point"}
}