{
  "type": "Feature",
  "properties": {
    "iso:country":"US",
    "sg:address":"7504 Fossil Garden Dr",
    "sg:city":"Arlington",
    "sg:classifiers":[
        {
            "category":"Organizations",
            "subcategory":"Religious Organization",
            "type":"Services"
        }
    ],
    "sg:phone":"+1 817 784 3930",
    "sg:postcode":"76002",
    "sg:province":"TX",
    "wof:name":"Koinonia Baptist Church",
    "wof:placetype":"venue"
},
  "geometry": {"coordinates":[-97.099896,32.621662],"type":"Point"}
}