{
  "type": "Feature",
  "properties": {
    "iso:country":"US",
    "sg:address":"12271 Plano Rd",
    "sg:city":"Dallas",
    "sg:classifiers":[
        {
            "category":"Retail",
            "subcategory":"Auto Repair",
            "type":"Services"
        }
    ],
    "sg:phone":"+1 972 792 0802",
    "sg:postcode":"75243",
    "sg:province":"TX",
    "sg:tags":[
        "repairing",
        "automobile",
        "general"
    ],
    "wof:name":"L T Auto Repair",
    "wof:placetype":"venue"
},
  "geometry": {"coordinates":[-96.70052200000001,32.913303],"type":"Point"}
}