{
  "type": "Feature",
  "properties": {
    "iso:country":"US",
    "sg:address":"11398 Harry Hines Blvd",
    "sg:city":"Dallas",
    "sg:classifiers":[
        {
            "category":"Shopping",
            "subcategory":"Adult",
            "type":"Retail Goods"
        }
    ],
    "sg:phone":"+1 972 243 9220",
    "sg:postcode":"75229",
    "sg:province":"TX",
    "sg:tags":[
        "entertainment"
    ],
    "wof:name":"Silk & Satin",
    "wof:placetype":"venue"
},
  "geometry": {"coordinates":[-96.890857,32.896169],"type":"Point"}
}