{
  "type": "Feature",
  "properties": {
    "iso:country":"US",
    "sg:address":"4750 North Jupiter Rd Suit 106",
    "sg:city":"Garland",
    "sg:classifiers":[
        {
            "category":"Personal",
            "subcategory":"Barber",
            "type":"Services"
        }
    ],
    "sg:phone":"+1 972 530 7779",
    "sg:postcode":"75044",
    "sg:province":"TX",
    "wof:name":"Peter's Barber Shop",
    "wof:placetype":"venue"
},
  "geometry": {"coordinates":[-96.682,32.959616],"type":"Point"}
}