{
  "type": "Feature",
  "properties": {
    "iso:country":"US",
    "sg:address":"502 E Columbia St",
    "sg:city":"San Augustine",
    "sg:classifiers":[
        {
            "category":"Organizations",
            "subcategory":"Religious Organization",
            "type":"Services"
        }
    ],
    "sg:phone":"+1 936 275 2326",
    "sg:postcode":"75972",
    "sg:province":"TX",
    "wof:name":"First Bptst Chrch San Agustine",
    "wof:placetype":"venue"
},
  "geometry": {"coordinates":[-94.1057,31.529995],"type":"Point"}
}