{
  "type": "Feature",
  "properties": {
    "iso:country":"US",
    "sg:address":"623 Brook Hollow Dr",
    "sg:city":"Conroe",
    "sg:classifiers":[
        {
            "category":"Professional",
            "type":"Services"
        }
    ],
    "sg:phone":"+1 936 321 4421",
    "sg:postcode":"77385",
    "sg:province":"TX",
    "wof:name":"Kokoro Inc",
    "wof:placetype":"venue"
},
  "geometry": {"coordinates":[-95.444862,30.230674],"type":"Point"}
}