{
  "type": "Feature",
  "properties": {
    "iso:country":"US",
    "sg:address":"5409 Ponciana Drive",
    "sg:city":"Austin",
    "sg:classifiers":[
        {
            "category":"Social Services",
            "subcategory":"Child Care",
            "type":"Services"
        }
    ],
    "sg:phone":"+1 512 441 6016",
    "sg:postcode":"78744",
    "sg:province":"TX",
    "sg:tags":[
        "day"
    ],
    "sg:website":"www.eackids.org",
    "wof:name":"Extend-A-Care For Kids",
    "wof:placetype":"venue"
},
  "geometry": {"coordinates":[-97.755351,30.198201],"type":"Point"}
}