{
  "type": "Feature",
  "properties": {
    "iso:country":"US",
    "sg:address":"13834 A la Entrada St",
    "sg:city":"Corpus Christi",
    "sg:classifiers":[
        {
            "category":"Restaurant",
            "type":"Food & Drink"
        }
    ],
    "sg:phone":"+1 361 949 7703",
    "sg:postcode":"78418",
    "sg:province":"TX",
    "wof:name":"Pier 99",
    "wof:placetype":"venue"
},
  "geometry": {"coordinates":[-97.232337,27.623743],"type":"Point"}
}