{
  "type": "Feature",
  "properties": {
    "iso:country":"US",
    "sg:address":"113 Timber Trl",
    "sg:city":"Longview",
    "sg:classifiers":[
        {
            "category":"Professional",
            "type":"Services"
        }
    ],
    "sg:phone":"+1 903 297 1431",
    "sg:postcode":"75605",
    "sg:province":"TX",
    "wof:name":"Texas Fire Svc",
    "wof:placetype":"venue"
},
  "geometry": {"coordinates":[-94.792287,32.544368],"type":"Point"}
}