{
  "type": "Feature",
  "properties": {
    "iso:country":"US",
    "sg:address":"1013 James St",
    "sg:city":"Deer Park",
    "sg:classifiers":[
        {
            "category":"Shopping",
            "subcategory":"Gifts & Souvenirs",
            "type":"Retail Goods"
        }
    ],
    "sg:phone":"+1 281 479 0384",
    "sg:postcode":"77536",
    "sg:province":"TX",
    "wof:name":"All Season Screen Printing",
    "wof:placetype":"venue"
},
  "geometry": {"coordinates":[-95.120137,29.702448],"type":"Point"}
}