{
  "type": "Feature",
  "properties": {
    "iso:country":"US",
    "sg:address":"8406 Oak Stream St",
    "sg:city":"Dallas",
    "sg:classifiers":[
        {
            "category":"Building & Trades",
            "subcategory":"Construction",
            "type":"Services"
        }
    ],
    "sg:phone":"+1 214 349 6620",
    "sg:postcode":"75243",
    "sg:province":"TX",
    "sg:tags":[
        "designer",
        "dealer",
        "pool",
        "swimming"
    ],
    "wof:name":"Tropical Pools Of Dallas",
    "wof:placetype":"venue"
},
  "geometry": {"coordinates":[-96.725995,32.894959],"type":"Point"}
}