{
  "type": "Feature",
  "properties": {
    "iso:country":"US",
    "sg:address":"4828 S Broadway Ave # 166",
    "sg:city":"Tyler",
    "sg:classifiers":[
        {
            "category":"Transit Center",
            "subcategory":"Passenger",
            "type":"Transportation"
        },
        {
            "category":"Local Transit",
            "type":"Transportation"
        }
    ],
    "sg:phone":"+1 903 597 9325",
    "sg:postcode":"75703",
    "sg:province":"TX",
    "sg:tags":[
        "line",
        "public"
    ],
    "wof:name":"East Texas Limo & Shuttle",
    "wof:placetype":"venue"
},
  "geometry": {"coordinates":[-95.300791,32.29877],"type":"Point"}
}