{
  "type": "Feature",
  "properties": {
    "iso:country":"US",
    "sg:address":"2700 Belhaven Dr",
    "sg:city":"Mesquite",
    "sg:classifiers":[
        {
            "category":"Freight",
            "type":"Transportation"
        }
    ],
    "sg:phone":"+1 972 681 4747",
    "sg:postcode":"75150",
    "sg:province":"TX",
    "sg:tags":[
        "trucking"
    ],
    "wof:name":"Cecil Wilkins Trucking",
    "wof:placetype":"venue"
},
  "geometry": {"coordinates":[-96.642202,32.800083],"type":"Point"}
}