{
  "type": "Feature",
  "properties": {
    "iso:country":"US",
    "sg:address":"6802 Castile de Oro",
    "sg:city":"San Antonio",
    "sg:classifiers":[
        {
            "category":"Social Services",
            "subcategory":"Adult Care",
            "type":"Services"
        }
    ],
    "sg:phone":"+1 210 654 3521",
    "sg:postcode":"78239",
    "sg:province":"TX",
    "sg:tags":[
        "residential"
    ],
    "wof:name":"Castile De Oro Personal Care",
    "wof:placetype":"venue"
},
  "geometry": {"coordinates":[-98.350418,29.500628],"type":"Point"}
}