{
  "type": "Feature",
  "properties": {
    "iso:country":"US",
    "sg:address":"101 Munger St",
    "sg:city":"Pasadena",
    "sg:classifiers":[
        {
            "category":"Wholesale",
            "subcategory":"Machinery & Supplies",
            "type":"Manufacturing & Wholesale Goods"
        }
    ],
    "sg:phone":"+1 713 477 1109",
    "sg:postcode":"77506",
    "sg:province":"TX",
    "sg:tags":[
        "equipment",
        "printing"
    ],
    "wof:name":"Discount Graphics Supply",
    "wof:placetype":"venue"
},
  "geometry": {"coordinates":[-95.21059700000001,29.71142],"type":"Point"}
}