{
  "type": "Feature",
  "properties": {
    "iso:country":"US",
    "sg:address":"2008 W Beauregard Ave",
    "sg:city":"San Angelo",
    "sg:classifiers":[
        {
            "category":"Food & Beverages",
            "subcategory":"Groceries & Convenience Stores",
            "type":"Retail Goods"
        }
    ],
    "sg:phone":"+1 325 947 4863",
    "sg:postcode":"76901",
    "sg:province":"TX",
    "sg:tags":[
        "market"
    ],
    "wof:name":"A-1 Market",
    "wof:placetype":"venue"
},
  "geometry": {"coordinates":[-100.46378300000001,31.451583],"type":"Point"}
}