{
  "type": "Feature",
  "properties": {
    "iso:country":"US",
    "sg:address":"11511 Fernald Ave",
    "sg:city":"Dallas",
    "sg:classifiers":[
        {
            "category":"Building & Trades",
            "subcategory":"Construction",
            "type":"Services"
        }
    ],
    "sg:phone":"+1 214 460 0021",
    "sg:postcode":"75218",
    "sg:province":"TX",
    "sg:tags":[
        "interior",
        "residential",
        "painting",
        "exterior"
    ],
    "wof:name":"Hernandez Painting",
    "wof:placetype":"venue"
},
  "geometry": {"coordinates":[-96.679096,32.86004],"type":"Point"}
}