{
  "type": "Feature",
  "properties": {
    "iso:country":"US",
    "sg:address":"206 Carl Ship Dr",
    "sg:city":"Liberty Hill",
    "sg:classifiers":[
        {
            "category":"Professional",
            "subcategory":"Computer Services",
            "type":"Services"
        }
    ],
    "sg:phone":"+1 512 515 7974",
    "sg:postcode":"78642",
    "sg:province":"TX",
    "wof:name":"Compamerica Kar City",
    "wof:placetype":"venue"
},
  "geometry": {"coordinates":[-97.915182,30.667061],"type":"Point"}
}