{
  "type": "Feature",
  "properties": {
    "iso:country":"US",
    "sg:address":"3306 W Shady Grove Rd",
    "sg:city":"Irving",
    "sg:classifiers":[
        {
            "category":"Retail",
            "subcategory":"Auto Repair",
            "type":"Services"
        }
    ],
    "sg:phone":"+1 972 986 9224",
    "sg:postcode":"75060",
    "sg:province":"TX",
    "sg:tags":[
        "general"
    ],
    "wof:name":"Deans Automotive Service",
    "wof:placetype":"venue"
},
  "geometry": {"coordinates":[-96.991146,32.803783],"type":"Point"}
}