{
  "type": "Feature",
  "properties": {
    "iso:country":"US",
    "sg:address":"3698 N Bryant Blvd",
    "sg:city":"San Angelo",
    "sg:classifiers":[
        {
            "category":"Wholesale",
            "subcategory":"Machinery & Supplies",
            "type":"Manufacturing & Wholesale Goods"
        }
    ],
    "sg:phone":"+1 325 655 0649",
    "sg:postcode":"76903",
    "sg:province":"TX",
    "sg:tags":[
        "pump"
    ],
    "wof:name":"Austin Pump & Supply Co",
    "wof:placetype":"venue"
},
  "geometry": {"coordinates":[-100.478754,31.500491],"type":"Point"}
}