{
  "type": "Feature",
  "properties": {
    "iso:country":"US",
    "sg:address":"212 W Allday St",
    "sg:city":"Atlanta",
    "sg:classifiers":[
        {
            "category":"Retail",
            "subcategory":"Car Wash",
            "type":"Services"
        }
    ],
    "sg:phone":"+1 903 796 2358",
    "sg:postcode":"75551",
    "sg:province":"TX",
    "sg:tags":[
        "polishing",
        "washing"
    ],
    "wof:name":"Hcwh Car Care",
    "wof:placetype":"venue"
},
  "geometry": {"coordinates":[-94.168617,33.119587],"type":"Point"}
}