{
  "type": "Feature",
  "properties": {
    "iso:country":"US",
    "sg:address":"318 Gershwin Dr",
    "sg:city":"Houston",
    "sg:classifiers":[
        {
            "category":"Professional",
            "subcategory":"Business Services",
            "type":"Services"
        }
    ],
    "sg:phone":"+1 713 467 9701",
    "sg:postcode":"77079",
    "sg:province":"TX",
    "wof:name":"Divine Discoveries",
    "wof:placetype":"venue"
},
  "geometry": {"coordinates":[-95.56572799999999,29.765931],"type":"Point"}
}