{
  "type": "Feature",
  "properties": {
    "iso:country":"US",
    "sg:address":"4719 Broadway St",
    "sg:city":"Galveston",
    "sg:classifiers":[
        {
            "category":"Wholesale",
            "subcategory":"Machinery & Supplies",
            "type":"Manufacturing & Wholesale Goods"
        }
    ],
    "sg:phone":"+1 409 765 7050",
    "sg:postcode":"77551",
    "sg:province":"TX",
    "sg:tags":[
        "equipment",
        "retail",
        "establishment"
    ],
    "wof:name":"Solid Gold Beauty Supply",
    "wof:placetype":"venue"
},
  "geometry": {"coordinates":[-94.82044399999999,29.292548],"type":"Point"}
}