{
  "type": "Feature",
  "properties": {
    "iso:country":"US",
    "sg:address":"222 E Hamilton St",
    "sg:city":"Stamford",
    "sg:classifiers":[
        {
            "category":"Retail",
            "subcategory":"Repair Shop",
            "type":"Services"
        },
        {
            "category":"Building & Trades",
            "subcategory":"Plumbing",
            "type":"Services"
        }
    ],
    "sg:phone":"+1 325 773 5176",
    "sg:postcode":"79553",
    "sg:province":"TX",
    "sg:tags":[
        "household",
        "appliance",
        "system",
        "contractor",
        "refrigeration",
        "conditioning",
        "air"
    ],
    "wof:name":"Faulks Refrigeration Inc",
    "wof:placetype":"venue"
},
  "geometry": {"coordinates":[-99.801427,32.944024],"type":"Point"}
}