{
  "type": "Feature",
  "properties": {
    "iso:country":"US",
    "sg:address":"1226 W University Dr",
    "sg:city":"Edinburg",
    "sg:classifiers":[
        {
            "category":"Social Services",
            "subcategory":"Child Care",
            "type":"Services"
        }
    ],
    "sg:phone":"+1 956 292 0131",
    "sg:postcode":"78539",
    "sg:province":"TX",
    "wof:name":"Little U Learning Ctr",
    "wof:placetype":"venue"
},
  "geometry": {"coordinates":[-98.17706099999999,26.303456],"type":"Point"}
}