{
  "type": "Feature",
  "properties": {
    "iso:country":"US",
    "sg:address":"101 Oakwood Pl",
    "sg:city":"Joshua",
    "sg:classifiers":[
        {
            "category":"Building & Trades",
            "subcategory":"Locksmith",
            "type":"Services"
        }
    ],
    "sg:phone":"+1 817 717 2668",
    "sg:postcode":"76058",
    "sg:province":"TX",
    "sg:tags":[
        "key"
    ],
    "wof:name":"Always Affective Available Emergency Locks",
    "wof:placetype":"venue"
},
  "geometry": {"coordinates":[-97.366652,32.485837],"type":"Point"}
}