{
  "type": "Feature",
  "properties": {
    "iso:country":"US",
    "sg:address":"106 Carefree Cir",
    "sg:city":"Austin",
    "sg:classifiers":[
        {
            "category":"Professional",
            "subcategory":"Business Services",
            "type":"Services"
        }
    ],
    "sg:phone":"+1 512 261 9272",
    "sg:postcode":"78734",
    "sg:province":"TX",
    "wof:name":"GWC Enterprises LLC",
    "wof:placetype":"venue"
},
  "geometry": {"coordinates":[-97.96062999999999,30.369388],"type":"Point"}
}