{
  "type": "Feature",
  "properties": {
    "iso:country":"US",
    "sg:address":"3007 Longhorn Blvd. Suite 102",
    "sg:city":"Austin",
    "sg:classifiers":[
        {
            "category":"Professional",
            "type":"Services"
        }
    ],
    "sg:phone":"+1 512 327 3277",
    "sg:postcode":"78731",
    "sg:province":"TX",
    "sg:website":"www.aatg.net",
    "wof:name":"A & A Telecom Group",
    "wof:placetype":"venue"
},
  "geometry": {"coordinates":[-97.729005,30.381477],"type":"Point"}
}