{
  "type": "Feature",
  "properties": {
    "iso:country":"US",
    "sg:address":"1515 Russell Dr",
    "sg:city":"Brownsville",
    "sg:classifiers":[
        {
            "category":"Building & Trades",
            "subcategory":"Construction",
            "type":"Services"
        }
    ],
    "sg:phone":"+1 956 546 1459",
    "sg:postcode":"78520",
    "sg:province":"TX",
    "sg:tags":[
        "control",
        "corrosion",
        "contractor"
    ],
    "wof:name":"Corrosion Busters",
    "wof:placetype":"venue"
},
  "geometry": {"coordinates":[-97.513426,25.928115],"type":"Point"}
}