{
  "type": "Feature",
  "properties": {
    "iso:country":"US",
    "sg:address":"1501 E Crosby Rd",
    "sg:city":"Carrollton",
    "sg:classifiers":[
        {
            "category":"Social Services",
            "subcategory":"Child Care",
            "type":"Services"
        },
        {
            "category":"Education",
            "subcategory":"Preschool",
            "type":"Public Place"
        },
        {
            "category":"Education",
            "subcategory":"School",
            "type":"Public Place"
        }
    ],
    "sg:phone":"+1 972 245 7331",
    "sg:postcode":"75006",
    "sg:province":"TX",
    "sg:tags":[
        "elementary",
        "day"
    ],
    "wof:name":"Kiddie Kollege Child Care Cntr",
    "wof:placetype":"venue"
},
  "geometry": {"coordinates":[-96.89969600000001,32.949299],"type":"Point"}
}