{
  "type": "Feature",
  "properties": {
    "iso:country":"US",
    "sg:address":"1201 E 15th St",
    "sg:city":"Plano",
    "sg:classifiers":[
        {
            "category":"Building & Trades",
            "subcategory":"Construction",
            "type":"Services"
        }
    ],
    "sg:phone":"+1 972 424 1246",
    "sg:postcode":"75074",
    "sg:province":"TX",
    "sg:tags":[
        "concrete",
        "contractor"
    ],
    "wof:name":"Pool Craft",
    "wof:placetype":"venue"
},
  "geometry": {"coordinates":[-96.696365,33.019691],"type":"Point"}
}