{
  "type": "Feature",
  "properties": {
    "iso:country":"US",
    "sg:address":"6550 Fannin St Ste 2201",
    "sg:city":"Houston",
    "sg:classifiers":[
        {
            "category":"Health Services",
            "subcategory":"Doctor",
            "type":"Services"
        }
    ],
    "sg:phone":"+1 713 797 9498",
    "sg:postcode":"77030",
    "sg:province":"TX",
    "sg:tags":[
        "obstetrician",
        "gynecologist"
    ],
    "wof:name":"University OB-Gyn of Texas",
    "wof:placetype":"venue"
},
  "geometry": {"coordinates":[-95.399261,29.709947],"type":"Point"}
}