{
  "type": "Feature",
  "properties": {
    "iso:country":"US",
    "sg:address":"6523 Turtlewood St",
    "sg:city":"Houston",
    "sg:classifiers":[
        {
            "category":"Building & Trades",
            "subcategory":"Cleaning & Sanitation",
            "type":"Services"
        }
    ],
    "sg:phone":"+1 281 459 1236",
    "sg:postcode":"77049",
    "sg:province":"TX",
    "sg:tags":[
        "maintenance"
    ],
    "wof:name":"Noris Building Cleaning Servic",
    "wof:placetype":"venue"
},
  "geometry": {"coordinates":[-95.205783,29.821385],"type":"Point"}
}