{
  "type": "Feature",
  "properties": {
    "iso:country":"US",
    "sg:address":"3151 Justin Rd",
    "sg:city":"Flower Mound",
    "sg:classifiers":[
        {
            "category":"Manufacturing",
            "subcategory":"Jewelry",
            "type":"Manufacturing & Wholesale Goods"
        },
        {
            "category":"Wholesale",
            "subcategory":"Jewelry",
            "type":"Manufacturing & Wholesale Goods"
        }
    ],
    "sg:phone":"+1 972 355 3285",
    "sg:postcode":"75028",
    "sg:province":"TX",
    "sg:tags":[
        "precious",
        "jeweler",
        "metal",
        "costume",
        "mfg"
    ],
    "wof:name":"Premier Manufacturing Co",
    "wof:placetype":"venue"
},
  "geometry": {"coordinates":[-97.078276,33.073539],"type":"Point"}
}