{
  "type": "Feature",
  "properties": {
    "iso:country":"US",
    "sg:address":"308 N 4th St",
    "sg:city":"Wills Point",
    "sg:classifiers":[
        {
            "category":"Autos & Motor Vehicles",
            "subcategory":"Fuel & Gas Station",
            "type":"Retail Goods"
        }
    ],
    "sg:phone":"+1 903 873 2700",
    "sg:postcode":"75169",
    "sg:province":"TX",
    "sg:tags":[
        "grocery",
        "station",
        "gasoline",
        "oil"
    ],
    "wof:name":"Ben's Mobil",
    "wof:placetype":"venue"
},
  "geometry": {"coordinates":[-96.007672,32.712018],"type":"Point"}
}