{
  "type": "Feature",
  "properties": {
    "iso:country":"US",
    "sg:address":"712 Lee St",
    "sg:city":"Sulphur Springs",
    "sg:classifiers":[
        {
            "category":"Organizations",
            "subcategory":"Religious Organization",
            "type":"Services"
        }
    ],
    "sg:phone":"+1 903 885 4207",
    "sg:postcode":"75482",
    "sg:province":"TX",
    "wof:name":"Shooks Chapel Methodist Church",
    "wof:placetype":"venue"
},
  "geometry": {"coordinates":[-95.61173599999999,33.119528],"type":"Point"}
}