{
  "type": "Feature",
  "properties": {
    "iso:country":"US",
    "sg:address":"6225 State Hwy 289",
    "sg:city":"Howe",
    "sg:classifiers":[
        {
            "category":"Farming",
            "subcategory":"Livestock Farm",
            "type":"Manufacturing & Wholesale Goods"
        }
    ],
    "sg:phone":"+1 903 476 5852",
    "sg:postcode":"75459",
    "sg:province":"TX",
    "sg:tags":[
        "wheat",
        "cattle"
    ],
    "wof:name":"Phillip Wildman Farm",
    "wof:placetype":"venue"
},
  "geometry": {"coordinates":[-96.708353,33.530333],"type":"Point"}
}