{
  "type": "Feature",
  "properties": {
    "iso:country":"US",
    "sg:address":"2813 Galleria Dr",
    "sg:city":"Arlington",
    "sg:classifiers":[
        {
            "category":"Organizations",
            "subcategory":"Religious Organization",
            "type":"Services"
        }
    ],
    "sg:phone":"+1 817 385 4434",
    "sg:postcode":"76011",
    "sg:province":"TX",
    "sg:tags":[
        "church"
    ],
    "wof:name":"Deliverance By Faith",
    "wof:placetype":"venue"
},
  "geometry": {"coordinates":[-97.05833699999999,32.746464],"type":"Point"}
}