{
  "type": "Feature",
  "properties": {
    "iso:country":"US",
    "sg:address":"3204 Russell Rd",
    "sg:city":"Arlington",
    "sg:classifiers":[
        {
            "category":"Professional",
            "subcategory":"Business Services",
            "type":"Services"
        }
    ],
    "sg:phone":"+1 817 483 9186",
    "sg:postcode":"76001",
    "sg:province":"TX",
    "sg:tags":[
        "recording",
        "studio"
    ],
    "wof:name":"Green Audio",
    "wof:placetype":"venue"
},
  "geometry": {"coordinates":[-97.162425,32.623679],"type":"Point"}
}