{
  "type": "Feature",
  "properties": {
    "iso:country":"US",
    "sg:address":"6920 Sheila Ln",
    "sg:city":"Burleson",
    "sg:classifiers":[
        {
            "category":"Professional",
            "type":"Services"
        }
    ],
    "sg:phone":"+1 817 447 2727",
    "sg:postcode":"76028",
    "sg:province":"TX",
    "wof:name":"Country Crafts & Woods",
    "wof:placetype":"venue"
},
  "geometry": {"coordinates":[-97.26118200000001,32.510889],"type":"Point"}
}