{
  "type": "Feature",
  "properties": {
    "iso:country":"US",
    "sg:address":"653 Oak Dr",
    "sg:city":"Hurst",
    "sg:classifiers":[
        {
            "category":"Professional",
            "subcategory":"Business Services",
            "type":"Services"
        }
    ],
    "sg:phone":"+1 817 282 6082",
    "sg:postcode":"76053",
    "sg:province":"TX",
    "sg:tags":[
        "arbitrator"
    ],
    "wof:name":"Carol Kyler",
    "wof:placetype":"venue"
},
  "geometry": {"coordinates":[-97.181307,32.821834],"type":"Point"}
}