{
  "type": "Feature",
  "properties": {
    "iso:country":"US",
    "sg:address":"2709 Danville Rd",
    "sg:city":"Kilgore",
    "sg:classifiers":[
        {
            "category":"Freight",
            "type":"Transportation"
        }
    ],
    "sg:phone":"+1 903 983 2763",
    "sg:postcode":"75662",
    "sg:province":"TX",
    "sg:tags":[
        "operator",
        "local",
        "trucking"
    ],
    "wof:name":"Haskins Trucking",
    "wof:placetype":"venue"
},
  "geometry": {"coordinates":[-94.815826,32.404823],"type":"Point"}
}