{
  "type": "Feature",
  "properties": {
    "iso:country":"US",
    "sg:address":"10409 E Miller Rd",
    "sg:city":"Dallas",
    "sg:classifiers":[
        {
            "category":"Insurance",
            "subcategory":"Insurance Agent",
            "type":"Services"
        }
    ],
    "sg:phone":"+1 214 553 6781",
    "sg:postcode":"75238",
    "sg:province":"TX",
    "wof:name":"Sears National Claims Cen",
    "wof:placetype":"venue"
},
  "geometry": {"coordinates":[-96.706434,32.894637],"type":"Point"}
}