{
  "type": "Feature",
  "properties": {
    "iso:country":"US",
    "sg:address":"3460 Southmost Rd",
    "sg:city":"Brownsville",
    "sg:classifiers":[
        {
            "category":"Home & Garden",
            "subcategory":"Building Materials",
            "type":"Retail Goods"
        },
        {
            "category":"Building & Trades",
            "subcategory":"Construction",
            "type":"Services"
        }
    ],
    "sg:phone":"+1 956 544 0024",
    "sg:postcode":"78521",
    "sg:province":"TX",
    "sg:tags":[
        "fence-sales",
        "fence",
        "contractor"
    ],
    "wof:name":"Lezama Fence Supply & More",
    "wof:placetype":"venue"
},
  "geometry": {"coordinates":[-97.454936,25.90118],"type":"Point"}
}