{
  "type": "Feature",
  "properties": {
    "iso:country":"US",
    "sg:address":"1900 Scofield Ridge Pkwy",
    "sg:city":"Austin",
    "sg:classifiers":[
        {
            "category":"Retail",
            "subcategory":"Laundry & Dry Cleaning",
            "type":"Services"
        }
    ],
    "sg:phone":"+1 512 837 1004",
    "sg:postcode":"78727",
    "sg:province":"TX",
    "sg:tags":[
        "drycleaning",
        "plant"
    ],
    "wof:name":"Fabric Cleaners Inc",
    "wof:placetype":"venue"
},
  "geometry": {"coordinates":[-97.68464,30.427777],"type":"Point"}
}