{
  "type": "Feature",
  "properties": {
    "iso:country":"US",
    "sg:address":"300 N Akard St Inside Pulse Fitness at The Mosaic",
    "sg:city":"Dallas",
    "sg:classifiers":[
        {
            "category":"Arena",
            "subcategory":"Sports Club",
            "type":"Entertainment"
        }
    ],
    "sg:phone":"+1 214 507 3567",
    "sg:postcode":"75201",
    "sg:province":"TX",
    "sg:tags":[
        "martial art"
    ],
    "sg:website":"www.KFM-USA.com",
    "wof:name":"KFM- Downtown",
    "wof:placetype":"venue"
},
  "geometry": {"coordinates":[-96.80008599999999,32.7827],"type":"Point"}
}