{
  "type": "Feature",
  "properties": {
    "iso:country":"US",
    "sg:address":"8327 Wind Veil Dr",
    "sg:city":"Houston",
    "sg:classifiers":[
        {
            "category":"Building & Trades",
            "subcategory":"Landscaping Services",
            "type":"Services"
        }
    ],
    "sg:phone":"+1 713 937 7768",
    "sg:postcode":"77040",
    "sg:province":"TX",
    "wof:name":"Majestic Landscape System",
    "wof:placetype":"venue"
},
  "geometry": {"coordinates":[-95.542993,29.893258],"type":"Point"}
}