{
  "type": "Feature",
  "properties": {
    "iso:country":"US",
    "sg:address":"5250 Coffee Port Rd",
    "sg:city":"Brownsville",
    "sg:classifiers":[
        {
            "category":"Building & Trades",
            "subcategory":"Construction",
            "type":"Services"
        }
    ],
    "sg:phone":"+1 956 831 3304",
    "sg:postcode":"78521",
    "sg:province":"TX",
    "sg:tags":[
        "carpentry",
        "cabinet",
        "contractor",
        "maker",
        "mfg"
    ],
    "sg:website":"www.stx-woodmill.com",
    "wof:name":"Woodmill",
    "wof:placetype":"venue"
},
  "geometry": {"coordinates":[-97.431096,25.938589],"type":"Point"}
}