{
  "type": "Feature",
  "properties": {
    "iso:country":"US",
    "sg:address":"16034 Sweetwater Creek Dr",
    "sg:city":"Houston",
    "sg:classifiers":[
        {
            "category":"Personal",
            "subcategory":"Barber",
            "type":"Services"
        }
    ],
    "sg:phone":"+1 281 858 1460",
    "sg:postcode":"77095",
    "sg:province":"TX",
    "sg:tags":[
        "shop"
    ],
    "wof:name":"Grass Barber",
    "wof:placetype":"venue"
},
  "geometry": {"coordinates":[-95.65168199999999,29.898733],"type":"Point"}
}