{
  "type": "Feature",
  "properties": {
    "iso:country":"US",
    "sg:address":"5412 Holly Trl",
    "sg:city":"Arlington",
    "sg:classifiers":[
        {
            "category":"Banks & Credit Unions",
            "subcategory":"Investment Brokerage",
            "type":"Services"
        }
    ],
    "sg:phone":"+1 817 451 8383",
    "sg:postcode":"76016",
    "sg:province":"TX",
    "sg:tags":[
        "advisory"
    ],
    "wof:name":"Allen Financial Advisors",
    "wof:placetype":"venue"
},
  "geometry": {"coordinates":[-97.188956,32.699006],"type":"Point"}
}