{
  "type": "Feature",
  "properties": {
    "iso:country":"US",
    "sg:address":"1407 Jacaman Rd",
    "sg:city":"Laredo",
    "sg:classifiers":[
        {
            "category":"Personal",
            "subcategory":"Beauty Salon",
            "type":"Services"
        }
    ],
    "sg:phone":"+1 956 753 2826",
    "sg:postcode":"78041",
    "sg:province":"TX",
    "wof:name":"Salon De Soleil",
    "wof:placetype":"venue"
},
  "geometry": {"coordinates":[-99.468206,27.560248],"type":"Point"}
}