{
  "type": "Feature",
  "properties": {
    "iso:country":"US",
    "sg:address":"2410 McKinney Ave",
    "sg:city":"Dallas",
    "sg:classifiers":[
        {
            "category":"Shopping",
            "type":"Retail Goods"
        }
    ],
    "sg:phone":"+1 214 729 3346",
    "sg:postcode":"75201",
    "sg:province":"TX",
    "sg:tags":[
        "wedding",
        "supply"
    ],
    "wof:name":"Baking Elegance",
    "wof:placetype":"venue"
},
  "geometry": {"coordinates":[-96.802081,32.794958],"type":"Point"}
}