{
  "type": "Feature",
  "properties": {
    "iso:country":"US",
    "sg:address":"2819 Pease St",
    "sg:city":"Houston",
    "sg:classifiers":[
        {
            "category":"Utilities",
            "subcategory":"Fuel Oil & Lpg",
            "type":"Services"
        }
    ],
    "sg:phone":"+1 713 532 7162",
    "sg:postcode":"77003",
    "sg:province":"TX",
    "sg:tags":[
        "dealer"
    ],
    "wof:name":"Providers Export International",
    "wof:placetype":"venue"
},
  "geometry": {"coordinates":[-95.351928,29.741713],"type":"Point"}
}