{
  "type": "Feature",
  "properties": {
    "iso:country":"US",
    "sg:address":"2204 Emerald Oaks Ct",
    "sg:city":"Arlington",
    "sg:classifiers":[
        {
            "category":"Professional",
            "type":"Services"
        }
    ],
    "sg:phone":"+1 214 648 6843",
    "sg:postcode":"76017",
    "sg:province":"TX",
    "wof:name":"Kennedy Flying Service",
    "wof:placetype":"venue"
},
  "geometry": {"coordinates":[-97.143614,32.656209],"type":"Point"}
}