{
  "type": "Feature",
  "properties": {
    "iso:country":"US",
    "sg:address":"304 E 1st St",
    "sg:city":"Borger",
    "sg:classifiers":[
        {
            "category":"Restaurant",
            "type":"Food & Drink"
        }
    ],
    "sg:phone":"+1 806 226 2594",
    "sg:postcode":"79007",
    "sg:province":"TX",
    "wof:name":"Corley's Diner",
    "wof:placetype":"venue"
},
  "geometry": {"coordinates":[-101.387581,35.665791],"type":"Point"}
}