{
  "type": "Feature",
  "properties": {
    "iso:country":"US",
    "sg:address":"141 Oak St",
    "sg:city":"Abilene",
    "sg:classifiers":[
        {
            "category":"Organizations",
            "subcategory":"Community Association",
            "type":"Services"
        }
    ],
    "sg:phone":"+1 325 675 0704",
    "sg:postcode":"79602",
    "sg:province":"TX",
    "sg:tags":[
        "club"
    ],
    "wof:name":"Stairs Club",
    "wof:placetype":"venue"
},
  "geometry": {"coordinates":[-99.7324,32.448381],"type":"Point"}
}