{
  "type": "Feature",
  "properties": {
    "iso:country":"US",
    "sg:address":"3602 Colony Creek Dr",
    "sg:city":"Nacogdoches",
    "sg:classifiers":[
        {
            "category":"Farming",
            "subcategory":"Farm",
            "type":"Manufacturing & Wholesale Goods"
        }
    ],
    "sg:phone":"+1 936 564 9716",
    "sg:postcode":"75965",
    "sg:province":"TX",
    "wof:name":"Spring Creek Farm",
    "wof:placetype":"venue"
},
  "geometry": {"coordinates":[-94.619033,31.651011],"type":"Point"}
}