{
  "type": "Feature",
  "properties": {
    "iso:country":"US",
    "sg:address":"1103 Divide Ave",
    "sg:city":"El Campo",
    "sg:classifiers":[
        {
            "category":"Home & Garden",
            "subcategory":"Garden Supply",
            "type":"Retail Goods"
        }
    ],
    "sg:phone":"+1 979 543 3802",
    "sg:postcode":"77437",
    "sg:province":"TX",
    "sg:tags":[
        "engine"
    ],
    "wof:name":"El Campo Engine & Compressor",
    "wof:placetype":"venue"
},
  "geometry": {"coordinates":[-96.25486100000001,29.194688],"type":"Point"}
}