{
  "type": "Feature",
  "properties": {
    "iso:country":"US",
    "sg:address":"269 Deerview Dr",
    "sg:city":"China Spring",
    "sg:classifiers":[
        {
            "category":"Insurance",
            "subcategory":"Insurance Agent",
            "type":"Services"
        }
    ],
    "sg:phone":"+1 254 836 0207",
    "sg:postcode":"76633",
    "sg:province":"TX",
    "wof:name":"Robert L Smith",
    "wof:placetype":"venue"
},
  "geometry": {"coordinates":[-97.30609800000001,31.673755],"type":"Point"}
}