{
  "type": "Feature",
  "properties": {
    "iso:country":"US",
    "sg:address":"18523 Haughland Dr",
    "sg:city":"Cypress",
    "sg:classifiers":[
        {
            "category":"Professional",
            "subcategory":"Business Services",
            "type":"Services"
        }
    ],
    "sg:phone":"+1 281 463 2172",
    "sg:postcode":"77433",
    "sg:province":"TX",
    "sg:tags":[
        "trade",
        "contractor"
    ],
    "wof:name":"Eddies Pool Service",
    "wof:placetype":"venue"
},
  "geometry": {"coordinates":[-95.69221,29.883346],"type":"Point"}
}