{
  "type": "Feature",
  "properties": {
    "iso:country":"US",
    "sg:address":"4615 Southwest Fwy Ste 817",
    "sg:city":"Houston",
    "sg:classifiers":[
        {
            "category":"Banks & Credit Unions",
            "subcategory":"Financial Services",
            "type":"Services"
        }
    ],
    "sg:phone":"+1 713 355 4288",
    "sg:postcode":"77027",
    "sg:province":"TX",
    "sg:tags":[
        "broker",
        "mortgage"
    ],
    "wof:name":"Neider Mortgage Consultants",
    "wof:placetype":"venue"
},
  "geometry": {"coordinates":[-95.450897,29.741501],"type":"Point"}
}