{
  "type": "Feature",
  "properties": {
    "iso:country":"US",
    "sg:address":"1012 N Galloway Ave Ste 101",
    "sg:city":"Mesquite",
    "sg:classifiers":[
        {
            "category":"Health Services",
            "subcategory":"Doctor",
            "type":"Services"
        }
    ],
    "sg:phone":"+1 972 288 7337",
    "sg:postcode":"75149",
    "sg:province":"TX",
    "wof:name":"Stiles Laura Pediatrician",
    "wof:placetype":"venue"
},
  "geometry": {"coordinates":[-96.599602,32.777599],"type":"Point"}
}