{
  "type": "Feature",
  "properties": {
    "iso:country":"US",
    "sg:address":"13445 Woodforest Blvd",
    "sg:city":"Houston",
    "sg:classifiers":[
        {
            "category":"Insurance",
            "subcategory":"Title Insurance",
            "type":"Services"
        }
    ],
    "sg:phone":"+1 713 453 2117",
    "sg:postcode":"77015",
    "sg:province":"TX",
    "wof:name":"Texas American Title Co",
    "wof:placetype":"venue"
},
  "geometry": {"coordinates":[-95.185281,29.791837],"type":"Point"}
}