{
  "type": "Feature",
  "properties": {
    "iso:country":"US",
    "sg:address":"133 W Mistletoe Ave",
    "sg:city":"San Antonio",
    "sg:classifiers":[
        {
            "category":"Real Estate",
            "subcategory":"Architect",
            "type":"Services"
        }
    ],
    "sg:phone":"+1 210 732 9268",
    "sg:postcode":"78212",
    "sg:province":"TX",
    "sg:tags":[
        "architectural"
    ],
    "wof:name":"Mainstreet Architects Inc",
    "wof:placetype":"venue"
},
  "geometry": {"coordinates":[-98.495088,29.453944],"type":"Point"}
}