{
  "type": "Feature",
  "properties": {
    "iso:country":"US",
    "sg:address":"1621 Krenek Rd",
    "sg:city":"Crosby",
    "sg:classifiers":[
        {
            "category":"Retail",
            "subcategory":"Auto Repair",
            "type":"Services"
        }
    ],
    "sg:phone":"+1 281 328 1305",
    "sg:postcode":"77532",
    "sg:province":"TX",
    "sg:tags":[
        "exhaust"
    ],
    "wof:name":"Garbs Muffler Shop Inc",
    "wof:placetype":"venue"
},
  "geometry": {"coordinates":[-95.040177,29.898635],"type":"Point"}
}