{
  "type": "Feature",
  "properties": {
    "iso:country":"US",
    "sg:address":"1823 Fortview Rd Ste 106",
    "sg:city":"Austin",
    "sg:classifiers":[
        {
            "category":"Health Services",
            "subcategory":"Doctor",
            "type":"Services"
        },
        {
            "category":"Health Services",
            "subcategory":"Clinic",
            "type":"Services"
        }
    ],
    "sg:phone":"+1 512 444 6110",
    "sg:postcode":"78704",
    "sg:province":"TX",
    "sg:tags":[
        "counseling",
        "mental"
    ],
    "wof:name":"Andrews Sandy PHD",
    "wof:placetype":"venue"
},
  "geometry": {"coordinates":[-97.78589599999999,30.230101],"type":"Point"}
}