{
  "type": "Feature",
  "properties": {
    "iso:country":"US",
    "sg:address":"10823 Sagebluff Dr",
    "sg:city":"Houston",
    "sg:classifiers":[
        {
            "category":"Building & Trades",
            "subcategory":"Cleaning & Sanitation",
            "type":"Services"
        }
    ],
    "sg:phone":"+1 281 484 1565",
    "sg:postcode":"77089",
    "sg:province":"TX",
    "sg:tags":[
        "janitor"
    ],
    "wof:name":"Luxury Building Maintenance",
    "wof:placetype":"venue"
},
  "geometry": {"coordinates":[-95.231669,29.58944],"type":"Point"}
}