{
  "type": "Feature",
  "properties": {
    "iso:country":"US",
    "sg:address":"104 Main St",
    "sg:city":"Gruver",
    "sg:classifiers":[
        {
            "category":"Autos & Motor Vehicles",
            "subcategory":"Auto Supplies",
            "type":"Retail Goods"
        }
    ],
    "sg:phone":"+1 806 733 2668",
    "sg:postcode":"79040",
    "sg:province":"TX",
    "sg:tags":[
        "automobile",
        "part",
        "accessory"
    ],
    "wof:name":"Morse Implement Auto Supply",
    "wof:placetype":"venue"
},
  "geometry": {"coordinates":[-101.405567,36.268413],"type":"Point"}
}