{
  "type": "Feature",
  "properties": {
    "iso:country":"US",
    "sg:address":"3131 Eastside St",
    "sg:city":"Houston",
    "sg:classifiers":[
        {
            "category":"Health Services",
            "subcategory":"Doctor",
            "type":"Services"
        }
    ],
    "sg:phone":"+1 713 627 7068",
    "sg:postcode":"77098",
    "sg:province":"TX",
    "wof:name":"Mark Lee Speck DDS",
    "wof:placetype":"venue"
},
  "geometry": {"coordinates":[-95.42469800000001,29.736937],"type":"Point"}
}