{
  "type": "Feature",
  "properties": {
    "iso:country":"US",
    "sg:address":"1510 Industrial Blvd",
    "sg:city":"Mckinney",
    "sg:classifiers":[
        {
            "category":"Government",
            "subcategory":"Office",
            "type":"Public Place"
        }
    ],
    "sg:phone":"+1 972 369 0431",
    "sg:postcode":"75069",
    "sg:province":"TX",
    "sg:tags":[
        "federal"
    ],
    "wof:name":"Us Govt Ditco Faa",
    "wof:placetype":"venue"
},
  "geometry": {"coordinates":[-96.604725,33.178002],"type":"Point"}
}