{
  "type": "Feature",
  "properties": {
    "iso:country":"US",
    "sg:address":"6805 Poco Dr",
    "sg:city":"Allen",
    "sg:classifiers":[
        {
            "category":"Farming",
            "subcategory":"Farm",
            "type":"Manufacturing & Wholesale Goods"
        }
    ],
    "sg:phone":"+1 972 442 2046",
    "sg:postcode":"75002",
    "sg:province":"TX",
    "sg:tags":[
        "crop",
        "general"
    ],
    "wof:name":"McAllister Farms",
    "wof:placetype":"venue"
},
  "geometry": {"coordinates":[-96.60141400000001,33.059468],"type":"Point"}
}