{
  "type": "Feature",
  "properties": {
    "iso:country":"US",
    "sg:address":"115 W Bolivar St",
    "sg:city":"Vidor",
    "sg:classifiers":[
        {
            "category":"Shopping",
            "subcategory":"Discount & Variety Stores",
            "type":"Retail Goods"
        },
        {
            "category":"Shopping",
            "subcategory":"Department Store",
            "type":"Retail Goods"
        }
    ],
    "sg:phone":"+1 409 783 0822",
    "sg:postcode":"77662",
    "sg:province":"TX",
    "sg:tags":[
        "shop"
    ],
    "wof:name":"Family Dollar Stores",
    "wof:placetype":"venue"
},
  "geometry": {"coordinates":[-94.014898,30.126516],"type":"Point"}
}