{
  "type": "Feature",
  "properties": {
    "iso:country":"US",
    "sg:address":"508 Silvestre St",
    "sg:city":"Uvalde",
    "sg:classifiers":[
        {
            "category":"Personal",
            "subcategory":"Beauty Salon",
            "type":"Services"
        }
    ],
    "sg:phone":"+1 830 486 0408",
    "sg:postcode":"78801",
    "sg:province":"TX",
    "wof:name":"Delilahs Beauty Salon",
    "wof:placetype":"venue"
},
  "geometry": {"coordinates":[-99.792602,29.202829],"type":"Point"}
}