{
  "type": "Feature",
  "properties": {
    "iso:country":"US",
    "sg:address":"157 E 2nd St",
    "sg:city":"Colorado City",
    "sg:classifiers":[
        {
            "category":"Shopping",
            "subcategory":"Used Merchandise",
            "type":"Retail Goods"
        }
    ],
    "sg:phone":"+1 325 728 8877",
    "sg:postcode":"79512",
    "sg:province":"TX",
    "wof:name":"Good Ole Days",
    "wof:placetype":"venue"
},
  "geometry": {"coordinates":[-100.866462,32.388639],"type":"Point"}
}