{
  "type": "Feature",
  "properties": {
    "iso:country":"US",
    "sg:address":"8000 Galveston Rd",
    "sg:city":"Houston",
    "sg:classifiers":[
        {
            "category":"Personal",
            "type":"Services"
        },
        {
            "category":"Retail",
            "subcategory":"Auto Repair",
            "type":"Services"
        }
    ],
    "sg:phone":"+1 713 943 8280",
    "sg:postcode":"77034",
    "sg:province":"TX",
    "sg:tags":[
        "towing"
    ],
    "wof:name":"Eagle Auto Repair",
    "wof:placetype":"venue"
},
  "geometry": {"coordinates":[-95.216103,29.642401],"type":"Point"}
}