{
  "type": "Feature",
  "properties": {
    "iso:country":"US",
    "sg:address":"1080 Ballpark Way",
    "sg:city":"Arlington",
    "sg:classifiers":[
        {
            "category":"Communications",
            "subcategory":"Radio Station",
            "type":"Services"
        }
    ],
    "sg:phone":"+1 972 445 1080",
    "sg:postcode":"76011",
    "sg:province":"TX",
    "sg:tags":[
        "broadcast"
    ],
    "wof:name":"Texas State Network Inc",
    "wof:placetype":"venue"
},
  "geometry": {"coordinates":[-97.081003,32.750364],"type":"Point"}
}