{
  "type": "Feature",
  "properties": {
    "iso:country":"US",
    "sg:address":"1406 N Edwards Ave",
    "sg:city":"Mount Pleasant",
    "sg:classifiers":[
        {
            "category":"Organizations",
            "subcategory":"Non-profit Organization",
            "type":"Services"
        }
    ],
    "sg:phone":"+1 903 572 9561",
    "sg:postcode":"75455",
    "sg:province":"TX",
    "sg:tags":[
        "social"
    ],
    "wof:name":"Senior Citizens Meal-A-Day Ctr",
    "wof:placetype":"venue"
},
  "geometry": {"coordinates":[-94.97742599999999,33.169227],"type":"Point"}
}