{
  "type": "Feature",
  "properties": {
    "iso:country":"US",
    "sg:address":"1805 Taft St",
    "sg:city":"Houston",
    "sg:classifiers":[
        {
            "category":"Organizations",
            "subcategory":"Religious Organization",
            "type":"Services"
        }
    ],
    "sg:phone":"+1 713 524 9830",
    "sg:postcode":"77006",
    "sg:province":"TX",
    "sg:tags":[
        "church"
    ],
    "wof:name":"American Church",
    "wof:placetype":"venue"
},
  "geometry": {"coordinates":[-95.385597,29.752199],"type":"Point"}
}