{
  "type": "Feature",
  "properties": {
    "iso:country":"US",
    "sg:address":"717 E 2nd St",
    "sg:city":"Odessa",
    "sg:classifiers":[
        {
            "category":"Autos & Motor Vehicles",
            "subcategory":"Automobile Sales",
            "type":"Retail Goods"
        }
    ],
    "sg:phone":"+1 432 580 8442",
    "sg:postcode":"79761",
    "sg:province":"TX",
    "sg:tags":[
        "used"
    ],
    "wof:name":"All America Auto Sales 2",
    "wof:placetype":"venue"
},
  "geometry": {"coordinates":[-102.35939500000001,31.850037],"type":"Point"}
}