{
  "type": "Feature",
  "properties": {
    "iso:country":"US",
    "sg:address":"335 E Round Grove Rd",
    "sg:city":"Lewisville",
    "sg:classifiers":[
        {
            "category":"Food & Beverages",
            "subcategory":"Bakery",
            "type":"Retail Goods"
        }
    ],
    "sg:phone":"+1 214 488 5000",
    "sg:postcode":"75067",
    "sg:province":"TX",
    "sg:tags":[
        "sandwich"
    ],
    "sg:website":"www.jimmyjohns.com",
    "wof:name":"Jimmy John's",
    "wof:placetype":"venue"
},
  "geometry": {"coordinates":[-96.983727,33.004744],"type":"Point"}
}