{
  "type": "Feature",
  "properties": {
    "iso:country":"US",
    "sg:address":"600 Preston St",
    "sg:city":"Richmond",
    "sg:classifiers":[
        {
            "category":"Government",
            "subcategory":"Police Station",
            "type":"Public Place"
        }
    ],
    "sg:phone":"+1 281 342 2849",
    "sg:postcode":"77469",
    "sg:province":"TX",
    "sg:tags":[
        "department",
        "protection"
    ],
    "sg:website":"www.richmondtxpolice.com",
    "wof:name":"Richmond Police Department",
    "wof:placetype":"venue"
},
  "geometry": {"coordinates":[-95.764095,29.583627],"type":"Point"}
}