{
  "type": "Feature",
  "properties": {
    "iso:country":"US",
    "sg:address":"13900 Dallas Pkwy",
    "sg:city":"Dallas",
    "sg:classifiers":[
        {
            "category":"Retail",
            "subcategory":"Portrait Studio",
            "type":"Services"
        }
    ],
    "sg:phone":"+1 972 980 9592",
    "sg:postcode":"75240",
    "sg:province":"TX",
    "sg:tags":[
        "photography",
        "store"
    ],
    "sg:website":"www.buybuybaby.com/PortraitStudi...",
    "wof:name":"Buy Buy Baby Portrait Studio Shooting Stars",
    "wof:placetype":"venue"
},
  "geometry": {"coordinates":[-96.821566,32.936156],"type":"Point"}
}