{
  "type": "Feature",
  "properties": {
    "iso:country":"US",
    "sg:address":"1699 Romano Park Ln",
    "sg:city":"Houston",
    "sg:classifiers":[
        {
            "category":"Autos & Motor Vehicles",
            "subcategory":"Automobile Sales",
            "type":"Retail Goods"
        }
    ],
    "sg:phone":"+1 281 893 8486",
    "sg:postcode":"77090",
    "sg:province":"TX",
    "sg:tags":[
        "used"
    ],
    "wof:name":"Quicker Car Sales",
    "wof:placetype":"venue"
},
  "geometry": {"coordinates":[-95.453948,30.009749],"type":"Point"}
}