{
  "type": "Feature",
  "properties": {
    "iso:country":"US",
    "sg:address":"550 W Texas Ave",
    "sg:city":"Midland",
    "sg:classifiers":[
        {
            "category":"Mining & Drilling",
            "type":"Manufacturing & Wholesale Goods"
        }
    ],
    "sg:phone":"+1 432 683 3344",
    "sg:postcode":"79701",
    "sg:province":"TX",
    "sg:tags":[
        "oil",
        "gas",
        "producer"
    ],
    "sg:website":"www.vfpetroleum.com",
    "wof:name":"V-F Petroleum Inc",
    "wof:placetype":"venue"
},
  "geometry": {"coordinates":[-102.08001400000001,31.998519],"type":"Point"}
}