{
  "type": "Feature",
  "properties": {
    "iso:country":"US",
    "sg:address":"6505 Forestview Dr",
    "sg:city":"Arlington",
    "sg:classifiers":[
        {
            "category":"Building & Trades",
            "subcategory":"Construction",
            "type":"Services"
        }
    ],
    "sg:phone":"+1 817 572 2272",
    "sg:postcode":"76016",
    "sg:province":"TX",
    "sg:tags":[
        "business",
        "contractor"
    ],
    "wof:name":"Reflection Pools",
    "wof:placetype":"venue"
},
  "geometry": {"coordinates":[-97.210562,32.675098],"type":"Point"}
}