{
  "type": "Feature",
  "properties": {
    "iso:country":"US",
    "sg:address":"276 Placid Cove Dr",
    "sg:city":"New Braunfels",
    "sg:classifiers":[
        {
            "category":"Wholesale",
            "subcategory":"Furniture",
            "type":"Manufacturing & Wholesale Goods"
        }
    ],
    "sg:phone":"+1 830 629 7216",
    "sg:postcode":"78130",
    "sg:province":"TX",
    "wof:name":"E D & F Associates",
    "wof:placetype":"venue"
},
  "geometry": {"coordinates":[-98.084232,29.668674],"type":"Point"}
}