{
  "type": "Feature",
  "properties": {
    "iso:country":"US",
    "sg:address":"9617 Great Hills Trl",
    "sg:city":"Austin",
    "sg:classifiers":[
        {
            "category":"Professional",
            "subcategory":"Business Services",
            "type":"Services"
        }
    ],
    "sg:phone":"+1 512 349 2010",
    "sg:postcode":"78759",
    "sg:province":"TX",
    "wof:name":"B & G Graphics",
    "wof:placetype":"venue"
},
  "geometry": {"coordinates":[-97.750122,30.394084],"type":"Point"}
}