{
  "type": "Feature",
  "properties": {
    "iso:country":"US",
    "sg:address":"1100 Bridgewood Dr",
    "sg:city":"Fort Worth",
    "sg:classifiers":[
        {
            "category":"Professional",
            "subcategory":"Accounting & Tax Preparation",
            "type":"Services"
        }
    ],
    "sg:phone":"+1 817 496 6300",
    "sg:postcode":"76112",
    "sg:province":"TX",
    "sg:tags":[
        "return",
        "filing"
    ],
    "wof:name":"Colbert Ball Tax Svc",
    "wof:placetype":"venue"
},
  "geometry": {"coordinates":[-97.217529,32.763183],"type":"Point"}
}