{
  "type": "Feature",
  "properties": {
    "iso:country":"US",
    "sg:address":"155 Koehler Ct",
    "sg:city":"San Antonio",
    "sg:classifiers":[
        {
            "category":"Restaurant",
            "type":"Food & Drink"
        }
    ],
    "sg:phone":"+1 210 532 3305",
    "sg:postcode":"78223",
    "sg:province":"TX",
    "sg:tags":[
        "eating"
    ],
    "wof:name":"Candyman Moes Ice Cream",
    "wof:placetype":"venue"
},
  "geometry": {"coordinates":[-98.46815100000001,29.36669],"type":"Point"}
}