{
  "type": "Feature",
  "properties": {
    "iso:country":"US",
    "sg:address":"518 NW 17th St",
    "sg:city":"Grand Prairie",
    "sg:classifiers":[
        {
            "category":"Organizations",
            "subcategory":"Religious Organization",
            "type":"Services"
        }
    ],
    "sg:phone":"+1 972 237 7771",
    "sg:postcode":"75050",
    "sg:province":"TX",
    "sg:tags":[
        "church"
    ],
    "wof:name":"Arise and Build Christian Chur",
    "wof:placetype":"venue"
},
  "geometry": {"coordinates":[-97.026663,32.74715],"type":"Point"}
}