{
  "type": "Feature",
  "properties": {
    "iso:country":"US",
    "sg:address":"612 Shepherd Rd",
    "sg:city":"Georgetown",
    "sg:classifiers":[
        {
            "category":"Manufacturing",
            "subcategory":"Metals",
            "type":"Manufacturing & Wholesale Goods"
        }
    ],
    "sg:phone":"+1 512 863 9498",
    "sg:postcode":"78628",
    "sg:province":"TX",
    "sg:tags":[
        "mfg",
        "laminated",
        "plastic"
    ],
    "wof:name":"Signcraft",
    "wof:placetype":"venue"
},
  "geometry": {"coordinates":[-97.71001699999999,30.655949],"type":"Point"}
}