{
  "type": "Feature",
  "properties": {
    "iso:country":"US",
    "sg:address":"4002 Fairmont Pkwy",
    "sg:city":"Pasadena",
    "sg:classifiers":[
        {
            "category":"Shopping",
            "subcategory":"Gifts & Souvenirs",
            "type":"Retail Goods"
        }
    ],
    "sg:phone":"+1 832 230 4213",
    "sg:postcode":"77504",
    "sg:province":"TX",
    "sg:tags":[
        "flower"
    ],
    "wof:name":"Let's Party",
    "wof:placetype":"venue"
},
  "geometry": {"coordinates":[-95.184804,29.650642],"type":"Point"}
}