{
  "type": "Feature",
  "properties": {
    "iso:country":"US",
    "sg:address":"1001 E Euless Blvd",
    "sg:city":"Euless",
    "sg:classifiers":[
        {
            "category":"Organizations",
            "subcategory":"Professional Association",
            "type":"Services"
        }
    ],
    "sg:phone":"+1 817 545 2332",
    "sg:postcode":"76040",
    "sg:province":"TX",
    "wof:name":"Association-Flight Attendants",
    "wof:placetype":"venue"
},
  "geometry": {"coordinates":[-97.098119,32.829247],"type":"Point"}
}