{
  "type": "Feature",
  "properties": {
    "iso:country":"US",
    "sg:address":"110 Wembley Way",
    "sg:city":"Rockwall",
    "sg:classifiers":[
        {
            "category":"Restaurant",
            "type":"Food & Drink"
        },
        {
            "category":"Food & Beverages",
            "subcategory":"Ethnic Foods",
            "type":"Retail Goods"
        }
    ],
    "sg:phone":"+1 972 771 3729",
    "sg:postcode":"75032",
    "sg:province":"TX",
    "sg:tags":[
        "asian",
        "pan",
        "vietnamese"
    ],
    "wof:name":"Soul Garden P H O",
    "wof:placetype":"venue"
},
  "geometry": {"coordinates":[-96.458589,32.894782],"type":"Point"}
}