{
  "type": "Feature",
  "properties": {
    "iso:country":"US",
    "sg:address":"619 Stiles St",
    "sg:city":"Houston",
    "sg:classifiers":[
        {
            "category":"Social Services",
            "subcategory":"Child Care",
            "type":"Services"
        }
    ],
    "sg:phone":"+1 713 928 8920",
    "sg:postcode":"77011",
    "sg:province":"TX",
    "wof:name":"Osorio Alodia",
    "wof:placetype":"venue"
},
  "geometry": {"coordinates":[-95.32772900000001,29.742138],"type":"Point"}
}