{
  "type": "Feature",
  "properties": {
    "iso:country":"US",
    "sg:address":"609 Jenny Gaye Ln",
    "sg:city":"Highlands",
    "sg:classifiers":[
        {
            "category":"Wholesale",
            "subcategory":"Durable Goods & Equipment",
            "type":"Manufacturing & Wholesale Goods"
        }
    ],
    "sg:phone":"+1 281 426 8008",
    "sg:postcode":"77562",
    "sg:province":"TX",
    "wof:name":"Gensco Supply Co",
    "wof:placetype":"venue"
},
  "geometry": {"coordinates":[-95.05472899999999,29.824855],"type":"Point"}
}