{
  "type": "Feature",
  "properties": {
    "iso:country":"US",
    "sg:address":"12621 Highway 105 W",
    "sg:city":"Conroe",
    "sg:phone":"+1 936 588 0355",
    "sg:postcode":"77304",
    "sg:province":"TX",
    "wof:name":"Salon By The Lake",
    "wof:placetype":"venue"
},
  "geometry": {"coordinates":[-95.551511,30.342818],"type":"Point"}
}