{
  "type": "Feature",
  "properties": {
    "iso:country":"US",
    "sg:address":"13106 Apple Tree Rd",
    "sg:city":"Houston",
    "sg:classifiers":[
        {
            "category":"Real Estate",
            "subcategory":"Architect",
            "type":"Services"
        }
    ],
    "sg:phone":"+1 713 461 9329",
    "sg:postcode":"77079",
    "sg:province":"TX",
    "wof:name":"Dennis W Rainoshek Inc",
    "wof:placetype":"venue"
},
  "geometry": {"coordinates":[-95.57279200000001,29.76958],"type":"Point"}
}