{
  "type": "Feature",
  "properties": {
    "iso:country":"US",
    "sg:address":"8529 San Miguel Dr",
    "sg:city":"El Paso",
    "sg:classifiers":[
        {
            "category":"Organizations",
            "subcategory":"Community Association",
            "type":"Services"
        }
    ],
    "sg:phone":"+1 915 858 5429",
    "sg:postcode":"79907",
    "sg:province":"TX",
    "wof:name":"Homecoming Corsages",
    "wof:placetype":"venue"
},
  "geometry": {"coordinates":[-106.346886,31.703263],"type":"Point"}
}