{
  "type": "Feature",
  "properties": {
    "iso:country":"US",
    "sg:address":"2302 Mc Cullough St",
    "sg:city":"Austin",
    "sg:classifiers":[
        {
            "category":"Shopping",
            "subcategory":"Hobbies, Toys, & Games",
            "type":"Retail Goods"
        }
    ],
    "sg:phone":"+1 512 451 9405",
    "sg:postcode":"78703",
    "sg:province":"TX",
    "wof:name":"Hues of Reign Bough",
    "wof:placetype":"venue"
},
  "geometry": {"coordinates":[-97.76155900000001,30.299843],"type":"Point"}
}