{
  "type": "Feature",
  "properties": {
    "iso:country":"US",
    "sg:address":"12770 Cimarron Path",
    "sg:city":"San Antonio",
    "sg:classifiers":[
        {
            "category":"Professional",
            "subcategory":"Business Services",
            "type":"Services"
        }
    ],
    "sg:phone":"+1 210 877 2800",
    "sg:postcode":"78249",
    "sg:province":"TX",
    "sg:tags":[
        "recording",
        "studio"
    ],
    "wof:name":"DISALLC",
    "wof:placetype":"venue"
},
  "geometry": {"coordinates":[-98.598946,29.559624],"type":"Point"}
}