{
  "type": "Feature",
  "properties": {
    "iso:country":"US",
    "sg:address":"108 W 8th St",
    "sg:city":"Elgin",
    "sg:classifiers":[
        {
            "category":"Professional",
            "type":"Services"
        },
        {
            "category":"Building & Trades",
            "subcategory":"Construction",
            "type":"Services"
        }
    ],
    "sg:phone":"+1 512 285 3022",
    "sg:postcode":"78621",
    "sg:province":"TX",
    "sg:tags":[
        "house",
        "establishment"
    ],
    "wof:name":"Land One Solutions Inc",
    "wof:placetype":"venue"
},
  "geometry": {"coordinates":[-97.374971,30.351948],"type":"Point"}
}