{
  "type": "Feature",
  "properties": {
    "iso:country":"US",
    "sg:address":"204 N Mason St",
    "sg:city":"Bowie",
    "sg:classifiers":[
        {
            "category":"Banks & Credit Unions",
            "subcategory":"Bank",
            "type":"Services"
        },
        {
            "category":"Shopping",
            "subcategory":"Used Merchandise",
            "type":"Retail Goods"
        }
    ],
    "sg:phone":"+1 940 872 6711",
    "sg:postcode":"76230",
    "sg:province":"TX",
    "sg:tags":[
        "resale",
        "shop",
        "second",
        "hand"
    ],
    "wof:name":"Happy Heart Antiques Etc",
    "wof:placetype":"venue"
},
  "geometry": {"coordinates":[-97.849953,33.557157],"type":"Point"}
}