{
  "type": "Feature",
  "properties": {
    "iso:country":"US",
    "sg:address":"10975 Applewhite Rd",
    "sg:city":"San Antonio",
    "sg:classifiers":[
        {
            "category":"Social Services",
            "type":"Services"
        }
    ],
    "sg:phone":"+1 210 628 1833",
    "sg:postcode":"78224",
    "sg:province":"TX",
    "sg:tags":[
        "probation"
    ],
    "wof:name":"Adult Probation-Restitution",
    "wof:placetype":"venue"
},
  "geometry": {"coordinates":[-98.54966400000001,29.308896],"type":"Point"}
}