{
  "type": "Feature",
  "properties": {
    "iso:country":"US",
    "sg:address":"4200 Prospect Ln",
    "sg:city":"Plano",
    "sg:classifiers":[
        {
            "category":"Professional",
            "subcategory":"Management & Consulting",
            "type":"Services"
        }
    ],
    "sg:phone":"+1 469 569 5202",
    "sg:postcode":"75093",
    "sg:province":"TX",
    "wof:name":"Edh Tech Inc",
    "wof:placetype":"venue"
},
  "geometry": {"coordinates":[-96.77426800000001,33.024473],"type":"Point"}
}