{
  "type": "Feature",
  "properties": {
    "iso:country":"US",
    "sg:address":"4311 Oak Lawn Ave Ste 100",
    "sg:city":"Dallas",
    "sg:classifiers":[
        {
            "category":"Wholesale",
            "subcategory":"Books, Periodicals, & Newspapers",
            "type":"Manufacturing & Wholesale Goods"
        }
    ],
    "sg:phone":"+1 214 939 3636",
    "sg:postcode":"75219",
    "sg:province":"TX",
    "sg:tags":[
        "magazine"
    ],
    "wof:name":"D Magazine Partners, L.P.",
    "wof:placetype":"venue"
},
  "geometry": {"coordinates":[-96.802378,32.822033],"type":"Point"}
}