{
  "type": "Feature",
  "properties": {
    "iso:country":"US",
    "sg:address":"5870 State Hwy 6",
    "sg:city":"Houston",
    "sg:classifiers":[
        {
            "category":"Real Estate",
            "subcategory":"Real Estate Agent",
            "type":"Services"
        }
    ],
    "sg:phone":"+1 281 463 3300",
    "sg:postcode":"77084",
    "sg:province":"TX",
    "wof:name":"Re/Max",
    "wof:placetype":"venue"
},
  "geometry": {"coordinates":[-95.645186,29.861242],"type":"Point"}
}