{
  "type": "Feature",
  "properties": {
    "iso:country":"US",
    "sg:address":"7960 Long Point Rd",
    "sg:city":"Houston",
    "sg:classifiers":[
        {
            "category":"Cinema",
            "subcategory":"Movie Rental",
            "type":"Entertainment"
        }
    ],
    "sg:phone":"+1 713 461 8170",
    "sg:postcode":"77055",
    "sg:province":"TX",
    "sg:tags":[
        "game",
        "video"
    ],
    "wof:name":"Redbox",
    "wof:placetype":"venue"
},
  "geometry": {"coordinates":[-95.485888,29.802971],"type":"Point"}
}