{
  "type": "Feature",
  "properties": {
    "iso:country":"US",
    "sg:address":"221 W 6th St",
    "sg:city":"Austin",
    "sg:classifiers":[
        {
            "category":"Insurance",
            "subcategory":"Life Insurance",
            "type":"Services"
        }
    ],
    "sg:phone":"+1 512 472 0694",
    "sg:postcode":"78701",
    "sg:province":"TX",
    "sg:tags":[
        "company"
    ],
    "wof:name":"Bradford National Lf Insur Co",
    "wof:placetype":"venue"
},
  "geometry": {"coordinates":[-97.745035,30.268583],"type":"Point"}
}