{
  "type": "Feature",
  "properties": {
    "iso:country":"US",
    "sg:address":"8130 Holiday Ln",
    "sg:city":"Houston",
    "sg:classifiers":[
        {
            "category":"Building & Trades",
            "subcategory":"Cleaning & Sanitation",
            "type":"Services"
        }
    ],
    "sg:phone":"+1 713 991 6765",
    "sg:postcode":"77075",
    "sg:province":"TX",
    "sg:tags":[
        "maintenance"
    ],
    "wof:name":"Maintenance On Call",
    "wof:placetype":"venue"
},
  "geometry": {"coordinates":[-95.271755,29.621882],"type":"Point"}
}