{
  "type": "Feature",
  "properties": {
    "iso:country":"US",
    "sg:address":"1316 San Bernardo Ave",
    "sg:city":"Laredo",
    "sg:classifiers":[
        {
            "category":"Organizations",
            "subcategory":"Religious Organization",
            "type":"Services"
        }
    ],
    "sg:phone":"+1 956 723 9475",
    "sg:postcode":"78040",
    "sg:province":"TX",
    "sg:tags":[
        "churches-baptist",
        "church"
    ],
    "wof:name":"Primera Iglesia Bautista",
    "wof:placetype":"venue"
},
  "geometry": {"coordinates":[-99.50458999999999,27.51077],"type":"Point"}
}