{
  "type": "Feature",
  "properties": {
    "iso:country":"US",
    "sg:address":"6516 Farmers Ln",
    "sg:city":"Texarkana",
    "sg:classifiers":[
        {
            "category":"Insurance",
            "subcategory":"Insurance Agent",
            "type":"Services"
        }
    ],
    "sg:phone":"+1 903 793 0121",
    "sg:postcode":"75503",
    "sg:province":"TX",
    "wof:name":"Hudgins Carl",
    "wof:placetype":"venue"
},
  "geometry": {"coordinates":[-94.04624800000001,33.493208],"type":"Point"}
}