{
  "type": "Feature",
  "properties": {
    "iso:country":"US",
    "sg:address":"1707 Arvada Dr",
    "sg:city":"Richardson",
    "sg:classifiers":[
        {
            "category":"Home & Garden",
            "subcategory":"Building Materials",
            "type":"Retail Goods"
        }
    ],
    "sg:phone":"+1 972 424 3921",
    "sg:postcode":"75081",
    "sg:province":"TX",
    "wof:name":"Art Glass Gallery & Studio",
    "wof:placetype":"venue"
},
  "geometry": {"coordinates":[-96.69233199999999,32.971565],"type":"Point"}
}