{
  "type": "Feature",
  "properties": {
    "iso:country":"US",
    "sg:address":"4400 N Lamar Blvd Suite 101",
    "sg:city":"Austin",
    "sg:classifiers":[
        {
            "category":"Fast Food",
            "type":"Food & Drink"
        },
        {
            "category":"Restaurant",
            "type":"Food & Drink"
        }
    ],
    "sg:phone":"+1 512 419 9898",
    "sg:postcode":"78756",
    "sg:province":"TX",
    "sg:tags":[
        "mexican",
        "take"
    ],
    "sg:website":"www.chipotle.com",
    "wof:name":"Chipotle Mexican Grill",
    "wof:placetype":"venue"
},
  "geometry": {"coordinates":[-97.738854,30.31239],"type":"Point"}
}