{
  "type": "Feature",
  "properties": {
    "iso:country":"US",
    "sg:address":"2125 E Pioneer Pkwy",
    "sg:city":"Arlington",
    "sg:classifiers":[
        {
            "category":"Restaurant",
            "type":"Food & Drink"
        }
    ],
    "sg:phone":"+1 817 860 9225",
    "sg:postcode":"76010",
    "sg:province":"TX",
    "sg:tags":[
        "eating"
    ],
    "wof:name":"Popeyes Chicken & Biscuits",
    "wof:placetype":"venue"
},
  "geometry": {"coordinates":[-97.071879,32.712068],"type":"Point"}
}