{
  "type": "Feature",
  "properties": {
    "iso:country":"US",
    "sg:address":"1763 N Main St",
    "sg:city":"Weatherford",
    "sg:classifiers":[
        {
            "category":"Retail",
            "subcategory":"Auto Repair",
            "type":"Services"
        }
    ],
    "sg:phone":"+1 817 594 1442",
    "sg:postcode":"76085",
    "sg:province":"TX",
    "sg:tags":[
        "truck"
    ],
    "wof:name":"Sargents Truck & Auto Repair",
    "wof:placetype":"venue"
},
  "geometry": {"coordinates":[-97.797234,32.780133],"type":"Point"}
}