{
  "type": "Feature",
  "properties": {
    "iso:country":"US",
    "sg:address":"10800 S Gessner Dr",
    "sg:city":"Houston",
    "sg:classifiers":[
        {
            "category":"Personal",
            "subcategory":"Beauty Salon",
            "type":"Services"
        }
    ],
    "sg:phone":"+1 713 541 0082",
    "sg:postcode":"77071",
    "sg:province":"TX",
    "sg:tags":[
        "shop"
    ],
    "wof:name":"Elegance Braids Salon",
    "wof:placetype":"venue"
},
  "geometry": {"coordinates":[-95.528018,29.664091],"type":"Point"}
}