{
  "type": "Feature",
  "properties": {
    "iso:country":"US",
    "sg:address":"5922 Forest Ridge",
    "sg:city":"San Antonio",
    "sg:classifiers":[
        {
            "category":"Building & Trades",
            "subcategory":"Construction",
            "type":"Services"
        }
    ],
    "sg:phone":"+1 210 684 3512",
    "sg:postcode":"78240",
    "sg:province":"TX",
    "sg:tags":[
        "nonresidential"
    ],
    "wof:name":"Red Coat Remodeling",
    "wof:placetype":"venue"
},
  "geometry": {"coordinates":[-98.60283,29.502234],"type":"Point"}
}