{
  "type": "Feature",
  "properties": {
    "iso:country":"US",
    "sg:address":"4530 Kingwood Dr",
    "sg:city":"Humble",
    "sg:classifiers":[
        {
            "category":"Food & Beverages",
            "subcategory":"Liquor & Beverages",
            "type":"Retail Goods"
        }
    ],
    "sg:phone":"+1 281 360 3770",
    "sg:postcode":"77345",
    "sg:province":"TX",
    "sg:tags":[
        "alcoholic"
    ],
    "wof:name":"G R Hmaidan Inc",
    "wof:placetype":"venue"
},
  "geometry": {"coordinates":[-95.181848,30.050714],"type":"Point"}
}