{
  "type": "Feature",
  "properties": {
    "iso:country":"US",
    "sg:address":"512 US Hwy 377",
    "sg:city":"Argyle",
    "sg:classifiers":[
        {
            "category":"Shopping",
            "subcategory":"Gifts & Souvenirs",
            "type":"Retail Goods"
        }
    ],
    "sg:phone":"+1 940 243 2248",
    "sg:postcode":"76226",
    "sg:province":"TX",
    "sg:tags":[
        "shop"
    ],
    "wof:name":"Elements Of Argyle",
    "wof:placetype":"venue"
},
  "geometry": {"coordinates":[-97.185388,33.121215],"type":"Point"}
}