{
  "type": "Feature",
  "properties": {
    "iso:country":"US",
    "sg:address":"312 Main St",
    "sg:city":"Liberty",
    "sg:classifiers":[
        {
            "category":"Professional",
            "subcategory":"Lawyer & Legal Services",
            "type":"Services"
        }
    ],
    "sg:phone":"+1 936 336 5776",
    "sg:postcode":"77575",
    "sg:province":"TX",
    "sg:tags":[
        "attorney"
    ],
    "wof:name":"Morefield Mark & Assoc",
    "wof:placetype":"venue"
},
  "geometry": {"coordinates":[-94.79578100000001,30.058749],"type":"Point"}
}