{
  "type": "Feature",
  "properties": {
    "iso:country":"US",
    "sg:address":"1511 Preston St",
    "sg:city":"Houston",
    "sg:classifiers":[
        {
            "category":"Government",
            "subcategory":"Office",
            "type":"Public Place"
        }
    ],
    "sg:phone":"+1 713 222 6808",
    "sg:postcode":"77002",
    "sg:province":"TX",
    "wof:name":"Texas Dept Criminal Justice",
    "wof:placetype":"venue"
},
  "geometry": {"coordinates":[-95.356184,29.758496],"type":"Point"}
}