{
  "type": "Feature",
  "properties": {
    "iso:country":"US",
    "sg:address":"2105 Kippling Dr",
    "sg:city":"Austin",
    "sg:classifiers":[
        {
            "category":"Personal",
            "type":"Services"
        }
    ],
    "sg:phone":"+1 512 371 0630",
    "sg:postcode":"78752",
    "sg:province":"TX",
    "sg:tags":[
        "miscellaneous"
    ],
    "wof:name":"PIPA",
    "wof:placetype":"venue"
},
  "geometry": {"coordinates":[-97.68089999999999,30.32573],"type":"Point"}
}