{
  "type": "Feature",
  "properties": {
    "iso:country":"US",
    "sg:address":"6601 Blanco Rd",
    "sg:city":"San Antonio",
    "sg:classifiers":[
        {
            "category":"Professional",
            "subcategory":"Business Services",
            "type":"Services"
        }
    ],
    "sg:phone":"+1 210 308 8411",
    "sg:postcode":"78216",
    "sg:province":"TX",
    "wof:name":"Avant Model & Casting",
    "wof:placetype":"venue"
},
  "geometry": {"coordinates":[-98.50687600000001,29.515814],"type":"Point"}
}