{
  "type": "Feature",
  "properties": {
    "iso:country":"US",
    "sg:address":"5316 Warm Springs Trl",
    "sg:city":"Fort Worth",
    "sg:classifiers":[
        {
            "category":"Professional",
            "subcategory":"Business Services",
            "type":"Services"
        },
        {
            "category":"Professional",
            "subcategory":"Advertising",
            "type":"Services"
        }
    ],
    "sg:phone":"+1 817 832 5138",
    "sg:postcode":"76137",
    "sg:province":"TX",
    "sg:tags":[
        "designer",
        "display",
        "producer"
    ],
    "wof:name":"Impact Trade Show Display Co",
    "wof:placetype":"venue"
},
  "geometry": {"coordinates":[-97.270528,32.86947],"type":"Point"}
}