{
  "type": "Feature",
  "properties": {
    "iso:country":"US",
    "sg:address":"100 W Main St",
    "sg:city":"Eastland",
    "sg:classifiers":[
        {
            "category":"Government",
            "subcategory":"Office",
            "type":"Public Place"
        }
    ],
    "sg:phone":"+1 254 629 1093",
    "sg:postcode":"76448",
    "sg:province":"TX",
    "wof:name":"Eastland County Ext Agent-Ag",
    "wof:placetype":"venue"
},
  "geometry": {"coordinates":[-98.819035,32.401776],"type":"Point"}
}