{
  "type": "Feature",
  "properties": {
    "iso:country":"US",
    "sg:address":"223 Rosabell St",
    "sg:city":"San Antonio",
    "sg:classifiers":[
        {
            "category":"Professional",
            "subcategory":"Business Services",
            "type":"Services"
        }
    ],
    "sg:phone":"+1 210 523 5698",
    "sg:postcode":"78228",
    "sg:province":"TX",
    "wof:name":"Renteria & Associates",
    "wof:placetype":"venue"
},
  "geometry": {"coordinates":[-98.56631299999999,29.44619],"type":"Point"}
}