{
  "type": "Feature",
  "properties": {
    "iso:country":"US",
    "sg:address":"7111 Spencer Hwy",
    "sg:city":"Pasadena",
    "sg:classifiers":[
        {
            "category":"Food & Beverages",
            "subcategory":"Bakery",
            "type":"Retail Goods"
        }
    ],
    "sg:phone":"+1 281 478 4001",
    "sg:postcode":"77505",
    "sg:province":"TX",
    "sg:tags":[
        "doughnut"
    ],
    "wof:name":"Dina's Donuts",
    "wof:placetype":"venue"
},
  "geometry": {"coordinates":[-95.129165,29.663637],"type":"Point"}
}