{
  "type": "Feature",
  "properties": {
    "iso:country":"US",
    "sg:address":"265 State Hwy 36",
    "sg:city":"Caldwell",
    "sg:classifiers":[
        {
            "category":"Restaurant",
            "type":"Food & Drink"
        }
    ],
    "sg:phone":"+1 979 567 7475",
    "sg:postcode":"77836",
    "sg:province":"TX",
    "sg:tags":[
        "eating"
    ],
    "wof:name":"Cherokee Rose Cafe",
    "wof:placetype":"venue"
},
  "geometry": {"coordinates":[-96.689435,30.533867],"type":"Point"}
}