{
  "type": "Feature",
  "properties": {
    "iso:country":"US",
    "sg:address":"5029 Lodgepole Ln",
    "sg:city":"Fort Worth",
    "sg:classifiers":[
        {
            "category":"Professional",
            "subcategory":"Computer Services",
            "type":"Services"
        }
    ],
    "sg:phone":"+1 817 905 5356",
    "sg:postcode":"76137",
    "sg:province":"TX",
    "sg:tags":[
        "information",
        "retrieval"
    ],
    "wof:name":"Ugottocom",
    "wof:placetype":"venue"
},
  "geometry": {"coordinates":[-97.276303,32.864837],"type":"Point"}
}