{
  "type": "Feature",
  "properties": {
    "iso:country":"US",
    "sg:address":"11009 Katy Fwy",
    "sg:city":"Houston",
    "sg:classifiers":[
        {
            "category":"Retail",
            "subcategory":"Auto Rental",
            "type":"Services"
        }
    ],
    "sg:phone":"+1 281 493 5327",
    "sg:postcode":"77079",
    "sg:province":"TX",
    "sg:tags":[
        "passenger",
        "car"
    ],
    "wof:name":"Thrifty Car Rental",
    "wof:placetype":"venue"
},
  "geometry": {"coordinates":[-95.573323,29.783991],"type":"Point"}
}