{
  "type": "Feature",
  "properties": {
    "iso:country":"US",
    "sg:address":"905 Creekline Way",
    "sg:city":"Mc Kinney",
    "sg:classifiers":[
        {
            "category":"Health Services",
            "subcategory":"Clinic",
            "type":"Services"
        }
    ],
    "sg:phone":"+1 972 540 6905",
    "sg:postcode":"75070",
    "sg:province":"TX",
    "wof:name":"August Healthcare Inc",
    "wof:placetype":"venue"
},
  "geometry": {"coordinates":[-96.704601,33.193788],"type":"Point"}
}