{
  "type": "Feature",
  "properties": {
    "iso:country":"US",
    "sg:address":"2885 Meadow Port Dr",
    "sg:city":"Dallas",
    "sg:classifiers":[
        {
            "category":"Utilities",
            "subcategory":"Telephone",
            "type":"Services"
        }
    ],
    "sg:phone":"+1 972 484 9915",
    "sg:postcode":"75234",
    "sg:province":"TX",
    "sg:tags":[
        "telecommunication"
    ],
    "sg:website":"www.voicestamps.com",
    "wof:name":"VOICESTAMPS.COM",
    "wof:placetype":"venue"
},
  "geometry": {"coordinates":[-96.884428,32.914021],"type":"Point"}
}