{
  "type": "Feature",
  "properties": {
    "iso:country":"US",
    "sg:address":"415 W Munson St",
    "sg:city":"Denison",
    "sg:classifiers":[
        {
            "category":"Building & Trades",
            "subcategory":"Construction",
            "type":"Services"
        },
        {
            "category":"Military Area",
            "subcategory":"Armory",
            "type":"Public Place"
        }
    ],
    "sg:phone":"+1 903 465 2933",
    "sg:postcode":"75020",
    "sg:province":"TX",
    "sg:tags":[
        "repair",
        "fence-sales",
        "fence",
        "contractor"
    ],
    "wof:name":"Skaggs Fence Co",
    "wof:placetype":"venue"
},
  "geometry": {"coordinates":[-96.540583,33.747356],"type":"Point"}
}