{
  "type": "Feature",
  "properties": {
    "iso:country":"US",
    "sg:address":"902 Jennifer Ct",
    "sg:city":"Cleburne",
    "sg:classifiers":[
        {
            "category":"Professional",
            "type":"Services"
        }
    ],
    "sg:phone":"+1 817 641 9208",
    "sg:postcode":"76033",
    "sg:province":"TX",
    "wof:name":"Cleburne Carwashes",
    "wof:placetype":"venue"
},
  "geometry": {"coordinates":[-97.41198,32.325738],"type":"Point"}
}