{
  "type": "Feature",
  "properties": {
    "iso:country":"US",
    "sg:address":"408 Oak St",
    "sg:city":"Anahuac",
    "sg:classifiers":[
        {
            "category":"Freight",
            "type":"Transportation"
        }
    ],
    "sg:phone":"+1 409 267 3468",
    "sg:postcode":"77514",
    "sg:province":"TX",
    "sg:tags":[
        "storage",
        "unit"
    ],
    "wof:name":"Anahuac Storage",
    "wof:placetype":"venue"
},
  "geometry": {"coordinates":[-94.674615,29.75957],"type":"Point"}
}