{
  "type": "Feature",
  "properties": {
    "iso:country":"US",
    "sg:address":"1807 Treadwell St",
    "sg:city":"Austin",
    "sg:classifiers":[
        {
            "category":"Professional",
            "subcategory":"Business Services",
            "type":"Services"
        }
    ],
    "sg:phone":"+1 512 448 2659",
    "sg:postcode":"78704",
    "sg:province":"TX",
    "sg:tags":[
        "organizing",
        "services-household"
    ],
    "wof:name":"Stenger Management",
    "wof:placetype":"venue"
},
  "geometry": {"coordinates":[-97.76656,30.258709],"type":"Point"}
}