{
  "type": "Feature",
  "properties": {
    "iso:country":"US",
    "sg:address":"3883 Lakeview Ct",
    "sg:city":"Addison",
    "sg:classifiers":[
        {
            "category":"Professional",
            "subcategory":"Business Services",
            "type":"Services"
        }
    ],
    "sg:phone":"+1 972 620 7098",
    "sg:postcode":"75001",
    "sg:province":"TX",
    "wof:name":"Carol Brown Designs",
    "wof:placetype":"venue"
},
  "geometry": {"coordinates":[-96.84982100000001,32.947724],"type":"Point"}
}