{
  "type": "Feature",
  "properties": {
    "iso:country":"US",
    "sg:address":"6346 N New Braunfels Ave",
    "sg:city":"San Antonio",
    "sg:classifiers":[
        {
            "category":"Shopping",
            "subcategory":"Florist",
            "type":"Retail Goods"
        }
    ],
    "sg:phone":"+1 210 804 7673",
    "sg:postcode":"78209",
    "sg:province":"TX",
    "wof:name":"Kabloom",
    "wof:placetype":"venue"
},
  "geometry": {"coordinates":[-98.45924100000001,29.485996],"type":"Point"}
}