{
  "type": "Feature",
  "properties": {
    "iso:country":"US",
    "sg:address":"2703 Mockingbird Ln",
    "sg:city":"Amarillo",
    "sg:classifiers":[
        {
            "category":"Health Services",
            "subcategory":"Doctor",
            "type":"Services"
        }
    ],
    "sg:phone":"+1 806 359 3558",
    "sg:postcode":"79109",
    "sg:province":"TX",
    "wof:name":"James A Hale DDS",
    "wof:placetype":"venue"
},
  "geometry": {"coordinates":[-101.86613,35.182487],"type":"Point"}
}