{
  "type": "Feature",
  "properties": {
    "iso:country":"US",
    "sg:address":"707 Washington Dr",
    "sg:city":"Arlington",
    "sg:classifiers":[
        {
            "category":"Real Estate",
            "subcategory":"Real Estate Operator",
            "type":"Services"
        }
    ],
    "sg:phone":"+1 817 265 7365",
    "sg:postcode":"76011",
    "sg:province":"TX",
    "sg:tags":[
        "building",
        "apartment"
    ],
    "wof:name":"Arrowood Apts",
    "wof:placetype":"venue"
},
  "geometry": {"coordinates":[-97.10244,32.769714],"type":"Point"}
}