{
  "type": "Feature",
  "properties": {
    "iso:country":"US",
    "sg:address":"432 Houghton Ave",
    "sg:city":"Marlin",
    "sg:classifiers":[
        {
            "category":"Social Services",
            "subcategory":"Child Care",
            "type":"Services"
        }
    ],
    "sg:phone":"+1 254 883 2145",
    "sg:postcode":"76661",
    "sg:province":"TX",
    "sg:tags":[
        "day"
    ],
    "wof:name":"Total Child Learning Center",
    "wof:placetype":"venue"
},
  "geometry": {"coordinates":[-96.89063899999999,31.312194],"type":"Point"}
}