{
  "type": "Feature",
  "properties": {
    "iso:country":"US",
    "sg:address":"2021 FM 1092",
    "sg:city":"Missouri City",
    "sg:classifiers":[
        {
            "category":"Social Services",
            "subcategory":"Adult Care",
            "type":"Services"
        },
        {
            "category":"Health Services",
            "subcategory":"Nursing And Care Facility",
            "type":"Services"
        }
    ],
    "sg:phone":"+1 281 565 4144",
    "sg:postcode":"77459",
    "sg:province":"TX",
    "sg:tags":[
        "residential"
    ],
    "wof:name":"Optimum Personal Care Inc",
    "wof:placetype":"venue"
},
  "geometry": {"coordinates":[-95.56406800000001,29.590464],"type":"Point"}
}