{
  "type": "Feature",
  "properties": {
    "iso:country":"US",
    "sg:address":"4201 Cedar Elm Ln",
    "sg:city":"Wichita Falls",
    "sg:classifiers":[
        {
            "category":"Real Estate",
            "subcategory":"Real Estate Operator",
            "type":"Services"
        }
    ],
    "sg:phone":"+1 940 692 8052",
    "sg:postcode":"76308",
    "sg:province":"TX",
    "sg:tags":[
        "apartment"
    ],
    "wof:name":"French Quarter Apartments",
    "wof:placetype":"venue"
},
  "geometry": {"coordinates":[-98.516412,33.869182],"type":"Point"}
}