{
  "type": "Feature",
  "properties": {
    "iso:country":"US",
    "sg:address":"4243 S Alameda St",
    "sg:city":"Corpus Christi",
    "sg:classifiers":[
        {
            "category":"Personal",
            "subcategory":"Beauty Salon",
            "type":"Services"
        }
    ],
    "sg:phone":"+1 361 985 6722",
    "sg:postcode":"78412",
    "sg:province":"TX",
    "wof:name":"Pat's Hair Studio",
    "wof:placetype":"venue"
},
  "geometry": {"coordinates":[-97.372732,27.731008],"type":"Point"}
}