{
  "type": "Feature",
  "properties": {
    "iso:country":"US",
    "sg:address":"12063 Garland Rd",
    "sg:city":"Dallas",
    "sg:classifiers":[
        {
            "category":"Autos & Motor Vehicles",
            "subcategory":"Automobile Sales",
            "type":"Retail Goods"
        }
    ],
    "sg:phone":"+1 214 321 9668",
    "sg:postcode":"75218",
    "sg:province":"TX",
    "sg:tags":[
        "car",
        "dealer"
    ],
    "wof:name":"Dove Auto Sales",
    "wof:placetype":"venue"
},
  "geometry": {"coordinates":[-96.670204,32.864811],"type":"Point"}
}