{
  "type": "Feature",
  "properties": {
    "iso:country":"US",
    "sg:address":"3434 Fallen Leaf Ln",
    "sg:city":"San Antonio",
    "sg:classifiers":[
        {
            "category":"Professional",
            "type":"Services"
        }
    ],
    "sg:phone":"+1 210 342 2941",
    "sg:postcode":"78230",
    "sg:province":"TX",
    "wof:name":"B&B Products Co",
    "wof:placetype":"venue"
},
  "geometry": {"coordinates":[-98.54862300000001,29.519523],"type":"Point"}
}