{
  "type": "Feature",
  "properties": {
    "iso:country":"US",
    "sg:address":"404 W Broadway St",
    "sg:city":"Winnsboro",
    "sg:classifiers":[
        {
            "category":"Restaurant",
            "type":"Food & Drink"
        }
    ],
    "sg:menulink":"http://www.allmenus.com/tx/winnsboro/130746-subway/menu/",
    "sg:phone":"+1 903 342 3556",
    "sg:postcode":"75494",
    "sg:province":"TX",
    "sg:tags":[
        "american",
        "sandwich"
    ],
    "wof:name":"Subway",
    "wof:placetype":"venue"
},
  "geometry": {"coordinates":[-95.29271,32.957748],"type":"Point"}
}