{
  "type": "Feature",
  "properties": {
    "iso:country":"US",
    "sg:address":"5390 W 34th St",
    "sg:city":"Houston",
    "sg:classifiers":[
        {
            "category":"Professional",
            "subcategory":"Computer Services",
            "type":"Services"
        }
    ],
    "sg:phone":"+1 713 957 4999",
    "sg:postcode":"77092",
    "sg:province":"TX",
    "sg:tags":[
        "repair"
    ],
    "sg:website":"www.champion-computers.com",
    "wof:name":"Champion Computers Inc",
    "wof:placetype":"venue"
},
  "geometry": {"coordinates":[-95.468091,29.819657],"type":"Point"}
}