{
  "type": "Feature",
  "properties": {
    "iso:country":"US",
    "sg:address":"7048 el Cajon Dr",
    "sg:city":"El Paso",
    "sg:classifiers":[
        {
            "category":"Professional",
            "subcategory":"Detective & Security Services",
            "type":"Services"
        }
    ],
    "sg:phone":"+1 915 581 1184",
    "sg:postcode":"79912",
    "sg:province":"TX",
    "sg:tags":[
        "system"
    ],
    "wof:name":"Knockout Security Systems",
    "wof:placetype":"venue"
},
  "geometry": {"coordinates":[-106.55353700000001,31.831855],"type":"Point"}
}