{
  "type": "Feature",
  "properties": {
    "iso:country":"US",
    "sg:address":"5919 Ingram Rd",
    "sg:city":"San Antonio",
    "sg:classifiers":[
        {
            "category":"Organizations",
            "subcategory":"Religious Organization",
            "type":"Services"
        }
    ],
    "sg:phone":"+1 210 435 6211",
    "sg:postcode":"78228",
    "sg:province":"TX",
    "sg:tags":[
        "church"
    ],
    "wof:name":"Saint Dominic Church",
    "wof:placetype":"venue"
},
  "geometry": {"coordinates":[-98.600872,29.466198],"type":"Point"}
}