{
  "type": "Feature",
  "properties": {
    "iso:country":"US",
    "sg:address":"3901 W University Dr",
    "sg:city":"Edinburg",
    "sg:classifiers":[
        {
            "category":"Social Services",
            "subcategory":"Job Training",
            "type":"Services"
        },
        {
            "category":"Social Services",
            "type":"Services"
        }
    ],
    "sg:phone":"+1 956 289 1224",
    "sg:postcode":"78539",
    "sg:province":"TX",
    "sg:tags":[
        "employee",
        "assistance",
        "program"
    ],
    "wof:name":"South Texas Occupational Train",
    "wof:placetype":"venue"
},
  "geometry": {"coordinates":[-98.184928,26.304736],"type":"Point"}
}