{
  "type": "Feature",
  "properties": {
    "iso:country":"US",
    "sg:address":"5815 Montana Ave",
    "sg:city":"El Paso",
    "sg:classifiers":[
        {
            "category":"Autos & Motor Vehicles",
            "subcategory":"Automobile Sales",
            "type":"Retail Goods"
        }
    ],
    "sg:phone":"+1 915 779 2272",
    "sg:postcode":"79925",
    "sg:province":"TX",
    "sg:tags":[
        "car",
        "dealer"
    ],
    "sg:website":"www.casaford.com",
    "wof:name":"Casa Ford Inc",
    "wof:placetype":"venue"
},
  "geometry": {"coordinates":[-106.41829300000001,31.783827],"type":"Point"}
}