{
  "type": "Feature",
  "properties": {
    "iso:country":"US",
    "sg:address":"2207 N Beach St",
    "sg:city":"Fort Worth",
    "sg:classifiers":[
        {
            "category":"Health Services",
            "subcategory":"Doctor",
            "type":"Services"
        }
    ],
    "sg:phone":"+1 817 838 2332",
    "sg:postcode":"76111",
    "sg:province":"TX",
    "sg:tags":[
        "medical"
    ],
    "wof:name":"Cabansag C Filemon MD",
    "wof:placetype":"venue"
},
  "geometry": {"coordinates":[-97.29066,32.791486],"type":"Point"}
}