{
  "type": "Feature",
  "properties": {
    "iso:country":"US",
    "sg:address":"2002 Thousand Pines Dr",
    "sg:city":"Humble",
    "sg:classifiers":[
        {
            "category":"Recreation",
            "type":"Entertainment"
        }
    ],
    "sg:phone":"+1 281 358 0397",
    "sg:postcode":"77339",
    "sg:province":"TX",
    "wof:name":"Black Belt Promotions",
    "wof:placetype":"venue"
},
  "geometry": {"coordinates":[-95.22203,30.046802],"type":"Point"}
}