{
  "type": "Feature",
  "properties": {
    "iso:country":"US",
    "sg:address":"2217 Handley Ederville Rd",
    "sg:city":"Fort Worth",
    "sg:classifiers":[
        {
            "category":"Manufacturing",
            "subcategory":"Printing",
            "type":"Manufacturing & Wholesale Goods"
        }
    ],
    "sg:phone":"+1 817 589 2011",
    "sg:postcode":"76118",
    "sg:province":"TX",
    "sg:tags":[
        "label"
    ],
    "sg:website":"www.precisionpressandlabel.com",
    "wof:name":"Precision Press",
    "wof:placetype":"venue"
},
  "geometry": {"coordinates":[-97.217146,32.778814],"type":"Point"}
}