{
  "type": "Feature",
  "properties": {
    "iso:country":"US",
    "sg:address":"7202 N Fm 620",
    "sg:city":"Austin",
    "sg:classifiers":[
        {
            "category":"Building & Trades",
            "subcategory":"Construction",
            "type":"Services"
        }
    ],
    "sg:phone":"+1 512 918 2655",
    "sg:postcode":"78726",
    "sg:province":"TX",
    "sg:tags":[
        "contractor"
    ],
    "wof:name":"New Austin Homes",
    "wof:placetype":"venue"
},
  "geometry": {"coordinates":[-97.853307,30.405016],"type":"Point"}
}