{
  "type": "Feature",
  "properties": {
    "iso:country":"US",
    "sg:address":"875 Straus Rd Ste 500",
    "sg:city":"Cedar Hill",
    "sg:classifiers":[
        {
            "category":"Professional",
            "subcategory":"Lawyer & Legal Services",
            "type":"Services"
        }
    ],
    "sg:phone":"+1 972 293 3090",
    "sg:postcode":"75104",
    "sg:province":"TX",
    "sg:website":"www.markjcarroll.com",
    "wof:name":"Mark J Carroll, Attorney",
    "wof:placetype":"venue"
},
  "geometry": {"coordinates":[-96.951042,32.603376],"type":"Point"}
}