{
  "type": "Feature",
  "properties": {
    "iso:country":"US",
    "sg:address":"135 Lamar Ave",
    "sg:city":"Paris",
    "sg:classifiers":[
        {
            "category":"Shopping",
            "subcategory":"Clothing, Apparel, & Fashions",
            "type":"Retail Goods"
        }
    ],
    "sg:phone":"+1 903 739 9778",
    "sg:postcode":"75460",
    "sg:province":"TX",
    "sg:tags":[
        "boutique"
    ],
    "wof:name":"Dressed To A Tea",
    "wof:placetype":"venue"
},
  "geometry": {"coordinates":[-95.555121,33.66152],"type":"Point"}
}