{
  "type": "Feature",
  "properties": {
    "iso:country":"US",
    "sg:address":"160 W Gray St",
    "sg:city":"Houston",
    "sg:classifiers":[
        {
            "category":"Bars & Pubs",
            "subcategory":"Sports Bar",
            "type":"Food & Drink"
        }
    ],
    "sg:phone":"+1 713 523 7768",
    "sg:postcode":"77019",
    "sg:province":"TX",
    "sg:website":"www.junctionbarandgrill.com/",
    "wof:name":"Junction Bar & Grill",
    "wof:placetype":"venue"
},
  "geometry": {"coordinates":[-95.38117,29.753269],"type":"Point"}
}