{
  "type": "Feature",
  "properties": {
    "iso:country":"US",
    "sg:address":"5860 Westheimer Rd",
    "sg:city":"Houston",
    "sg:classifiers":[
        {
            "category":"Deli",
            "type":"Food & Drink"
        },
        {
            "category":"Restaurant",
            "type":"Food & Drink"
        }
    ],
    "sg:menulink":"http://www.allmenus.com/tx/houston/12830-jasons-deli/menu/",
    "sg:phone":"+1 713 975 7878",
    "sg:postcode":"77057",
    "sg:province":"TX",
    "sg:tags":[
        "deli",
        "american"
    ],
    "wof:name":"Jason's Deli",
    "wof:placetype":"venue"
},
  "geometry": {"coordinates":[-95.48362,29.737901],"type":"Point"}
}