{
  "type": "Feature",
  "properties": {
    "iso:country":"US",
    "sg:address":"8926 N Lamar Blvd",
    "sg:city":"Austin",
    "sg:classifiers":[
        {
            "category":"Building & Trades",
            "subcategory":"Landscaping Services",
            "type":"Services"
        },
        {
            "category":"Home & Garden",
            "subcategory":"Building Materials",
            "type":"Retail Goods"
        },
        {
            "category":"Building & Trades",
            "subcategory":"Construction",
            "type":"Services"
        }
    ],
    "sg:phone":"+1 512 832 5423",
    "sg:postcode":"78753",
    "sg:province":"TX",
    "sg:tags":[
        "repair",
        "altering",
        "contractor",
        "maintenance",
        "improvement",
        "remodeling",
        "landscape"
    ],
    "wof:name":"Gadgetronics",
    "wof:placetype":"venue"
},
  "geometry": {"coordinates":[-97.699642,30.358476],"type":"Point"}
}