{
  "type": "Feature",
  "properties": {
    "iso:country":"US",
    "sg:address":"270 Kensington Ln",
    "sg:city":"Austin",
    "sg:classifiers":[
        {
            "category":"Professional",
            "subcategory":"Management & Consulting",
            "type":"Services"
        }
    ],
    "sg:phone":"+1 512 301 5666",
    "sg:postcode":"78737",
    "sg:province":"TX",
    "sg:tags":[
        "science",
        "consultant",
        "academic"
    ],
    "wof:name":"Otto Environmental Systems",
    "wof:placetype":"venue"
},
  "geometry": {"coordinates":[-97.987442,30.199003],"type":"Point"}
}