{
  "type": "Feature",
  "properties": {
    "iso:country":"US",
    "sg:address":"9519 Brewster St",
    "sg:city":"Dallas",
    "sg:classifiers":[
        {
            "category":"Professional",
            "type":"Services"
        }
    ],
    "sg:phone":"+1 214 275 0080",
    "sg:postcode":"75227",
    "sg:province":"TX",
    "wof:name":"Patricks",
    "wof:placetype":"venue"
},
  "geometry": {"coordinates":[-96.658423,32.766143],"type":"Point"}
}