{
  "type": "Feature",
  "properties": {
    "iso:country":"US",
    "sg:address":"2909 Feathercrest Dr",
    "sg:city":"Austin",
    "sg:classifiers":[
        {
            "category":"Home & Garden",
            "subcategory":"Home Furnishings",
            "type":"Retail Goods"
        }
    ],
    "sg:phone":"+1 512 246 2987",
    "sg:postcode":"78728",
    "sg:province":"TX",
    "wof:name":"Kandha International Inc",
    "wof:placetype":"venue"
},
  "geometry": {"coordinates":[-97.685698,30.448972],"type":"Point"}
}