{
  "type": "Feature",
  "properties": {
    "iso:country":"US",
    "sg:address":"8515 Fondren Rd",
    "sg:city":"Houston",
    "sg:classifiers":[
        {
            "category":"Real Estate",
            "subcategory":"Surveying",
            "type":"Services"
        },
        {
            "category":"Building & Trades",
            "subcategory":"Construction",
            "type":"Services"
        }
    ],
    "sg:phone":"+1 713 776 8853",
    "sg:postcode":"77074",
    "sg:province":"TX",
    "sg:tags":[
        "surveyor",
        "residential"
    ],
    "wof:name":"Wright Land Survey",
    "wof:placetype":"venue"
},
  "geometry": {"coordinates":[-95.508684,29.687216],"type":"Point"}
}