{
  "type": "Feature",
  "properties": {
    "iso:country":"US",
    "sg:address":"6 Jardine Ct",
    "sg:city":"Conroe",
    "sg:classifiers":[
        {
            "category":"Shopping",
            "type":"Retail Goods"
        }
    ],
    "sg:phone":"+1 936 321 8915",
    "sg:postcode":"77385",
    "sg:province":"TX",
    "sg:tags":[
        "merchandise"
    ],
    "wof:name":"Datasystem Solutions",
    "wof:placetype":"venue"
},
  "geometry": {"coordinates":[-95.439975,30.218666],"type":"Point"}
}