{
  "type": "Feature",
  "properties": {
    "iso:country":"US",
    "sg:address":"1706 Old Mill Rd",
    "sg:city":"Cedar Park",
    "sg:classifiers":[
        {
            "category":"Retail",
            "subcategory":"Repair Shop",
            "type":"Services"
        },
        {
            "category":"Retail",
            "subcategory":"Funeral Services",
            "type":"Services"
        }
    ],
    "sg:phone":"+1 512 331 1979",
    "sg:postcode":"78613",
    "sg:province":"TX",
    "sg:tags":[
        "information"
    ],
    "wof:name":"Ken Lyons Consulting",
    "wof:placetype":"venue"
},
  "geometry": {"coordinates":[-97.833915,30.471517],"type":"Point"}
}