{
  "type": "Feature",
  "properties": {
    "iso:country":"US",
    "sg:address":"1221 W Airport Fwy",
    "sg:city":"Irving",
    "sg:classifiers":[
        {
            "category":"Professional",
            "subcategory":"Advertising",
            "type":"Services"
        }
    ],
    "sg:phone":"+1 972 594 8005",
    "sg:postcode":"75062",
    "sg:province":"TX",
    "sg:tags":[
        "mailing",
        "shipping"
    ],
    "wof:name":"Mail N More",
    "wof:placetype":"venue"
},
  "geometry": {"coordinates":[-96.96055800000001,32.837386],"type":"Point"}
}