{
  "type": "Feature",
  "properties": {
    "iso:country":"US",
    "sg:address":"2708 Burke Rd",
    "sg:city":"Pasadena",
    "sg:classifiers":[
        {
            "category":"Building & Trades",
            "subcategory":"Construction",
            "type":"Services"
        }
    ],
    "sg:phone":"+1 713 946 2421",
    "sg:postcode":"77502",
    "sg:province":"TX",
    "sg:tags":[
        "wallcoverings-installation",
        "wallpaper",
        "painting",
        "contractor"
    ],
    "wof:name":"Castillos Painting Co",
    "wof:placetype":"venue"
},
  "geometry": {"coordinates":[-95.186829,29.6712],"type":"Point"}
}