{
  "type": "Feature",
  "properties": {
    "iso:country":"US",
    "sg:address":"508 W Esparada Dr",
    "sg:city":"Georgetown",
    "sg:classifiers":[
        {
            "category":"Manufacturing",
            "subcategory":"Rubber & Plastics",
            "type":"Manufacturing & Wholesale Goods"
        }
    ],
    "sg:phone":"+1 512 863 7953",
    "sg:postcode":"78628",
    "sg:province":"TX",
    "sg:tags":[
        "product",
        "mfg"
    ],
    "wof:name":"Eco Action",
    "wof:placetype":"venue"
},
  "geometry": {"coordinates":[-97.71096,30.680458],"type":"Point"}
}