{
  "type": "Feature",
  "properties": {
    "iso:country":"US",
    "sg:address":"15301 Dallas parkway Ste 1005",
    "sg:city":"Addison",
    "sg:classifiers":[
        {
            "category":"Banks & Credit Unions",
            "subcategory":"Financial Services",
            "type":"Services"
        }
    ],
    "sg:phone":"+1 972 866 7960",
    "sg:postcode":"75001",
    "sg:province":"TX",
    "wof:name":"Windfall Profit",
    "wof:placetype":"venue"
},
  "geometry": {"coordinates":[-96.822677,32.958374],"type":"Point"}
}