{
  "type": "Feature",
  "properties": {
    "iso:country":"US",
    "sg:address":"2304 Ruby St",
    "sg:city":"Rosenberg",
    "sg:classifiers":[
        {
            "category":"Building & Trades",
            "subcategory":"Construction",
            "type":"Services"
        }
    ],
    "sg:phone":"+1 281 342 5854",
    "sg:postcode":"77471",
    "sg:province":"TX",
    "sg:tags":[
        "concrete",
        "contractor"
    ],
    "wof:name":"Fernandez Concrete",
    "wof:placetype":"venue"
},
  "geometry": {"coordinates":[-95.823232,29.541999],"type":"Point"}
}