{
  "type": "Feature",
  "properties": {
    "iso:country":"US",
    "sg:address":"307 S 2nd St",
    "sg:city":"Crockett",
    "sg:classifiers":[
        {
            "category":"Organizations",
            "subcategory":"Religious Organization",
            "type":"Services"
        }
    ],
    "sg:phone":"+1 936 545 0806",
    "sg:postcode":"75835",
    "sg:province":"TX",
    "sg:tags":[
        "church"
    ],
    "wof:name":"Greater St Paul Baptist Church",
    "wof:placetype":"venue"
},
  "geometry": {"coordinates":[-95.45940400000001,31.316244],"type":"Point"}
}