{
  "type": "Feature",
  "properties": {
    "iso:country":"US",
    "sg:address":"3415 Custer Rd",
    "sg:city":"Plano",
    "sg:classifiers":[
        {
            "category":"Professional",
            "type":"Services"
        },
        {
            "category":"Wholesale",
            "subcategory":"Electrical",
            "type":"Manufacturing & Wholesale Goods"
        }
    ],
    "sg:phone":"+1 972 943 8400",
    "sg:postcode":"75023",
    "sg:province":"TX",
    "sg:tags":[
        "connector"
    ],
    "wof:name":"Molex Inc",
    "wof:placetype":"venue"
},
  "geometry": {"coordinates":[-96.73347699999999,33.042206],"type":"Point"}
}