{
  "type": "Feature",
  "properties": {
    "iso:country":"US",
    "sg:address":"1101 N Cage Blvd",
    "sg:city":"Pharr",
    "sg:classifiers":[
        {
            "category":"Professional",
            "subcategory":"Accounting & Tax Preparation",
            "type":"Services"
        }
    ],
    "sg:phone":"+1 956 787 0521",
    "sg:postcode":"78577",
    "sg:province":"TX",
    "sg:tags":[
        "accountant"
    ],
    "wof:name":"Juan Nunez CPA",
    "wof:placetype":"venue"
},
  "geometry": {"coordinates":[-98.182265,26.205946],"type":"Point"}
}