{
  "type": "Feature",
  "properties": {
    "iso:country":"US",
    "sg:address":"249 S 11th St",
    "sg:city":"Abilene",
    "sg:classifiers":[
        {
            "category":"Manufacturing",
            "subcategory":"Pet Food",
            "type":"Manufacturing & Wholesale Goods"
        }
    ],
    "sg:phone":"+1 325 676 3302",
    "sg:postcode":"79602",
    "sg:province":"TX",
    "sg:tags":[
        "feed",
        "mfg",
        "prepared"
    ],
    "wof:name":"Volume Feed & Seed Inc",
    "wof:placetype":"venue"
},
  "geometry": {"coordinates":[-99.72599200000001,32.436774],"type":"Point"}
}