{
  "type": "Feature",
  "properties": {
    "iso:country":"US",
    "sg:address":"120 W Myrtle St",
    "sg:city":"Angleton",
    "sg:classifiers":[
        {
            "category":"Professional",
            "subcategory":"Lawyer & Legal Services",
            "type":"Services"
        }
    ],
    "sg:phone":"+1 979 265 6931",
    "sg:postcode":"77515",
    "sg:province":"TX",
    "wof:name":"Watson Thomas W",
    "wof:placetype":"venue"
},
  "geometry": {"coordinates":[-95.432059,29.165557],"type":"Point"}
}