{
  "type": "Feature",
  "properties": {
    "iso:country":"US",
    "sg:address":"207 E South St",
    "sg:city":"Alvin",
    "sg:classifiers":[
        {
            "category":"Food & Beverages",
            "subcategory":"Groceries & Convenience Stores",
            "type":"Retail Goods"
        }
    ],
    "sg:phone":"+1 281 585 5188",
    "sg:postcode":"77511",
    "sg:province":"TX",
    "sg:tags":[
        "grocer"
    ],
    "wof:name":"H E B Foods",
    "wof:placetype":"venue"
},
  "geometry": {"coordinates":[-95.242842,29.409302],"type":"Point"}
}