{
  "type": "Feature",
  "properties": {
    "iso:country":"US",
    "sg:address":"9255 W Sam Houston Pkwy S Ofc",
    "sg:city":"Houston",
    "sg:classifiers":[
        {
            "category":"Real Estate",
            "subcategory":"Real Estate Operator",
            "type":"Services"
        }
    ],
    "sg:phone":"+1 713 988 3535",
    "sg:postcode":"77099",
    "sg:province":"TX",
    "sg:tags":[
        "apartment"
    ],
    "wof:name":"Glenwood Apartments",
    "wof:placetype":"venue"
},
  "geometry": {"coordinates":[-95.558403,29.6824],"type":"Point"}
}