{
  "type": "Feature",
  "properties": {
    "iso:country":"US",
    "sg:address":"5486 Walzem Rd",
    "sg:city":"San Antonio",
    "sg:classifiers":[
        {
            "category":"Shopping",
            "subcategory":"Gifts & Souvenirs",
            "type":"Retail Goods"
        }
    ],
    "sg:phone":"+1 210 650 4795",
    "sg:postcode":"78218",
    "sg:province":"TX",
    "sg:tags":[
        "shop"
    ],
    "wof:name":"Saigon Music & Oriental Gifts",
    "wof:placetype":"venue"
},
  "geometry": {"coordinates":[-98.38121700000001,29.510208],"type":"Point"}
}