{
  "type": "Feature",
  "properties": {
    "iso:country":"US",
    "sg:address":"2801 Greenlee Dr",
    "sg:city":"Austin",
    "sg:classifiers":[
        {
            "category":"Professional",
            "subcategory":"Business Services",
            "type":"Services"
        }
    ],
    "sg:phone":"+1 512 236 1413",
    "sg:postcode":"78703",
    "sg:province":"TX",
    "sg:tags":[
        "auction"
    ],
    "wof:name":"Jessee Liquidating Partnership Gp",
    "wof:placetype":"venue"
},
  "geometry": {"coordinates":[-97.767403,30.300911],"type":"Point"}
}