{
  "type": "Feature",
  "properties": {
    "iso:country":"US",
    "sg:address":"1805 Great Oaks Dr",
    "sg:city":"Round Rock",
    "sg:classifiers":[
        {
            "category":"Local Transit",
            "type":"Transportation"
        }
    ],
    "sg:phone":"+1 512 345 5466",
    "sg:postcode":"78681",
    "sg:province":"TX",
    "sg:tags":[
        "limousine"
    ],
    "wof:name":"Austin Prime-Time Limousine",
    "wof:placetype":"venue"
},
  "geometry": {"coordinates":[-97.737645,30.530311],"type":"Point"}
}