{
  "type": "Feature",
  "properties": {
    "iso:country":"US",
    "sg:address":"1304 Greenbriar Ave",
    "sg:city":"Friendswood",
    "sg:classifiers":[
        {
            "category":"Professional",
            "subcategory":"Business Services",
            "type":"Services"
        }
    ],
    "sg:phone":"+1 281 992 1223",
    "sg:postcode":"77546",
    "sg:province":"TX",
    "wof:name":"Brady Aviation Ltd Co",
    "wof:placetype":"venue"
},
  "geometry": {"coordinates":[-95.20226099999999,29.507765],"type":"Point"}
}