{
  "type": "Feature",
  "properties": {
    "iso:country":"US",
    "sg:address":"179 Pasadena Town Square Mall",
    "sg:city":"Pasadena",
    "sg:classifiers":[
        {
            "category":"Restaurant",
            "type":"Food & Drink"
        }
    ],
    "sg:menulink":"http://www.allmenus.com/tx/pasadena/179367-chick-fil-a/menu/",
    "sg:phone":"+1 713 473 5092",
    "sg:postcode":"77506",
    "sg:province":"TX",
    "sg:tags":[
        "wrap",
        "soup",
        "american",
        "sandwich",
        "salad"
    ],
    "wof:name":"Chick-fil-A",
    "wof:placetype":"venue"
},
  "geometry": {"coordinates":[-95.20060700000001,29.697191],"type":"Point"}
}