{
  "type": "Feature",
  "properties": {
    "iso:country":"US",
    "sg:address":"9900 S I H 35 Ste B",
    "sg:city":"Austin",
    "sg:classifiers":[
        {
            "category":"Home & Garden",
            "subcategory":"Furniture",
            "type":"Retail Goods"
        }
    ],
    "sg:phone":"+1 512 292 1004",
    "sg:postcode":"78748",
    "sg:province":"TX",
    "sg:tags":[
        "store"
    ],
    "wof:name":"Bassett Furniture",
    "wof:placetype":"venue"
},
  "geometry": {"coordinates":[-97.791191,30.156157],"type":"Point"}
}