{
  "type": "Feature",
  "properties": {
    "iso:country":"US",
    "sg:address":"9710 Beechnut St",
    "sg:city":"Houston",
    "sg:classifiers":[
        {
            "category":"Food & Beverages",
            "subcategory":"Groceries & Convenience Stores",
            "type":"Retail Goods"
        }
    ],
    "sg:phone":"+1 713 778 1142",
    "sg:postcode":"77036",
    "sg:province":"TX",
    "wof:name":"Valero",
    "wof:placetype":"venue"
},
  "geometry": {"coordinates":[-95.55291800000001,29.689907],"type":"Point"}
}