{
  "type": "Feature",
  "properties": {
    "iso:country":"US",
    "sg:address":"5220 Broadway",
    "sg:city":"San Antonio",
    "sg:classifiers":[
        {
            "category":"Personal",
            "subcategory":"Beauty Salon",
            "type":"Services"
        }
    ],
    "sg:phone":"+1 210 822 4040",
    "sg:postcode":"78209",
    "sg:province":"TX",
    "wof:name":"Arcadia Hair Studio",
    "wof:placetype":"venue"
},
  "geometry": {"coordinates":[-98.462794,29.475737],"type":"Point"}
}