{
  "type": "Feature",
  "properties": {
    "iso:country":"US",
    "sg:address":"1200 Lake Air Dr #162",
    "sg:city":"Waco",
    "sg:classifiers":[
        {
            "category":"Landmark",
            "subcategory":"Tourist Information",
            "type":"Public Place"
        }
    ],
    "sg:phone":"+1 254 754 8687",
    "sg:postcode":"76710",
    "sg:province":"TX",
    "sg:tags":[
        "promoter",
        "tours-operators"
    ],
    "sg:website":"http://www.snobbytours.com",
    "wof:name":"Snobby Tours, Inc., and Americana Heritage Tours by Snobby Tours, Inc.",
    "wof:placetype":"venue"
},
  "geometry": {"coordinates":[-97.186249,31.532471],"type":"Point"}
}