{
  "type": "Feature",
  "properties": {
    "iso:country":"US",
    "sg:address":"6312 N 19th St",
    "sg:city":"Waco",
    "sg:classifiers":[
        {
            "category":"Retail",
            "subcategory":"Laundry & Dry Cleaning",
            "type":"Services"
        }
    ],
    "sg:phone":"+1 254 757 1707",
    "sg:postcode":"76708",
    "sg:province":"TX",
    "sg:tags":[
        "cleaner",
        "rug",
        "carpet"
    ],
    "wof:name":"American Carpet Cleaners",
    "wof:placetype":"venue"
},
  "geometry": {"coordinates":[-97.195104,31.602579],"type":"Point"}
}