{
  "type": "Feature",
  "properties": {
    "iso:country":"US",
    "sg:address":"7205 Breezy Pass Cv",
    "sg:city":"Austin",
    "sg:classifiers":[
        {
            "category":"Communications",
            "type":"Services"
        }
    ],
    "sg:phone":"+1 512 963 1096",
    "sg:postcode":"78749",
    "sg:province":"TX",
    "wof:name":"Columbus Communications",
    "wof:placetype":"venue"
},
  "geometry": {"coordinates":[-97.875733,30.231003],"type":"Point"}
}