{
  "type": "Feature",
  "properties": {
    "iso:country":"US",
    "sg:address":"500 Inwood Rd",
    "sg:city":"Texarkana",
    "sg:classifiers":[
        {
            "category":"Shopping",
            "subcategory":"Department Store",
            "type":"Retail Goods"
        }
    ],
    "sg:phone":"+1 903 832 5262",
    "sg:postcode":"75501",
    "sg:province":"TX",
    "wof:name":"Brintwood Addition Lots",
    "wof:placetype":"venue"
},
  "geometry": {"coordinates":[-94.190459,33.423551],"type":"Point"}
}