{
  "type": "Feature",
  "properties": {
    "iso:country":"US",
    "sg:address":"1600 Lake Woodlands Dr",
    "sg:city":"The Woodlands",
    "sg:classifiers":[
        {
            "category":"Shopping",
            "type":"Retail Goods"
        }
    ],
    "sg:phone":"+1 281 419 7405",
    "sg:postcode":"77380",
    "sg:province":"TX",
    "sg:tags":[
        "cosmetic",
        "perfume"
    ],
    "wof:name":"Ulta 3 Cosmetics",
    "wof:placetype":"venue"
},
  "geometry": {"coordinates":[-95.460499,30.166382],"type":"Point"}
}