{
  "type": "Feature",
  "properties": {
    "iso:country":"US",
    "sg:address":"6050 Melody Ln",
    "sg:city":"Dallas",
    "sg:classifiers":[
        {
            "category":"Restaurant",
            "type":"Food & Drink"
        }
    ],
    "sg:phone":"+1 214 696 6793",
    "sg:postcode":"75231",
    "sg:province":"TX",
    "sg:tags":[
        "caterer"
    ],
    "wof:name":"Creative Touch Catering Svc",
    "wof:placetype":"venue"
},
  "geometry": {"coordinates":[-96.760802,32.868108],"type":"Point"}
}