{
  "type": "Feature",
  "properties": {
    "iso:country":"US",
    "sg:address":"1018 Lexington Cir",
    "sg:city":"Edinburg",
    "sg:classifiers":[
        {
            "category":"Building & Trades",
            "subcategory":"Construction",
            "type":"Services"
        }
    ],
    "sg:phone":"+1 956 453 9999",
    "sg:postcode":"78539",
    "sg:province":"TX",
    "sg:tags":[
        "contractor"
    ],
    "wof:name":"Payne Canal Lining Tech LLC",
    "wof:placetype":"venue"
},
  "geometry": {"coordinates":[-98.182512,26.29592],"type":"Point"}
}