{
  "type": "Feature",
  "properties": {
    "iso:country":"US",
    "sg:address":"3814 Herald St",
    "sg:city":"Houston",
    "sg:classifiers":[
        {
            "category":"Organizations",
            "subcategory":"Religious Organization",
            "type":"Services"
        }
    ],
    "sg:phone":"+1 713 675 7860",
    "sg:postcode":"77029",
    "sg:province":"TX",
    "sg:tags":[
        "church"
    ],
    "wof:name":"Fellowship Missionary Baptist Church",
    "wof:placetype":"venue"
},
  "geometry": {"coordinates":[-95.2752,29.796801],"type":"Point"}
}