{
  "type": "Feature",
  "properties": {
    "iso:country":"US",
    "sg:address":"11442 Hempstead Rd",
    "sg:city":"Houston",
    "sg:classifiers":[
        {
            "category":"Autos & Motor Vehicles",
            "subcategory":"Auto Supplies",
            "type":"Retail Goods"
        }
    ],
    "sg:phone":"+1 713 680 1665",
    "sg:postcode":"77092",
    "sg:province":"TX",
    "wof:name":"Ardons Tires",
    "wof:placetype":"venue"
},
  "geometry": {"coordinates":[-95.477532,29.814058],"type":"Point"}
}