{
  "type": "Feature",
  "properties": {
    "iso:country":"US",
    "sg:address":"3130 Lawrence Rd",
    "sg:city":"Wichita Falls",
    "sg:classifiers":[
        {
            "category":"Personal",
            "subcategory":"Beauty Salon",
            "type":"Services"
        }
    ],
    "sg:phone":"+1 940 691 2990",
    "sg:postcode":"76308",
    "sg:province":"TX",
    "wof:name":"Smart Style Family Hair Salon",
    "wof:placetype":"venue"
},
  "geometry": {"coordinates":[-98.53999399999999,33.875818],"type":"Point"}
}