{
  "type": "Feature",
  "properties": {
    "iso:country":"US",
    "sg:address":"2501 Oak Lawn Ave",
    "sg:city":"Dallas",
    "sg:classifiers":[
        {
            "category":"Banks & Credit Unions",
            "subcategory":"Investment Brokerage",
            "type":"Services"
        }
    ],
    "sg:phone":"+1 214 219 2891",
    "sg:postcode":"75219",
    "sg:province":"TX",
    "sg:tags":[
        "advisory",
        "financial",
        "broker",
        "mortgage"
    ],
    "wof:name":"Woodhaven Financial Services",
    "wof:placetype":"venue"
},
  "geometry": {"coordinates":[-96.81380799999999,32.804791],"type":"Point"}
}