{
  "type": "Feature",
  "properties": {
    "iso:country":"US",
    "sg:address":"3430 W Gist Ave",
    "sg:city":"Midland",
    "sg:classifiers":[
        {
            "category":"Building & Trades",
            "subcategory":"Plumbing",
            "type":"Services"
        }
    ],
    "sg:phone":"+1 432 689 2951",
    "sg:postcode":"79701",
    "sg:province":"TX",
    "sg:tags":[
        "product",
        "management",
        "energy",
        "system"
    ],
    "wof:name":"Temp Energy",
    "wof:placetype":"venue"
},
  "geometry": {"coordinates":[-102.111093,31.971413],"type":"Point"}
}