{
  "type": "Feature",
  "properties": {
    "iso:country":"US",
    "sg:address":"3226 FM 1997",
    "sg:city":"Marshall",
    "sg:classifiers":[
        {
            "category":"Building & Trades",
            "subcategory":"Construction",
            "type":"Services"
        }
    ],
    "sg:phone":"+1 903 935 7427",
    "sg:postcode":"75670",
    "sg:province":"TX",
    "sg:tags":[
        "general",
        "contractor"
    ],
    "wof:name":"B G Construction",
    "wof:placetype":"venue"
},
  "geometry": {"coordinates":[-94.373013,32.573972],"type":"Point"}
}