{
  "type": "Feature",
  "properties": {
    "iso:country":"US",
    "sg:address":"746 Alpine Dr",
    "sg:city":"Kerrville",
    "sg:classifiers":[
        {
            "category":"Health Services",
            "subcategory":"Nursing And Care Facility",
            "type":"Services"
        }
    ],
    "sg:phone":"+1 830 896 2323",
    "sg:postcode":"78028",
    "sg:province":"TX",
    "sg:tags":[
        "home",
        "convalescent"
    ],
    "wof:name":"Alpine Terrace Retirement Vlg",
    "wof:placetype":"venue"
},
  "geometry": {"coordinates":[-99.11277800000001,30.066531],"type":"Point"}
}