{
  "type": "Feature",
  "properties": {
    "iso:country":"US",
    "sg:address":"9323 Skillman St",
    "sg:city":"Dallas",
    "sg:classifiers":[
        {
            "category":"Retail",
            "subcategory":"Repair Shop",
            "type":"Services"
        }
    ],
    "sg:phone":"+1 214 221 3931",
    "sg:postcode":"75243",
    "sg:province":"TX",
    "sg:tags":[
        "appliance"
    ],
    "sg:website":"www.eandmhomeservice.com",
    "wof:name":"E & M Home Svc",
    "wof:placetype":"venue"
},
  "geometry": {"coordinates":[-96.716954,32.901656],"type":"Point"}
}