{
  "type": "Feature",
  "properties": {
    "iso:country":"US",
    "sg:address":"2915 Scott Mill Rd",
    "sg:city":"Carrollton",
    "sg:classifiers":[
        {
            "category":"Education",
            "subcategory":"School",
            "type":"Public Place"
        }
    ],
    "sg:phone":"+1 972 968 3400",
    "sg:postcode":"75007",
    "sg:province":"TX",
    "sg:tags":[
        "high",
        "middle",
        "elementary"
    ],
    "wof:name":"Carrollton-Farmers Branch Independent School District",
    "wof:placetype":"venue"
},
  "geometry": {"coordinates":[-96.880182,32.994102],"type":"Point"}
}