{
  "type": "Feature",
  "properties": {
    "iso:country":"US",
    "sg:address":"1941 N I- 35E",
    "sg:city":"Carrollton",
    "sg:classifiers":[
        {
            "category":"Autos & Motor Vehicles",
            "subcategory":"Fuel & Gas Station",
            "type":"Retail Goods"
        }
    ],
    "sg:phone":"+1 972 245 1170",
    "sg:postcode":"75006",
    "sg:province":"TX",
    "sg:tags":[
        "store"
    ],
    "wof:name":"Chevron",
    "wof:placetype":"venue"
},
  "geometry": {"coordinates":[-96.919067,32.966584],"type":"Point"}
}