{
  "type": "Feature",
  "properties": {
    "iso:country":"US",
    "sg:address":"840 Travis St",
    "sg:city":"Vidor",
    "sg:classifiers":[
        {
            "category":"Home & Garden",
            "subcategory":"Home Furnishings",
            "type":"Retail Goods"
        }
    ],
    "sg:phone":"+1 409 769 7306",
    "sg:postcode":"77662",
    "sg:province":"TX",
    "sg:tags":[
        "appliance",
        "household",
        "u"
    ],
    "wof:name":"Hext Enterprises Inc",
    "wof:placetype":"venue"
},
  "geometry": {"coordinates":[-94.01294900000001,30.135059],"type":"Point"}
}