{
  "type": "Feature",
  "properties": {
    "iso:country":"US",
    "sg:address":"800 W Airport Fwy Ste 1001",
    "sg:city":"Irving",
    "sg:classifiers":[
        {
            "category":"Real Estate",
            "subcategory":"Architect",
            "type":"Services"
        }
    ],
    "sg:phone":"+1 972 438 4380",
    "sg:postcode":"75062",
    "sg:province":"TX",
    "sg:website":"www.hkiarchitects.com",
    "wof:name":"Hki Architects",
    "wof:placetype":"venue"
},
  "geometry": {"coordinates":[-96.954123,32.835763],"type":"Point"}
}