{
  "type": "Feature",
  "properties": {
    "iso:country":"US",
    "sg:address":"937 N Wilcrest Dr",
    "sg:city":"Houston",
    "sg:classifiers":[
        {
            "category":"Shopping",
            "subcategory":"Florist",
            "type":"Retail Goods"
        }
    ],
    "sg:phone":"+1 713 461 5112",
    "sg:postcode":"77079",
    "sg:province":"TX",
    "wof:name":"Nosegay Flower Shop",
    "wof:placetype":"venue"
},
  "geometry": {"coordinates":[-95.575712,29.782556],"type":"Point"}
}