{
  "type": "Feature",
  "properties": {
    "iso:country":"US",
    "sg:address":"7030 Pine Grove Dr",
    "sg:city":"Houston",
    "sg:classifiers":[
        {
            "category":"Building & Trades",
            "subcategory":"Landscaping Services",
            "type":"Services"
        }
    ],
    "sg:phone":"+1 713 462 1268",
    "sg:postcode":"77092",
    "sg:province":"TX",
    "sg:tags":[
        "lawn",
        "maintenance",
        "grounds"
    ],
    "wof:name":"Kenton Soots Lawn Svc",
    "wof:placetype":"venue"
},
  "geometry": {"coordinates":[-95.495136,29.854728],"type":"Point"}
}