{
  "type": "Feature",
  "properties": {
    "iso:country":"US",
    "sg:address":"2401 W Waco Dr",
    "sg:city":"Waco",
    "sg:classifiers":[
        {
            "category":"Professional",
            "subcategory":"Credit Reporting & Collection",
            "type":"Services"
        },
        {
            "category":"Banks & Credit Unions",
            "subcategory":"Bank",
            "type":"Services"
        }
    ],
    "sg:phone":"+1 254 753 0033",
    "sg:postcode":"76707",
    "sg:province":"TX",
    "sg:tags":[
        "financing"
    ],
    "wof:name":"Sun Loan Co",
    "wof:placetype":"venue"
},
  "geometry": {"coordinates":[-97.15319100000001,31.543004],"type":"Point"}
}