{
  "type": "Feature",
  "properties": {
    "iso:country":"US",
    "sg:address":"1216 N Central Expy Ste 104",
    "sg:city":"Mckinney",
    "sg:classifiers":[
        {
            "category":"Organizations",
            "subcategory":"Religious Organization",
            "type":"Services"
        }
    ],
    "sg:phone":"+1 214 585 3225",
    "sg:postcode":"75070",
    "sg:province":"TX",
    "sg:tags":[
        "counseling"
    ],
    "wof:name":"RHEMA Counseling Associates",
    "wof:placetype":"venue"
},
  "geometry": {"coordinates":[-96.63764500000001,33.208705],"type":"Point"}
}