{
  "type": "Feature",
  "properties": {
    "iso:country":"US",
    "sg:address":"6959 Arapaho Rd Ste 200",
    "sg:city":"Dallas",
    "sg:classifiers":[
        {
            "category":"Personal",
            "subcategory":"Barber",
            "type":"Services"
        }
    ],
    "sg:phone":"+1 972 503 4444",
    "sg:postcode":"75248",
    "sg:province":"TX",
    "wof:name":"Executive Barbers by Laurie",
    "wof:placetype":"venue"
},
  "geometry": {"coordinates":[-96.78939800000001,32.9622],"type":"Point"}
}