{
  "type": "Feature",
  "properties": {
    "iso:country":"US",
    "sg:address":"202 N Greenville Ave Ste B",
    "sg:city":"Richardson",
    "sg:classifiers":[
        {
            "category":"Shopping",
            "subcategory":"Hobbies, Toys, & Games",
            "type":"Retail Goods"
        }
    ],
    "sg:phone":"+1 972 234 5500",
    "sg:postcode":"75081",
    "sg:province":"TX",
    "sg:tags":[
        "toy",
        "store"
    ],
    "sg:website":"www.enchantedplayhouse.com",
    "wof:name":"Enchanted Cottage the",
    "wof:placetype":"venue"
},
  "geometry": {"coordinates":[-96.72930100000001,32.949299],"type":"Point"}
}