{
  "type": "Feature",
  "properties": {
    "iso:country":"US",
    "sg:address":"9002 Petersham Dr",
    "sg:city":"Houston",
    "sg:classifiers":[
        {
            "category":"Building & Trades",
            "subcategory":"Electrical",
            "type":"Services"
        }
    ],
    "sg:phone":"+1 713 270 7034",
    "sg:postcode":"77031",
    "sg:province":"TX",
    "sg:tags":[
        "electrical",
        "contractor"
    ],
    "wof:name":"Hwa Electric Inc",
    "wof:placetype":"venue"
},
  "geometry": {"coordinates":[-95.54450799999999,29.654156],"type":"Point"}
}