{
  "type": "Feature",
  "properties": {
    "iso:country":"US",
    "sg:address":"722 S Belt Line Rd",
    "sg:city":"Irving",
    "sg:classifiers":[
        {
            "category":"Building & Trades",
            "subcategory":"Construction",
            "type":"Services"
        }
    ],
    "sg:phone":"+1 972 986 5977",
    "sg:postcode":"75060",
    "sg:province":"TX",
    "sg:tags":[
        "interior",
        "automobile",
        "stripping",
        "pain",
        "used"
    ],
    "wof:name":"Storage Vehicles",
    "wof:placetype":"venue"
},
  "geometry": {"coordinates":[-96.994427,32.805282],"type":"Point"}
}