{
  "type": "Feature",
  "properties": {
    "iso:country":"US",
    "sg:address":"5437 Cedar Creek Dr",
    "sg:city":"Houston",
    "sg:classifiers":[
        {
            "category":"Professional",
            "subcategory":"Business Services",
            "type":"Services"
        }
    ],
    "sg:phone":"+1 713 621 1207",
    "sg:postcode":"77056",
    "sg:province":"TX",
    "sg:tags":[
        "acquisition"
    ],
    "wof:name":"Gulf Financial Resources",
    "wof:placetype":"venue"
},
  "geometry": {"coordinates":[-95.470698,29.75221],"type":"Point"}
}