{
  "type": "Feature",
  "properties": {
    "iso:country":"US",
    "sg:address":"518 S Broadway St Ste A",
    "sg:city":"Plainview",
    "sg:classifiers":[
        {
            "category":"Personal",
            "subcategory":"Beauty Salon",
            "type":"Services"
        }
    ],
    "sg:phone":"+1 806 293 9903",
    "sg:postcode":"79072",
    "sg:province":"TX",
    "wof:name":"Off Broadway Hair Designs",
    "wof:placetype":"venue"
},
  "geometry": {"coordinates":[-101.70284100000001,34.174386],"type":"Point"}
}