{
  "type": "Feature",
  "properties": {
    "iso:country":"US",
    "sg:address":"6321 Carter Rd",
    "sg:city":"Granbury",
    "sg:classifiers":[
        {
            "category":"Local Transit",
            "type":"Transportation"
        }
    ],
    "sg:phone":"+1 817 573 2198",
    "sg:postcode":"76048",
    "sg:province":"TX",
    "wof:name":"The Airport Service",
    "wof:placetype":"venue"
},
  "geometry": {"coordinates":[-97.71955699999999,32.387215],"type":"Point"}
}