{
  "type": "Feature",
  "properties": {
    "iso:country":"US",
    "sg:address":"1312 Brook Hollow Way",
    "sg:city":"Bryan",
    "sg:classifiers":[
        {
            "category":"Professional",
            "subcategory":"Lawyer & Legal Services",
            "type":"Services"
        }
    ],
    "sg:phone":"+1 979 774 4003",
    "sg:postcode":"77802",
    "sg:province":"TX",
    "sg:tags":[
        "attorney",
        "criminal",
        "law"
    ],
    "wof:name":"Michael D Price",
    "wof:placetype":"venue"
},
  "geometry": {"coordinates":[-96.36272,30.659536],"type":"Point"}
}