{
  "type": "Feature",
  "properties": {
    "iso:country":"US",
    "sg:address":"1500 E Lamar Blvd",
    "sg:city":"Arlington",
    "sg:classifiers":[
        {
            "category":"Real Estate",
            "subcategory":"Real Estate Operator",
            "type":"Services"
        }
    ],
    "sg:phone":"+1 817 265 2822",
    "sg:postcode":"76011",
    "sg:province":"TX",
    "sg:tags":[
        "building",
        "apartment"
    ],
    "wof:name":"Carriage House Apartments",
    "wof:placetype":"venue"
},
  "geometry": {"coordinates":[-97.088599,32.764631],"type":"Point"}
}