{
  "type": "Feature",
  "properties": {
    "iso:country":"US",
    "sg:address":"229 19th St",
    "sg:city":"Hondo",
    "sg:phone":"+1 830 426 2247",
    "sg:postcode":"78861",
    "sg:province":"TX",
    "sg:website":"http://www.whataburger.com",
    "wof:name":"Whataburger Restaurants",
    "wof:placetype":"venue"
},
  "geometry": {"coordinates":[-99.128906,29.348258],"type":"Point"}
}