{
  "type": "Feature",
  "properties": {
    "iso:country":"US",
    "sg:address":"4214 S Hwy 183",
    "sg:city":"Austin",
    "sg:classifiers":[
        {
            "category":"Autos & Motor Vehicles",
            "subcategory":"Automobile Sales",
            "type":"Retail Goods"
        }
    ],
    "sg:phone":"+1 512 385 5188",
    "sg:postcode":"78744",
    "sg:province":"TX",
    "sg:tags":[
        "car",
        "used",
        "dealer"
    ],
    "wof:name":"Cars America S A",
    "wof:placetype":"venue"
},
  "geometry": {"coordinates":[-97.686026,30.189255],"type":"Point"}
}