{
  "type": "Feature",
  "properties": {
    "iso:country":"US",
    "sg:address":"800 E Collins St",
    "sg:city":"Llano",
    "sg:classifiers":[
        {
            "category":"Shopping",
            "subcategory":"Musical Instruments",
            "type":"Retail Goods"
        }
    ],
    "sg:phone":"+1 325 247 4057",
    "sg:postcode":"78643",
    "sg:province":"TX",
    "wof:name":"Berrio Music Retail",
    "wof:placetype":"venue"
},
  "geometry": {"coordinates":[-98.66464499999999,30.767663],"type":"Point"}
}