{
  "type": "Feature",
  "properties": {
    "iso:country":"US",
    "sg:address":"115 Greystone Cir",
    "sg:city":"Boerne",
    "sg:classifiers":[
        {
            "category":"Wholesale",
            "subcategory":"Hardware",
            "type":"Manufacturing & Wholesale Goods"
        }
    ],
    "sg:phone":"+1 830 336 4574",
    "sg:postcode":"78006",
    "sg:province":"TX",
    "sg:tags":[
        "hardware-wholesale",
        "manufacturer"
    ],
    "wof:name":"Shill X Bradley",
    "wof:placetype":"venue"
},
  "geometry": {"coordinates":[-98.612358,29.858879],"type":"Point"}
}