{
  "type": "Feature",
  "properties": {
    "iso:country":"US",
    "sg:address":"3310 Windsor Rd",
    "sg:city":"Austin",
    "sg:classifiers":[
        {
            "category":"Professional",
            "type":"Services"
        }
    ],
    "sg:phone":"+1 512 477 9196",
    "sg:postcode":"78703",
    "sg:province":"TX",
    "wof:name":"Jennifer Tuthill Johnston",
    "wof:placetype":"venue"
},
  "geometry": {"coordinates":[-97.771989,30.298974],"type":"Point"}
}