{
  "type": "Feature",
  "properties": {
    "iso:country":"US",
    "sg:address":"180 Hirth Dr",
    "sg:city":"Crowley",
    "sg:classifiers":[
        {
            "category":"Autos & Motor Vehicles",
            "subcategory":"Automobile Sales",
            "type":"Retail Goods"
        }
    ],
    "sg:phone":"+1 817 721 0786",
    "sg:postcode":"76036",
    "sg:province":"TX",
    "sg:tags":[
        "dealers-used",
        "car",
        "used",
        "cars-wholesale"
    ],
    "wof:name":"E C Cars",
    "wof:placetype":"venue"
},
  "geometry": {"coordinates":[-97.348292,32.570671],"type":"Point"}
}