{
  "type": "Feature",
  "properties": {
    "iso:country":"US",
    "sg:address":"6854 Arkansas Rd",
    "sg:city":"Lubbock",
    "sg:classifiers":[
        {
            "category":"Manufacturing",
            "subcategory":"Buildings",
            "type":"Manufacturing & Wholesale Goods"
        },
        {
            "category":"Building & Trades",
            "subcategory":"Construction",
            "type":"Services"
        }
    ],
    "sg:phone":"+1 806 438 1255",
    "sg:postcode":"79407",
    "sg:province":"TX",
    "sg:tags":[
        "home",
        "builder",
        "contractor"
    ],
    "wof:name":"R-Gar Construction Co.",
    "wof:placetype":"venue"
},
  "geometry": {"coordinates":[-102.093738,33.586977],"type":"Point"}
}