{
  "type": "Feature",
  "properties": {
    "iso:country":"US",
    "sg:address":"1408 Mill Creek Dr",
    "sg:city":"Salado",
    "sg:classifiers":[
        {
            "category":"Professional",
            "type":"Services"
        },
        {
            "category":"Manufacturing",
            "subcategory":"Petroleum Products",
            "type":"Manufacturing & Wholesale Goods"
        },
        {
            "category":"Utilities",
            "subcategory":"Fuel Oil & Lpg",
            "type":"Services"
        },
        {
            "category":"Wholesale",
            "subcategory":"Petroleum",
            "type":"Manufacturing & Wholesale Goods"
        }
    ],
    "sg:phone":"+1 254 947 8186",
    "sg:postcode":"76571",
    "sg:province":"TX",
    "sg:tags":[
        "development",
        "products-wholesale",
        "oils-petroleum",
        "gas",
        "field",
        "exploration",
        "manufacturer"
    ],
    "wof:name":"Salado Oil Co",
    "wof:placetype":"venue"
},
  "geometry": {"coordinates":[-97.52154899999999,30.955333],"type":"Point"}
}