{
  "type": "Feature",
  "properties": {
    "iso:country":"US",
    "sg:address":"10633 Lake Creek Pkwy",
    "sg:city":"Austin",
    "sg:classifiers":[
        {
            "category":"Education",
            "subcategory":"School",
            "type":"Public Place"
        }
    ],
    "sg:phone":"+1 512 258 5878",
    "sg:postcode":"78750",
    "sg:province":"TX",
    "wof:name":"Anderson Mill Christian Academy",
    "wof:placetype":"venue"
},
  "geometry": {"coordinates":[-97.802803,30.457399],"type":"Point"}
}