{
  "type": "Feature",
  "properties": {
    "iso:country":"US",
    "sg:address":"1270 N Oakmont Loop",
    "sg:city":"Laredo",
    "sg:classifiers":[
        {
            "category":"Retail",
            "subcategory":"Repair Shop",
            "type":"Services"
        },
        {
            "category":"Shopping",
            "subcategory":"Bicycles & Sporting Goods",
            "type":"Retail Goods"
        }
    ],
    "sg:phone":"+1 956 791 2300",
    "sg:postcode":"78045",
    "sg:province":"TX",
    "sg:tags":[
        "equipment",
        "golf",
        "refinishing"
    ],
    "wof:name":"Tee Time Custom Golf",
    "wof:placetype":"venue"
},
  "geometry": {"coordinates":[-99.472825,27.590667],"type":"Point"}
}