{
  "type": "Feature",
  "properties": {
    "iso:country":"US",
    "sg:address":"909 W Lewis St",
    "sg:city":"Conroe",
    "sg:classifiers":[
        {
            "category":"Professional",
            "subcategory":"Advertising",
            "type":"Services"
        },
        {
            "category":"Professional",
            "subcategory":"Computer Services",
            "type":"Services"
        }
    ],
    "sg:phone":"+1 936 756 2292",
    "sg:postcode":"77301",
    "sg:province":"TX",
    "sg:tags":[
        "publisher",
        "software",
        "agency",
        "specialty",
        "developer"
    ],
    "sg:website":"http://www.tcconcepts.com",
    "wof:name":"Tc Concepts",
    "wof:placetype":"venue"
},
  "geometry": {"coordinates":[-95.464353,30.315745],"type":"Point"}
}