{
  "type": "Feature",
  "properties": {
    "iso:country":"US",
    "sg:address":"3114 E 13th St",
    "sg:city":"Austin",
    "sg:classifiers":[
        {
            "category":"Professional",
            "type":"Services"
        }
    ],
    "sg:phone":"+1 512 478 6961",
    "sg:postcode":"78702",
    "sg:province":"TX",
    "wof:name":"Lloyd C & Lillian G Kerle",
    "wof:placetype":"venue"
},
  "geometry": {"coordinates":[-97.700936,30.277659],"type":"Point"}
}