{
  "type": "Feature",
  "properties": {
    "iso:country":"US",
    "sg:address":"1003 Antoine Dr",
    "sg:city":"Houston",
    "sg:classifiers":[
        {
            "category":"Wholesale",
            "subcategory":"Painting Supplies",
            "type":"Manufacturing & Wholesale Goods"
        }
    ],
    "sg:phone":"+1 713 688 5976",
    "sg:postcode":"77055",
    "sg:province":"TX",
    "sg:tags":[
        "paint"
    ],
    "wof:name":"ICI Dulux Paint",
    "wof:placetype":"venue"
},
  "geometry": {"coordinates":[-95.476128,29.787234],"type":"Point"}
}