{
  "type": "Feature",
  "properties": {
    "iso:country":"US",
    "sg:address":"3430 Rockyridge Dr",
    "sg:city":"Houston",
    "sg:classifiers":[
        {
            "category":"Sports & Exercise",
            "subcategory":"Swimming Pool",
            "type":"Entertainment"
        }
    ],
    "sg:phone":"+1 832 252 6851",
    "sg:postcode":"77063",
    "sg:province":"TX",
    "sg:website":"www.wildewestpool.com",
    "wof:name":"Wilde West Pool",
    "wof:placetype":"venue"
},
  "geometry": {"coordinates":[-95.5326,29.7257],"type":"Point"}
}