{
  "type": "Feature",
  "properties": {
    "iso:country":"US",
    "sg:address":"17802 Davenport Rd",
    "sg:city":"Dallas",
    "sg:classifiers":[
        {
            "category":"Shopping",
            "subcategory":"Optical Goods",
            "type":"Retail Goods"
        }
    ],
    "sg:phone":"+1 972 248 7780",
    "sg:postcode":"75252",
    "sg:province":"TX",
    "wof:name":"Nouveau Eyewear",
    "wof:placetype":"venue"
},
  "geometry": {"coordinates":[-96.79361,32.993909],"type":"Point"}
}