{
  "type": "Feature",
  "properties": {
    "iso:country":"US",
    "sg:address":"9312 Faircrest Dr",
    "sg:city":"Dallas",
    "sg:classifiers":[
        {
            "category":"Professional",
            "subcategory":"Computer Services",
            "type":"Services"
        }
    ],
    "sg:phone":"+1 214 348 7589",
    "sg:postcode":"75238",
    "sg:province":"TX",
    "sg:tags":[
        "related"
    ],
    "wof:name":"Rudd Technical Services L",
    "wof:placetype":"venue"
},
  "geometry": {"coordinates":[-96.723179,32.889587],"type":"Point"}
}