{
  "type": "Feature",
  "properties": {
    "iso:country":"US",
    "sg:address":"1710 Ayers St",
    "sg:city":"Corpus Christi",
    "sg:classifiers":[
        {
            "category":"Shopping",
            "subcategory":"Jewelry",
            "type":"Retail Goods"
        }
    ],
    "sg:phone":"+1 361 884 7114",
    "sg:postcode":"78404",
    "sg:province":"TX",
    "wof:name":"Jaclyn Floral and Boutique",
    "wof:placetype":"venue"
},
  "geometry": {"coordinates":[-97.40445,27.771545],"type":"Point"}
}