{
  "type": "Feature",
  "properties": {
    "iso:country":"US",
    "sg:address":"1312 Ginger Spice. Ln.",
    "sg:city":"Pflugerville",
    "sg:classifiers":[
        {
            "category":"Professional",
            "type":"Services"
        }
    ],
    "sg:phone":"+1 512 293 7394",
    "sg:postcode":"78660",
    "sg:province":"TX",
    "sg:website":"www.AtticCare.com",
    "wof:name":"Attic Care Ltd. Co.",
    "wof:placetype":"venue"
},
  "geometry": {"coordinates":[-97.636037,30.426196],"type":"Point"}
}