{
  "type": "Feature",
  "properties": {
    "iso:country":"US",
    "sg:address":"327 Roundabout Rd",
    "sg:city":"Huntsville",
    "sg:classifiers":[
        {
            "category":"Wholesale",
            "subcategory":"Stationery",
            "type":"Manufacturing & Wholesale Goods"
        }
    ],
    "sg:phone":"+1 936 294 0490",
    "sg:postcode":"77320",
    "sg:province":"TX",
    "sg:tags":[
        "cards",
        "greeting"
    ],
    "wof:name":"R & R Sales Co",
    "wof:placetype":"venue"
},
  "geometry": {"coordinates":[-95.56612,30.727571],"type":"Point"}
}