{
  "type": "Feature",
  "properties": {
    "iso:country":"US",
    "sg:address":"6826 Hyacinth Ln",
    "sg:city":"Dallas",
    "sg:classifiers":[
        {
            "category":"Building & Trades",
            "subcategory":"Construction",
            "type":"Services"
        }
    ],
    "sg:phone":"+1 972 380 5656",
    "sg:postcode":"75252",
    "sg:province":"TX",
    "sg:tags":[
        "for",
        "residential",
        "commercial",
        "general",
        "build",
        "contractor"
    ],
    "wof:name":"Diamond General Contrs Inc",
    "wof:placetype":"venue"
},
  "geometry": {"coordinates":[-96.784672,32.990884],"type":"Point"}
}