{
  "type": "Feature",
  "properties": {
    "iso:country":"US",
    "sg:address":"9210 Converse Business Ln",
    "sg:city":"Converse",
    "sg:classifiers":[
        {
            "category":"Retail",
            "subcategory":"Repair Shop",
            "type":"Services"
        }
    ],
    "sg:phone":"+1 210 658 0208",
    "sg:postcode":"78109",
    "sg:province":"TX",
    "sg:tags":[
        "upholsterer"
    ],
    "wof:name":"Mark's Custom Upholstery",
    "wof:placetype":"venue"
},
  "geometry": {"coordinates":[-98.30523599999999,29.512779],"type":"Point"}
}