{
  "type": "Feature",
  "properties": {
    "iso:country":"US",
    "sg:address":"3571 Far West Blvd Ste 31",
    "sg:city":"Austin",
    "sg:classifiers":[
        {
            "category":"Building & Trades",
            "subcategory":"Construction",
            "type":"Services"
        }
    ],
    "sg:phone":"+1 512 217 7136",
    "sg:postcode":"78634",
    "sg:province":"TX",
    "sg:tags":[
        "air",
        "heating",
        "conditioning/hvac"
    ],
    "sg:website":"www.superiorairquality.com",
    "wof:name":"Superior Air Quality",
    "wof:placetype":"venue"
},
  "geometry": {"coordinates":[-97.754588,30.353435],"type":"Point"}
}