{
  "type": "Feature",
  "properties": {
    "iso:country":"US",
    "sg:address":"13376 N US Hwy 183",
    "sg:city":"Austin",
    "sg:classifiers":[
        {
            "category":"Real Estate",
            "subcategory":"Real Estate Agent",
            "type":"Services"
        }
    ],
    "sg:phone":"+1 512 258 6677",
    "sg:postcode":"78750",
    "sg:province":"TX",
    "wof:name":"Coldwell Banker",
    "wof:placetype":"venue"
},
  "geometry": {"coordinates":[-97.789965,30.44647],"type":"Point"}
}