{
  "type": "Feature",
  "properties": {
    "iso:country":"US",
    "sg:address":"202 E 2nd St",
    "sg:city":"Lampasas",
    "sg:classifiers":[
        {
            "category":"Organizations",
            "subcategory":"Religious Organization",
            "type":"Services"
        }
    ],
    "sg:phone":"+1 512 556 8624",
    "sg:postcode":"76550",
    "sg:province":"TX",
    "wof:name":"Edge Youth Hangout Lampasas",
    "wof:placetype":"venue"
},
  "geometry": {"coordinates":[-98.18067000000001,31.066076],"type":"Point"}
}