{
  "type": "Feature",
  "properties": {
    "iso:country":"US",
    "sg:address":"7913 Harwood Rd",
    "sg:city":"N Richland Hills",
    "sg:classifiers":[
        {
            "category":"Retail",
            "subcategory":"Car Wash",
            "type":"Services"
        }
    ],
    "sg:phone":"+1 817 503 9813",
    "sg:postcode":"76180",
    "sg:province":"TX",
    "sg:tags":[
        "polishing",
        "washing"
    ],
    "wof:name":"Sweet Spot Car Wash",
    "wof:placetype":"venue"
},
  "geometry": {"coordinates":[-97.210345,32.842626],"type":"Point"}
}