{
  "type": "Feature",
  "properties": {
    "iso:country":"US",
    "sg:address":"512 Manor Rd",
    "sg:city":"Laredo",
    "sg:classifiers":[
        {
            "category":"Freight",
            "type":"Transportation"
        }
    ],
    "sg:phone":"+1 956 725 9138",
    "sg:postcode":"78041",
    "sg:province":"TX",
    "wof:name":"Casso Imex Forwarding Inc",
    "wof:placetype":"venue"
},
  "geometry": {"coordinates":[-99.474863,27.566511],"type":"Point"}
}