{
  "type": "Feature",
  "properties": {
    "iso:country":"US",
    "sg:address":"2050 N Stemmons Fwy",
    "sg:city":"Dallas",
    "sg:classifiers":[
        {
            "category":"Wholesale",
            "subcategory":"Furniture",
            "type":"Manufacturing & Wholesale Goods"
        }
    ],
    "sg:phone":"+1 214 747 5233",
    "sg:postcode":"75207",
    "sg:province":"TX",
    "wof:name":"Estate House",
    "wof:placetype":"venue"
},
  "geometry": {"coordinates":[-96.82226,32.799989],"type":"Point"}
}