{
  "type": "Feature",
  "properties": {
    "iso:country":"US",
    "sg:address":"3620 Katy Fwy",
    "sg:city":"Houston",
    "sg:classifiers":[
        {
            "category":"Restaurant",
            "type":"Food & Drink"
        }
    ],
    "sg:phone":"+1 713 861 0778",
    "sg:postcode":"77007",
    "sg:province":"TX",
    "sg:tags":[
        "eating"
    ],
    "wof:name":"Subway Sandwiches 28320",
    "wof:placetype":"venue"
},
  "geometry": {"coordinates":[-95.39722,29.777061],"type":"Point"}
}