{
  "type": "Feature",
  "properties": {
    "iso:country":"US",
    "sg:address":"1030 Early Blvd",
    "sg:city":"Brownwood",
    "sg:phone":"+1 325 643 3596",
    "sg:postcode":"76802",
    "sg:province":"TX",
    "sg:tags":[
        "equipment",
        "station"
    ],
    "wof:name":"Chambers Pump Svc Inc",
    "wof:placetype":"venue"
},
  "geometry": {"coordinates":[-98.93724400000001,31.745812],"type":"Point"}
}