{
  "type": "Feature",
  "properties": {
    "iso:country":"US",
    "sg:address":"3303 Sherwood Way",
    "sg:city":"San Angelo",
    "sg:classifiers":[
        {
            "category":"Ice Cream",
            "type":"Food & Drink"
        }
    ],
    "sg:menulink":"http://www.allmenus.com/tx/san-angelo/242728-baskin-robbins/menu/",
    "sg:phone":"+1 325 944 3699",
    "sg:postcode":"76901",
    "sg:province":"TX",
    "sg:tags":[
        "american"
    ],
    "wof:name":"Baskin-Robbins",
    "wof:placetype":"venue"
},
  "geometry": {"coordinates":[-100.480081,31.445187],"type":"Point"}
}