{
  "type": "Feature",
  "properties": {
    "iso:country":"US",
    "sg:address":"2450 Wickersham Ln # 1202",
    "sg:city":"Austin",
    "sg:classifiers":[
        {
            "category":"Communications",
            "type":"Services"
        }
    ],
    "sg:phone":"+1 512 833 5915",
    "sg:postcode":"78741",
    "sg:province":"TX",
    "sg:tags":[
        "translator",
        "interpreter"
    ],
    "wof:name":"Pan American Translations, Inc.",
    "wof:placetype":"venue"
},
  "geometry": {"coordinates":[-97.725081,30.224921],"type":"Point"}
}