{
  "type": "Feature",
  "properties": {
    "iso:country":"US",
    "sg:address":"15612 Poynette Pl",
    "sg:city":"Austin",
    "sg:classifiers":[
        {
            "category":"Professional",
            "subcategory":"Computer Services",
            "type":"Services"
        }
    ],
    "sg:phone":"+1 512 255 2676",
    "sg:postcode":"78717",
    "sg:province":"TX",
    "sg:tags":[
        "related"
    ],
    "wof:name":"Success Connection",
    "wof:placetype":"venue"
},
  "geometry": {"coordinates":[-97.73757000000001,30.486761],"type":"Point"}
}