{
  "type": "Feature",
  "properties": {
    "iso:country":"US",
    "sg:address":"1220 Ellis Ave",
    "sg:city":"Lufkin",
    "sg:classifiers":[
        {
            "category":"Professional",
            "subcategory":"Art Services",
            "type":"Services"
        },
        {
            "category":"Professional",
            "subcategory":"Advertising",
            "type":"Services"
        }
    ],
    "sg:phone":"+1 936 637 9411",
    "sg:postcode":"75904",
    "sg:province":"TX",
    "sg:tags":[
        "graphic",
        "agency",
        "designer"
    ],
    "wof:name":"Pioneer Design Group",
    "wof:placetype":"venue"
},
  "geometry": {"coordinates":[-94.743661,31.335067],"type":"Point"}
}