{
  "type": "Feature",
  "properties": {
    "iso:country":"US",
    "sg:address":"14700 Tomball Parkway",
    "sg:city":"Houston",
    "sg:classifiers":[
        {
            "category":"Autos & Motor Vehicles",
            "subcategory":"Automobile Sales",
            "type":"Retail Goods"
        }
    ],
    "sg:phone":"+1 281 445 1083",
    "sg:postcode":"77086",
    "sg:province":"TX",
    "sg:tags":[
        "dealers-used",
        "car",
        "cars-wholesale",
        "used",
        "truck"
    ],
    "wof:name":"Fincher Fred Motors",
    "wof:placetype":"venue"
},
  "geometry": {"coordinates":[-95.504735,29.928087],"type":"Point"}
}