{
  "type": "Feature",
  "properties": {
    "iso:country":"US",
    "sg:address":"1800 Royston Ln",
    "sg:city":"Round Rock",
    "sg:classifiers":[
        {
            "category":"Professional",
            "type":"Services"
        }
    ],
    "sg:phone":"+1 512 990 8470",
    "sg:postcode":"78664",
    "sg:province":"TX",
    "wof:name":"Huges",
    "wof:placetype":"venue"
},
  "geometry": {"coordinates":[-97.659505,30.461886],"type":"Point"}
}