{
  "type": "Feature",
  "properties": {
    "iso:country":"US",
    "sg:address":"4008 Spring Branch Dr W",
    "sg:city":"Pearland",
    "sg:classifiers":[
        {
            "category":"Building & Trades",
            "subcategory":"Plumbing",
            "type":"Services"
        }
    ],
    "sg:phone":"+1 281 489 9638",
    "sg:postcode":"77584",
    "sg:province":"TX",
    "sg:tags":[
        "air",
        "conditioning",
        "contractor",
        "system",
        "heating"
    ],
    "wof:name":"Kneeland Air & Heat Inc",
    "wof:placetype":"venue"
},
  "geometry": {"coordinates":[-95.305367,29.535113],"type":"Point"}
}