{
  "type": "Feature",
  "properties": {
    "iso:country":"US",
    "sg:address":"19525 Mcdonald St",
    "sg:city":"Lytle",
    "sg:classifiers":[
        {
            "category":"Travel",
            "subcategory":"Hotels & Motels",
            "type":"Entertainment"
        }
    ],
    "sg:phone":"+1 830 772 4777",
    "sg:postcode":"78052",
    "sg:province":"TX",
    "sg:tags":[
        "lodging"
    ],
    "sg:website":"http://www.daysinn.com",
    "wof:name":"San Antonio/Lytle Days Inn",
    "wof:placetype":"venue"
},
  "geometry": {"coordinates":[-98.791451,29.236344],"type":"Point"}
}