{
  "type": "Feature",
  "properties": {
    "iso:country":"US",
    "sg:address":"4564 Cedar Path Dr",
    "sg:city":"Dallas",
    "sg:classifiers":[
        {
            "category":"Freight",
            "type":"Transportation"
        }
    ],
    "sg:phone":"+1 214 339 8671",
    "sg:postcode":"75211",
    "sg:province":"TX",
    "sg:tags":[
        "operator",
        "local",
        "trucking"
    ],
    "wof:name":"Aleman Dump Truck Service",
    "wof:placetype":"venue"
},
  "geometry": {"coordinates":[-96.895511,32.720922],"type":"Point"}
}