{
  "type": "Feature",
  "properties": {
    "iso:country":"US",
    "sg:address":"2427 Crow Valley St",
    "sg:city":"San Antonio",
    "sg:classifiers":[
        {
            "category":"Personal",
            "type":"Services"
        }
    ],
    "sg:phone":"+1 210 496 7907",
    "sg:postcode":"78232",
    "sg:province":"TX",
    "wof:name":"Robert Andrew Maxwell",
    "wof:placetype":"venue"
},
  "geometry": {"coordinates":[-98.453896,29.578305],"type":"Point"}
}