{
  "type": "Feature",
  "properties": {
    "iso:country":"US",
    "sg:address":"2001 State Hwy 114 Bus",
    "sg:city":"Roanoke",
    "sg:classifiers":[
        {
            "category":"Health Services",
            "subcategory":"Doctor",
            "type":"Services"
        }
    ],
    "sg:phone":"+1 817 490 9885",
    "sg:postcode":"76262",
    "sg:province":"TX",
    "sg:tags":[
        "dentist"
    ],
    "sg:website":"www.summitdentalcare.net",
    "wof:name":"Summit Dental Care Inc",
    "wof:placetype":"venue"
},
  "geometry": {"coordinates":[-97.234138,33.010225],"type":"Point"}
}