{
  "type": "Feature",
  "properties": {
    "iso:country":"US",
    "sg:address":"2724 W Gentry Pkwy",
    "sg:city":"Tyler",
    "sg:classifiers":[
        {
            "category":"Shopping",
            "subcategory":"Discount & Variety Stores",
            "type":"Retail Goods"
        }
    ],
    "sg:phone":"+1 903 533 9516",
    "sg:postcode":"75702",
    "sg:province":"TX",
    "wof:name":"Dollar General",
    "wof:placetype":"venue"
},
  "geometry": {"coordinates":[-95.331486,32.369926],"type":"Point"}
}