{
  "type": "Feature",
  "properties": {
    "iso:country":"US",
    "sg:address":"7216 Marywood Cir",
    "sg:city":"Austin",
    "sg:classifiers":[
        {
            "category":"Professional",
            "type":"Services"
        }
    ],
    "sg:phone":"+1 512 926 0618",
    "sg:postcode":"78723",
    "sg:province":"TX",
    "wof:name":"Theresa Bayer",
    "wof:placetype":"venue"
},
  "geometry": {"coordinates":[-97.67602100000001,30.321653],"type":"Point"}
}