{
  "type": "Feature",
  "properties": {
    "iso:country":"US",
    "sg:address":"100 FM 730",
    "sg:city":"Boyd",
    "sg:classifiers":[
        {
            "category":"Restaurant",
            "type":"Food & Drink"
        }
    ],
    "sg:phone":"+1 940 433 5955",
    "sg:postcode":"76023",
    "sg:province":"TX",
    "sg:tags":[
        "eating"
    ],
    "wof:name":"Alfred Sons Dva Boyd Pitt Stop",
    "wof:placetype":"venue"
},
  "geometry": {"coordinates":[-97.565119,33.078528],"type":"Point"}
}