{
  "type": "Feature",
  "properties": {
    "iso:country":"US",
    "sg:address":"841 Southway Cir",
    "sg:city":"Fort Worth",
    "sg:classifiers":[
        {
            "category":"Home & Garden",
            "subcategory":"Building Materials",
            "type":"Retail Goods"
        },
        {
            "category":"Building & Trades",
            "subcategory":"Construction",
            "type":"Services"
        }
    ],
    "sg:phone":"+1 817 921 3641",
    "sg:postcode":"76115",
    "sg:province":"TX",
    "sg:tags":[
        "door",
        "installation",
        "contractor"
    ],
    "sg:website":"www.overheaddoor.com",
    "wof:name":"Overhead Door Co Of Fort Worth",
    "wof:placetype":"venue"
},
  "geometry": {"coordinates":[-97.31682000000001,32.670427],"type":"Point"}
}