{
  "type": "Feature",
  "properties": {
    "iso:country":"US",
    "sg:address":"5851 Westheimer Rd",
    "sg:city":"Houston",
    "sg:classifiers":[
        {
            "category":"Personal",
            "type":"Services"
        }
    ],
    "sg:phone":"+1 713 334 7400",
    "sg:postcode":"77057",
    "sg:province":"TX",
    "sg:tags":[
        "cosmetic"
    ],
    "wof:name":"Laser Permanent Cosmetic Rmvl",
    "wof:placetype":"venue"
},
  "geometry": {"coordinates":[-95.48378599999999,29.737734],"type":"Point"}
}