{
  "type": "Feature",
  "properties": {
    "iso:country":"US",
    "sg:address":"2917 Campbell Rd",
    "sg:city":"Houston",
    "sg:classifiers":[
        {
            "category":"Retail",
            "subcategory":"Auto Repair",
            "type":"Services"
        }
    ],
    "sg:phone":"+1 713 690 2958",
    "sg:postcode":"77080",
    "sg:province":"TX",
    "wof:name":"Canlas Tire & Auto Service",
    "wof:placetype":"venue"
},
  "geometry": {"coordinates":[-95.526398,29.8197],"type":"Point"}
}