{
  "type": "Feature",
  "properties": {
    "iso:country":"US",
    "sg:address":"1717 S Pleasant Valley Rd",
    "sg:city":"Austin",
    "sg:classifiers":[
        {
            "category":"Home & Garden",
            "subcategory":"Furniture",
            "type":"Retail Goods"
        }
    ],
    "sg:phone":"+1 512 389 1012",
    "sg:postcode":"78741",
    "sg:province":"TX",
    "wof:name":"Angelas Home Furnishings",
    "wof:placetype":"venue"
},
  "geometry": {"coordinates":[-97.720742,30.236997],"type":"Point"}
}