{
  "type": "Feature",
  "properties": {
    "iso:country":"US",
    "sg:address":"1105 Pine Hurst Ct",
    "sg:city":"Mansfield",
    "sg:classifiers":[
        {
            "category":"Retail",
            "subcategory":"Funeral Services",
            "type":"Services"
        }
    ],
    "sg:phone":"+1 817 473 7897",
    "sg:postcode":"76063",
    "sg:province":"TX",
    "wof:name":"Emerald Hills Funeral Corp",
    "wof:placetype":"venue"
},
  "geometry": {"coordinates":[-97.12392,32.582613],"type":"Point"}
}