{
  "type": "Feature",
  "properties": {
    "iso:country":"US",
    "sg:address":"2808 S Laurent St",
    "sg:city":"Victoria",
    "sg:classifiers":[
        {
            "category":"Restaurant",
            "type":"Food & Drink"
        }
    ],
    "sg:phone":"+1 361 576 3005",
    "sg:postcode":"77901",
    "sg:province":"TX",
    "sg:tags":[
        "mexican"
    ],
    "wof:name":"Taco Express",
    "wof:placetype":"venue"
},
  "geometry": {"coordinates":[-96.980177,28.77077],"type":"Point"}
}