{
  "type": "Feature",
  "properties": {
    "iso:country":"US",
    "sg:address":"607 Andover St",
    "sg:city":"Spring",
    "sg:classifiers":[
        {
            "category":"Professional",
            "subcategory":"Business Services",
            "type":"Services"
        }
    ],
    "sg:phone":"+1 281 350 4151",
    "sg:postcode":"77373",
    "sg:province":"TX",
    "wof:name":"Family Service Group Inc",
    "wof:placetype":"venue"
},
  "geometry": {"coordinates":[-95.42357199999999,30.048637],"type":"Point"}
}