{
  "type": "Feature",
  "properties": {
    "iso:country":"US",
    "sg:address":"4715 Allencrest Ln",
    "sg:city":"Dallas",
    "sg:classifiers":[
        {
            "category":"Shopping",
            "subcategory":"Clothing, Apparel, & Fashions",
            "type":"Retail Goods"
        }
    ],
    "sg:phone":"+1 972 239 9986",
    "sg:postcode":"75244",
    "sg:province":"TX",
    "sg:tags":[
        "infant",
        "woman",
        "lingerie",
        "wear",
        "gift"
    ],
    "wof:name":"Sunshine & Rainbows Boutique",
    "wof:placetype":"venue"
},
  "geometry": {"coordinates":[-96.828036,32.911007],"type":"Point"}
}