{
  "type": "Feature",
  "properties": {
    "iso:country":"US",
    "sg:address":"1121 Front St",
    "sg:city":"Columbus",
    "sg:classifiers":[
        {
            "category":"Retail",
            "subcategory":"Auto Repair",
            "type":"Services"
        }
    ],
    "sg:phone":"+1 979 732 2462",
    "sg:postcode":"78934",
    "sg:province":"TX",
    "sg:tags":[
        "body",
        "automobile",
        "painting"
    ],
    "wof:name":"Jack's Body Shop",
    "wof:placetype":"venue"
},
  "geometry": {"coordinates":[-96.537903,29.70633],"type":"Point"}
}