{
  "type": "Feature",
  "properties": {
    "iso:country":"US",
    "sg:address":"613 SE Parkway St",
    "sg:city":"Azle",
    "sg:classifiers":[
        {
            "category":"Government",
            "subcategory":"Fire Station",
            "type":"Public Place"
        }
    ],
    "sg:phone":"+1 817 444 3221",
    "sg:postcode":"76020",
    "sg:province":"TX",
    "sg:tags":[
        "department"
    ],
    "wof:name":"Azle Ambulance Svc",
    "wof:placetype":"venue"
},
  "geometry": {"coordinates":[-97.537198,32.883821],"type":"Point"}
}