{
  "type": "Feature",
  "properties": {
    "iso:country":"US",
    "sg:address":"604 W Calton Rd",
    "sg:city":"Laredo",
    "sg:classifiers":[
        {
            "category":"Recreation",
            "type":"Entertainment"
        }
    ],
    "sg:phone":"+1 956 744 0725",
    "sg:postcode":"78041",
    "sg:province":"TX",
    "sg:tags":[
        "martial",
        "arts",
        "instruction"
    ],
    "wof:name":"Laredo Martial Arts Ctr",
    "wof:placetype":"venue"
},
  "geometry": {"coordinates":[-99.49985599999999,27.543763],"type":"Point"}
}