{
  "type": "Feature",
  "properties": {
    "iso:country":"US",
    "sg:address":"105 W Riverside Dr",
    "sg:city":"Austin",
    "sg:classifiers":[
        {
            "category":"Government",
            "subcategory":"Office",
            "type":"Public Place"
        }
    ],
    "sg:phone":"+1 512 469 7811",
    "sg:postcode":"78704",
    "sg:province":"TX",
    "sg:tags":[
        "state",
        "resource"
    ],
    "wof:name":"Workers Compensation Research",
    "wof:placetype":"venue"
},
  "geometry": {"coordinates":[-97.74795399999999,30.258056],"type":"Point"}
}