{
  "type": "Feature",
  "properties": {
    "iso:country":"US",
    "sg:address":"17330 Lowick St",
    "sg:city":"Spring",
    "sg:classifiers":[
        {
            "category":"Real Estate",
            "subcategory":"Real Estate Agent",
            "type":"Services"
        }
    ],
    "sg:phone":"+1 281 379 6511",
    "sg:postcode":"77379",
    "sg:province":"TX",
    "wof:name":"Mike Ross Realtor",
    "wof:placetype":"venue"
},
  "geometry": {"coordinates":[-95.560661,30.022343],"type":"Point"}
}