{
  "type": "Feature",
  "properties": {
    "iso:country":"US",
    "sg:address":"11840 Gloger St",
    "sg:city":"Houston",
    "sg:classifiers":[
        {
            "category":"Building & Trades",
            "subcategory":"Electrical",
            "type":"Services"
        }
    ],
    "sg:phone":"+1 281 987 3069",
    "sg:postcode":"77039",
    "sg:province":"TX",
    "sg:tags":[
        "electrician"
    ],
    "wof:name":"D & L Electric Co Inc",
    "wof:placetype":"venue"
},
  "geometry": {"coordinates":[-95.331001,29.8953],"type":"Point"}
}