{
  "type": "Feature",
  "properties": {
    "iso:country":"US",
    "sg:address":"1865 Briarcrest Dr",
    "sg:city":"Bryan",
    "sg:classifiers":[
        {
            "category":"Home & Garden",
            "subcategory":"Building Materials",
            "type":"Retail Goods"
        }
    ],
    "sg:phone":"+1 979 776 9812",
    "sg:postcode":"77802",
    "sg:province":"TX",
    "wof:name":"Iris Glass",
    "wof:placetype":"venue"
},
  "geometry": {"coordinates":[-96.336163,30.655503],"type":"Point"}
}