{
  "type": "Feature",
  "properties": {
    "iso:country":"US",
    "sg:address":"433 Elmview Dr",
    "sg:city":"Hurst",
    "sg:classifiers":[
        {
            "category":"Insurance",
            "subcategory":"Insurance Agent",
            "type":"Services"
        }
    ],
    "sg:phone":"+1 817 282 2017",
    "sg:postcode":"76053",
    "sg:province":"TX",
    "wof:name":"Wayne F Swanzy",
    "wof:placetype":"venue"
},
  "geometry": {"coordinates":[-97.176829,32.837784],"type":"Point"}
}