{
  "type": "Feature",
  "properties": {
    "iso:country":"US",
    "sg:address":"16211 Willow Park Dr",
    "sg:city":"Tomball",
    "sg:classifiers":[
        {
            "category":"Real Estate",
            "subcategory":"Developer",
            "type":"Services"
        }
    ],
    "sg:phone":"+1 713 683 0404",
    "sg:postcode":"77377",
    "sg:province":"TX",
    "wof:name":"Resource Commercial RE Svcs",
    "wof:placetype":"venue"
},
  "geometry": {"coordinates":[-95.609961,30.010734],"type":"Point"}
}