{
  "type": "Feature",
  "properties": {
    "iso:country":"US",
    "sg:address":"401 E Main St",
    "sg:city":"Whitesboro",
    "sg:classifiers":[
        {
            "category":"Health Services",
            "subcategory":"Clinic",
            "type":"Services"
        }
    ],
    "sg:phone":"+1 903 564 7709",
    "sg:postcode":"76273",
    "sg:province":"TX",
    "sg:tags":[
        "home"
    ],
    "wof:name":"Whitesboro Home Health Inc",
    "wof:placetype":"venue"
},
  "geometry": {"coordinates":[-96.902551,33.655629],"type":"Point"}
}