{
  "type": "Feature",
  "properties": {
    "iso:country":"US",
    "sg:address":"1159 Rs County Road 3374",
    "sg:city":"Alba",
    "sg:classifiers":[
        {
            "category":"Utilities",
            "subcategory":"Natural Gas",
            "type":"Services"
        }
    ],
    "sg:phone":"+1 903 473 2191",
    "sg:postcode":"75410",
    "sg:province":"TX",
    "sg:tags":[
        "propane"
    ],
    "wof:name":"Regency Gas Services",
    "wof:placetype":"venue"
},
  "geometry": {"coordinates":[-95.678634,32.855607],"type":"Point"}
}