{
  "type": "Feature",
  "properties": {
    "iso:country":"US",
    "sg:address":"7711 Prestwood Dr",
    "sg:city":"Houston",
    "sg:classifiers":[
        {
            "category":"Wholesale",
            "subcategory":"Groceries",
            "type":"Manufacturing & Wholesale Goods"
        }
    ],
    "sg:phone":"+1 713 975 6368",
    "sg:postcode":"77036",
    "sg:province":"TX",
    "sg:tags":[
        "food",
        "broker"
    ],
    "wof:name":"Menu Marketing Food Svc",
    "wof:placetype":"venue"
},
  "geometry": {"coordinates":[-95.521805,29.71615],"type":"Point"}
}