{
  "type": "Feature",
  "properties": {
    "iso:country":"US",
    "sg:address":"1029 Howze St",
    "sg:city":"El Paso",
    "sg:classifiers":[
        {
            "category":"Recreation",
            "type":"Entertainment"
        }
    ],
    "sg:phone":"+1 915 775 0545",
    "sg:postcode":"79903",
    "sg:province":"TX",
    "sg:tags":[
        "hall",
        "auditorium"
    ],
    "wof:name":"Columbus Club Assn Hall",
    "wof:placetype":"venue"
},
  "geometry": {"coordinates":[-106.431701,31.783927],"type":"Point"}
}