{
  "type": "Feature",
  "properties": {
    "iso:country":"US",
    "sg:address":"11119 Nepau Dr",
    "sg:city":"Stafford",
    "sg:classifiers":[
        {
            "category":"Personal",
            "subcategory":"Beauty Salon",
            "type":"Services"
        }
    ],
    "sg:phone":"+1 281 495 2536",
    "sg:postcode":"77477",
    "sg:province":"TX",
    "sg:tags":[
        "shop"
    ],
    "wof:name":"Kingsway Hair Salon",
    "wof:placetype":"venue"
},
  "geometry": {"coordinates":[-95.59088,29.662546],"type":"Point"}
}