{
  "type": "Feature",
  "properties": {
    "iso:country":"US",
    "sg:address":"1314 Rivercrest Blvd",
    "sg:city":"Allen",
    "sg:classifiers":[
        {
            "category":"Organizations",
            "subcategory":"Religious Organization",
            "type":"Services"
        }
    ],
    "sg:phone":"+1 972 359 7561",
    "sg:postcode":"75002",
    "sg:province":"TX",
    "sg:tags":[
        "church"
    ],
    "wof:name":"Church St Jude Catholic",
    "wof:placetype":"venue"
},
  "geometry": {"coordinates":[-96.640765,33.108595],"type":"Point"}
}