{
  "type": "Feature",
  "properties": {
    "iso:country":"US",
    "sg:address":"901 Boston St",
    "sg:city":"Brady",
    "sg:classifiers":[
        {
            "category":"Building & Trades",
            "subcategory":"Landscaping Services",
            "type":"Services"
        }
    ],
    "sg:phone":"+1 325 597 1617",
    "sg:postcode":"76825",
    "sg:province":"TX",
    "sg:tags":[
        "landscape"
    ],
    "wof:name":"Gilbert S Mata",
    "wof:placetype":"venue"
},
  "geometry": {"coordinates":[-99.341442,31.150582],"type":"Point"}
}