{
  "type": "Feature",
  "properties": {
    "iso:country":"US",
    "sg:address":"706 N Vista Dr",
    "sg:city":"Houston",
    "sg:classifiers":[
        {
            "category":"Freight",
            "type":"Transportation"
        }
    ],
    "sg:phone":"+1 281 443 3803",
    "sg:postcode":"77073",
    "sg:province":"TX",
    "sg:tags":[
        "operator",
        "local",
        "trucking"
    ],
    "wof:name":"Cws Express Delivery",
    "wof:placetype":"venue"
},
  "geometry": {"coordinates":[-95.414367,30.008526],"type":"Point"}
}