{
  "type": "Feature",
  "properties": {
    "iso:country":"US",
    "sg:address":"1000 E 41st St",
    "sg:city":"Austin",
    "sg:classifiers":[
        {
            "category":"Shopping",
            "subcategory":"Hobbies, Toys, & Games",
            "type":"Retail Goods"
        },
        {
            "category":"Cinema",
            "subcategory":"Movie Rental",
            "type":"Entertainment"
        }
    ],
    "sg:phone":"+1 512 459 1533",
    "sg:postcode":"78751",
    "sg:province":"TX",
    "sg:tags":[
        "shop",
        "hobby",
        "video"
    ],
    "wof:name":"Game Crazy",
    "wof:placetype":"venue"
},
  "geometry": {"coordinates":[-97.719719,30.300167],"type":"Point"}
}