{
  "type": "Feature",
  "properties": {
    "iso:country":"US",
    "sg:address":"1840 N Lee Trevino Dr",
    "sg:city":"El Paso",
    "sg:classifiers":[
        {
            "category":"Restaurant",
            "type":"Food & Drink"
        }
    ],
    "sg:phone":"+1 915 594 4016",
    "sg:postcode":"79936",
    "sg:province":"TX",
    "sg:tags":[
        "pizza"
    ],
    "wof:name":"Little Caesars Pizza",
    "wof:placetype":"venue"
},
  "geometry": {"coordinates":[-106.31890300000001,31.767667],"type":"Point"}
}