{
  "type": "Feature",
  "properties": {
    "iso:country":"US",
    "sg:address":"5515 Alabama St",
    "sg:city":"El Paso",
    "sg:classifiers":[
        {
            "category":"Home & Garden",
            "subcategory":"Hardware",
            "type":"Retail Goods"
        }
    ],
    "sg:phone":"+1 915 566 5083",
    "sg:postcode":"79904",
    "sg:province":"TX",
    "sg:tags":[
        "tool",
        "used"
    ],
    "wof:name":"Tool Cribs Integrators Inc",
    "wof:placetype":"venue"
},
  "geometry": {"coordinates":[-106.456158,31.82586],"type":"Point"}
}