{
  "type": "Feature",
  "properties": {
    "iso:country":"US",
    "sg:address":"8947 Sundrop Falls",
    "sg:city":"San Antonio",
    "sg:classifiers":[
        {
            "category":"Health Services",
            "subcategory":"Doctor",
            "type":"Services"
        }
    ],
    "sg:phone":"+1 210 932 4148",
    "sg:postcode":"78224",
    "sg:province":"TX",
    "sg:tags":[
        "clinic"
    ],
    "wof:name":"Med Inc Tex Co",
    "wof:placetype":"venue"
},
  "geometry": {"coordinates":[-98.54400699999999,29.334874],"type":"Point"}
}