{
  "type": "Feature",
  "properties": {
    "iso:country":"US",
    "sg:address":"9817 Glenshee Dr",
    "sg:city":"Rowlett",
    "sg:classifiers":[
        {
            "category":"Building & Trades",
            "subcategory":"Equipment Rental",
            "type":"Services"
        }
    ],
    "sg:phone":"+1 972 463 6184",
    "sg:postcode":"75089",
    "sg:province":"TX",
    "wof:name":"A Majestic Affair By Design",
    "wof:placetype":"venue"
},
  "geometry": {"coordinates":[-96.537406,32.949978],"type":"Point"}
}