{
  "type": "Feature",
  "properties": {
    "iso:country":"US",
    "sg:address":"1502 6th St",
    "sg:city":"Anson",
    "sg:classifiers":[
        {
            "category":"Real Estate",
            "subcategory":"Real Estate Operator",
            "type":"Services"
        }
    ],
    "sg:phone":"+1 325 823 2937",
    "sg:postcode":"79501",
    "sg:province":"TX",
    "sg:tags":[
        "farm",
        "property",
        "lessor",
        "cotton"
    ],
    "wof:name":"Gilbert John",
    "wof:placetype":"venue"
},
  "geometry": {"coordinates":[-99.90281299999999,32.762129],"type":"Point"}
}