{
  "type": "Feature",
  "properties": {
    "iso:country":"US",
    "sg:address":"1251 Co Rd 170",
    "sg:city":"Round Rock",
    "sg:classifiers":[
        {
            "category":"Freight",
            "type":"Transportation"
        }
    ],
    "sg:phone":"+1 512 244 4382",
    "sg:postcode":"78664",
    "sg:province":"TX",
    "sg:tags":[
        "hauling",
        "trucking"
    ],
    "wof:name":"U-Haul Co",
    "wof:placetype":"venue"
},
  "geometry": {"coordinates":[-97.651066,30.485756],"type":"Point"}
}