{
  "type": "Feature",
  "properties": {
    "iso:country":"US",
    "sg:address":"1525 Airport Rd",
    "sg:city":"Conroe",
    "sg:classifiers":[
        {
            "category":"Manufacturing",
            "subcategory":"Tools & Machinery",
            "type":"Manufacturing & Wholesale Goods"
        }
    ],
    "sg:phone":"+1 936 539 4419",
    "sg:postcode":"77301",
    "sg:province":"TX",
    "sg:tags":[
        "equipment",
        "blueprinting",
        "supply"
    ],
    "sg:website":"www.reprotechnology.com",
    "wof:name":"Repro Technology Inc",
    "wof:placetype":"venue"
},
  "geometry": {"coordinates":[-95.440732,30.324379],"type":"Point"}
}