{
  "type": "Feature",
  "properties": {
    "iso:country":"US",
    "sg:address":"4211 Tulia Dr",
    "sg:city":"Amarillo",
    "sg:classifiers":[
        {
            "category":"Insurance",
            "subcategory":"Title Insurance",
            "type":"Services"
        },
        {
            "category":"Real Estate",
            "subcategory":"Real Estate Services",
            "type":"Services"
        }
    ],
    "sg:phone":"+1 806 359 1613",
    "sg:postcode":"79109",
    "sg:province":"TX",
    "sg:tags":[
        "company",
        "carrier",
        "abstract"
    ],
    "wof:name":"Robert R Byers Land Title",
    "wof:placetype":"venue"
},
  "geometry": {"coordinates":[-101.88173399999999,35.163906],"type":"Point"}
}