{
  "type": "Feature",
  "properties": {
    "iso:country":"US",
    "sg:address":"2600 Rigsby Ave",
    "sg:city":"San Antonio",
    "sg:classifiers":[
        {
            "category":"Government",
            "subcategory":"Office",
            "type":"Public Place"
        }
    ],
    "sg:phone":"+1 210 333 0414",
    "sg:postcode":"78222",
    "sg:province":"TX",
    "sg:tags":[
        "social"
    ],
    "wof:name":"Comanche Park Nutrition Site",
    "wof:placetype":"venue"
},
  "geometry": {"coordinates":[-98.41503400000001,29.39908],"type":"Point"}
}