{
  "type": "Feature",
  "properties": {
    "iso:country":"US",
    "sg:address":"3614 Pecan Blvd",
    "sg:city":"Mcallen",
    "sg:classifiers":[
        {
            "category":"Insurance",
            "subcategory":"Insurance Agent",
            "type":"Services"
        }
    ],
    "sg:phone":"+1 956 994 0041",
    "sg:postcode":"78501",
    "sg:province":"TX",
    "wof:name":"Amco Auto Insurance",
    "wof:placetype":"venue"
},
  "geometry": {"coordinates":[-98.264292,26.220311],"type":"Point"}
}