{
  "type": "Feature",
  "properties": {
    "iso:country":"US",
    "sg:address":"5726 Belmont Ave",
    "sg:city":"Dallas",
    "sg:classifiers":[
        {
            "category":"Health Services",
            "subcategory":"Doctor",
            "type":"Services"
        }
    ],
    "sg:phone":"+1 214 821 2275",
    "sg:postcode":"75206",
    "sg:province":"TX",
    "sg:tags":[
        "clinic",
        "medical"
    ],
    "wof:name":"Infirma Care Medical Center",
    "wof:placetype":"venue"
},
  "geometry": {"coordinates":[-96.76849900000001,32.817283],"type":"Point"}
}