{
  "type": "Feature",
  "properties": {
    "iso:country":"US",
    "sg:address":"602 Old Plantersville Rd",
    "sg:city":"Montgomery",
    "sg:classifiers":[
        {
            "category":"Building & Trades",
            "subcategory":"Construction",
            "type":"Services"
        }
    ],
    "sg:phone":"+1 936 597 4445",
    "sg:postcode":"77316",
    "sg:province":"TX",
    "sg:tags":[
        "home",
        "builder"
    ],
    "wof:name":"Keith Downs Custom Homes",
    "wof:placetype":"venue"
},
  "geometry": {"coordinates":[-95.703307,30.386311],"type":"Point"}
}