{
  "type": "Feature",
  "properties": {
    "iso:country":"US",
    "sg:address":"5901 Glenmont Dr",
    "sg:city":"Houston",
    "sg:classifiers":[
        {
            "category":"Food & Beverages",
            "subcategory":"Groceries & Convenience Stores",
            "type":"Retail Goods"
        }
    ],
    "sg:phone":"+1 713 669 9707",
    "sg:postcode":"77081",
    "sg:province":"TX",
    "wof:name":"One Stop Minimart",
    "wof:placetype":"venue"
},
  "geometry": {"coordinates":[-95.48664100000001,29.720036],"type":"Point"}
}