{
  "type": "Feature",
  "properties": {
    "iso:country":"US",
    "sg:address":"121 Highway 332 W",
    "sg:city":"Lake Jackson",
    "sg:classifiers":[
        {
            "category":"Health Services",
            "subcategory":"Optometrist",
            "type":"Services"
        }
    ],
    "sg:phone":"+1 979 480 9424",
    "sg:postcode":"77566",
    "sg:province":"TX",
    "sg:website":"www.julienguyen.com",
    "wof:name":"Julie Nguyen OD",
    "wof:placetype":"venue"
},
  "geometry": {"coordinates":[-95.459158,29.775514],"type":"Point"}
}