{
  "type": "Feature",
  "properties": {
    "iso:country":"US",
    "sg:address":"20832 Co Rd 482",
    "sg:city":"Lindale",
    "sg:classifiers":[
        {
            "category":"Building & Trades",
            "subcategory":"Plumbing",
            "type":"Services"
        }
    ],
    "sg:phone":"+1 903 882 9135",
    "sg:postcode":"75771",
    "sg:province":"TX",
    "sg:tags":[
        "contractor"
    ],
    "wof:name":"King A/C Service",
    "wof:placetype":"venue"
},
  "geometry": {"coordinates":[-95.487369,32.569844],"type":"Point"}
}