{
  "type": "Feature",
  "properties": {
    "iso:country":"US",
    "sg:address":"12611 Woodforest Blvd Ste C",
    "sg:city":"Houston",
    "sg:classifiers":[
        {
            "category":"Arts & Performance",
            "subcategory":"Art Gallery",
            "type":"Entertainment"
        }
    ],
    "sg:phone":"+1 713 453 0042",
    "sg:postcode":"77015",
    "sg:province":"TX",
    "wof:name":"Village Frame Shoppe",
    "wof:placetype":"venue"
},
  "geometry": {"coordinates":[-95.201897,29.791401],"type":"Point"}
}