{
  "type": "Feature",
  "properties": {
    "iso:country":"US",
    "sg:address":"1420 Cypress Creek Rd",
    "sg:city":"Cedar Park",
    "sg:classifiers":[
        {
            "category":"Insurance",
            "subcategory":"Insurance Agent",
            "type":"Services"
        }
    ],
    "sg:phone":"+1 512 259 3881",
    "sg:postcode":"78613",
    "sg:province":"TX",
    "wof:name":"Alpha Omega Insurance Group",
    "wof:placetype":"venue"
},
  "geometry": {"coordinates":[-97.82842100000001,30.491821],"type":"Point"}
}