{
  "type": "Feature",
  "properties": {
    "iso:country":"US",
    "sg:address":"2509 Co Rd 318",
    "sg:city":"Yoakum",
    "sg:classifiers":[
        {
            "category":"Manufacturing",
            "subcategory":"Petroleum Products",
            "type":"Manufacturing & Wholesale Goods"
        }
    ],
    "sg:phone":"+1 361 293 9773",
    "sg:postcode":"77995",
    "sg:province":"TX",
    "wof:name":"Scout Petroleum",
    "wof:placetype":"venue"
},
  "geometry": {"coordinates":[-97.124476,29.367584],"type":"Point"}
}