{
  "type": "Feature",
  "properties": {
    "iso:country":"US",
    "sg:address":"4110 Arthur Ln Apt 15",
    "sg:city":"Beaumont",
    "sg:classifiers":[
        {
            "category":"Professional",
            "subcategory":"Advertising",
            "type":"Services"
        }
    ],
    "sg:phone":"+1 409 898 3955",
    "sg:postcode":"77706",
    "sg:province":"TX",
    "sg:tags":[
        "agency",
        "specialty"
    ],
    "wof:name":"World Buys",
    "wof:placetype":"venue"
},
  "geometry": {"coordinates":[-94.146057,30.11409],"type":"Point"}
}