{
  "type": "Feature",
  "properties": {
    "iso:country":"US",
    "sg:address":"127 N Austin St",
    "sg:city":"Ranger",
    "sg:classifiers":[
        {
            "category":"Personal",
            "subcategory":"Barber",
            "type":"Services"
        }
    ],
    "sg:phone":"+1 254 647 1140",
    "sg:postcode":"76470",
    "sg:province":"TX",
    "sg:tags":[
        "shop"
    ],
    "wof:name":"Ray's Barber Shop",
    "wof:placetype":"venue"
},
  "geometry": {"coordinates":[-98.681586,32.471769],"type":"Point"}
}