{
  "type": "Feature",
  "properties": {
    "iso:country":"US",
    "sg:address":"110 S Collins St",
    "sg:city":"Arlington",
    "sg:classifiers":[
        {
            "category":"Shopping",
            "type":"Retail Goods"
        }
    ],
    "sg:phone":"+1 817 795 7378",
    "sg:postcode":"76010",
    "sg:province":"TX",
    "sg:tags":[
        "chemical"
    ],
    "wof:name":"Today's Products",
    "wof:placetype":"venue"
},
  "geometry": {"coordinates":[-97.097408,32.735693],"type":"Point"}
}