{
  "type": "Feature",
  "properties": {
    "iso:country":"US",
    "sg:address":"12812 W I-10",
    "sg:city":"San Antonio",
    "sg:classifiers":[
        {
            "category":"Restaurant",
            "type":"Food & Drink"
        }
    ],
    "sg:menulink":"http://www.allmenus.com/tx/san-antonio/199912-long-john-silvers/menu/",
    "sg:phone":"+1 210 561 9030",
    "sg:postcode":"78249",
    "sg:province":"TX",
    "sg:tags":[
        "seafood",
        "american"
    ],
    "wof:name":"Long John Silver's",
    "wof:placetype":"venue"
},
  "geometry": {"coordinates":[-98.59201,29.564484],"type":"Point"}
}