{
  "type": "Feature",
  "properties": {
    "iso:country":"US",
    "sg:address":"390 Park St Ste 500",
    "sg:city":"Beaumont",
    "sg:classifiers":[
        {
            "category":"Wholesale",
            "subcategory":"Non-durable Goods",
            "type":"Manufacturing & Wholesale Goods"
        }
    ],
    "sg:phone":"+1 409 835 3891",
    "sg:postcode":"77701",
    "sg:province":"TX",
    "sg:tags":[
        "dry",
        "goods-wholesale"
    ],
    "wof:name":"County Seat Supply Lumber And Building Materials, Inc.",
    "wof:placetype":"venue"
},
  "geometry": {"coordinates":[-94.094116,30.066569],"type":"Point"}
}