{
  "type": "Feature",
  "properties": {
    "iso:country":"US",
    "sg:address":"2704 E Griffin Pkwy",
    "sg:city":"Mission",
    "sg:classifiers":[
        {
            "category":"Wholesale",
            "subcategory":"Medical Equipment & Supplies",
            "type":"Manufacturing & Wholesale Goods"
        }
    ],
    "sg:phone":"+1 956 682 2280",
    "sg:postcode":"78572",
    "sg:province":"TX",
    "sg:tags":[
        "physician",
        "surgeon"
    ],
    "wof:name":"Scientific Medical Supplies",
    "wof:placetype":"venue"
},
  "geometry": {"coordinates":[-98.27601,26.223047],"type":"Point"}
}