{
  "type": "Feature",
  "properties": {
    "iso:country":"US",
    "sg:address":"2922 Martin Luther King Jr Blvd",
    "sg:city":"Dallas",
    "sg:classifiers":[
        {
            "category":"Government",
            "subcategory":"Office",
            "type":"Public Place"
        }
    ],
    "sg:phone":"+1 214 670 8267",
    "sg:postcode":"75215",
    "sg:province":"TX",
    "sg:tags":[
        "administrative",
        "program",
        "health"
    ],
    "wof:name":"Environmental & Hlth Svcs Dept",
    "wof:placetype":"venue"
},
  "geometry": {"coordinates":[-96.766204,32.770909],"type":"Point"}
}