{
  "type": "Feature",
  "properties": {
    "iso:country":"US",
    "sg:address":"5033 Norwich Ct",
    "sg:city":"Corpus Christi",
    "sg:classifiers":[
        {
            "category":"Professional",
            "subcategory":"Engineering",
            "type":"Services"
        }
    ],
    "sg:phone":"+1 361 991 2192",
    "sg:postcode":"78413",
    "sg:province":"TX",
    "wof:name":"Shaw Environmental Inc",
    "wof:placetype":"venue"
},
  "geometry": {"coordinates":[-97.400291,27.676446],"type":"Point"}
}