{
  "type": "Feature",
  "properties": {
    "iso:country":"US",
    "sg:address":"1400 Gillingham Ln",
    "sg:city":"Sugar Land",
    "sg:classifiers":[
        {
            "category":"Wholesale",
            "subcategory":"Electrical",
            "type":"Manufacturing & Wholesale Goods"
        }
    ],
    "sg:phone":"+1 281 243 7206",
    "sg:postcode":"77478",
    "sg:province":"TX",
    "sg:tags":[
        "electronic",
        "mfg"
    ],
    "wof:name":"Avnet Inc",
    "wof:placetype":"venue"
},
  "geometry": {"coordinates":[-95.613456,29.639389],"type":"Point"}
}