{
  "type": "Feature",
  "properties": {
    "iso:country":"US",
    "sg:address":"735 Kyle Cir",
    "sg:city":"Azle",
    "sg:classifiers":[
        {
            "category":"Professional",
            "subcategory":"Accounting & Tax Preparation",
            "type":"Services"
        }
    ],
    "sg:phone":"+1 817 270 0308",
    "sg:postcode":"76020",
    "sg:province":"TX",
    "wof:name":"Larry Reeves Inc",
    "wof:placetype":"venue"
},
  "geometry": {"coordinates":[-97.55278300000001,32.935101],"type":"Point"}
}