{
  "type": "Feature",
  "properties": {
    "iso:country":"US",
    "sg:address":"215 W Pleasant St",
    "sg:city":"Mt Pleasant",
    "sg:classifiers":[
        {
            "category":"Organizations",
            "subcategory":"Religious Organization",
            "type":"Services"
        }
    ],
    "sg:phone":"+1 903 577 7787",
    "sg:postcode":"75455",
    "sg:province":"TX",
    "sg:tags":[
        "church"
    ],
    "wof:name":"Calvary Mt Pleasant",
    "wof:placetype":"venue"
},
  "geometry": {"coordinates":[-94.972233,33.143735],"type":"Point"}
}