{
  "type": "Feature",
  "properties": {
    "iso:country":"US",
    "sg:address":"7335 Airport Fwy",
    "sg:city":"Richland Hills",
    "sg:classifiers":[
        {
            "category":"Banks & Credit Unions",
            "subcategory":"Financial Services",
            "type":"Services"
        }
    ],
    "sg:phone":"+1 817 804 5650",
    "sg:postcode":"76118",
    "sg:province":"TX",
    "sg:tags":[
        "trust",
        "investment",
        "real estate"
    ],
    "wof:name":"First Industrial Realty Trust",
    "wof:placetype":"venue"
},
  "geometry": {"coordinates":[-97.215699,32.804042],"type":"Point"}
}