{
  "type": "Feature",
  "properties": {
    "iso:country":"US",
    "sg:address":"5427 Co Rd 3214",
    "sg:city":"Lone Oak",
    "sg:classifiers":[
        {
            "category":"Professional",
            "type":"Services"
        }
    ],
    "sg:phone":"+1 903 662 5878",
    "sg:postcode":"75453",
    "sg:province":"TX",
    "wof:name":"Frankie D Hill",
    "wof:placetype":"venue"
},
  "geometry": {"coordinates":[-95.92389799999999,33.033084],"type":"Point"}
}