{
  "type": "Feature",
  "properties": {
    "iso:country":"US",
    "sg:address":"1219 Shillington Dr",
    "sg:city":"Katy",
    "sg:classifiers":[
        {
            "category":"Professional",
            "subcategory":"Art Services",
            "type":"Services"
        }
    ],
    "sg:phone":"+1 281 579 1662",
    "sg:postcode":"77450",
    "sg:province":"TX",
    "sg:tags":[
        "commercial",
        "design"
    ],
    "wof:name":"Jeffrey Smart Design",
    "wof:placetype":"venue"
},
  "geometry": {"coordinates":[-95.72703199999999,29.767712],"type":"Point"}
}