{
  "type": "Feature",
  "properties": {
    "iso:country":"US",
    "sg:address":"2802 Celinda Cir",
    "sg:city":"College Station",
    "sg:classifiers":[
        {
            "category":"Professional",
            "type":"Services"
        }
    ],
    "sg:phone":"+1 979 764 1039",
    "sg:postcode":"77845",
    "sg:province":"TX",
    "wof:name":"Tuga LLC",
    "wof:placetype":"venue"
},
  "geometry": {"coordinates":[-96.298388,30.587632],"type":"Point"}
}