{
  "type": "Feature",
  "properties": {
    "iso:country":"US",
    "sg:address":"689 Orion Dr",
    "sg:city":"New Braunfels",
    "sg:classifiers":[
        {
            "category":"Retail",
            "subcategory":"Animal Services",
            "type":"Services"
        }
    ],
    "sg:phone":"+1 830 609 5959",
    "sg:postcode":"78130",
    "sg:province":"TX",
    "wof:name":"Symphony Equine & Canine Svcs",
    "wof:placetype":"venue"
},
  "geometry": {"coordinates":[-98.079753,29.749216],"type":"Point"}
}