{
  "type": "Feature",
  "properties": {
    "iso:country":"US",
    "sg:address":"837 W 12th Street",
    "sg:city":"Austin",
    "sg:classifiers":[
        {
            "category":"Arts & Performance",
            "subcategory":"Art Gallery",
            "type":"Entertainment"
        }
    ],
    "sg:phone":"+1 512 477 4929",
    "sg:postcode":"78701",
    "sg:province":"TX",
    "wof:name":"Davis Gallery",
    "wof:placetype":"venue"
},
  "geometry": {"coordinates":[-97.74909,30.276143],"type":"Point"}
}