{
  "type": "Feature",
  "properties": {
    "iso:country":"US",
    "sg:address":"114 S 14th St",
    "sg:city":"Junction",
    "sg:classifiers":[
        {
            "category":"Retail",
            "subcategory":"Repair Shop",
            "type":"Services"
        }
    ],
    "sg:phone":"+1 325 446 2175",
    "sg:postcode":"76849",
    "sg:province":"TX",
    "wof:name":"Furniture Refinishing",
    "wof:placetype":"venue"
},
  "geometry": {"coordinates":[-99.774227,30.488179],"type":"Point"}
}