{
  "type": "Feature",
  "properties": {
    "iso:country":"US",
    "sg:address":"600 S Louisiana Ave",
    "sg:city":"San Diego",
    "sg:classifiers":[
        {
            "category":"Retail",
            "subcategory":"Repair Shop",
            "type":"Services"
        }
    ],
    "sg:phone":"+1 361 279 2079",
    "sg:postcode":"78384",
    "sg:province":"TX",
    "sg:tags":[
        "welding"
    ],
    "wof:name":"Reyes Welding Service",
    "wof:placetype":"venue"
},
  "geometry": {"coordinates":[-98.243078,27.754852],"type":"Point"}
}