{
  "type": "Feature",
  "properties": {
    "iso:country":"US",
    "sg:address":"3267 Bee Caves Rd",
    "sg:city":"Austin",
    "sg:classifiers":[
        {
            "category":"Food & Beverages",
            "subcategory":"Liquor & Beverages",
            "type":"Retail Goods"
        },
        {
            "category":"Food & Beverages",
            "subcategory":"Groceries & Convenience Stores",
            "type":"Retail Goods"
        }
    ],
    "sg:phone":"+1 512 294 2530",
    "sg:postcode":"78746",
    "sg:province":"TX",
    "sg:tags":[
        "beer",
        "spirit",
        "wine"
    ],
    "sg:website":"www.themeathouse.com",
    "wof:name":"Meat House",
    "wof:placetype":"venue"
},
  "geometry": {"coordinates":[-97.830755,30.296982],"type":"Point"}
}