{
  "type": "Feature",
  "properties": {
    "iso:country":"US",
    "sg:address":"5607 Saint Moritz St",
    "sg:city":"Bellaire",
    "sg:classifiers":[
        {
            "category":"Professional",
            "subcategory":"Lawyer & Legal Services",
            "type":"Services"
        }
    ],
    "sg:phone":"+1 713 660 7990",
    "sg:postcode":"77401",
    "sg:province":"TX",
    "wof:name":"Evans Sally I Apr PR Counsel",
    "wof:placetype":"venue"
},
  "geometry": {"coordinates":[-95.4524,29.718399],"type":"Point"}
}