{
  "type": "Feature",
  "properties": {
    "iso:country":"US",
    "sg:address":"1900 Pine St",
    "sg:city":"Abilene",
    "sg:classifiers":[
        {
            "category":"Health Services",
            "subcategory":"Hospital",
            "type":"Services"
        }
    ],
    "sg:phone":"+1 325 670 2000",
    "sg:postcode":"79601",
    "sg:province":"TX",
    "sg:tags":[
        "general"
    ],
    "wof:name":"Hendrick Medical Center",
    "wof:placetype":"venue"
},
  "geometry": {"coordinates":[-99.73112500000001,32.47312],"type":"Point"}
}