{
  "type": "Feature",
  "properties": {
    "iso:country":"US",
    "sg:address":"2731 S FM 369",
    "sg:city":"Wichita Falls",
    "sg:classifiers":[
        {
            "category":"Food & Beverages",
            "subcategory":"Groceries & Convenience Stores",
            "type":"Retail Goods"
        }
    ],
    "sg:phone":"+1 940 692 9519",
    "sg:postcode":"76310",
    "sg:province":"TX",
    "wof:name":"Circle K Store",
    "wof:placetype":"venue"
},
  "geometry": {"coordinates":[-98.606246,33.889761],"type":"Point"}
}