{
  "type": "Feature",
  "properties": {
    "iso:country":"US",
    "sg:address":"1575 Thousand Oaks Dr",
    "sg:city":"San Antonio",
    "sg:classifiers":[
        {
            "category":"Retail",
            "subcategory":"Funeral Services",
            "type":"Services"
        }
    ],
    "sg:phone":"+1 210 495 3232",
    "sg:postcode":"78232",
    "sg:province":"TX",
    "sg:tags":[
        "director"
    ],
    "wof:name":"Mission North Central",
    "wof:placetype":"venue"
},
  "geometry": {"coordinates":[-98.46738499999999,29.591997],"type":"Point"}
}