{
  "type": "Feature",
  "properties": {
    "iso:country":"US",
    "sg:address":"6224 24th St",
    "sg:city":"Lubbock",
    "sg:classifiers":[
        {
            "category":"Freight",
            "type":"Transportation"
        }
    ],
    "sg:phone":"+1 806 786 0163",
    "sg:postcode":"79407",
    "sg:province":"TX",
    "sg:tags":[
        "mover"
    ],
    "wof:name":"AAA Moving Svc",
    "wof:placetype":"venue"
},
  "geometry": {"coordinates":[-101.952342,33.572608],"type":"Point"}
}