{
  "type": "Feature",
  "properties": {
    "iso:country":"US",
    "sg:address":"1100 N Highway 377",
    "sg:city":"Roanoke",
    "sg:classifiers":[
        {
            "category":"Fast Food",
            "type":"Food & Drink"
        },
        {
            "category":"Restaurant",
            "type":"Food & Drink"
        }
    ],
    "sg:phone":"+1 817 491 3502",
    "sg:postcode":"76262",
    "sg:province":"TX",
    "sg:tags":[
        "hamburger",
        "hot",
        "dog",
        "american",
        "take",
        "chicken"
    ],
    "sg:website":"http://www.mcdonalds.com",
    "wof:name":"McDonald's",
    "wof:placetype":"venue"
},
  "geometry": {"coordinates":[-97.223494,33.009537],"type":"Point"}
}