{
  "type": "Feature",
  "properties": {
    "iso:country":"US",
    "sg:address":"2950 Shaver St Ste B9",
    "sg:city":"Pasadena",
    "sg:classifiers":[
        {
            "category":"Retail",
            "subcategory":"Repair Shop",
            "type":"Services"
        }
    ],
    "sg:phone":"+1 713 941 1061",
    "sg:postcode":"77502",
    "sg:province":"TX",
    "sg:tags":[
        "reupholstery",
        "furniture"
    ],
    "wof:name":"Pro Tops & Trim",
    "wof:placetype":"venue"
},
  "geometry": {"coordinates":[-95.209029,29.666324],"type":"Point"}
}