{
  "type": "Feature",
  "properties": {
    "iso:country":"US",
    "sg:address":"4537 S I H 35",
    "sg:city":"Austin",
    "sg:classifiers":[
        {
            "category":"Travel",
            "subcategory":"Hotels & Motels",
            "type":"Entertainment"
        }
    ],
    "sg:phone":"+1 512 912 1100",
    "sg:postcode":"78744",
    "sg:province":"TX",
    "wof:name":"Residence Inn by Marriott-Austin Airport South",
    "wof:placetype":"venue"
},
  "geometry": {"coordinates":[-97.754689,30.209902],"type":"Point"}
}