{
  "type": "Feature",
  "properties": {
    "iso:country":"US",
    "sg:address":"1607 N Columbia St",
    "sg:city":"Plainview",
    "sg:classifiers":[
        {
            "category":"Manufacturing",
            "subcategory":"Tools & Machinery",
            "type":"Manufacturing & Wholesale Goods"
        }
    ],
    "sg:phone":"+1 806 296 0726",
    "sg:postcode":"79072",
    "sg:province":"TX",
    "sg:tags":[
        "industrial",
        "mfg"
    ],
    "wof:name":"Automotive Machine",
    "wof:placetype":"venue"
},
  "geometry": {"coordinates":[-101.70728200000001,34.198887],"type":"Point"}
}