{
  "type": "Feature",
  "properties": {
    "iso:country":"US",
    "sg:address":"301 E Burbank St",
    "sg:city":"Fredericksburg",
    "sg:classifiers":[
        {
            "category":"Education",
            "subcategory":"Special Training",
            "type":"Public Place"
        }
    ],
    "sg:phone":"+1 830 997 6229",
    "sg:postcode":"78624",
    "sg:province":"TX",
    "sg:tags":[
        "tutoring"
    ],
    "wof:name":"Basics & Beyond",
    "wof:placetype":"venue"
},
  "geometry": {"coordinates":[-98.861368,30.281077],"type":"Point"}
}