{
  "type": "Feature",
  "properties": {
    "iso:country":"US",
    "sg:address":"5616 Corl St",
    "sg:city":"Houston",
    "sg:classifiers":[
        {
            "category":"Manufacturing",
            "subcategory":"Metals",
            "type":"Manufacturing & Wholesale Goods"
        }
    ],
    "sg:phone":"+1 713 644 3882",
    "sg:postcode":"77087",
    "sg:province":"TX",
    "sg:tags":[
        "coating"
    ],
    "wof:name":"Dean-Chem Co",
    "wof:placetype":"venue"
},
  "geometry": {"coordinates":[-95.309603,29.683051],"type":"Point"}
}