{
  "type": "Feature",
  "properties": {
    "iso:country":"US",
    "sg:address":"2323 Timberbranch Ct",
    "sg:city":"Magnolia",
    "sg:classifiers":[
        {
            "category":"Wholesale",
            "subcategory":"Stationery",
            "type":"Manufacturing & Wholesale Goods"
        }
    ],
    "sg:phone":"+1 281 259 6632",
    "sg:postcode":"77355",
    "sg:province":"TX",
    "sg:tags":[
        "paper"
    ],
    "wof:name":"Powell & Assoc",
    "wof:placetype":"venue"
},
  "geometry": {"coordinates":[-95.690921,30.141679],"type":"Point"}
}