{
  "type": "Feature",
  "properties": {
    "iso:country":"US",
    "sg:address":"3310 W Main St",
    "sg:city":"Houston",
    "sg:classifiers":[
        {
            "category":"Health Services",
            "subcategory":"Clinic",
            "type":"Services"
        }
    ],
    "sg:phone":"+1 713 960 9611",
    "sg:postcode":"77098",
    "sg:province":"TX",
    "sg:tags":[
        "related",
        "facility"
    ],
    "wof:name":"Imagine Health Related Suites",
    "wof:placetype":"venue"
},
  "geometry": {"coordinates":[-95.426998,29.735677],"type":"Point"}
}