{
  "type": "Feature",
  "properties": {
    "iso:country":"US",
    "sg:address":"30611 Quinn Rd",
    "sg:city":"Tomball",
    "sg:classifiers":[
        {
            "category":"Professional",
            "subcategory":"Business Services",
            "type":"Services"
        }
    ],
    "sg:phone":"+1 281 255 3535",
    "sg:postcode":"77375",
    "sg:province":"TX",
    "wof:name":"Deans Design",
    "wof:placetype":"venue"
},
  "geometry": {"coordinates":[-95.629034,30.113424],"type":"Point"}
}