{
  "type": "Feature",
  "properties": {
    "iso:country":"US",
    "sg:address":"1332 E Denman Ave",
    "sg:city":"Lufkin",
    "sg:classifiers":[
        {
            "category":"Wholesale",
            "subcategory":"Electrical",
            "type":"Manufacturing & Wholesale Goods"
        }
    ],
    "sg:phone":"+1 936 639 1251",
    "sg:postcode":"75901",
    "sg:province":"TX",
    "sg:tags":[
        "fire",
        "equipment",
        "protection"
    ],
    "wof:name":"Masterguard Of Lufkin",
    "wof:placetype":"venue"
},
  "geometry": {"coordinates":[-94.710115,31.324235],"type":"Point"}
}