{
  "type": "Feature",
  "properties": {
    "iso:country":"US",
    "sg:address":"1703 Judson Rd",
    "sg:city":"Longview",
    "sg:classifiers":[
        {
            "category":"Professional",
            "subcategory":"Lawyer & Legal Services",
            "type":"Services"
        }
    ],
    "sg:phone":"+1 903 757 3992",
    "sg:postcode":"75601",
    "sg:province":"TX",
    "sg:tags":[
        "attorney"
    ],
    "wof:name":"Andrew G Khoury PC",
    "wof:placetype":"venue"
},
  "geometry": {"coordinates":[-94.742622,32.526348],"type":"Point"}
}