{
  "type": "Feature",
  "properties": {
    "iso:country":"US",
    "sg:address":"10943 Covered Bridge St",
    "sg:city":"Houston",
    "sg:classifiers":[
        {
            "category":"Professional",
            "subcategory":"Business Services",
            "type":"Services"
        }
    ],
    "sg:phone":"+1 713 991 2157",
    "sg:postcode":"77075",
    "sg:province":"TX",
    "wof:name":"Creative Forms & Specials",
    "wof:placetype":"venue"
},
  "geometry": {"coordinates":[-95.249071,29.607975],"type":"Point"}
}