{
  "type": "Feature",
  "properties": {
    "iso:country":"US",
    "sg:address":"3103 Honey Tree Ln",
    "sg:city":"Austin",
    "sg:classifiers":[
        {
            "category":"Real Estate",
            "subcategory":"Surveying",
            "type":"Services"
        }
    ],
    "sg:phone":"+1 512 329 0845",
    "sg:postcode":"78746",
    "sg:province":"TX",
    "sg:tags":[
        "surveyor",
        "land"
    ],
    "wof:name":"Mckinney Willis Land & Ca",
    "wof:placetype":"venue"
},
  "geometry": {"coordinates":[-97.797758,30.270445],"type":"Point"}
}