{
  "type": "Feature",
  "properties": {
    "iso:country":"US",
    "sg:address":"1522 Inverness Rd",
    "sg:city":"Mansfield",
    "sg:classifiers":[
        {
            "category":"Wholesale",
            "subcategory":"Non-durable Goods",
            "type":"Manufacturing & Wholesale Goods"
        }
    ],
    "sg:phone":"+1 817 477 3043",
    "sg:postcode":"76063",
    "sg:province":"TX",
    "wof:name":"Gemini Trading Co",
    "wof:placetype":"venue"
},
  "geometry": {"coordinates":[-97.12196900000001,32.59161],"type":"Point"}
}