{
  "type": "Feature",
  "properties": {
    "iso:country":"US",
    "sg:address":"11745 State Hwy 64",
    "sg:city":"Tyler",
    "sg:classifiers":[
        {
            "category":"Home & Garden",
            "subcategory":"Garden Supply",
            "type":"Retail Goods"
        }
    ],
    "sg:phone":"+1 903 597 9951",
    "sg:postcode":"75704",
    "sg:province":"TX",
    "sg:tags":[
        "ornamental",
        "nursery"
    ],
    "wof:name":"Thompson-Hills Nursery",
    "wof:placetype":"venue"
},
  "geometry": {"coordinates":[-95.36058,32.357304],"type":"Point"}
}