{
  "type": "Feature",
  "properties": {
    "iso:country":"US",
    "sg:address":"985 N Dick Dowling St",
    "sg:city":"San Benito",
    "sg:classifiers":[
        {
            "category":"Shopping",
            "type":"Retail Goods"
        }
    ],
    "sg:phone":"+1 956 361 0561",
    "sg:postcode":"78586",
    "sg:province":"TX",
    "sg:tags":[
        "miscellaneous",
        "store"
    ],
    "wof:name":"KEC Products",
    "wof:placetype":"venue"
},
  "geometry": {"coordinates":[-97.62328599999999,26.136395],"type":"Point"}
}