{
  "type": "Feature",
  "properties": {
    "iso:country":"US",
    "sg:address":"1108 State Hwy 80",
    "sg:city":"San Marcos",
    "sg:classifiers":[
        {
            "category":"Building & Trades",
            "subcategory":"Equipment Rental",
            "type":"Services"
        }
    ],
    "sg:phone":"+1 512 353 1633",
    "sg:postcode":"78666",
    "sg:province":"TX",
    "sg:tags":[
        "contractor"
    ],
    "wof:name":"San Marcos Rent Alls Inc",
    "wof:placetype":"venue"
},
  "geometry": {"coordinates":[-97.91439200000001,29.881125],"type":"Point"}
}