{
  "type": "Feature",
  "properties": {
    "iso:country":"US",
    "sg:address":"1212 S Gaston St",
    "sg:city":"Crane",
    "sg:classifiers":[
        {
            "category":"Health Services",
            "subcategory":"Doctor",
            "type":"Services"
        }
    ],
    "sg:phone":"+1 432 558 7114",
    "sg:postcode":"79731",
    "sg:province":"TX",
    "sg:tags":[
        "clinic"
    ],
    "wof:name":"Crane Chiropractic Clinic",
    "wof:placetype":"venue"
},
  "geometry": {"coordinates":[-102.348517,31.391765],"type":"Point"}
}