{
  "type": "Feature",
  "properties": {
    "iso:country":"US",
    "sg:address":"151 Bowie St",
    "sg:city":"San Antonio",
    "sg:classifiers":[
        {
            "category":"Shopping",
            "subcategory":"Department Store",
            "type":"Retail Goods"
        }
    ],
    "sg:phone":"+1 210 554 6850",
    "sg:postcode":"78205",
    "sg:province":"TX",
    "wof:name":"Foleys Department Store",
    "wof:placetype":"venue"
},
  "geometry": {"coordinates":[-98.48322,29.423195],"type":"Point"}
}