{
  "type": "Feature",
  "properties": {
    "iso:country":"US",
    "sg:address":"16750 Hedgecroft Dr",
    "sg:city":"Houston",
    "sg:classifiers":[
        {
            "category":"Shopping",
            "type":"Retail Goods"
        }
    ],
    "sg:phone":"+1 281 260 7744",
    "sg:postcode":"77060",
    "sg:province":"TX",
    "sg:tags":[
        "awning",
        "canopy"
    ],
    "wof:name":"Gulftex",
    "wof:placetype":"venue"
},
  "geometry": {"coordinates":[-95.38903000000001,29.942692],"type":"Point"}
}