{
  "type": "Feature",
  "properties": {
    "iso:country":"US",
    "sg:address":"7109 Lawndale St",
    "sg:city":"Houston",
    "sg:classifiers":[
        {
            "category":"Health Services",
            "subcategory":"Podiatrist",
            "type":"Services"
        }
    ],
    "sg:phone":"+1 713 926 9996",
    "sg:postcode":"77023",
    "sg:province":"TX",
    "wof:name":"Vargas Marko DPM PA",
    "wof:placetype":"venue"
},
  "geometry": {"coordinates":[-95.29347799999999,29.717413],"type":"Point"}
}