{
  "type": "Feature",
  "properties": {
    "iso:country":"US",
    "sg:address":"1701 Analog Dr",
    "sg:city":"Richardson",
    "sg:classifiers":[
        {
            "category":"Manufacturing",
            "subcategory":"Electronics",
            "type":"Manufacturing & Wholesale Goods"
        }
    ],
    "sg:phone":"+1 972 231 5300",
    "sg:postcode":"75081",
    "sg:province":"TX",
    "sg:tags":[
        "semiconductor",
        "devices"
    ],
    "sg:website":"www.allamerican.com",
    "wof:name":"All American Semiconductor",
    "wof:placetype":"venue"
},
  "geometry": {"coordinates":[-96.699868,32.972102],"type":"Point"}
}