{
  "type": "Feature",
  "properties": {
    "iso:country":"US",
    "sg:address":"18413 Angel Valley Dr",
    "sg:city":"Leander",
    "sg:classifiers":[
        {
            "category":"Professional",
            "subcategory":"Management & Consulting",
            "type":"Services"
        }
    ],
    "sg:phone":"+1 512 267 3330",
    "sg:postcode":"78641",
    "sg:province":"TX",
    "wof:name":"Ace Marketing",
    "wof:placetype":"venue"
},
  "geometry": {"coordinates":[-97.90513199999999,30.515332],"type":"Point"}
}