{
  "type": "Feature",
  "properties": {
    "iso:country":"US",
    "sg:address":"417 S Locust St",
    "sg:city":"Denton",
    "sg:classifiers":[
        {
            "category":"Personal",
            "subcategory":"Beauty Salon",
            "type":"Services"
        }
    ],
    "sg:phone":"+1 940 380 1110",
    "sg:postcode":"76201",
    "sg:province":"TX",
    "wof:name":"Lapage II Salon",
    "wof:placetype":"venue"
},
  "geometry": {"coordinates":[-97.132395,33.21175],"type":"Point"}
}