{
  "type": "Feature",
  "properties": {
    "iso:country":"US",
    "sg:address":"2738 Colony Dr",
    "sg:city":"Sugar Land",
    "sg:classifiers":[
        {
            "category":"Professional",
            "subcategory":"Art Services",
            "type":"Services"
        }
    ],
    "sg:phone":"+1 281 242 2414",
    "sg:postcode":"77479",
    "sg:province":"TX",
    "sg:tags":[
        "commercial",
        "design"
    ],
    "wof:name":"Judes Works of Art",
    "wof:placetype":"venue"
},
  "geometry": {"coordinates":[-95.60723900000001,29.58516],"type":"Point"}
}