{
  "type": "Feature",
  "properties": {
    "iso:country":"US",
    "sg:address":"16003 Bollard Dr",
    "sg:city":"Crosby",
    "sg:classifiers":[
        {
            "category":"Professional",
            "subcategory":"Detective & Security Services",
            "type":"Services"
        }
    ],
    "sg:phone":"+1 281 328 1354",
    "sg:postcode":"77532",
    "sg:province":"TX",
    "sg:tags":[
        "car"
    ],
    "wof:name":"Buddy Wood Investigations",
    "wof:placetype":"venue"
},
  "geometry": {"coordinates":[-95.099307,29.91711],"type":"Point"}
}