{
  "type": "Feature",
  "properties": {
    "iso:country":"US",
    "sg:address":"631 Villa Creek Dr",
    "sg:city":"Duncanville",
    "sg:classifiers":[
        {
            "category":"Utilities",
            "subcategory":"Telephone",
            "type":"Services"
        }
    ],
    "sg:phone":"+1 972 296 4673",
    "sg:postcode":"75137",
    "sg:province":"TX",
    "sg:tags":[
        "communications"
    ],
    "wof:name":"Rj Enterprises",
    "wof:placetype":"venue"
},
  "geometry": {"coordinates":[-96.921578,32.630951],"type":"Point"}
}