{
  "type": "Feature",
  "properties": {
    "iso:country":"US",
    "sg:address":"7640 Northfield Dr",
    "sg:city":"Fort Worth",
    "sg:classifiers":[
        {
            "category":"Home & Garden",
            "subcategory":"Carpets & Floor Coverings",
            "type":"Retail Goods"
        }
    ],
    "sg:phone":"+1 817 656 3293",
    "sg:postcode":"76180",
    "sg:province":"TX",
    "wof:name":"Cen Tex Carpet",
    "wof:placetype":"venue"
},
  "geometry": {"coordinates":[-97.19932,32.887718],"type":"Point"}
}