{
  "type": "Feature",
  "properties": {
    "iso:country":"US",
    "sg:address":"111 N Holland St",
    "sg:city":"Willis",
    "sg:classifiers":[
        {
            "category":"Autos & Motor Vehicles",
            "subcategory":"Auto Supplies",
            "type":"Retail Goods"
        }
    ],
    "sg:phone":"+1 936 856 8473",
    "sg:postcode":"77378",
    "sg:province":"TX",
    "sg:tags":[
        "tire"
    ],
    "wof:name":"Abc Tires Of Willis",
    "wof:placetype":"venue"
},
  "geometry": {"coordinates":[-95.485142,30.422763],"type":"Point"}
}