{
  "type": "Feature",
  "properties": {
    "iso:country":"US",
    "sg:address":"619 Houston St",
    "sg:city":"Laredo",
    "sg:classifiers":[
        {
            "category":"Professional",
            "type":"Services"
        }
    ],
    "sg:phone":"+1 956 791 0850",
    "sg:postcode":"78040",
    "sg:province":"TX",
    "sg:tags":[
        "establishment"
    ],
    "wof:name":"Cuevas Ramiro",
    "wof:placetype":"venue"
},
  "geometry": {"coordinates":[-99.50255,27.506982],"type":"Point"}
}