{
  "type": "Feature",
  "properties": {
    "iso:country":"US",
    "sg:address":"216 W Franklin St",
    "sg:city":"Waxahachie",
    "sg:classifiers":[
        {
            "category":"Professional",
            "subcategory":"Lawyer & Legal Services",
            "type":"Services"
        }
    ],
    "sg:phone":"+1 972 923 7787",
    "sg:postcode":"75165",
    "sg:province":"TX",
    "sg:tags":[
        "attorney"
    ],
    "wof:name":"David Abbot Attorney",
    "wof:placetype":"venue"
},
  "geometry": {"coordinates":[-96.84905999999999,32.385668],"type":"Point"}
}