{
  "type": "Feature",
  "properties": {
    "iso:country":"US",
    "sg:address":"3011 Crossview Dr",
    "sg:city":"Houston",
    "sg:classifiers":[
        {
            "category":"Utilities",
            "subcategory":"Telephone",
            "type":"Services"
        }
    ],
    "sg:phone":"+1 800 235 9800",
    "sg:postcode":"77063",
    "sg:province":"TX",
    "sg:tags":[
        "communication"
    ],
    "wof:name":"Southwestern Bell Telephone LP",
    "wof:placetype":"venue"
},
  "geometry": {"coordinates":[-95.519581,29.733153],"type":"Point"}
}