{
  "type": "Feature",
  "properties": {
    "iso:country":"US",
    "sg:address":"7900 N Stadium Dr",
    "sg:city":"Houston",
    "sg:classifiers":[
        {
            "category":"Professional",
            "subcategory":"Lawyer & Legal Services",
            "type":"Services"
        }
    ],
    "sg:phone":"+1 713 522 9563",
    "sg:postcode":"77030",
    "sg:province":"TX",
    "wof:name":"Naron Joe Edwin Atty",
    "wof:placetype":"venue"
},
  "geometry": {"coordinates":[-95.408699,29.695601],"type":"Point"}
}