{
  "type": "Feature",
  "properties": {
    "iso:country":"US",
    "sg:address":"4055 Frankford Rd",
    "sg:city":"Dallas",
    "sg:classifiers":[
        {
            "category":"Freight",
            "type":"Transportation"
        }
    ],
    "sg:phone":"+1 214 680 2003",
    "sg:postcode":"75287",
    "sg:province":"TX",
    "sg:tags":[
        "operator",
        "local",
        "trucking"
    ],
    "wof:name":"Coleman Delivery Service",
    "wof:placetype":"venue"
},
  "geometry": {"coordinates":[-96.838859,32.997659],"type":"Point"}
}