{
  "type": "Feature",
  "properties": {
    "iso:country":"US",
    "sg:address":"100 Ave H",
    "sg:city":"Marble Falls",
    "sg:classifiers":[
        {
            "category":"Government",
            "subcategory":"Office",
            "type":"Public Place"
        }
    ],
    "sg:phone":"+1 830 693 6193",
    "sg:postcode":"78654",
    "sg:province":"TX",
    "wof:name":"Vehicle Registration Div",
    "wof:placetype":"venue"
},
  "geometry": {"coordinates":[-98.27682299999999,30.570483],"type":"Point"}
}