{
  "type": "Feature",
  "properties": {
    "iso:country":"US",
    "sg:address":"10200 Richmond Ave",
    "sg:city":"Houston",
    "sg:classifiers":[
        {
            "category":"Professional",
            "subcategory":"Management & Consulting",
            "type":"Services"
        }
    ],
    "sg:phone":"+1 713 784 0290",
    "sg:postcode":"77042",
    "sg:province":"TX",
    "sg:tags":[
        "food",
        "facility"
    ],
    "sg:website":"www.worrelldesign.com",
    "wof:name":"WORRELL Design Group",
    "wof:placetype":"venue"
},
  "geometry": {"coordinates":[-95.551299,29.728469],"type":"Point"}
}