{
  "type": "Feature",
  "properties": {
    "iso:country":"US",
    "sg:address":"606 Suncrest St",
    "sg:city":"Bryan",
    "sg:classifiers":[
        {
            "category":"Professional",
            "subcategory":"Business Services",
            "type":"Services"
        }
    ],
    "sg:phone":"+1 979 822 3185",
    "sg:postcode":"77803",
    "sg:province":"TX",
    "wof:name":"Maria D Contreras Notary Pub",
    "wof:placetype":"venue"
},
  "geometry": {"coordinates":[-96.400248,30.663982],"type":"Point"}
}