{
  "type": "Feature",
  "properties": {
    "iso:country":"US",
    "sg:address":"315 W Mulberry St",
    "sg:city":"Sherman",
    "sg:classifiers":[
        {
            "category":"Retail",
            "subcategory":"Portrait Studio",
            "type":"Services"
        }
    ],
    "sg:phone":"+1 903 893 0219",
    "sg:postcode":"75090",
    "sg:province":"TX",
    "sg:tags":[
        "photographer"
    ],
    "wof:name":"Quin Studio",
    "wof:placetype":"venue"
},
  "geometry": {"coordinates":[-96.614299,33.63942],"type":"Point"}
}