{
  "type": "Feature",
  "properties": {
    "iso:country":"US",
    "sg:address":"8280 State Hwy 5",
    "sg:city":"Melissa",
    "sg:classifiers":[
        {
            "category":"Manufacturing",
            "subcategory":"Glass & Minerals",
            "type":"Manufacturing & Wholesale Goods"
        }
    ],
    "sg:phone":"+1 972 838 4400",
    "sg:postcode":"75454",
    "sg:province":"TX",
    "sg:tags":[
        "ready"
    ],
    "wof:name":"Farris Concrete Co",
    "wof:placetype":"venue"
},
  "geometry": {"coordinates":[-96.559614,33.314391],"type":"Point"}
}