{
  "type": "Feature",
  "properties": {
    "iso:country":"US",
    "sg:address":"1801 Chamois Knoll",
    "sg:city":"Round Rock",
    "sg:classifiers":[
        {
            "category":"Wholesale",
            "subcategory":"Auto Parts",
            "type":"Manufacturing & Wholesale Goods"
        }
    ],
    "sg:phone":"+1 512 658 3070",
    "sg:postcode":"78664",
    "sg:province":"TX",
    "wof:name":"Capitol Caps",
    "wof:placetype":"venue"
},
  "geometry": {"coordinates":[-97.652798,30.470356],"type":"Point"}
}