{
  "type": "Feature",
  "properties": {
    "iso:country":"US",
    "sg:address":"3909 S 7th St",
    "sg:city":"Abilene",
    "sg:classifiers":[
        {
            "category":"Professional",
            "subcategory":"Research",
            "type":"Services"
        }
    ],
    "sg:phone":"+1 325 672 6848",
    "sg:postcode":"79605",
    "sg:province":"TX",
    "sg:tags":[
        "market",
        "analysis"
    ],
    "wof:name":"WARR Strategies Group",
    "wof:placetype":"venue"
},
  "geometry": {"coordinates":[-99.771041,32.443686],"type":"Point"}
}