{
  "type": "Feature",
  "properties": {
    "iso:country":"US",
    "sg:address":"3381 State Hwy 46",
    "sg:city":"Seguin",
    "sg:classifiers":[
        {
            "category":"Wholesale",
            "subcategory":"Furniture",
            "type":"Manufacturing & Wholesale Goods"
        }
    ],
    "sg:phone":"+1 830 372 5445",
    "sg:postcode":"78155",
    "sg:province":"TX",
    "sg:tags":[
        "equipment",
        "school"
    ],
    "wof:name":"Greeting Tree",
    "wof:placetype":"venue"
},
  "geometry": {"coordinates":[-97.97504600000001,29.528898],"type":"Point"}
}