{
  "type": "Feature",
  "properties": {
    "iso:country":"US",
    "sg:address":"5402 Telephone Rd",
    "sg:city":"Houston",
    "sg:classifiers":[
        {
            "category":"Personal",
            "subcategory":"Beauty Salon",
            "type":"Services"
        }
    ],
    "sg:phone":"+1 713 644 1581",
    "sg:postcode":"77087",
    "sg:province":"TX",
    "sg:tags":[
        "spa"
    ],
    "wof:name":"La Coquet Salon",
    "wof:placetype":"venue"
},
  "geometry": {"coordinates":[-95.297163,29.68591],"type":"Point"}
}