{
  "type": "Feature",
  "properties": {
    "iso:country":"US",
    "sg:address":"12008 County Line Rd",
    "sg:city":"Elgin",
    "sg:classifiers":[
        {
            "category":"Professional",
            "type":"Services"
        }
    ],
    "sg:phone":"+1 512 281 9615",
    "sg:postcode":"78621",
    "sg:province":"TX",
    "wof:name":"Sandifers Custom Guide SE",
    "wof:placetype":"venue"
},
  "geometry": {"coordinates":[-97.427915,30.327091],"type":"Point"}
}