{
  "type": "Feature",
  "properties": {
    "iso:country":"US",
    "sg:address":"2320 Irving Blvd",
    "sg:city":"Dallas",
    "sg:classifiers":[
        {
            "category":"Manufacturing",
            "subcategory":"Printing",
            "type":"Manufacturing & Wholesale Goods"
        }
    ],
    "sg:phone":"+1 214 637 7971",
    "sg:postcode":"75207",
    "sg:province":"TX",
    "sg:tags":[
        "mounting",
        "finishing"
    ],
    "sg:website":"www.mapsco.com",
    "wof:name":"Lamtex Graphic Finishing",
    "wof:placetype":"venue"
},
  "geometry": {"coordinates":[-96.84033700000001,32.798666],"type":"Point"}
}