{
  "type": "Feature",
  "properties": {
    "iso:country":"US",
    "sg:address":"3249 SW Military Dr",
    "sg:city":"San Antonio",
    "sg:classifiers":[
        {
            "category":"Retail",
            "subcategory":"Auto Repair",
            "type":"Services"
        }
    ],
    "sg:phone":"+1 210 922 0902",
    "sg:postcode":"78211",
    "sg:province":"TX",
    "sg:tags":[
        "repairing",
        "automobile",
        "general"
    ],
    "wof:name":"Chuck's Auto Repair",
    "wof:placetype":"venue"
},
  "geometry": {"coordinates":[-98.55317700000001,29.357748],"type":"Point"}
}