{
  "type": "Feature",
  "properties": {
    "iso:country":"US",
    "sg:address":"224 Corinth St",
    "sg:city":"Dallas",
    "sg:classifiers":[
        {
            "category":"Wholesale",
            "subcategory":"Auto Parts",
            "type":"Manufacturing & Wholesale Goods"
        }
    ],
    "sg:phone":"+1 214 426 6449",
    "sg:postcode":"75207",
    "sg:province":"TX",
    "wof:name":"Bishop Aquisition & Sales",
    "wof:placetype":"venue"
},
  "geometry": {"coordinates":[-96.792653,32.761848],"type":"Point"}
}