{
  "type": "Feature",
  "properties": {
    "iso:country":"US",
    "sg:address":"2713 S Highland St",
    "sg:city":"Amarillo",
    "sg:classifiers":[
        {
            "category":"Shopping",
            "type":"Retail Goods"
        }
    ],
    "sg:phone":"+1 806 372 7849",
    "sg:postcode":"79103",
    "sg:province":"TX",
    "sg:tags":[
        "merchandise"
    ],
    "wof:name":"Proverbs 31 Mom",
    "wof:placetype":"venue"
},
  "geometry": {"coordinates":[-101.80301799999999,35.183157],"type":"Point"}
}