{
  "type": "Feature",
  "properties": {
    "iso:country":"US",
    "sg:address":"2914 Crestway Dr",
    "sg:city":"Perryton",
    "sg:classifiers":[
        {
            "category":"Mining & Drilling",
            "type":"Manufacturing & Wholesale Goods"
        }
    ],
    "sg:phone":"+1 806 435 3450",
    "sg:postcode":"79070",
    "sg:province":"TX",
    "sg:tags":[
        "field"
    ],
    "wof:name":"Nall Contract Pumping Inc",
    "wof:placetype":"venue"
},
  "geometry": {"coordinates":[-100.799222,36.371491],"type":"Point"}
}