{
  "type": "Feature",
  "properties": {
    "iso:country":"US",
    "sg:address":"2831 W Clarendon Dr",
    "sg:city":"Dallas",
    "sg:classifiers":[
        {
            "category":"Building & Trades",
            "subcategory":"Construction",
            "type":"Services"
        }
    ],
    "sg:phone":"+1 214 337 5334",
    "sg:postcode":"75211",
    "sg:province":"TX",
    "sg:tags":[
        "contractor"
    ],
    "wof:name":"New World Tile",
    "wof:placetype":"venue"
},
  "geometry": {"coordinates":[-96.86817000000001,32.734521],"type":"Point"}
}