{
  "type": "Feature",
  "properties": {
    "iso:country":"US",
    "sg:address":"2401 Southmore Ave",
    "sg:city":"Pasadena",
    "sg:classifiers":[
        {
            "category":"Social Services",
            "subcategory":"Adult Care",
            "type":"Services"
        }
    ],
    "sg:phone":"+1 713 473 3733",
    "sg:postcode":"77502",
    "sg:province":"TX",
    "sg:tags":[
        "residential"
    ],
    "wof:name":"Southmore Park",
    "wof:placetype":"venue"
},
  "geometry": {"coordinates":[-95.178518,29.691754],"type":"Point"}
}