{
  "type": "Feature",
  "properties": {
    "iso:country":"US",
    "sg:address":"5602 Reiger Ave",
    "sg:city":"Dallas",
    "sg:classifiers":[
        {
            "category":"Banks & Credit Unions",
            "subcategory":"Financial Services",
            "type":"Services"
        }
    ],
    "sg:phone":"+1 214 821 6829",
    "sg:postcode":"75214",
    "sg:province":"TX",
    "sg:tags":[
        "management",
        "open",
        "investment"
    ],
    "wof:name":"Beacon & Reiger Properties",
    "wof:placetype":"venue"
},
  "geometry": {"coordinates":[-96.756156,32.802845],"type":"Point"}
}