{
  "type": "Feature",
  "properties": {
    "iso:country":"US",
    "sg:address":"724 S Bibb Ave",
    "sg:city":"Eagle Pass",
    "sg:classifiers":[
        {
            "category":"Personal",
            "subcategory":"Beauty Salon",
            "type":"Services"
        }
    ],
    "sg:phone":"+1 830 757 5033",
    "sg:postcode":"78852",
    "sg:province":"TX",
    "sg:tags":[
        "manicuring"
    ],
    "wof:name":"Eagle Nails",
    "wof:placetype":"venue"
},
  "geometry": {"coordinates":[-100.48483899999999,28.697646],"type":"Point"}
}