{
  "type": "Feature",
  "properties": {
    "iso:country":"US",
    "sg:address":"2026 Valencia",
    "sg:city":"San Antonio",
    "sg:classifiers":[
        {
            "category":"Professional",
            "subcategory":"Business Services",
            "type":"Services"
        }
    ],
    "sg:phone":"+1 210 434 3656",
    "sg:postcode":"78237",
    "sg:province":"TX",
    "wof:name":"Ya Hawkins Enterprises",
    "wof:placetype":"venue"
},
  "geometry": {"coordinates":[-98.569294,29.409768],"type":"Point"}
}