{
  "type": "Feature",
  "properties": {
    "iso:country":"US",
    "sg:address":"14530 Josey Ln",
    "sg:city":"Dallas",
    "sg:classifiers":[
        {
            "category":"Restaurant",
            "type":"Food & Drink"
        }
    ],
    "sg:phone":"+1 972 481 9812",
    "sg:postcode":"75234",
    "sg:province":"TX",
    "sg:tags":[
        "parlor",
        "ice",
        "cream"
    ],
    "wof:name":"Neveria Tierra Caliente",
    "wof:placetype":"venue"
},
  "geometry": {"coordinates":[-96.89021,32.945363],"type":"Point"}
}