{
  "type": "Feature",
  "properties": {
    "iso:country":"US",
    "sg:address":"733 Parson's",
    "sg:city":"Abilene",
    "sg:classifiers":[
        {
            "category":"Professional",
            "type":"Services"
        }
    ],
    "sg:phone":"+1 325 437 2827",
    "sg:postcode":"79602",
    "sg:province":"TX",
    "sg:tags":[
        "establishment"
    ],
    "wof:name":"ELI",
    "wof:placetype":"venue"
},
  "geometry": {"coordinates":[-99.694283,32.342605],"type":"Point"}
}