{
  "type": "Feature",
  "properties": {
    "iso:country":"US",
    "sg:address":"816 Travis St",
    "sg:city":"Wichita Falls",
    "sg:classifiers":[
        {
            "category":"Manufacturing",
            "subcategory":"Signs",
            "type":"Manufacturing & Wholesale Goods"
        }
    ],
    "sg:phone":"+1 940 322 2565",
    "sg:postcode":"76301",
    "sg:province":"TX",
    "sg:website":"www.signsbygwynn.com",
    "wof:name":"Signs By Gwynn",
    "wof:placetype":"venue"
},
  "geometry": {"coordinates":[-98.493675,33.909781],"type":"Point"}
}