{
  "type": "Feature",
  "properties": {
    "iso:country":"US",
    "sg:address":"616 N Main St",
    "sg:city":"Cleburne",
    "sg:classifiers":[
        {
            "category":"Restaurant",
            "type":"Food & Drink"
        }
    ],
    "sg:menulink":"http://www.allmenus.com/tx/cleburne/13303-churchs-chicken/menu/",
    "sg:phone":"+1 817 556 0570",
    "sg:postcode":"76033",
    "sg:province":"TX",
    "sg:tags":[
        "chicken",
        "wing"
    ],
    "wof:name":"Church's Chicken",
    "wof:placetype":"venue"
},
  "geometry": {"coordinates":[-97.388366,32.353037],"type":"Point"}
}