{
  "type": "Feature",
  "properties": {
    "iso:country":"US",
    "sg:address":"1522 Perennial Dr",
    "sg:city":"San Antonio",
    "sg:classifiers":[
        {
            "category":"Building & Trades",
            "subcategory":"Construction",
            "type":"Services"
        }
    ],
    "sg:phone":"+1 210 495 3371",
    "sg:postcode":"78232",
    "sg:province":"TX",
    "sg:tags":[
        "builder",
        "deck"
    ],
    "wof:name":"Copeland Construction",
    "wof:placetype":"venue"
},
  "geometry": {"coordinates":[-98.46387900000001,29.557012],"type":"Point"}
}