{
  "type": "Feature",
  "properties": {
    "iso:country":"US",
    "sg:address":"1905 Webster Ave",
    "sg:city":"Waco",
    "sg:classifiers":[
        {
            "category":"Retail",
            "subcategory":"Auto Repair",
            "type":"Services"
        }
    ],
    "sg:phone":"+1 254 754 1282",
    "sg:postcode":"76706",
    "sg:province":"TX",
    "sg:tags":[
        "body"
    ],
    "wof:name":"Ikes Paint & Body Shop",
    "wof:placetype":"venue"
},
  "geometry": {"coordinates":[-97.14169099999999,31.541489],"type":"Point"}
}