{
  "type": "Feature",
  "properties": {
    "iso:country":"US",
    "sg:address":"2100 Kramer Ln Ste 200",
    "sg:city":"Austin",
    "sg:classifiers":[
        {
            "category":"Health Services",
            "subcategory":"Doctor",
            "type":"Services"
        }
    ],
    "sg:phone":"+1 512 835 1994",
    "sg:postcode":"78758",
    "sg:province":"TX",
    "sg:tags":[
        "consultant",
        "medical",
        "practice"
    ],
    "sg:website":"http://www.lahasolutions.com",
    "wof:name":"La Hacienda's Solutions",
    "wof:placetype":"venue"
},
  "geometry": {"coordinates":[-97.71121599999999,30.389122],"type":"Point"}
}