{
  "type": "Feature",
  "properties": {
    "iso:country":"US",
    "sg:address":"1925 N Lake Trl",
    "sg:city":"Denton",
    "sg:classifiers":[
        {
            "category":"Shopping",
            "subcategory":"Hobbies, Toys, & Games",
            "type":"Retail Goods"
        }
    ],
    "sg:phone":"+1 940 243 4091",
    "sg:postcode":"76201",
    "sg:province":"TX",
    "sg:tags":[
        "craft"
    ],
    "wof:name":"Special Occasion Scrape Books",
    "wof:placetype":"venue"
},
  "geometry": {"coordinates":[-97.152585,33.23296],"type":"Point"}
}