{
  "type": "Feature",
  "properties": {
    "iso:country":"US",
    "sg:address":"5500 Block Line Rd",
    "sg:city":"Snyder",
    "sg:classifiers":[
        {
            "category":"Wholesale",
            "subcategory":"Petroleum",
            "type":"Manufacturing & Wholesale Goods"
        }
    ],
    "sg:phone":"+1 325 573 0178",
    "sg:postcode":"79549",
    "sg:province":"TX",
    "sg:tags":[
        "pipe",
        "line",
        "company"
    ],
    "wof:name":"Koch Pipeline Co",
    "wof:placetype":"venue"
},
  "geometry": {"coordinates":[-100.965204,32.656579],"type":"Point"}
}