{
  "type": "Feature",
  "properties": {
    "iso:country":"US",
    "sg:address":"126 Mittmann Cir",
    "sg:city":"New Braunfels",
    "sg:classifiers":[
        {
            "category":"Organizations",
            "subcategory":"Religious Organization",
            "type":"Services"
        }
    ],
    "sg:phone":"+1 830 629 3586",
    "sg:postcode":"78132",
    "sg:province":"TX",
    "sg:tags":[
        "science",
        "christian",
        "practitioner"
    ],
    "wof:name":"Judith Hahnssen",
    "wof:placetype":"venue"
},
  "geometry": {"coordinates":[-98.196595,29.717868],"type":"Point"}
}