{
  "type": "Feature",
  "properties": {
    "iso:country":"US",
    "sg:address":"332 Afton Rd",
    "sg:city":"Fort Worth",
    "sg:classifiers":[
        {
            "category":"Insurance",
            "subcategory":"Insurance Agent",
            "type":"Services"
        }
    ],
    "sg:phone":"+1 817 293 8903",
    "sg:postcode":"76134",
    "sg:province":"TX",
    "wof:name":"M&M Appraisal Services",
    "wof:placetype":"venue"
},
  "geometry": {"coordinates":[-97.33014900000001,32.643264],"type":"Point"}
}