{
  "type": "Feature",
  "properties": {
    "iso:country":"US",
    "sg:address":"2139 Gilmer Rd",
    "sg:city":"Longview",
    "sg:classifiers":[
        {
            "category":"Home & Garden",
            "subcategory":"Home Furnishings",
            "type":"Retail Goods"
        }
    ],
    "sg:phone":"+1 903 759 2494",
    "sg:postcode":"75604",
    "sg:province":"TX",
    "wof:name":"Blinds-Direct 2u",
    "wof:placetype":"venue"
},
  "geometry": {"coordinates":[-94.787747,32.529525],"type":"Point"}
}