{
  "type": "Feature",
  "properties": {
    "iso:country":"US",
    "sg:address":"200 Apple St",
    "sg:city":"Bryan",
    "sg:phone":"+1 979 822 0559",
    "sg:postcode":"77803",
    "sg:province":"TX",
    "sg:tags":[
        "oil"
    ],
    "wof:name":"Superior Race Fuel",
    "wof:placetype":"venue"
},
  "geometry": {"coordinates":[-96.368072,30.684132],"type":"Point"}
}