{
  "type": "Feature",
  "properties": {
    "iso:country":"US",
    "sg:address":"203 W Fuller Dr",
    "sg:city":"Bergheim",
    "sg:classifiers":[
        {
            "category":"Building & Trades",
            "subcategory":"Construction",
            "type":"Services"
        }
    ],
    "sg:phone":"+1 830 336 3844",
    "sg:postcode":"78004",
    "sg:province":"TX",
    "sg:tags":[
        "house"
    ],
    "wof:name":"Brian Lowe Homes Inc",
    "wof:placetype":"venue"
},
  "geometry": {"coordinates":[-98.548142,29.829978],"type":"Point"}
}