{
  "type": "Feature",
  "properties": {
    "iso:country":"US",
    "sg:address":"103 E Depot St",
    "sg:city":"Rio Vista",
    "sg:classifiers":[
        {
            "category":"Shopping",
            "subcategory":"Used Merchandise",
            "type":"Retail Goods"
        }
    ],
    "sg:phone":"+1 817 373 3123",
    "sg:postcode":"76093",
    "sg:province":"TX",
    "wof:name":"Seconds LTD",
    "wof:placetype":"venue"
},
  "geometry": {"coordinates":[-97.37688199999999,32.233018],"type":"Point"}
}