{
  "type": "Feature",
  "properties": {
    "iso:country":"US",
    "sg:address":"12710 Island Dr",
    "sg:city":"Tomball",
    "sg:classifiers":[
        {
            "category":"Professional",
            "subcategory":"Computer Services",
            "type":"Services"
        }
    ],
    "sg:phone":"+1 281 370 3835",
    "sg:postcode":"77377",
    "sg:province":"TX",
    "sg:tags":[
        "programing",
        "custom"
    ],
    "wof:name":"Custom Computer Solutions",
    "wof:placetype":"venue"
},
  "geometry": {"coordinates":[-95.618105,30.008234],"type":"Point"}
}