{
  "type": "Feature",
  "properties": {
    "iso:country":"US",
    "sg:address":"1105 Trinidad Ln",
    "sg:city":"Garland",
    "sg:classifiers":[
        {
            "category":"Shopping",
            "subcategory":"Computers & Home Electronics",
            "type":"Retail Goods"
        }
    ],
    "sg:phone":"+1 972 487 9618",
    "sg:postcode":"75040",
    "sg:province":"TX",
    "wof:name":"Box Directory Computers &",
    "wof:placetype":"venue"
},
  "geometry": {"coordinates":[-96.611676,32.925255],"type":"Point"}
}