{
  "type": "Feature",
  "properties": {
    "iso:country":"US",
    "sg:address":"6748 Starnes Rd",
    "sg:city":"Fort Worth",
    "sg:classifiers":[
        {
            "category":"Professional",
            "subcategory":"Engineering",
            "type":"Services"
        }
    ],
    "sg:phone":"+1 817 656 4412",
    "sg:postcode":"76180",
    "sg:province":"TX",
    "sg:tags":[
        "billboard",
        "consulting"
    ],
    "wof:name":"Media Engineering",
    "wof:placetype":"venue"
},
  "geometry": {"coordinates":[-97.23544800000001,32.881479],"type":"Point"}
}