{
  "type": "Feature",
  "properties": {
    "iso:country":"US",
    "sg:address":"10000 W Commerce St",
    "sg:city":"San Antonio",
    "sg:classifiers":[
        {
            "category":"Farming",
            "subcategory":"Farm",
            "type":"Manufacturing & Wholesale Goods"
        }
    ],
    "sg:phone":"+1 210 416 6261",
    "sg:postcode":"78227",
    "sg:province":"TX",
    "sg:tags":[
        "primarily",
        "crop",
        "general"
    ],
    "wof:name":"Rancho Colorado",
    "wof:placetype":"venue"
},
  "geometry": {"coordinates":[-98.62918999999999,29.436262],"type":"Point"}
}