{
  "type": "Feature",
  "properties": {
    "iso:country":"US",
    "sg:address":"5406 Crested Butte Cir",
    "sg:city":"Arlington",
    "sg:classifiers":[
        {
            "category":"Wholesale",
            "subcategory":"Vending Machines",
            "type":"Manufacturing & Wholesale Goods"
        }
    ],
    "sg:phone":"+1 817 478 1554",
    "sg:postcode":"76017",
    "sg:province":"TX",
    "sg:tags":[
        "operator"
    ],
    "wof:name":"Tarrant County Vending Inc",
    "wof:placetype":"venue"
},
  "geometry": {"coordinates":[-97.201893,32.65977],"type":"Point"}
}