{
  "type": "Feature",
  "properties": {
    "iso:country":"US",
    "sg:address":"10219 N Central Expy",
    "sg:city":"Dallas",
    "sg:classifiers":[
        {
            "category":"Retail",
            "subcategory":"Self-service Laundry",
            "type":"Services"
        }
    ],
    "sg:phone":"+1 214 265 9733",
    "sg:postcode":"75231",
    "sg:province":"TX",
    "sg:tags":[
        "coin"
    ],
    "wof:name":"Meadow Coin Wash",
    "wof:placetype":"venue"
},
  "geometry": {"coordinates":[-96.769513,32.886761],"type":"Point"}
}