{
  "type": "Feature",
  "properties": {
    "iso:country":"US",
    "sg:address":"458 Westview Ter",
    "sg:city":"Arlington",
    "sg:classifiers":[
        {
            "category":"Shopping",
            "subcategory":"Clothing, Apparel, & Fashions",
            "type":"Retail Goods"
        }
    ],
    "sg:phone":"+1 817 265 3456",
    "sg:postcode":"76013",
    "sg:province":"TX",
    "sg:tags":[
        "family"
    ],
    "wof:name":"Golden Age Security",
    "wof:placetype":"venue"
},
  "geometry": {"coordinates":[-97.136349,32.732987],"type":"Point"}
}