{
  "type": "Feature",
  "properties": {
    "iso:country":"US",
    "sg:address":"617 Candle Meadow Blvd",
    "sg:city":"Desoto",
    "sg:classifiers":[
        {
            "category":"Building & Trades",
            "subcategory":"Construction",
            "type":"Services"
        }
    ],
    "sg:phone":"+1 972 230 9191",
    "sg:postcode":"75115",
    "sg:province":"TX",
    "sg:tags":[
        "home",
        "builder"
    ],
    "wof:name":"Lagacy Homes At Desoto",
    "wof:placetype":"venue"
},
  "geometry": {"coordinates":[-96.89041899999999,32.57975],"type":"Point"}
}