{
  "type": "Feature",
  "properties": {
    "iso:country":"US",
    "sg:address":"1000 Las Vacas St",
    "sg:city":"Del Rio",
    "sg:classifiers":[
        {
            "category":"Shopping",
            "subcategory":"Music",
            "type":"Retail Goods"
        }
    ],
    "sg:phone":"+1 830 774 1609",
    "sg:postcode":"78840",
    "sg:province":"TX",
    "wof:name":"Del Rio Video",
    "wof:placetype":"venue"
},
  "geometry": {"coordinates":[-100.908145,29.353303],"type":"Point"}
}