{
  "type": "Feature",
  "properties": {
    "iso:country":"US",
    "sg:address":"1430 W Palm Dr",
    "sg:city":"Aransas Pass",
    "sg:classifiers":[
        {
            "category":"Shopping",
            "type":"Retail Goods"
        }
    ],
    "sg:phone":"+1 361 758 6866",
    "sg:postcode":"78336",
    "sg:province":"TX",
    "sg:tags":[
        "merchandise"
    ],
    "wof:name":"Coastal Paradise Scrapboo",
    "wof:placetype":"venue"
},
  "geometry": {"coordinates":[-97.16167799999999,27.912134],"type":"Point"}
}