{
  "type": "Feature",
  "properties": {
    "iso:country":"US",
    "sg:address":"100 S 12th Ave",
    "sg:city":"Edinburg",
    "sg:classifiers":[
        {
            "category":"Shopping",
            "subcategory":"Florist",
            "type":"Retail Goods"
        }
    ],
    "sg:phone":"+1 956 287 0303",
    "sg:postcode":"78539",
    "sg:province":"TX",
    "wof:name":"Divine Ideas",
    "wof:placetype":"venue"
},
  "geometry": {"coordinates":[-98.161417,26.300217],"type":"Point"}
}