{
  "type": "Feature",
  "properties": {
    "iso:country":"US",
    "sg:address":"1 Village Dr",
    "sg:city":"Abilene",
    "sg:classifiers":[
        {
            "category":"Insurance",
            "subcategory":"Insurance Agent",
            "type":"Services"
        }
    ],
    "sg:phone":"+1 325 673 7586",
    "sg:postcode":"79606",
    "sg:province":"TX",
    "wof:name":"AFLAC",
    "wof:placetype":"venue"
},
  "geometry": {"coordinates":[-99.769639,32.408136],"type":"Point"}
}