{
  "type": "Feature",
  "properties": {
    "iso:country":"US",
    "sg:address":"3301 Richmond Rd",
    "sg:city":"Texarkana",
    "sg:classifiers":[
        {
            "category":"Insurance",
            "subcategory":"Insurance Agent",
            "type":"Services"
        },
        {
            "category":"Insurance",
            "subcategory":"Hazard Insurance",
            "type":"Services"
        },
        {
            "category":"Insurance",
            "subcategory":"Title Insurance",
            "type":"Services"
        },
        {
            "category":"Insurance",
            "subcategory":"Life Insurance",
            "type":"Services"
        }
    ],
    "sg:phone":"+1 903 832 5881",
    "sg:postcode":"75503",
    "sg:province":"TX",
    "sg:tags":[
        "business",
        "auto",
        "commercial",
        "homeowner",
        "motorcycle",
        "renter"
    ],
    "wof:name":"Allstate Insurance Company - Brian Purtle",
    "wof:placetype":"venue"
},
  "geometry": {"coordinates":[-94.094582,33.465389],"type":"Point"}
}