{
  "type": "Feature",
  "properties": {
    "iso:country":"US",
    "sg:address":"505 SE 3rd St",
    "sg:city":"Mineral Wells",
    "sg:classifiers":[
        {
            "category":"Building & Trades",
            "subcategory":"Construction",
            "type":"Services"
        }
    ],
    "sg:phone":"+1 940 325 4819",
    "sg:postcode":"76067",
    "sg:province":"TX",
    "sg:tags":[
        "contractor"
    ],
    "wof:name":"Triple J Roofing",
    "wof:placetype":"venue"
},
  "geometry": {"coordinates":[-98.109416,32.807059],"type":"Point"}
}