{
  "type": "Feature",
  "properties": {
    "iso:country":"US",
    "sg:address":"4918 Everhart Rd",
    "sg:city":"Corpus Christi",
    "sg:classifiers":[
        {
            "category":"Personal",
            "subcategory":"Beauty Salon",
            "type":"Services"
        }
    ],
    "sg:phone":"+1 361 993 7995",
    "sg:postcode":"78411",
    "sg:province":"TX",
    "wof:name":"Le Salon & Boutique",
    "wof:placetype":"venue"
},
  "geometry": {"coordinates":[-97.382656,27.71723],"type":"Point"}
}