{
  "type": "Feature",
  "properties": {
    "iso:country":"US",
    "sg:address":"1413 Comal Ave",
    "sg:city":"Pasadena",
    "sg:classifiers":[
        {
            "category":"Retail",
            "subcategory":"Laundry & Dry Cleaning",
            "type":"Services"
        },
        {
            "category":"Building & Trades",
            "subcategory":"Cleaning & Sanitation",
            "type":"Services"
        },
        {
            "category":"Home & Garden",
            "subcategory":"Carpets & Floor Coverings",
            "type":"Retail Goods"
        }
    ],
    "sg:phone":"+1 713 472 2088",
    "sg:postcode":"77506",
    "sg:province":"TX",
    "sg:tags":[
        "cleaner",
        "installation",
        "rug"
    ],
    "wof:name":"Ray's Carpet Service",
    "wof:placetype":"venue"
},
  "geometry": {"coordinates":[-95.22666099999999,29.696307],"type":"Point"}
}