{
  "type": "Feature",
  "properties": {
    "iso:country":"US",
    "sg:address":"7160 Dallas Pkwy",
    "sg:city":"Plano",
    "sg:classifiers":[
        {
            "category":"Wholesale",
            "subcategory":"Groceries",
            "type":"Manufacturing & Wholesale Goods"
        },
        {
            "category":"Professional",
            "subcategory":"Advertising",
            "type":"Services"
        }
    ],
    "sg:phone":"+1 972 473 7309",
    "sg:postcode":"75024",
    "sg:province":"TX",
    "sg:tags":[
        "distribution",
        "beverage"
    ],
    "wof:name":"Ford Distributing Inc",
    "wof:placetype":"venue"
},
  "geometry": {"coordinates":[-96.823875,33.076052],"type":"Point"}
}