{
  "type": "Feature",
  "properties": {
    "iso:country":"US",
    "sg:address":"2509 Rosehill Ln",
    "sg:city":"Plano",
    "sg:classifiers":[
        {
            "category":"Wholesale",
            "subcategory":"Stationery",
            "type":"Manufacturing & Wholesale Goods"
        }
    ],
    "sg:phone":"+1 972 943 0415",
    "sg:postcode":"75093",
    "sg:province":"TX",
    "sg:tags":[
        "paper"
    ],
    "wof:name":"James A Sievers Inc",
    "wof:placetype":"venue"
},
  "geometry": {"coordinates":[-96.77274300000001,33.032377],"type":"Point"}
}