{
  "type": "Feature",
  "properties": {
    "iso:country":"US",
    "sg:address":"1415 N Loop W Frwy",
    "sg:city":"Houston",
    "sg:classifiers":[
        {
            "category":"Professional",
            "subcategory":"Detective & Security Services",
            "type":"Services"
        }
    ],
    "sg:phone":"+1 281 826 2540",
    "sg:postcode":"77018",
    "sg:province":"TX",
    "sg:tags":[
        "system"
    ],
    "wof:name":"Houston Video Security Systems",
    "wof:placetype":"venue"
},
  "geometry": {"coordinates":[-95.428225,29.812312],"type":"Point"}
}