{
  "type": "Feature",
  "properties": {
    "iso:country":"US",
    "sg:address":"1208 Michael Ave",
    "sg:city":"Lewisville",
    "sg:classifiers":[
        {
            "category":"Real Estate",
            "subcategory":"Real Estate Services",
            "type":"Services"
        }
    ],
    "sg:phone":"+1 940 239 7663",
    "sg:postcode":"75077",
    "sg:province":"TX",
    "sg:tags":[
        "commercial"
    ],
    "wof:name":"Dgd & Associates Inc.",
    "wof:placetype":"venue"
},
  "geometry": {"coordinates":[-97.023364,33.060891],"type":"Point"}
}