{
  "type": "Feature",
  "properties": {
    "iso:country":"US",
    "sg:address":"813 Front St",
    "sg:city":"Comfort",
    "sg:classifiers":[
        {
            "category":"Banks & Credit Unions",
            "subcategory":"Bank",
            "type":"Services"
        }
    ],
    "sg:phone":"+1 830 995 2816",
    "sg:postcode":"78013",
    "sg:province":"TX",
    "wof:name":"Guaranty Federal Bank F S B",
    "wof:placetype":"venue"
},
  "geometry": {"coordinates":[-98.90548800000001,29.967446],"type":"Point"}
}