{
  "type": "Feature",
  "properties": {
    "iso:country":"US",
    "sg:address":"502 W Clinton St",
    "sg:city":"Dublin",
    "sg:classifiers":[
        {
            "category":"Manufacturing",
            "subcategory":"Buildings",
            "type":"Manufacturing & Wholesale Goods"
        },
        {
            "category":"Building & Trades",
            "subcategory":"Construction",
            "type":"Services"
        }
    ],
    "sg:phone":"+1 254 445 3693",
    "sg:postcode":"76446",
    "sg:province":"TX",
    "sg:tags":[
        "home",
        "builder",
        "contractor"
    ],
    "sg:website":"http://www.patbays.com",
    "wof:name":"Pat Bays Construction",
    "wof:placetype":"venue"
},
  "geometry": {"coordinates":[-98.344491,32.097889],"type":"Point"}
}