{
  "type": "Feature",
  "properties": {
    "iso:country":"US",
    "sg:address":"2701 Pasadena Blvd",
    "sg:city":"Pasadena",
    "sg:classifiers":[
        {
            "category":"Building & Trades",
            "subcategory":"Plumbing",
            "type":"Services"
        }
    ],
    "sg:phone":"+1 713 740 9302",
    "sg:postcode":"77502",
    "sg:province":"TX",
    "wof:name":"Thermal Service Ac & Heating",
    "wof:placetype":"venue"
},
  "geometry": {"coordinates":[-95.17456,29.682367],"type":"Point"}
}