{
  "type": "Feature",
  "properties": {
    "iso:country":"US",
    "sg:address":"4750 W Cedar Bayou Lynchburg Rd",
    "sg:city":"Baytown",
    "sg:classifiers":[
        {
            "category":"Building & Trades",
            "subcategory":"Construction",
            "type":"Services"
        }
    ],
    "sg:phone":"+1 281 424 3324",
    "sg:postcode":"77521",
    "sg:province":"TX",
    "sg:tags":[
        "contractor"
    ],
    "wof:name":"Southern Metal Processing Co",
    "wof:placetype":"venue"
},
  "geometry": {"coordinates":[-95.017228,29.784683],"type":"Point"}
}