{
  "type": "Feature",
  "properties": {
    "iso:country":"US",
    "sg:address":"2345 Reagan St",
    "sg:city":"Dallas",
    "sg:classifiers":[
        {
            "category":"Organizations",
            "subcategory":"Non-profit Organization",
            "type":"Services"
        }
    ],
    "sg:phone":"+1 214 999 1044",
    "sg:postcode":"75219",
    "sg:province":"TX",
    "sg:tags":[
        "information",
        "alcoholism",
        "treatment"
    ],
    "wof:name":"Phoenix Houses Of Texas",
    "wof:placetype":"venue"
},
  "geometry": {"coordinates":[-96.819057,32.803476],"type":"Point"}
}