{
  "type": "Feature",
  "properties": {
    "iso:country":"US",
    "sg:address":"15370 Vickery Dr",
    "sg:city":"Houston",
    "sg:classifiers":[
        {
            "category":"Government",
            "subcategory":"Office",
            "type":"Public Place"
        }
    ],
    "sg:phone":"+1 281 227 5000",
    "sg:postcode":"77032",
    "sg:province":"TX",
    "wof:name":"Select Carrier Group",
    "wof:placetype":"venue"
},
  "geometry": {"coordinates":[-95.315612,29.94246],"type":"Point"}
}