{
  "type": "Feature",
  "properties": {
    "iso:country":"US",
    "sg:address":"255 Scenic Loop Dr",
    "sg:city":"Goliad",
    "sg:classifiers":[
        {
            "category":"Manufacturing",
            "subcategory":"Tools & Machinery",
            "type":"Manufacturing & Wholesale Goods"
        }
    ],
    "sg:phone":"+1 361 645 2210",
    "sg:postcode":"77963",
    "sg:province":"TX",
    "sg:tags":[
        "devices",
        "mfg"
    ],
    "wof:name":"Fullencheks Gauging Services",
    "wof:placetype":"venue"
},
  "geometry": {"coordinates":[-97.440192,28.708031],"type":"Point"}
}