{
  "type": "Feature",
  "properties": {
    "iso:country":"US",
    "sg:address":"4501 Medical Center Dr Ste 300",
    "sg:city":"Mckinney",
    "sg:classifiers":[
        {
            "category":"Health Services",
            "subcategory":"Doctor",
            "type":"Services"
        },
        {
            "category":"Health Services",
            "subcategory":"Podiatrist",
            "type":"Services"
        }
    ],
    "sg:phone":"+1 972 542 2155",
    "sg:postcode":"75069",
    "sg:province":"TX",
    "sg:tags":[
        "physician",
        "oncology",
        "surgeons",
        "pediatrics-orthopedics",
        "medicine",
        "pediatrics-hematology",
        "sport"
    ],
    "sg:website":"http://www.advancedfoottexas.com",
    "wof:name":"McKinney Foot & Ankle Clinic",
    "wof:placetype":"venue"
},
  "geometry": {"coordinates":[-96.635521,33.161677],"type":"Point"}
}