{
  "type": "Feature",
  "properties": {
    "iso:country":"US",
    "sg:address":"12400 Network Blvd",
    "sg:city":"San Antonio",
    "sg:classifiers":[
        {
            "category":"Real Estate",
            "subcategory":"Real Estate Services",
            "type":"Services"
        }
    ],
    "sg:phone":"+1 210 308 9999",
    "sg:postcode":"78249",
    "sg:province":"TX",
    "sg:tags":[
        "abstract",
        "title"
    ],
    "wof:name":"Commercial Abstract & Title Co",
    "wof:placetype":"venue"
},
  "geometry": {"coordinates":[-98.58981300000001,29.550034],"type":"Point"}
}