{
  "type": "Feature",
  "properties": {
    "iso:country":"US",
    "sg:address":"704 1st Ave",
    "sg:city":"Mc Kinney",
    "sg:classifiers":[
        {
            "category":"Building & Trades",
            "subcategory":"Cleaning & Sanitation",
            "type":"Services"
        }
    ],
    "sg:phone":"+1 972 562 8393",
    "sg:postcode":"75069",
    "sg:province":"TX",
    "sg:tags":[
        "maintenance"
    ],
    "wof:name":"T & M Cleaning Services",
    "wof:placetype":"venue"
},
  "geometry": {"coordinates":[-96.621455,33.213661],"type":"Point"}
}