{
  "type": "Feature",
  "properties": {
    "iso:country":"US",
    "sg:address":"7704 Guadalupe Ct",
    "sg:city":"Fort Worth",
    "sg:classifiers":[
        {
            "category":"Shopping",
            "subcategory":"Clothing, Apparel, & Fashions",
            "type":"Retail Goods"
        }
    ],
    "sg:phone":"+1 817 577 9559",
    "sg:postcode":"76137",
    "sg:province":"TX",
    "wof:name":"Chican Junction",
    "wof:placetype":"venue"
},
  "geometry": {"coordinates":[-97.279168,32.87748],"type":"Point"}
}