{
  "type": "Feature",
  "properties": {
    "iso:country":"US",
    "sg:address":"5137 69th St",
    "sg:city":"Lubbock",
    "sg:classifiers":[
        {
            "category":"Retail",
            "subcategory":"Animal Services",
            "type":"Services"
        }
    ],
    "sg:phone":"+1 806 794 0897",
    "sg:postcode":"79424",
    "sg:province":"TX",
    "sg:tags":[
        "pet",
        "grooming",
        "washing"
    ],
    "wof:name":"Cimarron Pet Svc",
    "wof:placetype":"venue"
},
  "geometry": {"coordinates":[-101.92049900000001,33.531095],"type":"Point"}
}