{
  "type": "Feature",
  "properties": {
    "iso:country":"US",
    "sg:address":"105 E Main St",
    "sg:city":"Brenham",
    "sg:classifiers":[
        {
            "category":"Social Services",
            "type":"Services"
        }
    ],
    "sg:phone":"+1 979 836 9633",
    "sg:postcode":"77833",
    "sg:province":"TX",
    "wof:name":"Hand Cnseling Consulting Group",
    "wof:placetype":"venue"
},
  "geometry": {"coordinates":[-96.397447,30.167576],"type":"Point"}
}