{
  "type": "Feature",
  "properties": {
    "iso:country":"US",
    "sg:address":"830 Keller Pkwy",
    "sg:city":"Keller",
    "sg:classifiers":[
        {
            "category":"Retail",
            "subcategory":"Auto Rental",
            "type":"Services"
        }
    ],
    "sg:phone":"+1 817 431 1579",
    "sg:postcode":"76248",
    "sg:province":"TX",
    "sg:tags":[
        "renting",
        "automobile",
        "truck"
    ],
    "sg:website":"http://www.enterprise.com/car_rental/deeplinkmap.do?gpbr=09AK&bid=004&cnty=US&arc=YPTRL01&cm_mmc=Yellowpages.com-_-IYP-_-Tradelisting-_-branch",
    "wof:name":"Enterprise Rent-A-Car",
    "wof:placetype":"venue"
},
  "geometry": {"coordinates":[-97.235634,32.934238],"type":"Point"}
}