{
  "type": "Feature",
  "properties": {
    "iso:country":"US",
    "sg:address":"206 Sykes Ln",
    "sg:city":"Killeen",
    "sg:classifiers":[
        {
            "category":"Building & Trades",
            "subcategory":"Pest Control",
            "type":"Services"
        }
    ],
    "sg:phone":"+1 254 501 9681",
    "sg:postcode":"76542",
    "sg:province":"TX",
    "sg:tags":[
        "industrial",
        "services-commercial"
    ],
    "wof:name":"A1 Pest Control",
    "wof:placetype":"venue"
},
  "geometry": {"coordinates":[-97.749374,31.021645],"type":"Point"}
}