{
  "type": "Feature",
  "properties": {
    "iso:country":"US",
    "sg:address":"1220 Barranca Dr",
    "sg:city":"El Paso",
    "sg:classifiers":[
        {
            "category":"Retail",
            "subcategory":"Auto Repair",
            "type":"Services"
        }
    ],
    "sg:phone":"+1 915 593 9200",
    "sg:postcode":"79935",
    "sg:province":"TX",
    "sg:tags":[
        "automobile",
        "customizing"
    ],
    "wof:name":"915 Customs",
    "wof:placetype":"venue"
},
  "geometry": {"coordinates":[-106.331411,31.752792],"type":"Point"}
}