{
  "type": "Feature",
  "properties": {
    "iso:country":"US",
    "sg:address":"9701 Meyer Forest Dr",
    "sg:city":"Houston",
    "sg:classifiers":[
        {
            "category":"Wholesale",
            "subcategory":"Books, Periodicals, & Newspapers",
            "type":"Manufacturing & Wholesale Goods"
        }
    ],
    "sg:phone":"+1 713 359 9879",
    "sg:postcode":"77096",
    "sg:province":"TX",
    "sg:tags":[
        "publisher",
        "book"
    ],
    "wof:name":"Triniti Publishing",
    "wof:placetype":"venue"
},
  "geometry": {"coordinates":[-95.455833,29.674709],"type":"Point"}
}