{
  "type": "Feature",
  "properties": {
    "iso:country":"US",
    "sg:address":"1535 W Summit Ave",
    "sg:city":"San Antonio",
    "sg:classifiers":[
        {
            "category":"Personal",
            "subcategory":"Barber",
            "type":"Services"
        }
    ],
    "sg:phone":"+1 210 738 9516",
    "sg:postcode":"78201",
    "sg:province":"TX",
    "wof:name":"Angel's Barber Shop",
    "wof:placetype":"venue"
},
  "geometry": {"coordinates":[-98.519431,29.459191],"type":"Point"}
}