{
  "type": "Feature",
  "properties": {
    "iso:country":"US",
    "sg:address":"2901 Morton St",
    "sg:city":"Fort Worth",
    "sg:classifiers":[
        {
            "category":"Professional",
            "subcategory":"Management & Consulting",
            "type":"Services"
        }
    ],
    "sg:phone":"+1 817 885 8223",
    "sg:postcode":"76107",
    "sg:province":"TX",
    "sg:tags":[
        "benefit"
    ],
    "wof:name":"F B H Inc",
    "wof:placetype":"venue"
},
  "geometry": {"coordinates":[-97.360203,32.749251],"type":"Point"}
}