{
  "type": "Feature",
  "properties": {
    "iso:country":"US",
    "sg:address":"212 Camp Willow Rd",
    "sg:city":"New Braunfels",
    "sg:classifiers":[
        {
            "category":"Building & Trades",
            "subcategory":"Construction",
            "type":"Services"
        }
    ],
    "sg:phone":"+1 830 620 5832",
    "sg:postcode":"78130",
    "sg:province":"TX",
    "sg:tags":[
        "floor",
        "laying",
        "contractor"
    ],
    "wof:name":"Superior Hardwood Floors",
    "wof:placetype":"venue"
},
  "geometry": {"coordinates":[-98.061065,29.67166],"type":"Point"}
}