{
  "type": "Feature",
  "properties": {
    "iso:country":"US",
    "sg:address":"3700 Procter St",
    "sg:city":"Port Arthur",
    "sg:classifiers":[
        {
            "category":"Professional",
            "subcategory":"Management & Consulting",
            "type":"Services"
        }
    ],
    "sg:phone":"+1 409 982 8030",
    "sg:postcode":"77642",
    "sg:province":"TX",
    "sg:tags":[
        "business"
    ],
    "wof:name":"Conquest Administrative Svcs",
    "wof:placetype":"venue"
},
  "geometry": {"coordinates":[-93.908559,29.899908],"type":"Point"}
}