{
  "type": "Feature",
  "properties": {
    "iso:country":"US",
    "sg:address":"1333 W Lucas Dr",
    "sg:city":"Beaumont",
    "sg:classifiers":[
        {
            "category":"Personal",
            "type":"Services"
        }
    ],
    "sg:phone":"+1 409 896 2800",
    "sg:postcode":"77706",
    "sg:province":"TX",
    "sg:tags":[
        "therapist",
        "massage"
    ],
    "wof:name":"Body Mind Massage Therapy Clnc",
    "wof:placetype":"venue"
},
  "geometry": {"coordinates":[-94.147565,30.097794],"type":"Point"}
}