{
  "type": "Feature",
  "properties": {
    "iso:country":"US",
    "sg:address":"104 Persons St",
    "sg:city":"Stockdale",
    "sg:classifiers":[
        {
            "category":"Freight",
            "type":"Transportation"
        }
    ],
    "sg:phone":"+1 830 996 3454",
    "sg:postcode":"78160",
    "sg:province":"TX",
    "sg:tags":[
        "courier"
    ],
    "wof:name":"S S Express LLC",
    "wof:placetype":"venue"
},
  "geometry": {"coordinates":[-97.959491,29.23594],"type":"Point"}
}