{
  "type": "Feature",
  "properties": {
    "iso:country":"US",
    "sg:address":"622 Belt Line Rd",
    "sg:city":"Garland",
    "sg:classifiers":[
        {
            "category":"Travel",
            "subcategory":"Hotels & Motels",
            "type":"Entertainment"
        }
    ],
    "sg:phone":"+1 972 226 7621",
    "sg:postcode":"75040",
    "sg:province":"TX",
    "wof:name":"Days Inn",
    "wof:placetype":"venue"
},
  "geometry": {"coordinates":[-96.635696,32.939201],"type":"Point"}
}