{
  "type": "Feature",
  "properties": {
    "iso:country":"US",
    "sg:address":"5826 US Hwy 59",
    "sg:city":"Beeville",
    "sg:classifiers":[
        {
            "category":"Farming",
            "subcategory":"Livestock Farm",
            "type":"Manufacturing & Wholesale Goods"
        }
    ],
    "sg:phone":"+1 361 439 7550",
    "sg:postcode":"78102",
    "sg:province":"TX",
    "sg:tags":[
        "animal",
        "general"
    ],
    "wof:name":"Handy Farm & Ranch",
    "wof:placetype":"venue"
},
  "geometry": {"coordinates":[-97.639939,28.496289],"type":"Point"}
}