{
  "type": "Feature",
  "properties": {
    "iso:country":"US",
    "sg:address":"3901 E 29th St",
    "sg:city":"Bryan",
    "sg:classifiers":[
        {
            "category":"Retail",
            "subcategory":"Auto Repair",
            "type":"Services"
        }
    ],
    "sg:phone":"+1 979 846 0861",
    "sg:postcode":"77802",
    "sg:province":"TX",
    "sg:tags":[
        "repairing",
        "automobile"
    ],
    "wof:name":"Olympic Automotive Auto Svc",
    "wof:placetype":"venue"
},
  "geometry": {"coordinates":[-96.332584,30.644066],"type":"Point"}
}