{
  "type": "Feature",
  "properties": {
    "iso:country":"US",
    "sg:address":"705 Falling Leaf Dr",
    "sg:city":"Friendswood",
    "sg:classifiers":[
        {
            "category":"Professional",
            "subcategory":"Computer Services",
            "type":"Services"
        }
    ],
    "sg:phone":"+1 281 993 5130",
    "sg:postcode":"77546",
    "sg:province":"TX",
    "sg:tags":[
        "development",
        "software"
    ],
    "wof:name":"Rodgers Enterprises Inc",
    "wof:placetype":"venue"
},
  "geometry": {"coordinates":[-95.206447,29.518675],"type":"Point"}
}