{
  "type": "Feature",
  "properties": {
    "iso:country":"US",
    "sg:address":"1634 E Cesar Chavez St",
    "sg:city":"Austin",
    "sg:classifiers":[
        {
            "category":"Health Services",
            "subcategory":"Chiropractor",
            "type":"Services"
        }
    ],
    "sg:phone":"+1 512 457 9476",
    "sg:postcode":"78702",
    "sg:province":"TX",
    "wof:name":"Minors Chiropractic Inc A",
    "wof:placetype":"venue"
},
  "geometry": {"coordinates":[-97.727217,30.258139],"type":"Point"}
}