{
  "type": "Feature",
  "properties": {
    "iso:country":"US",
    "sg:address":"2200 Airport Fwy",
    "sg:city":"Bedford",
    "sg:classifiers":[
        {
            "category":"Restaurant",
            "type":"Food & Drink"
        }
    ],
    "sg:phone":"+1 817 399 1111",
    "sg:postcode":"76022",
    "sg:province":"TX",
    "sg:tags":[
        "eating"
    ],
    "wof:name":"Cafe Amore",
    "wof:placetype":"venue"
},
  "geometry": {"coordinates":[-97.132141,32.836465],"type":"Point"}
}