{
  "type": "Feature",
  "properties": {
    "iso:country":"US",
    "sg:address":"20701 Kingsland Blvd",
    "sg:city":"Katy",
    "sg:classifiers":[
        {
            "category":"Food & Beverages",
            "subcategory":"Groceries & Convenience Stores",
            "type":"Retail Goods"
        }
    ],
    "sg:phone":"+1 281 578 2650",
    "sg:postcode":"77450",
    "sg:province":"TX",
    "wof:name":"7 Days Food Store",
    "wof:placetype":"venue"
},
  "geometry": {"coordinates":[-95.730361,29.776017],"type":"Point"}
}