{
  "type": "Feature",
  "properties": {
    "iso:country":"US",
    "sg:address":"1806 Cherry Orchard Dr",
    "sg:city":"Austin",
    "sg:classifiers":[
        {
            "category":"Utilities",
            "subcategory":"Electric",
            "type":"Services"
        },
        {
            "category":"Manufacturing",
            "subcategory":"Electronics",
            "type":"Manufacturing & Wholesale Goods"
        },
        {
            "category":"Building & Trades",
            "subcategory":"Electrical",
            "type":"Services"
        }
    ],
    "sg:phone":"+1 512 441 7534",
    "sg:postcode":"78745",
    "sg:province":"TX",
    "sg:tags":[
        "industrial",
        "electrician",
        "contractors-commercial",
        "equipment-testing"
    ],
    "wof:name":"J C Electric Company",
    "wof:placetype":"venue"
},
  "geometry": {"coordinates":[-97.803809,30.201491],"type":"Point"}
}