{
  "type": "Feature",
  "properties": {
    "iso:country":"US",
    "sg:address":"4406 55th St",
    "sg:city":"Lubbock",
    "sg:classifiers":[
        {
            "category":"Shopping",
            "type":"Retail Goods"
        }
    ],
    "sg:phone":"+1 806 793 1999",
    "sg:postcode":"79414",
    "sg:province":"TX",
    "sg:tags":[
        "merchandise"
    ],
    "wof:name":"Breath Of Life",
    "wof:placetype":"venue"
},
  "geometry": {"coordinates":[-101.907134,33.544287],"type":"Point"}
}