{
  "type": "Feature",
  "properties": {
    "iso:country":"US",
    "sg:address":"4701 N Main St",
    "sg:city":"Fort Worth",
    "sg:classifiers":[
        {
            "category":"Autos & Motor Vehicles",
            "subcategory":"Automobile Sales",
            "type":"Retail Goods"
        }
    ],
    "sg:phone":"+1 817 263 3299",
    "sg:postcode":"76106",
    "sg:province":"TX",
    "sg:tags":[
        "used"
    ],
    "wof:name":"Rinos Auto Sales",
    "wof:placetype":"venue"
},
  "geometry": {"coordinates":[-97.355913,32.826105],"type":"Point"}
}