{
  "type": "Feature",
  "properties": {
    "iso:country":"US",
    "sg:address":"915 E Johnson St",
    "sg:city":"Waco",
    "sg:classifiers":[
        {
            "category":"Home & Garden",
            "subcategory":"Building Materials",
            "type":"Retail Goods"
        },
        {
            "category":"Building & Trades",
            "subcategory":"Plumbing",
            "type":"Services"
        }
    ],
    "sg:phone":"+1 254 799 9393",
    "sg:postcode":"76705",
    "sg:province":"TX",
    "sg:tags":[
        "sheet",
        "work",
        "metal",
        "contractor"
    ],
    "wof:name":"Wes Bran Metals",
    "wof:placetype":"venue"
},
  "geometry": {"coordinates":[-97.11352100000001,31.58359],"type":"Point"}
}