{
  "type": "Feature",
  "properties": {
    "iso:country":"US",
    "sg:address":"700 W Applegate Dr",
    "sg:city":"Austin",
    "sg:classifiers":[
        {
            "category":"Personal",
            "subcategory":"Day Spa",
            "type":"Services"
        },
        {
            "category":"Building & Trades",
            "subcategory":"Construction",
            "type":"Services"
        },
        {
            "category":"Sports & Exercise",
            "subcategory":"Swimming Pool",
            "type":"Entertainment"
        }
    ],
    "sg:phone":"+1 512 339 9304",
    "sg:postcode":"78753",
    "sg:province":"TX",
    "sg:tags":[
        "repair",
        "consulting",
        "hot",
        "designing",
        "tub"
    ],
    "sg:website":"http://www.poolrelief.com",
    "wof:name":"Crystal Clear Pools",
    "wof:placetype":"venue"
},
  "geometry": {"coordinates":[-97.690079,30.373098],"type":"Point"}
}