{
  "type": "Feature",
  "properties": {
    "iso:country":"US",
    "sg:address":"1705 W University Dr",
    "sg:city":"Mckinney",
    "sg:classifiers":[
        {
            "category":"Shopping",
            "subcategory":"Jewelry",
            "type":"Retail Goods"
        }
    ],
    "sg:phone":"+1 972 562 3933",
    "sg:postcode":"75069",
    "sg:province":"TX",
    "sg:tags":[
        "precious",
        "semi-precious",
        "stone"
    ],
    "wof:name":"Davis Jewelers",
    "wof:placetype":"venue"
},
  "geometry": {"coordinates":[-96.63178499999999,33.216485],"type":"Point"}
}