{
  "type": "Feature",
  "properties": {
    "iso:country":"US",
    "sg:address":"6 Butterfield Trail Blvd",
    "sg:city":"El Paso",
    "sg:classifiers":[
        {
            "category":"Manufacturing",
            "subcategory":"Electronics",
            "type":"Manufacturing & Wholesale Goods"
        }
    ],
    "sg:phone":"+1 915 593 2011",
    "sg:postcode":"79906",
    "sg:province":"TX",
    "sg:tags":[
        "equipment",
        "mfg",
        "electrical",
        "motor",
        "vehicle"
    ],
    "wof:name":"Stoneridge Inc",
    "wof:placetype":"venue"
},
  "geometry": {"coordinates":[-106.401062,31.812641],"type":"Point"}
}