{
  "type": "Feature",
  "properties": {
    "iso:country":"US",
    "sg:address":"1507 Kennebeck Pl",
    "sg:city":"Houston",
    "sg:classifiers":[
        {
            "category":"Manufacturing",
            "subcategory":"Tools & Machinery",
            "type":"Manufacturing & Wholesale Goods"
        }
    ],
    "sg:phone":"+1 281 679 0020",
    "sg:postcode":"77077",
    "sg:province":"TX",
    "sg:tags":[
        "devices",
        "mfg"
    ],
    "wof:name":"Kress Technologies",
    "wof:placetype":"venue"
},
  "geometry": {"coordinates":[-95.62958,29.757376],"type":"Point"}
}