{
  "type": "Feature",
  "properties": {
    "iso:country":"US",
    "sg:address":"367 N Las Gallinas",
    "sg:city":"Pleasanton",
    "sg:classifiers":[
        {
            "category":"Retail",
            "subcategory":"Laundry & Dry Cleaning",
            "type":"Services"
        }
    ],
    "sg:phone":"+1 210 392 3911",
    "sg:postcode":"78064",
    "sg:province":"TX",
    "wof:name":"Rock and B Tile",
    "wof:placetype":"venue"
},
  "geometry": {"coordinates":[-98.470347,29.116983],"type":"Point"}
}