{
  "type": "Feature",
  "properties": {
    "iso:country":"US",
    "sg:address":"6566 McGrew St",
    "sg:city":"Houston",
    "sg:classifiers":[
        {
            "category":"Home & Garden",
            "subcategory":"Carpets & Floor Coverings",
            "type":"Retail Goods"
        }
    ],
    "sg:phone":"+1 713 649 2223",
    "sg:postcode":"77087",
    "sg:province":"TX",
    "sg:tags":[
        "dealer",
        "rug"
    ],
    "wof:name":"Affordable Floors",
    "wof:placetype":"venue"
},
  "geometry": {"coordinates":[-95.310506,29.685368],"type":"Point"}
}