{
  "type": "Feature",
  "properties": {
    "iso:country":"US",
    "sg:address":"625 S Colorado Ave",
    "sg:city":"Mercedes",
    "sg:classifiers":[
        {
            "category":"Building & Trades",
            "subcategory":"Cleaning & Sanitation",
            "type":"Services"
        }
    ],
    "sg:phone":"+1 956 565 2396",
    "sg:postcode":"78570",
    "sg:province":"TX",
    "sg:tags":[
        "maintenance"
    ],
    "wof:name":"Cantu Janitorial Service",
    "wof:placetype":"venue"
},
  "geometry": {"coordinates":[-97.92172100000001,26.145584],"type":"Point"}
}