{
  "type": "Feature",
  "properties": {
    "iso:country":"US",
    "sg:address":"9404 San Leon Ave",
    "sg:city":"Dallas",
    "sg:classifiers":[
        {
            "category":"Wholesale",
            "subcategory":"Vending Machines",
            "type":"Manufacturing & Wholesale Goods"
        }
    ],
    "sg:phone":"+1 214 398 0510",
    "sg:postcode":"75217",
    "sg:province":"TX",
    "sg:tags":[
        "operator"
    ],
    "wof:name":"T&R Vending",
    "wof:placetype":"venue"
},
  "geometry": {"coordinates":[-96.660948,32.729451],"type":"Point"}
}