{
  "type": "Feature",
  "properties": {
    "iso:country":"US",
    "sg:address":"712 Fort Worth Ave",
    "sg:city":"Dallas",
    "sg:classifiers":[
        {
            "category":"Travel",
            "subcategory":"Hotels & Motels",
            "type":"Entertainment"
        }
    ],
    "sg:phone":"+1 214 748 7444",
    "sg:postcode":"75208",
    "sg:province":"TX",
    "wof:name":"Alamo Inn",
    "wof:placetype":"venue"
},
  "geometry": {"coordinates":[-96.83471299999999,32.770807],"type":"Point"}
}