{
  "type": "Feature",
  "properties": {
    "iso:country":"US",
    "sg:address":"7611 Cooper Ln",
    "sg:city":"Austin",
    "sg:classifiers":[
        {
            "category":"Building & Trades",
            "subcategory":"Landscaping Services",
            "type":"Services"
        }
    ],
    "sg:phone":"+1 512 452 3987",
    "sg:postcode":"78745",
    "sg:province":"TX",
    "sg:tags":[
        "tree"
    ],
    "wof:name":"Ogden's Tree Svc",
    "wof:placetype":"venue"
},
  "geometry": {"coordinates":[-97.794061,30.188701],"type":"Point"}
}