{
  "type": "Feature",
  "properties": {
    "iso:country":"US",
    "sg:address":"105 E California St Ste B",
    "sg:city":"Gainesville",
    "sg:classifiers":[
        {
            "category":"Shopping",
            "subcategory":"Department Store",
            "type":"Retail Goods"
        }
    ],
    "sg:phone":"+1 940 665 6332",
    "sg:postcode":"76240",
    "sg:province":"TX",
    "sg:website":"http://www.jcpenney.com",
    "wof:name":"Ctlg Sales Merchant",
    "wof:placetype":"venue"
},
  "geometry": {"coordinates":[-97.14528199999999,33.624279],"type":"Point"}
}