{
  "type": "Feature",
  "properties": {
    "iso:country":"US",
    "sg:address":"2624 Skinner Dr",
    "sg:city":"Flower Mound",
    "sg:classifiers":[
        {
            "category":"Utilities",
            "subcategory":"Telephone",
            "type":"Services"
        }
    ],
    "sg:phone":"+1 972 965 9186",
    "sg:postcode":"75028",
    "sg:province":"TX",
    "sg:tags":[
        "communications"
    ],
    "wof:name":"Converged Communications Inc",
    "wof:placetype":"venue"
},
  "geometry": {"coordinates":[-97.04977599999999,33.020232],"type":"Point"}
}