{
  "type": "Feature",
  "properties": {
    "iso:country":"US",
    "sg:address":"1707 Post Oak Blvd",
    "sg:city":"Houston",
    "sg:classifiers":[
        {
            "category":"Ice Cream",
            "type":"Food & Drink"
        }
    ],
    "sg:phone":"+1 713 622 5483",
    "sg:postcode":"77056",
    "sg:province":"TX",
    "sg:tags":[
        "frozen",
        "yogurt"
    ],
    "sg:website":"www.tastidlite.com",
    "wof:name":"Tasti D-Lite",
    "wof:placetype":"venue"
},
  "geometry": {"coordinates":[-95.462688,29.749869],"type":"Point"}
}