{
  "type": "Feature",
  "properties": {
    "iso:country":"US",
    "sg:address":"854 Greenview Dr",
    "sg:city":"Grand Prairie",
    "sg:classifiers":[
        {
            "category":"Manufacturing",
            "subcategory":"Tools & Machinery",
            "type":"Manufacturing & Wholesale Goods"
        }
    ],
    "sg:phone":"+1 972 606 8740",
    "sg:postcode":"75050",
    "sg:province":"TX",
    "sg:tags":[
        "mfg",
        "optical",
        "computer",
        "custom"
    ],
    "wof:name":"Origin Instruments Corp",
    "wof:placetype":"venue"
},
  "geometry": {"coordinates":[-97.055939,32.772217],"type":"Point"}
}