{
  "type": "Feature",
  "properties": {
    "iso:country":"US",
    "sg:address":"2404 N Texas Ave",
    "sg:city":"Bryan",
    "sg:classifiers":[
        {
            "category":"Professional",
            "type":"Services"
        }
    ],
    "sg:phone":"+1 979 361 7823",
    "sg:postcode":"77803",
    "sg:province":"TX",
    "sg:tags":[
        "establishment"
    ],
    "wof:name":"D & D Global Enterprises",
    "wof:placetype":"venue"
},
  "geometry": {"coordinates":[-96.379594,30.693764],"type":"Point"}
}