{
  "type": "Feature",
  "properties": {
    "iso:country":"US",
    "sg:address":"920 Studemont St",
    "sg:city":"Houston",
    "sg:classifiers":[
        {
            "category":"Retail",
            "subcategory":"Laundry & Dry Cleaning",
            "type":"Services"
        }
    ],
    "sg:phone":"+1 713 880 9910",
    "sg:postcode":"77007",
    "sg:province":"TX",
    "wof:name":"Urban Cleaners",
    "wof:placetype":"venue"
},
  "geometry": {"coordinates":[-95.39209700000001,29.767799],"type":"Point"}
}