{
  "type": "Feature",
  "properties": {
    "iso:country":"US",
    "sg:address":"715 Fm 1959 Rd Apt 1502",
    "sg:city":"Houston",
    "sg:classifiers":[
        {
            "category":"Real Estate",
            "subcategory":"Real Estate Operator",
            "type":"Services"
        }
    ],
    "sg:phone":"+1 281 484 8738",
    "sg:postcode":"77034",
    "sg:province":"TX",
    "sg:tags":[
        "apartment"
    ],
    "wof:name":"Suncreek Apartments",
    "wof:placetype":"venue"
},
  "geometry": {"coordinates":[-95.180199,29.5921],"type":"Point"}
}