{
  "type": "Feature",
  "properties": {
    "iso:country":"US",
    "sg:address":"703 Grandview Ave",
    "sg:city":"Seagoville",
    "sg:classifiers":[
        {
            "category":"Building & Trades",
            "subcategory":"Construction",
            "type":"Services"
        }
    ],
    "sg:phone":"+1 972 564 9299",
    "sg:postcode":"75159",
    "sg:province":"TX",
    "sg:tags":[
        "house"
    ],
    "wof:name":"Shepard Place Homes",
    "wof:placetype":"venue"
},
  "geometry": {"coordinates":[-96.537661,32.653687],"type":"Point"}
}