{
  "type": "Feature",
  "properties": {
    "iso:country":"US",
    "sg:address":"1912 Bench Mark Dr",
    "sg:city":"Austin",
    "sg:classifiers":[
        {
            "category":"Retail",
            "subcategory":"Repair Shop",
            "type":"Services"
        }
    ],
    "sg:phone":"+1 512 989 3111",
    "sg:postcode":"78728",
    "sg:province":"TX",
    "sg:tags":[
        "cleaning",
        "lot",
        "parking"
    ],
    "wof:name":"Sweep Across Texas",
    "wof:placetype":"venue"
},
  "geometry": {"coordinates":[-97.682092,30.432842],"type":"Point"}
}