{
  "type": "Feature",
  "properties": {
    "iso:country":"US",
    "sg:address":"5212 87th St",
    "sg:city":"Lubbock",
    "sg:classifiers":[
        {
            "category":"Real Estate",
            "subcategory":"Real Estate Agent",
            "type":"Services"
        }
    ],
    "sg:phone":"+1 806 786 1375",
    "sg:postcode":"79424",
    "sg:province":"TX",
    "sg:tags":[
        "inspection"
    ],
    "wof:name":"Joe Bellar Real Estate",
    "wof:placetype":"venue"
},
  "geometry": {"coordinates":[-101.923925,33.514466],"type":"Point"}
}