{
  "type": "Feature",
  "properties": {
    "iso:country":"US",
    "sg:address":"2000 Seabiscuit Trce",
    "sg:city":"Longview",
    "sg:classifiers":[
        {
            "category":"Professional",
            "subcategory":"Management & Consulting",
            "type":"Services"
        }
    ],
    "sg:phone":"+1 903 759 7253",
    "sg:postcode":"75604",
    "sg:province":"TX",
    "sg:tags":[
        "business"
    ],
    "wof:name":"Champion Packaging",
    "wof:placetype":"venue"
},
  "geometry": {"coordinates":[-94.78903699999999,32.527254],"type":"Point"}
}