{
  "type": "Feature",
  "properties": {
    "iso:country":"US",
    "sg:address":"1425 20th St NE",
    "sg:city":"Paris",
    "sg:classifiers":[
        {
            "category":"Retail",
            "subcategory":"Laundry & Dry Cleaning",
            "type":"Services"
        }
    ],
    "sg:phone":"+1 903 785 0975",
    "sg:postcode":"75460",
    "sg:province":"TX",
    "sg:tags":[
        "cleaners"
    ],
    "wof:name":"Best Laundry & Cleaner",
    "wof:placetype":"venue"
},
  "geometry": {"coordinates":[-95.532106,33.673909],"type":"Point"}
}