{
  "type": "Feature",
  "properties": {
    "iso:country":"US",
    "sg:address":"10914 Fuqua St",
    "sg:city":"Houston",
    "sg:classifiers":[
        {
            "category":"Real Estate",
            "subcategory":"Real Estate Services",
            "type":"Services"
        }
    ],
    "sg:phone":"+1 281 481 9000",
    "sg:postcode":"77089",
    "sg:province":"TX",
    "wof:name":"Century 21",
    "wof:placetype":"venue"
},
  "geometry": {"coordinates":[-95.224098,29.611601],"type":"Point"}
}