{
  "type": "Feature",
  "properties": {
    "iso:country":"US",
    "sg:address":"12155 Jones Rd",
    "sg:city":"Houston",
    "sg:classifiers":[
        {
            "category":"Sports & Exercise",
            "subcategory":"Gym",
            "type":"Entertainment"
        }
    ],
    "sg:phone":"+1 281 890 4772",
    "sg:postcode":"77070",
    "sg:province":"TX",
    "sg:tags":[
        "spa",
        "day",
        "resort"
    ],
    "wof:name":"Utopia Spa Inc",
    "wof:placetype":"venue"
},
  "geometry": {"coordinates":[-95.584896,29.94985],"type":"Point"}
}