{
  "type": "Feature",
  "properties": {
    "iso:country":"US",
    "sg:address":"1000 Sycamore Creek Dr",
    "sg:city":"Dripping Springs",
    "sg:classifiers":[
        {
            "category":"Insurance",
            "subcategory":"Insurance Agent",
            "type":"Services"
        }
    ],
    "sg:phone":"+1 512 858 7636",
    "sg:postcode":"78620",
    "sg:province":"TX",
    "wof:name":"Ecological Dsgn & Plnng",
    "wof:placetype":"venue"
},
  "geometry": {"coordinates":[-98.197215,30.262576],"type":"Point"}
}