{
  "type": "Feature",
  "properties": {
    "iso:country":"US",
    "sg:address":"1000 S Western St",
    "sg:city":"Amarillo",
    "sg:classifiers":[
        {
            "category":"Retail",
            "subcategory":"Auto Repair",
            "type":"Services"
        }
    ],
    "sg:phone":"+1 806 679 4029",
    "sg:postcode":"79106",
    "sg:province":"TX",
    "sg:tags":[
        "repairing",
        "automobile"
    ],
    "wof:name":"4k Car Unlock",
    "wof:placetype":"venue"
},
  "geometry": {"coordinates":[-101.884029,35.203963],"type":"Point"}
}