{
  "type": "Feature",
  "properties": {
    "iso:country":"US",
    "sg:address":"1219 S Eddy St",
    "sg:city":"Pecos",
    "sg:classifiers":[
        {
            "category":"Health Services",
            "subcategory":"Chiropractor",
            "type":"Services"
        }
    ],
    "sg:phone":"+1 432 447 9999",
    "sg:postcode":"79772",
    "sg:province":"TX",
    "wof:name":"Pecos Paint & Accident Chiro",
    "wof:placetype":"venue"
},
  "geometry": {"coordinates":[-103.50134,31.414334],"type":"Point"}
}