{
  "type": "Feature",
  "properties": {
    "iso:country":"US",
    "sg:address":"505 Rabbit Blvd",
    "sg:city":"Atlanta",
    "sg:classifiers":[
        {
            "category":"Education",
            "subcategory":"School",
            "type":"Public Place"
        }
    ],
    "sg:phone":"+1 903 796 8115",
    "sg:postcode":"75551",
    "sg:province":"TX",
    "sg:tags":[
        "elementary"
    ],
    "wof:name":"Atlanta Pri Elementary School",
    "wof:placetype":"venue"
},
  "geometry": {"coordinates":[-94.145391,33.117433],"type":"Point"}
}