{
  "type": "Feature",
  "properties": {
    "iso:country":"US",
    "sg:address":"2710 Chase St",
    "sg:city":"Brenham",
    "sg:classifiers":[
        {
            "category":"Building & Trades",
            "subcategory":"Construction",
            "type":"Services"
        }
    ],
    "sg:phone":"+1 979 836 9897",
    "sg:postcode":"77833",
    "sg:province":"TX",
    "sg:tags":[
        "wallcoverings-installation",
        "wallpaper",
        "painting",
        "contractor"
    ],
    "wof:name":"Jean Kroll-Oil Painting",
    "wof:placetype":"venue"
},
  "geometry": {"coordinates":[-96.366158,30.146762],"type":"Point"}
}