{
  "type": "Feature",
  "properties": {
    "iso:country":"US",
    "sg:address":"820 Hedgcoxe Rd",
    "sg:city":"Plano",
    "sg:classifiers":[
        {
            "category":"Professional",
            "type":"Services"
        }
    ],
    "sg:phone":"+1 972 517 1362",
    "sg:postcode":"75025",
    "sg:province":"TX",
    "wof:name":"Rickman Services Co",
    "wof:placetype":"venue"
},
  "geometry": {"coordinates":[-96.70829500000001,33.084859],"type":"Point"}
}