{
  "type": "Feature",
  "properties": {
    "iso:country":"US",
    "sg:address":"2905 Forest Ln",
    "sg:city":"Garland",
    "sg:classifiers":[
        {
            "category":"Retail",
            "subcategory":"Auto Repair",
            "type":"Services"
        }
    ],
    "sg:phone":"+1 972 272 6795",
    "sg:postcode":"75042",
    "sg:province":"TX",
    "sg:tags":[
        "body",
        "shop"
    ],
    "wof:name":"Jc Auto Collision Center",
    "wof:placetype":"venue"
},
  "geometry": {"coordinates":[-96.674004,32.909302],"type":"Point"}
}