{
  "type": "Feature",
  "properties": {
    "iso:country":"US",
    "sg:address":"4510 Washington Blvd",
    "sg:city":"Beaumont",
    "sg:classifiers":[
        {
            "category":"Retail",
            "subcategory":"Auto Repair",
            "type":"Services"
        }
    ],
    "sg:phone":"+1 409 840 6447",
    "sg:postcode":"77707",
    "sg:province":"TX",
    "sg:tags":[
        "truck"
    ],
    "wof:name":"Interstate Tire & Mechanical",
    "wof:placetype":"venue"
},
  "geometry": {"coordinates":[-94.140749,30.055726],"type":"Point"}
}