{
  "type": "Feature",
  "properties": {
    "iso:country":"US",
    "sg:address":"1207 W 45th St",
    "sg:city":"Austin",
    "sg:classifiers":[
        {
            "category":"Organizations",
            "subcategory":"Religious Organization",
            "type":"Services"
        }
    ],
    "sg:phone":"+1 512 453 3835",
    "sg:postcode":"78756",
    "sg:province":"TX",
    "sg:tags":[
        "lutheran",
        "church"
    ],
    "wof:name":"Trinity Lutheran Church",
    "wof:placetype":"venue"
},
  "geometry": {"coordinates":[-97.74054700000001,30.314808],"type":"Point"}
}