{
  "type": "Feature",
  "properties": {
    "iso:country":"US",
    "sg:address":"1919 San Pedro Ave",
    "sg:city":"San Antonio",
    "sg:classifiers":[
        {
            "category":"Professional",
            "subcategory":"Lawyer & Legal Services",
            "type":"Services"
        }
    ],
    "sg:phone":"+1 210 223 5752",
    "sg:postcode":"78212",
    "sg:province":"TX",
    "wof:name":"Pamela Thompson",
    "wof:placetype":"venue"
},
  "geometry": {"coordinates":[-98.499369,29.452755],"type":"Point"}
}