{
  "type": "Feature",
  "properties": {
    "iso:country":"US",
    "sg:address":"2408 Timberloch Pl",
    "sg:city":"Spring",
    "sg:classifiers":[
        {
            "category":"Wholesale",
            "subcategory":"Machinery & Supplies",
            "type":"Manufacturing & Wholesale Goods"
        }
    ],
    "sg:phone":"+1 281 367 8866",
    "sg:postcode":"77380",
    "sg:province":"TX",
    "sg:tags":[
        "industrial"
    ],
    "wof:name":"Shawcor Inc",
    "wof:placetype":"venue"
},
  "geometry": {"coordinates":[-95.469341,30.158173],"type":"Point"}
}