{
  "type": "Feature",
  "properties": {
    "iso:country":"US",
    "sg:address":"4312 Versailles Ave",
    "sg:city":"Dallas",
    "sg:classifiers":[
        {
            "category":"Arts & Performance",
            "subcategory":"Theater",
            "type":"Entertainment"
        }
    ],
    "sg:phone":"+1 214 521 0862",
    "sg:postcode":"75205",
    "sg:province":"TX",
    "sg:tags":[
        "music"
    ],
    "wof:name":"Al Entertainment",
    "wof:placetype":"venue"
},
  "geometry": {"coordinates":[-96.809569,32.831227],"type":"Point"}
}