{
  "type": "Feature",
  "properties": {
    "iso:country":"US",
    "sg:address":"26 S Cliffwood Dr",
    "sg:city":"Belton",
    "sg:classifiers":[
        {
            "category":"Banks & Credit Unions",
            "subcategory":"Financial Services",
            "type":"Services"
        }
    ],
    "sg:phone":"+1 254 780 9853",
    "sg:postcode":"76513",
    "sg:province":"TX",
    "sg:tags":[
        "investment",
        "closed"
    ],
    "wof:name":"Nesa Management",
    "wof:placetype":"venue"
},
  "geometry": {"coordinates":[-97.479902,31.151459],"type":"Point"}
}