{
  "type": "Feature",
  "properties": {
    "iso:country":"US",
    "sg:address":"809 E 2nd St",
    "sg:city":"Hereford",
    "sg:classifiers":[
        {
            "category":"Retail",
            "subcategory":"Auto Repair",
            "type":"Services"
        }
    ],
    "sg:phone":"+1 806 363 6308",
    "sg:postcode":"79045",
    "sg:province":"TX",
    "sg:tags":[
        "general"
    ],
    "wof:name":"Auto AG Service Inc",
    "wof:placetype":"venue"
},
  "geometry": {"coordinates":[-102.39030700000001,34.820009],"type":"Point"}
}