{
  "type": "Feature",
  "properties": {
    "iso:country":"US",
    "sg:address":"3601 22nd St",
    "sg:city":"Lubbock",
    "sg:classifiers":[
        {
            "category":"Health Services",
            "subcategory":"Doctor",
            "type":"Services"
        }
    ],
    "sg:phone":"+1 806 797 9666",
    "sg:postcode":"79410",
    "sg:province":"TX",
    "sg:tags":[
        "medical"
    ],
    "wof:name":"Dilip K Pal MD",
    "wof:placetype":"venue"
},
  "geometry": {"coordinates":[-101.894268,33.575029],"type":"Point"}
}