{
  "type": "Feature",
  "properties": {
    "iso:country":"US",
    "sg:address":"610 Autumn Leaves Trl",
    "sg:city":"Irving",
    "sg:classifiers":[
        {
            "category":"Building & Trades",
            "subcategory":"Landscaping Services",
            "type":"Services"
        }
    ],
    "sg:phone":"+1 972 870 1122",
    "sg:postcode":"75060",
    "sg:province":"TX",
    "wof:name":"Francisco Lawn Care Service",
    "wof:placetype":"venue"
},
  "geometry": {"coordinates":[-96.995037,32.810075],"type":"Point"}
}