{
  "type": "Feature",
  "properties": {
    "iso:country":"US",
    "sg:address":"4000 Telephone Rd",
    "sg:city":"Houston",
    "sg:classifiers":[
        {
            "category":"Wholesale",
            "subcategory":"Machinery & Supplies",
            "type":"Manufacturing & Wholesale Goods"
        },
        {
            "category":"Manufacturing",
            "subcategory":"Tools & Machinery",
            "type":"Manufacturing & Wholesale Goods"
        }
    ],
    "sg:phone":"+1 713 643 4426",
    "sg:postcode":"77087",
    "sg:province":"TX",
    "sg:tags":[
        "mfg",
        "construction",
        "contractor"
    ],
    "wof:name":"Brunner & Lay Inc",
    "wof:placetype":"venue"
},
  "geometry": {"coordinates":[-95.30897299999999,29.706332],"type":"Point"}
}