{
  "type": "Feature",
  "properties": {
    "iso:country":"US",
    "sg:address":"401 W Main St",
    "sg:city":"Denison",
    "sg:classifiers":[
        {
            "category":"Shopping",
            "subcategory":"Books",
            "type":"Retail Goods"
        }
    ],
    "sg:phone":"+1 903 463 2310",
    "sg:postcode":"75020",
    "sg:province":"TX",
    "sg:tags":[
        "re"
    ],
    "wof:name":"Christian Book Store",
    "wof:placetype":"venue"
},
  "geometry": {"coordinates":[-96.54152999999999,33.755511],"type":"Point"}
}