{
  "type": "Feature",
  "properties": {
    "iso:country":"US",
    "sg:address":"6214 Scottsboro Ln",
    "sg:city":"Garland",
    "sg:classifiers":[
        {
            "category":"Professional",
            "subcategory":"Management & Consulting",
            "type":"Services"
        }
    ],
    "sg:phone":"+1 972 530 3867",
    "sg:postcode":"75044",
    "sg:province":"TX",
    "wof:name":"Best Dam Consultants Inc",
    "wof:placetype":"venue"
},
  "geometry": {"coordinates":[-96.619928,32.971989],"type":"Point"}
}