{
  "type": "Feature",
  "properties": {
    "iso:country":"US",
    "sg:address":"6101 Balcones Dr Ste 100",
    "sg:city":"Austin",
    "sg:classifiers":[
        {
            "category":"Personal",
            "subcategory":"Massage",
            "type":"Services"
        },
        {
            "category":"Personal",
            "subcategory":"Day Spa",
            "type":"Services"
        },
        {
            "category":"Personal",
            "subcategory":"Skin Care",
            "type":"Services"
        }
    ],
    "sg:phone":"+1 512 453 7000",
    "sg:postcode":"78731",
    "sg:province":"TX",
    "sg:website":"www.3gracesspa.com",
    "wof:name":"3 Graces Spa",
    "wof:placetype":"venue"
},
  "geometry": {"coordinates":[-97.75304800000001,30.343326],"type":"Point"}
}