{
  "type": "Feature",
  "properties": {
    "iso:country":"US",
    "sg:address":"1720 Hayden Dr",
    "sg:city":"Carrollton",
    "sg:classifiers":[
        {
            "category":"Manufacturing",
            "subcategory":"Tools & Machinery",
            "type":"Manufacturing & Wholesale Goods"
        }
    ],
    "sg:phone":"+1 972 387 0850",
    "sg:postcode":"75006",
    "sg:province":"TX",
    "sg:tags":[
        "battery"
    ],
    "sg:website":"www.ubcbattery.com",
    "wof:name":"Universal Power Group Inc",
    "wof:placetype":"venue"
},
  "geometry": {"coordinates":[-96.883543,32.958634],"type":"Point"}
}