{
  "type": "Feature",
  "properties": {
    "iso:country":"US",
    "sg:address":"120 Harper Rd",
    "sg:city":"Kerrville",
    "sg:classifiers":[
        {
            "category":"Home & Garden",
            "subcategory":"Furniture",
            "type":"Retail Goods"
        },
        {
            "category":"Banks & Credit Unions",
            "subcategory":"Bank",
            "type":"Services"
        }
    ],
    "sg:phone":"+1 830 895 5311",
    "sg:postcode":"78028",
    "sg:province":"TX",
    "sg:tags":[
        "consumer",
        "finance"
    ],
    "sg:website":"www.mooreshomefurnishings.com",
    "wof:name":"Moore's Home Furnishing Ctr",
    "wof:placetype":"venue"
},
  "geometry": {"coordinates":[-99.16324899999999,30.060376],"type":"Point"}
}