{
  "type": "Feature",
  "properties": {
    "iso:country":"US",
    "sg:address":"245 Beech St",
    "sg:city":"Lumberton",
    "sg:classifiers":[
        {
            "category":"Insurance",
            "subcategory":"Insurance Agent",
            "type":"Services"
        }
    ],
    "sg:phone":"+1 409 755 0387",
    "sg:postcode":"77657",
    "sg:province":"TX",
    "wof:name":"Randy & Gail Hicks",
    "wof:placetype":"venue"
},
  "geometry": {"coordinates":[-94.199817,30.284465],"type":"Point"}
}