{
  "type": "Feature",
  "properties": {
    "iso:country":"US",
    "sg:address":"29 Yellow Tail Cove",
    "sg:city":"Austin",
    "sg:classifiers":[
        {
            "category":"Wholesale",
            "subcategory":"Electrical",
            "type":"Manufacturing & Wholesale Goods"
        }
    ],
    "sg:phone":"+1 512 891 8558",
    "sg:postcode":"78745",
    "sg:province":"TX",
    "sg:tags":[
        "electronic"
    ],
    "wof:name":"Mission Parts Inc",
    "wof:placetype":"venue"
},
  "geometry": {"coordinates":[-97.81437699999999,30.224681],"type":"Point"}
}