{
  "type": "Feature",
  "properties": {
    "iso:country":"US",
    "sg:address":"2349 W McCormick St",
    "sg:city":"Odessa",
    "sg:classifiers":[
        {
            "category":"Building & Trades",
            "subcategory":"Construction",
            "type":"Services"
        }
    ],
    "sg:phone":"+1 432 332 9908",
    "sg:postcode":"79766",
    "sg:province":"TX",
    "sg:tags":[
        "concrete",
        "contractor"
    ],
    "wof:name":"Hmr Cement Contractors",
    "wof:placetype":"venue"
},
  "geometry": {"coordinates":[-102.380454,31.798202],"type":"Point"}
}