{
  "type": "Feature",
  "properties": {
    "iso:country":"US",
    "sg:address":"1601 W Frank Ave",
    "sg:city":"Lufkin",
    "sg:classifiers":[
        {
            "category":"Wholesale",
            "subcategory":"Auto Parts",
            "type":"Manufacturing & Wholesale Goods"
        }
    ],
    "sg:phone":"+1 936 634 6664",
    "sg:postcode":"75904",
    "sg:province":"TX",
    "wof:name":"NAPA Auto Parts",
    "wof:placetype":"venue"
},
  "geometry": {"coordinates":[-94.75030099999999,31.334771],"type":"Point"}
}