{
  "type": "Feature",
  "properties": {
    "iso:country":"US",
    "sg:address":"607 Schley Ave",
    "sg:city":"Alice",
    "sg:classifiers":[
        {
            "category":"Building & Trades",
            "subcategory":"Plumbing",
            "type":"Services"
        }
    ],
    "sg:phone":"+1 361 664 0803",
    "sg:postcode":"78332",
    "sg:province":"TX",
    "sg:tags":[
        "contractor"
    ],
    "wof:name":"Reuben G AC",
    "wof:placetype":"venue"
},
  "geometry": {"coordinates":[-98.06996599999999,27.740685],"type":"Point"}
}