{
  "type": "Feature",
  "properties": {
    "iso:country":"US",
    "sg:address":"2650 Calder Ave",
    "sg:city":"Beaumont",
    "sg:classifiers":[
        {
            "category":"Retail",
            "subcategory":"Repair Shop",
            "type":"Services"
        }
    ],
    "sg:phone":"+1 409 839 0313",
    "sg:postcode":"77702",
    "sg:province":"TX",
    "sg:tags":[
        "equipment",
        "telephone",
        "system"
    ],
    "wof:name":"CTE Inc",
    "wof:placetype":"venue"
},
  "geometry": {"coordinates":[-94.128648,30.085717],"type":"Point"}
}