{
  "type": "Feature",
  "properties": {
    "iso:country":"US",
    "sg:address":"1122 Colorado St",
    "sg:city":"Austin",
    "sg:classifiers":[
        {
            "category":"Organizations",
            "subcategory":"Professional Association",
            "type":"Services"
        }
    ],
    "sg:phone":"+1 512 472 3232",
    "sg:postcode":"78701",
    "sg:province":"TX",
    "wof:name":"Texas Package Stores Assn",
    "wof:placetype":"venue"
},
  "geometry": {"coordinates":[-97.742636,30.274136],"type":"Point"}
}