{
  "type": "Feature",
  "properties": {
    "iso:country":"US",
    "sg:address":"208 Chaparral Dr",
    "sg:city":"Burleson",
    "sg:classifiers":[
        {
            "category":"Insurance",
            "subcategory":"Insurance Agent",
            "type":"Services"
        }
    ],
    "sg:phone":"+1 817 447 7286",
    "sg:postcode":"76028",
    "sg:province":"TX",
    "wof:name":"Strahan Insurance",
    "wof:placetype":"venue"
},
  "geometry": {"coordinates":[-97.285827,32.506715],"type":"Point"}
}