{
  "type": "Feature",
  "properties": {
    "iso:country":"US",
    "sg:address":"614 Coral Pl",
    "sg:city":"Corpus Christi",
    "sg:classifiers":[
        {
            "category":"Utilities",
            "subcategory":"Telephone",
            "type":"Services"
        }
    ],
    "sg:phone":"+1 361 857 2532",
    "sg:postcode":"78411",
    "sg:province":"TX",
    "sg:tags":[
        "communications"
    ],
    "wof:name":"Cribz Co",
    "wof:placetype":"venue"
},
  "geometry": {"coordinates":[-97.377256,27.734419],"type":"Point"}
}