{
  "type": "Feature",
  "properties": {
    "iso:country":"US",
    "sg:address":"1408 Woodlawn Dr",
    "sg:city":"Corpus Christi",
    "sg:classifiers":[
        {
            "category":"Manufacturing",
            "subcategory":"Printing",
            "type":"Manufacturing & Wholesale Goods"
        }
    ],
    "sg:phone":"+1 361 993 6647",
    "sg:postcode":"78412",
    "sg:province":"TX",
    "sg:tags":[
        "commercial"
    ],
    "wof:name":"Dvb Printing",
    "wof:placetype":"venue"
},
  "geometry": {"coordinates":[-97.35279,27.701528],"type":"Point"}
}