{
  "type": "Feature",
  "properties": {
    "iso:country":"US",
    "sg:address":"7007 S Polk St Ste B",
    "sg:city":"Dallas",
    "sg:classifiers":[
        {
            "category":"Insurance",
            "subcategory":"Hazard Insurance",
            "type":"Services"
        }
    ],
    "sg:phone":"+1 214 372 2263",
    "sg:postcode":"75232",
    "sg:province":"TX",
    "wof:name":"Access Insurance Agency",
    "wof:placetype":"venue"
},
  "geometry": {"coordinates":[-96.839996,32.6633],"type":"Point"}
}