{
  "type": "Feature",
  "properties": {
    "iso:country":"US",
    "sg:address":"919 N Palestine St",
    "sg:city":"Athens",
    "sg:classifiers":[
        {
            "category":"Professional",
            "subcategory":"Computer Services",
            "type":"Services"
        }
    ],
    "sg:phone":"+1 903 677 0387",
    "sg:postcode":"75751",
    "sg:province":"TX",
    "sg:website":"http://www.sms-computers.net",
    "wof:name":"Sms Computers",
    "wof:placetype":"venue"
},
  "geometry": {"coordinates":[-95.853644,32.216148],"type":"Point"}
}