{
  "type": "Feature",
  "properties": {
    "iso:country":"US",
    "sg:address":"10138 Long Point Rd",
    "sg:city":"Houston",
    "sg:classifiers":[
        {
            "category":"Home & Garden",
            "subcategory":"Carpets & Floor Coverings",
            "type":"Retail Goods"
        }
    ],
    "sg:phone":"+1 713 467 2929",
    "sg:postcode":"77043",
    "sg:province":"TX",
    "sg:tags":[
        "wholesale",
        "including"
    ],
    "wof:name":"Bond Tile & Flooring Corp",
    "wof:placetype":"venue"
},
  "geometry": {"coordinates":[-95.545969,29.794241],"type":"Point"}
}