{
  "type": "Feature",
  "properties": {
    "iso:country":"US",
    "sg:address":"10650 Kinghurst St",
    "sg:city":"Houston",
    "sg:classifiers":[
        {
            "category":"Shopping",
            "subcategory":"Clothing, Apparel, & Fashions",
            "type":"Retail Goods"
        }
    ],
    "sg:phone":"+1 281 933 3300",
    "sg:postcode":"77099",
    "sg:province":"TX",
    "wof:name":"Fun Apparel Inc",
    "wof:placetype":"venue"
},
  "geometry": {"coordinates":[-95.566101,29.662201],"type":"Point"}
}