{
  "type": "Feature",
  "properties": {
    "iso:country":"US",
    "sg:address":"300 N Highland Ave",
    "sg:city":"Sherman",
    "sg:classifiers":[
        {
            "category":"Health Services",
            "subcategory":"Doctor",
            "type":"Services"
        }
    ],
    "sg:phone":"+1 903 892 1005",
    "sg:postcode":"75092",
    "sg:province":"TX",
    "sg:tags":[
        "physician",
        "surgeon"
    ],
    "wof:name":"Women's Health Assoc",
    "wof:placetype":"venue"
},
  "geometry": {"coordinates":[-96.623232,33.636894],"type":"Point"}
}