{
  "type": "Feature",
  "properties": {
    "iso:country":"US",
    "sg:address":"19364 Hidden Lake Dr",
    "sg:city":"Tyler",
    "sg:classifiers":[
        {
            "category":"Professional",
            "type":"Services"
        }
    ],
    "sg:phone":"+1 903 839 6997",
    "sg:postcode":"75703",
    "sg:province":"TX",
    "wof:name":"Vhrs LLC",
    "wof:placetype":"venue"
},
  "geometry": {"coordinates":[-95.29773900000001,32.19754],"type":"Point"}
}