{
  "type": "Feature",
  "properties": {
    "iso:country":"US",
    "sg:address":"523 N Crockett St",
    "sg:city":"Granbury",
    "sg:classifiers":[
        {
            "category":"Retail",
            "subcategory":"Repair Shop",
            "type":"Services"
        }
    ],
    "sg:phone":"+1 817 573 8810",
    "sg:postcode":"76048",
    "sg:province":"TX",
    "wof:name":"Walker House Antiques",
    "wof:placetype":"venue"
},
  "geometry": {"coordinates":[-97.786619,32.447332],"type":"Point"}
}