{
  "type": "Feature",
  "properties": {
    "iso:country":"US",
    "sg:address":"8175 7th St",
    "sg:city":"Somerset",
    "sg:classifiers":[
        {
            "category":"Organizations",
            "subcategory":"Religious Organization",
            "type":"Services"
        }
    ],
    "sg:phone":"+1 830 701 3255",
    "sg:postcode":"78069",
    "sg:province":"TX",
    "sg:tags":[
        "church"
    ],
    "wof:name":"Somerset United Methodist Chr",
    "wof:placetype":"venue"
},
  "geometry": {"coordinates":[-98.659075,29.225084],"type":"Point"}
}