{
  "type": "Feature",
  "properties": {
    "iso:country":"US",
    "sg:address":"3902 Kimball Ct N",
    "sg:city":"Missouri City",
    "sg:classifiers":[
        {
            "category":"Manufacturing",
            "subcategory":"Building Materials",
            "type":"Manufacturing & Wholesale Goods"
        }
    ],
    "sg:phone":"+1 281 778 7681",
    "sg:postcode":"77459",
    "sg:province":"TX",
    "sg:tags":[
        "mfg"
    ],
    "wof:name":"Callaloo Co",
    "wof:placetype":"venue"
},
  "geometry": {"coordinates":[-95.524079,29.501918],"type":"Point"}
}