{
  "type": "Feature",
  "properties": {
    "iso:country":"US",
    "sg:address":"4220 Matlock Rd",
    "sg:city":"Arlington",
    "sg:classifiers":[
        {
            "category":"Retail",
            "subcategory":"Laundry & Dry Cleaning",
            "type":"Services"
        },
        {
            "category":"Shopping",
            "subcategory":"Clothing, Apparel, & Fashions",
            "type":"Retail Goods"
        }
    ],
    "sg:phone":"+1 817 465 0669",
    "sg:postcode":"76018",
    "sg:province":"TX",
    "sg:tags":[
        "alteration"
    ],
    "wof:name":"Fine Line Alterations",
    "wof:placetype":"venue"
},
  "geometry": {"coordinates":[-97.115137,32.674233],"type":"Point"}
}