{
  "type": "Feature",
  "properties": {
    "iso:country":"US",
    "sg:address":"9304 Crowley Rd Ste C",
    "sg:city":"Fort Worth",
    "sg:classifiers":[
        {
            "category":"Retail",
            "subcategory":"Auto Repair",
            "type":"Services"
        }
    ],
    "sg:phone":"+1 817 568 1355",
    "sg:postcode":"76134",
    "sg:province":"TX",
    "sg:tags":[
        "body",
        "shop"
    ],
    "wof:name":"Ken's Body & Fender Works",
    "wof:placetype":"venue"
},
  "geometry": {"coordinates":[-97.34870100000001,32.6199],"type":"Point"}
}