{
  "type": "Feature",
  "properties": {
    "iso:country":"US",
    "sg:address":"1436 Broadhead Rd",
    "sg:city":"Waxahachie",
    "sg:classifiers":[
        {
            "category":"Building & Trades",
            "subcategory":"Construction",
            "type":"Services"
        }
    ],
    "sg:phone":"+1 972 935 0403",
    "sg:postcode":"75165",
    "sg:province":"TX",
    "sg:tags":[
        "residential"
    ],
    "wof:name":"R & R Services",
    "wof:placetype":"venue"
},
  "geometry": {"coordinates":[-96.793189,32.419904],"type":"Point"}
}