{
  "type": "Feature",
  "properties": {
    "iso:country":"US",
    "sg:address":"611 S Harrison Ave",
    "sg:city":"Crosbyton",
    "sg:phone":"+1 806 675 2293",
    "sg:postcode":"79322",
    "sg:province":"TX",
    "sg:tags":[
        "farm",
        "cotton"
    ],
    "wof:name":"Morris Brothers",
    "wof:placetype":"venue"
},
  "geometry": {"coordinates":[-101.24649700000001,33.652275],"type":"Point"}
}