{
  "type": "Feature",
  "properties": {
    "iso:country":"US",
    "sg:address":"8122 Twin Hills Dr",
    "sg:city":"Houston",
    "sg:classifiers":[
        {
            "category":"Professional",
            "subcategory":"Management & Consulting",
            "type":"Services"
        }
    ],
    "sg:phone":"+1 713 271 5920",
    "sg:postcode":"77071",
    "sg:province":"TX",
    "wof:name":"Cas Financial Services",
    "wof:placetype":"venue"
},
  "geometry": {"coordinates":[-95.524226,29.667418],"type":"Point"}
}