{
  "type": "Feature",
  "properties": {
    "iso:country":"US",
    "sg:address":"528 Jubal Early Ln",
    "sg:city":"Conroe",
    "sg:classifiers":[
        {
            "category":"Professional",
            "subcategory":"Management & Consulting",
            "type":"Services"
        }
    ],
    "sg:phone":"+1 936 271 1152",
    "sg:postcode":"77302",
    "sg:province":"TX",
    "wof:name":"T F Muczynski",
    "wof:placetype":"venue"
},
  "geometry": {"coordinates":[-95.43844900000001,30.258317],"type":"Point"}
}