{
  "type": "Feature",
  "properties": {
    "iso:country":"US",
    "sg:address":"524 N Lamar Blvd Ste 104",
    "sg:city":"Austin",
    "sg:classifiers":[
        {
            "category":"Home & Garden",
            "subcategory":"Furniture",
            "type":"Retail Goods"
        }
    ],
    "sg:phone":"+1 512 472 9234",
    "sg:postcode":"78703",
    "sg:province":"TX",
    "sg:tags":[
        "store"
    ],
    "wof:name":"Zanzibar",
    "wof:placetype":"venue"
},
  "geometry": {"coordinates":[-97.75412799999999,30.27129],"type":"Point"}
}