{
  "type": "Feature",
  "properties": {
    "iso:country":"US",
    "sg:address":"1456 N Bolton St",
    "sg:city":"Jacksonville",
    "sg:classifiers":[
        {
            "category":"Building & Trades",
            "subcategory":"Plumbing",
            "type":"Services"
        }
    ],
    "sg:phone":"+1 903 586 9638",
    "sg:postcode":"75766",
    "sg:province":"TX",
    "sg:tags":[
        "conditioning",
        "air",
        "system",
        "contractor"
    ],
    "wof:name":"Snoke Special Prods",
    "wof:placetype":"venue"
},
  "geometry": {"coordinates":[-95.276487,31.985213],"type":"Point"}
}