{
  "type": "Feature",
  "properties": {
    "iso:country":"US",
    "sg:address":"2737 S Broadway Ave",
    "sg:city":"Tyler",
    "sg:classifiers":[
        {
            "category":"Social Services",
            "type":"Services"
        }
    ],
    "sg:phone":"+1 903 535 9056",
    "sg:postcode":"75701",
    "sg:province":"TX",
    "wof:name":"Network",
    "wof:placetype":"venue"
},
  "geometry": {"coordinates":[-95.300707,32.316283],"type":"Point"}
}