{
  "type": "Feature",
  "properties": {
    "iso:country":"US",
    "sg:address":"107 RM 620 N",
    "sg:city":"Austin",
    "sg:classifiers":[
        {
            "category":"Food & Beverages",
            "subcategory":"Specialty",
            "type":"Retail Goods"
        }
    ],
    "sg:phone":"+1 512 261 5009",
    "sg:postcode":"78734",
    "sg:province":"TX",
    "wof:name":"Karemor Distributor",
    "wof:placetype":"venue"
},
  "geometry": {"coordinates":[-97.951724,30.364955],"type":"Point"}
}