{
  "type": "Feature",
  "properties": {
    "iso:country":"US",
    "sg:address":"10107 Antrim Ln",
    "sg:city":"La Porte",
    "sg:classifiers":[
        {
            "category":"Freight",
            "type":"Transportation"
        }
    ],
    "sg:phone":"+1 281 471 8594",
    "sg:postcode":"77571",
    "sg:province":"TX",
    "wof:name":"L&W Transportation Inc",
    "wof:placetype":"venue"
},
  "geometry": {"coordinates":[-95.07931000000001,29.663193],"type":"Point"}
}