{
  "type": "Feature",
  "properties": {
    "iso:country":"US",
    "sg:address":"5359 US Hwy 175",
    "sg:city":"Kaufman",
    "sg:classifiers":[
        {
            "category":"Manufacturing",
            "subcategory":"Signs",
            "type":"Manufacturing & Wholesale Goods"
        }
    ],
    "sg:phone":"+1 972 932 8270",
    "sg:postcode":"75142",
    "sg:province":"TX",
    "wof:name":"Xtreme Signs",
    "wof:placetype":"venue"
},
  "geometry": {"coordinates":[-96.269582,32.520972],"type":"Point"}
}