{
  "type": "Feature",
  "properties": {
    "iso:country":"US",
    "sg:address":"2625 S Loop 35",
    "sg:city":"Alvin",
    "sg:classifiers":[
        {
            "category":"Banks & Credit Unions",
            "subcategory":"Bank",
            "type":"Services"
        }
    ],
    "sg:phone":"+1 281 585 5500",
    "sg:postcode":"77511",
    "sg:province":"TX",
    "sg:tags":[
        "financing",
        "institution",
        "business"
    ],
    "wof:name":"Reliable Finance Co",
    "wof:placetype":"venue"
},
  "geometry": {"coordinates":[-95.24464,29.399708],"type":"Point"}
}