{
  "type": "Feature",
  "properties": {
    "iso:country":"US",
    "sg:address":"1818 Paisley St",
    "sg:city":"San Antonio",
    "sg:classifiers":[
        {
            "category":"Building & Trades",
            "subcategory":"Construction",
            "type":"Services"
        }
    ],
    "sg:phone":"+1 210 492 6089",
    "sg:postcode":"78231",
    "sg:province":"TX",
    "sg:tags":[
        "nonresidential"
    ],
    "wof:name":"Wongs Family Enterprises Ltd",
    "wof:placetype":"venue"
},
  "geometry": {"coordinates":[-98.523685,29.549978],"type":"Point"}
}