{
  "type": "Feature",
  "properties": {
    "iso:country":"US",
    "sg:address":"1607 Kennedy Dr",
    "sg:city":"Wylie",
    "sg:classifiers":[
        {
            "category":"Utilities",
            "subcategory":"Telephone",
            "type":"Services"
        }
    ],
    "sg:phone":"+1 972 442 4923",
    "sg:postcode":"75098",
    "sg:province":"TX",
    "sg:tags":[
        "communications"
    ],
    "wof:name":"Fortune Telecom Systems",
    "wof:placetype":"venue"
},
  "geometry": {"coordinates":[-96.569914,33.023854],"type":"Point"}
}