{
  "type": "Feature",
  "properties": {
    "iso:country":"US",
    "sg:address":"711 Broadway",
    "sg:city":"San Antonio",
    "sg:classifiers":[
        {
            "category":"Health Services",
            "subcategory":"Clinic",
            "type":"Services"
        }
    ],
    "sg:phone":"+1 210 224 1749",
    "sg:postcode":"78215",
    "sg:province":"TX",
    "sg:tags":[
        "center"
    ],
    "wof:name":"Nabi Biopharmaceuticals",
    "wof:placetype":"venue"
},
  "geometry": {"coordinates":[-98.48277400000001,29.432601],"type":"Point"}
}