{
  "type": "Feature",
  "properties": {
    "iso:country":"US",
    "sg:address":"320 Meadowhill Dr",
    "sg:city":"Fort Worth",
    "sg:classifiers":[
        {
            "category":"Shopping",
            "subcategory":"Gifts & Souvenirs",
            "type":"Retail Goods"
        }
    ],
    "sg:phone":"+1 817 249 6767",
    "sg:postcode":"76126",
    "sg:province":"TX",
    "wof:name":"Dragons Tale",
    "wof:placetype":"venue"
},
  "geometry": {"coordinates":[-97.485345,32.669501],"type":"Point"}
}