{
  "type": "Feature",
  "properties": {
    "iso:country":"US",
    "sg:address":"2031 Amistad Dr",
    "sg:city":"San Benito",
    "sg:classifiers":[
        {
            "category":"Building & Trades",
            "subcategory":"Construction",
            "type":"Services"
        }
    ],
    "sg:phone":"+1 956 399 2271",
    "sg:postcode":"78586",
    "sg:province":"TX",
    "wof:name":"Royal Metal Building Component",
    "wof:placetype":"venue"
},
  "geometry": {"coordinates":[-97.656085,26.138215],"type":"Point"}
}