{
  "type": "Feature",
  "properties": {
    "iso:country":"US",
    "sg:address":"500 E Arapaho Rd Ste 111",
    "sg:city":"Richardson",
    "sg:classifiers":[
        {
            "category":"Building & Trades",
            "subcategory":"Plumbing",
            "type":"Services"
        }
    ],
    "sg:phone":"+1 972 235 7458",
    "sg:postcode":"75081",
    "sg:province":"TX",
    "wof:name":"Chambers Plumbing Inc",
    "wof:placetype":"venue"
},
  "geometry": {"coordinates":[-96.717758,32.960512],"type":"Point"}
}