{
  "type": "Feature",
  "properties": {
    "iso:country":"US",
    "sg:address":"4514 Travis St Ste 235",
    "sg:city":"Dallas",
    "sg:classifiers":[
        {
            "category":"Building & Trades",
            "subcategory":"Construction",
            "type":"Services"
        },
        {
            "category":"Real Estate",
            "subcategory":"Architect",
            "type":"Services"
        }
    ],
    "sg:phone":"+1 214 528 4499",
    "sg:postcode":"75205",
    "sg:province":"TX",
    "sg:tags":[
        "interior",
        "design"
    ],
    "wof:name":"Selzer Associates Inc",
    "wof:placetype":"venue"
},
  "geometry": {"coordinates":[-96.791,32.8223],"type":"Point"}
}