{
  "type": "Feature",
  "properties": {
    "iso:country":"US",
    "sg:address":"201 Spring St",
    "sg:city":"Brackettville",
    "sg:classifiers":[
        {
            "category":"Social Services",
            "type":"Services"
        }
    ],
    "sg:phone":"+1 830 563 9694",
    "sg:postcode":"78832",
    "sg:province":"TX",
    "sg:tags":[
        "organization",
        "welfare"
    ],
    "wof:name":"Bracketville Career Ctr",
    "wof:placetype":"venue"
},
  "geometry": {"coordinates":[-100.421105,29.312354],"type":"Point"}
}