{
  "type": "Feature",
  "properties": {
    "iso:country":"US",
    "sg:address":"5806 Sedgefield Dr",
    "sg:city":"Austin",
    "sg:classifiers":[
        {
            "category":"Professional",
            "type":"Services"
        }
    ],
    "sg:phone":"+1 512 327 9697",
    "sg:postcode":"78746",
    "sg:province":"TX",
    "wof:name":"Mvigil LLC",
    "wof:placetype":"venue"
},
  "geometry": {"coordinates":[-97.833202,30.280678],"type":"Point"}
}