{
  "type": "Feature",
  "properties": {
    "iso:country":"US",
    "sg:address":"339 Tamerlaine Dr",
    "sg:city":"Houston",
    "sg:classifiers":[
        {
            "category":"Building & Trades",
            "subcategory":"Construction",
            "type":"Services"
        }
    ],
    "sg:phone":"+1 713 825 1114",
    "sg:postcode":"77024",
    "sg:province":"TX",
    "sg:tags":[
        "development",
        "property",
        "commercial"
    ],
    "wof:name":"Davis Development",
    "wof:placetype":"venue"
},
  "geometry": {"coordinates":[-95.547415,29.763996],"type":"Point"}
}