{
  "type": "Feature",
  "properties": {
    "iso:country":"US",
    "sg:address":"4731 Callery Creek Dr",
    "sg:city":"Houston",
    "sg:classifiers":[
        {
            "category":"Professional",
            "subcategory":"Business Services",
            "type":"Services"
        }
    ],
    "sg:phone":"+1 281 437 5138",
    "sg:postcode":"77053",
    "sg:province":"TX",
    "sg:tags":[
        "alteration",
        "bed",
        "linen",
        "design",
        "apparel",
        "drapery"
    ],
    "wof:name":"Small Tokens",
    "wof:placetype":"venue"
},
  "geometry": {"coordinates":[-95.451126,29.595482],"type":"Point"}
}