{
  "type": "Feature",
  "properties": {
    "iso:country":"US",
    "sg:address":"3526 Samuell Blvd",
    "sg:city":"Dallas",
    "sg:classifiers":[
        {
            "category":"Food & Beverages",
            "subcategory":"Liquor & Beverages",
            "type":"Retail Goods"
        }
    ],
    "sg:phone":"+1 214 821 6511",
    "sg:postcode":"75223",
    "sg:province":"TX",
    "sg:tags":[
        "beer",
        "spirit",
        "wine"
    ],
    "wof:name":"Super Discount Beverage Grocery Beer & Wine",
    "wof:placetype":"venue"
},
  "geometry": {"coordinates":[-96.7342,32.7929],"type":"Point"}
}