{
  "type": "Feature",
  "properties": {
    "iso:country":"US",
    "sg:address":"12023 Mulholland Dr",
    "sg:city":"Stafford",
    "sg:classifiers":[
        {
            "category":"Manufacturing",
            "subcategory":"Jewelry",
            "type":"Manufacturing & Wholesale Goods"
        }
    ],
    "sg:phone":"+1 281 933 0092",
    "sg:postcode":"77477",
    "sg:province":"TX",
    "sg:tags":[
        "precious",
        "metal",
        "mfg"
    ],
    "wof:name":"Dazzle By Darlane",
    "wof:placetype":"venue"
},
  "geometry": {"coordinates":[-95.594103,29.652346],"type":"Point"}
}