{
  "type": "Feature",
  "properties": {
    "iso:country":"US",
    "sg:address":"5330 Hialeah Dr",
    "sg:city":"Houston",
    "sg:classifiers":[
        {
            "category":"Professional",
            "type":"Services"
        }
    ],
    "sg:phone":"+1 713 681 3644",
    "sg:postcode":"77092",
    "sg:province":"TX",
    "wof:name":"Cobalt Room",
    "wof:placetype":"venue"
},
  "geometry": {"coordinates":[-95.472381,29.826573],"type":"Point"}
}