{
  "type": "Feature",
  "properties": {
    "iso:country":"US",
    "sg:address":"4310 James Casey St",
    "sg:city":"Austin",
    "sg:classifiers":[
        {
            "category":"Health Services",
            "subcategory":"Health Practitioner",
            "type":"Services"
        }
    ],
    "sg:phone":"+1 512 445 5213",
    "sg:postcode":"78745",
    "sg:province":"TX",
    "sg:tags":[
        "therapist",
        "physical"
    ],
    "sg:website":"www.affiliatedtherapies.com",
    "wof:name":"Affilated Therapy",
    "wof:placetype":"venue"
},
  "geometry": {"coordinates":[-97.773521,30.227266],"type":"Point"}
}