{
  "type": "Feature",
  "properties": {
    "iso:country":"US",
    "sg:address":"11624 Jollyville Rd",
    "sg:city":"Austin",
    "sg:classifiers":[
        {
            "category":"Professional",
            "subcategory":"Computer Services",
            "type":"Services"
        },
        {
            "category":"Shopping",
            "subcategory":"Computers & Home Electronics",
            "type":"Retail Goods"
        }
    ],
    "sg:phone":"+1 512 249 1611",
    "sg:postcode":"78759",
    "sg:province":"TX",
    "sg:tags":[
        "prepackaged",
        "software"
    ],
    "wof:name":"Constructive Software Tech",
    "wof:placetype":"venue"
},
  "geometry": {"coordinates":[-97.748875,30.415908],"type":"Point"}
}