{
  "type": "Feature",
  "properties": {
    "iso:country":"US",
    "sg:address":"1110 Airport Fwy",
    "sg:city":"Bedford",
    "sg:classifiers":[
        {
            "category":"Wholesale",
            "subcategory":"Sporting Goods",
            "type":"Manufacturing & Wholesale Goods"
        }
    ],
    "sg:phone":"+1 817 354 7484",
    "sg:postcode":"76022",
    "sg:province":"TX",
    "wof:name":"Tommy Hawk Sportsware",
    "wof:placetype":"venue"
},
  "geometry": {"coordinates":[-97.151286,32.839079],"type":"Point"}
}