{
  "type": "Feature",
  "properties": {
    "iso:country":"US",
    "sg:address":"515 E College St",
    "sg:city":"Seguin",
    "sg:classifiers":[
        {
            "category":"Manufacturing",
            "subcategory":"Jewelry",
            "type":"Manufacturing & Wholesale Goods"
        }
    ],
    "sg:phone":"+1 830 379 6080",
    "sg:postcode":"78155",
    "sg:province":"TX",
    "sg:tags":[
        "precious",
        "metal",
        "mfg"
    ],
    "wof:name":"Franks Jewelry & Gifts",
    "wof:placetype":"venue"
},
  "geometry": {"coordinates":[-97.960823,29.574494],"type":"Point"}
}