{
  "type": "Feature",
  "properties": {
    "iso:country":"US",
    "sg:address":"825 E Pleasant Run Rd",
    "sg:city":"De Soto",
    "sg:classifiers":[
        {
            "category":"Real Estate",
            "subcategory":"Real Estate Operator",
            "type":"Services"
        }
    ],
    "sg:phone":"+1 972 224 7527",
    "sg:postcode":"75115",
    "sg:province":"TX",
    "sg:tags":[
        "building",
        "apartment"
    ],
    "wof:name":"Alliance Residential MGT",
    "wof:placetype":"venue"
},
  "geometry": {"coordinates":[-96.83904099999999,32.604253],"type":"Point"}
}