{
  "type": "Feature",
  "properties": {
    "iso:country":"US",
    "sg:address":"1505 Eden Valley Ln",
    "sg:city":"Plano",
    "sg:classifiers":[
        {
            "category":"Wholesale",
            "subcategory":"Furniture",
            "type":"Manufacturing & Wholesale Goods"
        }
    ],
    "sg:phone":"+1 214 908 9292",
    "sg:postcode":"75093",
    "sg:province":"TX",
    "wof:name":"Jpn Inc",
    "wof:placetype":"venue"
},
  "geometry": {"coordinates":[-96.775155,33.019443],"type":"Point"}
}