{
  "type": "Feature",
  "properties": {
    "iso:country":"US",
    "sg:address":"512 N 76th St",
    "sg:city":"Houston",
    "sg:classifiers":[
        {
            "category":"Retail",
            "subcategory":"Auto Repair",
            "type":"Services"
        }
    ],
    "sg:phone":"+1 713 923 6410",
    "sg:postcode":"77012",
    "sg:province":"TX",
    "sg:tags":[
        "automobile",
        "inspection"
    ],
    "wof:name":"A-1 Inspection Express",
    "wof:placetype":"venue"
},
  "geometry": {"coordinates":[-95.288793,29.735029],"type":"Point"}
}