{
  "type": "Feature",
  "properties": {
    "iso:country":"US",
    "sg:address":"4015 David Phillips St",
    "sg:city":"Dallas",
    "sg:classifiers":[
        {
            "category":"Social Services",
            "type":"Services"
        }
    ],
    "sg:phone":"+1 214 275 4446",
    "sg:postcode":"75227",
    "sg:province":"TX",
    "sg:tags":[
        "counseling"
    ],
    "wof:name":"Shavers Plus Counseling Sols",
    "wof:placetype":"venue"
},
  "geometry": {"coordinates":[-96.662251,32.772896],"type":"Point"}
}