{
  "type": "Feature",
  "properties": {
    "iso:country":"US",
    "sg:address":"5207 Spartan Dr",
    "sg:city":"Houston",
    "sg:classifiers":[
        {
            "category":"Food & Beverages",
            "subcategory":"Candy",
            "type":"Retail Goods"
        }
    ],
    "sg:phone":"+1 713 937 3485",
    "sg:postcode":"77041",
    "sg:province":"TX",
    "wof:name":"Veras Cakes & Candies",
    "wof:placetype":"venue"
},
  "geometry": {"coordinates":[-95.60681599999999,29.844256],"type":"Point"}
}