{
  "type": "Feature",
  "properties": {
    "iso:country":"US",
    "sg:address":"3130 Jazz St",
    "sg:city":"Round Rock",
    "sg:classifiers":[
        {
            "category":"Building & Trades",
            "subcategory":"Construction",
            "type":"Services"
        }
    ],
    "sg:phone":"+1 512 255 7635",
    "sg:postcode":"78664",
    "sg:province":"TX",
    "sg:tags":[
        "contractor"
    ],
    "wof:name":"Liquid Dreams Custom Pools",
    "wof:placetype":"venue"
},
  "geometry": {"coordinates":[-97.65620699999999,30.478728],"type":"Point"}
}