{
  "type": "Feature",
  "properties": {
    "iso:country":"US",
    "sg:address":"2316 6th St",
    "sg:city":"Port Neches",
    "sg:classifiers":[
        {
            "category":"Shopping",
            "subcategory":"Used Merchandise",
            "type":"Retail Goods"
        }
    ],
    "sg:phone":"+1 409 722 8137",
    "sg:postcode":"77651",
    "sg:province":"TX",
    "wof:name":"Today Treasure",
    "wof:placetype":"venue"
},
  "geometry": {"coordinates":[-93.973443,29.982999],"type":"Point"}
}