{
  "type": "Feature",
  "properties": {
    "iso:country":"US",
    "sg:address":"6002 Spring Creek Grove Ln L",
    "sg:city":"Spring",
    "sg:classifiers":[
        {
            "category":"Professional",
            "subcategory":"Management & Consulting",
            "type":"Services"
        }
    ],
    "sg:phone":"+1 281 379 2613",
    "sg:postcode":"77379",
    "sg:province":"TX",
    "sg:tags":[
        "consultant"
    ],
    "wof:name":"The Plasenica Group Inc",
    "wof:placetype":"venue"
},
  "geometry": {"coordinates":[-95.511425,30.036824],"type":"Point"}
}