{
  "type": "Feature",
  "properties": {
    "iso:country":"US",
    "sg:address":"11503 Sweetwater Trl",
    "sg:city":"Austin",
    "sg:classifiers":[
        {
            "category":"Professional",
            "type":"Services"
        }
    ],
    "sg:phone":"+1 512 249 9263",
    "sg:postcode":"78750",
    "sg:province":"TX",
    "wof:name":"Elite Home Network",
    "wof:placetype":"venue"
},
  "geometry": {"coordinates":[-97.81848100000001,30.451915],"type":"Point"}
}