{
  "type": "Feature",
  "properties": {
    "iso:country":"US",
    "sg:address":"1512 Vards Ln",
    "sg:city":"Sweetwater",
    "sg:classifiers":[
        {
            "category":"Professional",
            "type":"Services"
        }
    ],
    "sg:phone":"+1 325 235 4461",
    "sg:postcode":"79556",
    "sg:province":"TX",
    "wof:name":"Terry Henson",
    "wof:placetype":"venue"
},
  "geometry": {"coordinates":[-100.39247400000001,32.486777],"type":"Point"}
}