{
  "type": "Feature",
  "properties": {
    "iso:country":"US",
    "sg:address":"2525 John Glen Pkwy",
    "sg:city":"Mesquite",
    "sg:classifiers":[
        {
            "category":"Recreation",
            "type":"Entertainment"
        }
    ],
    "sg:phone":"+1 972 270 2683",
    "sg:postcode":"75150",
    "sg:province":"TX",
    "sg:tags":[
        "pool",
        "swimming"
    ],
    "wof:name":"Town East Pool",
    "wof:placetype":"venue"
},
  "geometry": {"coordinates":[-96.63404199999999,32.804961],"type":"Point"}
}