{
  "type": "Feature",
  "properties": {
    "iso:country":"US",
    "sg:address":"2100 Andover Dr",
    "sg:city":"Round Rock",
    "sg:classifiers":[
        {
            "category":"Building & Trades",
            "subcategory":"Construction",
            "type":"Services"
        }
    ],
    "sg:phone":"+1 512 388 1011",
    "sg:postcode":"78664",
    "sg:province":"TX",
    "sg:tags":[
        "concrete",
        "contractor"
    ],
    "wof:name":"Two Sons Concrete Contractor",
    "wof:placetype":"venue"
},
  "geometry": {"coordinates":[-97.67568900000001,30.530469],"type":"Point"}
}