{
  "type": "Feature",
  "properties": {
    "iso:country":"US",
    "sg:address":"11930 Brittmoore Park Dr",
    "sg:city":"Houston",
    "sg:classifiers":[
        {
            "category":"Banks & Credit Unions",
            "subcategory":"Financial Services",
            "type":"Services"
        }
    ],
    "sg:phone":"+1 713 725 6651",
    "sg:postcode":"77041",
    "sg:province":"TX",
    "sg:tags":[
        "investor"
    ],
    "wof:name":"E K Salls Jr Interests L L C",
    "wof:placetype":"venue"
},
  "geometry": {"coordinates":[-95.58577699999999,29.856283],"type":"Point"}
}