{
  "type": "Feature",
  "properties": {
    "iso:country":"US",
    "sg:address":"21506 Green Thicket Ct",
    "sg:city":"Spring",
    "sg:classifiers":[
        {
            "category":"Wholesale",
            "subcategory":"Machinery & Supplies",
            "type":"Manufacturing & Wholesale Goods"
        }
    ],
    "sg:phone":"+1 281 353 3482",
    "sg:postcode":"77388",
    "sg:province":"TX",
    "sg:tags":[
        "industrial",
        "valve"
    ],
    "wof:name":"Latex Ind Supply Co",
    "wof:placetype":"venue"
},
  "geometry": {"coordinates":[-95.45143400000001,30.074166],"type":"Point"}
}