{
  "type": "Feature",
  "properties": {
    "iso:country":"US",
    "sg:address":"8014 Barnhill Dr",
    "sg:city":"Humble",
    "sg:classifiers":[
        {
            "category":"Shopping",
            "subcategory":"Jewelry",
            "type":"Retail Goods"
        }
    ],
    "sg:phone":"+1 281 446 3657",
    "sg:postcode":"77338",
    "sg:province":"TX",
    "wof:name":"Carlo Monte Jewelry Inc",
    "wof:placetype":"venue"
},
  "geometry": {"coordinates":[-95.305564,30.007621],"type":"Point"}
}