{
  "type": "Feature",
  "properties": {
    "iso:country":"US",
    "sg:address":"7809 W Rim Dr",
    "sg:city":"Austin",
    "sg:classifiers":[
        {
            "category":"Shopping",
            "subcategory":"Gifts & Souvenirs",
            "type":"Retail Goods"
        }
    ],
    "sg:phone":"+1 512 342 7178",
    "sg:postcode":"78731",
    "sg:province":"TX",
    "wof:name":"Bonnie G Lang",
    "wof:placetype":"venue"
},
  "geometry": {"coordinates":[-97.765722,30.372097],"type":"Point"}
}