{
  "type": "Feature",
  "properties": {
    "iso:country":"US",
    "sg:address":"41 Lonesome Dove Dr",
    "sg:city":"Sherman",
    "sg:classifiers":[
        {
            "category":"Building & Trades",
            "subcategory":"Landscaping Services",
            "type":"Services"
        }
    ],
    "sg:phone":"+1 903 868 2207",
    "sg:postcode":"75090",
    "sg:province":"TX",
    "sg:tags":[
        "lawn",
        "care"
    ],
    "wof:name":"Texoma Lawn Care",
    "wof:placetype":"venue"
},
  "geometry": {"coordinates":[-96.601795,33.550356],"type":"Point"}
}