{
  "type": "Feature",
  "properties": {
    "iso:country":"US",
    "sg:address":"451 W 6th St",
    "sg:city":"Muenster",
    "sg:classifiers":[
        {
            "category":"Mining & Drilling",
            "type":"Manufacturing & Wholesale Goods"
        }
    ],
    "sg:phone":"+1 940 759 4119",
    "sg:postcode":"76252",
    "sg:province":"TX",
    "sg:tags":[
        "oil",
        "gas",
        "producer"
    ],
    "wof:name":"Wayne R Grewing Oil & Gas",
    "wof:placetype":"venue"
},
  "geometry": {"coordinates":[-97.384761,33.654567],"type":"Point"}
}