{
  "type": "Feature",
  "properties": {
    "iso:country":"US",
    "sg:address":"325 Tulum Ln",
    "sg:city":"China Spring",
    "sg:classifiers":[
        {
            "category":"Building & Trades",
            "subcategory":"Construction",
            "type":"Services"
        }
    ],
    "sg:phone":"+1 254 836 4145",
    "sg:postcode":"76633",
    "sg:province":"TX",
    "sg:tags":[
        "house"
    ],
    "wof:name":"Elite Custom Construction",
    "wof:placetype":"venue"
},
  "geometry": {"coordinates":[-97.286168,31.632507],"type":"Point"}
}