{
  "type": "Feature",
  "properties": {
    "iso:country":"US",
    "sg:address":"5000 Westheimer Rd",
    "sg:city":"Houston",
    "sg:classifiers":[
        {
            "category":"Health Services",
            "subcategory":"Optometrist",
            "type":"Services"
        }
    ],
    "sg:phone":"+1 713 623 2000",
    "sg:postcode":"77056",
    "sg:province":"TX",
    "sg:tags":[
        "optical",
        "good"
    ],
    "wof:name":"Doctor Wilma E Barnes",
    "wof:placetype":"venue"
},
  "geometry": {"coordinates":[-95.461906,29.740734],"type":"Point"}
}