{
  "type": "Feature",
  "properties": {
    "iso:country":"US",
    "sg:address":"625 Fuller St",
    "sg:city":"Arlington",
    "sg:classifiers":[
        {
            "category":"Building & Trades",
            "subcategory":"Cleaning & Sanitation",
            "type":"Services"
        }
    ],
    "sg:phone":"+1 817 795 4927",
    "sg:postcode":"76011",
    "sg:province":"TX",
    "sg:tags":[
        "maintenance"
    ],
    "wof:name":"Finesse Care Services",
    "wof:placetype":"venue"
},
  "geometry": {"coordinates":[-97.11222100000001,32.747353],"type":"Point"}
}