{
  "type": "Feature",
  "properties": {
    "iso:country":"US",
    "sg:address":"2562 US Highway 69 N",
    "sg:city":"Lufkin",
    "sg:classifiers":[
        {
            "category":"Autos & Motor Vehicles",
            "subcategory":"Auto Supplies",
            "type":"Retail Goods"
        },
        {
            "category":"Wholesale",
            "subcategory":"Electrical",
            "type":"Manufacturing & Wholesale Goods"
        }
    ],
    "sg:phone":"+1 936 632 2571",
    "sg:postcode":"75904",
    "sg:province":"TX",
    "sg:tags":[
        "battery",
        "batteries-storage-wholesale",
        "batteries-storage",
        "manufacturer"
    ],
    "wof:name":"Interstate Battery System Of America, Inc",
    "wof:placetype":"venue"
},
  "geometry": {"coordinates":[-94.760586,31.373433],"type":"Point"}
}