{
  "type": "Feature",
  "properties": {
    "iso:country":"US",
    "sg:address":"1701 Salesville Rd",
    "sg:city":"Mineral Wells",
    "sg:classifiers":[
        {
            "category":"Shopping",
            "subcategory":"Gifts & Souvenirs",
            "type":"Retail Goods"
        }
    ],
    "sg:phone":"+1 940 327 0065",
    "sg:postcode":"76067",
    "sg:province":"TX",
    "sg:tags":[
        "collectible"
    ],
    "wof:name":"Mary's Melting Pot",
    "wof:placetype":"venue"
},
  "geometry": {"coordinates":[-98.088441,32.919463],"type":"Point"}
}