{
  "type": "Feature",
  "properties": {
    "iso:country":"US",
    "sg:address":"500 Turtle Cove Blvd",
    "sg:city":"Rockwall",
    "sg:classifiers":[
        {
            "category":"Professional",
            "subcategory":"Accounting & Tax Preparation",
            "type":"Services"
        }
    ],
    "sg:phone":"+1 972 771 6489",
    "sg:postcode":"75087",
    "sg:province":"TX",
    "wof:name":"Bush Jack",
    "wof:placetype":"venue"
},
  "geometry": {"coordinates":[-96.46813899999999,32.903016],"type":"Point"}
}