{
  "type": "Feature",
  "properties": {
    "iso:country":"US",
    "sg:address":"3610 Trent Rd",
    "sg:city":"Huffman",
    "sg:classifiers":[
        {
            "category":"Retail",
            "subcategory":"Auto Repair",
            "type":"Services"
        }
    ],
    "sg:phone":"+1 281 360 8416",
    "sg:postcode":"77336",
    "sg:province":"TX",
    "sg:tags":[
        "general"
    ],
    "wof:name":"Owen Auto Repair",
    "wof:placetype":"venue"
},
  "geometry": {"coordinates":[-95.098142,30.092264],"type":"Point"}
}