{
  "type": "Feature",
  "properties": {
    "iso:country":"US",
    "sg:address":"5402 Miller Ave",
    "sg:city":"Dallas",
    "sg:classifiers":[
        {
            "category":"Professional",
            "type":"Services"
        }
    ],
    "sg:phone":"+1 214 887 8833",
    "sg:postcode":"75206",
    "sg:province":"TX",
    "wof:name":"Trufaux LLC",
    "wof:placetype":"venue"
},
  "geometry": {"coordinates":[-96.774767,32.82122],"type":"Point"}
}