{
  "type": "Feature",
  "properties": {
    "iso:country":"US",
    "sg:address":"7222 Fair Oaks Ave",
    "sg:city":"Dallas",
    "sg:classifiers":[
        {
            "category":"Professional",
            "subcategory":"Management & Consulting",
            "type":"Services"
        }
    ],
    "sg:phone":"+1 214 346 9781",
    "sg:postcode":"75231",
    "sg:province":"TX",
    "sg:tags":[
        "consultant"
    ],
    "wof:name":"M M Consulting Svc",
    "wof:placetype":"venue"
},
  "geometry": {"coordinates":[-96.754862,32.8754],"type":"Point"}
}