{
  "type": "Feature",
  "properties": {
    "iso:country":"US",
    "sg:address":"1500 Cascade St",
    "sg:city":"Mesquite",
    "sg:classifiers":[
        {
            "category":"Professional",
            "subcategory":"Management & Consulting",
            "type":"Services"
        }
    ],
    "sg:phone":"+1 972 288 9337",
    "sg:postcode":"75149",
    "sg:province":"TX",
    "wof:name":"Vivian Gomez",
    "wof:placetype":"venue"
},
  "geometry": {"coordinates":[-96.60657500000001,32.780414],"type":"Point"}
}