{
  "type": "Feature",
  "properties": {
    "iso:country":"US",
    "sg:address":"1901 Mississippi St",
    "sg:city":"Baytown",
    "sg:classifiers":[
        {
            "category":"Professional",
            "subcategory":"Business Services",
            "type":"Services"
        }
    ],
    "sg:phone":"+1 281 422 7649",
    "sg:postcode":"77520",
    "sg:province":"TX",
    "wof:name":"Oscars Surplus of Industrial",
    "wof:placetype":"venue"
},
  "geometry": {"coordinates":[-94.995115,29.722475],"type":"Point"}
}