{
  "type": "Feature",
  "properties": {
    "iso:country":"US",
    "sg:address":"802 Old Jacksboro Hwy",
    "sg:city":"Wichita Falls",
    "sg:classifiers":[
        {
            "category":"Building & Trades",
            "subcategory":"Electrical",
            "type":"Services"
        },
        {
            "category":"Building & Trades",
            "subcategory":"Construction",
            "type":"Services"
        }
    ],
    "sg:phone":"+1 940 766 0288",
    "sg:postcode":"76301",
    "sg:province":"TX",
    "sg:tags":[
        "repair",
        "work",
        "electrical",
        "electric",
        "contractor"
    ],
    "wof:name":"Lloyd Thomas Co Inc",
    "wof:placetype":"venue"
},
  "geometry": {"coordinates":[-98.483611,33.899945],"type":"Point"}
}