{
  "type": "Feature",
  "properties": {
    "iso:country":"US",
    "sg:address":"102 County Road 4033",
    "sg:city":"Chilton",
    "sg:classifiers":[
        {
            "category":"Utilities",
            "subcategory":"Water",
            "type":"Services"
        }
    ],
    "sg:phone":"+1 254 546 2919",
    "sg:postcode":"76632",
    "sg:province":"TX",
    "sg:tags":[
        "company-utility",
        "system",
        "supply"
    ],
    "wof:name":"Sudduth Water Supply, Inc.",
    "wof:placetype":"venue"
},
  "geometry": {"coordinates":[-97.07831899999999,31.351186],"type":"Point"}
}