{
  "type": "Feature",
  "properties": {
    "iso:country":"US",
    "sg:address":"4304 Live Oak St",
    "sg:city":"Dallas",
    "sg:classifiers":[
        {
            "category":"Fast Food",
            "type":"Food & Drink"
        },
        {
            "category":"Restaurant",
            "type":"Food & Drink"
        },
        {
            "category":"Professional",
            "type":"Services"
        }
    ],
    "sg:phone":"+1 214 826 8855",
    "sg:postcode":"75204",
    "sg:province":"TX",
    "sg:tags":[
        "delivery",
        "take",
        "pizza"
    ],
    "sg:website":"www.pizzainn.com",
    "wof:name":"Pizza Inn",
    "wof:placetype":"venue"
},
  "geometry": {"coordinates":[-96.77800000000001,32.797798],"type":"Point"}
}