{
  "type": "Feature",
  "properties": {
    "iso:country":"US",
    "sg:address":"432 Houghton Ave",
    "sg:city":"Marlin",
    "sg:classifiers":[
        {
            "category":"Organizations",
            "subcategory":"Religious Organization",
            "type":"Services"
        }
    ],
    "sg:phone":"+1 254 803 2475",
    "sg:postcode":"76661",
    "sg:province":"TX",
    "wof:name":"Grace Lutheran Church",
    "wof:placetype":"venue"
},
  "geometry": {"coordinates":[-96.89063899999999,31.312194],"type":"Point"}
}