{
  "type": "Feature",
  "properties": {
    "iso:country":"US",
    "sg:address":"7919 Reward Pl",
    "sg:city":"Amarillo",
    "sg:classifiers":[
        {
            "category":"Farming",
            "subcategory":"Livestock Farm",
            "type":"Manufacturing & Wholesale Goods"
        }
    ],
    "sg:phone":"+1 806 352 9584",
    "sg:postcode":"79119",
    "sg:province":"TX",
    "sg:tags":[
        "beef",
        "feedlot",
        "cattle"
    ],
    "wof:name":"Double Heart Land & Cattle",
    "wof:placetype":"venue"
},
  "geometry": {"coordinates":[-101.917751,35.128949],"type":"Point"}
}