{
  "type": "Feature",
  "properties": {
    "iso:country":"US",
    "sg:address":"1820 W American Blvd",
    "sg:city":"Muleshoe",
    "sg:classifiers":[
        {
            "category":"Restaurant",
            "type":"Food & Drink"
        }
    ],
    "sg:phone":"+1 806 272 8999",
    "sg:postcode":"79347",
    "sg:province":"TX",
    "sg:tags":[
        "eating"
    ],
    "wof:name":"Tong Sing Chinese Restaurant",
    "wof:placetype":"venue"
},
  "geometry": {"coordinates":[-102.744105,34.2366],"type":"Point"}
}