{
  "type": "Feature",
  "properties": {
    "iso:country":"US",
    "sg:address":"110 Deer Crossing Ln",
    "sg:city":"Wimberley",
    "sg:classifiers":[
        {
            "category":"Education",
            "subcategory":"Vocational School",
            "type":"Public Place"
        }
    ],
    "sg:phone":"+1 512 847 9618",
    "sg:postcode":"78676",
    "sg:province":"TX",
    "sg:tags":[
        "application"
    ],
    "wof:name":"Knee High Aviation",
    "wof:placetype":"venue"
},
  "geometry": {"coordinates":[-98.103702,29.989905],"type":"Point"}
}