{
  "type": "Feature",
  "properties": {
    "iso:country":"US",
    "sg:address":"10001 Woodloch Forest Dr",
    "sg:city":"Spring",
    "sg:classifiers":[
        {
            "category":"Professional",
            "subcategory":"Lawyer & Legal Services",
            "type":"Services"
        }
    ],
    "sg:phone":"+1 281 419 6364",
    "sg:postcode":"77380",
    "sg:province":"TX",
    "sg:tags":[
        "firm",
        "law"
    ],
    "wof:name":"Andrews Kurth LLP",
    "wof:placetype":"venue"
},
  "geometry": {"coordinates":[-95.455918,30.158546],"type":"Point"}
}