{
  "type": "Feature",
  "properties": {
    "iso:country":"US",
    "sg:address":"9920 Highway 290 W",
    "sg:city":"Austin",
    "sg:classifiers":[
        {
            "category":"Food & Beverages",
            "subcategory":"Groceries & Convenience Stores",
            "type":"Retail Goods"
        }
    ],
    "sg:phone":"+1 512 288 5528",
    "sg:postcode":"78736",
    "sg:province":"TX",
    "sg:website":"www.triplepetroleum.com",
    "wof:name":"Triple S Petroleum",
    "wof:placetype":"venue"
},
  "geometry": {"coordinates":[-97.939482,30.233759],"type":"Point"}
}