{
  "type": "Feature",
  "properties": {
    "iso:country":"US",
    "sg:address":"19943 Arbor Creek Dr",
    "sg:city":"Katy",
    "sg:classifiers":[
        {
            "category":"Building & Trades",
            "subcategory":"Construction",
            "type":"Services"
        }
    ],
    "sg:phone":"+1 281 859 5984",
    "sg:postcode":"77449",
    "sg:province":"TX",
    "sg:tags":[
        "floor",
        "laying",
        "contractor"
    ],
    "wof:name":"Kdk Flooring",
    "wof:placetype":"venue"
},
  "geometry": {"coordinates":[-95.72085800000001,29.873306],"type":"Point"}
}