{
  "type": "Feature",
  "properties": {
    "iso:country":"US",
    "sg:address":"1223 N Jefferson Ave",
    "sg:city":"Mount Pleasant",
    "sg:classifiers":[
        {
            "category":"Autos & Motor Vehicles",
            "subcategory":"Auto Supplies",
            "type":"Retail Goods"
        }
    ],
    "sg:phone":"+1 903 572 8705",
    "sg:postcode":"75455",
    "sg:province":"TX",
    "wof:name":"Chavez Tire Shop",
    "wof:placetype":"venue"
},
  "geometry": {"coordinates":[-94.970341,33.169933],"type":"Point"}
}