{
  "type": "Feature",
  "properties": {
    "iso:country":"US",
    "sg:address":"1030 State Hwy 5",
    "sg:city":"Mc Kinney",
    "sg:classifiers":[
        {
            "category":"Professional",
            "subcategory":"Business Services",
            "type":"Services"
        }
    ],
    "sg:phone":"+1 972 562 8110",
    "sg:postcode":"75069",
    "sg:province":"TX",
    "wof:name":"Angle Designs",
    "wof:placetype":"venue"
},
  "geometry": {"coordinates":[-96.63133500000001,33.158831],"type":"Point"}
}