{
  "type": "Feature",
  "properties": {
    "iso:country":"US",
    "sg:address":"2413 Paramount Blvd",
    "sg:city":"Amarillo",
    "sg:classifiers":[
        {
            "category":"Retail",
            "subcategory":"Auto Repair",
            "type":"Services"
        }
    ],
    "sg:phone":"+1 806 355 0521",
    "sg:postcode":"79109",
    "sg:province":"TX",
    "sg:tags":[
        "repairing",
        "automobile"
    ],
    "wof:name":"Pit Stop",
    "wof:placetype":"venue"
},
  "geometry": {"coordinates":[-101.873227,35.188077],"type":"Point"}
}