{
  "type": "Feature",
  "properties": {
    "iso:country":"US",
    "sg:address":"931 N Resler Dr",
    "sg:city":"El Paso",
    "sg:classifiers":[
        {
            "category":"Personal",
            "subcategory":"Beauty Salon",
            "type":"Services"
        }
    ],
    "sg:phone":"+1 915 584 5626",
    "sg:postcode":"79912",
    "sg:province":"TX",
    "sg:tags":[
        "shop"
    ],
    "wof:name":"Cs Nails",
    "wof:placetype":"venue"
},
  "geometry": {"coordinates":[-106.55805599999999,31.860851],"type":"Point"}
}