{
  "type": "Feature",
  "properties": {
    "iso:country":"US",
    "sg:address":"202 S Zang Blvd",
    "sg:city":"Dallas",
    "sg:classifiers":[
        {
            "category":"Professional",
            "subcategory":"Secretarial Services",
            "type":"Services"
        }
    ],
    "sg:phone":"+1 214 943 3384",
    "sg:postcode":"75208",
    "sg:province":"TX",
    "sg:tags":[
        "reporting",
        "court"
    ],
    "wof:name":"General Office & Clerical Svc",
    "wof:placetype":"venue"
},
  "geometry": {"coordinates":[-96.824561,32.743144],"type":"Point"}
}