{
  "type": "Feature",
  "properties": {
    "iso:country":"US",
    "sg:address":"406 N Elm St",
    "sg:city":"Arlington",
    "sg:classifiers":[
        {
            "category":"Manufacturing",
            "subcategory":"Paper Products",
            "type":"Manufacturing & Wholesale Goods"
        }
    ],
    "sg:phone":"+1 817 274 8722",
    "sg:postcode":"76011",
    "sg:province":"TX",
    "sg:tags":[
        "converted",
        "mfg"
    ],
    "wof:name":"Karen Joy Arrington",
    "wof:placetype":"venue"
},
  "geometry": {"coordinates":[-97.10435,32.742691],"type":"Point"}
}