{
  "type": "Feature",
  "properties": {
    "iso:country":"US",
    "sg:address":"117 Ave M",
    "sg:city":"Marble Falls",
    "sg:classifiers":[
        {
            "category":"Social Services",
            "type":"Services"
        }
    ],
    "sg:phone":"+1 830 693 3109",
    "sg:postcode":"78654",
    "sg:province":"TX",
    "sg:tags":[
        "organization",
        "welfare"
    ],
    "wof:name":"Neighborhood Centers Inc",
    "wof:placetype":"venue"
},
  "geometry": {"coordinates":[-98.282827,30.57239],"type":"Point"}
}