{
  "type": "Feature",
  "properties": {
    "iso:country":"US",
    "sg:address":"1700 W Dickinson Blvd",
    "sg:city":"Fort Stockton",
    "sg:classifiers":[
        {
            "category":"Shopping",
            "subcategory":"Department Store",
            "type":"Retail Goods"
        }
    ],
    "sg:phone":"+1 432 336 3389",
    "sg:postcode":"79735",
    "sg:province":"TX",
    "sg:tags":[
        "discount"
    ],
    "wof:name":"Wal-Mart",
    "wof:placetype":"venue"
},
  "geometry": {"coordinates":[-102.896793,30.893925],"type":"Point"}
}