{
  "type": "Feature",
  "properties": {
    "iso:country":"US",
    "sg:address":"1920 Abrams Parkway Suite 087",
    "sg:city":"Dallas",
    "sg:classifiers":[
        {
            "category":"Personal",
            "type":"Services"
        }
    ],
    "sg:phone":"+1 214 382 2710",
    "sg:postcode":"75214",
    "sg:province":"TX",
    "sg:tags":[
        "local"
    ],
    "sg:website":"www.budgetdumpster.com",
    "wof:name":"Budget Dumpster Rental",
    "wof:placetype":"venue"
},
  "geometry": {"coordinates":[-96.752741,32.812404],"type":"Point"}
}