{
  "type": "Feature",
  "properties": {
    "iso:country":"US",
    "sg:address":"4302 Richmond Ave",
    "sg:city":"Houston",
    "sg:classifiers":[
        {
            "category":"Restaurant",
            "type":"Food & Drink"
        }
    ],
    "sg:phone":"+1 713 623 6321",
    "sg:postcode":"77027",
    "sg:province":"TX",
    "sg:tags":[
        "cajun/creole",
        "eating"
    ],
    "sg:website":"www.ragin-cajun.com",
    "wof:name":"Ragin Cajun",
    "wof:placetype":"venue"
},
  "geometry": {"coordinates":[-95.447304,29.7327],"type":"Point"}
}