{
  "type": "Feature",
  "properties": {
    "iso:country":"US",
    "sg:address":"1120 Luke St",
    "sg:city":"Irving",
    "sg:classifiers":[
        {
            "category":"Organizations",
            "subcategory":"Religious Organization",
            "type":"Services"
        }
    ],
    "sg:phone":"+1 972 513 0285",
    "sg:postcode":"75061",
    "sg:province":"TX",
    "wof:name":"Greater Mt Olive Baptst Church",
    "wof:placetype":"venue"
},
  "geometry": {"coordinates":[-96.991347,32.827775],"type":"Point"}
}