{
  "type": "Feature",
  "properties": {
    "iso:country":"US",
    "sg:address":"605 E Cedar St",
    "sg:city":"Angleton",
    "sg:classifiers":[
        {
            "category":"Shopping",
            "subcategory":"Used Merchandise",
            "type":"Retail Goods"
        }
    ],
    "sg:phone":"+1 979 864 3123",
    "sg:postcode":"77515",
    "sg:province":"TX",
    "wof:name":"Harlequin Antiques",
    "wof:placetype":"venue"
},
  "geometry": {"coordinates":[-95.426149,29.169948],"type":"Point"}
}