{
  "type": "Feature",
  "properties": {
    "iso:country":"US",
    "sg:address":"9459 Estate Ln",
    "sg:city":"Dallas",
    "sg:classifiers":[
        {
            "category":"Education",
            "subcategory":"Special Training",
            "type":"Public Place"
        }
    ],
    "sg:phone":"+1 214 349 2596",
    "sg:postcode":"75238",
    "sg:province":"TX",
    "sg:tags":[
        "tutoring"
    ],
    "wof:name":"Lake Highlands Tutoring Co",
    "wof:placetype":"venue"
},
  "geometry": {"coordinates":[-96.72626099999999,32.883829],"type":"Point"}
}