{
  "type": "Feature",
  "properties": {
    "iso:country":"US",
    "sg:address":"14304 Fallen Timber Dr",
    "sg:city":"Austin",
    "sg:classifiers":[
        {
            "category":"Building & Trades",
            "subcategory":"Landscaping Services",
            "type":"Services"
        }
    ],
    "sg:phone":"+1 512 266 6119",
    "sg:postcode":"78734",
    "sg:province":"TX",
    "wof:name":"KWIK Kerb Hill Country Borders",
    "wof:placetype":"venue"
},
  "geometry": {"coordinates":[-97.915052,30.39211],"type":"Point"}
}