{
  "type": "Feature",
  "properties": {
    "iso:country":"US",
    "sg:address":"1003 Bellcrest Dr",
    "sg:city":"Arlington",
    "sg:classifiers":[
        {
            "category":"Professional",
            "type":"Services"
        }
    ],
    "sg:phone":"+1 817 467 1419",
    "sg:postcode":"76002",
    "sg:province":"TX",
    "wof:name":"T Landry Inc",
    "wof:placetype":"venue"
},
  "geometry": {"coordinates":[-97.09343699999999,32.640883],"type":"Point"}
}