{
  "type": "Feature",
  "properties": {
    "iso:country":"US",
    "sg:address":"1500 N Frazier St",
    "sg:city":"Conroe",
    "sg:classifiers":[
        {
            "category":"Organizations",
            "subcategory":"Religious Organization",
            "type":"Services"
        }
    ],
    "sg:phone":"+1 936 756 8988",
    "sg:postcode":"77301",
    "sg:province":"TX",
    "sg:tags":[
        "church"
    ],
    "wof:name":"Conroe Church Of Christ",
    "wof:placetype":"venue"
},
  "geometry": {"coordinates":[-95.46468900000001,30.32433],"type":"Point"}
}