{
  "type": "Feature",
  "properties": {
    "iso:country":"US",
    "sg:address":"17440 Dallas Pkwy",
    "sg:city":"Dallas",
    "sg:classifiers":[
        {
            "category":"Professional",
            "subcategory":"Management & Consulting",
            "type":"Services"
        }
    ],
    "sg:phone":"+1 972 818 4262",
    "sg:postcode":"75287",
    "sg:province":"TX",
    "sg:tags":[
        "marketing",
        "consultant"
    ],
    "wof:name":"Harrah's Marketing Svc",
    "wof:placetype":"venue"
},
  "geometry": {"coordinates":[-96.828064,32.988264],"type":"Point"}
}