{
  "type": "Feature",
  "properties": {
    "iso:country":"US",
    "sg:address":"4398 Preston Rd",
    "sg:city":"Frisco",
    "sg:classifiers":[
        {
            "category":"Communications",
            "type":"Services"
        }
    ],
    "sg:phone":"+1 972 377 2187",
    "sg:postcode":"75034",
    "sg:province":"TX",
    "sg:tags":[
        "carrier",
        "radiotelephone",
        "communications-common"
    ],
    "sg:website":"http://www.americantower.com",
    "wof:name":"American Tower Corp",
    "wof:placetype":"venue"
},
  "geometry": {"coordinates":[-96.80548899999999,33.115977],"type":"Point"}
}