{
  "type": "Feature",
  "properties": {
    "iso:country":"US",
    "sg:address":"302 E Dodge St",
    "sg:city":"Bryan",
    "sg:classifiers":[
        {
            "category":"Retail",
            "subcategory":"Auto Repair",
            "type":"Services"
        }
    ],
    "sg:phone":"+1 979 775 2961",
    "sg:postcode":"77803",
    "sg:province":"TX",
    "sg:tags":[
        "body",
        "automobile",
        "painting",
        "repairing"
    ],
    "wof:name":"Henry Benavides",
    "wof:placetype":"venue"
},
  "geometry": {"coordinates":[-96.36957700000001,30.660069],"type":"Point"}
}