{
  "type": "Feature",
  "properties": {
    "iso:country":"US",
    "sg:address":"8140 Arbor Ave",
    "sg:city":"Fort Worth",
    "sg:classifiers":[
        {
            "category":"Real Estate",
            "subcategory":"Real Estate Agent",
            "type":"Services"
        }
    ],
    "sg:phone":"+1 817 244 0463",
    "sg:postcode":"76116",
    "sg:province":"TX",
    "wof:name":"Barefield James E Jr Etux",
    "wof:placetype":"venue"
},
  "geometry": {"coordinates":[-97.45612199999999,32.727598],"type":"Point"}
}