{
  "type": "Feature",
  "properties": {
    "iso:country":"US",
    "sg:address":"1402 Saint Francis Ln",
    "sg:city":"Flower Mound",
    "sg:classifiers":[
        {
            "category":"Banks & Credit Unions",
            "subcategory":"Investment Brokerage",
            "type":"Services"
        },
        {
            "category":"Professional",
            "subcategory":"Management & Consulting",
            "type":"Services"
        }
    ],
    "sg:phone":"+1 972 691 9023",
    "sg:postcode":"75028",
    "sg:province":"TX",
    "sg:website":"www.techsyon.com",
    "wof:name":"Techsyon Group LLC",
    "wof:placetype":"venue"
},
  "geometry": {"coordinates":[-97.047488,33.005475],"type":"Point"}
}