{
  "type": "Feature",
  "properties": {
    "iso:country":"US",
    "sg:address":"24441 FM 2090",
    "sg:city":"Splendora",
    "sg:classifiers":[
        {
            "category":"Autos & Motor Vehicles",
            "subcategory":"Automobile Sales",
            "type":"Retail Goods"
        },
        {
            "category":"Retail",
            "subcategory":"Auto Repair",
            "type":"Services"
        }
    ],
    "sg:phone":"+1 281 689 1313",
    "sg:postcode":"77372",
    "sg:province":"TX",
    "sg:tags":[
        "car",
        "dealer",
        "general"
    ],
    "wof:name":"Wetzel's Automotive",
    "wof:placetype":"venue"
},
  "geometry": {"coordinates":[-95.186797,30.243971],"type":"Point"}
}