{
  "type": "Feature",
  "properties": {
    "iso:country":"US",
    "sg:address":"250 Guilford Forge",
    "sg:city":"Universal City",
    "sg:classifiers":[
        {
            "category":"Health Services",
            "subcategory":"Nursing And Care Facility",
            "type":"Services"
        },
        {
            "category":"Social Services",
            "subcategory":"Adult Care",
            "type":"Services"
        }
    ],
    "sg:phone":"+1 210 658 0412",
    "sg:postcode":"78148",
    "sg:province":"TX",
    "sg:tags":[
        "disabled",
        "retardation",
        "skilled",
        "dev",
        "home"
    ],
    "wof:name":"Texas Home Management Inc",
    "wof:placetype":"venue"
},
  "geometry": {"coordinates":[-98.321068,29.534218],"type":"Point"}
}