{
  "type": "Feature",
  "properties": {
    "iso:country":"US",
    "sg:address":"907 Walters Dr",
    "sg:city":"Cedar Hill",
    "sg:classifiers":[
        {
            "category":"Shopping",
            "subcategory":"Books",
            "type":"Retail Goods"
        }
    ],
    "sg:phone":"+1 972 293 2963",
    "sg:postcode":"75104",
    "sg:province":"TX",
    "sg:tags":[
        "dealer"
    ],
    "wof:name":"Book Of Genesis Inc",
    "wof:placetype":"venue"
},
  "geometry": {"coordinates":[-96.927087,32.586046],"type":"Point"}
}