{
  "type": "Feature",
  "properties": {
    "iso:country":"US",
    "sg:address":"8000 Research Forest Dr",
    "sg:city":"Spring",
    "sg:classifiers":[
        {
            "category":"Restaurant",
            "type":"Food & Drink"
        }
    ],
    "sg:menulink":"http://www.allmenus.com/tx/southeast-montgomery/30427-ricos/menu/",
    "sg:phone":"+1 281 465 4820",
    "sg:postcode":"77382",
    "sg:province":"TX",
    "sg:tags":[
        "mexican"
    ],
    "wof:name":"Rico's",
    "wof:placetype":"venue"
},
  "geometry": {"coordinates":[-95.527629,30.210076],"type":"Point"}
}