{
  "type": "Feature",
  "properties": {
    "iso:country":"US",
    "sg:address":"1249 Commerce Dr",
    "sg:city":"Richardson",
    "sg:classifiers":[
        {
            "category":"Shopping",
            "type":"Retail Goods"
        }
    ],
    "sg:phone":"+1 972 480 9998",
    "sg:postcode":"75081",
    "sg:province":"TX",
    "sg:tags":[
        "equipment",
        "telephone",
        "supply"
    ],
    "wof:name":"American Digicom Corp",
    "wof:placetype":"venue"
},
  "geometry": {"coordinates":[-96.703923,32.966008],"type":"Point"}
}