{
  "type": "Feature",
  "properties": {
    "iso:country":"US",
    "sg:address":"10744 Bramblecrest Dr",
    "sg:city":"Austin",
    "sg:classifiers":[
        {
            "category":"Banks & Credit Unions",
            "subcategory":"Financial Services",
            "type":"Services"
        }
    ],
    "sg:phone":"+1 512 250 9645",
    "sg:postcode":"78726",
    "sg:province":"TX",
    "sg:tags":[
        "investor"
    ],
    "wof:name":"Investing Insights Inc",
    "wof:placetype":"venue"
},
  "geometry": {"coordinates":[-97.815752,30.435253],"type":"Point"}
}