{
  "type": "Feature",
  "properties": {
    "iso:country":"US",
    "sg:address":"2727 Goliad Rd",
    "sg:city":"San Antonio",
    "sg:classifiers":[
        {
            "category":"Restaurant",
            "type":"Food & Drink"
        }
    ],
    "sg:phone":"+1 210 337 7168",
    "sg:postcode":"78223",
    "sg:province":"TX",
    "sg:tags":[
        "chinese"
    ],
    "wof:name":"Lotus Chinese Restaurant The",
    "wof:placetype":"venue"
},
  "geometry": {"coordinates":[-98.433449,29.355779],"type":"Point"}
}