{
  "type": "Feature",
  "properties": {
    "iso:country":"US",
    "sg:address":"8 Northcrest Cir",
    "sg:city":"Rockwall",
    "sg:classifiers":[
        {
            "category":"Professional",
            "subcategory":"Engineering",
            "type":"Services"
        }
    ],
    "sg:phone":"+1 972 772 9500",
    "sg:postcode":"75087",
    "sg:province":"TX",
    "sg:tags":[
        "engineer"
    ],
    "sg:website":"www.oldenassociates.com",
    "wof:name":"Olden Associates",
    "wof:placetype":"venue"
},
  "geometry": {"coordinates":[-96.42187,32.960195],"type":"Point"}
}