{
  "type": "Feature",
  "properties": {
    "iso:country":"US",
    "sg:address":"1102 Longfellow Dr",
    "sg:city":"Beaumont",
    "sg:classifiers":[
        {
            "category":"Insurance",
            "subcategory":"Insurance Agent",
            "type":"Services"
        }
    ],
    "sg:phone":"+1 409 898 8565",
    "sg:postcode":"77706",
    "sg:province":"TX",
    "wof:name":"Insurance Source",
    "wof:placetype":"venue"
},
  "geometry": {"coordinates":[-94.13699099999999,30.090437],"type":"Point"}
}