{
  "type": "Feature",
  "properties": {
    "iso:country":"US",
    "sg:address":"501 Golder Ave",
    "sg:city":"Odessa",
    "sg:classifiers":[
        {
            "category":"Health Services",
            "subcategory":"Medical Lab",
            "type":"Services"
        }
    ],
    "sg:phone":"+1 432 333 8060",
    "sg:postcode":"79761",
    "sg:province":"TX",
    "sg:tags":[
        "laboratory"
    ],
    "wof:name":"Diagnostic Vascular Lab-West",
    "wof:placetype":"venue"
},
  "geometry": {"coordinates":[-102.376516,31.846003],"type":"Point"}
}