{
  "type": "Feature",
  "properties": {
    "iso:country":"US",
    "sg:address":"111 S Garland Ave",
    "sg:city":"Garland",
    "sg:classifiers":[
        {
            "category":"Professional",
            "subcategory":"Lawyer & Legal Services",
            "type":"Services"
        }
    ],
    "sg:phone":"+1 972 494 0706",
    "sg:postcode":"75040",
    "sg:province":"TX",
    "wof:name":"Law Office Of E A Weinberg",
    "wof:placetype":"venue"
},
  "geometry": {"coordinates":[-96.648303,32.912239],"type":"Point"}
}