{
  "type": "Feature",
  "properties": {
    "iso:country":"US",
    "sg:address":"2115 Ave F",
    "sg:city":"Del Rio",
    "sg:classifiers":[
        {
            "category":"Travel",
            "subcategory":"Hotels & Motels",
            "type":"Entertainment"
        }
    ],
    "sg:phone":"+1 830 774 2115",
    "sg:postcode":"78840",
    "sg:province":"TX",
    "sg:tags":[
        "operation"
    ],
    "wof:name":"Motel 6",
    "wof:placetype":"venue"
},
  "geometry": {"coordinates":[-100.905219,29.387952],"type":"Point"}
}