{
  "type": "Feature",
  "properties": {
    "iso:country":"US",
    "sg:address":"7208 McNeil Dr",
    "sg:city":"Austin",
    "sg:classifiers":[
        {
            "category":"Personal",
            "type":"Services"
        },
        {
            "category":"Home & Garden",
            "subcategory":"Carpets & Floor Coverings",
            "type":"Retail Goods"
        }
    ],
    "sg:phone":"+1 512 279 7777",
    "sg:postcode":"78729",
    "sg:province":"TX",
    "sg:tags":[
        "mattress"
    ],
    "sg:website":"www.discountmattressplus.com",
    "wof:name":"Austin Discount Mattress Plus",
    "wof:placetype":"venue"
},
  "geometry": {"coordinates":[-97.76497000000001,30.435834],"type":"Point"}
}