{
  "type": "Feature",
  "properties": {
    "iso:country":"US",
    "sg:address":"5502 Maplegate Dr",
    "sg:city":"Spring",
    "sg:classifiers":[
        {
            "category":"Professional",
            "subcategory":"Business Services",
            "type":"Services"
        }
    ],
    "sg:phone":"+1 281 209 9507",
    "sg:postcode":"77373",
    "sg:province":"TX",
    "wof:name":"Edge Express",
    "wof:placetype":"venue"
},
  "geometry": {"coordinates":[-95.34705599999999,30.041058],"type":"Point"}
}