{
  "type": "Feature",
  "properties": {
    "iso:country":"US",
    "sg:address":"8229 Shoal Creek Blvd",
    "sg:city":"Austin",
    "sg:classifiers":[
        {
            "category":"Health Services",
            "subcategory":"Doctor",
            "type":"Services"
        }
    ],
    "sg:phone":"+1 512 478 4653",
    "sg:postcode":"78757",
    "sg:province":"TX",
    "sg:tags":[
        "surgeon",
        "oral"
    ],
    "wof:name":"James T Cordera, DDS",
    "wof:placetype":"venue"
},
  "geometry": {"coordinates":[-97.737573,30.367137],"type":"Point"}
}