{
  "type": "Feature",
  "properties": {
    "iso:country":"US",
    "sg:address":"1021 Shady Oaks St",
    "sg:city":"Giddings",
    "sg:classifiers":[
        {
            "category":"Building & Trades",
            "subcategory":"Construction",
            "type":"Services"
        }
    ],
    "sg:phone":"+1 979 542 7758",
    "sg:postcode":"78942",
    "sg:province":"TX",
    "sg:tags":[
        "general"
    ],
    "wof:name":"Don Eddie Construction",
    "wof:placetype":"venue"
},
  "geometry": {"coordinates":[-96.959013,30.188052],"type":"Point"}
}