{
  "type": "Feature",
  "properties": {
    "iso:country":"US",
    "sg:address":"8961 3rd St",
    "sg:city":"Frisco",
    "sg:classifiers":[
        {
            "category":"Retail",
            "subcategory":"Auto Repair",
            "type":"Services"
        }
    ],
    "sg:phone":"+1 972 335 9099",
    "sg:postcode":"75034",
    "sg:province":"TX",
    "sg:tags":[
        "repairing",
        "automobile"
    ],
    "wof:name":"Kustom Korner Automobile",
    "wof:placetype":"venue"
},
  "geometry": {"coordinates":[-96.82619800000001,33.151546],"type":"Point"}
}