{
  "type": "Feature",
  "properties": {
    "iso:country":"US",
    "sg:address":"7761 Raintree Way",
    "sg:city":"Frisco",
    "sg:classifiers":[
        {
            "category":"Health Services",
            "subcategory":"Clinic",
            "type":"Services"
        }
    ],
    "sg:phone":"+1 972 668 8242",
    "sg:postcode":"75034",
    "sg:province":"TX",
    "sg:tags":[
        "hospice",
        "home"
    ],
    "sg:website":"http://www.familycaresrv.com",
    "wof:name":"Family Care Svc Inc",
    "wof:placetype":"venue"
},
  "geometry": {"coordinates":[-96.815978,33.165173],"type":"Point"}
}