{
  "type": "Feature",
  "properties": {
    "iso:country":"US",
    "sg:address":"9428 Abbey Rd",
    "sg:city":"Irving",
    "sg:classifiers":[
        {
            "category":"Professional",
            "type":"Services"
        }
    ],
    "sg:phone":"+1 972 402 0133",
    "sg:postcode":"75063",
    "sg:province":"TX",
    "sg:tags":[
        "establishment"
    ],
    "wof:name":"Expressions Of Design",
    "wof:placetype":"venue"
},
  "geometry": {"coordinates":[-96.960313,32.93382],"type":"Point"}
}