{
  "type": "Feature",
  "properties": {
    "iso:country":"US",
    "sg:address":"4838 Holly Ave",
    "sg:city":"Pasadena",
    "sg:classifiers":[
        {
            "category":"Building & Trades",
            "subcategory":"Construction",
            "type":"Services"
        }
    ],
    "sg:phone":"+1 281 487 0221",
    "sg:postcode":"77503",
    "sg:province":"TX",
    "sg:tags":[
        "contractor"
    ],
    "wof:name":"Brocks Pools",
    "wof:placetype":"venue"
},
  "geometry": {"coordinates":[-95.168481,29.66852],"type":"Point"}
}