{
  "type": "Feature",
  "properties": {
    "iso:country":"US",
    "sg:address":"445 Walnut St",
    "sg:city":"Richardson",
    "sg:classifiers":[
        {
            "category":"Health Services",
            "subcategory":"Chiropractor",
            "type":"Services"
        }
    ],
    "sg:phone":"+1 972 644 4744",
    "sg:postcode":"75069",
    "sg:province":"TX",
    "wof:name":"Richland Chiropractic Clinic",
    "wof:placetype":"venue"
},
  "geometry": {"coordinates":[-96.612441,33.192223],"type":"Point"}
}