{
  "type": "Feature",
  "properties": {
    "iso:country":"US",
    "sg:address":"2218 S 14th St",
    "sg:city":"Abilene",
    "sg:classifiers":[
        {
            "category":"Recreation",
            "type":"Entertainment"
        }
    ],
    "sg:phone":"+1 325 676 2424",
    "sg:postcode":"79605",
    "sg:province":"TX",
    "sg:tags":[
        "martial",
        "arts",
        "instruction"
    ],
    "wof:name":"Lim's Tae KWON Do",
    "wof:placetype":"venue"
},
  "geometry": {"coordinates":[-99.749377,32.432224],"type":"Point"}
}