{
  "type": "Feature",
  "properties": {
    "iso:country":"US",
    "sg:address":"342 Nora Miller Rd",
    "sg:city":"Abilene",
    "sg:classifiers":[
        {
            "category":"Building & Trades",
            "subcategory":"Construction",
            "type":"Services"
        }
    ],
    "sg:phone":"+1 325 529 5923",
    "sg:postcode":"79602",
    "sg:province":"TX",
    "sg:tags":[
        "home",
        "builder"
    ],
    "wof:name":"Westex Custom Homes",
    "wof:placetype":"venue"
},
  "geometry": {"coordinates":[-99.67405599999999,32.334056],"type":"Point"}
}