{
  "type": "Feature",
  "properties": {
    "iso:country":"US",
    "sg:address":"9930 Hempstead Rd",
    "sg:city":"Houston",
    "sg:classifiers":[
        {
            "category":"Restaurant",
            "type":"Food & Drink"
        }
    ],
    "sg:phone":"+1 713 680 9172",
    "sg:postcode":"77092",
    "sg:province":"TX",
    "wof:name":"Chick-Fil-A Restaurants of",
    "wof:placetype":"venue"
},
  "geometry": {"coordinates":[-95.459,29.801001],"type":"Point"}
}