{
  "type": "Feature",
  "properties": {
    "iso:country":"US",
    "sg:address":"2792 County Road 4342",
    "sg:city":"Bivins",
    "sg:classifiers":[
        {
            "category":"Place Of Worship",
            "subcategory":"Church",
            "type":"Public Place"
        },
        {
            "category":"Place Of Worship",
            "type":"Public Place"
        }
    ],
    "sg:phone":"+1 903 796 1768",
    "sg:postcode":"75555",
    "sg:province":"TX",
    "sg:tags":[
        "churches-baptist-general",
        "churches-baptist"
    ],
    "wof:name":"St. Paul Baptist Church",
    "wof:placetype":"venue"
},
  "geometry": {"coordinates":[-94.155934,32.976504],"type":"Point"}
}