{
  "type": "Feature",
  "properties": {
    "iso:country":"US",
    "sg:address":"37034 Whipstock Rd",
    "sg:city":"Magnolia",
    "sg:classifiers":[
        {
            "category":"Shopping",
            "subcategory":"Gifts & Souvenirs",
            "type":"Retail Goods"
        }
    ],
    "sg:phone":"+1 281 356 6981",
    "sg:postcode":"77354",
    "sg:province":"TX",
    "wof:name":"Ceramic Creations",
    "wof:placetype":"venue"
},
  "geometry": {"coordinates":[-95.701519,30.188058],"type":"Point"}
}