{
  "type": "Feature",
  "properties": {
    "iso:country":"US",
    "sg:address":"9831 Deanwood St",
    "sg:city":"Houston",
    "sg:classifiers":[
        {
            "category":"Professional",
            "subcategory":"Business Services",
            "type":"Services"
        }
    ],
    "sg:phone":"+1 713 466 8850",
    "sg:postcode":"77040",
    "sg:province":"TX",
    "wof:name":"Terry Witson or Doris",
    "wof:placetype":"venue"
},
  "geometry": {"coordinates":[-95.501254,29.883667],"type":"Point"}
}