{
  "type": "Feature",
  "properties": {
    "iso:country":"US",
    "sg:address":"409 S Main St",
    "sg:city":"Copperas Cove",
    "sg:classifiers":[
        {
            "category":"Professional",
            "subcategory":"Accounting & Tax Preparation",
            "type":"Services"
        }
    ],
    "sg:phone":"+1 254 547 8451",
    "sg:postcode":"76522",
    "sg:province":"TX",
    "sg:tags":[
        "return",
        "filing"
    ],
    "wof:name":"Jackson Hewitt Tax Svc",
    "wof:placetype":"venue"
},
  "geometry": {"coordinates":[-97.903695,31.119957],"type":"Point"}
}