{
  "type": "Feature",
  "properties": {
    "iso:country":"US",
    "sg:address":"19075 I- 45 S",
    "sg:city":"Conroe",
    "sg:classifiers":[
        {
            "category":"Shopping",
            "subcategory":"Hobbies, Toys, & Games",
            "type":"Retail Goods"
        }
    ],
    "sg:phone":"+1 936 271 0011",
    "sg:postcode":"77385",
    "sg:province":"TX",
    "sg:tags":[
        "craft",
        "supply"
    ],
    "wof:name":"Michaels Arts & Crafts Store",
    "wof:placetype":"venue"
},
  "geometry": {"coordinates":[-95.451649,30.18015],"type":"Point"}
}