{
  "type": "Feature",
  "properties": {
    "iso:country":"US",
    "sg:address":"1325 Teasley Ln",
    "sg:city":"Denton",
    "sg:classifiers":[
        {
            "category":"Manufacturing",
            "subcategory":"Tools & Machinery",
            "type":"Manufacturing & Wholesale Goods"
        },
        {
            "category":"Wholesale",
            "subcategory":"Machinery & Supplies",
            "type":"Manufacturing & Wholesale Goods"
        }
    ],
    "sg:phone":"+1 940 383 1483",
    "sg:postcode":"76205",
    "sg:province":"TX",
    "sg:tags":[
        "tools-wholesale",
        "industrial",
        "manufacturer",
        "equipment"
    ],
    "sg:website":"http://www.dentonbolt.com",
    "wof:name":"Dbc Industrial Supply",
    "wof:placetype":"venue"
},
  "geometry": {"coordinates":[-97.122299,33.199076],"type":"Point"}
}