{
  "type": "Feature",
  "properties": {
    "iso:country":"US",
    "sg:address":"11919 Silver Canyon Ln",
    "sg:city":"Houston",
    "sg:classifiers":[
        {
            "category":"Professional",
            "subcategory":"Business Services",
            "type":"Services"
        }
    ],
    "sg:phone":"+1 281 537 6738",
    "sg:postcode":"77067",
    "sg:province":"TX",
    "wof:name":"Billingslea Group",
    "wof:placetype":"venue"
},
  "geometry": {"coordinates":[-95.47200100000001,29.957888],"type":"Point"}
}