{
  "type": "Feature",
  "properties": {
    "iso:country":"US",
    "sg:address":"624 N Main St",
    "sg:city":"Boerne",
    "sg:classifiers":[
        {
            "category":"Professional",
            "subcategory":"Management & Consulting",
            "type":"Services"
        }
    ],
    "sg:phone":"+1 830 248 1095",
    "sg:postcode":"78006",
    "sg:province":"TX",
    "sg:tags":[
        "fuel"
    ],
    "wof:name":"Employer Liability Mgmt Inc",
    "wof:placetype":"venue"
},
  "geometry": {"coordinates":[-98.73468200000001,29.799261],"type":"Point"}
}