{
  "type": "Feature",
  "properties": {
    "iso:country":"US",
    "sg:address":"3448 Sherwood Way",
    "sg:city":"San Angelo",
    "sg:classifiers":[
        {
            "category":"Retail",
            "subcategory":"Repair Shop",
            "type":"Services"
        }
    ],
    "sg:phone":"+1 325 949 2011",
    "sg:postcode":"76901",
    "sg:province":"TX",
    "sg:tags":[
        "upholsterer"
    ],
    "wof:name":"Truck Outfitters & Trim Shop",
    "wof:placetype":"venue"
},
  "geometry": {"coordinates":[-100.480552,31.445069],"type":"Point"}
}