{
  "type": "Feature",
  "properties": {
    "iso:country":"US",
    "sg:address":"9839 Childress Dr",
    "sg:city":"Austin",
    "sg:classifiers":[
        {
            "category":"Shopping",
            "subcategory":"Stationery & Office Supplies",
            "type":"Retail Goods"
        }
    ],
    "sg:phone":"+1 512 837 8122",
    "sg:postcode":"78753",
    "sg:province":"TX",
    "sg:tags":[
        "stationer"
    ],
    "wof:name":"Expressive Images",
    "wof:placetype":"venue"
},
  "geometry": {"coordinates":[-97.67610500000001,30.359244],"type":"Point"}
}