{
  "type": "Feature",
  "properties": {
    "iso:country":"US",
    "sg:address":"25025 I- 45",
    "sg:city":"Spring",
    "sg:classifiers":[
        {
            "category":"Banks & Credit Unions",
            "subcategory":"Bank",
            "type":"Services"
        }
    ],
    "sg:phone":"+1 281 292 3881",
    "sg:postcode":"77380",
    "sg:province":"TX",
    "sg:tags":[
        "financing"
    ],
    "wof:name":"Extend-A-Pay",
    "wof:placetype":"venue"
},
  "geometry": {"coordinates":[-95.443252,30.124603],"type":"Point"}
}