{
  "type": "Feature",
  "properties": {
    "iso:country":"US",
    "sg:address":"523 W Water St",
    "sg:city":"Kerrville",
    "sg:classifiers":[
        {
            "category":"Real Estate",
            "subcategory":"Real Estate Agent",
            "type":"Services"
        }
    ],
    "sg:phone":"+1 830 257 9001",
    "sg:postcode":"78028",
    "sg:province":"TX",
    "sg:tags":[
        "management"
    ],
    "wof:name":"Olson Associates Inc",
    "wof:placetype":"venue"
},
  "geometry": {"coordinates":[-99.153654,30.057311],"type":"Point"}
}