{
  "type": "Feature",
  "properties": {
    "iso:country":"US",
    "sg:address":"131 Huggins Ln",
    "sg:city":"Denison",
    "sg:classifiers":[
        {
            "category":"Home & Garden",
            "subcategory":"Home Furnishings",
            "type":"Retail Goods"
        }
    ],
    "sg:phone":"+1 903 463 6910",
    "sg:postcode":"75020",
    "sg:province":"TX",
    "sg:tags":[
        "housewares"
    ],
    "wof:name":"Saladmaster B & B Cookware",
    "wof:placetype":"venue"
},
  "geometry": {"coordinates":[-96.57437400000001,33.712257],"type":"Point"}
}