{
  "type": "Feature",
  "properties": {
    "iso:country":"US",
    "sg:address":"217 Wind Ridge Cove",
    "sg:city":"Georgetown",
    "sg:classifiers":[
        {
            "category":"Professional",
            "subcategory":"Employment Agencies",
            "type":"Services"
        }
    ],
    "sg:phone":"+1 512 819 9722",
    "sg:postcode":"78628",
    "sg:province":"TX",
    "sg:tags":[
        "help",
        "supply"
    ],
    "wof:name":"Galt Sheryl",
    "wof:placetype":"venue"
},
  "geometry": {"coordinates":[-97.772553,30.654748],"type":"Point"}
}