{
  "type": "Feature",
  "properties": {
    "iso:country":"US",
    "sg:address":"2139 FM 1960 W",
    "sg:city":"Houston",
    "sg:classifiers":[
        {
            "category":"Shopping",
            "subcategory":"Shoes",
            "type":"Retail Goods"
        }
    ],
    "sg:phone":"+1 281 580 1737",
    "sg:postcode":"77090",
    "sg:province":"TX",
    "sg:tags":[
        "shoe",
        "store"
    ],
    "wof:name":"Red Wing Shoe Store",
    "wof:placetype":"venue"
},
  "geometry": {"coordinates":[-95.459081,30.009601],"type":"Point"}
}