{
  "type": "Feature",
  "properties": {
    "iso:country":"US",
    "sg:address":"2114 Overview Ln",
    "sg:city":"Garland",
    "sg:classifiers":[
        {
            "category":"Building & Trades",
            "subcategory":"Construction",
            "type":"Services"
        }
    ],
    "sg:phone":"+1 972 414 8777",
    "sg:postcode":"75044",
    "sg:province":"TX",
    "sg:tags":[
        "house"
    ],
    "wof:name":"Renovations By Scott",
    "wof:placetype":"venue"
},
  "geometry": {"coordinates":[-96.67662199999999,32.933098],"type":"Point"}
}