{
  "type": "Feature",
  "properties": {
    "iso:country":"US",
    "sg:address":"5116 Northeast Pkwy",
    "sg:city":"Fort Worth",
    "sg:classifiers":[
        {
            "category":"Professional",
            "subcategory":"Advertising",
            "type":"Services"
        }
    ],
    "sg:phone":"+1 817 626 9660",
    "sg:postcode":"76106",
    "sg:province":"TX",
    "sg:tags":[
        "mailing",
        "shipping"
    ],
    "sg:website":"www.mail-presort.com",
    "wof:name":"Mail Presort",
    "wof:placetype":"venue"
},
  "geometry": {"coordinates":[-97.315718,32.831182],"type":"Point"}
}