{
  "type": "Feature",
  "properties": {
    "iso:country":"US",
    "sg:address":"9501 Forest Ln",
    "sg:city":"Dallas",
    "sg:classifiers":[
        {
            "category":"Restaurant",
            "type":"Food & Drink"
        }
    ],
    "sg:menulink":"http://www.allmenus.com/tx/northeast/192344-wendys/menu/",
    "sg:phone":"+1 972 783 4839",
    "sg:postcode":"75243",
    "sg:province":"TX",
    "sg:tags":[
        "burger",
        "american",
        "soup"
    ],
    "wof:name":"Wendy's",
    "wof:placetype":"venue"
},
  "geometry": {"coordinates":[-96.73119800000001,32.909232],"type":"Point"}
}