{
  "type": "Feature",
  "properties": {
    "iso:country":"US",
    "sg:address":"5175 Westheimer Rd",
    "sg:city":"Houston",
    "sg:classifiers":[
        {
            "category":"Personal",
            "subcategory":"Beauty Salon",
            "type":"Services"
        }
    ],
    "sg:phone":"+1 832 404 8980",
    "sg:postcode":"77056",
    "sg:province":"TX",
    "sg:tags":[
        "hair",
        "eyelash"
    ],
    "sg:website":"www.krinalee.com",
    "wof:name":"KrinaLee Studio",
    "wof:placetype":"venue"
},
  "geometry": {"coordinates":[-95.466016,29.740486],"type":"Point"}
}