{
  "type": "Feature",
  "properties": {
    "iso:country":"US",
    "sg:address":"2530 Pecan Blvd",
    "sg:city":"Mcallen",
    "sg:classifiers":[
        {
            "category":"Personal",
            "subcategory":"Beauty Salon",
            "type":"Services"
        }
    ],
    "sg:phone":"+1 956 631 1781",
    "sg:postcode":"78501",
    "sg:province":"TX",
    "wof:name":"Jasmine",
    "wof:placetype":"venue"
},
  "geometry": {"coordinates":[-98.247241,26.219059],"type":"Point"}
}