{
  "type": "Feature",
  "properties": {
    "iso:country":"US",
    "sg:address":"508 S Van Buren St",
    "sg:city":"Henderson",
    "sg:classifiers":[
        {
            "category":"Autos & Motor Vehicles",
            "subcategory":"Fuel & Gas Station",
            "type":"Retail Goods"
        }
    ],
    "sg:phone":"+1 903 657 0061",
    "sg:postcode":"75654",
    "sg:province":"TX",
    "sg:tags":[
        "oil"
    ],
    "wof:name":"Pump & Save",
    "wof:placetype":"venue"
},
  "geometry": {"coordinates":[-94.80116700000001,32.147548],"type":"Point"}
}