{
  "type": "Feature",
  "properties": {
    "iso:country":"US",
    "sg:address":"280 E Fawn Dr",
    "sg:city":"Buchanan Dam",
    "sg:classifiers":[
        {
            "category":"Food & Beverages",
            "subcategory":"Candy",
            "type":"Retail Goods"
        }
    ],
    "sg:phone":"+1 512 793 2515",
    "sg:postcode":"78609",
    "sg:province":"TX",
    "sg:tags":[
        "confectionery"
    ],
    "wof:name":"Sweet Blossum's",
    "wof:placetype":"venue"
},
  "geometry": {"coordinates":[-98.423996,30.74114],"type":"Point"}
}