{
  "type": "Feature",
  "properties": {
    "iso:country":"US",
    "sg:address":"7316 Cielo Vista Dr",
    "sg:city":"El Paso",
    "sg:classifiers":[
        {
            "category":"Professional",
            "subcategory":"Detective & Security Services",
            "type":"Services"
        }
    ],
    "sg:phone":"+1 915 778 4121",
    "sg:postcode":"79925",
    "sg:province":"TX",
    "sg:tags":[
        "guard"
    ],
    "wof:name":"Hector Bernal",
    "wof:placetype":"venue"
},
  "geometry": {"coordinates":[-106.389732,31.787373],"type":"Point"}
}