{
  "type": "Feature",
  "properties": {
    "iso:country":"US",
    "sg:address":"2603 Oak Lawn Ave",
    "sg:city":"Dallas",
    "sg:classifiers":[
        {
            "category":"Building & Trades",
            "subcategory":"Locksmith",
            "type":"Services"
        }
    ],
    "sg:phone":"+1 214 635 4701",
    "sg:postcode":"75219",
    "sg:province":"TX",
    "sg:tags":[
        "key"
    ],
    "wof:name":"City Locksmith Dallas TX",
    "wof:placetype":"venue"
},
  "geometry": {"coordinates":[-96.81327899999999,32.80548],"type":"Point"}
}