{
  "type": "Feature",
  "properties": {
    "iso:country":"US",
    "sg:address":"5401 Pleasant Valley Rd",
    "sg:city":"Wylie",
    "sg:classifiers":[
        {
            "category":"Building & Trades",
            "subcategory":"Construction",
            "type":"Services"
        }
    ],
    "sg:phone":"+1 214 607 4858",
    "sg:postcode":"75048",
    "sg:province":"TX",
    "sg:tags":[
        "contractor"
    ],
    "wof:name":"Eagle Contracting",
    "wof:placetype":"venue"
},
  "geometry": {"coordinates":[-96.54623599999999,32.972159],"type":"Point"}
}