{
  "type": "Feature",
  "properties": {
    "iso:country":"US",
    "sg:address":"14644 Highway 3",
    "sg:city":"Webster",
    "sg:classifiers":[
        {
            "category":"Retail",
            "subcategory":"Laundry & Dry Cleaning",
            "type":"Services"
        }
    ],
    "sg:phone":"+1 281 486 0520",
    "sg:postcode":"77598",
    "sg:province":"TX",
    "sg:tags":[
        "cleaner",
        "rug",
        "carpet"
    ],
    "wof:name":"Pro Care",
    "wof:placetype":"venue"
},
  "geometry": {"coordinates":[-95.15131100000001,29.573234],"type":"Point"}
}