{
  "type": "Feature",
  "properties": {
    "iso:country":"US",
    "sg:address":"1826 Kramer Ln",
    "sg:city":"Austin",
    "sg:classifiers":[
        {
            "category":"Wholesale",
            "subcategory":"Electrical",
            "type":"Manufacturing & Wholesale Goods"
        }
    ],
    "sg:phone":"+1 512 929 1880",
    "sg:postcode":"78758",
    "sg:province":"TX",
    "sg:tags":[
        "semiconductor",
        "device"
    ],
    "wof:name":"Suss Microtech",
    "wof:placetype":"venue"
},
  "geometry": {"coordinates":[-97.706478,30.386832],"type":"Point"}
}