{
  "type": "Feature",
  "properties": {
    "iso:country":"US",
    "sg:address":"535 Scenic Valley Rd",
    "sg:city":"Kerrville",
    "sg:classifiers":[
        {
            "category":"Professional",
            "subcategory":"Business Services",
            "type":"Services"
        }
    ],
    "sg:phone":"+1 830 792 5538",
    "sg:postcode":"78028",
    "sg:province":"TX",
    "sg:tags":[
        "consultant",
        "coach"
    ],
    "sg:website":"http://www.channelsupplies.com",
    "wof:name":"Channel Supplies",
    "wof:placetype":"venue"
},
  "geometry": {"coordinates":[-99.105592,30.106523],"type":"Point"}
}