{
  "type": "Feature",
  "properties": {
    "iso:country":"US",
    "sg:address":"600 Travis St",
    "sg:city":"Houston",
    "sg:classifiers":[
        {
            "category":"Professional",
            "subcategory":"Lawyer & Legal Services",
            "type":"Services"
        }
    ],
    "sg:phone":"+1 713 229 8733",
    "sg:postcode":"77002",
    "sg:province":"TX",
    "sg:tags":[
        "attorney"
    ],
    "wof:name":"Burke Kristen T",
    "wof:placetype":"venue"
},
  "geometry": {"coordinates":[-95.36402099999999,29.759725],"type":"Point"}
}