{
  "type": "Feature",
  "properties": {
    "iso:country":"US",
    "sg:address":"606 Cheetah Trl",
    "sg:city":"Harker Heights",
    "sg:classifiers":[
        {
            "category":"Real Estate",
            "subcategory":"Real Estate Operator",
            "type":"Services"
        }
    ],
    "sg:phone":"+1 254 698 3656",
    "sg:postcode":"76548",
    "sg:province":"TX",
    "sg:tags":[
        "building",
        "apartment"
    ],
    "wof:name":"N Ellis Management LLC",
    "wof:placetype":"venue"
},
  "geometry": {"coordinates":[-97.65583700000001,31.070331],"type":"Point"}
}