{
  "type": "Feature",
  "properties": {
    "iso:country":"US",
    "sg:address":"1724 W Division St",
    "sg:city":"Arlington",
    "sg:classifiers":[
        {
            "category":"Restaurant",
            "type":"Food & Drink"
        }
    ],
    "sg:phone":"+1 817 275 7881",
    "sg:postcode":"76012",
    "sg:province":"TX",
    "wof:name":"Arlington Steak House Inc",
    "wof:placetype":"venue"
},
  "geometry": {"coordinates":[-97.134934,32.735837],"type":"Point"}
}