{
  "type": "Feature",
  "properties": {
    "iso:country":"US",
    "sg:address":"4802 Up River Rd",
    "sg:city":"Corpus Christi",
    "sg:classifiers":[
        {
            "category":"Government",
            "subcategory":"Fire Station",
            "type":"Public Place"
        }
    ],
    "sg:phone":"+1 361 882 6253",
    "sg:postcode":"78407",
    "sg:province":"TX",
    "sg:tags":[
        "department"
    ],
    "sg:website":"www.rtfc.org",
    "wof:name":"Refinery Terminal Fire Co",
    "wof:placetype":"venue"
},
  "geometry": {"coordinates":[-97.44368299999999,27.803458],"type":"Point"}
}