{
  "type": "Feature",
  "properties": {
    "iso:country":"US",
    "sg:address":"2203 del Ray Ct",
    "sg:city":"Arlington",
    "sg:classifiers":[
        {
            "category":"Real Estate",
            "subcategory":"Real Estate Agent",
            "type":"Services"
        }
    ],
    "sg:phone":"+1 817 446 7209",
    "sg:postcode":"76013",
    "sg:province":"TX",
    "wof:name":"Milestone Resource Manage",
    "wof:placetype":"venue"
},
  "geometry": {"coordinates":[-97.196118,32.70978],"type":"Point"}
}