{
  "type": "Feature",
  "properties": {
    "iso:country":"US",
    "sg:address":"1718 Fry Rd",
    "sg:city":"Houston",
    "sg:classifiers":[
        {
            "category":"Real Estate",
            "subcategory":"Real Estate Agent",
            "type":"Services"
        }
    ],
    "sg:phone":"+1 281 395 5600",
    "sg:postcode":"77084",
    "sg:province":"TX",
    "wof:name":"Legacy Realty",
    "wof:placetype":"venue"
},
  "geometry": {"coordinates":[-95.718796,29.790911],"type":"Point"}
}