{
  "type": "Feature",
  "properties": {
    "iso:country":"US",
    "sg:address":"112 San Antonio Cir",
    "sg:city":"Los Fresnos",
    "sg:classifiers":[
        {
            "category":"Shopping",
            "type":"Retail Goods"
        }
    ],
    "sg:phone":"+1 956 943 1920",
    "sg:postcode":"78566",
    "sg:province":"TX",
    "sg:tags":[
        "candle"
    ],
    "wof:name":"Country Primitive Candle Co",
    "wof:placetype":"venue"
},
  "geometry": {"coordinates":[-97.491162,26.087793],"type":"Point"}
}