{
  "type": "Feature",
  "properties": {
    "iso:country":"US",
    "sg:address":"3503 Avenue E",
    "sg:city":"Nederland",
    "sg:classifiers":[
        {
            "category":"Personal",
            "subcategory":"Beauty Salon",
            "type":"Services"
        }
    ],
    "sg:phone":"+1 409 729 6700",
    "sg:postcode":"77627",
    "sg:province":"TX",
    "sg:tags":[
        "shop"
    ],
    "wof:name":"Textures Hair and Nail Salon",
    "wof:placetype":"venue"
},
  "geometry": {"coordinates":[-94.002398,29.953702],"type":"Point"}
}