{
  "type": "Feature",
  "properties": {
    "iso:country":"US",
    "sg:address":"416 Denrock Ave",
    "sg:city":"Dalhart",
    "sg:classifiers":[
        {
            "category":"Shopping",
            "subcategory":"Gifts & Souvenirs",
            "type":"Retail Goods"
        }
    ],
    "sg:phone":"+1 806 244 9794",
    "sg:postcode":"79022",
    "sg:province":"TX",
    "wof:name":"Amys Hang UPS",
    "wof:placetype":"venue"
},
  "geometry": {"coordinates":[-102.523235,36.061969],"type":"Point"}
}