{
  "type": "Feature",
  "properties": {
    "iso:country":"US",
    "sg:address":"2320 Airport Rd",
    "sg:city":"Temple",
    "sg:classifiers":[
        {
            "category":"Personal",
            "subcategory":"Massage",
            "type":"Services"
        },
        {
            "category":"Personal",
            "subcategory":"Beauty Salon",
            "type":"Services"
        },
        {
            "category":"Personal",
            "subcategory":"Day Spa",
            "type":"Services"
        },
        {
            "category":"Personal",
            "subcategory":"Skin Care",
            "type":"Services"
        }
    ],
    "sg:phone":"+1 254 771 4040",
    "sg:postcode":"76504",
    "sg:province":"TX",
    "sg:tags":[
        "hair",
        "stylist"
    ],
    "wof:name":"E'Lan Salon and Spa",
    "wof:placetype":"venue"
},
  "geometry": {"coordinates":[-97.36553600000001,31.106092],"type":"Point"}
}