{
  "type": "Feature",
  "properties": {
    "iso:country":"US",
    "sg:address":"2109 Barbell Ln",
    "sg:city":"Fort Worth",
    "sg:classifiers":[
        {
            "category":"Shopping",
            "subcategory":"Discount & Variety Stores",
            "type":"Retail Goods"
        }
    ],
    "sg:phone":"+1 817 834 4153",
    "sg:postcode":"76111",
    "sg:province":"TX",
    "wof:name":"Western Variety",
    "wof:placetype":"venue"
},
  "geometry": {"coordinates":[-97.29874599999999,32.791413],"type":"Point"}
}