{
  "type": "Feature",
  "properties": {
    "iso:country":"US",
    "sg:address":"304 S Broadway St",
    "sg:city":"Mcallen",
    "sg:classifiers":[
        {
            "category":"Wholesale",
            "subcategory":"Medical Equipment & Supplies",
            "type":"Manufacturing & Wholesale Goods"
        },
        {
            "category":"Shopping",
            "subcategory":"Pharmacy",
            "type":"Retail Goods"
        }
    ],
    "sg:phone":"+1 956 682 3822",
    "sg:postcode":"78501",
    "sg:province":"TX",
    "sg:tags":[
        "home",
        "health",
        "care"
    ],
    "wof:name":"Texas Laboratories & Medical Supplies",
    "wof:placetype":"venue"
},
  "geometry": {"coordinates":[-98.23376399999999,26.201261],"type":"Point"}
}