{
  "type": "Feature",
  "properties": {
    "iso:country":"US",
    "sg:address":"2109 N I St",
    "sg:city":"Mcallen",
    "sg:classifiers":[
        {
            "category":"Shopping",
            "subcategory":"Crafts & Fabrics",
            "type":"Retail Goods"
        }
    ],
    "sg:phone":"+1 956 683 9266",
    "sg:postcode":"78501",
    "sg:province":"TX",
    "sg:tags":[
        "sewing"
    ],
    "wof:name":"Sun Tex",
    "wof:placetype":"venue"
},
  "geometry": {"coordinates":[-98.20731499999999,26.219391],"type":"Point"}
}