{
  "type": "Feature",
  "properties": {
    "iso:country":"US",
    "sg:address":"1809 Rock Island St",
    "sg:city":"Dallas",
    "sg:classifiers":[
        {
            "category":"Food & Beverages",
            "subcategory":"Specialty",
            "type":"Retail Goods"
        },
        {
            "category":"Manufacturing",
            "subcategory":"Petroleum Products",
            "type":"Manufacturing & Wholesale Goods"
        },
        {
            "category":"Autos & Motor Vehicles",
            "subcategory":"Auto Supplies",
            "type":"Retail Goods"
        }
    ],
    "sg:phone":"+1 214 421 4147",
    "sg:postcode":"75207",
    "sg:province":"TX",
    "sg:tags":[
        "lubricating",
        "oil",
        "solvent",
        "lubricant"
    ],
    "sg:website":"http://www.buckleyoil.com",
    "wof:name":"Buckley Oil Company",
    "wof:placetype":"venue"
},
  "geometry": {"coordinates":[-96.797532,32.760367],"type":"Point"}
}