{
  "type": "Feature",
  "properties": {
    "iso:country":"US",
    "sg:address":"973 Wakefield Dr",
    "sg:city":"Houston",
    "sg:classifiers":[
        {
            "category":"Insurance",
            "subcategory":"Insurance Agent",
            "type":"Services"
        }
    ],
    "sg:phone":"+1 713 681 4976",
    "sg:postcode":"77018",
    "sg:province":"TX",
    "wof:name":"Bob Smith Insurance",
    "wof:placetype":"venue"
},
  "geometry": {"coordinates":[-95.42187800000001,29.821422],"type":"Point"}
}