{
  "type": "Feature",
  "properties": {
    "iso:country":"US",
    "sg:address":"800 Boston St",
    "sg:city":"Laredo",
    "sg:classifiers":[
        {
            "category":"Cemetery",
            "type":"Public Place"
        },
        {
            "category":"Retail",
            "subcategory":"Funeral Services",
            "type":"Services"
        }
    ],
    "sg:phone":"+1 956 723 2978",
    "sg:postcode":"78041",
    "sg:province":"TX",
    "sg:tags":[
        "director",
        "embalmer",
        "crematory"
    ],
    "wof:name":"Hernandez Lopez & Sons Funeral Chapels",
    "wof:placetype":"venue"
},
  "geometry": {"coordinates":[-99.503349,27.533649],"type":"Point"}
}