{
  "type": "Feature",
  "properties": {
    "iso:country":"US",
    "sg:address":"11000 E Davis St",
    "sg:city":"Conroe",
    "sg:classifiers":[
        {
            "category":"Restaurant",
            "type":"Food & Drink"
        }
    ],
    "sg:menulink":"http://www.allmenus.com/tx/southeast-montgomery/202893-mcdonalds/menu/",
    "sg:postcode":"77301",
    "sg:province":"TX",
    "sg:tags":[
        "burger",
        "american"
    ],
    "wof:name":"McDonald's",
    "wof:placetype":"venue"
},
  "geometry": {"coordinates":[-95.402231,30.323424],"type":"Point"}
}