{
  "type": "Feature",
  "properties": {
    "iso:country":"US",
    "sg:address":"2303 Padre Blvd",
    "sg:city":"S Padre Island",
    "sg:classifiers":[
        {
            "category":"Shopping",
            "subcategory":"Tobacco",
            "type":"Retail Goods"
        }
    ],
    "sg:phone":"+1 956 761 9262",
    "sg:postcode":"78597",
    "sg:province":"TX",
    "sg:tags":[
        "cigarette",
        "cigar",
        "dealer"
    ],
    "wof:name":"Cloud Nine",
    "wof:placetype":"venue"
},
  "geometry": {"coordinates":[-97.167192,26.101761],"type":"Point"}
}