{
  "type": "Feature",
  "properties": {
    "iso:country":"US",
    "sg:address":"5600 FM 424",
    "sg:city":"Aubrey",
    "sg:classifiers":[
        {
            "category":"Shopping",
            "subcategory":"Clothing, Apparel, & Fashions",
            "type":"Retail Goods"
        }
    ],
    "sg:phone":"+1 940 365 3360",
    "sg:postcode":"76227",
    "sg:province":"TX",
    "wof:name":"Just US Girls",
    "wof:placetype":"venue"
},
  "geometry": {"coordinates":[-96.98831,33.237678],"type":"Point"}
}