{
  "type": "Feature",
  "properties": {
    "iso:country":"US",
    "sg:address":"1612 Driftwood Dr",
    "sg:city":"Dallas",
    "sg:classifiers":[
        {
            "category":"Professional",
            "subcategory":"Employment Agencies",
            "type":"Services"
        }
    ],
    "sg:phone":"+1 214 331 6790",
    "sg:postcode":"75224",
    "sg:province":"TX",
    "wof:name":"Roshanda Austin",
    "wof:placetype":"venue"
},
  "geometry": {"coordinates":[-96.84912,32.702438],"type":"Point"}
}