{
  "type": "Feature",
  "properties": {
    "iso:country":"US",
    "sg:address":"819 Sunfish St",
    "sg:city":"Lakeway",
    "sg:classifiers":[
        {
            "category":"Manufacturing",
            "subcategory":"Signs",
            "type":"Manufacturing & Wholesale Goods"
        }
    ],
    "sg:phone":"+1 512 346 5380",
    "sg:postcode":"78734",
    "sg:province":"TX",
    "wof:name":"Bob Jones Co Signs & Graphics",
    "wof:placetype":"venue"
},
  "geometry": {"coordinates":[-97.983205,30.368797],"type":"Point"}
}