{
  "type": "Feature",
  "properties": {
    "iso:country":"US",
    "sg:address":"110 N Coit Rd",
    "sg:city":"Richardson",
    "sg:classifiers":[
        {
            "category":"Banks & Credit Unions",
            "subcategory":"Bank",
            "type":"Services"
        }
    ],
    "sg:phone":"+1 972 231 9400",
    "sg:postcode":"75080",
    "sg:province":"TX",
    "wof:name":"JPMorgan Chase & Co",
    "wof:placetype":"venue"
},
  "geometry": {"coordinates":[-96.768646,32.951509],"type":"Point"}
}