{
  "type": "Feature",
  "properties": {
    "iso:country":"US",
    "sg:address":"20595 FM 16 W",
    "sg:city":"Lindale",
    "sg:classifiers":[
        {
            "category":"Personal",
            "type":"Services"
        }
    ],
    "sg:phone":"+1 903 881 8260",
    "sg:postcode":"75771",
    "sg:province":"TX",
    "wof:name":"Bruce Hill Concepts",
    "wof:placetype":"venue"
},
  "geometry": {"coordinates":[-95.504896,32.510377],"type":"Point"}
}