{
  "type": "Feature",
  "properties": {
    "iso:country":"US",
    "sg:address":"563 US Hwy 90 Alt",
    "sg:city":"Sealy",
    "sg:classifiers":[
        {
            "category":"Building & Trades",
            "subcategory":"Construction",
            "type":"Services"
        }
    ],
    "sg:phone":"+1 979 885 2299",
    "sg:postcode":"77434",
    "sg:province":"TX",
    "wof:name":"Brandenburg Building",
    "wof:placetype":"venue"
},
  "geometry": {"coordinates":[-96.33815800000001,29.585904],"type":"Point"}
}