{
  "type": "Feature",
  "properties": {
    "iso:country":"US",
    "sg:address":"513 Gillette Blvd",
    "sg:city":"San Antonio",
    "sg:classifiers":[
        {
            "category":"Retail",
            "subcategory":"Repair Shop",
            "type":"Services"
        }
    ],
    "sg:phone":"+1 210 922 0683",
    "sg:postcode":"78221",
    "sg:province":"TX",
    "sg:tags":[
        "farm",
        "equipment",
        "parts",
        "machinery"
    ],
    "wof:name":"Wallace Tractors & Equipment",
    "wof:placetype":"venue"
},
  "geometry": {"coordinates":[-98.515996,29.330315],"type":"Point"}
}