{
  "type": "Feature",
  "properties": {
    "iso:country":"US",
    "sg:address":"1535 Elton St",
    "sg:city":"Houston",
    "sg:classifiers":[
        {
            "category":"Food & Beverages",
            "subcategory":"Groceries & Convenience Stores",
            "type":"Retail Goods"
        }
    ],
    "sg:phone":"+1 713 910 0074",
    "sg:postcode":"77034",
    "sg:province":"TX",
    "wof:name":"La Michoacana Meat Market",
    "wof:placetype":"venue"
},
  "geometry": {"coordinates":[-95.247545,29.649436],"type":"Point"}
}