{
  "type": "Feature",
  "properties": {
    "iso:country":"US",
    "sg:address":"2525 N Loop Fwy",
    "sg:city":"Houston",
    "sg:classifiers":[
        {
            "category":"Professional",
            "subcategory":"Lawyer & Legal Services",
            "type":"Services"
        }
    ],
    "sg:phone":"+1 832 618 1910",
    "sg:postcode":"77008",
    "sg:province":"TX",
    "sg:tags":[
        "attorney"
    ],
    "wof:name":"Lori Noack-May",
    "wof:placetype":"venue"
},
  "geometry": {"coordinates":[-95.44154399999999,29.808169],"type":"Point"}
}