{
  "type": "Feature",
  "properties": {
    "iso:country":"US",
    "sg:address":"2208 Rey Dr",
    "sg:city":"Waco",
    "sg:classifiers":[
        {
            "category":"Professional",
            "type":"Services"
        }
    ],
    "sg:phone":"+1 254 666 2061",
    "sg:postcode":"76712",
    "sg:province":"TX",
    "wof:name":"Howells Handyman Service",
    "wof:placetype":"venue"
},
  "geometry": {"coordinates":[-97.212988,31.474246],"type":"Point"}
}