{
  "type": "Feature",
  "properties": {
    "iso:country":"US",
    "sg:address":"4008 Buena Vista St",
    "sg:city":"Dallas",
    "sg:classifiers":[
        {
            "category":"Real Estate",
            "subcategory":"Real Estate Agent",
            "type":"Services"
        }
    ],
    "sg:phone":"+1 214 526 0948",
    "sg:postcode":"75204",
    "sg:province":"TX",
    "sg:tags":[
        "agency",
        "rental"
    ],
    "wof:name":"Parker Rentals Inc",
    "wof:placetype":"venue"
},
  "geometry": {"coordinates":[-96.795877,32.815094],"type":"Point"}
}