{
  "type": "Feature",
  "properties": {
    "iso:country":"US",
    "sg:address":"9507 Silver Crown",
    "sg:city":"San Antonio",
    "sg:classifiers":[
        {
            "category":"Building & Trades",
            "subcategory":"Electrical",
            "type":"Services"
        }
    ],
    "sg:phone":"+1 210 647 3138",
    "sg:postcode":"78254",
    "sg:province":"TX",
    "sg:tags":[
        "electrical",
        "contractor"
    ],
    "wof:name":"Absolute Power Electrical",
    "wof:placetype":"venue"
},
  "geometry": {"coordinates":[-98.67110099999999,29.540184],"type":"Point"}
}