{
  "type": "Feature",
  "properties": {
    "iso:country":"US",
    "sg:address":"5057 Keller Springs Rd",
    "sg:city":"Addison",
    "sg:classifiers":[
        {
            "category":"Banks & Credit Unions",
            "subcategory":"Financial Services",
            "type":"Services"
        }
    ],
    "sg:phone":"+1 469 484 6590",
    "sg:postcode":"75001",
    "sg:province":"TX",
    "sg:tags":[
        "broker",
        "mortgage"
    ],
    "wof:name":"Worldwide Mortgage",
    "wof:placetype":"venue"
},
  "geometry": {"coordinates":[-96.82316899999999,32.968727],"type":"Point"}
}