{
  "type": "Feature",
  "properties": {
    "iso:country":"US",
    "sg:address":"1506 Ave D",
    "sg:city":"Moody",
    "sg:classifiers":[
        {
            "category":"Organizations",
            "subcategory":"Religious Organization",
            "type":"Services"
        }
    ],
    "sg:phone":"+1 254 853 9390",
    "sg:postcode":"76557",
    "sg:province":"TX",
    "sg:tags":[
        "church"
    ],
    "wof:name":"Church Of Christ Moody",
    "wof:placetype":"venue"
},
  "geometry": {"coordinates":[-97.363305,31.30108],"type":"Point"}
}