{
  "type": "Feature",
  "properties": {
    "iso:country":"US",
    "sg:address":"406 Raymond St",
    "sg:city":"Farmersville",
    "sg:classifiers":[
        {
            "category":"Government",
            "subcategory":"Office",
            "type":"Public Place"
        }
    ],
    "sg:phone":"+1 972 782 8671",
    "sg:postcode":"75442",
    "sg:province":"TX",
    "wof:name":"Collin County Justice Of Peace",
    "wof:placetype":"venue"
},
  "geometry": {"coordinates":[-96.371439,33.160455],"type":"Point"}
}