{
  "type": "Feature",
  "properties": {
    "iso:country":"US",
    "sg:address":"2710 International Blvd",
    "sg:city":"Brownsville",
    "sg:classifiers":[
        {
            "category":"Retail",
            "subcategory":"Auto Repair",
            "type":"Services"
        },
        {
            "category":"Autos & Motor Vehicles",
            "subcategory":"Auto Supplies",
            "type":"Retail Goods"
        }
    ],
    "sg:phone":"+1 956 544 8300",
    "sg:postcode":"78521",
    "sg:province":"TX",
    "sg:tags":[
        "automotive",
        "alarm",
        "automobile"
    ],
    "wof:name":"Audio Designs",
    "wof:placetype":"venue"
},
  "geometry": {"coordinates":[-97.47920000000001,25.907778],"type":"Point"}
}