{
  "type": "Feature",
  "properties": {
    "iso:country":"US",
    "sg:address":"6922 Satsuma Dr",
    "sg:city":"Houston",
    "sg:classifiers":[
        {
            "category":"Professional",
            "subcategory":"Engineering",
            "type":"Services"
        },
        {
            "category":"Home & Garden",
            "subcategory":"Building Materials",
            "type":"Retail Goods"
        },
        {
            "category":"Building & Trades",
            "subcategory":"Construction",
            "type":"Services"
        }
    ],
    "sg:phone":"+1 281 619 8806",
    "sg:postcode":"77041",
    "sg:province":"TX",
    "sg:tags":[
        "system",
        "specialty",
        "heating",
        "contractor",
        "equipment",
        "air conditioning"
    ],
    "sg:website":"http://find.trane.com/tcs-dealer-414972?utm_source=YP&utm_medium=banner&utm_campaign=TL",
    "wof:name":"Redmon Heating & Cooling",
    "wof:placetype":"venue"
},
  "geometry": {"coordinates":[-95.60244299999999,29.8791],"type":"Point"}
}