{
  "type": "Feature",
  "properties": {
    "iso:country":"US",
    "sg:address":"15630 Mission Ridge",
    "sg:city":"San Antonio",
    "sg:classifiers":[
        {
            "category":"Professional",
            "subcategory":"Detective & Security Services",
            "type":"Services"
        }
    ],
    "sg:phone":"+1 210 494 2851",
    "sg:postcode":"78232",
    "sg:province":"TX",
    "sg:tags":[
        "car"
    ],
    "wof:name":"Mission Ridge Guard House",
    "wof:placetype":"venue"
},
  "geometry": {"coordinates":[-98.512505,29.588403],"type":"Point"}
}