{
  "type": "Feature",
  "properties": {
    "iso:country":"US",
    "sg:address":"12205 Lower Seguin Rd",
    "sg:city":"Schertz",
    "sg:classifiers":[
        {
            "category":"Farming",
            "subcategory":"Farm",
            "type":"Manufacturing & Wholesale Goods"
        }
    ],
    "sg:phone":"+1 210 658 2922",
    "sg:postcode":"78154",
    "sg:province":"TX",
    "sg:tags":[
        "crop",
        "general"
    ],
    "wof:name":"Schneider Alton",
    "wof:placetype":"venue"
},
  "geometry": {"coordinates":[-98.215835,29.530298],"type":"Point"}
}