{
  "type": "Feature",
  "properties": {
    "iso:country":"US",
    "sg:address":"2809 Abbey Rd",
    "sg:city":"Mc Kinney",
    "sg:classifiers":[
        {
            "category":"Retail",
            "subcategory":"Animal Services",
            "type":"Services"
        }
    ],
    "sg:phone":"+1 972 529 9952",
    "sg:postcode":"75070",
    "sg:province":"TX",
    "wof:name":"Hungry Dog Deli",
    "wof:placetype":"venue"
},
  "geometry": {"coordinates":[-96.655593,33.170953],"type":"Point"}
}