{
  "type": "Feature",
  "properties": {
    "iso:country":"US",
    "sg:address":"1315 Fort Worth Dr",
    "sg:city":"Denton",
    "sg:classifiers":[
        {
            "category":"Manufacturing",
            "subcategory":"Glass & Minerals",
            "type":"Manufacturing & Wholesale Goods"
        }
    ],
    "sg:phone":"+1 940 382 7414",
    "sg:postcode":"76205",
    "sg:province":"TX",
    "sg:tags":[
        "brick",
        "common"
    ],
    "wof:name":"Acme Brick Tile & More",
    "wof:placetype":"venue"
},
  "geometry": {"coordinates":[-97.13984600000001,33.191629],"type":"Point"}
}