{
  "type": "Feature",
  "properties": {
    "iso:country":"US",
    "sg:address":"314 Texas St",
    "sg:city":"Cedar Hill",
    "sg:classifiers":[
        {
            "category":"Professional",
            "subcategory":"Business Services",
            "type":"Services"
        }
    ],
    "sg:phone":"+1 972 291 7231",
    "sg:postcode":"75104",
    "sg:province":"TX",
    "wof:name":"Wr House Enterprises Inc",
    "wof:placetype":"venue"
},
  "geometry": {"coordinates":[-96.952089,32.587893],"type":"Point"}
}