{
  "type": "Feature",
  "properties": {
    "iso:country":"US",
    "sg:address":"4th and Guadalupe",
    "sg:city":"Austin",
    "sg:classifiers":[
        {
            "category":"Food & Beverages",
            "subcategory":"Farmers Market",
            "type":"Retail Goods"
        }
    ],
    "sg:phone":"+1 512 524 0688",
    "sg:postcode":"78701",
    "sg:province":"TX",
    "sg:website":"austinfarmersmarket.org",
    "wof:name":"Dai Due Austin Farmer's Market Stand",
    "wof:placetype":"venue"
},
  "geometry": {"coordinates":[-97.746962,30.267184],"type":"Point"}
}