{
  "type": "Feature",
  "properties": {
    "iso:country":"US",
    "sg:address":"2801 Avenue N",
    "sg:city":"Galveston",
    "sg:classifiers":[
        {
            "category":"Organizations",
            "subcategory":"Religious Organization",
            "type":"Services"
        }
    ],
    "sg:phone":"+1 409 763 2696",
    "sg:postcode":"77550",
    "sg:province":"TX",
    "wof:name":"Second Christn CHR",
    "wof:placetype":"venue"
},
  "geometry": {"coordinates":[-94.796915,29.29393],"type":"Point"}
}