{
  "type": "Feature",
  "properties": {
    "iso:country":"US",
    "sg:address":"2309 Remuda Pl",
    "sg:city":"Amarillo",
    "sg:classifiers":[
        {
            "category":"Building & Trades",
            "subcategory":"Construction",
            "type":"Services"
        }
    ],
    "sg:phone":"+1 806 356 9782",
    "sg:postcode":"79124",
    "sg:province":"TX",
    "sg:tags":[
        "residential"
    ],
    "wof:name":"Boray Inc",
    "wof:placetype":"venue"
},
  "geometry": {"coordinates":[-101.919612,35.235063],"type":"Point"}
}