{
  "type": "Feature",
  "properties": {
    "iso:country":"US",
    "sg:address":"5116 Lake Falls Dr",
    "sg:city":"Plano",
    "sg:classifiers":[
        {
            "category":"Manufacturing",
            "subcategory":"Printing",
            "type":"Manufacturing & Wholesale Goods"
        },
        {
            "category":"Professional",
            "subcategory":"Advertising",
            "type":"Services"
        },
        {
            "category":"Wholesale",
            "subcategory":"Books, Periodicals, & Newspapers",
            "type":"Manufacturing & Wholesale Goods"
        }
    ],
    "sg:phone":"+1 972 378 3770",
    "sg:postcode":"75093",
    "sg:province":"TX",
    "sg:tags":[
        "directory",
        "publisher",
        "guide",
        "publishers-directory"
    ],
    "wof:name":"Holistic Network",
    "wof:placetype":"venue"
},
  "geometry": {"coordinates":[-96.799819,33.052674],"type":"Point"}
}