{
  "type": "Feature",
  "properties": {
    "iso:country":"US",
    "sg:address":"1615 Hillendahl Blvd",
    "sg:city":"Houston",
    "sg:classifiers":[
        {
            "category":"Health Services",
            "subcategory":"Nursing And Care Facility",
            "type":"Services"
        }
    ],
    "sg:phone":"+1 713 365 0561",
    "sg:postcode":"77055",
    "sg:province":"TX",
    "sg:tags":[
        "skilled",
        "center"
    ],
    "wof:name":"Heritage Sam Houston Gardens",
    "wof:placetype":"venue"
},
  "geometry": {"coordinates":[-95.493309,29.799597],"type":"Point"}
}