{
  "type": "Feature",
  "properties": {
    "iso:country":"US",
    "sg:address":"302 N Ave D",
    "sg:city":"Clifton",
    "sg:classifiers":[
        {
            "category":"Shopping",
            "subcategory":"Clothing, Apparel, & Fashions",
            "type":"Retail Goods"
        }
    ],
    "sg:phone":"+1 254 675 6487",
    "sg:postcode":"76634",
    "sg:province":"TX",
    "sg:tags":[
        "family"
    ],
    "wof:name":"Denises Scrubs & Treasure Che",
    "wof:placetype":"venue"
},
  "geometry": {"coordinates":[-97.575777,31.786466],"type":"Point"}
}