{
  "type": "Feature",
  "properties": {
    "iso:country":"US",
    "sg:address":"717 S Greenville Ave",
    "sg:city":"Allen",
    "sg:classifiers":[
        {
            "category":"Restaurant",
            "type":"Food & Drink"
        }
    ],
    "sg:phone":"+1 214 509 9997",
    "sg:postcode":"75002",
    "sg:province":"TX",
    "sg:tags":[
        "eating"
    ],
    "wof:name":"Ballpark Diner Inc",
    "wof:placetype":"venue"
},
  "geometry": {"coordinates":[-96.67082000000001,33.087826],"type":"Point"}
}