{
  "type": "Feature",
  "properties": {
    "iso:country":"US",
    "sg:address":"2121 Anthony Dr",
    "sg:city":"Tyler",
    "sg:classifiers":[
        {
            "category":"Wholesale",
            "subcategory":"Machinery & Supplies",
            "type":"Manufacturing & Wholesale Goods"
        }
    ],
    "sg:phone":"+1 903 561 9446",
    "sg:postcode":"75701",
    "sg:province":"TX",
    "sg:tags":[
        "contractor"
    ],
    "wof:name":"Hartmann Building Specialties",
    "wof:placetype":"venue"
},
  "geometry": {"coordinates":[-95.328796,32.301784],"type":"Point"}
}