{
  "type": "Feature",
  "properties": {
    "iso:country":"US",
    "sg:address":"3807 Riley St",
    "sg:city":"Houston",
    "sg:classifiers":[
        {
            "category":"Professional",
            "subcategory":"Business Services",
            "type":"Services"
        }
    ],
    "sg:phone":"+1 713 592 8319",
    "sg:postcode":"77005",
    "sg:province":"TX",
    "wof:name":"Power Fund LLC",
    "wof:placetype":"venue"
},
  "geometry": {"coordinates":[-95.439312,29.708636],"type":"Point"}
}