{
  "type": "Feature",
  "properties": {
    "iso:country":"US",
    "sg:address":"2812 Dinah Ln",
    "sg:city":"Tyler",
    "sg:classifiers":[
        {
            "category":"Professional",
            "type":"Services"
        }
    ],
    "sg:phone":"+1 903 593 8149",
    "sg:postcode":"75701",
    "sg:province":"TX",
    "wof:name":"Rusty Buffalo",
    "wof:placetype":"venue"
},
  "geometry": {"coordinates":[-95.281282,32.316142],"type":"Point"}
}