{
  "type": "Feature",
  "properties": {
    "iso:country":"US",
    "sg:address":"104 Baycliff Ln",
    "sg:city":"Laredo",
    "sg:classifiers":[
        {
            "category":"Shopping",
            "type":"Retail Goods"
        }
    ],
    "sg:phone":"+1 956 725 2872",
    "sg:postcode":"78041",
    "sg:province":"TX",
    "sg:tags":[
        "merchandise"
    ],
    "wof:name":"Espinosa Enterprise",
    "wof:placetype":"venue"
},
  "geometry": {"coordinates":[-99.485766,27.553655],"type":"Point"}
}