{
  "type": "Feature",
  "properties": {
    "iso:country":"US",
    "sg:address":"7302 Bellaire Blvd",
    "sg:city":"Houston",
    "sg:classifiers":[
        {
            "category":"Banks & Credit Unions",
            "subcategory":"Bank",
            "type":"Services"
        }
    ],
    "sg:phone":"+1 713 772 0316",
    "sg:postcode":"77036",
    "sg:province":"TX",
    "sg:website":"www.wachovia.com",
    "wof:name":"Wachovia",
    "wof:placetype":"venue"
},
  "geometry": {"coordinates":[-95.513407,29.704733],"type":"Point"}
}