{
  "type": "Feature",
  "properties": {
    "iso:country":"US",
    "sg:address":"5086 E Marigold St",
    "sg:city":"Gardendale",
    "sg:classifiers":[
        {
            "category":"Autos & Motor Vehicles",
            "subcategory":"Automobile Sales",
            "type":"Retail Goods"
        }
    ],
    "sg:phone":"+1 432 363 9344",
    "sg:postcode":"79758",
    "sg:province":"TX",
    "sg:tags":[
        "car",
        "dealer"
    ],
    "wof:name":"Eicher & Eicher",
    "wof:placetype":"venue"
},
  "geometry": {"coordinates":[-102.37611,32.02855],"type":"Point"}
}