{
  "type": "Feature",
  "properties": {
    "iso:country":"US",
    "sg:address":"1419 Springfield Ave",
    "sg:city":"Laredo",
    "sg:classifiers":[
        {
            "category":"Wholesale",
            "subcategory":"Auto Parts",
            "type":"Manufacturing & Wholesale Goods"
        }
    ],
    "sg:phone":"+1 956 726 0171",
    "sg:postcode":"78040",
    "sg:province":"TX",
    "sg:tags":[
        "automotive"
    ],
    "wof:name":"Border Transmission Parts",
    "wof:placetype":"venue"
},
  "geometry": {"coordinates":[-99.492767,27.509145],"type":"Point"}
}