{
  "type": "Feature",
  "properties": {
    "iso:country":"US",
    "sg:address":"114 W Woodard St",
    "sg:city":"Denison",
    "sg:classifiers":[
        {
            "category":"Social Services",
            "type":"Services"
        }
    ],
    "sg:phone":"+1 903 463 1359",
    "sg:postcode":"75021",
    "sg:province":"TX",
    "sg:tags":[
        "probation"
    ],
    "wof:name":"Grayson County Adult Probation",
    "wof:placetype":"venue"
},
  "geometry": {"coordinates":[-96.536641,33.756247],"type":"Point"}
}