{
  "type": "Feature",
  "properties": {
    "iso:country":"US",
    "sg:address":"5200 Navigation Blvd",
    "sg:city":"Houston",
    "sg:classifiers":[
        {
            "category":"Health Services",
            "subcategory":"Doctor",
            "type":"Services"
        }
    ],
    "sg:phone":"+1 713 514 0191",
    "sg:postcode":"77011",
    "sg:province":"TX",
    "sg:tags":[
        "physician",
        "surgeon"
    ],
    "wof:name":"Network Of Physicians",
    "wof:placetype":"venue"
},
  "geometry": {"coordinates":[-95.319914,29.749785],"type":"Point"}
}