{
  "type": "Feature",
  "properties": {
    "iso:country":"US",
    "sg:address":"1400 W Main St",
    "sg:city":"Denison",
    "sg:classifiers":[
        {
            "category":"Shopping",
            "subcategory":"Used Merchandise",
            "type":"Retail Goods"
        }
    ],
    "sg:phone":"+1 903 327 4250",
    "sg:postcode":"75020",
    "sg:province":"TX",
    "wof:name":"Red River Antiques",
    "wof:placetype":"venue"
},
  "geometry": {"coordinates":[-96.556743,33.756005],"type":"Point"}
}