{
  "type": "Feature",
  "properties": {
    "iso:country":"US",
    "sg:address":"2309 Birdcreek Ter",
    "sg:city":"Temple",
    "sg:classifiers":[
        {
            "category":"Professional",
            "subcategory":"Employment Agencies",
            "type":"Services"
        }
    ],
    "sg:phone":"+1 254 577 4210",
    "sg:postcode":"76502",
    "sg:province":"TX",
    "sg:tags":[
        "temporary",
        "help",
        "contractor"
    ],
    "sg:website":"http://www.spherion.com",
    "wof:name":"Spherion",
    "wof:placetype":"venue"
},
  "geometry": {"coordinates":[-97.38910199999999,31.086488],"type":"Point"}
}