{
  "type": "Feature",
  "properties": {
    "iso:country":"US",
    "sg:address":"1121 E Tyler Ave",
    "sg:city":"Harlingen",
    "sg:classifiers":[
        {
            "category":"Health Services",
            "subcategory":"Chiropractor",
            "type":"Services"
        }
    ],
    "sg:phone":"+1 956 423 5762",
    "sg:postcode":"78550",
    "sg:province":"TX",
    "wof:name":"Lyndon Jones DC",
    "wof:placetype":"venue"
},
  "geometry": {"coordinates":[-97.68387199999999,26.189723],"type":"Point"}
}