{
  "type": "Feature",
  "properties": {
    "iso:country":"US",
    "sg:address":"324 E San Antonio Ave",
    "sg:city":"El Paso",
    "sg:classifiers":[
        {
            "category":"Professional",
            "type":"Services"
        }
    ],
    "sg:phone":"+1 915 533 7797",
    "sg:postcode":"79901",
    "sg:province":"TX",
    "sg:tags":[
        "establishment"
    ],
    "wof:name":"Payment Inc",
    "wof:placetype":"venue"
},
  "geometry": {"coordinates":[-106.48679300000001,31.758221],"type":"Point"}
}