{
  "type": "Feature",
  "properties": {
    "iso:country":"US",
    "sg:address":"9240 Guilbeau Rd",
    "sg:city":"San Antonio",
    "sg:classifiers":[
        {
            "category":"Social Services",
            "subcategory":"Child Care",
            "type":"Services"
        }
    ],
    "sg:phone":"+1 210 682 5671",
    "sg:postcode":"78250",
    "sg:province":"TX",
    "sg:tags":[
        "day"
    ],
    "wof:name":"LA Petite Kid Station",
    "wof:placetype":"venue"
},
  "geometry": {"coordinates":[-98.664416,29.51894],"type":"Point"}
}