{
  "type": "Feature",
  "properties": {
    "iso:country":"US",
    "sg:address":"112 E Cleveland Ave",
    "sg:city":"Electra",
    "sg:classifiers":[
        {
            "category":"Mining & Drilling",
            "type":"Manufacturing & Wholesale Goods"
        }
    ],
    "sg:phone":"+1 940 495 2402",
    "sg:postcode":"76360",
    "sg:province":"TX",
    "sg:tags":[
        "oil",
        "gas",
        "producer"
    ],
    "wof:name":"Douglas Mineral Trust",
    "wof:placetype":"venue"
},
  "geometry": {"coordinates":[-98.918538,34.029707],"type":"Point"}
}