{
  "type": "Feature",
  "properties": {
    "iso:country":"US",
    "sg:address":"3050 Schwartz Ave",
    "sg:city":"Fort Worth",
    "sg:classifiers":[
        {
            "category":"Organizations",
            "subcategory":"Religious Organization",
            "type":"Services"
        }
    ],
    "sg:phone":"+1 817 625 2092",
    "sg:postcode":"76106",
    "sg:province":"TX",
    "wof:name":"Emmanuel Baptist Church",
    "wof:placetype":"venue"
},
  "geometry": {"coordinates":[-97.332509,32.799574],"type":"Point"}
}