{
  "type": "Feature",
  "properties": {
    "iso:country":"US",
    "sg:address":"1304 E Tamarack Ave",
    "sg:city":"Mcallen",
    "sg:classifiers":[
        {
            "category":"Building & Trades",
            "subcategory":"Construction",
            "type":"Services"
        }
    ],
    "sg:phone":"+1 956 630 5850",
    "sg:postcode":"78501",
    "sg:province":"TX",
    "sg:tags":[
        "maker",
        "cabinet"
    ],
    "wof:name":"Ramos Woodworks",
    "wof:placetype":"venue"
},
  "geometry": {"coordinates":[-98.20339,26.21786],"type":"Point"}
}