{
  "type": "Feature",
  "properties": {
    "iso:country":"US",
    "sg:address":"11601 Pellicano Dr",
    "sg:city":"El Paso",
    "sg:classifiers":[
        {
            "category":"Health Services",
            "subcategory":"Doctor",
            "type":"Services"
        }
    ],
    "sg:phone":"+1 915 593 1328",
    "sg:postcode":"79936",
    "sg:province":"TX",
    "sg:tags":[
        "dentist"
    ],
    "wof:name":"Marquez Dental Ctr",
    "wof:placetype":"venue"
},
  "geometry": {"coordinates":[-106.30112800000001,31.744297],"type":"Point"}
}