{
  "type": "Feature",
  "properties": {
    "iso:country":"US",
    "sg:address":"6818 Fisher Rd",
    "sg:city":"Dallas",
    "sg:classifiers":[
        {
            "category":"Recreation",
            "type":"Entertainment"
        }
    ],
    "sg:phone":"+1 972 661 2433",
    "sg:postcode":"75214",
    "sg:province":"TX",
    "sg:tags":[
        "amusement"
    ],
    "wof:name":"Cheer Basics Inc",
    "wof:placetype":"venue"
},
  "geometry": {"coordinates":[-96.741962,32.846721],"type":"Point"}
}