{
  "type": "Feature",
  "properties": {
    "iso:country":"US",
    "sg:address":"4520 Hemlock Dr",
    "sg:city":"Baytown",
    "sg:classifiers":[
        {
            "category":"Real Estate",
            "subcategory":"Real Estate Operator",
            "type":"Services"
        }
    ],
    "sg:phone":"+1 281 424 3689",
    "sg:postcode":"77521",
    "sg:province":"TX",
    "sg:tags":[
        "apartment",
        "complex"
    ],
    "wof:name":"Sunshine Apts",
    "wof:placetype":"venue"
},
  "geometry": {"coordinates":[-95.00735899999999,29.771761],"type":"Point"}
}