{
  "type": "Feature",
  "properties": {
    "iso:country":"US",
    "sg:address":"1006 N Grant St",
    "sg:city":"Roma",
    "sg:classifiers":[
        {
            "category":"Manufacturing",
            "subcategory":"Printing",
            "type":"Manufacturing & Wholesale Goods"
        }
    ],
    "sg:phone":"+1 956 849 1464",
    "sg:postcode":"78584",
    "sg:province":"TX",
    "sg:tags":[
        "commercial"
    ],
    "wof:name":"Jessies Custom Airbrush",
    "wof:placetype":"venue"
},
  "geometry": {"coordinates":[-99.018006,26.40897],"type":"Point"}
}