{
  "type": "Feature",
  "properties": {
    "iso:country":"US",
    "sg:address":"8100 Woodcreek Dr",
    "sg:city":"Waco",
    "sg:classifiers":[
        {
            "category":"Professional",
            "subcategory":"Business Services",
            "type":"Services"
        }
    ],
    "sg:phone":"+1 254 776 5568",
    "sg:postcode":"76712",
    "sg:province":"TX",
    "wof:name":"Tex Ore Enterprises Inc",
    "wof:placetype":"venue"
},
  "geometry": {"coordinates":[-97.21643899999999,31.510714],"type":"Point"}
}