{
  "type": "Feature",
  "properties": {
    "iso:country":"US",
    "sg:address":"650 Central Ave",
    "sg:city":"Wake Village",
    "sg:classifiers":[
        {
            "category":"Shopping",
            "subcategory":"Optical Goods",
            "type":"Retail Goods"
        }
    ],
    "sg:phone":"+1 903 831 2324",
    "sg:postcode":"75501",
    "sg:province":"TX",
    "sg:tags":[
        "sun",
        "goggles",
        "sunglasses"
    ],
    "wof:name":"Sunglass Shop",
    "wof:placetype":"venue"
},
  "geometry": {"coordinates":[-94.113437,33.418555],"type":"Point"}
}