{
  "type": "Feature",
  "properties": {
    "iso:country":"US",
    "sg:address":"5855 Bicentennial St",
    "sg:city":"San Antonio",
    "sg:classifiers":[
        {
            "category":"Freight",
            "type":"Transportation"
        }
    ],
    "sg:phone":"+1 210 946 3255",
    "sg:postcode":"78219",
    "sg:province":"TX",
    "sg:tags":[
        "trucking"
    ],
    "wof:name":"Hensley Freight Lines",
    "wof:placetype":"venue"
},
  "geometry": {"coordinates":[-98.37470399999999,29.444478],"type":"Point"}
}