{
  "type": "Feature",
  "properties": {
    "iso:country":"US",
    "sg:address":"2612 N Walker Dr",
    "sg:city":"Leander",
    "sg:classifiers":[
        {
            "category":"Professional",
            "type":"Services"
        }
    ],
    "sg:phone":"+1 512 432 9413",
    "sg:postcode":"78641",
    "sg:province":"TX",
    "wof:name":"Nelson Revis",
    "wof:placetype":"venue"
},
  "geometry": {"coordinates":[-97.829334,30.54826],"type":"Point"}
}