{
  "type": "Feature",
  "properties": {
    "iso:country":"US",
    "sg:address":"600 S Center St",
    "sg:city":"Arlington",
    "sg:classifiers":[
        {
            "category":"Food & Beverages",
            "subcategory":"Groceries & Convenience Stores",
            "type":"Retail Goods"
        }
    ],
    "sg:phone":"+1 817 274 3821",
    "sg:postcode":"76010",
    "sg:province":"TX",
    "wof:name":"7-Eleven",
    "wof:placetype":"venue"
},
  "geometry": {"coordinates":[-97.10702499999999,32.730108],"type":"Point"}
}