{
  "type": "Feature",
  "properties": {
    "iso:country":"US",
    "sg:address":"905 E Los Ebanos Blvd",
    "sg:city":"Brownsville",
    "sg:classifiers":[
        {
            "category":"Social Services",
            "type":"Services"
        }
    ],
    "sg:phone":"+1 956 541 8040",
    "sg:postcode":"78520",
    "sg:province":"TX",
    "sg:tags":[
        "counselor",
        "marriage",
        "family"
    ],
    "wof:name":"Willows Treatment Ctr",
    "wof:placetype":"venue"
},
  "geometry": {"coordinates":[-97.503759,25.932024],"type":"Point"}
}