{
  "type": "Feature",
  "properties": {
    "iso:country":"US",
    "sg:address":"5409 4th St",
    "sg:city":"Lubbock",
    "sg:classifiers":[
        {
            "category":"Retail",
            "subcategory":"Laundry & Dry Cleaning",
            "type":"Services"
        },
        {
            "category":"Shopping",
            "subcategory":"Clothing, Apparel, & Fashions",
            "type":"Retail Goods"
        }
    ],
    "sg:phone":"+1 806 791 0637",
    "sg:postcode":"79416",
    "sg:province":"TX",
    "sg:tags":[
        "ready",
        "to",
        "alteration",
        "wear"
    ],
    "wof:name":"Alterations Unlimited",
    "wof:placetype":"venue"
},
  "geometry": {"coordinates":[-101.928805,33.592283],"type":"Point"}
}