{
  "type": "Feature",
  "properties": {
    "iso:country":"US",
    "sg:address":"114 Ruelle Ln",
    "sg:city":"San Antonio",
    "sg:classifiers":[
        {
            "category":"Home & Garden",
            "subcategory":"Furniture",
            "type":"Retail Goods"
        }
    ],
    "sg:phone":"+1 210 826 0110",
    "sg:postcode":"78209",
    "sg:province":"TX",
    "sg:tags":[
        "decor",
        "other",
        "kitchenware"
    ],
    "wof:name":"Casa Mortell",
    "wof:placetype":"venue"
},
  "geometry": {"coordinates":[-98.457762,29.492562],"type":"Point"}
}