{
  "type": "Feature",
  "properties": {
    "iso:country":"US",
    "sg:address":"3959 Gulfway Dr",
    "sg:city":"Port Arthur",
    "sg:classifiers":[
        {
            "category":"Social Services",
            "type":"Services"
        }
    ],
    "sg:phone":"+1 409 982 4842",
    "sg:postcode":"77642",
    "sg:province":"TX",
    "sg:tags":[
        "organization",
        "welfare"
    ],
    "wof:name":"Hospitality Center",
    "wof:placetype":"venue"
},
  "geometry": {"coordinates":[-93.916802,29.91174],"type":"Point"}
}