{
  "type": "Feature",
  "properties": {
    "iso:country":"US",
    "sg:address":"2737 S Broadway Ave",
    "sg:city":"Tyler",
    "sg:classifiers":[
        {
            "category":"Professional",
            "type":"Services"
        }
    ],
    "sg:phone":"+1 903 595 4458",
    "sg:postcode":"75701",
    "sg:province":"TX",
    "sg:tags":[
        "establishment"
    ],
    "wof:name":"Concentra Advanced Wc Sltns",
    "wof:placetype":"venue"
},
  "geometry": {"coordinates":[-95.300707,32.316283],"type":"Point"}
}