{
  "type": "Feature",
  "properties": {
    "iso:country":"US",
    "sg:address":"1500 Circle Dr",
    "sg:city":"Fort Worth",
    "sg:classifiers":[
        {
            "category":"Education",
            "subcategory":"School",
            "type":"Public Place"
        }
    ],
    "sg:phone":"+1 817 531 7770",
    "sg:postcode":"76119",
    "sg:province":"TX",
    "wof:name":"New Lives School",
    "wof:placetype":"venue"
},
  "geometry": {"coordinates":[-97.303674,32.672579],"type":"Point"}
}