{
  "type": "Feature",
  "properties": {
    "iso:country":"US",
    "sg:address":"8205 Martin L King Blvd",
    "sg:city":"Lubbock",
    "sg:classifiers":[
        {
            "category":"Building & Trades",
            "subcategory":"Construction",
            "type":"Services"
        }
    ],
    "sg:phone":"+1 806 785 5166",
    "sg:postcode":"79404",
    "sg:province":"TX",
    "sg:tags":[
        "roofing",
        "contractor"
    ],
    "wof:name":"Lubbock Roofing & Siding",
    "wof:placetype":"venue"
},
  "geometry": {"coordinates":[-101.81835,33.5216],"type":"Point"}
}