{
  "type": "Feature",
  "properties": {
    "iso:country":"US",
    "sg:address":"2373 E Hwy 35",
    "sg:city":"Angleton",
    "sg:classifiers":[
        {
            "category":"Utilities",
            "subcategory":"Water",
            "type":"Services"
        }
    ],
    "sg:phone":"+1 979 848 1583",
    "sg:postcode":"77515",
    "sg:province":"TX",
    "sg:tags":[
        "company",
        "sewage"
    ],
    "wof:name":"Angleton Parks Dept",
    "wof:placetype":"venue"
},
  "geometry": {"coordinates":[-95.402654,29.193106],"type":"Point"}
}