{
  "type": "Feature",
  "properties": {
    "iso:country":"US",
    "sg:address":"412A N Sam Houston Pkwy E",
    "sg:city":"Houston",
    "sg:classifiers":[
        {
            "category":"Health Services",
            "subcategory":"Doctor",
            "type":"Services"
        },
        {
            "category":"Health Services",
            "subcategory":"Clinic",
            "type":"Services"
        },
        {
            "category":"Social Services",
            "subcategory":"Adult Care",
            "type":"Services"
        }
    ],
    "sg:phone":"+1 281 847 5364",
    "sg:postcode":"77060",
    "sg:province":"TX",
    "sg:tags":[
        "physician",
        "medical",
        "centers-adult",
        "surgeon",
        "day"
    ],
    "wof:name":"Vitality Health Services Inc",
    "wof:placetype":"venue"
},
  "geometry": {"coordinates":[-95.39587899999999,29.938608],"type":"Point"}
}