{
  "type": "Feature",
  "properties": {
    "iso:country":"US",
    "sg:address":"5509 Cunningham Dr",
    "sg:city":"Pearland",
    "sg:classifiers":[
        {
            "category":"Health Services",
            "subcategory":"Health Practitioner",
            "type":"Services"
        }
    ],
    "sg:phone":"+1 281 412 0636",
    "sg:postcode":"77581",
    "sg:province":"TX",
    "wof:name":"Michael L Markowitz",
    "wof:placetype":"venue"
},
  "geometry": {"coordinates":[-95.30393100000001,29.564149],"type":"Point"}
}