{
  "type": "Feature",
  "properties": {
    "iso:country":"US",
    "sg:address":"2008 Pearl St",
    "sg:city":"Dayton",
    "sg:classifiers":[
        {
            "category":"Professional",
            "type":"Services"
        }
    ],
    "sg:phone":"+1 936 257 1097",
    "sg:postcode":"77535",
    "sg:province":"TX",
    "wof:name":"Stephnies Hmade Scnted Candles",
    "wof:placetype":"venue"
},
  "geometry": {"coordinates":[-94.889793,30.062009],"type":"Point"}
}