{
  "type": "Feature",
  "properties": {
    "iso:country":"US",
    "sg:address":"1345 Brownfield Rd",
    "sg:city":"Brownsville",
    "sg:classifiers":[
        {
            "category":"Shopping",
            "subcategory":"Clothing, Apparel, & Fashions",
            "type":"Retail Goods"
        }
    ],
    "sg:phone":"+1 956 548 9495",
    "sg:postcode":"78520",
    "sg:province":"TX",
    "wof:name":"Margaret Fashions",
    "wof:placetype":"venue"
},
  "geometry": {"coordinates":[-97.512154,25.929846],"type":"Point"}
}