{
  "type": "Feature",
  "properties": {
    "iso:country":"US",
    "sg:address":"927 E Pioneer Dr",
    "sg:city":"Irving",
    "sg:classifiers":[
        {
            "category":"Professional",
            "subcategory":"Accounting & Tax Preparation",
            "type":"Services"
        }
    ],
    "sg:phone":"+1 972 445 1243",
    "sg:postcode":"75061",
    "sg:province":"TX",
    "sg:tags":[
        "return"
    ],
    "wof:name":"MI Pueblo Services Inc",
    "wof:placetype":"venue"
},
  "geometry": {"coordinates":[-96.934668,32.8177],"type":"Point"}
}