{
  "type": "Feature",
  "properties": {
    "iso:country":"US",
    "sg:address":"403 S Cuyler St",
    "sg:city":"Pampa",
    "sg:classifiers":[
        {
            "category":"Restaurant",
            "type":"Food & Drink"
        }
    ],
    "sg:phone":"+1 806 669 2061",
    "sg:postcode":"79065",
    "sg:province":"TX",
    "sg:tags":[
        "eating"
    ],
    "wof:name":"Lampliter Chinese Restaurant",
    "wof:placetype":"venue"
},
  "geometry": {"coordinates":[-100.959469,35.533081],"type":"Point"}
}