{
  "type": "Feature",
  "properties": {
    "iso:country":"US",
    "sg:address":"310 S Main St",
    "sg:city":"Weatherford",
    "sg:classifiers":[
        {
            "category":"Food & Beverages",
            "subcategory":"Bakery",
            "type":"Retail Goods"
        }
    ],
    "sg:phone":"+1 817 594 2902",
    "sg:postcode":"76086",
    "sg:province":"TX",
    "sg:tags":[
        "baker"
    ],
    "wof:name":"Mrs Baird's Bakeries Inc",
    "wof:placetype":"venue"
},
  "geometry": {"coordinates":[-97.79745,32.75624],"type":"Point"}
}