{
  "type": "Feature",
  "properties": {
    "iso:country":"US",
    "sg:address":"311 Kerens St",
    "sg:city":"Nevada",
    "sg:classifiers":[
        {
            "category":"Restaurant",
            "type":"Food & Drink"
        }
    ],
    "sg:phone":"+1 972 843 0277",
    "sg:postcode":"75173",
    "sg:province":"TX",
    "sg:tags":[
        "eating"
    ],
    "wof:name":"MI Ranchito",
    "wof:placetype":"venue"
},
  "geometry": {"coordinates":[-96.372225,33.038299],"type":"Point"}
}