{
  "type": "Feature",
  "properties": {
    "iso:country":"US",
    "sg:address":"1226 Heppner Dr",
    "sg:city":"Cedar Park",
    "sg:classifiers":[
        {
            "category":"Professional",
            "subcategory":"Management & Consulting",
            "type":"Services"
        }
    ],
    "sg:phone":"+1 512 335 3112",
    "sg:postcode":"78613",
    "sg:province":"TX",
    "sg:tags":[
        "business"
    ],
    "wof:name":"Ilseng Engineering & Consultin",
    "wof:placetype":"venue"
},
  "geometry": {"coordinates":[-97.827119,30.465742],"type":"Point"}
}