{
  "type": "Feature",
  "properties": {
    "iso:country":"US",
    "sg:address":"919 Fairway Dr",
    "sg:city":"Duncanville",
    "sg:classifiers":[
        {
            "category":"Building & Trades",
            "subcategory":"Construction",
            "type":"Services"
        }
    ],
    "sg:phone":"+1 972 709 2892",
    "sg:postcode":"75137",
    "sg:province":"TX",
    "sg:tags":[
        "hanging",
        "contractor"
    ],
    "wof:name":"Vf Painting",
    "wof:placetype":"venue"
},
  "geometry": {"coordinates":[-96.89027400000001,32.624343],"type":"Point"}
}