{
  "type": "Feature",
  "properties": {
    "iso:country":"US",
    "sg:address":"2510 Burning Trail St",
    "sg:city":"San Antonio",
    "sg:classifiers":[
        {
            "category":"Insurance",
            "subcategory":"Insurance Agent",
            "type":"Services"
        }
    ],
    "sg:phone":"+1 210 545 3343",
    "sg:postcode":"78232",
    "sg:province":"TX",
    "wof:name":"Agent Working From Home",
    "wof:placetype":"venue"
},
  "geometry": {"coordinates":[-98.451173,29.570715],"type":"Point"}
}