{
  "type": "Feature",
  "properties": {
    "iso:country":"US",
    "sg:address":"6211 Royalton St",
    "sg:city":"Houston",
    "sg:classifiers":[
        {
            "category":"Wholesale",
            "subcategory":"Machinery & Supplies",
            "type":"Manufacturing & Wholesale Goods"
        },
        {
            "category":"Retail",
            "subcategory":"Repair Shop",
            "type":"Services"
        }
    ],
    "sg:phone":"+1 713 665 0032",
    "sg:postcode":"77081",
    "sg:province":"TX",
    "sg:tags":[
        "machine",
        "tool",
        "sales",
        "related"
    ],
    "wof:name":"Mill Repair Company",
    "wof:placetype":"venue"
},
  "geometry": {"coordinates":[-95.472104,29.713935],"type":"Point"}
}