{
  "type": "Feature",
  "properties": {
    "iso:country":"US",
    "sg:address":"1711 Delano St",
    "sg:city":"Houston",
    "sg:classifiers":[
        {
            "category":"Professional",
            "subcategory":"Computer Services",
            "type":"Services"
        }
    ],
    "sg:phone":"+1 281 500 1213",
    "sg:postcode":"77003",
    "sg:province":"TX",
    "sg:tags":[
        "repair"
    ],
    "sg:website":"www.digitalcrisis.com",
    "wof:name":"Digital Crisis",
    "wof:placetype":"venue"
},
  "geometry": {"coordinates":[-95.354051,29.741881],"type":"Point"}
}