{
  "type": "Feature",
  "properties": {
    "iso:country":"US",
    "sg:address":"6501 Wesley St",
    "sg:city":"Greenville",
    "sg:classifiers":[
        {
            "category":"Restaurant",
            "type":"Food & Drink"
        }
    ],
    "sg:menulink":"http://www.allmenus.com/tx/greenville/130900-subway/menu/",
    "sg:phone":"+1 903 455 7199",
    "sg:postcode":"75402",
    "sg:province":"TX",
    "sg:tags":[
        "american",
        "sandwich"
    ],
    "wof:name":"Subway",
    "wof:placetype":"venue"
},
  "geometry": {"coordinates":[-96.10958599999999,33.106646],"type":"Point"}
}