{
  "type": "Feature",
  "properties": {
    "iso:country":"US",
    "sg:address":"5319 Evergreen Valley Dr",
    "sg:city":"Humble",
    "sg:classifiers":[
        {
            "category":"Professional",
            "subcategory":"Accounting & Tax Preparation",
            "type":"Services"
        }
    ],
    "sg:phone":"+1 281 360 6574",
    "sg:postcode":"77345",
    "sg:province":"TX",
    "sg:tags":[
        "return"
    ],
    "wof:name":"Tax Focus Inc",
    "wof:placetype":"venue"
},
  "geometry": {"coordinates":[-95.165269,30.066786],"type":"Point"}
}