{
  "type": "Feature",
  "properties": {
    "iso:country":"US",
    "sg:address":"3899 State Hwy 1604",
    "sg:city":"Adkins",
    "sg:classifiers":[
        {
            "category":"Freight",
            "type":"Transportation"
        },
        {
            "category":"Building & Trades",
            "subcategory":"Construction",
            "type":"Services"
        }
    ],
    "sg:phone":"+1 210 649 1878",
    "sg:postcode":"78101",
    "sg:province":"TX",
    "sg:tags":[
        "house",
        "mover",
        "including"
    ],
    "wof:name":"A-O K House Moving",
    "wof:placetype":"venue"
},
  "geometry": {"coordinates":[-98.240058,29.383052],"type":"Point"}
}