{
  "type": "Feature",
  "properties": {
    "iso:country":"US",
    "sg:address":"7 Edgewater Dr",
    "sg:city":"Amarillo",
    "sg:classifiers":[
        {
            "category":"Professional",
            "subcategory":"Business Services",
            "type":"Services"
        }
    ],
    "sg:phone":"+1 806 354 8608",
    "sg:postcode":"79106",
    "sg:province":"TX",
    "sg:tags":[
        "holding"
    ],
    "wof:name":"Jkg-Cdk, Ltd.",
    "wof:placetype":"venue"
},
  "geometry": {"coordinates":[-101.89660600000001,35.20993],"type":"Point"}
}