{
  "type": "Feature",
  "properties": {
    "iso:country":"US",
    "sg:address":"201 S Carver St",
    "sg:city":"Midland",
    "sg:classifiers":[
        {
            "category":"Organizations",
            "subcategory":"Religious Organization",
            "type":"Services"
        }
    ],
    "sg:phone":"+1 432 682 7120",
    "sg:postcode":"79701",
    "sg:province":"TX",
    "sg:tags":[
        "church"
    ],
    "wof:name":"Macadonia Baptist Church",
    "wof:placetype":"venue"
},
  "geometry": {"coordinates":[-102.05892900000001,31.99673],"type":"Point"}
}