{
  "type": "Feature",
  "properties": {
    "iso:country":"US",
    "sg:address":"210 E Texas Blvd",
    "sg:city":"Dalhart",
    "sg:classifiers":[
        {
            "category":"Health Services",
            "subcategory":"Nursing And Care Facility",
            "type":"Services"
        }
    ],
    "sg:phone":"+1 806 244 8555",
    "sg:postcode":"79022",
    "sg:province":"TX",
    "sg:tags":[
        "home",
        "convalescent"
    ],
    "wof:name":"Coon Memorial Nursing Home",
    "wof:placetype":"venue"
},
  "geometry": {"coordinates":[-102.520667,36.052269],"type":"Point"}
}