{
  "type": "Feature",
  "properties": {
    "iso:country":"US",
    "sg:address":"313 College St S",
    "sg:city":"Keller",
    "sg:classifiers":[
        {
            "category":"Building & Trades",
            "subcategory":"Construction",
            "type":"Services"
        }
    ],
    "sg:phone":"+1 817 431 8094",
    "sg:postcode":"76248",
    "sg:province":"TX",
    "sg:tags":[
        "work",
        "sheet",
        "mfg",
        "drop",
        "metal",
        "hammer"
    ],
    "wof:name":"Ace Sheet Metal",
    "wof:placetype":"venue"
},
  "geometry": {"coordinates":[-97.24687400000001,32.930325],"type":"Point"}
}