{
  "type": "Feature",
  "properties": {
    "iso:country":"US",
    "sg:address":"110 McCullough Ave",
    "sg:city":"San Antonio",
    "sg:classifiers":[
        {
            "category":"Social Services",
            "type":"Services"
        }
    ],
    "sg:phone":"+1 210 223 4099",
    "sg:postcode":"78215",
    "sg:province":"TX",
    "sg:tags":[
        "agency",
        "family"
    ],
    "wof:name":"Christian Assistance Ministry",
    "wof:placetype":"venue"
},
  "geometry": {"coordinates":[-98.482671,29.42829],"type":"Point"}
}