{
  "type": "Feature",
  "properties": {
    "iso:country":"US",
    "sg:address":"2404 Golden Ave",
    "sg:city":"Bay City",
    "sg:classifiers":[
        {
            "category":"Utilities",
            "subcategory":"Cable",
            "type":"Services"
        }
    ],
    "sg:phone":"+1 979 245 5511",
    "sg:postcode":"77414",
    "sg:province":"TX",
    "sg:tags":[
        "television"
    ],
    "wof:name":"Northland Cable",
    "wof:placetype":"venue"
},
  "geometry": {"coordinates":[-95.96296100000001,28.997798],"type":"Point"}
}