{
  "type": "Feature",
  "properties": {
    "iso:country":"US",
    "sg:address":"9324 Whittenburg Gate",
    "sg:city":"Dallas",
    "sg:classifiers":[
        {
            "category":"Professional",
            "subcategory":"Management & Consulting",
            "type":"Services"
        }
    ],
    "sg:phone":"+1 214 553 1799",
    "sg:postcode":"75243",
    "sg:province":"TX",
    "sg:tags":[
        "public",
        "relations"
    ],
    "wof:name":"Hattie Wayne Public Relations",
    "wof:placetype":"venue"
},
  "geometry": {"coordinates":[-96.76132800000001,32.903891],"type":"Point"}
}