{
  "type": "Feature",
  "properties": {
    "iso:country":"US",
    "sg:address":"1525 N Grand St",
    "sg:city":"Amarillo",
    "sg:classifiers":[
        {
            "category":"Organizations",
            "subcategory":"Religious Organization",
            "type":"Services"
        }
    ],
    "sg:phone":"+1 806 383 5329",
    "sg:postcode":"79107",
    "sg:province":"TX",
    "sg:tags":[
        "church"
    ],
    "wof:name":"Community Of Grace",
    "wof:placetype":"venue"
},
  "geometry": {"coordinates":[-101.795441,35.228691],"type":"Point"}
}