{
  "type": "Feature",
  "properties": {
    "iso:country":"US",
    "sg:address":"2624 Brandywyne Dr",
    "sg:city":"Carrollton",
    "sg:classifiers":[
        {
            "category":"Professional",
            "subcategory":"Advertising",
            "type":"Services"
        }
    ],
    "sg:phone":"+1 972 416 3160",
    "sg:postcode":"75007",
    "sg:province":"TX",
    "sg:tags":[
        "agency"
    ],
    "wof:name":"Richardson Specialty Advrtisng",
    "wof:placetype":"venue"
},
  "geometry": {"coordinates":[-96.863096,32.987628],"type":"Point"}
}