{
  "type": "Feature",
  "properties": {
    "iso:country":"US",
    "sg:address":"400 W Kaufman St",
    "sg:city":"Rockwall",
    "sg:classifiers":[
        {
            "category":"Building & Trades",
            "subcategory":"Construction",
            "type":"Services"
        }
    ],
    "sg:phone":"+1 972 772 3288",
    "sg:postcode":"75087",
    "sg:province":"TX",
    "sg:tags":[
        "home",
        "builder"
    ],
    "wof:name":"Pulte Homes Corp",
    "wof:placetype":"venue"
},
  "geometry": {"coordinates":[-96.463438,32.931795],"type":"Point"}
}