{
  "type": "Feature",
  "properties": {
    "iso:country":"US",
    "sg:address":"4358 McFarland Cir",
    "sg:city":"Orange",
    "sg:classifiers":[
        {
            "category":"Shopping",
            "subcategory":"Computers & Home Electronics",
            "type":"Retail Goods"
        }
    ],
    "sg:phone":"+1 409 745 3589",
    "sg:postcode":"77632",
    "sg:province":"TX",
    "wof:name":"Kestech",
    "wof:placetype":"venue"
},
  "geometry": {"coordinates":[-93.905676,30.133141],"type":"Point"}
}