{
  "type": "Feature",
  "properties": {
    "iso:country":"US",
    "sg:address":"118 Ridgeway Dr",
    "sg:city":"San Marcos",
    "sg:classifiers":[
        {
            "category":"Professional",
            "type":"Services"
        }
    ],
    "sg:phone":"+1 512 392 9230",
    "sg:postcode":"78666",
    "sg:province":"TX",
    "wof:name":"William Hinkson",
    "wof:placetype":"venue"
},
  "geometry": {"coordinates":[-97.946721,29.896056],"type":"Point"}
}