{
  "type": "Feature",
  "properties": {
    "iso:country":"US",
    "sg:address":"2517 Chene Dr",
    "sg:city":"Garland",
    "sg:classifiers":[
        {
            "category":"Wholesale",
            "subcategory":"Electrical",
            "type":"Manufacturing & Wholesale Goods"
        }
    ],
    "sg:phone":"+1 972 414 8542",
    "sg:postcode":"75048",
    "sg:province":"TX",
    "sg:tags":[
        "electronic"
    ],
    "wof:name":"Emtek Electronics Corp",
    "wof:placetype":"venue"
},
  "geometry": {"coordinates":[-96.597392,32.971495],"type":"Point"}
}