{
  "type": "Feature",
  "properties": {
    "iso:country":"US",
    "sg:address":"1217 E Main St",
    "sg:city":"Alice",
    "sg:classifiers":[
        {
            "category":"Restaurant",
            "type":"Food & Drink"
        }
    ],
    "sg:phone":"+1 361 661 0453",
    "sg:postcode":"78332",
    "sg:province":"TX",
    "sg:tags":[
        "style",
        "family"
    ],
    "wof:name":"Danny's Restaurant",
    "wof:placetype":"venue"
},
  "geometry": {"coordinates":[-98.06115200000001,27.753299],"type":"Point"}
}