{
  "type": "Feature",
  "properties": {
    "iso:country":"US",
    "sg:address":"4020 Crestpark Dr",
    "sg:city":"Dallas",
    "sg:classifiers":[
        {
            "category":"Professional",
            "subcategory":"Management & Consulting",
            "type":"Services"
        }
    ],
    "sg:phone":"+1 972 243 8450",
    "sg:postcode":"75244",
    "sg:province":"TX",
    "sg:tags":[
        "business"
    ],
    "wof:name":"Dana K Land",
    "wof:placetype":"venue"
},
  "geometry": {"coordinates":[-96.85152600000001,32.922653],"type":"Point"}
}