{
  "type": "Feature",
  "properties": {
    "iso:country":"US",
    "sg:address":"117 White Oak St",
    "sg:city":"Lockhart",
    "sg:classifiers":[
        {
            "category":"Banks & Credit Unions",
            "subcategory":"Investment Brokerage",
            "type":"Services"
        },
        {
            "category":"Insurance",
            "subcategory":"Hazard Insurance",
            "type":"Services"
        }
    ],
    "sg:phone":"+1 512 376 5141",
    "sg:postcode":"78644",
    "sg:province":"TX",
    "wof:name":"The Insurance Team",
    "wof:placetype":"venue"
},
  "geometry": {"coordinates":[-97.669968,29.873911],"type":"Point"}
}