{
  "type": "Feature",
  "properties": {
    "iso:country":"US",
    "sg:address":"8103 Pampas Cove",
    "sg:city":"Austin",
    "sg:classifiers":[
        {
            "category":"Professional",
            "subcategory":"Business Services",
            "type":"Services"
        }
    ],
    "sg:phone":"+1 512 795 9760",
    "sg:postcode":"78750",
    "sg:province":"TX",
    "wof:name":"Upstream Technology",
    "wof:placetype":"venue"
},
  "geometry": {"coordinates":[-97.80104900000001,30.390003],"type":"Point"}
}