{
  "type": "Feature",
  "properties": {
    "iso:country":"US",
    "sg:address":"5072 W Plano Pkwy Suite 270",
    "sg:city":"Plano",
    "sg:classifiers":[
        {
            "category":"Health Services",
            "subcategory":"Dentist",
            "type":"Services"
        }
    ],
    "sg:phone":"+1 972 267 6244",
    "sg:postcode":"75093",
    "sg:province":"TX",
    "sg:website":"www.dannasmile.com",
    "wof:name":"Jodi D. Danna, DDS",
    "wof:placetype":"venue"
},
  "geometry": {"coordinates":[-96.79943799999999,33.01591],"type":"Point"}
}