{
  "type": "Feature",
  "properties": {
    "iso:country":"US",
    "sg:address":"1601 Lipan Trl",
    "sg:city":"Austin",
    "sg:classifiers":[
        {
            "category":"Health Services",
            "subcategory":"Doctor",
            "type":"Services"
        }
    ],
    "sg:phone":"+1 512 263 4270",
    "sg:postcode":"78733",
    "sg:province":"TX",
    "sg:tags":[
        "clinic"
    ],
    "wof:name":"Westside Clinic Of Chiropratrc",
    "wof:placetype":"venue"
},
  "geometry": {"coordinates":[-97.868759,30.34176],"type":"Point"}
}