{
  "type": "Feature",
  "properties": {
    "iso:country":"US",
    "sg:address":"16602 E Hardy Rd",
    "sg:city":"Houston",
    "sg:classifiers":[
        {
            "category":"Wholesale",
            "subcategory":"Motor Vehicles",
            "type":"Manufacturing & Wholesale Goods"
        }
    ],
    "sg:phone":"+1 281 443 1300",
    "sg:postcode":"77032",
    "sg:province":"TX",
    "sg:tags":[
        "auction",
        "automobile"
    ],
    "wof:name":"Bayou City Auction Pool Inc",
    "wof:placetype":"venue"
},
  "geometry": {"coordinates":[-95.38764999999999,29.963067],"type":"Point"}
}