{
  "type": "Feature",
  "properties": {
    "iso:country":"US",
    "sg:address":"8597 Fm 78",
    "sg:city":"Converse",
    "sg:classifiers":[
        {
            "category":"Autos & Motor Vehicles",
            "subcategory":"Automobile Sales",
            "type":"Retail Goods"
        }
    ],
    "sg:phone":"+1 210 666 2923",
    "sg:postcode":"78109",
    "sg:province":"TX",
    "sg:tags":[
        "car",
        "used"
    ],
    "wof:name":"Auto Xchange",
    "wof:placetype":"venue"
},
  "geometry": {"coordinates":[-98.318956,29.499073],"type":"Point"}
}