{
  "type": "Feature",
  "properties": {
    "iso:country":"US",
    "sg:address":"1044 Woodmere Dr",
    "sg:city":"Lewisville",
    "sg:classifiers":[
        {
            "category":"Building & Trades",
            "subcategory":"Construction",
            "type":"Services"
        }
    ],
    "sg:phone":"+1 972 436 8291",
    "sg:postcode":"75067",
    "sg:province":"TX",
    "sg:tags":[
        "painter"
    ],
    "wof:name":"Mungia Tile & Painting Svc",
    "wof:placetype":"venue"
},
  "geometry": {"coordinates":[-97.020618,33.03215],"type":"Point"}
}