{
  "type": "Feature",
  "properties": {
    "iso:country":"US",
    "sg:address":"2015 Elderoaks Ln",
    "sg:city":"Dallas",
    "sg:classifiers":[
        {
            "category":"Shopping",
            "subcategory":"Clothing, Apparel, & Fashions",
            "type":"Retail Goods"
        }
    ],
    "sg:phone":"+1 214 330 4024",
    "sg:postcode":"75232",
    "sg:province":"TX",
    "wof:name":"C C Fashion Collection",
    "wof:placetype":"venue"
},
  "geometry": {"coordinates":[-96.852419,32.662929],"type":"Point"}
}