{
  "type": "Feature",
  "properties": {
    "iso:country":"US",
    "sg:address":"6942 Casa Loma Ave",
    "sg:city":"Dallas",
    "sg:classifiers":[
        {
            "category":"Manufacturing",
            "subcategory":"Jewelry",
            "type":"Manufacturing & Wholesale Goods"
        }
    ],
    "sg:phone":"+1 214 324 5298",
    "sg:postcode":"75214",
    "sg:province":"TX",
    "sg:tags":[
        "costume",
        "mfg"
    ],
    "wof:name":"City Metal",
    "wof:placetype":"venue"
},
  "geometry": {"coordinates":[-96.739105,32.81291],"type":"Point"}
}