{
  "type": "Feature",
  "properties": {
    "iso:country":"US",
    "sg:address":"1506 Serenade Ln",
    "sg:city":"Dallas",
    "sg:classifiers":[
        {
            "category":"Communications",
            "type":"Services"
        }
    ],
    "sg:phone":"+1 214 376 8150",
    "sg:postcode":"75241",
    "sg:province":"TX",
    "wof:name":"Ray Rich Communications",
    "wof:placetype":"venue"
},
  "geometry": {"coordinates":[-96.798543,32.67708],"type":"Point"}
}