{
  "type": "Feature",
  "properties": {
    "iso:country":"US",
    "sg:address":"2813 Lee St",
    "sg:city":"Greenville",
    "sg:classifiers":[
        {
            "category":"Insurance",
            "subcategory":"Hazard Insurance",
            "type":"Services"
        }
    ],
    "sg:phone":"+1 903 455 7200",
    "sg:postcode":"75401",
    "sg:province":"TX",
    "sg:tags":[
        "bond"
    ],
    "wof:name":"A Plus Bail Bonds",
    "wof:placetype":"venue"
},
  "geometry": {"coordinates":[-96.10905200000001,33.139782],"type":"Point"}
}