{
  "type": "Feature",
  "properties": {
    "iso:country":"US",
    "sg:address":"3020 Legacy Dr",
    "sg:city":"Plano",
    "sg:classifiers":[
        {
            "category":"Professional",
            "subcategory":"Management & Consulting",
            "type":"Services"
        }
    ],
    "sg:phone":"+1 972 818 9283",
    "sg:postcode":"75023",
    "sg:province":"TX",
    "sg:tags":[
        "telecommunication"
    ],
    "wof:name":"Global Air/Wave Communications",
    "wof:placetype":"venue"
},
  "geometry": {"coordinates":[-96.75106100000001,33.07168],"type":"Point"}
}