{
  "type": "Feature",
  "properties": {
    "iso:country":"US",
    "sg:address":"1600 Delta Dr",
    "sg:city":"El Paso",
    "sg:classifiers":[
        {
            "category":"Wholesale",
            "subcategory":"Durable Goods & Equipment",
            "type":"Manufacturing & Wholesale Goods"
        }
    ],
    "sg:phone":"+1 915 532 8956",
    "sg:postcode":"79901",
    "sg:province":"TX",
    "sg:tags":[
        "exporter"
    ],
    "wof:name":"JFGM Exports",
    "wof:placetype":"venue"
},
  "geometry": {"coordinates":[-106.473687,31.758557],"type":"Point"}
}