{
  "type": "Feature",
  "properties": {
    "iso:country":"US",
    "sg:address":"3415 Orchid Ln",
    "sg:city":"Rowlett",
    "sg:classifiers":[
        {
            "category":"Health Services",
            "subcategory":"Clinic",
            "type":"Services"
        }
    ],
    "sg:phone":"+1 972 412 6599",
    "sg:postcode":"75089",
    "sg:province":"TX",
    "sg:tags":[
        "home",
        "care"
    ],
    "wof:name":"Private Home Health Care Inc",
    "wof:placetype":"venue"
},
  "geometry": {"coordinates":[-96.570211,32.915695],"type":"Point"}
}