{
  "type": "Feature",
  "properties": {
    "iso:country":"US",
    "sg:address":"419 W Oak St",
    "sg:city":"Winnie",
    "sg:classifiers":[
        {
            "category":"Organizations",
            "subcategory":"Religious Organization",
            "type":"Services"
        }
    ],
    "sg:phone":"+1 409 296 2271",
    "sg:postcode":"77665",
    "sg:province":"TX",
    "sg:tags":[
        "clergy"
    ],
    "wof:name":"Larry Simon",
    "wof:placetype":"venue"
},
  "geometry": {"coordinates":[-94.388037,29.821586],"type":"Point"}
}