{
  "type": "Feature",
  "properties": {
    "iso:country":"US",
    "sg:address":"3019 W 7th St",
    "sg:city":"Plainview",
    "sg:classifiers":[
        {
            "category":"Building & Trades",
            "subcategory":"Equipment Rental",
            "type":"Services"
        }
    ],
    "sg:phone":"+1 806 291 8100",
    "sg:postcode":"79072",
    "sg:province":"TX",
    "sg:tags":[
        "leasing"
    ],
    "wof:name":"P & E Leasing Inc",
    "wof:placetype":"venue"
},
  "geometry": {"coordinates":[-101.739604,34.186221],"type":"Point"}
}