{
  "type": "Feature",
  "properties": {
    "iso:country":"US",
    "sg:address":"5007 Jefferson Dr",
    "sg:city":"Garland",
    "sg:classifiers":[
        {
            "category":"Shopping",
            "subcategory":"Clothing, Apparel, & Fashions",
            "type":"Retail Goods"
        }
    ],
    "sg:phone":"+1 972 495 3378",
    "sg:postcode":"75048",
    "sg:province":"TX",
    "wof:name":"Brides On A Budget",
    "wof:placetype":"venue"
},
  "geometry": {"coordinates":[-96.60727,32.970061],"type":"Point"}
}