{
  "type": "Feature",
  "properties": {
    "iso:country":"US",
    "sg:address":"1802 N Osage St",
    "sg:city":"Amarillo",
    "sg:classifiers":[
        {
            "category":"Building & Trades",
            "subcategory":"Construction",
            "type":"Services"
        }
    ],
    "sg:phone":"+1 806 381 9404",
    "sg:postcode":"79107",
    "sg:province":"TX",
    "sg:tags":[
        "house"
    ],
    "wof:name":"Ra Grim Builder",
    "wof:placetype":"venue"
},
  "geometry": {"coordinates":[-101.81259799999999,35.234791],"type":"Point"}
}