{
  "type": "Feature",
  "properties": {
    "iso:country":"US",
    "sg:address":"1125 Legacy Dr",
    "sg:city":"Frisco",
    "sg:classifiers":[
        {
            "category":"Restaurant",
            "type":"Food & Drink"
        }
    ],
    "sg:menulink":"http://www.allmenus.com/tx/mckinney/12589-cantina-laredo/menu/",
    "sg:phone":"+1 214 618 9860",
    "sg:postcode":"75034",
    "sg:province":"TX",
    "sg:tags":[
        "mexican"
    ],
    "wof:name":"Cantina Laredo",
    "wof:placetype":"venue"
},
  "geometry": {"coordinates":[-96.839308,33.087894],"type":"Point"}
}