{
  "type": "Feature",
  "properties": {
    "iso:country":"US",
    "sg:address":"4275 Gate Crst",
    "sg:city":"San Antonio",
    "sg:classifiers":[
        {
            "category":"Professional",
            "type":"Services"
        }
    ],
    "sg:phone":"+1 210 590 2758",
    "sg:postcode":"78217",
    "sg:province":"TX",
    "sg:tags":[
        "establishment"
    ],
    "wof:name":"Windsor International",
    "wof:placetype":"venue"
},
  "geometry": {"coordinates":[-98.409926,29.521852],"type":"Point"}
}