{
  "type": "Feature",
  "properties": {
    "iso:country":"US",
    "sg:address":"5440 Bettes Ln",
    "sg:city":"Beaumont",
    "sg:classifiers":[
        {
            "category":"Personal",
            "subcategory":"Beauty Salon",
            "type":"Services"
        }
    ],
    "sg:phone":"+1 409 892 0632",
    "sg:postcode":"77708",
    "sg:province":"TX",
    "sg:tags":[
        "shop"
    ],
    "wof:name":"Tops & Nails By Laura",
    "wof:placetype":"venue"
},
  "geometry": {"coordinates":[-94.145286,30.129166],"type":"Point"}
}