{
  "type": "Feature",
  "properties": {
    "iso:country":"US",
    "sg:address":"310 Sorrelwood Dr",
    "sg:city":"League City",
    "sg:classifiers":[
        {
            "category":"Wholesale",
            "subcategory":"Machinery & Supplies",
            "type":"Manufacturing & Wholesale Goods"
        }
    ],
    "sg:phone":"+1 281 334 2953",
    "sg:postcode":"77573",
    "sg:province":"TX",
    "sg:tags":[
        "equipment",
        "irrigation",
        "system"
    ],
    "wof:name":"Gulf Coast Sprinkler Service",
    "wof:placetype":"venue"
},
  "geometry": {"coordinates":[-95.052639,29.518774],"type":"Point"}
}