{
  "type": "Feature",
  "properties": {
    "iso:country":"US",
    "sg:address":"1025 W Hebron Pkwy",
    "sg:city":"Carrollton",
    "sg:classifiers":[
        {
            "category":"Restaurant",
            "type":"Food & Drink"
        }
    ],
    "sg:phone":"+1 972 939 4888",
    "sg:postcode":"75010",
    "sg:province":"TX",
    "sg:tags":[
        "pizza"
    ],
    "sg:website":"www.cicispizza.com",
    "wof:name":"Cici's Pizza",
    "wof:placetype":"venue"
},
  "geometry": {"coordinates":[-96.91660299999999,33.0205],"type":"Point"}
}