{
  "type": "Feature",
  "properties": {
    "iso:country":"US",
    "sg:address":"3316 Claymore Dr",
    "sg:city":"Plano",
    "sg:classifiers":[
        {
            "category":"Manufacturing",
            "subcategory":"Electronics",
            "type":"Manufacturing & Wholesale Goods"
        }
    ],
    "sg:phone":"+1 972 519 6658",
    "sg:postcode":"75075",
    "sg:province":"TX",
    "sg:tags":[
        "apparatus",
        "mfg"
    ],
    "wof:name":"Alcatel USA International Mktg",
    "wof:placetype":"venue"
},
  "geometry": {"coordinates":[-96.75859199999999,33.019845],"type":"Point"}
}