{
  "type": "Feature",
  "properties": {
    "iso:country":"US",
    "sg:address":"730 W Randol Mill Rd",
    "sg:city":"Arlington",
    "sg:classifiers":[
        {
            "category":"Personal",
            "subcategory":"Beauty Salon",
            "type":"Services"
        }
    ],
    "sg:phone":"+1 817 795 3383",
    "sg:postcode":"76012",
    "sg:province":"TX",
    "sg:tags":[
        "shop"
    ],
    "wof:name":"Jolindas Hair Styles",
    "wof:placetype":"venue"
},
  "geometry": {"coordinates":[-97.115542,32.750053],"type":"Point"}
}