{
  "type": "Feature",
  "properties": {
    "iso:country":"US",
    "sg:address":"6313 Airport Fwy",
    "sg:city":"Fort Worth",
    "sg:classifiers":[
        {
            "category":"Wholesale",
            "subcategory":"Stationery",
            "type":"Manufacturing & Wholesale Goods"
        }
    ],
    "sg:phone":"+1 817 831 2225",
    "sg:postcode":"76117",
    "sg:province":"TX",
    "sg:tags":[
        "product",
        "paper"
    ],
    "wof:name":"O-K Paper Center",
    "wof:placetype":"venue"
},
  "geometry": {"coordinates":[-97.247647,32.791705],"type":"Point"}
}