{
  "type": "Feature",
  "properties": {
    "iso:country":"US",
    "sg:address":"329 Highbrook Dr",
    "sg:city":"Richardson",
    "sg:classifiers":[
        {
            "category":"Real Estate",
            "subcategory":"Architect",
            "type":"Services"
        }
    ],
    "sg:phone":"+1 972 238 7411",
    "sg:postcode":"75080",
    "sg:province":"TX",
    "sg:tags":[
        "architectural"
    ],
    "wof:name":"Bob Nelson & Assoc",
    "wof:placetype":"venue"
},
  "geometry": {"coordinates":[-96.72049800000001,32.995845],"type":"Point"}
}