{
  "type": "Feature",
  "properties": {
    "iso:country":"US",
    "sg:address":"3215 Garden Brook Dr",
    "sg:city":"Dallas",
    "sg:classifiers":[
        {
            "category":"Autos & Motor Vehicles",
            "subcategory":"Automobile Sales",
            "type":"Retail Goods"
        }
    ],
    "sg:phone":"+1 972 243 4006",
    "sg:postcode":"75234",
    "sg:province":"TX",
    "sg:tags":[
        "car",
        "used",
        "dealer"
    ],
    "wof:name":"Motor Cars Of Dallas",
    "wof:placetype":"venue"
},
  "geometry": {"coordinates":[-96.86569299999999,32.950354],"type":"Point"}
}