{
  "type": "Feature",
  "properties": {
    "iso:country":"US",
    "sg:address":"1700 Research Pkwy",
    "sg:city":"College Station",
    "sg:classifiers":[
        {
            "category":"Wholesale",
            "subcategory":"Petroleum",
            "type":"Manufacturing & Wholesale Goods"
        }
    ],
    "sg:phone":"+1 979 268 5600",
    "sg:postcode":"77845",
    "sg:province":"TX",
    "sg:tags":[
        "product",
        "oil"
    ],
    "wof:name":"Schlumberger",
    "wof:placetype":"venue"
},
  "geometry": {"coordinates":[-96.359466,30.605133],"type":"Point"}
}