{
  "type": "Feature",
  "properties": {
    "iso:country":"US",
    "sg:address":"945 Harvey Ln",
    "sg:city":"Vidor",
    "sg:classifiers":[
        {
            "category":"Building & Trades",
            "subcategory":"Plumbing",
            "type":"Services"
        }
    ],
    "sg:phone":"+1 409 769 9648",
    "sg:postcode":"77662",
    "sg:province":"TX",
    "sg:tags":[
        "septic"
    ],
    "wof:name":"AAA Septic Pumping",
    "wof:placetype":"venue"
},
  "geometry": {"coordinates":[-94.02696299999999,30.138434],"type":"Point"}
}