{
  "type": "Feature",
  "properties": {
    "iso:country":"US",
    "sg:address":"18106 Northwest Fwy",
    "sg:city":"Houston",
    "sg:classifiers":[
        {
            "category":"Retail",
            "subcategory":"Auto Rental",
            "type":"Services"
        }
    ],
    "sg:phone":"+1 281 970 0150",
    "sg:postcode":"77065",
    "sg:province":"TX",
    "sg:tags":[
        "truck"
    ],
    "sg:website":"http://www.ryder.com/",
    "wof:name":"Ryder",
    "wof:placetype":"venue"
},
  "geometry": {"coordinates":[-95.593965,29.897574],"type":"Point"}
}