{
  "type": "Feature",
  "properties": {
    "iso:country":"US",
    "sg:address":"10115 Hidden Meadow Dr",
    "sg:city":"Austin",
    "sg:classifiers":[
        {
            "category":"Home & Garden",
            "subcategory":"Home Furnishings",
            "type":"Retail Goods"
        }
    ],
    "sg:phone":"+1 512 258 0620",
    "sg:postcode":"78750",
    "sg:province":"TX",
    "sg:tags":[
        "quilting"
    ],
    "wof:name":"Texas Quiltery",
    "wof:placetype":"venue"
},
  "geometry": {"coordinates":[-97.797419,30.452717],"type":"Point"}
}