{
  "type": "Feature",
  "properties": {
    "iso:country":"US",
    "sg:address":"20607 Park Bend Dr",
    "sg:city":"Katy",
    "sg:classifiers":[
        {
            "category":"Professional",
            "type":"Services"
        }
    ],
    "sg:phone":"+1 281 578 6010",
    "sg:postcode":"77450",
    "sg:province":"TX",
    "wof:name":"White Bison Energy Inc",
    "wof:placetype":"venue"
},
  "geometry": {"coordinates":[-95.732754,29.765455],"type":"Point"}
}