{
  "type": "Feature",
  "properties": {
    "iso:country":"US",
    "sg:address":"726 Highway 62",
    "sg:city":"Wolfforth",
    "sg:classifiers":[
        {
            "category":"Ice Cream",
            "type":"Food & Drink"
        }
    ],
    "sg:menulink":"http://www.allmenus.com/tx/lubbock/162591-dairy-queen/menu/",
    "sg:phone":"+1 806 866 4864",
    "sg:postcode":"79382",
    "sg:province":"TX",
    "sg:tags":[
        "burger",
        "american"
    ],
    "wof:name":"Dairy Queen",
    "wof:placetype":"venue"
},
  "geometry": {"coordinates":[-102.01540300000001,33.500817],"type":"Point"}
}