{
  "type": "Feature",
  "properties": {
    "iso:country":"US",
    "sg:address":"6344 Telephone Rd",
    "sg:city":"Houston",
    "sg:classifiers":[
        {
            "category":"Banks & Credit Unions",
            "subcategory":"Bank",
            "type":"Services"
        }
    ],
    "sg:phone":"+1 713 454 8360",
    "sg:postcode":"77087",
    "sg:province":"TX",
    "sg:website":"www.bankofamerica.com",
    "wof:name":"Bank of America",
    "wof:placetype":"venue"
},
  "geometry": {"coordinates":[-95.28943700000001,29.67396],"type":"Point"}
}