{
  "type": "Feature",
  "properties": {
    "iso:country":"US",
    "sg:address":"6740 Moss Ln",
    "sg:city":"Fort Worth",
    "sg:classifiers":[
        {
            "category":"Professional",
            "subcategory":"Business Services",
            "type":"Services"
        }
    ],
    "sg:phone":"+1 817 656 5720",
    "sg:postcode":"76180",
    "sg:province":"TX",
    "wof:name":"Health & Home Solutions",
    "wof:placetype":"venue"
},
  "geometry": {"coordinates":[-97.235291,32.887857],"type":"Point"}
}