{
  "type": "Feature",
  "properties": {
    "iso:country":"US",
    "sg:address":"8051 Jetstar Dr",
    "sg:city":"Irving",
    "sg:classifiers":[
        {
            "category":"Building & Trades",
            "subcategory":"Equipment Rental",
            "type":"Services"
        }
    ],
    "sg:phone":"+1 972 570 1118",
    "sg:postcode":"75063",
    "sg:province":"TX",
    "sg:tags":[
        "audio",
        "leasing"
    ],
    "sg:website":"www.andrews-media.com",
    "wof:name":"Andrews Media Svc",
    "wof:placetype":"venue"
},
  "geometry": {"coordinates":[-97.002723,32.915955],"type":"Point"}
}