{
  "type": "Feature",
  "properties": {
    "iso:country":"US",
    "sg:address":"6311 Cupertino Trl",
    "sg:city":"Dallas",
    "sg:classifiers":[
        {
            "category":"Social Services",
            "subcategory":"Child Care",
            "type":"Services"
        }
    ],
    "sg:phone":"+1 972 250 1337",
    "sg:postcode":"75252",
    "sg:province":"TX",
    "sg:tags":[
        "day"
    ],
    "wof:name":"Saiba Joint Venture",
    "wof:placetype":"venue"
},
  "geometry": {"coordinates":[-96.796738,33.0043],"type":"Point"}
}