{
  "type": "Feature",
  "properties": {
    "iso:country":"US",
    "sg:address":"20810 Fernbush Ln",
    "sg:city":"Houston",
    "sg:classifiers":[
        {
            "category":"Professional",
            "subcategory":"Management & Consulting",
            "type":"Services"
        }
    ],
    "sg:phone":"+1 713 691 4365",
    "sg:postcode":"77073",
    "sg:province":"TX",
    "wof:name":"Oakhurst Management Corp",
    "wof:placetype":"venue"
},
  "geometry": {"coordinates":[-95.400696,29.991857],"type":"Point"}
}