{
  "type": "Feature",
  "properties": {
    "iso:country":"US",
    "sg:address":"3520 Guthrie Rd",
    "sg:city":"Garland",
    "sg:classifiers":[
        {
            "category":"Education",
            "subcategory":"School",
            "type":"Public Place"
        }
    ],
    "sg:phone":"+1 972 226 3922",
    "sg:postcode":"75043",
    "sg:province":"TX",
    "wof:name":"Toler Elementary School",
    "wof:placetype":"venue"
},
  "geometry": {"coordinates":[-96.57759900000001,32.8391],"type":"Point"}
}