{
  "type": "Feature",
  "properties": {
    "iso:country":"US",
    "sg:address":"6520 Frint Rd",
    "sg:city":"Beaumont",
    "sg:classifiers":[
        {
            "category":"Professional",
            "type":"Services"
        }
    ],
    "sg:phone":"+1 409 842 6928",
    "sg:postcode":"77705",
    "sg:province":"TX",
    "wof:name":"Tammy Rena Ayres",
    "wof:placetype":"venue"
},
  "geometry": {"coordinates":[-94.168964,30.002216],"type":"Point"}
}