{
  "type": "Feature",
  "properties": {
    "iso:country":"US",
    "sg:address":"9109 Dyer St",
    "sg:city":"El Paso",
    "sg:classifiers":[
        {
            "category":"Shopping",
            "type":"Retail Goods"
        }
    ],
    "sg:phone":"+1 915 759 6007",
    "sg:postcode":"79924",
    "sg:province":"TX",
    "sg:tags":[
        "telephone",
        "cellular"
    ],
    "wof:name":"Southwest Paging",
    "wof:placetype":"venue"
},
  "geometry": {"coordinates":[-106.428042,31.870289],"type":"Point"}
}