{
  "type": "Feature",
  "properties": {
    "iso:country":"US",
    "sg:address":"1807 Bingle Rd",
    "sg:city":"Houston",
    "sg:classifiers":[
        {
            "category":"Local Transit",
            "type":"Transportation"
        }
    ],
    "sg:phone":"+1 713 932 8842",
    "sg:postcode":"77055",
    "sg:province":"TX",
    "sg:tags":[
        "bus",
        "line"
    ],
    "wof:name":"Transportes San Pedro",
    "wof:placetype":"venue"
},
  "geometry": {"coordinates":[-95.500972,29.803865],"type":"Point"}
}