{
  "type": "Feature",
  "properties": {
    "iso:country":"US",
    "sg:address":"516 S Post Oak Ln",
    "sg:city":"Houston",
    "sg:classifiers":[
        {
            "category":"Utilities",
            "subcategory":"Electric",
            "type":"Services"
        }
    ],
    "sg:phone":"+1 713 443 4385",
    "sg:postcode":"77056",
    "sg:province":"TX",
    "wof:name":"ARC Energy LLC",
    "wof:placetype":"venue"
},
  "geometry": {"coordinates":[-95.46346,29.76279],"type":"Point"}
}