{
  "type": "Feature",
  "properties": {
    "iso:country":"US",
    "sg:address":"1532 Ave B",
    "sg:city":"Beaumont",
    "sg:classifiers":[
        {
            "category":"Professional",
            "type":"Services"
        }
    ],
    "sg:phone":"+1 409 833 2224",
    "sg:postcode":"77701",
    "sg:province":"TX",
    "wof:name":"Roberto and Maria Martina Torr",
    "wof:placetype":"venue"
},
  "geometry": {"coordinates":[-94.100515,30.067359],"type":"Point"}
}