{
  "type": "Feature",
  "properties": {
    "iso:country":"US",
    "sg:address":"11203 Salt Cedar Trl",
    "sg:city":"Austin",
    "sg:classifiers":[
        {
            "category":"Professional",
            "type":"Services"
        }
    ],
    "sg:phone":"+1 512 589 5029",
    "sg:postcode":"78750",
    "sg:province":"TX",
    "wof:name":"Freelance Korean Interpreter",
    "wof:placetype":"venue"
},
  "geometry": {"coordinates":[-97.816909,30.461686],"type":"Point"}
}