{
  "type": "Feature",
  "properties": {
    "iso:country":"US",
    "sg:address":"8406 Lyndon Ln",
    "sg:city":"Austin",
    "sg:classifiers":[
        {
            "category":"Building & Trades",
            "subcategory":"Construction",
            "type":"Services"
        }
    ],
    "sg:phone":"+1 512 249 5298",
    "sg:postcode":"78729",
    "sg:province":"TX",
    "sg:tags":[
        "dry wall",
        "contractor"
    ],
    "wof:name":"Quik Finish Dry Wall",
    "wof:placetype":"venue"
},
  "geometry": {"coordinates":[-97.76256600000001,30.459624],"type":"Point"}
}