{
  "type": "Feature",
  "properties": {
    "iso:country":"US",
    "sg:address":"5638 Westheimer Rd",
    "sg:city":"Houston",
    "sg:classifiers":[
        {
            "category":"Health Services",
            "subcategory":"Chiropractor",
            "type":"Services"
        }
    ],
    "sg:phone":"+1 713 993 9449",
    "sg:postcode":"77056",
    "sg:province":"TX",
    "wof:name":"Gaye Shoettle, DC",
    "wof:placetype":"venue"
},
  "geometry": {"coordinates":[-95.47519699999999,29.7381],"type":"Point"}
}