{
  "type": "Feature",
  "properties": {
    "iso:country":"US",
    "sg:address":"5644 Gleneagles Dr",
    "sg:city":"Plano",
    "sg:classifiers":[
        {
            "category":"Professional",
            "subcategory":"Business Services",
            "type":"Services"
        }
    ],
    "sg:phone":"+1 972 403 7007",
    "sg:postcode":"75093",
    "sg:province":"TX",
    "wof:name":"Symbiot Business Group",
    "wof:placetype":"venue"
},
  "geometry": {"coordinates":[-96.81332999999999,33.041917],"type":"Point"}
}