{
  "type": "Feature",
  "properties": {
    "iso:country":"US",
    "sg:address":"12900 Dionysus Dr",
    "sg:city":"Austin",
    "sg:classifiers":[
        {
            "category":"Professional",
            "subcategory":"Art Services",
            "type":"Services"
        }
    ],
    "sg:phone":"+1 512 989 6376",
    "sg:postcode":"78753",
    "sg:province":"TX",
    "sg:tags":[
        "commercial",
        "design"
    ],
    "wof:name":"Just Plain Graphics",
    "wof:placetype":"venue"
},
  "geometry": {"coordinates":[-97.651657,30.400565],"type":"Point"}
}