{
  "type": "Feature",
  "properties": {
    "iso:country":"US",
    "sg:address":"16259 Rutley Cir",
    "sg:city":"Spring",
    "sg:classifiers":[
        {
            "category":"Freight",
            "type":"Transportation"
        }
    ],
    "sg:phone":"+1 281 374 7925",
    "sg:postcode":"77379",
    "sg:province":"TX",
    "sg:tags":[
        "mover"
    ],
    "wof:name":"Daniel Movers",
    "wof:placetype":"venue"
},
  "geometry": {"coordinates":[-95.543217,30.004045],"type":"Point"}
}