{
  "type": "Feature",
  "properties": {
    "iso:country":"US",
    "sg:address":"381 Liberty St",
    "sg:city":"Beaumont",
    "sg:classifiers":[
        {
            "category":"Professional",
            "subcategory":"Lawyer & Legal Services",
            "type":"Services"
        }
    ],
    "sg:phone":"+1 409 838 1871",
    "sg:postcode":"77701",
    "sg:province":"TX",
    "sg:tags":[
        "information",
        "attorney",
        "referral",
        "plan"
    ],
    "wof:name":"Brent Coon & Associates",
    "wof:placetype":"venue"
},
  "geometry": {"coordinates":[-94.100647,30.084136],"type":"Point"}
}