{
  "type": "Feature",
  "properties": {
    "iso:country":"US",
    "sg:address":"14053 Cashel Forest Dr",
    "sg:city":"Houston",
    "sg:classifiers":[
        {
            "category":"Wholesale",
            "subcategory":"Toys & Hobbies",
            "type":"Manufacturing & Wholesale Goods"
        }
    ],
    "sg:phone":"+1 281 583 8356",
    "sg:postcode":"77069",
    "sg:province":"TX",
    "wof:name":"Glorious Scents",
    "wof:placetype":"venue"
},
  "geometry": {"coordinates":[-95.503788,29.986039],"type":"Point"}
}