{
  "type": "Feature",
  "properties": {
    "iso:country":"US",
    "sg:address":"1011 Gibbins Rd",
    "sg:city":"Arlington",
    "sg:classifiers":[
        {
            "category":"Retail",
            "subcategory":"Laundry & Dry Cleaning",
            "type":"Services"
        }
    ],
    "sg:phone":"+1 817 274 1117",
    "sg:postcode":"76011",
    "sg:province":"TX",
    "sg:tags":[
        "laundries-self",
        "operated",
        "washer",
        "dryer",
        "coin"
    ],
    "wof:name":"H O Vu",
    "wof:placetype":"venue"
},
  "geometry": {"coordinates":[-97.11131399999999,32.750331],"type":"Point"}
}