{
  "type": "Feature",
  "properties": {
    "iso:country":"US",
    "sg:address":"7380 State Hwy 105",
    "sg:city":"Beaumont",
    "sg:classifiers":[
        {
            "category":"Restaurant",
            "type":"Food & Drink"
        }
    ],
    "sg:phone":"+1 409 898 1666",
    "sg:postcode":"77713",
    "sg:province":"TX",
    "wof:name":"Jack In The Box",
    "wof:placetype":"venue"
},
  "geometry": {"coordinates":[-94.189211,30.133212],"type":"Point"}
}