{
  "type": "Feature",
  "properties": {
    "iso:country":"US",
    "sg:address":"521 Covey Ln",
    "sg:city":"Mesquite",
    "sg:classifiers":[
        {
            "category":"Building & Trades",
            "subcategory":"Plumbing",
            "type":"Services"
        }
    ],
    "sg:phone":"+1 972 613 2477",
    "sg:postcode":"75150",
    "sg:province":"TX",
    "sg:tags":[
        "fire",
        "sprinkler",
        "install",
        "system"
    ],
    "wof:name":"Quality Autmtc Fire Protection",
    "wof:placetype":"venue"
},
  "geometry": {"coordinates":[-96.60453200000001,32.803948],"type":"Point"}
}