{
  "type": "Feature",
  "properties": {
    "iso:country":"US",
    "sg:address":"2514 Wardmont St",
    "sg:city":"Houston",
    "sg:classifiers":[
        {
            "category":"Building & Trades",
            "subcategory":"Cleaning & Sanitation",
            "type":"Services"
        }
    ],
    "sg:phone":"+1 281 987 9801",
    "sg:postcode":"77093",
    "sg:province":"TX",
    "sg:tags":[
        "maintenance"
    ],
    "wof:name":"Adrianas Maid Service",
    "wof:placetype":"venue"
},
  "geometry": {"coordinates":[-95.34787799999999,29.880417],"type":"Point"}
}