{
  "type": "Feature",
  "properties": {
    "iso:country":"US",
    "sg:address":"1111 Belt Line Rd",
    "sg:city":"Garland",
    "sg:classifiers":[
        {
            "category":"Professional",
            "subcategory":"Lawyer & Legal Services",
            "type":"Services"
        }
    ],
    "sg:phone":"+1 972 494 1373",
    "sg:postcode":"75044",
    "sg:province":"TX",
    "sg:tags":[
        "attorney"
    ],
    "wof:name":"Robert E Young",
    "wof:placetype":"venue"
},
  "geometry": {"coordinates":[-96.644828,32.944324],"type":"Point"}
}