{
  "type": "Feature",
  "properties": {
    "iso:country":"US",
    "sg:address":"717 W Mount Houston Rd",
    "sg:city":"Houston",
    "sg:classifiers":[
        {
            "category":"Personal",
            "subcategory":"Shoe Repair & Shine",
            "type":"Services"
        }
    ],
    "sg:phone":"+1 281 447 6947",
    "sg:postcode":"77038",
    "sg:province":"TX",
    "sg:tags":[
        "parlor",
        "shoeshine"
    ],
    "wof:name":"Anthonys Boot & Shoe Repair",
    "wof:placetype":"venue"
},
  "geometry": {"coordinates":[-95.414117,29.898195],"type":"Point"}
}