{
  "type": "Feature",
  "properties": {
    "iso:country":"US",
    "sg:address":"806 S Twin City Hwy",
    "sg:city":"Nederland",
    "sg:classifiers":[
        {
            "category":"Home & Garden",
            "subcategory":"Household Appliances",
            "type":"Retail Goods"
        }
    ],
    "sg:phone":"+1 409 724 7129",
    "sg:postcode":"77627",
    "sg:province":"TX",
    "wof:name":"Rainbow Center",
    "wof:placetype":"venue"
},
  "geometry": {"coordinates":[-93.98349,29.971817],"type":"Point"}
}