{
  "type": "Feature",
  "properties": {
    "iso:country":"US",
    "sg:address":"4408 Kingswick Dr",
    "sg:city":"Arlington",
    "sg:classifiers":[
        {
            "category":"Professional",
            "type":"Services"
        }
    ],
    "sg:phone":"+1 817 492 4814",
    "sg:postcode":"76016",
    "sg:province":"TX",
    "wof:name":"McConnell Scoping Services",
    "wof:placetype":"venue"
},
  "geometry": {"coordinates":[-97.175871,32.6947],"type":"Point"}
}