{
  "type": "Feature",
  "properties": {
    "iso:country":"US",
    "sg:address":"1744 Norfolk St",
    "sg:city":"Houston",
    "sg:classifiers":[
        {
            "category":"Professional",
            "subcategory":"Lawyer & Legal Services",
            "type":"Services"
        }
    ],
    "sg:phone":"+1 713 521 9216",
    "sg:postcode":"77098",
    "sg:province":"TX",
    "wof:name":"Glass Greg Atty",
    "wof:placetype":"venue"
},
  "geometry": {"coordinates":[-95.403099,29.7328],"type":"Point"}
}