{
  "type": "Feature",
  "properties": {
    "iso:country":"US",
    "sg:address":"14505 Crystal Ct",
    "sg:city":"Austin",
    "sg:classifiers":[
        {
            "category":"Shopping",
            "subcategory":"Computers & Home Electronics",
            "type":"Retail Goods"
        }
    ],
    "sg:phone":"+1 512 252 2829",
    "sg:postcode":"78728",
    "sg:province":"TX",
    "sg:tags":[
        "software"
    ],
    "wof:name":"Kthree Software Inc",
    "wof:placetype":"venue"
},
  "geometry": {"coordinates":[-97.677076,30.439311],"type":"Point"}
}