{
  "type": "Feature",
  "properties": {
    "iso:country":"US",
    "sg:address":"2812 4th St",
    "sg:city":"Lubbock",
    "sg:classifiers":[
        {
            "category":"Food & Beverages",
            "subcategory":"Specialty",
            "type":"Retail Goods"
        }
    ],
    "sg:phone":"+1 806 765 9193",
    "sg:postcode":"79415",
    "sg:province":"TX",
    "sg:tags":[
        "health",
        "diet"
    ],
    "wof:name":"Lubbock Nutrition Store No 2",
    "wof:placetype":"venue"
},
  "geometry": {"coordinates":[-101.877177,33.592392],"type":"Point"}
}