{
  "type": "Feature",
  "properties": {
    "iso:country":"US",
    "sg:address":"5908 Caracas Dr",
    "sg:city":"Dallas",
    "sg:classifiers":[
        {
            "category":"Education",
            "subcategory":"School",
            "type":"Public Place"
        }
    ],
    "sg:phone":"+1 214 375 8767",
    "sg:postcode":"75232",
    "sg:province":"TX",
    "wof:name":"Language Academy & Guidance",
    "wof:placetype":"venue"
},
  "geometry": {"coordinates":[-96.84538999999999,32.675258],"type":"Point"}
}