{
  "type": "Feature",
  "properties": {
    "iso:country":"US",
    "sg:address":"513 N Walnut St",
    "sg:city":"Roanoke",
    "sg:classifiers":[
        {
            "category":"Building & Trades",
            "subcategory":"Cleaning & Sanitation",
            "type":"Services"
        }
    ],
    "sg:phone":"+1 817 491 3455",
    "sg:postcode":"76262",
    "sg:province":"TX",
    "sg:tags":[
        "maintenance"
    ],
    "wof:name":"We Do Services",
    "wof:placetype":"venue"
},
  "geometry": {"coordinates":[-97.224958,33.001674],"type":"Point"}
}