{
  "type": "Feature",
  "properties": {
    "iso:country":"US",
    "sg:address":"2407 Howard Ln",
    "sg:city":"Austin",
    "sg:classifiers":[
        {
            "category":"Autos & Motor Vehicles",
            "subcategory":"Auto Supplies",
            "type":"Retail Goods"
        }
    ],
    "sg:phone":"+1 512 251 6800",
    "sg:postcode":"78728",
    "sg:province":"TX",
    "sg:tags":[
        "tire"
    ],
    "wof:name":"Tire Centers Inc",
    "wof:placetype":"venue"
},
  "geometry": {"coordinates":[-97.689003,30.436001],"type":"Point"}
}