{
  "type": "Feature",
  "properties": {
    "iso:country":"US",
    "sg:address":"17944 Castle Bend Dr",
    "sg:city":"Dallas",
    "sg:classifiers":[
        {
            "category":"Banks & Credit Unions",
            "subcategory":"Bank",
            "type":"Services"
        }
    ],
    "sg:phone":"+1 214 418 7924",
    "sg:postcode":"75287",
    "sg:province":"TX",
    "sg:tags":[
        "broker",
        "mortgage"
    ],
    "wof:name":"Reverse Mortgage Texas Inc",
    "wof:placetype":"venue"
},
  "geometry": {"coordinates":[-96.8317,32.99486],"type":"Point"}
}