{
  "type": "Feature",
  "properties": {
    "iso:country":"US",
    "sg:address":"1975 Martin Luther King Rd",
    "sg:city":"Beaumont",
    "sg:classifiers":[
        {
            "category":"Autos & Motor Vehicles",
            "subcategory":"Fuel & Gas Station",
            "type":"Retail Goods"
        }
    ],
    "sg:phone":"+1 409 832 4345",
    "sg:postcode":"77713",
    "sg:province":"TX",
    "sg:tags":[
        "convenience",
        "station",
        "store"
    ],
    "wof:name":"Grocery Place",
    "wof:placetype":"venue"
},
  "geometry": {"coordinates":[-94.24739700000001,29.988236],"type":"Point"}
}