{
  "type": "Feature",
  "properties": {
    "iso:country":"US",
    "sg:address":"3889 Dryden Rd",
    "sg:city":"Port Arthur",
    "sg:classifiers":[
        {
            "category":"Building & Trades",
            "subcategory":"Plumbing",
            "type":"Services"
        }
    ],
    "sg:phone":"+1 409 985 4009",
    "sg:postcode":"77642",
    "sg:province":"TX",
    "sg:tags":[
        "contractor"
    ],
    "wof:name":"Taylor Air Conditioning & Htg",
    "wof:placetype":"venue"
},
  "geometry": {"coordinates":[-93.91907999999999,29.911742],"type":"Point"}
}