{
  "type": "Feature",
  "properties": {
    "iso:country":"US",
    "sg:address":"3030 Old State Hwy 146",
    "sg:city":"La Porte",
    "sg:classifiers":[
        {
            "category":"Professional",
            "subcategory":"Computer Services",
            "type":"Services"
        }
    ],
    "sg:phone":"+1 281 471 7237",
    "sg:postcode":"77571",
    "sg:province":"TX",
    "sg:tags":[
        "related"
    ],
    "wof:name":"Wandering Ink",
    "wof:placetype":"venue"
},
  "geometry": {"coordinates":[-95.018551,29.628141],"type":"Point"}
}