{
  "type": "Feature",
  "properties": {
    "iso:country":"US",
    "sg:address":"4 Luau Ln",
    "sg:city":"Rockport",
    "sg:classifiers":[
        {
            "category":"Professional",
            "subcategory":"Art Services",
            "type":"Services"
        }
    ],
    "sg:phone":"+1 361 790 8608",
    "sg:postcode":"78382",
    "sg:province":"TX",
    "sg:tags":[
        "commercial",
        "design"
    ],
    "wof:name":"Laconcha Designs",
    "wof:placetype":"venue"
},
  "geometry": {"coordinates":[-97.02675499999999,28.039147],"type":"Point"}
}