{
  "type": "Feature",
  "properties": {
    "iso:country":"US",
    "sg:address":"5300 Memorial Dr Ste 360",
    "sg:city":"Houston",
    "sg:classifiers":[
        {
            "category":"Banks & Credit Unions",
            "subcategory":"Investment Brokerage",
            "type":"Services"
        },
        {
            "category":"Banks & Credit Unions",
            "subcategory":"Bank",
            "type":"Services"
        },
        {
            "category":"Banks & Credit Unions",
            "subcategory":"Financial Services",
            "type":"Services"
        }
    ],
    "sg:phone":"+1 713 333 4850",
    "sg:postcode":"77007",
    "sg:province":"TX",
    "sg:tags":[
        "retirement",
        "transfer",
        "broker",
        "agent",
        "plan",
        "annuity",
        "stock",
        "insurance",
        "bond"
    ],
    "wof:name":"Mcquilling Brokerage Partners",
    "wof:placetype":"venue"
},
  "geometry": {"coordinates":[-95.41557299999999,29.76173],"type":"Point"}
}