{
  "type": "Feature",
  "properties": {
    "iso:country":"US",
    "sg:address":"4542 E Houston St",
    "sg:city":"San Antonio",
    "sg:classifiers":[
        {
            "category":"Organizations",
            "subcategory":"Religious Organization",
            "type":"Services"
        }
    ],
    "sg:phone":"+1 210 661 3726",
    "sg:postcode":"78220",
    "sg:province":"TX",
    "wof:name":"Peace Lutheran Church",
    "wof:placetype":"venue"
},
  "geometry": {"coordinates":[-98.402699,29.423947],"type":"Point"}
}