{
  "type": "Feature",
  "properties": {
    "iso:country":"US",
    "sg:address":"1606 Old Tract Rd",
    "sg:city":"Pflugerville",
    "sg:classifiers":[
        {
            "category":"Building & Trades",
            "subcategory":"Construction",
            "type":"Services"
        }
    ],
    "sg:phone":"+1 512 990 7854",
    "sg:postcode":"78660",
    "sg:province":"TX",
    "sg:tags":[
        "contractor"
    ],
    "wof:name":"TI Contracting",
    "wof:placetype":"venue"
},
  "geometry": {"coordinates":[-97.60928800000001,30.425449],"type":"Point"}
}