{
  "type": "Feature",
  "properties": {
    "iso:country":"US",
    "sg:address":"6125 I- 20",
    "sg:city":"Fort Worth",
    "sg:classifiers":[
        {
            "category":"Restaurant",
            "type":"Food & Drink"
        }
    ],
    "sg:phone":"+1 817 423 3124",
    "sg:postcode":"76119",
    "sg:province":"TX",
    "wof:name":"Rio Mambo",
    "wof:placetype":"venue"
},
  "geometry": {"coordinates":[-97.240633,32.665789],"type":"Point"}
}