{
  "type": "Feature",
  "properties": {
    "iso:country":"US",
    "sg:address":"2801 Skyline Dr",
    "sg:city":"Mesquite",
    "sg:classifiers":[
        {
            "category":"Organizations",
            "subcategory":"Religious Organization",
            "type":"Services"
        }
    ],
    "sg:phone":"+1 972 288 8341",
    "sg:postcode":"75149",
    "sg:province":"TX",
    "wof:name":"Church of Jesus Christ The",
    "wof:placetype":"venue"
},
  "geometry": {"coordinates":[-96.640675,32.780543],"type":"Point"}
}