{
  "type": "Feature",
  "properties": {
    "iso:country":"US",
    "sg:address":"6617 Airport Blvd",
    "sg:city":"Austin",
    "sg:classifiers":[
        {
            "category":"Shopping",
            "subcategory":"Tobacco",
            "type":"Retail Goods"
        },
        {
            "category":"Bars & Pubs",
            "subcategory":"Hookah Bar",
            "type":"Food & Drink"
        },
        {
            "category":"Restaurant",
            "type":"Food & Drink"
        }
    ],
    "sg:phone":"+1 512 467 2233",
    "sg:postcode":"78752",
    "sg:province":"TX",
    "sg:tags":[
        "shop",
        "middle",
        "eastern"
    ],
    "wof:name":"Yahala Hookah Lounge",
    "wof:placetype":"venue"
},
  "geometry": {"coordinates":[-97.715138,30.3311],"type":"Point"}
}