{
  "type": "Feature",
  "properties": {
    "iso:country":"US",
    "sg:address":"4800 S Riverside Dr",
    "sg:city":"Fort Worth",
    "sg:classifiers":[
        {
            "category":"Organizations",
            "subcategory":"Religious Organization",
            "type":"Services"
        }
    ],
    "sg:phone":"+1 817 535 8631",
    "sg:postcode":"76119",
    "sg:province":"TX",
    "wof:name":"Pilgrim Valy Msnry Bpst Chrch",
    "wof:placetype":"venue"
},
  "geometry": {"coordinates":[-97.300217,32.692266],"type":"Point"}
}