{
  "type": "Feature",
  "properties": {
    "iso:country":"US",
    "sg:address":"884 S Sam Houston Blvd",
    "sg:city":"San Benito",
    "sg:classifiers":[
        {
            "category":"Freight",
            "type":"Transportation"
        }
    ],
    "sg:phone":"+1 956 361 3699",
    "sg:postcode":"78586",
    "sg:province":"TX",
    "sg:tags":[
        "operator",
        "local",
        "trucking"
    ],
    "wof:name":"Giddy Up Delivery Service Inc",
    "wof:placetype":"venue"
},
  "geometry": {"coordinates":[-97.637933,26.125193],"type":"Point"}
}