{
  "type": "Feature",
  "properties": {
    "iso:country":"US",
    "sg:address":"5100 E Grand Ave",
    "sg:city":"Dallas",
    "sg:classifiers":[
        {
            "category":"Home & Garden",
            "subcategory":"Building Materials",
            "type":"Retail Goods"
        }
    ],
    "sg:phone":"+1 214 827 1740",
    "sg:postcode":"75223",
    "sg:province":"TX",
    "sg:tags":[
        "door"
    ],
    "sg:website":"www.aepspan.com",
    "wof:name":"Aep-Span",
    "wof:placetype":"venue"
},
  "geometry": {"coordinates":[-96.752174,32.789181],"type":"Point"}
}