{
  "type": "Feature",
  "properties": {
    "iso:country":"US",
    "sg:address":"150 N Texas Ave",
    "sg:city":"Mercedes",
    "sg:classifiers":[
        {
            "category":"Professional",
            "type":"Services"
        }
    ],
    "sg:phone":"+1 956 565 5997",
    "sg:postcode":"78570",
    "sg:province":"TX",
    "sg:tags":[
        "establishment"
    ],
    "wof:name":"Guadaljara Curios",
    "wof:placetype":"venue"
},
  "geometry": {"coordinates":[-97.913566,26.151826],"type":"Point"}
}