{
  "type": "Feature",
  "properties": {
    "iso:country":"US",
    "sg:address":"555 W Sunset Rd",
    "sg:city":"San Antonio",
    "sg:classifiers":[
        {
            "category":"Freight",
            "type":"Transportation"
        }
    ],
    "sg:phone":"+1 210 824 2307",
    "sg:postcode":"78216",
    "sg:province":"TX",
    "sg:tags":[
        "commercial",
        "storage"
    ],
    "wof:name":"Public Storage Inc",
    "wof:placetype":"venue"
},
  "geometry": {"coordinates":[-98.478962,29.507954],"type":"Point"}
}