{
  "type": "Feature",
  "properties": {
    "iso:country":"US",
    "sg:address":"520 Atascocita Rd",
    "sg:city":"Humble",
    "sg:classifiers":[
        {
            "category":"Personal",
            "subcategory":"Beauty Salon",
            "type":"Services"
        }
    ],
    "sg:phone":"+1 281 441 4636",
    "sg:postcode":"77396",
    "sg:province":"TX",
    "sg:tags":[
        "shop"
    ],
    "wof:name":"Shelleys Beauty Salon",
    "wof:placetype":"venue"
},
  "geometry": {"coordinates":[-95.260058,29.958698],"type":"Point"}
}