{
  "type": "Feature",
  "properties": {
    "iso:country":"US",
    "sg:address":"108 Washington Ave",
    "sg:city":"Anahuac",
    "sg:classifiers":[
        {
            "category":"Personal",
            "subcategory":"Beauty Salon",
            "type":"Services"
        }
    ],
    "sg:phone":"+1 409 267 3696",
    "sg:postcode":"77514",
    "sg:province":"TX",
    "sg:tags":[
        "shop"
    ],
    "wof:name":"Arlette's",
    "wof:placetype":"venue"
},
  "geometry": {"coordinates":[-94.684438,29.772818],"type":"Point"}
}