{
  "type": "Feature",
  "properties": {
    "iso:country":"US",
    "sg:address":"417 Owens St",
    "sg:city":"Houston",
    "sg:classifiers":[
        {
            "category":"Social Services",
            "type":"Services"
        }
    ],
    "sg:phone":"+1 713 673 7116",
    "sg:postcode":"77029",
    "sg:province":"TX",
    "wof:name":"Full Cir Leadership",
    "wof:placetype":"venue"
},
  "geometry": {"coordinates":[-95.254024,29.741067],"type":"Point"}
}