{
  "type": "Feature",
  "properties": {
    "iso:country":"US",
    "sg:address":"1200 E Adams St",
    "sg:city":"Brownsville",
    "sg:classifiers":[
        {
            "category":"Shopping",
            "subcategory":"Pharmacy",
            "type":"Retail Goods"
        }
    ],
    "sg:phone":"+1 956 541 8122",
    "sg:postcode":"78520",
    "sg:province":"TX",
    "wof:name":"Maldonado Pharmacy",
    "wof:placetype":"venue"
},
  "geometry": {"coordinates":[-97.49592199999999,25.901522],"type":"Point"}
}