{
  "type": "Feature",
  "properties": {
    "iso:country":"US",
    "sg:address":"3016 Band Rd",
    "sg:city":"Rosenberg",
    "sg:classifiers":[
        {
            "category":"Restaurant",
            "type":"Food & Drink"
        }
    ],
    "sg:phone":"+1 281 232 8555",
    "sg:postcode":"77471",
    "sg:province":"TX",
    "sg:tags":[
        "eating"
    ],
    "wof:name":"Bob's Taco Station",
    "wof:placetype":"venue"
},
  "geometry": {"coordinates":[-95.82373699999999,29.502235],"type":"Point"}
}