{
  "type": "Feature",
  "properties": {
    "iso:country":"US",
    "sg:address":"1716 State Loop 288",
    "sg:city":"Denton",
    "sg:classifiers":[
        {
            "category":"Restaurant",
            "type":"Food & Drink"
        }
    ],
    "sg:phone":"+1 940 566 2324",
    "sg:postcode":"76205",
    "sg:province":"TX",
    "wof:name":"Popeyes Chicken & Biscuits",
    "wof:placetype":"venue"
},
  "geometry": {"coordinates":[-97.09749600000001,33.192582],"type":"Point"}
}