{
  "type": "Feature",
  "properties": {
    "iso:country":"US",
    "sg:address":"1714 W Avenue E H",
    "sg:city":"Muleshoe",
    "sg:classifiers":[
        {
            "category":"Manufacturing",
            "subcategory":"Food",
            "type":"Manufacturing & Wholesale Goods"
        },
        {
            "category":"Farming",
            "subcategory":"Farm",
            "type":"Manufacturing & Wholesale Goods"
        }
    ],
    "sg:phone":"+1 806 272 4187",
    "sg:postcode":"79347",
    "sg:province":"TX",
    "sg:tags":[
        "corn",
        "product"
    ],
    "sg:website":"http://www.wedelfarms.com",
    "wof:name":"Wedel Farms",
    "wof:placetype":"venue"
},
  "geometry": {"coordinates":[-102.74461100000001,34.232114],"type":"Point"}
}