{
  "type": "Feature",
  "properties": {
    "iso:country":"US",
    "sg:address":"4930 Dacoma St",
    "sg:city":"Houston",
    "sg:classifiers":[
        {
            "category":"Building & Trades",
            "subcategory":"Landscaping Services",
            "type":"Services"
        }
    ],
    "sg:phone":"+1 713 688 2673",
    "sg:postcode":"77092",
    "sg:province":"TX",
    "wof:name":"Core Landscape Group",
    "wof:placetype":"venue"
},
  "geometry": {"coordinates":[-95.46533599999999,29.806937],"type":"Point"}
}