{
  "type": "Feature",
  "properties": {
    "iso:country":"US",
    "sg:address":"10426 Pearl Dr",
    "sg:city":"Houston",
    "sg:classifiers":[
        {
            "category":"Building & Trades",
            "subcategory":"Construction",
            "type":"Services"
        }
    ],
    "sg:phone":"+1 281 469 5173",
    "sg:postcode":"77064",
    "sg:province":"TX",
    "sg:tags":[
        "house"
    ],
    "wof:name":"Christian Gs Construction",
    "wof:placetype":"venue"
},
  "geometry": {"coordinates":[-95.576087,29.899707],"type":"Point"}
}