{
  "type": "Feature",
  "properties": {
    "iso:country":"US",
    "sg:address":"5416 Winton St",
    "sg:city":"Dallas",
    "sg:classifiers":[
        {
            "category":"Professional",
            "subcategory":"Computer Services",
            "type":"Services"
        },
        {
            "category":"Shopping",
            "subcategory":"Computers & Home Electronics",
            "type":"Retail Goods"
        }
    ],
    "sg:phone":"+1 214 887 0405",
    "sg:postcode":"75206",
    "sg:province":"TX",
    "sg:tags":[
        "prepackaged",
        "software",
        "custom"
    ],
    "sg:website":"www.leveltendesign.com",
    "wof:name":"Lorentz Consulting Group LLC",
    "wof:placetype":"venue"
},
  "geometry": {"coordinates":[-96.777052,32.835127],"type":"Point"}
}