{
  "type": "Feature",
  "properties": {
    "iso:country":"US",
    "sg:address":"3304 W Mile 5 Rd",
    "sg:city":"Mission",
    "sg:classifiers":[
        {
            "category":"Personal",
            "subcategory":"Beauty Salon",
            "type":"Services"
        }
    ],
    "sg:phone":"+1 956 584 2475",
    "sg:postcode":"78574",
    "sg:province":"TX",
    "sg:tags":[
        "hair",
        "stylist"
    ],
    "wof:name":"Impression Hair Studio",
    "wof:placetype":"venue"
},
  "geometry": {"coordinates":[-98.35362499999999,26.292676],"type":"Point"}
}