{
  "type": "Feature",
  "properties": {
    "iso:country":"US",
    "sg:address":"460 E 1st St",
    "sg:city":"Groveton",
    "sg:classifiers":[
        {
            "category":"Food & Beverages",
            "subcategory":"Groceries & Convenience Stores",
            "type":"Retail Goods"
        }
    ],
    "sg:phone":"+1 936 642 1120",
    "sg:postcode":"75845",
    "sg:province":"TX",
    "sg:tags":[
        "grocer"
    ],
    "wof:name":"B & B Food Store",
    "wof:placetype":"venue"
},
  "geometry": {"coordinates":[-95.121506,31.052858],"type":"Point"}
}