{
  "type": "Feature",
  "properties": {
    "iso:country":"US",
    "sg:address":"929 Azalia Dr",
    "sg:city":"Lewisville",
    "sg:classifiers":[
        {
            "category":"Professional",
            "subcategory":"Computer Services",
            "type":"Services"
        }
    ],
    "sg:phone":"+1 972 221 7329",
    "sg:postcode":"75067",
    "sg:province":"TX",
    "sg:tags":[
        "programing",
        "custom"
    ],
    "wof:name":"On Target L F Bracken",
    "wof:placetype":"venue"
},
  "geometry": {"coordinates":[-97.031308,33.03266],"type":"Point"}
}