{
  "type": "Feature",
  "properties": {
    "iso:country":"US",
    "sg:address":"115 N 23rd St",
    "sg:city":"Temple",
    "sg:classifiers":[
        {
            "category":"Manufacturing",
            "subcategory":"Apparel",
            "type":"Manufacturing & Wholesale Goods"
        }
    ],
    "sg:phone":"+1 254 791 4739",
    "sg:postcode":"76504",
    "sg:province":"TX",
    "sg:tags":[
        "textile",
        "product",
        "fabricated",
        "mfg"
    ],
    "wof:name":"It Seams Sew Perfect",
    "wof:placetype":"venue"
},
  "geometry": {"coordinates":[-97.352085,31.101991],"type":"Point"}
}