{
  "type": "Feature",
  "properties": {
    "iso:country":"US",
    "sg:address":"213 W Southmore Ave",
    "sg:city":"Pasadena",
    "sg:classifiers":[
        {
            "category":"Professional",
            "subcategory":"Business Services",
            "type":"Services"
        }
    ],
    "sg:phone":"+1 713 920 0845",
    "sg:postcode":"77502",
    "sg:province":"TX",
    "wof:name":"Industrial Marketing and Graph",
    "wof:placetype":"venue"
},
  "geometry": {"coordinates":[-95.212423,29.690712],"type":"Point"}
}