{
  "type": "Feature",
  "properties": {
    "iso:country":"US",
    "sg:address":"503 Uhland Rd",
    "sg:city":"San Marcos",
    "sg:classifiers":[
        {
            "category":"Banks & Credit Unions",
            "subcategory":"Bank",
            "type":"Services"
        }
    ],
    "sg:phone":"+1 512 878 1849",
    "sg:postcode":"78666",
    "sg:province":"TX",
    "sg:tags":[
        "loan",
        "real estate"
    ],
    "wof:name":"Benchmark Mortgage",
    "wof:placetype":"venue"
},
  "geometry": {"coordinates":[-97.91575400000001,29.896488],"type":"Point"}
}