{
  "type": "Feature",
  "properties": {
    "iso:country":"US",
    "sg:address":"5450 N Riverside Dr",
    "sg:city":"Fort Worth",
    "sg:classifiers":[
        {
            "category":"Shopping",
            "subcategory":"Pharmacy",
            "type":"Retail Goods"
        }
    ],
    "sg:phone":"+1 817 850 5000",
    "sg:postcode":"76137",
    "sg:province":"TX",
    "wof:name":"Precision Rx Inc",
    "wof:placetype":"venue"
},
  "geometry": {"coordinates":[-97.30057499999999,32.842121],"type":"Point"}
}