{
  "type": "Feature",
  "properties": {
    "iso:country":"US",
    "sg:address":"4009 Hildring Dr E",
    "sg:city":"Fort Worth",
    "sg:classifiers":[
        {
            "category":"Health Services",
            "subcategory":"Doctor",
            "type":"Services"
        }
    ],
    "sg:phone":"+1 817 924 0944",
    "sg:postcode":"76109",
    "sg:province":"TX",
    "sg:tags":[
        "medical"
    ],
    "wof:name":"R L Stinson Jones MD",
    "wof:placetype":"venue"
},
  "geometry": {"coordinates":[-97.382521,32.688452],"type":"Point"}
}