{
  "type": "Feature",
  "properties": {
    "iso:country":"US",
    "sg:address":"525 Mansfield Rd",
    "sg:city":"Paris",
    "sg:classifiers":[
        {
            "category":"Retail",
            "subcategory":"Repair Shop",
            "type":"Services"
        }
    ],
    "sg:phone":"+1 903 785 5854",
    "sg:postcode":"75462",
    "sg:province":"TX",
    "wof:name":"Frazier Cycles",
    "wof:placetype":"venue"
},
  "geometry": {"coordinates":[-95.48739399999999,33.664763],"type":"Point"}
}