{
  "type": "Feature",
  "properties": {
    "iso:country":"US",
    "sg:address":"14220 Rossiter Ln",
    "sg:city":"Houston",
    "sg:classifiers":[
        {
            "category":"Building & Trades",
            "subcategory":"Construction",
            "type":"Services"
        }
    ],
    "sg:phone":"+1 281 458 1493",
    "sg:postcode":"77049",
    "sg:province":"TX",
    "sg:tags":[
        "carpet",
        "contractor",
        "laying",
        "cleaning",
        "floor"
    ],
    "wof:name":"Ken's Karpet Service",
    "wof:placetype":"venue"
},
  "geometry": {"coordinates":[-95.174786,29.840262],"type":"Point"}
}