{
  "type": "Feature",
  "properties": {
    "iso:country":"US",
    "sg:address":"1504 E Broadway St",
    "sg:city":"Sweetwater",
    "sg:classifiers":[
        {
            "category":"Real Estate",
            "subcategory":"Real Estate Agent",
            "type":"Services"
        }
    ],
    "sg:phone":"+1 325 235 3000",
    "sg:postcode":"79556",
    "sg:province":"TX",
    "wof:name":"Stan Johnson Real Estate",
    "wof:placetype":"venue"
},
  "geometry": {"coordinates":[-100.393123,32.47662],"type":"Point"}
}