{
  "type": "Feature",
  "properties": {
    "iso:country":"US",
    "sg:address":"5522 Falls Rd",
    "sg:city":"Dallas",
    "sg:classifiers":[
        {
            "category":"Wholesale",
            "subcategory":"Electrical",
            "type":"Manufacturing & Wholesale Goods"
        }
    ],
    "sg:phone":"+1 214 368 3440",
    "sg:postcode":"75220",
    "sg:province":"TX",
    "sg:tags":[
        "representative",
        "mfg"
    ],
    "wof:name":"Humphrey Northwick Ltg Group",
    "wof:placetype":"venue"
},
  "geometry": {"coordinates":[-96.81165799999999,32.876982],"type":"Point"}
}