{
  "type": "Feature",
  "properties": {
    "iso:country":"US",
    "sg:address":"10215 Tanner Rd",
    "sg:city":"Houston",
    "sg:classifiers":[
        {
            "category":"Building & Trades",
            "subcategory":"Construction",
            "type":"Services"
        }
    ],
    "sg:phone":"+1 713 466 4737",
    "sg:postcode":"77041",
    "sg:province":"TX",
    "sg:tags":[
        "clearing",
        "land",
        "leveling"
    ],
    "wof:name":"C J & Wc Trucking & Excvtng",
    "wof:placetype":"venue"
},
  "geometry": {"coordinates":[-95.545562,29.85006],"type":"Point"}
}