{
  "type": "Feature",
  "properties": {
    "iso:country":"US",
    "sg:address":"1330 N Town East Blvd",
    "sg:city":"Mesquite",
    "sg:classifiers":[
        {
            "category":"Shopping",
            "subcategory":"Hobbies, Toys, & Games",
            "type":"Retail Goods"
        }
    ],
    "sg:phone":"+1 972 613 9935",
    "sg:postcode":"75150",
    "sg:province":"TX",
    "wof:name":"Kb Toy Works",
    "wof:placetype":"venue"
},
  "geometry": {"coordinates":[-96.615071,32.810671],"type":"Point"}
}