{
  "type": "Feature",
  "properties": {
    "iso:country":"US",
    "sg:address":"3400 Steck Avenue",
    "sg:city":"Austin",
    "sg:classifiers":[
        {
            "category":"Home & Garden",
            "subcategory":"Hardware",
            "type":"Retail Goods"
        }
    ],
    "sg:phone":"+1 512 465 4200",
    "sg:postcode":"78757",
    "sg:province":"TX",
    "sg:tags":[
        "store"
    ],
    "wof:name":"Bmc West Corporation",
    "wof:placetype":"venue"
},
  "geometry": {"coordinates":[-97.740617,30.36746],"type":"Point"}
}