{
  "type": "Feature",
  "properties": {
    "iso:country":"US",
    "sg:address":"4527 Speight Ave",
    "sg:city":"Waco",
    "sg:classifiers":[
        {
            "category":"Banks & Credit Unions",
            "subcategory":"Bank",
            "type":"Services"
        }
    ],
    "sg:phone":"+1 254 754 1168",
    "sg:postcode":"76711",
    "sg:province":"TX",
    "sg:tags":[
        "federal"
    ],
    "wof:name":"WACO Postal Credit Union",
    "wof:placetype":"venue"
},
  "geometry": {"coordinates":[-97.155468,31.513485],"type":"Point"}
}