{
  "type": "Feature",
  "properties": {
    "iso:country":"US",
    "sg:address":"7801 Burns St",
    "sg:city":"Hitchcock",
    "sg:classifiers":[
        {
            "category":"Organizations",
            "subcategory":"Religious Organization",
            "type":"Services"
        }
    ],
    "sg:phone":"+1 409 986 7889",
    "sg:postcode":"77563",
    "sg:province":"TX",
    "sg:tags":[
        "church"
    ],
    "sg:website":"www.trustandobey.org",
    "wof:name":"Gulf Coast Four Square Church",
    "wof:placetype":"venue"
},
  "geometry": {"coordinates":[-95.00916100000001,29.334787],"type":"Point"}
}