{
  "type": "Feature",
  "properties": {
    "iso:country":"US",
    "sg:address":"617 Travis Ave",
    "sg:city":"Fort Worth",
    "sg:classifiers":[
        {
            "category":"Health Services",
            "subcategory":"Doctor",
            "type":"Services"
        }
    ],
    "sg:phone":"+1 817 335 3279",
    "sg:postcode":"76104",
    "sg:province":"TX",
    "sg:tags":[
        "physician",
        "surgeon"
    ],
    "wof:name":"Satya P Kaushik Pa",
    "wof:placetype":"venue"
},
  "geometry": {"coordinates":[-97.332689,32.737528],"type":"Point"}
}