{
  "type": "Feature",
  "properties": {
    "iso:country":"US",
    "sg:address":"618 S Beard Ave",
    "sg:city":"Dumas",
    "sg:classifiers":[
        {
            "category":"Health Services",
            "subcategory":"Doctor",
            "type":"Services"
        }
    ],
    "sg:phone":"+1 806 935 2300",
    "sg:postcode":"79029",
    "sg:province":"TX",
    "sg:tags":[
        "osteopathic"
    ],
    "wof:name":"Price Paul Jr Do",
    "wof:placetype":"venue"
},
  "geometry": {"coordinates":[-101.96780099999999,35.859647],"type":"Point"}
}