{
  "type": "Feature",
  "properties": {
    "iso:country":"US",
    "sg:address":"2839 Timber Ct",
    "sg:city":"Grand Prairie",
    "sg:classifiers":[
        {
            "category":"Banks & Credit Unions",
            "subcategory":"Bank",
            "type":"Services"
        }
    ],
    "sg:phone":"+1 972 988 0160",
    "sg:postcode":"75052",
    "sg:province":"TX",
    "sg:tags":[
        "federal",
        "savings",
        "institution"
    ],
    "wof:name":"Ln Humiston & Co",
    "wof:placetype":"venue"
},
  "geometry": {"coordinates":[-97.05278,32.649494],"type":"Point"}
}