{
  "type": "Feature",
  "properties": {
    "iso:country":"US",
    "sg:address":"116 6 Pines Rd",
    "sg:city":"San Marcos",
    "sg:classifiers":[
        {
            "category":"Retail",
            "subcategory":"Animal Services",
            "type":"Services"
        }
    ],
    "sg:phone":"+1 512 353 4745",
    "sg:postcode":"78666",
    "sg:province":"TX",
    "wof:name":"Critter Sitter",
    "wof:placetype":"venue"
},
  "geometry": {"coordinates":[-97.938998,29.927011],"type":"Point"}
}