{
  "type": "Feature",
  "properties": {
    "iso:country":"US",
    "sg:address":"1613 Brazos Trl",
    "sg:city":"Plano",
    "sg:classifiers":[
        {
            "category":"Manufacturing",
            "subcategory":"Printing",
            "type":"Manufacturing & Wholesale Goods"
        }
    ],
    "sg:phone":"+1 972 423 7490",
    "sg:postcode":"75075",
    "sg:province":"TX",
    "sg:tags":[
        "lithographic",
        "commercial"
    ],
    "wof:name":"Mill Print",
    "wof:placetype":"venue"
},
  "geometry": {"coordinates":[-96.72372799999999,33.020958],"type":"Point"}
}