{
  "type": "Feature",
  "properties": {
    "iso:country":"US",
    "sg:address":"5122 I- 30",
    "sg:city":"Greenville",
    "sg:classifiers":[
        {
            "category":"Banks & Credit Unions",
            "subcategory":"Bank",
            "type":"Services"
        }
    ],
    "sg:phone":"+1 903 454 3393",
    "sg:postcode":"75402",
    "sg:province":"TX",
    "wof:name":"American National Bank",
    "wof:placetype":"venue"
},
  "geometry": {"coordinates":[-96.097292,33.119157],"type":"Point"}
}