{
  "type": "Feature",
  "properties": {
    "iso:country":"US",
    "sg:address":"4303 Stephen St",
    "sg:city":"Grand Prairie",
    "sg:classifiers":[
        {
            "category":"Organizations",
            "subcategory":"Professional Association",
            "type":"Services"
        }
    ],
    "sg:phone":"+1 972 264 3549",
    "sg:postcode":"75052",
    "sg:province":"TX",
    "wof:name":"Naacp Grand Prairie Chptr",
    "wof:placetype":"venue"
},
  "geometry": {"coordinates":[-97.00736999999999,32.666703],"type":"Point"}
}