{
  "type": "Feature",
  "properties": {
    "iso:country":"US",
    "sg:address":"5445 Caruth Haven Ln",
    "sg:city":"Dallas",
    "sg:classifiers":[
        {
            "category":"Professional",
            "subcategory":"Business Services",
            "type":"Services"
        }
    ],
    "sg:phone":"+1 214 459 0818",
    "sg:postcode":"75225",
    "sg:province":"TX",
    "wof:name":"K Lea Design",
    "wof:placetype":"venue"
},
  "geometry": {"coordinates":[-96.776273,32.863924],"type":"Point"}
}