{
  "type": "Feature",
  "properties": {
    "iso:country":"US",
    "sg:address":"2600-2799 N Lamar Blvd Along Lamar, Between 24th & 29th Streets",
    "sg:city":"Austin",
    "sg:classifiers":[
        {
            "category":"Shopping",
            "subcategory":"Pets & Pet Supplies",
            "type":"Retail Goods"
        }
    ],
    "sg:phone":"+1 512 974 6700",
    "sg:postcode":"78705",
    "sg:province":"TX",
    "sg:website":"www.ci.austin.tx.us/parks/dogpar...",
    "wof:name":"Shoal Creek Greenbelt Leash-Free Area",
    "wof:placetype":"venue"
},
  "geometry": {"coordinates":[-97.747209,30.293834],"type":"Point"}
}