{
  "type": "Feature",
  "properties": {
    "iso:country":"US",
    "sg:address":"806 Foxglove Dr",
    "sg:city":"Edna",
    "sg:classifiers":[
        {
            "category":"Professional",
            "type":"Services"
        }
    ],
    "sg:phone":"+1 361 782 0233",
    "sg:postcode":"77957",
    "sg:province":"TX",
    "wof:name":"Home Environmental Servic",
    "wof:placetype":"venue"
},
  "geometry": {"coordinates":[-96.647333,28.964837],"type":"Point"}
}