{
  "type": "Feature",
  "properties": {
    "iso:country":"US",
    "sg:address":"509 FM 148",
    "sg:city":"Terrell",
    "sg:classifiers":[
        {
            "category":"Retail",
            "subcategory":"Veterinary Services",
            "type":"Services"
        }
    ],
    "sg:phone":"+1 972 563 3305",
    "sg:postcode":"75160",
    "sg:province":"TX",
    "wof:name":"Casey M Risinger",
    "wof:placetype":"venue"
},
  "geometry": {"coordinates":[-96.31310499999999,32.72616],"type":"Point"}
}