{
  "type": "Feature",
  "properties": {
    "iso:country":"US",
    "sg:address":"1342 Sunny Glen Pl",
    "sg:city":"Dallas",
    "sg:classifiers":[
        {
            "category":"Shopping",
            "subcategory":"Clothing, Apparel, & Fashions",
            "type":"Retail Goods"
        }
    ],
    "sg:phone":"+1 214 330 1673",
    "sg:postcode":"75232",
    "sg:province":"TX",
    "wof:name":"D Towne",
    "wof:placetype":"venue"
},
  "geometry": {"coordinates":[-96.845417,32.6862],"type":"Point"}
}