{
  "type": "Feature",
  "properties": {
    "iso:country":"US",
    "sg:address":"3205 N Shepherd Dr",
    "sg:city":"Houston",
    "sg:classifiers":[
        {
            "category":"Insurance",
            "subcategory":"Insurance Agent",
            "type":"Services"
        }
    ],
    "sg:phone":"+1 713 864 7721",
    "sg:postcode":"77018",
    "sg:province":"TX",
    "wof:name":"Luttrell Insurance Agency",
    "wof:placetype":"venue"
},
  "geometry": {"coordinates":[-95.410499,29.81684],"type":"Point"}
}