{
  "type": "Feature",
  "properties": {
    "iso:country":"US",
    "sg:address":"10305 Loving Trail Dr",
    "sg:city":"Frisco",
    "sg:classifiers":[
        {
            "category":"Manufacturing",
            "subcategory":"Electronics",
            "type":"Manufacturing & Wholesale Goods"
        },
        {
            "category":"Shopping",
            "subcategory":"Computers & Home Electronics",
            "type":"Retail Goods"
        }
    ],
    "sg:phone":"+1 972 712 7419",
    "sg:postcode":"75035",
    "sg:province":"TX",
    "sg:tags":[
        "equipment",
        "supply",
        "component",
        "electronic",
        "mfg"
    ],
    "wof:name":"Electronics 4 U",
    "wof:placetype":"venue"
},
  "geometry": {"coordinates":[-96.790087,33.120923],"type":"Point"}
}