{
  "type": "Feature",
  "properties": {
    "iso:country":"US",
    "sg:address":"4206 Rainfall Dr",
    "sg:city":"Pasadena",
    "sg:classifiers":[
        {
            "category":"Professional",
            "subcategory":"Management & Consulting",
            "type":"Services"
        }
    ],
    "sg:phone":"+1 281 991 1107",
    "sg:postcode":"77505",
    "sg:province":"TX",
    "sg:tags":[
        "consultant",
        "business"
    ],
    "wof:name":"C T Consultants Inc",
    "wof:placetype":"venue"
},
  "geometry": {"coordinates":[-95.121419,29.646917],"type":"Point"}
}