{
  "type": "Feature",
  "properties": {
    "iso:country":"US",
    "sg:address":"2829 Hurstview Dr",
    "sg:city":"Hurst",
    "sg:classifiers":[
        {
            "category":"Shopping",
            "subcategory":"Gifts & Souvenirs",
            "type":"Retail Goods"
        }
    ],
    "sg:phone":"+1 817 514 7177",
    "sg:postcode":"76054",
    "sg:province":"TX",
    "wof:name":"Treasures To Trinkets",
    "wof:placetype":"venue"
},
  "geometry": {"coordinates":[-97.178507,32.870198],"type":"Point"}
}