{
  "type": "Feature",
  "properties": {
    "iso:country":"US",
    "sg:address":"601 N Pino St",
    "sg:city":"Weslaco",
    "sg:classifiers":[
        {
            "category":"Manufacturing",
            "subcategory":"Food",
            "type":"Manufacturing & Wholesale Goods"
        }
    ],
    "sg:phone":"+1 956 968 2585",
    "sg:postcode":"78596",
    "sg:province":"TX",
    "sg:tags":[
        "mfg",
        "sweet",
        "tortilla",
        "bread"
    ],
    "wof:name":"A Cavazos Sons Inc",
    "wof:placetype":"venue"
},
  "geometry": {"coordinates":[-97.99238099999999,26.167963],"type":"Point"}
}