{
  "type": "Feature",
  "properties": {
    "iso:country":"US",
    "sg:address":"230 Moody St",
    "sg:city":"Sealy",
    "sg:classifiers":[
        {
            "category":"Shopping",
            "subcategory":"Discount & Variety Stores",
            "type":"Retail Goods"
        }
    ],
    "sg:phone":"+1 979 885 7175",
    "sg:postcode":"77474",
    "sg:province":"TX",
    "wof:name":"Dollar General",
    "wof:placetype":"venue"
},
  "geometry": {"coordinates":[-96.153419,29.769314],"type":"Point"}
}