{
  "type": "Feature",
  "properties": {
    "iso:country":"US",
    "sg:address":"2440 W Irving Blvd",
    "sg:city":"Irving",
    "sg:classifiers":[
        {
            "category":"Food & Beverages",
            "subcategory":"Bakery",
            "type":"Retail Goods"
        }
    ],
    "sg:phone":"+1 972 790 1445",
    "sg:postcode":"75061",
    "sg:province":"TX",
    "sg:tags":[
        "doughnut"
    ],
    "wof:name":"Willy's Donut",
    "wof:placetype":"venue"
},
  "geometry": {"coordinates":[-96.97880499999999,32.828878],"type":"Point"}
}