{
  "type": "Feature",
  "properties": {
    "iso:country":"US",
    "sg:address":"1401 Autumn Trl",
    "sg:city":"Lewisville",
    "sg:classifiers":[
        {
            "category":"Manufacturing",
            "subcategory":"Glass & Minerals",
            "type":"Manufacturing & Wholesale Goods"
        }
    ],
    "sg:phone":"+1 972 436 3837",
    "sg:postcode":"75067",
    "sg:province":"TX",
    "sg:tags":[
        "ready",
        "concrete",
        "mfg"
    ],
    "wof:name":"Trinity Industries Inc",
    "wof:placetype":"venue"
},
  "geometry": {"coordinates":[-97.03397,33.019419],"type":"Point"}
}