{
  "type": "Feature",
  "properties": {
    "iso:country":"US",
    "sg:address":"4426 Cedardale Dr",
    "sg:city":"Dallas",
    "sg:classifiers":[
        {
            "category":"Retail",
            "subcategory":"Auto Repair",
            "type":"Services"
        }
    ],
    "sg:phone":"+1 972 225 9642",
    "sg:postcode":"75241",
    "sg:province":"TX",
    "sg:tags":[
        "transmission",
        "horse",
        "training"
    ],
    "wof:name":"Sebastians Enterprise",
    "wof:placetype":"venue"
},
  "geometry": {"coordinates":[-96.747715,32.658016],"type":"Point"}
}