{
  "type": "Feature",
  "properties": {
    "iso:country":"US",
    "sg:address":"510 Old Caney Rd",
    "sg:city":"Wharton",
    "sg:classifiers":[
        {
            "category":"Professional",
            "type":"Services"
        }
    ],
    "sg:phone":"+1 979 531 1161",
    "sg:postcode":"77488",
    "sg:province":"TX",
    "sg:tags":[
        "establishment"
    ],
    "wof:name":"Anadrill Schlumberger",
    "wof:placetype":"venue"
},
  "geometry": {"coordinates":[-96.067217,29.304103],"type":"Point"}
}