{
  "type": "Feature",
  "properties": {
    "iso:country":"US",
    "sg:address":"225 W Oak St",
    "sg:city":"Denton",
    "sg:classifiers":[
        {
            "category":"Professional",
            "subcategory":"Business Services",
            "type":"Services"
        }
    ],
    "sg:phone":"+1 940 387 0580",
    "sg:postcode":"76201",
    "sg:province":"TX",
    "sg:tags":[
        "embroidery"
    ],
    "sg:website":"www.planetpike.com",
    "wof:name":"Loyd's Embroidery",
    "wof:placetype":"venue"
},
  "geometry": {"coordinates":[-97.13442000000001,33.215517],"type":"Point"}
}