{
  "type": "Feature",
  "properties": {
    "iso:country":"US",
    "sg:address":"450 N Sunset Strip St",
    "sg:city":"Kenedy",
    "sg:classifiers":[
        {
            "category":"Shopping",
            "subcategory":"Gifts & Souvenirs",
            "type":"Retail Goods"
        }
    ],
    "sg:phone":"+1 830 583 3056",
    "sg:postcode":"78119",
    "sg:province":"TX",
    "sg:tags":[
        "shop"
    ],
    "wof:name":"Shelby's Gifts",
    "wof:placetype":"venue"
},
  "geometry": {"coordinates":[-97.85891599999999,28.818522],"type":"Point"}
}