{
  "type": "Feature",
  "properties": {
    "iso:country":"US",
    "sg:address":"5215 Sycamore Ave",
    "sg:city":"Pasadena",
    "sg:classifiers":[
        {
            "category":"Professional",
            "subcategory":"Management & Consulting",
            "type":"Services"
        }
    ],
    "sg:phone":"+1 281 487 5417",
    "sg:postcode":"77503",
    "sg:province":"TX",
    "sg:tags":[
        "consultant",
        "traffic",
        "parking"
    ],
    "wof:name":"C J Hensch & Assoc Inc",
    "wof:placetype":"venue"
},
  "geometry": {"coordinates":[-95.16291,29.670612],"type":"Point"}
}