{
  "type": "Feature",
  "properties": {
    "iso:country":"US",
    "sg:address":"5800 Granite Pkwy",
    "sg:city":"Plano",
    "sg:classifiers":[
        {
            "category":"Professional",
            "subcategory":"Computer Services",
            "type":"Services"
        }
    ],
    "sg:phone":"+1 972 987 3000",
    "sg:postcode":"75024",
    "sg:province":"TX",
    "sg:tags":[
        "system",
        "cad"
    ],
    "wof:name":"UGS Corp",
    "wof:placetype":"venue"
},
  "geometry": {"coordinates":[-96.817476,33.087017],"type":"Point"}
}