{
  "type": "Feature",
  "properties": {
    "iso:country":"US",
    "sg:address":"209 Wolf Trl",
    "sg:city":"Wimberley",
    "sg:classifiers":[
        {
            "category":"Retail",
            "subcategory":"Repair Shop",
            "type":"Services"
        }
    ],
    "sg:phone":"+1 512 847 2444",
    "sg:postcode":"78676",
    "sg:province":"TX",
    "sg:tags":[
        "welding"
    ],
    "wof:name":"Dale E Abernathy Welding",
    "wof:placetype":"venue"
},
  "geometry": {"coordinates":[-98.241184,30.006448],"type":"Point"}
}