{
  "type": "Feature",
  "properties": {
    "iso:country":"US",
    "sg:address":"6900 Preston Rd",
    "sg:city":"Plano",
    "sg:classifiers":[
        {
            "category":"Professional",
            "type":"Services"
        }
    ],
    "sg:phone":"+1 972 618 5082",
    "sg:postcode":"75024",
    "sg:province":"TX",
    "wof:name":"Conrad Stamps",
    "wof:placetype":"venue"
},
  "geometry": {"coordinates":[-96.795497,33.071269],"type":"Point"}
}