{
  "type": "Feature",
  "properties": {
    "iso:country":"US",
    "sg:address":"7530 Remcon Cir",
    "sg:city":"El Paso",
    "sg:classifiers":[
        {
            "category":"Travel",
            "subcategory":"Hotels & Motels",
            "type":"Entertainment"
        }
    ],
    "sg:phone":"+1 915 587 9977",
    "sg:postcode":"79912",
    "sg:province":"TX",
    "wof:name":"Red Roof Inns",
    "wof:placetype":"venue"
},
  "geometry": {"coordinates":[-106.56199599999999,31.839399],"type":"Point"}
}