{
  "type": "Feature",
  "properties": {
    "iso:country":"US",
    "sg:address":"11722 Bell Ave",
    "sg:city":"Austin",
    "sg:classifiers":[
        {
            "category":"Retail",
            "subcategory":"Animal Services",
            "type":"Services"
        }
    ],
    "sg:phone":"+1 512 257 0972",
    "sg:postcode":"78759",
    "sg:province":"TX",
    "wof:name":"Northwest Pampered Pet Sitting",
    "wof:placetype":"venue"
},
  "geometry": {"coordinates":[-97.751727,30.418925],"type":"Point"}
}