{
  "type": "Feature",
  "properties": {
    "iso:country":"US",
    "sg:address":"2701 Lake Ville Dr",
    "sg:city":"Flower Mound",
    "sg:classifiers":[
        {
            "category":"Retail",
            "subcategory":"Repair Shop",
            "type":"Services"
        }
    ],
    "sg:phone":"+1 972 874 2532",
    "sg:postcode":"75022",
    "sg:province":"TX",
    "wof:name":"Accent On Clean",
    "wof:placetype":"venue"
},
  "geometry": {"coordinates":[-97.07217,33.00304],"type":"Point"}
}