{
  "type": "Feature",
  "properties": {
    "iso:country":"US",
    "sg:address":"1600 E Sarah Dewitt Dr",
    "sg:city":"Gonzales",
    "sg:classifiers":[
        {
            "category":"Personal",
            "subcategory":"Beauty Salon",
            "type":"Services"
        }
    ],
    "sg:phone":"+1 830 672 2020",
    "sg:postcode":"78629",
    "sg:province":"TX",
    "wof:name":"New Image Salon",
    "wof:placetype":"venue"
},
  "geometry": {"coordinates":[-97.424852,29.512696],"type":"Point"}
}