{
  "type": "Feature",
  "properties": {
    "iso:country":"US",
    "sg:address":"2795 Holly Hall St",
    "sg:city":"Houston",
    "sg:classifiers":[
        {
            "category":"Airline",
            "type":"Transportation"
        }
    ],
    "sg:phone":"+1 713 783 0425",
    "sg:postcode":"77054",
    "sg:province":"TX",
    "sg:tags":[
        "courier",
        "air"
    ],
    "wof:name":"Fedex",
    "wof:placetype":"venue"
},
  "geometry": {"coordinates":[-95.38077199999999,29.686983],"type":"Point"}
}