{
  "type": "Feature",
  "properties": {
    "iso:country":"US",
    "sg:address":"2901 N Capital of Texas Hwy",
    "sg:city":"Austin",
    "sg:classifiers":[
        {
            "category":"Ice Cream",
            "type":"Food & Drink"
        }
    ],
    "sg:phone":"+1 512 327 0939",
    "sg:postcode":"78701",
    "sg:province":"TX",
    "sg:tags":[
        "frozen",
        "yogurt"
    ],
    "wof:name":"Swensen's Ice Cream Restaurant",
    "wof:placetype":"venue"
},
  "geometry": {"coordinates":[-97.743604,30.269853],"type":"Point"}
}