{
  "type": "Feature",
  "properties": {
    "iso:country":"US",
    "sg:address":"24706 I- 45",
    "sg:city":"Spring",
    "sg:classifiers":[
        {
            "category":"Banks & Credit Unions",
            "subcategory":"Bank",
            "type":"Services"
        }
    ],
    "sg:phone":"+1 281 367 8887",
    "sg:postcode":"77386",
    "sg:province":"TX",
    "sg:tags":[
        "loan",
        "real estate"
    ],
    "wof:name":"CMC Mortgage Co",
    "wof:placetype":"venue"
},
  "geometry": {"coordinates":[-95.436134,30.111068],"type":"Point"}
}