{
  "type": "Feature",
  "properties": {
    "iso:country":"US",
    "sg:address":"507 Main St",
    "sg:city":"Texarkana",
    "sg:classifiers":[
        {
            "category":"Health Services",
            "subcategory":"Chiropractor",
            "type":"Services"
        }
    ],
    "sg:phone":"+1 903 794 7981",
    "sg:postcode":"75501",
    "sg:province":"TX",
    "wof:name":"Dr Stolba Chiropractic",
    "wof:placetype":"venue"
},
  "geometry": {"coordinates":[-94.046229,33.4246],"type":"Point"}
}