{
  "type": "Feature",
  "properties": {
    "iso:country":"US",
    "sg:address":"1301 W 38th St Ste 205",
    "sg:city":"Austin",
    "sg:classifiers":[
        {
            "category":"Health Services",
            "subcategory":"Doctor",
            "type":"Services"
        }
    ],
    "sg:phone":"+1 512 451 0161",
    "sg:postcode":"78705",
    "sg:province":"TX",
    "wof:name":"Austin Regional Clinic",
    "wof:placetype":"venue"
},
  "geometry": {"coordinates":[-97.745811,30.306302],"type":"Point"}
}