{
  "type": "Feature",
  "properties": {
    "iso:country":"US",
    "sg:address":"5100 Belt Line Suite 532",
    "sg:city":"Dallas",
    "sg:classifiers":[
        {
            "category":"Travel",
            "subcategory":"Travel Agent",
            "type":"Entertainment"
        }
    ],
    "sg:phone":"+1 972 991 0191",
    "sg:postcode":"75254",
    "sg:province":"TX",
    "sg:website":"www.travelex.com",
    "wof:name":"Travelex Currency Services",
    "wof:placetype":"venue"
},
  "geometry": {"coordinates":[-96.82057399999999,32.951931],"type":"Point"}
}