{
  "type": "Feature",
  "properties": {
    "iso:country":"US",
    "sg:address":"620 Four Oaks Ranch Rd",
    "sg:city":"Vidor",
    "sg:classifiers":[
        {
            "category":"Mining & Drilling",
            "type":"Manufacturing & Wholesale Goods"
        }
    ],
    "sg:phone":"+1 409 786 3433",
    "sg:postcode":"77662",
    "sg:province":"TX",
    "sg:tags":[
        "development",
        "gas",
        "oil",
        "exploration"
    ],
    "wof:name":"Ballard Exploration Company",
    "wof:placetype":"venue"
},
  "geometry": {"coordinates":[-94.09846899999999,30.188221],"type":"Point"}
}