{
  "type": "Feature",
  "properties": {
    "iso:country":"US",
    "sg:address":"2901 Wilcrest Dr",
    "sg:city":"Houston",
    "sg:classifiers":[
        {
            "category":"Professional",
            "subcategory":"Management & Consulting",
            "type":"Services"
        }
    ],
    "sg:phone":"+1 713 647 8324",
    "sg:postcode":"77042",
    "sg:province":"TX",
    "sg:tags":[
        "environmental"
    ],
    "wof:name":"Resource Management Group",
    "wof:placetype":"venue"
},
  "geometry": {"coordinates":[-95.57170499999999,29.733016],"type":"Point"}
}