{
  "type": "Feature",
  "properties": {
    "iso:country":"US",
    "sg:address":"812 W Main St",
    "sg:city":"League City",
    "sg:classifiers":[
        {
            "category":"Building & Trades",
            "subcategory":"Construction",
            "type":"Services"
        }
    ],
    "sg:phone":"+1 281 486 9875",
    "sg:postcode":"77573",
    "sg:province":"TX",
    "sg:tags":[
        "repairing",
        "remodeling",
        "contractor"
    ],
    "wof:name":"H & H Builders",
    "wof:placetype":"venue"
},
  "geometry": {"coordinates":[-95.101833,29.506184],"type":"Point"}
}