{
  "type": "Feature",
  "properties": {
    "iso:country":"US",
    "sg:address":"12989 Jupiter Rd",
    "sg:city":"Dallas",
    "sg:classifiers":[
        {
            "category":"Professional",
            "subcategory":"Computer Services",
            "type":"Services"
        }
    ],
    "sg:phone":"+1 972 475 9459",
    "sg:postcode":"75238",
    "sg:province":"TX",
    "sg:tags":[
        "related"
    ],
    "wof:name":"One Call Computer Services",
    "wof:placetype":"venue"
},
  "geometry": {"coordinates":[-96.683261,32.872865],"type":"Point"}
}