{
  "type": "Feature",
  "properties": {
    "iso:country":"US",
    "sg:address":"800 Vis Valet",
    "sg:city":"San Antonio",
    "sg:classifiers":[
        {
            "category":"Manufacturing",
            "subcategory":"Furniture",
            "type":"Manufacturing & Wholesale Goods"
        }
    ],
    "sg:phone":"+1 210 264 1155",
    "sg:postcode":"78216",
    "sg:province":"TX",
    "sg:tags":[
        "metal",
        "locker",
        "retail",
        "shelving",
        "mfg"
    ],
    "wof:name":"Outlet Lockers & Shelving",
    "wof:placetype":"venue"
},
  "geometry": {"coordinates":[-98.510581,29.55968],"type":"Point"}
}