{
  "type": "Feature",
  "properties": {
    "iso:country":"US",
    "sg:address":"3721 Millet Ave",
    "sg:city":"Fort Worth",
    "sg:classifiers":[
        {
            "category":"Professional",
            "type":"Services"
        }
    ],
    "sg:phone":"+1 817 536 7037",
    "sg:postcode":"76105",
    "sg:province":"TX",
    "wof:name":"Lane's General Svc",
    "wof:placetype":"venue"
},
  "geometry": {"coordinates":[-97.269606,32.722687],"type":"Point"}
}