{
  "type": "Feature",
  "properties": {
    "iso:country":"US",
    "sg:address":"201 E Anaya Rd",
    "sg:city":"Pharr",
    "sg:classifiers":[
        {
            "category":"Manufacturing",
            "subcategory":"Tools & Machinery",
            "type":"Manufacturing & Wholesale Goods"
        }
    ],
    "sg:phone":"+1 956 702 7528",
    "sg:postcode":"78577",
    "sg:province":"TX",
    "sg:tags":[
        "wheelchair",
        "mfg"
    ],
    "wof:name":"Invacare Corporation",
    "wof:placetype":"venue"
},
  "geometry": {"coordinates":[-98.19803,26.108903],"type":"Point"}
}