{
  "type": "Feature",
  "properties": {
    "iso:country":"US",
    "sg:address":"115 W 5th St",
    "sg:city":"Odessa",
    "sg:classifiers":[
        {
            "category":"Professional",
            "subcategory":"Lawyer & Legal Services",
            "type":"Services"
        }
    ],
    "sg:phone":"+1 432 334 6969",
    "sg:postcode":"79761",
    "sg:province":"TX",
    "sg:tags":[
        "attorney"
    ],
    "wof:name":"Holmes Mike",
    "wof:placetype":"venue"
},
  "geometry": {"coordinates":[-102.369749,31.848287],"type":"Point"}
}