{
  "type": "Feature",
  "properties": {
    "iso:country":"US",
    "sg:address":"2005 Dodge Trl",
    "sg:city":"Grand Prairie",
    "sg:classifiers":[
        {
            "category":"Health Services",
            "subcategory":"Medical Lab",
            "type":"Services"
        }
    ],
    "sg:phone":"+1 972 660 4029",
    "sg:postcode":"75052",
    "sg:province":"TX",
    "sg:tags":[
        "laboratory",
        "dental"
    ],
    "wof:name":"Cornerstone Dental Labs",
    "wof:placetype":"venue"
},
  "geometry": {"coordinates":[-97.030995,32.659581],"type":"Point"}
}