{
  "type": "Feature",
  "properties": {
    "iso:country":"US",
    "sg:address":"6008 N O Connor Blvd",
    "sg:city":"Irving",
    "sg:classifiers":[
        {
            "category":"Building & Trades",
            "subcategory":"Landscaping Services",
            "type":"Services"
        }
    ],
    "sg:phone":"+1 972 399 8433",
    "sg:postcode":"75039",
    "sg:province":"TX",
    "wof:name":"Clean Cut Inc",
    "wof:placetype":"venue"
},
  "geometry": {"coordinates":[-96.93387300000001,32.886012],"type":"Point"}
}