{
  "type": "Feature",
  "properties": {
    "iso:country":"US",
    "sg:address":"182 W Sundance Cir",
    "sg:city":"Spring",
    "sg:classifiers":[
        {
            "category":"Professional",
            "subcategory":"Computer Services",
            "type":"Services"
        }
    ],
    "sg:phone":"+1 281 296 0962",
    "sg:postcode":"77382",
    "sg:province":"TX",
    "sg:tags":[
        "related"
    ],
    "wof:name":"Ben W Bender",
    "wof:placetype":"venue"
},
  "geometry": {"coordinates":[-95.55501599999999,30.213708],"type":"Point"}
}