{
  "type": "Feature",
  "properties": {
    "iso:country":"US",
    "sg:address":"108 S Colorado St",
    "sg:city":"Whitney",
    "sg:classifiers":[
        {
            "category":"Health Services",
            "subcategory":"Nursing And Care Facility",
            "type":"Services"
        }
    ],
    "sg:phone":"+1 254 580 9424",
    "sg:postcode":"76692",
    "sg:province":"TX",
    "sg:tags":[
        "home",
        "manages",
        "owns",
        "operates"
    ],
    "wof:name":"Pyramid Health Care Corp",
    "wof:placetype":"venue"
},
  "geometry": {"coordinates":[-97.32233100000001,31.949483],"type":"Point"}
}