{
  "type": "Feature",
  "properties": {
    "iso:country":"US",
    "sg:address":"14695 Brown Rd",
    "sg:city":"Tomball",
    "sg:classifiers":[
        {
            "category":"Home & Garden",
            "subcategory":"Home Furnishings",
            "type":"Retail Goods"
        }
    ],
    "sg:phone":"+1 281 351 5553",
    "sg:postcode":"77377",
    "sg:province":"TX",
    "sg:tags":[
        "venetian",
        "blind"
    ],
    "wof:name":"Action Drapery Inc",
    "wof:placetype":"venue"
},
  "geometry": {"coordinates":[-95.646807,30.101996],"type":"Point"}
}