{
  "type": "Feature",
  "properties": {
    "iso:country":"US",
    "sg:address":"2407 US Hwy 183",
    "sg:city":"Leander",
    "sg:classifiers":[
        {
            "category":"Recreation",
            "subcategory":"Marina",
            "type":"Entertainment"
        }
    ],
    "sg:phone":"+1 512 259 3823",
    "sg:postcode":"78641",
    "sg:province":"TX",
    "sg:tags":[
        "operation",
        "special"
    ],
    "wof:name":"R & K Self Storage",
    "wof:placetype":"venue"
},
  "geometry": {"coordinates":[-97.86165,30.606676],"type":"Point"}
}