{
  "type": "Feature",
  "properties": {
    "iso:country":"US",
    "sg:address":"5090 Tin Top Rd",
    "sg:city":"Weatherford",
    "sg:classifiers":[
        {
            "category":"Coffee & Tea",
            "type":"Food & Drink"
        },
        {
            "category":"Restaurant",
            "type":"Food & Drink"
        }
    ],
    "sg:phone":"+1 817 594 0203",
    "sg:postcode":"76087",
    "sg:province":"TX",
    "sg:tags":[
        "espresso"
    ],
    "wof:name":"Mary's Brazos Cafe",
    "wof:placetype":"venue"
},
  "geometry": {"coordinates":[-97.812825,32.598557],"type":"Point"}
}