{
  "type": "Feature",
  "properties": {
    "iso:country":"US",
    "sg:address":"232 Brandon Ln",
    "sg:city":"Murphy",
    "sg:classifiers":[
        {
            "category":"Building & Trades",
            "subcategory":"Construction",
            "type":"Services"
        }
    ],
    "sg:phone":"+1 972 516 9062",
    "sg:postcode":"75094",
    "sg:province":"TX",
    "sg:tags":[
        "home",
        "builder"
    ],
    "wof:name":"Standard Pacific Homes",
    "wof:placetype":"venue"
},
  "geometry": {"coordinates":[-96.624976,33.015876],"type":"Point"}
}