{
  "type": "Feature",
  "properties": {
    "iso:country":"US",
    "sg:address":"2041 Rose Pointe",
    "sg:city":"Athens",
    "sg:classifiers":[
        {
            "category":"Banks & Credit Unions",
            "subcategory":"Financial Services",
            "type":"Services"
        }
    ],
    "sg:phone":"+1 903 245 4724",
    "sg:postcode":"75752",
    "sg:province":"TX",
    "sg:tags":[
        "investor"
    ],
    "wof:name":"Microshield of E Texas",
    "wof:placetype":"venue"
},
  "geometry": {"coordinates":[-95.780192,32.222595],"type":"Point"}
}