{
  "type": "Feature",
  "properties": {
    "iso:country":"US",
    "sg:address":"1101 N Archer St",
    "sg:city":"Beeville",
    "sg:classifiers":[
        {
            "category":"Personal",
            "subcategory":"Beauty Salon",
            "type":"Services"
        }
    ],
    "sg:phone":"+1 361 358 0188",
    "sg:postcode":"78102",
    "sg:province":"TX",
    "sg:tags":[
        "shop"
    ],
    "wof:name":"Johns Hair Cuttery",
    "wof:placetype":"venue"
},
  "geometry": {"coordinates":[-97.74472,28.415668],"type":"Point"}
}