{
  "type": "Feature",
  "properties": {
    "iso:country":"US",
    "sg:address":"401 Island Ave",
    "sg:city":"Port Isabel",
    "sg:classifiers":[
        {
            "category":"Retail",
            "subcategory":"Repair Shop",
            "type":"Services"
        }
    ],
    "sg:phone":"+1 956 943 4453",
    "sg:postcode":"78578",
    "sg:province":"TX",
    "sg:tags":[
        "cleaning"
    ],
    "wof:name":"Richard Karon",
    "wof:placetype":"venue"
},
  "geometry": {"coordinates":[-97.21960799999999,26.075425],"type":"Point"}
}