{
  "type": "Feature",
  "properties": {
    "iso:country":"US",
    "sg:address":"5411 Golden Stream Dr",
    "sg:city":"Houston",
    "sg:classifiers":[
        {
            "category":"Professional",
            "subcategory":"Lawyer & Legal Services",
            "type":"Services"
        }
    ],
    "sg:phone":"+1 281 440 6900",
    "sg:postcode":"77066",
    "sg:province":"TX",
    "wof:name":"Jennette L Boone Atty",
    "wof:placetype":"venue"
},
  "geometry": {"coordinates":[-95.49856699999999,29.942594],"type":"Point"}
}