{
  "type": "Feature",
  "properties": {
    "iso:country":"US",
    "sg:address":"3601 Fannin St",
    "sg:city":"Houston",
    "sg:classifiers":[
        {
            "category":"Education",
            "subcategory":"Library",
            "type":"Public Place"
        }
    ],
    "sg:phone":"+1 713 522 6363",
    "sg:postcode":"77004",
    "sg:province":"TX",
    "sg:tags":[
        "special",
        "interest"
    ],
    "wof:name":"Hudson Thrall Library",
    "wof:placetype":"venue"
},
  "geometry": {"coordinates":[-95.37867199999999,29.737954],"type":"Point"}
}