{
  "type": "Feature",
  "properties": {
    "iso:country":"US",
    "sg:address":"1090 Rainbow Dr",
    "sg:city":"Spring Branch",
    "sg:classifiers":[
        {
            "category":"Building & Trades",
            "subcategory":"Plumbing",
            "type":"Services"
        }
    ],
    "sg:phone":"+1 830 438 2475",
    "sg:postcode":"78070",
    "sg:province":"TX",
    "wof:name":"Aerohead Service",
    "wof:placetype":"venue"
},
  "geometry": {"coordinates":[-98.412201,29.812401],"type":"Point"}
}