{
  "type": "Feature",
  "properties": {
    "iso:country":"US",
    "sg:address":"915 E Saint Elmo Rd",
    "sg:city":"Austin",
    "sg:classifiers":[
        {
            "category":"Retail",
            "subcategory":"Auto Repair",
            "type":"Services"
        }
    ],
    "sg:phone":"+1 512 280 2955",
    "sg:postcode":"78745",
    "sg:province":"TX",
    "sg:tags":[
        "wrecker"
    ],
    "wof:name":"Autofreight Towing Svc",
    "wof:placetype":"venue"
},
  "geometry": {"coordinates":[-97.75564300000001,30.214203],"type":"Point"}
}