{
  "type": "Feature",
  "properties": {
    "iso:country":"US",
    "sg:address":"205 Pebblebrook St",
    "sg:city":"Arlington",
    "sg:classifiers":[
        {
            "category":"Professional",
            "subcategory":"Computer Services",
            "type":"Services"
        }
    ],
    "sg:phone":"+1 817 226 1923",
    "sg:postcode":"76014",
    "sg:province":"TX",
    "sg:tags":[
        "related"
    ],
    "wof:name":"Crosswind Network Service",
    "wof:placetype":"venue"
},
  "geometry": {"coordinates":[-97.111756,32.702168],"type":"Point"}
}