{
  "type": "Feature",
  "properties": {
    "iso:country":"US",
    "sg:address":"130 E Ulex Ave",
    "sg:city":"Mcallen",
    "sg:classifiers":[
        {
            "category":"Professional",
            "type":"Services"
        }
    ],
    "sg:phone":"+1 956 682 2615",
    "sg:postcode":"78504",
    "sg:province":"TX",
    "sg:tags":[
        "establishment"
    ],
    "wof:name":"Hna Logistics",
    "wof:placetype":"venue"
},
  "geometry": {"coordinates":[-98.21035500000001,26.244532],"type":"Point"}
}