{
  "type": "Feature",
  "properties": {
    "iso:country":"US",
    "sg:address":"383 Olive St",
    "sg:city":"Jasper",
    "sg:classifiers":[
        {
            "category":"Organizations",
            "subcategory":"Religious Organization",
            "type":"Services"
        }
    ],
    "sg:phone":"+1 409 384 8113",
    "sg:postcode":"75951",
    "sg:province":"TX",
    "sg:tags":[
        "church"
    ],
    "wof:name":"Life Tabernacle",
    "wof:placetype":"venue"
},
  "geometry": {"coordinates":[-94.0034,30.925671],"type":"Point"}
}