{
  "type": "Feature",
  "properties": {
    "iso:country":"US",
    "sg:address":"1604 Ennis St",
    "sg:city":"Plainview",
    "sg:classifiers":[
        {
            "category":"Personal",
            "type":"Services"
        }
    ],
    "sg:phone":"+1 806 293 7261",
    "sg:postcode":"79072",
    "sg:province":"TX",
    "wof:name":"Pam Shannon Massage Therapist",
    "wof:placetype":"venue"
},
  "geometry": {"coordinates":[-101.742102,34.199144],"type":"Point"}
}