{
  "type": "Feature",
  "properties": {
    "iso:country":"US",
    "sg:address":"622 Richey St",
    "sg:city":"Pasadena",
    "sg:classifiers":[
        {
            "category":"Building & Trades",
            "subcategory":"Construction",
            "type":"Services"
        }
    ],
    "sg:phone":"+1 713 473 4444",
    "sg:postcode":"77506",
    "sg:province":"TX",
    "sg:tags":[
        "contractor"
    ],
    "wof:name":"Westbranch Roofing",
    "wof:placetype":"venue"
},
  "geometry": {"coordinates":[-95.219928,29.70321],"type":"Point"}
}