{
  "type": "Feature",
  "properties": {
    "iso:country":"US",
    "sg:address":"2753 S Foster Rd",
    "sg:city":"San Antonio",
    "sg:classifiers":[
        {
            "category":"Manufacturing",
            "subcategory":"Chemicals & Compounds",
            "type":"Manufacturing & Wholesale Goods"
        }
    ],
    "sg:phone":"+1 210 648 0189",
    "sg:postcode":"78220",
    "sg:province":"TX",
    "sg:tags":[
        "marking",
        "mfg",
        "product",
        "ink"
    ],
    "wof:name":"Odessa Inkorporated",
    "wof:placetype":"venue"
},
  "geometry": {"coordinates":[-98.360888,29.396792],"type":"Point"}
}