{
  "type": "Feature",
  "properties": {
    "iso:country":"US",
    "sg:address":"1000 Canton Dr",
    "sg:city":"Fort Worth",
    "sg:classifiers":[
        {
            "category":"Professional",
            "subcategory":"Business Services",
            "type":"Services"
        }
    ],
    "sg:phone":"+1 817 516 9229",
    "sg:postcode":"76112",
    "sg:province":"TX",
    "sg:tags":[
        "repossessing"
    ],
    "wof:name":"Sundance Recovery Of Texas",
    "wof:placetype":"venue"
},
  "geometry": {"coordinates":[-97.23012,32.733129],"type":"Point"}
}