{
  "type": "Feature",
  "properties": {
    "iso:country":"US",
    "sg:address":"8360 Spring Valley Rd",
    "sg:city":"Dallas",
    "sg:classifiers":[
        {
            "category":"Retail",
            "subcategory":"Repair Shop",
            "type":"Services"
        }
    ],
    "sg:phone":"+1 469 330 7697",
    "sg:postcode":"75240",
    "sg:province":"TX",
    "wof:name":"Star Quality Cleaning",
    "wof:placetype":"venue"
},
  "geometry": {"coordinates":[-96.758228,32.939974],"type":"Point"}
}