{
  "type": "Feature",
  "properties": {
    "iso:country":"US",
    "sg:address":"1208 Acanthus St",
    "sg:city":"Pflugerville",
    "sg:classifiers":[
        {
            "category":"Home & Garden",
            "subcategory":"Carpets & Floor Coverings",
            "type":"Retail Goods"
        }
    ],
    "sg:phone":"+1 512 252 3596",
    "sg:postcode":"78660",
    "sg:province":"TX",
    "wof:name":"New Century Carpet",
    "wof:placetype":"venue"
},
  "geometry": {"coordinates":[-97.632699,30.460111],"type":"Point"}
}