{
  "type": "Feature",
  "properties": {
    "iso:country":"US",
    "sg:address":"740 N Grand St",
    "sg:city":"Amarillo",
    "sg:classifiers":[
        {
            "category":"Autos & Motor Vehicles",
            "subcategory":"Automobile Sales",
            "type":"Retail Goods"
        }
    ],
    "sg:phone":"+1 806 381 8423",
    "sg:postcode":"79107",
    "sg:province":"TX",
    "sg:tags":[
        "car",
        "used",
        "dealer"
    ],
    "wof:name":"Monterey Auto Sales & Parts",
    "wof:placetype":"venue"
},
  "geometry": {"coordinates":[-101.79535799999999,35.221924],"type":"Point"}
}