{
  "type": "Feature",
  "properties": {
    "iso:country":"US",
    "sg:address":"4465 Sharpsburg Dr",
    "sg:city":"Grand Prairie",
    "sg:classifiers":[
        {
            "category":"Professional",
            "type":"Services"
        }
    ],
    "sg:phone":"+1 972 660 7099",
    "sg:postcode":"75052",
    "sg:province":"TX",
    "wof:name":"Larry W White",
    "wof:placetype":"venue"
},
  "geometry": {"coordinates":[-97.019642,32.662525],"type":"Point"}
}