{
  "type": "Feature",
  "properties": {
    "iso:country":"US",
    "sg:address":"1501 Bayport Blvd",
    "sg:city":"Seabrook",
    "sg:classifiers":[
        {
            "category":"Retail",
            "subcategory":"Auto Repair",
            "type":"Services"
        }
    ],
    "sg:phone":"+1 281 291 9823",
    "sg:postcode":"77586",
    "sg:province":"TX",
    "sg:tags":[
        "general"
    ],
    "wof:name":"Benjamins Auto Service",
    "wof:placetype":"venue"
},
  "geometry": {"coordinates":[-95.02652999999999,29.568286],"type":"Point"}
}