{
  "type": "Feature",
  "properties": {
    "iso:country":"US",
    "sg:address":"6430 Richmond Ave Ste 110",
    "sg:city":"Houston",
    "sg:classifiers":[
        {
            "category":"Health Services",
            "subcategory":"Doctor",
            "type":"Services"
        }
    ],
    "sg:phone":"+1 713 785 6430",
    "sg:postcode":"77057",
    "sg:province":"TX",
    "sg:tags":[
        "surgeon",
        "oral"
    ],
    "sg:website":"www.albriknazarian.com",
    "wof:name":"Nazarian Albrik DDS",
    "wof:placetype":"venue"
},
  "geometry": {"coordinates":[-95.4991,29.731701],"type":"Point"}
}