{
  "type": "Feature",
  "properties": {
    "iso:country":"US",
    "sg:address":"1428 E Irving Blvd",
    "sg:city":"Irving",
    "sg:classifiers":[
        {
            "category":"Autos & Motor Vehicles",
            "subcategory":"Auto Supplies",
            "type":"Retail Goods"
        }
    ],
    "sg:phone":"+1 214 441 0947",
    "sg:postcode":"75060",
    "sg:province":"TX",
    "sg:tags":[
        "tire"
    ],
    "wof:name":"Wills Discount Tire 2",
    "wof:placetype":"venue"
},
  "geometry": {"coordinates":[-96.929046,32.808658],"type":"Point"}
}