{
  "type": "Feature",
  "properties": {
    "iso:country":"US",
    "sg:address":"853 E Milam St",
    "sg:city":"La Grange",
    "sg:classifiers":[
        {
            "category":"Professional",
            "type":"Services"
        }
    ],
    "sg:phone":"+1 979 968 9008",
    "sg:postcode":"78945",
    "sg:province":"TX",
    "wof:name":"I & W Svc",
    "wof:placetype":"venue"
},
  "geometry": {"coordinates":[-96.866288,29.908293],"type":"Point"}
}