{
  "type": "Feature",
  "properties": {
    "iso:country":"US",
    "sg:address":"3320 Westview Dr",
    "sg:city":"Mc Kinney",
    "sg:classifiers":[
        {
            "category":"Restaurant",
            "type":"Food & Drink"
        }
    ],
    "sg:phone":"+1 972 547 0511",
    "sg:postcode":"75070",
    "sg:province":"TX",
    "sg:tags":[
        "eating"
    ],
    "wof:name":"Ricky Rays Famous Bar B Que",
    "wof:placetype":"venue"
},
  "geometry": {"coordinates":[-96.67986399999999,33.167468],"type":"Point"}
}