{
  "type": "Feature",
  "properties": {
    "iso:country":"US",
    "sg:address":"3611 Morriss Rd",
    "sg:city":"Flower Mound",
    "sg:classifiers":[
        {
            "category":"Health Services",
            "subcategory":"Doctor",
            "type":"Services"
        }
    ],
    "sg:phone":"+1 972 874 3776",
    "sg:postcode":"75028",
    "sg:province":"TX",
    "sg:tags":[
        "physician",
        "surgeon"
    ],
    "wof:name":"Modern Medical Clinic",
    "wof:placetype":"venue"
},
  "geometry": {"coordinates":[-97.062422,33.03325],"type":"Point"}
}