{
  "type": "Feature",
  "properties": {
    "iso:country":"US",
    "sg:address":"2105 Desco Dr",
    "sg:city":"Austin",
    "sg:classifiers":[
        {
            "category":"Building & Trades",
            "subcategory":"Equipment Rental",
            "type":"Services"
        }
    ],
    "sg:phone":"+1 512 282 7383",
    "sg:postcode":"78748",
    "sg:province":"TX",
    "wof:name":"A&R Snacks",
    "wof:placetype":"venue"
},
  "geometry": {"coordinates":[-97.835994,30.157857],"type":"Point"}
}