{
  "type": "Feature",
  "properties": {
    "iso:country":"US",
    "sg:address":"109 US Hwy 281",
    "sg:city":"Burnet",
    "sg:classifiers":[
        {
            "category":"Food & Beverages",
            "subcategory":"Groceries & Convenience Stores",
            "type":"Retail Goods"
        }
    ],
    "sg:phone":"+1 512 756 6751",
    "sg:postcode":"78611",
    "sg:province":"TX",
    "wof:name":"7-Eleven",
    "wof:placetype":"venue"
},
  "geometry": {"coordinates":[-98.228663,30.758047],"type":"Point"}
}