{
  "type": "Feature",
  "properties": {
    "iso:country":"US",
    "sg:address":"643 Eastwood Dr",
    "sg:city":"Brownsville",
    "sg:classifiers":[
        {
            "category":"Professional",
            "type":"Services"
        }
    ],
    "sg:phone":"+1 956 550 0748",
    "sg:postcode":"78521",
    "sg:province":"TX",
    "wof:name":"Storytellers & Such",
    "wof:placetype":"venue"
},
  "geometry": {"coordinates":[-97.46207,25.928854],"type":"Point"}
}