{
  "type": "Feature",
  "properties": {
    "iso:country":"US",
    "sg:address":"3000 Irving Blvd",
    "sg:city":"Dallas",
    "sg:classifiers":[
        {
            "category":"Education",
            "subcategory":"Vocational School",
            "type":"Public Place"
        }
    ],
    "sg:phone":"+1 214 276 1066",
    "sg:postcode":"75247",
    "sg:province":"TX",
    "sg:tags":[
        "training",
        "computer"
    ],
    "wof:name":"Business Application Svc",
    "wof:placetype":"venue"
},
  "geometry": {"coordinates":[-96.85900700000001,32.808276],"type":"Point"}
}