{
  "type": "Feature",
  "properties": {
    "iso:country":"US",
    "sg:address":"4770 Harrys Ln",
    "sg:city":"Dallas",
    "sg:classifiers":[
        {
            "category":"Shopping",
            "type":"Retail Goods"
        }
    ],
    "sg:phone":"+1 214 369 8291",
    "sg:postcode":"75229",
    "sg:province":"TX",
    "sg:tags":[
        "merchandise"
    ],
    "wof:name":"Dovies Gift",
    "wof:placetype":"venue"
},
  "geometry": {"coordinates":[-96.825588,32.890762],"type":"Point"}
}