{
  "type": "Feature",
  "properties": {
    "iso:country":"US",
    "sg:address":"6017 Davenport Rd",
    "sg:city":"Dallas",
    "sg:classifiers":[
        {
            "category":"Wholesale",
            "subcategory":"Durable Goods & Equipment",
            "type":"Manufacturing & Wholesale Goods"
        }
    ],
    "sg:phone":"+1 972 931 6564",
    "sg:postcode":"75248",
    "sg:province":"TX",
    "sg:tags":[
        "professional"
    ],
    "wof:name":"Rizer & Assoc",
    "wof:placetype":"venue"
},
  "geometry": {"coordinates":[-96.802693,32.976267],"type":"Point"}
}