{
  "type": "Feature",
  "properties": {
    "iso:country":"US",
    "sg:address":"2200 N. Loop W",
    "sg:city":"Houston",
    "sg:classifiers":[
        {
            "category":"Restaurant",
            "type":"Food & Drink"
        },
        {
            "category":"Professional",
            "subcategory":"Business Services",
            "type":"Services"
        }
    ],
    "sg:phone":"+1 832 390 0474",
    "sg:postcode":"77018",
    "sg:province":"TX",
    "sg:tags":[
        "delivery",
        "breakfast",
        "brunch"
    ],
    "wof:name":"Moonlight Craving Cupcake & Breakfast-in-Bed Club Delivery",
    "wof:placetype":"venue"
},
  "geometry": {"coordinates":[-95.446433,29.806027],"type":"Point"}
}