{
  "type": "Feature",
  "properties": {
    "iso:country":"US",
    "sg:address":"103 S 7th St",
    "sg:city":"Gatesville",
    "sg:classifiers":[
        {
            "category":"Retail",
            "subcategory":"Repair Shop",
            "type":"Services"
        },
        {
            "category":"Professional",
            "subcategory":"Detective & Security Services",
            "type":"Services"
        }
    ],
    "sg:phone":"+1 254 865 0353",
    "sg:postcode":"76528",
    "sg:province":"TX",
    "sg:tags":[
        "skip",
        "tracing",
        "bail",
        "bond"
    ],
    "wof:name":"Free Bird Bail Bonds",
    "wof:placetype":"venue"
},
  "geometry": {"coordinates":[-97.74954200000001,31.434913],"type":"Point"}
}