{
  "type": "Feature",
  "properties": {
    "iso:country":"US",
    "sg:address":"701 N Bailey St",
    "sg:city":"Mexia",
    "sg:classifiers":[
        {
            "category":"Personal",
            "subcategory":"Beauty Salon",
            "type":"Services"
        }
    ],
    "sg:phone":"+1 254 562 0820",
    "sg:postcode":"76667",
    "sg:province":"TX",
    "sg:tags":[
        "spa",
        "day"
    ],
    "sg:website":"www.serenityescape.com",
    "wof:name":"Serenity Spa & Boutique",
    "wof:placetype":"venue"
},
  "geometry": {"coordinates":[-96.471628,31.688875],"type":"Point"}
}