{
  "type": "Feature",
  "properties": {
    "iso:country":"US",
    "sg:address":"834 S Treadaway Blvd",
    "sg:city":"Abilene",
    "sg:classifiers":[
        {
            "category":"Wholesale",
            "subcategory":"Machinery & Supplies",
            "type":"Manufacturing & Wholesale Goods"
        }
    ],
    "sg:phone":"+1 325 673 6464",
    "sg:postcode":"79602",
    "sg:province":"TX",
    "sg:tags":[
        "contractor"
    ],
    "wof:name":"Roberts Supply LTD",
    "wof:placetype":"venue"
},
  "geometry": {"coordinates":[-99.728481,32.439528],"type":"Point"}
}