{
  "type": "Feature",
  "properties": {
    "iso:country":"US",
    "sg:address":"1722 N 1st St",
    "sg:city":"Garland",
    "sg:classifiers":[
        {
            "category":"Professional",
            "type":"Services"
        },
        {
            "category":"Professional",
            "subcategory":"Business Services",
            "type":"Services"
        }
    ],
    "sg:phone":"+1 972 485 8100",
    "sg:postcode":"75040",
    "sg:province":"TX",
    "sg:tags":[
        "establishment"
    ],
    "wof:name":"Ralph Segars & Associates",
    "wof:placetype":"venue"
},
  "geometry": {"coordinates":[-96.63073,32.92907],"type":"Point"}
}