{
  "type": "Feature",
  "properties": {
    "iso:country":"US",
    "sg:address":"3202 Summerhill Rd",
    "sg:city":"Texarkana",
    "sg:classifiers":[
        {
            "category":"Autos & Motor Vehicles",
            "subcategory":"Automobile Sales",
            "type":"Retail Goods"
        }
    ],
    "sg:phone":"+1 903 792 1878",
    "sg:postcode":"75503",
    "sg:province":"TX",
    "sg:tags":[
        "used"
    ],
    "wof:name":"Orr Mitsubishi",
    "wof:placetype":"venue"
},
  "geometry": {"coordinates":[-94.065422,33.448853],"type":"Point"}
}