{
  "type": "Feature",
  "properties": {
    "iso:country":"US",
    "sg:address":"7374 Wilderness Way",
    "sg:city":"Weatherford",
    "sg:classifiers":[
        {
            "category":"Professional",
            "subcategory":"Detective & Security Services",
            "type":"Services"
        }
    ],
    "sg:phone":"+1 817 677 4700",
    "sg:postcode":"76085",
    "sg:province":"TX",
    "sg:tags":[
        "system"
    ],
    "wof:name":"Nextech Inc",
    "wof:placetype":"venue"
},
  "geometry": {"coordinates":[-97.638589,32.881171],"type":"Point"}
}