{
  "type": "Feature",
  "properties": {
    "iso:country":"US",
    "sg:address":"5101 Gus Thomasson Rd",
    "sg:city":"Mesquite",
    "sg:classifiers":[
        {
            "category":"Food & Beverages",
            "subcategory":"Groceries & Convenience Stores",
            "type":"Retail Goods"
        }
    ],
    "sg:phone":"+1 972 682 9804",
    "sg:postcode":"75150",
    "sg:province":"TX",
    "wof:name":"Terrys Supermarket",
    "wof:placetype":"venue"
},
  "geometry": {"coordinates":[-96.65770000000001,32.833],"type":"Point"}
}