{
  "type": "Feature",
  "properties": {
    "iso:country":"US",
    "sg:address":"3615 Stratford Arms Ln",
    "sg:city":"Sugar Land",
    "sg:classifiers":[
        {
            "category":"Social Services",
            "subcategory":"Child Care",
            "type":"Services"
        }
    ],
    "sg:phone":"+1 281 277 2722",
    "sg:postcode":"77478",
    "sg:province":"TX",
    "wof:name":"Loretta Patterson",
    "wof:placetype":"venue"
},
  "geometry": {"coordinates":[-95.68264499999999,29.630061],"type":"Point"}
}