{
  "type": "Feature",
  "properties": {
    "iso:country":"US",
    "sg:address":"3212 Knox St # 3214",
    "sg:city":"Dallas",
    "sg:classifiers":[
        {
            "category":"Home & Garden",
            "subcategory":"Furniture",
            "type":"Retail Goods"
        }
    ],
    "sg:phone":"+1 214 252 9106",
    "sg:postcode":"75205",
    "sg:province":"TX",
    "sg:tags":[
        "store"
    ],
    "wof:name":"Pottery Barn",
    "wof:placetype":"venue"
},
  "geometry": {"coordinates":[-96.78903200000001,32.823362],"type":"Point"}
}