{
  "type": "Feature",
  "properties": {
    "iso:country":"US",
    "sg:address":"5307 Imperial Grove Dr",
    "sg:city":"Houston",
    "sg:classifiers":[
        {
            "category":"Professional",
            "subcategory":"Computer Services",
            "type":"Services"
        }
    ],
    "sg:phone":"+1 281 537 2842",
    "sg:postcode":"77066",
    "sg:province":"TX",
    "wof:name":"Mac First Aid",
    "wof:placetype":"venue"
},
  "geometry": {"coordinates":[-95.49849399999999,29.942513],"type":"Point"}
}