{
  "type": "Feature",
  "properties": {
    "iso:country":"US",
    "sg:address":"5136 Sun Valley Dr",
    "sg:city":"Fort Worth",
    "sg:classifiers":[
        {
            "category":"Professional",
            "type":"Services"
        }
    ],
    "sg:phone":"+1 817 478 4800",
    "sg:postcode":"76119",
    "sg:province":"TX",
    "sg:tags":[
        "establishment"
    ],
    "wof:name":"Talo Enterprises",
    "wof:placetype":"venue"
},
  "geometry": {"coordinates":[-97.246656,32.679093],"type":"Point"}
}