{
  "type": "Feature",
  "properties": {
    "iso:country":"US",
    "sg:address":"6122 9th St",
    "sg:city":"Lubbock",
    "sg:classifiers":[
        {
            "category":"Building & Trades",
            "subcategory":"Construction",
            "type":"Services"
        }
    ],
    "sg:phone":"+1 806 785 1879",
    "sg:postcode":"79416",
    "sg:province":"TX",
    "sg:tags":[
        "concrete",
        "contractor"
    ],
    "wof:name":"Apex Concrete Coatings",
    "wof:placetype":"venue"
},
  "geometry": {"coordinates":[-101.95000899999999,33.587598],"type":"Point"}
}