{
  "type": "Feature",
  "properties": {
    "iso:country":"US",
    "sg:address":"5402 Ave Q",
    "sg:city":"Galveston",
    "sg:classifiers":[
        {
            "category":"Freight",
            "type":"Transportation"
        }
    ],
    "sg:phone":"+1 409 762 6263",
    "sg:postcode":"77551",
    "sg:province":"TX",
    "sg:tags":[
        "operator",
        "trucking"
    ],
    "wof:name":"A-1 Transport",
    "wof:placetype":"venue"
},
  "geometry": {"coordinates":[-94.825354,29.280865],"type":"Point"}
}