{
  "type": "Feature",
  "properties": {
    "iso:country":"US",
    "sg:address":"2631 John West Rd",
    "sg:city":"Dallas",
    "sg:classifiers":[
        {
            "category":"Shopping",
            "type":"Retail Goods"
        }
    ],
    "sg:phone":"+1 214 327 9333",
    "sg:postcode":"75228",
    "sg:province":"TX",
    "sg:tags":[
        "hearing",
        "equipment",
        "supply",
        "impaired"
    ],
    "wof:name":"Treymoore Eastfield",
    "wof:placetype":"venue"
},
  "geometry": {"coordinates":[-96.672206,32.80705],"type":"Point"}
}