{
  "type": "Feature",
  "properties": {
    "iso:country":"US",
    "sg:address":"2602 Manor Way",
    "sg:city":"Dallas",
    "sg:classifiers":[
        {
            "category":"Health Services",
            "subcategory":"Medical Lab",
            "type":"Services"
        }
    ],
    "sg:phone":"+1 214 353 2754",
    "sg:postcode":"75235",
    "sg:province":"TX",
    "sg:tags":[
        "laboratory",
        "dental"
    ],
    "wof:name":"Bautista Dental Lab",
    "wof:placetype":"venue"
},
  "geometry": {"coordinates":[-96.83939100000001,32.82742],"type":"Point"}
}