{
  "type": "Feature",
  "properties": {
    "iso:country":"US",
    "sg:address":"317 Commerce St",
    "sg:city":"Palacios",
    "sg:classifiers":[
        {
            "category":"Retail",
            "subcategory":"Photofinishing",
            "type":"Services"
        }
    ],
    "sg:phone":"+1 361 972 2309",
    "sg:postcode":"77465",
    "sg:province":"TX",
    "sg:tags":[
        "photo",
        "finishing"
    ],
    "wof:name":"C & B Photo & Video",
    "wof:placetype":"venue"
},
  "geometry": {"coordinates":[-96.215048,28.700311],"type":"Point"}
}