{
  "type": "Feature",
  "properties": {
    "iso:country":"US",
    "sg:address":"146 W Oleander Ave",
    "sg:city":"La Feria",
    "sg:classifiers":[
        {
            "category":"Personal",
            "subcategory":"Beauty Salon",
            "type":"Services"
        }
    ],
    "sg:phone":"+1 956 797 9086",
    "sg:postcode":"78559",
    "sg:province":"TX",
    "wof:name":"Del Carmen'z Salon",
    "wof:placetype":"venue"
},
  "geometry": {"coordinates":[-97.824904,26.157806],"type":"Point"}
}