{
  "type": "Feature",
  "properties": {
    "iso:country":"US",
    "sg:address":"1605 Nueces St",
    "sg:city":"Austin",
    "sg:classifiers":[
        {
            "category":"Health Services",
            "subcategory":"Dentist",
            "type":"Services"
        }
    ],
    "sg:phone":"+1 512 477 0060",
    "sg:postcode":"78701",
    "sg:province":"TX",
    "wof:name":"Charles R Peck",
    "wof:placetype":"venue"
},
  "geometry": {"coordinates":[-97.744776,30.279486],"type":"Point"}
}