{
  "type": "Feature",
  "properties": {
    "iso:country":"US",
    "sg:address":"408 N Chaparral St",
    "sg:city":"Corpus Christi",
    "sg:classifiers":[
        {
            "category":"Shopping",
            "subcategory":"Jewelry",
            "type":"Retail Goods"
        }
    ],
    "sg:phone":"+1 361 882 6286",
    "sg:postcode":"78401",
    "sg:province":"TX",
    "sg:tags":[
        "wholesale",
        "jeweler"
    ],
    "wof:name":"Roberts Jewelers Inc",
    "wof:placetype":"venue"
},
  "geometry": {"coordinates":[-97.393812,27.795996],"type":"Point"}
}