{
  "type": "Feature",
  "properties": {
    "iso:country":"US",
    "sg:address":"1966 W Northwest Hwy",
    "sg:city":"Dallas",
    "sg:classifiers":[
        {
            "category":"Animal Shelter",
            "type":"Public Place"
        }
    ],
    "sg:phone":"+1 972 869 1097",
    "sg:postcode":"75220",
    "sg:province":"TX",
    "sg:tags":[
        "adult"
    ],
    "wof:name":"New Fine Arts",
    "wof:placetype":"venue"
},
  "geometry": {"coordinates":[-96.91061000000001,32.867313],"type":"Point"}
}