{
  "type": "Feature",
  "properties": {
    "iso:country":"US",
    "sg:address":"13501 Bayswater Garden",
    "sg:city":"Austin",
    "sg:classifiers":[
        {
            "category":"Retail",
            "subcategory":"Auto Repair",
            "type":"Services"
        }
    ],
    "sg:phone":"+1 512 203 0034",
    "sg:postcode":"78729",
    "sg:province":"TX",
    "sg:tags":[
        "automobile",
        "lubrication"
    ],
    "wof:name":"Mobile Pit Stop Of Austin",
    "wof:placetype":"venue"
},
  "geometry": {"coordinates":[-97.77804500000001,30.470263],"type":"Point"}
}