{
  "type": "Feature",
  "properties": {
    "iso:country":"US",
    "sg:address":"2809 Erastus St",
    "sg:city":"Houston",
    "sg:classifiers":[
        {
            "category":"Organizations",
            "subcategory":"Religious Organization",
            "type":"Services"
        }
    ],
    "sg:phone":"+1 713 674 5038",
    "sg:postcode":"77026",
    "sg:province":"TX",
    "sg:tags":[
        "church"
    ],
    "wof:name":"Charity Baptist Church",
    "wof:placetype":"venue"
},
  "geometry": {"coordinates":[-95.317578,29.788254],"type":"Point"}
}