{
  "type": "Feature",
  "properties": {
    "iso:country":"US",
    "sg:address":"3468 Courtyard Cir",
    "sg:city":"Farmers Branch",
    "sg:classifiers":[
        {
            "category":"Shopping",
            "subcategory":"Computers & Home Electronics",
            "type":"Retail Goods"
        }
    ],
    "sg:phone":"+1 972 484 2838",
    "sg:postcode":"75234",
    "sg:province":"TX",
    "sg:tags":[
        "equipment",
        "satellite",
        "system"
    ],
    "wof:name":"Arris Tele Wire Supply",
    "wof:placetype":"venue"
},
  "geometry": {"coordinates":[-96.864957,32.93323],"type":"Point"}
}