{
  "type": "Feature",
  "properties": {
    "iso:country":"US",
    "sg:address":"3142 Christopher St",
    "sg:city":"Grand Prairie",
    "sg:classifiers":[
        {
            "category":"Education",
            "subcategory":"School",
            "type":"Public Place"
        }
    ],
    "sg:phone":"+1 972 262 0417",
    "sg:postcode":"75052",
    "sg:province":"TX",
    "wof:name":"Victory Christian Fellows",
    "wof:placetype":"venue"
},
  "geometry": {"coordinates":[-97.008483,32.6942],"type":"Point"}
}