{
  "type": "Feature",
  "properties": {
    "iso:country":"US",
    "sg:address":"1805 Farhills Dr",
    "sg:city":"Killeen",
    "sg:classifiers":[
        {
            "category":"Professional",
            "type":"Services"
        }
    ],
    "sg:phone":"+1 254 554 3227",
    "sg:postcode":"76549",
    "sg:province":"TX",
    "wof:name":"Enchanted Waters",
    "wof:placetype":"venue"
},
  "geometry": {"coordinates":[-97.765191,31.096362],"type":"Point"}
}