{
  "type": "Feature",
  "properties": {
    "iso:country":"US",
    "sg:address":"234 Fronda Walk",
    "sg:city":"San Antonio",
    "sg:classifiers":[
        {
            "category":"Social Services",
            "subcategory":"Child Care",
            "type":"Services"
        }
    ],
    "sg:phone":"+1 210 224 7429",
    "sg:postcode":"78207",
    "sg:province":"TX",
    "wof:name":"Parent/Child Inc",
    "wof:placetype":"venue"
},
  "geometry": {"coordinates":[-98.527958,29.405147],"type":"Point"}
}