{
  "type": "Feature",
  "properties": {
    "iso:country":"US",
    "sg:address":"7 Hornsilver Pl",
    "sg:city":"Spring",
    "sg:classifiers":[
        {
            "category":"Shopping",
            "subcategory":"Used Merchandise",
            "type":"Retail Goods"
        }
    ],
    "sg:phone":"+1 281 793 7799",
    "sg:postcode":"77381",
    "sg:province":"TX",
    "wof:name":"Peoples",
    "wof:placetype":"venue"
},
  "geometry": {"coordinates":[-95.494407,30.183286],"type":"Point"}
}