{
  "type": "Feature",
  "properties": {
    "iso:country":"US",
    "sg:address":"3023 Bledsoe St",
    "sg:city":"Fort Worth",
    "sg:classifiers":[
        {
            "category":"Health Services",
            "subcategory":"Clinic",
            "type":"Services"
        }
    ],
    "sg:phone":"+1 817 810 4014",
    "sg:postcode":"76107",
    "sg:province":"TX",
    "sg:tags":[
        "medical"
    ],
    "wof:name":"DFW Euro Wave LLC",
    "wof:placetype":"venue"
},
  "geometry": {"coordinates":[-97.361586,32.748264],"type":"Point"}
}