{
  "type": "Feature",
  "properties": {
    "iso:country":"US",
    "sg:address":"2314 E 7th St",
    "sg:city":"Austin",
    "sg:classifiers":[
        {
            "category":"Professional",
            "subcategory":"Business Services",
            "type":"Services"
        }
    ],
    "sg:phone":"+1 512 320 8676",
    "sg:postcode":"78702",
    "sg:province":"TX",
    "wof:name":"Syed Enterprises",
    "wof:placetype":"venue"
},
  "geometry": {"coordinates":[-97.716308,30.261418],"type":"Point"}
}