{
  "type": "Feature",
  "properties": {
    "iso:country":"US",
    "sg:address":"5813 Distribution",
    "sg:city":"San Antonio",
    "sg:classifiers":[
        {
            "category":"Building & Trades",
            "subcategory":"Construction",
            "type":"Services"
        }
    ],
    "sg:phone":"+1 210 249 0267",
    "sg:postcode":"78218",
    "sg:province":"TX",
    "sg:tags":[
        "resurfacing",
        "laying",
        "refinishing",
        "floor"
    ],
    "wof:name":"Impact Floors Of Texas Llt",
    "wof:placetype":"venue"
},
  "geometry": {"coordinates":[-98.39182599999999,29.477845],"type":"Point"}
}