{
  "type": "Feature",
  "properties": {
    "iso:country":"US",
    "sg:address":"4392 Trexler Rd",
    "sg:city":"Texarkana",
    "sg:classifiers":[
        {
            "category":"Building & Trades",
            "subcategory":"Construction",
            "type":"Services"
        }
    ],
    "sg:phone":"+1 903 293 8108",
    "sg:postcode":"75501",
    "sg:province":"TX",
    "sg:tags":[
        "wallcoverings-installation",
        "wallpaper",
        "painting",
        "contractor"
    ],
    "wof:name":"Brad Neal Painting",
    "wof:placetype":"venue"
},
  "geometry": {"coordinates":[-94.20580200000001,33.388017],"type":"Point"}
}