{
  "type": "Feature",
  "properties": {
    "iso:country":"US",
    "sg:address":"25082 US Highway 281 N",
    "sg:city":"Bulverde",
    "sg:classifiers":[
        {
            "category":"Shopping",
            "subcategory":"Party Supplies",
            "type":"Retail Goods"
        }
    ],
    "sg:phone":"+1 830 438 3415",
    "sg:postcode":"78163",
    "sg:province":"TX",
    "wof:name":"Mr W Fireworks",
    "wof:placetype":"venue"
},
  "geometry": {"coordinates":[-98.432503,29.7735],"type":"Point"}
}