{
  "type": "Feature",
  "properties": {
    "iso:country":"US",
    "sg:address":"4027 Westheimer Rd",
    "sg:city":"Houston",
    "sg:classifiers":[
        {
            "category":"Personal",
            "subcategory":"Beauty Salon",
            "type":"Services"
        }
    ],
    "sg:phone":"+1 713 877 1645",
    "sg:postcode":"77027",
    "sg:province":"TX",
    "sg:tags":[
        "hair",
        "shop"
    ],
    "wof:name":"Michael Kemper Salon",
    "wof:placetype":"venue"
},
  "geometry": {"coordinates":[-95.446899,29.741501],"type":"Point"}
}