{
  "type": "Feature",
  "properties": {
    "iso:country":"US",
    "sg:address":"790 S Leggett Dr",
    "sg:city":"Abilene",
    "sg:classifiers":[
        {
            "category":"Manufacturing",
            "subcategory":"Furniture",
            "type":"Manufacturing & Wholesale Goods"
        },
        {
            "category":"Wholesale",
            "subcategory":"Furniture",
            "type":"Manufacturing & Wholesale Goods"
        }
    ],
    "sg:phone":"+1 325 692 4304",
    "sg:postcode":"79605",
    "sg:province":"TX",
    "sg:tags":[
        "chair",
        "mfg"
    ],
    "wof:name":"Adjustec Manufacturing Inc",
    "wof:placetype":"venue"
},
  "geometry": {"coordinates":[-99.771176,32.443589],"type":"Point"}
}