{
  "type": "Feature",
  "properties": {
    "iso:country":"US",
    "sg:address":"708 Edwards Dr",
    "sg:city":"Harker Heights",
    "sg:classifiers":[
        {
            "category":"Restaurant",
            "type":"Food & Drink"
        }
    ],
    "sg:phone":"+1 254 680 2770",
    "sg:postcode":"76548",
    "sg:province":"TX",
    "wof:name":"Butter Churn Restaurant",
    "wof:placetype":"venue"
},
  "geometry": {"coordinates":[-97.645428,31.083697],"type":"Point"}
}