{
  "type": "Feature",
  "properties": {
    "iso:country":"US",
    "sg:address":"5702 N Jupiter Rd",
    "sg:city":"Garland",
    "sg:classifiers":[
        {
            "category":"Social Services",
            "subcategory":"Child Care",
            "type":"Services"
        }
    ],
    "sg:phone":"+1 972 495 7839",
    "sg:postcode":"75044",
    "sg:province":"TX",
    "sg:tags":[
        "day"
    ],
    "sg:website":"www.concordiatx.org",
    "wof:name":"Concordia Learning Center",
    "wof:placetype":"venue"
},
  "geometry": {"coordinates":[-96.68240400000001,32.9673],"type":"Point"}
}