{
  "type": "Feature",
  "properties": {
    "iso:country":"US",
    "sg:address":"3111 Colony Dr",
    "sg:city":"San Antonio",
    "sg:classifiers":[
        {
            "category":"Shopping",
            "type":"Retail Goods"
        }
    ],
    "sg:phone":"+1 210 614 3897",
    "sg:postcode":"78230",
    "sg:province":"TX",
    "sg:tags":[
        "art",
        "gallery",
        "dealer"
    ],
    "wof:name":"Raul Gutierrez Gallery",
    "wof:placetype":"venue"
},
  "geometry": {"coordinates":[-98.546295,29.534966],"type":"Point"}
}