{
  "type": "Feature",
  "properties": {
    "iso:country":"US",
    "sg:address":"4300 Nixon Ln",
    "sg:city":"Austin",
    "sg:classifiers":[
        {
            "category":"Building & Trades",
            "subcategory":"Construction",
            "type":"Services"
        }
    ],
    "sg:phone":"+1 512 928 4002",
    "sg:postcode":"78725",
    "sg:province":"TX",
    "sg:tags":[
        "insulation",
        "heat",
        "contractor"
    ],
    "wof:name":"Williams Insulation Inc",
    "wof:placetype":"venue"
},
  "geometry": {"coordinates":[-97.64959,30.273253],"type":"Point"}
}