{
  "type": "Feature",
  "properties": {
    "iso:country":"US",
    "sg:address":"2301 Dalworth St",
    "sg:city":"Grand Prairie",
    "sg:classifiers":[
        {
            "category":"Real Estate",
            "subcategory":"Real Estate Agent",
            "type":"Services"
        }
    ],
    "sg:phone":"+1 972 641 2821",
    "sg:postcode":"75050",
    "sg:province":"TX",
    "sg:tags":[
        "property",
        "management"
    ],
    "wof:name":"Prairie Oaks Apartments",
    "wof:placetype":"venue"
},
  "geometry": {"coordinates":[-97.03891400000001,32.744706],"type":"Point"}
}