{
  "type": "Feature",
  "properties": {
    "iso:country":"US",
    "sg:address":"3625 McDonald Rd",
    "sg:city":"Tyler",
    "sg:classifiers":[
        {
            "category":"Organizations",
            "subcategory":"Religious Organization",
            "type":"Services"
        }
    ],
    "sg:phone":"+1 903 566 4331",
    "sg:postcode":"75701",
    "sg:province":"TX",
    "wof:name":"Lords Refuge  Inc",
    "wof:placetype":"venue"
},
  "geometry": {"coordinates":[-95.25022,32.322871],"type":"Point"}
}