{
  "type": "Feature",
  "properties": {
    "iso:country":"US",
    "sg:address":"6600 Westwind Dr",
    "sg:city":"El Paso",
    "sg:classifiers":[
        {
            "category":"Professional",
            "subcategory":"Engineering",
            "type":"Services"
        },
        {
            "category":"Real Estate",
            "subcategory":"Surveying",
            "type":"Services"
        }
    ],
    "sg:phone":"+1 915 584 4457",
    "sg:postcode":"79912",
    "sg:province":"TX",
    "sg:tags":[
        "civil",
        "land",
        "engineer"
    ],
    "wof:name":"S L I Engineering Inc",
    "wof:placetype":"venue"
},
  "geometry": {"coordinates":[-106.53596,31.844372],"type":"Point"}
}