{
  "type": "Feature",
  "properties": {
    "iso:country":"US",
    "sg:address":"5745 S 6th Ave",
    "sg:city":"Fort Worth",
    "sg:classifiers":[
        {
            "category":"Organizations",
            "subcategory":"Non-profit Organization",
            "type":"Services"
        }
    ],
    "sg:phone":"+1 817 293 8393",
    "sg:postcode":"76134",
    "sg:province":"TX",
    "wof:name":"Friends Of Quanah Parker Park",
    "wof:placetype":"venue"
},
  "geometry": {"coordinates":[-97.339303,32.662343],"type":"Point"}
}