{
  "type": "Feature",
  "properties": {
    "iso:country":"US",
    "sg:address":"1429 W Rochelle Rd",
    "sg:city":"Irving",
    "sg:classifiers":[
        {
            "category":"Restaurant",
            "type":"Food & Drink"
        }
    ],
    "sg:phone":"+1 972 830 6287",
    "sg:postcode":"75062",
    "sg:province":"TX",
    "sg:tags":[
        "chinese"
    ],
    "wof:name":"Empress of China",
    "wof:placetype":"venue"
},
  "geometry": {"coordinates":[-96.964268,32.844369],"type":"Point"}
}