{
  "type": "Feature",
  "properties": {
    "iso:country":"US",
    "sg:address":"8768 Sunset Heights Ln",
    "sg:city":"Conroe",
    "sg:classifiers":[
        {
            "category":"Banks & Credit Unions",
            "subcategory":"Investment Brokerage",
            "type":"Services"
        }
    ],
    "sg:phone":"+1 936 441 6561",
    "sg:postcode":"77302",
    "sg:province":"TX",
    "sg:tags":[
        "security"
    ],
    "wof:name":"Edward Jones 22000",
    "wof:placetype":"venue"
},
  "geometry": {"coordinates":[-95.44670600000001,30.261692],"type":"Point"}
}