{
  "type": "Feature",
  "properties": {
    "iso:country":"US",
    "sg:address":"1721 Quarry Ln",
    "sg:city":"Mc Kinney",
    "sg:classifiers":[
        {
            "category":"Professional",
            "type":"Services"
        }
    ],
    "sg:phone":"+1 972 540 9279",
    "sg:postcode":"75070",
    "sg:province":"TX",
    "wof:name":"Perfect World Events",
    "wof:placetype":"venue"
},
  "geometry": {"coordinates":[-96.71194,33.185399],"type":"Point"}
}