{
  "type": "Feature",
  "properties": {
    "iso:country":"US",
    "sg:address":"105 Meredith Dr",
    "sg:city":"Irving",
    "sg:classifiers":[
        {
            "category":"Shopping",
            "subcategory":"Computers & Home Electronics",
            "type":"Retail Goods"
        }
    ],
    "sg:phone":"+1 972 401 0017",
    "sg:postcode":"75063",
    "sg:province":"TX",
    "sg:tags":[
        "publishing"
    ],
    "wof:name":"M W Resources",
    "wof:placetype":"venue"
},
  "geometry": {"coordinates":[-96.945334,32.941607],"type":"Point"}
}