{
  "type": "Feature",
  "properties": {
    "iso:country":"US",
    "sg:address":"12718 North Fwy",
    "sg:city":"Houston",
    "sg:classifiers":[
        {
            "category":"Shopping",
            "type":"Retail Goods"
        }
    ],
    "sg:phone":"+1 281 872 7949",
    "sg:postcode":"77060",
    "sg:province":"TX",
    "sg:tags":[
        "monument"
    ],
    "wof:name":"Houston Memorials",
    "wof:placetype":"venue"
},
  "geometry": {"coordinates":[-95.418342,29.954505],"type":"Point"}
}