{
  "type": "Feature",
  "properties": {
    "iso:country":"US",
    "sg:address":"4975 Preston Park Blvd Ste 360",
    "sg:city":"Plano",
    "sg:classifiers":[
        {
            "category":"Building & Trades",
            "subcategory":"Construction",
            "type":"Services"
        }
    ],
    "sg:phone":"+1 972 985 5505",
    "sg:postcode":"75093",
    "sg:province":"TX",
    "sg:tags":[
        "contractor"
    ],
    "wof:name":"Shaddock Development Company",
    "wof:placetype":"venue"
},
  "geometry": {"coordinates":[-96.7938,33.022999],"type":"Point"}
}