{
  "type": "Feature",
  "properties": {
    "iso:country":"US",
    "sg:address":"3940 Samuell Blvd",
    "sg:city":"Mesquite",
    "sg:classifiers":[
        {
            "category":"Freight",
            "type":"Transportation"
        }
    ],
    "sg:phone":"+1 972 289 9392",
    "sg:postcode":"75149",
    "sg:province":"TX",
    "sg:tags":[
        "mover"
    ],
    "wof:name":"Riteplace Self Storage",
    "wof:placetype":"venue"
},
  "geometry": {"coordinates":[-96.66149900000001,32.792198],"type":"Point"}
}