{
  "type": "Feature",
  "properties": {
    "iso:country":"US",
    "sg:address":"131 W Church St",
    "sg:city":"Weatherford",
    "sg:classifiers":[
        {
            "category":"Real Estate",
            "subcategory":"Real Estate Agent",
            "type":"Services"
        },
        {
            "category":"Building & Trades",
            "subcategory":"Construction",
            "type":"Services"
        }
    ],
    "sg:phone":"+1 817 410 7893",
    "sg:postcode":"76086",
    "sg:province":"TX",
    "sg:tags":[
        "water",
        "well",
        "drilling"
    ],
    "wof:name":"Texas Wyoming Drilling Inc",
    "wof:placetype":"venue"
},
  "geometry": {"coordinates":[-97.798901,32.758283],"type":"Point"}
}