{
  "type": "Feature",
  "properties": {
    "iso:country":"US",
    "sg:address":"7403 Irvington Blvd",
    "sg:city":"Houston",
    "sg:classifiers":[
        {
            "category":"Restaurant",
            "type":"Food & Drink"
        }
    ],
    "sg:phone":"+1 713 742 6611",
    "sg:postcode":"77022",
    "sg:province":"TX",
    "wof:name":"Taqueria San Miguel",
    "wof:placetype":"venue"
},
  "geometry": {"coordinates":[-95.361504,29.8279],"type":"Point"}
}