{
  "type": "Feature",
  "properties": {
    "iso:country":"US",
    "sg:address":"12916 Eastgate Dr",
    "sg:city":"Mesquite",
    "sg:classifiers":[
        {
            "category":"Professional",
            "type":"Services"
        }
    ],
    "sg:phone":"+1 972 913 5070",
    "sg:postcode":"75181",
    "sg:province":"TX",
    "wof:name":"Betos Complete Services",
    "wof:placetype":"venue"
},
  "geometry": {"coordinates":[-96.606505,32.729583],"type":"Point"}
}