{
  "type": "Feature",
  "properties": {
    "iso:country":"US",
    "sg:address":"4 Twelve Pines Ct",
    "sg:city":"Spring",
    "sg:classifiers":[
        {
            "category":"Professional",
            "subcategory":"Management & Consulting",
            "type":"Services"
        },
        {
            "category":"Professional",
            "subcategory":"Employment Agencies",
            "type":"Services"
        }
    ],
    "sg:phone":"+1 281 364 0554",
    "sg:postcode":"77381",
    "sg:province":"TX",
    "sg:tags":[
        "consultant",
        "search",
        "executive",
        "opportunity"
    ],
    "wof:name":"Rps Consultants",
    "wof:placetype":"venue"
},
  "geometry": {"coordinates":[-95.48819,30.168623],"type":"Point"}
}