{
  "type": "Feature",
  "properties": {
    "iso:country":"US",
    "sg:address":"1105 Rio Grande St",
    "sg:city":"Austin",
    "sg:classifiers":[
        {
            "category":"Personal",
            "subcategory":"Beauty Salon",
            "type":"Services"
        }
    ],
    "sg:phone":"+1 512 476 2236",
    "sg:postcode":"78701",
    "sg:province":"TX",
    "sg:tags":[
        "shop"
    ],
    "wof:name":"West Avenue Salon",
    "wof:placetype":"venue"
},
  "geometry": {"coordinates":[-97.74731300000001,30.275674],"type":"Point"}
}