{
  "type": "Feature",
  "properties": {
    "iso:country":"US",
    "sg:address":"246 Windy Ln",
    "sg:city":"Rockwall",
    "sg:classifiers":[
        {
            "category":"Wholesale",
            "subcategory":"Machinery & Supplies",
            "type":"Manufacturing & Wholesale Goods"
        }
    ],
    "sg:phone":"+1 972 722 3992",
    "sg:postcode":"75087",
    "sg:province":"TX",
    "sg:tags":[
        "packaging"
    ],
    "wof:name":"KWIK Lok Corp",
    "wof:placetype":"venue"
},
  "geometry": {"coordinates":[-96.445453,32.959702],"type":"Point"}
}