{
  "type": "Feature",
  "properties": {
    "iso:country":"US",
    "sg:address":"7 S 11th St",
    "sg:city":"Mcallen",
    "sg:classifiers":[
        {
            "category":"Professional",
            "subcategory":"Computer Services",
            "type":"Services"
        }
    ],
    "sg:phone":"+1 956 686 5588",
    "sg:postcode":"78501",
    "sg:province":"TX",
    "sg:tags":[
        "prepackaged",
        "software"
    ],
    "wof:name":"Computer Educational Pdts Inc",
    "wof:placetype":"venue"
},
  "geometry": {"coordinates":[-98.231167,26.202894],"type":"Point"}
}