{
  "type": "Feature",
  "properties": {
    "iso:country":"US",
    "sg:address":"1722 Sandringham",
    "sg:city":"San Antonio",
    "sg:classifiers":[
        {
            "category":"Building & Trades",
            "subcategory":"Construction",
            "type":"Services"
        }
    ],
    "sg:phone":"+1 210 479 9969",
    "sg:postcode":"78258",
    "sg:province":"TX",
    "sg:tags":[
        "paving",
        "contractor"
    ],
    "wof:name":"Kuntz Contracting",
    "wof:placetype":"venue"
},
  "geometry": {"coordinates":[-98.519598,29.611837],"type":"Point"}
}