{
  "type": "Feature",
  "properties": {
    "iso:country":"US",
    "sg:address":"2401 W 16th St",
    "sg:city":"Odessa",
    "sg:classifiers":[
        {
            "category":"Organizations",
            "subcategory":"Religious Organization",
            "type":"Services"
        }
    ],
    "sg:phone":"+1 432 332 7727",
    "sg:postcode":"79763",
    "sg:province":"TX",
    "wof:name":"Sunset Heights Baptist Church",
    "wof:placetype":"venue"
},
  "geometry": {"coordinates":[-102.399123,31.849171],"type":"Point"}
}