{
  "type": "Feature",
  "properties": {
    "iso:country":"US",
    "sg:address":"3274 S 27th St",
    "sg:city":"Abilene",
    "sg:classifiers":[
        {
            "category":"Real Estate",
            "subcategory":"Real Estate Agent",
            "type":"Services"
        }
    ],
    "sg:phone":"+1 325 690 4025",
    "sg:postcode":"79605",
    "sg:province":"TX",
    "wof:name":"Joann Guthrie",
    "wof:placetype":"venue"
},
  "geometry": {"coordinates":[-99.762029,32.417822],"type":"Point"}
}