{
  "type": "Feature",
  "properties": {
    "iso:country":"US",
    "sg:address":"434 E Creek St",
    "sg:city":"Fredericksburg",
    "sg:classifiers":[
        {
            "category":"Professional",
            "subcategory":"Employment Agencies",
            "type":"Services"
        }
    ],
    "sg:phone":"+1 830 990 2270",
    "sg:postcode":"78624",
    "sg:province":"TX",
    "sg:tags":[
        "help",
        "supply"
    ],
    "wof:name":"Cox Alice D",
    "wof:placetype":"venue"
},
  "geometry": {"coordinates":[-98.867436,30.268497],"type":"Point"}
}