{
  "type": "Feature",
  "properties": {
    "iso:country":"US",
    "sg:address":"1006 W Calton Rd",
    "sg:city":"Laredo",
    "sg:classifiers":[
        {
            "category":"Travel",
            "subcategory":"Hotels & Motels",
            "type":"Entertainment"
        }
    ],
    "sg:phone":"+1 956 712 0733",
    "sg:postcode":"78041",
    "sg:province":"TX",
    "sg:tags":[
        "operation"
    ],
    "wof:name":"Red Roof Inn",
    "wof:placetype":"venue"
},
  "geometry": {"coordinates":[-99.507138,27.544777],"type":"Point"}
}