{
  "type": "Feature",
  "properties": {
    "iso:country":"US",
    "sg:address":"1514 Ellis Ave",
    "sg:city":"Lufkin",
    "sg:classifiers":[
        {
            "category":"Health Services",
            "subcategory":"Doctor",
            "type":"Services"
        }
    ],
    "sg:phone":"+1 936 632 3999",
    "sg:postcode":"75904",
    "sg:province":"TX",
    "sg:tags":[
        "medicine",
        "physician",
        "practice",
        "surgeons",
        "family"
    ],
    "wof:name":"Calvin Cargill Md",
    "wof:placetype":"venue"
},
  "geometry": {"coordinates":[-94.750563,31.334116],"type":"Point"}
}