{
  "type": "Feature",
  "properties": {
    "iso:country":"US",
    "sg:address":"2306 Highland Meadows Dr",
    "sg:city":"Colleyville",
    "sg:classifiers":[
        {
            "category":"Organizations",
            "subcategory":"Membership Organization",
            "type":"Services"
        }
    ],
    "sg:phone":"+1 817 488 1275",
    "sg:postcode":"76034",
    "sg:province":"TX",
    "wof:name":"Defenders Of The Alamo Inc",
    "wof:placetype":"venue"
},
  "geometry": {"coordinates":[-97.13096400000001,32.898334],"type":"Point"}
}