{
  "type": "Feature",
  "properties": {
    "iso:country":"US",
    "sg:address":"816 W McDermott Dr",
    "sg:city":"Allen",
    "sg:classifiers":[
        {
            "category":"Shopping",
            "type":"Retail Goods"
        }
    ],
    "sg:phone":"+1 972 747 7040",
    "sg:postcode":"75013",
    "sg:province":"TX",
    "sg:tags":[
        "merchandise"
    ],
    "wof:name":"Petco",
    "wof:placetype":"venue"
},
  "geometry": {"coordinates":[-96.679074,33.101733],"type":"Point"}
}