{
  "type": "Feature",
  "properties": {
    "iso:country":"US",
    "sg:address":"6528 Whitemarsh Valley Walk",
    "sg:city":"West Lake Hills",
    "sg:classifiers":[
        {
            "category":"Retail",
            "subcategory":"Storage",
            "type":"Services"
        }
    ],
    "sg:phone":"+1 512 305 3720",
    "sg:postcode":"78746",
    "sg:province":"TX",
    "sg:tags":[
        "self"
    ],
    "wof:name":"HL Marine",
    "wof:placetype":"venue"
},
  "geometry": {"coordinates":[-97.84174400000001,30.285193],"type":"Point"}
}