{
  "type": "Feature",
  "properties": {
    "iso:country":"US",
    "sg:address":"412 N Washington Ave",
    "sg:city":"Livingston",
    "sg:classifiers":[
        {
            "category":"Professional",
            "subcategory":"Lawyer & Legal Services",
            "type":"Services"
        }
    ],
    "sg:phone":"+1 936 327 6842",
    "sg:postcode":"77351",
    "sg:province":"TX",
    "wof:name":"Linebarger Goggn Blair & Smpsn",
    "wof:placetype":"venue"
},
  "geometry": {"coordinates":[-94.932937,30.711713],"type":"Point"}
}