{
  "type": "Feature",
  "properties": {
    "iso:country":"US",
    "sg:address":"904 W 29th St",
    "sg:city":"Austin",
    "sg:classifiers":[
        {
            "category":"Professional",
            "subcategory":"Lawyer & Legal Services",
            "type":"Services"
        }
    ],
    "sg:phone":"+1 512 469 0176",
    "sg:postcode":"78705",
    "sg:province":"TX",
    "sg:tags":[
        "attorney"
    ],
    "sg:website":"www.vacationnude.com",
    "wof:name":"Thomas E Tiemann",
    "wof:placetype":"venue"
},
  "geometry": {"coordinates":[-97.746353,30.297093],"type":"Point"}
}