{
  "type": "Feature",
  "properties": {
    "iso:country":"US",
    "sg:address":"4807 Trail Crest Cir",
    "sg:city":"Austin",
    "sg:phone":"+1 512 358 8066",
    "sg:postcode":"78735",
    "sg:province":"TX",
    "wof:name":"Alpha Gizmo",
    "wof:placetype":"venue"
},
  "geometry": {"coordinates":[-97.82892200000001,30.250589],"type":"Point"}
}