{
  "type": "Feature",
  "properties": {
    "iso:country":"US",
    "sg:address":"2808 Alcorn Oaks Dr",
    "sg:city":"Sugar Land",
    "sg:classifiers":[
        {
            "category":"Education",
            "subcategory":"School",
            "type":"Public Place"
        }
    ],
    "sg:phone":"+1 281 265 7888",
    "sg:postcode":"77479",
    "sg:province":"TX",
    "wof:name":"Honor Roll",
    "wof:placetype":"venue"
},
  "geometry": {"coordinates":[-95.630455,29.571783],"type":"Point"}
}