{
  "type": "Feature",
  "properties": {
    "iso:country":"US",
    "sg:address":"1222 N Main Ave",
    "sg:city":"San Antonio",
    "sg:classifiers":[
        {
            "category":"Professional",
            "type":"Services"
        }
    ],
    "sg:phone":"+1 210 575 9881",
    "sg:postcode":"78212",
    "sg:province":"TX",
    "sg:tags":[
        "establishment"
    ],
    "wof:name":"Vista Vocational Resources",
    "wof:placetype":"venue"
},
  "geometry": {"coordinates":[-98.494119,29.440406],"type":"Point"}
}