{
  "type": "Feature",
  "properties": {
    "iso:country":"US",
    "sg:address":"112 S Blackburn St",
    "sg:city":"Brady",
    "sg:classifiers":[
        {
            "category":"Professional",
            "subcategory":"Accounting & Tax Preparation",
            "type":"Services"
        }
    ],
    "sg:phone":"+1 325 597 1615",
    "sg:postcode":"76825",
    "sg:province":"TX",
    "sg:tags":[
        "accountant"
    ],
    "wof:name":"Glenn T Miller CPA",
    "wof:placetype":"venue"
},
  "geometry": {"coordinates":[-99.33410600000001,31.13468],"type":"Point"}
}