{
  "type": "Feature",
  "properties": {
    "iso:country":"US",
    "sg:address":"119 Glen Ridge Dr",
    "sg:city":"Plano",
    "sg:classifiers":[
        {
            "category":"Building & Trades",
            "subcategory":"Construction",
            "type":"Services"
        }
    ],
    "sg:phone":"+1 972 633 1445",
    "sg:postcode":"75094",
    "sg:province":"TX",
    "sg:tags":[
        "house"
    ],
    "wof:name":"First Texas Homes Inc",
    "wof:placetype":"venue"
},
  "geometry": {"coordinates":[-96.613713,33.018118],"type":"Point"}
}