{
  "type": "Feature",
  "properties": {
    "iso:country":"US",
    "sg:address":"9732 Timberside Dr",
    "sg:city":"Houston",
    "sg:classifiers":[
        {
            "category":"Manufacturing",
            "subcategory":"Printing",
            "type":"Manufacturing & Wholesale Goods"
        }
    ],
    "sg:phone":"+1 713 664 5454",
    "sg:postcode":"77025",
    "sg:province":"TX",
    "sg:tags":[
        "services-commercial",
        "commercial",
        "lithographic"
    ],
    "wof:name":"Roger Printing Co",
    "wof:placetype":"venue"
},
  "geometry": {"coordinates":[-95.43234099999999,29.676894],"type":"Point"}
}