{
  "type": "Feature",
  "properties": {
    "iso:country":"US",
    "sg:address":"1016 State Hwy 323",
    "sg:city":"Tyler",
    "sg:classifiers":[
        {
            "category":"Utilities",
            "subcategory":"Mobile Phone",
            "type":"Services"
        }
    ],
    "sg:phone":"+1 903 561 5575",
    "sg:postcode":"75701",
    "sg:province":"TX",
    "sg:tags":[
        "telephone",
        "cellular"
    ],
    "wof:name":"Alltel Mobile",
    "wof:placetype":"venue"
},
  "geometry": {"coordinates":[-95.315164,32.303494],"type":"Point"}
}