{
  "type": "Feature",
  "properties": {
    "iso:country":"US",
    "sg:address":"7063 Alameda Ave",
    "sg:city":"El Paso",
    "sg:classifiers":[
        {
            "category":"Autos & Motor Vehicles",
            "subcategory":"Automobile Sales",
            "type":"Retail Goods"
        }
    ],
    "sg:phone":"+1 915 775 9939",
    "sg:postcode":"79915",
    "sg:province":"TX",
    "sg:tags":[
        "car",
        "dealer"
    ],
    "wof:name":"Flamingo Motors",
    "wof:placetype":"venue"
},
  "geometry": {"coordinates":[-106.394672,31.755762],"type":"Point"}
}