{
  "type": "Feature",
  "properties": {
    "iso:country":"US",
    "sg:address":"901 W Brand Rd",
    "sg:city":"Garland",
    "sg:classifiers":[
        {
            "category":"Real Estate",
            "subcategory":"Real Estate Operator",
            "type":"Services"
        }
    ],
    "sg:phone":"+1 972 495 0800",
    "sg:postcode":"75040",
    "sg:province":"TX",
    "sg:tags":[
        "building",
        "apartment"
    ],
    "wof:name":"Brandon Walk Apts",
    "wof:placetype":"venue"
},
  "geometry": {"coordinates":[-96.639926,32.949723],"type":"Point"}
}