{
  "type": "Feature",
  "properties": {
    "iso:country":"US",
    "sg:address":"2605 Mansfield Hwy",
    "sg:city":"Fort Worth",
    "sg:classifiers":[
        {
            "category":"Professional",
            "subcategory":"Art Services",
            "type":"Services"
        }
    ],
    "sg:phone":"+1 817 534 9649",
    "sg:postcode":"76119",
    "sg:province":"TX",
    "sg:tags":[
        "graphic",
        "designer"
    ],
    "wof:name":"B & F Graphix 2000",
    "wof:placetype":"venue"
},
  "geometry": {"coordinates":[-97.293807,32.689609],"type":"Point"}
}