{
  "type": "Feature",
  "properties": {
    "iso:country":"US",
    "sg:address":"1220 E Main St",
    "sg:city":"Grand Prairie",
    "sg:classifiers":[
        {
            "category":"Wholesale",
            "subcategory":"Motor Vehicles",
            "type":"Manufacturing & Wholesale Goods"
        }
    ],
    "sg:phone":"+1 972 263 3952",
    "sg:postcode":"75050",
    "sg:province":"TX",
    "sg:tags":[
        "automobile",
        "used"
    ],
    "wof:name":"Century Wholesale Trucks",
    "wof:placetype":"venue"
},
  "geometry": {"coordinates":[-96.988726,32.747006],"type":"Point"}
}