{
  "type": "Feature",
  "properties": {
    "iso:country":"US",
    "sg:address":"100 E US Hwy 83",
    "sg:city":"San Juan",
    "sg:classifiers":[
        {
            "category":"Utilities",
            "subcategory":"Mobile Phone",
            "type":"Services"
        }
    ],
    "sg:phone":"+1 956 782 9806",
    "sg:postcode":"78589",
    "sg:province":"TX",
    "sg:tags":[
        "telephone",
        "cellular"
    ],
    "wof:name":"Cell Plus Wireless",
    "wof:placetype":"venue"
},
  "geometry": {"coordinates":[-98.15393400000001,26.18929],"type":"Point"}
}