{
  "type": "Feature",
  "properties": {
    "iso:country":"US",
    "sg:address":"2721 Cladius Dr",
    "sg:city":"Grand Prairie",
    "sg:classifiers":[
        {
            "category":"Professional",
            "subcategory":"Engineering",
            "type":"Services"
        }
    ],
    "sg:phone":"+1 972 660 8482",
    "sg:postcode":"75052",
    "sg:province":"TX",
    "wof:name":"Cadick Corp",
    "wof:placetype":"venue"
},
  "geometry": {"coordinates":[-97.050268,32.683124],"type":"Point"}
}