{
  "type": "Feature",
  "properties": {
    "iso:country":"US",
    "sg:address":"4607 US Hwy 54",
    "sg:city":"Dalhart",
    "sg:classifiers":[
        {
            "category":"Freight",
            "type":"Transportation"
        },
        {
            "category":"Wholesale",
            "subcategory":"Farm Supplies",
            "type":"Manufacturing & Wholesale Goods"
        }
    ],
    "sg:phone":"+1 806 384 2164",
    "sg:postcode":"79022",
    "sg:province":"TX",
    "sg:tags":[
        "bean",
        "grain",
        "elevator"
    ],
    "wof:name":"Sunray Co-Op",
    "wof:placetype":"venue"
},
  "geometry": {"coordinates":[-102.24103599999999,36.233056],"type":"Point"}
}