{
  "type": "Feature",
  "properties": {
    "iso:country":"US",
    "sg:address":"7193 W Circle Dr",
    "sg:city":"Dallas",
    "sg:classifiers":[
        {
            "category":"Sports & Exercise",
            "subcategory":"Golf",
            "type":"Entertainment"
        }
    ],
    "sg:phone":"+1 214 824 5667",
    "sg:postcode":"75214",
    "sg:province":"TX",
    "sg:tags":[
        "course",
        "public"
    ],
    "sg:website":"www.caddieclubgolf.com",
    "wof:name":"Caddie Club",
    "wof:placetype":"venue"
},
  "geometry": {"coordinates":[-96.733299,32.843102],"type":"Point"}
}