{
  "type": "Feature",
  "properties": {
    "iso:country":"US",
    "sg:address":"3071 Locke Ln",
    "sg:city":"Houston",
    "sg:classifiers":[
        {
            "category":"Building & Trades",
            "subcategory":"Construction",
            "type":"Services"
        }
    ],
    "sg:phone":"+1 713 523 2784",
    "sg:postcode":"77019",
    "sg:province":"TX",
    "sg:tags":[
        "housing"
    ],
    "wof:name":"Acorn Home Builders Inc",
    "wof:placetype":"venue"
},
  "geometry": {"coordinates":[-95.421007,29.743138],"type":"Point"}
}