{
  "type": "Feature",
  "properties": {
    "iso:country":"US",
    "sg:address":"515 Riggs Cir",
    "sg:city":"Mesquite",
    "sg:classifiers":[
        {
            "category":"Retail",
            "subcategory":"Laundry & Dry Cleaning",
            "type":"Services"
        }
    ],
    "sg:phone":"+1 972 216 3588",
    "sg:postcode":"75149",
    "sg:province":"TX",
    "sg:tags":[
        "repairing",
        "rug",
        "carpet"
    ],
    "wof:name":"Tom Cat Mold Remediation",
    "wof:placetype":"venue"
},
  "geometry": {"coordinates":[-96.604178,32.751294],"type":"Point"}
}