{
  "type": "Feature",
  "properties": {
    "iso:country":"US",
    "sg:address":"8601 Ranch Rd 2222",
    "sg:city":"Austin",
    "sg:classifiers":[
        {
            "category":"Professional",
            "subcategory":"Management & Consulting",
            "type":"Services"
        }
    ],
    "sg:phone":"+1 512 241 8613",
    "sg:postcode":"78730",
    "sg:province":"TX",
    "wof:name":"Jetfuel Partners Inc",
    "wof:placetype":"venue"
},
  "geometry": {"coordinates":[-97.818579,30.383441],"type":"Point"}
}