{
  "type": "Feature",
  "properties": {
    "iso:country":"US",
    "sg:address":"3975 State Hwy 92",
    "sg:city":"Stamford",
    "sg:phone":"+1 325 773 2189",
    "sg:postcode":"79553",
    "sg:province":"TX",
    "sg:tags":[
        "farm",
        "wheat",
        "cotton"
    ],
    "wof:name":"Carl Marugg",
    "wof:placetype":"venue"
},
  "geometry": {"coordinates":[-99.89962800000001,32.922778],"type":"Point"}
}