{
  "type": "Feature",
  "properties": {
    "iso:country":"US",
    "sg:address":"454 E Highway 67",
    "sg:city":"Duncanville",
    "sg:classifiers":[
        {
            "category":"Food & Beverages",
            "subcategory":"Groceries & Convenience Stores",
            "type":"Retail Goods"
        }
    ],
    "sg:phone":"+1 972 572 3155",
    "sg:postcode":"75137",
    "sg:province":"TX",
    "wof:name":"Panther Market",
    "wof:placetype":"venue"
},
  "geometry": {"coordinates":[-96.900299,32.631802],"type":"Point"}
}