{
  "type": "Feature",
  "properties": {
    "iso:country":"US",
    "sg:address":"3026 Cinnamon Glen Dr",
    "sg:city":"Houston",
    "sg:classifiers":[
        {
            "category":"Professional",
            "subcategory":"Business Services",
            "type":"Services"
        }
    ],
    "sg:phone":"+1 281 209 1348",
    "sg:postcode":"77073",
    "sg:province":"TX",
    "wof:name":"Sam Maghett Express",
    "wof:placetype":"venue"
},
  "geometry": {"coordinates":[-95.377638,30.012459],"type":"Point"}
}