{
  "type": "Feature",
  "properties": {
    "iso:country":"US",
    "sg:address":"6060 Richmond Ave",
    "sg:city":"Houston",
    "sg:classifiers":[
        {
            "category":"Real Estate",
            "subcategory":"Real Estate Agent",
            "type":"Services"
        }
    ],
    "sg:phone":"+1 713 334 6766",
    "sg:postcode":"77057",
    "sg:province":"TX",
    "wof:name":"Townhome Realty",
    "wof:placetype":"venue"
},
  "geometry": {"coordinates":[-95.486296,29.731768],"type":"Point"}
}