{
  "type": "Feature",
  "properties": {
    "iso:country":"US",
    "sg:address":"1904 Quaker Ave",
    "sg:city":"Lubbock",
    "sg:classifiers":[
        {
            "category":"Retail",
            "subcategory":"Auto Repair",
            "type":"Services"
        }
    ],
    "sg:phone":"+1 806 793 1211",
    "sg:postcode":"79407",
    "sg:province":"TX",
    "sg:tags":[
        "automotive",
        "general"
    ],
    "wof:name":"Rapid Oil Change Inc",
    "wof:placetype":"venue"
},
  "geometry": {"coordinates":[-101.905181,33.575023],"type":"Point"}
}