{
  "type": "Feature",
  "properties": {
    "iso:country":"US",
    "sg:address":"9623 Boerne Spring",
    "sg:city":"Boerne",
    "sg:classifiers":[
        {
            "category":"Retail",
            "subcategory":"Repair Shop",
            "type":"Services"
        }
    ],
    "sg:phone":"+1 210 275 7883",
    "sg:postcode":"78006",
    "sg:province":"TX",
    "sg:tags":[
        "mobile",
        "refinishing",
        "furniture"
    ],
    "wof:name":"Guardsman Furniture Pro",
    "wof:placetype":"venue"
},
  "geometry": {"coordinates":[-98.682743,29.70157],"type":"Point"}
}