{
  "type": "Feature",
  "properties": {
    "iso:country":"US",
    "sg:address":"6803 Almeda Rd",
    "sg:city":"Houston",
    "sg:classifiers":[
        {
            "category":"Food & Beverages",
            "subcategory":"Bakery",
            "type":"Retail Goods"
        },
        {
            "category":"Wholesale",
            "subcategory":"Groceries",
            "type":"Manufacturing & Wholesale Goods"
        }
    ],
    "sg:phone":"+1 713 749 0400",
    "sg:postcode":"77021",
    "sg:province":"TX",
    "sg:tags":[
        "cooky",
        "crackers-wholesale",
        "cracker",
        "manufacturer"
    ],
    "sg:website":"http://www.kraftfoods.com",
    "wof:name":"Nabisco",
    "wof:placetype":"venue"
},
  "geometry": {"coordinates":[-95.385262,29.703175],"type":"Point"}
}