{
  "type": "Feature",
  "properties": {
    "iso:country":"US",
    "sg:address":"4820 Ave H",
    "sg:city":"Rosenberg",
    "sg:classifiers":[
        {
            "category":"Autos & Motor Vehicles",
            "subcategory":"Automobile Sales",
            "type":"Retail Goods"
        }
    ],
    "sg:phone":"+1 281 633 9011",
    "sg:postcode":"77471",
    "sg:province":"TX",
    "sg:tags":[
        "car",
        "dealer"
    ],
    "wof:name":"Car Choice",
    "wof:placetype":"venue"
},
  "geometry": {"coordinates":[-95.779123,29.56821],"type":"Point"}
}