{
  "type": "Feature",
  "properties": {
    "iso:country":"US",
    "sg:address":"7350 Harwin Dr",
    "sg:city":"Houston",
    "sg:classifiers":[
        {
            "category":"Wholesale",
            "subcategory":"Apparel",
            "type":"Manufacturing & Wholesale Goods"
        }
    ],
    "sg:phone":"+1 713 278 1448",
    "sg:postcode":"77036",
    "sg:province":"TX",
    "sg:tags":[
        "clothing"
    ],
    "wof:name":"Suits Plus",
    "wof:placetype":"venue"
},
  "geometry": {"coordinates":[-95.510885,29.717827],"type":"Point"}
}