{
  "type": "Feature",
  "properties": {
    "iso:country":"US",
    "sg:address":"1252 W Kingsbury St",
    "sg:city":"Seguin",
    "sg:classifiers":[
        {
            "category":"Retail",
            "subcategory":"Veterinary Services",
            "type":"Services"
        }
    ],
    "sg:phone":"+1 830 379 3821",
    "sg:postcode":"78155",
    "sg:province":"TX",
    "sg:tags":[
        "veterinarian"
    ],
    "wof:name":"Seguin Animal Hospital",
    "wof:placetype":"venue"
},
  "geometry": {"coordinates":[-97.98080899999999,29.579728],"type":"Point"}
}