{
  "type": "Feature",
  "properties": {
    "iso:country":"US",
    "sg:address":"177 Artillery Loop",
    "sg:city":"San Antonio",
    "sg:classifiers":[
        {
            "category":"Manufacturing",
            "subcategory":"Printing",
            "type":"Manufacturing & Wholesale Goods"
        }
    ],
    "sg:phone":"+1 210 224 1522",
    "sg:postcode":"78234",
    "sg:province":"TX",
    "sg:tags":[
        "publishing"
    ],
    "wof:name":"Compass Publishing LP",
    "wof:placetype":"venue"
},
  "geometry": {"coordinates":[-98.462125,29.45238],"type":"Point"}
}