{
  "type": "Feature",
  "properties": {
    "iso:country":"US",
    "sg:address":"3038 S 31st St",
    "sg:city":"Temple",
    "sg:classifiers":[
        {
            "category":"Restaurant",
            "type":"Food & Drink"
        }
    ],
    "sg:phone":"+1 254 742 1207",
    "sg:postcode":"76502",
    "sg:province":"TX",
    "sg:tags":[
        "delicatessen"
    ],
    "wof:name":"Roly Poly",
    "wof:placetype":"venue"
},
  "geometry": {"coordinates":[-97.36851,31.07216],"type":"Point"}
}