{
  "type": "Feature",
  "properties": {
    "iso:country":"US",
    "sg:address":"102 Decker Ct",
    "sg:city":"Irving",
    "sg:classifiers":[
        {
            "category":"Health Services",
            "subcategory":"Doctor",
            "type":"Services"
        }
    ],
    "sg:phone":"+1 972 717 6262",
    "sg:postcode":"75062",
    "sg:province":"TX",
    "sg:tags":[
        "physician",
        "surgeon",
        "psychiatrist"
    ],
    "wof:name":"University Hills Clinical Research",
    "wof:placetype":"venue"
},
  "geometry": {"coordinates":[-96.94789900000001,32.865002],"type":"Point"}
}