{
  "type": "Feature",
  "properties": {
    "iso:country":"US",
    "sg:address":"31218 Bermar St",
    "sg:city":"Magnolia",
    "sg:classifiers":[
        {
            "category":"Building & Trades",
            "subcategory":"Construction",
            "type":"Services"
        }
    ],
    "sg:phone":"+1 281 356 9316",
    "sg:postcode":"77355",
    "sg:province":"TX",
    "sg:tags":[
        "heavy"
    ],
    "wof:name":"East Texas Improvements",
    "wof:placetype":"venue"
},
  "geometry": {"coordinates":[-95.72506300000001,30.114684],"type":"Point"}
}