{
  "type": "Feature",
  "properties": {
    "iso:country":"US",
    "sg:address":"2111 Crockett St",
    "sg:city":"Orange",
    "sg:classifiers":[
        {
            "category":"Building & Trades",
            "subcategory":"Construction",
            "type":"Services"
        }
    ],
    "sg:phone":"+1 409 882 9245",
    "sg:postcode":"77630",
    "sg:province":"TX",
    "sg:tags":[
        "mobile",
        "home"
    ],
    "wof:name":"National Mobile Home Svc",
    "wof:placetype":"venue"
},
  "geometry": {"coordinates":[-93.753744,30.081724],"type":"Point"}
}