{
  "type": "Feature",
  "properties": {
    "iso:country":"US",
    "sg:address":"7399 Alameda Ave",
    "sg:city":"El Paso",
    "sg:classifiers":[
        {
            "category":"Insurance",
            "subcategory":"Insurance Agent",
            "type":"Services"
        }
    ],
    "sg:phone":"+1 915 772 9380",
    "sg:postcode":"79915",
    "sg:province":"TX",
    "wof:name":"Pan American Insurance Agency",
    "wof:placetype":"venue"
},
  "geometry": {"coordinates":[-106.380887,31.744491],"type":"Point"}
}