{
  "type": "Feature",
  "properties": {
    "iso:country":"US",
    "sg:address":"9922 Woodlake Dr",
    "sg:city":"Dallas",
    "sg:classifiers":[
        {
            "category":"Professional",
            "type":"Services"
        }
    ],
    "sg:phone":"+1 972 907 8088",
    "sg:postcode":"75243",
    "sg:province":"TX",
    "wof:name":"Akemis RE Creations",
    "wof:placetype":"venue"
},
  "geometry": {"coordinates":[-96.715425,32.912496],"type":"Point"}
}