{
  "type": "Feature",
  "properties": {
    "iso:country":"US",
    "sg:address":"6706 Dinner Creek Ct",
    "sg:city":"Katy",
    "sg:classifiers":[
        {
            "category":"Professional",
            "type":"Services"
        }
    ],
    "sg:phone":"+1 281 373 1694",
    "sg:postcode":"77449",
    "sg:province":"TX",
    "wof:name":"Mksystems",
    "wof:placetype":"venue"
},
  "geometry": {"coordinates":[-95.68541500000001,29.87172],"type":"Point"}
}