{
  "type": "Feature",
  "properties": {
    "iso:country":"US",
    "sg:address":"4301 Cavazos St",
    "sg:city":"Mission",
    "sg:classifiers":[
        {
            "category":"Home & Garden",
            "subcategory":"Building Materials",
            "type":"Retail Goods"
        }
    ],
    "sg:phone":"+1 956 585 2503",
    "sg:postcode":"78573",
    "sg:province":"TX",
    "sg:tags":[
        "repair"
    ],
    "wof:name":"Angels Garage Doors",
    "wof:placetype":"venue"
},
  "geometry": {"coordinates":[-98.337051,26.260892],"type":"Point"}
}