{
  "type": "Feature",
  "properties": {
    "iso:country":"US",
    "sg:address":"951 FM 1266",
    "sg:city":"Kemah",
    "sg:classifiers":[
        {
            "category":"Recreation",
            "type":"Entertainment"
        }
    ],
    "sg:phone":"+1 281 538 5850",
    "sg:postcode":"77565",
    "sg:province":"TX",
    "sg:tags":[
        "amusement"
    ],
    "wof:name":"Universal Cheer & Dance",
    "wof:placetype":"venue"
},
  "geometry": {"coordinates":[-95.03749500000001,29.523309],"type":"Point"}
}