{
  "type": "Feature",
  "properties": {
    "iso:country":"US",
    "sg:address":"3521 N Business 45",
    "sg:city":"Corsicana",
    "sg:classifiers":[
        {
            "category":"Place Of Worship",
            "subcategory":"Church",
            "type":"Public Place"
        },
        {
            "category":"Place Of Worship",
            "type":"Public Place"
        }
    ],
    "sg:phone":"+1 903 872 3664",
    "sg:postcode":"75110",
    "sg:province":"TX",
    "sg:tags":[
        "churches-pentecostal-independent",
        "churches-pentecostal"
    ],
    "wof:name":"East Texas District Pentecostal Church Of God",
    "wof:placetype":"venue"
},
  "geometry": {"coordinates":[-96.467451,32.131961],"type":"Point"}
}