{
  "type": "Feature",
  "properties": {
    "iso:country":"US",
    "sg:address":"512 E Hamilton St",
    "sg:city":"Stamford",
    "sg:classifiers":[
        {
            "category":"Food & Beverages",
            "subcategory":"Groceries & Convenience Stores",
            "type":"Retail Goods"
        }
    ],
    "sg:phone":"+1 325 773 3993",
    "sg:postcode":"79553",
    "sg:province":"TX",
    "wof:name":"Wes-T-Go",
    "wof:placetype":"venue"
},
  "geometry": {"coordinates":[-99.796454,32.943947],"type":"Point"}
}