{
  "type": "Feature",
  "properties": {
    "iso:country":"US",
    "sg:address":"10039 Bissonnet St",
    "sg:city":"Houston",
    "sg:classifiers":[
        {
            "category":"Social Services",
            "subcategory":"Adult Care",
            "type":"Services"
        }
    ],
    "sg:phone":"+1 713 484 7233",
    "sg:postcode":"77036",
    "sg:province":"TX",
    "sg:tags":[
        "residential"
    ],
    "wof:name":"Safe Haven Community Foster CA",
    "wof:placetype":"venue"
},
  "geometry": {"coordinates":[-95.555432,29.674896],"type":"Point"}
}