{
  "type": "Feature",
  "properties": {
    "iso:country":"US",
    "sg:address":"6611 Killough St",
    "sg:city":"Houston",
    "sg:classifiers":[
        {
            "category":"Wholesale",
            "subcategory":"Machinery & Supplies",
            "type":"Manufacturing & Wholesale Goods"
        }
    ],
    "sg:phone":"+1 281 999 0991",
    "sg:postcode":"77086",
    "sg:province":"TX",
    "sg:tags":[
        "equipment",
        "industrial"
    ],
    "wof:name":"Glitsch Technology",
    "wof:placetype":"venue"
},
  "geometry": {"coordinates":[-95.49559600000001,29.903783],"type":"Point"}
}