{
  "type": "Feature",
  "properties": {
    "iso:country":"US",
    "sg:address":"504 S Buffalo Ave",
    "sg:city":"Cedar Park",
    "sg:classifiers":[
        {
            "category":"Building & Trades",
            "subcategory":"Electrical",
            "type":"Services"
        }
    ],
    "sg:phone":"+1 512 259 2918",
    "sg:postcode":"78613",
    "sg:province":"TX",
    "sg:tags":[
        "equipment",
        "protection",
        "lightning"
    ],
    "wof:name":"Texas Lightening Rod Co",
    "wof:placetype":"venue"
},
  "geometry": {"coordinates":[-97.812353,30.507943],"type":"Point"}
}