{
  "type": "Feature",
  "properties": {
    "iso:country":"US",
    "sg:address":"3024 Barron Ln",
    "sg:city":"Missouri City",
    "sg:classifiers":[
        {
            "category":"Building & Trades",
            "subcategory":"Landscaping Services",
            "type":"Services"
        }
    ],
    "sg:phone":"+1 281 437 1157",
    "sg:postcode":"77489",
    "sg:province":"TX",
    "sg:tags":[
        "landscape",
        "contractor"
    ],
    "wof:name":"Advance Landscaping Inc",
    "wof:placetype":"venue"
},
  "geometry": {"coordinates":[-95.50470900000001,29.583003],"type":"Point"}
}