{
  "type": "Feature",
  "properties": {
    "iso:country":"US",
    "sg:address":"339 Culebra Rd",
    "sg:city":"San Antonio",
    "sg:classifiers":[
        {
            "category":"Professional",
            "type":"Services"
        }
    ],
    "sg:phone":"+1 210 734 7033",
    "sg:postcode":"78201",
    "sg:province":"TX",
    "sg:tags":[
        "establishment"
    ],
    "wof:name":"Garza Way",
    "wof:placetype":"venue"
},
  "geometry": {"coordinates":[-98.508253,29.443557],"type":"Point"}
}