{
  "type": "Feature",
  "properties": {
    "iso:country":"US",
    "sg:address":"4101 Oak Lawn Ave",
    "sg:city":"Dallas",
    "sg:classifiers":[
        {
            "category":"Autos & Motor Vehicles",
            "subcategory":"Automobile Sales",
            "type":"Retail Goods"
        }
    ],
    "sg:phone":"+1 214 520 7485",
    "sg:postcode":"75219",
    "sg:province":"TX",
    "sg:tags":[
        "car"
    ],
    "wof:name":"Audi-Park Place Audi",
    "wof:placetype":"venue"
},
  "geometry": {"coordinates":[-96.802992,32.818922],"type":"Point"}
}