{
  "type": "Feature",
  "properties": {
    "iso:country":"US",
    "sg:address":"1901 US Hwy 83",
    "sg:city":"Crystal City",
    "sg:classifiers":[
        {
            "category":"Food & Beverages",
            "subcategory":"Groceries & Convenience Stores",
            "type":"Retail Goods"
        }
    ],
    "sg:phone":"+1 830 374 0044",
    "sg:postcode":"78839",
    "sg:province":"TX",
    "wof:name":"Cleo's Travel Ctr",
    "wof:placetype":"venue"
},
  "geometry": {"coordinates":[-99.830687,28.694335],"type":"Point"}
}