{
  "type": "Feature",
  "properties": {
    "iso:country":"US",
    "sg:address":"1510 I- 45 N",
    "sg:city":"Conroe",
    "sg:classifiers":[
        {
            "category":"Mining & Drilling",
            "type":"Manufacturing & Wholesale Goods"
        }
    ],
    "sg:phone":"+1 936 539 1020",
    "sg:postcode":"77301",
    "sg:province":"TX",
    "sg:tags":[
        "development",
        "gas",
        "oil",
        "exploration"
    ],
    "wof:name":"San Jacinto Energy Production",
    "wof:placetype":"venue"
},
  "geometry": {"coordinates":[-95.47321100000001,30.321405],"type":"Point"}
}