{
  "type": "Feature",
  "properties": {
    "iso:country":"US",
    "sg:address":"2240 Shorecrest Dr",
    "sg:city":"Rockwall",
    "sg:classifiers":[
        {
            "category":"Building & Trades",
            "subcategory":"Construction",
            "type":"Services"
        }
    ],
    "sg:phone":"+1 972 772 0118",
    "sg:postcode":"75087",
    "sg:province":"TX",
    "sg:tags":[
        "house"
    ],
    "wof:name":"Drees Homes Co",
    "wof:placetype":"venue"
},
  "geometry": {"coordinates":[-96.48336,32.945762],"type":"Point"}
}