{
  "type": "Feature",
  "properties": {
    "iso:country":"US",
    "sg:address":"700 N Garcia St",
    "sg:city":"Rio Grande City",
    "sg:classifiers":[
        {
            "category":"Restaurant",
            "type":"Food & Drink"
        }
    ],
    "sg:phone":"+1 956 488 2348",
    "sg:postcode":"78582",
    "sg:province":"TX",
    "sg:tags":[
        "eating"
    ],
    "wof:name":"El Cid Caravan 106 Inc",
    "wof:placetype":"venue"
},
  "geometry": {"coordinates":[-98.824625,26.387068],"type":"Point"}
}