{
  "type": "Feature",
  "properties": {
    "iso:country":"US",
    "sg:address":"1236 S Expressway 83",
    "sg:city":"Brownsville",
    "sg:classifiers":[
        {
            "category":"Autos & Motor Vehicles",
            "subcategory":"Automobile Sales",
            "type":"Retail Goods"
        }
    ],
    "sg:phone":"+1 956 544 2601",
    "sg:postcode":"78521",
    "sg:province":"TX",
    "sg:tags":[
        "used",
        "car",
        "dealers-used",
        "new",
        "cars-wholesale"
    ],
    "wof:name":"South Point Auto Sales",
    "wof:placetype":"venue"
},
  "geometry": {"coordinates":[-97.49038899999999,25.919675],"type":"Point"}
}