{
  "type": "Feature",
  "properties": {
    "iso:country":"US",
    "sg:address":"529 FM 400",
    "sg:city":"Plainview",
    "sg:classifiers":[
        {
            "category":"Farming",
            "subcategory":"Farm",
            "type":"Manufacturing & Wholesale Goods"
        }
    ],
    "sg:phone":"+1 806 296 7081",
    "sg:postcode":"79072",
    "sg:province":"TX",
    "sg:tags":[
        "crop",
        "general"
    ],
    "wof:name":"H W R W Palmer Partnership",
    "wof:placetype":"venue"
},
  "geometry": {"coordinates":[-101.673265,34.245345],"type":"Point"}
}