{
  "type": "Feature",
  "properties": {
    "iso:country":"US",
    "sg:address":"2103 Market St",
    "sg:city":"Baytown",
    "sg:classifiers":[
        {
            "category":"Government",
            "subcategory":"Office",
            "type":"Public Place"
        }
    ],
    "sg:phone":"+1 281 420 5399",
    "sg:postcode":"77520",
    "sg:province":"TX",
    "sg:tags":[
        "village"
    ],
    "wof:name":"Baytown Traffic Control Oper",
    "wof:placetype":"venue"
},
  "geometry": {"coordinates":[-94.99196000000001,29.731021],"type":"Point"}
}