{
  "type": "Feature",
  "properties": {
    "iso:country":"US",
    "sg:address":"1408 W Elm St",
    "sg:city":"Tyler",
    "sg:classifiers":[
        {
            "category":"Manufacturing",
            "subcategory":"Signs",
            "type":"Manufacturing & Wholesale Goods"
        }
    ],
    "sg:phone":"+1 903 593 6226",
    "sg:postcode":"75702",
    "sg:province":"TX",
    "wof:name":"Kirkland Sign Co Inc",
    "wof:placetype":"venue"
},
  "geometry": {"coordinates":[-95.31779299999999,32.349316],"type":"Point"}
}