{
  "type": "Feature",
  "properties": {
    "iso:country":"US",
    "sg:address":"1314 Pilot Point Dr",
    "sg:city":"Houston",
    "sg:classifiers":[
        {
            "category":"Building & Trades",
            "subcategory":"Construction",
            "type":"Services"
        }
    ],
    "sg:phone":"+1 281 447 7604",
    "sg:postcode":"77038",
    "sg:province":"TX",
    "sg:tags":[
        "contractor"
    ],
    "wof:name":"Tile By Montemayor",
    "wof:placetype":"venue"
},
  "geometry": {"coordinates":[-95.443331,29.919755],"type":"Point"}
}