{
  "type": "Feature",
  "properties": {
    "iso:country":"US",
    "sg:address":"5602 Slide Rd",
    "sg:city":"Lubbock",
    "sg:classifiers":[
        {
            "category":"Health Services",
            "subcategory":"Optometrist",
            "type":"Services"
        }
    ],
    "sg:phone":"+1 806 785 1403",
    "sg:postcode":"79414",
    "sg:province":"TX",
    "wof:name":"Eyeworld Associates",
    "wof:placetype":"venue"
},
  "geometry": {"coordinates":[-101.92250199999999,33.543766],"type":"Point"}
}