{
  "type": "Feature",
  "properties": {
    "iso:country":"US",
    "sg:address":"310 N Clearview Ave",
    "sg:city":"Odessa",
    "sg:classifiers":[
        {
            "category":"Mining & Drilling",
            "type":"Manufacturing & Wholesale Goods"
        }
    ],
    "sg:phone":"+1 432 381 4221",
    "sg:postcode":"79763",
    "sg:province":"TX",
    "sg:tags":[
        "pipe",
        "inspection"
    ],
    "wof:name":"Allen Inspection Svc",
    "wof:placetype":"venue"
},
  "geometry": {"coordinates":[-102.481694,31.816967],"type":"Point"}
}