{
  "type": "Feature",
  "properties": {
    "iso:country":"US",
    "sg:address":"108 Creekside Dr",
    "sg:city":"Hutto",
    "sg:classifiers":[
        {
            "category":"Organizations",
            "subcategory":"Religious Organization",
            "type":"Services"
        }
    ],
    "sg:phone":"+1 512 759 9791",
    "sg:postcode":"78634",
    "sg:province":"TX",
    "wof:name":"Lifepointe Fellowship",
    "wof:placetype":"venue"
},
  "geometry": {"coordinates":[-97.54360800000001,30.550106],"type":"Point"}
}