{
  "type": "Feature",
  "properties": {
    "iso:country":"US",
    "sg:address":"208 W Dallas St",
    "sg:city":"Canton",
    "sg:classifiers":[
        {
            "category":"Wholesale",
            "subcategory":"Home Furnishings",
            "type":"Manufacturing & Wholesale Goods"
        }
    ],
    "sg:phone":"+1 903 567 7323",
    "sg:postcode":"75103",
    "sg:province":"TX",
    "sg:tags":[
        "pottery"
    ],
    "wof:name":"Canton Dish Barn",
    "wof:placetype":"venue"
},
  "geometry": {"coordinates":[-95.864597,32.556819],"type":"Point"}
}