{
  "type": "Feature",
  "properties": {
    "iso:country":"US",
    "sg:address":"4105 Rio Bravo St",
    "sg:city":"El Paso",
    "sg:classifiers":[
        {
            "category":"Professional",
            "subcategory":"Advertising",
            "type":"Services"
        }
    ],
    "sg:phone":"+1 915 544 9400",
    "sg:postcode":"79902",
    "sg:province":"TX",
    "sg:tags":[
        "counselor",
        "agency"
    ],
    "sg:website":"www.mithoffburton.com",
    "wof:name":"Mithoff/Burton Partners",
    "wof:placetype":"venue"
},
  "geometry": {"coordinates":[-106.516211,31.795082],"type":"Point"}
}