{
  "type": "Feature",
  "properties": {
    "iso:country":"US",
    "sg:address":"2616 Avenida Loop",
    "sg:city":"Irving",
    "sg:classifiers":[
        {
            "category":"Building & Trades",
            "subcategory":"Construction",
            "type":"Services"
        }
    ],
    "sg:phone":"+1 817 228 4499",
    "sg:postcode":"75062",
    "sg:province":"TX",
    "sg:tags":[
        "resurfacing",
        "laying",
        "refinishing",
        "floor"
    ],
    "wof:name":"T & H Tile",
    "wof:placetype":"venue"
},
  "geometry": {"coordinates":[-96.996044,32.842994],"type":"Point"}
}