{
  "type": "Feature",
  "properties": {
    "iso:country":"US",
    "sg:address":"23803 Clover Trl",
    "sg:city":"Katy",
    "sg:classifiers":[
        {
            "category":"Retail",
            "subcategory":"Auto Repair",
            "type":"Services"
        }
    ],
    "sg:phone":"+1 281 394 2239",
    "sg:postcode":"77494",
    "sg:province":"TX",
    "sg:tags":[
        "windshield"
    ],
    "wof:name":"Triumph Cabling Systems",
    "wof:placetype":"venue"
},
  "geometry": {"coordinates":[-95.786264,29.70227],"type":"Point"}
}