{
  "type": "Feature",
  "properties": {
    "iso:country":"US",
    "sg:address":"3627 Bonnie View Rd",
    "sg:city":"Dallas",
    "sg:classifiers":[
        {
            "category":"Professional",
            "subcategory":"Management & Consulting",
            "type":"Services"
        }
    ],
    "sg:phone":"+1 214 376 5500",
    "sg:postcode":"75216",
    "sg:province":"TX",
    "sg:tags":[
        "shop",
        "product",
        "tobacco"
    ],
    "wof:name":"Discount Tobacco Sales",
    "wof:placetype":"venue"
},
  "geometry": {"coordinates":[-96.77600099999999,32.714901],"type":"Point"}
}