{
  "type": "Feature",
  "properties": {
    "iso:country":"US",
    "sg:address":"16231 Green Smoke Dr",
    "sg:city":"Houston",
    "sg:classifiers":[
        {
            "category":"Professional",
            "subcategory":"Business Services",
            "type":"Services"
        }
    ],
    "sg:phone":"+1 281 855 8839",
    "sg:postcode":"77095",
    "sg:province":"TX",
    "wof:name":"Mmd Business Services",
    "wof:placetype":"venue"
},
  "geometry": {"coordinates":[-95.65379799999999,29.910571],"type":"Point"}
}