{
  "type": "Feature",
  "properties": {
    "iso:country":"US",
    "sg:address":"4201 W Parmer Ln",
    "sg:city":"Austin",
    "sg:classifiers":[
        {
            "category":"Health Services",
            "subcategory":"Doctor",
            "type":"Services"
        },
        {
            "category":"Insurance",
            "subcategory":"Hazard Insurance",
            "type":"Services"
        },
        {
            "category":"Insurance",
            "subcategory":"Health Insurance",
            "type":"Services"
        }
    ],
    "sg:phone":"+1 512 832 9922",
    "sg:postcode":"78727",
    "sg:province":"TX",
    "sg:tags":[
        "physician",
        "surgeon",
        "maintenance"
    ],
    "sg:website":"http://www.humanaventures.com",
    "wof:name":"Humana",
    "wof:placetype":"venue"
},
  "geometry": {"coordinates":[-97.717201,30.426411],"type":"Point"}
}