{
  "type": "Feature",
  "properties": {
    "iso:country":"US",
    "sg:address":"1101 State Loop 360",
    "sg:city":"Austin",
    "sg:classifiers":[
        {
            "category":"Health Services",
            "subcategory":"Health Practitioner",
            "type":"Services"
        }
    ],
    "sg:phone":"+1 512 347 1133",
    "sg:postcode":"78746",
    "sg:province":"TX",
    "sg:tags":[
        "psychologist"
    ],
    "wof:name":"Robert J Silver",
    "wof:placetype":"venue"
},
  "geometry": {"coordinates":[-97.819907,30.278209],"type":"Point"}
}