{
  "type": "Feature",
  "properties": {
    "iso:country":"US",
    "sg:address":"3401 Banning St",
    "sg:city":"Dallas",
    "sg:classifiers":[
        {
            "category":"Autos & Motor Vehicles",
            "subcategory":"Automobile Sales",
            "type":"Retail Goods"
        }
    ],
    "sg:phone":"+1 214 337 3065",
    "sg:postcode":"75233",
    "sg:province":"TX",
    "sg:tags":[
        "car",
        "dealer"
    ],
    "wof:name":"M J's Auto Sales",
    "wof:placetype":"venue"
},
  "geometry": {"coordinates":[-96.87665200000001,32.716994],"type":"Point"}
}