{
  "type": "Feature",
  "properties": {
    "iso:country":"US",
    "sg:address":"1501 Seamist Dr",
    "sg:city":"Houston",
    "sg:classifiers":[
        {
            "category":"Manufacturing",
            "subcategory":"Petroleum Products",
            "type":"Manufacturing & Wholesale Goods"
        }
    ],
    "sg:phone":"+1 713 849 2236",
    "sg:postcode":"77008",
    "sg:province":"TX",
    "sg:tags":[
        "contract"
    ],
    "wof:name":"Quiet Flex",
    "wof:placetype":"venue"
},
  "geometry": {"coordinates":[-95.43808,29.796391],"type":"Point"}
}