{
  "type": "Feature",
  "properties": {
    "iso:country":"US",
    "sg:address":"3821 Vancouver Cir",
    "sg:city":"Dallas",
    "sg:classifiers":[
        {
            "category":"Building & Trades",
            "subcategory":"Plumbing",
            "type":"Services"
        },
        {
            "category":"Retail",
            "subcategory":"Repair Shop",
            "type":"Services"
        }
    ],
    "sg:phone":"+1 214 351 2288",
    "sg:postcode":"75229",
    "sg:province":"TX",
    "sg:tags":[
        "system",
        "contractor",
        "equipment",
        "air conditioning"
    ],
    "wof:name":"Kittle Air Conditioning",
    "wof:placetype":"venue"
},
  "geometry": {"coordinates":[-96.85102000000001,32.896527],"type":"Point"}
}