{
  "type": "Feature",
  "properties": {
    "iso:country":"US",
    "sg:address":"3559 Belgium Ln",
    "sg:city":"San Antonio",
    "sg:classifiers":[
        {
            "category":"Professional",
            "subcategory":"Business Services",
            "type":"Services"
        }
    ],
    "sg:phone":"+1 210 467 0041",
    "sg:postcode":"78219",
    "sg:province":"TX",
    "sg:tags":[
        "for",
        "facility",
        "decoration",
        "convention",
        "meeting",
        "event",
        "special"
    ],
    "sg:website":"www.condec.com",
    "wof:name":"Convention Decorating Service",
    "wof:placetype":"venue"
},
  "geometry": {"coordinates":[-98.426497,29.439473],"type":"Point"}
}