{
  "type": "Feature",
  "properties": {
    "iso:country":"US",
    "sg:address":"11250 Briar Forest Dr",
    "sg:city":"Houston",
    "sg:classifiers":[
        {
            "category":"Banks & Credit Unions",
            "subcategory":"Investment Brokerage",
            "type":"Services"
        }
    ],
    "sg:phone":"+1 713 952 1669",
    "sg:postcode":"77042",
    "sg:province":"TX",
    "sg:tags":[
        "advisory",
        "mfg",
        "jewelry",
        "costume"
    ],
    "wof:name":"Art 2000",
    "wof:placetype":"venue"
},
  "geometry": {"coordinates":[-95.576089,29.748009],"type":"Point"}
}