{
  "type": "Feature",
  "properties": {
    "iso:country":"US",
    "sg:address":"131 Highway Dr",
    "sg:city":"San Antonio",
    "sg:classifiers":[
        {
            "category":"Shopping",
            "subcategory":"Hobbies, Toys, & Games",
            "type":"Retail Goods"
        }
    ],
    "sg:phone":"+1 210 337 1347",
    "sg:postcode":"78219",
    "sg:province":"TX",
    "wof:name":"On Sight Game Repair",
    "wof:placetype":"venue"
},
  "geometry": {"coordinates":[-98.40939299999999,29.426053],"type":"Point"}
}