{
  "type": "Feature",
  "properties": {
    "iso:country":"US",
    "sg:address":"2821 W 11th St",
    "sg:city":"Houston",
    "sg:classifiers":[
        {
            "category":"Manufacturing",
            "subcategory":"Electronics",
            "type":"Manufacturing & Wholesale Goods"
        }
    ],
    "sg:phone":"+1 713 880 0909",
    "sg:postcode":"77008",
    "sg:province":"TX",
    "sg:tags":[
        "electronic",
        "power",
        "supply"
    ],
    "sg:website":"www.custom-power.com",
    "wof:name":"Custom Power Inc",
    "wof:placetype":"venue"
},
  "geometry": {"coordinates":[-95.42780999999999,29.789275],"type":"Point"}
}