{
  "type": "Feature",
  "properties": {
    "iso:country":"US",
    "sg:address":"2230 Bissonnet St",
    "sg:city":"Houston",
    "sg:classifiers":[
        {
            "category":"Shopping",
            "subcategory":"Used Merchandise",
            "type":"Retail Goods"
        }
    ],
    "sg:phone":"+1 713 524 3272",
    "sg:postcode":"77005",
    "sg:province":"TX",
    "sg:tags":[
        "antique"
    ],
    "sg:website":"www.lrantiques.com",
    "wof:name":"L & R Antiques",
    "wof:placetype":"venue"
},
  "geometry": {"coordinates":[-95.412003,29.7257],"type":"Point"}
}