{
  "type": "Feature",
  "properties": {
    "iso:country":"US",
    "sg:address":"811 Voss Ave",
    "sg:city":"Odem",
    "sg:classifiers":[
        {
            "category":"Fast Food",
            "type":"Food & Drink"
        },
        {
            "category":"Restaurant",
            "type":"Food & Drink"
        }
    ],
    "sg:phone":"+1 361 368 4405",
    "sg:postcode":"78370",
    "sg:province":"TX",
    "sg:tags":[
        "hamburger",
        "hot",
        "dog",
        "american",
        "take",
        "chicken"
    ],
    "sg:website":"http://www.mcdonalds.com",
    "wof:name":"McDonald's",
    "wof:placetype":"venue"
},
  "geometry": {"coordinates":[-97.584593,27.947909],"type":"Point"}
}