{
  "type": "Feature",
  "properties": {
    "iso:country":"US",
    "sg:address":"3100 River Bend Dr",
    "sg:city":"Hurst",
    "sg:classifiers":[
        {
            "category":"Personal",
            "type":"Services"
        }
    ],
    "sg:phone":"+1 817 581 3777",
    "sg:postcode":"76054",
    "sg:province":"TX",
    "wof:name":"Northeast Wedding Chapel",
    "wof:placetype":"venue"
},
  "geometry": {"coordinates":[-97.17372400000001,32.878257],"type":"Point"}
}