{
  "type": "Feature",
  "properties": {
    "iso:country":"US",
    "sg:address":"8311 Damascus Dr",
    "sg:city":"Boerne",
    "sg:classifiers":[
        {
            "category":"Shopping",
            "subcategory":"Clothing, Apparel, & Fashions",
            "type":"Retail Goods"
        }
    ],
    "sg:phone":"+1 210 687 1332",
    "sg:postcode":"78015",
    "sg:province":"TX",
    "sg:tags":[
        "wear"
    ],
    "wof:name":"Bluebonnets & Bows Boutique",
    "wof:placetype":"venue"
},
  "geometry": {"coordinates":[-98.6477,29.722831],"type":"Point"}
}