{
  "type": "Feature",
  "properties": {
    "iso:country":"US",
    "sg:address":"3410 Hondo Pass Ave",
    "sg:city":"El Paso",
    "sg:classifiers":[
        {
            "category":"Health Services",
            "subcategory":"Doctor",
            "type":"Services"
        }
    ],
    "sg:phone":"+1 915 759 7700",
    "sg:postcode":"79904",
    "sg:province":"TX",
    "sg:tags":[
        "physician",
        "surgeon"
    ],
    "wof:name":"Mountain View Dermatology",
    "wof:placetype":"venue"
},
  "geometry": {"coordinates":[-106.451733,31.869373],"type":"Point"}
}