{
  "type": "Feature",
  "properties": {
    "iso:country":"US",
    "sg:address":"115 Dellis St",
    "sg:city":"Terrell",
    "sg:classifiers":[
        {
            "category":"Shopping",
            "subcategory":"Jewelry",
            "type":"Retail Goods"
        }
    ],
    "sg:phone":"+1 972 563 3654",
    "sg:postcode":"75160",
    "sg:province":"TX",
    "wof:name":"D R Martin",
    "wof:placetype":"venue"
},
  "geometry": {"coordinates":[-96.266819,32.735792],"type":"Point"}
}