{
  "type": "Feature",
  "properties": {
    "iso:country":"US",
    "sg:address":"1505 Panola Dr",
    "sg:city":"Mesquite",
    "sg:classifiers":[
        {
            "category":"Manufacturing",
            "subcategory":"Tools & Machinery",
            "type":"Manufacturing & Wholesale Goods"
        }
    ],
    "sg:phone":"+1 972 686 6403",
    "sg:postcode":"75150",
    "sg:province":"TX",
    "sg:tags":[
        "computer",
        "electronic",
        "mfg"
    ],
    "wof:name":"RC Electronics",
    "wof:placetype":"venue"
},
  "geometry": {"coordinates":[-96.61979700000001,32.819124],"type":"Point"}
}