{
  "type": "Feature",
  "properties": {
    "iso:country":"US",
    "sg:address":"326 Meadowlakes Dr",
    "sg:city":"Marble Falls",
    "sg:classifiers":[
        {
            "category":"Manufacturing",
            "subcategory":"Toys & Sporting Goods",
            "type":"Manufacturing & Wholesale Goods"
        }
    ],
    "sg:phone":"+1 830 693 6101",
    "sg:postcode":"78654",
    "sg:province":"TX",
    "sg:tags":[
        "mfg"
    ],
    "wof:name":"Catherine Hicks",
    "wof:placetype":"venue"
},
  "geometry": {"coordinates":[-98.29922500000001,30.556791],"type":"Point"}
}