{
  "type": "Feature",
  "properties": {
    "iso:country":"US",
    "sg:address":"7927 W University Blvd",
    "sg:city":"Odessa",
    "sg:classifiers":[
        {
            "category":"Retail",
            "subcategory":"Auto Repair",
            "type":"Services"
        }
    ],
    "sg:phone":"+1 432 381 2100",
    "sg:postcode":"79764",
    "sg:province":"TX",
    "sg:tags":[
        "exchanging",
        "engine"
    ],
    "wof:name":"White's Engine Repair",
    "wof:placetype":"venue"
},
  "geometry": {"coordinates":[-102.46963599999999,31.848179],"type":"Point"}
}