{
  "type": "Feature",
  "properties": {
    "iso:country":"US",
    "sg:address":"202 State Hwy 107",
    "sg:city":"Edinburg",
    "sg:classifiers":[
        {
            "category":"Travel",
            "subcategory":"Hotels & Motels",
            "type":"Entertainment"
        }
    ],
    "sg:phone":"+1 956 381 1688",
    "sg:postcode":"78539",
    "sg:province":"TX",
    "wof:name":"Super 8 Motel",
    "wof:placetype":"venue"
},
  "geometry": {"coordinates":[-98.160173,26.300988],"type":"Point"}
}