{
  "type": "Feature",
  "properties": {
    "iso:country":"US",
    "sg:address":"5909 West Loop South #470",
    "sg:city":"Houston",
    "sg:classifiers":[
        {
            "category":"Health Services",
            "subcategory":"Clinic",
            "type":"Services"
        }
    ],
    "sg:phone":"+1 713 906 4234",
    "sg:postcode":"77035",
    "sg:province":"TX",
    "sg:tags":[
        "medical"
    ],
    "sg:website":"www.melanieharrell.com",
    "wof:name":"Melanie Harrell",
    "wof:placetype":"venue"
},
  "geometry": {"coordinates":[-95.452077,29.801526],"type":"Point"}
}