{
  "type": "Feature",
  "properties": {
    "iso:country":"US",
    "sg:address":"5800 Avery Island Ave",
    "sg:city":"Austin",
    "sg:classifiers":[
        {
            "category":"Wholesale",
            "subcategory":"Machinery & Supplies",
            "type":"Manufacturing & Wholesale Goods"
        }
    ],
    "sg:phone":"+1 512 918 8435",
    "sg:postcode":"78727",
    "sg:province":"TX",
    "sg:tags":[
        "equipment",
        "printing"
    ],
    "wof:name":"Roman & Roman Tile Setter",
    "wof:placetype":"venue"
},
  "geometry": {"coordinates":[-97.742535,30.433435],"type":"Point"}
}