{
  "type": "Feature",
  "properties": {
    "iso:country":"US",
    "sg:address":"5402 North Fwy",
    "sg:city":"Houston",
    "sg:classifiers":[
        {
            "category":"Autos & Motor Vehicles",
            "subcategory":"Fuel & Gas Station",
            "type":"Retail Goods"
        }
    ],
    "sg:phone":"+1 713 691 0276",
    "sg:postcode":"77076",
    "sg:province":"TX",
    "wof:name":"Exxon Company U S A",
    "wof:placetype":"venue"
},
  "geometry": {"coordinates":[-95.392403,29.8458],"type":"Point"}
}