{
  "type": "Feature",
  "properties": {
    "iso:country":"US",
    "sg:address":"1415 S Zapata Hwy",
    "sg:city":"Laredo",
    "sg:classifiers":[
        {
            "category":"Retail",
            "subcategory":"Auto Repair",
            "type":"Services"
        }
    ],
    "sg:phone":"+1 956 725 6306",
    "sg:postcode":"78046",
    "sg:province":"TX",
    "sg:tags":[
        "general"
    ],
    "wof:name":"Benavides Service Center",
    "wof:placetype":"venue"
},
  "geometry": {"coordinates":[-99.47179300000001,27.48421],"type":"Point"}
}