{
  "type": "Feature",
  "properties": {
    "iso:country":"US",
    "sg:address":"8701 N Mo Pac Expy # 110",
    "sg:city":"Austin",
    "sg:classifiers":[
        {
            "category":"Organizations",
            "subcategory":"Non-profit Organization",
            "type":"Services"
        }
    ],
    "sg:phone":"+1 512 343 0663",
    "sg:postcode":"78759",
    "sg:province":"TX",
    "sg:tags":[
        "fund",
        "raising"
    ],
    "sg:website":"http://www.jdrfgeorgia.org",
    "wof:name":"Jdrfi",
    "wof:placetype":"venue"
},
  "geometry": {"coordinates":[-97.73994399999999,30.373795],"type":"Point"}
}