{
  "type": "Feature",
  "properties": {
    "iso:country":"US",
    "sg:address":"595 Christine Rd",
    "sg:city":"Jourdanton",
    "sg:classifiers":[
        {
            "category":"Building & Trades",
            "subcategory":"Construction",
            "type":"Services"
        },
        {
            "category":"Manufacturing",
            "subcategory":"Building Materials",
            "type":"Manufacturing & Wholesale Goods"
        }
    ],
    "sg:phone":"+1 830 769 2150",
    "sg:postcode":"78026",
    "sg:province":"TX",
    "sg:tags":[
        "cabinetmakers-commercial",
        "industrial",
        "maker",
        "cabinet"
    ],
    "wof:name":"Affordable Cabinets",
    "wof:placetype":"venue"
},
  "geometry": {"coordinates":[-98.5231,28.894758],"type":"Point"}
}