{
  "type": "Feature",
  "properties": {
    "iso:country":"US",
    "sg:address":"5540 North Fwy",
    "sg:city":"Houston",
    "sg:classifiers":[
        {
            "category":"Shopping",
            "subcategory":"Clothing, Apparel, & Fashions",
            "type":"Retail Goods"
        }
    ],
    "sg:phone":"+1 713 694 6504",
    "sg:postcode":"77076",
    "sg:province":"TX",
    "wof:name":"Fallas Paredes",
    "wof:placetype":"venue"
},
  "geometry": {"coordinates":[-95.39402699999999,29.847086],"type":"Point"}
}