{
  "type": "Feature",
  "properties": {
    "iso:country":"US",
    "sg:address":"3406 Dorothy Jane Dr",
    "sg:city":"Killeen",
    "sg:classifiers":[
        {
            "category":"Shopping",
            "subcategory":"Clothing, Apparel, & Fashions",
            "type":"Retail Goods"
        }
    ],
    "sg:phone":"+1 254 526 6331",
    "sg:postcode":"76542",
    "sg:province":"TX",
    "sg:tags":[
        "uniform"
    ],
    "wof:name":"K K & J Uniforms",
    "wof:placetype":"venue"
},
  "geometry": {"coordinates":[-97.727936,31.084985],"type":"Point"}
}