{
  "type": "Feature",
  "properties": {
    "iso:country":"US",
    "sg:address":"216 W Cedar St",
    "sg:city":"Whitewright",
    "sg:classifiers":[
        {
            "category":"Social Services",
            "subcategory":"Child Care",
            "type":"Services"
        }
    ],
    "sg:phone":"+1 903 364 5379",
    "sg:postcode":"75491",
    "sg:province":"TX",
    "sg:tags":[
        "day"
    ],
    "wof:name":"Premier Day Care",
    "wof:placetype":"venue"
},
  "geometry": {"coordinates":[-96.394578,33.516896],"type":"Point"}
}