{
  "type": "Feature",
  "properties": {
    "iso:country":"US",
    "sg:address":"4945 Highbank Dr",
    "sg:city":"Arlington",
    "sg:classifiers":[
        {
            "category":"Retail",
            "subcategory":"Laundry & Dry Cleaning",
            "type":"Services"
        }
    ],
    "sg:phone":"+1 817 465 0646",
    "sg:postcode":"76018",
    "sg:province":"TX",
    "sg:tags":[
        "cleaners"
    ],
    "wof:name":"$1.79 Dry Clean USA",
    "wof:placetype":"venue"
},
  "geometry": {"coordinates":[-97.08017700000001,32.665138],"type":"Point"}
}