{
  "type": "Feature",
  "properties": {
    "iso:country":"US",
    "sg:address":"32105 State Hwy 249",
    "sg:city":"Pinehurst",
    "sg:classifiers":[
        {
            "category":"Food & Beverages",
            "subcategory":"Bakery",
            "type":"Retail Goods"
        }
    ],
    "sg:phone":"+1 281 356 2809",
    "sg:postcode":"77362",
    "sg:province":"TX",
    "wof:name":"Country Bakery",
    "wof:placetype":"venue"
},
  "geometry": {"coordinates":[-95.653369,30.13173],"type":"Point"}
}