{
  "type": "Feature",
  "properties": {
    "iso:country":"US",
    "sg:address":"225 N Kimball Ave",
    "sg:city":"Southlake",
    "sg:classifiers":[
        {
            "category":"Restaurant",
            "type":"Food & Drink"
        }
    ],
    "sg:phone":"+1 817 329 8959",
    "sg:postcode":"76092",
    "sg:province":"TX",
    "sg:tags":[
        "eating"
    ],
    "wof:name":"McDonalds",
    "wof:placetype":"venue"
},
  "geometry": {"coordinates":[-97.116584,32.943299],"type":"Point"}
}