{
  "type": "Feature",
  "properties": {
    "iso:country":"US",
    "sg:address":"1512 Polk St",
    "sg:city":"Wichita Falls",
    "sg:classifiers":[
        {
            "category":"Retail",
            "subcategory":"Auto Repair",
            "type":"Services"
        }
    ],
    "sg:phone":"+1 940 761 5943",
    "sg:postcode":"76309",
    "sg:province":"TX",
    "sg:tags":[
        "repairing",
        "automobile"
    ],
    "wof:name":"Roy's Automotive",
    "wof:placetype":"venue"
},
  "geometry": {"coordinates":[-98.51898300000001,33.896997],"type":"Point"}
}