{
  "type": "Feature",
  "properties": {
    "iso:country":"US",
    "sg:address":"206 W Main St",
    "sg:city":"Weimar",
    "sg:classifiers":[
        {
            "category":"Travel",
            "subcategory":"Hotels & Motels",
            "type":"Entertainment"
        }
    ],
    "sg:phone":"+1 979 725 8133",
    "sg:postcode":"78962",
    "sg:province":"TX",
    "wof:name":"Weimar Motel",
    "wof:placetype":"venue"
},
  "geometry": {"coordinates":[-96.78365599999999,29.703079],"type":"Point"}
}