{
  "type": "Feature",
  "properties": {
    "iso:country":"US",
    "sg:address":"117 E Walnut St",
    "sg:city":"Lockhart",
    "sg:classifiers":[
        {
            "category":"Professional",
            "type":"Services"
        }
    ],
    "sg:phone":"+1 512 398 6755",
    "sg:postcode":"78644",
    "sg:province":"TX",
    "wof:name":"Hfse Inc",
    "wof:placetype":"venue"
},
  "geometry": {"coordinates":[-97.67173699999999,29.885745],"type":"Point"}
}