{
  "type": "Feature",
  "properties": {
    "iso:country":"US",
    "sg:address":"1408 10th St",
    "sg:city":"Wichita Falls",
    "sg:classifiers":[
        {
            "category":"Freight",
            "type":"Transportation"
        }
    ],
    "sg:phone":"+1 940 767 0421",
    "sg:postcode":"76301",
    "sg:province":"TX",
    "sg:tags":[
        "commercial",
        "storage"
    ],
    "wof:name":"Saf-T-Loc Self Storage",
    "wof:placetype":"venue"
},
  "geometry": {"coordinates":[-98.497821,33.905928],"type":"Point"}
}