{
  "type": "Feature",
  "properties": {
    "iso:country":"US",
    "sg:address":"11129 Savin Hill Ln",
    "sg:city":"Austin",
    "sg:classifiers":[
        {
            "category":"Wholesale",
            "subcategory":"Home Furnishings",
            "type":"Manufacturing & Wholesale Goods"
        }
    ],
    "sg:phone":"+1 512 301 8784",
    "sg:postcode":"78739",
    "sg:province":"TX",
    "sg:tags":[
        "mattresses-wholesale",
        "manufacturer"
    ],
    "wof:name":"Minky Dink",
    "wof:placetype":"venue"
},
  "geometry": {"coordinates":[-97.890551,30.18232],"type":"Point"}
}