{
  "type": "Feature",
  "properties": {
    "iso:country":"US",
    "sg:address":"2224 Eldger Dr",
    "sg:city":"Plano",
    "sg:classifiers":[
        {
            "category":"Professional",
            "subcategory":"Business Services",
            "type":"Services"
        }
    ],
    "sg:phone":"+1 972 208 0696",
    "sg:postcode":"75025",
    "sg:province":"TX",
    "wof:name":"Mancuso Resource Dev Svcs",
    "wof:placetype":"venue"
},
  "geometry": {"coordinates":[-96.738586,33.075797],"type":"Point"}
}