{
  "type": "Feature",
  "properties": {
    "iso:country":"US",
    "sg:address":"1410 Linda Dr",
    "sg:city":"Daingerfield",
    "sg:classifiers":[
        {
            "category":"Personal",
            "subcategory":"Beauty Salon",
            "type":"Services"
        }
    ],
    "sg:phone":"+1 903 645 7039",
    "sg:postcode":"75638",
    "sg:province":"TX",
    "sg:tags":[
        "shop"
    ],
    "wof:name":"Cut It Up Hair Gallery",
    "wof:placetype":"venue"
},
  "geometry": {"coordinates":[-94.720004,33.015285],"type":"Point"}
}