{
  "type": "Feature",
  "properties": {
    "iso:country":"US",
    "sg:address":"123 S Doughty St",
    "sg:city":"Rockport",
    "sg:classifiers":[
        {
            "category":"Organizations",
            "subcategory":"Religious Organization",
            "type":"Services"
        }
    ],
    "sg:phone":"+1 361 727 9997",
    "sg:postcode":"78382",
    "sg:province":"TX",
    "wof:name":"New Beginnings Ministries",
    "wof:placetype":"venue"
},
  "geometry": {"coordinates":[-97.06482200000001,28.023202],"type":"Point"}
}