{
  "type": "Feature",
  "properties": {
    "iso:country":"US",
    "sg:address":"7000 Kellam Rd",
    "sg:city":"Del Valle",
    "sg:classifiers":[
        {
            "category":"Wholesale",
            "subcategory":"Furniture",
            "type":"Manufacturing & Wholesale Goods"
        }
    ],
    "sg:phone":"+1 512 247 7688",
    "sg:postcode":"78617",
    "sg:province":"TX",
    "wof:name":"Rustic Creations",
    "wof:placetype":"venue"
},
  "geometry": {"coordinates":[-97.62197,30.15891],"type":"Point"}
}