{
  "type": "Feature",
  "properties": {
    "iso:country":"US",
    "sg:address":"325 Lark Ave",
    "sg:city":"Mcallen",
    "sg:classifiers":[
        {
            "category":"Retail",
            "subcategory":"Repair Shop",
            "type":"Services"
        }
    ],
    "sg:phone":"+1 956 686 4297",
    "sg:postcode":"78504",
    "sg:province":"TX",
    "sg:tags":[
        "welding"
    ],
    "wof:name":"Bell Welding Enterprises",
    "wof:placetype":"venue"
},
  "geometry": {"coordinates":[-98.212502,26.259183],"type":"Point"}
}