{
  "type": "Feature",
  "properties": {
    "iso:country":"US",
    "sg:address":"3310 Shadowwalk Dr",
    "sg:city":"Houston",
    "sg:classifiers":[
        {
            "category":"Manufacturing",
            "subcategory":"Tools & Machinery",
            "type":"Manufacturing & Wholesale Goods"
        }
    ],
    "sg:phone":"+1 281 759 9209",
    "sg:postcode":"77082",
    "sg:province":"TX",
    "sg:tags":[
        "set",
        "mfg"
    ],
    "wof:name":"A & R Turbines",
    "wof:placetype":"venue"
},
  "geometry": {"coordinates":[-95.602092,29.726634],"type":"Point"}
}