{
  "type": "Feature",
  "properties": {
    "iso:country":"US",
    "sg:address":"2200 N Hwy 175",
    "sg:city":"Seagoville",
    "sg:classifiers":[
        {
            "category":"Autos & Motor Vehicles",
            "subcategory":"Automobile Sales",
            "type":"Retail Goods"
        }
    ],
    "sg:phone":"+1 972 287 3397",
    "sg:postcode":"75159",
    "sg:province":"TX",
    "sg:tags":[
        "used"
    ],
    "wof:name":"Reynolds Motors",
    "wof:placetype":"venue"
},
  "geometry": {"coordinates":[-96.573002,32.662053],"type":"Point"}
}