{
  "type": "Feature",
  "properties": {
    "iso:country":"US",
    "sg:address":"4105 Sunmeadows St",
    "sg:city":"Plano",
    "sg:classifiers":[
        {
            "category":"Organizations",
            "subcategory":"Religious Organization",
            "type":"Services"
        }
    ],
    "sg:phone":"+1 972 491 1091",
    "sg:postcode":"75024",
    "sg:province":"TX",
    "wof:name":"Machen Chris & Diane",
    "wof:placetype":"venue"
},
  "geometry": {"coordinates":[-96.773858,33.076899],"type":"Point"}
}