{
  "type": "Feature",
  "properties": {
    "iso:country":"US",
    "sg:address":"3990 W Lucas Dr",
    "sg:city":"Beaumont",
    "sg:classifiers":[
        {
            "category":"Autos & Motor Vehicles",
            "subcategory":"Automobile Sales",
            "type":"Retail Goods"
        }
    ],
    "sg:phone":"+1 409 899 4365",
    "sg:postcode":"77706",
    "sg:province":"TX",
    "sg:tags":[
        "car",
        "dealer"
    ],
    "wof:name":"Enterprise Car Sales",
    "wof:placetype":"venue"
},
  "geometry": {"coordinates":[-94.146102,30.11648],"type":"Point"}
}