{
  "type": "Feature",
  "properties": {
    "iso:country":"US",
    "sg:address":"4204 Gardendale",
    "sg:city":"San Antonio",
    "sg:classifiers":[
        {
            "category":"Insurance",
            "subcategory":"Insurance Agent",
            "type":"Services"
        }
    ],
    "sg:phone":"+1 210 615 8251",
    "sg:postcode":"78229",
    "sg:province":"TX",
    "sg:website":"www.genewilliamsins.com",
    "wof:name":"Gene Williams General Ins",
    "wof:placetype":"venue"
},
  "geometry": {"coordinates":[-98.566959,29.5232],"type":"Point"}
}