{
  "type": "Feature",
  "properties": {
    "iso:country":"US",
    "sg:address":"1808 Doubletree Trl",
    "sg:city":"Flower Mound",
    "sg:classifiers":[
        {
            "category":"Manufacturing",
            "subcategory":"Metals",
            "type":"Manufacturing & Wholesale Goods"
        }
    ],
    "sg:phone":"+1 972 539 9355",
    "sg:postcode":"75028",
    "sg:province":"TX",
    "sg:tags":[
        "hardware",
        "mfg"
    ],
    "wof:name":"Boyd Scroggins",
    "wof:placetype":"venue"
},
  "geometry": {"coordinates":[-97.052972,33.004338],"type":"Point"}
}