{
  "type": "Feature",
  "properties": {
    "iso:country":"US",
    "sg:address":"531 Rivercrest Rd",
    "sg:city":"Valley Mills",
    "sg:classifiers":[
        {
            "category":"Shopping",
            "subcategory":"Gifts & Souvenirs",
            "type":"Retail Goods"
        }
    ],
    "sg:phone":"+1 254 932 5134",
    "sg:postcode":"76689",
    "sg:province":"TX",
    "wof:name":"R&K Antiques & Gifts",
    "wof:placetype":"venue"
},
  "geometry": {"coordinates":[-97.454847,31.656582],"type":"Point"}
}