{
  "type": "Feature",
  "properties": {
    "iso:country":"US",
    "sg:address":"16550 Henderson Pass",
    "sg:city":"San Antonio",
    "sg:classifiers":[
        {
            "category":"Building & Trades",
            "subcategory":"Landscaping Services",
            "type":"Services"
        }
    ],
    "sg:phone":"+1 210 496 6840",
    "sg:postcode":"78232",
    "sg:province":"TX",
    "sg:tags":[
        "landscape",
        "contractor"
    ],
    "wof:name":"S Texas Clearing & Landscaping",
    "wof:placetype":"venue"
},
  "geometry": {"coordinates":[-98.45042100000001,29.592241],"type":"Point"}
}