{
  "type": "Feature",
  "properties": {
    "iso:country":"US",
    "sg:address":"6411 N Beach St",
    "sg:city":"Fort Worth",
    "sg:classifiers":[
        {
            "category":"Professional",
            "subcategory":"Accounting & Tax Preparation",
            "type":"Services"
        }
    ],
    "sg:phone":"+1 817 847 6622",
    "sg:postcode":"76137",
    "sg:province":"TX",
    "sg:tags":[
        "return"
    ],
    "wof:name":"H & R Block",
    "wof:placetype":"venue"
},
  "geometry": {"coordinates":[-97.29014599999999,32.86091],"type":"Point"}
}