{
  "type": "Feature",
  "properties": {
    "iso:country":"US",
    "sg:address":"1712 N Fitzhugh Ave",
    "sg:city":"Dallas",
    "sg:classifiers":[
        {
            "category":"Retail",
            "subcategory":"Auto Repair",
            "type":"Services"
        }
    ],
    "sg:phone":"+1 214 828 9690",
    "sg:postcode":"75204",
    "sg:province":"TX",
    "wof:name":"PV Autoservice",
    "wof:placetype":"venue"
},
  "geometry": {"coordinates":[-96.77628900000001,32.806397],"type":"Point"}
}