{
  "type": "Feature",
  "properties": {
    "iso:country":"US",
    "sg:address":"10325 North Fwy",
    "sg:city":"Houston",
    "sg:classifiers":[
        {
            "category":"Restaurant",
            "type":"Food & Drink"
        }
    ],
    "sg:phone":"+1 281 272 2210",
    "sg:postcode":"77037",
    "sg:province":"TX",
    "sg:tags":[
        "mexican"
    ],
    "wof:name":"Taco Cabana",
    "wof:placetype":"venue"
},
  "geometry": {"coordinates":[-95.413101,29.916599],"type":"Point"}
}