{
  "type": "Feature",
  "properties": {
    "iso:country":"US",
    "sg:address":"711 Hewitt St",
    "sg:city":"League City",
    "sg:classifiers":[
        {
            "category":"Building & Trades",
            "subcategory":"Construction",
            "type":"Services"
        }
    ],
    "sg:phone":"+1 281 332 2957",
    "sg:postcode":"77573",
    "sg:province":"TX",
    "sg:tags":[
        "home",
        "speculative",
        "builder"
    ],
    "wof:name":"Creative Homes & Services Inc",
    "wof:placetype":"venue"
},
  "geometry": {"coordinates":[-95.076978,29.500338],"type":"Point"}
}