{
  "type": "Feature",
  "properties": {
    "iso:country":"US",
    "sg:address":"5015 Knoxville Ave",
    "sg:city":"Lubbock",
    "sg:classifiers":[
        {
            "category":"Organizations",
            "subcategory":"Professional Association",
            "type":"Services"
        }
    ],
    "sg:phone":"+1 806 795 9533",
    "sg:postcode":"79413",
    "sg:province":"TX",
    "sg:website":"www.lubbockrealtors.com",
    "wof:name":"Lubbock Association-Realtors",
    "wof:placetype":"venue"
},
  "geometry": {"coordinates":[-101.892015,33.547104],"type":"Point"}
}