{
  "type": "Feature",
  "properties": {
    "iso:country":"US",
    "sg:address":"6401 39th St",
    "sg:city":"Groves",
    "sg:classifiers":[
        {
            "category":"Personal",
            "subcategory":"Beauty Salon",
            "type":"Services"
        }
    ],
    "sg:phone":"+1 409 963 0584",
    "sg:postcode":"77619",
    "sg:province":"TX",
    "sg:tags":[
        "hair",
        "stylist"
    ],
    "sg:website":"http://www.acutabovehair.com",
    "wof:name":"A Cut Above",
    "wof:placetype":"venue"
},
  "geometry": {"coordinates":[-93.916206,29.94935],"type":"Point"}
}