{
  "type": "Feature",
  "properties": {
    "iso:country":"US",
    "sg:address":"7500 Bellaire Blvd Ste 913",
    "sg:city":"Houston",
    "sg:classifiers":[
        {
            "category":"Shopping",
            "subcategory":"Clothing, Apparel, & Fashions",
            "type":"Retail Goods"
        }
    ],
    "sg:phone":"+1 713 981 9411",
    "sg:postcode":"77036",
    "sg:province":"TX",
    "sg:tags":[
        "children's",
        "clothing"
    ],
    "wof:name":"Kids For Less",
    "wof:placetype":"venue"
},
  "geometry": {"coordinates":[-95.518303,29.705299],"type":"Point"}
}