{
  "type": "Feature",
  "properties": {
    "iso:country":"US",
    "sg:address":"5555 Spring Valley Rd",
    "sg:city":"Dallas",
    "sg:classifiers":[
        {
            "category":"Real Estate",
            "subcategory":"Real Estate Operator",
            "type":"Services"
        }
    ],
    "sg:phone":"+1 972 385 0815",
    "sg:postcode":"75254",
    "sg:province":"TX",
    "sg:tags":[
        "apartment",
        "complex"
    ],
    "wof:name":"Ventana Apartment Homes",
    "wof:placetype":"venue"
},
  "geometry": {"coordinates":[-96.810676,32.939216],"type":"Point"}
}