{
  "type": "Feature",
  "properties": {
    "iso:country":"US",
    "sg:address":"1003 N 10th St",
    "sg:city":"Killeen",
    "sg:classifiers":[
        {
            "category":"Personal",
            "subcategory":"Beauty Salon",
            "type":"Services"
        }
    ],
    "sg:phone":"+1 254 501 4495",
    "sg:postcode":"76541",
    "sg:province":"TX",
    "wof:name":"Creative Looks",
    "wof:placetype":"venue"
},
  "geometry": {"coordinates":[-97.723416,31.125238],"type":"Point"}
}