{
  "type": "Feature",
  "properties": {
    "iso:country":"US",
    "sg:address":"4100 E Piedras Dr",
    "sg:city":"San Antonio",
    "sg:classifiers":[
        {
            "category":"Health Services",
            "subcategory":"Clinic",
            "type":"Services"
        }
    ],
    "sg:phone":"+1 210 736 3339",
    "sg:postcode":"78228",
    "sg:province":"TX",
    "sg:tags":[
        "colonic",
        "irrigation"
    ],
    "wof:name":"JND & Assoc",
    "wof:placetype":"venue"
},
  "geometry": {"coordinates":[-98.568533,29.489017],"type":"Point"}
}