{
  "type": "Feature",
  "properties": {
    "iso:country":"US",
    "sg:address":"8315 Anastasia Ave",
    "sg:city":"Beaumont",
    "sg:classifiers":[
        {
            "category":"Professional",
            "subcategory":"Engineering",
            "type":"Services"
        }
    ],
    "sg:phone":"+1 409 794 1744",
    "sg:postcode":"77705",
    "sg:province":"TX",
    "sg:tags":[
        "consulting",
        "engineer"
    ],
    "wof:name":"Webster Stone Engineer",
    "wof:placetype":"venue"
},
  "geometry": {"coordinates":[-94.217049,29.931471],"type":"Point"}
}