{
  "type": "Feature",
  "properties": {
    "iso:country":"US",
    "sg:address":"2416 Balmorhea Ave",
    "sg:city":"Houston",
    "sg:classifiers":[
        {
            "category":"Freight",
            "type":"Transportation"
        }
    ],
    "sg:phone":"+1 281 449 9187",
    "sg:postcode":"77039",
    "sg:province":"TX",
    "sg:tags":[
        "operator",
        "local",
        "trucking"
    ],
    "wof:name":"Cargo All Kinds",
    "wof:placetype":"venue"
},
  "geometry": {"coordinates":[-95.347066,29.914612],"type":"Point"}
}