{
  "type": "Feature",
  "properties": {
    "iso:country":"US",
    "sg:address":"2651 N Hwy 146",
    "sg:city":"Baytown",
    "sg:classifiers":[
        {
            "category":"Recreation",
            "subcategory":"Marina",
            "type":"Entertainment"
        }
    ],
    "sg:phone":"+1 281 420 5076",
    "sg:postcode":"77520",
    "sg:province":"TX",
    "wof:name":"Bayland Marina",
    "wof:placetype":"venue"
},
  "geometry": {"coordinates":[-94.916489,29.770283],"type":"Point"}
}