{
  "type": "Feature",
  "properties": {
    "iso:country":"US",
    "sg:address":"203 E Rio Grande St",
    "sg:city":"Victoria",
    "sg:classifiers":[
        {
            "category":"Retail",
            "subcategory":"Auto Repair",
            "type":"Services"
        }
    ],
    "sg:phone":"+1 361 578 1551",
    "sg:postcode":"77901",
    "sg:province":"TX",
    "sg:tags":[
        "automotive",
        "general"
    ],
    "wof:name":"Bill Tumlinson Automotive",
    "wof:placetype":"venue"
},
  "geometry": {"coordinates":[-97.001473,28.805501],"type":"Point"}
}