{
  "type": "Feature",
  "properties": {
    "iso:country":"US",
    "sg:address":"261 Co Rd 150",
    "sg:city":"Breckenridge",
    "sg:classifiers":[
        {
            "category":"Farming",
            "subcategory":"Farm & Veterinary Services",
            "type":"Manufacturing & Wholesale Goods"
        }
    ],
    "sg:phone":"+1 254 559 2022",
    "sg:postcode":"76424",
    "sg:province":"TX",
    "sg:tags":[
        "aerial",
        "applicator"
    ],
    "wof:name":"Tuttle Spraying Co",
    "wof:placetype":"venue"
},
  "geometry": {"coordinates":[-98.894209,32.722639],"type":"Point"}
}