{
  "type": "Feature",
  "properties": {
    "iso:country":"US",
    "sg:address":"3000 N Main St",
    "sg:city":"Baytown",
    "sg:classifiers":[
        {
            "category":"Retail",
            "subcategory":"Auto Repair",
            "type":"Services"
        }
    ],
    "sg:phone":"+1 281 420 9296",
    "sg:postcode":"77521",
    "sg:province":"TX",
    "sg:tags":[
        "general"
    ],
    "wof:name":"S&B Complete Auto Repair",
    "wof:placetype":"venue"
},
  "geometry": {"coordinates":[-94.963784,29.754917],"type":"Point"}
}