{
  "type": "Feature",
  "properties": {
    "iso:country":"US",
    "sg:address":"10034 Long Point Rd",
    "sg:city":"Houston",
    "sg:classifiers":[
        {
            "category":"Shopping",
            "subcategory":"Discount & Variety Stores",
            "type":"Retail Goods"
        }
    ],
    "sg:phone":"+1 713 465 3070",
    "sg:postcode":"77055",
    "sg:province":"TX",
    "sg:tags":[
        "merchandise",
        "general"
    ],
    "wof:name":"HM Dollar Store",
    "wof:placetype":"venue"
},
  "geometry": {"coordinates":[-95.543311,29.794343],"type":"Point"}
}