{
  "type": "Feature",
  "properties": {
    "iso:country":"US",
    "sg:address":"8917 US Hwy 87",
    "sg:city":"San Angelo",
    "sg:classifiers":[
        {
            "category":"Manufacturing",
            "subcategory":"Glass & Minerals",
            "type":"Manufacturing & Wholesale Goods"
        }
    ],
    "sg:phone":"+1 325 658 5079",
    "sg:postcode":"76901",
    "sg:province":"TX",
    "sg:tags":[
        "concrete",
        "brick",
        "prod",
        "block"
    ],
    "wof:name":"Landers Septic & Concrete",
    "wof:placetype":"venue"
},
  "geometry": {"coordinates":[-100.574967,31.569573],"type":"Point"}
}