{
  "type": "Feature",
  "properties": {
    "iso:country":"US",
    "sg:address":"2277 N Masch Branch Rd",
    "sg:city":"Denton",
    "sg:classifiers":[
        {
            "category":"Building & Trades",
            "subcategory":"Construction",
            "type":"Services"
        }
    ],
    "sg:phone":"+1 972 247 9683",
    "sg:postcode":"76207",
    "sg:province":"TX",
    "sg:tags":[
        "excavation",
        "driveway",
        "paving",
        "road",
        "contractor"
    ],
    "wof:name":"Jrj Paving, Lp",
    "wof:placetype":"venue"
},
  "geometry": {"coordinates":[-97.19709400000001,33.238669],"type":"Point"}
}