{
  "type": "Feature",
  "properties": {
    "iso:country":"US",
    "sg:address":"3333 Finley Rd",
    "sg:city":"Irving",
    "sg:classifiers":[
        {
            "category":"Home & Garden",
            "subcategory":"Garden Supply",
            "type":"Retail Goods"
        }
    ],
    "sg:phone":"+1 972 594 6462",
    "sg:postcode":"75062",
    "sg:province":"TX",
    "sg:tags":[
        "tree",
        "christmas"
    ],
    "wof:name":"Ac Inc",
    "wof:placetype":"venue"
},
  "geometry": {"coordinates":[-96.99182500000001,32.850947],"type":"Point"}
}