{
  "type": "Feature",
  "properties": {
    "iso:country":"US",
    "sg:address":"11911 Martin Luther King Jr Blvd",
    "sg:city":"Houston",
    "sg:classifiers":[
        {
            "category":"Professional",
            "type":"Services"
        }
    ],
    "sg:phone":"+1 713 733 6808",
    "sg:postcode":"77048",
    "sg:province":"TX",
    "wof:name":"Porchas Braid",
    "wof:placetype":"venue"
},
  "geometry": {"coordinates":[-95.339359,29.631078],"type":"Point"}
}