{
  "type": "Feature",
  "properties": {
    "iso:country":"US",
    "sg:address":"1124 Valley View Mall",
    "sg:city":"Dallas",
    "sg:classifiers":[
        {
            "category":"Shopping",
            "subcategory":"Clothing, Apparel, & Fashions",
            "type":"Retail Goods"
        }
    ],
    "sg:phone":"+1 972 239 1201",
    "sg:postcode":"75240",
    "sg:province":"TX",
    "sg:tags":[
        "shop",
        "jewelry",
        "specialty"
    ],
    "wof:name":"Icing By Claire's",
    "wof:placetype":"venue"
},
  "geometry": {"coordinates":[-96.80933400000001,32.92685],"type":"Point"}
}