{
  "type": "Feature",
  "properties": {
    "iso:country":"US",
    "sg:address":"111 N Bell Blvd",
    "sg:city":"Cedar Park",
    "sg:classifiers":[
        {
            "category":"Building & Trades",
            "subcategory":"Construction",
            "type":"Services"
        }
    ],
    "sg:phone":"+1 512 336 5592",
    "sg:postcode":"78613",
    "sg:province":"TX",
    "sg:tags":[
        "repairing",
        "remodeling",
        "contractor"
    ],
    "wof:name":"Austin Affordable Gutters",
    "wof:placetype":"venue"
},
  "geometry": {"coordinates":[-97.824091,30.511708],"type":"Point"}
}