{
  "type": "Feature",
  "properties": {
    "iso:country":"US",
    "sg:address":"417 Hovenkamp St",
    "sg:city":"Keller",
    "sg:classifiers":[
        {
            "category":"Building & Trades",
            "subcategory":"Construction",
            "type":"Services"
        }
    ],
    "sg:phone":"+1 817 988 3513",
    "sg:postcode":"76248",
    "sg:province":"TX",
    "sg:tags":[
        "repairing",
        "remodeling",
        "contractor"
    ],
    "wof:name":"W D & Son Remodeling",
    "wof:placetype":"venue"
},
  "geometry": {"coordinates":[-97.24796499999999,32.94078],"type":"Point"}
}