{
  "type": "Feature",
  "properties": {
    "iso:country":"US",
    "sg:address":"5021 Goldenrod Dr",
    "sg:city":"Frisco",
    "sg:classifiers":[
        {
            "category":"Wholesale",
            "subcategory":"Non-durable Goods",
            "type":"Manufacturing & Wholesale Goods"
        }
    ],
    "sg:phone":"+1 469 287 2850",
    "sg:postcode":"75035",
    "sg:province":"TX",
    "wof:name":"Karisma Collections",
    "wof:placetype":"venue"
},
  "geometry": {"coordinates":[-96.79462599999999,33.120222],"type":"Point"}
}