{
  "type": "Feature",
  "properties": {
    "iso:country":"US",
    "sg:address":"11806 Wilcrest Dr",
    "sg:city":"Houston",
    "sg:classifiers":[
        {
            "category":"Real Estate",
            "subcategory":"Real Estate Services",
            "type":"Services"
        }
    ],
    "sg:phone":"+1 281 776 9863",
    "sg:postcode":"77031",
    "sg:province":"TX",
    "wof:name":"Koshy M Abraham realtor",
    "wof:placetype":"venue"
},
  "geometry": {"coordinates":[-95.56762500000001,29.650461],"type":"Point"}
}