{
  "type": "Feature",
  "properties": {
    "iso:country":"US",
    "sg:address":"502 S Padre Island Dr",
    "sg:city":"Corpus Christi",
    "sg:classifiers":[
        {
            "category":"Professional",
            "type":"Services"
        }
    ],
    "sg:phone":"+1 361 814 4647",
    "sg:postcode":"78405",
    "sg:province":"TX",
    "wof:name":"Hog Chapter Of Corpus Christi",
    "wof:placetype":"venue"
},
  "geometry": {"coordinates":[-97.46037699999999,27.755806],"type":"Point"}
}