{
  "type": "Feature",
  "properties": {
    "iso:country":"US",
    "sg:address":"2331 Goliad Rd",
    "sg:city":"San Antonio",
    "sg:classifiers":[
        {
            "category":"Freight",
            "type":"Transportation"
        }
    ],
    "sg:phone":"+1 210 333 2300",
    "sg:postcode":"78223",
    "sg:province":"TX",
    "sg:tags":[
        "commercial",
        "storage"
    ],
    "wof:name":"Spacesavers",
    "wof:placetype":"venue"
},
  "geometry": {"coordinates":[-98.43800400000001,29.362007],"type":"Point"}
}