{
  "type": "Feature",
  "properties": {
    "iso:country":"US",
    "sg:address":"3601 N State Line Ave Ste 4",
    "sg:city":"Texarkana",
    "sg:classifiers":[
        {
            "category":"Personal",
            "subcategory":"Nail Salon",
            "type":"Services"
        }
    ],
    "sg:phone":"+1 903 793 6973",
    "sg:postcode":"75503",
    "sg:province":"TX",
    "wof:name":"L A Nails",
    "wof:placetype":"venue"
},
  "geometry": {"coordinates":[-94.043159,33.451752],"type":"Point"}
}