{
  "type": "Feature",
  "properties": {
    "iso:country":"US",
    "sg:address":"8403 Mesa Drive",
    "sg:city":"Austin",
    "sg:classifiers":[
        {
            "category":"Education",
            "subcategory":"School",
            "type":"Public Place"
        }
    ],
    "sg:phone":"+1 512 414 2538",
    "sg:postcode":"78759",
    "sg:province":"TX",
    "sg:website":"www.austin.isd.tenet.edu",
    "wof:name":"Austin Independent School District",
    "wof:placetype":"venue"
},
  "geometry": {"coordinates":[-97.754667,30.375836],"type":"Point"}
}