{
  "type": "Feature",
  "properties": {
    "iso:country":"US",
    "sg:address":"409 Camden St",
    "sg:city":"San Antonio",
    "sg:classifiers":[
        {
            "category":"Shopping",
            "subcategory":"Optical Goods",
            "type":"Retail Goods"
        }
    ],
    "sg:phone":"+1 210 223 2461",
    "sg:postcode":"78215",
    "sg:province":"TX",
    "wof:name":"Weissler Optical",
    "wof:placetype":"venue"
},
  "geometry": {"coordinates":[-98.4905,29.4356],"type":"Point"}
}