{
  "type": "Feature",
  "properties": {
    "iso:country":"US",
    "sg:address":"2516 Bear Haven Dr",
    "sg:city":"Grapevine",
    "sg:classifiers":[
        {
            "category":"Wholesale",
            "subcategory":"Machinery & Supplies",
            "type":"Manufacturing & Wholesale Goods"
        }
    ],
    "sg:phone":"+1 817 329 0126",
    "sg:postcode":"76051",
    "sg:province":"TX",
    "sg:tags":[
        "equipment",
        "plastic"
    ],
    "wof:name":"Mercer Engineers",
    "wof:placetype":"venue"
},
  "geometry": {"coordinates":[-97.11484799999999,32.911816],"type":"Point"}
}