{
  "type": "Feature",
  "properties": {
    "iso:country":"US",
    "sg:address":"135 Glenwood Ct",
    "sg:city":"San Antonio",
    "sg:classifiers":[
        {
            "category":"Building & Trades",
            "subcategory":"Construction",
            "type":"Services"
        }
    ],
    "sg:phone":"+1 210 844 4762",
    "sg:postcode":"78210",
    "sg:province":"TX",
    "sg:tags":[
        "painter"
    ],
    "wof:name":"Vinnie's Painting/Remodeling",
    "wof:placetype":"venue"
},
  "geometry": {"coordinates":[-98.477966,29.38855],"type":"Point"}
}