{
  "type": "Feature",
  "properties": {
    "iso:country":"US",
    "sg:address":"5173 River Oaks Blvd",
    "sg:city":"Fort Worth",
    "sg:classifiers":[
        {
            "category":"Retail",
            "subcategory":"Auto Repair",
            "type":"Services"
        }
    ],
    "sg:phone":"+1 817 378 8311",
    "sg:postcode":"76114",
    "sg:province":"TX",
    "sg:tags":[
        "general"
    ],
    "wof:name":"Bronco Garage No 2",
    "wof:placetype":"venue"
},
  "geometry": {"coordinates":[-97.398094,32.774466],"type":"Point"}
}