{
  "type": "Feature",
  "properties": {
    "iso:country":"US",
    "sg:address":"8500 N Mo Pac Expy",
    "sg:city":"Austin",
    "sg:classifiers":[
        {
            "category":"Health Services",
            "subcategory":"Hospital",
            "type":"Services"
        },
        {
            "category":"Health Services",
            "subcategory":"Health Practitioner",
            "type":"Services"
        }
    ],
    "sg:phone":"+1 512 346 3224",
    "sg:postcode":"78759",
    "sg:province":"TX",
    "sg:tags":[
        "medical",
        "center",
        "birth"
    ],
    "sg:website":"www.austinabc.com",
    "wof:name":"Austin Area Birthing Ctr Inc",
    "wof:placetype":"venue"
},
  "geometry": {"coordinates":[-97.74112599999999,30.372828],"type":"Point"}
}