{
  "type": "Feature",
  "properties": {
    "iso:country":"US",
    "sg:address":"125 E John Carpenter Fwy 8",
    "sg:city":"Irving",
    "sg:classifiers":[
        {
            "category":"Government",
            "subcategory":"Office",
            "type":"Public Place"
        }
    ],
    "sg:phone":"+1 469 446 6229",
    "sg:postcode":"75062",
    "sg:province":"TX",
    "sg:tags":[
        "security",
        "homeland"
    ],
    "sg:website":"http://www.ruylebrewer.com",
    "wof:name":"United States Department Of Homeland Security",
    "wof:placetype":"venue"
},
  "geometry": {"coordinates":[-96.94409899999999,32.86687],"type":"Point"}
}