{
  "type": "Feature",
  "properties": {
    "iso:country":"US",
    "sg:address":"4504 Harvard St",
    "sg:city":"Amarillo",
    "sg:classifiers":[
        {
            "category":"Farming",
            "subcategory":"Farm",
            "type":"Manufacturing & Wholesale Goods"
        }
    ],
    "sg:phone":"+1 806 355 7883",
    "sg:postcode":"79109",
    "sg:province":"TX",
    "sg:tags":[
        "crop",
        "general"
    ],
    "wof:name":"Riedt Farm",
    "wof:placetype":"venue"
},
  "geometry": {"coordinates":[-101.894784,35.158933],"type":"Point"}
}