{
  "type": "Feature",
  "properties": {
    "iso:country":"US",
    "sg:address":"1116 Damon St",
    "sg:city":"Rosenberg",
    "sg:classifiers":[
        {
            "category":"Retail",
            "subcategory":"Repair Shop",
            "type":"Services"
        }
    ],
    "sg:phone":"+1 713 977 9999",
    "sg:postcode":"77471",
    "sg:province":"TX",
    "sg:tags":[
        "retailer",
        "electrical",
        "equipment"
    ],
    "wof:name":"ESP Office Solutions",
    "wof:placetype":"venue"
},
  "geometry": {"coordinates":[-95.795293,29.55718],"type":"Point"}
}