{
  "type": "Feature",
  "properties": {
    "iso:country":"US",
    "sg:address":"308 S Oak St",
    "sg:city":"Crowley",
    "sg:classifiers":[
        {
            "category":"Building & Trades",
            "subcategory":"Landscaping Services",
            "type":"Services"
        }
    ],
    "sg:phone":"+1 817 297 6455",
    "sg:postcode":"76036",
    "sg:province":"TX",
    "sg:tags":[
        "tree"
    ],
    "wof:name":"Edward's Tree & Lawn Svc",
    "wof:placetype":"venue"
},
  "geometry": {"coordinates":[-97.366083,32.576797],"type":"Point"}
}