{
  "type": "Feature",
  "properties": {
    "iso:country":"US",
    "sg:address":"205 S Smith Ave",
    "sg:city":"Hebbronville",
    "sg:classifiers":[
        {
            "category":"Health Services",
            "subcategory":"Doctor",
            "type":"Services"
        }
    ],
    "sg:phone":"+1 361 527 3254",
    "sg:postcode":"78361",
    "sg:province":"TX",
    "sg:tags":[
        "physician",
        "surgeon"
    ],
    "wof:name":"Glendenning Clinic",
    "wof:placetype":"venue"
},
  "geometry": {"coordinates":[-98.67849699999999,27.305229],"type":"Point"}
}