{
  "type": "Feature",
  "properties": {
    "iso:country":"US",
    "sg:address":"401 N Kimball Ave",
    "sg:city":"Southlake",
    "sg:classifiers":[
        {
            "category":"Food & Beverages",
            "subcategory":"Groceries & Convenience Stores",
            "type":"Retail Goods"
        }
    ],
    "sg:phone":"+1 817 488 8525",
    "sg:postcode":"76092",
    "sg:province":"TX",
    "sg:tags":[
        "station",
        "gasoline"
    ],
    "wof:name":"Circle E Food Mart",
    "wof:placetype":"venue"
},
  "geometry": {"coordinates":[-97.116608,32.951714],"type":"Point"}
}