{
  "type": "Feature",
  "properties": {
    "iso:country":"US",
    "sg:address":"4707 Bayberry St",
    "sg:city":"Flower Mound",
    "sg:classifiers":[
        {
            "category":"Retail",
            "subcategory":"Repair Shop",
            "type":"Services"
        }
    ],
    "sg:phone":"+1 972 539 0218",
    "sg:postcode":"75028",
    "sg:province":"TX",
    "sg:tags":[
        "refrigeration"
    ],
    "wof:name":"Teds Appliance Service",
    "wof:placetype":"venue"
},
  "geometry": {"coordinates":[-97.083504,33.049321],"type":"Point"}
}