{
  "type": "Feature",
  "properties": {
    "iso:country":"US",
    "sg:address":"8326 N Kilarny Rd",
    "sg:city":"Beaumont",
    "sg:classifiers":[
        {
            "category":"Freight",
            "type":"Transportation"
        }
    ],
    "sg:phone":"+1 409 722 2067",
    "sg:postcode":"77705",
    "sg:province":"TX",
    "sg:tags":[
        "operator",
        "local",
        "trucking"
    ],
    "wof:name":"Segrest Trucking",
    "wof:placetype":"venue"
},
  "geometry": {"coordinates":[-94.03172000000001,29.958471],"type":"Point"}
}