{
  "type": "Feature",
  "properties": {
    "iso:country":"US",
    "sg:address":"4429 Seville Ln",
    "sg:city":"Mc Kinney",
    "sg:classifiers":[
        {
            "category":"Professional",
            "subcategory":"Business Services",
            "type":"Services"
        }
    ],
    "sg:phone":"+1 972 540 6517",
    "sg:postcode":"75070",
    "sg:province":"TX",
    "wof:name":"D&G Technologies",
    "wof:placetype":"venue"
},
  "geometry": {"coordinates":[-96.669961,33.16119],"type":"Point"}
}