{
  "type": "Feature",
  "properties": {
    "iso:country":"US",
    "sg:address":"7100 Crowley Rd",
    "sg:city":"Fort Worth",
    "sg:classifiers":[
        {
            "category":"Real Estate",
            "subcategory":"Developer",
            "type":"Services"
        }
    ],
    "sg:phone":"+1 817 293 1350",
    "sg:postcode":"76134",
    "sg:province":"TX",
    "sg:tags":[
        "cemetery"
    ],
    "wof:name":"Laurel Land Memorial Park",
    "wof:placetype":"venue"
},
  "geometry": {"coordinates":[-97.348457,32.644346],"type":"Point"}
}