{
  "type": "Feature",
  "properties": {
    "iso:country":"US",
    "sg:address":"10122 Losa Dr",
    "sg:city":"Dallas",
    "sg:classifiers":[
        {
            "category":"Education",
            "subcategory":"School",
            "type":"Public Place"
        }
    ],
    "sg:phone":"+1 972 749 7900",
    "sg:postcode":"75218",
    "sg:province":"TX",
    "sg:website":"www.dallasisd.org",
    "wof:name":"Schools",
    "wof:placetype":"venue"
},
  "geometry": {"coordinates":[-96.69259599999999,32.8372],"type":"Point"}
}