{
  "type": "Feature",
  "properties": {
    "iso:country":"US",
    "sg:address":"4691 N Mesa St",
    "sg:city":"El Paso",
    "sg:classifiers":[
        {
            "category":"Professional",
            "subcategory":"Management & Consulting",
            "type":"Services"
        }
    ],
    "sg:phone":"+1 915 351 3853",
    "sg:postcode":"79912",
    "sg:province":"TX",
    "sg:tags":[
        "marketing",
        "program"
    ],
    "wof:name":"Choicepoint Precision Mktg Inc",
    "wof:placetype":"venue"
},
  "geometry": {"coordinates":[-106.50967199999999,31.803086],"type":"Point"}
}