{
  "type": "Feature",
  "properties": {
    "iso:country":"US",
    "sg:address":"7412 Lemmon Ave",
    "sg:city":"Dallas",
    "sg:classifiers":[
        {
            "category":"Freight",
            "type":"Transportation"
        }
    ],
    "sg:phone":"+1 877 258 8230",
    "sg:postcode":"75209",
    "sg:province":"TX",
    "sg:tags":[
        "marina",
        "storage",
        "household",
        "commercial",
        "operation"
    ],
    "sg:website":"http://www.publicstorage.com/?pid=ypcomCPCingenio",
    "wof:name":"Public Storage",
    "wof:placetype":"venue"
},
  "geometry": {"coordinates":[-96.835193,32.845543],"type":"Point"}
}