{
  "type": "Feature",
  "properties": {
    "iso:country":"US",
    "sg:address":"6706 Winnipeg Cv",
    "sg:city":"Austin",
    "sg:classifiers":[
        {
            "category":"Social Services",
            "type":"Services"
        },
        {
            "category":"Professional",
            "subcategory":"Employment Agencies",
            "type":"Services"
        }
    ],
    "sg:phone":"+1 512 338 0011",
    "sg:postcode":"78759",
    "sg:province":"TX",
    "sg:tags":[
        "workers'",
        "placement",
        "volunteer"
    ],
    "wof:name":"Cjr Foundation, Inc",
    "wof:placetype":"venue"
},
  "geometry": {"coordinates":[-97.770554,30.412227],"type":"Point"}
}