{
  "type": "Feature",
  "properties": {
    "iso:country":"US",
    "sg:address":"6090 Campbell Rd",
    "sg:city":"Dallas",
    "sg:classifiers":[
        {
            "category":"Shopping",
            "subcategory":"Jewelry",
            "type":"Retail Goods"
        }
    ],
    "sg:phone":"+1 972 713 9191",
    "sg:postcode":"75248",
    "sg:province":"TX",
    "sg:tags":[
        "jeweler"
    ],
    "wof:name":"Gems & Treasures",
    "wof:placetype":"venue"
},
  "geometry": {"coordinates":[-96.80098700000001,32.982025],"type":"Point"}
}