{
  "type": "Feature",
  "properties": {
    "iso:country":"US",
    "sg:address":"402 Raymond St",
    "sg:city":"Farmersville",
    "sg:classifiers":[
        {
            "category":"Shopping",
            "subcategory":"Bicycles & Sporting Goods",
            "type":"Retail Goods"
        }
    ],
    "sg:phone":"+1 972 782 8305",
    "sg:postcode":"75442",
    "sg:province":"TX",
    "sg:tags":[
        "tack"
    ],
    "wof:name":"Blackwood Manufacture",
    "wof:placetype":"venue"
},
  "geometry": {"coordinates":[-96.371442,33.16042],"type":"Point"}
}