{
  "type": "Feature",
  "properties": {
    "iso:country":"US",
    "sg:address":"2324 Chimney Hill Dr",
    "sg:city":"Arlington",
    "sg:classifiers":[
        {
            "category":"Shopping",
            "subcategory":"Clothing, Apparel, & Fashions",
            "type":"Retail Goods"
        }
    ],
    "sg:phone":"+1 817 861 3230",
    "sg:postcode":"76012",
    "sg:province":"TX",
    "wof:name":"Carlisie Classics",
    "wof:placetype":"venue"
},
  "geometry": {"coordinates":[-97.132543,32.77553],"type":"Point"}
}