{
  "type": "Feature",
  "properties": {
    "iso:country":"US",
    "sg:address":"401 Talbot Ave",
    "sg:city":"Canutillo",
    "sg:classifiers":[
        {
            "category":"Restaurant",
            "type":"Food & Drink"
        }
    ],
    "sg:phone":"+1 915 877 1638",
    "sg:postcode":"79835",
    "sg:province":"TX",
    "wof:name":"Speedy Gonzalez Mexican Food",
    "wof:placetype":"venue"
},
  "geometry": {"coordinates":[-106.595269,31.908261],"type":"Point"}
}