{
  "type": "Feature",
  "properties": {
    "iso:country":"US",
    "sg:address":"1135 Walnut Hill Ln",
    "sg:city":"De Soto",
    "sg:classifiers":[
        {
            "category":"Health Services",
            "subcategory":"Medical Lab",
            "type":"Services"
        }
    ],
    "sg:phone":"+1 972 224 1732",
    "sg:postcode":"75115",
    "sg:province":"TX",
    "sg:tags":[
        "laboratory"
    ],
    "wof:name":"Obtainable Cure Clinical",
    "wof:placetype":"venue"
},
  "geometry": {"coordinates":[-96.82896700000001,32.610399],"type":"Point"}
}