{
  "type": "Feature",
  "properties": {
    "iso:country":"US",
    "sg:address":"3600 College Ave",
    "sg:city":"Snyder",
    "sg:classifiers":[
        {
            "category":"Manufacturing",
            "subcategory":"Printing",
            "type":"Manufacturing & Wholesale Goods"
        }
    ],
    "sg:phone":"+1 325 573 5486",
    "sg:postcode":"79549",
    "sg:province":"TX",
    "sg:tags":[
        "newspaper"
    ],
    "sg:website":"www.snyderdailynews.com",
    "wof:name":"Snyder Daily News",
    "wof:placetype":"venue"
},
  "geometry": {"coordinates":[-100.919025,32.705673],"type":"Point"}
}