{
  "type": "Feature",
  "properties": {
    "iso:country":"US",
    "sg:address":"618 N High St",
    "sg:city":"Longview",
    "sg:classifiers":[
        {
            "category":"Insurance",
            "subcategory":"Insurance Agent",
            "type":"Services"
        }
    ],
    "sg:phone":"+1 903 753 3950",
    "sg:postcode":"75601",
    "sg:province":"TX",
    "sg:tags":[
        "adjuster"
    ],
    "wof:name":"John T Parker Claims Svc",
    "wof:placetype":"venue"
},
  "geometry": {"coordinates":[-94.740274,32.502394],"type":"Point"}
}