{
  "type": "Feature",
  "properties": {
    "iso:country":"US",
    "sg:address":"1643 FM 1819",
    "sg:city":"Pollok",
    "sg:classifiers":[
        {
            "category":"Autos & Motor Vehicles",
            "subcategory":"Automobile Sales",
            "type":"Retail Goods"
        }
    ],
    "sg:phone":"+1 936 853 2699",
    "sg:postcode":"75969",
    "sg:province":"TX",
    "sg:tags":[
        "used"
    ],
    "wof:name":"White Oak Auto Sales",
    "wof:placetype":"venue"
},
  "geometry": {"coordinates":[-94.93104700000001,31.411477],"type":"Point"}
}