{
  "type": "Feature",
  "properties": {
    "iso:country":"US",
    "sg:address":"2050 Vine Ln",
    "sg:city":"Dallas",
    "sg:classifiers":[
        {
            "category":"Building & Trades",
            "subcategory":"Construction",
            "type":"Services"
        }
    ],
    "sg:phone":"+1 972 286 9669",
    "sg:postcode":"75217",
    "sg:province":"TX",
    "sg:tags":[
        "contractor"
    ],
    "wof:name":"York Roofing",
    "wof:placetype":"venue"
},
  "geometry": {"coordinates":[-96.660928,32.675205],"type":"Point"}
}