{
  "type": "Feature",
  "properties": {
    "iso:country":"US",
    "sg:address":"5679 Landry Ln",
    "sg:city":"Beaumont",
    "sg:classifiers":[
        {
            "category":"Organizations",
            "subcategory":"Religious Organization",
            "type":"Services"
        }
    ],
    "sg:phone":"+1 409 924 8859",
    "sg:postcode":"77708",
    "sg:province":"TX",
    "wof:name":"Apostolic Church of Jesus",
    "wof:placetype":"venue"
},
  "geometry": {"coordinates":[-94.14765800000001,30.126263],"type":"Point"}
}