{
  "type": "Feature",
  "properties": {
    "iso:country":"US",
    "sg:address":"2631 Natchez Ct",
    "sg:city":"League City",
    "sg:classifiers":[
        {
            "category":"Retail",
            "subcategory":"Repair Shop",
            "type":"Services"
        }
    ],
    "sg:phone":"+1 409 740 4601",
    "sg:postcode":"77573",
    "sg:province":"TX",
    "sg:tags":[
        "upholsterer"
    ],
    "wof:name":"Richard's Upholstery & Design",
    "wof:placetype":"venue"
},
  "geometry": {"coordinates":[-95.089,29.476248],"type":"Point"}
}