{
  "type": "Feature",
  "properties": {
    "iso:country":"US",
    "sg:address":"209 State Hwy 79",
    "sg:city":"Olney",
    "sg:classifiers":[
        {
            "category":"Autos & Motor Vehicles",
            "subcategory":"Automobile Sales",
            "type":"Retail Goods"
        }
    ],
    "sg:phone":"+1 940 564 5589",
    "sg:postcode":"76374",
    "sg:province":"TX",
    "sg:tags":[
        "car",
        "dealer"
    ],
    "wof:name":"Willis Auto Sales",
    "wof:placetype":"venue"
},
  "geometry": {"coordinates":[-98.75032899999999,33.371547],"type":"Point"}
}