{
  "type": "Feature",
  "properties": {
    "iso:country":"US",
    "sg:address":"23 E State Highway 22",
    "sg:city":"Hamilton",
    "sg:classifiers":[
        {
            "category":"Home & Garden",
            "subcategory":"Garden Supply",
            "type":"Retail Goods"
        }
    ],
    "sg:phone":"+1 254 386 3913",
    "sg:postcode":"76531",
    "sg:province":"TX",
    "sg:tags":[
        "soil",
        "conservation"
    ],
    "wof:name":"Natural Resources Conservation Service",
    "wof:placetype":"venue"
},
  "geometry": {"coordinates":[-98.107483,31.699673],"type":"Point"}
}