{
  "type": "Feature",
  "properties": {
    "iso:country":"US",
    "sg:address":"4220 Pinemont Dr",
    "sg:city":"Houston",
    "sg:classifiers":[
        {
            "category":"Professional",
            "subcategory":"Accounting & Tax Preparation",
            "type":"Services"
        }
    ],
    "sg:phone":"+1 713 686 8558",
    "sg:postcode":"77018",
    "sg:province":"TX",
    "sg:tags":[
        "bookkeeping",
        "general"
    ],
    "wof:name":"Bickel Bookeeping Svc",
    "wof:placetype":"venue"
},
  "geometry": {"coordinates":[-95.45653799999999,29.840954],"type":"Point"}
}