{
  "type": "Feature",
  "properties": {
    "iso:country":"US",
    "sg:address":"505 Rushy Creek Trl",
    "sg:city":"Red Oak",
    "sg:classifiers":[
        {
            "category":"Home & Garden",
            "subcategory":"Building Materials",
            "type":"Retail Goods"
        }
    ],
    "sg:phone":"+1 972 617 3667",
    "sg:postcode":"75154",
    "sg:province":"TX",
    "sg:tags":[
        "repair"
    ],
    "wof:name":"Door Doctor",
    "wof:placetype":"venue"
},
  "geometry": {"coordinates":[-96.786092,32.522644],"type":"Point"}
}