{
  "type": "Feature",
  "properties": {
    "iso:country":"US",
    "sg:address":"7301 N Fm 620",
    "sg:city":"Austin",
    "sg:classifiers":[
        {
            "category":"Shopping",
            "subcategory":"Pharmacy",
            "type":"Retail Goods"
        },
        {
            "category":"Food & Beverages",
            "subcategory":"Groceries & Convenience Stores",
            "type":"Retail Goods"
        }
    ],
    "sg:phone":"+1 512 336 7706",
    "sg:postcode":"78726",
    "sg:province":"TX",
    "sg:tags":[
        "drugstore"
    ],
    "wof:name":"H-E-B Pharmacy",
    "wof:placetype":"venue"
},
  "geometry": {"coordinates":[-97.84410800000001,30.399958],"type":"Point"}
}