{
  "type": "Feature",
  "properties": {
    "iso:country":"US",
    "sg:address":"1401 Link Rd",
    "sg:city":"League City",
    "sg:classifiers":[
        {
            "category":"Building & Trades",
            "subcategory":"Construction",
            "type":"Services"
        }
    ],
    "sg:phone":"+1 281 332 7334",
    "sg:postcode":"77573",
    "sg:province":"TX",
    "sg:tags":[
        "excavation",
        "dirt",
        "general",
        "contractor"
    ],
    "wof:name":"Ddt Excavating & Site Work",
    "wof:placetype":"venue"
},
  "geometry": {"coordinates":[-95.099763,29.491121],"type":"Point"}
}