{
  "type": "Feature",
  "properties": {
    "iso:country":"US",
    "sg:address":"19429 Haude Rd",
    "sg:city":"Spring",
    "sg:classifiers":[
        {
            "category":"Real Estate",
            "subcategory":"Real Estate Agent",
            "type":"Services"
        }
    ],
    "sg:phone":"+1 281 355 6047",
    "sg:postcode":"77388",
    "sg:province":"TX",
    "wof:name":"Esther Cordova Realtor",
    "wof:placetype":"venue"
},
  "geometry": {"coordinates":[-95.456919,30.048662],"type":"Point"}
}