{
  "type": "Feature",
  "properties": {
    "iso:country":"US",
    "sg:address":"1430 Regal Row Ste 360",
    "sg:city":"Dallas",
    "sg:classifiers":[
        {
            "category":"Banks & Credit Unions",
            "subcategory":"Bank",
            "type":"Services"
        }
    ],
    "sg:phone":"+1 214 273 5094",
    "sg:postcode":"75247",
    "sg:province":"TX",
    "sg:website":"www.lascolinasfcu.com",
    "wof:name":"Las Colinas Federal Credit Union",
    "wof:placetype":"venue"
},
  "geometry": {"coordinates":[-96.87835200000001,32.833027],"type":"Point"}
}