{
  "type": "Feature",
  "properties": {
    "iso:country":"US",
    "sg:address":"11612 Scott Simpson Dr",
    "sg:city":"El Paso",
    "sg:classifiers":[
        {
            "category":"Government",
            "subcategory":"Office",
            "type":"Public Place"
        }
    ],
    "sg:phone":"+1 915 849 4100",
    "sg:postcode":"79936",
    "sg:province":"TX",
    "sg:tags":[
        "state",
        "program"
    ],
    "wof:name":"Driver License Div",
    "wof:placetype":"venue"
},
  "geometry": {"coordinates":[-106.30012499999999,31.746064],"type":"Point"}
}