{
  "type": "Feature",
  "properties": {
    "iso:country":"US",
    "sg:address":"102 Clear Lake Ct",
    "sg:city":"Southlake",
    "sg:classifiers":[
        {
            "category":"Building & Trades",
            "subcategory":"Construction",
            "type":"Services"
        }
    ],
    "sg:phone":"+1 817 329 5911",
    "sg:postcode":"76092",
    "sg:province":"TX",
    "sg:tags":[
        "contractor"
    ],
    "wof:name":"Southwall Technologies",
    "wof:placetype":"venue"
},
  "geometry": {"coordinates":[-97.157346,32.939865],"type":"Point"}
}