{
  "type": "Feature",
  "properties": {
    "iso:country":"US",
    "sg:address":"4041 W Wheatland Rd",
    "sg:city":"Dallas",
    "sg:classifiers":[
        {
            "category":"Professional",
            "type":"Services"
        }
    ],
    "sg:phone":"+1 972 565 0080",
    "sg:postcode":"75237",
    "sg:province":"TX",
    "wof:name":"Kenoos Inc",
    "wof:placetype":"venue"
},
  "geometry": {"coordinates":[-96.880965,32.647675],"type":"Point"}
}