{
  "type": "Feature",
  "properties": {
    "iso:country":"US",
    "sg:address":"315 W Foster Ave",
    "sg:city":"Pampa",
    "sg:classifiers":[
        {
            "category":"Home & Garden",
            "subcategory":"Building Materials",
            "type":"Retail Goods"
        },
        {
            "category":"Building & Trades",
            "subcategory":"Construction",
            "type":"Services"
        }
    ],
    "sg:phone":"+1 806 665 7170",
    "sg:postcode":"79065",
    "sg:province":"TX",
    "sg:tags":[
        "plate",
        "window",
        "contractor",
        "glass",
        "automotive"
    ],
    "wof:name":"D & K Glass",
    "wof:placetype":"venue"
},
  "geometry": {"coordinates":[-100.96311900000001,35.534933],"type":"Point"}
}