{
  "type": "Feature",
  "properties": {
    "iso:country":"US",
    "sg:address":"989 E Nasa Pkwy",
    "sg:city":"Houston",
    "sg:classifiers":[
        {
            "category":"Professional",
            "subcategory":"Printing & Photocopies",
            "type":"Services"
        }
    ],
    "sg:phone":"+1 281 488 7900",
    "sg:postcode":"77058",
    "sg:province":"TX",
    "sg:tags":[
        "photocopying"
    ],
    "wof:name":"Ridgways Ltd",
    "wof:placetype":"venue"
},
  "geometry": {"coordinates":[-95.106613,29.545933],"type":"Point"}
}