{
  "type": "Feature",
  "properties": {
    "iso:country":"US",
    "sg:address":"14924 Northwest Fwy",
    "sg:city":"Houston",
    "sg:classifiers":[
        {
            "category":"Personal",
            "subcategory":"Beauty Salon",
            "type":"Services"
        }
    ],
    "sg:phone":"+1 713 895 0260",
    "sg:postcode":"77040",
    "sg:province":"TX",
    "wof:name":"Le Cut Hair Design",
    "wof:placetype":"venue"
},
  "geometry": {"coordinates":[-95.54675899999999,29.869961],"type":"Point"}
}