{
  "type": "Feature",
  "properties": {
    "iso:country":"US",
    "sg:address":"88 Coronado Dr N",
    "sg:city":"Kerrville",
    "sg:classifiers":[
        {
            "category":"Wholesale",
            "subcategory":"Medical Equipment & Supplies",
            "type":"Manufacturing & Wholesale Goods"
        }
    ],
    "sg:phone":"+1 830 792 5071",
    "sg:postcode":"78028",
    "sg:province":"TX",
    "sg:tags":[
        "physician",
        "surgeon"
    ],
    "sg:website":"www.hillcountrymfg.com",
    "wof:name":"Hill Country Mfg",
    "wof:placetype":"venue"
},
  "geometry": {"coordinates":[-99.179027,30.066746],"type":"Point"}
}