{
  "type": "Feature",
  "properties": {
    "iso:country":"US",
    "sg:address":"1742 FM 2673",
    "sg:city":"Canyon Lake",
    "sg:classifiers":[
        {
            "category":"Health Services",
            "subcategory":"Chiropractor",
            "type":"Services"
        }
    ],
    "sg:phone":"+1 830 907 3811",
    "sg:postcode":"78133",
    "sg:province":"TX",
    "wof:name":"Hites Chiropractic",
    "wof:placetype":"venue"
},
  "geometry": {"coordinates":[-98.179453,29.846988],"type":"Point"}
}