{
  "type": "Feature",
  "properties": {
    "iso:country":"US",
    "sg:address":"204 High Canyon Ct",
    "sg:city":"Richardson",
    "sg:classifiers":[
        {
            "category":"Wholesale",
            "subcategory":"Machinery & Supplies",
            "type":"Manufacturing & Wholesale Goods"
        }
    ],
    "sg:phone":"+1 972 644 4386",
    "sg:postcode":"75080",
    "sg:province":"TX",
    "sg:tags":[
        "equipment",
        "industrial"
    ],
    "wof:name":"Technologies I Cybermagix",
    "wof:placetype":"venue"
},
  "geometry": {"coordinates":[-96.71744099999999,32.984108],"type":"Point"}
}