{
  "type": "Feature",
  "properties": {
    "iso:country":"US",
    "sg:address":"20710 FM 685",
    "sg:city":"Pflugerville",
    "sg:classifiers":[
        {
            "category":"Building & Trades",
            "subcategory":"Construction",
            "type":"Services"
        },
        {
            "category":"Home & Garden",
            "subcategory":"Furniture",
            "type":"Retail Goods"
        }
    ],
    "sg:phone":"+1 512 989 1858",
    "sg:postcode":"78660",
    "sg:province":"TX",
    "sg:tags":[
        "contractor",
        "top",
        "counter",
        "nonresidential"
    ],
    "wof:name":"Cornerstone Countertops Inc",
    "wof:placetype":"venue"
},
  "geometry": {"coordinates":[-97.583161,30.490856],"type":"Point"}
}