{
  "type": "Feature",
  "properties": {
    "iso:country":"US",
    "sg:address":"143 E Main St",
    "sg:city":"Fredericksburg",
    "sg:classifiers":[
        {
            "category":"Shopping",
            "subcategory":"Books",
            "type":"Retail Goods"
        }
    ],
    "sg:phone":"+1 830 997 2375",
    "sg:postcode":"78624",
    "sg:province":"TX",
    "sg:tags":[
        "dealer"
    ],
    "wof:name":"Main Book Shop",
    "wof:placetype":"venue"
},
  "geometry": {"coordinates":[-98.87170399999999,30.274507],"type":"Point"}
}