{
  "type": "Feature",
  "properties": {
    "iso:country":"US",
    "sg:address":"11 Center St",
    "sg:city":"Deer Park",
    "sg:classifiers":[
        {
            "category":"Professional",
            "subcategory":"Lawyer & Legal Services",
            "type":"Services"
        }
    ],
    "sg:phone":"+1 281 479 5953",
    "sg:postcode":"77536",
    "sg:province":"TX",
    "sg:tags":[
        "attorney"
    ],
    "wof:name":"Michael A Culling",
    "wof:placetype":"venue"
},
  "geometry": {"coordinates":[-95.123923,29.710619],"type":"Point"}
}