{
  "type": "Feature",
  "properties": {
    "iso:country":"US",
    "sg:address":"2023 W McDermott Dr",
    "sg:city":"Allen",
    "sg:classifiers":[
        {
            "category":"Restaurant",
            "type":"Food & Drink"
        }
    ],
    "sg:phone":"+1 972 727 6447",
    "sg:postcode":"75013",
    "sg:province":"TX",
    "wof:name":"Micasa Tex Mex Grill",
    "wof:placetype":"venue"
},
  "geometry": {"coordinates":[-96.732713,33.100738],"type":"Point"}
}