{
  "type": "Feature",
  "properties": {
    "iso:country":"US",
    "sg:address":"13311 Broadmeade Ave",
    "sg:city":"Austin",
    "sg:classifiers":[
        {
            "category":"Education",
            "subcategory":"Special Training",
            "type":"Public Place"
        }
    ],
    "sg:phone":"+1 512 250 1292",
    "sg:postcode":"78729",
    "sg:province":"TX",
    "sg:tags":[
        "program"
    ],
    "wof:name":"Microage Training & Consulting",
    "wof:placetype":"venue"
},
  "geometry": {"coordinates":[-97.78151200000001,30.4687],"type":"Point"}
}