{
  "type": "Feature",
  "properties": {
    "iso:country":"US",
    "sg:address":"512 E 11th St Ste 205",
    "sg:city":"Austin",
    "sg:classifiers":[
        {
            "category":"Professional",
            "subcategory":"Lawyer & Legal Services",
            "type":"Services"
        }
    ],
    "sg:phone":"+1 512 236 1590",
    "sg:postcode":"78701",
    "sg:province":"TX",
    "sg:tags":[
        "attorney",
        "law",
        "practice",
        "appellate",
        "criminal"
    ],
    "sg:website":"www.appellatecourtlaw.com",
    "wof:name":"Law Office Of Margaret Schmucker",
    "wof:placetype":"venue"
},
  "geometry": {"coordinates":[-97.736028,30.271479],"type":"Point"}
}