{
  "type": "Feature",
  "properties": {
    "iso:country":"US",
    "sg:address":"24111 Shin Oak Dr",
    "sg:city":"Huffman",
    "sg:classifiers":[
        {
            "category":"Professional",
            "subcategory":"Engineering",
            "type":"Services"
        }
    ],
    "sg:phone":"+1 281 324 1616",
    "sg:postcode":"77336",
    "sg:province":"TX",
    "wof:name":"Power Tech",
    "wof:placetype":"venue"
},
  "geometry": {"coordinates":[-95.109487,30.022175],"type":"Point"}
}