{
  "type": "Feature",
  "properties": {
    "iso:country":"US",
    "sg:address":"1225 Belt Line Rd Ste 10",
    "sg:city":"Garland",
    "sg:classifiers":[
        {
            "category":"Professional",
            "subcategory":"Employment Agencies",
            "type":"Services"
        }
    ],
    "sg:phone":"+1 972 675 2548",
    "sg:postcode":"75040",
    "sg:province":"TX",
    "sg:tags":[
        "opportunity"
    ],
    "sg:website":"http://www.staffmark.com",
    "wof:name":"Staffmark",
    "wof:placetype":"venue"
},
  "geometry": {"coordinates":[-96.645307,32.944707],"type":"Point"}
}