{
  "type": "Feature",
  "properties": {
    "iso:country":"US",
    "sg:address":"1318 Avenue H",
    "sg:city":"Rosenberg",
    "sg:classifiers":[
        {
            "category":"Restaurant",
            "type":"Food & Drink"
        }
    ],
    "sg:phone":"+1 281 239 0545",
    "sg:postcode":"77471",
    "sg:province":"TX",
    "wof:name":"Pollos Y Carnes Asadas #90",
    "wof:placetype":"venue"
},
  "geometry": {"coordinates":[-95.814196,29.558145],"type":"Point"}
}