{
  "type": "Feature",
  "properties": {
    "iso:country":"US",
    "sg:address":"400 Live Oak",
    "sg:city":"Ingram",
    "sg:classifiers":[
        {
            "category":"Real Estate",
            "subcategory":"Real Estate Operator",
            "type":"Services"
        }
    ],
    "sg:phone":"+1 830 367 2426",
    "sg:postcode":"78025",
    "sg:province":"TX",
    "sg:tags":[
        "mobile",
        "home",
        "community"
    ],
    "wof:name":"Ingram Oaks Retirement Cmnty",
    "wof:placetype":"venue"
},
  "geometry": {"coordinates":[-99.257805,30.076327],"type":"Point"}
}