{
  "type": "Feature",
  "properties": {
    "iso:country":"US",
    "sg:address":"1006 Voss Rd",
    "sg:city":"Houston",
    "sg:classifiers":[
        {
            "category":"Organizations",
            "subcategory":"Community Association",
            "type":"Services"
        }
    ],
    "sg:phone":"+1 713 467 9622",
    "sg:postcode":"77055",
    "sg:province":"TX",
    "wof:name":"Westside Family Y M C A",
    "wof:placetype":"venue"
},
  "geometry": {"coordinates":[-95.50308699999999,29.78604],"type":"Point"}
}