{
  "type": "Feature",
  "properties": {
    "iso:country":"US",
    "sg:address":"12129 Ranch Road 620 North #520",
    "sg:city":"Austin",
    "sg:classifiers":[
        {
            "category":"Building & Trades",
            "subcategory":"Construction",
            "type":"Services"
        }
    ],
    "sg:phone":"+1 800 871 7115",
    "sg:postcode":"78750",
    "sg:province":"TX",
    "sg:tags":[
        "contractor"
    ],
    "sg:website":"www.cedarvalleyexteriors.com/",
    "wof:name":"Cedar Valley Exteriors",
    "wof:placetype":"venue"
},
  "geometry": {"coordinates":[-97.81822,30.461428],"type":"Point"}
}