{
  "type": "Feature",
  "properties": {
    "iso:country":"US",
    "sg:address":"2600 Mossrock Dr",
    "sg:city":"San Antonio",
    "sg:classifiers":[
        {
            "category":"Wholesale",
            "subcategory":"Auto Parts",
            "type":"Manufacturing & Wholesale Goods"
        }
    ],
    "sg:phone":"+1 210 863 7080",
    "sg:postcode":"78230",
    "sg:province":"TX",
    "wof:name":"Longhorn Truck Equipment",
    "wof:placetype":"venue"
},
  "geometry": {"coordinates":[-98.53848499999999,29.512907],"type":"Point"}
}