{
  "type": "Feature",
  "properties": {
    "iso:country":"US",
    "sg:address":"14645 Waterview Cir",
    "sg:city":"Addison",
    "sg:classifiers":[
        {
            "category":"Building & Trades",
            "subcategory":"Construction",
            "type":"Services"
        }
    ],
    "sg:phone":"+1 972 738 5220",
    "sg:postcode":"75001",
    "sg:province":"TX",
    "sg:tags":[
        "interior",
        "design"
    ],
    "wof:name":"Jah Interior Designs",
    "wof:placetype":"venue"
},
  "geometry": {"coordinates":[-96.848198,32.945301],"type":"Point"}
}