{
  "type": "Feature",
  "properties": {
    "iso:country":"US",
    "sg:address":"1205 Ashford Dr",
    "sg:city":"San Angelo",
    "sg:classifiers":[
        {
            "category":"Shopping",
            "type":"Retail Goods"
        }
    ],
    "sg:phone":"+1 325 223 1394",
    "sg:postcode":"76901",
    "sg:province":"TX",
    "sg:tags":[
        "cosmetic",
        "perfume"
    ],
    "wof:name":"Mary Kay Cosmetics",
    "wof:placetype":"venue"
},
  "geometry": {"coordinates":[-100.514675,31.440404],"type":"Point"}
}