{
  "type": "Feature",
  "properties": {
    "iso:country":"US",
    "sg:address":"5101 Lawnview Ave",
    "sg:city":"Dallas",
    "sg:classifiers":[
        {
            "category":"Wholesale",
            "subcategory":"Metals & Minerals",
            "type":"Manufacturing & Wholesale Goods"
        }
    ],
    "sg:phone":"+1 214 275 5565",
    "sg:postcode":"75227",
    "sg:province":"TX",
    "sg:tags":[
        "specialty"
    ],
    "wof:name":"Kirb Service",
    "wof:placetype":"venue"
},
  "geometry": {"coordinates":[-96.72568699999999,32.791008],"type":"Point"}
}