{
  "type": "Feature",
  "properties": {
    "iso:country":"US",
    "sg:address":"3739 SW Military Dr",
    "sg:city":"San Antonio",
    "sg:classifiers":[
        {
            "category":"Professional",
            "subcategory":"Accounting & Tax Preparation",
            "type":"Services"
        }
    ],
    "sg:phone":"+1 210 922 4831",
    "sg:postcode":"78211",
    "sg:province":"TX",
    "sg:tags":[
        "bookkeeping",
        "general"
    ],
    "wof:name":"A J Bookeeping",
    "wof:placetype":"venue"
},
  "geometry": {"coordinates":[-98.56307,29.358604],"type":"Point"}
}