{
  "type": "Feature",
  "properties": {
    "iso:country":"US",
    "sg:address":"8213 Turnberry St",
    "sg:city":"Rowlett",
    "sg:classifiers":[
        {
            "category":"Retail",
            "subcategory":"Laundry & Dry Cleaning",
            "type":"Services"
        }
    ],
    "sg:phone":"+1 972 226 2266",
    "sg:postcode":"75089",
    "sg:province":"TX",
    "sg:tags":[
        "cleaners",
        "rug",
        "carpet"
    ],
    "wof:name":"Cleaner Image",
    "wof:placetype":"venue"
},
  "geometry": {"coordinates":[-96.53424,32.93988],"type":"Point"}
}