{
  "type": "Feature",
  "properties": {
    "iso:country":"US",
    "sg:address":"3001 FM 1629",
    "sg:city":"Bonham",
    "sg:classifiers":[
        {
            "category":"Farming",
            "subcategory":"Livestock Farm",
            "type":"Manufacturing & Wholesale Goods"
        }
    ],
    "sg:phone":"+1 903 583 2625",
    "sg:postcode":"75418",
    "sg:province":"TX",
    "sg:tags":[
        "beef",
        "feedlot",
        "cattle"
    ],
    "wof:name":"Scott Hartwell Farms",
    "wof:placetype":"venue"
},
  "geometry": {"coordinates":[-96.213982,33.530622],"type":"Point"}
}