{
  "type": "Feature",
  "properties": {
    "iso:country":"US",
    "sg:address":"3969 Teasley Ln",
    "sg:city":"Denton",
    "sg:classifiers":[
        {
            "category":"Retail",
            "subcategory":"Laundry & Dry Cleaning",
            "type":"Services"
        }
    ],
    "sg:phone":"+1 940 380 1900",
    "sg:postcode":"76210",
    "sg:province":"TX",
    "sg:tags":[
        "cleaners"
    ],
    "wof:name":"Best 1 Hr Cleaners & Laundry",
    "wof:placetype":"venue"
},
  "geometry": {"coordinates":[-97.105581,33.159653],"type":"Point"}
}