{
  "type": "Feature",
  "properties": {
    "iso:country":"US",
    "sg:address":"133 Big Joshua Creek Rd",
    "sg:city":"Comfort",
    "sg:classifiers":[
        {
            "category":"Wholesale",
            "subcategory":"Durable Goods & Equipment",
            "type":"Manufacturing & Wholesale Goods"
        }
    ],
    "sg:phone":"+1 830 995 2648",
    "sg:postcode":"78013",
    "sg:province":"TX",
    "sg:tags":[
        "antique",
        "dealers-wholesale"
    ],
    "wof:name":"A Little Room",
    "wof:placetype":"venue"
},
  "geometry": {"coordinates":[-98.86292299999999,29.901593],"type":"Point"}
}