{
  "type": "Feature",
  "properties": {
    "iso:country":"US",
    "sg:address":"4819 Hershe St",
    "sg:city":"Houston",
    "sg:classifiers":[
        {
            "category":"Organizations",
            "subcategory":"Religious Organization",
            "type":"Services"
        }
    ],
    "sg:phone":"+1 713 672 6822",
    "sg:postcode":"77020",
    "sg:province":"TX",
    "sg:tags":[
        "church"
    ],
    "wof:name":"Mount Pleasant Baptist Church",
    "wof:placetype":"venue"
},
  "geometry": {"coordinates":[-95.32121100000001,29.777752],"type":"Point"}
}