{
  "type": "Feature",
  "properties": {
    "iso:country":"US",
    "sg:address":"2530 Tangley St",
    "sg:city":"Houston",
    "sg:classifiers":[
        {
            "category":"Real Estate",
            "subcategory":"Real Estate Operator",
            "type":"Services"
        }
    ],
    "sg:phone":"+1 713 523 8115",
    "sg:postcode":"77005",
    "sg:province":"TX",
    "sg:tags":[
        "building",
        "nonresidential"
    ],
    "wof:name":"Bartash Co",
    "wof:placetype":"venue"
},
  "geometry": {"coordinates":[-95.418019,29.719914],"type":"Point"}
}