{
  "type": "Feature",
  "properties": {
    "iso:country":"US",
    "sg:address":"925 Santa Fe Dr",
    "sg:city":"Weatherford",
    "sg:classifiers":[
        {
            "category":"Real Estate",
            "subcategory":"Real Estate Agent",
            "type":"Services"
        }
    ],
    "sg:phone":"+1 817 594 0220",
    "sg:postcode":"76086",
    "sg:province":"TX",
    "wof:name":"Perry Mader Properties",
    "wof:placetype":"venue"
},
  "geometry": {"coordinates":[-97.784831,32.749796],"type":"Point"}
}