{
  "type": "Feature",
  "properties": {
    "iso:country":"US",
    "sg:address":"1201 Bundrant Dr",
    "sg:city":"Killeen",
    "sg:classifiers":[
        {
            "category":"Organizations",
            "subcategory":"Religious Organization",
            "type":"Services"
        }
    ],
    "sg:phone":"+1 254 634 0178",
    "sg:postcode":"76543",
    "sg:province":"TX",
    "sg:tags":[
        "church"
    ],
    "wof:name":"Christian Assistance Network",
    "wof:placetype":"venue"
},
  "geometry": {"coordinates":[-97.69903499999999,31.121108],"type":"Point"}
}