{
  "type": "Feature",
  "properties": {
    "iso:country":"US",
    "sg:address":"4013 RM 620 N",
    "sg:city":"Austin",
    "sg:classifiers":[
        {
            "category":"Retail",
            "subcategory":"Photofinishing",
            "type":"Services"
        }
    ],
    "sg:phone":"+1 512 266 2822",
    "sg:postcode":"78734",
    "sg:province":"TX",
    "sg:tags":[
        "laboratory",
        "savings",
        "institution"
    ],
    "wof:name":"Capital Capitol",
    "wof:placetype":"venue"
},
  "geometry": {"coordinates":[-97.921683,30.396578],"type":"Point"}
}