{
  "type": "Feature",
  "properties": {
    "iso:country":"US",
    "sg:address":"905 S 19th St",
    "sg:city":"Slaton",
    "sg:classifiers":[
        {
            "category":"Home & Garden",
            "subcategory":"Carpets & Floor Coverings",
            "type":"Retail Goods"
        }
    ],
    "sg:phone":"+1 806 828 4174",
    "sg:postcode":"79364",
    "sg:province":"TX",
    "sg:tags":[
        "laying",
        "contractor"
    ],
    "wof:name":"Winchester Carpets",
    "wof:placetype":"venue"
},
  "geometry": {"coordinates":[-101.65558900000001,33.430908],"type":"Point"}
}