{
  "type": "Feature",
  "properties": {
    "iso:country":"US",
    "sg:address":"14511 Ridge Meadow Dr",
    "sg:city":"San Antonio",
    "sg:classifiers":[
        {
            "category":"Wholesale",
            "subcategory":"Electrical",
            "type":"Manufacturing & Wholesale Goods"
        }
    ],
    "sg:phone":"+1 210 946 4285",
    "sg:postcode":"78233",
    "sg:province":"TX",
    "sg:tags":[
        "equipment"
    ],
    "wof:name":"Prodigy Security",
    "wof:placetype":"venue"
},
  "geometry": {"coordinates":[-98.36425300000001,29.573961],"type":"Point"}
}