{
  "type": "Feature",
  "properties": {
    "iso:country":"US",
    "sg:address":"4326 Lea Ln",
    "sg:city":"Richmond",
    "sg:classifiers":[
        {
            "category":"Professional",
            "type":"Services"
        }
    ],
    "sg:phone":"+1 281 346 1239",
    "sg:postcode":"77469",
    "sg:province":"TX",
    "wof:name":"Cada Remy Inc",
    "wof:placetype":"venue"
},
  "geometry": {"coordinates":[-95.87568899999999,29.66653],"type":"Point"}
}