{
  "type": "Feature",
  "properties": {
    "iso:country":"US",
    "sg:address":"33596 Stahl Lane",
    "sg:city":"Bulverde",
    "sg:classifiers":[
        {
            "category":"Professional",
            "subcategory":"Accounting & Tax Preparation",
            "type":"Services"
        }
    ],
    "sg:phone":"+1 830 980 3368",
    "sg:postcode":"78163",
    "sg:province":"TX",
    "sg:tags":[
        "accountant"
    ],
    "sg:website":"www.tolbertcpa.com",
    "wof:name":"Tolbert Cpa Llc",
    "wof:placetype":"venue"
},
  "geometry": {"coordinates":[-98.410326,29.788576],"type":"Point"}
}