{
  "type": "Feature",
  "properties": {
    "iso:country":"US",
    "sg:address":"890 Shores Blvd",
    "sg:city":"Rockwall",
    "sg:classifiers":[
        {
            "category":"Real Estate",
            "subcategory":"Real Estate Agent",
            "type":"Services"
        }
    ],
    "sg:phone":"+1 214 797 0502",
    "sg:postcode":"75087",
    "sg:province":"TX",
    "sg:tags":[
        "inspection"
    ],
    "wof:name":"National Property Inspections",
    "wof:placetype":"venue"
},
  "geometry": {"coordinates":[-96.48194100000001,32.946222],"type":"Point"}
}