{
  "type": "Feature",
  "properties": {
    "iso:country":"US",
    "sg:address":"1901 S Voss Rd",
    "sg:city":"Houston",
    "sg:classifiers":[
        {
            "category":"Building & Trades",
            "subcategory":"Landscaping Services",
            "type":"Services"
        }
    ],
    "sg:phone":"+1 832 216 1222",
    "sg:postcode":"77057",
    "sg:province":"TX",
    "sg:tags":[
        "removal"
    ],
    "wof:name":"J-Mac Enterprises",
    "wof:placetype":"venue"
},
  "geometry": {"coordinates":[-95.50101100000001,29.749745],"type":"Point"}
}