{
  "type": "Feature",
  "properties": {
    "iso:country":"US",
    "sg:address":"655 W Illinois Ave",
    "sg:city":"Dallas",
    "sg:classifiers":[
        {
            "category":"Shopping",
            "subcategory":"Discount & Variety Stores",
            "type":"Retail Goods"
        }
    ],
    "sg:phone":"+1 214 943 1844",
    "sg:postcode":"75224",
    "sg:province":"TX",
    "wof:name":"Family Dollar Stores",
    "wof:placetype":"venue"
},
  "geometry": {"coordinates":[-96.835335,32.720393],"type":"Point"}
}