{
  "type": "Feature",
  "properties": {
    "iso:country":"US",
    "sg:address":"3601 W Alabama St",
    "sg:city":"Houston",
    "sg:classifiers":[
        {
            "category":"Retail",
            "subcategory":"Repair Shop",
            "type":"Services"
        },
        {
            "category":"Shopping",
            "type":"Retail Goods"
        }
    ],
    "sg:phone":"+1 713 961 7371",
    "sg:postcode":"77027",
    "sg:province":"TX",
    "sg:tags":[
        "lock",
        "safe",
        "item",
        "vault"
    ],
    "wof:name":"Knapp Lock & Safe Co Inc",
    "wof:placetype":"venue"
},
  "geometry": {"coordinates":[-95.43462599999999,29.738291],"type":"Point"}
}