{
  "type": "Feature",
  "properties": {
    "iso:country":"US",
    "sg:address":"2909 Westridge",
    "sg:city":"Houston",
    "sg:classifiers":[
        {
            "category":"Shopping",
            "type":"Retail Goods"
        }
    ],
    "sg:phone":"+1 713 661 0038",
    "sg:postcode":"77054",
    "sg:province":"TX",
    "sg:tags":[
        "cosmetic",
        "perfume"
    ],
    "wof:name":"Bestway Beauty Supply & Fshn",
    "wof:placetype":"venue"
},
  "geometry": {"coordinates":[-95.421673,29.682168],"type":"Point"}
}