{
  "type": "Feature",
  "properties": {
    "iso:country":"US",
    "sg:address":"1800 Mormon Mill Rd",
    "sg:city":"Marble Falls",
    "sg:classifiers":[
        {
            "category":"Health Services",
            "subcategory":"Doctor",
            "type":"Services"
        }
    ],
    "sg:phone":"+1 830 693 0040",
    "sg:postcode":"78654",
    "sg:province":"TX",
    "sg:tags":[
        "physician",
        "surgeon",
        "medical"
    ],
    "wof:name":"Austin Heart",
    "wof:placetype":"venue"
},
  "geometry": {"coordinates":[-98.26888,30.587167],"type":"Point"}
}