{
  "type": "Feature",
  "properties": {
    "iso:country":"US",
    "sg:address":"29130 Huffman Cleveland Rd",
    "sg:city":"Huffman",
    "sg:classifiers":[
        {
            "category":"Home & Garden",
            "subcategory":"Home Furnishings",
            "type":"Retail Goods"
        }
    ],
    "sg:phone":"+1 281 324 6600",
    "sg:postcode":"77336",
    "sg:province":"TX",
    "sg:tags":[
        "pottery"
    ],
    "wof:name":"H & H Pottery & Iron",
    "wof:placetype":"venue"
},
  "geometry": {"coordinates":[-95.11096999999999,30.081113],"type":"Point"}
}