{
  "type": "Feature",
  "properties": {
    "iso:country":"US",
    "sg:address":"1421 N Main St",
    "sg:city":"Liberty",
    "sg:classifiers":[
        {
            "category":"Shopping",
            "subcategory":"Computers & Home Electronics",
            "type":"Retail Goods"
        }
    ],
    "sg:phone":"+1 936 336 4124",
    "sg:postcode":"77575",
    "sg:province":"TX",
    "sg:tags":[
        "related",
        "software"
    ],
    "wof:name":"Computer Solutions",
    "wof:placetype":"venue"
},
  "geometry": {"coordinates":[-94.792799,30.0684],"type":"Point"}
}