{
  "type": "Feature",
  "properties": {
    "iso:country":"US",
    "sg:address":"9012 Garland Rd",
    "sg:city":"Dallas",
    "sg:classifiers":[
        {
            "category":"Personal",
            "subcategory":"Tattoo Parlor",
            "type":"Services"
        },
        {
            "category":"Personal",
            "subcategory":"Hair Removal",
            "type":"Services"
        }
    ],
    "sg:phone":"+1 214 394 6824",
    "sg:postcode":"75218",
    "sg:province":"TX",
    "sg:website":"www.fadefast.com",
    "wof:name":"Fade Fast Tattoo Removal",
    "wof:placetype":"venue"
},
  "geometry": {"coordinates":[-96.709338,32.827354],"type":"Point"}
}