{
  "type": "Feature",
  "properties": {
    "iso:country":"US",
    "sg:address":"10825 Waterbridge Cir",
    "sg:city":"Dallas",
    "sg:classifiers":[
        {
            "category":"Shopping",
            "subcategory":"Used Merchandise",
            "type":"Retail Goods"
        }
    ],
    "sg:phone":"+1 214 324 3672",
    "sg:postcode":"75218",
    "sg:province":"TX",
    "wof:name":"This New House",
    "wof:placetype":"venue"
},
  "geometry": {"coordinates":[-96.691677,32.85047],"type":"Point"}
}