{
  "type": "Feature",
  "properties": {
    "iso:country":"US",
    "sg:address":"5400 Brodie Ln Ste 210",
    "sg:city":"Sunset Valley",
    "sg:classifiers":[
        {
            "category":"Recreation",
            "subcategory":"Arcade",
            "type":"Entertainment"
        },
        {
            "category":"Cinema",
            "subcategory":"Movie Rental",
            "type":"Entertainment"
        },
        {
            "category":"Shopping",
            "subcategory":"Computers & Home Electronics",
            "type":"Retail Goods"
        }
    ],
    "sg:phone":"+1 512 891 6837",
    "sg:postcode":"78745",
    "sg:province":"TX",
    "sg:tags":[
        "game",
        "video"
    ],
    "sg:website":"www.gameovervideogames.com",
    "wof:name":"Game Over Videogames",
    "wof:placetype":"venue"
},
  "geometry": {"coordinates":[-97.822371,30.227914],"type":"Point"}
}