{
  "type": "Feature",
  "properties": {
    "iso:country":"US",
    "sg:address":"10200 Grogans Mill Rd",
    "sg:city":"Spring",
    "sg:classifiers":[
        {
            "category":"Professional",
            "subcategory":"Lawyer & Legal Services",
            "type":"Services"
        }
    ],
    "sg:phone":"+1 281 465 0712",
    "sg:postcode":"77380",
    "sg:province":"TX",
    "sg:tags":[
        "attorney"
    ],
    "wof:name":"Lane & Reitzer Atty At Law",
    "wof:placetype":"venue"
},
  "geometry": {"coordinates":[-95.47203399999999,30.157007],"type":"Point"}
}