{
  "type": "Feature",
  "properties": {
    "iso:country":"US",
    "sg:address":"3801 Beverly Dr",
    "sg:city":"Dallas",
    "sg:classifiers":[
        {
            "category":"Professional",
            "subcategory":"Business Services",
            "type":"Services"
        }
    ],
    "sg:phone":"+1 214 521 0521",
    "sg:postcode":"75205",
    "sg:province":"TX",
    "wof:name":"Walnut Interiors",
    "wof:placetype":"venue"
},
  "geometry": {"coordinates":[-96.798266,32.83235],"type":"Point"}
}