{
  "type": "Feature",
  "properties": {
    "iso:country":"US",
    "sg:address":"1019 Forest Home Dr",
    "sg:city":"Houston",
    "sg:classifiers":[
        {
            "category":"Professional",
            "subcategory":"Art Services",
            "type":"Services"
        }
    ],
    "sg:phone":"+1 281 497 3176",
    "sg:postcode":"77077",
    "sg:province":"TX",
    "sg:tags":[
        "photography",
        "commercial"
    ],
    "wof:name":"Sam Pierson Jr Photography",
    "wof:placetype":"venue"
},
  "geometry": {"coordinates":[-95.637382,29.768244],"type":"Point"}
}