{
  "type": "Feature",
  "properties": {
    "iso:country":"US",
    "sg:address":"309 N Jackson St",
    "sg:city":"Beeville",
    "sg:classifiers":[
        {
            "category":"Education",
            "subcategory":"Special Training",
            "type":"Public Place"
        }
    ],
    "sg:phone":"+1 361 358 9586",
    "sg:postcode":"78102",
    "sg:province":"TX",
    "wof:name":"Bee Co Literacy Council",
    "wof:placetype":"venue"
},
  "geometry": {"coordinates":[-97.753407,28.402602],"type":"Point"}
}