{
  "type": "Feature",
  "properties": {
    "iso:country":"US",
    "sg:address":"9064 Sandy Rd",
    "sg:city":"Wichita Falls",
    "sg:classifiers":[
        {
            "category":"Professional",
            "type":"Services"
        }
    ],
    "sg:phone":"+1 940 855 4598",
    "sg:postcode":"76305",
    "sg:province":"TX",
    "wof:name":"Beverly N Messer",
    "wof:placetype":"venue"
},
  "geometry": {"coordinates":[-98.512185,34.049684],"type":"Point"}
}