{
  "type": "Feature",
  "properties": {
    "iso:country":"US",
    "sg:address":"3800 Southwest Fwy Ste 104",
    "sg:city":"Houston",
    "sg:classifiers":[
        {
            "category":"Education",
            "subcategory":"Music School",
            "type":"Public Place"
        }
    ],
    "sg:phone":"+1 713 524 2900",
    "sg:postcode":"77027",
    "sg:province":"TX",
    "sg:tags":[
        "instrument",
        "teacher",
        "musical"
    ],
    "sg:website":"www.forsheypiano.com",
    "wof:name":"Forshey Piano Company",
    "wof:placetype":"venue"
},
  "geometry": {"coordinates":[-95.43735,29.72942],"type":"Point"}
}