{
  "type": "Feature",
  "properties": {
    "iso:country":"US",
    "sg:address":"7508 Rall Cir",
    "sg:city":"Fort Worth",
    "sg:classifiers":[
        {
            "category":"Professional",
            "subcategory":"Business Services",
            "type":"Services"
        }
    ],
    "sg:phone":"+1 817 292 1219",
    "sg:postcode":"76132",
    "sg:province":"TX",
    "wof:name":"Carol Fisher Intr",
    "wof:placetype":"venue"
},
  "geometry": {"coordinates":[-97.424376,32.652399],"type":"Point"}
}