{
  "type": "Feature",
  "properties": {
    "iso:country":"US",
    "sg:address":"3708 Gulfway Dr",
    "sg:city":"Port Arthur",
    "sg:classifiers":[
        {
            "category":"Banks & Credit Unions",
            "subcategory":"Investment Brokerage",
            "type":"Services"
        }
    ],
    "sg:phone":"+1 409 985 8828",
    "sg:postcode":"77642",
    "sg:province":"TX",
    "sg:tags":[
        "security",
        "insurance"
    ],
    "wof:name":"Tat Insurance Agency",
    "wof:placetype":"venue"
},
  "geometry": {"coordinates":[-93.919421,29.90875],"type":"Point"}
}