{
  "type": "Feature",
  "properties": {
    "iso:country":"US",
    "sg:address":"1906 37th St",
    "sg:city":"Lubbock",
    "sg:classifiers":[
        {
            "category":"Professional",
            "subcategory":"Business Services",
            "type":"Services"
        }
    ],
    "sg:phone":"+1 806 744 1620",
    "sg:postcode":"79412",
    "sg:province":"TX",
    "wof:name":"Perfection Interiors",
    "wof:placetype":"venue"
},
  "geometry": {"coordinates":[-101.861665,33.56063],"type":"Point"}
}