{
  "type": "Feature",
  "properties": {
    "iso:country":"US",
    "sg:address":"701 Moss Wood",
    "sg:city":"Schertz",
    "sg:classifiers":[
        {
            "category":"Organizations",
            "subcategory":"Community Association",
            "type":"Services"
        }
    ],
    "sg:phone":"+1 210 659 8703",
    "sg:postcode":"78154",
    "sg:province":"TX",
    "wof:name":"The Park At Woodland Oaks Owners Association",
    "wof:placetype":"venue"
},
  "geometry": {"coordinates":[-98.273369,29.573978],"type":"Point"}
}