{
  "type": "Feature",
  "properties": {
    "iso:country":"US",
    "sg:address":"7509 Quarry Chase Trl",
    "sg:city":"Plano",
    "sg:classifiers":[
        {
            "category":"Retail",
            "subcategory":"Repair Shop",
            "type":"Services"
        }
    ],
    "sg:phone":"+1 972 618 8510",
    "sg:postcode":"75025",
    "sg:province":"TX",
    "wof:name":"Jims Small Engine Maintenance",
    "wof:placetype":"venue"
},
  "geometry": {"coordinates":[-96.744659,33.079116],"type":"Point"}
}