{
  "type": "Feature",
  "properties": {
    "iso:country":"US",
    "sg:address":"1500 E Fayle Ave",
    "sg:city":"Baytown",
    "sg:classifiers":[
        {
            "category":"Professional",
            "subcategory":"Business Services",
            "type":"Services"
        }
    ],
    "sg:phone":"+1 281 420 1162",
    "sg:postcode":"77520",
    "sg:province":"TX",
    "sg:tags":[
        "home",
        "health",
        "care"
    ],
    "wof:name":"My 3 Sons",
    "wof:placetype":"venue"
},
  "geometry": {"coordinates":[-94.947569,29.732819],"type":"Point"}
}