{
  "type": "Feature",
  "properties": {
    "iso:country":"US",
    "sg:address":"1172 Webberville Rd",
    "sg:city":"Austin",
    "sg:classifiers":[
        {
            "category":"Real Estate",
            "subcategory":"Real Estate Operator",
            "type":"Services"
        }
    ],
    "sg:phone":"+1 512 926 9311",
    "sg:postcode":"78721",
    "sg:province":"TX",
    "sg:tags":[
        "building",
        "apartment"
    ],
    "wof:name":"Rollins-Martin Apartments",
    "wof:placetype":"venue"
},
  "geometry": {"coordinates":[-97.686829,30.277081],"type":"Point"}
}