{
  "type": "Feature",
  "properties": {
    "iso:country":"US",
    "sg:address":"12606 Campsite Trl",
    "sg:city":"Cypress",
    "sg:classifiers":[
        {
            "category":"Wholesale",
            "subcategory":"Medical Equipment & Supplies",
            "type":"Manufacturing & Wholesale Goods"
        }
    ],
    "sg:phone":"+1 281 890 6220",
    "sg:postcode":"77429",
    "sg:province":"TX",
    "wof:name":"Ultramed",
    "wof:placetype":"venue"
},
  "geometry": {"coordinates":[-95.623384,29.960569],"type":"Point"}
}