{
  "type": "Feature",
  "properties": {
    "iso:country":"US",
    "sg:address":"6002 Tributary Ridge Ct",
    "sg:city":"Austin",
    "sg:classifiers":[
        {
            "category":"Health Services",
            "subcategory":"Clinic",
            "type":"Services"
        }
    ],
    "sg:phone":"+1 512 250 9789",
    "sg:postcode":"78759",
    "sg:province":"TX",
    "sg:tags":[
        "wellness",
        "program"
    ],
    "wof:name":"Nikken Wellness",
    "wof:placetype":"venue"
},
  "geometry": {"coordinates":[-97.761471,30.411007],"type":"Point"}
}