{
  "type": "Feature",
  "properties": {
    "iso:country":"US",
    "sg:address":"11301 Boothill Dr",
    "sg:city":"Austin",
    "sg:classifiers":[
        {
            "category":"Retail",
            "subcategory":"Car Wash",
            "type":"Services"
        }
    ],
    "sg:phone":"+1 512 990 2226",
    "sg:postcode":"78748",
    "sg:province":"TX",
    "sg:tags":[
        "polishing",
        "washing"
    ],
    "wof:name":"Squeeky Clean-North",
    "wof:placetype":"venue"
},
  "geometry": {"coordinates":[-97.85598,30.164292],"type":"Point"}
}