{
  "type": "Feature",
  "properties": {
    "iso:country":"US",
    "sg:address":"2601 River View Trl",
    "sg:city":"Granbury",
    "sg:classifiers":[
        {
            "category":"Building & Trades",
            "subcategory":"Construction",
            "type":"Services"
        }
    ],
    "sg:phone":"+1 817 573 4294",
    "sg:postcode":"76048",
    "sg:province":"TX",
    "sg:tags":[
        "contractor"
    ],
    "wof:name":"Arrowhead Stone & Rock Inc",
    "wof:placetype":"venue"
},
  "geometry": {"coordinates":[-97.723268,32.349755],"type":"Point"}
}