{
  "type": "Feature",
  "properties": {
    "iso:country":"US",
    "sg:address":"2213 Oates Dr",
    "sg:city":"Mesquite",
    "sg:classifiers":[
        {
            "category":"Autos & Motor Vehicles",
            "subcategory":"Fuel & Gas Station",
            "type":"Retail Goods"
        }
    ],
    "sg:phone":"+1 972 279 0009",
    "sg:postcode":"75150",
    "sg:province":"TX",
    "sg:tags":[
        "grocery"
    ],
    "wof:name":"Oates Mobil",
    "wof:placetype":"venue"
},
  "geometry": {"coordinates":[-96.6339,32.834097],"type":"Point"}
}