{
  "type": "Feature",
  "properties": {
    "iso:country":"US",
    "sg:address":"3030 Lincoln Ct",
    "sg:city":"Garland",
    "sg:classifiers":[
        {
            "category":"Professional",
            "type":"Services"
        }
    ],
    "sg:phone":"+1 972 238 0383",
    "sg:postcode":"75041",
    "sg:province":"TX",
    "sg:tags":[
        "establishment"
    ],
    "wof:name":"PPUSA Corp",
    "wof:placetype":"venue"
},
  "geometry": {"coordinates":[-96.680325,32.879271],"type":"Point"}
}