{
  "type": "Feature",
  "properties": {
    "iso:country":"US",
    "sg:address":"2215 State Loop 288",
    "sg:city":"Denton",
    "sg:classifiers":[
        {
            "category":"Shopping",
            "subcategory":"Bicycles & Sporting Goods",
            "type":"Retail Goods"
        }
    ],
    "sg:phone":"+1 940 382 3090",
    "sg:postcode":"76205",
    "sg:province":"TX",
    "wof:name":"Denton Sports Center",
    "wof:placetype":"venue"
},
  "geometry": {"coordinates":[-97.10423,33.189169],"type":"Point"}
}