{
  "type": "Feature",
  "properties": {
    "iso:country":"US",
    "sg:address":"104 E 6th Ave",
    "sg:city":"Amarillo",
    "sg:classifiers":[
        {
            "category":"Professional",
            "subcategory":"Printing & Photocopies",
            "type":"Services"
        }
    ],
    "sg:phone":"+1 806 794 9414",
    "sg:postcode":"79101",
    "sg:province":"AR",
    "sg:tags":[
        "duplicating",
        "copying"
    ],
    "sg:website":"www.lason.com",
    "wof:name":"Lason Inc",
    "wof:placetype":"venue"
},
  "geometry": {"coordinates":[-101.835838,35.207392],"type":"Point"}
}