{
  "type": "Feature",
  "properties": {
    "iso:country":"US",
    "sg:address":"3005 Woodlark Dr",
    "sg:city":"Fort Worth",
    "sg:classifiers":[
        {
            "category":"Food & Beverages",
            "subcategory":"Specialty",
            "type":"Retail Goods"
        }
    ],
    "sg:phone":"+1 817 294 4939",
    "sg:postcode":"76123",
    "sg:province":"TX",
    "wof:name":"Sams Coffee Service",
    "wof:placetype":"venue"
},
  "geometry": {"coordinates":[-97.364034,32.632605],"type":"Point"}
}