{
  "type": "Feature",
  "properties": {
    "iso:country":"US",
    "sg:address":"701 S Persimmon St",
    "sg:city":"Tomball",
    "sg:classifiers":[
        {
            "category":"Manufacturing",
            "subcategory":"Tools & Machinery",
            "type":"Manufacturing & Wholesale Goods"
        }
    ],
    "sg:phone":"+1 281 290 9950",
    "sg:postcode":"77375",
    "sg:province":"TX",
    "sg:tags":[
        "machine",
        "shop"
    ],
    "wof:name":"Advanced Precision Services LP",
    "wof:placetype":"venue"
},
  "geometry": {"coordinates":[-95.59962299999999,30.090177],"type":"Point"}
}