{
  "type": "Feature",
  "properties": {
    "iso:country":"US",
    "sg:address":"4571 Cape Charles Dr",
    "sg:city":"Plano",
    "sg:classifiers":[
        {
            "category":"Professional",
            "subcategory":"Business Services",
            "type":"Services"
        }
    ],
    "sg:phone":"+1 972 377 8260",
    "sg:postcode":"75024",
    "sg:province":"TX",
    "wof:name":"Pdl Enterprises LLC",
    "wof:placetype":"venue"
},
  "geometry": {"coordinates":[-96.786987,33.091877],"type":"Point"}
}