{
  "type": "Feature",
  "properties": {
    "iso:country":"US",
    "sg:address":"337 Murdock Rd",
    "sg:city":"Dallas",
    "sg:classifiers":[
        {
            "category":"Retail",
            "subcategory":"Auto Repair",
            "type":"Services"
        }
    ],
    "sg:phone":"+1 214 391 9633",
    "sg:postcode":"75217",
    "sg:province":"TX",
    "sg:tags":[
        "repairing",
        "automobile"
    ],
    "wof:name":"Erving Enterprise Svc",
    "wof:placetype":"venue"
},
  "geometry": {"coordinates":[-96.683159,32.709079],"type":"Point"}
}