{
  "type": "Feature",
  "properties": {
    "iso:country":"US",
    "sg:address":"5515 Kelvin",
    "sg:city":"Houston",
    "sg:classifiers":[
        {
            "category":"Shopping",
            "subcategory":"Clothing, Apparel, & Fashions",
            "type":"Retail Goods"
        }
    ],
    "sg:phone":"+1 713 942 2016",
    "sg:postcode":"77005",
    "sg:province":"TX",
    "sg:tags":[
        "clothing",
        "women's"
    ],
    "sg:website":"www.shophemline.com/store/",
    "wof:name":"Hemline",
    "wof:placetype":"venue"
},
  "geometry": {"coordinates":[-95.416652,29.716544],"type":"Point"}
}