{
  "type": "Feature",
  "properties": {
    "iso:country":"US",
    "sg:address":"1604 NW Military Hwy",
    "sg:city":"San Antonio",
    "sg:classifiers":[
        {
            "category":"Utilities",
            "subcategory":"Telephone",
            "type":"Services"
        }
    ],
    "sg:phone":"+1 210 308 5778",
    "sg:postcode":"78213",
    "sg:province":"TX",
    "sg:tags":[
        "communications"
    ],
    "wof:name":"Loop Networks",
    "wof:placetype":"venue"
},
  "geometry": {"coordinates":[-98.51683800000001,29.525219],"type":"Point"}
}