{
  "type": "Feature",
  "properties": {
    "iso:country":"US",
    "sg:address":"3913 N Co Rd 1130",
    "sg:city":"Midland",
    "sg:classifiers":[
        {
            "category":"Mining & Drilling",
            "type":"Manufacturing & Wholesale Goods"
        }
    ],
    "sg:phone":"+1 432 682 8104",
    "sg:postcode":"79705",
    "sg:province":"TX",
    "sg:tags":[
        "field",
        "oil"
    ],
    "wof:name":"C W Backhoe Svc",
    "wof:placetype":"venue"
},
  "geometry": {"coordinates":[-101.99467300000001,32.057421],"type":"Point"}
}