{
  "type": "Feature",
  "properties": {
    "iso:country":"US",
    "sg:address":"2251 FM 1103",
    "sg:city":"Universal City",
    "sg:classifiers":[
        {
            "category":"Retail",
            "subcategory":"Repair Shop",
            "type":"Services"
        }
    ],
    "sg:phone":"+1 210 659 5598",
    "sg:postcode":"78108",
    "sg:province":"TX",
    "sg:tags":[
        "upholsterer"
    ],
    "wof:name":"T & N Upholstery",
    "wof:placetype":"venue"
},
  "geometry": {"coordinates":[-98.21859600000001,29.578321],"type":"Point"}
}