{
  "type": "Feature",
  "properties": {
    "iso:country":"US",
    "sg:address":"1430 Oday Rd",
    "sg:city":"Pearland",
    "sg:classifiers":[
        {
            "category":"Wholesale",
            "subcategory":"Machinery & Supplies",
            "type":"Manufacturing & Wholesale Goods"
        }
    ],
    "sg:phone":"+1 281 997 7500",
    "sg:postcode":"77581",
    "sg:province":"TX",
    "sg:tags":[
        "equipment",
        "construction",
        "general"
    ],
    "wof:name":"Poston Equipment Sales Inc",
    "wof:placetype":"venue"
},
  "geometry": {"coordinates":[-95.314956,29.586442],"type":"Point"}
}