{
  "type": "Feature",
  "properties": {
    "iso:country":"US",
    "sg:address":"11235 Grissom Ln Ste A",
    "sg:city":"Dallas",
    "sg:classifiers":[
        {
            "category":"Arts & Performance",
            "subcategory":"Art Gallery",
            "type":"Entertainment"
        }
    ],
    "sg:phone":"+1 972 243 8899",
    "sg:postcode":"75229",
    "sg:province":"TX",
    "wof:name":"Perry Berns Gallery",
    "wof:placetype":"venue"
},
  "geometry": {"coordinates":[-96.887001,32.902901],"type":"Point"}
}