{
  "type": "Feature",
  "properties": {
    "iso:country":"US",
    "sg:address":"2213 Biscayne Dr E",
    "sg:city":"Irving",
    "sg:classifiers":[
        {
            "category":"Freight",
            "type":"Transportation"
        }
    ],
    "sg:phone":"+1 972 313 9310",
    "sg:postcode":"75060",
    "sg:province":"TX",
    "wof:name":"Kennard Freight Brokerage",
    "wof:placetype":"venue"
},
  "geometry": {"coordinates":[-96.97890099999999,32.788087],"type":"Point"}
}