{
  "type": "Feature",
  "properties": {
    "iso:country":"US",
    "sg:address":"9311 San Pedro Ave",
    "sg:city":"San Antonio",
    "sg:classifiers":[
        {
            "category":"Manufacturing",
            "subcategory":"Printing",
            "type":"Manufacturing & Wholesale Goods"
        }
    ],
    "sg:phone":"+1 210 524 7759",
    "sg:postcode":"78216",
    "sg:province":"TX",
    "sg:tags":[
        "publisher",
        "guide"
    ],
    "wof:name":"Guest Informant",
    "wof:placetype":"venue"
},
  "geometry": {"coordinates":[-98.498611,29.52677],"type":"Point"}
}