{
  "type": "Feature",
  "properties": {
    "iso:country":"US",
    "sg:address":"201 W Spring Dr",
    "sg:city":"West Lake Hills",
    "sg:classifiers":[
        {
            "category":"Building & Trades",
            "subcategory":"Construction",
            "type":"Services"
        }
    ],
    "sg:phone":"+1 512 306 9515",
    "sg:postcode":"78746",
    "sg:province":"TX",
    "sg:tags":[
        "contractor"
    ],
    "wof:name":"Brand Builders Co",
    "wof:placetype":"venue"
},
  "geometry": {"coordinates":[-97.807621,30.285212],"type":"Point"}
}