{
  "type": "Feature",
  "properties": {
    "iso:country":"US",
    "sg:address":"1445 Co Rd 115",
    "sg:city":"Pleasanton",
    "sg:classifiers":[
        {
            "category":"Building & Trades",
            "subcategory":"Construction",
            "type":"Services"
        }
    ],
    "sg:phone":"+1 830 216 7420",
    "sg:postcode":"78064",
    "sg:province":"TX",
    "sg:tags":[
        "highway",
        "maintenance"
    ],
    "wof:name":"K-Bar Services Inc",
    "wof:placetype":"venue"
},
  "geometry": {"coordinates":[-98.368505,29.141108],"type":"Point"}
}