{
  "type": "Feature",
  "properties": {
    "iso:country":"US",
    "sg:address":"3218 Restview St",
    "sg:city":"Longview",
    "sg:classifiers":[
        {
            "category":"Professional",
            "subcategory":"Art Services",
            "type":"Services"
        }
    ],
    "sg:phone":"+1 903 297 5393",
    "sg:postcode":"75605",
    "sg:province":"TX",
    "sg:tags":[
        "artist"
    ],
    "wof:name":"Erika's Art",
    "wof:placetype":"venue"
},
  "geometry": {"coordinates":[-94.77797,32.544099],"type":"Point"}
}