{
  "type": "Feature",
  "properties": {
    "iso:country":"US",
    "sg:address":"3400 W Marshall Ave",
    "sg:city":"Longview",
    "sg:classifiers":[
        {
            "category":"Restaurant",
            "type":"Food & Drink"
        }
    ],
    "sg:phone":"+1 903 935 6161",
    "sg:postcode":"75604",
    "sg:province":"TX",
    "sg:tags":[
        "eating"
    ],
    "wof:name":"Whataburger",
    "wof:placetype":"venue"
},
  "geometry": {"coordinates":[-94.79246999999999,32.506983],"type":"Point"}
}