{
  "type": "Feature",
  "properties": {
    "iso:country":"US",
    "sg:address":"2110 S. Lamar Blvd.",
    "sg:city":"Austin",
    "sg:classifiers":[
        {
            "category":"Personal",
            "subcategory":"Beauty Salon",
            "type":"Services"
        }
    ],
    "sg:phone":"+1 512 284 6000",
    "sg:postcode":"78704",
    "sg:province":"TX",
    "sg:tags":[
        "spa"
    ],
    "sg:website":"www.pureaustinnails.com",
    "wof:name":"Pure Austin Nails",
    "wof:placetype":"venue"
},
  "geometry": {"coordinates":[-97.771542,30.248244],"type":"Point"}
}