{
  "type": "Feature",
  "properties": {
    "iso:country":"US",
    "sg:address":"5400 E Mockingbird Ln",
    "sg:city":"Dallas",
    "sg:phone":"+1 214 823 2800",
    "sg:postcode":"75206",
    "sg:province":"TX",
    "sg:website":"http://www.reventeresale.com",
    "wof:name":"Revente - Ladies Upscale Resale",
    "wof:placetype":"venue"
},
  "geometry": {"coordinates":[-96.77522999999999,32.83651],"type":"Point"}
}