{
  "type": "Feature",
  "properties": {
    "iso:country":"US",
    "sg:address":"2542 Greene Ave",
    "sg:city":"Fort Worth",
    "sg:classifiers":[
        {
            "category":"Restaurant",
            "type":"Food & Drink"
        }
    ],
    "sg:phone":"+1 817 377 3110",
    "sg:postcode":"76109",
    "sg:province":"TX",
    "sg:tags":[
        "eating"
    ],
    "wof:name":"A & W Restaurants Inc",
    "wof:placetype":"venue"
},
  "geometry": {"coordinates":[-97.358343,32.714741],"type":"Point"}
}