{
  "type": "Feature",
  "properties": {
    "iso:country":"US",
    "sg:address":"1007 Earlsferry Dr",
    "sg:city":"Channelview",
    "sg:classifiers":[
        {
            "category":"Organizations",
            "subcategory":"Religious Organization",
            "type":"Services"
        }
    ],
    "sg:phone":"+1 281 452 2415",
    "sg:postcode":"77530",
    "sg:province":"TX",
    "sg:tags":[
        "church"
    ],
    "wof:name":"Cornerstone Community Church",
    "wof:placetype":"venue"
},
  "geometry": {"coordinates":[-95.154247,29.795766],"type":"Point"}
}