{
  "type": "Feature",
  "properties": {
    "iso:country":"US",
    "sg:address":"13345 Fm 1960 Rd W",
    "sg:city":"Houston",
    "sg:classifiers":[
        {
            "category":"Restaurant",
            "type":"Food & Drink"
        }
    ],
    "sg:menulink":"http://www.allmenus.com/tx/houston/10513-texas-roadhouse/menu/",
    "sg:phone":"+1 832 237 3015",
    "sg:postcode":"77065",
    "sg:province":"TX",
    "sg:tags":[
        "american",
        "steakhouse"
    ],
    "wof:name":"Texas Roadhouse",
    "wof:placetype":"venue"
},
  "geometry": {"coordinates":[-95.61738200000001,29.915333],"type":"Point"}
}