{
  "type": "Feature",
  "properties": {
    "iso:country":"US",
    "sg:address":"14239 FM 2920",
    "sg:city":"Tomball",
    "sg:classifiers":[
        {
            "category":"Restaurant",
            "type":"Food & Drink"
        }
    ],
    "sg:phone":"+1 281 351 4060",
    "sg:postcode":"77377",
    "sg:province":"TX",
    "wof:name":"Harris County Smokehouse",
    "wof:placetype":"venue"
},
  "geometry": {"coordinates":[-95.638721,30.089436],"type":"Point"}
}