{
  "type": "Feature",
  "properties": {
    "iso:country":"US",
    "sg:address":"506 S Bridge St",
    "sg:city":"Victoria",
    "sg:classifiers":[
        {
            "category":"Retail",
            "subcategory":"Repair Shop",
            "type":"Services"
        }
    ],
    "sg:phone":"+1 361 573 7668",
    "sg:postcode":"77901",
    "sg:province":"TX",
    "sg:tags":[
        "electrical"
    ],
    "wof:name":"Boldt Electric Service",
    "wof:placetype":"venue"
},
  "geometry": {"coordinates":[-97.008753,28.795133],"type":"Point"}
}