{
  "type": "Feature",
  "properties": {
    "iso:country":"US",
    "sg:address":"1001 Cross Timbers Rd",
    "sg:city":"Flower Mound",
    "sg:classifiers":[
        {
            "category":"Government",
            "subcategory":"Office",
            "type":"Public Place"
        }
    ],
    "sg:phone":"+1 972 874 6310",
    "sg:postcode":"75028",
    "sg:province":"TX",
    "sg:tags":[
        "village"
    ],
    "sg:website":"www.flower-mound.com",
    "wof:name":"Flower Mound Engineering",
    "wof:placetype":"venue"
},
  "geometry": {"coordinates":[-97.04061799999999,33.042212],"type":"Point"}
}