{
  "type": "Feature",
  "properties": {
    "iso:country":"US",
    "sg:address":"2024 Estates Dr",
    "sg:city":"Waco",
    "sg:classifiers":[
        {
            "category":"Banks & Credit Unions",
            "subcategory":"Investment Brokerage",
            "type":"Services"
        }
    ],
    "sg:phone":"+1 254 776 7358",
    "sg:postcode":"76712",
    "sg:province":"TX",
    "sg:tags":[
        "security"
    ],
    "wof:name":"Grandy Investment Corp",
    "wof:placetype":"venue"
},
  "geometry": {"coordinates":[-97.237234,31.519925],"type":"Point"}
}