{
  "type": "Feature",
  "properties": {
    "iso:country":"US",
    "sg:address":"812 W Royal Ln",
    "sg:city":"Irving",
    "sg:classifiers":[
        {
            "category":"Professional",
            "subcategory":"Management & Consulting",
            "type":"Services"
        }
    ],
    "sg:phone":"+1 972 506 7664",
    "sg:postcode":"75039",
    "sg:province":"TX",
    "sg:tags":[
        "business"
    ],
    "wof:name":"Powerstorm Corporation",
    "wof:placetype":"venue"
},
  "geometry": {"coordinates":[-96.959063,32.895881],"type":"Point"}
}