{
  "type": "Feature",
  "properties": {
    "iso:country":"US",
    "sg:address":"1625 11th St",
    "sg:city":"Wichita Falls",
    "sg:classifiers":[
        {
            "category":"Health Services",
            "subcategory":"Doctor",
            "type":"Services"
        }
    ],
    "sg:phone":"+1 940 723 0435",
    "sg:postcode":"76301",
    "sg:province":"TX",
    "sg:tags":[
        "dentist"
    ],
    "wof:name":"Family Dentistry Of Texoma",
    "wof:placetype":"venue"
},
  "geometry": {"coordinates":[-98.50072900000001,33.902693],"type":"Point"}
}