{
  "type": "Feature",
  "properties": {
    "iso:country":"US",
    "sg:address":"210 S Mesquite St",
    "sg:city":"Arlington",
    "sg:classifiers":[
        {
            "category":"Food & Beverages",
            "subcategory":"Specialty",
            "type":"Retail Goods"
        }
    ],
    "sg:phone":"+1 817 795 5790",
    "sg:postcode":"76010",
    "sg:province":"TX",
    "sg:tags":[
        "tea",
        "coffee"
    ],
    "wof:name":"Coffee Haus",
    "wof:placetype":"venue"
},
  "geometry": {"coordinates":[-97.105991,32.734956],"type":"Point"}
}