{
  "type": "Feature",
  "properties": {
    "iso:country":"US",
    "sg:address":"7714 FM 359",
    "sg:city":"Richmond",
    "sg:classifiers":[
        {
            "category":"Recreation",
            "type":"Entertainment"
        }
    ],
    "sg:phone":"+1 281 342 9800",
    "sg:postcode":"77469",
    "sg:province":"TX",
    "wof:name":"Gordon Campsite",
    "wof:placetype":"venue"
},
  "geometry": {"coordinates":[-95.82986200000001,29.645202],"type":"Point"}
}