{
  "type": "Feature",
  "properties": {
    "iso:country":"US",
    "sg:address":"612 Beech St",
    "sg:city":"Plainview",
    "sg:classifiers":[
        {
            "category":"Retail",
            "subcategory":"Auto Repair",
            "type":"Services"
        }
    ],
    "sg:phone":"+1 806 293 4766",
    "sg:postcode":"79072",
    "sg:province":"TX",
    "sg:tags":[
        "body",
        "repairing",
        "painting",
        "automobile"
    ],
    "wof:name":"Quality Body Shop",
    "wof:placetype":"venue"
},
  "geometry": {"coordinates":[-101.70044900000001,34.185833],"type":"Point"}
}