{
  "type": "Feature",
  "properties": {
    "iso:country":"US",
    "sg:address":"626 W San Antonio St",
    "sg:city":"San Marcos",
    "sg:classifiers":[
        {
            "category":"Cinema",
            "subcategory":"Movie Theater",
            "type":"Entertainment"
        }
    ],
    "sg:phone":"+1 512 396 8188",
    "sg:postcode":"78666",
    "sg:province":"TX",
    "sg:tags":[
        "motion",
        "picture"
    ],
    "wof:name":"San Marcos Prfrmg Arts Assoc",
    "wof:placetype":"venue"
},
  "geometry": {"coordinates":[-97.94684599999999,29.879088],"type":"Point"}
}