{
  "type": "Feature",
  "properties": {
    "iso:country":"US",
    "sg:address":"3749 US Hwy 183",
    "sg:city":"Briggs",
    "sg:classifiers":[
        {
            "category":"Food & Beverages",
            "subcategory":"Groceries & Convenience Stores",
            "type":"Retail Goods"
        }
    ],
    "sg:phone":"+1 512 489 9095",
    "sg:postcode":"78641",
    "sg:province":"TX",
    "wof:name":"Bright Briggs Lane",
    "wof:placetype":"venue"
},
  "geometry": {"coordinates":[-97.861369,30.600386],"type":"Point"}
}