{
  "type": "Feature",
  "properties": {
    "iso:country":"US",
    "sg:address":"3 Elmwood Rd",
    "sg:city":"Texarkana",
    "sg:classifiers":[
        {
            "category":"Social Services",
            "subcategory":"Child Care",
            "type":"Services"
        }
    ],
    "sg:phone":"+1 903 838 4814",
    "sg:postcode":"75501",
    "sg:province":"TX",
    "sg:tags":[
        "day"
    ],
    "wof:name":"Creative Teaching",
    "wof:placetype":"venue"
},
  "geometry": {"coordinates":[-94.169521,33.406447],"type":"Point"}
}