{
  "type": "Feature",
  "properties": {
    "iso:country":"US",
    "sg:address":"1054 Nevada St",
    "sg:city":"Mathis",
    "sg:classifiers":[
        {
            "category":"Freight",
            "type":"Transportation"
        }
    ],
    "sg:phone":"+1 361 547 6163",
    "sg:postcode":"78368",
    "sg:province":"TX",
    "sg:tags":[
        "operator",
        "local",
        "trucking"
    ],
    "wof:name":"Alfredo G Pena",
    "wof:placetype":"venue"
},
  "geometry": {"coordinates":[-97.823966,28.081607],"type":"Point"}
}