{
  "type": "Feature",
  "properties": {
    "iso:country":"US",
    "sg:address":"16420 Addison Rd",
    "sg:city":"Addison",
    "sg:classifiers":[
        {
            "category":"Retail",
            "subcategory":"Portrait Studio",
            "type":"Services"
        }
    ],
    "sg:phone":"+1 972 733 1122",
    "sg:postcode":"75001",
    "sg:province":"TX",
    "wof:name":"Portrait Studio",
    "wof:placetype":"venue"
},
  "geometry": {"coordinates":[-96.830331,32.975805],"type":"Point"}
}