{
  "type": "Feature",
  "properties": {
    "iso:country":"US",
    "sg:address":"3300 39th St",
    "sg:city":"Port Arthur",
    "sg:classifiers":[
        {
            "category":"Food & Beverages",
            "subcategory":"Groceries & Convenience Stores",
            "type":"Retail Goods"
        }
    ],
    "sg:phone":"+1 409 982 7788",
    "sg:postcode":"77642",
    "sg:province":"TX",
    "wof:name":"Express Stop",
    "wof:placetype":"venue"
},
  "geometry": {"coordinates":[-93.94326100000001,29.920325],"type":"Point"}
}