{
  "type": "Feature",
  "properties": {
    "iso:country":"US",
    "sg:address":"606 Frawley St",
    "sg:city":"Houston",
    "sg:classifiers":[
        {
            "category":"Building & Trades",
            "subcategory":"Construction",
            "type":"Services"
        }
    ],
    "sg:phone":"+1 713 694 1877",
    "sg:postcode":"77009",
    "sg:province":"TX",
    "sg:tags":[
        "hanging",
        "contractor"
    ],
    "wof:name":"Pedraza Paintg Contractor",
    "wof:placetype":"venue"
},
  "geometry": {"coordinates":[-95.363421,29.801575],"type":"Point"}
}