{
  "type": "Feature",
  "properties": {
    "iso:country":"US",
    "sg:address":"3209 Funston St",
    "sg:city":"Austin",
    "sg:classifiers":[
        {
            "category":"Insurance",
            "subcategory":"Hazard Insurance",
            "type":"Services"
        }
    ],
    "sg:phone":"+1 512 454 4073",
    "sg:postcode":"78703",
    "sg:province":"TX",
    "sg:tags":[
        "carrier"
    ],
    "wof:name":"ABC Property Casualty Insuranc",
    "wof:placetype":"venue"
},
  "geometry": {"coordinates":[-97.756908,30.306887],"type":"Point"}
}