{
  "type": "Feature",
  "properties": {
    "iso:country":"US",
    "sg:address":"4414 Lemmon Ave",
    "sg:city":"Dallas",
    "sg:classifiers":[
        {
            "category":"Real Estate",
            "subcategory":"Real Estate Services",
            "type":"Services"
        },
        {
            "category":"Real Estate",
            "subcategory":"Real Estate Operator",
            "type":"Services"
        }
    ],
    "sg:phone":"+1 972 432 6550",
    "sg:postcode":"75056",
    "sg:province":"TX",
    "sg:tags":[
        "apartment"
    ],
    "sg:website":"www.apartmentsophisticated.com",
    "wof:name":"Apartment Sophisticated",
    "wof:placetype":"venue"
},
  "geometry": {"coordinates":[-96.81264299999999,32.818501],"type":"Point"}
}