{
  "type": "Feature",
  "properties": {
    "iso:country":"US",
    "sg:address":"1416 Prospect St",
    "sg:city":"Texarkana",
    "sg:classifiers":[
        {
            "category":"Professional",
            "type":"Services"
        }
    ],
    "sg:phone":"+1 870 772 3436",
    "sg:postcode":"71854",
    "sg:province":"TX",
    "sg:tags":[
        "attendant",
        "park"
    ],
    "wof:name":"Copeland Contracting",
    "wof:placetype":"venue"
},
  "geometry": {"coordinates":[-94.04033699999999,33.408537],"type":"Point"}
}