{
  "type": "Feature",
  "properties": {
    "iso:country":"US",
    "sg:address":"3729 Topping St",
    "sg:city":"Houston",
    "sg:classifiers":[
        {
            "category":"Building & Trades",
            "subcategory":"Construction",
            "type":"Services"
        }
    ],
    "sg:phone":"+1 713 304 9513",
    "sg:postcode":"77093",
    "sg:province":"TX",
    "sg:tags":[
        "general",
        "contractor"
    ],
    "wof:name":"Manbro Construction",
    "wof:placetype":"venue"
},
  "geometry": {"coordinates":[-95.33017599999999,29.856937],"type":"Point"}
}