{
  "type": "Feature",
  "properties": {
    "iso:country":"US",
    "sg:address":"7340 Gessner Dr",
    "sg:city":"Houston",
    "sg:classifiers":[
        {
            "category":"Education",
            "subcategory":"School",
            "type":"Public Place"
        }
    ],
    "sg:phone":"+1 713 983 8668",
    "sg:postcode":"77040",
    "sg:province":"TX",
    "wof:name":"Harmony School of Excelence",
    "wof:placetype":"venue"
},
  "geometry": {"coordinates":[-95.540533,29.881348],"type":"Point"}
}