{
  "type": "Feature",
  "properties": {
    "iso:country":"US",
    "sg:address":"11257 Wharf Cove Dr",
    "sg:city":"El Paso",
    "sg:classifiers":[
        {
            "category":"Shopping",
            "subcategory":"Hobbies, Toys, & Games",
            "type":"Retail Goods"
        }
    ],
    "sg:phone":"+1 915 629 9935",
    "sg:postcode":"79936",
    "sg:province":"TX",
    "wof:name":"Ceramicas Lizette",
    "wof:placetype":"venue"
},
  "geometry": {"coordinates":[-106.305279,31.782952],"type":"Point"}
}