{
  "type": "Feature",
  "properties": {
    "iso:country":"US",
    "sg:address":"999 S Sam Houston Blvd",
    "sg:city":"San Benito",
    "sg:classifiers":[
        {
            "category":"Restaurant",
            "type":"Food & Drink"
        }
    ],
    "sg:phone":"+1 956 361 0998",
    "sg:postcode":"78586",
    "sg:province":"TX",
    "wof:name":"Mi Casita",
    "wof:placetype":"venue"
},
  "geometry": {"coordinates":[-97.638645,26.124235],"type":"Point"}
}