{
  "type": "Feature",
  "properties": {
    "iso:country":"US",
    "sg:address":"110 E Charnwood St",
    "sg:city":"Tyler",
    "sg:classifiers":[
        {
            "category":"Mining & Drilling",
            "type":"Manufacturing & Wholesale Goods"
        }
    ],
    "sg:phone":"+1 903 597 4279",
    "sg:postcode":"75701",
    "sg:province":"TX",
    "sg:tags":[
        "operator",
        "oil"
    ],
    "wof:name":"Southwest Operating Inc",
    "wof:placetype":"venue"
},
  "geometry": {"coordinates":[-95.29904500000001,32.342626],"type":"Point"}
}