{
  "type": "Feature",
  "properties": {
    "iso:country":"US",
    "sg:address":"7546 S Hall St",
    "sg:city":"Houston",
    "sg:classifiers":[
        {
            "category":"Shopping",
            "subcategory":"Clothing, Apparel, & Fashions",
            "type":"Retail Goods"
        }
    ],
    "sg:phone":"+1 713 633 4051",
    "sg:postcode":"77028",
    "sg:province":"TX",
    "sg:tags":[
        "family"
    ],
    "wof:name":"DS Things",
    "wof:placetype":"venue"
},
  "geometry": {"coordinates":[-95.292652,29.835723],"type":"Point"}
}