{
  "type": "Feature",
  "properties": {
    "iso:country":"US",
    "sg:address":"3040 Fm 1960 Rd E",
    "sg:city":"Houston",
    "sg:classifiers":[
        {
            "category":"Restaurant",
            "type":"Food & Drink"
        }
    ],
    "sg:menulink":"http://www.allmenus.com/tx/houston/46796-los-arcos-mexican-restaurant/menu/",
    "sg:phone":"+1 281 443 8200",
    "sg:postcode":"77073",
    "sg:province":"TX",
    "sg:tags":[
        "mexican"
    ],
    "wof:name":"Los Arcos Mexican Restaurant",
    "wof:placetype":"venue"
},
  "geometry": {"coordinates":[-95.381979,30.020644],"type":"Point"}
}