{
  "type": "Feature",
  "properties": {
    "iso:country":"US",
    "sg:address":"16418 Villa del Norte Dr",
    "sg:city":"Houston",
    "sg:classifiers":[
        {
            "category":"Building & Trades",
            "subcategory":"Pest Control",
            "type":"Services"
        }
    ],
    "sg:phone":"+1 281 821 1470",
    "sg:postcode":"77073",
    "sg:province":"TX",
    "wof:name":"Kc Pest Control",
    "wof:placetype":"venue"
},
  "geometry": {"coordinates":[-95.41726800000001,30.00515],"type":"Point"}
}