{
  "type": "Feature",
  "properties": {
    "iso:country":"US",
    "sg:address":"2623 Lauder Rd",
    "sg:city":"Houston",
    "sg:classifiers":[
        {
            "category":"Health Services",
            "subcategory":"Doctor",
            "type":"Services"
        }
    ],
    "sg:phone":"+1 281 449 4439",
    "sg:postcode":"77039",
    "sg:province":"TX",
    "sg:tags":[
        "surgeon",
        "oral"
    ],
    "wof:name":"Maddox Ronald Lee DDS",
    "wof:placetype":"venue"
},
  "geometry": {"coordinates":[-95.344902,29.913099],"type":"Point"}
}