{
  "type": "Feature",
  "properties": {
    "iso:country":"US",
    "sg:address":"3100 5th St",
    "sg:city":"Wichita Falls",
    "sg:classifiers":[
        {
            "category":"Home & Garden",
            "subcategory":"Household Appliances",
            "type":"Retail Goods"
        }
    ],
    "sg:phone":"+1 940 763 2202",
    "sg:postcode":"76301",
    "sg:province":"TX",
    "sg:tags":[
        "cleaners",
        "vacuum"
    ],
    "sg:website":"www.proair-delphin.com",
    "wof:name":"Aqua-Industries",
    "wof:placetype":"venue"
},
  "geometry": {"coordinates":[-98.526921,33.909659],"type":"Point"}
}