{
  "type": "Feature",
  "properties": {
    "iso:country":"US",
    "sg:address":"1800 FM 1092",
    "sg:city":"Missouri City",
    "sg:classifiers":[
        {
            "category":"Home & Garden",
            "subcategory":"Carpets & Floor Coverings",
            "type":"Retail Goods"
        }
    ],
    "sg:phone":"+1 281 403 8902",
    "sg:postcode":"77459",
    "sg:province":"TX",
    "wof:name":"Aries Discount Carpet",
    "wof:placetype":"venue"
},
  "geometry": {"coordinates":[-95.56431600000001,29.59549],"type":"Point"}
}