{
  "type": "Feature",
  "properties": {
    "iso:country":"US",
    "sg:address":"2580 Co Rd 430",
    "sg:city":"Jourdanton",
    "sg:classifiers":[
        {
            "category":"Building & Trades",
            "subcategory":"Equipment Rental",
            "type":"Services"
        }
    ],
    "sg:phone":"+1 830 769 9070",
    "sg:postcode":"78026",
    "sg:province":"TX",
    "sg:tags":[
        "leasing"
    ],
    "wof:name":"Wiley's Lease Svc",
    "wof:placetype":"venue"
},
  "geometry": {"coordinates":[-98.519976,28.914024],"type":"Point"}
}