{
  "type": "Feature",
  "properties": {
    "iso:country":"US",
    "sg:address":"3334 E Southcross Blvd",
    "sg:city":"San Antonio",
    "sg:classifiers":[
        {
            "category":"Food & Beverages",
            "subcategory":"Groceries & Convenience Stores",
            "type":"Retail Goods"
        }
    ],
    "sg:phone":"+1 210 533 0028",
    "sg:postcode":"78223",
    "sg:province":"TX",
    "wof:name":"King Cigar Inc",
    "wof:placetype":"venue"
},
  "geometry": {"coordinates":[-98.43366899999999,29.377573],"type":"Point"}
}