{
  "type": "Feature",
  "properties": {
    "iso:country":"US",
    "sg:address":"9000 Decker Ln",
    "sg:city":"Austin",
    "sg:classifiers":[
        {
            "category":"Professional",
            "subcategory":"Engineering",
            "type":"Services"
        }
    ],
    "sg:phone":"+1 512 278 0921",
    "sg:postcode":"78724",
    "sg:province":"TX",
    "sg:tags":[
        "electrical",
        "electronic",
        "engineer"
    ],
    "wof:name":"Sabal Semiconductor Inc",
    "wof:placetype":"venue"
},
  "geometry": {"coordinates":[-97.61264799999999,30.31498],"type":"Point"}
}