{
  "type": "Feature",
  "properties": {
    "iso:country":"US",
    "sg:address":"3418 E Oak Dr",
    "sg:city":"Spring",
    "sg:classifiers":[
        {
            "category":"Professional",
            "subcategory":"Business Services",
            "type":"Services"
        }
    ],
    "sg:phone":"+1 281 528 0990",
    "sg:postcode":"77365",
    "sg:province":"TX",
    "wof:name":"Nijah Enterprise",
    "wof:placetype":"venue"
},
  "geometry": {"coordinates":[-95.217747,30.095849],"type":"Point"}
}