{
  "type": "Feature",
  "properties": {
    "iso:country":"US",
    "sg:address":"1149 Tracy Ln",
    "sg:city":"Lancaster",
    "sg:classifiers":[
        {
            "category":"Building & Trades",
            "subcategory":"Landscaping Services",
            "type":"Services"
        }
    ],
    "sg:phone":"+1 972 227 7565",
    "sg:postcode":"75134",
    "sg:province":"TX",
    "wof:name":"Cut Creators Lawn Care",
    "wof:placetype":"venue"
},
  "geometry": {"coordinates":[-96.78279499999999,32.60833],"type":"Point"}
}