{
  "type": "Feature",
  "properties": {
    "iso:country":"US",
    "sg:address":"2911 Medical Arts St",
    "sg:city":"Austin",
    "sg:classifiers":[
        {
            "category":"Health Services",
            "subcategory":"Doctor",
            "type":"Services"
        }
    ],
    "sg:phone":"+1 512 391 0175",
    "sg:postcode":"78705",
    "sg:province":"TX",
    "wof:name":"Eng Caroline MD",
    "wof:placetype":"venue"
},
  "geometry": {"coordinates":[-97.728617,30.288731],"type":"Point"}
}