{
  "type": "Feature",
  "properties": {
    "iso:country":"US",
    "sg:address":"7405 Callbram Ln",
    "sg:city":"Austin",
    "sg:classifiers":[
        {
            "category":"Professional",
            "subcategory":"Management & Consulting",
            "type":"Services"
        }
    ],
    "sg:phone":"+1 512 288 3053",
    "sg:postcode":"78736",
    "sg:province":"TX",
    "wof:name":"Passion Marketing & Events",
    "wof:placetype":"venue"
},
  "geometry": {"coordinates":[-97.891273,30.235299],"type":"Point"}
}