{
  "type": "Feature",
  "properties": {
    "iso:country":"US",
    "sg:address":"302 Glenview Cir",
    "sg:city":"Woodway",
    "sg:classifiers":[
        {
            "category":"Autos & Motor Vehicles",
            "subcategory":"Automobile Sales",
            "type":"Retail Goods"
        }
    ],
    "sg:phone":"+1 254 776 6132",
    "sg:postcode":"76712",
    "sg:province":"TX",
    "sg:tags":[
        "new",
        "used",
        "car"
    ],
    "wof:name":"Trackstar Motorworks Inc",
    "wof:placetype":"venue"
},
  "geometry": {"coordinates":[-97.238663,31.490773],"type":"Point"}
}