{
  "type": "Feature",
  "properties": {
    "iso:country":"US",
    "sg:address":"4839 W Broadway Ave",
    "sg:city":"Fort Worth",
    "sg:classifiers":[
        {
            "category":"Professional",
            "type":"Services"
        }
    ],
    "sg:phone":"+1 817 831 6464",
    "sg:postcode":"76117",
    "sg:province":"TX",
    "wof:name":"Haltom City Parks & Recreation",
    "wof:placetype":"venue"
},
  "geometry": {"coordinates":[-97.278741,32.809744],"type":"Point"}
}