{
  "type": "Feature",
  "properties": {
    "iso:country":"US",
    "sg:address":"931 W Woodlawn Ave",
    "sg:city":"San Antonio",
    "sg:classifiers":[
        {
            "category":"Shopping",
            "subcategory":"Used Merchandise",
            "type":"Retail Goods"
        }
    ],
    "sg:phone":"+1 210 738 1880",
    "sg:postcode":"78201",
    "sg:province":"TX",
    "wof:name":"Gerald E Lockey Jr",
    "wof:placetype":"venue"
},
  "geometry": {"coordinates":[-98.50939200000001,29.452952],"type":"Point"}
}