{
  "type": "Feature",
  "properties": {
    "iso:country":"US",
    "sg:address":"12315 Jones Maltsberger Rd",
    "sg:city":"San Antonio",
    "sg:classifiers":[
        {
            "category":"Real Estate",
            "subcategory":"Real Estate Operator",
            "type":"Services"
        }
    ],
    "sg:phone":"+1 210 496 1036",
    "sg:postcode":"78247",
    "sg:province":"TX",
    "sg:tags":[
        "building",
        "apartment"
    ],
    "wof:name":"Santa Fe Condominiums",
    "wof:placetype":"venue"
},
  "geometry": {"coordinates":[-98.46721700000001,29.553467],"type":"Point"}
}