{
  "type": "Feature",
  "properties": {
    "iso:country":"US",
    "sg:address":"2742 Jeanetta St",
    "sg:city":"Houston",
    "sg:classifiers":[
        {
            "category":"Wholesale",
            "subcategory":"Scrap",
            "type":"Manufacturing & Wholesale Goods"
        },
        {
            "category":"Utilities",
            "subcategory":"Recycling",
            "type":"Services"
        }
    ],
    "sg:phone":"+1 713 498 4777",
    "sg:postcode":"77063",
    "sg:province":"TX",
    "sg:tags":[
        "junk",
        "hauling",
        "removal"
    ],
    "sg:website":"www.NotTrash-Houston.net",
    "wof:name":"NotTrash",
    "wof:placetype":"venue"
},
  "geometry": {"coordinates":[-95.526128,29.735996],"type":"Point"}
}