{
  "type": "Feature",
  "properties": {
    "iso:country":"US",
    "sg:address":"2010 Gilmer Rd Suite 107",
    "sg:city":"Longview",
    "sg:classifiers":[
        {
            "category":"Social Services",
            "type":"Services"
        },
        {
            "category":"Health Services",
            "subcategory":"Doctor",
            "type":"Services"
        },
        {
            "category":"Sports & Exercise",
            "subcategory":"Gym",
            "type":"Entertainment"
        },
        {
            "category":"Health Services",
            "subcategory":"Health Practitioner",
            "type":"Services"
        },
        {
            "category":"Community Center",
            "subcategory":"Social",
            "type":"Public Place"
        }
    ],
    "sg:phone":"+1 903 295 3100",
    "sg:postcode":"75604",
    "sg:province":"TX",
    "sg:tags":[
        "information",
        "stress",
        "management",
        "individual",
        "family",
        "smoker",
        "psychologist",
        "therapist",
        "marriage",
        "treatment",
        "child",
        "counselor",
        "prevention",
        "hypnotist"
    ],
    "sg:website":"http://www.jerebpsychology.com",
    "wof:name":"Jereb, Ronald J",
    "wof:placetype":"venue"
},
  "geometry": {"coordinates":[-94.784181,32.525619],"type":"Point"}
}