{
  "type": "Feature",
  "properties": {
    "iso:country":"US",
    "sg:address":"8830 Long Point Rd",
    "sg:city":"Houston",
    "sg:classifiers":[
        {
            "category":"Health Services",
            "subcategory":"Clinic",
            "type":"Services"
        },
        {
            "category":"Health Services",
            "subcategory":"Medical Lab",
            "type":"Services"
        }
    ],
    "sg:phone":"+1 713 467 2351",
    "sg:postcode":"77055",
    "sg:province":"TX",
    "sg:tags":[
        "detection",
        "equipment",
        "drug"
    ],
    "wof:name":"Med Tech Inc",
    "wof:placetype":"venue"
},
  "geometry": {"coordinates":[-95.507012,29.803122],"type":"Point"}
}