{
  "type": "Feature",
  "properties": {
    "iso:country":"US",
    "sg:address":"6450 Fm 1960 Rd W",
    "sg:city":"Houston",
    "sg:classifiers":[
        {
            "category":"Food & Beverages",
            "subcategory":"Liquor & Beverages",
            "type":"Retail Goods"
        },
        {
            "category":"Wholesale",
            "subcategory":"Wine & Distilled Alcoholic Beverages",
            "type":"Manufacturing & Wholesale Goods"
        }
    ],
    "sg:phone":"+1 281 397 0057",
    "sg:postcode":"77069",
    "sg:province":"TX",
    "sg:tags":[
        "liquors-wholesale",
        "store"
    ],
    "wof:name":"International Spirits Wholesal",
    "wof:placetype":"venue"
},
  "geometry": {"coordinates":[-95.52670000000001,29.972287],"type":"Point"}
}