{
  "type": "Feature",
  "properties": {
    "iso:country":"US",
    "sg:address":"5215 N O Connor Blvd",
    "sg:city":"Irving",
    "sg:classifiers":[
        {
            "category":"Wholesale",
            "subcategory":"Durable Goods & Equipment",
            "type":"Manufacturing & Wholesale Goods"
        }
    ],
    "sg:phone":"+1 972 556 1155",
    "sg:postcode":"75039",
    "sg:province":"TX",
    "sg:tags":[
        "professional"
    ],
    "sg:website":"www.oceusa.com",
    "wof:name":"Oce North America",
    "wof:placetype":"venue"
},
  "geometry": {"coordinates":[-96.939939,32.869855],"type":"Point"}
}