{
  "type": "Feature",
  "properties": {
    "iso:country":"US",
    "sg:address":"6400 Mc Neil Dr",
    "sg:city":"Austin",
    "sg:classifiers":[
        {
            "category":"Insurance",
            "subcategory":"Insurance Agent",
            "type":"Services"
        }
    ],
    "sg:phone":"+1 512 335 6196",
    "sg:postcode":"78729",
    "sg:province":"TX",
    "wof:name":"Maulding & Mauling",
    "wof:placetype":"venue"
},
  "geometry": {"coordinates":[-97.75289100000001,30.439894],"type":"Point"}
}