{
  "type": "Feature",
  "properties": {
    "iso:country":"US",
    "sg:address":"6212 Avery Island Ave",
    "sg:city":"Austin",
    "sg:classifiers":[
        {
            "category":"Professional",
            "subcategory":"Engineering",
            "type":"Services"
        }
    ],
    "sg:phone":"+1 512 828 0606",
    "sg:postcode":"78727",
    "sg:province":"TX",
    "sg:tags":[
        "consulting",
        "business"
    ],
    "wof:name":"Forshey Consulting Service",
    "wof:placetype":"venue"
},
  "geometry": {"coordinates":[-97.749278,30.437603],"type":"Point"}
}