{
  "type": "Feature",
  "properties": {
    "iso:country":"US",
    "sg:address":"1151 W Parker Rd",
    "sg:city":"Plano",
    "sg:classifiers":[
        {
            "category":"Retail",
            "subcategory":"Animal Services",
            "type":"Services"
        }
    ],
    "sg:phone":"+1 972 398 6008",
    "sg:postcode":"75023",
    "sg:province":"TX",
    "wof:name":"Waggin Tail Dycre & Boardng",
    "wof:placetype":"venue"
},
  "geometry": {"coordinates":[-96.717088,33.041154],"type":"Point"}
}