{
  "type": "Feature",
  "properties": {
    "iso:country":"US",
    "sg:address":"3201 S Belt Line Rd",
    "sg:city":"Mesquite",
    "sg:classifiers":[
        {
            "category":"Building & Trades",
            "subcategory":"Construction",
            "type":"Services"
        }
    ],
    "sg:phone":"+1 972 222 1209",
    "sg:postcode":"75181",
    "sg:province":"TX",
    "sg:tags":[
        "repairing",
        "remodeling",
        "contractor"
    ],
    "wof:name":"Monarch Mastercrafts",
    "wof:placetype":"venue"
},
  "geometry": {"coordinates":[-96.599024,32.723867],"type":"Point"}
}