{
  "type": "Feature",
  "properties": {
    "iso:country":"US",
    "sg:address":"11606 Cliveden Dr",
    "sg:city":"Houston",
    "sg:classifiers":[
        {
            "category":"Shopping",
            "subcategory":"Gifts & Souvenirs",
            "type":"Retail Goods"
        }
    ],
    "sg:phone":"+1 281 537 5089",
    "sg:postcode":"77066",
    "sg:province":"TX",
    "wof:name":"Entre Amis",
    "wof:placetype":"venue"
},
  "geometry": {"coordinates":[-95.482671,29.952762],"type":"Point"}
}