{
  "type": "Feature",
  "properties": {
    "iso:country":"US",
    "sg:address":"2923 Lavell Ave",
    "sg:city":"Wichita Falls",
    "sg:classifiers":[
        {
            "category":"Building & Trades",
            "subcategory":"Landscaping Services",
            "type":"Services"
        }
    ],
    "sg:phone":"+1 940 691 1695",
    "sg:postcode":"76308",
    "sg:province":"TX",
    "sg:tags":[
        "tree"
    ],
    "wof:name":"Dino's Professional Tree Svc",
    "wof:placetype":"venue"
},
  "geometry": {"coordinates":[-98.54179499999999,33.859975],"type":"Point"}
}