{
  "type": "Feature",
  "properties": {
    "iso:country":"US",
    "sg:address":"1115 N Velasco St",
    "sg:city":"Angleton",
    "sg:classifiers":[
        {
            "category":"Personal",
            "subcategory":"Beauty Salon",
            "type":"Services"
        }
    ],
    "sg:phone":"+1 979 849 3225",
    "sg:postcode":"77515",
    "sg:province":"TX",
    "wof:name":"Cuts & More",
    "wof:placetype":"venue"
},
  "geometry": {"coordinates":[-95.43283599999999,29.179971],"type":"Point"}
}