{
  "type": "Feature",
  "properties": {
    "iso:country":"US",
    "sg:address":"500 W 6th St",
    "sg:city":"Irving",
    "sg:classifiers":[
        {
            "category":"Restaurant",
            "type":"Food & Drink"
        }
    ],
    "sg:phone":"+1 972 596 1279",
    "sg:postcode":"75060",
    "sg:province":"TX",
    "sg:tags":[
        "eating"
    ],
    "wof:name":"Vermex & Assoc Building Cafe",
    "wof:placetype":"venue"
},
  "geometry": {"coordinates":[-96.95349,32.808606],"type":"Point"}
}