{
  "type": "Feature",
  "properties": {
    "iso:country":"US",
    "sg:address":"1233 N Orange St",
    "sg:city":"Giddings",
    "sg:classifiers":[
        {
            "category":"Manufacturing",
            "subcategory":"Tools & Machinery",
            "type":"Manufacturing & Wholesale Goods"
        }
    ],
    "sg:phone":"+1 979 542 3654",
    "sg:postcode":"78942",
    "sg:province":"TX",
    "sg:website":"www.aiptfe.com",
    "wof:name":"American Industrial Polymers",
    "wof:placetype":"venue"
},
  "geometry": {"coordinates":[-96.923716,30.192078],"type":"Point"}
}