{
  "type": "Feature",
  "properties": {
    "iso:country":"US",
    "sg:address":"5314B Ponciana Dr",
    "sg:city":"Austin",
    "sg:classifiers":[
        {
            "category":"Arts & Performance",
            "subcategory":"Art Gallery",
            "type":"Entertainment"
        }
    ],
    "sg:phone":"+1 512 326 2662",
    "sg:postcode":"78744",
    "sg:province":"TX",
    "sg:tags":[
        "consultant",
        "galleries"
    ],
    "wof:name":"Toddities",
    "wof:placetype":"venue"
},
  "geometry": {"coordinates":[-97.75481000000001,30.199298],"type":"Point"}
}