{
  "type": "Feature",
  "properties": {
    "iso:country":"US",
    "sg:address":"10709 Memorial Dr",
    "sg:city":"Houston",
    "sg:classifiers":[
        {
            "category":"Recreation",
            "type":"Entertainment"
        },
        {
            "category":"Organizations",
            "subcategory":"Community Association",
            "type":"Services"
        }
    ],
    "sg:phone":"+1 713 464 4811",
    "sg:postcode":"77024",
    "sg:province":"TX",
    "sg:tags":[
        "club",
        "membership",
        "physical",
        "fitness"
    ],
    "sg:website":"www.houstonracquetclub.com",
    "wof:name":"Houston Racquet Club Inc",
    "wof:placetype":"venue"
},
  "geometry": {"coordinates":[-95.50110599999999,29.765424],"type":"Point"}
}