{
  "type": "Feature",
  "properties": {
    "iso:country":"US",
    "sg:address":"8805 S Hwy 183",
    "sg:city":"Austin",
    "sg:classifiers":[
        {
            "category":"Building & Trades",
            "subcategory":"Electrical",
            "type":"Services"
        }
    ],
    "sg:phone":"+1 512 656 3609",
    "sg:postcode":"78747",
    "sg:province":"TX",
    "sg:tags":[
        "electrical",
        "contractor"
    ],
    "wof:name":"AM PM Electrical Service Inc",
    "wof:placetype":"venue"
},
  "geometry": {"coordinates":[-97.69572100000001,30.126758],"type":"Point"}
}