{
  "type": "Feature",
  "properties": {
    "iso:country":"US",
    "sg:address":"140 Diaz St",
    "sg:city":"San Benito",
    "sg:classifiers":[
        {
            "category":"Organizations",
            "subcategory":"Religious Organization",
            "type":"Services"
        }
    ],
    "sg:phone":"+1 956 399 3595",
    "sg:postcode":"78586",
    "sg:province":"TX",
    "sg:tags":[
        "church"
    ],
    "wof:name":"Iglesia Presbiteriana",
    "wof:placetype":"venue"
},
  "geometry": {"coordinates":[-97.637229,26.134206],"type":"Point"}
}