{
  "type": "Feature",
  "properties": {
    "iso:country":"US",
    "sg:address":"Austin Visitor Center 209 E 6th St",
    "sg:city":"Austin",
    "sg:classifiers":[
        {
            "category":"Landmark",
            "subcategory":"Tourist Information",
            "type":"Public Place"
        }
    ],
    "sg:phone":"+1 512 659 9478",
    "sg:postcode":"78701",
    "sg:province":"TX",
    "sg:tags":[
        "tour"
    ],
    "sg:website":"austinovertures.com",
    "wof:name":"Austin Overtures Sightseeing",
    "wof:placetype":"venue"
},
  "geometry": {"coordinates":[-97.74109799999999,30.267479],"type":"Point"}
}