{
  "type": "Feature",
  "properties": {
    "iso:country":"US",
    "sg:address":"200 S Shoreline Blvd",
    "sg:city":"Corpus Christi",
    "sg:classifiers":[
        {
            "category":"Retail",
            "subcategory":"Repair Shop",
            "type":"Services"
        }
    ],
    "sg:phone":"+1 361 883 8080",
    "sg:postcode":"78401",
    "sg:province":"TX",
    "sg:tags":[
        "engine",
        "marine"
    ],
    "wof:name":"Gulf Stream Marine",
    "wof:placetype":"venue"
},
  "geometry": {"coordinates":[-97.394194,27.788961],"type":"Point"}
}