{
  "type": "Feature",
  "properties": {
    "iso:country":"US",
    "sg:address":"9230 Cedar Pt",
    "sg:city":"Helotes",
    "sg:classifiers":[
        {
            "category":"Wholesale",
            "subcategory":"Vending Machines",
            "type":"Manufacturing & Wholesale Goods"
        }
    ],
    "sg:phone":"+1 210 372 9917",
    "sg:postcode":"78023",
    "sg:province":"TX",
    "sg:tags":[
        "operator"
    ],
    "wof:name":"Alonzo & Assoc",
    "wof:placetype":"venue"
},
  "geometry": {"coordinates":[-98.66494,29.562878],"type":"Point"}
}