{
  "type": "Feature",
  "properties": {
    "iso:country":"US",
    "sg:address":"807 Sugar Creek Blvd",
    "sg:city":"Sugar Land",
    "sg:classifiers":[
        {
            "category":"Building & Trades",
            "subcategory":"Pest Control",
            "type":"Services"
        }
    ],
    "sg:phone":"+1 281 313 3200",
    "sg:postcode":"77478",
    "sg:province":"TX",
    "wof:name":"Adtech Termite & Pest Control",
    "wof:placetype":"venue"
},
  "geometry": {"coordinates":[-95.59583600000001,29.615623],"type":"Point"}
}