{
  "type": "Feature",
  "properties": {
    "iso:country":"US",
    "sg:address":"600 Wisteria",
    "sg:city":"La Marque",
    "sg:classifiers":[
        {
            "category":"Education",
            "subcategory":"School",
            "type":"Public Place"
        }
    ],
    "sg:phone":"+1 409 935 8043",
    "sg:postcode":"77568",
    "sg:province":"TX",
    "wof:name":"Inter-City Elementary School",
    "wof:placetype":"venue"
},
  "geometry": {"coordinates":[-94.96197600000001,29.377999],"type":"Point"}
}