{
  "type": "Feature",
  "properties": {
    "iso:country":"US",
    "sg:address":"167 Oak Hill Dr",
    "sg:city":"Beeville",
    "sg:classifiers":[
        {
            "category":"Professional",
            "subcategory":"Detective & Security Services",
            "type":"Services"
        }
    ],
    "sg:phone":"+1 361 358 4003",
    "sg:postcode":"78102",
    "sg:province":"TX",
    "sg:tags":[
        "information",
        "bureau"
    ],
    "wof:name":"Geological Services Inc",
    "wof:placetype":"venue"
},
  "geometry": {"coordinates":[-97.76446,28.448893],"type":"Point"}
}