{
  "type": "Feature",
  "properties": {
    "iso:country":"US",
    "sg:address":"1100 S Pecan St",
    "sg:city":"Kountze",
    "sg:classifiers":[
        {
            "category":"Professional",
            "subcategory":"Lawyer & Legal Services",
            "type":"Services"
        }
    ],
    "sg:phone":"+1 409 246 2770",
    "sg:postcode":"77625",
    "sg:province":"TX",
    "sg:tags":[
        "plan"
    ],
    "sg:website":"http://www.ibwlawoffice.com",
    "wof:name":"Lindsey B. Whisenhant",
    "wof:placetype":"venue"
},
  "geometry": {"coordinates":[-94.315963,30.367115],"type":"Point"}
}