{
  "type": "Feature",
  "properties": {
    "iso:country":"US",
    "sg:address":"5640 Montana Ave",
    "sg:city":"El Paso",
    "sg:classifiers":[
        {
            "category":"Ice Cream",
            "type":"Food & Drink"
        }
    ],
    "sg:menulink":"http://www.allmenus.com/tx/el-paso/242745-baskin-robbins/menu/",
    "sg:phone":"+1 915 772 4905",
    "sg:postcode":"79925",
    "sg:province":"TX",
    "sg:tags":[
        "american"
    ],
    "wof:name":"Baskin-Robbins",
    "wof:placetype":"venue"
},
  "geometry": {"coordinates":[-106.42073499999999,31.782923],"type":"Point"}
}