{
  "type": "Feature",
  "properties": {
    "iso:country":"US",
    "sg:address":"19408 Park Row",
    "sg:city":"Houston",
    "sg:classifiers":[
        {
            "category":"Manufacturing",
            "subcategory":"Tools & Machinery",
            "type":"Manufacturing & Wholesale Goods"
        }
    ],
    "sg:phone":"+1 281 398 7890",
    "sg:postcode":"77084",
    "sg:province":"TX",
    "sg:tags":[
        "equipment",
        "electronic",
        "mfg"
    ],
    "wof:name":"Solartron Inc",
    "wof:placetype":"venue"
},
  "geometry": {"coordinates":[-95.71102,29.791476],"type":"Point"}
}