{
  "type": "Feature",
  "properties": {
    "iso:country":"US",
    "sg:address":"752 N Harvey Mitchell Pkwy",
    "sg:city":"Bryan",
    "sg:classifiers":[
        {
            "category":"Retail",
            "subcategory":"Laundry & Dry Cleaning",
            "type":"Services"
        }
    ],
    "sg:phone":"+1 979 696 0101",
    "sg:postcode":"77807",
    "sg:province":"TX",
    "sg:tags":[
        "cleaners",
        "rug",
        "carpet"
    ],
    "wof:name":"Steamatic Of Brazos Valley",
    "wof:placetype":"venue"
},
  "geometry": {"coordinates":[-96.381366,30.638694],"type":"Point"}
}