{
  "type": "Feature",
  "properties": {
    "iso:country":"US",
    "sg:address":"113 E Crawford St",
    "sg:city":"Palestine",
    "sg:classifiers":[
        {
            "category":"Professional",
            "subcategory":"Business Services",
            "type":"Services"
        }
    ],
    "sg:phone":"+1 903 729 5252",
    "sg:postcode":"75801",
    "sg:province":"TX",
    "wof:name":"Dial A Prayer",
    "wof:placetype":"venue"
},
  "geometry": {"coordinates":[-95.63053499999999,31.763505],"type":"Point"}
}