{
  "type": "Feature",
  "properties": {
    "iso:country":"US",
    "sg:address":"1701 E Lamar Blvd",
    "sg:city":"Arlington",
    "sg:classifiers":[
        {
            "category":"Real Estate",
            "subcategory":"Developer",
            "type":"Services"
        }
    ],
    "sg:phone":"+1 817 461 3550",
    "sg:postcode":"76006",
    "sg:province":"TX",
    "sg:tags":[
        "project",
        "consultant",
        "energy",
        "electrical",
        "power"
    ],
    "wof:name":"Tenaska Inc",
    "wof:placetype":"venue"
},
  "geometry": {"coordinates":[-97.085303,32.763576],"type":"Point"}
}