{
  "type": "Feature",
  "properties": {
    "iso:country":"US",
    "sg:address":"8407 Sterling St",
    "sg:city":"Irving",
    "sg:classifiers":[
        {
            "category":"Home & Garden",
            "subcategory":"Carpets & Floor Coverings",
            "type":"Retail Goods"
        }
    ],
    "sg:phone":"+1 972 929 1934",
    "sg:postcode":"75063",
    "sg:province":"TX",
    "sg:tags":[
        "dealer",
        "rug"
    ],
    "wof:name":"Shaw Industries Inc",
    "wof:placetype":"venue"
},
  "geometry": {"coordinates":[-97.01317400000001,32.922149],"type":"Point"}
}