{
  "type": "Feature",
  "properties": {
    "iso:country":"US",
    "sg:address":"6652 Canyon Dr",
    "sg:city":"Amarillo",
    "sg:classifiers":[
        {
            "category":"Home & Garden",
            "subcategory":"Garden Supply",
            "type":"Retail Goods"
        }
    ],
    "sg:phone":"+1 806 350 7808",
    "sg:postcode":"79109",
    "sg:province":"TX",
    "sg:tags":[
        "lawn"
    ],
    "wof:name":"Primera Landscape Supply",
    "wof:placetype":"venue"
},
  "geometry": {"coordinates":[-101.89654299999999,35.135987],"type":"Point"}
}