{
  "type": "Feature",
  "properties": {
    "iso:country":"US",
    "sg:address":"4695 State Hwy 121",
    "sg:city":"Lewisville",
    "sg:classifiers":[
        {
            "category":"Food & Beverages",
            "subcategory":"Liquor & Beverages",
            "type":"Retail Goods"
        }
    ],
    "sg:phone":"+1 972 625 9252",
    "sg:postcode":"75056",
    "sg:province":"TX",
    "sg:tags":[
        "alcoholic"
    ],
    "wof:name":"Articbeer & Wine",
    "wof:placetype":"venue"
},
  "geometry": {"coordinates":[-96.876878,33.07183],"type":"Point"}
}