{
  "type": "Feature",
  "properties": {
    "iso:country":"US",
    "sg:address":"7706 Rohrdanz",
    "sg:city":"San Antonio",
    "sg:classifiers":[
        {
            "category":"Professional",
            "type":"Services"
        }
    ],
    "sg:phone":"+1 210 654 6654",
    "sg:postcode":"78233",
    "sg:province":"TX",
    "wof:name":"Bail Out Bond Svcs",
    "wof:placetype":"venue"
},
  "geometry": {"coordinates":[-98.335887,29.560728],"type":"Point"}
}