{
  "type": "Feature",
  "properties": {
    "iso:country":"US",
    "sg:address":"5823 US Hwy 287",
    "sg:city":"Alvord",
    "sg:classifiers":[
        {
            "category":"Wholesale",
            "subcategory":"Furniture",
            "type":"Manufacturing & Wholesale Goods"
        }
    ],
    "sg:phone":"+1 940 427 2310",
    "sg:postcode":"76225",
    "sg:province":"TX",
    "wof:name":"Lizzy's Western Designs",
    "wof:placetype":"venue"
},
  "geometry": {"coordinates":[-97.676874,33.338718],"type":"Point"}
}