{
  "type": "Feature",
  "properties": {
    "iso:country":"US",
    "sg:address":"565 W Oaks",
    "sg:city":"Garland",
    "sg:classifiers":[
        {
            "category":"Professional",
            "subcategory":"Business Services",
            "type":"Services"
        }
    ],
    "sg:phone":"+1 972 276 5663",
    "sg:postcode":"75040",
    "sg:province":"TX",
    "sg:tags":[
        "delivery",
        "courier"
    ],
    "wof:name":"Greyhound Bus Lines",
    "wof:placetype":"venue"
},
  "geometry": {"coordinates":[-96.62159699999999,32.9207],"type":"Point"}
}