{
  "type": "Feature",
  "properties": {
    "iso:country":"US",
    "sg:address":"7060 State Hwy 123",
    "sg:city":"Seguin",
    "sg:classifiers":[
        {
            "category":"Retail",
            "subcategory":"Auto Repair",
            "type":"Services"
        }
    ],
    "sg:phone":"+1 830 372 2100",
    "sg:postcode":"78155",
    "sg:province":"TX",
    "sg:tags":[
        "repairing",
        "automobile"
    ],
    "wof:name":"Vehicle Medics",
    "wof:placetype":"venue"
},
  "geometry": {"coordinates":[-97.964382,29.702386],"type":"Point"}
}