{
  "type": "Feature",
  "properties": {
    "iso:country":"US",
    "sg:address":"PO Box 66447",
    "sg:city":"Houston",
    "sg:classifiers":[
        {
            "category":"Arts & Performance",
            "subcategory":"Art Gallery",
            "type":"Entertainment"
        }
    ],
    "sg:phone":"+1 832 200 3108",
    "sg:postcode":"77266",
    "sg:province":"TX",
    "wof:name":"John Palmer Art",
    "wof:placetype":"venue"
},
  "geometry": {"coordinates":[-95.393799,29.747299],"type":"Point"}
}