{
  "type": "Feature",
  "properties": {
    "iso:country":"US",
    "sg:address":"2103 Robert E Lee Dr",
    "sg:city":"Killeen",
    "sg:classifiers":[
        {
            "category":"Professional",
            "subcategory":"Business Services",
            "type":"Services"
        }
    ],
    "sg:phone":"+1 254 526 4289",
    "sg:postcode":"76543",
    "sg:province":"TX",
    "wof:name":"Bradford Entertainment Co",
    "wof:placetype":"venue"
},
  "geometry": {"coordinates":[-97.70458600000001,31.132014],"type":"Point"}
}