{
  "type": "Feature",
  "properties": {
    "iso:country":"US",
    "sg:address":"6722 Calm Lake Dr",
    "sg:city":"San Antonio",
    "sg:classifiers":[
        {
            "category":"Government",
            "subcategory":"Office",
            "type":"Public Place"
        }
    ],
    "sg:phone":"+1 210 659 5857",
    "sg:postcode":"78244",
    "sg:province":"TX",
    "sg:tags":[
        "state",
        "program",
        "health"
    ],
    "wof:name":"Center For Health Care Svc",
    "wof:placetype":"venue"
},
  "geometry": {"coordinates":[-98.356386,29.471789],"type":"Point"}
}