{
  "type": "Feature",
  "properties": {
    "iso:country":"US",
    "sg:address":"2015 Richey St",
    "sg:city":"Pasadena",
    "sg:classifiers":[
        {
            "category":"Shopping",
            "subcategory":"Used Merchandise",
            "type":"Retail Goods"
        }
    ],
    "sg:phone":"+1 713 473 9478",
    "sg:postcode":"77502",
    "sg:province":"TX",
    "sg:tags":[
        "resale",
        "shop"
    ],
    "wof:name":"Bridge Resale Shop",
    "wof:placetype":"venue"
},
  "geometry": {"coordinates":[-95.225279,29.683026],"type":"Point"}
}