{
  "type": "Feature",
  "properties": {
    "iso:country":"US",
    "sg:address":"8989 Monroe Rd",
    "sg:city":"Houston",
    "sg:classifiers":[
        {
            "category":"Wholesale",
            "subcategory":"Motor Vehicles",
            "type":"Manufacturing & Wholesale Goods"
        }
    ],
    "sg:phone":"+1 713 943 2288",
    "sg:postcode":"77061",
    "sg:province":"TX",
    "wof:name":"Moto Laverda USA Inc",
    "wof:placetype":"venue"
},
  "geometry": {"coordinates":[-95.264691,29.638944],"type":"Point"}
}