{
  "type": "Feature",
  "properties": {
    "iso:country":"US",
    "sg:address":"2303 S Gordon St",
    "sg:city":"Alvin",
    "sg:classifiers":[
        {
            "category":"Autos & Motor Vehicles",
            "subcategory":"Auto Supplies",
            "type":"Retail Goods"
        }
    ],
    "sg:phone":"+1 281 756 9576",
    "sg:postcode":"77511",
    "sg:province":"TX",
    "wof:name":"Sharp Racing Performance",
    "wof:placetype":"venue"
},
  "geometry": {"coordinates":[-95.244693,29.404118],"type":"Point"}
}