{
  "type": "Feature",
  "properties": {
    "iso:country":"US",
    "sg:address":"930 E Campbell Rd",
    "sg:city":"Richardson",
    "sg:classifiers":[
        {
            "category":"Professional",
            "subcategory":"Computer Services",
            "type":"Services"
        }
    ],
    "sg:phone":"+1 972 231 6101",
    "sg:postcode":"75081",
    "sg:province":"TX",
    "sg:tags":[
        "repair"
    ],
    "wof:name":"Hewlett-Packard Company",
    "wof:placetype":"venue"
},
  "geometry": {"coordinates":[-96.70909899999999,32.975201],"type":"Point"}
}