{
  "type": "Feature",
  "properties": {
    "iso:country":"US",
    "sg:address":"419 Dalton Dr",
    "sg:city":"Desoto",
    "sg:classifiers":[
        {
            "category":"Building & Trades",
            "subcategory":"Construction",
            "type":"Services"
        }
    ],
    "sg:phone":"+1 972 846 3333",
    "sg:postcode":"75115",
    "sg:province":"TX",
    "sg:tags":[
        "contractor"
    ],
    "wof:name":"Hamlin Construction",
    "wof:placetype":"venue"
},
  "geometry": {"coordinates":[-96.864777,32.60087],"type":"Point"}
}