{
  "type": "Feature",
  "properties": {
    "iso:country":"US",
    "sg:address":"8414 Ave X",
    "sg:city":"Lubbock",
    "sg:classifiers":[
        {
            "category":"Organizations",
            "subcategory":"Religious Organization",
            "type":"Services"
        }
    ],
    "sg:phone":"+1 806 745 8831",
    "sg:postcode":"79423",
    "sg:province":"TX",
    "wof:name":"His Way In Ministries Inc",
    "wof:placetype":"venue"
},
  "geometry": {"coordinates":[-101.867741,33.518225],"type":"Point"}
}