{
  "type": "Feature",
  "properties": {
    "iso:country":"US",
    "sg:address":"502 S Garland Ave",
    "sg:city":"Garland",
    "sg:classifiers":[
        {
            "category":"Autos & Motor Vehicles",
            "subcategory":"Auto Supplies",
            "type":"Retail Goods"
        }
    ],
    "sg:phone":"+1 972 205 0701",
    "sg:postcode":"75040",
    "sg:province":"TX",
    "wof:name":"T & C Tires & Wheels",
    "wof:placetype":"venue"
},
  "geometry": {"coordinates":[-96.64824400000001,32.907554],"type":"Point"}
}