{
  "type": "Feature",
  "properties": {
    "iso:country":"US",
    "sg:address":"335 Centre St",
    "sg:city":"Dallas",
    "sg:classifiers":[
        {
            "category":"Banks & Credit Unions",
            "subcategory":"Bank",
            "type":"Services"
        }
    ],
    "sg:phone":"+1 214 943 9990",
    "sg:postcode":"75208",
    "sg:province":"TX",
    "wof:name":"Appraisal Bank",
    "wof:placetype":"venue"
},
  "geometry": {"coordinates":[-96.82776200000001,32.742351],"type":"Point"}
}