{
  "type": "Feature",
  "properties": {
    "iso:country":"US",
    "sg:address":"2303 Pam St",
    "sg:city":"Longview",
    "sg:classifiers":[
        {
            "category":"Retail",
            "subcategory":"Repair Shop",
            "type":"Services"
        }
    ],
    "sg:phone":"+1 903 236 0954",
    "sg:postcode":"75602",
    "sg:province":"TX",
    "sg:tags":[
        "residential",
        "cleaning"
    ],
    "wof:name":"R&B Cleaning Co",
    "wof:placetype":"venue"
},
  "geometry": {"coordinates":[-94.71867,32.463733],"type":"Point"}
}