{
  "type": "Feature",
  "properties": {
    "iso:country":"US",
    "sg:address":"11127 Cedar Elm Dr",
    "sg:city":"San Antonio",
    "sg:classifiers":[
        {
            "category":"Professional",
            "subcategory":"Management & Consulting",
            "type":"Services"
        }
    ],
    "sg:phone":"+1 210 415 6700",
    "sg:postcode":"78230",
    "sg:province":"TX",
    "sg:tags":[
        "consultant",
        "business"
    ],
    "wof:name":"Dale Dorsey Management",
    "wof:placetype":"venue"
},
  "geometry": {"coordinates":[-98.531043,29.542881],"type":"Point"}
}