{
  "type": "Feature",
  "properties": {
    "iso:country":"US",
    "sg:address":"1508 7th St",
    "sg:city":"League City",
    "sg:classifiers":[
        {
            "category":"Wholesale",
            "subcategory":"Construction Materials",
            "type":"Manufacturing & Wholesale Goods"
        }
    ],
    "sg:phone":"+1 281 480 1440",
    "sg:postcode":"77573",
    "sg:province":"TX",
    "sg:tags":[
        "repair",
        "skylight",
        "architectural",
        "system"
    ],
    "wof:name":"Mc Laughlin Erectors Inc",
    "wof:placetype":"venue"
},
  "geometry": {"coordinates":[-95.090564,29.520992],"type":"Point"}
}