{
  "type": "Feature",
  "properties": {
    "iso:country":"US",
    "sg:address":"10809 Garland Rd",
    "sg:city":"Dallas",
    "sg:classifiers":[
        {
            "category":"Health Services",
            "subcategory":"Clinic",
            "type":"Services"
        }
    ],
    "sg:phone":"+1 972 289 0040",
    "sg:postcode":"75218",
    "sg:province":"TX",
    "sg:tags":[
        "welfare"
    ],
    "wof:name":"A Medical House Calls",
    "wof:placetype":"venue"
},
  "geometry": {"coordinates":[-96.688475,32.845022],"type":"Point"}
}