{
  "type": "Feature",
  "properties": {
    "iso:country":"US",
    "sg:address":"15914 Ridgeroe Ln",
    "sg:city":"Houston",
    "sg:classifiers":[
        {
            "category":"Education",
            "subcategory":"Special Training",
            "type":"Public Place"
        }
    ],
    "sg:phone":"+1 281 438 2757",
    "sg:postcode":"77053",
    "sg:province":"TX",
    "sg:tags":[
        "school",
        "educational"
    ],
    "wof:name":"Superior Tutors",
    "wof:placetype":"venue"
},
  "geometry": {"coordinates":[-95.45452299999999,29.591743],"type":"Point"}
}