{
  "type": "Feature",
  "properties": {
    "iso:country":"US",
    "sg:address":"8484 Hosston Vivian Rd",
    "sg:city":"Vivian",
    "sg:classifiers":[
        {
            "category":"Mining & Drilling",
            "type":"Manufacturing & Wholesale Goods"
        }
    ],
    "sg:phone":"+1 318 375 2662",
    "sg:postcode":"71082",
    "sg:province":"TX",
    "sg:tags":[
        "oil",
        "gas",
        "producer"
    ],
    "wof:name":"Southern Oil & Gas",
    "wof:placetype":"venue"
},
  "geometry": {"coordinates":[-93.948376,32.866659],"type":"Point"}
}