{
  "type": "Feature",
  "properties": {
    "iso:country":"US",
    "sg:address":"1604 Meadowview Dr",
    "sg:city":"Port Lavaca",
    "sg:classifiers":[
        {
            "category":"Retail",
            "subcategory":"Auto Repair",
            "type":"Services"
        }
    ],
    "sg:phone":"+1 361 552 4227",
    "sg:postcode":"77979",
    "sg:province":"TX",
    "sg:tags":[
        "automobile",
        "top",
        "upholstery"
    ],
    "wof:name":"Dennis Auto Trim",
    "wof:placetype":"venue"
},
  "geometry": {"coordinates":[-96.63791500000001,28.605527],"type":"Point"}
}