{
  "type": "Feature",
  "properties": {
    "iso:country":"US",
    "sg:address":"3802 Balcones Dr",
    "sg:city":"Austin",
    "sg:classifiers":[
        {
            "category":"Professional",
            "subcategory":"Business Services",
            "type":"Services"
        }
    ],
    "sg:phone":"+1 512 451 6877",
    "sg:postcode":"78731",
    "sg:province":"TX",
    "sg:tags":[
        "interior",
        "consultant",
        "design",
        "decorator"
    ],
    "wof:name":"Susan Lubin Interior Design",
    "wof:placetype":"venue"
},
  "geometry": {"coordinates":[-97.767934,30.319989],"type":"Point"}
}