{
  "type": "Feature",
  "properties": {
    "iso:country":"US",
    "sg:address":"1330 River Bend Dr",
    "sg:city":"Dallas",
    "sg:classifiers":[
        {
            "category":"Professional",
            "subcategory":"Detective & Security Services",
            "type":"Services"
        }
    ],
    "sg:phone":"+1 972 241 9992",
    "sg:postcode":"75247",
    "sg:province":"TX",
    "sg:tags":[
        "system"
    ],
    "wof:name":"Entergy Security",
    "wof:placetype":"venue"
},
  "geometry": {"coordinates":[-96.861976,32.817604],"type":"Point"}
}