{
  "type": "Feature",
  "properties": {
    "iso:country":"US",
    "sg:address":"1300 E Arapaho Rd",
    "sg:city":"Richardson",
    "sg:classifiers":[
        {
            "category":"Real Estate",
            "subcategory":"Architect",
            "type":"Services"
        }
    ],
    "sg:phone":"+1 972 644 8830",
    "sg:postcode":"75081",
    "sg:province":"TX",
    "wof:name":"Nelson & Assoc",
    "wof:placetype":"venue"
},
  "geometry": {"coordinates":[-96.701776,32.960583],"type":"Point"}
}