{
  "type": "Feature",
  "properties": {
    "iso:country":"US",
    "sg:address":"3410 Castle Pond Ct",
    "sg:city":"Pearland",
    "sg:classifiers":[
        {
            "category":"Banks & Credit Unions",
            "subcategory":"Financial Services",
            "type":"Services"
        }
    ],
    "sg:phone":"+1 281 997 0868",
    "sg:postcode":"77584",
    "sg:province":"TX",
    "sg:tags":[
        "investor"
    ],
    "wof:name":"Anderson JD Investments LLC",
    "wof:placetype":"venue"
},
  "geometry": {"coordinates":[-95.35350099999999,29.545171],"type":"Point"}
}