{
  "type": "Feature",
  "properties": {
    "iso:country":"US",
    "sg:address":"8201 Cypresswood Dr Suite 102",
    "sg:city":"Spring",
    "sg:classifiers":[
        {
            "category":"Insurance",
            "subcategory":"Hazard Insurance",
            "type":"Services"
        },
        {
            "category":"Insurance",
            "subcategory":"Insurance Agent",
            "type":"Services"
        },
        {
            "category":"Insurance",
            "subcategory":"Life Insurance",
            "type":"Services"
        },
        {
            "category":"Insurance",
            "subcategory":"Title Insurance",
            "type":"Services"
        }
    ],
    "sg:phone":"+1 281 655 9958",
    "sg:postcode":"77379",
    "sg:province":"TX",
    "sg:tags":[
        "auto",
        "homeowner"
    ],
    "sg:website":"http://www.nationwide.com/agent/Spring-TEXAS-insurance-agent/gary-pollard/office.html",
    "wof:name":"Gary Pollard Agy Grp Inc - Nationwide Insurance",
    "wof:placetype":"venue"
},
  "geometry": {"coordinates":[-95.531176,30.002346],"type":"Point"}
}