{
  "type": "Feature",
  "properties": {
    "iso:country":"US",
    "sg:address":"2334 Gulf Terminal Dr",
    "sg:city":"Houston",
    "sg:classifiers":[
        {
            "category":"Freight",
            "type":"Transportation"
        }
    ],
    "sg:phone":"+1 713 928 2228",
    "sg:postcode":"77023",
    "sg:province":"TX",
    "sg:tags":[
        "trucking"
    ],
    "wof:name":"ACI Motor Freight",
    "wof:placetype":"venue"
},
  "geometry": {"coordinates":[-95.32347799999999,29.716984],"type":"Point"}
}