{
  "type": "Feature",
  "properties": {
    "iso:country":"US",
    "sg:address":"913 Sycamore Dr",
    "sg:city":"Garland",
    "sg:classifiers":[
        {
            "category":"Professional",
            "subcategory":"Art Services",
            "type":"Services"
        }
    ],
    "sg:phone":"+1 972 271 4725",
    "sg:postcode":"75041",
    "sg:province":"TX",
    "sg:tags":[
        "graphic",
        "designer"
    ],
    "wof:name":"Bazzell Graphics",
    "wof:placetype":"venue"
},
  "geometry": {"coordinates":[-96.64336400000001,32.888024],"type":"Point"}
}