{
  "type": "Feature",
  "properties": {
    "iso:country":"US",
    "sg:address":"16700 Ledgestone Dr",
    "sg:city":"San Antonio",
    "sg:classifiers":[
        {
            "category":"Professional",
            "subcategory":"Business Services",
            "type":"Services"
        }
    ],
    "sg:phone":"+1 210 496 1831",
    "sg:postcode":"78232",
    "sg:province":"TX",
    "wof:name":"Leroy V Janda",
    "wof:placetype":"venue"
},
  "geometry": {"coordinates":[-98.462711,29.59274],"type":"Point"}
}