{
  "type": "Feature",
  "properties": {
    "iso:country":"US",
    "sg:address":"2111 Cross Creek Ct",
    "sg:city":"Arlington",
    "sg:classifiers":[
        {
            "category":"Professional",
            "subcategory":"Management & Consulting",
            "type":"Services"
        }
    ],
    "sg:phone":"+1 817 467 4240",
    "sg:postcode":"76017",
    "sg:province":"TX",
    "sg:tags":[
        "business"
    ],
    "wof:name":"Robert C Dorn Family Ltd",
    "wof:placetype":"venue"
},
  "geometry": {"coordinates":[-97.14308699999999,32.667817],"type":"Point"}
}