{
  "type": "Feature",
  "properties": {
    "iso:country":"US",
    "sg:address":"100 Horizon Blvd",
    "sg:city":"El Paso",
    "sg:classifiers":[
        {
            "category":"Restaurant",
            "type":"Food & Drink"
        }
    ],
    "sg:menulink":"http://www.allmenus.com/tx/el-paso-east/157136-whataburger/menu/",
    "sg:phone":"+1 915 858 2993",
    "sg:postcode":"79927",
    "sg:province":"TX",
    "sg:tags":[
        "burger",
        "american"
    ],
    "wof:name":"Whataburger",
    "wof:placetype":"venue"
},
  "geometry": {"coordinates":[-106.28596,31.649634],"type":"Point"}
}