{
  "type": "Feature",
  "properties": {
    "iso:country":"US",
    "sg:address":"7028 Wabash Cir",
    "sg:city":"Dallas",
    "sg:classifiers":[
        {
            "category":"Professional",
            "subcategory":"Advertising",
            "type":"Services"
        }
    ],
    "sg:phone":"+1 214 328 8774",
    "sg:postcode":"75214",
    "sg:province":"TX",
    "sg:tags":[
        "agency"
    ],
    "wof:name":"Hansen Ross",
    "wof:placetype":"venue"
},
  "geometry": {"coordinates":[-96.73757999999999,32.824803],"type":"Point"}
}