{
  "type": "Feature",
  "properties": {
    "iso:country":"US",
    "sg:address":"322 Aldine Mail Rd",
    "sg:city":"Houston",
    "sg:classifiers":[
        {
            "category":"Organizations",
            "subcategory":"Religious Organization",
            "type":"Services"
        }
    ],
    "sg:phone":"+1 281 447 7212",
    "sg:postcode":"77037",
    "sg:province":"TX",
    "sg:tags":[
        "church"
    ],
    "wof:name":"International Pentecostal Chr",
    "wof:placetype":"venue"
},
  "geometry": {"coordinates":[-95.397306,29.902556],"type":"Point"}
}