{
  "type": "Feature",
  "properties": {
    "iso:country":"US",
    "sg:address":"3270 Ivy Ln",
    "sg:city":"Nederland",
    "sg:classifiers":[
        {
            "category":"Professional",
            "type":"Services"
        }
    ],
    "sg:phone":"+1 409 962 6419",
    "sg:postcode":"77627",
    "sg:province":"TX",
    "wof:name":"Orbit International",
    "wof:placetype":"venue"
},
  "geometry": {"coordinates":[-94.031046,29.977156],"type":"Point"}
}