{
  "type": "Feature",
  "properties": {
    "iso:country":"US",
    "sg:address":"1140 Business Center Dr Ste 403",
    "sg:city":"Houston",
    "sg:classifiers":[
        {
            "category":"Health Services",
            "subcategory":"Doctor",
            "type":"Services"
        }
    ],
    "sg:phone":"+1 713 935 9758",
    "sg:postcode":"77043",
    "sg:province":"TX",
    "wof:name":"Sabbagh Amer MD",
    "wof:placetype":"venue"
},
  "geometry": {"coordinates":[-95.568044,29.78958],"type":"Point"}
}