{
  "type": "Feature",
  "properties": {
    "iso:country":"US",
    "sg:address":"230 Hummingbird Ln",
    "sg:city":"Wimberley",
    "sg:classifiers":[
        {
            "category":"Building & Trades",
            "subcategory":"Construction",
            "type":"Services"
        }
    ],
    "sg:phone":"+1 512 847 7816",
    "sg:postcode":"78676",
    "sg:province":"TX",
    "sg:tags":[
        "altering",
        "remodeling",
        "contractor"
    ],
    "wof:name":"Tom Miller Home Builder & Remodeling",
    "wof:placetype":"venue"
},
  "geometry": {"coordinates":[-98.220287,30.029081],"type":"Point"}
}