{
  "type": "Feature",
  "properties": {
    "iso:country":"US",
    "sg:address":"137 North St",
    "sg:city":"New Boston",
    "sg:classifiers":[
        {
            "category":"Restaurant",
            "type":"Food & Drink"
        }
    ],
    "sg:phone":"+1 903 628 9312",
    "sg:postcode":"75570",
    "sg:province":"TX",
    "sg:tags":[
        "eating"
    ],
    "wof:name":"China Cafe",
    "wof:placetype":"venue"
},
  "geometry": {"coordinates":[-94.417531,33.462248],"type":"Point"}
}