{
  "type": "Feature",
  "properties": {
    "iso:country":"US",
    "sg:address":"2612 US Hwy 80 E",
    "sg:city":"Mesquite",
    "sg:classifiers":[
        {
            "category":"Autos & Motor Vehicles",
            "subcategory":"Automobile Sales",
            "type":"Retail Goods"
        }
    ],
    "sg:phone":"+1 972 285 3775",
    "sg:postcode":"75149",
    "sg:province":"TX",
    "sg:tags":[
        "car",
        "dealer"
    ],
    "wof:name":"Affordable Wholesale Autos",
    "wof:placetype":"venue"
},
  "geometry": {"coordinates":[-96.63697999999999,32.791953],"type":"Point"}
}