{
  "type": "Feature",
  "properties": {
    "iso:country":"US",
    "sg:address":"11261 Gulf Fwy",
    "sg:city":"Houston",
    "sg:classifiers":[
        {
            "category":"Home & Garden",
            "subcategory":"Furniture",
            "type":"Retail Goods"
        }
    ],
    "sg:phone":"+1 713 943 3366",
    "sg:postcode":"77034",
    "sg:province":"TX",
    "wof:name":"Mattress Firm",
    "wof:placetype":"venue"
},
  "geometry": {"coordinates":[-95.205957,29.606846],"type":"Point"}
}