{
  "type": "Feature",
  "properties": {
    "iso:country":"US",
    "sg:address":"1502 E Red River St",
    "sg:city":"Victoria",
    "sg:classifiers":[
        {
            "category":"Professional",
            "subcategory":"Advertising",
            "type":"Services"
        }
    ],
    "sg:phone":"+1 361 575 9553",
    "sg:postcode":"77901",
    "sg:province":"TX",
    "sg:tags":[
        "mailing",
        "shipping"
    ],
    "wof:name":"Red River Postal Station",
    "wof:placetype":"venue"
},
  "geometry": {"coordinates":[-96.987313,28.814022],"type":"Point"}
}