{
  "type": "Feature",
  "properties": {
    "iso:country":"US",
    "sg:address":"700 W Spring Creek Pkwy",
    "sg:city":"Plano",
    "sg:classifiers":[
        {
            "category":"Shopping",
            "subcategory":"Gifts & Souvenirs",
            "type":"Retail Goods"
        }
    ],
    "sg:phone":"+1 972 633 2619",
    "sg:postcode":"75023",
    "sg:province":"TX",
    "wof:name":"Mail & Gift",
    "wof:placetype":"venue"
},
  "geometry": {"coordinates":[-96.70702199999999,33.056935],"type":"Point"}
}