{
  "type": "Feature",
  "properties": {
    "iso:country":"US",
    "sg:address":"844 Central Blvd",
    "sg:city":"Brownsville",
    "sg:classifiers":[
        {
            "category":"Social Services",
            "type":"Services"
        }
    ],
    "sg:phone":"+1 956 544 1512",
    "sg:postcode":"78520",
    "sg:province":"TX",
    "sg:tags":[
        "information",
        "center",
        "diabetes"
    ],
    "wof:name":"Center For Diabetes Management",
    "wof:placetype":"venue"
},
  "geometry": {"coordinates":[-97.51217,25.91903],"type":"Point"}
}