{
  "type": "Feature",
  "properties": {
    "iso:country":"US",
    "sg:address":"6701 Concord Park Dr",
    "sg:city":"Houston",
    "sg:classifiers":[
        {
            "category":"Wholesale",
            "subcategory":"Stationery",
            "type":"Manufacturing & Wholesale Goods"
        }
    ],
    "sg:phone":"+1 713 329 9400",
    "sg:postcode":"77040",
    "sg:province":"TX",
    "sg:tags":[
        "business",
        "system",
        "form",
        "supply"
    ],
    "sg:website":"http://www.gabp.com",
    "wof:name":"Great American Business Products",
    "wof:placetype":"venue"
},
  "geometry": {"coordinates":[-95.546837,29.86669],"type":"Point"}
}