{
  "type": "Feature",
  "properties": {
    "iso:country":"US",
    "sg:address":"1201 Antoine Dr",
    "sg:city":"Houston",
    "sg:classifiers":[
        {
            "category":"Professional",
            "subcategory":"Lawyer & Legal Services",
            "type":"Services"
        }
    ],
    "sg:phone":"+1 713 957 0151",
    "sg:postcode":"77055",
    "sg:province":"TX",
    "wof:name":"Carl C Roy",
    "wof:placetype":"venue"
},
  "geometry": {"coordinates":[-95.475589,29.790647],"type":"Point"}
}