{
  "type": "Feature",
  "properties": {
    "iso:country":"US",
    "sg:address":"701 Garland Ave",
    "sg:city":"Waco",
    "sg:classifiers":[
        {
            "category":"Building & Trades",
            "subcategory":"Cleaning & Sanitation",
            "type":"Services"
        }
    ],
    "sg:phone":"+1 254 759 0390",
    "sg:postcode":"76707",
    "sg:province":"TX",
    "sg:tags":[
        "janitor"
    ],
    "wof:name":"General Cleaning Simovich",
    "wof:placetype":"venue"
},
  "geometry": {"coordinates":[-97.148696,31.564777],"type":"Point"}
}