{
  "type": "Feature",
  "properties": {
    "iso:country":"US",
    "sg:address":"6390 Lyndon B Johnson Fwy",
    "sg:city":"Dallas",
    "sg:classifiers":[
        {
            "category":"Professional",
            "type":"Services"
        }
    ],
    "sg:phone":"+1 972 788 0286",
    "sg:postcode":"75240",
    "sg:province":"TX",
    "sg:tags":[
        "establishment"
    ],
    "wof:name":"Moseley Production Co",
    "wof:placetype":"venue"
},
  "geometry": {"coordinates":[-96.79460400000001,32.92441],"type":"Point"}
}