{
  "type": "Feature",
  "properties": {
    "iso:country":"US",
    "sg:address":"3000 Richmond Ave",
    "sg:city":"Houston",
    "sg:classifiers":[
        {
            "category":"Organizations",
            "subcategory":"Non-profit Organization",
            "type":"Services"
        }
    ],
    "sg:phone":"+1 713 523 7326",
    "sg:postcode":"77098",
    "sg:province":"TX",
    "wof:name":"I Have A Dream-Houston",
    "wof:placetype":"venue"
},
  "geometry": {"coordinates":[-95.423783,29.73411],"type":"Point"}
}