{
  "type": "Feature",
  "properties": {
    "iso:country":"US",
    "sg:address":"12946 Dairy Ashford Rd",
    "sg:city":"Sugar Land",
    "sg:classifiers":[
        {
            "category":"Professional",
            "subcategory":"Management & Consulting",
            "type":"Services"
        }
    ],
    "sg:phone":"+1 281 565 4242",
    "sg:postcode":"77478",
    "sg:province":"TX",
    "sg:tags":[
        "public",
        "relations"
    ],
    "wof:name":"Meximize Inc",
    "wof:placetype":"venue"
},
  "geometry": {"coordinates":[-95.59789000000001,29.631218],"type":"Point"}
}