{
  "type": "Feature",
  "properties": {
    "iso:country":"US",
    "sg:address":"417 Arrowhead Trce",
    "sg:city":"Grand Prairie",
    "sg:classifiers":[
        {
            "category":"Organizations",
            "subcategory":"Community Association",
            "type":"Services"
        }
    ],
    "sg:phone":"+1 972 262 0235",
    "sg:postcode":"75051",
    "sg:province":"TX",
    "wof:name":"American Veterans of Worl",
    "wof:placetype":"venue"
},
  "geometry": {"coordinates":[-97.012288,32.739998],"type":"Point"}
}