{
  "type": "Feature",
  "properties": {
    "iso:country":"US",
    "sg:address":"737 Buddy L Dr",
    "sg:city":"Fort Worth",
    "sg:classifiers":[
        {
            "category":"Professional",
            "subcategory":"Business Services",
            "type":"Services"
        }
    ],
    "sg:phone":"+1 817 367 6000",
    "sg:postcode":"76108",
    "sg:province":"TX",
    "wof:name":"Hayden Group Inc",
    "wof:placetype":"venue"
},
  "geometry": {"coordinates":[-97.51771100000001,32.752897],"type":"Point"}
}