{
  "type": "Feature",
  "properties": {
    "iso:country":"US",
    "sg:address":"2405 Sanguinet St",
    "sg:city":"Fort Worth",
    "sg:classifiers":[
        {
            "category":"Building & Trades",
            "subcategory":"Cleaning & Sanitation",
            "type":"Services"
        }
    ],
    "sg:phone":"+1 817 737 6337",
    "sg:postcode":"76107",
    "sg:province":"TX",
    "sg:tags":[
        "maintenance"
    ],
    "wof:name":"Brighter Days Window Cleaning",
    "wof:placetype":"venue"
},
  "geometry": {"coordinates":[-97.391261,32.735812],"type":"Point"}
}