{
  "type": "Feature",
  "properties": {
    "iso:country":"US",
    "sg:address":"411 W 7th St",
    "sg:city":"Fort Worth",
    "sg:classifiers":[
        {
            "category":"Wholesale",
            "subcategory":"Auto Parts",
            "type":"Manufacturing & Wholesale Goods"
        }
    ],
    "sg:phone":"+1 817 339 1480",
    "sg:postcode":"76102",
    "sg:province":"TX",
    "sg:tags":[
        "tire"
    ],
    "wof:name":"B F Goodrich",
    "wof:placetype":"venue"
},
  "geometry": {"coordinates":[-97.33290599999999,32.751132],"type":"Point"}
}