{
  "type": "Feature",
  "properties": {
    "iso:country":"US",
    "sg:address":"4676 Beech St",
    "sg:city":"Bellaire",
    "sg:classifiers":[
        {
            "category":"Sports & Exercise",
            "subcategory":"Gym",
            "type":"Entertainment"
        }
    ],
    "sg:phone":"+1 713 667 7072",
    "sg:postcode":"77401",
    "sg:province":"TX",
    "sg:tags":[
        "fitness",
        "physical",
        "facility"
    ],
    "wof:name":"T R K Fitness",
    "wof:placetype":"venue"
},
  "geometry": {"coordinates":[-95.45933100000001,29.710816],"type":"Point"}
}