{
  "type": "Feature",
  "properties": {
    "iso:country":"US",
    "sg:address":"1306 Tony St",
    "sg:city":"White Oak",
    "sg:classifiers":[
        {
            "category":"Building & Trades",
            "subcategory":"Construction",
            "type":"Services"
        }
    ],
    "sg:phone":"+1 903 291 0062",
    "sg:postcode":"75693",
    "sg:province":"TX",
    "sg:tags":[
        "steel",
        "fabrication",
        "welding"
    ],
    "wof:name":"Lifetime Steel Framed Home",
    "wof:placetype":"venue"
},
  "geometry": {"coordinates":[-94.860146,32.5524],"type":"Point"}
}