{
  "type": "Feature",
  "properties": {
    "iso:country":"US",
    "sg:address":"1805 Burr Oak St",
    "sg:city":"Arlington",
    "sg:classifiers":[
        {
            "category":"Education",
            "subcategory":"Special Training",
            "type":"Public Place"
        }
    ],
    "sg:phone":"+1 817 459 2100",
    "sg:postcode":"76012",
    "sg:province":"TX",
    "sg:tags":[
        "program"
    ],
    "wof:name":"Accountability Plus",
    "wof:placetype":"venue"
},
  "geometry": {"coordinates":[-97.144364,32.764337],"type":"Point"}
}