{
  "type": "Feature",
  "properties": {
    "iso:country":"US",
    "sg:address":"419 S Main St",
    "sg:city":"Del Rio",
    "sg:classifiers":[
        {
            "category":"Retail",
            "subcategory":"Portrait Studio",
            "type":"Services"
        }
    ],
    "sg:phone":"+1 830 775 2724",
    "sg:postcode":"78840",
    "sg:province":"TX",
    "sg:tags":[
        "photo",
        "photography",
        "camera",
        "finishing"
    ],
    "wof:name":"Warren Studio & Photography",
    "wof:placetype":"venue"
},
  "geometry": {"coordinates":[-100.89963400000001,29.360985],"type":"Point"}
}