{
  "type": "Feature",
  "properties": {
    "iso:country":"US",
    "sg:address":"1702 Texas Ave S",
    "sg:city":"Bryan",
    "sg:classifiers":[
        {
            "category":"Health Services",
            "subcategory":"Clinic",
            "type":"Services"
        }
    ],
    "sg:phone":"+1 979 822 1870",
    "sg:postcode":"77802",
    "sg:province":"TX",
    "sg:tags":[
        "specialty",
        "outpatient"
    ],
    "wof:name":"Bvcaa Family Health Services",
    "wof:placetype":"venue"
},
  "geometry": {"coordinates":[-96.363991,30.653289],"type":"Point"}
}