{
  "type": "Feature",
  "properties": {
    "iso:country":"US",
    "sg:address":"158 N Texas Ave",
    "sg:city":"Mercedes",
    "sg:classifiers":[
        {
            "category":"Social Services",
            "subcategory":"Adult Care",
            "type":"Services"
        }
    ],
    "sg:phone":"+1 956 514 5503",
    "sg:postcode":"78570",
    "sg:province":"TX",
    "sg:tags":[
        "residential"
    ],
    "wof:name":"Santa Cruz Daycare For Adults",
    "wof:placetype":"venue"
},
  "geometry": {"coordinates":[-97.913566,26.15177],"type":"Point"}
}