{
  "type": "Feature",
  "properties": {
    "iso:country":"US",
    "sg:address":"3517 Mattye Maye Dr",
    "sg:city":"Pasadena",
    "sg:classifiers":[
        {
            "category":"Freight",
            "type":"Transportation"
        }
    ],
    "sg:phone":"+1 713 475 0574",
    "sg:postcode":"77503",
    "sg:province":"TX",
    "sg:tags":[
        "operator",
        "trucking"
    ],
    "wof:name":"Mc Murray Trucking",
    "wof:placetype":"venue"
},
  "geometry": {"coordinates":[-95.158361,29.692512],"type":"Point"}
}