{
  "type": "Feature",
  "properties": {
    "iso:country":"US",
    "sg:address":"5458 FM 1960 W",
    "sg:city":"Houston",
    "sg:classifiers":[
        {
            "category":"Shopping",
            "subcategory":"Clothing, Apparel, & Fashions",
            "type":"Retail Goods"
        }
    ],
    "sg:phone":"+1 281 587 1612",
    "sg:postcode":"77069",
    "sg:province":"TX",
    "sg:tags":[
        "lingerie"
    ],
    "wof:name":"Victorias Secret",
    "wof:placetype":"venue"
},
  "geometry": {"coordinates":[-95.50832200000001,29.982246],"type":"Point"}
}