{
  "type": "Feature",
  "properties": {
    "iso:country":"US",
    "sg:address":"8247 San Fernando Way",
    "sg:city":"Dallas",
    "sg:classifiers":[
        {
            "category":"Manufacturing",
            "subcategory":"Toys & Sporting Goods",
            "type":"Manufacturing & Wholesale Goods"
        }
    ],
    "sg:phone":"+1 214 324 5656",
    "sg:postcode":"75218",
    "sg:province":"TX",
    "sg:tags":[
        "mfg"
    ],
    "wof:name":"Cayuga Trains",
    "wof:placetype":"venue"
},
  "geometry": {"coordinates":[-96.71951900000001,32.814716],"type":"Point"}
}