{
  "type": "Feature",
  "properties": {
    "iso:country":"US",
    "sg:address":"4503 Live Oak St",
    "sg:city":"Dallas",
    "sg:classifiers":[
        {
            "category":"Restaurant",
            "type":"Food & Drink"
        }
    ],
    "sg:phone":"+1 214 827 5990",
    "sg:postcode":"75204",
    "sg:province":"TX",
    "wof:name":"Huge American Restuarant Inc",
    "wof:placetype":"venue"
},
  "geometry": {"coordinates":[-96.77619900000001,32.799702],"type":"Point"}
}