{
  "type": "Feature",
  "properties": {
    "iso:country":"US",
    "sg:address":"13616 Dandelion Trl",
    "sg:city":"Belton",
    "sg:classifiers":[
        {
            "category":"Insurance",
            "subcategory":"Hazard Insurance",
            "type":"Services"
        }
    ],
    "sg:phone":"+1 254 780 9812",
    "sg:postcode":"76513",
    "sg:province":"TX",
    "wof:name":"James L Kent",
    "wof:placetype":"venue"
},
  "geometry": {"coordinates":[-97.49257,31.124767],"type":"Point"}
}