{
  "type": "Feature",
  "properties": {
    "iso:country":"US",
    "sg:address":"409 3rd St",
    "sg:city":"Graham",
    "sg:classifiers":[
        {
            "category":"Shopping",
            "type":"Retail Goods"
        }
    ],
    "sg:phone":"+1 940 549 9449",
    "sg:postcode":"76450",
    "sg:province":"TX",
    "sg:tags":[
        "pet",
        "food",
        "supply"
    ],
    "wof:name":"Paws 2 Claws",
    "wof:placetype":"venue"
},
  "geometry": {"coordinates":[-98.59281799999999,33.105992],"type":"Point"}
}