{
  "type": "Feature",
  "properties": {
    "iso:country":"US",
    "sg:address":"324 Rolling Hills Dr",
    "sg:city":"Midlothian",
    "sg:classifiers":[
        {
            "category":"Real Estate",
            "subcategory":"Real Estate Agent",
            "type":"Services"
        }
    ],
    "sg:phone":"+1 972 723 2193",
    "sg:postcode":"76065",
    "sg:province":"TX",
    "wof:name":"Burnitt Realty & Appraisal",
    "wof:placetype":"venue"
},
  "geometry": {"coordinates":[-96.9965,32.501145],"type":"Point"}
}