{
  "type": "Feature",
  "properties": {
    "iso:country":"US",
    "sg:address":"3520 Fairmont Pkwy",
    "sg:city":"Pasadena",
    "sg:classifiers":[
        {
            "category":"Retail",
            "subcategory":"Repair Shop",
            "type":"Services"
        }
    ],
    "sg:phone":"+1 281 998 0122",
    "sg:postcode":"77504",
    "sg:province":"TX",
    "sg:tags":[
        "electrical"
    ],
    "wof:name":"Larrys TV Service Inc",
    "wof:placetype":"venue"
},
  "geometry": {"coordinates":[-95.184045,29.650726],"type":"Point"}
}