{
  "type": "Feature",
  "properties": {
    "iso:country":"US",
    "sg:address":"16222 Clay Rd",
    "sg:city":"Houston",
    "sg:classifiers":[
        {
            "category":"Real Estate",
            "subcategory":"Real Estate Operator",
            "type":"Services"
        }
    ],
    "sg:phone":"+1 281 463 7777",
    "sg:postcode":"77084",
    "sg:province":"TX",
    "sg:tags":[
        "building",
        "apartment"
    ],
    "sg:website":"http://www.viningsart.com",
    "wof:name":"Clay Creek Apartments",
    "wof:placetype":"venue"
},
  "geometry": {"coordinates":[-95.648758,29.836069],"type":"Point"}
}