{
  "type": "Feature",
  "properties": {
    "iso:country":"US",
    "sg:address":"2800 Regal Rd",
    "sg:city":"Plano",
    "sg:classifiers":[
        {
            "category":"Mining & Drilling",
            "type":"Manufacturing & Wholesale Goods"
        }
    ],
    "sg:phone":"+1 972 985 6091",
    "sg:postcode":"75075",
    "sg:province":"TX",
    "sg:tags":[
        "crude",
        "production",
        "gas"
    ],
    "wof:name":"Chestnut Petroleum Inc",
    "wof:placetype":"venue"
},
  "geometry": {"coordinates":[-96.74779599999999,33.021656],"type":"Point"}
}