{
  "type": "Feature",
  "properties": {
    "iso:country":"US",
    "sg:address":"701 N Elm St",
    "sg:city":"Palestine",
    "sg:classifiers":[
        {
            "category":"Professional",
            "subcategory":"Lawyer & Legal Services",
            "type":"Services"
        }
    ],
    "sg:phone":"+1 903 729 8011",
    "sg:postcode":"75801",
    "sg:province":"TX",
    "wof:name":"Cargill",
    "wof:placetype":"venue"
},
  "geometry": {"coordinates":[-95.62833000000001,31.766782],"type":"Point"}
}