{
  "type": "Feature",
  "properties": {
    "iso:country":"US",
    "sg:address":"1908 Massouh St",
    "sg:city":"Victoria",
    "sg:classifiers":[
        {
            "category":"Building & Trades",
            "subcategory":"Construction",
            "type":"Services"
        }
    ],
    "sg:phone":"+1 361 570 3531",
    "sg:postcode":"77901",
    "sg:province":"TX",
    "sg:tags":[
        "contractor"
    ],
    "wof:name":"G Ang G Roofing",
    "wof:placetype":"venue"
},
  "geometry": {"coordinates":[-96.953283,28.802646],"type":"Point"}
}