{
  "type": "Feature",
  "properties": {
    "iso:country":"US",
    "sg:address":"3505 Summerhill Rd",
    "sg:city":"Texarkana",
    "sg:classifiers":[
        {
            "category":"Shopping",
            "type":"Retail Goods"
        }
    ],
    "sg:phone":"+1 903 793 7101",
    "sg:postcode":"75503",
    "sg:province":"TX",
    "sg:tags":[
        "merchandise"
    ],
    "wof:name":"Mid Texas Communication Co",
    "wof:placetype":"venue"
},
  "geometry": {"coordinates":[-94.06515400000001,33.452825],"type":"Point"}
}