{
  "type": "Feature",
  "properties": {
    "iso:country":"US",
    "sg:address":"704 S Texas Blvd",
    "sg:city":"Weslaco",
    "sg:classifiers":[
        {
            "category":"Health Services",
            "subcategory":"Doctor",
            "type":"Services"
        }
    ],
    "sg:phone":"+1 956 968 7200",
    "sg:postcode":"78596",
    "sg:province":"TX",
    "sg:tags":[
        "dentist"
    ],
    "wof:name":"Valley Orthodontics Ctr",
    "wof:placetype":"venue"
},
  "geometry": {"coordinates":[-97.990645,26.15352],"type":"Point"}
}