{
  "type": "Feature",
  "properties": {
    "iso:country":"US",
    "sg:address":"1319 Austin Ave",
    "sg:city":"Waco",
    "sg:classifiers":[
        {
            "category":"Personal",
            "subcategory":"Beauty Salon",
            "type":"Services"
        }
    ],
    "sg:phone":"+1 254 752 3767",
    "sg:postcode":"76701",
    "sg:province":"TX",
    "sg:tags":[
        "shop"
    ],
    "wof:name":"Techniques Salon",
    "wof:placetype":"venue"
},
  "geometry": {"coordinates":[-97.139938,31.549779],"type":"Point"}
}