{
  "type": "Feature",
  "properties": {
    "iso:country":"US",
    "sg:address":"10112 Co Rd 6010",
    "sg:city":"Munday",
    "sg:classifiers":[
        {
            "category":"Manufacturing",
            "subcategory":"Signs",
            "type":"Manufacturing & Wholesale Goods"
        }
    ],
    "sg:phone":"+1 940 422 5488",
    "sg:postcode":"76371",
    "sg:province":"TX",
    "wof:name":"Sign On",
    "wof:placetype":"venue"
},
  "geometry": {"coordinates":[-99.65441300000001,33.529863],"type":"Point"}
}