{
  "type": "Feature",
  "properties": {
    "iso:country":"US",
    "sg:address":"125 Siebert Hill Ln",
    "sg:city":"Sherman",
    "sg:classifiers":[
        {
            "category":"Building & Trades",
            "subcategory":"Construction",
            "type":"Services"
        }
    ],
    "sg:phone":"+1 903 564 3753",
    "sg:postcode":"75092",
    "sg:province":"TX",
    "sg:tags":[
        "excavating",
        "contractor"
    ],
    "wof:name":"Crow Backhoe Svc",
    "wof:placetype":"venue"
},
  "geometry": {"coordinates":[-96.824386,33.678281],"type":"Point"}
}