{
  "type": "Feature",
  "properties": {
    "iso:country":"US",
    "sg:address":"1423 FM 812",
    "sg:city":"Cedar Creek",
    "sg:classifiers":[
        {
            "category":"Building & Trades",
            "subcategory":"Equipment Rental",
            "type":"Services"
        }
    ],
    "sg:phone":"+1 512 303 1369",
    "sg:postcode":"78612",
    "sg:province":"TX",
    "wof:name":"Longhorn Trailer Rentals",
    "wof:placetype":"venue"
},
  "geometry": {"coordinates":[-97.53646500000001,30.019868],"type":"Point"}
}