{
  "type": "Feature",
  "properties": {
    "iso:country":"US",
    "sg:address":"1017 Cedarland Blvd",
    "sg:city":"Arlington",
    "sg:classifiers":[
        {
            "category":"Real Estate",
            "subcategory":"Real Estate Agent",
            "type":"Services"
        }
    ],
    "sg:phone":"+1 817 275 5102",
    "sg:postcode":"76011",
    "sg:province":"TX",
    "wof:name":"Jeha Nine Inc",
    "wof:placetype":"venue"
},
  "geometry": {"coordinates":[-97.095641,32.752184],"type":"Point"}
}