{
  "type": "Feature",
  "properties": {
    "iso:country":"US",
    "sg:address":"425 Atkinson Dr",
    "sg:city":"Lufkin",
    "sg:classifiers":[
        {
            "category":"Food & Beverages",
            "subcategory":"Groceries & Convenience Stores",
            "type":"Retail Goods"
        }
    ],
    "sg:phone":"+1 936 634 5001",
    "sg:postcode":"75901",
    "sg:province":"TX",
    "wof:name":"P & C Grocery Store",
    "wof:placetype":"venue"
},
  "geometry": {"coordinates":[-94.721709,31.345472],"type":"Point"}
}