{
  "type": "Feature",
  "properties": {
    "iso:country":"US",
    "sg:address":"645 W FM 495",
    "sg:city":"Pharr",
    "sg:classifiers":[
        {
            "category":"Retail",
            "subcategory":"Auto Repair",
            "type":"Services"
        }
    ],
    "sg:phone":"+1 956 781 2787",
    "sg:postcode":"78577",
    "sg:province":"TX",
    "sg:tags":[
        "general"
    ],
    "wof:name":"Sepulvedas Auto Service",
    "wof:placetype":"venue"
},
  "geometry": {"coordinates":[-98.190861,26.212822],"type":"Point"}
}