{
  "type": "Feature",
  "properties": {
    "iso:country":"US",
    "sg:address":"204 N 31st St",
    "sg:city":"Nederland",
    "sg:classifiers":[
        {
            "category":"Real Estate",
            "subcategory":"Real Estate Agent",
            "type":"Services"
        }
    ],
    "sg:phone":"+1 409 466 1611",
    "sg:postcode":"77627",
    "sg:province":"TX",
    "wof:name":"Keith Calfee",
    "wof:placetype":"venue"
},
  "geometry": {"coordinates":[-94.003147,29.961852],"type":"Point"}
}