{
  "type": "Feature",
  "properties": {
    "iso:country":"US",
    "sg:address":"1410 E Sandy Lake Rd",
    "sg:city":"Coppell",
    "sg:classifiers":[
        {
            "category":"Health Services",
            "subcategory":"Health Practitioner",
            "type":"Services"
        }
    ],
    "sg:phone":"+1 972 304 4444",
    "sg:postcode":"75019",
    "sg:province":"TX",
    "sg:tags":[
        "therapy",
        "physical"
    ],
    "sg:website":"www.sandylakerehab.com",
    "wof:name":"Sandy Lake Rehabilitation and Care Center",
    "wof:placetype":"venue"
},
  "geometry": {"coordinates":[-96.950143,32.966918],"type":"Point"}
}