{
  "type": "Feature",
  "properties": {
    "iso:country":"US",
    "sg:address":"9802 State Hwy 171",
    "sg:city":"Itasca",
    "sg:classifiers":[
        {
            "category":"Food & Beverages",
            "subcategory":"Groceries & Convenience Stores",
            "type":"Retail Goods"
        }
    ],
    "sg:phone":"+1 254 687 2832",
    "sg:postcode":"76050",
    "sg:province":"TX",
    "sg:tags":[
        "station"
    ],
    "wof:name":"Cordells Grocery & Service Stn",
    "wof:placetype":"venue"
},
  "geometry": {"coordinates":[-97.273151,32.231932],"type":"Point"}
}