{
  "type": "Feature",
  "properties": {
    "iso:country":"US",
    "sg:address":"3313 Garden Brook Dr",
    "sg:city":"Dallas",
    "sg:classifiers":[
        {
            "category":"Education",
            "subcategory":"Music School",
            "type":"Public Place"
        }
    ],
    "sg:phone":"+1 972 488 5397",
    "sg:postcode":"75234",
    "sg:province":"TX",
    "sg:tags":[
        "instrument",
        "teacher",
        "musical"
    ],
    "sg:website":"www.pianogallery.com",
    "wof:name":"Piano Gallery",
    "wof:placetype":"venue"
},
  "geometry": {"coordinates":[-96.865438,32.950384],"type":"Point"}
}