{
  "type": "Feature",
  "properties": {
    "iso:country":"US",
    "sg:address":"2015 Cedar Bend Dr",
    "sg:city":"Austin",
    "sg:classifiers":[
        {
            "category":"Real Estate",
            "subcategory":"Real Estate Operator",
            "type":"Services"
        }
    ],
    "sg:phone":"+1 512 834 7755",
    "sg:postcode":"78758",
    "sg:province":"TX",
    "sg:tags":[
        "apartment"
    ],
    "wof:name":"Champion's Crossing Apartments",
    "wof:placetype":"venue"
},
  "geometry": {"coordinates":[-97.69986400000001,30.410307],"type":"Point"}
}