{
  "type": "Feature",
  "properties": {
    "iso:country":"US",
    "sg:address":"6530 W Little York Rd",
    "sg:city":"Houston",
    "sg:classifiers":[
        {
            "category":"Government",
            "subcategory":"Fire Station",
            "type":"Public Place"
        }
    ],
    "sg:phone":"+1 713 222 7643",
    "sg:postcode":"77040",
    "sg:province":"TX",
    "sg:tags":[
        "protection"
    ],
    "wof:name":"Fire Dept-Station 4",
    "wof:placetype":"venue"
},
  "geometry": {"coordinates":[-95.49047400000001,29.8658],"type":"Point"}
}