{
  "type": "Feature",
  "properties": {
    "iso:country":"US",
    "sg:address":"2635 Beltway 8",
    "sg:city":"Pasadena",
    "sg:classifiers":[
        {
            "category":"Manufacturing",
            "subcategory":"Motor Vehicles & Parts",
            "type":"Manufacturing & Wholesale Goods"
        }
    ],
    "sg:phone":"+1 281 991 4601",
    "sg:postcode":"77503",
    "sg:province":"TX",
    "sg:tags":[
        "shaft",
        "drive"
    ],
    "wof:name":"Drive Line Svc Co Of Texas",
    "wof:placetype":"venue"
},
  "geometry": {"coordinates":[-95.155585,29.673111],"type":"Point"}
}