{
  "type": "Feature",
  "properties": {
    "iso:country":"US",
    "sg:address":"20306 Aspenwilde Dr",
    "sg:city":"Cypress",
    "sg:classifiers":[
        {
            "category":"Professional",
            "type":"Services"
        }
    ],
    "sg:phone":"+1 281 304 1104",
    "sg:postcode":"77433",
    "sg:province":"TX",
    "wof:name":"Great West Retirement Services",
    "wof:placetype":"venue"
},
  "geometry": {"coordinates":[-95.733965,29.999044],"type":"Point"}
}