{
  "type": "Feature",
  "properties": {
    "iso:country":"US",
    "sg:address":"123 Parland Pl",
    "sg:city":"San Antonio",
    "sg:classifiers":[
        {
            "category":"Social Services",
            "subcategory":"Adult Care",
            "type":"Services"
        }
    ],
    "sg:phone":"+1 210 828 1460",
    "sg:postcode":"78209",
    "sg:province":"TX",
    "sg:tags":[
        "residential"
    ],
    "wof:name":"Francis Keith Residential Care",
    "wof:placetype":"venue"
},
  "geometry": {"coordinates":[-98.467394,29.458468],"type":"Point"}
}