{
  "type": "Feature",
  "properties": {
    "iso:country":"US",
    "sg:address":"1108 Santa Fe Dr",
    "sg:city":"Weatherford",
    "sg:classifiers":[
        {
            "category":"Professional",
            "subcategory":"Business Services",
            "type":"Services"
        }
    ],
    "sg:phone":"+1 817 596 0078",
    "sg:postcode":"76086",
    "sg:province":"TX",
    "sg:tags":[
        "appraisers-business",
        "industrial",
        "commercial",
        "appraiser"
    ],
    "wof:name":"Parker County Apraisal District",
    "wof:placetype":"venue"
},
  "geometry": {"coordinates":[-97.782228,32.746815],"type":"Point"}
}