{
  "type": "Feature",
  "properties": {
    "iso:country":"US",
    "sg:address":"5718 Crater Lake Dr",
    "sg:city":"San Antonio",
    "sg:classifiers":[
        {
            "category":"Organizations",
            "subcategory":"Community Association",
            "type":"Services"
        }
    ],
    "sg:phone":"+1 210 666 4414",
    "sg:postcode":"78244",
    "sg:province":"TX",
    "wof:name":"Scout Master LLC",
    "wof:placetype":"venue"
},
  "geometry": {"coordinates":[-98.35134100000001,29.479543],"type":"Point"}
}