{
  "type": "Feature",
  "properties": {
    "iso:country":"US",
    "sg:address":"12011 West Ave",
    "sg:city":"San Antonio",
    "sg:classifiers":[
        {
            "category":"Food & Beverages",
            "subcategory":"Groceries & Convenience Stores",
            "type":"Retail Goods"
        }
    ],
    "sg:phone":"+1 210 979 9586",
    "sg:postcode":"78216",
    "sg:province":"TX",
    "wof:name":"Triple S Express",
    "wof:placetype":"venue"
},
  "geometry": {"coordinates":[-98.502754,29.552249],"type":"Point"}
}