{
  "type": "Feature",
  "properties": {
    "iso:country":"US",
    "sg:address":"983 S Mason Rd",
    "sg:city":"Katy",
    "sg:classifiers":[
        {
            "category":"Ice Cream",
            "type":"Food & Drink"
        }
    ],
    "sg:menulink":"http://www.allmenus.com/tx/houston/162324-dairy-queen/menu/",
    "sg:phone":"+1 713 579 7698",
    "sg:postcode":"77450",
    "sg:province":"TX",
    "sg:tags":[
        "burger",
        "american"
    ],
    "wof:name":"Dairy Queen",
    "wof:placetype":"venue"
},
  "geometry": {"coordinates":[-95.751231,29.768707],"type":"Point"}
}