{
  "type": "Feature",
  "properties": {
    "iso:country":"US",
    "sg:address":"5900 Chimney Rock Rd",
    "sg:city":"Houston",
    "sg:classifiers":[
        {
            "category":"Health Services",
            "subcategory":"Doctor",
            "type":"Services"
        }
    ],
    "sg:phone":"+1 713 664 1577",
    "sg:postcode":"77081",
    "sg:province":"TX",
    "sg:tags":[
        "clinic",
        "obstetrician",
        "medical",
        "gynecologist"
    ],
    "wof:name":"Clinica De La Vida",
    "wof:placetype":"venue"
},
  "geometry": {"coordinates":[-95.476501,29.7174],"type":"Point"}
}