{
  "type": "Feature",
  "properties": {
    "iso:country":"US",
    "sg:address":"13926 Texarkana St",
    "sg:city":"Houston",
    "sg:classifiers":[
        {
            "category":"Retail",
            "subcategory":"Animal Services",
            "type":"Services"
        }
    ],
    "sg:phone":"+1 713 455 6244",
    "sg:postcode":"77015",
    "sg:province":"TX",
    "sg:tags":[
        "pet",
        "grooming",
        "washing"
    ],
    "wof:name":"Bon-A-Parte Retreat Poodle Shp",
    "wof:placetype":"venue"
},
  "geometry": {"coordinates":[-95.176609,29.785025],"type":"Point"}
}