{
  "type": "Feature",
  "properties": {
    "iso:country":"US",
    "sg:address":"4746 Covey Ln",
    "sg:city":"Silsbee",
    "sg:classifiers":[
        {
            "category":"Building & Trades",
            "subcategory":"Landscaping Services",
            "type":"Services"
        }
    ],
    "sg:phone":"+1 409 385 6125",
    "sg:postcode":"77656",
    "sg:province":"TX",
    "wof:name":"Lone Star Lawn Service",
    "wof:placetype":"venue"
},
  "geometry": {"coordinates":[-94.168389,30.4302],"type":"Point"}
}