{
  "type": "Feature",
  "properties": {
    "iso:country":"US",
    "sg:address":"1502 Mangrum St",
    "sg:city":"Pflugerville",
    "sg:classifiers":[
        {
            "category":"Professional",
            "subcategory":"Accounting & Tax Preparation",
            "type":"Services"
        }
    ],
    "sg:phone":"+1 512 251 2812",
    "sg:postcode":"78660",
    "sg:province":"TX",
    "sg:tags":[
        "return"
    ],
    "wof:name":"Taxman Tax Services",
    "wof:placetype":"venue"
},
  "geometry": {"coordinates":[-97.66152700000001,30.444841],"type":"Point"}
}