{
  "type": "Feature",
  "properties": {
    "iso:country":"US",
    "sg:address":"1921 S Main St",
    "sg:city":"Keller",
    "sg:classifiers":[
        {
            "category":"Ice Cream",
            "type":"Food & Drink"
        }
    ],
    "sg:menulink":"http://www.allmenus.com/tx/northeast-tarrant/92774-steak-n-shake/menu/",
    "sg:phone":"+1 817 431 1924",
    "sg:postcode":"76248",
    "sg:province":"TX",
    "sg:tags":[
        "american"
    ],
    "wof:name":"Steak 'n Shake",
    "wof:placetype":"venue"
},
  "geometry": {"coordinates":[-97.258194,32.897403],"type":"Point"}
}