{
  "type": "Feature",
  "properties": {
    "iso:country":"US",
    "sg:address":"58 Highland Park Vlg",
    "sg:city":"Dallas",
    "sg:classifiers":[
        {
            "category":"Shopping Center",
            "type":"Public Place"
        }
    ],
    "sg:phone":"+1 214 522 5270",
    "sg:postcode":"75205",
    "sg:province":"TX",
    "sg:website":"www.hpvillage.com",
    "wof:name":"HIGHLAND PARK VILLAGE",
    "wof:placetype":"venue"
},
  "geometry": {"coordinates":[-96.806285,32.83624],"type":"Point"}
}