{
  "type": "Feature",
  "properties": {
    "iso:country":"US",
    "sg:address":"2682 W Roundbunch Rd",
    "sg:city":"Orange",
    "sg:classifiers":[
        {
            "category":"Food & Beverages",
            "subcategory":"Meat & Fish",
            "type":"Retail Goods"
        }
    ],
    "sg:phone":"+1 409 886 1115",
    "sg:postcode":"77630",
    "sg:province":"TX",
    "wof:name":"Bridge City Bait",
    "wof:placetype":"venue"
},
  "geometry": {"coordinates":[-93.854612,30.035517],"type":"Point"}
}