{
  "type": "Feature",
  "properties": {
    "iso:country":"US",
    "sg:address":"25 Jordans Wood Cir",
    "sg:city":"San Antonio",
    "sg:classifiers":[
        {
            "category":"Professional",
            "subcategory":"Engineering",
            "type":"Services"
        }
    ],
    "sg:phone":"+1 210 492 0678",
    "sg:postcode":"78248",
    "sg:province":"TX",
    "wof:name":"Tri Bell Microwave Inc",
    "wof:placetype":"venue"
},
  "geometry": {"coordinates":[-98.529326,29.590748],"type":"Point"}
}