{
  "type": "Feature",
  "properties": {
    "iso:country":"US",
    "sg:address":"202 S State Hwy 205",
    "sg:city":"Mc Kinney",
    "sg:classifiers":[
        {
            "category":"Manufacturing",
            "subcategory":"Electronics",
            "type":"Manufacturing & Wholesale Goods"
        }
    ],
    "sg:phone":"+1 214 544 2428",
    "sg:postcode":"75032",
    "sg:province":"TX",
    "sg:tags":[
        "design",
        "printed",
        "circuit",
        "boards"
    ],
    "wof:name":"Dallas Circuit Interconnects",
    "wof:placetype":"venue"
},
  "geometry": {"coordinates":[-96.38431199999999,32.848359],"type":"Point"}
}