{
  "type": "Feature",
  "properties": {
    "iso:country":"US",
    "sg:address":"362 Capehill Dr",
    "sg:city":"Webster",
    "sg:classifiers":[
        {
            "category":"Building & Trades",
            "subcategory":"Construction",
            "type":"Services"
        }
    ],
    "sg:phone":"+1 281 474 9334",
    "sg:postcode":"77598",
    "sg:province":"TX",
    "sg:tags":[
        "house"
    ],
    "wof:name":"Residential Consulting Service",
    "wof:placetype":"venue"
},
  "geometry": {"coordinates":[-95.138595,29.550153],"type":"Point"}
}