{
  "type": "Feature",
  "properties": {
    "iso:country":"US",
    "sg:address":"1221 Abrams Rd",
    "sg:city":"Dallas",
    "sg:classifiers":[
        {
            "category":"Real Estate",
            "subcategory":"Real Estate Agent",
            "type":"Services"
        }
    ],
    "sg:phone":"+1 972 808 9473",
    "sg:postcode":"75214",
    "sg:province":"TX",
    "wof:name":"Patricia Wise",
    "wof:placetype":"venue"
},
  "geometry": {"coordinates":[-96.756286,32.801551],"type":"Point"}
}