{
  "type": "Feature",
  "properties": {
    "iso:country":"US",
    "sg:address":"6421 Wesley St Ste B",
    "sg:city":"Greenville",
    "sg:classifiers":[
        {
            "category":"Banks & Credit Unions",
            "subcategory":"Financial Services",
            "type":"Services"
        }
    ],
    "sg:phone":"+1 903 455 8456",
    "sg:postcode":"75402",
    "sg:province":"TX",
    "sg:tags":[
        "financing",
        "cashing",
        "money",
        "loan",
        "check",
        "payday",
        "order"
    ],
    "sg:website":"http://ad.doubleclick.net/clk;225053199;48888911;w?http://www.checkngo.com?source=yellowpages&cat=TLs&AfsCampaignId=642",
    "wof:name":"Check 'n Go",
    "wof:placetype":"venue"
},
  "geometry": {"coordinates":[-96.109585,33.10668],"type":"Point"}
}