{
  "type": "Feature",
  "properties": {
    "iso:country":"US",
    "sg:address":"1217 Pecan Blvd",
    "sg:city":"Mcallen",
    "sg:classifiers":[
        {
            "category":"Communications",
            "subcategory":"Film & Video Production",
            "type":"Services"
        }
    ],
    "sg:phone":"+1 956 618 1212",
    "sg:postcode":"78501",
    "sg:province":"TX",
    "sg:tags":[
        "taping"
    ],
    "wof:name":"DRC Productions",
    "wof:placetype":"venue"
},
  "geometry": {"coordinates":[-98.231171,26.218223],"type":"Point"}
}