{
  "type": "Feature",
  "properties": {
    "iso:country":"US",
    "sg:address":"112 W Oak St",
    "sg:city":"Deer Park",
    "sg:classifiers":[
        {
            "category":"Travel",
            "subcategory":"Travel Agent",
            "type":"Entertainment"
        }
    ],
    "sg:phone":"+1 281 433 1573",
    "sg:postcode":"77536",
    "sg:province":"TX",
    "sg:tags":[
        "agency"
    ],
    "wof:name":"Sylvia K Travel",
    "wof:placetype":"venue"
},
  "geometry": {"coordinates":[-95.127551,29.693256],"type":"Point"}
}