{
  "type": "Feature",
  "properties": {
    "iso:country":"US",
    "sg:address":"4221 Auburn Dr",
    "sg:city":"Flower Mound",
    "sg:classifiers":[
        {
            "category":"Professional",
            "subcategory":"Management & Consulting",
            "type":"Services"
        }
    ],
    "sg:phone":"+1 972 874 1314",
    "sg:postcode":"75028",
    "sg:province":"TX",
    "sg:tags":[
        "business"
    ],
    "wof:name":"Stefford Consulting Group",
    "wof:placetype":"venue"
},
  "geometry": {"coordinates":[-97.08743699999999,33.044033],"type":"Point"}
}