{
  "type": "Feature",
  "properties": {
    "iso:country":"US",
    "sg:address":"734 Loganwood Ave",
    "sg:city":"Richardson",
    "sg:classifiers":[
        {
            "category":"Shopping",
            "subcategory":"Jewelry",
            "type":"Retail Goods"
        }
    ],
    "sg:phone":"+1 972 235 4896",
    "sg:postcode":"75080",
    "sg:province":"TX",
    "wof:name":"Ear Gear Unltd",
    "wof:placetype":"venue"
},
  "geometry": {"coordinates":[-96.746539,32.975915],"type":"Point"}
}