{
  "type": "Feature",
  "properties": {
    "iso:country":"US",
    "sg:address":"1733 Holt St",
    "sg:city":"Fort Worth",
    "sg:classifiers":[
        {
            "category":"Professional",
            "subcategory":"Computer Services",
            "type":"Services"
        }
    ],
    "sg:phone":"+1 817 534 9701",
    "sg:postcode":"76103",
    "sg:province":"TX",
    "sg:tags":[
        "related"
    ],
    "wof:name":"On Remote Spec Writing",
    "wof:placetype":"venue"
},
  "geometry": {"coordinates":[-97.250944,32.752073],"type":"Point"}
}