{
  "type": "Feature",
  "properties": {
    "iso:country":"US",
    "sg:address":"4025 N Central Expy",
    "sg:city":"Dallas",
    "sg:classifiers":[
        {
            "category":"Wholesale",
            "subcategory":"Apparel",
            "type":"Manufacturing & Wholesale Goods"
        }
    ],
    "sg:phone":"+1 214 526 1822",
    "sg:postcode":"75204",
    "sg:province":"TX",
    "sg:tags":[
        "shoes"
    ],
    "wof:name":"Autry Industries",
    "wof:placetype":"venue"
},
  "geometry": {"coordinates":[-96.789068,32.815438],"type":"Point"}
}