{
  "type": "Feature",
  "properties": {
    "iso:country":"US",
    "sg:address":"1365 Crystal Farms Rd",
    "sg:city":"Tatum",
    "sg:classifiers":[
        {
            "category":"Retail",
            "subcategory":"Repair Shop",
            "type":"Services"
        }
    ],
    "sg:phone":"+1 903 947 2841",
    "sg:postcode":"75691",
    "sg:province":"TX",
    "sg:tags":[
        "repairing",
        "lawn",
        "mower"
    ],
    "wof:name":"Power Pro Small Engine Repair",
    "wof:placetype":"venue"
},
  "geometry": {"coordinates":[-94.53010999999999,32.327338],"type":"Point"}
}