{
  "type": "Feature",
  "properties": {
    "iso:country":"US",
    "sg:address":"21543 W Martin Dr",
    "sg:city":"Porter",
    "sg:classifiers":[
        {
            "category":"Insurance",
            "subcategory":"Hazard Insurance",
            "type":"Services"
        },
        {
            "category":"Insurance",
            "subcategory":"Insurance Agent",
            "type":"Services"
        },
        {
            "category":"Insurance",
            "subcategory":"Life Insurance",
            "type":"Services"
        },
        {
            "category":"Insurance",
            "subcategory":"Title Insurance",
            "type":"Services"
        }
    ],
    "sg:phone":"+1 281 354 5116",
    "sg:postcode":"77365",
    "sg:province":"TX",
    "sg:tags":[
        "auto",
        "commercial",
        "business",
        "homeowner"
    ],
    "sg:website":"http://www.farmersagent.com/fwetz/",
    "wof:name":"Fred Wetz - Farmers Insurance",
    "wof:placetype":"venue"
},
  "geometry": {"coordinates":[-95.241879,30.08838],"type":"Point"}
}