{
  "type": "Feature",
  "properties": {
    "iso:country":"US",
    "sg:address":"13210 Ranch Road 12 Ste 1",
    "sg:city":"Wimberley",
    "sg:classifiers":[
        {
            "category":"Insurance",
            "subcategory":"Hazard Insurance",
            "type":"Services"
        }
    ],
    "sg:phone":"+1 512 847 9400",
    "sg:postcode":"78676",
    "sg:province":"TX",
    "sg:tags":[
        "commercial",
        "business"
    ],
    "wof:name":"Shane E Oliver",
    "wof:placetype":"venue"
},
  "geometry": {"coordinates":[-98.096012,29.996348],"type":"Point"}
}