{
  "type": "Feature",
  "properties": {
    "iso:country":"US",
    "sg:address":"1801 Broadway",
    "sg:city":"Lubbock",
    "sg:classifiers":[
        {
            "category":"Professional",
            "subcategory":"Advertising",
            "type":"Services"
        },
        {
            "category":"Communications",
            "subcategory":"Film & Video Production",
            "type":"Services"
        }
    ],
    "sg:phone":"+1 806 763 5033",
    "sg:postcode":"79401",
    "sg:province":"TX",
    "sg:tags":[
        "marketing",
        "agency",
        "internet"
    ],
    "sg:website":"http://www.pricegroupinc.com",
    "wof:name":"Price Group Inc The",
    "wof:placetype":"venue"
},
  "geometry": {"coordinates":[-101.85649100000001,33.584499],"type":"Point"}
}