{
  "type": "Feature",
  "properties": {
    "iso:country":"US",
    "sg:address":"3333 Earhart Dr Ste 200",
    "sg:city":"Carrollton",
    "sg:classifiers":[
        {
            "category":"Insurance",
            "subcategory":"Health Insurance",
            "type":"Services"
        }
    ],
    "sg:phone":"+1 972 239 6889",
    "sg:postcode":"75006",
    "sg:province":"TX",
    "sg:tags":[
        "market"
    ],
    "wof:name":"Proto Source",
    "wof:placetype":"venue"
},
  "geometry": {"coordinates":[-96.843597,32.966999],"type":"Point"}
}