{
  "type": "Feature",
  "properties": {
    "iso:country":"US",
    "sg:address":"306 W Buchanan St",
    "sg:city":"Harlingen",
    "sg:classifiers":[
        {
            "category":"Home & Garden",
            "subcategory":"Home Furnishings",
            "type":"Retail Goods"
        }
    ],
    "sg:phone":"+1 956 423 2770",
    "sg:postcode":"78550",
    "sg:province":"TX",
    "wof:name":"J D Hightower",
    "wof:placetype":"venue"
},
  "geometry": {"coordinates":[-97.69882800000001,26.184454],"type":"Point"}
}