{
  "type": "Feature",
  "properties": {
    "iso:country":"US",
    "sg:address":"910 E Waylon Jennings Blvd",
    "sg:city":"Littlefield",
    "sg:classifiers":[
        {
            "category":"Manufacturing",
            "subcategory":"Tools & Machinery",
            "type":"Manufacturing & Wholesale Goods"
        }
    ],
    "sg:phone":"+1 806 385 4811",
    "sg:postcode":"79339",
    "sg:province":"TX",
    "sg:tags":[
        "machine",
        "shop",
        "industrial",
        "mfg"
    ],
    "wof:name":"Purdy Machine",
    "wof:placetype":"venue"
},
  "geometry": {"coordinates":[-102.326391,33.917282],"type":"Point"}
}