{
  "type": "Feature",
  "properties": {
    "iso:country":"US",
    "sg:address":"1401 E Elms Rd",
    "sg:city":"Killeen",
    "sg:classifiers":[
        {
            "category":"Organizations",
            "subcategory":"Religious Organization",
            "type":"Services"
        }
    ],
    "sg:phone":"+1 254 634 6990",
    "sg:postcode":"76542",
    "sg:province":"TX",
    "sg:tags":[
        "church"
    ],
    "wof:name":"Grace Christian Center",
    "wof:placetype":"venue"
},
  "geometry": {"coordinates":[-97.735608,31.080548],"type":"Point"}
}