{
  "type": "Feature",
  "properties": {
    "iso:country":"US",
    "sg:address":"515 W Mayfield Rd",
    "sg:city":"Arlington",
    "sg:classifiers":[
        {
            "category":"Health Services",
            "subcategory":"Doctor",
            "type":"Services"
        }
    ],
    "sg:phone":"+1 817 419 8748",
    "sg:postcode":"76014",
    "sg:province":"TX",
    "sg:tags":[
        "medical"
    ],
    "wof:name":"Kline Ronald S",
    "wof:placetype":"venue"
},
  "geometry": {"coordinates":[-97.113438,32.691068],"type":"Point"}
}