{
  "type": "Feature",
  "properties": {
    "iso:country":"US",
    "sg:address":"3728 Spring Ave # R",
    "sg:city":"Dallas",
    "sg:classifiers":[
        {
            "category":"Personal",
            "subcategory":"Beauty Salon",
            "type":"Services"
        },
        {
            "category":"Personal",
            "subcategory":"Barber",
            "type":"Services"
        }
    ],
    "sg:phone":"+1 972 247 6151",
    "sg:postcode":"75210",
    "sg:province":"TX",
    "sg:tags":[
        "hair"
    ],
    "wof:name":"Hair Quarters",
    "wof:placetype":"venue"
},
  "geometry": {"coordinates":[-96.7491,32.768501],"type":"Point"}
}