{
  "type": "Feature",
  "properties": {
    "iso:country":"US",
    "sg:address":"4008 Ave A",
    "sg:city":"Lubbock",
    "sg:classifiers":[
        {
            "category":"Autos & Motor Vehicles",
            "subcategory":"Motorcycle Sales",
            "type":"Retail Goods"
        }
    ],
    "sg:phone":"+1 806 763 9393",
    "sg:postcode":"79404",
    "sg:province":"TX",
    "sg:tags":[
        "car",
        "golf",
        "cart"
    ],
    "wof:name":"High Plains Golf & Industrial",
    "wof:placetype":"venue"
},
  "geometry": {"coordinates":[-101.835714,33.556098],"type":"Point"}
}