{
  "type": "Feature",
  "properties": {
    "iso:country":"US",
    "sg:address":"2210 Denton Dr",
    "sg:city":"Austin",
    "sg:classifiers":[
        {
            "category":"Building & Trades",
            "subcategory":"Electrical",
            "type":"Services"
        }
    ],
    "sg:phone":"+1 512 833 5816",
    "sg:postcode":"78758",
    "sg:province":"TX",
    "sg:tags":[
        "electrical"
    ],
    "wof:name":"Mills Electric LP",
    "wof:placetype":"venue"
},
  "geometry": {"coordinates":[-97.715129,30.386257],"type":"Point"}
}