{
  "type": "Feature",
  "properties": {
    "iso:country":"US",
    "sg:address":"250 Hidden Oak Rd",
    "sg:city":"Dale",
    "sg:classifiers":[
        {
            "category":"Retail",
            "subcategory":"Repair Shop",
            "type":"Services"
        }
    ],
    "sg:phone":"+1 512 601 1197",
    "sg:postcode":"78616",
    "sg:province":"TX",
    "wof:name":"Longhorn Air & Hydraulic Eqp",
    "wof:placetype":"venue"
},
  "geometry": {"coordinates":[-97.566441,29.989153],"type":"Point"}
}