{
  "type": "Feature",
  "properties": {
    "iso:country":"US",
    "sg:address":"2033 11th St",
    "sg:city":"Huntsville",
    "sg:classifiers":[
        {
            "category":"Banks & Credit Unions",
            "subcategory":"Bank",
            "type":"Services"
        }
    ],
    "sg:phone":"+1 936 291 3232",
    "sg:postcode":"77320",
    "sg:province":"TX",
    "wof:name":"First Victoria National Bank",
    "wof:placetype":"venue"
},
  "geometry": {"coordinates":[-95.55699199999999,30.723468],"type":"Point"}
}