{
  "type": "Feature",
  "properties": {
    "iso:country":"US",
    "sg:address":"203 E 4th St",
    "sg:city":"Denver City",
    "sg:classifiers":[
        {
            "category":"Professional",
            "type":"Services"
        }
    ],
    "sg:phone":"+1 806 592 8176",
    "sg:postcode":"79323",
    "sg:province":"TX",
    "sg:tags":[
        "establishment"
    ],
    "wof:name":"Arc Presser Data Inc",
    "wof:placetype":"venue"
},
  "geometry": {"coordinates":[-102.828013,32.967984],"type":"Point"}
}