{
  "type": "Feature",
  "properties": {
    "iso:country":"US",
    "sg:address":"9828 Montana Ave",
    "sg:city":"El Paso",
    "sg:classifiers":[
        {
            "category":"Personal",
            "type":"Services"
        }
    ],
    "sg:phone":"+1 915 591 8282",
    "sg:postcode":"79925",
    "sg:province":"TX",
    "sg:tags":[
        "ear",
        "piercing"
    ],
    "wof:name":"House Of Pain",
    "wof:placetype":"venue"
},
  "geometry": {"coordinates":[-106.354488,31.794889],"type":"Point"}
}