{
  "type": "Feature",
  "properties": {
    "iso:country":"US",
    "sg:address":"4401 Cline Rd",
    "sg:city":"Amarillo",
    "sg:classifiers":[
        {
            "category":"Building & Trades",
            "subcategory":"Construction",
            "type":"Services"
        }
    ],
    "sg:phone":"+1 806 352 7754",
    "sg:postcode":"79110",
    "sg:province":"TX",
    "sg:tags":[
        "contractor"
    ],
    "wof:name":"North Plains Roofing Co",
    "wof:placetype":"venue"
},
  "geometry": {"coordinates":[-101.85413699999999,35.1621],"type":"Point"}
}