{
  "type": "Feature",
  "properties": {
    "iso:country":"US",
    "sg:address":"359 Brookhaven Dr",
    "sg:city":"Waco",
    "sg:classifiers":[
        {
            "category":"Professional",
            "type":"Services"
        }
    ],
    "sg:phone":"+1 254 848 9027",
    "sg:postcode":"76712",
    "sg:province":"TX",
    "wof:name":"Michael J Daley",
    "wof:placetype":"venue"
},
  "geometry": {"coordinates":[-97.29438,31.563662],"type":"Point"}
}