{
  "type": "Feature",
  "properties": {
    "iso:country":"US",
    "sg:address":"119 N 1st St",
    "sg:city":"Temple",
    "sg:classifiers":[
        {
            "category":"Building & Trades",
            "subcategory":"Cleaning & Sanitation",
            "type":"Services"
        }
    ],
    "sg:phone":"+1 254 773 0528",
    "sg:postcode":"76501",
    "sg:province":"TX",
    "sg:tags":[
        "maintenance"
    ],
    "wof:name":"Aim Building Maintenance",
    "wof:placetype":"venue"
},
  "geometry": {"coordinates":[-97.34141700000001,31.098701],"type":"Point"}
}