{
  "type": "Feature",
  "properties": {
    "iso:country":"US",
    "sg:address":"5336 East Rd",
    "sg:city":"Baytown",
    "sg:classifiers":[
        {
            "category":"Manufacturing",
            "subcategory":"Tools & Machinery",
            "type":"Manufacturing & Wholesale Goods"
        }
    ],
    "sg:phone":"+1 281 421 3013",
    "sg:postcode":"77521",
    "sg:province":"TX",
    "sg:tags":[
        "filtering",
        "material",
        "supply"
    ],
    "sg:website":"www.filtersunltd.com",
    "wof:name":"Filters Unlimited Inc",
    "wof:placetype":"venue"
},
  "geometry": {"coordinates":[-94.970878,29.781105],"type":"Point"}
}