{
  "type": "Feature",
  "properties": {
    "iso:country":"US",
    "sg:address":"1228 E Scyene Rd",
    "sg:city":"Mesquite",
    "sg:classifiers":[
        {
            "category":"Manufacturing",
            "subcategory":"Motor Vehicles & Parts",
            "type":"Manufacturing & Wholesale Goods"
        }
    ],
    "sg:phone":"+1 972 285 5179",
    "sg:postcode":"75181",
    "sg:province":"TX",
    "sg:tags":[
        "automobile",
        "supply"
    ],
    "wof:name":"Drive Train Of Mesquite",
    "wof:placetype":"venue"
},
  "geometry": {"coordinates":[-96.584784,32.765894],"type":"Point"}
}