{
  "type": "Feature",
  "properties": {
    "iso:country":"US",
    "sg:address":"998 Little Den Dr",
    "sg:city":"Lewisville",
    "sg:classifiers":[
        {
            "category":"Professional",
            "subcategory":"Employment Agencies",
            "type":"Services"
        }
    ],
    "sg:phone":"+1 972 316 1575",
    "sg:postcode":"75067",
    "sg:province":"TX",
    "sg:tags":[
        "staffing"
    ],
    "wof:name":"Team Staffg Hlth Pro",
    "wof:placetype":"venue"
},
  "geometry": {"coordinates":[-97.01482,33.010939],"type":"Point"}
}