{
  "type": "Feature",
  "properties": {
    "iso:country":"US",
    "sg:address":"1833 Carpenter Rd",
    "sg:city":"Hutchins",
    "sg:classifiers":[
        {
            "category":"Professional",
            "type":"Services"
        }
    ],
    "sg:phone":"+1 972 225 1517",
    "sg:postcode":"75141",
    "sg:province":"TX",
    "sg:tags":[
        "establishment"
    ],
    "wof:name":"Transporter Inc",
    "wof:placetype":"venue"
},
  "geometry": {"coordinates":[-96.71062499999999,32.624391],"type":"Point"}
}