{
  "type": "Feature",
  "properties": {
    "iso:country":"US",
    "sg:address":"322 S 2nd St",
    "sg:city":"Kenedy",
    "sg:classifiers":[
        {
            "category":"Autos & Motor Vehicles",
            "subcategory":"Fuel & Gas Station",
            "type":"Retail Goods"
        }
    ],
    "sg:phone":"+1 830 583 3397",
    "sg:postcode":"78119",
    "sg:province":"TX",
    "sg:tags":[
        "station",
        "gasoline"
    ],
    "wof:name":"Diamond Shamrock",
    "wof:placetype":"venue"
},
  "geometry": {"coordinates":[-97.848257,28.81693],"type":"Point"}
}