{
  "type": "Feature",
  "properties": {
    "iso:country":"US",
    "sg:address":"27 Briar Meadow",
    "sg:city":"Huntsville",
    "sg:classifiers":[
        {
            "category":"Bars & Pubs",
            "type":"Food & Drink"
        }
    ],
    "sg:phone":"+1 936 294 0050",
    "sg:postcode":"77320",
    "sg:province":"TX",
    "sg:tags":[
        "drinking"
    ],
    "wof:name":"Daddy Os Sports Bar Inc",
    "wof:placetype":"venue"
},
  "geometry": {"coordinates":[-95.63155999999999,30.703764],"type":"Point"}
}