{
  "type": "Feature",
  "properties": {
    "iso:country":"US",
    "sg:address":"9605 Bell Mountain Dr",
    "sg:city":"Austin",
    "sg:classifiers":[
        {
            "category":"Real Estate",
            "subcategory":"Real Estate Services",
            "type":"Services"
        }
    ],
    "sg:phone":"+1 512 346 4069",
    "sg:postcode":"78730",
    "sg:province":"TX",
    "sg:tags":[
        "management",
        "property"
    ],
    "wof:name":"Ronan Management Services Inc",
    "wof:placetype":"venue"
},
  "geometry": {"coordinates":[-97.83339700000001,30.383101],"type":"Point"}
}