{
  "type": "Feature",
  "properties": {
    "iso:country":"US",
    "sg:address":"1200 W Oaks Mall",
    "sg:city":"Houston",
    "sg:classifiers":[
        {
            "category":"Health Services",
            "subcategory":"Optometrist",
            "type":"Services"
        }
    ],
    "sg:phone":"+1 281 496 6335",
    "sg:postcode":"77082",
    "sg:province":"TX",
    "wof:name":"Nancy Harrison OD",
    "wof:placetype":"venue"
},
  "geometry": {"coordinates":[-95.657883,29.72693],"type":"Point"}
}