{
  "type": "Feature",
  "properties": {
    "iso:country":"US",
    "sg:address":"3023 Bayou Dr",
    "sg:city":"La Porte",
    "sg:classifiers":[
        {
            "category":"Shopping",
            "subcategory":"Florist",
            "type":"Retail Goods"
        }
    ],
    "sg:phone":"+1 281 470 2232",
    "sg:postcode":"77571",
    "sg:province":"TX",
    "wof:name":"Bayou Drive Orchids",
    "wof:placetype":"venue"
},
  "geometry": {"coordinates":[-95.02140199999999,29.625921],"type":"Point"}
}