{
  "type": "Feature",
  "properties": {
    "iso:country":"US",
    "sg:address":"243 Oak Creek Cir",
    "sg:city":"Mc Gregor",
    "sg:classifiers":[
        {
            "category":"Manufacturing",
            "subcategory":"Glass & Minerals",
            "type":"Manufacturing & Wholesale Goods"
        }
    ],
    "sg:phone":"+1 254 848 5581",
    "sg:postcode":"76657",
    "sg:province":"TX",
    "sg:tags":[
        "concrete",
        "brick",
        "prod",
        "block"
    ],
    "wof:name":"Texas Hardscapes",
    "wof:placetype":"venue"
},
  "geometry": {"coordinates":[-97.31429799999999,31.476796],"type":"Point"}
}