{
  "type": "Feature",
  "properties": {
    "iso:country":"US",
    "sg:address":"7655 W 81st Ave",
    "sg:city":"Amarillo",
    "sg:classifiers":[
        {
            "category":"Building & Trades",
            "subcategory":"Construction",
            "type":"Services"
        }
    ],
    "sg:phone":"+1 806 359 5409",
    "sg:postcode":"79119",
    "sg:province":"TX",
    "sg:tags":[
        "roofing",
        "contractor"
    ],
    "wof:name":"Andrus Brothers",
    "wof:placetype":"venue"
},
  "geometry": {"coordinates":[-101.922785,35.125848],"type":"Point"}
}