{
  "type": "Feature",
  "properties": {
    "iso:country":"US",
    "sg:address":"2302 Stanley Rd",
    "sg:city":"Fort Sam Houston",
    "sg:classifiers":[
        {
            "category":"Banks & Credit Unions",
            "subcategory":"Bank",
            "type":"Services"
        }
    ],
    "sg:phone":"+1 210 227 7131",
    "sg:postcode":"78234",
    "sg:province":"TX",
    "sg:website":"www.enbank.com",
    "wof:name":"Eisenhower Bank",
    "wof:placetype":"venue"
},
  "geometry": {"coordinates":[-98.45159200000001,29.451368],"type":"Point"}
}