{
  "type": "Feature",
  "properties": {
    "iso:country":"US",
    "sg:address":"23919 Griffin House Ln",
    "sg:city":"Katy",
    "sg:classifiers":[
        {
            "category":"Retail",
            "subcategory":"Repair Shop",
            "type":"Services"
        }
    ],
    "sg:phone":"+1 281 347 0445",
    "sg:postcode":"77493",
    "sg:province":"TX",
    "wof:name":"A & A Locksmith",
    "wof:placetype":"venue"
},
  "geometry": {"coordinates":[-95.78051000000001,29.798356],"type":"Point"}
}