{
  "type": "Feature",
  "properties": {
    "iso:country":"US",
    "sg:address":"311 S Waco St",
    "sg:city":"Hillsboro",
    "sg:classifiers":[
        {
            "category":"Education",
            "subcategory":"School",
            "type":"Public Place"
        }
    ],
    "sg:phone":"+1 254 582 0963",
    "sg:postcode":"76645",
    "sg:province":"TX",
    "wof:name":"Hill County Alternative School",
    "wof:placetype":"venue"
},
  "geometry": {"coordinates":[-97.130117,32.005811],"type":"Point"}
}