{
  "type": "Feature",
  "properties": {
    "iso:country":"US",
    "sg:address":"1106 Smith Rd",
    "sg:city":"Austin",
    "sg:classifiers":[
        {
            "category":"Professional",
            "subcategory":"Detective & Security Services",
            "type":"Services"
        }
    ],
    "sg:phone":"+1 512 385 3208",
    "sg:postcode":"78721",
    "sg:province":"TX",
    "sg:tags":[
        "car",
        "armored"
    ],
    "wof:name":"Dunbar Armored Car",
    "wof:placetype":"venue"
},
  "geometry": {"coordinates":[-97.67912,30.256803],"type":"Point"}
}