{
  "type": "Feature",
  "properties": {
    "iso:country":"US",
    "sg:address":"3109 Heron Ave",
    "sg:city":"Mcallen",
    "sg:classifiers":[
        {
            "category":"Wholesale",
            "subcategory":"Vending Machines",
            "type":"Manufacturing & Wholesale Goods"
        }
    ],
    "sg:phone":"+1 956 630 5946",
    "sg:postcode":"78504",
    "sg:province":"TX",
    "wof:name":"Bob's Vending",
    "wof:placetype":"venue"
},
  "geometry": {"coordinates":[-98.246956,26.26046],"type":"Point"}
}