{
  "type": "Feature",
  "properties": {
    "iso:country":"US",
    "sg:address":"1720 N Central Expy",
    "sg:city":"Mc Kinney",
    "sg:classifiers":[
        {
            "category":"Health Services",
            "subcategory":"Doctor",
            "type":"Services"
        }
    ],
    "sg:phone":"+1 972 547 6033",
    "sg:postcode":"75070",
    "sg:province":"TX",
    "sg:tags":[
        "dentist"
    ],
    "wof:name":"Monarch Dental Assoc",
    "wof:placetype":"venue"
},
  "geometry": {"coordinates":[-96.63648499999999,33.214115],"type":"Point"}
}