{
  "type": "Feature",
  "properties": {
    "iso:country":"US",
    "sg:address":"6150 W Eldorado Pkwy",
    "sg:city":"Mckinney",
    "sg:classifiers":[
        {
            "category":"Restaurant",
            "type":"Food & Drink"
        }
    ],
    "sg:phone":"+1 972 548 4900",
    "sg:postcode":"75070",
    "sg:province":"TX",
    "sg:tags":[
        "pizza"
    ],
    "wof:name":"Brother's Pizza",
    "wof:placetype":"venue"
},
  "geometry": {"coordinates":[-96.695921,33.174145],"type":"Point"}
}