{
  "type": "Feature",
  "properties": {
    "iso:country":"US",
    "sg:address":"13846 Chrisman Rd",
    "sg:city":"Houston",
    "sg:classifiers":[
        {
            "category":"Wholesale",
            "subcategory":"Construction Materials",
            "type":"Manufacturing & Wholesale Goods"
        },
        {
            "category":"Manufacturing",
            "subcategory":"Rubber & Plastics",
            "type":"Manufacturing & Wholesale Goods"
        }
    ],
    "sg:phone":"+1 281 442 4481",
    "sg:postcode":"77039",
    "sg:province":"TX",
    "sg:tags":[
        "product",
        "foam"
    ],
    "wof:name":"Associated Foam Plastics Inc",
    "wof:placetype":"venue"
},
  "geometry": {"coordinates":[-95.363541,29.916407],"type":"Point"}
}