{
  "type": "Feature",
  "properties": {
    "iso:country":"US",
    "sg:address":"5124 Briargrove Ln",
    "sg:city":"Dallas",
    "sg:classifiers":[
        {
            "category":"Professional",
            "subcategory":"Business Services",
            "type":"Services"
        }
    ],
    "sg:phone":"+1 214 679 0501",
    "sg:postcode":"75287",
    "sg:province":"TX",
    "wof:name":"B R C Sales Inc",
    "wof:placetype":"venue"
},
  "geometry": {"coordinates":[-96.819289,32.992423],"type":"Point"}
}