{
  "type": "Feature",
  "properties": {
    "iso:country":"US",
    "sg:address":"3102 Colony Dr",
    "sg:city":"San Antonio",
    "sg:classifiers":[
        {
            "category":"Shopping",
            "subcategory":"Jewelry",
            "type":"Retail Goods"
        }
    ],
    "sg:phone":"+1 210 690 7522",
    "sg:postcode":"78230",
    "sg:province":"TX",
    "wof:name":"Ogavy S Inactive",
    "wof:placetype":"venue"
},
  "geometry": {"coordinates":[-98.54633800000001,29.534715],"type":"Point"}
}