{
  "type": "Feature",
  "properties": {
    "iso:country":"US",
    "sg:address":"3730 Dilido #104",
    "sg:city":"Dallas",
    "sg:classifiers":[
        {
            "category":"Building & Trades",
            "subcategory":"Electrical",
            "type":"Services"
        }
    ],
    "sg:phone":"+1 214 329 4567",
    "sg:postcode":"75228",
    "sg:province":"TX",
    "sg:tags":[
        "electrician"
    ],
    "sg:website":"www.caddellelectric.com",
    "wof:name":"Caddell Electric",
    "wof:placetype":"venue"
},
  "geometry": {"coordinates":[-96.68733400000001,32.798692],"type":"Point"}
}