{
  "type": "Feature",
  "properties": {
    "iso:country":"US",
    "sg:address":"325 Country Ln",
    "sg:city":"Cibolo",
    "sg:classifiers":[
        {
            "category":"Shopping",
            "subcategory":"Gifts & Souvenirs",
            "type":"Retail Goods"
        }
    ],
    "sg:phone":"+1 210 945 2970",
    "sg:postcode":"78108",
    "sg:province":"TX",
    "sg:tags":[
        "novelty"
    ],
    "wof:name":"Cibolo Heritage Imports",
    "wof:placetype":"venue"
},
  "geometry": {"coordinates":[-98.21023099999999,29.562558],"type":"Point"}
}