{
  "type": "Feature",
  "properties": {
    "iso:country":"US",
    "sg:address":"1364 Juniper Ln",
    "sg:city":"Lewisville",
    "sg:classifiers":[
        {
            "category":"Building & Trades",
            "subcategory":"Construction",
            "type":"Services"
        }
    ],
    "sg:phone":"+1 972 434 3560",
    "sg:postcode":"75077",
    "sg:province":"TX",
    "sg:tags":[
        "industrial"
    ],
    "wof:name":"Jams Trim",
    "wof:placetype":"venue"
},
  "geometry": {"coordinates":[-97.027703,33.051559],"type":"Point"}
}