{
  "type": "Feature",
  "properties": {
    "iso:country":"US",
    "sg:address":"2523 Ohio Dr",
    "sg:city":"Plano",
    "sg:classifiers":[
        {
            "category":"Wholesale",
            "subcategory":"Durable Goods & Equipment",
            "type":"Manufacturing & Wholesale Goods"
        }
    ],
    "sg:phone":"+1 972 769 2847",
    "sg:postcode":"75093",
    "sg:province":"TX",
    "wof:name":"R & F Wholesale Inc",
    "wof:placetype":"venue"
},
  "geometry": {"coordinates":[-96.790002,33.032494],"type":"Point"}
}