{
  "type": "Feature",
  "properties": {
    "iso:country":"US",
    "sg:address":"755 Loop 337",
    "sg:city":"New Braunfels",
    "sg:classifiers":[
        {
            "category":"Travel",
            "subcategory":"Travel Agent",
            "type":"Entertainment"
        }
    ],
    "sg:phone":"+1 830 620 1060",
    "sg:postcode":"78130",
    "sg:province":"TX",
    "sg:tags":[
        "agency",
        "bureau"
    ],
    "wof:name":"Roadrunner Travel",
    "wof:placetype":"venue"
},
  "geometry": {"coordinates":[-98.101631,29.710102],"type":"Point"}
}