{
  "type": "Feature",
  "properties": {
    "iso:country":"US",
    "sg:address":"28765 Bass Blvd",
    "sg:city":"Harlingen",
    "sg:classifiers":[
        {
            "category":"Retail",
            "subcategory":"Animal Services",
            "type":"Services"
        }
    ],
    "sg:phone":"+1 956 428 2020",
    "sg:postcode":"78552",
    "sg:province":"TX",
    "sg:tags":[
        "pet",
        "boarding",
        "sitting"
    ],
    "wof:name":"Lanehaus Kennels",
    "wof:placetype":"venue"
},
  "geometry": {"coordinates":[-97.7822,26.141013],"type":"Point"}
}