{
  "type": "Feature",
  "properties": {
    "iso:country":"US",
    "sg:address":"807 W Bois D Arc St",
    "sg:city":"Henrietta",
    "sg:classifiers":[
        {
            "category":"Social Services",
            "subcategory":"Job Training",
            "type":"Services"
        },
        {
            "category":"Social Services",
            "subcategory":"Adult Care",
            "type":"Services"
        }
    ],
    "sg:phone":"+1 940 538 4303",
    "sg:postcode":"76365",
    "sg:province":"TX",
    "sg:tags":[
        "nurses-home",
        "nursing",
        "homes-skilled",
        "facility"
    ],
    "wof:name":"Henrietta Care Center",
    "wof:placetype":"venue"
},
  "geometry": {"coordinates":[-98.20256500000001,33.81311],"type":"Point"}
}