{
  "type": "Feature",
  "properties": {
    "iso:country":"US",
    "sg:address":"15923 McKay Rd",
    "sg:city":"Willis",
    "sg:classifiers":[
        {
            "category":"Building & Trades",
            "subcategory":"Construction",
            "type":"Services"
        }
    ],
    "sg:phone":"+1 936 890 1845",
    "sg:postcode":"77378",
    "sg:province":"TX",
    "sg:tags":[
        "house"
    ],
    "wof:name":"Renegade Renovations",
    "wof:placetype":"venue"
},
  "geometry": {"coordinates":[-95.31864299999999,30.416099],"type":"Point"}
}