{
  "type": "Feature",
  "properties": {
    "iso:country":"US",
    "sg:address":"301 E Pioneer Pkwy",
    "sg:city":"Grand Prairie",
    "sg:classifiers":[
        {
            "category":"Retail",
            "subcategory":"Laundry & Dry Cleaning",
            "type":"Services"
        }
    ],
    "sg:phone":"+1 972 262 8638",
    "sg:postcode":"75051",
    "sg:province":"TX",
    "wof:name":"Regal Cleaners",
    "wof:placetype":"venue"
},
  "geometry": {"coordinates":[-97.00029600000001,32.70948],"type":"Point"}
}