{
  "type": "Feature",
  "properties": {
    "iso:country":"US",
    "sg:address":"1307 E Coliseum Dr",
    "sg:city":"Snyder",
    "sg:classifiers":[
        {
            "category":"Travel",
            "subcategory":"Hotels & Motels",
            "type":"Entertainment"
        }
    ],
    "sg:phone":"+1 325 573 5432",
    "sg:postcode":"79549",
    "sg:province":"TX",
    "sg:tags":[
        "lodging"
    ],
    "wof:name":"American Motor Inn",
    "wof:placetype":"venue"
},
  "geometry": {"coordinates":[-100.877471,32.702303],"type":"Point"}
}