{
  "type": "Feature",
  "properties": {
    "iso:country":"US",
    "sg:address":"113 Flato St",
    "sg:city":"San Antonio",
    "sg:classifiers":[
        {
            "category":"Retail",
            "subcategory":"Repair Shop",
            "type":"Services"
        }
    ],
    "sg:phone":"+1 210 534 1658",
    "sg:postcode":"78204",
    "sg:province":"TX",
    "sg:tags":[
        "equipment",
        "medical"
    ],
    "wof:name":"A & R Medical Repairs",
    "wof:placetype":"venue"
},
  "geometry": {"coordinates":[-98.502698,29.39378],"type":"Point"}
}