{
  "type": "Feature",
  "properties": {
    "iso:country":"US",
    "sg:address":"1500 Dragon St",
    "sg:city":"Dallas",
    "sg:classifiers":[
        {
            "category":"Manufacturing",
            "subcategory":"Pottery",
            "type":"Manufacturing & Wholesale Goods"
        }
    ],
    "sg:phone":"+1 214 742 3300",
    "sg:postcode":"75207",
    "sg:province":"TX",
    "sg:tags":[
        "products-decorative",
        "ceramic"
    ],
    "wof:name":"Prosource Dallas Market Center",
    "wof:placetype":"venue"
},
  "geometry": {"coordinates":[-96.81976400000001,32.791514],"type":"Point"}
}