{
  "type": "Feature",
  "properties": {
    "iso:country":"US",
    "sg:address":"1001 7th St",
    "sg:city":"Corpus Christi",
    "sg:classifiers":[
        {
            "category":"Professional",
            "subcategory":"Business Services",
            "type":"Services"
        }
    ],
    "sg:phone":"+1 361 884 4780",
    "sg:postcode":"78404",
    "sg:province":"TX",
    "sg:tags":[
        "record",
        "company",
        "producing"
    ],
    "wof:name":"Supremo Records",
    "wof:placetype":"venue"
},
  "geometry": {"coordinates":[-97.400752,27.781578],"type":"Point"}
}