{
  "type": "Feature",
  "properties": {
    "iso:country":"US",
    "sg:address":"1609 Meadowcrest Dr",
    "sg:city":"Garland",
    "sg:classifiers":[
        {
            "category":"Retail",
            "subcategory":"Portrait Studio",
            "type":"Services"
        }
    ],
    "sg:phone":"+1 972 272 3236",
    "sg:postcode":"75042",
    "sg:province":"TX",
    "sg:tags":[
        "photo"
    ],
    "wof:name":"Bill Bunch Photography",
    "wof:placetype":"venue"
},
  "geometry": {"coordinates":[-96.65279700000001,32.92272],"type":"Point"}
}