{
  "type": "Feature",
  "properties": {
    "iso:country":"US",
    "sg:address":"412 N Main St",
    "sg:city":"Euless",
    "sg:classifiers":[
        {
            "category":"Insurance",
            "subcategory":"Insurance Agent",
            "type":"Services"
        }
    ],
    "sg:phone":"+1 817 318 1030",
    "sg:postcode":"76039",
    "sg:province":"TX",
    "wof:name":"Costlow & Associates",
    "wof:placetype":"venue"
},
  "geometry": {"coordinates":[-97.08250200000001,32.842976],"type":"Point"}
}