{
  "type": "Feature",
  "properties": {
    "iso:country":"US",
    "sg:address":"3902 Gallaher Ct",
    "sg:city":"Missouri City",
    "sg:classifiers":[
        {
            "category":"Professional",
            "subcategory":"Management & Consulting",
            "type":"Services"
        }
    ],
    "sg:phone":"+1 281 778 7908",
    "sg:postcode":"77459",
    "sg:province":"TX",
    "sg:tags":[
        "business"
    ],
    "wof:name":"APM International",
    "wof:placetype":"venue"
},
  "geometry": {"coordinates":[-95.528052,29.501959],"type":"Point"}
}