{
  "type": "Feature",
  "properties": {
    "iso:country":"US",
    "sg:address":"8521 Starcrest Dr",
    "sg:city":"San Antonio",
    "sg:classifiers":[
        {
            "category":"Personal",
            "subcategory":"Beauty Salon",
            "type":"Services"
        }
    ],
    "sg:phone":"+1 210 656 5550",
    "sg:postcode":"78217",
    "sg:province":"TX",
    "sg:tags":[
        "shop"
    ],
    "wof:name":"Echesalons Hair & Nails",
    "wof:placetype":"venue"
},
  "geometry": {"coordinates":[-98.422915,29.51954],"type":"Point"}
}