{
  "type": "Feature",
  "properties": {
    "iso:country":"US",
    "sg:address":"777 Green Meadow Ln",
    "sg:city":"Houston",
    "sg:classifiers":[
        {
            "category":"Organizations",
            "subcategory":"Religious Organization",
            "type":"Services"
        }
    ],
    "sg:phone":"+1 713 694 7624",
    "sg:postcode":"77091",
    "sg:province":"TX",
    "sg:tags":[
        "church"
    ],
    "wof:name":"Green Meadow Missionary Church",
    "wof:placetype":"venue"
},
  "geometry": {"coordinates":[-95.416346,29.866816],"type":"Point"}
}