{
  "type": "Feature",
  "properties": {
    "iso:country":"US",
    "sg:address":"709 E Bonita Ave",
    "sg:city":"Amarillo",
    "sg:classifiers":[
        {
            "category":"Building & Trades",
            "subcategory":"Construction",
            "type":"Services"
        }
    ],
    "sg:phone":"+1 806 383 8887",
    "sg:postcode":"79108",
    "sg:province":"TX",
    "sg:tags":[
        "concrete",
        "contractor"
    ],
    "wof:name":"Ayala Cement Contractor",
    "wof:placetype":"venue"
},
  "geometry": {"coordinates":[-101.82218899999999,35.254607],"type":"Point"}
}