{
  "type": "Feature",
  "properties": {
    "iso:country":"US",
    "sg:address":"10726 Burgoyne Rd",
    "sg:city":"Houston",
    "sg:classifiers":[
        {
            "category":"Wholesale",
            "subcategory":"Medical Equipment & Supplies",
            "type":"Manufacturing & Wholesale Goods"
        }
    ],
    "sg:phone":"+1 832 242 2282",
    "sg:postcode":"77042",
    "sg:province":"TX",
    "sg:tags":[
        "physician",
        "surgeon"
    ],
    "wof:name":"Uromed",
    "wof:placetype":"venue"
},
  "geometry": {"coordinates":[-95.56458600000001,29.741645],"type":"Point"}
}