{
  "type": "Feature",
  "properties": {
    "iso:country":"US",
    "sg:address":"2700 Meadowview Dr",
    "sg:city":"Arlington",
    "sg:classifiers":[
        {
            "category":"Professional",
            "subcategory":"Business Services",
            "type":"Services"
        }
    ],
    "sg:phone":"+1 817 896 9377",
    "sg:postcode":"76016",
    "sg:province":"TX",
    "wof:name":"Atlantis Agency",
    "wof:placetype":"venue"
},
  "geometry": {"coordinates":[-97.169588,32.698922],"type":"Point"}
}