{
  "type": "Feature",
  "properties": {
    "iso:country":"US",
    "sg:address":"3025 E Seminary Dr",
    "sg:city":"Fort Worth",
    "sg:classifiers":[
        {
            "category":"Personal",
            "subcategory":"Barber",
            "type":"Services"
        }
    ],
    "sg:phone":"+1 817 535 5576",
    "sg:postcode":"76119",
    "sg:province":"TX",
    "sg:tags":[
        "shop"
    ],
    "wof:name":"Head Hunter's Barber Shop",
    "wof:placetype":"venue"
},
  "geometry": {"coordinates":[-97.285477,32.68491],"type":"Point"}
}