{
  "type": "Feature",
  "properties": {
    "iso:country":"US",
    "sg:address":"203 Dogwood Trl",
    "sg:city":"Magnolia",
    "sg:classifiers":[
        {
            "category":"Building & Trades",
            "subcategory":"Electrical",
            "type":"Services"
        },
        {
            "category":"Professional",
            "subcategory":"Business Services",
            "type":"Services"
        }
    ],
    "sg:phone":"+1 281 356 8027",
    "sg:postcode":"77354",
    "sg:province":"TX",
    "sg:tags":[
        "booth",
        "equipment",
        "telephone",
        "pay"
    ],
    "wof:name":"Payphone Intellect Network",
    "wof:placetype":"venue"
},
  "geometry": {"coordinates":[-95.743487,30.2202],"type":"Point"}
}