{
  "type": "Feature",
  "properties": {
    "iso:country":"US",
    "sg:address":"14602 Huebner Rd",
    "sg:city":"San Antonio",
    "sg:classifiers":[
        {
            "category":"Food & Beverages",
            "subcategory":"Liquor & Beverages",
            "type":"Retail Goods"
        }
    ],
    "sg:phone":"+1 210 492 9463",
    "sg:postcode":"78230",
    "sg:province":"TX",
    "wof:name":"Thrifty Liquor 1",
    "wof:placetype":"venue"
},
  "geometry": {"coordinates":[-98.54742299999999,29.572936],"type":"Point"}
}