{
  "type": "Feature",
  "properties": {
    "iso:country":"US",
    "sg:address":"2341 Wroxton Rd",
    "sg:city":"Houston",
    "sg:classifiers":[
        {
            "category":"Professional",
            "subcategory":"Management & Consulting",
            "type":"Services"
        }
    ],
    "sg:phone":"+1 713 522 2188",
    "sg:postcode":"77005",
    "sg:province":"TX",
    "wof:name":"Drei Management",
    "wof:placetype":"venue"
},
  "geometry": {"coordinates":[-95.414215,29.724599],"type":"Point"}
}