{
  "type": "Feature",
  "properties": {
    "iso:country":"US",
    "sg:address":"13378 Preston Rd",
    "sg:city":"Dallas",
    "sg:classifiers":[
        {
            "category":"Food & Beverages",
            "subcategory":"Bakery",
            "type":"Retail Goods"
        }
    ],
    "sg:phone":"+1 972 385 9100",
    "sg:postcode":"75240",
    "sg:province":"TX",
    "sg:tags":[
        "sandwich"
    ],
    "sg:website":"jerseymikes.com",
    "wof:name":"Jersey Mike Sub",
    "wof:placetype":"venue"
},
  "geometry": {"coordinates":[-96.80347,32.929256],"type":"Point"}
}