{
  "type": "Feature",
  "properties": {
    "iso:country":"US",
    "sg:address":"105 Strickland",
    "sg:city":"Converse",
    "sg:classifiers":[
        {
            "category":"Autos & Motor Vehicles",
            "subcategory":"Automobile Sales",
            "type":"Retail Goods"
        }
    ],
    "sg:phone":"+1 210 659 4500",
    "sg:postcode":"78109",
    "sg:province":"TX",
    "sg:tags":[
        "car",
        "used"
    ],
    "wof:name":"Bob Hall Motors",
    "wof:placetype":"venue"
},
  "geometry": {"coordinates":[-98.315664,29.517547],"type":"Point"}
}