{
  "type": "Feature",
  "properties": {
    "iso:country":"US",
    "sg:address":"6321 Gold Ave",
    "sg:city":"Edinburg",
    "sg:classifiers":[
        {
            "category":"Professional",
            "type":"Services"
        }
    ],
    "sg:phone":"+1 956 316 0108",
    "sg:postcode":"78541",
    "sg:province":"TX",
    "sg:tags":[
        "equipment",
        "electrical"
    ],
    "wof:name":"Blue Star Security",
    "wof:placetype":"venue"
},
  "geometry": {"coordinates":[-98.143998,26.365558],"type":"Point"}
}