{
  "type": "Feature",
  "properties": {
    "iso:country":"US",
    "sg:address":"435 W Elizabeth St",
    "sg:city":"Brownsville",
    "sg:classifiers":[
        {
            "category":"Health Services",
            "subcategory":"Clinic",
            "type":"Services"
        }
    ],
    "sg:phone":"+1 956 541 0275",
    "sg:postcode":"78520",
    "sg:province":"TX",
    "sg:tags":[
        "home"
    ],
    "wof:name":"Tropical Home Health",
    "wof:placetype":"venue"
},
  "geometry": {"coordinates":[-97.510299,25.912264],"type":"Point"}
}