{
  "type": "Feature",
  "properties": {
    "iso:country":"US",
    "sg:address":"3021 Ramona Dr",
    "sg:city":"Fort Worth",
    "sg:classifiers":[
        {
            "category":"Building & Trades",
            "subcategory":"Plumbing",
            "type":"Services"
        }
    ],
    "sg:phone":"+1 817 244 6933",
    "sg:postcode":"76116",
    "sg:province":"TX",
    "sg:tags":[
        "mechanical",
        "contractor"
    ],
    "wof:name":"Bryan Mechanical",
    "wof:placetype":"venue"
},
  "geometry": {"coordinates":[-97.44482499999999,32.728957],"type":"Point"}
}