{
  "type": "Feature",
  "properties": {
    "iso:country":"US",
    "sg:address":"2310 Planters Row",
    "sg:city":"Sugar Land",
    "sg:classifiers":[
        {
            "category":"Building & Trades",
            "subcategory":"Plumbing",
            "type":"Services"
        }
    ],
    "sg:phone":"+1 281 980 2727",
    "sg:postcode":"77478",
    "sg:province":"TX",
    "sg:tags":[
        "contractor"
    ],
    "wof:name":"Absolute American Air Conditio",
    "wof:placetype":"venue"
},
  "geometry": {"coordinates":[-95.611473,29.596036],"type":"Point"}
}