{
  "type": "Feature",
  "properties": {
    "iso:country":"US",
    "sg:address":"13801 Ann Place",
    "sg:city":"Austin",
    "sg:classifiers":[
        {
            "category":"Building & Trades",
            "subcategory":"Construction",
            "type":"Services"
        }
    ],
    "sg:phone":"+1 512 990 2468",
    "sg:postcode":"78728",
    "sg:province":"TX",
    "sg:tags":[
        "contractor"
    ],
    "wof:name":"Jj and C Construction",
    "wof:placetype":"venue"
},
  "geometry": {"coordinates":[-97.673929,30.428688],"type":"Point"}
}