{
  "type": "Feature",
  "properties": {
    "iso:country":"US",
    "sg:address":"23365 US Highway 281 N",
    "sg:city":"San Antonio",
    "sg:classifiers":[
        {
            "category":"Retail",
            "subcategory":"Veterinary Services",
            "type":"Services"
        }
    ],
    "sg:phone":"+1 210 497 4449",
    "sg:postcode":"78258",
    "sg:province":"TX",
    "sg:tags":[
        "veterinarian"
    ],
    "wof:name":"Bulverde Bexar Veterinary Clinic",
    "wof:placetype":"venue"
},
  "geometry": {"coordinates":[-98.450401,29.661699],"type":"Point"}
}