{
  "type": "Feature",
  "properties": {
    "iso:country":"US",
    "sg:address":"3482 W 11th St",
    "sg:city":"Houston",
    "sg:classifiers":[
        {
            "category":"Professional",
            "type":"Services"
        }
    ],
    "sg:phone":"+1 713 880 8831",
    "sg:postcode":"77008",
    "sg:province":"TX",
    "sg:tags":[
        "establishment"
    ],
    "wof:name":"Joe Presswood Co",
    "wof:placetype":"venue"
},
  "geometry": {"coordinates":[-95.43674300000001,29.789153],"type":"Point"}
}