{
  "type": "Feature",
  "properties": {
    "iso:country":"US",
    "sg:address":"210 Morningside Dr",
    "sg:city":"Mexia",
    "sg:classifiers":[
        {
            "category":"Health Services",
            "subcategory":"Clinic",
            "type":"Services"
        }
    ],
    "sg:phone":"+1 254 472 0669",
    "sg:postcode":"76667",
    "sg:province":"TX",
    "wof:name":"Excalibur Health Assoc In",
    "wof:placetype":"venue"
},
  "geometry": {"coordinates":[-96.466009,31.678885],"type":"Point"}
}