{
  "type": "Feature",
  "properties": {
    "iso:country":"US",
    "sg:address":"1222 W Powell St",
    "sg:city":"Brownfield",
    "sg:classifiers":[
        {
            "category":"Freight",
            "type":"Transportation"
        }
    ],
    "sg:phone":"+1 806 637 9590",
    "sg:postcode":"79316",
    "sg:province":"TX",
    "sg:tags":[
        "operator",
        "local",
        "trucking"
    ],
    "wof:name":"Mireles Trucking",
    "wof:placetype":"venue"
},
  "geometry": {"coordinates":[-102.289638,33.181062],"type":"Point"}
}