{
  "type": "Feature",
  "properties": {
    "iso:country":"US",
    "sg:address":"2121 S Harwood St",
    "sg:city":"Dallas",
    "sg:classifiers":[
        {
            "category":"Manufacturing",
            "subcategory":"Printing",
            "type":"Manufacturing & Wholesale Goods"
        }
    ],
    "sg:phone":"+1 214 428 5111",
    "sg:postcode":"75215",
    "sg:province":"TX",
    "sg:tags":[
        "bookbinder"
    ],
    "sg:website":"www.printersbindery.com",
    "wof:name":"Printers Bindery Svc",
    "wof:placetype":"venue"
},
  "geometry": {"coordinates":[-96.78240099999999,32.77083],"type":"Point"}
}