{
  "type": "Feature",
  "properties": {
    "iso:country":"US",
    "sg:address":"1812 Deer Trl",
    "sg:city":"Floresville",
    "sg:classifiers":[
        {
            "category":"Professional",
            "subcategory":"Advertising",
            "type":"Services"
        }
    ],
    "sg:phone":"+1 830 216 4290",
    "sg:postcode":"78114",
    "sg:province":"TX",
    "sg:tags":[
        "counselor"
    ],
    "wof:name":"Ginger Gauthier & Assoc Inc",
    "wof:placetype":"venue"
},
  "geometry": {"coordinates":[-98.18830699999999,29.203754],"type":"Point"}
}