{
  "type": "Feature",
  "properties": {
    "iso:country":"US",
    "sg:address":"620 W Felix St",
    "sg:city":"Fort Worth",
    "sg:classifiers":[
        {
            "category":"Wholesale",
            "subcategory":"Machinery & Supplies",
            "type":"Manufacturing & Wholesale Goods"
        }
    ],
    "sg:phone":"+1 817 924 3360",
    "sg:postcode":"76115",
    "sg:province":"TX",
    "sg:tags":[
        "equipment",
        "safety",
        "clothing"
    ],
    "sg:website":"www.jlmatthews.com",
    "wof:name":"J L Matthews Co",
    "wof:placetype":"venue"
},
  "geometry": {"coordinates":[-97.329628,32.678134],"type":"Point"}
}