{
  "type": "Feature",
  "properties": {
    "iso:country":"US",
    "sg:address":"10495 Olympic Dr",
    "sg:city":"Dallas",
    "sg:classifiers":[
        {
            "category":"Social Services",
            "type":"Services"
        },
        {
            "category":"Shopping",
            "subcategory":"Used Merchandise",
            "type":"Retail Goods"
        },
        {
            "category":"Banks & Credit Unions",
            "subcategory":"Bank",
            "type":"Services"
        },
        {
            "category":"Shopping",
            "subcategory":"Thrift Store",
            "type":"Retail Goods"
        },
        {
            "category":"Organizations",
            "subcategory":"Non-profit Organization",
            "type":"Services"
        }
    ],
    "sg:phone":"+1 214 358 0094",
    "sg:postcode":"75220",
    "sg:province":"TX",
    "sg:tags":[
        "shop",
        "foundations-educational",
        "philanthropic",
        "research",
        "resale",
        "second",
        "hand",
        "furniture",
        "charity"
    ],
    "wof:name":"Goodwill Industries Of Dallas",
    "wof:placetype":"venue"
},
  "geometry": {"coordinates":[-96.887351,32.864467],"type":"Point"}
}