{
  "type": "Feature",
  "properties": {
    "iso:country":"US",
    "sg:address":"3425 Irving Ln",
    "sg:city":"Amarillo",
    "sg:classifiers":[
        {
            "category":"Professional",
            "subcategory":"Employment Agencies",
            "type":"Services"
        }
    ],
    "sg:phone":"+1 806 331 0390",
    "sg:postcode":"79121",
    "sg:province":"TX",
    "sg:tags":[
        "help",
        "supply"
    ],
    "wof:name":"At Your Aide",
    "wof:placetype":"venue"
},
  "geometry": {"coordinates":[-101.930215,35.174467],"type":"Point"}
}