{
  "type": "Feature",
  "properties": {
    "iso:country":"US",
    "sg:address":"25147 Co Rd 460",
    "sg:city":"Grand Saline",
    "sg:classifiers":[
        {
            "category":"Home & Garden",
            "subcategory":"Building Materials",
            "type":"Retail Goods"
        }
    ],
    "sg:phone":"+1 903 569 0035",
    "sg:postcode":"75140",
    "sg:province":"TX",
    "wof:name":"Harley John",
    "wof:placetype":"venue"
},
  "geometry": {"coordinates":[-95.57711999999999,32.627595],"type":"Point"}
}