{
  "type": "Feature",
  "properties": {
    "iso:country":"US",
    "sg:address":"328 Jasmine Ct",
    "sg:city":"Burleson",
    "sg:classifiers":[
        {
            "category":"Building & Trades",
            "subcategory":"Plumbing",
            "type":"Services"
        }
    ],
    "sg:phone":"+1 817 295 7877",
    "sg:postcode":"76028",
    "sg:province":"TX",
    "sg:tags":[
        "contractor",
        "mechanical"
    ],
    "wof:name":"Chrisco Services",
    "wof:placetype":"venue"
},
  "geometry": {"coordinates":[-97.32411,32.535771],"type":"Point"}
}