{
  "type": "Feature",
  "properties": {
    "iso:country":"US",
    "sg:address":"5410 Lake Trail Ct",
    "sg:city":"San Angelo",
    "sg:classifiers":[
        {
            "category":"Building & Trades",
            "subcategory":"Construction",
            "type":"Services"
        }
    ],
    "sg:phone":"+1 325 942 8642",
    "sg:postcode":"76904",
    "sg:province":"TX",
    "sg:tags":[
        "residential",
        "contractor"
    ],
    "wof:name":"Trollinger Enterprises",
    "wof:placetype":"venue"
},
  "geometry": {"coordinates":[-100.469601,31.404224],"type":"Point"}
}