{
  "type": "Feature",
  "properties": {
    "iso:country":"US",
    "sg:address":"47 Knob Hill Dr",
    "sg:city":"Little Elm",
    "sg:classifiers":[
        {
            "category":"Shopping",
            "subcategory":"Gifts & Souvenirs",
            "type":"Retail Goods"
        }
    ],
    "sg:phone":"+1 281 298 8993",
    "sg:postcode":"75068",
    "sg:province":"TX",
    "sg:tags":[
        "basket",
        "parcel"
    ],
    "wof:name":"Whimsical Gift Baskets",
    "wof:placetype":"venue"
},
  "geometry": {"coordinates":[-96.955208,33.179105],"type":"Point"}
}