{
  "type": "Feature",
  "properties": {
    "iso:country":"US",
    "sg:address":"10214 Georgibelle Dr",
    "sg:city":"Houston",
    "sg:classifiers":[
        {
            "category":"Building & Trades",
            "subcategory":"Construction",
            "type":"Services"
        }
    ],
    "sg:phone":"+1 713 468 1480",
    "sg:postcode":"77043",
    "sg:province":"TX",
    "sg:tags":[
        "utility",
        "contractor"
    ],
    "wof:name":"Absolute Underground Works",
    "wof:placetype":"venue"
},
  "geometry": {"coordinates":[-95.549702,29.787687],"type":"Point"}
}