{
  "type": "Feature",
  "properties": {
    "iso:country":"US",
    "sg:address":"23654 FM 1314",
    "sg:city":"Porter",
    "sg:classifiers":[
        {
            "category":"Professional",
            "subcategory":"Business Services",
            "type":"Services"
        }
    ],
    "sg:phone":"+1 281 354 4875",
    "sg:postcode":"77365",
    "sg:province":"TX",
    "sg:tags":[
        "paging",
        "answering"
    ],
    "wof:name":"Apollo III Answers",
    "wof:placetype":"venue"
},
  "geometry": {"coordinates":[-95.255912,30.105867],"type":"Point"}
}