{
  "type": "Feature",
  "properties": {
    "iso:country":"US",
    "sg:address":"1631 Highway 35 N",
    "sg:city":"Rockport",
    "sg:classifiers":[
        {
            "category":"Retail",
            "subcategory":"Laundry & Dry Cleaning",
            "type":"Services"
        }
    ],
    "sg:phone":"+1 361 790 8594",
    "sg:postcode":"78382",
    "sg:province":"TX",
    "sg:tags":[
        "cleaner",
        "rug",
        "carpet"
    ],
    "wof:name":"Chem-Dry",
    "wof:placetype":"venue"
},
  "geometry": {"coordinates":[-97.042519,28.040633],"type":"Point"}
}