{
  "type": "Feature",
  "properties": {
    "iso:country":"US",
    "sg:address":"2920 E Randol Mill Rd",
    "sg:city":"Arlington",
    "sg:classifiers":[
        {
            "category":"Utilities",
            "subcategory":"Refuse",
            "type":"Services"
        },
        {
            "category":"Wholesale",
            "subcategory":"Scrap",
            "type":"Manufacturing & Wholesale Goods"
        }
    ],
    "sg:phone":"+1 817 640 3111",
    "sg:postcode":"76011",
    "sg:province":"TX",
    "sg:tags":[
        "recycling",
        "center",
        "system"
    ],
    "wof:name":"Corrugated Services Inc",
    "wof:placetype":"venue"
},
  "geometry": {"coordinates":[-97.056489,32.748831],"type":"Point"}
}