{
  "type": "Feature",
  "properties": {
    "iso:country":"US",
    "sg:address":"1042 Carter St",
    "sg:city":"Amarillo",
    "sg:classifiers":[
        {
            "category":"Retail",
            "subcategory":"Photofinishing",
            "type":"Services"
        }
    ],
    "sg:phone":"+1 806 373 7033",
    "sg:postcode":"79104",
    "sg:province":"TX",
    "sg:tags":[
        "laboratory"
    ],
    "wof:name":"Wise Photo",
    "wof:placetype":"venue"
},
  "geometry": {"coordinates":[-101.781863,35.196858],"type":"Point"}
}