{
  "type": "Feature",
  "properties": {
    "iso:country":"US",
    "sg:address":"806 S 2nd St",
    "sg:city":"Abilene",
    "sg:classifiers":[
        {
            "category":"Freight",
            "type":"Transportation"
        }
    ],
    "sg:phone":"+1 325 676 7007",
    "sg:postcode":"79602",
    "sg:province":"TX",
    "sg:tags":[
        "trucking"
    ],
    "wof:name":"Dan-Vic Distribution Systems",
    "wof:placetype":"venue"
},
  "geometry": {"coordinates":[-99.73245900000001,32.447501],"type":"Point"}
}