{
  "type": "Feature",
  "properties": {
    "iso:country":"US",
    "sg:address":"2929 Allen Pkwy",
    "sg:city":"Houston",
    "sg:classifiers":[
        {
            "category":"Professional",
            "type":"Services"
        }
    ],
    "sg:phone":"+1 713 224 8000",
    "sg:postcode":"77019",
    "sg:province":"TX",
    "sg:tags":[
        "establishment"
    ],
    "wof:name":"Crispin Co",
    "wof:placetype":"venue"
},
  "geometry": {"coordinates":[-95.3969,29.761575],"type":"Point"}
}