{
  "type": "Feature",
  "properties": {
    "iso:country":"US",
    "sg:address":"6714 N New Braunfels Ave",
    "sg:city":"San Antonio",
    "sg:classifiers":[
        {
            "category":"Farming",
            "subcategory":"Livestock Farm",
            "type":"Manufacturing & Wholesale Goods"
        }
    ],
    "sg:phone":"+1 210 820 8202",
    "sg:postcode":"78209",
    "sg:province":"TX",
    "sg:tags":[
        "beef",
        "feedlot",
        "cattle"
    ],
    "wof:name":"Brokers Best",
    "wof:placetype":"venue"
},
  "geometry": {"coordinates":[-98.45924100000001,29.492131],"type":"Point"}
}