{
  "type": "Feature",
  "properties": {
    "iso:country":"US",
    "sg:address":"1307 Blanco Woods",
    "sg:city":"San Antonio",
    "sg:classifiers":[
        {
            "category":"Organizations",
            "subcategory":"Religious Organization",
            "type":"Services"
        }
    ],
    "sg:phone":"+1 210 492 8038",
    "sg:postcode":"78248",
    "sg:province":"TX",
    "wof:name":"Faith Presbyterian Church",
    "wof:placetype":"venue"
},
  "geometry": {"coordinates":[-98.513605,29.597953],"type":"Point"}
}