{
  "type": "Feature",
  "properties": {
    "iso:country":"US",
    "sg:address":"3410 Fordham Rd",
    "sg:city":"Dallas",
    "sg:classifiers":[
        {
            "category":"Real Estate",
            "subcategory":"Real Estate Operator",
            "type":"Services"
        }
    ],
    "sg:phone":"+1 214 376 6580",
    "sg:postcode":"75216",
    "sg:province":"TX",
    "sg:tags":[
        "apartment",
        "complex"
    ],
    "wof:name":"Hemmingway House Apartments",
    "wof:placetype":"venue"
},
  "geometry": {"coordinates":[-96.76658500000001,32.7141],"type":"Point"}
}