{
  "type": "Feature",
  "properties": {
    "iso:country":"US",
    "sg:address":"416 E Oak St",
    "sg:city":"Aledo",
    "sg:classifiers":[
        {
            "category":"Food & Beverages",
            "subcategory":"Specialty",
            "type":"Retail Goods"
        }
    ],
    "sg:phone":"+1 817 441 5062",
    "sg:postcode":"76008",
    "sg:province":"TX",
    "sg:tags":[
        "water",
        "bulk",
        "company"
    ],
    "wof:name":"Parker County Water",
    "wof:placetype":"venue"
},
  "geometry": {"coordinates":[-97.598258,32.694724],"type":"Point"}
}