{
  "type": "Feature",
  "properties": {
    "iso:country":"US",
    "sg:address":"3103 Estes Pkwy",
    "sg:city":"Longview",
    "sg:classifiers":[
        {
            "category":"Travel",
            "subcategory":"Hotels & Motels",
            "type":"Entertainment"
        }
    ],
    "sg:phone":"+1 903 758 1113",
    "sg:postcode":"75602",
    "sg:province":"TX",
    "sg:tags":[
        "operation"
    ],
    "wof:name":"Days Inn",
    "wof:placetype":"venue"
},
  "geometry": {"coordinates":[-94.722174,32.447411],"type":"Point"}
}