{
  "type": "Feature",
  "properties": {
    "iso:country":"US",
    "sg:address":"103 N 6th St",
    "sg:city":"Carrizo Springs",
    "sg:classifiers":[
        {
            "category":"Government",
            "subcategory":"Jail",
            "type":"Public Place"
        }
    ],
    "sg:phone":"+1 830 876 2218",
    "sg:postcode":"78834",
    "sg:province":"TX",
    "sg:tags":[
        "county",
        "govt",
        "institution"
    ],
    "wof:name":"Dimmit County Jail",
    "wof:placetype":"venue"
},
  "geometry": {"coordinates":[-99.86088700000001,28.522769],"type":"Point"}
}