{
  "type": "Feature",
  "properties": {
    "iso:country":"US",
    "sg:address":"132 Candice Dr",
    "sg:city":"Kerrville",
    "sg:classifiers":[
        {
            "category":"Shopping",
            "subcategory":"Gifts & Souvenirs",
            "type":"Retail Goods"
        }
    ],
    "sg:phone":"+1 830 896 0572",
    "sg:postcode":"78028",
    "sg:province":"TX",
    "wof:name":"Shindigstore Com",
    "wof:placetype":"venue"
},
  "geometry": {"coordinates":[-99.173638,30.070289],"type":"Point"}
}