{
  "type": "Feature",
  "properties": {
    "iso:country":"US",
    "sg:address":"7600 N Lamar Blvd",
    "sg:city":"Austin",
    "sg:classifiers":[
        {
            "category":"Food & Beverages",
            "subcategory":"Liquor & Beverages",
            "type":"Retail Goods"
        }
    ],
    "sg:phone":"+1 512 533 9200",
    "sg:postcode":"78752",
    "sg:province":"TX",
    "wof:name":"Spirits Of Austin",
    "wof:placetype":"venue"
},
  "geometry": {"coordinates":[-97.715464,30.343188],"type":"Point"}
}