{
  "type": "Feature",
  "properties": {
    "iso:country":"US",
    "sg:address":"713 S 6th Ave",
    "sg:city":"Mansfield",
    "sg:classifiers":[
        {
            "category":"Freight",
            "type":"Transportation"
        }
    ],
    "sg:phone":"+1 817 453 9852",
    "sg:postcode":"76063",
    "sg:province":"TX",
    "sg:tags":[
        "warehouse"
    ],
    "wof:name":"GAO Systems",
    "wof:placetype":"venue"
},
  "geometry": {"coordinates":[-97.15240900000001,32.549592],"type":"Point"}
}