{
  "type": "Feature",
  "properties": {
    "iso:country":"US",
    "sg:address":"2222 Washington Ln",
    "sg:city":"Waco",
    "sg:classifiers":[
        {
            "category":"Wholesale",
            "subcategory":"Machinery & Supplies",
            "type":"Manufacturing & Wholesale Goods"
        },
        {
            "category":"Home & Garden",
            "subcategory":"Garden Supply",
            "type":"Retail Goods"
        }
    ],
    "sg:phone":"+1 254 752 5341",
    "sg:postcode":"76708",
    "sg:province":"TX",
    "sg:tags":[
        "sprinkler"
    ],
    "wof:name":"Heart Texas Irrigation Systems",
    "wof:placetype":"venue"
},
  "geometry": {"coordinates":[-97.179962,31.624101],"type":"Point"}
}