{
  "type": "Feature",
  "properties": {
    "iso:country":"US",
    "sg:address":"5022 Collingwood Dr",
    "sg:city":"Garland",
    "sg:classifiers":[
        {
            "category":"Restaurant",
            "type":"Food & Drink"
        }
    ],
    "sg:phone":"+1 972 675 1294",
    "sg:postcode":"75043",
    "sg:province":"TX",
    "sg:tags":[
        "eating"
    ],
    "wof:name":"S & Cs Catering",
    "wof:placetype":"venue"
},
  "geometry": {"coordinates":[-96.60895600000001,32.85354],"type":"Point"}
}