{
  "type": "Feature",
  "properties": {
    "iso:country":"US",
    "sg:address":"13852 N Highway 183",
    "sg:city":"Austin",
    "sg:classifiers":[
        {
            "category":"Restaurant",
            "type":"Food & Drink"
        }
    ],
    "sg:menulink":"http://www.allmenus.com/tx/georgetown-round-rock/15094-saccones/menu/",
    "sg:phone":"+1 512 257 1200",
    "sg:postcode":"78750",
    "sg:province":"TX",
    "sg:tags":[
        "american",
        "pizza"
    ],
    "wof:name":"Saccone's",
    "wof:placetype":"venue"
},
  "geometry": {"coordinates":[-97.796938,30.466846],"type":"Point"}
}