{
  "type": "Feature",
  "properties": {
    "iso:country":"US",
    "sg:address":"1120 S Capital of Texas Hwy Bldg 3",
    "sg:city":"Austin",
    "sg:classifiers":[
        {
            "category":"Professional",
            "subcategory":"Computer Services",
            "type":"Services"
        }
    ],
    "sg:phone":"+1 512 442 2222",
    "sg:postcode":"78746",
    "sg:province":"TX",
    "sg:tags":[
        "repair"
    ],
    "sg:website":"www.sigmasolutions.com",
    "wof:name":"Sigma Solutions",
    "wof:placetype":"venue"
},
  "geometry": {"coordinates":[-97.82513,30.282454],"type":"Point"}
}