{
  "type": "Feature",
  "properties": {
    "iso:country":"US",
    "sg:address":"7122 Boone Rd",
    "sg:city":"Houston",
    "sg:classifiers":[
        {
            "category":"Autos & Motor Vehicles",
            "subcategory":"Automobile Sales",
            "type":"Retail Goods"
        }
    ],
    "sg:phone":"+1 281 983 0745",
    "sg:postcode":"77072",
    "sg:province":"TX",
    "sg:tags":[
        "car",
        "dealer"
    ],
    "wof:name":"Deluxe Auto Sales & Body",
    "wof:placetype":"venue"
},
  "geometry": {"coordinates":[-95.57539,29.699118],"type":"Point"}
}