{
  "type": "Feature",
  "properties": {
    "iso:country":"US",
    "sg:address":"6406 N I H 35",
    "sg:city":"Austin",
    "sg:classifiers":[
        {
            "category":"Personal",
            "subcategory":"Tanning Parlor",
            "type":"Services"
        }
    ],
    "sg:phone":"+1 512 451 5125",
    "sg:postcode":"78752",
    "sg:province":"TX",
    "wof:name":"Sun-Lite Tanning Center",
    "wof:placetype":"venue"
},
  "geometry": {"coordinates":[-97.69380200000001,30.3307],"type":"Point"}
}