{
  "type": "Feature",
  "properties": {
    "iso:country":"US",
    "sg:address":"3209 Toler Rd",
    "sg:city":"Rowlett",
    "sg:classifiers":[
        {
            "category":"Professional",
            "subcategory":"Business Services",
            "type":"Services"
        }
    ],
    "sg:phone":"+1 972 463 9033",
    "sg:postcode":"75089",
    "sg:province":"TX",
    "wof:name":"Gdp Auctioneer Services",
    "wof:placetype":"venue"
},
  "geometry": {"coordinates":[-96.570205,32.926109],"type":"Point"}
}