{
  "type": "Feature",
  "properties": {
    "iso:country":"US",
    "sg:address":"4306 Western Oak St",
    "sg:city":"Nacogdoches",
    "sg:classifiers":[
        {
            "category":"Professional",
            "subcategory":"Accounting & Tax Preparation",
            "type":"Services"
        }
    ],
    "sg:phone":"+1 936 462 7844",
    "sg:postcode":"75964",
    "sg:province":"TX",
    "sg:tags":[
        "billing"
    ],
    "wof:name":"Physicians Management Svc",
    "wof:placetype":"venue"
},
  "geometry": {"coordinates":[-94.68441199999999,31.566943],"type":"Point"}
}