{
  "type": "Feature",
  "properties": {
    "iso:country":"US",
    "sg:address":"207 Cheyenne Run",
    "sg:city":"Hallsville",
    "sg:classifiers":[
        {
            "category":"Health Services",
            "subcategory":"Health Practitioner",
            "type":"Services"
        }
    ],
    "sg:phone":"+1 903 668 4985",
    "sg:postcode":"75650",
    "sg:province":"TX",
    "sg:tags":[
        "therapist",
        "physical"
    ],
    "wof:name":"Healing Hands Rehab Svc",
    "wof:placetype":"venue"
},
  "geometry": {"coordinates":[-94.59160799999999,32.511311],"type":"Point"}
}