{
  "type": "Feature",
  "properties": {
    "iso:country":"US",
    "sg:address":"2621 Centenary St",
    "sg:city":"Houston",
    "sg:classifiers":[
        {
            "category":"Professional",
            "subcategory":"Management & Consulting",
            "type":"Services"
        }
    ],
    "sg:phone":"+1 713 218 9525",
    "sg:postcode":"77005",
    "sg:province":"TX",
    "sg:tags":[
        "development",
        "transfer",
        "product",
        "technology"
    ],
    "wof:name":"Apogee Advisors LLC",
    "wof:placetype":"venue"
},
  "geometry": {"coordinates":[-95.419838,29.710314],"type":"Point"}
}