{
  "type": "Feature",
  "properties": {
    "iso:country":"US",
    "sg:address":"605 W 18th St",
    "sg:city":"Austin",
    "sg:classifiers":[
        {
            "category":"Education",
            "subcategory":"Special Training",
            "type":"Public Place"
        }
    ],
    "sg:phone":"+1 512 478 3038",
    "sg:postcode":"78701",
    "sg:province":"TX",
    "sg:tags":[
        "instruction",
        "music"
    ],
    "sg:website":"www.fivefacts.com",
    "wof:name":"Satellite Studio",
    "wof:placetype":"venue"
},
  "geometry": {"coordinates":[-97.745221,30.281463],"type":"Point"}
}