{
  "type": "Feature",
  "properties": {
    "iso:country":"US",
    "sg:address":"4347 W Northwest Hwy",
    "sg:city":"Dallas",
    "sg:classifiers":[
        {
            "category":"Personal",
            "type":"Services"
        }
    ],
    "sg:phone":"+1 214 987 0790",
    "sg:postcode":"75220",
    "sg:province":"TX",
    "sg:tags":[
        "sewing",
        "alteration"
    ],
    "wof:name":"John's Tailors",
    "wof:placetype":"venue"
},
  "geometry": {"coordinates":[-96.83575,32.864021],"type":"Point"}
}