{
  "type": "Feature",
  "properties": {
    "iso:country":"US",
    "sg:address":"1820 Edna St",
    "sg:city":"Arlington",
    "sg:classifiers":[
        {
            "category":"Professional",
            "subcategory":"Business Services",
            "type":"Services"
        }
    ],
    "sg:phone":"+1 817 274 0499",
    "sg:postcode":"76010",
    "sg:province":"TX",
    "wof:name":"RPM Services",
    "wof:placetype":"venue"
},
  "geometry": {"coordinates":[-97.081062,32.734338],"type":"Point"}
}