{
  "type": "Feature",
  "properties": {
    "iso:country":"US",
    "sg:address":"14 Farington Way",
    "sg:city":"Spring",
    "sg:classifiers":[
        {
            "category":"Banks & Credit Unions",
            "subcategory":"Financial Services",
            "type":"Services"
        }
    ],
    "sg:phone":"+1 281 296 2255",
    "sg:postcode":"77382",
    "sg:province":"TX",
    "sg:tags":[
        "investor"
    ],
    "wof:name":"J & D RE Investments LLC",
    "wof:placetype":"venue"
},
  "geometry": {"coordinates":[-95.54732199999999,30.185913],"type":"Point"}
}