{
  "type": "Feature",
  "properties": {
    "iso:country":"US",
    "sg:address":"320 S Wilcox St",
    "sg:city":"Rockdale",
    "sg:classifiers":[
        {
            "category":"Wholesale",
            "subcategory":"Hardware",
            "type":"Manufacturing & Wholesale Goods"
        }
    ],
    "sg:phone":"+1 512 446 3481",
    "sg:postcode":"76567",
    "sg:province":"TX",
    "sg:tags":[
        "nut",
        "bolt"
    ],
    "wof:name":"Anixter",
    "wof:placetype":"venue"
},
  "geometry": {"coordinates":[-97.00349799999999,30.649186],"type":"Point"}
}