{
  "type": "Feature",
  "properties": {
    "iso:country":"US",
    "sg:address":"2400 Old South Dr",
    "sg:city":"Richmond",
    "sg:classifiers":[
        {
            "category":"Real Estate",
            "subcategory":"Real Estate Services",
            "type":"Services"
        },
        {
            "category":"Real Estate",
            "subcategory":"Real Estate Operator",
            "type":"Services"
        }
    ],
    "sg:phone":"+1 281 342 9414",
    "sg:postcode":"77406",
    "sg:province":"TX",
    "sg:tags":[
        "vacancy",
        "apartment",
        "rental",
        "finder",
        "listing"
    ],
    "sg:website":"http://www.dogwood-creek.com",
    "wof:name":"South Grand Apartments",
    "wof:placetype":"venue"
},
  "geometry": {"coordinates":[-95.734077,29.63077],"type":"Point"}
}