{
  "type": "Feature",
  "properties": {
    "iso:country":"US",
    "sg:address":"200 S Ware Rd",
    "sg:city":"Mcallen",
    "sg:classifiers":[
        {
            "category":"Freight",
            "type":"Transportation"
        }
    ],
    "sg:phone":"+1 956 631 6888",
    "sg:postcode":"78501",
    "sg:province":"TX",
    "sg:tags":[
        "commercial",
        "storage"
    ],
    "wof:name":"Best Little Warehouse of Texas",
    "wof:placetype":"venue"
},
  "geometry": {"coordinates":[-98.262711,26.201209],"type":"Point"}
}