{
  "type": "Feature",
  "properties": {
    "iso:country":"US",
    "sg:address":"311 E 16th St",
    "sg:city":"Mt Pleasant",
    "sg:classifiers":[
        {
            "category":"Insurance",
            "subcategory":"Insurance Agent",
            "type":"Services"
        }
    ],
    "sg:phone":"+1 903 575 1199",
    "sg:postcode":"75455",
    "sg:province":"TX",
    "wof:name":"Dominguez Insurance Agency",
    "wof:placetype":"venue"
},
  "geometry": {"coordinates":[-94.96775,33.171775],"type":"Point"}
}