{
  "type": "Feature",
  "properties": {
    "iso:country":"US",
    "sg:address":"1232 E Griffin Pkwy",
    "sg:city":"Mission",
    "sg:classifiers":[
        {
            "category":"Retail",
            "subcategory":"Auto Repair",
            "type":"Services"
        }
    ],
    "sg:phone":"+1 956 585 8257",
    "sg:postcode":"78572",
    "sg:province":"TX",
    "sg:tags":[
        "general"
    ],
    "wof:name":"Jl Quintanilla Truck Serv",
    "wof:placetype":"venue"
},
  "geometry": {"coordinates":[-98.307491,26.227475],"type":"Point"}
}