{
  "type": "Feature",
  "properties": {
    "iso:country":"US",
    "sg:address":"6903 Petre Dr",
    "sg:city":"Houston",
    "sg:classifiers":[
        {
            "category":"Personal",
            "subcategory":"Beauty Salon",
            "type":"Services"
        }
    ],
    "sg:phone":"+1 713 697 5937",
    "sg:postcode":"77076",
    "sg:province":"TX",
    "sg:tags":[
        "treatment",
        "skin"
    ],
    "wof:name":"Derma Shield",
    "wof:placetype":"venue"
},
  "geometry": {"coordinates":[-95.38753800000001,29.862798],"type":"Point"}
}