{
  "type": "Feature",
  "properties": {
    "iso:country":"US",
    "sg:address":"8000 Westglen Dr",
    "sg:city":"Houston",
    "sg:classifiers":[
        {
            "category":"Wholesale",
            "subcategory":"Vending Machines",
            "type":"Manufacturing & Wholesale Goods"
        }
    ],
    "sg:phone":"+1 713 923 5985",
    "sg:postcode":"77063",
    "sg:province":"TX",
    "wof:name":"Big State Vending Co",
    "wof:placetype":"venue"
},
  "geometry": {"coordinates":[-95.506271,29.724769],"type":"Point"}
}