{
  "type": "Feature",
  "properties": {
    "iso:country":"US",
    "sg:address":"27401 State Hwy 345",
    "sg:city":"San Benito",
    "sg:classifiers":[
        {
            "category":"Real Estate",
            "subcategory":"Real Estate Operator",
            "type":"Services"
        }
    ],
    "sg:phone":"+1 956 399 8960",
    "sg:postcode":"78586",
    "sg:province":"TX",
    "sg:tags":[
        "mobile",
        "home",
        "community"
    ],
    "wof:name":"Pan American Mobile Home & Rv",
    "wof:placetype":"venue"
},
  "geometry": {"coordinates":[-97.60812300000001,26.161082],"type":"Point"}
}