{
  "type": "Feature",
  "properties": {
    "iso:country":"US",
    "sg:address":"2318 Foxcroft Ln",
    "sg:city":"Arlington",
    "sg:classifiers":[
        {
            "category":"Building & Trades",
            "subcategory":"Landscaping Services",
            "type":"Services"
        }
    ],
    "sg:phone":"+1 817 557 1501",
    "sg:postcode":"76014",
    "sg:province":"TX",
    "sg:tags":[
        "lawn",
        "maintenance",
        "grounds"
    ],
    "wof:name":"Beaver Trim Lawn Svc",
    "wof:placetype":"venue"
},
  "geometry": {"coordinates":[-97.070284,32.685675],"type":"Point"}
}