{
  "type": "Feature",
  "properties": {
    "iso:country":"US",
    "sg:address":"303 Alamo Ave",
    "sg:city":"Lake Dallas",
    "sg:classifiers":[
        {
            "category":"Building & Trades",
            "subcategory":"Construction",
            "type":"Services"
        }
    ],
    "sg:phone":"+1 940 497 2226",
    "sg:postcode":"75065",
    "sg:province":"TX",
    "sg:tags":[
        "marking",
        "maintenance",
        "parking"
    ],
    "wof:name":"Lake Dallas Street Dept",
    "wof:placetype":"venue"
},
  "geometry": {"coordinates":[-97.026945,33.11926],"type":"Point"}
}