{
  "type": "Feature",
  "properties": {
    "iso:country":"US",
    "sg:address":"2811 McKinney Ave",
    "sg:city":"Dallas",
    "sg:classifiers":[
        {
            "category":"Professional",
            "subcategory":"Business Services",
            "type":"Services"
        }
    ],
    "sg:phone":"+1 214 220 9003",
    "sg:postcode":"75204",
    "sg:province":"TX",
    "wof:name":"R Austin & Sons USA Inc",
    "wof:placetype":"venue"
},
  "geometry": {"coordinates":[-96.80096500000001,32.799626],"type":"Point"}
}