{
  "type": "Feature",
  "properties": {
    "iso:country":"US",
    "sg:address":"2919 Surrey Trail Ln",
    "sg:city":"Katy",
    "sg:classifiers":[
        {
            "category":"Building & Trades",
            "subcategory":"Construction",
            "type":"Services"
        }
    ],
    "sg:phone":"+1 281 579 7781",
    "sg:postcode":"77450",
    "sg:province":"TX",
    "sg:tags":[
        "house"
    ],
    "wof:name":"Rocky Mountain Steel Pier",
    "wof:placetype":"venue"
},
  "geometry": {"coordinates":[-95.730065,29.739012],"type":"Point"}
}