{
  "type": "Feature",
  "properties": {
    "iso:country":"US",
    "sg:address":"1614 Maple St",
    "sg:city":"Irving",
    "sg:classifiers":[
        {
            "category":"Wholesale",
            "subcategory":"Construction Materials",
            "type":"Manufacturing & Wholesale Goods"
        }
    ],
    "sg:phone":"+1 972 438 5533",
    "sg:postcode":"75060",
    "sg:province":"TX",
    "sg:tags":[
        "concrete",
        "form"
    ],
    "wof:name":"Reeder Concrete Inc",
    "wof:placetype":"venue"
},
  "geometry": {"coordinates":[-96.936909,32.797695],"type":"Point"}
}