{
  "type": "Feature",
  "properties": {
    "iso:country":"US",
    "sg:address":"561 Broadway Ave",
    "sg:city":"Winnie",
    "sg:classifiers":[
        {
            "category":"Home & Garden",
            "subcategory":"Hardware",
            "type":"Retail Goods"
        }
    ],
    "sg:phone":"+1 409 296 2561",
    "sg:postcode":"77665",
    "sg:province":"TX",
    "wof:name":"Farm & Home Supply Inc",
    "wof:placetype":"venue"
},
  "geometry": {"coordinates":[-94.376358,29.820601],"type":"Point"}
}