{
  "type": "Feature",
  "properties": {
    "iso:country":"US",
    "sg:address":"25043 Toutant Beauregard Rd",
    "sg:city":"San Antonio",
    "sg:classifiers":[
        {
            "category":"Professional",
            "type":"Services"
        }
    ],
    "sg:phone":"+1 830 981 8892",
    "sg:postcode":"78255",
    "sg:province":"TX",
    "wof:name":"Delavan Services Inc",
    "wof:placetype":"venue"
},
  "geometry": {"coordinates":[-98.68380999999999,29.676156],"type":"Point"}
}