{
  "type": "Feature",
  "properties": {
    "iso:country":"US",
    "sg:address":"3810 Ash Glade Ct",
    "sg:city":"Humble",
    "sg:classifiers":[
        {
            "category":"Banks & Credit Unions",
            "subcategory":"Bank",
            "type":"Services"
        }
    ],
    "sg:phone":"+1 281 360 2123",
    "sg:postcode":"77345",
    "sg:province":"TX",
    "sg:tags":[
        "mortgage"
    ],
    "wof:name":"Sotkahomeloanscom",
    "wof:placetype":"venue"
},
  "geometry": {"coordinates":[-95.176208,30.074594],"type":"Point"}
}