{
  "type": "Feature",
  "properties": {
    "iso:country":"US",
    "sg:address":"2801 Wolflin Ave",
    "sg:city":"Amarillo",
    "sg:classifiers":[
        {
            "category":"Real Estate",
            "subcategory":"Real Estate Services",
            "type":"Services"
        },
        {
            "category":"Real Estate",
            "subcategory":"Real Estate Agent",
            "type":"Services"
        }
    ],
    "sg:phone":"+1 806 331 1104",
    "sg:postcode":"79109",
    "sg:province":"TX",
    "sg:tags":[
        "buyer",
        "broker"
    ],
    "wof:name":"Latham Hometown Realty",
    "wof:placetype":"venue"
},
  "geometry": {"coordinates":[-101.867807,35.192848],"type":"Point"}
}