{
  "type": "Feature",
  "properties": {
    "iso:country":"US",
    "sg:address":"19018 Sandridge Ct",
    "sg:city":"Houston",
    "sg:classifiers":[
        {
            "category":"Manufacturing",
            "subcategory":"Toys & Sporting Goods",
            "type":"Manufacturing & Wholesale Goods"
        }
    ],
    "sg:phone":"+1 281 923 6862",
    "sg:postcode":"77049",
    "sg:province":"TX",
    "sg:tags":[
        "mfg"
    ],
    "wof:name":"Caddie Connnections",
    "wof:placetype":"venue"
},
  "geometry": {"coordinates":[-95.085521,29.828819],"type":"Point"}
}