{
  "type": "Feature",
  "properties": {
    "iso:country":"US",
    "sg:address":"1659 W Durango Blvd",
    "sg:city":"San Antonio",
    "sg:classifiers":[
        {
            "category":"Wholesale",
            "subcategory":"Stationery",
            "type":"Manufacturing & Wholesale Goods"
        }
    ],
    "sg:phone":"+1 210 494 5098",
    "sg:postcode":"78207",
    "sg:province":"TX",
    "sg:tags":[
        "supply"
    ],
    "wof:name":"Chase Business Forms",
    "wof:placetype":"venue"
},
  "geometry": {"coordinates":[-98.515517,29.422849],"type":"Point"}
}