{
  "type": "Feature",
  "properties": {
    "iso:country":"US",
    "sg:address":"22477 Murrell Rd",
    "sg:city":"Hockley",
    "sg:classifiers":[
        {
            "category":"Professional",
            "type":"Services"
        }
    ],
    "sg:phone":"+1 936 931 1780",
    "sg:postcode":"77447",
    "sg:province":"TX",
    "wof:name":"Energy Is LLC",
    "wof:placetype":"venue"
},
  "geometry": {"coordinates":[-95.813298,30.084521],"type":"Point"}
}