{
  "type": "Feature",
  "properties": {
    "iso:country":"US",
    "sg:address":"5100 Canyongate Dr",
    "sg:city":"Plano",
    "sg:classifiers":[
        {
            "category":"Professional",
            "type":"Services"
        }
    ],
    "sg:phone":"+1 972 618 7224",
    "sg:postcode":"75093",
    "sg:province":"TX",
    "wof:name":"Sundayonline Co Inc",
    "wof:placetype":"venue"
},
  "geometry": {"coordinates":[-96.800355,33.028833],"type":"Point"}
}