{
  "type": "Feature",
  "properties": {
    "iso:country":"US",
    "sg:address":"1014 N Fielder Rd",
    "sg:city":"Arlington",
    "sg:classifiers":[
        {
            "category":"Social Services",
            "subcategory":"Child Care",
            "type":"Services"
        }
    ],
    "sg:phone":"+1 817 277 7279",
    "sg:postcode":"76012",
    "sg:province":"TX",
    "sg:tags":[
        "day"
    ],
    "wof:name":"Childrens World Lrng Ctr 017",
    "wof:placetype":"venue"
},
  "geometry": {"coordinates":[-97.131782,32.749024],"type":"Point"}
}