{
  "type": "Feature",
  "properties": {
    "iso:country":"US",
    "sg:address":"2211 S Cooper St",
    "sg:city":"Arlington",
    "sg:classifiers":[
        {
            "category":"Communications",
            "subcategory":"Film & Video Production",
            "type":"Services"
        },
        {
            "category":"Shopping",
            "subcategory":"Music",
            "type":"Retail Goods"
        },
        {
            "category":"Shopping",
            "subcategory":"Books",
            "type":"Retail Goods"
        }
    ],
    "sg:phone":"+1 817 860 5247",
    "sg:postcode":"76013",
    "sg:province":"TX",
    "sg:tags":[
        "used",
        "rare",
        "tapes",
        "record",
        "vintage",
        "dealers-used",
        "records",
        "tapes-wholesale",
        "cd's",
        "store",
        "manufacturer"
    ],
    "sg:website":"http://www.halfpricebooks.com",
    "wof:name":"Half Price Books, Records & Magazines",
    "wof:placetype":"venue"
},
  "geometry": {"coordinates":[-97.116679,32.707452],"type":"Point"}
}