{
  "type": "Feature",
  "properties": {
    "iso:country":"US",
    "sg:address":"222 Grover Ave",
    "sg:city":"Lubbock",
    "sg:classifiers":[
        {
            "category":"Banks & Credit Unions",
            "subcategory":"Financial Services",
            "type":"Services"
        }
    ],
    "sg:phone":"+1 806 795 3674",
    "sg:postcode":"79416",
    "sg:province":"TX",
    "sg:tags":[
        "company",
        "holding"
    ],
    "wof:name":"Crystal Holdings LLC",
    "wof:placetype":"venue"
},
  "geometry": {"coordinates":[-101.94456700000001,33.59414],"type":"Point"}
}