{
  "type": "Feature",
  "properties": {
    "iso:country":"US",
    "sg:address":"3614 S Shepherd Dr",
    "sg:city":"Houston",
    "sg:classifiers":[
        {
            "category":"Recreation",
            "type":"Entertainment"
        }
    ],
    "sg:phone":"+1 713 660 9599",
    "sg:postcode":"77098",
    "sg:province":"TX",
    "sg:tags":[
        "aquarium"
    ],
    "wof:name":"Aquarium Environments Inc",
    "wof:placetype":"venue"
},
  "geometry": {"coordinates":[-95.410753,29.733542],"type":"Point"}
}