{
  "type": "Feature",
  "properties": {
    "iso:country":"US",
    "sg:address":"10646 Gulfdale St",
    "sg:city":"San Antonio",
    "sg:classifiers":[
        {
            "category":"Wholesale",
            "subcategory":"Machinery & Supplies",
            "type":"Manufacturing & Wholesale Goods"
        },
        {
            "category":"Autos & Motor Vehicles",
            "subcategory":"Automobile Sales",
            "type":"Retail Goods"
        }
    ],
    "sg:phone":"+1 210 340 6658",
    "sg:postcode":"78216",
    "sg:province":"TX",
    "sg:tags":[
        "equipment",
        "aircraft",
        "parts"
    ],
    "wof:name":"Commercial Imexport Inc",
    "wof:placetype":"venue"
},
  "geometry": {"coordinates":[-98.488758,29.535882],"type":"Point"}
}