{
  "type": "Feature",
  "properties": {
    "iso:country":"US",
    "sg:address":"804 Russell Palmer Rd",
    "sg:city":"Humble",
    "sg:classifiers":[
        {
            "category":"Education",
            "subcategory":"Dance Studio",
            "type":"Public Place"
        }
    ],
    "sg:phone":"+1 281 348 7802",
    "sg:postcode":"77339",
    "sg:province":"TX",
    "sg:tags":[
        "instruction",
        "dancing"
    ],
    "wof:name":"Call To Glory",
    "wof:placetype":"venue"
},
  "geometry": {"coordinates":[-95.227268,30.064879],"type":"Point"}
}