{
  "type": "Feature",
  "properties": {
    "iso:country":"US",
    "sg:address":"701 W Parker Rd",
    "sg:city":"Plano",
    "sg:classifiers":[
        {
            "category":"Restaurant",
            "type":"Food & Drink"
        }
    ],
    "sg:phone":"+1 469 467 8025",
    "sg:postcode":"75023",
    "sg:province":"TX",
    "wof:name":"Frankie's Cafe",
    "wof:placetype":"venue"
},
  "geometry": {"coordinates":[-96.709093,33.040998],"type":"Point"}
}