{
  "type": "Feature",
  "properties": {
    "iso:country":"US",
    "sg:address":"6005 Lindy Ln",
    "sg:city":"Fort Worth",
    "sg:classifiers":[
        {
            "category":"Building & Trades",
            "subcategory":"Construction",
            "type":"Services"
        }
    ],
    "sg:phone":"+1 817 514 3930",
    "sg:postcode":"76148",
    "sg:province":"TX",
    "sg:tags":[
        "floor",
        "laying",
        "contractor"
    ],
    "wof:name":"Resilient Floor Co",
    "wof:placetype":"venue"
},
  "geometry": {"coordinates":[-97.250049,32.863081],"type":"Point"}
}