{
  "type": "Feature",
  "properties": {
    "iso:country":"US",
    "sg:address":"1409 Hailey St",
    "sg:city":"Sweetwater",
    "sg:classifiers":[
        {
            "category":"Personal",
            "subcategory":"Beauty Salon",
            "type":"Services"
        }
    ],
    "sg:phone":"+1 325 235 4342",
    "sg:postcode":"79556",
    "sg:province":"TX",
    "wof:name":"Mirror Image",
    "wof:placetype":"venue"
},
  "geometry": {"coordinates":[-100.401011,32.483377],"type":"Point"}
}