{
  "type": "Feature",
  "properties": {
    "iso:country":"US",
    "sg:address":"109 E Grayson St",
    "sg:city":"Llano",
    "sg:classifiers":[
        {
            "category":"Shopping",
            "subcategory":"Used Merchandise",
            "type":"Retail Goods"
        }
    ],
    "sg:phone":"+1 325 247 4701",
    "sg:postcode":"78643",
    "sg:province":"TX",
    "wof:name":"Antique Station",
    "wof:placetype":"venue"
},
  "geometry": {"coordinates":[-98.675521,30.755615],"type":"Point"}
}