{
  "type": "Feature",
  "properties": {
    "iso:country":"US",
    "sg:address":"11331 Bayou Place Ln",
    "sg:city":"Houston",
    "sg:classifiers":[
        {
            "category":"Local Transit",
            "type":"Transportation"
        }
    ],
    "sg:phone":"+1 281 530 6538",
    "sg:postcode":"77099",
    "sg:province":"TX",
    "sg:tags":[
        "passenger"
    ],
    "wof:name":"Young Lu",
    "wof:placetype":"venue"
},
  "geometry": {"coordinates":[-95.578794,29.659355],"type":"Point"}
}