{
  "type": "Feature",
  "properties": {
    "iso:country":"US",
    "sg:address":"3701 E Saunders St",
    "sg:city":"Laredo",
    "sg:classifiers":[
        {
            "category":"Autos & Motor Vehicles",
            "subcategory":"Automobile Sales",
            "type":"Retail Goods"
        }
    ],
    "sg:phone":"+1 956 523 8888",
    "sg:postcode":"78041",
    "sg:province":"TX",
    "sg:tags":[
        "car",
        "dealer"
    ],
    "sg:website":"www.paulyoungautomall.com",
    "wof:name":"Paul Young Auto Mall",
    "wof:placetype":"venue"
},
  "geometry": {"coordinates":[-99.457763,27.529226],"type":"Point"}
}