{
  "type": "Feature",
  "properties": {
    "iso:country":"US",
    "sg:address":"10107 Falcon Ridge Dr",
    "sg:city":"Austin",
    "sg:classifiers":[
        {
            "category":"Shopping",
            "subcategory":"Gifts & Souvenirs",
            "type":"Retail Goods"
        }
    ],
    "sg:phone":"+1 512 347 7002",
    "sg:postcode":"78733",
    "sg:province":"TX",
    "wof:name":"Dos Hermanas",
    "wof:placetype":"venue"
},
  "geometry": {"coordinates":[-97.878506,30.331494],"type":"Point"}
}