{
  "type": "Feature",
  "properties": {
    "iso:country":"US",
    "sg:address":"945 Woodlawn Dr",
    "sg:city":"Corpus Christi",
    "sg:classifiers":[
        {
            "category":"Government",
            "subcategory":"Police Station",
            "type":"Public Place"
        }
    ],
    "sg:phone":"+1 361 980 8018",
    "sg:postcode":"78412",
    "sg:province":"TX",
    "sg:tags":[
        "officer"
    ],
    "wof:name":"David Rene Martinez",
    "wof:placetype":"venue"
},
  "geometry": {"coordinates":[-97.34930900000001,27.708752],"type":"Point"}
}