{
  "type": "Feature",
  "properties": {
    "iso:country":"US",
    "sg:address":"1637 Harding St",
    "sg:city":"Wichita Falls",
    "sg:classifiers":[
        {
            "category":"Organizations",
            "subcategory":"Religious Organization",
            "type":"Services"
        }
    ],
    "sg:phone":"+1 940 767 1566",
    "sg:postcode":"76301",
    "sg:province":"TX",
    "sg:tags":[
        "church"
    ],
    "wof:name":"Church Of The Living God",
    "wof:placetype":"venue"
},
  "geometry": {"coordinates":[-98.44565900000001,33.913906],"type":"Point"}
}