{
  "type": "Feature",
  "properties": {
    "iso:country":"US",
    "sg:address":"2110 Pine River Dr",
    "sg:city":"Kingwood",
    "sg:classifiers":[
        {
            "category":"Real Estate",
            "subcategory":"Surveying",
            "type":"Services"
        }
    ],
    "sg:phone":"+1 281 358 2463",
    "sg:postcode":"77339",
    "sg:province":"TX",
    "sg:tags":[
        "geophysicist"
    ],
    "wof:name":"Mcqueen & Mcqueen",
    "wof:placetype":"venue"
},
  "geometry": {"coordinates":[-95.2197,30.051302],"type":"Point"}
}