{
  "type": "Feature",
  "properties": {
    "iso:country":"US",
    "sg:address":"1610 Danbury Dr",
    "sg:city":"Garland",
    "sg:classifiers":[
        {
            "category":"Professional",
            "type":"Services"
        }
    ],
    "sg:phone":"+1 972 840 6044",
    "sg:postcode":"75040",
    "sg:province":"TX",
    "wof:name":"Luong Nguyen Inc",
    "wof:placetype":"venue"
},
  "geometry": {"coordinates":[-96.618032,32.898489],"type":"Point"}
}