{
  "type": "Feature",
  "properties": {
    "iso:country":"US",
    "sg:address":"1501 I- 20 E",
    "sg:city":"Arlington",
    "sg:classifiers":[
        {
            "category":"Autos & Motor Vehicles",
            "subcategory":"Automobile Sales",
            "type":"Retail Goods"
        }
    ],
    "sg:phone":"+1 817 466 3300",
    "sg:postcode":"76018",
    "sg:province":"TX",
    "sg:tags":[
        "car",
        "dealer"
    ],
    "wof:name":"Tommy Manuel Chrysler Jeep Inc",
    "wof:placetype":"venue"
},
  "geometry": {"coordinates":[-97.082646,32.67869],"type":"Point"}
}