{
  "type": "Feature",
  "properties": {
    "iso:country":"US",
    "sg:address":"13434 Greenbriar Dr",
    "sg:city":"Sugar Land",
    "sg:classifiers":[
        {
            "category":"Retail",
            "subcategory":"Repair Shop",
            "type":"Services"
        }
    ],
    "sg:phone":"+1 281 565 9383",
    "sg:postcode":"77478",
    "sg:province":"TX",
    "wof:name":"Optics Maid EZ",
    "wof:placetype":"venue"
},
  "geometry": {"coordinates":[-95.619547,29.649343],"type":"Point"}
}