{
  "type": "Feature",
  "properties": {
    "iso:country":"US",
    "sg:address":"2421 Glenda Ln",
    "sg:city":"Dallas",
    "sg:classifiers":[
        {
            "category":"Building & Trades",
            "subcategory":"Construction",
            "type":"Services"
        }
    ],
    "sg:phone":"+1 972 241 0116",
    "sg:postcode":"75229",
    "sg:province":"TX",
    "sg:tags":[
        "glass",
        "glazing",
        "contractor"
    ],
    "wof:name":"Universal Glass Co",
    "wof:placetype":"venue"
},
  "geometry": {"coordinates":[-96.89462,32.889801],"type":"Point"}
}