{
  "type": "Feature",
  "properties": {
    "iso:country":"US",
    "sg:address":"350 S 9th St",
    "sg:city":"Slaton",
    "sg:classifiers":[
        {
            "category":"Autos & Motor Vehicles",
            "subcategory":"Fuel & Gas Station",
            "type":"Retail Goods"
        },
        {
            "category":"Retail",
            "subcategory":"Auto Repair",
            "type":"Services"
        }
    ],
    "sg:phone":"+1 806 828 5700",
    "sg:postcode":"79364",
    "sg:province":"TX",
    "sg:tags":[
        "repairing",
        "automobile",
        "station",
        "gasoline"
    ],
    "wof:name":"Cecil's Phillips 66",
    "wof:placetype":"venue"
},
  "geometry": {"coordinates":[-101.64335199999999,33.4351],"type":"Point"}
}