{
  "type": "Feature",
  "properties": {
    "iso:country":"US",
    "sg:address":"7557 Harwin Dr",
    "sg:city":"Houston",
    "sg:classifiers":[
        {
            "category":"Professional",
            "subcategory":"Computer Services",
            "type":"Services"
        }
    ],
    "sg:phone":"+1 713 706 4050",
    "sg:postcode":"77036",
    "sg:province":"TX",
    "sg:tags":[
        "programing",
        "custom"
    ],
    "wof:name":"Enterprise Alliance Systems",
    "wof:placetype":"venue"
},
  "geometry": {"coordinates":[-95.517337,29.717567],"type":"Point"}
}