{
  "type": "Feature",
  "properties": {
    "iso:country":"US",
    "sg:address":"408 W 8th St",
    "sg:city":"Dallas",
    "sg:classifiers":[
        {
            "category":"Organizations",
            "subcategory":"Community Association",
            "type":"Services"
        }
    ],
    "sg:phone":"+1 214 943 0566",
    "sg:postcode":"75208",
    "sg:province":"TX",
    "sg:tags":[
        "environmental",
        "org"
    ],
    "wof:name":"National Fish & Wildlife Found",
    "wof:placetype":"venue"
},
  "geometry": {"coordinates":[-96.830079,32.747987],"type":"Point"}
}