{
  "type": "Feature",
  "properties": {
    "iso:country":"US",
    "sg:address":"810 Campbell",
    "sg:city":"Lockhart",
    "sg:classifiers":[
        {
            "category":"Home & Garden",
            "subcategory":"Garden Supply",
            "type":"Retail Goods"
        }
    ],
    "sg:phone":"+1 512 398 9451",
    "sg:postcode":"78644",
    "sg:province":"TX",
    "wof:name":"Texas Mountain Flora",
    "wof:placetype":"venue"
},
  "geometry": {"coordinates":[-97.678045,29.877396],"type":"Point"}
}