{
  "type": "Feature",
  "properties": {
    "iso:country":"US",
    "sg:address":"7302 Boggess Rd",
    "sg:city":"Houston",
    "sg:classifiers":[
        {
            "category":"Arts & Performance",
            "subcategory":"Theater",
            "type":"Entertainment"
        }
    ],
    "sg:phone":"+1 713 635 8506",
    "sg:postcode":"77016",
    "sg:province":"TX",
    "wof:name":"Mayes Enterprise",
    "wof:placetype":"venue"
},
  "geometry": {"coordinates":[-95.29396199999999,29.861461],"type":"Point"}
}