{
  "type": "Feature",
  "properties": {
    "iso:country":"US",
    "sg:address":"630 Co Rd 664",
    "sg:city":"Devine",
    "sg:classifiers":[
        {
            "category":"Shopping",
            "subcategory":"Gifts & Souvenirs",
            "type":"Retail Goods"
        }
    ],
    "sg:phone":"+1 830 663 5646",
    "sg:postcode":"78016",
    "sg:province":"TX",
    "wof:name":"Blossoms of Lytle",
    "wof:placetype":"venue"
},
  "geometry": {"coordinates":[-98.905405,29.18712],"type":"Point"}
}