{
  "type": "Feature",
  "properties": {
    "iso:country":"US",
    "sg:address":"CoHabitat Dallas 2517 Thomas Avenue",
    "sg:city":"Dallas",
    "sg:classifiers":[
        {
            "category":"Professional",
            "subcategory":"Computer Services",
            "type":"Services"
        }
    ],
    "sg:phone":"+1 214 351 5200",
    "sg:postcode":"75201",
    "sg:province":"TX",
    "sg:tags":[
        "travel",
        "social",
        "itinerary",
        "dashboard",
        "mint",
        "tripit",
        "dopplr",
        "loyalty",
        "point",
        "tracker"
    ],
    "sg:website":"http://www.traxo.com",
    "wof:name":"Traxo",
    "wof:placetype":"venue"
},
  "geometry": {"coordinates":[-96.80224200000001,32.792316],"type":"Point"}
}