{
  "type": "Feature",
  "properties": {
    "iso:country":"US",
    "sg:address":"13009 Winding Creek Rd",
    "sg:city":"Austin",
    "sg:classifiers":[
        {
            "category":"Building & Trades",
            "subcategory":"Construction",
            "type":"Services"
        }
    ],
    "sg:phone":"+1 512 288 4940",
    "sg:postcode":"78736",
    "sg:province":"TX",
    "sg:tags":[
        "home",
        "builder"
    ],
    "sg:website":"www.themaroneycompany.com",
    "wof:name":"Maroney Co",
    "wof:placetype":"venue"
},
  "geometry": {"coordinates":[-97.990494,30.233869],"type":"Point"}
}