{
  "type": "Feature",
  "properties": {
    "iso:country":"US",
    "sg:address":"121 W Mall Dr",
    "sg:city":"Corsicana",
    "sg:classifiers":[
        {
            "category":"Organizations",
            "subcategory":"Religious Organization",
            "type":"Services"
        }
    ],
    "sg:phone":"+1 903 641 0172",
    "sg:postcode":"75110",
    "sg:province":"TX",
    "sg:tags":[
        "church"
    ],
    "wof:name":"Living Word Christian Fellowsh",
    "wof:placetype":"venue"
},
  "geometry": {"coordinates":[-96.46830300000001,32.100176],"type":"Point"}
}