{
  "type": "Feature",
  "properties": {
    "iso:country":"US",
    "sg:address":"6306 82nd St",
    "sg:city":"Lubbock",
    "sg:classifiers":[
        {
            "category":"Manufacturing",
            "subcategory":"Rubber & Plastics",
            "type":"Manufacturing & Wholesale Goods"
        },
        {
            "category":"Autos & Motor Vehicles",
            "subcategory":"Auto Supplies",
            "type":"Retail Goods"
        }
    ],
    "sg:phone":"+1 806 698 0055",
    "sg:postcode":"79424",
    "sg:province":"TX",
    "sg:tags":[
        "wheel",
        "tires-wholesale",
        "tire",
        "manufacturer"
    ],
    "sg:website":"http://www.discounttire.com/dtcs/home.do?utm_source=YellowPages&utm_medium=iyp&utm_campaign=YellowPagesIYPOrg",
    "wof:name":"Discount Tire",
    "wof:placetype":"venue"
},
  "geometry": {"coordinates":[-101.95579499999999,33.519749],"type":"Point"}
}