{
  "type": "Feature",
  "properties": {
    "iso:country":"US",
    "sg:address":"2116 Spring Hollow Path",
    "sg:city":"Round Rock",
    "sg:classifiers":[
        {
            "category":"Banks & Credit Unions",
            "subcategory":"Bank",
            "type":"Services"
        }
    ],
    "sg:phone":"+1 512 248 9669",
    "sg:postcode":"78681",
    "sg:province":"TX",
    "sg:tags":[
        "mortgage"
    ],
    "wof:name":"CNB Delta Mortgage",
    "wof:placetype":"venue"
},
  "geometry": {"coordinates":[-97.706281,30.512903],"type":"Point"}
}