{
  "type": "Feature",
  "properties": {
    "iso:country":"US",
    "sg:address":"9010 Royal Ln",
    "sg:city":"Dallas",
    "sg:classifiers":[
        {
            "category":"Home & Garden",
            "subcategory":"Household Appliances",
            "type":"Retail Goods"
        }
    ],
    "sg:phone":"+1 972 456 2777",
    "sg:postcode":"75231",
    "sg:province":"TX",
    "wof:name":"Outokumpu Heatcraft Usa LLC",
    "wof:placetype":"venue"
},
  "geometry": {"coordinates":[-96.72983600000001,32.894429],"type":"Point"}
}