{
  "type": "Feature",
  "properties": {
    "iso:country":"US",
    "sg:address":"600 W Northwest Hwy",
    "sg:city":"Grapevine",
    "sg:classifiers":[
        {
            "category":"Banks & Credit Unions",
            "subcategory":"Investment Brokerage",
            "type":"Services"
        },
        {
            "category":"Professional",
            "subcategory":"Management & Consulting",
            "type":"Services"
        }
    ],
    "sg:phone":"+1 817 310 0700",
    "sg:postcode":"76051",
    "sg:province":"TX",
    "sg:tags":[
        "advisory",
        "financial"
    ],
    "wof:name":"Supreme Financial Services LLC",
    "wof:placetype":"venue"
},
  "geometry": {"coordinates":[-97.083411,32.941069],"type":"Point"}
}