{
  "type": "Feature",
  "properties": {
    "iso:country":"US",
    "sg:address":"3201 Cherry Ridge St",
    "sg:city":"San Antonio",
    "sg:classifiers":[
        {
            "category":"Insurance",
            "subcategory":"Insurance Agent",
            "type":"Services"
        }
    ],
    "sg:phone":"+1 210 366 4800",
    "sg:postcode":"78230",
    "sg:province":"TX",
    "sg:tags":[
        "broker"
    ],
    "wof:name":"The Brokerage Store Inc",
    "wof:placetype":"venue"
},
  "geometry": {"coordinates":[-98.548092,29.508483],"type":"Point"}
}