{
  "type": "Feature",
  "properties": {
    "iso:country":"US",
    "sg:address":"310 Main St",
    "sg:city":"Spring",
    "sg:classifiers":[
        {
            "category":"Shopping",
            "subcategory":"Gifts & Souvenirs",
            "type":"Retail Goods"
        }
    ],
    "sg:phone":"+1 281 651 1360",
    "sg:postcode":"77373",
    "sg:province":"TX",
    "wof:name":"World Mirage",
    "wof:placetype":"venue"
},
  "geometry": {"coordinates":[-95.420863,30.0792],"type":"Point"}
}