{
  "type": "Feature",
  "properties": {
    "iso:country":"US",
    "sg:address":"27015 Buttercup Ln",
    "sg:city":"Magnolia",
    "sg:classifiers":[
        {
            "category":"Professional",
            "subcategory":"Management & Consulting",
            "type":"Services"
        }
    ],
    "sg:phone":"+1 281 259 7875",
    "sg:postcode":"77354",
    "sg:province":"TX",
    "wof:name":"Steelhammer Marketing",
    "wof:placetype":"venue"
},
  "geometry": {"coordinates":[-95.64242299999999,30.167813],"type":"Point"}
}