{
  "type": "Feature",
  "properties": {
    "iso:country":"US",
    "sg:address":"5414 Chevy Chase Dr",
    "sg:city":"Corpus Christi",
    "sg:classifiers":[
        {
            "category":"Restaurant",
            "type":"Food & Drink"
        }
    ],
    "sg:phone":"+1 361 993 7596",
    "sg:postcode":"78412",
    "sg:province":"TX",
    "sg:tags":[
        "eating"
    ],
    "wof:name":"Sheps Chicken Shack",
    "wof:placetype":"venue"
},
  "geometry": {"coordinates":[-97.34817200000001,27.724888],"type":"Point"}
}