{
  "type": "Feature",
  "properties": {
    "iso:country":"US",
    "sg:address":"105 S Ward Dr",
    "sg:city":"Longview",
    "sg:classifiers":[
        {
            "category":"Manufacturing",
            "subcategory":"Signs",
            "type":"Manufacturing & Wholesale Goods"
        }
    ],
    "sg:phone":"+1 903 295 7446",
    "sg:postcode":"75604",
    "sg:province":"TX",
    "sg:tags":[
        "advertising",
        "specialty"
    ],
    "wof:name":"Sign Man",
    "wof:placetype":"venue"
},
  "geometry": {"coordinates":[-94.782141,32.503292],"type":"Point"}
}