{
  "type": "Feature",
  "properties": {
    "iso:country":"US",
    "sg:address":"6025 Edgemoor Dr",
    "sg:city":"Houston",
    "sg:classifiers":[
        {
            "category":"Manufacturing",
            "subcategory":"Printing",
            "type":"Manufacturing & Wholesale Goods"
        }
    ],
    "sg:phone":"+1 713 666 9990",
    "sg:postcode":"77081",
    "sg:province":"TX",
    "sg:tags":[
        "printer"
    ],
    "wof:name":"Gulf Coast Grafix",
    "wof:placetype":"venue"
},
  "geometry": {"coordinates":[-95.48729899999999,29.703625],"type":"Point"}
}