{
  "type": "Feature",
  "properties": {
    "iso:country":"US",
    "sg:address":"901 N Lee Ave",
    "sg:city":"Odessa",
    "sg:classifiers":[
        {
            "category":"Education",
            "subcategory":"School",
            "type":"Public Place"
        }
    ],
    "sg:phone":"+1 432 332 3453",
    "sg:postcode":"79761",
    "sg:province":"TX",
    "wof:name":"Austin Elementary School",
    "wof:placetype":"venue"
},
  "geometry": {"coordinates":[-102.373857,31.852342],"type":"Point"}
}