{
  "type": "Feature",
  "properties": {
    "iso:country":"US",
    "sg:address":"485 North St",
    "sg:city":"Vidor",
    "sg:classifiers":[
        {
            "category":"Travel",
            "subcategory":"Travel Agent",
            "type":"Entertainment"
        },
        {
            "category":"Autos & Motor Vehicles",
            "subcategory":"Recreational Vehicle Sales",
            "type":"Retail Goods"
        }
    ],
    "sg:phone":"+1 409 769 6623",
    "sg:postcode":"77662",
    "sg:province":"TX",
    "sg:tags":[
        "home",
        "trailer"
    ],
    "wof:name":"Hodge Casino Slot",
    "wof:placetype":"venue"
},
  "geometry": {"coordinates":[-93.954994,30.14397],"type":"Point"}
}