{
  "type": "Feature",
  "properties": {
    "iso:country":"US",
    "sg:address":"929 Melbourne Rd",
    "sg:city":"Hurst",
    "sg:classifiers":[
        {
            "category":"Shopping",
            "subcategory":"Clothing, Apparel, & Fashions",
            "type":"Retail Goods"
        }
    ],
    "sg:phone":"+1 817 284 6443",
    "sg:postcode":"76053",
    "sg:province":"TX",
    "wof:name":"Catherines Plus Sizes",
    "wof:placetype":"venue"
},
  "geometry": {"coordinates":[-97.198342,32.826418],"type":"Point"}
}