{
  "type": "Feature",
  "properties": {
    "iso:country":"US",
    "sg:address":"110 S 8th St",
    "sg:city":"Slaton",
    "sg:classifiers":[
        {
            "category":"Manufacturing",
            "subcategory":"Printing",
            "type":"Manufacturing & Wholesale Goods"
        }
    ],
    "sg:phone":"+1 806 828 4952",
    "sg:postcode":"79364",
    "sg:province":"TX",
    "sg:tags":[
        "lithographic",
        "commercial"
    ],
    "wof:name":"Slat-Co Printing",
    "wof:placetype":"venue"
},
  "geometry": {"coordinates":[-101.642763,33.437904],"type":"Point"}
}