{
  "type": "Feature",
  "properties": {
    "iso:country":"US",
    "sg:address":"1925 FM 466",
    "sg:city":"Seguin",
    "sg:classifiers":[
        {
            "category":"Shopping",
            "subcategory":"Jewelry",
            "type":"Retail Goods"
        }
    ],
    "sg:phone":"+1 830 303 8554",
    "sg:postcode":"78155",
    "sg:province":"TX",
    "sg:tags":[
        "jeweler"
    ],
    "wof:name":"Valdez's Jewelry",
    "wof:placetype":"venue"
},
  "geometry": {"coordinates":[-97.930857,29.545559],"type":"Point"}
}