{
  "type": "Feature",
  "properties": {
    "iso:country":"US",
    "sg:address":"19503 Old Burnet Rd",
    "sg:city":"Jonestown",
    "sg:classifiers":[
        {
            "category":"Real Estate",
            "subcategory":"Real Estate Agent",
            "type":"Services"
        }
    ],
    "sg:phone":"+1 512 267 4000",
    "sg:postcode":"78645",
    "sg:province":"TX",
    "sg:website":"www.northshoreatthehollows.com",
    "wof:name":"Hollows",
    "wof:placetype":"venue"
},
  "geometry": {"coordinates":[-97.959671,30.462924],"type":"Point"}
}