{
  "type": "Feature",
  "properties": {
    "iso:country":"US",
    "sg:address":"4606 New West Rd",
    "sg:city":"Pasadena",
    "sg:classifiers":[
        {
            "category":"Manufacturing",
            "subcategory":"Chemicals & Compounds",
            "type":"Manufacturing & Wholesale Goods"
        }
    ],
    "sg:phone":"+1 281 474 3689",
    "sg:postcode":"77507",
    "sg:province":"TX",
    "sg:tags":[
        "chemicals-wholesale",
        "manufacturer"
    ],
    "sg:website":"http://www.harcroschem.com",
    "wof:name":"Harcros Chemicals Inc",
    "wof:placetype":"venue"
},
  "geometry": {"coordinates":[-95.093163,29.646008],"type":"Point"}
}