{
  "type": "Feature",
  "properties": {
    "iso:country":"US",
    "sg:address":"703 N 3rd St",
    "sg:city":"Abilene",
    "sg:classifiers":[
        {
            "category":"Shopping",
            "subcategory":"Gifts & Souvenirs",
            "type":"Retail Goods"
        }
    ],
    "sg:phone":"+1 325 690 1080",
    "sg:postcode":"79601",
    "sg:province":"TX",
    "sg:tags":[
        "shop"
    ],
    "wof:name":"Tassels Trims & Treasures",
    "wof:placetype":"venue"
},
  "geometry": {"coordinates":[-99.729045,32.451201],"type":"Point"}
}