{
  "type": "Feature",
  "properties": {
    "iso:country":"US",
    "sg:address":"15895 Ridgecroft Rd",
    "sg:city":"Houston",
    "sg:classifiers":[
        {
            "category":"Real Estate",
            "subcategory":"Real Estate Agent",
            "type":"Services"
        }
    ],
    "sg:phone":"+1 281 835 6058",
    "sg:postcode":"77053",
    "sg:province":"TX",
    "sg:tags":[
        "management",
        "property"
    ],
    "wof:name":"Heritage Homes",
    "wof:placetype":"venue"
},
  "geometry": {"coordinates":[-95.448402,29.5902],"type":"Point"}
}