{
  "type": "Feature",
  "properties": {
    "iso:country":"US",
    "sg:address":"14 Christi Ln",
    "sg:city":"Krum",
    "sg:classifiers":[
        {
            "category":"Wholesale",
            "subcategory":"Computers",
            "type":"Manufacturing & Wholesale Goods"
        }
    ],
    "sg:phone":"+1 940 482 1788",
    "sg:postcode":"76249",
    "sg:province":"TX",
    "sg:tags":[
        "website",
        "re",
        "design",
        "hosting",
        "troubleshooting"
    ],
    "wof:name":"Krum Computer Medics",
    "wof:placetype":"venue"
},
  "geometry": {"coordinates":[-97.232438,33.262982],"type":"Point"}
}