{
  "type": "Feature",
  "properties": {
    "iso:country":"US",
    "sg:address":"10010 Broadway",
    "sg:city":"San Antonio",
    "sg:classifiers":[
        {
            "category":"Real Estate",
            "subcategory":"Real Estate Operator",
            "type":"Services"
        }
    ],
    "sg:phone":"+1 210 826 8635",
    "sg:postcode":"78217",
    "sg:province":"TX",
    "sg:tags":[
        "building",
        "apartment"
    ],
    "wof:name":"Woodlands Apts",
    "wof:placetype":"venue"
},
  "geometry": {"coordinates":[-98.45152400000001,29.529677],"type":"Point"}
}