{
  "type": "Feature",
  "properties": {
    "iso:country":"US",
    "sg:address":"4804 Sadler St",
    "sg:city":"Houston",
    "sg:classifiers":[
        {
            "category":"Restaurant",
            "type":"Food & Drink"
        }
    ],
    "sg:phone":"+1 713 635 9233",
    "sg:postcode":"77016",
    "sg:province":"TX",
    "sg:tags":[
        "eating"
    ],
    "wof:name":"Barretts Catering",
    "wof:placetype":"venue"
},
  "geometry": {"coordinates":[-95.31893100000001,29.834841],"type":"Point"}
}