{
  "type": "Feature",
  "properties": {
    "iso:country":"US",
    "sg:address":"3710 Rawlins St",
    "sg:city":"Dallas",
    "sg:classifiers":[
        {
            "category":"Professional",
            "subcategory":"Lawyer & Legal Services",
            "type":"Services"
        }
    ],
    "sg:phone":"+1 214 969 0100",
    "sg:postcode":"75219",
    "sg:province":"TX",
    "wof:name":"Denton & Associates",
    "wof:placetype":"venue"
},
  "geometry": {"coordinates":[-96.80570400000001,32.810642],"type":"Point"}
}