{
  "type": "Feature",
  "properties": {
    "iso:country":"US",
    "sg:address":"314 Old Hwy 183",
    "sg:city":"Cedar Park",
    "sg:classifiers":[
        {
            "category":"Home & Garden",
            "subcategory":"Home Furnishings",
            "type":"Retail Goods"
        }
    ],
    "sg:phone":"+1 512 331 0299",
    "sg:postcode":"78613",
    "sg:province":"TX",
    "sg:tags":[
        "upholstery",
        "fabric"
    ],
    "wof:name":"Madison's Interiors",
    "wof:placetype":"venue"
},
  "geometry": {"coordinates":[-97.82067000000001,30.506033],"type":"Point"}
}