{
  "type": "Feature",
  "properties": {
    "iso:country":"US",
    "sg:address":"318 Singh St",
    "sg:city":"El Paso",
    "sg:classifiers":[
        {
            "category":"Building & Trades",
            "subcategory":"Electrical",
            "type":"Services"
        }
    ],
    "sg:phone":"+1 915 860 1948",
    "sg:postcode":"79907",
    "sg:province":"TX",
    "sg:tags":[
        "electric",
        "contractor"
    ],
    "wof:name":"Masters Electric",
    "wof:placetype":"venue"
},
  "geometry": {"coordinates":[-106.32486,31.685128],"type":"Point"}
}