{
  "type": "Feature",
  "properties": {
    "iso:country":"US",
    "sg:address":"117 E Main Ave",
    "sg:city":"Round Rock",
    "sg:classifiers":[
        {
            "category":"Social Services",
            "subcategory":"Child Care",
            "type":"Services"
        },
        {
            "category":"Personal",
            "subcategory":"Beauty Salon",
            "type":"Services"
        }
    ],
    "sg:phone":"+1 512 310 1114",
    "sg:postcode":"78664",
    "sg:province":"TX",
    "sg:tags":[
        "day"
    ],
    "wof:name":"Envy Salon & Day Spa",
    "wof:placetype":"venue"
},
  "geometry": {"coordinates":[-97.677887,30.508748],"type":"Point"}
}