{
  "type": "Feature",
  "properties": {
    "iso:country":"US",
    "sg:address":"1700 Pacific Ave Ste 2700",
    "sg:city":"Dallas",
    "sg:classifiers":[
        {
            "category":"Professional",
            "subcategory":"Lawyer & Legal Services",
            "type":"Services"
        }
    ],
    "sg:phone":"+1 214 658 1900",
    "sg:postcode":"75201",
    "sg:province":"TX",
    "sg:tags":[
        "litigation",
        "attorney",
        "business",
        "practice",
        "tort",
        "plan",
        "real estate",
        "law"
    ],
    "sg:website":"http://www.hoaf.com",
    "wof:name":"Henry Oddo Austin & Fletcher PC",
    "wof:placetype":"venue"
},
  "geometry": {"coordinates":[-96.7976,32.7826],"type":"Point"}
}