{
  "type": "Feature",
  "properties": {
    "iso:country":"US",
    "sg:address":"704 Quietwood Dr",
    "sg:city":"Dallas",
    "sg:classifiers":[
        {
            "category":"Restaurant",
            "type":"Food & Drink"
        }
    ],
    "sg:phone":"+1 972 557 0523",
    "sg:postcode":"75253",
    "sg:province":"TX",
    "wof:name":"Kiss My Ribs BBQ",
    "wof:placetype":"venue"
},
  "geometry": {"coordinates":[-96.59824500000001,32.701865],"type":"Point"}
}