{
  "type": "Feature",
  "properties": {
    "iso:country":"US",
    "sg:address":"12250 Lake June Rd",
    "sg:city":"Mesquite",
    "sg:classifiers":[
        {
            "category":"Shopping",
            "subcategory":"Shoes",
            "type":"Retail Goods"
        }
    ],
    "sg:phone":"+1 972 286 5828",
    "sg:postcode":"75180",
    "sg:province":"TX",
    "sg:tags":[
        "store"
    ],
    "wof:name":"Payless ShoeSource",
    "wof:placetype":"venue"
},
  "geometry": {"coordinates":[-96.615973,32.733835],"type":"Point"}
}