{
  "type": "Feature",
  "properties": {
    "iso:country":"US",
    "sg:address":"3200 S Lancaster Rd",
    "sg:city":"Dallas",
    "sg:classifiers":[
        {
            "category":"Social Services",
            "type":"Services"
        }
    ],
    "sg:phone":"+1 214 670 0506",
    "sg:postcode":"75216",
    "sg:province":"TX",
    "sg:tags":[
        "administrative"
    ],
    "wof:name":"Social Services- Child Care",
    "wof:placetype":"venue"
},
  "geometry": {"coordinates":[-96.80210099999999,32.708349],"type":"Point"}
}