{
  "type": "Feature",
  "properties": {
    "iso:country":"US",
    "sg:address":"4501 Magnolia Cove Dr",
    "sg:city":"Kingwood",
    "sg:classifiers":[
        {
            "category":"Real Estate",
            "subcategory":"Real Estate Services",
            "type":"Services"
        },
        {
            "category":"Building & Trades",
            "subcategory":"Cleaning & Sanitation",
            "type":"Services"
        }
    ],
    "sg:phone":"+1 281 360 7700",
    "sg:postcode":"77345",
    "sg:province":"TX",
    "sg:tags":[
        "maintenance",
        "cleaners-interior"
    ],
    "wof:name":"F M Facility Maintenance",
    "wof:placetype":"venue"
},
  "geometry": {"coordinates":[-95.17340900000001,30.032619],"type":"Point"}
}