{
  "type": "Feature",
  "properties": {
    "iso:country":"US",
    "sg:address":"8132 Kirby Dr",
    "sg:city":"Houston",
    "sg:classifiers":[
        {
            "category":"Shopping",
            "subcategory":"Shoes",
            "type":"Retail Goods"
        }
    ],
    "sg:phone":"+1 713 661 6090",
    "sg:postcode":"77246",
    "sg:province":"TX",
    "sg:tags":[
        "store"
    ],
    "wof:name":"Payless Shoesource",
    "wof:placetype":"venue"
},
  "geometry": {"coordinates":[-95.412611,29.690544],"type":"Point"}
}