{
  "type": "Feature",
  "properties": {
    "iso:country":"US",
    "sg:address":"12627 Roesler Rd",
    "sg:city":"Needville",
    "sg:classifiers":[
        {
            "category":"Retail",
            "subcategory":"Car Wash",
            "type":"Services"
        }
    ],
    "sg:phone":"+1 979 793 6014",
    "sg:postcode":"77461",
    "sg:province":"TX",
    "sg:tags":[
        "carwash"
    ],
    "wof:name":"Lewis Enterprise Enviro",
    "wof:placetype":"venue"
},
  "geometry": {"coordinates":[-95.80963300000001,29.382995],"type":"Point"}
}