{
  "type": "Feature",
  "properties": {
    "iso:country":"US",
    "sg:address":"15720 Twin Cove Dr",
    "sg:city":"Frisco",
    "sg:classifiers":[
        {
            "category":"Real Estate",
            "subcategory":"Real Estate Operator",
            "type":"Services"
        }
    ],
    "sg:phone":"+1 972 678 1901",
    "sg:postcode":"75035",
    "sg:province":"TX",
    "sg:tags":[
        "mobile",
        "home",
        "site"
    ],
    "wof:name":"Red Rock Home Solutions LLC",
    "wof:placetype":"venue"
},
  "geometry": {"coordinates":[-96.736707,33.134379],"type":"Point"}
}