{
  "type": "Feature",
  "properties": {
    "iso:country":"US",
    "sg:address":"1801 Sonoma Cove",
    "sg:city":"Leander",
    "sg:classifiers":[
        {
            "category":"Professional",
            "subcategory":"Computer Services",
            "type":"Services"
        }
    ],
    "sg:phone":"+1 512 528 8990",
    "sg:postcode":"78641",
    "sg:province":"TX",
    "sg:tags":[
        "datum"
    ],
    "wof:name":"Data Processing",
    "wof:placetype":"venue"
},
  "geometry": {"coordinates":[-97.83855800000001,30.556569],"type":"Point"}
}