{
  "type": "Feature",
  "properties": {
    "iso:country":"US",
    "sg:address":"5709 Kempson Dr",
    "sg:city":"Austin",
    "sg:classifiers":[
        {
            "category":"Health Services",
            "subcategory":"Health Practitioner",
            "type":"Services"
        }
    ],
    "sg:phone":"+1 512 248 9429",
    "sg:postcode":"78735",
    "sg:province":"TX",
    "sg:tags":[
        "nutritionist"
    ],
    "sg:website":"www.haustinnutrition.com",
    "wof:name":"Heart of Austin Nutrition",
    "wof:placetype":"venue"
},
  "geometry": {"coordinates":[-97.874921,30.250495],"type":"Point"}
}