{
  "type": "Feature",
  "properties": {
    "iso:country":"US",
    "sg:address":"1415 Cherie Brook Dr",
    "sg:city":"Goliad",
    "sg:classifiers":[
        {
            "category":"Retail",
            "subcategory":"Repair Shop",
            "type":"Services"
        }
    ],
    "sg:phone":"+1 361 645 1721",
    "sg:postcode":"77963",
    "sg:province":"TX",
    "wof:name":"Billy Boy Enterprises",
    "wof:placetype":"venue"
},
  "geometry": {"coordinates":[-97.39299800000001,28.682349],"type":"Point"}
}