{
  "type": "Feature",
  "properties": {
    "iso:country":"US",
    "sg:address":"300 N Reagan St",
    "sg:city":"West",
    "sg:classifiers":[
        {
            "category":"Professional",
            "subcategory":"Detective & Security Services",
            "type":"Services"
        }
    ],
    "sg:phone":"+1 254 826 5113",
    "sg:postcode":"76691",
    "sg:province":"TX",
    "sg:tags":[
        "car",
        "investigator"
    ],
    "wof:name":"Lassetter & Associates",
    "wof:placetype":"venue"
},
  "geometry": {"coordinates":[-97.09349400000001,31.804495],"type":"Point"}
}