{
  "type": "Feature",
  "properties": {
    "iso:country":"US",
    "sg:address":"1302 N Texas Blvd",
    "sg:city":"Weslaco",
    "sg:classifiers":[
        {
            "category":"Restaurant",
            "type":"Food & Drink"
        }
    ],
    "sg:menulink":"http://www.allmenus.com/tx/southeast-hidalgo/70655-pizza-hut/menu/",
    "sg:phone":"+1 956 969 1133",
    "sg:postcode":"78596",
    "sg:province":"TX",
    "sg:tags":[
        "american",
        "pizza"
    ],
    "wof:name":"PIZZA HUT",
    "wof:placetype":"venue"
},
  "geometry": {"coordinates":[-97.99090099999999,26.174611],"type":"Point"}
}