{
  "type": "Feature",
  "properties": {
    "iso:country":"US",
    "sg:address":"3101 Beale St",
    "sg:city":"Waco",
    "sg:classifiers":[
        {
            "category":"Shopping",
            "subcategory":"Used Merchandise",
            "type":"Retail Goods"
        }
    ],
    "sg:phone":"+1 254 412 2311",
    "sg:postcode":"76705",
    "sg:province":"TX",
    "sg:tags":[
        "clothing"
    ],
    "wof:name":"Stella's Too",
    "wof:placetype":"venue"
},
  "geometry": {"coordinates":[-97.099312,31.590249],"type":"Point"}
}