{
  "type": "Feature",
  "properties": {
    "iso:country":"US",
    "sg:address":"1803 W Mockingbird Ln",
    "sg:city":"Dallas",
    "sg:classifiers":[
        {
            "category":"Restaurant",
            "type":"Food & Drink"
        }
    ],
    "sg:phone":"+1 214 638 7227",
    "sg:postcode":"75235",
    "sg:province":"TX",
    "sg:tags":[
        "barbecue"
    ],
    "wof:name":"Brisket Bar-B-Q",
    "wof:placetype":"venue"
},
  "geometry": {"coordinates":[-96.857556,32.822298],"type":"Point"}
}