{
  "type": "Feature",
  "properties": {
    "iso:country":"US",
    "sg:address":"509 S Guadalupe St",
    "sg:city":"Seguin",
    "sg:classifiers":[
        {
            "category":"Retail",
            "subcategory":"Repair Shop",
            "type":"Services"
        }
    ],
    "sg:phone":"+1 830 379 3566",
    "sg:postcode":"78155",
    "sg:province":"TX",
    "sg:tags":[
        "electric",
        "motor"
    ],
    "wof:name":"Suarez Electric Motors",
    "wof:placetype":"venue"
},
  "geometry": {"coordinates":[-97.96939399999999,29.565471],"type":"Point"}
}