{
  "type": "Feature",
  "properties": {
    "iso:country":"US",
    "sg:address":"10720 E Miller Rd",
    "sg:city":"Dallas",
    "sg:classifiers":[
        {
            "category":"Wholesale",
            "subcategory":"Machinery & Supplies",
            "type":"Manufacturing & Wholesale Goods"
        }
    ],
    "sg:phone":"+1 214 343 3722",
    "sg:postcode":"75238",
    "sg:province":"TX",
    "sg:tags":[
        "pressure",
        "washing",
        "equipment"
    ],
    "wof:name":"ACTION Cleaning Systems",
    "wof:placetype":"venue"
},
  "geometry": {"coordinates":[-96.698509,32.894505],"type":"Point"}
}