{
  "type": "Feature",
  "properties": {
    "iso:country":"US",
    "sg:address":"33035 Tamina Rd",
    "sg:city":"Magnolia",
    "sg:classifiers":[
        {
            "category":"Real Estate",
            "subcategory":"Real Estate Services",
            "type":"Services"
        },
        {
            "category":"Real Estate",
            "subcategory":"Real Estate Agent",
            "type":"Services"
        }
    ],
    "sg:phone":"+1 281 356 5858",
    "sg:postcode":"77354",
    "sg:province":"TX",
    "sg:tags":[
        "buyer",
        "broker"
    ],
    "wof:name":"Kwwd",
    "wof:placetype":"venue"
},
  "geometry": {"coordinates":[-95.584738,30.219609],"type":"Point"}
}