{
  "type": "Feature",
  "properties": {
    "iso:country":"US",
    "sg:address":"2603 Hospital Dr",
    "sg:city":"Victoria",
    "sg:classifiers":[
        {
            "category":"Health Services",
            "subcategory":"Doctor",
            "type":"Services"
        }
    ],
    "sg:phone":"+1 361 576 2110",
    "sg:postcode":"77901",
    "sg:province":"TX",
    "sg:tags":[
        "medical"
    ],
    "wof:name":"Regional Matrnl Chld Hlth Prog",
    "wof:placetype":"venue"
},
  "geometry": {"coordinates":[-96.976612,28.812071],"type":"Point"}
}