{
  "type": "Feature",
  "properties": {
    "iso:country":"US",
    "sg:address":"2621 Bear Creek Rd",
    "sg:city":"Lancaster",
    "sg:classifiers":[
        {
            "category":"Recreation",
            "type":"Entertainment"
        }
    ],
    "sg:phone":"+1 972 230 4153",
    "sg:postcode":"75146",
    "sg:province":"TX",
    "sg:tags":[
        "club",
        "membership"
    ],
    "wof:name":"Riders of Distinction",
    "wof:placetype":"venue"
},
  "geometry": {"coordinates":[-96.813991,32.560734],"type":"Point"}
}