{
  "type": "Feature",
  "properties": {
    "iso:country":"US",
    "sg:address":"5926 Southwest Fwy",
    "sg:city":"Houston",
    "sg:classifiers":[
        {
            "category":"Retail",
            "subcategory":"Auto Repair",
            "type":"Services"
        }
    ],
    "sg:phone":"+1 713 782 1887",
    "sg:postcode":"77057",
    "sg:province":"TX",
    "sg:tags":[
        "transmission"
    ],
    "wof:name":"AAMCO Transmissions",
    "wof:placetype":"venue"
},
  "geometry": {"coordinates":[-95.48075,29.726306],"type":"Point"}
}