{
  "type": "Feature",
  "properties": {
    "iso:country":"US",
    "sg:address":"12614 Independence Ave",
    "sg:city":"San Antonio",
    "sg:classifiers":[
        {
            "category":"Building & Trades",
            "subcategory":"Construction",
            "type":"Services"
        }
    ],
    "sg:phone":"+1 210 650 4650",
    "sg:postcode":"78233",
    "sg:province":"TX",
    "sg:tags":[
        "nonresidential"
    ],
    "wof:name":"Axis Tile & Remodeling",
    "wof:placetype":"venue"
},
  "geometry": {"coordinates":[-98.369822,29.555476],"type":"Point"}
}