{
  "type": "Feature",
  "properties": {
    "iso:country":"US",
    "sg:address":"1234 W Hudgins St",
    "sg:city":"Grapevine",
    "sg:classifiers":[
        {
            "category":"Professional",
            "subcategory":"Business Services",
            "type":"Services"
        }
    ],
    "sg:phone":"+1 817 488 6117",
    "sg:postcode":"76051",
    "sg:province":"TX",
    "wof:name":"Edwin T McKibben",
    "wof:placetype":"venue"
},
  "geometry": {"coordinates":[-97.08825299999999,32.932847],"type":"Point"}
}