{
  "type": "Feature",
  "properties": {
    "iso:country":"US",
    "sg:address":"375 Claiborne St",
    "sg:city":"Vidor",
    "sg:classifiers":[
        {
            "category":"Government",
            "subcategory":"Police Station",
            "type":"Public Place"
        }
    ],
    "sg:phone":"+1 409 769 6391",
    "sg:postcode":"77662",
    "sg:province":"TX",
    "sg:tags":[
        "sheriff"
    ],
    "wof:name":"Orange County Sheriff's Dept",
    "wof:placetype":"venue"
},
  "geometry": {"coordinates":[-94.002708,30.13458],"type":"Point"}
}