{
  "type": "Feature",
  "properties": {
    "iso:country":"US",
    "sg:address":"4638 Oakside Dr",
    "sg:city":"Houston",
    "sg:classifiers":[
        {
            "category":"Real Estate",
            "subcategory":"Real Estate Services",
            "type":"Services"
        }
    ],
    "sg:phone":"+1 713 433 5941",
    "sg:postcode":"77053",
    "sg:province":"TX",
    "sg:tags":[
        "search",
        "company",
        "title"
    ],
    "wof:name":"Houston-Metroplex RE Svc",
    "wof:placetype":"venue"
},
  "geometry": {"coordinates":[-95.44851199999999,29.606588],"type":"Point"}
}