{
  "type": "Feature",
  "properties": {
    "iso:country":"US",
    "sg:address":"9119 Lake Park Dr",
    "sg:city":"Houston",
    "sg:classifiers":[
        {
            "category":"Building & Trades",
            "subcategory":"Plumbing",
            "type":"Services"
        }
    ],
    "sg:phone":"+1 713 635 5459",
    "sg:postcode":"77078",
    "sg:province":"TX",
    "sg:tags":[
        "plumber",
        "industrial",
        "contractors-commercial"
    ],
    "wof:name":"Sanchez Beauty Shop",
    "wof:placetype":"venue"
},
  "geometry": {"coordinates":[-95.26116399999999,29.844241],"type":"Point"}
}