{
  "type": "Feature",
  "properties": {
    "iso:country":"US",
    "sg:address":"4801 Goldfield Dr",
    "sg:city":"San Antonio",
    "sg:classifiers":[
        {
            "category":"Wholesale",
            "subcategory":"Vending Machines",
            "type":"Manufacturing & Wholesale Goods"
        }
    ],
    "sg:phone":"+1 210 661 7668",
    "sg:postcode":"78218",
    "sg:province":"TX",
    "wof:name":"Maggi's Vending",
    "wof:placetype":"venue"
},
  "geometry": {"coordinates":[-98.39747300000001,29.482772],"type":"Point"}
}