{
  "type": "Feature",
  "properties": {
    "iso:country":"US",
    "sg:address":"5912 Irvington Blvd",
    "sg:city":"Houston",
    "sg:classifiers":[
        {
            "category":"Professional",
            "subcategory":"Lawyer & Legal Services",
            "type":"Services"
        }
    ],
    "sg:phone":"+1 713 742 6979",
    "sg:postcode":"77009",
    "sg:province":"TX",
    "sg:tags":[
        "notary"
    ],
    "wof:name":"Guerrero & Sanchez Notary Public & income Tax",
    "wof:placetype":"venue"
},
  "geometry": {"coordinates":[-95.360921,29.812512],"type":"Point"}
}