{
  "type": "Feature",
  "properties": {
    "iso:country":"US",
    "sg:address":"3540 E Emporium Cir",
    "sg:city":"Mesquite",
    "sg:classifiers":[
        {
            "category":"Shopping",
            "subcategory":"Bicycles & Sporting Goods",
            "type":"Retail Goods"
        }
    ],
    "sg:phone":"+1 972 686 1885",
    "sg:postcode":"75150",
    "sg:province":"TX",
    "wof:name":"Gart Sports",
    "wof:placetype":"venue"
},
  "geometry": {"coordinates":[-96.622423,32.812822],"type":"Point"}
}