{
  "type": "Feature",
  "properties": {
    "iso:country":"US",
    "sg:address":"3658 N Belt Line Rd",
    "sg:city":"Irving",
    "sg:classifiers":[
        {
            "category":"Banks & Credit Unions",
            "subcategory":"Bank",
            "type":"Services"
        }
    ],
    "sg:phone":"+1 972 252 1306",
    "sg:postcode":"75062",
    "sg:province":"TX",
    "sg:tags":[
        "cashing",
        "depository",
        "check",
        "banking"
    ],
    "wof:name":"Ace Cash Express",
    "wof:placetype":"venue"
},
  "geometry": {"coordinates":[-96.992199,32.850896],"type":"Point"}
}