{
  "type": "Feature",
  "properties": {
    "iso:country":"US",
    "sg:address":"8811 Westheimer Rd Ste 211",
    "sg:city":"Houston",
    "sg:classifiers":[
        {
            "category":"Insurance",
            "subcategory":"Hazard Insurance",
            "type":"Services"
        }
    ],
    "sg:phone":"+1 713 785 2138",
    "sg:postcode":"77063",
    "sg:province":"TX",
    "sg:website":"www.713auto.com",
    "wof:name":"ABC Insurance",
    "wof:placetype":"venue"
},
  "geometry": {"coordinates":[-95.520205,29.737065],"type":"Point"}
}