{
  "type": "Feature",
  "properties": {
    "iso:country":"US",
    "sg:address":"7002 Rd B",
    "sg:city":"Corpus Christi",
    "sg:classifiers":[
        {
            "category":"Building & Trades",
            "subcategory":"Construction",
            "type":"Services"
        }
    ],
    "sg:phone":"+1 361 994 0600",
    "sg:postcode":"78414",
    "sg:province":"TX",
    "sg:tags":[
        "house"
    ],
    "wof:name":"Cw Custom Remodeling",
    "wof:placetype":"venue"
},
  "geometry": {"coordinates":[-97.370722,27.651711],"type":"Point"}
}