{
  "type": "Feature",
  "properties": {
    "iso:country":"US",
    "sg:address":"1108 Kesser Dr",
    "sg:city":"Plano",
    "sg:classifiers":[
        {
            "category":"Personal",
            "type":"Services"
        }
    ],
    "sg:phone":"+1 972 517 1334",
    "sg:postcode":"75025",
    "sg:province":"TX",
    "wof:name":"Balance Your Life Massage",
    "wof:placetype":"venue"
},
  "geometry": {"coordinates":[-96.712532,33.079253],"type":"Point"}
}