{
  "type": "Feature",
  "properties": {
    "iso:country":"US",
    "sg:address":"425 E Sinton St",
    "sg:city":"Sinton",
    "sg:classifiers":[
        {
            "category":"Retail",
            "subcategory":"Repair Shop",
            "type":"Services"
        }
    ],
    "sg:phone":"+1 361 364 2177",
    "sg:postcode":"78387",
    "sg:province":"TX",
    "wof:name":"Karens Keys",
    "wof:placetype":"venue"
},
  "geometry": {"coordinates":[-97.505898,28.036746],"type":"Point"}
}