{
  "type": "Feature",
  "properties": {
    "iso:country":"US",
    "sg:address":"113 Pecan Hollow Dr",
    "sg:city":"Coppell",
    "sg:classifiers":[
        {
            "category":"Retail",
            "subcategory":"Car Wash",
            "type":"Services"
        }
    ],
    "sg:phone":"+1 972 393 7515",
    "sg:postcode":"75019",
    "sg:province":"TX",
    "sg:tags":[
        "carwash"
    ],
    "wof:name":"Texas Pro Wash Inc",
    "wof:placetype":"venue"
},
  "geometry": {"coordinates":[-96.986327,32.975325],"type":"Point"}
}