{
  "type": "Feature",
  "properties": {
    "iso:country":"US",
    "sg:address":"1444 San Jacinto Mall",
    "sg:city":"Baytown",
    "sg:classifiers":[
        {
            "category":"Personal",
            "subcategory":"Beauty Salon",
            "type":"Services"
        }
    ],
    "sg:phone":"+1 281 421 7936",
    "sg:postcode":"77521",
    "sg:province":"TX",
    "sg:tags":[
        "shop",
        "manicuring"
    ],
    "wof:name":"Fashion Nails",
    "wof:placetype":"venue"
},
  "geometry": {"coordinates":[-94.98640899999999,29.802795],"type":"Point"}
}