{
  "type": "Feature",
  "properties": {
    "iso:country":"US",
    "sg:address":"8915 Crazy Horse Trl",
    "sg:city":"Houston",
    "sg:classifiers":[
        {
            "category":"Building & Trades",
            "subcategory":"Equipment Rental",
            "type":"Services"
        }
    ],
    "sg:phone":"+1 832 912 6596",
    "sg:postcode":"77064",
    "sg:province":"TX",
    "wof:name":"Vjer Aviation LLC",
    "wof:placetype":"venue"
},
  "geometry": {"coordinates":[-95.571562,29.903254],"type":"Point"}
}