{
  "type": "Feature",
  "properties": {
    "iso:country":"US",
    "sg:address":"2005 S Goliad St",
    "sg:city":"Rockwall",
    "sg:classifiers":[
        {
            "category":"Restaurant",
            "type":"Food & Drink"
        }
    ],
    "sg:phone":"+1 972 722 3033",
    "sg:postcode":"75032",
    "sg:province":"TX",
    "sg:tags":[
        "eating"
    ],
    "wof:name":"KFC",
    "wof:placetype":"venue"
},
  "geometry": {"coordinates":[-96.450255,32.909596],"type":"Point"}
}