{
  "type": "Feature",
  "properties": {
    "iso:country":"US",
    "sg:address":"200 Westlake Park Blvd",
    "sg:city":"Houston",
    "sg:classifiers":[
        {
            "category":"Mining & Drilling",
            "type":"Manufacturing & Wholesale Goods"
        }
    ],
    "sg:phone":"+1 281 560 1800",
    "sg:postcode":"77079",
    "sg:province":"TX",
    "sg:tags":[
        "exploration"
    ],
    "wof:name":"Eri Supply & Logistics",
    "wof:placetype":"venue"
},
  "geometry": {"coordinates":[-95.63024299999999,29.7844],"type":"Point"}
}