{
  "type": "Feature",
  "properties": {
    "iso:country":"US",
    "sg:address":"306 W 8th St",
    "sg:city":"Georgetown",
    "sg:classifiers":[
        {
            "category":"Shopping",
            "subcategory":"Jewelry",
            "type":"Retail Goods"
        },
        {
            "category":"Manufacturing",
            "subcategory":"Jewelry",
            "type":"Manufacturing & Wholesale Goods"
        },
        {
            "category":"Retail",
            "subcategory":"Repair Shop",
            "type":"Services"
        }
    ],
    "sg:phone":"+1 512 869 0097",
    "sg:postcode":"78626",
    "sg:province":"TX",
    "sg:tags":[
        "repairing",
        "stone",
        "designer",
        "jewelers-wholesale",
        "clock",
        "watch",
        "jeweler",
        "precious",
        "semi-precious",
        "manufacturer"
    ],
    "wof:name":"Bandy Jewelers",
    "wof:placetype":"venue"
},
  "geometry": {"coordinates":[-97.679064,30.636569],"type":"Point"}
}