{
  "type": "Feature",
  "properties": {
    "iso:country":"US",
    "sg:address":"619 Houston St",
    "sg:city":"Laredo",
    "sg:classifiers":[
        {
            "category":"Professional",
            "subcategory":"Business Services",
            "type":"Services"
        }
    ],
    "sg:phone":"+1 956 724 1664",
    "sg:postcode":"78040",
    "sg:province":"TX",
    "sg:tags":[
        "license"
    ],
    "wof:name":"E C Group",
    "wof:placetype":"venue"
},
  "geometry": {"coordinates":[-99.501806,27.50708],"type":"Point"}
}