{
  "type": "Feature",
  "properties": {
    "iso:country":"US",
    "sg:address":"424 S Bridge St",
    "sg:city":"Hidalgo",
    "sg:classifiers":[
        {
            "category":"Organizations",
            "subcategory":"Religious Organization",
            "type":"Services"
        }
    ],
    "sg:phone":"+1 956 843 7700",
    "sg:postcode":"78557",
    "sg:province":"TX",
    "sg:tags":[
        "church"
    ],
    "wof:name":"Community Baptist Church",
    "wof:placetype":"venue"
},
  "geometry": {"coordinates":[-98.262817,26.102186],"type":"Point"}
}