{
  "type": "Feature",
  "properties": {
    "iso:country":"US",
    "sg:address":"2215 Gus Thomasson Rd",
    "sg:city":"Dallas",
    "sg:classifiers":[
        {
            "category":"Shopping",
            "subcategory":"Used Merchandise",
            "type":"Retail Goods"
        }
    ],
    "sg:phone":"+1 214 319 6991",
    "sg:postcode":"75228",
    "sg:province":"TX",
    "sg:tags":[
        "shop",
        "thrift"
    ],
    "wof:name":"Donation Center",
    "wof:placetype":"venue"
},
  "geometry": {"coordinates":[-96.673659,32.834826],"type":"Point"}
}