{
  "type": "Feature",
  "properties": {
    "iso:country":"US",
    "sg:address":"2803 Highway 473",
    "sg:city":"Kendalia",
    "sg:classifiers":[
        {
            "category":"Real Estate",
            "subcategory":"Real Estate Services",
            "type":"Services"
        },
        {
            "category":"Real Estate",
            "subcategory":"Real Estate Agent",
            "type":"Services"
        }
    ],
    "sg:phone":"+1 830 336 2587",
    "sg:postcode":"78027",
    "sg:province":"TX",
    "sg:tags":[
        "management"
    ],
    "wof:name":"Kjk-Wrm",
    "wof:placetype":"venue"
},
  "geometry": {"coordinates":[-98.452856,29.964622],"type":"Point"}
}