{
  "type": "Feature",
  "properties": {
    "iso:country":"US",
    "sg:address":"3361 Boyington Dr",
    "sg:city":"Carrollton",
    "sg:classifiers":[
        {
            "category":"Wholesale",
            "subcategory":"Electrical",
            "type":"Manufacturing & Wholesale Goods"
        }
    ],
    "sg:phone":"+1 972 247 8300",
    "sg:postcode":"75006",
    "sg:province":"TX",
    "sg:tags":[
        "lighting"
    ],
    "sg:website":"www.bulbman.com",
    "wof:name":"Bulbman Inc",
    "wof:placetype":"venue"
},
  "geometry": {"coordinates":[-96.842174,32.965143],"type":"Point"}
}