{
  "type": "Feature",
  "properties": {
    "iso:country":"US",
    "sg:address":"2532 Dove Creek Ln",
    "sg:city":"Carrollton",
    "sg:classifiers":[
        {
            "category":"Shopping",
            "subcategory":"Clothing, Apparel, & Fashions",
            "type":"Retail Goods"
        }
    ],
    "sg:phone":"+1 214 999 4608",
    "sg:postcode":"75006",
    "sg:province":"TX",
    "sg:tags":[
        "woman",
        "specialty",
        "store",
        "accessory"
    ],
    "wof:name":"Angels Anns",
    "wof:placetype":"venue"
},
  "geometry": {"coordinates":[-96.868357,32.981247],"type":"Point"}
}