{
  "type": "Feature",
  "properties": {
    "iso:country":"US",
    "sg:address":"20742 Magnolia",
    "sg:city":"Mathis",
    "sg:classifiers":[
        {
            "category":"Organizations",
            "subcategory":"Religious Organization",
            "type":"Services"
        }
    ],
    "sg:phone":"+1 361 547 5748",
    "sg:postcode":"78368",
    "sg:province":"TX",
    "wof:name":"St Patricks Mission",
    "wof:placetype":"venue"
},
  "geometry": {"coordinates":[-97.770601,27.954422],"type":"Point"}
}