{
  "type": "Feature",
  "properties": {
    "iso:country":"US",
    "sg:address":"2835 Gulfway Dr",
    "sg:city":"Port Arthur",
    "sg:classifiers":[
        {
            "category":"Building & Trades",
            "subcategory":"Construction",
            "type":"Services"
        }
    ],
    "sg:phone":"+1 409 982 0249",
    "sg:postcode":"77640",
    "sg:province":"TX",
    "sg:tags":[
        "repairing",
        "nonresidential",
        "remodeling",
        "contractor"
    ],
    "wof:name":"Collins Carpentry & Home Rmdlg",
    "wof:placetype":"venue"
},
  "geometry": {"coordinates":[-93.929051,29.898633],"type":"Point"}
}