{
  "type": "Feature",
  "properties": {
    "iso:country":"US",
    "sg:address":"1019 Fox Ave",
    "sg:city":"Lewisville",
    "sg:classifiers":[
        {
            "category":"Professional",
            "subcategory":"Accounting & Tax Preparation",
            "type":"Services"
        }
    ],
    "sg:phone":"+1 972 221 5225",
    "sg:postcode":"75067",
    "sg:province":"TX",
    "sg:tags":[
        "return",
        "filing"
    ],
    "wof:name":"Muniz Insurance",
    "wof:placetype":"venue"
},
  "geometry": {"coordinates":[-97.01217200000001,33.034945],"type":"Point"}
}