{
  "type": "Feature",
  "properties": {
    "iso:country":"US",
    "sg:address":"1260 Hillcrest Dr N",
    "sg:city":"Sulphur Springs",
    "sg:classifiers":[
        {
            "category":"Autos & Motor Vehicles",
            "subcategory":"Recreational Vehicle Sales",
            "type":"Retail Goods"
        }
    ],
    "sg:phone":"+1 903 885 9656",
    "sg:postcode":"75482",
    "sg:province":"TX",
    "sg:tags":[
        "parts",
        "trailer"
    ],
    "sg:website":"www.rednecktrailersupply.com",
    "wof:name":"Redneck Trailer Supplies",
    "wof:placetype":"venue"
},
  "geometry": {"coordinates":[-95.624066,33.148779],"type":"Point"}
}