{
  "type": "Feature",
  "properties": {
    "iso:country":"US",
    "sg:address":"1201 Main St Ste 110",
    "sg:city":"Houston",
    "sg:classifiers":[
        {
            "category":"Shopping",
            "subcategory":"Books",
            "type":"Retail Goods"
        }
    ],
    "sg:phone":"+1 713 353 5496",
    "sg:postcode":"77002",
    "sg:province":"TX",
    "sg:tags":[
        "bookstore"
    ],
    "sg:website":"www.booksamillioninc.com",
    "wof:name":"Books-A-Million Inc",
    "wof:placetype":"venue"
},
  "geometry": {"coordinates":[-95.365967,29.755373],"type":"Point"}
}