{
  "type": "Feature",
  "properties": {
    "iso:country":"US",
    "sg:address":"4809 Gerona Dr",
    "sg:city":"Austin",
    "sg:classifiers":[
        {
            "category":"Building & Trades",
            "subcategory":"Construction",
            "type":"Services"
        }
    ],
    "sg:phone":"+1 512 218 1055",
    "sg:postcode":"78759",
    "sg:province":"TX",
    "sg:tags":[
        "residential",
        "commercial"
    ],
    "wof:name":"Brooks Roofing",
    "wof:placetype":"venue"
},
  "geometry": {"coordinates":[-97.74074899999999,30.408238],"type":"Point"}
}