{
  "type": "Feature",
  "properties": {
    "iso:country":"US",
    "sg:address":"435 Kraupahen St",
    "sg:city":"Fredericksburg",
    "sg:classifiers":[
        {
            "category":"Manufacturing",
            "subcategory":"Metals",
            "type":"Manufacturing & Wholesale Goods"
        }
    ],
    "sg:phone":"+1 830 997 3440",
    "sg:postcode":"78624",
    "sg:province":"TX",
    "sg:tags":[
        "metalwork",
        "sheet",
        "mfg"
    ],
    "wof:name":"Wahl Sheet Metal & Repair",
    "wof:placetype":"venue"
},
  "geometry": {"coordinates":[-98.872629,30.267354],"type":"Point"}
}