{
  "type": "Feature",
  "properties": {
    "iso:country":"US",
    "sg:address":"825 S Austin Ave",
    "sg:city":"Denison",
    "sg:classifiers":[
        {
            "category":"Retail",
            "subcategory":"Auto Repair",
            "type":"Services"
        }
    ],
    "sg:phone":"+1 903 465 2535",
    "sg:postcode":"75020",
    "sg:province":"TX",
    "sg:tags":[
        "general"
    ],
    "wof:name":"Gumaer Keith Automotive",
    "wof:placetype":"venue"
},
  "geometry": {"coordinates":[-96.537311,33.747536],"type":"Point"}
}