{
  "type": "Feature",
  "properties": {
    "iso:country":"US",
    "sg:address":"1612 Austin St",
    "sg:city":"Houston",
    "sg:classifiers":[
        {
            "category":"Sports & Exercise",
            "subcategory":"Gym",
            "type":"Entertainment"
        }
    ],
    "sg:phone":"+1 713 658 0299",
    "sg:postcode":"77002",
    "sg:province":"TX",
    "sg:tags":[
        "fitness",
        "physical",
        "facility"
    ],
    "wof:name":"Top Ten Boxing",
    "wof:placetype":"venue"
},
  "geometry": {"coordinates":[-95.36561500000001,29.749784],"type":"Point"}
}