{
  "type": "Feature",
  "properties": {
    "iso:country":"US",
    "sg:address":"1610 N Colorado St",
    "sg:city":"San Antonio",
    "sg:classifiers":[
        {
            "category":"Manufacturing",
            "subcategory":"Tools & Machinery",
            "type":"Manufacturing & Wholesale Goods"
        }
    ],
    "sg:phone":"+1 210 734 4261",
    "sg:postcode":"78201",
    "sg:province":"TX",
    "sg:tags":[
        "concrete",
        "vibrator",
        "mfg"
    ],
    "wof:name":"Dreyer Vibrator Co Inc",
    "wof:placetype":"venue"
},
  "geometry": {"coordinates":[-98.50895300000001,29.443445],"type":"Point"}
}