{
  "type": "Feature",
  "properties": {
    "iso:country":"US",
    "sg:address":"511 8th St",
    "sg:city":"Somerville",
    "sg:classifiers":[
        {
            "category":"Retail",
            "subcategory":"Funeral Services",
            "type":"Services"
        }
    ],
    "sg:phone":"+1 979 596 2133",
    "sg:postcode":"77879",
    "sg:province":"TX",
    "sg:tags":[
        "director"
    ],
    "wof:name":"Strickland Funeral Home",
    "wof:placetype":"venue"
},
  "geometry": {"coordinates":[-96.53338100000001,30.342798],"type":"Point"}
}