{
  "type": "Feature",
  "properties": {
    "iso:country":"US",
    "sg:address":"900 Hwy Ave",
    "sg:city":"Sunray",
    "sg:classifiers":[
        {
            "category":"Freight",
            "type":"Transportation"
        }
    ],
    "sg:phone":"+1 806 948 1610",
    "sg:postcode":"79086",
    "sg:province":"TX",
    "sg:tags":[
        "local",
        "storage",
        "hauling",
        "trucking"
    ],
    "wof:name":"Unity Trucking",
    "wof:placetype":"venue"
},
  "geometry": {"coordinates":[-101.824986,36.014798],"type":"Point"}
}