{
  "type": "Feature",
  "properties": {
    "iso:country":"US",
    "sg:address":"1009 Inwood Ln",
    "sg:city":"Colleyville",
    "sg:classifiers":[
        {
            "category":"Professional",
            "type":"Services"
        }
    ],
    "sg:phone":"+1 817 577 9593",
    "sg:postcode":"76034",
    "sg:province":"TX",
    "wof:name":"Petra Opportunities LP",
    "wof:placetype":"venue"
},
  "geometry": {"coordinates":[-97.152593,32.86965],"type":"Point"}
}