{
  "type": "Feature",
  "properties": {
    "iso:country":"US",
    "sg:address":"500 S Ervay St",
    "sg:city":"Dallas",
    "sg:classifiers":[
        {
            "category":"Professional",
            "subcategory":"Business Services",
            "type":"Services"
        }
    ],
    "sg:phone":"+1 214 747 8245",
    "sg:postcode":"75201",
    "sg:province":"TX",
    "sg:tags":[
        "telemarketing"
    ],
    "wof:name":"Disadvantage Workshop",
    "wof:placetype":"venue"
},
  "geometry": {"coordinates":[-96.79588,32.776935],"type":"Point"}
}