{
  "type": "Feature",
  "properties": {
    "iso:country":"US",
    "sg:address":"521 NW 3rd St",
    "sg:city":"Cooper",
    "sg:classifiers":[
        {
            "category":"Organizations",
            "subcategory":"Religious Organization",
            "type":"Services"
        }
    ],
    "sg:phone":"+1 903 395 2133",
    "sg:postcode":"75432",
    "sg:province":"TX",
    "sg:tags":[
        "churches-community",
        "christ",
        "church"
    ],
    "wof:name":"Friendship House Of Praise Community Church",
    "wof:placetype":"venue"
},
  "geometry": {"coordinates":[-95.690375,33.377634],"type":"Point"}
}