{
  "type": "Feature",
  "properties": {
    "iso:country":"US",
    "sg:address":"1910 Westmead Dr",
    "sg:city":"Houston",
    "sg:classifiers":[
        {
            "category":"Real Estate",
            "subcategory":"Real Estate Operator",
            "type":"Services"
        }
    ],
    "sg:phone":"+1 281 497 7006",
    "sg:postcode":"77077",
    "sg:province":"TX",
    "sg:tags":[
        "apartment",
        "complex"
    ],
    "wof:name":"Ashton Park Apartments",
    "wof:placetype":"venue"
},
  "geometry": {"coordinates":[-95.61445399999999,29.745013],"type":"Point"}
}