{
  "type": "Feature",
  "properties": {
    "iso:country":"US",
    "sg:address":"2808 Exeter Ave",
    "sg:city":"Midland",
    "sg:classifiers":[
        {
            "category":"Wholesale",
            "subcategory":"Machinery & Supplies",
            "type":"Manufacturing & Wholesale Goods"
        }
    ],
    "sg:phone":"+1 432 694 3375",
    "sg:postcode":"79705",
    "sg:province":"TX",
    "sg:tags":[
        "field",
        "oil",
        "equipment"
    ],
    "wof:name":"Bob Herell Inc",
    "wof:placetype":"venue"
},
  "geometry": {"coordinates":[-102.121201,32.033086],"type":"Point"}
}