{
  "type": "Feature",
  "properties": {
    "iso:country":"US",
    "sg:address":"6200 Gulfton St",
    "sg:city":"Houston",
    "sg:classifiers":[
        {
            "category":"Real Estate",
            "subcategory":"Real Estate Operator",
            "type":"Services"
        }
    ],
    "sg:phone":"+1 713 777 3980",
    "sg:postcode":"77081",
    "sg:province":"TX",
    "sg:tags":[
        "apartment",
        "complex"
    ],
    "wof:name":"Jefferson House Apartments",
    "wof:placetype":"venue"
},
  "geometry": {"coordinates":[-95.490601,29.716438],"type":"Point"}
}