{
  "type": "Feature",
  "properties": {
    "iso:country":"US",
    "sg:address":"7835 Sweetwind Cir",
    "sg:city":"Boerne",
    "sg:classifiers":[
        {
            "category":"Professional",
            "subcategory":"Business Services",
            "type":"Services"
        }
    ],
    "sg:phone":"+1 830 981 8896",
    "sg:postcode":"78015",
    "sg:province":"TX",
    "sg:tags":[
        "interior",
        "designer",
        "decorator"
    ],
    "wof:name":"Tricia Howard Interiors",
    "wof:placetype":"venue"
},
  "geometry": {"coordinates":[-98.632688,29.740427],"type":"Point"}
}