{
  "type": "Feature",
  "properties": {
    "iso:country":"US",
    "sg:address":"959 Dragon St",
    "sg:city":"Dallas",
    "sg:classifiers":[
        {
            "category":"Freight",
            "type":"Transportation"
        }
    ],
    "sg:phone":"+1 214 698 1133",
    "sg:postcode":"75207",
    "sg:province":"TX",
    "sg:tags":[
        "commercial",
        "storage"
    ],
    "wof:name":"A-1 Crating",
    "wof:placetype":"venue"
},
  "geometry": {"coordinates":[-96.815699,32.785618],"type":"Point"}
}