{
  "type": "Feature",
  "properties": {
    "iso:country":"US",
    "sg:address":"17610 Midway Rd",
    "sg:city":"Dallas",
    "sg:classifiers":[
        {
            "category":"Professional",
            "subcategory":"Business Services",
            "type":"Services"
        }
    ],
    "sg:phone":"+1 972 625 1891",
    "sg:postcode":"75287",
    "sg:province":"TX",
    "wof:name":"Dupre Cartridge Sales",
    "wof:placetype":"venue"
},
  "geometry": {"coordinates":[-96.841998,32.98777],"type":"Point"}
}