{
  "type": "Feature",
  "properties": {
    "iso:country":"US",
    "sg:address":"511 Mirepoix",
    "sg:city":"San Antonio",
    "sg:classifiers":[
        {
            "category":"Professional",
            "subcategory":"Business Services",
            "type":"Services"
        }
    ],
    "sg:phone":"+1 210 545 5131",
    "sg:postcode":"78232",
    "sg:province":"TX",
    "wof:name":"Marx Ventures L L C",
    "wof:placetype":"venue"
},
  "geometry": {"coordinates":[-98.502483,29.59529],"type":"Point"}
}