{
  "type": "Feature",
  "properties": {
    "iso:country":"US",
    "sg:address":"808 S College St",
    "sg:city":"Mc Kinney",
    "sg:classifiers":[
        {
            "category":"Health Services",
            "subcategory":"Health Practitioner",
            "type":"Services"
        }
    ],
    "sg:phone":"+1 214 544 7145",
    "sg:postcode":"75069",
    "sg:province":"TX",
    "sg:tags":[
        "nurse",
        "registry"
    ],
    "wof:name":"Care Pros Staffing Inc",
    "wof:placetype":"venue"
},
  "geometry": {"coordinates":[-96.62152,33.190877],"type":"Point"}
}