{
  "type": "Feature",
  "properties": {
    "iso:country":"US",
    "sg:address":"2309 Fm 2123",
    "sg:city":"Paradise",
    "sg:classifiers":[
        {
            "category":"Professional",
            "subcategory":"Credit Reporting & Collection",
            "type":"Services"
        }
    ],
    "sg:phone":"+1 940 433 2161",
    "sg:postcode":"76073",
    "sg:province":"TX",
    "sg:tags":[
        "agency"
    ],
    "wof:name":"Clean Slate Credit Services",
    "wof:placetype":"venue"
},
  "geometry": {"coordinates":[-97.759389,33.123178],"type":"Point"}
}