{
  "type": "Feature",
  "properties": {
    "iso:country":"US",
    "sg:address":"1122 Bryant St",
    "sg:city":"Benbrook",
    "sg:classifiers":[
        {
            "category":"Place Of Worship",
            "subcategory":"Church",
            "type":"Public Place"
        },
        {
            "category":"Place Of Worship",
            "type":"Public Place"
        }
    ],
    "sg:phone":"+1 817 249 1257",
    "sg:postcode":"76126",
    "sg:province":"TX",
    "sg:tags":[
        "churches-united",
        "methodist",
        "churches-methodist"
    ],
    "sg:website":"http://www.benbrookumc.org",
    "wof:name":"Benbrook United Methodist Church",
    "wof:placetype":"venue"
},
  "geometry": {"coordinates":[-97.464027,32.67083],"type":"Point"}
}