{
  "type": "Feature",
  "properties": {
    "iso:country":"US",
    "sg:address":"1602 S Lamar Boulevard",
    "sg:city":"Austin",
    "sg:classifiers":[
        {
            "category":"Retail",
            "subcategory":"Auto Repair",
            "type":"Services"
        }
    ],
    "sg:phone":"+1 512 441 3737",
    "sg:postcode":"78704",
    "sg:province":"TX",
    "wof:name":"Quality Automotive of Austin",
    "wof:placetype":"venue"
},
  "geometry": {"coordinates":[-97.764651,30.251762],"type":"Point"}
}