{
  "type": "Feature",
  "properties": {
    "iso:country":"US",
    "sg:address":"5334 Everhart Rd",
    "sg:city":"Corpus Christi",
    "sg:classifiers":[
        {
            "category":"Organizations",
            "subcategory":"Religious Organization",
            "type":"Services"
        }
    ],
    "sg:phone":"+1 361 985 0840",
    "sg:postcode":"78411",
    "sg:province":"TX",
    "sg:tags":[
        "church"
    ],
    "wof:name":"A Course In Miracles",
    "wof:placetype":"venue"
},
  "geometry": {"coordinates":[-97.38668,27.711059],"type":"Point"}
}