{
  "type": "Feature",
  "properties": {
    "iso:country":"US",
    "sg:address":"7058 Lakeview Haven Dr",
    "sg:city":"Houston",
    "sg:classifiers":[
        {
            "category":"Professional",
            "subcategory":"Employment Agencies",
            "type":"Services"
        }
    ],
    "sg:phone":"+1 281 858 5800",
    "sg:postcode":"77095",
    "sg:province":"TX",
    "wof:name":"Swafford Resources",
    "wof:placetype":"venue"
},
  "geometry": {"coordinates":[-95.649883,29.880857],"type":"Point"}
}