{
  "type": "Feature",
  "properties": {
    "iso:country":"US",
    "sg:address":"6529 W Plano Pkwy Ste B",
    "sg:city":"Plano",
    "sg:classifiers":[
        {
            "category":"Health Services",
            "subcategory":"Doctor",
            "type":"Services"
        }
    ],
    "sg:phone":"+1 972 781 1414",
    "sg:postcode":"75093",
    "sg:province":"TX",
    "sg:tags":[
        "pediatrician"
    ],
    "sg:website":"www.pedswb.com",
    "wof:name":"Pediatric Offices At Willow Bend",
    "wof:placetype":"venue"
},
  "geometry": {"coordinates":[-96.838837,33.03083],"type":"Point"}
}