{
  "type": "Feature",
  "properties": {
    "iso:country":"US",
    "sg:address":"6329 Fm 1960 Rd W",
    "sg:city":"Houston",
    "sg:classifiers":[
        {
            "category":"Home & Garden",
            "subcategory":"Furniture",
            "type":"Retail Goods"
        },
        {
            "category":"Wholesale",
            "subcategory":"Furniture",
            "type":"Manufacturing & Wholesale Goods"
        },
        {
            "category":"Home & Garden",
            "subcategory":"Carpets & Floor Coverings",
            "type":"Retail Goods"
        }
    ],
    "sg:phone":"+1 281 587 1800",
    "sg:postcode":"77069",
    "sg:province":"TX",
    "sg:tags":[
        "manufacturer",
        "store",
        "furniture-wholesale",
        "mattress"
    ],
    "sg:website":"http://www.la-z-boy.com",
    "wof:name":"La-Z-Boy Furniture Galleries",
    "wof:placetype":"venue"
},
  "geometry": {"coordinates":[-95.52425100000001,29.973639],"type":"Point"}
}