{
  "type": "Feature",
  "properties": {
    "iso:country":"US",
    "sg:address":"3811 N I H 35",
    "sg:city":"Austin",
    "sg:classifiers":[
        {
            "category":"Restaurant",
            "type":"Food & Drink"
        }
    ],
    "sg:phone":"+1 512 459 9949",
    "sg:postcode":"78722",
    "sg:province":"TX",
    "wof:name":"Short Stop",
    "wof:placetype":"venue"
},
  "geometry": {"coordinates":[-97.7192,30.2952],"type":"Point"}
}