{
  "type": "Feature",
  "properties": {
    "iso:country":"US",
    "sg:address":"4080 Old Peveto Rd",
    "sg:city":"Orange",
    "sg:classifiers":[
        {
            "category":"Manufacturing",
            "subcategory":"Chemicals & Compounds",
            "type":"Manufacturing & Wholesale Goods"
        }
    ],
    "sg:phone":"+1 409 886 0919",
    "sg:postcode":"77632",
    "sg:province":"TX",
    "sg:tags":[
        "preparation",
        "toilet",
        "mfg"
    ],
    "wof:name":"Norja Cosmetics Etc",
    "wof:placetype":"venue"
},
  "geometry": {"coordinates":[-93.804558,30.170796],"type":"Point"}
}