{
  "type": "Feature",
  "properties": {
    "iso:country":"US",
    "sg:address":"7408 S Cage Blvd",
    "sg:city":"Pharr",
    "sg:classifiers":[
        {
            "category":"Bakery",
            "type":"Food & Drink"
        }
    ],
    "sg:phone":"+1 956 781 5057",
    "sg:postcode":"78577",
    "sg:province":"TX",
    "wof:name":"D'Sabores Pasteles Y Mas",
    "wof:placetype":"venue"
},
  "geometry": {"coordinates":[-98.196215,26.122342],"type":"Point"}
}