{
  "type": "Feature",
  "properties": {
    "iso:country":"US",
    "sg:address":"2011 S Sugar Rd",
    "sg:city":"Edinburg",
    "sg:classifiers":[
        {
            "category":"Organizations",
            "subcategory":"Religious Organization",
            "type":"Services"
        }
    ],
    "sg:phone":"+1 956 383 3584",
    "sg:postcode":"78539",
    "sg:province":"TX",
    "sg:tags":[
        "church"
    ],
    "wof:name":"Faith EC Church",
    "wof:placetype":"venue"
},
  "geometry": {"coordinates":[-98.18153599999999,26.285],"type":"Point"}
}