{
  "type": "Feature",
  "properties": {
    "iso:country":"US",
    "sg:address":"4121 Colleyville Blvd",
    "sg:city":"Colleyville",
    "sg:classifiers":[
        {
            "category":"Shopping",
            "type":"Retail Goods"
        }
    ],
    "sg:phone":"+1 817 581 4459",
    "sg:postcode":"76034",
    "sg:province":"TX",
    "sg:tags":[
        "picture",
        "frame"
    ],
    "wof:name":"Colleyville Frame Gallery",
    "wof:placetype":"venue"
},
  "geometry": {"coordinates":[-97.168109,32.87048],"type":"Point"}
}