{
  "type": "Feature",
  "properties": {
    "iso:country":"US",
    "sg:address":"26029 Aldine Westfield Rd",
    "sg:city":"Spring",
    "sg:classifiers":[
        {
            "category":"Professional",
            "subcategory":"Business Services",
            "type":"Services"
        }
    ],
    "sg:phone":"+1 281 353 8686",
    "sg:postcode":"77373",
    "sg:province":"TX",
    "sg:tags":[
        "inspection"
    ],
    "wof:name":"Exterior Inspections Inc",
    "wof:placetype":"venue"
},
  "geometry": {"coordinates":[-95.412727,30.076298],"type":"Point"}
}