{
  "type": "Feature",
  "properties": {
    "iso:country":"US",
    "sg:address":"3100 Timmons Ln Ste 120",
    "sg:city":"Houston",
    "sg:classifiers":[
        {
            "category":"Professional",
            "subcategory":"Computer Services",
            "type":"Services"
        }
    ],
    "sg:phone":"+1 713 521 9111",
    "sg:postcode":"77027",
    "sg:province":"TX",
    "sg:tags":[
        "repair"
    ],
    "wof:name":"Nieto Computers",
    "wof:placetype":"venue"
},
  "geometry": {"coordinates":[-95.4366,29.737301],"type":"Point"}
}