{
  "type": "Feature",
  "properties": {
    "iso:country":"US",
    "sg:address":"2250 Eldridge Pkwy",
    "sg:city":"Houston",
    "sg:classifiers":[
        {
            "category":"Real Estate",
            "subcategory":"Real Estate Services",
            "type":"Services"
        },
        {
            "category":"Real Estate",
            "subcategory":"Real Estate Operator",
            "type":"Services"
        }
    ],
    "sg:phone":"+1 281 752 8626",
    "sg:postcode":"77077",
    "sg:province":"TX",
    "sg:tags":[
        "vacancy",
        "apartment",
        "rental",
        "finder",
        "listing"
    ],
    "wof:name":"The Bridges Of Eldridge",
    "wof:placetype":"venue"
},
  "geometry": {"coordinates":[-95.62361900000001,29.739109],"type":"Point"}
}