{
  "type": "Feature",
  "properties": {
    "iso:country":"US",
    "sg:address":"1083 FM 812",
    "sg:city":"Cedar Creek",
    "sg:classifiers":[
        {
            "category":"Building & Trades",
            "subcategory":"Construction",
            "type":"Services"
        }
    ],
    "sg:phone":"+1 512 581 7997",
    "sg:postcode":"78612",
    "sg:province":"TX",
    "sg:tags":[
        "dry wall",
        "contractor"
    ],
    "wof:name":"Design Drywall Inc",
    "wof:placetype":"venue"
},
  "geometry": {"coordinates":[-97.51620200000001,30.002661],"type":"Point"}
}