{
  "type": "Feature",
  "properties": {
    "iso:country":"US",
    "sg:address":"201 E 6th St",
    "sg:city":"San Angelo",
    "sg:classifiers":[
        {
            "category":"Retail",
            "subcategory":"Auto Repair",
            "type":"Services"
        }
    ],
    "sg:phone":"+1 325 658 4472",
    "sg:postcode":"76903",
    "sg:province":"TX",
    "sg:tags":[
        "body"
    ],
    "wof:name":"J & C Body Shop",
    "wof:placetype":"venue"
},
  "geometry": {"coordinates":[-100.433623,31.472948],"type":"Point"}
}