{
  "type": "Feature",
  "properties": {
    "iso:country":"US",
    "sg:address":"18333 Preston Rd",
    "sg:city":"Dallas",
    "sg:classifiers":[
        {
            "category":"Real Estate",
            "subcategory":"Real Estate Agent",
            "type":"Services"
        }
    ],
    "sg:phone":"+1 972 991 2262",
    "sg:postcode":"75252",
    "sg:province":"TX",
    "sg:tags":[
        "management"
    ],
    "wof:name":"Preston North Ctr",
    "wof:placetype":"venue"
},
  "geometry": {"coordinates":[-96.797741,32.998359],"type":"Point"}
}