{
  "type": "Feature",
  "properties": {
    "iso:country":"US",
    "sg:address":"209 E. Ben White Blvd. Suite 116",
    "sg:city":"Austin",
    "sg:classifiers":[
        {
            "category":"Building & Trades",
            "subcategory":"Pest Control",
            "type":"Services"
        }
    ],
    "sg:phone":"+1 512 291 1200",
    "sg:postcode":"78704",
    "sg:province":"TX",
    "wof:name":"Bulwark Exterminating",
    "wof:placetype":"venue"
},
  "geometry": {"coordinates":[-97.76208800000001,30.220711],"type":"Point"}
}