{
  "type": "Feature",
  "properties": {
    "iso:country":"US",
    "sg:address":"11721 Whisper Dew St",
    "sg:city":"San Antonio",
    "sg:classifiers":[
        {
            "category":"Shopping",
            "subcategory":"Shoes",
            "type":"Retail Goods"
        }
    ],
    "sg:phone":"+1 210 885 3372",
    "sg:postcode":"78230",
    "sg:province":"TX",
    "wof:name":"Second Step Sneakers",
    "wof:placetype":"venue"
},
  "geometry": {"coordinates":[-98.54344399999999,29.548562],"type":"Point"}
}