{
  "type": "Feature",
  "properties": {
    "iso:country":"US",
    "sg:address":"1505 Loop 3443",
    "sg:city":"Eagle Pass",
    "sg:classifiers":[
        {
            "category":"Real Estate",
            "subcategory":"Real Estate Agent",
            "type":"Services"
        }
    ],
    "sg:phone":"+1 830 757 4522",
    "sg:postcode":"78852",
    "sg:province":"TX",
    "wof:name":"Charlotte Banks Realty",
    "wof:placetype":"venue"
},
  "geometry": {"coordinates":[-100.47370100000001,28.692149],"type":"Point"}
}