{
  "type": "Feature",
  "properties": {
    "iso:country":"US",
    "sg:address":"5113 Roberta Dr",
    "sg:city":"Fort Worth",
    "sg:classifiers":[
        {
            "category":"Professional",
            "subcategory":"Business Services",
            "type":"Services"
        }
    ],
    "sg:phone":"+1 817 485 6917",
    "sg:postcode":"76180",
    "sg:province":"TX",
    "wof:name":"Conniff Enterprises Inc",
    "wof:placetype":"venue"
},
  "geometry": {"coordinates":[-97.216613,32.840321],"type":"Point"}
}