{
  "type": "Feature",
  "properties": {
    "iso:country":"US",
    "sg:address":"2918 Southern Cross Dr",
    "sg:city":"Garland",
    "sg:classifiers":[
        {
            "category":"Home & Garden",
            "subcategory":"Home Furnishings",
            "type":"Retail Goods"
        }
    ],
    "sg:phone":"+1 972 414 6263",
    "sg:postcode":"75044",
    "sg:province":"TX",
    "wof:name":"Custom Slipcovers",
    "wof:placetype":"venue"
},
  "geometry": {"coordinates":[-96.671323,32.948529],"type":"Point"}
}