{
  "type": "Feature",
  "properties": {
    "iso:country":"US",
    "sg:address":"530 E Highway 62 82",
    "sg:city":"Wolfforth",
    "sg:classifiers":[
        {
            "category":"Banks & Credit Unions",
            "subcategory":"Bank",
            "type":"Services"
        }
    ],
    "sg:phone":"+1 806 775 5000",
    "sg:postcode":"79382",
    "sg:province":"TX",
    "sg:website":"http://www.americanbankofcommerce.com",
    "wof:name":"Abc Bank",
    "wof:placetype":"venue"
},
  "geometry": {"coordinates":[-101.99897799999999,33.514929],"type":"Point"}
}