{
  "type": "Feature",
  "properties": {
    "iso:country":"US",
    "sg:address":"908 Timbercreek Dr",
    "sg:city":"Lewisville",
    "sg:classifiers":[
        {
            "category":"Professional",
            "type":"Services"
        }
    ],
    "sg:phone":"+1 972 436 7632",
    "sg:postcode":"75067",
    "sg:province":"TX",
    "wof:name":"BJ Cattle Co Inc",
    "wof:placetype":"venue"
},
  "geometry": {"coordinates":[-97.01790200000001,33.022806],"type":"Point"}
}