{
  "type": "Feature",
  "properties": {
    "iso:country":"US",
    "sg:address":"9600 Great Hills Trl",
    "sg:city":"Austin",
    "sg:classifiers":[
        {
            "category":"Professional",
            "subcategory":"Employment Agencies",
            "type":"Services"
        }
    ],
    "sg:phone":"+1 512 795 9059",
    "sg:postcode":"78759",
    "sg:province":"TX",
    "sg:tags":[
        "consultant",
        "search",
        "executive"
    ],
    "wof:name":"Dunhill Professional Search",
    "wof:placetype":"venue"
},
  "geometry": {"coordinates":[-97.74976599999999,30.394192],"type":"Point"}
}