{
  "type": "Feature",
  "properties": {
    "iso:country":"US",
    "sg:address":"1612 Robertson",
    "sg:city":"Gonzales",
    "sg:classifiers":[
        {
            "category":"Organizations",
            "subcategory":"Community Association",
            "type":"Services"
        }
    ],
    "sg:phone":"+1 830 672 3636",
    "sg:postcode":"78629",
    "sg:province":"TX",
    "sg:tags":[
        "military"
    ],
    "wof:name":"American Legion",
    "wof:placetype":"venue"
},
  "geometry": {"coordinates":[-97.44265900000001,29.517646],"type":"Point"}
}