{
  "type": "Feature",
  "properties": {
    "iso:country":"US",
    "sg:address":"3714 Danbury Dr",
    "sg:city":"Arlington",
    "sg:classifiers":[
        {
            "category":"Professional",
            "subcategory":"Computer Services",
            "type":"Services"
        }
    ],
    "sg:phone":"+1 817 457 7762",
    "sg:postcode":"76016",
    "sg:province":"TX",
    "sg:tags":[
        "prepackaged",
        "software"
    ],
    "wof:name":"Micro Sher Inc",
    "wof:placetype":"venue"
},
  "geometry": {"coordinates":[-97.177363,32.687573],"type":"Point"}
}