{
  "type": "Feature",
  "properties": {
    "iso:country":"US",
    "sg:address":"904 S Garfield St",
    "sg:city":"Midland",
    "sg:classifiers":[
        {
            "category":"Shopping",
            "subcategory":"Shoes",
            "type":"Retail Goods"
        }
    ],
    "sg:phone":"+1 432 682 0017",
    "sg:postcode":"79701",
    "sg:province":"TX",
    "sg:tags":[
        "boot"
    ],
    "wof:name":"Daddy's Boots & Boutique",
    "wof:placetype":"venue"
},
  "geometry": {"coordinates":[-102.093391,31.985395],"type":"Point"}
}