{
  "type": "Feature",
  "properties": {
    "iso:country":"US",
    "sg:address":"16256 FM 1484",
    "sg:city":"Conroe",
    "sg:classifiers":[
        {
            "category":"Home & Garden",
            "subcategory":"Carpets & Floor Coverings",
            "type":"Retail Goods"
        }
    ],
    "sg:phone":"+1 936 264 2808",
    "sg:postcode":"77303",
    "sg:province":"TX",
    "wof:name":"Quality Floor Covering",
    "wof:placetype":"venue"
},
  "geometry": {"coordinates":[-95.328973,30.37929],"type":"Point"}
}