{
  "type": "Feature",
  "properties": {
    "iso:country":"US",
    "sg:address":"1600 Carson St",
    "sg:city":"Fort Worth",
    "sg:classifiers":[
        {
            "category":"Manufacturing",
            "subcategory":"Paper Products",
            "type":"Manufacturing & Wholesale Goods"
        }
    ],
    "sg:phone":"+1 817 429 6262",
    "sg:postcode":"76117",
    "sg:province":"TX",
    "sg:tags":[
        "corrugated",
        "solid",
        "fiber",
        "box"
    ],
    "wof:name":"Harris Packaging Corp",
    "wof:placetype":"venue"
},
  "geometry": {"coordinates":[-97.256676,32.784407],"type":"Point"}
}