{
  "type": "Feature",
  "properties": {
    "iso:country":"US",
    "sg:address":"310 W Lang St",
    "sg:city":"Alvin",
    "sg:classifiers":[
        {
            "category":"Communications",
            "subcategory":"Film & Video Production",
            "type":"Services"
        }
    ],
    "sg:phone":"+1 281 388 0425",
    "sg:postcode":"77511",
    "sg:province":"TX",
    "sg:tags":[
        "motion"
    ],
    "wof:name":"Grooveline Productions",
    "wof:placetype":"venue"
},
  "geometry": {"coordinates":[-95.246621,29.421203],"type":"Point"}
}