{
  "type": "Feature",
  "properties": {
    "iso:country":"US",
    "sg:address":"7515 S Kirkwood Rd",
    "sg:city":"Houston",
    "sg:classifiers":[
        {
            "category":"Retail",
            "subcategory":"Auto Repair",
            "type":"Services"
        }
    ],
    "sg:phone":"+1 281 495 3255",
    "sg:postcode":"77072",
    "sg:province":"TX",
    "sg:tags":[
        "repairing",
        "automobile",
        "general"
    ],
    "wof:name":"John's Auto Repair",
    "wof:placetype":"venue"
},
  "geometry": {"coordinates":[-95.58761199999999,29.695667],"type":"Point"}
}