{
  "type": "Feature",
  "properties": {
    "iso:country":"US",
    "sg:address":"303 E W M Watson Blvd",
    "sg:city":"Daingerfield",
    "sg:classifiers":[
        {
            "category":"Food & Beverages",
            "subcategory":"Groceries & Convenience Stores",
            "type":"Retail Goods"
        }
    ],
    "sg:phone":"+1 903 645 7590",
    "sg:postcode":"75638",
    "sg:province":"TX",
    "wof:name":"Jr Food Market",
    "wof:placetype":"venue"
},
  "geometry": {"coordinates":[-94.71918100000001,33.029555],"type":"Point"}
}