{
  "type": "Feature",
  "properties": {
    "iso:country":"US",
    "sg:address":"4515 S Georgia St",
    "sg:city":"Amarillo",
    "sg:classifiers":[
        {
            "category":"Shopping",
            "type":"Retail Goods"
        }
    ],
    "sg:phone":"+1 806 359 7884",
    "sg:postcode":"79110",
    "sg:province":"TX",
    "sg:tags":[
        "merchandise"
    ],
    "wof:name":"Auto Trixx",
    "wof:placetype":"venue"
},
  "geometry": {"coordinates":[-101.866225,35.16181],"type":"Point"}
}