{
  "type": "Feature",
  "properties": {
    "iso:country":"US",
    "sg:address":"201 Lindenwood Dr",
    "sg:city":"Laredo",
    "sg:classifiers":[
        {
            "category":"Education",
            "subcategory":"School",
            "type":"Public Place"
        }
    ],
    "sg:phone":"+1 956 473 6201",
    "sg:postcode":"78045",
    "sg:province":"TX",
    "sg:tags":[
        "k-",
        "private"
    ],
    "wof:name":"United Independent School District Uisd Administration",
    "wof:placetype":"venue"
},
  "geometry": {"coordinates":[-99.480583,27.57465],"type":"Point"}
}