{
  "type": "Feature",
  "properties": {
    "iso:country":"US",
    "sg:address":"1212 Sam Houston Dr",
    "sg:city":"Victoria",
    "sg:classifiers":[
        {
            "category":"Wholesale",
            "subcategory":"Electrical",
            "type":"Manufacturing & Wholesale Goods"
        }
    ],
    "sg:phone":"+1 361 485 0642",
    "sg:postcode":"77901",
    "sg:province":"TX",
    "sg:tags":[
        "equipment",
        "electric",
        "supply"
    ],
    "wof:name":"Wholesale Electric Supply Inc",
    "wof:placetype":"venue"
},
  "geometry": {"coordinates":[-96.978919,28.826849],"type":"Point"}
}