{
  "type": "Feature",
  "properties": {
    "iso:country":"US",
    "sg:address":"3913 Medical Pkwy Ste 101",
    "sg:city":"Austin",
    "sg:classifiers":[
        {
            "category":"Personal",
            "subcategory":"Massage",
            "type":"Services"
        }
    ],
    "sg:phone":"+1 512 796 6605",
    "sg:postcode":"78756",
    "sg:province":"TX",
    "sg:tags":[
        "therapist"
    ],
    "wof:name":"Miller Therapy Group",
    "wof:placetype":"venue"
},
  "geometry": {"coordinates":[-97.74292800000001,30.307581],"type":"Point"}
}