{
  "type": "Feature",
  "properties": {
    "iso:country":"US",
    "sg:address":"1368 Todd Dr",
    "sg:city":"Plano",
    "sg:classifiers":[
        {
            "category":"Personal",
            "type":"Services"
        },
        {
            "category":"Building & Trades",
            "subcategory":"Cleaning & Sanitation",
            "type":"Services"
        }
    ],
    "sg:phone":"+1 972 527 1811",
    "sg:postcode":"75023",
    "sg:province":"TX",
    "sg:tags":[
        "window",
        "butlers'",
        "maids'"
    ],
    "wof:name":"Nothing But Clean",
    "wof:placetype":"venue"
},
  "geometry": {"coordinates":[-96.71717099999999,33.067681],"type":"Point"}
}