{
  "type": "Feature",
  "properties": {
    "iso:country":"US",
    "sg:address":"2223 Golden Sails Dr",
    "sg:city":"League City",
    "sg:classifiers":[
        {
            "category":"Farming",
            "subcategory":"Livestock Farm",
            "type":"Manufacturing & Wholesale Goods"
        }
    ],
    "sg:phone":"+1 281 334 4834",
    "sg:postcode":"77573",
    "sg:province":"TX",
    "sg:tags":[
        "equine"
    ],
    "wof:name":"J M Quarter Horses",
    "wof:placetype":"venue"
},
  "geometry": {"coordinates":[-95.045759,29.540426],"type":"Point"}
}