{
  "type": "Feature",
  "properties": {
    "iso:country":"US",
    "sg:address":"1914 W Gray St",
    "sg:city":"Houston",
    "sg:classifiers":[
        {
            "category":"Autos & Motor Vehicles",
            "subcategory":"Automobile Sales",
            "type":"Retail Goods"
        }
    ],
    "sg:phone":"+1 713 807 7700",
    "sg:postcode":"77019",
    "sg:province":"TX",
    "sg:tags":[
        "truck"
    ],
    "wof:name":"Magnolia Builders",
    "wof:placetype":"venue"
},
  "geometry": {"coordinates":[-95.403752,29.753208],"type":"Point"}
}