{
  "type": "Feature",
  "properties": {
    "iso:country":"US",
    "sg:address":"904 Peggotty Pl",
    "sg:city":"Austin",
    "sg:classifiers":[
        {
            "category":"Shopping",
            "subcategory":"Beauty & Cosmetics",
            "type":"Retail Goods"
        }
    ],
    "sg:phone":"+1 512 339 7276",
    "sg:postcode":"78753",
    "sg:province":"TX",
    "sg:tags":[
        "merchandise"
    ],
    "wof:name":"Lavender Babies",
    "wof:placetype":"venue"
},
  "geometry": {"coordinates":[-97.665092,30.387752],"type":"Point"}
}