{
  "type": "Feature",
  "properties": {
    "iso:country":"US",
    "sg:address":"3777 S Gessner Rd",
    "sg:city":"Houston",
    "sg:classifiers":[
        {
            "category":"Shopping",
            "type":"Retail Goods"
        }
    ],
    "sg:phone":"+1 832 251 2544",
    "sg:postcode":"77063",
    "sg:province":"TX",
    "sg:tags":[
        "merchandise"
    ],
    "wof:name":"Karen M Hampton-Pine",
    "wof:placetype":"venue"
},
  "geometry": {"coordinates":[-95.539012,29.722523],"type":"Point"}
}