{
  "type": "Feature",
  "properties": {
    "iso:country":"US",
    "sg:address":"9237 Grunwald Rd",
    "sg:city":"Beasley",
    "sg:phone":"+1 979 387 2568",
    "sg:postcode":"77417",
    "sg:province":"TX",
    "sg:tags":[
        "farm",
        "corn",
        "cotton"
    ],
    "wof:name":"Grunwald Wilburn",
    "wof:placetype":"venue"
},
  "geometry": {"coordinates":[-95.94923199999999,29.488845],"type":"Point"}
}