{
  "type": "Feature",
  "properties": {
    "iso:country":"US",
    "sg:address":"321-B W 19th St",
    "sg:city":"Houston",
    "sg:classifiers":[
        {
            "category":"Shopping",
            "subcategory":"Crafts & Fabrics",
            "type":"Retail Goods"
        }
    ],
    "sg:phone":"+1 713 863 1144",
    "sg:postcode":"77008",
    "sg:province":"TX",
    "sg:tags":[
        "art"
    ],
    "sg:website":"www.sewcraftyhouston.com",
    "wof:name":"Sew Crafty Houston",
    "wof:placetype":"venue"
},
  "geometry": {"coordinates":[-95.402325,29.803175],"type":"Point"}
}