{
  "type": "Feature",
  "properties": {
    "iso:country":"US",
    "sg:address":"110 Summitt St",
    "sg:city":"Farmersville",
    "sg:classifiers":[
        {
            "category":"Shopping",
            "subcategory":"Gifts & Souvenirs",
            "type":"Retail Goods"
        }
    ],
    "sg:phone":"+1 972 784 2188",
    "sg:postcode":"75442",
    "sg:province":"TX",
    "sg:tags":[
        "shop"
    ],
    "wof:name":"Gracie's Gifts And Interiors",
    "wof:placetype":"venue"
},
  "geometry": {"coordinates":[-96.358643,33.158989],"type":"Point"}
}