{
  "type": "Feature",
  "properties": {
    "iso:country":"US",
    "sg:address":"5005 E Ben White Blvd",
    "sg:city":"Austin",
    "sg:classifiers":[
        {
            "category":"Personal",
            "subcategory":"Tanning Parlor",
            "type":"Services"
        }
    ],
    "sg:phone":"+1 512 707 8772",
    "sg:postcode":"78741",
    "sg:province":"TX",
    "sg:tags":[
        "salon"
    ],
    "wof:name":"El Sol",
    "wof:placetype":"venue"
},
  "geometry": {"coordinates":[-97.72394300000001,30.213663],"type":"Point"}
}