{
  "type": "Feature",
  "properties": {
    "iso:country":"US",
    "sg:address":"2004 N Valley Mills Dr",
    "sg:city":"Waco",
    "sg:classifiers":[
        {
            "category":"Professional",
            "type":"Services"
        }
    ],
    "sg:phone":"+1 254 772 6614",
    "sg:postcode":"76710",
    "sg:province":"TX",
    "sg:tags":[
        "establishment"
    ],
    "wof:name":"A Child's Dream",
    "wof:placetype":"venue"
},
  "geometry": {"coordinates":[-97.20420300000001,31.532703],"type":"Point"}
}