{
  "type": "Feature",
  "properties": {
    "iso:country":"US",
    "sg:address":"11939 Eastex Fwy",
    "sg:city":"Houston",
    "sg:classifiers":[
        {
            "category":"Bars & Pubs",
            "subcategory":"Sports Bar",
            "type":"Food & Drink"
        }
    ],
    "sg:phone":"+1 281 227 0775",
    "sg:postcode":"77039",
    "sg:province":"TX",
    "wof:name":"Sports Bar La Bola 8",
    "wof:placetype":"venue"
},
  "geometry": {"coordinates":[-95.314933,29.897479],"type":"Point"}
}