{
  "type": "Feature",
  "properties": {
    "iso:country":"US",
    "sg:address":"7004 Ranch Road 620 N",
    "sg:city":"Austin",
    "sg:classifiers":[
        {
            "category":"Food & Beverages",
            "subcategory":"Liquor & Beverages",
            "type":"Retail Goods"
        }
    ],
    "sg:phone":"+1 512 335 1755",
    "sg:postcode":"78732",
    "sg:province":"TX",
    "sg:tags":[
        "beer",
        "spirit",
        "wine"
    ],
    "wof:name":"Double B Liquor",
    "wof:placetype":"venue"
},
  "geometry": {"coordinates":[-97.85408700000001,30.403469],"type":"Point"}
}