{
  "type": "Feature",
  "properties": {
    "iso:country":"US",
    "sg:address":"2528 Elm St",
    "sg:city":"Dallas",
    "sg:classifiers":[
        {
            "category":"Professional",
            "subcategory":"Computer Services",
            "type":"Services"
        }
    ],
    "sg:phone":"+1 214 634 4477",
    "sg:postcode":"75226",
    "sg:province":"TX",
    "sg:tags":[
        "repair"
    ],
    "wof:name":"Intervisions",
    "wof:placetype":"venue"
},
  "geometry": {"coordinates":[-96.788498,32.783699],"type":"Point"}
}