{
  "type": "Feature",
  "properties": {
    "iso:country":"US",
    "sg:address":"8517 Lockheed Dr",
    "sg:city":"El Paso",
    "sg:classifiers":[
        {
            "category":"Professional",
            "subcategory":"Lawyer & Legal Services",
            "type":"Services"
        }
    ],
    "sg:phone":"+1 915 779 3595",
    "sg:postcode":"79925",
    "sg:province":"TX",
    "sg:tags":[
        "attorney"
    ],
    "wof:name":"Sergio Gonzalez Law Office",
    "wof:placetype":"venue"
},
  "geometry": {"coordinates":[-106.37711,31.792491],"type":"Point"}
}