{
  "type": "Feature",
  "properties": {
    "iso:country":"US",
    "sg:address":"30224 Oak Tree Dr",
    "sg:city":"Georgetown",
    "sg:classifiers":[
        {
            "category":"Professional",
            "type":"Services"
        }
    ],
    "sg:phone":"+1 512 869 2626",
    "sg:postcode":"78628",
    "sg:province":"TX",
    "wof:name":"Trovatore",
    "wof:placetype":"venue"
},
  "geometry": {"coordinates":[-97.673776,30.706822],"type":"Point"}
}