{
  "type": "Feature",
  "properties": {
    "iso:country":"US",
    "sg:address":"3504 Brees St",
    "sg:city":"Plano",
    "sg:classifiers":[
        {
            "category":"Professional",
            "subcategory":"Management & Consulting",
            "type":"Services"
        }
    ],
    "sg:phone":"+1 972 867 7026",
    "sg:postcode":"75075",
    "sg:province":"TX",
    "sg:tags":[
        "consultant",
        "training"
    ],
    "wof:name":"Achievers Cross Training",
    "wof:placetype":"venue"
},
  "geometry": {"coordinates":[-96.76119,33.029612],"type":"Point"}
}