{
  "type": "Feature",
  "properties": {
    "iso:country":"US",
    "sg:address":"959 W Centerville Rd",
    "sg:city":"Garland",
    "sg:classifiers":[
        {
            "category":"Insurance",
            "subcategory":"Insurance Agent",
            "type":"Services"
        }
    ],
    "sg:phone":"+1 972 270 4620",
    "sg:postcode":"75041",
    "sg:province":"TX",
    "wof:name":"Stan Luckie & Assoc Insurance",
    "wof:placetype":"venue"
},
  "geometry": {"coordinates":[-96.644954,32.859391],"type":"Point"}
}