{
  "type": "Feature",
  "properties": {
    "iso:country":"US",
    "sg:address":"702 Enterprise St",
    "sg:city":"Laredo",
    "sg:classifiers":[
        {
            "category":"Freight",
            "type":"Transportation"
        }
    ],
    "sg:phone":"+1 956 723 7777",
    "sg:postcode":"78045",
    "sg:province":"TX",
    "sg:tags":[
        "operator",
        "trucking"
    ],
    "wof:name":"Pakias Transport Inc",
    "wof:placetype":"venue"
},
  "geometry": {"coordinates":[-99.534734,27.613305],"type":"Point"}
}