{
  "type": "Feature",
  "properties": {
    "iso:country":"US",
    "sg:address":"1812 Adina St",
    "sg:city":"Austin",
    "sg:classifiers":[
        {
            "category":"Building & Trades",
            "subcategory":"Construction",
            "type":"Services"
        }
    ],
    "sg:phone":"+1 512 926 3306",
    "sg:postcode":"78721",
    "sg:province":"TX",
    "sg:tags":[
        "industrial"
    ],
    "wof:name":"McKinney Construction Co",
    "wof:placetype":"venue"
},
  "geometry": {"coordinates":[-97.67898599999999,30.283932],"type":"Point"}
}