{
  "type": "Feature",
  "properties": {
    "iso:country":"US",
    "sg:address":"104 Cannan Dr",
    "sg:city":"Angleton",
    "sg:classifiers":[
        {
            "category":"Government",
            "subcategory":"Police Station",
            "type":"Public Place"
        }
    ],
    "sg:phone":"+1 979 849 2383",
    "sg:postcode":"77515",
    "sg:province":"TX",
    "sg:tags":[
        "department"
    ],
    "sg:website":"http://www.brazoria-county.com",
    "wof:name":"Angleton Police Department",
    "wof:placetype":"venue"
},
  "geometry": {"coordinates":[-95.43295999999999,29.182609],"type":"Point"}
}