{
  "type": "Feature",
  "properties": {
    "iso:country":"US",
    "sg:address":"812 N Mcdonald St",
    "sg:city":"Mckinney",
    "sg:classifiers":[
        {
            "category":"Retail",
            "subcategory":"Storage",
            "type":"Services"
        },
        {
            "category":"Manufacturing",
            "subcategory":"Paper Products",
            "type":"Manufacturing & Wholesale Goods"
        }
    ],
    "sg:phone":"+1 972 542 7867",
    "sg:postcode":"75069",
    "sg:province":"TX",
    "sg:tags":[
        "fiber",
        "automobile",
        "household",
        "commercial",
        "boxes-corrugated",
        "self",
        "boat"
    ],
    "sg:website":"http://www.ustoreit.com/?utm_source=yellowpages&utm_medium=premium&utm_campaign=yp2010&phid=0449",
    "wof:name":"U-Store-It",
    "wof:placetype":"venue"
},
  "geometry": {"coordinates":[-96.61185,33.205565],"type":"Point"}
}