{
  "type": "Feature",
  "properties": {
    "iso:country":"US",
    "sg:address":"1331 W. Grand Parkway N. Suite 240",
    "sg:city":"Katy",
    "sg:classifiers":[
        {
            "category":"Health Services",
            "subcategory":"Doctor",
            "type":"Services"
        }
    ],
    "sg:phone":"+1 281 392 2266",
    "sg:postcode":"77493",
    "sg:province":"TX",
    "sg:tags":[
        "physician",
        "surgeons",
        "medicine",
        "surgeon",
        "rehabilitation",
        "physical"
    ],
    "sg:website":"http://www.obgynaffiliates.net",
    "wof:name":"Lin, Selina Ob Gyn",
    "wof:placetype":"venue"
},
  "geometry": {"coordinates":[-95.77713799999999,29.792933],"type":"Point"}
}