{
  "type": "Feature",
  "properties": {
    "iso:country":"US",
    "sg:address":"11014 S Sam Houston Pkwy W",
    "sg:city":"Houston",
    "sg:classifiers":[
        {
            "category":"Travel",
            "subcategory":"Hotels & Motels",
            "type":"Entertainment"
        }
    ],
    "sg:phone":"+1 713 272 9200",
    "sg:postcode":"77031",
    "sg:province":"TX",
    "wof:name":"Mustang Inn",
    "wof:placetype":"venue"
},
  "geometry": {"coordinates":[-95.5411,29.6465],"type":"Point"}
}