{
  "type": "Feature",
  "properties": {
    "iso:country":"US",
    "sg:address":"507 W Panola St",
    "sg:city":"Carthage",
    "sg:classifiers":[
        {
            "category":"Personal",
            "subcategory":"Barber",
            "type":"Services"
        }
    ],
    "sg:phone":"+1 903 693 9272",
    "sg:postcode":"75633",
    "sg:province":"TX",
    "sg:tags":[
        "shop"
    ],
    "wof:name":"Clint's Barber Shop",
    "wof:placetype":"venue"
},
  "geometry": {"coordinates":[-94.347345,32.156578],"type":"Point"}
}