{
  "type": "Feature",
  "properties": {
    "iso:country":"US",
    "sg:address":"211 W 7th St",
    "sg:city":"Plainview",
    "sg:classifiers":[
        {
            "category":"Organizations",
            "subcategory":"Religious Organization",
            "type":"Services"
        }
    ],
    "sg:phone":"+1 806 293 0085",
    "sg:postcode":"79072",
    "sg:province":"TX",
    "sg:tags":[
        "church"
    ],
    "wof:name":"Our Lady Of Guadalupe Church",
    "wof:placetype":"venue"
},
  "geometry": {"coordinates":[-101.705451,34.186889],"type":"Point"}
}