{
  "type": "Feature",
  "properties": {
    "iso:country":"US",
    "sg:address":"9939 Twin Shores Dr",
    "sg:city":"Willis",
    "sg:classifiers":[
        {
            "category":"Manufacturing",
            "subcategory":"Tools & Machinery",
            "type":"Manufacturing & Wholesale Goods"
        }
    ],
    "sg:phone":"+1 936 890 9043",
    "sg:postcode":"77318",
    "sg:province":"TX",
    "sg:tags":[
        "machine",
        "shop"
    ],
    "wof:name":"Aj Machine",
    "wof:placetype":"venue"
},
  "geometry": {"coordinates":[-95.553735,30.387897],"type":"Point"}
}