{
  "type": "Feature",
  "properties": {
    "iso:country":"US",
    "sg:address":"1500 Scenic Dr Apt 306",
    "sg:city":"Austin",
    "sg:classifiers":[
        {
            "category":"Sports & Exercise",
            "subcategory":"Playing Field",
            "type":"Entertainment"
        }
    ],
    "sg:phone":"+1 512 784 3888",
    "sg:postcode":"78703",
    "sg:province":"TX",
    "sg:tags":[
        "farm",
        "game"
    ],
    "sg:website":"http://www.palestar.com",
    "wof:name":"Koorosh The Great, Inc.",
    "wof:placetype":"venue"
},
  "geometry": {"coordinates":[-97.78379,30.296514],"type":"Point"}
}