{
  "type": "Feature",
  "properties": {
    "iso:country":"US",
    "sg:address":"13400 Blanco Rd",
    "sg:city":"San Antonio",
    "sg:classifiers":[
        {
            "category":"Building & Trades",
            "subcategory":"Construction",
            "type":"Services"
        }
    ],
    "sg:phone":"+1 210 492 1131",
    "sg:postcode":"78216",
    "sg:province":"TX",
    "sg:tags":[
        "contractor"
    ],
    "wof:name":"Village Contractors",
    "wof:placetype":"venue"
},
  "geometry": {"coordinates":[-98.518192,29.570166],"type":"Point"}
}