{
  "type": "Feature",
  "properties": {
    "iso:country":"US",
    "sg:address":"517 Parade Dr",
    "sg:city":"Corpus Christi",
    "sg:classifiers":[
        {
            "category":"Professional",
            "subcategory":"Accounting & Tax Preparation",
            "type":"Services"
        }
    ],
    "sg:phone":"+1 361 854 6525",
    "sg:postcode":"78412",
    "sg:province":"TX",
    "wof:name":"Danny C Woolsey",
    "wof:placetype":"venue"
},
  "geometry": {"coordinates":[-97.354084,27.717121],"type":"Point"}
}