{
  "type": "Feature",
  "properties": {
    "iso:country":"US",
    "sg:address":"601 E Walnut St",
    "sg:city":"Garland",
    "sg:classifiers":[
        {
            "category":"Building & Trades",
            "subcategory":"Construction",
            "type":"Services"
        }
    ],
    "sg:phone":"+1 972 272 9199",
    "sg:postcode":"75040",
    "sg:province":"TX",
    "sg:tags":[
        "contractor"
    ],
    "wof:name":"Ivy & Oak Landscape Services",
    "wof:placetype":"venue"
},
  "geometry": {"coordinates":[-96.624296,32.915037],"type":"Point"}
}