{
  "type": "Feature",
  "properties": {
    "iso:country":"US",
    "sg:address":"7621 Airline Dr",
    "sg:city":"Houston",
    "sg:classifiers":[
        {
            "category":"Banks & Credit Unions",
            "subcategory":"Financial Services",
            "type":"Services"
        }
    ],
    "sg:phone":"+1 281 448 6136",
    "sg:postcode":"77037",
    "sg:province":"TX",
    "sg:tags":[
        "investment",
        "closed"
    ],
    "wof:name":"Mahadev Investments Inc",
    "wof:placetype":"venue"
},
  "geometry": {"coordinates":[-95.384968,29.872048],"type":"Point"}
}