{
  "type": "Feature",
  "properties": {
    "iso:country":"US",
    "sg:address":"2990 Laurel St",
    "sg:city":"Beaumont",
    "sg:classifiers":[
        {
            "category":"Social Services",
            "subcategory":"Child Care",
            "type":"Services"
        }
    ],
    "sg:phone":"+1 409 832 4455",
    "sg:postcode":"77702",
    "sg:province":"TX",
    "sg:tags":[
        "center"
    ],
    "wof:name":"Hills Nursery",
    "wof:placetype":"venue"
},
  "geometry": {"coordinates":[-94.13373900000001,30.083663],"type":"Point"}
}