{
  "type": "Feature",
  "properties": {
    "iso:country":"US",
    "sg:address":"1188 W Broad St",
    "sg:city":"Mansfield",
    "sg:classifiers":[
        {
            "category":"Government",
            "subcategory":"Office",
            "type":"Public Place"
        }
    ],
    "sg:phone":"+1 817 473 0253",
    "sg:postcode":"76063",
    "sg:province":"TX",
    "sg:tags":[
        "village"
    ],
    "wof:name":"Neighborhood Resources Dev",
    "wof:placetype":"venue"
},
  "geometry": {"coordinates":[-97.162059,32.556425],"type":"Point"}
}