{
  "type": "Feature",
  "properties": {
    "iso:country":"US",
    "sg:address":"15627 Big Trail Dr",
    "sg:city":"San Antonio",
    "sg:classifiers":[
        {
            "category":"Professional",
            "subcategory":"Management & Consulting",
            "type":"Services"
        }
    ],
    "sg:phone":"+1 210 340 8045",
    "sg:postcode":"78232",
    "sg:province":"TX",
    "wof:name":"Kneese Land Management Co",
    "wof:placetype":"venue"
},
  "geometry": {"coordinates":[-98.51175000000001,29.585151],"type":"Point"}
}