{
  "type": "Feature",
  "properties": {
    "iso:country":"US",
    "sg:address":"2800 Culebra Rd",
    "sg:city":"San Antonio",
    "sg:classifiers":[
        {
            "category":"Food & Beverages",
            "subcategory":"Meat & Fish",
            "type":"Retail Goods"
        }
    ],
    "sg:phone":"+1 210 432 2170",
    "sg:postcode":"78228",
    "sg:province":"TX",
    "wof:name":"Culebra Meat Market",
    "wof:placetype":"venue"
},
  "geometry": {"coordinates":[-98.55439200000001,29.447993],"type":"Point"}
}