{
  "type": "Feature",
  "properties": {
    "iso:country":"US",
    "sg:address":"1401 Hawthorne St",
    "sg:city":"El Paso",
    "sg:classifiers":[
        {
            "category":"Professional",
            "subcategory":"Management & Consulting",
            "type":"Services"
        }
    ],
    "sg:phone":"+1 915 534 7620",
    "sg:postcode":"79902",
    "sg:province":"TX",
    "sg:tags":[
        "business"
    ],
    "wof:name":"Forensic Anthropology Services",
    "wof:placetype":"venue"
},
  "geometry": {"coordinates":[-106.500066,31.76567],"type":"Point"}
}