{
  "type": "Feature",
  "properties": {
    "iso:country":"US",
    "sg:address":"7 Rolling Glen",
    "sg:city":"Tomball",
    "sg:classifiers":[
        {
            "category":"Professional",
            "type":"Services"
        }
    ],
    "sg:phone":"+1 281 370 4308",
    "sg:postcode":"77375",
    "sg:province":"TX",
    "wof:name":"ADJ Appliances",
    "wof:placetype":"venue"
},
  "geometry": {"coordinates":[-95.583,30.030261],"type":"Point"}
}