{
  "type": "Feature",
  "properties": {
    "iso:country":"US",
    "sg:address":"375 Cedar Sage Dr",
    "sg:city":"Garland",
    "sg:classifiers":[
        {
            "category":"Insurance",
            "subcategory":"Insurance Agent",
            "type":"Services"
        },
        {
            "category":"Insurance",
            "subcategory":"Hazard Insurance",
            "type":"Services"
        }
    ],
    "sg:phone":"+1 972 530 2681",
    "sg:postcode":"75040",
    "sg:province":"TX",
    "sg:tags":[
        "consultant",
        "commercial",
        "analyst",
        "business"
    ],
    "sg:website":"http://www.statefarm.com",
    "wof:name":"State Farm Insurance",
    "wof:placetype":"venue"
},
  "geometry": {"coordinates":[-96.611132,32.952959],"type":"Point"}
}