{
  "type": "Feature",
  "properties": {
    "iso:country":"US",
    "sg:address":"3716 Stoney Creek Rd",
    "sg:city":"Fort Worth",
    "sg:classifiers":[
        {
            "category":"Retail",
            "subcategory":"Car Wash",
            "type":"Services"
        }
    ],
    "sg:phone":"+1 817 738 6756",
    "sg:postcode":"76116",
    "sg:province":"TX",
    "sg:tags":[
        "automatic"
    ],
    "wof:name":"Zanes Financial Services Inc",
    "wof:placetype":"venue"
},
  "geometry": {"coordinates":[-97.434438,32.69623],"type":"Point"}
}