{
  "type": "Feature",
  "properties": {
    "iso:country":"US",
    "sg:address":"5541 N Colony Blvd",
    "sg:city":"The Colony",
    "sg:classifiers":[
        {
            "category":"Building & Trades",
            "subcategory":"Cleaning & Sanitation",
            "type":"Services"
        }
    ],
    "sg:phone":"+1 972 624 0026",
    "sg:postcode":"75056",
    "sg:province":"TX",
    "sg:tags":[
        "window"
    ],
    "wof:name":"All Clean Window Cleaning",
    "wof:placetype":"venue"
},
  "geometry": {"coordinates":[-96.86550099999999,33.097564],"type":"Point"}
}