{
  "type": "Feature",
  "properties": {
    "iso:country":"US",
    "sg:address":"4424 N Shepherd Dr",
    "sg:city":"Houston",
    "sg:classifiers":[
        {
            "category":"Retail",
            "subcategory":"Event Space",
            "type":"Services"
        }
    ],
    "sg:phone":"+1 713 697 7560",
    "sg:postcode":"77018",
    "sg:province":"TX",
    "sg:tags":[
        "venue"
    ],
    "wof:name":"Star Party Hall",
    "wof:placetype":"venue"
},
  "geometry": {"coordinates":[-95.40992199999999,29.829486],"type":"Point"}
}