{
  "type": "Feature",
  "properties": {
    "iso:country":"US",
    "sg:address":"7905 Bandera Rd",
    "sg:city":"San Antonio",
    "sg:classifiers":[
        {
            "category":"Restaurant",
            "type":"Food & Drink"
        }
    ],
    "sg:menulink":"http://www.allmenus.com/tx/san-antonio/15014-tios-mexican-restaurant/menu/",
    "sg:phone":"+1 210 523 8888",
    "sg:postcode":"78250",
    "sg:province":"TX",
    "sg:tags":[
        "mexican"
    ],
    "wof:name":"Tios Mexican Restaurant",
    "wof:placetype":"venue"
},
  "geometry": {"coordinates":[-98.633246,29.513541],"type":"Point"}
}