{
  "type": "Feature",
  "properties": {
    "iso:country":"US",
    "sg:address":"2118 Edwin St",
    "sg:city":"Fort Worth",
    "sg:classifiers":[
        {
            "category":"Professional",
            "subcategory":"Management & Consulting",
            "type":"Services"
        }
    ],
    "sg:phone":"+1 817 846 4776",
    "sg:postcode":"76110",
    "sg:province":"TX",
    "sg:tags":[
        "industrial"
    ],
    "wof:name":"Joe Greenslade",
    "wof:placetype":"venue"
},
  "geometry": {"coordinates":[-97.350075,32.727882],"type":"Point"}
}