{
  "type": "Feature",
  "properties": {
    "iso:country":"US",
    "sg:address":"3157 S 11th St",
    "sg:city":"Abilene",
    "sg:classifiers":[
        {
            "category":"Professional",
            "subcategory":"Business Services",
            "type":"Services"
        }
    ],
    "sg:phone":"+1 325 690 1133",
    "sg:postcode":"79605",
    "sg:province":"TX",
    "wof:name":"Poetic Records",
    "wof:placetype":"venue"
},
  "geometry": {"coordinates":[-99.762398,32.437394],"type":"Point"}
}