{
  "type": "Feature",
  "properties": {
    "iso:country":"US",
    "sg:address":"305 Main St",
    "sg:city":"Liberty Hill",
    "sg:classifiers":[
        {
            "category":"Wholesale",
            "subcategory":"Farm Supplies",
            "type":"Manufacturing & Wholesale Goods"
        }
    ],
    "sg:phone":"+1 512 778 6400",
    "sg:postcode":"78642",
    "sg:province":"TX",
    "sg:tags":[
        "feed"
    ],
    "wof:name":"Liberty Hill Feed & Seed",
    "wof:placetype":"venue"
},
  "geometry": {"coordinates":[-97.910698,30.665507],"type":"Point"}
}