{
  "type": "Feature",
  "properties": {
    "iso:country":"US",
    "sg:address":"701 N San Jacinto St",
    "sg:city":"Houston",
    "sg:classifiers":[
        {
            "category":"Sports & Exercise",
            "subcategory":"Gym",
            "type":"Entertainment"
        }
    ],
    "sg:phone":"+1 713 755 8407",
    "sg:postcode":"77002",
    "sg:province":"TX",
    "sg:tags":[
        "fitness",
        "physical",
        "facility"
    ],
    "wof:name":"Sheriffs Dept",
    "wof:placetype":"venue"
},
  "geometry": {"coordinates":[-95.35700799999999,29.764996],"type":"Point"}
}