{
  "type": "Feature",
  "properties": {
    "iso:country":"US",
    "sg:address":"3011 34th St",
    "sg:city":"Lubbock",
    "sg:classifiers":[
        {
            "category":"Personal",
            "subcategory":"Beauty Salon",
            "type":"Services"
        }
    ],
    "sg:phone":"+1 806 777 6832",
    "sg:postcode":"79410",
    "sg:province":"TX",
    "wof:name":"Hair We Are",
    "wof:placetype":"venue"
},
  "geometry": {"coordinates":[-101.88108200000001,33.563191],"type":"Point"}
}