{
  "type": "Feature",
  "properties": {
    "iso:country":"US",
    "sg:address":"3419 N Main St",
    "sg:city":"Fort Worth",
    "sg:classifiers":[
        {
            "category":"Retail",
            "subcategory":"Self-service Laundry",
            "type":"Services"
        }
    ],
    "sg:phone":"+1 817 781 3357",
    "sg:postcode":"76106",
    "sg:province":"TX",
    "sg:tags":[
        "coin"
    ],
    "wof:name":"Northside Coin Laundry",
    "wof:placetype":"venue"
},
  "geometry": {"coordinates":[-97.351544,32.808191],"type":"Point"}
}