{
  "type": "Feature",
  "properties": {
    "iso:country":"US",
    "sg:address":"800 Panay Way Dr",
    "sg:city":"Fort Worth",
    "sg:classifiers":[
        {
            "category":"Building & Trades",
            "subcategory":"Cleaning & Sanitation",
            "type":"Services"
        }
    ],
    "sg:phone":"+1 817 246 0052",
    "sg:postcode":"76108",
    "sg:province":"TX",
    "sg:tags":[
        "maintenance"
    ],
    "wof:name":"Georgia Cleaning Services",
    "wof:placetype":"venue"
},
  "geometry": {"coordinates":[-97.49614099999999,32.747222],"type":"Point"}
}