{
  "type": "Feature",
  "properties": {
    "iso:country":"US",
    "sg:address":"1100 E 5th St",
    "sg:city":"Austin",
    "sg:classifiers":[
        {
            "category":"Professional",
            "subcategory":"Printing & Photocopies",
            "type":"Services"
        },
        {
            "category":"Professional",
            "subcategory":"Computer Services",
            "type":"Services"
        }
    ],
    "sg:phone":"+1 512 462 9190",
    "sg:postcode":"78702",
    "sg:province":"TX",
    "sg:tags":[
        "graphic",
        "duplicating",
        "copying"
    ],
    "wof:name":"Accent Computer Graphics",
    "wof:placetype":"venue"
},
  "geometry": {"coordinates":[-97.731916,30.263856],"type":"Point"}
}