{
  "type": "Feature",
  "properties": {
    "iso:country":"US",
    "sg:address":"18610 Kuykendahl Rd",
    "sg:city":"Spring",
    "sg:classifiers":[
        {
            "category":"Travel",
            "subcategory":"Travel Agent",
            "type":"Entertainment"
        }
    ],
    "sg:phone":"+1 281 353 4804",
    "sg:postcode":"77379",
    "sg:province":"TX",
    "sg:tags":[
        "agency"
    ],
    "wof:name":"Ace Travel House",
    "wof:placetype":"venue"
},
  "geometry": {"coordinates":[-95.492651,30.050339],"type":"Point"}
}