{
  "type": "Feature",
  "properties": {
    "iso:country":"US",
    "sg:address":"2501 Oak Lawn Ave",
    "sg:city":"Dallas",
    "sg:classifiers":[
        {
            "category":"Mining & Drilling",
            "type":"Manufacturing & Wholesale Goods"
        }
    ],
    "sg:phone":"+1 214 521 5757",
    "sg:postcode":"75219",
    "sg:province":"TX",
    "sg:tags":[
        "development",
        "gas",
        "oil",
        "exploration"
    ],
    "wof:name":"Geo Co",
    "wof:placetype":"venue"
},
  "geometry": {"coordinates":[-96.814181,32.804311],"type":"Point"}
}