{
  "type": "Feature",
  "properties": {
    "iso:country":"US",
    "sg:address":"17131 Ivy Green",
    "sg:city":"San Antonio",
    "sg:classifiers":[
        {
            "category":"Retail",
            "subcategory":"Repair Shop",
            "type":"Services"
        }
    ],
    "sg:phone":"+1 210 650 3458",
    "sg:postcode":"78247",
    "sg:province":"TX",
    "sg:tags":[
        "lawn",
        "mower"
    ],
    "wof:name":"Eddies Lawn Mower Repair",
    "wof:placetype":"venue"
},
  "geometry": {"coordinates":[-98.383486,29.597207],"type":"Point"}
}