{
  "type": "Feature",
  "properties": {
    "iso:country":"US",
    "sg:address":"13391 George Foster Rd",
    "sg:city":"Ponder",
    "sg:classifiers":[
        {
            "category":"Building & Trades",
            "subcategory":"Plumbing",
            "type":"Services"
        }
    ],
    "sg:phone":"+1 940 482 6005",
    "sg:postcode":"76259",
    "sg:province":"TX",
    "sg:tags":[
        "contractor"
    ],
    "wof:name":"Southwestern Plumbing Co",
    "wof:placetype":"venue"
},
  "geometry": {"coordinates":[-97.369703,33.237098],"type":"Point"}
}