{
  "type": "Feature",
  "properties": {
    "iso:country":"US",
    "sg:address":"3410 Far West Blvd",
    "sg:city":"Austin",
    "sg:classifiers":[
        {
            "category":"Professional",
            "subcategory":"Lawyer & Legal Services",
            "type":"Services"
        }
    ],
    "sg:phone":"+1 512 687 0765",
    "sg:postcode":"78731",
    "sg:province":"TX",
    "wof:name":"Law Office Of Robert R Kiesling",
    "wof:placetype":"venue"
},
  "geometry": {"coordinates":[-97.750146,30.352221],"type":"Point"}
}