{
  "type": "Feature",
  "properties": {
    "iso:country":"US",
    "sg:address":"9130 Jollyville Rd",
    "sg:city":"Austin",
    "sg:classifiers":[
        {
            "category":"Banks & Credit Unions",
            "subcategory":"Bank",
            "type":"Services"
        }
    ],
    "sg:phone":"+1 512 340 0077",
    "sg:postcode":"78759",
    "sg:province":"TX",
    "sg:tags":[
        "loan",
        "real estate"
    ],
    "sg:website":"www.txmortgageconsultants.com",
    "wof:name":"Texas Mortgage Consultants",
    "wof:placetype":"venue"
},
  "geometry": {"coordinates":[-97.74159400000001,30.380305],"type":"Point"}
}