{
  "type": "Feature",
  "properties": {
    "iso:country":"US",
    "sg:address":"3719 Dustin Trl",
    "sg:city":"Arlington",
    "sg:classifiers":[
        {
            "category":"Professional",
            "type":"Services"
        }
    ],
    "sg:phone":"+1 817 473 7819",
    "sg:postcode":"76016",
    "sg:province":"TX",
    "wof:name":"Gary W Reese",
    "wof:placetype":"venue"
},
  "geometry": {"coordinates":[-97.16179200000001,32.686491],"type":"Point"}
}