{
  "type": "Feature",
  "properties": {
    "iso:country":"US",
    "sg:address":"625 Manchester Dr",
    "sg:city":"Mansfield",
    "sg:classifiers":[
        {
            "category":"Manufacturing",
            "subcategory":"Tools & Machinery",
            "type":"Manufacturing & Wholesale Goods"
        }
    ],
    "sg:phone":"+1 817 705 4812",
    "sg:postcode":"76063",
    "sg:province":"TX",
    "sg:tags":[
        "mfg"
    ],
    "wof:name":"Mike Utzmans Co",
    "wof:placetype":"venue"
},
  "geometry": {"coordinates":[-97.13105,32.608295],"type":"Point"}
}