{
  "type": "Feature",
  "properties": {
    "iso:country":"US",
    "sg:address":"9540 Casa Linda Plz",
    "sg:city":"Dallas",
    "sg:classifiers":[
        {
            "category":"Shopping",
            "subcategory":"Mobile Phones",
            "type":"Retail Goods"
        }
    ],
    "sg:phone":"+1 214 321 1531",
    "sg:postcode":"75218",
    "sg:province":"TX",
    "wof:name":"T-Mobile",
    "wof:placetype":"venue"
},
  "geometry": {"coordinates":[-96.703883,32.835192],"type":"Point"}
}