{
  "type": "Feature",
  "properties": {
    "iso:country":"US",
    "sg:address":"107 Yale St",
    "sg:city":"Houston",
    "sg:classifiers":[
        {
            "category":"Wholesale",
            "subcategory":"Electrical",
            "type":"Manufacturing & Wholesale Goods"
        }
    ],
    "sg:phone":"+1 713 869 3356",
    "sg:postcode":"77007",
    "sg:province":"TX",
    "sg:tags":[
        "electric",
        "motor"
    ],
    "wof:name":"Heights",
    "wof:placetype":"venue"
},
  "geometry": {"coordinates":[-95.398689,29.771245],"type":"Point"}
}