{
  "type": "Feature",
  "properties": {
    "iso:country":"US",
    "sg:address":"1112 N Maddox Ave",
    "sg:city":"Dumas",
    "sg:classifiers":[
        {
            "category":"Building & Trades",
            "subcategory":"Construction",
            "type":"Services"
        }
    ],
    "sg:phone":"+1 806 935 1237",
    "sg:postcode":"79029",
    "sg:province":"TX",
    "sg:tags":[
        "excavation",
        "contractor"
    ],
    "wof:name":"Schnaufer Backhoe Service",
    "wof:placetype":"venue"
},
  "geometry": {"coordinates":[-101.96330500000001,35.889402],"type":"Point"}
}