{
  "type": "Feature",
  "properties": {
    "iso:country":"US",
    "sg:address":"8109 Smith Rd",
    "sg:city":"Lumberton",
    "sg:classifiers":[
        {
            "category":"Banks & Credit Unions",
            "subcategory":"Bank",
            "type":"Services"
        }
    ],
    "sg:phone":"+1 409 842 5233",
    "sg:postcode":"77657",
    "sg:province":"TX",
    "sg:website":"http://www.tccfcu.org",
    "wof:name":"Texas Coastal Credit Union",
    "wof:placetype":"venue"
},
  "geometry": {"coordinates":[-94.189667,30.225148],"type":"Point"}
}