{
  "type": "Feature",
  "properties": {
    "iso:country":"US",
    "sg:address":"707 Spofford St",
    "sg:city":"Austin",
    "sg:classifiers":[
        {
            "category":"Wholesale",
            "subcategory":"Medical Equipment & Supplies",
            "type":"Manufacturing & Wholesale Goods"
        },
        {
            "category":"Shopping",
            "subcategory":"Pharmacy",
            "type":"Retail Goods"
        }
    ],
    "sg:phone":"+1 512 450 1103",
    "sg:postcode":"78704",
    "sg:province":"TX",
    "sg:tags":[
        "home",
        "health",
        "care"
    ],
    "sg:website":"http://www.knissmedical.com",
    "wof:name":"K Medical",
    "wof:placetype":"venue"
},
  "geometry": {"coordinates":[-97.766266,30.261273],"type":"Point"}
}