{
  "type": "Feature",
  "properties": {
    "iso:country":"US",
    "sg:address":"767 S Saunders St",
    "sg:city":"Seguin",
    "sg:classifiers":[
        {
            "category":"Social Services",
            "subcategory":"Child Care",
            "type":"Services"
        }
    ],
    "sg:phone":"+1 830 303 0417",
    "sg:postcode":"78155",
    "sg:province":"TX",
    "sg:tags":[
        "day"
    ],
    "wof:name":"Early Intervention Program",
    "wof:placetype":"venue"
},
  "geometry": {"coordinates":[-97.97099300000001,29.56208],"type":"Point"}
}