{
  "type": "Feature",
  "properties": {
    "iso:country":"US",
    "sg:address":"1333 Confederate Rd",
    "sg:city":"Houston",
    "sg:classifiers":[
        {
            "category":"Professional",
            "type":"Services"
        }
    ],
    "sg:phone":"+1 713 465 8879",
    "sg:postcode":"77055",
    "sg:province":"TX",
    "wof:name":"Adtech Technical Services",
    "wof:placetype":"venue"
},
  "geometry": {"coordinates":[-95.52813500000001,29.793588],"type":"Point"}
}