{
  "type": "Feature",
  "properties": {
    "iso:country":"US",
    "sg:address":"714 Sue Barnett Dr",
    "sg:city":"Houston",
    "sg:classifiers":[
        {
            "category":"Professional",
            "type":"Services"
        }
    ],
    "sg:phone":"+1 713 742 5558",
    "sg:postcode":"77018",
    "sg:province":"TX",
    "sg:tags":[
        "establishment"
    ],
    "wof:name":"Leon Baez Corp",
    "wof:placetype":"venue"
},
  "geometry": {"coordinates":[-95.413786,29.820578],"type":"Point"}
}