{
  "type": "Feature",
  "properties": {
    "iso:country":"US",
    "sg:address":"3000 Northview Dr",
    "sg:city":"Grapevine",
    "sg:classifiers":[
        {
            "category":"Professional",
            "subcategory":"Management & Consulting",
            "type":"Services"
        }
    ],
    "sg:phone":"+1 817 416 1629",
    "sg:postcode":"76051",
    "sg:province":"TX",
    "sg:tags":[
        "business"
    ],
    "wof:name":"Classic Design",
    "wof:placetype":"venue"
},
  "geometry": {"coordinates":[-97.114024,32.90356],"type":"Point"}
}