{
  "type": "Feature",
  "properties": {
    "iso:country":"US",
    "sg:address":"2821 W 5th St",
    "sg:city":"Fort Worth",
    "sg:classifiers":[
        {
            "category":"Wholesale",
            "subcategory":"Auto Parts",
            "type":"Manufacturing & Wholesale Goods"
        }
    ],
    "sg:phone":"+1 817 335 6942",
    "sg:postcode":"76107",
    "sg:province":"TX",
    "sg:tags":[
        "automotive"
    ],
    "wof:name":"Chandlers Auto Parts Warehouse",
    "wof:placetype":"venue"
},
  "geometry": {"coordinates":[-97.35799900000001,32.752933],"type":"Point"}
}