{
  "type": "Feature",
  "properties": {
    "iso:country":"US",
    "sg:address":"2502 Ave Q",
    "sg:city":"Snyder",
    "sg:classifiers":[
        {
            "category":"Food & Beverages",
            "subcategory":"Bakery",
            "type":"Retail Goods"
        }
    ],
    "sg:phone":"+1 325 573 3272",
    "sg:postcode":"79549",
    "sg:province":"TX",
    "sg:tags":[
        "doughnut"
    ],
    "wof:name":"Daylight Donuts",
    "wof:placetype":"venue"
},
  "geometry": {"coordinates":[-100.915852,32.717115],"type":"Point"}
}