{
  "type": "Feature",
  "properties": {
    "iso:country":"US",
    "sg:address":"2210 US Hwy 290 E",
    "sg:city":"Brenham",
    "sg:classifiers":[
        {
            "category":"Shopping",
            "subcategory":"Used Merchandise",
            "type":"Retail Goods"
        }
    ],
    "sg:phone":"+1 979 836 4500",
    "sg:postcode":"77833",
    "sg:province":"TX",
    "sg:tags":[
        "pawnbroker"
    ],
    "wof:name":"Cash Station Jewelry & Loans",
    "wof:placetype":"venue"
},
  "geometry": {"coordinates":[-96.366839,30.143105],"type":"Point"}
}