{
  "type": "Feature",
  "properties": {
    "iso:country":"US",
    "sg:address":"1322 Round Rock Ave",
    "sg:city":"Round Rock",
    "sg:classifiers":[
        {
            "category":"Retail",
            "subcategory":"Self-service Laundry",
            "type":"Services"
        }
    ],
    "sg:phone":"+1 512 246 8822",
    "sg:postcode":"78681",
    "sg:province":"TX",
    "sg:tags":[
        "carwash",
        "coin"
    ],
    "wof:name":"Wash Tub",
    "wof:placetype":"venue"
},
  "geometry": {"coordinates":[-97.69813000000001,30.51216],"type":"Point"}
}