{
  "type": "Feature",
  "properties": {
    "iso:country":"US",
    "sg:address":"4600 Pine Valley Dr",
    "sg:city":"Frisco",
    "sg:classifiers":[
        {
            "category":"Professional",
            "type":"Services"
        }
    ],
    "sg:phone":"+1 972 625 5169",
    "sg:postcode":"75034",
    "sg:province":"TX",
    "wof:name":"Susan Creekmore",
    "wof:placetype":"venue"
},
  "geometry": {"coordinates":[-96.84804800000001,33.100743],"type":"Point"}
}