{
  "type": "Feature",
  "properties": {
    "iso:country":"US",
    "sg:address":"100 S Las Vegas Trl",
    "sg:city":"Fort Worth",
    "sg:classifiers":[
        {
            "category":"Organizations",
            "subcategory":"Membership Organization",
            "type":"Services"
        }
    ],
    "sg:phone":"+1 817 246 5556",
    "sg:postcode":"76108",
    "sg:province":"TX",
    "wof:name":"White Settlement Citizens",
    "wof:placetype":"venue"
},
  "geometry": {"coordinates":[-97.468864,32.758127],"type":"Point"}
}