{
  "type": "Feature",
  "properties": {
    "iso:country":"US",
    "sg:address":"2206 Lancaster St",
    "sg:city":"San Marcos",
    "sg:classifiers":[
        {
            "category":"Travel",
            "subcategory":"Travel Agent",
            "type":"Entertainment"
        }
    ],
    "sg:phone":"+1 512 396 3503",
    "sg:postcode":"78666",
    "sg:province":"TX",
    "sg:tags":[
        "agency"
    ],
    "wof:name":"Getaway Travel",
    "wof:placetype":"venue"
},
  "geometry": {"coordinates":[-97.969979,29.889926],"type":"Point"}
}