{
  "type": "Feature",
  "properties": {
    "iso:country":"US",
    "sg:address":"510 S Ellis St",
    "sg:city":"Groesbeck",
    "sg:classifiers":[
        {
            "category":"Farming",
            "subcategory":"Farm & Veterinary Services",
            "type":"Manufacturing & Wholesale Goods"
        }
    ],
    "sg:phone":"+1 254 729 5405",
    "sg:postcode":"76642",
    "sg:province":"TX",
    "sg:tags":[
        "livestock"
    ],
    "wof:name":"Groesbeck Meat Co",
    "wof:placetype":"venue"
},
  "geometry": {"coordinates":[-96.536913,31.520667],"type":"Point"}
}