{
  "type": "Feature",
  "properties": {
    "iso:country":"US",
    "sg:address":"1107 S 11th St",
    "sg:city":"Port Aransas",
    "sg:classifiers":[
        {
            "category":"Real Estate",
            "subcategory":"Real Estate Agent",
            "type":"Services"
        },
        {
            "category":"Real Estate",
            "subcategory":"Real Estate Operator",
            "type":"Services"
        }
    ],
    "sg:phone":"+1 361 749 6226",
    "sg:postcode":"78373",
    "sg:province":"TX",
    "sg:tags":[
        "condominium"
    ],
    "wof:name":"Pelican Condominium Assn",
    "wof:placetype":"venue"
},
  "geometry": {"coordinates":[-97.06480999999999,27.823208],"type":"Point"}
}