{
  "type": "Feature",
  "properties": {
    "iso:country":"US",
    "sg:address":"6110 Janey Dr",
    "sg:city":"Austin",
    "sg:classifiers":[
        {
            "category":"Social Services",
            "type":"Services"
        }
    ],
    "sg:phone":"+1 512 458 5072",
    "sg:postcode":"78757",
    "sg:province":"TX",
    "wof:name":"Ronald E Stevenson",
    "wof:placetype":"venue"
},
  "geometry": {"coordinates":[-97.751015,30.342079],"type":"Point"}
}