{
  "type": "Feature",
  "properties": {
    "iso:country":"US",
    "sg:address":"1310 Appomattox Dr",
    "sg:city":"Texas City",
    "sg:classifiers":[
        {
            "category":"Social Services",
            "type":"Services"
        }
    ],
    "sg:phone":"+1 409 935 0533",
    "sg:postcode":"77591",
    "sg:province":"TX",
    "wof:name":"Christian Fmly Counseling Ctr",
    "wof:placetype":"venue"
},
  "geometry": {"coordinates":[-95.005168,29.394166],"type":"Point"}
}