{
  "type": "Feature",
  "properties": {
    "iso:country":"US",
    "sg:address":"419 Annex Ln",
    "sg:city":"Little Elm",
    "sg:classifiers":[
        {
            "category":"Restaurant",
            "type":"Food & Drink"
        }
    ],
    "sg:phone":"+1 972 292 1574",
    "sg:postcode":"75068",
    "sg:province":"TX",
    "sg:tags":[
        "eating"
    ],
    "wof:name":"Pesey Express Bbq",
    "wof:placetype":"venue"
},
  "geometry": {"coordinates":[-96.98813800000001,33.136975],"type":"Point"}
}