{
  "type": "Feature",
  "properties": {
    "iso:country":"US",
    "sg:address":"1420 Valwood Pkwy",
    "sg:city":"Carrollton",
    "sg:classifiers":[
        {
            "category":"Manufacturing",
            "subcategory":"Printing",
            "type":"Manufacturing & Wholesale Goods"
        }
    ],
    "sg:phone":"+1 972 418 6652",
    "sg:postcode":"75006",
    "sg:province":"TX",
    "sg:tags":[
        "directory",
        "hispanic",
        "telephone",
        "publish"
    ],
    "wof:name":"Hispanic Yellow Pages LLC",
    "wof:placetype":"venue"
},
  "geometry": {"coordinates":[-96.916867,32.938686],"type":"Point"}
}