{
  "type": "Feature",
  "properties": {
    "iso:country":"US",
    "sg:address":"11424 Chairman Dr",
    "sg:city":"Dallas",
    "sg:classifiers":[
        {
            "category":"Shopping",
            "subcategory":"Discount & Variety Stores",
            "type":"Retail Goods"
        }
    ],
    "sg:phone":"+1 214 342 1900",
    "sg:postcode":"75243",
    "sg:province":"TX",
    "sg:tags":[
        "wholesale"
    ],
    "sg:website":"www.gzintlinc.com",
    "wof:name":"G&Z International",
    "wof:placetype":"venue"
},
  "geometry": {"coordinates":[-96.697812,32.902936],"type":"Point"}
}