{
  "type": "Feature",
  "properties": {
    "iso:country":"US",
    "sg:address":"909 Curtiss St",
    "sg:city":"Schertz",
    "sg:classifiers":[
        {
            "category":"Food & Beverages",
            "subcategory":"Supermarket",
            "type":"Retail Goods"
        },
        {
            "category":"Food & Beverages",
            "subcategory":"Groceries & Convenience Stores",
            "type":"Retail Goods"
        }
    ],
    "sg:phone":"+1 210 658 0452",
    "sg:postcode":"78154",
    "sg:province":"TX",
    "sg:tags":[
        "super"
    ],
    "wof:name":"Handy Andy Supermarkets",
    "wof:placetype":"venue"
},
  "geometry": {"coordinates":[-98.26512700000001,29.557762],"type":"Point"}
}