{
  "type": "Feature",
  "properties": {
    "iso:country":"US",
    "sg:address":"458 Kirkwood Dr",
    "sg:city":"Dallas",
    "sg:classifiers":[
        {
            "category":"Professional",
            "subcategory":"Business Services",
            "type":"Services"
        }
    ],
    "sg:phone":"+1 214 660 0700",
    "sg:postcode":"75218",
    "sg:province":"TX",
    "sg:tags":[
        "appraiser"
    ],
    "wof:name":"Appraisal Review Svc",
    "wof:placetype":"venue"
},
  "geometry": {"coordinates":[-96.71060300000001,32.854481],"type":"Point"}
}