{
  "type": "Feature",
  "properties": {
    "iso:country":"US",
    "sg:address":"408 N 25th St",
    "sg:city":"Waco",
    "sg:classifiers":[
        {
            "category":"Manufacturing",
            "subcategory":"Printing",
            "type":"Manufacturing & Wholesale Goods"
        }
    ],
    "sg:phone":"+1 254 753 6541",
    "sg:postcode":"76707",
    "sg:province":"TX",
    "sg:tags":[
        "lithographic",
        "commercial"
    ],
    "wof:name":"Toten Crown Printing",
    "wof:placetype":"venue"
},
  "geometry": {"coordinates":[-97.154555,31.544029],"type":"Point"}
}