{
  "type": "Feature",
  "properties": {
    "iso:country":"US",
    "sg:address":"2910 E 5th St",
    "sg:city":"Austin",
    "sg:classifiers":[
        {
            "category":"Transit Center",
            "subcategory":"Passenger",
            "type":"Transportation"
        },
        {
            "category":"Local Transit",
            "type":"Transportation"
        }
    ],
    "sg:phone":"+1 512 852 7201",
    "sg:postcode":"78702",
    "sg:province":"TX",
    "sg:tags":[
        "line",
        "public"
    ],
    "wof:name":"First Transit Region Cent",
    "wof:placetype":"venue"
},
  "geometry": {"coordinates":[-97.709997,30.256216],"type":"Point"}
}