{
  "type": "Feature",
  "properties": {
    "iso:country":"US",
    "sg:address":"911 Southside Dr",
    "sg:city":"Killeen",
    "sg:classifiers":[
        {
            "category":"Professional",
            "subcategory":"Testing Lab",
            "type":"Services"
        }
    ],
    "sg:phone":"+1 254 286 6009",
    "sg:postcode":"76541",
    "sg:province":"TX",
    "sg:tags":[
        "laboratory"
    ],
    "wof:name":"Joan Dynamics",
    "wof:placetype":"venue"
},
  "geometry": {"coordinates":[-97.736519,31.111017],"type":"Point"}
}