{
  "type": "Feature",
  "properties": {
    "iso:country":"US",
    "sg:address":"2720 Westminister Ave",
    "sg:city":"Dallas",
    "sg:classifiers":[
        {
            "category":"Professional",
            "subcategory":"Business Services",
            "type":"Services"
        }
    ],
    "sg:phone":"+1 214 363 4687",
    "sg:postcode":"75205",
    "sg:province":"TX",
    "wof:name":"Cynthia Cummings Design",
    "wof:placetype":"venue"
},
  "geometry": {"coordinates":[-96.774908,32.849991],"type":"Point"}
}