{
  "type": "Feature",
  "properties": {
    "iso:country":"US",
    "sg:address":"1438 Thompson Pl",
    "sg:city":"San Antonio",
    "sg:classifiers":[
        {
            "category":"Professional",
            "subcategory":"Detective & Security Services",
            "type":"Services"
        }
    ],
    "sg:phone":"+1 210 435 2172",
    "sg:postcode":"78226",
    "sg:province":"TX",
    "sg:tags":[
        "alarm",
        "agency",
        "guard"
    ],
    "wof:name":"Texas Professional Security",
    "wof:placetype":"venue"
},
  "geometry": {"coordinates":[-98.55046,29.396175],"type":"Point"}
}