{
  "type": "Feature",
  "properties": {
    "iso:country":"US",
    "sg:address":"7000 Lawndale St",
    "sg:city":"Houston",
    "sg:classifiers":[
        {
            "category":"Organizations",
            "subcategory":"Religious Organization",
            "type":"Services"
        }
    ],
    "sg:phone":"+1 713 923 2531",
    "sg:postcode":"77023",
    "sg:province":"TX",
    "wof:name":"San Pblo-Trinity Presbt Church",
    "wof:placetype":"venue"
},
  "geometry": {"coordinates":[-95.30402599999999,29.721828],"type":"Point"}
}