{
  "type": "Feature",
  "properties": {
    "iso:country":"US",
    "sg:address":"1515 E Auburn St",
    "sg:city":"Lubbock",
    "sg:classifiers":[
        {
            "category":"Home & Garden",
            "subcategory":"Furniture",
            "type":"Retail Goods"
        }
    ],
    "sg:phone":"+1 806 763 9126",
    "sg:postcode":"79403",
    "sg:province":"TX",
    "sg:tags":[
        "store"
    ],
    "wof:name":"Furniture Nook",
    "wof:placetype":"venue"
},
  "geometry": {"coordinates":[-101.820672,33.599008],"type":"Point"}
}