{
  "type": "Feature",
  "properties": {
    "iso:country":"US",
    "sg:address":"10625 Veterans Memorial Dr",
    "sg:city":"Houston",
    "sg:classifiers":[
        {
            "category":"Professional",
            "type":"Services"
        },
        {
            "category":"Food & Beverages",
            "subcategory":"Liquor & Beverages",
            "type":"Retail Goods"
        }
    ],
    "sg:phone":"+1 281 448 4369",
    "sg:postcode":"77038",
    "sg:province":"TX",
    "sg:tags":[
        "beer",
        "establishment",
        "wine"
    ],
    "wof:name":"Bida Phuong",
    "wof:placetype":"venue"
},
  "geometry": {"coordinates":[-95.456976,29.933526],"type":"Point"}
}