{
  "type": "Feature",
  "properties": {
    "iso:country":"US",
    "sg:address":"4007 Park Circle Way",
    "sg:city":"Houston",
    "sg:classifiers":[
        {
            "category":"Professional",
            "subcategory":"Engineering",
            "type":"Services"
        }
    ],
    "sg:phone":"+1 281 286 4403",
    "sg:postcode":"77059",
    "sg:province":"TX",
    "sg:tags":[
        "engineer"
    ],
    "wof:name":"Dufour Consulting Svc",
    "wof:placetype":"venue"
},
  "geometry": {"coordinates":[-95.11846,29.606578],"type":"Point"}
}