{
  "type": "Feature",
  "properties": {
    "iso:country":"US",
    "sg:address":"5900 Yosemite Dr",
    "sg:city":"Fort Worth",
    "sg:classifiers":[
        {
            "category":"Health Services",
            "subcategory":"Doctor",
            "type":"Services"
        }
    ],
    "sg:phone":"+1 817 492 7838",
    "sg:postcode":"76112",
    "sg:province":"TX",
    "sg:tags":[
        "clinic"
    ],
    "wof:name":"JPS Health Network",
    "wof:placetype":"venue"
},
  "geometry": {"coordinates":[-97.22867599999999,32.749846],"type":"Point"}
}