{
  "type": "Feature",
  "properties": {
    "iso:country":"US",
    "sg:address":"4855 N Mesa St",
    "sg:city":"El Paso",
    "sg:classifiers":[
        {
            "category":"Freight",
            "type":"Transportation"
        }
    ],
    "sg:phone":"+1 915 577 9007",
    "sg:postcode":"79912",
    "sg:province":"TX",
    "sg:tags":[
        "arrangement",
        "broker",
        "trucking"
    ],
    "wof:name":"Apollo Transportation",
    "wof:placetype":"venue"
},
  "geometry": {"coordinates":[-106.510318,31.808053],"type":"Point"}
}