{
  "type": "Feature",
  "properties": {
    "iso:country":"US",
    "sg:address":"1811 State Hwy 323 SE",
    "sg:city":"Tyler",
    "sg:classifiers":[
        {
            "category":"Building & Trades",
            "subcategory":"Cleaning & Sanitation",
            "type":"Services"
        }
    ],
    "sg:phone":"+1 903 593 2357",
    "sg:postcode":"75701",
    "sg:province":"TX",
    "sg:tags":[
        "janitor"
    ],
    "wof:name":"Clean Scene",
    "wof:placetype":"venue"
},
  "geometry": {"coordinates":[-95.26618999999999,32.329256],"type":"Point"}
}