{
  "type": "Feature",
  "properties": {
    "iso:country":"US",
    "sg:address":"500 Laurel Ln",
    "sg:city":"Lewisville",
    "sg:classifiers":[
        {
            "category":"Autos & Motor Vehicles",
            "subcategory":"Automobile Sales",
            "type":"Retail Goods"
        }
    ],
    "sg:phone":"+1 972 221 9033",
    "sg:postcode":"75067",
    "sg:province":"TX",
    "sg:tags":[
        "car",
        "dealer"
    ],
    "wof:name":"J D Motors Inc",
    "wof:placetype":"venue"
},
  "geometry": {"coordinates":[-97.0089,33.043666],"type":"Point"}
}