{
  "type": "Feature",
  "properties": {
    "iso:country":"US",
    "sg:address":"127 W Main St",
    "sg:city":"Lewisville",
    "sg:classifiers":[
        {
            "category":"Shopping",
            "subcategory":"Used Merchandise",
            "type":"Retail Goods"
        }
    ],
    "sg:phone":"+1 972 353 5033",
    "sg:postcode":"75057",
    "sg:province":"TX",
    "sg:tags":[
        "antique"
    ],
    "wof:name":"Classic Trends Antiques",
    "wof:placetype":"venue"
},
  "geometry": {"coordinates":[-96.994584,33.046386],"type":"Point"}
}