{
  "type": "Feature",
  "properties": {
    "iso:country":"US",
    "sg:address":"8224 Endicott Ln",
    "sg:city":"Dallas",
    "sg:classifiers":[
        {
            "category":"Organizations",
            "subcategory":"Religious Organization",
            "type":"Services"
        }
    ],
    "sg:phone":"+1 214 381 9427",
    "sg:postcode":"75227",
    "sg:province":"TX",
    "sg:tags":[
        "church"
    ],
    "wof:name":"Curry Temple C M E",
    "wof:placetype":"venue"
},
  "geometry": {"coordinates":[-96.676937,32.781431],"type":"Point"}
}