{
  "type": "Feature",
  "properties": {
    "iso:country":"US",
    "sg:address":"1419 S 10th St",
    "sg:city":"Mcallen",
    "sg:classifiers":[
        {
            "category":"Restaurant",
            "type":"Food & Drink"
        }
    ],
    "sg:menulink":"http://www.allmenus.com/tx/mcallen-pharr/157332-whataburger/menu/",
    "sg:phone":"+1 956 682 5597",
    "sg:postcode":"78501",
    "sg:province":"TX",
    "sg:tags":[
        "burger",
        "american"
    ],
    "wof:name":"Whataburger",
    "wof:placetype":"venue"
},
  "geometry": {"coordinates":[-98.232148,26.191115],"type":"Point"}
}