{
  "type": "Feature",
  "properties": {
    "iso:country":"US",
    "sg:address":"32883 Co Rd 2925",
    "sg:city":"Rio Hondo",
    "sg:classifiers":[
        {
            "category":"Building & Trades",
            "subcategory":"Construction",
            "type":"Services"
        }
    ],
    "sg:phone":"+1 956 748 2375",
    "sg:postcode":"78583",
    "sg:province":"TX",
    "sg:tags":[
        "general",
        "contractor"
    ],
    "wof:name":"Weldon Construction Services",
    "wof:placetype":"venue"
},
  "geometry": {"coordinates":[-97.498993,26.332684],"type":"Point"}
}