{
  "type": "Feature",
  "properties": {
    "iso:country":"US",
    "sg:address":"82 Coronado Dr N",
    "sg:city":"Kerrville",
    "sg:classifiers":[
        {
            "category":"Retail",
            "subcategory":"Auto Repair",
            "type":"Services"
        }
    ],
    "sg:phone":"+1 830 896 0100",
    "sg:postcode":"78028",
    "sg:province":"TX",
    "sg:tags":[
        "tire"
    ],
    "wof:name":"Wagoners Tire",
    "wof:placetype":"venue"
},
  "geometry": {"coordinates":[-99.17889599999999,30.066878],"type":"Point"}
}