{
  "type": "Feature",
  "properties": {
    "iso:country":"US",
    "sg:address":"10727 N Loop Dr",
    "sg:city":"Socorro",
    "sg:classifiers":[
        {
            "category":"Professional",
            "subcategory":"Accounting & Tax Preparation",
            "type":"Services"
        }
    ],
    "sg:phone":"+1 915 860 8525",
    "sg:postcode":"79927",
    "sg:province":"TX",
    "sg:tags":[
        "return",
        "filing"
    ],
    "wof:name":"Jackson Hewitt Tax Svc",
    "wof:placetype":"venue"
},
  "geometry": {"coordinates":[-106.26876300000001,31.653297],"type":"Point"}
}