{
  "type": "Feature",
  "properties": {
    "iso:country":"US",
    "sg:address":"1000 W Oaks Mall",
    "sg:city":"Houston",
    "sg:classifiers":[
        {
            "category":"Shopping",
            "subcategory":"Clothing, Apparel, & Fashions",
            "type":"Retail Goods"
        }
    ],
    "sg:phone":"+1 281 870 9550",
    "sg:postcode":"77082",
    "sg:province":"TX",
    "wof:name":"Eddie Bauer Inc",
    "wof:placetype":"venue"
},
  "geometry": {"coordinates":[-95.657842,29.727043],"type":"Point"}
}