{
  "type": "Feature",
  "properties": {
    "iso:country":"US",
    "sg:address":"2550 W Red Bird Ln",
    "sg:city":"Dallas",
    "sg:classifiers":[
        {
            "category":"Shopping",
            "subcategory":"Clothing, Apparel, & Fashions",
            "type":"Retail Goods"
        }
    ],
    "sg:phone":"+1 214 467 2870",
    "sg:postcode":"75237",
    "sg:province":"TX",
    "sg:tags":[
        "shop",
        "bridal"
    ],
    "wof:name":"Yvonne's Bridal",
    "wof:placetype":"venue"
},
  "geometry": {"coordinates":[-96.86203500000001,32.671178],"type":"Point"}
}