{
  "type": "Feature",
  "properties": {
    "iso:country":"US",
    "sg:address":"7324 West Loop S",
    "sg:city":"Bellaire",
    "sg:classifiers":[
        {
            "category":"Health Services",
            "subcategory":"Hospital",
            "type":"Services"
        }
    ],
    "sg:phone":"+1 713 779 0351",
    "sg:postcode":"77401",
    "sg:province":"TX",
    "sg:tags":[
        "sleep",
        "treatment",
        "disorders-information"
    ],
    "wof:name":"Suzie Phelps",
    "wof:placetype":"venue"
},
  "geometry": {"coordinates":[-95.45955499999999,29.700638],"type":"Point"}
}