{
  "type": "Feature",
  "properties": {
    "iso:country":"US",
    "sg:address":"4116 Briarbend Rd",
    "sg:city":"Dallas",
    "sg:classifiers":[
        {
            "category":"Manufacturing",
            "subcategory":"Pottery",
            "type":"Manufacturing & Wholesale Goods"
        }
    ],
    "sg:phone":"+1 972 741 0382",
    "sg:postcode":"75287",
    "sg:province":"TX",
    "sg:tags":[
        "pottery-wholesale",
        "manufacturer"
    ],
    "wof:name":"At Pottery",
    "wof:placetype":"venue"
},
  "geometry": {"coordinates":[-96.839961,33.006353],"type":"Point"}
}