{
  "type": "Feature",
  "properties": {
    "iso:country":"US",
    "sg:address":"20814 Gulf Fwy",
    "sg:city":"Webster",
    "sg:classifiers":[
        {
            "category":"Insurance",
            "subcategory":"Insurance Agent",
            "type":"Services"
        }
    ],
    "sg:phone":"+1 281 554 9000",
    "sg:postcode":"77598",
    "sg:province":"TX",
    "wof:name":"Amco Insurance",
    "wof:placetype":"venue"
},
  "geometry": {"coordinates":[-95.12836,29.525722],"type":"Point"}
}