{
  "type": "Feature",
  "properties": {
    "iso:country":"US",
    "sg:address":"127 Goliad Rd",
    "sg:city":"San Antonio",
    "sg:classifiers":[
        {
            "category":"Real Estate",
            "subcategory":"Real Estate Agent",
            "type":"Services"
        }
    ],
    "sg:phone":"+1 210 533 3200",
    "sg:postcode":"78223",
    "sg:province":"TX",
    "sg:website":"www.alex-realty.com",
    "wof:name":"Alex Realty",
    "wof:placetype":"venue"
},
  "geometry": {"coordinates":[-98.455574,29.382884],"type":"Point"}
}