{
  "type": "Feature",
  "properties": {
    "iso:country":"US",
    "sg:address":"3910 Larkin Ln",
    "sg:city":"Garland",
    "sg:classifiers":[
        {
            "category":"Autos & Motor Vehicles",
            "subcategory":"Automobile Sales",
            "type":"Retail Goods"
        }
    ],
    "sg:phone":"+1 972 240 2310",
    "sg:postcode":"75043",
    "sg:province":"TX",
    "sg:tags":[
        "used"
    ],
    "wof:name":"Statewide Motors Inc",
    "wof:placetype":"venue"
},
  "geometry": {"coordinates":[-96.600426,32.865792],"type":"Point"}
}