{
  "type": "Feature",
  "properties": {
    "iso:country":"US",
    "sg:address":"5800 Campus Circle Dr E",
    "sg:city":"Irving",
    "sg:classifiers":[
        {
            "category":"Insurance",
            "subcategory":"Insurance Agent",
            "type":"Services"
        }
    ],
    "sg:phone":"+1 972 518 2428",
    "sg:postcode":"75063",
    "sg:province":"TX",
    "wof:name":"Corporate Benefit Solution",
    "wof:placetype":"venue"
},
  "geometry": {"coordinates":[-96.98154599999999,32.892581],"type":"Point"}
}