{
  "type": "Feature",
  "properties": {
    "iso:country":"US",
    "sg:address":"4508 Garth Rd",
    "sg:city":"Baytown",
    "sg:classifiers":[
        {
            "category":"Personal",
            "subcategory":"Beauty Salon",
            "type":"Services"
        }
    ],
    "sg:phone":"+1 281 422 5342",
    "sg:postcode":"77521",
    "sg:province":"TX",
    "sg:tags":[
        "shop"
    ],
    "wof:name":"Supercuts",
    "wof:placetype":"venue"
},
  "geometry": {"coordinates":[-94.977475,29.769859],"type":"Point"}
}