{
  "type": "Feature",
  "properties": {
    "iso:country":"US",
    "sg:address":"5214 34th St",
    "sg:city":"Lubbock",
    "sg:classifiers":[
        {
            "category":"Home & Garden",
            "subcategory":"Home Furnishings",
            "type":"Retail Goods"
        }
    ],
    "sg:phone":"+1 806 795 4493",
    "sg:postcode":"79407",
    "sg:province":"TX",
    "sg:tags":[
        "repair"
    ],
    "wof:name":"Eddie Haddad Upholstery",
    "wof:placetype":"venue"
},
  "geometry": {"coordinates":[-101.926709,33.563332],"type":"Point"}
}