{
  "type": "Feature",
  "properties": {
    "iso:country":"US",
    "sg:address":"309 Windrose Pl",
    "sg:city":"El Paso",
    "sg:classifiers":[
        {
            "category":"Professional",
            "subcategory":"Business Services",
            "type":"Services"
        }
    ],
    "sg:phone":"+1 915 525 7770",
    "sg:postcode":"79912",
    "sg:province":"TX",
    "wof:name":"D T Home Inspections",
    "wof:placetype":"venue"
},
  "geometry": {"coordinates":[-106.536534,31.842122],"type":"Point"}
}