{
  "type": "Feature",
  "properties": {
    "iso:country":"US",
    "sg:address":"3621 Racquet Club Dr",
    "sg:city":"Grand Prairie",
    "sg:classifiers":[
        {
            "category":"Communications",
            "type":"Services"
        }
    ],
    "sg:phone":"+1 972 262 5866",
    "sg:postcode":"75052",
    "sg:province":"TX",
    "sg:tags":[
        "communication"
    ],
    "wof:name":"Gotmo Media",
    "wof:placetype":"venue"
},
  "geometry": {"coordinates":[-96.999944,32.689177],"type":"Point"}
}