{
  "type": "Feature",
  "properties": {
    "iso:country":"US",
    "sg:address":"4131 Shoreline Dr",
    "sg:city":"Dallas",
    "sg:classifiers":[
        {
            "category":"Wholesale",
            "subcategory":"Electrical",
            "type":"Manufacturing & Wholesale Goods"
        }
    ],
    "sg:phone":"+1 214 330 8491",
    "sg:postcode":"75233",
    "sg:province":"TX",
    "sg:tags":[
        "communications",
        "telephone"
    ],
    "wof:name":"Oliver Oliver Communications",
    "wof:placetype":"venue"
},
  "geometry": {"coordinates":[-96.88136299999999,32.693116],"type":"Point"}
}