{
  "type": "Feature",
  "properties": {
    "iso:country":"US",
    "sg:address":"1011 W 3rd St",
    "sg:city":"Weslaco",
    "sg:classifiers":[
        {
            "category":"Arts & Performance",
            "subcategory":"Theater",
            "type":"Entertainment"
        }
    ],
    "sg:phone":"+1 956 969 2368",
    "sg:postcode":"78596",
    "sg:province":"TX",
    "sg:tags":[
        "theatrical"
    ],
    "wof:name":"Tower Theatre",
    "wof:placetype":"venue"
},
  "geometry": {"coordinates":[-98.001671,26.158834],"type":"Point"}
}