{
  "type": "Feature",
  "properties": {
    "iso:country":"US",
    "sg:address":"721 Marlee Cir",
    "sg:city":"Coppell",
    "sg:classifiers":[
        {
            "category":"Professional",
            "subcategory":"Accounting & Tax Preparation",
            "type":"Services"
        }
    ],
    "sg:phone":"+1 972 393 2771",
    "sg:postcode":"75019",
    "sg:province":"TX",
    "wof:name":"Thomas Enterprises",
    "wof:placetype":"venue"
},
  "geometry": {"coordinates":[-96.970068,32.973899],"type":"Point"}
}