{
  "type": "Feature",
  "properties": {
    "iso:country":"US",
    "sg:address":"7010 E 9th St",
    "sg:city":"Texarkana",
    "sg:classifiers":[
        {
            "category":"Professional",
            "type":"Services"
        }
    ],
    "sg:phone":"+1 870 772 4153",
    "sg:postcode":"71854",
    "sg:province":"TX",
    "wof:name":"Cody and Marsha Dailey",
    "wof:placetype":"venue"
},
  "geometry": {"coordinates":[-93.956059,33.429547],"type":"Point"}
}