{
  "type": "Feature",
  "properties": {
    "iso:country":"US",
    "sg:address":"7804 Zurich Dr",
    "sg:city":"Plano",
    "sg:classifiers":[
        {
            "category":"Building & Trades",
            "subcategory":"Cleaning & Sanitation",
            "type":"Services"
        }
    ],
    "sg:phone":"+1 972 517 0074",
    "sg:postcode":"75025",
    "sg:province":"TX",
    "sg:tags":[
        "maintenance"
    ],
    "wof:name":"Pamela J Grimes Inc",
    "wof:placetype":"venue"
},
  "geometry": {"coordinates":[-96.73405200000001,33.083147],"type":"Point"}
}