{
  "type": "Feature",
  "properties": {
    "iso:country":"US",
    "sg:address":"213 W North Loop Blvd",
    "sg:city":"Austin",
    "sg:classifiers":[
        {
            "category":"Retail",
            "subcategory":"Repair Shop",
            "type":"Services"
        }
    ],
    "sg:phone":"+1 512 450 0071",
    "sg:postcode":"78751",
    "sg:province":"TX",
    "sg:tags":[
        "television",
        "radio"
    ],
    "wof:name":"Ray's Electronics",
    "wof:placetype":"venue"
},
  "geometry": {"coordinates":[-97.722534,30.317655],"type":"Point"}
}