{
  "type": "Feature",
  "properties": {
    "iso:country":"US",
    "sg:address":"10 Sherwood Dr",
    "sg:city":"Clute",
    "sg:classifiers":[
        {
            "category":"Freight",
            "type":"Transportation"
        }
    ],
    "sg:phone":"+1 979 265 3796",
    "sg:postcode":"77531",
    "sg:province":"TX",
    "sg:tags":[
        "operator",
        "local",
        "trucking"
    ],
    "wof:name":"Alpenglow Trucking LLC",
    "wof:placetype":"venue"
},
  "geometry": {"coordinates":[-95.416189,29.072135],"type":"Point"}
}