{
  "type": "Feature",
  "properties": {
    "iso:country":"US",
    "sg:address":"701 Capital of Tx Blvd.",
    "sg:city":"Austin",
    "sg:classifiers":[
        {
            "category":"Restaurant",
            "type":"Food & Drink"
        }
    ],
    "sg:menulink":"http://www.allmenus.com/tx/austin/106834-soup-man/menu/",
    "sg:phone":"+1 512 347 0670",
    "sg:postcode":"78746",
    "sg:province":"TX",
    "sg:tags":[
        "soup",
        "american",
        "salad"
    ],
    "wof:name":"Soup Man",
    "wof:placetype":"venue"
},
  "geometry": {"coordinates":[-97.828255,30.291669],"type":"Point"}
}