{
  "type": "Feature",
  "properties": {
    "iso:country":"US",
    "sg:address":"14035 Coit Rd",
    "sg:city":"Dallas",
    "sg:classifiers":[
        {
            "category":"Restaurant",
            "type":"Food & Drink"
        }
    ],
    "sg:phone":"+1 972 934 1175",
    "sg:postcode":"75240",
    "sg:province":"TX",
    "sg:tags":[
        "mexican"
    ],
    "wof:name":"La Paloma Taqueria",
    "wof:placetype":"venue"
},
  "geometry": {"coordinates":[-96.769153,32.93859],"type":"Point"}
}