{
  "type": "Feature",
  "properties": {
    "iso:country":"US",
    "sg:address":"416 Main St",
    "sg:city":"Marble Falls",
    "sg:classifiers":[
        {
            "category":"Shopping",
            "subcategory":"Used Merchandise",
            "type":"Retail Goods"
        }
    ],
    "sg:phone":"+1 830 693 5482",
    "sg:postcode":"78654",
    "sg:province":"TX",
    "wof:name":"Bettys Antiques",
    "wof:placetype":"venue"
},
  "geometry": {"coordinates":[-98.276321,30.573726],"type":"Point"}
}