{
  "type": "Feature",
  "properties": {
    "iso:country":"US",
    "sg:address":"2054 Monroe Dr",
    "sg:city":"Kerrville",
    "sg:classifiers":[
        {
            "category":"Building & Trades",
            "subcategory":"Construction",
            "type":"Services"
        }
    ],
    "sg:phone":"+1 830 257 2307",
    "sg:postcode":"78028",
    "sg:province":"TX",
    "sg:tags":[
        "house"
    ],
    "wof:name":"Mike Switzer Construcion",
    "wof:placetype":"venue"
},
  "geometry": {"coordinates":[-99.17099,30.010364],"type":"Point"}
}