{
  "type": "Feature",
  "properties": {
    "iso:country":"US",
    "sg:address":"1802 Wirt Rd",
    "sg:city":"Houston",
    "sg:classifiers":[
        {
            "category":"Shopping",
            "subcategory":"Clothing, Apparel, & Fashions",
            "type":"Retail Goods"
        }
    ],
    "sg:phone":"+1 713 476 9799",
    "sg:postcode":"77055",
    "sg:province":"TX",
    "wof:name":"Los Martinezs Western Wear",
    "wof:placetype":"venue"
},
  "geometry": {"coordinates":[-95.484796,29.804703],"type":"Point"}
}