{
  "type": "Feature",
  "properties": {
    "iso:country":"US",
    "sg:address":"8506 Kingsway Dr",
    "sg:city":"Canutillo",
    "sg:classifiers":[
        {
            "category":"Manufacturing",
            "subcategory":"Glass & Minerals",
            "type":"Manufacturing & Wholesale Goods"
        }
    ],
    "sg:phone":"+1 915 587 5120",
    "sg:postcode":"79835",
    "sg:province":"TX",
    "sg:tags":[
        "ready",
        "concrete",
        "mfg"
    ],
    "wof:name":"Tex Mix",
    "wof:placetype":"venue"
},
  "geometry": {"coordinates":[-106.580851,31.962662],"type":"Point"}
}