{
  "type": "Feature",
  "properties": {
    "iso:country":"US",
    "sg:address":"2129 Skyline Dr",
    "sg:city":"Fort Worth",
    "sg:classifiers":[
        {
            "category":"Health Services",
            "subcategory":"Nursing And Care Facility",
            "type":"Services"
        }
    ],
    "sg:phone":"+1 817 626 1956",
    "sg:postcode":"76114",
    "sg:province":"TX",
    "sg:tags":[
        "home",
        "convalescent"
    ],
    "wof:name":"Manor Care Health Svc",
    "wof:placetype":"venue"
},
  "geometry": {"coordinates":[-97.39829400000001,32.793372],"type":"Point"}
}