{
  "type": "Feature",
  "properties": {
    "iso:country":"US",
    "sg:address":"23915 Verngate Dr",
    "sg:city":"Spring",
    "sg:classifiers":[
        {
            "category":"Wholesale",
            "subcategory":"Auto Parts",
            "type":"Manufacturing & Wholesale Goods"
        }
    ],
    "sg:phone":"+1 281 528 9619",
    "sg:postcode":"77373",
    "sg:province":"TX",
    "wof:name":"Caldwell Equipment Services",
    "wof:placetype":"venue"
},
  "geometry": {"coordinates":[-95.375828,30.052562],"type":"Point"}
}