{
  "type": "Feature",
  "properties": {
    "iso:country":"US",
    "sg:address":"1714 Precinct Line Rd",
    "sg:city":"Hurst",
    "sg:classifiers":[
        {
            "category":"Professional",
            "subcategory":"Advertising",
            "type":"Services"
        },
        {
            "category":"Professional",
            "subcategory":"Printing & Photocopies",
            "type":"Services"
        },
        {
            "category":"Manufacturing",
            "subcategory":"Signs",
            "type":"Manufacturing & Wholesale Goods"
        }
    ],
    "sg:phone":"+1 817 503 0940",
    "sg:postcode":"76054",
    "sg:province":"TX",
    "sg:tags":[
        "banners",
        "flag",
        "specialty",
        "pennant"
    ],
    "wof:name":"J P Signs & Banners",
    "wof:placetype":"venue"
},
  "geometry": {"coordinates":[-97.186211,32.846149],"type":"Point"}
}