{
  "type": "Feature",
  "properties": {
    "iso:country":"US",
    "sg:address":"10020 Johns Rd",
    "sg:city":"Boerne",
    "sg:classifiers":[
        {
            "category":"Restaurant",
            "type":"Food & Drink"
        }
    ],
    "sg:phone":"+1 830 249 3120",
    "sg:postcode":"78006",
    "sg:province":"TX",
    "wof:name":"Japanese Gallery Hisago",
    "wof:placetype":"venue"
},
  "geometry": {"coordinates":[-98.757721,29.793091],"type":"Point"}
}