{
  "type": "Feature",
  "properties": {
    "iso:country":"US",
    "sg:address":"1301 E Collins Blvd",
    "sg:city":"Richardson",
    "sg:classifiers":[
        {
            "category":"Real Estate",
            "subcategory":"Real Estate Services",
            "type":"Services"
        }
    ],
    "sg:phone":"+1 972 699 9100",
    "sg:postcode":"75081",
    "sg:province":"TX",
    "sg:tags":[
        "management",
        "property"
    ],
    "sg:website":"www.ticpropertiesmanagement.com",
    "wof:name":"TIC Properties Management",
    "wof:placetype":"venue"
},
  "geometry": {"coordinates":[-96.701802,32.96814],"type":"Point"}
}