{
  "type": "Feature",
  "properties": {
    "iso:country":"US",
    "sg:address":"415 113th St",
    "sg:city":"Arlington",
    "sg:classifiers":[
        {
            "category":"Coffee & Tea",
            "type":"Food & Drink"
        },
        {
            "category":"Wholesale",
            "subcategory":"Vending Machines",
            "type":"Manufacturing & Wholesale Goods"
        }
    ],
    "sg:phone":"+1 817 640 1791",
    "sg:postcode":"76011",
    "sg:province":"TX",
    "sg:tags":[
        "supply",
        "devices-wholesale",
        "brewing",
        "machines-wholesale",
        "break",
        "machines-parts",
        "device",
        "merchandise",
        "manufacturer"
    ],
    "wof:name":"Mcliff Vending & Office Coffee Service",
    "wof:placetype":"venue"
},
  "geometry": {"coordinates":[-97.043081,32.74498],"type":"Point"}
}