{
  "type": "Feature",
  "properties": {
    "iso:country":"US",
    "sg:address":"18902 Sandia Pines Dr",
    "sg:city":"Humble",
    "sg:classifiers":[
        {
            "category":"Professional",
            "subcategory":"Business Services",
            "type":"Services"
        }
    ],
    "sg:phone":"+1 281 852 2106",
    "sg:postcode":"77346",
    "sg:province":"TX",
    "wof:name":"Dd & S Enterprises",
    "wof:placetype":"venue"
},
  "geometry": {"coordinates":[-95.164142,29.995545],"type":"Point"}
}