{
  "type": "Feature",
  "properties": {
    "iso:country":"US",
    "sg:address":"913 Clinton Dr",
    "sg:city":"Plano",
    "sg:classifiers":[
        {
            "category":"Building & Trades",
            "subcategory":"Construction",
            "type":"Services"
        }
    ],
    "sg:phone":"+1 972 422 7641",
    "sg:postcode":"75075",
    "sg:province":"TX",
    "sg:tags":[
        "contractor",
        "fence-sales"
    ],
    "wof:name":"Southwestern Fence Co",
    "wof:placetype":"venue"
},
  "geometry": {"coordinates":[-96.712433,33.035015],"type":"Point"}
}