{
  "type": "Feature",
  "properties": {
    "iso:country":"US",
    "sg:address":"3879 Irving Mall",
    "sg:city":"Irving",
    "sg:classifiers":[
        {
            "category":"Health Services",
            "subcategory":"Doctor",
            "type":"Services"
        }
    ],
    "sg:phone":"+1 469 417 0980",
    "sg:postcode":"75062",
    "sg:province":"TX",
    "sg:tags":[
        "dentist"
    ],
    "wof:name":"Irving Mall Fdc Pa",
    "wof:placetype":"venue"
},
  "geometry": {"coordinates":[-96.99356400000001,32.840911],"type":"Point"}
}