{
  "type": "Feature",
  "properties": {
    "iso:country":"US",
    "sg:address":"3721 Wilbarger St",
    "sg:city":"Vernon",
    "sg:classifiers":[
        {
            "category":"Professional",
            "subcategory":"Business Services",
            "type":"Services"
        }
    ],
    "sg:phone":"+1 940 552 9887",
    "sg:postcode":"76384",
    "sg:province":"TX",
    "wof:name":"World Finance",
    "wof:placetype":"venue"
},
  "geometry": {"coordinates":[-99.30539899999999,34.152387],"type":"Point"}
}