{
  "type": "Feature",
  "properties": {
    "iso:country":"US",
    "sg:address":"19734 Twin Canyon Ct",
    "sg:city":"Katy",
    "sg:classifiers":[
        {
            "category":"Professional",
            "subcategory":"Business Services",
            "type":"Services"
        }
    ],
    "sg:phone":"+1 281 787 2271",
    "sg:postcode":"77450",
    "sg:province":"TX",
    "wof:name":"Rainmaker Enterprises Inc",
    "wof:placetype":"venue"
},
  "geometry": {"coordinates":[-95.72851900000001,29.71232],"type":"Point"}
}