{
  "type": "Feature",
  "properties": {
    "iso:country":"US",
    "sg:address":"328 Woodlake Dr",
    "sg:city":"Plano",
    "sg:classifiers":[
        {
            "category":"Organizations",
            "subcategory":"Membership Organization",
            "type":"Services"
        }
    ],
    "sg:phone":"+1 972 881 1104",
    "sg:postcode":"75094",
    "sg:province":"TX",
    "wof:name":"Texas Boxer Rescue",
    "wof:placetype":"venue"
},
  "geometry": {"coordinates":[-96.60597199999999,33.008547],"type":"Point"}
}