{
  "type": "Feature",
  "properties": {
    "iso:country":"US",
    "sg:address":"800 Franklin Ave",
    "sg:city":"Waco",
    "sg:classifiers":[
        {
            "category":"Government",
            "subcategory":"Office",
            "type":"Public Place"
        }
    ],
    "sg:phone":"+1 254 755 8380",
    "sg:postcode":"76701",
    "sg:province":"TX",
    "wof:name":"Us Govt Pbs",
    "wof:placetype":"venue"
},
  "geometry": {"coordinates":[-97.134485,31.552784],"type":"Point"}
}