{
  "type": "Feature",
  "properties": {
    "iso:country":"US",
    "sg:address":"14300 Cornerstone Village Dr",
    "sg:city":"Houston",
    "sg:classifiers":[
        {
            "category":"Wholesale",
            "subcategory":"Machinery & Supplies",
            "type":"Manufacturing & Wholesale Goods"
        }
    ],
    "sg:phone":"+1 281 893 0027",
    "sg:postcode":"77014",
    "sg:province":"TX",
    "sg:tags":[
        "crane",
        "parts"
    ],
    "wof:name":"Gantrex Corp",
    "wof:placetype":"venue"
},
  "geometry": {"coordinates":[-95.482865,29.987904],"type":"Point"}
}