{
  "type": "Feature",
  "properties": {
    "iso:country":"US",
    "sg:address":"4405 Dalton Dr",
    "sg:city":"Midland",
    "sg:classifiers":[
        {
            "category":"Health Services",
            "subcategory":"Doctor",
            "type":"Services"
        }
    ],
    "sg:phone":"+1 432 570 6777",
    "sg:postcode":"79705",
    "sg:province":"TX",
    "sg:tags":[
        "medical"
    ],
    "wof:name":"Seamus E Carmody",
    "wof:placetype":"venue"
},
  "geometry": {"coordinates":[-102.11966099999999,32.033935],"type":"Point"}
}