{
  "type": "Feature",
  "properties": {
    "iso:country":"US",
    "sg:address":"9222 Burnet Rd Ste 101",
    "sg:city":"Austin",
    "sg:classifiers":[
        {
            "category":"Freight",
            "type":"Transportation"
        },
        {
            "category":"Professional",
            "subcategory":"Printing & Photocopies",
            "type":"Services"
        }
    ],
    "sg:phone":"+1 512 339 1191",
    "sg:postcode":"78758",
    "sg:province":"TX",
    "sg:tags":[
        "shipping"
    ],
    "sg:website":"www.fedex.com/us/office/",
    "wof:name":"FedEx Office Print & Ship Center",
    "wof:placetype":"venue"
},
  "geometry": {"coordinates":[-97.726223,30.376642],"type":"Point"}
}