{
  "type": "Feature",
  "properties": {
    "iso:country":"US",
    "sg:address":"1300 US Hwy 385",
    "sg:city":"Andrews",
    "sg:classifiers":[
        {
            "category":"Wholesale",
            "subcategory":"Auto Parts",
            "type":"Manufacturing & Wholesale Goods"
        }
    ],
    "sg:phone":"+1 432 523 7758",
    "sg:postcode":"79714",
    "sg:province":"TX",
    "sg:tags":[
        "automobile",
        "rebuilt"
    ],
    "wof:name":"Andrews Auto Salvage",
    "wof:placetype":"venue"
},
  "geometry": {"coordinates":[-102.55132399999999,32.334021],"type":"Point"}
}