{
  "type": "Feature",
  "properties": {
    "iso:country":"US",
    "sg:address":"111 Continental Ave",
    "sg:city":"Dallas",
    "sg:classifiers":[
        {
            "category":"Food & Beverages",
            "subcategory":"Groceries & Convenience Stores",
            "type":"Retail Goods"
        }
    ],
    "sg:phone":"+1 214 749 5050",
    "sg:postcode":"75207",
    "sg:province":"TX",
    "wof:name":"C Store Valero",
    "wof:placetype":"venue"
},
  "geometry": {"coordinates":[-96.819506,32.782702],"type":"Point"}
}