{
  "type": "Feature",
  "properties": {
    "iso:country":"US",
    "sg:address":"1630 W Bruton Rd",
    "sg:city":"Mesquite",
    "sg:classifiers":[
        {
            "category":"Retail",
            "subcategory":"Auto Repair",
            "type":"Services"
        }
    ],
    "sg:phone":"+1 972 289 0977",
    "sg:postcode":"75149",
    "sg:province":"TX",
    "wof:name":"R J R Auto Service",
    "wof:placetype":"venue"
},
  "geometry": {"coordinates":[-96.622398,32.748699],"type":"Point"}
}