{
  "type": "Feature",
  "properties": {
    "iso:country":"US",
    "sg:address":"9900 Doerr Ln",
    "sg:city":"Schertz",
    "sg:classifiers":[
        {
            "category":"Building & Trades",
            "subcategory":"Electrical",
            "type":"Services"
        }
    ],
    "sg:phone":"+1 210 651 8294",
    "sg:postcode":"78154",
    "sg:province":"TX",
    "sg:tags":[
        "industrial",
        "electrician",
        "contractors-commercial",
        "electric"
    ],
    "wof:name":"Houston Stafford Electric",
    "wof:placetype":"venue"
},
  "geometry": {"coordinates":[-98.291893,29.612301],"type":"Point"}
}