{
  "type": "Feature",
  "properties": {
    "iso:country":"US",
    "sg:address":"27110 Decker Woods Dr",
    "sg:city":"Magnolia",
    "sg:classifiers":[
        {
            "category":"Building & Trades",
            "subcategory":"Construction",
            "type":"Services"
        }
    ],
    "sg:phone":"+1 281 356 6625",
    "sg:postcode":"77354",
    "sg:province":"TX",
    "sg:tags":[
        "water",
        "works",
        "contractor"
    ],
    "wof:name":"Johnson Municipal Svc",
    "wof:placetype":"venue"
},
  "geometry": {"coordinates":[-95.637929,30.16528],"type":"Point"}
}