{
  "type": "Feature",
  "properties": {
    "iso:country":"US",
    "sg:address":"4123 S Jackson St",
    "sg:city":"Amarillo",
    "sg:classifiers":[
        {
            "category":"Retail",
            "subcategory":"Repair Shop",
            "type":"Services"
        }
    ],
    "sg:phone":"+1 806 376 7830",
    "sg:postcode":"79110",
    "sg:province":"TX",
    "sg:tags":[
        "upholsterer"
    ],
    "wof:name":"Ken's Upholstery",
    "wof:placetype":"venue"
},
  "geometry": {"coordinates":[-101.84549,35.169536],"type":"Point"}
}