{
  "type": "Feature",
  "properties": {
    "iso:country":"US",
    "sg:address":"1245 Indiana St",
    "sg:city":"Humble",
    "sg:classifiers":[
        {
            "category":"Building & Trades",
            "subcategory":"Construction",
            "type":"Services"
        }
    ],
    "sg:phone":"+1 281 446 7770",
    "sg:postcode":"77396",
    "sg:province":"TX",
    "sg:tags":[
        "roofing",
        "contractor"
    ],
    "wof:name":"Construction Services",
    "wof:placetype":"venue"
},
  "geometry": {"coordinates":[-95.250683,29.972287],"type":"Point"}
}