{
  "type": "Feature",
  "properties": {
    "iso:country":"US",
    "sg:address":"3451 McFarlin Blvd",
    "sg:city":"Dallas",
    "sg:classifiers":[
        {
            "category":"Building & Trades",
            "subcategory":"Cleaning & Sanitation",
            "type":"Services"
        }
    ],
    "sg:phone":"+1 817 308 8956",
    "sg:postcode":"75205",
    "sg:province":"TX",
    "sg:tags":[
        "window",
        "washing"
    ],
    "wof:name":"Texas Star Windows",
    "wof:placetype":"venue"
},
  "geometry": {"coordinates":[-96.78971900000001,32.843573],"type":"Point"}
}