{
  "type": "Feature",
  "properties": {
    "iso:country":"US",
    "sg:address":"9993 Kenworthy St",
    "sg:city":"El Paso",
    "sg:classifiers":[
        {
            "category":"Banks & Credit Unions",
            "subcategory":"Bank",
            "type":"Services"
        }
    ],
    "sg:phone":"+1 915 562 1172",
    "sg:postcode":"79924",
    "sg:province":"TX",
    "sg:website":"www.fbfcu.org",
    "wof:name":"Fort Bliss Federal Cu",
    "wof:placetype":"venue"
},
  "geometry": {"coordinates":[-106.433131,31.894809],"type":"Point"}
}