{
  "type": "Feature",
  "properties": {
    "iso:country":"US",
    "sg:address":"4700 N Mesa St",
    "sg:city":"El Paso",
    "sg:classifiers":[
        {
            "category":"Building & Trades",
            "subcategory":"Construction",
            "type":"Services"
        }
    ],
    "sg:phone":"+1 915 544 6364",
    "sg:postcode":"79912",
    "sg:province":"TX",
    "sg:tags":[
        "interior",
        "design"
    ],
    "wof:name":"Fabrics West",
    "wof:placetype":"venue"
},
  "geometry": {"coordinates":[-106.542,31.8424],"type":"Point"}
}