{
  "type": "Feature",
  "properties": {
    "iso:country":"US",
    "sg:address":"8341 Hammerly Blvd",
    "sg:city":"Houston",
    "sg:classifiers":[
        {
            "category":"Retail",
            "subcategory":"Auto Repair",
            "type":"Services"
        }
    ],
    "sg:phone":"+1 832 358 8237",
    "sg:postcode":"77055",
    "sg:province":"TX",
    "sg:tags":[
        "tire"
    ],
    "wof:name":"J Martinez Tire Shop",
    "wof:placetype":"venue"
},
  "geometry": {"coordinates":[-95.49606799999999,29.810936],"type":"Point"}
}