{
  "type": "Feature",
  "properties": {
    "iso:country":"US",
    "sg:address":"2020 Ave F",
    "sg:city":"Bay City",
    "sg:classifiers":[
        {
            "category":"Professional",
            "subcategory":"Management & Consulting",
            "type":"Services"
        }
    ],
    "sg:phone":"+1 281 341 6555",
    "sg:postcode":"77414",
    "sg:province":"TX",
    "wof:name":"Burger Biz Inc",
    "wof:placetype":"venue"
},
  "geometry": {"coordinates":[-95.97013800000001,28.983851],"type":"Point"}
}