{
  "type": "Feature",
  "properties": {
    "iso:country":"US",
    "sg:address":"3027 Bitters Rd",
    "sg:city":"San Antonio",
    "sg:classifiers":[
        {
            "category":"Personal",
            "subcategory":"Beauty Salon",
            "type":"Services"
        }
    ],
    "sg:phone":"+1 210 655 4744",
    "sg:postcode":"78217",
    "sg:province":"TX",
    "sg:tags":[
        "shop",
        "barber"
    ],
    "wof:name":"Debbie's Hair Designs",
    "wof:placetype":"venue"
},
  "geometry": {"coordinates":[-98.441151,29.527631],"type":"Point"}
}