{
  "type": "Feature",
  "properties": {
    "iso:country":"US",
    "sg:address":"404 Kiwi Ave",
    "sg:city":"Mcallen",
    "sg:classifiers":[
        {
            "category":"Professional",
            "subcategory":"Computer Services",
            "type":"Services"
        }
    ],
    "sg:phone":"+1 956 687 8722",
    "sg:postcode":"78504",
    "sg:province":"TX",
    "sg:tags":[
        "related"
    ],
    "wof:name":"Medtech Solutions LLC",
    "wof:placetype":"venue"
},
  "geometry": {"coordinates":[-98.21487399999999,26.258815],"type":"Point"}
}