{
  "type": "Feature",
  "properties": {
    "iso:country":"US",
    "sg:address":"8100 Aviation Pl",
    "sg:city":"Dallas",
    "sg:classifiers":[
        {
            "category":"Government",
            "subcategory":"Office",
            "type":"Public Place"
        }
    ],
    "sg:phone":"+1 214 353 1512",
    "sg:postcode":"75235",
    "sg:province":"TX",
    "sg:tags":[
        "transportation"
    ],
    "wof:name":"System Support Center",
    "wof:placetype":"venue"
},
  "geometry": {"coordinates":[-96.84101099999999,32.838097],"type":"Point"}
}