{
  "type": "Feature",
  "properties": {
    "iso:country":"US",
    "sg:address":"3651 Bluebonnet Blvd",
    "sg:city":"Houston",
    "sg:classifiers":[
        {
            "category":"Building & Trades",
            "subcategory":"Construction",
            "type":"Services"
        }
    ],
    "sg:phone":"+1 713 660 9120",
    "sg:postcode":"77025",
    "sg:province":"TX",
    "sg:tags":[
        "residential",
        "light"
    ],
    "wof:name":"Kirsten Construction Co Inc",
    "wof:placetype":"venue"
},
  "geometry": {"coordinates":[-95.432866,29.700402],"type":"Point"}
}