{
  "type": "Feature",
  "properties": {
    "iso:country":"US",
    "sg:address":"4312 Mohawk Dr",
    "sg:city":"Mesquite",
    "sg:classifiers":[
        {
            "category":"Professional",
            "subcategory":"Computer Services",
            "type":"Services"
        }
    ],
    "sg:phone":"+1 972 286 2988",
    "sg:postcode":"75180",
    "sg:province":"TX",
    "sg:tags":[
        "related"
    ],
    "wof:name":"Link Enterprises",
    "wof:placetype":"venue"
},
  "geometry": {"coordinates":[-96.602116,32.710238],"type":"Point"}
}