{
  "type": "Feature",
  "properties": {
    "iso:country":"US",
    "sg:address":"7203 W 36th Ave",
    "sg:city":"Amarillo",
    "sg:classifiers":[
        {
            "category":"Real Estate",
            "subcategory":"Real Estate Agent",
            "type":"Services"
        }
    ],
    "sg:phone":"+1 806 358 4491",
    "sg:postcode":"79109",
    "sg:province":"TX",
    "wof:name":"Jamie Johnson Realtor",
    "wof:placetype":"venue"
},
  "geometry": {"coordinates":[-101.919875,35.173745],"type":"Point"}
}