{
  "type": "Feature",
  "properties": {
    "iso:country":"US",
    "sg:address":"15212 Sandia",
    "sg:city":"San Antonio",
    "sg:classifiers":[
        {
            "category":"Real Estate",
            "subcategory":"Architect",
            "type":"Services"
        }
    ],
    "sg:phone":"+1 210 494 9462",
    "sg:postcode":"78232",
    "sg:province":"TX",
    "wof:name":"Hardy & Assoc",
    "wof:placetype":"venue"
},
  "geometry": {"coordinates":[-98.452623,29.57741],"type":"Point"}
}