{
  "type": "Feature",
  "properties": {
    "iso:country":"US",
    "sg:address":"10515 Katy Fwy",
    "sg:city":"Houston",
    "sg:classifiers":[
        {
            "category":"Home & Garden",
            "subcategory":"Home Furnishings",
            "type":"Retail Goods"
        }
    ],
    "sg:phone":"+1 713 461 6509",
    "sg:postcode":"77024",
    "sg:province":"TX",
    "sg:tags":[
        "housewares"
    ],
    "sg:website":"http://www.bedbathandbeyond.com",
    "wof:name":"Bed Bath & Beyond",
    "wof:placetype":"venue"
},
  "geometry": {"coordinates":[-95.557377,29.783841],"type":"Point"}
}