{
  "type": "Feature",
  "properties": {
    "iso:country":"US",
    "sg:address":"5187 Farmer St",
    "sg:city":"Houston",
    "sg:classifiers":[
        {
            "category":"Personal",
            "subcategory":"Beauty Salon",
            "type":"Services"
        }
    ],
    "sg:phone":"+1 832 375 1400",
    "sg:postcode":"77020",
    "sg:province":"TX",
    "sg:tags":[
        "shop"
    ],
    "wof:name":"CL &B Beauty Solutions",
    "wof:placetype":"venue"
},
  "geometry": {"coordinates":[-95.31822200000001,29.775718],"type":"Point"}
}