{
  "type": "Feature",
  "properties": {
    "iso:country":"US",
    "sg:address":"17103 Eagle Hollow Dr",
    "sg:city":"San Antonio",
    "sg:classifiers":[
        {
            "category":"Mining & Drilling",
            "type":"Manufacturing & Wholesale Goods"
        }
    ],
    "sg:phone":"+1 210 408 7361",
    "sg:postcode":"78248",
    "sg:province":"TX",
    "sg:tags":[
        "stone"
    ],
    "wof:name":"Stepping Stone Enterprises Inc",
    "wof:placetype":"venue"
},
  "geometry": {"coordinates":[-98.5217,29.599677],"type":"Point"}
}