{
  "type": "Feature",
  "properties": {
    "iso:country":"US",
    "sg:address":"902 Old Austin Hutto Rd",
    "sg:city":"Pflugerville",
    "sg:classifiers":[
        {
            "category":"Retail",
            "subcategory":"Auto Repair",
            "type":"Services"
        }
    ],
    "sg:phone":"+1 512 252 0404",
    "sg:postcode":"78660",
    "sg:province":"TX",
    "sg:tags":[
        "repairing",
        "automobile",
        "general"
    ],
    "wof:name":"Joe Coleman Automotive",
    "wof:placetype":"venue"
},
  "geometry": {"coordinates":[-97.607291,30.443213],"type":"Point"}
}