{
  "type": "Feature",
  "properties": {
    "iso:country":"US",
    "sg:address":"3411 Glenview Ave",
    "sg:city":"Austin",
    "sg:classifiers":[
        {
            "category":"Restaurant",
            "type":"Food & Drink"
        }
    ],
    "sg:phone":"+1 512 323 5177",
    "sg:postcode":"78703",
    "sg:province":"TX",
    "sg:tags":[
        "spanish",
        "modern",
        "steakhouse",
        "european"
    ],
    "sg:website":"www.elarbolrestaurant.com",
    "wof:name":"El Arbol",
    "wof:placetype":"venue"
},
  "geometry": {"coordinates":[-97.751166,30.307183],"type":"Point"}
}