{
  "type": "Feature",
  "properties": {
    "iso:country":"US",
    "sg:address":"10103 Fondren Rd Ste 155",
    "sg:city":"Houston",
    "sg:classifiers":[
        {
            "category":"Health Services",
            "subcategory":"Nursing And Care Facility",
            "type":"Services"
        },
        {
            "category":"Professional",
            "subcategory":"Employment Agencies",
            "type":"Services"
        }
    ],
    "sg:phone":"+1 713 272 7879",
    "sg:postcode":"77096",
    "sg:province":"TX",
    "sg:tags":[
        "nurse",
        "contractor"
    ],
    "sg:website":"http://www.flexmedicalservices.com",
    "wof:name":"Flex Career School",
    "wof:placetype":"venue"
},
  "geometry": {"coordinates":[-95.50850699999999,29.670843],"type":"Point"}
}