{
  "type": "Feature",
  "properties": {
    "iso:country":"US",
    "sg:address":"412 E Main St",
    "sg:city":"Alice",
    "sg:classifiers":[
        {
            "category":"Government",
            "subcategory":"Office",
            "type":"Public Place"
        }
    ],
    "sg:phone":"+1 361 668 0747",
    "sg:postcode":"78332",
    "sg:province":"TX",
    "sg:tags":[
        "state",
        "program",
        "health"
    ],
    "wof:name":"Health Dept",
    "wof:placetype":"venue"
},
  "geometry": {"coordinates":[-98.07232999999999,27.750073],"type":"Point"}
}