{
  "type": "Feature",
  "properties": {
    "iso:country":"US",
    "sg:address":"3711 N Chadbourne St",
    "sg:city":"San Angelo",
    "sg:classifiers":[
        {
            "category":"Shopping",
            "subcategory":"Music",
            "type":"Retail Goods"
        },
        {
            "category":"Cinema",
            "subcategory":"Movie Rental",
            "type":"Entertainment"
        }
    ],
    "sg:phone":"+1 325 486 8441",
    "sg:postcode":"76903",
    "sg:province":"TX",
    "sg:tags":[
        "leasing",
        "video",
        "disc",
        "tape"
    ],
    "wof:name":"Bubba's Video",
    "wof:placetype":"venue"
},
  "geometry": {"coordinates":[-100.460375,31.4987],"type":"Point"}
}