{
  "type": "Feature",
  "properties": {
    "iso:country":"US",
    "sg:address":"2501 Lone Oak Rd",
    "sg:city":"Houston",
    "sg:classifiers":[
        {
            "category":"Organizations",
            "subcategory":"Religious Organization",
            "type":"Services"
        }
    ],
    "sg:phone":"+1 281 590 7480",
    "sg:postcode":"77093",
    "sg:province":"TX",
    "sg:tags":[
        "church"
    ],
    "wof:name":"First Church-Lord Jesus Christ",
    "wof:placetype":"venue"
},
  "geometry": {"coordinates":[-95.34721,29.873574],"type":"Point"}
}