{
  "type": "Feature",
  "properties": {
    "iso:country":"US",
    "sg:address":"1814 Columbia St",
    "sg:city":"Houston",
    "sg:classifiers":[
        {
            "category":"Retail",
            "subcategory":"Funeral Services",
            "type":"Services"
        }
    ],
    "sg:phone":"+1 713 861 2861",
    "sg:postcode":"77008",
    "sg:province":"TX",
    "sg:tags":[
        "cemetery"
    ],
    "wof:name":"Parker Sherri A Funrl Dir",
    "wof:placetype":"venue"
},
  "geometry": {"coordinates":[-95.393204,29.8022],"type":"Point"}
}