{
  "type": "Feature",
  "properties": {
    "iso:country":"US",
    "sg:address":"1302 S Murray Ave",
    "sg:city":"Monahans",
    "sg:classifiers":[
        {
            "category":"Professional",
            "type":"Services"
        }
    ],
    "sg:phone":"+1 432 943 6024",
    "sg:postcode":"79756",
    "sg:province":"TX",
    "wof:name":"Everett West & Will",
    "wof:placetype":"venue"
},
  "geometry": {"coordinates":[-102.87539700000001,31.586504],"type":"Point"}
}