{
  "type": "Feature",
  "properties": {
    "iso:country":"US",
    "sg:address":"18700 John F Kennedy Blvd",
    "sg:city":"Houston",
    "sg:classifiers":[
        {
            "category":"Food & Beverages",
            "subcategory":"Dairy",
            "type":"Retail Goods"
        }
    ],
    "sg:phone":"+1 281 443 2855",
    "sg:postcode":"77039",
    "sg:province":"TX",
    "sg:tags":[
        "product"
    ],
    "wof:name":"Airport Ice Cream Inc",
    "wof:placetype":"venue"
},
  "geometry": {"coordinates":[-95.34275599999999,29.983633],"type":"Point"}
}