{
  "type": "Feature",
  "properties": {
    "iso:country":"US",
    "sg:address":"2601 S I- 35",
    "sg:city":"Austin",
    "sg:classifiers":[
        {
            "category":"Restaurant",
            "type":"Food & Drink"
        }
    ],
    "sg:phone":"+1 512 716 0100",
    "sg:postcode":"78741",
    "sg:province":"TX",
    "sg:tags":[
        "eating"
    ],
    "wof:name":"Zorba Greek Restaurant",
    "wof:placetype":"venue"
},
  "geometry": {"coordinates":[-97.742316,30.231016],"type":"Point"}
}