{
  "type": "Feature",
  "properties": {
    "iso:country":"US",
    "sg:address":"1441 Palm Valley Dr E",
    "sg:city":"Harlingen",
    "sg:classifiers":[
        {
            "category":"Professional",
            "subcategory":"Business Services",
            "type":"Services"
        }
    ],
    "sg:phone":"+1 956 425 9592",
    "sg:postcode":"78552",
    "sg:province":"TX",
    "sg:tags":[
        "holding"
    ],
    "wof:name":"Raymond Cooper Holdings, Ltd.",
    "wof:placetype":"venue"
},
  "geometry": {"coordinates":[-97.750872,26.198027],"type":"Point"}
}