{
  "type": "Feature",
  "properties": {
    "iso:country":"US",
    "sg:address":"515 Main St",
    "sg:city":"Bandera",
    "sg:classifiers":[
        {
            "category":"Education",
            "subcategory":"Library",
            "type":"Public Place"
        }
    ],
    "sg:phone":"+1 830 796 4213",
    "sg:postcode":"78003",
    "sg:province":"TX",
    "sg:website":"http://www.banderalibrary.org",
    "wof:name":"Bandera County Library",
    "wof:placetype":"venue"
},
  "geometry": {"coordinates":[-99.07264600000001,29.726039],"type":"Point"}
}