{
  "type": "Feature",
  "properties": {
    "iso:country":"US",
    "sg:address":"300 N Vista Dr",
    "sg:city":"Houston",
    "sg:classifiers":[
        {
            "category":"Real Estate",
            "subcategory":"Real Estate Operator",
            "type":"Services"
        }
    ],
    "sg:phone":"+1 281 821 6119",
    "sg:postcode":"77073",
    "sg:province":"TX",
    "sg:tags":[
        "apartment"
    ],
    "wof:name":"Apache Springs Apartments",
    "wof:placetype":"venue"
},
  "geometry": {"coordinates":[-95.42638599999999,30.005982],"type":"Point"}
}