{
  "type": "Feature",
  "properties": {
    "iso:country":"US",
    "sg:address":"8215 West Dr",
    "sg:city":"Leander",
    "sg:classifiers":[
        {
            "category":"Building & Trades",
            "subcategory":"Construction",
            "type":"Services"
        }
    ],
    "sg:phone":"+1 512 331 7851",
    "sg:postcode":"78641",
    "sg:province":"TX",
    "sg:tags":[
        "concrete",
        "contractor"
    ],
    "wof:name":"Nelson Robert",
    "wof:placetype":"venue"
},
  "geometry": {"coordinates":[-97.920709,30.456352],"type":"Point"}
}