{
  "type": "Feature",
  "properties": {
    "iso:country":"US",
    "sg:address":"5642 Williams Dr",
    "sg:city":"Corpus Christi",
    "sg:classifiers":[
        {
            "category":"Professional",
            "subcategory":"Business Services",
            "type":"Services"
        },
        {
            "category":"Building & Trades",
            "subcategory":"Construction",
            "type":"Services"
        }
    ],
    "sg:phone":"+1 361 993 7727",
    "sg:postcode":"78412",
    "sg:province":"TX",
    "sg:tags":[
        "repair",
        "designer",
        "po",
        "maintenance",
        "dealer",
        "pool",
        "swimming"
    ],
    "wof:name":"Certified Pool Spa Specialists",
    "wof:placetype":"venue"
},
  "geometry": {"coordinates":[-97.370248,27.703814],"type":"Point"}
}