{
  "type": "Feature",
  "properties": {
    "iso:country":"US",
    "sg:address":"4500 W Plano Pkwy",
    "sg:city":"Plano",
    "sg:classifiers":[
        {
            "category":"Autos & Motor Vehicles",
            "subcategory":"Automobile Sales",
            "type":"Retail Goods"
        }
    ],
    "sg:phone":"+1 888 467 1758",
    "sg:postcode":"75093",
    "sg:province":"TX",
    "sg:tags":[
        "new",
        "used",
        "car"
    ],
    "sg:website":"http://www.huffines.net",
    "wof:name":"Huffines Dealership",
    "wof:placetype":"venue"
},
  "geometry": {"coordinates":[-96.78502400000001,33.016399],"type":"Point"}
}