{
  "type": "Feature",
  "properties": {
    "iso:country":"US",
    "sg:address":"1509 Packsaddle Ln",
    "sg:city":"Baytown",
    "sg:classifiers":[
        {
            "category":"Building & Trades",
            "subcategory":"Construction",
            "type":"Services"
        }
    ],
    "sg:phone":"+1 281 422 2831",
    "sg:postcode":"77521",
    "sg:province":"TX",
    "sg:tags":[
        "contractor"
    ],
    "wof:name":"Siding By Campos",
    "wof:placetype":"venue"
},
  "geometry": {"coordinates":[-94.948657,29.770894],"type":"Point"}
}