{
  "type": "Feature",
  "properties": {
    "iso:country":"US",
    "sg:address":"4200 S Hulen St",
    "sg:city":"Fort Worth",
    "sg:classifiers":[
        {
            "category":"Social Services",
            "type":"Services"
        }
    ],
    "sg:phone":"+1 817 737 0658",
    "sg:postcode":"76109",
    "sg:province":"TX",
    "sg:tags":[
        "counselor",
        "marriage",
        "family"
    ],
    "wof:name":"Candleridge Counseling Ctr",
    "wof:placetype":"venue"
},
  "geometry": {"coordinates":[-97.39295,32.687701],"type":"Point"}
}