{
  "type": "Feature",
  "properties": {
    "iso:country":"US",
    "sg:address":"4605 State Hwy 6",
    "sg:city":"Houston",
    "sg:classifiers":[
        {
            "category":"Personal",
            "subcategory":"Beauty Salon",
            "type":"Services"
        }
    ],
    "sg:phone":"+1 281 858 5457",
    "sg:postcode":"77084",
    "sg:province":"TX",
    "sg:tags":[
        "shop"
    ],
    "wof:name":"Paul Hair Salon",
    "wof:placetype":"venue"
},
  "geometry": {"coordinates":[-95.64574,29.841641],"type":"Point"}
}