{
  "type": "Feature",
  "properties": {
    "iso:country":"US",
    "sg:address":"2301 Midwestern Pkwy",
    "sg:city":"Wichita Falls",
    "sg:classifiers":[
        {
            "category":"Personal",
            "subcategory":"Beauty Salon",
            "type":"Services"
        }
    ],
    "sg:phone":"+1 940 689 9546",
    "sg:postcode":"76308",
    "sg:province":"TX",
    "sg:tags":[
        "treatment",
        "skin"
    ],
    "wof:name":"Envy Day Spa",
    "wof:placetype":"venue"
},
  "geometry": {"coordinates":[-98.518523,33.87047],"type":"Point"}
}