{
  "type": "Feature",
  "properties": {
    "iso:country":"US",
    "sg:address":"512 Avenue E",
    "sg:city":"El Campo",
    "sg:classifiers":[
        {
            "category":"Retail",
            "subcategory":"Auto Repair",
            "type":"Services"
        }
    ],
    "sg:phone":"+1 979 543 7539",
    "sg:postcode":"77437",
    "sg:province":"TX",
    "sg:tags":[
        "automotive"
    ],
    "wof:name":"Oscar Wrecker Service",
    "wof:placetype":"venue"
},
  "geometry": {"coordinates":[-96.279411,29.194084],"type":"Point"}
}