{
  "type": "Feature",
  "properties": {
    "iso:country":"US",
    "sg:address":"810 Beth Dr",
    "sg:city":"Tyler",
    "sg:classifiers":[
        {
            "category":"Wholesale",
            "subcategory":"Books, Periodicals, & Newspapers",
            "type":"Manufacturing & Wholesale Goods"
        }
    ],
    "sg:phone":"+1 903 561 4554",
    "sg:postcode":"75703",
    "sg:province":"TX",
    "sg:tags":[
        "publisher",
        "book"
    ],
    "wof:name":"Water Express Of Tyler",
    "wof:placetype":"venue"
},
  "geometry": {"coordinates":[-95.293717,32.275761],"type":"Point"}
}