{
  "type": "Feature",
  "properties": {
    "iso:country":"US",
    "sg:address":"260 Belle St",
    "sg:city":"Bedford",
    "sg:classifiers":[
        {
            "category":"Shopping",
            "subcategory":"Computers & Home Electronics",
            "type":"Retail Goods"
        }
    ],
    "sg:phone":"+1 817 282 8300",
    "sg:postcode":"76022",
    "sg:province":"TX",
    "wof:name":"James Friday Enterprises",
    "wof:placetype":"venue"
},
  "geometry": {"coordinates":[-97.166067,32.832664],"type":"Point"}
}