{
  "type": "Feature",
  "properties": {
    "iso:country":"US",
    "sg:address":"7886 Grassbur Rd",
    "sg:city":"Bryan",
    "sg:classifiers":[
        {
            "category":"Food & Beverages",
            "subcategory":"Bakery",
            "type":"Retail Goods"
        }
    ],
    "sg:phone":"+1 979 589 2695",
    "sg:postcode":"77808",
    "sg:province":"TX",
    "sg:tags":[
        "special",
        "mfg"
    ],
    "wof:name":"Betty Little Store",
    "wof:placetype":"venue"
},
  "geometry": {"coordinates":[-96.244935,30.722017],"type":"Point"}
}