{
  "type": "Feature",
  "properties": {
    "iso:country":"US",
    "sg:address":"910 S Mason Rd",
    "sg:city":"Katy",
    "sg:classifiers":[
        {
            "category":"Retail",
            "subcategory":"Car Wash",
            "type":"Services"
        }
    ],
    "sg:phone":"+1 281 392 9274",
    "sg:postcode":"77450",
    "sg:province":"TX",
    "sg:tags":[
        "carwash",
        "automotive"
    ],
    "wof:name":"Simoniz Car Wash",
    "wof:placetype":"venue"
},
  "geometry": {"coordinates":[-95.751768,29.769256],"type":"Point"}
}