{
  "type": "Feature",
  "properties": {
    "iso:country":"US",
    "sg:address":"1701 Saul Kleinfeld Dr",
    "sg:city":"El Paso",
    "sg:classifiers":[
        {
            "category":"Banks & Credit Unions",
            "subcategory":"Bank",
            "type":"Services"
        }
    ],
    "sg:phone":"+1 915 856 8700",
    "sg:postcode":"79936",
    "sg:province":"TX",
    "wof:name":"First Savings Bank East",
    "wof:placetype":"venue"
},
  "geometry": {"coordinates":[-106.27730699999999,31.758578],"type":"Point"}
}