{
  "type": "Feature",
  "properties": {
    "iso:country":"US",
    "sg:address":"407 E Lee Ave",
    "sg:city":"Kingsville",
    "sg:classifiers":[
        {
            "category":"Shopping",
            "subcategory":"Florist",
            "type":"Retail Goods"
        }
    ],
    "sg:phone":"+1 361 592 6199",
    "sg:postcode":"78363",
    "sg:province":"TX",
    "wof:name":"Linda's Flower Shop & Gifts",
    "wof:placetype":"venue"
},
  "geometry": {"coordinates":[-97.86339099999999,27.519718],"type":"Point"}
}