{
  "type": "Feature",
  "properties": {
    "iso:country":"US",
    "sg:address":"4643 Green Cottage Ln",
    "sg:city":"Missouri City",
    "sg:classifiers":[
        {
            "category":"Retail",
            "subcategory":"Repair Shop",
            "type":"Services"
        }
    ],
    "sg:phone":"+1 281 208 9299",
    "sg:postcode":"77459",
    "sg:province":"TX",
    "sg:tags":[
        "electrical"
    ],
    "wof:name":"Sugarland Appliance Service",
    "wof:placetype":"venue"
},
  "geometry": {"coordinates":[-95.575658,29.601413],"type":"Point"}
}