{
  "type": "Feature",
  "properties": {
    "iso:country":"US",
    "sg:address":"1022 Confederate St",
    "sg:city":"Liberty",
    "sg:classifiers":[
        {
            "category":"Organizations",
            "subcategory":"Religious Organization",
            "type":"Services"
        }
    ],
    "sg:phone":"+1 936 336 9424",
    "sg:postcode":"77575",
    "sg:province":"TX",
    "sg:tags":[
        "church"
    ],
    "wof:name":"Hispanic First Baptist Church",
    "wof:placetype":"venue"
},
  "geometry": {"coordinates":[-94.807278,30.055629],"type":"Point"}
}