{
  "type": "Feature",
  "properties": {
    "iso:country":"US",
    "sg:address":"705 S Polk St",
    "sg:city":"Amarillo",
    "sg:phone":"+1 806 374 3058",
    "sg:postcode":"79101",
    "sg:province":"TX",
    "wof:name":"Cafe Marizon",
    "wof:placetype":"venue"
},
  "geometry": {"coordinates":[-101.83723500000001,35.206578],"type":"Point"}
}