{
  "type": "Feature",
  "properties": {
    "iso:country":"US",
    "sg:address":"2436 SW 36th St",
    "sg:city":"San Antonio",
    "sg:classifiers":[
        {
            "category":"Wholesale",
            "subcategory":"Apparel",
            "type":"Manufacturing & Wholesale Goods"
        }
    ],
    "sg:phone":"+1 210 432 1774",
    "sg:postcode":"78237",
    "sg:province":"TX",
    "sg:tags":[
        "piece"
    ],
    "wof:name":"J R Enterprises",
    "wof:placetype":"venue"
},
  "geometry": {"coordinates":[-98.575205,29.4033],"type":"Point"}
}