{
  "type": "Feature",
  "properties": {
    "iso:country":"US",
    "sg:address":"1221 Terry Way",
    "sg:city":"Irving",
    "sg:classifiers":[
        {
            "category":"Building & Trades",
            "subcategory":"Landscaping Services",
            "type":"Services"
        }
    ],
    "sg:phone":"+1 972 257 0216",
    "sg:postcode":"75060",
    "sg:province":"TX",
    "sg:tags":[
        "designer",
        "landscape"
    ],
    "wof:name":"Dallas Custom Irrigates",
    "wof:placetype":"venue"
},
  "geometry": {"coordinates":[-96.972182,32.801837],"type":"Point"}
}