{
  "type": "Feature",
  "properties": {
    "iso:country":"US",
    "sg:address":"24 Langan St",
    "sg:city":"Brownsville",
    "sg:classifiers":[
        {
            "category":"Building & Trades",
            "subcategory":"Equipment Rental",
            "type":"Services"
        }
    ],
    "sg:phone":"+1 956 544 5565",
    "sg:postcode":"78521",
    "sg:province":"TX",
    "wof:name":"Ef Audio Visual Rentals",
    "wof:placetype":"venue"
},
  "geometry": {"coordinates":[-97.49891700000001,25.947417],"type":"Point"}
}