{
  "type": "Feature",
  "properties": {
    "iso:country":"US",
    "sg:address":"12934 Hilltop Dr",
    "sg:city":"Mesquite",
    "sg:classifiers":[
        {
            "category":"Professional",
            "type":"Services"
        }
    ],
    "sg:phone":"+1 972 288 6891",
    "sg:postcode":"75180",
    "sg:province":"TX",
    "wof:name":"M Js",
    "wof:placetype":"venue"
},
  "geometry": {"coordinates":[-96.602687,32.745748],"type":"Point"}
}