{
  "type": "Feature",
  "properties": {
    "iso:country":"US",
    "sg:address":"2800 Arcadia Ln",
    "sg:city":"Carrollton",
    "sg:classifiers":[
        {
            "category":"Manufacturing",
            "subcategory":"Toys & Sporting Goods",
            "type":"Manufacturing & Wholesale Goods"
        }
    ],
    "sg:phone":"+1 972 242 4679",
    "sg:postcode":"75007",
    "sg:province":"TX",
    "sg:tags":[
        "mfg"
    ],
    "wof:name":"Lyndals Backyard Workshop",
    "wof:placetype":"venue"
},
  "geometry": {"coordinates":[-96.887812,32.99035],"type":"Point"}
}