{
  "type": "Feature",
  "properties": {
    "iso:country":"US",
    "sg:address":"16 S Holland St",
    "sg:city":"Bellville",
    "sg:classifiers":[
        {
            "category":"Shopping",
            "subcategory":"Jewelry",
            "type":"Retail Goods"
        }
    ],
    "sg:phone":"+1 979 865 3941",
    "sg:postcode":"77418",
    "sg:province":"TX",
    "sg:tags":[
        "jeweler"
    ],
    "wof:name":"Michele Jewelry",
    "wof:placetype":"venue"
},
  "geometry": {"coordinates":[-96.25781499999999,29.950338],"type":"Point"}
}