{
  "type": "Feature",
  "properties": {
    "iso:country":"US",
    "sg:address":"16538 Twin Fox",
    "sg:city":"San Antonio",
    "sg:classifiers":[
        {
            "category":"Building & Trades",
            "subcategory":"Cleaning & Sanitation",
            "type":"Services"
        }
    ],
    "sg:phone":"+1 210 492 4914",
    "sg:postcode":"78247",
    "sg:province":"TX",
    "sg:tags":[
        "janitor"
    ],
    "wof:name":"Cleaning Professionals Inc",
    "wof:placetype":"venue"
},
  "geometry": {"coordinates":[-98.364496,29.587947],"type":"Point"}
}