{
  "type": "Feature",
  "properties": {
    "iso:country":"US",
    "sg:address":"3101 Shoreline Dr",
    "sg:city":"Austin",
    "sg:classifiers":[
        {
            "category":"Manufacturing",
            "subcategory":"Tools & Machinery",
            "type":"Manufacturing & Wholesale Goods"
        }
    ],
    "sg:phone":"+1 512 310 0010",
    "sg:postcode":"78728",
    "sg:province":"TX",
    "wof:name":"Sublett Company",
    "wof:placetype":"venue"
},
  "geometry": {"coordinates":[-97.681427,30.453273],"type":"Point"}
}