{
  "type": "Feature",
  "properties": {
    "iso:country":"US",
    "sg:address":"5803 Greenville Ave",
    "sg:city":"Dallas",
    "sg:classifiers":[
        {
            "category":"Real Estate",
            "subcategory":"Real Estate Agent",
            "type":"Services"
        }
    ],
    "sg:phone":"+1 214 691 6541",
    "sg:postcode":"75206",
    "sg:province":"TX",
    "sg:tags":[
        "management"
    ],
    "wof:name":"Central Control Leasing Office",
    "wof:placetype":"venue"
},
  "geometry": {"coordinates":[-96.769289,32.854449],"type":"Point"}
}