{
  "type": "Feature",
  "properties": {
    "iso:country":"US",
    "sg:address":"502 W Pierce St",
    "sg:city":"San Saba",
    "sg:classifiers":[
        {
            "category":"Personal",
            "subcategory":"Beauty Salon",
            "type":"Services"
        }
    ],
    "sg:phone":"+1 325 372 3111",
    "sg:postcode":"76877",
    "sg:province":"TX",
    "wof:name":"Pamper Palace Beauty Salon",
    "wof:placetype":"venue"
},
  "geometry": {"coordinates":[-98.724408,31.201562],"type":"Point"}
}