{
  "type": "Feature",
  "properties": {
    "iso:country":"US",
    "sg:address":"8606 Southbay Cir",
    "sg:city":"Rowlett",
    "sg:classifiers":[
        {
            "category":"Food & Beverages",
            "subcategory":"Groceries & Convenience Stores",
            "type":"Retail Goods"
        }
    ],
    "sg:phone":"+1 972 412 8756",
    "sg:postcode":"75088",
    "sg:province":"TX",
    "wof:name":"IGA Family Food Center",
    "wof:placetype":"venue"
},
  "geometry": {"coordinates":[-96.51762600000001,32.884124],"type":"Point"}
}