{
  "type": "Feature",
  "properties": {
    "iso:country":"US",
    "sg:address":"26312 Choctaw Pass St",
    "sg:city":"San Antonio",
    "sg:classifiers":[
        {
            "category":"Professional",
            "subcategory":"Management & Consulting",
            "type":"Services"
        }
    ],
    "sg:phone":"+1 830 438 9269",
    "sg:postcode":"78260",
    "sg:province":"TX",
    "sg:tags":[
        "consultant",
        "automation"
    ],
    "wof:name":"Premier Automation",
    "wof:placetype":"venue"
},
  "geometry": {"coordinates":[-98.488696,29.691129],"type":"Point"}
}