{
  "type": "Feature",
  "properties": {
    "iso:country":"US",
    "sg:address":"2002 Yale St",
    "sg:city":"Houston",
    "sg:classifiers":[
        {
            "category":"Restaurant",
            "type":"Food & Drink"
        }
    ],
    "sg:menulink":"http://www.allmenus.com/tx/houston/139504-quiznos-sub/menu/",
    "sg:phone":"+1 713 861 0188",
    "sg:postcode":"77008",
    "sg:province":"TX",
    "sg:tags":[
        "wrap",
        "american",
        "sandwich"
    ],
    "wof:name":"Quiznos Sub",
    "wof:placetype":"venue"
},
  "geometry": {"coordinates":[-95.398911,29.804198],"type":"Point"}
}