{
  "type": "Feature",
  "properties": {
    "iso:country":"US",
    "sg:address":"12515 Turkey Ridge Ct",
    "sg:city":"Austin",
    "sg:classifiers":[
        {
            "category":"Home & Garden",
            "subcategory":"Building Materials",
            "type":"Retail Goods"
        }
    ],
    "sg:phone":"+1 512 630 9915",
    "sg:postcode":"78729",
    "sg:province":"TX",
    "sg:tags":[
        "glass",
        "leaded"
    ],
    "wof:name":"Looking Glass Studio",
    "wof:placetype":"venue"
},
  "geometry": {"coordinates":[-97.768896,30.445761],"type":"Point"}
}