{
  "type": "Feature",
  "properties": {
    "iso:country":"US",
    "sg:address":"408 N Harston St",
    "sg:city":"Henrietta",
    "sg:classifiers":[
        {
            "category":"Organizations",
            "subcategory":"Religious Organization",
            "type":"Services"
        }
    ],
    "sg:phone":"+1 940 538 4706",
    "sg:postcode":"76365",
    "sg:province":"TX",
    "sg:tags":[
        "church"
    ],
    "wof:name":"Henrietta Church Of God",
    "wof:placetype":"venue"
},
  "geometry": {"coordinates":[-98.18907299999999,33.818876],"type":"Point"}
}