{
  "type": "Feature",
  "properties": {
    "iso:country":"US",
    "sg:address":"10742 Bywood Dr",
    "sg:city":"El Paso",
    "sg:classifiers":[
        {
            "category":"Professional",
            "type":"Services"
        }
    ],
    "sg:phone":"+1 915 598 2878",
    "sg:postcode":"79935",
    "sg:province":"TX",
    "wof:name":"Highwayman & Co Inc",
    "wof:placetype":"venue"
},
  "geometry": {"coordinates":[-106.32351300000001,31.778837],"type":"Point"}
}