{
  "type": "Feature",
  "properties": {
    "iso:country":"US",
    "sg:address":"16807 el Camino Real",
    "sg:city":"Houston",
    "sg:classifiers":[
        {
            "category":"Personal",
            "subcategory":"Beauty Salon",
            "type":"Services"
        }
    ],
    "sg:phone":"+1 281 461 4700",
    "sg:postcode":"77058",
    "sg:province":"TX",
    "sg:tags":[
        "hair"
    ],
    "wof:name":"T G F Precision Haircutters",
    "wof:placetype":"venue"
},
  "geometry": {"coordinates":[-95.11977400000001,29.554447],"type":"Point"}
}