{
  "type": "Feature",
  "properties": {
    "iso:country":"US",
    "sg:address":"6757 Arapaho Rd",
    "sg:city":"Dallas",
    "sg:classifiers":[
        {
            "category":"Arena",
            "subcategory":"Sports Club",
            "type":"Entertainment"
        }
    ],
    "sg:phone":"+1 972 480 8860",
    "sg:postcode":"75248",
    "sg:province":"TX",
    "sg:tags":[
        "membership"
    ],
    "wof:name":"Dallas North Soccer Assn",
    "wof:placetype":"venue"
},
  "geometry": {"coordinates":[-96.792644,32.962783],"type":"Point"}
}