{
  "type": "Feature",
  "properties": {
    "iso:country":"US",
    "sg:address":"6750 W Loop Fwy",
    "sg:city":"Bellaire",
    "sg:classifiers":[
        {
            "category":"Professional",
            "type":"Services"
        }
    ],
    "sg:phone":"+1 713 662 8590",
    "sg:postcode":"77401",
    "sg:province":"TX",
    "sg:tags":[
        "establishment"
    ],
    "wof:name":"MSDS Online Inc",
    "wof:placetype":"venue"
},
  "geometry": {"coordinates":[-95.4598,29.705779],"type":"Point"}
}