{
  "type": "Feature",
  "properties": {
    "iso:country":"US",
    "sg:address":"2910 Oak Trail Ct",
    "sg:city":"Arlington",
    "sg:classifiers":[
        {
            "category":"Manufacturing",
            "subcategory":"Retail Goods",
            "type":"Manufacturing & Wholesale Goods"
        }
    ],
    "sg:phone":"+1 817 462 1015",
    "sg:postcode":"76016",
    "sg:province":"TX",
    "sg:tags":[
        "product",
        "mfg"
    ],
    "wof:name":"Kcog Industries Inc",
    "wof:placetype":"venue"
},
  "geometry": {"coordinates":[-97.157121,32.689565],"type":"Point"}
}