{
  "type": "Feature",
  "properties": {
    "iso:country":"US",
    "sg:address":"1001 Business Pkwy",
    "sg:city":"Richardson",
    "sg:classifiers":[
        {
            "category":"Shopping",
            "subcategory":"Computers & Home Electronics",
            "type":"Retail Goods"
        }
    ],
    "sg:phone":"+1 972 792 7638",
    "sg:postcode":"75081",
    "sg:province":"TX",
    "sg:tags":[
        "software"
    ],
    "wof:name":"Safasoft Computer Consulting",
    "wof:placetype":"venue"
},
  "geometry": {"coordinates":[-96.738069,32.939469],"type":"Point"}
}