{
  "type": "Feature",
  "properties": {
    "iso:country":"US",
    "sg:address":"5470 N Jim Miller Rd",
    "sg:city":"Dallas",
    "sg:classifiers":[
        {
            "category":"Retail",
            "subcategory":"Car Wash",
            "type":"Services"
        }
    ],
    "sg:phone":"+1 214 381 0002",
    "sg:postcode":"75227",
    "sg:province":"TX",
    "sg:tags":[
        "polishing",
        "washing"
    ],
    "wof:name":"Super Wash & Dry LLC",
    "wof:placetype":"venue"
},
  "geometry": {"coordinates":[-96.700022,32.790995],"type":"Point"}
}