{
  "type": "Feature",
  "properties": {
    "iso:country":"US",
    "sg:address":"4006 Twin Falls St",
    "sg:city":"Irving",
    "sg:classifiers":[
        {
            "category":"Food & Beverages",
            "subcategory":"Groceries & Convenience Stores",
            "type":"Retail Goods"
        }
    ],
    "sg:phone":"+1 972 252 3572",
    "sg:postcode":"75062",
    "sg:province":"TX",
    "wof:name":"Mohammed S Souri",
    "wof:placetype":"venue"
},
  "geometry": {"coordinates":[-97.005028,32.853773],"type":"Point"}
}