{
  "type": "Feature",
  "properties": {
    "iso:country":"US",
    "sg:address":"2616 E Amarillo Blvd",
    "sg:city":"Amarillo",
    "sg:classifiers":[
        {
            "category":"Bars & Pubs",
            "type":"Food & Drink"
        }
    ],
    "sg:phone":"+1 806 626 0004",
    "sg:postcode":"79107",
    "sg:province":"TX",
    "sg:tags":[
        "club",
        "drinking",
        "night"
    ],
    "wof:name":"Lydia's II",
    "wof:placetype":"venue"
},
  "geometry": {"coordinates":[-101.807112,35.221831],"type":"Point"}
}