{
  "type": "Feature",
  "properties": {
    "iso:country":"US",
    "sg:address":"911 Commerce St",
    "sg:city":"Portland",
    "sg:classifiers":[
        {
            "category":"Social Services",
            "subcategory":"Child Care",
            "type":"Services"
        }
    ],
    "sg:phone":"+1 361 777 0778",
    "sg:postcode":"78374",
    "sg:province":"TX",
    "sg:tags":[
        "day"
    ],
    "wof:name":"Adult Day Center",
    "wof:placetype":"venue"
},
  "geometry": {"coordinates":[-97.32049600000001,27.877442],"type":"Point"}
}