{
  "type": "Feature",
  "properties": {
    "iso:country":"US",
    "sg:address":"4875 Parker Dr",
    "sg:city":"Beaumont",
    "sg:classifiers":[
        {
            "category":"Airport",
            "type":"Transportation"
        }
    ],
    "sg:phone":"+1 409 722 0251",
    "sg:postcode":"77705",
    "sg:province":"TX",
    "sg:website":"www.co.jefferson.tx.us",
    "wof:name":"Southeast Tx Regional Airport",
    "wof:placetype":"venue"
},
  "geometry": {"coordinates":[-94.020695,29.960946],"type":"Point"}
}