{
  "type": "Feature",
  "properties": {
    "iso:country":"US",
    "sg:address":"404 Brookview Ln",
    "sg:city":"Palestine",
    "sg:classifiers":[
        {
            "category":"Personal",
            "type":"Services"
        }
    ],
    "sg:phone":"+1 903 723 9005",
    "sg:postcode":"75803",
    "sg:province":"TX",
    "sg:tags":[
        "therapist",
        "massage"
    ],
    "wof:name":"Austin Therapeutics",
    "wof:placetype":"venue"
},
  "geometry": {"coordinates":[-95.685164,31.738307],"type":"Point"}
}