{
  "type": "Feature",
  "properties": {
    "iso:country":"US",
    "sg:address":"11231 Alvin St",
    "sg:city":"Dallas",
    "sg:classifiers":[
        {
            "category":"Social Services",
            "type":"Services"
        }
    ],
    "sg:phone":"+1 214 320 9966",
    "sg:postcode":"75218",
    "sg:province":"TX",
    "wof:name":"Casa Group",
    "wof:placetype":"venue"
},
  "geometry": {"coordinates":[-96.68772,32.84497],"type":"Point"}
}