{
  "type": "Feature",
  "properties": {
    "iso:country":"US",
    "sg:address":"619 Quail Run Dr",
    "sg:city":"Murphy",
    "sg:classifiers":[
        {
            "category":"Building & Trades",
            "subcategory":"Construction",
            "type":"Services"
        }
    ],
    "sg:phone":"+1 972 384 0696",
    "sg:postcode":"75094",
    "sg:province":"TX",
    "sg:tags":[
        "home",
        "builder"
    ],
    "wof:name":"Hampton Homes",
    "wof:placetype":"venue"
},
  "geometry": {"coordinates":[-96.628682,33.03341],"type":"Point"}
}