{
  "type": "Feature",
  "properties": {
    "iso:country":"US",
    "sg:address":"5600 Cameron Road",
    "sg:city":"Austin",
    "sg:classifiers":[
        {
            "category":"Restaurant",
            "type":"Food & Drink"
        }
    ],
    "sg:phone":"+1 512 419 9030",
    "sg:postcode":"78723",
    "sg:province":"TX",
    "wof:name":"Long John Silvers",
    "wof:placetype":"venue"
},
  "geometry": {"coordinates":[-97.704058,30.313636],"type":"Point"}
}