{
  "type": "Feature",
  "properties": {
    "iso:country":"US",
    "sg:address":"2747 S Foster Rd",
    "sg:city":"San Antonio",
    "sg:classifiers":[
        {
            "category":"Building & Trades",
            "subcategory":"Equipment Rental",
            "type":"Services"
        }
    ],
    "sg:phone":"+1 210 495 3622",
    "sg:postcode":"78220",
    "sg:province":"TX",
    "wof:name":"Hawk Aero Ventures LLC",
    "wof:placetype":"venue"
},
  "geometry": {"coordinates":[-98.360888,29.396717],"type":"Point"}
}