{
  "type": "Feature",
  "properties": {
    "iso:country":"US",
    "sg:address":"3056 S FM 369",
    "sg:city":"Iowa Park",
    "sg:classifiers":[
        {
            "category":"Wholesale",
            "subcategory":"Home Furnishings",
            "type":"Manufacturing & Wholesale Goods"
        }
    ],
    "sg:phone":"+1 940 855 4572",
    "sg:postcode":"76367",
    "sg:province":"TX",
    "sg:tags":[
        "tile",
        "carpet"
    ],
    "wof:name":"Popular Flooring",
    "wof:placetype":"venue"
},
  "geometry": {"coordinates":[-98.602977,33.907329],"type":"Point"}
}