{
  "type": "Feature",
  "properties": {
    "iso:country":"US",
    "sg:address":"754 Love Rd",
    "sg:city":"Victoria",
    "sg:classifiers":[
        {
            "category":"Building & Trades",
            "subcategory":"Construction",
            "type":"Services"
        }
    ],
    "sg:phone":"+1 361 576 4340",
    "sg:postcode":"77904",
    "sg:province":"TX",
    "sg:tags":[
        "house"
    ],
    "wof:name":"Barts Roofing & Home Repair",
    "wof:placetype":"venue"
},
  "geometry": {"coordinates":[-97.079206,28.922794],"type":"Point"}
}