{
  "type": "Feature",
  "properties": {
    "iso:country":"US",
    "sg:address":"5490 Braesvalley Dr",
    "sg:city":"Houston",
    "sg:classifiers":[
        {
            "category":"Professional",
            "subcategory":"Advertising",
            "type":"Services"
        }
    ],
    "sg:phone":"+1 713 728 8142",
    "sg:postcode":"77096",
    "sg:province":"TX",
    "sg:tags":[
        "agency"
    ],
    "wof:name":"Carlock Design",
    "wof:placetype":"venue"
},
  "geometry": {"coordinates":[-95.48374099999999,29.679204],"type":"Point"}
}