{
  "type": "Feature",
  "properties": {
    "iso:country":"US",
    "sg:address":"13681 Wigginsville Rd",
    "sg:city":"Conroe",
    "sg:classifiers":[
        {
            "category":"Professional",
            "type":"Services"
        }
    ],
    "sg:phone":"+1 936 446 2948",
    "sg:postcode":"77302",
    "sg:province":"TX",
    "wof:name":"Texas Draw Inc",
    "wof:placetype":"venue"
},
  "geometry": {"coordinates":[-95.338015,30.252871],"type":"Point"}
}