{
  "type": "Feature",
  "properties": {
    "iso:country":"US",
    "sg:address":"2906 SE Loop 820",
    "sg:city":"Fort Worth",
    "sg:classifiers":[
        {
            "category":"Wholesale",
            "subcategory":"Durable Goods & Equipment",
            "type":"Manufacturing & Wholesale Goods"
        }
    ],
    "sg:phone":"+1 817 551 1510",
    "sg:postcode":"76140",
    "sg:province":"TX",
    "sg:tags":[
        "exporter"
    ],
    "wof:name":"M X Porters Co",
    "wof:placetype":"venue"
},
  "geometry": {"coordinates":[-97.292002,32.664605],"type":"Point"}
}