{
  "type": "Feature",
  "properties": {
    "iso:country":"US",
    "sg:address":"900 Hillsboro St",
    "sg:city":"Cleburne",
    "sg:classifiers":[
        {
            "category":"Recreation",
            "type":"Entertainment"
        }
    ],
    "sg:phone":"+1 817 641 3323",
    "sg:postcode":"76033",
    "sg:province":"TX",
    "sg:tags":[
        "pool",
        "swimming"
    ],
    "wof:name":"City Of Cleburne Swimming Pool",
    "wof:placetype":"venue"
},
  "geometry": {"coordinates":[-97.386145,32.339442],"type":"Point"}
}