{
  "type": "Feature",
  "properties": {
    "iso:country":"US",
    "sg:address":"19911 Country Lake Dr",
    "sg:city":"Magnolia",
    "sg:classifiers":[
        {
            "category":"Building & Trades",
            "subcategory":"Construction",
            "type":"Services"
        }
    ],
    "sg:phone":"+1 281 252 3399",
    "sg:postcode":"77355",
    "sg:province":"TX",
    "sg:tags":[
        "general",
        "contractor"
    ],
    "wof:name":"West Associates & C & S Tech",
    "wof:placetype":"venue"
},
  "geometry": {"coordinates":[-95.75877199999999,30.15907],"type":"Point"}
}