{
  "type": "Feature",
  "properties": {
    "iso:country":"US",
    "sg:address":"5235 W Davis St Ste 102",
    "sg:city":"Dallas",
    "sg:classifiers":[
        {
            "category":"Retail",
            "subcategory":"Laundry & Dry Cleaning",
            "type":"Services"
        }
    ],
    "sg:phone":"+1 972 258 0484",
    "sg:postcode":"75211",
    "sg:province":"TX",
    "sg:tags":[
        "laundries-self"
    ],
    "wof:name":"Rosa De La Laundry",
    "wof:placetype":"venue"
},
  "geometry": {"coordinates":[-96.91188099999999,32.749699],"type":"Point"}
}