{
  "type": "Feature",
  "properties": {
    "iso:country":"US",
    "sg:address":"9415 Wahada Ave",
    "sg:city":"San Antonio",
    "sg:classifiers":[
        {
            "category":"Building & Trades",
            "subcategory":"Construction",
            "type":"Services"
        }
    ],
    "sg:phone":"+1 210 822 6634",
    "sg:postcode":"78217",
    "sg:province":"TX",
    "sg:tags":[
        "residential"
    ],
    "wof:name":"Shyga",
    "wof:placetype":"venue"
},
  "geometry": {"coordinates":[-98.44781500000001,29.526117],"type":"Point"}
}