{
  "type": "Feature",
  "properties": {
    "iso:country":"US",
    "sg:address":"2519 Maverick Ave",
    "sg:city":"Dallas",
    "sg:classifiers":[
        {
            "category":"Building & Trades",
            "subcategory":"Construction",
            "type":"Services"
        }
    ],
    "sg:phone":"+1 214 319 7660",
    "sg:postcode":"75228",
    "sg:province":"TX",
    "sg:tags":[
        "contractor"
    ],
    "wof:name":"Control Roofing",
    "wof:placetype":"venue"
},
  "geometry": {"coordinates":[-96.674436,32.821353],"type":"Point"}
}