{
  "type": "Feature",
  "properties": {
    "iso:country":"US",
    "sg:address":"1404 Bedford St",
    "sg:city":"Dallas",
    "sg:classifiers":[
        {
            "category":"Building & Trades",
            "subcategory":"Landscaping Services",
            "type":"Services"
        }
    ],
    "sg:phone":"+1 214 749 4746",
    "sg:postcode":"75212",
    "sg:province":"TX",
    "sg:tags":[
        "landscape",
        "contractor"
    ],
    "wof:name":"Tony's Lawn Care & Land Scape",
    "wof:placetype":"venue"
},
  "geometry": {"coordinates":[-96.84381999999999,32.777346],"type":"Point"}
}