{
  "type": "Feature",
  "properties": {
    "iso:country":"US",
    "sg:address":"2210 Gulf Fwy",
    "sg:city":"La Marque",
    "sg:classifiers":[
        {
            "category":"Real Estate",
            "subcategory":"Real Estate Agent",
            "type":"Services"
        }
    ],
    "sg:phone":"+1 409 938 0503",
    "sg:postcode":"77568",
    "sg:province":"TX",
    "wof:name":"Carla Eriksson Realtor",
    "wof:placetype":"venue"
},
  "geometry": {"coordinates":[-94.976333,29.355787],"type":"Point"}
}