{
  "type": "Feature",
  "properties": {
    "iso:country":"US",
    "sg:address":"5833 Wales Ave",
    "sg:city":"Fort Worth",
    "sg:classifiers":[
        {
            "category":"Professional",
            "subcategory":"Business Services",
            "type":"Services"
        }
    ],
    "sg:phone":"+1 817 292 2456",
    "sg:postcode":"76133",
    "sg:province":"TX",
    "wof:name":"Bellaire Pool Service",
    "wof:placetype":"venue"
},
  "geometry": {"coordinates":[-97.389538,32.66],"type":"Point"}
}