{
  "type": "Feature",
  "properties": {
    "iso:country":"US",
    "sg:address":"13850 Gulf Fwy",
    "sg:city":"Houston",
    "sg:classifiers":[
        {
            "category":"Wholesale",
            "subcategory":"Machinery & Supplies",
            "type":"Manufacturing & Wholesale Goods"
        },
        {
            "category":"Mining & Drilling",
            "type":"Manufacturing & Wholesale Goods"
        }
    ],
    "sg:phone":"+1 281 464 9900",
    "sg:postcode":"77034",
    "sg:province":"TX",
    "sg:tags":[
        "field",
        "oil",
        "tank",
        "equipment"
    ],
    "wof:name":"Gonzalez Specialty Systems",
    "wof:placetype":"venue"
},
  "geometry": {"coordinates":[-95.20153000000001,29.601938],"type":"Point"}
}