{
  "type": "Feature",
  "properties": {
    "iso:country":"US",
    "sg:address":"15 Chartres St",
    "sg:city":"Houston",
    "sg:classifiers":[
        {
            "category":"Real Estate",
            "subcategory":"Real Estate Operator",
            "type":"Services"
        }
    ],
    "sg:phone":"+1 713 664 8817",
    "sg:postcode":"77002",
    "sg:province":"TX",
    "sg:tags":[
        "building",
        "apartment"
    ],
    "wof:name":"Oaks of Charleston Guard House",
    "wof:placetype":"venue"
},
  "geometry": {"coordinates":[-95.350399,29.759096],"type":"Point"}
}