{
  "type": "Feature",
  "properties": {
    "iso:country":"US",
    "sg:address":"18050 Kingsland Blvd",
    "sg:city":"Houston",
    "sg:classifiers":[
        {
            "category":"Retail",
            "subcategory":"Auto Repair",
            "type":"Services"
        }
    ],
    "sg:phone":"+1 281 398 6300",
    "sg:postcode":"77094",
    "sg:province":"TX",
    "sg:tags":[
        "general"
    ],
    "wof:name":"Tripps Auto Tech Inc",
    "wof:placetype":"venue"
},
  "geometry": {"coordinates":[-95.68884300000001,29.776556],"type":"Point"}
}