{
  "type": "Feature",
  "properties": {
    "iso:country":"US",
    "sg:address":"5911 Inks Lake Dr",
    "sg:city":"Arlington",
    "sg:classifiers":[
        {
            "category":"Retail",
            "subcategory":"Repair Shop",
            "type":"Services"
        }
    ],
    "sg:phone":"+1 817 557 3503",
    "sg:postcode":"76018",
    "sg:province":"TX",
    "wof:name":"Metro Cleaning",
    "wof:placetype":"venue"
},
  "geometry": {"coordinates":[-97.104895,32.64764],"type":"Point"}
}