{
  "type": "Feature",
  "properties": {
    "iso:country":"US",
    "sg:address":"10 Nandina Cir",
    "sg:city":"Abilene",
    "sg:classifiers":[
        {
            "category":"Professional",
            "type":"Services"
        }
    ],
    "sg:phone":"+1 325 692 7530",
    "sg:postcode":"79605",
    "sg:province":"TX",
    "wof:name":"Dmh Family",
    "wof:placetype":"venue"
},
  "geometry": {"coordinates":[-99.77345099999999,32.415996],"type":"Point"}
}