{
  "type": "Feature",
  "properties": {
    "iso:country":"US",
    "sg:address":"4012 Spring Branch Dr E",
    "sg:city":"Pearland",
    "sg:classifiers":[
        {
            "category":"Shopping",
            "subcategory":"Hobbies, Toys, & Games",
            "type":"Retail Goods"
        }
    ],
    "sg:phone":"+1 281 899 6850",
    "sg:postcode":"77584",
    "sg:province":"TX",
    "sg:tags":[
        "model",
        "supply"
    ],
    "wof:name":"James E Grotts Hobby Supplies",
    "wof:placetype":"venue"
},
  "geometry": {"coordinates":[-95.298152,29.536137],"type":"Point"}
}