{
  "type": "Feature",
  "properties": {
    "iso:country":"US",
    "sg:address":"6031 Breakpoint Trl",
    "sg:city":"Dallas",
    "sg:classifiers":[
        {
            "category":"Professional",
            "subcategory":"Computer Services",
            "type":"Services"
        }
    ],
    "sg:phone":"+1 972 380 5683",
    "sg:postcode":"75252",
    "sg:province":"TX",
    "sg:tags":[
        "programing",
        "custom"
    ],
    "wof:name":"Wuerfel Inc",
    "wof:placetype":"venue"
},
  "geometry": {"coordinates":[-96.801692,33.008915],"type":"Point"}
}