{
  "type": "Feature",
  "properties": {
    "iso:country":"US",
    "sg:address":"5615 Kirby Dr",
    "sg:city":"Houston",
    "sg:classifiers":[
        {
            "category":"Organizations",
            "subcategory":"Non-profit Organization",
            "type":"Services"
        }
    ],
    "sg:phone":"+1 713 529 4646",
    "sg:postcode":"77005",
    "sg:province":"TX",
    "sg:tags":[
        "fund",
        "raising"
    ],
    "wof:name":"Good Samaritan Foundation",
    "wof:placetype":"venue"
},
  "geometry": {"coordinates":[-95.41844,29.721576],"type":"Point"}
}