{
  "type": "Feature",
  "properties": {
    "iso:country":"US",
    "sg:address":"4702 FM 1960 W",
    "sg:city":"Houston",
    "sg:classifiers":[
        {
            "category":"Real Estate",
            "subcategory":"Real Estate Agent",
            "type":"Services"
        }
    ],
    "sg:phone":"+1 281 440 7444",
    "sg:postcode":"77069",
    "sg:province":"TX",
    "wof:name":"Executive Realty",
    "wof:placetype":"venue"
},
  "geometry": {"coordinates":[-95.501502,29.986058],"type":"Point"}
}