{
  "type": "Feature",
  "properties": {
    "iso:country":"US",
    "sg:address":"4520 Baldwin Blvd",
    "sg:city":"Corpus Christi",
    "sg:classifiers":[
        {
            "category":"Health Services",
            "subcategory":"Medical Lab",
            "type":"Services"
        }
    ],
    "sg:phone":"+1 361 885 0019",
    "sg:postcode":"78408",
    "sg:province":"TX",
    "sg:tags":[
        "x"
    ],
    "wof:name":"H & H X-Ray Svc",
    "wof:placetype":"venue"
},
  "geometry": {"coordinates":[-97.44564699999999,27.791658],"type":"Point"}
}