{
  "type": "Feature",
  "properties": {
    "iso:country":"US",
    "sg:address":"703 Thrush Dr",
    "sg:city":"Leander",
    "sg:classifiers":[
        {
            "category":"Shopping",
            "subcategory":"Music",
            "type":"Retail Goods"
        }
    ],
    "sg:phone":"+1 512 260 2192",
    "sg:postcode":"78641",
    "sg:province":"TX",
    "wof:name":"Crossroad Records LLC",
    "wof:placetype":"venue"
},
  "geometry": {"coordinates":[-97.839568,30.567346],"type":"Point"}
}