{
  "type": "Feature",
  "properties": {
    "iso:country":"US",
    "sg:address":"18100 Chisholm Trl",
    "sg:city":"Houston",
    "sg:classifiers":[
        {
            "category":"Freight",
            "type":"Transportation"
        }
    ],
    "sg:phone":"+1 800 723 1804",
    "sg:postcode":"77060",
    "sg:province":"TX",
    "sg:tags":[
        "carrier",
        "common"
    ],
    "wof:name":"J B Hunt Corporation",
    "wof:placetype":"venue"
},
  "geometry": {"coordinates":[-95.401646,29.962825],"type":"Point"}
}