{
  "type": "Feature",
  "properties": {
    "iso:country":"US",
    "sg:address":"3102 Live Oak Dr",
    "sg:city":"Rowlett",
    "sg:classifiers":[
        {
            "category":"Organizations",
            "subcategory":"Religious Organization",
            "type":"Services"
        }
    ],
    "sg:phone":"+1 972 412 2627",
    "sg:postcode":"75088",
    "sg:province":"TX",
    "sg:tags":[
        "church"
    ],
    "wof:name":"Church Of Christ",
    "wof:placetype":"venue"
},
  "geometry": {"coordinates":[-96.57359700000001,32.889558],"type":"Point"}
}