{
  "type": "Feature",
  "properties": {
    "iso:country":"US",
    "sg:address":"5333 Matlock Rd",
    "sg:city":"Arlington",
    "sg:classifiers":[
        {
            "category":"Autos & Motor Vehicles",
            "subcategory":"Auto Supplies",
            "type":"Retail Goods"
        },
        {
            "category":"Retail",
            "subcategory":"Auto Repair",
            "type":"Services"
        }
    ],
    "sg:phone":"+1 817 468 0200",
    "sg:postcode":"76018",
    "sg:province":"TX",
    "sg:tags":[
        "lube",
        "oil",
        "brake"
    ],
    "wof:name":"Kwik Kar Lube & Tune",
    "wof:placetype":"venue"
},
  "geometry": {"coordinates":[-97.114959,32.660923],"type":"Point"}
}