{
  "type": "Feature",
  "properties": {
    "iso:country":"US",
    "sg:address":"14610 Grisby Rd",
    "sg:city":"Houston",
    "sg:classifiers":[
        {
            "category":"Restaurant",
            "type":"Food & Drink"
        }
    ],
    "sg:phone":"+1 281 870 9682",
    "sg:postcode":"77079",
    "sg:province":"TX",
    "wof:name":"Charlie's Hamburger Joint",
    "wof:placetype":"venue"
},
  "geometry": {"coordinates":[-95.643672,29.782646],"type":"Point"}
}