{
  "type": "Feature",
  "properties": {
    "iso:country":"US",
    "sg:address":"3100 Timmons Ln",
    "sg:city":"Houston",
    "sg:classifiers":[
        {
            "category":"Personal",
            "subcategory":"Beauty Salon",
            "type":"Services"
        }
    ],
    "sg:phone":"+1 713 621 2572",
    "sg:postcode":"77027",
    "sg:province":"TX",
    "sg:tags":[
        "hair"
    ],
    "wof:name":"Coiffure Brittany",
    "wof:placetype":"venue"
},
  "geometry": {"coordinates":[-95.436711,29.736698],"type":"Point"}
}