{
  "type": "Feature",
  "properties": {
    "iso:country":"US",
    "sg:address":"101 S Orange St",
    "sg:city":"Sweeny",
    "sg:classifiers":[
        {
            "category":"Professional",
            "subcategory":"Business Services",
            "type":"Services"
        }
    ],
    "sg:phone":"+1 979 548 4910",
    "sg:postcode":"77480",
    "sg:province":"TX",
    "wof:name":"Transue Enterprises Inc",
    "wof:placetype":"venue"
},
  "geometry": {"coordinates":[-95.69533,29.040726],"type":"Point"}
}