{
  "type": "Feature",
  "properties": {
    "iso:country":"US",
    "sg:address":"3930 Brawner Pkwy",
    "sg:city":"Corpus Christi",
    "sg:classifiers":[
        {
            "category":"Building & Trades",
            "subcategory":"Construction",
            "type":"Services"
        }
    ],
    "sg:phone":"+1 361 854 1097",
    "sg:postcode":"78411",
    "sg:province":"TX",
    "sg:tags":[
        "painter"
    ],
    "wof:name":"Hernandez R L Painting",
    "wof:placetype":"venue"
},
  "geometry": {"coordinates":[-97.391847,27.740034],"type":"Point"}
}