{
  "type": "Feature",
  "properties": {
    "iso:country":"US",
    "sg:address":"2802 Kingswood Dr",
    "sg:city":"Garland",
    "sg:classifiers":[
        {
            "category":"Building & Trades",
            "subcategory":"Landscaping Services",
            "type":"Services"
        }
    ],
    "sg:phone":"+1 972 530 7190",
    "sg:postcode":"75040",
    "sg:province":"TX",
    "wof:name":"Classic Landscape & Maint",
    "wof:placetype":"venue"
},
  "geometry": {"coordinates":[-96.623339,32.941483],"type":"Point"}
}