{
  "type": "Feature",
  "properties": {
    "iso:country":"US",
    "sg:address":"800 S Polk St",
    "sg:city":"Amarillo",
    "sg:classifiers":[
        {
            "category":"Personal",
            "type":"Services"
        },
        {
            "category":"Restaurant",
            "type":"Food & Drink"
        },
        {
            "category":"Retail",
            "subcategory":"Event Space",
            "type":"Services"
        }
    ],
    "sg:phone":"+1 806 373 8889",
    "sg:postcode":"79101",
    "sg:province":"TX",
    "sg:tags":[
        "mexican",
        "facility",
        "hall",
        "planning",
        "reception",
        "party",
        "meeting",
        "banquet"
    ],
    "sg:website":"http://www.acapulcomexicanrestaurant.net",
    "wof:name":"Acapulco Mexican Restaurant",
    "wof:placetype":"venue"
},
  "geometry": {"coordinates":[-101.837433,35.205601],"type":"Point"}
}