{
  "type": "Feature",
  "properties": {
    "iso:country":"US",
    "sg:address":"6218 S Flores St",
    "sg:city":"San Antonio",
    "sg:classifiers":[
        {
            "category":"Shopping",
            "subcategory":"Clothing, Apparel, & Fashions",
            "type":"Retail Goods"
        }
    ],
    "sg:phone":"+1 210 923 7785",
    "sg:postcode":"78214",
    "sg:province":"TX",
    "sg:tags":[
        "alteration"
    ],
    "wof:name":"Pope's Cleaners & Laundry",
    "wof:placetype":"venue"
},
  "geometry": {"coordinates":[-98.49312,29.362007],"type":"Point"}
}