{
  "type": "Feature",
  "properties": {
    "iso:country":"US",
    "sg:address":"1905 Morningstar Trl",
    "sg:city":"Richardson",
    "sg:classifiers":[
        {
            "category":"Professional",
            "subcategory":"Business Services",
            "type":"Services"
        }
    ],
    "sg:phone":"+1 972 783 1176",
    "sg:postcode":"75081",
    "sg:province":"TX",
    "wof:name":"NSM Assoc",
    "wof:placetype":"venue"
},
  "geometry": {"coordinates":[-96.686922,32.940295],"type":"Point"}
}