{
  "type": "Feature",
  "properties": {
    "iso:country":"US",
    "sg:address":"10440 N Central Expy",
    "sg:city":"Dallas",
    "sg:classifiers":[
        {
            "category":"Professional",
            "subcategory":"Lawyer & Legal Services",
            "type":"Services"
        }
    ],
    "sg:phone":"+1 214 747 0422",
    "sg:postcode":"75231",
    "sg:province":"TX",
    "sg:tags":[
        "attorney"
    ],
    "sg:website":"www.brianloncar.com",
    "wof:name":"Loncar & Assoc",
    "wof:placetype":"venue"
},
  "geometry": {"coordinates":[-96.769361,32.887973],"type":"Point"}
}