{
  "type": "Feature",
  "properties": {
    "iso:country":"US",
    "sg:address":"2325 Woodside Dr",
    "sg:city":"Beaumont",
    "sg:classifiers":[
        {
            "category":"Recreation",
            "type":"Entertainment"
        }
    ],
    "sg:phone":"+1 409 860 9865",
    "sg:postcode":"77707",
    "sg:province":"TX",
    "wof:name":"Sno Mobile",
    "wof:placetype":"venue"
},
  "geometry": {"coordinates":[-94.201604,30.054308],"type":"Point"}
}