{
  "type": "Feature",
  "properties": {
    "iso:country":"US",
    "sg:address":"1317 N Loop Fwy",
    "sg:city":"Houston",
    "sg:classifiers":[
        {
            "category":"Organizations",
            "subcategory":"Religious Organization",
            "type":"Services"
        }
    ],
    "sg:phone":"+1 713 862 2133",
    "sg:postcode":"77022",
    "sg:province":"TX",
    "sg:tags":[
        "church"
    ],
    "wof:name":"Greater Mount Olive Baptist",
    "wof:placetype":"venue"
},
  "geometry": {"coordinates":[-95.381221,29.814442],"type":"Point"}
}