{
  "type": "Feature",
  "properties": {
    "iso:country":"US",
    "sg:address":"715 E End Blvd S",
    "sg:city":"Marshall",
    "sg:classifiers":[
        {
            "category":"Banks & Credit Unions",
            "subcategory":"Bank",
            "type":"Services"
        }
    ],
    "sg:phone":"+1 903 927 2040",
    "sg:postcode":"75670",
    "sg:province":"TX",
    "sg:website":"www.texasbankandtrust.com",
    "wof:name":"Texas Bank & Trust",
    "wof:placetype":"venue"
},
  "geometry": {"coordinates":[-94.34952,32.539056],"type":"Point"}
}