{
  "type": "Feature",
  "properties": {
    "iso:country":"US",
    "sg:address":"5671 Hazen St",
    "sg:city":"Houston",
    "sg:classifiers":[
        {
            "category":"Professional",
            "type":"Services"
        }
    ],
    "sg:phone":"+1 713 777 5012",
    "sg:postcode":"77081",
    "sg:province":"TX",
    "wof:name":"Keith Lindloff Pllc",
    "wof:placetype":"venue"
},
  "geometry": {"coordinates":[-95.491784,29.691534],"type":"Point"}
}