{
  "type": "Feature",
  "properties": {
    "iso:country":"US",
    "sg:address":"4211 Main St",
    "sg:city":"Lewisville",
    "sg:classifiers":[
        {
            "category":"Professional",
            "subcategory":"Business Services",
            "type":"Services"
        }
    ],
    "sg:phone":"+1 972 434 2640",
    "sg:postcode":"75056",
    "sg:province":"TX",
    "wof:name":"Burgess Bail Bonds",
    "wof:placetype":"venue"
},
  "geometry": {"coordinates":[-96.892481,33.071724],"type":"Point"}
}