{
  "type": "Feature",
  "properties": {
    "iso:country":"US",
    "sg:address":"1701 Gateway Blvd Ste 349",
    "sg:city":"Richardson",
    "sg:classifiers":[
        {
            "category":"Health Services",
            "subcategory":"Doctor",
            "type":"Services"
        },
        {
            "category":"Professional",
            "subcategory":"Business Services",
            "type":"Services"
        },
        {
            "category":"Wholesale",
            "subcategory":"Books, Periodicals, & Newspapers",
            "type":"Manufacturing & Wholesale Goods"
        }
    ],
    "sg:phone":"+1 972 918 9588",
    "sg:postcode":"75080",
    "sg:province":"TX",
    "sg:tags":[
        "consultant",
        "publisher",
        "publishing",
        "representative"
    ],
    "sg:website":"http://www.rossinst.com",
    "wof:name":"Ross Institute",
    "wof:placetype":"venue"
},
  "geometry": {"coordinates":[-96.721733,32.97115],"type":"Point"}
}