{
  "type": "Feature",
  "properties": {
    "iso:country":"US",
    "sg:address":"6101 I- 20",
    "sg:city":"Fort Worth",
    "sg:classifiers":[
        {
            "category":"Shopping",
            "subcategory":"Bicycles & Sporting Goods",
            "type":"Retail Goods"
        }
    ],
    "sg:phone":"+1 817 346 6622",
    "sg:postcode":"76119",
    "sg:province":"TX",
    "sg:tags":[
        "athletic",
        "apparel",
        "sport",
        "footwear"
    ],
    "wof:name":"Academy Sports & Outdoors",
    "wof:placetype":"venue"
},
  "geometry": {"coordinates":[-97.240775,32.665754],"type":"Point"}
}