{
  "type": "Feature",
  "properties": {
    "iso:country":"US",
    "sg:address":"5306 Treewood Dr",
    "sg:city":"Humble",
    "sg:classifiers":[
        {
            "category":"Shopping",
            "subcategory":"Used Merchandise",
            "type":"Retail Goods"
        }
    ],
    "sg:phone":"+1 281 442 7425",
    "sg:postcode":"77346",
    "sg:province":"TX",
    "sg:tags":[
        "second",
        "store",
        "hand"
    ],
    "wof:name":"Ace Of Hearts",
    "wof:placetype":"venue"
},
  "geometry": {"coordinates":[-95.194652,30.013001],"type":"Point"}
}