{
  "type": "Feature",
  "properties": {
    "iso:country":"US",
    "sg:address":"2825 Stadium Dr",
    "sg:city":"Fort Worth",
    "sg:classifiers":[
        {
            "category":"Health Services",
            "subcategory":"Doctor",
            "type":"Services"
        }
    ],
    "sg:phone":"+1 817 257 7940",
    "sg:postcode":"76109",
    "sg:province":"TX",
    "sg:tags":[
        "physician",
        "surgeon"
    ],
    "sg:website":"www.healthcenter.tcu.edu",
    "wof:name":"TCU Health Ctr",
    "wof:placetype":"venue"
},
  "geometry": {"coordinates":[-97.365222,32.710301],"type":"Point"}
}