{
  "type": "Feature",
  "properties": {
    "iso:country":"US",
    "sg:address":"2336 Moneda St",
    "sg:city":"Fort Worth",
    "sg:classifiers":[
        {
            "category":"Building & Trades",
            "subcategory":"Landscaping Services",
            "type":"Services"
        }
    ],
    "sg:phone":"+1 817 834 4044",
    "sg:postcode":"76117",
    "sg:province":"TX",
    "sg:tags":[
        "landscape",
        "contractor"
    ],
    "wof:name":"Terra Nova Landscape Mntnc",
    "wof:placetype":"venue"
},
  "geometry": {"coordinates":[-97.254324,32.793975],"type":"Point"}
}