{
  "type": "Feature",
  "properties": {
    "iso:country":"US",
    "sg:address":"222 Ridge Rd",
    "sg:city":"Breckenridge",
    "sg:classifiers":[
        {
            "category":"Shopping",
            "subcategory":"Clothing, Apparel, & Fashions",
            "type":"Retail Goods"
        }
    ],
    "sg:phone":"+1 254 559 3086",
    "sg:postcode":"76424",
    "sg:province":"TX",
    "sg:tags":[
        "boutique",
        "lady"
    ],
    "wof:name":"Jeans Selections & Boutique",
    "wof:placetype":"venue"
},
  "geometry": {"coordinates":[-98.93310200000001,32.757674],"type":"Point"}
}