{
  "type": "Feature",
  "properties": {
    "iso:country":"US",
    "sg:address":"402 S C M Allen Pkwy",
    "sg:city":"San Marcos",
    "sg:classifiers":[
        {
            "category":"Professional",
            "subcategory":"Business Services",
            "type":"Services"
        },
        {
            "category":"Professional",
            "subcategory":"Management & Consulting",
            "type":"Services"
        }
    ],
    "sg:phone":"+1 512 754 6801",
    "sg:postcode":"78666",
    "sg:province":"TX",
    "wof:name":"International Business Svcs Co",
    "wof:placetype":"venue"
},
  "geometry": {"coordinates":[-97.935249,29.876925],"type":"Point"}
}