{
  "type": "Feature",
  "properties": {
    "iso:country":"US",
    "sg:address":"1901 N Akard St",
    "sg:city":"Dallas",
    "sg:classifiers":[
        {
            "category":"Banks & Credit Unions",
            "subcategory":"Investment Brokerage",
            "type":"Services"
        }
    ],
    "sg:phone":"+1 214 969 7088",
    "sg:postcode":"75201",
    "sg:province":"TX",
    "sg:tags":[
        "investing"
    ],
    "wof:name":"Rutland Dickson Asset Management",
    "wof:placetype":"venue"
},
  "geometry": {"coordinates":[-96.80239899999999,32.7868],"type":"Point"}
}