{
  "type": "Feature",
  "properties": {
    "iso:country":"US",
    "sg:address":"1006 Guadalupe St Ofc",
    "sg:city":"Kerrville",
    "sg:classifiers":[
        {
            "category":"Real Estate",
            "subcategory":"Real Estate Services",
            "type":"Services"
        }
    ],
    "sg:phone":"+1 830 895 1722",
    "sg:postcode":"78028",
    "sg:province":"TX",
    "sg:tags":[
        "management",
        "condominium"
    ],
    "wof:name":"Guadalupe River Condominiums",
    "wof:placetype":"venue"
},
  "geometry": {"coordinates":[-99.16623,30.056736],"type":"Point"}
}