{
  "type": "Feature",
  "properties": {
    "iso:country":"US",
    "sg:address":"2401 Fountainview Dr Ste 800",
    "sg:city":"Houston",
    "sg:classifiers":[
        {
            "category":"Professional",
            "subcategory":"Employment Agencies",
            "type":"Services"
        }
    ],
    "sg:phone":"+1 713 952 6760",
    "sg:postcode":"77057",
    "sg:province":"TX",
    "sg:website":"www.executeam.com",
    "wof:name":"ExecuTeam Staffing",
    "wof:placetype":"venue"
},
  "geometry": {"coordinates":[-95.55843299999999,29.753678],"type":"Point"}
}