{
  "type": "Feature",
  "properties": {
    "iso:country":"US",
    "sg:address":"6902 S Highway 35",
    "sg:city":"Alvin",
    "sg:classifiers":[
        {
            "category":"Wholesale",
            "subcategory":"Non-durable Goods",
            "type":"Manufacturing & Wholesale Goods"
        }
    ],
    "sg:phone":"+1 281 331 6320",
    "sg:postcode":"77511",
    "sg:province":"TX",
    "sg:tags":[
        "merchandise-wholesale"
    ],
    "wof:name":"S H Trading",
    "wof:placetype":"venue"
},
  "geometry": {"coordinates":[-95.282183,29.339875],"type":"Point"}
}