{
  "type": "Feature",
  "properties": {
    "iso:country":"US",
    "sg:address":"11123 Shady Trl",
    "sg:city":"Dallas",
    "sg:classifiers":[
        {
            "category":"Wholesale",
            "subcategory":"Painting Supplies",
            "type":"Manufacturing & Wholesale Goods"
        }
    ],
    "sg:phone":"+1 972 484 8120",
    "sg:postcode":"75229",
    "sg:province":"TX",
    "sg:tags":[
        "wallpaper"
    ],
    "sg:website":"www.trikes.com",
    "wof:name":"Tandem Contract Wallcovering",
    "wof:placetype":"venue"
},
  "geometry": {"coordinates":[-96.890522,32.88464],"type":"Point"}
}