{
  "type": "Feature",
  "properties": {
    "iso:country":"US",
    "sg:address":"1406 Hether St",
    "sg:city":"Austin",
    "sg:classifiers":[
        {
            "category":"Real Estate",
            "subcategory":"Surveying",
            "type":"Services"
        }
    ],
    "sg:phone":"+1 512 444 1781",
    "sg:postcode":"78704",
    "sg:province":"TX",
    "sg:tags":[
        "surveyor",
        "land"
    ],
    "wof:name":"Harris Grant Surveying Inc",
    "wof:placetype":"venue"
},
  "geometry": {"coordinates":[-97.76921400000001,30.25056],"type":"Point"}
}