{
  "type": "Feature",
  "properties": {
    "iso:country":"US",
    "sg:address":"18420 Old Hwy 105 W",
    "sg:city":"Montgomery",
    "sg:classifiers":[
        {
            "category":"Real Estate",
            "subcategory":"Real Estate Agent",
            "type":"Services"
        }
    ],
    "sg:phone":"+1 936 582 1700",
    "sg:postcode":"77356",
    "sg:province":"TX",
    "sg:website":"www.topgunsrealty.com",
    "wof:name":"Top Guns Realty On The Lake",
    "wof:placetype":"venue"
},
  "geometry": {"coordinates":[-95.793268,30.345565],"type":"Point"}
}