{
  "type": "Feature",
  "properties": {
    "iso:country":"US",
    "sg:address":"206 S Main St",
    "sg:city":"Muleshoe",
    "sg:classifiers":[
        {
            "category":"Communications",
            "type":"Services"
        },
        {
            "category":"Shopping",
            "subcategory":"Computers & Home Electronics",
            "type":"Retail Goods"
        }
    ],
    "sg:phone":"+1 806 272 3957",
    "sg:postcode":"79347",
    "sg:province":"TX",
    "sg:tags":[
        "sound",
        "television",
        "system",
        "equipment",
        "radio",
        "store"
    ],
    "wof:name":"Advanced Audio Systems",
    "wof:placetype":"venue"
},
  "geometry": {"coordinates":[-102.723662,34.224798],"type":"Point"}
}