{
  "type": "Feature",
  "properties": {
    "iso:country":"US",
    "sg:address":"1621 Enterprise St",
    "sg:city":"Wichita Falls",
    "sg:classifiers":[
        {
            "category":"Restaurant",
            "type":"Food & Drink"
        }
    ],
    "sg:phone":"+1 940 855 2686",
    "sg:postcode":"76306",
    "sg:province":"TX",
    "sg:tags":[
        "eating"
    ],
    "wof:name":"Kelly's Kanteen",
    "wof:placetype":"venue"
},
  "geometry": {"coordinates":[-98.51763,33.960552],"type":"Point"}
}