{
  "type": "Feature",
  "properties": {
    "iso:country":"US",
    "sg:address":"522 N Main St",
    "sg:city":"Mcallen",
    "sg:classifiers":[
        {
            "category":"Professional",
            "subcategory":"Accounting & Tax Preparation",
            "type":"Services"
        }
    ],
    "sg:phone":"+1 956 688 6815",
    "sg:postcode":"78501",
    "sg:province":"TX",
    "wof:name":"Valley Dial A Check Ltd",
    "wof:placetype":"venue"
},
  "geometry": {"coordinates":[-98.233513,26.209135],"type":"Point"}
}