{
  "type": "Feature",
  "properties": {
    "iso:country":"US",
    "sg:address":"900 W Baker Rd",
    "sg:city":"Baytown",
    "sg:classifiers":[
        {
            "category":"Organizations",
            "subcategory":"Religious Organization",
            "type":"Services"
        }
    ],
    "sg:phone":"+1 281 427 0506",
    "sg:postcode":"77521",
    "sg:province":"TX",
    "sg:tags":[
        "church"
    ],
    "sg:website":"www.brbcbaytown.org",
    "wof:name":"Baker Road Baptist Church Inc",
    "wof:placetype":"venue"
},
  "geometry": {"coordinates":[-94.978561,29.76974],"type":"Point"}
}