{
  "type": "Feature",
  "properties": {
    "iso:country":"US",
    "sg:address":"1037 E Erwin St",
    "sg:city":"Tyler",
    "sg:classifiers":[
        {
            "category":"Professional",
            "type":"Services"
        }
    ],
    "sg:phone":"+1 903 596 9985",
    "sg:postcode":"75702",
    "sg:province":"TX",
    "wof:name":"Galaxy Arcade & Pool",
    "wof:placetype":"venue"
},
  "geometry": {"coordinates":[-95.28877300000001,32.351135],"type":"Point"}
}