{
  "type": "Feature",
  "properties": {
    "iso:country":"US",
    "sg:address":"11032 Lakewood Ave",
    "sg:city":"El Paso",
    "sg:classifiers":[
        {
            "category":"Professional",
            "subcategory":"Business Services",
            "type":"Services"
        }
    ],
    "sg:phone":"+1 915 591 2103",
    "sg:postcode":"79935",
    "sg:province":"TX",
    "sg:tags":[
        "broker"
    ],
    "wof:name":"Bussiness Brokerage",
    "wof:placetype":"venue"
},
  "geometry": {"coordinates":[-106.33224800000001,31.764789],"type":"Point"}
}