{
  "type": "Feature",
  "properties": {
    "iso:country":"US",
    "sg:address":"5346 Summit Lodge Dr",
    "sg:city":"Katy",
    "sg:classifiers":[
        {
            "category":"Professional",
            "type":"Services"
        }
    ],
    "sg:phone":"+1 281 856 8388",
    "sg:postcode":"77449",
    "sg:province":"TX",
    "wof:name":"Brays Bayou Nursery",
    "wof:placetype":"venue"
},
  "geometry": {"coordinates":[-95.72381900000001,29.848696],"type":"Point"}
}