{
  "type": "Feature",
  "properties": {
    "iso:country":"US",
    "sg:address":"14118 Cascade Falls Dr",
    "sg:city":"Houston",
    "sg:classifiers":[
        {
            "category":"Insurance",
            "subcategory":"Insurance Agent",
            "type":"Services"
        }
    ],
    "sg:phone":"+1 281 218 0200",
    "sg:postcode":"77062",
    "sg:province":"TX",
    "wof:name":"Allstate Insurance",
    "wof:placetype":"venue"
},
  "geometry": {"coordinates":[-95.13787000000001,29.590879],"type":"Point"}
}