{
  "type": "Feature",
  "properties": {
    "iso:country":"US",
    "sg:address":"600 Gulfgate Center Mall",
    "sg:city":"Houston",
    "sg:classifiers":[
        {
            "category":"Personal",
            "type":"Services"
        },
        {
            "category":"Restaurant",
            "type":"Food & Drink"
        }
    ],
    "sg:phone":"+1 713 645 5660",
    "sg:postcode":"77087",
    "sg:province":"TX",
    "sg:tags":[
        "party",
        "planning",
        "event",
        "pizza"
    ],
    "sg:website":"www.chuckecheese.com",
    "wof:name":"Chuck E Cheese's",
    "wof:placetype":"venue"
},
  "geometry": {"coordinates":[-95.29922000000001,29.697131],"type":"Point"}
}