{
  "type": "Feature",
  "properties": {
    "iso:country":"US",
    "sg:address":"10105 US Hwy 183",
    "sg:city":"Austin",
    "sg:classifiers":[
        {
            "category":"Organizations",
            "subcategory":"Religious Organization",
            "type":"Services"
        }
    ],
    "sg:phone":"+1 512 243 3655",
    "sg:postcode":"78747",
    "sg:province":"TX",
    "sg:tags":[
        "church"
    ],
    "wof:name":"Fountain Living Water Church",
    "wof:placetype":"venue"
},
  "geometry": {"coordinates":[-97.69429599999999,30.101895],"type":"Point"}
}