{
  "type": "Feature",
  "properties": {
    "iso:country":"US",
    "sg:address":"313 Graphite Dr",
    "sg:city":"El Paso",
    "sg:classifiers":[
        {
            "category":"Shopping",
            "subcategory":"Clothing, Apparel, & Fashions",
            "type":"Retail Goods"
        }
    ],
    "sg:phone":"+1 915 587 4336",
    "sg:postcode":"79932",
    "sg:province":"TX",
    "wof:name":"Sonias Fashions",
    "wof:placetype":"venue"
},
  "geometry": {"coordinates":[-106.576036,31.8487],"type":"Point"}
}