{
  "type": "Feature",
  "properties": {
    "iso:country":"US",
    "sg:address":"6222 Richmond Ave",
    "sg:city":"Houston",
    "sg:classifiers":[
        {
            "category":"Banks & Credit Unions",
            "subcategory":"Financial Services",
            "type":"Services"
        }
    ],
    "sg:phone":"+1 713 787 1900",
    "sg:postcode":"77057",
    "sg:province":"TX",
    "sg:tags":[
        "broker",
        "mortgage"
    ],
    "wof:name":"Silver Express Showroom",
    "wof:placetype":"venue"
},
  "geometry": {"coordinates":[-95.490601,29.731899],"type":"Point"}
}