{
  "type": "Feature",
  "properties": {
    "iso:country":"US",
    "sg:address":"2115 Palmer Hwy",
    "sg:city":"Texas City",
    "sg:classifiers":[
        {
            "category":"Bars & Pubs",
            "type":"Food & Drink"
        }
    ],
    "sg:phone":"+1 409 948 1765",
    "sg:postcode":"77590",
    "sg:province":"TX",
    "sg:tags":[
        "drinking",
        "eating"
    ],
    "wof:name":"Alfies Fish N Chips",
    "wof:placetype":"venue"
},
  "geometry": {"coordinates":[-94.92543499999999,29.393209],"type":"Point"}
}