{
  "type": "Feature",
  "properties": {
    "iso:country":"US",
    "sg:address":"900 S Roberts St",
    "sg:city":"Amarillo",
    "sg:classifiers":[
        {
            "category":"Retail",
            "subcategory":"Auto Repair",
            "type":"Services"
        }
    ],
    "sg:phone":"+1 806 373 0692",
    "sg:postcode":"79102",
    "sg:province":"TX",
    "sg:tags":[
        "shop",
        "automotive"
    ],
    "wof:name":"Rogers Truck Repair",
    "wof:placetype":"venue"
},
  "geometry": {"coordinates":[-101.82046800000001,35.201262],"type":"Point"}
}