{
  "type": "Feature",
  "properties": {
    "iso:country":"US",
    "sg:address":"711 Table Rock Dr",
    "sg:city":"Prosper",
    "sg:classifiers":[
        {
            "category":"Sports & Exercise",
            "subcategory":"Bowling",
            "type":"Entertainment"
        }
    ],
    "sg:phone":"+1 972 346 2928",
    "sg:postcode":"75078",
    "sg:province":"TX",
    "wof:name":"Bowling Speech Therapy",
    "wof:placetype":"venue"
},
  "geometry": {"coordinates":[-96.79055700000001,33.246958],"type":"Point"}
}