{
  "type": "Feature",
  "properties": {
    "iso:country":"US",
    "sg:address":"11925 Gateway Blvd W",
    "sg:city":"El Paso",
    "sg:classifiers":[
        {
            "category":"Restaurant",
            "type":"Food & Drink"
        }
    ],
    "sg:menulink":"http://www.allmenus.com/tx/el-paso/95747-furrs/menu/",
    "sg:phone":"+1 915 633 6107",
    "sg:postcode":"79936",
    "sg:province":"TX",
    "sg:tags":[
        "american"
    ],
    "wof:name":"Furr's",
    "wof:placetype":"venue"
},
  "geometry": {"coordinates":[-106.305521,31.721735],"type":"Point"}
}