{
  "type": "Feature",
  "properties": {
    "iso:country":"US",
    "sg:address":"578 Falling Leaves Dr",
    "sg:city":"Duncanville",
    "sg:classifiers":[
        {
            "category":"Retail",
            "subcategory":"Auto Repair",
            "type":"Services"
        }
    ],
    "sg:phone":"+1 972 283 8094",
    "sg:postcode":"75116",
    "sg:province":"TX",
    "sg:tags":[
        "truck"
    ],
    "wof:name":"Redbird Systems",
    "wof:placetype":"venue"
},
  "geometry": {"coordinates":[-96.90079299999999,32.659268],"type":"Point"}
}