{
  "type": "Feature",
  "properties": {
    "iso:country":"US",
    "sg:address":"100 N Edward Gray St",
    "sg:city":"San Marcos",
    "sg:classifiers":[
        {
            "category":"Professional",
            "subcategory":"Accounting & Tax Preparation",
            "type":"Services"
        }
    ],
    "sg:phone":"+1 512 392 1050",
    "sg:postcode":"78666",
    "sg:province":"TX",
    "sg:tags":[
        "bookkeeping",
        "general"
    ],
    "wof:name":"Network Business Svc",
    "wof:placetype":"venue"
},
  "geometry": {"coordinates":[-97.93884199999999,29.88337],"type":"Point"}
}