{
  "type": "Feature",
  "properties": {
    "iso:country":"US",
    "sg:address":"2944 Motley Dr",
    "sg:city":"Mesquite",
    "sg:classifiers":[
        {
            "category":"Shopping",
            "type":"Retail Goods"
        }
    ],
    "sg:phone":"+1 972 682 5999",
    "sg:postcode":"75150",
    "sg:province":"TX",
    "sg:tags":[
        "equipment",
        "medical"
    ],
    "wof:name":"Your Health Services LLC",
    "wof:placetype":"venue"
},
  "geometry": {"coordinates":[-96.648938,32.804827],"type":"Point"}
}