{
  "type": "Feature",
  "properties": {
    "iso:country":"US",
    "sg:address":"6306 Hamman St",
    "sg:city":"Houston",
    "sg:classifiers":[
        {
            "category":"Home & Garden",
            "subcategory":"Furniture",
            "type":"Retail Goods"
        }
    ],
    "sg:phone":"+1 713 868 4472",
    "sg:postcode":"77007",
    "sg:province":"TX",
    "wof:name":"Furniture Manufacturing",
    "wof:placetype":"venue"
},
  "geometry": {"coordinates":[-95.425572,29.776009],"type":"Point"}
}