{
  "type": "Feature",
  "properties": {
    "iso:country":"US",
    "sg:address":"903 Highland Dr",
    "sg:city":"Euless",
    "sg:classifiers":[
        {
            "category":"Building & Trades",
            "subcategory":"Plumbing",
            "type":"Services"
        }
    ],
    "sg:phone":"+1 817 267 9082",
    "sg:postcode":"76040",
    "sg:province":"TX",
    "sg:tags":[
        "lawn",
        "installation",
        "sprinkler"
    ],
    "wof:name":"Parker Irragation",
    "wof:placetype":"venue"
},
  "geometry": {"coordinates":[-97.105695,32.822476],"type":"Point"}
}