{
  "type": "Feature",
  "properties": {
    "iso:country":"US",
    "sg:address":"1125 College St",
    "sg:city":"Belton",
    "sg:classifiers":[
        {
            "category":"Organizations",
            "subcategory":"Religious Organization",
            "type":"Services"
        }
    ],
    "sg:phone":"+1 254 939 0761",
    "sg:postcode":"76513",
    "sg:province":"TX",
    "sg:tags":[
        "church"
    ],
    "sg:website":"www.bellchurches.com",
    "wof:name":"Bell Baptist Assoc",
    "wof:placetype":"venue"
},
  "geometry": {"coordinates":[-97.462214,31.067732],"type":"Point"}
}