{
  "type": "Feature",
  "properties": {
    "iso:country":"US",
    "sg:address":"1635 N Bend Rd",
    "sg:city":"Weatherford",
    "sg:classifiers":[
        {
            "category":"Professional",
            "type":"Services"
        }
    ],
    "sg:phone":"+1 817 599 7884",
    "sg:postcode":"76085",
    "sg:province":"TX",
    "wof:name":"Derrick L Geis",
    "wof:placetype":"venue"
},
  "geometry": {"coordinates":[-97.768636,32.793225],"type":"Point"}
}