{
  "type": "Feature",
  "properties": {
    "iso:country":"US",
    "sg:address":"12216 South Fwy",
    "sg:city":"Burleson",
    "sg:classifiers":[
        {
            "category":"Shopping",
            "subcategory":"Gifts & Souvenirs",
            "type":"Retail Goods"
        }
    ],
    "sg:phone":"+1 817 551 5578",
    "sg:postcode":"76028",
    "sg:province":"TX",
    "wof:name":"Smokin Dragon Gifts",
    "wof:placetype":"venue"
},
  "geometry": {"coordinates":[-97.31905500000001,32.581315],"type":"Point"}
}