{
  "type": "Feature",
  "properties": {
    "iso:country":"US",
    "sg:address":"216 N Ed Carey Dr",
    "sg:city":"Harlingen",
    "sg:classifiers":[
        {
            "category":"Organizations",
            "subcategory":"Community Association",
            "type":"Services"
        }
    ],
    "sg:phone":"+1 956 577 0277",
    "sg:postcode":"78550",
    "sg:province":"TX",
    "sg:tags":[
        "club"
    ],
    "wof:name":"Club Nco",
    "wof:placetype":"venue"
},
  "geometry": {"coordinates":[-97.66305800000001,26.196056],"type":"Point"}
}