{
  "type": "Feature",
  "properties": {
    "iso:country":"US",
    "sg:address":"3403 Barthelome St",
    "sg:city":"Corpus Christi",
    "sg:classifiers":[
        {
            "category":"Shopping",
            "subcategory":"Hobbies, Toys, & Games",
            "type":"Retail Goods"
        }
    ],
    "sg:phone":"+1 361 887 7747",
    "sg:postcode":"78408",
    "sg:province":"TX",
    "wof:name":"Smokestack",
    "wof:placetype":"venue"
},
  "geometry": {"coordinates":[-97.428104,27.796159],"type":"Point"}
}