{
  "type": "Feature",
  "properties": {
    "iso:country":"US",
    "sg:address":"1631 Center St",
    "sg:city":"Deer Park",
    "sg:classifiers":[
        {
            "category":"Shopping",
            "subcategory":"Florist",
            "type":"Retail Goods"
        }
    ],
    "sg:phone":"+1 281 479 1200",
    "sg:postcode":"77536",
    "sg:province":"TX",
    "wof:name":"Deer Country Florist",
    "wof:placetype":"venue"
},
  "geometry": {"coordinates":[-95.12362,29.697234],"type":"Point"}
}