{
  "type": "Feature",
  "properties": {
    "iso:country":"US",
    "sg:address":"228 S Chadbourne St",
    "sg:city":"San Angelo",
    "sg:classifiers":[
        {
            "category":"Banks & Credit Unions",
            "subcategory":"Bank",
            "type":"Services"
        }
    ],
    "sg:phone":"+1 325 655 3432",
    "sg:postcode":"76903",
    "sg:province":"TX",
    "sg:tags":[
        "loan"
    ],
    "wof:name":"San Angelo Finance Co",
    "wof:placetype":"venue"
},
  "geometry": {"coordinates":[-100.435706,31.460338],"type":"Point"}
}