{
  "type": "Feature",
  "properties": {
    "iso:country":"US",
    "sg:address":"8750 N Central Expy",
    "sg:city":"Dallas",
    "sg:classifiers":[
        {
            "category":"Professional",
            "subcategory":"Accounting & Tax Preparation",
            "type":"Services"
        }
    ],
    "sg:phone":"+1 214 265 0808",
    "sg:postcode":"75231",
    "sg:province":"TX",
    "wof:name":"Ross M Jessup",
    "wof:placetype":"venue"
},
  "geometry": {"coordinates":[-96.7697,32.870431],"type":"Point"}
}