{
  "type": "Feature",
  "properties": {
    "iso:country":"US",
    "sg:address":"1033 E 15th St",
    "sg:city":"Plano",
    "sg:classifiers":[
        {
            "category":"Shopping",
            "subcategory":"Clothing, Apparel, & Fashions",
            "type":"Retail Goods"
        }
    ],
    "sg:phone":"+1 972 423 2201",
    "sg:postcode":"75074",
    "sg:province":"TX",
    "sg:tags":[
        "shop",
        "infant",
        "maternity"
    ],
    "wof:name":"New Addition Infant & Children",
    "wof:placetype":"venue"
},
  "geometry": {"coordinates":[-96.69958,33.019769],"type":"Point"}
}