{
  "type": "Feature",
  "properties": {
    "iso:country":"US",
    "sg:address":"1813 W Commerce St",
    "sg:city":"Dallas",
    "sg:classifiers":[
        {
            "category":"Banks & Credit Unions",
            "subcategory":"Investment Brokerage",
            "type":"Services"
        },
        {
            "category":"Professional",
            "subcategory":"Business Services",
            "type":"Services"
        }
    ],
    "sg:phone":"+1 214 742 6949",
    "sg:postcode":"75208",
    "sg:province":"TX",
    "sg:tags":[
        "broker",
        "commodity"
    ],
    "wof:name":"Refinery Castings Co Inc",
    "wof:placetype":"venue"
},
  "geometry": {"coordinates":[-96.84823900000001,32.772653],"type":"Point"}
}