{
  "type": "Feature",
  "properties": {
    "iso:country":"US",
    "sg:address":"892 Helpen Stell Rd",
    "sg:city":"Nacogdoches",
    "sg:classifiers":[
        {
            "category":"Home & Garden",
            "subcategory":"Building Materials",
            "type":"Retail Goods"
        },
        {
            "category":"Shopping",
            "subcategory":"Jewelry",
            "type":"Retail Goods"
        }
    ],
    "sg:phone":"+1 936 564 4990",
    "sg:postcode":"75965",
    "sg:province":"TX",
    "sg:tags":[
        "jeweler"
    ],
    "wof:name":"Sunset River Studio",
    "wof:placetype":"venue"
},
  "geometry": {"coordinates":[-94.66640599999999,31.825525],"type":"Point"}
}