{
  "type": "Feature",
  "properties": {
    "iso:country":"US",
    "sg:address":"11255 Tanner Rd",
    "sg:city":"Houston",
    "sg:classifiers":[
        {
            "category":"Shopping",
            "subcategory":"Gifts & Souvenirs",
            "type":"Retail Goods"
        }
    ],
    "sg:phone":"+1 713 937 3230",
    "sg:postcode":"77041",
    "sg:province":"TX",
    "sg:tags":[
        "shop"
    ],
    "wof:name":"All Precious Gifts",
    "wof:placetype":"venue"
},
  "geometry": {"coordinates":[-95.574496,29.85022],"type":"Point"}
}