{
  "type": "Feature",
  "properties": {
    "iso:country":"US",
    "sg:address":"106 Mesquite Dr",
    "sg:city":"Weatherford",
    "sg:classifiers":[
        {
            "category":"Building & Trades",
            "subcategory":"Equipment Rental",
            "type":"Services"
        }
    ],
    "sg:phone":"+1 817 596 5611",
    "sg:postcode":"76086",
    "sg:province":"TX",
    "wof:name":"Ameritex Rentals Ltd",
    "wof:placetype":"venue"
},
  "geometry": {"coordinates":[-97.773455,32.772361],"type":"Point"}
}