{
  "type": "Feature",
  "properties": {
    "iso:country":"US",
    "sg:address":"2441 E I- 20",
    "sg:city":"Odessa",
    "sg:classifiers":[
        {
            "category":"Retail",
            "subcategory":"Auto Repair",
            "type":"Services"
        }
    ],
    "sg:phone":"+1 432 580 7571",
    "sg:postcode":"79701",
    "sg:province":"TX",
    "sg:tags":[
        "parts",
        "truck"
    ],
    "wof:name":"Bruckner Truck Sales Inc",
    "wof:placetype":"venue"
},
  "geometry": {"coordinates":[-102.04006,31.982456],"type":"Point"}
}