{
  "type": "Feature",
  "properties": {
    "iso:country":"US",
    "sg:address":"3074 Co Rd 855",
    "sg:city":"Alvin",
    "sg:classifiers":[
        {
            "category":"Retail",
            "subcategory":"Auto Repair",
            "type":"Services"
        }
    ],
    "sg:phone":"+1 281 585 0432",
    "sg:postcode":"77511",
    "sg:province":"TX",
    "sg:tags":[
        "glass",
        "replacement"
    ],
    "wof:name":"Mirror & Glass Specialists",
    "wof:placetype":"venue"
},
  "geometry": {"coordinates":[-95.27519599999999,29.471728],"type":"Point"}
}