{
  "type": "Feature",
  "properties": {
    "iso:country":"US",
    "sg:address":"310 Gaslight Blvd",
    "sg:city":"Lufkin",
    "sg:classifiers":[
        {
            "category":"Health Services",
            "subcategory":"Doctor",
            "type":"Services"
        }
    ],
    "sg:phone":"+1 936 632 8787",
    "sg:postcode":"75904",
    "sg:province":"TX",
    "sg:tags":[
        "specialist",
        "surgeon",
        "cardiology",
        "physician"
    ],
    "wof:name":"Heart Institute East Texas P A",
    "wof:placetype":"venue"
},
  "geometry": {"coordinates":[-94.75174800000001,31.331519],"type":"Point"}
}