{
  "type": "Feature",
  "properties": {
    "iso:country":"US",
    "sg:address":"902 W Central Texas Expy",
    "sg:city":"Killeen",
    "sg:classifiers":[
        {
            "category":"Utilities",
            "subcategory":"Mobile Phone",
            "type":"Services"
        }
    ],
    "sg:phone":"+1 254 526 5756",
    "sg:postcode":"76541",
    "sg:province":"TX",
    "sg:tags":[
        "installs",
        "communication",
        "equipment"
    ],
    "wof:name":"Teletouch",
    "wof:placetype":"venue"
},
  "geometry": {"coordinates":[-97.74759299999999,31.108214],"type":"Point"}
}