{
  "type": "Feature",
  "properties": {
    "iso:country":"US",
    "sg:address":"1810 Woodvine Cir",
    "sg:city":"San Antonio",
    "sg:classifiers":[
        {
            "category":"Retail",
            "subcategory":"Portrait Studio",
            "type":"Services"
        }
    ],
    "sg:phone":"+1 210 495 1793",
    "sg:postcode":"78232",
    "sg:province":"TX",
    "sg:tags":[
        "photography"
    ],
    "wof:name":"Photography Cricket",
    "wof:placetype":"venue"
},
  "geometry": {"coordinates":[-98.46249899999999,29.563199],"type":"Point"}
}