{
  "type": "Feature",
  "properties": {
    "iso:country":"US",
    "sg:address":"190 E Ave J",
    "sg:city":"Silsbee",
    "sg:classifiers":[
        {
            "category":"Social Services",
            "type":"Services"
        }
    ],
    "sg:phone":"+1 409 385 0822",
    "sg:postcode":"77656",
    "sg:province":"TX",
    "sg:tags":[
        "organization",
        "child",
        "day",
        "care",
        "welfare"
    ],
    "wof:name":"Jo Ann Fries House",
    "wof:placetype":"venue"
},
  "geometry": {"coordinates":[-94.177706,30.347419],"type":"Point"}
}