{
  "type": "Feature",
  "properties": {
    "iso:country":"US",
    "sg:address":"201 US Highway 77A S",
    "sg:city":"Yoakum",
    "sg:classifiers":[
        {
            "category":"Shopping",
            "subcategory":"Department Store",
            "type":"Retail Goods"
        }
    ],
    "sg:phone":"+1 361 293 5900",
    "sg:postcode":"77995",
    "sg:province":"TX",
    "wof:name":"Duckwall Alco Stores Inc",
    "wof:placetype":"venue"
},
  "geometry": {"coordinates":[-97.156509,29.3018],"type":"Point"}
}