{
  "type": "Feature",
  "properties": {
    "iso:country":"US",
    "sg:address":"19506 Cardiff Park Ln",
    "sg:city":"Houston",
    "sg:classifiers":[
        {
            "category":"Shopping",
            "subcategory":"Florist",
            "type":"Retail Goods"
        }
    ],
    "sg:phone":"+1 281 599 7442",
    "sg:postcode":"77094",
    "sg:province":"TX",
    "wof:name":"Lauras Flowers & Gifts",
    "wof:placetype":"venue"
},
  "geometry": {"coordinates":[-95.708251,29.765834],"type":"Point"}
}