{
  "type": "Feature",
  "properties": {
    "iso:country":"US",
    "sg:address":"4402 Crane St",
    "sg:city":"Houston",
    "sg:classifiers":[
        {
            "category":"Food & Beverages",
            "subcategory":"Groceries & Convenience Stores",
            "type":"Retail Goods"
        }
    ],
    "sg:phone":"+1 713 673 1637",
    "sg:postcode":"77026",
    "sg:province":"TX",
    "wof:name":"Kowloon Super Market",
    "wof:placetype":"venue"
},
  "geometry": {"coordinates":[-95.32405199999999,29.796854],"type":"Point"}
}