{
  "type": "Feature",
  "properties": {
    "iso:country":"US",
    "sg:address":"1034 Baronridge Dr",
    "sg:city":"Seabrook",
    "sg:classifiers":[
        {
            "category":"Social Services",
            "type":"Services"
        }
    ],
    "sg:phone":"+1 281 648 0929",
    "sg:postcode":"77586",
    "sg:province":"TX",
    "sg:tags":[
        "organization",
        "welfare"
    ],
    "wof:name":"League Women Voters Bay Area",
    "wof:placetype":"venue"
},
  "geometry": {"coordinates":[-95.066636,29.579874],"type":"Point"}
}