{
  "type": "Feature",
  "properties": {
    "iso:country":"US",
    "sg:address":"303 County Road 474",
    "sg:city":"Lott",
    "sg:classifiers":[
        {
            "category":"Building & Trades",
            "subcategory":"Landscaping Services",
            "type":"Services"
        }
    ],
    "sg:phone":"+1 254 546 2226",
    "sg:postcode":"76656",
    "sg:province":"TX",
    "sg:tags":[
        "lawn",
        "maintenance"
    ],
    "wof:name":"Bobs Lawn Care",
    "wof:placetype":"venue"
},
  "geometry": {"coordinates":[-97.078783,31.229722],"type":"Point"}
}