{
  "type": "Feature",
  "properties": {
    "iso:country":"US",
    "sg:address":"2817 Lovers Ln",
    "sg:city":"Dallas",
    "sg:classifiers":[
        {
            "category":"Organizations",
            "subcategory":"Community Association",
            "type":"Services"
        }
    ],
    "sg:phone":"+1 214 696 5645",
    "sg:postcode":"75225",
    "sg:province":"TX",
    "wof:name":"Ww & Company",
    "wof:placetype":"venue"
},
  "geometry": {"coordinates":[-96.775459,32.85101],"type":"Point"}
}