{
  "type": "Feature",
  "properties": {
    "iso:country":"US",
    "sg:address":"331 Melrose Dr",
    "sg:city":"Richardson",
    "sg:classifiers":[
        {
            "category":"Professional",
            "subcategory":"Advertising",
            "type":"Services"
        },
        {
            "category":"Professional",
            "subcategory":"Business Services",
            "type":"Services"
        },
        {
            "category":"Wholesale",
            "subcategory":"Books, Periodicals, & Newspapers",
            "type":"Manufacturing & Wholesale Goods"
        }
    ],
    "sg:phone":"+1 972 479 0008",
    "sg:postcode":"75080",
    "sg:province":"TX",
    "sg:tags":[
        "publisher",
        "publishing",
        "specialty",
        "consultant"
    ],
    "wof:name":"Texas Job Connection",
    "wof:placetype":"venue"
},
  "geometry": {"coordinates":[-96.72774200000001,32.969262],"type":"Point"}
}