{
  "type": "Feature",
  "properties": {
    "iso:country":"US",
    "sg:address":"7002 Harry Hines Blvd",
    "sg:city":"Dallas",
    "sg:classifiers":[
        {
            "category":"Travel",
            "subcategory":"Hotels & Motels",
            "type":"Entertainment"
        }
    ],
    "sg:phone":"+1 214 352 4838",
    "sg:postcode":"75235",
    "sg:province":"TX",
    "sg:tags":[
        "lodging"
    ],
    "wof:name":"Colemanor Motel",
    "wof:placetype":"venue"
},
  "geometry": {"coordinates":[-96.854797,32.826302],"type":"Point"}
}