{
  "type": "Feature",
  "properties": {
    "iso:country":"US",
    "sg:address":"4227 Springview Dr",
    "sg:city":"San Antonio",
    "sg:classifiers":[
        {
            "category":"Shopping",
            "subcategory":"Gifts & Souvenirs",
            "type":"Retail Goods"
        }
    ],
    "sg:phone":"+1 210 333 3040",
    "sg:postcode":"78222",
    "sg:province":"TX",
    "wof:name":"3ds Export",
    "wof:placetype":"venue"
},
  "geometry": {"coordinates":[-98.413145,29.378805],"type":"Point"}
}