{
  "type": "Feature",
  "properties": {
    "iso:country":"US",
    "sg:address":"3131 Bell St",
    "sg:city":"Amarillo",
    "sg:classifiers":[
        {
            "category":"Professional",
            "subcategory":"Management & Consulting",
            "type":"Services"
        }
    ],
    "sg:phone":"+1 806 331 0087",
    "sg:postcode":"79106",
    "sg:province":"TX",
    "wof:name":"Seniors Only",
    "wof:placetype":"venue"
},
  "geometry": {"coordinates":[-101.902247,35.181258],"type":"Point"}
}