{
  "type": "Feature",
  "properties": {
    "iso:country":"US",
    "sg:address":"211 York Ave",
    "sg:city":"Weatherford",
    "sg:classifiers":[
        {
            "category":"Professional",
            "type":"Services"
        }
    ],
    "sg:phone":"+1 817 594 4929",
    "sg:postcode":"76086",
    "sg:province":"TX",
    "sg:tags":[
        "establishment"
    ],
    "wof:name":"Miller's Crossing",
    "wof:placetype":"venue"
},
  "geometry": {"coordinates":[-97.798157,32.761414],"type":"Point"}
}