{
  "type": "Feature",
  "properties": {
    "iso:country":"US",
    "sg:address":"5724 New Territory Blvd",
    "sg:city":"Sugar Land",
    "sg:classifiers":[
        {
            "category":"Insurance",
            "subcategory":"Insurance Agent",
            "type":"Services"
        }
    ],
    "sg:phone":"+1 281 565 8000",
    "sg:postcode":"77479",
    "sg:province":"TX",
    "wof:name":"State Farm Insurance",
    "wof:placetype":"venue"
},
  "geometry": {"coordinates":[-95.661466,29.5896],"type":"Point"}
}