{
  "type": "Feature",
  "properties": {
    "iso:country":"US",
    "sg:address":"7846 Albin Ln",
    "sg:city":"Houston",
    "sg:classifiers":[
        {
            "category":"Autos & Motor Vehicles",
            "subcategory":"Automobile Sales",
            "type":"Retail Goods"
        }
    ],
    "sg:phone":"+1 713 777 0190",
    "sg:postcode":"77071",
    "sg:province":"TX",
    "sg:tags":[
        "car",
        "used",
        "dealer"
    ],
    "wof:name":"Big G's Auto Sales",
    "wof:placetype":"venue"
},
  "geometry": {"coordinates":[-95.51532899999999,29.657778],"type":"Point"}
}