{
  "type": "Feature",
  "properties": {
    "iso:country":"US",
    "sg:address":"10356 Ballymote Dr",
    "sg:city":"El Paso",
    "sg:classifiers":[
        {
            "category":"Professional",
            "subcategory":"Accounting & Tax Preparation",
            "type":"Services"
        }
    ],
    "sg:phone":"+1 915 592 9646",
    "sg:postcode":"79925",
    "sg:province":"TX",
    "sg:tags":[
        "bookkeeping",
        "general"
    ],
    "wof:name":"Anderson & Associates",
    "wof:placetype":"venue"
},
  "geometry": {"coordinates":[-106.33639599999999,31.786869],"type":"Point"}
}