{
  "type": "Feature",
  "properties": {
    "iso:country":"US",
    "sg:address":"808 W Moore Ave",
    "sg:city":"Terrell",
    "sg:classifiers":[
        {
            "category":"Restaurant",
            "type":"Food & Drink"
        }
    ],
    "sg:phone":"+1 972 551 2320",
    "sg:postcode":"75160",
    "sg:province":"TX",
    "wof:name":"El Girasol",
    "wof:placetype":"venue"
},
  "geometry": {"coordinates":[-96.28646999999999,32.737516],"type":"Point"}
}