{
  "type": "Feature",
  "properties": {
    "iso:country":"US",
    "sg:address":"131 Casa Loma Cir",
    "sg:city":"Georgetown",
    "sg:classifiers":[
        {
            "category":"Professional",
            "subcategory":"Business Services",
            "type":"Services"
        }
    ],
    "sg:phone":"+1 512 930 0625",
    "sg:postcode":"78633",
    "sg:province":"TX",
    "wof:name":"Barcad",
    "wof:placetype":"venue"
},
  "geometry": {"coordinates":[-97.74132299999999,30.701492],"type":"Point"}
}