{
  "type": "Feature",
  "properties": {
    "iso:country":"US",
    "sg:address":"8804 la Siesta Bnd",
    "sg:city":"Austin",
    "sg:classifiers":[
        {
            "category":"Travel",
            "subcategory":"Travel Agent",
            "type":"Entertainment"
        }
    ],
    "sg:phone":"+1 512 431 6503",
    "sg:postcode":"78749",
    "sg:province":"TX",
    "sg:tags":[
        "agency",
        "services-commercial"
    ],
    "wof:name":"Fantasy Travel",
    "wof:placetype":"venue"
},
  "geometry": {"coordinates":[-97.87957900000001,30.211645],"type":"Point"}
}