{
  "type": "Feature",
  "properties": {
    "iso:country":"US",
    "sg:address":"824 W 10th St",
    "sg:city":"Austin",
    "sg:classifiers":[
        {
            "category":"Professional",
            "subcategory":"Lawyer & Legal Services",
            "type":"Services"
        }
    ],
    "sg:phone":"+1 512 476 4416",
    "sg:postcode":"78701",
    "sg:province":"TX",
    "sg:tags":[
        "attorney"
    ],
    "wof:name":"Thad Son Attorney At Law",
    "wof:placetype":"venue"
},
  "geometry": {"coordinates":[-97.751042,30.274634],"type":"Point"}
}