{
  "type": "Feature",
  "properties": {
    "iso:country":"US",
    "sg:address":"115 Co Rd 305D",
    "sg:city":"Carthage",
    "sg:classifiers":[
        {
            "category":"Wholesale",
            "subcategory":"Machinery & Supplies",
            "type":"Manufacturing & Wholesale Goods"
        }
    ],
    "sg:phone":"+1 903 693 6628",
    "sg:postcode":"75654",
    "sg:province":"TX",
    "sg:tags":[
        "tractor"
    ],
    "wof:name":"Anderson Tractor Sales",
    "wof:placetype":"venue"
},
  "geometry": {"coordinates":[-94.77794900000001,32.121024],"type":"Point"}
}