{
  "type": "Feature",
  "properties": {
    "iso:country":"US",
    "sg:address":"415 S 1st St",
    "sg:city":"Lufkin",
    "sg:classifiers":[
        {
            "category":"Banks & Credit Unions",
            "subcategory":"Investment Brokerage",
            "type":"Services"
        }
    ],
    "sg:phone":"+1 936 639 9638",
    "sg:postcode":"75901",
    "sg:province":"TX",
    "sg:tags":[
        "security"
    ],
    "wof:name":"Texas Mncpl Leag Intrgvrnmntal",
    "wof:placetype":"venue"
},
  "geometry": {"coordinates":[-94.729992,31.33611],"type":"Point"}
}