{
  "type": "Feature",
  "properties": {
    "iso:country":"US",
    "sg:address":"2910 Broadway Blvd",
    "sg:city":"Garland",
    "sg:classifiers":[
        {
            "category":"Health Services",
            "subcategory":"Doctor",
            "type":"Services"
        }
    ],
    "sg:phone":"+1 972 686 1200",
    "sg:postcode":"75041",
    "sg:province":"TX",
    "wof:name":"Robert Max Motley DDS",
    "wof:placetype":"venue"
},
  "geometry": {"coordinates":[-96.62315599999999,32.880209],"type":"Point"}
}