{
  "type": "Feature",
  "properties": {
    "iso:country":"US",
    "sg:address":"511 W Pearl St",
    "sg:city":"Goliad",
    "sg:classifiers":[
        {
            "category":"Personal",
            "subcategory":"Beauty Salon",
            "type":"Services"
        }
    ],
    "sg:phone":"+1 361 645 2600",
    "sg:postcode":"77963",
    "sg:province":"TX",
    "wof:name":"Bobbis Hair Designs",
    "wof:placetype":"venue"
},
  "geometry": {"coordinates":[-97.398056,28.66819],"type":"Point"}
}