{
  "type": "Feature",
  "properties": {
    "iso:country":"US",
    "sg:address":"5501 Avenue S",
    "sg:city":"Galveston",
    "sg:classifiers":[
        {
            "category":"Social Services",
            "subcategory":"Child Care",
            "type":"Services"
        }
    ],
    "sg:phone":"+1 409 744 3162",
    "sg:postcode":"77551",
    "sg:province":"TX",
    "wof:name":"YMCA Prime Time Day Care",
    "wof:placetype":"venue"
},
  "geometry": {"coordinates":[-94.82531,29.277016],"type":"Point"}
}