{
  "type": "Feature",
  "properties": {
    "iso:country":"US",
    "sg:address":"1724 State Hwy 71F Bus",
    "sg:city":"Columbus",
    "sg:classifiers":[
        {
            "category":"Wholesale",
            "subcategory":"Hardware",
            "type":"Manufacturing & Wholesale Goods"
        }
    ],
    "sg:phone":"+1 979 733 9595",
    "sg:postcode":"78934",
    "sg:province":"TX",
    "sg:tags":[
        "plumbing",
        "supply"
    ],
    "wof:name":"Colorado Valley Pipe & Supply",
    "wof:placetype":"venue"
},
  "geometry": {"coordinates":[-96.545497,29.699445],"type":"Point"}
}