{
  "type": "Feature",
  "properties": {
    "iso:country":"US",
    "sg:address":"404 W Main St",
    "sg:city":"Fairfield",
    "sg:classifiers":[
        {
            "category":"Autos & Motor Vehicles",
            "subcategory":"Boat Sales",
            "type":"Retail Goods"
        }
    ],
    "sg:phone":"+1 903 389 5844",
    "sg:postcode":"75840",
    "sg:province":"TX",
    "sg:tags":[
        "dealer",
        "sales"
    ],
    "wof:name":"Whitecapp Marine",
    "wof:placetype":"venue"
},
  "geometry": {"coordinates":[-96.16759500000001,31.726413],"type":"Point"}
}