{
  "type": "Feature",
  "properties": {
    "iso:country":"US",
    "sg:address":"Barton Creek Square Mall 2901 South Capital of Texas Highway",
    "sg:city":"Austin",
    "sg:classifiers":[
        {
            "category":"Personal",
            "subcategory":"Day Spa",
            "type":"Services"
        }
    ],
    "sg:phone":"+1 512 732 2771",
    "sg:postcode":"78746",
    "sg:province":"TX",
    "wof:name":"Relax Day Spa",
    "wof:placetype":"venue"
},
  "geometry": {"coordinates":[-97.810013,30.256213],"type":"Point"}
}