{
  "type": "Feature",
  "properties": {
    "iso:country":"US",
    "sg:address":"25966 US Hwy 281",
    "sg:city":"San Antonio",
    "sg:classifiers":[
        {
            "category":"Retail",
            "subcategory":"Repair Shop",
            "type":"Services"
        }
    ],
    "sg:phone":"+1 830 980 3390",
    "sg:postcode":"78258",
    "sg:province":"TX",
    "wof:name":"Ace Lawn & Garden",
    "wof:placetype":"venue"
},
  "geometry": {"coordinates":[-98.453131,29.687039],"type":"Point"}
}