{
  "type": "Feature",
  "properties": {
    "iso:country":"US",
    "sg:address":"900 E Hall St",
    "sg:city":"Bangs",
    "sg:classifiers":[
        {
            "category":"Ice Cream",
            "type":"Food & Drink"
        }
    ],
    "sg:menulink":"http://www.allmenus.com/tx/bangs/162087-dairy-queen/menu/",
    "sg:phone":"+1 325 752 7007",
    "sg:postcode":"76823",
    "sg:province":"TX",
    "sg:tags":[
        "burger",
        "american"
    ],
    "wof:name":"Dairy Queen",
    "wof:placetype":"venue"
},
  "geometry": {"coordinates":[-99.12353899999999,31.717218],"type":"Point"}
}