{
  "type": "Feature",
  "properties": {
    "iso:country":"US",
    "sg:address":"911 E Mulberry St",
    "sg:city":"Angleton",
    "sg:classifiers":[
        {
            "category":"Restaurant",
            "type":"Food & Drink"
        }
    ],
    "sg:phone":"+1 979 849 4372",
    "sg:postcode":"77515",
    "sg:province":"TX",
    "sg:tags":[
        "eating"
    ],
    "wof:name":"Pizza Hut",
    "wof:placetype":"venue"
},
  "geometry": {"coordinates":[-95.419805,29.167379],"type":"Point"}
}