{
  "type": "Feature",
  "properties": {
    "iso:country":"US",
    "sg:address":"8511 Co Rd 156",
    "sg:city":"Kaufman",
    "sg:classifiers":[
        {
            "category":"Retail",
            "subcategory":"Auto Repair",
            "type":"Services"
        }
    ],
    "sg:phone":"+1 972 962 8787",
    "sg:postcode":"75143",
    "sg:province":"TX",
    "sg:tags":[
        "recreational",
        "vehicle"
    ],
    "wof:name":"Ricks RV Svc",
    "wof:placetype":"venue"
},
  "geometry": {"coordinates":[-96.269882,32.520438],"type":"Point"}
}