{
  "type": "Feature",
  "properties": {
    "iso:country":"US",
    "sg:address":"11283 Newberry Dr",
    "sg:city":"Frisco",
    "sg:classifiers":[
        {
            "category":"Real Estate",
            "subcategory":"Real Estate Operator",
            "type":"Services"
        }
    ],
    "sg:phone":"+1 972 731 0511",
    "sg:postcode":"75035",
    "sg:province":"TX",
    "sg:tags":[
        "building",
        "nonresidential"
    ],
    "wof:name":"D K E Properties L L C",
    "wof:placetype":"venue"
},
  "geometry": {"coordinates":[-96.77885499999999,33.134348],"type":"Point"}
}