{
  "type": "Feature",
  "properties": {
    "iso:country":"US",
    "sg:address":"6501 Ashcroft Dr",
    "sg:city":"Houston",
    "sg:classifiers":[
        {
            "category":"Autos & Motor Vehicles",
            "subcategory":"Automobile Sales",
            "type":"Retail Goods"
        }
    ],
    "sg:phone":"+1 713 773 9546",
    "sg:postcode":"77081",
    "sg:province":"TX",
    "sg:tags":[
        "car",
        "used",
        "dealer"
    ],
    "wof:name":"Caprile's Auto Sales",
    "wof:placetype":"venue"
},
  "geometry": {"coordinates":[-95.490865,29.709679],"type":"Point"}
}