{
  "type": "Feature",
  "properties": {
    "iso:country":"US",
    "sg:address":"1201 N Main St",
    "sg:city":"Liberty",
    "sg:classifiers":[
        {
            "category":"Autos & Motor Vehicles",
            "subcategory":"Auto Supplies",
            "type":"Retail Goods"
        }
    ],
    "sg:phone":"+1 936 336 6423",
    "sg:postcode":"77575",
    "sg:province":"TX",
    "wof:name":"OReilly Auto Parts",
    "wof:placetype":"venue"
},
  "geometry": {"coordinates":[-94.794313,30.067335],"type":"Point"}
}