{
  "type": "Feature",
  "properties": {
    "iso:country":"US",
    "sg:address":"2622 Berkshire Ln",
    "sg:city":"Grand Prairie",
    "sg:classifiers":[
        {
            "category":"Personal",
            "subcategory":"Beauty Salon",
            "type":"Services"
        }
    ],
    "sg:phone":"+1 972 660 5029",
    "sg:postcode":"75052",
    "sg:province":"TX",
    "sg:tags":[
        "shop"
    ],
    "wof:name":"Studio 2 K",
    "wof:placetype":"venue"
},
  "geometry": {"coordinates":[-97.046758,32.666129],"type":"Point"}
}