{
  "type": "Feature",
  "properties": {
    "iso:country":"US",
    "sg:address":"3605 Chenault St",
    "sg:city":"Fort Worth",
    "sg:classifiers":[
        {
            "category":"Freight",
            "type":"Transportation"
        }
    ],
    "sg:phone":"+1 817 831 8046",
    "sg:postcode":"76111",
    "sg:province":"TX",
    "wof:name":"R F Transportation",
    "wof:placetype":"venue"
},
  "geometry": {"coordinates":[-97.29458099999999,32.764306],"type":"Point"}
}