{
  "type": "Feature",
  "properties": {
    "iso:country":"US",
    "sg:address":"4544 Woodside St",
    "sg:city":"Houston",
    "sg:classifiers":[
        {
            "category":"Wholesale",
            "subcategory":"Durable Goods & Equipment",
            "type":"Manufacturing & Wholesale Goods"
        }
    ],
    "sg:phone":"+1 713 923 7976",
    "sg:postcode":"77023",
    "sg:province":"TX",
    "sg:tags":[
        "importer"
    ],
    "wof:name":"Grant Imports",
    "wof:placetype":"venue"
},
  "geometry": {"coordinates":[-95.33183099999999,29.738468],"type":"Point"}
}