{
  "type": "Feature",
  "properties": {
    "iso:country":"US",
    "sg:address":"10515 N Mopac Expwy Suite 125B",
    "sg:city":"Austin",
    "sg:classifiers":[
        {
            "category":"Restaurant",
            "type":"Food & Drink"
        }
    ],
    "sg:phone":"+1 512 345 6060",
    "sg:postcode":"78759",
    "sg:province":"TX",
    "sg:tags":[
        "pizza"
    ],
    "sg:website":"www.redbrickpizza.com",
    "wof:name":"Red Brick Pizza",
    "wof:placetype":"venue"
},
  "geometry": {"coordinates":[-97.73298699999999,30.392245],"type":"Point"}
}