{
  "type": "Feature",
  "properties": {
    "iso:country":"US",
    "sg:address":"500 SW Wilshire Blvd",
    "sg:city":"Burleson",
    "sg:classifiers":[
        {
            "category":"Ice Cream",
            "type":"Food & Drink"
        }
    ],
    "sg:menulink":"http://www.allmenus.com/tx/burleson-joshua/218944-braums-ice-cream--dairy-stores/menu/",
    "sg:phone":"+1 817 295 0095",
    "sg:postcode":"76028",
    "sg:province":"TX",
    "sg:tags":[
        "american"
    ],
    "wof:name":"Braum's Ice Cream & Dairy Stores",
    "wof:placetype":"venue"
},
  "geometry": {"coordinates":[-97.33325499999999,32.538268],"type":"Point"}
}