{
  "type": "Feature",
  "properties": {
    "iso:country":"US",
    "sg:address":"2914 Whitewing Dr",
    "sg:city":"Brownsville",
    "sg:classifiers":[
        {
            "category":"Manufacturing",
            "subcategory":"Tools & Machinery",
            "type":"Manufacturing & Wholesale Goods"
        }
    ],
    "sg:phone":"+1 956 592 2369",
    "sg:postcode":"78521",
    "sg:province":"TX",
    "sg:tags":[
        "water",
        "equipment",
        "treatment",
        "mfg"
    ],
    "wof:name":"Real Quality Solutions",
    "wof:placetype":"venue"
},
  "geometry": {"coordinates":[-97.49775200000001,25.944112],"type":"Point"}
}