{
  "type": "Feature",
  "properties": {
    "iso:country":"US",
    "sg:address":"205 N Star Dr",
    "sg:city":"Victoria",
    "sg:classifiers":[
        {
            "category":"Bars & Pubs",
            "type":"Food & Drink"
        }
    ],
    "sg:phone":"+1 361 572 0606",
    "sg:postcode":"77904",
    "sg:province":"TX",
    "sg:tags":[
        "club",
        "drinking",
        "night"
    ],
    "wof:name":"Dodge City",
    "wof:placetype":"venue"
},
  "geometry": {"coordinates":[-97.004206,28.838525],"type":"Point"}
}