{
  "type": "Feature",
  "properties": {
    "iso:country":"US",
    "sg:address":"103 Erinwood Ct",
    "sg:city":"Spring",
    "sg:classifiers":[
        {
            "category":"Shopping",
            "subcategory":"Clothing, Apparel, & Fashions",
            "type":"Retail Goods"
        }
    ],
    "sg:phone":"+1 281 370 3502",
    "sg:postcode":"77379",
    "sg:province":"TX",
    "wof:name":"Susans Creations",
    "wof:placetype":"venue"
},
  "geometry": {"coordinates":[-95.53601999999999,30.031518],"type":"Point"}
}