{
  "type": "Feature",
  "properties": {
    "iso:country":"US",
    "sg:address":"7001 N 10th St",
    "sg:city":"Mcallen",
    "sg:classifiers":[
        {
            "category":"Freight",
            "type":"Transportation"
        }
    ],
    "sg:phone":"+1 956 683 9837",
    "sg:postcode":"78504",
    "sg:province":"TX",
    "wof:name":"Abanto Forwarding",
    "wof:placetype":"venue"
},
  "geometry": {"coordinates":[-98.219031,26.267978],"type":"Point"}
}