{
  "type": "Feature",
  "properties": {
    "iso:country":"US",
    "sg:address":"711 N 19th St",
    "sg:city":"Copperas Cove",
    "sg:classifiers":[
        {
            "category":"Professional",
            "type":"Services"
        }
    ],
    "sg:phone":"+1 254 542 2810",
    "sg:postcode":"76522",
    "sg:province":"TX",
    "wof:name":"World Reachers",
    "wof:placetype":"venue"
},
  "geometry": {"coordinates":[-97.90761500000001,31.136197],"type":"Point"}
}