{
  "type": "Feature",
  "properties": {
    "iso:country":"US",
    "sg:address":"2505 Yucca Ave",
    "sg:city":"Mcallen",
    "sg:classifiers":[
        {
            "category":"Health Services",
            "subcategory":"Clinic",
            "type":"Services"
        }
    ],
    "sg:phone":"+1 956 618 4879",
    "sg:postcode":"78504",
    "sg:province":"TX",
    "sg:tags":[
        "welfare"
    ],
    "wof:name":"Spa Nail Clinic",
    "wof:placetype":"venue"
},
  "geometry": {"coordinates":[-98.240285,26.25163],"type":"Point"}
}