{
  "type": "Feature",
  "properties": {
    "iso:country":"US",
    "sg:address":"604 E Highland Mall Blvd",
    "sg:city":"Austin",
    "sg:classifiers":[
        {
            "category":"Autos & Motor Vehicles",
            "subcategory":"Boat Sales",
            "type":"Retail Goods"
        }
    ],
    "sg:phone":"+1 512 454 7171",
    "sg:postcode":"78752",
    "sg:province":"TX",
    "sg:tags":[
        "supply",
        "sailboat",
        "accessory",
        "equipment"
    ],
    "wof:name":"Sailboat Shop Inc",
    "wof:placetype":"venue"
},
  "geometry": {"coordinates":[-97.710982,30.328658],"type":"Point"}
}