{
  "type": "Feature",
  "properties": {
    "iso:country":"US",
    "sg:address":"1810 Bell Street",
    "sg:city":"Houston",
    "sg:classifiers":[
        {
            "category":"Travel",
            "subcategory":"Hotels & Motels",
            "type":"Entertainment"
        },
        {
            "category":"Retail",
            "subcategory":"Event Space",
            "type":"Services"
        }
    ],
    "sg:phone":"+1 713 652 9400",
    "sg:postcode":"77003",
    "sg:province":"TX",
    "sg:tags":[
        "venue"
    ],
    "sg:website":"www.holidayinnexpress.com",
    "wof:name":"Holiday Inn Express Hotel & Suites Houston-Dwtn Conv Ctr",
    "wof:placetype":"venue"
},
  "geometry": {"coordinates":[-95.360919,29.748431],"type":"Point"}
}