{
  "type": "Feature",
  "properties": {
    "iso:country":"US",
    "sg:address":"4720 Clinton Dr",
    "sg:city":"Houston",
    "sg:classifiers":[
        {
            "category":"Professional",
            "type":"Services"
        }
    ],
    "sg:phone":"+1 713 975 1111",
    "sg:postcode":"77020",
    "sg:province":"TX",
    "sg:tags":[
        "purchasing"
    ],
    "wof:name":"Houston Procurement & Lgstcs",
    "wof:placetype":"venue"
},
  "geometry": {"coordinates":[-95.32286499999999,29.765516],"type":"Point"}
}