{
  "type": "Feature",
  "properties": {
    "iso:country":"US",
    "sg:address":"2436 Lockhart Ave",
    "sg:city":"Dallas",
    "sg:classifiers":[
        {
            "category":"Retail",
            "subcategory":"Auto Repair",
            "type":"Services"
        }
    ],
    "sg:phone":"+1 214 327 7905",
    "sg:postcode":"75228",
    "sg:province":"TX",
    "sg:tags":[
        "automotive"
    ],
    "wof:name":"Japo Wrecker",
    "wof:placetype":"venue"
},
  "geometry": {"coordinates":[-96.676204,32.820067],"type":"Point"}
}