{
  "type": "Feature",
  "properties": {
    "iso:country":"US",
    "sg:address":"6302 Windcrest Dr",
    "sg:city":"Plano",
    "sg:classifiers":[
        {
            "category":"Shopping",
            "subcategory":"Beauty & Cosmetics",
            "type":"Retail Goods"
        }
    ],
    "sg:phone":"+1 972 403 0860",
    "sg:postcode":"75024",
    "sg:province":"TX",
    "sg:tags":[
        "merchandise"
    ],
    "wof:name":"Susie Gray Cosmetics",
    "wof:placetype":"venue"
},
  "geometry": {"coordinates":[-96.805049,33.060572],"type":"Point"}
}