{
  "type": "Feature",
  "properties": {
    "iso:country":"US",
    "sg:address":"1700 Campbell Ave",
    "sg:city":"Jourdanton",
    "sg:classifiers":[
        {
            "category":"Organizations",
            "subcategory":"Religious Organization",
            "type":"Services"
        }
    ],
    "sg:phone":"+1 830 769 3687",
    "sg:postcode":"78026",
    "sg:province":"TX",
    "sg:tags":[
        "church"
    ],
    "wof:name":"St Matthew's Catholic Church",
    "wof:placetype":"venue"
},
  "geometry": {"coordinates":[-98.54732799999999,28.921478],"type":"Point"}
}