{
  "type": "Feature",
  "properties": {
    "iso:country":"US",
    "sg:address":"905 Palo Pinto St",
    "sg:city":"Weatherford",
    "sg:classifiers":[
        {
            "category":"Communications",
            "type":"Services"
        }
    ],
    "sg:phone":"+1 817 594 8767",
    "sg:postcode":"76086",
    "sg:province":"TX",
    "wof:name":"Communication Sales & Svc Inc",
    "wof:placetype":"venue"
},
  "geometry": {"coordinates":[-97.809634,32.758772],"type":"Point"}
}