{
  "type": "Feature",
  "properties": {
    "iso:country":"US",
    "sg:address":"9854 Harwin Dr",
    "sg:city":"Houston",
    "sg:classifiers":[
        {
            "category":"Shopping",
            "subcategory":"Gifts & Souvenirs",
            "type":"Retail Goods"
        }
    ],
    "sg:phone":"+1 713 953 0708",
    "sg:postcode":"77036",
    "sg:province":"TX",
    "sg:tags":[
        "shop"
    ],
    "wof:name":"Gift Center The",
    "wof:placetype":"venue"
},
  "geometry": {"coordinates":[-95.536464,29.717812],"type":"Point"}
}