{
  "type": "Feature",
  "properties": {
    "iso:country":"US",
    "sg:address":"1145 14th St",
    "sg:city":"Plano",
    "sg:classifiers":[
        {
            "category":"Mining & Drilling",
            "type":"Manufacturing & Wholesale Goods"
        }
    ],
    "sg:phone":"+1 469 241 9830",
    "sg:postcode":"75074",
    "sg:province":"TX",
    "sg:tags":[
        "development",
        "gas",
        "oil",
        "exploration"
    ],
    "wof:name":"SJS Resources LLC",
    "wof:placetype":"venue"
},
  "geometry": {"coordinates":[-96.69838799999999,33.018474],"type":"Point"}
}