{
  "type": "Feature",
  "properties": {
    "iso:country":"US",
    "sg:address":"3608 E 29th St",
    "sg:city":"Bryan",
    "sg:classifiers":[
        {
            "category":"Banks & Credit Unions",
            "subcategory":"Bank",
            "type":"Services"
        }
    ],
    "sg:phone":"+1 979 846 6828",
    "sg:postcode":"77802",
    "sg:province":"TX",
    "sg:tags":[
        "loan"
    ],
    "wof:name":"American General Auto Finance",
    "wof:placetype":"venue"
},
  "geometry": {"coordinates":[-96.33480299999999,30.649877],"type":"Point"}
}