{
  "type": "Feature",
  "properties": {
    "iso:country":"US",
    "sg:address":"1121 Yellow Jacket Ln",
    "sg:city":"Rockwall",
    "sg:classifiers":[
        {
            "category":"Professional",
            "type":"Services"
        }
    ],
    "sg:phone":"+1 972 771 2946",
    "sg:postcode":"75087",
    "sg:province":"TX",
    "wof:name":"Andy Kolori Century 21",
    "wof:placetype":"venue"
},
  "geometry": {"coordinates":[-96.458415,32.907169],"type":"Point"}
}