{
  "type": "Feature",
  "properties": {
    "iso:country":"US",
    "sg:address":"5002 Garth Rd",
    "sg:city":"Baytown",
    "sg:classifiers":[
        {
            "category":"Home & Garden",
            "subcategory":"Building Materials",
            "type":"Retail Goods"
        }
    ],
    "sg:phone":"+1 281 421 3180",
    "sg:postcode":"77521",
    "sg:province":"TX",
    "sg:tags":[
        "center",
        "improvement"
    ],
    "sg:website":"http://www.lowes.com",
    "wof:name":"Lowe's",
    "wof:placetype":"venue"
},
  "geometry": {"coordinates":[-94.977667,29.778004],"type":"Point"}
}