{
  "type": "Feature",
  "properties": {
    "iso:country":"US",
    "sg:address":"900 S Preston Rd",
    "sg:city":"Prosper",
    "sg:classifiers":[
        {
            "category":"Banks & Credit Unions",
            "subcategory":"Bank",
            "type":"Services"
        }
    ],
    "sg:phone":"+1 972 548 3400",
    "sg:postcode":"75078",
    "sg:province":"TX",
    "wof:name":"First State Bank Of Prosper",
    "wof:placetype":"venue"
},
  "geometry": {"coordinates":[-96.78971300000001,33.236101],"type":"Point"}
}