{
  "type": "Feature",
  "properties": {
    "iso:country":"US",
    "sg:address":"3106 Catalina Dr",
    "sg:city":"Austin",
    "sg:classifiers":[
        {
            "category":"Personal",
            "type":"Services"
        }
    ],
    "sg:phone":"+1 512 693 7387",
    "sg:postcode":"78741",
    "sg:province":"TX",
    "wof:name":"Apple A Day Personal Pet Care",
    "wof:placetype":"venue"
},
  "geometry": {"coordinates":[-97.737482,30.221155],"type":"Point"}
}