{
  "type": "Feature",
  "properties": {
    "iso:country":"US",
    "sg:address":"2302 Farnswood Cir",
    "sg:city":"Austin",
    "sg:classifiers":[
        {
            "category":"Manufacturing",
            "subcategory":"Glass & Minerals",
            "type":"Manufacturing & Wholesale Goods"
        }
    ],
    "sg:phone":"+1 512 442 1246",
    "sg:postcode":"78704",
    "sg:province":"TX",
    "sg:tags":[
        "glass-wholesale",
        "shape",
        "circle",
        "special",
        "manufacturer"
    ],
    "wof:name":"Kimberley Glass",
    "wof:placetype":"venue"
},
  "geometry": {"coordinates":[-97.79083,30.251718],"type":"Point"}
}