{
  "type": "Feature",
  "properties": {
    "iso:country":"US",
    "sg:address":"106 Rosehurst St",
    "sg:city":"Bridge City",
    "sg:classifiers":[
        {
            "category":"Professional",
            "type":"Services"
        }
    ],
    "sg:phone":"+1 409 735 9275",
    "sg:postcode":"77611",
    "sg:province":"TX",
    "wof:name":"Steven L Holland",
    "wof:placetype":"venue"
},
  "geometry": {"coordinates":[-93.85471699999999,30.04177],"type":"Point"}
}