{
  "type": "Feature",
  "properties": {
    "iso:country":"US",
    "sg:address":"5701 US Hwy 277 S",
    "sg:city":"Abilene",
    "sg:classifiers":[
        {
            "category":"Retail",
            "subcategory":"Funeral Services",
            "type":"Services"
        }
    ],
    "sg:phone":"+1 325 677 4355",
    "sg:postcode":"79606",
    "sg:province":"TX",
    "sg:tags":[
        "director"
    ],
    "wof:name":"Elliott-Hamil Funeral Homes",
    "wof:placetype":"venue"
},
  "geometry": {"coordinates":[-99.801655,32.40989],"type":"Point"}
}