{
  "type": "Feature",
  "properties": {
    "iso:country":"US",
    "sg:address":"14505 Torrey Chase Blvd",
    "sg:city":"Houston",
    "sg:classifiers":[
        {
            "category":"Banks & Credit Unions",
            "subcategory":"Investment Brokerage",
            "type":"Services"
        }
    ],
    "sg:phone":"+1 281 880 7200",
    "sg:postcode":"77014",
    "sg:province":"TX",
    "sg:tags":[
        "advisory",
        "financial"
    ],
    "wof:name":"Managed Financial Svc Corp Inc",
    "wof:placetype":"venue"
},
  "geometry": {"coordinates":[-95.49245999999999,29.986288],"type":"Point"}
}