{
  "type": "Feature",
  "properties": {
    "iso:country":"US",
    "sg:address":"2700 Woodland Park Dr",
    "sg:city":"Houston",
    "sg:classifiers":[
        {
            "category":"Professional",
            "type":"Services"
        }
    ],
    "sg:phone":"+1 281 531 7159",
    "sg:postcode":"77082",
    "sg:province":"TX",
    "wof:name":"Robinson Superior",
    "wof:placetype":"venue"
},
  "geometry": {"coordinates":[-95.58062200000001,29.73425],"type":"Point"}
}