{
  "type": "Feature",
  "properties": {
    "iso:country":"US",
    "sg:address":"1543 W Summit Ave",
    "sg:city":"San Antonio",
    "sg:classifiers":[
        {
            "category":"Banks & Credit Unions",
            "subcategory":"Bank",
            "type":"Services"
        }
    ],
    "sg:phone":"+1 210 731 0154",
    "sg:postcode":"78201",
    "sg:province":"TX",
    "sg:tags":[
        "loan",
        "real estate"
    ],
    "wof:name":"Rhino Mortgage",
    "wof:placetype":"venue"
},
  "geometry": {"coordinates":[-98.519153,29.45919],"type":"Point"}
}