{
  "type": "Feature",
  "properties": {
    "iso:country":"US",
    "sg:address":"104 Rothrock Dr",
    "sg:city":"Longview",
    "sg:classifiers":[
        {
            "category":"Retail",
            "subcategory":"Repair Shop",
            "type":"Services"
        }
    ],
    "sg:phone":"+1 903 753 0146",
    "sg:postcode":"75602",
    "sg:province":"TX",
    "sg:tags":[
        "satellite",
        "system"
    ],
    "wof:name":"Comm Craft Inc",
    "wof:placetype":"venue"
},
  "geometry": {"coordinates":[-94.715058,32.496717],"type":"Point"}
}