{
  "type": "Feature",
  "properties": {
    "iso:country":"US",
    "sg:address":"11149 Research Boulevard",
    "sg:city":"Austin",
    "sg:classifiers":[
        {
            "category":"Professional",
            "subcategory":"Employment Agencies",
            "type":"Services"
        }
    ],
    "sg:phone":"+1 512 795 8950",
    "sg:postcode":"78759",
    "sg:province":"TX",
    "wof:name":"Appleone Employment Services",
    "wof:placetype":"venue"
},
  "geometry": {"coordinates":[-97.744818,30.40634],"type":"Point"}
}