{
  "type": "Feature",
  "properties": {
    "iso:country":"US",
    "sg:address":"120 School Rd",
    "sg:city":"Lavon",
    "sg:classifiers":[
        {
            "category":"Government",
            "subcategory":"Office",
            "type":"Public Place"
        }
    ],
    "sg:phone":"+1 972 843 4220",
    "sg:postcode":"75166",
    "sg:province":"TX",
    "sg:tags":[
        "city"
    ],
    "wof:name":"Lavon City Hall",
    "wof:placetype":"venue"
},
  "geometry": {"coordinates":[-96.433635,33.0263],"type":"Point"}
}