{
  "type": "Feature",
  "properties": {
    "iso:country":"US",
    "sg:address":"1107 Shepherd Dr",
    "sg:city":"Houston",
    "sg:classifiers":[
        {
            "category":"Organizations",
            "subcategory":"Religious Organization",
            "type":"Services"
        }
    ],
    "sg:phone":"+1 713 861 6670",
    "sg:postcode":"77007",
    "sg:province":"TX",
    "wof:name":"Bethel United Church Of Christ",
    "wof:placetype":"venue"
},
  "geometry": {"coordinates":[-95.40956799999999,29.771893],"type":"Point"}
}