{
  "type": "Feature",
  "properties": {
    "iso:country":"US",
    "sg:address":"140 S Ave B",
    "sg:city":"Albany",
    "sg:classifiers":[
        {
            "category":"Organizations",
            "subcategory":"Religious Organization",
            "type":"Services"
        }
    ],
    "sg:phone":"+1 325 762 2833",
    "sg:postcode":"76430",
    "sg:province":"TX",
    "sg:tags":[
        "church"
    ],
    "wof:name":"Trinity Episcopal Church",
    "wof:placetype":"venue"
},
  "geometry": {"coordinates":[-99.301821,32.724442],"type":"Point"}
}