{
  "type": "Feature",
  "properties": {
    "iso:country":"US",
    "sg:address":"9311 Co Rd 35",
    "sg:city":"Tyler",
    "sg:classifiers":[
        {
            "category":"Building & Trades",
            "subcategory":"Landscaping Services",
            "type":"Services"
        }
    ],
    "sg:phone":"+1 903 597 2118",
    "sg:postcode":"75706",
    "sg:province":"TX",
    "wof:name":"Weems Tree Service LLC",
    "wof:placetype":"venue"
},
  "geometry": {"coordinates":[-95.299504,32.403813],"type":"Point"}
}