{
  "type": "Feature",
  "properties": {
    "iso:country":"US",
    "sg:address":"2515 South Loop W",
    "sg:city":"Houston",
    "sg:classifiers":[
        {
            "category":"Restaurant",
            "type":"Food & Drink"
        }
    ],
    "sg:phone":"+1 713 668 5756",
    "sg:postcode":"77054",
    "sg:province":"TX",
    "sg:tags":[
        "tex-mex"
    ],
    "sg:website":"pappasitos.com",
    "wof:name":"Pappasito's Cantina",
    "wof:placetype":"venue"
},
  "geometry": {"coordinates":[-95.415457,29.676731],"type":"Point"}
}