{
  "type": "Feature",
  "properties": {
    "iso:country":"US",
    "sg:address":"3816 S Lamar Blvd",
    "sg:city":"Austin",
    "sg:classifiers":[
        {
            "category":"Food & Beverages",
            "subcategory":"Bakery",
            "type":"Retail Goods"
        },
        {
            "category":"Wholesale",
            "subcategory":"Groceries",
            "type":"Manufacturing & Wholesale Goods"
        }
    ],
    "sg:phone":"+1 512 734 0978",
    "sg:postcode":"78704",
    "sg:province":"TX",
    "sg:tags":[
        "cooky",
        "crackers-wholesale",
        "bakers-wholesale",
        "manufacturer"
    ],
    "wof:name":"Masterbaker Adult Novelty Cookies",
    "wof:placetype":"venue"
},
  "geometry": {"coordinates":[-97.78930699999999,30.238661],"type":"Point"}
}