{
  "type": "Feature",
  "properties": {
    "iso:country":"US",
    "sg:address":"203 Ravenwood St",
    "sg:city":"Henderson",
    "sg:classifiers":[
        {
            "category":"Utilities",
            "subcategory":"Telephone",
            "type":"Services"
        }
    ],
    "sg:phone":"+1 903 657 2917",
    "sg:postcode":"75654",
    "sg:province":"TX",
    "sg:tags":[
        "communications"
    ],
    "wof:name":"John M Mellon",
    "wof:placetype":"venue"
},
  "geometry": {"coordinates":[-94.82749200000001,32.148879],"type":"Point"}
}