{
  "type": "Feature",
  "properties": {
    "iso:country":"US",
    "sg:address":"3519 Timber Dr",
    "sg:city":"Amarillo",
    "sg:classifiers":[
        {
            "category":"Shopping",
            "type":"Retail Goods"
        }
    ],
    "sg:phone":"+1 806 463 7676",
    "sg:postcode":"79121",
    "sg:province":"TX",
    "sg:tags":[
        "merchandise"
    ],
    "wof:name":"Marble Depot Inc",
    "wof:placetype":"venue"
},
  "geometry": {"coordinates":[-101.92608199999999,35.174264],"type":"Point"}
}