{
  "type": "Feature",
  "properties": {
    "iso:country":"US",
    "sg:address":"2325 Kildeer Trl",
    "sg:city":"Grand Prairie",
    "sg:classifiers":[
        {
            "category":"Social Services",
            "type":"Services"
        }
    ],
    "sg:phone":"+1 972 606 1741",
    "sg:postcode":"75052",
    "sg:province":"TX",
    "wof:name":"David W Denbow",
    "wof:placetype":"venue"
},
  "geometry": {"coordinates":[-97.036845,32.692968],"type":"Point"}
}