{
  "type": "Feature",
  "properties": {
    "iso:country":"US",
    "sg:address":"11611 Bissonnet St",
    "sg:city":"Houston",
    "sg:classifiers":[
        {
            "category":"Retail",
            "subcategory":"Auto Repair",
            "type":"Services"
        }
    ],
    "sg:phone":"+1 281 933 6262",
    "sg:postcode":"77099",
    "sg:province":"TX",
    "sg:tags":[
        "repairing",
        "automobile"
    ],
    "wof:name":"B T Professional Japanese Car",
    "wof:placetype":"venue"
},
  "geometry": {"coordinates":[-95.583339,29.674926],"type":"Point"}
}