{
  "type": "Feature",
  "properties": {
    "iso:country":"US",
    "sg:address":"1819 Birnam Glen Dr",
    "sg:city":"Sugar Land",
    "sg:classifiers":[
        {
            "category":"Manufacturing",
            "subcategory":"Motor Vehicles & Parts",
            "type":"Manufacturing & Wholesale Goods"
        }
    ],
    "sg:phone":"+1 281 937 0414",
    "sg:postcode":"77479",
    "sg:province":"TX",
    "sg:tags":[
        "mfg",
        "trimming"
    ],
    "wof:name":"Mums For All",
    "wof:placetype":"venue"
},
  "geometry": {"coordinates":[-95.675409,29.562167],"type":"Point"}
}