{
  "type": "Feature",
  "properties": {
    "iso:country":"US",
    "sg:address":"11030 Kingspoint Rd",
    "sg:city":"Houston",
    "sg:classifiers":[
        {
            "category":"Personal",
            "subcategory":"Beauty Salon",
            "type":"Services"
        }
    ],
    "sg:phone":"+1 713 941 4247",
    "sg:postcode":"77075",
    "sg:province":"TX",
    "sg:tags":[
        "shop",
        "school"
    ],
    "wof:name":"American Career Institute",
    "wof:placetype":"venue"
},
  "geometry": {"coordinates":[-95.223597,29.620331],"type":"Point"}
}