{
  "type": "Feature",
  "properties": {
    "iso:country":"US",
    "sg:address":"1201 W 6th St Ste F",
    "sg:city":"Austin",
    "sg:classifiers":[
        {
            "category":"Communications",
            "type":"Services"
        }
    ],
    "sg:phone":"+1 512 436 8586",
    "sg:postcode":"78703",
    "sg:province":"TX",
    "sg:tags":[
        "web",
        "design"
    ],
    "sg:website":"www.dbinteractive.com",
    "wof:name":"DB Interactive, Inc",
    "wof:placetype":"venue"
},
  "geometry": {"coordinates":[-97.757852,30.27274],"type":"Point"}
}