{
  "type": "Feature",
  "properties": {
    "iso:country":"US",
    "sg:address":"2 Shadow Ln",
    "sg:city":"Bay City",
    "sg:classifiers":[
        {
            "category":"Wholesale",
            "subcategory":"Electrical",
            "type":"Manufacturing & Wholesale Goods"
        }
    ],
    "sg:phone":"+1 979 244 4920",
    "sg:postcode":"77414",
    "sg:province":"TX",
    "sg:tags":[
        "alarm",
        "burglar",
        "system"
    ],
    "sg:website":"www.bugsweep.com",
    "wof:name":"Communications Security Inc",
    "wof:placetype":"venue"
},
  "geometry": {"coordinates":[-95.95915100000001,28.96876],"type":"Point"}
}