{
  "type": "Feature",
  "properties": {
    "iso:country":"US",
    "sg:address":"1224 Shaver St",
    "sg:city":"Pasadena",
    "sg:classifiers":[
        {
            "category":"Banks & Credit Unions",
            "subcategory":"Bank",
            "type":"Services"
        }
    ],
    "sg:phone":"+1 713 475 9400",
    "sg:postcode":"77506",
    "sg:province":"TX",
    "sg:tags":[
        "personal",
        "broker",
        "mortgage",
        "institution"
    ],
    "sg:website":"www.lsfacsh.com",
    "wof:name":"Lone Star Finance",
    "wof:placetype":"venue"
},
  "geometry": {"coordinates":[-95.211502,29.692101],"type":"Point"}
}