{
  "type": "Feature",
  "properties": {
    "iso:country":"US",
    "sg:address":"20202 Highway 59 N",
    "sg:city":"Humble",
    "sg:classifiers":[
        {
            "category":"Banks & Credit Unions",
            "subcategory":"Financial Services",
            "type":"Services"
        },
        {
            "category":"Professional",
            "subcategory":"Credit Reporting & Collection",
            "type":"Services"
        }
    ],
    "sg:phone":"+1 281 540 7500",
    "sg:postcode":"77338",
    "sg:province":"TX",
    "sg:tags":[
        "debt",
        "adjuster",
        "agency"
    ],
    "wof:name":"Deerwood M S O Lp",
    "wof:placetype":"venue"
},
  "geometry": {"coordinates":[-95.26563299999999,30.008956],"type":"Point"}
}