{
  "type": "Feature",
  "properties": {
    "iso:country":"US",
    "sg:address":"7211 Regency Square Blvd",
    "sg:city":"Houston",
    "sg:classifiers":[
        {
            "category":"Professional",
            "subcategory":"Detective & Security Services",
            "type":"Services"
        }
    ],
    "sg:phone":"+1 713 789 4450",
    "sg:postcode":"77036",
    "sg:province":"TX",
    "sg:tags":[
        "investigator"
    ],
    "wof:name":"Carco Group Inc",
    "wof:placetype":"venue"
},
  "geometry": {"coordinates":[-95.50958300000001,29.715601],"type":"Point"}
}