{
  "type": "Feature",
  "properties": {
    "iso:country":"US",
    "sg:address":"114 S Austin St",
    "sg:city":"Seguin",
    "sg:classifiers":[
        {
            "category":"Restaurant",
            "type":"Food & Drink"
        }
    ],
    "sg:phone":"+1 830 386 2900",
    "sg:postcode":"78155",
    "sg:province":"TX",
    "sg:tags":[
        "eating"
    ],
    "wof:name":"Central Park Java",
    "wof:placetype":"venue"
},
  "geometry": {"coordinates":[-97.964681,29.568267],"type":"Point"}
}