{
  "type": "Feature",
  "properties": {
    "iso:country":"US",
    "sg:address":"430 Indian Hills Trl",
    "sg:city":"Kyle",
    "sg:classifiers":[
        {
            "category":"Retail",
            "subcategory":"Animal Services",
            "type":"Services"
        }
    ],
    "sg:phone":"+1 512 262 1210",
    "sg:postcode":"78640",
    "sg:province":"TX",
    "wof:name":"Janosek Horse Farm",
    "wof:placetype":"venue"
},
  "geometry": {"coordinates":[-97.933446,30.032876],"type":"Point"}
}