{
  "type": "Feature",
  "properties": {
    "iso:country":"US",
    "sg:address":"19710 Northwest Fwy",
    "sg:city":"Houston",
    "sg:classifiers":[
        {
            "category":"Fast Food",
            "type":"Food & Drink"
        },
        {
            "category":"Restaurant",
            "type":"Food & Drink"
        },
        {
            "category":"Bakery",
            "type":"Food & Drink"
        },
        {
            "category":"Professional",
            "type":"Services"
        }
    ],
    "sg:phone":"+1 281 720 1000",
    "sg:postcode":"77065",
    "sg:province":"TX",
    "sg:tags":[
        "wedding",
        "french",
        "lunch",
        "pastry",
        "caterer",
        "cake",
        "brunch",
        "breakfast",
        "take"
    ],
    "wof:name":"la Madeleine",
    "wof:placetype":"venue"
},
  "geometry": {"coordinates":[-95.612765,29.912382],"type":"Point"}
}