{
  "type": "Feature",
  "properties": {
    "iso:country":"US",
    "sg:address":"3101 S 14th St",
    "sg:city":"Abilene",
    "sg:classifiers":[
        {
            "category":"Retail",
            "subcategory":"Repair Shop",
            "type":"Services"
        },
        {
            "category":"Shopping",
            "type":"Retail Goods"
        }
    ],
    "sg:phone":"+1 325 692 3775",
    "sg:postcode":"79605",
    "sg:province":"TX",
    "sg:tags":[
        "picture",
        "frame"
    ],
    "wof:name":"Surroundings Art Gallery-Frame",
    "wof:placetype":"venue"
},
  "geometry": {"coordinates":[-99.760474,32.432229],"type":"Point"}
}