{
  "type": "Feature",
  "properties": {
    "iso:country":"US",
    "sg:address":"511 Early Blvd",
    "sg:city":"Brownwood",
    "sg:classifiers":[
        {
            "category":"Insurance",
            "subcategory":"Insurance Agent",
            "type":"Services"
        }
    ],
    "sg:phone":"+1 325 641 0366",
    "sg:postcode":"76802",
    "sg:province":"TX",
    "wof:name":"Texas Insurance Proc System",
    "wof:placetype":"venue"
},
  "geometry": {"coordinates":[-98.955975,31.738019],"type":"Point"}
}