{
  "type": "Feature",
  "properties": {
    "iso:country":"US",
    "sg:address":"1436 Kingsmill Ct",
    "sg:city":"Coppell",
    "sg:classifiers":[
        {
            "category":"Organizations",
            "subcategory":"Membership Organization",
            "type":"Services"
        }
    ],
    "sg:phone":"+1 214 350 8477",
    "sg:postcode":"75019",
    "sg:province":"TX",
    "sg:tags":[
        "youth"
    ],
    "wof:name":"Continental Societies Inc",
    "wof:placetype":"venue"
},
  "geometry": {"coordinates":[-96.94771799999999,32.959995],"type":"Point"}
}