{
  "type": "Feature",
  "properties": {
    "iso:country":"US",
    "sg:address":"2009 Industrial Blvd",
    "sg:city":"Abilene",
    "sg:classifiers":[
        {
            "category":"Autos & Motor Vehicles",
            "subcategory":"Auto Supplies",
            "type":"Retail Goods"
        }
    ],
    "sg:phone":"+1 325 691 9770",
    "sg:postcode":"79602",
    "sg:province":"TX",
    "wof:name":"Truck Accessories Discount Out",
    "wof:placetype":"venue"
},
  "geometry": {"coordinates":[-99.748648,32.4013],"type":"Point"}
}