{
  "type": "Feature",
  "properties": {
    "iso:country":"US",
    "sg:address":"1002 E Columbia St",
    "sg:city":"Weatherford",
    "sg:classifiers":[
        {
            "category":"Wholesale",
            "subcategory":"Groceries",
            "type":"Manufacturing & Wholesale Goods"
        }
    ],
    "sg:phone":"+1 817 594 5438",
    "sg:postcode":"76086",
    "sg:province":"TX",
    "sg:tags":[
        "grocer"
    ],
    "wof:name":"C D Hartnett Co",
    "wof:placetype":"venue"
},
  "geometry": {"coordinates":[-97.780162,32.755611],"type":"Point"}
}