{
  "type": "Feature",
  "properties": {
    "iso:country":"US",
    "sg:address":"1830 Range Dr",
    "sg:city":"Mesquite",
    "sg:classifiers":[
        {
            "category":"Shopping",
            "subcategory":"Gifts & Souvenirs",
            "type":"Retail Goods"
        }
    ],
    "sg:phone":"+1 972 285 2002",
    "sg:postcode":"75149",
    "sg:province":"TX",
    "sg:tags":[
        "shop"
    ],
    "wof:name":"Rusty Barn",
    "wof:placetype":"venue"
},
  "geometry": {"coordinates":[-96.59771600000001,32.786939],"type":"Point"}
}