{
  "type": "Feature",
  "properties": {
    "iso:country":"US",
    "sg:address":"534 Bandera Rd",
    "sg:city":"San Antonio",
    "sg:classifiers":[
        {
            "category":"Home & Garden",
            "subcategory":"Building Materials",
            "type":"Retail Goods"
        }
    ],
    "sg:phone":"+1 210 734 2454",
    "sg:postcode":"78228",
    "sg:province":"TX",
    "wof:name":"Rays Installation Service & S",
    "wof:placetype":"venue"
},
  "geometry": {"coordinates":[-98.54918499999999,29.452859],"type":"Point"}
}