{
  "type": "Feature",
  "properties": {
    "iso:country":"US",
    "sg:address":"1584 Walker Rd",
    "sg:city":"Huntington",
    "sg:classifiers":[
        {
            "category":"Building & Trades",
            "subcategory":"Construction",
            "type":"Services"
        }
    ],
    "sg:phone":"+1 936 422 4009",
    "sg:postcode":"75949",
    "sg:province":"TX",
    "sg:tags":[
        "steel",
        "erection",
        "structural"
    ],
    "wof:name":"Phillips Steel Erectors",
    "wof:placetype":"venue"
},
  "geometry": {"coordinates":[-94.57304999999999,31.229247],"type":"Point"}
}