{
  "type": "Feature",
  "properties": {
    "iso:country":"US",
    "sg:address":"1613 Tennessee Ave",
    "sg:city":"Dalhart",
    "sg:classifiers":[
        {
            "category":"Health Services",
            "subcategory":"Chiropractor",
            "type":"Services"
        }
    ],
    "sg:phone":"+1 806 244 5571",
    "sg:postcode":"79022",
    "sg:province":"TX",
    "sg:tags":[
        "chiropractic"
    ],
    "wof:name":"Stephen R Shepherd",
    "wof:placetype":"venue"
},
  "geometry": {"coordinates":[-102.51355700000001,36.05069],"type":"Point"}
}