{
  "type": "Feature",
  "properties": {
    "iso:country":"US",
    "sg:address":"109 Main St",
    "sg:city":"Italy",
    "sg:classifiers":[
        {
            "category":"Utilities",
            "subcategory":"Water",
            "type":"Services"
        }
    ],
    "sg:phone":"+1 972 483 6885",
    "sg:postcode":"76651",
    "sg:province":"TX",
    "sg:tags":[
        "company",
        "sewage"
    ],
    "wof:name":"South Ellis County Water Supl",
    "wof:placetype":"venue"
},
  "geometry": {"coordinates":[-96.887199,32.183818],"type":"Point"}
}