{
  "type": "Feature",
  "properties": {
    "iso:country":"US",
    "sg:address":"202 State Hwy 1604",
    "sg:city":"San Antonio",
    "sg:classifiers":[
        {
            "category":"Shopping",
            "subcategory":"Computers & Home Electronics",
            "type":"Retail Goods"
        }
    ],
    "sg:phone":"+1 210 499 1202",
    "sg:postcode":"78232",
    "sg:province":"TX",
    "sg:tags":[
        "audio"
    ],
    "wof:name":"Automatic Gates Camera's",
    "wof:placetype":"venue"
},
  "geometry": {"coordinates":[-98.491665,29.608891],"type":"Point"}
}