{
  "type": "Feature",
  "properties": {
    "iso:country":"US",
    "sg:address":"1308 Summit Ave",
    "sg:city":"Plano",
    "sg:classifiers":[
        {
            "category":"Wholesale",
            "subcategory":"Hardware",
            "type":"Manufacturing & Wholesale Goods"
        }
    ],
    "sg:phone":"+1 972 398 6292",
    "sg:postcode":"75074",
    "sg:province":"TX",
    "sg:tags":[
        "equipment",
        "heating",
        "condition",
        "air"
    ],
    "wof:name":"Baker Distributing 236",
    "wof:placetype":"venue"
},
  "geometry": {"coordinates":[-96.69708300000001,33.009396],"type":"Point"}
}