{
  "type": "Feature",
  "properties": {
    "iso:country":"US",
    "sg:address":"3219 S Main St",
    "sg:city":"Stafford",
    "sg:classifiers":[
        {
            "category":"Real Estate",
            "subcategory":"Real Estate Services",
            "type":"Services"
        }
    ],
    "sg:phone":"+1 281 969 8692",
    "sg:postcode":"77477",
    "sg:province":"TX",
    "sg:tags":[
        "management",
        "property"
    ],
    "sg:website":"www.trendrealty.com",
    "wof:name":"Trend American Realty",
    "wof:placetype":"venue"
},
  "geometry": {"coordinates":[-95.563329,29.617303],"type":"Point"}
}