{
  "type": "Feature",
  "properties": {
    "iso:country":"US",
    "sg:address":"5861 I- 10",
    "sg:city":"Orange",
    "sg:classifiers":[
        {
            "category":"Shopping",
            "subcategory":"Computers & Home Electronics",
            "type":"Retail Goods"
        }
    ],
    "sg:phone":"+1 409 670 1500",
    "sg:postcode":"77630",
    "sg:province":"TX",
    "sg:tags":[
        "equipment",
        "satellite",
        "system"
    ],
    "wof:name":"Direct Entertainment",
    "wof:placetype":"venue"
},
  "geometry": {"coordinates":[-93.82226900000001,30.115667],"type":"Point"}
}