{
  "type": "Feature",
  "properties": {
    "iso:country":"US",
    "sg:address":"12324 Mustang Cir",
    "sg:city":"Forney",
    "sg:classifiers":[
        {
            "category":"Building & Trades",
            "subcategory":"Electrical",
            "type":"Services"
        }
    ],
    "sg:phone":"+1 972 564 1554",
    "sg:postcode":"75126",
    "sg:province":"TX",
    "sg:tags":[
        "electrical",
        "contractor"
    ],
    "wof:name":"Melar Electric",
    "wof:placetype":"venue"
},
  "geometry": {"coordinates":[-96.42607599999999,32.692374],"type":"Point"}
}