{
  "type": "Feature",
  "properties": {
    "iso:country":"US",
    "sg:address":"10016 N Crowley Rd",
    "sg:city":"Crowley",
    "sg:classifiers":[
        {
            "category":"Retail",
            "subcategory":"Auto Repair",
            "type":"Services"
        }
    ],
    "sg:phone":"+1 817 293 9666",
    "sg:postcode":"76036",
    "sg:province":"TX",
    "sg:tags":[
        "body",
        "shop",
        "painting",
        "automobile"
    ],
    "sg:website":"www.paintbysteve.com",
    "wof:name":"Paint by Steve",
    "wof:placetype":"venue"
},
  "geometry": {"coordinates":[-97.351996,32.609682],"type":"Point"}
}