{
  "type": "Feature",
  "properties": {
    "iso:country":"US",
    "sg:address":"12918 Kimberley Ln",
    "sg:city":"Houston",
    "sg:classifiers":[
        {
            "category":"Manufacturing",
            "subcategory":"Metals",
            "type":"Manufacturing & Wholesale Goods"
        }
    ],
    "sg:phone":"+1 713 906 0508",
    "sg:postcode":"77079",
    "sg:province":"TX",
    "sg:tags":[
        "product",
        "fabricated",
        "mfg"
    ],
    "wof:name":"Art & Frame World",
    "wof:placetype":"venue"
},
  "geometry": {"coordinates":[-95.564717,29.776075],"type":"Point"}
}