{
  "type": "Feature",
  "properties": {
    "iso:country":"US",
    "sg:address":"3712 7th St",
    "sg:city":"Bay City",
    "sg:classifiers":[
        {
            "category":"Travel",
            "subcategory":"Hotels & Motels",
            "type":"Entertainment"
        }
    ],
    "sg:phone":"+1 979 245 5115",
    "sg:postcode":"77414",
    "sg:province":"TX",
    "wof:name":"Econo Lodge",
    "wof:placetype":"venue"
},
  "geometry": {"coordinates":[-95.946496,28.982817],"type":"Point"}
}