{
  "type": "Feature",
  "properties": {
    "iso:country":"US",
    "sg:address":"2515 Clay Ave",
    "sg:city":"Waco",
    "sg:classifiers":[
        {
            "category":"Restaurant",
            "type":"Food & Drink"
        }
    ],
    "sg:phone":"+1 254 754 3434",
    "sg:postcode":"76706",
    "sg:province":"TX",
    "sg:tags":[
        "eating"
    ],
    "wof:name":"MI Casa",
    "wof:placetype":"venue"
},
  "geometry": {"coordinates":[-97.146281,31.535794],"type":"Point"}
}