{
  "type": "Feature",
  "properties": {
    "iso:country":"US",
    "sg:address":"2825 N Harwood St",
    "sg:city":"Dallas",
    "sg:classifiers":[
        {
            "category":"Organizations",
            "subcategory":"Membership Organization",
            "type":"Services"
        }
    ],
    "sg:phone":"+1 214 303 1380",
    "sg:postcode":"75201",
    "sg:province":"TX",
    "sg:tags":[
        "athletic"
    ],
    "wof:name":"Heroes Foundation",
    "wof:placetype":"venue"
},
  "geometry": {"coordinates":[-96.809077,32.794563],"type":"Point"}
}