{
  "type": "Feature",
  "properties": {
    "iso:country":"US",
    "sg:address":"216 W 9th St",
    "sg:city":"Tyler",
    "sg:classifiers":[
        {
            "category":"Shopping",
            "subcategory":"Used Merchandise",
            "type":"Retail Goods"
        }
    ],
    "sg:phone":"+1 903 597 8500",
    "sg:postcode":"75701",
    "sg:province":"TX",
    "sg:tags":[
        "shop",
        "consignment"
    ],
    "wof:name":"My Sister's Room",
    "wof:placetype":"venue"
},
  "geometry": {"coordinates":[-95.301834,32.327048],"type":"Point"}
}