{
  "type": "Feature",
  "properties": {
    "iso:country":"US",
    "sg:address":"10417 Firethorn Ln",
    "sg:city":"Austin",
    "sg:classifiers":[
        {
            "category":"Home & Garden",
            "subcategory":"Garden Supply",
            "type":"Retail Goods"
        }
    ],
    "sg:phone":"+1 512 996 8100",
    "sg:postcode":"78750",
    "sg:province":"TX",
    "sg:tags":[
        "sodding",
        "sod"
    ],
    "wof:name":"The Grass Outlet",
    "wof:placetype":"venue"
},
  "geometry": {"coordinates":[-97.801096,30.454972],"type":"Point"}
}