{
  "type": "Feature",
  "properties": {
    "iso:country":"US",
    "sg:address":"5950 Selinsky Rd",
    "sg:city":"Houston",
    "sg:classifiers":[
        {
            "category":"Social Services",
            "type":"Services"
        }
    ],
    "sg:phone":"+1 713 991 5083",
    "sg:postcode":"77048",
    "sg:province":"TX",
    "wof:name":"Boys Girls CLB Greater Houston",
    "wof:placetype":"venue"
},
  "geometry": {"coordinates":[-95.325745,29.63746],"type":"Point"}
}