{
  "type": "Feature",
  "properties": {
    "iso:country":"US",
    "sg:address":"1109 Wonder Dr",
    "sg:city":"Round Rock",
    "sg:classifiers":[
        {
            "category":"Building & Trades",
            "subcategory":"Plumbing",
            "type":"Services"
        }
    ],
    "sg:phone":"+1 512 255 5134",
    "sg:postcode":"78681",
    "sg:province":"TX",
    "sg:tags":[
        "conditioning",
        "air",
        "system",
        "contractor"
    ],
    "wof:name":"Round Rock Air Cond & Heating",
    "wof:placetype":"venue"
},
  "geometry": {"coordinates":[-97.693574,30.51843],"type":"Point"}
}