{
  "type": "Feature",
  "properties": {
    "iso:country":"US",
    "sg:address":"3801 Kirby Dr",
    "sg:city":"Houston",
    "sg:classifiers":[
        {
            "category":"Health Services",
            "subcategory":"Doctor",
            "type":"Services"
        }
    ],
    "sg:phone":"+1 713 520 8860",
    "sg:postcode":"77098",
    "sg:province":"TX",
    "wof:name":"M H Radiation Oncology",
    "wof:placetype":"venue"
},
  "geometry": {"coordinates":[-95.418048,29.732552],"type":"Point"}
}