{
  "type": "Feature",
  "properties": {
    "iso:country":"US",
    "sg:address":"7127 N Loop Fwy",
    "sg:city":"Houston",
    "sg:classifiers":[
        {
            "category":"Health Services",
            "subcategory":"Doctor",
            "type":"Services"
        }
    ],
    "sg:phone":"+1 713 673 6610",
    "sg:postcode":"77028",
    "sg:province":"TX",
    "sg:tags":[
        "medical",
        "practice"
    ],
    "wof:name":"US Healthworks Inc",
    "wof:placetype":"venue"
},
  "geometry": {"coordinates":[-95.29364,29.804665],"type":"Point"}
}