{
  "type": "Feature",
  "properties": {
    "iso:country":"US",
    "sg:address":"19 Silkbay Pl",
    "sg:city":"The Woodlands",
    "sg:classifiers":[
        {
            "category":"Health Services",
            "subcategory":"Clinic",
            "type":"Services"
        }
    ],
    "sg:phone":"+1 281 259 7174",
    "sg:postcode":"77382",
    "sg:province":"TX",
    "sg:tags":[
        "control",
        "system",
        "bed",
        "wetting"
    ],
    "wof:name":"Hargitt House Foundation",
    "wof:placetype":"venue"
},
  "geometry": {"coordinates":[-95.528464,30.216574],"type":"Point"}
}