{
  "type": "Feature",
  "properties": {
    "iso:country":"US",
    "sg:address":"1511 E 5th St",
    "sg:city":"Lubbock",
    "sg:classifiers":[
        {
            "category":"Restaurant",
            "type":"Food & Drink"
        }
    ],
    "sg:phone":"+1 806 762 1377",
    "sg:postcode":"79403",
    "sg:province":"TX",
    "sg:tags":[
        "eating"
    ],
    "wof:name":"Lunch House",
    "wof:placetype":"venue"
},
  "geometry": {"coordinates":[-101.818952,33.591181],"type":"Point"}
}