{
  "type": "Feature",
  "properties": {
    "iso:country":"US",
    "sg:address":"7006 Norfolk Ave",
    "sg:city":"Lubbock",
    "sg:classifiers":[
        {
            "category":"Retail",
            "subcategory":"Repair Shop",
            "type":"Services"
        }
    ],
    "sg:phone":"+1 806 799 0364",
    "sg:postcode":"79413",
    "sg:province":"TX",
    "sg:tags":[
        "electrical"
    ],
    "wof:name":"Good Housekeeping Appliance Ce",
    "wof:placetype":"venue"
},
  "geometry": {"coordinates":[-101.899452,33.529736],"type":"Point"}
}