{
  "type": "Feature",
  "properties": {
    "iso:country":"US",
    "sg:address":"3609 41st St",
    "sg:city":"Lubbock",
    "sg:classifiers":[
        {
            "category":"Retail",
            "subcategory":"Car Wash",
            "type":"Services"
        }
    ],
    "sg:phone":"+1 806 438 1383",
    "sg:postcode":"79413",
    "sg:province":"TX",
    "sg:tags":[
        "automobile",
        "detailing"
    ],
    "wof:name":"Nova Wash",
    "wof:placetype":"venue"
},
  "geometry": {"coordinates":[-101.89223699999999,33.557098],"type":"Point"}
}