{
  "type": "Feature",
  "properties": {
    "iso:country":"US",
    "sg:address":"112 S Pecan St",
    "sg:city":"Woodville",
    "sg:classifiers":[
        {
            "category":"Professional",
            "type":"Services"
        }
    ],
    "sg:phone":"+1 409 283 3599",
    "sg:postcode":"75979",
    "sg:province":"TX",
    "wof:name":"Holly Tree",
    "wof:placetype":"venue"
},
  "geometry": {"coordinates":[-94.423588,30.775089],"type":"Point"}
}