{
  "type": "Feature",
  "properties": {
    "iso:country":"US",
    "sg:address":"2129 Utica Dr",
    "sg:city":"Dallas",
    "sg:classifiers":[
        {
            "category":"Retail",
            "subcategory":"Repair Shop",
            "type":"Services"
        }
    ],
    "sg:phone":"+1 214 388 2234",
    "sg:postcode":"75227",
    "sg:province":"TX",
    "sg:tags":[
        "welding"
    ],
    "wof:name":"Victor Solis Welding",
    "wof:placetype":"venue"
},
  "geometry": {"coordinates":[-96.68567400000001,32.751958],"type":"Point"}
}