{
  "type": "Feature",
  "properties": {
    "iso:country":"US",
    "sg:address":"402 E North St",
    "sg:city":"Victoria",
    "sg:classifiers":[
        {
            "category":"Organizations",
            "subcategory":"Religious Organization",
            "type":"Services"
        }
    ],
    "sg:phone":"+1 361 575 0116",
    "sg:postcode":"77901",
    "sg:province":"TX",
    "sg:tags":[
        "church"
    ],
    "wof:name":"God's Church Of Restoration",
    "wof:placetype":"venue"
},
  "geometry": {"coordinates":[-96.999937,28.803097],"type":"Point"}
}