{
  "type": "Feature",
  "properties": {
    "iso:country":"US",
    "sg:address":"9180 Forest Ln",
    "sg:city":"Dallas",
    "sg:classifiers":[
        {
            "category":"Travel",
            "subcategory":"Travel Agent",
            "type":"Entertainment"
        }
    ],
    "sg:phone":"+1 214 341 7725",
    "sg:postcode":"75243",
    "sg:province":"TX",
    "sg:tags":[
        "corporate",
        "arrangement"
    ],
    "wof:name":"Express Travelers",
    "wof:placetype":"venue"
},
  "geometry": {"coordinates":[-96.746487,32.909167],"type":"Point"}
}