{
  "type": "Feature",
  "properties": {
    "iso:country":"US",
    "sg:address":"259 White Ln",
    "sg:city":"Beeville",
    "sg:classifiers":[
        {
            "category":"Professional",
            "subcategory":"Detective & Security Services",
            "type":"Services"
        }
    ],
    "sg:phone":"+1 361 358 6659",
    "sg:postcode":"78102",
    "sg:province":"TX",
    "sg:tags":[
        "information",
        "bureau"
    ],
    "wof:name":"Justins Welding Service",
    "wof:placetype":"venue"
},
  "geometry": {"coordinates":[-97.761837,28.443862],"type":"Point"}
}