{
  "type": "Feature",
  "properties": {
    "iso:country":"US",
    "sg:address":"195 Lewis Clark",
    "sg:city":"Johnson City",
    "sg:classifiers":[
        {
            "category":"Professional",
            "subcategory":"Business Services",
            "type":"Services"
        }
    ],
    "sg:phone":"+1 830 868 2266",
    "sg:postcode":"78636",
    "sg:province":"TX",
    "wof:name":"Kathleen Ann Laros",
    "wof:placetype":"venue"
},
  "geometry": {"coordinates":[-98.26499699999999,30.246375],"type":"Point"}
}