{
  "type": "Feature",
  "properties": {
    "iso:country":"US",
    "sg:address":"121 Coad St",
    "sg:city":"Fort Worth",
    "sg:classifiers":[
        {
            "category":"Manufacturing",
            "subcategory":"Tools & Machinery",
            "type":"Manufacturing & Wholesale Goods"
        }
    ],
    "sg:phone":"+1 817 293 3488",
    "sg:postcode":"76140",
    "sg:province":"TX",
    "sg:tags":[
        "machine",
        "shop",
        "industrial",
        "mfg"
    ],
    "wof:name":"Machine Specialties Inc",
    "wof:placetype":"venue"
},
  "geometry": {"coordinates":[-97.317756,32.604376],"type":"Point"}
}