{
  "type": "Feature",
  "properties": {
    "iso:country":"US",
    "sg:address":"5905 Charleston Dr",
    "sg:city":"Frisco",
    "sg:classifiers":[
        {
            "category":"Manufacturing",
            "subcategory":"Textiles",
            "type":"Manufacturing & Wholesale Goods"
        }
    ],
    "sg:phone":"+1 972 335 3415",
    "sg:postcode":"75035",
    "sg:province":"TX",
    "sg:tags":[
        "mill",
        "knitting"
    ],
    "wof:name":"Kristi R Hudson",
    "wof:placetype":"venue"
},
  "geometry": {"coordinates":[-96.784716,33.127388],"type":"Point"}
}