{
  "type": "Feature",
  "properties": {
    "iso:country":"US",
    "sg:address":"22722 Acorn Valley Dr",
    "sg:city":"Spring",
    "sg:classifiers":[
        {
            "category":"Autos & Motor Vehicles",
            "subcategory":"Auto Supplies",
            "type":"Retail Goods"
        }
    ],
    "sg:phone":"+1 281 288 5756",
    "sg:postcode":"77389",
    "sg:province":"TX",
    "wof:name":"Gt Tire & Supply",
    "wof:placetype":"venue"
},
  "geometry": {"coordinates":[-95.474844,30.09803],"type":"Point"}
}