{
  "type": "Feature",
  "properties": {
    "iso:country":"US",
    "sg:address":"1130 E Arapaho Rd",
    "sg:city":"Richardson",
    "sg:classifiers":[
        {
            "category":"Professional",
            "subcategory":"Lawyer & Legal Services",
            "type":"Services"
        }
    ],
    "sg:phone":"+1 214 360 9343",
    "sg:postcode":"75081",
    "sg:province":"TX",
    "wof:name":"Marx Randy P Atty",
    "wof:placetype":"venue"
},
  "geometry": {"coordinates":[-96.70737,32.959908],"type":"Point"}
}