{
  "type": "Feature",
  "properties": {
    "iso:country":"US",
    "sg:address":"530 Weeping Oaks Ln",
    "sg:city":"Spring",
    "sg:classifiers":[
        {
            "category":"Building & Trades",
            "subcategory":"Construction",
            "type":"Services"
        }
    ],
    "sg:phone":"+1 281 350 6699",
    "sg:postcode":"77388",
    "sg:province":"TX",
    "sg:tags":[
        "builder",
        "operative"
    ],
    "wof:name":"Aztex Interests",
    "wof:placetype":"venue"
},
  "geometry": {"coordinates":[-95.439635,30.04216],"type":"Point"}
}