{
  "type": "Feature",
  "properties": {
    "iso:country":"US",
    "sg:address":"1112 N Floyd Rd",
    "sg:city":"Richardson",
    "sg:classifiers":[
        {
            "category":"Health Services",
            "subcategory":"Doctor",
            "type":"Services"
        }
    ],
    "sg:phone":"+1 972 235 6911",
    "sg:postcode":"75080",
    "sg:province":"TX",
    "sg:tags":[
        "physician",
        "medical",
        "surgeon"
    ],
    "wof:name":"John R Porter Pa",
    "wof:placetype":"venue"
},
  "geometry": {"coordinates":[-96.74345099999999,32.963354],"type":"Point"}
}