{
  "type": "Feature",
  "properties": {
    "iso:country":"US",
    "sg:address":"1117 Austin St",
    "sg:city":"Rosenberg",
    "sg:classifiers":[
        {
            "category":"Communications",
            "subcategory":"Film & Video Production",
            "type":"Services"
        }
    ],
    "sg:phone":"+1 281 342 5233",
    "sg:postcode":"77471",
    "sg:province":"TX",
    "sg:tags":[
        "motion",
        "picture"
    ],
    "wof:name":"Ghost Mountain Music",
    "wof:placetype":"venue"
},
  "geometry": {"coordinates":[-95.79611199999999,29.557164],"type":"Point"}
}