{
  "type": "Feature",
  "properties": {
    "iso:country":"US",
    "sg:address":"3344 Mansfield Hwy",
    "sg:city":"Fort Worth",
    "sg:classifiers":[
        {
            "category":"Bars & Pubs",
            "type":"Food & Drink"
        }
    ],
    "sg:phone":"+1 817 535 6010",
    "sg:postcode":"76119",
    "sg:province":"TX",
    "sg:tags":[
        "drinking"
    ],
    "wof:name":"Fiesta Guadalajara",
    "wof:placetype":"venue"
},
  "geometry": {"coordinates":[-97.275942,32.681211],"type":"Point"}
}