{
  "type": "Feature",
  "properties": {
    "iso:country":"US",
    "sg:address":"121 Lynnie Penny St",
    "sg:city":"Midlothian",
    "sg:classifiers":[
        {
            "category":"Building & Trades",
            "subcategory":"Construction",
            "type":"Services"
        }
    ],
    "sg:phone":"+1 972 754 0515",
    "sg:postcode":"76065",
    "sg:province":"TX",
    "sg:tags":[
        "contractor"
    ],
    "wof:name":"Hawkeye Discount Siding",
    "wof:placetype":"venue"
},
  "geometry": {"coordinates":[-96.96813899999999,32.484306],"type":"Point"}
}