{
  "type": "Feature",
  "properties": {
    "iso:country":"US",
    "sg:address":"3823 Appalachian Trl",
    "sg:city":"Humble",
    "sg:classifiers":[
        {
            "category":"Professional",
            "subcategory":"Computer Services",
            "type":"Services"
        }
    ],
    "sg:phone":"+1 281 361 3146",
    "sg:postcode":"77345",
    "sg:province":"TX",
    "sg:tags":[
        "prepackaged",
        "software"
    ],
    "wof:name":"Wasco Technical Software",
    "wof:placetype":"venue"
},
  "geometry": {"coordinates":[-95.186318,30.075648],"type":"Point"}
}