{
  "type": "Feature",
  "properties": {
    "iso:country":"US",
    "sg:address":"1600 S I- 35",
    "sg:city":"Carrollton",
    "sg:classifiers":[
        {
            "category":"Building & Trades",
            "subcategory":"Construction",
            "type":"Services"
        }
    ],
    "sg:phone":"+1 972 446 2121",
    "sg:postcode":"75006",
    "sg:province":"TX",
    "sg:tags":[
        "nonresidential"
    ],
    "wof:name":"S K Padayachee",
    "wof:placetype":"venue"
},
  "geometry": {"coordinates":[-96.905119,32.944974],"type":"Point"}
}