{
  "type": "Feature",
  "properties": {
    "iso:country":"US",
    "sg:address":"120 E Ovilla Rd",
    "sg:city":"Red Oak",
    "sg:classifiers":[
        {
            "category":"Professional",
            "subcategory":"Accounting & Tax Preparation",
            "type":"Services"
        }
    ],
    "sg:phone":"+1 972 617 3000",
    "sg:postcode":"75154",
    "sg:province":"TX",
    "sg:tags":[
        "return",
        "filing"
    ],
    "wof:name":"Ben Heckathorn",
    "wof:placetype":"venue"
},
  "geometry": {"coordinates":[-96.85706999999999,32.531795],"type":"Point"}
}