{
  "type": "Feature",
  "properties": {
    "iso:country":"US",
    "sg:address":"2050 N Tram Rd",
    "sg:city":"Vidor",
    "sg:classifiers":[
        {
            "category":"Shopping",
            "subcategory":"Beauty & Cosmetics",
            "type":"Retail Goods"
        }
    ],
    "sg:phone":"+1 409 769 9550",
    "sg:postcode":"77662",
    "sg:province":"TX",
    "sg:tags":[
        "perfume",
        "salons-equipment",
        "supply"
    ],
    "wof:name":"Celeste Cormier",
    "wof:placetype":"venue"
},
  "geometry": {"coordinates":[-94.003288,30.149723],"type":"Point"}
}