{
  "type": "Feature",
  "properties": {
    "iso:country":"US",
    "sg:address":"2804 Ave L",
    "sg:city":"Wichita Falls",
    "sg:classifiers":[
        {
            "category":"Professional",
            "subcategory":"Computer Services",
            "type":"Services"
        }
    ],
    "sg:phone":"+1 940 766 2836",
    "sg:postcode":"76309",
    "sg:province":"TX",
    "wof:name":"Golden Byte Computers",
    "wof:placetype":"venue"
},
  "geometry": {"coordinates":[-98.52949099999999,33.892899],"type":"Point"}
}