{
  "type": "Feature",
  "properties": {
    "iso:country":"US",
    "sg:address":"3509 Needles Dr",
    "sg:city":"Austin",
    "sg:classifiers":[
        {
            "category":"Professional",
            "type":"Services"
        }
    ],
    "sg:phone":"+1 512 327 8013",
    "sg:postcode":"78746",
    "sg:province":"TX",
    "wof:name":"Dan & Sylvia Sharplin",
    "wof:placetype":"venue"
},
  "geometry": {"coordinates":[-97.805803,30.333553],"type":"Point"}
}