{
  "type": "Feature",
  "properties": {
    "iso:country":"US",
    "sg:address":"2700 Live Oak St",
    "sg:city":"Dallas",
    "sg:classifiers":[
        {
            "category":"Shopping",
            "subcategory":"Computers & Home Electronics",
            "type":"Retail Goods"
        }
    ],
    "sg:phone":"+1 214 823 9899",
    "sg:postcode":"75204",
    "sg:province":"TX",
    "sg:tags":[
        "equipment",
        "dealer"
    ],
    "wof:name":"En Pointe Technologies",
    "wof:placetype":"venue"
},
  "geometry": {"coordinates":[-96.78848600000001,32.78933],"type":"Point"}
}