{
  "type": "Feature",
  "properties": {
    "iso:country":"US",
    "sg:address":"135 Oyster Creek Dr",
    "sg:city":"Lake Jackson",
    "sg:classifiers":[
        {
            "category":"Health Services",
            "subcategory":"Doctor",
            "type":"Services"
        }
    ],
    "sg:phone":"+1 979 848 8217",
    "sg:postcode":"77566",
    "sg:province":"TX",
    "sg:tags":[
        "medical"
    ],
    "wof:name":"Genesis Center Inc",
    "wof:placetype":"venue"
},
  "geometry": {"coordinates":[-95.450315,29.04536],"type":"Point"}
}