{
  "type": "Feature",
  "properties": {
    "iso:country":"US",
    "sg:address":"1723 39th St",
    "sg:city":"Galveston",
    "sg:classifiers":[
        {
            "category":"Professional",
            "type":"Services"
        }
    ],
    "sg:phone":"+1 409 763 6317",
    "sg:postcode":"77550",
    "sg:province":"TX",
    "wof:name":"Galvan Elueterro",
    "wof:placetype":"venue"
},
  "geometry": {"coordinates":[-94.807958,29.288207],"type":"Point"}
}