{
  "type": "Feature",
  "properties": {
    "iso:country":"US",
    "sg:address":"1417 Bellaire Dr",
    "sg:city":"Grapevine",
    "sg:classifiers":[
        {
            "category":"Transit Center",
            "subcategory":"Freight",
            "type":"Transportation"
        }
    ],
    "sg:phone":"+1 817 481 3710",
    "sg:postcode":"76051",
    "sg:province":"TX",
    "sg:tags":[
        "trucking-light",
        "hauling"
    ],
    "wof:name":"Andy S Cartage Co",
    "wof:placetype":"venue"
},
  "geometry": {"coordinates":[-97.081985,32.926085],"type":"Point"}
}