{
  "type": "Feature",
  "properties": {
    "iso:country":"US",
    "sg:address":"3013 38th St",
    "sg:city":"Lubbock",
    "sg:classifiers":[
        {
            "category":"Wholesale",
            "subcategory":"Drugs",
            "type":"Manufacturing & Wholesale Goods"
        }
    ],
    "sg:phone":"+1 806 771 4346",
    "sg:postcode":"79413",
    "sg:province":"TX",
    "sg:tags":[
        "pharmaceutical",
        "product"
    ],
    "wof:name":"Pfizer",
    "wof:placetype":"venue"
},
  "geometry": {"coordinates":[-101.881046,33.559574],"type":"Point"}
}