{
  "type": "Feature",
  "properties": {
    "iso:country":"US",
    "sg:address":"4020 Rhea Rd",
    "sg:city":"Wichita Falls",
    "sg:classifiers":[
        {
            "category":"Health Services",
            "subcategory":"Medical Lab",
            "type":"Services"
        }
    ],
    "sg:phone":"+1 940 723 5085",
    "sg:postcode":"76308",
    "sg:province":"TX",
    "sg:tags":[
        "laboratory"
    ],
    "wof:name":"Victory Dental Lab",
    "wof:placetype":"venue"
},
  "geometry": {"coordinates":[-98.539648,33.869087],"type":"Point"}
}