{
  "type": "Feature",
  "properties": {
    "iso:country":"US",
    "sg:address":"43 Meandering Way",
    "sg:city":"Round Rock",
    "sg:classifiers":[
        {
            "category":"Building & Trades",
            "subcategory":"Construction",
            "type":"Services"
        }
    ],
    "sg:phone":"+1 512 248 1174",
    "sg:postcode":"78664",
    "sg:province":"TX",
    "sg:tags":[
        "house"
    ],
    "wof:name":"Zoller Homes Inc",
    "wof:placetype":"venue"
},
  "geometry": {"coordinates":[-97.60670399999999,30.522296],"type":"Point"}
}