{
  "type": "Feature",
  "properties": {
    "iso:country":"US",
    "sg:address":"10028 Homestead Rd",
    "sg:city":"Houston",
    "sg:classifiers":[
        {
            "category":"Retail",
            "subcategory":"Laundry & Dry Cleaning",
            "type":"Services"
        }
    ],
    "sg:phone":"+1 713 633 6162",
    "sg:postcode":"77016",
    "sg:province":"TX",
    "wof:name":"Inwood Cleaners",
    "wof:placetype":"venue"
},
  "geometry": {"coordinates":[-95.300301,29.8563],"type":"Point"}
}