{
  "type": "Feature",
  "properties": {
    "iso:country":"US",
    "sg:address":"1200 S Bridge Ave",
    "sg:city":"Weslaco",
    "sg:classifiers":[
        {
            "category":"Place Of Worship",
            "subcategory":"Church",
            "type":"Public Place"
        },
        {
            "category":"Place Of Worship",
            "type":"Public Place"
        }
    ],
    "sg:phone":"+1 956 968 5631",
    "sg:postcode":"78596",
    "sg:province":"TX",
    "sg:tags":[
        "churches-seventh-day",
        "adventist",
        "christian",
        "churches-advent"
    ],
    "sg:website":"http://www.adventist.org",
    "wof:name":"Seventh Day Adventist Church",
    "wof:placetype":"venue"
},
  "geometry": {"coordinates":[-97.98236799999999,26.1462],"type":"Point"}
}