{
  "type": "Feature",
  "properties": {
    "iso:country":"US",
    "sg:address":"977 Nasa Pkwy",
    "sg:city":"Houston",
    "sg:phone":"+1 281 486 9888",
    "sg:postcode":"77058",
    "sg:province":"TX",
    "sg:website":"http://www.masasushitexas.com",
    "wof:name":"Masa Sushi",
    "wof:placetype":"venue"
},
  "geometry": {"coordinates":[-95.106801,29.545751],"type":"Point"}
}