{
  "type": "Feature",
  "properties": {
    "iso:country":"US",
    "sg:address":"510 N Tennessee Ave",
    "sg:city":"Palestine",
    "sg:classifiers":[
        {
            "category":"Autos & Motor Vehicles",
            "subcategory":"Automobile Sales",
            "type":"Retail Goods"
        }
    ],
    "sg:phone":"+1 903 723 5446",
    "sg:postcode":"75801",
    "sg:province":"TX",
    "sg:tags":[
        "used"
    ],
    "wof:name":"Jovan Autos Inc",
    "wof:placetype":"venue"
},
  "geometry": {"coordinates":[-95.63569,31.76453],"type":"Point"}
}