{
  "type": "Feature",
  "properties": {
    "iso:country":"US",
    "sg:address":"1102 Augusta Ave",
    "sg:city":"Tyler",
    "sg:classifiers":[
        {
            "category":"Organizations",
            "subcategory":"Religious Organization",
            "type":"Services"
        }
    ],
    "sg:phone":"+1 903 533 0607",
    "sg:postcode":"75701",
    "sg:province":"TX",
    "sg:tags":[
        "church"
    ],
    "wof:name":"Family Way Missionary Baptist",
    "wof:placetype":"venue"
},
  "geometry": {"coordinates":[-95.30710500000001,32.336026],"type":"Point"}
}