{
  "type": "Feature",
  "properties": {
    "iso:country":"US",
    "sg:address":"225 S 3rd St",
    "sg:city":"Crockett",
    "sg:classifiers":[
        {
            "category":"Education",
            "subcategory":"School",
            "type":"Public Place"
        }
    ],
    "sg:phone":"+1 936 544 4025",
    "sg:postcode":"75835",
    "sg:province":"TX",
    "sg:tags":[
        "elementary"
    ],
    "sg:website":"http://www.crockettisd.net",
    "wof:name":"City of Crockett",
    "wof:placetype":"venue"
},
  "geometry": {"coordinates":[-95.458725,31.316788],"type":"Point"}
}