{
  "type": "Feature",
  "properties": {
    "iso:country":"US",
    "sg:address":"4605 Post Oak Place Dr",
    "sg:city":"Houston",
    "sg:classifiers":[
        {
            "category":"Professional",
            "subcategory":"Business Services",
            "type":"Services"
        }
    ],
    "sg:phone":"+1 713 961 1121",
    "sg:postcode":"77027",
    "sg:province":"TX",
    "sg:tags":[
        "consultant",
        "petroleum"
    ],
    "wof:name":"J R Butler & Co",
    "wof:placetype":"venue"
},
  "geometry": {"coordinates":[-95.4538,29.750216],"type":"Point"}
}