{
  "type": "Feature",
  "properties": {
    "iso:country":"US",
    "sg:address":"4141 Office Parkway",
    "sg:city":"Dallas",
    "sg:classifiers":[
        {
            "category":"Professional",
            "subcategory":"Advertising",
            "type":"Services"
        },
        {
            "category":"Communications",
            "subcategory":"Film & Video Production",
            "type":"Services"
        },
        {
            "category":"Internet Cafe",
            "subcategory":"None",
            "type":"Food & Drink"
        }
    ],
    "sg:phone":"+1 214 280 9185",
    "sg:postcode":"75204",
    "sg:province":"TX",
    "sg:tags":[
        "marketing",
        "product",
        "medium",
        "agency",
        "interactive"
    ],
    "sg:website":"http://www.achillesinteractive.com",
    "wof:name":"Achilles Interactive, Inc.",
    "wof:placetype":"venue"
},
  "geometry": {"coordinates":[-96.78845699999999,32.804109],"type":"Point"}
}