{
  "type": "Feature",
  "properties": {
    "iso:country":"US",
    "sg:address":"5444 50th St",
    "sg:city":"Lubbock",
    "sg:classifiers":[
        {
            "category":"Food & Beverages",
            "subcategory":"Groceries & Convenience Stores",
            "type":"Retail Goods"
        }
    ],
    "sg:phone":"+1 806 795 9441",
    "sg:postcode":"79414",
    "sg:province":"TX",
    "wof:name":"E- Z Mart 248",
    "wof:placetype":"venue"
},
  "geometry": {"coordinates":[-101.927358,33.548747],"type":"Point"}
}