{
  "type": "Feature",
  "properties": {
    "iso:country":"US",
    "sg:address":"4805 Journey St",
    "sg:city":"Amarillo",
    "sg:classifiers":[
        {
            "category":"Manufacturing",
            "subcategory":"Wood Products",
            "type":"Manufacturing & Wholesale Goods"
        }
    ],
    "sg:phone":"+1 806 356 6403",
    "sg:postcode":"79110",
    "sg:province":"TX",
    "sg:tags":[
        "mfg"
    ],
    "wof:name":"Canyon Kreek",
    "wof:placetype":"venue"
},
  "geometry": {"coordinates":[-101.867608,35.157714],"type":"Point"}
}