{
  "type": "Feature",
  "properties": {
    "iso:country":"US",
    "sg:address":"725 Cliffmoor Dr",
    "sg:city":"Keller",
    "sg:classifiers":[
        {
            "category":"Manufacturing",
            "subcategory":"Tools & Machinery",
            "type":"Manufacturing & Wholesale Goods"
        }
    ],
    "sg:phone":"+1 817 514 0745",
    "sg:postcode":"76248",
    "sg:province":"TX",
    "sg:tags":[
        "bin",
        "recycle",
        "recycling",
        "caddy",
        "mfg"
    ],
    "wof:name":"Delmar Manufacturing",
    "wof:placetype":"venue"
},
  "geometry": {"coordinates":[-97.23598800000001,32.908811],"type":"Point"}
}