{
  "type": "Feature",
  "properties": {
    "iso:country":"US",
    "sg:address":"507 S Ann St",
    "sg:city":"Rockport",
    "sg:classifiers":[
        {
            "category":"Organizations",
            "subcategory":"Membership Organization",
            "type":"Services"
        }
    ],
    "sg:phone":"+1 361 790 9828",
    "sg:postcode":"78382",
    "sg:province":"TX",
    "sg:tags":[
        "charitable"
    ],
    "wof:name":"Good Samaritan Service Center",
    "wof:placetype":"venue"
},
  "geometry": {"coordinates":[-97.05587800000001,28.023544],"type":"Point"}
}