{
  "type": "Feature",
  "properties": {
    "iso:country":"US",
    "sg:address":"2126 E Winn St",
    "sg:city":"Kemah",
    "sg:classifiers":[
        {
            "category":"Building & Trades",
            "subcategory":"Construction",
            "type":"Services"
        }
    ],
    "sg:phone":"+1 281 334 4823",
    "sg:postcode":"77565",
    "sg:province":"TX",
    "sg:tags":[
        "contractor"
    ],
    "wof:name":"Rwf Contracting",
    "wof:placetype":"venue"
},
  "geometry": {"coordinates":[-95.052876,29.548406],"type":"Point"}
}