{
  "type": "Feature",
  "properties": {
    "iso:country":"US",
    "sg:address":"2900 FM 225 S",
    "sg:city":"Henderson",
    "sg:classifiers":[
        {
            "category":"Organizations",
            "subcategory":"Religious Organization",
            "type":"Services"
        }
    ],
    "sg:phone":"+1 903 657 1203",
    "sg:postcode":"75654",
    "sg:province":"TX",
    "sg:tags":[
        "church"
    ],
    "wof:name":"Wesley Chapel Methodist",
    "wof:placetype":"venue"
},
  "geometry": {"coordinates":[-94.81007200000001,32.119458],"type":"Point"}
}