{
  "type": "Feature",
  "properties": {
    "iso:country":"US",
    "sg:address":"1315 N Blanco St",
    "sg:city":"Lockhart",
    "sg:classifiers":[
        {
            "category":"Government",
            "subcategory":"Office",
            "type":"Public Place"
        }
    ],
    "sg:phone":"+1 512 398 2412",
    "sg:postcode":"78644",
    "sg:province":"TX",
    "sg:tags":[
        "state",
        "program"
    ],
    "wof:name":"Transportation Dept",
    "wof:placetype":"venue"
},
  "geometry": {"coordinates":[-97.677121,29.895902],"type":"Point"}
}