{
  "type": "Feature",
  "properties": {
    "iso:country":"US",
    "sg:address":"5323 Spring Valley Rd",
    "sg:city":"Dallas",
    "sg:classifiers":[
        {
            "category":"Insurance",
            "subcategory":"Insurance Agent",
            "type":"Services"
        }
    ],
    "sg:phone":"+1 972 788 1128",
    "sg:postcode":"75254",
    "sg:province":"TX",
    "wof:name":"Dallas Financial Wholesalers",
    "wof:placetype":"venue"
},
  "geometry": {"coordinates":[-96.814477,32.939486],"type":"Point"}
}