{
  "type": "Feature",
  "properties": {
    "iso:country":"US",
    "sg:address":"1730 W Randol Mill Rd",
    "sg:city":"Arlington",
    "sg:classifiers":[
        {
            "category":"Home & Garden",
            "subcategory":"Garden Supply",
            "type":"Retail Goods"
        },
        {
            "category":"Shopping",
            "subcategory":"Gifts & Souvenirs",
            "type":"Retail Goods"
        },
        {
            "category":"Shopping",
            "subcategory":"Crafts & Fabrics",
            "type":"Retail Goods"
        },
        {
            "category":"Shopping",
            "subcategory":"Florist",
            "type":"Retail Goods"
        }
    ],
    "sg:phone":"+1 817 261 9400",
    "sg:postcode":"76012",
    "sg:province":"TX",
    "sg:tags":[
        "plant",
        "etc-retail",
        "dried",
        "basket",
        "trees-silk",
        "flowers"
    ],
    "sg:website":"http://www.arlingtonflowerexchange.com",
    "wof:name":"Arlington Flowers",
    "wof:placetype":"venue"
},
  "geometry": {"coordinates":[-97.136087,32.750241],"type":"Point"}
}