{
  "type": "Feature",
  "properties": {
    "iso:country":"US",
    "sg:address":"3501 Chaney Ln",
    "sg:city":"Plano",
    "sg:classifiers":[
        {
            "category":"Professional",
            "type":"Services"
        }
    ],
    "sg:phone":"+1 972 596 5083",
    "sg:postcode":"75093",
    "sg:province":"TX",
    "wof:name":"Steve Fischer PC",
    "wof:placetype":"venue"
},
  "geometry": {"coordinates":[-96.78513100000001,33.044701],"type":"Point"}
}