{
  "type": "Feature",
  "properties": {
    "iso:country":"US",
    "sg:address":"7504 Manning Ln",
    "sg:city":"Houston",
    "sg:classifiers":[
        {
            "category":"Building & Trades",
            "subcategory":"Construction",
            "type":"Services"
        }
    ],
    "sg:phone":"+1 713 991 5230",
    "sg:postcode":"77075",
    "sg:province":"TX",
    "sg:tags":[
        "foundation",
        "concrete",
        "contractor"
    ],
    "wof:name":"Lifesaver Drilling Inc",
    "wof:placetype":"venue"
},
  "geometry": {"coordinates":[-95.28709499999999,29.614063],"type":"Point"}
}