{
  "type": "Feature",
  "properties": {
    "iso:country":"US",
    "sg:address":"27671 Ramblewood St",
    "sg:city":"San Antonio",
    "sg:classifiers":[
        {
            "category":"Professional",
            "subcategory":"Management & Consulting",
            "type":"Services"
        }
    ],
    "sg:phone":"+1 830 980 8691",
    "sg:postcode":"78261",
    "sg:province":"TX",
    "sg:tags":[
        "consultant",
        "medical"
    ],
    "wof:name":"Majomed Corporation",
    "wof:placetype":"venue"
},
  "geometry": {"coordinates":[-98.44211900000001,29.711935],"type":"Point"}
}