{
  "type": "Feature",
  "properties": {
    "iso:country":"US",
    "sg:address":"2026 Mapleton Dr",
    "sg:city":"Houston",
    "sg:classifiers":[
        {
            "category":"Professional",
            "subcategory":"Business Services",
            "type":"Services"
        }
    ],
    "sg:phone":"+1 713 463 8290",
    "sg:postcode":"77043",
    "sg:province":"TX",
    "wof:name":"Signet Consulting Group",
    "wof:placetype":"venue"
},
  "geometry": {"coordinates":[-95.561397,29.808595],"type":"Point"}
}