{
  "type": "Feature",
  "properties": {
    "iso:country":"US",
    "sg:address":"14002 Seagoville Rd",
    "sg:city":"Dallas",
    "sg:classifiers":[
        {
            "category":"Shopping",
            "subcategory":"Gifts & Souvenirs",
            "type":"Retail Goods"
        }
    ],
    "sg:phone":"+1 972 557 4392",
    "sg:postcode":"75253",
    "sg:province":"TX",
    "wof:name":"Sandra K Benavides",
    "wof:placetype":"venue"
},
  "geometry": {"coordinates":[-96.59959000000001,32.697397],"type":"Point"}
}