{
  "type": "Feature",
  "properties": {
    "iso:country":"US",
    "sg:address":"508 S Kaufman St",
    "sg:city":"Ennis",
    "sg:classifiers":[
        {
            "category":"Professional",
            "subcategory":"Accounting & Tax Preparation",
            "type":"Services"
        }
    ],
    "sg:phone":"+1 972 875 3996",
    "sg:postcode":"75119",
    "sg:province":"TX",
    "sg:tags":[
        "bookkeeping",
        "general"
    ],
    "wof:name":"A Plus Bookkeeping and Tax Stn",
    "wof:placetype":"venue"
},
  "geometry": {"coordinates":[-96.621711,32.325297],"type":"Point"}
}