{
  "type": "Feature",
  "properties": {
    "iso:country":"US",
    "sg:address":"1202 N Jefferson Ave",
    "sg:city":"Mount Pleasant",
    "sg:classifiers":[
        {
            "category":"Shopping",
            "subcategory":"Computers & Home Electronics",
            "type":"Retail Goods"
        }
    ],
    "sg:phone":"+1 903 572 4182",
    "sg:postcode":"75455",
    "sg:province":"TX",
    "sg:tags":[
        "repair"
    ],
    "wof:name":"Newman Electronics",
    "wof:placetype":"venue"
},
  "geometry": {"coordinates":[-94.970157,33.168535],"type":"Point"}
}