{
  "type": "Feature",
  "properties": {
    "iso:country":"US",
    "sg:address":"6411 Hillman Glen Cir",
    "sg:city":"Houston",
    "sg:classifiers":[
        {
            "category":"Freight",
            "type":"Transportation"
        }
    ],
    "sg:phone":"+1 281 272 2795",
    "sg:postcode":"77086",
    "sg:province":"TX",
    "wof:name":"4t Transportation",
    "wof:placetype":"venue"
},
  "geometry": {"coordinates":[-95.48253099999999,29.915659],"type":"Point"}
}