{
  "type": "Feature",
  "properties": {
    "iso:country":"US",
    "sg:address":"2618 S 27th St",
    "sg:city":"Abilene",
    "sg:classifiers":[
        {
            "category":"Personal",
            "subcategory":"Beauty Salon",
            "type":"Services"
        }
    ],
    "sg:phone":"+1 325 698 1464",
    "sg:postcode":"79605",
    "sg:province":"TX",
    "wof:name":"Hair By Shari Hurley",
    "wof:placetype":"venue"
},
  "geometry": {"coordinates":[-99.75562499999999,32.417403],"type":"Point"}
}