{
  "type": "Feature",
  "properties": {
    "iso:country":"US",
    "sg:address":"2028 E Griffin Pkwy",
    "sg:city":"Mission",
    "sg:classifiers":[
        {
            "category":"Wholesale",
            "subcategory":"Durable Goods & Equipment",
            "type":"Manufacturing & Wholesale Goods"
        }
    ],
    "sg:phone":"+1 956 581 3963",
    "sg:postcode":"78572",
    "sg:province":"TX",
    "sg:tags":[
        "representative",
        "manufacturer"
    ],
    "wof:name":"Bpam Inc",
    "wof:placetype":"venue"
},
  "geometry": {"coordinates":[-98.290054,26.224983],"type":"Point"}
}