{
  "type": "Feature",
  "properties": {
    "iso:country":"US",
    "sg:address":"801 Shady Oaks Dr",
    "sg:city":"Southlake",
    "sg:classifiers":[
        {
            "category":"Education",
            "subcategory":"Special Training",
            "type":"Public Place"
        },
        {
            "category":"Education",
            "subcategory":"Preschool",
            "type":"Public Place"
        },
        {
            "category":"Education",
            "subcategory":"School",
            "type":"Public Place"
        }
    ],
    "sg:phone":"+1 817 949 4400",
    "sg:postcode":"76092",
    "sg:province":"TX",
    "sg:tags":[
        "kindergarten",
        "educational",
        "elementary"
    ],
    "sg:website":"http://www.southlakecarroll.edu",
    "wof:name":"Durham Elementary School",
    "wof:placetype":"venue"
},
  "geometry": {"coordinates":[-97.159691,32.950658],"type":"Point"}
}