{
  "type": "Feature",
  "properties": {
    "iso:country":"US",
    "sg:address":"19327 Amistad Dr",
    "sg:city":"Tomball",
    "sg:classifiers":[
        {
            "category":"Building & Trades",
            "subcategory":"Landscaping Services",
            "type":"Services"
        }
    ],
    "sg:phone":"+1 281 290 8220",
    "sg:postcode":"77375",
    "sg:province":"TX",
    "wof:name":"Z&C Lawn Care",
    "wof:placetype":"venue"
},
  "geometry": {"coordinates":[-95.605355,30.046303],"type":"Point"}
}