{
  "type": "Feature",
  "properties": {
    "iso:country":"US",
    "sg:address":"818 W Ennis Ave",
    "sg:city":"Ennis",
    "sg:classifiers":[
        {
            "category":"Health Services",
            "subcategory":"Clinic",
            "type":"Services"
        }
    ],
    "sg:phone":"+1 972 875 8469",
    "sg:postcode":"75119",
    "sg:province":"TX",
    "sg:tags":[
        "kidney",
        "dialysis",
        "center"
    ],
    "wof:name":"Bio-Mdcal Applcations of Ennis",
    "wof:placetype":"venue"
},
  "geometry": {"coordinates":[-96.633861,32.324479],"type":"Point"}
}