{
  "type": "Feature",
  "properties": {
    "iso:country":"US",
    "sg:address":"1620 Thomas Ln, Suite D",
    "sg:city":"Carrollton",
    "sg:phone":"+1 571 426 9990",
    "sg:postcode":"75010",
    "sg:province":"TX",
    "sg:website":"http://dbuttercoookies.com",
    "wof:name":"D's Gourmet Butter Cookies",
    "wof:placetype":"venue"
},
  "geometry": {"coordinates":[-96.936841,33.033369],"type":"Point"}
}