{
  "type": "Feature",
  "properties": {
    "iso:country":"US",
    "sg:address":"2903 Post Oak Ln",
    "sg:city":"Mc Kinney",
    "sg:classifiers":[
        {
            "category":"Professional",
            "subcategory":"Engineering",
            "type":"Services"
        }
    ],
    "sg:phone":"+1 972 548 8182",
    "sg:postcode":"75070",
    "sg:province":"TX",
    "wof:name":"Sentanova Design Services",
    "wof:placetype":"venue"
},
  "geometry": {"coordinates":[-96.654256,33.197131],"type":"Point"}
}