{
  "type": "Feature",
  "properties": {
    "iso:country":"US",
    "sg:address":"2219 Fitzhugh St",
    "sg:city":"Lancaster",
    "sg:classifiers":[
        {
            "category":"Building & Trades",
            "subcategory":"Construction",
            "type":"Services"
        }
    ],
    "sg:phone":"+1 972 227 8091",
    "sg:postcode":"75146",
    "sg:province":"TX",
    "wof:name":"Hodges Asphalt and Paving",
    "wof:placetype":"venue"
},
  "geometry": {"coordinates":[-96.80204999999999,32.599727],"type":"Point"}
}