{
  "type": "Feature",
  "properties": {
    "iso:country":"US",
    "sg:address":"7500 Stonebrook Pkwy",
    "sg:city":"Frisco",
    "sg:classifiers":[
        {
            "category":"Health Services",
            "subcategory":"Doctor",
            "type":"Services"
        }
    ],
    "sg:phone":"+1 972 377 7117",
    "sg:postcode":"75034",
    "sg:province":"TX",
    "sg:tags":[
        "medical"
    ],
    "wof:name":"Stonebrook Family Chiropractic",
    "wof:placetype":"venue"
},
  "geometry": {"coordinates":[-96.820325,33.136814],"type":"Point"}
}