{
  "type": "Feature",
  "properties": {
    "iso:country":"US",
    "sg:address":"700 E 8th St",
    "sg:city":"Odessa",
    "sg:classifiers":[
        {
            "category":"Health Services",
            "subcategory":"Medical Lab",
            "type":"Services"
        }
    ],
    "sg:phone":"+1 432 582 0000",
    "sg:postcode":"79761",
    "sg:province":"TX",
    "sg:tags":[
        "info",
        "pathology",
        "speech",
        "language"
    ],
    "wof:name":"Clinical Pathology Labs Inc",
    "wof:placetype":"venue"
},
  "geometry": {"coordinates":[-102.36453899999999,31.854643],"type":"Point"}
}