{
  "type": "Feature",
  "properties": {
    "iso:country":"US",
    "sg:address":"12859 Kimberley Ln",
    "sg:city":"Houston",
    "sg:classifiers":[
        {
            "category":"Banks & Credit Unions",
            "subcategory":"Bank",
            "type":"Services"
        }
    ],
    "sg:phone":"+1 713 461 8707",
    "sg:postcode":"77024",
    "sg:province":"TX",
    "sg:website":"www.wachovia.com",
    "wof:name":"Wachovia",
    "wof:placetype":"venue"
},
  "geometry": {"coordinates":[-95.561537,29.77587],"type":"Point"}
}