{
  "type": "Feature",
  "properties": {
    "iso:country":"US",
    "sg:address":"7100 Regency Square Blvd Ste 289",
    "sg:city":"Houston",
    "sg:classifiers":[
        {
            "category":"Health Services",
            "subcategory":"Health Practitioner",
            "type":"Services"
        }
    ],
    "sg:phone":"+1 713 840 9355",
    "sg:postcode":"77036",
    "sg:province":"TX",
    "sg:tags":[
        "naturopathic/holistic"
    ],
    "wof:name":"The Whole Health Center",
    "wof:placetype":"venue"
},
  "geometry": {"coordinates":[-95.507615,29.716449],"type":"Point"}
}