{
  "type": "Feature",
  "properties": {
    "iso:country":"US",
    "sg:address":"1673 Briarcrest Dr",
    "sg:city":"Bryan",
    "sg:classifiers":[
        {
            "category":"Professional",
            "type":"Services"
        }
    ],
    "sg:phone":"+1 979 776 9757",
    "sg:postcode":"77802",
    "sg:province":"TX",
    "sg:tags":[
        "establishment"
    ],
    "wof:name":"Peirson & Patterson",
    "wof:placetype":"venue"
},
  "geometry": {"coordinates":[-96.34328499999999,30.650606],"type":"Point"}
}