{
  "type": "Feature",
  "properties": {
    "iso:country":"US",
    "sg:address":"821 Brooks Ave",
    "sg:city":"Schertz",
    "sg:classifiers":[
        {
            "category":"Building & Trades",
            "subcategory":"Construction",
            "type":"Services"
        }
    ],
    "sg:phone":"+1 210 658 4178",
    "sg:postcode":"78154",
    "sg:province":"TX",
    "sg:tags":[
        "house"
    ],
    "wof:name":"Quality Remodeling",
    "wof:placetype":"venue"
},
  "geometry": {"coordinates":[-98.26812,29.55955],"type":"Point"}
}