{
  "type": "Feature",
  "properties": {
    "iso:country":"US",
    "sg:address":"5002 S 14th St",
    "sg:city":"Abilene",
    "sg:classifiers":[
        {
            "category":"Autos & Motor Vehicles",
            "subcategory":"Auto Supplies",
            "type":"Retail Goods"
        }
    ],
    "sg:phone":"+1 325 695 1950",
    "sg:postcode":"79605",
    "sg:province":"TX",
    "sg:tags":[
        "tire"
    ],
    "wof:name":"Arnold's Tire & Service",
    "wof:placetype":"venue"
},
  "geometry": {"coordinates":[-99.784252,32.428616],"type":"Point"}
}