{
  "type": "Feature",
  "properties": {
    "iso:country":"US",
    "sg:address":"2626 Club Meadow Dr",
    "sg:city":"Garland",
    "sg:classifiers":[
        {
            "category":"Professional",
            "subcategory":"Employment Agencies",
            "type":"Services"
        }
    ],
    "sg:phone":"+1 972 840 3273",
    "sg:postcode":"75043",
    "sg:province":"TX",
    "sg:tags":[
        "executive",
        "placement"
    ],
    "wof:name":"Cooper",
    "wof:placetype":"venue"
},
  "geometry": {"coordinates":[-96.60615199999999,32.886672],"type":"Point"}
}