{
  "type": "Feature",
  "properties": {
    "iso:country":"US",
    "sg:address":"2509 Plantation Dr",
    "sg:city":"Round Rock",
    "sg:classifiers":[
        {
            "category":"Professional",
            "subcategory":"Management & Consulting",
            "type":"Services"
        }
    ],
    "sg:phone":"+1 512 825 8700",
    "sg:postcode":"78681",
    "sg:province":"TX",
    "sg:tags":[
        "public",
        "relations"
    ],
    "wof:name":"Silicon Image",
    "wof:placetype":"venue"
},
  "geometry": {"coordinates":[-97.706794,30.535265],"type":"Point"}
}