{
  "type": "Feature",
  "properties": {
    "iso:country":"US",
    "sg:address":"204 Padre Blvd",
    "sg:city":"South Padre Island",
    "sg:classifiers":[
        {
            "category":"Professional",
            "subcategory":"Business Services",
            "type":"Services"
        }
    ],
    "sg:phone":"+1 956 761 8411",
    "sg:postcode":"78597",
    "sg:province":"TX",
    "wof:name":"Border Town Enterprises",
    "wof:placetype":"venue"
},
  "geometry": {"coordinates":[-97.165668,26.079531],"type":"Point"}
}