{
  "type": "Feature",
  "properties": {
    "iso:country":"US",
    "sg:address":"6500 FM 1464",
    "sg:city":"Clodine",
    "sg:classifiers":[
        {
            "category":"Real Estate",
            "subcategory":"Real Estate Agent",
            "type":"Services"
        }
    ],
    "sg:phone":"+1 281 277 3452",
    "sg:postcode":"77469",
    "sg:province":"TX",
    "wof:name":"Nemec Co",
    "wof:placetype":"venue"
},
  "geometry": {"coordinates":[-95.688125,29.707364],"type":"Point"}
}