{
  "type": "Feature",
  "properties": {
    "iso:country":"US",
    "sg:address":"84 N.E Loop 410 Suite 325",
    "sg:city":"San Antonio",
    "sg:classifiers":[
        {
            "category":"Professional",
            "subcategory":"Computer Services",
            "type":"Services"
        }
    ],
    "sg:phone":"+1 210 789 0369",
    "sg:postcode":"78239",
    "sg:province":"TX",
    "sg:tags":[
        "wordpress",
        "hosting",
        "managed-wordpress-hosting"
    ],
    "sg:website":"http://zippykid.com/",
    "wof:name":"ZippyKid",
    "wof:placetype":"venue"
},
  "geometry": {"coordinates":[-98.493775,29.520078],"type":"Point"}
}