{
  "type": "Feature",
  "properties": {
    "iso:country":"US",
    "sg:address":"20630 State Hwy 64",
    "sg:city":"Canton",
    "sg:classifiers":[
        {
            "category":"Building & Trades",
            "subcategory":"Equipment Rental",
            "type":"Services"
        }
    ],
    "sg:phone":"+1 903 567 7300",
    "sg:postcode":"75103",
    "sg:province":"TX",
    "sg:tags":[
        "yard"
    ],
    "wof:name":"Canton Equipment Rentals",
    "wof:placetype":"venue"
},
  "geometry": {"coordinates":[-95.77820699999999,32.498978],"type":"Point"}
}