{
  "type": "Feature",
  "properties": {
    "iso:country":"US",
    "sg:address":"12709 Palfrey Dr",
    "sg:city":"Austin",
    "sg:classifiers":[
        {
            "category":"Personal",
            "type":"Services"
        }
    ],
    "sg:phone":"+1 512 388 0757",
    "sg:postcode":"78727",
    "sg:province":"TX",
    "sg:tags":[
        "therapist",
        "massage"
    ],
    "wof:name":"Spirit Of Grace",
    "wof:placetype":"venue"
},
  "geometry": {"coordinates":[-97.706684,30.425618],"type":"Point"}
}