{
  "type": "Feature",
  "properties": {
    "iso:country":"US",
    "sg:address":"2223 Burton Dr",
    "sg:city":"Austin",
    "sg:classifiers":[
        {
            "category":"Professional",
            "type":"Services"
        }
    ],
    "sg:phone":"+1 512 383 9530",
    "sg:postcode":"78741",
    "sg:province":"TX",
    "wof:name":"A Magic Pleasure Grameroom",
    "wof:placetype":"venue"
},
  "geometry": {"coordinates":[-97.732106,30.232982],"type":"Point"}
}