{
  "type": "Feature",
  "properties": {
    "iso:country":"US",
    "sg:address":"2710 N Stemmons Fwy",
    "sg:city":"Dallas",
    "sg:classifiers":[
        {
            "category":"Professional",
            "subcategory":"Lawyer & Legal Services",
            "type":"Services"
        }
    ],
    "sg:phone":"+1 214 770 7251",
    "sg:postcode":"75207",
    "sg:province":"TX",
    "wof:name":"Hammerle Finley Law Firm",
    "wof:placetype":"venue"
},
  "geometry": {"coordinates":[-96.843498,32.808498],"type":"Point"}
}