{
  "type": "Feature",
  "properties": {
    "iso:country":"US",
    "sg:address":"9519 Twilight Moon Dr",
    "sg:city":"Houston",
    "sg:classifiers":[
        {
            "category":"Professional",
            "type":"Services"
        }
    ],
    "sg:phone":"+1 281 970 3493",
    "sg:postcode":"77064",
    "sg:province":"TX",
    "sg:tags":[
        "establishment"
    ],
    "wof:name":"At&T Cits",
    "wof:placetype":"venue"
},
  "geometry": {"coordinates":[-95.565596,29.925575],"type":"Point"}
}