{
  "type": "Feature",
  "properties": {
    "iso:country":"US",
    "sg:address":"3511 E State Hwy 158",
    "sg:city":"Midland",
    "sg:classifiers":[
        {
            "category":"Mining & Drilling",
            "type":"Manufacturing & Wholesale Goods"
        }
    ],
    "sg:phone":"+1 432 684 6681",
    "sg:postcode":"79706",
    "sg:province":"TX",
    "sg:tags":[
        "field",
        "oil"
    ],
    "wof:name":"Butch's Rathole & Anchor Svc",
    "wof:placetype":"venue"
},
  "geometry": {"coordinates":[-102.008955,31.974548],"type":"Point"}
}