{
  "type": "Feature",
  "properties": {
    "iso:country":"US",
    "sg:address":"1000 N Main St",
    "sg:city":"Mansfield",
    "sg:classifiers":[
        {
            "category":"Wholesale",
            "subcategory":"Electrical",
            "type":"Manufacturing & Wholesale Goods"
        }
    ],
    "sg:phone":"+1 817 804 3800",
    "sg:postcode":"76063",
    "sg:province":"TX",
    "sg:tags":[
        "electronic",
        "component"
    ],
    "wof:name":"Mouser Electronics Inc",
    "wof:placetype":"venue"
},
  "geometry": {"coordinates":[-97.146677,32.576318],"type":"Point"}
}