{
  "type": "Feature",
  "properties": {
    "iso:country":"US",
    "sg:address":"4625 Old Agnes Rd",
    "sg:city":"Weatherford",
    "sg:classifiers":[
        {
            "category":"Manufacturing",
            "subcategory":"Rubber & Plastics",
            "type":"Manufacturing & Wholesale Goods"
        }
    ],
    "sg:phone":"+1 817 613 9233",
    "sg:postcode":"76088",
    "sg:province":"TX",
    "sg:tags":[
        "product",
        "mfg"
    ],
    "wof:name":"John W Stoltz Co",
    "wof:placetype":"venue"
},
  "geometry": {"coordinates":[-97.788977,32.904486],"type":"Point"}
}