{
  "type": "Feature",
  "properties": {
    "iso:country":"US",
    "sg:address":"2301 Hayes Rd",
    "sg:city":"Houston",
    "sg:classifiers":[
        {
            "category":"Professional",
            "subcategory":"Credit Reporting & Collection",
            "type":"Services"
        }
    ],
    "sg:phone":"+1 713 532 0332",
    "sg:postcode":"77077",
    "sg:province":"TX",
    "wof:name":"Dianne C Nelson",
    "wof:placetype":"venue"
},
  "geometry": {"coordinates":[-95.576207,29.73967],"type":"Point"}
}