{
  "type": "Feature",
  "properties": {
    "iso:country":"US",
    "sg:address":"7530 Mary Dan Dr",
    "sg:city":"Dallas",
    "sg:classifiers":[
        {
            "category":"Building & Trades",
            "subcategory":"Construction",
            "type":"Services"
        }
    ],
    "sg:phone":"+1 214 398 9265",
    "sg:postcode":"75217",
    "sg:province":"TX",
    "sg:tags":[
        "concrete",
        "contractor"
    ],
    "wof:name":"Magic Inlets Concrete",
    "wof:placetype":"venue"
},
  "geometry": {"coordinates":[-96.69000699999999,32.728595],"type":"Point"}
}