{
  "type": "Feature",
  "properties": {
    "iso:country":"US",
    "sg:address":"11550 N North Loop Rd",
    "sg:city":"San Antonio",
    "sg:classifiers":[
        {
            "category":"Wholesale",
            "subcategory":"Machinery & Supplies",
            "type":"Manufacturing & Wholesale Goods"
        },
        {
            "category":"Wholesale",
            "subcategory":"Scrap",
            "type":"Manufacturing & Wholesale Goods"
        }
    ],
    "sg:phone":"+1 210 494 3466",
    "sg:postcode":"78216",
    "sg:province":"TX",
    "sg:tags":[
        "aircraft",
        "parts",
        "salvage"
    ],
    "sg:website":"www.tradewindsac.com",
    "wof:name":"Tradewinds Aircraft Supply Inc",
    "wof:placetype":"venue"
},
  "geometry": {"coordinates":[-98.48945500000001,29.55015],"type":"Point"}
}