{
  "type": "Feature",
  "properties": {
    "iso:country":"US",
    "sg:address":"2626 Gus Thomasson Rd",
    "sg:city":"Dallas",
    "sg:classifiers":[
        {
            "category":"Organizations",
            "subcategory":"Religious Organization",
            "type":"Services"
        }
    ],
    "sg:phone":"+1 214 324 3040",
    "sg:postcode":"75228",
    "sg:province":"TX",
    "sg:tags":[
        "church"
    ],
    "wof:name":"Intercessory Prayer Room",
    "wof:placetype":"venue"
},
  "geometry": {"coordinates":[-96.668622,32.834681],"type":"Point"}
}