{
  "type": "Feature",
  "properties": {
    "iso:country":"US",
    "sg:address":"13651 Montfort Dr",
    "sg:city":"Dallas",
    "sg:classifiers":[
        {
            "category":"Banks & Credit Unions",
            "subcategory":"Bank",
            "type":"Services"
        }
    ],
    "sg:phone":"+1 214 748 9393",
    "sg:postcode":"75240",
    "sg:province":"TX",
    "wof:name":"Neighborhood Credit Union",
    "wof:placetype":"venue"
},
  "geometry": {"coordinates":[-96.789299,32.935299],"type":"Point"}
}