{
  "type": "Feature",
  "properties": {
    "iso:country":"US",
    "sg:address":"223 Mango Rd",
    "sg:city":"El Paso",
    "sg:classifiers":[
        {
            "category":"Shopping",
            "subcategory":"Clothing, Apparel, & Fashions",
            "type":"Retail Goods"
        }
    ],
    "sg:phone":"+1 915 775 1316",
    "sg:postcode":"79915",
    "sg:province":"TX",
    "wof:name":"Players Style Clothing",
    "wof:placetype":"venue"
},
  "geometry": {"coordinates":[-106.384035,31.736275],"type":"Point"}
}