{
  "type": "Feature",
  "properties": {
    "iso:country":"US",
    "sg:address":"1401 Ransom St",
    "sg:city":"Pflugerville",
    "sg:classifiers":[
        {
            "category":"Building & Trades",
            "subcategory":"Construction",
            "type":"Services"
        }
    ],
    "sg:phone":"+1 512 251 5566",
    "sg:postcode":"78660",
    "sg:province":"TX",
    "sg:tags":[
        "house"
    ],
    "wof:name":"Mtc Home Remodeling & Repairs",
    "wof:placetype":"venue"
},
  "geometry": {"coordinates":[-97.662741,30.446481],"type":"Point"}
}