{
  "type": "Feature",
  "properties": {
    "iso:country":"US",
    "sg:address":"1110 E Main St",
    "sg:city":"League City",
    "sg:classifiers":[
        {
            "category":"Personal",
            "subcategory":"Beauty Salon",
            "type":"Services"
        }
    ],
    "sg:phone":"+1 281 557 0121",
    "sg:postcode":"77573",
    "sg:province":"TX",
    "sg:tags":[
        "shop",
        "equipment",
        "establishment"
    ],
    "wof:name":"N F Beauty Salon",
    "wof:placetype":"venue"
},
  "geometry": {"coordinates":[-95.085823,29.51471],"type":"Point"}
}