{
  "type": "Feature",
  "properties": {
    "iso:country":"US",
    "sg:address":"1652 Vassar St",
    "sg:city":"Houston",
    "sg:classifiers":[
        {
            "category":"Professional",
            "type":"Services"
        },
        {
            "category":"Professional",
            "subcategory":"Secretarial Services",
            "type":"Services"
        }
    ],
    "sg:phone":"+1 713 521 0768",
    "sg:postcode":"77006",
    "sg:province":"TX",
    "sg:tags":[
        "writer",
        "reporting"
    ],
    "wof:name":"Barbara Eaves Writing & Mktng",
    "wof:placetype":"venue"
},
  "geometry": {"coordinates":[-95.40089500000001,29.730489],"type":"Point"}
}