{
  "type": "Feature",
  "properties": {
    "iso:country":"US",
    "sg:address":"7909 Powerline Rd",
    "sg:city":"Richmond",
    "sg:classifiers":[
        {
            "category":"Building & Trades",
            "subcategory":"Construction",
            "type":"Services"
        }
    ],
    "sg:phone":"+1 281 341 0998",
    "sg:postcode":"77469",
    "sg:province":"TX",
    "sg:tags":[
        "residential",
        "bu",
        "industrial",
        "contractor"
    ],
    "wof:name":"Champion Construction",
    "wof:placetype":"venue"
},
  "geometry": {"coordinates":[-95.76320699999999,29.486279],"type":"Point"}
}