{
  "type": "Feature",
  "properties": {
    "iso:country":"US",
    "sg:address":"604 Catalina Dr",
    "sg:city":"Waco",
    "sg:classifiers":[
        {
            "category":"Health Services",
            "subcategory":"Clinic",
            "type":"Services"
        }
    ],
    "sg:phone":"+1 254 776 1652",
    "sg:postcode":"76712",
    "sg:province":"TX",
    "sg:tags":[
        "organization",
        "maintenance"
    ],
    "wof:name":"Association Field Svc",
    "wof:placetype":"venue"
},
  "geometry": {"coordinates":[-97.208793,31.517638],"type":"Point"}
}