{
  "type": "Feature",
  "properties": {
    "iso:country":"US",
    "sg:address":"1421 West St",
    "sg:city":"Rosenberg",
    "sg:classifiers":[
        {
            "category":"Organizations",
            "subcategory":"Religious Organization",
            "type":"Services"
        }
    ],
    "sg:phone":"+1 281 239 0141",
    "sg:postcode":"77471",
    "sg:province":"TX",
    "sg:tags":[
        "church"
    ],
    "wof:name":"New Beginnings Christian Ctr",
    "wof:placetype":"venue"
},
  "geometry": {"coordinates":[-95.814123,29.553779],"type":"Point"}
}