{
  "type": "Feature",
  "properties": {
    "iso:country":"US",
    "sg:address":"430 Lexington Ln",
    "sg:city":"Richardson",
    "sg:classifiers":[
        {
            "category":"Building & Trades",
            "subcategory":"Construction",
            "type":"Services"
        }
    ],
    "sg:phone":"+1 972 231 1540",
    "sg:postcode":"75080",
    "sg:province":"TX",
    "sg:tags":[
        "nonresidential",
        "contractor"
    ],
    "wof:name":"Roofing",
    "wof:placetype":"venue"
},
  "geometry": {"coordinates":[-96.732877,32.971337],"type":"Point"}
}