{
  "type": "Feature",
  "properties": {
    "iso:country":"US",
    "sg:address":"6873 Chickering Rd",
    "sg:city":"Fort Worth",
    "sg:classifiers":[
        {
            "category":"Retail",
            "subcategory":"Repair Shop",
            "type":"Services"
        }
    ],
    "sg:phone":"+1 817 909 7591",
    "sg:postcode":"76116",
    "sg:province":"TX",
    "wof:name":"Drain Man",
    "wof:placetype":"venue"
},
  "geometry": {"coordinates":[-97.431927,32.70627],"type":"Point"}
}