{
  "type": "Feature",
  "properties": {
    "iso:country":"US",
    "sg:address":"3936 E Everglade Ave",
    "sg:city":"Odessa",
    "sg:classifiers":[
        {
            "category":"Professional",
            "subcategory":"Computer Services",
            "type":"Services"
        }
    ],
    "sg:phone":"+1 432 550 6517",
    "sg:postcode":"79762",
    "sg:province":"TX",
    "wof:name":"Laptop Rentals & Services",
    "wof:placetype":"venue"
},
  "geometry": {"coordinates":[-102.34526200000001,31.886593],"type":"Point"}
}