{
  "type": "Feature",
  "properties": {
    "iso:country":"US",
    "sg:address":"1425 State Hwy 75",
    "sg:city":"Huntsville",
    "sg:classifiers":[
        {
            "category":"Local Transit",
            "type":"Transportation"
        }
    ],
    "sg:phone":"+1 936 295 7665",
    "sg:postcode":"77320",
    "sg:province":"TX",
    "sg:tags":[
        "ambulance"
    ],
    "wof:name":"Medpro Emergency Medical Svc",
    "wof:placetype":"venue"
},
  "geometry": {"coordinates":[-95.551331,30.720036],"type":"Point"}
}