{
  "type": "Feature",
  "properties": {
    "iso:country":"US",
    "sg:address":"1617 E Commerce St",
    "sg:city":"San Antonio",
    "sg:classifiers":[
        {
            "category":"Professional",
            "subcategory":"Art Services",
            "type":"Services"
        }
    ],
    "sg:phone":"+1 210 444 2319",
    "sg:postcode":"78205",
    "sg:province":"TX",
    "sg:tags":[
        "commercial",
        "design"
    ],
    "wof:name":"Mighty Studio",
    "wof:placetype":"venue"
},
  "geometry": {"coordinates":[-98.47043600000001,29.419942],"type":"Point"}
}