{
  "type": "Feature",
  "properties": {
    "iso:country":"US",
    "sg:address":"2563 Sunset Dr",
    "sg:city":"San Angelo",
    "sg:classifiers":[
        {
            "category":"Restaurant",
            "type":"Food & Drink"
        }
    ],
    "sg:phone":"+1 325 944 3417",
    "sg:postcode":"76904",
    "sg:province":"TX",
    "sg:tags":[
        "delicatessen"
    ],
    "wof:name":"Tumble Weedz Deli Bakery Ctrng",
    "wof:placetype":"venue"
},
  "geometry": {"coordinates":[-100.47250200000001,31.421435],"type":"Point"}
}