{
  "type": "Feature",
  "properties": {
    "iso:country":"US",
    "sg:address":"632 N Ed Carey Dr",
    "sg:city":"Harlingen",
    "sg:classifiers":[
        {
            "category":"Health Services",
            "subcategory":"Doctor",
            "type":"Services"
        }
    ],
    "sg:phone":"+1 956 421 2665",
    "sg:postcode":"78550",
    "sg:province":"TX",
    "sg:tags":[
        "physician",
        "surgeon"
    ],
    "wof:name":"Charles T Folsom MD",
    "wof:placetype":"venue"
},
  "geometry": {"coordinates":[-97.663082,26.210175],"type":"Point"}
}