{
  "type": "Feature",
  "properties": {
    "iso:country":"US",
    "sg:address":"3602 Mohegan Dr",
    "sg:city":"San Antonio",
    "sg:classifiers":[
        {
            "category":"Retail",
            "subcategory":"Auto Repair",
            "type":"Services"
        }
    ],
    "sg:phone":"+1 210 735 2866",
    "sg:postcode":"78228",
    "sg:province":"TX",
    "sg:tags":[
        "general"
    ],
    "wof:name":"Slayden Auto Accent Trim",
    "wof:placetype":"venue"
},
  "geometry": {"coordinates":[-98.555819,29.478683],"type":"Point"}
}