{
  "type": "Feature",
  "properties": {
    "iso:country":"US",
    "sg:address":"2174 Co Rd 53",
    "sg:city":"Corpus Christi",
    "sg:classifiers":[
        {
            "category":"Shopping",
            "subcategory":"Gifts & Souvenirs",
            "type":"Retail Goods"
        }
    ],
    "sg:phone":"+1 361 852 8497",
    "sg:postcode":"78415",
    "sg:province":"TX",
    "wof:name":"3 B Enterprizes",
    "wof:placetype":"venue"
},
  "geometry": {"coordinates":[-97.51955,27.660359],"type":"Point"}
}