{
  "type": "Feature",
  "properties": {
    "iso:country":"US",
    "sg:address":"12600 Brookglade Cir",
    "sg:city":"Houston",
    "sg:classifiers":[
        {
            "category":"Shopping",
            "subcategory":"Gifts & Souvenirs",
            "type":"Retail Goods"
        }
    ],
    "sg:phone":"+1 281 933 5240",
    "sg:postcode":"77099",
    "sg:province":"TX",
    "sg:tags":[
        "shop"
    ],
    "wof:name":"Debbie's Joys & Gifts",
    "wof:placetype":"venue"
},
  "geometry": {"coordinates":[-95.60050099999999,29.679741],"type":"Point"}
}