{
  "type": "Feature",
  "properties": {
    "iso:country":"US",
    "sg:address":"5303 Rolling Hls",
    "sg:city":"Texarkana",
    "sg:classifiers":[
        {
            "category":"Wholesale",
            "subcategory":"Non-durable Goods",
            "type":"Manufacturing & Wholesale Goods"
        }
    ],
    "sg:phone":"+1 903 831 7536",
    "sg:postcode":"75503",
    "sg:province":"TX",
    "sg:tags":[
        "dry",
        "goods-wholesale"
    ],
    "wof:name":"D S Machinery Supply",
    "wof:placetype":"venue"
},
  "geometry": {"coordinates":[-94.124769,33.48948],"type":"Point"}
}