{
  "type": "Feature",
  "properties": {
    "iso:country":"US",
    "sg:address":"120 E Lufkin Ave",
    "sg:city":"Lufkin",
    "sg:classifiers":[
        {
            "category":"Professional",
            "type":"Services"
        }
    ],
    "sg:phone":"+1 936 699 2213",
    "sg:postcode":"75901",
    "sg:province":"TX",
    "sg:tags":[
        "establishment"
    ],
    "wof:name":"Lufkin District Office Umc",
    "wof:placetype":"venue"
},
  "geometry": {"coordinates":[-94.728661,31.33896],"type":"Point"}
}