{
  "type": "Feature",
  "properties": {
    "iso:country":"US",
    "sg:address":"811 Central Dr",
    "sg:city":"Colleyville",
    "sg:classifiers":[
        {
            "category":"Food & Beverages",
            "subcategory":"Specialty",
            "type":"Retail Goods"
        }
    ],
    "sg:phone":"+1 817 577 0179",
    "sg:postcode":"76034",
    "sg:province":"TX",
    "wof:name":"H2o Store The",
    "wof:placetype":"venue"
},
  "geometry": {"coordinates":[-97.15601599999999,32.887134],"type":"Point"}
}