{
  "type": "Feature",
  "properties": {
    "iso:country":"US",
    "sg:address":"1202 Charisse St",
    "sg:city":"Killeen",
    "sg:classifiers":[
        {
            "category":"Professional",
            "type":"Services"
        }
    ],
    "sg:phone":"+1 254 680 1734",
    "sg:postcode":"76543",
    "sg:province":"TX",
    "wof:name":"Jrz Audio",
    "wof:placetype":"venue"
},
  "geometry": {"coordinates":[-97.698714,31.097409],"type":"Point"}
}