{
  "type": "Feature",
  "properties": {
    "iso:country":"US",
    "sg:address":"1505 109th St",
    "sg:city":"Grand Prairie",
    "sg:classifiers":[
        {
            "category":"Manufacturing",
            "subcategory":"Chemicals & Compounds",
            "type":"Manufacturing & Wholesale Goods"
        }
    ],
    "sg:phone":"+1 972 647 1641",
    "sg:postcode":"75050",
    "sg:province":"TX",
    "sg:tags":[
        "printing",
        "ink"
    ],
    "wof:name":"Sun Chemical Ink",
    "wof:placetype":"venue"
},
  "geometry": {"coordinates":[-97.053236,32.774909],"type":"Point"}
}