{
  "type": "Feature",
  "properties": {
    "iso:country":"US",
    "sg:address":"9100 Forest Crossing Dr",
    "sg:city":"Spring",
    "sg:classifiers":[
        {
            "category":"Health Services",
            "subcategory":"Doctor",
            "type":"Services"
        }
    ],
    "sg:phone":"+1 281 363 1571",
    "sg:postcode":"77381",
    "sg:province":"TX",
    "sg:tags":[
        "dentist"
    ],
    "wof:name":"W Bryon Satterfield DDS",
    "wof:placetype":"venue"
},
  "geometry": {"coordinates":[-95.48783899999999,30.182425],"type":"Point"}
}