{
  "type": "Feature",
  "properties": {
    "iso:country":"US",
    "sg:address":"826 Martin Rd",
    "sg:city":"Amarillo",
    "sg:classifiers":[
        {
            "category":"Health Services",
            "subcategory":"Optometrist",
            "type":"Services"
        }
    ],
    "sg:phone":"+1 806 373 0502",
    "sg:postcode":"79107",
    "sg:province":"TX",
    "sg:tags":[
        "optometry",
        "doctor"
    ],
    "wof:name":"Martindale Eye Care Center",
    "wof:placetype":"venue"
},
  "geometry": {"coordinates":[-101.812023,35.225446],"type":"Point"}
}