{
  "type": "Feature",
  "properties": {
    "iso:country":"US",
    "sg:address":"156 Quail Run",
    "sg:city":"Odessa",
    "sg:classifiers":[
        {
            "category":"Insurance",
            "subcategory":"Insurance Agent",
            "type":"Services"
        }
    ],
    "sg:phone":"+1 432 367 7539",
    "sg:postcode":"79761",
    "sg:province":"TX",
    "sg:tags":[
        "appraisal",
        "damage"
    ],
    "wof:name":"Property Damagey Appraisers",
    "wof:placetype":"venue"
},
  "geometry": {"coordinates":[-102.31549800000001,31.878219],"type":"Point"}
}