{
  "type": "Feature",
  "properties": {
    "iso:country":"US",
    "sg:address":"570 FM 2295",
    "sg:city":"Alice",
    "sg:classifiers":[
        {
            "category":"Food & Beverages",
            "subcategory":"Groceries & Convenience Stores",
            "type":"Retail Goods"
        }
    ],
    "sg:phone":"+1 361 256 4141",
    "sg:postcode":"78332",
    "sg:province":"TX",
    "wof:name":"Gonzalitoz Grocery",
    "wof:placetype":"venue"
},
  "geometry": {"coordinates":[-98.111009,27.553584],"type":"Point"}
}