{
  "type": "Feature",
  "properties": {
    "iso:country":"US",
    "sg:address":"2926 State Hwy 36",
    "sg:city":"Gatesville",
    "sg:classifiers":[
        {
            "category":"Wholesale",
            "subcategory":"Construction Materials",
            "type":"Manufacturing & Wholesale Goods"
        }
    ],
    "sg:phone":"+1 254 248 4171",
    "sg:postcode":"76528",
    "sg:province":"TX",
    "sg:tags":[
        "sand",
        "gravel"
    ],
    "wof:name":"Grib's Septic Tank Svc",
    "wof:placetype":"venue"
},
  "geometry": {"coordinates":[-97.714471,31.42072],"type":"Point"}
}