{
  "type": "Feature",
  "properties": {
    "iso:country":"US",
    "sg:address":"3114 Morgan Ave",
    "sg:city":"Corpus Christi",
    "sg:classifiers":[
        {
            "category":"Food & Beverages",
            "subcategory":"Meat & Fish",
            "type":"Retail Goods"
        },
        {
            "category":"Wholesale",
            "subcategory":"Meat",
            "type":"Manufacturing & Wholesale Goods"
        }
    ],
    "sg:phone":"+1 361 884 8118",
    "sg:postcode":"78405",
    "sg:province":"TX",
    "wof:name":"Penas' Meat Market",
    "wof:placetype":"venue"
},
  "geometry": {"coordinates":[-97.423892,27.777967],"type":"Point"}
}