{
  "type": "Feature",
  "properties": {
    "iso:country":"US",
    "sg:address":"1410 Starpoint Ln",
    "sg:city":"Wylie",
    "sg:classifiers":[
        {
            "category":"Building & Trades",
            "subcategory":"Landscaping Services",
            "type":"Services"
        }
    ],
    "sg:phone":"+1 972 429 4185",
    "sg:postcode":"75098",
    "sg:province":"TX",
    "wof:name":"Etc Lawn & Landscape",
    "wof:placetype":"venue"
},
  "geometry": {"coordinates":[-96.564263,33.039778],"type":"Point"}
}