{
  "type": "Feature",
  "properties": {
    "iso:country":"US",
    "sg:address":"701 E Campbell Rd",
    "sg:city":"Richardson",
    "sg:classifiers":[
        {
            "category":"Travel",
            "subcategory":"Hotels & Motels",
            "type":"Entertainment"
        },
        {
            "category":"Restaurant",
            "type":"Food & Drink"
        }
    ],
    "sg:phone":"+1 972 231 9600",
    "sg:postcode":"75081",
    "sg:province":"TX",
    "sg:website":"www.therichardsonhotel.com",
    "wof:name":"The Richardson Hotel",
    "wof:placetype":"venue"
},
  "geometry": {"coordinates":[-96.715103,32.975399],"type":"Point"}
}