{
  "type": "Feature",
  "properties": {
    "iso:country":"US",
    "sg:address":"1708 Toronto Ave",
    "sg:city":"Mcallen",
    "sg:classifiers":[
        {
            "category":"Personal",
            "subcategory":"Beauty Salon",
            "type":"Services"
        }
    ],
    "sg:phone":"+1 956 994 3164",
    "sg:postcode":"78503",
    "sg:province":"TX",
    "sg:tags":[
        "shop"
    ],
    "wof:name":"Citi Divina Salon",
    "wof:placetype":"venue"
},
  "geometry": {"coordinates":[-98.24068,26.187067],"type":"Point"}
}