{
  "type": "Feature",
  "properties": {
    "iso:country":"US",
    "sg:address":"16100 Cairnway Dr #350",
    "sg:city":"Houston",
    "sg:classifiers":[
        {
            "category":"Health Services",
            "subcategory":"Clinic",
            "type":"Services"
        },
        {
            "category":"Personal",
            "type":"Services"
        },
        {
            "category":"Health Services",
            "subcategory":"Health Practitioner",
            "type":"Services"
        }
    ],
    "sg:phone":"+1 832 380 8597",
    "sg:postcode":"77084",
    "sg:province":"TX",
    "sg:tags":[
        "information",
        "maids'",
        "drug",
        "abuse",
        "butlers'",
        "treatment",
        "addiction",
        "alcoholism"
    ],
    "sg:website":"http://www.anewapproachcounseling.com",
    "wof:name":"A New Approach Counseling Service",
    "wof:placetype":"venue"
},
  "geometry": {"coordinates":[-95.643963,29.841362],"type":"Point"}
}