{
  "type": "Feature",
  "properties": {
    "iso:country":"US",
    "sg:address":"552 New Laredo Hwy",
    "sg:city":"San Antonio",
    "sg:classifiers":[
        {
            "category":"Wholesale",
            "subcategory":"Motor Vehicles",
            "type":"Manufacturing & Wholesale Goods"
        }
    ],
    "sg:phone":"+1 210 924 4305",
    "sg:postcode":"78211",
    "sg:province":"TX",
    "sg:tags":[
        "automobile"
    ],
    "wof:name":"DBA Ace Auto Parts",
    "wof:placetype":"venue"
},
  "geometry": {"coordinates":[-98.546566,29.367353],"type":"Point"}
}