{
  "type": "Feature",
  "properties": {
    "iso:country":"US",
    "sg:address":"19 Pin Oak Estates Ct",
    "sg:city":"Bellaire",
    "sg:classifiers":[
        {
            "category":"Professional",
            "type":"Services"
        }
    ],
    "sg:phone":"+1 713 668 4217",
    "sg:postcode":"77401",
    "sg:province":"TX",
    "wof:name":"Lietamente",
    "wof:placetype":"venue"
},
  "geometry": {"coordinates":[-95.452789,29.706785],"type":"Point"}
}