{
  "type": "Feature",
  "properties": {
    "iso:country":"US",
    "sg:address":"2017 David Dr",
    "sg:city":"Fort Worth",
    "sg:classifiers":[
        {
            "category":"Building & Trades",
            "subcategory":"Construction",
            "type":"Services"
        }
    ],
    "sg:phone":"+1 817 838 6267",
    "sg:postcode":"76111",
    "sg:province":"TX",
    "sg:tags":[
        "concrete",
        "cutting",
        "breaking",
        "sawing"
    ],
    "wof:name":"J & J Coring",
    "wof:placetype":"venue"
},
  "geometry": {"coordinates":[-97.29785699999999,32.791319],"type":"Point"}
}