{
  "type": "Feature",
  "properties": {
    "iso:country":"US",
    "sg:address":"1322 Castle Glen Dr",
    "sg:city":"Houston",
    "sg:classifiers":[
        {
            "category":"Place Of Worship",
            "subcategory":"Church",
            "type":"Public Place"
        },
        {
            "category":"Place Of Worship",
            "type":"Public Place"
        }
    ],
    "sg:phone":"+1 281 452 6765",
    "sg:postcode":"77015",
    "sg:province":"TX",
    "sg:tags":[
        "christ",
        "churches-community"
    ],
    "wof:name":"Solid Rock East Community Church",
    "wof:placetype":"venue"
},
  "geometry": {"coordinates":[-95.161247,29.798118],"type":"Point"}
}