{
  "type": "Feature",
  "properties": {
    "iso:country":"US",
    "sg:address":"2010 US Hwy 80",
    "sg:city":"Monahans",
    "sg:classifiers":[
        {
            "category":"Mining & Drilling",
            "type":"Manufacturing & Wholesale Goods"
        }
    ],
    "sg:phone":"+1 432 943 7667",
    "sg:postcode":"79761",
    "sg:province":"TX",
    "sg:tags":[
        "oil",
        "gas",
        "producer"
    ],
    "wof:name":"A & B Oil",
    "wof:placetype":"venue"
},
  "geometry": {"coordinates":[-102.344246,31.856304],"type":"Point"}
}