{
  "type": "Feature",
  "properties": {
    "iso:country":"US",
    "sg:address":"449 Akin St",
    "sg:city":"Nash",
    "sg:classifiers":[
        {
            "category":"Manufacturing",
            "subcategory":"Tools & Machinery",
            "type":"Manufacturing & Wholesale Goods"
        }
    ],
    "sg:phone":"+1 903 838 3239",
    "sg:postcode":"75569",
    "sg:province":"TX",
    "sg:tags":[
        "machine",
        "shop"
    ],
    "wof:name":"Robertson Machine",
    "wof:placetype":"venue"
},
  "geometry": {"coordinates":[-94.129479,33.437733],"type":"Point"}
}