{
  "type": "Feature",
  "properties": {
    "iso:country":"US",
    "sg:address":"1217 Northlake Dr",
    "sg:city":"Richardson",
    "sg:classifiers":[
        {
            "category":"Organizations",
            "subcategory":"Professional Association",
            "type":"Services"
        }
    ],
    "sg:phone":"+1 972 231 3782",
    "sg:postcode":"75080",
    "sg:province":"TX",
    "sg:tags":[
        "trade"
    ],
    "wof:name":"Southwest Conference Rural Let",
    "wof:placetype":"venue"
},
  "geometry": {"coordinates":[-96.761729,32.958891],"type":"Point"}
}