{
  "type": "Feature",
  "properties": {
    "iso:country":"US",
    "sg:address":"2nd and Congress",
    "sg:city":"Austin",
    "sg:classifiers":[
        {
            "category":"Coffee & Tea",
            "type":"Food & Drink"
        }
    ],
    "sg:phone":"+1 512 535 3955",
    "sg:postcode":"78701",
    "sg:province":"TX",
    "sg:website":"www.patikacoffee.com",
    "wof:name":"Patika Coffee",
    "wof:placetype":"venue"
},
  "geometry": {"coordinates":[-97.744197,30.26432],"type":"Point"}
}