{
  "type": "Feature",
  "properties": {
    "iso:country":"US",
    "sg:address":"3909 Sunset Dr",
    "sg:city":"San Angelo",
    "sg:classifiers":[
        {
            "category":"Restaurant",
            "type":"Food & Drink"
        }
    ],
    "sg:phone":"+1 325 942 6711",
    "sg:postcode":"76904",
    "sg:province":"TX",
    "wof:name":"Red Lobster Restaurant",
    "wof:placetype":"venue"
},
  "geometry": {"coordinates":[-100.49479599999999,31.428029],"type":"Point"}
}