{
  "type": "Feature",
  "properties": {
    "iso:country":"US",
    "sg:address":"1200 Crescent Dr",
    "sg:city":"Andrews",
    "sg:classifiers":[
        {
            "category":"Organizations",
            "subcategory":"Religious Organization",
            "type":"Services"
        }
    ],
    "sg:phone":"+1 432 523 5532",
    "sg:postcode":"79714",
    "sg:province":"TX",
    "sg:tags":[
        "church"
    ],
    "wof:name":"Jehovah's Witnesses",
    "wof:placetype":"venue"
},
  "geometry": {"coordinates":[-102.536635,32.33619],"type":"Point"}
}