{
  "type": "Feature",
  "properties": {
    "iso:country":"US",
    "sg:address":"213 E Austin St",
    "sg:city":"Port Lavaca",
    "sg:classifiers":[
        {
            "category":"Organizations",
            "subcategory":"Religious Organization",
            "type":"Services"
        }
    ],
    "sg:phone":"+1 361 552 2805",
    "sg:postcode":"77979",
    "sg:province":"TX",
    "sg:tags":[
        "church"
    ],
    "wof:name":"Episcopal Church Grace Parish",
    "wof:placetype":"venue"
},
  "geometry": {"coordinates":[-96.62272,28.613474],"type":"Point"}
}