{
  "type": "Feature",
  "properties": {
    "iso:country":"US",
    "sg:address":"4219 Richmond Ave Ste 208",
    "sg:city":"Houston",
    "sg:classifiers":[
        {
            "category":"Health Services",
            "subcategory":"Doctor",
            "type":"Services"
        }
    ],
    "sg:phone":"+1 713 627 7070",
    "sg:postcode":"77027",
    "sg:province":"TX",
    "sg:tags":[
        "medicine",
        "physician",
        "addiction",
        "surgeons"
    ],
    "wof:name":"Shana Clark",
    "wof:placetype":"venue"
},
  "geometry": {"coordinates":[-95.44542800000001,29.732464],"type":"Point"}
}