{
  "type": "Feature",
  "properties": {
    "iso:country":"US",
    "sg:address":"8349 Parker Rd",
    "sg:city":"Houston",
    "sg:classifiers":[
        {
            "category":"Manufacturing",
            "subcategory":"Glass & Minerals",
            "type":"Manufacturing & Wholesale Goods"
        }
    ],
    "sg:phone":"+1 713 633 0050",
    "sg:postcode":"77078",
    "sg:province":"TX",
    "sg:tags":[
        "tank",
        "septic",
        "concrete",
        "mfg",
        "water",
        "equipment",
        "treatment"
    ],
    "wof:name":"Svetlik Products & Service",
    "wof:placetype":"venue"
},
  "geometry": {"coordinates":[-95.272368,29.860716],"type":"Point"}
}