{
  "type": "Feature",
  "properties": {
    "iso:country":"US",
    "sg:address":"3400 Thomason Dr",
    "sg:city":"Midland",
    "sg:classifiers":[
        {
            "category":"Food & Beverages",
            "subcategory":"Meat & Fish",
            "type":"Retail Goods"
        }
    ],
    "sg:phone":"+1 432 694 2401",
    "sg:postcode":"79703",
    "sg:province":"TX",
    "wof:name":"Bowens Drive In Grocery Inc",
    "wof:placetype":"venue"
},
  "geometry": {"coordinates":[-102.114074,31.978372],"type":"Point"}
}