{
  "type": "Feature",
  "properties": {
    "iso:country":"US",
    "sg:address":"610 Cutty Trl",
    "sg:city":"Austin",
    "sg:classifiers":[
        {
            "category":"Shopping",
            "subcategory":"Gifts & Souvenirs",
            "type":"Retail Goods"
        }
    ],
    "sg:phone":"+1 512 261 4346",
    "sg:postcode":"78734",
    "sg:province":"TX",
    "wof:name":"Sweet Passions",
    "wof:placetype":"venue"
},
  "geometry": {"coordinates":[-97.969863,30.371158],"type":"Point"}
}