{
  "type": "Feature",
  "properties": {
    "iso:country":"US",
    "sg:address":"117 West St",
    "sg:city":"Coleman",
    "sg:classifiers":[
        {
            "category":"Government",
            "subcategory":"Office",
            "type":"Public Place"
        }
    ],
    "sg:phone":"+1 325 625 2151",
    "sg:postcode":"76834",
    "sg:province":"TX",
    "sg:tags":[
        "federal"
    ],
    "wof:name":"Natural Resources Conservation",
    "wof:placetype":"venue"
},
  "geometry": {"coordinates":[-99.423626,31.831826],"type":"Point"}
}