{
  "type": "Feature",
  "properties": {
    "iso:country":"US",
    "sg:address":"718 W Arapaho Rd Ste 90",
    "sg:city":"Richardson",
    "sg:classifiers":[
        {
            "category":"Communications",
            "subcategory":"Film & Video Production",
            "type":"Services"
        },
        {
            "category":"Professional",
            "subcategory":"Art Services",
            "type":"Services"
        },
        {
            "category":"Professional",
            "subcategory":"Advertising",
            "type":"Services"
        }
    ],
    "sg:phone":"+1 972 437 2021",
    "sg:postcode":"75080",
    "sg:province":"TX",
    "sg:tags":[
        "video/film",
        "graphic",
        "design",
        "videographers"
    ],
    "sg:website":"www.actionvideoservice.com",
    "wof:name":"Action Video Service",
    "wof:placetype":"venue"
},
  "geometry": {"coordinates":[-96.745828,32.963714],"type":"Point"}
}