{
  "type": "Feature",
  "properties": {
    "iso:country":"US",
    "sg:address":"1121 Simpson Dr",
    "sg:city":"Hurst",
    "sg:classifiers":[
        {
            "category":"Shopping",
            "type":"Retail Goods"
        }
    ],
    "sg:phone":"+1 817 282 0114",
    "sg:postcode":"76053",
    "sg:province":"TX",
    "sg:tags":[
        "picture",
        "frame"
    ],
    "wof:name":"Precious Angel Frames",
    "wof:placetype":"venue"
},
  "geometry": {"coordinates":[-97.169087,32.828982],"type":"Point"}
}