{
  "type": "Feature",
  "properties": {
    "iso:country":"US",
    "sg:address":"1941 Hwy 35 N",
    "sg:city":"Rockport",
    "sg:classifiers":[
        {
            "category":"Real Estate",
            "subcategory":"Real Estate Agent",
            "type":"Services"
        }
    ],
    "sg:phone":"+1 361 727 0022",
    "sg:postcode":"78382",
    "sg:province":"TX",
    "wof:name":"Texas Coast Real Estate Inc",
    "wof:placetype":"venue"
},
  "geometry": {"coordinates":[-97.042502,28.044743],"type":"Point"}
}