{
  "type": "Feature",
  "properties": {
    "iso:country":"US",
    "sg:address":"207 Cliffdale Dr",
    "sg:city":"Euless",
    "sg:classifiers":[
        {
            "category":"Restaurant",
            "type":"Food & Drink"
        }
    ],
    "sg:phone":"+1 817 571 5230",
    "sg:postcode":"76039",
    "sg:province":"TX",
    "sg:tags":[
        "eating"
    ],
    "wof:name":"Greek Italian Leather Corp",
    "wof:placetype":"venue"
},
  "geometry": {"coordinates":[-97.079761,32.825993],"type":"Point"}
}