{
  "type": "Feature",
  "properties": {
    "iso:country":"US",
    "sg:address":"9908 Cork Dr",
    "sg:city":"El Paso",
    "sg:classifiers":[
        {
            "category":"Building & Trades",
            "subcategory":"Landscaping Services",
            "type":"Services"
        }
    ],
    "sg:phone":"+1 915 598 8399",
    "sg:postcode":"79925",
    "sg:province":"TX",
    "sg:tags":[
        "tree"
    ],
    "wof:name":"Daniel's Tree & Landscaping",
    "wof:placetype":"venue"
},
  "geometry": {"coordinates":[-106.351415,31.782628],"type":"Point"}
}