{
  "type": "Feature",
  "properties": {
    "iso:country":"US",
    "sg:address":"1405 Darlene Ln",
    "sg:city":"Arlington",
    "sg:classifiers":[
        {
            "category":"Personal",
            "type":"Services"
        }
    ],
    "sg:phone":"+1 817 274 9649",
    "sg:postcode":"76010",
    "sg:province":"TX",
    "wof:name":"Organizational Developmen",
    "wof:placetype":"venue"
},
  "geometry": {"coordinates":[-97.08542199999999,32.710544],"type":"Point"}
}