{
  "type": "Feature",
  "properties": {
    "iso:country":"US",
    "sg:address":"814 Maple Ave",
    "sg:city":"Odessa",
    "sg:classifiers":[
        {
            "category":"Food & Beverages",
            "subcategory":"Liquor & Beverages",
            "type":"Retail Goods"
        }
    ],
    "sg:phone":"+1 432 332 4621",
    "sg:postcode":"79761",
    "sg:province":"TX",
    "sg:tags":[
        "store"
    ],
    "wof:name":"Pinkies Liquor Store 28",
    "wof:placetype":"venue"
},
  "geometry": {"coordinates":[-102.358597,31.858691],"type":"Point"}
}