{
  "type": "Feature",
  "properties": {
    "iso:country":"US",
    "sg:address":"7110 Louetta Rd",
    "sg:city":"Spring",
    "sg:classifiers":[
        {
            "category":"Personal",
            "subcategory":"Barber",
            "type":"Services"
        }
    ],
    "sg:phone":"+1 281 251 4591",
    "sg:postcode":"77379",
    "sg:province":"TX",
    "sg:tags":[
        "shop"
    ],
    "wof:name":"Looks Barber & Styling Center",
    "wof:placetype":"venue"
},
  "geometry": {"coordinates":[-95.521416,30.022278],"type":"Point"}
}