{
  "type": "Feature",
  "properties": {
    "iso:country":"US",
    "sg:address":"3800 Spencer Hwy Ste K",
    "sg:city":"Pasadena",
    "sg:classifiers":[
        {
            "category":"Personal",
            "subcategory":"Beauty Salon",
            "type":"Services"
        },
        {
            "category":"Personal",
            "subcategory":"Nail Salon",
            "type":"Services"
        }
    ],
    "sg:phone":"+1 713 943 2233",
    "sg:postcode":"77504",
    "sg:province":"TX",
    "wof:name":"Dr Nails by Cindy",
    "wof:placetype":"venue"
},
  "geometry": {"coordinates":[-95.186401,29.6651],"type":"Point"}
}