{
  "type": "Feature",
  "properties": {
    "iso:country":"US",
    "sg:address":"6206 Homestead Trl",
    "sg:city":"Austin",
    "sg:classifiers":[
        {
            "category":"Retail",
            "subcategory":"Repair Shop",
            "type":"Services"
        }
    ],
    "sg:phone":"+1 512 288 0922",
    "sg:postcode":"78735",
    "sg:province":"TX",
    "wof:name":"Upholestry By Kerry",
    "wof:placetype":"venue"
},
  "geometry": {"coordinates":[-97.88159899999999,30.247667],"type":"Point"}
}