{
  "type": "Feature",
  "properties": {
    "iso:country":"US",
    "sg:address":"2870 W Pioneer Pkwy",
    "sg:city":"Arlington",
    "sg:classifiers":[
        {
            "category":"Retail",
            "subcategory":"Auto Repair",
            "type":"Services"
        }
    ],
    "sg:phone":"+1 817 548 5959",
    "sg:postcode":"76013",
    "sg:province":"TX",
    "sg:tags":[
        "automobile",
        "inspection",
        "automotive"
    ],
    "wof:name":"Tire Mart Auto Center",
    "wof:placetype":"venue"
},
  "geometry": {"coordinates":[-97.15250899999999,32.709616],"type":"Point"}
}