{
  "type": "Feature",
  "properties": {
    "iso:country":"US",
    "sg:address":"302 Droinwich Cir",
    "sg:city":"Allen",
    "sg:classifiers":[
        {
            "category":"Insurance",
            "subcategory":"Insurance Agent",
            "type":"Services"
        }
    ],
    "sg:phone":"+1 972 727 4935",
    "sg:postcode":"75002",
    "sg:province":"TX",
    "wof:name":"Farmers Insurance Group",
    "wof:placetype":"venue"
},
  "geometry": {"coordinates":[-96.645779,33.0965],"type":"Point"}
}