{
  "type": "Feature",
  "properties": {
    "iso:country":"US",
    "sg:address":"2138 Richmond Ave",
    "sg:city":"Houston",
    "sg:classifiers":[
        {
            "category":"Professional",
            "subcategory":"Management & Consulting",
            "type":"Services"
        }
    ],
    "sg:phone":"+1 713 523 2655",
    "sg:postcode":"77098",
    "sg:province":"TX",
    "sg:tags":[
        "personnel",
        "consultant"
    ],
    "wof:name":"Wolff R L & Associates",
    "wof:placetype":"venue"
},
  "geometry": {"coordinates":[-95.411906,29.734267],"type":"Point"}
}