{
  "type": "Feature",
  "properties": {
    "iso:country":"US",
    "sg:address":"146 State Hwy 46",
    "sg:city":"New Braunfels",
    "sg:classifiers":[
        {
            "category":"Food & Beverages",
            "subcategory":"Meat & Fish",
            "type":"Retail Goods"
        },
        {
            "category":"Restaurant",
            "type":"Food & Drink"
        }
    ],
    "sg:phone":"+1 830 625 9138",
    "sg:postcode":"78130",
    "sg:province":"TX",
    "sg:tags":[
        "eating",
        "processed",
        "family"
    ],
    "sg:website":"www.nbsmokehouse.com",
    "wof:name":"New Braunfels Smokehouse Inc",
    "wof:placetype":"venue"
},
  "geometry": {"coordinates":[-98.095996,29.701989],"type":"Point"}
}