{
  "type": "Feature",
  "properties": {
    "iso:country":"US",
    "sg:address":"205 E 8th St",
    "sg:city":"Plainview",
    "sg:classifiers":[
        {
            "category":"Manufacturing",
            "subcategory":"Tools & Machinery",
            "type":"Manufacturing & Wholesale Goods"
        }
    ],
    "sg:phone":"+1 806 296 6280",
    "sg:postcode":"79072",
    "sg:province":"TX",
    "sg:tags":[
        "machine",
        "shop",
        "parts",
        "auto"
    ],
    "wof:name":"Carlisle Mtr Mch Svc & Sup Inc",
    "wof:placetype":"venue"
},
  "geometry": {"coordinates":[-101.700495,34.1884],"type":"Point"}
}