{
  "type": "Feature",
  "properties": {
    "iso:country":"US",
    "sg:address":"5746 Belcrest St",
    "sg:city":"Houston",
    "sg:classifiers":[
        {
            "category":"Building & Trades",
            "subcategory":"Plumbing",
            "type":"Services"
        }
    ],
    "sg:phone":"+1 713 738 3992",
    "sg:postcode":"77033",
    "sg:province":"TX",
    "sg:tags":[
        "contractor"
    ],
    "wof:name":"Ratcliff Air Conditioning",
    "wof:placetype":"venue"
},
  "geometry": {"coordinates":[-95.334518,29.66463],"type":"Point"}
}