{
  "type": "Feature",
  "properties": {
    "iso:country":"US",
    "sg:address":"13330 Noble Crest Dr",
    "sg:city":"Houston",
    "sg:classifiers":[
        {
            "category":"Shopping",
            "subcategory":"Gifts & Souvenirs",
            "type":"Retail Goods"
        }
    ],
    "sg:phone":"+1 713 856 8519",
    "sg:postcode":"77041",
    "sg:province":"TX",
    "wof:name":"Mirna Flower Plants & Gifts",
    "wof:placetype":"venue"
},
  "geometry": {"coordinates":[-95.608895,29.884716],"type":"Point"}
}