{
  "type": "Feature",
  "properties": {
    "iso:country":"US",
    "sg:address":"207 NE 7th Ave",
    "sg:city":"Mineral Wells",
    "sg:classifiers":[
        {
            "category":"Education",
            "subcategory":"Special Training",
            "type":"Public Place"
        }
    ],
    "sg:phone":"+1 940 325 6858",
    "sg:postcode":"76067",
    "sg:province":"TX",
    "wof:name":"Henry L & Josephine Smith",
    "wof:placetype":"venue"
},
  "geometry": {"coordinates":[-98.10677800000001,32.810775],"type":"Point"}
}