{
  "type": "Feature",
  "properties": {
    "iso:country":"US",
    "sg:address":"308 N 8th St",
    "sg:city":"Wolfforth",
    "sg:classifiers":[
        {
            "category":"Professional",
            "subcategory":"Business Services",
            "type":"Services"
        }
    ],
    "sg:phone":"+1 806 855 6285",
    "sg:postcode":"79382",
    "sg:province":"TX",
    "sg:tags":[
        "consultant",
        "coach"
    ],
    "wof:name":"Michael Wells Consulting Services",
    "wof:placetype":"venue"
},
  "geometry": {"coordinates":[-102.008072,33.527388],"type":"Point"}
}