{
  "type": "Feature",
  "properties": {
    "iso:country":"US",
    "sg:address":"405 N I Rd",
    "sg:city":"Pharr",
    "sg:classifiers":[
        {
            "category":"Restaurant",
            "type":"Food & Drink"
        }
    ],
    "sg:phone":"+1 956 787 6353",
    "sg:postcode":"78577",
    "sg:province":"TX",
    "sg:tags":[
        "eating"
    ],
    "wof:name":"Taqueria LA Muneca",
    "wof:placetype":"venue"
},
  "geometry": {"coordinates":[-98.166996,26.196253],"type":"Point"}
}