{
  "type": "Feature",
  "properties": {
    "iso:country":"US",
    "sg:address":"12132 Leslie Rd",
    "sg:city":"Helotes",
    "sg:classifiers":[
        {
            "category":"Recreation",
            "type":"Entertainment"
        },
        {
            "category":"Real Estate",
            "subcategory":"Real Estate Operator",
            "type":"Services"
        }
    ],
    "sg:phone":"+1 210 695 2772",
    "sg:postcode":"78023",
    "sg:province":"TX",
    "sg:tags":[
        "building",
        "nonresidential",
        "hall",
        "auditorium"
    ],
    "wof:name":"Helotes 4h Activity Ctr",
    "wof:placetype":"venue"
},
  "geometry": {"coordinates":[-98.68362999999999,29.554562],"type":"Point"}
}