{
  "type": "Feature",
  "properties": {
    "iso:country":"US",
    "sg:address":"3206 Las Cruces Blvd",
    "sg:city":"Temple",
    "sg:classifiers":[
        {
            "category":"Organizations",
            "subcategory":"Membership Organization",
            "type":"Services"
        }
    ],
    "sg:phone":"+1 254 773 4825",
    "sg:postcode":"76502",
    "sg:province":"TX",
    "wof:name":"Childrens Care of Tex Inc",
    "wof:placetype":"venue"
},
  "geometry": {"coordinates":[-97.392163,31.077394],"type":"Point"}
}