{
  "type": "Feature",
  "properties": {
    "iso:country":"US",
    "sg:address":"309 Cemetery Rd",
    "sg:city":"Clute",
    "sg:classifiers":[
        {
            "category":"Real Estate",
            "subcategory":"Real Estate Operator",
            "type":"Services"
        }
    ],
    "sg:phone":"+1 979 265 8465",
    "sg:postcode":"77531",
    "sg:province":"TX",
    "sg:tags":[
        "mobile",
        "home",
        "site"
    ],
    "wof:name":"Trailer Park",
    "wof:placetype":"venue"
},
  "geometry": {"coordinates":[-95.408821,29.016291],"type":"Point"}
}