{
  "type": "Feature",
  "properties": {
    "iso:country":"US",
    "sg:address":"3737 8th St",
    "sg:city":"Port Arthur",
    "sg:classifiers":[
        {
            "category":"Organizations",
            "subcategory":"Religious Organization",
            "type":"Services"
        }
    ],
    "sg:phone":"+1 409 985 2392",
    "sg:postcode":"77642",
    "sg:province":"TX",
    "sg:tags":[
        "church"
    ],
    "wof:name":"Central Church Of The Nazarene",
    "wof:placetype":"venue"
},
  "geometry": {"coordinates":[-93.911411,29.902642],"type":"Point"}
}