{
  "type": "Feature",
  "properties": {
    "iso:country":"US",
    "sg:address":"15630 Vision Dr",
    "sg:city":"Pflugerville",
    "sg:classifiers":[
        {
            "category":"Restaurant",
            "type":"Food & Drink"
        }
    ],
    "sg:phone":"+1 512 251 6544",
    "sg:postcode":"78660",
    "sg:province":"TX",
    "sg:tags":[
        "eating"
    ],
    "wof:name":"King Arthur Mobile Catering",
    "wof:placetype":"venue"
},
  "geometry": {"coordinates":[-97.662161,30.451073],"type":"Point"}
}