{
  "type": "Feature",
  "properties": {
    "iso:country":"US",
    "sg:address":"1703 Johnson St",
    "sg:city":"Marble Falls",
    "sg:classifiers":[
        {
            "category":"Professional",
            "subcategory":"Business Services",
            "type":"Services"
        }
    ],
    "sg:phone":"+1 830 693 4200",
    "sg:postcode":"78654",
    "sg:province":"TX",
    "wof:name":"Vision Designs & Associates",
    "wof:placetype":"venue"
},
  "geometry": {"coordinates":[-98.291498,30.571727],"type":"Point"}
}