{
  "type": "Feature",
  "properties": {
    "iso:country":"US",
    "sg:address":"40 Kearny Brook Pl",
    "sg:city":"Spring",
    "sg:classifiers":[
        {
            "category":"Professional",
            "subcategory":"Business Services",
            "type":"Services"
        }
    ],
    "sg:phone":"+1 281 292 4898",
    "sg:postcode":"77381",
    "sg:province":"TX",
    "wof:name":"Designs By Robin",
    "wof:placetype":"venue"
},
  "geometry": {"coordinates":[-95.509676,30.17617],"type":"Point"}
}