{
  "type": "Feature",
  "properties": {
    "iso:country":"US",
    "sg:address":"1418 Cardinal Hill Dr",
    "sg:city":"Austin",
    "sg:classifiers":[
        {
            "category":"Real Estate",
            "subcategory":"Real Estate Services",
            "type":"Services"
        }
    ],
    "sg:phone":"+1 512 294 7845",
    "sg:postcode":"78758",
    "sg:province":"TX",
    "sg:tags":[
        "vacancy",
        "rental",
        "listing"
    ],
    "wof:name":"Galvan & Associates",
    "wof:placetype":"venue"
},
  "geometry": {"coordinates":[-97.68547100000001,30.410009],"type":"Point"}
}