{
  "type": "Feature",
  "properties": {
    "iso:country":"US",
    "sg:address":"8316 Baumgarten Dr",
    "sg:city":"Dallas",
    "sg:classifiers":[
        {
            "category":"Restaurant",
            "type":"Food & Drink"
        }
    ],
    "sg:phone":"+1 214 327 2003",
    "sg:postcode":"75228",
    "sg:province":"TX",
    "sg:tags":[
        "eating"
    ],
    "wof:name":"Cusos Executive Aircraft",
    "wof:placetype":"venue"
},
  "geometry": {"coordinates":[-96.696116,32.802121],"type":"Point"}
}