{
  "type": "Feature",
  "properties": {
    "iso:country":"US",
    "sg:address":"6211 W Northwest Hwy Apt 2306",
    "sg:city":"Dallas",
    "sg:classifiers":[
        {
            "category":"Professional",
            "subcategory":"Management & Consulting",
            "type":"Services"
        }
    ],
    "sg:phone":"+1 214 244 2101",
    "sg:postcode":"75225",
    "sg:province":"TX",
    "sg:tags":[
        "consultant"
    ],
    "sg:website":"http://www.itsthehow.com",
    "wof:name":"It's The How",
    "wof:placetype":"venue"
},
  "geometry": {"coordinates":[-96.80029999999999,32.86573],"type":"Point"}
}