{
  "type": "Feature",
  "properties": {
    "iso:country":"US",
    "sg:address":"7928 el Dorado Dr",
    "sg:city":"Austin",
    "sg:classifiers":[
        {
            "category":"Professional",
            "subcategory":"Detective & Security Services",
            "type":"Services"
        }
    ],
    "sg:phone":"+1 512 301 7468",
    "sg:postcode":"78737",
    "sg:province":"TX",
    "sg:tags":[
        "car"
    ],
    "wof:name":"Pan Vision Security LLC",
    "wof:placetype":"venue"
},
  "geometry": {"coordinates":[-97.911421,30.217287],"type":"Point"}
}