{
  "type": "Feature",
  "properties": {
    "iso:country":"US",
    "sg:address":"292 Kings Hwy",
    "sg:city":"Brownsville",
    "sg:classifiers":[
        {
            "category":"Banks & Credit Unions",
            "subcategory":"Bank",
            "type":"Services"
        }
    ],
    "sg:phone":"+1 956 546 6444",
    "sg:postcode":"78521",
    "sg:province":"TX",
    "sg:tags":[
        "loan",
        "mortgage",
        "real estate"
    ],
    "wof:name":"Mortgage Savings",
    "wof:placetype":"venue"
},
  "geometry": {"coordinates":[-97.471923,25.921314],"type":"Point"}
}