{
  "type": "Feature",
  "properties": {
    "iso:country":"US",
    "sg:address":"7309 Pensacola Ave",
    "sg:city":"Fort Worth",
    "sg:classifiers":[
        {
            "category":"Building & Trades",
            "subcategory":"Landscaping Services",
            "type":"Services"
        }
    ],
    "sg:phone":"+1 817 738 7957",
    "sg:postcode":"76116",
    "sg:province":"TX",
    "sg:tags":[
        "landscape"
    ],
    "wof:name":"New Life Landscaping",
    "wof:placetype":"venue"
},
  "geometry": {"coordinates":[-97.442148,32.708855],"type":"Point"}
}