{
  "type": "Feature",
  "properties": {
    "iso:country":"US",
    "sg:address":"402 Cantrell St",
    "sg:city":"Waxahachie",
    "sg:classifiers":[
        {
            "category":"Manufacturing",
            "subcategory":"Building Materials",
            "type":"Manufacturing & Wholesale Goods"
        }
    ],
    "sg:phone":"+1 972 938 9623",
    "sg:postcode":"75165",
    "sg:province":"TX",
    "sg:tags":[
        "cabinet"
    ],
    "sg:website":"www.cabinetspecialists.com",
    "wof:name":"Cabinet Specialist",
    "wof:placetype":"venue"
},
  "geometry": {"coordinates":[-96.854849,32.381416],"type":"Point"}
}