{
  "type": "Feature",
  "properties": {
    "iso:country":"US",
    "sg:address":"445 Roosevelt Dr",
    "sg:city":"Silsbee",
    "sg:classifiers":[
        {
            "category":"Health Services",
            "subcategory":"Doctor",
            "type":"Services"
        }
    ],
    "sg:phone":"+1 409 385 3783",
    "sg:postcode":"77656",
    "sg:province":"TX",
    "sg:tags":[
        "physician",
        "surgeon"
    ],
    "wof:name":"Tennison Clinic",
    "wof:placetype":"venue"
},
  "geometry": {"coordinates":[-94.18038,30.353853],"type":"Point"}
}