{
  "type": "Feature",
  "properties": {
    "iso:country":"US",
    "sg:address":"129 Chaparral Dr",
    "sg:city":"Graham",
    "sg:classifiers":[
        {
            "category":"Shopping",
            "type":"Retail Goods"
        }
    ],
    "sg:phone":"+1 940 549 0768",
    "sg:postcode":"76450",
    "sg:province":"TX",
    "sg:tags":[
        "merchandise"
    ],
    "wof:name":"Donna K Thornbrue",
    "wof:placetype":"venue"
},
  "geometry": {"coordinates":[-98.606804,33.113857],"type":"Point"}
}