{
  "type": "Feature",
  "properties": {
    "iso:country":"US",
    "sg:address":"8505 Freeport Pkwy",
    "sg:city":"Irving",
    "sg:classifiers":[
        {
            "category":"Professional",
            "subcategory":"Management & Consulting",
            "type":"Services"
        }
    ],
    "sg:phone":"+1 972 621 0345",
    "sg:postcode":"75063",
    "sg:province":"TX",
    "sg:tags":[
        "ready",
        "concrete",
        "mfg"
    ],
    "wof:name":"Hanson Concrete",
    "wof:placetype":"venue"
},
  "geometry": {"coordinates":[-97.018519,32.923518],"type":"Point"}
}