{
  "type": "Feature",
  "properties": {
    "iso:country":"US",
    "sg:address":"2500 W Parmer Ln",
    "sg:city":"Austin",
    "sg:classifiers":[
        {
            "category":"Shopping",
            "type":"Retail Goods"
        }
    ],
    "sg:phone":"+1 512 255 2208",
    "sg:postcode":"78727",
    "sg:province":"TX",
    "sg:website":"www.dollartree.com",
    "wof:name":"Dollar Tree",
    "wof:placetype":"venue"
},
  "geometry": {"coordinates":[-97.701926,30.42061],"type":"Point"}
}