{
  "type": "Feature",
  "properties": {
    "iso:country":"US",
    "sg:address":"1637 Japonica Ln",
    "sg:city":"Plano",
    "sg:classifiers":[
        {
            "category":"Retail",
            "subcategory":"Portrait Studio",
            "type":"Services"
        }
    ],
    "sg:phone":"+1 972 578 0783",
    "sg:postcode":"75074",
    "sg:province":"TX",
    "sg:tags":[
        "photo"
    ],
    "wof:name":"Danny Briggs & Co",
    "wof:placetype":"venue"
},
  "geometry": {"coordinates":[-96.69305799999999,33.03406],"type":"Point"}
}