{
  "type": "Feature",
  "properties": {
    "iso:country":"US",
    "sg:address":"2602 Harwood Rd",
    "sg:city":"Bedford",
    "sg:classifiers":[
        {
            "category":"Personal",
            "type":"Services"
        }
    ],
    "sg:phone":"+1 817 545 0200",
    "sg:postcode":"76021",
    "sg:province":"TX",
    "sg:tags":[
        "real estate"
    ],
    "wof:name":"APT Locator Service Inc",
    "wof:placetype":"venue"
},
  "geometry": {"coordinates":[-97.122339,32.851869],"type":"Point"}
}