{
  "type": "Feature",
  "properties": {
    "iso:country":"US",
    "sg:address":"2301 S Riverside Dr",
    "sg:city":"Fort Worth",
    "sg:classifiers":[
        {
            "category":"Food & Beverages",
            "subcategory":"Groceries & Convenience Stores",
            "type":"Retail Goods"
        }
    ],
    "sg:phone":"+1 817 413 4711",
    "sg:postcode":"76104",
    "sg:province":"TX",
    "sg:tags":[
        "grocer"
    ],
    "wof:name":"Homeboy Food Mart",
    "wof:placetype":"venue"
},
  "geometry": {"coordinates":[-97.30432999999999,32.719029],"type":"Point"}
}