{
  "type": "Feature",
  "properties": {
    "iso:country":"US",
    "sg:address":"713 Airline Rd",
    "sg:city":"Corpus Christi",
    "sg:classifiers":[
        {
            "category":"Travel",
            "subcategory":"Travel Agent",
            "type":"Entertainment"
        }
    ],
    "sg:phone":"+1 361 985 2005",
    "sg:postcode":"78412",
    "sg:province":"TX",
    "sg:tags":[
        "passenger",
        "transportation",
        "arrangement"
    ],
    "wof:name":"Airline Motors",
    "wof:placetype":"venue"
},
  "geometry": {"coordinates":[-97.362089,27.720278],"type":"Point"}
}