{
  "type": "Feature",
  "properties": {
    "iso:country":"US",
    "sg:address":"4121 Osage St",
    "sg:city":"Houston",
    "sg:classifiers":[
        {
            "category":"Freight",
            "type":"Transportation"
        }
    ],
    "sg:phone":"+1 713 783 0323",
    "sg:postcode":"77036",
    "sg:province":"TX",
    "sg:tags":[
        "special",
        "general"
    ],
    "wof:name":"Sundown Wrecker Service",
    "wof:placetype":"venue"
},
  "geometry": {"coordinates":[-95.52628799999999,29.720354],"type":"Point"}
}