{
  "type": "Feature",
  "properties": {
    "iso:country":"US",
    "sg:address":"140 Hunter St",
    "sg:city":"Cedar Hill",
    "sg:classifiers":[
        {
            "category":"Professional",
            "type":"Services"
        }
    ],
    "sg:phone":"+1 972 293 9216",
    "sg:postcode":"75104",
    "sg:province":"TX",
    "wof:name":"Celtic",
    "wof:placetype":"venue"
},
  "geometry": {"coordinates":[-96.946235,32.615565],"type":"Point"}
}