{
  "type": "Feature",
  "properties": {
    "iso:country":"US",
    "sg:address":"101 SE 17th Ave",
    "sg:city":"Mineral Wells",
    "sg:classifiers":[
        {
            "category":"Food & Beverages",
            "subcategory":"Groceries & Convenience Stores",
            "type":"Retail Goods"
        }
    ],
    "sg:phone":"+1 940 328 1697",
    "sg:postcode":"76067",
    "sg:province":"TX",
    "sg:tags":[
        "grocer"
    ],
    "wof:name":"Save-A-Lot",
    "wof:placetype":"venue"
},
  "geometry": {"coordinates":[-98.09651599999999,32.809159],"type":"Point"}
}