{
  "type": "Feature",
  "properties": {
    "iso:country":"US",
    "sg:address":"626 Mary Lake Dr",
    "sg:city":"Bryan",
    "sg:classifiers":[
        {
            "category":"Shopping",
            "subcategory":"Crafts & Fabrics",
            "type":"Retail Goods"
        }
    ],
    "sg:phone":"+1 979 822 5088",
    "sg:postcode":"77801",
    "sg:province":"TX",
    "sg:tags":[
        "sewing"
    ],
    "wof:name":"Embroidery Business",
    "wof:placetype":"venue"
},
  "geometry": {"coordinates":[-96.34891399999999,30.638986],"type":"Point"}
}