{
  "type": "Feature",
  "properties": {
    "iso:country":"US",
    "sg:address":"1300 Whitestone Ln",
    "sg:city":"Cedar Park",
    "sg:classifiers":[
        {
            "category":"Building & Trades",
            "subcategory":"Construction",
            "type":"Services"
        }
    ],
    "sg:phone":"+1 512 258 6725",
    "sg:postcode":"78613",
    "sg:province":"TX",
    "sg:tags":[
        "foundation",
        "contractor"
    ],
    "wof:name":"Bell & Son Hole Drilling",
    "wof:placetype":"venue"
},
  "geometry": {"coordinates":[-97.833067,30.521867],"type":"Point"}
}