{
  "type": "Feature",
  "properties": {
    "iso:country":"US",
    "sg:address":"542 Arlington St",
    "sg:city":"Houston",
    "sg:classifiers":[
        {
            "category":"Professional",
            "subcategory":"Business Services",
            "type":"Services"
        }
    ],
    "sg:phone":"+1 713 705 1061",
    "sg:postcode":"77007",
    "sg:province":"TX",
    "sg:tags":[
        "translator",
        "interpreter"
    ],
    "wof:name":"EAC Interpreters & Trnsltrs",
    "wof:placetype":"venue"
},
  "geometry": {"coordinates":[-95.393933,29.780727],"type":"Point"}
}