{
  "type": "Feature",
  "properties": {
    "iso:country":"US",
    "sg:address":"5889 W Valley Cir",
    "sg:city":"El Paso",
    "sg:classifiers":[
        {
            "category":"Retail",
            "subcategory":"Repair Shop",
            "type":"Services"
        }
    ],
    "sg:phone":"+1 915 587 7665",
    "sg:postcode":"79932",
    "sg:province":"TX",
    "sg:tags":[
        "lock",
        "locksmith"
    ],
    "wof:name":"Lone Star Towing",
    "wof:placetype":"venue"
},
  "geometry": {"coordinates":[-106.589659,31.864327],"type":"Point"}
}