{
  "type": "Feature",
  "properties": {
    "iso:country":"US",
    "sg:address":"12867 Westhorpe Dr",
    "sg:city":"Houston",
    "sg:classifiers":[
        {
            "category":"Professional",
            "subcategory":"Accounting & Tax Preparation",
            "type":"Services"
        }
    ],
    "sg:phone":"+1 281 752 4957",
    "sg:postcode":"77077",
    "sg:province":"TX",
    "sg:tags":[
        "bookkeeping",
        "general"
    ],
    "wof:name":"C J's Bookkeeping",
    "wof:placetype":"venue"
},
  "geometry": {"coordinates":[-95.61403900000001,29.748487],"type":"Point"}
}