{
  "type": "Feature",
  "properties": {
    "iso:country":"US",
    "sg:address":"100 Crescent Ct Ste 250",
    "sg:city":"Dallas",
    "sg:classifiers":[
        {
            "category":"Banks & Credit Unions",
            "subcategory":"Investment Brokerage",
            "type":"Services"
        }
    ],
    "sg:phone":"+1 214 661 3180",
    "sg:postcode":"75201",
    "sg:province":"TX",
    "sg:tags":[
        "investing"
    ],
    "wof:name":"Round Rock Capital Management",
    "wof:placetype":"venue"
},
  "geometry": {"coordinates":[-96.805099,32.793701],"type":"Point"}
}