{
  "type": "Feature",
  "properties": {
    "iso:country":"US",
    "sg:address":"1418 Beech Ave",
    "sg:city":"Mcallen",
    "sg:classifiers":[
        {
            "category":"Building & Trades",
            "subcategory":"Construction",
            "type":"Services"
        }
    ],
    "sg:phone":"+1 956 618 1642",
    "sg:postcode":"78501",
    "sg:province":"TX",
    "sg:tags":[
        "contractor",
        "mason"
    ],
    "wof:name":"Avance Inc",
    "wof:placetype":"venue"
},
  "geometry": {"coordinates":[-98.23460300000001,26.205609],"type":"Point"}
}