{
  "type": "Feature",
  "properties": {
    "iso:country":"US",
    "sg:address":"840 N Crowley Rd",
    "sg:city":"Crowley",
    "sg:classifiers":[
        {
            "category":"Retail",
            "subcategory":"Veterinary Services",
            "type":"Services"
        }
    ],
    "sg:phone":"+1 817 297 1191",
    "sg:postcode":"76036",
    "sg:province":"TX",
    "sg:tags":[
        "hospital",
        "veterinarian",
        "animal"
    ],
    "wof:name":"Crowley Road Animal Hospital",
    "wof:placetype":"venue"
},
  "geometry": {"coordinates":[-97.350899,32.587601],"type":"Point"}
}