{
  "type": "Feature",
  "properties": {
    "iso:country":"US",
    "sg:address":"108 Woodland Cir",
    "sg:city":"Crockett",
    "sg:classifiers":[
        {
            "category":"Shopping",
            "subcategory":"Clothing, Apparel, & Fashions",
            "type":"Retail Goods"
        }
    ],
    "sg:phone":"+1 936 544 3865",
    "sg:postcode":"75835",
    "sg:province":"TX",
    "wof:name":"Shop & Save",
    "wof:placetype":"venue"
},
  "geometry": {"coordinates":[-95.44292900000001,31.327516],"type":"Point"}
}