{
  "type": "Feature",
  "properties": {
    "iso:country":"US",
    "sg:address":"1715 S Hampton Rd",
    "sg:city":"Red Oak",
    "sg:classifiers":[
        {
            "category":"Personal",
            "subcategory":"Barber",
            "type":"Services"
        }
    ],
    "sg:phone":"+1 972 223 8833",
    "sg:postcode":"75154",
    "sg:province":"TX",
    "wof:name":"Ed's Barber Shop",
    "wof:placetype":"venue"
},
  "geometry": {"coordinates":[-96.856888,32.556648],"type":"Point"}
}