{
  "type": "Feature",
  "properties": {
    "iso:country":"US",
    "sg:address":"209 Las Colinas Dr",
    "sg:city":"Georgetown",
    "sg:classifiers":[
        {
            "category":"Professional",
            "subcategory":"Business Services",
            "type":"Services"
        }
    ],
    "sg:phone":"+1 512 863 3663",
    "sg:postcode":"78628",
    "sg:province":"TX",
    "wof:name":"Westwood Group",
    "wof:placetype":"venue"
},
  "geometry": {"coordinates":[-97.684783,30.70951],"type":"Point"}
}