{
  "type": "Feature",
  "properties": {
    "iso:country":"US",
    "sg:address":"655 Doty Rd",
    "sg:city":"Vidor",
    "sg:classifiers":[
        {
            "category":"Retail",
            "subcategory":"Repair Shop",
            "type":"Services"
        }
    ],
    "sg:phone":"+1 806 769 7418",
    "sg:postcode":"77662",
    "sg:province":"TX",
    "wof:name":"Sidra Inc",
    "wof:placetype":"venue"
},
  "geometry": {"coordinates":[-93.94782499999999,30.140147],"type":"Point"}
}