{
  "type": "Feature",
  "properties": {
    "iso:country":"US",
    "sg:address":"2310 College Ave",
    "sg:city":"Garland",
    "sg:classifiers":[
        {
            "category":"Place Of Worship",
            "subcategory":"Church",
            "type":"Public Place"
        },
        {
            "category":"Place Of Worship",
            "type":"Public Place"
        },
        {
            "category":"Organizations",
            "subcategory":"Religious Organization",
            "type":"Services"
        }
    ],
    "sg:phone":"+1 972 485 9905",
    "sg:postcode":"75042",
    "sg:province":"TX",
    "sg:tags":[
        "testament",
        "christ-new",
        "churches-church",
        "christ"
    ],
    "wof:name":"Iglesia Ni Cristo",
    "wof:placetype":"venue"
},
  "geometry": {"coordinates":[-96.66211199999999,32.915249],"type":"Point"}
}