{
  "type": "Feature",
  "properties": {
    "iso:country":"US",
    "sg:address":"36 Shadow Ln",
    "sg:city":"Pottsboro",
    "sg:classifiers":[
        {
            "category":"Building & Trades",
            "subcategory":"Construction",
            "type":"Services"
        }
    ],
    "sg:phone":"+1 903 786 6003",
    "sg:postcode":"75076",
    "sg:province":"TX",
    "sg:tags":[
        "contractor"
    ],
    "wof:name":"Gladney Services",
    "wof:placetype":"venue"
},
  "geometry": {"coordinates":[-96.702871,33.816966],"type":"Point"}
}