{
  "type": "Feature",
  "properties": {
    "iso:country":"US",
    "sg:address":"431 E Northwest Hwy",
    "sg:city":"Grapevine",
    "sg:classifiers":[
        {
            "category":"Building & Trades",
            "subcategory":"Construction",
            "type":"Services"
        }
    ],
    "sg:phone":"+1 817 481 8843",
    "sg:postcode":"76051",
    "sg:province":"TX",
    "sg:tags":[
        "contractor"
    ],
    "wof:name":"Independent Builders Inc",
    "wof:placetype":"venue"
},
  "geometry": {"coordinates":[-97.0745,32.941113],"type":"Point"}
}