{
  "type": "Feature",
  "properties": {
    "iso:country":"US",
    "sg:address":"7501 Sandia Loop",
    "sg:city":"Austin",
    "sg:classifiers":[
        {
            "category":"Banks & Credit Unions",
            "subcategory":"Financial Services",
            "type":"Services"
        }
    ],
    "sg:phone":"+1 512 658 4464",
    "sg:postcode":"78735",
    "sg:province":"TX",
    "sg:tags":[
        "company",
        "holding"
    ],
    "wof:name":"Queretero Ltd",
    "wof:placetype":"venue"
},
  "geometry": {"coordinates":[-97.857123,30.274751],"type":"Point"}
}