{
  "type": "Feature",
  "properties": {
    "iso:country":"US",
    "sg:address":"8810 Croes Dr",
    "sg:city":"Houston",
    "sg:classifiers":[
        {
            "category":"Banks & Credit Unions",
            "subcategory":"Financial Services",
            "type":"Services"
        }
    ],
    "sg:phone":"+1 713 461 1753",
    "sg:postcode":"77055",
    "sg:province":"TX",
    "sg:tags":[
        "trust",
        "investment",
        "real estate"
    ],
    "wof:name":"Hogden Corp",
    "wof:placetype":"venue"
},
  "geometry": {"coordinates":[-95.50812000000001,29.789432],"type":"Point"}
}