{
  "type": "Feature",
  "properties": {
    "iso:country":"US",
    "sg:address":"205 W Olmos Dr",
    "sg:city":"San Antonio",
    "sg:classifiers":[
        {
            "category":"Professional",
            "subcategory":"Management & Consulting",
            "type":"Services"
        }
    ],
    "sg:phone":"+1 210 930 3000",
    "sg:postcode":"78212",
    "sg:province":"TX",
    "sg:tags":[
        "consultant",
        "lighting"
    ],
    "wof:name":"Murray & Assoc Inc",
    "wof:placetype":"venue"
},
  "geometry": {"coordinates":[-98.49547,29.471015],"type":"Point"}
}