{
  "type": "Feature",
  "properties": {
    "iso:country":"US",
    "sg:address":"401 Country Ridge",
    "sg:city":"Rockwall",
    "sg:classifiers":[
        {
            "category":"Building & Trades",
            "subcategory":"Equipment Rental",
            "type":"Services"
        }
    ],
    "sg:phone":"+1 972 772 7998",
    "sg:postcode":"75087",
    "sg:province":"TX",
    "wof:name":"Mae James Leasing LLC",
    "wof:placetype":"venue"
},
  "geometry": {"coordinates":[-96.45956099999999,32.970638],"type":"Point"}
}