{
  "type": "Feature",
  "properties": {
    "iso:country":"US",
    "sg:address":"3490 Wharton Ln",
    "sg:city":"Belton",
    "sg:classifiers":[
        {
            "category":"Real Estate",
            "subcategory":"Real Estate Services",
            "type":"Services"
        },
        {
            "category":"Real Estate",
            "subcategory":"Real Estate Agent",
            "type":"Services"
        }
    ],
    "sg:phone":"+1 254 939 6520",
    "sg:postcode":"76513",
    "sg:province":"TX",
    "sg:tags":[
        "management"
    ],
    "wof:name":"K & P Rentals",
    "wof:placetype":"venue"
},
  "geometry": {"coordinates":[-97.51275099999999,31.040615],"type":"Point"}
}