{
  "type": "Feature",
  "properties": {
    "iso:country":"US",
    "sg:address":"13270 Hunters Lark St",
    "sg:city":"San Antonio",
    "sg:classifiers":[
        {
            "category":"Professional",
            "type":"Services"
        }
    ],
    "sg:phone":"+1 210 479 3538",
    "sg:postcode":"78230",
    "sg:province":"TX",
    "wof:name":"Tc Designs",
    "wof:placetype":"venue"
},
  "geometry": {"coordinates":[-98.54953,29.56942],"type":"Point"}
}