{
  "type": "Feature",
  "properties": {
    "iso:country":"US",
    "sg:address":"203 Fletcher Dr",
    "sg:city":"Del Rio",
    "sg:classifiers":[
        {
            "category":"Personal",
            "subcategory":"Beauty Salon",
            "type":"Services"
        }
    ],
    "sg:phone":"+1 830 775 8045",
    "sg:postcode":"78840",
    "sg:province":"TX",
    "wof:name":"Chaleons Hair Studio",
    "wof:placetype":"venue"
},
  "geometry": {"coordinates":[-100.913622,29.387516],"type":"Point"}
}