{
  "type": "Feature",
  "properties": {
    "iso:country":"US",
    "sg:address":"412 FM 718",
    "sg:city":"Newark",
    "sg:classifiers":[
        {
            "category":"Restaurant",
            "type":"Food & Drink"
        }
    ],
    "sg:phone":"+1 817 489 5900",
    "sg:postcode":"76071",
    "sg:province":"TX",
    "sg:tags":[
        "eating"
    ],
    "wof:name":"Big Eds Texan CAF",
    "wof:placetype":"venue"
},
  "geometry": {"coordinates":[-97.493661,33.008242],"type":"Point"}
}