{
  "type": "Feature",
  "properties": {
    "iso:country":"US",
    "sg:address":"5210 Apple Blossom Ln",
    "sg:city":"Friendswood",
    "sg:classifiers":[
        {
            "category":"Shopping",
            "subcategory":"Gifts & Souvenirs",
            "type":"Retail Goods"
        }
    ],
    "sg:phone":"+1 281 482 6711",
    "sg:postcode":"77546",
    "sg:province":"TX",
    "wof:name":"R & L Gifts",
    "wof:placetype":"venue"
},
  "geometry": {"coordinates":[-95.18571300000001,29.534802],"type":"Point"}
}