{
  "type": "Feature",
  "properties": {
    "iso:country":"US",
    "sg:address":"4505 Spicewood Springs Road",
    "sg:city":"Austin",
    "sg:classifiers":[
        {
            "category":"Banks & Credit Unions",
            "subcategory":"Financial Services",
            "type":"Services"
        }
    ],
    "sg:phone":"+1 512 795 2870",
    "sg:postcode":"78759",
    "sg:province":"TX",
    "sg:tags":[
        "broker",
        "mortgage"
    ],
    "wof:name":"Easter Mortgage Services",
    "wof:placetype":"venue"
},
  "geometry": {"coordinates":[-97.75913,30.374243],"type":"Point"}
}