{
  "type": "Feature",
  "properties": {
    "iso:country":"US",
    "sg:address":"2916 Ruidosa Ave",
    "sg:city":"Dallas",
    "sg:classifiers":[
        {
            "category":"Real Estate",
            "subcategory":"Real Estate Operator",
            "type":"Services"
        }
    ],
    "sg:phone":"+1 972 352 1116",
    "sg:postcode":"75228",
    "sg:province":"TX",
    "sg:tags":[
        "apartment"
    ],
    "wof:name":"Shiloh Apartment Homes",
    "wof:placetype":"venue"
},
  "geometry": {"coordinates":[-96.664985,32.845227],"type":"Point"}
}