{
  "type": "Feature",
  "properties": {
    "iso:country":"US",
    "sg:address":"1607 Whitlock Ln",
    "sg:city":"Carrollton",
    "sg:classifiers":[
        {
            "category":"Autos & Motor Vehicles",
            "subcategory":"Automobile Sales",
            "type":"Retail Goods"
        }
    ],
    "sg:phone":"+1 972 242 6671",
    "sg:postcode":"75006",
    "sg:province":"TX",
    "sg:tags":[
        "car",
        "used",
        "dealer"
    ],
    "wof:name":"Imports Specialist",
    "wof:placetype":"venue"
},
  "geometry": {"coordinates":[-96.916532,32.968489],"type":"Point"}
}