{
  "type": "Feature",
  "properties": {
    "iso:country":"US",
    "sg:address":"2300 N Lee Trevino Dr",
    "sg:city":"El Paso",
    "sg:classifiers":[
        {
            "category":"Organizations",
            "subcategory":"Labor Organization",
            "type":"Services"
        }
    ],
    "sg:phone":"+1 915 873 8368",
    "sg:postcode":"79936",
    "sg:province":"TX",
    "wof:name":"Nong LLC",
    "wof:placetype":"venue"
},
  "geometry": {"coordinates":[-106.32128,31.774564],"type":"Point"}
}