{
  "type": "Feature",
  "properties": {
    "iso:country":"US",
    "sg:address":"1864 Fountain View Dr",
    "sg:city":"Houston",
    "sg:classifiers":[
        {
            "category":"Personal",
            "subcategory":"Beauty Salon",
            "type":"Services"
        }
    ],
    "sg:phone":"+1 713 781 0405",
    "sg:postcode":"77057",
    "sg:province":"TX",
    "wof:name":"Jim Reynolds Hair Design",
    "wof:placetype":"venue"
},
  "geometry": {"coordinates":[-95.486056,29.748051],"type":"Point"}
}