{
  "type": "Feature",
  "properties": {
    "iso:country":"US",
    "sg:address":"2258 Regency Pt",
    "sg:city":"San Antonio",
    "sg:classifiers":[
        {
            "category":"Professional",
            "subcategory":"Business Services",
            "type":"Services"
        }
    ],
    "sg:phone":"+1 210 492 0574",
    "sg:postcode":"78231",
    "sg:province":"TX",
    "wof:name":"A Room To Go",
    "wof:placetype":"venue"
},
  "geometry": {"coordinates":[-98.53171399999999,29.567078],"type":"Point"}
}