{
  "type": "Feature",
  "properties": {
    "iso:country":"US",
    "sg:address":"1519 Hi Line Dr",
    "sg:city":"Dallas",
    "sg:classifiers":[
        {
            "category":"Manufacturing",
            "subcategory":"Textiles",
            "type":"Manufacturing & Wholesale Goods"
        }
    ],
    "sg:phone":"+1 214 749 0663",
    "sg:postcode":"75207",
    "sg:province":"TX",
    "sg:tags":[
        "rug",
        "carpet"
    ],
    "wof:name":"Collins & Aikman Floor Cvrng",
    "wof:placetype":"venue"
},
  "geometry": {"coordinates":[-96.81683200000001,32.794677],"type":"Point"}
}