{
  "type": "Feature",
  "properties": {
    "iso:country":"US",
    "sg:address":"5400 N Lamar Boulevard Suite 207",
    "sg:city":"Austin",
    "sg:classifiers":[
        {
            "category":"Building & Trades",
            "subcategory":"Plumbing",
            "type":"Services"
        }
    ],
    "sg:phone":"+1 512 458 9451",
    "sg:postcode":"78751",
    "sg:province":"TX",
    "sg:tags":[
        "plumber",
        "industrial",
        "contractors-commercial"
    ],
    "sg:website":"www.marshallplumbing.com",
    "wof:name":"Marshall Plumbing",
    "wof:placetype":"venue"
},
  "geometry": {"coordinates":[-97.728849,30.322002],"type":"Point"}
}