{
  "type": "Feature",
  "properties": {
    "iso:country":"US",
    "sg:address":"7211 Barton Oaks Dr",
    "sg:city":"Houston",
    "sg:classifiers":[
        {
            "category":"Building & Trades",
            "subcategory":"Construction",
            "type":"Services"
        }
    ],
    "sg:phone":"+1 281 859 6121",
    "sg:postcode":"77095",
    "sg:province":"TX",
    "sg:tags":[
        "contractor"
    ],
    "wof:name":"S&R Fence Co",
    "wof:placetype":"venue"
},
  "geometry": {"coordinates":[-95.667087,29.882808],"type":"Point"}
}