{
  "type": "Feature",
  "properties": {
    "iso:country":"US",
    "sg:address":"9918 W I- 20",
    "sg:city":"Midland",
    "sg:classifiers":[
        {
            "category":"Wholesale",
            "subcategory":"Computers",
            "type":"Manufacturing & Wholesale Goods"
        }
    ],
    "sg:phone":"+1 432 563 5804",
    "sg:postcode":"79706",
    "sg:province":"TX",
    "wof:name":"Midessa Computer Systems Inc",
    "wof:placetype":"venue"
},
  "geometry": {"coordinates":[-102.207278,31.916054],"type":"Point"}
}