{
  "type": "Feature",
  "properties": {
    "iso:country":"US",
    "sg:address":"1119 Marine Point Dr",
    "sg:city":"Strawn",
    "sg:classifiers":[
        {
            "category":"Autos & Motor Vehicles",
            "subcategory":"Boat Sales",
            "type":"Retail Goods"
        }
    ],
    "sg:phone":"+1 940 779 3911",
    "sg:postcode":"76475",
    "sg:province":"TX",
    "wof:name":"Bluff Creek Marina Sales & Svc",
    "wof:placetype":"venue"
},
  "geometry": {"coordinates":[-98.491829,32.84242],"type":"Point"}
}