{
  "type": "Feature",
  "properties": {
    "iso:country":"US",
    "sg:address":"228 Spanos Ranch Rd",
    "sg:city":"Crawford",
    "sg:classifiers":[
        {
            "category":"Restaurant",
            "type":"Food & Drink"
        }
    ],
    "sg:phone":"+1 254 486 2732",
    "sg:postcode":"76638",
    "sg:province":"TX",
    "sg:tags":[
        "eating"
    ],
    "wof:name":"Spanos Coffee Station Inc",
    "wof:placetype":"venue"
},
  "geometry": {"coordinates":[-97.503156,31.516953],"type":"Point"}
}