{
  "type": "Feature",
  "properties": {
    "iso:country":"US",
    "sg:address":"2218 Atkinson Dr",
    "sg:city":"Lufkin",
    "sg:classifiers":[
        {
            "category":"Food & Beverages",
            "subcategory":"Groceries & Convenience Stores",
            "type":"Retail Goods"
        }
    ],
    "sg:phone":"+1 936 634 3120",
    "sg:postcode":"75901",
    "sg:province":"TX",
    "sg:tags":[
        "market"
    ],
    "wof:name":"Boles Food Market",
    "wof:placetype":"venue"
},
  "geometry": {"coordinates":[-94.69918,31.351448],"type":"Point"}
}