{
  "type": "Feature",
  "properties": {
    "iso:country":"US",
    "sg:address":"200 E Houston St",
    "sg:city":"San Antonio",
    "sg:classifiers":[
        {
            "category":"Professional",
            "type":"Services"
        }
    ],
    "sg:phone":"+1 210 354 1200",
    "sg:postcode":"78205",
    "sg:province":"TX",
    "sg:tags":[
        "establishment"
    ],
    "wof:name":"Davenport",
    "wof:placetype":"venue"
},
  "geometry": {"coordinates":[-98.48972500000001,29.426472],"type":"Point"}
}