{
  "type": "Feature",
  "properties": {
    "iso:country":"US",
    "sg:address":"507 E Malone St",
    "sg:city":"Celina",
    "sg:classifiers":[
        {
            "category":"Education",
            "subcategory":"School",
            "type":"Public Place"
        }
    ],
    "sg:phone":"+1 972 382 8996",
    "sg:postcode":"75009",
    "sg:province":"TX",
    "wof:name":"Celina Intermediate School",
    "wof:placetype":"venue"
},
  "geometry": {"coordinates":[-96.77979999999999,33.327202],"type":"Point"}
}