{
  "type": "Feature",
  "properties": {
    "iso:country":"US",
    "sg:address":"7601 N MacArthur Blvd",
    "sg:city":"Irving",
    "sg:classifiers":[
        {
            "category":"Restaurant",
            "type":"Food & Drink"
        }
    ],
    "sg:phone":"+1 972 869 9800",
    "sg:postcode":"75063",
    "sg:province":"TX",
    "wof:name":"Tin Star Las Colinas",
    "wof:placetype":"venue"
},
  "geometry": {"coordinates":[-96.9589,32.91],"type":"Point"}
}