{
  "type": "Feature",
  "properties": {
    "iso:country":"US",
    "sg:address":"2305 E Main St",
    "sg:city":"Uvalde",
    "sg:classifiers":[
        {
            "category":"Wholesale",
            "subcategory":"Machinery & Supplies",
            "type":"Manufacturing & Wholesale Goods"
        }
    ],
    "sg:phone":"+1 830 278 5628",
    "sg:postcode":"78801",
    "sg:province":"TX",
    "sg:tags":[
        "farm",
        "equipment",
        "heavy",
        "agriculture"
    ],
    "wof:name":"Uvalde Tractor & Implement Inc",
    "wof:placetype":"venue"
},
  "geometry": {"coordinates":[-99.76352199999999,29.222032],"type":"Point"}
}