{
  "type": "Feature",
  "properties": {
    "iso:country":"US",
    "sg:address":"8343 Howard Dr",
    "sg:city":"Houston",
    "sg:classifiers":[
        {
            "category":"Building & Trades",
            "subcategory":"Plumbing",
            "type":"Services"
        }
    ],
    "sg:phone":"+1 713 643 0889",
    "sg:postcode":"77017",
    "sg:province":"TX",
    "sg:tags":[
        "contractor"
    ],
    "sg:website":"www.national-plumbing.com",
    "wof:name":"National Plumbing Co",
    "wof:placetype":"venue"
},
  "geometry": {"coordinates":[-95.259201,29.6824],"type":"Point"}
}