{
  "type": "Feature",
  "properties": {
    "iso:country":"US",
    "sg:address":"6101 Southwest Fwy",
    "sg:city":"Houston",
    "sg:classifiers":[
        {
            "category":"Building & Trades",
            "subcategory":"Cleaning & Sanitation",
            "type":"Services"
        }
    ],
    "sg:phone":"+1 713 592 9092",
    "sg:postcode":"77057",
    "sg:province":"TX",
    "sg:tags":[
        "house"
    ],
    "wof:name":"Conquest Maintenance",
    "wof:placetype":"venue"
},
  "geometry": {"coordinates":[-95.48764,29.725472],"type":"Point"}
}