{
  "type": "Feature",
  "properties": {
    "iso:country":"US",
    "sg:address":"1411 Commerce St",
    "sg:city":"Dallas",
    "sg:classifiers":[
        {
            "category":"Local Transit",
            "type":"Transportation"
        }
    ],
    "sg:phone":"+1 972 670 6646",
    "sg:postcode":"75201",
    "sg:province":"TX",
    "sg:tags":[
        "limousine"
    ],
    "wof:name":"Allen Limousine Svc Of Dallas",
    "wof:placetype":"venue"
},
  "geometry": {"coordinates":[-96.798649,32.780048],"type":"Point"}
}