{
  "type": "Feature",
  "properties": {
    "iso:country":"US",
    "sg:address":"4417 Harrison St",
    "sg:city":"Waco",
    "sg:classifiers":[
        {
            "category":"Organizations",
            "subcategory":"Religious Organization",
            "type":"Services"
        }
    ],
    "sg:phone":"+1 254 799 1699",
    "sg:postcode":"76705",
    "sg:province":"TX",
    "wof:name":"Oasis Ministries Internat",
    "wof:placetype":"venue"
},
  "geometry": {"coordinates":[-97.07961899999999,31.603085],"type":"Point"}
}