{
  "type": "Feature",
  "properties": {
    "iso:country":"US",
    "sg:address":"1612 Allen Dr",
    "sg:city":"Cedar Hill",
    "sg:classifiers":[
        {
            "category":"Professional",
            "subcategory":"Business Services",
            "type":"Services"
        }
    ],
    "sg:phone":"+1 469 272 3599",
    "sg:postcode":"75104",
    "sg:province":"TX",
    "wof:name":"Cad Group Productions",
    "wof:placetype":"venue"
},
  "geometry": {"coordinates":[-96.939578,32.623998],"type":"Point"}
}