{
  "type": "Feature",
  "properties": {
    "iso:country":"US",
    "sg:address":"125 E Main St",
    "sg:city":"Cuero",
    "sg:classifiers":[
        {
            "category":"Personal",
            "subcategory":"Beauty Salon",
            "type":"Services"
        }
    ],
    "sg:phone":"+1 361 277 8220",
    "sg:postcode":"77954",
    "sg:province":"TX",
    "sg:tags":[
        "shop",
        "spa",
        "day"
    ],
    "wof:name":"125 Main Hair and Day Spa",
    "wof:placetype":"venue"
},
  "geometry": {"coordinates":[-97.291319,29.090391],"type":"Point"}
}