{
  "type": "Feature",
  "properties": {
    "iso:country":"US",
    "sg:address":"10804 Fallstone Rd",
    "sg:city":"Houston",
    "sg:classifiers":[
        {
            "category":"Manufacturing",
            "subcategory":"Apparel",
            "type":"Manufacturing & Wholesale Goods"
        }
    ],
    "sg:phone":"+1 281 879 5270",
    "sg:postcode":"77099",
    "sg:province":"TX",
    "sg:tags":[
        "household",
        "furnishing",
        "mfg"
    ],
    "wof:name":"Creative Quilting & Spreads",
    "wof:placetype":"venue"
},
  "geometry": {"coordinates":[-95.56756,29.661007],"type":"Point"}
}