{
  "type": "Feature",
  "properties": {
    "iso:country":"US",
    "sg:address":"1615 W Airport Fwy",
    "sg:city":"Irving",
    "sg:classifiers":[
        {
            "category":"Organizations",
            "subcategory":"Religious Organization",
            "type":"Services"
        }
    ],
    "sg:phone":"+1 972 255 4185",
    "sg:postcode":"75062",
    "sg:province":"TX",
    "sg:website":"www.umc.org",
    "wof:name":"Plymouth Park United Methodist Church",
    "wof:placetype":"venue"
},
  "geometry": {"coordinates":[-96.96729999999999,32.8372],"type":"Point"}
}