{
  "type": "Feature",
  "properties": {
    "iso:country":"US",
    "sg:address":"2012 Northmoor Way",
    "sg:city":"Carrollton",
    "sg:classifiers":[
        {
            "category":"Professional",
            "subcategory":"Business Services",
            "type":"Services"
        }
    ],
    "sg:phone":"+1 972 242 3337",
    "sg:postcode":"75006",
    "sg:province":"TX",
    "wof:name":"Jewels of Sky Kiters Assoc",
    "wof:placetype":"venue"
},
  "geometry": {"coordinates":[-96.88752100000001,32.984548],"type":"Point"}
}