{
  "type": "Feature",
  "properties": {
    "iso:country":"US",
    "sg:address":"2405 Lemmontree Ln",
    "sg:city":"Plano",
    "sg:classifiers":[
        {
            "category":"Shopping",
            "subcategory":"Clothing, Apparel, & Fashions",
            "type":"Retail Goods"
        }
    ],
    "sg:phone":"+1 972 422 7674",
    "sg:postcode":"75074",
    "sg:province":"TX",
    "wof:name":"Awesome Words of Inspiration",
    "wof:placetype":"venue"
},
  "geometry": {"coordinates":[-96.68114300000001,33.033206],"type":"Point"}
}