{
  "type": "Feature",
  "properties": {
    "iso:country":"US",
    "sg:address":"2558 W Commerce St",
    "sg:city":"Dallas",
    "sg:classifiers":[
        {
            "category":"Freight",
            "type":"Transportation"
        }
    ],
    "sg:phone":"+1 214 638 2401",
    "sg:postcode":"75212",
    "sg:province":"TX",
    "sg:tags":[
        "warehouse"
    ],
    "wof:name":"Rol Manufacturing of America",
    "wof:placetype":"venue"
},
  "geometry": {"coordinates":[-96.86344699999999,32.77356],"type":"Point"}
}