{
  "type": "Feature",
  "properties": {
    "iso:country":"US",
    "sg:address":"3406 Kewanee Ave",
    "sg:city":"Lubbock",
    "sg:classifiers":[
        {
            "category":"Building & Trades",
            "subcategory":"Plumbing",
            "type":"Services"
        }
    ],
    "sg:phone":"+1 806 797 2204",
    "sg:postcode":"79407",
    "sg:province":"TX",
    "sg:tags":[
        "contractor"
    ],
    "wof:name":"SPD Services",
    "wof:placetype":"venue"
},
  "geometry": {"coordinates":[-101.952811,33.561931],"type":"Point"}
}