{
  "type": "Feature",
  "properties": {
    "iso:country":"US",
    "sg:address":"209 E Garfield St",
    "sg:city":"Del Rio",
    "sg:classifiers":[
        {
            "category":"Organizations",
            "subcategory":"Community Association",
            "type":"Services"
        }
    ],
    "sg:phone":"+1 830 774 5271",
    "sg:postcode":"78840",
    "sg:province":"TX",
    "wof:name":"Boy Scout Troop 271",
    "wof:placetype":"venue"
},
  "geometry": {"coordinates":[-100.897811,29.361361],"type":"Point"}
}