{
  "type": "Feature",
  "properties": {
    "iso:country":"US",
    "sg:address":"5603 72nd St",
    "sg:city":"Lubbock",
    "sg:classifiers":[
        {
            "category":"Wholesale",
            "subcategory":"Home Furnishings",
            "type":"Manufacturing & Wholesale Goods"
        }
    ],
    "sg:phone":"+1 806 798 8500",
    "sg:postcode":"79424",
    "sg:province":"TX",
    "wof:name":"Tupperware",
    "wof:placetype":"venue"
},
  "geometry": {"coordinates":[-101.93535900000001,33.528164],"type":"Point"}
}