{
  "type": "Feature",
  "properties": {
    "iso:country":"US",
    "sg:address":"17215 Veterans Dr",
    "sg:city":"Manvel",
    "sg:classifiers":[
        {
            "category":"Building & Trades",
            "subcategory":"Construction",
            "type":"Services"
        }
    ],
    "sg:phone":"+1 281 489 1190",
    "sg:postcode":"77584",
    "sg:province":"TX",
    "sg:tags":[
        "insulation",
        "heat",
        "contractor"
    ],
    "wof:name":"Larsen Insulation Contractor",
    "wof:placetype":"venue"
},
  "geometry": {"coordinates":[-95.289006,29.527928],"type":"Point"}
}