{
  "type": "Feature",
  "properties": {
    "iso:country":"US",
    "sg:address":"2548 Bitters Rd",
    "sg:city":"San Antonio",
    "sg:classifiers":[
        {
            "category":"Building & Trades",
            "subcategory":"Plumbing",
            "type":"Services"
        }
    ],
    "sg:phone":"+1 210 494 5493",
    "sg:postcode":"78217",
    "sg:province":"TX",
    "sg:tags":[
        "conditioning",
        "air",
        "system",
        "contractor"
    ],
    "wof:name":"Paschal-Harper Inc",
    "wof:placetype":"venue"
},
  "geometry": {"coordinates":[-98.448826,29.533313],"type":"Point"}
}