{
  "type": "Feature",
  "properties": {
    "iso:country":"US",
    "sg:address":"811 S Ripple Creek Dr",
    "sg:city":"Houston",
    "sg:classifiers":[
        {
            "category":"Professional",
            "subcategory":"Management & Consulting",
            "type":"Services"
        }
    ],
    "sg:phone":"+1 713 984 8070",
    "sg:postcode":"77057",
    "sg:province":"TX",
    "sg:tags":[
        "business"
    ],
    "wof:name":"Holco Holck Leadership Conslt",
    "wof:placetype":"venue"
},
  "geometry": {"coordinates":[-95.497074,29.758357],"type":"Point"}
}