{
  "type": "Feature",
  "properties": {
    "iso:country":"US",
    "sg:address":"1114 S E St",
    "sg:city":"Harlingen",
    "sg:classifiers":[
        {
            "category":"Restaurant",
            "type":"Food & Drink"
        }
    ],
    "sg:phone":"+1 956 423 6965",
    "sg:postcode":"78550",
    "sg:province":"TX",
    "sg:tags":[
        "eating"
    ],
    "wof:name":"Dannys Restaurant",
    "wof:placetype":"venue"
},
  "geometry": {"coordinates":[-97.701155,26.182581],"type":"Point"}
}