{
  "type": "Feature",
  "properties": {
    "iso:country":"US",
    "sg:address":"15015 Blue Ridge Rd",
    "sg:city":"Missouri City",
    "sg:classifiers":[
        {
            "category":"Shopping",
            "subcategory":"Books",
            "type":"Retail Goods"
        }
    ],
    "sg:phone":"+1 281 438 5536",
    "sg:postcode":"77489",
    "sg:province":"TX",
    "wof:name":"Fedsa Enterprises",
    "wof:placetype":"venue"
},
  "geometry": {"coordinates":[-95.493008,29.608667],"type":"Point"}
}