{
  "type": "Feature",
  "properties": {
    "iso:country":"US",
    "sg:address":"3300 Killingsworth Ln",
    "sg:city":"Pflugerville",
    "sg:classifiers":[
        {
            "category":"Professional",
            "subcategory":"Business Services",
            "type":"Services"
        }
    ],
    "sg:phone":"+1 956 346 2173",
    "sg:postcode":"78660",
    "sg:province":"TX",
    "wof:name":"Dental Account Co Dac",
    "wof:placetype":"venue"
},
  "geometry": {"coordinates":[-97.610591,30.414985],"type":"Point"}
}