{
  "type": "Feature",
  "properties": {
    "iso:country":"US",
    "sg:address":"13154 Coit Rd",
    "sg:city":"Dallas",
    "sg:classifiers":[
        {
            "category":"Professional",
            "subcategory":"Business Services",
            "type":"Services"
        }
    ],
    "sg:phone":"+1 972 907 9000",
    "sg:postcode":"75240",
    "sg:province":"TX",
    "sg:tags":[
        "inventory"
    ],
    "wof:name":"RGIS Inventory Specialist",
    "wof:placetype":"venue"
},
  "geometry": {"coordinates":[-96.76909999999999,32.928337],"type":"Point"}
}