{
  "type": "Feature",
  "properties": {
    "iso:country":"US",
    "sg:address":"1310 Madera Ct",
    "sg:city":"Keller",
    "sg:classifiers":[
        {
            "category":"Professional",
            "subcategory":"Business Services",
            "type":"Services"
        }
    ],
    "sg:phone":"+1 817 427 4737",
    "sg:postcode":"76248",
    "sg:province":"TX",
    "wof:name":"Designer House",
    "wof:placetype":"venue"
},
  "geometry": {"coordinates":[-97.224013,32.909465],"type":"Point"}
}