{
  "type": "Feature",
  "properties": {
    "iso:country":"US",
    "sg:address":"713 E 17th St",
    "sg:city":"Houston",
    "sg:classifiers":[
        {
            "category":"Professional",
            "type":"Services"
        }
    ],
    "sg:phone":"+1 713 553 6082",
    "sg:postcode":"77008",
    "sg:province":"TX",
    "wof:name":"Dot Sisters Printong & Accesso",
    "wof:placetype":"venue"
},
  "geometry": {"coordinates":[-95.389884,29.800757],"type":"Point"}
}