{
  "type": "Feature",
  "properties": {
    "iso:country":"US",
    "sg:address":"11219 Ashford Pt",
    "sg:city":"Sugar Land",
    "sg:classifiers":[
        {
            "category":"Wholesale",
            "subcategory":"Apparel",
            "type":"Manufacturing & Wholesale Goods"
        }
    ],
    "sg:phone":"+1 281 242 5756",
    "sg:postcode":"77478",
    "sg:province":"TX",
    "sg:tags":[
        "clothing"
    ],
    "wof:name":"Tropical Collections Company",
    "wof:placetype":"venue"
},
  "geometry": {"coordinates":[-95.598376,29.657225],"type":"Point"}
}