{
  "type": "Feature",
  "properties": {
    "iso:country":"US",
    "sg:address":"823 Patton Ave",
    "sg:city":"Austin",
    "sg:classifiers":[
        {
            "category":"Professional",
            "subcategory":"Accounting & Tax Preparation",
            "type":"Services"
        }
    ],
    "sg:phone":"+1 512 385 5471",
    "sg:postcode":"78742",
    "sg:province":"TX",
    "sg:tags":[
        "return",
        "filing"
    ],
    "wof:name":"Rodney Krawl Tax Svc",
    "wof:placetype":"venue"
},
  "geometry": {"coordinates":[-97.68110299999999,30.23272],"type":"Point"}
}