{
  "type": "Feature",
  "properties": {
    "iso:country":"US",
    "sg:address":"517 S Mesa St",
    "sg:city":"El Paso",
    "sg:classifiers":[
        {
            "category":"Shopping",
            "subcategory":"Gifts & Souvenirs",
            "type":"Retail Goods"
        }
    ],
    "sg:phone":"+1 915 532 0792",
    "sg:postcode":"79901",
    "sg:province":"TX",
    "wof:name":"LA Estrella",
    "wof:placetype":"venue"
},
  "geometry": {"coordinates":[-106.48566,31.754005],"type":"Point"}
}