{
  "type": "Feature",
  "properties": {
    "iso:country":"US",
    "sg:address":"7918 Kings Reach",
    "sg:city":"San Antonio",
    "sg:classifiers":[
        {
            "category":"Real Estate",
            "subcategory":"Real Estate Agent",
            "type":"Services"
        }
    ],
    "sg:phone":"+1 210 821 6655",
    "sg:postcode":"78209",
    "sg:province":"TX",
    "wof:name":"Judy Rohm & Assoc",
    "wof:placetype":"venue"
},
  "geometry": {"coordinates":[-98.462583,29.508731],"type":"Point"}
}