{
  "type": "Feature",
  "properties": {
    "iso:country":"US",
    "sg:address":"908 N Canyonwood Dr",
    "sg:city":"Dripping Springs",
    "sg:classifiers":[
        {
            "category":"Manufacturing",
            "subcategory":"Printing",
            "type":"Manufacturing & Wholesale Goods"
        }
    ],
    "sg:phone":"+1 512 858 5208",
    "sg:postcode":"78620",
    "sg:province":"TX",
    "sg:tags":[
        "book"
    ],
    "wof:name":"Growing In Grief Center",
    "wof:placetype":"venue"
},
  "geometry": {"coordinates":[-98.034659,30.212942],"type":"Point"}
}