{
  "type": "Feature",
  "properties": {
    "iso:country":"US",
    "sg:address":"580 Fm 3237 Apt C",
    "sg:city":"Wimberley",
    "sg:classifiers":[
        {
            "category":"Professional",
            "subcategory":"Lawyer & Legal Services",
            "type":"Services"
        }
    ],
    "sg:phone":"+1 512 847 0250",
    "sg:postcode":"78676",
    "sg:province":"TX",
    "sg:tags":[
        "attorney",
        "practice"
    ],
    "wof:name":"The Tom Fulkerson Law Offices Of P",
    "wof:placetype":"venue"
},
  "geometry": {"coordinates":[-98.084991,29.998833],"type":"Point"}
}