{
  "type": "Feature",
  "properties": {
    "iso:country":"US",
    "sg:address":"8507 Louisville Dr",
    "sg:city":"Lubbock",
    "sg:classifiers":[
        {
            "category":"Shopping",
            "type":"Retail Goods"
        }
    ],
    "sg:phone":"+1 806 797 6475",
    "sg:postcode":"79423",
    "sg:province":"TX",
    "sg:tags":[
        "merchandise"
    ],
    "wof:name":"Hodges Arts",
    "wof:placetype":"venue"
},
  "geometry": {"coordinates":[-101.893568,33.514168],"type":"Point"}
}