{
  "type": "Feature",
  "properties": {
    "iso:country":"US",
    "sg:address":"3910 Fairmont Pkwy",
    "sg:city":"Pasadena",
    "sg:classifiers":[
        {
            "category":"Professional",
            "type":"Services"
        }
    ],
    "sg:phone":"+1 281 991 5080",
    "sg:postcode":"77504",
    "sg:province":"TX",
    "wof:name":"Merchant John",
    "wof:placetype":"venue"
},
  "geometry": {"coordinates":[-95.18894400000001,29.651328],"type":"Point"}
}