{
  "type": "Feature",
  "properties": {
    "iso:country":"US",
    "sg:address":"5204 E Ben White Blvd",
    "sg:city":"Austin",
    "sg:classifiers":[
        {
            "category":"Wholesale",
            "subcategory":"Electrical",
            "type":"Manufacturing & Wholesale Goods"
        }
    ],
    "sg:phone":"+1 512 691 8500",
    "sg:postcode":"78741",
    "sg:province":"TX",
    "sg:tags":[
        "electronic"
    ],
    "wof:name":"Spansion",
    "wof:placetype":"venue"
},
  "geometry": {"coordinates":[-97.716325,30.212922],"type":"Point"}
}