{
  "type": "Feature",
  "properties": {
    "iso:country":"US",
    "sg:address":"4200 Lockfield St",
    "sg:city":"Houston",
    "sg:classifiers":[
        {
            "category":"Real Estate",
            "subcategory":"Real Estate Operator",
            "type":"Services"
        }
    ],
    "sg:phone":"+1 866 534 4268",
    "sg:postcode":"77092",
    "sg:province":"TX",
    "sg:tags":[
        "apartment"
    ],
    "sg:website":"http://local.ingenio.com/Listings/Details.aspx?NUM=a%3a10238054%3a13%3a4859924%3a14%3a0%3a7",
    "wof:name":"Crossings At Willow Bend",
    "wof:placetype":"venue"
},
  "geometry": {"coordinates":[-95.486864,29.83091],"type":"Point"}
}