{
  "type": "Feature",
  "properties": {
    "iso:country":"US",
    "sg:address":"2420 113th St",
    "sg:city":"Grand Prairie",
    "sg:classifiers":[
        {
            "category":"Building & Trades",
            "subcategory":"Landscaping Services",
            "type":"Services"
        }
    ],
    "sg:phone":"+1 972 647 0026",
    "sg:postcode":"75050",
    "sg:province":"TX",
    "sg:tags":[
        "lawn",
        "maintenance",
        "grounds"
    ],
    "wof:name":"Tru Green Chem Lawn",
    "wof:placetype":"venue"
},
  "geometry": {"coordinates":[-97.042035,32.788826],"type":"Point"}
}