{
  "type": "Feature",
  "properties": {
    "iso:country":"US",
    "sg:address":"1414 Pirates Cove",
    "sg:city":"Houston",
    "sg:classifiers":[
        {
            "category":"Professional",
            "subcategory":"Accounting & Tax Preparation",
            "type":"Services"
        }
    ],
    "sg:phone":"+1 281 333 2574",
    "sg:postcode":"77058",
    "sg:province":"TX",
    "wof:name":"Stuart L Leiss CPA",
    "wof:placetype":"venue"
},
  "geometry": {"coordinates":[-95.092581,29.539324],"type":"Point"}
}