{
  "type": "Feature",
  "properties": {
    "iso:country":"US",
    "sg:address":"816 Park Dr",
    "sg:city":"La Porte",
    "sg:classifiers":[
        {
            "category":"Organizations",
            "subcategory":"Religious Organization",
            "type":"Services"
        }
    ],
    "sg:phone":"+1 281 471 2000",
    "sg:postcode":"77571",
    "sg:province":"TX",
    "wof:name":"St Marys Catholic Church",
    "wof:placetype":"venue"
},
  "geometry": {"coordinates":[-95.011522,29.655799],"type":"Point"}
}