{
  "type": "Feature",
  "properties": {
    "iso:country":"US",
    "sg:address":"2618 S Flores St",
    "sg:city":"San Antonio",
    "sg:classifiers":[
        {
            "category":"Shopping",
            "subcategory":"Jewelry",
            "type":"Retail Goods"
        }
    ],
    "sg:phone":"+1 210 223 3800",
    "sg:postcode":"78204",
    "sg:province":"TX",
    "wof:name":"Lindas Treasures",
    "wof:placetype":"venue"
},
  "geometry": {"coordinates":[-98.50445499999999,29.398234],"type":"Point"}
}