{
  "type": "Feature",
  "properties": {
    "iso:country":"US",
    "sg:address":"501 Holland",
    "sg:city":"Galena Park",
    "sg:classifiers":[
        {
            "category":"Building & Trades",
            "subcategory":"Electrical",
            "type":"Services"
        }
    ],
    "sg:phone":"+1 713 290 1131",
    "sg:postcode":"77547",
    "sg:province":"TX",
    "sg:tags":[
        "electrical",
        "contractor"
    ],
    "wof:name":"Allamo Siding and Roofing",
    "wof:placetype":"venue"
},
  "geometry": {"coordinates":[-95.232895,29.736133],"type":"Point"}
}