{
  "type": "Feature",
  "properties": {
    "iso:country":"US",
    "sg:address":"402 Oak St",
    "sg:city":"Texarkana",
    "sg:classifiers":[
        {
            "category":"Professional",
            "subcategory":"Testing Lab",
            "type":"Services"
        }
    ],
    "sg:phone":"+1 903 793 4563",
    "sg:postcode":"75501",
    "sg:province":"TX",
    "sg:tags":[
        "laboratory"
    ],
    "wof:name":"Rain",
    "wof:placetype":"venue"
},
  "geometry": {"coordinates":[-94.048905,33.422331],"type":"Point"}
}