{
  "type": "Feature",
  "properties": {
    "iso:country":"US",
    "sg:address":"10677 E Northwest Hwy",
    "sg:city":"Dallas",
    "sg:classifiers":[
        {
            "category":"Professional",
            "subcategory":"Printing & Photocopies",
            "type":"Services"
        }
    ],
    "sg:phone":"+1 214 553 8500",
    "sg:postcode":"75238",
    "sg:province":"TX",
    "sg:tags":[
        "duplicating",
        "copying"
    ],
    "wof:name":"Eagle Postal Ctr",
    "wof:placetype":"venue"
},
  "geometry": {"coordinates":[-96.70303,32.864361],"type":"Point"}
}