{
  "type": "Feature",
  "properties": {
    "iso:country":"US",
    "sg:address":"600 US Hwy 281 S",
    "sg:city":"Johnson City",
    "sg:classifiers":[
        {
            "category":"Real Estate",
            "subcategory":"Real Estate Agent",
            "type":"Services"
        }
    ],
    "sg:phone":"+1 830 868 7678",
    "sg:postcode":"78636",
    "sg:province":"TX",
    "wof:name":"R & R Smith Investments",
    "wof:placetype":"venue"
},
  "geometry": {"coordinates":[-98.39899699999999,30.270172],"type":"Point"}
}