{
  "type": "Feature",
  "properties": {
    "iso:country":"US",
    "sg:address":"9900 Westpark Dr",
    "sg:city":"Houston",
    "sg:classifiers":[
        {
            "category":"Professional",
            "subcategory":"Engineering",
            "type":"Services"
        }
    ],
    "sg:phone":"+1 713 954 0141",
    "sg:postcode":"77063",
    "sg:province":"TX",
    "sg:tags":[
        "heavy",
        "construction",
        "engineer"
    ],
    "wof:name":"Kellogg Brown & Root Services",
    "wof:placetype":"venue"
},
  "geometry": {"coordinates":[-95.534345,29.720263],"type":"Point"}
}