{
  "type": "Feature",
  "properties": {
    "iso:country":"US",
    "sg:address":"2495 E Long Ave",
    "sg:city":"Fort Worth",
    "sg:classifiers":[
        {
            "category":"Railroad",
            "type":"Transportation"
        }
    ],
    "sg:phone":"+1 817 222 9798",
    "sg:postcode":"76106",
    "sg:province":"TX",
    "sg:tags":[
        "rail"
    ],
    "wof:name":"Fort Worth & Western Railroad",
    "wof:placetype":"venue"
},
  "geometry": {"coordinates":[-97.31587500000001,32.809141],"type":"Point"}
}