{
  "type": "Feature",
  "properties": {
    "iso:country":"US",
    "sg:address":"214 E 6th St",
    "sg:city":"Austin",
    "sg:classifiers":[
        {
            "category":"Bars & Pubs",
            "type":"Food & Drink"
        },
        {
            "category":"Bars & Pubs",
            "subcategory":"Lounge",
            "type":"Food & Drink"
        },
        {
            "category":"Restaurant",
            "type":"Food & Drink"
        },
        {
            "category":"Bars & Pubs",
            "subcategory":"Sports Bar",
            "type":"Food & Drink"
        }
    ],
    "sg:phone":"+1 512 469 0001",
    "sg:postcode":"78701",
    "sg:province":"TX",
    "sg:tags":[
        "grill",
        "brew",
        "cocktail"
    ],
    "sg:website":"www.bikinissportsbarandgrill.com",
    "wof:name":"Bikini's Sports Bar & Grill",
    "wof:placetype":"venue"
},
  "geometry": {"coordinates":[-97.740692,30.267775],"type":"Point"}
}