{
  "type": "Feature",
  "properties": {
    "iso:country":"US",
    "sg:address":"2127 Bissonnet St",
    "sg:city":"Houston",
    "sg:classifiers":[
        {
            "category":"Professional",
            "subcategory":"Business Services",
            "type":"Services"
        }
    ],
    "sg:phone":"+1 713 942 7175",
    "sg:postcode":"77005",
    "sg:province":"TX",
    "wof:name":"Degner Enterprise LLC",
    "wof:placetype":"venue"
},
  "geometry": {"coordinates":[-95.41009099999999,29.725514],"type":"Point"}
}