{
  "type": "Feature",
  "properties": {
    "iso:country":"US",
    "sg:address":"402 N Nursery Rd Ste 118",
    "sg:city":"Irving",
    "sg:classifiers":[
        {
            "category":"Retail",
            "subcategory":"Auto Repair",
            "type":"Services"
        }
    ],
    "sg:phone":"+1 972 579 3466",
    "sg:postcode":"75061",
    "sg:province":"TX",
    "sg:tags":[
        "body",
        "shop"
    ],
    "wof:name":"Sam's Body Shop",
    "wof:placetype":"venue"
},
  "geometry": {"coordinates":[-96.934303,32.815102],"type":"Point"}
}