{
  "type": "Feature",
  "properties": {
    "iso:country":"US",
    "sg:address":"3422 Pemberton Dr",
    "sg:city":"Pearland",
    "sg:classifiers":[
        {
            "category":"Manufacturing",
            "subcategory":"Metals",
            "type":"Manufacturing & Wholesale Goods"
        }
    ],
    "sg:phone":"+1 281 692 0923",
    "sg:postcode":"77584",
    "sg:province":"TX",
    "sg:tags":[
        "product",
        "fabricated",
        "mfg"
    ],
    "wof:name":"Eastman Collection",
    "wof:placetype":"venue"
},
  "geometry": {"coordinates":[-95.366398,29.538512],"type":"Point"}
}