{
  "type": "Feature",
  "properties": {
    "iso:country":"US",
    "sg:address":"246 Oak Valley Dr",
    "sg:city":"La Vernia",
    "sg:classifiers":[
        {
            "category":"Wholesale",
            "subcategory":"Non-durable Goods",
            "type":"Manufacturing & Wholesale Goods"
        }
    ],
    "sg:phone":"+1 830 217 4137",
    "sg:postcode":"78121",
    "sg:province":"TX",
    "wof:name":"J & L Distributing",
    "wof:placetype":"venue"
},
  "geometry": {"coordinates":[-98.036714,29.317857],"type":"Point"}
}