{
  "type": "Feature",
  "properties": {
    "iso:country":"US",
    "sg:address":"20303 Whispering Water Way",
    "sg:city":"Cypress",
    "sg:classifiers":[
        {
            "category":"Wholesale",
            "subcategory":"Vending Machines",
            "type":"Manufacturing & Wholesale Goods"
        }
    ],
    "sg:phone":"+1 281 256 3932",
    "sg:postcode":"77433",
    "sg:province":"TX",
    "sg:tags":[
        "operator"
    ],
    "wof:name":"Michelle Lucas",
    "wof:placetype":"venue"
},
  "geometry": {"coordinates":[-95.740281,30.006791],"type":"Point"}
}