{
  "type": "Feature",
  "properties": {
    "iso:country":"US",
    "sg:address":"10422 Robindale Dr",
    "sg:city":"Dallas",
    "sg:classifiers":[
        {
            "category":"Recreation",
            "type":"Entertainment"
        }
    ],
    "sg:phone":"+1 214 349 8967",
    "sg:postcode":"75238",
    "sg:province":"TX",
    "wof:name":"Stitchin Friends",
    "wof:placetype":"venue"
},
  "geometry": {"coordinates":[-96.70482,32.885279],"type":"Point"}
}