{
  "type": "Feature",
  "properties": {
    "iso:country":"US",
    "sg:address":"1437 Pintoresco Dr",
    "sg:city":"El Paso",
    "sg:classifiers":[
        {
            "category":"Professional",
            "subcategory":"Computer Services",
            "type":"Services"
        }
    ],
    "sg:phone":"+1 915 594 1838",
    "sg:postcode":"79935",
    "sg:province":"TX",
    "wof:name":"Campos Enterprises",
    "wof:placetype":"venue"
},
  "geometry": {"coordinates":[-106.331743,31.760322],"type":"Point"}
}