{
  "type": "Feature",
  "properties": {
    "iso:country":"US",
    "sg:address":"3055 Sage Rd",
    "sg:city":"Houston",
    "sg:classifiers":[
        {
            "category":"Retail",
            "subcategory":"Laundry & Dry Cleaning",
            "type":"Services"
        }
    ],
    "sg:phone":"+1 713 622 2468",
    "sg:postcode":"77056",
    "sg:province":"TX",
    "wof:name":"A 2 Z Cleaners",
    "wof:placetype":"venue"
},
  "geometry": {"coordinates":[-95.46654100000001,29.734985],"type":"Point"}
}