{
  "type": "Feature",
  "properties": {
    "iso:country":"US",
    "sg:address":"10223 del Monte Dr",
    "sg:city":"Houston",
    "sg:classifiers":[
        {
            "category":"Professional",
            "type":"Services"
        }
    ],
    "sg:phone":"+1 713 278 2730",
    "sg:postcode":"77042",
    "sg:province":"TX",
    "wof:name":"A 1-Flash Internet Direct",
    "wof:placetype":"venue"
},
  "geometry": {"coordinates":[-95.553573,29.744765],"type":"Point"}
}