{
  "type": "Feature",
  "properties": {
    "iso:country":"US",
    "sg:address":"5801 S Staples St",
    "sg:city":"Corpus Christi",
    "sg:classifiers":[
        {
            "category":"Restaurant",
            "type":"Food & Drink"
        }
    ],
    "sg:phone":"+1 361 993 0150",
    "sg:postcode":"78413",
    "sg:province":"TX",
    "sg:tags":[
        "eating"
    ],
    "wof:name":"Little Caesars",
    "wof:placetype":"venue"
},
  "geometry": {"coordinates":[-97.377263,27.69625],"type":"Point"}
}