{
  "type": "Feature",
  "properties": {
    "iso:country":"US",
    "sg:address":"7903 Neff St",
    "sg:city":"Houston",
    "sg:classifiers":[
        {
            "category":"Banks & Credit Unions",
            "subcategory":"Financial Services",
            "type":"Services"
        }
    ],
    "sg:phone":"+1 713 774 3188",
    "sg:postcode":"77036",
    "sg:province":"TX",
    "sg:tags":[
        "trust",
        "investment",
        "real estate"
    ],
    "wof:name":"Jcomm Research Inc",
    "wof:placetype":"venue"
},
  "geometry": {"coordinates":[-95.527764,29.701409],"type":"Point"}
}