{
  "type": "Feature",
  "properties": {
    "iso:country":"US",
    "sg:address":"333 45th St",
    "sg:city":"Corpus Christi",
    "sg:classifiers":[
        {
            "category":"Wholesale",
            "subcategory":"Metals & Minerals",
            "type":"Manufacturing & Wholesale Goods"
        }
    ],
    "sg:phone":"+1 361 884 1677",
    "sg:postcode":"78405",
    "sg:province":"TX",
    "sg:tags":[
        "center"
    ],
    "wof:name":"Industrial Piping & Steel Co",
    "wof:placetype":"venue"
},
  "geometry": {"coordinates":[-97.443687,27.779314],"type":"Point"}
}