{
  "type": "Feature",
  "properties": {
    "iso:country":"US",
    "sg:address":"701 Bellaire Dr",
    "sg:city":"Killeen",
    "sg:classifiers":[
        {
            "category":"Retail",
            "subcategory":"Portrait Studio",
            "type":"Services"
        }
    ],
    "sg:phone":"+1 254 526 3936",
    "sg:postcode":"76541",
    "sg:province":"TX",
    "sg:tags":[
        "photo"
    ],
    "wof:name":"Details By Jerry",
    "wof:placetype":"venue"
},
  "geometry": {"coordinates":[-97.73486200000001,31.09825],"type":"Point"}
}