{
  "type": "Feature",
  "properties": {
    "iso:country":"US",
    "sg:address":"5608 Malvey Ave",
    "sg:city":"Fort Worth",
    "sg:classifiers":[
        {
            "category":"Professional",
            "subcategory":"Engineering",
            "type":"Services"
        }
    ],
    "sg:phone":"+1 817 735 1035",
    "sg:postcode":"76107",
    "sg:province":"TX",
    "sg:tags":[
        "engineer"
    ],
    "sg:website":"www.cnceng.com",
    "wof:name":"C & C Engineering",
    "wof:placetype":"venue"
},
  "geometry": {"coordinates":[-97.407785,32.73316],"type":"Point"}
}