{
  "type": "Feature",
  "properties": {
    "iso:country":"US",
    "sg:address":"850 Fannin St",
    "sg:city":"Beaumont",
    "sg:classifiers":[
        {
            "category":"Manufacturing",
            "subcategory":"Printing",
            "type":"Manufacturing & Wholesale Goods"
        }
    ],
    "sg:phone":"+1 409 833 8618",
    "sg:postcode":"77701",
    "sg:province":"TX",
    "sg:tags":[
        "printer"
    ],
    "sg:website":"www.beckerprint.com",
    "wof:name":"Becker Printing Co",
    "wof:placetype":"venue"
},
  "geometry": {"coordinates":[-94.10237100000001,30.078963],"type":"Point"}
}