{
  "type": "Feature",
  "properties": {
    "iso:country":"US",
    "sg:address":"965 N Garden Ridge Blvd",
    "sg:city":"Lewisville",
    "sg:classifiers":[
        {
            "category":"Health Services",
            "subcategory":"Nursing And Care Facility",
            "type":"Services"
        }
    ],
    "sg:phone":"+1 972 420 9600",
    "sg:postcode":"75077",
    "sg:province":"TX",
    "wof:name":"Sterling House of Lewisville",
    "wof:placetype":"venue"
},
  "geometry": {"coordinates":[-97.03525399999999,33.054368],"type":"Point"}
}