{
  "type": "Feature",
  "properties": {
    "iso:country":"US",
    "sg:address":"12111 W Co Rd 125",
    "sg:city":"Odessa",
    "sg:classifiers":[
        {
            "category":"Building & Trades",
            "subcategory":"Construction",
            "type":"Services"
        }
    ],
    "sg:phone":"+1 432 561 9233",
    "sg:postcode":"79765",
    "sg:province":"TX",
    "sg:tags":[
        "home",
        "builder"
    ],
    "wof:name":"Kevin Riggs Builder",
    "wof:placetype":"venue"
},
  "geometry": {"coordinates":[-102.24405,31.907543],"type":"Point"}
}