{
  "type": "Feature",
  "properties": {
    "iso:country":"US",
    "sg:address":"890 N Resler Dr",
    "sg:city":"El Paso",
    "sg:classifiers":[
        {
            "category":"Shopping",
            "subcategory":"Pharmacy",
            "type":"Retail Goods"
        }
    ],
    "sg:phone":"+1 915 584 1359",
    "sg:postcode":"79912",
    "sg:province":"TX",
    "sg:tags":[
        "drugstore"
    ],
    "sg:website":"www.walgreens.com",
    "wof:name":"Walgreens",
    "wof:placetype":"venue"
},
  "geometry": {"coordinates":[-106.55761800000001,31.859109],"type":"Point"}
}