{
  "type": "Feature",
  "properties": {
    "iso:country":"US",
    "sg:address":"10750 Sandhill Rd Ste B",
    "sg:city":"Dallas",
    "sg:classifiers":[
        {
            "category":"Building & Trades",
            "subcategory":"Construction",
            "type":"Services"
        }
    ],
    "sg:phone":"+1 214 340 4999",
    "sg:postcode":"75238",
    "sg:province":"TX",
    "sg:tags":[
        "contractor",
        "conditioning/hvac",
        "heating",
        "air"
    ],
    "sg:website":"www.chapmanair.com/",
    "wof:name":"Chapman Air & Heat",
    "wof:placetype":"venue"
},
  "geometry": {"coordinates":[-96.70886,32.896444],"type":"Point"}
}