{
  "type": "Feature",
  "properties": {
    "iso:country":"US",
    "sg:address":"2110 Potomac Dr",
    "sg:city":"Houston",
    "sg:classifiers":[
        {
            "category":"Professional",
            "subcategory":"Management & Consulting",
            "type":"Services"
        }
    ],
    "sg:phone":"+1 713 787 9212",
    "sg:postcode":"77057",
    "sg:province":"TX",
    "sg:tags":[
        "consultant",
        "business"
    ],
    "wof:name":"Herbalife Distributor",
    "wof:placetype":"venue"
},
  "geometry": {"coordinates":[-95.488698,29.742292],"type":"Point"}
}