{
  "type": "Feature",
  "properties": {
    "iso:country":"US",
    "sg:address":"9601 Dyer St",
    "sg:city":"El Paso",
    "sg:classifiers":[
        {
            "category":"Food & Beverages",
            "subcategory":"Groceries & Convenience Stores",
            "type":"Retail Goods"
        }
    ],
    "sg:phone":"+1 915 757 3871",
    "sg:postcode":"79924",
    "sg:province":"TX",
    "wof:name":"OK Texaco",
    "wof:placetype":"venue"
},
  "geometry": {"coordinates":[-106.41649,31.887663],"type":"Point"}
}