{
  "type": "Feature",
  "properties": {
    "iso:country":"US",
    "sg:address":"209 W 5th St",
    "sg:city":"Austin",
    "sg:classifiers":[
        {
            "category":"Bars & Pubs",
            "type":"Food & Drink"
        }
    ],
    "sg:phone":"+1 512 479 7700",
    "sg:postcode":"78701",
    "sg:province":"TX",
    "sg:tags":[
        "club",
        "drinking",
        "establishment",
        "night"
    ],
    "wof:name":"Lucky Lounge",
    "wof:placetype":"venue"
},
  "geometry": {"coordinates":[-97.74549399999999,30.267698],"type":"Point"}
}