{
  "type": "Feature",
  "properties": {
    "iso:country":"US",
    "sg:address":"320 E Ave G",
    "sg:city":"Muleshoe",
    "sg:phone":"+1 806 965 2693",
    "sg:postcode":"79347",
    "sg:province":"TX",
    "sg:tags":[
        "wheat",
        "beef",
        "farm",
        "corn",
        "cattle",
        "cotton"
    ],
    "wof:name":"Wilcox Farms",
    "wof:placetype":"venue"
},
  "geometry": {"coordinates":[-102.726071,34.219749],"type":"Point"}
}