{
  "type": "Feature",
  "properties": {
    "iso:country":"US",
    "sg:address":"6012 Brook Hollow Dr",
    "sg:city":"El Paso",
    "sg:classifiers":[
        {
            "category":"Retail",
            "subcategory":"Auto Repair",
            "type":"Services"
        }
    ],
    "sg:phone":"+1 915 778 4999",
    "sg:postcode":"79925",
    "sg:province":"TX",
    "sg:tags":[
        "body",
        "paint",
        "shop"
    ],
    "wof:name":"Pinons Auto Body & Paint Shop",
    "wof:placetype":"venue"
},
  "geometry": {"coordinates":[-106.41692399999999,31.78658],"type":"Point"}
}