{
  "type": "Feature",
  "properties": {
    "iso:country":"US",
    "sg:address":"5120 W Lovers Ln",
    "sg:city":"Dallas",
    "sg:classifiers":[
        {
            "category":"Personal",
            "type":"Services"
        }
    ],
    "sg:phone":"+1 214 340 0343",
    "sg:postcode":"75209",
    "sg:province":"TX",
    "wof:name":"Trigger Tan Salon & Spa",
    "wof:placetype":"venue"
},
  "geometry": {"coordinates":[-96.824663,32.851124],"type":"Point"}
}