{
  "type": "Feature",
  "properties": {
    "iso:country":"US",
    "sg:address":"708 S Lamar Blvd",
    "sg:city":"Austin",
    "sg:classifiers":[
        {
            "category":"Communications",
            "subcategory":"Film & Video Production",
            "type":"Services"
        }
    ],
    "sg:phone":"+1 512 442 9944",
    "sg:postcode":"78704",
    "sg:province":"TX",
    "sg:tags":[
        "taping"
    ],
    "sg:website":"www.castleviewproductions.com",
    "wof:name":"Castleview Productions",
    "wof:placetype":"venue"
},
  "geometry": {"coordinates":[-97.76013500000001,30.257709],"type":"Point"}
}