{
  "type": "Feature",
  "properties": {
    "iso:country":"US",
    "sg:address":"5803 S Gessner Dr",
    "sg:city":"Houston",
    "sg:classifiers":[
        {
            "category":"Retail",
            "subcategory":"Auto Repair",
            "type":"Services"
        }
    ],
    "sg:phone":"+1 713 785 9798",
    "sg:postcode":"77036",
    "sg:province":"TX",
    "wof:name":"Gessner Auto Center",
    "wof:placetype":"venue"
},
  "geometry": {"coordinates":[-95.538696,29.716499],"type":"Point"}
}