{
  "type": "Feature",
  "properties": {
    "iso:country":"US",
    "sg:address":"222 W Centre St",
    "sg:city":"Fredericksburg",
    "sg:classifiers":[
        {
            "category":"Professional",
            "subcategory":"Management & Consulting",
            "type":"Services"
        }
    ],
    "sg:phone":"+1 830 997 1858",
    "sg:postcode":"78624",
    "sg:province":"TX",
    "sg:tags":[
        "business"
    ],
    "wof:name":"Lane Consulting Svcs",
    "wof:placetype":"venue"
},
  "geometry": {"coordinates":[-98.869626,30.282439],"type":"Point"}
}