{
  "type": "Feature",
  "properties": {
    "iso:country":"US",
    "sg:address":"5919 Berkshire Ridge Dr",
    "sg:city":"Sugar Land",
    "sg:classifiers":[
        {
            "category":"Recreation",
            "type":"Entertainment"
        }
    ],
    "sg:phone":"+1 281 937 0289",
    "sg:postcode":"77479",
    "sg:province":"TX",
    "wof:name":"Stretch N Grow of Sugar Land",
    "wof:placetype":"venue"
},
  "geometry": {"coordinates":[-95.67554699999999,29.577914],"type":"Point"}
}