{
  "type": "Feature",
  "properties": {
    "iso:country":"US",
    "sg:address":"10314 Bickham Rd",
    "sg:city":"Dallas",
    "sg:classifiers":[
        {
            "category":"Building & Trades",
            "subcategory":"Construction",
            "type":"Services"
        },
        {
            "category":"Home & Garden",
            "subcategory":"Carpets & Floor Coverings",
            "type":"Retail Goods"
        }
    ],
    "sg:phone":"+1 214 962 8160",
    "sg:postcode":"75220",
    "sg:province":"TX",
    "sg:tags":[
        "flooring",
        "contractor"
    ],
    "wof:name":"Arce's Granite",
    "wof:placetype":"venue"
},
  "geometry": {"coordinates":[-96.904837,32.862236],"type":"Point"}
}