{
  "type": "Feature",
  "properties": {
    "iso:country":"US",
    "sg:address":"311 N Stemmons Fwy",
    "sg:city":"Dallas",
    "sg:classifiers":[
        {
            "category":"Wholesale",
            "subcategory":"Office Equipment",
            "type":"Manufacturing & Wholesale Goods"
        },
        {
            "category":"Retail",
            "subcategory":"Repair Shop",
            "type":"Services"
        }
    ],
    "sg:phone":"+1 214 742 1706",
    "sg:postcode":"75207",
    "sg:province":"TX",
    "sg:tags":[
        "machine",
        "printer",
        "facsimile",
        "typewriter"
    ],
    "sg:website":"www.dop-inc.com",
    "wof:name":"Diversified Office Products",
    "wof:placetype":"venue"
},
  "geometry": {"coordinates":[-96.812515,32.781873],"type":"Point"}
}