{
  "type": "Feature",
  "properties": {
    "iso:country":"US",
    "sg:address":"2223 W Clarendon Dr",
    "sg:city":"Dallas",
    "sg:classifiers":[
        {
            "category":"Autos & Motor Vehicles",
            "subcategory":"Auto Supplies",
            "type":"Retail Goods"
        }
    ],
    "sg:phone":"+1 214 942 5596",
    "sg:postcode":"75208",
    "sg:province":"TX",
    "wof:name":"Horse Power Performance",
    "wof:placetype":"venue"
},
  "geometry": {"coordinates":[-96.855225,32.734675],"type":"Point"}
}