{
  "type": "Feature",
  "properties": {
    "iso:country":"US",
    "sg:address":"14141 W Highway 290",
    "sg:city":"Austin",
    "sg:classifiers":[
        {
            "category":"Building & Trades",
            "subcategory":"Construction",
            "type":"Services"
        },
        {
            "category":"Sports & Exercise",
            "subcategory":"Swimming Pool",
            "type":"Entertainment"
        }
    ],
    "sg:phone":"+1 512 894 4052",
    "sg:postcode":"78737",
    "sg:province":"TX",
    "wof:name":"Blue Haven Swimming Pools",
    "wof:placetype":"venue"
},
  "geometry": {"coordinates":[-98.011962,30.196729],"type":"Point"}
}