{
  "type": "Feature",
  "properties": {
    "iso:country":"US",
    "sg:address":"418 Villita St",
    "sg:city":"San Antonio",
    "sg:classifiers":[
        {
            "category":"Insurance",
            "subcategory":"Insurance Agent",
            "type":"Services"
        }
    ],
    "sg:phone":"+1 210 224 8400",
    "sg:postcode":"78205",
    "sg:province":"TX",
    "wof:name":"Bolivar Cafe In LA Villita",
    "wof:placetype":"venue"
},
  "geometry": {"coordinates":[-98.48899900000001,29.421765],"type":"Point"}
}