{
  "type": "Feature",
  "properties": {
    "iso:country":"US",
    "sg:address":"401 Amity Ave",
    "sg:city":"Rule",
    "sg:classifiers":[
        {
            "category":"Farming",
            "subcategory":"Livestock Farm",
            "type":"Manufacturing & Wholesale Goods"
        }
    ],
    "sg:phone":"+1 940 997 2206",
    "sg:postcode":"79547",
    "sg:province":"TX",
    "sg:tags":[
        "ranch"
    ],
    "wof:name":"Miller Farms",
    "wof:placetype":"venue"
},
  "geometry": {"coordinates":[-99.896395,33.181816],"type":"Point"}
}