{
  "type": "Feature",
  "properties": {
    "iso:country":"US",
    "sg:address":"5301 Ross Rd",
    "sg:city":"Del Valle",
    "sg:classifiers":[
        {
            "category":"Education",
            "subcategory":"School",
            "type":"Public Place"
        }
    ],
    "sg:phone":"+1 512 386 3000",
    "sg:postcode":"78617",
    "sg:province":"TX",
    "sg:website":"www.del-valle.k12.tx.us",
    "wof:name":"Del Valle Independent School District",
    "wof:placetype":"venue"
},
  "geometry": {"coordinates":[-97.630798,30.170401],"type":"Point"}
}