{
  "type": "Feature",
  "properties": {
    "iso:country":"US",
    "sg:address":"1103 Venus St",
    "sg:city":"Cedar Hill",
    "sg:classifiers":[
        {
            "category":"Shopping",
            "type":"Retail Goods"
        }
    ],
    "sg:phone":"+1 972 291 4086",
    "sg:postcode":"75104",
    "sg:province":"TX",
    "sg:tags":[
        "merchandise"
    ],
    "wof:name":"Db Audio",
    "wof:placetype":"venue"
},
  "geometry": {"coordinates":[-96.946192,32.567906],"type":"Point"}
}