{
  "type": "Feature",
  "properties": {
    "iso:country":"US",
    "sg:address":"210 Green Meadows",
    "sg:city":"Converse",
    "sg:classifiers":[
        {
            "category":"Organizations",
            "subcategory":"Religious Organization",
            "type":"Services"
        }
    ],
    "sg:phone":"+1 210 945 0545",
    "sg:postcode":"78109",
    "sg:province":"TX",
    "wof:name":"Spirit Led Ministries",
    "wof:placetype":"venue"
},
  "geometry": {"coordinates":[-98.31475500000001,29.524064],"type":"Point"}
}