{
  "type": "Feature",
  "properties": {
    "iso:country":"US",
    "sg:address":"4306 S Co Rd 1290",
    "sg:city":"Odessa",
    "sg:classifiers":[
        {
            "category":"Wholesale",
            "subcategory":"Machinery & Supplies",
            "type":"Manufacturing & Wholesale Goods"
        }
    ],
    "sg:phone":"+1 432 561 9495",
    "sg:postcode":"79765",
    "sg:province":"TX",
    "sg:tags":[
        "equipment",
        "industrial"
    ],
    "wof:name":"Teal Supply",
    "wof:placetype":"venue"
},
  "geometry": {"coordinates":[-102.231162,31.903753],"type":"Point"}
}