{
  "type": "Feature",
  "properties": {
    "iso:country":"US",
    "sg:address":"6618 Lost Horizon Dr",
    "sg:city":"Austin",
    "sg:classifiers":[
        {
            "category":"Professional",
            "subcategory":"Business Services",
            "type":"Services"
        }
    ],
    "sg:phone":"+1 512 336 9805",
    "sg:postcode":"78759",
    "sg:province":"TX",
    "wof:name":"Passport Enterprises LLC",
    "wof:placetype":"venue"
},
  "geometry": {"coordinates":[-97.76784499999999,30.413596],"type":"Point"}
}