{
  "type": "Feature",
  "properties": {
    "iso:country":"US",
    "sg:address":"1322 Round Table Dr",
    "sg:city":"Dallas",
    "sg:classifiers":[
        {
            "category":"Manufacturing",
            "subcategory":"Apparel",
            "type":"Manufacturing & Wholesale Goods"
        }
    ],
    "sg:phone":"+1 214 634 1286",
    "sg:postcode":"75247",
    "sg:province":"TX",
    "sg:tags":[
        "hat",
        "mfg"
    ],
    "wof:name":"Bierner Hat Company",
    "wof:placetype":"venue"
},
  "geometry": {"coordinates":[-96.88463400000001,32.830945],"type":"Point"}
}