{
  "type": "Feature",
  "properties": {
    "iso:country":"US",
    "sg:address":"1117 Tobola St",
    "sg:city":"Rosenberg",
    "sg:classifiers":[
        {
            "category":"Professional",
            "subcategory":"Management & Consulting",
            "type":"Services"
        }
    ],
    "sg:phone":"+1 281 232 9819",
    "sg:postcode":"77471",
    "sg:province":"TX",
    "wof:name":"Occupational Training of Amer",
    "wof:placetype":"venue"
},
  "geometry": {"coordinates":[-95.790795,29.557726],"type":"Point"}
}