{
  "type": "Feature",
  "properties": {
    "iso:country":"US",
    "sg:address":"100 I- 45 N",
    "sg:city":"Conroe",
    "sg:classifiers":[
        {
            "category":"Home & Garden",
            "subcategory":"Building Materials",
            "type":"Retail Goods"
        }
    ],
    "sg:phone":"+1 936 441 3930",
    "sg:postcode":"77301",
    "sg:province":"TX",
    "sg:tags":[
        "stone"
    ],
    "wof:name":"Hanson Aggregates",
    "wof:placetype":"venue"
},
  "geometry": {"coordinates":[-95.469325,30.311038],"type":"Point"}
}