{
  "type": "Feature",
  "properties": {
    "iso:country":"US",
    "sg:address":"6711 N Sam Houston Pkwy W",
    "sg:city":"Houston",
    "sg:classifiers":[
        {
            "category":"Building & Trades",
            "subcategory":"Construction",
            "type":"Services"
        }
    ],
    "sg:phone":"+1 832 688 9256",
    "sg:postcode":"77064",
    "sg:province":"TX",
    "sg:tags":[
        "contractor"
    ],
    "wof:name":"Metro Remodeling Systems",
    "wof:placetype":"venue"
},
  "geometry": {"coordinates":[-95.525929,29.935866],"type":"Point"}
}