{
  "type": "Feature",
  "properties": {
    "iso:country":"US",
    "sg:address":"300 W 17th St",
    "sg:city":"Houston",
    "sg:classifiers":[
        {
            "category":"Education",
            "subcategory":"School",
            "type":"Public Place"
        }
    ],
    "sg:phone":"+1 713 867 5234",
    "sg:postcode":"77008",
    "sg:province":"TX",
    "sg:tags":[
        "high",
        "middle",
        "elementary"
    ],
    "wof:name":"Schools",
    "wof:placetype":"venue"
},
  "geometry": {"coordinates":[-95.401357,29.800732],"type":"Point"}
}