{
  "type": "Feature",
  "properties": {
    "iso:country":"US",
    "sg:address":"821 Sky Creek Ct",
    "sg:city":"Fort Worth",
    "sg:classifiers":[
        {
            "category":"Manufacturing",
            "subcategory":"Retail Goods",
            "type":"Manufacturing & Wholesale Goods"
        }
    ],
    "sg:phone":"+1 817 232 3358",
    "sg:postcode":"76179",
    "sg:province":"TX",
    "sg:tags":[
        "product",
        "mfg"
    ],
    "wof:name":"Paradise Scents",
    "wof:placetype":"venue"
},
  "geometry": {"coordinates":[-97.37741800000001,32.853535],"type":"Point"}
}