{
  "type": "Feature",
  "properties": {
    "iso:country":"US",
    "sg:address":"4109 College Hills Blvd",
    "sg:city":"San Angelo",
    "sg:classifiers":[
        {
            "category":"Banks & Credit Unions",
            "subcategory":"Bank",
            "type":"Services"
        }
    ],
    "sg:phone":"+1 325 947 2784",
    "sg:postcode":"76904",
    "sg:province":"TX",
    "sg:tags":[
        "mortgage"
    ],
    "wof:name":"Bank Of America",
    "wof:placetype":"venue"
},
  "geometry": {"coordinates":[-100.483692,31.422478],"type":"Point"}
}