{
  "type": "Feature",
  "properties": {
    "iso:country":"US",
    "sg:address":"10734 New Sulphur Springs Rd",
    "sg:city":"San Antonio",
    "sg:classifiers":[
        {
            "category":"Building & Trades",
            "subcategory":"Construction",
            "type":"Services"
        }
    ],
    "sg:phone":"+1 210 649 1311",
    "sg:postcode":"78263",
    "sg:province":"TX",
    "sg:tags":[
        "roofing",
        "contractor"
    ],
    "wof:name":"Marlowe Roofing & Rmdlng Inc",
    "wof:placetype":"venue"
},
  "geometry": {"coordinates":[-98.26126499999999,29.329596],"type":"Point"}
}