{
  "type": "Feature",
  "properties": {
    "iso:country":"US",
    "sg:address":"4974 State Hwy 6",
    "sg:city":"Houston",
    "sg:classifiers":[
        {
            "category":"Autos & Motor Vehicles",
            "subcategory":"Fuel & Gas Station",
            "type":"Retail Goods"
        }
    ],
    "sg:phone":"+1 281 855 0716",
    "sg:postcode":"77084",
    "sg:province":"TX",
    "sg:tags":[
        "oil"
    ],
    "wof:name":"Diamond Shamrock",
    "wof:placetype":"venue"
},
  "geometry": {"coordinates":[-95.64570999999999,29.84862],"type":"Point"}
}