{
  "type": "Feature",
  "properties": {
    "iso:country":"US",
    "sg:address":"8802 Little Walnut Dr",
    "sg:city":"Austin",
    "sg:classifiers":[
        {
            "category":"Building & Trades",
            "subcategory":"Construction",
            "type":"Services"
        }
    ],
    "sg:phone":"+1 512 833 6934",
    "sg:postcode":"78753",
    "sg:province":"TX",
    "sg:tags":[
        "hanging",
        "contractor"
    ],
    "wof:name":"G & R Painting",
    "wof:placetype":"venue"
},
  "geometry": {"coordinates":[-97.697851,30.35361],"type":"Point"}
}