{
  "type": "Feature",
  "properties": {
    "iso:country":"US",
    "sg:address":"401 Domingo Dr",
    "sg:city":"Grand Prairie",
    "sg:classifiers":[
        {
            "category":"Autos & Motor Vehicles",
            "subcategory":"Boat Sales",
            "type":"Retail Goods"
        }
    ],
    "sg:phone":"+1 972 266 0174",
    "sg:postcode":"75051",
    "sg:province":"TX",
    "wof:name":"Colgins Boating",
    "wof:placetype":"venue"
},
  "geometry": {"coordinates":[-96.99694700000001,32.715493],"type":"Point"}
}