{
  "type": "Feature",
  "properties": {
    "iso:country":"US",
    "sg:address":"6414 Autumn Thistle Dr",
    "sg:city":"Katy",
    "sg:classifiers":[
        {
            "category":"Retail",
            "subcategory":"Laundry & Dry Cleaning",
            "type":"Services"
        }
    ],
    "sg:phone":"+1 281 858 5273",
    "sg:postcode":"77449",
    "sg:province":"TX",
    "wof:name":"Best Carpet Care",
    "wof:placetype":"venue"
},
  "geometry": {"coordinates":[-95.69408,29.872131],"type":"Point"}
}