{
  "type": "Feature",
  "properties": {
    "iso:country":"US",
    "sg:address":"17419 Victoria Lakes Cir",
    "sg:city":"Spring",
    "sg:classifiers":[
        {
            "category":"Professional",
            "subcategory":"Management & Consulting",
            "type":"Services"
        }
    ],
    "sg:phone":"+1 281 251 5954",
    "sg:postcode":"77379",
    "sg:province":"TX",
    "sg:tags":[
        "business"
    ],
    "wof:name":"Duncan Marine Tech",
    "wof:placetype":"venue"
},
  "geometry": {"coordinates":[-95.564706,30.022375],"type":"Point"}
}