{
  "type": "Feature",
  "properties": {
    "iso:country":"US",
    "sg:address":"701 E Grant Ave",
    "sg:city":"Morton",
    "sg:classifiers":[
        {
            "category":"Building & Trades",
            "subcategory":"Construction",
            "type":"Services"
        }
    ],
    "sg:phone":"+1 806 266 8650",
    "sg:postcode":"79346",
    "sg:province":"TX",
    "sg:tags":[
        "water",
        "pump",
        "well",
        "drilling",
        "contractor"
    ],
    "wof:name":"Gillco Drilling Co",
    "wof:placetype":"venue"
},
  "geometry": {"coordinates":[-102.75215900000001,33.719238],"type":"Point"}
}