{
  "type": "Feature",
  "properties": {
    "iso:country":"US",
    "sg:address":"3007 London Ct",
    "sg:city":"Pearland",
    "sg:classifiers":[
        {
            "category":"Education",
            "subcategory":"School",
            "type":"Public Place"
        }
    ],
    "sg:phone":"+1 281 485 7881",
    "sg:postcode":"77581",
    "sg:province":"TX",
    "wof:name":"Arch Homeschoolers",
    "wof:placetype":"venue"
},
  "geometry": {"coordinates":[-95.26370300000001,29.563935],"type":"Point"}
}