{
  "type": "Feature",
  "properties": {
    "iso:country":"US",
    "sg:address":"907 Blue Jay Dr",
    "sg:city":"Murphy",
    "sg:classifiers":[
        {
            "category":"Communications",
            "subcategory":"Television Station",
            "type":"Services"
        }
    ],
    "sg:phone":"+1 972 423 3793",
    "sg:postcode":"75094",
    "sg:province":"TX",
    "sg:tags":[
        "network"
    ],
    "wof:name":"L1 Star",
    "wof:placetype":"venue"
},
  "geometry": {"coordinates":[-96.624252,33.03038],"type":"Point"}
}