{
  "type": "Feature",
  "properties": {
    "iso:country":"US",
    "sg:address":"950 N 19th St",
    "sg:city":"Abilene",
    "sg:classifiers":[
        {
            "category":"Health Services",
            "subcategory":"Doctor",
            "type":"Services"
        }
    ],
    "sg:phone":"+1 325 672 3252",
    "sg:postcode":"79601",
    "sg:province":"TX",
    "sg:tags":[
        "physician",
        "family",
        "practice",
        "surgeons",
        "medicine",
        "surgeon"
    ],
    "wof:name":"Rae Ann Hamilton",
    "wof:placetype":"venue"
},
  "geometry": {"coordinates":[-99.730493,32.471556],"type":"Point"}
}