{
  "type": "Feature",
  "properties": {
    "iso:country":"US",
    "sg:address":"5212 Marsha Sharp Fwy",
    "sg:city":"Lubbock",
    "sg:classifiers":[
        {
            "category":"Manufacturing",
            "subcategory":"Chemicals & Compounds",
            "type":"Manufacturing & Wholesale Goods"
        },
        {
            "category":"Professional",
            "subcategory":"Business Services",
            "type":"Services"
        },
        {
            "category":"Building & Trades",
            "subcategory":"Pest Control",
            "type":"Services"
        }
    ],
    "sg:phone":"+1 806 686 4049",
    "sg:postcode":"79407",
    "sg:province":"TX",
    "sg:tags":[
        "industrial",
        "supply",
        "services-commercial",
        "termite",
        "bee",
        "equipment",
        "repellent",
        "mothproofing",
        "barriers",
        "removal",
        "inspection",
        "bird"
    ],
    "wof:name":"Terminix",
    "wof:placetype":"venue"
},
  "geometry": {"coordinates":[-101.923087,33.564596],"type":"Point"}
}