{
  "type": "Feature",
  "properties": {
    "iso:country":"US",
    "sg:address":"220 W 8th St",
    "sg:city":"Post",
    "sg:classifiers":[
        {
            "category":"Restaurant",
            "type":"Food & Drink"
        }
    ],
    "sg:phone":"+1 806 495 2365",
    "sg:postcode":"79356",
    "sg:province":"TX",
    "sg:tags":[
        "eating"
    ],
    "wof:name":"Funky Chicken",
    "wof:placetype":"venue"
},
  "geometry": {"coordinates":[-101.380639,33.189319],"type":"Point"}
}