{
  "type": "Feature",
  "properties": {
    "iso:country":"US",
    "sg:address":"32508 Watersmeet",
    "sg:city":"Fulshear",
    "sg:classifiers":[
        {
            "category":"Banks & Credit Unions",
            "subcategory":"Financial Services",
            "type":"Services"
        }
    ],
    "sg:phone":"+1 281 346 2002",
    "sg:postcode":"77441",
    "sg:province":"TX",
    "sg:tags":[
        "investor",
        "investment",
        "closed"
    ],
    "wof:name":"Foley Investments Ltd",
    "wof:placetype":"venue"
},
  "geometry": {"coordinates":[-95.932181,29.68235],"type":"Point"}
}