{
  "type": "Feature",
  "properties": {
    "iso:country":"US",
    "sg:address":"4733 Gayle Dr",
    "sg:city":"Corpus Christi",
    "sg:classifiers":[
        {
            "category":"Shopping",
            "subcategory":"Clothing, Apparel, & Fashions",
            "type":"Retail Goods"
        }
    ],
    "sg:phone":"+1 361 852 3494",
    "sg:postcode":"78413",
    "sg:province":"TX",
    "sg:tags":[
        "alteration"
    ],
    "wof:name":"Ramirez Tailor Shop",
    "wof:placetype":"venue"
},
  "geometry": {"coordinates":[-97.394184,27.700264],"type":"Point"}
}