{
  "type": "Feature",
  "properties": {
    "iso:country":"US",
    "sg:address":"10415 Sagerock Dr",
    "sg:city":"Houston",
    "sg:classifiers":[
        {
            "category":"Wholesale",
            "subcategory":"Machinery & Supplies",
            "type":"Manufacturing & Wholesale Goods"
        }
    ],
    "sg:phone":"+1 281 481 6203",
    "sg:postcode":"77089",
    "sg:province":"TX",
    "sg:tags":[
        "field",
        "oil",
        "equipment"
    ],
    "wof:name":"E T Intrnational Oil Field Sup",
    "wof:placetype":"venue"
},
  "geometry": {"coordinates":[-95.22274,29.586013],"type":"Point"}
}