{
  "type": "Feature",
  "properties": {
    "iso:country":"US",
    "sg:address":"3600 S 4th St",
    "sg:city":"Waco",
    "sg:classifiers":[
        {
            "category":"Building & Trades",
            "subcategory":"Construction",
            "type":"Services"
        }
    ],
    "sg:phone":"+1 254 749 2268",
    "sg:postcode":"76706",
    "sg:province":"TX",
    "sg:tags":[
        "hanging",
        "contractor"
    ],
    "wof:name":"Phillip Logan",
    "wof:placetype":"venue"
},
  "geometry": {"coordinates":[-97.100994,31.531335],"type":"Point"}
}