{
  "type": "Feature",
  "properties": {
    "iso:country":"US",
    "sg:address":"3612 Pinehurst Ct",
    "sg:city":"Plano",
    "sg:classifiers":[
        {
            "category":"Insurance",
            "subcategory":"Insurance Agent",
            "type":"Services"
        }
    ],
    "sg:phone":"+1 972 599 0672",
    "sg:postcode":"75075",
    "sg:province":"TX",
    "wof:name":"Uni Care",
    "wof:placetype":"venue"
},
  "geometry": {"coordinates":[-96.76353899999999,33.036275],"type":"Point"}
}