{
  "type": "Feature",
  "properties": {
    "iso:country":"US",
    "sg:address":"6363 Maverick Trail Dr",
    "sg:city":"San Antonio",
    "sg:classifiers":[
        {
            "category":"Professional",
            "type":"Services"
        }
    ],
    "sg:phone":"+1 210 543 9624",
    "sg:postcode":"78240",
    "sg:province":"TX",
    "wof:name":"Noel R La Guardia",
    "wof:placetype":"venue"
},
  "geometry": {"coordinates":[-98.612458,29.515332],"type":"Point"}
}