{
  "type": "Feature",
  "properties": {
    "iso:country":"US",
    "sg:address":"12312 FM 2100",
    "sg:city":"Crosby",
    "sg:classifiers":[
        {
            "category":"Food & Beverages",
            "subcategory":"Groceries & Convenience Stores",
            "type":"Retail Goods"
        }
    ],
    "sg:phone":"+1 281 328 3406",
    "sg:postcode":"77532",
    "sg:province":"TX",
    "wof:name":"Barrett's Mini Stop",
    "wof:placetype":"venue"
},
  "geometry": {"coordinates":[-95.06320700000001,29.872178],"type":"Point"}
}