{
  "type": "Feature",
  "properties": {
    "iso:country":"US",
    "sg:address":"6630 Cypresswood Dr",
    "sg:city":"Spring",
    "sg:classifiers":[
        {
            "category":"Professional",
            "subcategory":"Lawyer & Legal Services",
            "type":"Services"
        }
    ],
    "sg:phone":"+1 713 862 7766",
    "sg:postcode":"77379",
    "sg:province":"TX",
    "sg:tags":[
        "attorney"
    ],
    "wof:name":"Gerald E Bourque",
    "wof:placetype":"venue"
},
  "geometry": {"coordinates":[-95.50520899999999,30.016303],"type":"Point"}
}