{
  "type": "Feature",
  "properties": {
    "iso:country":"US",
    "sg:address":"4703 7th St",
    "sg:city":"Bay City",
    "sg:classifiers":[
        {
            "category":"Shopping",
            "type":"Retail Goods"
        }
    ],
    "sg:phone":"+1 979 244 0500",
    "sg:postcode":"77414",
    "sg:province":"TX",
    "sg:tags":[
        "merchandise"
    ],
    "wof:name":"Prime Communications",
    "wof:placetype":"venue"
},
  "geometry": {"coordinates":[-95.930983,28.988356],"type":"Point"}
}