{
  "type": "Feature",
  "properties": {
    "iso:country":"US",
    "sg:address":"6303 Navaho Trl",
    "sg:city":"Granbury",
    "sg:classifiers":[
        {
            "category":"Professional",
            "type":"Services"
        }
    ],
    "sg:phone":"+1 817 326 4698",
    "sg:postcode":"76049",
    "sg:province":"TX",
    "wof:name":"Southern Lighting Parts",
    "wof:placetype":"venue"
},
  "geometry": {"coordinates":[-97.67739400000001,32.424793],"type":"Point"}
}