{
  "type": "Feature",
  "properties": {
    "iso:country":"US",
    "sg:address":"2156 Sandy Ln",
    "sg:city":"Dallas",
    "sg:classifiers":[
        {
            "category":"Wholesale",
            "subcategory":"Groceries",
            "type":"Manufacturing & Wholesale Goods"
        }
    ],
    "sg:phone":"+1 972 401 3600",
    "sg:postcode":"75220",
    "sg:province":"TX",
    "sg:tags":[
        "bakery"
    ],
    "wof:name":"Reyniers French Bakery Inc",
    "wof:placetype":"venue"
},
  "geometry": {"coordinates":[-96.90425999999999,32.86045],"type":"Point"}
}