{
  "type": "Feature",
  "properties": {
    "iso:country":"US",
    "sg:address":"2530 N 11th St",
    "sg:city":"Beaumont",
    "sg:classifiers":[
        {
            "category":"Arts & Performance",
            "subcategory":"Theater",
            "type":"Entertainment"
        }
    ],
    "sg:phone":"+1 409 924 7424",
    "sg:postcode":"77703",
    "sg:province":"TX",
    "sg:tags":[
        "theatrical"
    ],
    "wof:name":"Vortex",
    "wof:placetype":"venue"
},
  "geometry": {"coordinates":[-94.130459,30.101352],"type":"Point"}
}