{
  "type": "Feature",
  "properties": {
    "iso:country":"US",
    "sg:address":"5039 Parkridge Dr",
    "sg:city":"Houston",
    "sg:classifiers":[
        {
            "category":"Retail",
            "subcategory":"Repair Shop",
            "type":"Services"
        }
    ],
    "sg:phone":"+1 713 413 4564",
    "sg:postcode":"77053",
    "sg:province":"TX",
    "sg:tags":[
        "appliance"
    ],
    "wof:name":"Appliance Doctor & Sons",
    "wof:placetype":"venue"
},
  "geometry": {"coordinates":[-95.463326,29.583867],"type":"Point"}
}