{
  "type": "Feature",
  "properties": {
    "iso:country":"US",
    "sg:address":"4100 Caven Rd",
    "sg:city":"Austin",
    "sg:classifiers":[
        {
            "category":"Wholesale",
            "subcategory":"Apparel",
            "type":"Manufacturing & Wholesale Goods"
        },
        {
            "category":"Shopping",
            "subcategory":"Luggage & Leather Goods",
            "type":"Retail Goods"
        }
    ],
    "sg:phone":"+1 512 441 7600",
    "sg:postcode":"78744",
    "sg:province":"TX",
    "sg:tags":[
        "wallet",
        "belt"
    ],
    "wof:name":"Rogers-Whitley Inc",
    "wof:placetype":"venue"
},
  "geometry": {"coordinates":[-97.729687,30.206088],"type":"Point"}
}