{
  "type": "Feature",
  "properties": {
    "iso:country":"US",
    "sg:address":"6709 Yolanda Dr",
    "sg:city":"Fort Worth",
    "sg:classifiers":[
        {
            "category":"Wholesale",
            "subcategory":"Auto Parts",
            "type":"Manufacturing & Wholesale Goods"
        }
    ],
    "sg:phone":"+1 817 429 7110",
    "sg:postcode":"76112",
    "sg:province":"TX",
    "wof:name":"M F Automotive Equipment",
    "wof:placetype":"venue"
},
  "geometry": {"coordinates":[-97.21461499999999,32.752016],"type":"Point"}
}