{
  "type": "Feature",
  "properties": {
    "iso:country":"US",
    "sg:address":"504 N Longview St",
    "sg:city":"Kilgore",
    "sg:classifiers":[
        {
            "category":"Farming",
            "subcategory":"Farm & Veterinary Services",
            "type":"Manufacturing & Wholesale Goods"
        }
    ],
    "sg:phone":"+1 903 984 7578",
    "sg:postcode":"75662",
    "sg:province":"TX",
    "sg:tags":[
        "control",
        "weed"
    ],
    "wof:name":"Guaranteed Weed Control",
    "wof:placetype":"venue"
},
  "geometry": {"coordinates":[-94.874093,32.390825],"type":"Point"}
}