{
  "type": "Feature",
  "properties": {
    "iso:country":"US",
    "sg:address":"3700 Convict Hill Rd",
    "sg:city":"Austin",
    "sg:classifiers":[
        {
            "category":"Education",
            "subcategory":"School",
            "type":"Public Place"
        }
    ],
    "sg:phone":"+1 512 892 5551",
    "sg:postcode":"78749",
    "sg:province":"TX",
    "wof:name":"Convington Student Act Lines",
    "wof:placetype":"venue"
},
  "geometry": {"coordinates":[-97.834822,30.211482],"type":"Point"}
}