{
  "type": "Feature",
  "properties": {
    "iso:country":"US",
    "sg:address":"3754 Hemphill St",
    "sg:city":"Fort Worth",
    "sg:classifiers":[
        {
            "category":"Bars & Pubs",
            "type":"Food & Drink"
        }
    ],
    "sg:phone":"+1 817 926 7462",
    "sg:postcode":"76110",
    "sg:province":"TX",
    "sg:tags":[
        "drinking"
    ],
    "wof:name":"Company Lounge",
    "wof:placetype":"venue"
},
  "geometry": {"coordinates":[-97.331776,32.693048],"type":"Point"}
}