{
  "type": "Feature",
  "properties": {
    "iso:country":"US",
    "sg:address":"10527 Homestead Rd",
    "sg:city":"Houston",
    "sg:classifiers":[
        {
            "category":"Government",
            "subcategory":"Office",
            "type":"Public Place"
        }
    ],
    "sg:phone":"+1 713 633 3390",
    "sg:postcode":"77016",
    "sg:province":"TX",
    "sg:tags":[
        "executive"
    ],
    "wof:name":"State Representative",
    "wof:placetype":"venue"
},
  "geometry": {"coordinates":[-95.300636,29.866176],"type":"Point"}
}