{
  "type": "Feature",
  "properties": {
    "iso:country":"US",
    "sg:address":"217 Deborah Dr",
    "sg:city":"New Braunfels",
    "sg:classifiers":[
        {
            "category":"Building & Trades",
            "subcategory":"Construction",
            "type":"Services"
        }
    ],
    "sg:phone":"+1 830 626 1300",
    "sg:postcode":"78130",
    "sg:province":"TX",
    "sg:tags":[
        "carpentry",
        "contractor"
    ],
    "wof:name":"Cabinet Shop",
    "wof:placetype":"venue"
},
  "geometry": {"coordinates":[-98.060428,29.683923],"type":"Point"}
}