{
  "type": "Feature",
  "properties": {
    "iso:country":"US",
    "sg:address":"5846 49th St",
    "sg:city":"Lubbock",
    "sg:classifiers":[
        {
            "category":"Building & Trades",
            "subcategory":"Cleaning & Sanitation",
            "type":"Services"
        }
    ],
    "sg:phone":"+1 806 793 9319",
    "sg:postcode":"79424",
    "sg:province":"TX",
    "sg:tags":[
        "waxing",
        "floor"
    ],
    "wof:name":"Clean N Brite Floor Maint",
    "wof:placetype":"venue"
},
  "geometry": {"coordinates":[-101.942606,33.549742],"type":"Point"}
}