{
  "type": "Feature",
  "properties": {
    "iso:country":"US",
    "sg:address":"3110 Queenswood Ln",
    "sg:city":"Garland",
    "sg:classifiers":[
        {
            "category":"Social Services",
            "type":"Services"
        }
    ],
    "sg:phone":"+1 972 530 2075",
    "sg:postcode":"75040",
    "sg:province":"TX",
    "wof:name":"Do Mar Inc",
    "wof:placetype":"venue"
},
  "geometry": {"coordinates":[-96.629069,32.946782],"type":"Point"}
}