{
  "type": "Feature",
  "properties": {
    "iso:country":"US",
    "sg:address":"4001 Sunset Dr",
    "sg:city":"San Angelo",
    "sg:classifiers":[
        {
            "category":"Shopping",
            "subcategory":"Music",
            "type":"Retail Goods"
        }
    ],
    "sg:phone":"+1 325 942 1132",
    "sg:postcode":"76904",
    "sg:province":"TX",
    "sg:tags":[
        "product",
        "prerecorded",
        "tape",
        "blank",
        "small",
        "video",
        "audio"
    ],
    "wof:name":"Sam Goody 650",
    "wof:placetype":"venue"
},
  "geometry": {"coordinates":[-100.494961,31.428097],"type":"Point"}
}