{
  "type": "Feature",
  "properties": {
    "iso:country":"US",
    "sg:address":"6431 Fannin St Ste 1244",
    "sg:city":"Houston",
    "sg:classifiers":[
        {
            "category":"Health Services",
            "subcategory":"Doctor",
            "type":"Services"
        }
    ],
    "sg:phone":"+1 713 500 6559",
    "sg:postcode":"77030",
    "sg:province":"TX",
    "sg:tags":[
        "physician",
        "surgeon",
        "surgeons",
        "cardiology"
    ],
    "wof:name":"Smalling, Richard, Md - University Of Tx Houston Med",
    "wof:placetype":"venue"
},
  "geometry": {"coordinates":[-95.397324,29.714127],"type":"Point"}
}