{
  "type": "Feature",
  "properties": {
    "iso:country":"US",
    "sg:address":"2700 W Anderson Ln",
    "sg:city":"Austin",
    "sg:classifiers":[
        {
            "category":"Real Estate",
            "subcategory":"Real Estate Agent",
            "type":"Services"
        }
    ],
    "sg:phone":"+1 512 452 8903",
    "sg:postcode":"78757",
    "sg:province":"TX",
    "wof:name":"Owen W B & Associates",
    "wof:placetype":"venue"
},
  "geometry": {"coordinates":[-97.73747,30.359419],"type":"Point"}
}