{
  "type": "Feature",
  "properties": {
    "iso:country":"US",
    "sg:address":"3710 Belt Line Rd",
    "sg:city":"Addison",
    "sg:classifiers":[
        {
            "category":"Autos & Motor Vehicles",
            "subcategory":"Fuel & Gas Station",
            "type":"Retail Goods"
        },
        {
            "category":"Food & Beverages",
            "subcategory":"Groceries & Convenience Stores",
            "type":"Retail Goods"
        }
    ],
    "sg:phone":"+1 972 620 5755",
    "sg:postcode":"75001",
    "sg:province":"TX",
    "sg:website":"www.exxon.com",
    "wof:name":"Exxon Shop",
    "wof:placetype":"venue"
},
  "geometry": {"coordinates":[-96.855239,32.952912],"type":"Point"}
}