{
  "type": "Feature",
  "properties": {
    "iso:country":"US",
    "sg:address":"13858 Brook Hollow Blvd",
    "sg:city":"San Antonio",
    "sg:classifiers":[
        {
            "category":"Professional",
            "subcategory":"Advertising",
            "type":"Services"
        }
    ],
    "sg:phone":"+1 210 496 4734",
    "sg:postcode":"78232",
    "sg:province":"TX",
    "sg:tags":[
        "agency"
    ],
    "wof:name":"Ron Cook",
    "wof:placetype":"venue"
},
  "geometry": {"coordinates":[-98.463166,29.571924],"type":"Point"}
}