{
  "type": "Feature",
  "properties": {
    "iso:country":"US",
    "sg:address":"1605 Estrella Dr",
    "sg:city":"Plano",
    "sg:classifiers":[
        {
            "category":"Professional",
            "subcategory":"Detective & Security Services",
            "type":"Services"
        }
    ],
    "sg:phone":"+1 972 612 4711",
    "sg:postcode":"75074",
    "sg:province":"TX",
    "sg:tags":[
        "car",
        "private",
        "investigator"
    ],
    "wof:name":"Heritage Investigations",
    "wof:placetype":"venue"
},
  "geometry": {"coordinates":[-96.65550500000001,33.018133],"type":"Point"}
}