{
  "type": "Feature",
  "properties": {
    "iso:country":"US",
    "sg:address":"7205 Hwy 691",
    "sg:city":"Denison",
    "sg:classifiers":[
        {
            "category":"Restaurant",
            "type":"Food & Drink"
        }
    ],
    "sg:phone":"+1 903 463 5222",
    "sg:postcode":"75020",
    "sg:province":"TX",
    "wof:name":"Pizza Inn",
    "wof:placetype":"venue"
},
  "geometry": {"coordinates":[-96.64558,33.70886],"type":"Point"}
}