{
  "type": "Feature",
  "properties": {
    "iso:country":"US",
    "sg:address":"1016 S Main St",
    "sg:city":"Weatherford",
    "sg:classifiers":[
        {
            "category":"Restaurant",
            "type":"Food & Drink"
        }
    ],
    "sg:phone":"+1 817 594 9090",
    "sg:postcode":"76086",
    "sg:province":"TX",
    "sg:tags":[
        "pizza"
    ],
    "wof:name":"Nizza Pizza Pasta & Subs",
    "wof:placetype":"venue"
},
  "geometry": {"coordinates":[-97.79753599999999,32.748033],"type":"Point"}
}