{
  "type": "Feature",
  "properties": {
    "iso:country":"US",
    "sg:address":"1472 Wilcrest Dr",
    "sg:city":"Houston",
    "sg:classifiers":[
        {
            "category":"Restaurant",
            "type":"Food & Drink"
        }
    ],
    "sg:phone":"+1 713 278 8718",
    "sg:postcode":"77042",
    "sg:province":"TX",
    "wof:name":"Hearne's Grill",
    "wof:placetype":"venue"
},
  "geometry": {"coordinates":[-95.57249899999999,29.751403],"type":"Point"}
}