{
  "type": "Feature",
  "properties": {
    "iso:country":"US",
    "sg:address":"901 N Mill St",
    "sg:city":"Lewisville",
    "sg:classifiers":[
        {
            "category":"Retail",
            "subcategory":"Repair Shop",
            "type":"Services"
        }
    ],
    "sg:phone":"+1 972 221 4448",
    "sg:postcode":"75057",
    "sg:province":"TX",
    "sg:tags":[
        "renting",
        "engine",
        "lawn",
        "garden",
        "supply",
        "equipment",
        "small"
    ],
    "sg:website":"http://www.stihldealer.net/default-dealer-001163.aspx",
    "wof:name":"Lowery Motor Service",
    "wof:placetype":"venue"
},
  "geometry": {"coordinates":[-97.000337,33.056995],"type":"Point"}
}