{
  "type": "Feature",
  "properties": {
    "iso:country":"US",
    "sg:address":"15614 Cloud Top St",
    "sg:city":"San Antonio",
    "sg:classifiers":[
        {
            "category":"Manufacturing",
            "subcategory":"Printing",
            "type":"Manufacturing & Wholesale Goods"
        }
    ],
    "sg:phone":"+1 210 493 3131",
    "sg:postcode":"78248",
    "sg:province":"TX",
    "sg:tags":[
        "lithographic",
        "commercial"
    ],
    "wof:name":"Personal Print",
    "wof:placetype":"venue"
},
  "geometry": {"coordinates":[-98.517539,29.593049],"type":"Point"}
}