{
  "type": "Feature",
  "properties": {
    "iso:country":"US",
    "sg:address":"900 W Kramer Rd",
    "sg:city":"Burkburnett",
    "sg:phone":"+1 940 569 3315",
    "sg:postcode":"76354",
    "sg:province":"TX",
    "sg:website":"http://www.pizzahut.com",
    "wof:name":"Pizza Hut",
    "wof:placetype":"venue"
},
  "geometry": {"coordinates":[-98.577309,34.08012],"type":"Point"}
}