{
  "type": "Feature",
  "properties": {
    "iso:country":"US",
    "sg:address":"526 Porter St",
    "sg:city":"San Antonio",
    "sg:classifiers":[
        {
            "category":"Professional",
            "subcategory":"Management & Consulting",
            "type":"Services"
        }
    ],
    "sg:phone":"+1 210 534 9544",
    "sg:postcode":"78210",
    "sg:province":"TX",
    "sg:tags":[
        "retail",
        "direct",
        "sales"
    ],
    "wof:name":"Mmm Taco",
    "wof:placetype":"venue"
},
  "geometry": {"coordinates":[-98.45950499999999,29.405828],"type":"Point"}
}