{
  "type": "Feature",
  "properties": {
    "iso:country":"US",
    "sg:address":"43 Chelsea Dr",
    "sg:city":"Fort Worth",
    "sg:classifiers":[
        {
            "category":"Farming",
            "subcategory":"Farm",
            "type":"Manufacturing & Wholesale Goods"
        }
    ],
    "sg:phone":"+1 817 293 8264",
    "sg:postcode":"76134",
    "sg:province":"TX",
    "sg:tags":[
        "crop",
        "general"
    ],
    "wof:name":"Albright Farms Inc",
    "wof:placetype":"venue"
},
  "geometry": {"coordinates":[-97.341032,32.659931],"type":"Point"}
}