{
  "type": "Feature",
  "properties": {
    "iso:country":"US",
    "sg:address":"3305 Robinson Dr",
    "sg:city":"Waco",
    "sg:classifiers":[
        {
            "category":"Government",
            "subcategory":"Office",
            "type":"Public Place"
        }
    ],
    "sg:phone":"+1 254 752 3199",
    "sg:postcode":"76706",
    "sg:province":"TX",
    "wof:name":"Mc Lennan County Constable",
    "wof:placetype":"venue"
},
  "geometry": {"coordinates":[-97.12694500000001,31.505724],"type":"Point"}
}