{
  "type": "Feature",
  "properties": {
    "iso:country":"US",
    "sg:address":"5410 Kingfisher Rd",
    "sg:city":"Garland",
    "sg:classifiers":[
        {
            "category":"Retail",
            "subcategory":"Auto Repair",
            "type":"Services"
        }
    ],
    "sg:phone":"+1 972 203 8880",
    "sg:postcode":"75043",
    "sg:province":"TX",
    "sg:tags":[
        "automotive"
    ],
    "wof:name":"Pioneer Electricals Contrs",
    "wof:placetype":"venue"
},
  "geometry": {"coordinates":[-96.550889,32.856322],"type":"Point"}
}