{
  "type": "Feature",
  "properties": {
    "iso:country":"US",
    "sg:address":"210 W Chestnut St",
    "sg:city":"Grapeland",
    "sg:classifiers":[
        {
            "category":"Fast Food",
            "type":"Food & Drink"
        },
        {
            "category":"Restaurant",
            "type":"Food & Drink"
        }
    ],
    "sg:phone":"+1 936 687 2460",
    "sg:postcode":"75844",
    "sg:province":"TX",
    "sg:tags":[
        "take",
        "buffet",
        "pizza"
    ],
    "sg:website":"http://www.pizzapro.com",
    "wof:name":"Pizza Pro",
    "wof:placetype":"venue"
},
  "geometry": {"coordinates":[-95.480144,31.490917],"type":"Point"}
}