{
  "type": "Feature",
  "properties": {
    "iso:country":"US",
    "sg:address":"2900 Wilcrest Dr",
    "sg:city":"Houston",
    "sg:classifiers":[
        {
            "category":"Insurance",
            "subcategory":"Hazard Insurance",
            "type":"Services"
        }
    ],
    "sg:phone":"+1 713 334 3455",
    "sg:postcode":"77042",
    "sg:province":"TX",
    "sg:tags":[
        "carrier"
    ],
    "wof:name":"United Sttes Arcft Insur Group",
    "wof:placetype":"venue"
},
  "geometry": {"coordinates":[-95.57170499999999,29.733016],"type":"Point"}
}