{
  "type": "Feature",
  "properties": {
    "iso:country":"US",
    "sg:address":"1133 Mission Rd",
    "sg:city":"San Antonio",
    "sg:classifiers":[
        {
            "category":"Recreation",
            "type":"Entertainment"
        },
        {
            "category":"Social Services",
            "type":"Services"
        }
    ],
    "sg:phone":"+1 210 532 8141",
    "sg:postcode":"78210",
    "sg:province":"TX",
    "sg:tags":[
        "youth",
        "organization",
        "center"
    ],
    "wof:name":"Don Bosco Youth Center",
    "wof:placetype":"venue"
},
  "geometry": {"coordinates":[-98.490031,29.386546],"type":"Point"}
}