{
  "type": "Feature",
  "properties": {
    "iso:country":"US",
    "sg:address":"157 Greenbriar Dr",
    "sg:city":"Magnolia",
    "sg:classifiers":[
        {
            "category":"Building & Trades",
            "subcategory":"Electrical",
            "type":"Services"
        }
    ],
    "sg:phone":"+1 936 372 9847",
    "sg:postcode":"77355",
    "sg:province":"TX",
    "sg:tags":[
        "electrical",
        "contractor"
    ],
    "wof:name":"Gressett Electric Co",
    "wof:placetype":"venue"
},
  "geometry": {"coordinates":[-95.821472,30.177222],"type":"Point"}
}