{
  "type": "Feature",
  "properties": {
    "iso:country":"US",
    "sg:address":"13115 Cleveland Rd",
    "sg:city":"Conroe",
    "sg:classifiers":[
        {
            "category":"Freight",
            "type":"Transportation"
        }
    ],
    "sg:phone":"+1 281 224 1867",
    "sg:postcode":"77304",
    "sg:province":"TX",
    "sg:tags":[
        "trucking"
    ],
    "wof:name":"Davis Transport Inc",
    "wof:placetype":"venue"
},
  "geometry": {"coordinates":[-95.566114,30.342416],"type":"Point"}
}