{
  "type": "Feature",
  "properties": {
    "iso:country":"US",
    "sg:address":"2726 82nd St",
    "sg:city":"Lubbock",
    "sg:classifiers":[
        {
            "category":"Cinema",
            "subcategory":"Movie Theater",
            "type":"Entertainment"
        }
    ],
    "sg:phone":"+1 806 745 1693",
    "sg:postcode":"79423",
    "sg:province":"TX",
    "wof:name":"Noret Theatres General Office",
    "wof:placetype":"venue"
},
  "geometry": {"coordinates":[-101.873789,33.5198],"type":"Point"}
}