{
  "type": "Feature",
  "properties": {
    "iso:country":"US",
    "sg:address":"10343 Shelburne Dr",
    "sg:city":"Dallas",
    "sg:classifiers":[
        {
            "category":"Professional",
            "subcategory":"Business Services",
            "type":"Services"
        }
    ],
    "sg:phone":"+1 972 329 6776",
    "sg:postcode":"75227",
    "sg:province":"TX",
    "wof:name":"B & T Tax Professionals",
    "wof:placetype":"venue"
},
  "geometry": {"coordinates":[-96.645545,32.751928],"type":"Point"}
}