{
  "type": "Feature",
  "properties": {
    "iso:country":"US",
    "sg:address":"5410 Scott St",
    "sg:city":"Houston",
    "sg:classifiers":[
        {
            "category":"Social Services",
            "subcategory":"Child Care",
            "type":"Services"
        }
    ],
    "sg:phone":"+1 713 748 7797",
    "sg:postcode":"77021",
    "sg:province":"TX",
    "sg:tags":[
        "day"
    ],
    "wof:name":"NE-Ne's Kiddie Kollege",
    "wof:placetype":"venue"
},
  "geometry": {"coordinates":[-95.356796,29.709499],"type":"Point"}
}