{
  "type": "Feature",
  "properties": {
    "iso:country":"US",
    "sg:address":"707 Sandpiper Dr",
    "sg:city":"Sugar Land",
    "sg:classifiers":[
        {
            "category":"Building & Trades",
            "subcategory":"Construction",
            "type":"Services"
        }
    ],
    "sg:phone":"+1 281 242 4997",
    "sg:postcode":"77478",
    "sg:province":"TX",
    "sg:tags":[
        "house"
    ],
    "wof:name":"Master Builders",
    "wof:placetype":"venue"
},
  "geometry": {"coordinates":[-95.618978,29.614658],"type":"Point"}
}