{
  "type": "Feature",
  "properties": {
    "iso:country":"US",
    "sg:address":"1036 E Ashley Rd",
    "sg:city":"San Antonio",
    "sg:classifiers":[
        {
            "category":"Restaurant",
            "type":"Food & Drink"
        }
    ],
    "sg:phone":"+1 210 922 5595",
    "sg:postcode":"78221",
    "sg:province":"TX",
    "sg:tags":[
        "eating"
    ],
    "wof:name":"Ranch House Trlr Park",
    "wof:placetype":"venue"
},
  "geometry": {"coordinates":[-98.482173,29.333971],"type":"Point"}
}