{
  "type": "Feature",
  "properties": {
    "iso:country":"US",
    "sg:address":"4337 McMahon Cir",
    "sg:city":"El Paso",
    "sg:classifiers":[
        {
            "category":"Social Services",
            "subcategory":"Child Care",
            "type":"Services"
        }
    ],
    "sg:phone":"+1 915 755 6553",
    "sg:postcode":"79904",
    "sg:province":"TX",
    "sg:tags":[
        "day"
    ],
    "wof:name":"Tiny Hands and Feet",
    "wof:placetype":"venue"
},
  "geometry": {"coordinates":[-106.444074,31.850863],"type":"Point"}
}