{
  "type": "Feature",
  "properties": {
    "iso:country":"US",
    "sg:address":"366 Harbor Point Rd",
    "sg:city":"Gun Barrel City",
    "sg:classifiers":[
        {
            "category":"Building & Trades",
            "subcategory":"Plumbing",
            "type":"Services"
        }
    ],
    "sg:phone":"+1 903 887 5815",
    "sg:postcode":"75156",
    "sg:province":"TX",
    "sg:tags":[
        "conditioning",
        "air",
        "system",
        "contractor"
    ],
    "wof:name":"Air-O-Service Co",
    "wof:placetype":"venue"
},
  "geometry": {"coordinates":[-96.144904,32.33092],"type":"Point"}
}