{
  "type": "Feature",
  "properties": {
    "iso:country":"US",
    "sg:address":"1838 Rolling Hills Rd",
    "sg:city":"Conroe",
    "sg:classifiers":[
        {
            "category":"Retail",
            "subcategory":"Auto Repair",
            "type":"Services"
        },
        {
            "category":"Manufacturing",
            "subcategory":"Tools & Machinery",
            "type":"Manufacturing & Wholesale Goods"
        }
    ],
    "sg:phone":"+1 936 264 1700",
    "sg:postcode":"77303",
    "sg:province":"TX",
    "sg:tags":[
        "manufacture",
        "carburetor"
    ],
    "sg:website":"www.davincicarb.com",
    "wof:name":"Davinci Carburetor Ltd",
    "wof:placetype":"venue"
},
  "geometry": {"coordinates":[-95.373513,30.345165],"type":"Point"}
}