{
  "type": "Feature",
  "properties": {
    "iso:country":"US",
    "sg:address":"1708 E Poplar Ave",
    "sg:city":"Victoria",
    "sg:classifiers":[
        {
            "category":"Social Services",
            "subcategory":"Child Care",
            "type":"Services"
        }
    ],
    "sg:phone":"+1 361 579 9158",
    "sg:postcode":"77901",
    "sg:province":"TX",
    "sg:tags":[
        "day"
    ],
    "wof:name":"Noahs Ark Day Care",
    "wof:placetype":"venue"
},
  "geometry": {"coordinates":[-96.985302,28.823125],"type":"Point"}
}