{
  "type": "Feature",
  "properties": {
    "iso:country":"US",
    "sg:address":"2426 Clippers Cove Dr",
    "sg:city":"Houston",
    "sg:classifiers":[
        {
            "category":"Shopping",
            "subcategory":"Computers & Home Electronics",
            "type":"Retail Goods"
        },
        {
            "category":"Manufacturing",
            "subcategory":"Printing",
            "type":"Manufacturing & Wholesale Goods"
        }
    ],
    "sg:phone":"+1 281 333 4685",
    "sg:postcode":"77058",
    "sg:province":"TX",
    "sg:tags":[
        "equipment",
        "dealer",
        "periodical"
    ],
    "wof:name":"Computer Pilot Assoc America",
    "wof:placetype":"venue"
},
  "geometry": {"coordinates":[-95.082871,29.550774],"type":"Point"}
}