{
  "type": "Feature",
  "properties": {
    "iso:country":"US",
    "sg:address":"5004 Spyglass Dr",
    "sg:city":"Dallas",
    "sg:classifiers":[
        {
            "category":"Health Services",
            "subcategory":"Doctor",
            "type":"Services"
        }
    ],
    "sg:phone":"+1 972 931 1073",
    "sg:postcode":"75287",
    "sg:province":"TX",
    "sg:tags":[
        "medicine",
        "physician",
        "practice",
        "surgeons",
        "family"
    ],
    "wof:name":"Thomas Louis Borok, M.D., P.A.",
    "wof:placetype":"venue"
},
  "geometry": {"coordinates":[-96.822672,32.990651],"type":"Point"}
}