{
  "type": "Feature",
  "properties": {
    "iso:country":"US",
    "sg:address":"5206 Forest Trl",
    "sg:city":"Baytown",
    "sg:classifiers":[
        {
            "category":"Shopping",
            "subcategory":"Florist",
            "type":"Retail Goods"
        }
    ],
    "sg:phone":"+1 281 421 3088",
    "sg:postcode":"77521",
    "sg:province":"TX",
    "wof:name":"Stems & Co",
    "wof:placetype":"venue"
},
  "geometry": {"coordinates":[-94.927286,29.784155],"type":"Point"}
}