{
  "type": "Feature",
  "properties": {
    "iso:country":"US",
    "sg:address":"1985 N Main St",
    "sg:city":"Vidor",
    "sg:classifiers":[
        {
            "category":"Organizations",
            "subcategory":"Religious Organization",
            "type":"Services"
        }
    ],
    "sg:phone":"+1 409 769 3864",
    "sg:postcode":"77662",
    "sg:province":"TX",
    "sg:tags":[
        "church"
    ],
    "wof:name":"Grace Baptist Church Inc",
    "wof:placetype":"venue"
},
  "geometry": {"coordinates":[-94.01792,30.152545],"type":"Point"}
}