{
  "type": "Feature",
  "properties": {
    "iso:country":"US",
    "sg:address":"14034 Alderson St",
    "sg:city":"Houston",
    "sg:classifiers":[
        {
            "category":"Manufacturing",
            "subcategory":"Metals",
            "type":"Manufacturing & Wholesale Goods"
        }
    ],
    "sg:phone":"+1 713 451 6835",
    "sg:postcode":"77015",
    "sg:province":"TX",
    "sg:tags":[
        "fence"
    ],
    "wof:name":"Alex Fence",
    "wof:placetype":"venue"
},
  "geometry": {"coordinates":[-95.17484399999999,29.788007],"type":"Point"}
}