{
  "type": "Feature",
  "properties": {
    "iso:country":"US",
    "sg:address":"4211 88th St",
    "sg:city":"Lubbock",
    "sg:classifiers":[
        {
            "category":"Building & Trades",
            "subcategory":"Construction",
            "type":"Services"
        }
    ],
    "sg:phone":"+1 806 794 2042",
    "sg:postcode":"79423",
    "sg:province":"TX",
    "sg:tags":[
        "house"
    ],
    "wof:name":"Burgess Remodeling Contractors",
    "wof:placetype":"venue"
},
  "geometry": {"coordinates":[-101.903499,33.513301],"type":"Point"}
}