{
  "type": "Feature",
  "properties": {
    "iso:country":"US",
    "sg:address":"6632 Southwest Fwy",
    "sg:city":"Houston",
    "sg:classifiers":[
        {
            "category":"Shopping",
            "subcategory":"Clothing, Apparel, & Fashions",
            "type":"Retail Goods"
        }
    ],
    "sg:phone":"+1 832 641 8121",
    "sg:postcode":"77074",
    "sg:province":"TX",
    "sg:tags":[
        "item",
        "boutique"
    ],
    "wof:name":"Renyon Boutique",
    "wof:placetype":"venue"
},
  "geometry": {"coordinates":[-95.500135,29.716494],"type":"Point"}
}