{
  "type": "Feature",
  "properties": {
    "iso:country":"US",
    "sg:address":"236 W Hwy 199",
    "sg:city":"Springtown",
    "sg:classifiers":[
        {
            "category":"Retail",
            "subcategory":"Auto Repair",
            "type":"Services"
        }
    ],
    "sg:phone":"+1 817 220 0227",
    "sg:postcode":"76082",
    "sg:province":"TX",
    "sg:tags":[
        "repairing",
        "automobile"
    ],
    "wof:name":"Trinity Auto Svc",
    "wof:placetype":"venue"
},
  "geometry": {"coordinates":[-97.685008,32.96361],"type":"Point"}
}