{
  "type": "Feature",
  "properties": {
    "iso:country":"US",
    "sg:address":"502 N Otyson Ave",
    "sg:city":"Mt Pleasant",
    "sg:classifiers":[
        {
            "category":"Education",
            "subcategory":"School",
            "type":"Public Place"
        }
    ],
    "sg:phone":"+1 903 575 2070",
    "sg:postcode":"75455",
    "sg:province":"TX",
    "wof:name":"Vivian Fowler Elementary Schl",
    "wof:placetype":"venue"
},
  "geometry": {"coordinates":[-94.970601,33.14367],"type":"Point"}
}