{
  "type": "Feature",
  "properties": {
    "iso:country":"US",
    "sg:address":"2650 Midway Rd Ste 100",
    "sg:city":"Carrollton",
    "sg:classifiers":[
        {
            "category":"Banks & Credit Unions",
            "subcategory":"Bank",
            "type":"Services"
        }
    ],
    "sg:phone":"+1 972 248 2003",
    "sg:postcode":"75006",
    "sg:province":"TX",
    "sg:website":"www.edscu.net",
    "wof:name":"EDS Credit Union",
    "wof:placetype":"venue"
},
  "geometry": {"coordinates":[-96.841886,32.985018],"type":"Point"}
}