{
  "type": "Feature",
  "properties": {
    "iso:country":"US",
    "sg:address":"3902 Apollo Rd",
    "sg:city":"Corpus Christi",
    "sg:classifiers":[
        {
            "category":"Building & Trades",
            "subcategory":"Construction",
            "type":"Services"
        }
    ],
    "sg:phone":"+1 361 854 0664",
    "sg:postcode":"78413",
    "sg:province":"TX",
    "sg:tags":[
        "dry wall",
        "contractor"
    ],
    "wof:name":"George Sahadi Inc",
    "wof:placetype":"venue"
},
  "geometry": {"coordinates":[-97.41742000000001,27.694838],"type":"Point"}
}