{
  "type": "Feature",
  "properties": {
    "iso:country":"US",
    "sg:address":"216 North St",
    "sg:city":"San Marcos",
    "sg:classifiers":[
        {
            "category":"Real Estate",
            "subcategory":"Real Estate Agent",
            "type":"Services"
        }
    ],
    "sg:phone":"+1 512 396 4857",
    "sg:postcode":"78666",
    "sg:province":"TX",
    "wof:name":"Intercare Corporation",
    "wof:placetype":"venue"
},
  "geometry": {"coordinates":[-97.94562000000001,29.883477],"type":"Point"}
}