{
  "type": "Feature",
  "properties": {
    "iso:country":"US",
    "sg:address":"10721 Research Blvd",
    "sg:city":"Austin",
    "sg:classifiers":[
        {
            "category":"Manufacturing",
            "subcategory":"Signs",
            "type":"Manufacturing & Wholesale Goods"
        }
    ],
    "sg:phone":"+1 512 342 1067",
    "sg:postcode":"78759",
    "sg:province":"TX",
    "wof:name":"Absolute Signage",
    "wof:placetype":"venue"
},
  "geometry": {"coordinates":[-97.74567999999999,30.398399],"type":"Point"}
}