{
  "type": "Feature",
  "properties": {
    "iso:country":"US",
    "sg:address":"535 Regal Row",
    "sg:city":"Dallas",
    "sg:classifiers":[
        {
            "category":"Wholesale",
            "subcategory":"Groceries",
            "type":"Manufacturing & Wholesale Goods"
        }
    ],
    "sg:phone":"+1 214 634 7839",
    "sg:postcode":"75247",
    "sg:province":"TX",
    "sg:tags":[
        "tortilla"
    ],
    "sg:website":"www.rudystortillas.com",
    "wof:name":"Rudy's Tortillas",
    "wof:placetype":"venue"
},
  "geometry": {"coordinates":[-96.897463,32.818352],"type":"Point"}
}