{
  "type": "Feature",
  "properties": {
    "iso:country":"US",
    "sg:address":"1410 Ransom Rd",
    "sg:city":"Richmond",
    "sg:classifiers":[
        {
            "category":"Government",
            "subcategory":"Police Station",
            "type":"Public Place"
        },
        {
            "category":"Government",
            "subcategory":"Office",
            "type":"Public Place"
        }
    ],
    "sg:phone":"+1 281 341 4665",
    "sg:postcode":"77469",
    "sg:province":"TX",
    "sg:tags":[
        "department",
        "parish",
        "government-county"
    ],
    "wof:name":"Fort Bend County Sheriff",
    "wof:placetype":"venue"
},
  "geometry": {"coordinates":[-95.755341,29.575791],"type":"Point"}
}