{
  "type": "Feature",
  "properties": {
    "iso:country":"US",
    "sg:address":"3000 Harkness Dr",
    "sg:city":"Plano",
    "sg:classifiers":[
        {
            "category":"Building & Trades",
            "subcategory":"Construction",
            "type":"Services"
        }
    ],
    "sg:phone":"+1 972 378 0300",
    "sg:postcode":"75093",
    "sg:province":"TX",
    "sg:tags":[
        "interior",
        "commercial"
    ],
    "wof:name":"Dallas Interior Construction",
    "wof:placetype":"venue"
},
  "geometry": {"coordinates":[-96.83778,33.040347],"type":"Point"}
}