{
  "type": "Feature",
  "properties": {
    "iso:country":"US",
    "sg:address":"514 E Ikard St",
    "sg:city":"Henrietta",
    "sg:classifiers":[
        {
            "category":"Social Services",
            "subcategory":"Child Care",
            "type":"Services"
        }
    ],
    "sg:phone":"+1 940 538 5132",
    "sg:postcode":"76365",
    "sg:province":"TX",
    "sg:tags":[
        "day"
    ],
    "wof:name":"Glenda Lavys Daycare",
    "wof:placetype":"venue"
},
  "geometry": {"coordinates":[-98.191095,33.816477],"type":"Point"}
}