{
  "type": "Feature",
  "properties": {
    "iso:country":"US",
    "sg:address":"5664 Paso Real Dr",
    "sg:city":"Brownsville",
    "sg:classifiers":[
        {
            "category":"Manufacturing",
            "subcategory":"Tools & Machinery",
            "type":"Manufacturing & Wholesale Goods"
        }
    ],
    "sg:phone":"+1 956 504 1912",
    "sg:postcode":"78521",
    "sg:province":"TX",
    "sg:tags":[
        "machine",
        "shop"
    ],
    "wof:name":"H G Machine Shop",
    "wof:placetype":"venue"
},
  "geometry": {"coordinates":[-97.428853,25.926557],"type":"Point"}
}