{
  "type": "Feature",
  "properties": {
    "iso:country":"US",
    "sg:address":"2435 Southmost Rd",
    "sg:city":"Brownsville",
    "sg:classifiers":[
        {
            "category":"Organizations",
            "subcategory":"Religious Organization",
            "type":"Services"
        }
    ],
    "sg:phone":"+1 956 542 7528",
    "sg:postcode":"78521",
    "sg:province":"TX",
    "sg:tags":[
        "church"
    ],
    "wof:name":"Bella Vista Christian Chr",
    "wof:placetype":"venue"
},
  "geometry": {"coordinates":[-97.46829099999999,25.908296],"type":"Point"}
}