{
  "type": "Feature",
  "properties": {
    "iso:country":"US",
    "sg:address":"3610 Potomac Ave",
    "sg:city":"Texarkana",
    "sg:classifiers":[
        {
            "category":"Professional",
            "subcategory":"Management & Consulting",
            "type":"Services"
        }
    ],
    "sg:phone":"+1 903 792 0782",
    "sg:postcode":"75503",
    "sg:province":"TX",
    "wof:name":"Jerry V Sparks",
    "wof:placetype":"venue"
},
  "geometry": {"coordinates":[-94.059957,33.452744],"type":"Point"}
}