{
  "type": "Feature",
  "properties": {
    "iso:country":"US",
    "sg:address":"8206 Bedford Euless Rd",
    "sg:city":"Fort Worth",
    "sg:classifiers":[
        {
            "category":"Restaurant",
            "type":"Food & Drink"
        }
    ],
    "sg:phone":"+1 817 485 8661",
    "sg:postcode":"76180",
    "sg:province":"TX",
    "sg:tags":[
        "bar"
    ],
    "wof:name":"Ernie's Restaurant & Bar",
    "wof:placetype":"venue"
},
  "geometry": {"coordinates":[-97.204714,32.834109],"type":"Point"}
}