{
  "type": "Feature",
  "properties": {
    "iso:country":"US",
    "sg:address":"5806 Foresthaven Dr",
    "sg:city":"Houston",
    "sg:classifiers":[
        {
            "category":"Professional",
            "type":"Services"
        }
    ],
    "sg:phone":"+1 713 537 6817",
    "sg:postcode":"77066",
    "sg:province":"TX",
    "wof:name":"Prospexx",
    "wof:placetype":"venue"
},
  "geometry": {"coordinates":[-95.51185099999999,29.973066],"type":"Point"}
}