{
  "type": "Feature",
  "properties": {
    "iso:country":"US",
    "sg:address":"604 Colonial Ln",
    "sg:city":"Killeen",
    "sg:classifiers":[
        {
            "category":"Freight",
            "type":"Transportation"
        }
    ],
    "sg:phone":"+1 254 699 4750",
    "sg:postcode":"76543",
    "sg:province":"TX",
    "wof:name":"SC Vaughns Transport",
    "wof:placetype":"venue"
},
  "geometry": {"coordinates":[-97.69455600000001,31.113646],"type":"Point"}
}