{
  "type": "Feature",
  "properties": {
    "iso:country":"US",
    "sg:address":"303 Silver Springs Rd",
    "sg:city":"Conroe",
    "sg:classifiers":[
        {
            "category":"Professional",
            "subcategory":"Business Services",
            "type":"Services"
        }
    ],
    "sg:phone":"+1 281 350 8630",
    "sg:postcode":"77303",
    "sg:province":"TX",
    "sg:tags":[
        "water",
        "treatment"
    ],
    "wof:name":"Hoffland Environmental",
    "wof:placetype":"venue"
},
  "geometry": {"coordinates":[-95.47658699999999,30.388824],"type":"Point"}
}