{
  "type": "Feature",
  "properties": {
    "iso:country":"US",
    "sg:address":"9614 Arborhill Dr",
    "sg:city":"Dallas",
    "sg:classifiers":[
        {
            "category":"Professional",
            "subcategory":"Business Services",
            "type":"Services"
        }
    ],
    "sg:phone":"+1 214 343 6302",
    "sg:postcode":"75243",
    "sg:province":"TX",
    "wof:name":"North Shore Group LLC",
    "wof:placetype":"venue"
},
  "geometry": {"coordinates":[-96.729293,32.906226],"type":"Point"}
}