{
  "type": "Feature",
  "properties": {
    "iso:country":"US",
    "sg:address":"1600 E Broad St",
    "sg:city":"Mansfield",
    "sg:classifiers":[
        {
            "category":"Food & Beverages",
            "subcategory":"Groceries & Convenience Stores",
            "type":"Retail Goods"
        }
    ],
    "sg:phone":"+1 817 473 1769",
    "sg:postcode":"76063",
    "sg:province":"TX",
    "wof:name":"Kountry Food Store",
    "wof:placetype":"venue"
},
  "geometry": {"coordinates":[-97.11432600000001,32.569111],"type":"Point"}
}