{
  "type": "Feature",
  "properties": {
    "iso:country":"US",
    "sg:address":"19953 Monk Ln",
    "sg:city":"Montgomery",
    "sg:classifiers":[
        {
            "category":"Restaurant",
            "type":"Food & Drink"
        }
    ],
    "sg:phone":"+1 936 449 6831",
    "sg:postcode":"77316",
    "sg:province":"TX",
    "sg:tags":[
        "eating"
    ],
    "wof:name":"Its Bento",
    "wof:placetype":"venue"
},
  "geometry": {"coordinates":[-95.673931,30.32079],"type":"Point"}
}