{
  "type": "Feature",
  "properties": {
    "iso:country":"US",
    "sg:address":"270 Long Leaf Cir",
    "sg:city":"Lufkin",
    "sg:classifiers":[
        {
            "category":"Building & Trades",
            "subcategory":"Plumbing",
            "type":"Services"
        }
    ],
    "sg:phone":"+1 936 634 5765",
    "sg:postcode":"75904",
    "sg:province":"TX",
    "sg:tags":[
        "tank",
        "septic"
    ],
    "wof:name":"Sarges Septic Systems",
    "wof:placetype":"venue"
},
  "geometry": {"coordinates":[-94.784183,31.359892],"type":"Point"}
}