{
  "type": "Feature",
  "properties": {
    "iso:country":"US",
    "sg:address":"1016 Red Oak St",
    "sg:city":"Azle",
    "sg:classifiers":[
        {
            "category":"Retail",
            "subcategory":"Repair Shop",
            "type":"Services"
        }
    ],
    "sg:phone":"+1 817 444 1091",
    "sg:postcode":"76020",
    "sg:province":"TX",
    "sg:tags":[
        "upholsterer"
    ],
    "wof:name":"A & H Upholstery By Design",
    "wof:placetype":"venue"
},
  "geometry": {"coordinates":[-97.549161,32.911298],"type":"Point"}
}