{
  "type": "Feature",
  "properties": {
    "iso:country":"US",
    "sg:address":"344 Harvard St",
    "sg:city":"Houston",
    "sg:classifiers":[
        {
            "category":"Mining & Drilling",
            "type":"Manufacturing & Wholesale Goods"
        }
    ],
    "sg:phone":"+1 713 880 0810",
    "sg:postcode":"77007",
    "sg:province":"TX",
    "sg:tags":[
        "development",
        "gas",
        "oil",
        "exploration"
    ],
    "wof:name":"Garrett Petrochemicals",
    "wof:placetype":"venue"
},
  "geometry": {"coordinates":[-95.396083,29.777469],"type":"Point"}
}