{
  "type": "Feature",
  "properties": {
    "iso:country":"US",
    "sg:address":"1318 Lucille St",
    "sg:city":"Burkburnett",
    "sg:classifiers":[
        {
            "category":"Retail",
            "subcategory":"Repair Shop",
            "type":"Services"
        }
    ],
    "sg:phone":"+1 940 569 4658",
    "sg:postcode":"76354",
    "sg:province":"TX",
    "sg:tags":[
        "lock",
        "locksmith"
    ],
    "wof:name":"Glen's Mobile Lock & Key Svc",
    "wof:placetype":"venue"
},
  "geometry": {"coordinates":[-98.54351800000001,34.07145],"type":"Point"}
}