{
  "type": "Feature",
  "properties": {
    "iso:country":"US",
    "sg:address":"701 N Texas Ave",
    "sg:city":"Bryan",
    "sg:classifiers":[
        {
            "category":"Real Estate",
            "subcategory":"Architect",
            "type":"Services"
        }
    ],
    "sg:phone":"+1 979 775 6036",
    "sg:postcode":"77803",
    "sg:province":"TX",
    "sg:tags":[
        "architectural"
    ],
    "wof:name":"Patterson Architects",
    "wof:placetype":"venue"
},
  "geometry": {"coordinates":[-96.369134,30.679717],"type":"Point"}
}