{
  "type": "Feature",
  "properties": {
    "iso:country":"US",
    "sg:address":"1110 S Friendswood Dr",
    "sg:city":"Friendswood",
    "sg:classifiers":[
        {
            "category":"Manufacturing",
            "subcategory":"Tools & Machinery",
            "type":"Manufacturing & Wholesale Goods"
        }
    ],
    "sg:phone":"+1 281 996 1549",
    "sg:postcode":"77546",
    "sg:province":"TX",
    "sg:tags":[
        "device",
        "medical"
    ],
    "wof:name":"Bioelectronics Corporation",
    "wof:placetype":"venue"
},
  "geometry": {"coordinates":[-95.19073,29.519731],"type":"Point"}
}