{
  "type": "Feature",
  "properties": {
    "iso:country":"US",
    "sg:address":"2110 Cypresstree Dr",
    "sg:city":"Spring",
    "sg:classifiers":[
        {
            "category":"Building & Trades",
            "subcategory":"Cleaning & Sanitation",
            "type":"Services"
        }
    ],
    "sg:phone":"+1 281 651 9380",
    "sg:postcode":"77373",
    "sg:province":"TX",
    "sg:tags":[
        "maintenance"
    ],
    "wof:name":"Loredos Maintenance & Detail",
    "wof:placetype":"venue"
},
  "geometry": {"coordinates":[-95.398297,30.04161],"type":"Point"}
}