{
  "type": "Feature",
  "properties": {
    "iso:country":"US",
    "sg:address":"2031 W Houston St",
    "sg:city":"Sherman",
    "sg:classifiers":[
        {
            "category":"Freight",
            "type":"Transportation"
        }
    ],
    "sg:phone":"+1 903 893 5189",
    "sg:postcode":"75092",
    "sg:province":"TX",
    "sg:tags":[
        "warehouse",
        "self",
        "storage"
    ],
    "wof:name":"Gilbert Mini Warehouse",
    "wof:placetype":"venue"
},
  "geometry": {"coordinates":[-96.63346300000001,33.630391],"type":"Point"}
}