{
  "type": "Feature",
  "properties": {
    "iso:country":"US",
    "sg:address":"823 Carrie Ct",
    "sg:city":"Little Elm",
    "sg:classifiers":[
        {
            "category":"Home & Garden",
            "subcategory":"Home Furnishings",
            "type":"Retail Goods"
        }
    ],
    "sg:phone":"+1 972 294 1111",
    "sg:postcode":"75068",
    "sg:province":"TX",
    "wof:name":"Fontaine Bearden Design",
    "wof:placetype":"venue"
},
  "geometry": {"coordinates":[-96.978053,33.132333],"type":"Point"}
}