{
  "type": "Feature",
  "properties": {
    "iso:country":"US",
    "sg:address":"525 W 42nd St",
    "sg:city":"Odessa",
    "sg:classifiers":[
        {
            "category":"Freight",
            "type":"Transportation"
        }
    ],
    "sg:phone":"+1 432 332 9991",
    "sg:postcode":"79764",
    "sg:province":"TX",
    "sg:tags":[
        "commercial",
        "storage"
    ],
    "wof:name":"A-1 U-Store-It Lockers",
    "wof:placetype":"venue"
},
  "geometry": {"coordinates":[-102.393109,31.880519],"type":"Point"}
}