{
  "type": "Feature",
  "properties": {
    "iso:country":"US",
    "sg:address":"413 Victorian Dr",
    "sg:city":"Waxahachie",
    "sg:classifiers":[
        {
            "category":"Professional",
            "subcategory":"Business Services",
            "type":"Services"
        },
        {
            "category":"Professional",
            "subcategory":"Computer Services",
            "type":"Services"
        }
    ],
    "sg:phone":"+1 972 923 2330",
    "sg:postcode":"75165",
    "sg:province":"TX",
    "sg:tags":[
        "consultant",
        "designer"
    ],
    "wof:name":"Southwest Data Solutions",
    "wof:placetype":"venue"
},
  "geometry": {"coordinates":[-96.804984,32.425235],"type":"Point"}
}