{
  "type": "Feature",
  "properties": {
    "iso:country":"US",
    "sg:address":"100 Independence Pl",
    "sg:city":"Tyler",
    "sg:classifiers":[
        {
            "category":"Organizations",
            "subcategory":"Religious Organization",
            "type":"Services"
        }
    ],
    "sg:phone":"+1 903 939 1201",
    "sg:postcode":"75703",
    "sg:province":"TX",
    "sg:website":"http://www.bibleteachingresources.org",
    "wof:name":"Bible Teaching Resources",
    "wof:placetype":"venue"
},
  "geometry": {"coordinates":[-95.30078899999999,32.298801],"type":"Point"}
}