{
  "type": "Feature",
  "properties": {
    "iso:country":"US",
    "sg:address":"1102 Ferguson St",
    "sg:city":"Conroe",
    "sg:classifiers":[
        {
            "category":"Shopping",
            "subcategory":"Clothing, Apparel, & Fashions",
            "type":"Retail Goods"
        }
    ],
    "sg:phone":"+1 936 441 5842",
    "sg:postcode":"77301",
    "sg:province":"TX",
    "wof:name":"Natalie Fashion Merchandising",
    "wof:placetype":"venue"
},
  "geometry": {"coordinates":[-95.46921500000001,30.324407],"type":"Point"}
}