{
  "type": "Feature",
  "properties": {
    "iso:country":"US",
    "sg:address":"7914 Carolwood Dr",
    "sg:city":"Houston",
    "sg:classifiers":[
        {
            "category":"Wholesale",
            "subcategory":"Apparel",
            "type":"Manufacturing & Wholesale Goods"
        }
    ],
    "sg:phone":"+1 713 633 7390",
    "sg:postcode":"77028",
    "sg:province":"TX",
    "sg:tags":[
        "hosiery",
        "merchandise",
        "general"
    ],
    "wof:name":"R B King & Son Supply Inc",
    "wof:placetype":"venue"
},
  "geometry": {"coordinates":[-95.28232800000001,29.836139],"type":"Point"}
}