{
  "type": "Feature",
  "properties": {
    "iso:country":"US",
    "sg:address":"3023 Bledsoe St",
    "sg:city":"Fort Worth",
    "sg:classifiers":[
        {
            "category":"Government",
            "subcategory":"Office",
            "type":"Public Place"
        }
    ],
    "sg:phone":"+1 817 870 2276",
    "sg:postcode":"76107",
    "sg:province":"TX",
    "sg:tags":[
        "human"
    ],
    "wof:name":"Human Services Texas Dept of",
    "wof:placetype":"venue"
},
  "geometry": {"coordinates":[-97.361586,32.748264],"type":"Point"}
}