{
  "type": "Feature",
  "properties": {
    "iso:country":"US",
    "sg:address":"2517 Montana Ave",
    "sg:city":"El Paso",
    "sg:classifiers":[
        {
            "category":"Professional",
            "subcategory":"Lawyer & Legal Services",
            "type":"Services"
        }
    ],
    "sg:phone":"+1 915 532 3647",
    "sg:postcode":"79903",
    "sg:province":"TX",
    "wof:name":"Frank L Hart",
    "wof:placetype":"venue"
},
  "geometry": {"coordinates":[-106.46573100000001,31.780642],"type":"Point"}
}