{
  "type": "Feature",
  "properties": {
    "iso:country":"US",
    "sg:address":"4841 Leopard St",
    "sg:city":"Corpus Christi",
    "sg:classifiers":[
        {
            "category":"Manufacturing",
            "subcategory":"Metals",
            "type":"Manufacturing & Wholesale Goods"
        }
    ],
    "sg:phone":"+1 361 881 8182",
    "sg:postcode":"78408",
    "sg:province":"TX",
    "sg:tags":[
        "industrial",
        "valve",
        "meter",
        "mfg"
    ],
    "wof:name":"Dresser Flow Control",
    "wof:placetype":"venue"
},
  "geometry": {"coordinates":[-97.450543,27.79717],"type":"Point"}
}