{
  "type": "Feature",
  "properties": {
    "iso:country":"US",
    "sg:address":"5100 Eldorado Pkwy",
    "sg:city":"Mc Kinney",
    "sg:classifiers":[
        {
            "category":"Restaurant",
            "type":"Food & Drink"
        }
    ],
    "sg:phone":"+1 972 548 7380",
    "sg:postcode":"75070",
    "sg:province":"TX",
    "sg:tags":[
        "pizza"
    ],
    "wof:name":"Little Caesars Pizza",
    "wof:placetype":"venue"
},
  "geometry": {"coordinates":[-96.685413,33.174103],"type":"Point"}
}