{
  "type": "Feature",
  "properties": {
    "iso:country":"US",
    "sg:address":"11623 Angus Road Suite 17",
    "sg:city":"Austin",
    "sg:classifiers":[
        {
            "category":"Health Services",
            "subcategory":"Doctor",
            "type":"Services"
        }
    ],
    "sg:phone":"+1 512 346 5562",
    "sg:postcode":"78759",
    "sg:province":"TX",
    "wof:name":"Tobey David N Jr MD",
    "wof:placetype":"venue"
},
  "geometry": {"coordinates":[-97.744175,30.413989],"type":"Point"}
}