{
  "type": "Feature",
  "properties": {
    "iso:country":"US",
    "sg:address":"1902 S Congress Ave",
    "sg:city":"Austin",
    "sg:classifiers":[
        {
            "category":"Personal",
            "subcategory":"Beauty Salon",
            "type":"Services"
        },
        {
            "category":"Personal",
            "subcategory":"Barber",
            "type":"Services"
        }
    ],
    "sg:phone":"+1 512 445 0500",
    "sg:postcode":"78704",
    "sg:province":"TX",
    "sg:tags":[
        "hair"
    ],
    "sg:website":"www.birdsbarbershop.com",
    "wof:name":"Birds Barbershop",
    "wof:placetype":"venue"
},
  "geometry": {"coordinates":[-97.751767,30.244998],"type":"Point"}
}