{
  "type": "Feature",
  "properties": {
    "iso:country":"US",
    "sg:address":"3218 Oklahoma St",
    "sg:city":"Houston",
    "sg:classifiers":[
        {
            "category":"Health Services",
            "subcategory":"Clinic",
            "type":"Services"
        }
    ],
    "sg:phone":"+1 713 694 4844",
    "sg:postcode":"77093",
    "sg:province":"TX",
    "wof:name":"TLC Home Health Care",
    "wof:placetype":"venue"
},
  "geometry": {"coordinates":[-95.339527,29.822802],"type":"Point"}
}