{
  "type": "Feature",
  "properties": {
    "iso:country":"US",
    "sg:address":"600 Kenrick Dr",
    "sg:city":"Houston",
    "sg:classifiers":[
        {
            "category":"Organizations",
            "subcategory":"Religious Organization",
            "type":"Services"
        }
    ],
    "sg:phone":"+1 281 999 8016",
    "sg:postcode":"77060",
    "sg:province":"TX",
    "sg:tags":[
        "church"
    ],
    "wof:name":"First Born Investments Inc",
    "wof:placetype":"venue"
},
  "geometry": {"coordinates":[-95.388846,29.941948],"type":"Point"}
}