{
  "type": "Feature",
  "properties": {
    "iso:country":"US",
    "sg:address":"1007 Francis Dr",
    "sg:city":"College Station",
    "sg:classifiers":[
        {
            "category":"Professional",
            "subcategory":"Management & Consulting",
            "type":"Services"
        }
    ],
    "sg:phone":"+1 979 694 7199",
    "sg:postcode":"77840",
    "sg:province":"TX",
    "sg:tags":[
        "environmental",
        "legal"
    ],
    "wof:name":"Quality Assurance Associates",
    "wof:placetype":"venue"
},
  "geometry": {"coordinates":[-96.315612,30.632721],"type":"Point"}
}