{
  "type": "Feature",
  "properties": {
    "iso:country":"US",
    "sg:address":"7530 Chevy Chase Dr",
    "sg:city":"Houston",
    "sg:classifiers":[
        {
            "category":"Professional",
            "subcategory":"Business Services",
            "type":"Services"
        }
    ],
    "sg:phone":"+1 713 787 0899",
    "sg:postcode":"77063",
    "sg:province":"TX",
    "wof:name":"Solutionworld Inc",
    "wof:placetype":"venue"
},
  "geometry": {"coordinates":[-95.50242799999999,29.744775],"type":"Point"}
}