{
  "type": "Feature",
  "properties": {
    "iso:country":"US",
    "sg:address":"7907 Co Rd 3802",
    "sg:city":"Bullard",
    "sg:classifiers":[
        {
            "category":"Building & Trades",
            "subcategory":"Construction",
            "type":"Services"
        }
    ],
    "sg:phone":"+1 903 894 4245",
    "sg:postcode":"75778",
    "sg:province":"TX",
    "sg:tags":[
        "designer",
        "dealer",
        "pool",
        "swimming"
    ],
    "wof:name":"Southwest Poolworks",
    "wof:placetype":"venue"
},
  "geometry": {"coordinates":[-95.750602,32.345127],"type":"Point"}
}