{
  "type": "Feature",
  "properties": {
    "iso:country":"US",
    "sg:address":"5655 W Lovers Ln",
    "sg:city":"Dallas",
    "sg:classifiers":[
        {
            "category":"Wholesale",
            "subcategory":"Home Furnishings",
            "type":"Manufacturing & Wholesale Goods"
        },
        {
            "category":"Shopping",
            "subcategory":"Jewelry",
            "type":"Retail Goods"
        }
    ],
    "sg:phone":"+1 214 357 7115",
    "sg:postcode":"75209",
    "sg:province":"TX",
    "sg:tags":[
        "silverware"
    ],
    "wof:name":"Silver Vault",
    "wof:placetype":"venue"
},
  "geometry": {"coordinates":[-96.816452,32.85124],"type":"Point"}
}