{
  "type": "Feature",
  "properties": {
    "iso:country":"US",
    "sg:address":"915 Isernia Dr",
    "sg:city":"Austin",
    "sg:classifiers":[
        {
            "category":"Wholesale",
            "subcategory":"Hardware",
            "type":"Manufacturing & Wholesale Goods"
        }
    ],
    "sg:phone":"+1 512 280 4636",
    "sg:postcode":"78748",
    "sg:province":"TX",
    "wof:name":"Clean Air Diagnostics LLC",
    "wof:placetype":"venue"
},
  "geometry": {"coordinates":[-97.815721,30.163078],"type":"Point"}
}