{
  "type": "Feature",
  "properties": {
    "iso:country":"US",
    "sg:address":"6107 Sienna Arbor Ln",
    "sg:city":"Houston",
    "sg:classifiers":[
        {
            "category":"Real Estate",
            "subcategory":"Real Estate Agent",
            "type":"Services"
        }
    ],
    "sg:phone":"+1 713 896 0902",
    "sg:postcode":"77041",
    "sg:province":"TX",
    "wof:name":"AJK Enterprises",
    "wof:placetype":"venue"
},
  "geometry": {"coordinates":[-95.598985,29.86034],"type":"Point"}
}