{
  "type": "Feature",
  "properties": {
    "iso:country":"US",
    "sg:address":"2401 Westport Pkwy",
    "sg:city":"Fort Worth",
    "sg:classifiers":[
        {
            "category":"Restaurant",
            "type":"Food & Drink"
        }
    ],
    "sg:phone":"+1 817 837 1077",
    "sg:postcode":"76177",
    "sg:province":"TX",
    "wof:name":"Snooty Pig Cafe",
    "wof:placetype":"venue"
},
  "geometry": {"coordinates":[-97.31238500000001,32.972175],"type":"Point"}
}