{
  "type": "Feature",
  "properties": {
    "iso:country":"US",
    "sg:address":"2122 Crystal Downs Dr",
    "sg:city":"Katy",
    "sg:classifiers":[
        {
            "category":"Building & Trades",
            "subcategory":"Plumbing",
            "type":"Services"
        }
    ],
    "sg:phone":"+1 281 395 9700",
    "sg:postcode":"77450",
    "sg:province":"TX",
    "sg:tags":[
        "conditioning",
        "air",
        "system",
        "contractor"
    ],
    "wof:name":"Ashford Air",
    "wof:placetype":"venue"
},
  "geometry": {"coordinates":[-95.764483,29.750257],"type":"Point"}
}