{
  "type": "Feature",
  "properties": {
    "iso:country":"US",
    "sg:address":"24703 Pecan Dr",
    "sg:city":"New Caney",
    "sg:classifiers":[
        {
            "category":"Real Estate",
            "subcategory":"Real Estate Agent",
            "type":"Services"
        }
    ],
    "sg:phone":"+1 281 399 3333",
    "sg:postcode":"77357",
    "sg:province":"TX",
    "wof:name":"Results Home Buyers Inc",
    "wof:placetype":"venue"
},
  "geometry": {"coordinates":[-95.186564,30.141737],"type":"Point"}
}