{
  "type": "Feature",
  "properties": {
    "iso:country":"US",
    "sg:address":"2001 Merrick St",
    "sg:city":"Fort Worth",
    "sg:classifiers":[
        {
            "category":"Professional",
            "type":"Services"
        }
    ],
    "sg:phone":"+1 817 735 1123",
    "sg:postcode":"76107",
    "sg:province":"TX",
    "wof:name":"LLC Phillips Lake",
    "wof:placetype":"venue"
},
  "geometry": {"coordinates":[-97.39800099999999,32.740634],"type":"Point"}
}