{
  "type": "Feature",
  "properties": {
    "iso:country":"US",
    "sg:address":"3030 Mockingbird Ln",
    "sg:city":"Dallas",
    "sg:classifiers":[
        {
            "category":"Retail",
            "subcategory":"Laundry & Dry Cleaning",
            "type":"Services"
        }
    ],
    "sg:phone":"+1 214 987 0665",
    "sg:postcode":"75205",
    "sg:province":"TX",
    "wof:name":"Swiss Cleaners & Laundry",
    "wof:placetype":"venue"
},
  "geometry": {"coordinates":[-96.7826,32.8367],"type":"Point"}
}