{
  "type": "Feature",
  "properties": {
    "iso:country":"US",
    "sg:address":"105 Gum Springs Rd",
    "sg:city":"Longview",
    "sg:classifiers":[
        {
            "category":"Wholesale",
            "subcategory":"Machinery & Supplies",
            "type":"Manufacturing & Wholesale Goods"
        }
    ],
    "sg:phone":"+1 903 236 2533",
    "sg:postcode":"75602",
    "sg:province":"TX",
    "sg:tags":[
        "equipment",
        "industrial"
    ],
    "wof:name":"Outdoor Power Equipment",
    "wof:placetype":"venue"
},
  "geometry": {"coordinates":[-94.71363100000001,32.490802],"type":"Point"}
}