{
  "type": "Feature",
  "properties": {
    "iso:country":"US",
    "sg:address":"8530 Ewing Halsell Dr",
    "sg:city":"San Antonio",
    "sg:classifiers":[
        {
            "category":"Education",
            "subcategory":"School",
            "type":"Public Place"
        }
    ],
    "sg:phone":"+1 210 692 6100",
    "sg:postcode":"78229",
    "sg:province":"TX",
    "sg:website":"www.ncc.com",
    "wof:name":"Northside Children Ctr",
    "wof:placetype":"venue"
},
  "geometry": {"coordinates":[-98.579824,29.519554],"type":"Point"}
}