{
  "type": "Feature",
  "properties": {
    "iso:country":"US",
    "sg:address":"35623 FM 149",
    "sg:city":"Pinehurst",
    "sg:classifiers":[
        {
            "category":"Recreation",
            "subcategory":"Marina",
            "type":"Entertainment"
        }
    ],
    "sg:phone":"+1 281 356 7954",
    "sg:postcode":"77362",
    "sg:province":"TX",
    "sg:tags":[
        "operation"
    ],
    "wof:name":"Hendricks Boat Rv Mini-Storage",
    "wof:placetype":"venue"
},
  "geometry": {"coordinates":[-95.683589,30.173477],"type":"Point"}
}