{
  "type": "Feature",
  "properties": {
    "iso:country":"US",
    "sg:address":"824 N Main St",
    "sg:city":"Boerne",
    "sg:classifiers":[
        {
            "category":"Fast Food",
            "type":"Food & Drink"
        },
        {
            "category":"Restaurant",
            "type":"Food & Drink"
        }
    ],
    "sg:phone":"+1 830 249 9777",
    "sg:postcode":"78006",
    "sg:province":"TX",
    "sg:tags":[
        "pizza"
    ],
    "wof:name":"Fargo Pizza",
    "wof:placetype":"venue"
},
  "geometry": {"coordinates":[-98.729055,29.786228],"type":"Point"}
}