{
  "type": "Feature",
  "properties": {
    "iso:country":"US",
    "sg:address":"7447 Harwin Dr",
    "sg:city":"Houston",
    "sg:classifiers":[
        {
            "category":"Health Services",
            "subcategory":"Hospital",
            "type":"Services"
        }
    ],
    "sg:phone":"+1 713 800 8669",
    "sg:postcode":"77036",
    "sg:province":"TX",
    "sg:tags":[
        "ambulance"
    ],
    "wof:name":"Rapid Ems",
    "wof:placetype":"venue"
},
  "geometry": {"coordinates":[-95.51396099999999,29.717625],"type":"Point"}
}