{
  "type": "Feature",
  "properties": {
    "iso:country":"US",
    "sg:address":"505 W Cano St",
    "sg:city":"Edinburg",
    "sg:classifiers":[
        {
            "category":"Professional",
            "subcategory":"Lawyer & Legal Services",
            "type":"Services"
        }
    ],
    "sg:phone":"+1 956 318 1517",
    "sg:postcode":"78539",
    "sg:province":"TX",
    "wof:name":"Law Office of John Rivera",
    "wof:placetype":"venue"
},
  "geometry": {"coordinates":[-98.168071,26.30122],"type":"Point"}
}