{
  "type": "Feature",
  "properties": {
    "iso:country":"US",
    "sg:address":"2412 Richland Ave",
    "sg:city":"Dallas",
    "sg:classifiers":[
        {
            "category":"Retail",
            "subcategory":"Repair Shop",
            "type":"Services"
        }
    ],
    "sg:phone":"+1 214 637 1264",
    "sg:postcode":"75234",
    "sg:province":"TX",
    "sg:tags":[
        "repairing",
        "saw",
        "power",
        "mfg"
    ],
    "wof:name":"Dallas Saw & Supply Co",
    "wof:placetype":"venue"
},
  "geometry": {"coordinates":[-96.89649799999999,32.929179],"type":"Point"}
}