{
  "type": "Feature",
  "properties": {
    "iso:country":"US",
    "sg:address":"14552 Hirschi Loop",
    "sg:city":"Electra",
    "sg:phone":"+1 940 569 0341",
    "sg:postcode":"76360",
    "sg:province":"TX",
    "sg:tags":[
        "wheat",
        "beef",
        "farm",
        "cattle",
        "feedlot",
        "cotton"
    ],
    "wof:name":"Double L Farms",
    "wof:placetype":"venue"
},
  "geometry": {"coordinates":[-98.78091499999999,34.120594],"type":"Point"}
}