{
  "type": "Feature",
  "properties": {
    "iso:country":"US",
    "sg:address":"711 Sunset Ave",
    "sg:city":"Dallas",
    "sg:classifiers":[
        {
            "category":"Health Services",
            "subcategory":"Chiropractor",
            "type":"Services"
        }
    ],
    "sg:phone":"+1 214 943 9444",
    "sg:postcode":"75208",
    "sg:province":"TX",
    "wof:name":"David Alexander",
    "wof:placetype":"venue"
},
  "geometry": {"coordinates":[-96.83561,32.744235],"type":"Point"}
}