{
  "type": "Feature",
  "properties": {
    "iso:country":"US",
    "sg:address":"610 Leaflet Ln",
    "sg:city":"Spring",
    "sg:classifiers":[
        {
            "category":"Shopping",
            "subcategory":"Used Merchandise",
            "type":"Retail Goods"
        }
    ],
    "sg:phone":"+1 281 528 8884",
    "sg:postcode":"77388",
    "sg:province":"TX",
    "wof:name":"Nancy McJunkin",
    "wof:placetype":"venue"
},
  "geometry": {"coordinates":[-95.440719,30.04254],"type":"Point"}
}