{
  "type": "Feature",
  "properties": {
    "iso:country":"US",
    "sg:address":"8428 Denton Hwy",
    "sg:city":"Fort Worth",
    "sg:classifiers":[
        {
            "category":"Restaurant",
            "type":"Food & Drink"
        }
    ],
    "sg:menulink":"http://www.allmenus.com/tx/northeast-tarrant/106887-soup-man/menu/",
    "sg:phone":"+1 817 581 4135",
    "sg:postcode":"76148",
    "sg:province":"TX",
    "sg:tags":[
        "soup",
        "american",
        "salad"
    ],
    "wof:name":"Soup Man",
    "wof:placetype":"venue"
},
  "geometry": {"coordinates":[-97.257161,32.893443],"type":"Point"}
}