{
  "type": "Feature",
  "properties": {
    "iso:country":"US",
    "sg:address":"4635 Sugar Mill Rd",
    "sg:city":"Dallas",
    "sg:classifiers":[
        {
            "category":"Professional",
            "subcategory":"Lawyer & Legal Services",
            "type":"Services"
        }
    ],
    "sg:phone":"+1 972 490 5038",
    "sg:postcode":"75244",
    "sg:province":"TX",
    "wof:name":"Meyer James S Atty",
    "wof:placetype":"venue"
},
  "geometry": {"coordinates":[-96.828598,32.9189],"type":"Point"}
}