{
  "type": "Feature",
  "properties": {
    "iso:country":"US",
    "sg:address":"411 Noonday Ln",
    "sg:city":"Houston",
    "sg:classifiers":[
        {
            "category":"Building & Trades",
            "subcategory":"Construction",
            "type":"Services"
        }
    ],
    "sg:phone":"+1 281 447 7777",
    "sg:postcode":"77060",
    "sg:province":"TX",
    "sg:tags":[
        "nonresidential"
    ],
    "wof:name":"Samson Construction",
    "wof:placetype":"venue"
},
  "geometry": {"coordinates":[-95.392352,29.920347],"type":"Point"}
}