{
  "type": "Feature",
  "properties": {
    "iso:country":"US",
    "sg:address":"2204 Lobo Dr",
    "sg:city":"Bryan",
    "sg:classifiers":[
        {
            "category":"Professional",
            "subcategory":"Business Services",
            "type":"Services"
        },
        {
            "category":"Shopping",
            "subcategory":"Crafts & Fabrics",
            "type":"Retail Goods"
        }
    ],
    "sg:phone":"+1 979 779 2494",
    "sg:postcode":"77807",
    "sg:province":"TX",
    "sg:tags":[
        "sewing",
        "embroidery"
    ],
    "wof:name":"Luckie Touch Embroidery Dgtzng",
    "wof:placetype":"venue"
},
  "geometry": {"coordinates":[-96.383004,30.623492],"type":"Point"}
}