{
  "type": "Feature",
  "properties": {
    "iso:country":"US",
    "sg:address":"1140 Broadway",
    "sg:city":"Kerrville",
    "sg:classifiers":[
        {
            "category":"Home & Garden",
            "subcategory":"Building Materials",
            "type":"Retail Goods"
        }
    ],
    "sg:phone":"+1 830 257 3350",
    "sg:postcode":"78028",
    "sg:province":"TX",
    "sg:tags":[
        "glass",
        "window",
        "plate"
    ],
    "wof:name":"C D Tile",
    "wof:placetype":"venue"
},
  "geometry": {"coordinates":[-99.13512900000001,30.042017],"type":"Point"}
}