{
  "type": "Feature",
  "properties": {
    "iso:country":"US",
    "sg:address":"108 US Hwy 80 E",
    "sg:city":"Mesquite",
    "sg:classifiers":[
        {
            "category":"Food & Beverages",
            "subcategory":"Groceries & Convenience Stores",
            "type":"Retail Goods"
        }
    ],
    "sg:phone":"+1 972 285 3902",
    "sg:postcode":"75149",
    "sg:province":"TX",
    "wof:name":"Golden Rissco Inc",
    "wof:placetype":"venue"
},
  "geometry": {"coordinates":[-96.596515,32.790135],"type":"Point"}
}