{
  "type": "Feature",
  "properties": {
    "iso:country":"US",
    "sg:address":"16812 Ave B",
    "sg:city":"Channelview",
    "sg:classifiers":[
        {
            "category":"Wholesale",
            "subcategory":"Vending Machines",
            "type":"Manufacturing & Wholesale Goods"
        }
    ],
    "sg:phone":"+1 281 452 7672",
    "sg:postcode":"77530",
    "sg:province":"TX",
    "sg:tags":[
        "operator"
    ],
    "wof:name":"Neal Vending",
    "wof:placetype":"venue"
},
  "geometry": {"coordinates":[-95.100227,29.790862],"type":"Point"}
}