{
  "type": "Feature",
  "properties": {
    "iso:country":"US",
    "sg:address":"1502 Cedarbrook Dr",
    "sg:city":"Houston",
    "sg:classifiers":[
        {
            "category":"Health Services",
            "subcategory":"Clinic",
            "type":"Services"
        }
    ],
    "sg:phone":"+1 713 932 6012",
    "sg:postcode":"77055",
    "sg:province":"TX",
    "sg:tags":[
        "home",
        "care"
    ],
    "wof:name":"Jmh Resources Inc",
    "wof:placetype":"venue"
},
  "geometry": {"coordinates":[-95.506136,29.795688],"type":"Point"}
}