{
  "type": "Feature",
  "properties": {
    "iso:country":"US",
    "sg:address":"613 Farmington Rd",
    "sg:city":"Howe",
    "sg:classifiers":[
        {
            "category":"Autos & Motor Vehicles",
            "subcategory":"Fuel & Gas Station",
            "type":"Retail Goods"
        }
    ],
    "sg:phone":"+1 903 532 6919",
    "sg:postcode":"75459",
    "sg:province":"TX",
    "sg:tags":[
        "terminal",
        "truck"
    ],
    "wof:name":"Flat-Gard Inc",
    "wof:placetype":"venue"
},
  "geometry": {"coordinates":[-96.618261,33.500593],"type":"Point"}
}