{
  "type": "Feature",
  "properties": {
    "iso:country":"US",
    "sg:address":"7000 Regency Square Blvd",
    "sg:city":"Houston",
    "sg:classifiers":[
        {
            "category":"Professional",
            "subcategory":"Business Services",
            "type":"Services"
        }
    ],
    "sg:phone":"+1 713 266 0804",
    "sg:postcode":"77036",
    "sg:province":"TX",
    "wof:name":"Tai Appraisal Inc",
    "wof:placetype":"venue"
},
  "geometry": {"coordinates":[-95.506827,29.715681],"type":"Point"}
}