{
  "type": "Feature",
  "properties": {
    "iso:country":"US",
    "sg:address":"1075 Orange St",
    "sg:city":"Vidor",
    "sg:classifiers":[
        {
            "category":"Food & Beverages",
            "subcategory":"Groceries & Convenience Stores",
            "type":"Retail Goods"
        }
    ],
    "sg:phone":"+1 409 769 0731",
    "sg:postcode":"77662",
    "sg:province":"TX",
    "wof:name":"Country Pantry",
    "wof:placetype":"venue"
},
  "geometry": {"coordinates":[-93.998001,30.123726],"type":"Point"}
}