{
  "type": "Feature",
  "properties": {
    "iso:country":"US",
    "sg:address":"6326 Wynnwood Ln",
    "sg:city":"Houston",
    "sg:classifiers":[
        {
            "category":"Building & Trades",
            "subcategory":"Construction",
            "type":"Services"
        }
    ],
    "sg:phone":"+1 713 869 4262",
    "sg:postcode":"77008",
    "sg:province":"TX",
    "sg:tags":[
        "contractor"
    ],
    "wof:name":"Bygary Building Specialist",
    "wof:placetype":"venue"
},
  "geometry": {"coordinates":[-95.425335,29.794605],"type":"Point"}
}