{
  "type": "Feature",
  "properties": {
    "iso:country":"US",
    "sg:address":"503 US Hwy 83",
    "sg:city":"Zapata",
    "sg:classifiers":[
        {
            "category":"Food & Beverages",
            "subcategory":"Groceries & Convenience Stores",
            "type":"Retail Goods"
        }
    ],
    "sg:phone":"+1 956 765 0940",
    "sg:postcode":"78076",
    "sg:province":"TX",
    "wof:name":"Seven Days Express",
    "wof:placetype":"venue"
},
  "geometry": {"coordinates":[-99.266402,26.901003],"type":"Point"}
}