{
  "type": "Feature",
  "properties": {
    "iso:country":"US",
    "sg:address":"1000 Markham Ln",
    "sg:city":"Austin",
    "sg:classifiers":[
        {
            "category":"Autos & Motor Vehicles",
            "subcategory":"Automobile Sales",
            "type":"Retail Goods"
        }
    ],
    "sg:phone":"+1 512 473 8818",
    "sg:postcode":"78753",
    "sg:province":"TX",
    "sg:tags":[
        "car",
        "dealer"
    ],
    "wof:name":"Emerald Drilling Solutions Inc",
    "wof:placetype":"venue"
},
  "geometry": {"coordinates":[-97.660089,30.393693],"type":"Point"}
}