{
  "type": "Feature",
  "properties": {
    "iso:country":"US",
    "sg:address":"19221 I- 45 S",
    "sg:city":"Conroe",
    "sg:classifiers":[
        {
            "category":"Real Estate",
            "subcategory":"Real Estate Agent",
            "type":"Services"
        }
    ],
    "sg:phone":"+1 281 465 0950",
    "sg:postcode":"77385",
    "sg:province":"TX",
    "wof:name":"Triple Net Properties",
    "wof:placetype":"venue"
},
  "geometry": {"coordinates":[-95.450991,30.173969],"type":"Point"}
}