{
  "type": "Feature",
  "properties": {
    "iso:country":"US",
    "sg:address":"Hwy 290 & 71",
    "sg:city":"Austin",
    "sg:classifiers":[
        {
            "category":"Personal",
            "subcategory":"Beauty Salon",
            "type":"Services"
        }
    ],
    "sg:phone":"+1 512 301 1460",
    "sg:postcode":"78736",
    "sg:province":"TX",
    "sg:tags":[
        "makeup",
        "artist"
    ],
    "sg:website":"www.makeupbysabrina.com",
    "wof:name":"Makeup By Sabrina",
    "wof:placetype":"venue"
},
  "geometry": {"coordinates":[-97.87475499999999,30.233414],"type":"Point"}
}