{
  "type": "Feature",
  "properties": {
    "iso:country":"US",
    "sg:address":"855 Montgomery St",
    "sg:city":"Fort Worth",
    "sg:classifiers":[
        {
            "category":"Health Services",
            "subcategory":"Doctor",
            "type":"Services"
        }
    ],
    "sg:phone":"+1 817 735 2238",
    "sg:postcode":"76107",
    "sg:province":"TX",
    "sg:tags":[
        "physician",
        "surgeon"
    ],
    "wof:name":"Obstetrics & Gynecology Clinic",
    "wof:placetype":"venue"
},
  "geometry": {"coordinates":[-97.36981299999999,32.750988],"type":"Point"}
}