{
  "type": "Feature",
  "properties": {
    "iso:country":"US",
    "sg:address":"172 Spring Town Rd",
    "sg:city":"Van Alstyne",
    "sg:classifiers":[
        {
            "category":"Building & Trades",
            "subcategory":"Plumbing",
            "type":"Services"
        }
    ],
    "sg:phone":"+1 903 482 6407",
    "sg:postcode":"75495",
    "sg:province":"TX",
    "sg:tags":[
        "plumbing",
        "contractor"
    ],
    "wof:name":"J & J Plumbing",
    "wof:placetype":"venue"
},
  "geometry": {"coordinates":[-96.499207,33.419156],"type":"Point"}
}