{
  "type": "Feature",
  "properties": {
    "iso:country":"US",
    "sg:address":"7615 Yuma Dr",
    "sg:city":"El Paso",
    "sg:classifiers":[
        {
            "category":"Education",
            "subcategory":"School",
            "type":"Public Place"
        }
    ],
    "sg:phone":"+1 915 434 2300",
    "sg:postcode":"79915",
    "sg:province":"TX",
    "wof:name":"Ranchland Hills Middle School",
    "wof:placetype":"venue"
},
  "geometry": {"coordinates":[-106.360866,31.757634],"type":"Point"}
}