{
  "type": "Feature",
  "properties": {
    "iso:country":"US",
    "sg:address":"119 Short Ave",
    "sg:city":"Seguin",
    "sg:classifiers":[
        {
            "category":"Personal",
            "subcategory":"Beauty Salon",
            "type":"Services"
        }
    ],
    "sg:phone":"+1 830 379 1677",
    "sg:postcode":"78155",
    "sg:province":"TX",
    "wof:name":"All About Hair",
    "wof:placetype":"venue"
},
  "geometry": {"coordinates":[-97.977861,29.569116],"type":"Point"}
}