{
  "type": "Feature",
  "properties": {
    "iso:country":"US",
    "sg:address":"414 E Tyler St",
    "sg:city":"Athens",
    "sg:classifiers":[
        {
            "category":"Banks & Credit Unions",
            "subcategory":"Financial Services",
            "type":"Services"
        }
    ],
    "sg:phone":"+1 903 675 0002",
    "sg:postcode":"75751",
    "sg:province":"TX",
    "sg:tags":[
        "cashing",
        "loan",
        "payday",
        "alternative",
        "check"
    ],
    "sg:website":"http://www.acecashexpress.com",
    "wof:name":"ACE Cash Express",
    "wof:placetype":"venue"
},
  "geometry": {"coordinates":[-95.849981,32.205429],"type":"Point"}
}