{
  "type": "Feature",
  "properties": {
    "iso:country":"US",
    "sg:address":"954 FM 1960 W",
    "sg:city":"Houston",
    "sg:classifiers":[
        {
            "category":"Professional",
            "type":"Services"
        }
    ],
    "sg:phone":"+1 281 866 0639",
    "sg:postcode":"77090",
    "sg:province":"TX",
    "wof:name":"Fajardo Elsy",
    "wof:placetype":"venue"
},
  "geometry": {"coordinates":[-95.45018,30.014302],"type":"Point"}
}