{
  "type": "Feature",
  "properties": {
    "iso:country":"US",
    "sg:address":"507 Western Hills Trl",
    "sg:city":"Granbury",
    "sg:classifiers":[
        {
            "category":"Organizations",
            "subcategory":"Religious Organization",
            "type":"Services"
        }
    ],
    "sg:phone":"+1 817 573 7588",
    "sg:postcode":"76049",
    "sg:province":"TX",
    "wof:name":"Western Hills Baptist Church",
    "wof:placetype":"venue"
},
  "geometry": {"coordinates":[-97.75561399999999,32.434906],"type":"Point"}
}