{
  "type": "Feature",
  "properties": {
    "iso:country":"US",
    "sg:address":"5667 Colin Powell Ave",
    "sg:city":"El Paso",
    "sg:classifiers":[
        {
            "category":"Professional",
            "subcategory":"Printing & Photocopies",
            "type":"Services"
        }
    ],
    "sg:phone":"+1 915 821 0404",
    "sg:postcode":"79934",
    "sg:province":"TX",
    "sg:tags":[
        "photocopying"
    ],
    "wof:name":"Bonanza Printing & Paper",
    "wof:placetype":"venue"
},
  "geometry": {"coordinates":[-106.41191600000001,31.932125],"type":"Point"}
}