{
  "type": "Feature",
  "properties": {
    "iso:country":"US",
    "sg:address":"7529 S Kirkwood Rd",
    "sg:city":"Houston",
    "sg:classifiers":[
        {
            "category":"Autos & Motor Vehicles",
            "subcategory":"Automobile Sales",
            "type":"Retail Goods"
        }
    ],
    "sg:phone":"+1 281 933 8550",
    "sg:postcode":"77072",
    "sg:province":"TX",
    "sg:tags":[
        "dealers-used",
        "used",
        "cars-wholesale",
        "car"
    ],
    "wof:name":"Tx Enterprises",
    "wof:placetype":"venue"
},
  "geometry": {"coordinates":[-95.587633,29.696539],"type":"Point"}
}