{
  "type": "Feature",
  "properties": {
    "iso:country":"US",
    "sg:address":"477 Shiloh Rd",
    "sg:city":"Bastrop",
    "sg:classifiers":[
        {
            "category":"Retail",
            "subcategory":"Animal Services",
            "type":"Services"
        }
    ],
    "sg:phone":"+1 512 303 7656",
    "sg:postcode":"78602",
    "sg:province":"TX",
    "wof:name":"Puppy Love Kennel",
    "wof:placetype":"venue"
},
  "geometry": {"coordinates":[-97.38476199999999,30.094195],"type":"Point"}
}