{
  "type": "Feature",
  "properties": {
    "iso:country":"US",
    "sg:address":"537 Chamberlain St",
    "sg:city":"Corpus Christi",
    "sg:classifiers":[
        {
            "category":"Building & Trades",
            "subcategory":"Landscaping Services",
            "type":"Services"
        }
    ],
    "sg:phone":"+1 361 855 1951",
    "sg:postcode":"78404",
    "sg:province":"TX",
    "sg:tags":[
        "landscape"
    ],
    "wof:name":"Doug Wade Landscape Architect",
    "wof:placetype":"venue"
},
  "geometry": {"coordinates":[-97.39406700000001,27.760259],"type":"Point"}
}