{
  "type": "Feature",
  "properties": {
    "iso:country":"US",
    "sg:address":"12609 Dessau Rd Ste 560",
    "sg:city":"Austin",
    "sg:classifiers":[
        {
            "category":"Communications",
            "subcategory":"Film & Video Production",
            "type":"Services"
        }
    ],
    "sg:phone":"+1 832 681 1617",
    "sg:postcode":"78754",
    "sg:province":"TX",
    "sg:tags":[
        "video/film"
    ],
    "wof:name":"NewBlock Video",
    "wof:placetype":"venue"
},
  "geometry": {"coordinates":[-97.642107,30.391869],"type":"Point"}
}