{
  "type": "Feature",
  "properties": {
    "iso:country":"US",
    "sg:address":"500 W 3rd Ave",
    "sg:city":"Corsicana",
    "sg:classifiers":[
        {
            "category":"Railroad",
            "type":"Transportation"
        }
    ],
    "sg:phone":"+1 903 872 5422",
    "sg:postcode":"75110",
    "sg:province":"TX",
    "sg:tags":[
        "operator",
        "line"
    ],
    "wof:name":"Brenco Incorporated",
    "wof:placetype":"venue"
},
  "geometry": {"coordinates":[-96.46985599999999,32.094135],"type":"Point"}
}