{
  "type": "Feature",
  "properties": {
    "iso:country":"US",
    "sg:address":"1708 Grand Ave",
    "sg:city":"Beaumont",
    "sg:classifiers":[
        {
            "category":"Shopping",
            "subcategory":"Clothing, Apparel, & Fashions",
            "type":"Retail Goods"
        }
    ],
    "sg:phone":"+1 409 212 9530",
    "sg:postcode":"77703",
    "sg:province":"TX",
    "wof:name":"Too Sexy Clothes",
    "wof:placetype":"venue"
},
  "geometry": {"coordinates":[-94.102902,30.09749],"type":"Point"}
}