{
  "type": "Feature",
  "properties": {
    "iso:country":"US",
    "sg:address":"303 E Harwood Ave",
    "sg:city":"Beeville",
    "sg:classifiers":[
        {
            "category":"Professional",
            "type":"Services"
        }
    ],
    "sg:phone":"+1 361 358 3030",
    "sg:postcode":"78102",
    "sg:province":"TX",
    "sg:tags":[
        "establishment"
    ],
    "wof:name":"Texas Professional Institute",
    "wof:placetype":"venue"
},
  "geometry": {"coordinates":[-97.753821,28.418267],"type":"Point"}
}