{
  "type": "Feature",
  "properties": {
    "iso:country":"US",
    "sg:address":"1729 Lafoy Ln",
    "sg:city":"Longview",
    "sg:classifiers":[
        {
            "category":"Building & Trades",
            "subcategory":"Pest Control",
            "type":"Services"
        }
    ],
    "sg:phone":"+1 903 758 5508",
    "sg:postcode":"75604",
    "sg:province":"TX",
    "sg:tags":[
        "spraying"
    ],
    "wof:name":"Rid-X Termite & Pest Control",
    "wof:placetype":"venue"
},
  "geometry": {"coordinates":[-94.77298,32.511077],"type":"Point"}
}