{
  "type": "Feature",
  "properties": {
    "iso:country":"US",
    "sg:address":"3695 Stagg Dr",
    "sg:city":"Beaumont",
    "sg:classifiers":[
        {
            "category":"Manufacturing",
            "subcategory":"Signs",
            "type":"Manufacturing & Wholesale Goods"
        }
    ],
    "sg:phone":"+1 409 833 3278",
    "sg:postcode":"77701",
    "sg:province":"TX",
    "sg:tags":[
        "specialty",
        "merchandise",
        "mfg"
    ],
    "wof:name":"Signs First",
    "wof:placetype":"venue"
},
  "geometry": {"coordinates":[-94.13297300000001,30.069967],"type":"Point"}
}