{
  "type": "Feature",
  "properties": {
    "iso:country":"US",
    "sg:address":"128 W Vaughan St",
    "sg:city":"Bertram",
    "sg:classifiers":[
        {
            "category":"Government",
            "subcategory":"Fire Station",
            "type":"Public Place"
        }
    ],
    "sg:phone":"+1 512 355 3431",
    "sg:postcode":"78605",
    "sg:province":"TX",
    "sg:tags":[
        "department"
    ],
    "wof:name":"Bertram Fire Department",
    "wof:placetype":"venue"
},
  "geometry": {"coordinates":[-98.056102,30.743333],"type":"Point"}
}