{
  "type": "Feature",
  "properties": {
    "iso:country":"US",
    "sg:address":"3212 Padre Blvd",
    "sg:city":"S Padre Island",
    "sg:classifiers":[
        {
            "category":"Restaurant",
            "type":"Food & Drink"
        }
    ],
    "sg:phone":"+1 956 761 8999",
    "sg:postcode":"78597",
    "sg:province":"TX",
    "wof:name":"Tom & Jerry's Inc",
    "wof:placetype":"venue"
},
  "geometry": {"coordinates":[-97.16866400000001,26.107383],"type":"Point"}
}