{
  "type": "Feature",
  "properties": {
    "iso:country":"US",
    "sg:address":"905 9th St",
    "sg:city":"Wichita Falls",
    "sg:classifiers":[
        {
            "category":"Mining & Drilling",
            "type":"Manufacturing & Wholesale Goods"
        }
    ],
    "sg:phone":"+1 940 767 3301",
    "sg:postcode":"76301",
    "sg:province":"TX",
    "sg:tags":[
        "exploration"
    ],
    "wof:name":"Murphy Robt D",
    "wof:placetype":"venue"
},
  "geometry": {"coordinates":[-98.493424,33.909626],"type":"Point"}
}