{
  "type": "Feature",
  "properties": {
    "iso:country":"US",
    "sg:address":"7721 N Loop Dr",
    "sg:city":"El Paso",
    "sg:classifiers":[
        {
            "category":"Organizations",
            "subcategory":"Religious Organization",
            "type":"Services"
        }
    ],
    "sg:phone":"+1 915 591 3304",
    "sg:postcode":"79915",
    "sg:province":"TX",
    "sg:tags":[
        "church"
    ],
    "wof:name":"LA Verdad Community Church",
    "wof:placetype":"venue"
},
  "geometry": {"coordinates":[-106.361148,31.737696],"type":"Point"}
}