{
  "type": "Feature",
  "properties": {
    "iso:country":"US",
    "sg:address":"10621 Goodnight Ln",
    "sg:city":"Dallas",
    "sg:classifiers":[
        {
            "category":"Autos & Motor Vehicles",
            "subcategory":"Automobile Sales",
            "type":"Retail Goods"
        }
    ],
    "sg:phone":"+1 972 506 9171",
    "sg:postcode":"75220",
    "sg:province":"TX",
    "sg:tags":[
        "dealers-used",
        "car",
        "used",
        "cars-wholesale",
        "new"
    ],
    "wof:name":"Leslie Auto Sales",
    "wof:placetype":"venue"
},
  "geometry": {"coordinates":[-96.902383,32.869539],"type":"Point"}
}