{
  "type": "Feature",
  "properties": {
    "iso:country":"US",
    "sg:address":"13719 Sablegarden Ln",
    "sg:city":"Houston",
    "sg:classifiers":[
        {
            "category":"Food & Beverages",
            "subcategory":"Bakery",
            "type":"Retail Goods"
        }
    ],
    "sg:phone":"+1 281 587 0458",
    "sg:postcode":"77014",
    "sg:province":"TX",
    "wof:name":"Pacos Bakery",
    "wof:placetype":"venue"
},
  "geometry": {"coordinates":[-95.48378200000001,29.976621],"type":"Point"}
}