{
  "type": "Feature",
  "properties": {
    "iso:country":"US",
    "sg:address":"15000 Hog Eye Rd",
    "sg:city":"Manor",
    "sg:classifiers":[
        {
            "category":"Retail",
            "subcategory":"Funeral Services",
            "type":"Services"
        }
    ],
    "sg:phone":"+1 512 251 4556",
    "sg:postcode":"78653",
    "sg:province":"TX",
    "sg:tags":[
        "director"
    ],
    "wof:name":"Barry Franklin",
    "wof:placetype":"venue"
},
  "geometry": {"coordinates":[-97.582487,30.288207],"type":"Point"}
}