{
  "type": "Feature",
  "properties": {
    "iso:country":"US",
    "sg:address":"2425 McIver Ln",
    "sg:city":"Carrollton",
    "sg:classifiers":[
        {
            "category":"Wholesale",
            "subcategory":"Electrical",
            "type":"Manufacturing & Wholesale Goods"
        }
    ],
    "sg:phone":"+1 972 247 7996",
    "sg:postcode":"75006",
    "sg:province":"TX",
    "sg:tags":[
        "lighting",
        "fixture"
    ],
    "wof:name":"Elong International",
    "wof:placetype":"venue"
},
  "geometry": {"coordinates":[-96.92867,32.919218],"type":"Point"}
}