{
  "type": "Feature",
  "properties": {
    "iso:country":"US",
    "sg:address":"1600 Financial Plz",
    "sg:city":"Huntsville",
    "sg:classifiers":[
        {
            "category":"Shopping",
            "subcategory":"Clothing, Apparel, & Fashions",
            "type":"Retail Goods"
        }
    ],
    "sg:phone":"+1 936 291 9101",
    "sg:postcode":"77340",
    "sg:province":"TX",
    "wof:name":"Cato Fashions",
    "wof:placetype":"venue"
},
  "geometry": {"coordinates":[-95.57490799999999,30.716697],"type":"Point"}
}