{
  "type": "Feature",
  "properties": {
    "iso:country":"US",
    "sg:address":"1251 W Campbell Rd",
    "sg:city":"Richardson",
    "sg:classifiers":[
        {
            "category":"Restaurant",
            "type":"Food & Drink"
        }
    ],
    "sg:menulink":"http://www.allmenus.com/tx/northeast/237924-sonny-bryans-smokehouse/menu/",
    "sg:phone":"+1 972 664 9494",
    "sg:postcode":"75080",
    "sg:province":"TX",
    "sg:tags":[
        "barbecue",
        "american",
        "steakhouse"
    ],
    "wof:name":"Sonny Bryan's Smokehouse",
    "wof:placetype":"venue"
},
  "geometry": {"coordinates":[-96.762204,32.97814],"type":"Point"}
}