{
  "type": "Feature",
  "properties": {
    "iso:country":"US",
    "sg:address":"2407 Bluebonnet Dr",
    "sg:city":"Killeen",
    "sg:classifiers":[
        {
            "category":"Social Services",
            "subcategory":"Child Care",
            "type":"Services"
        }
    ],
    "sg:phone":"+1 254 634 1694",
    "sg:postcode":"76549",
    "sg:province":"TX",
    "sg:tags":[
        "day"
    ],
    "wof:name":"Shirleys Day Care",
    "wof:placetype":"venue"
},
  "geometry": {"coordinates":[-97.76795300000001,31.104721],"type":"Point"}
}