{
  "type": "Feature",
  "properties": {
    "iso:country":"US",
    "sg:address":"1207 Woodsey Ct",
    "sg:city":"Southlake",
    "sg:classifiers":[
        {
            "category":"Building & Trades",
            "subcategory":"Construction",
            "type":"Services"
        }
    ],
    "sg:phone":"+1 817 430 1776",
    "sg:postcode":"76092",
    "sg:province":"TX",
    "sg:tags":[
        "roofing",
        "contractor"
    ],
    "wof:name":"Anderson Industrial Roofing",
    "wof:placetype":"venue"
},
  "geometry": {"coordinates":[-97.12239700000001,32.922479],"type":"Point"}
}