{
  "type": "Feature",
  "properties": {
    "iso:country":"US",
    "sg:address":"401 US Hwy 77",
    "sg:city":"Waxahachie",
    "sg:classifiers":[
        {
            "category":"Restaurant",
            "type":"Food & Drink"
        }
    ],
    "sg:phone":"+1 972 935 9715",
    "sg:postcode":"75165",
    "sg:province":"TX",
    "wof:name":"El Rancho Mexican Restaurant",
    "wof:placetype":"venue"
},
  "geometry": {"coordinates":[-96.842878,32.405774],"type":"Point"}
}