{
  "type": "Feature",
  "properties": {
    "iso:country":"US",
    "sg:address":"241 S Texas Blvd",
    "sg:city":"Weslaco",
    "sg:classifiers":[
        {
            "category":"Restaurant",
            "type":"Food & Drink"
        }
    ],
    "sg:phone":"+1 956 447 4543",
    "sg:postcode":"78596",
    "sg:province":"TX",
    "wof:name":"Sevilla Restaurant",
    "wof:placetype":"venue"
},
  "geometry": {"coordinates":[-97.990675,26.160492],"type":"Point"}
}