{
  "type": "Feature",
  "properties": {
    "iso:country":"US",
    "sg:address":"3330 Sam Houston Pkwy",
    "sg:city":"Houston",
    "sg:classifiers":[
        {
            "category":"Manufacturing",
            "subcategory":"Tools & Machinery",
            "type":"Manufacturing & Wholesale Goods"
        }
    ],
    "sg:phone":"+1 713 943 0750",
    "sg:postcode":"77047",
    "sg:province":"TX",
    "sg:tags":[
        "company",
        "holding"
    ],
    "wof:name":"Plank Companies Inc",
    "wof:placetype":"venue"
},
  "geometry": {"coordinates":[-95.37211000000001,29.597603],"type":"Point"}
}