{
  "type": "Feature",
  "properties": {
    "iso:country":"US",
    "sg:address":"5007 Ave R",
    "sg:city":"Galveston",
    "sg:classifiers":[
        {
            "category":"Freight",
            "type":"Transportation"
        }
    ],
    "sg:phone":"+1 409 740 8943",
    "sg:postcode":"77551",
    "sg:province":"TX",
    "wof:name":"Shoreline Moving Service Inc",
    "wof:placetype":"venue"
},
  "geometry": {"coordinates":[-94.820093,29.280204],"type":"Point"}
}