{
  "type": "Feature",
  "properties": {
    "iso:country":"US",
    "sg:address":"1233 Jacksonville Square Dr",
    "sg:city":"Jacksonville",
    "sg:classifiers":[
        {
            "category":"Restaurant",
            "type":"Food & Drink"
        }
    ],
    "sg:menulink":"http://www.allmenus.com/tx/jacksonville/210038-happiness-chinese-buffet-restaurant/menu/",
    "sg:phone":"+1 904 781 6793",
    "sg:postcode":"75766",
    "sg:province":"TX",
    "sg:tags":[
        "asian",
        "chinese"
    ],
    "wof:name":"Happiness Chinese Buffet Restaurant",
    "wof:placetype":"venue"
},
  "geometry": {"coordinates":[-95.255554,31.945223],"type":"Point"}
}