{
  "type": "Feature",
  "properties": {
    "iso:country":"US",
    "sg:address":"11675 Betty Ln",
    "sg:city":"Kaufman",
    "sg:classifiers":[
        {
            "category":"Shopping",
            "subcategory":"Florist",
            "type":"Retail Goods"
        }
    ],
    "sg:phone":"+1 972 962 4247",
    "sg:postcode":"75142",
    "sg:province":"TX",
    "wof:name":"Emotions In Bloom",
    "wof:placetype":"venue"
},
  "geometry": {"coordinates":[-96.14332400000001,32.58564],"type":"Point"}
}