{
  "type": "Feature",
  "properties": {
    "iso:country":"US",
    "sg:address":"6930 N Mesa St",
    "sg:city":"El Paso",
    "sg:classifiers":[
        {
            "category":"Restaurant",
            "type":"Food & Drink"
        }
    ],
    "sg:phone":"+1 915 833 4100",
    "sg:postcode":"79912",
    "sg:province":"TX",
    "sg:tags":[
        "pizza"
    ],
    "sg:website":"www.papajohns.com",
    "wof:name":"Papa John's Pizza",
    "wof:placetype":"venue"
},
  "geometry": {"coordinates":[-106.549004,31.8354],"type":"Point"}
}