{
  "type": "Feature",
  "properties": {
    "iso:country":"US",
    "sg:address":"200 Main St",
    "sg:city":"Utopia",
    "sg:classifiers":[
        {
            "category":"Real Estate",
            "subcategory":"Real Estate Agent",
            "type":"Services"
        }
    ],
    "sg:phone":"+1 830 966 3434",
    "sg:postcode":"78852",
    "sg:province":"TX",
    "wof:name":"Thompson Real Estate & Ins",
    "wof:placetype":"venue"
},
  "geometry": {"coordinates":[-100.50509099999999,28.70827],"type":"Point"}
}