{
  "type": "Feature",
  "properties": {
    "iso:country":"US",
    "sg:address":"808 Old Genoa Red Bluff Rd",
    "sg:city":"Houston",
    "sg:classifiers":[
        {
            "category":"Building & Trades",
            "subcategory":"Construction",
            "type":"Services"
        }
    ],
    "sg:phone":"+1 281 484 1366",
    "sg:postcode":"77034",
    "sg:province":"TX",
    "sg:tags":[
        "contractor"
    ],
    "wof:name":"J Wallace Construction",
    "wof:placetype":"venue"
},
  "geometry": {"coordinates":[-95.185053,29.625295],"type":"Point"}
}