{
  "type": "Feature",
  "properties": {
    "iso:country":"US",
    "sg:address":"8302 Broadway St",
    "sg:city":"Pearland",
    "sg:classifiers":[
        {
            "category":"Restaurant",
            "type":"Food & Drink"
        }
    ],
    "sg:phone":"+1 281 412 6533",
    "sg:postcode":"77581",
    "sg:province":"TX",
    "wof:name":"Mc Donald's",
    "wof:placetype":"venue"
},
  "geometry": {"coordinates":[-95.347763,29.559079],"type":"Point"}
}