{
  "type": "Feature",
  "properties": {
    "iso:country":"US",
    "sg:address":"1491 N Kealy St",
    "sg:city":"Lewisville",
    "sg:classifiers":[
        {
            "category":"Professional",
            "subcategory":"Business Services",
            "type":"Services"
        }
    ],
    "sg:phone":"+1 972 221 7171",
    "sg:postcode":"75057",
    "sg:province":"TX",
    "wof:name":"P N A Inc",
    "wof:placetype":"venue"
},
  "geometry": {"coordinates":[-96.992504,33.061999],"type":"Point"}
}