{
  "type": "Feature",
  "properties": {
    "iso:country":"US",
    "sg:address":"4040 Abrams Rd",
    "sg:city":"Dallas",
    "sg:classifiers":[
        {
            "category":"Restaurant",
            "type":"Food & Drink"
        }
    ],
    "sg:menulink":"http://www.allmenus.com/tx/northeast/95152-ihop/menu/",
    "sg:phone":"+1 214 824 5300",
    "sg:postcode":"75214",
    "sg:province":"TX",
    "sg:tags":[
        "sandwich",
        "salad",
        "burger",
        "soup",
        "american",
        "steakhouse",
        "wrap"
    ],
    "wof:name":"IHOP",
    "wof:placetype":"venue"
},
  "geometry": {"coordinates":[-96.75293499999999,32.834862],"type":"Point"}
}