{
  "type": "Feature",
  "properties": {
    "iso:country":"US",
    "sg:address":"1812 Topaz Cove",
    "sg:city":"Whitehouse",
    "sg:classifiers":[
        {
            "category":"Manufacturing",
            "subcategory":"Metals",
            "type":"Manufacturing & Wholesale Goods"
        }
    ],
    "sg:phone":"+1 903 520 8733",
    "sg:postcode":"75791",
    "sg:province":"TX",
    "sg:tags":[
        "steel"
    ],
    "wof:name":"Dobbs Construction Inc",
    "wof:placetype":"venue"
},
  "geometry": {"coordinates":[-95.188817,32.222426],"type":"Point"}
}