{
  "type": "Feature",
  "properties": {
    "iso:country":"US",
    "sg:address":"2013 W Jonquil Ave",
    "sg:city":"Mcallen",
    "sg:classifiers":[
        {
            "category":"Organizations",
            "subcategory":"Religious Organization",
            "type":"Services"
        }
    ],
    "sg:phone":"+1 956 683 1362",
    "sg:postcode":"78501",
    "sg:province":"TX",
    "wof:name":"Mcallen Rivers Of Life Worship Center",
    "wof:placetype":"venue"
},
  "geometry": {"coordinates":[-98.23603199999999,26.237825],"type":"Point"}
}