{
  "type": "Feature",
  "properties": {
    "iso:country":"US",
    "sg:address":"2305 Laurel St",
    "sg:city":"Beaumont",
    "sg:classifiers":[
        {
            "category":"Health Services",
            "subcategory":"Doctor",
            "type":"Services"
        }
    ],
    "sg:phone":"+1 409 833 0920",
    "sg:postcode":"77702",
    "sg:province":"TX",
    "sg:tags":[
        "dentist"
    ],
    "wof:name":"Thomas Gautreaux DDS",
    "wof:placetype":"venue"
},
  "geometry": {"coordinates":[-94.121087,30.082829],"type":"Point"}
}