{
  "type": "Feature",
  "properties": {
    "iso:country":"US",
    "sg:address":"1501 Texas Dr Ste 200",
    "sg:city":"Weatherford",
    "sg:classifiers":[
        {
            "category":"Government",
            "subcategory":"Office",
            "type":"Public Place"
        }
    ],
    "sg:phone":"+1 817 599 3084",
    "sg:postcode":"76086",
    "sg:province":"TX",
    "sg:tags":[
        "government-united",
        "state"
    ],
    "wof:name":"Child Protective Services",
    "wof:placetype":"venue"
},
  "geometry": {"coordinates":[-97.783573,32.740155],"type":"Point"}
}