{
  "type": "Feature",
  "properties": {
    "iso:country":"US",
    "sg:address":"5909 West Loop S",
    "sg:city":"Bellaire",
    "sg:classifiers":[
        {
            "category":"Health Services",
            "subcategory":"Clinic",
            "type":"Services"
        }
    ],
    "sg:phone":"+1 713 668 4066",
    "sg:postcode":"77401",
    "sg:province":"TX",
    "sg:tags":[
        "counseling",
        "mental"
    ],
    "wof:name":"Center For Cognitive Therapy",
    "wof:placetype":"venue"
},
  "geometry": {"coordinates":[-95.45970199999999,29.7181],"type":"Point"}
}