{
  "type": "Feature",
  "properties": {
    "iso:country":"US",
    "sg:address":"3136 Routh St",
    "sg:city":"Dallas",
    "sg:classifiers":[
        {
            "category":"Wholesale",
            "subcategory":"Apparel",
            "type":"Manufacturing & Wholesale Goods"
        }
    ],
    "sg:phone":"+1 214 630 4010",
    "sg:postcode":"75201",
    "sg:province":"TX",
    "sg:tags":[
        "textile"
    ],
    "wof:name":"Solomon Marshall Textiles",
    "wof:placetype":"venue"
},
  "geometry": {"coordinates":[-96.807334,32.801325],"type":"Point"}
}