{
  "type": "Feature",
  "properties": {
    "iso:country":"US",
    "sg:address":"1809 Baker Dr",
    "sg:city":"Mesquite",
    "sg:classifiers":[
        {
            "category":"Real Estate",
            "subcategory":"Real Estate Operator",
            "type":"Services"
        }
    ],
    "sg:phone":"+1 972 279 1728",
    "sg:postcode":"75150",
    "sg:province":"TX",
    "sg:tags":[
        "apartment"
    ],
    "wof:name":"Baker Square Apts",
    "wof:placetype":"venue"
},
  "geometry": {"coordinates":[-96.63835400000001,32.792846],"type":"Point"}
}