{
  "type": "Feature",
  "properties": {
    "iso:country":"US",
    "sg:address":"2110 Woodstream Dr",
    "sg:city":"Humble",
    "sg:classifiers":[
        {
            "category":"Professional",
            "subcategory":"Management & Consulting",
            "type":"Services"
        }
    ],
    "sg:phone":"+1 281 358 0647",
    "sg:postcode":"77339",
    "sg:province":"TX",
    "sg:tags":[
        "business"
    ],
    "wof:name":"Apperson Consulting LLC",
    "wof:placetype":"venue"
},
  "geometry": {"coordinates":[-95.22335099999999,30.034181],"type":"Point"}
}