{
  "type": "Feature",
  "properties": {
    "iso:country":"US",
    "sg:address":"1250 W McGregor Dr",
    "sg:city":"Mc Gregor",
    "sg:classifiers":[
        {
            "category":"Food & Beverages",
            "subcategory":"Groceries & Convenience Stores",
            "type":"Retail Goods"
        }
    ],
    "sg:phone":"+1 254 840 6040",
    "sg:postcode":"76657",
    "sg:province":"TX",
    "wof:name":"Brookshire Brothers 68",
    "wof:placetype":"venue"
},
  "geometry": {"coordinates":[-97.418975,31.440764],"type":"Point"}
}