{
  "type": "Feature",
  "properties": {
    "iso:country":"US",
    "sg:address":"1503 23rd St",
    "sg:city":"Galveston",
    "sg:classifiers":[
        {
            "category":"Organizations",
            "subcategory":"Community Association",
            "type":"Services"
        }
    ],
    "sg:phone":"+1 409 763 2505",
    "sg:postcode":"77550",
    "sg:province":"TX",
    "wof:name":"American Legion Post 20",
    "wof:placetype":"venue"
},
  "geometry": {"coordinates":[-94.79023599999999,29.294753],"type":"Point"}
}