{
  "type": "Feature",
  "properties": {
    "iso:country":"US",
    "sg:address":"11211 Katy Fwy",
    "sg:city":"Houston",
    "sg:classifiers":[
        {
            "category":"Insurance",
            "subcategory":"Insurance Agent",
            "type":"Services"
        }
    ],
    "sg:phone":"+1 713 468 1191",
    "sg:postcode":"77079",
    "sg:province":"TX",
    "wof:name":"Employee Benefit Associates",
    "wof:placetype":"venue"
},
  "geometry": {"coordinates":[-95.57907400000001,29.784021],"type":"Point"}
}