{
  "type": "Feature",
  "properties": {
    "iso:country":"US",
    "sg:address":"9742 Rustic Gate Rd",
    "sg:city":"La Porte",
    "sg:classifiers":[
        {
            "category":"Insurance",
            "subcategory":"Insurance Agent",
            "type":"Services"
        }
    ],
    "sg:phone":"+1 281 471 7572",
    "sg:postcode":"77571",
    "sg:province":"TX",
    "wof:name":"John Billings Insurance Agency",
    "wof:placetype":"venue"
},
  "geometry": {"coordinates":[-95.084952,29.65609],"type":"Point"}
}