{
  "type": "Feature",
  "properties": {
    "iso:country":"US",
    "sg:address":"2434 Junction Hwy",
    "sg:city":"Kerrville",
    "sg:classifiers":[
        {
            "category":"Manufacturing",
            "subcategory":"Food",
            "type":"Manufacturing & Wholesale Goods"
        }
    ],
    "sg:phone":"+1 817 293 6230",
    "sg:postcode":"78028",
    "sg:province":"TX",
    "sg:tags":[
        "product",
        "mfg"
    ],
    "wof:name":"Mrs Bairds Bakeries",
    "wof:placetype":"venue"
},
  "geometry": {"coordinates":[-99.196523,30.07384],"type":"Point"}
}