{
  "type": "Feature",
  "properties": {
    "iso:country":"US",
    "sg:address":"709 de Soto Dr",
    "sg:city":"Desoto",
    "sg:classifiers":[
        {
            "category":"Building & Trades",
            "subcategory":"Construction",
            "type":"Services"
        }
    ],
    "sg:phone":"+1 972 230 6617",
    "sg:postcode":"75115",
    "sg:province":"TX",
    "sg:tags":[
        "concrete",
        "contractor"
    ],
    "wof:name":"National Concrete Place",
    "wof:placetype":"venue"
},
  "geometry": {"coordinates":[-96.863669,32.576017],"type":"Point"}
}