{
  "type": "Feature",
  "properties": {
    "iso:country":"US",
    "sg:address":"5205 Manhassett Dr",
    "sg:city":"Arlington",
    "sg:classifiers":[
        {
            "category":"Travel",
            "subcategory":"Travel Agent",
            "type":"Entertainment"
        }
    ],
    "sg:phone":"+1 817 465 8609",
    "sg:postcode":"76018",
    "sg:province":"TX",
    "sg:tags":[
        "operator",
        "tour"
    ],
    "wof:name":"Tour Bus Studios",
    "wof:placetype":"venue"
},
  "geometry": {"coordinates":[-97.06768,32.66175],"type":"Point"}
}