{
  "type": "Feature",
  "properties": {
    "iso:country":"US",
    "sg:address":"11624 W FM 471",
    "sg:city":"San Antonio",
    "sg:classifiers":[
        {
            "category":"Social Services",
            "type":"Services"
        }
    ],
    "sg:phone":"+1 210 688 7150",
    "sg:postcode":"78253",
    "sg:province":"TX",
    "sg:tags":[
        "counselor",
        "marriage",
        "family"
    ],
    "wof:name":"Marian Cordi Sisters Family",
    "wof:placetype":"venue"
},
  "geometry": {"coordinates":[-98.725793,29.50211],"type":"Point"}
}