{
  "type": "Feature",
  "properties": {
    "iso:country":"US",
    "sg:address":"2705 Canton St",
    "sg:city":"Dallas",
    "sg:classifiers":[
        {
            "category":"Professional",
            "subcategory":"Computer Services",
            "type":"Services"
        }
    ],
    "sg:phone":"+1 214 741 4529",
    "sg:postcode":"75226",
    "sg:province":"TX",
    "sg:tags":[
        "datum"
    ],
    "wof:name":"Expertsourcenet",
    "wof:placetype":"venue"
},
  "geometry": {"coordinates":[-96.78307700000001,32.782321],"type":"Point"}
}