{
  "type": "Feature",
  "properties": {
    "iso:country":"US",
    "sg:address":"107 Magnolia Ln",
    "sg:city":"Conroe",
    "sg:classifiers":[
        {
            "category":"Banks & Credit Unions",
            "subcategory":"Bank",
            "type":"Services"
        },
        {
            "category":"Shopping",
            "subcategory":"Used Merchandise",
            "type":"Retail Goods"
        }
    ],
    "sg:phone":"+1 936 441 6507",
    "sg:postcode":"77304",
    "sg:province":"TX",
    "sg:tags":[
        "resale",
        "shop",
        "second",
        "hand"
    ],
    "wof:name":"Clutter & Stuff",
    "wof:placetype":"venue"
},
  "geometry": {"coordinates":[-95.500823,30.305311],"type":"Point"}
}