{
  "type": "Feature",
  "properties": {
    "iso:country":"US",
    "sg:address":"1828 State Loop 197",
    "sg:city":"Texas City",
    "sg:classifiers":[
        {
            "category":"Personal",
            "subcategory":"Beauty Salon",
            "type":"Services"
        }
    ],
    "sg:phone":"+1 409 943 4488",
    "sg:postcode":"77590",
    "sg:province":"TX",
    "wof:name":"Shears Hair Salon",
    "wof:placetype":"venue"
},
  "geometry": {"coordinates":[-94.902624,29.402264],"type":"Point"}
}