{
  "type": "Feature",
  "properties": {
    "iso:country":"US",
    "sg:address":"415 Gail Cir",
    "sg:city":"Marshall",
    "sg:classifiers":[
        {
            "category":"Health Services",
            "subcategory":"Doctor",
            "type":"Services"
        }
    ],
    "sg:phone":"+1 903 938 4394",
    "sg:postcode":"75670",
    "sg:province":"TX",
    "sg:tags":[
        "clinic"
    ],
    "wof:name":"Marshall Medical Ctr Inc",
    "wof:placetype":"venue"
},
  "geometry": {"coordinates":[-94.363131,32.528706],"type":"Point"}
}