{
  "type": "Feature",
  "properties": {
    "iso:country":"US",
    "sg:address":"2004 Galaxy Dr",
    "sg:city":"Killeen",
    "sg:classifiers":[
        {
            "category":"Building & Trades",
            "subcategory":"Construction",
            "type":"Services"
        }
    ],
    "sg:phone":"+1 254 680 4463",
    "sg:postcode":"76543",
    "sg:province":"TX",
    "sg:tags":[
        "contractor"
    ],
    "wof:name":"Steel Tech",
    "wof:placetype":"venue"
},
  "geometry": {"coordinates":[-97.674757,31.121621],"type":"Point"}
}