{
  "type": "Feature",
  "properties": {
    "iso:country":"US",
    "sg:address":"5955 Armour Dr",
    "sg:city":"Houston",
    "sg:classifiers":[
        {
            "category":"Retail",
            "subcategory":"Repair Shop",
            "type":"Services"
        }
    ],
    "sg:phone":"+1 713 674 9571",
    "sg:postcode":"77020",
    "sg:province":"TX",
    "sg:tags":[
        "equipment",
        "hydraulic"
    ],
    "sg:website":"http://www.joneshydraulic.com",
    "wof:name":"Jones Hydraulic Service",
    "wof:placetype":"venue"
},
  "geometry": {"coordinates":[-95.305272,29.757748],"type":"Point"}
}