{
  "type": "Feature",
  "properties": {
    "iso:country":"US",
    "sg:address":"50 Briar Hollow Ln",
    "sg:city":"Houston",
    "sg:classifiers":[
        {
            "category":"Professional",
            "subcategory":"Lawyer & Legal Services",
            "type":"Services"
        }
    ],
    "sg:phone":"+1 713 426 4242",
    "sg:postcode":"77027",
    "sg:province":"TX",
    "wof:name":"John Victor Mastriani P C",
    "wof:placetype":"venue"
},
  "geometry": {"coordinates":[-95.45195,29.752445],"type":"Point"}
}