{
  "type": "Feature",
  "properties": {
    "iso:country":"US",
    "sg:address":"7810 Doniphan Dr",
    "sg:city":"Vinton",
    "sg:classifiers":[
        {
            "category":"Wholesale",
            "subcategory":"Farm Supplies",
            "type":"Manufacturing & Wholesale Goods"
        }
    ],
    "sg:phone":"+1 915 544 8070",
    "sg:postcode":"79821",
    "sg:province":"NM",
    "sg:tags":[
        "bulb",
        "seed"
    ],
    "wof:name":"Del Norte Seed Co",
    "wof:placetype":"venue"
},
  "geometry": {"coordinates":[-106.602946,31.951043],"type":"Point"}
}