{
  "type": "Feature",
  "properties": {
    "iso:country":"US",
    "sg:address":"6801 N I H 35",
    "sg:city":"Austin",
    "sg:classifiers":[
        {
            "category":"Restaurant",
            "type":"Food & Drink"
        }
    ],
    "sg:phone":"+1 512 323 6663",
    "sg:postcode":"78752",
    "sg:province":"TX",
    "sg:tags":[
        "sushi",
        "bar",
        "japanese"
    ],
    "sg:website":"www.sushijaponaustin.com",
    "wof:name":"Sushi Japon",
    "wof:placetype":"venue"
},
  "geometry": {"coordinates":[-97.705387,30.328504],"type":"Point"}
}