{
  "type": "Feature",
  "properties": {
    "iso:country":"US",
    "sg:address":"4100 Factory Hill St",
    "sg:city":"San Antonio",
    "sg:classifiers":[
        {
            "category":"Wholesale",
            "subcategory":"Machinery & Supplies",
            "type":"Manufacturing & Wholesale Goods"
        }
    ],
    "sg:phone":"+1 210 337 7426",
    "sg:postcode":"78219",
    "sg:province":"TX",
    "sg:tags":[
        "equipment",
        "contractor"
    ],
    "wof:name":"Equipment Max Inc",
    "wof:placetype":"venue"
},
  "geometry": {"coordinates":[-98.40486199999999,29.447297],"type":"Point"}
}