{
  "type": "Feature",
  "properties": {
    "iso:country":"US",
    "sg:address":"118 N Walden Elms Cir",
    "sg:city":"Spring",
    "sg:classifiers":[
        {
            "category":"Building & Trades",
            "subcategory":"Equipment Rental",
            "type":"Services"
        }
    ],
    "sg:phone":"+1 281 298 7170",
    "sg:postcode":"77382",
    "sg:province":"TX",
    "wof:name":"Deltide Fishing & Rental Tools",
    "wof:placetype":"venue"
},
  "geometry": {"coordinates":[-95.535903,30.213824],"type":"Point"}
}