{
  "type": "Feature",
  "properties": {
    "iso:country":"US",
    "sg:address":"4912 N I- 35",
    "sg:city":"Austin",
    "sg:classifiers":[
        {
            "category":"Arts & Performance",
            "subcategory":"Theater",
            "type":"Entertainment"
        }
    ],
    "sg:phone":"+1 512 453 1920",
    "sg:postcode":"78751",
    "sg:province":"TX",
    "sg:tags":[
        "entertainer"
    ],
    "wof:name":"Foxxies",
    "wof:placetype":"venue"
},
  "geometry": {"coordinates":[-97.711499,30.309013],"type":"Point"}
}