{
  "type": "Feature",
  "properties": {
    "iso:country":"US",
    "sg:address":"129 Quail Run",
    "sg:city":"Nacogdoches",
    "sg:classifiers":[
        {
            "category":"Organizations",
            "subcategory":"Religious Organization",
            "type":"Services"
        }
    ],
    "sg:phone":"+1 936 568 9848",
    "sg:postcode":"75965",
    "sg:province":"TX",
    "wof:name":"Corinth Prmitive Baptst Church",
    "wof:placetype":"venue"
},
  "geometry": {"coordinates":[-94.61777600000001,31.719401],"type":"Point"}
}