{
  "type": "Feature",
  "properties": {
    "iso:country":"US",
    "sg:address":"900 E Fronton St",
    "sg:city":"Brownsville",
    "sg:classifiers":[
        {
            "category":"Shopping",
            "subcategory":"Used Merchandise",
            "type":"Retail Goods"
        }
    ],
    "sg:phone":"+1 956 550 8088",
    "sg:postcode":"78520",
    "sg:province":"TX",
    "wof:name":"Texbi International",
    "wof:placetype":"venue"
},
  "geometry": {"coordinates":[-97.50236099999999,25.899957],"type":"Point"}
}