{
  "type": "Feature",
  "properties": {
    "iso:country":"US",
    "sg:address":"709 W Abram St",
    "sg:city":"Arlington",
    "sg:classifiers":[
        {
            "category":"Travel",
            "subcategory":"Travel Agent",
            "type":"Entertainment"
        }
    ],
    "sg:phone":"+1 817 543 3700",
    "sg:postcode":"76013",
    "sg:province":"TX",
    "sg:tags":[
        "agency",
        "bureau"
    ],
    "sg:website":"www.dandipert.com",
    "wof:name":"Dan Dipert Tours",
    "wof:placetype":"venue"
},
  "geometry": {"coordinates":[-97.11605,32.735839],"type":"Point"}
}