{
  "type": "Feature",
  "properties": {
    "iso:country":"US",
    "sg:address":"112 S Dixon St",
    "sg:city":"Gainesville",
    "sg:classifiers":[
        {
            "category":"Restaurant",
            "type":"Food & Drink"
        },
        {
            "category":"Food & Beverages",
            "subcategory":"Groceries & Convenience Stores",
            "type":"Retail Goods"
        }
    ],
    "sg:phone":"+1 940 668 2477",
    "sg:postcode":"76240",
    "sg:province":"TX",
    "sg:tags":[
        "shop",
        "sandwich"
    ],
    "wof:name":"Carousel Sandwich Shop & Tea Room",
    "wof:placetype":"venue"
},
  "geometry": {"coordinates":[-97.145319,33.624194],"type":"Point"}
}