{
  "type": "Feature",
  "properties": {
    "iso:country":"US",
    "sg:address":"393 State Hwy 321",
    "sg:city":"Cleveland",
    "sg:classifiers":[
        {
            "category":"Organizations",
            "subcategory":"Community Association",
            "type":"Services"
        }
    ],
    "sg:phone":"+1 281 592 5543",
    "sg:postcode":"77327",
    "sg:province":"TX",
    "sg:tags":[
        "military"
    ],
    "wof:name":"American Legion",
    "wof:placetype":"venue"
},
  "geometry": {"coordinates":[-95.08529299999999,30.341325],"type":"Point"}
}