{
  "type": "Feature",
  "properties": {
    "iso:country":"US",
    "sg:address":"23111 Hampton Forest Ln",
    "sg:city":"Spring",
    "sg:phone":"+1 281 370 9309",
    "sg:postcode":"77389",
    "sg:province":"TX",
    "sg:tags":[
        "equipment",
        "commercial"
    ],
    "wof:name":"Chemmark Of East Texas",
    "wof:placetype":"venue"
},
  "geometry": {"coordinates":[-95.510445,30.100128],"type":"Point"}
}