{
  "type": "Feature",
  "properties": {
    "iso:country":"US",
    "sg:address":"3545 Pendleton St",
    "sg:city":"El Paso",
    "sg:classifiers":[
        {
            "category":"Building & Trades",
            "subcategory":"Construction",
            "type":"Services"
        }
    ],
    "sg:phone":"+1 915 855 3290",
    "sg:postcode":"79936",
    "sg:province":"TX",
    "sg:tags":[
        "plastering",
        "contractor"
    ],
    "wof:name":"De Larosa & Sons Plaster",
    "wof:placetype":"venue"
},
  "geometry": {"coordinates":[-106.298175,31.79647],"type":"Point"}
}