{
  "type": "Feature",
  "properties": {
    "iso:country":"US",
    "sg:address":"7000 Independence Pkwy",
    "sg:city":"Plano",
    "sg:classifiers":[
        {
            "category":"Building & Trades",
            "subcategory":"Landscaping Services",
            "type":"Services"
        }
    ],
    "sg:phone":"+1 972 491 6974",
    "sg:postcode":"75025",
    "sg:province":"TX",
    "wof:name":"A Plano Lawn Service",
    "wof:placetype":"venue"
},
  "geometry": {"coordinates":[-96.75014899999999,33.072961],"type":"Point"}
}