{
  "type": "Feature",
  "properties": {
    "iso:country":"US",
    "sg:address":"8300 Douglas Ave Ste 731",
    "sg:city":"Dallas",
    "sg:classifiers":[
        {
            "category":"Health Services",
            "subcategory":"Doctor",
            "type":"Services"
        }
    ],
    "sg:phone":"+1 214 739 8600",
    "sg:postcode":"75225",
    "sg:province":"TX",
    "sg:tags":[
        "physician",
        "pediatrics-emergency",
        "pediatrics",
        "surgeons",
        "medicine",
        "surgeon"
    ],
    "wof:name":"Behavorial & Developmental Ctr",
    "wof:placetype":"venue"
},
  "geometry": {"coordinates":[-96.808571,32.863571],"type":"Point"}
}