{
  "type": "Feature",
  "properties": {
    "iso:country":"US",
    "sg:address":"3177 Executive Dr",
    "sg:city":"San Angelo",
    "sg:classifiers":[
        {
            "category":"Education",
            "subcategory":"Vocational School",
            "type":"Public Place"
        }
    ],
    "sg:phone":"+1 325 942 6797",
    "sg:postcode":"76904",
    "sg:province":"TX",
    "sg:tags":[
        "secretarial"
    ],
    "sg:website":"www.acc-careers.com",
    "wof:name":"American Commercial Colleges",
    "wof:placetype":"venue"
},
  "geometry": {"coordinates":[-100.46357,31.423119],"type":"Point"}
}