{
  "type": "Feature",
  "properties": {
    "iso:country":"US",
    "sg:address":"7402 Tierwester St",
    "sg:city":"Houston",
    "sg:classifiers":[
        {
            "category":"Organizations",
            "subcategory":"Religious Organization",
            "type":"Services"
        }
    ],
    "sg:phone":"+1 713 748 6264",
    "sg:postcode":"77021",
    "sg:province":"TX",
    "wof:name":"New Bethel Church",
    "wof:placetype":"venue"
},
  "geometry": {"coordinates":[-95.371371,29.685872],"type":"Point"}
}