{
  "type": "Feature",
  "properties": {
    "iso:country":"US",
    "sg:address":"3746 Plumb St",
    "sg:city":"Houston",
    "sg:classifiers":[
        {
            "category":"Shopping",
            "subcategory":"Hobbies, Toys, & Games",
            "type":"Retail Goods"
        }
    ],
    "sg:phone":"+1 713 677 0595",
    "sg:postcode":"77005",
    "sg:province":"TX",
    "sg:tags":[
        "toy",
        "store"
    ],
    "wof:name":"Christopher Toy",
    "wof:placetype":"venue"
},
  "geometry": {"coordinates":[-95.43532999999999,29.718738],"type":"Point"}
}