{
  "type": "Feature",
  "properties": {
    "iso:country":"US",
    "sg:address":"8619 Wall St",
    "sg:city":"Austin",
    "sg:classifiers":[
        {
            "category":"Freight",
            "type":"Transportation"
        }
    ],
    "sg:phone":"+1 512 339 5050",
    "sg:postcode":"78754",
    "sg:province":"TX",
    "sg:tags":[
        "courier"
    ],
    "wof:name":"Velocity Express",
    "wof:placetype":"venue"
},
  "geometry": {"coordinates":[-97.66970999999999,30.34233],"type":"Point"}
}