{
  "type": "Feature",
  "properties": {
    "iso:country":"US",
    "sg:address":"3110 E Causeway Blvd",
    "sg:city":"Corpus Christi",
    "sg:classifiers":[
        {
            "category":"Organizations",
            "subcategory":"Religious Organization",
            "type":"Services"
        }
    ],
    "sg:phone":"+1 361 883 4507",
    "sg:postcode":"78402",
    "sg:province":"TX",
    "sg:tags":[
        "church"
    ],
    "wof:name":"Our Lady Star Of The Sea",
    "wof:placetype":"venue"
},
  "geometry": {"coordinates":[-97.392926,27.82048],"type":"Point"}
}