{
  "type": "Feature",
  "properties": {
    "iso:country":"US",
    "sg:address":"21641 E Knox Dr",
    "sg:city":"Porter",
    "sg:classifiers":[
        {
            "category":"Shopping",
            "type":"Retail Goods"
        }
    ],
    "sg:phone":"+1 281 354 7669",
    "sg:postcode":"77365",
    "sg:province":"TX",
    "sg:tags":[
        "merchandise"
    ],
    "wof:name":"Texas Snow LLC",
    "wof:placetype":"venue"
},
  "geometry": {"coordinates":[-95.23924700000001,30.078784],"type":"Point"}
}