{
  "type": "Feature",
  "properties": {
    "iso:country":"US",
    "sg:address":"3555 W Walnut St",
    "sg:city":"Garland",
    "sg:classifiers":[
        {
            "category":"Restaurant",
            "type":"Food & Drink"
        }
    ],
    "sg:postcode":"75042",
    "sg:province":"TX",
    "sg:tags":[
        "vietnamese"
    ],
    "wof:name":"Viet Tofu",
    "wof:placetype":"venue"
},
  "geometry": {"coordinates":[-96.68402500000001,32.917214],"type":"Point"}
}