{
  "type": "Feature",
  "properties": {
    "iso:country":"US",
    "sg:address":"1901 Rd To Six Flags E",
    "sg:city":"Arlington",
    "sg:classifiers":[
        {
            "category":"Arts & Performance",
            "subcategory":"Theater",
            "type":"Entertainment"
        }
    ],
    "sg:phone":"+1 817 459 3338",
    "sg:postcode":"76011",
    "sg:province":"TX",
    "sg:tags":[
        "television",
        "production",
        "vehicle"
    ],
    "wof:name":"Lone Star Mobile Television",
    "wof:placetype":"venue"
},
  "geometry": {"coordinates":[-97.078228,32.752429],"type":"Point"}
}