{
  "type": "Feature",
  "properties": {
    "iso:country":"US",
    "sg:address":"1922 Co Rd 150",
    "sg:city":"Gainesville",
    "sg:classifiers":[
        {
            "category":"Shopping",
            "subcategory":"Hobbies, Toys, & Games",
            "type":"Retail Goods"
        }
    ],
    "sg:phone":"+1 940 665 9493",
    "sg:postcode":"76240",
    "sg:province":"TX",
    "wof:name":"Babas",
    "wof:placetype":"venue"
},
  "geometry": {"coordinates":[-96.986637,33.626777],"type":"Point"}
}