{
  "type": "Feature",
  "properties": {
    "iso:country":"US",
    "sg:address":"9990 East Fwy",
    "sg:city":"Houston",
    "sg:classifiers":[
        {
            "category":"Freight",
            "type":"Transportation"
        }
    ],
    "sg:phone":"+1 713 676 2273",
    "sg:postcode":"77029",
    "sg:province":"TX",
    "sg:tags":[
        "warehouse"
    ],
    "sg:website":"www.palmerlogistics.com",
    "wof:name":"Hermann Warehouse Southwest",
    "wof:placetype":"venue"
},
  "geometry": {"coordinates":[-95.25582900000001,29.773778],"type":"Point"}
}