{
  "type": "Feature",
  "properties": {
    "iso:country":"US",
    "sg:address":"1101 S Sherman St",
    "sg:city":"Richardson",
    "sg:classifiers":[
        {
            "category":"Wholesale",
            "subcategory":"Construction Materials",
            "type":"Manufacturing & Wholesale Goods"
        }
    ],
    "sg:phone":"+1 972 690 5724",
    "sg:postcode":"75081",
    "sg:province":"TX",
    "sg:tags":[
        "tile",
        "ceramic",
        "mfg"
    ],
    "wof:name":"Daltile",
    "wof:placetype":"venue"
},
  "geometry": {"coordinates":[-96.74231899999999,32.93634],"type":"Point"}
}