{
  "type": "Feature",
  "properties": {
    "iso:country":"US",
    "sg:address":"207 Flint Dr",
    "sg:city":"Levelland",
    "sg:classifiers":[
        {
            "category":"Professional",
            "type":"Services"
        }
    ],
    "sg:phone":"+1 806 897 4835",
    "sg:postcode":"79336",
    "sg:province":"TX",
    "wof:name":"Black Diamond",
    "wof:placetype":"venue"
},
  "geometry": {"coordinates":[-102.353537,33.586448],"type":"Point"}
}