{
  "type": "Feature",
  "properties": {
    "iso:country":"US",
    "sg:address":"1501 N Britain Rd",
    "sg:city":"Irving",
    "sg:classifiers":[
        {
            "category":"Education",
            "subcategory":"School",
            "type":"Public Place"
        }
    ],
    "sg:phone":"+1 972 721 3400",
    "sg:postcode":"75061",
    "sg:province":"TX",
    "sg:website":"www.irvingisd.net",
    "wof:name":"IRVING INDEPENDENT SCHOOL DISTRICT ADMINISTRATIVE ANNEX",
    "wof:placetype":"venue"
},
  "geometry": {"coordinates":[-96.944247,32.829293],"type":"Point"}
}