{
  "type": "Feature",
  "properties": {
    "iso:country":"US",
    "sg:address":"1696 Spring Cypress Rd",
    "sg:city":"Spring",
    "sg:classifiers":[
        {
            "category":"Autos & Motor Vehicles",
            "subcategory":"Fuel & Gas Station",
            "type":"Retail Goods"
        },
        {
            "category":"Sports & Exercise",
            "subcategory":"Race Track",
            "type":"Entertainment"
        }
    ],
    "sg:phone":"+1 281 528 5660",
    "sg:postcode":"77388",
    "sg:province":"TX",
    "wof:name":"Raceway 6771",
    "wof:placetype":"venue"
},
  "geometry": {"coordinates":[-95.43987199999999,30.072977],"type":"Point"}
}