{
  "type": "Feature",
  "properties": {
    "iso:country":"US",
    "sg:address":"7993 Carnation Ave",
    "sg:city":"San Angelo",
    "sg:classifiers":[
        {
            "category":"Building & Trades",
            "subcategory":"Cleaning & Sanitation",
            "type":"Services"
        }
    ],
    "sg:phone":"+1 325 944 7606",
    "sg:postcode":"76901",
    "sg:province":"TX",
    "sg:tags":[
        "maintenance"
    ],
    "wof:name":"Valley Chimney Sweep",
    "wof:placetype":"venue"
},
  "geometry": {"coordinates":[-100.542242,31.55359],"type":"Point"}
}