{
  "type": "Feature",
  "properties": {
    "iso:country":"US",
    "sg:address":"2584 W Jefferson St",
    "sg:city":"Grand Prairie",
    "sg:classifiers":[
        {
            "category":"Food & Beverages",
            "subcategory":"Groceries & Convenience Stores",
            "type":"Retail Goods"
        }
    ],
    "sg:phone":"+1 972 660 3233",
    "sg:postcode":"75051",
    "sg:province":"TX",
    "wof:name":"Finaserve",
    "wof:placetype":"venue"
},
  "geometry": {"coordinates":[-97.045058,32.738056],"type":"Point"}
}