{
  "type": "Feature",
  "properties": {
    "iso:country":"US",
    "sg:address":"850 Schneider",
    "sg:city":"Cibolo",
    "sg:classifiers":[
        {
            "category":"Autos & Motor Vehicles",
            "subcategory":"Auto Supplies",
            "type":"Retail Goods"
        },
        {
            "category":"Retail",
            "subcategory":"Auto Repair",
            "type":"Services"
        }
    ],
    "sg:phone":"+1 210 566 4447",
    "sg:postcode":"78108",
    "sg:province":"TX",
    "sg:tags":[
        "transmission",
        "part",
        "transmissions-other"
    ],
    "wof:name":"Absolute Automotive",
    "wof:placetype":"venue"
},
  "geometry": {"coordinates":[-98.242512,29.562058],"type":"Point"}
}