{
  "type": "Feature",
  "properties": {
    "iso:country":"US",
    "sg:address":"5418 Ramirez Dr",
    "sg:city":"Laredo",
    "sg:classifiers":[
        {
            "category":"Social Services",
            "subcategory":"Child Care",
            "type":"Services"
        }
    ],
    "sg:phone":"+1 956 725 1790",
    "sg:postcode":"78043",
    "sg:province":"TX",
    "sg:tags":[
        "day"
    ],
    "wof:name":"Johnsons Daycare",
    "wof:placetype":"venue"
},
  "geometry": {"coordinates":[-99.442031,27.52404],"type":"Point"}
}