{
  "type": "Feature",
  "properties": {
    "iso:country":"US",
    "sg:address":"2300 Jasper St",
    "sg:city":"Wichita Falls",
    "sg:classifiers":[
        {
            "category":"Organizations",
            "subcategory":"Religious Organization",
            "type":"Services"
        }
    ],
    "sg:phone":"+1 940 767 2355",
    "sg:postcode":"76301",
    "sg:province":"TX",
    "wof:name":"Miracle Mission Church",
    "wof:placetype":"venue"
},
  "geometry": {"coordinates":[-98.48981499999999,33.891504],"type":"Point"}
}