{
  "type": "Feature",
  "properties": {
    "iso:country":"US",
    "sg:address":"107 Lakeview Cir",
    "sg:city":"Waxahachie",
    "sg:classifiers":[
        {
            "category":"Shopping",
            "subcategory":"Gifts & Souvenirs",
            "type":"Retail Goods"
        }
    ],
    "sg:phone":"+1 972 937 7040",
    "sg:postcode":"75165",
    "sg:province":"TX",
    "sg:tags":[
        "basket",
        "parcel"
    ],
    "wof:name":"A Taste Of Cajun",
    "wof:placetype":"venue"
},
  "geometry": {"coordinates":[-96.783686,32.466338],"type":"Point"}
}