{
  "type": "Feature",
  "properties": {
    "iso:country":"US",
    "sg:address":"698 Highway 71 W",
    "sg:city":"Bastrop",
    "sg:classifiers":[
        {
            "category":"Fast Food",
            "type":"Food & Drink"
        },
        {
            "category":"Restaurant",
            "type":"Food & Drink"
        }
    ],
    "sg:phone":"+1 512 332 0478",
    "sg:postcode":"78602",
    "sg:province":"TX",
    "sg:tags":[
        "mexican"
    ],
    "sg:website":"http://www.tacocabana.com/",
    "wof:name":"Taco Cabana",
    "wof:placetype":"venue"
},
  "geometry": {"coordinates":[-97.350143,30.110754],"type":"Point"}
}