{
  "type": "Feature",
  "properties": {
    "iso:country":"US",
    "sg:address":"818 S Central Expy",
    "sg:city":"Dallas",
    "sg:classifiers":[
        {
            "category":"Freight",
            "type":"Transportation"
        }
    ],
    "sg:phone":"+1 972 239 8185",
    "sg:postcode":"75201",
    "sg:province":"TX",
    "sg:tags":[
        "mover"
    ],
    "wof:name":"Delicate Moving Systems",
    "wof:placetype":"venue"
},
  "geometry": {"coordinates":[-96.788522,32.778689],"type":"Point"}
}