{
  "type": "Feature",
  "properties": {
    "iso:country":"US",
    "sg:address":"4207 James Casey St Ste 317",
    "sg:city":"Austin",
    "sg:classifiers":[
        {
            "category":"Health Services",
            "subcategory":"Optometrist",
            "type":"Services"
        }
    ],
    "sg:phone":"+1 512 398 7103",
    "sg:postcode":"78745",
    "sg:province":"TX",
    "wof:name":"McGlathery William T MD",
    "wof:placetype":"venue"
},
  "geometry": {"coordinates":[-97.77380599999999,30.225572],"type":"Point"}
}