{
  "type": "Feature",
  "properties": {
    "iso:country":"US",
    "sg:address":"1200 Binz St Ste 850",
    "sg:city":"Houston",
    "sg:classifiers":[
        {
            "category":"Health Services",
            "subcategory":"Doctor",
            "type":"Services"
        }
    ],
    "sg:phone":"+1 713 522 0680",
    "sg:postcode":"77004",
    "sg:province":"TX",
    "wof:name":"Serrano Juan H MD PA",
    "wof:placetype":"venue"
},
  "geometry": {"coordinates":[-95.387001,29.724199],"type":"Point"}
}