{
  "type": "Feature",
  "properties": {
    "iso:country":"US",
    "sg:address":"2130 Co Rd 137",
    "sg:city":"Round Rock",
    "sg:classifiers":[
        {
            "category":"Autos & Motor Vehicles",
            "subcategory":"Automobile Sales",
            "type":"Retail Goods"
        }
    ],
    "sg:phone":"+1 512 388 0909",
    "sg:postcode":"78611",
    "sg:province":"TX",
    "sg:tags":[
        "used"
    ],
    "wof:name":"Gibsons Auto Sales",
    "wof:placetype":"venue"
},
  "geometry": {"coordinates":[-98.353386,30.824301],"type":"Point"}
}