{
  "type": "Feature",
  "properties": {
    "iso:country":"US",
    "sg:address":"139 Edwards",
    "sg:city":"Merkel",
    "sg:classifiers":[
        {
            "category":"Personal",
            "subcategory":"Beauty Salon",
            "type":"Services"
        }
    ],
    "sg:phone":"+1 325 928 4054",
    "sg:postcode":"79536",
    "sg:province":"TX",
    "wof:name":"Kut-N-Kurl",
    "wof:placetype":"venue"
},
  "geometry": {"coordinates":[-100.011375,32.470934],"type":"Point"}
}