{
  "type": "Feature",
  "properties": {
    "iso:country":"US",
    "sg:address":"6414 San Pedro Ave",
    "sg:city":"San Antonio",
    "sg:classifiers":[
        {
            "category":"Freight",
            "type":"Transportation"
        }
    ],
    "sg:phone":"+1 210 342 7273",
    "sg:postcode":"78216",
    "sg:province":"TX",
    "sg:tags":[
        "commercial",
        "storage"
    ],
    "wof:name":"National Self Storage",
    "wof:placetype":"venue"
},
  "geometry": {"coordinates":[-98.49919199999999,29.495619],"type":"Point"}
}