{
  "type": "Feature",
  "properties": {
    "iso:country":"US",
    "sg:address":"101 Walnut Hill Dr",
    "sg:city":"Flint",
    "sg:classifiers":[
        {
            "category":"Manufacturing",
            "subcategory":"Buildings",
            "type":"Manufacturing & Wholesale Goods"
        },
        {
            "category":"Home & Garden",
            "subcategory":"Home Furnishings",
            "type":"Retail Goods"
        },
        {
            "category":"Building & Trades",
            "subcategory":"Construction",
            "type":"Services"
        },
        {
            "category":"Real Estate",
            "subcategory":"Architect",
            "type":"Services"
        }
    ],
    "sg:phone":"+1 903 530 6464",
    "sg:postcode":"75762",
    "sg:province":"TX",
    "sg:tags":[
        "planning",
        "builder",
        "designer",
        "design",
        "contractor"
    ],
    "sg:website":"http://www.pyramidhomes.com",
    "wof:name":"Pyramid Homes",
    "wof:placetype":"venue"
},
  "geometry": {"coordinates":[-95.320015,32.198196],"type":"Point"}
}