{
  "type": "Feature",
  "properties": {
    "iso:country":"US",
    "sg:address":"206 W Campbell Rd",
    "sg:city":"Richardson",
    "sg:classifiers":[
        {
            "category":"Shopping",
            "subcategory":"Mobile Phones",
            "type":"Retail Goods"
        }
    ],
    "sg:phone":"+1 972 669 1210",
    "sg:postcode":"75080",
    "sg:province":"TX",
    "sg:website":"www.radioshack.com",
    "wof:name":"RadioShack",
    "wof:placetype":"venue"
},
  "geometry": {"coordinates":[-96.71993399999999,32.975667],"type":"Point"}
}