{
  "type": "Feature",
  "properties": {
    "iso:country":"US",
    "sg:address":"4210 John Ben Shepperd Pkwy",
    "sg:city":"Odessa",
    "sg:classifiers":[
        {
            "category":"Personal",
            "subcategory":"Nail Salon",
            "type":"Services"
        }
    ],
    "sg:phone":"+1 432 362 1717",
    "sg:postcode":"79762",
    "sg:province":"TX",
    "wof:name":"U S Nails",
    "wof:placetype":"venue"
},
  "geometry": {"coordinates":[-102.33429,31.894321],"type":"Point"}
}