{
  "type": "Feature",
  "properties": {
    "iso:country":"US",
    "sg:address":"5904 Spring Stuebner Rd",
    "sg:city":"Spring",
    "sg:classifiers":[
        {
            "category":"Building & Trades",
            "subcategory":"Construction",
            "type":"Services"
        }
    ],
    "sg:phone":"+1 281 288 3266",
    "sg:postcode":"77389",
    "sg:province":"TX",
    "sg:tags":[
        "carpentry",
        "contractor"
    ],
    "wof:name":"Oswald Ron Cabinet Craft",
    "wof:placetype":"venue"
},
  "geometry": {"coordinates":[-95.50994900000001,30.084296],"type":"Point"}
}