{
  "type": "Feature",
  "properties": {
    "iso:country":"US",
    "sg:address":"4301 Fredericksburg Rd",
    "sg:city":"San Antonio",
    "sg:classifiers":[
        {
            "category":"Food & Beverages",
            "subcategory":"Groceries & Convenience Stores",
            "type":"Retail Goods"
        }
    ],
    "sg:phone":"+1 210 733 9294",
    "sg:postcode":"78201",
    "sg:province":"TX",
    "wof:name":"Right Choice",
    "wof:placetype":"venue"
},
  "geometry": {"coordinates":[-98.55009099999999,29.488698],"type":"Point"}
}