{
  "type": "Feature",
  "properties": {
    "iso:country":"US",
    "sg:address":"833 N Main St",
    "sg:city":"Schulenburg",
    "sg:classifiers":[
        {
            "category":"Retail",
            "subcategory":"Car Wash",
            "type":"Services"
        }
    ],
    "sg:phone":"+1 979 743 3342",
    "sg:postcode":"78956",
    "sg:province":"TX",
    "sg:tags":[
        "carwash"
    ],
    "wof:name":"B & B Kar Klean",
    "wof:placetype":"venue"
},
  "geometry": {"coordinates":[-96.910472,29.679806],"type":"Point"}
}