{
  "type": "Feature",
  "properties": {
    "iso:country":"US",
    "sg:address":"305 W Criddle St",
    "sg:city":"Waxahachie",
    "sg:classifiers":[
        {
            "category":"Building & Trades",
            "subcategory":"Construction",
            "type":"Services"
        }
    ],
    "sg:phone":"+1 214 546 1932",
    "sg:postcode":"75165",
    "sg:province":"TX",
    "sg:tags":[
        "home",
        "builder"
    ],
    "wof:name":"Starr Lite Custom Homes",
    "wof:placetype":"venue"
},
  "geometry": {"coordinates":[-96.844281,32.398284],"type":"Point"}
}