{
  "type": "Feature",
  "properties": {
    "iso:country":"US",
    "sg:address":"132 Princeton Ave",
    "sg:city":"San Antonio",
    "sg:classifiers":[
        {
            "category":"Retail",
            "subcategory":"Laundry & Dry Cleaning",
            "type":"Services"
        }
    ],
    "sg:phone":"+1 210 735 0680",
    "sg:postcode":"78201",
    "sg:province":"TX",
    "wof:name":"Amazing Carpet Cleaning",
    "wof:placetype":"venue"
},
  "geometry": {"coordinates":[-98.508448,29.44558],"type":"Point"}
}