{
  "type": "Feature",
  "properties": {
    "iso:country":"US",
    "sg:address":"16210 W FM 140",
    "sg:city":"Pearsall",
    "sg:classifiers":[
        {
            "category":"Building & Trades",
            "subcategory":"Construction",
            "type":"Services"
        }
    ],
    "sg:phone":"+1 830 334 8260",
    "sg:postcode":"78061",
    "sg:province":"TX",
    "sg:tags":[
        "contractor"
    ],
    "wof:name":"2 Fence",
    "wof:placetype":"venue"
},
  "geometry": {"coordinates":[-99.307528,29.015247],"type":"Point"}
}