{
  "type": "Feature",
  "properties": {
    "iso:country":"US",
    "sg:address":"2524 Stadium Dr",
    "sg:city":"Fort Worth",
    "sg:classifiers":[
        {
            "category":"Freight",
            "type":"Transportation"
        },
        {
            "category":"Professional",
            "subcategory":"Business Services",
            "type":"Services"
        }
    ],
    "sg:phone":"+1 817 926 2000",
    "sg:postcode":"76109",
    "sg:province":"TX",
    "sg:tags":[
        "shipping",
        "agent"
    ],
    "wof:name":"I T W Shippers Products",
    "wof:placetype":"venue"
},
  "geometry": {"coordinates":[-97.365551,32.714412],"type":"Point"}
}