{
  "type": "Feature",
  "properties": {
    "iso:country":"US",
    "sg:address":"24906 Parview Cir",
    "sg:city":"San Antonio",
    "sg:classifiers":[
        {
            "category":"Professional",
            "subcategory":"Business Services",
            "type":"Services"
        }
    ],
    "sg:phone":"+1 210 710 9583",
    "sg:postcode":"78260",
    "sg:province":"TX",
    "wof:name":"Refresh & Renew Interiors",
    "wof:placetype":"venue"
},
  "geometry": {"coordinates":[-98.466784,29.672129],"type":"Point"}
}