{
  "type": "Feature",
  "properties": {
    "iso:country":"US",
    "sg:address":"601 W Thompson Ave",
    "sg:city":"Temple",
    "sg:classifiers":[
        {
            "category":"Communications",
            "type":"Services"
        },
        {
            "category":"Communications",
            "subcategory":"Television Station",
            "type":"Services"
        }
    ],
    "sg:phone":"+1 254 774 7898",
    "sg:postcode":"76501",
    "sg:province":"TX",
    "sg:tags":[
        "satellite",
        "antenna",
        "cable",
        "tv",
        "system",
        "equipment",
        "carrier",
        "communications-common"
    ],
    "wof:name":"Satellite Tv",
    "wof:placetype":"venue"
},
  "geometry": {"coordinates":[-97.339973,31.11706],"type":"Point"}
}