{
  "type": "Feature",
  "properties": {
    "iso:country":"US",
    "sg:address":"1910 Texas Ave",
    "sg:city":"Bridge City",
    "sg:classifiers":[
        {
            "category":"Shopping",
            "subcategory":"Pharmacy",
            "type":"Retail Goods"
        }
    ],
    "sg:phone":"+1 409 735 5555",
    "sg:postcode":"77611",
    "sg:province":"TX",
    "sg:tags":[
        "drug",
        "store"
    ],
    "wof:name":"Harrington's Pharmacy",
    "wof:placetype":"venue"
},
  "geometry": {"coordinates":[-93.827231,30.03903],"type":"Point"}
}