{
  "type": "Feature",
  "properties": {
    "iso:country":"US",
    "sg:address":"3120 Calder Ave",
    "sg:city":"Beaumont",
    "sg:classifiers":[
        {
            "category":"Food & Beverages",
            "subcategory":"Liquor & Beverages",
            "type":"Retail Goods"
        }
    ],
    "sg:phone":"+1 409 835 0016",
    "sg:postcode":"77702",
    "sg:province":"TX",
    "wof:name":"A J's Disc Liquor Stores",
    "wof:placetype":"venue"
},
  "geometry": {"coordinates":[-94.13529200000001,30.085594],"type":"Point"}
}