{
  "type": "Feature",
  "properties": {
    "iso:country":"US",
    "sg:address":"7200 Hatton Rd",
    "sg:city":"Amarillo",
    "sg:classifiers":[
        {
            "category":"Freight",
            "type":"Transportation"
        }
    ],
    "sg:phone":"+1 806 355 5383",
    "sg:postcode":"79110",
    "sg:province":"TX",
    "sg:tags":[
        "trucking"
    ],
    "wof:name":"Bar Double S Trucking Inc",
    "wof:placetype":"venue"
},
  "geometry": {"coordinates":[-101.894999,35.133655],"type":"Point"}
}