{
  "type": "Feature",
  "properties": {
    "iso:country":"US",
    "sg:address":"2509 Nasa Road 1",
    "sg:city":"Seabrook",
    "sg:classifiers":[
        {
            "category":"Autos & Motor Vehicles",
            "subcategory":"Boat Sales",
            "type":"Retail Goods"
        }
    ],
    "sg:phone":"+1 281 474 4101",
    "sg:postcode":"77586",
    "sg:province":"TX",
    "sg:tags":[
        "dealer",
        "sales"
    ],
    "sg:website":"www.jb-yachts.com",
    "wof:name":"Jay Bettis & Co Yacht Sales",
    "wof:placetype":"venue"
},
  "geometry": {"coordinates":[-95.03346000000001,29.560431],"type":"Point"}
}