{
  "type": "Feature",
  "properties": {
    "iso:country":"US",
    "sg:address":"4959 Louetta Rd",
    "sg:city":"Spring",
    "sg:classifiers":[
        {
            "category":"Insurance",
            "subcategory":"Insurance Agent",
            "type":"Services"
        },
        {
            "category":"Insurance",
            "subcategory":"Hazard Insurance",
            "type":"Services"
        }
    ],
    "sg:phone":"+1 281 205 4614",
    "sg:postcode":"77379",
    "sg:province":"TX",
    "sg:tags":[
        "auto",
        "motorcycle"
    ],
    "sg:website":"http://www.firstacceptancecorp.com/Locations.aspx",
    "wof:name":"Acceptance Auto Insurance- Spring",
    "wof:placetype":"venue"
},
  "geometry": {"coordinates":[-95.489503,30.039895],"type":"Point"}
}