{
  "type": "Feature",
  "properties": {
    "iso:country":"US",
    "sg:address":"22751 Black Cherry",
    "sg:city":"Elmendorf",
    "sg:classifiers":[
        {
            "category":"Bars & Pubs",
            "type":"Food & Drink"
        }
    ],
    "sg:phone":"+1 210 621 9456",
    "sg:postcode":"78112",
    "sg:province":"TX",
    "sg:tags":[
        "drinking"
    ],
    "wof:name":"Alizzays Sports Bar",
    "wof:placetype":"venue"
},
  "geometry": {"coordinates":[-98.40080500000001,29.186999],"type":"Point"}
}