{
  "type": "Feature",
  "properties": {
    "iso:country":"US",
    "sg:address":"1313 Slocum St #103",
    "sg:city":"Dallas",
    "sg:classifiers":[
        {
            "category":"Arts & Performance",
            "subcategory":"Art Gallery",
            "type":"Entertainment"
        }
    ],
    "sg:phone":"+1 214 352 1811",
    "sg:postcode":"75207",
    "sg:province":"TX",
    "sg:website":"www.banksfineart.com",
    "wof:name":"Banks Fine Art",
    "wof:placetype":"venue"
},
  "geometry": {"coordinates":[-96.817263,32.790585],"type":"Point"}
}