{
  "type": "Feature",
  "properties": {
    "iso:country":"US",
    "sg:address":"4314 Tidwell Rd",
    "sg:city":"Houston",
    "sg:classifiers":[
        {
            "category":"Building & Trades",
            "subcategory":"Pest Control",
            "type":"Services"
        }
    ],
    "sg:phone":"+1 713 694 7171",
    "sg:postcode":"77093",
    "sg:province":"TX",
    "sg:website":"www.northhoustonexterminators.com",
    "wof:name":"North Houston Exterminators",
    "wof:placetype":"venue"
},
  "geometry": {"coordinates":[-95.3253,29.847921],"type":"Point"}
}