{
  "type": "Feature",
  "properties": {
    "iso:country":"US",
    "sg:address":"1503 W Industrial Ave",
    "sg:city":"Midland",
    "sg:classifiers":[
        {
            "category":"Wholesale",
            "subcategory":"Durable Goods & Equipment",
            "type":"Manufacturing & Wholesale Goods"
        }
    ],
    "sg:phone":"+1 432 682 5151",
    "sg:postcode":"79701",
    "sg:province":"TX",
    "sg:tags":[
        "importer"
    ],
    "wof:name":"Bowington Morgan Imports",
    "wof:placetype":"venue"
},
  "geometry": {"coordinates":[-102.089192,31.98748],"type":"Point"}
}