{
  "type": "Feature",
  "properties": {
    "iso:country":"US",
    "sg:address":"105 North Dr",
    "sg:city":"San Antonio",
    "sg:classifiers":[
        {
            "category":"Banks & Credit Unions",
            "subcategory":"Financial Services",
            "type":"Services"
        }
    ],
    "sg:phone":"+1 210 731 9161",
    "sg:postcode":"78201",
    "sg:province":"TX",
    "sg:tags":[
        "investor"
    ],
    "wof:name":"Rio Azul Investments LLC",
    "wof:placetype":"venue"
},
  "geometry": {"coordinates":[-98.52891200000001,29.467101],"type":"Point"}
}