{
  "type": "Feature",
  "properties": {
    "iso:country":"US",
    "sg:address":"103 Chestnut Hill Cove",
    "sg:city":"Lakeway",
    "sg:classifiers":[
        {
            "category":"Professional",
            "subcategory":"Employment Agencies",
            "type":"Services"
        }
    ],
    "sg:phone":"+1 512 261 5314",
    "sg:postcode":"78734",
    "sg:province":"TX",
    "sg:tags":[
        "leasing"
    ],
    "wof:name":"Peo Pro's",
    "wof:placetype":"venue"
},
  "geometry": {"coordinates":[-97.97291300000001,30.380801],"type":"Point"}
}