{
  "type": "Feature",
  "properties": {
    "iso:country":"US",
    "sg:address":"13115 Crieffe Rd",
    "sg:city":"Houston",
    "sg:classifiers":[
        {
            "category":"Food & Beverages",
            "subcategory":"Supermarket",
            "type":"Retail Goods"
        },
        {
            "category":"Food & Beverages",
            "subcategory":"Groceries & Convenience Stores",
            "type":"Retail Goods"
        }
    ],
    "sg:phone":"+1 832 598 2275",
    "sg:postcode":"77039",
    "sg:province":"TX",
    "sg:tags":[
        "super"
    ],
    "wof:name":"LATINO SUPERMARKET",
    "wof:placetype":"venue"
},
  "geometry": {"coordinates":[-95.320735,29.909945],"type":"Point"}
}