{
  "type": "Feature",
  "properties": {
    "iso:country":"US",
    "sg:address":"202 Trade Center Dr",
    "sg:city":"New Braunfels",
    "sg:classifiers":[
        {
            "category":"Wholesale",
            "subcategory":"Electrical",
            "type":"Manufacturing & Wholesale Goods"
        }
    ],
    "sg:phone":"+1 210 653 6666",
    "sg:postcode":"78130",
    "sg:province":"TX",
    "sg:tags":[
        "fire",
        "equipment",
        "protection"
    ],
    "wof:name":"Automatic Protection Systems",
    "wof:placetype":"venue"
},
  "geometry": {"coordinates":[-98.111628,29.687607],"type":"Point"}
}