{
  "type": "Feature",
  "properties": {
    "iso:country":"US",
    "sg:address":"1655 S 23rd St",
    "sg:city":"Beaumont",
    "sg:classifiers":[
        {
            "category":"Building & Trades",
            "subcategory":"Electrical",
            "type":"Services"
        }
    ],
    "sg:phone":"+1 409 842 4652",
    "sg:postcode":"77707",
    "sg:province":"TX",
    "sg:tags":[
        "general",
        "electrical",
        "electric",
        "contractor"
    ],
    "wof:name":"Gold Crest Electric Co Inc",
    "wof:placetype":"venue"
},
  "geometry": {"coordinates":[-94.142758,30.056733],"type":"Point"}
}