{
  "type": "Feature",
  "properties": {
    "iso:country":"US",
    "sg:address":"449 5th Ave",
    "sg:city":"Port Arthur",
    "sg:classifiers":[
        {
            "category":"Shopping",
            "subcategory":"Clothing, Apparel, & Fashions",
            "type":"Retail Goods"
        }
    ],
    "sg:phone":"+1 409 982 1222",
    "sg:postcode":"77642",
    "sg:province":"TX",
    "wof:name":"C & R Unlimited",
    "wof:placetype":"venue"
},
  "geometry": {"coordinates":[-93.91347500000001,29.895417],"type":"Point"}
}