{
  "type": "Feature",
  "properties": {
    "iso:country":"US",
    "sg:address":"3514 Autumn Bend Dr",
    "sg:city":"Sugar Land",
    "sg:classifiers":[
        {
            "category":"Travel",
            "subcategory":"Travel Agent",
            "type":"Entertainment"
        }
    ],
    "sg:phone":"+1 281 265 3020",
    "sg:postcode":"77479",
    "sg:province":"TX",
    "sg:tags":[
        "agency"
    ],
    "wof:name":"Four Way Travels",
    "wof:placetype":"venue"
},
  "geometry": {"coordinates":[-95.636543,29.565253],"type":"Point"}
}