{
  "type": "Feature",
  "properties": {
    "iso:country":"US",
    "sg:address":"6711 Theall Rd",
    "sg:city":"Houston",
    "sg:classifiers":[
        {
            "category":"Wholesale",
            "subcategory":"Plants",
            "type":"Manufacturing & Wholesale Goods"
        }
    ],
    "sg:phone":"+1 281 360 8978",
    "sg:postcode":"77066",
    "sg:province":"TX",
    "sg:tags":[
        "nursery",
        "tree"
    ],
    "wof:name":"Moreland Wholesale Nursery",
    "wof:placetype":"venue"
},
  "geometry": {"coordinates":[-95.52455399999999,29.965082],"type":"Point"}
}