{
  "type": "Feature",
  "properties": {
    "iso:country":"US",
    "sg:address":"4701 W Gate Blvd",
    "sg:city":"Austin",
    "sg:classifiers":[
        {
            "category":"Real Estate",
            "subcategory":"Real Estate Agent",
            "type":"Services"
        }
    ],
    "sg:phone":"+1 512 892 6886",
    "sg:postcode":"78745",
    "sg:province":"TX",
    "wof:name":"Phillips Group",
    "wof:placetype":"venue"
},
  "geometry": {"coordinates":[-97.80189799999999,30.228082],"type":"Point"}
}