{
  "type": "Feature",
  "properties": {
    "iso:country":"US",
    "sg:address":"3100 County Road 104",
    "sg:city":"Georgetown",
    "sg:classifiers":[
        {
            "category":"Health Services",
            "subcategory":"Clinic",
            "type":"Services"
        }
    ],
    "sg:phone":"+1 512 658 5438",
    "sg:postcode":"78626",
    "sg:province":"TX",
    "sg:tags":[
        "information",
        "alcoholism",
        "treatment"
    ],
    "wof:name":"San Gabriel Independent Therapists",
    "wof:placetype":"venue"
},
  "geometry": {"coordinates":[-97.615662,30.62159],"type":"Point"}
}