{
  "type": "Feature",
  "properties": {
    "iso:country":"US",
    "sg:address":"7554 Sand St",
    "sg:city":"Fort Worth",
    "sg:classifiers":[
        {
            "category":"Manufacturing",
            "subcategory":"Printing",
            "type":"Manufacturing & Wholesale Goods"
        }
    ],
    "sg:phone":"+1 817 589 2960",
    "sg:postcode":"76118",
    "sg:province":"TX",
    "sg:tags":[
        "miscellaneous",
        "publishing"
    ],
    "wof:name":"Peniel Publications",
    "wof:placetype":"venue"
},
  "geometry": {"coordinates":[-97.212999,32.795678],"type":"Point"}
}