{
  "type": "Feature",
  "properties": {
    "iso:country":"US",
    "sg:address":"900 Grapevine Hwy",
    "sg:city":"Hurst",
    "sg:classifiers":[
        {
            "category":"Autos & Motor Vehicles",
            "subcategory":"Fuel & Gas Station",
            "type":"Retail Goods"
        },
        {
            "category":"Autos & Motor Vehicles",
            "subcategory":"Auto Supplies",
            "type":"Retail Goods"
        },
        {
            "category":"Retail",
            "subcategory":"Auto Repair",
            "type":"Services"
        }
    ],
    "sg:phone":"+1 817 577 4280",
    "sg:postcode":"76054",
    "sg:province":"TX",
    "sg:tags":[
        "automobile",
        "lube",
        "oil",
        "inspection"
    ],
    "wof:name":"Pit Stop Xpress",
    "wof:placetype":"venue"
},
  "geometry": {"coordinates":[-97.185721,32.85611],"type":"Point"}
}