{
  "type": "Feature",
  "properties": {
    "iso:country":"US",
    "sg:address":"3711 Medical Dr",
    "sg:city":"San Antonio",
    "sg:classifiers":[
        {
            "category":"Professional",
            "subcategory":"Business Services",
            "type":"Services"
        }
    ],
    "sg:phone":"+1 210 593 4200",
    "sg:postcode":"78229",
    "sg:province":"TX",
    "sg:tags":[
        "packaging"
    ],
    "wof:name":"Vulcan Information Packaging",
    "wof:placetype":"venue"
},
  "geometry": {"coordinates":[-98.557956,29.521203],"type":"Point"}
}