{
  "type": "Feature",
  "properties": {
    "iso:country":"US",
    "sg:address":"14032 Distribution Way",
    "sg:city":"Dallas",
    "sg:classifiers":[
        {
            "category":"Utilities",
            "subcategory":"Electric",
            "type":"Services"
        }
    ],
    "sg:phone":"+1 214 236 4941",
    "sg:postcode":"75234",
    "sg:province":"TX",
    "wof:name":"Txu US Holdings Co",
    "wof:placetype":"venue"
},
  "geometry": {"coordinates":[-96.898994,32.935196],"type":"Point"}
}