{
  "type": "Feature",
  "properties": {
    "iso:country":"US",
    "sg:address":"14214 Spotted Cedar",
    "sg:city":"San Antonio",
    "sg:classifiers":[
        {
            "category":"Professional",
            "subcategory":"Business Services",
            "type":"Services"
        }
    ],
    "sg:phone":"+1 210 877 1280",
    "sg:postcode":"78249",
    "sg:province":"TX",
    "wof:name":"Interesting Solutions",
    "wof:placetype":"venue"
},
  "geometry": {"coordinates":[-98.635166,29.583569],"type":"Point"}
}