{
  "type": "Feature",
  "properties": {
    "iso:country":"US",
    "sg:address":"4040 Krag St",
    "sg:city":"El Paso",
    "sg:classifiers":[
        {
            "category":"Wholesale",
            "subcategory":"Hardware",
            "type":"Manufacturing & Wholesale Goods"
        },
        {
            "category":"Manufacturing",
            "subcategory":"Tools & Machinery",
            "type":"Manufacturing & Wholesale Goods"
        }
    ],
    "sg:phone":"+1 915 857 1048",
    "sg:postcode":"79938",
    "sg:province":"TX",
    "sg:tags":[
        "plant",
        "ice",
        "machine",
        "equipment",
        "refrigeration",
        "fabricator",
        "making",
        "block",
        "con"
    ],
    "wof:name":"C ESA Inc",
    "wof:placetype":"venue"
},
  "geometry": {"coordinates":[-106.177952,31.81706],"type":"Point"}
}