{
  "type": "Feature",
  "properties": {
    "iso:country":"US",
    "sg:address":"7020 Fair Oaks Ave",
    "sg:city":"Dallas",
    "sg:classifiers":[
        {
            "category":"Food & Beverages",
            "subcategory":"Groceries & Convenience Stores",
            "type":"Retail Goods"
        }
    ],
    "sg:phone":"+1 214 361 0702",
    "sg:postcode":"75231",
    "sg:province":"TX",
    "wof:name":"B Bonito",
    "wof:placetype":"venue"
},
  "geometry": {"coordinates":[-96.759085,32.871895],"type":"Point"}
}