{
  "type": "Feature",
  "properties": {
    "iso:country":"US",
    "sg:address":"2151 Farrington St",
    "sg:city":"Dallas",
    "sg:classifiers":[
        {
            "category":"Shopping",
            "subcategory":"Florist",
            "type":"Retail Goods"
        }
    ],
    "sg:phone":"+1 214 655 1200",
    "sg:postcode":"75207",
    "sg:province":"TX",
    "wof:name":"Dallas Delivery Pool",
    "wof:placetype":"venue"
},
  "geometry": {"coordinates":[-96.831299,32.796799],"type":"Point"}
}