{
  "type": "Feature",
  "properties": {
    "iso:country":"US",
    "sg:address":"1212 Northwood Dr",
    "sg:city":"Commerce",
    "sg:classifiers":[
        {
            "category":"Organizations",
            "subcategory":"Religious Organization",
            "type":"Services"
        }
    ],
    "sg:phone":"+1 903 886 8086",
    "sg:postcode":"75428",
    "sg:province":"TX",
    "sg:tags":[
        "church"
    ],
    "wof:name":"First Christian Church Parsong",
    "wof:placetype":"venue"
},
  "geometry": {"coordinates":[-95.900099,33.261439],"type":"Point"}
}