{
  "type": "Feature",
  "properties": {
    "iso:country":"US",
    "sg:address":"11809 Rain Forest Cove",
    "sg:city":"Austin",
    "sg:classifiers":[
        {
            "category":"Professional",
            "subcategory":"Management & Consulting",
            "type":"Services"
        }
    ],
    "sg:phone":"+1 512 331 0146",
    "sg:postcode":"78759",
    "sg:province":"TX",
    "sg:tags":[
        "consultant",
        "business"
    ],
    "wof:name":"Pinnacle Health Systems",
    "wof:placetype":"venue"
},
  "geometry": {"coordinates":[-97.751341,30.421354],"type":"Point"}
}