{
  "type": "Feature",
  "properties": {
    "iso:country":"US",
    "sg:address":"140 W Fm 1382",
    "sg:city":"Cedar Hill",
    "sg:classifiers":[
        {
            "category":"Restaurant",
            "type":"Food & Drink"
        }
    ],
    "sg:phone":"+1 972 291 7888",
    "sg:postcode":"75104",
    "sg:province":"TX",
    "sg:tags":[
        "pizza"
    ],
    "sg:website":"www.cicispizza.com",
    "wof:name":"Cici's Pizza",
    "wof:placetype":"venue"
},
  "geometry": {"coordinates":[-96.942802,32.598999],"type":"Point"}
}