{
  "type": "Feature",
  "properties": {
    "iso:country":"US",
    "sg:address":"632 N Ed Carey Dr",
    "sg:city":"Harlingen",
    "sg:classifiers":[
        {
            "category":"Health Services",
            "subcategory":"Clinic",
            "type":"Services"
        }
    ],
    "sg:phone":"+1 956 440 1110",
    "sg:postcode":"78550",
    "sg:province":"TX",
    "sg:tags":[
        "home",
        "care"
    ],
    "wof:name":"Little Nighbors Pediatric Care",
    "wof:placetype":"venue"
},
  "geometry": {"coordinates":[-97.663082,26.210175],"type":"Point"}
}