{
  "type": "Feature",
  "properties": {
    "iso:country":"US",
    "sg:address":"519 Golder Ave",
    "sg:city":"Odessa",
    "sg:classifiers":[
        {
            "category":"Health Services",
            "subcategory":"Doctor",
            "type":"Services"
        }
    ],
    "sg:phone":"+1 432 332 3300",
    "sg:postcode":"79761",
    "sg:province":"TX",
    "sg:tags":[
        "medical"
    ],
    "wof:name":"Abdul Kadir MD",
    "wof:placetype":"venue"
},
  "geometry": {"coordinates":[-102.376482,31.845799],"type":"Point"}
}