{
  "type": "Feature",
  "properties": {
    "iso:country":"US",
    "sg:address":"5310 San Antonio Ct",
    "sg:city":"Midland",
    "sg:classifiers":[
        {
            "category":"Building & Trades",
            "subcategory":"Construction",
            "type":"Services"
        }
    ],
    "sg:phone":"+1 432 520 0028",
    "sg:postcode":"79707",
    "sg:province":"TX",
    "sg:tags":[
        "water",
        "abandonment",
        "well",
        "plugging"
    ],
    "wof:name":"Upc Micro",
    "wof:placetype":"venue"
},
  "geometry": {"coordinates":[-102.159289,32.020905],"type":"Point"}
}