{
  "type": "Feature",
  "properties": {
    "iso:country":"US",
    "sg:address":"5718 Chesterfield Ave",
    "sg:city":"Austin",
    "sg:classifiers":[
        {
            "category":"Professional",
            "subcategory":"Business Services",
            "type":"Services"
        }
    ],
    "sg:phone":"+1 512 896 5086",
    "sg:postcode":"78752",
    "sg:province":"TX",
    "wof:name":"Brent Buford Design",
    "wof:placetype":"venue"
},
  "geometry": {"coordinates":[-97.720955,30.3249],"type":"Point"}
}