{
  "type": "Feature",
  "properties": {
    "iso:country":"US",
    "sg:address":"307 E San Saba Ave",
    "sg:city":"Wortham",
    "sg:classifiers":[
        {
            "category":"Home & Garden",
            "subcategory":"Building Materials",
            "type":"Retail Goods"
        }
    ],
    "sg:phone":"+1 254 765 8922",
    "sg:postcode":"76693",
    "sg:province":"TX",
    "sg:tags":[
        "glass",
        "window",
        "plate"
    ],
    "wof:name":"E & W Windshield Replacement",
    "wof:placetype":"venue"
},
  "geometry": {"coordinates":[-96.45841,31.789032],"type":"Point"}
}