{
  "type": "Feature",
  "properties": {
    "iso:country":"US",
    "sg:address":"2800 Erwin Rd",
    "sg:city":"Jacksboro",
    "sg:classifiers":[
        {
            "category":"Shopping",
            "subcategory":"Discount & Variety Stores",
            "type":"Retail Goods"
        },
        {
            "category":"Shopping",
            "subcategory":"Gifts & Souvenirs",
            "type":"Retail Goods"
        }
    ],
    "sg:phone":"+1 940 374 3567",
    "sg:postcode":"76487",
    "sg:province":"TX",
    "sg:tags":[
        "merchandise",
        "general"
    ],
    "wof:name":"J & R Specialty Merchandise",
    "wof:placetype":"venue"
},
  "geometry": {"coordinates":[-97.823803,32.964742],"type":"Point"}
}