{
  "type": "Feature",
  "properties": {
    "iso:country":"US",
    "sg:address":"902 S Main St",
    "sg:city":"Weatherford",
    "sg:classifiers":[
        {
            "category":"Restaurant",
            "type":"Food & Drink"
        }
    ],
    "sg:menulink":"http://www.allmenus.com/tx/weatherford/177260-kfc---kentucky-fried-chicken/menu/",
    "sg:phone":"+1 817 594 1391",
    "sg:postcode":"76086",
    "sg:province":"TX",
    "sg:tags":[
        "american",
        "chicken"
    ],
    "wof:name":"KFC - Kentucky Fried Chicken",
    "wof:placetype":"venue"
},
  "geometry": {"coordinates":[-97.79753599999999,32.749298],"type":"Point"}
}