{
  "type": "Feature",
  "properties": {
    "iso:country":"US",
    "sg:address":"1100 Stone Rd",
    "sg:city":"Kilgore",
    "sg:classifiers":[
        {
            "category":"Building & Trades",
            "subcategory":"Electrical",
            "type":"Services"
        }
    ],
    "sg:phone":"+1 903 984 5981",
    "sg:postcode":"75662",
    "sg:province":"TX",
    "sg:tags":[
        "electrical",
        "electric",
        "contractor"
    ],
    "wof:name":"Alliance Electric",
    "wof:placetype":"venue"
},
  "geometry": {"coordinates":[-94.86657700000001,32.391981],"type":"Point"}
}