{
  "type": "Feature",
  "properties": {
    "iso:country":"US",
    "sg:address":"22 Waugh Dr",
    "sg:city":"Houston",
    "sg:classifiers":[
        {
            "category":"Professional",
            "subcategory":"Management & Consulting",
            "type":"Services"
        }
    ],
    "sg:phone":"+1 713 861 1180",
    "sg:postcode":"77007",
    "sg:province":"TX",
    "sg:tags":[
        "business"
    ],
    "wof:name":"Newbury Management",
    "wof:placetype":"venue"
},
  "geometry": {"coordinates":[-95.398383,29.768789],"type":"Point"}
}