{
  "type": "Feature",
  "properties": {
    "iso:country":"US",
    "sg:address":"385 Other Place Dr",
    "sg:city":"New Braunfels",
    "sg:classifiers":[
        {
            "category":"Travel",
            "subcategory":"Hotels & Motels",
            "type":"Entertainment"
        }
    ],
    "sg:phone":"+1 830 625 5114",
    "sg:postcode":"78130",
    "sg:province":"TX",
    "sg:tags":[
        "resort",
        "camp",
        "tourist"
    ],
    "sg:website":"www.theotherplaceresort.com",
    "wof:name":"Other Place The",
    "wof:placetype":"venue"
},
  "geometry": {"coordinates":[-98.11771899999999,29.702703],"type":"Point"}
}