{
  "type": "Feature",
  "properties": {
    "iso:country":"US",
    "sg:address":"12006 Coulson Cir",
    "sg:city":"Houston",
    "sg:classifiers":[
        {
            "category":"Home & Garden",
            "subcategory":"Home Furnishings",
            "type":"Retail Goods"
        },
        {
            "category":"Building & Trades",
            "subcategory":"Construction",
            "type":"Services"
        },
        {
            "category":"Wholesale",
            "subcategory":"Home Furnishings",
            "type":"Manufacturing & Wholesale Goods"
        }
    ],
    "sg:phone":"+1 832 603 4170",
    "sg:postcode":"77015",
    "sg:province":"TX",
    "sg:tags":[
        "draperies",
        "installation",
        "window",
        "treatment",
        "shades-wholesale",
        "curtain",
        "manufacturer"
    ],
    "wof:name":"McCord Window Covering Services",
    "wof:placetype":"venue"
},
  "geometry": {"coordinates":[-95.220241,29.763799],"type":"Point"}
}