{
  "type": "Feature",
  "properties": {
    "iso:country":"US",
    "sg:address":"932 Brae Loch Dr",
    "sg:city":"Dallas",
    "sg:classifiers":[
        {
            "category":"Mining & Drilling",
            "type":"Manufacturing & Wholesale Goods"
        }
    ],
    "sg:phone":"+1 972 557 3906",
    "sg:postcode":"75217",
    "sg:province":"TX",
    "sg:tags":[
        "field"
    ],
    "wof:name":"Zjs Compactor & Bailer Repair",
    "wof:placetype":"venue"
},
  "geometry": {"coordinates":[-96.65269600000001,32.728578],"type":"Point"}
}