{
  "type": "Feature",
  "properties": {
    "iso:country":"US",
    "sg:address":"618 N Brookside Dr",
    "sg:city":"Dallas",
    "sg:classifiers":[
        {
            "category":"Social Services",
            "type":"Services"
        }
    ],
    "sg:phone":"+1 214 821 1649",
    "sg:postcode":"75214",
    "sg:province":"TX",
    "sg:tags":[
        "worker"
    ],
    "wof:name":"Nancy Stark",
    "wof:placetype":"venue"
},
  "geometry": {"coordinates":[-96.74997999999999,32.811884],"type":"Point"}
}