{
  "type": "Feature",
  "properties": {
    "iso:country":"US",
    "sg:address":"3776 Darcus St",
    "sg:city":"Houston",
    "sg:classifiers":[
        {
            "category":"Education",
            "subcategory":"Special Training",
            "type":"Public Place"
        }
    ],
    "sg:phone":"+1 713 664 2246",
    "sg:postcode":"77005",
    "sg:province":"TX",
    "wof:name":"Franklin Educatn Developement",
    "wof:placetype":"venue"
},
  "geometry": {"coordinates":[-95.434854,29.70828],"type":"Point"}
}