{
  "type": "Feature",
  "properties": {
    "iso:country":"US",
    "sg:address":"2513 S Stemmons Fwy",
    "sg:city":"Lewisville",
    "sg:classifiers":[
        {
            "category":"Restaurant",
            "type":"Food & Drink"
        }
    ],
    "sg:phone":"+1 972 459 6642",
    "sg:postcode":"75067",
    "sg:province":"TX",
    "sg:tags":[
        "steakhouse"
    ],
    "sg:website":"logansroadhouse.com/Default.aspx",
    "wof:name":"Logans Roadhouse",
    "wof:placetype":"venue"
},
  "geometry": {"coordinates":[-96.973602,33.008598],"type":"Point"}
}