{
  "type": "Feature",
  "properties": {
    "iso:country":"US",
    "sg:address":"4407 E Rosedale St",
    "sg:city":"Fort Worth",
    "sg:classifiers":[
        {
            "category":"Restaurant",
            "type":"Food & Drink"
        }
    ],
    "sg:phone":"+1 817 531 3920",
    "sg:postcode":"76105",
    "sg:province":"TX",
    "sg:tags":[
        "eating"
    ],
    "wof:name":"One Stop Seafood & More",
    "wof:placetype":"venue"
},
  "geometry": {"coordinates":[-97.257921,32.731311],"type":"Point"}
}