{
  "type": "Feature",
  "properties": {
    "iso:country":"US",
    "sg:address":"724 Green Cove Ln",
    "sg:city":"Dallas",
    "sg:classifiers":[
        {
            "category":"Building & Trades",
            "subcategory":"Construction",
            "type":"Services"
        }
    ],
    "sg:phone":"+1 214 375 7894",
    "sg:postcode":"75232",
    "sg:province":"TX",
    "sg:tags":[
        "residential"
    ],
    "wof:name":"Mdi General Contractors",
    "wof:placetype":"venue"
},
  "geometry": {"coordinates":[-96.834369,32.684634],"type":"Point"}
}