{
  "type": "Feature",
  "properties": {
    "iso:country":"US",
    "sg:address":"13207 Blossomheath Rd",
    "sg:city":"Cypress",
    "sg:classifiers":[
        {
            "category":"Wholesale",
            "subcategory":"Vending Machines",
            "type":"Manufacturing & Wholesale Goods"
        }
    ],
    "sg:phone":"+1 281 373 1167",
    "sg:postcode":"77429",
    "sg:province":"TX",
    "sg:tags":[
        "operator"
    ],
    "wof:name":"Southwest Houston Vending Svc",
    "wof:placetype":"venue"
},
  "geometry": {"coordinates":[-95.641237,29.96734],"type":"Point"}
}