{
  "type": "Feature",
  "properties": {
    "iso:country":"US",
    "sg:address":"1901 S Goliad St",
    "sg:city":"Rockwall",
    "sg:classifiers":[
        {
            "category":"Home & Garden",
            "subcategory":"Home Furnishings",
            "type":"Retail Goods"
        }
    ],
    "sg:phone":"+1 972 771 6751",
    "sg:postcode":"75087",
    "sg:province":"TX",
    "sg:tags":[
        "mirror"
    ],
    "wof:name":"Rockwall Glass",
    "wof:placetype":"venue"
},
  "geometry": {"coordinates":[-96.450209,32.909661],"type":"Point"}
}