{
  "type": "Feature",
  "properties": {
    "iso:country":"US",
    "sg:address":"1708 Dungan Ln",
    "sg:city":"Austin",
    "sg:classifiers":[
        {
            "category":"Health Services",
            "subcategory":"Medical Lab",
            "type":"Services"
        }
    ],
    "sg:phone":"+1 512 491 8600",
    "sg:postcode":"78754",
    "sg:province":"TX",
    "sg:tags":[
        "laboratory"
    ],
    "wof:name":"Dossing Orthodontic Lab",
    "wof:placetype":"venue"
},
  "geometry": {"coordinates":[-97.672635,30.351377],"type":"Point"}
}