{
  "type": "Feature",
  "properties": {
    "iso:country":"US",
    "sg:address":"13853 Creekside Pl",
    "sg:city":"Dallas",
    "sg:classifiers":[
        {
            "category":"Professional",
            "subcategory":"Business Services",
            "type":"Services"
        }
    ],
    "sg:phone":"+1 972 726 7387",
    "sg:postcode":"75240",
    "sg:province":"TX",
    "wof:name":"Butler Patrica Kelly",
    "wof:placetype":"venue"
},
  "geometry": {"coordinates":[-96.789378,32.935703],"type":"Point"}
}