{
  "type": "Feature",
  "properties": {
    "iso:country":"US",
    "sg:address":"2933 Willowdale Ct",
    "sg:city":"Mc Kinney",
    "sg:classifiers":[
        {
            "category":"Building & Trades",
            "subcategory":"Construction",
            "type":"Services"
        }
    ],
    "sg:phone":"+1 214 785 1014",
    "sg:postcode":"75070",
    "sg:province":"TX",
    "sg:tags":[
        "excavation",
        "contractor"
    ],
    "wof:name":"Performance Excavation",
    "wof:placetype":"venue"
},
  "geometry": {"coordinates":[-96.66124000000001,33.181841],"type":"Point"}
}