{
  "type": "Feature",
  "properties": {
    "iso:country":"US",
    "sg:address":"8403 Cross Park Dr Ste 3H",
    "sg:city":"Austin",
    "sg:classifiers":[
        {
            "category":"Professional",
            "type":"Services"
        }
    ],
    "sg:phone":"+1 512 828 7738",
    "sg:postcode":"78754",
    "sg:province":"TX",
    "sg:tags":[
        "processing",
        "data"
    ],
    "wof:name":"Datacom Spot, The",
    "wof:placetype":"venue"
},
  "geometry": {"coordinates":[-97.67647100000001,30.338088],"type":"Point"}
}