{
  "type": "Feature",
  "properties": {
    "iso:country":"US",
    "sg:address":"933 Canyon Ridge Dr",
    "sg:city":"De Soto",
    "sg:classifiers":[
        {
            "category":"Restaurant",
            "type":"Food & Drink"
        }
    ],
    "sg:phone":"+1 972 274 1657",
    "sg:postcode":"75115",
    "sg:province":"TX",
    "sg:tags":[
        "eating"
    ],
    "wof:name":"Moms Kountry Kitchen",
    "wof:placetype":"venue"
},
  "geometry": {"coordinates":[-96.871044,32.605308],"type":"Point"}
}