{
  "type": "Feature",
  "properties": {
    "iso:country":"US",
    "sg:address":"5174 Richmond Ave",
    "sg:city":"Houston",
    "sg:classifiers":[
        {
            "category":"Banks & Credit Unions",
            "subcategory":"Bank",
            "type":"Services"
        }
    ],
    "sg:phone":"+1 281 648 2387",
    "sg:postcode":"77056",
    "sg:province":"TX",
    "wof:name":"HomeTown Bank Of Friendswood",
    "wof:placetype":"venue"
},
  "geometry": {"coordinates":[-95.466216,29.731797],"type":"Point"}
}