{
  "type": "Feature",
  "properties": {
    "iso:country":"US",
    "sg:address":"9206 Bluebell Dr",
    "sg:city":"San Antonio",
    "sg:classifiers":[
        {
            "category":"Home & Garden",
            "subcategory":"Garden Supply",
            "type":"Retail Goods"
        }
    ],
    "sg:phone":"+1 210 651 4042",
    "sg:postcode":"78266",
    "sg:province":"TX",
    "wof:name":"Back To Nature",
    "wof:placetype":"venue"
},
  "geometry": {"coordinates":[-98.302076,29.635639],"type":"Point"}
}