{
  "type": "Feature",
  "properties": {
    "iso:country":"US",
    "sg:address":"4901 David Strickland Rd",
    "sg:city":"Fort Worth",
    "sg:classifiers":[
        {
            "category":"Freight",
            "type":"Transportation"
        }
    ],
    "sg:phone":"+1 817 478 0129",
    "sg:postcode":"76119",
    "sg:province":"TX",
    "sg:tags":[
        "operator",
        "local",
        "trucking"
    ],
    "wof:name":"C S E",
    "wof:placetype":"venue"
},
  "geometry": {"coordinates":[-97.249403,32.681787],"type":"Point"}
}