{
  "type": "Feature",
  "properties": {
    "iso:country":"US",
    "sg:address":"106 Oak St",
    "sg:city":"Clyde",
    "sg:classifiers":[
        {
            "category":"Shopping",
            "type":"Retail Goods"
        }
    ],
    "sg:phone":"+1 325 893 5862",
    "sg:postcode":"79510",
    "sg:province":"TX",
    "sg:tags":[
        "trophy",
        "medal",
        "award"
    ],
    "wof:name":"Big Country Trophies",
    "wof:placetype":"venue"
},
  "geometry": {"coordinates":[-99.493633,32.407184],"type":"Point"}
}