{
  "type": "Feature",
  "properties": {
    "iso:country":"US",
    "sg:address":"7259 US Hwy 87",
    "sg:city":"San Antonio",
    "sg:classifiers":[
        {
            "category":"Professional",
            "subcategory":"Business Services",
            "type":"Services"
        }
    ],
    "sg:phone":"+1 210 648 2200",
    "sg:postcode":"78263",
    "sg:province":"TX",
    "sg:tags":[
        "water",
        "treatment"
    ],
    "wof:name":"Dawn Service & Supply",
    "wof:placetype":"venue"
},
  "geometry": {"coordinates":[-98.34666199999999,29.388102],"type":"Point"}
}