{
  "type": "Feature",
  "properties": {
    "iso:country":"US",
    "sg:address":"910 9th St",
    "sg:city":"Marble Falls",
    "sg:classifiers":[
        {
            "category":"Government",
            "subcategory":"Office",
            "type":"Public Place"
        }
    ],
    "sg:phone":"+1 830 693 7277",
    "sg:postcode":"78654",
    "sg:province":"TX",
    "sg:tags":[
        "village"
    ],
    "wof:name":"Marble Falls Emergency Medical",
    "wof:placetype":"venue"
},
  "geometry": {"coordinates":[-98.274092,30.577602],"type":"Point"}
}