{
  "type": "Feature",
  "properties": {
    "iso:country":"US",
    "sg:address":"1422 Airway Blvd",
    "sg:city":"El Paso",
    "sg:classifiers":[
        {
            "category":"Insurance",
            "subcategory":"Insurance Agent",
            "type":"Services"
        }
    ],
    "sg:phone":"+1 915 843 4300",
    "sg:postcode":"79925",
    "sg:province":"TX",
    "wof:name":"Unistar Auto Insurance",
    "wof:placetype":"venue"
},
  "geometry": {"coordinates":[-106.39531599999999,31.785791],"type":"Point"}
}