{
  "type": "Feature",
  "properties": {
    "iso:country":"US",
    "sg:address":"16775 Addison Rd Ste 103",
    "sg:city":"Addison",
    "sg:classifiers":[
        {
            "category":"Real Estate",
            "subcategory":"Real Estate Services",
            "type":"Services"
        }
    ],
    "sg:phone":"+1 972 250 6400",
    "sg:postcode":"75001",
    "sg:province":"TX",
    "sg:tags":[
        "management",
        "property"
    ],
    "wof:name":"Lauderdale Clark Company",
    "wof:placetype":"venue"
},
  "geometry": {"coordinates":[-96.830299,32.980499],"type":"Point"}
}