{
  "type": "Feature",
  "properties": {
    "iso:country":"US",
    "sg:address":"1319 Creekford Cir",
    "sg:city":"Sugar Land",
    "sg:classifiers":[
        {
            "category":"Banks & Credit Unions",
            "subcategory":"Investment Brokerage",
            "type":"Services"
        }
    ],
    "sg:phone":"+1 281 494 1919",
    "sg:postcode":"77478",
    "sg:province":"TX",
    "sg:tags":[
        "advisory",
        "financial"
    ],
    "wof:name":"Port Folio Management",
    "wof:placetype":"venue"
},
  "geometry": {"coordinates":[-95.59998400000001,29.60392],"type":"Point"}
}