{
  "type": "Feature",
  "properties": {
    "iso:country":"US",
    "sg:address":"1331 W Day St",
    "sg:city":"Denison",
    "sg:classifiers":[
        {
            "category":"Wholesale",
            "subcategory":"Jewelry",
            "type":"Manufacturing & Wholesale Goods"
        }
    ],
    "sg:phone":"+1 903 327 8946",
    "sg:postcode":"75020",
    "sg:province":"TX",
    "sg:tags":[
        "hardware",
        "stone"
    ],
    "wof:name":"Grayson Studio",
    "wof:placetype":"venue"
},
  "geometry": {"coordinates":[-96.555316,33.749008],"type":"Point"}
}