{
  "type": "Feature",
  "properties": {
    "iso:country":"US",
    "sg:address":"25503 Candy Ln",
    "sg:city":"Magnolia",
    "sg:classifiers":[
        {
            "category":"Building & Trades",
            "subcategory":"Construction",
            "type":"Services"
        }
    ],
    "sg:phone":"+1 281 259 7955",
    "sg:postcode":"77355",
    "sg:province":"TX",
    "sg:tags":[
        "earth",
        "moving",
        "contractor"
    ],
    "wof:name":"Coe Construction",
    "wof:placetype":"venue"
},
  "geometry": {"coordinates":[-95.668989,30.113942],"type":"Point"}
}