{
  "type": "Feature",
  "properties": {
    "iso:country":"US",
    "sg:address":"4201 Boston Ave",
    "sg:city":"Lubbock",
    "sg:classifiers":[
        {
            "category":"Organizations",
            "subcategory":"Religious Organization",
            "type":"Services"
        }
    ],
    "sg:phone":"+1 806 797 1974",
    "sg:postcode":"79413",
    "sg:province":"TX",
    "wof:name":"Lubbock Intl House Of Prayer",
    "wof:placetype":"venue"
},
  "geometry": {"coordinates":[-101.874765,33.555109],"type":"Point"}
}