{
  "type": "Feature",
  "properties": {
    "iso:country":"US",
    "sg:address":"5401 E Belknap St",
    "sg:city":"Haltom City",
    "sg:classifiers":[
        {
            "category":"Retail",
            "subcategory":"Auto Repair",
            "type":"Services"
        }
    ],
    "sg:phone":"+1 817 759 1258",
    "sg:postcode":"76117",
    "sg:province":"TX",
    "sg:tags":[
        "glass",
        "coating",
        "tinting"
    ],
    "wof:name":"Tint A",
    "wof:placetype":"venue"
},
  "geometry": {"coordinates":[-97.267893,32.797503],"type":"Point"}
}