{
  "type": "Feature",
  "properties": {
    "iso:country":"US",
    "sg:address":"1404 S Broadway St",
    "sg:city":"Sulphur Springs",
    "sg:classifiers":[
        {
            "category":"Banks & Credit Unions",
            "subcategory":"Bank",
            "type":"Services"
        }
    ],
    "sg:phone":"+1 903 885 9444",
    "sg:postcode":"75482",
    "sg:province":"TX",
    "wof:name":"Community Bank",
    "wof:placetype":"venue"
},
  "geometry": {"coordinates":[-95.59650499999999,33.113559],"type":"Point"}
}