{
  "type": "Feature",
  "properties": {
    "iso:country":"US",
    "sg:address":"2617 Bolton Boone Dr",
    "sg:city":"Desoto",
    "sg:classifiers":[
        {
            "category":"Health Services",
            "subcategory":"Doctor",
            "type":"Services"
        }
    ],
    "sg:phone":"+1 972 296 5036",
    "sg:postcode":"75115",
    "sg:province":"TX",
    "sg:tags":[
        "physician",
        "surgeon"
    ],
    "wof:name":"Vicki V Chancellor MD",
    "wof:placetype":"venue"
},
  "geometry": {"coordinates":[-96.87853200000001,32.643042],"type":"Point"}
}