{
  "type": "Feature",
  "properties": {
    "iso:country":"US",
    "sg:address":"1950 Oak St",
    "sg:city":"Abilene",
    "sg:classifiers":[
        {
            "category":"Building & Trades",
            "subcategory":"Construction",
            "type":"Services"
        }
    ],
    "sg:phone":"+1 325 721 3397",
    "sg:postcode":"79602",
    "sg:province":"TX",
    "sg:tags":[
        "contractor"
    ],
    "wof:name":"Stubbs Drywall",
    "wof:placetype":"venue"
},
  "geometry": {"coordinates":[-99.733749,32.425575],"type":"Point"}
}