{
  "type": "Feature",
  "properties": {
    "iso:country":"US",
    "sg:address":"1205 Texas Ave",
    "sg:city":"Lubbock",
    "sg:classifiers":[
        {
            "category":"Government",
            "subcategory":"Office",
            "type":"Public Place"
        }
    ],
    "sg:phone":"+1 806 472 7664",
    "sg:postcode":"79401",
    "sg:province":"TX",
    "wof:name":"US Dept Of Transportation",
    "wof:placetype":"venue"
},
  "geometry": {"coordinates":[-101.845561,33.583574],"type":"Point"}
}