{
  "type": "Feature",
  "properties": {
    "iso:country":"US",
    "sg:address":"508 S Gray St",
    "sg:city":"Killeen",
    "sg:classifiers":[
        {
            "category":"Personal",
            "type":"Services"
        }
    ],
    "sg:phone":"+1 254 634 6363",
    "sg:postcode":"76541",
    "sg:province":"TX",
    "wof:name":"Family Life Center",
    "wof:placetype":"venue"
},
  "geometry": {"coordinates":[-97.72949,31.115105],"type":"Point"}
}