{
  "type": "Feature",
  "properties": {
    "iso:country":"US",
    "sg:address":"5121 Wally Dr",
    "sg:city":"El Paso",
    "sg:classifiers":[
        {
            "category":"Manufacturing",
            "subcategory":"Printing",
            "type":"Manufacturing & Wholesale Goods"
        }
    ],
    "sg:phone":"+1 915 757 6255",
    "sg:postcode":"79924",
    "sg:province":"TX",
    "sg:tags":[
        "lithographic",
        "commercial"
    ],
    "wof:name":"Creative Foil Printing",
    "wof:placetype":"venue"
},
  "geometry": {"coordinates":[-106.420973,31.890286],"type":"Point"}
}