{
  "type": "Feature",
  "properties": {
    "iso:country":"US",
    "sg:address":"817 Water St",
    "sg:city":"Kerrville",
    "sg:classifiers":[
        {
            "category":"Insurance",
            "subcategory":"Hazard Insurance",
            "type":"Services"
        },
        {
            "category":"Professional",
            "subcategory":"Business Services",
            "type":"Services"
        }
    ],
    "sg:phone":"+1 830 895 2663",
    "sg:postcode":"78028",
    "sg:province":"TX",
    "sg:tags":[
        "bond"
    ],
    "wof:name":"Davis Bonding Co",
    "wof:placetype":"venue"
},
  "geometry": {"coordinates":[-99.140441,30.04536],"type":"Point"}
}