{
  "type": "Feature",
  "properties": {
    "iso:country":"US",
    "sg:address":"1935 Club Xing",
    "sg:city":"New Braunfels",
    "sg:classifiers":[
        {
            "category":"Professional",
            "subcategory":"Engineering",
            "type":"Services"
        }
    ],
    "sg:phone":"+1 830 626 1071",
    "sg:postcode":"78130",
    "sg:province":"TX",
    "wof:name":"Lth Inc",
    "wof:placetype":"venue"
},
  "geometry": {"coordinates":[-98.094842,29.731475],"type":"Point"}
}