{
  "type": "Feature",
  "properties": {
    "iso:country":"US",
    "sg:address":"4030 N Macarthur Blvd",
    "sg:city":"Irving",
    "sg:classifiers":[
        {
            "category":"Shopping",
            "subcategory":"Florist",
            "type":"Retail Goods"
        }
    ],
    "sg:phone":"+1 972 258 0688",
    "sg:postcode":"75038",
    "sg:province":"TX",
    "sg:tags":[
        "fresh",
        "flower"
    ],
    "wof:name":"Flowers Of Las Colinas",
    "wof:placetype":"venue"
},
  "geometry": {"coordinates":[-96.95955499999999,32.860994],"type":"Point"}
}