{
  "type": "Feature",
  "properties": {
    "iso:country":"US",
    "sg:address":"3028 W Fm 1753",
    "sg:city":"Ravenna",
    "sg:classifiers":[
        {
            "category":"Manufacturing",
            "subcategory":"Pet Food",
            "type":"Manufacturing & Wholesale Goods"
        },
        {
            "category":"Farming",
            "subcategory":"Livestock Farm",
            "type":"Manufacturing & Wholesale Goods"
        },
        {
            "category":"Farming",
            "subcategory":"Farm",
            "type":"Manufacturing & Wholesale Goods"
        }
    ],
    "sg:phone":"+1 903 583 5172",
    "sg:postcode":"75476",
    "sg:province":"TX",
    "sg:tags":[
        "hay",
        "ranch"
    ],
    "wof:name":"Shaul Farm",
    "wof:placetype":"venue"
},
  "geometry": {"coordinates":[-96.226446,33.673482],"type":"Point"}
}