{
  "type": "Feature",
  "properties": {
    "iso:country":"US",
    "sg:address":"142 N Valley Oaks Cir",
    "sg:city":"Spring",
    "sg:classifiers":[
        {
            "category":"Real Estate",
            "subcategory":"Real Estate Services",
            "type":"Services"
        },
        {
            "category":"Real Estate",
            "subcategory":"Real Estate Agent",
            "type":"Services"
        }
    ],
    "sg:phone":"+1 281 705 2486",
    "sg:postcode":"77382",
    "sg:province":"TX",
    "sg:tags":[
        "buyer",
        "broker"
    ],
    "wof:name":"John Martin Real Estate",
    "wof:placetype":"venue"
},
  "geometry": {"coordinates":[-95.505379,30.214842],"type":"Point"}
}