{
  "type": "Feature",
  "properties": {
    "iso:country":"US",
    "sg:address":"905 Sagebrush Dr",
    "sg:city":"Austin",
    "sg:classifiers":[
        {
            "category":"Retail",
            "subcategory":"Auto Repair",
            "type":"Services"
        }
    ],
    "sg:phone":"+1 512 837 3874",
    "sg:postcode":"78758",
    "sg:province":"TX",
    "sg:tags":[
        "repairing",
        "automobile"
    ],
    "wof:name":"Qualitech Automotive",
    "wof:placetype":"venue"
},
  "geometry": {"coordinates":[-97.69259599999999,30.3741],"type":"Point"}
}