{
  "type": "Feature",
  "properties": {
    "iso:country":"US",
    "sg:address":"2257 Deer Path Dr",
    "sg:city":"Dallas",
    "sg:classifiers":[
        {
            "category":"Banks & Credit Unions",
            "subcategory":"Financial Services",
            "type":"Services"
        }
    ],
    "sg:phone":"+1 214 371 7033",
    "sg:postcode":"75216",
    "sg:province":"TX",
    "sg:tags":[
        "investor"
    ],
    "wof:name":"Fort Worth Investment Group",
    "wof:placetype":"venue"
},
  "geometry": {"coordinates":[-96.79115,32.712296],"type":"Point"}
}