{
  "type": "Feature",
  "properties": {
    "iso:country":"US",
    "sg:address":"1510 Sarazen Ct",
    "sg:city":"Laredo",
    "sg:classifiers":[
        {
            "category":"Shopping",
            "subcategory":"Clothing, Apparel, & Fashions",
            "type":"Retail Goods"
        }
    ],
    "sg:phone":"+1 956 725 0224",
    "sg:postcode":"78045",
    "sg:province":"TX",
    "wof:name":"Galleria",
    "wof:placetype":"venue"
},
  "geometry": {"coordinates":[-99.470007,27.584505],"type":"Point"}
}