{
  "type": "Feature",
  "properties": {
    "iso:country":"US",
    "sg:address":"2307 Rosefield Dr",
    "sg:city":"Houston",
    "sg:classifiers":[
        {
            "category":"Health Services",
            "subcategory":"Doctor",
            "type":"Services"
        }
    ],
    "sg:phone":"+1 713 827 4711",
    "sg:postcode":"77080",
    "sg:province":"TX",
    "wof:name":"Brunson Nathan MD",
    "wof:placetype":"venue"
},
  "geometry": {"coordinates":[-95.537852,29.812375],"type":"Point"}
}