{
  "type": "Feature",
  "properties": {
    "iso:country":"US",
    "sg:address":"2009 Brazos Ct",
    "sg:city":"Mission",
    "sg:classifiers":[
        {
            "category":"Food & Beverages",
            "subcategory":"Groceries & Convenience Stores",
            "type":"Retail Goods"
        }
    ],
    "sg:phone":"+1 956 580 3869",
    "sg:postcode":"78572",
    "sg:province":"TX",
    "sg:tags":[
        "product"
    ],
    "wof:name":"Rogali International Food",
    "wof:placetype":"venue"
},
  "geometry": {"coordinates":[-98.296126,26.193936],"type":"Point"}
}