{
  "type": "Feature",
  "properties": {
    "iso:country":"US",
    "sg:address":"214 N Ave D",
    "sg:city":"Clifton",
    "sg:classifiers":[
        {
            "category":"Health Services",
            "subcategory":"Clinic",
            "type":"Services"
        }
    ],
    "sg:phone":"+1 254 675 8305",
    "sg:postcode":"76634",
    "sg:province":"TX",
    "sg:tags":[
        "home"
    ],
    "wof:name":"Cen Tex Home Care Inc",
    "wof:placetype":"venue"
},
  "geometry": {"coordinates":[-97.575186,31.78533],"type":"Point"}
}