{
  "type": "Feature",
  "properties": {
    "iso:country":"US",
    "sg:address":"3013 Co Rd 3815",
    "sg:city":"Athens",
    "sg:classifiers":[
        {
            "category":"Building & Trades",
            "subcategory":"Construction",
            "type":"Services"
        }
    ],
    "sg:phone":"+1 903 670 3446",
    "sg:postcode":"75752",
    "sg:province":"TX",
    "sg:tags":[
        "excavation",
        "contractor"
    ],
    "wof:name":"Daniel Asphalt Paving Co",
    "wof:placetype":"venue"
},
  "geometry": {"coordinates":[-95.812556,32.265771],"type":"Point"}
}