{
  "type": "Feature",
  "properties": {
    "iso:country":"US",
    "sg:address":"915 One Oak Chase Rd",
    "sg:city":"Rosharon",
    "sg:classifiers":[
        {
            "category":"Building & Trades",
            "subcategory":"Construction",
            "type":"Services"
        }
    ],
    "sg:phone":"+1 281 431 2382",
    "sg:postcode":"77583",
    "sg:province":"TX",
    "sg:tags":[
        "hanging",
        "contractor"
    ],
    "wof:name":"Ferrel Fence Contractor",
    "wof:placetype":"venue"
},
  "geometry": {"coordinates":[-95.481398,29.49464],"type":"Point"}
}