{
  "type": "Feature",
  "properties": {
    "iso:country":"US",
    "sg:address":"3821 Kimberly Dr",
    "sg:city":"Pearland",
    "sg:classifiers":[
        {
            "category":"Personal",
            "type":"Services"
        }
    ],
    "sg:phone":"+1 281 992 0618",
    "sg:postcode":"77581",
    "sg:province":"TX",
    "wof:name":"Autumn Grupp",
    "wof:placetype":"venue"
},
  "geometry": {"coordinates":[-95.22063799999999,29.535258],"type":"Point"}
}