{
  "type": "Feature",
  "properties": {
    "iso:country":"US",
    "sg:address":"122 S Commercial St",
    "sg:city":"Goliad",
    "sg:classifiers":[
        {
            "category":"Government",
            "subcategory":"Office",
            "type":"Public Place"
        }
    ],
    "sg:phone":"+1 361 645 3572",
    "sg:postcode":"77963",
    "sg:province":"TX",
    "sg:tags":[
        "state",
        "resource"
    ],
    "wof:name":"Children's Protective Svc",
    "wof:placetype":"venue"
},
  "geometry": {"coordinates":[-97.392668,28.667964],"type":"Point"}
}