{
  "type": "Feature",
  "properties": {
    "iso:country":"US",
    "sg:address":"100 S Front St",
    "sg:city":"Kyle",
    "sg:classifiers":[
        {
            "category":"Government",
            "subcategory":"Police Station",
            "type":"Public Place"
        }
    ],
    "sg:phone":"+1 512 268 0349",
    "sg:postcode":"78640",
    "sg:province":"TX",
    "sg:tags":[
        "sheriff"
    ],
    "wof:name":"Hays County Sheriff Office",
    "wof:placetype":"venue"
},
  "geometry": {"coordinates":[-97.875366,29.98855],"type":"Point"}
}