{
  "type": "Feature",
  "properties": {
    "iso:country":"US",
    "sg:address":"5600 W Lovers Ln",
    "sg:city":"Dallas",
    "sg:classifiers":[
        {
            "category":"Professional",
            "type":"Services"
        }
    ],
    "sg:phone":"+1 214 350 2081",
    "sg:postcode":"75209",
    "sg:province":"TX",
    "sg:tags":[
        "establishment"
    ],
    "wof:name":"John Astin Perkins Inc",
    "wof:placetype":"venue"
},
  "geometry": {"coordinates":[-96.815361,32.851161],"type":"Point"}
}