{
  "type": "Feature",
  "properties": {
    "iso:country":"US",
    "sg:address":"509 W Redd Rd",
    "sg:city":"El Paso",
    "sg:classifiers":[
        {
            "category":"Retail",
            "subcategory":"Laundry & Dry Cleaning",
            "type":"Services"
        }
    ],
    "sg:phone":"+1 915 760 6140",
    "sg:postcode":"79932",
    "sg:province":"TX",
    "sg:tags":[
        "power"
    ],
    "wof:name":"Laundry World",
    "wof:placetype":"venue"
},
  "geometry": {"coordinates":[-106.595608,31.859975],"type":"Point"}
}