{
  "type": "Feature",
  "properties": {
    "iso:country":"US",
    "sg:address":"344 Avenue E",
    "sg:city":"Dallas",
    "sg:classifiers":[
        {
            "category":"Organizations",
            "subcategory":"Religious Organization",
            "type":"Services"
        }
    ],
    "sg:phone":"+1 214 946 9262",
    "sg:postcode":"75203",
    "sg:province":"TX",
    "wof:name":"Steven Temple Church of God In",
    "wof:placetype":"venue"
},
  "geometry": {"coordinates":[-96.794183,32.743664],"type":"Point"}
}