{
  "type": "Feature",
  "properties": {
    "iso:country":"US",
    "sg:address":"308 Cincinnati Ave",
    "sg:city":"El Paso",
    "sg:classifiers":[
        {
            "category":"Health Services",
            "subcategory":"Doctor",
            "type":"Services"
        }
    ],
    "sg:phone":"+1 915 533 4427",
    "sg:postcode":"79902",
    "sg:province":"TX",
    "sg:tags":[
        "dentist"
    ],
    "wof:name":"Francisco A Vargas Inc",
    "wof:placetype":"venue"
},
  "geometry": {"coordinates":[-106.501452,31.777941],"type":"Point"}
}