{
  "type": "Feature",
  "properties": {
    "iso:country":"US",
    "sg:address":"2410 Texas Ave S",
    "sg:city":"College Station",
    "sg:classifiers":[
        {
            "category":"Shopping",
            "subcategory":"Books",
            "type":"Retail Goods"
        }
    ],
    "sg:phone":"+1 979 696 2325",
    "sg:postcode":"77840",
    "sg:province":"TX",
    "wof:name":"Half Price Books Rec Magazines",
    "wof:placetype":"venue"
},
  "geometry": {"coordinates":[-96.310186,30.608207],"type":"Point"}
}