{
  "type": "Feature",
  "properties": {
    "iso:country":"US",
    "sg:address":"4348 Carter Creek Pkwy",
    "sg:city":"Bryan",
    "sg:classifiers":[
        {
            "category":"Professional",
            "subcategory":"Business Services",
            "type":"Services"
        }
    ],
    "sg:phone":"+1 979 268 3848",
    "sg:postcode":"77802",
    "sg:province":"TX",
    "sg:tags":[
        "drafting"
    ],
    "wof:name":"Kissinger Drafting & Design",
    "wof:placetype":"venue"
},
  "geometry": {"coordinates":[-96.331397,30.64445],"type":"Point"}
}