{
  "type": "Feature",
  "properties": {
    "iso:country":"US",
    "sg:address":"3390 Harrison Ave",
    "sg:city":"Beaumont",
    "sg:classifiers":[
        {
            "category":"Building & Trades",
            "subcategory":"Cleaning & Sanitation",
            "type":"Services"
        }
    ],
    "sg:phone":"+1 409 892 2235",
    "sg:postcode":"77702",
    "sg:province":"TX",
    "sg:tags":[
        "janitor"
    ],
    "wof:name":"Towers Elite Svc",
    "wof:placetype":"venue"
},
  "geometry": {"coordinates":[-94.136546,30.089549],"type":"Point"}
}