{
  "type": "Feature",
  "properties": {
    "iso:country":"US",
    "sg:address":"3355 International Blvd",
    "sg:city":"Brownsville",
    "sg:classifiers":[
        {
            "category":"Fast Food",
            "type":"Food & Drink"
        },
        {
            "category":"Restaurant",
            "type":"Food & Drink"
        }
    ],
    "sg:phone":"+1 956 544 5999",
    "sg:postcode":"78521",
    "sg:province":"TX",
    "sg:tags":[
        "american",
        "hot",
        "hamburger",
        "dog"
    ],
    "sg:website":"http://www.jackinthebox.com",
    "wof:name":"Jack in the Box",
    "wof:placetype":"venue"
},
  "geometry": {"coordinates":[-97.484039,25.90506],"type":"Point"}
}