{
  "type": "Feature",
  "properties": {
    "iso:country":"US",
    "sg:address":"124 Oak Springs Dr",
    "sg:city":"New Braunfels",
    "sg:classifiers":[
        {
            "category":"Retail",
            "subcategory":"Repair Shop",
            "type":"Services"
        }
    ],
    "sg:phone":"+1 830 899 7107",
    "sg:postcode":"78133",
    "sg:province":"TX",
    "sg:tags":[
        "refrigeration"
    ],
    "wof:name":"Kool-It Refrigeration",
    "wof:placetype":"venue"
},
  "geometry": {"coordinates":[-98.287674,29.87217],"type":"Point"}
}