{
  "type": "Feature",
  "properties": {
    "iso:country":"US",
    "sg:address":"221 Airport Rd",
    "sg:city":"Kenedy",
    "sg:classifiers":[
        {
            "category":"Professional",
            "subcategory":"Engineering",
            "type":"Services"
        }
    ],
    "sg:phone":"+1 830 583 9237",
    "sg:postcode":"78119",
    "sg:province":"TX",
    "sg:tags":[
        "consulting",
        "engineer"
    ],
    "wof:name":"Select Energy Services",
    "wof:placetype":"venue"
},
  "geometry": {"coordinates":[-97.861491,28.82711],"type":"Point"}
}