{
  "type": "Feature",
  "properties": {
    "iso:country":"US",
    "sg:address":"18022 Upper Bay Rd",
    "sg:city":"Houston",
    "sg:classifiers":[
        {
            "category":"Restaurant",
            "type":"Food & Drink"
        }
    ],
    "sg:menulink":"http://www.allmenus.com/tx/houston/139493-quiznos-sub/menu/",
    "sg:phone":"+1 281 335 7174",
    "sg:postcode":"77058",
    "sg:province":"TX",
    "sg:tags":[
        "wrap",
        "american",
        "sandwich"
    ],
    "wof:name":"Quiznos Sub",
    "wof:placetype":"venue"
},
  "geometry": {"coordinates":[-95.09003199999999,29.55076],"type":"Point"}
}