{
  "type": "Feature",
  "properties": {
    "iso:country":"US",
    "sg:address":"2889 State Hwy 19",
    "sg:city":"Huntsville",
    "sg:classifiers":[
        {
            "category":"Shopping",
            "subcategory":"Used Merchandise",
            "type":"Retail Goods"
        }
    ],
    "sg:phone":"+1 936 291 0267",
    "sg:postcode":"77320",
    "sg:province":"TX",
    "sg:tags":[
        "shop",
        "consignment"
    ],
    "wof:name":"Thee Hospice Shop",
    "wof:placetype":"venue"
},
  "geometry": {"coordinates":[-95.457059,30.798125],"type":"Point"}
}