{
  "type": "Feature",
  "properties": {
    "iso:country":"US",
    "sg:address":"13307 Rowe Dr",
    "sg:city":"San Antonio",
    "sg:classifiers":[
        {
            "category":"Utilities",
            "subcategory":"Cable",
            "type":"Services"
        }
    ],
    "sg:phone":"+1 210 491 4441",
    "sg:postcode":"78247",
    "sg:province":"TX",
    "sg:tags":[
        "television"
    ],
    "wof:name":"Cable & Computer Communication",
    "wof:placetype":"venue"
},
  "geometry": {"coordinates":[-98.43568,29.563563],"type":"Point"}
}