{
  "type": "Feature",
  "properties": {
    "iso:country":"US",
    "sg:address":"214 S Main St Ste 103-104",
    "sg:city":"Duncanville",
    "sg:classifiers":[
        {
            "category":"Personal",
            "subcategory":"Beauty Salon",
            "type":"Services"
        }
    ],
    "sg:phone":"+1 972 780 2660",
    "sg:postcode":"75116",
    "sg:province":"TX",
    "sg:website":"http://www.perfectlooksalons.com",
    "wof:name":"Perfect Look Salons",
    "wof:placetype":"venue"
},
  "geometry": {"coordinates":[-96.908449,32.650632],"type":"Point"}
}