{
  "type": "Feature",
  "properties": {
    "iso:country":"US",
    "sg:address":"2125 Augusta Dr",
    "sg:city":"Houston",
    "sg:classifiers":[
        {
            "category":"Banks & Credit Unions",
            "subcategory":"Investment Brokerage",
            "type":"Services"
        }
    ],
    "sg:phone":"+1 713 785 4675",
    "sg:postcode":"77057",
    "sg:province":"TX",
    "sg:tags":[
        "advisory"
    ],
    "wof:name":"Legacy Financial Services",
    "wof:placetype":"venue"
},
  "geometry": {"coordinates":[-95.482499,29.745279],"type":"Point"}
}