{
  "type": "Feature",
  "properties": {
    "iso:country":"US",
    "sg:address":"10025 Plano Rd",
    "sg:city":"Dallas",
    "sg:classifiers":[
        {
            "category":"Home & Garden",
            "subcategory":"Garden Supply",
            "type":"Retail Goods"
        },
        {
            "category":"Building & Trades",
            "subcategory":"Landscaping Services",
            "type":"Services"
        }
    ],
    "sg:phone":"+1 214 348 0810",
    "sg:postcode":"75238",
    "sg:province":"TX",
    "sg:tags":[
        "grass",
        "sod"
    ],
    "wof:name":"Miller Grass Co",
    "wof:placetype":"venue"
},
  "geometry": {"coordinates":[-96.70053799999999,32.885087],"type":"Point"}
}