{
  "type": "Feature",
  "properties": {
    "iso:country":"US",
    "sg:address":"1200 1st St",
    "sg:city":"Floresville",
    "sg:classifiers":[
        {
            "category":"Government",
            "subcategory":"Office",
            "type":"Public Place"
        }
    ],
    "sg:phone":"+1 830 393 0579",
    "sg:postcode":"78114",
    "sg:province":"TX",
    "sg:tags":[
        "village"
    ],
    "wof:name":"Floresville City Mechanic Shop",
    "wof:placetype":"venue"
},
  "geometry": {"coordinates":[-98.162515,29.133605],"type":"Point"}
}