{
  "type": "Feature",
  "properties": {
    "iso:country":"US",
    "sg:address":"1315 Virgie Joe Dr",
    "sg:city":"Mesquite",
    "sg:classifiers":[
        {
            "category":"Professional",
            "type":"Services"
        }
    ],
    "sg:phone":"+1 972 289 6756",
    "sg:postcode":"75149",
    "sg:province":"TX",
    "wof:name":"North Central Texas Permi",
    "wof:placetype":"venue"
},
  "geometry": {"coordinates":[-96.57641,32.749896],"type":"Point"}
}