{
  "type": "Feature",
  "properties": {
    "iso:country":"US",
    "sg:address":"101 S Gordon St",
    "sg:city":"Bryan",
    "sg:classifiers":[
        {
            "category":"Building & Trades",
            "subcategory":"Construction",
            "type":"Services"
        }
    ],
    "sg:phone":"+1 979 779 6132",
    "sg:postcode":"77802",
    "sg:province":"TX",
    "sg:tags":[
        "fence",
        "contractor"
    ],
    "wof:name":"Rakowitz & Rakowitz",
    "wof:placetype":"venue"
},
  "geometry": {"coordinates":[-96.359183,30.666197],"type":"Point"}
}