{
  "type": "Feature",
  "properties": {
    "iso:country":"US",
    "sg:address":"700 S Main St",
    "sg:city":"Electra",
    "sg:classifiers":[
        {
            "category":"Education",
            "subcategory":"School",
            "type":"Public Place"
        }
    ],
    "sg:phone":"+1 940 495 3682",
    "sg:postcode":"76360",
    "sg:province":"TX",
    "wof:name":"Dinsmore Elementary School",
    "wof:placetype":"venue"
},
  "geometry": {"coordinates":[-98.92188,34.024943],"type":"Point"}
}