{
  "type": "Feature",
  "properties": {
    "iso:country":"US",
    "sg:address":"190 S Peytonville Ave",
    "sg:city":"Southlake",
    "sg:classifiers":[
        {
            "category":"Shopping",
            "type":"Retail Goods"
        }
    ],
    "sg:phone":"+1 817 329 1500",
    "sg:postcode":"76092",
    "sg:province":"TX",
    "sg:tags":[
        "hearing",
        "equipment",
        "supply",
        "impaired"
    ],
    "wof:name":"Owens Ear Ctr",
    "wof:placetype":"venue"
},
  "geometry": {"coordinates":[-97.177153,32.939817],"type":"Point"}
}