{
  "type": "Feature",
  "properties": {
    "iso:country":"US",
    "sg:address":"2310 N Richmond Rd",
    "sg:city":"Wharton",
    "sg:classifiers":[
        {
            "category":"Shopping",
            "subcategory":"Used Merchandise",
            "type":"Retail Goods"
        },
        {
            "category":"Shopping",
            "subcategory":"Jewelry",
            "type":"Retail Goods"
        }
    ],
    "sg:phone":"+1 979 532 0971",
    "sg:postcode":"77488",
    "sg:province":"TX",
    "sg:tags":[
        "personal",
        "credit",
        "pawnbroker",
        "institution"
    ],
    "wof:name":"Tyler's Jewelry & Pawn",
    "wof:placetype":"venue"
},
  "geometry": {"coordinates":[-96.094601,29.33167],"type":"Point"}
}