{
  "type": "Feature",
  "properties": {
    "iso:country":"US",
    "sg:address":"5111 Kings Hwy",
    "sg:city":"Austin",
    "sg:classifiers":[
        {
            "category":"Professional",
            "type":"Services"
        }
    ],
    "sg:phone":"+1 512 444 2728",
    "sg:postcode":"78745",
    "sg:province":"TX",
    "sg:tags":[
        "lecture",
        "speakers",
        "seminar"
    ],
    "sg:website":"http://www.askmarygordon.com",
    "wof:name":"Mary Gordon Ask",
    "wof:placetype":"venue"
},
  "geometry": {"coordinates":[-97.792013,30.21923],"type":"Point"}
}