{
  "type": "Feature",
  "properties": {
    "iso:country":"US",
    "sg:address":"797 Co Rd 660",
    "sg:city":"Devine",
    "sg:classifiers":[
        {
            "category":"Retail",
            "subcategory":"Repair Shop",
            "type":"Services"
        }
    ],
    "sg:phone":"+1 830 665 3143",
    "sg:postcode":"78016",
    "sg:province":"TX",
    "wof:name":"Bill Allen Horseshoeing",
    "wof:placetype":"venue"
},
  "geometry": {"coordinates":[-98.996954,29.157919],"type":"Point"}
}