{
  "type": "Feature",
  "properties": {
    "iso:country":"US",
    "sg:address":"2704 Rio Grande St",
    "sg:city":"Austin",
    "sg:classifiers":[
        {
            "category":"Personal",
            "subcategory":"Beauty Salon",
            "type":"Services"
        }
    ],
    "sg:phone":"+1 512 472 6567",
    "sg:postcode":"78705",
    "sg:province":"TX",
    "sg:tags":[
        "shop"
    ],
    "wof:name":"Color Works",
    "wof:placetype":"venue"
},
  "geometry": {"coordinates":[-97.74435099999999,30.292],"type":"Point"}
}