{
  "type": "Feature",
  "properties": {
    "iso:country":"US",
    "sg:address":"1204 Joshua Tree Dr",
    "sg:city":"Plano",
    "sg:classifiers":[
        {
            "category":"Organizations",
            "subcategory":"Professional Association",
            "type":"Services"
        }
    ],
    "sg:phone":"+1 972 423 9595",
    "sg:postcode":"75023",
    "sg:province":"TX",
    "sg:tags":[
        "business"
    ],
    "wof:name":"Marilyn Fowler & Associates",
    "wof:placetype":"venue"
},
  "geometry": {"coordinates":[-96.71619,33.044131],"type":"Point"}
}