{
  "type": "Feature",
  "properties": {
    "iso:country":"US",
    "sg:address":"1118 Vance Jackson Rd",
    "sg:city":"San Antonio",
    "sg:classifiers":[
        {
            "category":"Coffee & Tea",
            "type":"Food & Drink"
        }
    ],
    "sg:menulink":"http://www.allmenus.com/tx/san-antonio/113131-starbucks-coffee/menu/",
    "sg:phone":"+1 210 785 9594",
    "sg:postcode":"78201",
    "sg:province":"TX",
    "sg:tags":[
        "american"
    ],
    "wof:name":"Starbucks Coffee",
    "wof:placetype":"venue"
},
  "geometry": {"coordinates":[-98.53443300000001,29.484092],"type":"Point"}
}