{
  "type": "Feature",
  "properties": {
    "iso:country":"US",
    "sg:address":"9444 Nottingham Dr",
    "sg:city":"El Paso",
    "sg:classifiers":[
        {
            "category":"Professional",
            "type":"Services"
        }
    ],
    "sg:phone":"+1 915 860 0241",
    "sg:postcode":"79907",
    "sg:province":"TX",
    "wof:name":"Mirellas",
    "wof:placetype":"venue"
},
  "geometry": {"coordinates":[-106.307637,31.689563],"type":"Point"}
}