{
  "type": "Feature",
  "properties": {
    "iso:country":"US",
    "sg:address":"7500 Callaghan Rd",
    "sg:city":"San Antonio",
    "sg:classifiers":[
        {
            "category":"Banks & Credit Unions",
            "subcategory":"Investment Brokerage",
            "type":"Services"
        }
    ],
    "sg:phone":"+1 210 341 1156",
    "sg:postcode":"78229",
    "sg:province":"TX",
    "wof:name":"William Comstock Investments",
    "wof:placetype":"venue"
},
  "geometry": {"coordinates":[-98.558374,29.504952],"type":"Point"}
}