{
  "type": "Feature",
  "properties": {
    "iso:country":"US",
    "sg:address":"6811 Heatherknoll Dr",
    "sg:city":"Dallas",
    "sg:classifiers":[
        {
            "category":"Travel",
            "subcategory":"Travel Agent",
            "type":"Entertainment"
        }
    ],
    "sg:phone":"+1 214 750 9390",
    "sg:postcode":"75248",
    "sg:province":"TX",
    "sg:tags":[
        "agency"
    ],
    "wof:name":"Travel Unique of Dallas Inc",
    "wof:placetype":"venue"
},
  "geometry": {"coordinates":[-96.79028099999999,32.950744],"type":"Point"}
}