{
  "type": "Feature",
  "properties": {
    "iso:country":"US",
    "sg:address":"9330 Katy Fwy",
    "sg:city":"Houston",
    "sg:classifiers":[
        {
            "category":"Retail",
            "subcategory":"Auto Rental",
            "type":"Services"
        }
    ],
    "sg:phone":"+1 713 984 1553",
    "sg:postcode":"77055",
    "sg:province":"TX",
    "sg:tags":[
        "car"
    ],
    "sg:website":"www.budget.com",
    "wof:name":"Budget Car Rental",
    "wof:placetype":"venue"
},
  "geometry": {"coordinates":[-95.52250100000001,29.784925],"type":"Point"}
}