{
  "type": "Feature",
  "properties": {
    "iso:country":"US",
    "sg:address":"505 Huntland Dr E",
    "sg:city":"Austin",
    "sg:classifiers":[
        {
            "category":"Professional",
            "subcategory":"Lawyer & Legal Services",
            "type":"Services"
        }
    ],
    "sg:phone":"+1 512 463 1454",
    "sg:postcode":"78752",
    "sg:province":"TX",
    "sg:tags":[
        "clinic"
    ],
    "wof:name":"Texas Board-Legal Speclztn",
    "wof:placetype":"venue"
},
  "geometry": {"coordinates":[-97.707796,30.330848],"type":"Point"}
}