{
  "type": "Feature",
  "properties": {
    "iso:country":"US",
    "sg:address":"515 Illinois",
    "sg:city":"Houston",
    "sg:classifiers":[
        {
            "category":"Home & Garden",
            "subcategory":"Household Appliances",
            "type":"Retail Goods"
        },
        {
            "category":"Building & Trades",
            "subcategory":"Plumbing",
            "type":"Services"
        },
        {
            "category":"Building & Trades",
            "subcategory":"Electrical",
            "type":"Services"
        }
    ],
    "sg:phone":"+1 713 777 7777",
    "sg:postcode":"77002",
    "sg:province":"TX",
    "sg:tags":[
        "repair",
        "electrician"
    ],
    "wof:name":"A R S-American Residential Services",
    "wof:placetype":"venue"
},
  "geometry": {"coordinates":[-95.364799,29.753901],"type":"Point"}
}