{
  "type": "Feature",
  "properties": {
    "iso:country":"US",
    "sg:address":"2008 Indian Trl",
    "sg:city":"Salado",
    "sg:classifiers":[
        {
            "category":"Building & Trades",
            "subcategory":"Landscaping Services",
            "type":"Services"
        }
    ],
    "sg:phone":"+1 254 947 0269",
    "sg:postcode":"76571",
    "sg:province":"TX",
    "wof:name":"Lawn Aeration",
    "wof:placetype":"venue"
},
  "geometry": {"coordinates":[-97.518747,30.950097],"type":"Point"}
}