{
  "type": "Feature",
  "properties": {
    "iso:country":"US",
    "sg:address":"3324 Greenbrier Dr",
    "sg:city":"Dallas",
    "sg:classifiers":[
        {
            "category":"Real Estate",
            "subcategory":"Real Estate Agent",
            "type":"Services"
        }
    ],
    "sg:phone":"+1 214 363 6681",
    "sg:postcode":"75225",
    "sg:province":"TX",
    "wof:name":"Joan Ochel Realtor",
    "wof:placetype":"venue"
},
  "geometry": {"coordinates":[-96.784724,32.858196],"type":"Point"}
}