{
  "type": "Feature",
  "properties": {
    "iso:country":"US",
    "sg:address":"1522 Laurence Dr",
    "sg:city":"Rockwall",
    "sg:classifiers":[
        {
            "category":"Building & Trades",
            "subcategory":"Construction",
            "type":"Services"
        }
    ],
    "sg:phone":"+1 972 771 3759",
    "sg:postcode":"75032",
    "sg:province":"TX",
    "sg:tags":[
        "home",
        "builder"
    ],
    "wof:name":"Hall & Hall Builders",
    "wof:placetype":"venue"
},
  "geometry": {"coordinates":[-96.470348,32.86021],"type":"Point"}
}