{
  "type": "Feature",
  "properties": {
    "iso:country":"US",
    "sg:address":"6659 State Hwy 111 S",
    "sg:city":"Edna",
    "sg:classifiers":[
        {
            "category":"Building & Trades",
            "subcategory":"Construction",
            "type":"Services"
        }
    ],
    "sg:phone":"+1 361 782 6542",
    "sg:postcode":"77957",
    "sg:province":"TX",
    "sg:tags":[
        "backhoe"
    ],
    "wof:name":"Hahns Backhoe Service",
    "wof:placetype":"venue"
},
  "geometry": {"coordinates":[-96.547101,28.953812],"type":"Point"}
}