{
  "type": "Feature",
  "properties": {
    "iso:country":"US",
    "sg:address":"5925 Lovell Ave",
    "sg:city":"Fort Worth",
    "sg:classifiers":[
        {
            "category":"Wholesale",
            "subcategory":"Electrical",
            "type":"Manufacturing & Wholesale Goods"
        }
    ],
    "sg:phone":"+1 817 263 0909",
    "sg:postcode":"76107",
    "sg:province":"TX",
    "sg:tags":[
        "lighting",
        "fixture"
    ],
    "wof:name":"Rabbit Tanaka Corp",
    "wof:placetype":"venue"
},
  "geometry": {"coordinates":[-97.41298399999999,32.731125],"type":"Point"}
}