{
  "type": "Feature",
  "properties": {
    "iso:country":"US",
    "sg:address":"1779 Wells Branch Pkwy 110B-242",
    "sg:city":"Austin",
    "sg:classifiers":[
        {
            "category":"Health Services",
            "subcategory":"Clinic",
            "type":"Services"
        }
    ],
    "sg:phone":"+1 310 430 0286",
    "sg:postcode":"78728",
    "sg:province":"TX",
    "sg:tags":[
        "medical"
    ],
    "sg:website":"www.icebergpainrelief.com",
    "wof:name":"Iceberg Pain Relief LLC",
    "wof:placetype":"venue"
},
  "geometry": {"coordinates":[-97.67441700000001,30.435445],"type":"Point"}
}