{
  "type": "Feature",
  "properties": {
    "iso:country":"US",
    "sg:address":"14416 Debbie Rd",
    "sg:city":"Dalhart",
    "sg:phone":"+1 806 362 4840",
    "sg:postcode":"79022",
    "sg:province":"TX",
    "sg:tags":[
        "farm",
        "wheat"
    ],
    "wof:name":"Danny Carter",
    "wof:placetype":"venue"
},
  "geometry": {"coordinates":[-102.881755,36.39508],"type":"Point"}
}