{
  "type": "Feature",
  "properties": {
    "iso:country":"US",
    "sg:address":"13334 Partridge Hill",
    "sg:city":"San Antonio",
    "sg:classifiers":[
        {
            "category":"Wholesale",
            "subcategory":"Medical Equipment & Supplies",
            "type":"Manufacturing & Wholesale Goods"
        }
    ],
    "sg:phone":"+1 210 403 9770",
    "sg:postcode":"78247",
    "sg:province":"TX",
    "sg:tags":[
        "hospital"
    ],
    "wof:name":"San Antonio Scooter & Power",
    "wof:placetype":"venue"
},
  "geometry": {"coordinates":[-98.437759,29.564096],"type":"Point"}
}