{
  "type": "Feature",
  "properties": {
    "iso:country":"US",
    "sg:address":"4615 Spring Shadow Dr",
    "sg:city":"Wichita Falls",
    "sg:classifiers":[
        {
            "category":"Social Services",
            "subcategory":"Child Care",
            "type":"Services"
        }
    ],
    "sg:phone":"+1 940 691 5359",
    "sg:postcode":"76310",
    "sg:province":"TX",
    "sg:tags":[
        "day"
    ],
    "wof:name":"Wee Ones",
    "wof:placetype":"venue"
},
  "geometry": {"coordinates":[-98.58309300000001,33.860787],"type":"Point"}
}