{
  "type": "Feature",
  "properties": {
    "iso:country":"US",
    "sg:address":"2447 Graham Dr S",
    "sg:city":"Arlington",
    "sg:classifiers":[
        {
            "category":"Shopping",
            "type":"Retail Goods"
        }
    ],
    "sg:phone":"+1 817 261 7493",
    "sg:postcode":"76013",
    "sg:province":"TX",
    "sg:tags":[
        "merchandise"
    ],
    "wof:name":"Patricia K Stewart",
    "wof:placetype":"venue"
},
  "geometry": {"coordinates":[-97.148399,32.727656],"type":"Point"}
}