{
  "type": "Feature",
  "properties": {
    "iso:country":"US",
    "sg:address":"3016 Marina Bay Dr",
    "sg:city":"League City",
    "sg:classifiers":[
        {
            "category":"Cinema",
            "subcategory":"Movie Rental",
            "type":"Entertainment"
        }
    ],
    "sg:phone":"+1 281 538 8011",
    "sg:postcode":"77573",
    "sg:province":"TX",
    "sg:tags":[
        "leasing",
        "video",
        "disc",
        "tape"
    ],
    "sg:website":"www.blockbuster.com",
    "wof:name":"Blockbuster Video",
    "wof:placetype":"venue"
},
  "geometry": {"coordinates":[-95.061728,29.541733],"type":"Point"}
}