{
  "type": "Feature",
  "properties": {
    "iso:country":"US",
    "sg:address":"6126 la Cosa Dr",
    "sg:city":"Dallas",
    "sg:classifiers":[
        {
            "category":"Professional",
            "subcategory":"Engineering",
            "type":"Services"
        }
    ],
    "sg:phone":"+1 972 726 0041",
    "sg:postcode":"75248",
    "sg:province":"TX",
    "sg:tags":[
        "engineer",
        "integration",
        "system"
    ],
    "wof:name":"5 Dimensions Cnstr Consulting",
    "wof:placetype":"venue"
},
  "geometry": {"coordinates":[-96.801688,32.959663],"type":"Point"}
}