{
  "type": "Feature",
  "properties": {
    "iso:country":"US",
    "sg:address":"2570 W Pioneer Pkwy",
    "sg:city":"Arlington",
    "sg:classifiers":[
        {
            "category":"Restaurant",
            "type":"Food & Drink"
        }
    ],
    "sg:menulink":"http://www.allmenus.com/tx/arlington/130645-subway/menu/",
    "sg:phone":"+1 817 804 0500",
    "sg:postcode":"76013",
    "sg:province":"TX",
    "sg:tags":[
        "american",
        "sandwich"
    ],
    "wof:name":"Subway",
    "wof:placetype":"venue"
},
  "geometry": {"coordinates":[-97.15047199999999,32.709641],"type":"Point"}
}