{
  "type": "Feature",
  "properties": {
    "iso:country":"US",
    "sg:address":"9011 John W Carpenter Fwy",
    "sg:city":"Dallas",
    "sg:classifiers":[
        {
            "category":"Manufacturing",
            "subcategory":"Printing",
            "type":"Manufacturing & Wholesale Goods"
        }
    ],
    "sg:phone":"+1 214 638 2774",
    "sg:postcode":"75247",
    "sg:province":"TX",
    "sg:tags":[
        "printer"
    ],
    "wof:name":"Texas Commerce Printing",
    "wof:placetype":"venue"
},
  "geometry": {"coordinates":[-96.883754,32.825469],"type":"Point"}
}