{
  "type": "Feature",
  "properties": {
    "iso:country":"US",
    "sg:address":"7324 Skillman St",
    "sg:city":"Dallas",
    "sg:classifiers":[
        {
            "category":"Real Estate",
            "subcategory":"Real Estate Operator",
            "type":"Services"
        }
    ],
    "sg:phone":"+1 214 553 4200",
    "sg:postcode":"75231",
    "sg:province":"TX",
    "sg:tags":[
        "apartment"
    ],
    "sg:website":"www.cncinvestments.com",
    "wof:name":"Huntington Lakes",
    "wof:placetype":"venue"
},
  "geometry": {"coordinates":[-96.734472,32.88251],"type":"Point"}
}