{
  "type": "Feature",
  "properties": {
    "iso:country":"US",
    "sg:address":"11903 Coit Rd Apt 203T",
    "sg:city":"Dallas",
    "sg:classifiers":[
        {
            "category":"Retail",
            "subcategory":"Auto Repair",
            "type":"Services"
        }
    ],
    "sg:phone":"+1 972 385 0515",
    "sg:postcode":"75251",
    "sg:province":"TX",
    "sg:tags":[
        "body",
        "automobile",
        "painting",
        "repairing"
    ],
    "wof:name":"Elegant Body Shaper",
    "wof:placetype":"venue"
},
  "geometry": {"coordinates":[-96.769363,32.910574],"type":"Point"}
}