{
  "type": "Feature",
  "properties": {
    "iso:country":"US",
    "sg:address":"4054 Fresenius Rd",
    "sg:city":"Silsbee",
    "sg:classifiers":[
        {
            "category":"Arts & Performance",
            "subcategory":"Theater",
            "type":"Entertainment"
        }
    ],
    "sg:phone":"+1 409 385 8939",
    "sg:postcode":"77656",
    "sg:province":"TX",
    "sg:tags":[
        "bureau"
    ],
    "wof:name":"Cook's Entertainment Plaza",
    "wof:placetype":"venue"
},
  "geometry": {"coordinates":[-94.216612,30.358921],"type":"Point"}
}