{
  "type": "Feature",
  "properties": {
    "iso:country":"US",
    "sg:address":"1010 W Airport Fwy",
    "sg:city":"Euless",
    "sg:classifiers":[
        {
            "category":"Autos & Motor Vehicles",
            "subcategory":"Fuel & Gas Station",
            "type":"Retail Goods"
        }
    ],
    "sg:phone":"+1 817 571 0129",
    "sg:postcode":"76039",
    "sg:province":"TX",
    "sg:tags":[
        "grocery",
        "station",
        "gasoline",
        "oil"
    ],
    "wof:name":"Euless Mobile",
    "wof:placetype":"venue"
},
  "geometry": {"coordinates":[-97.099852,32.838045],"type":"Point"}
}