{
  "type": "Feature",
  "properties": {
    "iso:country":"US",
    "sg:address":"302 S Timberland Dr",
    "sg:city":"Lufkin",
    "sg:classifiers":[
        {
            "category":"Restaurant",
            "type":"Food & Drink"
        }
    ],
    "sg:phone":"+1 936 634 9091",
    "sg:postcode":"75901",
    "sg:province":"TX",
    "sg:tags":[
        "eating"
    ],
    "wof:name":"Chen's China Inn",
    "wof:placetype":"venue"
},
  "geometry": {"coordinates":[-94.720097,31.333509],"type":"Point"}
}