{
  "type": "Feature",
  "properties": {
    "iso:country":"US",
    "sg:address":"4815 W Braker Ln Ste 510",
    "sg:city":"Austin",
    "sg:classifiers":[
        {
            "category":"Restaurant",
            "type":"Food & Drink"
        }
    ],
    "sg:phone":"+1 512 794 8772",
    "sg:postcode":"78759",
    "sg:province":"TX",
    "sg:tags":[
        "chinese"
    ],
    "wof:name":"Twin Lion Chinese Restaurant",
    "wof:placetype":"venue"
},
  "geometry": {"coordinates":[-97.746803,30.4007],"type":"Point"}
}