{
  "type": "Feature",
  "properties": {
    "iso:country":"US",
    "sg:address":"9669 N Central Expy",
    "sg:city":"Dallas",
    "sg:classifiers":[
        {
            "category":"Health Services",
            "subcategory":"Dentist",
            "type":"Services"
        }
    ],
    "sg:phone":"+1 214 696 9966",
    "sg:postcode":"75231",
    "sg:province":"TX",
    "wof:name":"Cothern Ashly Dr",
    "wof:placetype":"venue"
},
  "geometry": {"coordinates":[-96.770853,32.87924],"type":"Point"}
}