{
  "type": "Feature",
  "properties": {
    "iso:country":"US",
    "sg:address":"1606 Dywer Ave",
    "sg:city":"Austin",
    "sg:classifiers":[
        {
            "category":"Communications",
            "subcategory":"Film & Video Production",
            "type":"Services"
        }
    ],
    "sg:phone":"+1 512 441 0737",
    "sg:postcode":"78704",
    "sg:province":"TX",
    "sg:tags":[
        "motion",
        "picture",
        "taping"
    ],
    "sg:website":"www.bigkids.com",
    "wof:name":"Big Kids Productions Inc",
    "wof:placetype":"venue"
},
  "geometry": {"coordinates":[-97.76700200000001,30.255916],"type":"Point"}
}