{
  "type": "Feature",
  "properties": {
    "iso:country":"US",
    "sg:address":"4 Regency Ct",
    "sg:city":"Conroe",
    "sg:classifiers":[
        {
            "category":"Wholesale",
            "subcategory":"Toys & Hobbies",
            "type":"Manufacturing & Wholesale Goods"
        }
    ],
    "sg:phone":"+1 936 539 5593",
    "sg:postcode":"77304",
    "sg:province":"TX",
    "wof:name":"Conroe Industrial Automat",
    "wof:placetype":"venue"
},
  "geometry": {"coordinates":[-95.477417,30.288514],"type":"Point"}
}