{
  "type": "Feature",
  "properties": {
    "iso:country":"US",
    "sg:address":"21201 Kathy Ln",
    "sg:city":"Spicewood",
    "sg:classifiers":[
        {
            "category":"Professional",
            "type":"Services"
        }
    ],
    "sg:phone":"+1 512 388 4961",
    "sg:postcode":"78669",
    "sg:province":"TX",
    "sg:tags":[
        "establishment"
    ],
    "wof:name":"J Lynne Studio's",
    "wof:placetype":"venue"
},
  "geometry": {"coordinates":[-98.048678,30.379046],"type":"Point"}
}