{
  "type": "Feature",
  "properties": {
    "iso:country":"US",
    "sg:address":"9725 Kempwood Dr",
    "sg:city":"Houston",
    "sg:classifiers":[
        {
            "category":"Education",
            "subcategory":"School",
            "type":"Public Place"
        }
    ],
    "sg:phone":"+1 713 462 7343",
    "sg:postcode":"77080",
    "sg:province":"TX",
    "wof:name":"Spring Shadows Elementary",
    "wof:placetype":"venue"
},
  "geometry": {"coordinates":[-95.531898,29.821699],"type":"Point"}
}