{
  "type": "Feature",
  "properties": {
    "iso:country":"US",
    "sg:address":"6340 Co Rd 488",
    "sg:city":"Nevada",
    "sg:classifiers":[
        {
            "category":"Manufacturing",
            "subcategory":"Building Materials",
            "type":"Manufacturing & Wholesale Goods"
        }
    ],
    "sg:phone":"+1 972 843 2800",
    "sg:postcode":"75173",
    "sg:province":"TX",
    "wof:name":"Surewood Interior Millwork I",
    "wof:placetype":"venue"
},
  "geometry": {"coordinates":[-96.44499,33.070847],"type":"Point"}
}