{
  "type": "Feature",
  "properties": {
    "iso:country":"US",
    "sg:address":"18885 Colonel Fisher Blvd",
    "sg:city":"Houston",
    "sg:classifiers":[
        {
            "category":"Airport",
            "type":"Transportation"
        }
    ],
    "sg:phone":"+1 281 553 6300",
    "sg:postcode":"77032",
    "sg:province":"TX",
    "sg:tags":[
        "equipment",
        "maintenance",
        "structural"
    ],
    "wof:name":"FMC Technologies Inc",
    "wof:placetype":"venue"
},
  "geometry": {"coordinates":[-95.318022,29.987569],"type":"Point"}
}