{
  "type": "Feature",
  "properties": {
    "iso:country":"US",
    "sg:address":"1600 W T C Jester Blvd",
    "sg:city":"Houston",
    "sg:classifiers":[
        {
            "category":"Shopping",
            "subcategory":"Computers & Home Electronics",
            "type":"Retail Goods"
        },
        {
            "category":"Professional",
            "subcategory":"Computer Services",
            "type":"Services"
        }
    ],
    "sg:phone":"+1 713 266 1213",
    "sg:postcode":"77008",
    "sg:province":"TX",
    "sg:tags":[
        "software",
        "programing",
        "custom"
    ],
    "wof:name":"Bozco",
    "wof:placetype":"venue"
},
  "geometry": {"coordinates":[-95.42685400000001,29.798679],"type":"Point"}
}