{
  "type": "Feature",
  "properties": {
    "iso:country":"US",
    "sg:address":"620 W Hickory St",
    "sg:city":"Denton",
    "sg:classifiers":[
        {
            "category":"Professional",
            "type":"Services"
        }
    ],
    "sg:phone":"+1 940 483 0656",
    "sg:postcode":"76201",
    "sg:province":"TX",
    "sg:tags":[
        "establishment"
    ],
    "wof:name":"Denton County Shopper",
    "wof:placetype":"venue"
},
  "geometry": {"coordinates":[-97.13828599999999,33.214665],"type":"Point"}
}