{
  "type": "Feature",
  "properties": {
    "iso:country":"US",
    "sg:address":"3061 Northaven Rd",
    "sg:city":"Dallas",
    "sg:classifiers":[
        {
            "category":"Organizations",
            "subcategory":"Religious Organization",
            "type":"Services"
        }
    ],
    "sg:phone":"+1 972 241 5079",
    "sg:postcode":"75229",
    "sg:province":"TX",
    "wof:name":"Park Jung Ung Yong Chu",
    "wof:placetype":"venue"
},
  "geometry": {"coordinates":[-96.874754,32.903998],"type":"Point"}
}