{
  "type": "Feature",
  "properties": {
    "iso:country":"US",
    "sg:address":"721 N Ann St",
    "sg:city":"Port Lavaca",
    "sg:classifiers":[
        {
            "category":"Organizations",
            "subcategory":"Religious Organization",
            "type":"Services"
        }
    ],
    "sg:phone":"+1 361 553 6652",
    "sg:postcode":"77979",
    "sg:province":"TX",
    "sg:tags":[
        "church"
    ],
    "wof:name":"Christ Community Church",
    "wof:placetype":"venue"
},
  "geometry": {"coordinates":[-96.63178499999999,28.619788],"type":"Point"}
}