{
  "type": "Feature",
  "properties": {
    "iso:country":"US",
    "sg:address":"2200 N Lamar St",
    "sg:city":"Dallas",
    "sg:classifiers":[
        {
            "category":"Arts & Performance",
            "subcategory":"Music",
            "type":"Entertainment"
        },
        {
            "category":"Restaurant",
            "type":"Food & Drink"
        },
        {
            "category":"Retail",
            "subcategory":"Event Space",
            "type":"Services"
        }
    ],
    "sg:phone":"+1 214 978 2583",
    "sg:postcode":"75202",
    "sg:province":"TX",
    "sg:tags":[
        "venue",
        "cajun/creole"
    ],
    "sg:website":"www.hob.com",
    "wof:name":"House of Blues",
    "wof:placetype":"venue"
},
  "geometry": {"coordinates":[-96.808089,32.785326],"type":"Point"}
}