{
  "type": "Feature",
  "properties": {
    "iso:country":"US",
    "sg:address":"18319 Leinad Dr",
    "sg:city":"Houston",
    "sg:classifiers":[
        {
            "category":"Insurance",
            "subcategory":"Insurance Agent",
            "type":"Services"
        }
    ],
    "sg:phone":"+1 281 440 9123",
    "sg:postcode":"77090",
    "sg:province":"TX",
    "wof:name":"Allstate",
    "wof:placetype":"venue"
},
  "geometry": {"coordinates":[-95.45259799999999,30.035155],"type":"Point"}
}