{
  "type": "Feature",
  "properties": {
    "iso:country":"US",
    "sg:address":"2207 Windsor Dr",
    "sg:city":"Richardson",
    "sg:classifiers":[
        {
            "category":"Building & Trades",
            "subcategory":"Construction",
            "type":"Services"
        }
    ],
    "sg:phone":"+1 972 234 1650",
    "sg:postcode":"75082",
    "sg:province":"TX",
    "sg:tags":[
        "house"
    ],
    "wof:name":"T4r Homes Inc",
    "wof:placetype":"venue"
},
  "geometry": {"coordinates":[-96.691827,32.978704],"type":"Point"}
}