{
  "type": "Feature",
  "properties": {
    "iso:country":"US",
    "sg:address":"13006 US Hwy 281",
    "sg:city":"Santo",
    "sg:classifiers":[
        {
            "category":"Home & Garden",
            "subcategory":"Furniture",
            "type":"Retail Goods"
        }
    ],
    "sg:phone":"+1 940 769 2807",
    "sg:postcode":"76472",
    "sg:province":"TX",
    "wof:name":"Sleep Safe LLC",
    "wof:placetype":"venue"
},
  "geometry": {"coordinates":[-98.101226,32.640842],"type":"Point"}
}