{
  "type": "Feature",
  "properties": {
    "iso:country":"US",
    "sg:address":"3441 Bridgette Ln",
    "sg:city":"Baytown",
    "sg:classifiers":[
        {
            "category":"Building & Trades",
            "subcategory":"Electrical",
            "type":"Services"
        }
    ],
    "sg:phone":"+1 281 576 0515",
    "sg:postcode":"77520",
    "sg:province":"TX",
    "sg:tags":[
        "electrical",
        "contractor"
    ],
    "wof:name":"Jt Electric",
    "wof:placetype":"venue"
},
  "geometry": {"coordinates":[-94.85724999999999,29.846126],"type":"Point"}
}