{
  "type": "Feature",
  "properties": {
    "iso:country":"US",
    "sg:address":"6705 Levelland Rd",
    "sg:city":"Dallas",
    "sg:classifiers":[
        {
            "category":"Professional",
            "subcategory":"Engineering",
            "type":"Services"
        }
    ],
    "sg:phone":"+1 972 248 3214",
    "sg:postcode":"75252",
    "sg:province":"TX",
    "sg:tags":[
        "engineer"
    ],
    "wof:name":"Ewave",
    "wof:placetype":"venue"
},
  "geometry": {"coordinates":[-96.792666,32.98892],"type":"Point"}
}