{
  "type": "Feature",
  "properties": {
    "iso:country":"US",
    "sg:address":"17445 John F Kennedy Blvd",
    "sg:city":"Houston",
    "sg:classifiers":[
        {
            "category":"Transit Center",
            "subcategory":"Freight",
            "type":"Transportation"
        },
        {
            "category":"Airline",
            "type":"Transportation"
        }
    ],
    "sg:phone":"+1 832 353 1000",
    "sg:postcode":"77032",
    "sg:province":"TX",
    "sg:tags":[
        "air",
        "cargo",
        "express",
        "package"
    ],
    "sg:website":"http://www.continental.com",
    "wof:name":"Continental Airlines",
    "wof:placetype":"venue"
},
  "geometry": {"coordinates":[-95.33653,29.967126],"type":"Point"}
}