{
  "type": "Feature",
  "properties": {
    "iso:country":"US",
    "sg:address":"1038 W Kings Hwy",
    "sg:city":"San Antonio",
    "sg:classifiers":[
        {
            "category":"Building & Trades",
            "subcategory":"Construction",
            "type":"Services"
        }
    ],
    "sg:phone":"+1 210 733 7650",
    "sg:postcode":"78201",
    "sg:province":"TX",
    "sg:tags":[
        "contractor"
    ],
    "wof:name":"John Mlncon Hndyman Rstoration",
    "wof:placetype":"venue"
},
  "geometry": {"coordinates":[-98.511228,29.459555],"type":"Point"}
}