{
  "type": "Feature",
  "properties": {
    "iso:country":"US",
    "sg:address":"736 FM 1092",
    "sg:city":"Stafford",
    "sg:classifiers":[
        {
            "category":"Education",
            "subcategory":"Special Training",
            "type":"Public Place"
        }
    ],
    "sg:phone":"+1 281 499 7056",
    "sg:postcode":"77477",
    "sg:province":"TX",
    "wof:name":"Starks Ernest K",
    "wof:placetype":"venue"
},
  "geometry": {"coordinates":[-95.564526,29.608807],"type":"Point"}
}