{
  "type": "Feature",
  "properties": {
    "iso:country":"US",
    "sg:address":"6200 Richmond Ave",
    "sg:city":"Houston",
    "sg:classifiers":[
        {
            "category":"Freight",
            "type":"Transportation"
        }
    ],
    "sg:phone":"+1 713 781 8086",
    "sg:postcode":"77057",
    "sg:province":"TX",
    "sg:tags":[
        "operator",
        "local",
        "trucking"
    ],
    "wof:name":"Gulf Central Moving Services",
    "wof:placetype":"venue"
},
  "geometry": {"coordinates":[-95.493235,29.731762],"type":"Point"}
}