{
  "type": "Feature",
  "properties": {
    "iso:country":"US",
    "sg:address":"4901 Bosque Blvd",
    "sg:city":"Waco",
    "sg:classifiers":[
        {
            "category":"Banks & Credit Unions",
            "subcategory":"Bank",
            "type":"Services"
        }
    ],
    "sg:phone":"+1 254 751 3491",
    "sg:postcode":"76710",
    "sg:province":"TX",
    "sg:tags":[
        "national",
        "commercial"
    ],
    "wof:name":"Bank Of America",
    "wof:placetype":"venue"
},
  "geometry": {"coordinates":[-97.189852,31.534796],"type":"Point"}
}