{
  "type": "Feature",
  "properties": {
    "iso:country":"US",
    "sg:address":"107 E Calhoun St",
    "sg:city":"El Campo",
    "sg:classifiers":[
        {
            "category":"Insurance",
            "subcategory":"Insurance Agent",
            "type":"Services"
        }
    ],
    "sg:phone":"+1 979 543 6235",
    "sg:postcode":"77437",
    "sg:province":"TX",
    "wof:name":"Wright Insurance",
    "wof:placetype":"venue"
},
  "geometry": {"coordinates":[-96.2704,29.199168],"type":"Point"}
}