{
  "type": "Feature",
  "properties": {
    "iso:country":"US",
    "sg:address":"7112 Halprin Ct",
    "sg:city":"Dallas",
    "sg:classifiers":[
        {
            "category":"Professional",
            "type":"Services"
        }
    ],
    "sg:phone":"+1 972 250 0568",
    "sg:postcode":"75252",
    "sg:province":"TX",
    "wof:name":"Bmr Concepts Inc",
    "wof:placetype":"venue"
},
  "geometry": {"coordinates":[-96.78013,32.99621],"type":"Point"}
}