{
  "type": "Feature",
  "properties": {
    "iso:country":"US",
    "sg:address":"9786 Skillman St",
    "sg:city":"Dallas",
    "sg:classifiers":[
        {
            "category":"Education",
            "subcategory":"School",
            "type":"Public Place"
        }
    ],
    "sg:phone":"+1 214 341 0045",
    "sg:postcode":"75243",
    "sg:province":"TX",
    "wof:name":"Pro Tac Training Group",
    "wof:placetype":"venue"
},
  "geometry": {"coordinates":[-96.70697199999999,32.908194],"type":"Point"}
}