{
  "type": "Feature",
  "properties": {
    "iso:country":"US",
    "sg:address":"4101 Hahn Blvd",
    "sg:city":"Fort Worth",
    "sg:classifiers":[
        {
            "category":"Manufacturing",
            "subcategory":"Rubber & Plastics",
            "type":"Manufacturing & Wholesale Goods"
        }
    ],
    "sg:phone":"+1 817 281 9010",
    "sg:postcode":"76117",
    "sg:province":"TX",
    "wof:name":"Thermo Plastics Corp",
    "wof:placetype":"venue"
},
  "geometry": {"coordinates":[-97.281678,32.826628],"type":"Point"}
}