{
  "type": "Feature",
  "properties": {
    "iso:country":"US",
    "sg:address":"3137 Highway 36",
    "sg:city":"Sealy",
    "sg:classifiers":[
        {
            "category":"Education",
            "subcategory":"School",
            "type":"Public Place"
        }
    ],
    "sg:phone":"+1 979 885 2622",
    "sg:postcode":"77474",
    "sg:province":"TX",
    "sg:tags":[
        "k-",
        "private"
    ],
    "wof:name":"Sch. Development",
    "wof:placetype":"venue"
},
  "geometry": {"coordinates":[-96.14693,29.749113],"type":"Point"}
}