{
  "type": "Feature",
  "properties": {
    "iso:country":"US",
    "sg:address":"2400 Preston Rd",
    "sg:city":"Plano",
    "sg:classifiers":[
        {
            "category":"Restaurant",
            "type":"Food & Drink"
        }
    ],
    "sg:phone":"+1 972 964 0684",
    "sg:postcode":"75093",
    "sg:province":"TX",
    "sg:tags":[
        "chinese"
    ],
    "wof:name":"Chinese Kitchen",
    "wof:placetype":"venue"
},
  "geometry": {"coordinates":[-96.794601,33.030602],"type":"Point"}
}