{
  "type": "Feature",
  "properties": {
    "iso:country":"US",
    "sg:address":"1404 S Jefferson Ave",
    "sg:city":"Mount Pleasant",
    "sg:classifiers":[
        {
            "category":"Insurance",
            "subcategory":"Insurance Agent",
            "type":"Services"
        }
    ],
    "sg:phone":"+1 903 572 1867",
    "sg:postcode":"75455",
    "sg:province":"TX",
    "wof:name":"State Farm Insurance",
    "wof:placetype":"venue"
},
  "geometry": {"coordinates":[-94.968132,33.142303],"type":"Point"}
}