{
  "type": "Feature",
  "properties": {
    "iso:country":"US",
    "sg:address":"3129 Zulch Rd",
    "sg:city":"North Zulch",
    "sg:classifiers":[
        {
            "category":"Professional",
            "subcategory":"Research",
            "type":"Services"
        }
    ],
    "sg:phone":"+1 979 845 7568",
    "sg:postcode":"77872",
    "sg:province":"TX",
    "sg:tags":[
        "organization",
        "noncommercial"
    ],
    "wof:name":"Texas Transportation Institute",
    "wof:placetype":"venue"
},
  "geometry": {"coordinates":[-96.10695800000001,30.913062],"type":"Point"}
}