{
  "type": "Feature",
  "properties": {
    "iso:country":"US",
    "sg:address":"228 Moody St",
    "sg:city":"Sealy",
    "sg:classifiers":[
        {
            "category":"Autos & Motor Vehicles",
            "subcategory":"Auto Supplies",
            "type":"Retail Goods"
        }
    ],
    "sg:phone":"+1 979 885 6300",
    "sg:postcode":"77474",
    "sg:province":"TX",
    "sg:tags":[
        "parts"
    ],
    "wof:name":"OReilly Automotive Inc",
    "wof:placetype":"venue"
},
  "geometry": {"coordinates":[-96.153397,29.769321],"type":"Point"}
}