{
  "type": "Feature",
  "properties": {
    "iso:country":"US",
    "sg:address":"401 E 38th St",
    "sg:city":"Odessa",
    "sg:classifiers":[
        {
            "category":"Shopping",
            "subcategory":"Florist",
            "type":"Retail Goods"
        }
    ],
    "sg:phone":"+1 432 367 4255",
    "sg:postcode":"79762",
    "sg:province":"TX",
    "wof:name":"Sisters Floral Designs",
    "wof:placetype":"venue"
},
  "geometry": {"coordinates":[-102.37800900000001,31.880841],"type":"Point"}
}