{
  "type": "Feature",
  "properties": {
    "iso:country":"US",
    "sg:address":"1805 W Park Row Dr",
    "sg:city":"Arlington",
    "sg:classifiers":[
        {
            "category":"Real Estate",
            "subcategory":"Architect",
            "type":"Services"
        }
    ],
    "sg:phone":"+1 817 274 3871",
    "sg:postcode":"76013",
    "sg:province":"TX",
    "wof:name":"Davis & Davis",
    "wof:placetype":"venue"
},
  "geometry": {"coordinates":[-97.137224,32.721368],"type":"Point"}
}