{
  "type": "Feature",
  "properties": {
    "iso:country":"US",
    "sg:address":"7540 E Grand Ave",
    "sg:city":"Dallas",
    "sg:classifiers":[
        {
            "category":"Health Services",
            "subcategory":"Clinic",
            "type":"Services"
        },
        {
            "category":"Wholesale",
            "subcategory":"Wine & Distilled Alcoholic Beverages",
            "type":"Manufacturing & Wholesale Goods"
        }
    ],
    "sg:phone":"+1 214 321 6460",
    "sg:postcode":"75214",
    "sg:province":"TX",
    "sg:tags":[
        "information",
        "treatment",
        "alcoholism",
        "liquors-wholesale"
    ],
    "wof:name":"Dallas Beer Wine Liquor",
    "wof:placetype":"venue"
},
  "geometry": {"coordinates":[-96.72962800000001,32.810729],"type":"Point"}
}