{
  "type": "Feature",
  "properties": {
    "iso:country":"US",
    "sg:address":"705 N Greenville Ave",
    "sg:city":"Allen",
    "sg:classifiers":[
        {
            "category":"Professional",
            "subcategory":"Employment Agencies",
            "type":"Services"
        },
        {
            "category":"Health Services",
            "subcategory":"Clinic",
            "type":"Services"
        },
        {
            "category":"Health Services",
            "subcategory":"Nursing And Care Facility",
            "type":"Services"
        },
        {
            "category":"Health Services",
            "subcategory":"Health Practitioner",
            "type":"Services"
        },
        {
            "category":"Insurance",
            "subcategory":"Hazard Insurance",
            "type":"Services"
        }
    ],
    "sg:phone":"+1 972 747 0821",
    "sg:postcode":"75002",
    "sg:province":"TX",
    "sg:tags":[
        "home",
        "medical",
        "welfare",
        "eldercare-home",
        "contractor"
    ],
    "wof:name":"Prestige Health Services",
    "wof:placetype":"venue"
},
  "geometry": {"coordinates":[-96.65393,33.112911],"type":"Point"}
}