{
  "type": "Feature",
  "properties": {
    "iso:country":"US",
    "sg:address":"4730 Lark Ave",
    "sg:city":"San Antonio",
    "sg:classifiers":[
        {
            "category":"Freight",
            "type":"Transportation"
        }
    ],
    "sg:phone":"+1 210 436 7786",
    "sg:postcode":"78228",
    "sg:province":"TX",
    "sg:tags":[
        "operator",
        "local",
        "trucking"
    ],
    "wof:name":"Barreto Trucking",
    "wof:placetype":"venue"
},
  "geometry": {"coordinates":[-98.57882600000001,29.452139],"type":"Point"}
}