{
  "type": "Feature",
  "properties": {
    "iso:country":"US",
    "sg:address":"2701 N Hwy 146",
    "sg:city":"Baytown",
    "sg:classifiers":[
        {
            "category":"Restaurant",
            "type":"Food & Drink"
        }
    ],
    "sg:phone":"+1 281 427 0709",
    "sg:postcode":"77520",
    "sg:province":"TX",
    "sg:tags":[
        "seafood"
    ],
    "wof:name":"Galley Restaurant",
    "wof:placetype":"venue"
},
  "geometry": {"coordinates":[-94.916487,29.770284],"type":"Point"}
}