{
  "type": "Feature",
  "properties": {
    "iso:country":"US",
    "sg:address":"10615 N Ave L",
    "sg:city":"La Porte",
    "sg:classifiers":[
        {
            "category":"Education",
            "subcategory":"School",
            "type":"Public Place"
        }
    ],
    "sg:phone":"+1 281 867 4321",
    "sg:postcode":"77571",
    "sg:province":"TX",
    "wof:name":"Medallion School Partnerships",
    "wof:placetype":"venue"
},
  "geometry": {"coordinates":[-95.067977,29.680112],"type":"Point"}
}