{
  "type": "Feature",
  "properties": {
    "iso:country":"US",
    "sg:address":"4345 Whitfield Ave",
    "sg:city":"Fort Worth",
    "sg:classifiers":[
        {
            "category":"Professional",
            "subcategory":"Advertising",
            "type":"Services"
        }
    ],
    "sg:phone":"+1 817 927 5735",
    "sg:postcode":"76109",
    "sg:province":"TX",
    "sg:tags":[
        "counselor"
    ],
    "wof:name":"Ad PAC",
    "wof:placetype":"venue"
},
  "geometry": {"coordinates":[-97.38924799999999,32.680128],"type":"Point"}
}