{
  "type": "Feature",
  "properties": {
    "iso:country":"US",
    "sg:address":"7929 Shining Willow Ln",
    "sg:city":"Dallas",
    "sg:classifiers":[
        {
            "category":"Professional",
            "type":"Services"
        }
    ],
    "sg:phone":"+1 214 360 9530",
    "sg:postcode":"75230",
    "sg:province":"TX",
    "sg:tags":[
        "establishment"
    ],
    "wof:name":"GMA",
    "wof:placetype":"venue"
},
  "geometry": {"coordinates":[-96.772121,32.882977],"type":"Point"}
}