{
  "type": "Feature",
  "properties": {
    "iso:country":"US",
    "sg:address":"102 Cordelia St",
    "sg:city":"Lufkin",
    "sg:classifiers":[
        {
            "category":"Wholesale",
            "subcategory":"Meat",
            "type":"Manufacturing & Wholesale Goods"
        },
        {
            "category":"Banks & Credit Unions",
            "subcategory":"Investment Brokerage",
            "type":"Services"
        }
    ],
    "sg:phone":"+1 936 637 1909",
    "sg:postcode":"75904",
    "sg:province":"TX",
    "sg:tags":[
        "contract",
        "consulting",
        "management",
        "broker",
        "commodity"
    ],
    "wof:name":"Project Brokers And Traders, Inc",
    "wof:placetype":"venue"
},
  "geometry": {"coordinates":[-94.74694,31.334198],"type":"Point"}
}