{
  "type": "Feature",
  "properties": {
    "iso:country":"US",
    "sg:address":"770 Post St",
    "sg:city":"Houston",
    "sg:classifiers":[
        {
            "category":"Professional",
            "subcategory":"Accounting & Tax Preparation",
            "type":"Services"
        }
    ],
    "sg:phone":"+1 713 626 0662",
    "sg:postcode":"77022",
    "sg:province":"TX",
    "wof:name":"McMahan & Co",
    "wof:placetype":"venue"
},
  "geometry": {"coordinates":[-95.364564,29.826323],"type":"Point"}
}