{
  "type": "Feature",
  "properties": {
    "iso:country":"US",
    "sg:address":"5011 Cranfill Dr",
    "sg:city":"Dallas",
    "sg:classifiers":[
        {
            "category":"Retail",
            "subcategory":"Auto Repair",
            "type":"Services"
        }
    ],
    "sg:phone":"+1 214 941 9945",
    "sg:postcode":"75241",
    "sg:province":"TX",
    "sg:tags":[
        "repairing",
        "automobile"
    ],
    "wof:name":"Longbeach Auto Mechanics",
    "wof:placetype":"venue"
},
  "geometry": {"coordinates":[-96.760727,32.696158],"type":"Point"}
}