{
  "type": "Feature",
  "properties": {
    "iso:country":"US",
    "sg:address":"616 Spatz",
    "sg:city":"Hondo",
    "sg:classifiers":[
        {
            "category":"Utilities",
            "subcategory":"Refuse",
            "type":"Services"
        }
    ],
    "sg:phone":"+1 830 426 4261",
    "sg:postcode":"78861",
    "sg:province":"TX",
    "sg:tags":[
        "garbage",
        "collection"
    ],
    "wof:name":"South Texas Refuse Inc",
    "wof:placetype":"venue"
},
  "geometry": {"coordinates":[-99.163021,29.360372],"type":"Point"}
}