{
  "type": "Feature",
  "properties": {
    "iso:country":"US",
    "sg:address":"506 Sandau Rd",
    "sg:city":"San Antonio",
    "sg:classifiers":[
        {
            "category":"Wholesale",
            "subcategory":"Machinery & Supplies",
            "type":"Manufacturing & Wholesale Goods"
        }
    ],
    "sg:phone":"+1 210 342 3163",
    "sg:postcode":"78216",
    "sg:province":"TX",
    "sg:tags":[
        "equipment",
        "pneumatic",
        "component"
    ],
    "wof:name":"Sunsource/Air-Dreco",
    "wof:placetype":"venue"
},
  "geometry": {"coordinates":[-98.485861,29.537797],"type":"Point"}
}