{
  "type": "Feature",
  "properties": {
    "iso:country":"US",
    "sg:address":"107 Fm 1100",
    "sg:city":"Elgin",
    "sg:classifiers":[
        {
            "category":"Health Services",
            "subcategory":"Dentist",
            "type":"Services"
        }
    ],
    "sg:phone":"+1 512 281 4260",
    "sg:postcode":"78621",
    "sg:province":"TX",
    "sg:tags":[
        "clinic",
        "dental"
    ],
    "wof:name":"Robertson, Randy M Dds Pc",
    "wof:placetype":"venue"
},
  "geometry": {"coordinates":[-97.387236,30.357251],"type":"Point"}
}