{
  "type": "Feature",
  "properties": {
    "iso:country":"US",
    "sg:address":"3370 Shaver St",
    "sg:city":"Pasadena",
    "sg:classifiers":[
        {
            "category":"Food & Beverages",
            "subcategory":"Meat & Fish",
            "type":"Retail Goods"
        }
    ],
    "sg:phone":"+1 713 943 2058",
    "sg:postcode":"77504",
    "sg:province":"TX",
    "wof:name":"Guadalupana Meat Market",
    "wof:placetype":"venue"
},
  "geometry": {"coordinates":[-95.208281,29.659412],"type":"Point"}
}