{
  "type": "Feature",
  "properties": {
    "iso:country":"US",
    "sg:address":"416 Hickory St",
    "sg:city":"Mt Pleasant",
    "sg:classifiers":[
        {
            "category":"Building & Trades",
            "subcategory":"Landscaping Services",
            "type":"Services"
        }
    ],
    "sg:phone":"+1 903 572 7985",
    "sg:postcode":"75455",
    "sg:province":"TX",
    "sg:tags":[
        "landscape",
        "contractor"
    ],
    "wof:name":"Total Lawn & Fence Co",
    "wof:placetype":"venue"
},
  "geometry": {"coordinates":[-94.959954,33.137217],"type":"Point"}
}