{
  "type": "Feature",
  "properties": {
    "iso:country":"US",
    "sg:address":"1222 Trace Dr",
    "sg:city":"Houston",
    "sg:classifiers":[
        {
            "category":"Professional",
            "subcategory":"Management & Consulting",
            "type":"Services"
        }
    ],
    "sg:phone":"+1 281 493 9133",
    "sg:postcode":"77077",
    "sg:province":"TX",
    "wof:name":"Rita Tucker Wright Proper",
    "wof:placetype":"venue"
},
  "geometry": {"coordinates":[-95.610979,29.75947],"type":"Point"}
}