{
  "type": "Feature",
  "properties": {
    "iso:country":"US",
    "sg:address":"4520 Reading Rd",
    "sg:city":"Rosenberg",
    "sg:classifiers":[
        {
            "category":"Government",
            "subcategory":"Office",
            "type":"Public Place"
        }
    ],
    "sg:phone":"+1 281 341 8617",
    "sg:postcode":"77471",
    "sg:province":"TX",
    "sg:tags":[
        "general"
    ],
    "wof:name":"Human Resources Dept",
    "wof:placetype":"venue"
},
  "geometry": {"coordinates":[-95.77913599999999,29.565251],"type":"Point"}
}