{
  "type": "Feature",
  "properties": {
    "iso:country":"US",
    "sg:address":"300 Lake Air Dr",
    "sg:city":"Waco",
    "sg:classifiers":[
        {
            "category":"Shopping",
            "subcategory":"Clothing, Apparel, & Fashions",
            "type":"Retail Goods"
        }
    ],
    "sg:phone":"+1 254 741 9971",
    "sg:postcode":"76710",
    "sg:province":"TX",
    "wof:name":"Waco Scout Shop",
    "wof:placetype":"venue"
},
  "geometry": {"coordinates":[-97.18279099999999,31.522304],"type":"Point"}
}