{
  "type": "Feature",
  "properties": {
    "iso:country":"US",
    "sg:address":"2501 Saulsbury Dr",
    "sg:city":"Temple",
    "sg:classifiers":[
        {
            "category":"Wholesale",
            "subcategory":"Medical Equipment & Supplies",
            "type":"Manufacturing & Wholesale Goods"
        }
    ],
    "sg:phone":"+1 254 778 8515",
    "sg:postcode":"76504",
    "sg:province":"TX",
    "wof:name":"Eagle Home Medical Corp",
    "wof:placetype":"venue"
},
  "geometry": {"coordinates":[-97.365313,31.11013],"type":"Point"}
}