{
  "type": "Feature",
  "properties": {
    "iso:country":"US",
    "sg:address":"509 S Choctaw St",
    "sg:city":"Shamrock",
    "sg:classifiers":[
        {
            "category":"Retail",
            "subcategory":"Auto Repair",
            "type":"Services"
        }
    ],
    "sg:phone":"+1 806 256 1493",
    "sg:postcode":"79079",
    "sg:province":"TX",
    "sg:tags":[
        "general"
    ],
    "wof:name":"66 Shop",
    "wof:placetype":"venue"
},
  "geometry": {"coordinates":[-100.251751,35.207797],"type":"Point"}
}