{
  "type": "Feature",
  "properties": {
    "iso:country":"US",
    "sg:address":"4025 Willowbend Blvd",
    "sg:city":"Houston",
    "sg:classifiers":[
        {
            "category":"Shopping",
            "type":"Retail Goods"
        }
    ],
    "sg:phone":"+1 713 432 1080",
    "sg:postcode":"77025",
    "sg:province":"TX",
    "sg:tags":[
        "merchandise"
    ],
    "wof:name":"Pro Mobility",
    "wof:placetype":"venue"
},
  "geometry": {"coordinates":[-95.44141500000001,29.665017],"type":"Point"}
}