{
  "type": "Feature",
  "properties": {
    "iso:country":"US",
    "sg:address":"706 Elm St",
    "sg:city":"Longview",
    "sg:classifiers":[
        {
            "category":"Wholesale",
            "subcategory":"Machinery & Supplies",
            "type":"Manufacturing & Wholesale Goods"
        }
    ],
    "sg:phone":"+1 903 757 6053",
    "sg:postcode":"75605",
    "sg:province":"TX",
    "sg:tags":[
        "equipment",
        "industrial",
        "oil",
        "field"
    ],
    "wof:name":"B F Oilfield Supply",
    "wof:placetype":"venue"
},
  "geometry": {"coordinates":[-94.730642,32.530971],"type":"Point"}
}