{
  "type": "Feature",
  "properties": {
    "iso:country":"US",
    "sg:address":"315 Hwy 35 S",
    "sg:city":"Rockport",
    "sg:classifiers":[
        {
            "category":"Organizations",
            "subcategory":"Religious Organization",
            "type":"Services"
        }
    ],
    "sg:phone":"+1 361 729 6882",
    "sg:postcode":"78382",
    "sg:province":"TX",
    "sg:tags":[
        "church"
    ],
    "wof:name":"Rockport Church Of God",
    "wof:placetype":"venue"
},
  "geometry": {"coordinates":[-97.058857,28.024907],"type":"Point"}
}