{
  "type": "Feature",
  "properties": {
    "iso:country":"US",
    "sg:address":"5712 Carrington Ct",
    "sg:city":"Richardson",
    "sg:classifiers":[
        {
            "category":"Professional",
            "subcategory":"Business Services",
            "type":"Services"
        }
    ],
    "sg:phone":"+1 972 235 1301",
    "sg:postcode":"75082",
    "sg:province":"TX",
    "wof:name":"Designs By Dana",
    "wof:placetype":"venue"
},
  "geometry": {"coordinates":[-96.616433,32.997995],"type":"Point"}
}