{
  "type": "Feature",
  "properties": {
    "iso:country":"US",
    "sg:address":"1600 W 38th Street",
    "sg:city":"Austin",
    "sg:classifiers":[
        {
            "category":"Health Services",
            "subcategory":"Optometrist",
            "type":"Services"
        }
    ],
    "sg:phone":"+1 512 452 8598",
    "sg:postcode":"78731",
    "sg:province":"TX",
    "sg:website":"www.robertross-austin.com/",
    "wof:name":"Ross Robert A Optmtrst",
    "wof:placetype":"venue"
},
  "geometry": {"coordinates":[-97.749748,30.308858],"type":"Point"}
}