{
  "type": "Feature",
  "properties": {
    "iso:country":"US",
    "sg:address":"424 E Veterans Memorial Blvd",
    "sg:city":"Killeen",
    "sg:classifiers":[
        {
            "category":"Autos & Motor Vehicles",
            "subcategory":"Automobile Sales",
            "type":"Retail Goods"
        }
    ],
    "sg:phone":"+1 254 628 8445",
    "sg:postcode":"76541",
    "sg:province":"TX",
    "sg:tags":[
        "used"
    ],
    "wof:name":"Killeen Auto Ranch Inc",
    "wof:placetype":"venue"
},
  "geometry": {"coordinates":[-97.726812,31.116685],"type":"Point"}
}