{
  "type": "Feature",
  "properties": {
    "iso:country":"US",
    "sg:address":"4303 41st St E",
    "sg:city":"Dickinson",
    "sg:classifiers":[
        {
            "category":"Food & Beverages",
            "subcategory":"Groceries & Convenience Stores",
            "type":"Retail Goods"
        }
    ],
    "sg:phone":"+1 281 534 4111",
    "sg:postcode":"77539",
    "sg:province":"TX",
    "wof:name":"Shoppers Mart",
    "wof:placetype":"venue"
},
  "geometry": {"coordinates":[-95.045366,29.463578],"type":"Point"}
}