{
  "type": "Feature",
  "properties": {
    "iso:country":"US",
    "sg:address":"7405 Lake Como Dr",
    "sg:city":"Corpus Christi",
    "sg:classifiers":[
        {
            "category":"Banks & Credit Unions",
            "subcategory":"Financial Services",
            "type":"Services"
        }
    ],
    "sg:phone":"+1 361 850 7612",
    "sg:postcode":"78413",
    "sg:province":"TX",
    "sg:tags":[
        "company",
        "holding"
    ],
    "wof:name":"Owl Creek Holdings Inc",
    "wof:placetype":"venue"
},
  "geometry": {"coordinates":[-97.413681,27.676731],"type":"Point"}
}