{
  "type": "Feature",
  "properties": {
    "iso:country":"US",
    "sg:address":"3359 Quail Run Rd",
    "sg:city":"Brenham",
    "sg:classifiers":[
        {
            "category":"Retail",
            "subcategory":"Laundry & Dry Cleaning",
            "type":"Services"
        }
    ],
    "sg:phone":"+1 979 836 5493",
    "sg:postcode":"77833",
    "sg:province":"TX",
    "sg:tags":[
        "cleaner",
        "rug",
        "carpet"
    ],
    "wof:name":"Bayer Carpet Cleaning",
    "wof:placetype":"venue"
},
  "geometry": {"coordinates":[-96.461618,30.199491],"type":"Point"}
}