{
  "type": "Feature",
  "properties": {
    "iso:country":"US",
    "sg:address":"5315 Us Highway 87 E",
    "sg:city":"San Antonio",
    "sg:classifiers":[
        {
            "category":"Restaurant",
            "type":"Food & Drink"
        }
    ],
    "sg:menulink":"http://www.allmenus.com/tx/san-antonio/177216-kfc---kentucky-fried-chicken/menu/",
    "sg:phone":"+1 210 648 4872",
    "sg:postcode":"78222",
    "sg:province":"TX",
    "sg:tags":[
        "american",
        "chicken"
    ],
    "wof:name":"KFC - Kentucky Fried Chicken",
    "wof:placetype":"venue"
},
  "geometry": {"coordinates":[-98.386343,29.398724],"type":"Point"}
}