{
  "type": "Feature",
  "properties": {
    "iso:country":"US",
    "sg:address":"4556 Winding Wood Trl",
    "sg:city":"Plano",
    "sg:classifiers":[
        {
            "category":"Shopping",
            "type":"Retail Goods"
        }
    ],
    "sg:phone":"+1 972 491 2143",
    "sg:postcode":"75024",
    "sg:province":"TX",
    "sg:tags":[
        "merchandise"
    ],
    "wof:name":"Colorful Beads & Findings",
    "wof:placetype":"venue"
},
  "geometry": {"coordinates":[-96.78675800000001,33.084484],"type":"Point"}
}