{
  "type": "Feature",
  "properties": {
    "iso:country":"US",
    "sg:address":"1337 Thorpe Ln",
    "sg:city":"San Marcos",
    "sg:classifiers":[
        {
            "category":"Health Services",
            "subcategory":"Doctor",
            "type":"Services"
        }
    ],
    "sg:phone":"+1 512 396 5225",
    "sg:postcode":"78666",
    "sg:province":"TX",
    "sg:tags":[
        "dentist"
    ],
    "wof:name":"Donnelly J Robert DDS",
    "wof:placetype":"venue"
},
  "geometry": {"coordinates":[-97.923036,29.88819],"type":"Point"}
}