{
  "type": "Feature",
  "properties": {
    "iso:country":"US",
    "sg:address":"920 Frostwood Dr Ste 670",
    "sg:city":"Houston",
    "sg:classifiers":[
        {
            "category":"Health Services",
            "subcategory":"Doctor",
            "type":"Services"
        }
    ],
    "sg:phone":"+1 713 973 6078",
    "sg:postcode":"77024",
    "sg:province":"TX",
    "wof:name":"Rensimer E R MD",
    "wof:placetype":"venue"
},
  "geometry": {"coordinates":[-95.547798,29.778999],"type":"Point"}
}