{
  "type": "Feature",
  "properties": {
    "iso:country":"US",
    "sg:address":"5090 Richmond Ave",
    "sg:city":"Houston",
    "sg:classifiers":[
        {
            "category":"Manufacturing",
            "subcategory":"Paper Products",
            "type":"Manufacturing & Wholesale Goods"
        }
    ],
    "sg:phone":"+1 314 239 1428",
    "sg:postcode":"77056",
    "sg:province":"TX",
    "sg:tags":[
        "corrugated",
        "packaging",
        "fulfillment"
    ],
    "wof:name":"Destiny Packaging Inc",
    "wof:placetype":"venue"
},
  "geometry": {"coordinates":[-95.463949,29.731866],"type":"Point"}
}