{
  "type": "Feature",
  "properties": {
    "iso:country":"US",
    "sg:address":"1020 Jefferson Chemical Rd",
    "sg:city":"Conroe",
    "sg:classifiers":[
        {
            "category":"Wholesale",
            "subcategory":"Chemicals & Plastics",
            "type":"Manufacturing & Wholesale Goods"
        }
    ],
    "sg:phone":"+1 936 756 4022",
    "sg:postcode":"77306",
    "sg:province":"TX",
    "sg:tags":[
        "industrial",
        "gas"
    ],
    "wof:name":"Air Products",
    "wof:placetype":"venue"
},
  "geometry": {"coordinates":[-95.38793699999999,30.32463],"type":"Point"}
}