{
  "type": "Feature",
  "properties": {
    "iso:country":"US",
    "sg:address":"5431 Santa Chase Ln",
    "sg:city":"Sugar Land",
    "sg:classifiers":[
        {
            "category":"Professional",
            "subcategory":"Computer Services",
            "type":"Services"
        }
    ],
    "sg:phone":"+1 713 320 4249",
    "sg:postcode":"77479",
    "sg:province":"TX",
    "wof:name":"PC Destinations",
    "wof:placetype":"venue"
},
  "geometry": {"coordinates":[-95.682192,29.59041],"type":"Point"}
}