{
  "type": "Feature",
  "properties": {
    "iso:country":"US",
    "sg:address":"5001 Spring Valley Rd",
    "sg:city":"Dallas",
    "sg:classifiers":[
        {
            "category":"Mining & Drilling",
            "type":"Manufacturing & Wholesale Goods"
        }
    ],
    "sg:phone":"+1 972 239 2600",
    "sg:postcode":"75244",
    "sg:province":"TX",
    "sg:tags":[
        "development",
        "gas",
        "oil",
        "exploration"
    ],
    "wof:name":"Richman Petroleum Corp",
    "wof:placetype":"venue"
},
  "geometry": {"coordinates":[-96.825773,32.939597],"type":"Point"}
}