{
  "type": "Feature",
  "properties": {
    "iso:country":"US",
    "sg:address":"1712 W Frankford Rd Ste 108",
    "sg:city":"Carrollton",
    "sg:classifiers":[
        {
            "category":"Retail",
            "subcategory":"Veterinary Services",
            "type":"Services"
        }
    ],
    "sg:phone":"+1 972 323 1310",
    "sg:postcode":"75007",
    "sg:province":"TX",
    "sg:tags":[
        "veterinarian"
    ],
    "wof:name":"North Texas Emergency Pet Clinic",
    "wof:placetype":"venue"
},
  "geometry": {"coordinates":[-96.889503,33.004601],"type":"Point"}
}