{
  "type": "Feature",
  "properties": {
    "iso:country":"US",
    "sg:address":"111 Wilcrest Dr",
    "sg:city":"Houston",
    "sg:classifiers":[
        {
            "category":"Social Services",
            "type":"Services"
        }
    ],
    "sg:phone":"+1 713 266 8002",
    "sg:postcode":"77042",
    "sg:province":"TX",
    "sg:tags":[
        "medical"
    ],
    "wof:name":"House of Charity",
    "wof:placetype":"venue"
},
  "geometry": {"coordinates":[-95.576078,29.765644],"type":"Point"}
}