{
  "type": "Feature",
  "properties": {
    "iso:country":"US",
    "sg:address":"1001 W Marfa Ave",
    "sg:city":"Alpine",
    "sg:classifiers":[
        {
            "category":"Professional",
            "subcategory":"Business Services",
            "type":"Services"
        }
    ],
    "sg:phone":"+1 432 837 0045",
    "sg:postcode":"79830",
    "sg:province":"TX",
    "sg:tags":[
        "soil",
        "map"
    ],
    "wof:name":"Jeremy D Clausen",
    "wof:placetype":"venue"
},
  "geometry": {"coordinates":[-103.67565,30.365022],"type":"Point"}
}