{
  "type": "Feature",
  "properties": {
    "iso:country":"US",
    "sg:address":"504 This Way St Ste C",
    "sg:city":"Lake Jackson",
    "sg:classifiers":[
        {
            "category":"Personal",
            "subcategory":"Day Spa",
            "type":"Services"
        }
    ],
    "sg:phone":"+1 979 285 9800",
    "sg:postcode":"77566",
    "sg:province":"TX",
    "sg:website":"www.dermaculture-lakejackson.com",
    "wof:name":"Dermaculture Of Lake Jackson",
    "wof:placetype":"venue"
},
  "geometry": {"coordinates":[-95.460869,29.799549],"type":"Point"}
}