{
  "type": "Feature",
  "properties": {
    "iso:country":"US",
    "sg:address":"10688 Jefferson Chemical Rd",
    "sg:city":"Conroe",
    "sg:classifiers":[
        {
            "category":"Retail",
            "subcategory":"Repair Shop",
            "type":"Services"
        }
    ],
    "sg:phone":"+1 281 660 4675",
    "sg:postcode":"77301",
    "sg:province":"TX",
    "wof:name":"Pump Service Repair",
    "wof:placetype":"venue"
},
  "geometry": {"coordinates":[-95.38467799999999,30.295424],"type":"Point"}
}