{
  "type": "Feature",
  "properties": {
    "iso:country":"US",
    "sg:address":"1025 W Hebron Pkwy Ste 144",
    "sg:city":"Carrollton",
    "sg:classifiers":[
        {
            "category":"Personal",
            "subcategory":"Skin Care",
            "type":"Services"
        },
        {
            "category":"Personal",
            "subcategory":"Day Spa",
            "type":"Services"
        }
    ],
    "sg:phone":"+1 972 395 8700",
    "sg:postcode":"75010",
    "sg:province":"TX",
    "wof:name":"Spa International",
    "wof:placetype":"venue"
},
  "geometry": {"coordinates":[-96.91660299999999,33.0205],"type":"Point"}
}