{
  "type": "Feature",
  "properties": {
    "iso:country":"US",
    "sg:address":"10325 Brockwood Rd",
    "sg:city":"Dallas",
    "sg:classifiers":[
        {
            "category":"Manufacturing",
            "subcategory":"Printing",
            "type":"Manufacturing & Wholesale Goods"
        }
    ],
    "sg:phone":"+1 214 348 9494",
    "sg:postcode":"75238",
    "sg:province":"TX",
    "sg:tags":[
        "label"
    ],
    "wof:name":"Bar Code Labels & Systems",
    "wof:placetype":"venue"
},
  "geometry": {"coordinates":[-96.70681999999999,32.893249],"type":"Point"}
}