{
  "type": "Feature",
  "properties": {
    "iso:country":"US",
    "sg:address":"5736 W Little York Rd",
    "sg:city":"Houston",
    "sg:classifiers":[
        {
            "category":"Organizations",
            "subcategory":"Religious Organization",
            "type":"Services"
        }
    ],
    "sg:phone":"+1 281 820 7070",
    "sg:postcode":"77091",
    "sg:province":"TX",
    "wof:name":"Church God Spirit of Faith",
    "wof:placetype":"venue"
},
  "geometry": {"coordinates":[-95.474728,29.863427],"type":"Point"}
}