{
  "type": "Feature",
  "properties": {
    "iso:country":"US",
    "sg:address":"5810 Babcock Rd",
    "sg:city":"San Antonio",
    "sg:classifiers":[
        {
            "category":"Shopping",
            "subcategory":"Used Merchandise",
            "type":"Retail Goods"
        }
    ],
    "sg:phone":"+1 210 558 7358",
    "sg:postcode":"78240",
    "sg:province":"TX",
    "wof:name":"Nearly New",
    "wof:placetype":"venue"
},
  "geometry": {"coordinates":[-98.602721,29.529182],"type":"Point"}
}