{
  "type": "Feature",
  "properties": {
    "iso:country":"US",
    "sg:address":"5330 Palomar Ln",
    "sg:city":"Dallas",
    "sg:classifiers":[
        {
            "category":"Manufacturing",
            "subcategory":"Retail Goods",
            "type":"Manufacturing & Wholesale Goods"
        }
    ],
    "sg:phone":"+1 972 620 8039",
    "sg:postcode":"75229",
    "sg:province":"TX",
    "sg:tags":[
        "product",
        "mfg"
    ],
    "wof:name":"Wichita Industries Inc",
    "wof:placetype":"venue"
},
  "geometry": {"coordinates":[-96.81542399999999,32.8896],"type":"Point"}
}