{
  "type": "Feature",
  "properties": {
    "iso:country":"US",
    "sg:address":"6204 Kenosha Dr",
    "sg:city":"Lubbock",
    "sg:classifiers":[
        {
            "category":"Real Estate",
            "subcategory":"Real Estate Operator",
            "type":"Services"
        }
    ],
    "sg:phone":"+1 806 795 6278",
    "sg:postcode":"79413",
    "sg:province":"TX",
    "sg:tags":[
        "property",
        "lessor"
    ],
    "wof:name":"K & L Wylie Inc",
    "wof:placetype":"venue"
},
  "geometry": {"coordinates":[-101.889906,33.5355],"type":"Point"}
}