{
  "type": "Feature",
  "properties": {
    "iso:country":"US",
    "sg:address":"1725 Seley Ave",
    "sg:city":"Waco",
    "sg:classifiers":[
        {
            "category":"Retail",
            "subcategory":"Auto Repair",
            "type":"Services"
        }
    ],
    "sg:phone":"+1 254 753 6261",
    "sg:postcode":"76704",
    "sg:province":"TX",
    "sg:tags":[
        "repairing",
        "automobile"
    ],
    "wof:name":"Oliver Brothers Transmissions",
    "wof:placetype":"venue"
},
  "geometry": {"coordinates":[-97.11805,31.58505],"type":"Point"}
}