{
  "type": "Feature",
  "properties": {
    "iso:country":"US",
    "sg:address":"401 Towne Oaks Dr",
    "sg:city":"Waco",
    "sg:classifiers":[
        {
            "category":"Recreation",
            "type":"Entertainment"
        }
    ],
    "sg:phone":"+1 254 772 0042",
    "sg:postcode":"76710",
    "sg:province":"TX",
    "sg:tags":[
        "skating",
        "rink"
    ],
    "wof:name":"Skate World",
    "wof:placetype":"venue"
},
  "geometry": {"coordinates":[-97.180092,31.525936],"type":"Point"}
}