{
  "type": "Feature",
  "properties": {
    "iso:country":"US",
    "sg:address":"24890 FM 1314",
    "sg:city":"Porter",
    "sg:classifiers":[
        {
            "category":"Restaurant",
            "type":"Food & Drink"
        }
    ],
    "sg:phone":"+1 281 354 8854",
    "sg:postcode":"77365",
    "sg:province":"TX",
    "wof:name":"Hofbrau Steaks",
    "wof:placetype":"venue"
},
  "geometry": {"coordinates":[-95.23362299999999,30.103569],"type":"Point"}
}