{
  "type": "Feature",
  "properties": {
    "iso:country":"US",
    "sg:address":"8042 Wurzbach Rd",
    "sg:city":"San Antonio",
    "sg:classifiers":[
        {
            "category":"Health Services",
            "subcategory":"Clinic",
            "type":"Services"
        }
    ],
    "sg:phone":"+1 210 226 6260",
    "sg:postcode":"78229",
    "sg:province":"TX",
    "sg:tags":[
        "specialty",
        "outpatient"
    ],
    "wof:name":"Dr Barker & Dr Cottle",
    "wof:placetype":"venue"
},
  "geometry": {"coordinates":[-98.57670400000001,29.515402],"type":"Point"}
}