{
  "type": "Feature",
  "properties": {
    "iso:country":"US",
    "sg:address":"6650 Prue Rd",
    "sg:city":"San Antonio",
    "sg:classifiers":[
        {
            "category":"Real Estate",
            "subcategory":"Real Estate Operator",
            "type":"Services"
        }
    ],
    "sg:phone":"+1 210 558 0910",
    "sg:postcode":"78240",
    "sg:province":"TX",
    "sg:tags":[
        "apartment"
    ],
    "wof:name":"Enclave At Buckhorn Crossing",
    "wof:placetype":"venue"
},
  "geometry": {"coordinates":[-98.61851299999999,29.544635],"type":"Point"}
}