{
  "type": "Feature",
  "properties": {
    "iso:country":"US",
    "sg:address":"11940 Golden Gate Rd",
    "sg:city":"El Paso",
    "sg:classifiers":[
        {
            "category":"Professional",
            "subcategory":"Testing Lab",
            "type":"Services"
        }
    ],
    "sg:phone":"+1 915 849 1322",
    "sg:postcode":"79936",
    "sg:province":"TX",
    "sg:tags":[
        "laboratory",
        "consulting",
        "business"
    ],
    "wof:name":"Dynatec Scientific Labs",
    "wof:placetype":"venue"
},
  "geometry": {"coordinates":[-106.281273,31.752426],"type":"Point"}
}