{
  "type": "Feature",
  "properties": {
    "iso:country":"US",
    "sg:address":"5904 S Cooper St",
    "sg:city":"Arlington",
    "sg:classifiers":[
        {
            "category":"Restaurant",
            "type":"Food & Drink"
        }
    ],
    "sg:menulink":"http://www.allmenus.com/tx/arlington/65131-cicis-pizza-buffet/menu/",
    "sg:phone":"+1 817 465 2345",
    "sg:postcode":"76017",
    "sg:province":"TX",
    "sg:tags":[
        "american",
        "pizza"
    ],
    "wof:name":"CiCi's Pizza Buffet",
    "wof:placetype":"venue"
},
  "geometry": {"coordinates":[-97.13479100000001,32.650748],"type":"Point"}
}