{
  "type": "Feature",
  "properties": {
    "iso:country":"US",
    "sg:address":"6915 Fulton Ave",
    "sg:city":"Lubbock",
    "sg:classifiers":[
        {
            "category":"Banks & Credit Unions",
            "subcategory":"Financial Services",
            "type":"Services"
        }
    ],
    "sg:phone":"+1 806 798 6226",
    "sg:postcode":"79424",
    "sg:province":"TX",
    "sg:tags":[
        "investment",
        "closed"
    ],
    "wof:name":"New Matrix Inc",
    "wof:placetype":"venue"
},
  "geometry": {"coordinates":[-101.94150999999999,33.531243],"type":"Point"}
}