{
  "type": "Feature",
  "properties": {
    "iso:country":"US",
    "sg:address":"4500 S I- 35",
    "sg:city":"Georgetown",
    "sg:classifiers":[
        {
            "category":"Autos & Motor Vehicles",
            "subcategory":"Recreational Vehicle Sales",
            "type":"Retail Goods"
        }
    ],
    "sg:phone":"+1 512 930 4922",
    "sg:postcode":"78626",
    "sg:province":"TX",
    "sg:tags":[
        "supply"
    ],
    "sg:website":"www.rvoutletmall.com",
    "wof:name":"R V Outlet Mall",
    "wof:placetype":"venue"
},
  "geometry": {"coordinates":[-97.68766100000001,30.602941],"type":"Point"}
}