{
  "type": "Feature",
  "properties": {
    "iso:country":"US",
    "sg:address":"910 FM 211",
    "sg:city":"Tahoka",
    "sg:classifiers":[
        {
            "category":"Professional",
            "type":"Services"
        }
    ],
    "sg:phone":"+1 806 924 7333",
    "sg:postcode":"79373",
    "sg:province":"TX",
    "wof:name":"Purple Circle Magazine",
    "wof:placetype":"venue"
},
  "geometry": {"coordinates":[-101.944885,33.326786],"type":"Point"}
}