{
  "type": "Feature",
  "properties": {
    "iso:country":"US",
    "sg:address":"4520 Frankfort Ave",
    "sg:city":"El Paso",
    "sg:classifiers":[
        {
            "category":"Building & Trades",
            "subcategory":"Construction",
            "type":"Services"
        }
    ],
    "sg:phone":"+1 915 422 7091",
    "sg:postcode":"79903",
    "sg:province":"TX",
    "sg:tags":[
        "floor",
        "laying",
        "contractor"
    ],
    "wof:name":"E&G Roofing & Flooring System",
    "wof:placetype":"venue"
},
  "geometry": {"coordinates":[-106.436098,31.797722],"type":"Point"}
}