{
  "type": "Feature",
  "properties": {
    "iso:country":"US",
    "sg:address":"116 Creekpark Dr",
    "sg:city":"Floresville",
    "sg:classifiers":[
        {
            "category":"Retail",
            "subcategory":"Repair Shop",
            "type":"Services"
        }
    ],
    "sg:phone":"+1 830 216 4641",
    "sg:postcode":"78114",
    "sg:province":"TX",
    "sg:tags":[
        "electrical"
    ],
    "wof:name":"Martinez Generator Service",
    "wof:placetype":"venue"
},
  "geometry": {"coordinates":[-98.267762,29.250737],"type":"Point"}
}