{
  "type": "Feature",
  "properties": {
    "iso:country":"US",
    "sg:address":"3214 Wildlife Cir",
    "sg:city":"Bryan",
    "sg:classifiers":[
        {
            "category":"Building & Trades",
            "subcategory":"Construction",
            "type":"Services"
        }
    ],
    "sg:phone":"+1 979 774 6041",
    "sg:postcode":"77802",
    "sg:province":"TX",
    "sg:tags":[
        "wallcoverings-installation",
        "wallpaper",
        "painting",
        "contractor"
    ],
    "wof:name":"Brent Hooks",
    "wof:placetype":"venue"
},
  "geometry": {"coordinates":[-96.324033,30.668147],"type":"Point"}
}