{
  "type": "Feature",
  "properties": {
    "iso:country":"US",
    "sg:address":"6011 Connection Dr",
    "sg:city":"Irving",
    "sg:classifiers":[
        {
            "category":"Deli",
            "type":"Food & Drink"
        }
    ],
    "sg:postcode":"75039",
    "sg:province":"TX",
    "wof:name":"Agora",
    "wof:placetype":"venue"
},
  "geometry": {"coordinates":[-96.968112,32.895452],"type":"Point"}
}