{
  "type": "Feature",
  "properties": {
    "iso:country":"US",
    "sg:address":"4006 W Plano Pkwy",
    "sg:city":"Plano",
    "sg:classifiers":[
        {
            "category":"Shopping",
            "subcategory":"Optical Goods",
            "type":"Retail Goods"
        }
    ],
    "sg:phone":"+1 972 519 0001",
    "sg:postcode":"75093",
    "sg:province":"TX",
    "wof:name":"West Plano Optical Co Inc",
    "wof:placetype":"venue"
},
  "geometry": {"coordinates":[-96.767268,33.009958],"type":"Point"}
}