{
  "type": "Feature",
  "properties": {
    "iso:country":"US",
    "sg:address":"3216 Georgetown St",
    "sg:city":"Houston",
    "sg:classifiers":[
        {
            "category":"Professional",
            "subcategory":"Research",
            "type":"Services"
        }
    ],
    "sg:phone":"+1 713 668 6874",
    "sg:postcode":"77005",
    "sg:province":"TX",
    "sg:tags":[
        "consulting",
        "commercial",
        "business",
        "physical"
    ],
    "wof:name":"BAC-Ground",
    "wof:placetype":"venue"
},
  "geometry": {"coordinates":[-95.428675,29.718061],"type":"Point"}
}