{
  "type": "Feature",
  "properties": {
    "iso:country":"US",
    "sg:address":"1301 Travis St",
    "sg:city":"Houston",
    "sg:classifiers":[
        {
            "category":"Real Estate",
            "subcategory":"Real Estate Services",
            "type":"Services"
        }
    ],
    "sg:phone":"+1 713 651 0602",
    "sg:postcode":"77002",
    "sg:province":"TX",
    "sg:tags":[
        "management",
        "property"
    ],
    "wof:name":"Navisys Group",
    "wof:placetype":"venue"
},
  "geometry": {"coordinates":[-95.367599,29.755199],"type":"Point"}
}