{
  "type": "Feature",
  "properties": {
    "iso:country":"US",
    "sg:address":"1473 N Mockingbird Ln",
    "sg:city":"Abilene",
    "sg:classifiers":[
        {
            "category":"Building & Trades",
            "subcategory":"Landscaping Services",
            "type":"Services"
        }
    ],
    "sg:phone":"+1 325 675 0065",
    "sg:postcode":"79603",
    "sg:province":"TX",
    "sg:tags":[
        "lawn",
        "maintenance",
        "grounds"
    ],
    "wof:name":"Rey's Lawn Svc",
    "wof:placetype":"venue"
},
  "geometry": {"coordinates":[-99.75773100000001,32.465806],"type":"Point"}
}