{
  "type": "Feature",
  "properties": {
    "iso:country":"US",
    "sg:address":"4140 Legacy Dr",
    "sg:city":"Plano",
    "sg:classifiers":[
        {
            "category":"Professional",
            "type":"Services"
        }
    ],
    "sg:phone":"+1 469 467 8257",
    "sg:postcode":"75024",
    "sg:province":"TX",
    "sg:tags":[
        "establishment"
    ],
    "wof:name":"Barclay Group",
    "wof:placetype":"venue"
},
  "geometry": {"coordinates":[-96.77453,33.07123],"type":"Point"}
}