{
  "type": "Feature",
  "properties": {
    "iso:country":"US",
    "sg:address":"1508 K Ave",
    "sg:city":"Plano",
    "sg:classifiers":[
        {
            "category":"Shopping",
            "subcategory":"Discount & Variety Stores",
            "type":"Retail Goods"
        }
    ],
    "sg:phone":"+1 972 422 7338",
    "sg:postcode":"75074",
    "sg:province":"TX",
    "sg:tags":[
        "merchandise",
        "general"
    ],
    "wof:name":"Dallas Corvette Sales Inc",
    "wof:placetype":"venue"
},
  "geometry": {"coordinates":[-96.699156,33.01994],"type":"Point"}
}