{
  "type": "Feature",
  "properties": {
    "iso:country":"US",
    "sg:address":"5358 W Vickery Blvd",
    "sg:city":"Fort Worth",
    "sg:classifiers":[
        {
            "category":"Building & Trades",
            "subcategory":"Construction",
            "type":"Services"
        }
    ],
    "sg:phone":"+1 817 737 5849",
    "sg:postcode":"76107",
    "sg:province":"TX",
    "sg:tags":[
        "home",
        "builder"
    ],
    "wof:name":"Ramsey Construction Co",
    "wof:placetype":"venue"
},
  "geometry": {"coordinates":[-97.404145,32.712924],"type":"Point"}
}