{
  "type": "Feature",
  "properties": {
    "iso:country":"US",
    "sg:address":"1601 N Hinze Rd",
    "sg:city":"Carmine",
    "sg:classifiers":[
        {
            "category":"Wholesale",
            "subcategory":"Farm Supplies",
            "type":"Manufacturing & Wholesale Goods"
        }
    ],
    "sg:phone":"+1 979 278 3203",
    "sg:postcode":"78932",
    "sg:province":"TX",
    "sg:tags":[
        "corn",
        "livestock"
    ],
    "wof:name":"Howard Fuchs",
    "wof:placetype":"venue"
},
  "geometry": {"coordinates":[-96.65775600000001,30.1316],"type":"Point"}
}