{
  "type": "Feature",
  "properties": {
    "iso:country":"US",
    "sg:address":"580 S Denton Tap Rd",
    "sg:city":"Coppell",
    "sg:classifiers":[
        {
            "category":"Health Services",
            "subcategory":"Doctor",
            "type":"Services"
        }
    ],
    "sg:phone":"+1 972 462 0762",
    "sg:postcode":"75019",
    "sg:province":"TX",
    "sg:tags":[
        "clinic",
        "medical"
    ],
    "wof:name":"Coppell Family Medical Center",
    "wof:placetype":"venue"
},
  "geometry": {"coordinates":[-96.993514,32.95995],"type":"Point"}
}