{
  "type": "Feature",
  "properties": {
    "iso:country":"US",
    "sg:address":"550 N Yarbrough Dr",
    "sg:city":"El Paso",
    "sg:classifiers":[
        {
            "category":"Health Services",
            "subcategory":"Clinic",
            "type":"Services"
        }
    ],
    "sg:phone":"+1 915 599 8810",
    "sg:postcode":"79915",
    "sg:province":"TX",
    "sg:tags":[
        "outpatient",
        "drug"
    ],
    "wof:name":"MI Familia Project",
    "wof:placetype":"venue"
},
  "geometry": {"coordinates":[-106.345006,31.736762],"type":"Point"}
}