{
  "type": "Feature",
  "properties": {
    "iso:country":"US",
    "sg:address":"9404 Timberbluff Rd",
    "sg:city":"Dallas",
    "sg:classifiers":[
        {
            "category":"Professional",
            "type":"Services"
        }
    ],
    "sg:phone":"+1 972 296 4953",
    "sg:postcode":"75249",
    "sg:province":"TX",
    "wof:name":"Odilon Lopez",
    "wof:placetype":"venue"
},
  "geometry": {"coordinates":[-96.94785400000001,32.636416],"type":"Point"}
}