{
  "type": "Feature",
  "properties": {
    "iso:country":"US",
    "sg:address":"748 12th St",
    "sg:city":"Houston",
    "sg:classifiers":[
        {
            "category":"Personal",
            "subcategory":"Beauty Salon",
            "type":"Services"
        }
    ],
    "sg:phone":"+1 713 426 1777",
    "sg:postcode":"77008",
    "sg:province":"TX",
    "sg:tags":[
        "hair"
    ],
    "wof:name":"Studio 12 Salon and Spa",
    "wof:placetype":"venue"
},
  "geometry": {"coordinates":[-95.40546000000001,29.792407],"type":"Point"}
}