{
  "type": "Feature",
  "properties": {
    "iso:country":"US",
    "sg:address":"4580 Beechnut St Apt 201",
    "sg:city":"Houston",
    "sg:classifiers":[
        {
            "category":"Professional",
            "subcategory":"Engineering",
            "type":"Services"
        },
        {
            "category":"Professional",
            "subcategory":"Computer Services",
            "type":"Services"
        }
    ],
    "sg:phone":"+1 713 661 1430",
    "sg:postcode":"77096",
    "sg:province":"TX",
    "sg:tags":[
        "engineer",
        "consultant",
        "designer",
        "integration",
        "system"
    ],
    "sg:website":"http://www.rsinetworking.com",
    "wof:name":"Reliance Systems Inc",
    "wof:placetype":"venue"
},
  "geometry": {"coordinates":[-95.454488,29.689252],"type":"Point"}
}