{
  "type": "Feature",
  "properties": {
    "iso:country":"US",
    "sg:address":"805 E Central Ave",
    "sg:city":"Comanche",
    "sg:classifiers":[
        {
            "category":"Retail",
            "subcategory":"Auto Repair",
            "type":"Services"
        }
    ],
    "sg:phone":"+1 325 356 1599",
    "sg:postcode":"76442",
    "sg:province":"TX",
    "sg:tags":[
        "general"
    ],
    "wof:name":"Ruckers Service",
    "wof:placetype":"venue"
},
  "geometry": {"coordinates":[-98.59404499999999,31.89762],"type":"Point"}
}