{
  "type": "Feature",
  "properties": {
    "iso:country":"US",
    "sg:address":"703 N 7th St",
    "sg:city":"Sanger",
    "sg:classifiers":[
        {
            "category":"Retail",
            "subcategory":"Auto Repair",
            "type":"Services"
        }
    ],
    "sg:phone":"+1 940 458 2838",
    "sg:postcode":"76266",
    "sg:province":"TX",
    "sg:tags":[
        "transmission"
    ],
    "wof:name":"Enlow Motors & Transmissions",
    "wof:placetype":"venue"
},
  "geometry": {"coordinates":[-97.17577900000001,33.36679],"type":"Point"}
}