{
  "type": "Feature",
  "properties": {
    "iso:country":"US",
    "sg:address":"4501 S Pinemont Dr",
    "sg:city":"Houston",
    "sg:classifiers":[
        {
            "category":"Recreation",
            "type":"Entertainment"
        }
    ],
    "sg:phone":"+1 713 524 6666",
    "sg:postcode":"77041",
    "sg:province":"TX",
    "sg:tags":[
        "ticket"
    ],
    "wof:name":"ADOT",
    "wof:placetype":"venue"
},
  "geometry": {"coordinates":[-95.516088,29.836183],"type":"Point"}
}