{
  "type": "Feature",
  "properties": {
    "iso:country":"US",
    "sg:address":"3314 Shady Glen Ln",
    "sg:city":"Missouri City",
    "sg:classifiers":[
        {
            "category":"Freight",
            "type":"Transportation"
        }
    ],
    "sg:phone":"+1 281 499 4083",
    "sg:postcode":"77459",
    "sg:province":"TX",
    "sg:tags":[
        "trucking"
    ],
    "wof:name":"MDG Transport Inc",
    "wof:placetype":"venue"
},
  "geometry": {"coordinates":[-95.555701,29.577763],"type":"Point"}
}