{
  "type": "Feature",
  "properties": {
    "iso:country":"US",
    "sg:address":"14902 Preston Rd Ste 900",
    "sg:city":"Dallas",
    "sg:classifiers":[
        {
            "category":"Personal",
            "subcategory":"Shoe Repair & Shine",
            "type":"Services"
        }
    ],
    "sg:phone":"+1 972 991 9429",
    "sg:postcode":"75254",
    "sg:province":"TX",
    "wof:name":"Akard Shoe Repair",
    "wof:placetype":"venue"
},
  "geometry": {"coordinates":[-96.803596,32.9524],"type":"Point"}
}