{
  "type": "Feature",
  "properties": {
    "iso:country":"US",
    "sg:address":"201 NW 8th St",
    "sg:city":"Andrews",
    "sg:classifiers":[
        {
            "category":"Shopping",
            "subcategory":"Florist",
            "type":"Retail Goods"
        },
        {
            "category":"Food & Beverages",
            "subcategory":"Bakery",
            "type":"Retail Goods"
        }
    ],
    "sg:phone":"+1 432 523 6206",
    "sg:postcode":"79714",
    "sg:province":"TX",
    "sg:tags":[
        "cake",
        "baker",
        "flower",
        "wedding"
    ],
    "wof:name":"Celebrations",
    "wof:placetype":"venue"
},
  "geometry": {"coordinates":[-102.55672800000001,32.318604],"type":"Point"}
}