{
  "type": "Feature",
  "properties": {
    "iso:country":"US",
    "sg:address":"3145 State Hwy 6",
    "sg:city":"Hitchcock",
    "sg:classifiers":[
        {
            "category":"Restaurant",
            "type":"Food & Drink"
        }
    ],
    "sg:phone":"+1 409 935 1200",
    "sg:postcode":"77563",
    "sg:province":"TX",
    "sg:tags":[
        "eating"
    ],
    "wof:name":"Big Daddy's Smoke House & Gril",
    "wof:placetype":"venue"
},
  "geometry": {"coordinates":[-94.9423,29.33144],"type":"Point"}
}