{
  "type": "Feature",
  "properties": {
    "iso:country":"US",
    "sg:address":"7444 W Military Dr",
    "sg:city":"San Antonio",
    "sg:classifiers":[
        {
            "category":"Professional",
            "subcategory":"Employment Agencies",
            "type":"Services"
        }
    ],
    "sg:phone":"+1 210 674 1850",
    "sg:postcode":"78227",
    "sg:province":"TX",
    "sg:tags":[
        "temporary",
        "labor"
    ],
    "wof:name":"Labor Ready",
    "wof:placetype":"venue"
},
  "geometry": {"coordinates":[-98.629586,29.416749],"type":"Point"}
}