{
  "type": "Feature",
  "properties": {
    "iso:country":"US",
    "sg:address":"2640 Elm St",
    "sg:city":"Dallas",
    "sg:classifiers":[
        {
            "category":"Restaurant",
            "type":"Food & Drink"
        }
    ],
    "sg:phone":"+1 214 573 6655",
    "sg:postcode":"75226",
    "sg:province":"TX",
    "wof:name":"Imsonia Coffee Hse & Art Cafe",
    "wof:placetype":"venue"
},
  "geometry": {"coordinates":[-96.784108,32.7845],"type":"Point"}
}