{
  "type": "Feature",
  "properties": {
    "iso:country":"US",
    "sg:address":"3200 Rosedale Ave",
    "sg:city":"Dallas",
    "sg:classifiers":[
        {
            "category":"Professional",
            "type":"Services"
        }
    ],
    "sg:phone":"+1 214 369 6264",
    "sg:postcode":"75205",
    "sg:province":"TX",
    "sg:tags":[
        "arts",
        "artist"
    ],
    "wof:name":"Rebecca Lee Thompson",
    "wof:placetype":"venue"
},
  "geometry": {"coordinates":[-96.78490600000001,32.847592],"type":"Point"}
}