{
  "type": "Feature",
  "properties": {
    "iso:country":"US",
    "sg:address":"8325 White Settlement Rd",
    "sg:city":"Fort Worth",
    "sg:classifiers":[
        {
            "category":"Personal",
            "subcategory":"Beauty Salon",
            "type":"Services"
        }
    ],
    "sg:phone":"+1 817 246 8947",
    "sg:postcode":"76108",
    "sg:province":"TX",
    "sg:tags":[
        "shop"
    ],
    "wof:name":"Lois' Hair Affair",
    "wof:placetype":"venue"
},
  "geometry": {"coordinates":[-97.461237,32.759699],"type":"Point"}
}