{
  "type": "Feature",
  "properties": {
    "iso:country":"US",
    "sg:address":"15725 Lakeview Dr",
    "sg:city":"Houston",
    "sg:classifiers":[
        {
            "category":"Health Services",
            "subcategory":"Clinic",
            "type":"Services"
        }
    ],
    "sg:phone":"+1 713 466 6444",
    "sg:postcode":"77040",
    "sg:province":"TX",
    "wof:name":"Type Connection Inc",
    "wof:placetype":"venue"
},
  "geometry": {"coordinates":[-95.558831,29.885129],"type":"Point"}
}