{
  "type": "Feature",
  "properties": {
    "iso:country":"US",
    "sg:address":"5420 Stonegate Way",
    "sg:city":"Corpus Christi",
    "sg:classifiers":[
        {
            "category":"Real Estate",
            "subcategory":"Real Estate Operator",
            "type":"Services"
        }
    ],
    "sg:phone":"+1 361 654 5555",
    "sg:postcode":"78411",
    "sg:province":"TX",
    "sg:tags":[
        "building",
        "apartment"
    ],
    "wof:name":"Village Park Townhomes",
    "wof:placetype":"venue"
},
  "geometry": {"coordinates":[-97.38853400000001,27.710728],"type":"Point"}
}