{
  "type": "Feature",
  "properties": {
    "iso:country":"US",
    "sg:address":"308 Variah St",
    "sg:city":"Palestine",
    "sg:classifiers":[
        {
            "category":"Organizations",
            "subcategory":"Religious Organization",
            "type":"Services"
        }
    ],
    "sg:phone":"+1 903 729 1112",
    "sg:postcode":"75803",
    "sg:province":"TX",
    "sg:tags":[
        "church"
    ],
    "wof:name":"New Life Seventh Day Adventist",
    "wof:placetype":"venue"
},
  "geometry": {"coordinates":[-95.650204,31.753866],"type":"Point"}
}