{
  "type": "Feature",
  "properties": {
    "iso:country":"US",
    "sg:address":"407 N Horne St",
    "sg:city":"Duncanville",
    "sg:classifiers":[
        {
            "category":"Building & Trades",
            "subcategory":"Plumbing",
            "type":"Services"
        }
    ],
    "sg:phone":"+1 972 298 5523",
    "sg:postcode":"75116",
    "sg:province":"TX",
    "wof:name":"Happy House Plumbing Inc",
    "wof:placetype":"venue"
},
  "geometry": {"coordinates":[-96.915746,32.65454],"type":"Point"}
}