{
  "type": "Feature",
  "properties": {
    "iso:country":"US",
    "sg:address":"3904 Co Rd 302",
    "sg:city":"Granbury",
    "sg:classifiers":[
        {
            "category":"Professional",
            "subcategory":"Management & Consulting",
            "type":"Services"
        }
    ],
    "sg:phone":"+1 817 738 0382",
    "sg:postcode":"76043",
    "sg:province":"TX",
    "sg:tags":[
        "implementation",
        "quality",
        "program",
        "design",
        "assurance"
    ],
    "wof:name":"Doug Henry Consulting",
    "wof:placetype":"venue"
},
  "geometry": {"coordinates":[-97.74417,32.296304],"type":"Point"}
}