{
  "type": "Feature",
  "properties": {
    "iso:country":"US",
    "sg:address":"2304 Stonewall St",
    "sg:city":"Greenville",
    "sg:classifiers":[
        {
            "category":"Social Services",
            "type":"Services"
        }
    ],
    "sg:phone":"+1 903 455 7414",
    "sg:postcode":"75401",
    "sg:province":"TX",
    "sg:tags":[
        "organization",
        "welfare"
    ],
    "wof:name":"United Way Of Hunt County Inc",
    "wof:placetype":"venue"
},
  "geometry": {"coordinates":[-96.10727300000001,33.14115],"type":"Point"}
}