{
  "type": "Feature",
  "properties": {
    "iso:country":"US",
    "sg:address":"6416 Wrigley Way",
    "sg:city":"Fort Worth",
    "sg:classifiers":[
        {
            "category":"Professional",
            "subcategory":"Business Services",
            "type":"Services"
        }
    ],
    "sg:phone":"+1 817 294 9355",
    "sg:postcode":"76133",
    "sg:province":"TX",
    "sg:tags":[
        "interior",
        "consultant",
        "design",
        "decorator"
    ],
    "wof:name":"Joel V Bailey & Assoc",
    "wof:placetype":"venue"
},
  "geometry": {"coordinates":[-97.398664,32.652717],"type":"Point"}
}