{
  "type": "Feature",
  "properties": {
    "iso:country":"US",
    "sg:address":"14247 FM 296",
    "sg:city":"Texline",
    "sg:classifiers":[
        {
            "category":"Wholesale",
            "subcategory":"Machinery & Supplies",
            "type":"Manufacturing & Wholesale Goods"
        }
    ],
    "sg:phone":"+1 806 362 4847",
    "sg:postcode":"79087",
    "sg:province":"TX",
    "sg:tags":[
        "feed",
        "equipment",
        "retail"
    ],
    "wof:name":"Schmidt Irrigation",
    "wof:placetype":"venue"
},
  "geometry": {"coordinates":[-103.028814,36.368251],"type":"Point"}
}