{
  "type": "Feature",
  "properties": {
    "iso:country":"US",
    "sg:address":"1700 S Wheeler St",
    "sg:city":"Jasper",
    "sg:classifiers":[
        {
            "category":"Travel",
            "subcategory":"Hotels & Motels",
            "type":"Entertainment"
        },
        {
            "category":"Travel",
            "subcategory":"Bed & Breakfast",
            "type":"Entertainment"
        }
    ],
    "sg:phone":"+1 409 384 6816",
    "sg:postcode":"75951",
    "sg:province":"TX",
    "sg:tags":[
        "inn",
        "lodging"
    ],
    "sg:website":"http://www.americasbestvalueinn.com/bestv.cfm?idp=1604",
    "wof:name":"Americas Best Value Inn",
    "wof:placetype":"venue"
},
  "geometry": {"coordinates":[-93.993242,30.90398],"type":"Point"}
}