{
  "type": "Feature",
  "properties": {
    "iso:country":"US",
    "sg:address":"1401 Elm St",
    "sg:city":"Dallas",
    "sg:classifiers":[
        {
            "category":"Utilities",
            "subcategory":"Telephone",
            "type":"Services"
        }
    ],
    "sg:phone":"+1 214 749 1292",
    "sg:postcode":"75202",
    "sg:province":"TX",
    "sg:tags":[
        "internet",
        "provider"
    ],
    "wof:name":"Phoenix Internet Texas",
    "wof:placetype":"venue"
},
  "geometry": {"coordinates":[-96.799725,32.78134],"type":"Point"}
}