{
  "type": "Feature",
  "properties": {
    "iso:country":"US",
    "sg:address":"8445 Freeport Pkwy",
    "sg:city":"Irving",
    "sg:classifiers":[
        {
            "category":"Professional",
            "subcategory":"Employment Agencies",
            "type":"Services"
        }
    ],
    "sg:phone":"+1 972 929 2270",
    "sg:postcode":"75063",
    "sg:province":"TX",
    "sg:tags":[
        "consultant",
        "search",
        "executive"
    ],
    "wof:name":"Rise Inc",
    "wof:placetype":"venue"
},
  "geometry": {"coordinates":[-97.018953,32.923298],"type":"Point"}
}