{
  "type": "Feature",
  "properties": {
    "iso:country":"US",
    "sg:address":"3221 Commerce St",
    "sg:city":"Amarillo",
    "sg:classifiers":[
        {
            "category":"Professional",
            "subcategory":"Business Services",
            "type":"Services"
        },
        {
            "category":"Shopping",
            "subcategory":"Crafts & Fabrics",
            "type":"Retail Goods"
        }
    ],
    "sg:phone":"+1 806 352 1152",
    "sg:postcode":"79109",
    "sg:province":"TX",
    "sg:tags":[
        "monogram"
    ],
    "wof:name":"The Monogram Shop",
    "wof:placetype":"venue"
},
  "geometry": {"coordinates":[-101.882717,35.182295],"type":"Point"}
}