{
  "type": "Feature",
  "properties": {
    "iso:country":"US",
    "sg:address":"605 Brookhaven Trl",
    "sg:city":"Austin",
    "sg:classifiers":[
        {
            "category":"Farming",
            "subcategory":"Livestock Farm",
            "type":"Manufacturing & Wholesale Goods"
        }
    ],
    "sg:phone":"+1 512 327 0178",
    "sg:postcode":"78746",
    "sg:province":"TX",
    "sg:tags":[
        "beef",
        "feedlot",
        "cattle"
    ],
    "wof:name":"Rhoda Hornaday",
    "wof:placetype":"venue"
},
  "geometry": {"coordinates":[-97.7991,30.282309],"type":"Point"}
}