{
  "type": "Feature",
  "properties": {
    "iso:country":"US",
    "sg:address":"3500 Sun Bowl Dr",
    "sg:city":"El Paso",
    "sg:classifiers":[
        {
            "category":"Real Estate",
            "subcategory":"Real Estate Operator",
            "type":"Services"
        }
    ],
    "sg:phone":"+1 915 533 0638",
    "sg:postcode":"79902",
    "sg:province":"TX",
    "sg:tags":[
        "apartment"
    ],
    "wof:name":"El Dorado Apartments",
    "wof:placetype":"venue"
},
  "geometry": {"coordinates":[-106.50739400000001,31.783961],"type":"Point"}
}