{
  "type": "Feature",
  "properties": {
    "iso:country":"US",
    "sg:address":"113 N Church St",
    "sg:city":"Brady",
    "sg:classifiers":[
        {
            "category":"Personal",
            "subcategory":"Beauty Salon",
            "type":"Services"
        }
    ],
    "sg:phone":"+1 325 597 9241",
    "sg:postcode":"76825",
    "sg:province":"TX",
    "sg:tags":[
        "shop"
    ],
    "wof:name":"Shorts Kim Nails",
    "wof:placetype":"venue"
},
  "geometry": {"coordinates":[-99.33584,31.135479],"type":"Point"}
}