{
  "type": "Feature",
  "properties": {
    "iso:country":"US",
    "sg:address":"1600 Versailles Dr",
    "sg:city":"Richardson",
    "sg:classifiers":[
        {
            "category":"Manufacturing",
            "subcategory":"Paper Products",
            "type":"Manufacturing & Wholesale Goods"
        }
    ],
    "sg:phone":"+1 972 699 3897",
    "sg:postcode":"75081",
    "sg:province":"TX",
    "sg:tags":[
        "converted",
        "mfg"
    ],
    "wof:name":"Imperial Deco",
    "wof:placetype":"venue"
},
  "geometry": {"coordinates":[-96.69711100000001,32.967951],"type":"Point"}
}