{
  "type": "Feature",
  "properties": {
    "iso:country":"US",
    "sg:address":"7811 Hoover Ave",
    "sg:city":"El Paso",
    "sg:classifiers":[
        {
            "category":"Professional",
            "subcategory":"Employment Agencies",
            "type":"Services"
        }
    ],
    "sg:phone":"+1 915 877 2648",
    "sg:postcode":"79912",
    "sg:province":"TX",
    "sg:tags":[
        "opportunity"
    ],
    "wof:name":"Instaff Personnel",
    "wof:placetype":"venue"
},
  "geometry": {"coordinates":[-106.577045,31.903178],"type":"Point"}
}