{
  "type": "Feature",
  "properties": {
    "iso:country":"US",
    "sg:address":"1422 Bonnie View Rd",
    "sg:city":"Dallas",
    "sg:classifiers":[
        {
            "category":"Personal",
            "subcategory":"Beauty Salon",
            "type":"Services"
        }
    ],
    "sg:phone":"+1 214 946 0088",
    "sg:postcode":"75203",
    "sg:province":"TX",
    "sg:tags":[
        "shop"
    ],
    "wof:name":"Hollywood Cuts",
    "wof:placetype":"venue"
},
  "geometry": {"coordinates":[-96.79300000000001,32.731376],"type":"Point"}
}