{
  "type": "Feature",
  "properties": {
    "iso:country":"US",
    "sg:address":"12605 Bissonnet St",
    "sg:city":"Houston",
    "sg:classifiers":[
        {
            "category":"Social Services",
            "subcategory":"Child Care",
            "type":"Services"
        }
    ],
    "sg:phone":"+1 281 530 3652",
    "sg:postcode":"77099",
    "sg:province":"TX",
    "wof:name":"Creative Child Development Ctr",
    "wof:placetype":"venue"
},
  "geometry": {"coordinates":[-95.600195,29.677247],"type":"Point"}
}