{
  "type": "Feature",
  "properties": {
    "iso:country":"US",
    "sg:address":"4014 Market St",
    "sg:city":"Houston",
    "sg:classifiers":[
        {
            "category":"Social Services",
            "type":"Services"
        }
    ],
    "sg:phone":"+1 713 238 2257",
    "sg:postcode":"77020",
    "sg:province":"TX",
    "sg:tags":[
        "administrative"
    ],
    "wof:name":"Citiznss Assstance Office-East",
    "wof:placetype":"venue"
},
  "geometry": {"coordinates":[-95.329291,29.772607],"type":"Point"}
}