{
  "type": "Feature",
  "properties": {
    "iso:country":"US",
    "sg:address":"8616 Flint Ave",
    "sg:city":"Lubbock",
    "sg:classifiers":[
        {
            "category":"Professional",
            "subcategory":"Business Services",
            "type":"Services"
        }
    ],
    "sg:phone":"+1 806 745 8851",
    "sg:postcode":"79423",
    "sg:province":"TX",
    "wof:name":"Ric Shaw Jr Enterprises",
    "wof:placetype":"venue"
},
  "geometry": {"coordinates":[-101.88084000000001,33.514485],"type":"Point"}
}