{
  "type": "Feature",
  "properties": {
    "iso:country":"US",
    "sg:address":"365 E Pecan St",
    "sg:city":"Hurst",
    "sg:classifiers":[
        {
            "category":"Real Estate",
            "subcategory":"Real Estate Operator",
            "type":"Services"
        }
    ],
    "sg:phone":"+1 817 280 0497",
    "sg:postcode":"76053",
    "sg:province":"TX",
    "sg:tags":[
        "building",
        "apartment"
    ],
    "wof:name":"Team Management",
    "wof:placetype":"venue"
},
  "geometry": {"coordinates":[-97.16412200000001,32.819422],"type":"Point"}
}