{
  "type": "Feature",
  "properties": {
    "iso:country":"US",
    "sg:address":"2613 Alexa Ct",
    "sg:city":"Plano",
    "sg:classifiers":[
        {
            "category":"Professional",
            "subcategory":"Management & Consulting",
            "type":"Services"
        }
    ],
    "sg:phone":"+1 972 596 6061",
    "sg:postcode":"75075",
    "sg:province":"TX",
    "sg:tags":[
        "business"
    ],
    "wof:name":"Xtreme Consulting",
    "wof:placetype":"venue"
},
  "geometry": {"coordinates":[-96.73677000000001,33.033187],"type":"Point"}
}