{
  "type": "Feature",
  "properties": {
    "iso:country":"US",
    "sg:address":"2222 Commerce Dr",
    "sg:city":"Arlington",
    "sg:classifiers":[
        {
            "category":"Building & Trades",
            "subcategory":"Construction",
            "type":"Services"
        }
    ],
    "sg:phone":"+1 817 640 9200",
    "sg:postcode":"76011",
    "sg:province":"TX",
    "sg:tags":[
        "foundation"
    ],
    "wof:name":"All American Foundation Repair",
    "wof:placetype":"venue"
},
  "geometry": {"coordinates":[-97.06948199999999,32.744419],"type":"Point"}
}