{
  "type": "Feature",
  "properties": {
    "iso:country":"US",
    "sg:address":"17950 Preston Rd Ste 640",
    "sg:city":"Dallas",
    "sg:classifiers":[
        {
            "category":"Professional",
            "subcategory":"Lawyer & Legal Services",
            "type":"Services"
        }
    ],
    "sg:phone":"+1 972 387 4409",
    "sg:postcode":"75252",
    "sg:province":"TX",
    "wof:name":"Goenawein Wesley A Atty",
    "wof:placetype":"venue"
},
  "geometry": {"coordinates":[-96.797574,32.996395],"type":"Point"}
}