{
  "type": "Feature",
  "properties": {
    "iso:country":"US",
    "sg:address":"615 E Pecan St",
    "sg:city":"Sherman",
    "sg:classifiers":[
        {
            "category":"Recreation",
            "type":"Entertainment"
        }
    ],
    "sg:phone":"+1 903 893 1400",
    "sg:postcode":"75090",
    "sg:province":"TX",
    "sg:tags":[
        "club",
        "membership"
    ],
    "wof:name":"Studio One",
    "wof:placetype":"venue"
},
  "geometry": {"coordinates":[-96.602313,33.640124],"type":"Point"}
}