{
  "type": "Feature",
  "properties": {
    "iso:country":"US",
    "sg:address":"9124 Co Rd 523",
    "sg:city":"Burleson",
    "sg:classifiers":[
        {
            "category":"Wholesale",
            "subcategory":"Durable Goods & Equipment",
            "type":"Manufacturing & Wholesale Goods"
        }
    ],
    "sg:phone":"+1 817 419 0690",
    "sg:postcode":"76028",
    "sg:province":"TX",
    "sg:tags":[
        "representative",
        "manufacturer"
    ],
    "wof:name":"Air Representatives Inc",
    "wof:placetype":"venue"
},
  "geometry": {"coordinates":[-97.221778,32.507574],"type":"Point"}
}