{
  "type": "Feature",
  "properties": {
    "iso:country":"US",
    "sg:address":"1619 Post Office St",
    "sg:city":"Galveston",
    "sg:classifiers":[
        {
            "category":"Professional",
            "subcategory":"Lawyer & Legal Services",
            "type":"Services"
        }
    ],
    "sg:phone":"+1 409 762 3500",
    "sg:postcode":"77550",
    "sg:province":"TX",
    "sg:tags":[
        "attorney"
    ],
    "wof:name":"G Earnest Caldwell PC",
    "wof:placetype":"venue"
},
  "geometry": {"coordinates":[-94.786424,29.306303],"type":"Point"}
}