{
  "type": "Feature",
  "properties": {
    "iso:country":"US",
    "sg:address":"220 W 6th St",
    "sg:city":"San Juan",
    "sg:classifiers":[
        {
            "category":"Education",
            "subcategory":"Special Training",
            "type":"Public Place"
        }
    ],
    "sg:phone":"+1 956 781 4559",
    "sg:postcode":"78589",
    "sg:province":"TX",
    "wof:name":"Martinez Driving School",
    "wof:placetype":"venue"
},
  "geometry": {"coordinates":[-98.15848099999999,26.18898],"type":"Point"}
}