{
  "type": "Feature",
  "properties": {
    "iso:country":"US",
    "sg:address":"7513 Cimarron Dr",
    "sg:city":"Fort Worth",
    "sg:classifiers":[
        {
            "category":"Wholesale",
            "subcategory":"Machinery & Supplies",
            "type":"Manufacturing & Wholesale Goods"
        }
    ],
    "sg:phone":"+1 817 485 2402",
    "sg:postcode":"76180",
    "sg:province":"TX",
    "sg:tags":[
        "industrial"
    ],
    "wof:name":"Diversified Industries Inc",
    "wof:placetype":"venue"
},
  "geometry": {"coordinates":[-97.228195,32.884297],"type":"Point"}
}