{
  "type": "Feature",
  "properties": {
    "iso:country":"US",
    "sg:address":"7900 Fm 1826 Ste 120",
    "sg:city":"Austin",
    "sg:classifiers":[
        {
            "category":"Health Services",
            "subcategory":"Doctor",
            "type":"Services"
        }
    ],
    "sg:phone":"+1 512 322 9163",
    "sg:postcode":"78737",
    "sg:province":"TX",
    "wof:name":"Welsh Scott MD",
    "wof:placetype":"venue"
},
  "geometry": {"coordinates":[-97.888447,30.229248],"type":"Point"}
}