{
  "type": "Feature",
  "properties": {
    "iso:country":"US",
    "sg:address":"1801 Kinney Ave",
    "sg:city":"Austin",
    "sg:classifiers":[
        {
            "category":"Organizations",
            "subcategory":"Religious Organization",
            "type":"Services"
        }
    ],
    "sg:phone":"+1 512 442 6719",
    "sg:postcode":"78704",
    "sg:province":"TX",
    "sg:tags":[
        "church"
    ],
    "wof:name":"Kinney Ave Baptist Church Inc",
    "wof:placetype":"venue"
},
  "geometry": {"coordinates":[-97.76881,30.25135],"type":"Point"}
}