{
  "type": "Feature",
  "properties": {
    "iso:country":"US",
    "sg:address":"2425 Riverside Dr",
    "sg:city":"Houston",
    "sg:classifiers":[
        {
            "category":"Personal",
            "subcategory":"Barber",
            "type":"Services"
        }
    ],
    "sg:phone":"+1 713 528 8148",
    "sg:postcode":"77004",
    "sg:province":"TX",
    "wof:name":"Houston Barber Shop",
    "wof:placetype":"venue"
},
  "geometry": {"coordinates":[-95.37751,29.71701],"type":"Point"}
}