{
  "type": "Feature",
  "properties": {
    "iso:country":"US",
    "sg:address":"3006 Spurlock St",
    "sg:city":"Dallas",
    "sg:classifiers":[
        {
            "category":"Personal",
            "subcategory":"Beauty Salon",
            "type":"Services"
        }
    ],
    "sg:phone":"+1 214 887 8177",
    "sg:postcode":"75223",
    "sg:province":"TX",
    "sg:tags":[
        "shop"
    ],
    "wof:name":"Designer Cuts & Wraps",
    "wof:placetype":"venue"
},
  "geometry": {"coordinates":[-96.743909,32.785406],"type":"Point"}
}