{
  "type": "Feature",
  "properties": {
    "iso:country":"US",
    "sg:address":"2734 Blake St",
    "sg:city":"Corpus Christi",
    "sg:classifiers":[
        {
            "category":"Restaurant",
            "type":"Food & Drink"
        }
    ],
    "sg:phone":"+1 361 814 1500",
    "sg:postcode":"78405",
    "sg:province":"TX",
    "sg:tags":[
        "eating"
    ],
    "wof:name":"J Eguias Bakery",
    "wof:placetype":"venue"
},
  "geometry": {"coordinates":[-97.42528900000001,27.775928],"type":"Point"}
}