{
  "type": "Feature",
  "properties": {
    "iso:country":"US",
    "sg:address":"1111 Augusta Dr",
    "sg:city":"Houston",
    "sg:classifiers":[
        {
            "category":"Health Services",
            "subcategory":"Doctor",
            "type":"Services"
        },
        {
            "category":"Health Services",
            "subcategory":"Hospital",
            "type":"Services"
        }
    ],
    "sg:phone":"+1 713 442 2400",
    "sg:postcode":"77057",
    "sg:province":"TX",
    "sg:tags":[
        "obstetrician",
        "gynecologist"
    ],
    "sg:website":"www.kelseyseyboldclinic.com",
    "wof:name":"Shah Sonal MD",
    "wof:placetype":"venue"
},
  "geometry": {"coordinates":[-95.482597,29.7565],"type":"Point"}
}