{
  "type": "Feature",
  "properties": {
    "iso:country":"US",
    "sg:address":"1817 Sealy St",
    "sg:city":"Galveston",
    "sg:classifiers":[
        {
            "category":"Shopping",
            "subcategory":"Clothing, Apparel, & Fashions",
            "type":"Retail Goods"
        }
    ],
    "sg:phone":"+1 409 766 7557",
    "sg:postcode":"77550",
    "sg:province":"TX",
    "wof:name":"Ann Santee Mcafee Retail",
    "wof:placetype":"venue"
},
  "geometry": {"coordinates":[-94.787554,29.302227],"type":"Point"}
}