{
  "type": "Feature",
  "properties": {
    "iso:country":"US",
    "sg:address":"14421 Fm 849",
    "sg:city":"Lindale",
    "sg:classifiers":[
        {
            "category":"Building & Trades",
            "subcategory":"Landscaping Services",
            "type":"Services"
        },
        {
            "category":"Manufacturing",
            "subcategory":"Paper Products",
            "type":"Manufacturing & Wholesale Goods"
        }
    ],
    "sg:phone":"+1 903 882 8610",
    "sg:postcode":"75771",
    "sg:province":"TX",
    "sg:tags":[
        "bamboo",
        "tree"
    ],
    "sg:website":"http://www.treesusa.com",
    "wof:name":"Trees USA",
    "wof:placetype":"venue"
},
  "geometry": {"coordinates":[-95.43380500000001,32.489373],"type":"Point"}
}