{
  "type": "Feature",
  "properties": {
    "iso:country":"US",
    "sg:address":"2527 Willowbrook Rd",
    "sg:city":"Dallas",
    "sg:classifiers":[
        {
            "category":"Insurance",
            "subcategory":"Hazard Insurance",
            "type":"Services"
        }
    ],
    "sg:phone":"+1 214 351 6875",
    "sg:postcode":"75220",
    "sg:province":"TX",
    "sg:tags":[
        "bond"
    ],
    "wof:name":"Day & Night Bail Bond Svc",
    "wof:placetype":"venue"
},
  "geometry": {"coordinates":[-96.883859,32.861661],"type":"Point"}
}