{
  "type": "Feature",
  "properties": {
    "iso:country":"US",
    "sg:address":"5722 Westbrook Rd",
    "sg:city":"Houston",
    "sg:classifiers":[
        {
            "category":"Personal",
            "subcategory":"Beauty Salon",
            "type":"Services"
        }
    ],
    "sg:phone":"+1 713 633 4070",
    "sg:postcode":"77016",
    "sg:province":"TX",
    "sg:tags":[
        "shop"
    ],
    "wof:name":"Revon Hair & Care",
    "wof:placetype":"venue"
},
  "geometry": {"coordinates":[-95.314635,29.856055],"type":"Point"}
}