{
  "type": "Feature",
  "properties": {
    "iso:country":"US",
    "sg:address":"4222 Harry Hines Blvd",
    "sg:city":"Dallas",
    "sg:classifiers":[
        {
            "category":"Autos & Motor Vehicles",
            "subcategory":"Auto Supplies",
            "type":"Retail Goods"
        }
    ],
    "sg:phone":"+1 214 520 6583",
    "sg:postcode":"75219",
    "sg:province":"TX",
    "sg:tags":[
        "glass"
    ],
    "wof:name":"Binswanger Glass Company",
    "wof:placetype":"venue"
},
  "geometry": {"coordinates":[-96.821701,32.804699],"type":"Point"}
}