{
  "type": "Feature",
  "properties": {
    "iso:country":"US",
    "sg:address":"3306 Greenwood Glen Dr",
    "sg:city":"Humble",
    "sg:classifiers":[
        {
            "category":"Real Estate",
            "subcategory":"Surveying",
            "type":"Services"
        }
    ],
    "sg:phone":"+1 281 360 2244",
    "sg:postcode":"77345",
    "sg:province":"TX",
    "wof:name":"Texas Speleological Survey",
    "wof:placetype":"venue"
},
  "geometry": {"coordinates":[-95.17731000000001,30.061848],"type":"Point"}
}