{
  "type": "Feature",
  "properties": {
    "iso:country":"US",
    "sg:address":"5050 Grace Ln",
    "sg:city":"Brenham",
    "sg:classifiers":[
        {
            "category":"Professional",
            "subcategory":"Business Services",
            "type":"Services"
        }
    ],
    "sg:phone":"+1 979 836 2923",
    "sg:postcode":"77833",
    "sg:province":"TX",
    "wof:name":"Heartland Enterprises",
    "wof:placetype":"venue"
},
  "geometry": {"coordinates":[-96.342119,30.209051],"type":"Point"}
}