{
  "type": "Feature",
  "properties": {
    "iso:country":"US",
    "sg:address":"1024 Orlando Cir",
    "sg:city":"Plano",
    "sg:classifiers":[
        {
            "category":"Building & Trades",
            "subcategory":"Plumbing",
            "type":"Services"
        }
    ],
    "sg:phone":"+1 972 422 4438",
    "sg:postcode":"75075",
    "sg:province":"TX",
    "sg:tags":[
        "conditioning",
        "contractor"
    ],
    "wof:name":"All About Air Inc",
    "wof:placetype":"venue"
},
  "geometry": {"coordinates":[-96.71616400000001,33.030885],"type":"Point"}
}