{
  "type": "Feature",
  "properties": {
    "iso:country":"US",
    "sg:address":"1717 Woodland Dr",
    "sg:city":"Laredo",
    "sg:classifiers":[
        {
            "category":"Professional",
            "subcategory":"Management & Consulting",
            "type":"Services"
        }
    ],
    "sg:phone":"+1 956 726 9140",
    "sg:postcode":"78045",
    "sg:province":"TX",
    "wof:name":"S & R Marketing",
    "wof:placetype":"venue"
},
  "geometry": {"coordinates":[-99.465479,27.59805],"type":"Point"}
}