{
  "type": "Feature",
  "properties": {
    "iso:country":"US",
    "sg:address":"13331 Veterans Memorial Dr",
    "sg:city":"Houston",
    "sg:classifiers":[
        {
            "category":"Retail",
            "subcategory":"Car Wash",
            "type":"Services"
        }
    ],
    "sg:phone":"+1 281 580 3126",
    "sg:postcode":"77014",
    "sg:province":"TX",
    "sg:tags":[
        "carwash"
    ],
    "wof:name":"Auto-Kleen USA",
    "wof:placetype":"venue"
},
  "geometry": {"coordinates":[-95.49278099999999,29.980328],"type":"Point"}
}