{
  "type": "Feature",
  "properties": {
    "iso:country":"US",
    "sg:address":"930 Fm 1092 Rd",
    "sg:city":"Missouri City",
    "sg:classifiers":[
        {
            "category":"Education",
            "subcategory":"School",
            "type":"Public Place"
        }
    ],
    "sg:phone":"+1 281 208 8115",
    "sg:postcode":"77459",
    "sg:province":"TX",
    "wof:name":"L Lowell Byrd Acadamy",
    "wof:placetype":"venue"
},
  "geometry": {"coordinates":[-95.564499,29.6057],"type":"Point"}
}