{
  "type": "Feature",
  "properties": {
    "iso:country":"US",
    "sg:address":"16836 State Hwy 3",
    "sg:city":"Webster",
    "sg:classifiers":[
        {
            "category":"Shopping",
            "subcategory":"Crafts & Fabrics",
            "type":"Retail Goods"
        }
    ],
    "sg:phone":"+1 281 332 3216",
    "sg:postcode":"77598",
    "sg:province":"TX",
    "sg:tags":[
        "sewing"
    ],
    "wof:name":"Elegant Stitch",
    "wof:placetype":"venue"
},
  "geometry": {"coordinates":[-95.128339,29.548539],"type":"Point"}
}