{
  "type": "Feature",
  "properties": {
    "iso:country":"US",
    "sg:address":"1025 Central Expy",
    "sg:city":"Plano",
    "sg:classifiers":[
        {
            "category":"Building & Trades",
            "subcategory":"Construction",
            "type":"Services"
        }
    ],
    "sg:phone":"+1 972 896 4485",
    "sg:postcode":"75075",
    "sg:province":"TX",
    "sg:tags":[
        "contractor"
    ],
    "wof:name":"Groves Demolition",
    "wof:placetype":"venue"
},
  "geometry": {"coordinates":[-96.708913,33.0155],"type":"Point"}
}