{
  "type": "Feature",
  "properties": {
    "iso:country":"US",
    "sg:address":"6003 Gardenridge Hollow",
    "sg:city":"Austin",
    "sg:classifiers":[
        {
            "category":"Professional",
            "type":"Services"
        }
    ],
    "sg:phone":"+1 512 345 3573",
    "sg:postcode":"78750",
    "sg:province":"TX",
    "sg:tags":[
        "establishment"
    ],
    "wof:name":"Outernet",
    "wof:placetype":"venue"
},
  "geometry": {"coordinates":[-97.789276,30.371057],"type":"Point"}
}