{
  "type": "Feature",
  "properties": {
    "iso:country":"US",
    "sg:address":"17326 Butera Rd",
    "sg:city":"Magnolia",
    "sg:classifiers":[
        {
            "category":"Organizations",
            "subcategory":"Religious Organization",
            "type":"Services"
        }
    ],
    "sg:phone":"+1 281 259 0696",
    "sg:postcode":"77355",
    "sg:province":"TX",
    "sg:tags":[
        "church"
    ],
    "wof:name":"Walnut Creek Baptist Church of",
    "wof:placetype":"venue"
},
  "geometry": {"coordinates":[-95.74339500000001,30.133906],"type":"Point"}
}