{
  "type": "Feature",
  "properties": {
    "iso:country":"US",
    "sg:address":"404 W Mary Jane Dr",
    "sg:city":"Killeen",
    "sg:classifiers":[
        {
            "category":"Building & Trades",
            "subcategory":"Landscaping Services",
            "type":"Services"
        }
    ],
    "sg:phone":"+1 254 634 0906",
    "sg:postcode":"76541",
    "sg:province":"TX",
    "wof:name":"Randy & Pj Lawn Service",
    "wof:placetype":"venue"
},
  "geometry": {"coordinates":[-97.738998,31.105411],"type":"Point"}
}