{
  "type": "Feature",
  "properties": {
    "iso:country":"US",
    "sg:address":"1122 Highbush Dr",
    "sg:city":"Fort Worth",
    "sg:classifiers":[
        {
            "category":"Manufacturing",
            "subcategory":"Jewelry",
            "type":"Manufacturing & Wholesale Goods"
        }
    ],
    "sg:phone":"+1 817 249 6903",
    "sg:postcode":"76126",
    "sg:province":"TX",
    "sg:tags":[
        "precious",
        "metal",
        "mfg"
    ],
    "wof:name":"Prairie Rose",
    "wof:placetype":"venue"
},
  "geometry": {"coordinates":[-97.450749,32.67534],"type":"Point"}
}