{
  "type": "Feature",
  "properties": {
    "iso:country":"US",
    "sg:address":"11602 Stancliff Rd",
    "sg:city":"Houston",
    "sg:classifiers":[
        {
            "category":"Shopping",
            "subcategory":"Clothing, Apparel, & Fashions",
            "type":"Retail Goods"
        }
    ],
    "sg:phone":"+1 281 530 7097",
    "sg:postcode":"77099",
    "sg:province":"TX",
    "wof:name":"Tsunami Clothing",
    "wof:placetype":"venue"
},
  "geometry": {"coordinates":[-95.58379499999999,29.66322],"type":"Point"}
}