{
  "type": "Feature",
  "properties": {
    "iso:country":"US",
    "sg:address":"10786 Bellaire Blvd",
    "sg:city":"Houston",
    "sg:classifiers":[
        {
            "category":"Health Services",
            "subcategory":"Chiropractor",
            "type":"Services"
        }
    ],
    "sg:phone":"+1 281 933 8000",
    "sg:postcode":"77072",
    "sg:province":"TX",
    "sg:tags":[
        "chiropractic"
    ],
    "wof:name":"Bellaire Chiropractic Clinic",
    "wof:placetype":"venue"
},
  "geometry": {"coordinates":[-95.569005,29.704011],"type":"Point"}
}