{
  "type": "Feature",
  "properties": {
    "iso:country":"US",
    "sg:address":"8800 Citypark Loop",
    "sg:city":"Houston",
    "sg:classifiers":[
        {
            "category":"Professional",
            "subcategory":"Detective & Security Services",
            "type":"Services"
        }
    ],
    "sg:phone":"+1 713 678 4633",
    "sg:postcode":"77013",
    "sg:province":"TX",
    "sg:tags":[
        "car"
    ],
    "wof:name":"American Citadel Guards",
    "wof:placetype":"venue"
},
  "geometry": {"coordinates":[-95.267431,29.80172],"type":"Point"}
}