{
  "type": "Feature",
  "properties": {
    "iso:country":"US",
    "sg:address":"2703 Grissom Rd",
    "sg:city":"Webster",
    "sg:classifiers":[
        {
            "category":"Building & Trades",
            "subcategory":"Pest Control",
            "type":"Services"
        }
    ],
    "sg:phone":"+1 281 338 2733",
    "sg:postcode":"77598",
    "sg:province":"TX",
    "wof:name":"Rikson Pest Control Inc",
    "wof:placetype":"venue"
},
  "geometry": {"coordinates":[-95.142861,29.513804],"type":"Point"}
}