{
  "type": "Feature",
  "properties": {
    "iso:country":"US",
    "sg:address":"4227 Glenchase Ln",
    "sg:city":"Houston",
    "sg:classifiers":[
        {
            "category":"Building & Trades",
            "subcategory":"Construction",
            "type":"Services"
        }
    ],
    "sg:phone":"+1 281 893 8469",
    "sg:postcode":"77014",
    "sg:province":"TX",
    "sg:tags":[
        "house"
    ],
    "wof:name":"Vircon Builders",
    "wof:placetype":"venue"
},
  "geometry": {"coordinates":[-95.487737,29.982234],"type":"Point"}
}