{
  "type": "Feature",
  "properties": {
    "iso:country":"US",
    "sg:address":"11160 Goodnight Ln",
    "sg:city":"Dallas",
    "sg:classifiers":[
        {
            "category":"Building & Trades",
            "subcategory":"Landscaping Services",
            "type":"Services"
        }
    ],
    "sg:phone":"+1 972 488 3866",
    "sg:postcode":"75229",
    "sg:province":"TX",
    "sg:tags":[
        "tree"
    ],
    "wof:name":"Gallery Lawn Treatment Svc",
    "wof:placetype":"venue"
},
  "geometry": {"coordinates":[-96.90186799999999,32.886923],"type":"Point"}
}