{
  "type": "Feature",
  "properties": {
    "iso:country":"US",
    "sg:address":"9188 Jamaica Beach",
    "sg:city":"Galveston",
    "sg:classifiers":[
        {
            "category":"Building & Trades",
            "subcategory":"Construction",
            "type":"Services"
        }
    ],
    "sg:phone":"+1 409 737 4152",
    "sg:postcode":"77554",
    "sg:province":"TX",
    "sg:tags":[
        "nonresidential"
    ],
    "wof:name":"James Drywall & Remodeling",
    "wof:placetype":"venue"
},
  "geometry": {"coordinates":[-94.978013,29.178286],"type":"Point"}
}