{
  "type": "Feature",
  "properties": {
    "iso:country":"US",
    "sg:address":"4202 N Hills Dr",
    "sg:city":"Austin",
    "sg:classifiers":[
        {
            "category":"Professional",
            "subcategory":"Business Services",
            "type":"Services"
        }
    ],
    "sg:phone":"+1 512 346 1559",
    "sg:postcode":"78731",
    "sg:province":"TX",
    "wof:name":"Apex Partnership LP",
    "wof:placetype":"venue"
},
  "geometry": {"coordinates":[-97.7688,30.359961],"type":"Point"}
}