{
  "type": "Feature",
  "properties": {
    "iso:country":"US",
    "sg:address":"335 Partridge Ln",
    "sg:city":"Houston",
    "sg:classifiers":[
        {
            "category":"Retail",
            "subcategory":"Portrait Studio",
            "type":"Services"
        }
    ],
    "sg:phone":"+1 281 445 8184",
    "sg:postcode":"77060",
    "sg:province":"TX",
    "sg:tags":[
        "photo"
    ],
    "wof:name":"Hairston Photography",
    "wof:placetype":"venue"
},
  "geometry": {"coordinates":[-95.397086,29.927963],"type":"Point"}
}