{
  "type": "Feature",
  "properties": {
    "iso:country":"US",
    "sg:address":"2620 Old Columbus Rd",
    "sg:city":"Sealy",
    "sg:classifiers":[
        {
            "category":"Wholesale",
            "subcategory":"Apparel",
            "type":"Manufacturing & Wholesale Goods"
        }
    ],
    "sg:phone":"+1 979 885 6526",
    "sg:postcode":"77474",
    "sg:province":"TX",
    "sg:tags":[
        "fabric"
    ],
    "wof:name":"Upholstery Shop",
    "wof:placetype":"venue"
},
  "geometry": {"coordinates":[-96.290001,29.745387],"type":"Point"}
}