{
  "type": "Feature",
  "properties": {
    "iso:country":"US",
    "sg:address":"2723 Valley View Ln",
    "sg:city":"Dallas",
    "sg:classifiers":[
        {
            "category":"Professional",
            "subcategory":"Management & Consulting",
            "type":"Services"
        }
    ],
    "sg:phone":"+1 972 239 1911",
    "sg:postcode":"75234",
    "sg:province":"TX",
    "sg:tags":[
        "consultant",
        "business"
    ],
    "sg:website":"www.marketresearchdallas.com",
    "wof:name":"Market Research Dallas",
    "wof:placetype":"venue"
},
  "geometry": {"coordinates":[-96.885335,32.924632],"type":"Point"}
}