{
  "type": "Feature",
  "properties": {
    "iso:country":"US",
    "sg:address":"735 Ferrari Dr",
    "sg:city":"Humble",
    "sg:classifiers":[
        {
            "category":"Home & Garden",
            "subcategory":"Mobile Homes",
            "type":"Retail Goods"
        }
    ],
    "sg:phone":"+1 281 441 1470",
    "sg:postcode":"77396",
    "sg:province":"TX",
    "wof:name":"Diamante Developers LLC",
    "wof:placetype":"venue"
},
  "geometry": {"coordinates":[-95.254975,29.960727],"type":"Point"}
}