{
  "type": "Feature",
  "properties": {
    "iso:country":"US",
    "sg:address":"2309 Investment Dr",
    "sg:city":"Pflugerville",
    "sg:classifiers":[
        {
            "category":"Professional",
            "subcategory":"Printing & Photocopies",
            "type":"Services"
        }
    ],
    "sg:phone":"+1 512 252 8751",
    "sg:postcode":"78660",
    "sg:province":"TX",
    "sg:tags":[
        "lithographer"
    ],
    "wof:name":"A S M Lithography Inc",
    "wof:placetype":"venue"
},
  "geometry": {"coordinates":[-97.629413,30.401199],"type":"Point"}
}