{
  "type": "Feature",
  "properties": {
    "iso:country":"US",
    "sg:address":"14222 Gulf Fwy",
    "sg:city":"Houston",
    "sg:classifiers":[
        {
            "category":"Professional",
            "subcategory":"Computer Services",
            "type":"Services"
        }
    ],
    "sg:phone":"+1 281 484 4900",
    "sg:postcode":"77034",
    "sg:province":"TX",
    "sg:tags":[
        "repair"
    ],
    "sg:website":"www.nrerealty.com",
    "wof:name":"Nre Realty",
    "wof:placetype":"venue"
},
  "geometry": {"coordinates":[-95.19499999999999,29.5956],"type":"Point"}
}