{
  "type": "Feature",
  "properties": {
    "iso:country":"US",
    "sg:address":"600 West St",
    "sg:city":"Sealy",
    "sg:classifiers":[
        {
            "category":"Organizations",
            "subcategory":"Religious Organization",
            "type":"Services"
        }
    ],
    "sg:phone":"+1 979 885 6023",
    "sg:postcode":"77474",
    "sg:province":"TX",
    "sg:tags":[
        "church"
    ],
    "wof:name":"Church Of Jesus Christ Of Lds",
    "wof:placetype":"venue"
},
  "geometry": {"coordinates":[-96.16373900000001,29.776349],"type":"Point"}
}