{
  "type": "Feature",
  "properties": {
    "iso:country":"US",
    "sg:address":"4032 Vance Jackson Rd",
    "sg:city":"San Antonio",
    "sg:classifiers":[
        {
            "category":"Bars & Pubs",
            "type":"Food & Drink"
        }
    ],
    "sg:phone":"+1 210 340 0656",
    "sg:postcode":"78213",
    "sg:province":"TX",
    "sg:tags":[
        "lounge",
        "cocktail"
    ],
    "wof:name":"Club Calico",
    "wof:placetype":"venue"
},
  "geometry": {"coordinates":[-98.535048,29.511122],"type":"Point"}
}