{
  "type": "Feature",
  "properties": {
    "iso:country":"US",
    "sg:address":"1700 Commerce St",
    "sg:city":"Dallas",
    "sg:classifiers":[
        {
            "category":"Professional",
            "subcategory":"Computer Services",
            "type":"Services"
        }
    ],
    "sg:phone":"+1 214 358 6481",
    "sg:postcode":"75201",
    "sg:province":"TX",
    "sg:tags":[
        "consultant",
        "designer"
    ],
    "sg:website":"www.ecom-inc.com",
    "wof:name":"ECOM Computer Consultants",
    "wof:placetype":"venue"
},
  "geometry": {"coordinates":[-96.796134,32.780512],"type":"Point"}
}