{
  "type": "Feature",
  "properties": {
    "iso:country":"US",
    "sg:address":"4514 Cole Ave",
    "sg:city":"Dallas",
    "sg:classifiers":[
        {
            "category":"Professional",
            "subcategory":"Detective & Security Services",
            "type":"Services"
        }
    ],
    "sg:phone":"+1 214 447 7042",
    "sg:postcode":"75205",
    "sg:province":"TX",
    "sg:tags":[
        "system"
    ],
    "wof:name":"Dallas Video Security Systems",
    "wof:placetype":"venue"
},
  "geometry": {"coordinates":[-96.789215,32.82181],"type":"Point"}
}