{
  "type": "Feature",
  "properties": {
    "iso:country":"US",
    "sg:address":"80 State Hwy 24 Bus",
    "sg:city":"Cooper",
    "sg:classifiers":[
        {
            "category":"Organizations",
            "subcategory":"Professional Association",
            "type":"Services"
        }
    ],
    "sg:phone":"+1 903 395 4471",
    "sg:postcode":"75432",
    "sg:province":"TX",
    "sg:tags":[
        "district",
        "utility"
    ],
    "wof:name":"Delta Cnty Municpl Utility Dst",
    "wof:placetype":"venue"
},
  "geometry": {"coordinates":[-95.68865,33.373981],"type":"Point"}
}