{
  "type": "Feature",
  "properties": {
    "iso:country":"US",
    "sg:address":"1921 1/2 Greenville Ave Studio A",
    "sg:city":"Dallas",
    "sg:classifiers":[
        {
            "category":"Personal",
            "subcategory":"Beauty Salon",
            "type":"Services"
        }
    ],
    "sg:phone":"+1 432 352 8383",
    "sg:postcode":"75206",
    "sg:province":"TX",
    "sg:tags":[
        "makeup",
        "artist"
    ],
    "sg:website":"www.tcmakeup.com",
    "wof:name":"TCMakeup Studio",
    "wof:placetype":"venue"
},
  "geometry": {"coordinates":[-96.770228,32.813741],"type":"Point"}
}