{
  "type": "Feature",
  "properties": {
    "iso:country":"US",
    "sg:address":"3807 Craig St",
    "sg:city":"Bryan",
    "sg:classifiers":[
        {
            "category":"Professional",
            "subcategory":"Management & Consulting",
            "type":"Services"
        }
    ],
    "sg:phone":"+1 979 268 1570",
    "sg:postcode":"77802",
    "sg:province":"TX",
    "sg:tags":[
        "business"
    ],
    "wof:name":"J M Educational Consulting",
    "wof:placetype":"venue"
},
  "geometry": {"coordinates":[-96.33838299999999,30.644257],"type":"Point"}
}