{
  "type": "Feature",
  "properties": {
    "iso:country":"US",
    "sg:address":"1404 E 6th St",
    "sg:city":"Irving",
    "sg:classifiers":[
        {
            "category":"Restaurant",
            "type":"Food & Drink"
        }
    ],
    "sg:phone":"+1 972 870 0135",
    "sg:postcode":"75060",
    "sg:province":"TX",
    "sg:tags":[
        "new",
        "american",
        "mexican",
        "tex-mex"
    ],
    "sg:website":"mayrasrestaurant.com",
    "wof:name":"Mayra's Restaurant",
    "wof:placetype":"venue"
},
  "geometry": {"coordinates":[-96.92966800000001,32.80833],"type":"Point"}
}