{
  "type": "Feature",
  "properties": {
    "iso:country":"US",
    "sg:address":"575 Vesper",
    "sg:city":"New Braunfels",
    "sg:classifiers":[
        {
            "category":"Shopping",
            "subcategory":"Used Merchandise",
            "type":"Retail Goods"
        }
    ],
    "sg:phone":"+1 830 935 2713",
    "sg:postcode":"78133",
    "sg:province":"TX",
    "wof:name":"Jerry O Maler",
    "wof:placetype":"venue"
},
  "geometry": {"coordinates":[-98.271918,29.932301],"type":"Point"}
}