{
  "type": "Feature",
  "properties": {
    "iso:country":"US",
    "sg:address":"7305 San Dario Ave",
    "sg:city":"Laredo",
    "sg:classifiers":[
        {
            "category":"Cinema",
            "subcategory":"Movie Rental",
            "type":"Entertainment"
        }
    ],
    "sg:phone":"+1 956 728 1488",
    "sg:postcode":"78045",
    "sg:province":"TX",
    "sg:tags":[
        "video",
        "tape"
    ],
    "wof:name":"Blockbuster",
    "wof:placetype":"venue"
},
  "geometry": {"coordinates":[-99.50214,27.57199],"type":"Point"}
}