{
  "type": "Feature",
  "properties": {
    "iso:country":"US",
    "sg:address":"1408 Stonehollow Dr",
    "sg:city":"Humble",
    "sg:classifiers":[
        {
            "category":"Professional",
            "type":"Services"
        }
    ],
    "sg:phone":"+1 281 359 6299",
    "sg:postcode":"77339",
    "sg:province":"TX",
    "sg:tags":[
        "establishment"
    ],
    "wof:name":"Impex Trading",
    "wof:placetype":"venue"
},
  "geometry": {"coordinates":[-95.237347,30.051466],"type":"Point"}
}