{
  "type": "Feature",
  "properties": {
    "iso:country":"US",
    "sg:address":"6532 Lyndon B Johnson Fwy",
    "sg:city":"Dallas",
    "sg:classifiers":[
        {
            "category":"Professional",
            "subcategory":"Business Services",
            "type":"Services"
        }
    ],
    "sg:phone":"+1 972 392 1949",
    "sg:postcode":"75240",
    "sg:province":"TX",
    "sg:tags":[
        "heavy",
        "duty",
        "natural",
        "gas",
        "engine"
    ],
    "wof:name":"Alternatine Fuel Technology",
    "wof:placetype":"venue"
},
  "geometry": {"coordinates":[-96.79335,32.924419],"type":"Point"}
}