{
  "type": "Feature",
  "properties": {
    "iso:country":"US",
    "sg:address":"15619 Hermitage Oaks Dr",
    "sg:city":"Tomball",
    "sg:classifiers":[
        {
            "category":"Professional",
            "subcategory":"Computer Services",
            "type":"Services"
        }
    ],
    "sg:phone":"+1 832 717 4057",
    "sg:postcode":"77377",
    "sg:province":"TX",
    "sg:tags":[
        "related"
    ],
    "wof:name":"Tamhoi Inc",
    "wof:placetype":"venue"
},
  "geometry": {"coordinates":[-95.602306,30.003287],"type":"Point"}
}