{
  "type": "Feature",
  "properties": {
    "iso:country":"US",
    "sg:address":"812 Grande Dr",
    "sg:city":"Mesquite",
    "sg:classifiers":[
        {
            "category":"Autos & Motor Vehicles",
            "subcategory":"Automobile Sales",
            "type":"Retail Goods"
        }
    ],
    "sg:phone":"+1 972 329 2970",
    "sg:postcode":"75149",
    "sg:province":"TX",
    "wof:name":"Keely Car",
    "wof:placetype":"venue"
},
  "geometry": {"coordinates":[-96.590149,32.754534],"type":"Point"}
}