{
  "type": "Feature",
  "properties": {
    "iso:country":"US",
    "sg:address":"10101 Fondren Rd",
    "sg:city":"Houston",
    "sg:classifiers":[
        {
            "category":"Professional",
            "subcategory":"Employment Agencies",
            "type":"Services"
        }
    ],
    "sg:phone":"+1 713 981 1300",
    "sg:postcode":"77096",
    "sg:province":"TX",
    "sg:tags":[
        "opportunity"
    ],
    "wof:name":"Higginbotham Staffing Sltns",
    "wof:placetype":"venue"
},
  "geometry": {"coordinates":[-95.508574,29.670665],"type":"Point"}
}