{
  "type": "Feature",
  "properties": {
    "iso:country":"US",
    "sg:address":"408 N 3rd St",
    "sg:city":"Lufkin",
    "sg:classifiers":[
        {
            "category":"Professional",
            "subcategory":"Engineering",
            "type":"Services"
        }
    ],
    "sg:phone":"+1 936 634 5528",
    "sg:postcode":"75901",
    "sg:province":"TX",
    "sg:tags":[
        "engineer"
    ],
    "wof:name":"Everett Griffith Jr & Assoc",
    "wof:placetype":"venue"
},
  "geometry": {"coordinates":[-94.725039,31.342147],"type":"Point"}
}