{
  "type": "Feature",
  "properties": {
    "iso:country":"US",
    "sg:address":"1690 Co Rd 268",
    "sg:city":"Oglesby",
    "sg:classifiers":[
        {
            "category":"Health Services",
            "subcategory":"Doctor",
            "type":"Services"
        }
    ],
    "sg:phone":"+1 254 470 2268",
    "sg:postcode":"76561",
    "sg:province":"TX",
    "sg:tags":[
        "anesthesiologist"
    ],
    "wof:name":"Joseph V Augeri Sr",
    "wof:placetype":"venue"
},
  "geometry": {"coordinates":[-97.588843,31.435517],"type":"Point"}
}