{
  "type": "Feature",
  "properties": {
    "iso:country":"US",
    "sg:address":"2006 N Valley Mills Dr",
    "sg:city":"Waco",
    "sg:classifiers":[
        {
            "category":"Bars & Pubs",
            "type":"Food & Drink"
        }
    ],
    "sg:phone":"+1 254 772 1866",
    "sg:postcode":"76710",
    "sg:province":"TX",
    "sg:tags":[
        "drinking"
    ],
    "wof:name":"Grape The",
    "wof:placetype":"venue"
},
  "geometry": {"coordinates":[-97.20418100000001,31.5327],"type":"Point"}
}