{
  "type": "Feature",
  "properties": {
    "iso:country":"US",
    "sg:address":"221 Crestwood Dr",
    "sg:city":"Dallas",
    "sg:classifiers":[
        {
            "category":"Health Services",
            "subcategory":"Doctor",
            "type":"Services"
        }
    ],
    "sg:phone":"+1 214 941 7022",
    "sg:postcode":"75216",
    "sg:province":"TX",
    "sg:tags":[
        "medical"
    ],
    "wof:name":"Surgical Pthologists of Dallas",
    "wof:placetype":"venue"
},
  "geometry": {"coordinates":[-96.820752,32.728858],"type":"Point"}
}