{
  "type": "Feature",
  "properties": {
    "iso:country":"US",
    "sg:address":"309 N Galloway Ave",
    "sg:city":"Mesquite",
    "sg:phone":"+1 972 289 0013",
    "sg:postcode":"75149",
    "sg:province":"TX",
    "wof:name":"Skunk Works",
    "wof:placetype":"venue"
},
  "geometry": {"coordinates":[-96.599148,32.768852],"type":"Point"}
}