{
  "type": "Feature",
  "properties": {
    "iso:country":"US",
    "sg:address":"3923 Childress St",
    "sg:city":"Houston",
    "sg:classifiers":[
        {
            "category":"Professional",
            "subcategory":"Business Services",
            "type":"Services"
        }
    ],
    "sg:phone":"+1 713 666 9831",
    "sg:postcode":"77005",
    "sg:province":"TX",
    "wof:name":"Lynn Carothers Interiors",
    "wof:placetype":"venue"
},
  "geometry": {"coordinates":[-95.439627,29.727054],"type":"Point"}
}