{
  "type": "Feature",
  "properties": {
    "iso:country":"US",
    "sg:address":"1324 Colmar Dr",
    "sg:city":"Plano",
    "sg:classifiers":[
        {
            "category":"Utilities",
            "subcategory":"Fuel Oil & Lpg",
            "type":"Services"
        }
    ],
    "sg:phone":"+1 972 320 4333",
    "sg:postcode":"75023",
    "sg:province":"TX",
    "sg:tags":[
        "development",
        "exploration",
        "gas"
    ],
    "wof:name":"Wise Exploration Corporati",
    "wof:placetype":"venue"
},
  "geometry": {"coordinates":[-96.71602799999999,33.063374],"type":"Point"}
}