{
  "type": "Feature",
  "properties": {
    "iso:country":"US",
    "sg:address":"18043 Bruno Rd",
    "sg:city":"Justin",
    "sg:classifiers":[
        {
            "category":"Retail",
            "subcategory":"Repair Shop",
            "type":"Services"
        }
    ],
    "sg:phone":"+1 940 648 3823",
    "sg:postcode":"76247",
    "sg:province":"TX",
    "wof:name":"R&B Upholstery",
    "wof:placetype":"venue"
},
  "geometry": {"coordinates":[-97.33512500000001,33.056984],"type":"Point"}
}