{
  "type": "Feature",
  "properties": {
    "iso:country":"US",
    "sg:address":"3001 Ranch Road 620 S",
    "sg:city":"Austin",
    "sg:classifiers":[
        {
            "category":"Real Estate",
            "subcategory":"Developer",
            "type":"Services"
        }
    ],
    "sg:phone":"+1 512 346 1741",
    "sg:postcode":"78738",
    "sg:province":"TX",
    "sg:tags":[
        "land",
        "oil",
        "lease"
    ],
    "wof:name":"Hoch, Roger W",
    "wof:placetype":"venue"
},
  "geometry": {"coordinates":[-97.968925,30.334509],"type":"Point"}
}