{
  "type": "Feature",
  "properties": {
    "iso:country":"US",
    "sg:address":"622 Harvard St",
    "sg:city":"Houston",
    "sg:classifiers":[
        {
            "category":"Professional",
            "subcategory":"Art Services",
            "type":"Services"
        }
    ],
    "sg:phone":"+1 713 868 2848",
    "sg:postcode":"77007",
    "sg:province":"TX",
    "sg:tags":[
        "photography",
        "commercial"
    ],
    "wof:name":"Damian Hevia Photographer",
    "wof:placetype":"venue"
},
  "geometry": {"coordinates":[-95.39618400000001,29.782916],"type":"Point"}
}