{
  "type": "Feature",
  "properties": {
    "iso:country":"US",
    "sg:address":"3901 Marion St",
    "sg:city":"Corpus Christi",
    "sg:classifiers":[
        {
            "category":"Building & Trades",
            "subcategory":"Construction",
            "type":"Services"
        }
    ],
    "sg:phone":"+1 361 855 2604",
    "sg:postcode":"78415",
    "sg:province":"TX",
    "sg:tags":[
        "carpentry",
        "contractor"
    ],
    "wof:name":"Ahmuty Thor",
    "wof:placetype":"venue"
},
  "geometry": {"coordinates":[-97.396737,27.727808],"type":"Point"}
}