{
  "type": "Feature",
  "properties": {
    "iso:country":"US",
    "sg:address":"8015 Airport Rd",
    "sg:city":"Angleton",
    "sg:classifiers":[
        {
            "category":"Airport",
            "type":"Transportation"
        }
    ],
    "sg:phone":"+1 979 849 5755",
    "sg:postcode":"77515",
    "sg:province":"TX",
    "sg:website":"www.airport1.com",
    "wof:name":"Brazoria County Airport",
    "wof:placetype":"venue"
},
  "geometry": {"coordinates":[-95.458963,29.118182],"type":"Point"}
}