{
  "type": "Feature",
  "properties": {
    "iso:country":"US",
    "sg:address":"1020 Yvonne Dr",
    "sg:city":"Joshua",
    "sg:classifiers":[
        {
            "category":"Professional",
            "type":"Services"
        }
    ],
    "sg:phone":"+1 817 295 9319",
    "sg:postcode":"76058",
    "sg:province":"TX",
    "wof:name":"A Touch of Vitality",
    "wof:placetype":"venue"
},
  "geometry": {"coordinates":[-97.381801,32.48412],"type":"Point"}
}