{
  "type": "Feature",
  "properties": {
    "iso:country":"US",
    "sg:address":"179 S Seagoville Rd",
    "sg:city":"Dallas",
    "sg:classifiers":[
        {
            "category":"Home & Garden",
            "subcategory":"Furniture",
            "type":"Retail Goods"
        }
    ],
    "sg:phone":"+1 214 398 0465",
    "sg:postcode":"75217",
    "sg:province":"TX",
    "wof:name":"Carpet Solutions & Furniture",
    "wof:placetype":"venue"
},
  "geometry": {"coordinates":[-96.662217,32.711294],"type":"Point"}
}