{
  "type": "Feature",
  "properties": {
    "iso:country":"US",
    "sg:address":"2520 Scenic Dr",
    "sg:city":"Plano",
    "sg:classifiers":[
        {
            "category":"Education",
            "subcategory":"School",
            "type":"Public Place"
        }
    ],
    "sg:phone":"+1 469 752 3900",
    "sg:postcode":"75025",
    "sg:province":"TX",
    "wof:name":"Thomas Wesley Andrews Elem Sch",
    "wof:placetype":"venue"
},
  "geometry": {"coordinates":[-96.739766,33.092105],"type":"Point"}
}