{
  "type": "Feature",
  "properties": {
    "iso:country":"US",
    "sg:address":"4208 Southwest Blvd",
    "sg:city":"Fort Worth",
    "sg:classifiers":[
        {
            "category":"Professional",
            "subcategory":"Secretarial Services",
            "type":"Services"
        }
    ],
    "sg:phone":"+1 817 738 2611",
    "sg:postcode":"76116",
    "sg:province":"TX",
    "wof:name":"Mary K Flores",
    "wof:placetype":"venue"
},
  "geometry": {"coordinates":[-97.4397,32.710116],"type":"Point"}
}