{
  "type": "Feature",
  "properties": {
    "iso:country":"US",
    "sg:address":"7629 W Hwy 71",
    "sg:city":"Austin",
    "sg:classifiers":[
        {
            "category":"Personal",
            "type":"Services"
        }
    ],
    "sg:phone":"+1 512 301 1664",
    "sg:postcode":"78735",
    "sg:province":"TX",
    "wof:name":"Austin Pet Butler",
    "wof:placetype":"venue"
},
  "geometry": {"coordinates":[-97.881765,30.24147],"type":"Point"}
}