{
  "type": "Feature",
  "properties": {
    "iso:country":"US",
    "sg:address":"500 State Hwy 1604",
    "sg:city":"San Antonio",
    "sg:classifiers":[
        {
            "category":"Mining & Drilling",
            "type":"Manufacturing & Wholesale Goods"
        }
    ],
    "sg:phone":"+1 210 496 5300",
    "sg:postcode":"78232",
    "sg:province":"TX",
    "sg:tags":[
        "development",
        "exploration",
        "production",
        "gas",
        "oil"
    ],
    "wof:name":"Exploration Company of Del Inc",
    "wof:placetype":"venue"
},
  "geometry": {"coordinates":[-98.488384,29.609116],"type":"Point"}
}