{
  "type": "Feature",
  "properties": {
    "iso:country":"US",
    "sg:address":"1257 Elmdale Rd",
    "sg:city":"Abilene",
    "sg:classifiers":[
        {
            "category":"Manufacturing",
            "subcategory":"Soap",
            "type":"Manufacturing & Wholesale Goods"
        }
    ],
    "sg:phone":"+1 325 676 2975",
    "sg:postcode":"79601",
    "sg:province":"TX",
    "sg:tags":[
        "detergent",
        "industrial",
        "organic",
        "mfg"
    ],
    "wof:name":"Texas Soap & Sundries",
    "wof:placetype":"venue"
},
  "geometry": {"coordinates":[-99.639679,32.433302],"type":"Point"}
}