{
  "type": "Feature",
  "properties": {
    "iso:country":"US",
    "sg:address":"2610 Timber Dr",
    "sg:city":"Dickinson",
    "sg:classifiers":[
        {
            "category":"Home & Garden",
            "subcategory":"Building Materials",
            "type":"Retail Goods"
        },
        {
            "category":"Building & Trades",
            "subcategory":"Construction",
            "type":"Services"
        }
    ],
    "sg:phone":"+1 281 534 4890",
    "sg:postcode":"77539",
    "sg:province":"TX",
    "sg:tags":[
        "concrete",
        "staining",
        "contractor"
    ],
    "wof:name":"Walker Lively Concrete",
    "wof:placetype":"venue"
},
  "geometry": {"coordinates":[-95.066321,29.469236],"type":"Point"}
}