{
  "type": "Feature",
  "properties": {
    "iso:country":"US",
    "sg:address":"11536 Harry Hines Blvd # 202",
    "sg:city":"Dallas",
    "sg:classifiers":[
        {
            "category":"Wholesale",
            "subcategory":"Medical Equipment & Supplies",
            "type":"Manufacturing & Wholesale Goods"
        }
    ],
    "sg:phone":"+1 972 488 1000",
    "sg:postcode":"75229",
    "sg:province":"TX",
    "sg:tags":[
        "optometrists'"
    ],
    "wof:name":"Majestic Eyewear",
    "wof:placetype":"venue"
},
  "geometry": {"coordinates":[-96.89238400000001,32.899296],"type":"Point"}
}