{
  "type": "Feature",
  "properties": {
    "iso:country":"US",
    "sg:address":"2929 Carlisle St",
    "sg:city":"Dallas",
    "sg:classifiers":[
        {
            "category":"Government",
            "subcategory":"Office",
            "type":"Public Place"
        }
    ],
    "sg:phone":"+1 972 380 9183",
    "sg:postcode":"75204",
    "sg:province":"TX",
    "sg:tags":[
        "international",
        "affairs"
    ],
    "wof:name":"Dreams Bright International",
    "wof:placetype":"venue"
},
  "geometry": {"coordinates":[-96.803349,32.802984],"type":"Point"}
}