{
  "type": "Feature",
  "properties": {
    "iso:country":"US",
    "sg:address":"11331 Richmond Ave",
    "sg:city":"Houston",
    "sg:classifiers":[
        {
            "category":"Autos & Motor Vehicles",
            "subcategory":"Automobile Sales",
            "type":"Retail Goods"
        }
    ],
    "sg:phone":"+1 281 759 3696",
    "sg:postcode":"77082",
    "sg:province":"TX",
    "sg:tags":[
        "dealers-used",
        "car",
        "used",
        "cars-wholesale",
        "new"
    ],
    "wof:name":"Enzo Motors",
    "wof:placetype":"venue"
},
  "geometry": {"coordinates":[-95.57733899999999,29.727779],"type":"Point"}
}