{
  "type": "Feature",
  "properties": {
    "iso:country":"US",
    "sg:address":"1504 10th St",
    "sg:city":"Wichita Falls",
    "sg:classifiers":[
        {
            "category":"Organizations",
            "subcategory":"Religious Organization",
            "type":"Services"
        }
    ],
    "sg:phone":"+1 940 723 5288",
    "sg:postcode":"76301",
    "sg:province":"TX",
    "sg:tags":[
        "church"
    ],
    "sg:website":"www.sacredheartwf.org",
    "wof:name":"Sacred Heart Catholic Church",
    "wof:placetype":"venue"
},
  "geometry": {"coordinates":[-98.50111800000001,33.904035],"type":"Point"}
}