{
  "type": "Feature",
  "properties": {
    "iso:country":"US",
    "sg:address":"6424 N 1st Lane Ct",
    "sg:city":"Mcallen",
    "sg:classifiers":[
        {
            "category":"Real Estate",
            "subcategory":"Real Estate Agent",
            "type":"Services"
        }
    ],
    "sg:phone":"+1 956 686 2049",
    "sg:postcode":"78504",
    "sg:province":"TX",
    "wof:name":"Properties International Inc",
    "wof:placetype":"venue"
},
  "geometry": {"coordinates":[-98.210233,26.259199],"type":"Point"}
}