{
  "type": "Feature",
  "properties": {
    "iso:country":"US",
    "sg:address":"821 E 3rd St Ste B",
    "sg:city":"Irving",
    "sg:classifiers":[
        {
            "category":"Autos & Motor Vehicles",
            "subcategory":"Auto Supplies",
            "type":"Retail Goods"
        }
    ],
    "sg:phone":"+1 972 579 1472",
    "sg:postcode":"75060",
    "sg:province":"TX",
    "sg:tags":[
        "glass"
    ],
    "wof:name":"Southern Auto Glass",
    "wof:placetype":"venue"
},
  "geometry": {"coordinates":[-96.937698,32.811298],"type":"Point"}
}