{
  "type": "Feature",
  "properties": {
    "iso:country":"US",
    "sg:address":"2715 Sailors Moon Dr",
    "sg:city":"Friendswood",
    "sg:classifiers":[
        {
            "category":"Professional",
            "subcategory":"Lawyer & Legal Services",
            "type":"Services"
        }
    ],
    "sg:phone":"+1 281 996 5261",
    "sg:postcode":"77546",
    "sg:province":"TX",
    "sg:tags":[
        "attorney"
    ],
    "sg:website":"www.uspatentagent.com",
    "wof:name":"Sherman D Pernia",
    "wof:placetype":"venue"
},
  "geometry": {"coordinates":[-95.16495500000001,29.529688],"type":"Point"}
}