{
  "type": "Feature",
  "properties": {
    "iso:country":"US",
    "sg:address":"2000 Witt Rd",
    "sg:city":"Frisco",
    "sg:classifiers":[
        {
            "category":"Building & Trades",
            "subcategory":"Plumbing",
            "type":"Services"
        }
    ],
    "sg:phone":"+1 972 712 7423",
    "sg:postcode":"75034",
    "sg:province":"TX",
    "sg:tags":[
        "conditioning",
        "air",
        "system",
        "contractor"
    ],
    "wof:name":"Air Rescue Svc",
    "wof:placetype":"venue"
},
  "geometry": {"coordinates":[-96.893854,33.151535],"type":"Point"}
}