{
  "type": "Feature",
  "properties": {
    "iso:country":"US",
    "sg:address":"119 W Kingsley Rd",
    "sg:city":"Garland",
    "sg:classifiers":[
        {
            "category":"Restaurant",
            "type":"Food & Drink"
        }
    ],
    "sg:phone":"+1 972 926 0620",
    "sg:postcode":"75041",
    "sg:province":"TX",
    "wof:name":"Carniceria Y Taqueria-Primera",
    "wof:placetype":"venue"
},
  "geometry": {"coordinates":[-96.633174,32.87874],"type":"Point"}
}