{
  "type": "Feature",
  "properties": {
    "iso:country":"US",
    "sg:address":"3740 Wow Rd",
    "sg:city":"Corpus Christi",
    "sg:classifiers":[
        {
            "category":"Building & Trades",
            "subcategory":"Construction",
            "type":"Services"
        }
    ],
    "sg:phone":"+1 361 654 2785",
    "sg:postcode":"78413",
    "sg:province":"TX",
    "sg:tags":[
        "repairing",
        "remodeling",
        "contractor"
    ],
    "wof:name":"Delta Remodeling",
    "wof:placetype":"venue"
},
  "geometry": {"coordinates":[-97.41977,27.697945],"type":"Point"}
}