{
  "type": "Feature",
  "properties": {
    "iso:country":"US",
    "sg:address":"475 Coneflower Dr",
    "sg:city":"Garland",
    "sg:classifiers":[
        {
            "category":"Shopping",
            "subcategory":"Clothing, Apparel, & Fashions",
            "type":"Retail Goods"
        },
        {
            "category":"Shopping",
            "subcategory":"Baby Store",
            "type":"Retail Goods"
        },
        {
            "category":"Shopping",
            "subcategory":"Jewelry",
            "type":"Retail Goods"
        },
        {
            "category":"Home & Garden",
            "subcategory":"Home Furnishings",
            "type":"Retail Goods"
        },
        {
            "category":"Shopping",
            "subcategory":"Luggage & Leather Goods",
            "type":"Retail Goods"
        }
    ],
    "sg:phone":"+1 972 414 9361",
    "sg:postcode":"75040",
    "sg:province":"TX",
    "sg:tags":[
        "infant",
        "apparel",
        "bedding",
        "men's",
        "watch",
        "women's",
        "children's",
        "wear",
        "handbag",
        "accessory",
        "clothing"
    ],
    "sg:website":"http://www.eddiebauer.com",
    "wof:name":"Eddie Bauer",
    "wof:placetype":"venue"
},
  "geometry": {"coordinates":[-96.612208,32.953181],"type":"Point"}
}