{
  "type": "Feature",
  "properties": {
    "iso:country":"US",
    "sg:address":"1433 Franklin St",
    "sg:city":"Abilene",
    "sg:classifiers":[
        {
            "category":"Personal",
            "subcategory":"Beauty Salon",
            "type":"Services"
        }
    ],
    "sg:phone":"+1 325 660 8267",
    "sg:postcode":"79601",
    "sg:province":"TX",
    "wof:name":"First Impressions By Charlene",
    "wof:placetype":"venue"
},
  "geometry": {"coordinates":[-99.73811000000001,32.497497],"type":"Point"}
}