{
  "type": "Feature",
  "properties": {
    "iso:country":"US",
    "sg:address":"650 Co Rd 141",
    "sg:city":"Georgetown",
    "sg:classifiers":[
        {
            "category":"Food & Beverages",
            "subcategory":"Specialty",
            "type":"Retail Goods"
        }
    ],
    "sg:phone":"+1 512 863 4488",
    "sg:postcode":"78626",
    "sg:province":"TX",
    "wof:name":"Natural Health",
    "wof:placetype":"venue"
},
  "geometry": {"coordinates":[-97.619209,30.722423],"type":"Point"}
}