{
  "type": "Feature",
  "properties": {
    "iso:country":"US",
    "sg:address":"2129 Ave G",
    "sg:city":"Bay City",
    "sg:classifiers":[
        {
            "category":"Shopping",
            "subcategory":"Jewelry",
            "type":"Retail Goods"
        }
    ],
    "sg:phone":"+1 979 245 4633",
    "sg:postcode":"77414",
    "sg:province":"TX",
    "sg:tags":[
        "jeweler"
    ],
    "wof:name":"Secrest Jewelers",
    "wof:placetype":"venue"
},
  "geometry": {"coordinates":[-95.9687,28.982714],"type":"Point"}
}