{
  "type": "Feature",
  "properties": {
    "iso:country":"US",
    "sg:address":"5701 Louetta Rd",
    "sg:city":"Spring",
    "sg:classifiers":[
        {
            "category":"Social Services",
            "subcategory":"Child Care",
            "type":"Services"
        }
    ],
    "sg:phone":"+1 281 320 8665",
    "sg:postcode":"77379",
    "sg:province":"TX",
    "wof:name":"Gymnastics USA & Child Care",
    "wof:placetype":"venue"
},
  "geometry": {"coordinates":[-95.502765,30.032555],"type":"Point"}
}