{
  "type": "Feature",
  "properties": {
    "iso:country":"US",
    "sg:address":"15289 Marsh Rd",
    "sg:city":"Hamshire",
    "sg:classifiers":[
        {
            "category":"Shopping",
            "subcategory":"Gifts & Souvenirs",
            "type":"Retail Goods"
        }
    ],
    "sg:phone":"+1 409 243 3109",
    "sg:postcode":"77622",
    "sg:province":"TX",
    "wof:name":"Etcetera",
    "wof:placetype":"venue"
},
  "geometry": {"coordinates":[-94.325608,29.863033],"type":"Point"}
}