{
  "type": "Feature",
  "properties": {
    "iso:country":"US",
    "sg:address":"207 S Bridge St",
    "sg:city":"Jefferson",
    "sg:classifiers":[
        {
            "category":"Professional",
            "subcategory":"Detective & Security Services",
            "type":"Services"
        }
    ],
    "sg:phone":"+1 903 244 1625",
    "sg:postcode":"75657",
    "sg:province":"TX",
    "sg:tags":[
        "car"
    ],
    "wof:name":"Quality Investigation",
    "wof:placetype":"venue"
},
  "geometry": {"coordinates":[-94.34951700000001,32.760328],"type":"Point"}
}