{
  "type": "Feature",
  "properties": {
    "iso:country":"US",
    "sg:address":"1355 Junction Hwy",
    "sg:city":"Kerrville",
    "sg:classifiers":[
        {
            "category":"Coffee & Tea",
            "type":"Food & Drink"
        }
    ],
    "sg:menulink":"http://www.allmenus.com/tx/kerrville/113015-starbucks-coffee/menu/",
    "sg:phone":"+1 830 257 4163",
    "sg:postcode":"78028",
    "sg:province":"TX",
    "sg:tags":[
        "american"
    ],
    "wof:name":"Starbucks Coffee",
    "wof:placetype":"venue"
},
  "geometry": {"coordinates":[-99.170931,30.062154],"type":"Point"}
}