{
  "type": "Feature",
  "properties": {
    "iso:country":"US",
    "sg:address":"2720 N Stemmons Fwy",
    "sg:city":"Dallas",
    "sg:classifiers":[
        {
            "category":"Real Estate",
            "subcategory":"Real Estate Operator",
            "type":"Services"
        }
    ],
    "sg:phone":"+1 214 688 0295",
    "sg:postcode":"75207",
    "sg:province":"TX",
    "sg:tags":[
        "building",
        "parks"
    ],
    "wof:name":"2700 Stemmons Corp",
    "wof:placetype":"venue"
},
  "geometry": {"coordinates":[-96.842151,32.807954],"type":"Point"}
}