{
  "type": "Feature",
  "properties": {
    "iso:country":"US",
    "sg:address":"7950 Great Northern Blvd",
    "sg:city":"Austin",
    "sg:classifiers":[
        {
            "category":"Sports & Exercise",
            "subcategory":"Gym",
            "type":"Entertainment"
        }
    ],
    "sg:phone":"+1 512 407 9909",
    "sg:postcode":"78757",
    "sg:province":"TX",
    "sg:tags":[
        "yoga"
    ],
    "sg:website":"www.yogagroove.com",
    "wof:name":"Yogagroove",
    "wof:placetype":"venue"
},
  "geometry": {"coordinates":[-97.741203,30.362301],"type":"Point"}
}