{
  "type": "Feature",
  "properties": {
    "iso:country":"US",
    "sg:address":"4934 Bridgemont Ln",
    "sg:city":"Spring",
    "sg:classifiers":[
        {
            "category":"Wholesale",
            "subcategory":"Electrical",
            "type":"Manufacturing & Wholesale Goods"
        }
    ],
    "sg:phone":"+1 281 350 3548",
    "sg:postcode":"77388",
    "sg:province":"TX",
    "sg:tags":[
        "high",
        "export",
        "technology",
        "telecommunication",
        "system"
    ],
    "wof:name":"Trate Inc",
    "wof:placetype":"venue"
},
  "geometry": {"coordinates":[-95.494298,30.065288],"type":"Point"}
}