{
  "type": "Feature",
  "properties": {
    "iso:country":"US",
    "sg:address":"302 Coke Ave",
    "sg:city":"Hillsboro",
    "sg:classifiers":[
        {
            "category":"Building & Trades",
            "subcategory":"Equipment Rental",
            "type":"Services"
        }
    ],
    "sg:phone":"+1 254 580 0712",
    "sg:postcode":"76645",
    "sg:province":"TX",
    "sg:tags":[
        "computer",
        "leasing",
        "furniture"
    ],
    "wof:name":"Aarons Sales & Lease Ownership",
    "wof:placetype":"venue"
},
  "geometry": {"coordinates":[-97.098857,32.006895],"type":"Point"}
}