{
  "type": "Feature",
  "properties": {
    "iso:country":"US",
    "sg:address":"1211 Seminole Trl",
    "sg:city":"Carrollton",
    "sg:classifiers":[
        {
            "category":"Professional",
            "subcategory":"Business Services",
            "type":"Services"
        }
    ],
    "sg:phone":"+1 972 395 0821",
    "sg:postcode":"75007",
    "sg:province":"TX",
    "wof:name":"Translations On Q",
    "wof:placetype":"venue"
},
  "geometry": {"coordinates":[-96.92021,33.01455],"type":"Point"}
}