{
  "type": "Feature",
  "properties": {
    "iso:country":"US",
    "sg:address":"700 E Mulberry St",
    "sg:city":"Angleton",
    "sg:classifiers":[
        {
            "category":"Retail",
            "subcategory":"Auto Repair",
            "type":"Services"
        }
    ],
    "sg:phone":"+1 979 849 6000",
    "sg:postcode":"77515",
    "sg:province":"TX",
    "sg:tags":[
        "automotive"
    ],
    "wof:name":"Vasuts Paint & Body Wrckr Svc",
    "wof:placetype":"venue"
},
  "geometry": {"coordinates":[-95.423422,29.164845],"type":"Point"}
}