{
  "type": "Feature",
  "properties": {
    "iso:country":"US",
    "sg:address":"9915 Woodrow Rd",
    "sg:city":"Ropesville",
    "sg:classifiers":[
        {
            "category":"Professional",
            "subcategory":"Business Services",
            "type":"Services"
        }
    ],
    "sg:phone":"+1 806 863 4438",
    "sg:postcode":"79358",
    "sg:province":"TX",
    "sg:tags":[
        "magazine",
        "publication"
    ],
    "wof:name":"Lubbock TV Tempo Magazine",
    "wof:placetype":"venue"
},
  "geometry": {"coordinates":[-102.033821,33.447032],"type":"Point"}
}