{
  "type": "Feature",
  "properties": {
    "iso:country":"US",
    "sg:address":"3010 Kathleen Ln",
    "sg:city":"Euless",
    "sg:classifiers":[
        {
            "category":"Shopping",
            "subcategory":"Gifts & Souvenirs",
            "type":"Retail Goods"
        }
    ],
    "sg:phone":"+1 817 267 9280",
    "sg:postcode":"76039",
    "sg:province":"TX",
    "sg:tags":[
        "shop",
        "novelty"
    ],
    "wof:name":"The Cherubs Collection",
    "wof:placetype":"venue"
},
  "geometry": {"coordinates":[-97.086181,32.879405],"type":"Point"}
}