{
  "type": "Feature",
  "properties": {
    "iso:country":"US",
    "sg:address":"711 Eaglecreek Dr",
    "sg:city":"Leander",
    "sg:classifiers":[
        {
            "category":"Building & Trades",
            "subcategory":"Construction",
            "type":"Services"
        }
    ],
    "sg:phone":"+1 512 260 9063",
    "sg:postcode":"78641",
    "sg:province":"TX",
    "sg:tags":[
        "home",
        "builder"
    ],
    "wof:name":"Ryland Scott Felder Homes",
    "wof:placetype":"venue"
},
  "geometry": {"coordinates":[-97.87697,30.577896],"type":"Point"}
}