{
  "type": "Feature",
  "properties": {
    "iso:country":"US",
    "sg:address":"2951 Lazy Lake Dr",
    "sg:city":"Harlingen",
    "sg:classifiers":[
        {
            "category":"Professional",
            "type":"Services"
        }
    ],
    "sg:phone":"+1 956 425 6046",
    "sg:postcode":"78550",
    "sg:province":"TX",
    "wof:name":"Auxano Corporation",
    "wof:placetype":"venue"
},
  "geometry": {"coordinates":[-97.658027,26.182262],"type":"Point"}
}