{
  "type": "Feature",
  "properties": {
    "iso:country":"US",
    "sg:address":"2118 N Austin Ave",
    "sg:city":"Georgetown",
    "sg:classifiers":[
        {
            "category":"Shopping",
            "type":"Retail Goods"
        }
    ],
    "sg:phone":"+1 512 868 0047",
    "sg:postcode":"78626",
    "sg:province":"TX",
    "sg:tags":[
        "pet",
        "food",
        "supply"
    ],
    "wof:name":"Tail Waggins Dog Baker",
    "wof:placetype":"venue"
},
  "geometry": {"coordinates":[-97.66758900000001,30.663031],"type":"Point"}
}