{
  "type": "Feature",
  "properties": {
    "iso:country":"US",
    "sg:address":"7613 Wade Rd",
    "sg:city":"Baytown",
    "sg:classifiers":[
        {
            "category":"Organizations",
            "subcategory":"Non-profit Organization",
            "type":"Services"
        }
    ],
    "sg:phone":"+1 281 426 3970",
    "sg:postcode":"77521",
    "sg:province":"TX",
    "sg:tags":[
        "action",
        "agency",
        "community"
    ],
    "wof:name":"J D Walker Headstart Ctr",
    "wof:placetype":"venue"
},
  "geometry": {"coordinates":[-95.016856,29.807015],"type":"Point"}
}