{
  "type": "Feature",
  "properties": {
    "iso:country":"US",
    "sg:address":"810 Saybrook",
    "sg:city":"Houston",
    "sg:classifiers":[
        {
            "category":"Real Estate",
            "subcategory":"Architect",
            "type":"Services"
        }
    ],
    "sg:phone":"+1 713 463 5385",
    "sg:postcode":"77024",
    "sg:province":"TX",
    "sg:tags":[
        "architectural"
    ],
    "wof:name":"R2 Hinge LLC",
    "wof:placetype":"venue"
},
  "geometry": {"coordinates":[-95.513963,29.779136],"type":"Point"}
}