{
  "type": "Feature",
  "properties": {
    "iso:country":"US",
    "sg:address":"4609 Dyer St",
    "sg:city":"El Paso",
    "sg:classifiers":[
        {
            "category":"Autos & Motor Vehicles",
            "subcategory":"Auto Supplies",
            "type":"Retail Goods"
        }
    ],
    "sg:phone":"+1 915 565 0157",
    "sg:postcode":"79930",
    "sg:province":"TX",
    "wof:name":"New Image",
    "wof:placetype":"venue"
},
  "geometry": {"coordinates":[-106.444732,31.818128],"type":"Point"}
}