{
  "type": "Feature",
  "properties": {
    "iso:country":"US",
    "sg:address":"6410 Covecreek Pl",
    "sg:city":"Dallas",
    "sg:classifiers":[
        {
            "category":"Professional",
            "subcategory":"Business Services",
            "type":"Services"
        }
    ],
    "sg:phone":"+1 972 385 9356",
    "sg:postcode":"75240",
    "sg:province":"TX",
    "sg:tags":[
        "interior",
        "consultant",
        "design",
        "decorator"
    ],
    "wof:name":"Judy Paschall Winger Interior",
    "wof:placetype":"venue"
},
  "geometry": {"coordinates":[-96.793772,32.92792],"type":"Point"}
}