{
  "type": "Feature",
  "properties": {
    "iso:country":"US",
    "sg:address":"468 Rancho Viejo Dr",
    "sg:city":"El Paso",
    "sg:classifiers":[
        {
            "category":"Building & Trades",
            "subcategory":"Construction",
            "type":"Services"
        }
    ],
    "sg:phone":"+1 915 851 0424",
    "sg:postcode":"79927",
    "sg:province":"TX",
    "sg:tags":[
        "contractor"
    ],
    "wof:name":"Best Plastering Construction",
    "wof:placetype":"venue"
},
  "geometry": {"coordinates":[-106.242582,31.615128],"type":"Point"}
}