{
  "type": "Feature",
  "properties": {
    "iso:country":"US",
    "sg:address":"2115 San Luis St",
    "sg:city":"San Antonio",
    "sg:classifiers":[
        {
            "category":"Building & Trades",
            "subcategory":"Construction",
            "type":"Services"
        }
    ],
    "sg:phone":"+1 210 224 4556",
    "sg:postcode":"78207",
    "sg:province":"TX",
    "sg:tags":[
        "contractor"
    ],
    "wof:name":"Fernandez Ceramic Tile",
    "wof:placetype":"venue"
},
  "geometry": {"coordinates":[-98.52291200000001,29.422456],"type":"Point"}
}