{
  "type": "Feature",
  "properties": {
    "iso:country":"US",
    "sg:address":"2112 Regency Dr",
    "sg:city":"Irving",
    "sg:classifiers":[
        {
            "category":"Manufacturing",
            "subcategory":"Printing",
            "type":"Manufacturing & Wholesale Goods"
        }
    ],
    "sg:phone":"+1 972 554 0013",
    "sg:postcode":"75062",
    "sg:province":"TX",
    "sg:tags":[
        "printer"
    ],
    "wof:name":"Beddoe Printing",
    "wof:placetype":"venue"
},
  "geometry": {"coordinates":[-96.89531599999999,32.836664],"type":"Point"}
}