{
  "type": "Feature",
  "properties": {
    "iso:country":"US",
    "sg:address":"125 Legacy Dr",
    "sg:city":"Plano",
    "sg:classifiers":[
        {
            "category":"Autos & Motor Vehicles",
            "subcategory":"Fuel & Gas Station",
            "type":"Retail Goods"
        }
    ],
    "sg:phone":"+1 972 527 4535",
    "sg:postcode":"75023",
    "sg:province":"TX",
    "sg:tags":[
        "oil"
    ],
    "wof:name":"Racetrac Petroleum Inc",
    "wof:placetype":"venue"
},
  "geometry": {"coordinates":[-96.69319900000001,33.067783],"type":"Point"}
}