{
  "type": "Feature",
  "properties": {
    "iso:country":"US",
    "sg:address":"2609 E Hwy 82",
    "sg:city":"Gainesville",
    "sg:classifiers":[
        {
            "category":"Real Estate",
            "subcategory":"Real Estate Operator",
            "type":"Services"
        }
    ],
    "sg:phone":"+1 940 668 7931",
    "sg:postcode":"76240",
    "sg:province":"TX",
    "sg:tags":[
        "apartment"
    ],
    "wof:name":"Woodglen Park",
    "wof:placetype":"venue"
},
  "geometry": {"coordinates":[-97.11194,33.643623],"type":"Point"}
}