{
  "type": "Feature",
  "properties": {
    "iso:country":"US",
    "sg:address":"13014 Stillforest St",
    "sg:city":"Austin",
    "sg:classifiers":[
        {
            "category":"Retail",
            "subcategory":"Repair Shop",
            "type":"Services"
        }
    ],
    "sg:phone":"+1 512 331 4595",
    "sg:postcode":"78729",
    "sg:province":"TX",
    "sg:tags":[
        "equipment",
        "conditioning",
        "air"
    ],
    "wof:name":"Aire Steam Air Conditioning",
    "wof:placetype":"venue"
},
  "geometry": {"coordinates":[-97.776691,30.459665],"type":"Point"}
}