{
  "type": "Feature",
  "properties": {
    "iso:country":"US",
    "sg:address":"3863 Royal Ln",
    "sg:city":"Dallas",
    "sg:classifiers":[
        {
            "category":"Autos & Motor Vehicles",
            "subcategory":"Automobile Sales",
            "type":"Retail Goods"
        }
    ],
    "sg:phone":"+1 214 956 9563",
    "sg:postcode":"75229",
    "sg:province":"TX",
    "sg:tags":[
        "aircraft"
    ],
    "wof:name":"Aircraft Security & Allert",
    "wof:placetype":"venue"
},
  "geometry": {"coordinates":[-96.848439,32.895201],"type":"Point"}
}