{
  "type": "Feature",
  "properties": {
    "iso:country":"US",
    "sg:address":"1921 Anei Cir",
    "sg:city":"Brownsville",
    "sg:classifiers":[
        {
            "category":"Transit Center",
            "subcategory":"Freight",
            "type":"Transportation"
        }
    ],
    "sg:phone":"+1 956 542 6984",
    "sg:postcode":"78521",
    "sg:province":"TX",
    "sg:tags":[
        "container",
        "broker"
    ],
    "wof:name":"R B Group",
    "wof:placetype":"venue"
},
  "geometry": {"coordinates":[-97.45437800000001,25.940829],"type":"Point"}
}