{
  "type": "Feature",
  "properties": {
    "iso:country":"US",
    "sg:address":"712 S Saint Marys St",
    "sg:city":"San Antonio",
    "sg:classifiers":[
        {
            "category":"Shopping",
            "type":"Retail Goods"
        },
        {
            "category":"Wholesale",
            "subcategory":"Durable Goods & Equipment",
            "type":"Manufacturing & Wholesale Goods"
        }
    ],
    "sg:phone":"+1 210 212 5020",
    "sg:postcode":"78205",
    "sg:province":"TX",
    "sg:tags":[
        "importer",
        "merchandise"
    ],
    "wof:name":"Maria Cristina Imports",
    "wof:placetype":"venue"
},
  "geometry": {"coordinates":[-98.48983,29.416771],"type":"Point"}
}