{
  "type": "Feature",
  "properties": {
    "iso:country":"US",
    "sg:address":"214 S Travis St",
    "sg:city":"Seguin",
    "sg:classifiers":[
        {
            "category":"Professional",
            "subcategory":"Art Services",
            "type":"Services"
        }
    ],
    "sg:phone":"+1 830 379 6117",
    "sg:postcode":"78155",
    "sg:province":"TX",
    "sg:tags":[
        "photo",
        "photography",
        "commercial",
        "studio",
        "portrait"
    ],
    "wof:name":"Glenewinkel Photography",
    "wof:placetype":"venue"
},
  "geometry": {"coordinates":[-97.966386,29.56751],"type":"Point"}
}