{
  "type": "Feature",
  "properties": {
    "iso:country":"US",
    "sg:address":"13550 King Phillip Ct",
    "sg:city":"Corpus Christi",
    "sg:phone":"+1 361 949 9394",
    "sg:postcode":"78418",
    "sg:province":"TX",
    "sg:tags":[
        "shelving"
    ],
    "wof:name":"Benchmark Filing & Shelving",
    "wof:placetype":"venue"
},
  "geometry": {"coordinates":[-97.242028,27.610609],"type":"Point"}
}