{
  "type": "Feature",
  "properties": {
    "iso:country":"US",
    "sg:address":"1216 Center St",
    "sg:city":"Pasadena",
    "sg:classifiers":[
        {
            "category":"Home & Garden",
            "subcategory":"Furniture",
            "type":"Retail Goods"
        }
    ],
    "sg:phone":"+1 713 473 1903",
    "sg:postcode":"77506",
    "sg:province":"TX",
    "sg:tags":[
        "store"
    ],
    "wof:name":"A Pasadena Furn Bargain Barn",
    "wof:placetype":"venue"
},
  "geometry": {"coordinates":[-95.20422600000001,29.692973],"type":"Point"}
}