{
  "type": "Feature",
  "properties": {
    "iso:country":"US",
    "sg:address":"517 Roberts Cut Off Rd",
    "sg:city":"River Oaks",
    "sg:classifiers":[
        {
            "category":"Building & Trades",
            "subcategory":"Construction",
            "type":"Services"
        }
    ],
    "sg:phone":"+1 817 731 0754",
    "sg:postcode":"76114",
    "sg:province":"TX",
    "sg:tags":[
        "masonry",
        "contractor"
    ],
    "wof:name":"Vance Franks Masonry",
    "wof:placetype":"venue"
},
  "geometry": {"coordinates":[-97.399894,32.768835],"type":"Point"}
}