{
  "type": "Feature",
  "properties": {
    "iso:country":"US",
    "sg:address":"338 Co Rd 2745",
    "sg:city":"Caddo Mills",
    "sg:classifiers":[
        {
            "category":"Home & Garden",
            "subcategory":"Building Materials",
            "type":"Retail Goods"
        }
    ],
    "sg:phone":"+1 903 268 4319",
    "sg:postcode":"75135",
    "sg:province":"TX",
    "sg:tags":[
        "glass",
        "window",
        "plate"
    ],
    "wof:name":"Rick's Auto Glass",
    "wof:placetype":"venue"
},
  "geometry": {"coordinates":[-96.26555999999999,33.150624],"type":"Point"}
}