{
  "type": "Feature",
  "properties": {
    "iso:country":"US",
    "sg:address":"6440 N Central Expy",
    "sg:city":"Dallas",
    "sg:classifiers":[
        {
            "category":"Communications",
            "subcategory":"Film & Video Production",
            "type":"Services"
        }
    ],
    "sg:phone":"+1 214 346 9611",
    "sg:postcode":"75206",
    "sg:province":"TX",
    "sg:tags":[
        "motion"
    ],
    "wof:name":"PKI Productions",
    "wof:placetype":"venue"
},
  "geometry": {"coordinates":[-96.77321499999999,32.845212],"type":"Point"}
}