{
  "type": "Feature",
  "properties": {
    "iso:country":"US",
    "sg:address":"1707 Colt Cir",
    "sg:city":"Marble Falls",
    "sg:classifiers":[
        {
            "category":"Manufacturing",
            "subcategory":"Retail Goods",
            "type":"Manufacturing & Wholesale Goods"
        }
    ],
    "sg:phone":"+1 830 693 1761",
    "sg:postcode":"78654",
    "sg:province":"TX",
    "sg:tags":[
        "candle",
        "mfg"
    ],
    "wof:name":"Natures Finest",
    "wof:placetype":"venue"
},
  "geometry": {"coordinates":[-98.271777,30.594323],"type":"Point"}
}