{
  "type": "Feature",
  "properties": {
    "iso:country":"US",
    "sg:address":"2804 Creeks Edge Pkwy",
    "sg:city":"Austin",
    "sg:classifiers":[
        {
            "category":"Professional",
            "subcategory":"Management & Consulting",
            "type":"Services"
        }
    ],
    "sg:phone":"+1 512 402 0101",
    "sg:postcode":"78733",
    "sg:province":"TX",
    "sg:tags":[
        "building",
        "commercial",
        "automation"
    ],
    "wof:name":"Estructures Inc",
    "wof:placetype":"venue"
},
  "geometry": {"coordinates":[-97.88579799999999,30.295112],"type":"Point"}
}