{
  "type": "Feature",
  "properties": {
    "iso:country":"US",
    "sg:address":"8387 Co Rd 2316",
    "sg:city":"Quinlan",
    "sg:classifiers":[
        {
            "category":"Professional",
            "type":"Services"
        }
    ],
    "sg:phone":"+1 903 356 4454",
    "sg:postcode":"75474",
    "sg:province":"TX",
    "wof:name":"Stanley Hempstead",
    "wof:placetype":"venue"
},
  "geometry": {"coordinates":[-96.17908199999999,32.905849],"type":"Point"}
}