{
  "type": "Feature",
  "properties": {
    "iso:country":"US",
    "sg:address":"1705 FM 1021",
    "sg:city":"Quemado",
    "sg:classifiers":[
        {
            "category":"Autos & Motor Vehicles",
            "subcategory":"Automobile Sales",
            "type":"Retail Goods"
        }
    ],
    "sg:phone":"+1 830 757 8390",
    "sg:postcode":"78852",
    "sg:province":"TX",
    "sg:tags":[
        "car",
        "dealer"
    ],
    "wof:name":"Pereda Used Cars",
    "wof:placetype":"venue"
},
  "geometry": {"coordinates":[-100.492203,28.700606],"type":"Point"}
}