{
  "type": "Feature",
  "properties": {
    "iso:country":"US",
    "sg:address":"14211 Cornelia Dr",
    "sg:city":"Cypress",
    "sg:classifiers":[
        {
            "category":"Professional",
            "subcategory":"Business Services",
            "type":"Services"
        }
    ],
    "sg:phone":"+1 281 807 3570",
    "sg:postcode":"77429",
    "sg:province":"TX",
    "wof:name":"Lone Star Home Inspection Inc",
    "wof:placetype":"venue"
},
  "geometry": {"coordinates":[-95.63765100000001,29.945063],"type":"Point"}
}