{
  "type": "Feature",
  "properties": {
    "iso:country":"US",
    "sg:address":"189 N Seguin Ave",
    "sg:city":"New Braunfels",
    "sg:classifiers":[
        {
            "category":"Retail",
            "subcategory":"Funeral Services",
            "type":"Services"
        }
    ],
    "sg:phone":"+1 830 625 3434",
    "sg:postcode":"78130",
    "sg:province":"TX",
    "sg:tags":[
        "director"
    ],
    "wof:name":"Doeppenschmidt Funeral Home",
    "wof:placetype":"venue"
},
  "geometry": {"coordinates":[-98.125052,29.703156],"type":"Point"}
}