{
  "type": "Feature",
  "properties": {
    "iso:country":"US",
    "sg:address":"56 Arabian Stallion Run",
    "sg:city":"Dale",
    "sg:classifiers":[
        {
            "category":"Professional",
            "type":"Services"
        }
    ],
    "sg:phone":"+1 512 376 5984",
    "sg:postcode":"78616",
    "sg:province":"TX",
    "sg:tags":[
        "establishment"
    ],
    "wof:name":"Austin Stamp Works",
    "wof:placetype":"venue"
},
  "geometry": {"coordinates":[-97.661625,30.033309],"type":"Point"}
}