{
  "type": "Feature",
  "properties": {
    "iso:country":"US",
    "sg:address":"301 W Clay St",
    "sg:city":"Houston",
    "sg:classifiers":[
        {
            "category":"Professional",
            "subcategory":"Management & Consulting",
            "type":"Services"
        }
    ],
    "sg:phone":"+1 713 942 2039",
    "sg:postcode":"77019",
    "sg:province":"TX",
    "sg:tags":[
        "business"
    ],
    "wof:name":"Atlas Transfer Management Inc",
    "wof:placetype":"venue"
},
  "geometry": {"coordinates":[-95.38892300000001,29.755519],"type":"Point"}
}