{
  "type": "Feature",
  "properties": {
    "iso:country":"US",
    "sg:address":"2909 Greenville Ave",
    "sg:city":"Dallas",
    "sg:classifiers":[
        {
            "category":"Professional",
            "type":"Services"
        }
    ],
    "sg:phone":"+1 214 827 8100",
    "sg:postcode":"75206",
    "sg:province":"TX",
    "sg:tags":[
        "caterer"
    ],
    "sg:website":"www.bluegoose.com",
    "wof:name":"Blue Goose Catering",
    "wof:placetype":"venue"
},
  "geometry": {"coordinates":[-96.77031599999999,32.823809],"type":"Point"}
}