{
  "type": "Feature",
  "properties": {
    "iso:country":"US",
    "sg:address":"1628 S Presa St",
    "sg:city":"San Antonio",
    "sg:classifiers":[
        {
            "category":"Bars & Pubs",
            "type":"Food & Drink"
        }
    ],
    "sg:phone":"+1 210 533 2442",
    "sg:postcode":"78210",
    "sg:province":"TX",
    "sg:tags":[
        "drinking"
    ],
    "wof:name":"El Sauzeno Lounge",
    "wof:placetype":"venue"
},
  "geometry": {"coordinates":[-98.483698,29.404144],"type":"Point"}
}