{
  "type": "Feature",
  "properties": {
    "iso:country":"US",
    "sg:address":"14304 Gulf Fwy",
    "sg:city":"Houston",
    "sg:classifiers":[
        {
            "category":"Banks & Credit Unions",
            "subcategory":"Bank",
            "type":"Services"
        }
    ],
    "sg:phone":"+1 281 464 0352",
    "sg:postcode":"77034",
    "sg:province":"TX",
    "sg:tags":[
        "machine",
        "teller",
        "automated"
    ],
    "wof:name":"Access Cash Intl",
    "wof:placetype":"venue"
},
  "geometry": {"coordinates":[-95.19651399999999,29.597266],"type":"Point"}
}