{
  "type": "Feature",
  "properties": {
    "iso:country":"US",
    "sg:address":"3602 Beau Ln",
    "sg:city":"Houston",
    "sg:classifiers":[
        {
            "category":"Shopping",
            "subcategory":"Jewelry",
            "type":"Retail Goods"
        }
    ],
    "sg:phone":"+1 281 449 3692",
    "sg:postcode":"77039",
    "sg:province":"TX",
    "wof:name":"Garcias Gold Jewelry",
    "wof:placetype":"venue"
},
  "geometry": {"coordinates":[-95.33826500000001,29.899971],"type":"Point"}
}