{
  "type": "Feature",
  "properties": {
    "iso:country":"US",
    "sg:address":"20940 Katy Fwy",
    "sg:city":"Katy",
    "sg:classifiers":[
        {
            "category":"Restaurant",
            "type":"Food & Drink"
        },
        {
            "category":"Food & Beverages",
            "subcategory":"Meat & Fish",
            "type":"Retail Goods"
        }
    ],
    "sg:phone":"+1 281 646 0700",
    "sg:postcode":"77449",
    "sg:province":"TX",
    "sg:tags":[
        "cajun",
        "seafood-wholesale",
        "creole",
        "seafood"
    ],
    "sg:website":"http://www.orleansseafoodkitchen.com",
    "wof:name":"Orleans Seafood Kitchen",
    "wof:placetype":"venue"
},
  "geometry": {"coordinates":[-95.743719,29.78575],"type":"Point"}
}