{
  "type": "Feature",
  "properties": {
    "iso:country":"US",
    "sg:address":"9226 Sequoia Dr",
    "sg:city":"Houston",
    "sg:classifiers":[
        {
            "category":"Retail",
            "subcategory":"Pet Boarding",
            "type":"Services"
        }
    ],
    "sg:phone":"+1 713 690 3111",
    "sg:postcode":"77041",
    "sg:province":"TX",
    "sg:tags":[
        "boarding/pet",
        "sitting"
    ],
    "sg:website":"www.jhb-enterprises.com/homeisbest",
    "wof:name":"Home Is Best Pet Sitting",
    "wof:placetype":"venue"
},
  "geometry": {"coordinates":[-95.520522,29.840674],"type":"Point"}
}