{
  "type": "Feature",
  "properties": {
    "iso:country":"US",
    "sg:address":"1112 Woodcrest St",
    "sg:city":"Azle",
    "sg:classifiers":[
        {
            "category":"Building & Trades",
            "subcategory":"Electrical",
            "type":"Services"
        }
    ],
    "sg:phone":"+1 817 444 6830",
    "sg:postcode":"76020",
    "sg:province":"TX",
    "sg:tags":[
        "electrical",
        "contractor"
    ],
    "wof:name":"Barnett Electric",
    "wof:placetype":"venue"
},
  "geometry": {"coordinates":[-97.560654,32.875532],"type":"Point"}
}