{
  "type": "Feature",
  "properties": {
    "iso:country":"US",
    "sg:address":"201 Royal Oaks Ct",
    "sg:city":"Denton",
    "sg:classifiers":[
        {
            "category":"Professional",
            "subcategory":"Engineering",
            "type":"Services"
        }
    ],
    "sg:phone":"+1 940 565 1579",
    "sg:postcode":"76210",
    "sg:province":"TX",
    "wof:name":"Cooper Consulting Engineers",
    "wof:placetype":"venue"
},
  "geometry": {"coordinates":[-97.12951,33.16211],"type":"Point"}
}