{
  "type": "Feature",
  "properties": {
    "iso:country":"US",
    "sg:address":"11826 Wurzbach Rd",
    "sg:city":"San Antonio",
    "sg:classifiers":[
        {
            "category":"Restaurant",
            "type":"Food & Drink"
        }
    ],
    "sg:phone":"+1 210 492 1359",
    "sg:postcode":"78230",
    "sg:province":"TX",
    "wof:name":"Pam's Patio Kitchen",
    "wof:placetype":"venue"
},
  "geometry": {"coordinates":[-98.541456,29.550981],"type":"Point"}
}