{
  "type": "Feature",
  "properties": {
    "iso:country":"US",
    "sg:address":"730 Division Ave",
    "sg:city":"San Antonio",
    "sg:classifiers":[
        {
            "category":"Professional",
            "type":"Services"
        }
    ],
    "sg:phone":"+1 210 924 9353",
    "sg:postcode":"78225",
    "sg:province":"TX",
    "sg:tags":[
        "establishment"
    ],
    "wof:name":"Carlos Terrazas",
    "wof:placetype":"venue"
},
  "geometry": {"coordinates":[-98.51616799999999,29.379462],"type":"Point"}
}