{
  "type": "Feature",
  "properties": {
    "iso:country":"US",
    "sg:address":"7000 Allen Place Dr",
    "sg:city":"Fort Worth",
    "sg:classifiers":[
        {
            "category":"Building & Trades",
            "subcategory":"Construction",
            "type":"Services"
        }
    ],
    "sg:phone":"+1 817 735 1304",
    "sg:postcode":"76116",
    "sg:province":"TX",
    "sg:tags":[
        "house"
    ],
    "wof:name":"Lawson & Associates Inc",
    "wof:placetype":"venue"
},
  "geometry": {"coordinates":[-97.43037099999999,32.698366],"type":"Point"}
}