{
  "type": "Feature",
  "properties": {
    "iso:country":"US",
    "sg:address":"2714 Smith St",
    "sg:city":"Houston",
    "sg:classifiers":[
        {
            "category":"Banks & Credit Unions",
            "subcategory":"Bank",
            "type":"Services"
        },
        {
            "category":"Banks & Credit Unions",
            "subcategory":"Financial Services",
            "type":"Services"
        }
    ],
    "sg:phone":"+1 713 522 0616",
    "sg:postcode":"77006",
    "sg:province":"TX",
    "sg:tags":[
        "commercial",
        "loan",
        "saving",
        "mortgage"
    ],
    "sg:website":"https://www.wellsfargo.com/wfonline/",
    "wof:name":"Wells Fargo Bank",
    "wof:placetype":"venue"
},
  "geometry": {"coordinates":[-95.378147,29.746686],"type":"Point"}
}