{
  "type": "Feature",
  "properties": {
    "iso:country":"US",
    "sg:address":"6506 Bandera Rd",
    "sg:city":"San Antonio",
    "sg:classifiers":[
        {
            "category":"Home & Garden",
            "subcategory":"Furniture",
            "type":"Retail Goods"
        }
    ],
    "sg:phone":"+1 210 509 6036",
    "sg:postcode":"78238",
    "sg:province":"TX",
    "sg:tags":[
        "cabinet"
    ],
    "wof:name":"Cabinet Shop",
    "wof:placetype":"venue"
},
  "geometry": {"coordinates":[-98.615968,29.493326],"type":"Point"}
}