{
  "type": "Feature",
  "properties": {
    "iso:country":"US",
    "sg:address":"21435 Roseville Dr",
    "sg:city":"Spring",
    "sg:classifiers":[
        {
            "category":"Professional",
            "subcategory":"Business Services",
            "type":"Services"
        }
    ],
    "sg:phone":"+1 281 350 1692",
    "sg:postcode":"77388",
    "sg:province":"TX",
    "wof:name":"Extreme Enterprises",
    "wof:placetype":"venue"
},
  "geometry": {"coordinates":[-95.472089,30.07218],"type":"Point"}
}