{
  "type": "Feature",
  "properties": {
    "iso:country":"US",
    "sg:address":"3613 Rancho del Rey",
    "sg:city":"Edinburg",
    "sg:classifiers":[
        {
            "category":"Wholesale",
            "subcategory":"Non-durable Goods",
            "type":"Manufacturing & Wholesale Goods"
        }
    ],
    "sg:phone":"+1 956 381 8321",
    "sg:postcode":"78541",
    "sg:province":"TX",
    "wof:name":"Leal Distributing Co",
    "wof:placetype":"venue"
},
  "geometry": {"coordinates":[-98.12090600000001,26.3193],"type":"Point"}
}