{
  "type": "Feature",
  "properties": {
    "iso:country":"US",
    "sg:address":"1504 2nd St",
    "sg:city":"Pleasanton",
    "sg:classifiers":[
        {
            "category":"Insurance",
            "subcategory":"Insurance Agent",
            "type":"Services"
        }
    ],
    "sg:phone":"+1 830 281 3366",
    "sg:postcode":"78064",
    "sg:province":"TX",
    "wof:name":"Amco Auto Insurance",
    "wof:placetype":"venue"
},
  "geometry": {"coordinates":[-98.478819,28.973908],"type":"Point"}
}