{
  "type": "Feature",
  "properties": {
    "iso:country":"US",
    "sg:address":"8900 Shoal Creek Blvd Ste 121",
    "sg:city":"Austin",
    "sg:classifiers":[
        {
            "category":"Building & Trades",
            "subcategory":"Construction",
            "type":"Services"
        }
    ],
    "sg:phone":"+1 512 258 9114",
    "sg:postcode":"78757",
    "sg:province":"TX",
    "sg:tags":[
        "contractor"
    ],
    "wof:name":"Omni Environmental",
    "wof:placetype":"venue"
},
  "geometry": {"coordinates":[-97.734219,30.375881],"type":"Point"}
}