{
  "type": "Feature",
  "properties": {
    "iso:country":"US",
    "sg:address":"443 Vernet St",
    "sg:city":"Richardson",
    "sg:classifiers":[
        {
            "category":"Building & Trades",
            "subcategory":"Landscaping Services",
            "type":"Services"
        }
    ],
    "sg:phone":"+1 972 907 1005",
    "sg:postcode":"75080",
    "sg:province":"TX",
    "sg:tags":[
        "landscape"
    ],
    "wof:name":"Jema Landscape",
    "wof:placetype":"venue"
},
  "geometry": {"coordinates":[-96.732148,32.966178],"type":"Point"}
}