{
  "type": "Feature",
  "properties": {
    "iso:country":"US",
    "sg:address":"2928 N Industrial Ave",
    "sg:city":"Tyler",
    "sg:classifiers":[
        {
            "category":"Wholesale",
            "subcategory":"Scrap",
            "type":"Manufacturing & Wholesale Goods"
        },
        {
            "category":"Utilities",
            "subcategory":"Recycling",
            "type":"Services"
        }
    ],
    "sg:phone":"+1 903 597 6242",
    "sg:postcode":"75708",
    "sg:province":"TX",
    "sg:tags":[
        "junk",
        "metal"
    ],
    "wof:name":"Bloch Metals",
    "wof:placetype":"venue"
},
  "geometry": {"coordinates":[-95.274845,32.382934],"type":"Point"}
}