{
  "type": "Feature",
  "properties": {
    "iso:country":"US",
    "sg:address":"3716 Miramar Ave",
    "sg:city":"Dallas",
    "sg:classifiers":[
        {
            "category":"Professional",
            "subcategory":"Business Services",
            "type":"Services"
        }
    ],
    "sg:phone":"+1 214 526 8112",
    "sg:postcode":"75205",
    "sg:province":"TX",
    "wof:name":"The Empty Nest",
    "wof:placetype":"venue"
},
  "geometry": {"coordinates":[-96.796211,32.83096],"type":"Point"}
}