{
  "type": "Feature",
  "properties": {
    "iso:country":"US",
    "sg:address":"904 Libold Dr",
    "sg:city":"Devine",
    "sg:classifiers":[
        {
            "category":"Wholesale",
            "subcategory":"Machinery & Supplies",
            "type":"Manufacturing & Wholesale Goods"
        }
    ],
    "sg:phone":"+1 830 663 5032",
    "sg:postcode":"78016",
    "sg:province":"TX",
    "wof:name":"Aftermarket AG Parts",
    "wof:placetype":"venue"
},
  "geometry": {"coordinates":[-98.904253,29.150584],"type":"Point"}
}