{
  "type": "Feature",
  "properties": {
    "iso:country":"US",
    "sg:address":"3704 S Polk St",
    "sg:city":"Amarillo",
    "sg:classifiers":[
        {
            "category":"Professional",
            "subcategory":"Business Services",
            "type":"Services"
        }
    ],
    "sg:phone":"+1 806 376 9160",
    "sg:postcode":"79110",
    "sg:province":"TX",
    "sg:tags":[
        "sewing"
    ],
    "wof:name":"Perfect Fit",
    "wof:placetype":"venue"
},
  "geometry": {"coordinates":[-101.841128,35.174471],"type":"Point"}
}