{
  "type": "Feature",
  "properties": {
    "iso:country":"US",
    "sg:address":"5818 Balcones Dr",
    "sg:city":"Austin",
    "sg:classifiers":[
        {
            "category":"Professional",
            "subcategory":"Lawyer & Legal Services",
            "type":"Services"
        }
    ],
    "sg:phone":"+1 512 452 9954",
    "sg:postcode":"78731",
    "sg:province":"TX",
    "wof:name":"Law Off of William P Harbeson",
    "wof:placetype":"venue"
},
  "geometry": {"coordinates":[-97.752911,30.343901],"type":"Point"}
}