{
  "type": "Feature",
  "properties": {
    "iso:country":"US",
    "sg:address":"201 Brothers Blvd",
    "sg:city":"Red Oak",
    "sg:classifiers":[
        {
            "category":"Building & Trades",
            "subcategory":"Cleaning & Sanitation",
            "type":"Services"
        },
        {
            "category":"Building & Trades",
            "subcategory":"Construction",
            "type":"Services"
        }
    ],
    "sg:phone":"+1 972 617 9757",
    "sg:postcode":"75154",
    "sg:province":"TX",
    "sg:tags":[
        "maintenance",
        "contractor"
    ],
    "wof:name":"J & D Maintenance Inc",
    "wof:placetype":"venue"
},
  "geometry": {"coordinates":[-96.81997699999999,32.514807],"type":"Point"}
}