{
  "type": "Feature",
  "properties": {
    "iso:country":"US",
    "sg:address":"623 S Leona St",
    "sg:city":"San Antonio",
    "sg:classifiers":[
        {
            "category":"Manufacturing",
            "subcategory":"Food",
            "type":"Manufacturing & Wholesale Goods"
        },
        {
            "category":"Food & Beverages",
            "subcategory":"Fruits & Vegetables",
            "type":"Retail Goods"
        }
    ],
    "sg:phone":"+1 210 472 1688",
    "sg:postcode":"78207",
    "sg:province":"TX",
    "sg:tags":[
        "juice",
        "mfg",
        "specialty",
        "canned"
    ],
    "wof:name":"Alamo Mexican Food Distrs",
    "wof:placetype":"venue"
},
  "geometry": {"coordinates":[-98.50351499999999,29.419712],"type":"Point"}
}