{
  "type": "Feature",
  "properties": {
    "iso:country":"US",
    "sg:address":"303 Main St",
    "sg:city":"Smithville",
    "sg:classifiers":[
        {
            "category":"Professional",
            "subcategory":"Advertising",
            "type":"Services"
        }
    ],
    "sg:phone":"+1 512 237 4655",
    "sg:postcode":"78957",
    "sg:province":"TX",
    "wof:name":"Smithville Times",
    "wof:placetype":"venue"
},
  "geometry": {"coordinates":[-97.15916799999999,30.009337],"type":"Point"}
}