{
  "type": "Feature",
  "properties": {
    "iso:country":"US",
    "sg:address":"1801 N White Oak Rd",
    "sg:city":"White Oak",
    "sg:classifiers":[
        {
            "category":"Professional",
            "subcategory":"Testing Lab",
            "type":"Services"
        }
    ],
    "sg:phone":"+1 903 297 5972",
    "sg:postcode":"75693",
    "sg:province":"TX",
    "sg:tags":[
        "calibration"
    ],
    "wof:name":"Automationeering",
    "wof:placetype":"venue"
},
  "geometry": {"coordinates":[-94.862784,32.558881],"type":"Point"}
}