{
  "type": "Feature",
  "properties": {
    "iso:country":"US",
    "sg:address":"3201 Duval Rd Apt 224",
    "sg:city":"Austin",
    "sg:classifiers":[
        {
            "category":"Insurance",
            "subcategory":"Hazard Insurance",
            "type":"Services"
        }
    ],
    "sg:phone":"+1 512 491 6589",
    "sg:postcode":"78759",
    "sg:province":"TX",
    "wof:name":"Mopactech Ltd Liability Co",
    "wof:placetype":"venue"
},
  "geometry": {"coordinates":[-97.716312,30.409548],"type":"Point"}
}