{
  "type": "Feature",
  "properties": {
    "iso:country":"US",
    "sg:address":"1418 Roy St",
    "sg:city":"Houston",
    "sg:classifiers":[
        {
            "category":"Wholesale",
            "subcategory":"Vending Machines",
            "type":"Manufacturing & Wholesale Goods"
        }
    ],
    "sg:phone":"+1 713 861 5331",
    "sg:postcode":"77007",
    "sg:province":"TX",
    "sg:tags":[
        "operated",
        "phonograph"
    ],
    "wof:name":"Apollo Music Co",
    "wof:placetype":"venue"
},
  "geometry": {"coordinates":[-95.412475,29.773306],"type":"Point"}
}