{
  "type": "Feature",
  "properties": {
    "iso:country":"US",
    "sg:address":"10000 US Hwy 183",
    "sg:city":"Florence",
    "sg:classifiers":[
        {
            "category":"Recreation",
            "type":"Entertainment"
        }
    ],
    "sg:phone":"+1 254 793 3906",
    "sg:postcode":"76527",
    "sg:province":"TX",
    "sg:tags":[
        "safety",
        "instruction",
        "marksmanship",
        "gun"
    ],
    "wof:name":"Tony's Guns & Range",
    "wof:placetype":"venue"
},
  "geometry": {"coordinates":[-97.88628799999999,30.797981],"type":"Point"}
}