{
  "type": "Feature",
  "properties": {
    "iso:country":"US",
    "sg:address":"2243 Oakwood Ln",
    "sg:city":"Abilene",
    "sg:classifiers":[
        {
            "category":"Restaurant",
            "type":"Food & Drink"
        }
    ],
    "sg:phone":"+1 325 692 8253",
    "sg:postcode":"79605",
    "sg:province":"TX",
    "sg:tags":[
        "eating"
    ],
    "wof:name":"Pyland Sub & Mary",
    "wof:placetype":"venue"
},
  "geometry": {"coordinates":[-99.76693299999999,32.424107],"type":"Point"}
}