{
  "type": "Feature",
  "properties": {
    "iso:country":"US",
    "sg:address":"115 Legion Dr",
    "sg:city":"Richmond",
    "sg:classifiers":[
        {
            "category":"Government",
            "subcategory":"Office",
            "type":"Public Place"
        }
    ],
    "sg:phone":"+1 281 633 7400",
    "sg:postcode":"77469",
    "sg:province":"TX",
    "wof:name":"Fort Bend Cnty Juvenile Prbtn",
    "wof:placetype":"venue"
},
  "geometry": {"coordinates":[-95.751563,29.574044],"type":"Point"}
}