{
  "type": "Feature",
  "properties": {
    "iso:country":"US",
    "sg:address":"604 Worthview Dr",
    "sg:city":"Fort Worth",
    "sg:classifiers":[
        {
            "category":"Retail",
            "subcategory":"Auto Repair",
            "type":"Services"
        }
    ],
    "sg:phone":"+1 817 763 5175",
    "sg:postcode":"76114",
    "sg:province":"TX",
    "sg:tags":[
        "general"
    ],
    "wof:name":"Harolds Mobile",
    "wof:placetype":"venue"
},
  "geometry": {"coordinates":[-97.392854,32.769631],"type":"Point"}
}