{
  "type": "Feature",
  "properties": {
    "iso:country":"US",
    "sg:address":"654 FM 1848",
    "sg:city":"Buffalo",
    "sg:classifiers":[
        {
            "category":"Professional",
            "type":"Services"
        }
    ],
    "sg:phone":"+1 903 322 1326",
    "sg:postcode":"75831",
    "sg:province":"TX",
    "wof:name":"Destiny Carriage Service",
    "wof:placetype":"venue"
},
  "geometry": {"coordinates":[-96.055262,31.473705],"type":"Point"}
}