{
  "type": "Feature",
  "properties": {
    "iso:country":"US",
    "sg:address":"990 Rayford Rd",
    "sg:city":"Spring",
    "sg:classifiers":[
        {
            "category":"Professional",
            "subcategory":"Business Services",
            "type":"Services"
        }
    ],
    "sg:phone":"+1 281 419 2091",
    "sg:postcode":"77386",
    "sg:province":"TX",
    "sg:tags":[
        "notary"
    ],
    "wof:name":"N B Signing Agency",
    "wof:placetype":"venue"
},
  "geometry": {"coordinates":[-95.42173099999999,30.125919],"type":"Point"}
}