{
  "type": "Feature",
  "properties": {
    "iso:country":"US",
    "sg:address":"1601 Main St",
    "sg:city":"Richmond",
    "sg:classifiers":[
        {
            "category":"Health Services",
            "subcategory":"Doctor",
            "type":"Services"
        }
    ],
    "sg:phone":"+1 281 341 6161",
    "sg:postcode":"77469",
    "sg:province":"TX",
    "sg:tags":[
        "medical"
    ],
    "wof:name":"Peter J Curtis",
    "wof:placetype":"venue"
},
  "geometry": {"coordinates":[-95.768395,29.577194],"type":"Point"}
}