{
  "type": "Feature",
  "properties": {
    "iso:country":"US",
    "sg:address":"322 State Hwy 323",
    "sg:city":"Tyler",
    "sg:classifiers":[
        {
            "category":"Professional",
            "subcategory":"Accounting & Tax Preparation",
            "type":"Services"
        }
    ],
    "sg:phone":"+1 903 561 5683",
    "sg:postcode":"75701",
    "sg:province":"TX",
    "sg:tags":[
        "return"
    ],
    "wof:name":"All Star Tax Refund",
    "wof:placetype":"venue"
},
  "geometry": {"coordinates":[-95.301598,32.302827],"type":"Point"}
}