{
  "type": "Feature",
  "properties": {
    "iso:country":"US",
    "sg:address":"2110 S Lamar Blvd Ste F",
    "sg:city":"Austin",
    "sg:classifiers":[
        {
            "category":"Shopping",
            "subcategory":"Optician",
            "type":"Retail Goods"
        }
    ],
    "sg:phone":"+1 512 382 6197",
    "sg:postcode":"78704",
    "sg:province":"TX",
    "sg:tags":[
        "eyewear"
    ],
    "wof:name":"Spectacle Sunglasses",
    "wof:placetype":"venue"
},
  "geometry": {"coordinates":[-97.77157699999999,30.248259],"type":"Point"}
}