{
  "type": "Feature",
  "properties": {
    "iso:country":"US",
    "sg:address":"1408 Whitson St",
    "sg:city":"Bay City",
    "sg:classifiers":[
        {
            "category":"Real Estate",
            "subcategory":"Real Estate Operator",
            "type":"Services"
        }
    ],
    "sg:phone":"+1 979 245 6582",
    "sg:postcode":"77414",
    "sg:province":"TX",
    "sg:tags":[
        "apartment"
    ],
    "wof:name":"Roland Hillard Memorial Apts",
    "wof:placetype":"venue"
},
  "geometry": {"coordinates":[-95.97070600000001,28.969342],"type":"Point"}
}