{
  "type": "Feature",
  "properties": {
    "iso:country":"US",
    "sg:address":"2045 US Hwy 183",
    "sg:city":"Breckenridge",
    "sg:classifiers":[
        {
            "category":"Wholesale",
            "subcategory":"Chemicals & Plastics",
            "type":"Manufacturing & Wholesale Goods"
        }
    ],
    "sg:phone":"+1 254 559 9108",
    "sg:postcode":"76424",
    "sg:province":"TX",
    "wof:name":"Champion Technologies",
    "wof:placetype":"venue"
},
  "geometry": {"coordinates":[-98.902698,32.780133],"type":"Point"}
}