{
  "type": "Feature",
  "properties": {
    "iso:country":"US",
    "sg:address":"1207 W 2nd St",
    "sg:city":"Tyler",
    "sg:classifiers":[
        {
            "category":"Professional",
            "type":"Services"
        }
    ],
    "sg:phone":"+1 903 597 4542",
    "sg:postcode":"75701",
    "sg:province":"TX",
    "sg:tags":[
        "establishment"
    ],
    "wof:name":"Pittman N R",
    "wof:placetype":"venue"
},
  "geometry": {"coordinates":[-95.31511,32.334064],"type":"Point"}
}