{
  "type": "Feature",
  "properties": {
    "iso:country":"US",
    "sg:address":"1001 Federal Rd",
    "sg:city":"Houston",
    "sg:classifiers":[
        {
            "category":"Home & Garden",
            "subcategory":"Furniture",
            "type":"Retail Goods"
        }
    ],
    "sg:phone":"+1 713 455 8707",
    "sg:postcode":"77015",
    "sg:province":"TX",
    "sg:tags":[
        "store"
    ],
    "wof:name":"Ez Auto Insurance",
    "wof:placetype":"venue"
},
  "geometry": {"coordinates":[-95.214203,29.771999],"type":"Point"}
}