{
  "type": "Feature",
  "properties": {
    "iso:country":"US",
    "sg:address":"8511 Cedarbrake Dr",
    "sg:city":"Houston",
    "sg:classifiers":[
        {
            "category":"Shopping",
            "subcategory":"Clothing, Apparel, & Fashions",
            "type":"Retail Goods"
        }
    ],
    "sg:phone":"+1 713 461 7401",
    "sg:postcode":"77055",
    "sg:province":"TX",
    "wof:name":"Carole Viamin",
    "wof:placetype":"venue"
},
  "geometry": {"coordinates":[-95.49941699999999,29.790983],"type":"Point"}
}