{
  "type": "Feature",
  "properties": {
    "iso:country":"US",
    "sg:address":"1515 Saddlecreek Dr",
    "sg:city":"Houston",
    "sg:classifiers":[
        {
            "category":"Shopping",
            "subcategory":"Gifts & Souvenirs",
            "type":"Retail Goods"
        }
    ],
    "sg:phone":"+1 281 895 6842",
    "sg:postcode":"77090",
    "sg:province":"TX",
    "wof:name":"Kristin A Wallis",
    "wof:placetype":"venue"
},
  "geometry": {"coordinates":[-95.456149,30.019157],"type":"Point"}
}