{
  "type": "Feature",
  "properties": {
    "iso:country":"US",
    "sg:address":"216 S Grants Ln",
    "sg:city":"White Settlement",
    "sg:classifiers":[
        {
            "category":"Real Estate",
            "subcategory":"Real Estate Operator",
            "type":"Services"
        }
    ],
    "sg:phone":"+1 817 246 4025",
    "sg:postcode":"76108",
    "sg:province":"TX",
    "sg:tags":[
        "mobile",
        "home",
        "community"
    ],
    "wof:name":"Rollahome Park",
    "wof:placetype":"venue"
},
  "geometry": {"coordinates":[-97.446055,32.75829],"type":"Point"}
}