{
  "type": "Feature",
  "properties": {
    "iso:country":"US",
    "sg:address":"1731 W Wheeler Ave",
    "sg:city":"Aransas Pass",
    "sg:classifiers":[
        {
            "category":"Health Services",
            "subcategory":"Doctor",
            "type":"Services"
        }
    ],
    "sg:phone":"+1 361 729 4050",
    "sg:postcode":"78336",
    "sg:province":"TX",
    "sg:tags":[
        "osteopathic"
    ],
    "wof:name":"Pj Marshio",
    "wof:placetype":"venue"
},
  "geometry": {"coordinates":[-97.160213,27.914941],"type":"Point"}
}