{
  "type": "Feature",
  "properties": {
    "iso:country":"US",
    "sg:address":"3330 N Galloway Ave",
    "sg:city":"Mesquite",
    "sg:classifiers":[
        {
            "category":"Retail",
            "subcategory":"Portrait Studio",
            "type":"Services"
        }
    ],
    "sg:phone":"+1 972 222 8787",
    "sg:postcode":"75150",
    "sg:province":"TX",
    "sg:tags":[
        "photographer"
    ],
    "wof:name":"Photography By Dana",
    "wof:placetype":"venue"
},
  "geometry": {"coordinates":[-96.611194,32.810109],"type":"Point"}
}