{
  "type": "Feature",
  "properties": {
    "iso:country":"US",
    "sg:address":"1403 Wunsche Loop",
    "sg:city":"Spring",
    "sg:classifiers":[
        {
            "category":"Professional",
            "subcategory":"Business Services",
            "type":"Services"
        }
    ],
    "sg:phone":"+1 281 353 5707",
    "sg:postcode":"77373",
    "sg:province":"TX",
    "wof:name":"Fairway Enterprises",
    "wof:placetype":"venue"
},
  "geometry": {"coordinates":[-95.43240900000001,30.079364],"type":"Point"}
}