{
  "type": "Feature",
  "properties": {
    "iso:country":"US",
    "sg:address":"28377 FM 529",
    "sg:city":"Katy",
    "sg:classifiers":[
        {
            "category":"Manufacturing",
            "subcategory":"Tools & Machinery",
            "type":"Manufacturing & Wholesale Goods"
        }
    ],
    "sg:phone":"+1 281 371 2424",
    "sg:postcode":"77493",
    "sg:province":"TX",
    "sg:tags":[
        "field",
        "oil",
        "equipment"
    ],
    "sg:website":"www.marhyd.com",
    "wof:name":"M H PYRAMID Inc",
    "wof:placetype":"venue"
},
  "geometry": {"coordinates":[-95.848068,29.874319],"type":"Point"}
}