{
  "type": "Feature",
  "properties": {
    "iso:country":"US",
    "sg:address":"3718 Rau Dr",
    "sg:city":"Dickinson",
    "sg:classifiers":[
        {
            "category":"Building & Trades",
            "subcategory":"Construction",
            "type":"Services"
        }
    ],
    "sg:phone":"+1 281 337 6104",
    "sg:postcode":"77539",
    "sg:province":"TX",
    "sg:tags":[
        "hanging",
        "contractor"
    ],
    "wof:name":"Decorating Unlimited",
    "wof:placetype":"venue"
},
  "geometry": {"coordinates":[-95.08652600000001,29.444025],"type":"Point"}
}