{
  "type": "Feature",
  "properties": {
    "iso:country":"US",
    "sg:address":"1911 Woodland Dr",
    "sg:city":"Cedar Park",
    "sg:classifiers":[
        {
            "category":"Building & Trades",
            "subcategory":"Landscaping Services",
            "type":"Services"
        }
    ],
    "sg:phone":"+1 512 259 4438",
    "sg:postcode":"78613",
    "sg:province":"TX",
    "wof:name":"All American Lawn Maintenance",
    "wof:placetype":"venue"
},
  "geometry": {"coordinates":[-97.848562,30.52761],"type":"Point"}
}