{
  "type": "Feature",
  "properties": {
    "iso:country":"US",
    "sg:address":"6602 State Hwy 6",
    "sg:city":"Houston",
    "sg:classifiers":[
        {
            "category":"Autos & Motor Vehicles",
            "subcategory":"Auto Supplies",
            "type":"Retail Goods"
        }
    ],
    "sg:phone":"+1 281 345 4600",
    "sg:postcode":"77084",
    "sg:province":"TX",
    "sg:tags":[
        "tire"
    ],
    "sg:website":"www.tires.com",
    "wof:name":"Discount Tire Co",
    "wof:placetype":"venue"
},
  "geometry": {"coordinates":[-95.64515400000001,29.874056],"type":"Point"}
}