{
  "type": "Feature",
  "properties": {
    "iso:country":"US",
    "sg:address":"707 Preston Royal Shopping Center",
    "sg:city":"Dallas",
    "sg:classifiers":[
        {
            "category":"Restaurant",
            "type":"Food & Drink"
        }
    ],
    "sg:phone":"+1 214 360 9760",
    "sg:postcode":"75230",
    "sg:province":"TX",
    "wof:name":"Popolo's Restaurant",
    "wof:placetype":"venue"
},
  "geometry": {"coordinates":[-96.80550599999999,32.8954],"type":"Point"}
}