{
  "type": "Feature",
  "properties": {
    "iso:country":"US",
    "sg:address":"618 W Houston St",
    "sg:city":"Sherman",
    "sg:classifiers":[
        {
            "category":"Retail",
            "subcategory":"Auto Repair",
            "type":"Services"
        }
    ],
    "sg:phone":"+1 903 868 1190",
    "sg:postcode":"75090",
    "sg:province":"TX",
    "sg:tags":[
        "repairing",
        "automobile"
    ],
    "wof:name":"David Ellis Automotive Svc Ctr",
    "wof:placetype":"venue"
},
  "geometry": {"coordinates":[-96.614881,33.635373],"type":"Point"}
}