{
  "type": "Feature",
  "properties": {
    "iso:country":"US",
    "sg:address":"3679 Calder Ave",
    "sg:city":"Beaumont",
    "sg:classifiers":[
        {
            "category":"Education",
            "subcategory":"Special Training",
            "type":"Public Place"
        }
    ],
    "sg:phone":"+1 409 832 4301",
    "sg:postcode":"77706",
    "sg:province":"TX",
    "sg:tags":[
        "school",
        "massage"
    ],
    "wof:name":"Body Mind School Of Massage",
    "wof:placetype":"venue"
},
  "geometry": {"coordinates":[-94.140349,30.085369],"type":"Point"}
}