{
  "type": "Feature",
  "properties": {
    "iso:country":"US",
    "sg:address":"13915 Waterloo Dr",
    "sg:city":"Houston",
    "sg:classifiers":[
        {
            "category":"Shopping",
            "type":"Retail Goods"
        }
    ],
    "sg:phone":"+1 713 434 8203",
    "sg:postcode":"77045",
    "sg:province":"TX",
    "sg:tags":[
        "merchandise"
    ],
    "wof:name":"J & S Ashion Depot",
    "wof:placetype":"venue"
},
  "geometry": {"coordinates":[-95.424402,29.624888],"type":"Point"}
}