{
  "type": "Feature",
  "properties": {
    "iso:country":"US",
    "sg:address":"10300 Shady Ln",
    "sg:city":"Houston",
    "sg:classifiers":[
        {
            "category":"Education",
            "subcategory":"School",
            "type":"Public Place"
        }
    ],
    "sg:phone":"+1 713 691 2929",
    "sg:postcode":"77093",
    "sg:province":"TX",
    "sg:tags":[
        "k-",
        "private"
    ],
    "wof:name":"Golden Kids Academy",
    "wof:placetype":"venue"
},
  "geometry": {"coordinates":[-95.34311700000001,29.861719],"type":"Point"}
}