{
  "type": "Feature",
  "properties": {
    "iso:country":"US",
    "sg:address":"201 Walls Dr",
    "sg:city":"Cleburne",
    "sg:classifiers":[
        {
            "category":"Health Services",
            "subcategory":"Doctor",
            "type":"Services"
        }
    ],
    "sg:phone":"+1 817 645 1100",
    "sg:postcode":"76033",
    "sg:province":"TX",
    "sg:tags":[
        "physician",
        "surgeon"
    ],
    "wof:name":"Ford Ray Pa",
    "wof:placetype":"venue"
},
  "geometry": {"coordinates":[-97.437974,32.330548],"type":"Point"}
}