{
  "type": "Feature",
  "properties": {
    "iso:country":"US",
    "sg:address":"201 S Bonham Ave",
    "sg:city":"Cleveland",
    "sg:classifiers":[
        {
            "category":"Shopping",
            "subcategory":"Florist",
            "type":"Retail Goods"
        },
        {
            "category":"Home & Garden",
            "subcategory":"Garden Supply",
            "type":"Retail Goods"
        }
    ],
    "sg:phone":"+1 281 593 0621",
    "sg:postcode":"77327",
    "sg:province":"TX",
    "wof:name":"Vannee's Bloomin' Yard",
    "wof:placetype":"venue"
},
  "geometry": {"coordinates":[-95.086883,30.340564],"type":"Point"}
}