{
  "type": "Feature",
  "properties": {
    "iso:country":"US",
    "sg:address":"411 Richmond Ave",
    "sg:city":"Houston",
    "sg:classifiers":[
        {
            "category":"Food & Beverages",
            "subcategory":"Groceries & Convenience Stores",
            "type":"Retail Goods"
        }
    ],
    "sg:phone":"+1 713 521 9881",
    "sg:postcode":"77002",
    "sg:province":"TX",
    "wof:name":"Chaban Enterprize",
    "wof:placetype":"venue"
},
  "geometry": {"coordinates":[-95.38483600000001,29.734472],"type":"Point"}
}