{
  "type": "Feature",
  "properties": {
    "iso:country":"US",
    "sg:address":"1609 Beaumont Ave",
    "sg:city":"Mcallen",
    "sg:classifiers":[
        {
            "category":"Taxi",
            "type":"Transportation"
        }
    ],
    "sg:phone":"+1 956 686 4334",
    "sg:postcode":"78501",
    "sg:province":"TX",
    "sg:tags":[
        "taxicab"
    ],
    "wof:name":"Valley Taxi",
    "wof:placetype":"venue"
},
  "geometry": {"coordinates":[-98.237973,26.202768],"type":"Point"}
}