{
  "type": "Feature",
  "properties": {
    "iso:country":"US",
    "sg:address":"5005 John Stockbauer Dr",
    "sg:city":"Victoria",
    "sg:classifiers":[
        {
            "category":"Health Services",
            "subcategory":"Chiropractor",
            "type":"Services"
        }
    ],
    "sg:phone":"+1 361 576 9156",
    "sg:postcode":"77904",
    "sg:province":"TX",
    "wof:name":"Family Chiropractic Center",
    "wof:placetype":"venue"
},
  "geometry": {"coordinates":[-96.949662,28.821665],"type":"Point"}
}