{
  "type": "Feature",
  "properties": {
    "iso:country":"US",
    "sg:address":"1317 E Quebec Ave",
    "sg:city":"Mcallen",
    "sg:classifiers":[
        {
            "category":"Professional",
            "subcategory":"Lawyer & Legal Services",
            "type":"Services"
        }
    ],
    "sg:phone":"+1 956 618 0115",
    "sg:postcode":"78503",
    "sg:province":"TX",
    "sg:tags":[
        "attorney"
    ],
    "wof:name":"Steven M Gonzalez & Assoc PC",
    "wof:placetype":"venue"
},
  "geometry": {"coordinates":[-98.20825499999999,26.184806],"type":"Point"}
}