{
  "type": "Feature",
  "properties": {
    "iso:country":"US",
    "sg:address":"2905 Belt Line Rd Ste A",
    "sg:city":"Garland",
    "sg:classifiers":[
        {
            "category":"Retail",
            "subcategory":"Laundry & Dry Cleaning",
            "type":"Services"
        }
    ],
    "sg:phone":"+1 972 414 3076",
    "sg:postcode":"75044",
    "sg:province":"TX",
    "wof:name":"Towngate Cleaners",
    "wof:placetype":"venue"
},
  "geometry": {"coordinates":[-96.6717,32.944801],"type":"Point"}
}