{
  "type": "Feature",
  "properties": {
    "iso:country":"US",
    "sg:address":"1004 Keller Pkwy",
    "sg:city":"Keller",
    "sg:classifiers":[
        {
            "category":"Health Services",
            "subcategory":"Optometrist",
            "type":"Services"
        }
    ],
    "sg:phone":"+1 817 431 3937",
    "sg:postcode":"76248",
    "sg:province":"TX",
    "wof:name":"Keller Eye Associates",
    "wof:placetype":"venue"
},
  "geometry": {"coordinates":[-97.2316,32.934288],"type":"Point"}
}