{
  "type": "Feature",
  "properties": {
    "iso:country":"US",
    "sg:address":"12002 Cypress North Houston Rd",
    "sg:city":"Cypress",
    "sg:classifiers":[
        {
            "category":"Retail",
            "subcategory":"Veterinary Services",
            "type":"Services"
        }
    ],
    "sg:phone":"+1 281 469 8056",
    "sg:postcode":"77429",
    "sg:province":"TX",
    "sg:tags":[
        "hospital",
        "animal"
    ],
    "wof:name":"Cypress Veterinary Hospital",
    "wof:placetype":"venue"
},
  "geometry": {"coordinates":[-95.60175599999999,29.952447],"type":"Point"}
}