{
  "type": "Feature",
  "properties": {
    "iso:country":"US",
    "sg:address":"101 W Southwest Pkwy",
    "sg:city":"Lewisville",
    "sg:classifiers":[
        {
            "category":"Restaurant",
            "type":"Food & Drink"
        }
    ],
    "sg:menulink":"http://www.allmenus.com/tx/lewisville/157302-whataburger/menu/",
    "sg:phone":"+1 972 434 2505",
    "sg:postcode":"75067",
    "sg:province":"TX",
    "sg:tags":[
        "burger",
        "american"
    ],
    "wof:name":"Whataburger",
    "wof:placetype":"venue"
},
  "geometry": {"coordinates":[-96.993089,33.019151],"type":"Point"}
}