{
  "type": "Feature",
  "properties": {
    "iso:country":"US",
    "sg:address":"830 FM 1960 W",
    "sg:city":"Houston",
    "sg:classifiers":[
        {
            "category":"Health Services",
            "subcategory":"Doctor",
            "type":"Services"
        }
    ],
    "sg:phone":"+1 281 580 3800",
    "sg:postcode":"77090",
    "sg:province":"TX",
    "sg:tags":[
        "clinic"
    ],
    "wof:name":"Houston Kidney Physician",
    "wof:placetype":"venue"
},
  "geometry": {"coordinates":[-95.441441,30.01749],"type":"Point"}
}