{
  "type": "Feature",
  "properties": {
    "iso:country":"US",
    "sg:address":"110 E FM 2410",
    "sg:city":"Harker Heights",
    "sg:classifiers":[
        {
            "category":"Health Services",
            "subcategory":"Health Practitioner",
            "type":"Services"
        }
    ],
    "sg:phone":"+1 254 699 7040",
    "sg:postcode":"76548",
    "sg:province":"TX",
    "wof:name":"Too Key West",
    "wof:placetype":"venue"
},
  "geometry": {"coordinates":[-97.67257499999999,31.073213],"type":"Point"}
}