{
  "type": "Feature",
  "properties": {
    "iso:country":"US",
    "sg:address":"408 E Walker St",
    "sg:city":"Decatur",
    "sg:classifiers":[
        {
            "category":"Recreation",
            "type":"Entertainment"
        },
        {
            "category":"Shopping",
            "subcategory":"Bicycles & Sporting Goods",
            "type":"Retail Goods"
        }
    ],
    "sg:phone":"+1 940 627 4748",
    "sg:postcode":"76234",
    "sg:province":"TX",
    "sg:tags":[
        "equipment",
        "arts",
        "supply",
        "martial"
    ],
    "wof:name":"Eastside Kenpo Karate Inc",
    "wof:placetype":"venue"
},
  "geometry": {"coordinates":[-97.58235000000001,33.22194],"type":"Point"}
}