{
  "type": "Feature",
  "properties": {
    "iso:country":"US",
    "sg:address":"908 S Staples St",
    "sg:city":"Corpus Christi",
    "sg:classifiers":[
        {
            "category":"Building & Trades",
            "subcategory":"Construction",
            "type":"Services"
        }
    ],
    "sg:phone":"+1 361 765 3425",
    "sg:postcode":"78404",
    "sg:province":"TX",
    "sg:tags":[
        "general",
        "contractor"
    ],
    "wof:name":"Emerald Bay Builders",
    "wof:placetype":"venue"
},
  "geometry": {"coordinates":[-97.401764,27.782462],"type":"Point"}
}