{
  "type": "Feature",
  "properties": {
    "iso:country":"US",
    "sg:address":"120 S Preston St",
    "sg:city":"Joaquin",
    "sg:classifiers":[
        {
            "category":"Banks & Credit Unions",
            "subcategory":"Bank",
            "type":"Services"
        }
    ],
    "sg:phone":"+1 936 269 3121",
    "sg:postcode":"75954",
    "sg:province":"TX",
    "sg:tags":[
        "saving",
        "commercial"
    ],
    "sg:website":"http://www.texasstatebank.com",
    "wof:name":"Texas State Bank",
    "wof:placetype":"venue"
},
  "geometry": {"coordinates":[-94.05471300000001,31.968552],"type":"Point"}
}