{
  "type": "Feature",
  "properties": {
    "iso:country":"US",
    "sg:address":"9610 Long Point Rd",
    "sg:city":"Houston",
    "sg:classifiers":[
        {
            "category":"Manufacturing",
            "subcategory":"Printing",
            "type":"Manufacturing & Wholesale Goods"
        }
    ],
    "sg:phone":"+1 713 827 0063",
    "sg:postcode":"77055",
    "sg:province":"TX",
    "sg:tags":[
        "print",
        "newspaper",
        "medium"
    ],
    "wof:name":"Korea World Inc the",
    "wof:placetype":"venue"
},
  "geometry": {"coordinates":[-95.529701,29.7962],"type":"Point"}
}