{
  "type": "Feature",
  "properties": {
    "iso:country":"US",
    "sg:address":"128 N 8th St",
    "sg:city":"Midlothian",
    "sg:classifiers":[
        {
            "category":"Professional",
            "type":"Services"
        },
        {
            "category":"Sports & Exercise",
            "subcategory":"Gym",
            "type":"Entertainment"
        }
    ],
    "sg:phone":"+1 972 775 6770",
    "sg:postcode":"76065",
    "sg:province":"TX",
    "sg:tags":[
        "club",
        "health",
        "studio",
        "gymnasium"
    ],
    "wof:name":"Figures & Physiques LLP",
    "wof:placetype":"venue"
},
  "geometry": {"coordinates":[-96.994433,32.482968],"type":"Point"}
}