{
  "type": "Feature",
  "properties": {
    "iso:country":"US",
    "sg:address":"6356 Singleton Blvd",
    "sg:city":"Dallas",
    "sg:classifiers":[
        {
            "category":"Retail",
            "subcategory":"Repair Shop",
            "type":"Services"
        }
    ],
    "sg:phone":"+1 214 630 6024",
    "sg:postcode":"75212",
    "sg:province":"TX",
    "sg:tags":[
        "equipment",
        "hydraulic"
    ],
    "wof:name":"USA Hydraulic Svc",
    "wof:placetype":"venue"
},
  "geometry": {"coordinates":[-96.92022299999999,32.778523],"type":"Point"}
}