{
  "type": "Feature",
  "properties": {
    "iso:country":"US",
    "sg:address":"104 W State Hwy 71",
    "sg:city":"Ellinger",
    "sg:classifiers":[
        {
            "category":"Farming",
            "subcategory":"Livestock Farm",
            "type":"Manufacturing & Wholesale Goods"
        }
    ],
    "sg:phone":"+1 979 378 2326",
    "sg:postcode":"78938",
    "sg:province":"TX",
    "sg:tags":[
        "beef",
        "feedlot",
        "cattle"
    ],
    "wof:name":"Jerome Cernoch",
    "wof:placetype":"venue"
},
  "geometry": {"coordinates":[-96.70952200000001,29.835585],"type":"Point"}
}