{
  "type": "Feature",
  "properties": {
    "iso:country":"US",
    "sg:address":"520 S Main St",
    "sg:city":"Grapevine",
    "sg:classifiers":[
        {
            "category":"Banks & Credit Unions",
            "subcategory":"Investment Brokerage",
            "type":"Services"
        }
    ],
    "sg:phone":"+1 817 421 2185",
    "sg:postcode":"76051",
    "sg:province":"TX",
    "sg:tags":[
        "security",
        "executive"
    ],
    "wof:name":"CMC Financial",
    "wof:placetype":"venue"
},
  "geometry": {"coordinates":[-97.07843200000001,32.935781],"type":"Point"}
}