{
  "type": "Feature",
  "properties": {
    "iso:country":"US",
    "sg:address":"3555 HIGHWAY 36 S",
    "sg:city":"ROSENBERG",
    "sg:classifiers":[
        {
            "category":"Travel",
            "subcategory":"Hotels & Motels",
            "type":"Entertainment"
        }
    ],
    "sg:phone":"+1 281 232 7300",
    "sg:postcode":"77471",
    "sg:province":"TX",
    "sg:tags":[
        "lodging"
    ],
    "sg:website":"http://www.comfortinn.com/hotel-rosenberg-texas-TX120",
    "wof:name":"Comfort Inn",
    "wof:placetype":"venue"
},
  "geometry": {"coordinates":[-95.8081,29.528304],"type":"Point"}
}