{
  "type": "Feature",
  "properties": {
    "iso:country":"US",
    "sg:address":"3113 S 10th St",
    "sg:city":"Mcallen",
    "sg:classifiers":[
        {
            "category":"Autos & Motor Vehicles",
            "subcategory":"Fuel & Gas Station",
            "type":"Retail Goods"
        }
    ],
    "sg:phone":"+1 956 682 3113",
    "sg:postcode":"78503",
    "sg:province":"TX",
    "sg:tags":[
        "grocery",
        "station",
        "gasoline"
    ],
    "wof:name":"Airport Valley Shamrock",
    "wof:placetype":"venue"
},
  "geometry": {"coordinates":[-98.230452,26.170362],"type":"Point"}
}