{
  "type": "Feature",
  "properties": {
    "iso:country":"US",
    "sg:address":"4656 Leston St",
    "sg:city":"Dallas",
    "sg:classifiers":[
        {
            "category":"Professional",
            "subcategory":"Business Services",
            "type":"Services"
        }
    ],
    "sg:phone":"+1 214 637 4330",
    "sg:postcode":"75247",
    "sg:province":"TX",
    "sg:tags":[
        "packaging"
    ],
    "wof:name":"Packing Of Dallas",
    "wof:placetype":"venue"
},
  "geometry": {"coordinates":[-96.893793,32.810594],"type":"Point"}
}