{
  "type": "Feature",
  "properties": {
    "iso:country":"US",
    "sg:address":"4 Rip Van Winkle Ln",
    "sg:city":"Houston",
    "sg:classifiers":[
        {
            "category":"Organizations",
            "subcategory":"Community Association",
            "type":"Services"
        }
    ],
    "sg:phone":"+1 713 935 9242",
    "sg:postcode":"77024",
    "sg:province":"TX",
    "wof:name":"Texas Eagles Baseball",
    "wof:placetype":"venue"
},
  "geometry": {"coordinates":[-95.53797299999999,29.767333],"type":"Point"}
}