{
  "type": "Feature",
  "properties": {
    "iso:country":"US",
    "sg:address":"720 N Post Oak Rd",
    "sg:city":"Houston",
    "sg:classifiers":[
        {
            "category":"Professional",
            "subcategory":"Lawyer & Legal Services",
            "type":"Services"
        }
    ],
    "sg:phone":"+1 713 686 5444",
    "sg:postcode":"77024",
    "sg:province":"TX",
    "wof:name":"James C Holland Jr Attorney At Law",
    "wof:placetype":"venue"
},
  "geometry": {"coordinates":[-95.456596,29.7796],"type":"Point"}
}