{
  "type": "Feature",
  "properties": {
    "iso:country":"US",
    "sg:address":"1845 Summit Ave",
    "sg:city":"Plano",
    "sg:classifiers":[
        {
            "category":"Manufacturing",
            "subcategory":"Printing",
            "type":"Manufacturing & Wholesale Goods"
        }
    ],
    "sg:phone":"+1 972 509 5707",
    "sg:postcode":"75074",
    "sg:province":"TX",
    "sg:tags":[
        "publishes",
        "book",
        "college",
        "guide",
        "sport"
    ],
    "sg:website":"www.thesportsource.com",
    "wof:name":"Sports Source",
    "wof:placetype":"venue"
},
  "geometry": {"coordinates":[-96.682829,33.009948],"type":"Point"}
}