{
  "type": "Feature",
  "properties": {
    "iso:country":"US",
    "sg:address":"2965 International Blvd",
    "sg:city":"Brownsville",
    "sg:classifiers":[
        {
            "category":"Autos & Motor Vehicles",
            "subcategory":"Auto Supplies",
            "type":"Retail Goods"
        }
    ],
    "sg:phone":"+1 956 574 9909",
    "sg:postcode":"78521",
    "sg:province":"TX",
    "sg:tags":[
        "tire"
    ],
    "wof:name":"International Tire & Wheel",
    "wof:placetype":"venue"
},
  "geometry": {"coordinates":[-97.47662,25.909419],"type":"Point"}
}