{
  "type": "Feature",
  "properties": {
    "iso:country":"US",
    "sg:address":"1700 McKinley Ave",
    "sg:city":"El Paso",
    "sg:classifiers":[
        {
            "category":"Recreation",
            "subcategory":"Amusement Park",
            "type":"Entertainment"
        }
    ],
    "sg:phone":"+1 915 562 9899",
    "sg:postcode":"79930",
    "sg:province":"TX",
    "sg:tags":[
        "park"
    ],
    "wof:name":"Wyler Aerial Tramway",
    "wof:placetype":"venue"
},
  "geometry": {"coordinates":[-106.476862,31.809613],"type":"Point"}
}