{
  "type": "Feature",
  "properties": {
    "iso:country":"US",
    "sg:address":"213 Lyndsey Dr",
    "sg:city":"Montgomery",
    "sg:classifiers":[
        {
            "category":"Manufacturing",
            "subcategory":"Food",
            "type":"Manufacturing & Wholesale Goods"
        }
    ],
    "sg:phone":"+1 936 447 6640",
    "sg:postcode":"77316",
    "sg:province":"TX",
    "sg:tags":[
        "canned",
        "mfg"
    ],
    "wof:name":"Lm Vending Inc",
    "wof:placetype":"venue"
},
  "geometry": {"coordinates":[-95.588134,30.307809],"type":"Point"}
}