{
  "type": "Feature",
  "properties": {
    "iso:country":"US",
    "sg:address":"602 E Church St",
    "sg:city":"Livingston",
    "sg:classifiers":[
        {
            "category":"Social Services",
            "type":"Services"
        }
    ],
    "sg:phone":"+1 936 327 6867",
    "sg:postcode":"77351",
    "sg:province":"TX",
    "sg:tags":[
        "organization",
        "welfare"
    ],
    "wof:name":"American Red Cross",
    "wof:placetype":"venue"
},
  "geometry": {"coordinates":[-94.928426,30.710974],"type":"Point"}
}