{
  "type": "Feature",
  "properties": {
    "iso:country":"US",
    "sg:address":"13810 Welch Rd",
    "sg:city":"Dallas",
    "sg:classifiers":[
        {
            "category":"Shopping",
            "subcategory":"Stationery & Office Supplies",
            "type":"Retail Goods"
        },
        {
            "category":"Home & Garden",
            "subcategory":"Furniture",
            "type":"Retail Goods"
        }
    ],
    "sg:phone":"+1 972 239 4946",
    "sg:postcode":"75244",
    "sg:province":"TX",
    "sg:tags":[
        "equipment",
        "store"
    ],
    "wof:name":"Freedom Furniture and Design",
    "wof:placetype":"venue"
},
  "geometry": {"coordinates":[-96.830399,32.9361],"type":"Point"}
}