{
  "type": "Feature",
  "properties": {
    "iso:country":"US",
    "sg:address":"4805 Neptune Ct",
    "sg:city":"Flower Mound",
    "sg:classifiers":[
        {
            "category":"Professional",
            "subcategory":"Management & Consulting",
            "type":"Services"
        }
    ],
    "sg:phone":"+1 972 874 9277",
    "sg:postcode":"75022",
    "sg:province":"TX",
    "wof:name":"G4 Management Ltd",
    "wof:placetype":"venue"
},
  "geometry": {"coordinates":[-97.10398600000001,33.014953],"type":"Point"}
}