{
  "type": "Feature",
  "properties": {
    "iso:country":"US",
    "sg:address":"865 C Rd",
    "sg:city":"La Vernia",
    "sg:classifiers":[
        {
            "category":"Freight",
            "type":"Transportation"
        }
    ],
    "sg:phone":"+1 830 253 1258",
    "sg:postcode":"78161",
    "sg:province":"TX",
    "sg:tags":[
        "operator",
        "local",
        "trucking"
    ],
    "wof:name":"Bellino Trucking",
    "wof:placetype":"venue"
},
  "geometry": {"coordinates":[-98.018525,29.313132],"type":"Point"}
}