{
  "type": "Feature",
  "properties": {
    "iso:country":"US",
    "sg:address":"200 N 26th St",
    "sg:city":"Mcallen",
    "sg:classifiers":[
        {
            "category":"Manufacturing",
            "subcategory":"Paper Products",
            "type":"Manufacturing & Wholesale Goods"
        }
    ],
    "sg:phone":"+1 956 682 9406",
    "sg:postcode":"78501",
    "sg:province":"TX",
    "sg:tags":[
        "box",
        "fiber",
        "mfg",
        "i",
        "paperboard",
        "mill"
    ],
    "wof:name":"Weyerhaeuser Company",
    "wof:placetype":"venue"
},
  "geometry": {"coordinates":[-98.25003,26.207793],"type":"Point"}
}