{
  "type": "Feature",
  "properties": {
    "iso:country":"US",
    "sg:address":"625 Yarbrough Dr",
    "sg:city":"El Paso",
    "sg:classifiers":[
        {
            "category":"Real Estate",
            "subcategory":"Real Estate Agent",
            "type":"Services"
        }
    ],
    "sg:phone":"+1 915 590 1515",
    "sg:postcode":"79915",
    "sg:province":"TX",
    "sg:tags":[
        "management"
    ],
    "wof:name":"Investment Builders",
    "wof:placetype":"venue"
},
  "geometry": {"coordinates":[-106.366733,31.71281],"type":"Point"}
}