{
  "type": "Feature",
  "properties": {
    "iso:country":"US",
    "sg:address":"1577 Wiggins Rd",
    "sg:city":"West",
    "sg:classifiers":[
        {
            "category":"Building & Trades",
            "subcategory":"Pest Control",
            "type":"Services"
        }
    ],
    "sg:phone":"+1 254 829 2244",
    "sg:postcode":"76691",
    "sg:province":"TX",
    "wof:name":"Texas Pest Control-West",
    "wof:placetype":"venue"
},
  "geometry": {"coordinates":[-97.119733,31.746585],"type":"Point"}
}