{
  "type": "Feature",
  "properties": {
    "iso:country":"US",
    "sg:address":"3240 Fondren Rd",
    "sg:city":"Houston",
    "sg:classifiers":[
        {
            "category":"Restaurant",
            "type":"Food & Drink"
        }
    ],
    "sg:phone":"+1 713 334 8999",
    "sg:postcode":"77063",
    "sg:province":"TX",
    "sg:tags":[
        "mexican"
    ],
    "wof:name":"Milas Taqueria Mexico",
    "wof:placetype":"venue"
},
  "geometry": {"coordinates":[-95.52059,29.729855],"type":"Point"}
}