{
  "type": "Feature",
  "properties": {
    "iso:country":"US",
    "sg:address":"105 Industrial Ct",
    "sg:city":"Kennedale",
    "sg:classifiers":[
        {
            "category":"Building & Trades",
            "subcategory":"Construction",
            "type":"Services"
        },
        {
            "category":"Professional",
            "subcategory":"Art Services",
            "type":"Services"
        },
        {
            "category":"Military Area",
            "subcategory":"Armory",
            "type":"Public Place"
        },
        {
            "category":"Manufacturing",
            "subcategory":"Building Materials",
            "type":"Manufacturing & Wholesale Goods"
        },
        {
            "category":"Sports & Exercise",
            "subcategory":"Swimming Pool",
            "type":"Entertainment"
        }
    ],
    "sg:phone":"+1 817 572 5949",
    "sg:postcode":"76060",
    "sg:province":"TX",
    "sg:tags":[
        "ornamental",
        "fence",
        "repair",
        "metal",
        "work",
        "cover",
        "contractor",
        "gate",
        "accessory",
        "enclosure",
        "fence-sales"
    ],
    "sg:website":"http://www.esterdayfence.com",
    "wof:name":"Esterday Fence",
    "wof:placetype":"venue"
},
  "geometry": {"coordinates":[-97.23083200000001,32.655712],"type":"Point"}
}