{
  "type": "Feature",
  "properties": {
    "iso:country":"US",
    "sg:address":"2608 Ross Ave",
    "sg:city":"Dallas",
    "sg:classifiers":[
        {
            "category":"Building & Trades",
            "subcategory":"Construction",
            "type":"Services"
        }
    ],
    "sg:phone":"+1 214 965 0888",
    "sg:postcode":"75201",
    "sg:province":"TX",
    "sg:tags":[
        "contractor"
    ],
    "sg:website":"www.jpiconstruction.com",
    "wof:name":"JPI Construction",
    "wof:placetype":"venue"
},
  "geometry": {"coordinates":[-96.794692,32.790583],"type":"Point"}
}