{
  "type": "Feature",
  "properties": {
    "iso:country":"US",
    "sg:address":"1315 E Hackberry Ave",
    "sg:city":"Mcallen",
    "sg:classifiers":[
        {
            "category":"Building & Trades",
            "subcategory":"Construction",
            "type":"Services"
        },
        {
            "category":"Home & Garden",
            "subcategory":"Carpets & Floor Coverings",
            "type":"Retail Goods"
        }
    ],
    "sg:phone":"+1 956 682 9655",
    "sg:postcode":"78501",
    "sg:province":"TX",
    "sg:tags":[
        "contractor",
        "dealer",
        "rug"
    ],
    "wof:name":"South Padre Tile Carpet & Pain",
    "wof:placetype":"venue"
},
  "geometry": {"coordinates":[-98.20431600000001,26.207643],"type":"Point"}
}