{
  "type": "Feature",
  "properties": {
    "iso:country":"US",
    "sg:address":"2511 W 45th St",
    "sg:city":"Austin",
    "sg:classifiers":[
        {
            "category":"Building & Trades",
            "subcategory":"Construction",
            "type":"Services"
        }
    ],
    "sg:phone":"+1 512 917 5691",
    "sg:postcode":"78756",
    "sg:province":"TX",
    "sg:tags":[
        "house"
    ],
    "wof:name":"Derek Brooks Construction",
    "wof:placetype":"venue"
},
  "geometry": {"coordinates":[-97.748031,30.318346],"type":"Point"}
}