{
  "type": "Feature",
  "properties": {
    "iso:country":"US",
    "sg:address":"1656 Dowelling Ct",
    "sg:city":"Frisco",
    "sg:classifiers":[
        {
            "category":"Building & Trades",
            "subcategory":"Construction",
            "type":"Services"
        }
    ],
    "sg:phone":"+1 972 668 3820",
    "sg:postcode":"75034",
    "sg:province":"TX",
    "sg:tags":[
        "house"
    ],
    "wof:name":"Woodmount Construction & Dev",
    "wof:placetype":"venue"
},
  "geometry": {"coordinates":[-96.87734500000001,33.150722],"type":"Point"}
}