{
  "type": "Feature",
  "properties": {
    "iso:country":"US",
    "sg:address":"4400 E Lancaster Ave",
    "sg:city":"Fort Worth",
    "sg:classifiers":[
        {
            "category":"Retail",
            "subcategory":"Self-service Laundry",
            "type":"Services"
        }
    ],
    "sg:phone":"+1 817 535 9774",
    "sg:postcode":"76103",
    "sg:province":"TX",
    "sg:tags":[
        "coin"
    ],
    "wof:name":"3 D Wash World",
    "wof:placetype":"venue"
},
  "geometry": {"coordinates":[-97.25609799999999,32.740927],"type":"Point"}
}