{
  "type": "Feature",
  "properties": {
    "iso:country":"US",
    "sg:address":"318 N Main St",
    "sg:city":"Winnsboro",
    "sg:classifiers":[
        {
            "category":"Organizations",
            "subcategory":"Membership Organization",
            "type":"Services"
        }
    ],
    "sg:phone":"+1 903 342 1106",
    "sg:postcode":"75494",
    "sg:province":"TX",
    "wof:name":"Winnsboro Living At Home",
    "wof:placetype":"venue"
},
  "geometry": {"coordinates":[-95.289698,32.959079],"type":"Point"}
}