{
  "type": "Feature",
  "properties": {
    "iso:country":"US",
    "sg:address":"1929 Marvin Cir",
    "sg:city":"Seabrook",
    "sg:classifiers":[
        {
            "category":"Manufacturing",
            "subcategory":"Chemicals & Compounds",
            "type":"Manufacturing & Wholesale Goods"
        }
    ],
    "sg:phone":"+1 281 474 9777",
    "sg:postcode":"77586",
    "sg:province":"TX",
    "sg:website":"www.kiwo.com",
    "wof:name":"Kiwo Inc",
    "wof:placetype":"venue"
},
  "geometry": {"coordinates":[-95.02624900000001,29.574409],"type":"Point"}
}