{
  "type": "Feature",
  "properties": {
    "iso:country":"US",
    "sg:address":"120 Porter St",
    "sg:city":"Taylor",
    "sg:classifiers":[
        {
            "category":"Retail",
            "subcategory":"Laundry & Dry Cleaning",
            "type":"Services"
        }
    ],
    "sg:phone":"+1 512 352 2501",
    "sg:postcode":"76574",
    "sg:province":"TX",
    "wof:name":"Lone Star Linen",
    "wof:placetype":"venue"
},
  "geometry": {"coordinates":[-97.40825599999999,30.568583],"type":"Point"}
}