{
  "type": "Feature",
  "properties": {
    "iso:country":"US",
    "sg:address":"2135 Oak Bend Dr",
    "sg:city":"San Antonio",
    "sg:classifiers":[
        {
            "category":"Professional",
            "subcategory":"Management & Consulting",
            "type":"Services"
        }
    ],
    "sg:phone":"+1 210 481 0283",
    "sg:postcode":"78259",
    "sg:province":"TX",
    "wof:name":"G&L McGuire Management Service",
    "wof:placetype":"venue"
},
  "geometry": {"coordinates":[-98.446904,29.632231],"type":"Point"}
}