{
  "type": "Feature",
  "properties": {
    "iso:country":"US",
    "sg:address":"13707 Oleoke Ln",
    "sg:city":"Houston",
    "sg:classifiers":[
        {
            "category":"Banks & Credit Unions",
            "subcategory":"Financial Services",
            "type":"Services"
        }
    ],
    "sg:phone":"+1 713 451 2991",
    "sg:postcode":"77015",
    "sg:province":"TX",
    "sg:tags":[
        "investment",
        "real estate"
    ],
    "wof:name":"Gaylords Investments",
    "wof:placetype":"venue"
},
  "geometry": {"coordinates":[-95.17956,29.802219],"type":"Point"}
}