{
  "type": "Feature",
  "properties": {
    "iso:country":"US",
    "sg:address":"903 Sam Houston Dr",
    "sg:city":"Victoria",
    "sg:classifiers":[
        {
            "category":"Insurance",
            "subcategory":"Hazard Insurance",
            "type":"Services"
        }
    ],
    "sg:phone":"+1 361 578 7171",
    "sg:postcode":"77901",
    "sg:province":"TX",
    "sg:tags":[
        "carrier"
    ],
    "wof:name":"State Farm Insurance",
    "wof:placetype":"venue"
},
  "geometry": {"coordinates":[-96.97380699999999,28.822063],"type":"Point"}
}