{
  "type": "Feature",
  "properties": {
    "iso:country":"US",
    "sg:address":"3201 Houston Hwy",
    "sg:city":"Victoria",
    "sg:classifiers":[
        {
            "category":"Autos & Motor Vehicles",
            "subcategory":"Automobile Sales",
            "type":"Retail Goods"
        }
    ],
    "sg:phone":"+1 361 576 1531",
    "sg:postcode":"77901",
    "sg:province":"TX",
    "sg:tags":[
        "car",
        "used",
        "dealer",
        "supply"
    ],
    "wof:name":"A 1 Used Cars",
    "wof:placetype":"venue"
},
  "geometry": {"coordinates":[-96.96894399999999,28.81439],"type":"Point"}
}