{
  "type": "Feature",
  "properties": {
    "iso:country":"US",
    "sg:address":"1909 Capri Ln",
    "sg:city":"Seabrook",
    "sg:classifiers":[
        {
            "category":"Insurance",
            "subcategory":"Insurance Agent",
            "type":"Services"
        }
    ],
    "sg:phone":"+1 281 474 7558",
    "sg:postcode":"77586",
    "sg:province":"TX",
    "wof:name":"Ellis Floyd Insurance Storm",
    "wof:placetype":"venue"
},
  "geometry": {"coordinates":[-95.024627,29.568415],"type":"Point"}
}