{
  "type": "Feature",
  "properties": {
    "iso:country":"US",
    "sg:address":"3707 Highgate Ln",
    "sg:city":"Carrollton",
    "sg:classifiers":[
        {
            "category":"Wholesale",
            "subcategory":"Stationery",
            "type":"Manufacturing & Wholesale Goods"
        }
    ],
    "sg:phone":"+1 972 394 8781",
    "sg:postcode":"75007",
    "sg:province":"TX",
    "sg:tags":[
        "cards",
        "greeting"
    ],
    "wof:name":"Carmel's Cards",
    "wof:placetype":"venue"
},
  "geometry": {"coordinates":[-96.885159,33.0126],"type":"Point"}
}