{
  "type": "Feature",
  "properties": {
    "iso:country":"US",
    "sg:address":"5201 Richmond Ave Ste G",
    "sg:city":"Houston",
    "sg:classifiers":[
        {
            "category":"Personal",
            "subcategory":"Nail Salon",
            "type":"Services"
        }
    ],
    "sg:phone":"+1 713 627 8838",
    "sg:postcode":"77056",
    "sg:province":"TX",
    "wof:name":"Classic Nails",
    "wof:placetype":"venue"
},
  "geometry": {"coordinates":[-95.46669799999999,29.731501],"type":"Point"}
}