{
  "type": "Feature",
  "properties": {
    "iso:country":"US",
    "sg:address":"124 E Slaton Rd",
    "sg:city":"Lubbock",
    "sg:classifiers":[
        {
            "category":"Autos & Motor Vehicles",
            "subcategory":"Auto Supplies",
            "type":"Retail Goods"
        }
    ],
    "sg:phone":"+1 806 745 2052",
    "sg:postcode":"79404",
    "sg:province":"TX",
    "sg:tags":[
        "accessories-wholesale",
        "automobile",
        "part",
        "parts",
        "manufacturer"
    ],
    "wof:name":"Bristo Battery & Supply Inc",
    "wof:placetype":"venue"
},
  "geometry": {"coordinates":[-101.83345799999999,33.533991],"type":"Point"}
}