{
  "type": "Feature",
  "properties": {
    "iso:country":"US",
    "sg:address":"1001 S Main St",
    "sg:city":"Boerne",
    "sg:classifiers":[
        {
            "category":"Real Estate",
            "subcategory":"Surveying",
            "type":"Services"
        }
    ],
    "sg:phone":"+1 830 249 3385",
    "sg:postcode":"78006",
    "sg:province":"TX",
    "sg:tags":[
        "surveyor"
    ],
    "wof:name":"Thomas C Pfeiffer Land Srvyng",
    "wof:placetype":"venue"
},
  "geometry": {"coordinates":[-98.72902999999999,29.784457],"type":"Point"}
}