{
  "type": "Feature",
  "properties": {
    "iso:country":"US",
    "sg:address":"4416 Twin City Blvd",
    "sg:city":"Belton",
    "sg:classifiers":[
        {
            "category":"Insurance",
            "subcategory":"Insurance Agent",
            "type":"Services"
        }
    ],
    "sg:phone":"+1 254 939 4100",
    "sg:postcode":"76502",
    "sg:province":"TX",
    "wof:name":"State Farm Insurance",
    "wof:placetype":"venue"
},
  "geometry": {"coordinates":[-97.423804,31.072928],"type":"Point"}
}