{
  "type": "Feature",
  "properties": {
    "iso:country":"US",
    "sg:address":"4425 FM 236",
    "sg:city":"Victoria",
    "sg:classifiers":[
        {
            "category":"Shopping",
            "type":"Retail Goods"
        }
    ],
    "sg:phone":"+1 361 579 9395",
    "sg:postcode":"77905",
    "sg:province":"TX",
    "sg:tags":[
        "merchandise"
    ],
    "wof:name":"Angel Memorial Etc",
    "wof:placetype":"venue"
},
  "geometry": {"coordinates":[-97.103634,28.825532],"type":"Point"}
}