{
  "type": "Feature",
  "properties": {
    "iso:country":"US",
    "sg:address":"112 E Jones St",
    "sg:city":"Dimmitt",
    "sg:classifiers":[
        {
            "category":"Health Services",
            "subcategory":"Clinic",
            "type":"Services"
        }
    ],
    "sg:phone":"+1 806 647 1187",
    "sg:postcode":"79027",
    "sg:province":"TX",
    "sg:tags":[
        "alternative",
        "care"
    ],
    "wof:name":"Covenant Family Healthcare C",
    "wof:placetype":"venue"
},
  "geometry": {"coordinates":[-102.31232799999999,34.549732],"type":"Point"}
}