{
  "type": "Feature",
  "properties": {
    "iso:country":"US",
    "sg:address":"250 S Collins Rd",
    "sg:city":"Sunnyvale",
    "sg:classifiers":[
        {
            "category":"Retail",
            "subcategory":"Auto Repair",
            "type":"Services"
        }
    ],
    "sg:phone":"+1 972 203 3599",
    "sg:postcode":"75182",
    "sg:province":"TX",
    "sg:website":"www.ateamautomotive.com",
    "wof:name":"A-Team Automotive Repair",
    "wof:placetype":"venue"
},
  "geometry": {"coordinates":[-96.56873899999999,32.775729],"type":"Point"}
}