{
  "type": "Feature",
  "properties": {
    "iso:country":"US",
    "sg:address":"4316 Murray Ave",
    "sg:city":"Fort Worth",
    "sg:classifiers":[
        {
            "category":"Wholesale",
            "subcategory":"Chemicals & Plastics",
            "type":"Manufacturing & Wholesale Goods"
        }
    ],
    "sg:phone":"+1 817 577 0633",
    "sg:postcode":"76117",
    "sg:province":"TX",
    "sg:tags":[
        "industrial"
    ],
    "wof:name":"Kase Products",
    "wof:placetype":"venue"
},
  "geometry": {"coordinates":[-97.27952000000001,32.82781],"type":"Point"}
}