{
  "type": "Feature",
  "properties": {
    "iso:country":"US",
    "sg:address":"11403 Hall Rd",
    "sg:city":"Houston",
    "sg:classifiers":[
        {
            "category":"Shopping",
            "subcategory":"Clothing, Apparel, & Fashions",
            "type":"Retail Goods"
        }
    ],
    "sg:phone":"+1 281 464 8500",
    "sg:postcode":"77089",
    "sg:province":"TX",
    "sg:tags":[
        "children's",
        "clothing"
    ],
    "wof:name":"Kids Corner",
    "wof:placetype":"venue"
},
  "geometry": {"coordinates":[-95.228464,29.596177],"type":"Point"}
}