{
  "type": "Feature",
  "properties": {
    "iso:country":"US",
    "sg:address":"12 Westridge Sq",
    "sg:city":"Plainview",
    "sg:classifiers":[
        {
            "category":"Health Services",
            "subcategory":"Doctor",
            "type":"Services"
        }
    ],
    "sg:phone":"+1 806 293 0444",
    "sg:postcode":"79072",
    "sg:province":"TX",
    "sg:tags":[
        "dentist"
    ],
    "wof:name":"Crawford Felix C DDS Inc",
    "wof:placetype":"venue"
},
  "geometry": {"coordinates":[-101.754096,34.17731],"type":"Point"}
}