{
  "type": "Feature",
  "properties": {
    "iso:country":"US",
    "sg:address":"4535 Old Jacksonville Hwy",
    "sg:city":"Tyler",
    "sg:classifiers":[
        {
            "category":"Home & Garden",
            "subcategory":"Garden Supply",
            "type":"Retail Goods"
        }
    ],
    "sg:phone":"+1 903 939 9200",
    "sg:postcode":"75703",
    "sg:province":"TX",
    "sg:tags":[
        "lawn",
        "mower"
    ],
    "wof:name":"Cutter Equipment",
    "wof:placetype":"venue"
},
  "geometry": {"coordinates":[-95.32308399999999,32.30124],"type":"Point"}
}