{
  "type": "Feature",
  "properties": {
    "iso:country":"US",
    "sg:address":"15902 Palo Seco Dr",
    "sg:city":"Corpus Christi",
    "sg:classifiers":[
        {
            "category":"Professional",
            "subcategory":"Business Services",
            "type":"Services"
        }
    ],
    "sg:phone":"+1 361 949 6849",
    "sg:postcode":"78418",
    "sg:province":"TX",
    "sg:tags":[
        "plant",
        "design",
        "maintenance"
    ],
    "wof:name":"Green Things",
    "wof:placetype":"venue"
},
  "geometry": {"coordinates":[-97.230666,27.585416],"type":"Point"}
}