{
  "type": "Feature",
  "properties": {
    "iso:country":"US",
    "sg:address":"121 Ava Dr",
    "sg:city":"Hewitt",
    "sg:classifiers":[
        {
            "category":"Wholesale",
            "subcategory":"Apparel",
            "type":"Manufacturing & Wholesale Goods"
        }
    ],
    "sg:phone":"+1 254 666 1001",
    "sg:postcode":"76643",
    "sg:province":"TX",
    "sg:tags":[
        "curtain",
        "fabric",
        "drapery"
    ],
    "sg:website":"www.creativefabrics.com",
    "wof:name":"Creative Fabrics Inc",
    "wof:placetype":"venue"
},
  "geometry": {"coordinates":[-97.198241,31.478141],"type":"Point"}
}