{
  "type": "Feature",
  "properties": {
    "iso:country":"US",
    "sg:address":"806 13th St",
    "sg:city":"Bridgeport",
    "sg:classifiers":[
        {
            "category":"Shopping",
            "subcategory":"Discount & Variety Stores",
            "type":"Retail Goods"
        }
    ],
    "sg:phone":"+1 940 683 3105",
    "sg:postcode":"76426",
    "sg:province":"TX",
    "sg:tags":[
        "merchandise",
        "general"
    ],
    "wof:name":"Dry Creek Store",
    "wof:placetype":"venue"
},
  "geometry": {"coordinates":[-97.75447800000001,33.206143],"type":"Point"}
}