{
  "type": "Feature",
  "properties": {
    "iso:country":"US",
    "sg:address":"4527 Birchman Ave",
    "sg:city":"Fort Worth",
    "sg:classifiers":[
        {
            "category":"Professional",
            "type":"Services"
        }
    ],
    "sg:phone":"+1 817 735 9851",
    "sg:postcode":"76107",
    "sg:province":"TX",
    "wof:name":"Amy L Turlington",
    "wof:placetype":"venue"
},
  "geometry": {"coordinates":[-97.387411,32.734717],"type":"Point"}
}