{
  "type": "Feature",
  "properties": {
    "iso:country":"US",
    "sg:address":"600 N Main St",
    "sg:city":"Taylor",
    "sg:classifiers":[
        {
            "category":"Food & Beverages",
            "subcategory":"Groceries & Convenience Stores",
            "type":"Retail Goods"
        }
    ],
    "sg:phone":"+1 512 365 7964",
    "sg:postcode":"76574",
    "sg:province":"TX",
    "wof:name":"Power Mart",
    "wof:placetype":"venue"
},
  "geometry": {"coordinates":[-97.409983,30.573493],"type":"Point"}
}