{
  "type": "Feature",
  "properties": {
    "iso:country":"US",
    "sg:address":"8706 Emmott Rd",
    "sg:city":"Houston",
    "sg:classifiers":[
        {
            "category":"Professional",
            "type":"Services"
        }
    ],
    "sg:phone":"+1 713 937 4932",
    "sg:postcode":"77040",
    "sg:province":"TX",
    "wof:name":"Ocean Corporate Services Inc",
    "wof:placetype":"venue"
},
  "geometry": {"coordinates":[-95.52923,29.873921],"type":"Point"}
}