{
  "type": "Feature",
  "properties": {
    "iso:country":"US",
    "sg:address":"311 Center Ave",
    "sg:city":"Brownwood",
    "sg:classifiers":[
        {
            "category":"Professional",
            "subcategory":"Accounting & Tax Preparation",
            "type":"Services"
        }
    ],
    "sg:phone":"+1 325 646 8838",
    "sg:postcode":"76801",
    "sg:province":"TX",
    "sg:tags":[
        "accountant"
    ],
    "wof:name":"Burl D Lowery CPA",
    "wof:placetype":"venue"
},
  "geometry": {"coordinates":[-98.982049,31.720881],"type":"Point"}
}