{
  "type": "Feature",
  "properties": {
    "iso:country":"US",
    "sg:address":"3218 S Glenbrook Dr",
    "sg:city":"Garland",
    "sg:classifiers":[
        {
            "category":"Farming",
            "subcategory":"Livestock Farm",
            "type":"Manufacturing & Wholesale Goods"
        }
    ],
    "sg:phone":"+1 972 271 1742",
    "sg:postcode":"75041",
    "sg:province":"TX",
    "sg:tags":[
        "beef",
        "feedlot",
        "cattle"
    ],
    "wof:name":"Richards Brangus",
    "wof:placetype":"venue"
},
  "geometry": {"coordinates":[-96.63856699999999,32.877475],"type":"Point"}
}