{
  "type": "Feature",
  "properties": {
    "iso:country":"US",
    "sg:address":"1815 Shearn St",
    "sg:city":"Houston",
    "sg:classifiers":[
        {
            "category":"Manufacturing",
            "subcategory":"Tools & Machinery",
            "type":"Manufacturing & Wholesale Goods"
        }
    ],
    "sg:phone":"+1 713 869 5771",
    "sg:postcode":"77007",
    "sg:province":"TX",
    "sg:tags":[
        "oil",
        "gas"
    ],
    "sg:website":"www.halliburton.com",
    "wof:name":"Halliburton Energy Svc",
    "wof:placetype":"venue"
},
  "geometry": {"coordinates":[-95.376884,29.774367],"type":"Point"}
}