{
  "type": "Feature",
  "properties": {
    "iso:country":"US",
    "sg:address":"42823 Old Houston Hwy",
    "sg:city":"Waller",
    "sg:classifiers":[
        {
            "category":"Wholesale",
            "subcategory":"Fruits & Vegetables",
            "type":"Manufacturing & Wholesale Goods"
        }
    ],
    "sg:phone":"+1 936 372 2121",
    "sg:postcode":"77484",
    "sg:province":"TX",
    "sg:tags":[
        "shipper"
    ],
    "wof:name":"Texas Orchards Inc",
    "wof:placetype":"venue"
},
  "geometry": {"coordinates":[-95.96816699999999,30.066112],"type":"Point"}
}