{
  "type": "Feature",
  "properties": {
    "iso:country":"US",
    "sg:address":"205 Lakeshore Dr",
    "sg:city":"Port Arthur",
    "sg:classifiers":[
        {
            "category":"Manufacturing",
            "subcategory":"Chemicals & Compounds",
            "type":"Manufacturing & Wholesale Goods"
        }
    ],
    "sg:phone":"+1 409 983 7800",
    "sg:postcode":"77640",
    "sg:province":"TX",
    "sg:tags":[
        "preparation",
        "mfg",
        "plastic"
    ],
    "wof:name":"Spill Textile Corporation",
    "wof:placetype":"venue"
},
  "geometry": {"coordinates":[-93.934963,29.867258],"type":"Point"}
}