{
  "type": "Feature",
  "properties": {
    "iso:country":"US",
    "sg:address":"5717 Christy Ln",
    "sg:city":"Fort Worth",
    "sg:classifiers":[
        {
            "category":"Building & Trades",
            "subcategory":"Equipment Rental",
            "type":"Services"
        }
    ],
    "sg:phone":"+1 817 281 5648",
    "sg:postcode":"76137",
    "sg:province":"TX",
    "sg:tags":[
        "party",
        "supply"
    ],
    "wof:name":"Starwalk Moonwalk Rental & Sls",
    "wof:placetype":"venue"
},
  "geometry": {"coordinates":[-97.28943099999999,32.851459],"type":"Point"}
}