{
  "type": "Feature",
  "properties": {
    "iso:country":"US",
    "sg:address":"2010 Cartwright St",
    "sg:city":"Dallas",
    "sg:classifiers":[
        {
            "category":"Retail",
            "subcategory":"Repair Shop",
            "type":"Services"
        }
    ],
    "sg:phone":"+1 214 905 1580",
    "sg:postcode":"75212",
    "sg:province":"TX",
    "sg:tags":[
        "grease",
        "trap"
    ],
    "wof:name":"Dal-Worth Industries Inc",
    "wof:placetype":"venue"
},
  "geometry": {"coordinates":[-96.919174,32.770538],"type":"Point"}
}