{
  "type": "Feature",
  "properties": {
    "iso:country":"US",
    "sg:address":"26760 Brentwood Rd",
    "sg:city":"Splendora",
    "sg:classifiers":[
        {
            "category":"Professional",
            "type":"Services"
        }
    ],
    "sg:phone":"+1 281 689 3050",
    "sg:postcode":"77372",
    "sg:province":"TX",
    "wof:name":"Sherry Fulk",
    "wof:placetype":"venue"
},
  "geometry": {"coordinates":[-95.14074599999999,30.217565],"type":"Point"}
}