{
  "type": "Feature",
  "properties": {
    "iso:country":"US",
    "sg:address":"410 S Market St",
    "sg:city":"Hearne",
    "sg:classifiers":[
        {
            "category":"Autos & Motor Vehicles",
            "subcategory":"Fuel & Gas Station",
            "type":"Retail Goods"
        }
    ],
    "sg:phone":"+1 979 279 3852",
    "sg:postcode":"77859",
    "sg:province":"TX",
    "sg:tags":[
        "oil"
    ],
    "wof:name":"Shell",
    "wof:placetype":"venue"
},
  "geometry": {"coordinates":[-96.594311,30.880136],"type":"Point"}
}