{
  "type": "Feature",
  "properties": {
    "iso:country":"US",
    "sg:address":"5510 N Cage Blvd",
    "sg:city":"Pharr",
    "sg:classifiers":[
        {
            "category":"Social Services",
            "subcategory":"Adult Care",
            "type":"Services"
        }
    ],
    "sg:phone":"+1 956 782 9009",
    "sg:postcode":"78577",
    "sg:province":"TX",
    "sg:tags":[
        "centers-adult",
        "day"
    ],
    "wof:name":"Mi Gente Adult Day Care Inc",
    "wof:placetype":"venue"
},
  "geometry": {"coordinates":[-98.17662900000001,26.243266],"type":"Point"}
}