{
  "type": "Feature",
  "properties": {
    "iso:country":"US",
    "sg:address":"13635 Michel Rd",
    "sg:city":"Tomball",
    "sg:classifiers":[
        {
            "category":"Health Services",
            "subcategory":"Hospital",
            "type":"Services"
        }
    ],
    "sg:phone":"+1 281 351 7261",
    "sg:postcode":"77375",
    "sg:province":"TX",
    "sg:tags":[
        "specialty"
    ],
    "wof:name":"Sports Medicine Center",
    "wof:placetype":"venue"
},
  "geometry": {"coordinates":[-95.627746,30.082386],"type":"Point"}
}