{
  "type": "Feature",
  "properties": {
    "iso:country":"US",
    "sg:address":"3646 Willowwood Blvd",
    "sg:city":"San Antonio",
    "sg:classifiers":[
        {
            "category":"Shopping",
            "subcategory":"Beauty & Cosmetics",
            "type":"Retail Goods"
        }
    ],
    "sg:phone":"+1 210 224 7169",
    "sg:postcode":"78219",
    "sg:province":"TX",
    "sg:tags":[
        "merchandise"
    ],
    "wof:name":"Fashion Two Twenty Cosmetics",
    "wof:placetype":"venue"
},
  "geometry": {"coordinates":[-98.428302,29.442862],"type":"Point"}
}