{
  "type": "Feature",
  "properties": {
    "iso:country":"US",
    "sg:address":"24210 Royalwick Dr",
    "sg:city":"Tomball",
    "sg:classifiers":[
        {
            "category":"Shopping",
            "subcategory":"Catalog Store",
            "type":"Retail Goods"
        }
    ],
    "sg:phone":"+1 281 351 8766",
    "sg:postcode":"77375",
    "sg:province":"TX",
    "sg:tags":[
        "mail",
        "house"
    ],
    "wof:name":"Abccybermallcom",
    "wof:placetype":"venue"
},
  "geometry": {"coordinates":[-95.558582,30.11328],"type":"Point"}
}