{
  "type": "Feature",
  "properties": {
    "iso:country":"US",
    "sg:address":"8918 Inwood North Dr",
    "sg:city":"Houston",
    "sg:classifiers":[
        {
            "category":"Banks & Credit Unions",
            "subcategory":"Financial Services",
            "type":"Services"
        }
    ],
    "sg:phone":"+1 281 820 5702",
    "sg:postcode":"77088",
    "sg:province":"TX",
    "sg:tags":[
        "company",
        "holding"
    ],
    "wof:name":"B&A Venture Holding Inc",
    "wof:placetype":"venue"
},
  "geometry": {"coordinates":[-95.488429,29.895344],"type":"Point"}
}