{
  "type": "Feature",
  "properties": {
    "iso:country":"US",
    "sg:address":"7575 S Westmoreland Rd",
    "sg:city":"Dallas",
    "sg:classifiers":[
        {
            "category":"Real Estate",
            "subcategory":"Real Estate Operator",
            "type":"Services"
        }
    ],
    "sg:phone":"+1 972 298 7265",
    "sg:postcode":"75237",
    "sg:province":"TX",
    "sg:tags":[
        "building",
        "apartment"
    ],
    "wof:name":"Park Village",
    "wof:placetype":"venue"
},
  "geometry": {"coordinates":[-96.884311,32.656887],"type":"Point"}
}