{
  "type": "Feature",
  "properties": {
    "iso:country":"US",
    "sg:address":"602 Pine St",
    "sg:city":"Texarkana",
    "sg:classifiers":[
        {
            "category":"Professional",
            "subcategory":"Lawyer & Legal Services",
            "type":"Services"
        }
    ],
    "sg:phone":"+1 903 792 1608",
    "sg:postcode":"75501",
    "sg:province":"TX",
    "sg:tags":[
        "divorce",
        "assistance",
        "law",
        "attorney",
        "business"
    ],
    "sg:website":"http://www.alwinsmith.com",
    "wof:name":"Alwin A Smith Attorney At Law",
    "wof:placetype":"venue"
},
  "geometry": {"coordinates":[-94.045208,33.425172],"type":"Point"}
}