{
  "type": "Feature",
  "properties": {
    "iso:country":"US",
    "sg:address":"1700 Galveston Ave",
    "sg:city":"Fort Worth",
    "sg:classifiers":[
        {
            "category":"Food & Beverages",
            "subcategory":"Groceries & Convenience Stores",
            "type":"Retail Goods"
        }
    ],
    "sg:phone":"+1 817 924 8069",
    "sg:postcode":"76110",
    "sg:province":"TX",
    "wof:name":"Mr T Food Store",
    "wof:placetype":"venue"
},
  "geometry": {"coordinates":[-97.32727300000001,32.724829],"type":"Point"}
}