{
  "type": "Feature",
  "properties": {
    "iso:country":"US",
    "sg:address":"3920 W Cardinal Dr",
    "sg:city":"Beaumont",
    "sg:classifiers":[
        {
            "category":"Social Services",
            "type":"Services"
        }
    ],
    "sg:phone":"+1 409 659 5937",
    "sg:postcode":"77705",
    "sg:province":"TX",
    "wof:name":"Jehovah Jireh Village Community Development Center",
    "wof:placetype":"venue"
},
  "geometry": {"coordinates":[-94.133415,30.042541],"type":"Point"}
}