{
  "type": "Feature",
  "properties": {
    "iso:country":"US",
    "sg:address":"405 S Washington St",
    "sg:city":"Seymour",
    "sg:classifiers":[
        {
            "category":"Travel",
            "subcategory":"Hotels & Motels",
            "type":"Entertainment"
        }
    ],
    "sg:phone":"+1 940 888 8413",
    "sg:postcode":"76380",
    "sg:province":"TX",
    "wof:name":"Seymour Lodge",
    "wof:placetype":"venue"
},
  "geometry": {"coordinates":[-99.261499,33.584657],"type":"Point"}
}