{
  "type": "Feature",
  "properties": {
    "iso:country":"US",
    "sg:address":"2570 Southwell Rd",
    "sg:city":"Dallas",
    "sg:classifiers":[
        {
            "category":"Arts & Performance",
            "subcategory":"Theater",
            "type":"Entertainment"
        }
    ],
    "sg:phone":"+1 972 247 8981",
    "sg:postcode":"75229",
    "sg:province":"TX",
    "sg:tags":[
        "theatrical"
    ],
    "wof:name":"Future Stars",
    "wof:placetype":"venue"
},
  "geometry": {"coordinates":[-96.891661,32.886274],"type":"Point"}
}