{
  "type": "Feature",
  "properties": {
    "iso:country":"US",
    "sg:address":"8102 Shady Brook Ln",
    "sg:city":"Celina",
    "sg:classifiers":[
        {
            "category":"Retail",
            "subcategory":"Animal Services",
            "type":"Services"
        }
    ],
    "sg:phone":"+1 972 712 2515",
    "sg:postcode":"75009",
    "sg:province":"TX",
    "sg:tags":[
        "pet",
        "training",
        "specialty"
    ],
    "wof:name":"North Texas Hunting Retrievers",
    "wof:placetype":"venue"
},
  "geometry": {"coordinates":[-96.694293,33.336193],"type":"Point"}
}