{
  "type": "Feature",
  "properties": {
    "iso:country":"US",
    "sg:address":"261 S Highway 67",
    "sg:city":"Cedar Hill",
    "sg:classifiers":[
        {
            "category":"Restaurant",
            "type":"Food & Drink"
        }
    ],
    "sg:phone":"+1 972 291 2636",
    "sg:postcode":"75104",
    "sg:province":"TX",
    "wof:name":"Burgers & More Cafe 67",
    "wof:placetype":"venue"
},
  "geometry": {"coordinates":[-96.949997,32.586601],"type":"Point"}
}