{
  "type": "Feature",
  "properties": {
    "iso:country":"US",
    "sg:address":"1776 Yorktown Suite 570",
    "sg:city":"Houston",
    "sg:classifiers":[
        {
            "category":"Professional",
            "subcategory":"Lawyer & Legal Services",
            "type":"Services"
        }
    ],
    "sg:phone":"+1 713 888 0811",
    "sg:postcode":"77056",
    "sg:province":"TX",
    "sg:website":"www.ilaganlaw.com",
    "wof:name":"Ilagan & Associates, P.c.",
    "wof:placetype":"venue"
},
  "geometry": {"coordinates":[-95.471515,29.747497],"type":"Point"}
}