{
  "type": "Feature",
  "properties": {
    "iso:country":"US",
    "sg:address":"23441 El Campo Rd",
    "sg:city":"Harlingen",
    "sg:classifiers":[
        {
            "category":"Building & Trades",
            "subcategory":"Construction",
            "type":"Services"
        }
    ],
    "sg:phone":"+1 956 440 0094",
    "sg:postcode":"78552",
    "sg:province":"TX",
    "sg:tags":[
        "roofing",
        "contractor"
    ],
    "wof:name":"New Horizon Quality Sales",
    "wof:placetype":"venue"
},
  "geometry": {"coordinates":[-97.74018599999999,26.219512],"type":"Point"}
}