{
  "type": "Feature",
  "properties": {
    "iso:country":"US",
    "sg:address":"926 Thistle Green Ln",
    "sg:city":"Duncanville",
    "sg:classifiers":[
        {
            "category":"Education",
            "subcategory":"Special Training",
            "type":"Public Place"
        }
    ],
    "sg:phone":"+1 972 298 2652",
    "sg:postcode":"75137",
    "sg:province":"TX",
    "wof:name":"Sfc Assciates Spt Field Conslt",
    "wof:placetype":"venue"
},
  "geometry": {"coordinates":[-96.929187,32.633216],"type":"Point"}
}