{
  "type": "Feature",
  "properties": {
    "iso:country":"US",
    "sg:address":"1410 W Houston St",
    "sg:city":"Sherman",
    "sg:classifiers":[
        {
            "category":"Professional",
            "subcategory":"Business Services",
            "type":"Services"
        }
    ],
    "sg:phone":"+1 903 870 9504",
    "sg:postcode":"75092",
    "sg:province":"TX",
    "sg:tags":[
        "embroidery"
    ],
    "wof:name":"ESP Designs",
    "wof:placetype":"venue"
},
  "geometry": {"coordinates":[-96.626769,33.632965],"type":"Point"}
}