{
  "type": "Feature",
  "properties": {
    "iso:country":"US",
    "sg:address":"4232 Lemmon Ave",
    "sg:city":"Dallas",
    "sg:classifiers":[
        {
            "category":"Autos & Motor Vehicles",
            "subcategory":"Fuel & Gas Station",
            "type":"Retail Goods"
        }
    ],
    "sg:phone":"+1 214 520 9274",
    "sg:postcode":"75219",
    "sg:province":"TX",
    "sg:tags":[
        "oil"
    ],
    "wof:name":"Lemmon Ave Self Svc",
    "wof:placetype":"venue"
},
  "geometry": {"coordinates":[-96.810828,32.816568],"type":"Point"}
}