{
  "type": "Feature",
  "properties": {
    "iso:country":"US",
    "sg:address":"19618 Mackinaw Isle Ct",
    "sg:city":"Cypress",
    "sg:classifiers":[
        {
            "category":"Community Center",
            "subcategory":"Senior",
            "type":"Public Place"
        },
        {
            "category":"Social Services",
            "subcategory":"Job Training",
            "type":"Services"
        },
        {
            "category":"Health Services",
            "subcategory":"Nursing And Care Facility",
            "type":"Services"
        },
        {
            "category":"Social Services",
            "subcategory":"Retirement Home",
            "type":"Services"
        },
        {
            "category":"Social Services",
            "subcategory":"Adult Care",
            "type":"Services"
        }
    ],
    "sg:phone":"+1 281 818 4556",
    "sg:postcode":"77429",
    "sg:province":"TX",
    "sg:tags":[
        "living",
        "homes-skilled",
        "assisted",
        "elder",
        "convalescent",
        "citizen",
        "homes-intermediate"
    ],
    "sg:website":"http://www.mcphersonspersonalcare.com",
    "wof:name":"McPherson's Personal Care Homes",
    "wof:placetype":"venue"
},
  "geometry": {"coordinates":[-95.72424599999999,29.988129],"type":"Point"}
}