{
  "type": "Feature",
  "properties": {
    "iso:country":"US",
    "sg:address":"12009 Lake June Rd",
    "sg:city":"Mesquite",
    "sg:classifiers":[
        {
            "category":"Building & Trades",
            "subcategory":"Equipment Rental",
            "type":"Services"
        }
    ],
    "sg:phone":"+1 972 216 5779",
    "sg:postcode":"75180",
    "sg:province":"TX",
    "sg:tags":[
        "furniture"
    ],
    "wof:name":"A-O K Rent To Own",
    "wof:placetype":"venue"
},
  "geometry": {"coordinates":[-96.62185700000001,32.734215],"type":"Point"}
}