{
  "type": "Feature",
  "properties": {
    "iso:country":"US",
    "sg:address":"7619 Greendowns St",
    "sg:city":"Houston",
    "sg:classifiers":[
        {
            "category":"Building & Trades",
            "subcategory":"Pest Control",
            "type":"Services"
        }
    ],
    "sg:phone":"+1 713 643 5963",
    "sg:postcode":"77087",
    "sg:province":"TX",
    "wof:name":"Demand Pest Control Inc",
    "wof:placetype":"venue"
},
  "geometry": {"coordinates":[-95.287599,29.690736],"type":"Point"}
}