{
  "type": "Feature",
  "properties": {
    "iso:country":"US",
    "sg:address":"7715 Katy Fwy",
    "sg:city":"Houston",
    "sg:classifiers":[
        {
            "category":"Freight",
            "type":"Transportation"
        }
    ],
    "sg:phone":"+1 888 857 8144",
    "sg:postcode":"77024",
    "sg:province":"TX",
    "sg:tags":[
        "general"
    ],
    "wof:name":"Public Storage Inc",
    "wof:placetype":"venue"
},
  "geometry": {"coordinates":[-95.471592,29.783609],"type":"Point"}
}