{
  "type": "Feature",
  "properties": {
    "iso:country":"US",
    "sg:address":"1421 Champion Dr Ste 304",
    "sg:city":"Carrollton",
    "sg:classifiers":[
        {
            "category":"Shopping",
            "subcategory":"Stationery & Office Supplies",
            "type":"Retail Goods"
        }
    ],
    "sg:phone":"+1 972 481 1222",
    "sg:postcode":"75006",
    "sg:province":"TX",
    "sg:tags":[
        "equipment"
    ],
    "wof:name":"Brother International",
    "wof:placetype":"venue"
},
  "geometry": {"coordinates":[-96.917416,32.931478],"type":"Point"}
}