{
  "type": "Feature",
  "properties": {
    "iso:country":"US",
    "sg:address":"100 W Fogg St",
    "sg:city":"Fort Worth",
    "sg:classifiers":[
        {
            "category":"Professional",
            "type":"Services"
        }
    ],
    "sg:phone":"+1 817 923 8582",
    "sg:postcode":"76110",
    "sg:province":"TX",
    "sg:tags":[
        "establishment"
    ],
    "wof:name":"IHM Neighborhood Clean-Up",
    "wof:placetype":"venue"
},
  "geometry": {"coordinates":[-97.32840899999999,32.691058],"type":"Point"}
}