{
  "type": "Feature",
  "properties": {
    "iso:country":"US",
    "sg:address":"719 E Main St",
    "sg:city":"Gatesville",
    "sg:classifiers":[
        {
            "category":"Shopping",
            "subcategory":"Florist",
            "type":"Retail Goods"
        }
    ],
    "sg:phone":"+1 254 865 2274",
    "sg:postcode":"76528",
    "sg:province":"TX",
    "wof:name":"Graves Florist",
    "wof:placetype":"venue"
},
  "geometry": {"coordinates":[-97.749375,31.435018],"type":"Point"}
}