{
  "type": "Feature",
  "properties": {
    "iso:country":"US",
    "sg:address":"1303 Jolly St",
    "sg:city":"Borger",
    "sg:classifiers":[
        {
            "category":"Retail",
            "subcategory":"Repair Shop",
            "type":"Services"
        }
    ],
    "sg:phone":"+1 806 274 5708",
    "sg:postcode":"79007",
    "sg:province":"TX",
    "wof:name":"T&H Repair Services",
    "wof:placetype":"venue"
},
  "geometry": {"coordinates":[-101.38716700000001,35.681875],"type":"Point"}
}