{
  "type": "Feature",
  "properties": {
    "iso:country":"US",
    "sg:address":"1001 S Main St",
    "sg:city":"Euless",
    "sg:classifiers":[
        {
            "category":"Shopping",
            "subcategory":"Party Supplies",
            "type":"Retail Goods"
        },
        {
            "category":"Personal",
            "type":"Services"
        }
    ],
    "sg:phone":"+1 817 545 2744",
    "sg:postcode":"76040",
    "sg:province":"TX",
    "sg:tags":[
        "decoration",
        "favors",
        "planning",
        "event"
    ],
    "wof:name":"Nazzaro Enterprises",
    "wof:placetype":"venue"
},
  "geometry": {"coordinates":[-97.082306,32.823357],"type":"Point"}
}