{
  "type": "Feature",
  "properties": {
    "iso:country":"US",
    "sg:address":"5318 Belt Line Rd",
    "sg:city":"Dallas",
    "sg:classifiers":[
        {
            "category":"Government",
            "subcategory":"Office",
            "type":"Public Place"
        }
    ],
    "sg:phone":"+1 972 774 0037",
    "sg:postcode":"75254",
    "sg:province":"TX",
    "sg:tags":[
        "program",
        "administrative"
    ],
    "wof:name":"Lone Star Invstgtions Recovery",
    "wof:placetype":"venue"
},
  "geometry": {"coordinates":[-96.81441,32.953877],"type":"Point"}
}