{
  "type": "Feature",
  "properties": {
    "iso:country":"US",
    "sg:address":"4020 Christopher Way",
    "sg:city":"Plano",
    "sg:classifiers":[
        {
            "category":"Wholesale",
            "subcategory":"Durable Goods & Equipment",
            "type":"Manufacturing & Wholesale Goods"
        }
    ],
    "sg:phone":"+1 214 929 6790",
    "sg:postcode":"75024",
    "sg:province":"TX",
    "wof:name":"Tamil Movie Usa Com",
    "wof:placetype":"venue"
},
  "geometry": {"coordinates":[-96.77248299999999,33.082576],"type":"Point"}
}