{
  "type": "Feature",
  "properties": {
    "iso:country":"US",
    "sg:address":"415 W US Hwy 79",
    "sg:city":"Rockdale",
    "sg:classifiers":[
        {
            "category":"Building & Trades",
            "subcategory":"Construction",
            "type":"Services"
        }
    ],
    "sg:phone":"+1 512 446 3641",
    "sg:postcode":"76567",
    "sg:province":"TX",
    "wof:name":"Rafter S Inc",
    "wof:placetype":"venue"
},
  "geometry": {"coordinates":[-97.004952,30.653894],"type":"Point"}
}