{
  "type": "Feature",
  "properties": {
    "iso:country":"US",
    "sg:address":"505 Houston St",
    "sg:city":"Laredo",
    "sg:classifiers":[
        {
            "category":"Communications",
            "subcategory":"Radio Station",
            "type":"Services"
        }
    ],
    "sg:phone":"+1 956 795 1490",
    "sg:postcode":"78040",
    "sg:province":"TX",
    "sg:tags":[
        "broadcast"
    ],
    "wof:name":"K L N T Listener",
    "wof:placetype":"venue"
},
  "geometry": {"coordinates":[-99.501645,27.506981],"type":"Point"}
}