{
  "type": "Feature",
  "properties": {
    "iso:country":"US",
    "sg:address":"518 S Enterprize Pkwy",
    "sg:city":"Corpus Christi",
    "sg:classifiers":[
        {
            "category":"Manufacturing",
            "subcategory":"Printing",
            "type":"Manufacturing & Wholesale Goods"
        }
    ],
    "sg:phone":"+1 361 289 0996",
    "sg:postcode":"78405",
    "sg:province":"TX",
    "sg:tags":[
        "newsletter",
        "business"
    ],
    "wof:name":"South Texas Chapter",
    "wof:placetype":"venue"
},
  "geometry": {"coordinates":[-97.459684,27.75901],"type":"Point"}
}