{
  "type": "Feature",
  "properties": {
    "iso:country":"US",
    "sg:address":"404 Riverside Dr",
    "sg:city":"Fort Worth",
    "sg:classifiers":[
        {
            "category":"Wholesale",
            "subcategory":"Construction Materials",
            "type":"Manufacturing & Wholesale Goods"
        }
    ],
    "sg:phone":"+1 817 335 3273",
    "sg:postcode":"76111",
    "sg:province":"TX",
    "sg:tags":[
        "glass"
    ],
    "wof:name":"American Glass Distributors",
    "wof:placetype":"venue"
},
  "geometry": {"coordinates":[-97.30179800000001,32.761287],"type":"Point"}
}