{
  "type": "Feature",
  "properties": {
    "iso:country":"US",
    "sg:address":"211 Ave D",
    "sg:city":"El Campo",
    "sg:classifiers":[
        {
            "category":"Health Services",
            "subcategory":"Health Practitioner",
            "type":"Services"
        }
    ],
    "sg:phone":"+1 979 543 6789",
    "sg:postcode":"77437",
    "sg:province":"TX",
    "wof:name":"Mary P Sappington",
    "wof:placetype":"venue"
},
  "geometry": {"coordinates":[-96.27723899999999,29.193198],"type":"Point"}
}