{
  "type": "Feature",
  "properties": {
    "iso:country":"US",
    "sg:address":"2607 Timberline Dr",
    "sg:city":"Flower Mound",
    "sg:classifiers":[
        {
            "category":"Professional",
            "subcategory":"Computer Services",
            "type":"Services"
        }
    ],
    "sg:phone":"+1 214 995 7142",
    "sg:postcode":"75028",
    "sg:province":"TX",
    "sg:tags":[
        "datum"
    ],
    "wof:name":"Renderaid Com",
    "wof:placetype":"venue"
},
  "geometry": {"coordinates":[-97.073025,33.057773],"type":"Point"}
}