{
  "type": "Feature",
  "properties": {
    "iso:country":"US",
    "sg:address":"205 W Rancier Ave",
    "sg:city":"Killeen",
    "sg:classifiers":[
        {
            "category":"Building & Trades",
            "subcategory":"Equipment Rental",
            "type":"Services"
        }
    ],
    "sg:phone":"+1 254 526 6655",
    "sg:postcode":"76541",
    "sg:province":"TX",
    "sg:tags":[
        "yard",
        "appliance",
        "accessory",
        "home",
        "electronics",
        "furniture"
    ],
    "wof:name":"Rent-A-Center",
    "wof:placetype":"venue"
},
  "geometry": {"coordinates":[-97.730575,31.127176],"type":"Point"}
}