{
  "type": "Feature",
  "properties": {
    "iso:country":"US",
    "sg:address":"4703 W Spring Valley Rd",
    "sg:city":"Lorena",
    "sg:classifiers":[
        {
            "category":"Shopping",
            "subcategory":"Bicycles & Sporting Goods",
            "type":"Retail Goods"
        }
    ],
    "sg:phone":"+1 254 857 4513",
    "sg:postcode":"76655",
    "sg:province":"TX",
    "wof:name":"J B Hill Jr",
    "wof:placetype":"venue"
},
  "geometry": {"coordinates":[-97.26330900000001,31.411867],"type":"Point"}
}