{
  "type": "Feature",
  "properties": {
    "iso:country":"US",
    "sg:address":"12243 Shiloh Rd",
    "sg:city":"Dallas",
    "sg:classifiers":[
        {
            "category":"Autos & Motor Vehicles",
            "subcategory":"Automobile Sales",
            "type":"Retail Goods"
        }
    ],
    "sg:phone":"+1 214 327 1412",
    "sg:postcode":"75228",
    "sg:province":"TX",
    "sg:tags":[
        "used"
    ],
    "wof:name":"John Hester Auto Sales",
    "wof:placetype":"venue"
},
  "geometry": {"coordinates":[-96.66583,32.865164],"type":"Point"}
}