{
  "type": "Feature",
  "properties": {
    "iso:country":"US",
    "sg:address":"1303 Martin Luther King Jr Blvd",
    "sg:city":"Killeen",
    "sg:classifiers":[
        {
            "category":"Retail",
            "subcategory":"Auto Repair",
            "type":"Services"
        }
    ],
    "sg:phone":"+1 254 690 3776",
    "sg:postcode":"76543",
    "sg:province":"TX",
    "sg:tags":[
        "repairing",
        "automobile"
    ],
    "wof:name":"Earl Reece's Automotive Svc",
    "wof:placetype":"venue"
},
  "geometry": {"coordinates":[-97.695482,31.090971],"type":"Point"}
}