{
  "type": "Feature",
  "properties": {
    "iso:country":"US",
    "sg:address":"4747 Bellaire Blvd Ste 150",
    "sg:city":"Bellaire",
    "sg:classifiers":[
        {
            "category":"Professional",
            "subcategory":"Employment Agencies",
            "type":"Services"
        }
    ],
    "sg:phone":"+1 713 660 6071",
    "sg:postcode":"77401",
    "sg:province":"TX",
    "wof:name":"Superior Staffing Services",
    "wof:placetype":"venue"
},
  "geometry": {"coordinates":[-95.46109800000001,29.7057],"type":"Point"}
}