{
  "type": "Feature",
  "properties": {
    "iso:country":"US",
    "sg:address":"11404 Cll Verde Cove",
    "sg:city":"Austin",
    "sg:classifiers":[
        {
            "category":"Manufacturing",
            "subcategory":"Tools & Machinery",
            "type":"Manufacturing & Wholesale Goods"
        }
    ],
    "sg:phone":"+1 512 346 8951",
    "sg:postcode":"78759",
    "sg:province":"TX",
    "sg:tags":[
        "field",
        "oil",
        "equipment"
    ],
    "wof:name":"Adair Group Intl Inc",
    "wof:placetype":"venue"
},
  "geometry": {"coordinates":[-97.730125,30.404118],"type":"Point"}
}