{
  "type": "Feature",
  "properties": {
    "iso:country":"US",
    "sg:address":"500 W Main St",
    "sg:city":"Palestine",
    "sg:classifiers":[
        {
            "category":"Manufacturing",
            "subcategory":"Tools & Machinery",
            "type":"Manufacturing & Wholesale Goods"
        }
    ],
    "sg:phone":"+1 903 729 6234",
    "sg:postcode":"75801",
    "sg:province":"TX",
    "sg:tags":[
        "equipment",
        "seismograph",
        "supply"
    ],
    "wof:name":"Exploration Products Co",
    "wof:placetype":"venue"
},
  "geometry": {"coordinates":[-95.63560200000001,31.762171],"type":"Point"}
}