{
  "type": "Feature",
  "properties": {
    "iso:country":"US",
    "sg:address":"13535 Walcik Rd",
    "sg:city":"Guy",
    "sg:classifiers":[
        {
            "category":"Manufacturing",
            "subcategory":"Tools & Machinery",
            "type":"Manufacturing & Wholesale Goods"
        }
    ],
    "sg:phone":"+1 979 793 3888",
    "sg:postcode":"77444",
    "sg:province":"TX",
    "sg:tags":[
        "machine",
        "shop"
    ],
    "wof:name":"A & T Machine Services",
    "wof:placetype":"venue"
},
  "geometry": {"coordinates":[-95.795782,29.353598],"type":"Point"}
}