{
  "type": "Feature",
  "properties": {
    "iso:country":"US",
    "sg:address":"110 S Cockrell Hill Rd",
    "sg:city":"Desoto",
    "sg:classifiers":[
        {
            "category":"Professional",
            "type":"Services"
        },
        {
            "category":"Real Estate",
            "subcategory":"Real Estate Services",
            "type":"Services"
        }
    ],
    "sg:phone":"+1 972 274 5525",
    "sg:postcode":"75115",
    "sg:province":"TX",
    "sg:tags":[
        "company",
        "title"
    ],
    "wof:name":"Blue Star Titile",
    "wof:placetype":"venue"
},
  "geometry": {"coordinates":[-96.891108,32.5849],"type":"Point"}
}