{
  "type": "Feature",
  "properties": {
    "iso:country":"US",
    "sg:address":"1513 New York Ave",
    "sg:city":"Arlington",
    "sg:classifiers":[
        {
            "category":"Personal",
            "subcategory":"Beauty Salon",
            "type":"Services"
        }
    ],
    "sg:phone":"+1 817 277 6077",
    "sg:postcode":"76010",
    "sg:province":"TX",
    "sg:tags":[
        "shop"
    ],
    "wof:name":"Rich & Famous Hair & Nail",
    "wof:placetype":"venue"
},
  "geometry": {"coordinates":[-97.08023,32.718934],"type":"Point"}
}