{
  "type": "Feature",
  "properties": {
    "iso:country":"US",
    "sg:address":"11114 Pinecone Ln",
    "sg:city":"Houston",
    "sg:classifiers":[
        {
            "category":"Professional",
            "type":"Services"
        }
    ],
    "sg:phone":"+1 713 896 6238",
    "sg:postcode":"77041",
    "sg:province":"TX",
    "wof:name":"Mediterranio International LLC",
    "wof:placetype":"venue"
},
  "geometry": {"coordinates":[-95.573702,29.865487],"type":"Point"}
}