{
  "type": "Feature",
  "properties": {
    "iso:country":"US",
    "sg:address":"212 N 12th Ave",
    "sg:city":"Edinburg",
    "sg:classifiers":[
        {
            "category":"Food & Beverages",
            "subcategory":"Bakery",
            "type":"Retail Goods"
        }
    ],
    "sg:phone":"+1 956 381 8180",
    "sg:postcode":"78541",
    "sg:province":"TX",
    "sg:tags":[
        "baker"
    ],
    "wof:name":"D & S Cakes & Goodies",
    "wof:placetype":"venue"
},
  "geometry": {"coordinates":[-98.160819,26.303167],"type":"Point"}
}