{
  "type": "Feature",
  "properties": {
    "iso:country":"US",
    "sg:address":"1307 Purdue Dr",
    "sg:city":"Longview",
    "sg:classifiers":[
        {
            "category":"Social Services",
            "subcategory":"Adult Care",
            "type":"Services"
        }
    ],
    "sg:phone":"+1 903 758 3266",
    "sg:postcode":"75601",
    "sg:province":"TX",
    "sg:tags":[
        "retardation",
        "home",
        "dev",
        "disabled"
    ],
    "wof:name":"Kindred Homes Inc",
    "wof:placetype":"venue"
},
  "geometry": {"coordinates":[-94.758233,32.51235],"type":"Point"}
}