{
  "type": "Feature",
  "properties": {
    "iso:country":"US",
    "sg:address":"1514 Gessner Dr",
    "sg:city":"Houston",
    "sg:classifiers":[
        {
            "category":"Shopping",
            "subcategory":"Clothing, Apparel, & Fashions",
            "type":"Retail Goods"
        }
    ],
    "sg:phone":"+1 713 464 6200",
    "sg:postcode":"77080",
    "sg:province":"TX",
    "sg:tags":[
        "salvage",
        "surplus",
        "merchandise"
    ],
    "wof:name":"Costello Surplus",
    "wof:placetype":"venue"
},
  "geometry": {"coordinates":[-95.54469899999999,29.798213],"type":"Point"}
}