{
  "type": "Feature",
  "properties": {
    "iso:country":"US",
    "sg:address":"4101 Medical Pkwy Ste 202",
    "sg:city":"Austin",
    "sg:classifiers":[
        {
            "category":"Professional",
            "subcategory":"Business Services",
            "type":"Services"
        }
    ],
    "sg:phone":"+1 512 451 2462",
    "sg:postcode":"78756",
    "sg:province":"TX",
    "sg:tags":[
        "drafting"
    ],
    "wof:name":"Peter Green Architect",
    "wof:placetype":"venue"
},
  "geometry": {"coordinates":[-97.742622,30.30986],"type":"Point"}
}