{
  "type": "Feature",
  "properties": {
    "iso:country":"US",
    "sg:address":"2102 Branard St",
    "sg:city":"Houston",
    "sg:classifiers":[
        {
            "category":"Recreation",
            "type":"Entertainment"
        }
    ],
    "sg:phone":"+1 713 524 6666",
    "sg:postcode":"77098",
    "sg:province":"TX",
    "wof:name":"Ticket Bomb",
    "wof:placetype":"venue"
},
  "geometry": {"coordinates":[-95.412834,29.736873],"type":"Point"}
}