{
  "type": "Feature",
  "properties": {
    "iso:country":"US",
    "sg:address":"225 N Crockett St",
    "sg:city":"Sherman",
    "sg:classifiers":[
        {
            "category":"Professional",
            "subcategory":"Lawyer & Legal Services",
            "type":"Services"
        }
    ],
    "sg:phone":"+1 903 870 2104",
    "sg:postcode":"75090",
    "sg:province":"TX",
    "wof:name":"Jeff C Wilson",
    "wof:placetype":"venue"
},
  "geometry": {"coordinates":[-96.61093,33.6381],"type":"Point"}
}