{
  "type": "Feature",
  "properties": {
    "iso:country":"US",
    "sg:address":"2801 Lovers Ln",
    "sg:city":"Dallas",
    "sg:classifiers":[
        {
            "category":"Professional",
            "subcategory":"Advertising",
            "type":"Services"
        }
    ],
    "sg:phone":"+1 214 691 6397",
    "sg:postcode":"75225",
    "sg:province":"TX",
    "sg:tags":[
        "counselor"
    ],
    "wof:name":"Gaither Advertising",
    "wof:placetype":"venue"
},
  "geometry": {"coordinates":[-96.77521299999999,32.851084],"type":"Point"}
}