{
  "type": "Feature",
  "properties": {
    "iso:country":"US",
    "sg:address":"719 Sawdust Rd",
    "sg:city":"Spring",
    "sg:classifiers":[
        {
            "category":"Home & Garden",
            "subcategory":"Hardware",
            "type":"Retail Goods"
        }
    ],
    "sg:phone":"+1 281 419 6440",
    "sg:postcode":"77380",
    "sg:province":"TX",
    "sg:tags":[
        "field",
        "pump",
        "oil"
    ],
    "wof:name":"New Coleman Pump Co Inc",
    "wof:placetype":"venue"
},
  "geometry": {"coordinates":[-95.456928,30.126695],"type":"Point"}
}