{
  "type": "Feature",
  "properties": {
    "iso:country":"US",
    "sg:address":"704 Lake Rd",
    "sg:city":"Lake Jackson",
    "sg:classifiers":[
        {
            "category":"Real Estate",
            "subcategory":"Real Estate Operator",
            "type":"Services"
        }
    ],
    "sg:phone":"+1 979 297 1606",
    "sg:postcode":"77566",
    "sg:province":"TX",
    "sg:tags":[
        "building",
        "nonresidential"
    ],
    "wof:name":"Ers Properties LLC",
    "wof:placetype":"venue"
},
  "geometry": {"coordinates":[-95.471586,29.05853],"type":"Point"}
}