{
  "type": "Feature",
  "properties": {
    "iso:country":"US",
    "sg:address":"12113 Metric Blvd",
    "sg:city":"Austin",
    "sg:classifiers":[
        {
            "category":"Home & Garden",
            "subcategory":"Home Furnishings",
            "type":"Retail Goods"
        },
        {
            "category":"Real Estate",
            "subcategory":"Architect",
            "type":"Services"
        }
    ],
    "sg:phone":"+1 866 907 8253",
    "sg:postcode":"78758",
    "sg:province":"TX",
    "sg:tags":[
        "building",
        "planning",
        "designer",
        "design"
    ],
    "wof:name":"Design Space & Color",
    "wof:placetype":"venue"
},
  "geometry": {"coordinates":[-97.698116,30.404687],"type":"Point"}
}