{
  "type": "Feature",
  "properties": {
    "iso:country":"US",
    "sg:address":"2278 County Road 499",
    "sg:city":"Hico",
    "sg:classifiers":[
        {
            "category":"Building & Trades",
            "subcategory":"Electrical",
            "type":"Services"
        }
    ],
    "sg:phone":"+1 254 785 2368",
    "sg:postcode":"76457",
    "sg:province":"TX",
    "sg:tags":[
        "electrician"
    ],
    "wof:name":"B & B Auto",
    "wof:placetype":"venue"
},
  "geometry": {"coordinates":[-98.157263,31.948561],"type":"Point"}
}