{
  "type": "Feature",
  "properties": {
    "iso:country":"US",
    "sg:address":"10204 Max Ln",
    "sg:city":"Frisco",
    "sg:classifiers":[
        {
            "category":"Wholesale",
            "subcategory":"Apparel",
            "type":"Manufacturing & Wholesale Goods"
        }
    ],
    "sg:phone":"+1 972 377 9337",
    "sg:postcode":"75035",
    "sg:province":"TX",
    "sg:tags":[
        "infant",
        "wear"
    ],
    "wof:name":"Rocket Entertainment",
    "wof:placetype":"venue"
},
  "geometry": {"coordinates":[-96.788873,33.111219],"type":"Point"}
}