{
  "type": "Feature",
  "properties": {
    "iso:country":"US",
    "sg:address":"1609 Texas Ave",
    "sg:city":"San Antonio",
    "sg:classifiers":[
        {
            "category":"Building & Trades",
            "subcategory":"Plumbing",
            "type":"Services"
        }
    ],
    "sg:phone":"+1 210 789 5342",
    "sg:postcode":"78201",
    "sg:province":"TX",
    "sg:tags":[
        "air",
        "conditioning",
        "contractor"
    ],
    "wof:name":"Teys A/C & Heating",
    "wof:placetype":"venue"
},
  "geometry": {"coordinates":[-98.538656,29.449839],"type":"Point"}
}