{
  "type": "Feature",
  "properties": {
    "iso:country":"US",
    "sg:address":"920 Winnsboro St",
    "sg:city":"Quitman",
    "sg:classifiers":[
        {
            "category":"Wholesale",
            "subcategory":"Durable Goods & Equipment",
            "type":"Manufacturing & Wholesale Goods"
        }
    ],
    "sg:phone":"+1 903 763 4234",
    "sg:postcode":"75783",
    "sg:province":"TX",
    "sg:tags":[
        "representative",
        "manufacturer"
    ],
    "wof:name":"Ted Rye Sales",
    "wof:placetype":"venue"
},
  "geometry": {"coordinates":[-95.438501,32.80485],"type":"Point"}
}