{
  "type": "Feature",
  "properties": {
    "iso:country":"US",
    "sg:address":"19765 Mercedell",
    "sg:city":"Porter",
    "sg:classifiers":[
        {
            "category":"Building & Trades",
            "subcategory":"Construction",
            "type":"Services"
        }
    ],
    "sg:phone":"+1 281 354 3934",
    "sg:postcode":"77365",
    "sg:province":"TX",
    "sg:tags":[
        "contractor"
    ],
    "wof:name":"Rs Marchisio",
    "wof:placetype":"venue"
},
  "geometry": {"coordinates":[-95.270973,30.10602],"type":"Point"}
}