{
  "type": "Feature",
  "properties": {
    "iso:country":"US",
    "sg:address":"6743 Ambush Dr",
    "sg:city":"San Antonio",
    "sg:classifiers":[
        {
            "category":"Health Services",
            "subcategory":"Doctor",
            "type":"Services"
        }
    ],
    "sg:phone":"+1 210 567 5347",
    "sg:postcode":"78240",
    "sg:province":"TX",
    "sg:tags":[
        "medical",
        "practitioner"
    ],
    "wof:name":"Mark Fredrickson",
    "wof:placetype":"venue"
},
  "geometry": {"coordinates":[-98.62594799999999,29.530346],"type":"Point"}
}