{
  "type": "Feature",
  "properties": {
    "iso:country":"US",
    "sg:address":"1506 Casa de Oro Dr",
    "sg:city":"Corpus Christi",
    "sg:classifiers":[
        {
            "category":"Retail",
            "subcategory":"Repair Shop",
            "type":"Services"
        }
    ],
    "sg:phone":"+1 361 888 6184",
    "sg:postcode":"78411",
    "sg:province":"TX",
    "sg:tags":[
        "machine",
        "sewing",
        "electrical"
    ],
    "wof:name":"Dial Sewing Machine Service",
    "wof:placetype":"venue"
},
  "geometry": {"coordinates":[-97.402422,27.744582],"type":"Point"}
}