{
  "type": "Feature",
  "properties": {
    "iso:country":"US",
    "sg:address":"4715 S 31st St",
    "sg:city":"Temple",
    "sg:classifiers":[
        {
            "category":"Freight",
            "type":"Transportation"
        }
    ],
    "sg:phone":"+1 254 778 0965",
    "sg:postcode":"76502",
    "sg:province":"TX",
    "sg:tags":[
        "general"
    ],
    "wof:name":"Southpark Self Storage",
    "wof:placetype":"venue"
},
  "geometry": {"coordinates":[-97.374493,31.056242],"type":"Point"}
}