{
  "type": "Feature",
  "properties": {
    "iso:country":"US",
    "sg:address":"902 Bartholomae St",
    "sg:city":"Seguin",
    "sg:classifiers":[
        {
            "category":"Real Estate",
            "subcategory":"Real Estate Agent",
            "type":"Services"
        }
    ],
    "sg:phone":"+1 830 303 0987",
    "sg:postcode":"78155",
    "sg:province":"TX",
    "wof:name":"Always Home Inc",
    "wof:placetype":"venue"
},
  "geometry": {"coordinates":[-97.961142,29.576701],"type":"Point"}
}