{
  "type": "Feature",
  "properties": {
    "iso:country":"US",
    "sg:address":"33 Pfeiffer Rd",
    "sg:city":"Boerne",
    "sg:classifiers":[
        {
            "category":"Shopping",
            "subcategory":"Computers & Home Electronics",
            "type":"Retail Goods"
        }
    ],
    "sg:phone":"+1 830 249 9603",
    "sg:postcode":"78006",
    "sg:province":"TX",
    "sg:tags":[
        "equipment",
        "electronic",
        "supply"
    ],
    "wof:name":"Great Southern Electronics",
    "wof:placetype":"venue"
},
  "geometry": {"coordinates":[-98.75381,29.83047],"type":"Point"}
}