{
  "type": "Feature",
  "properties": {
    "iso:country":"US",
    "sg:address":"133 Raley Rd",
    "sg:city":"Cedar Park",
    "sg:classifiers":[
        {
            "category":"Real Estate",
            "subcategory":"Real Estate Agent",
            "type":"Services"
        }
    ],
    "sg:phone":"+1 512 259 0989",
    "sg:postcode":"78613",
    "sg:province":"TX",
    "wof:name":"John Dudgeon Realty Inc",
    "wof:placetype":"venue"
},
  "geometry": {"coordinates":[-97.765852,30.539295],"type":"Point"}
}