{
  "type": "Feature",
  "properties": {
    "iso:country":"US",
    "sg:address":"1716 Woodridge Dr",
    "sg:city":"Brownwood",
    "sg:classifiers":[
        {
            "category":"Retail",
            "subcategory":"Repair Shop",
            "type":"Services"
        }
    ],
    "sg:phone":"+1 325 646 0946",
    "sg:postcode":"76801",
    "sg:province":"TX",
    "sg:tags":[
        "electrical"
    ],
    "wof:name":"Dudleys Appliance & Rfrgn",
    "wof:placetype":"venue"
},
  "geometry": {"coordinates":[-98.95877299999999,31.668777],"type":"Point"}
}