{
  "type": "Feature",
  "properties": {
    "iso:country":"US",
    "sg:address":"4750 S Colony Blvd",
    "sg:city":"The Colony",
    "sg:classifiers":[
        {
            "category":"Personal",
            "subcategory":"Beauty Salon",
            "type":"Services"
        }
    ],
    "sg:phone":"+1 972 370 2896",
    "sg:postcode":"75056",
    "sg:province":"TX",
    "wof:name":"Kim & Vicki Beautyland",
    "wof:placetype":"venue"
},
  "geometry": {"coordinates":[-96.891868,33.080472],"type":"Point"}
}