{
  "type": "Feature",
  "properties": {
    "iso:country":"US",
    "sg:address":"1830 W Hermosa Dr",
    "sg:city":"San Antonio",
    "sg:classifiers":[
        {
            "category":"Professional",
            "subcategory":"Computer Services",
            "type":"Services"
        }
    ],
    "sg:phone":"+1 210 735 1340",
    "sg:postcode":"78201",
    "sg:province":"TX",
    "sg:tags":[
        "design",
        "system"
    ],
    "wof:name":"K Rap Computers",
    "wof:placetype":"venue"
},
  "geometry": {"coordinates":[-98.525542,29.478407],"type":"Point"}
}