{
  "type": "Feature",
  "properties": {
    "iso:country":"US",
    "sg:address":"1612 S Washington St",
    "sg:city":"Amarillo",
    "sg:classifiers":[
        {
            "category":"Manufacturing",
            "subcategory":"Printing",
            "type":"Manufacturing & Wholesale Goods"
        }
    ],
    "sg:phone":"+1 806 376 9063",
    "sg:postcode":"79102",
    "sg:province":"TX",
    "sg:tags":[
        "publishing"
    ],
    "wof:name":"TV Times",
    "wof:placetype":"venue"
},
  "geometry": {"coordinates":[-101.848517,35.196591],"type":"Point"}
}