{
  "type": "Feature",
  "properties": {
    "iso:country":"US",
    "sg:address":"104 Country Club Ter",
    "sg:city":"Dumas",
    "sg:classifiers":[
        {
            "category":"Manufacturing",
            "subcategory":"Apparel",
            "type":"Manufacturing & Wholesale Goods"
        },
        {
            "category":"Home & Garden",
            "subcategory":"Home Furnishings",
            "type":"Retail Goods"
        }
    ],
    "sg:phone":"+1 806 935 8619",
    "sg:postcode":"79029",
    "sg:province":"TX",
    "sg:tags":[
        "household",
        "quilting",
        "mfg"
    ],
    "wof:name":"Charlee's Quilting",
    "wof:placetype":"venue"
},
  "geometry": {"coordinates":[-101.96478,35.923047],"type":"Point"}
}