{
  "type": "Feature",
  "properties": {
    "iso:country":"US",
    "sg:address":"17732 Regal Row",
    "sg:city":"Flint",
    "sg:classifiers":[
        {
            "category":"Professional",
            "subcategory":"Computer Services",
            "type":"Services"
        }
    ],
    "sg:phone":"+1 903 825 9509",
    "sg:postcode":"75762",
    "sg:province":"TX",
    "sg:tags":[
        "home",
        "consulting",
        "page",
        "dev",
        "internet"
    ],
    "sg:website":"www.silverfins.com",
    "wof:name":"Web Stream Development",
    "wof:placetype":"venue"
},
  "geometry": {"coordinates":[-95.469089,32.168254],"type":"Point"}
}