{
  "type": "Feature",
  "properties": {
    "iso:country":"US",
    "sg:address":"20208 Auger Cove",
    "sg:city":"Spicewood",
    "sg:classifiers":[
        {
            "category":"Organizations",
            "subcategory":"Community Association",
            "type":"Services"
        }
    ],
    "sg:phone":"+1 512 264 2115",
    "sg:postcode":"78669",
    "sg:province":"TX",
    "sg:tags":[
        "blind"
    ],
    "wof:name":"Accusight Inc",
    "wof:placetype":"venue"
},
  "geometry": {"coordinates":[-98.043897,30.358215],"type":"Point"}
}