{
  "type": "Feature",
  "properties": {
    "iso:country":"US",
    "sg:address":"4200 W 34th St",
    "sg:city":"Houston",
    "sg:classifiers":[
        {
            "category":"Professional",
            "subcategory":"Business Services",
            "type":"Services"
        }
    ],
    "sg:phone":"+1 713 956 5621",
    "sg:postcode":"77092",
    "sg:province":"TX",
    "wof:name":"Rapid Clean Enterprises",
    "wof:placetype":"venue"
},
  "geometry": {"coordinates":[-95.45055499999999,29.817392],"type":"Point"}
}