{
  "type": "Feature",
  "properties": {
    "iso:country":"US",
    "sg:address":"3555 US Hwy 281",
    "sg:city":"Mineral Wells",
    "sg:classifiers":[
        {
            "category":"Manufacturing",
            "subcategory":"Retail Goods",
            "type":"Manufacturing & Wholesale Goods"
        }
    ],
    "sg:phone":"+1 940 328 4880",
    "sg:postcode":"76067",
    "sg:province":"TX",
    "sg:tags":[
        "assembly",
        "fabricating"
    ],
    "wof:name":"Wells Custom Fabrication",
    "wof:placetype":"venue"
},
  "geometry": {"coordinates":[-98.10509999999999,32.76055],"type":"Point"}
}