{
  "type": "Feature",
  "properties": {
    "iso:country":"US",
    "sg:address":"13653 Rutledge Spur",
    "sg:city":"Austin",
    "sg:classifiers":[
        {
            "category":"Building & Trades",
            "subcategory":"Construction",
            "type":"Services"
        }
    ],
    "sg:phone":"+1 512 331 6673",
    "sg:postcode":"78717",
    "sg:province":"TX",
    "sg:tags":[
        "contractor"
    ],
    "wof:name":"Austin Filter Systems Inc",
    "wof:placetype":"venue"
},
  "geometry": {"coordinates":[-97.780998,30.475401],"type":"Point"}
}