{
  "type": "Feature",
  "properties": {
    "iso:country":"US",
    "sg:address":"6007 Gallant Forest Dr",
    "sg:city":"Houston",
    "sg:classifiers":[
        {
            "category":"Building & Trades",
            "subcategory":"Construction",
            "type":"Services"
        }
    ],
    "sg:phone":"+1 281 405 0643",
    "sg:postcode":"77088",
    "sg:province":"TX",
    "sg:tags":[
        "general",
        "contractor"
    ],
    "wof:name":"Ball Construction",
    "wof:placetype":"venue"
},
  "geometry": {"coordinates":[-95.48312,29.888851],"type":"Point"}
}