{
  "type": "Feature",
  "properties": {
    "iso:country":"US",
    "sg:address":"8459 Five Palms Dr",
    "sg:city":"San Antonio",
    "sg:classifiers":[
        {
            "category":"Restaurant",
            "type":"Food & Drink"
        }
    ],
    "sg:phone":"+1 210 623 5800",
    "sg:postcode":"78242",
    "sg:province":"TX",
    "sg:tags":[
        "eating"
    ],
    "wof:name":"Church's Chicken",
    "wof:placetype":"venue"
},
  "geometry": {"coordinates":[-98.61587900000001,29.348342],"type":"Point"}
}