{
  "type": "Feature",
  "properties": {
    "iso:country":"US",
    "sg:address":"1868 Santa Fe Ave",
    "sg:city":"Snyder",
    "sg:classifiers":[
        {
            "category":"Home & Garden",
            "subcategory":"Home Furnishings",
            "type":"Retail Goods"
        }
    ],
    "sg:phone":"+1 325 573 0825",
    "sg:postcode":"79549",
    "sg:province":"TX",
    "wof:name":"Pretty Windows",
    "wof:placetype":"venue"
},
  "geometry": {"coordinates":[-100.94846099999999,32.713519],"type":"Point"}
}