{
  "type": "Feature",
  "properties": {
    "iso:country":"US",
    "sg:address":"4275 Deerfield Dr",
    "sg:city":"College Station",
    "sg:classifiers":[
        {
            "category":"Retail",
            "subcategory":"Veterinary Services",
            "type":"Services"
        }
    ],
    "sg:phone":"+1 979 776 8996",
    "sg:postcode":"77845",
    "sg:province":"TX",
    "sg:tags":[
        "veterinarian"
    ],
    "wof:name":"Highway 30 Veterinary Clinic",
    "wof:placetype":"venue"
},
  "geometry": {"coordinates":[-96.269499,30.649612],"type":"Point"}
}