{
  "type": "Feature",
  "properties": {
    "iso:country":"US",
    "sg:address":"411 S Lynn Ave",
    "sg:city":"Lamesa",
    "sg:classifiers":[
        {
            "category":"Wholesale",
            "subcategory":"Metals & Minerals",
            "type":"Manufacturing & Wholesale Goods"
        }
    ],
    "sg:phone":"+1 806 872 3202",
    "sg:postcode":"79331",
    "sg:province":"TX",
    "sg:tags":[
        "steel",
        "pipe",
        "process",
        "scrap"
    ],
    "wof:name":"Brock Steel Co",
    "wof:placetype":"venue"
},
  "geometry": {"coordinates":[-101.948297,32.730533],"type":"Point"}
}