{
  "type": "Feature",
  "properties": {
    "iso:country":"US",
    "sg:address":"2041 Harvey Mitchell Pkwy S",
    "sg:city":"College Station",
    "sg:classifiers":[
        {
            "category":"Retail",
            "subcategory":"Portrait Studio",
            "type":"Services"
        }
    ],
    "sg:phone":"+1 979 695 8201",
    "sg:postcode":"77840",
    "sg:province":"TX",
    "sg:tags":[
        "photographer"
    ],
    "wof:name":"Studio One Photographics",
    "wof:placetype":"venue"
},
  "geometry": {"coordinates":[-96.309912,30.593212],"type":"Point"}
}