{
  "type": "Feature",
  "properties": {
    "iso:country":"US",
    "sg:address":"2203 E James St",
    "sg:city":"Baytown",
    "sg:classifiers":[
        {
            "category":"Manufacturing",
            "subcategory":"Apparel",
            "type":"Manufacturing & Wholesale Goods"
        }
    ],
    "sg:phone":"+1 281 837 6518",
    "sg:postcode":"77520",
    "sg:province":"TX",
    "sg:tags":[
        "clothing",
        "mfg"
    ],
    "wof:name":"Casual Ski Design",
    "wof:placetype":"venue"
},
  "geometry": {"coordinates":[-94.94242300000001,29.727797],"type":"Point"}
}