{
  "type": "Feature",
  "properties": {
    "iso:country":"US",
    "sg:address":"601 S Industrial Hwy",
    "sg:city":"Perryton",
    "sg:phone":"+1 806 435 3717",
    "sg:postcode":"79070",
    "sg:province":"TX",
    "sg:tags":[
        "oil"
    ],
    "wof:name":"Campbell Oil Co",
    "wof:placetype":"venue"
},
  "geometry": {"coordinates":[-100.791476,36.394105],"type":"Point"}
}