{
  "type": "Feature",
  "properties": {
    "iso:country":"US",
    "sg:address":"1152 Winding Creek Trl",
    "sg:city":"Spring Branch",
    "sg:classifiers":[
        {
            "category":"Professional",
            "subcategory":"Management & Consulting",
            "type":"Services"
        }
    ],
    "sg:phone":"+1 830 885 6719",
    "sg:postcode":"78070",
    "sg:province":"TX",
    "sg:tags":[
        "retail",
        "direct",
        "sales"
    ],
    "wof:name":"Bonnie Sue Williams",
    "wof:placetype":"venue"
},
  "geometry": {"coordinates":[-98.344171,29.929286],"type":"Point"}
}