{
  "type": "Feature",
  "properties": {
    "iso:country":"US",
    "sg:address":"308 N Teel Dr",
    "sg:city":"Devine",
    "sg:classifiers":[
        {
            "category":"Freight",
            "type":"Transportation"
        }
    ],
    "sg:phone":"+1 830 663 4798",
    "sg:postcode":"78016",
    "sg:province":"TX",
    "sg:tags":[
        "commercial",
        "storage"
    ],
    "wof:name":"Bargain Center Mini Storage",
    "wof:placetype":"venue"
},
  "geometry": {"coordinates":[-98.903645,29.14307],"type":"Point"}
}