{
  "type": "Feature",
  "properties": {
    "iso:country":"US",
    "sg:address":"8750 N Central Expy Ste 1070",
    "sg:city":"Dallas",
    "sg:classifiers":[
        {
            "category":"Professional",
            "subcategory":"Lawyer & Legal Services",
            "type":"Services"
        }
    ],
    "sg:phone":"+1 214 987 0660",
    "sg:postcode":"75231",
    "sg:province":"TX",
    "wof:name":"Ashcraft Law Firm",
    "wof:placetype":"venue"
},
  "geometry": {"coordinates":[-96.769699,32.869301],"type":"Point"}
}