{
  "type": "Feature",
  "properties": {
    "iso:country":"US",
    "sg:address":"4262 S Kirkwood Rd",
    "sg:city":"Houston",
    "sg:classifiers":[
        {
            "category":"Retail",
            "subcategory":"Laundry & Dry Cleaning",
            "type":"Services"
        }
    ],
    "sg:phone":"+1 281 933 4474",
    "sg:postcode":"77072",
    "sg:province":"TX",
    "sg:tags":[
        "drycleaning",
        "plant"
    ],
    "wof:name":"Gucci Cleaners",
    "wof:placetype":"venue"
},
  "geometry": {"coordinates":[-95.587991,29.711896],"type":"Point"}
}