{
  "type": "Feature",
  "properties": {
    "iso:country":"US",
    "sg:address":"11221 Market St",
    "sg:city":"Houston",
    "sg:classifiers":[
        {
            "category":"Retail",
            "subcategory":"Repair Shop",
            "type":"Services"
        }
    ],
    "sg:phone":"+1 713 451 4958",
    "sg:postcode":"77029",
    "sg:province":"TX",
    "sg:tags":[
        "refrigeration",
        "appliance"
    ],
    "wof:name":"Pena Refrigeration Inc",
    "wof:placetype":"venue"
},
  "geometry": {"coordinates":[-95.23281299999999,29.767702],"type":"Point"}
}