{
  "type": "Feature",
  "properties": {
    "iso:country":"US",
    "sg:address":"7845 Lettie St",
    "sg:city":"Houston",
    "sg:classifiers":[
        {
            "category":"Autos & Motor Vehicles",
            "subcategory":"Auto Supplies",
            "type":"Retail Goods"
        },
        {
            "category":"Retail",
            "subcategory":"Auto Repair",
            "type":"Services"
        }
    ],
    "sg:phone":"+1 713 987 2111",
    "sg:postcode":"77075",
    "sg:province":"TX",
    "sg:tags":[
        "body",
        "shop",
        "glass"
    ],
    "wof:name":"ABC Auto & Hot Rod Heaven",
    "wof:placetype":"venue"
},
  "geometry": {"coordinates":[-95.283096,29.604799],"type":"Point"}
}