{
  "type": "Feature",
  "properties": {
    "iso:country":"US",
    "sg:address":"984 S Weatherred Dr",
    "sg:city":"Richardson",
    "sg:classifiers":[
        {
            "category":"Professional",
            "type":"Services"
        }
    ],
    "sg:phone":"+1 972 907 9434",
    "sg:postcode":"75080",
    "sg:province":"TX",
    "wof:name":"Mary Gail McDonald",
    "wof:placetype":"venue"
},
  "geometry": {"coordinates":[-96.751531,32.941395],"type":"Point"}
}