{
  "type": "Feature",
  "properties": {
    "iso:country":"US",
    "sg:address":"1325 US Hwy 77X Bus",
    "sg:city":"Harlingen",
    "sg:classifiers":[
        {
            "category":"Retail",
            "subcategory":"Portrait Studio",
            "type":"Services"
        }
    ],
    "sg:phone":"+1 956 421 4472",
    "sg:postcode":"78550",
    "sg:province":"TX",
    "sg:tags":[
        "photo"
    ],
    "wof:name":"Benavides Photography",
    "wof:placetype":"venue"
},
  "geometry": {"coordinates":[-97.68974300000001,26.205493],"type":"Point"}
}