{
  "type": "Feature",
  "properties": {
    "iso:country":"US",
    "sg:address":"713 Sawdust Rd",
    "sg:city":"Spring",
    "sg:classifiers":[
        {
            "category":"Retail",
            "subcategory":"Auto Repair",
            "type":"Services"
        }
    ],
    "sg:phone":"+1 281 367 0645",
    "sg:postcode":"77380",
    "sg:province":"TX",
    "sg:tags":[
        "automotive",
        "complete"
    ],
    "wof:name":"Midas Muffler",
    "wof:placetype":"venue"
},
  "geometry": {"coordinates":[-95.45698899999999,30.126694],"type":"Point"}
}