{
  "type": "Feature",
  "properties": {
    "iso:country":"US",
    "sg:address":"1418 South St",
    "sg:city":"Nacogdoches",
    "sg:classifiers":[
        {
            "category":"Autos & Motor Vehicles",
            "subcategory":"Auto Supplies",
            "type":"Retail Goods"
        },
        {
            "category":"Wholesale",
            "subcategory":"Auto Parts",
            "type":"Manufacturing & Wholesale Goods"
        }
    ],
    "sg:phone":"+1 936 564 2185",
    "sg:postcode":"75964",
    "sg:province":"TX",
    "sg:tags":[
        "repair",
        "rebuilt",
        "used",
        "automobile",
        "automotive"
    ],
    "wof:name":"Alternator Services Co",
    "wof:placetype":"venue"
},
  "geometry": {"coordinates":[-94.664576,31.593642],"type":"Point"}
}