{
  "type": "Feature",
  "properties": {
    "iso:country":"US",
    "sg:address":"4040 Broadway",
    "sg:city":"San Antonio",
    "sg:classifiers":[
        {
            "category":"Wholesale",
            "subcategory":"Groceries",
            "type":"Manufacturing & Wholesale Goods"
        }
    ],
    "sg:phone":"+1 210 824 0090",
    "sg:postcode":"78209",
    "sg:province":"TX",
    "sg:tags":[
        "food",
        "to",
        "manufacturer"
    ],
    "wof:name":"Sinoveg International",
    "wof:placetype":"venue"
},
  "geometry": {"coordinates":[-98.465498,29.462824],"type":"Point"}
}