{
  "type": "Feature",
  "properties": {
    "iso:country":"US",
    "sg:address":"2912 N Macarthur Blvd Suite 100",
    "sg:city":"Irving",
    "sg:classifiers":[
        {
            "category":"Insurance",
            "subcategory":"Hazard Insurance",
            "type":"Services"
        },
        {
            "category":"Insurance",
            "subcategory":"Insurance Agent",
            "type":"Services"
        },
        {
            "category":"Insurance",
            "subcategory":"Life Insurance",
            "type":"Services"
        }
    ],
    "sg:phone":"+1 972 791 8803",
    "sg:postcode":"75062",
    "sg:province":"TX",
    "sg:tags":[
        "auto",
        "renter"
    ],
    "sg:website":"http://statefarm.mqgroup.com/url.asp?usr=437960",
    "wof:name":"Taylor, Lyndon - State Farm Insurance Agent",
    "wof:placetype":"venue"
},
  "geometry": {"coordinates":[-96.959023,32.846458],"type":"Point"}
}