{
  "type": "Feature",
  "properties": {
    "iso:country":"US",
    "sg:address":"3142 Brincrest Dr",
    "sg:city":"Dallas",
    "sg:classifiers":[
        {
            "category":"Retail",
            "subcategory":"Auto Repair",
            "type":"Services"
        }
    ],
    "sg:phone":"+1 972 406 0625",
    "sg:postcode":"75234",
    "sg:province":"TX",
    "sg:tags":[
        "windshield"
    ],
    "wof:name":"Mpact Windshield Repair",
    "wof:placetype":"venue"
},
  "geometry": {"coordinates":[-96.871714,32.9179],"type":"Point"}
}