{
  "type": "Feature",
  "properties": {
    "iso:country":"US",
    "sg:address":"601 Elm St",
    "sg:city":"Graham",
    "sg:classifiers":[
        {
            "category":"Professional",
            "type":"Services"
        },
        {
            "category":"Mining & Drilling",
            "type":"Manufacturing & Wholesale Goods"
        }
    ],
    "sg:phone":"+1 940 521 0785",
    "sg:postcode":"76450",
    "sg:province":"TX",
    "sg:tags":[
        "field",
        "oil"
    ],
    "wof:name":"A & C Petroleum Landman Svc",
    "wof:placetype":"venue"
},
  "geometry": {"coordinates":[-98.589562,33.105888],"type":"Point"}
}