{
  "type": "Feature",
  "properties": {
    "iso:country":"US",
    "sg:address":"1801 North St",
    "sg:city":"Beaumont",
    "sg:classifiers":[
        {
            "category":"Retail",
            "subcategory":"Repair Shop",
            "type":"Services"
        }
    ],
    "sg:phone":"+1 409 833 7490",
    "sg:postcode":"77701",
    "sg:province":"TX",
    "sg:tags":[
        "upholsterer"
    ],
    "wof:name":"O & J Upholstery Car Detailing",
    "wof:placetype":"venue"
},
  "geometry": {"coordinates":[-94.11462400000001,30.087888],"type":"Point"}
}