{
  "type": "Feature",
  "properties": {
    "iso:country":"US",
    "sg:address":"311 N Stemmons Fwy",
    "sg:city":"Dallas",
    "sg:classifiers":[
        {
            "category":"Professional",
            "subcategory":"Lawyer & Legal Services",
            "type":"Services"
        }
    ],
    "sg:phone":"+1 214 744 0401",
    "sg:postcode":"75207",
    "sg:province":"TX",
    "wof:name":"Teter Law Firm",
    "wof:placetype":"venue"
},
  "geometry": {"coordinates":[-96.812515,32.781873],"type":"Point"}
}