{
  "type": "Feature",
  "properties": {
    "iso:country":"US",
    "sg:address":"5024 E 5th St",
    "sg:city":"Katy",
    "sg:classifiers":[
        {
            "category":"Real Estate",
            "subcategory":"Real Estate Agent",
            "type":"Services"
        }
    ],
    "sg:phone":"+1 281 391 2050",
    "sg:postcode":"77493",
    "sg:province":"TX",
    "wof:name":"Stout & Associates",
    "wof:placetype":"venue"
},
  "geometry": {"coordinates":[-95.80340200000001,29.789994],"type":"Point"}
}