{
  "type": "Feature",
  "properties": {
    "iso:country":"US",
    "sg:address":"1809 Geneva Ln",
    "sg:city":"Plano",
    "sg:classifiers":[
        {
            "category":"Shopping",
            "subcategory":"Used Merchandise",
            "type":"Retail Goods"
        }
    ],
    "sg:phone":"+1 972 423 2410",
    "sg:postcode":"75075",
    "sg:province":"TX",
    "wof:name":"Laquinta Village Antique",
    "wof:placetype":"venue"
},
  "geometry": {"coordinates":[-96.727626,33.023483],"type":"Point"}
}