{
  "type": "Feature",
  "properties": {
    "iso:country":"US",
    "sg:address":"9025 Diana Dr",
    "sg:city":"El Paso",
    "sg:classifiers":[
        {
            "category":"Organizations",
            "subcategory":"Religious Organization",
            "type":"Services"
        }
    ],
    "sg:phone":"+1 915 755 7658",
    "sg:postcode":"79904",
    "sg:province":"TX",
    "sg:tags":[
        "church"
    ],
    "wof:name":"Blessed Sacrament Church",
    "wof:placetype":"venue"
},
  "geometry": {"coordinates":[-106.423309,31.868792],"type":"Point"}
}