{
  "type": "Feature",
  "properties": {
    "iso:country":"US",
    "sg:address":"1814 Salford Dr",
    "sg:city":"Houston",
    "sg:classifiers":[
        {
            "category":"Professional",
            "subcategory":"Business Services",
            "type":"Services"
        }
    ],
    "sg:phone":"+1 713 862 7673",
    "sg:postcode":"77008",
    "sg:province":"TX",
    "wof:name":"Noel Bass Assoc Inc",
    "wof:placetype":"venue"
},
  "geometry": {"coordinates":[-95.445151,29.803584],"type":"Point"}
}