{
  "type": "Feature",
  "properties": {
    "iso:country":"US",
    "sg:address":"207 Kickapoo Trl",
    "sg:city":"Henderson",
    "sg:classifiers":[
        {
            "category":"Building & Trades",
            "subcategory":"Construction",
            "type":"Services"
        }
    ],
    "sg:phone":"+1 903 657 2374",
    "sg:postcode":"75652",
    "sg:province":"TX",
    "sg:tags":[
        "hanging",
        "contractor"
    ],
    "wof:name":"Knight Painting Contrg Ka",
    "wof:placetype":"venue"
},
  "geometry": {"coordinates":[-94.79373200000001,32.193102],"type":"Point"}
}