{
  "type": "Feature",
  "properties": {
    "iso:country":"US",
    "sg:address":"915 Sulphur St",
    "sg:city":"Houston",
    "sg:classifiers":[
        {
            "category":"Professional",
            "type":"Services"
        }
    ],
    "sg:phone":"+1 713 947 1204",
    "sg:postcode":"77034",
    "sg:province":"TX",
    "wof:name":"Hierberito Seafood",
    "wof:placetype":"venue"
},
  "geometry": {"coordinates":[-95.236985,29.64768],"type":"Point"}
}