{
  "type": "Feature",
  "properties": {
    "iso:country":"US",
    "sg:address":"810 E Van Buren St",
    "sg:city":"Brownsville",
    "sg:classifiers":[
        {
            "category":"Professional",
            "subcategory":"Detective & Security Services",
            "type":"Services"
        }
    ],
    "sg:phone":"+1 956 544 4726",
    "sg:postcode":"78520",
    "sg:province":"TX",
    "sg:tags":[
        "guard",
        "patrol"
    ],
    "wof:name":"Valley Wide Security",
    "wof:placetype":"venue"
},
  "geometry": {"coordinates":[-97.495576,25.907271],"type":"Point"}
}