{
  "type": "Feature",
  "properties": {
    "iso:country":"US",
    "sg:address":"1901 Bell St",
    "sg:city":"Amarillo",
    "sg:classifiers":[
        {
            "category":"Food & Beverages",
            "subcategory":"Groceries & Convenience Stores",
            "type":"Retail Goods"
        }
    ],
    "sg:phone":"+1 806 354 7196",
    "sg:postcode":"79106",
    "sg:province":"TX",
    "sg:website":"www.tootntotum.com",
    "wof:name":"Toot'n Totum Food Stores",
    "wof:placetype":"venue"
},
  "geometry": {"coordinates":[-101.902361,35.191216],"type":"Point"}
}