{
  "type": "Feature",
  "properties": {
    "iso:country":"US",
    "sg:address":"5706 Pioneer Ridge Ct",
    "sg:city":"Sugar Land",
    "sg:classifiers":[
        {
            "category":"Building & Trades",
            "subcategory":"Construction",
            "type":"Services"
        }
    ],
    "sg:phone":"+1 713 272 7226",
    "sg:postcode":"77479",
    "sg:province":"TX",
    "sg:tags":[
        "house"
    ],
    "wof:name":"Fran Kev Homes",
    "wof:placetype":"venue"
},
  "geometry": {"coordinates":[-95.677891,29.579994],"type":"Point"}
}