{
  "type": "Feature",
  "properties": {
    "iso:country":"US",
    "sg:address":"1605 Blake Dr",
    "sg:city":"Richardson",
    "sg:classifiers":[
        {
            "category":"Freight",
            "type":"Transportation"
        }
    ],
    "sg:phone":"+1 214 236 0329",
    "sg:postcode":"75081",
    "sg:province":"TX",
    "sg:tags":[
        "cargo",
        "handler",
        "marine"
    ],
    "wof:name":"G&C Services",
    "wof:placetype":"venue"
},
  "geometry": {"coordinates":[-96.692846,32.964206],"type":"Point"}
}