{
  "type": "Feature",
  "properties": {
    "iso:country":"US",
    "sg:address":"2901 S 5th St",
    "sg:city":"Garland",
    "sg:classifiers":[
        {
            "category":"Personal",
            "type":"Services"
        }
    ],
    "sg:phone":"+1 214 227 5374",
    "sg:postcode":"75041",
    "sg:province":"TX",
    "wof:name":"Nutri Kwik 1",
    "wof:placetype":"venue"
},
  "geometry": {"coordinates":[-96.63360299999999,32.882041],"type":"Point"}
}