{
  "type": "Feature",
  "properties": {
    "iso:country":"US",
    "sg:address":"8332 Paluxy Dr",
    "sg:city":"Tyler",
    "sg:classifiers":[
        {
            "category":"Freight",
            "type":"Transportation"
        }
    ],
    "sg:phone":"+1 903 534 6014",
    "sg:postcode":"75703",
    "sg:province":"TX",
    "wof:name":"Judi's Carrier",
    "wof:placetype":"venue"
},
  "geometry": {"coordinates":[-95.27925,32.264535],"type":"Point"}
}