{
  "type": "Feature",
  "properties": {
    "iso:country":"US",
    "sg:address":"500 E 4th St 8th Fl",
    "sg:city":"Austin",
    "sg:classifiers":[
        {
            "category":"Personal",
            "subcategory":"Day Spa",
            "type":"Services"
        }
    ],
    "sg:phone":"+1 512 493 4903",
    "sg:postcode":"78701",
    "sg:province":"TX",
    "sg:website":"www.hilton.com/en/hi/hotels/hote...",
    "wof:name":"Tower Health Club & Spa",
    "wof:placetype":"venue"
},
  "geometry": {"coordinates":[-97.738623,30.265065],"type":"Point"}
}