{
  "type": "Feature",
  "properties": {
    "iso:country":"US",
    "sg:address":"121 N Tone Ave",
    "sg:city":"Denison",
    "sg:classifiers":[
        {
            "category":"Retail",
            "subcategory":"Animal Services",
            "type":"Services"
        }
    ],
    "sg:phone":"+1 903 465 8122",
    "sg:postcode":"75020",
    "sg:province":"TX",
    "sg:tags":[
        "pet",
        "grooming"
    ],
    "wof:name":"Big Dog Little Dog",
    "wof:placetype":"venue"
},
  "geometry": {"coordinates":[-96.55079600000001,33.756033],"type":"Point"}
}