{
  "type": "Feature",
  "properties": {
    "iso:country":"US",
    "sg:address":"502 E 6th St",
    "sg:city":"Austin",
    "sg:classifiers":[
        {
            "category":"Food & Beverages",
            "subcategory":"Groceries & Convenience Stores",
            "type":"Retail Goods"
        }
    ],
    "sg:phone":"+1 512 476 2015",
    "sg:postcode":"78701",
    "sg:province":"TX",
    "wof:name":"Lonestar Souviner & Food Mart",
    "wof:placetype":"venue"
},
  "geometry": {"coordinates":[-97.73819399999999,30.266915],"type":"Point"}
}