{
  "type": "Feature",
  "properties": {
    "iso:country":"US",
    "sg:address":"217 Pershing Ave",
    "sg:city":"San Antonio",
    "sg:classifiers":[
        {
            "category":"Education",
            "subcategory":"School",
            "type":"Public Place"
        }
    ],
    "sg:phone":"+1 210 822 0461",
    "sg:postcode":"78209",
    "sg:province":"TX",
    "sg:tags":[
        "child",
        "day",
        "care"
    ],
    "wof:name":"Circle School",
    "wof:placetype":"venue"
},
  "geometry": {"coordinates":[-98.465289,29.461267],"type":"Point"}
}