{
  "type": "Feature",
  "properties": {
    "iso:country":"US",
    "sg:address":"1506 Shadow Crest Dr",
    "sg:city":"Corinth",
    "sg:classifiers":[
        {
            "category":"Professional",
            "subcategory":"Business Services",
            "type":"Services"
        }
    ],
    "sg:phone":"+1 940 497 3966",
    "sg:postcode":"76210",
    "sg:province":"TX",
    "sg:tags":[
        "consultant",
        "coach"
    ],
    "wof:name":"Gentech Consulting",
    "wof:placetype":"venue"
},
  "geometry": {"coordinates":[-97.074798,33.158966],"type":"Point"}
}