{
  "type": "Feature",
  "properties": {
    "iso:country":"US",
    "sg:address":"11242 Hillgreen Dr",
    "sg:city":"Conroe",
    "sg:classifiers":[
        {
            "category":"Building & Trades",
            "subcategory":"Construction",
            "type":"Services"
        }
    ],
    "sg:phone":"+1 936 264 3269",
    "sg:postcode":"77303",
    "sg:province":"TX",
    "sg:tags":[
        "contractor"
    ],
    "wof:name":"Shelly Remodeling",
    "wof:placetype":"venue"
},
  "geometry": {"coordinates":[-95.404234,30.336668],"type":"Point"}
}