{
  "type": "Feature",
  "properties": {
    "iso:country":"US",
    "sg:address":"4213 Frontier Trl",
    "sg:city":"Killeen",
    "sg:classifiers":[
        {
            "category":"Home & Garden",
            "subcategory":"Garden Supply",
            "type":"Retail Goods"
        }
    ],
    "sg:phone":"+1 254 290 4978",
    "sg:postcode":"76542",
    "sg:province":"TX",
    "sg:tags":[
        "sprinkler"
    ],
    "wof:name":"Every Green Lawn Care",
    "wof:placetype":"venue"
},
  "geometry": {"coordinates":[-97.70564400000001,31.06497],"type":"Point"}
}