{
  "type": "Feature",
  "properties": {
    "iso:country":"US",
    "sg:address":"3807 Judson Rd",
    "sg:city":"Longview",
    "sg:classifiers":[
        {
            "category":"Building & Trades",
            "subcategory":"Construction",
            "type":"Services"
        }
    ],
    "sg:phone":"+1 903 663 3549",
    "sg:postcode":"75605",
    "sg:province":"TX",
    "sg:tags":[
        "home",
        "builder"
    ],
    "wof:name":"Choice Homes",
    "wof:placetype":"venue"
},
  "geometry": {"coordinates":[-94.751881,32.556735],"type":"Point"}
}