{
  "type": "Feature",
  "properties": {
    "iso:country":"US",
    "sg:address":"1005 High Cotton Ln",
    "sg:city":"Rockwall",
    "sg:classifiers":[
        {
            "category":"Wholesale",
            "subcategory":"Electrical",
            "type":"Manufacturing & Wholesale Goods"
        }
    ],
    "sg:phone":"+1 972 771 7568",
    "sg:postcode":"75087",
    "sg:province":"TX",
    "sg:tags":[
        "repair",
        "electronic"
    ],
    "wof:name":"J-4 Communications Inc",
    "wof:placetype":"venue"
},
  "geometry": {"coordinates":[-96.44996500000001,32.936908],"type":"Point"}
}