{
  "type": "Feature",
  "properties": {
    "iso:country":"US",
    "sg:address":"850 E Central Pkwy",
    "sg:city":"Plano",
    "sg:classifiers":[
        {
            "category":"Health Services",
            "subcategory":"Clinic",
            "type":"Services"
        }
    ],
    "sg:phone":"+1 972 422 1375",
    "sg:postcode":"75074",
    "sg:province":"TX",
    "sg:tags":[
        "home"
    ],
    "wof:name":"REACHOUT Home Care",
    "wof:placetype":"venue"
},
  "geometry": {"coordinates":[-96.70390999999999,33.028853],"type":"Point"}
}