{
  "type": "Feature",
  "properties": {
    "iso:country":"US",
    "sg:address":"203 W Wall St",
    "sg:city":"Midland",
    "sg:classifiers":[
        {
            "category":"Shopping",
            "subcategory":"Jewelry",
            "type":"Retail Goods"
        }
    ],
    "sg:phone":"+1 432 683 4411",
    "sg:postcode":"79701",
    "sg:province":"TX",
    "sg:tags":[
        "jeweler"
    ],
    "wof:name":"Cristiani S Jewelers",
    "wof:placetype":"venue"
},
  "geometry": {"coordinates":[-102.076804,31.997386],"type":"Point"}
}