{
  "type": "Feature",
  "properties": {
    "iso:country":"US",
    "sg:address":"101 W Mesquite",
    "sg:city":"Granger",
    "sg:classifiers":[
        {
            "category":"Professional",
            "subcategory":"Management & Consulting",
            "type":"Services"
        }
    ],
    "sg:phone":"+1 512 859 2676",
    "sg:postcode":"76530",
    "sg:province":"TX",
    "sg:tags":[
        "farm"
    ],
    "wof:name":"Joe Shirocky",
    "wof:placetype":"venue"
},
  "geometry": {"coordinates":[-97.443871,30.71567],"type":"Point"}
}