{
  "type": "Feature",
  "properties": {
    "iso:country":"US",
    "sg:address":"1010 S Main St",
    "sg:city":"Shamrock",
    "sg:classifiers":[
        {
            "category":"Health Services",
            "subcategory":"Hospital",
            "type":"Services"
        }
    ],
    "sg:phone":"+1 806 256 5148",
    "sg:postcode":"79079",
    "sg:province":"TX",
    "sg:tags":[
        "general"
    ],
    "wof:name":"Family Care Clinic",
    "wof:placetype":"venue"
},
  "geometry": {"coordinates":[-100.24910199999999,35.199565],"type":"Point"}
}