{
  "type": "Feature",
  "properties": {
    "iso:country":"US",
    "sg:address":"2531 Chestnut Ridge Dr",
    "sg:city":"Humble",
    "sg:classifiers":[
        {
            "category":"Food & Beverages",
            "subcategory":"Groceries & Convenience Stores",
            "type":"Retail Goods"
        }
    ],
    "sg:phone":"+1 281 358 9215",
    "sg:postcode":"77339",
    "sg:province":"TX",
    "wof:name":"Circle K Store",
    "wof:placetype":"venue"
},
  "geometry": {"coordinates":[-95.240769,30.048784],"type":"Point"}
}