{
  "type": "Feature",
  "properties": {
    "iso:country":"US",
    "sg:address":"2311 Balsam Dr",
    "sg:city":"Arlington",
    "sg:classifiers":[
        {
            "category":"Professional",
            "type":"Services"
        }
    ],
    "sg:phone":"+1 817 368 0538",
    "sg:postcode":"76006",
    "sg:province":"TX",
    "wof:name":"Wiar",
    "wof:placetype":"venue"
},
  "geometry": {"coordinates":[-97.067798,32.771934],"type":"Point"}
}