{
  "type": "Feature",
  "properties": {
    "iso:country":"US",
    "sg:address":"6110 Rain Cloud Dr",
    "sg:city":"San Antonio",
    "sg:classifiers":[
        {
            "category":"Professional",
            "type":"Services"
        }
    ],
    "sg:phone":"+1 210 684 5162",
    "sg:postcode":"78238",
    "sg:province":"TX",
    "wof:name":"Kc Handyman Svcs",
    "wof:placetype":"venue"
},
  "geometry": {"coordinates":[-98.608611,29.473687],"type":"Point"}
}