{
  "type": "Feature",
  "properties": {
    "iso:country":"US",
    "sg:address":"1930 Webster St",
    "sg:city":"San Angelo",
    "sg:classifiers":[
        {
            "category":"Professional",
            "subcategory":"Business Services",
            "type":"Services"
        }
    ],
    "sg:phone":"+1 325 949 3415",
    "sg:postcode":"76901",
    "sg:province":"TX",
    "wof:name":"Sara R Hasty",
    "wof:placetype":"venue"
},
  "geometry": {"coordinates":[-100.47034499999999,31.463507],"type":"Point"}
}