{
  "type": "Feature",
  "properties": {
    "iso:country":"US",
    "sg:address":"812 Justin Ln",
    "sg:city":"Austin",
    "sg:classifiers":[
        {
            "category":"Professional",
            "subcategory":"Computer Services",
            "type":"Services"
        }
    ],
    "sg:phone":"+1 512 451 1716",
    "sg:postcode":"78757",
    "sg:province":"TX",
    "sg:tags":[
        "fiber",
        "cabling",
        "datum",
        "contractor",
        "voice",
        "optics"
    ],
    "wof:name":"Convergence Cabling",
    "wof:placetype":"venue"
},
  "geometry": {"coordinates":[-97.721355,30.337682],"type":"Point"}
}