{
  "type": "Feature",
  "properties": {
    "iso:country":"US",
    "sg:address":"422 Blanco St",
    "sg:city":"Duncanville",
    "sg:classifiers":[
        {
            "category":"Professional",
            "subcategory":"Business Services",
            "type":"Services"
        }
    ],
    "sg:phone":"+1 972 283 1328",
    "sg:postcode":"75137",
    "sg:province":"TX",
    "wof:name":"Bateman Technologies",
    "wof:placetype":"venue"
},
  "geometry": {"coordinates":[-96.901011,32.636293],"type":"Point"}
}