{
  "type": "Feature",
  "properties": {
    "iso:country":"US",
    "sg:address":"800 N Sumner St",
    "sg:city":"Pampa",
    "sg:classifiers":[
        {
            "category":"Health Services",
            "subcategory":"Clinic",
            "type":"Services"
        }
    ],
    "sg:phone":"+1 806 665 6677",
    "sg:postcode":"79065",
    "sg:province":"TX",
    "sg:tags":[
        "hospital",
        "specialty"
    ],
    "wof:name":"Baptist Saint Anthy Hlth Care",
    "wof:placetype":"venue"
},
  "geometry": {"coordinates":[-100.97526000000001,35.541165],"type":"Point"}
}