{
  "type": "Feature",
  "properties": {
    "iso:country":"US",
    "sg:address":"1512 Big Meadow Dr",
    "sg:city":"Cedar Park",
    "sg:classifiers":[
        {
            "category":"Shopping",
            "subcategory":"Bicycles & Sporting Goods",
            "type":"Retail Goods"
        }
    ],
    "sg:phone":"+1 512 845 7621",
    "sg:postcode":"78613",
    "sg:province":"TX",
    "wof:name":"Wadesworld 300",
    "wof:placetype":"venue"
},
  "geometry": {"coordinates":[-97.82228499999999,30.470713],"type":"Point"}
}