{
  "type": "Feature",
  "properties": {
    "iso:country":"US",
    "sg:address":"13902 Hawksnest Bay Dr",
    "sg:city":"Corpus Christi",
    "sg:classifiers":[
        {
            "category":"Real Estate",
            "subcategory":"Real Estate Agent",
            "type":"Services"
        }
    ],
    "sg:phone":"+1 361 949 1166",
    "sg:postcode":"78418",
    "sg:province":"TX",
    "wof:name":"Rhoco Real Estate Inspection",
    "wof:placetype":"venue"
},
  "geometry": {"coordinates":[-97.231432,27.593358],"type":"Point"}
}