{
  "type": "Feature",
  "properties": {
    "iso:country":"US",
    "sg:address":"612 N Johnson St",
    "sg:city":"Alice",
    "sg:classifiers":[
        {
            "category":"Personal",
            "subcategory":"Beauty Salon",
            "type":"Services"
        }
    ],
    "sg:phone":"+1 361 396 0169",
    "sg:postcode":"78332",
    "sg:province":"TX",
    "wof:name":"Unique Transformations Salon",
    "wof:placetype":"venue"
},
  "geometry": {"coordinates":[-98.08248500000001,27.757078],"type":"Point"}
}