{
  "type": "Feature",
  "properties": {
    "iso:country":"US",
    "sg:address":"7503 S Kirkwood Rd",
    "sg:city":"Houston",
    "sg:classifiers":[
        {
            "category":"Food & Beverages",
            "subcategory":"Groceries & Convenience Stores",
            "type":"Retail Goods"
        }
    ],
    "sg:phone":"+1 281 933 5573",
    "sg:postcode":"77072",
    "sg:province":"TX",
    "wof:name":"One Stop Food Store",
    "wof:placetype":"venue"
},
  "geometry": {"coordinates":[-95.58768499999999,29.695586],"type":"Point"}
}