{
  "type": "Feature",
  "properties": {
    "iso:country":"US",
    "sg:address":"11309 Sagedowne Ln",
    "sg:city":"Houston",
    "sg:classifiers":[
        {
            "category":"Education",
            "subcategory":"School",
            "type":"Public Place"
        }
    ],
    "sg:phone":"+1 281 929 3850",
    "sg:postcode":"77089",
    "sg:province":"TX",
    "wof:name":"George A Thompson Interm Sch",
    "wof:placetype":"venue"
},
  "geometry": {"coordinates":[-95.214996,29.594846],"type":"Point"}
}