{
  "type": "Feature",
  "properties": {
    "iso:country":"US",
    "sg:address":"105 E Main St",
    "sg:city":"Rocksprings",
    "sg:classifiers":[
        {
            "category":"Travel",
            "subcategory":"Hotels & Motels",
            "type":"Entertainment"
        }
    ],
    "sg:phone":"+1 830 683 3241",
    "sg:postcode":"78880",
    "sg:province":"TX",
    "wof:name":"Mesa Motel",
    "wof:placetype":"venue"
},
  "geometry": {"coordinates":[-100.206718,30.015739],"type":"Point"}
}