{
  "type": "Feature",
  "properties": {
    "iso:country":"US",
    "sg:address":"3300 Shepherd Ln",
    "sg:city":"Mesquite",
    "sg:classifiers":[
        {
            "category":"Building & Trades",
            "subcategory":"Locksmith",
            "type":"Services"
        }
    ],
    "sg:phone":"+1 972 286 8955",
    "sg:postcode":"75180",
    "sg:province":"TX",
    "sg:tags":[
        "lock",
        "industrial",
        "key",
        "locksmiths-commercial"
    ],
    "wof:name":"Key Services",
    "wof:placetype":"venue"
},
  "geometry": {"coordinates":[-96.614082,32.724689],"type":"Point"}
}