{
  "type": "Feature",
  "properties": {
    "iso:country":"US",
    "sg:address":"18714 Denise Dale Ln",
    "sg:city":"Houston",
    "sg:classifiers":[
        {
            "category":"Building & Trades",
            "subcategory":"Construction",
            "type":"Services"
        }
    ],
    "sg:phone":"+1 281 599 0059",
    "sg:postcode":"77084",
    "sg:province":"TX",
    "sg:tags":[
        "house"
    ],
    "wof:name":"Primeau Home Repair",
    "wof:placetype":"venue"
},
  "geometry": {"coordinates":[-95.691298,29.827395],"type":"Point"}
}