{
  "type": "Feature",
  "properties": {
    "iso:country":"US",
    "sg:address":"300 W. 6th St Suite 1910",
    "sg:city":"Austin",
    "sg:classifiers":[
        {
            "category":"Professional",
            "subcategory":"Advertising",
            "type":"Services"
        }
    ],
    "sg:phone":"+1 512 814 5858",
    "sg:postcode":"78701",
    "sg:province":"TX",
    "sg:tags":[
        "marketing"
    ],
    "sg:website":"www.blueline-strategies.com",
    "wof:name":"BlueLine Strategies, LLC",
    "wof:placetype":"venue"
},
  "geometry": {"coordinates":[-97.745576,30.269631],"type":"Point"}
}