{
  "type": "Feature",
  "properties": {
    "iso:country":"US",
    "sg:address":"1200 Wallace Blvd",
    "sg:city":"Amarillo",
    "sg:classifiers":[
        {
            "category":"Health Services",
            "subcategory":"Doctor",
            "type":"Services"
        }
    ],
    "sg:phone":"+1 806 351 4152",
    "sg:postcode":"79106",
    "sg:province":"TX",
    "sg:tags":[
        "clinic"
    ],
    "wof:name":"Northwest Texas Wound Care Ctr",
    "wof:placetype":"venue"
},
  "geometry": {"coordinates":[-101.91602399999999,35.200633],"type":"Point"}
}