{
  "type": "Feature",
  "properties": {
    "iso:country":"US",
    "sg:address":"3044 Eastman Rd",
    "sg:city":"Longview",
    "sg:classifiers":[
        {
            "category":"Travel",
            "subcategory":"Hotels & Motels",
            "type":"Entertainment"
        }
    ],
    "sg:phone":"+1 903 663 8670",
    "sg:postcode":"75605",
    "sg:province":"TX",
    "sg:website":"http://hamptoninn1.hilton.com/",
    "wof:name":"Hampton Inn Longview North",
    "wof:placetype":"venue"
},
  "geometry": {"coordinates":[-94.722343,32.532694],"type":"Point"}
}