{
  "type": "Feature",
  "properties": {
    "iso:country":"US",
    "sg:address":"17311 Dallas Pkwy Ste 200",
    "sg:city":"Dallas",
    "sg:classifiers":[
        {
            "category":"Building & Trades",
            "subcategory":"Construction",
            "type":"Services"
        }
    ],
    "sg:phone":"+1 972 250 2727",
    "sg:postcode":"75248",
    "sg:province":"TX",
    "sg:tags":[
        "contractor"
    ],
    "wof:name":"Dal-Tech Construction Inc",
    "wof:placetype":"venue"
},
  "geometry": {"coordinates":[-96.8283,32.985802],"type":"Point"}
}