{
  "type": "Feature",
  "properties": {
    "iso:country":"US",
    "sg:address":"4100 Andys Ln",
    "sg:city":"Allen",
    "sg:classifiers":[
        {
            "category":"Building & Trades",
            "subcategory":"Construction",
            "type":"Services"
        }
    ],
    "sg:phone":"+1 972 442 7661",
    "sg:postcode":"75002",
    "sg:province":"TX",
    "sg:tags":[
        "general",
        "contractor"
    ],
    "wof:name":"Romine Construction",
    "wof:placetype":"venue"
},
  "geometry": {"coordinates":[-96.608661,33.057069],"type":"Point"}
}