{
  "type": "Feature",
  "properties": {
    "iso:country":"US",
    "sg:address":"292 Hubertus Rd",
    "sg:city":"New Braunfels",
    "sg:classifiers":[
        {
            "category":"Autos & Motor Vehicles",
            "subcategory":"Automobile Sales",
            "type":"Retail Goods"
        }
    ],
    "sg:phone":"+1 830 609 6608",
    "sg:postcode":"78132",
    "sg:province":"TX",
    "sg:tags":[
        "truck"
    ],
    "wof:name":"Eagle Diesel",
    "wof:placetype":"venue"
},
  "geometry": {"coordinates":[-98.242159,29.630275],"type":"Point"}
}