{
  "type": "Feature",
  "properties": {
    "iso:country":"US",
    "sg:address":"5357 Spicewood Ln",
    "sg:city":"Frisco",
    "sg:classifiers":[
        {
            "category":"Shopping",
            "subcategory":"Stationery & Office Supplies",
            "type":"Retail Goods"
        }
    ],
    "sg:phone":"+1 972 712 9484",
    "sg:postcode":"75034",
    "sg:province":"TX",
    "wof:name":"Jlh Gifts",
    "wof:placetype":"venue"
},
  "geometry": {"coordinates":[-96.82856,33.122112],"type":"Point"}
}