{
  "type": "Feature",
  "properties": {
    "iso:country":"US",
    "sg:address":"518 Hatfield Dr",
    "sg:city":"San Antonio",
    "sg:classifiers":[
        {
            "category":"Shopping",
            "subcategory":"Bicycles & Sporting Goods",
            "type":"Retail Goods"
        }
    ],
    "sg:phone":"+1 210 674 7299",
    "sg:postcode":"78227",
    "sg:province":"TX",
    "wof:name":"Cardenas Oralia",
    "wof:placetype":"venue"
},
  "geometry": {"coordinates":[-98.660479,29.396763],"type":"Point"}
}