{
  "type": "Feature",
  "properties": {
    "iso:country":"US",
    "sg:address":"3639 Gus Thomasson Rd",
    "sg:city":"Mesquite",
    "sg:classifiers":[
        {
            "category":"Shopping",
            "subcategory":"Music",
            "type":"Retail Goods"
        }
    ],
    "sg:phone":"+1 972 682 5826",
    "sg:postcode":"75150",
    "sg:province":"TX",
    "wof:name":"Alltime Partytime Music",
    "wof:placetype":"venue"
},
  "geometry": {"coordinates":[-96.634246,32.808539],"type":"Point"}
}