{
  "type": "Feature",
  "properties": {
    "iso:country":"US",
    "sg:address":"201 S Shore Dr",
    "sg:city":"Amarillo",
    "sg:classifiers":[
        {
            "category":"Building & Trades",
            "subcategory":"Electrical",
            "type":"Services"
        }
    ],
    "sg:phone":"+1 806 622 3888",
    "sg:postcode":"79118",
    "sg:province":"TX",
    "sg:tags":[
        "repair",
        "transformer",
        "oil",
        "electrical",
        "circuit"
    ],
    "wof:name":"Amarillo Electric Service",
    "wof:placetype":"venue"
},
  "geometry": {"coordinates":[-101.78465199999999,35.06004],"type":"Point"}
}