{
  "type": "Feature",
  "properties": {
    "iso:country":"US",
    "sg:address":"5818 Richmond Ave",
    "sg:city":"Houston",
    "sg:classifiers":[
        {
            "category":"Restaurant",
            "type":"Food & Drink"
        }
    ],
    "sg:phone":"+1 713 952 3576",
    "sg:postcode":"77057",
    "sg:province":"TX",
    "wof:name":"Family Eats LTD",
    "wof:placetype":"venue"
},
  "geometry": {"coordinates":[-95.481328,29.731593],"type":"Point"}
}