{
  "type": "Feature",
  "properties": {
    "iso:country":"US",
    "sg:address":"3737 Gateway Blvd W",
    "sg:city":"El Paso",
    "sg:classifiers":[
        {
            "category":"Wholesale",
            "subcategory":"Home Furnishings",
            "type":"Manufacturing & Wholesale Goods"
        }
    ],
    "sg:phone":"+1 915 562 9521",
    "sg:postcode":"79903",
    "sg:province":"TX",
    "sg:tags":[
        "carpet",
        "laying",
        "contractor"
    ],
    "wof:name":"Casa Crpets Tile Whl Dstrbters",
    "wof:placetype":"venue"
},
  "geometry": {"coordinates":[-106.447666,31.778185],"type":"Point"}
}