{
  "type": "Feature",
  "properties": {
    "iso:country":"US",
    "sg:address":"601 E San Antonio St",
    "sg:city":"Victoria",
    "sg:classifiers":[
        {
            "category":"Health Services",
            "subcategory":"Doctor",
            "type":"Services"
        }
    ],
    "sg:phone":"+1 361 572 9173",
    "sg:postcode":"77901",
    "sg:province":"TX",
    "sg:tags":[
        "physician",
        "surgeon"
    ],
    "wof:name":"Ana M Delgado MD",
    "wof:placetype":"venue"
},
  "geometry": {"coordinates":[-96.99734599999999,28.8077],"type":"Point"}
}