{
  "type": "Feature",
  "properties": {
    "iso:country":"US",
    "sg:address":"1609 Texas Ave S",
    "sg:city":"College Station",
    "sg:classifiers":[
        {
            "category":"Professional",
            "subcategory":"Accounting & Tax Preparation",
            "type":"Services"
        }
    ],
    "sg:phone":"+1 979 693 2739",
    "sg:postcode":"77840",
    "sg:province":"TX",
    "sg:tags":[
        "return"
    ],
    "wof:name":"H & R Block",
    "wof:placetype":"venue"
},
  "geometry": {"coordinates":[-96.31984,30.615903],"type":"Point"}
}