{
  "type": "Feature",
  "properties": {
    "iso:country":"US",
    "sg:address":"4200 Airport Fwy",
    "sg:city":"Fort Worth",
    "sg:classifiers":[
        {
            "category":"Professional",
            "subcategory":"Accounting & Tax Preparation",
            "type":"Services"
        }
    ],
    "sg:phone":"+1 817 831 3553",
    "sg:postcode":"76117",
    "sg:province":"TX",
    "sg:tags":[
        "accountant"
    ],
    "wof:name":"Estes & Assoc",
    "wof:placetype":"venue"
},
  "geometry": {"coordinates":[-97.286677,32.775016],"type":"Point"}
}