{
  "type": "Feature",
  "properties": {
    "iso:country":"US",
    "sg:address":"5217 Davis Blvd",
    "sg:city":"Fort Worth",
    "sg:classifiers":[
        {
            "category":"Professional",
            "subcategory":"Engineering",
            "type":"Services"
        }
    ],
    "sg:phone":"+1 817 656 0618",
    "sg:postcode":"76180",
    "sg:province":"TX",
    "wof:name":"Housing Engineers",
    "wof:placetype":"venue"
},
  "geometry": {"coordinates":[-97.21437899999999,32.84224],"type":"Point"}
}