{
  "type": "Feature",
  "properties": {
    "iso:country":"US",
    "sg:address":"1324 Wood Ave",
    "sg:city":"Woodsboro",
    "sg:classifiers":[
        {
            "category":"Place Of Worship",
            "subcategory":"Church",
            "type":"Public Place"
        },
        {
            "category":"Place Of Worship",
            "type":"Public Place"
        }
    ],
    "sg:phone":"+1 361 543 5453",
    "sg:postcode":"78393",
    "sg:province":"TX",
    "sg:tags":[
        "churches-interdenominational",
        "churches-various",
        "denomination"
    ],
    "wof:name":"Jehovah's Witnesses Woodsboro",
    "wof:placetype":"venue"
},
  "geometry": {"coordinates":[-97.314303,28.237448],"type":"Point"}
}