{
  "type": "Feature",
  "properties": {
    "iso:country":"US",
    "sg:address":"300 N King St",
    "sg:city":"Alice",
    "sg:classifiers":[
        {
            "category":"Home & Garden",
            "subcategory":"Building Materials",
            "type":"Retail Goods"
        }
    ],
    "sg:phone":"+1 361 664 7359",
    "sg:postcode":"78332",
    "sg:province":"TX",
    "sg:tags":[
        "glass",
        "window",
        "plate"
    ],
    "wof:name":"Hub City Glass Co Inc",
    "wof:placetype":"venue"
},
  "geometry": {"coordinates":[-98.07557799999999,27.754095],"type":"Point"}
}