{
  "type": "Feature",
  "properties": {
    "iso:country":"US",
    "sg:address":"1629 Central Expy",
    "sg:city":"Plano",
    "sg:classifiers":[
        {
            "category":"Shopping",
            "subcategory":"Hobbies, Toys, & Games",
            "type":"Retail Goods"
        }
    ],
    "sg:phone":"+1 972 516 1199",
    "sg:postcode":"75075",
    "sg:province":"TX",
    "wof:name":"Game X Change",
    "wof:placetype":"venue"
},
  "geometry": {"coordinates":[-96.71022600000001,33.0214],"type":"Point"}
}