{
  "type": "Feature",
  "properties": {
    "iso:country":"US",
    "sg:address":"1516 1st Ave",
    "sg:city":"Dallas",
    "sg:classifiers":[
        {
            "category":"Communications",
            "subcategory":"Radio Station",
            "type":"Services"
        }
    ],
    "sg:phone":"+1 214 670 8888",
    "sg:postcode":"75210",
    "sg:province":"TX",
    "sg:website":"www.wrr101.com",
    "wof:name":"WRR Classical 101.1 FM",
    "wof:placetype":"venue"
},
  "geometry": {"coordinates":[-96.760516,32.776626],"type":"Point"}
}