{
  "type": "Feature",
  "properties": {
    "iso:country":"US",
    "sg:address":"2616 Roberts Cut Off Rd",
    "sg:city":"Fort Worth",
    "sg:classifiers":[
        {
            "category":"Professional",
            "subcategory":"Computer Services",
            "type":"Services"
        }
    ],
    "sg:phone":"+1 469 775 7277",
    "sg:postcode":"76114",
    "sg:province":"TX",
    "sg:tags":[
        "datum"
    ],
    "wof:name":"David Rheaume",
    "wof:placetype":"venue"
},
  "geometry": {"coordinates":[-97.4119,32.800809],"type":"Point"}
}