{
  "type": "Feature",
  "properties": {
    "iso:country":"US",
    "sg:address":"7507 Blacksmith Ct",
    "sg:city":"Houston",
    "sg:classifiers":[
        {
            "category":"Home & Garden",
            "subcategory":"Home Furnishings",
            "type":"Retail Goods"
        }
    ],
    "sg:phone":"+1 713 937 3420",
    "sg:postcode":"77064",
    "sg:province":"TX",
    "wof:name":"Iwen Enterprises",
    "wof:placetype":"venue"
},
  "geometry": {"coordinates":[-95.502638,29.902276],"type":"Point"}
}