{
  "type": "Feature",
  "properties": {
    "iso:country":"US",
    "sg:address":"113 Laura Dr",
    "sg:city":"Mineola",
    "sg:classifiers":[
        {
            "category":"Shopping",
            "subcategory":"Antiques",
            "type":"Retail Goods"
        }
    ],
    "sg:phone":"+1 903 569 9464",
    "sg:postcode":"75773",
    "sg:province":"TX",
    "wof:name":"Rocking Chair Antiques",
    "wof:placetype":"venue"
},
  "geometry": {"coordinates":[-95.483857,32.681198],"type":"Point"}
}