{
  "type": "Feature",
  "properties": {
    "iso:country":"US",
    "sg:address":"5192 E I- 20",
    "sg:city":"Weatherford",
    "sg:classifiers":[
        {
            "category":"Building & Trades",
            "subcategory":"Construction",
            "type":"Services"
        }
    ],
    "sg:phone":"+1 972 489 5926",
    "sg:postcode":"76008",
    "sg:province":"TX",
    "sg:tags":[
        "general",
        "contractor"
    ],
    "wof:name":"A & W General Contractors",
    "wof:placetype":"venue"
},
  "geometry": {"coordinates":[-97.607021,32.729065],"type":"Point"}
}