{
  "type": "Feature",
  "properties": {
    "iso:country":"US",
    "sg:address":"15000 FM 2854",
    "sg:city":"Montgomery",
    "sg:classifiers":[
        {
            "category":"Retail",
            "subcategory":"Animal Services",
            "type":"Services"
        }
    ],
    "sg:phone":"+1 936 588 1481",
    "sg:postcode":"77316",
    "sg:province":"TX",
    "sg:tags":[
        "pet",
        "boarding",
        "sitting"
    ],
    "wof:name":"Lake Conroe Boarding Kennels",
    "wof:placetype":"venue"
},
  "geometry": {"coordinates":[-95.59110699999999,30.319362],"type":"Point"}
}