{
  "type": "Feature",
  "properties": {
    "iso:country":"US",
    "sg:address":"1 Telge Rd",
    "sg:city":"Tomball",
    "sg:classifiers":[
        {
            "category":"Building & Trades",
            "subcategory":"Construction",
            "type":"Services"
        }
    ],
    "sg:phone":"+1 281 351 2205",
    "sg:postcode":"77377",
    "sg:province":"TX",
    "sg:tags":[
        "residential"
    ],
    "wof:name":"Heritage General Contractors",
    "wof:placetype":"venue"
},
  "geometry": {"coordinates":[-95.664085,30.066661],"type":"Point"}
}