{
  "type": "Feature",
  "properties": {
    "iso:country":"US",
    "sg:address":"401 S Broadway St",
    "sg:city":"Brownwood",
    "sg:classifiers":[
        {
            "category":"Retail",
            "subcategory":"Auto Repair",
            "type":"Services"
        }
    ],
    "sg:phone":"+1 325 646 6811",
    "sg:postcode":"76802",
    "sg:province":"TX",
    "sg:tags":[
        "body",
        "automobile",
        "painting"
    ],
    "wof:name":"York's Body Shop",
    "wof:placetype":"venue"
},
  "geometry": {"coordinates":[-98.976011,31.724119],"type":"Point"}
}