{
  "type": "Feature",
  "properties": {
    "iso:country":"US",
    "sg:address":"13302 Eastex Fwy",
    "sg:city":"Houston",
    "sg:classifiers":[
        {
            "category":"Personal",
            "type":"Services"
        }
    ],
    "sg:phone":"+1 281 987 8697",
    "sg:postcode":"77039",
    "sg:province":"TX",
    "sg:tags":[
        "towing"
    ],
    "wof:name":"Humble Towing Service",
    "wof:placetype":"venue"
},
  "geometry": {"coordinates":[-95.308601,29.9119],"type":"Point"}
}