{
  "type": "Feature",
  "properties": {
    "iso:country":"US",
    "sg:address":"1400 Schertz Pkwy",
    "sg:city":"Schertz",
    "sg:classifiers":[
        {
            "category":"Government",
            "subcategory":"Office",
            "type":"Public Place"
        }
    ],
    "sg:phone":"+1 210 658 7477",
    "sg:postcode":"78154",
    "sg:province":"TX",
    "sg:tags":[
        "village"
    ],
    "sg:website":"www.schertz.com",
    "wof:name":"Municipal Offices",
    "wof:placetype":"venue"
},
  "geometry": {"coordinates":[-98.267779,29.561674],"type":"Point"}
}