{
  "type": "Feature",
  "properties": {
    "iso:country":"US",
    "sg:address":"3333 Fannin St Ste 100",
    "sg:city":"Houston",
    "sg:classifiers":[
        {
            "category":"Arts & Performance",
            "subcategory":"Arts Center",
            "type":"Entertainment"
        }
    ],
    "sg:phone":"+1 713 523 2623",
    "sg:postcode":"77004",
    "sg:province":"TX",
    "sg:tags":[
        "performing"
    ],
    "sg:website":"www.praisenmotion.com",
    "wof:name":"Praise N Motion",
    "wof:placetype":"venue"
},
  "geometry": {"coordinates":[-95.37674800000001,29.74011],"type":"Point"}
}