{
  "type": "Feature",
  "properties": {
    "iso:country":"US",
    "sg:address":"1105 E Tyler Ave",
    "sg:city":"Harlingen",
    "sg:classifiers":[
        {
            "category":"Insurance",
            "subcategory":"Insurance Agent",
            "type":"Services"
        }
    ],
    "sg:phone":"+1 956 428 1908",
    "sg:postcode":"78550",
    "sg:province":"TX",
    "wof:name":"Trinity Universal Insurance Co",
    "wof:placetype":"venue"
},
  "geometry": {"coordinates":[-97.683712,26.189723],"type":"Point"}
}