{
  "type": "Feature",
  "properties": {
    "iso:country":"US",
    "sg:address":"7456 Reindeer Trl",
    "sg:city":"San Antonio",
    "sg:classifiers":[
        {
            "category":"Professional",
            "subcategory":"Business Services",
            "type":"Services"
        }
    ],
    "sg:phone":"+1 210 520 3577",
    "sg:postcode":"78238",
    "sg:province":"TX",
    "sg:tags":[
        "interior",
        "consultant",
        "design",
        "decorator"
    ],
    "wof:name":"Bridle Creek Interiors",
    "wof:placetype":"venue"
},
  "geometry": {"coordinates":[-98.629835,29.500591],"type":"Point"}
}