{
  "type": "Feature",
  "properties": {
    "iso:country":"US",
    "sg:address":"104 Lariat Trl",
    "sg:city":"Red Oak",
    "sg:classifiers":[
        {
            "category":"Wholesale",
            "subcategory":"Machinery & Supplies",
            "type":"Manufacturing & Wholesale Goods"
        }
    ],
    "sg:phone":"+1 972 217 9401",
    "sg:postcode":"75154",
    "sg:province":"TX",
    "sg:tags":[
        "component",
        "jet"
    ],
    "wof:name":"Jet Components",
    "wof:placetype":"venue"
},
  "geometry": {"coordinates":[-96.874224,32.547414],"type":"Point"}
}