{
  "type": "Feature",
  "properties": {
    "iso:country":"US",
    "sg:address":"6812 Saddletree Trl",
    "sg:city":"Plano",
    "sg:classifiers":[
        {
            "category":"Wholesale",
            "subcategory":"Medical Equipment & Supplies",
            "type":"Manufacturing & Wholesale Goods"
        }
    ],
    "sg:phone":"+1 972 943 9611",
    "sg:postcode":"75023",
    "sg:province":"TX",
    "wof:name":"Smart",
    "wof:placetype":"venue"
},
  "geometry": {"coordinates":[-96.751305,33.067271],"type":"Point"}
}