{
  "type": "Feature",
  "properties": {
    "iso:country":"US",
    "sg:address":"214 Elliott St W",
    "sg:city":"Austin",
    "sg:classifiers":[
        {
            "category":"Professional",
            "subcategory":"Management & Consulting",
            "type":"Services"
        }
    ],
    "sg:phone":"+1 512 339 2398",
    "sg:postcode":"78753",
    "sg:province":"TX",
    "wof:name":"Scenariolab LLC",
    "wof:placetype":"venue"
},
  "geometry": {"coordinates":[-97.700515,30.353912],"type":"Point"}
}