{
  "type": "Feature",
  "properties": {
    "iso:country":"US",
    "sg:address":"27503 Tomball Pkwy",
    "sg:city":"Tomball",
    "sg:classifiers":[
        {
            "category":"Building & Trades",
            "subcategory":"Construction",
            "type":"Services"
        }
    ],
    "sg:phone":"+1 281 351 7095",
    "sg:postcode":"77375",
    "sg:province":"TX",
    "sg:tags":[
        "contractor",
        "above",
        "sup",
        "ground",
        "pool",
        "swimming"
    ],
    "wof:name":"Treasure Pools",
    "wof:placetype":"venue"
},
  "geometry": {"coordinates":[-95.625276,30.070691],"type":"Point"}
}