{
  "type": "Feature",
  "properties": {
    "iso:country":"US",
    "sg:address":"13027 W 2nd St",
    "sg:city":"Vernon",
    "sg:classifiers":[
        {
            "category":"Professional",
            "subcategory":"Business Services",
            "type":"Services"
        }
    ],
    "sg:phone":"+1 940 552 2287",
    "sg:postcode":"76384",
    "sg:province":"TX",
    "wof:name":"Branin Bail Bonds",
    "wof:placetype":"venue"
},
  "geometry": {"coordinates":[-99.371036,34.084104],"type":"Point"}
}