{
  "type": "Feature",
  "properties": {
    "iso:country":"US",
    "sg:address":"8004 Tiffany Dr",
    "sg:city":"Austin",
    "sg:classifiers":[
        {
            "category":"Home & Garden",
            "subcategory":"Home Furnishings",
            "type":"Retail Goods"
        }
    ],
    "sg:phone":"+1 512 280 7250",
    "sg:postcode":"78749",
    "sg:province":"TX",
    "wof:name":"Austin Window Covering E",
    "wof:placetype":"venue"
},
  "geometry": {"coordinates":[-97.851071,30.209777],"type":"Point"}
}