{
  "type": "Feature",
  "properties": {
    "iso:country":"US",
    "sg:address":"9131 Hillcroft St",
    "sg:city":"Houston",
    "sg:classifiers":[
        {
            "category":"Food & Beverages",
            "subcategory":"Liquor & Beverages",
            "type":"Retail Goods"
        }
    ],
    "sg:phone":"+1 713 774 6606",
    "sg:postcode":"77096",
    "sg:province":"TX",
    "sg:tags":[
        "grocery",
        "alcoholic"
    ],
    "wof:name":"H Liquor",
    "wof:placetype":"venue"
},
  "geometry": {"coordinates":[-95.492599,29.6796],"type":"Point"}
}