{
  "type": "Feature",
  "properties": {
    "iso:country":"US",
    "sg:address":"8616 Barrow Glen Loop",
    "sg:city":"Austin",
    "sg:classifiers":[
        {
            "category":"Professional",
            "subcategory":"Testing Lab",
            "type":"Services"
        }
    ],
    "sg:phone":"+1 512 282 7222",
    "sg:postcode":"78749",
    "sg:province":"TX",
    "sg:tags":[
        "biological",
        "laboratory"
    ],
    "sg:website":"http://www.janssenbiological.com",
    "wof:name":"Janssen Biological",
    "wof:placetype":"venue"
},
  "geometry": {"coordinates":[-97.85594,30.203507],"type":"Point"}
}