{
  "type": "Feature",
  "properties": {
    "iso:country":"US",
    "sg:address":"1414 E Richey Rd Bldg C",
    "sg:city":"Houston",
    "sg:classifiers":[
        {
            "category":"Manufacturing",
            "subcategory":"Electronics",
            "type":"Manufacturing & Wholesale Goods"
        }
    ],
    "sg:phone":"+1 281 951 0003",
    "sg:postcode":"77073",
    "sg:province":"TX",
    "sg:tags":[
        "equipment",
        "heat",
        "exchanger"
    ],
    "wof:name":"R & R Heat Exchangers",
    "wof:placetype":"venue"
},
  "geometry": {"coordinates":[-95.386724,29.996481],"type":"Point"}
}