{
  "type": "Feature",
  "properties": {
    "iso:country":"US",
    "sg:address":"1109 Rosine St",
    "sg:city":"Houston",
    "sg:classifiers":[
        {
            "category":"Professional",
            "subcategory":"Engineering",
            "type":"Services"
        }
    ],
    "sg:phone":"+1 713 526 5054",
    "sg:postcode":"77019",
    "sg:province":"TX",
    "sg:tags":[
        "engineer"
    ],
    "wof:name":"Frank J Dillard & Assoc Inc",
    "wof:placetype":"venue"
},
  "geometry": {"coordinates":[-95.398871,29.756043],"type":"Point"}
}