{
  "type": "Feature",
  "properties": {
    "iso:country":"US",
    "sg:address":"31315 FM 2920",
    "sg:city":"Waller",
    "sg:classifiers":[
        {
            "category":"Retail",
            "subcategory":"Veterinary Services",
            "type":"Services"
        }
    ],
    "sg:phone":"+1 936 372 2323",
    "sg:postcode":"77484",
    "sg:province":"TX",
    "wof:name":"Wallervick Clinic",
    "wof:placetype":"venue"
},
  "geometry": {"coordinates":[-95.91314199999999,30.058823],"type":"Point"}
}