{
  "type": "Feature",
  "properties": {
    "iso:country":"US",
    "sg:address":"25700 I- 45",
    "sg:city":"Spring",
    "sg:classifiers":[
        {
            "category":"Wholesale",
            "subcategory":"Machinery & Supplies",
            "type":"Manufacturing & Wholesale Goods"
        }
    ],
    "sg:phone":"+1 281 362 7457",
    "sg:postcode":"77386",
    "sg:province":"TX",
    "sg:tags":[
        "field",
        "industrial",
        "oil",
        "equipment"
    ],
    "wof:name":"Altec Gas Lift Inc",
    "wof:placetype":"venue"
},
  "geometry": {"coordinates":[-95.44475300000001,30.136971],"type":"Point"}
}