{
  "type": "Feature",
  "properties": {
    "iso:country":"US",
    "sg:address":"200 Verna St",
    "sg:city":"Jasper",
    "sg:classifiers":[
        {
            "category":"Professional",
            "subcategory":"Computer Services",
            "type":"Services"
        }
    ],
    "sg:phone":"+1 409 384 9007",
    "sg:postcode":"75951",
    "sg:province":"TX",
    "sg:tags":[
        "prepackaged",
        "software"
    ],
    "wof:name":"BS Software",
    "wof:placetype":"venue"
},
  "geometry": {"coordinates":[-94.004277,30.928158],"type":"Point"}
}