{
  "type": "Feature",
  "properties": {
    "iso:country":"US",
    "sg:address":"819 N Montclair Ave",
    "sg:city":"Dallas",
    "sg:classifiers":[
        {
            "category":"Real Estate",
            "subcategory":"Real Estate Agent",
            "type":"Services"
        }
    ],
    "sg:phone":"+1 214 948 7068",
    "sg:postcode":"75208",
    "sg:province":"TX",
    "wof:name":"David Roland Realty",
    "wof:placetype":"venue"
},
  "geometry": {"coordinates":[-96.846513,32.753357],"type":"Point"}
}