{
  "type": "Feature",
  "properties": {
    "iso:country":"US",
    "sg:address":"10 Desta Dr",
    "sg:city":"Orla",
    "sg:classifiers":[
        {
            "category":"Mining & Drilling",
            "type":"Manufacturing & Wholesale Goods"
        }
    ],
    "sg:phone":"+1 432 273 4331",
    "sg:postcode":"79705",
    "sg:province":"TX",
    "sg:tags":[
        "operator",
        "oil"
    ],
    "wof:name":"Primrose Operating Co",
    "wof:placetype":"venue"
},
  "geometry": {"coordinates":[-102.08756099999999,32.030997],"type":"Point"}
}