{
  "type": "Feature",
  "properties": {
    "iso:country":"US",
    "sg:address":"1701 Pennsylvania Ave",
    "sg:city":"Fort Worth",
    "sg:classifiers":[
        {
            "category":"Health Services",
            "subcategory":"Doctor",
            "type":"Services"
        }
    ],
    "sg:phone":"+1 817 334 0530",
    "sg:postcode":"76104",
    "sg:province":"TX",
    "sg:tags":[
        "osteopathic"
    ],
    "wof:name":"James M Cogdill",
    "wof:placetype":"venue"
},
  "geometry": {"coordinates":[-97.34589699999999,32.738548],"type":"Point"}
}