{
  "type": "Feature",
  "properties": {
    "iso:country":"US",
    "sg:address":"2420 Ridgepoint Dr",
    "sg:city":"Austin",
    "sg:classifiers":[
        {
            "category":"Professional",
            "subcategory":"Employment Agencies",
            "type":"Services"
        }
    ],
    "sg:phone":"+1 512 674 8129",
    "sg:postcode":"78754",
    "sg:province":"TX",
    "wof:name":"Adecco",
    "wof:placetype":"venue"
},
  "geometry": {"coordinates":[-97.67345,30.328264],"type":"Point"}
}