{
  "type": "Feature",
  "properties": {
    "iso:country":"US",
    "sg:address":"550 Westcott St",
    "sg:city":"Houston",
    "sg:classifiers":[
        {
            "category":"Professional",
            "subcategory":"Lawyer & Legal Services",
            "type":"Services"
        }
    ],
    "sg:phone":"+1 713 877 1881",
    "sg:postcode":"77007",
    "sg:province":"TX",
    "wof:name":"Dillard Luecretia Atty",
    "wof:placetype":"venue"
},
  "geometry": {"coordinates":[-95.4216,29.767],"type":"Point"}
}