{
  "type": "Feature",
  "properties": {
    "iso:country":"US",
    "sg:address":"401 S Houston St",
    "sg:city":"Groesbeck",
    "sg:classifiers":[
        {
            "category":"Real Estate",
            "subcategory":"Real Estate Operator",
            "type":"Services"
        }
    ],
    "sg:phone":"+1 254 729 2558",
    "sg:postcode":"76642",
    "sg:province":"TX",
    "sg:tags":[
        "building",
        "apartment"
    ],
    "wof:name":"Alpine Apartments",
    "wof:placetype":"venue"
},
  "geometry": {"coordinates":[-96.532331,31.519263],"type":"Point"}
}