{
  "type": "Feature",
  "properties": {
    "iso:country":"US",
    "sg:address":"114 E Elizabeth St",
    "sg:city":"Brownsville",
    "sg:classifiers":[
        {
            "category":"Restaurant",
            "type":"Food & Drink"
        }
    ],
    "sg:phone":"+1 956 546 1504",
    "sg:postcode":"78520",
    "sg:province":"TX",
    "wof:name":"Estrella Mexican Plate",
    "wof:placetype":"venue"
},
  "geometry": {"coordinates":[-97.505363,25.907755],"type":"Point"}
}