{
  "type": "Feature",
  "properties": {
    "iso:country":"US",
    "sg:address":"6019 Winterhaven Dr",
    "sg:city":"Houston",
    "sg:classifiers":[
        {
            "category":"Organizations",
            "subcategory":"Religious Organization",
            "type":"Services"
        }
    ],
    "sg:phone":"+1 713 644 3200",
    "sg:postcode":"77087",
    "sg:province":"TX",
    "sg:tags":[
        "church"
    ],
    "wof:name":"Christ Apostolic Church Of God",
    "wof:placetype":"venue"
},
  "geometry": {"coordinates":[-95.29580199999999,29.678592],"type":"Point"}
}