{
  "type": "Feature",
  "properties": {
    "iso:country":"US",
    "sg:address":"402 Spillar Ln",
    "sg:city":"Austin",
    "sg:classifiers":[
        {
            "category":"Health Services",
            "subcategory":"Doctor",
            "type":"Services"
        }
    ],
    "sg:phone":"+1 512 327 1111",
    "sg:postcode":"78746",
    "sg:province":"TX",
    "wof:name":"Kevin Delane DDS",
    "wof:placetype":"venue"
},
  "geometry": {"coordinates":[-97.81222200000001,30.289681],"type":"Point"}
}