{
  "type": "Feature",
  "properties": {
    "iso:country":"US",
    "sg:address":"8410 Lockheed Ave",
    "sg:city":"Houston",
    "sg:classifiers":[
        {
            "category":"Government",
            "subcategory":"Office",
            "type":"Public Place"
        }
    ],
    "sg:phone":"+1 713 847 1400",
    "sg:postcode":"77061",
    "sg:province":"TX",
    "sg:tags":[
        "government-united",
        "state"
    ],
    "sg:website":"http://www.faa.gov",
    "wof:name":"Airport Traffic Control Tower",
    "wof:placetype":"venue"
},
  "geometry": {"coordinates":[-95.287718,29.646052],"type":"Point"}
}