{
  "type": "Feature",
  "properties": {
    "iso:country":"US",
    "sg:address":"210 E Juan Linn St",
    "sg:city":"Victoria",
    "sg:classifiers":[
        {
            "category":"Travel",
            "subcategory":"Hotels & Motels",
            "type":"Entertainment"
        }
    ],
    "sg:phone":"+1 361 575 0000",
    "sg:postcode":"77901",
    "sg:province":"TX",
    "sg:tags":[
        "personal",
        "operation"
    ],
    "wof:name":"Friendly Oaks Bed & Breakfast",
    "wof:placetype":"venue"
},
  "geometry": {"coordinates":[-97.004892,28.79687],"type":"Point"}
}