{
  "type": "Feature",
  "properties": {
    "iso:country":"US",
    "sg:address":"2965 E 13th St",
    "sg:city":"Brownsville",
    "sg:classifiers":[
        {
            "category":"Building & Trades",
            "subcategory":"Plumbing",
            "type":"Services"
        }
    ],
    "sg:phone":"+1 956 541 9317",
    "sg:postcode":"78521",
    "sg:province":"TX",
    "sg:tags":[
        "contractor"
    ],
    "wof:name":"A C I Srvc-Air Cnditioning Htg",
    "wof:placetype":"venue"
},
  "geometry": {"coordinates":[-97.480014,25.913193],"type":"Point"}
}