{
  "type": "Feature",
  "properties": {
    "iso:country":"US",
    "sg:address":"6731 Bridge St",
    "sg:city":"Fort Worth",
    "sg:classifiers":[
        {
            "category":"Shopping",
            "subcategory":"Gifts & Souvenirs",
            "type":"Retail Goods"
        }
    ],
    "sg:phone":"+1 817 446 5853",
    "sg:postcode":"76112",
    "sg:province":"TX",
    "sg:tags":[
        "basket",
        "parcel"
    ],
    "wof:name":"Best Basket",
    "wof:placetype":"venue"
},
  "geometry": {"coordinates":[-97.21517799999999,32.766188],"type":"Point"}
}