{
  "type": "Feature",
  "properties": {
    "iso:country":"US",
    "sg:address":"2008 Town Pl",
    "sg:city":"Garland",
    "sg:classifiers":[
        {
            "category":"Professional",
            "subcategory":"Business Services",
            "type":"Services"
        }
    ],
    "sg:phone":"+1 972 278 2263",
    "sg:postcode":"75041",
    "sg:province":"TX",
    "wof:name":"A De Enterprises",
    "wof:placetype":"venue"
},
  "geometry": {"coordinates":[-96.65912,32.868529],"type":"Point"}
}