{
  "type": "Feature",
  "properties": {
    "iso:country":"US",
    "sg:address":"8014 Baltzell Dr",
    "sg:city":"Spring",
    "sg:classifiers":[
        {
            "category":"Food & Beverages",
            "subcategory":"Groceries & Convenience Stores",
            "type":"Retail Goods"
        }
    ],
    "sg:phone":"+1 281 351 4838",
    "sg:postcode":"77389",
    "sg:province":"TX",
    "wof:name":"Warren Food Group LLC",
    "wof:placetype":"venue"
},
  "geometry": {"coordinates":[-95.548157,30.119394],"type":"Point"}
}