{
  "type": "Feature",
  "properties": {
    "iso:country":"US",
    "sg:address":"4500 35th St",
    "sg:city":"Dickinson",
    "sg:classifiers":[
        {
            "category":"Building & Trades",
            "subcategory":"Construction",
            "type":"Services"
        }
    ],
    "sg:phone":"+1 281 534 3125",
    "sg:postcode":"77539",
    "sg:province":"TX",
    "sg:tags":[
        "manufactured",
        "housing-communities"
    ],
    "wof:name":"Menotti Mobile Home Park",
    "wof:placetype":"venue"
},
  "geometry": {"coordinates":[-95.043243,29.468966],"type":"Point"}
}