{
  "type": "Feature",
  "properties": {
    "iso:country":"US",
    "sg:address":"7027 Misty Ridge Dr",
    "sg:city":"Converse",
    "sg:classifiers":[
        {
            "category":"Social Services",
            "subcategory":"Child Care",
            "type":"Services"
        }
    ],
    "sg:phone":"+1 210 654 3801",
    "sg:postcode":"78109",
    "sg:province":"TX",
    "wof:name":"YMCA School Age Care",
    "wof:placetype":"venue"
},
  "geometry": {"coordinates":[-98.34814900000001,29.528832],"type":"Point"}
}