{
  "type": "Feature",
  "properties": {
    "iso:country":"US",
    "sg:address":"7069 Beechnut St",
    "sg:city":"Houston",
    "sg:classifiers":[
        {
            "category":"Restaurant",
            "type":"Food & Drink"
        }
    ],
    "sg:phone":"+1 713 988 2258",
    "sg:postcode":"77074",
    "sg:province":"TX",
    "sg:tags":[
        "fast"
    ],
    "wof:name":"KFC",
    "wof:placetype":"venue"
},
  "geometry": {"coordinates":[-95.513696,29.691048],"type":"Point"}
}