{
  "type": "Feature",
  "properties": {
    "iso:country":"US",
    "sg:address":"500 W Paisano Dr",
    "sg:city":"El Paso",
    "sg:classifiers":[
        {
            "category":"Building & Trades",
            "subcategory":"Construction",
            "type":"Services"
        }
    ],
    "sg:phone":"+1 915 544 3600",
    "sg:postcode":"79901",
    "sg:province":"TX",
    "sg:tags":[
        "insulation",
        "heat",
        "contractor"
    ],
    "wof:name":"Jace Contracting",
    "wof:placetype":"venue"
},
  "geometry": {"coordinates":[-106.49405899999999,31.755414],"type":"Point"}
}