{
  "type": "Feature",
  "properties": {
    "iso:country":"US",
    "sg:address":"4310 W 45th Ave",
    "sg:city":"Amarillo",
    "sg:classifiers":[
        {
            "category":"Home & Garden",
            "subcategory":"Furniture",
            "type":"Retail Goods"
        }
    ],
    "sg:phone":"+1 806 352 4600",
    "sg:postcode":"79109",
    "sg:province":"TX",
    "wof:name":"LA-Z-Boy Furntiure Galleries",
    "wof:placetype":"venue"
},
  "geometry": {"coordinates":[-101.889082,35.161736],"type":"Point"}
}