{
  "type": "Feature",
  "properties": {
    "iso:country":"US",
    "sg:address":"1715 Montana Ave",
    "sg:city":"El Paso",
    "sg:classifiers":[
        {
            "category":"Real Estate",
            "subcategory":"Real Estate Agent",
            "type":"Services"
        }
    ],
    "sg:phone":"+1 915 533 1261",
    "sg:postcode":"79902",
    "sg:province":"TX",
    "sg:tags":[
        "finding",
        "apartment",
        "rental"
    ],
    "wof:name":"Anchondo Real Estate",
    "wof:placetype":"venue"
},
  "geometry": {"coordinates":[-106.47537699999999,31.774442],"type":"Point"}
}