{
  "type": "Feature",
  "properties": {
    "iso:country":"US",
    "sg:address":"1100 N Conway Ave",
    "sg:city":"Mission",
    "sg:classifiers":[
        {
            "category":"Shopping",
            "subcategory":"Pharmacy",
            "type":"Retail Goods"
        }
    ],
    "sg:phone":"+1 956 583 3551",
    "sg:postcode":"78572",
    "sg:province":"TX",
    "wof:name":"Medico Pharmacy & Medical Eqpt",
    "wof:placetype":"venue"
},
  "geometry": {"coordinates":[-98.32531899999999,26.21789],"type":"Point"}
}