{
  "type": "Feature",
  "properties": {
    "iso:country":"US",
    "sg:address":"8312 S Congress Avenue",
    "sg:city":"Austin",
    "sg:classifiers":[
        {
            "category":"Manufacturing",
            "subcategory":"Tools & Machinery",
            "type":"Manufacturing & Wholesale Goods"
        },
        {
            "category":"Home & Garden",
            "subcategory":"Household Appliances",
            "type":"Retail Goods"
        },
        {
            "category":"Building & Trades",
            "subcategory":"Construction",
            "type":"Services"
        },
        {
            "category":"Professional",
            "subcategory":"Engineering",
            "type":"Services"
        }
    ],
    "sg:phone":"+1 512 440 0123",
    "sg:postcode":"78745",
    "sg:province":"TX",
    "sg:tags":[
        "screens-wholesale",
        "system",
        "specialty",
        "equipment",
        "pump",
        "heating",
        "insulation",
        "contractor",
        "heat",
        "air conditioning",
        "manufacturer"
    ],
    "sg:website":"www.trane.com",
    "wof:name":"Climate Mechanical",
    "wof:placetype":"venue"
},
  "geometry": {"coordinates":[-97.784797,30.17498],"type":"Point"}
}