{
  "type": "Feature",
  "properties": {
    "iso:country":"US",
    "sg:address":"3740 N Josey Ln",
    "sg:city":"Carrollton",
    "sg:classifiers":[
        {
            "category":"Health Services",
            "subcategory":"Doctor",
            "type":"Services"
        }
    ],
    "sg:phone":"+1 214 731 0031",
    "sg:postcode":"75007",
    "sg:province":"TX",
    "sg:tags":[
        "medicine",
        "internal"
    ],
    "wof:name":"Ashraf Akber MD",
    "wof:placetype":"venue"
},
  "geometry": {"coordinates":[-96.886743,33.400661],"type":"Point"}
}