{
  "type": "Feature",
  "properties": {
    "iso:country":"US",
    "sg:address":"206 E Main St",
    "sg:city":"Bronte",
    "sg:classifiers":[
        {
            "category":"Personal",
            "subcategory":"Beauty Salon",
            "type":"Services"
        }
    ],
    "sg:phone":"+1 325 473 8652",
    "sg:postcode":"76933",
    "sg:province":"TX",
    "wof:name":"Longhorn Salon",
    "wof:placetype":"venue"
},
  "geometry": {"coordinates":[-100.290801,31.88734],"type":"Point"}
}