{
  "type": "Feature",
  "properties": {
    "iso:country":"US",
    "sg:address":"600 Bellaire Dr",
    "sg:city":"Hurst",
    "sg:classifiers":[
        {
            "category":"Real Estate",
            "subcategory":"Real Estate Operator",
            "type":"Services"
        }
    ],
    "sg:phone":"+1 817 280 0939",
    "sg:postcode":"76053",
    "sg:province":"TX",
    "sg:tags":[
        "building",
        "apartment"
    ],
    "wof:name":"Whispering Run Apartments",
    "wof:placetype":"venue"
},
  "geometry": {"coordinates":[-97.15987800000001,32.820583],"type":"Point"}
}