{
  "type": "Feature",
  "properties": {
    "iso:country":"US",
    "sg:address":"3300 Hillcrest Dr",
    "sg:city":"Waco",
    "sg:classifiers":[
        {
            "category":"Health Services",
            "subcategory":"Clinic",
            "type":"Services"
        }
    ],
    "sg:phone":"+1 254 752 6352",
    "sg:postcode":"76708",
    "sg:province":"TX",
    "sg:tags":[
        "limb",
        "making",
        "prosthetics"
    ],
    "wof:name":"Elite Prosthetics",
    "wof:placetype":"venue"
},
  "geometry": {"coordinates":[-97.18007799999999,31.555863],"type":"Point"}
}