{
  "type": "Feature",
  "properties": {
    "iso:country":"US",
    "sg:address":"303 Woodcombe Dr",
    "sg:city":"Houston",
    "sg:classifiers":[
        {
            "category":"Real Estate",
            "subcategory":"Real Estate Operator",
            "type":"Services"
        }
    ],
    "sg:phone":"+1 281 286 1347",
    "sg:postcode":"77062",
    "sg:province":"TX",
    "sg:tags":[
        "building",
        "nonresidential"
    ],
    "wof:name":"Woodcombe Properties",
    "wof:placetype":"venue"
},
  "geometry": {"coordinates":[-95.143202,29.569868],"type":"Point"}
}