{
  "type": "Feature",
  "properties": {
    "iso:country":"US",
    "sg:address":"2224 Bay Haven Way",
    "sg:city":"League City",
    "sg:classifiers":[
        {
            "category":"Professional",
            "type":"Services"
        }
    ],
    "sg:phone":"+1 281 334 6979",
    "sg:postcode":"77573",
    "sg:province":"TX",
    "sg:tags":[
        "establishment"
    ],
    "wof:name":"Implemetrics Inc",
    "wof:placetype":"venue"
},
  "geometry": {"coordinates":[-95.050359,29.538087],"type":"Point"}
}