{
  "type": "Feature",
  "properties": {
    "iso:country":"US",
    "sg:address":"5802 Circulo Dr",
    "sg:city":"Leander",
    "sg:classifiers":[
        {
            "category":"Arena",
            "subcategory":"Sports Club",
            "type":"Entertainment"
        }
    ],
    "sg:phone":"+1 512 656 9970",
    "sg:postcode":"78645",
    "sg:province":"TX",
    "wof:name":"Synergy Sports",
    "wof:placetype":"venue"
},
  "geometry": {"coordinates":[-97.993314,30.455589],"type":"Point"}
}