{
  "type": "Feature",
  "properties": {
    "iso:country":"US",
    "sg:address":"2605 Newcomb St",
    "sg:city":"Lubbock",
    "sg:classifiers":[
        {
            "category":"Professional",
            "subcategory":"Business Services",
            "type":"Services"
        }
    ],
    "sg:phone":"+1 806 741 1196",
    "sg:postcode":"79415",
    "sg:province":"TX",
    "wof:name":"Rickel Holdings Inc",
    "wof:placetype":"venue"
},
  "geometry": {"coordinates":[-101.87696200000001,33.639832],"type":"Point"}
}