{
  "type": "Feature",
  "properties": {
    "iso:country":"US",
    "sg:address":"7710 Hollow Glen Ln",
    "sg:city":"Houston",
    "sg:classifiers":[
        {
            "category":"Professional",
            "type":"Services"
        }
    ],
    "sg:phone":"+1 281 495 3639",
    "sg:postcode":"77072",
    "sg:province":"TX",
    "wof:name":"A1 Professional Services",
    "wof:placetype":"venue"
},
  "geometry": {"coordinates":[-95.60907899999999,29.693808],"type":"Point"}
}