{
  "type": "Feature",
  "properties": {
    "iso:country":"US",
    "sg:address":"2907 Wydewood Dr",
    "sg:city":"Midland",
    "sg:classifiers":[
        {
            "category":"Arts & Performance",
            "subcategory":"Theater",
            "type":"Entertainment"
        }
    ],
    "sg:phone":"+1 432 522 2270",
    "sg:postcode":"79707",
    "sg:province":"TX",
    "sg:tags":[
        "karaoke"
    ],
    "wof:name":"Boyd Karaoke & DJ Entertainmnt",
    "wof:placetype":"venue"
},
  "geometry": {"coordinates":[-102.14582299999999,32.008287],"type":"Point"}
}