{
  "type": "Feature",
  "properties": {
    "iso:country":"US",
    "sg:address":"822 Misty Cove Dr",
    "sg:city":"Arlington",
    "sg:classifiers":[
        {
            "category":"Shopping",
            "subcategory":"Computers & Home Electronics",
            "type":"Retail Goods"
        }
    ],
    "sg:phone":"+1 817 299 8264",
    "sg:postcode":"76013",
    "sg:province":"TX",
    "sg:tags":[
        "electronic"
    ],
    "wof:name":"A-Z Discount Computers",
    "wof:placetype":"venue"
},
  "geometry": {"coordinates":[-97.115971,32.710622],"type":"Point"}
}