{
  "type": "Feature",
  "properties": {
    "iso:country":"US",
    "sg:address":"1314 Trailwood Village Dr",
    "sg:city":"Humble",
    "sg:classifiers":[
        {
            "category":"Professional",
            "subcategory":"Computer Services",
            "type":"Services"
        }
    ],
    "sg:phone":"+1 281 312 4456",
    "sg:postcode":"77339",
    "sg:province":"TX",
    "sg:tags":[
        "related"
    ],
    "wof:name":"Jgn Bookkeeping",
    "wof:placetype":"venue"
},
  "geometry": {"coordinates":[-95.224254,30.033611],"type":"Point"}
}