{
  "type": "Feature",
  "properties": {
    "iso:country":"US",
    "sg:address":"400 Fuller-Wiser Rd",
    "sg:city":"Euless",
    "sg:classifiers":[
        {
            "category":"Government",
            "subcategory":"Office",
            "type":"Public Place"
        }
    ],
    "sg:phone":"+1 817 354 2610",
    "sg:postcode":"76039",
    "sg:province":"TX",
    "sg:tags":[
        "executive"
    ],
    "wof:name":"DOT/FAA Civil Avaition",
    "wof:placetype":"venue"
},
  "geometry": {"coordinates":[-97.072397,32.844376],"type":"Point"}
}