{
  "type": "Feature",
  "properties": {
    "iso:country":"US",
    "sg:address":"11322 Wonderland Trl",
    "sg:city":"Dallas",
    "sg:classifiers":[
        {
            "category":"Building & Trades",
            "subcategory":"Construction",
            "type":"Services"
        }
    ],
    "sg:phone":"+1 214 350 9401",
    "sg:postcode":"75229",
    "sg:province":"TX",
    "sg:tags":[
        "marble",
        "terrazzo"
    ],
    "wof:name":"Mar-Tek Industries",
    "wof:placetype":"venue"
},
  "geometry": {"coordinates":[-96.844804,32.903998],"type":"Point"}
}