{
  "type": "Feature",
  "properties": {
    "iso:country":"US",
    "sg:address":"117 Inwood Dr",
    "sg:city":"Silsbee",
    "sg:classifiers":[
        {
            "category":"Retail",
            "subcategory":"Repair Shop",
            "type":"Services"
        }
    ],
    "sg:phone":"+1 409 385 1175",
    "sg:postcode":"77656",
    "sg:province":"TX",
    "wof:name":"Thompsons Taxidermy",
    "wof:placetype":"venue"
},
  "geometry": {"coordinates":[-94.19057100000001,30.33321],"type":"Point"}
}