{
  "type": "Feature",
  "properties": {
    "iso:country":"US",
    "sg:address":"712 W Abram St",
    "sg:city":"Arlington",
    "sg:classifiers":[
        {
            "category":"Organizations",
            "subcategory":"Religious Organization",
            "type":"Services"
        }
    ],
    "sg:phone":"+1 817 860 1836",
    "sg:postcode":"76013",
    "sg:province":"TX",
    "sg:tags":[
        "church"
    ],
    "sg:website":"www.salvationarmy.uss.org",
    "wof:name":"Salvation Army",
    "wof:placetype":"venue"
},
  "geometry": {"coordinates":[-97.115998,32.735689],"type":"Point"}
}