{
  "type": "Feature",
  "properties": {
    "iso:country":"US",
    "sg:address":"1000 Mo Pac Cir",
    "sg:city":"Austin",
    "sg:classifiers":[
        {
            "category":"Real Estate",
            "subcategory":"Real Estate Services",
            "type":"Services"
        }
    ],
    "sg:phone":"+1 512 327 3910",
    "sg:postcode":"78746",
    "sg:province":"TX",
    "sg:tags":[
        "management",
        "property"
    ],
    "wof:name":"Jagger Dennie",
    "wof:placetype":"venue"
},
  "geometry": {"coordinates":[-97.78361200000001,30.265946],"type":"Point"}
}