{
  "type": "Feature",
  "properties": {
    "iso:country":"US",
    "sg:address":"421 W Freddy Gonzalez Dr",
    "sg:city":"Edinburg",
    "sg:classifiers":[
        {
            "category":"Health Services",
            "subcategory":"Doctor",
            "type":"Services"
        }
    ],
    "sg:phone":"+1 956 383 4988",
    "sg:postcode":"78539",
    "sg:province":"TX",
    "sg:tags":[
        "physician",
        "surgeon"
    ],
    "wof:name":"Naif C Mohamed MD",
    "wof:placetype":"venue"
},
  "geometry": {"coordinates":[-98.168178,26.287431],"type":"Point"}
}