{
  "type": "Feature",
  "properties": {
    "iso:country":"US",
    "sg:address":"400 W Malloy Bridge Rd",
    "sg:city":"Seagoville",
    "sg:classifiers":[
        {
            "category":"Manufacturing",
            "subcategory":"Metals",
            "type":"Manufacturing & Wholesale Goods"
        },
        {
            "category":"Building & Trades",
            "subcategory":"Plumbing",
            "type":"Services"
        }
    ],
    "sg:phone":"+1 972 287 8281",
    "sg:postcode":"75159",
    "sg:province":"TX",
    "sg:tags":[
        "installation",
        "work",
        "custom",
        "provides",
        "sheet",
        "fabricates",
        "contractor"
    ],
    "wof:name":"Mc Hone Metal Fabricators Inc",
    "wof:placetype":"venue"
},
  "geometry": {"coordinates":[-96.54124299999999,32.635849],"type":"Point"}
}