{
  "type": "Feature",
  "properties": {
    "iso:country":"US",
    "sg:address":"12120 Veterans Memorial Dr",
    "sg:city":"Houston",
    "sg:classifiers":[
        {
            "category":"Autos & Motor Vehicles",
            "subcategory":"Auto Supplies",
            "type":"Retail Goods"
        }
    ],
    "sg:phone":"+1 281 580 4245",
    "sg:postcode":"77067",
    "sg:province":"TX",
    "wof:name":"Hi-Lo Auto Supply 86",
    "wof:placetype":"venue"
},
  "geometry": {"coordinates":[-95.478454,29.961721],"type":"Point"}
}