{
  "type": "Feature",
  "properties": {
    "iso:country":"US",
    "sg:address":"4704 Candy Ln",
    "sg:city":"Tyler",
    "sg:classifiers":[
        {
            "category":"Building & Trades",
            "subcategory":"Electrical",
            "type":"Services"
        }
    ],
    "sg:phone":"+1 903 571 2788",
    "sg:postcode":"75701",
    "sg:province":"TX",
    "sg:tags":[
        "industrial",
        "electrician",
        "contractors-commercial",
        "electric"
    ],
    "wof:name":"Miller Electric",
    "wof:placetype":"venue"
},
  "geometry": {"coordinates":[-95.32701299999999,32.298292],"type":"Point"}
}