{
  "type": "Feature",
  "properties": {
    "iso:country":"US",
    "sg:address":"807 N Louisiana Ave",
    "sg:city":"Laredo",
    "sg:classifiers":[
        {
            "category":"Autos & Motor Vehicles",
            "subcategory":"Automobile Sales",
            "type":"Retail Goods"
        }
    ],
    "sg:phone":"+1 956 727 8009",
    "sg:postcode":"78043",
    "sg:province":"TX",
    "sg:tags":[
        "used"
    ],
    "wof:name":"Big Dads Auto Sale",
    "wof:placetype":"venue"
},
  "geometry": {"coordinates":[-99.469261,27.504644],"type":"Point"}
}