{
  "type": "Feature",
  "properties": {
    "iso:country":"US",
    "sg:address":"156 Beach Blvd",
    "sg:city":"Laguna Vista",
    "sg:classifiers":[
        {
            "category":"Professional",
            "type":"Services"
        }
    ],
    "sg:phone":"+1 956 943 6500",
    "sg:postcode":"78578",
    "sg:province":"TX",
    "sg:tags":[
        "establishment"
    ],
    "wof:name":"Towboat Us Port Isabel",
    "wof:placetype":"venue"
},
  "geometry": {"coordinates":[-97.28674100000001,26.098358],"type":"Point"}
}