{
  "type": "Feature",
  "properties": {
    "iso:country":"US",
    "sg:address":"121 W Oleander Ave",
    "sg:city":"La Feria",
    "sg:classifiers":[
        {
            "category":"Health Services",
            "subcategory":"Clinic",
            "type":"Services"
        }
    ],
    "sg:phone":"+1 956 797 4654",
    "sg:postcode":"78559",
    "sg:province":"TX",
    "sg:tags":[
        "home",
        "care"
    ],
    "wof:name":"La Feria Home Health",
    "wof:placetype":"venue"
},
  "geometry": {"coordinates":[-97.82441799999999,26.157662],"type":"Point"}
}