{
  "type": "Feature",
  "properties": {
    "iso:country":"US",
    "sg:address":"2122 Mars Dr",
    "sg:city":"Rosharon",
    "sg:classifiers":[
        {
            "category":"Building & Trades",
            "subcategory":"Cleaning & Sanitation",
            "type":"Services"
        }
    ],
    "sg:phone":"+1 281 489 3315",
    "sg:postcode":"77583",
    "sg:province":"TX",
    "sg:tags":[
        "maintenance"
    ],
    "wof:name":"Lilians Janitorial",
    "wof:placetype":"venue"
},
  "geometry": {"coordinates":[-95.417502,29.509135],"type":"Point"}
}