{
  "type": "Feature",
  "properties": {
    "iso:country":"US",
    "sg:address":"17035 Cairnladdie St",
    "sg:city":"Houston",
    "sg:classifiers":[
        {
            "category":"Food & Beverages",
            "subcategory":"Specialty",
            "type":"Retail Goods"
        }
    ],
    "sg:phone":"+1 281 859 3959",
    "sg:postcode":"77084",
    "sg:province":"TX",
    "wof:name":"American Nutrition & Heal",
    "wof:placetype":"venue"
},
  "geometry": {"coordinates":[-95.663225,29.847496],"type":"Point"}
}