{
  "type": "Feature",
  "properties": {
    "iso:country":"US",
    "sg:address":"8250 N Central Expy",
    "sg:city":"Dallas",
    "sg:classifiers":[
        {
            "category":"Education",
            "subcategory":"Special Training",
            "type":"Public Place"
        }
    ],
    "sg:phone":"+1 800 925 7737",
    "sg:postcode":"75206",
    "sg:province":"TX",
    "sg:tags":[
        "tutoring"
    ],
    "sg:website":"www.veritasprep.com/gmat/",
    "wof:name":"Veritas Prep GMAT Preparation",
    "wof:placetype":"venue"
},
  "geometry": {"coordinates":[-96.768833,32.862854],"type":"Point"}
}