{
  "type": "Feature",
  "properties": {
    "iso:country":"US",
    "sg:address":"12879 Josey Ln",
    "sg:city":"Dallas",
    "sg:classifiers":[
        {
            "category":"Shopping",
            "subcategory":"Discount & Variety Stores",
            "type":"Retail Goods"
        },
        {
            "category":"Shopping",
            "subcategory":"Department Store",
            "type":"Retail Goods"
        }
    ],
    "sg:phone":"+1 972 488 0300",
    "sg:postcode":"75234",
    "sg:province":"TX",
    "sg:tags":[
        "shop",
        "merchandise",
        "general"
    ],
    "wof:name":"Dollar General",
    "wof:placetype":"venue"
},
  "geometry": {"coordinates":[-96.88182999999999,32.920557],"type":"Point"}
}