{
  "type": "Feature",
  "properties": {
    "iso:country":"US",
    "sg:address":"15218 Wickbriar Dr",
    "sg:city":"Houston",
    "sg:classifiers":[
        {
            "category":"Professional",
            "type":"Services"
        }
    ],
    "sg:phone":"+1 713 433 4013",
    "sg:postcode":"77053",
    "sg:province":"TX",
    "wof:name":"Construction Sub Contr",
    "wof:placetype":"venue"
},
  "geometry": {"coordinates":[-95.455135,29.6052],"type":"Point"}
}