{
  "type": "Feature",
  "properties": {
    "iso:country":"US",
    "sg:address":"1200 Norman Cir",
    "sg:city":"Arlington",
    "sg:classifiers":[
        {
            "category":"Manufacturing",
            "subcategory":"Aerospace",
            "type":"Manufacturing & Wholesale Goods"
        }
    ],
    "sg:phone":"+1 817 472 9484",
    "sg:postcode":"76014",
    "sg:province":"TX",
    "sg:tags":[
        "aircraft",
        "mfg"
    ],
    "wof:name":"Hurns Aircraft",
    "wof:placetype":"venue"
},
  "geometry": {"coordinates":[-97.09191199999999,32.684461],"type":"Point"}
}