{
  "type": "Feature",
  "properties": {
    "iso:country":"US",
    "sg:address":"4925 Belmont St",
    "sg:city":"Beaumont",
    "sg:classifiers":[
        {
            "category":"Building & Trades",
            "subcategory":"Construction",
            "type":"Services"
        }
    ],
    "sg:phone":"+1 409 839 2713",
    "sg:postcode":"77707",
    "sg:province":"TX",
    "sg:tags":[
        "roofing",
        "industrial",
        "contractors-commercial",
        "contractor"
    ],
    "wof:name":"Discount Roofing",
    "wof:placetype":"venue"
},
  "geometry": {"coordinates":[-94.146514,30.066427],"type":"Point"}
}