{
  "type": "Feature",
  "properties": {
    "iso:country":"US",
    "sg:address":"421 N 25 Mile Ave",
    "sg:city":"Hereford",
    "sg:classifiers":[
        {
            "category":"Food & Beverages",
            "subcategory":"Bakery",
            "type":"Retail Goods"
        }
    ],
    "sg:phone":"+1 806 364 0376",
    "sg:postcode":"79045",
    "sg:province":"TX",
    "wof:name":"Mendez Bakery",
    "wof:placetype":"venue"
},
  "geometry": {"coordinates":[-102.405514,34.832476],"type":"Point"}
}