{
  "type": "Feature",
  "properties": {
    "iso:country":"US",
    "sg:address":"518 S Gaston St",
    "sg:city":"Crane",
    "sg:classifiers":[
        {
            "category":"Shopping",
            "subcategory":"Jewelry",
            "type":"Retail Goods"
        }
    ],
    "sg:phone":"+1 432 558 2140",
    "sg:postcode":"79731",
    "sg:province":"TX",
    "sg:tags":[
        "jeweler"
    ],
    "wof:name":"Butler Jewelry",
    "wof:placetype":"venue"
},
  "geometry": {"coordinates":[-102.350589,31.398214],"type":"Point"}
}