{
  "type": "Feature",
  "properties": {
    "iso:country":"US",
    "sg:address":"909 Texas Ave",
    "sg:city":"El Paso",
    "sg:classifiers":[
        {
            "category":"Manufacturing",
            "subcategory":"Food",
            "type":"Manufacturing & Wholesale Goods"
        }
    ],
    "sg:phone":"+1 915 544 3434",
    "sg:postcode":"79901",
    "sg:province":"TX",
    "sg:tags":[
        "salsa",
        "dip",
        "mfg"
    ],
    "wof:name":"Desert Pepper Trading Company",
    "wof:placetype":"venue"
},
  "geometry": {"coordinates":[-106.480487,31.763217],"type":"Point"}
}