{
  "type": "Feature",
  "properties": {
    "iso:country":"US",
    "sg:address":"403 W Marshall Ave",
    "sg:city":"Longview",
    "sg:classifiers":[
        {
            "category":"Autos & Motor Vehicles",
            "subcategory":"Automobile Sales",
            "type":"Retail Goods"
        }
    ],
    "sg:phone":"+1 903 234 2500",
    "sg:postcode":"75601",
    "sg:province":"TX",
    "sg:tags":[
        "car",
        "used",
        "truck"
    ],
    "wof:name":"Don's Auto Sales",
    "wof:placetype":"venue"
},
  "geometry": {"coordinates":[-94.74400300000001,32.500237],"type":"Point"}
}