{
  "type": "Feature",
  "properties": {
    "iso:country":"US",
    "sg:address":"6113 Hanson Rd",
    "sg:city":"Amarillo",
    "sg:classifiers":[
        {
            "category":"Banks & Credit Unions",
            "subcategory":"Investment Brokerage",
            "type":"Services"
        },
        {
            "category":"Professional",
            "subcategory":"Management & Consulting",
            "type":"Services"
        }
    ],
    "sg:phone":"+1 806 467 1231",
    "sg:postcode":"79106",
    "sg:province":"TX",
    "sg:tags":[
        "consultant",
        "planning",
        "financial"
    ],
    "wof:name":"Heath Financial & Tax Service",
    "wof:placetype":"venue"
},
  "geometry": {"coordinates":[-101.908348,35.185935],"type":"Point"}
}