{
  "type": "Feature",
  "properties": {
    "iso:country":"US",
    "sg:address":"404 Co Rd 104",
    "sg:city":"Georgetown",
    "sg:classifiers":[
        {
            "category":"Health Services",
            "subcategory":"Health Practitioner",
            "type":"Services"
        }
    ],
    "sg:phone":"+1 512 864 2520",
    "sg:postcode":"78626",
    "sg:province":"TX",
    "sg:tags":[
        "psychologist"
    ],
    "wof:name":"Betty L Clark PHD",
    "wof:placetype":"venue"
},
  "geometry": {"coordinates":[-97.613646,30.63933],"type":"Point"}
}