{
  "type": "Feature",
  "properties": {
    "iso:country":"US",
    "sg:address":"5804 Tinita Ct",
    "sg:city":"Austin",
    "sg:classifiers":[
        {
            "category":"Arts & Performance",
            "subcategory":"Theater",
            "type":"Entertainment"
        }
    ],
    "sg:phone":"+1 512 301 6903",
    "sg:postcode":"78739",
    "sg:province":"TX",
    "sg:tags":[
        "group"
    ],
    "wof:name":"Billy Riggs Enterprises",
    "wof:placetype":"venue"
},
  "geometry": {"coordinates":[-97.888578,30.184939],"type":"Point"}
}