{
  "type": "Feature",
  "properties": {
    "iso:country":"US",
    "sg:address":"8721 Clay Rd",
    "sg:city":"Houston",
    "sg:classifiers":[
        {
            "category":"Professional",
            "subcategory":"Advertising",
            "type":"Services"
        }
    ],
    "sg:phone":"+1 713 462 3030",
    "sg:postcode":"77080",
    "sg:province":"TX",
    "sg:tags":[
        "distributing",
        "sample",
        "service-circular"
    ],
    "wof:name":"Haulott Group",
    "wof:placetype":"venue"
},
  "geometry": {"coordinates":[-95.509872,29.832641],"type":"Point"}
}