{
  "type": "Feature",
  "properties": {
    "iso:country":"US",
    "sg:address":"3604 Gemini St",
    "sg:city":"El Paso",
    "sg:classifiers":[
        {
            "category":"Building & Trades",
            "subcategory":"Pest Control",
            "type":"Services"
        }
    ],
    "sg:phone":"+1 915 755 7378",
    "sg:postcode":"79904",
    "sg:province":"TX",
    "wof:name":"Bob's Pest Control",
    "wof:placetype":"venue"
},
  "geometry": {"coordinates":[-106.45017199999999,31.866474],"type":"Point"}
}