{
  "type": "Feature",
  "properties": {
    "iso:country":"US",
    "sg:address":"1801 N Vine St",
    "sg:city":"Victoria",
    "sg:classifiers":[
        {
            "category":"Shopping",
            "subcategory":"Gifts & Souvenirs",
            "type":"Retail Goods"
        }
    ],
    "sg:phone":"+1 361 573 0197",
    "sg:postcode":"77901",
    "sg:province":"TX",
    "wof:name":"Elizabeth B Fajkus",
    "wof:placetype":"venue"
},
  "geometry": {"coordinates":[-97.008134,28.810709],"type":"Point"}
}