{
  "type": "Feature",
  "properties": {
    "iso:country":"US",
    "sg:address":"203 Camille Ct",
    "sg:city":"Pflugerville",
    "sg:classifiers":[
        {
            "category":"Building & Trades",
            "subcategory":"Construction",
            "type":"Services"
        }
    ],
    "sg:phone":"+1 512 990 7593",
    "sg:postcode":"78660",
    "sg:province":"TX",
    "sg:tags":[
        "residential"
    ],
    "wof:name":"Gerald A Beathard Jr",
    "wof:placetype":"venue"
},
  "geometry": {"coordinates":[-97.619871,30.443994],"type":"Point"}
}