{
  "type": "Feature",
  "properties": {
    "iso:country":"US",
    "sg:address":"8005 Cardin Dr",
    "sg:city":"Austin",
    "sg:classifiers":[
        {
            "category":"Insurance",
            "subcategory":"Hazard Insurance",
            "type":"Services"
        }
    ],
    "sg:phone":"+1 512 451 0569",
    "sg:postcode":"78759",
    "sg:province":"TX",
    "sg:tags":[
        "commercial",
        "business"
    ],
    "wof:name":"Clark Benefit Group Inc.",
    "wof:placetype":"venue"
},
  "geometry": {"coordinates":[-97.751773,30.366837],"type":"Point"}
}