{
  "type": "Feature",
  "properties": {
    "iso:country":"US",
    "sg:address":"4802 S 31st St",
    "sg:city":"Temple",
    "sg:classifiers":[
        {
            "category":"Real Estate",
            "subcategory":"Real Estate Services",
            "type":"Services"
        },
        {
            "category":"Real Estate",
            "subcategory":"Real Estate Operator",
            "type":"Services"
        }
    ],
    "sg:phone":"+1 254 778 8680",
    "sg:postcode":"76502",
    "sg:province":"TX",
    "sg:tags":[
        "apartment",
        "vacancy",
        "listing",
        "rental",
        "finder"
    ],
    "wof:name":"Apple Creek Apts.",
    "wof:placetype":"venue"
},
  "geometry": {"coordinates":[-97.37481699999999,31.055531],"type":"Point"}
}