{
  "type": "Feature",
  "properties": {
    "iso:country":"US",
    "sg:address":"1105 Rice Dr",
    "sg:city":"Garland",
    "sg:classifiers":[
        {
            "category":"Wholesale",
            "subcategory":"Durable Goods & Equipment",
            "type":"Manufacturing & Wholesale Goods"
        }
    ],
    "sg:phone":"+1 972 276 6468",
    "sg:postcode":"75042",
    "sg:province":"TX",
    "sg:tags":[
        "representative",
        "manufacturer"
    ],
    "wof:name":"Sla International",
    "wof:placetype":"venue"
},
  "geometry": {"coordinates":[-96.69544399999999,32.923971],"type":"Point"}
}