{
  "type": "Feature",
  "properties": {
    "iso:country":"US",
    "sg:address":"501 W Stan Schlueter Loop",
    "sg:city":"Killeen",
    "sg:classifiers":[
        {
            "category":"Home & Garden",
            "subcategory":"Garden Supply",
            "type":"Retail Goods"
        },
        {
            "category":"Shopping",
            "subcategory":"Gifts & Souvenirs",
            "type":"Retail Goods"
        },
        {
            "category":"Shopping",
            "subcategory":"Florist",
            "type":"Retail Goods"
        }
    ],
    "sg:phone":"+1 254 501 9118",
    "sg:postcode":"76542",
    "sg:province":"TX",
    "sg:tags":[
        "basket",
        "plant"
    ],
    "sg:website":"http://www.alloccasionfloral.com",
    "wof:name":"All Occasion Floral & Gift",
    "wof:placetype":"venue"
},
  "geometry": {"coordinates":[-97.753484,31.076852],"type":"Point"}
}