{
  "type": "Feature",
  "properties": {
    "iso:country":"US",
    "sg:address":"3301 N 3rd St",
    "sg:city":"Abilene",
    "sg:classifiers":[
        {
            "category":"Health Services",
            "subcategory":"Doctor",
            "type":"Services"
        }
    ],
    "sg:phone":"+1 325 676 7444",
    "sg:postcode":"79603",
    "sg:province":"TX",
    "sg:tags":[
        "clinic"
    ],
    "wof:name":"Waldrip Chiropractic Clinic",
    "wof:placetype":"venue"
},
  "geometry": {"coordinates":[-99.763401,32.452946],"type":"Point"}
}