{
  "type": "Feature",
  "properties": {
    "iso:country":"US",
    "sg:address":"701 E Plano Pkwy",
    "sg:city":"Plano",
    "sg:classifiers":[
        {
            "category":"Wholesale",
            "subcategory":"Machinery & Supplies",
            "type":"Manufacturing & Wholesale Goods"
        }
    ],
    "sg:phone":"+1 972 424 9339",
    "sg:postcode":"75074",
    "sg:province":"TX",
    "sg:tags":[
        "crane",
        "derrick"
    ],
    "sg:website":"www.generalhandling.com",
    "wof:name":"General Handling Systems Inc",
    "wof:placetype":"venue"
},
  "geometry": {"coordinates":[-96.70418600000001,33.007546],"type":"Point"}
}