{
  "type": "Feature",
  "properties": {
    "iso:country":"US",
    "sg:address":"2200 Space Park Dr",
    "sg:city":"Houston",
    "sg:classifiers":[
        {
            "category":"Real Estate",
            "subcategory":"Real Estate Agent",
            "type":"Services"
        }
    ],
    "sg:phone":"+1 281 335 1311",
    "sg:postcode":"77058",
    "sg:province":"TX",
    "wof:name":"Design Services Corporation",
    "wof:placetype":"venue"
},
  "geometry": {"coordinates":[-95.087885,29.547926],"type":"Point"}
}