{
  "type": "Feature",
  "properties": {
    "iso:country":"US",
    "sg:address":"932 W Airport Fwy",
    "sg:city":"Irving",
    "sg:classifiers":[
        {
            "category":"Real Estate",
            "subcategory":"Real Estate Operator",
            "type":"Services"
        }
    ],
    "sg:phone":"+1 254 445 1050",
    "sg:postcode":"75062",
    "sg:province":"TX",
    "sg:tags":[
        "apartment"
    ],
    "wof:name":"Allfinder Apt Locater",
    "wof:placetype":"venue"
},
  "geometry": {"coordinates":[-96.956596,32.8368],"type":"Point"}
}