{
  "type": "Feature",
  "properties": {
    "iso:country":"US",
    "sg:address":"1007 W Gentry Pkwy",
    "sg:city":"Tyler",
    "sg:classifiers":[
        {
            "category":"Organizations",
            "subcategory":"Political Organization",
            "type":"Services"
        }
    ],
    "sg:phone":"+1 903 593 7061",
    "sg:postcode":"75702",
    "sg:province":"TX",
    "wof:name":"Democratic Party-Smith County",
    "wof:placetype":"venue"
},
  "geometry": {"coordinates":[-95.312203,32.359667],"type":"Point"}
}