{
  "type": "Feature",
  "properties": {
    "iso:country":"US",
    "sg:address":"124 Santa Monica Dr",
    "sg:city":"Mabank",
    "sg:classifiers":[
        {
            "category":"Health Services",
            "subcategory":"Doctor",
            "type":"Services"
        }
    ],
    "sg:phone":"+1 903 887 0383",
    "sg:postcode":"75156",
    "sg:province":"TX",
    "wof:name":"Randall L Callison DDS",
    "wof:placetype":"venue"
},
  "geometry": {"coordinates":[-96.141426,32.307126],"type":"Point"}
}