{
  "type": "Feature",
  "properties": {
    "iso:country":"US",
    "sg:address":"1041 N Town East Blvd",
    "sg:city":"Mesquite",
    "sg:classifiers":[
        {
            "category":"Food & Beverages",
            "subcategory":"Groceries & Convenience Stores",
            "type":"Retail Goods"
        }
    ],
    "sg:phone":"+1 972 681 5667",
    "sg:postcode":"75150",
    "sg:province":"TX",
    "sg:website":"www.7-eleven.com",
    "wof:name":"7-Eleven",
    "wof:placetype":"venue"
},
  "geometry": {"coordinates":[-96.611527,32.811253],"type":"Point"}
}