{
  "type": "Feature",
  "properties": {
    "iso:country":"US",
    "sg:address":"4606 FM 1960 W",
    "sg:city":"Houston",
    "sg:classifiers":[
        {
            "category":"Professional",
            "subcategory":"Lawyer & Legal Services",
            "type":"Services"
        }
    ],
    "sg:phone":"+1 281 583 7553",
    "sg:postcode":"77069",
    "sg:province":"TX",
    "wof:name":"Buskirk Assoc Attorney At Law",
    "wof:placetype":"venue"
},
  "geometry": {"coordinates":[-95.49987400000001,29.987105],"type":"Point"}
}