{
  "type": "Feature",
  "properties": {
    "iso:country":"US",
    "sg:address":"9501 Hwy 377 S",
    "sg:city":"Benbrook",
    "sg:classifiers":[
        {
            "category":"Food & Beverages",
            "subcategory":"Groceries & Convenience Stores",
            "type":"Retail Goods"
        }
    ],
    "sg:phone":"+1 817 249 8013",
    "sg:postcode":"76126",
    "sg:province":"TX",
    "wof:name":"Quickway",
    "wof:placetype":"venue"
},
  "geometry": {"coordinates":[-97.47376800000001,32.669179],"type":"Point"}
}