{
  "type": "Feature",
  "properties": {
    "iso:country":"US",
    "sg:address":"914 FM 1431",
    "sg:city":"Marble Falls",
    "sg:classifiers":[
        {
            "category":"Professional",
            "type":"Services"
        }
    ],
    "sg:phone":"+1 830 693 0789",
    "sg:postcode":"78654",
    "sg:province":"TX",
    "sg:tags":[
        "establishment"
    ],
    "wof:name":"Outdoor Heritage",
    "wof:placetype":"venue"
},
  "geometry": {"coordinates":[-98.273178,30.578445],"type":"Point"}
}