{
  "type": "Feature",
  "properties": {
    "iso:country":"US",
    "sg:address":"11506 Wickhollow Ln",
    "sg:city":"Houston",
    "sg:classifiers":[
        {
            "category":"Banks & Credit Unions",
            "subcategory":"Financial Services",
            "type":"Services"
        }
    ],
    "sg:phone":"+1 281 679 1105",
    "sg:postcode":"77043",
    "sg:province":"TX",
    "sg:tags":[
        "investor"
    ],
    "wof:name":"Melton & Denson Inv Group",
    "wof:placetype":"venue"
},
  "geometry": {"coordinates":[-95.58678999999999,29.78974],"type":"Point"}
}