{
  "type": "Feature",
  "properties": {
    "iso:country":"US",
    "sg:address":"13533 Balmore Cir",
    "sg:city":"Houston",
    "sg:classifiers":[
        {
            "category":"Banks & Credit Unions",
            "subcategory":"Bank",
            "type":"Services"
        }
    ],
    "sg:phone":"+1 281 583 0070",
    "sg:postcode":"77069",
    "sg:province":"TX",
    "sg:tags":[
        "mortgage"
    ],
    "wof:name":"Amstar Mortgage Corporation",
    "wof:placetype":"venue"
},
  "geometry": {"coordinates":[-95.515952,29.987392],"type":"Point"}
}