{
  "type": "Feature",
  "properties": {
    "iso:country":"US",
    "sg:address":"100 McClintock Dr",
    "sg:city":"El Paso",
    "sg:classifiers":[
        {
            "category":"Building & Trades",
            "subcategory":"Construction",
            "type":"Services"
        }
    ],
    "sg:phone":"+1 915 587 6615",
    "sg:postcode":"79932",
    "sg:province":"TX",
    "sg:tags":[
        "home",
        "builder"
    ],
    "wof:name":"Tierra Del Sol Housing Corp",
    "wof:placetype":"venue"
},
  "geometry": {"coordinates":[-106.58088499999999,31.844136],"type":"Point"}
}