{
  "type": "Feature",
  "properties": {
    "iso:country":"US",
    "sg:address":"305 Pace Bend Rd S",
    "sg:city":"Spicewood",
    "sg:classifiers":[
        {
            "category":"Food & Beverages",
            "subcategory":"Liquor & Beverages",
            "type":"Retail Goods"
        }
    ],
    "sg:phone":"+1 512 264 0068",
    "sg:postcode":"78669",
    "sg:province":"TX",
    "wof:name":"Pace Bend Liquor & Deli",
    "wof:placetype":"venue"
},
  "geometry": {"coordinates":[-98.058622,30.407611],"type":"Point"}
}