{
  "type": "Feature",
  "properties": {
    "iso:country":"US",
    "sg:address":"32211 Skyway St",
    "sg:city":"Waller",
    "sg:classifiers":[
        {
            "category":"Real Estate",
            "subcategory":"Real Estate Agent",
            "type":"Services"
        }
    ],
    "sg:phone":"+1 936 931 3699",
    "sg:postcode":"77484",
    "sg:province":"TX",
    "wof:name":"A & L Royalty",
    "wof:placetype":"venue"
},
  "geometry": {"coordinates":[-95.931944,29.991514],"type":"Point"}
}