{
  "type": "Feature",
  "properties": {
    "iso:country":"US",
    "sg:address":"604 Chinaberry Ct",
    "sg:city":"Cedar Park",
    "sg:classifiers":[
        {
            "category":"Shopping",
            "subcategory":"Beauty & Cosmetics",
            "type":"Retail Goods"
        }
    ],
    "sg:phone":"+1 512 635 4533",
    "sg:postcode":"78613",
    "sg:province":"TX",
    "sg:tags":[
        "merchandise"
    ],
    "wof:name":"U Anew",
    "wof:placetype":"venue"
},
  "geometry": {"coordinates":[-97.82755400000001,30.49974],"type":"Point"}
}