{
  "type": "Feature",
  "properties": {
    "iso:country":"US",
    "sg:address":"213 E University Blvd",
    "sg:city":"Odessa",
    "sg:classifiers":[
        {
            "category":"Personal",
            "subcategory":"Shoe Repair & Shine",
            "type":"Services"
        }
    ],
    "sg:phone":"+1 432 337 1742",
    "sg:postcode":"79762",
    "sg:province":"TX",
    "sg:tags":[
        "repairing",
        "boot"
    ],
    "wof:name":"Ruben & Sons Boot & Shoe Repr",
    "wof:placetype":"venue"
},
  "geometry": {"coordinates":[-102.379356,31.868578],"type":"Point"}
}