{
  "type": "Feature",
  "properties": {
    "iso:country":"US",
    "sg:address":"1001 Preston 4th Fl",
    "sg:city":"Houston",
    "sg:classifiers":[
        {
            "category":"Government",
            "subcategory":"City Hall",
            "type":"Public Place"
        },
        {
            "category":"Personal",
            "type":"Services"
        }
    ],
    "sg:phone":"+1 713 755 6965",
    "sg:postcode":"77002",
    "sg:province":"TX",
    "sg:tags":[
        "local"
    ],
    "sg:website":"www.harrisvotes.org",
    "wof:name":"Harris County Elections Division",
    "wof:placetype":"venue"
},
  "geometry": {"coordinates":[-95.36067199999999,29.761494],"type":"Point"}
}