{
  "type": "Feature",
  "properties": {
    "iso:country":"US",
    "sg:address":"6859 Tokalon Dr",
    "sg:city":"Dallas",
    "sg:classifiers":[
        {
            "category":"Professional",
            "subcategory":"Business Services",
            "type":"Services"
        }
    ],
    "sg:phone":"+1 214 324 5245",
    "sg:postcode":"75214",
    "sg:province":"TX",
    "wof:name":"Jsc Group",
    "wof:placetype":"venue"
},
  "geometry": {"coordinates":[-96.741871,32.819911],"type":"Point"}
}