{
  "type": "Feature",
  "properties": {
    "iso:country":"US",
    "sg:address":"6565 S Loop Fwy",
    "sg:city":"Houston",
    "sg:classifiers":[
        {
            "category":"Social Services",
            "subcategory":"Child Care",
            "type":"Services"
        }
    ],
    "sg:phone":"+1 281 495 6608",
    "sg:postcode":"77087",
    "sg:province":"TX",
    "wof:name":"Sarah James Jeaneva",
    "wof:placetype":"venue"
},
  "geometry": {"coordinates":[-95.311436,29.697567],"type":"Point"}
}