{
  "type": "Feature",
  "properties": {
    "iso:country":"US",
    "sg:address":"119 N 1st St",
    "sg:city":"Harlingen",
    "sg:classifiers":[
        {
            "category":"Organizations",
            "subcategory":"Religious Organization",
            "type":"Services"
        }
    ],
    "sg:phone":"+1 956 428 8477",
    "sg:postcode":"78550",
    "sg:province":"TX",
    "wof:name":"Harvest Pavilion Of Faith",
    "wof:placetype":"venue"
},
  "geometry": {"coordinates":[-97.69568700000001,26.193611],"type":"Point"}
}