{
  "type": "Feature",
  "properties": {
    "iso:country":"US",
    "sg:address":"1620 Niagara Blvd",
    "sg:city":"Lewisville",
    "sg:classifiers":[
        {
            "category":"Professional",
            "subcategory":"Management & Consulting",
            "type":"Services"
        }
    ],
    "sg:phone":"+1 972 317 8449",
    "sg:postcode":"75077",
    "sg:province":"TX",
    "sg:tags":[
        "retail",
        "direct",
        "sales"
    ],
    "wof:name":"Warm Fuzzies",
    "wof:placetype":"venue"
},
  "geometry": {"coordinates":[-97.04006,33.065509],"type":"Point"}
}