{
  "type": "Feature",
  "properties": {
    "iso:country":"US",
    "sg:address":"6225 County Road 325",
    "sg:city":"Blanket",
    "sg:classifiers":[
        {
            "category":"Building & Trades",
            "subcategory":"Construction",
            "type":"Services"
        },
        {
            "category":"Military Area",
            "subcategory":"Armory",
            "type":"Public Place"
        }
    ],
    "sg:phone":"+1 325 748 3021",
    "sg:postcode":"76432",
    "sg:province":"TX",
    "sg:tags":[
        "repair",
        "fence-sales",
        "fence",
        "contractor"
    ],
    "wof:name":"Adams Fence Co",
    "wof:placetype":"venue"
},
  "geometry": {"coordinates":[-98.810925,31.803565],"type":"Point"}
}