{
  "type": "Feature",
  "properties": {
    "iso:country":"US",
    "sg:address":"1427 S Reynolds St",
    "sg:city":"Alice",
    "sg:classifiers":[
        {
            "category":"Food & Beverages",
            "subcategory":"Groceries & Convenience Stores",
            "type":"Retail Goods"
        }
    ],
    "sg:phone":"+1 361 664 1982",
    "sg:postcode":"78332",
    "sg:province":"TX",
    "wof:name":"Economy Drive In 616",
    "wof:placetype":"venue"
},
  "geometry": {"coordinates":[-98.073307,27.736918],"type":"Point"}
}