{
  "type": "Feature",
  "properties": {
    "iso:country":"US",
    "sg:address":"6741 Savannah Ln",
    "sg:city":"Fort Worth",
    "sg:classifiers":[
        {
            "category":"Professional",
            "subcategory":"Management & Consulting",
            "type":"Services"
        }
    ],
    "sg:phone":"+1 817 370 1221",
    "sg:postcode":"76132",
    "sg:province":"TX",
    "wof:name":"Amandaline Management LLC",
    "wof:placetype":"venue"
},
  "geometry": {"coordinates":[-97.428372,32.673216],"type":"Point"}
}