{
  "type": "Feature",
  "properties": {
    "iso:country":"US",
    "sg:address":"1829 Rustic Dr",
    "sg:city":"Plano",
    "sg:classifiers":[
        {
            "category":"Organizations",
            "subcategory":"Professional Association",
            "type":"Services"
        }
    ],
    "sg:phone":"+1 972 964 8383",
    "sg:postcode":"75075",
    "sg:province":"TX",
    "sg:tags":[
        "business"
    ],
    "wof:name":"Vertical Commerce Solutio",
    "wof:placetype":"venue"
},
  "geometry": {"coordinates":[-96.73372500000001,33.024191],"type":"Point"}
}