{
  "type": "Feature",
  "properties": {
    "iso:country":"US",
    "sg:address":"6873 S Gessner Rd",
    "sg:city":"Houston",
    "sg:classifiers":[
        {
            "category":"Restaurant",
            "type":"Food & Drink"
        }
    ],
    "sg:phone":"+1 713 988 0137",
    "sg:postcode":"77036",
    "sg:province":"TX",
    "wof:name":"Ranchito Taqueria",
    "wof:placetype":"venue"
},
  "geometry": {"coordinates":[-95.538026,29.705824],"type":"Point"}
}