{
  "type": "Feature",
  "properties": {
    "iso:country":"US",
    "sg:address":"8901 Main St",
    "sg:city":"Frisco",
    "sg:classifiers":[
        {
            "category":"Shopping",
            "subcategory":"Used Merchandise",
            "type":"Retail Goods"
        }
    ],
    "sg:phone":"+1 972 335 1002",
    "sg:postcode":"75034",
    "sg:province":"TX",
    "wof:name":"Frisco Jewelry & Loan Inc",
    "wof:placetype":"venue"
},
  "geometry": {"coordinates":[-96.805537,33.151794],"type":"Point"}
}