{
  "type": "Feature",
  "properties": {
    "iso:country":"US",
    "sg:address":"4416 Travis St",
    "sg:city":"Dallas",
    "sg:classifiers":[
        {
            "category":"Professional",
            "subcategory":"Management & Consulting",
            "type":"Services"
        }
    ],
    "sg:phone":"+1 214 219 4696",
    "sg:postcode":"75205",
    "sg:province":"TX",
    "sg:tags":[
        "business"
    ],
    "wof:name":"Case In Point Consulting",
    "wof:placetype":"venue"
},
  "geometry": {"coordinates":[-96.79119300000001,32.821763],"type":"Point"}
}