{
  "type": "Feature",
  "properties": {
    "iso:country":"US",
    "sg:address":"604 Wady Ln",
    "sg:city":"Gladewater",
    "sg:classifiers":[
        {
            "category":"Retail",
            "subcategory":"Auto Repair",
            "type":"Services"
        }
    ],
    "sg:phone":"+1 903 981 1200",
    "sg:postcode":"75647",
    "sg:province":"TX",
    "sg:tags":[
        "recreational",
        "vehicle"
    ],
    "wof:name":"Mc Donald's Sales",
    "wof:placetype":"venue"
},
  "geometry": {"coordinates":[-94.986249,32.455185],"type":"Point"}
}