{
  "type": "Feature",
  "properties": {
    "iso:country":"US",
    "sg:address":"200 N Sanders St",
    "sg:city":"Winters",
    "sg:classifiers":[
        {
            "category":"Real Estate",
            "subcategory":"Real Estate Agent",
            "type":"Services"
        }
    ],
    "sg:phone":"+1 325 754 1238",
    "sg:postcode":"79567",
    "sg:province":"TX",
    "wof:name":"Underwood Realestate",
    "wof:placetype":"venue"
},
  "geometry": {"coordinates":[-99.970664,31.95974],"type":"Point"}
}