{
  "type": "Feature",
  "properties": {
    "iso:country":"US",
    "sg:address":"100 E Swordfish St",
    "sg:city":"S Padre Island",
    "sg:classifiers":[
        {
            "category":"Building & Trades",
            "subcategory":"Construction",
            "type":"Services"
        }
    ],
    "sg:phone":"+1 956 761 6007",
    "sg:postcode":"78597",
    "sg:province":"TX",
    "sg:tags":[
        "general",
        "contractor"
    ],
    "wof:name":"Bay Area Construction",
    "wof:placetype":"venue"
},
  "geometry": {"coordinates":[-97.165059,26.10493],"type":"Point"}
}