{
  "type": "Feature",
  "properties": {
    "iso:country":"US",
    "sg:address":"3015 Grovey St",
    "sg:city":"Houston",
    "sg:classifiers":[
        {
            "category":"Professional",
            "subcategory":"Business Services",
            "type":"Services"
        }
    ],
    "sg:phone":"+1 713 675 5994",
    "sg:postcode":"77026",
    "sg:province":"TX",
    "sg:tags":[
        "used",
        "merchandise"
    ],
    "wof:name":"Gary L Willis",
    "wof:placetype":"venue"
},
  "geometry": {"coordinates":[-95.33324,29.79055],"type":"Point"}
}