{
  "type": "Feature",
  "properties": {
    "iso:country":"US",
    "sg:address":"2903 Roosevelt Ave",
    "sg:city":"Fort Worth",
    "sg:classifiers":[
        {
            "category":"Restaurant",
            "type":"Food & Drink"
        }
    ],
    "sg:phone":"+1 817 625 2593",
    "sg:postcode":"76106",
    "sg:province":"TX",
    "sg:tags":[
        "eating"
    ],
    "wof:name":"Tomas Tacos",
    "wof:placetype":"venue"
},
  "geometry": {"coordinates":[-97.36837800000001,32.798037],"type":"Point"}
}