{
  "type": "Feature",
  "properties": {
    "iso:country":"US",
    "sg:address":"12205 Forsythe Dr",
    "sg:city":"Austin",
    "sg:classifiers":[
        {
            "category":"Building & Trades",
            "subcategory":"Construction",
            "type":"Services"
        }
    ],
    "sg:phone":"+1 512 835 6213",
    "sg:postcode":"78759",
    "sg:province":"TX",
    "sg:tags":[
        "hanging",
        "contractor"
    ],
    "wof:name":"Ofelias Painting",
    "wof:placetype":"venue"
},
  "geometry": {"coordinates":[-97.714727,30.415236],"type":"Point"}
}