{
  "type": "Feature",
  "properties": {
    "iso:country":"US",
    "sg:address":"27620 Tomball Pkwy",
    "sg:city":"Tomball",
    "sg:classifiers":[
        {
            "category":"Insurance",
            "subcategory":"Insurance Agent",
            "type":"Services"
        }
    ],
    "sg:phone":"+1 281 351 2886",
    "sg:postcode":"77375",
    "sg:province":"TX",
    "sg:website":"www.kenschultzinsurance.com",
    "wof:name":"Ken Schultz Insurance Agency",
    "wof:placetype":"venue"
},
  "geometry": {"coordinates":[-95.625243,30.07062],"type":"Point"}
}