{
  "type": "Feature",
  "properties": {
    "iso:country":"US",
    "sg:address":"14528 Hempstead Rd",
    "sg:city":"Houston",
    "sg:classifiers":[
        {
            "category":"Manufacturing",
            "subcategory":"Tools & Machinery",
            "type":"Manufacturing & Wholesale Goods"
        }
    ],
    "sg:phone":"+1 713 939 7858",
    "sg:postcode":"77040",
    "sg:province":"TX",
    "sg:tags":[
        "die",
        "maker",
        "mfg"
    ],
    "wof:name":"Elite Machine",
    "wof:placetype":"venue"
},
  "geometry": {"coordinates":[-95.53922,29.858159],"type":"Point"}
}