{
  "type": "Feature",
  "properties": {
    "iso:country":"US",
    "sg:address":"1201 Piney Woods Dr",
    "sg:city":"Friendswood",
    "sg:classifiers":[
        {
            "category":"Manufacturing",
            "subcategory":"Wood Products",
            "type":"Manufacturing & Wholesale Goods"
        }
    ],
    "sg:phone":"+1 281 648 9300",
    "sg:postcode":"77546",
    "sg:province":"TX",
    "sg:tags":[
        "mfg"
    ],
    "wof:name":"Down Stream",
    "wof:placetype":"venue"
},
  "geometry": {"coordinates":[-95.211995,29.504474],"type":"Point"}
}