{
  "type": "Feature",
  "properties": {
    "iso:country":"US",
    "sg:address":"4230 Annawood Cir",
    "sg:city":"Spring",
    "sg:classifiers":[
        {
            "category":"Shopping",
            "subcategory":"Used Merchandise",
            "type":"Retail Goods"
        }
    ],
    "sg:phone":"+1 281 288 6404",
    "sg:postcode":"77388",
    "sg:province":"TX",
    "wof:name":"Empty Nest Antiques",
    "wof:placetype":"venue"
},
  "geometry": {"coordinates":[-95.47694199999999,30.030072],"type":"Point"}
}