{
  "type": "Feature",
  "properties": {
    "iso:country":"US",
    "sg:address":"2323 Clear Lake City Blvd",
    "sg:city":"Webster",
    "sg:classifiers":[
        {
            "category":"Personal",
            "subcategory":"Nail Salon",
            "type":"Services"
        }
    ],
    "sg:phone":"+1 281 488 0041",
    "sg:postcode":"77598",
    "sg:province":"TX",
    "wof:name":"City Nails Two",
    "wof:placetype":"venue"
},
  "geometry": {"coordinates":[-95.157822,29.58009],"type":"Point"}
}