{
  "type": "Feature",
  "properties": {
    "iso:country":"US",
    "sg:address":"1700 S Southeast Loop 323",
    "sg:city":"Tyler",
    "sg:classifiers":[
        {
            "category":"Donuts",
            "subcategory":"None",
            "type":"Food & Drink"
        }
    ],
    "sg:phone":"+1 903 566 0006",
    "sg:postcode":"75701",
    "sg:province":"TX",
    "sg:tags":[
        "shop"
    ],
    "wof:name":"Shipley Donuts",
    "wof:placetype":"venue"
},
  "geometry": {"coordinates":[-95.26613999999999,32.33058],"type":"Point"}
}