{
  "type": "Feature",
  "properties": {
    "iso:country":"US",
    "sg:address":"8720 Fulton St",
    "sg:city":"Houston",
    "sg:classifiers":[
        {
            "category":"Retail",
            "subcategory":"Auto Repair",
            "type":"Services"
        }
    ],
    "sg:phone":"+1 713 699 4221",
    "sg:postcode":"77022",
    "sg:province":"TX",
    "wof:name":"Fulton Auto Sales & Repair",
    "wof:placetype":"venue"
},
  "geometry": {"coordinates":[-95.37539700000001,29.8395],"type":"Point"}
}