{
  "type": "Feature",
  "properties": {
    "iso:country":"US",
    "sg:address":"2202 113th St",
    "sg:city":"Grand Prairie",
    "sg:classifiers":[
        {
            "category":"Manufacturing",
            "subcategory":"Pet Food",
            "type":"Manufacturing & Wholesale Goods"
        }
    ],
    "sg:phone":"+1 972 601 9117",
    "sg:postcode":"75050",
    "sg:province":"TX",
    "sg:tags":[
        "grocery",
        "jewelry",
        "mfg"
    ],
    "wof:name":"Bil Jac of Texas",
    "wof:placetype":"venue"
},
  "geometry": {"coordinates":[-97.04203200000001,32.7871],"type":"Point"}
}