{
  "type": "Feature",
  "properties": {
    "iso:country":"US",
    "sg:address":"1732 Autumn Ridge Ln",
    "sg:city":"Grapevine",
    "sg:classifiers":[
        {
            "category":"Professional",
            "subcategory":"Computer Services",
            "type":"Services"
        }
    ],
    "sg:phone":"+1 817 421 4434",
    "sg:postcode":"76051",
    "sg:province":"TX",
    "sg:tags":[
        "related"
    ],
    "wof:name":"Trimeta Corp",
    "wof:placetype":"venue"
},
  "geometry": {"coordinates":[-97.09562099999999,32.957461],"type":"Point"}
}