{
  "type": "Feature",
  "properties": {
    "iso:country":"US",
    "sg:address":"101 S May St",
    "sg:city":"Whitewright",
    "sg:classifiers":[
        {
            "category":"Building & Trades",
            "subcategory":"Construction",
            "type":"Services"
        }
    ],
    "sg:phone":"+1 903 364 5341",
    "sg:postcode":"75491",
    "sg:province":"TX",
    "sg:tags":[
        "contractor"
    ],
    "wof:name":"A -Tech Foundation Repair",
    "wof:placetype":"venue"
},
  "geometry": {"coordinates":[-96.38632699999999,33.512541],"type":"Point"}
}