{
  "type": "Feature",
  "properties": {
    "iso:country":"US",
    "sg:address":"251 4th St",
    "sg:city":"Del Rio",
    "sg:classifiers":[
        {
            "category":"Professional",
            "subcategory":"Business Services",
            "type":"Services"
        }
    ],
    "sg:phone":"+1 830 298 5029",
    "sg:postcode":"75142",
    "sg:province":"TX",
    "wof:name":"Gsa 47th Ces Ceoe",
    "wof:placetype":"venue"
},
  "geometry": {"coordinates":[-96.293482,32.588632],"type":"Point"}
}