{
  "type": "Feature",
  "properties": {
    "iso:country":"US",
    "sg:address":"8016 Englewood Ave",
    "sg:city":"Lubbock",
    "sg:classifiers":[
        {
            "category":"Insurance",
            "subcategory":"Insurance Agent",
            "type":"Services"
        }
    ],
    "sg:phone":"+1 806 794 5104",
    "sg:postcode":"79424",
    "sg:province":"TX",
    "wof:name":"Tom Reynolds Insurance",
    "wof:placetype":"venue"
},
  "geometry": {"coordinates":[-101.937697,33.519843],"type":"Point"}
}