{
  "type": "Feature",
  "properties": {
    "iso:country":"US",
    "sg:address":"123 Main St",
    "sg:city":"Muleshoe",
    "sg:classifiers":[
        {
            "category":"Retail",
            "subcategory":"Laundry & Dry Cleaning",
            "type":"Services"
        }
    ],
    "sg:phone":"+1 806 272 4726",
    "sg:postcode":"79347",
    "sg:province":"TX",
    "sg:tags":[
        "cleaners"
    ],
    "wof:name":"Lambert Cleaners",
    "wof:placetype":"venue"
},
  "geometry": {"coordinates":[-102.722944,34.225401],"type":"Point"}
}