{
  "type": "Feature",
  "properties": {
    "iso:country":"US",
    "sg:address":"1213 Crabtree Ct",
    "sg:city":"Cedar Hill",
    "sg:classifiers":[
        {
            "category":"Professional",
            "subcategory":"Employment Agencies",
            "type":"Services"
        }
    ],
    "sg:phone":"+1 972 291 2021",
    "sg:postcode":"75104",
    "sg:province":"TX",
    "wof:name":"Cultural Connection",
    "wof:placetype":"venue"
},
  "geometry": {"coordinates":[-96.954036,32.564935],"type":"Point"}
}