{
  "type": "Feature",
  "properties": {
    "iso:country":"US",
    "sg:address":"185 Camp St",
    "sg:city":"Vidor",
    "sg:classifiers":[
        {
            "category":"Place Of Worship",
            "subcategory":"Church",
            "type":"Public Place"
        },
        {
            "category":"Place Of Worship",
            "type":"Public Place"
        }
    ],
    "sg:phone":"+1 409 769 9055",
    "sg:postcode":"77662",
    "sg:province":"TX",
    "sg:tags":[
        "churches-pentecostal-independent",
        "churches-pentecostal"
    ],
    "wof:name":"First United Pentecostal Church",
    "wof:placetype":"venue"
},
  "geometry": {"coordinates":[-94.012281,30.126632],"type":"Point"}
}