{
  "type": "Feature",
  "properties": {
    "iso:country":"US",
    "sg:address":"1015 Summers Dr",
    "sg:city":"Missouri City",
    "sg:classifiers":[
        {
            "category":"Professional",
            "subcategory":"Management & Consulting",
            "type":"Services"
        }
    ],
    "sg:phone":"+1 281 438 0256",
    "sg:postcode":"77489",
    "sg:province":"TX",
    "wof:name":"Dgm Management",
    "wof:placetype":"venue"
},
  "geometry": {"coordinates":[-95.516406,29.602722],"type":"Point"}
}