{
  "type": "Feature",
  "properties": {
    "iso:country":"US",
    "sg:address":"7120 Blanco Rd",
    "sg:city":"San Antonio",
    "sg:classifiers":[
        {
            "category":"Shopping",
            "subcategory":"Jewelry",
            "type":"Retail Goods"
        }
    ],
    "sg:phone":"+1 210 342 3412",
    "sg:postcode":"78216",
    "sg:province":"TX",
    "sg:tags":[
        "repair"
    ],
    "wof:name":"James Avery Craftsman Inc",
    "wof:placetype":"venue"
},
  "geometry": {"coordinates":[-98.505912,29.521753],"type":"Point"}
}