{
  "type": "Feature",
  "properties": {
    "iso:country":"US",
    "sg:address":"156 Co Rd 117",
    "sg:city":"Alice",
    "sg:classifiers":[
        {
            "category":"Wholesale",
            "subcategory":"Machinery & Supplies",
            "type":"Manufacturing & Wholesale Goods"
        }
    ],
    "sg:phone":"+1 361 664 7561",
    "sg:postcode":"78332",
    "sg:province":"TX",
    "sg:tags":[
        "field",
        "oil",
        "equipment"
    ],
    "wof:name":"Franks' Service & Equipment",
    "wof:placetype":"venue"
},
  "geometry": {"coordinates":[-98.083664,27.775668],"type":"Point"}
}