{
  "type": "Feature",
  "properties": {
    "iso:country":"US",
    "sg:address":"5533 Crosscreek Ln",
    "sg:city":"Fort Worth",
    "sg:classifiers":[
        {
            "category":"Professional",
            "subcategory":"Engineering",
            "type":"Services"
        }
    ],
    "sg:phone":"+1 817 732 2445",
    "sg:postcode":"76109",
    "sg:province":"TX",
    "wof:name":"Daryl A Pritchard",
    "wof:placetype":"venue"
},
  "geometry": {"coordinates":[-97.41333,32.69283],"type":"Point"}
}