{
  "type": "Feature",
  "properties": {
    "iso:country":"US",
    "sg:address":"333 N Central Expy",
    "sg:city":"Richardson",
    "sg:classifiers":[
        {
            "category":"Retail",
            "subcategory":"Auto Repair",
            "type":"Services"
        }
    ],
    "sg:phone":"+1 817 329 7717",
    "sg:postcode":"75080",
    "sg:province":"TX",
    "sg:tags":[
        "body",
        "shop"
    ],
    "wof:name":"Dent Zone Inc",
    "wof:placetype":"venue"
},
  "geometry": {"coordinates":[-96.73249800000001,32.955002],"type":"Point"}
}