{
  "type": "Feature",
  "properties": {
    "iso:country":"US",
    "sg:address":"6207 Oakmont Blvd",
    "sg:city":"Fort Worth",
    "sg:classifiers":[
        {
            "category":"Personal",
            "subcategory":"Beauty Salon",
            "type":"Services"
        }
    ],
    "sg:phone":"+1 817 263 8023",
    "sg:postcode":"76132",
    "sg:province":"TX",
    "sg:tags":[
        "shop"
    ],
    "wof:name":"Great Clips",
    "wof:placetype":"venue"
},
  "geometry": {"coordinates":[-97.402608,32.66272],"type":"Point"}
}