{
  "type": "Feature",
  "properties": {
    "iso:country":"US",
    "sg:address":"810 Everest St",
    "sg:city":"San Antonio",
    "sg:classifiers":[
        {
            "category":"Building & Trades",
            "subcategory":"Landscaping Services",
            "type":"Services"
        }
    ],
    "sg:phone":"+1 210 822 2523",
    "sg:postcode":"78209",
    "sg:province":"TX",
    "sg:tags":[
        "supply"
    ],
    "wof:name":"Four Seasons Lawn Care",
    "wof:placetype":"venue"
},
  "geometry": {"coordinates":[-98.471176,29.512461],"type":"Point"}
}