{
  "type": "Feature",
  "properties": {
    "iso:country":"US",
    "sg:address":"900 8th St",
    "sg:city":"Wichita Falls",
    "sg:classifiers":[
        {
            "category":"Professional",
            "subcategory":"Lawyer & Legal Services",
            "type":"Services"
        }
    ],
    "sg:phone":"+1 940 761 1777",
    "sg:postcode":"76301",
    "sg:province":"TX",
    "sg:tags":[
        "attorney"
    ],
    "wof:name":"Dottie Murphy Law Offices",
    "wof:placetype":"venue"
},
  "geometry": {"coordinates":[-98.49430599999999,33.91065],"type":"Point"}
}