{
  "type": "Feature",
  "properties": {
    "iso:country":"US",
    "sg:address":"1960 W Tarrant Rd",
    "sg:city":"Grand Prairie",
    "sg:classifiers":[
        {
            "category":"Shopping",
            "subcategory":"Catalog Store",
            "type":"Retail Goods"
        }
    ],
    "sg:phone":"+1 972 641 6123",
    "sg:postcode":"75050",
    "sg:province":"TX",
    "sg:tags":[
        "house",
        "order",
        "mail"
    ],
    "wof:name":"Maria's All Occasions Gifts",
    "wof:placetype":"venue"
},
  "geometry": {"coordinates":[-97.030755,32.757058],"type":"Point"}
}