{
  "type": "Feature",
  "properties": {
    "iso:country":"US",
    "sg:address":"3630 Saturn Rd",
    "sg:city":"Garland",
    "sg:classifiers":[
        {
            "category":"Shopping",
            "subcategory":"Mobile Phones",
            "type":"Retail Goods"
        }
    ],
    "sg:phone":"+1 972 271 0901",
    "sg:postcode":"75041",
    "sg:province":"TX",
    "wof:name":"Saturn Wireless",
    "wof:placetype":"venue"
},
  "geometry": {"coordinates":[-96.648056,32.87295],"type":"Point"}
}