{
  "type": "Feature",
  "properties": {
    "iso:country":"US",
    "sg:address":"7756 Northcross Dr",
    "sg:city":"Austin",
    "sg:classifiers":[
        {
            "category":"Home & Garden",
            "subcategory":"Carpets & Floor Coverings",
            "type":"Retail Goods"
        }
    ],
    "sg:phone":"+1 512 452 6639",
    "sg:postcode":"78757",
    "sg:province":"TX",
    "sg:tags":[
        "business"
    ],
    "wof:name":"Austin Flooring Group & Design",
    "wof:placetype":"venue"
},
  "geometry": {"coordinates":[-97.73468699999999,30.352726],"type":"Point"}
}