{
  "type": "Feature",
  "properties": {
    "iso:country":"US",
    "sg:address":"14607 Trophy Club Rd",
    "sg:city":"Houston",
    "sg:classifiers":[
        {
            "category":"Wholesale",
            "subcategory":"Jewelry",
            "type":"Manufacturing & Wholesale Goods"
        }
    ],
    "sg:phone":"+1 281 463 9654",
    "sg:postcode":"77095",
    "sg:province":"TX",
    "sg:tags":[
        "stone"
    ],
    "wof:name":"Beadazzle",
    "wof:placetype":"venue"
},
  "geometry": {"coordinates":[-95.62730500000001,29.891364],"type":"Point"}
}