{
  "type": "Feature",
  "properties": {
    "iso:country":"US",
    "sg:address":"2200 S 10th St",
    "sg:city":"Mcallen",
    "sg:classifiers":[
        {
            "category":"Utilities",
            "subcategory":"Telephone",
            "type":"Services"
        }
    ],
    "sg:phone":"+1 956 687 9561",
    "sg:postcode":"78503",
    "sg:province":"TX",
    "sg:tags":[
        "communications"
    ],
    "wof:name":"AT&T",
    "wof:placetype":"venue"
},
  "geometry": {"coordinates":[-98.23356,26.183135],"type":"Point"}
}