{
  "type": "Feature",
  "properties": {
    "iso:country":"US",
    "sg:address":"1002 Florence Place Rd",
    "sg:city":"Keller",
    "sg:classifiers":[
        {
            "category":"Manufacturing",
            "subcategory":"Tools & Machinery",
            "type":"Manufacturing & Wholesale Goods"
        },
        {
            "category":"Animal Shelter",
            "type":"Public Place"
        },
        {
            "category":"Building & Trades",
            "subcategory":"Pest Control",
            "type":"Services"
        }
    ],
    "sg:phone":"+1 817 379 6003",
    "sg:postcode":"76262",
    "sg:province":"TX",
    "sg:tags":[
        "equipment",
        "removal",
        "termite",
        "spraying",
        "bee"
    ],
    "sg:website":"http://www.venturapolygraph.com",
    "wof:name":"Bob's Best Termite & Pest Control",
    "wof:placetype":"venue"
},
  "geometry": {"coordinates":[-97.21421100000001,32.948848],"type":"Point"}
}