{
  "type": "Feature",
  "properties": {
    "iso:country":"US",
    "sg:address":"1206 Glouchester Ln",
    "sg:city":"Houston",
    "sg:classifiers":[
        {
            "category":"Wholesale",
            "subcategory":"Non-durable Goods",
            "type":"Manufacturing & Wholesale Goods"
        }
    ],
    "sg:phone":"+1 281 209 0946",
    "sg:postcode":"77073",
    "sg:province":"TX",
    "wof:name":"Glynn Associated Whole Sale",
    "wof:placetype":"venue"
},
  "geometry": {"coordinates":[-95.409801,30.033525],"type":"Point"}
}