{
  "type": "Feature",
  "properties": {
    "iso:country":"US",
    "sg:address":"7622 Co Rd 669B",
    "sg:city":"Alvin",
    "sg:classifiers":[
        {
            "category":"Wholesale",
            "subcategory":"Durable Goods & Equipment",
            "type":"Manufacturing & Wholesale Goods"
        }
    ],
    "sg:phone":"+1 281 489 6502",
    "sg:postcode":"77511",
    "sg:province":"TX",
    "wof:name":"Erasmo Ramirez",
    "wof:placetype":"venue"
},
  "geometry": {"coordinates":[-95.28645299999999,29.49948],"type":"Point"}
}