{
  "type": "Feature",
  "properties": {
    "iso:country":"US",
    "sg:address":"1420 W Irving Blvd",
    "sg:city":"Irving",
    "sg:classifiers":[
        {
            "category":"Wholesale",
            "subcategory":"Machinery & Supplies",
            "type":"Manufacturing & Wholesale Goods"
        }
    ],
    "sg:phone":"+1 972 254 2691",
    "sg:postcode":"75061",
    "sg:province":"TX",
    "sg:tags":[
        "equipment"
    ],
    "wof:name":"Efficiency Electrical Contrs",
    "wof:placetype":"venue"
},
  "geometry": {"coordinates":[-96.966765,32.822029],"type":"Point"}
}