{
  "type": "Feature",
  "properties": {
    "iso:country":"US",
    "sg:address":"4110 I- 20 W",
    "sg:city":"Arlington",
    "sg:classifiers":[
        {
            "category":"Mining & Drilling",
            "type":"Manufacturing & Wholesale Goods"
        }
    ],
    "sg:phone":"+1 817 516 9977",
    "sg:postcode":"76017",
    "sg:province":"TX",
    "sg:tags":[
        "field"
    ],
    "wof:name":"D I S/C O N International",
    "wof:placetype":"venue"
},
  "geometry": {"coordinates":[-97.17719200000001,32.675225],"type":"Point"}
}