{
  "type": "Feature",
  "properties": {
    "iso:country":"US",
    "sg:address":"2534 Doverglen Dr",
    "sg:city":"Missouri City",
    "sg:classifiers":[
        {
            "category":"Social Services",
            "subcategory":"Child Care",
            "type":"Services"
        }
    ],
    "sg:phone":"+1 281 438 1728",
    "sg:postcode":"77489",
    "sg:province":"TX",
    "sg:tags":[
        "day"
    ],
    "wof:name":"Tahibodeaux Kasey",
    "wof:placetype":"venue"
},
  "geometry": {"coordinates":[-95.509643,29.592655],"type":"Point"}
}