{
  "type": "Feature",
  "properties": {
    "iso:country":"US",
    "sg:address":"4000 Sunset Dr",
    "sg:city":"San Angelo",
    "sg:classifiers":[
        {
            "category":"Shopping",
            "subcategory":"Optical Goods",
            "type":"Retail Goods"
        }
    ],
    "sg:phone":"+1 325 942 5271",
    "sg:postcode":"76904",
    "sg:province":"TX",
    "sg:tags":[
        "optician"
    ],
    "wof:name":"Sears Optical",
    "wof:placetype":"venue"
},
  "geometry": {"coordinates":[-100.49490400000001,31.428236],"type":"Point"}
}