{
  "type": "Feature",
  "properties": {
    "iso:country":"US",
    "sg:address":"14800 Landmark Blvd",
    "sg:city":"Dallas",
    "sg:classifiers":[
        {
            "category":"Health Services",
            "subcategory":"Nursing And Care Facility",
            "type":"Services"
        },
        {
            "category":"Health Services",
            "subcategory":"Clinic",
            "type":"Services"
        }
    ],
    "sg:phone":"+1 972 789 1802",
    "sg:postcode":"75254",
    "sg:province":"TX",
    "sg:tags":[
        "hospice",
        "home"
    ],
    "wof:name":"Castle Peak Hospice",
    "wof:placetype":"venue"
},
  "geometry": {"coordinates":[-96.827975,32.950547],"type":"Point"}
}