{
  "type": "Feature",
  "properties": {
    "iso:country":"US",
    "sg:address":"2007 Maplewood Dr",
    "sg:city":"Gainesville",
    "sg:classifiers":[
        {
            "category":"Building & Trades",
            "subcategory":"Construction",
            "type":"Services"
        }
    ],
    "sg:phone":"+1 940 668 8180",
    "sg:postcode":"76240",
    "sg:province":"TX",
    "sg:tags":[
        "wooden",
        "walking",
        "cane",
        "mfg"
    ],
    "wof:name":"Bubba & Co",
    "wof:placetype":"venue"
},
  "geometry": {"coordinates":[-97.11836099999999,33.631535],"type":"Point"}
}