{
  "type": "Feature",
  "properties": {
    "iso:country":"US",
    "sg:address":"1204 Boston Ave",
    "sg:city":"Nederland",
    "sg:classifiers":[
        {
            "category":"Home & Garden",
            "subcategory":"Household Appliances",
            "type":"Retail Goods"
        }
    ],
    "sg:phone":"+1 409 729 7397",
    "sg:postcode":"77627",
    "sg:province":"TX",
    "sg:tags":[
        "machine",
        "sewing"
    ],
    "wof:name":"Sew Much More",
    "wof:placetype":"venue"
},
  "geometry": {"coordinates":[-93.991895,29.97514],"type":"Point"}
}