{
  "type": "Feature",
  "properties": {
    "iso:country":"US",
    "sg:address":"9916 Dyer St",
    "sg:city":"El Paso",
    "sg:classifiers":[
        {
            "category":"Personal",
            "subcategory":"Beauty Salon",
            "type":"Services"
        }
    ],
    "sg:phone":"+1 915 757 2003",
    "sg:postcode":"79924",
    "sg:province":"TX",
    "sg:tags":[
        "shop"
    ],
    "wof:name":"Professional Encore",
    "wof:placetype":"venue"
},
  "geometry": {"coordinates":[-106.41097600000001,31.896086],"type":"Point"}
}