{
  "type": "Feature",
  "properties": {
    "iso:country":"US",
    "sg:address":"4501 Travis St",
    "sg:city":"Dallas",
    "sg:classifiers":[
        {
            "category":"Bars & Pubs",
            "type":"Food & Drink"
        },
        {
            "category":"Restaurant",
            "type":"Food & Drink"
        }
    ],
    "sg:phone":"+1 214 528 1731",
    "sg:postcode":"75205",
    "sg:province":"TX",
    "sg:tags":[
        "tapa",
        "spanish"
    ],
    "sg:website":"www.cafemadrid-dallas.com",
    "wof:name":"Cafe Madrid",
    "wof:placetype":"venue"
},
  "geometry": {"coordinates":[-96.791298,32.822102],"type":"Point"}
}