{
  "type": "Feature",
  "properties": {
    "iso:country":"US",
    "sg:address":"6603 Independence Blvd",
    "sg:city":"Baytown",
    "sg:classifiers":[
        {
            "category":"Recreation",
            "type":"Entertainment"
        }
    ],
    "sg:phone":"+1 281 421 2958",
    "sg:postcode":"77521",
    "sg:province":"TX",
    "sg:tags":[
        "entertainers-family",
        "business"
    ],
    "wof:name":"Nm Entertainment",
    "wof:placetype":"venue"
},
  "geometry": {"coordinates":[-94.978104,29.798669],"type":"Point"}
}