{
  "type": "Feature",
  "properties": {
    "iso:country":"US",
    "sg:address":"719 Delgado St",
    "sg:city":"San Antonio",
    "sg:classifiers":[
        {
            "category":"Organizations",
            "subcategory":"Religious Organization",
            "type":"Services"
        }
    ],
    "sg:phone":"+1 210 738 1847",
    "sg:postcode":"78207",
    "sg:province":"TX",
    "wof:name":"Ln Iglesia Deldios Vivo Co",
    "wof:placetype":"venue"
},
  "geometry": {"coordinates":[-98.51563299999999,29.437697],"type":"Point"}
}