{
  "type": "Feature",
  "properties": {
    "iso:country":"US",
    "sg:address":"2400 Ross Ave",
    "sg:city":"Dallas",
    "sg:classifiers":[
        {
            "category":"Professional",
            "subcategory":"Management & Consulting",
            "type":"Services"
        }
    ],
    "sg:phone":"+1 214 720 0201",
    "sg:postcode":"75201",
    "sg:province":"TX",
    "sg:tags":[
        "business"
    ],
    "wof:name":"T Ross Alta",
    "wof:placetype":"venue"
},
  "geometry": {"coordinates":[-96.79577399999999,32.789851],"type":"Point"}
}