{
  "type": "Feature",
  "properties": {
    "iso:country":"US",
    "sg:address":"100 Main St",
    "sg:city":"Hooks",
    "sg:classifiers":[
        {
            "category":"Professional",
            "subcategory":"Engineering",
            "type":"Services"
        },
        {
            "category":"Professional",
            "subcategory":"Research",
            "type":"Services"
        }
    ],
    "sg:phone":"+1 903 223 0780",
    "sg:postcode":"75561",
    "sg:province":"TX",
    "sg:tags":[
        "development",
        "consulting",
        "electronics",
        "engineer"
    ],
    "wof:name":"Bae Systems",
    "wof:placetype":"venue"
},
  "geometry": {"coordinates":[-94.289207,33.466251],"type":"Point"}
}