{
  "type": "Feature",
  "properties": {
    "iso:country":"US",
    "sg:address":"110 W Louisiana Ave",
    "sg:city":"Midland",
    "sg:classifiers":[
        {
            "category":"Mining & Drilling",
            "type":"Manufacturing & Wholesale Goods"
        }
    ],
    "sg:phone":"+1 432 685 0085",
    "sg:postcode":"79701",
    "sg:province":"TX",
    "sg:tags":[
        "oil",
        "gas",
        "producer"
    ],
    "wof:name":"D K Boyd Oil & Gas Co",
    "wof:placetype":"venue"
},
  "geometry": {"coordinates":[-102.075678,32.00383],"type":"Point"}
}