{
  "type": "Feature",
  "properties": {
    "iso:country":"US",
    "sg:address":"817 Ridgehill Ct",
    "sg:city":"Burleson",
    "sg:classifiers":[
        {
            "category":"Personal",
            "subcategory":"Nail Salon",
            "type":"Services"
        }
    ],
    "sg:phone":"+1 817 426 2642",
    "sg:postcode":"76028",
    "sg:province":"TX",
    "wof:name":"Sporty Nails",
    "wof:placetype":"venue"
},
  "geometry": {"coordinates":[-97.34871099999999,32.541679],"type":"Point"}
}