{
  "type": "Feature",
  "properties": {
    "iso:country":"US",
    "sg:address":"1000 W Spring Valley Rd",
    "sg:city":"Richardson",
    "sg:classifiers":[
        {
            "category":"Real Estate",
            "subcategory":"Real Estate Agent",
            "type":"Services"
        }
    ],
    "sg:phone":"+1 972 231 4515",
    "sg:postcode":"75080",
    "sg:province":"TX",
    "sg:tags":[
        "finding",
        "apartment",
        "rental"
    ],
    "wof:name":"1998 Green Acres",
    "wof:placetype":"venue"
},
  "geometry": {"coordinates":[-96.756354,32.94004],"type":"Point"}
}