{
  "type": "Feature",
  "properties": {
    "iso:country":"US",
    "sg:address":"164 W 1st St",
    "sg:city":"Springtown",
    "sg:classifiers":[
        {
            "category":"Professional",
            "subcategory":"Management & Consulting",
            "type":"Services"
        }
    ],
    "sg:phone":"+1 817 220 3993",
    "sg:postcode":"76082",
    "sg:province":"TX",
    "sg:tags":[
        "business"
    ],
    "wof:name":"Aces It Consulting Service",
    "wof:placetype":"venue"
},
  "geometry": {"coordinates":[-97.684301,32.965707],"type":"Point"}
}