{
  "type": "Feature",
  "properties": {
    "iso:country":"US",
    "sg:address":"11929 Edgestone Rd",
    "sg:city":"Dallas",
    "sg:classifiers":[
        {
            "category":"Professional",
            "subcategory":"Computer Services",
            "type":"Services"
        },
        {
            "category":"Internet Cafe",
            "subcategory":"None",
            "type":"Food & Drink"
        }
    ],
    "sg:phone":"+1 972 980 2655",
    "sg:postcode":"75230",
    "sg:province":"TX",
    "sg:tags":[
        "product",
        "software"
    ],
    "sg:website":"http://www.skilledsolutions.com",
    "wof:name":"Skilled Solutions.Com",
    "wof:placetype":"venue"
},
  "geometry": {"coordinates":[-96.78361700000001,32.912368],"type":"Point"}
}