{
  "type": "Feature",
  "properties": {
    "iso:country":"US",
    "sg:address":"145 Donaho Rd",
    "sg:city":"Corsicana",
    "sg:classifiers":[
        {
            "category":"Professional",
            "type":"Services"
        }
    ],
    "sg:phone":"+1 903 874 5355",
    "sg:postcode":"75110",
    "sg:province":"TX",
    "wof:name":"Shannon T Paschal",
    "wof:placetype":"venue"
},
  "geometry": {"coordinates":[-96.467343,32.034135],"type":"Point"}
}