{
  "type": "Feature",
  "properties": {
    "iso:country":"US",
    "sg:address":"11505 Gun Fight Ln",
    "sg:city":"Austin",
    "sg:classifiers":[
        {
            "category":"Personal",
            "type":"Services"
        }
    ],
    "sg:phone":"+1 512 663 3175",
    "sg:postcode":"78748",
    "sg:province":"TX",
    "sg:tags":[
        "miscellaneous"
    ],
    "wof:name":"Just Indulgence",
    "wof:placetype":"venue"
},
  "geometry": {"coordinates":[-97.853911,30.160124],"type":"Point"}
}