{
  "type": "Feature",
  "properties": {
    "iso:country":"US",
    "sg:address":"2719 Pecan Dr",
    "sg:city":"Tyler",
    "sg:classifiers":[
        {
            "category":"Real Estate",
            "subcategory":"Real Estate Services",
            "type":"Services"
        },
        {
            "category":"Building & Trades",
            "subcategory":"Cleaning & Sanitation",
            "type":"Services"
        }
    ],
    "sg:phone":"+1 903 581 6628",
    "sg:postcode":"75701",
    "sg:province":"TX",
    "sg:tags":[
        "maintenance",
        "cleaners-interior"
    ],
    "wof:name":"Cleaner Homes By Diane",
    "wof:placetype":"venue"
},
  "geometry": {"coordinates":[-95.30767299999999,32.318884],"type":"Point"}
}