{
  "type": "Feature",
  "properties": {
    "iso:country":"US",
    "sg:address":"2125 Lake Village Dr",
    "sg:city":"Kingwood",
    "sg:classifiers":[
        {
            "category":"Professional",
            "type":"Services"
        }
    ],
    "sg:phone":"+1 281 359 4390",
    "sg:postcode":"77339",
    "sg:province":"TX",
    "sg:tags":[
        "establishment"
    ],
    "wof:name":"Ipsi",
    "wof:placetype":"venue"
},
  "geometry": {"coordinates":[-95.22474,30.043991],"type":"Point"}
}