{
  "type": "Feature",
  "properties": {
    "iso:country":"US",
    "sg:address":"509 State Hwy 34",
    "sg:city":"Ennis",
    "sg:classifiers":[
        {
            "category":"Autos & Motor Vehicles",
            "subcategory":"Automobile Sales",
            "type":"Retail Goods"
        }
    ],
    "sg:phone":"+1 972 875 6381",
    "sg:postcode":"75119",
    "sg:province":"TX",
    "sg:tags":[
        "a",
        "used",
        "general"
    ],
    "wof:name":"Trinity West Motors",
    "wof:placetype":"venue"
},
  "geometry": {"coordinates":[-96.62495699999999,32.324593],"type":"Point"}
}