{
  "type": "Feature",
  "properties": {
    "iso:country":"US",
    "sg:address":"4503 Cherry Ln",
    "sg:city":"Santa Fe",
    "sg:classifiers":[
        {
            "category":"Retail",
            "subcategory":"Animal Services",
            "type":"Services"
        }
    ],
    "sg:phone":"+1 409 925 7338",
    "sg:postcode":"77517",
    "sg:province":"TX",
    "wof:name":"Cherryville Farms",
    "wof:placetype":"venue"
},
  "geometry": {"coordinates":[-95.155057,29.390089],"type":"Point"}
}