{
  "type": "Feature",
  "properties": {
    "iso:country":"US",
    "sg:address":"2035 Lamar Ave",
    "sg:city":"Paris",
    "sg:classifiers":[
        {
            "category":"Autos & Motor Vehicles",
            "subcategory":"Auto Supplies",
            "type":"Retail Goods"
        },
        {
            "category":"Retail",
            "subcategory":"Auto Repair",
            "type":"Services"
        }
    ],
    "sg:phone":"+1 903 784 5514",
    "sg:postcode":"75460",
    "sg:province":"TX",
    "sg:tags":[
        "automotive",
        "part",
        "automobile"
    ],
    "sg:website":"http://www.oreillyauto.com?utm_source=yellowpages&utm_medium=iyp&utm_campaign=363",
    "wof:name":"O'Reilly Auto Parts",
    "wof:placetype":"venue"
},
  "geometry": {"coordinates":[-95.53459100000001,33.661223],"type":"Point"}
}