{
  "type": "Feature",
  "properties": {
    "iso:country":"US",
    "sg:address":"2307 W Alabama St",
    "sg:city":"Houston",
    "sg:classifiers":[
        {
            "category":"Building & Trades",
            "subcategory":"Construction",
            "type":"Services"
        }
    ],
    "sg:phone":"+1 713 521 2215",
    "sg:postcode":"77098",
    "sg:province":"TX",
    "sg:tags":[
        "contractor"
    ],
    "wof:name":"Pascal Designs",
    "wof:placetype":"venue"
},
  "geometry": {"coordinates":[-95.41475800000001,29.738459],"type":"Point"}
}