{
  "type": "Feature",
  "properties": {
    "iso:country":"US",
    "sg:address":"12220 Squire Dr",
    "sg:city":"Mesquite",
    "sg:classifiers":[
        {
            "category":"Professional",
            "type":"Services"
        }
    ],
    "sg:phone":"+1 972 286 7362",
    "sg:postcode":"75180",
    "sg:province":"TX",
    "wof:name":"Albert Brinkley",
    "wof:placetype":"venue"
},
  "geometry": {"coordinates":[-96.616669,32.711404],"type":"Point"}
}