{
  "type": "Feature",
  "properties": {
    "iso:country":"US",
    "sg:address":"1116 Colony North Dr",
    "sg:city":"Austin",
    "sg:classifiers":[
        {
            "category":"Manufacturing",
            "subcategory":"Aerospace",
            "type":"Manufacturing & Wholesale Goods"
        }
    ],
    "sg:phone":"+1 512 537 9005",
    "sg:postcode":"78758",
    "sg:province":"TX",
    "sg:tags":[
        "equipment",
        "aircraft",
        "part",
        "supply"
    ],
    "wof:name":"Ssi",
    "wof:placetype":"venue"
},
  "geometry": {"coordinates":[-97.71052899999999,30.35675],"type":"Point"}
}