{
  "type": "Feature",
  "properties": {
    "iso:country":"US",
    "sg:address":"209 State Hwy 323",
    "sg:city":"Tyler",
    "sg:classifiers":[
        {
            "category":"Restaurant",
            "type":"Food & Drink"
        }
    ],
    "sg:phone":"+1 903 561 7774",
    "sg:postcode":"75701",
    "sg:province":"TX",
    "sg:tags":[
        "eating"
    ],
    "wof:name":"Pizza Hut",
    "wof:placetype":"venue"
},
  "geometry": {"coordinates":[-95.303038,32.303071],"type":"Point"}
}