{
  "type": "Feature",
  "properties": {
    "iso:country":"US",
    "sg:address":"801 S Bowen Rd",
    "sg:city":"Arlington",
    "sg:classifiers":[
        {
            "category":"Real Estate",
            "subcategory":"Architect",
            "type":"Services"
        }
    ],
    "sg:phone":"+1 817 792 2071",
    "sg:postcode":"76013",
    "sg:province":"TX",
    "sg:tags":[
        "architectural"
    ],
    "wof:name":"Wheaton Don Architects",
    "wof:placetype":"venue"
},
  "geometry": {"coordinates":[-97.149142,32.725741],"type":"Point"}
}