{
  "type": "Feature",
  "properties": {
    "iso:country":"US",
    "sg:address":"25350 Budde Rd",
    "sg:city":"Spring",
    "sg:classifiers":[
        {
            "category":"Retail",
            "subcategory":"Auto Rental",
            "type":"Services"
        }
    ],
    "sg:phone":"+1 281 298 8208",
    "sg:postcode":"77380",
    "sg:province":"TX",
    "sg:tags":[
        "renting",
        "truck",
        "leasing"
    ],
    "wof:name":"U-Haul Co",
    "wof:placetype":"venue"
},
  "geometry": {"coordinates":[-95.449504,30.129486],"type":"Point"}
}