{
  "type": "Feature",
  "properties": {
    "iso:country":"US",
    "sg:address":"3202 Darling Ave",
    "sg:city":"Pasadena",
    "sg:classifiers":[
        {
            "category":"Wholesale",
            "subcategory":"Medical Equipment & Supplies",
            "type":"Manufacturing & Wholesale Goods"
        }
    ],
    "sg:phone":"+1 713 472 6155",
    "sg:postcode":"77503",
    "sg:province":"TX",
    "sg:tags":[
        "physician",
        "surgeon"
    ],
    "wof:name":"Davis Medical Supply Co Inc",
    "wof:placetype":"venue"
},
  "geometry": {"coordinates":[-95.16369,29.709343],"type":"Point"}
}