{
  "type": "Feature",
  "properties": {
    "iso:country":"US",
    "sg:address":"204 E Patton Ave",
    "sg:city":"Alvarado",
    "sg:classifiers":[
        {
            "category":"Social Services",
            "subcategory":"Child Care",
            "type":"Services"
        }
    ],
    "sg:phone":"+1 817 790 0352",
    "sg:postcode":"76009",
    "sg:province":"TX",
    "wof:name":"Kiddie Korral Day Care Ctr",
    "wof:placetype":"venue"
},
  "geometry": {"coordinates":[-97.21017999999999,32.407532],"type":"Point"}
}