{
  "type": "Feature",
  "properties": {
    "iso:country":"US",
    "sg:address":"1517 Tennison Pkwy",
    "sg:city":"Colleyville",
    "sg:classifiers":[
        {
            "category":"Shopping",
            "subcategory":"Bicycles & Sporting Goods",
            "type":"Retail Goods"
        }
    ],
    "sg:phone":"+1 817 442 5193",
    "sg:postcode":"76034",
    "sg:province":"TX",
    "wof:name":"Sons Sporting Goods Inc",
    "wof:placetype":"venue"
},
  "geometry": {"coordinates":[-97.14183199999999,32.907008],"type":"Point"}
}