{
  "type": "Feature",
  "properties": {
    "iso:country":"US",
    "sg:address":"10727 Turbeville Rd",
    "sg:city":"Dallas",
    "sg:classifiers":[
        {
            "category":"Wholesale",
            "subcategory":"Machinery & Supplies",
            "type":"Manufacturing & Wholesale Goods"
        }
    ],
    "sg:phone":"+1 214 343 6843",
    "sg:postcode":"75243",
    "sg:province":"TX",
    "sg:tags":[
        "transmission",
        "equipment",
        "rep",
        "power",
        "mfg"
    ],
    "wof:name":"Sisco",
    "wof:placetype":"venue"
},
  "geometry": {"coordinates":[-96.698592,32.903298],"type":"Point"}
}