{
  "type": "Feature",
  "properties": {
    "iso:country":"US",
    "sg:address":"1090 Lang Rd",
    "sg:city":"Portland",
    "sg:classifiers":[
        {
            "category":"Professional",
            "subcategory":"Detective & Security Services",
            "type":"Services"
        }
    ],
    "sg:phone":"+1 361 643 7387",
    "sg:postcode":"78374",
    "sg:province":"TX",
    "sg:tags":[
        "car"
    ],
    "wof:name":"Billy Watson Private Inve",
    "wof:placetype":"venue"
},
  "geometry": {"coordinates":[-97.333889,27.894258],"type":"Point"}
}