{
  "type": "Feature",
  "properties": {
    "iso:country":"US",
    "sg:address":"2216 S 1st St",
    "sg:city":"Lufkin",
    "sg:classifiers":[
        {
            "category":"Travel",
            "subcategory":"Hotels & Motels",
            "type":"Entertainment"
        }
    ],
    "sg:phone":"+1 936 632 8885",
    "sg:postcode":"75901",
    "sg:province":"TX",
    "sg:tags":[
        "operation"
    ],
    "wof:name":"Super 8 Motel",
    "wof:placetype":"venue"
},
  "geometry": {"coordinates":[-94.72749,31.300405],"type":"Point"}
}