{
  "type": "Feature",
  "properties": {
    "iso:country":"US",
    "sg:address":"115 E Airport Fwy",
    "sg:city":"Irving",
    "sg:classifiers":[
        {
            "category":"Retail",
            "subcategory":"Auto Rental",
            "type":"Services"
        }
    ],
    "sg:phone":"+1 972 594 4473",
    "sg:postcode":"75062",
    "sg:province":"TX",
    "sg:tags":[
        "car"
    ],
    "sg:website":"www.hertz.com",
    "wof:name":"Hertz Rent-A-Car",
    "wof:placetype":"venue"
},
  "geometry": {"coordinates":[-96.94416200000001,32.83728],"type":"Point"}
}