{
  "type": "Feature",
  "properties": {
    "iso:country":"US",
    "sg:address":"13359 N Highway 183 Ste 406",
    "sg:city":"Austin",
    "sg:phone":"+1 512 249 7447",
    "sg:postcode":"78750",
    "sg:province":"TX",
    "sg:website":"http://www.WeShipAustin.com",
    "wof:name":"Pak Mail",
    "wof:placetype":"venue"
},
  "geometry": {"coordinates":[-97.787796,30.444509],"type":"Point"}
}