{
  "type": "Feature",
  "properties": {
    "iso:country":"US",
    "sg:address":"1243 Bellview Rd",
    "sg:city":"Jonesville",
    "sg:classifiers":[
        {
            "category":"Manufacturing",
            "subcategory":"Retail Goods",
            "type":"Manufacturing & Wholesale Goods"
        }
    ],
    "sg:phone":"+1 903 935 5500",
    "sg:postcode":"75692",
    "sg:province":"TX",
    "sg:tags":[
        "manufacturer"
    ],
    "wof:name":"Cutting Edge",
    "wof:placetype":"venue"
},
  "geometry": {"coordinates":[-94.145673,32.501806],"type":"Point"}
}