{
  "type": "Feature",
  "properties": {
    "iso:country":"US",
    "sg:address":"1000 S 9th St",
    "sg:city":"Slaton",
    "sg:classifiers":[
        {
            "category":"Retail",
            "subcategory":"Auto Repair",
            "type":"Services"
        }
    ],
    "sg:phone":"+1 806 828 6447",
    "sg:postcode":"79364",
    "sg:province":"TX",
    "sg:tags":[
        "glass",
        "work",
        "replacement"
    ],
    "wof:name":"Bownds Body Shop",
    "wof:placetype":"venue"
},
  "geometry": {"coordinates":[-101.64301,33.430087],"type":"Point"}
}