{
  "type": "Feature",
  "properties": {
    "iso:country":"US",
    "sg:address":"3312 Buckner Blvd",
    "sg:city":"Dallas",
    "sg:classifiers":[
        {
            "category":"Government",
            "subcategory":"Office",
            "type":"Public Place"
        }
    ],
    "sg:phone":"+1 214 670 8225",
    "sg:postcode":"75228",
    "sg:province":"TX",
    "sg:tags":[
        "city",
        "resource",
        "human"
    ],
    "wof:name":"Dallas WIC Office",
    "wof:placetype":"venue"
},
  "geometry": {"coordinates":[-96.682366,32.804361],"type":"Point"}
}