{
  "type": "Feature",
  "properties": {
    "iso:country":"US",
    "sg:address":"2050 N Stemmons Fwy",
    "sg:city":"Dallas",
    "sg:classifiers":[
        {
            "category":"Building & Trades",
            "subcategory":"Construction",
            "type":"Services"
        }
    ],
    "sg:phone":"+1 214 747 7910",
    "sg:postcode":"75207",
    "sg:province":"TX",
    "sg:tags":[
        "interior",
        "design"
    ],
    "wof:name":"United Design Corporation",
    "wof:placetype":"venue"
},
  "geometry": {"coordinates":[-96.82485699999999,32.803042],"type":"Point"}
}