{
  "type": "Feature",
  "properties": {
    "iso:country":"US",
    "sg:address":"1301 Canterbury Dr",
    "sg:city":"Abilene",
    "sg:classifiers":[
        {
            "category":"Real Estate",
            "subcategory":"Real Estate Agent",
            "type":"Services"
        }
    ],
    "sg:phone":"+1 325 677 4135",
    "sg:postcode":"79602",
    "sg:province":"TX",
    "wof:name":"Juana Watson Realtors",
    "wof:placetype":"venue"
},
  "geometry": {"coordinates":[-99.70467499999999,32.433658],"type":"Point"}
}