{
  "type": "Feature",
  "properties": {
    "iso:country":"US",
    "sg:address":"417 San Jacinto St",
    "sg:city":"Houston",
    "sg:classifiers":[
        {
            "category":"Retail",
            "subcategory":"Repair Shop",
            "type":"Services"
        },
        {
            "category":"Professional",
            "subcategory":"Detective & Security Services",
            "type":"Services"
        }
    ],
    "sg:phone":"+1 713 222 0007",
    "sg:postcode":"77002",
    "sg:province":"TX",
    "sg:tags":[
        "skip",
        "tracing",
        "bail",
        "bond"
    ],
    "wof:name":"A Way Out Bail Bonds",
    "wof:placetype":"venue"
},
  "geometry": {"coordinates":[-95.35969,29.760384],"type":"Point"}
}