{
  "type": "Feature",
  "properties": {
    "iso:country":"US",
    "sg:address":"2103 17th St",
    "sg:city":"Galena Park",
    "sg:classifiers":[
        {
            "category":"Building & Trades",
            "subcategory":"Construction",
            "type":"Services"
        }
    ],
    "sg:phone":"+1 713 678 7189",
    "sg:postcode":"77547",
    "sg:province":"TX",
    "sg:tags":[
        "house"
    ],
    "wof:name":"Rodriguez Roofing & Remodeling",
    "wof:placetype":"venue"
},
  "geometry": {"coordinates":[-95.244118,29.744876],"type":"Point"}
}