{
  "type": "Feature",
  "properties": {
    "iso:country":"US",
    "sg:address":"1016 S Closner Blvd",
    "sg:city":"Edinburg",
    "sg:classifiers":[
        {
            "category":"Professional",
            "subcategory":"Accounting & Tax Preparation",
            "type":"Services"
        }
    ],
    "sg:phone":"+1 956 287 0370",
    "sg:postcode":"78539",
    "sg:province":"TX",
    "wof:name":"Professional Billing Services",
    "wof:placetype":"venue"
},
  "geometry": {"coordinates":[-98.164238,26.290887],"type":"Point"}
}