{
  "type": "Feature",
  "properties": {
    "iso:country":"US",
    "sg:address":"1218 Westminister Ln",
    "sg:city":"Duncanville",
    "sg:classifiers":[
        {
            "category":"Autos & Motor Vehicles",
            "subcategory":"Auto Supplies",
            "type":"Retail Goods"
        }
    ],
    "sg:phone":"+1 972 298 6987",
    "sg:postcode":"75137",
    "sg:province":"TX",
    "sg:tags":[
        "automobile",
        "accessory"
    ],
    "wof:name":"King Wheel Covers",
    "wof:placetype":"venue"
},
  "geometry": {"coordinates":[-96.934865,32.64269],"type":"Point"}
}