{
  "type": "Feature",
  "properties": {
    "iso:country":"US",
    "sg:address":"517 Ave A",
    "sg:city":"Lawn",
    "sg:classifiers":[
        {
            "category":"Retail",
            "subcategory":"Repair Shop",
            "type":"Services"
        }
    ],
    "sg:phone":"+1 325 583 2262",
    "sg:postcode":"79530",
    "sg:province":"TX",
    "wof:name":"Macks Maintenance",
    "wof:placetype":"venue"
},
  "geometry": {"coordinates":[-99.74999099999999,32.132928],"type":"Point"}
}