{
  "type": "Feature",
  "properties": {
    "iso:country":"US",
    "sg:address":"12602 Westheimer Rd",
    "sg:city":"Houston",
    "sg:classifiers":[
        {
            "category":"Autos & Motor Vehicles",
            "subcategory":"Fuel & Gas Station",
            "type":"Retail Goods"
        }
    ],
    "sg:phone":"+1 281 497 3436",
    "sg:postcode":"77077",
    "sg:province":"TX",
    "sg:tags":[
        "station",
        "gasoline"
    ],
    "wof:name":"Ashford Texaco",
    "wof:placetype":"venue"
},
  "geometry": {"coordinates":[-95.60587200000001,29.736253],"type":"Point"}
}