{
  "type": "Feature",
  "properties": {
    "iso:country":"US",
    "sg:address":"1601 N Windy Knoll Dr",
    "sg:city":"Devine",
    "sg:classifiers":[
        {
            "category":"Manufacturing",
            "subcategory":"Retail Goods",
            "type":"Manufacturing & Wholesale Goods"
        }
    ],
    "sg:phone":"+1 830 665 4577",
    "sg:postcode":"78016",
    "sg:province":"TX",
    "sg:tags":[
        "manufacturer"
    ],
    "wof:name":"Morales Industries",
    "wof:placetype":"venue"
},
  "geometry": {"coordinates":[-98.90958999999999,29.154083],"type":"Point"}
}