{
  "type": "Feature",
  "properties": {
    "iso:country":"US",
    "sg:address":"13407 Ravens Caw Dr",
    "sg:city":"Cypress",
    "sg:classifiers":[
        {
            "category":"Professional",
            "subcategory":"Business Services",
            "type":"Services"
        }
    ],
    "sg:phone":"+1 281 890 7065",
    "sg:postcode":"77429",
    "sg:province":"TX",
    "wof:name":"G & M Enterprises",
    "wof:placetype":"venue"
},
  "geometry": {"coordinates":[-95.62615,29.951163],"type":"Point"}
}