{
  "type": "Feature",
  "properties": {
    "iso:country":"US",
    "sg:address":"9901 S Cage Blvd",
    "sg:city":"Pharr",
    "sg:classifiers":[
        {
            "category":"Professional",
            "subcategory":"Detective & Security Services",
            "type":"Services"
        }
    ],
    "sg:phone":"+1 956 787 6874",
    "sg:postcode":"78577",
    "sg:province":"TX",
    "sg:tags":[
        "information",
        "bureau"
    ],
    "wof:name":"Eastco Building Services",
    "wof:placetype":"venue"
},
  "geometry": {"coordinates":[-98.20114700000001,26.092775],"type":"Point"}
}