{
  "type": "Feature",
  "properties": {
    "iso:country":"US",
    "sg:address":"500 E Lawrence St",
    "sg:city":"Dayton",
    "sg:classifiers":[
        {
            "category":"Shopping",
            "subcategory":"Hobbies, Toys, & Games",
            "type":"Retail Goods"
        }
    ],
    "sg:phone":"+1 936 258 9253",
    "sg:postcode":"77535",
    "sg:province":"TX",
    "wof:name":"Anns Art & Crafts",
    "wof:placetype":"venue"
},
  "geometry": {"coordinates":[-94.89161,30.060668],"type":"Point"}
}