{
  "type": "Feature",
  "properties": {
    "iso:country":"US",
    "sg:address":"2950 N Loop Fwy",
    "sg:city":"Houston",
    "sg:classifiers":[
        {
            "category":"Professional",
            "subcategory":"Engineering",
            "type":"Services"
        }
    ],
    "sg:phone":"+1 713 341 7575",
    "sg:postcode":"77092",
    "sg:province":"TX",
    "sg:tags":[
        "engineer"
    ],
    "wof:name":"Matrix Cio",
    "wof:placetype":"venue"
},
  "geometry": {"coordinates":[-95.447343,29.805217],"type":"Point"}
}