{
  "type": "Feature",
  "properties": {
    "iso:country":"US",
    "sg:address":"8931 Rich Trace St",
    "sg:city":"San Antonio",
    "sg:classifiers":[
        {
            "category":"Building & Trades",
            "subcategory":"Cleaning & Sanitation",
            "type":"Services"
        }
    ],
    "sg:phone":"+1 210 522 1421",
    "sg:postcode":"78251",
    "sg:province":"TX",
    "sg:tags":[
        "maintenance"
    ],
    "wof:name":"Clean Corners",
    "wof:placetype":"venue"
},
  "geometry": {"coordinates":[-98.658568,29.449653],"type":"Point"}
}