{
  "type": "Feature",
  "properties": {
    "iso:country":"US",
    "sg:address":"102 28th St S",
    "sg:city":"Texas City",
    "sg:classifiers":[
        {
            "category":"Manufacturing",
            "subcategory":"Tools & Machinery",
            "type":"Manufacturing & Wholesale Goods"
        }
    ],
    "sg:phone":"+1 409 948 3651",
    "sg:postcode":"77590",
    "sg:province":"TX",
    "sg:tags":[
        "machine",
        "shop"
    ],
    "wof:name":"Mainland Machine & Grinding Sp",
    "wof:placetype":"venue"
},
  "geometry": {"coordinates":[-94.935355,29.38329],"type":"Point"}
}