{
  "type": "Feature",
  "properties": {
    "iso:country":"US",
    "sg:address":"1220 Augusta Dr",
    "sg:city":"Houston",
    "sg:classifiers":[
        {
            "category":"Professional",
            "subcategory":"Advertising",
            "type":"Services"
        }
    ],
    "sg:phone":"+1 713 787 3100",
    "sg:postcode":"77057",
    "sg:province":"TX",
    "sg:tags":[
        "agency"
    ],
    "wof:name":"Creative License Inc",
    "wof:placetype":"venue"
},
  "geometry": {"coordinates":[-95.482714,29.755806],"type":"Point"}
}