{
  "type": "Feature",
  "properties": {
    "iso:country":"US",
    "sg:address":"3711 N Highway 77",
    "sg:city":"Waxahachie",
    "sg:classifiers":[
        {
            "category":"Home & Garden",
            "subcategory":"Building Materials",
            "type":"Retail Goods"
        }
    ],
    "sg:phone":"+1 972 576 2288",
    "sg:postcode":"75165",
    "sg:province":"TX",
    "sg:tags":[
        "grouting",
        "compound"
    ],
    "wof:name":"Southern Grouts & Mortars Inc",
    "wof:placetype":"venue"
},
  "geometry": {"coordinates":[-96.827251,32.482859],"type":"Point"}
}