{
  "type": "Feature",
  "properties": {
    "iso:country":"US",
    "sg:address":"2629 N Stemmons Fwy",
    "sg:city":"Dallas",
    "sg:classifiers":[
        {
            "category":"Wholesale",
            "subcategory":"Jewelry",
            "type":"Manufacturing & Wholesale Goods"
        }
    ],
    "sg:phone":"+1 214 631 6632",
    "sg:postcode":"75207",
    "sg:province":"TX",
    "sg:tags":[
        "jeweler"
    ],
    "sg:website":"www.modadesigns.com",
    "wof:name":"Moda Designs",
    "wof:placetype":"venue"
},
  "geometry": {"coordinates":[-96.841021,32.806318],"type":"Point"}
}