{
  "type": "Feature",
  "properties": {
    "iso:country":"US",
    "sg:address":"3309 Winthrop Ave",
    "sg:city":"Fort Worth",
    "sg:classifiers":[
        {
            "category":"Personal",
            "subcategory":"Barber",
            "type":"Services"
        }
    ],
    "sg:phone":"+1 817 737 5192",
    "sg:postcode":"76116",
    "sg:province":"TX",
    "wof:name":"Members Only",
    "wof:placetype":"venue"
},
  "geometry": {"coordinates":[-97.414108,32.727234],"type":"Point"}
}