{
  "type": "Feature",
  "properties": {
    "iso:country":"US",
    "sg:address":"104 N 8th St",
    "sg:city":"Midlothian",
    "sg:classifiers":[
        {
            "category":"Building & Trades",
            "subcategory":"Construction",
            "type":"Services"
        }
    ],
    "sg:phone":"+1 972 723 2800",
    "sg:postcode":"76065",
    "sg:province":"TX",
    "sg:tags":[
        "designer",
        "dealer",
        "pool",
        "swimming"
    ],
    "wof:name":"Louis Pools",
    "wof:placetype":"venue"
},
  "geometry": {"coordinates":[-96.994434,32.483229],"type":"Point"}
}