{
  "type": "Feature",
  "properties": {
    "iso:country":"US",
    "sg:address":"409 N Main St",
    "sg:city":"Weatherford",
    "sg:classifiers":[
        {
            "category":"Autos & Motor Vehicles",
            "subcategory":"Auto Supplies",
            "type":"Retail Goods"
        }
    ],
    "sg:phone":"+1 817 599 8625",
    "sg:postcode":"76086",
    "sg:province":"TX",
    "sg:tags":[
        "parts"
    ],
    "wof:name":"Automotive Parts Co",
    "wof:placetype":"venue"
},
  "geometry": {"coordinates":[-97.797257,32.762806],"type":"Point"}
}