{
  "type": "Feature",
  "properties": {
    "iso:country":"US",
    "sg:address":"7009 Meadow Park N",
    "sg:city":"N Richland Hills",
    "sg:classifiers":[
        {
            "category":"Social Services",
            "type":"Services"
        }
    ],
    "sg:phone":"+1 817 788 8866",
    "sg:postcode":"76180",
    "sg:province":"TX",
    "sg:tags":[
        "youth",
        "organization",
        "center"
    ],
    "wof:name":"Little Miss Kickball",
    "wof:placetype":"venue"
},
  "geometry": {"coordinates":[-97.23134899999999,32.846997],"type":"Point"}
}