{
  "type": "Feature",
  "properties": {
    "iso:country":"US",
    "sg:address":"1008 8th Ave",
    "sg:city":"Fort Worth",
    "sg:classifiers":[
        {
            "category":"Health Services",
            "subcategory":"Clinic",
            "type":"Services"
        }
    ],
    "sg:phone":"+1 817 336 3676",
    "sg:postcode":"76104",
    "sg:province":"TX",
    "sg:tags":[
        "home"
    ],
    "wof:name":"Tower Medic Homecare & Supply",
    "wof:placetype":"venue"
},
  "geometry": {"coordinates":[-97.343789,32.734055],"type":"Point"}
}