{
  "type": "Feature",
  "properties": {
    "iso:country":"US",
    "sg:address":"2538 W Kiest Blvd",
    "sg:city":"Dallas",
    "sg:classifiers":[
        {
            "category":"Wholesale",
            "subcategory":"Drugs",
            "type":"Manufacturing & Wholesale Goods"
        }
    ],
    "sg:phone":"+1 214 339 7605",
    "sg:postcode":"75233",
    "sg:province":"TX",
    "sg:tags":[
        "perfume-wholesale",
        "manufacturer"
    ],
    "wof:name":"Profit Sales",
    "wof:placetype":"venue"
},
  "geometry": {"coordinates":[-96.861192,32.704706],"type":"Point"}
}