{
  "type": "Feature",
  "properties": {
    "iso:country":"US",
    "sg:address":"802 S 1st St",
    "sg:city":"Harlingen",
    "sg:classifiers":[
        {
            "category":"Health Services",
            "subcategory":"Doctor",
            "type":"Services"
        }
    ],
    "sg:phone":"+1 956 425 8262",
    "sg:postcode":"78550",
    "sg:province":"TX",
    "wof:name":"David O Adame",
    "wof:placetype":"venue"
},
  "geometry": {"coordinates":[-97.695649,26.184402],"type":"Point"}
}