{
  "type": "Feature",
  "properties": {
    "iso:country":"US",
    "sg:address":"2817 Marshall St",
    "sg:city":"Pasadena",
    "sg:classifiers":[
        {
            "category":"Retail",
            "subcategory":"Repair Shop",
            "type":"Services"
        }
    ],
    "sg:phone":"+1 713 472 7995",
    "sg:postcode":"77506",
    "sg:province":"TX",
    "wof:name":"A A Saw Sharpening",
    "wof:placetype":"venue"
},
  "geometry": {"coordinates":[-95.17516500000001,29.708003],"type":"Point"}
}