{
  "type": "Feature",
  "properties": {
    "iso:country":"US",
    "sg:address":"126 S Covington St",
    "sg:city":"Hillsboro",
    "sg:classifiers":[
        {
            "category":"Professional",
            "subcategory":"Management & Consulting",
            "type":"Services"
        }
    ],
    "sg:phone":"+1 254 582 1186",
    "sg:postcode":"76645",
    "sg:province":"TX",
    "sg:tags":[
        "development",
        "economic",
        "agency"
    ],
    "wof:name":"Economic Oppertunities",
    "wof:placetype":"venue"
},
  "geometry": {"coordinates":[-97.131372,32.010162],"type":"Point"}
}