{
  "type": "Feature",
  "properties": {
    "iso:country":"US",
    "sg:address":"1421 S 10th St",
    "sg:city":"Mcallen",
    "sg:classifiers":[
        {
            "category":"Professional",
            "type":"Services"
        }
    ],
    "sg:phone":"+1 956 664 0897",
    "sg:postcode":"78501",
    "sg:province":"TX",
    "wof:name":"Krupa LLC",
    "wof:placetype":"venue"
},
  "geometry": {"coordinates":[-98.231983,26.191369],"type":"Point"}
}