{
  "type": "Feature",
  "properties": {
    "iso:country":"US",
    "sg:address":"614 Senisa Dr",
    "sg:city":"San Antonio",
    "sg:classifiers":[
        {
            "category":"Professional",
            "type":"Services"
        }
    ],
    "sg:phone":"+1 210 434 7136",
    "sg:postcode":"78228",
    "sg:province":"TX",
    "wof:name":"Criselda V Occhiuzzi",
    "wof:placetype":"venue"
},
  "geometry": {"coordinates":[-98.555284,29.462604],"type":"Point"}
}