{
  "type": "Feature",
  "properties": {
    "iso:country":"US",
    "sg:address":"4616 Bardin Rd",
    "sg:city":"Grand Prairie",
    "sg:classifiers":[
        {
            "category":"Education",
            "subcategory":"School",
            "type":"Public Place"
        }
    ],
    "sg:phone":"+1 972 522 7300",
    "sg:postcode":"75052",
    "sg:province":"TX",
    "sg:tags":[
        "high",
        "middle",
        "elementary"
    ],
    "wof:name":"Schools",
    "wof:placetype":"venue"
},
  "geometry": {"coordinates":[-96.996447,32.660984],"type":"Point"}
}