{
  "type": "Feature",
  "properties": {
    "iso:country":"US",
    "sg:address":"11510 FM 1488",
    "sg:city":"Magnolia",
    "sg:classifiers":[
        {
            "category":"Building & Trades",
            "subcategory":"Construction",
            "type":"Services"
        }
    ],
    "sg:phone":"+1 281 259 5908",
    "sg:postcode":"77354",
    "sg:province":"TX",
    "sg:tags":[
        "contractor"
    ],
    "wof:name":"Renaissance Pools",
    "wof:placetype":"venue"
},
  "geometry": {"coordinates":[-95.651627,30.2225],"type":"Point"}
}