{
  "type": "Feature",
  "properties": {
    "iso:country":"US",
    "sg:address":"2639 Walnut Hill Ln",
    "sg:city":"Dallas",
    "sg:classifiers":[
        {
            "category":"Wholesale",
            "subcategory":"Medical Equipment & Supplies",
            "type":"Manufacturing & Wholesale Goods"
        }
    ],
    "sg:phone":"+1 214 350 2190",
    "sg:postcode":"75229",
    "sg:province":"TX",
    "sg:tags":[
        "physician",
        "surgeon"
    ],
    "wof:name":"Aminos Medical Suplly",
    "wof:placetype":"venue"
},
  "geometry": {"coordinates":[-96.89034599999999,32.881037],"type":"Point"}
}