{
  "type": "Feature",
  "properties": {
    "iso:country":"US",
    "sg:address":"5800 S 42nd St Ste G",
    "sg:city":"Mcallen",
    "sg:classifiers":[
        {
            "category":"Shopping",
            "subcategory":"Computers & Home Electronics",
            "type":"Retail Goods"
        }
    ],
    "sg:phone":"+1 956 618 5833",
    "sg:postcode":"78503",
    "sg:province":"TX",
    "sg:tags":[
        "hardware",
        "supply"
    ],
    "wof:name":"Seagate Technology",
    "wof:placetype":"venue"
},
  "geometry": {"coordinates":[-98.275429,26.158859],"type":"Point"}
}