{
  "type": "Feature",
  "properties": {
    "iso:country":"US",
    "sg:address":"3306 Main St",
    "sg:city":"Rowlett",
    "sg:classifiers":[
        {
            "category":"Wholesale",
            "subcategory":"Vending Machines",
            "type":"Manufacturing & Wholesale Goods"
        }
    ],
    "sg:phone":"+1 214 221 4145",
    "sg:postcode":"75088",
    "sg:province":"TX",
    "sg:tags":[
        "operator",
        "business"
    ],
    "sg:website":"www.abcvending.net",
    "wof:name":"ABC Vending",
    "wof:placetype":"venue"
},
  "geometry": {"coordinates":[-96.57086,32.902404],"type":"Point"}
}