{
  "type": "Feature",
  "properties": {
    "iso:country":"US",
    "sg:address":"2741 Fallon Dr",
    "sg:city":"Sherman",
    "sg:classifiers":[
        {
            "category":"Professional",
            "subcategory":"Computer Services",
            "type":"Services"
        }
    ],
    "sg:phone":"+1 903 868 9511",
    "sg:postcode":"75090",
    "sg:province":"TX",
    "sg:tags":[
        "design",
        "system",
        "programing",
        "custom"
    ],
    "wof:name":"Skystream",
    "wof:placetype":"venue"
},
  "geometry": {"coordinates":[-96.57511700000001,33.687786],"type":"Point"}
}