{
  "type": "Feature",
  "properties": {
    "iso:country":"US",
    "sg:address":"900 Austin Ave",
    "sg:city":"Waco",
    "sg:classifiers":[
        {
            "category":"Personal",
            "subcategory":"Barber",
            "type":"Services"
        }
    ],
    "sg:phone":"+1 254 753 9668",
    "sg:postcode":"76701",
    "sg:province":"TX",
    "wof:name":"Tito's Downtown Barber Shop",
    "wof:placetype":"venue"
},
  "geometry": {"coordinates":[-97.13724999999999,31.552004],"type":"Point"}
}