{
  "type": "Feature",
  "properties": {
    "iso:country":"US",
    "sg:address":"3001 Eldorado Pkwy",
    "sg:city":"Mc Kinney",
    "sg:classifiers":[
        {
            "category":"Food & Beverages",
            "subcategory":"Groceries & Convenience Stores",
            "type":"Retail Goods"
        }
    ],
    "sg:phone":"+1 972 548 1003",
    "sg:postcode":"75070",
    "sg:province":"TX",
    "sg:tags":[
        "grocer"
    ],
    "wof:name":"Albertsons",
    "wof:placetype":"venue"
},
  "geometry": {"coordinates":[-96.664985,33.167704],"type":"Point"}
}