{
  "type": "Feature",
  "properties": {
    "iso:country":"US",
    "sg:address":"24250 US Highway 281 N",
    "sg:city":"Bulverde",
    "sg:classifiers":[
        {
            "category":"Shopping",
            "subcategory":"Bicycles & Sporting Goods",
            "type":"Retail Goods"
        },
        {
            "category":"Retail",
            "subcategory":"Pet Boarding",
            "type":"Services"
        }
    ],
    "sg:phone":"+1 830 980 4924",
    "sg:postcode":"78258",
    "sg:province":"TX",
    "sg:tags":[
        "boarding/pet",
        "sitting"
    ],
    "sg:website":"www.mummesinc.com",
    "wof:name":"Mumme's Inc",
    "wof:placetype":"venue"
},
  "geometry": {"coordinates":[-98.419721,29.795579],"type":"Point"}
}