{
  "type": "Feature",
  "properties": {
    "iso:country":"US",
    "sg:address":"410 28th St",
    "sg:city":"Hidalgo",
    "sg:classifiers":[
        {
            "category":"Retail",
            "subcategory":"Laundry & Dry Cleaning",
            "type":"Services"
        },
        {
            "category":"Building & Trades",
            "subcategory":"Cleaning & Sanitation",
            "type":"Services"
        }
    ],
    "sg:phone":"+1 956 843 7458",
    "sg:postcode":"78557",
    "sg:province":"TX",
    "sg:tags":[
        "cleaner",
        "house"
    ],
    "wof:name":"Master Cleaning",
    "wof:placetype":"venue"
},
  "geometry": {"coordinates":[-98.230136,26.096978],"type":"Point"}
}