{
  "type": "Feature",
  "properties": {
    "iso:country":"US",
    "sg:address":"4334 Echo Glen Dr",
    "sg:city":"Dallas",
    "sg:classifiers":[
        {
            "category":"Banks & Credit Unions",
            "subcategory":"Financial Services",
            "type":"Services"
        },
        {
            "category":"Professional",
            "subcategory":"Management & Consulting",
            "type":"Services"
        }
    ],
    "sg:phone":"+1 972 239 9066",
    "sg:postcode":"75244",
    "sg:province":"TX",
    "sg:tags":[
        "fuel",
        "investment",
        "closed"
    ],
    "wof:name":"Bonness Management LLC",
    "wof:placetype":"venue"
},
  "geometry": {"coordinates":[-96.83608700000001,32.91548],"type":"Point"}
}