{
  "type": "Feature",
  "properties": {
    "iso:country":"US",
    "sg:address":"10900 Bywood Dr",
    "sg:city":"El Paso",
    "sg:classifiers":[
        {
            "category":"Social Services",
            "subcategory":"Child Care",
            "type":"Services"
        }
    ],
    "sg:phone":"+1 915 599 1714",
    "sg:postcode":"79936",
    "sg:province":"TX",
    "sg:tags":[
        "day"
    ],
    "wof:name":"Tiny Toes Home Day Care",
    "wof:placetype":"venue"
},
  "geometry": {"coordinates":[-106.320356,31.780535],"type":"Point"}
}