{
  "type": "Feature",
  "properties": {
    "iso:country":"US",
    "sg:address":"3501 N Central Expy",
    "sg:city":"Plano",
    "sg:classifiers":[
        {
            "category":"Restaurant",
            "type":"Food & Drink"
        }
    ],
    "sg:menulink":"http://www.allmenus.com/tx/plano/127968-red-lobster/menu/",
    "sg:phone":"+1 972 881 4353",
    "sg:postcode":"75023",
    "sg:province":"TX",
    "sg:tags":[
        "seafood",
        "american"
    ],
    "wof:name":"Red Lobster",
    "wof:placetype":"venue"
},
  "geometry": {"coordinates":[-96.702308,33.042353],"type":"Point"}
}