{
  "type": "Feature",
  "properties": {
    "iso:country":"US",
    "sg:address":"7251 Prairie Dr",
    "sg:city":"Corpus Christi",
    "sg:classifiers":[
        {
            "category":"Professional",
            "subcategory":"Business Services",
            "type":"Services"
        }
    ],
    "sg:phone":"+1 361 980 8595",
    "sg:postcode":"78413",
    "sg:province":"TX",
    "wof:name":"Secrest Agency",
    "wof:placetype":"venue"
},
  "geometry": {"coordinates":[-97.404878,27.676147],"type":"Point"}
}