{
  "type": "Feature",
  "properties": {
    "iso:country":"US",
    "sg:address":"2637 Old Jacksboro Hwy",
    "sg:city":"Wichita Falls",
    "sg:classifiers":[
        {
            "category":"Autos & Motor Vehicles",
            "subcategory":"Automobile Sales",
            "type":"Retail Goods"
        }
    ],
    "sg:phone":"+1 940 766 4171",
    "sg:postcode":"76302",
    "sg:province":"TX",
    "sg:tags":[
        "car",
        "used",
        "dealer"
    ],
    "wof:name":"Hal Strother Motor Co",
    "wof:placetype":"venue"
},
  "geometry": {"coordinates":[-98.487604,33.885874],"type":"Point"}
}