{
  "type": "Feature",
  "properties": {
    "iso:country":"US",
    "sg:address":"1804 Boss Range Rd",
    "sg:city":"Justin",
    "sg:classifiers":[
        {
            "category":"Retail",
            "subcategory":"Repair Shop",
            "type":"Services"
        }
    ],
    "sg:phone":"+1 817 437 6196",
    "sg:postcode":"76247",
    "sg:province":"TX",
    "sg:tags":[
        "appliance"
    ],
    "wof:name":"In Home Appliance Repair",
    "wof:placetype":"venue"
},
  "geometry": {"coordinates":[-97.308914,33.072642],"type":"Point"}
}