{
  "type": "Feature",
  "properties": {
    "iso:country":"US",
    "sg:address":"115 Wildwood Ranch Rd",
    "sg:city":"Adkins",
    "sg:classifiers":[
        {
            "category":"Freight",
            "type":"Transportation"
        }
    ],
    "sg:phone":"+1 830 217 4009",
    "sg:postcode":"78101",
    "sg:province":"TX",
    "sg:tags":[
        "operator",
        "trucking"
    ],
    "wof:name":"Franks Mobil Transport",
    "wof:placetype":"venue"
},
  "geometry": {"coordinates":[-98.185761,29.309097],"type":"Point"}
}