{
  "type": "Feature",
  "properties": {
    "iso:country":"US",
    "sg:address":"407 S Main St",
    "sg:city":"Del Rio",
    "sg:classifiers":[
        {
            "category":"Banks & Credit Unions",
            "subcategory":"Bank",
            "type":"Services"
        }
    ],
    "sg:phone":"+1 830 775 5224",
    "sg:postcode":"78840",
    "sg:province":"TX",
    "sg:tags":[
        "institution",
        "business"
    ],
    "wof:name":"Family Loan Co",
    "wof:placetype":"venue"
},
  "geometry": {"coordinates":[-100.899715,29.361068],"type":"Point"}
}