{
  "type": "Feature",
  "properties": {
    "iso:country":"US",
    "sg:address":"615 N Main St",
    "sg:city":"Euless",
    "sg:classifiers":[
        {
            "category":"Professional",
            "subcategory":"Management & Consulting",
            "type":"Services"
        }
    ],
    "sg:phone":"+1 817 283 9795",
    "sg:postcode":"76039",
    "sg:province":"TX",
    "sg:tags":[
        "public",
        "relations"
    ],
    "wof:name":"Mayes & Assoc Inc",
    "wof:placetype":"venue"
},
  "geometry": {"coordinates":[-97.08266,32.844958],"type":"Point"}
}