{
  "type": "Feature",
  "properties": {
    "iso:country":"US",
    "sg:address":"5130 80th St",
    "sg:city":"Lubbock",
    "sg:classifiers":[
        {
            "category":"Restaurant",
            "type":"Food & Drink"
        }
    ],
    "sg:phone":"+1 806 687 9500",
    "sg:postcode":"79424",
    "sg:province":"TX",
    "sg:tags":[
        "eating"
    ],
    "wof:name":"Nirvana Fine Indian Cuisine",
    "wof:placetype":"venue"
},
  "geometry": {"coordinates":[-101.920311,33.521023],"type":"Point"}
}