{
  "type": "Feature",
  "properties": {
    "iso:country":"US",
    "sg:address":"2412 State Hwy 361",
    "sg:city":"Port Aransas",
    "sg:classifiers":[
        {
            "category":"Manufacturing",
            "subcategory":"Printing",
            "type":"Manufacturing & Wholesale Goods"
        }
    ],
    "sg:phone":"+1 361 749 7423",
    "sg:postcode":"78373",
    "sg:province":"TX",
    "sg:tags":[
        "periodical"
    ],
    "wof:name":"Pams Publishing",
    "wof:placetype":"venue"
},
  "geometry": {"coordinates":[-97.07576400000001,27.815383],"type":"Point"}
}