{
  "type": "Feature",
  "properties": {
    "iso:country":"US",
    "sg:address":"818 Rio Grande Dr",
    "sg:city":"Mission",
    "sg:classifiers":[
        {
            "category":"Real Estate",
            "subcategory":"Real Estate Agent",
            "type":"Services"
        }
    ],
    "sg:phone":"+1 956 583 3474",
    "sg:postcode":"78572",
    "sg:province":"TX",
    "wof:name":"Lawson Commercial Realty",
    "wof:placetype":"venue"
},
  "geometry": {"coordinates":[-98.29945600000001,26.182936],"type":"Point"}
}