{
  "type": "Feature",
  "properties": {
    "iso:country":"US",
    "sg:address":"1346 Thorpe Ln",
    "sg:city":"San Marcos",
    "sg:classifiers":[
        {
            "category":"Shopping",
            "subcategory":"Pharmacy",
            "type":"Retail Goods"
        }
    ],
    "sg:phone":"+1 512 353 5042",
    "sg:postcode":"78666",
    "sg:province":"TX",
    "wof:name":"Thorpe Lane Pharmacy",
    "wof:placetype":"venue"
},
  "geometry": {"coordinates":[-97.922921,29.888093],"type":"Point"}
}