{
  "type": "Feature",
  "properties": {
    "iso:country":"US",
    "sg:address":"888 S Greenville Ave",
    "sg:city":"Richardson",
    "sg:classifiers":[
        {
            "category":"Building & Trades",
            "subcategory":"Electrical",
            "type":"Services"
        },
        {
            "category":"Train Station",
            "subcategory":"Light Rail",
            "type":"Transportation"
        }
    ],
    "sg:phone":"+1 972 231 5007",
    "sg:postcode":"75081",
    "sg:province":"TX",
    "sg:tags":[
        "lighting",
        "electrician",
        "contractor"
    ],
    "sg:website":"http://www.omnisgi.com",
    "wof:name":"Suntech Wireless Inc",
    "wof:placetype":"venue"
},
  "geometry": {"coordinates":[-96.734138,32.937962],"type":"Point"}
}