{
  "type": "Feature",
  "properties": {
    "iso:country":"US",
    "sg:address":"424 S Snyder Ave",
    "sg:city":"Justin",
    "sg:classifiers":[
        {
            "category":"Place Of Worship",
            "subcategory":"Church",
            "type":"Public Place"
        },
        {
            "category":"Place Of Worship",
            "type":"Public Place"
        }
    ],
    "sg:phone":"+1 940 648 2482",
    "sg:postcode":"76247",
    "sg:province":"TX",
    "sg:tags":[
        "testament",
        "christ-new",
        "churches-church",
        "christ"
    ],
    "wof:name":"Justin Church Of Church",
    "wof:placetype":"venue"
},
  "geometry": {"coordinates":[-97.29749700000001,33.081184],"type":"Point"}
}