{
  "type": "Feature",
  "properties": {
    "iso:country":"US",
    "sg:address":"4717 Moss Point Rd",
    "sg:city":"Dallas",
    "sg:classifiers":[
        {
            "category":"Communications",
            "subcategory":"Film & Video Production",
            "type":"Services"
        }
    ],
    "sg:phone":"+1 214 374 9537",
    "sg:postcode":"75232",
    "sg:province":"TX",
    "sg:tags":[
        "motion"
    ],
    "wof:name":"Destiny Production",
    "wof:placetype":"venue"
},
  "geometry": {"coordinates":[-96.830383,32.685678],"type":"Point"}
}