{
  "type": "Feature",
  "properties": {
    "iso:country":"US",
    "sg:address":"8401 Princeton Rd",
    "sg:city":"Rowlett",
    "sg:classifiers":[
        {
            "category":"Organizations",
            "subcategory":"Religious Organization",
            "type":"Services"
        }
    ],
    "sg:phone":"+1 972 475 4750",
    "sg:postcode":"75089",
    "sg:province":"TX",
    "sg:tags":[
        "shrine",
        "temple",
        "church"
    ],
    "wof:name":"Lake Cities Baptist Chruch",
    "wof:placetype":"venue"
},
  "geometry": {"coordinates":[-96.531879,32.934593],"type":"Point"}
}