{
  "type": "Feature",
  "properties": {
    "iso:country":"US",
    "sg:address":"2370 Columbia St",
    "sg:city":"Beaumont",
    "sg:classifiers":[
        {
            "category":"Building & Trades",
            "subcategory":"Plumbing",
            "type":"Services"
        }
    ],
    "sg:phone":"+1 409 350 1972",
    "sg:postcode":"77701",
    "sg:province":"TX",
    "sg:tags":[
        "plumber"
    ],
    "wof:name":"Martha S Sewer Drainage Services",
    "wof:placetype":"venue"
},
  "geometry": {"coordinates":[-94.12590299999999,30.062937],"type":"Point"}
}