{
  "type": "Feature",
  "properties": {
    "iso:country":"US",
    "sg:address":"109 N Armstrong St",
    "sg:city":"Kingsville",
    "sg:classifiers":[
        {
            "category":"Shopping",
            "subcategory":"Used Merchandise",
            "type":"Retail Goods"
        }
    ],
    "sg:phone":"+1 361 592 6611",
    "sg:postcode":"78363",
    "sg:province":"TX",
    "wof:name":"White Elephant Thrift Shoppe",
    "wof:placetype":"venue"
},
  "geometry": {"coordinates":[-97.877818,27.517471],"type":"Point"}
}