{
  "type": "Feature",
  "properties": {
    "iso:country":"US",
    "sg:address":"5413 Stanley Keller Rd",
    "sg:city":"Fort Worth",
    "sg:classifiers":[
        {
            "category":"Health Services",
            "subcategory":"Doctor",
            "type":"Services"
        }
    ],
    "sg:phone":"+1 817 485 0155",
    "sg:postcode":"76117",
    "sg:province":"TX",
    "sg:tags":[
        "dentist"
    ],
    "wof:name":"Allen C Roach Jr DDS",
    "wof:placetype":"venue"
},
  "geometry": {"coordinates":[-97.26456399999999,32.824143],"type":"Point"}
}