{
  "type": "Feature",
  "properties": {
    "iso:country":"US",
    "sg:address":"411 W Prairie Lea St",
    "sg:city":"Lockhart",
    "sg:classifiers":[
        {
            "category":"Building & Trades",
            "subcategory":"Construction",
            "type":"Services"
        }
    ],
    "sg:phone":"+1 512 398 5854",
    "sg:postcode":"78644",
    "sg:province":"TX",
    "sg:tags":[
        "roofing",
        "contractor"
    ],
    "wof:name":"Castro David",
    "wof:placetype":"venue"
},
  "geometry": {"coordinates":[-97.675578,29.882396],"type":"Point"}
}