{
  "type": "Feature",
  "properties": {
    "iso:country":"US",
    "sg:address":"5943 Ingram Rd",
    "sg:city":"San Antonio",
    "sg:classifiers":[
        {
            "category":"Shopping",
            "subcategory":"Clothing, Apparel, & Fashions",
            "type":"Retail Goods"
        }
    ],
    "sg:phone":"+1 210 534 8719",
    "sg:postcode":"78228",
    "sg:province":"TX",
    "sg:tags":[
        "infant",
        "wear"
    ],
    "wof:name":"Baby Things",
    "wof:placetype":"venue"
},
  "geometry": {"coordinates":[-98.60023099999999,29.46598],"type":"Point"}
}