{
  "type": "Feature",
  "properties": {
    "iso:country":"US",
    "sg:address":"10350 W Montgomery Rd",
    "sg:city":"Houston",
    "sg:classifiers":[
        {
            "category":"Retail",
            "subcategory":"Auto Repair",
            "type":"Services"
        }
    ],
    "sg:phone":"+1 281 447 4060",
    "sg:postcode":"77088",
    "sg:province":"TX",
    "sg:tags":[
        "body",
        "automotive",
        "painting",
        "paint",
        "automobile"
    ],
    "wof:name":"Falcon Collision Ctr",
    "wof:placetype":"venue"
},
  "geometry": {"coordinates":[-95.455055,29.889139],"type":"Point"}
}