{
  "type": "Feature",
  "properties": {
    "iso:country":"US",
    "sg:address":"2400 Bolsover St",
    "sg:city":"Houston",
    "sg:classifiers":[
        {
            "category":"Retail",
            "subcategory":"Laundry & Dry Cleaning",
            "type":"Services"
        }
    ],
    "sg:phone":"+1 713 527 8973",
    "sg:postcode":"77005",
    "sg:province":"TX",
    "sg:tags":[
        "cleaners"
    ],
    "wof:name":"Good Neighbor Cleaners",
    "wof:placetype":"venue"
},
  "geometry": {"coordinates":[-95.416686,29.718276],"type":"Point"}
}