{
  "type": "Feature",
  "properties": {
    "iso:country":"US",
    "sg:address":"1717 Norman Dr",
    "sg:city":"Dallas",
    "sg:classifiers":[
        {
            "category":"Insurance",
            "subcategory":"Hazard Insurance",
            "type":"Services"
        }
    ],
    "sg:phone":"+1 214 337 2014",
    "sg:postcode":"75211",
    "sg:province":"TX",
    "wof:name":"Pay Less Ins",
    "wof:placetype":"venue"
},
  "geometry": {"coordinates":[-96.873651,32.727018],"type":"Point"}
}