{
  "type": "Feature",
  "properties": {
    "iso:country":"US",
    "sg:address":"2804 Wood Wind Dr",
    "sg:city":"Pantego",
    "sg:classifiers":[
        {
            "category":"Building & Trades",
            "subcategory":"Construction",
            "type":"Services"
        }
    ],
    "sg:phone":"+1 817 461 7873",
    "sg:postcode":"76013",
    "sg:province":"TX",
    "sg:tags":[
        "repairing",
        "remodeling",
        "contractor"
    ],
    "wof:name":"Remodeling With Care",
    "wof:placetype":"venue"
},
  "geometry": {"coordinates":[-97.15770999999999,32.717772],"type":"Point"}
}