{
  "type": "Feature",
  "properties": {
    "iso:country":"US",
    "sg:address":"3156 State Hwy 19",
    "sg:city":"Huntsville",
    "sg:classifiers":[
        {
            "category":"Mining & Drilling",
            "type":"Manufacturing & Wholesale Goods"
        }
    ],
    "sg:phone":"+1 936 291 2019",
    "sg:postcode":"77320",
    "sg:province":"TX",
    "sg:tags":[
        "exploration"
    ],
    "wof:name":"Harris Oil Gas",
    "wof:placetype":"venue"
},
  "geometry": {"coordinates":[-95.457059,30.798125],"type":"Point"}
}