{
  "type": "Feature",
  "properties": {
    "iso:country":"US",
    "sg:address":"5900 Denton Hwy",
    "sg:city":"Watauga",
    "sg:classifiers":[
        {
            "category":"Retail",
            "subcategory":"Laundry & Dry Cleaning",
            "type":"Services"
        }
    ],
    "sg:phone":"+1 817 656 8520",
    "sg:postcode":"76148",
    "sg:province":"TX",
    "sg:tags":[
        "cleaners"
    ],
    "wof:name":"Lee Cleaners",
    "wof:placetype":"venue"
},
  "geometry": {"coordinates":[-97.264028,32.855981],"type":"Point"}
}