{
  "type": "Feature",
  "properties": {
    "iso:country":"US",
    "sg:address":"929 J Pl",
    "sg:city":"Plano",
    "sg:classifiers":[
        {
            "category":"Building & Trades",
            "subcategory":"Landscaping Services",
            "type":"Services"
        },
        {
            "category":"Building & Trades",
            "subcategory":"Construction",
            "type":"Services"
        }
    ],
    "sg:phone":"+1 972 840 8578",
    "sg:postcode":"75074",
    "sg:province":"TX",
    "sg:tags":[
        "lawn",
        "installation",
        "deck",
        "builder",
        "contractor",
        "landscape",
        "maintenance",
        "sprinklers-garden",
        "patio",
        "gardener"
    ],
    "sg:website":"http://www.advspr.com",
    "wof:name":"Advanced Sprinkler & Landscape Services",
    "wof:placetype":"venue"
},
  "geometry": {"coordinates":[-96.70012199999999,33.011598],"type":"Point"}
}