{
  "type": "Feature",
  "properties": {
    "iso:country":"US",
    "sg:address":"3154 Saba Ln",
    "sg:city":"Port Neches",
    "sg:classifiers":[
        {
            "category":"Professional",
            "subcategory":"Management & Consulting",
            "type":"Services"
        }
    ],
    "sg:phone":"+1 409 729 4772",
    "sg:postcode":"77651",
    "sg:province":"TX",
    "sg:tags":[
        "consultant",
        "business"
    ],
    "wof:name":"Peak Practice Consultants",
    "wof:placetype":"venue"
},
  "geometry": {"coordinates":[-93.955504,29.953036],"type":"Point"}
}