{
  "type": "Feature",
  "properties": {
    "iso:country":"US",
    "sg:address":"606 W Lynn St",
    "sg:city":"Austin",
    "sg:classifiers":[
        {
            "category":"Professional",
            "subcategory":"Management & Consulting",
            "type":"Services"
        },
        {
            "category":"Professional",
            "subcategory":"Computer Services",
            "type":"Services"
        }
    ],
    "sg:phone":"+1 512 478 3112",
    "sg:postcode":"78703",
    "sg:province":"TX",
    "sg:tags":[
        "consultant",
        "related"
    ],
    "wof:name":"Deepcoolclear Inc",
    "wof:placetype":"venue"
},
  "geometry": {"coordinates":[-97.761475,30.276777],"type":"Point"}
}