{
  "type": "Feature",
  "properties": {
    "iso:country":"US",
    "sg:address":"1301 G Ave",
    "sg:city":"Plano",
    "sg:classifiers":[
        {
            "category":"Building & Trades",
            "subcategory":"Landscaping Services",
            "type":"Services"
        }
    ],
    "sg:phone":"+1 972 423 5702",
    "sg:postcode":"75074",
    "sg:province":"TX",
    "wof:name":"Moon Rock Data Systems",
    "wof:placetype":"venue"
},
  "geometry": {"coordinates":[-96.70510400000001,33.017711],"type":"Point"}
}