{
  "type": "Feature",
  "properties": {
    "iso:country":"US",
    "sg:address":"6556 Old Mill Cir",
    "sg:city":"Fort Worth",
    "sg:classifiers":[
        {
            "category":"Retail",
            "subcategory":"Laundry & Dry Cleaning",
            "type":"Services"
        }
    ],
    "sg:phone":"+1 817 656 1726",
    "sg:postcode":"76148",
    "sg:province":"TX",
    "sg:tags":[
        "cleaners",
        "rug",
        "carpet"
    ],
    "wof:name":"Metro Carpet Care",
    "wof:placetype":"venue"
},
  "geometry": {"coordinates":[-97.239801,32.854585],"type":"Point"}
}