{
  "type": "Feature",
  "properties": {
    "iso:country":"US",
    "sg:address":"8507 Rosemary Ln",
    "sg:city":"Austin",
    "sg:classifiers":[
        {
            "category":"Shopping",
            "subcategory":"Catalog Store",
            "type":"Retail Goods"
        }
    ],
    "sg:phone":"+1 512 380 7370",
    "sg:postcode":"78753",
    "sg:province":"TX",
    "sg:tags":[
        "mail",
        "order"
    ],
    "wof:name":"Q Bear Specialties",
    "wof:placetype":"venue"
},
  "geometry": {"coordinates":[-97.697275,30.350971],"type":"Point"}
}