{
  "type": "Feature",
  "properties": {
    "iso:country":"US",
    "sg:address":"2010 Castlerock Rd",
    "sg:city":"Houston",
    "sg:classifiers":[
        {
            "category":"Building & Trades",
            "subcategory":"Construction",
            "type":"Services"
        }
    ],
    "sg:phone":"+1 281 444 1051",
    "sg:postcode":"77090",
    "sg:province":"TX",
    "sg:tags":[
        "concrete",
        "contractor"
    ],
    "wof:name":"Samco Construction Spring Inc",
    "wof:placetype":"venue"
},
  "geometry": {"coordinates":[-95.467412,30.019819],"type":"Point"}
}