{
  "type": "Feature",
  "properties": {
    "iso:country":"US",
    "sg:address":"815 Walker St",
    "sg:city":"Houston",
    "sg:classifiers":[
        {
            "category":"Health Services",
            "subcategory":"Doctor",
            "type":"Services"
        }
    ],
    "sg:phone":"+1 713 223 3663",
    "sg:postcode":"77002",
    "sg:province":"TX",
    "sg:tags":[
        "medical"
    ],
    "wof:name":"White B L MD",
    "wof:placetype":"venue"
},
  "geometry": {"coordinates":[-95.365279,29.758361],"type":"Point"}
}