{
  "type": "Feature",
  "properties": {
    "iso:country":"US",
    "sg:address":"4810 Creekridge Pl",
    "sg:city":"Garland",
    "sg:classifiers":[
        {
            "category":"Retail",
            "subcategory":"Repair Shop",
            "type":"Services"
        }
    ],
    "sg:phone":"+1 972 226 5927",
    "sg:postcode":"75043",
    "sg:province":"TX",
    "wof:name":"All Star Electronics",
    "wof:placetype":"venue"
},
  "geometry": {"coordinates":[-96.55845100000001,32.846604],"type":"Point"}
}