{
  "type": "Feature",
  "properties": {
    "iso:country":"US",
    "sg:address":"805 W Price Rd",
    "sg:city":"Brownsville",
    "sg:classifiers":[
        {
            "category":"Professional",
            "subcategory":"Lawyer & Legal Services",
            "type":"Services"
        }
    ],
    "sg:phone":"+1 956 546 1924",
    "sg:postcode":"78520",
    "sg:province":"TX",
    "sg:tags":[
        "security",
        "counselor",
        "rep",
        "social"
    ],
    "wof:name":"Hilliard Disability Cons",
    "wof:placetype":"venue"
},
  "geometry": {"coordinates":[-97.509843,25.937514],"type":"Point"}
}