{
  "type": "Feature",
  "properties": {
    "iso:country":"US",
    "sg:address":"6719 Snider Plz",
    "sg:city":"Dallas",
    "sg:classifiers":[
        {
            "category":"Education",
            "subcategory":"Special Training",
            "type":"Public Place"
        }
    ],
    "sg:phone":"+1 214 750 5522",
    "sg:postcode":"75205",
    "sg:province":"TX",
    "sg:tags":[
        "school",
        "art"
    ],
    "wof:name":"A Little Artsy",
    "wof:placetype":"venue"
},
  "geometry": {"coordinates":[-96.78810799999999,32.847758],"type":"Point"}
}