{
  "type": "Feature",
  "properties": {
    "iso:country":"US",
    "sg:address":"209 Park Dr",
    "sg:city":"Bridge City",
    "sg:classifiers":[
        {
            "category":"Building & Trades",
            "subcategory":"Construction",
            "type":"Services"
        }
    ],
    "sg:phone":"+1 409 735 5688",
    "sg:postcode":"77611",
    "sg:province":"TX",
    "sg:tags":[
        "hanging",
        "contractor"
    ],
    "wof:name":"Truly Unique Designs",
    "wof:placetype":"venue"
},
  "geometry": {"coordinates":[-93.839254,30.012351],"type":"Point"}
}