{
  "type": "Feature",
  "properties": {
    "iso:country":"US",
    "sg:address":"106 E Old Settlers Blvd",
    "sg:city":"Round Rock",
    "sg:classifiers":[
        {
            "category":"Professional",
            "subcategory":"Computer Services",
            "type":"Services"
        }
    ],
    "sg:phone":"+1 512 610 1200",
    "sg:postcode":"78664",
    "sg:province":"TX",
    "sg:tags":[
        "repair"
    ],
    "sg:website":"www.incline-gts.com",
    "wof:name":"Incline",
    "wof:placetype":"venue"
},
  "geometry": {"coordinates":[-97.687445,30.533684],"type":"Point"}
}