{
  "type": "Feature",
  "properties": {
    "iso:country":"US",
    "sg:address":"14771 State Hwy 64",
    "sg:city":"Ben Wheeler",
    "sg:classifiers":[
        {
            "category":"Retail",
            "subcategory":"Auto Repair",
            "type":"Services"
        }
    ],
    "sg:phone":"+1 903 833 5710",
    "sg:postcode":"75754",
    "sg:province":"TX",
    "sg:tags":[
        "repairing",
        "automobile"
    ],
    "wof:name":"Herrington Automotive",
    "wof:placetype":"venue"
},
  "geometry": {"coordinates":[-95.71851700000001,32.457672],"type":"Point"}
}