{
  "type": "Feature",
  "properties": {
    "iso:country":"US",
    "sg:address":"7800 Shoal Creek Blvd",
    "sg:city":"Austin",
    "sg:classifiers":[
        {
            "category":"Social Services",
            "type":"Services"
        }
    ],
    "sg:phone":"+1 512 454 4816",
    "sg:postcode":"78757",
    "sg:province":"TX",
    "sg:tags":[
        "organization",
        "welfare"
    ],
    "sg:website":"www.advocacyinc.org",
    "wof:name":"Advocacy Inc",
    "wof:placetype":"venue"
},
  "geometry": {"coordinates":[-97.74085599999999,30.361026],"type":"Point"}
}