{
  "type": "Feature",
  "properties": {
    "iso:country":"US",
    "sg:address":"1409 W University Dr",
    "sg:city":"Mc Kinney",
    "sg:classifiers":[
        {
            "category":"Real Estate",
            "subcategory":"Real Estate Agent",
            "type":"Services"
        }
    ],
    "sg:phone":"+1 972 235 9911",
    "sg:postcode":"75069",
    "sg:province":"TX",
    "sg:tags":[
        "appraiser"
    ],
    "wof:name":"1st Appraisal Choice Inc",
    "wof:placetype":"venue"
},
  "geometry": {"coordinates":[-96.62496400000001,33.216113],"type":"Point"}
}