{
  "type": "Feature",
  "properties": {
    "iso:country":"US",
    "sg:address":"600 W Commerce St",
    "sg:city":"Buffalo",
    "sg:classifiers":[
        {
            "category":"Place Of Worship",
            "subcategory":"Church",
            "type":"Public Place"
        },
        {
            "category":"Place Of Worship",
            "type":"Public Place"
        }
    ],
    "sg:phone":"+1 903 322 4332",
    "sg:postcode":"75831",
    "sg:province":"TX",
    "sg:tags":[
        "churches-baptist-general",
        "churches-baptist"
    ],
    "wof:name":"First Baptist Church Of Buffalo",
    "wof:placetype":"venue"
},
  "geometry": {"coordinates":[-96.06822,31.45974],"type":"Point"}
}