{
  "type": "Feature",
  "properties": {
    "iso:country":"US",
    "sg:address":"9330 Poppy Dr",
    "sg:city":"Dallas",
    "sg:classifiers":[
        {
            "category":"Health Services",
            "subcategory":"Doctor",
            "type":"Services"
        }
    ],
    "sg:phone":"+1 214 328 4389",
    "sg:postcode":"75218",
    "sg:province":"TX",
    "sg:tags":[
        "medicine",
        "internal"
    ],
    "wof:name":"Bloom Christopher A MD",
    "wof:placetype":"venue"
},
  "geometry": {"coordinates":[-96.705479,32.835206],"type":"Point"}
}