{
  "type": "Feature",
  "properties": {
    "iso:country":"US",
    "sg:address":"130 E 42nd St",
    "sg:city":"Lubbock",
    "sg:classifiers":[
        {
            "category":"Manufacturing",
            "subcategory":"Food",
            "type":"Manufacturing & Wholesale Goods"
        }
    ],
    "sg:phone":"+1 806 765 5558",
    "sg:postcode":"79404",
    "sg:province":"TX",
    "sg:tags":[
        "ice"
    ],
    "sg:website":"www.arcticglacierinc.com",
    "wof:name":"Arctic Glacier Inc",
    "wof:placetype":"venue"
},
  "geometry": {"coordinates":[-101.832131,33.555957],"type":"Point"}
}