{
  "type": "Feature",
  "properties": {
    "iso:country":"US",
    "sg:address":"5719 95th St",
    "sg:city":"Lubbock",
    "sg:classifiers":[
        {
            "category":"Building & Trades",
            "subcategory":"Construction",
            "type":"Services"
        }
    ],
    "sg:phone":"+1 806 794 6844",
    "sg:postcode":"79424",
    "sg:province":"TX",
    "sg:tags":[
        "contractor"
    ],
    "wof:name":"Lusk Drywall Inc",
    "wof:placetype":"venue"
},
  "geometry": {"coordinates":[-101.938035,33.507557],"type":"Point"}
}