{
  "type": "Feature",
  "properties": {
    "iso:country":"US",
    "sg:address":"2801 Post Oak Blvd Ste 222",
    "sg:city":"Houston",
    "sg:classifiers":[
        {
            "category":"Communications",
            "type":"Services"
        }
    ],
    "sg:phone":"+1 713 599 1337",
    "sg:postcode":"77056",
    "sg:province":"TX",
    "sg:tags":[
        "web",
        "design"
    ],
    "wof:name":"Tanglewood Property",
    "wof:placetype":"venue"
},
  "geometry": {"coordinates":[-95.46041200000001,29.737937],"type":"Point"}
}