{
  "type": "Feature",
  "properties": {
    "iso:country":"US",
    "sg:address":"807 S Cedar St",
    "sg:city":"Borger",
    "sg:classifiers":[
        {
            "category":"Personal",
            "subcategory":"Barber",
            "type":"Services"
        }
    ],
    "sg:phone":"+1 806 274 5801",
    "sg:postcode":"79007",
    "sg:province":"TX",
    "sg:tags":[
        "shop"
    ],
    "wof:name":"Jay's Barber Shop",
    "wof:placetype":"venue"
},
  "geometry": {"coordinates":[-101.398709,35.658886],"type":"Point"}
}