{
  "type": "Feature",
  "properties": {
    "iso:country":"US",
    "sg:address":"5918 Canal St",
    "sg:city":"Houston",
    "sg:classifiers":[
        {
            "category":"Retail",
            "subcategory":"Auto Repair",
            "type":"Services"
        }
    ],
    "sg:phone":"+1 713 923 5671",
    "sg:postcode":"77011",
    "sg:province":"TX",
    "sg:tags":[
        "equipment",
        "electrical"
    ],
    "wof:name":"Quality Auto Electric Inc",
    "wof:placetype":"venue"
},
  "geometry": {"coordinates":[-95.31426999999999,29.744029],"type":"Point"}
}