{
  "type": "Feature",
  "properties": {
    "iso:country":"US",
    "sg:address":"327 W. 19th Street",
    "sg:city":"Houston",
    "sg:classifiers":[
        {
            "category":"Arts & Performance",
            "subcategory":"Art Gallery",
            "type":"Entertainment"
        }
    ],
    "sg:phone":"+1 713 426 2414",
    "sg:postcode":"77008",
    "sg:province":"TX",
    "sg:website":"gallery19heights.org",
    "wof:name":"Heights Gallery",
    "wof:placetype":"venue"
},
  "geometry": {"coordinates":[-95.402002,29.802899],"type":"Point"}
}