{
  "type": "Feature",
  "properties": {
    "iso:country":"US",
    "sg:address":"10714 Concho St",
    "sg:city":"Houston",
    "sg:classifiers":[
        {
            "category":"Professional",
            "type":"Services"
        }
    ],
    "sg:phone":"+1 281 498 5805",
    "sg:postcode":"77072",
    "sg:province":"TX",
    "sg:tags":[
        "miscellaneous"
    ],
    "wof:name":"AB Cdl Services",
    "wof:placetype":"venue"
},
  "geometry": {"coordinates":[-95.570819,29.693307],"type":"Point"}
}