{
  "type": "Feature",
  "properties": {
    "iso:country":"US",
    "sg:address":"3100 Ames Rd",
    "sg:city":"Lancaster",
    "sg:classifiers":[
        {
            "category":"Organizations",
            "subcategory":"Religious Organization",
            "type":"Services"
        }
    ],
    "sg:phone":"+1 972 227 4771",
    "sg:postcode":"75134",
    "sg:province":"TX",
    "wof:name":"Good Faith Bible Church",
    "wof:placetype":"venue"
},
  "geometry": {"coordinates":[-96.79540900000001,32.624337],"type":"Point"}
}