{
  "type": "Feature",
  "properties": {
    "iso:country":"US",
    "sg:address":"1501 North St",
    "sg:city":"Nacogdoches",
    "sg:classifiers":[
        {
            "category":"Food & Beverages",
            "subcategory":"Liquor & Beverages",
            "type":"Retail Goods"
        }
    ],
    "sg:phone":"+1 936 569 1933",
    "sg:postcode":"75965",
    "sg:province":"TX",
    "wof:name":"Liquor-Mart",
    "wof:placetype":"venue"
},
  "geometry": {"coordinates":[-94.652992,31.614314],"type":"Point"}
}