{
  "type": "Feature",
  "properties": {
    "iso:country":"US",
    "sg:address":"2027 Sherwood Way",
    "sg:city":"San Angelo",
    "sg:classifiers":[
        {
            "category":"Food & Beverages",
            "subcategory":"Meat & Fish",
            "type":"Retail Goods"
        }
    ],
    "sg:phone":"+1 325 224 8900",
    "sg:postcode":"76901",
    "sg:province":"TX",
    "wof:name":"Honey Glazed Ham & Deli",
    "wof:placetype":"venue"
},
  "geometry": {"coordinates":[-100.463787,31.45307],"type":"Point"}
}