{
  "type": "Feature",
  "properties": {
    "iso:country":"US",
    "sg:address":"2001 Birchwood Ln",
    "sg:city":"Grand Prairie",
    "sg:classifiers":[
        {
            "category":"Professional",
            "subcategory":"Business Services",
            "type":"Services"
        }
    ],
    "sg:phone":"+1 972 660 2760",
    "sg:postcode":"75050",
    "sg:province":"TX",
    "wof:name":"Giesing Mark Pool Service",
    "wof:placetype":"venue"
},
  "geometry": {"coordinates":[-97.030945,32.767649],"type":"Point"}
}