{
  "type": "Feature",
  "properties": {
    "iso:country":"US",
    "sg:address":"3307 Windy Harbor Dr",
    "sg:city":"Austin",
    "sg:classifiers":[
        {
            "category":"Real Estate",
            "subcategory":"Architect",
            "type":"Services"
        }
    ],
    "sg:phone":"+1 512 478 9828",
    "sg:postcode":"78734",
    "sg:province":"TX",
    "wof:name":"Husodo Lina Aia",
    "wof:placetype":"venue"
},
  "geometry": {"coordinates":[-97.916033,30.386262],"type":"Point"}
}