{
  "type": "Feature",
  "properties": {
    "iso:country":"US",
    "sg:address":"2215 Cedar Springs Rd",
    "sg:city":"Dallas",
    "sg:classifiers":[
        {
            "category":"Arts & Performance",
            "subcategory":"Art Gallery",
            "type":"Entertainment"
        }
    ],
    "sg:phone":"+1 214 871 9311",
    "sg:postcode":"75201",
    "sg:province":"TX",
    "wof:name":"Kristy Stubbs Gallery",
    "wof:placetype":"venue"
},
  "geometry": {"coordinates":[-96.80523599999999,32.794634],"type":"Point"}
}