{
  "type": "Feature",
  "properties": {
    "iso:country":"US",
    "sg:address":"1210 Lincoln St",
    "sg:city":"Laredo",
    "sg:classifiers":[
        {
            "category":"Wholesale",
            "subcategory":"Jewelry",
            "type":"Manufacturing & Wholesale Goods"
        }
    ],
    "sg:phone":"+1 956 791 5900",
    "sg:postcode":"78040",
    "sg:province":"TX",
    "sg:tags":[
        "watch"
    ],
    "wof:name":"Elegant Watches & Novelties",
    "wof:placetype":"venue"
},
  "geometry": {"coordinates":[-99.50839000000001,27.504346],"type":"Point"}
}