{
  "type": "Feature",
  "properties": {
    "iso:country":"US",
    "sg:address":"6211 FM 3180",
    "sg:city":"Baytown",
    "sg:classifiers":[
        {
            "category":"Retail",
            "subcategory":"Repair Shop",
            "type":"Services"
        }
    ],
    "sg:phone":"+1 281 573 1471",
    "sg:postcode":"77520",
    "sg:province":"TX",
    "wof:name":"Taxidermy Den",
    "wof:placetype":"venue"
},
  "geometry": {"coordinates":[-94.85533,29.783642],"type":"Point"}
}