{
  "type": "Feature",
  "properties": {
    "iso:country":"US",
    "sg:address":"4806 SW Moody St",
    "sg:city":"Victoria",
    "sg:classifiers":[
        {
            "category":"Building & Trades",
            "subcategory":"Landscaping Services",
            "type":"Services"
        }
    ],
    "sg:phone":"+1 361 580 3566",
    "sg:postcode":"77905",
    "sg:province":"TX",
    "wof:name":"McCoy Tree Surgery",
    "wof:placetype":"venue"
},
  "geometry": {"coordinates":[-97.05982,28.775564],"type":"Point"}
}