{
  "type": "Feature",
  "properties": {
    "iso:country":"US",
    "sg:address":"1222 Mc Ham St",
    "sg:city":"Irving",
    "sg:classifiers":[
        {
            "category":"Professional",
            "subcategory":"Business Services",
            "type":"Services"
        }
    ],
    "sg:phone":"+1 972 255 0866",
    "sg:postcode":"75062",
    "sg:province":"TX",
    "wof:name":"Convulted Solutions",
    "wof:placetype":"venue"
},
  "geometry": {"coordinates":[-96.962458,32.848718],"type":"Point"}
}