{
  "type": "Feature",
  "properties": {
    "iso:country":"US",
    "sg:address":"2230 W Park Row Dr",
    "sg:city":"Arlington",
    "sg:classifiers":[
        {
            "category":"Restaurant",
            "type":"Food & Drink"
        }
    ],
    "sg:phone":"+1 817 792 3430",
    "sg:postcode":"76013",
    "sg:province":"TX",
    "sg:tags":[
        "mexican"
    ],
    "wof:name":"Senor Sol",
    "wof:placetype":"venue"
},
  "geometry": {"coordinates":[-97.145363,32.721238],"type":"Point"}
}