{
  "type": "Feature",
  "properties": {
    "iso:country":"US",
    "sg:address":"16125 Cairnway Dr",
    "sg:city":"Houston",
    "sg:classifiers":[
        {
            "category":"Health Services",
            "subcategory":"Doctor",
            "type":"Services"
        },
        {
            "category":"Health Services",
            "subcategory":"Clinic",
            "type":"Services"
        },
        {
            "category":"Health Services",
            "subcategory":"Chiropractor",
            "type":"Services"
        }
    ],
    "sg:phone":"+1 281 463 3223",
    "sg:postcode":"77084",
    "sg:province":"TX",
    "sg:tags":[
        "physician",
        "medical",
        "surgeon",
        "chiropractic"
    ],
    "wof:name":"Bear Creek Chiropractic Clinic",
    "wof:placetype":"venue"
},
  "geometry": {"coordinates":[-95.643323,29.84137],"type":"Point"}
}