{
  "type": "Feature",
  "properties": {
    "iso:country":"US",
    "sg:address":"7322 Jones Maltsberger Rd",
    "sg:city":"San Antonio",
    "sg:classifiers":[
        {
            "category":"Restaurant",
            "type":"Food & Drink"
        }
    ],
    "sg:menulink":"http://www.allmenus.com/tx/san-antonio/222048-chipotle/menu/",
    "sg:phone":"+1 210 832 9444",
    "sg:postcode":"78209",
    "sg:province":"TX",
    "sg:tags":[
        "mexican"
    ],
    "wof:name":"Chipotle",
    "wof:placetype":"venue"
},
  "geometry": {"coordinates":[-98.48118100000001,29.498365],"type":"Point"}
}