{
  "type": "Feature",
  "properties": {
    "iso:country":"US",
    "sg:address":"12770 Coit Rd",
    "sg:city":"Dallas",
    "sg:classifiers":[
        {
            "category":"Insurance",
            "subcategory":"Insurance Agent",
            "type":"Services"
        }
    ],
    "sg:phone":"+1 972 455 1400",
    "sg:postcode":"75251",
    "sg:province":"TX",
    "sg:tags":[
        "broker"
    ],
    "wof:name":"Allied North America",
    "wof:placetype":"venue"
},
  "geometry": {"coordinates":[-96.76912,32.923019],"type":"Point"}
}