{
  "type": "Feature",
  "properties": {
    "iso:country":"US",
    "sg:address":"3789 Brookhaven Club Dr",
    "sg:city":"Addison",
    "sg:classifiers":[
        {
            "category":"Real Estate",
            "subcategory":"Real Estate Operator",
            "type":"Services"
        }
    ],
    "sg:phone":"+1 972 247 3328",
    "sg:postcode":"75001",
    "sg:province":"TX",
    "sg:tags":[
        "apartment"
    ],
    "wof:name":"Greenbrook Apartments",
    "wof:placetype":"venue"
},
  "geometry": {"coordinates":[-96.85242599999999,32.935517],"type":"Point"}
}