{
  "type": "Feature",
  "properties": {
    "iso:country":"US",
    "sg:address":"4120 Fairmont Pkwy",
    "sg:city":"Pasadena",
    "sg:classifiers":[
        {
            "category":"Real Estate",
            "subcategory":"Real Estate Agent",
            "type":"Services"
        }
    ],
    "sg:phone":"+1 281 487 8870",
    "sg:postcode":"77504",
    "sg:province":"TX",
    "sg:website":"www.coldwellbankerunited.com",
    "wof:name":"Coldwell Banker United Realtor",
    "wof:placetype":"venue"
},
  "geometry": {"coordinates":[-95.18210500000001,29.650734],"type":"Point"}
}