{
  "type": "Feature",
  "properties": {
    "iso:country":"US",
    "sg:address":"103 N Llano St",
    "sg:city":"Fredericksburg",
    "sg:classifiers":[
        {
            "category":"Shopping",
            "subcategory":"Bicycles & Sporting Goods",
            "type":"Retail Goods"
        }
    ],
    "sg:phone":"+1 830 997 3170",
    "sg:postcode":"78624",
    "sg:province":"TX",
    "wof:name":"Djh Guns & Ammo",
    "wof:placetype":"venue"
},
  "geometry": {"coordinates":[-98.869507,30.274883],"type":"Point"}
}