{
  "type": "Feature",
  "properties": {
    "iso:country":"US",
    "sg:address":"1802 E 6th St",
    "sg:city":"Austin",
    "sg:classifiers":[
        {
            "category":"Retail",
            "subcategory":"Auto Repair",
            "type":"Services"
        }
    ],
    "sg:phone":"+1 512 472 1025",
    "sg:postcode":"78702",
    "sg:province":"TX",
    "sg:tags":[
        "repairing",
        "automobile",
        "general"
    ],
    "wof:name":"Johnson's Automotive",
    "wof:placetype":"venue"
},
  "geometry": {"coordinates":[-97.723358,30.26211],"type":"Point"}
}