{
  "type": "Feature",
  "properties": {
    "iso:country":"US",
    "sg:address":"503 N Water St",
    "sg:city":"Burnet",
    "sg:classifiers":[
        {
            "category":"Building & Trades",
            "subcategory":"Construction",
            "type":"Services"
        }
    ],
    "sg:phone":"+1 512 756 4155",
    "sg:postcode":"78611",
    "sg:province":"TX",
    "sg:tags":[
        "hanging",
        "contractor"
    ],
    "wof:name":"Three Star Custom Painting",
    "wof:placetype":"venue"
},
  "geometry": {"coordinates":[-98.230619,30.76583],"type":"Point"}
}