{
  "type": "Feature",
  "properties": {
    "iso:country":"US",
    "sg:address":"445 Precinct Line Rd",
    "sg:city":"Hurst",
    "sg:classifiers":[
        {
            "category":"Professional",
            "type":"Services"
        }
    ],
    "sg:phone":"+1 817 589 7893",
    "sg:postcode":"76053",
    "sg:province":"TX",
    "wof:name":"I W T PC Services",
    "wof:placetype":"venue"
},
  "geometry": {"coordinates":[-97.186589,32.816526],"type":"Point"}
}