{
  "type": "Feature",
  "properties": {
    "iso:country":"US",
    "sg:address":"8320 Bee Caves Rd",
    "sg:city":"Austin",
    "sg:classifiers":[
        {
            "category":"Banks & Credit Unions",
            "subcategory":"Bank",
            "type":"Services"
        }
    ],
    "sg:phone":"+1 512 327 6396",
    "sg:postcode":"78746",
    "sg:province":"TX",
    "sg:tags":[
        "loan",
        "real estate"
    ],
    "wof:name":"Altex Mortgage",
    "wof:placetype":"venue"
},
  "geometry": {"coordinates":[-97.85273100000001,30.313343],"type":"Point"}
}