{
  "type": "Feature",
  "properties": {
    "iso:country":"US",
    "sg:address":"709 College Ave",
    "sg:city":"South Houston",
    "sg:classifiers":[
        {
            "category":"Personal",
            "subcategory":"Beauty Salon",
            "type":"Services"
        }
    ],
    "sg:phone":"+1 713 948 0080",
    "sg:postcode":"77587",
    "sg:province":"TX",
    "wof:name":"Berti's Beauty",
    "wof:placetype":"venue"
},
  "geometry": {"coordinates":[-95.239011,29.660733],"type":"Point"}
}