{
  "type": "Feature",
  "properties": {
    "iso:country":"US",
    "sg:address":"12501 John F Kennedy Blvd",
    "sg:city":"Houston",
    "sg:classifiers":[
        {
            "category":"Food & Beverages",
            "subcategory":"Groceries & Convenience Stores",
            "type":"Retail Goods"
        }
    ],
    "sg:phone":"+1 281 442 5177",
    "sg:postcode":"77039",
    "sg:province":"TX",
    "wof:name":"Fairway Food Mart",
    "wof:placetype":"venue"
},
  "geometry": {"coordinates":[-95.332199,29.905001],"type":"Point"}
}