{
  "type": "Feature",
  "properties": {
    "iso:country":"US",
    "sg:address":"217 Red Haven Dr",
    "sg:city":"Highlands",
    "sg:classifiers":[
        {
            "category":"Arena",
            "subcategory":"Sports Club",
            "type":"Entertainment"
        }
    ],
    "sg:phone":"+1 281 426 7482",
    "sg:postcode":"77562",
    "sg:province":"TX",
    "sg:tags":[
        "health"
    ],
    "wof:name":"O'dunn's Gym",
    "wof:placetype":"venue"
},
  "geometry": {"coordinates":[-95.05448199999999,29.831656],"type":"Point"}
}