{
  "type": "Feature",
  "properties": {
    "iso:country":"US",
    "sg:address":"1709 Madison Ave",
    "sg:city":"Austin",
    "sg:classifiers":[
        {
            "category":"Wholesale",
            "subcategory":"Vending Machines",
            "type":"Manufacturing & Wholesale Goods"
        }
    ],
    "sg:phone":"+1 512 371 0211",
    "sg:postcode":"78757",
    "sg:province":"TX",
    "sg:tags":[
        "operator"
    ],
    "wof:name":"Family Vending LLC",
    "wof:placetype":"venue"
},
  "geometry": {"coordinates":[-97.726634,30.344526],"type":"Point"}
}