{
  "type": "Feature",
  "properties": {
    "iso:country":"US",
    "sg:address":"2121 Brittmoore Rd",
    "sg:city":"Houston",
    "sg:classifiers":[
        {
            "category":"Building & Trades",
            "subcategory":"Construction",
            "type":"Services"
        }
    ],
    "sg:phone":"+1 713 460 9940",
    "sg:postcode":"77043",
    "sg:province":"TX",
    "sg:tags":[
        "contractor",
        "general"
    ],
    "wof:name":"Horizon Builders Inc",
    "wof:placetype":"venue"
},
  "geometry": {"coordinates":[-95.56999,29.813023],"type":"Point"}
}