{
  "type": "Feature",
  "properties": {
    "iso:country":"US",
    "sg:address":"805 NW 19th St",
    "sg:city":"San Antonio",
    "sg:classifiers":[
        {
            "category":"Food & Beverages",
            "subcategory":"Groceries & Convenience Stores",
            "type":"Retail Goods"
        }
    ],
    "sg:phone":"+1 210 436 2651",
    "sg:postcode":"78207",
    "sg:province":"TX",
    "wof:name":"Trevinos Grocery",
    "wof:placetype":"venue"
},
  "geometry": {"coordinates":[-98.535237,29.43666],"type":"Point"}
}