{
  "type": "Feature",
  "properties": {
    "iso:country":"US",
    "sg:address":"10501 Hard Rock Rd",
    "sg:city":"Austin",
    "sg:classifiers":[
        {
            "category":"Communications",
            "subcategory":"Film & Video Production",
            "type":"Services"
        }
    ],
    "sg:phone":"+1 512 336 7316",
    "sg:postcode":"78750",
    "sg:province":"TX",
    "sg:tags":[
        "motion"
    ],
    "wof:name":"North Fork Films",
    "wof:placetype":"venue"
},
  "geometry": {"coordinates":[-97.80769600000001,30.451898],"type":"Point"}
}