{
  "type": "Feature",
  "properties": {
    "iso:country":"US",
    "sg:address":"4716 Steffani Ln",
    "sg:city":"Houston",
    "sg:classifiers":[
        {
            "category":"Shopping",
            "subcategory":"Discount & Variety Stores",
            "type":"Retail Goods"
        }
    ],
    "sg:phone":"+1 713 896 1665",
    "sg:postcode":"77041",
    "sg:province":"TX",
    "sg:tags":[
        "liquidator"
    ],
    "wof:name":"Forest Roberts Sales",
    "wof:placetype":"venue"
},
  "geometry": {"coordinates":[-95.54616,29.838517],"type":"Point"}
}