{
  "type": "Feature",
  "properties": {
    "iso:country":"US",
    "sg:address":"695 Pineloch Dr",
    "sg:city":"Webster",
    "sg:classifiers":[
        {
            "category":"Building & Trades",
            "subcategory":"Pest Control",
            "type":"Services"
        }
    ],
    "sg:phone":"+1 281 286 2847",
    "sg:postcode":"77598",
    "sg:province":"TX",
    "wof:name":"Coastal Termite & Pest Control",
    "wof:placetype":"venue"
},
  "geometry": {"coordinates":[-95.14899200000001,29.570566],"type":"Point"}
}