{
  "type": "Feature",
  "properties": {
    "iso:country":"US",
    "sg:address":"2890 W Hwy 199",
    "sg:city":"Springtown",
    "sg:classifiers":[
        {
            "category":"Recreation",
            "type":"Entertainment"
        }
    ],
    "sg:phone":"+1 817 523 4646",
    "sg:postcode":"76082",
    "sg:province":"TX",
    "wof:name":"Tenacious Tumbling Trampoline",
    "wof:placetype":"venue"
},
  "geometry": {"coordinates":[-97.72675,32.97397],"type":"Point"}
}