{
  "type": "Feature",
  "properties": {
    "iso:country":"US",
    "sg:address":"616 W 35th St",
    "sg:city":"Austin",
    "sg:classifiers":[
        {
            "category":"Building & Trades",
            "subcategory":"Construction",
            "type":"Services"
        }
    ],
    "sg:phone":"+1 512 371 7071",
    "sg:postcode":"78705",
    "sg:province":"TX",
    "sg:tags":[
        "house"
    ],
    "wof:name":"Austin City Homes LLC",
    "wof:placetype":"venue"
},
  "geometry": {"coordinates":[-97.740515,30.301848],"type":"Point"}
}