{
  "type": "Feature",
  "properties": {
    "iso:country":"US",
    "sg:address":"1465 FM 2673",
    "sg:city":"New Braunfels",
    "sg:classifiers":[
        {
            "category":"Retail",
            "subcategory":"Repair Shop",
            "type":"Services"
        }
    ],
    "sg:phone":"+1 830 964 2211",
    "sg:postcode":"78133",
    "sg:province":"TX",
    "sg:tags":[
        "refrigeration"
    ],
    "wof:name":"Canyon Lake Air Conditioning",
    "wof:placetype":"venue"
},
  "geometry": {"coordinates":[-98.17357,29.849152],"type":"Point"}
}