{
  "type": "Feature",
  "properties": {
    "iso:country":"US",
    "sg:address":"3721 Ballet Ct",
    "sg:city":"Plano",
    "sg:classifiers":[
        {
            "category":"Professional",
            "subcategory":"Computer Services",
            "type":"Services"
        }
    ],
    "sg:phone":"+1 972 881 4254",
    "sg:postcode":"75023",
    "sg:province":"TX",
    "sg:tags":[
        "consultant"
    ],
    "wof:name":"Synaptic Solutions",
    "wof:placetype":"venue"
},
  "geometry": {"coordinates":[-96.709467,33.045993],"type":"Point"}
}