{
  "type": "Feature",
  "properties": {
    "iso:country":"US",
    "sg:address":"938 W Davis St",
    "sg:city":"Dallas",
    "sg:classifiers":[
        {
            "category":"Retail",
            "subcategory":"Auto Repair",
            "type":"Services"
        }
    ],
    "sg:phone":"+1 214 943 1933",
    "sg:postcode":"75208",
    "sg:province":"TX",
    "wof:name":"Lloyd Hall's Alignment & Brake Service",
    "wof:placetype":"venue"
},
  "geometry": {"coordinates":[-96.839203,32.749599],"type":"Point"}
}