{
  "type": "Feature",
  "properties": {
    "iso:country":"US",
    "sg:address":"4739 Maple Ave",
    "sg:city":"Dallas",
    "sg:classifiers":[
        {
            "category":"Professional",
            "subcategory":"Accounting & Tax Preparation",
            "type":"Services"
        }
    ],
    "sg:phone":"+1 214 219 6222",
    "sg:postcode":"75219",
    "sg:province":"TX",
    "sg:tags":[
        "accountant"
    ],
    "wof:name":"Sanchez Group Llc",
    "wof:placetype":"venue"
},
  "geometry": {"coordinates":[-96.826797,32.814701],"type":"Point"}
}