{
  "type": "Feature",
  "properties": {
    "iso:country":"US",
    "sg:address":"206 E US Hwy 80",
    "sg:city":"White Oak",
    "sg:classifiers":[
        {
            "category":"Banks & Credit Unions",
            "subcategory":"Bank",
            "type":"Services"
        }
    ],
    "sg:phone":"+1 903 295 1339",
    "sg:postcode":"75693",
    "sg:province":"TX",
    "wof:name":"Mid Valley Federal CU",
    "wof:placetype":"venue"
},
  "geometry": {"coordinates":[-94.856922,32.519194],"type":"Point"}
}