{
  "type": "Feature",
  "properties": {
    "iso:country":"US",
    "sg:address":"8445 Freeport Pkwy",
    "sg:city":"Irving",
    "sg:classifiers":[
        {
            "category":"Real Estate",
            "subcategory":"Developer",
            "type":"Services"
        }
    ],
    "sg:phone":"+1 972 929 1214",
    "sg:postcode":"75063",
    "sg:province":"TX",
    "sg:tags":[
        "engineering",
        "investor"
    ],
    "wof:name":"Pegasus Associates Inc",
    "wof:placetype":"venue"
},
  "geometry": {"coordinates":[-97.018953,32.923298],"type":"Point"}
}