{
  "type": "Feature",
  "properties": {
    "iso:country":"US",
    "sg:address":"1900 E Elizabeth St",
    "sg:city":"Brownsville",
    "sg:classifiers":[
        {
            "category":"Wholesale",
            "subcategory":"Groceries",
            "type":"Manufacturing & Wholesale Goods"
        }
    ],
    "sg:phone":"+1 956 554 7811",
    "sg:postcode":"78520",
    "sg:province":"TX",
    "wof:name":"Heritage Health & Products",
    "wof:placetype":"venue"
},
  "geometry": {"coordinates":[-97.49329899999999,25.896614],"type":"Point"}
}