{
  "type": "Feature",
  "properties": {
    "iso:country":"US",
    "sg:address":"211 Main St",
    "sg:city":"Hale Center",
    "sg:classifiers":[
        {
            "category":"Personal",
            "subcategory":"Beauty Salon",
            "type":"Services"
        }
    ],
    "sg:phone":"+1 806 839 2283",
    "sg:postcode":"79041",
    "sg:province":"TX",
    "wof:name":"Shear Class Salon",
    "wof:placetype":"venue"
},
  "geometry": {"coordinates":[-101.84538000000001,34.060097],"type":"Point"}
}