{
  "type": "Feature",
  "properties": {
    "iso:country":"US",
    "sg:address":"7015 Thrush Dr",
    "sg:city":"Houston",
    "sg:classifiers":[
        {
            "category":"Professional",
            "type":"Services"
        }
    ],
    "sg:phone":"+1 713 643 6460",
    "sg:postcode":"77087",
    "sg:province":"TX",
    "wof:name":"Bd Jay Services",
    "wof:placetype":"venue"
},
  "geometry": {"coordinates":[-95.30230400000001,29.667902],"type":"Point"}
}