{
  "type": "Feature",
  "properties": {
    "iso:country":"US",
    "sg:address":"4115 Jordan Valley Rd",
    "sg:city":"Dallas",
    "sg:classifiers":[
        {
            "category":"Building & Trades",
            "subcategory":"Landscaping Services",
            "type":"Services"
        }
    ],
    "sg:phone":"+1 214 256 0197",
    "sg:postcode":"75253",
    "sg:province":"TX",
    "sg:tags":[
        "tree"
    ],
    "wof:name":"Tj Tree Svc",
    "wof:placetype":"venue"
},
  "geometry": {"coordinates":[-96.64882299999999,32.65433],"type":"Point"}
}