{
  "type": "Feature",
  "properties": {
    "iso:country":"US",
    "sg:address":"209 W Trotwood St",
    "sg:city":"Edna",
    "sg:classifiers":[
        {
            "category":"Manufacturing",
            "subcategory":"Glass & Minerals",
            "type":"Manufacturing & Wholesale Goods"
        }
    ],
    "sg:phone":"+1 361 782 0078",
    "sg:postcode":"77957",
    "sg:province":"TX",
    "sg:tags":[
        "product",
        "nonmetallic",
        "mfg"
    ],
    "wof:name":"Mareks Accent",
    "wof:placetype":"venue"
},
  "geometry": {"coordinates":[-96.63930999999999,28.969674],"type":"Point"}
}