{
  "type": "Feature",
  "properties": {
    "iso:country":"US",
    "sg:address":"206 Geneseo Rd",
    "sg:city":"San Antonio",
    "sg:classifiers":[
        {
            "category":"Real Estate",
            "subcategory":"Real Estate Operator",
            "type":"Services"
        }
    ],
    "sg:phone":"+1 210 865 1254",
    "sg:postcode":"78209",
    "sg:province":"TX",
    "sg:tags":[
        "property",
        "lessor"
    ],
    "wof:name":"Bohls Interests LLC",
    "wof:placetype":"venue"
},
  "geometry": {"coordinates":[-98.453975,29.469635],"type":"Point"}
}