{
  "type": "Feature",
  "properties": {
    "iso:country":"US",
    "sg:address":"1700 Brook Ln",
    "sg:city":"Flower Mound",
    "sg:classifiers":[
        {
            "category":"Building & Trades",
            "subcategory":"Landscaping Services",
            "type":"Services"
        }
    ],
    "sg:phone":"+1 972 539 4495",
    "sg:postcode":"75028",
    "sg:province":"TX",
    "sg:tags":[
        "landscape"
    ],
    "wof:name":"Bouling Landscape Service",
    "wof:placetype":"venue"
},
  "geometry": {"coordinates":[-97.05718,33.01731],"type":"Point"}
}