{
  "type": "Feature",
  "properties": {
    "iso:country":"US",
    "sg:address":"475 N Valley Pkwy",
    "sg:city":"Lewisville",
    "sg:classifiers":[
        {
            "category":"Retail",
            "subcategory":"Auto Repair",
            "type":"Services"
        }
    ],
    "sg:phone":"+1 972 434 4340",
    "sg:postcode":"75067",
    "sg:province":"TX",
    "sg:tags":[
        "general"
    ],
    "wof:name":"City Garage",
    "wof:placetype":"venue"
},
  "geometry": {"coordinates":[-97.020403,33.047602],"type":"Point"}
}