{
  "type": "Feature",
  "properties": {
    "iso:country":"US",
    "sg:address":"1450 N Redbud Blvd",
    "sg:city":"Mc Kinney",
    "sg:classifiers":[
        {
            "category":"Social Services",
            "type":"Services"
        }
    ],
    "sg:phone":"+1 972 562 0601",
    "sg:postcode":"75069",
    "sg:province":"TX",
    "sg:tags":[
        "organization",
        "welfare"
    ],
    "wof:name":"American Red Cross",
    "wof:placetype":"venue"
},
  "geometry": {"coordinates":[-96.634253,33.210424],"type":"Point"}
}