{
  "type": "Feature",
  "properties": {
    "iso:country":"US",
    "sg:address":"1917 W Austin St",
    "sg:city":"Port Lavaca",
    "sg:classifiers":[
        {
            "category":"Home & Garden",
            "subcategory":"Household Appliances",
            "type":"Retail Goods"
        }
    ],
    "sg:phone":"+1 361 552 2317",
    "sg:postcode":"77979",
    "sg:province":"TX",
    "wof:name":"American Appliance",
    "wof:placetype":"venue"
},
  "geometry": {"coordinates":[-96.636623,28.601017],"type":"Point"}
}