{
  "type": "Feature",
  "properties": {
    "iso:country":"US",
    "sg:address":"609 N Main St",
    "sg:city":"Cleburne",
    "sg:classifiers":[
        {
            "category":"Real Estate",
            "subcategory":"Surveying",
            "type":"Services"
        }
    ],
    "sg:phone":"+1 817 556 3440",
    "sg:postcode":"76033",
    "sg:province":"TX",
    "sg:tags":[
        "surveyor"
    ],
    "wof:name":"Dumas Land Surveying",
    "wof:placetype":"venue"
},
  "geometry": {"coordinates":[-97.388408,32.352931],"type":"Point"}
}