{
  "type": "Feature",
  "properties": {
    "iso:country":"US",
    "sg:address":"2828 Patricia Ln",
    "sg:city":"Garland",
    "sg:classifiers":[
        {
            "category":"Real Estate",
            "subcategory":"Real Estate Agent",
            "type":"Services"
        }
    ],
    "sg:phone":"+1 972 473 2218",
    "sg:postcode":"75041",
    "sg:province":"TX",
    "wof:name":"Amax Investment Services",
    "wof:placetype":"venue"
},
  "geometry": {"coordinates":[-96.65836299999999,32.881962],"type":"Point"}
}