{
  "type": "Feature",
  "properties": {
    "iso:country":"US",
    "sg:address":"714 N Watson Rd",
    "sg:city":"Arlington",
    "sg:classifiers":[
        {
            "category":"Organizations",
            "subcategory":"Professional Association",
            "type":"Services"
        }
    ],
    "sg:phone":"+1 817 652 1298",
    "sg:postcode":"76011",
    "sg:province":"TX",
    "sg:tags":[
        "chambers",
        "commerce"
    ],
    "wof:name":"Us Department Of Commerce",
    "wof:placetype":"venue"
},
  "geometry": {"coordinates":[-97.06218699999999,32.749436],"type":"Point"}
}