{
  "type": "Feature",
  "properties": {
    "iso:country":"US",
    "sg:address":"3901 Westheimer Rd",
    "sg:city":"Houston",
    "sg:classifiers":[
        {
            "category":"Professional",
            "type":"Services"
        }
    ],
    "sg:phone":"+1 713 935 9700",
    "sg:postcode":"77027",
    "sg:province":"TX",
    "sg:tags":[
        "establishment"
    ],
    "wof:name":"Deutser IS",
    "wof:placetype":"venue"
},
  "geometry": {"coordinates":[-95.443808,29.74164],"type":"Point"}
}