{
  "type": "Feature",
  "properties": {
    "iso:country":"US",
    "sg:address":"13480 Northwest Fwy",
    "sg:city":"Houston",
    "sg:classifiers":[
        {
            "category":"Restaurant",
            "type":"Food & Drink"
        }
    ],
    "sg:phone":"+1 713 939 0935",
    "sg:postcode":"77040",
    "sg:province":"TX",
    "wof:name":"Taco Cabana",
    "wof:placetype":"venue"
},
  "geometry": {"coordinates":[-95.50720200000001,29.850401],"type":"Point"}
}