{
  "type": "Feature",
  "properties": {
    "iso:country":"US",
    "sg:address":"10030 Airline Dr",
    "sg:city":"Houston",
    "sg:classifiers":[
        {
            "category":"Home & Garden",
            "subcategory":"Furniture",
            "type":"Retail Goods"
        }
    ],
    "sg:phone":"+1 281 272 0020",
    "sg:postcode":"77037",
    "sg:province":"TX",
    "wof:name":"Jose's Furniture",
    "wof:placetype":"venue"
},
  "geometry": {"coordinates":[-95.400075,29.901615],"type":"Point"}
}