{
  "type": "Feature",
  "properties": {
    "iso:country":"US",
    "sg:address":"2553 Ranch Rd 1323",
    "sg:city":"Willow City",
    "sg:classifiers":[
        {
            "category":"Government",
            "subcategory":"Fire Station",
            "type":"Public Place"
        }
    ],
    "sg:phone":"+1 830 685 3376",
    "sg:postcode":"78636",
    "sg:province":"TX",
    "sg:tags":[
        "department"
    ],
    "wof:name":"Willow City Volunteer Fire",
    "wof:placetype":"venue"
},
  "geometry": {"coordinates":[-98.425646,30.327298],"type":"Point"}
}