{
  "type": "Feature",
  "properties": {
    "iso:country":"US",
    "sg:address":"530 N Main St",
    "sg:city":"Duncanville",
    "sg:classifiers":[
        {
            "category":"Building & Trades",
            "subcategory":"Construction",
            "type":"Services"
        }
    ],
    "sg:phone":"+1 817 461 7663",
    "sg:postcode":"75116",
    "sg:province":"TX",
    "sg:tags":[
        "roofing",
        "contractor"
    ],
    "wof:name":"Nations Roofing",
    "wof:placetype":"venue"
},
  "geometry": {"coordinates":[-96.907758,32.655561],"type":"Point"}
}