{
  "type": "Feature",
  "properties": {
    "iso:country":"US",
    "sg:address":"7700 Seawall Blvd",
    "sg:city":"Galveston",
    "sg:classifiers":[
        {
            "category":"Professional",
            "type":"Services"
        }
    ],
    "sg:phone":"+1 409 741 9521",
    "sg:postcode":"77551",
    "sg:province":"TX",
    "wof:name":"Douglas L Erwin",
    "wof:placetype":"venue"
},
  "geometry": {"coordinates":[-94.843305,29.257061],"type":"Point"}
}