{
  "type": "Feature",
  "properties": {
    "iso:country":"US",
    "sg:address":"1612 Woodhaven Dr",
    "sg:city":"Seagoville",
    "sg:classifiers":[
        {
            "category":"Building & Trades",
            "subcategory":"Construction",
            "type":"Services"
        }
    ],
    "sg:phone":"+1 972 287 4842",
    "sg:postcode":"75159",
    "sg:province":"TX",
    "sg:tags":[
        "specialty"
    ],
    "wof:name":"Amazing Buildings",
    "wof:placetype":"venue"
},
  "geometry": {"coordinates":[-96.553978,32.656144],"type":"Point"}
}