{
  "type": "Feature",
  "properties": {
    "iso:country":"US",
    "sg:address":"5834 Woodland Falls Dr",
    "sg:city":"Humble",
    "sg:classifiers":[
        {
            "category":"Farming",
            "subcategory":"Farm",
            "type":"Manufacturing & Wholesale Goods"
        }
    ],
    "sg:phone":"+1 281 360 3427",
    "sg:postcode":"77345",
    "sg:province":"TX",
    "sg:tags":[
        "crop",
        "general"
    ],
    "wof:name":"Dogwood Creek Farms",
    "wof:placetype":"venue"
},
  "geometry": {"coordinates":[-95.14999,30.04985],"type":"Point"}
}