{
  "type": "Feature",
  "properties": {
    "iso:country":"US",
    "sg:address":"3222 Ivy Falls Dr",
    "sg:city":"Houston",
    "sg:classifiers":[
        {
            "category":"Professional",
            "type":"Services"
        }
    ],
    "sg:phone":"+1 713 397 6629",
    "sg:postcode":"77068",
    "sg:province":"TX",
    "wof:name":"Paos",
    "wof:placetype":"venue"
},
  "geometry": {"coordinates":[-95.490407,30.014088],"type":"Point"}
}