{
  "type": "Feature",
  "properties": {
    "iso:country":"US",
    "sg:address":"9612 Hindo Dr",
    "sg:city":"Conroe",
    "sg:classifiers":[
        {
            "category":"Manufacturing",
            "subcategory":"Retail Goods",
            "type":"Manufacturing & Wholesale Goods"
        }
    ],
    "sg:phone":"+1 936 264 3703",
    "sg:postcode":"77303",
    "sg:province":"TX",
    "sg:tags":[
        "product",
        "mfg"
    ],
    "wof:name":"Conroe Candle Co",
    "wof:placetype":"venue"
},
  "geometry": {"coordinates":[-95.39914,30.372767],"type":"Point"}
}