{
  "type": "Feature",
  "properties": {
    "iso:country":"US",
    "sg:address":"114 Oak Dr",
    "sg:city":"Mc Queeney",
    "sg:classifiers":[
        {
            "category":"Manufacturing",
            "subcategory":"Apparel",
            "type":"Manufacturing & Wholesale Goods"
        }
    ],
    "sg:phone":"+1 210 834 3422",
    "sg:postcode":"78123",
    "sg:province":"TX",
    "sg:tags":[
        "outerwear",
        "mfg"
    ],
    "wof:name":"Kustom Kostumes",
    "wof:placetype":"venue"
},
  "geometry": {"coordinates":[-98.029985,29.609627],"type":"Point"}
}