{
  "type": "Feature",
  "properties": {
    "iso:country":"US",
    "sg:address":"805 19th St",
    "sg:city":"Hondo",
    "sg:classifiers":[
        {
            "category":"Real Estate",
            "subcategory":"Developer",
            "type":"Services"
        }
    ],
    "sg:phone":"+1 830 741 3310",
    "sg:postcode":"78861",
    "sg:province":"TX",
    "wof:name":"Bluegreen Southwest Land Inc",
    "wof:placetype":"venue"
},
  "geometry": {"coordinates":[-99.137199,29.347729],"type":"Point"}
}