{
  "type": "Feature",
  "properties": {
    "iso:country":"US",
    "sg:address":"901 23rd St",
    "sg:city":"Canyon",
    "sg:classifiers":[
        {
            "category":"Deli",
            "type":"Food & Drink"
        }
    ],
    "sg:menulink":"http://www.allmenus.com/tx/canyon/99778-schlotzskys/menu/",
    "sg:phone":"+1 806 655 2867",
    "sg:postcode":"79015",
    "sg:province":"TX",
    "sg:tags":[
        "wrap",
        "american",
        "sandwich",
        "pizza"
    ],
    "wof:name":"Schlotzsky's",
    "wof:placetype":"venue"
},
  "geometry": {"coordinates":[-101.919303,34.974499],"type":"Point"}
}