{
  "type": "Feature",
  "properties": {
    "iso:country":"US",
    "sg:address":"116 Oak Ave",
    "sg:city":"Sulphur Springs",
    "sg:classifiers":[
        {
            "category":"Organizations",
            "subcategory":"Religious Organization",
            "type":"Services"
        }
    ],
    "sg:phone":"+1 903 439 6010",
    "sg:postcode":"75482",
    "sg:province":"TX",
    "sg:tags":[
        "church"
    ],
    "sg:website":"www.ssfbc.org",
    "wof:name":"First Baptist Church Youth",
    "wof:placetype":"venue"
},
  "geometry": {"coordinates":[-95.600178,33.137195],"type":"Point"}
}