{
  "type": "Feature",
  "properties": {
    "iso:country":"US",
    "sg:address":"1240 Southridge Ct",
    "sg:city":"Hurst",
    "sg:classifiers":[
        {
            "category":"Insurance",
            "subcategory":"Insurance Agent",
            "type":"Services"
        }
    ],
    "sg:phone":"+1 817 282 8651",
    "sg:postcode":"76053",
    "sg:province":"TX",
    "wof:name":"Farmers Insurance Group",
    "wof:placetype":"venue"
},
  "geometry": {"coordinates":[-97.180582,32.833238],"type":"Point"}
}