{
  "type": "Feature",
  "properties": {
    "iso:country":"US",
    "sg:address":"4650 S Hampton Rd",
    "sg:city":"Dallas",
    "sg:classifiers":[
        {
            "category":"Organizations",
            "subcategory":"Religious Organization",
            "type":"Services"
        }
    ],
    "sg:phone":"+1 214 337 5800",
    "sg:postcode":"75232",
    "sg:province":"TX",
    "wof:name":"Oak Cliff Church of Christ",
    "wof:placetype":"venue"
},
  "geometry": {"coordinates":[-96.856801,32.6868],"type":"Point"}
}