{
  "type": "Feature",
  "properties": {
    "iso:country":"US",
    "sg:address":"4005 Schley Ct Ste 100",
    "sg:city":"Benbrook",
    "sg:classifiers":[
        {
            "category":"Professional",
            "subcategory":"Business Services",
            "type":"Services"
        }
    ],
    "sg:phone":"+1 817 244 5650",
    "sg:postcode":"76116",
    "sg:province":"TX",
    "sg:tags":[
        "broker"
    ],
    "wof:name":"Karen Roach Manufactures",
    "wof:placetype":"venue"
},
  "geometry": {"coordinates":[-97.472841,32.713023],"type":"Point"}
}