{
  "type": "Feature",
  "properties": {
    "iso:country":"US",
    "sg:address":"6418 Railroad St",
    "sg:city":"Wallis",
    "sg:classifiers":[
        {
            "category":"Government",
            "subcategory":"Post Office",
            "type":"Public Place"
        }
    ],
    "sg:phone":"+1 979 478 6733",
    "sg:postcode":"77485",
    "sg:province":"TX",
    "wof:name":"US Post Office",
    "wof:placetype":"venue"
},
  "geometry": {"coordinates":[-96.063114,29.631361],"type":"Point"}
}