{
  "type": "Feature",
  "properties": {
    "iso:country":"US",
    "sg:address":"2719 S Louisiana Ave",
    "sg:city":"Laredo",
    "sg:classifiers":[
        {
            "category":"Restaurant",
            "type":"Food & Drink"
        }
    ],
    "sg:phone":"+1 956 723 1531",
    "sg:postcode":"78046",
    "sg:province":"TX",
    "sg:tags":[
        "eating"
    ],
    "wof:name":"Toritos Cafe",
    "wof:placetype":"venue"
},
  "geometry": {"coordinates":[-99.468355,27.472369],"type":"Point"}
}