{
  "type": "Feature",
  "properties": {
    "iso:country":"US",
    "sg:address":"1605 Live Oak St",
    "sg:city":"Commerce",
    "sg:classifiers":[
        {
            "category":"Cinema",
            "subcategory":"Movie Rental",
            "type":"Entertainment"
        }
    ],
    "sg:phone":"+1 903 886 8021",
    "sg:postcode":"75428",
    "sg:province":"TX",
    "sg:tags":[
        "video",
        "tape"
    ],
    "wof:name":"Movie Gallery",
    "wof:placetype":"venue"
},
  "geometry": {"coordinates":[-95.90499199999999,33.247276],"type":"Point"}
}