{
  "type": "Feature",
  "properties": {
    "iso:country":"US",
    "sg:address":"132 E Craig Pl",
    "sg:city":"San Antonio",
    "sg:classifiers":[
        {
            "category":"Professional",
            "type":"Services"
        }
    ],
    "sg:phone":"+1 210 736 3234",
    "sg:postcode":"78212",
    "sg:province":"TX",
    "wof:name":"Kay Milne",
    "wof:placetype":"venue"
},
  "geometry": {"coordinates":[-98.49242,29.451902],"type":"Point"}
}