{
  "type": "Feature",
  "properties": {
    "iso:country":"US",
    "sg:address":"612 N Smith Ave",
    "sg:city":"Hebbronville",
    "sg:classifiers":[
        {
            "category":"Real Estate",
            "subcategory":"Real Estate Services",
            "type":"Services"
        },
        {
            "category":"Real Estate",
            "subcategory":"Real Estate Agent",
            "type":"Services"
        }
    ],
    "sg:phone":"+1 361 527 3266",
    "sg:postcode":"78361",
    "sg:province":"TX",
    "sg:tags":[
        "buyer",
        "broker"
    ],
    "wof:name":"Bbg Real Estate, Ltd.",
    "wof:placetype":"venue"
},
  "geometry": {"coordinates":[-98.678551,27.301573],"type":"Point"}
}