{
  "type": "Feature",
  "properties": {
    "iso:country":"US",
    "sg:address":"1000 Heritage Center Cir",
    "sg:city":"Round Rock",
    "sg:classifiers":[
        {
            "category":"Professional",
            "subcategory":"Computer Services",
            "type":"Services"
        }
    ],
    "sg:phone":"+1 512 238 3375",
    "sg:postcode":"78664",
    "sg:province":"TX",
    "sg:tags":[
        "datum"
    ],
    "wof:name":"Zland",
    "wof:placetype":"venue"
},
  "geometry": {"coordinates":[-97.67638100000001,30.518983],"type":"Point"}
}