{
  "type": "Feature",
  "properties": {
    "iso:country":"US",
    "sg:address":"8746 Wiggins St",
    "sg:city":"Houston",
    "sg:classifiers":[
        {
            "category":"Recreation",
            "type":"Entertainment"
        }
    ],
    "sg:phone":"+1 713 675 0297",
    "sg:postcode":"77029",
    "sg:province":"TX",
    "sg:tags":[
        "club",
        "membership"
    ],
    "wof:name":"Club 69 Fragrance Club",
    "wof:placetype":"venue"
},
  "geometry": {"coordinates":[-95.26769,29.764058],"type":"Point"}
}