{
  "type": "Feature",
  "properties": {
    "iso:country":"US",
    "sg:address":"1425 Gross Rd Ste 108",
    "sg:city":"Mesquite",
    "sg:classifiers":[
        {
            "category":"Shopping",
            "subcategory":"Hobbies, Toys, & Games",
            "type":"Retail Goods"
        },
        {
            "category":"Cinema",
            "subcategory":"Movie Rental",
            "type":"Entertainment"
        }
    ],
    "sg:phone":"+1 972 288 4200",
    "sg:postcode":"75149",
    "sg:province":"TX",
    "sg:tags":[
        "shop",
        "hobby",
        "video"
    ],
    "wof:name":"Game Trade",
    "wof:placetype":"venue"
},
  "geometry": {"coordinates":[-96.627888,32.784067],"type":"Point"}
}