{
  "type": "Feature",
  "properties": {
    "iso:country":"US",
    "sg:address":"1452 N Zaragoza Rd",
    "sg:city":"El Paso",
    "sg:classifiers":[
        {
            "category":"Insurance",
            "subcategory":"Insurance Agent",
            "type":"Services"
        }
    ],
    "sg:phone":"+1 915 855 2996",
    "sg:postcode":"79936",
    "sg:province":"TX",
    "wof:name":"Advantage Insurance Agency",
    "wof:placetype":"venue"
},
  "geometry": {"coordinates":[-106.29196,31.737677],"type":"Point"}
}