{
  "type": "Feature",
  "properties": {
    "iso:country":"US",
    "sg:address":"363 Sam Houston Pkwy",
    "sg:city":"Houston",
    "sg:classifiers":[
        {
            "category":"Banks & Credit Unions",
            "subcategory":"Investment Brokerage",
            "type":"Services"
        },
        {
            "category":"Professional",
            "subcategory":"Management & Consulting",
            "type":"Services"
        }
    ],
    "sg:phone":"+1 281 445 6611",
    "sg:postcode":"77060",
    "sg:province":"TX",
    "sg:tags":[
        "advisory",
        "financial"
    ],
    "sg:website":"www.growth-capital.com",
    "wof:name":"Growth Capital Partners Inc",
    "wof:placetype":"venue"
},
  "geometry": {"coordinates":[-95.399186,29.940137],"type":"Point"}
}