{
  "type": "Feature",
  "properties": {
    "iso:country":"US",
    "sg:address":"208 N Lovers Ln",
    "sg:city":"Gatesville",
    "sg:classifiers":[
        {
            "category":"Wholesale",
            "subcategory":"Petroleum",
            "type":"Manufacturing & Wholesale Goods"
        }
    ],
    "sg:phone":"+1 254 248 0756",
    "sg:postcode":"76528",
    "sg:province":"TX",
    "sg:tags":[
        "pipe",
        "line",
        "company"
    ],
    "wof:name":"TXU Pipeline",
    "wof:placetype":"venue"
},
  "geometry": {"coordinates":[-97.72501,31.436941],"type":"Point"}
}