{
  "type": "Feature",
  "properties": {
    "iso:country":"US",
    "sg:address":"1060 N Main St",
    "sg:city":"Euless",
    "sg:classifiers":[
        {
            "category":"Shopping",
            "subcategory":"Discount & Variety Stores",
            "type":"Retail Goods"
        },
        {
            "category":"Shopping",
            "type":"Retail Goods"
        }
    ],
    "sg:phone":"+1 817 318 0103",
    "sg:postcode":"76039",
    "sg:province":"TX",
    "sg:tags":[
        "merchandise"
    ],
    "wof:name":"Dollar Store",
    "wof:placetype":"venue"
},
  "geometry": {"coordinates":[-97.082454,32.851672],"type":"Point"}
}