{
  "type": "Feature",
  "properties": {
    "iso:country":"US",
    "sg:address":"4630 Nasa Road 1",
    "sg:city":"Seabrook",
    "sg:classifiers":[
        {
            "category":"Shopping",
            "subcategory":"Clothing, Apparel, & Fashions",
            "type":"Retail Goods"
        }
    ],
    "sg:phone":"+1 281 326 5115",
    "sg:postcode":"77586",
    "sg:province":"TX",
    "wof:name":"Casanova's Downfall",
    "wof:placetype":"venue"
},
  "geometry": {"coordinates":[-95.06005500000001,29.566693],"type":"Point"}
}