{
  "type": "Feature",
  "properties": {
    "iso:country":"US",
    "sg:address":"PO Box 801523",
    "sg:city":"Dallas",
    "sg:classifiers":[
        {
            "category":"Professional",
            "subcategory":"Accounting & Tax Preparation",
            "type":"Services"
        }
    ],
    "sg:phone":"+1 972 529 6677",
    "sg:postcode":"75380",
    "sg:province":"TX",
    "sg:tags":[
        "accountant"
    ],
    "wof:name":"Burns & Company P C",
    "wof:placetype":"venue"
},
  "geometry": {"coordinates":[-96.817497,32.933701],"type":"Point"}
}