{
  "type": "Feature",
  "properties": {
    "iso:country":"US",
    "sg:address":"614 Elley St",
    "sg:city":"Seguin",
    "sg:classifiers":[
        {
            "category":"Building & Trades",
            "subcategory":"Construction",
            "type":"Services"
        }
    ],
    "sg:phone":"+1 830 379 5662",
    "sg:postcode":"78155",
    "sg:province":"TX",
    "sg:tags":[
        "repairing",
        "remodeling",
        "contractor"
    ],
    "wof:name":"Gume Hernandez Construction",
    "wof:placetype":"venue"
},
  "geometry": {"coordinates":[-97.958607,29.583764],"type":"Point"}
}