{
  "type": "Feature",
  "properties": {
    "iso:country":"US",
    "sg:address":"1410 1st St",
    "sg:city":"Palacios",
    "sg:classifiers":[
        {
            "category":"Restaurant",
            "type":"Food & Drink"
        }
    ],
    "sg:phone":"+1 361 972 5955",
    "sg:postcode":"77465",
    "sg:province":"TX",
    "sg:tags":[
        "mexican"
    ],
    "wof:name":"Matamoros Taco House",
    "wof:placetype":"venue"
},
  "geometry": {"coordinates":[-96.210426,28.708998],"type":"Point"}
}