{
  "type": "Feature",
  "properties": {
    "iso:country":"US",
    "sg:address":"4555 Algernon Dr",
    "sg:city":"Spring",
    "sg:classifiers":[
        {
            "category":"Recreation",
            "type":"Entertainment"
        }
    ],
    "sg:phone":"+1 281 355 1616",
    "sg:postcode":"77373",
    "sg:province":"TX",
    "wof:name":"Freedom Charters LLC",
    "wof:placetype":"venue"
},
  "geometry": {"coordinates":[-95.362993,30.046471],"type":"Point"}
}