{
  "type": "Feature",
  "properties": {
    "iso:country":"US",
    "sg:address":"1208 FM 1845 S",
    "sg:city":"Longview",
    "sg:classifiers":[
        {
            "category":"Professional",
            "subcategory":"Business Services",
            "type":"Services"
        }
    ],
    "sg:phone":"+1 903 758 5267",
    "sg:postcode":"75603",
    "sg:province":"TX",
    "sg:tags":[
        "supply"
    ],
    "wof:name":"Gregg County Auto Auction",
    "wof:placetype":"venue"
},
  "geometry": {"coordinates":[-94.757987,32.466186],"type":"Point"}
}