{
  "type": "Feature",
  "properties": {
    "iso:country":"US",
    "sg:address":"300 Terrace Drive",
    "sg:city":"Richardson",
    "sg:classifiers":[
        {
            "category":"Restaurant",
            "type":"Food & Drink"
        }
    ],
    "sg:postcode":"75081",
    "sg:province":"TX",
    "wof:name":"Mein Cuisine",
    "wof:placetype":"venue"
},
  "geometry": {"coordinates":[-96.727767,32.951709],"type":"Point"}
}