{
  "type": "Feature",
  "properties": {
    "iso:country":"US",
    "sg:address":"226 W College St",
    "sg:city":"Fredericksburg",
    "sg:classifiers":[
        {
            "category":"Professional",
            "subcategory":"Detective & Security Services",
            "type":"Services"
        }
    ],
    "sg:phone":"+1 830 992 2199",
    "sg:postcode":"78624",
    "sg:province":"TX",
    "sg:tags":[
        "information",
        "bureau"
    ],
    "wof:name":"Fredericksburg Building Svc.",
    "wof:placetype":"venue"
},
  "geometry": {"coordinates":[-98.869552,30.280746],"type":"Point"}
}