{
  "type": "Feature",
  "properties": {
    "iso:country":"US",
    "sg:address":"3120 Haynie St",
    "sg:city":"Fort Worth",
    "sg:classifiers":[
        {
            "category":"Retail",
            "subcategory":"Auto Repair",
            "type":"Services"
        }
    ],
    "sg:phone":"+1 817 457 3314",
    "sg:postcode":"76112",
    "sg:province":"TX",
    "sg:tags":[
        "repairing",
        "automobile",
        "general"
    ],
    "wof:name":"David Daw's Quality Car Care",
    "wof:placetype":"venue"
},
  "geometry": {"coordinates":[-97.22125200000001,32.733981],"type":"Point"}
}