{
  "type": "Feature",
  "properties": {
    "iso:country":"US",
    "sg:address":"316 S 17th St",
    "sg:city":"Mcallen",
    "sg:classifiers":[
        {
            "category":"Professional",
            "subcategory":"Advertising",
            "type":"Services"
        }
    ],
    "sg:phone":"+1 956 631 9039",
    "sg:postcode":"78501",
    "sg:province":"TX",
    "sg:tags":[
        "mailing",
        "shipping"
    ],
    "wof:name":"Southwest Mail Svc",
    "wof:placetype":"venue"
},
  "geometry": {"coordinates":[-98.23842399999999,26.201116],"type":"Point"}
}