{
  "type": "Feature",
  "properties": {
    "iso:country":"US",
    "sg:address":"108 S 2nd St",
    "sg:city":"La Porte",
    "sg:classifiers":[
        {
            "category":"Professional",
            "subcategory":"Business Services",
            "type":"Services"
        }
    ],
    "sg:phone":"+1 281 470 1178",
    "sg:postcode":"77571",
    "sg:province":"TX",
    "sg:tags":[
        "plant",
        "treatment",
        "sewage"
    ],
    "wof:name":"Texas Municipal Utility Svcs",
    "wof:placetype":"venue"
},
  "geometry": {"coordinates":[-95.021503,29.665377],"type":"Point"}
}