{
  "type": "Feature",
  "properties": {
    "iso:country":"US",
    "sg:address":"15006 Walters Rd",
    "sg:city":"Houston",
    "sg:classifiers":[
        {
            "category":"Building & Trades",
            "subcategory":"Cleaning & Sanitation",
            "type":"Services"
        }
    ],
    "sg:phone":"+1 281 583 7868",
    "sg:postcode":"77068",
    "sg:province":"TX",
    "sg:tags":[
        "maintenance"
    ],
    "wof:name":"Tad Enterprises",
    "wof:placetype":"venue"
},
  "geometry": {"coordinates":[-95.489159,30.001809],"type":"Point"}
}