{
  "type": "Feature",
  "properties": {
    "iso:country":"US",
    "sg:address":"2151 Silver Moon Trl",
    "sg:city":"Crosby",
    "sg:classifiers":[
        {
            "category":"Shopping",
            "subcategory":"Hobbies, Toys, & Games",
            "type":"Retail Goods"
        }
    ],
    "sg:phone":"+1 281 324 2184",
    "sg:postcode":"77532",
    "sg:province":"TX",
    "wof:name":"Harry Haupt Inc",
    "wof:placetype":"venue"
},
  "geometry": {"coordinates":[-95.12280800000001,29.968257],"type":"Point"}
}