{
  "type": "Feature",
  "properties": {
    "iso:country":"US",
    "sg:address":"827 Martin Rd",
    "sg:city":"Amarillo",
    "sg:classifiers":[
        {
            "category":"Insurance",
            "subcategory":"Insurance Agent",
            "type":"Services"
        },
        {
            "category":"Insurance",
            "subcategory":"Hazard Insurance",
            "type":"Services"
        }
    ],
    "sg:phone":"+1 806 376 6000",
    "sg:postcode":"79107",
    "sg:province":"TX",
    "sg:tags":[
        "auto",
        "commercial",
        "business"
    ],
    "sg:website":"http://www.autopartnersins.com",
    "wof:name":"Autopartners Insurance Agency Inc",
    "wof:placetype":"venue"
},
  "geometry": {"coordinates":[-101.812135,35.222277],"type":"Point"}
}