{
  "type": "Feature",
  "properties": {
    "iso:country":"US",
    "sg:address":"3328 Dorothy Ln",
    "sg:city":"Wylie",
    "sg:classifiers":[
        {
            "category":"Professional",
            "subcategory":"Business Services",
            "type":"Services"
        }
    ],
    "sg:phone":"+1 972 475 1453",
    "sg:postcode":"75098",
    "sg:province":"TX",
    "wof:name":"Design Innovations By C C",
    "wof:placetype":"venue"
},
  "geometry": {"coordinates":[-96.529526,32.960391],"type":"Point"}
}