{
  "type": "Feature",
  "properties": {
    "iso:country":"US",
    "sg:address":"1720 Woodward St",
    "sg:city":"Austin",
    "sg:classifiers":[
        {
            "category":"Building & Trades",
            "subcategory":"Landscaping Services",
            "type":"Services"
        }
    ],
    "sg:phone":"+1 512 225 4485",
    "sg:postcode":"78741",
    "sg:province":"TX",
    "sg:tags":[
        "lawn",
        "stump",
        "tree",
        "grinding",
        "removal"
    ],
    "wof:name":"White Oak tree service",
    "wof:placetype":"venue"
},
  "geometry": {"coordinates":[-97.74452100000001,30.220346],"type":"Point"}
}