{
  "type": "Feature",
  "properties": {
    "iso:country":"US",
    "sg:address":"8517 N Capital of Texas Hwy",
    "sg:city":"Austin",
    "sg:classifiers":[
        {
            "category":"Professional",
            "subcategory":"Computer Services",
            "type":"Services"
        }
    ],
    "sg:phone":"+1 512 936 3727",
    "sg:postcode":"78759",
    "sg:province":"TX",
    "sg:tags":[
        "home",
        "consulting",
        "page",
        "dev",
        "internet"
    ],
    "wof:name":"Scott E Semegran Svc",
    "wof:placetype":"venue"
},
  "geometry": {"coordinates":[-97.762632,30.387628],"type":"Point"}
}