{
  "type": "Feature",
  "properties": {
    "iso:country":"US",
    "sg:address":"308 E Renfro St Ste 206",
    "sg:city":"Burleson",
    "sg:classifiers":[
        {
            "category":"Banks & Credit Unions",
            "subcategory":"Financial Services",
            "type":"Services"
        }
    ],
    "sg:phone":"+1 817 447 4443",
    "sg:postcode":"76028",
    "sg:province":"TX",
    "sg:tags":[
        "broker",
        "mortgage"
    ],
    "wof:name":"Cendera Funding",
    "wof:placetype":"venue"
},
  "geometry": {"coordinates":[-97.316508,32.543232],"type":"Point"}
}