{
  "type": "Feature",
  "properties": {
    "iso:country":"US",
    "sg:address":"7110 Eckhert Rd",
    "sg:city":"San Antonio",
    "sg:classifiers":[
        {
            "category":"Building & Trades",
            "subcategory":"Construction",
            "type":"Services"
        }
    ],
    "sg:phone":"+1 210 523 0364",
    "sg:postcode":"78238",
    "sg:province":"TX",
    "sg:tags":[
        "contractor"
    ],
    "wof:name":"Benjamin Solid Surfaces",
    "wof:placetype":"venue"
},
  "geometry": {"coordinates":[-98.63261900000001,29.504975],"type":"Point"}
}