{
  "type": "Feature",
  "properties": {
    "iso:country":"US",
    "sg:address":"11679 Betty Ln",
    "sg:city":"Kaufman",
    "sg:classifiers":[
        {
            "category":"Building & Trades",
            "subcategory":"Plumbing",
            "type":"Services"
        }
    ],
    "sg:phone":"+1 972 932 3259",
    "sg:postcode":"75142",
    "sg:province":"TX",
    "sg:tags":[
        "plumber",
        "industrial",
        "contractors-commercial"
    ],
    "wof:name":"D J Plumbing Heating",
    "wof:placetype":"venue"
},
  "geometry": {"coordinates":[-96.14325100000001,32.584853],"type":"Point"}
}