{
  "type": "Feature",
  "properties": {
    "iso:country":"US",
    "sg:address":"109 W Renfro St",
    "sg:city":"Burleson",
    "sg:classifiers":[
        {
            "category":"Real Estate",
            "subcategory":"Real Estate Agent",
            "type":"Services"
        },
        {
            "category":"Professional",
            "subcategory":"Management & Consulting",
            "type":"Services"
        }
    ],
    "sg:phone":"+1 817 426 4484",
    "sg:postcode":"76028",
    "sg:province":"TX",
    "sg:tags":[
        "consultant"
    ],
    "wof:name":"Exit Realty-The King Co",
    "wof:placetype":"venue"
},
  "geometry": {"coordinates":[-97.32117,32.54299],"type":"Point"}
}