{
  "type": "Feature",
  "properties": {
    "iso:country":"US",
    "sg:address":"406 Washington Pl",
    "sg:city":"Wylie",
    "sg:classifiers":[
        {
            "category":"Travel",
            "subcategory":"Travel Agent",
            "type":"Entertainment"
        }
    ],
    "sg:phone":"+1 972 442 2730",
    "sg:postcode":"75098",
    "sg:province":"TX",
    "sg:tags":[
        "agency"
    ],
    "wof:name":"Hagler Travel",
    "wof:placetype":"venue"
},
  "geometry": {"coordinates":[-96.57374,33.024537],"type":"Point"}
}