{
  "type": "Feature",
  "properties": {
    "iso:country":"US",
    "sg:address":"325 N Bell Blvd",
    "sg:city":"Cedar Park",
    "sg:classifiers":[
        {
            "category":"Restaurant",
            "type":"Food & Drink"
        }
    ],
    "sg:menulink":"http://www.allmenus.com/tx/liberty-hill-cedar-park/177342-jack-in-the-box/menu/",
    "sg:phone":"+1 512 335 3161",
    "sg:postcode":"78613",
    "sg:province":"TX",
    "sg:tags":[
        "burger",
        "american"
    ],
    "wof:name":"Jack in the Box",
    "wof:placetype":"venue"
},
  "geometry": {"coordinates":[-97.82530800000001,30.513031],"type":"Point"}
}