{
  "type": "Feature",
  "properties": {
    "iso:country":"US",
    "sg:address":"1217 Shannon Dr",
    "sg:city":"Cleburne",
    "sg:classifiers":[
        {
            "category":"Shopping",
            "subcategory":"Gifts & Souvenirs",
            "type":"Retail Goods"
        }
    ],
    "sg:phone":"+1 817 774 3130",
    "sg:postcode":"76031",
    "sg:province":"TX",
    "wof:name":"Leslie F Leake",
    "wof:placetype":"venue"
},
  "geometry": {"coordinates":[-97.28959500000001,32.376173],"type":"Point"}
}