{
  "type": "Feature",
  "properties": {
    "iso:country":"US",
    "sg:address":"9808 Timber Ridge Pass",
    "sg:city":"Austin",
    "sg:classifiers":[
        {
            "category":"Building & Trades",
            "subcategory":"Landscaping Services",
            "type":"Services"
        }
    ],
    "sg:phone":"+1 512 263 1900",
    "sg:postcode":"78733",
    "sg:province":"TX",
    "sg:tags":[
        "landscape",
        "contractor"
    ],
    "wof:name":"Groundsmasters Landscape Svcs",
    "wof:placetype":"venue"
},
  "geometry": {"coordinates":[-97.87091100000001,30.329497],"type":"Point"}
}