{
  "type": "Feature",
  "properties": {
    "iso:country":"US",
    "sg:address":"123 Main St",
    "sg:city":"Lone Star",
    "sg:classifiers":[
        {
            "category":"Health Services",
            "subcategory":"Doctor",
            "type":"Services"
        }
    ],
    "sg:phone":"+1 903 656 8613",
    "sg:postcode":"75668",
    "sg:province":"TX",
    "sg:tags":[
        "clinic"
    ],
    "wof:name":"Longview Regional Medical Ctr",
    "wof:placetype":"venue"
},
  "geometry": {"coordinates":[-94.71154300000001,32.940302],"type":"Point"}
}