{
  "type": "Feature",
  "properties": {
    "iso:country":"US",
    "sg:address":"2302 N Chadbourne St",
    "sg:city":"San Angelo",
    "sg:classifiers":[
        {
            "category":"Insurance",
            "subcategory":"Insurance Agent",
            "type":"Services"
        }
    ],
    "sg:phone":"+1 325 224 0007",
    "sg:postcode":"76903",
    "sg:province":"TX",
    "wof:name":"Trevino Insurance",
    "wof:placetype":"venue"
},
  "geometry": {"coordinates":[-100.450962,31.484264],"type":"Point"}
}