{
  "type": "Feature",
  "properties": {
    "iso:country":"US",
    "sg:address":"8850 FM 1405",
    "sg:city":"Baytown",
    "sg:classifiers":[
        {
            "category":"Home & Garden",
            "subcategory":"Building Materials",
            "type":"Retail Goods"
        }
    ],
    "sg:phone":"+1 281 383 1799",
    "sg:postcode":"77520",
    "sg:province":"TX",
    "sg:tags":[
        "mixed",
        "concrete"
    ],
    "wof:name":"Dorsette Brothers Concrete",
    "wof:placetype":"venue"
},
  "geometry": {"coordinates":[-94.91371700000001,29.690241],"type":"Point"}
}