{
  "type": "Feature",
  "properties": {
    "iso:country":"US",
    "sg:address":"8210 Garden North Dr",
    "sg:city":"San Antonio",
    "sg:classifiers":[
        {
            "category":"Professional",
            "subcategory":"Business Services",
            "type":"Services"
        }
    ],
    "sg:phone":"+1 210 710 3211",
    "sg:postcode":"78266",
    "sg:province":"TX",
    "sg:tags":[
        "interior",
        "design"
    ],
    "wof:name":"Interior Angles",
    "wof:placetype":"venue"
},
  "geometry": {"coordinates":[-98.32541399999999,29.645534],"type":"Point"}
}