{
  "type": "Feature",
  "properties": {
    "iso:country":"US",
    "sg:address":"1200 Castle Hill St",
    "sg:city":"Austin",
    "sg:classifiers":[
        {
            "category":"Professional",
            "subcategory":"Business Services",
            "type":"Services"
        }
    ],
    "sg:phone":"+1 512 474 4624",
    "sg:postcode":"78703",
    "sg:province":"TX",
    "wof:name":"Castle Hill Owners Assoc",
    "wof:placetype":"venue"
},
  "geometry": {"coordinates":[-97.752477,30.279455],"type":"Point"}
}