{
  "type": "Feature",
  "properties": {
    "iso:country":"US",
    "sg:address":"2137 N Hobart St",
    "sg:city":"Pampa",
    "sg:classifiers":[
        {
            "category":"Personal",
            "type":"Services"
        }
    ],
    "sg:phone":"+1 806 669 6836",
    "sg:postcode":"79065",
    "sg:province":"TX",
    "wof:name":"Chez Tanz",
    "wof:placetype":"venue"
},
  "geometry": {"coordinates":[-100.97201200000001,35.559849],"type":"Point"}
}