{
  "type": "Feature",
  "properties": {
    "iso:country":"US",
    "sg:address":"4647 Pine Timbers St",
    "sg:city":"Houston",
    "sg:classifiers":[
        {
            "category":"Retail",
            "subcategory":"Veterinary Services",
            "type":"Services"
        }
    ],
    "sg:phone":"+1 713 688 6667",
    "sg:postcode":"77041",
    "sg:province":"TX",
    "sg:tags":[
        "veterinarian"
    ],
    "wof:name":"Harris County Veterinary Med",
    "wof:placetype":"venue"
},
  "geometry": {"coordinates":[-95.514325,29.839112],"type":"Point"}
}