{
  "type": "Feature",
  "properties": {
    "iso:country":"US",
    "sg:address":"407 del Rio Ct",
    "sg:city":"Allen",
    "sg:classifiers":[
        {
            "category":"Place Of Worship",
            "type":"Public Place"
        }
    ],
    "sg:phone":"+1 972 727 7993",
    "sg:postcode":"75013",
    "sg:province":"TX",
    "sg:tags":[
        "church"
    ],
    "wof:name":"Green Church Association",
    "wof:placetype":"venue"
},
  "geometry": {"coordinates":[-96.70771999999999,33.10424],"type":"Point"}
}