{
  "type": "Feature",
  "properties": {
    "iso:country":"US",
    "sg:address":"123 E Post Office St",
    "sg:city":"Weimar",
    "sg:classifiers":[
        {
            "category":"Shopping",
            "subcategory":"Florist",
            "type":"Retail Goods"
        }
    ],
    "sg:phone":"+1 979 725 6534",
    "sg:postcode":"78962",
    "sg:province":"TX",
    "sg:tags":[
        "merchandise"
    ],
    "wof:name":"Flowers By Judy",
    "wof:placetype":"venue"
},
  "geometry": {"coordinates":[-96.779439,29.703677],"type":"Point"}
}