{
  "type": "Feature",
  "properties": {
    "iso:country":"US",
    "sg:address":"1225 N 23rd St",
    "sg:city":"Mcallen",
    "sg:classifiers":[
        {
            "category":"Food & Beverages",
            "subcategory":"Groceries & Convenience Stores",
            "type":"Retail Goods"
        }
    ],
    "sg:phone":"+1 956 682 8222",
    "sg:postcode":"78501",
    "sg:province":"TX",
    "wof:name":"Circle K",
    "wof:placetype":"venue"
},
  "geometry": {"coordinates":[-98.24364199999999,26.216404],"type":"Point"}
}