{
  "type": "Feature",
  "properties": {
    "iso:country":"US",
    "sg:address":"1224 N Hwy 377",
    "sg:city":"Roanoke",
    "sg:classifiers":[
        {
            "category":"Shopping",
            "subcategory":"Computers & Home Electronics",
            "type":"Retail Goods"
        }
    ],
    "sg:phone":"+1 682 831 1562",
    "sg:postcode":"76258",
    "sg:province":"TX",
    "sg:tags":[
        "game",
        "video"
    ],
    "sg:website":"www.gamestop.com",
    "wof:name":"Gamestop",
    "wof:placetype":"venue"
},
  "geometry": {"coordinates":[-96.92801,33.437899],"type":"Point"}
}