{
  "type": "Feature",
  "properties": {
    "iso:country":"US",
    "sg:address":"145 Oyster Creek Dr",
    "sg:city":"Lake Jackson",
    "sg:classifiers":[
        {
            "category":"Education",
            "subcategory":"Special Training",
            "type":"Public Place"
        }
    ],
    "sg:phone":"+1 979 480 9200",
    "sg:postcode":"77566",
    "sg:province":"TX",
    "sg:tags":[
        "tutoring"
    ],
    "wof:name":"Kumon Math & Reading Ctr",
    "wof:placetype":"venue"
},
  "geometry": {"coordinates":[-95.450909,29.045613],"type":"Point"}
}