{
  "type": "Feature",
  "properties": {
    "iso:country":"US",
    "sg:address":"2410 24th St N",
    "sg:city":"Texas City",
    "sg:classifiers":[
        {
            "category":"Real Estate",
            "subcategory":"Real Estate Operator",
            "type":"Services"
        }
    ],
    "sg:phone":"+1 409 945 8205",
    "sg:postcode":"77590",
    "sg:province":"TX",
    "wof:name":"Lakewood Apts",
    "wof:placetype":"venue"
},
  "geometry": {"coordinates":[-94.929063,29.407808],"type":"Point"}
}