{
  "type": "Feature",
  "properties": {
    "iso:country":"US",
    "sg:address":"3302 Nederland Ave",
    "sg:city":"Nederland",
    "sg:classifiers":[
        {
            "category":"Retail",
            "subcategory":"Repair Shop",
            "type":"Services"
        },
        {
            "category":"Home & Garden",
            "subcategory":"Furniture",
            "type":"Retail Goods"
        }
    ],
    "sg:phone":"+1 409 727 1107",
    "sg:postcode":"77627",
    "sg:province":"TX",
    "sg:tags":[
        "watch",
        "jewelry"
    ],
    "wof:name":"Marjorie's Jewelry",
    "wof:placetype":"venue"
},
  "geometry": {"coordinates":[-94.003939,29.959088],"type":"Point"}
}