{
  "type": "Feature",
  "properties": {
    "iso:country":"US",
    "sg:address":"2041 W Gray St",
    "sg:city":"Houston",
    "sg:classifiers":[
        {
            "category":"Shopping",
            "subcategory":"Clothing, Apparel, & Fashions",
            "type":"Retail Goods"
        }
    ],
    "sg:phone":"+1 713 522 0031",
    "sg:postcode":"77019",
    "sg:province":"TX",
    "sg:tags":[
        "ready"
    ],
    "wof:name":"Dance Centre",
    "wof:placetype":"venue"
},
  "geometry": {"coordinates":[-95.408626,29.752979],"type":"Point"}
}