{
  "type": "Feature",
  "properties": {
    "iso:country":"US",
    "sg:address":"1024 W Church St",
    "sg:city":"Livingston",
    "sg:classifiers":[
        {
            "category":"Professional",
            "type":"Services"
        }
    ],
    "sg:phone":"+1 936 327 1217",
    "sg:postcode":"77351",
    "sg:province":"TX",
    "wof:name":"Equipment Services Corp",
    "wof:placetype":"venue"
},
  "geometry": {"coordinates":[-94.94384700000001,30.710955],"type":"Point"}
}