{
  "type": "Feature",
  "properties": {
    "iso:country":"US",
    "sg:address":"10307 Sandra Lynn Dr",
    "sg:city":"Dallas",
    "sg:classifiers":[
        {
            "category":"Organizations",
            "subcategory":"Non-profit Organization",
            "type":"Services"
        }
    ],
    "sg:phone":"+1 972 279 1544",
    "sg:postcode":"75228",
    "sg:province":"TX",
    "wof:name":"Dallas Chapter Tx Federation",
    "wof:placetype":"venue"
},
  "geometry": {"coordinates":[-96.65653500000001,32.838028],"type":"Point"}
}