{
  "type": "Feature",
  "properties": {
    "iso:country":"US",
    "sg:address":"4109 San Bernardo Ave",
    "sg:city":"Laredo",
    "sg:classifiers":[
        {
            "category":"Travel",
            "subcategory":"Hotels & Motels",
            "type":"Entertainment"
        }
    ],
    "sg:phone":"+1 956 723 3661",
    "sg:postcode":"78041",
    "sg:province":"TX",
    "wof:name":"Siesta Motel",
    "wof:placetype":"venue"
},
  "geometry": {"coordinates":[-99.504358,27.536505],"type":"Point"}
}