{
  "type": "Feature",
  "properties": {
    "iso:country":"US",
    "sg:address":"8801 Clifford St",
    "sg:city":"Fort Worth",
    "sg:classifiers":[
        {
            "category":"Food & Beverages",
            "subcategory":"Groceries & Convenience Stores",
            "type":"Retail Goods"
        }
    ],
    "sg:phone":"+1 817 246 7515",
    "sg:postcode":"76108",
    "sg:province":"TX",
    "sg:tags":[
        "grocer"
    ],
    "wof:name":"Quik Sak Stores Inc",
    "wof:placetype":"venue"
},
  "geometry": {"coordinates":[-97.471508,32.76614],"type":"Point"}
}