{
  "type": "Feature",
  "properties": {
    "iso:country":"US",
    "sg:address":"300 Mill Creek Dr",
    "sg:city":"Longview",
    "sg:classifiers":[
        {
            "category":"Organizations",
            "subcategory":"Community Association",
            "type":"Services"
        }
    ],
    "sg:phone":"+1 903 759 5322",
    "sg:postcode":"75604",
    "sg:province":"TX",
    "wof:name":"Dramatic Order Knights of",
    "wof:placetype":"venue"
},
  "geometry": {"coordinates":[-94.804709,32.540419],"type":"Point"}
}