{
  "type": "Feature",
  "properties": {
    "iso:country":"US",
    "sg:address":"5501 S 1st St",
    "sg:city":"Abilene",
    "sg:classifiers":[
        {
            "category":"Wholesale",
            "subcategory":"Motor Vehicles",
            "type":"Manufacturing & Wholesale Goods"
        }
    ],
    "sg:phone":"+1 325 695 9990",
    "sg:postcode":"79605",
    "sg:province":"TX",
    "wof:name":"Jim Tatum Motors",
    "wof:placetype":"venue"
},
  "geometry": {"coordinates":[-99.799646,32.453035],"type":"Point"}
}