{
  "type": "Feature",
  "properties": {
    "iso:country":"US",
    "sg:address":"202 Tropical Dr",
    "sg:city":"Victoria",
    "sg:classifiers":[
        {
            "category":"Professional",
            "subcategory":"Management & Consulting",
            "type":"Services"
        }
    ],
    "sg:phone":"+1 361 575 8245",
    "sg:postcode":"77904",
    "sg:province":"TX",
    "wof:name":"Grandys",
    "wof:placetype":"venue"
},
  "geometry": {"coordinates":[-97.02563000000001,28.867411],"type":"Point"}
}