{
  "type": "Feature",
  "properties": {
    "iso:country":"US",
    "sg:address":"11413 FM 1464",
    "sg:city":"Richmond",
    "sg:classifiers":[
        {
            "category":"Freight",
            "type":"Transportation"
        }
    ],
    "sg:phone":"+1 281 277 1888",
    "sg:postcode":"77469",
    "sg:province":"TX",
    "sg:tags":[
        "special"
    ],
    "wof:name":"Clodine Self Storage",
    "wof:placetype":"venue"
},
  "geometry": {"coordinates":[-95.679019,29.649016],"type":"Point"}
}