{
  "type": "Feature",
  "properties": {
    "iso:country":"US",
    "sg:address":"2414 Gessner Dr",
    "sg:city":"Houston",
    "sg:classifiers":[
        {
            "category":"Shopping",
            "subcategory":"Mobile Phones",
            "type":"Retail Goods"
        }
    ],
    "sg:phone":"+1 713 461 4447",
    "sg:postcode":"77080",
    "sg:province":"TX",
    "wof:name":"Beauty Supply & Wireless",
    "wof:placetype":"venue"
},
  "geometry": {"coordinates":[-95.54494099999999,29.815188],"type":"Point"}
}