{
  "type": "Feature",
  "properties": {
    "iso:country":"US",
    "sg:address":"16800 Greenspoint Park Dr Ste 145S",
    "sg:city":"Houston",
    "sg:classifiers":[
        {
            "category":"Real Estate",
            "subcategory":"Real Estate Services",
            "type":"Services"
        }
    ],
    "sg:phone":"+1 281 872 5144",
    "sg:postcode":"77060",
    "sg:province":"TX",
    "sg:tags":[
        "management",
        "property"
    ],
    "wof:name":"R M Crow Management Company Inc",
    "wof:placetype":"venue"
},
  "geometry": {"coordinates":[-95.39720199999999,29.9389],"type":"Point"}
}