{
  "type": "Feature",
  "properties": {
    "iso:country":"US",
    "sg:address":"302 E Cano St",
    "sg:city":"Edinburg",
    "sg:classifiers":[
        {
            "category":"Shopping",
            "subcategory":"Discount & Variety Stores",
            "type":"Retail Goods"
        }
    ],
    "sg:phone":"+1 956 318 1787",
    "sg:postcode":"78539",
    "sg:province":"TX",
    "sg:tags":[
        "merchandise",
        "general"
    ],
    "wof:name":"Dollar General",
    "wof:placetype":"venue"
},
  "geometry": {"coordinates":[-98.15925,26.299818],"type":"Point"}
}