{
  "type": "Feature",
  "properties": {
    "iso:country":"US",
    "sg:address":"2747 Airport Fwy",
    "sg:city":"Fort Worth",
    "sg:classifiers":[
        {
            "category":"Professional",
            "subcategory":"Computer Services",
            "type":"Services"
        }
    ],
    "sg:phone":"+1 817 870 4726",
    "sg:postcode":"76111",
    "sg:province":"TX",
    "sg:tags":[
        "programing",
        "custom"
    ],
    "wof:name":"Future Innovations",
    "wof:placetype":"venue"
},
  "geometry": {"coordinates":[-97.307721,32.767935],"type":"Point"}
}