{
  "type": "Feature",
  "properties": {
    "iso:country":"US",
    "sg:address":"1045 E Hwy 121",
    "sg:city":"Lewisville",
    "sg:classifiers":[
        {
            "category":"Building & Trades",
            "subcategory":"Construction",
            "type":"Services"
        }
    ],
    "sg:phone":"+1 972 221 7535",
    "sg:postcode":"75057",
    "sg:province":"TX",
    "sg:tags":[
        "paving"
    ],
    "wof:name":"Abcon Paving Inc",
    "wof:placetype":"venue"
},
  "geometry": {"coordinates":[-96.9653,33.04549],"type":"Point"}
}