{
  "type": "Feature",
  "properties": {
    "iso:country":"US",
    "sg:address":"4700 W Fuqua St",
    "sg:city":"Houston",
    "sg:classifiers":[
        {
            "category":"Travel",
            "subcategory":"Hotels & Motels",
            "type":"Entertainment"
        }
    ],
    "sg:phone":"+1 713 434 0905",
    "sg:postcode":"77045",
    "sg:province":"TX",
    "wof:name":"Maxim III Motel",
    "wof:placetype":"venue"
},
  "geometry": {"coordinates":[-95.448944,29.613375],"type":"Point"}
}