{
  "type": "Feature",
  "properties": {
    "iso:country":"US",
    "sg:address":"3800 S Tyler St Ofc",
    "sg:city":"Dallas",
    "sg:classifiers":[
        {
            "category":"Real Estate",
            "subcategory":"Real Estate Operator",
            "type":"Services"
        }
    ],
    "sg:phone":"+1 214 371 8009",
    "sg:postcode":"75224",
    "sg:province":"TX",
    "sg:tags":[
        "apartment"
    ],
    "wof:name":"Carousel Court Apartments",
    "wof:placetype":"venue"
},
  "geometry": {"coordinates":[-96.83719600000001,32.697498],"type":"Point"}
}