{
  "type": "Feature",
  "properties": {
    "iso:country":"US",
    "sg:address":"1500 Harvey Rd",
    "sg:city":"College Station",
    "sg:classifiers":[
        {
            "category":"Shopping",
            "type":"Retail Goods"
        },
        {
            "category":"Shopping",
            "subcategory":"Computers & Home Electronics",
            "type":"Retail Goods"
        }
    ],
    "sg:phone":"+1 979 764 0050",
    "sg:postcode":"77840",
    "sg:province":"TX",
    "sg:tags":[
        "telephone",
        "cellular"
    ],
    "wof:name":"Radio Shack",
    "wof:placetype":"venue"
},
  "geometry": {"coordinates":[-96.304085,30.627919],"type":"Point"}
}