{
  "type": "Feature",
  "properties": {
    "iso:country":"US",
    "sg:address":"242 Lavon Dr",
    "sg:city":"Garland",
    "sg:classifiers":[
        {
            "category":"Autos & Motor Vehicles",
            "subcategory":"Auto Supplies",
            "type":"Retail Goods"
        },
        {
            "category":"Retail",
            "subcategory":"Auto Repair",
            "type":"Services"
        }
    ],
    "sg:phone":"+1 972 276 4415",
    "sg:postcode":"75040",
    "sg:province":"TX",
    "sg:tags":[
        "automobile",
        "part",
        "accessory"
    ],
    "wof:name":"R & I Automotive",
    "wof:placetype":"venue"
},
  "geometry": {"coordinates":[-96.628304,32.913601],"type":"Point"}
}