{
  "type": "Feature",
  "properties": {
    "iso:country":"US",
    "sg:address":"1122 O'Hara Dr",
    "sg:city":"San Antonio",
    "sg:classifiers":[
        {
            "category":"Building & Trades",
            "subcategory":"Cleaning & Sanitation",
            "type":"Services"
        }
    ],
    "sg:phone":"+1 210 647 3655",
    "sg:postcode":"78251",
    "sg:province":"TX",
    "sg:tags":[
        "janitorial"
    ],
    "wof:name":"Shine Cleaning Concept",
    "wof:placetype":"venue"
},
  "geometry": {"coordinates":[-98.54458700000001,29.33155],"type":"Point"}
}