{
  "type": "Feature",
  "properties": {
    "iso:country":"US",
    "sg:address":"4306 Elkhorn Trl",
    "sg:city":"Dallas",
    "sg:classifiers":[
        {
            "category":"Personal",
            "subcategory":"Beauty Salon",
            "type":"Services"
        }
    ],
    "sg:phone":"+1 214 375 6426",
    "sg:postcode":"75216",
    "sg:province":"TX",
    "sg:tags":[
        "shop"
    ],
    "wof:name":"Elegante Expressions",
    "wof:placetype":"venue"
},
  "geometry": {"coordinates":[-96.81986000000001,32.692293],"type":"Point"}
}