{
  "type": "Feature",
  "properties": {
    "iso:country":"US",
    "sg:address":"434 Burges St",
    "sg:city":"Seguin",
    "sg:classifiers":[
        {
            "category":"Building & Trades",
            "subcategory":"Pest Control",
            "type":"Services"
        }
    ],
    "sg:phone":"+1 830 386 0039",
    "sg:postcode":"78155",
    "sg:province":"TX",
    "wof:name":"All-American Pest Control",
    "wof:placetype":"venue"
},
  "geometry": {"coordinates":[-97.98093799999999,29.565341],"type":"Point"}
}