{
  "type": "Feature",
  "properties": {
    "iso:country":"US",
    "sg:address":"2301 Moctezuma St",
    "sg:city":"Laredo",
    "sg:classifiers":[
        {
            "category":"Shopping",
            "subcategory":"Computers & Home Electronics",
            "type":"Retail Goods"
        }
    ],
    "sg:phone":"+1 956 724 7264",
    "sg:postcode":"78040",
    "sg:province":"TX",
    "sg:tags":[
        "consumer"
    ],
    "wof:name":"Skl International Inc",
    "wof:placetype":"venue"
},
  "geometry": {"coordinates":[-99.51918499999999,27.509853],"type":"Point"}
}