{
  "type": "Feature",
  "properties": {
    "iso:country":"US",
    "sg:address":"7201 Miley St",
    "sg:city":"Houston",
    "sg:classifiers":[
        {
            "category":"Real Estate",
            "subcategory":"Real Estate Agent",
            "type":"Services"
        }
    ],
    "sg:phone":"+1 713 491 0122",
    "sg:postcode":"77028",
    "sg:province":"TX",
    "sg:tags":[
        "finding",
        "apartment",
        "rental"
    ],
    "wof:name":"Move In Apartment Locators",
    "wof:placetype":"venue"
},
  "geometry": {"coordinates":[-95.298923,29.81704],"type":"Point"}
}