{
  "type": "Feature",
  "properties": {
    "iso:country":"US",
    "sg:address":"120 W Redd Rd",
    "sg:city":"El Paso",
    "sg:classifiers":[
        {
            "category":"Education",
            "subcategory":"Kindergarten",
            "type":"Public Place"
        }
    ],
    "sg:phone":"+1 915 760 5205",
    "sg:postcode":"79932",
    "sg:province":"TX",
    "sg:tags":[
        "school",
        "driving"
    ],
    "wof:name":"Cherokee Driving School",
    "wof:placetype":"venue"
},
  "geometry": {"coordinates":[-106.587937,31.859926],"type":"Point"}
}