{
  "type": "Feature",
  "properties": {
    "iso:country":"US",
    "sg:address":"5729 Lebanon Rd",
    "sg:city":"Frisco",
    "sg:classifiers":[
        {
            "category":"Restaurant",
            "type":"Food & Drink"
        }
    ],
    "sg:menulink":"http://www.allmenus.com/tx/mckinney/130853-subway/menu/",
    "sg:phone":"+1 972 335 0208",
    "sg:postcode":"75034",
    "sg:province":"TX",
    "sg:tags":[
        "american",
        "sandwich"
    ],
    "wof:name":"Subway",
    "wof:placetype":"venue"
},
  "geometry": {"coordinates":[-96.837692,33.115765],"type":"Point"}
}