{
  "type": "Feature",
  "properties": {
    "iso:country":"US",
    "sg:address":"1724 Blue Danube St",
    "sg:city":"Arlington",
    "sg:classifiers":[
        {
            "category":"Wholesale",
            "subcategory":"Vending Machines",
            "type":"Manufacturing & Wholesale Goods"
        }
    ],
    "sg:phone":"+1 817 557 9618",
    "sg:postcode":"76015",
    "sg:province":"TX",
    "sg:tags":[
        "operator"
    ],
    "wof:name":"Thurman Vending",
    "wof:placetype":"venue"
},
  "geometry": {"coordinates":[-97.135797,32.691338],"type":"Point"}
}