{
  "type": "Feature",
  "properties": {
    "iso:country":"US",
    "sg:address":"1204 53rd St",
    "sg:city":"Galveston",
    "sg:classifiers":[
        {
            "category":"Organizations",
            "subcategory":"Community Association",
            "type":"Services"
        }
    ],
    "sg:phone":"+1 409 744 9964",
    "sg:postcode":"77551",
    "sg:province":"TX",
    "wof:name":"American Legion Post 614",
    "wof:placetype":"venue"
},
  "geometry": {"coordinates":[-94.825529,29.288844],"type":"Point"}
}