{
  "type": "Feature",
  "properties": {
    "iso:country":"US",
    "sg:address":"2950 S Gessner Rd",
    "sg:city":"Houston",
    "sg:classifiers":[
        {
            "category":"Professional",
            "type":"Services"
        }
    ],
    "sg:phone":"+1 713 785 9121",
    "sg:postcode":"77063",
    "sg:province":"TX",
    "sg:tags":[
        "establishment"
    ],
    "wof:name":"Ndr LTD",
    "wof:placetype":"venue"
},
  "geometry": {"coordinates":[-95.53933600000001,29.732414],"type":"Point"}
}