{
  "type": "Feature",
  "properties": {
    "iso:country":"US",
    "sg:address":"5500 N Braeswood Blvd",
    "sg:city":"Houston",
    "sg:classifiers":[
        {
            "category":"Wholesale",
            "subcategory":"Machinery & Supplies",
            "type":"Manufacturing & Wholesale Goods"
        }
    ],
    "sg:phone":"+1 713 728 0200",
    "sg:postcode":"77096",
    "sg:province":"TX",
    "sg:tags":[
        "equipment",
        "establishment"
    ],
    "wof:name":"Fire Response Systems",
    "wof:placetype":"venue"
},
  "geometry": {"coordinates":[-95.482546,29.676367],"type":"Point"}
}