{
  "type": "Feature",
  "properties": {
    "iso:country":"US",
    "sg:address":"3613 Rocky Ledge Cir",
    "sg:city":"Waco",
    "sg:classifiers":[
        {
            "category":"Real Estate",
            "subcategory":"Real Estate Agent",
            "type":"Services"
        }
    ],
    "sg:phone":"+1 254 754 7711",
    "sg:postcode":"76708",
    "sg:province":"TX",
    "wof:name":"Bolfing Farm",
    "wof:placetype":"venue"
},
  "geometry": {"coordinates":[-97.186218,31.561375],"type":"Point"}
}