{
  "type": "Feature",
  "properties": {
    "iso:country":"US",
    "sg:address":"6207 S Bayou Knoll Dr",
    "sg:city":"Houston",
    "sg:classifiers":[
        {
            "category":"Professional",
            "subcategory":"Business Services",
            "type":"Services"
        }
    ],
    "sg:phone":"+1 281 568 2254",
    "sg:postcode":"77072",
    "sg:province":"TX",
    "wof:name":"Tropical Integrated Technology",
    "wof:placetype":"venue"
},
  "geometry": {"coordinates":[-95.61411699999999,29.710695],"type":"Point"}
}