{
  "type": "Feature",
  "properties": {
    "iso:country":"US",
    "sg:address":"109 N 5th St",
    "sg:city":"Wills Point",
    "sg:classifiers":[
        {
            "category":"Manufacturing",
            "subcategory":"Printing",
            "type":"Manufacturing & Wholesale Goods"
        }
    ],
    "sg:phone":"+1 903 873 2525",
    "sg:postcode":"75169",
    "sg:province":"TX",
    "sg:tags":[
        "newspaper"
    ],
    "sg:website":"www.vanzandtnews.com",
    "wof:name":"East Texas Homes & Farms",
    "wof:placetype":"venue"
},
  "geometry": {"coordinates":[-96.009333,32.708221],"type":"Point"}
}