{
  "type": "Feature",
  "properties": {
    "iso:country":"US",
    "sg:address":"1305 NW 9th Ave",
    "sg:city":"Amarillo",
    "sg:classifiers":[
        {
            "category":"Organizations",
            "subcategory":"Religious Organization",
            "type":"Services"
        }
    ],
    "sg:phone":"+1 806 376 4954",
    "sg:postcode":"79107",
    "sg:province":"TX",
    "wof:name":"New Hope Baptist Church",
    "wof:placetype":"venue"
},
  "geometry": {"coordinates":[-101.85082199999999,35.222939],"type":"Point"}
}