{
  "type": "Feature",
  "properties": {
    "iso:country":"US",
    "sg:address":"1468 E Hwy 377",
    "sg:city":"Granbury",
    "sg:classifiers":[
        {
            "category":"Restaurant",
            "type":"Food & Drink"
        }
    ],
    "sg:phone":"+1 817 279 0382",
    "sg:postcode":"76048",
    "sg:province":"TX",
    "sg:tags":[
        "eating"
    ],
    "wof:name":"MI Famlia Mexican Rest Cantina",
    "wof:placetype":"venue"
},
  "geometry": {"coordinates":[-97.764726,32.438117],"type":"Point"}
}