{
  "type": "Feature",
  "properties": {
    "iso:country":"US",
    "sg:address":"1090 Lang Rd",
    "sg:city":"Portland",
    "sg:classifiers":[
        {
            "category":"Real Estate",
            "subcategory":"Real Estate Operator",
            "type":"Services"
        }
    ],
    "sg:phone":"+1 361 643 4040",
    "sg:postcode":"78374",
    "sg:province":"TX",
    "sg:tags":[
        "apartment",
        "complex"
    ],
    "wof:name":"Bridge Pnte Landing Apartments",
    "wof:placetype":"venue"
},
  "geometry": {"coordinates":[-97.333889,27.894258],"type":"Point"}
}