{
  "type": "Feature",
  "properties": {
    "iso:country":"US",
    "sg:address":"6065 Montana Ave",
    "sg:city":"El Paso",
    "sg:classifiers":[
        {
            "category":"Government",
            "subcategory":"Office",
            "type":"Public Place"
        }
    ],
    "sg:phone":"+1 915 779 1617",
    "sg:postcode":"79925",
    "sg:province":"TX",
    "sg:tags":[
        "armed",
        "national",
        "force",
        "security",
        "recruiting"
    ],
    "wof:name":"United States Navy Recruiting",
    "wof:placetype":"venue"
},
  "geometry": {"coordinates":[-106.414125,31.785114],"type":"Point"}
}