{
  "type": "Feature",
  "properties": {
    "iso:country":"US",
    "sg:address":"4571 Tulsa Rd",
    "sg:city":"Houston",
    "sg:classifiers":[
        {
            "category":"Wholesale",
            "subcategory":"Construction Materials",
            "type":"Manufacturing & Wholesale Goods"
        }
    ],
    "sg:phone":"+1 713 880 9898",
    "sg:postcode":"77092",
    "sg:province":"TX",
    "sg:tags":[
        "installation",
        "tubular",
        "skylight",
        "solar"
    ],
    "wof:name":"Solatube",
    "wof:placetype":"venue"
},
  "geometry": {"coordinates":[-95.457961,29.820467],"type":"Point"}
}