{
  "type": "Feature",
  "properties": {
    "iso:country":"US",
    "sg:address":"5550 Timbercreek Dr",
    "sg:city":"Houston",
    "sg:classifiers":[
        {
            "category":"Real Estate",
            "subcategory":"Real Estate Agent",
            "type":"Services"
        }
    ],
    "sg:phone":"+1 281 481 8351",
    "sg:postcode":"77017",
    "sg:province":"TX",
    "wof:name":"Golden Lion Homes Inc",
    "wof:placetype":"venue"
},
  "geometry": {"coordinates":[-95.237139,29.675502],"type":"Point"}
}