{
  "type": "Feature",
  "properties": {
    "iso:country":"US",
    "sg:address":"15715 San Pedro Ave",
    "sg:city":"San Antonio",
    "sg:classifiers":[
        {
            "category":"Restaurant",
            "type":"Food & Drink"
        }
    ],
    "sg:menulink":"http://www.allmenus.com/tx/san-antonio/203058-mcdonalds/menu/",
    "sg:postcode":"78232",
    "sg:province":"TX",
    "sg:tags":[
        "burger",
        "american"
    ],
    "wof:name":"McDonald's",
    "wof:placetype":"venue"
},
  "geometry": {"coordinates":[-98.475966,29.585616],"type":"Point"}
}