{
  "type": "Feature",
  "properties": {
    "iso:country":"US",
    "sg:address":"937 W 12th St",
    "sg:city":"Dallas",
    "sg:classifiers":[
        {
            "category":"Building & Trades",
            "subcategory":"Cleaning & Sanitation",
            "type":"Services"
        }
    ],
    "sg:phone":"+1 214 948 2002",
    "sg:postcode":"75208",
    "sg:province":"TX",
    "sg:tags":[
        "home"
    ],
    "wof:name":"House Keeping Services",
    "wof:placetype":"venue"
},
  "geometry": {"coordinates":[-96.83826999999999,32.741427],"type":"Point"}
}