{
  "type": "Feature",
  "properties": {
    "iso:country":"US",
    "sg:address":"8702 Beverlyhill St",
    "sg:city":"Houston",
    "sg:classifiers":[
        {
            "category":"Arena",
            "subcategory":"Sports Club",
            "type":"Entertainment"
        }
    ],
    "sg:phone":"+1 713 782 3939",
    "sg:postcode":"77063",
    "sg:province":"TX",
    "sg:tags":[
        "martial art"
    ],
    "wof:name":"Van Binh Self Defense Academy",
    "wof:placetype":"venue"
},
  "geometry": {"coordinates":[-95.517303,29.73],"type":"Point"}
}