{
  "type": "Feature",
  "properties": {
    "iso:country":"US",
    "sg:address":"2077 S Gessner Rd",
    "sg:city":"Houston",
    "sg:classifiers":[
        {
            "category":"Wholesale",
            "subcategory":"Farm Supplies",
            "type":"Manufacturing & Wholesale Goods"
        }
    ],
    "sg:phone":"+1 713 783 2112",
    "sg:postcode":"77063",
    "sg:province":"TX",
    "sg:tags":[
        "leather",
        "product",
        "hide"
    ],
    "wof:name":"Himex Inc",
    "wof:placetype":"venue"
},
  "geometry": {"coordinates":[-95.538327,29.744026],"type":"Point"}
}