{
  "type": "Feature",
  "properties": {
    "iso:country":"US",
    "sg:address":"11729 Co Rd 309",
    "sg:city":"Terrell",
    "sg:classifiers":[
        {
            "category":"Wholesale",
            "subcategory":"Groceries",
            "type":"Manufacturing & Wholesale Goods"
        }
    ],
    "sg:phone":"+1 214 212 2127",
    "sg:postcode":"75161",
    "sg:province":"TX",
    "sg:tags":[
        "general"
    ],
    "wof:name":"Webster Service",
    "wof:placetype":"venue"
},
  "geometry": {"coordinates":[-96.201897,32.725466],"type":"Point"}
}