{
  "type": "Feature",
  "properties": {
    "iso:country":"US",
    "sg:address":"4211 Ayers St",
    "sg:city":"Corpus Christi",
    "sg:classifiers":[
        {
            "category":"Banks & Credit Unions",
            "subcategory":"Financial Services",
            "type":"Services"
        }
    ],
    "sg:phone":"+1 361 850 6800",
    "sg:postcode":"78415",
    "sg:province":"TX",
    "sg:tags":[
        "company",
        "holding"
    ],
    "wof:name":"Brazosport Corp",
    "wof:placetype":"venue"
},
  "geometry": {"coordinates":[-97.41824099999999,27.750393],"type":"Point"}
}