{
  "type": "Feature",
  "properties": {
    "iso:country":"US",
    "sg:address":"2706 Valleywood Dr",
    "sg:city":"Grapevine",
    "sg:classifiers":[
        {
            "category":"Banks & Credit Unions",
            "subcategory":"Bank",
            "type":"Services"
        }
    ],
    "sg:phone":"+1 817 228 2996",
    "sg:postcode":"76051",
    "sg:province":"TX",
    "sg:tags":[
        "broker",
        "mortgage"
    ],
    "wof:name":"Trinity Mortgage Services",
    "wof:placetype":"venue"
},
  "geometry": {"coordinates":[-97.10858,32.891257],"type":"Point"}
}