{
  "type": "Feature",
  "properties": {
    "iso:country":"US",
    "sg:address":"601 E Jackson St",
    "sg:city":"El Campo",
    "sg:classifiers":[
        {
            "category":"Banks & Credit Unions",
            "subcategory":"Investment Brokerage",
            "type":"Services"
        }
    ],
    "sg:phone":"+1 979 543 2974",
    "sg:postcode":"77437",
    "sg:province":"TX",
    "sg:tags":[
        "land",
        "oil",
        "lease"
    ],
    "wof:name":"B J Popp Oil & Gas Lease Brkr",
    "wof:placetype":"venue"
},
  "geometry": {"coordinates":[-96.263784,29.200523],"type":"Point"}
}