{
  "type": "Feature",
  "properties": {
    "iso:country":"US",
    "sg:address":"1210 E 28th St",
    "sg:city":"San Angelo",
    "sg:classifiers":[
        {
            "category":"Farming",
            "subcategory":"Livestock Farm",
            "type":"Manufacturing & Wholesale Goods"
        }
    ],
    "sg:phone":"+1 325 653 4806",
    "sg:postcode":"76903",
    "sg:province":"TX",
    "sg:tags":[
        "printing",
        "commercial"
    ],
    "wof:name":"L Flying",
    "wof:placetype":"venue"
},
  "geometry": {"coordinates":[-100.420002,31.491974],"type":"Point"}
}