{
  "type": "Feature",
  "properties": {
    "iso:country":"US",
    "sg:address":"5305 E Paisano Dr",
    "sg:city":"El Paso",
    "sg:classifiers":[
        {
            "category":"Restaurant",
            "type":"Food & Drink"
        }
    ],
    "sg:menulink":"http://www.allmenus.com/tx/el-paso/202061-mcdonalds/menu/",
    "sg:postcode":"79905",
    "sg:province":"TX",
    "sg:tags":[
        "burger",
        "american"
    ],
    "wof:name":"McDonald's",
    "wof:placetype":"venue"
},
  "geometry": {"coordinates":[-106.42605,31.769975],"type":"Point"}
}