{
  "type": "Feature",
  "properties": {
    "iso:country":"US",
    "sg:address":"517 S Adams St",
    "sg:city":"Fredericksburg",
    "sg:classifiers":[
        {
            "category":"Personal",
            "subcategory":"Shoe Repair & Shine",
            "type":"Services"
        }
    ],
    "sg:phone":"+1 830 997 3911",
    "sg:postcode":"78624",
    "sg:province":"TX",
    "sg:tags":[
        "repairing",
        "parlor",
        "boot"
    ],
    "wof:name":"G & L Shoe Repair",
    "wof:placetype":"venue"
},
  "geometry": {"coordinates":[-98.87687,30.269951],"type":"Point"}
}