{
  "type": "Feature",
  "properties": {
    "iso:country":"US",
    "sg:address":"5903 Garden Hollow Ct",
    "sg:city":"Humble",
    "sg:classifiers":[
        {
            "category":"Professional",
            "subcategory":"Business Services",
            "type":"Services"
        }
    ],
    "sg:phone":"+1 281 360 1223",
    "sg:postcode":"77345",
    "sg:province":"TX",
    "wof:name":"Bdi Designs",
    "wof:placetype":"venue"
},
  "geometry": {"coordinates":[-95.153497,30.056537],"type":"Point"}
}