{
  "type": "Feature",
  "properties": {
    "iso:country":"US",
    "sg:address":"7657 Nez Perce Trce",
    "sg:city":"Manor",
    "sg:classifiers":[
        {
            "category":"Professional",
            "subcategory":"Secretarial Services",
            "type":"Services"
        }
    ],
    "sg:phone":"+1 512 276 9706",
    "sg:postcode":"78653",
    "sg:province":"TX",
    "sg:tags":[
        "reporting"
    ],
    "wof:name":"General Transcription Services",
    "wof:placetype":"venue"
},
  "geometry": {"coordinates":[-97.57069199999999,30.277949],"type":"Point"}
}