{
  "type": "Feature",
  "properties": {
    "iso:country":"US",
    "sg:address":"5425 W Oak St",
    "sg:city":"Palestine",
    "sg:classifiers":[
        {
            "category":"Mining & Drilling",
            "type":"Manufacturing & Wholesale Goods"
        }
    ],
    "sg:phone":"+1 903 322 1683",
    "sg:postcode":"75801",
    "sg:province":"TX",
    "sg:tags":[
        "field",
        "oil"
    ],
    "wof:name":"Q Services Of Texas Inc",
    "wof:placetype":"venue"
},
  "geometry": {"coordinates":[-95.70159099999999,31.716115],"type":"Point"}
}