{
  "type": "Feature",
  "properties": {
    "iso:country":"US",
    "sg:address":"2900 Bent Tree Ln",
    "sg:city":"Brenham",
    "sg:classifiers":[
        {
            "category":"Mining & Drilling",
            "type":"Manufacturing & Wholesale Goods"
        }
    ],
    "sg:phone":"+1 979 836 0047",
    "sg:postcode":"77833",
    "sg:province":"TX",
    "sg:tags":[
        "well"
    ],
    "wof:name":"Red Wolf Oil Co Inc",
    "wof:placetype":"venue"
},
  "geometry": {"coordinates":[-96.286753,30.241948],"type":"Point"}
}