{
  "type": "Feature",
  "properties": {
    "iso:country":"US",
    "sg:address":"25403 Kingsland Blvd",
    "sg:city":"Katy",
    "sg:classifiers":[
        {
            "category":"Social Services",
            "subcategory":"Child Care",
            "type":"Services"
        }
    ],
    "sg:phone":"+1 281 693 1999",
    "sg:postcode":"77494",
    "sg:province":"TX",
    "sg:tags":[
        "nursery",
        "day"
    ],
    "sg:website":"http://www.katyecec.com",
    "wof:name":"Katy's Early Childhood",
    "wof:placetype":"venue"
},
  "geometry": {"coordinates":[-95.813948,29.772974],"type":"Point"}
}