{
  "type": "Feature",
  "properties": {
    "iso:country":"US",
    "sg:address":"2726 Antero Dr",
    "sg:city":"Arlington",
    "sg:classifiers":[
        {
            "category":"Professional",
            "subcategory":"Management & Consulting",
            "type":"Services"
        }
    ],
    "sg:phone":"+1 817 860 7476",
    "sg:postcode":"76006",
    "sg:province":"TX",
    "sg:tags":[
        "resource",
        "human"
    ],
    "wof:name":"Human Resource Ally",
    "wof:placetype":"venue"
},
  "geometry": {"coordinates":[-97.10390700000001,32.784746],"type":"Point"}
}