{
  "type": "Feature",
  "properties": {
    "iso:country":"US",
    "sg:address":"17222 Red Oak Dr",
    "sg:city":"Houston",
    "sg:classifiers":[
        {
            "category":"Health Services",
            "subcategory":"Medical Lab",
            "type":"Services"
        }
    ],
    "sg:phone":"+1 281 893 1598",
    "sg:postcode":"77090",
    "sg:province":"TX",
    "sg:tags":[
        "laboratory"
    ],
    "wof:name":"Ceramic Smiles",
    "wof:placetype":"venue"
},
  "geometry": {"coordinates":[-95.44717,30.021924],"type":"Point"}
}