{
  "type": "Feature",
  "properties": {
    "iso:country":"US",
    "sg:address":"809 E Navarro St",
    "sg:city":"De Leon",
    "sg:classifiers":[
        {
            "category":"Health Services",
            "subcategory":"Nursing And Care Facility",
            "type":"Services"
        }
    ],
    "sg:phone":"+1 254 893 2075",
    "sg:postcode":"76444",
    "sg:province":"TX",
    "sg:tags":[
        "home",
        "convalescent"
    ],
    "wof:name":"Canterbury Villa Of De Leon",
    "wof:placetype":"venue"
},
  "geometry": {"coordinates":[-98.524596,32.115248],"type":"Point"}
}