{
  "type": "Feature",
  "properties": {
    "iso:country":"US",
    "sg:address":"701 S Capital of Texas Hwy",
    "sg:city":"Austin",
    "sg:classifiers":[
        {
            "category":"Shopping",
            "subcategory":"Stationery & Office Supplies",
            "type":"Retail Goods"
        }
    ],
    "sg:phone":"+1 512 327 4387",
    "sg:postcode":"78746",
    "sg:province":"TX",
    "sg:website":"www.officedepot.com",
    "wof:name":"Office Depot",
    "wof:placetype":"venue"
},
  "geometry": {"coordinates":[-97.828104,30.292519],"type":"Point"}
}