{
  "type": "Feature",
  "properties": {
    "iso:country":"US",
    "sg:address":"4901 W Eldorado Pkwy",
    "sg:city":"Mckinney",
    "sg:classifiers":[
        {
            "category":"Manufacturing",
            "subcategory":"Rubber & Plastics",
            "type":"Manufacturing & Wholesale Goods"
        },
        {
            "category":"Autos & Motor Vehicles",
            "subcategory":"Auto Supplies",
            "type":"Retail Goods"
        },
        {
            "category":"Retail",
            "subcategory":"Auto Repair",
            "type":"Services"
        }
    ],
    "sg:phone":"+1 214 504 0731",
    "sg:postcode":"75070",
    "sg:province":"TX",
    "sg:tags":[
        "wheel",
        "tires-wholesale",
        "tire",
        "retread",
        "balancing",
        "wheels-aligning",
        "recap",
        "brake",
        "manufacturer"
    ],
    "sg:website":"http://www.ntb.com",
    "wof:name":"NTB - National Tire & Battery",
    "wof:placetype":"venue"
},
  "geometry": {"coordinates":[-96.682508,33.17376],"type":"Point"}
}