{
  "type": "Feature",
  "properties": {
    "iso:country":"US",
    "sg:address":"1800 West Loop S",
    "sg:city":"Houston",
    "sg:classifiers":[
        {
            "category":"Professional",
            "subcategory":"Lawyer & Legal Services",
            "type":"Services"
        }
    ],
    "sg:phone":"+1 713 550 5710",
    "sg:postcode":"77027",
    "sg:province":"TX",
    "wof:name":"Shaper Sue Z PC",
    "wof:placetype":"venue"
},
  "geometry": {"coordinates":[-95.456596,29.748699],"type":"Point"}
}