{
  "type": "Feature",
  "properties": {
    "iso:country":"US",
    "sg:address":"3535 E 14th St",
    "sg:city":"Brownsville",
    "sg:classifiers":[
        {
            "category":"Manufacturing",
            "subcategory":"Tools & Machinery",
            "type":"Manufacturing & Wholesale Goods"
        }
    ],
    "sg:phone":"+1 956 541 7908",
    "sg:postcode":"78521",
    "sg:province":"TX",
    "sg:tags":[
        "resale",
        "industrial",
        "spare",
        "parts"
    ],
    "wof:name":"Refaccnes Indstrales De Mexico",
    "wof:placetype":"venue"
},
  "geometry": {"coordinates":[-97.47283299999999,25.916835],"type":"Point"}
}