{
  "type": "Feature",
  "properties": {
    "iso:country":"US",
    "sg:address":"711 S Main St",
    "sg:city":"Boerne",
    "sg:classifiers":[
        {
            "category":"Personal",
            "subcategory":"Beauty Salon",
            "type":"Services"
        }
    ],
    "sg:phone":"+1 830 249 2112",
    "sg:postcode":"78006",
    "sg:province":"TX",
    "sg:tags":[
        "shop"
    ],
    "wof:name":"George & Company Hair",
    "wof:placetype":"venue"
},
  "geometry": {"coordinates":[-98.728972,29.787239],"type":"Point"}
}