{
  "type": "Feature",
  "properties": {
    "iso:country":"US",
    "sg:address":"117 E Frank Ave",
    "sg:city":"Lufkin",
    "sg:classifiers":[
        {
            "category":"Retail",
            "subcategory":"Repair Shop",
            "type":"Services"
        }
    ],
    "sg:phone":"+1 936 639 2213",
    "sg:postcode":"75901",
    "sg:province":"TX",
    "sg:tags":[
        "appliance"
    ],
    "wof:name":"Appliance Doctor",
    "wof:placetype":"venue"
},
  "geometry": {"coordinates":[-94.728245,31.340091],"type":"Point"}
}