{
  "type": "Feature",
  "properties": {
    "iso:country":"US",
    "sg:address":"7707 Callbram Ln",
    "sg:city":"Austin",
    "sg:classifiers":[
        {
            "category":"Sports & Exercise",
            "subcategory":"Gym",
            "type":"Entertainment"
        }
    ],
    "sg:phone":"+1 512 301 3375",
    "sg:postcode":"78736",
    "sg:province":"TX",
    "sg:tags":[
        "fitness",
        "physical",
        "facility"
    ],
    "wof:name":"Xtreme Training",
    "wof:placetype":"venue"
},
  "geometry": {"coordinates":[-97.894323,30.234256],"type":"Point"}
}