{
  "type": "Feature",
  "properties": {
    "iso:country":"US",
    "sg:address":"7646 Drouet St",
    "sg:city":"Houston",
    "sg:classifiers":[
        {
            "category":"Freight",
            "type":"Transportation"
        }
    ],
    "sg:phone":"+1 713 644 4198",
    "sg:postcode":"77061",
    "sg:province":"TX",
    "sg:tags":[
        "operator",
        "local",
        "trucking"
    ],
    "wof:name":"Ibarra Trucking",
    "wof:placetype":"venue"
},
  "geometry": {"coordinates":[-95.285292,29.667565],"type":"Point"}
}