{
  "type": "Feature",
  "properties": {
    "iso:country":"US",
    "sg:address":"165 Johnson Ln",
    "sg:city":"Red Oak",
    "sg:classifiers":[
        {
            "category":"Bars & Pubs",
            "type":"Food & Drink"
        }
    ],
    "sg:phone":"+1 972 217 1119",
    "sg:postcode":"75154",
    "sg:province":"TX",
    "sg:tags":[
        "drinking"
    ],
    "wof:name":"Porkys Sports Bar & Grill",
    "wof:placetype":"venue"
},
  "geometry": {"coordinates":[-96.900485,32.546405],"type":"Point"}
}