{
  "type": "Feature",
  "properties": {
    "iso:country":"US",
    "sg:address":"21200 Creekside Dr",
    "sg:city":"Leander",
    "sg:classifiers":[
        {
            "category":"Retail",
            "subcategory":"Repair Shop",
            "type":"Services"
        }
    ],
    "sg:phone":"+1 512 267 4423",
    "sg:postcode":"78641",
    "sg:province":"TX",
    "wof:name":"Nomad Repair",
    "wof:placetype":"venue"
},
  "geometry": {"coordinates":[-97.955821,30.516319],"type":"Point"}
}