{
  "type": "Feature",
  "properties": {
    "iso:country":"US",
    "sg:address":"6007 Cary Dr",
    "sg:city":"Austin",
    "sg:classifiers":[
        {
            "category":"Real Estate",
            "subcategory":"Real Estate Agent",
            "type":"Services"
        }
    ],
    "sg:phone":"+1 512 453 1705",
    "sg:postcode":"78757",
    "sg:province":"TX",
    "sg:tags":[
        "inspection"
    ],
    "wof:name":"Bill Allen's Inspection Svc",
    "wof:placetype":"venue"
},
  "geometry": {"coordinates":[-97.74711600000001,30.336078],"type":"Point"}
}