{
  "type": "Feature",
  "properties": {
    "iso:country":"US",
    "sg:address":"3151 S Cooper St Ste 121",
    "sg:city":"Arlington",
    "sg:classifiers":[
        {
            "category":"Transit Center",
            "subcategory":"Freight",
            "type":"Transportation"
        }
    ],
    "sg:phone":"+1 817 801 0006",
    "sg:postcode":"76015",
    "sg:province":"TX",
    "sg:tags":[
        "trucking-heavy",
        "hauling"
    ],
    "wof:name":"North Star Carriers",
    "wof:placetype":"venue"
},
  "geometry": {"coordinates":[-97.126924,32.693789],"type":"Point"}
}