{
  "type": "Feature",
  "properties": {
    "iso:country":"US",
    "sg:address":"907 E Market St",
    "sg:city":"Rockport",
    "sg:classifiers":[
        {
            "category":"Professional",
            "type":"Services"
        }
    ],
    "sg:phone":"+1 361 729 9898",
    "sg:postcode":"78382",
    "sg:province":"TX",
    "sg:tags":[
        "establishment"
    ],
    "wof:name":"B & E Enterprises",
    "wof:placetype":"venue"
},
  "geometry": {"coordinates":[-97.05369899999999,28.020176],"type":"Point"}
}