{
  "type": "Feature",
  "properties": {
    "iso:country":"US",
    "sg:address":"7720 Jones Maltsberger Rd",
    "sg:city":"San Antonio",
    "sg:classifiers":[
        {
            "category":"Shopping",
            "subcategory":"Jewelry",
            "type":"Retail Goods"
        }
    ],
    "sg:phone":"+1 210 341 5495",
    "sg:postcode":"78216",
    "sg:province":"TX",
    "wof:name":"Karen Harley & Friends",
    "wof:placetype":"venue"
},
  "geometry": {"coordinates":[-98.48170399999999,29.504244],"type":"Point"}
}