{
  "type": "Feature",
  "properties": {
    "iso:country":"US",
    "sg:address":"101 Mesquite St",
    "sg:city":"Elm Mott",
    "sg:classifiers":[
        {
            "category":"Education",
            "subcategory":"School",
            "type":"Public Place"
        }
    ],
    "sg:phone":"+1 254 829 0022",
    "sg:postcode":"76640",
    "sg:province":"TX",
    "sg:website":"www.connally.org",
    "wof:name":"Elm MOTT Pre-Kindergarten Ctr",
    "wof:placetype":"venue"
},
  "geometry": {"coordinates":[-97.10016899999999,31.670074],"type":"Point"}
}