{
  "type": "Feature",
  "properties": {
    "iso:country":"US",
    "sg:address":"521 N Sam Houston Ave",
    "sg:city":"Odessa",
    "sg:classifiers":[
        {
            "category":"Professional",
            "subcategory":"Lawyer & Legal Services",
            "type":"Services"
        }
    ],
    "sg:phone":"+1 432 570 4444",
    "sg:postcode":"79761",
    "sg:province":"TX",
    "sg:tags":[
        "attorney",
        "criminal",
        "family",
        "personal",
        "divorce",
        "practice",
        "injury",
        "law"
    ],
    "wof:name":"The Guardiola Law Firm",
    "wof:placetype":"venue"
},
  "geometry": {"coordinates":[-102.372874,31.846903],"type":"Point"}
}