{
  "type": "Feature",
  "properties": {
    "iso:country":"US",
    "sg:address":"208 E Dickinson Blvd",
    "sg:city":"Fort Stockton",
    "sg:classifiers":[
        {
            "category":"Retail",
            "subcategory":"Auto Repair",
            "type":"Services"
        }
    ],
    "sg:phone":"+1 432 336 7049",
    "sg:postcode":"79735",
    "sg:province":"TX",
    "sg:tags":[
        "muffler",
        "exhaust",
        "system"
    ],
    "wof:name":"Muffler Shop",
    "wof:placetype":"venue"
},
  "geometry": {"coordinates":[-102.877922,30.892955],"type":"Point"}
}