{
  "type": "Feature",
  "properties": {
    "iso:country":"US",
    "sg:address":"1000 S Main St",
    "sg:city":"Shamrock",
    "sg:classifiers":[
        {
            "category":"Health Services",
            "subcategory":"Hospital",
            "type":"Services"
        }
    ],
    "sg:phone":"+1 806 256 2114",
    "sg:postcode":"79079",
    "sg:province":"TX",
    "wof:name":"Shamrock General Hospital",
    "wof:placetype":"venue"
},
  "geometry": {"coordinates":[-100.24918099999999,35.199804],"type":"Point"}
}