{
  "type": "Feature",
  "properties": {
    "iso:country":"US",
    "sg:address":"317 FM 620",
    "sg:city":"Austin",
    "sg:classifiers":[
        {
            "category":"Utilities",
            "subcategory":"Telephone",
            "type":"Services"
        }
    ],
    "sg:phone":"+1 512 263 7123",
    "sg:postcode":"78734",
    "sg:province":"TX",
    "sg:tags":[
        "communications"
    ],
    "wof:name":"Voip Routes LLC",
    "wof:placetype":"venue"
},
  "geometry": {"coordinates":[-97.94932,30.368615],"type":"Point"}
}