{
  "type": "Feature",
  "properties": {
    "iso:country":"US",
    "sg:address":"222 N Mound St",
    "sg:city":"Nacogdoches",
    "sg:classifiers":[
        {
            "category":"Professional",
            "type":"Services"
        },
        {
            "category":"Insurance",
            "subcategory":"Insurance Agent",
            "type":"Services"
        }
    ],
    "sg:phone":"+1 936 560 6353",
    "sg:postcode":"75961",
    "sg:province":"TX",
    "sg:tags":[
        "establishment"
    ],
    "wof:name":"American General Agent",
    "wof:placetype":"venue"
},
  "geometry": {"coordinates":[-94.65131,31.604741],"type":"Point"}
}