{
  "type": "Feature",
  "properties": {
    "iso:country":"US",
    "sg:address":"1833 Wood Dale Cir",
    "sg:city":"Cedar Hill",
    "sg:classifiers":[
        {
            "category":"Banks & Credit Unions",
            "subcategory":"Investment Brokerage",
            "type":"Services"
        }
    ],
    "sg:phone":"+1 972 293 7732",
    "sg:postcode":"75104",
    "sg:province":"TX",
    "sg:tags":[
        "advisory"
    ],
    "wof:name":"A & D Property Investments",
    "wof:placetype":"venue"
},
  "geometry": {"coordinates":[-96.981049,32.575062],"type":"Point"}
}