{
  "type": "Feature",
  "properties": {
    "iso:country":"US",
    "sg:address":"102 Beachview Way",
    "sg:city":"Bridgeport",
    "sg:classifiers":[
        {
            "category":"Professional",
            "subcategory":"Business Services",
            "type":"Services"
        }
    ],
    "sg:phone":"+1 940 575 4385",
    "sg:postcode":"76426",
    "sg:province":"TX",
    "wof:name":"Person Enterprises Inc",
    "wof:placetype":"venue"
},
  "geometry": {"coordinates":[-97.870633,33.175216],"type":"Point"}
}