{
  "type": "Feature",
  "properties": {
    "iso:country":"US",
    "sg:address":"2700 Post Oak Blvd Ste 2300",
    "sg:city":"Houston",
    "sg:classifiers":[
        {
            "category":"Communications",
            "subcategory":"Radio Station",
            "type":"Services"
        }
    ],
    "sg:phone":"+1 713 300 3551",
    "sg:postcode":"77056",
    "sg:province":"TX",
    "wof:name":"Power 97.5",
    "wof:placetype":"venue"
},
  "geometry": {"coordinates":[-95.460897,29.738911],"type":"Point"}
}