{
  "type": "Feature",
  "properties": {
    "iso:country":"US",
    "sg:address":"926 W Nolana Loop",
    "sg:city":"Pharr",
    "sg:classifiers":[
        {
            "category":"Professional",
            "subcategory":"Management & Consulting",
            "type":"Services"
        }
    ],
    "sg:phone":"+1 956 283 8700",
    "sg:postcode":"78577",
    "sg:province":"TX",
    "sg:tags":[
        "logistics"
    ],
    "wof:name":"Barbra's Logistics",
    "wof:placetype":"venue"
},
  "geometry": {"coordinates":[-98.194729,26.235616],"type":"Point"}
}