{
  "type": "Feature",
  "properties": {
    "iso:country":"US",
    "sg:address":"935 New Laredo Hwy",
    "sg:city":"San Antonio",
    "sg:classifiers":[
        {
            "category":"Organizations",
            "subcategory":"Non-profit Organization",
            "type":"Services"
        }
    ],
    "sg:phone":"+1 210 928 1251",
    "sg:postcode":"78211",
    "sg:province":"TX",
    "sg:tags":[
        "information",
        "alcoholism",
        "treatment"
    ],
    "wof:name":"Distrito #28 De Alcoholicos",
    "wof:placetype":"venue"
},
  "geometry": {"coordinates":[-98.553494,29.362565],"type":"Point"}
}