{
  "type": "Feature",
  "properties": {
    "iso:country":"US",
    "sg:address":"2925 Dowlen Rd",
    "sg:city":"Beaumont",
    "sg:classifiers":[
        {
            "category":"Banks & Credit Unions",
            "subcategory":"Bank",
            "type":"Services"
        }
    ],
    "sg:phone":"+1 409 866 8723",
    "sg:postcode":"77706",
    "sg:province":"TX",
    "wof:name":"Texas State Bank",
    "wof:placetype":"venue"
},
  "geometry": {"coordinates":[-94.168663,30.10882],"type":"Point"}
}