{
  "type": "Feature",
  "properties": {
    "iso:country":"US",
    "sg:address":"1706 Goodnight Ln",
    "sg:city":"Austin",
    "sg:classifiers":[
        {
            "category":"Travel",
            "subcategory":"Travel Agent",
            "type":"Entertainment"
        }
    ],
    "sg:phone":"+1 512 300 0011",
    "sg:postcode":"78757",
    "sg:province":"TX",
    "sg:tags":[
        "passenger",
        "transportation",
        "arrangement"
    ],
    "wof:name":"Tmg",
    "wof:placetype":"venue"
},
  "geometry": {"coordinates":[-97.73391700000001,30.337639],"type":"Point"}
}