{
  "type": "Feature",
  "properties": {
    "iso:country":"US",
    "sg:address":"3900 Ranch Rd 620 S",
    "sg:city":"Austin",
    "sg:classifiers":[
        {
            "category":"Building & Trades",
            "subcategory":"Construction",
            "type":"Services"
        }
    ],
    "sg:phone":"+1 512 402 1575",
    "sg:postcode":"78738",
    "sg:province":"TX",
    "sg:tags":[
        "home",
        "builder"
    ],
    "wof:name":"Peter Strobel & Assoc Inc",
    "wof:placetype":"venue"
},
  "geometry": {"coordinates":[-97.946562,30.311913],"type":"Point"}
}