{
  "type": "Feature",
  "properties": {
    "iso:country":"US",
    "sg:address":"601 E Whitestone Blvd",
    "sg:city":"Cedar Park",
    "sg:classifiers":[
        {
            "category":"Shopping",
            "subcategory":"Pharmacy",
            "type":"Retail Goods"
        }
    ],
    "sg:phone":"+1 512 267 3110",
    "sg:postcode":"78613",
    "sg:province":"TX",
    "wof:name":"Lago Vista Pharmacy",
    "wof:placetype":"venue"
},
  "geometry": {"coordinates":[-97.822487,30.523381],"type":"Point"}
}