{
  "type": "Feature",
  "properties": {
    "iso:country":"US",
    "sg:address":"2355 Bulverde Rd",
    "sg:city":"Bulverde",
    "sg:classifiers":[
        {
            "category":"Shopping",
            "subcategory":"Antiques",
            "type":"Retail Goods"
        }
    ],
    "sg:phone":"+1 830 438 2914",
    "sg:postcode":"78163",
    "sg:province":"TX",
    "wof:name":"DOWNTOWN BULVERDE EMPORIUM",
    "wof:placetype":"venue"
},
  "geometry": {"coordinates":[-98.454617,29.744596],"type":"Point"}
}