{
  "type": "Feature",
  "properties": {
    "iso:country":"US",
    "sg:address":"350 N Saint Paul St Ste 2650",
    "sg:city":"Dallas",
    "sg:classifiers":[
        {
            "category":"Utilities",
            "type":"Services"
        }
    ],
    "sg:phone":"+1 214 821 5865",
    "sg:postcode":"75201",
    "sg:province":"TX",
    "sg:tags":[
        "provider",
        "internet"
    ],
    "wof:name":"Tierone Converged Networks Inc",
    "wof:placetype":"venue"
},
  "geometry": {"coordinates":[-96.79746299999999,32.78394],"type":"Point"}
}