{
  "type": "Feature",
  "properties": {
    "iso:country":"US",
    "sg:address":"3808 S 1st St",
    "sg:city":"Austin",
    "sg:classifiers":[
        {
            "category":"Professional",
            "subcategory":"Lawyer & Legal Services",
            "type":"Services"
        }
    ],
    "sg:phone":"+1 512 478 1031",
    "sg:postcode":"78704",
    "sg:province":"TX",
    "wof:name":"Heisler Hughes & Associates",
    "wof:placetype":"venue"
},
  "geometry": {"coordinates":[-97.7687,30.2281],"type":"Point"}
}