{
  "type": "Feature",
  "properties": {
    "iso:country":"US",
    "sg:address":"2106 Brandywine Ln",
    "sg:city":"Austin",
    "sg:classifiers":[
        {
            "category":"Real Estate",
            "subcategory":"Real Estate Agent",
            "type":"Services"
        }
    ],
    "sg:phone":"+1 512 973 8188",
    "sg:postcode":"78727",
    "sg:province":"TX",
    "wof:name":"Ellmaker Realty LLC",
    "wof:placetype":"venue"
},
  "geometry": {"coordinates":[-97.69781399999999,30.417576],"type":"Point"}
}