{
  "type": "Feature",
  "properties": {
    "iso:country":"US",
    "sg:address":"3102 69th St",
    "sg:city":"Galveston",
    "sg:classifiers":[
        {
            "category":"Professional",
            "type":"Services"
        }
    ],
    "sg:phone":"+1 409 740 7244",
    "sg:postcode":"77551",
    "sg:province":"TX",
    "sg:tags":[
        "establishment"
    ],
    "wof:name":"Missiontx Houston South",
    "wof:placetype":"venue"
},
  "geometry": {"coordinates":[-94.83614300000001,29.266776],"type":"Point"}
}