{
  "type": "Feature",
  "properties": {
    "iso:country":"US",
    "sg:address":"400 Alton St",
    "sg:city":"Kaufman",
    "sg:classifiers":[
        {
            "category":"Government",
            "subcategory":"Office",
            "type":"Public Place"
        }
    ],
    "sg:phone":"+1 972 932 2161",
    "sg:postcode":"75142",
    "sg:province":"TX",
    "sg:tags":[
        "village"
    ],
    "wof:name":"Kaufman Landfill",
    "wof:placetype":"venue"
},
  "geometry": {"coordinates":[-96.301862,32.591865],"type":"Point"}
}