{
  "type": "Feature",
  "properties": {
    "iso:country":"US",
    "sg:address":"2680 Clayton Oaks Dr",
    "sg:city":"Dallas",
    "sg:classifiers":[
        {
            "category":"Building & Trades",
            "subcategory":"Cleaning & Sanitation",
            "type":"Services"
        }
    ],
    "sg:phone":"+1 972 288 0311",
    "sg:postcode":"75227",
    "sg:province":"TX",
    "sg:tags":[
        "maintenance"
    ],
    "wof:name":"Lion Cleaning Co",
    "wof:placetype":"venue"
},
  "geometry": {"coordinates":[-96.64738,32.758057],"type":"Point"}
}