{
  "type": "Feature",
  "properties": {
    "iso:country":"US",
    "sg:address":"2415 29th Ave N",
    "sg:city":"Texas City",
    "sg:classifiers":[
        {
            "category":"Restaurant",
            "type":"Food & Drink"
        }
    ],
    "sg:phone":"+1 409 948 1576",
    "sg:postcode":"77590",
    "sg:province":"TX",
    "sg:tags":[
        "eating"
    ],
    "wof:name":"Gomez Catering",
    "wof:placetype":"venue"
},
  "geometry": {"coordinates":[-94.930509,29.410856],"type":"Point"}
}