{
  "type": "Feature",
  "properties": {
    "iso:country":"US",
    "sg:address":"13031 Hughes Ln",
    "sg:city":"Dallas",
    "sg:classifiers":[
        {
            "category":"Shopping",
            "subcategory":"Used Merchandise",
            "type":"Retail Goods"
        }
    ],
    "sg:phone":"+1 972 233 4121",
    "sg:postcode":"75240",
    "sg:province":"TX",
    "wof:name":"Summerhouse Collections",
    "wof:placetype":"venue"
},
  "geometry": {"coordinates":[-96.79726700000001,32.925694],"type":"Point"}
}