{
  "type": "Feature",
  "properties": {
    "iso:country":"US",
    "sg:address":"433 E Commerce St",
    "sg:city":"Fairfield",
    "sg:classifiers":[
        {
            "category":"Personal",
            "subcategory":"Beauty Salon",
            "type":"Services"
        }
    ],
    "sg:phone":"+1 903 389 4719",
    "sg:postcode":"75840",
    "sg:province":"TX",
    "sg:tags":[
        "shop"
    ],
    "wof:name":"House Of Stylez",
    "wof:placetype":"venue"
},
  "geometry": {"coordinates":[-96.15630299999999,31.725189],"type":"Point"}
}