{
  "type": "Feature",
  "properties": {
    "iso:country":"US",
    "sg:address":"433 W Bandera Rd",
    "sg:city":"Boerne",
    "sg:classifiers":[
        {
            "category":"Restaurant",
            "type":"Food & Drink"
        }
    ],
    "sg:menulink":"http://www.allmenus.com/tx/boerne/104193-taco-cabana/menu/",
    "sg:phone":"+1 830 249 5500",
    "sg:postcode":"78006",
    "sg:province":"TX",
    "sg:tags":[
        "mexican"
    ],
    "wof:name":"Taco Cabana",
    "wof:placetype":"venue"
},
  "geometry": {"coordinates":[-98.735286,29.780507],"type":"Point"}
}