{
  "type": "Feature",
  "properties": {
    "iso:country":"US",
    "sg:address":"4238 Centergate St",
    "sg:city":"San Antonio",
    "sg:classifiers":[
        {
            "category":"Wholesale",
            "subcategory":"Apparel",
            "type":"Manufacturing & Wholesale Goods"
        },
        {
            "category":"Manufacturing",
            "subcategory":"Apparel",
            "type":"Manufacturing & Wholesale Goods"
        }
    ],
    "sg:phone":"+1 210 599 1062",
    "sg:postcode":"78217",
    "sg:province":"TX",
    "sg:tags":[
        "clothing",
        "mfg"
    ],
    "wof:name":"Falcon USA",
    "wof:placetype":"venue"
},
  "geometry": {"coordinates":[-98.409342,29.52044],"type":"Point"}
}