{
  "type": "Feature",
  "properties": {
    "iso:country":"US",
    "sg:address":"2408 Newport Ave",
    "sg:city":"Laredo",
    "sg:classifiers":[
        {
            "category":"Freight",
            "type":"Transportation"
        }
    ],
    "sg:phone":"+1 956 727 1739",
    "sg:postcode":"78043",
    "sg:province":"TX",
    "sg:tags":[
        "operator",
        "trucking"
    ],
    "wof:name":"Lgarcia J Ltrucking",
    "wof:placetype":"venue"
},
  "geometry": {"coordinates":[-99.45926900000001,27.518036],"type":"Point"}
}