{
  "type": "Feature",
  "properties": {
    "iso:country":"US",
    "sg:address":"323 S Oak St",
    "sg:city":"Pecos",
    "sg:classifiers":[
        {
            "category":"Shopping",
            "subcategory":"Discount & Variety Stores",
            "type":"Retail Goods"
        }
    ],
    "sg:phone":"+1 432 445 2435",
    "sg:postcode":"79772",
    "sg:province":"TX",
    "sg:tags":[
        "merchandise",
        "general"
    ],
    "wof:name":"Penny J C Co Inc Dept Store",
    "wof:placetype":"venue"
},
  "geometry": {"coordinates":[-103.49533700000001,31.425283],"type":"Point"}
}