{
  "type": "Feature",
  "properties": {
    "iso:country":"US",
    "sg:address":"1010 Boykin Dr",
    "sg:city":"Memphis",
    "sg:classifiers":[
        {
            "category":"Autos & Motor Vehicles",
            "subcategory":"Auto Supplies",
            "type":"Retail Goods"
        }
    ],
    "sg:phone":"+1 806 259 2551",
    "sg:postcode":"79245",
    "sg:province":"TX",
    "sg:tags":[
        "tire"
    ],
    "wof:name":"O K Tire",
    "wof:placetype":"venue"
},
  "geometry": {"coordinates":[-100.543851,34.734816],"type":"Point"}
}