{
  "type": "Feature",
  "properties": {
    "iso:country":"US",
    "sg:address":"210 N Kansas Ave",
    "sg:city":"League City",
    "sg:classifiers":[
        {
            "category":"Organizations",
            "subcategory":"Membership Organization",
            "type":"Services"
        }
    ],
    "sg:phone":"+1 281 554 2994",
    "sg:postcode":"77573",
    "sg:province":"TX",
    "wof:name":"League City Historical Society",
    "wof:placetype":"venue"
},
  "geometry": {"coordinates":[-95.089821,29.512991],"type":"Point"}
}