{
  "type": "Feature",
  "properties": {
    "iso:country":"US",
    "sg:address":"214 W Grand Ave",
    "sg:city":"Yoakum",
    "sg:classifiers":[
        {
            "category":"Shopping",
            "subcategory":"Computers & Home Electronics",
            "type":"Retail Goods"
        }
    ],
    "sg:phone":"+1 361 293 7337",
    "sg:postcode":"77995",
    "sg:province":"TX",
    "sg:tags":[
        "appliance"
    ],
    "wof:name":"Arnold TV Applance/Radio Shack",
    "wof:placetype":"venue"
},
  "geometry": {"coordinates":[-97.151645,29.289699],"type":"Point"}
}