{
  "type": "Feature",
  "properties": {
    "iso:country":"US",
    "sg:address":"11917 Oak Knoll Dr",
    "sg:city":"Austin",
    "sg:classifiers":[
        {
            "category":"Real Estate",
            "subcategory":"Real Estate Operator",
            "type":"Services"
        }
    ],
    "sg:phone":"+1 512 419 7202",
    "sg:postcode":"78759",
    "sg:province":"TX",
    "sg:tags":[
        "building",
        "apartment"
    ],
    "wof:name":"Avenel Apts",
    "wof:placetype":"venue"
},
  "geometry": {"coordinates":[-97.75999899999999,30.427698],"type":"Point"}
}