{
  "type": "Feature",
  "properties": {
    "iso:country":"US",
    "sg:address":"604 E 4th St",
    "sg:city":"Fort Worth",
    "sg:classifiers":[
        {
            "category":"Professional",
            "subcategory":"Lawyer & Legal Services",
            "type":"Services"
        }
    ],
    "sg:phone":"+1 817 334 0460",
    "sg:postcode":"76102",
    "sg:province":"TX",
    "sg:tags":[
        "attorney"
    ],
    "wof:name":"Christian D Tucker",
    "wof:placetype":"venue"
},
  "geometry": {"coordinates":[-97.326644,32.756608],"type":"Point"}
}