{
  "type": "Feature",
  "properties": {
    "iso:country":"US",
    "sg:address":"13408 FM 812",
    "sg:city":"Del Valle",
    "sg:classifiers":[
        {
            "category":"Professional",
            "subcategory":"Management & Consulting",
            "type":"Services"
        }
    ],
    "sg:phone":"+1 512 243 2944",
    "sg:postcode":"78617",
    "sg:province":"TX",
    "sg:tags":[
        "business"
    ],
    "wof:name":"Information Security Consultin",
    "wof:placetype":"venue"
},
  "geometry": {"coordinates":[-97.635271,30.120816],"type":"Point"}
}