{
  "type": "Feature",
  "properties": {
    "iso:country":"US",
    "sg:address":"43 Surrey Dr",
    "sg:city":"Alvin",
    "sg:classifiers":[
        {
            "category":"Building & Trades",
            "subcategory":"Electrical",
            "type":"Services"
        }
    ],
    "sg:phone":"+1 832 859 1926",
    "sg:postcode":"77511",
    "sg:province":"TX",
    "sg:tags":[
        "electrician"
    ],
    "wof:name":"Mccagg Electric",
    "wof:placetype":"venue"
},
  "geometry": {"coordinates":[-95.29349999999999,29.436049],"type":"Point"}
}