{
  "type": "Feature",
  "properties": {
    "iso:country":"US",
    "sg:address":"26 US Hwy 87",
    "sg:city":"Comfort",
    "sg:classifiers":[
        {
            "category":"Shopping",
            "subcategory":"Books",
            "type":"Retail Goods"
        }
    ],
    "sg:phone":"+1 830 995 2311",
    "sg:postcode":"78013",
    "sg:province":"TX",
    "wof:name":"Comfort Gas Inc",
    "wof:placetype":"venue"
},
  "geometry": {"coordinates":[-98.90409200000001,29.970802],"type":"Point"}
}