{
  "type": "Feature",
  "properties": {
    "iso:country":"US",
    "sg:address":"516 US Hwy 77",
    "sg:city":"San Benito",
    "sg:classifiers":[
        {
            "category":"Building & Trades",
            "subcategory":"Construction",
            "type":"Services"
        }
    ],
    "sg:phone":"+1 956 399 1809",
    "sg:postcode":"78586",
    "sg:province":"TX",
    "wof:name":"R&R Paving Co",
    "wof:placetype":"venue"
},
  "geometry": {"coordinates":[-97.64142099999999,26.130108],"type":"Point"}
}