{
  "type": "Feature",
  "properties": {
    "iso:country":"US",
    "sg:address":"30211 Legends Ridge Dr",
    "sg:city":"Spring",
    "sg:classifiers":[
        {
            "category":"Arts & Performance",
            "subcategory":"Art Gallery",
            "type":"Entertainment"
        },
        {
            "category":"Museum",
            "type":"Entertainment"
        }
    ],
    "sg:phone":"+1 281 419 2130",
    "sg:postcode":"77386",
    "sg:province":"TX",
    "sg:tags":[
        "consultant",
        "galleries"
    ],
    "wof:name":"The Legends Ranch Splash Pad",
    "wof:placetype":"venue"
},
  "geometry": {"coordinates":[-95.391183,30.129204],"type":"Point"}
}