{
  "type": "Feature",
  "properties": {
    "iso:country":"US",
    "sg:address":"200 SE 1st St",
    "sg:city":"Andrews",
    "sg:classifiers":[
        {
            "category":"Mining & Drilling",
            "type":"Manufacturing & Wholesale Goods"
        }
    ],
    "sg:phone":"+1 432 523 2906",
    "sg:postcode":"79714",
    "sg:province":"TX",
    "sg:tags":[
        "oil",
        "gas",
        "producer"
    ],
    "wof:name":"Rockpointe Resources Inc",
    "wof:placetype":"venue"
},
  "geometry": {"coordinates":[-102.545061,32.317994],"type":"Point"}
}