{
  "type": "Feature",
  "properties": {
    "iso:country":"US",
    "sg:address":"1116 N Foundation Dr",
    "sg:city":"Pilot Point",
    "sg:classifiers":[
        {
            "category":"Professional",
            "subcategory":"Business Services",
            "type":"Services"
        }
    ],
    "sg:phone":"+1 940 686 3003",
    "sg:postcode":"76258",
    "sg:province":"TX",
    "wof:name":"Astrum Group Inc",
    "wof:placetype":"venue"
},
  "geometry": {"coordinates":[-96.939651,33.405511],"type":"Point"}
}