{
  "type": "Feature",
  "properties": {
    "iso:country":"US",
    "sg:address":"5311 Mossgrey Ln",
    "sg:city":"Spring",
    "sg:classifiers":[
        {
            "category":"Professional",
            "subcategory":"Business Services",
            "type":"Services"
        }
    ],
    "sg:phone":"+1 281 350 0963",
    "sg:postcode":"77373",
    "sg:province":"TX",
    "wof:name":"Big K Enterprise",
    "wof:placetype":"venue"
},
  "geometry": {"coordinates":[-95.35262,30.051753],"type":"Point"}
}