{
  "type": "Feature",
  "properties": {
    "iso:country":"US",
    "sg:address":"11505 Heathrow Dr",
    "sg:city":"Austin",
    "sg:classifiers":[
        {
            "category":"Social Services",
            "subcategory":"Child Care",
            "type":"Services"
        }
    ],
    "sg:phone":"+1 512 219 5183",
    "sg:postcode":"78759",
    "sg:province":"TX",
    "sg:tags":[
        "day"
    ],
    "wof:name":"Jump Start Organizing",
    "wof:placetype":"venue"
},
  "geometry": {"coordinates":[-97.778178,30.431546],"type":"Point"}
}