{
  "type": "Feature",
  "properties": {
    "iso:country":"US",
    "sg:address":"5910 S M L King Jr Pkwy",
    "sg:city":"Beaumont",
    "sg:classifiers":[
        {
            "category":"Freight",
            "type":"Transportation"
        }
    ],
    "sg:phone":"+1 409 833 2700",
    "sg:postcode":"77705",
    "sg:province":"TX",
    "sg:tags":[
        "dry",
        "bulk",
        "trucking"
    ],
    "wof:name":"United Petroleum Transports",
    "wof:placetype":"venue"
},
  "geometry": {"coordinates":[-94.058995,30.029558],"type":"Point"}
}