{
  "type": "Feature",
  "properties": {
    "iso:country":"US",
    "sg:address":"1208 6th St",
    "sg:city":"Wichita Falls",
    "sg:classifiers":[
        {
            "category":"Professional",
            "subcategory":"Computer Services",
            "type":"Services"
        }
    ],
    "sg:phone":"+1 940 692 2364",
    "sg:postcode":"76301",
    "sg:province":"TX",
    "sg:tags":[
        "wiring"
    ],
    "wof:name":"Dirty Deeds",
    "wof:placetype":"venue"
},
  "geometry": {"coordinates":[-98.499163,33.910815],"type":"Point"}
}