{
  "type": "Feature",
  "properties": {
    "iso:country":"US",
    "sg:address":"8710 Westpark Dr",
    "sg:city":"Houston",
    "sg:classifiers":[
        {
            "category":"Freight",
            "type":"Transportation"
        }
    ],
    "sg:phone":"+1 713 339 4711",
    "sg:postcode":"77063",
    "sg:province":"TX",
    "sg:tags":[
        "delivery"
    ],
    "wof:name":"Express Parcel Svc",
    "wof:placetype":"venue"
},
  "geometry": {"coordinates":[-95.51674199999999,29.721831],"type":"Point"}
}