{
  "type": "Feature",
  "properties": {
    "iso:country":"US",
    "sg:address":"1700 Adams St",
    "sg:city":"Taylor",
    "sg:classifiers":[
        {
            "category":"Manufacturing",
            "subcategory":"Tools & Machinery",
            "type":"Manufacturing & Wholesale Goods"
        }
    ],
    "sg:phone":"+1 512 365 5383",
    "sg:postcode":"76574",
    "sg:province":"TX",
    "sg:tags":[
        "computer",
        "electronic",
        "mfg"
    ],
    "wof:name":"Sungod Technical Services",
    "wof:placetype":"venue"
},
  "geometry": {"coordinates":[-97.426912,30.575165],"type":"Point"}
}