{
  "type": "Feature",
  "properties": {
    "iso:country":"US",
    "sg:address":"3501 N Navarro St",
    "sg:city":"Victoria",
    "sg:classifiers":[
        {
            "category":"Professional",
            "subcategory":"Art Services",
            "type":"Services"
        }
    ],
    "sg:phone":"+1 361 575 2701",
    "sg:postcode":"77901",
    "sg:province":"TX",
    "sg:tags":[
        "laboratory",
        "photo",
        "photography",
        "commercial",
        "picture"
    ],
    "wof:name":"Korczynskis Photo Lab & Studio",
    "wof:placetype":"venue"
},
  "geometry": {"coordinates":[-97.001029,28.827945],"type":"Point"}
}