{
  "type": "Feature",
  "properties": {
    "iso:country":"US",
    "sg:address":"923 E University Dr",
    "sg:city":"Edinburg",
    "sg:classifiers":[
        {
            "category":"Wholesale",
            "subcategory":"Auto Parts",
            "type":"Manufacturing & Wholesale Goods"
        }
    ],
    "sg:phone":"+1 956 287 2441",
    "sg:postcode":"78539",
    "sg:province":"TX",
    "wof:name":"Burton Auto Supplu",
    "wof:placetype":"venue"
},
  "geometry": {"coordinates":[-98.15275,26.300074],"type":"Point"}
}