{
  "type": "Feature",
  "properties": {
    "iso:country":"US",
    "sg:address":"600 Belvidere St",
    "sg:city":"El Paso",
    "sg:classifiers":[
        {
            "category":"Real Estate",
            "subcategory":"Real Estate Operator",
            "type":"Services"
        }
    ],
    "sg:phone":"+1 915 845 0606",
    "sg:postcode":"79912",
    "sg:province":"TX",
    "sg:tags":[
        "condominium"
    ],
    "wof:name":"Franklin Place Townhomes",
    "wof:placetype":"venue"
},
  "geometry": {"coordinates":[-106.556406,31.85032],"type":"Point"}
}