{
  "type": "Feature",
  "properties": {
    "iso:country":"US",
    "sg:address":"1111 S Armstrong Ave",
    "sg:city":"Denison",
    "sg:classifiers":[
        {
            "category":"Retail",
            "subcategory":"Repair Shop",
            "type":"Services"
        }
    ],
    "sg:phone":"+1 903 463 2629",
    "sg:postcode":"75020",
    "sg:province":"TX",
    "sg:tags":[
        "used",
        "merchandise"
    ],
    "wof:name":"Denison TV",
    "wof:placetype":"venue"
},
  "geometry": {"coordinates":[-96.546767,33.744562],"type":"Point"}
}