{
  "type": "Feature",
  "properties": {
    "iso:country":"US",
    "sg:address":"5203 Pinemont Dr",
    "sg:city":"Houston",
    "sg:classifiers":[
        {
            "category":"Autos & Motor Vehicles",
            "subcategory":"Auto Supplies",
            "type":"Retail Goods"
        }
    ],
    "sg:phone":"+1 713 688 8764",
    "sg:postcode":"77092",
    "sg:province":"TX",
    "sg:tags":[
        "tire"
    ],
    "wof:name":"Pinemont Tires",
    "wof:placetype":"venue"
},
  "geometry": {"coordinates":[-95.46779600000001,29.840799],"type":"Point"}
}