{
  "type": "Feature",
  "properties": {
    "iso:country":"US",
    "sg:address":"9550 Fm 1960 Bypass Rd W",
    "sg:city":"Humble",
    "sg:classifiers":[
        {
            "category":"Communications",
            "type":"Services"
        }
    ],
    "sg:phone":"+1 281 446 3728",
    "sg:postcode":"77338",
    "sg:province":"TX",
    "sg:tags":[
        "carrier",
        "radiotelephone",
        "communications-common"
    ],
    "sg:website":"http://www.voicestream.com",
    "wof:name":"T-Mobile Usa, Inc",
    "wof:placetype":"venue"
},
  "geometry": {"coordinates":[-95.27819,30.004978],"type":"Point"}
}