{
  "type": "Feature",
  "properties": {
    "iso:country":"US",
    "sg:address":"3004 Bryker Dr",
    "sg:city":"Austin",
    "sg:classifiers":[
        {
            "category":"Professional",
            "type":"Services"
        }
    ],
    "sg:phone":"+1 512 452 7313",
    "sg:postcode":"78703",
    "sg:province":"TX",
    "wof:name":"George Bronner",
    "wof:placetype":"venue"
},
  "geometry": {"coordinates":[-97.755099,30.303734],"type":"Point"}
}