{
  "type": "Feature",
  "properties": {
    "iso:country":"US",
    "sg:address":"8825 Solon Rd",
    "sg:city":"Houston",
    "sg:classifiers":[
        {
            "category":"Manufacturing",
            "subcategory":"Paper Products",
            "type":"Manufacturing & Wholesale Goods"
        },
        {
            "category":"Manufacturing",
            "subcategory":"Printing",
            "type":"Manufacturing & Wholesale Goods"
        }
    ],
    "sg:phone":"+1 281 894 9100",
    "sg:postcode":"77064",
    "sg:province":"TX",
    "sg:tags":[
        "printer",
        "mfg"
    ],
    "wof:name":"I D Technology",
    "wof:placetype":"venue"
},
  "geometry": {"coordinates":[-95.551109,29.949696],"type":"Point"}
}