{
  "type": "Feature",
  "properties": {
    "iso:country":"US",
    "sg:address":"8440 Esters Blvd",
    "sg:city":"Irving",
    "sg:classifiers":[
        {
            "category":"Shopping",
            "subcategory":"Computers & Home Electronics",
            "type":"Retail Goods"
        }
    ],
    "sg:phone":"+1 972 929 0925",
    "sg:postcode":"75063",
    "sg:province":"TX",
    "sg:tags":[
        "software"
    ],
    "wof:name":"Cargo Data Mgmt Corp",
    "wof:placetype":"venue"
},
  "geometry": {"coordinates":[-97.007814,32.923407],"type":"Point"}
}