{
  "type": "Feature",
  "properties": {
    "iso:country":"US",
    "sg:address":"235 Forest Trl",
    "sg:city":"Argyle",
    "sg:classifiers":[
        {
            "category":"Health Services",
            "subcategory":"Doctor",
            "type":"Services"
        }
    ],
    "sg:phone":"+1 940 240 1301",
    "sg:postcode":"76226",
    "sg:province":"TX",
    "sg:tags":[
        "medical"
    ],
    "wof:name":"Jeannean Newsom Crna",
    "wof:placetype":"venue"
},
  "geometry": {"coordinates":[-97.195367,33.093412],"type":"Point"}
}