{
  "type": "Feature",
  "properties": {
    "iso:country":"US",
    "sg:address":"420 W Pipeline Rd",
    "sg:city":"Hurst",
    "sg:classifiers":[
        {
            "category":"Food & Beverages",
            "subcategory":"Bakery",
            "type":"Retail Goods"
        }
    ],
    "sg:phone":"+1 817 282 6868",
    "sg:postcode":"76053",
    "sg:province":"TX",
    "sg:tags":[
        "product",
        "mfg"
    ],
    "wof:name":"Best Little Donut In Town",
    "wof:placetype":"venue"
},
  "geometry": {"coordinates":[-97.176464,32.823677],"type":"Point"}
}