{
  "type": "Feature",
  "properties": {
    "iso:country":"US",
    "sg:address":"1012 Sunnyside Ave",
    "sg:city":"Dallas",
    "sg:classifiers":[
        {
            "category":"Government",
            "subcategory":"Office",
            "type":"Public Place"
        }
    ],
    "sg:phone":"+1 214 337 2678",
    "sg:postcode":"75211",
    "sg:province":"TX",
    "sg:tags":[
        "village"
    ],
    "wof:name":"Cockrell Hill Svc Ctr",
    "wof:placetype":"venue"
},
  "geometry": {"coordinates":[-96.888527,32.735144],"type":"Point"}
}