{
  "type": "Feature",
  "properties": {
    "iso:country":"US",
    "sg:address":"708 N Washington Ave",
    "sg:city":"Cameron",
    "sg:classifiers":[
        {
            "category":"Professional",
            "subcategory":"Management & Consulting",
            "type":"Services"
        }
    ],
    "sg:phone":"+1 254 697 4495",
    "sg:postcode":"76520",
    "sg:province":"TX",
    "wof:name":"Ballard Management Co",
    "wof:placetype":"venue"
},
  "geometry": {"coordinates":[-96.971402,30.854924],"type":"Point"}
}