{
  "type": "Feature",
  "properties": {
    "iso:country":"US",
    "sg:address":"2109 Sagebrush Dr",
    "sg:city":"Flower Mound",
    "sg:classifiers":[
        {
            "category":"Professional",
            "subcategory":"Management & Consulting",
            "type":"Services"
        }
    ],
    "sg:phone":"+1 972 355 2368",
    "sg:postcode":"75028",
    "sg:province":"TX",
    "wof:name":"Marado Management Co LLC",
    "wof:placetype":"venue"
},
  "geometry": {"coordinates":[-97.060153,33.030254],"type":"Point"}
}