{
  "type": "Feature",
  "properties": {
    "iso:country":"US",
    "sg:address":"2529 Waterstone Ln",
    "sg:city":"Rockwall",
    "sg:classifiers":[
        {
            "category":"Manufacturing",
            "subcategory":"Buildings",
            "type":"Manufacturing & Wholesale Goods"
        },
        {
            "category":"Building & Trades",
            "subcategory":"Construction",
            "type":"Services"
        }
    ],
    "sg:phone":"+1 214 771 0888",
    "sg:postcode":"75032",
    "sg:province":"TX",
    "sg:tags":[
        "home",
        "builder",
        "management",
        "contractor"
    ],
    "sg:website":"http://www.alturahomes.com",
    "wof:name":"Altura Homes",
    "wof:placetype":"venue"
},
  "geometry": {"coordinates":[-96.451505,32.899832],"type":"Point"}
}