{
  "type": "Feature",
  "properties": {
    "iso:country":"US",
    "sg:address":"920 E Arkansas Ln",
    "sg:city":"Arlington",
    "sg:classifiers":[
        {
            "category":"Wholesale",
            "subcategory":"Apparel",
            "type":"Manufacturing & Wholesale Goods"
        }
    ],
    "sg:phone":"+1 817 795 7100",
    "sg:postcode":"76014",
    "sg:province":"TX",
    "sg:tags":[
        "sewing",
        "thread",
        "supply"
    ],
    "wof:name":"Arlington Potex Co Inc",
    "wof:placetype":"venue"
},
  "geometry": {"coordinates":[-97.093805,32.706115],"type":"Point"}
}