{
  "type": "Feature",
  "properties": {
    "iso:country":"US",
    "sg:address":"227 Connally St",
    "sg:city":"Sulphur Springs",
    "sg:classifiers":[
        {
            "category":"Insurance",
            "subcategory":"Insurance Agent",
            "type":"Services"
        }
    ],
    "sg:phone":"+1 903 885 6547",
    "sg:postcode":"75482",
    "sg:province":"TX",
    "sg:website":"www.galyean-insurance.com",
    "wof:name":"Galyean Insurance",
    "wof:placetype":"venue"
},
  "geometry": {"coordinates":[-95.60205999999999,33.138454],"type":"Point"}
}