{
  "type": "Feature",
  "properties": {
    "iso:country":"US",
    "sg:address":"28044 Tomball Pkwy",
    "sg:city":"Tomball",
    "sg:classifiers":[
        {
            "category":"Home & Garden",
            "subcategory":"Building Materials",
            "type":"Retail Goods"
        }
    ],
    "sg:phone":"+1 281 351 1511",
    "sg:postcode":"77375",
    "sg:province":"TX",
    "wof:name":"Steele & Sons Overhead Door Co",
    "wof:placetype":"venue"
},
  "geometry": {"coordinates":[-95.63022599999999,30.081367],"type":"Point"}
}