{
  "type": "Feature",
  "properties": {
    "iso:country":"US",
    "sg:address":"2619 Austin Ave",
    "sg:city":"Brownwood",
    "sg:classifiers":[
        {
            "category":"Home & Garden",
            "subcategory":"Household Appliances",
            "type":"Retail Goods"
        }
    ],
    "sg:phone":"+1 325 646 2841",
    "sg:postcode":"76801",
    "sg:province":"TX",
    "sg:tags":[
        "repair",
        "electrical"
    ],
    "wof:name":"A A A Vacuum Cleaner",
    "wof:placetype":"venue"
},
  "geometry": {"coordinates":[-98.967872,31.696993],"type":"Point"}
}