{
  "type": "Feature",
  "properties": {
    "iso:country":"US",
    "sg:address":"6671 Southwest Fwy",
    "sg:city":"Houston",
    "sg:classifiers":[
        {
            "category":"Professional",
            "subcategory":"Accounting & Tax Preparation",
            "type":"Services"
        }
    ],
    "sg:phone":"+1 713 270 7177",
    "sg:postcode":"77074",
    "sg:province":"TX",
    "sg:tags":[
        "auditing",
        "bookkeeping"
    ],
    "wof:name":"Enterprise Services Company",
    "wof:placetype":"venue"
},
  "geometry": {"coordinates":[-95.500068,29.71535],"type":"Point"}
}