{
  "type": "Feature",
  "properties": {
    "iso:country":"US",
    "sg:address":"501 W Main St",
    "sg:city":"Fredericksburg",
    "sg:classifiers":[
        {
            "category":"Science Facility",
            "type":"Public Place"
        }
    ],
    "sg:phone":"+1 830 997 1864",
    "sg:postcode":"78624",
    "sg:province":"TX",
    "sg:tags":[
        "rodeo"
    ],
    "sg:website":"http://www.lmrodeo.com",
    "wof:name":"Lester Meier Rodeo Co Inc",
    "wof:placetype":"venue"
},
  "geometry": {"coordinates":[-98.879074,30.279982],"type":"Point"}
}