{
  "type": "Feature",
  "properties": {
    "iso:country":"US",
    "sg:address":"12420 State Hwy 155",
    "sg:city":"Tyler",
    "sg:classifiers":[
        {
            "category":"Retail",
            "subcategory":"Repair Shop",
            "type":"Services"
        }
    ],
    "sg:phone":"+1 903 939 9220",
    "sg:postcode":"75703",
    "sg:province":"TX",
    "sg:tags":[
        "upholsterer"
    ],
    "wof:name":"F T Upholstery",
    "wof:placetype":"venue"
},
  "geometry": {"coordinates":[-95.33996,32.301543],"type":"Point"}
}