{
  "type": "Feature",
  "properties": {
    "iso:country":"US",
    "sg:address":"2825 Greenville Ave",
    "sg:city":"Dallas",
    "sg:classifiers":[
        {
            "category":"Bars & Pubs",
            "type":"Food & Drink"
        }
    ],
    "sg:phone":"+1 214 827 0039",
    "sg:postcode":"75206",
    "sg:province":"TX",
    "sg:tags":[
        "club",
        "night"
    ],
    "wof:name":"Mick's",
    "wof:placetype":"venue"
},
  "geometry": {"coordinates":[-96.77022700000001,32.822671],"type":"Point"}
}