{
  "type": "Feature",
  "properties": {
    "iso:country":"US",
    "sg:address":"1715 Fm 1626",
    "sg:city":"Manchaca",
    "sg:classifiers":[
        {
            "category":"Insurance",
            "subcategory":"Hazard Insurance",
            "type":"Services"
        }
    ],
    "sg:phone":"+1 512 442 6363",
    "sg:postcode":"78652",
    "sg:province":"TX",
    "wof:name":"Sullivent T Agency",
    "wof:placetype":"venue"
},
  "geometry": {"coordinates":[-97.842246,30.142539],"type":"Point"}
}