{
  "type": "Feature",
  "properties": {
    "iso:country":"US",
    "sg:address":"1221 Newsom Rd",
    "sg:city":"Mesquite",
    "sg:classifiers":[
        {
            "category":"Real Estate",
            "subcategory":"Real Estate Agent",
            "type":"Services"
        }
    ],
    "sg:phone":"+1 972 329 0722",
    "sg:postcode":"75149",
    "sg:province":"TX",
    "wof:name":"Jam Investors",
    "wof:placetype":"venue"
},
  "geometry": {"coordinates":[-96.581452,32.760551],"type":"Point"}
}