{
  "type": "Feature",
  "properties": {
    "iso:country":"US",
    "sg:address":"691 N Post Oak Ln",
    "sg:city":"Houston",
    "sg:classifiers":[
        {
            "category":"Insurance",
            "subcategory":"Insurance Agent",
            "type":"Services"
        }
    ],
    "sg:phone":"+1 713 621 4722",
    "sg:postcode":"77024",
    "sg:province":"TX",
    "wof:name":"Health Insurance Specialists",
    "wof:placetype":"venue"
},
  "geometry": {"coordinates":[-95.457673,29.779408],"type":"Point"}
}