{
  "type": "Feature",
  "properties": {
    "iso:country":"US",
    "sg:address":"1010 Richey St",
    "sg:city":"Pasadena",
    "sg:classifiers":[
        {
            "category":"Organizations",
            "subcategory":"Religious Organization",
            "type":"Services"
        }
    ],
    "sg:phone":"+1 713 947 7111",
    "sg:postcode":"77506",
    "sg:province":"TX",
    "wof:name":"3 16 Community Center Inc",
    "wof:placetype":"venue"
},
  "geometry": {"coordinates":[-95.219809,29.69637],"type":"Point"}
}