{
  "type": "Feature",
  "properties": {
    "iso:country":"US",
    "sg:address":"12537 Oak Grove Rd S",
    "sg:city":"Burleson",
    "sg:classifiers":[
        {
            "category":"Home & Garden",
            "subcategory":"Furniture",
            "type":"Retail Goods"
        },
        {
            "category":"Wholesale",
            "subcategory":"Home Furnishings",
            "type":"Manufacturing & Wholesale Goods"
        }
    ],
    "sg:phone":"+1 817 568 1632",
    "sg:postcode":"76028",
    "sg:province":"TX",
    "sg:tags":[
        "equipment-wholesale",
        "kitchen",
        "equipment-household",
        "manufacturer",
        "cabinet"
    ],
    "wof:name":"Cruz Cabinet Shop",
    "wof:placetype":"venue"
},
  "geometry": {"coordinates":[-97.292288,32.573623],"type":"Point"}
}