{
  "type": "Feature",
  "properties": {
    "iso:country":"US",
    "sg:address":"26222 I- 45",
    "sg:city":"Spring",
    "sg:classifiers":[
        {
            "category":"Health Services",
            "subcategory":"Doctor",
            "type":"Services"
        }
    ],
    "sg:phone":"+1 281 364 0404",
    "sg:postcode":"77386",
    "sg:province":"TX",
    "sg:tags":[
        "clinic"
    ],
    "wof:name":"Urgent Care",
    "wof:placetype":"venue"
},
  "geometry": {"coordinates":[-95.44568700000001,30.14193],"type":"Point"}
}