{
  "type": "Feature",
  "properties": {
    "iso:country":"US",
    "sg:address":"2532 Beechmont Dr",
    "sg:city":"Dallas",
    "sg:classifiers":[
        {
            "category":"Building & Trades",
            "subcategory":"Landscaping Services",
            "type":"Services"
        }
    ],
    "sg:phone":"+1 214 319 0866",
    "sg:postcode":"75228",
    "sg:province":"TX",
    "wof:name":"Gilberts Lawns",
    "wof:placetype":"venue"
},
  "geometry": {"coordinates":[-96.68607900000001,32.822241],"type":"Point"}
}