{
  "type": "Feature",
  "properties": {
    "iso:country":"US",
    "sg:address":"5435 N Garland Ave # 140314",
    "sg:city":"Garland",
    "sg:classifiers":[
        {
            "category":"Professional",
            "subcategory":"Management & Consulting",
            "type":"Services"
        }
    ],
    "sg:phone":"+1 972 463 3080",
    "sg:postcode":"75040",
    "sg:province":"TX",
    "sg:tags":[
        "consultant"
    ],
    "sg:website":"http://www.base16.com",
    "wof:name":"Base 16 Corporation",
    "wof:placetype":"venue"
},
  "geometry": {"coordinates":[-96.64425900000001,32.964019],"type":"Point"}
}