{
  "type": "Feature",
  "properties": {
    "iso:country":"US",
    "sg:address":"3216 S Port Ave",
    "sg:city":"Corpus Christi",
    "sg:classifiers":[
        {
            "category":"Banks & Credit Unions",
            "subcategory":"Bank",
            "type":"Services"
        }
    ],
    "sg:phone":"+1 361 883 2274",
    "sg:postcode":"78415",
    "sg:province":"TX",
    "sg:tags":[
        "depository",
        "banking"
    ],
    "wof:name":"ACE Cash Express",
    "wof:placetype":"venue"
},
  "geometry": {"coordinates":[-97.42008,27.761938],"type":"Point"}
}