{
  "type": "Feature",
  "properties": {
    "iso:country":"US",
    "sg:address":"2350 Guadalupe",
    "sg:city":"Austin",
    "sg:classifiers":[
        {
            "category":"Fast Food",
            "type":"Food & Drink"
        },
        {
            "category":"Restaurant",
            "type":"Food & Drink"
        }
    ],
    "sg:phone":"+1 512 474 7482",
    "sg:postcode":"78705",
    "sg:province":"TX",
    "sg:tags":[
        "greek",
        "mediterranean"
    ],
    "sg:website":"www.pitapitaustin.com",
    "wof:name":"The Pita Pit",
    "wof:placetype":"venue"
},
  "geometry": {"coordinates":[-97.741945,30.287463],"type":"Point"}
}