{
  "type": "Feature",
  "properties": {
    "iso:country":"US",
    "sg:address":"12100 Overbrook Ln",
    "sg:city":"Houston",
    "sg:classifiers":[
        {
            "category":"Professional",
            "type":"Services"
        }
    ],
    "sg:phone":"+1 281 493 1566",
    "sg:postcode":"77077",
    "sg:province":"TX",
    "wof:name":"Mudanca Gratis",
    "wof:placetype":"venue"
},
  "geometry": {"coordinates":[-95.59265000000001,29.737935],"type":"Point"}
}