{
  "type": "Feature",
  "properties": {
    "iso:country":"US",
    "sg:address":"615 N Zaragoza Rd",
    "sg:city":"El Paso",
    "sg:classifiers":[
        {
            "category":"Personal",
            "subcategory":"Beauty Salon",
            "type":"Services"
        }
    ],
    "sg:phone":"+1 915 872 0991",
    "sg:postcode":"79907",
    "sg:province":"TX",
    "sg:tags":[
        "shop",
        "manicuring"
    ],
    "wof:name":"Natural Nail",
    "wof:placetype":"venue"
},
  "geometry": {"coordinates":[-106.318243,31.704496],"type":"Point"}
}