{
  "type": "Feature",
  "properties": {
    "iso:country":"US",
    "sg:address":"5329 Wharton St",
    "sg:city":"Corpus Christi",
    "sg:classifiers":[
        {
            "category":"Building & Trades",
            "subcategory":"Construction",
            "type":"Services"
        }
    ],
    "sg:phone":"+1 361 814 5605",
    "sg:postcode":"78415",
    "sg:province":"TX",
    "sg:tags":[
        "plastering",
        "contractor"
    ],
    "wof:name":"Hi Tech Plastering Inc",
    "wof:placetype":"venue"
},
  "geometry": {"coordinates":[-97.420806,27.726858],"type":"Point"}
}