{
  "type": "Feature",
  "properties": {
    "iso:country":"US",
    "sg:address":"717 Broadway St",
    "sg:city":"Plainview",
    "sg:classifiers":[
        {
            "category":"Arts & Performance",
            "subcategory":"Theater",
            "type":"Entertainment"
        }
    ],
    "sg:phone":"+1 806 293 4000",
    "sg:postcode":"79072",
    "sg:province":"TX",
    "wof:name":"Fair Theatre Inc",
    "wof:placetype":"venue"
},
  "geometry": {"coordinates":[-101.703132,34.188083],"type":"Point"}
}