{
  "type": "Feature",
  "properties": {
    "iso:country":"US",
    "sg:address":"6431 Ridgecrest Rd",
    "sg:city":"Dallas",
    "sg:classifiers":[
        {
            "category":"Real Estate",
            "subcategory":"Real Estate Operator",
            "type":"Services"
        }
    ],
    "sg:phone":"+1 214 378 5455",
    "sg:postcode":"75231",
    "sg:province":"TX",
    "sg:tags":[
        "apartment",
        "complex"
    ],
    "wof:name":"Northridge Villa Apartments",
    "wof:placetype":"venue"
},
  "geometry": {"coordinates":[-96.751065,32.866183],"type":"Point"}
}