{
  "type": "Feature",
  "properties": {
    "iso:country":"US",
    "sg:address":"4114 Camphor Way",
    "sg:city":"San Antonio",
    "sg:classifiers":[
        {
            "category":"Professional",
            "subcategory":"Business Services",
            "type":"Services"
        }
    ],
    "sg:phone":"+1 210 490 6954",
    "sg:postcode":"78247",
    "sg:province":"TX",
    "wof:name":"Antebellum Auction Co",
    "wof:placetype":"venue"
},
  "geometry": {"coordinates":[-98.41067,29.588343],"type":"Point"}
}