{
  "type": "Feature",
  "properties": {
    "iso:country":"US",
    "sg:address":"2508 Monterrey St",
    "sg:city":"Hidalgo",
    "sg:classifiers":[
        {
            "category":"Building & Trades",
            "subcategory":"Construction",
            "type":"Services"
        }
    ],
    "sg:phone":"+1 956 843 2811",
    "sg:postcode":"78557",
    "sg:province":"TX",
    "sg:tags":[
        "roofing",
        "industrial",
        "contractors-commercial",
        "contractor"
    ],
    "wof:name":"Rodriguez Roofing",
    "wof:placetype":"venue"
},
  "geometry": {"coordinates":[-98.231803,26.10355],"type":"Point"}
}