{
  "type": "Feature",
  "properties": {
    "iso:country":"US",
    "sg:address":"7103 Wedgewood Dr",
    "sg:city":"Magnolia",
    "sg:classifiers":[
        {
            "category":"Manufacturing",
            "subcategory":"Printing",
            "type":"Manufacturing & Wholesale Goods"
        }
    ],
    "sg:phone":"+1 281 252 8800",
    "sg:postcode":"77354",
    "sg:province":"TX",
    "sg:tags":[
        "commercial"
    ],
    "wof:name":"Babies N Bells",
    "wof:placetype":"venue"
},
  "geometry": {"coordinates":[-95.574366,30.212845],"type":"Point"}
}