{
  "type": "Feature",
  "properties": {
    "iso:country":"US",
    "sg:address":"3724 Old Denton Rd",
    "sg:city":"Carrollton",
    "sg:phone":"+1 972 394 7200",
    "sg:postcode":"75007",
    "sg:province":"TX",
    "wof:name":"American Municipal Services Corporation",
    "wof:placetype":"venue"
},
  "geometry": {"coordinates":[-96.911478,33.012038],"type":"Point"}
}