{
  "type": "Feature",
  "properties": {
    "iso:country":"US",
    "sg:address":"4800 Padre Blvd",
    "sg:city":"S Padre Island",
    "sg:classifiers":[
        {
            "category":"Professional",
            "subcategory":"Lawyer & Legal Services",
            "type":"Services"
        }
    ],
    "sg:phone":"+1 713 888 0500",
    "sg:postcode":"78597",
    "sg:province":"TX",
    "sg:tags":[
        "attorney"
    ],
    "wof:name":"Tricia K Hernden Law Offices",
    "wof:placetype":"venue"
},
  "geometry": {"coordinates":[-97.17026799999999,26.121333],"type":"Point"}
}