{
  "type": "Feature",
  "properties": {
    "iso:country":"US",
    "sg:address":"4909 W State Hwy 107",
    "sg:city":"Edinburg",
    "sg:classifiers":[
        {
            "category":"Retail",
            "subcategory":"Auto Repair",
            "type":"Services"
        }
    ],
    "sg:phone":"+1 956 381 9157",
    "sg:postcode":"78539",
    "sg:province":"TX",
    "sg:tags":[
        "towing"
    ],
    "wof:name":"Reynoldo Garzo",
    "wof:placetype":"venue"
},
  "geometry": {"coordinates":[-98.19313,26.305874],"type":"Point"}
}