{
  "type": "Feature",
  "properties": {
    "iso:country":"US",
    "sg:address":"17000 el Camino Real",
    "sg:city":"Houston",
    "sg:classifiers":[
        {
            "category":"Health Services",
            "subcategory":"Medical Lab",
            "type":"Services"
        }
    ],
    "sg:phone":"+1 281 486 4195",
    "sg:postcode":"77058",
    "sg:province":"TX",
    "sg:tags":[
        "laboratory",
        "testing"
    ],
    "wof:name":"Laboratory Corporation America",
    "wof:placetype":"venue"
},
  "geometry": {"coordinates":[-95.119545,29.554081],"type":"Point"}
}