{
  "type": "Feature",
  "properties": {
    "iso:country":"US",
    "sg:address":"1820 Preston Park Blvd",
    "sg:city":"Plano",
    "sg:classifiers":[
        {
            "category":"Professional",
            "subcategory":"Management & Consulting",
            "type":"Services"
        }
    ],
    "sg:phone":"+1 972 309 0700",
    "sg:postcode":"75093",
    "sg:province":"TX",
    "sg:tags":[
        "regional"
    ],
    "wof:name":"Kb Toys",
    "wof:placetype":"venue"
},
  "geometry": {"coordinates":[-96.78832800000001,33.026884],"type":"Point"}
}