{
  "type": "Feature",
  "properties": {
    "iso:country":"US",
    "sg:address":"12119 Flushing Meadows Dr",
    "sg:city":"Houston",
    "sg:classifiers":[
        {
            "category":"Professional",
            "type":"Services"
        }
    ],
    "sg:phone":"+1 281 481 6445",
    "sg:postcode":"77089",
    "sg:province":"TX",
    "wof:name":"Kfmk 1",
    "wof:placetype":"venue"
},
  "geometry": {"coordinates":[-95.19068799999999,29.588505],"type":"Point"}
}