{
  "type": "Feature",
  "properties": {
    "iso:country":"US",
    "sg:address":"1303 W Walnut Hill Ln",
    "sg:city":"Irving",
    "sg:classifiers":[
        {
            "category":"Banks & Credit Unions",
            "subcategory":"Bank",
            "type":"Services"
        }
    ],
    "sg:phone":"+1 972 756 9576",
    "sg:postcode":"75038",
    "sg:province":"TX",
    "sg:tags":[
        "loan",
        "real estate"
    ],
    "wof:name":"Irwin Mortgage",
    "wof:placetype":"venue"
},
  "geometry": {"coordinates":[-96.968369,32.885121],"type":"Point"}
}