{
  "type": "Feature",
  "properties": {
    "iso:country":"US",
    "sg:address":"1710 9th St",
    "sg:city":"Lubbock",
    "sg:classifiers":[
        {
            "category":"Real Estate",
            "subcategory":"Real Estate Operator",
            "type":"Services"
        }
    ],
    "sg:phone":"+1 806 744 0401",
    "sg:postcode":"79401",
    "sg:province":"TX",
    "sg:tags":[
        "apartment"
    ],
    "wof:name":"Irongate Apts",
    "wof:placetype":"venue"
},
  "geometry": {"coordinates":[-101.855255,33.587391],"type":"Point"}
}