{
  "type": "Feature",
  "properties": {
    "iso:country":"US",
    "sg:address":"524 Santa Fe Trl",
    "sg:city":"Irving",
    "sg:classifiers":[
        {
            "category":"Professional",
            "subcategory":"Secretarial Services",
            "type":"Services"
        }
    ],
    "sg:phone":"+1 972 409 7047",
    "sg:postcode":"75063",
    "sg:province":"TX",
    "sg:tags":[
        "reporting",
        "word",
        "processing"
    ],
    "wof:name":"Quality Word Svcs",
    "wof:placetype":"venue"
},
  "geometry": {"coordinates":[-96.954379,32.935799],"type":"Point"}
}