{
  "type": "Feature",
  "properties": {
    "iso:country":"US",
    "sg:address":"4848 Research Dr",
    "sg:city":"San Antonio",
    "sg:classifiers":[
        {
            "category":"Building & Trades",
            "subcategory":"Equipment Rental",
            "type":"Services"
        }
    ],
    "sg:phone":"+1 210 697 9933",
    "sg:postcode":"78240",
    "sg:province":"TX",
    "sg:tags":[
        "medical",
        "retail",
        "durable",
        "rent"
    ],
    "wof:name":"MED MART",
    "wof:placetype":"venue"
},
  "geometry": {"coordinates":[-98.581957,29.538648],"type":"Point"}
}