{
  "type": "Feature",
  "properties": {
    "iso:country":"US",
    "sg:address":"1908 Broadway St",
    "sg:city":"Houston",
    "sg:classifiers":[
        {
            "category":"Recreation",
            "type":"Entertainment"
        }
    ],
    "sg:phone":"+1 281 996 1515",
    "sg:postcode":"77012",
    "sg:province":"TX",
    "sg:tags":[
        "stable"
    ],
    "wof:name":"Bay Area Equestrian Ctr",
    "wof:placetype":"venue"
},
  "geometry": {"coordinates":[-95.27816799999999,29.708859],"type":"Point"}
}