{
  "type": "Feature",
  "properties": {
    "iso:country":"US",
    "sg:address":"13626 Cannady Ct",
    "sg:city":"Houston",
    "sg:classifiers":[
        {
            "category":"Professional",
            "type":"Services"
        }
    ],
    "sg:phone":"+1 281 537 0674",
    "sg:postcode":"77069",
    "sg:province":"TX",
    "wof:name":"GRD Svc Inc",
    "wof:placetype":"venue"
},
  "geometry": {"coordinates":[-95.53766899999999,29.97659],"type":"Point"}
}