{
  "type": "Feature",
  "properties": {
    "iso:country":"US",
    "sg:address":"1507 Clay Ave",
    "sg:city":"Waco",
    "sg:classifiers":[
        {
            "category":"Shopping",
            "type":"Retail Goods"
        }
    ],
    "sg:phone":"+1 254 755 7647",
    "sg:postcode":"76706",
    "sg:province":"TX",
    "sg:tags":[
        "merchandise"
    ],
    "wof:name":"Billie Robert",
    "wof:placetype":"venue"
},
  "geometry": {"coordinates":[-97.136995,31.543907],"type":"Point"}
}