{
  "type": "Feature",
  "properties": {
    "iso:country":"US",
    "sg:address":"218 E Austin St",
    "sg:city":"New Braunfels",
    "sg:classifiers":[
        {
            "category":"Shopping",
            "subcategory":"Optical Goods",
            "type":"Retail Goods"
        }
    ],
    "sg:phone":"+1 830 625 2015",
    "sg:postcode":"78130",
    "sg:province":"TX",
    "wof:name":"Realeyes Optical",
    "wof:placetype":"venue"
},
  "geometry": {"coordinates":[-98.12220600000001,29.717285],"type":"Point"}
}