{
  "type": "Feature",
  "properties": {
    "iso:country":"US",
    "sg:address":"7224 Forest Hill Dr",
    "sg:city":"Fort Worth",
    "sg:classifiers":[
        {
            "category":"Organizations",
            "subcategory":"Religious Organization",
            "type":"Services"
        }
    ],
    "sg:phone":"+1 817 293 8499",
    "sg:postcode":"76119",
    "sg:province":"TX",
    "sg:tags":[
        "church"
    ],
    "wof:name":"Forest Hills Seventh Day Adven",
    "wof:placetype":"venue"
},
  "geometry": {"coordinates":[-97.269999,32.651803],"type":"Point"}
}