{
  "type": "Feature",
  "properties": {
    "iso:country":"US",
    "sg:address":"5400 Brodie Lane Suite 500",
    "sg:city":"Sunset Valley",
    "sg:classifiers":[
        {
            "category":"Shopping",
            "subcategory":"Department Store",
            "type":"Retail Goods"
        }
    ],
    "sg:phone":"+1 512 892 2874",
    "sg:postcode":"78745",
    "sg:province":"TX",
    "sg:website":"www.rossstores.com",
    "wof:name":"Ross Dress For Less",
    "wof:placetype":"venue"
},
  "geometry": {"coordinates":[-97.821611,30.227786],"type":"Point"}
}