{
  "type": "Feature",
  "properties": {
    "iso:country":"US",
    "sg:address":"10842 Braun Rd",
    "sg:city":"San Antonio",
    "sg:classifiers":[
        {
            "category":"Social Services",
            "type":"Services"
        }
    ],
    "sg:phone":"+1 210 688 2188",
    "sg:postcode":"78254",
    "sg:province":"TX",
    "sg:tags":[
        "shelter",
        "woman",
        "for",
        "child"
    ],
    "wof:name":"Rainbow Hse For Women Children",
    "wof:placetype":"venue"
},
  "geometry": {"coordinates":[-98.705626,29.541825],"type":"Point"}
}