{
  "type": "Feature",
  "properties": {
    "iso:country":"US",
    "sg:address":"4325 Red Bluff Rd",
    "sg:city":"Pasadena",
    "sg:classifiers":[
        {
            "category":"Food & Beverages",
            "subcategory":"Liquor & Beverages",
            "type":"Retail Goods"
        }
    ],
    "sg:phone":"+1 281 479 0129",
    "sg:postcode":"77503",
    "sg:province":"TX",
    "sg:tags":[
        "alcoholic"
    ],
    "wof:name":"Super A",
    "wof:placetype":"venue"
},
  "geometry": {"coordinates":[-95.143123,29.677141],"type":"Point"}
}