{
  "type": "Feature",
  "properties": {
    "iso:country":"US",
    "sg:address":"2629 E Grauwyler Rd",
    "sg:city":"Irving",
    "sg:classifiers":[
        {
            "category":"Building & Trades",
            "subcategory":"Construction",
            "type":"Services"
        }
    ],
    "sg:phone":"+1 972 871 8300",
    "sg:postcode":"75061",
    "sg:province":"TX",
    "sg:tags":[
        "general",
        "contractor"
    ],
    "wof:name":"Construction Concepts Inc",
    "wof:placetype":"venue"
},
  "geometry": {"coordinates":[-96.899299,32.831012],"type":"Point"}
}