{
  "type": "Feature",
  "properties": {
    "iso:country":"US",
    "sg:address":"237 Industrial Blvd",
    "sg:city":"Graham",
    "sg:classifiers":[
        {
            "category":"Mining & Drilling",
            "type":"Manufacturing & Wholesale Goods"
        }
    ],
    "sg:phone":"+1 940 521 0915",
    "sg:postcode":"76426",
    "sg:province":"TX",
    "sg:tags":[
        "field",
        "oil"
    ],
    "wof:name":"Parker Tool Co",
    "wof:placetype":"venue"
},
  "geometry": {"coordinates":[-97.752205,33.193991],"type":"Point"}
}