{
  "type": "Feature",
  "properties": {
    "iso:country":"US",
    "sg:address":"4318 Stagecoach Trl",
    "sg:city":"Temple",
    "sg:classifiers":[
        {
            "category":"Professional",
            "subcategory":"Accounting & Tax Preparation",
            "type":"Services"
        }
    ],
    "sg:phone":"+1 254 773 9915",
    "sg:postcode":"76502",
    "sg:province":"TX",
    "wof:name":"Rapid Recovery",
    "wof:placetype":"venue"
},
  "geometry": {"coordinates":[-97.381533,31.061387],"type":"Point"}
}