{
  "type": "Feature",
  "properties": {
    "iso:country":"US",
    "sg:address":"6618 Sitio del Rio Blvd E10",
    "sg:city":"Austin",
    "sg:classifiers":[
        {
            "category":"Banks & Credit Unions",
            "subcategory":"Investment Brokerage",
            "type":"Services"
        }
    ],
    "sg:phone":"+1 512 852 2226",
    "sg:postcode":"78730",
    "sg:province":"TX",
    "sg:tags":[
        "security"
    ],
    "wof:name":"Raymond James",
    "wof:placetype":"venue"
},
  "geometry": {"coordinates":[-97.842358,30.391563],"type":"Point"}
}