{
  "type": "Feature",
  "properties": {
    "iso:country":"US",
    "sg:address":"113 Texas Ave",
    "sg:city":"San Marcos",
    "sg:classifiers":[
        {
            "category":"Home & Garden",
            "subcategory":"Carpets & Floor Coverings",
            "type":"Retail Goods"
        }
    ],
    "sg:phone":"+1 512 392 6903",
    "sg:postcode":"78666",
    "sg:province":"TX",
    "sg:tags":[
        "vinyl"
    ],
    "wof:name":"Gabriel & Son Vinyl Top Spec",
    "wof:placetype":"venue"
},
  "geometry": {"coordinates":[-97.95360100000001,29.859412],"type":"Point"}
}