{
  "type": "Feature",
  "properties": {
    "iso:country":"US",
    "sg:address":"1336 Willow Glen Cir",
    "sg:city":"Fort Worth",
    "sg:classifiers":[
        {
            "category":"Professional",
            "subcategory":"Accounting & Tax Preparation",
            "type":"Services"
        }
    ],
    "sg:phone":"+1 817 293 2590",
    "sg:postcode":"76134",
    "sg:province":"TX",
    "sg:tags":[
        "return",
        "filing"
    ],
    "wof:name":"Mutual Income Tax Svc",
    "wof:placetype":"venue"
},
  "geometry": {"coordinates":[-97.33920000000001,32.63515],"type":"Point"}
}