{
  "type": "Feature",
  "properties": {
    "iso:country":"US",
    "sg:address":"1220 Mockingbird Ln",
    "sg:city":"Sulphur Springs",
    "sg:classifiers":[
        {
            "category":"Restaurant",
            "type":"Food & Drink"
        }
    ],
    "sg:phone":"+1 903 885 6456",
    "sg:postcode":"75482",
    "sg:province":"TX",
    "sg:tags":[
        "eating"
    ],
    "wof:name":"Bodacious Barbecue",
    "wof:placetype":"venue"
},
  "geometry": {"coordinates":[-95.594971,33.119599],"type":"Point"}
}