{
  "type": "Feature",
  "properties": {
    "iso:country":"US",
    "sg:address":"605 Bluebell Rd",
    "sg:city":"Kerrville",
    "sg:classifiers":[
        {
            "category":"Organizations",
            "subcategory":"Religious Organization",
            "type":"Services"
        }
    ],
    "sg:phone":"+1 830 896 6167",
    "sg:postcode":"78028",
    "sg:province":"TX",
    "sg:tags":[
        "church"
    ],
    "wof:name":"Trinity Baptist Church",
    "wof:placetype":"venue"
},
  "geometry": {"coordinates":[-99.15394499999999,30.06367],"type":"Point"}
}