{
  "type": "Feature",
  "properties": {
    "iso:country":"US",
    "sg:address":"10000 N Central Expy Ste 1400",
    "sg:city":"Dallas",
    "sg:classifiers":[
        {
            "category":"Professional",
            "subcategory":"Accounting & Tax Preparation",
            "type":"Services"
        }
    ],
    "sg:phone":"+1 214 329 9543",
    "sg:postcode":"75231",
    "sg:province":"TX",
    "sg:tags":[
        "accountant"
    ],
    "sg:website":"www.ablonco.com",
    "wof:name":"Ablon and Co Pllc",
    "wof:placetype":"venue"
},
  "geometry": {"coordinates":[-96.769699,32.8834],"type":"Point"}
}