{
  "type": "Feature",
  "properties": {
    "iso:country":"US",
    "sg:address":"4401 9th St",
    "sg:city":"Lubbock",
    "sg:classifiers":[
        {
            "category":"Insurance",
            "subcategory":"Insurance Agent",
            "type":"Services"
        }
    ],
    "sg:phone":"+1 806 796 2469",
    "sg:postcode":"79416",
    "sg:province":"TX",
    "wof:name":"AFLAC",
    "wof:placetype":"venue"
},
  "geometry": {"coordinates":[-101.906508,33.587771],"type":"Point"}
}