{
  "type": "Feature",
  "properties": {
    "iso:country":"US",
    "sg:address":"5302 Singleton Blvd",
    "sg:city":"Dallas",
    "sg:classifiers":[
        {
            "category":"Insurance",
            "subcategory":"Insurance Agent",
            "type":"Services"
        }
    ],
    "sg:phone":"+1 214 819 9844",
    "sg:postcode":"75212",
    "sg:province":"TX",
    "wof:name":"Servi Mex Insurance Agency",
    "wof:placetype":"venue"
},
  "geometry": {"coordinates":[-96.90974799999999,32.778508],"type":"Point"}
}