{
  "type": "Feature",
  "properties": {
    "iso:country":"US",
    "sg:address":"2708 Lakeside",
    "sg:city":"Mc Kinney",
    "sg:classifiers":[
        {
            "category":"Professional",
            "subcategory":"Management & Consulting",
            "type":"Services"
        }
    ],
    "sg:phone":"+1 972 569 9006",
    "sg:postcode":"75070",
    "sg:province":"TX",
    "wof:name":"Accord Group The",
    "wof:placetype":"venue"
},
  "geometry": {"coordinates":[-96.64981400000001,33.180661],"type":"Point"}
}