{
  "type": "Feature",
  "properties": {
    "iso:country":"US",
    "sg:address":"11705 River Oaks Trl",
    "sg:city":"Austin",
    "sg:classifiers":[
        {
            "category":"Banks & Credit Unions",
            "subcategory":"Bank",
            "type":"Services"
        }
    ],
    "sg:phone":"+1 512 719 5059",
    "sg:postcode":"78753",
    "sg:province":"TX",
    "sg:tags":[
        "broker",
        "mortgage"
    ],
    "wof:name":"Anchor Mortgage Lending",
    "wof:placetype":"venue"
},
  "geometry": {"coordinates":[-97.664993,30.381864],"type":"Point"}
}