{
  "type": "Feature",
  "properties": {
    "iso:country":"US",
    "sg:address":"1405 Sheffield Blvd",
    "sg:city":"Houston",
    "sg:classifiers":[
        {
            "category":"Retail",
            "subcategory":"Auto Repair",
            "type":"Services"
        }
    ],
    "sg:phone":"+1 713 451 5902",
    "sg:postcode":"77015",
    "sg:province":"TX",
    "wof:name":"Taller Tamaulipas",
    "wof:placetype":"venue"
},
  "geometry": {"coordinates":[-95.205101,29.7652],"type":"Point"}
}