{
  "type": "Feature",
  "properties": {
    "iso:country":"US",
    "sg:address":"120 Orchard Ln",
    "sg:city":"Rockwall",
    "sg:classifiers":[
        {
            "category":"Wholesale",
            "subcategory":"Vending Machines",
            "type":"Manufacturing & Wholesale Goods"
        }
    ],
    "sg:phone":"+1 972 771 0878",
    "sg:postcode":"75087",
    "sg:province":"TX",
    "sg:tags":[
        "operator"
    ],
    "wof:name":"Labarres Vending",
    "wof:placetype":"venue"
},
  "geometry": {"coordinates":[-96.430262,32.952449],"type":"Point"}
}