{
  "type": "Feature",
  "properties": {
    "iso:country":"US",
    "sg:address":"1016 Murdock Rd",
    "sg:city":"Dallas",
    "sg:classifiers":[
        {
            "category":"Food & Beverages",
            "subcategory":"Groceries & Convenience Stores",
            "type":"Retail Goods"
        }
    ],
    "sg:phone":"+1 214 391 7267",
    "sg:postcode":"75217",
    "sg:province":"TX",
    "sg:tags":[
        "grocer"
    ],
    "wof:name":"Hilda's Grocery",
    "wof:placetype":"venue"
},
  "geometry": {"coordinates":[-96.682999,32.700802],"type":"Point"}
}