{
  "type": "Feature",
  "properties": {
    "iso:country":"US",
    "sg:address":"3311 Sunlite St",
    "sg:city":"Amarillo",
    "sg:classifiers":[
        {
            "category":"Professional",
            "subcategory":"Lawyer & Legal Services",
            "type":"Services"
        }
    ],
    "sg:phone":"+1 806 467 1235",
    "sg:postcode":"79106",
    "sg:province":"TX",
    "wof:name":"Charles G Bouton",
    "wof:placetype":"venue"
},
  "geometry": {"coordinates":[-101.88946199999999,35.176609],"type":"Point"}
}