{
  "type": "Feature",
  "properties": {
    "iso:country":"US",
    "sg:address":"11994 Cedar Ln",
    "sg:city":"Conroe",
    "sg:classifiers":[
        {
            "category":"Arts & Performance",
            "subcategory":"Dance",
            "type":"Entertainment"
        }
    ],
    "sg:phone":"+1 936 445 2155",
    "sg:postcode":"77303",
    "sg:province":"TX",
    "sg:tags":[
        "instruction",
        "dancing"
    ],
    "wof:name":"Carol Elaine Bilbrey Rn",
    "wof:placetype":"venue"
},
  "geometry": {"coordinates":[-95.368605,30.409929],"type":"Point"}
}