{
  "type": "Feature",
  "properties": {
    "iso:country":"US",
    "sg:address":"404 Memorial Dr",
    "sg:city":"Victoria",
    "sg:classifiers":[
        {
            "category":"Organizations",
            "subcategory":"Community Association",
            "type":"Services"
        }
    ],
    "sg:phone":"+1 361 575 5777",
    "sg:postcode":"77901",
    "sg:province":"TX",
    "sg:tags":[
        "club"
    ],
    "wof:name":"Victoria Horseman's Club",
    "wof:placetype":"venue"
},
  "geometry": {"coordinates":[-97.02184800000001,28.812348],"type":"Point"}
}