{
  "type": "Feature",
  "properties": {
    "iso:country":"US",
    "sg:address":"5500 E Loop 820 S",
    "sg:city":"Fort Worth",
    "sg:classifiers":[
        {
            "category":"Real Estate",
            "subcategory":"Real Estate Agent",
            "type":"Services"
        }
    ],
    "sg:phone":"+1 817 483 7680",
    "sg:postcode":"76119",
    "sg:province":"TX",
    "wof:name":"Optimum Realty",
    "wof:placetype":"venue"
},
  "geometry": {"coordinates":[-97.241045,32.676614],"type":"Point"}
}