{
  "type": "Feature",
  "properties": {
    "iso:country":"US",
    "sg:address":"2979 Saint Paul Rd",
    "sg:city":"Venus",
    "sg:classifiers":[
        {
            "category":"Building & Trades",
            "subcategory":"Construction",
            "type":"Services"
        }
    ],
    "sg:phone":"+1 817 319 2609",
    "sg:postcode":"76084",
    "sg:province":"TX",
    "sg:tags":[
        "system",
        "specialty",
        "heating",
        "contractor",
        "air conditioning"
    ],
    "wof:name":"Bartlett Air Conditioning And Heating",
    "wof:placetype":"venue"
},
  "geometry": {"coordinates":[-97.09217599999999,32.512752],"type":"Point"}
}