{
  "type": "Feature",
  "properties": {
    "iso:country":"US",
    "sg:address":"11837 Judd Ct",
    "sg:city":"Dallas",
    "sg:classifiers":[
        {
            "category":"Manufacturing",
            "subcategory":"Wood Products",
            "type":"Manufacturing & Wholesale Goods"
        },
        {
            "category":"Wholesale",
            "subcategory":"Home Furnishings",
            "type":"Manufacturing & Wholesale Goods"
        }
    ],
    "sg:phone":"+1 972 234 4330",
    "sg:postcode":"75243",
    "sg:province":"TX",
    "sg:tags":[
        "picture",
        "frame",
        "household",
        "mfg"
    ],
    "wof:name":"Jan Sevadjian Designs",
    "wof:placetype":"venue"
},
  "geometry": {"coordinates":[-96.74315,32.910362],"type":"Point"}
}