{
  "type": "Feature",
  "properties": {
    "iso:country":"US",
    "sg:address":"5210 Merlin Dr",
    "sg:city":"San Antonio",
    "sg:classifiers":[
        {
            "category":"Building & Trades",
            "subcategory":"Pest Control",
            "type":"Services"
        }
    ],
    "sg:phone":"+1 210 653 0730",
    "sg:postcode":"78218",
    "sg:province":"TX",
    "sg:tags":[
        "structure"
    ],
    "wof:name":"Steve Scott Pest Control",
    "wof:placetype":"venue"
},
  "geometry": {"coordinates":[-98.387935,29.500294],"type":"Point"}
}