{
  "type": "Feature",
  "properties": {
    "iso:country":"US",
    "sg:address":"13511 Primwood St",
    "sg:city":"San Antonio",
    "sg:classifiers":[
        {
            "category":"Shopping",
            "subcategory":"Clothing, Apparel, & Fashions",
            "type":"Retail Goods"
        }
    ],
    "sg:phone":"+1 210 637 7046",
    "sg:postcode":"78233",
    "sg:province":"TX",
    "sg:tags":[
        "dressmaker"
    ],
    "wof:name":"Lisa's Dressmaking Alterations",
    "wof:placetype":"venue"
},
  "geometry": {"coordinates":[-98.377821,29.563194],"type":"Point"}
}