{
  "type": "Feature",
  "properties": {
    "iso:country":"US",
    "sg:address":"5308 Rio Grande Dr",
    "sg:city":"Midland",
    "sg:classifiers":[
        {
            "category":"Retail",
            "subcategory":"Laundry & Dry Cleaning",
            "type":"Services"
        }
    ],
    "sg:phone":"+1 432 699 1649",
    "sg:postcode":"79707",
    "sg:province":"TX",
    "sg:tags":[
        "cleaners",
        "rug",
        "carpet"
    ],
    "wof:name":"Steam Clean",
    "wof:placetype":"venue"
},
  "geometry": {"coordinates":[-102.15903900000001,32.020238],"type":"Point"}
}