{
  "type": "Feature",
  "properties": {
    "iso:country":"US",
    "sg:address":"309 Frazier St",
    "sg:city":"Tow",
    "sg:classifiers":[
        {
            "category":"Building & Trades",
            "subcategory":"Construction",
            "type":"Services"
        }
    ],
    "sg:phone":"+1 325 379 9681",
    "sg:postcode":"78672",
    "sg:province":"TX",
    "sg:tags":[
        "water",
        "well",
        "drilling"
    ],
    "wof:name":"Highland Drilling Inc",
    "wof:placetype":"venue"
},
  "geometry": {"coordinates":[-98.451587,30.861293],"type":"Point"}
}