{
  "type": "Feature",
  "properties": {
    "iso:country":"US",
    "sg:address":"6018 W 34th St",
    "sg:city":"Houston",
    "sg:classifiers":[
        {
            "category":"Freight",
            "type":"Transportation"
        }
    ],
    "sg:phone":"+1 713 956 2788",
    "sg:postcode":"77092",
    "sg:province":"TX",
    "sg:tags":[
        "delivery"
    ],
    "wof:name":"Action Crating Svc Inc",
    "wof:placetype":"venue"
},
  "geometry": {"coordinates":[-95.477442,29.819357],"type":"Point"}
}