{
  "type": "Feature",
  "properties": {
    "iso:country":"US",
    "sg:address":"1304 E Adams St",
    "sg:city":"Brownsville",
    "sg:classifiers":[
        {
            "category":"Shopping",
            "subcategory":"Department Store",
            "type":"Retail Goods"
        }
    ],
    "sg:phone":"+1 956 546 4133",
    "sg:postcode":"78520",
    "sg:province":"TX",
    "wof:name":"La Casa Del Nylon",
    "wof:placetype":"venue"
},
  "geometry": {"coordinates":[-97.495278,25.900865],"type":"Point"}
}