{
  "type": "Feature",
  "properties": {
    "iso:country":"US",
    "sg:address":"8 Lacewood Lane",
    "sg:city":"Houston",
    "sg:classifiers":[
        {
            "category":"Communications",
            "type":"Services"
        },
        {
            "category":"Utilities",
            "type":"Services"
        }
    ],
    "sg:phone":"+1 877 754 6493",
    "sg:postcode":"77024",
    "sg:province":"TX",
    "sg:tags":[
        "web",
        "provider",
        "design",
        "internet"
    ],
    "sg:website":"www.slingshothost.com",
    "wof:name":"Slingshot Communications",
    "wof:placetype":"venue"
},
  "geometry": {"coordinates":[-95.510092,29.759768],"type":"Point"}
}