{
  "type": "Feature",
  "properties": {
    "iso:country":"US",
    "sg:address":"1451 S Cherry Ln",
    "sg:city":"Fort Worth",
    "sg:classifiers":[
        {
            "category":"Utilities",
            "subcategory":"Mobile Phone",
            "type":"Services"
        },
        {
            "category":"Shopping",
            "type":"Retail Goods"
        }
    ],
    "sg:phone":"+1 817 367 3597",
    "sg:postcode":"76108",
    "sg:province":"TX",
    "sg:tags":[
        "communication",
        "merchandise",
        "radiotelephone",
        "cellular",
        "telephone"
    ],
    "wof:name":"Wireless Retail Inc",
    "wof:placetype":"venue"
},
  "geometry": {"coordinates":[-97.451674,32.744986],"type":"Point"}
}