{
  "type": "Feature",
  "properties": {
    "iso:country":"US",
    "sg:address":"8730 Timber Cloud St",
    "sg:city":"San Antonio",
    "sg:classifiers":[
        {
            "category":"Shopping",
            "subcategory":"Jewelry",
            "type":"Retail Goods"
        }
    ],
    "sg:phone":"+1 210 647 4815",
    "sg:postcode":"78251",
    "sg:province":"TX",
    "wof:name":"Mayan Treasures",
    "wof:placetype":"venue"
},
  "geometry": {"coordinates":[-98.664551,29.466883],"type":"Point"}
}