{
  "type": "Feature",
  "properties": {
    "iso:country":"US",
    "sg:address":"7726 S Howton St",
    "sg:city":"Houston",
    "sg:classifiers":[
        {
            "category":"Building & Trades",
            "subcategory":"Construction",
            "type":"Services"
        }
    ],
    "sg:phone":"+1 713 674 3397",
    "sg:postcode":"77028",
    "sg:province":"TX",
    "sg:tags":[
        "contractor"
    ],
    "wof:name":"Rhodes Mobile Pressure",
    "wof:placetype":"venue"
},
  "geometry": {"coordinates":[-95.28634099999999,29.818118],"type":"Point"}
}