{
  "type": "Feature",
  "properties": {
    "iso:country":"US",
    "sg:address":"1521 S Flores St",
    "sg:city":"San Antonio",
    "sg:classifiers":[
        {
            "category":"Restaurant",
            "type":"Food & Drink"
        }
    ],
    "sg:phone":"+1 210 271 9533",
    "sg:postcode":"78204",
    "sg:province":"TX",
    "sg:tags":[
        "eating"
    ],
    "wof:name":"LA Parrilla Azteca",
    "wof:placetype":"venue"
},
  "geometry": {"coordinates":[-98.5017,29.408182],"type":"Point"}
}