{
  "type": "Feature",
  "properties": {
    "iso:country":"US",
    "sg:address":"3305 Pleasant Valley Ln",
    "sg:city":"Arlington",
    "sg:classifiers":[
        {
            "category":"Arts & Performance",
            "subcategory":"Theater",
            "type":"Entertainment"
        }
    ],
    "sg:phone":"+1 817 468 0070",
    "sg:postcode":"76015",
    "sg:province":"TX",
    "sg:tags":[
        "television",
        "program",
        "producer"
    ],
    "wof:name":"Tel Fax Inc",
    "wof:placetype":"venue"
},
  "geometry": {"coordinates":[-97.12212599999999,32.692329],"type":"Point"}
}