{
  "type": "Feature",
  "properties": {
    "iso:country":"US",
    "sg:address":"12715 Telge Rd",
    "sg:city":"Cypress",
    "sg:classifiers":[
        {
            "category":"Professional",
            "subcategory":"Advertising",
            "type":"Services"
        }
    ],
    "sg:phone":"+1 281 256 4100",
    "sg:postcode":"77429",
    "sg:province":"TX",
    "sg:tags":[
        "parcel"
    ],
    "wof:name":"Eagle Franchise Systems Inc",
    "wof:placetype":"venue"
},
  "geometry": {"coordinates":[-95.650273,29.961349],"type":"Point"}
}