{
  "type": "Feature",
  "properties": {
    "iso:country":"US",
    "sg:address":"529 Pinar del Rio Dr",
    "sg:city":"El Paso",
    "sg:classifiers":[
        {
            "category":"Professional",
            "subcategory":"Management & Consulting",
            "type":"Services"
        }
    ],
    "sg:phone":"+1 915 587 0015",
    "sg:postcode":"79932",
    "sg:province":"TX",
    "sg:tags":[
        "consultant"
    ],
    "wof:name":"BMB Consultants",
    "wof:placetype":"venue"
},
  "geometry": {"coordinates":[-106.59542,31.862307],"type":"Point"}
}