{
  "type": "Feature",
  "properties": {
    "iso:country":"US",
    "sg:address":"2304 Clifford St",
    "sg:city":"Alvin",
    "sg:classifiers":[
        {
            "category":"Professional",
            "subcategory":"Business Services",
            "type":"Services"
        }
    ],
    "sg:phone":"+1 281 331 2811",
    "sg:postcode":"77511",
    "sg:province":"TX",
    "wof:name":"Gina L Davis",
    "wof:placetype":"venue"
},
  "geometry": {"coordinates":[-95.22636199999999,29.440602],"type":"Point"}
}