{
  "type": "Feature",
  "properties": {
    "iso:country":"US",
    "sg:address":"4018 Bikini Dr",
    "sg:city":"San Antonio",
    "sg:classifiers":[
        {
            "category":"Organizations",
            "subcategory":"Membership Organization",
            "type":"Services"
        }
    ],
    "sg:phone":"+1 210 656 3117",
    "sg:postcode":"78218",
    "sg:province":"TX",
    "wof:name":"Camerata San Antonio",
    "wof:placetype":"venue"
},
  "geometry": {"coordinates":[-98.41548299999999,29.493203],"type":"Point"}
}