{
  "type": "Feature",
  "properties": {
    "iso:country":"US",
    "sg:address":"11558 Warner Rd",
    "sg:city":"Cleveland",
    "sg:classifiers":[
        {
            "category":"Professional",
            "subcategory":"Management & Consulting",
            "type":"Services"
        }
    ],
    "sg:phone":"+1 281 592 3871",
    "sg:postcode":"77328",
    "sg:province":"TX",
    "sg:tags":[
        "business"
    ],
    "wof:name":"Akt Consulting",
    "wof:placetype":"venue"
},
  "geometry": {"coordinates":[-95.149265,30.276142],"type":"Point"}
}