{
  "type": "Feature",
  "properties": {
    "iso:country":"US",
    "sg:address":"4420 Village Oak Dr",
    "sg:city":"Waco",
    "sg:classifiers":[
        {
            "category":"Wholesale",
            "subcategory":"Chemicals & Plastics",
            "type":"Manufacturing & Wholesale Goods"
        }
    ],
    "sg:phone":"+1 254 772 3712",
    "sg:postcode":"76710",
    "sg:province":"TX",
    "wof:name":"Beyond Border",
    "wof:placetype":"venue"
},
  "geometry": {"coordinates":[-97.195009,31.5647],"type":"Point"}
}