{
  "type": "Feature",
  "properties": {
    "iso:country":"US",
    "sg:address":"4545 Fireman's Ln",
    "sg:city":"Lone Oak",
    "sg:classifiers":[
        {
            "category":"Farming",
            "subcategory":"Livestock Farm",
            "type":"Manufacturing & Wholesale Goods"
        }
    ],
    "sg:phone":"+1 903 662 5674",
    "sg:postcode":"75453",
    "sg:province":"TX",
    "sg:tags":[
        "beef",
        "feedlot",
        "cattle"
    ],
    "wof:name":"Donald Isenburg",
    "wof:placetype":"venue"
},
  "geometry": {"coordinates":[-95.873103,33.016998],"type":"Point"}
}