{
  "type": "Feature",
  "properties": {
    "iso:country":"US",
    "sg:address":"109 Ford St",
    "sg:city":"Eagle Pass",
    "sg:classifiers":[
        {
            "category":"Shopping",
            "subcategory":"Used Merchandise",
            "type":"Retail Goods"
        }
    ],
    "sg:phone":"+1 830 773 7210",
    "sg:postcode":"78852",
    "sg:province":"TX",
    "sg:tags":[
        "shop",
        "thrift"
    ],
    "wof:name":"Gonzalez Segunda",
    "wof:placetype":"venue"
},
  "geometry": {"coordinates":[-100.50746599999999,28.709374],"type":"Point"}
}