{
  "type": "Feature",
  "properties": {
    "iso:country":"US",
    "sg:address":"4601 Gila Bend Ln",
    "sg:city":"Fort Worth",
    "sg:classifiers":[
        {
            "category":"Professional",
            "type":"Services"
        }
    ],
    "sg:phone":"+1 817 498 7516",
    "sg:postcode":"76137",
    "sg:province":"TX",
    "wof:name":"Billy Pye Hockey Inc",
    "wof:placetype":"venue"
},
  "geometry": {"coordinates":[-97.285043,32.886404],"type":"Point"}
}