{
  "type": "Feature",
  "properties": {
    "iso:country":"US",
    "sg:address":"1910 Park St",
    "sg:city":"Houston",
    "sg:phone":"+1 713 523 0650",
    "sg:postcode":"77019",
    "sg:province":"TX",
    "sg:tags":[
        "farm"
    ],
    "wof:name":"Camille Waters",
    "wof:placetype":"venue"
},
  "geometry": {"coordinates":[-95.403036,29.74831],"type":"Point"}
}