{
  "type": "Feature",
  "properties": {
    "iso:country":"US",
    "sg:address":"4021 Preston Rd",
    "sg:city":"Plano",
    "sg:classifiers":[
        {
            "category":"Restaurant",
            "type":"Food & Drink"
        }
    ],
    "sg:menulink":"http://www.allmenus.com/tx/plano/41260-which-wich/menu/",
    "sg:phone":"+1 972 378 9422",
    "sg:postcode":"75093",
    "sg:province":"TX",
    "sg:tags":[
        "wrap",
        "american",
        "sandwich"
    ],
    "wof:name":"Which Wich",
    "wof:placetype":"venue"
},
  "geometry": {"coordinates":[-96.794292,33.051492],"type":"Point"}
}