{
  "type": "Feature",
  "properties": {
    "iso:country":"US",
    "sg:address":"11211 Kingsgate Dr",
    "sg:city":"Austin",
    "sg:classifiers":[
        {
            "category":"Arts & Performance",
            "subcategory":"Theater",
            "type":"Entertainment"
        }
    ],
    "sg:phone":"+1 512 291 5576",
    "sg:postcode":"78748",
    "sg:province":"TX",
    "sg:tags":[
        "group"
    ],
    "wof:name":"Omniversalata Entertainment LL",
    "wof:placetype":"venue"
},
  "geometry": {"coordinates":[-97.839769,30.159275],"type":"Point"}
}