{
  "type": "Feature",
  "properties": {
    "iso:country":"US",
    "sg:address":"1003 Narcille St",
    "sg:city":"Baytown",
    "sg:classifiers":[
        {
            "category":"Wholesale",
            "subcategory":"Electrical",
            "type":"Manufacturing & Wholesale Goods"
        }
    ],
    "sg:phone":"+1 281 773 0871",
    "sg:postcode":"77520",
    "sg:province":"TX",
    "sg:tags":[
        "electronic"
    ],
    "wof:name":"Golden Electronics & Trade",
    "wof:placetype":"venue"
},
  "geometry": {"coordinates":[-94.94270400000001,29.731792],"type":"Point"}
}