{
  "type": "Feature",
  "properties": {
    "iso:country":"US",
    "sg:address":"618 Ernest St",
    "sg:city":"Fort Worth",
    "sg:classifiers":[
        {
            "category":"Arts & Performance",
            "subcategory":"Theater",
            "type":"Entertainment"
        }
    ],
    "sg:phone":"+1 817 531 2324",
    "sg:postcode":"76105",
    "sg:province":"TX",
    "sg:tags":[
        "group"
    ],
    "wof:name":"Threadneedle Street",
    "wof:placetype":"venue"
},
  "geometry": {"coordinates":[-97.292633,32.738643],"type":"Point"}
}