{
  "type": "Feature",
  "properties": {
    "iso:country":"US",
    "sg:address":"25739 Green River Dr",
    "sg:city":"San Antonio",
    "sg:classifiers":[
        {
            "category":"Professional",
            "type":"Services"
        }
    ],
    "sg:phone":"+1 210 497 5262",
    "sg:postcode":"78260",
    "sg:province":"TX",
    "wof:name":"Lj Designs",
    "wof:placetype":"venue"
},
  "geometry": {"coordinates":[-98.508988,29.684182],"type":"Point"}
}