{
  "type": "Feature",
  "properties": {
    "iso:country":"US",
    "sg:address":"1509 Duke Ave",
    "sg:city":"Mcallen",
    "sg:classifiers":[
        {
            "category":"Health Services",
            "subcategory":"Nursing And Care Facility",
            "type":"Services"
        }
    ],
    "sg:phone":"+1 956 618 3117",
    "sg:postcode":"78504",
    "sg:province":"TX",
    "sg:tags":[
        "nurse",
        "practice-arnp",
        "nurses-advanced"
    ],
    "wof:name":"Shumway Ctr Co Pc",
    "wof:placetype":"venue"
},
  "geometry": {"coordinates":[-98.22354199999999,26.276839],"type":"Point"}
}