{
  "type": "Feature",
  "properties": {
    "iso:country":"US",
    "sg:address":"546 Scates Dr",
    "sg:city":"San Antonio",
    "sg:classifiers":[
        {
            "category":"Personal",
            "subcategory":"Beauty Salon",
            "type":"Services"
        }
    ],
    "sg:phone":"+1 210 435 6499",
    "sg:postcode":"78227",
    "sg:province":"TX",
    "sg:tags":[
        "shop"
    ],
    "wof:name":"Styles & Sounds",
    "wof:placetype":"venue"
},
  "geometry": {"coordinates":[-98.660359,29.401094],"type":"Point"}
}