{
  "type": "Feature",
  "properties": {
    "iso:country":"US",
    "sg:address":"903 W Main St",
    "sg:city":"Waxahachie",
    "sg:classifiers":[
        {
            "category":"Travel",
            "subcategory":"Hotels & Motels",
            "type":"Entertainment"
        }
    ],
    "sg:phone":"+1 972 923 0343",
    "sg:postcode":"75165",
    "sg:province":"TX",
    "sg:tags":[
        "breakfast",
        "operation",
        "bed",
        "accommodation"
    ],
    "wof:name":"Rosemary Mansion On Main St",
    "wof:placetype":"venue"
},
  "geometry": {"coordinates":[-96.85634400000001,32.391813],"type":"Point"}
}