{
  "type": "Feature",
  "properties": {
    "iso:country":"US",
    "sg:address":"5919 Forest Hill Dr",
    "sg:city":"Fort Worth",
    "sg:classifiers":[
        {
            "category":"Building & Trades",
            "subcategory":"Construction",
            "type":"Services"
        }
    ],
    "sg:phone":"+1 817 535 7835",
    "sg:postcode":"76119",
    "sg:province":"TX",
    "sg:tags":[
        "contractor"
    ],
    "wof:name":"Lester Enterprises",
    "wof:placetype":"venue"
},
  "geometry": {"coordinates":[-97.27524099999999,32.672003],"type":"Point"}
}