{
  "type": "Feature",
  "properties": {
    "iso:country":"US",
    "sg:address":"600 Wilcrest Dr Apt 47",
    "sg:city":"Houston",
    "sg:classifiers":[
        {
            "category":"Home & Garden",
            "subcategory":"Home Furnishings",
            "type":"Retail Goods"
        }
    ],
    "sg:phone":"+1 281 759 7320",
    "sg:postcode":"77042",
    "sg:province":"TX",
    "sg:tags":[
        "candle"
    ],
    "wof:name":"Desert Rain Inc",
    "wof:placetype":"venue"
},
  "geometry": {"coordinates":[-95.57643899999999,29.7598],"type":"Point"}
}