{
  "type": "Feature",
  "properties": {
    "iso:country":"US",
    "sg:address":"1200 Farragut St",
    "sg:city":"Laredo",
    "sg:classifiers":[
        {
            "category":"Restaurant",
            "type":"Food & Drink"
        }
    ],
    "sg:phone":"+1 956 725 0417",
    "sg:postcode":"78040",
    "sg:province":"TX",
    "wof:name":"Popeyes Chicken & Biscuits",
    "wof:placetype":"venue"
},
  "geometry": {"coordinates":[-99.508461,27.505682],"type":"Point"}
}