{
  "type": "Feature",
  "properties": {
    "iso:country":"US",
    "sg:address":"287 Oaklane St",
    "sg:city":"New Braunfels",
    "sg:classifiers":[
        {
            "category":"Building & Trades",
            "subcategory":"Construction",
            "type":"Services"
        }
    ],
    "sg:phone":"+1 830 899 2578",
    "sg:postcode":"78133",
    "sg:province":"TX",
    "sg:tags":[
        "house"
    ],
    "wof:name":"Lonestar Home Improvements",
    "wof:placetype":"venue"
},
  "geometry": {"coordinates":[-98.297911,29.863327],"type":"Point"}
}