{
  "type": "Feature",
  "properties": {
    "iso:country":"US",
    "sg:address":"24106 Farm Hill Rd",
    "sg:city":"Spring",
    "sg:classifiers":[
        {
            "category":"Farming",
            "subcategory":"Livestock Farm",
            "type":"Manufacturing & Wholesale Goods"
        }
    ],
    "sg:phone":"+1 281 353 2935",
    "sg:postcode":"77373",
    "sg:province":"TX",
    "sg:tags":[
        "animal",
        "general"
    ],
    "wof:name":"Ej Ranch & Tractor Service",
    "wof:placetype":"venue"
},
  "geometry": {"coordinates":[-95.386759,30.061963],"type":"Point"}
}