{
  "type": "Feature",
  "properties": {
    "iso:country":"US",
    "sg:address":"3125 Inwood Rd",
    "sg:city":"Dallas",
    "sg:classifiers":[
        {
            "category":"Restaurant",
            "type":"Food & Drink"
        }
    ],
    "sg:menulink":"http://www.allmenus.com/tx/northeast/257966-big-als-smokehouse/menu/",
    "sg:phone":"+1 214 350 2649",
    "sg:postcode":"75235",
    "sg:province":"TX",
    "sg:tags":[
        "barbecue",
        "american"
    ],
    "wof:name":"Big Al's Smokehouse",
    "wof:placetype":"venue"
},
  "geometry": {"coordinates":[-96.83051399999999,32.826597],"type":"Point"}
}