{
  "type": "Feature",
  "properties": {
    "iso:country":"US",
    "sg:address":"3019 E Highway 82",
    "sg:city":"Gainesville",
    "sg:classifiers":[
        {
            "category":"Travel",
            "subcategory":"Hotels & Motels",
            "type":"Entertainment"
        }
    ],
    "sg:phone":"+1 940 668 6441",
    "sg:postcode":"76240",
    "sg:province":"TX",
    "wof:name":"Trails Inn Motel",
    "wof:placetype":"venue"
},
  "geometry": {"coordinates":[-97.180999,33.640969],"type":"Point"}
}