{
  "type": "Feature",
  "properties": {
    "iso:country":"US",
    "sg:address":"1206 Belmont St",
    "sg:city":"Gainesville",
    "sg:classifiers":[
        {
            "category":"Building & Trades",
            "subcategory":"Cleaning & Sanitation",
            "type":"Services"
        }
    ],
    "sg:phone":"+1 940 665 1439",
    "sg:postcode":"76240",
    "sg:province":"TX",
    "sg:tags":[
        "janitor"
    ],
    "wof:name":"J & J Janitors",
    "wof:placetype":"venue"
},
  "geometry": {"coordinates":[-97.12572299999999,33.6401],"type":"Point"}
}