{
  "type": "Feature",
  "properties": {
    "iso:country":"US",
    "sg:address":"13070 Cherokee Rd",
    "sg:city":"Sanger",
    "sg:classifiers":[
        {
            "category":"Freight",
            "type":"Transportation"
        }
    ],
    "sg:phone":"+1 940 458 5082",
    "sg:postcode":"76266",
    "sg:province":"TX",
    "sg:tags":[
        "operator",
        "local",
        "trucking"
    ],
    "wof:name":"Ronald M Cassity",
    "wof:placetype":"venue"
},
  "geometry": {"coordinates":[-97.16382299999999,33.405039],"type":"Point"}
}