{
  "type": "Feature",
  "properties": {
    "iso:country":"US",
    "sg:address":"204 S Main St",
    "sg:city":"Buda",
    "sg:classifiers":[
        {
            "category":"Professional",
            "subcategory":"Accounting & Tax Preparation",
            "type":"Services"
        }
    ],
    "sg:phone":"+1 512 295 4586",
    "sg:postcode":"78610",
    "sg:province":"TX",
    "sg:tags":[
        "bookkeeping",
        "general"
    ],
    "wof:name":"ABS Bookkeeping & Tax Svc",
    "wof:placetype":"venue"
},
  "geometry": {"coordinates":[-97.844414,30.078815],"type":"Point"}
}