{
  "type": "Feature",
  "properties": {
    "iso:country":"US",
    "sg:address":"98 Briggs Ave",
    "sg:city":"San Antonio",
    "sg:classifiers":[
        {
            "category":"Health Services",
            "subcategory":"Doctor",
            "type":"Services"
        }
    ],
    "sg:phone":"+1 210 927 1472",
    "sg:postcode":"78224",
    "sg:province":"TX",
    "sg:tags":[
        "medical"
    ],
    "wof:name":"Raul E Gaona",
    "wof:placetype":"venue"
},
  "geometry": {"coordinates":[-98.55043999999999,29.355016],"type":"Point"}
}