{
  "type": "Feature",
  "properties": {
    "iso:country":"US",
    "sg:address":"5803 Thunderbird St",
    "sg:city":"Lago Vista",
    "sg:classifiers":[
        {
            "category":"Government",
            "subcategory":"Post Office",
            "type":"Public Place"
        }
    ],
    "sg:phone":"+1 512 267 3187",
    "sg:postcode":"78645",
    "sg:province":"TX",
    "wof:name":"US Post Office",
    "wof:placetype":"venue"
},
  "geometry": {"coordinates":[-97.98798600000001,30.452469],"type":"Point"}
}