{
  "type": "Feature",
  "properties": {
    "iso:country":"US",
    "sg:address":"120 Farms Rd",
    "sg:city":"Mc Kinney",
    "sg:classifiers":[
        {
            "category":"Building & Trades",
            "subcategory":"Construction",
            "type":"Services"
        }
    ],
    "sg:phone":"+1 972 250 4502",
    "sg:postcode":"75071",
    "sg:province":"TX",
    "sg:tags":[
        "floor",
        "laying",
        "contractor"
    ],
    "wof:name":"Blast Off Floor Preparation",
    "wof:placetype":"venue"
},
  "geometry": {"coordinates":[-96.557782,33.214073],"type":"Point"}
}