{
  "type": "Feature",
  "properties": {
    "iso:country":"US",
    "sg:address":"1701 Castroville Rd",
    "sg:city":"San Antonio",
    "sg:classifiers":[
        {
            "category":"Bars & Pubs",
            "type":"Food & Drink"
        }
    ],
    "sg:phone":"+1 210 432 8449",
    "sg:postcode":"78237",
    "sg:province":"TX",
    "sg:tags":[
        "lounge",
        "cocktail"
    ],
    "wof:name":"J & A Lounge",
    "wof:placetype":"venue"
},
  "geometry": {"coordinates":[-98.56338100000001,29.414427],"type":"Point"}
}