{
  "type": "Feature",
  "properties": {
    "iso:country":"US",
    "sg:address":"13631 Ashridge Dr",
    "sg:city":"Dallas",
    "sg:classifiers":[
        {
            "category":"Professional",
            "subcategory":"Management & Consulting",
            "type":"Services"
        }
    ],
    "sg:phone":"+1 972 385 8878",
    "sg:postcode":"75240",
    "sg:province":"TX",
    "sg:tags":[
        "business"
    ],
    "wof:name":"Matthews Consultants Inc",
    "wof:placetype":"venue"
},
  "geometry": {"coordinates":[-96.78310999999999,32.934419],"type":"Point"}
}