{
  "type": "Feature",
  "properties": {
    "iso:country":"US",
    "sg:address":"7401 Spring Lea Way",
    "sg:city":"Fort Worth",
    "sg:classifiers":[
        {
            "category":"Insurance",
            "subcategory":"Insurance Agent",
            "type":"Services"
        }
    ],
    "sg:phone":"+1 817 485 8001",
    "sg:postcode":"76180",
    "sg:province":"TX",
    "wof:name":"Healthcare Insurance Svc",
    "wof:placetype":"venue"
},
  "geometry": {"coordinates":[-97.22751100000001,32.884067],"type":"Point"}
}