{
  "type": "Feature",
  "properties": {
    "iso:country":"US",
    "sg:address":"17401 Red Oak Dr",
    "sg:city":"Houston",
    "sg:classifiers":[
        {
            "category":"Professional",
            "subcategory":"Employment Agencies",
            "type":"Services"
        }
    ],
    "sg:phone":"+1 281 440 0991",
    "sg:postcode":"77090",
    "sg:province":"TX",
    "wof:name":"J Kelley Staffing",
    "wof:placetype":"venue"
},
  "geometry": {"coordinates":[-95.4466,30.020736],"type":"Point"}
}