{
  "type": "Feature",
  "properties": {
    "iso:country":"US",
    "sg:address":"1022 N Montclair Ave",
    "sg:city":"Dallas",
    "sg:classifiers":[
        {
            "category":"Professional",
            "subcategory":"Art Services",
            "type":"Services"
        }
    ],
    "sg:phone":"+1 214 941 1170",
    "sg:postcode":"75208",
    "sg:province":"TX",
    "sg:tags":[
        "commercial",
        "design"
    ],
    "wof:name":"Bill Kelsey Graphics",
    "wof:placetype":"venue"
},
  "geometry": {"coordinates":[-96.846605,32.757504],"type":"Point"}
}