{
  "type": "Feature",
  "properties": {
    "iso:country":"US",
    "sg:address":"5290 Belt Line Rd Ste 103",
    "sg:city":"Dallas",
    "sg:phone":"+1 972 788 2717",
    "sg:postcode":"75254",
    "sg:province":"TX",
    "wof:name":"Desi Wok",
    "wof:placetype":"venue"
},
  "geometry": {"coordinates":[-96.81842,32.953991],"type":"Point"}
}