{
  "type": "Feature",
  "properties": {
    "iso:country":"US",
    "sg:address":"631 Blakeley Dr",
    "sg:city":"San Antonio",
    "sg:classifiers":[
        {
            "category":"Building & Trades",
            "subcategory":"Construction",
            "type":"Services"
        }
    ],
    "sg:phone":"+1 210 824 4974",
    "sg:postcode":"78209",
    "sg:province":"TX",
    "sg:tags":[
        "contractor"
    ],
    "wof:name":"Prosser Sheet Metal Roofing",
    "wof:placetype":"venue"
},
  "geometry": {"coordinates":[-98.43301599999999,29.485686],"type":"Point"}
}