{
  "type": "Feature",
  "properties": {
    "iso:country":"US",
    "sg:address":"101 W 8th St",
    "sg:city":"Venus",
    "sg:classifiers":[
        {
            "category":"Government",
            "subcategory":"Post Office",
            "type":"Public Place"
        }
    ],
    "sg:phone":"+1 972 366 3643",
    "sg:postcode":"76058",
    "sg:province":"TX",
    "wof:name":"US Post Office",
    "wof:placetype":"venue"
},
  "geometry": {"coordinates":[-97.387456,32.463519],"type":"Point"}
}