{
  "type": "Feature",
  "properties": {
    "iso:country":"US",
    "sg:address":"10940 Stancliff Rd",
    "sg:city":"Houston",
    "sg:classifiers":[
        {
            "category":"Building & Trades",
            "subcategory":"Plumbing",
            "type":"Services"
        }
    ],
    "sg:phone":"+1 281 530 3700",
    "sg:postcode":"77099",
    "sg:province":"TX",
    "sg:tags":[
        "system",
        "contractor",
        "equipment",
        "air conditioning"
    ],
    "sg:website":"http://www.acengsys.com",
    "wof:name":"AC Engineered System",
    "wof:placetype":"venue"
},
  "geometry": {"coordinates":[-95.572102,29.660086],"type":"Point"}
}