{
  "type": "Feature",
  "properties": {
    "iso:country":"US",
    "sg:address":"311 Palo Alto Rd",
    "sg:city":"San Antonio",
    "sg:classifiers":[
        {
            "category":"Restaurant",
            "type":"Food & Drink"
        }
    ],
    "sg:phone":"+1 210 932 3305",
    "sg:postcode":"78211",
    "sg:province":"TX",
    "wof:name":"Chica Cafe",
    "wof:placetype":"venue"
},
  "geometry": {"coordinates":[-98.55233200000001,29.349814],"type":"Point"}
}