{
  "type": "Feature",
  "properties": {
    "iso:country":"US",
    "sg:address":"701 E Hidalgo St",
    "sg:city":"Rio Grande City",
    "sg:classifiers":[
        {
            "category":"Organizations",
            "subcategory":"Religious Organization",
            "type":"Services"
        }
    ],
    "sg:phone":"+1 956 487 0020",
    "sg:postcode":"78582",
    "sg:province":"TX",
    "sg:tags":[
        "church"
    ],
    "wof:name":"Asamblea De Dios",
    "wof:placetype":"venue"
},
  "geometry": {"coordinates":[-98.812433,26.38391],"type":"Point"}
}