{
  "type": "Feature",
  "properties": {
    "iso:country":"US",
    "sg:address":"5325 San Mateo Ct",
    "sg:city":"Arlington",
    "sg:classifiers":[
        {
            "category":"Building & Trades",
            "subcategory":"Construction",
            "type":"Services"
        }
    ],
    "sg:phone":"+1 817 658 9295",
    "sg:postcode":"76017",
    "sg:province":"TX",
    "sg:tags":[
        "coping",
        "plastering",
        "tiling",
        "pool",
        "swimming"
    ],
    "wof:name":"Nicholas Pool Svc",
    "wof:placetype":"venue"
},
  "geometry": {"coordinates":[-97.163076,32.659387],"type":"Point"}
}