{
  "type": "Feature",
  "properties": {
    "iso:country":"US",
    "sg:address":"6630 Roxburgh Dr",
    "sg:city":"Houston",
    "sg:classifiers":[
        {
            "category":"Health Services",
            "subcategory":"Chiropractor",
            "type":"Services"
        }
    ],
    "sg:phone":"+1 281 890 0001",
    "sg:postcode":"77041",
    "sg:province":"TX",
    "wof:name":"Nova Health Care Centers",
    "wof:placetype":"venue"
},
  "geometry": {"coordinates":[-95.55556799999999,29.865814],"type":"Point"}
}