{
  "type": "Feature",
  "properties": {
    "iso:country":"US",
    "sg:address":"209 W Holland Ave",
    "sg:city":"Alpine",
    "sg:classifiers":[
        {
            "category":"Professional",
            "subcategory":"Art Services",
            "type":"Services"
        }
    ],
    "sg:phone":"+1 432 837 9008",
    "sg:postcode":"79830",
    "sg:province":"TX",
    "sg:tags":[
        "graphic",
        "designer"
    ],
    "wof:name":"Vast Graphics",
    "wof:placetype":"venue"
},
  "geometry": {"coordinates":[-103.662424,30.357371],"type":"Point"}
}