{
  "type": "Feature",
  "properties": {
    "iso:country":"US",
    "sg:address":"1511 Judson Rd",
    "sg:city":"Longview",
    "sg:classifiers":[
        {
            "category":"Recreation",
            "subcategory":"Marina",
            "type":"Entertainment"
        }
    ],
    "sg:phone":"+1 903 753 5856",
    "sg:postcode":"75601",
    "sg:province":"TX",
    "sg:tags":[
        "operation"
    ],
    "wof:name":"Best Self Store",
    "wof:placetype":"venue"
},
  "geometry": {"coordinates":[-94.741743,32.52095],"type":"Point"}
}