{
  "type": "Feature",
  "properties": {
    "iso:country":"US",
    "sg:address":"5105 Stonecrest Dr",
    "sg:city":"Mc Kinney",
    "sg:classifiers":[
        {
            "category":"Building & Trades",
            "subcategory":"Construction",
            "type":"Services"
        }
    ],
    "sg:phone":"+1 972 562 5007",
    "sg:postcode":"75071",
    "sg:province":"TX",
    "sg:tags":[
        "home",
        "builder"
    ],
    "wof:name":"Calmark Homes",
    "wof:placetype":"venue"
},
  "geometry": {"coordinates":[-96.68188499999999,33.202142],"type":"Point"}
}