{
  "type": "Feature",
  "properties": {
    "iso:country":"US",
    "sg:address":"100 Ventura Ct",
    "sg:city":"Allen",
    "sg:classifiers":[
        {
            "category":"Insurance",
            "subcategory":"Insurance Agent",
            "type":"Services"
        }
    ],
    "sg:phone":"+1 972 390 2025",
    "sg:postcode":"75013",
    "sg:province":"TX",
    "wof:name":"Rowlett Insurance Agency",
    "wof:placetype":"venue"
},
  "geometry": {"coordinates":[-96.691446,33.100392],"type":"Point"}
}