{
  "type": "Feature",
  "properties": {
    "iso:country":"US",
    "sg:address":"5208 Rush Creek Ct",
    "sg:city":"Keller",
    "sg:classifiers":[
        {
            "category":"Autos & Motor Vehicles",
            "subcategory":"Automobile Sales",
            "type":"Retail Goods"
        }
    ],
    "sg:phone":"+1 817 741 1324",
    "sg:postcode":"76248",
    "sg:province":"TX",
    "sg:tags":[
        "used"
    ],
    "wof:name":"Baron Auto Sales Inc",
    "wof:placetype":"venue"
},
  "geometry": {"coordinates":[-97.268266,32.944417],"type":"Point"}
}