{
  "type": "Feature",
  "properties": {
    "iso:country":"US",
    "sg:address":"11441 N Stemmons Fwy",
    "sg:city":"Dallas",
    "sg:classifiers":[
        {
            "category":"Personal",
            "subcategory":"Beauty Salon",
            "type":"Services"
        }
    ],
    "sg:phone":"+1 972 280 9400",
    "sg:postcode":"75229",
    "sg:province":"TX",
    "sg:tags":[
        "shop"
    ],
    "wof:name":"Salern Salon Essentials",
    "wof:placetype":"venue"
},
  "geometry": {"coordinates":[-96.898039,32.896333],"type":"Point"}
}