{
  "type": "Feature",
  "properties": {
    "iso:country":"US",
    "sg:address":"324 Peach St",
    "sg:city":"Pecos",
    "sg:classifiers":[
        {
            "category":"Organizations",
            "subcategory":"Religious Organization",
            "type":"Services"
        }
    ],
    "sg:phone":"+1 432 445 9906",
    "sg:postcode":"79772",
    "sg:province":"TX",
    "sg:tags":[
        "church"
    ],
    "wof:name":"St James Baptist Church",
    "wof:placetype":"venue"
},
  "geometry": {"coordinates":[-103.489221,31.427352],"type":"Point"}
}