{
  "type": "Feature",
  "properties": {
    "iso:country":"US",
    "sg:address":"3681 State Hwy 6",
    "sg:city":"Sugar Land",
    "sg:classifiers":[
        {
            "category":"Health Services",
            "subcategory":"Doctor",
            "type":"Services"
        }
    ],
    "sg:phone":"+1 281 980 7777",
    "sg:postcode":"77478",
    "sg:province":"TX",
    "sg:tags":[
        "dentist"
    ],
    "wof:name":"R Greg Carroll DDS",
    "wof:placetype":"venue"
},
  "geometry": {"coordinates":[-95.59727599999999,29.589365],"type":"Point"}
}