{
  "type": "Feature",
  "properties": {
    "iso:country":"US",
    "sg:address":"9022 Vincik Ehlert Rd",
    "sg:city":"Beasley",
    "sg:classifiers":[
        {
            "category":"Utilities",
            "subcategory":"Water",
            "type":"Services"
        }
    ],
    "sg:phone":"+1 979 387 3223",
    "sg:postcode":"77417",
    "sg:province":"TX",
    "sg:tags":[
        "pump",
        "well",
        "drilling",
        "contractor"
    ],
    "wof:name":"Rdt-Usa",
    "wof:placetype":"venue"
},
  "geometry": {"coordinates":[-95.922364,29.469091],"type":"Point"}
}