{
  "type": "Feature",
  "properties": {
    "iso:country":"US",
    "sg:address":"1205 Hidden Oaks Dr",
    "sg:city":"Bulverde",
    "sg:classifiers":[
        {
            "category":"Wholesale",
            "subcategory":"Computers",
            "type":"Manufacturing & Wholesale Goods"
        }
    ],
    "sg:phone":"+1 830 980 6480",
    "sg:postcode":"78163",
    "sg:province":"TX",
    "sg:tags":[
        "sales",
        "software"
    ],
    "wof:name":"Array Systems Inc",
    "wof:placetype":"venue"
},
  "geometry": {"coordinates":[-98.534238,29.757],"type":"Point"}
}