{
  "type": "Feature",
  "properties": {
    "iso:country":"US",
    "sg:address":"11462 Kline Dr",
    "sg:city":"Conroe",
    "sg:classifiers":[
        {
            "category":"Building & Trades",
            "subcategory":"Construction",
            "type":"Services"
        }
    ],
    "sg:phone":"+1 936 494 3080",
    "sg:postcode":"77303",
    "sg:province":"TX",
    "sg:tags":[
        "house"
    ],
    "wof:name":"West Home Repair",
    "wof:placetype":"venue"
},
  "geometry": {"coordinates":[-95.400881,30.327042],"type":"Point"}
}