{
  "type": "Feature",
  "properties": {
    "iso:country":"US",
    "sg:address":"16803 Butera Rd",
    "sg:city":"Magnolia",
    "sg:classifiers":[
        {
            "category":"Banks & Credit Unions",
            "subcategory":"Investment Brokerage",
            "type":"Services"
        }
    ],
    "sg:phone":"+1 281 252 8450",
    "sg:postcode":"77355",
    "sg:province":"TX",
    "sg:tags":[
        "advisory"
    ],
    "wof:name":"Universal Land Acquisitions, Inc.",
    "wof:placetype":"venue"
},
  "geometry": {"coordinates":[-95.731919,30.131532],"type":"Point"}
}