{
  "type": "Feature",
  "properties": {
    "iso:country":"US",
    "sg:address":"2061 Antwerp Ave",
    "sg:city":"Plano",
    "sg:classifiers":[
        {
            "category":"Building & Trades",
            "subcategory":"Cleaning & Sanitation",
            "type":"Services"
        }
    ],
    "sg:phone":"+1 972 398 3660",
    "sg:postcode":"75025",
    "sg:province":"TX",
    "sg:tags":[
        "maintenance"
    ],
    "wof:name":"Global Services",
    "wof:placetype":"venue"
},
  "geometry": {"coordinates":[-96.733108,33.07891],"type":"Point"}
}