{
  "type": "Feature",
  "properties": {
    "iso:country":"US",
    "sg:address":"3705 Medical Pkwy Ste 540",
    "sg:city":"Austin",
    "sg:classifiers":[
        {
            "category":"Health Services",
            "subcategory":"Doctor",
            "type":"Services"
        }
    ],
    "sg:phone":"+1 512 452 8888",
    "sg:postcode":"78705",
    "sg:province":"TX",
    "wof:name":"Balcones Obstetrics and Gynecology",
    "wof:placetype":"venue"
},
  "geometry": {"coordinates":[-97.74448099999999,30.304625],"type":"Point"}
}