{
  "type": "Feature",
  "properties": {
    "iso:country":"US",
    "sg:address":"2501 Saunders Ave",
    "sg:city":"San Antonio",
    "sg:classifiers":[
        {
            "category":"Shopping",
            "subcategory":"Gifts & Souvenirs",
            "type":"Retail Goods"
        }
    ],
    "sg:phone":"+1 210 436 1439",
    "sg:postcode":"78207",
    "sg:province":"TX",
    "wof:name":"Alamo City World of Gifts",
    "wof:placetype":"venue"
},
  "geometry": {"coordinates":[-98.527332,29.42494],"type":"Point"}
}