{
  "type": "Feature",
  "properties": {
    "iso:country":"US",
    "sg:address":"3933 Steck Ave",
    "sg:city":"Austin",
    "sg:classifiers":[
        {
            "category":"Professional",
            "subcategory":"Lawyer & Legal Services",
            "type":"Services"
        }
    ],
    "sg:phone":"+1 512 482 0602",
    "sg:postcode":"78759",
    "sg:province":"TX",
    "sg:tags":[
        "attorney"
    ],
    "wof:name":"Shanks Tritter & Ledbetter",
    "wof:placetype":"venue"
},
  "geometry": {"coordinates":[-97.752863,30.372977],"type":"Point"}
}