{
  "type": "Feature",
  "properties": {
    "iso:country":"US",
    "sg:address":"110 N Main St",
    "sg:city":"Vidor",
    "sg:classifiers":[
        {
            "category":"Retail",
            "subcategory":"Auto Repair",
            "type":"Services"
        }
    ],
    "sg:phone":"+1 409 769 2757",
    "sg:postcode":"77662",
    "sg:province":"TX",
    "sg:tags":[
        "muffler",
        "exhaust",
        "system"
    ],
    "wof:name":"Harris Muffler & Brake",
    "wof:placetype":"venue"
},
  "geometry": {"coordinates":[-94.012805,30.125118],"type":"Point"}
}