{
  "type": "Feature",
  "properties": {
    "iso:country":"US",
    "sg:address":"1928 13th St",
    "sg:city":"Port Arthur",
    "sg:classifiers":[
        {
            "category":"Freight",
            "type":"Transportation"
        }
    ],
    "sg:phone":"+1 409 982 6943",
    "sg:postcode":"77640",
    "sg:province":"TX",
    "sg:tags":[
        "operator",
        "local",
        "trucking"
    ],
    "wof:name":"Mae Lois Streeter",
    "wof:placetype":"venue"
},
  "geometry": {"coordinates":[-93.932919,29.889574],"type":"Point"}
}