{
  "type": "Feature",
  "properties": {
    "iso:country":"US",
    "sg:address":"515 Gladstone Ave",
    "sg:city":"San Antonio",
    "sg:classifiers":[
        {
            "category":"Retail",
            "subcategory":"Auto Repair",
            "type":"Services"
        }
    ],
    "sg:phone":"+1 210 534 1951",
    "sg:postcode":"78225",
    "sg:province":"TX",
    "sg:tags":[
        "repairing",
        "shop",
        "general",
        "automotive",
        "automobile"
    ],
    "wof:name":"Joe's Auto Clinic",
    "wof:placetype":"venue"
},
  "geometry": {"coordinates":[-98.51520600000001,29.382427],"type":"Point"}
}