{
  "type": "Feature",
  "properties": {
    "iso:country":"US",
    "sg:address":"6010 Hazelwood Dr",
    "sg:city":"Orange",
    "sg:classifiers":[
        {
            "category":"Professional",
            "type":"Services"
        }
    ],
    "sg:phone":"+1 409 883 4691",
    "sg:postcode":"77632",
    "sg:province":"TX",
    "sg:tags":[
        "establishment"
    ],
    "wof:name":"Recall Exp Data",
    "wof:placetype":"venue"
},
  "geometry": {"coordinates":[-93.744868,30.156185],"type":"Point"}
}