{
  "type": "Feature",
  "properties": {
    "iso:country":"US",
    "sg:address":"25000 Pitkin Rd",
    "sg:city":"Spring",
    "sg:classifiers":[
        {
            "category":"Personal",
            "subcategory":"Beauty Salon",
            "type":"Services"
        }
    ],
    "sg:phone":"+1 281 367 9955",
    "sg:postcode":"77386",
    "sg:province":"TX",
    "sg:tags":[
        "shop"
    ],
    "wof:name":"Medical Beauty Stress Relief",
    "wof:placetype":"venue"
},
  "geometry": {"coordinates":[-95.439903,30.122019],"type":"Point"}
}