{
  "type": "Feature",
  "properties": {
    "iso:country":"US",
    "sg:address":"709 E Calton Rd",
    "sg:city":"Laredo",
    "sg:classifiers":[
        {
            "category":"Insurance",
            "subcategory":"Insurance Agent",
            "type":"Services"
        }
    ],
    "sg:phone":"+1 956 523 0638",
    "sg:postcode":"78041",
    "sg:province":"TX",
    "wof:name":"Metlife",
    "wof:placetype":"venue"
},
  "geometry": {"coordinates":[-99.48735499999999,27.541584],"type":"Point"}
}