{
  "type": "Feature",
  "properties": {
    "iso:country":"US",
    "sg:address":"1177 Rockingham Ln",
    "sg:city":"Richardson",
    "sg:classifiers":[
        {
            "category":"Professional",
            "subcategory":"Management & Consulting",
            "type":"Services"
        }
    ],
    "sg:phone":"+1 972 690 1117",
    "sg:postcode":"75080",
    "sg:province":"TX",
    "sg:tags":[
        "health"
    ],
    "wof:name":"Israel Donna A PH D Rd",
    "wof:placetype":"venue"
},
  "geometry": {"coordinates":[-96.74092400000001,32.963857],"type":"Point"}
}