{
  "type": "Feature",
  "properties": {
    "iso:country":"US",
    "sg:address":"34 Rentfro Blvd",
    "sg:city":"Brownsville",
    "sg:classifiers":[
        {
            "category":"Farming",
            "subcategory":"Livestock Farm",
            "type":"Manufacturing & Wholesale Goods"
        }
    ],
    "sg:phone":"+1 956 541 3094",
    "sg:postcode":"78521",
    "sg:province":"TX",
    "sg:tags":[
        "specialty",
        "animal"
    ],
    "wof:name":"Rio Bravo Reptiles",
    "wof:placetype":"venue"
},
  "geometry": {"coordinates":[-97.481692,25.924338],"type":"Point"}
}