{
  "type": "Feature",
  "properties": {
    "iso:country":"US",
    "sg:address":"2600 E Santa Gertrudis St",
    "sg:city":"Kingsville",
    "sg:classifiers":[
        {
            "category":"Manufacturing",
            "subcategory":"Electronics",
            "type":"Manufacturing & Wholesale Goods"
        }
    ],
    "sg:phone":"+1 361 592 3615",
    "sg:postcode":"78363",
    "sg:province":"TX",
    "sg:tags":[
        "semiconductor",
        "related",
        "devices",
        "mfg"
    ],
    "wof:name":"Kodiak Manufacturing Inc",
    "wof:placetype":"venue"
},
  "geometry": {"coordinates":[-97.840401,27.523035],"type":"Point"}
}