{
  "type": "Feature",
  "properties": {
    "iso:country":"US",
    "sg:address":"8523 Blanco Rd",
    "sg:city":"San Antonio",
    "sg:classifiers":[
        {
            "category":"Government",
            "subcategory":"Office",
            "type":"Public Place"
        }
    ],
    "sg:phone":"+1 210 207 6150",
    "sg:postcode":"78216",
    "sg:province":"TX",
    "sg:tags":[
        "village"
    ],
    "wof:name":"Valley View Community Link Svc",
    "wof:placetype":"venue"
},
  "geometry": {"coordinates":[-98.508689,29.546077],"type":"Point"}
}