{
  "type": "Feature",
  "properties": {
    "iso:country":"US",
    "sg:address":"3522 Heather Brook Dr",
    "sg:city":"Arlington",
    "sg:classifiers":[
        {
            "category":"Manufacturing",
            "subcategory":"Printing",
            "type":"Manufacturing & Wholesale Goods"
        }
    ],
    "sg:phone":"+1 817 467 0276",
    "sg:postcode":"76001",
    "sg:province":"TX",
    "sg:tags":[
        "consulting",
        "promotional",
        "sales",
        "advertising"
    ],
    "wof:name":"Adventres In Advg Lnestar Logo",
    "wof:placetype":"venue"
},
  "geometry": {"coordinates":[-97.16316,32.644831],"type":"Point"}
}