{
  "type": "Feature",
  "properties": {
    "iso:country":"US",
    "sg:address":"2330 Carson St",
    "sg:city":"Fort Worth",
    "sg:classifiers":[
        {
            "category":"Building & Trades",
            "subcategory":"Construction",
            "type":"Services"
        }
    ],
    "sg:phone":"+1 817 222 2200",
    "sg:postcode":"76117",
    "sg:province":"TX",
    "sg:tags":[
        "foundation"
    ],
    "wof:name":"Uretek ICR",
    "wof:placetype":"venue"
},
  "geometry": {"coordinates":[-97.25576599999999,32.792864],"type":"Point"}
}