{
  "type": "Feature",
  "properties": {
    "iso:country":"US",
    "sg:address":"621 N Hall St",
    "sg:city":"Dallas",
    "sg:classifiers":[
        {
            "category":"Health Services",
            "subcategory":"Doctor",
            "type":"Services"
        }
    ],
    "sg:phone":"+1 214 821 9600",
    "sg:postcode":"75226",
    "sg:province":"TX",
    "sg:website":"www.texasvascularassociates.com",
    "wof:name":"Gable Dennis MD",
    "wof:placetype":"venue"
},
  "geometry": {"coordinates":[-96.780197,32.787899],"type":"Point"}
}