{
  "type": "Feature",
  "properties": {
    "iso:country":"US",
    "sg:address":"4205 W Plano Pkwy",
    "sg:city":"Plano",
    "sg:classifiers":[
        {
            "category":"Retail",
            "subcategory":"Auto Repair",
            "type":"Services"
        }
    ],
    "sg:phone":"+1 972 867 5803",
    "sg:postcode":"75093",
    "sg:province":"TX",
    "sg:tags":[
        "body",
        "automobile",
        "painting"
    ],
    "sg:website":"www.serviceking.com",
    "wof:name":"Service King Collision",
    "wof:placetype":"venue"
},
  "geometry": {"coordinates":[-96.77507799999999,33.016416],"type":"Point"}
}