{
  "type": "Feature",
  "properties": {
    "iso:country":"US",
    "sg:address":"1497 W Cardinal Dr",
    "sg:city":"Beaumont",
    "sg:classifiers":[
        {
            "category":"Wholesale",
            "subcategory":"Machinery & Supplies",
            "type":"Manufacturing & Wholesale Goods"
        }
    ],
    "sg:phone":"+1 409 840 2011",
    "sg:postcode":"77705",
    "sg:province":"TX",
    "sg:tags":[
        "equipment",
        "industrial"
    ],
    "wof:name":"Sprint Industrial Svc LLC",
    "wof:placetype":"venue"
},
  "geometry": {"coordinates":[-94.09556000000001,30.032809],"type":"Point"}
}