{
  "type": "Feature",
  "properties": {
    "iso:country":"US",
    "sg:address":"2212 Fort Worth Dr",
    "sg:city":"Denton",
    "sg:classifiers":[
        {
            "category":"Building & Trades",
            "subcategory":"Construction",
            "type":"Services"
        }
    ],
    "sg:phone":"+1 940 382 0407",
    "sg:postcode":"76205",
    "sg:province":"TX",
    "sg:tags":[
        "contractor"
    ],
    "wof:name":"David Gass",
    "wof:placetype":"venue"
},
  "geometry": {"coordinates":[-97.139027,33.18213],"type":"Point"}
}