{
  "type": "Feature",
  "properties": {
    "iso:country":"US",
    "sg:address":"705 E Florida Ave",
    "sg:city":"Midland",
    "sg:classifiers":[
        {
            "category":"Professional",
            "subcategory":"Business Services",
            "type":"Services"
        }
    ],
    "sg:phone":"+1 432 520 0765",
    "sg:postcode":"79701",
    "sg:province":"TX",
    "sg:tags":[
        "a",
        "on",
        "fee",
        "auctioneer",
        "basis"
    ],
    "wof:name":"Osborn and Associates",
    "wof:placetype":"venue"
},
  "geometry": {"coordinates":[-102.06558800000001,31.989369],"type":"Point"}
}