{
  "type": "Feature",
  "properties": {
    "iso:country":"US",
    "sg:address":"1505 Brown Trl",
    "sg:city":"Bedford",
    "sg:classifiers":[
        {
            "category":"Restaurant",
            "type":"Food & Drink"
        }
    ],
    "sg:menulink":"http://www.allmenus.com/tx/northeast-tarrant/176958-kfc---kentucky-fried-chicken/menu/",
    "sg:phone":"+1 817 268 1876",
    "sg:postcode":"76022",
    "sg:province":"TX",
    "sg:tags":[
        "american",
        "chicken"
    ],
    "wof:name":"KFC - Kentucky Fried Chicken",
    "wof:placetype":"venue"
},
  "geometry": {"coordinates":[-97.160473,32.838608],"type":"Point"}
}