{
  "type": "Feature",
  "properties": {
    "iso:country":"US",
    "sg:address":"7517 Bryn Mawr Dr",
    "sg:city":"Rowlett",
    "sg:classifiers":[
        {
            "category":"Building & Trades",
            "subcategory":"Electrical",
            "type":"Services"
        }
    ],
    "sg:phone":"+1 469 366 7050",
    "sg:postcode":"75089",
    "sg:province":"TX",
    "sg:tags":[
        "electrical",
        "contractor"
    ],
    "wof:name":"Ventura Electric",
    "wof:placetype":"venue"
},
  "geometry": {"coordinates":[-96.52778499999999,32.930289],"type":"Point"}
}