{
  "type": "Feature",
  "properties": {
    "iso:country":"US",
    "sg:address":"3250 Telephone Rd",
    "sg:city":"Houston",
    "sg:classifiers":[
        {
            "category":"Wholesale",
            "subcategory":"Auto Parts",
            "type":"Manufacturing & Wholesale Goods"
        }
    ],
    "sg:phone":"+1 713 926 6094",
    "sg:postcode":"77023",
    "sg:province":"TX",
    "sg:tags":[
        "body",
        "automobile",
        "shop"
    ],
    "wof:name":"Hou-Tex",
    "wof:placetype":"venue"
},
  "geometry": {"coordinates":[-95.31611100000001,29.712594],"type":"Point"}
}