{
  "type": "Feature",
  "properties": {
    "iso:country":"US",
    "sg:address":"2505 Aspen Ln",
    "sg:city":"Burleson",
    "sg:classifiers":[
        {
            "category":"Professional",
            "subcategory":"Computer Services",
            "type":"Services"
        }
    ],
    "sg:phone":"+1 817 447 9609",
    "sg:postcode":"76028",
    "sg:province":"TX",
    "sg:tags":[
        "consultant",
        "designer"
    ],
    "wof:name":"M Path",
    "wof:placetype":"venue"
},
  "geometry": {"coordinates":[-97.23267199999999,32.535901],"type":"Point"}
}