{
  "type": "Feature",
  "properties": {
    "iso:country":"US",
    "sg:address":"200 Dominion Park Dr",
    "sg:city":"Houston",
    "sg:classifiers":[
        {
            "category":"Professional",
            "type":"Services"
        }
    ],
    "sg:phone":"+1 281 875 6918",
    "sg:postcode":"77090",
    "sg:province":"TX",
    "wof:name":"Anime & Gaming",
    "wof:placetype":"venue"
},
  "geometry": {"coordinates":[-95.42699399999999,29.975351],"type":"Point"}
}