{
  "type": "Feature",
  "properties": {
    "iso:country":"US",
    "sg:address":"3035 Cedar Dr",
    "sg:city":"La Marque",
    "sg:classifiers":[
        {
            "category":"Personal",
            "type":"Services"
        }
    ],
    "sg:phone":"+1 409 935 7563",
    "sg:postcode":"77568",
    "sg:province":"TX",
    "wof:name":"Creative Weddings By Carla",
    "wof:placetype":"venue"
},
  "geometry": {"coordinates":[-94.99164500000001,29.368221],"type":"Point"}
}