{
  "type": "Feature",
  "properties": {
    "iso:country":"US",
    "sg:address":"2828 N Haskell Ave",
    "sg:city":"Dallas",
    "sg:classifiers":[
        {
            "category":"Professional",
            "subcategory":"Research",
            "type":"Services"
        }
    ],
    "sg:phone":"+1 214 841 8083",
    "sg:postcode":"75204",
    "sg:province":"TX",
    "wof:name":"A C S Business Services Inc",
    "wof:placetype":"venue"
},
  "geometry": {"coordinates":[-96.792159,32.807083],"type":"Point"}
}