{
  "type": "Feature",
  "properties": {
    "iso:country":"US",
    "sg:address":"202 W Harrison St",
    "sg:city":"Jefferson",
    "sg:classifiers":[
        {
            "category":"Building & Trades",
            "subcategory":"Construction",
            "type":"Services"
        }
    ],
    "sg:phone":"+1 903 665 6039",
    "sg:postcode":"75657",
    "sg:province":"TX",
    "sg:tags":[
        "house"
    ],
    "wof:name":"Varnell Construction Co",
    "wof:placetype":"venue"
},
  "geometry": {"coordinates":[-94.35610800000001,32.768407],"type":"Point"}
}