{
  "type": "Feature",
  "properties": {
    "iso:country":"US",
    "sg:address":"5201 Forego Ave",
    "sg:city":"Edinburg",
    "sg:classifiers":[
        {
            "category":"Building & Trades",
            "subcategory":"Construction",
            "type":"Services"
        }
    ],
    "sg:phone":"+1 956 783 9960",
    "sg:postcode":"78539",
    "sg:province":"TX",
    "sg:tags":[
        "house"
    ],
    "wof:name":"Corporate Construction",
    "wof:placetype":"venue"
},
  "geometry": {"coordinates":[-98.17600899999999,26.251918],"type":"Point"}
}