{
  "type": "Feature",
  "properties": {
    "iso:country":"US",
    "sg:address":"2337 S International Pkwy DFW Airport",
    "sg:city":"Dallas",
    "sg:classifiers":[
        {
            "category":"Travel",
            "subcategory":"Hotels & Motels",
            "type":"Entertainment"
        }
    ],
    "sg:phone":"+1 972 973 1234",
    "sg:postcode":"75261",
    "sg:province":"TX",
    "sg:website":"www.grandhyattdfw.com",
    "wof:name":"Grand Hyatt DFW",
    "wof:placetype":"venue"
},
  "geometry": {"coordinates":[-96.84356200000001,33.01887],"type":"Point"}
}