{
  "type": "Feature",
  "properties": {
    "iso:country":"US",
    "sg:address":"910 Washington St",
    "sg:city":"South Houston",
    "sg:classifiers":[
        {
            "category":"Organizations",
            "subcategory":"Religious Organization",
            "type":"Services"
        }
    ],
    "sg:phone":"+1 713 946 4259",
    "sg:postcode":"77587",
    "sg:province":"TX",
    "wof:name":"Templo Bautista",
    "wof:placetype":"venue"
},
  "geometry": {"coordinates":[-95.238995,29.657835],"type":"Point"}
}