{
  "type": "Feature",
  "properties": {
    "iso:country":"US",
    "sg:address":"2415 E Santa Gertrudis St",
    "sg:city":"Kingsville",
    "sg:classifiers":[
        {
            "category":"Building & Trades",
            "subcategory":"Construction",
            "type":"Services"
        }
    ],
    "sg:phone":"+1 361 516 0526",
    "sg:postcode":"78363",
    "sg:province":"TX",
    "sg:tags":[
        "general",
        "contractor"
    ],
    "wof:name":"Chapman Construction",
    "wof:placetype":"venue"
},
  "geometry": {"coordinates":[-97.838947,27.522968],"type":"Point"}
}