{
  "type": "Feature",
  "properties": {
    "iso:country":"US",
    "sg:address":"1411 Lemay Dr Ste 105",
    "sg:city":"Carrollton",
    "sg:classifiers":[
        {
            "category":"Home & Garden",
            "subcategory":"Carpets & Floor Coverings",
            "type":"Retail Goods"
        }
    ],
    "sg:phone":"+1 972 242 5065",
    "sg:postcode":"75007",
    "sg:province":"TX",
    "sg:tags":[
        "carpeting"
    ],
    "sg:website":"www.copelandscarpets.com",
    "wof:name":"Copeland's Carpets & More",
    "wof:placetype":"venue"
},
  "geometry": {"coordinates":[-96.92089799999999,32.989101],"type":"Point"}
}