{
  "type": "Feature",
  "properties": {
    "iso:country":"US",
    "sg:address":"108 E Ovilla Rd",
    "sg:city":"Red Oak",
    "sg:classifiers":[
        {
            "category":"Retail",
            "subcategory":"Laundry & Dry Cleaning",
            "type":"Services"
        }
    ],
    "sg:phone":"+1 972 617 1977",
    "sg:postcode":"75154",
    "sg:province":"TX",
    "sg:tags":[
        "cleaners",
        "plant",
        "drycleaning"
    ],
    "wof:name":"Cadillac Cleaners & Laundry",
    "wof:placetype":"venue"
},
  "geometry": {"coordinates":[-96.85685700000001,32.531796],"type":"Point"}
}