{
  "type": "Feature",
  "properties": {
    "iso:country":"US",
    "sg:address":"408 Lindberg Ave",
    "sg:city":"Mcallen",
    "sg:classifiers":[
        {
            "category":"Professional",
            "subcategory":"Art Services",
            "type":"Services"
        }
    ],
    "sg:phone":"+1 956 664 2200",
    "sg:postcode":"78501",
    "sg:province":"TX",
    "sg:tags":[
        "interior",
        "designer",
        "decorator"
    ],
    "wof:name":"Nora Design Studio",
    "wof:placetype":"venue"
},
  "geometry": {"coordinates":[-98.225616,26.191726],"type":"Point"}
}