{
  "type": "Feature",
  "properties": {
    "iso:country":"US",
    "sg:address":"716 W 11th St",
    "sg:city":"Amherst",
    "sg:classifiers":[
        {
            "category":"Professional",
            "subcategory":"Accounting & Tax Preparation",
            "type":"Services"
        }
    ],
    "sg:phone":"+1 806 246 3616",
    "sg:postcode":"79312",
    "sg:province":"TX",
    "sg:tags":[
        "bookkeeping",
        "general"
    ],
    "wof:name":"Boleyn's Bookeeping Svc",
    "wof:placetype":"venue"
},
  "geometry": {"coordinates":[-102.421314,34.010964],"type":"Point"}
}