{
  "type": "Feature",
  "properties": {
    "iso:country":"US",
    "sg:address":"702 Colorado St",
    "sg:city":"Austin",
    "sg:classifiers":[
        {
            "category":"Professional",
            "subcategory":"Lawyer & Legal Services",
            "type":"Services"
        }
    ],
    "sg:phone":"+1 512 476 7163",
    "sg:postcode":"78701",
    "sg:province":"TX",
    "wof:name":"G Wellington Smith PC",
    "wof:placetype":"venue"
},
  "geometry": {"coordinates":[-97.743719,30.269598],"type":"Point"}
}