{
  "type": "Feature",
  "properties": {
    "iso:country":"US",
    "sg:address":"4201 Ed Bluestein Blvd",
    "sg:city":"Austin",
    "sg:classifiers":[
        {
            "category":"Government",
            "subcategory":"Fire Station",
            "type":"Public Place"
        }
    ],
    "sg:phone":"+1 512 477 5784",
    "sg:postcode":"78721",
    "sg:province":"TX",
    "sg:tags":[
        "protection"
    ],
    "wof:name":"Austin Fire Dept City of",
    "wof:placetype":"venue"
},
  "geometry": {"coordinates":[-97.66525900000001,30.285619],"type":"Point"}
}