{
  "type": "Feature",
  "properties": {
    "iso:country":"US",
    "sg:address":"1106 Industrial Park Rd",
    "sg:city":"Belton",
    "sg:classifiers":[
        {
            "category":"Manufacturing",
            "subcategory":"Rubber & Plastics",
            "type":"Manufacturing & Wholesale Goods"
        }
    ],
    "sg:phone":"+1 254 939 6379",
    "sg:postcode":"76513",
    "sg:province":"TX",
    "sg:tags":[
        "foam",
        "fabrication"
    ],
    "wof:name":"Southwestern Foam Technologies",
    "wof:placetype":"venue"
},
  "geometry": {"coordinates":[-97.463373,31.075311],"type":"Point"}
}