{
  "type": "Feature",
  "properties": {
    "iso:country":"US",
    "sg:address":"8054 Streamside Dr",
    "sg:city":"Houston",
    "sg:classifiers":[
        {
            "category":"Autos & Motor Vehicles",
            "subcategory":"Automobile Sales",
            "type":"Retail Goods"
        }
    ],
    "sg:phone":"+1 281 272 5600",
    "sg:postcode":"77088",
    "sg:province":"TX",
    "sg:tags":[
        "car",
        "dealer"
    ],
    "wof:name":"El Cierre Auto Sales",
    "wof:placetype":"venue"
},
  "geometry": {"coordinates":[-95.467597,29.88789],"type":"Point"}
}