{
  "type": "Feature",
  "properties": {
    "iso:country":"US",
    "sg:address":"2129 Greta Ln",
    "sg:city":"Fort Worth",
    "sg:classifiers":[
        {
            "category":"Organizations",
            "subcategory":"Religious Organization",
            "type":"Services"
        }
    ],
    "sg:phone":"+1 817 275 8500",
    "sg:postcode":"76120",
    "sg:province":"TX",
    "sg:tags":[
        "church"
    ],
    "wof:name":"Christian Soldiers",
    "wof:placetype":"venue"
},
  "geometry": {"coordinates":[-97.165153,32.749516],"type":"Point"}
}