{
  "type": "Feature",
  "properties": {
    "iso:country":"US",
    "sg:address":"4224 Hyde Park Dr",
    "sg:city":"Mesquite",
    "sg:classifiers":[
        {
            "category":"Building & Trades",
            "subcategory":"Construction",
            "type":"Services"
        }
    ],
    "sg:phone":"+1 972 613 0679",
    "sg:postcode":"75150",
    "sg:province":"TX",
    "sg:tags":[
        "house"
    ],
    "wof:name":"Custom Home Repairs Mesquit",
    "wof:placetype":"venue"
},
  "geometry": {"coordinates":[-96.653425,32.824487],"type":"Point"}
}