{
  "type": "Feature",
  "properties": {
    "iso:country":"US",
    "sg:address":"13445 East Fwy",
    "sg:city":"Houston",
    "sg:classifiers":[
        {
            "category":"Health Services",
            "subcategory":"Chiropractor",
            "type":"Services"
        }
    ],
    "sg:phone":"+1 713 451 9911",
    "sg:postcode":"77015",
    "sg:province":"TX",
    "wof:name":"RUdOlph Yvonne DC",
    "wof:placetype":"venue"
},
  "geometry": {"coordinates":[-95.185417,29.771144],"type":"Point"}
}