{
  "type": "Feature",
  "properties": {
    "iso:country":"US",
    "sg:address":"9090 Jollyville Road",
    "sg:city":"Austin",
    "sg:classifiers":[
        {
            "category":"Building & Trades",
            "subcategory":"Construction",
            "type":"Services"
        }
    ],
    "sg:phone":"+1 512 345 4813",
    "sg:postcode":"78759",
    "sg:province":"TX",
    "sg:tags":[
        "contractor"
    ],
    "wof:name":"Kang R",
    "wof:placetype":"venue"
},
  "geometry": {"coordinates":[-97.753311,30.40119],"type":"Point"}
}