{
  "type": "Feature",
  "properties": {
    "iso:country":"US",
    "sg:address":"3535 Shiloh Rd",
    "sg:city":"Tyler",
    "sg:classifiers":[
        {
            "category":"Manufacturing",
            "subcategory":"Buildings",
            "type":"Manufacturing & Wholesale Goods"
        },
        {
            "category":"Building & Trades",
            "subcategory":"Construction",
            "type":"Services"
        }
    ],
    "sg:phone":"+1 903 561 3000",
    "sg:postcode":"75707",
    "sg:province":"TX",
    "sg:tags":[
        "home",
        "builder",
        "contractor"
    ],
    "sg:website":"http://www.tylerbuilding.com",
    "wof:name":"Tyler Building Systems L.P.",
    "wof:placetype":"venue"
},
  "geometry": {"coordinates":[-95.24949700000001,32.295346],"type":"Point"}
}