{
  "type": "Feature",
  "properties": {
    "iso:country":"US",
    "sg:address":"3205 Parker St",
    "sg:city":"Amarillo",
    "sg:classifiers":[
        {
            "category":"Real Estate",
            "subcategory":"Real Estate Agent",
            "type":"Services"
        }
    ],
    "sg:phone":"+1 806 358 0088",
    "sg:postcode":"79109",
    "sg:province":"TX",
    "wof:name":"Sr Genesis Management Company",
    "wof:placetype":"venue"
},
  "geometry": {"coordinates":[-101.855176,35.178347],"type":"Point"}
}