{
  "type": "Feature",
  "properties": {
    "iso:country":"US",
    "sg:address":"1900 Co Rd 3511",
    "sg:city":"Sulphur Springs",
    "sg:classifiers":[
        {
            "category":"Building & Trades",
            "subcategory":"Plumbing",
            "type":"Services"
        }
    ],
    "sg:phone":"+1 903 438 8017",
    "sg:postcode":"75474",
    "sg:province":"TX",
    "sg:tags":[
        "heating",
        "contractor"
    ],
    "wof:name":"Mc Garity's Heating & Air Cond",
    "wof:placetype":"venue"
},
  "geometry": {"coordinates":[-96.092629,32.955615],"type":"Point"}
}