{
  "type": "Feature",
  "properties": {
    "iso:country":"US",
    "sg:address":"3450 S Clack St",
    "sg:city":"Abilene",
    "sg:classifiers":[
        {
            "category":"Travel",
            "subcategory":"Hotels & Motels",
            "type":"Entertainment"
        }
    ],
    "sg:phone":"+1 325 695 7700",
    "sg:postcode":"79606",
    "sg:province":"TX",
    "wof:name":"Ramada Inn",
    "wof:placetype":"venue"
},
  "geometry": {"coordinates":[-99.77130699999999,32.409343],"type":"Point"}
}