{
  "type": "Feature",
  "properties": {
    "iso:country":"US",
    "sg:address":"349 State Hwy 276",
    "sg:city":"Quinlan",
    "sg:classifiers":[
        {
            "category":"Professional",
            "subcategory":"Business Services",
            "type":"Services"
        }
    ],
    "sg:phone":"+1 903 447 3207",
    "sg:postcode":"75474",
    "sg:province":"TX",
    "wof:name":"Martin Enterprise",
    "wof:placetype":"venue"
},
  "geometry": {"coordinates":[-96.03809200000001,32.903552],"type":"Point"}
}