{
  "type": "Feature",
  "properties": {
    "iso:country":"US",
    "sg:address":"710 W Renner Rd",
    "sg:city":"Richardson",
    "sg:classifiers":[
        {
            "category":"Restaurant",
            "type":"Food & Drink"
        }
    ],
    "sg:phone":"+1 214 575 6868",
    "sg:postcode":"75080",
    "sg:province":"TX",
    "sg:tags":[
        "eating"
    ],
    "wof:name":"Tasty Egg Rolls Inc",
    "wof:placetype":"venue"
},
  "geometry": {"coordinates":[-96.73018500000001,32.997704],"type":"Point"}
}