{
  "type": "Feature",
  "properties": {
    "iso:country":"US",
    "sg:address":"8401 N Central Expy",
    "sg:city":"Dallas",
    "sg:classifiers":[
        {
            "category":"Professional",
            "subcategory":"Employment Agencies",
            "type":"Services"
        }
    ],
    "sg:phone":"+1 214 220 2033",
    "sg:postcode":"75225",
    "sg:province":"TX",
    "sg:tags":[
        "consultant",
        "search",
        "executive"
    ],
    "sg:website":"www.russellreynolds.com",
    "wof:name":"Russell Reynolds Associates",
    "wof:placetype":"venue"
},
  "geometry": {"coordinates":[-96.77038400000001,32.865336],"type":"Point"}
}