{
  "type": "Feature",
  "properties": {
    "iso:country":"US",
    "sg:address":"10151 Hammerly Blvd",
    "sg:city":"Houston",
    "sg:classifiers":[
        {
            "category":"Personal",
            "subcategory":"Beauty Salon",
            "type":"Services"
        }
    ],
    "sg:phone":"+1 713 461 0051",
    "sg:postcode":"77080",
    "sg:province":"TX",
    "wof:name":"Hair Designs",
    "wof:placetype":"venue"
},
  "geometry": {"coordinates":[-95.541887,29.81271],"type":"Point"}
}