{
  "type": "Feature",
  "properties": {
    "iso:country":"US",
    "sg:address":"9140 Paluxy Dr",
    "sg:city":"Tyler",
    "sg:classifiers":[
        {
            "category":"Professional",
            "subcategory":"Management & Consulting",
            "type":"Services"
        }
    ],
    "sg:phone":"+1 903 939 0018",
    "sg:postcode":"75703",
    "sg:province":"TX",
    "sg:tags":[
        "business"
    ],
    "wof:name":"Billups Consulting",
    "wof:placetype":"venue"
},
  "geometry": {"coordinates":[-95.277327,32.247872],"type":"Point"}
}