{
  "type": "Feature",
  "properties": {
    "iso:country":"US",
    "sg:address":"1101 Westlynn St",
    "sg:city":"Austin",
    "sg:classifiers":[
        {
            "category":"Coffee & Tea",
            "type":"Food & Drink"
        }
    ],
    "sg:phone":"+1 512 524 5049",
    "sg:postcode":"78703",
    "sg:province":"TX",
    "sg:website":"www.caffemedici.com/",
    "wof:name":"Caffe Medici",
    "wof:placetype":"venue"
},
  "geometry": {"coordinates":[-97.75934700000001,30.279483],"type":"Point"}
}