{
  "type": "Feature",
  "properties": {
    "iso:country":"US",
    "sg:address":"4920 Hondo Pass Ave",
    "sg:city":"El Paso",
    "sg:classifiers":[
        {
            "category":"Autos & Motor Vehicles",
            "subcategory":"Automobile Sales",
            "type":"Retail Goods"
        },
        {
            "category":"Manufacturing",
            "subcategory":"Aerospace",
            "type":"Manufacturing & Wholesale Goods"
        }
    ],
    "sg:phone":"+1 915 751 0228",
    "sg:postcode":"79924",
    "sg:province":"TX",
    "sg:tags":[
        "supply",
        "equipment",
        "aircraft",
        "parts",
        "mfg"
    ],
    "wof:name":"H Q Aviation",
    "wof:placetype":"venue"
},
  "geometry": {"coordinates":[-106.424021,31.869841],"type":"Point"}
}