{
  "type": "Feature",
  "properties": {
    "iso:country":"US",
    "sg:address":"104 Thistle Ct",
    "sg:city":"Lewisville",
    "sg:classifiers":[
        {
            "category":"Banks & Credit Unions",
            "subcategory":"Investment Brokerage",
            "type":"Services"
        }
    ],
    "sg:phone":"+1 972 317 8529",
    "sg:postcode":"75077",
    "sg:province":"TX",
    "wof:name":"Hoover Consulting",
    "wof:placetype":"venue"
},
  "geometry": {"coordinates":[-97.076089,33.074904],"type":"Point"}
}