{
  "type": "Feature",
  "properties": {
    "iso:country":"US",
    "sg:address":"1107 Dana St",
    "sg:city":"Bowie",
    "sg:classifiers":[
        {
            "category":"Personal",
            "type":"Services"
        }
    ],
    "sg:phone":"+1 940 872 2825",
    "sg:postcode":"76230",
    "sg:province":"TX",
    "wof:name":"Sun Sations",
    "wof:placetype":"venue"
},
  "geometry": {"coordinates":[-97.823894,33.553856],"type":"Point"}
}