{
  "type": "Feature",
  "properties": {
    "iso:country":"US",
    "sg:address":"10400 Socorro Rd",
    "sg:city":"El Paso",
    "sg:classifiers":[
        {
            "category":"Organizations",
            "subcategory":"Membership Organization",
            "type":"Services"
        },
        {
            "category":"Organizations",
            "subcategory":"Community Association",
            "type":"Services"
        }
    ],
    "sg:phone":"+1 915 860 9528",
    "sg:postcode":"79927",
    "sg:province":"TX",
    "wof:name":"Texas A & M Chud Colonias Prog",
    "wof:placetype":"venue"
},
  "geometry": {"coordinates":[-106.301192,31.646475],"type":"Point"}
}