{
  "type": "Feature",
  "properties": {
    "iso:country":"US",
    "sg:address":"3840 Airport Blvd",
    "sg:city":"Austin",
    "sg:classifiers":[
        {
            "category":"Banks & Credit Unions",
            "subcategory":"Bank",
            "type":"Services"
        }
    ],
    "sg:phone":"+1 512 476 3183",
    "sg:postcode":"78722",
    "sg:province":"TX",
    "sg:tags":[
        "depository",
        "banking"
    ],
    "wof:name":"Money Box The 9",
    "wof:placetype":"venue"
},
  "geometry": {"coordinates":[-97.70754700000001,30.291546],"type":"Point"}
}