{
  "type": "Feature",
  "properties": {
    "iso:country":"US",
    "sg:address":"10200 Cypress Hills Dr",
    "sg:city":"Fort Worth",
    "sg:classifiers":[
        {
            "category":"Building & Trades",
            "subcategory":"Construction",
            "type":"Services"
        }
    ],
    "sg:phone":"+1 817 237 2213",
    "sg:postcode":"76108",
    "sg:province":"TX",
    "sg:tags":[
        "dry wall",
        "contractor"
    ],
    "wof:name":"Duncan Dry Wall",
    "wof:placetype":"venue"
},
  "geometry": {"coordinates":[-97.504088,32.736446],"type":"Point"}
}