{
  "type": "Feature",
  "properties": {
    "iso:country":"US",
    "sg:address":"1700 George Bush Dr E",
    "sg:city":"College Station",
    "sg:classifiers":[
        {
            "category":"Home & Garden",
            "subcategory":"Household Appliances",
            "type":"Retail Goods"
        }
    ],
    "sg:phone":"+1 979 694 6825",
    "sg:postcode":"77840",
    "sg:province":"TX",
    "sg:tags":[
        "machine",
        "sewing"
    ],
    "wof:name":"Singer Sales",
    "wof:placetype":"venue"
},
  "geometry": {"coordinates":[-96.317358,30.618124],"type":"Point"}
}