{
  "type": "Feature",
  "properties": {
    "iso:country":"US",
    "sg:address":"121 S Prairieville St",
    "sg:city":"Athens",
    "sg:classifiers":[
        {
            "category":"Education",
            "subcategory":"Library",
            "type":"Public Place"
        }
    ],
    "sg:phone":"+1 903 677 6350",
    "sg:postcode":"75751",
    "sg:province":"TX",
    "wof:name":"Cw Murchison Memorial Lib",
    "wof:placetype":"venue"
},
  "geometry": {"coordinates":[-95.854968,32.204142],"type":"Point"}
}