{
  "type": "Feature",
  "properties": {
    "iso:country":"US",
    "sg:address":"1050 Yale Suite 7667",
    "sg:city":"Houston",
    "sg:classifiers":[
        {
            "category":"Real Estate",
            "subcategory":"Real Estate Operator",
            "type":"Services"
        }
    ],
    "sg:phone":"+1 713 518 5997",
    "sg:postcode":"77008",
    "sg:province":"TX",
    "sg:tags":[
        "apartment"
    ],
    "sg:website":"www.innerlooplandlords.com",
    "wof:name":"Inner Loop Landlords",
    "wof:placetype":"venue"
},
  "geometry": {"coordinates":[-95.398146,29.79037],"type":"Point"}
}