{
  "type": "Feature",
  "properties": {
    "iso:country":"US",
    "sg:address":"13840 Aston St",
    "sg:city":"Houston",
    "sg:classifiers":[
        {
            "category":"Autos & Motor Vehicles",
            "subcategory":"Recreational Vehicle Sales",
            "type":"Retail Goods"
        },
        {
            "category":"Retail",
            "subcategory":"Auto Rental",
            "type":"Services"
        }
    ],
    "sg:phone":"+1 713 895 0000",
    "sg:postcode":"77040",
    "sg:province":"TX",
    "sg:tags":[
        "renting",
        "leasing",
        "trailer"
    ],
    "wof:name":"Aaron's Trailers",
    "wof:placetype":"venue"
},
  "geometry": {"coordinates":[-95.527219,29.850968],"type":"Point"}
}