{
  "type": "Feature",
  "properties": {
    "iso:country":"US",
    "sg:address":"5170 Randolph Blvd",
    "sg:city":"San Antonio",
    "sg:classifiers":[
        {
            "category":"Retail",
            "subcategory":"Repair Shop",
            "type":"Services"
        }
    ],
    "sg:phone":"+1 210 653 3832",
    "sg:postcode":"78233",
    "sg:province":"TX",
    "sg:tags":[
        "reupholstery",
        "work",
        "refrigeration"
    ],
    "wof:name":"Hamms Custom Upholstery",
    "wof:placetype":"venue"
},
  "geometry": {"coordinates":[-98.38810700000001,29.525706],"type":"Point"}
}