{
  "type": "Feature",
  "properties": {
    "iso:country":"US",
    "sg:address":"1732 Holland",
    "sg:city":"Houston",
    "sg:classifiers":[
        {
            "category":"Wholesale",
            "subcategory":"Dairy",
            "type":"Manufacturing & Wholesale Goods"
        }
    ],
    "sg:phone":"+1 713 675 8821",
    "sg:postcode":"77029",
    "sg:province":"TX",
    "sg:tags":[
        "product"
    ],
    "wof:name":"Rainbo",
    "wof:placetype":"venue"
},
  "geometry": {"coordinates":[-95.233722,29.76077],"type":"Point"}
}