{
  "type": "Feature",
  "properties": {
    "iso:country":"US",
    "sg:address":"1801 N Velasco St",
    "sg:city":"Angleton",
    "sg:classifiers":[
        {
            "category":"Banks & Credit Unions",
            "subcategory":"Bank",
            "type":"Services"
        }
    ],
    "sg:phone":"+1 979 549 0822",
    "sg:postcode":"77515",
    "sg:province":"TX",
    "wof:name":"Woodforest National Bank",
    "wof:placetype":"venue"
},
  "geometry": {"coordinates":[-95.434127,29.197465],"type":"Point"}
}