{
  "type": "Feature",
  "properties": {
    "iso:country":"US",
    "sg:address":"3106 42nd St",
    "sg:city":"Lubbock",
    "sg:classifiers":[
        {
            "category":"Building & Trades",
            "subcategory":"Cleaning & Sanitation",
            "type":"Services"
        }
    ],
    "sg:phone":"+1 806 767 6734",
    "sg:postcode":"79413",
    "sg:province":"TX",
    "sg:tags":[
        "maintenance"
    ],
    "wof:name":"Tex Aus Cleaning Systems",
    "wof:placetype":"venue"
},
  "geometry": {"coordinates":[-101.88331599999999,33.556097],"type":"Point"}
}