{
  "type": "Feature",
  "properties": {
    "iso:country":"US",
    "sg:address":"1845 Precinct Line Rd Suite 107",
    "sg:city":"Hurst",
    "sg:classifiers":[
        {
            "category":"Health Services",
            "subcategory":"Nursing And Care Facility",
            "type":"Services"
        },
        {
            "category":"Health Services",
            "subcategory":"Health Practitioner",
            "type":"Services"
        },
        {
            "category":"Social Services",
            "subcategory":"Adult Care",
            "type":"Services"
        },
        {
            "category":"Health Services",
            "subcategory":"Hospice",
            "type":"Services"
        }
    ],
    "sg:phone":"+1 817 849 8880",
    "sg:postcode":"76054",
    "sg:province":"TX",
    "sg:tags":[
        "nurses-home",
        "nurse",
        "therapist",
        "physical",
        "home"
    ],
    "sg:website":"http://www.heartlandhomehealth.com/FtWorth",
    "wof:name":"Heartland Hospice Services",
    "wof:placetype":"venue"
},
  "geometry": {"coordinates":[-97.186188,32.849239],"type":"Point"}
}