{
  "type": "Feature",
  "properties": {
    "iso:country":"US",
    "sg:address":"305 SW 16th St",
    "sg:city":"Grand Prairie",
    "sg:classifiers":[
        {
            "category":"Shopping",
            "subcategory":"Books",
            "type":"Retail Goods"
        }
    ],
    "sg:phone":"+1 972 262 7070",
    "sg:postcode":"75051",
    "sg:province":"TX",
    "wof:name":"D L Jackson Enterprises",
    "wof:placetype":"venue"
},
  "geometry": {"coordinates":[-97.025254,32.737067],"type":"Point"}
}