{
  "type": "Feature",
  "properties": {
    "iso:country":"US",
    "sg:address":"110 N 15th St",
    "sg:city":"Lamesa",
    "sg:classifiers":[
        {
            "category":"Organizations",
            "subcategory":"Religious Organization",
            "type":"Services"
        }
    ],
    "sg:phone":"+1 806 872 5313",
    "sg:postcode":"79331",
    "sg:province":"TX",
    "sg:tags":[
        "clergy"
    ],
    "wof:name":"Foursquare Church Parsonage",
    "wof:placetype":"venue"
},
  "geometry": {"coordinates":[-101.95197,32.747452],"type":"Point"}
}