{
  "type": "Feature",
  "properties": {
    "iso:country":"US",
    "sg:address":"828 Heights Blvd",
    "sg:city":"Houston",
    "sg:classifiers":[
        {
            "category":"Shopping",
            "subcategory":"Used Merchandise",
            "type":"Retail Goods"
        }
    ],
    "sg:phone":"+1 713 864 0001",
    "sg:postcode":"77007",
    "sg:province":"TX",
    "wof:name":"Stringnet",
    "wof:placetype":"venue"
},
  "geometry": {"coordinates":[-95.397533,29.78648],"type":"Point"}
}