{
  "type": "Feature",
  "properties": {
    "iso:country":"US",
    "sg:address":"18512 Carrot St Ste 100",
    "sg:city":"Spring",
    "sg:classifiers":[
        {
            "category":"Building & Trades",
            "subcategory":"Pest Control",
            "type":"Services"
        }
    ],
    "sg:phone":"+1 281 351 9400",
    "sg:postcode":"77379",
    "sg:province":"TX",
    "sg:tags":[
        "industrial",
        "services-commercial"
    ],
    "wof:name":"Hart Pest & Termite Services, Inc",
    "wof:placetype":"venue"
},
  "geometry": {"coordinates":[-95.492771,30.039252],"type":"Point"}
}