{
  "type": "Feature",
  "properties": {
    "iso:country":"US",
    "sg:address":"506 E 2nd St",
    "sg:city":"Rio Grande City",
    "sg:classifiers":[
        {
            "category":"Wholesale",
            "subcategory":"Furniture",
            "type":"Manufacturing & Wholesale Goods"
        }
    ],
    "sg:phone":"+1 956 487 4550",
    "sg:postcode":"78582",
    "sg:province":"TX",
    "sg:tags":[
        "photocopying",
        "supply"
    ],
    "wof:name":"San Antonio Office Supplies",
    "wof:placetype":"venue"
},
  "geometry": {"coordinates":[-98.81643800000001,26.378612],"type":"Point"}
}