{
  "type": "Feature",
  "properties": {
    "iso:country":"US",
    "sg:address":"12309 Dessau Road",
    "sg:city":"Austin",
    "sg:classifiers":[
        {
            "category":"Restaurant",
            "type":"Food & Drink"
        }
    ],
    "sg:phone":"+1 512 491 8200",
    "sg:postcode":"78754",
    "sg:province":"TX",
    "sg:website":"www.jackinthebox.com",
    "wof:name":"Jack In the Box",
    "wof:placetype":"venue"
},
  "geometry": {"coordinates":[-97.648375,30.387413],"type":"Point"}
}