{
  "type": "Feature",
  "properties": {
    "iso:country":"US",
    "sg:address":"1500 Norwood Dr",
    "sg:city":"Hurst",
    "sg:classifiers":[
        {
            "category":"Professional",
            "subcategory":"Computer Services",
            "type":"Services"
        }
    ],
    "sg:phone":"+1 817 285 6100",
    "sg:postcode":"76054",
    "sg:province":"TX",
    "sg:tags":[
        "consultant",
        "designer"
    ],
    "wof:name":"Applogix Development Group Inc",
    "wof:placetype":"venue"
},
  "geometry": {"coordinates":[-97.16769499999999,32.841999],"type":"Point"}
}