{
  "type": "Feature",
  "properties": {
    "iso:country":"US",
    "sg:address":"1011 Westlake Drive",
    "sg:city":"West Lake Hills",
    "sg:classifiers":[
        {
            "category":"Building & Trades",
            "subcategory":"Construction",
            "type":"Services"
        }
    ],
    "sg:phone":"+1 512 327 7897",
    "sg:postcode":"78746",
    "sg:province":"TX",
    "sg:tags":[
        "contractor"
    ],
    "wof:name":"Sloan Construction Company",
    "wof:placetype":"venue"
},
  "geometry": {"coordinates":[-97.799291,30.291998],"type":"Point"}
}