{
  "type": "Feature",
  "properties": {
    "iso:country":"US",
    "sg:address":"514 W Sarah St",
    "sg:city":"Cuero",
    "sg:classifiers":[
        {
            "category":"Manufacturing",
            "subcategory":"Furniture",
            "type":"Manufacturing & Wholesale Goods"
        }
    ],
    "sg:phone":"+1 361 275 2422",
    "sg:postcode":"77954",
    "sg:province":"TX",
    "sg:tags":[
        "mfg",
        "fixture",
        "store",
        "custom"
    ],
    "sg:website":"www.lancasterindustries.com",
    "wof:name":"Lancaster Industries Inc",
    "wof:placetype":"venue"
},
  "geometry": {"coordinates":[-97.294892,29.098795],"type":"Point"}
}