{
  "type": "Feature",
  "properties": {
    "iso:country":"US",
    "sg:address":"15726 Aberdeen Trails Dr",
    "sg:city":"Houston",
    "sg:classifiers":[
        {
            "category":"Manufacturing",
            "subcategory":"Petroleum Products",
            "type":"Manufacturing & Wholesale Goods"
        },
        {
            "category":"Building & Trades",
            "subcategory":"Construction",
            "type":"Services"
        }
    ],
    "sg:phone":"+1 281 855 0338",
    "sg:postcode":"77095",
    "sg:province":"TX",
    "sg:tags":[
        "mfg",
        "paving",
        "asphalt",
        "contractor"
    ],
    "wof:name":"C B Construction Co",
    "wof:placetype":"venue"
},
  "geometry": {"coordinates":[-95.644992,29.911223],"type":"Point"}
}