{
  "type": "Feature",
  "properties": {
    "iso:country":"US",
    "sg:address":"11222 Della Torre Dr",
    "sg:city":"Austin",
    "sg:classifiers":[
        {
            "category":"Farming",
            "subcategory":"Livestock Farm",
            "type":"Manufacturing & Wholesale Goods"
        }
    ],
    "sg:phone":"+1 512 258 2787",
    "sg:postcode":"78750",
    "sg:province":"TX",
    "sg:tags":[
        "specialty",
        "animal"
    ],
    "wof:name":"Hobo Joe",
    "wof:placetype":"venue"
},
  "geometry": {"coordinates":[-97.80348499999999,30.437718],"type":"Point"}
}