{
  "type": "Feature",
  "properties": {
    "iso:country":"US",
    "sg:address":"6901 Branchwood Dr",
    "sg:city":"Austin",
    "sg:classifiers":[
        {
            "category":"Professional",
            "subcategory":"Art Services",
            "type":"Services"
        }
    ],
    "sg:phone":"+1 512 451 0707",
    "sg:postcode":"78744",
    "sg:province":"TX",
    "sg:tags":[
        "commercial",
        "design"
    ],
    "wof:name":"Dean Zebug Design",
    "wof:placetype":"venue"
},
  "geometry": {"coordinates":[-97.75928399999999,30.180861],"type":"Point"}
}