{
  "type": "Feature",
  "properties": {
    "iso:country":"US",
    "sg:address":"909 Business Park Dr",
    "sg:city":"Mission",
    "sg:classifiers":[
        {
            "category":"Health Services",
            "subcategory":"Nursing And Care Facility",
            "type":"Services"
        },
        {
            "category":"Health Services",
            "subcategory":"Health Practitioner",
            "type":"Services"
        },
        {
            "category":"Social Services",
            "subcategory":"Adult Care",
            "type":"Services"
        }
    ],
    "sg:phone":"+1 956 584 7103",
    "sg:postcode":"78572",
    "sg:province":"TX",
    "sg:tags":[
        "nurses-home",
        "nurse",
        "eldercare-home",
        "home"
    ],
    "wof:name":"Expert Home Health Care Inc",
    "wof:placetype":"venue"
},
  "geometry": {"coordinates":[-98.318319,26.196301],"type":"Point"}
}