{
  "type": "Feature",
  "properties": {
    "iso:country":"US",
    "sg:address":"4540 Lawnview Ave",
    "sg:city":"Dallas",
    "sg:classifiers":[
        {
            "category":"Personal",
            "subcategory":"Barber",
            "type":"Services"
        }
    ],
    "sg:phone":"+1 214 388 0237",
    "sg:postcode":"75227",
    "sg:province":"TX",
    "wof:name":"Boyz On The Cut Barber Shop",
    "wof:placetype":"venue"
},
  "geometry": {"coordinates":[-96.722292,32.784362],"type":"Point"}
}