{
  "type": "Feature",
  "properties": {
    "iso:country":"US",
    "sg:address":"248 Justin Rd",
    "sg:city":"Plano",
    "sg:classifiers":[
        {
            "category":"Professional",
            "subcategory":"Management & Consulting",
            "type":"Services"
        }
    ],
    "sg:phone":"+1 214 770 0408",
    "sg:postcode":"75094",
    "sg:province":"TX",
    "wof:name":"Msk & Associates",
    "wof:placetype":"venue"
},
  "geometry": {"coordinates":[-96.631203,33.016215],"type":"Point"}
}