{
  "type": "Feature",
  "properties": {
    "iso:country":"US",
    "sg:address":"5720 Bandera Rd",
    "sg:city":"San Antonio",
    "sg:classifiers":[
        {
            "category":"Autos & Motor Vehicles",
            "subcategory":"Automobile Sales",
            "type":"Retail Goods"
        }
    ],
    "sg:phone":"+1 210 682 8811",
    "sg:postcode":"78238",
    "sg:province":"TX",
    "sg:tags":[
        "car",
        "dealer"
    ],
    "wof:name":"Cavender Online",
    "wof:placetype":"venue"
},
  "geometry": {"coordinates":[-98.598682,29.482075],"type":"Point"}
}