{
  "type": "Feature",
  "properties": {
    "iso:country":"US",
    "sg:address":"1406 Stonehollow Dr",
    "sg:city":"Humble",
    "sg:classifiers":[
        {
            "category":"Building & Trades",
            "subcategory":"Construction",
            "type":"Services"
        }
    ],
    "sg:phone":"+1 281 358 4332",
    "sg:postcode":"77339",
    "sg:province":"TX",
    "sg:tags":[
        "repairing",
        "remodeling",
        "contractor"
    ],
    "wof:name":"American Restoration Inc",
    "wof:placetype":"venue"
},
  "geometry": {"coordinates":[-95.237359,30.051467],"type":"Point"}
}