{
  "type": "Feature",
  "properties": {
    "iso:country":"US",
    "sg:address":"1438 S Denley Dr",
    "sg:city":"Dallas",
    "sg:classifiers":[
        {
            "category":"Organizations",
            "subcategory":"Religious Organization",
            "type":"Services"
        }
    ],
    "sg:phone":"+1 214 943 2202",
    "sg:postcode":"75216",
    "sg:province":"TX",
    "sg:tags":[
        "church"
    ],
    "wof:name":"Greater Love COGIC",
    "wof:placetype":"venue"
},
  "geometry": {"coordinates":[-96.80540499999999,32.72991],"type":"Point"}
}