{
  "type": "Feature",
  "properties": {
    "iso:country":"US",
    "sg:address":"1101 E Saunders St",
    "sg:city":"Laredo",
    "sg:classifiers":[
        {
            "category":"Shopping",
            "subcategory":"Musical Instruments",
            "type":"Retail Goods"
        }
    ],
    "sg:phone":"+1 956 726 9111",
    "sg:postcode":"78041",
    "sg:province":"TX",
    "sg:tags":[
        "store"
    ],
    "wof:name":"Elmo Lopez Music Center",
    "wof:placetype":"venue"
},
  "geometry": {"coordinates":[-99.48445599999999,27.530561],"type":"Point"}
}