{
  "type": "Feature",
  "properties": {
    "iso:country":"US",
    "sg:address":"4412 Legacy Dr",
    "sg:city":"Plano",
    "sg:classifiers":[
        {
            "category":"Organizations",
            "subcategory":"Religious Organization",
            "type":"Services"
        }
    ],
    "sg:phone":"+1 972 618 7033",
    "sg:postcode":"75024",
    "sg:province":"TX",
    "wof:name":"Atonement Lutheran Church",
    "wof:placetype":"venue"
},
  "geometry": {"coordinates":[-96.77762300000001,33.070522],"type":"Point"}
}