{
  "type": "Feature",
  "properties": {
    "iso:country":"US",
    "sg:address":"3210 N Shepherd Dr",
    "sg:city":"Houston",
    "sg:classifiers":[
        {
            "category":"Autos & Motor Vehicles",
            "subcategory":"Fuel & Gas Station",
            "type":"Retail Goods"
        }
    ],
    "sg:phone":"+1 713 861 0345",
    "sg:postcode":"77018",
    "sg:province":"TX",
    "sg:tags":[
        "oil"
    ],
    "wof:name":"Kim's Service Station",
    "wof:placetype":"venue"
},
  "geometry": {"coordinates":[-95.41033899999999,29.816457],"type":"Point"}
}