{
  "type": "Feature",
  "properties": {
    "iso:country":"US",
    "sg:address":"15400 Knoll Trail Dr",
    "sg:city":"Dallas",
    "sg:classifiers":[
        {
            "category":"Banks & Credit Unions",
            "subcategory":"Bank",
            "type":"Services"
        }
    ],
    "sg:phone":"+1 972 221 2996",
    "sg:postcode":"75248",
    "sg:province":"TX",
    "sg:tags":[
        "mortgage",
        "loan",
        "broker",
        "real estate"
    ],
    "sg:website":"www.wwmortgage.com",
    "wof:name":"Worldwide Mortgage Co",
    "wof:placetype":"venue"
},
  "geometry": {"coordinates":[-96.818901,32.962898],"type":"Point"}
}