{
  "type": "Feature",
  "properties": {
    "iso:country":"US",
    "sg:address":"2463 E Long Ave",
    "sg:city":"Fort Worth",
    "sg:classifiers":[
        {
            "category":"Manufacturing",
            "subcategory":"Tools & Machinery",
            "type":"Manufacturing & Wholesale Goods"
        },
        {
            "category":"Retail",
            "subcategory":"Auto Repair",
            "type":"Services"
        }
    ],
    "sg:phone":"+1 817 626 6800",
    "sg:postcode":"76106",
    "sg:province":"TX",
    "sg:tags":[
        "shop",
        "automobile",
        "machine",
        "industrial",
        "mfg"
    ],
    "wof:name":"Mike Smith Machine Shop",
    "wof:placetype":"venue"
},
  "geometry": {"coordinates":[-97.31787300000001,32.806447],"type":"Point"}
}