{
  "type": "Feature",
  "properties": {
    "iso:country":"US",
    "sg:address":"1025 Orlando Cir",
    "sg:city":"Plano",
    "sg:classifiers":[
        {
            "category":"Real Estate",
            "subcategory":"Real Estate Agent",
            "type":"Services"
        }
    ],
    "sg:phone":"+1 972 424 9555",
    "sg:postcode":"75075",
    "sg:province":"TX",
    "wof:name":"Oley Realtors",
    "wof:placetype":"venue"
},
  "geometry": {"coordinates":[-96.71616400000001,33.030885],"type":"Point"}
}