{
  "type": "Feature",
  "properties": {
    "iso:country":"US",
    "sg:address":"13259 Kidd Rd",
    "sg:city":"Conroe",
    "sg:classifiers":[
        {
            "category":"Retail",
            "subcategory":"Animal Services",
            "type":"Services"
        }
    ],
    "sg:phone":"+1 936 273 2042",
    "sg:postcode":"77302",
    "sg:province":"TX",
    "wof:name":"Wellmann Farms",
    "wof:placetype":"venue"
},
  "geometry": {"coordinates":[-95.429118,30.263706],"type":"Point"}
}