{
  "type": "Feature",
  "properties": {
    "iso:country":"US",
    "sg:address":"7404 Topeka Ave",
    "sg:city":"Lubbock",
    "sg:classifiers":[
        {
            "category":"Retail",
            "subcategory":"Repair Shop",
            "type":"Services"
        }
    ],
    "sg:phone":"+1 806 799 0165",
    "sg:postcode":"79424",
    "sg:province":"TX",
    "sg:tags":[
        "watch",
        "jewelry"
    ],
    "wof:name":"Nicholson Jewelers Inc",
    "wof:placetype":"venue"
},
  "geometry": {"coordinates":[-101.912719,33.525659],"type":"Point"}
}