{
  "type": "Feature",
  "properties": {
    "iso:country":"US",
    "sg:address":"1600 N 8th St",
    "sg:city":"Mcallen",
    "sg:classifiers":[
        {
            "category":"Shopping",
            "type":"Retail Goods"
        }
    ],
    "sg:phone":"+1 956 683 9335",
    "sg:postcode":"78501",
    "sg:province":"TX",
    "sg:tags":[
        "mexican"
    ],
    "wof:name":"Hacienda San Miguel",
    "wof:placetype":"venue"
},
  "geometry": {"coordinates":[-98.225371,26.21756],"type":"Point"}
}