{
  "type": "Feature",
  "properties": {
    "iso:country":"US",
    "sg:address":"12790 Bret Harte Dr",
    "sg:city":"El Paso",
    "sg:classifiers":[
        {
            "category":"Wholesale",
            "subcategory":"Durable Goods & Equipment",
            "type":"Manufacturing & Wholesale Goods"
        }
    ],
    "sg:phone":"+1 915 852 0602",
    "sg:postcode":"79928",
    "sg:province":"TX",
    "wof:name":"Antones Memories",
    "wof:placetype":"venue"
},
  "geometry": {"coordinates":[-106.242825,31.680764],"type":"Point"}
}