{
  "type": "Feature",
  "properties": {
    "iso:country":"US",
    "sg:address":"8410 E Hardy Rd",
    "sg:city":"Houston",
    "sg:classifiers":[
        {
            "category":"Freight",
            "type":"Transportation"
        },
        {
            "category":"Retail",
            "subcategory":"Auto Repair",
            "type":"Services"
        }
    ],
    "sg:phone":"+1 713 697 4906",
    "sg:postcode":"77093",
    "sg:province":"TX",
    "sg:tags":[
        "automobile",
        "storage",
        "general"
    ],
    "wof:name":"Hubbard Enterprises Inc",
    "wof:placetype":"venue"
},
  "geometry": {"coordinates":[-95.355152,29.833725],"type":"Point"}
}