{
  "type": "Feature",
  "properties": {
    "iso:country":"US",
    "sg:address":"7224 Misty Meadow Dr S",
    "sg:city":"Fort Worth",
    "sg:classifiers":[
        {
            "category":"Wholesale",
            "subcategory":"Durable Goods & Equipment",
            "type":"Manufacturing & Wholesale Goods"
        }
    ],
    "sg:phone":"+1 817 292 0141",
    "sg:postcode":"76133",
    "sg:province":"TX",
    "wof:name":"Personal Touch Portraits",
    "wof:placetype":"venue"
},
  "geometry": {"coordinates":[-97.377852,32.636957],"type":"Point"}
}