{
  "type": "Feature",
  "properties": {
    "iso:country":"US",
    "sg:address":"6359 Appaloosa Trl",
    "sg:city":"San Angelo",
    "sg:classifiers":[
        {
            "category":"Social Services",
            "subcategory":"Adult Care",
            "type":"Services"
        }
    ],
    "sg:phone":"+1 325 944 9564",
    "sg:postcode":"76901",
    "sg:province":"TX",
    "sg:tags":[
        "residential"
    ],
    "wof:name":"Rio Concho West",
    "wof:placetype":"venue"
},
  "geometry": {"coordinates":[-100.517016,31.430655],"type":"Point"}
}