{
  "type": "Feature",
  "properties": {
    "iso:country":"US",
    "sg:address":"701 Bluebonnet Cir",
    "sg:city":"Harker Heights",
    "sg:classifiers":[
        {
            "category":"Social Services",
            "type":"Services"
        }
    ],
    "sg:phone":"+1 254 698 6813",
    "sg:postcode":"76548",
    "sg:province":"TX",
    "wof:name":"Ames Counseling & Family Svc",
    "wof:placetype":"venue"
},
  "geometry": {"coordinates":[-97.638222,31.07612],"type":"Point"}
}