{
  "type": "Feature",
  "properties": {
    "iso:country":"US",
    "sg:address":"503 N 4th St",
    "sg:city":"Wills Point",
    "sg:classifiers":[
        {
            "category":"Cinema",
            "subcategory":"Movie Rental",
            "type":"Entertainment"
        }
    ],
    "sg:phone":"+1 903 873 4646",
    "sg:postcode":"75169",
    "sg:province":"TX",
    "sg:tags":[
        "leasing",
        "video",
        "disc",
        "tape"
    ],
    "wof:name":"O K Video",
    "wof:placetype":"venue"
},
  "geometry": {"coordinates":[-96.007667,32.714074],"type":"Point"}
}