{
  "type": "Feature",
  "properties": {
    "iso:country":"US",
    "sg:address":"2916 36th St",
    "sg:city":"Port Arthur",
    "sg:classifiers":[
        {
            "category":"Building & Trades",
            "subcategory":"Landscaping Services",
            "type":"Services"
        }
    ],
    "sg:phone":"+1 409 985 2929",
    "sg:postcode":"77642",
    "sg:province":"TX",
    "sg:tags":[
        "landscape",
        "contractor"
    ],
    "wof:name":"Apex Landscape Svc",
    "wof:placetype":"venue"
},
  "geometry": {"coordinates":[-93.945215,29.912339],"type":"Point"}
}