{
  "type": "Feature",
  "properties": {
    "iso:country":"US",
    "sg:address":"8071 Antoine Dr",
    "sg:city":"Houston",
    "sg:classifiers":[
        {
            "category":"Shopping",
            "subcategory":"Clothing, Apparel, & Fashions",
            "type":"Retail Goods"
        }
    ],
    "sg:phone":"+1 281 999 3871",
    "sg:postcode":"77088",
    "sg:province":"TX",
    "sg:tags":[
        "wig",
        "hairpiece",
        "beauty",
        "supply",
        "toupee",
        "cosmetic"
    ],
    "wof:name":"J S Beauty Supply",
    "wof:placetype":"venue"
},
  "geometry": {"coordinates":[-95.474098,29.8853],"type":"Point"}
}