{
  "type": "Feature",
  "properties": {
    "iso:country":"US",
    "sg:address":"2307 W 12th St",
    "sg:city":"Austin",
    "sg:classifiers":[
        {
            "category":"Real Estate",
            "subcategory":"Architect",
            "type":"Services"
        }
    ],
    "sg:phone":"+1 512 479 6475",
    "sg:postcode":"78703",
    "sg:province":"TX",
    "sg:tags":[
        "architectural"
    ],
    "wof:name":"Baez Architects",
    "wof:placetype":"venue"
},
  "geometry": {"coordinates":[-97.769558,30.285388],"type":"Point"}
}