{
  "type": "Feature",
  "properties": {
    "iso:country":"US",
    "sg:address":"108 C St",
    "sg:city":"Diboll",
    "sg:classifiers":[
        {
            "category":"Building & Trades",
            "subcategory":"Cleaning & Sanitation",
            "type":"Services"
        }
    ],
    "sg:phone":"+1 936 829 4130",
    "sg:postcode":"75941",
    "sg:province":"TX",
    "sg:tags":[
        "janitor"
    ],
    "wof:name":"Super T's Janitorial Svc",
    "wof:placetype":"venue"
},
  "geometry": {"coordinates":[-94.78380900000001,31.190607],"type":"Point"}
}