{
  "type": "Feature",
  "properties": {
    "iso:country":"US",
    "sg:address":"1122 Smith Rd",
    "sg:city":"Rockwall",
    "sg:classifiers":[
        {
            "category":"Building & Trades",
            "subcategory":"Construction",
            "type":"Services"
        }
    ],
    "sg:phone":"+1 214 629 5154",
    "sg:postcode":"75032",
    "sg:province":"TX",
    "sg:tags":[
        "home",
        "builder"
    ],
    "wof:name":"Country Aire Custom Homes",
    "wof:placetype":"venue"
},
  "geometry": {"coordinates":[-96.40097400000001,32.82853],"type":"Point"}
}