{
  "type": "Feature",
  "properties": {
    "iso:country":"US",
    "sg:address":"13027 Hiram Clarke Rd",
    "sg:city":"Houston",
    "sg:classifiers":[
        {
            "category":"Real Estate",
            "subcategory":"Real Estate Agent",
            "type":"Services"
        }
    ],
    "sg:phone":"+1 713 729 6212",
    "sg:postcode":"77045",
    "sg:province":"TX",
    "wof:name":"Hodge & Co Realtors",
    "wof:placetype":"venue"
},
  "geometry": {"coordinates":[-95.44627199999999,29.638168],"type":"Point"}
}