{
  "type": "Feature",
  "properties": {
    "iso:country":"US",
    "sg:address":"403 Pickford Dr",
    "sg:city":"Katy",
    "sg:classifiers":[
        {
            "category":"Manufacturing",
            "subcategory":"Tools & Machinery",
            "type":"Manufacturing & Wholesale Goods"
        }
    ],
    "sg:phone":"+1 281 392 1062",
    "sg:postcode":"77450",
    "sg:province":"TX",
    "sg:tags":[
        "machine",
        "vending",
        "mfg"
    ],
    "wof:name":"Faseler Sales Operations",
    "wof:placetype":"venue"
},
  "geometry": {"coordinates":[-95.764196,29.777208],"type":"Point"}
}