{
  "type": "Feature",
  "properties": {
    "iso:country":"US",
    "sg:address":"6320 Co Rd 1023",
    "sg:city":"Wolfe City",
    "sg:classifiers":[
        {
            "category":"Professional",
            "subcategory":"Business Services",
            "type":"Services"
        }
    ],
    "sg:phone":"+1 903 496 9202",
    "sg:postcode":"75496",
    "sg:province":"TX",
    "wof:name":"Buchanan Industrial Group Inc",
    "wof:placetype":"venue"
},
  "geometry": {"coordinates":[-96.11425199999999,33.31107],"type":"Point"}
}