{
  "type": "Feature",
  "properties": {
    "iso:country":"US",
    "sg:address":"4813 Fredericksburg Rd",
    "sg:city":"San Antonio",
    "sg:classifiers":[
        {
            "category":"Social Services",
            "subcategory":"Job Training",
            "type":"Services"
        }
    ],
    "sg:phone":"+1 210 344 7300",
    "sg:postcode":"78229",
    "sg:province":"TX",
    "sg:tags":[
        "rehabilitation"
    ],
    "wof:name":"Hernandez Disability Mgmt",
    "wof:placetype":"venue"
},
  "geometry": {"coordinates":[-98.55610900000001,29.497152],"type":"Point"}
}