{
  "type": "Feature",
  "properties": {
    "iso:country":"US",
    "sg:address":"10046 Rosbrook Dr",
    "sg:city":"Houston",
    "sg:classifiers":[
        {
            "category":"Communications",
            "subcategory":"Film & Video Production",
            "type":"Services"
        }
    ],
    "sg:phone":"+1 281 999 6855",
    "sg:postcode":"77038",
    "sg:province":"TX",
    "sg:tags":[
        "motion"
    ],
    "wof:name":"Black-Out",
    "wof:placetype":"venue"
},
  "geometry": {"coordinates":[-95.434568,29.911777],"type":"Point"}
}