{
  "type": "Feature",
  "properties": {
    "iso:country":"US",
    "sg:address":"15381 Tradesman",
    "sg:city":"San Antonio",
    "sg:classifiers":[
        {
            "category":"Building & Trades",
            "subcategory":"Plumbing",
            "type":"Services"
        }
    ],
    "sg:phone":"+1 210 764 2004",
    "sg:postcode":"78249",
    "sg:province":"TX",
    "sg:tags":[
        "conditioning",
        "air",
        "system",
        "contractor"
    ],
    "wof:name":"C B Svc",
    "wof:placetype":"venue"
},
  "geometry": {"coordinates":[-98.58493799999999,29.58886],"type":"Point"}
}