{
  "type": "Feature",
  "properties": {
    "iso:country":"US",
    "sg:address":"423 Gilmer Rd",
    "sg:city":"Longview",
    "sg:classifiers":[
        {
            "category":"Banks & Credit Unions",
            "subcategory":"Bank",
            "type":"Services"
        }
    ],
    "sg:phone":"+1 903 753 5588",
    "sg:postcode":"75604",
    "sg:province":"TX",
    "sg:website":"www.telcoplus.com",
    "wof:name":"Telco Plus Credit Union",
    "wof:placetype":"venue"
},
  "geometry": {"coordinates":[-94.7688,32.51007],"type":"Point"}
}