{
  "type": "Feature",
  "properties": {
    "iso:country":"US",
    "sg:address":"631 N Resler Dr",
    "sg:city":"El Paso",
    "sg:classifiers":[
        {
            "category":"Restaurant",
            "type":"Food & Drink"
        }
    ],
    "sg:phone":"+1 915 307 3057",
    "sg:postcode":"79912",
    "sg:province":"TX",
    "wof:name":"La Jolla Kitchen",
    "wof:placetype":"venue"
},
  "geometry": {"coordinates":[-106.552842,31.847857],"type":"Point"}
}