{
  "type": "Feature",
  "properties": {
    "iso:country":"US",
    "sg:address":"1700 Clinton Dr",
    "sg:city":"Galena Park",
    "sg:classifiers":[
        {
            "category":"Autos & Motor Vehicles",
            "subcategory":"Automobile Sales",
            "type":"Retail Goods"
        }
    ],
    "sg:phone":"+1 713 675 0559",
    "sg:postcode":"77547",
    "sg:province":"TX",
    "sg:tags":[
        "car",
        "used",
        "dealer"
    ],
    "wof:name":"Galena Park Motors Inc",
    "wof:placetype":"venue"
},
  "geometry": {"coordinates":[-95.24012999999999,29.732439],"type":"Point"}
}