{
  "type": "Feature",
  "properties": {
    "iso:country":"US",
    "sg:address":"208 Drake Ln",
    "sg:city":"Taylor",
    "sg:classifiers":[
        {
            "category":"Shopping",
            "subcategory":"Jewelry",
            "type":"Retail Goods"
        }
    ],
    "sg:phone":"+1 512 352 6260",
    "sg:postcode":"76574",
    "sg:province":"TX",
    "sg:tags":[
        "jeweler"
    ],
    "wof:name":"Karat's Unlimited",
    "wof:placetype":"venue"
},
  "geometry": {"coordinates":[-97.414737,30.588677],"type":"Point"}
}