{
  "type": "Feature",
  "properties": {
    "iso:country":"US",
    "sg:address":"4432 Old 36 Rd",
    "sg:city":"Bellville",
    "sg:classifiers":[
        {
            "category":"Bars & Pubs",
            "type":"Food & Drink"
        }
    ],
    "sg:phone":"+1 979 865 0999",
    "sg:postcode":"77418",
    "sg:province":"TX",
    "wof:name":"Blue Moon Saloon",
    "wof:placetype":"venue"
},
  "geometry": {"coordinates":[-96.34811999999999,30.049417],"type":"Point"}
}