{
  "type": "Feature",
  "properties": {
    "iso:country":"US",
    "sg:address":"5103 I- 30",
    "sg:city":"Greenville",
    "sg:classifiers":[
        {
            "category":"Travel",
            "subcategory":"Hotels & Motels",
            "type":"Entertainment"
        }
    ],
    "sg:phone":"+1 903 455 8808",
    "sg:postcode":"75402",
    "sg:province":"TX",
    "wof:name":"Economy Inn",
    "wof:placetype":"venue"
},
  "geometry": {"coordinates":[-96.09716,33.119314],"type":"Point"}
}