{
  "type": "Feature",
  "properties": {
    "iso:country":"US",
    "sg:address":"8140 Quail Hollow",
    "sg:city":"Texarkana",
    "sg:classifiers":[
        {
            "category":"Professional",
            "subcategory":"Management & Consulting",
            "type":"Services"
        }
    ],
    "sg:phone":"+1 903 832 2691",
    "sg:postcode":"75503",
    "sg:province":"TX",
    "sg:tags":[
        "break",
        "coffee",
        "supply"
    ],
    "wof:name":"Twin City Coffee Svc",
    "wof:placetype":"venue"
},
  "geometry": {"coordinates":[-94.163645,33.481442],"type":"Point"}
}