{
  "type": "Feature",
  "properties": {
    "iso:country":"US",
    "sg:address":"3200 Johnson Rd",
    "sg:city":"Southlake",
    "sg:classifiers":[
        {
            "category":"Shopping",
            "subcategory":"Computers & Home Electronics",
            "type":"Retail Goods"
        }
    ],
    "sg:phone":"+1 817 379 8520",
    "sg:postcode":"76092",
    "sg:province":"TX",
    "wof:name":"Original Production",
    "wof:placetype":"venue"
},
  "geometry": {"coordinates":[-97.20134,32.941716],"type":"Point"}
}