{
  "type": "Feature",
  "properties": {
    "iso:country":"US",
    "sg:address":"5580 Frost St",
    "sg:city":"Beaumont",
    "sg:classifiers":[
        {
            "category":"Real Estate",
            "subcategory":"Real Estate Services",
            "type":"Services"
        }
    ],
    "sg:phone":"+1 409 896 5356",
    "sg:postcode":"77706",
    "sg:province":"TX",
    "sg:tags":[
        "rental"
    ],
    "wof:name":"Hemmings Rental Properties",
    "wof:placetype":"venue"
},
  "geometry": {"coordinates":[-94.156736,30.088386],"type":"Point"}
}