{
  "type": "Feature",
  "properties": {
    "iso:country":"US",
    "sg:address":"2401 Seasons Rd",
    "sg:city":"Arlington",
    "sg:classifiers":[
        {
            "category":"Professional",
            "type":"Services"
        }
    ],
    "sg:phone":"+1 817 303 3557",
    "sg:postcode":"76014",
    "sg:province":"TX",
    "wof:name":"Kendall Jackson",
    "wof:placetype":"venue"
},
  "geometry": {"coordinates":[-97.06362799999999,32.702847],"type":"Point"}
}