{
  "type": "Feature",
  "properties": {
    "iso:country":"US",
    "sg:address":"5307 Mockingbird Ln",
    "sg:city":"Dallas",
    "sg:classifiers":[
        {
            "category":"Shopping",
            "subcategory":"Florist",
            "type":"Retail Goods"
        }
    ],
    "sg:phone":"+1 214 823 4311",
    "sg:postcode":"75206",
    "sg:province":"TX",
    "sg:website":"www.cymbidiumflowers.com",
    "wof:name":"Cymbidium A Floral Design",
    "wof:placetype":"venue"
},
  "geometry": {"coordinates":[-96.77866299999999,32.836585],"type":"Point"}
}