{
  "type": "Feature",
  "properties": {
    "iso:country":"US",
    "sg:address":"2231 W Gentry Pkwy",
    "sg:city":"Tyler",
    "sg:classifiers":[
        {
            "category":"Shopping",
            "subcategory":"Discount & Variety Stores",
            "type":"Retail Goods"
        }
    ],
    "sg:phone":"+1 903 526 7778",
    "sg:postcode":"75702",
    "sg:province":"TX",
    "sg:tags":[
        "merchandise",
        "general"
    ],
    "wof:name":"Just A Dollar",
    "wof:placetype":"venue"
},
  "geometry": {"coordinates":[-95.326702,32.367468],"type":"Point"}
}