{
  "type": "Feature",
  "properties": {
    "iso:country":"US",
    "sg:address":"4112 Tablerock Dr",
    "sg:city":"Austin",
    "sg:classifiers":[
        {
            "category":"Food & Beverages",
            "subcategory":"Specialty",
            "type":"Retail Goods"
        }
    ],
    "sg:phone":"+1 512 826 5520",
    "sg:postcode":"78731",
    "sg:province":"TX",
    "wof:name":"Chez Moi",
    "wof:placetype":"venue"
},
  "geometry": {"coordinates":[-97.763431,30.36739],"type":"Point"}
}