{
  "type": "Feature",
  "properties": {
    "iso:country":"US",
    "sg:address":"18953 Oakridge Dr",
    "sg:city":"Cleveland",
    "sg:classifiers":[
        {
            "category":"Banks & Credit Unions",
            "subcategory":"Investment Brokerage",
            "type":"Services"
        }
    ],
    "sg:phone":"+1 281 592 3510",
    "sg:postcode":"77328",
    "sg:province":"TX",
    "sg:tags":[
        "advisory"
    ],
    "wof:name":"Dan Heil & Assoc",
    "wof:placetype":"venue"
},
  "geometry": {"coordinates":[-95.275679,30.357196],"type":"Point"}
}