{
  "type": "Feature",
  "properties": {
    "iso:country":"US",
    "sg:address":"3700 9th Ave N",
    "sg:city":"Texas City",
    "sg:classifiers":[
        {
            "category":"Real Estate",
            "subcategory":"Real Estate Operator",
            "type":"Services"
        }
    ],
    "sg:phone":"+1 409 945 3700",
    "sg:postcode":"77590",
    "sg:province":"TX",
    "sg:tags":[
        "building",
        "apartment"
    ],
    "wof:name":"Veranda",
    "wof:placetype":"venue"
},
  "geometry": {"coordinates":[-94.952012,29.391764],"type":"Point"}
}