{
  "type": "Feature",
  "properties": {
    "iso:country":"US",
    "sg:address":"22522 Cove Hollow Dr",
    "sg:city":"Katy",
    "sg:classifiers":[
        {
            "category":"Professional",
            "subcategory":"Computer Services",
            "type":"Services"
        }
    ],
    "sg:phone":"+1 281 392 8491",
    "sg:postcode":"77450",
    "sg:province":"TX",
    "sg:tags":[
        "web",
        "system",
        "site",
        "desktop",
        "design",
        "publishing"
    ],
    "wof:name":"Solutions On Site",
    "wof:placetype":"venue"
},
  "geometry": {"coordinates":[-95.761408,29.756485],"type":"Point"}
}