{
  "type": "Feature",
  "properties": {
    "iso:country":"US",
    "sg:address":"13411 FM 812",
    "sg:city":"Del Valle",
    "sg:classifiers":[
        {
            "category":"Farming",
            "subcategory":"Livestock Farm",
            "type":"Manufacturing & Wholesale Goods"
        }
    ],
    "sg:phone":"+1 512 243 1397",
    "sg:postcode":"78617",
    "sg:province":"TX",
    "sg:tags":[
        "beef",
        "feedlot",
        "cattle"
    ],
    "wof:name":"Andy Alexander",
    "wof:placetype":"venue"
},
  "geometry": {"coordinates":[-97.635411,30.120742],"type":"Point"}
}