{
  "type": "Feature",
  "properties": {
    "iso:country":"US",
    "sg:address":"2503 Whitehurst Dr",
    "sg:city":"Fort Worth",
    "sg:classifiers":[
        {
            "category":"Personal",
            "type":"Services"
        }
    ],
    "sg:phone":"+1 817 294 3389",
    "sg:postcode":"76133",
    "sg:province":"TX",
    "wof:name":"Evelyns Closet",
    "wof:placetype":"venue"
},
  "geometry": {"coordinates":[-97.356061,32.643382],"type":"Point"}
}