{
  "type": "Feature",
  "properties": {
    "iso:country":"US",
    "sg:address":"11734 Barker Cypress Rd",
    "sg:city":"Cypress",
    "sg:classifiers":[
        {
            "category":"Real Estate",
            "subcategory":"Real Estate Agent",
            "type":"Services"
        }
    ],
    "sg:phone":"+1 832 334 0001",
    "sg:postcode":"77433",
    "sg:province":"TX",
    "wof:name":"Prudential Gary Greene Realtors",
    "wof:placetype":"venue"
},
  "geometry": {"coordinates":[-95.676789,29.946196],"type":"Point"}
}