{
  "type": "Feature",
  "properties": {
    "iso:country":"US",
    "sg:address":"1208 N I- 35",
    "sg:city":"Round Rock",
    "sg:classifiers":[
        {
            "category":"Health Services",
            "subcategory":"Clinic",
            "type":"Services"
        }
    ],
    "sg:phone":"+1 512 310 7665",
    "sg:postcode":"78628",
    "sg:province":"TX",
    "sg:tags":[
        "specialty",
        "outpatient"
    ],
    "wof:name":"Texas Health Services",
    "wof:placetype":"venue"
},
  "geometry": {"coordinates":[-97.673711,30.65833],"type":"Point"}
}