{
  "type": "Feature",
  "properties": {
    "iso:country":"US",
    "sg:address":"2655 FM 368 N",
    "sg:city":"Iowa Park",
    "sg:classifiers":[
        {
            "category":"Building & Trades",
            "subcategory":"Construction",
            "type":"Services"
        }
    ],
    "sg:phone":"+1 940 592 4530",
    "sg:postcode":"76367",
    "sg:province":"TX",
    "sg:tags":[
        "masonry",
        "contractor"
    ],
    "wof:name":"Rlh Masonry Inc",
    "wof:placetype":"venue"
},
  "geometry": {"coordinates":[-98.67307,33.971978],"type":"Point"}
}