{
  "type": "Feature",
  "properties": {
    "iso:country":"US",
    "sg:address":"104 Cottonwood St",
    "sg:city":"Lake Jackson",
    "sg:classifiers":[
        {
            "category":"Professional",
            "subcategory":"Employment Agencies",
            "type":"Services"
        }
    ],
    "sg:phone":"+1 979 266 8530",
    "sg:postcode":"77566",
    "sg:province":"TX",
    "sg:tags":[
        "help",
        "supply"
    ],
    "wof:name":"Americas Healthcare Staffing",
    "wof:placetype":"venue"
},
  "geometry": {"coordinates":[-95.427881,29.055201],"type":"Point"}
}