{
  "type": "Feature",
  "properties": {
    "iso:country":"US",
    "sg:address":"1127 Fort Worth Dr",
    "sg:city":"Denton",
    "sg:classifiers":[
        {
            "category":"Recreation",
            "type":"Entertainment"
        }
    ],
    "sg:phone":"+1 940 383 3573",
    "sg:postcode":"76205",
    "sg:province":"TX",
    "sg:tags":[
        "parlor",
        "billiard"
    ],
    "wof:name":"J R Pockets",
    "wof:placetype":"venue"
},
  "geometry": {"coordinates":[-97.140136,33.193302],"type":"Point"}
}