{
  "type": "Feature",
  "properties": {
    "iso:country":"US",
    "sg:address":"4527 Grey Dawn Dr",
    "sg:city":"Arlington",
    "sg:classifiers":[
        {
            "category":"Building & Trades",
            "subcategory":"Construction",
            "type":"Services"
        }
    ],
    "sg:phone":"+1 817 845 9800",
    "sg:postcode":"76017",
    "sg:province":"TX",
    "sg:tags":[
        "builder",
        "deck"
    ],
    "wof:name":"Masterpiece Deck & Tile",
    "wof:placetype":"venue"
},
  "geometry": {"coordinates":[-97.186199,32.673068],"type":"Point"}
}