{
  "type": "Feature",
  "properties": {
    "iso:country":"US",
    "sg:address":"16614 Sea Lark Rd",
    "sg:city":"Houston",
    "sg:classifiers":[
        {
            "category":"Recreation",
            "type":"Entertainment"
        }
    ],
    "sg:phone":"+1 281 480 1911",
    "sg:postcode":"77062",
    "sg:province":"TX",
    "wof:name":"Bridge Club",
    "wof:placetype":"venue"
},
  "geometry": {"coordinates":[-95.121583,29.55563],"type":"Point"}
}