{
  "type": "Feature",
  "properties": {
    "iso:country":"US",
    "sg:address":"17325 el Camino Real",
    "sg:city":"Houston",
    "sg:classifiers":[
        {
            "category":"Building & Trades",
            "subcategory":"Construction",
            "type":"Services"
        }
    ],
    "sg:phone":"+1 281 480 8883",
    "sg:postcode":"77058",
    "sg:province":"TX",
    "sg:tags":[
        "maker",
        "cabinet"
    ],
    "wof:name":"Kent Moore Cabinets",
    "wof:placetype":"venue"
},
  "geometry": {"coordinates":[-95.114385,29.551485],"type":"Point"}
}