{
  "type": "Feature",
  "properties": {
    "iso:country":"US",
    "sg:address":"431 W Wintergreen Rd",
    "sg:city":"Desoto",
    "sg:classifiers":[
        {
            "category":"Building & Trades",
            "subcategory":"Construction",
            "type":"Services"
        }
    ],
    "sg:phone":"+1 972 296 0523",
    "sg:postcode":"75115",
    "sg:province":"TX",
    "sg:tags":[
        "contractor"
    ],
    "wof:name":"Brasha Builders",
    "wof:placetype":"venue"
},
  "geometry": {"coordinates":[-96.865948,32.618707],"type":"Point"}
}