{
  "type": "Feature",
  "properties": {
    "iso:country":"US",
    "sg:address":"7773 Park Ave",
    "sg:city":"Terrell",
    "sg:classifiers":[
        {
            "category":"Professional",
            "subcategory":"Business Services",
            "type":"Services"
        }
    ],
    "sg:phone":"+1 972 524 1729",
    "sg:postcode":"75160",
    "sg:province":"TX",
    "wof:name":"Satyu Nr Enterprises",
    "wof:placetype":"venue"
},
  "geometry": {"coordinates":[-96.298708,32.671173],"type":"Point"}
}