{
  "type": "Feature",
  "properties": {
    "iso:country":"US",
    "sg:address":"310 W Crawford St",
    "sg:city":"Palestine",
    "sg:classifiers":[
        {
            "category":"Personal",
            "subcategory":"Beauty Salon",
            "type":"Services"
        }
    ],
    "sg:phone":"+1 903 731 4304",
    "sg:postcode":"75801",
    "sg:province":"TX",
    "wof:name":"K9 Classic Cuts",
    "wof:placetype":"venue"
},
  "geometry": {"coordinates":[-95.633589,31.763059],"type":"Point"}
}