{
  "type": "Feature",
  "properties": {
    "iso:country":"US",
    "sg:address":"926 W Baetz Blvd",
    "sg:city":"San Antonio",
    "sg:classifiers":[
        {
            "category":"Professional",
            "subcategory":"Business Services",
            "type":"Services"
        }
    ],
    "sg:phone":"+1 210 921 1714",
    "sg:postcode":"78221",
    "sg:province":"TX",
    "wof:name":"Rivercity Express Pay LLC",
    "wof:placetype":"venue"
},
  "geometry": {"coordinates":[-98.517681,29.332295],"type":"Point"}
}