{
  "type": "Feature",
  "properties": {
    "iso:country":"US",
    "sg:address":"403 W Hwy 90",
    "sg:city":"Dayton",
    "sg:classifiers":[
        {
            "category":"Restaurant",
            "type":"Food & Drink"
        }
    ],
    "sg:phone":"+1 936 258 5060",
    "sg:postcode":"77535",
    "sg:province":"TX",
    "wof:name":"Pappy's Bar-B-Que & Catering",
    "wof:placetype":"venue"
},
  "geometry": {"coordinates":[-94.89192199999999,30.042804],"type":"Point"}
}