{
  "type": "Feature",
  "properties": {
    "iso:country":"US",
    "sg:address":"1854 Lockhill Selma Rd",
    "sg:city":"San Antonio",
    "sg:classifiers":[
        {
            "category":"Health Services",
            "subcategory":"Hospital",
            "type":"Services"
        }
    ],
    "sg:phone":"+1 210 525 1979",
    "sg:postcode":"78213",
    "sg:province":"TX",
    "sg:tags":[
        "specialty"
    ],
    "wof:name":"Connections Center The",
    "wof:placetype":"venue"
},
  "geometry": {"coordinates":[-98.52366000000001,29.537435],"type":"Point"}
}