{
  "type": "Feature",
  "properties": {
    "iso:country":"US",
    "sg:address":"3010 Atascocita Rd",
    "sg:city":"Humble",
    "sg:classifiers":[
        {
            "category":"Autos & Motor Vehicles",
            "subcategory":"Automobile Sales",
            "type":"Retail Goods"
        }
    ],
    "sg:phone":"+1 832 605 1009",
    "sg:postcode":"77396",
    "sg:province":"TX",
    "sg:tags":[
        "car",
        "used"
    ],
    "sg:website":"http://www.sandmotorcars.com",
    "wof:name":"SAND Motorcars",
    "wof:placetype":"venue"
},
  "geometry": {"coordinates":[-95.226508,29.974414],"type":"Point"}
}