{
  "type": "Feature",
  "properties": {
    "iso:country":"US",
    "sg:address":"2720 Beechwood St",
    "sg:city":"Odessa",
    "sg:classifiers":[
        {
            "category":"Arts & Performance",
            "subcategory":"Theater",
            "type":"Entertainment"
        }
    ],
    "sg:phone":"+1 432 272 3835",
    "sg:postcode":"79761",
    "sg:province":"TX",
    "sg:tags":[
        "group"
    ],
    "wof:name":"Tinker Clown",
    "wof:placetype":"venue"
},
  "geometry": {"coordinates":[-102.333893,31.86704],"type":"Point"}
}