{
  "type": "Feature",
  "properties": {
    "iso:country":"US",
    "sg:address":"1015 E Davis St",
    "sg:city":"Luling",
    "sg:classifiers":[
        {
            "category":"Shopping",
            "type":"Retail Goods"
        }
    ],
    "sg:phone":"+1 830 875 0226",
    "sg:postcode":"78648",
    "sg:province":"TX",
    "sg:tags":[
        "pet",
        "shop"
    ],
    "wof:name":"Pet Project Texas Inc",
    "wof:placetype":"venue"
},
  "geometry": {"coordinates":[-97.64744,29.681394],"type":"Point"}
}