{
  "type": "Feature",
  "properties": {
    "iso:country":"US",
    "sg:address":"1801 W Harrison Ave",
    "sg:city":"Harlingen",
    "sg:classifiers":[
        {
            "category":"Autos & Motor Vehicles",
            "subcategory":"Automobile Sales",
            "type":"Retail Goods"
        }
    ],
    "sg:phone":"+1 956 428 9480",
    "sg:postcode":"78550",
    "sg:province":"TX",
    "sg:tags":[
        "car",
        "dealer"
    ],
    "wof:name":"Tarpon Auto Sales",
    "wof:placetype":"venue"
},
  "geometry": {"coordinates":[-97.71744200000001,26.19014],"type":"Point"}
}