{
  "type": "Feature",
  "properties": {
    "iso:country":"US",
    "sg:address":"13134 Dairy Ashford Rd",
    "sg:city":"Sugar Land",
    "sg:classifiers":[
        {
            "category":"Retail",
            "subcategory":"Laundry & Dry Cleaning",
            "type":"Services"
        }
    ],
    "sg:phone":"+1 281 313 4410",
    "sg:postcode":"77478",
    "sg:province":"TX",
    "sg:tags":[
        "drycleaning",
        "plant"
    ],
    "wof:name":"Deluxe Cleaners",
    "wof:placetype":"venue"
},
  "geometry": {"coordinates":[-95.597855,29.628592],"type":"Point"}
}