{
  "type": "Feature",
  "properties": {
    "iso:country":"US",
    "sg:address":"321 N Highland Ave",
    "sg:city":"Sherman",
    "sg:classifiers":[
        {
            "category":"Health Services",
            "subcategory":"Doctor",
            "type":"Services"
        }
    ],
    "sg:phone":"+1 903 465 4881",
    "sg:postcode":"75092",
    "sg:province":"TX",
    "sg:tags":[
        "medical"
    ],
    "wof:name":"Orthopedic Spt Medicine Assoc",
    "wof:placetype":"venue"
},
  "geometry": {"coordinates":[-96.623099,33.636711],"type":"Point"}
}