{
  "type": "Feature",
  "properties": {
    "iso:country":"US",
    "sg:address":"2105 Nathan Dr",
    "sg:city":"Austin",
    "sg:classifiers":[
        {
            "category":"Professional",
            "subcategory":"Testing Lab",
            "type":"Services"
        }
    ],
    "sg:phone":"+1 512 251 8388",
    "sg:postcode":"78728",
    "sg:province":"TX",
    "sg:tags":[
        "laboratory"
    ],
    "wof:name":"Jimmie Ann Bolton Laboratory",
    "wof:placetype":"venue"
},
  "geometry": {"coordinates":[-97.67540099999999,30.448027],"type":"Point"}
}