{
  "type": "Feature",
  "properties": {
    "iso:country":"US",
    "sg:address":"211 Rock Prairie Rd",
    "sg:city":"College Station",
    "sg:classifiers":[
        {
            "category":"Shopping",
            "subcategory":"Clothing, Apparel, & Fashions",
            "type":"Retail Goods"
        }
    ],
    "sg:phone":"+1 979 694 7463",
    "sg:postcode":"77845",
    "sg:province":"TX",
    "sg:tags":[
        "dancing",
        "supply"
    ],
    "wof:name":"A Dancers Trunk",
    "wof:placetype":"venue"
},
  "geometry": {"coordinates":[-96.308425,30.573145],"type":"Point"}
}