{
  "type": "Feature",
  "properties": {
    "iso:country":"US",
    "sg:address":"612 Keeler Ave",
    "sg:city":"Dalhart",
    "sg:classifiers":[
        {
            "category":"Farming",
            "subcategory":"Farm",
            "type":"Manufacturing & Wholesale Goods"
        }
    ],
    "sg:phone":"+1 806 377 6198",
    "sg:postcode":"79022",
    "sg:province":"TX",
    "wof:name":"Metcalf Farms Inc",
    "wof:placetype":"venue"
},
  "geometry": {"coordinates":[-102.52067,36.05947],"type":"Point"}
}