{
  "type": "Feature",
  "properties": {
    "iso:country":"US",
    "sg:address":"4500 S Versailles Ave",
    "sg:city":"Dallas",
    "sg:classifiers":[
        {
            "category":"Home & Garden",
            "subcategory":"Furniture",
            "type":"Retail Goods"
        }
    ],
    "sg:phone":"+1 214 599 9558",
    "sg:postcode":"75205",
    "sg:province":"TX",
    "wof:name":"Unique One",
    "wof:placetype":"venue"
},
  "geometry": {"coordinates":[-96.81555,32.830287],"type":"Point"}
}