{
  "type": "Feature",
  "properties": {
    "iso:country":"US",
    "sg:address":"1610 US Hwy 59",
    "sg:city":"Carthage",
    "sg:classifiers":[
        {
            "category":"Shopping",
            "subcategory":"Hobbies, Toys, & Games",
            "type":"Retail Goods"
        }
    ],
    "sg:phone":"+1 903 693 9182",
    "sg:postcode":"75633",
    "sg:province":"TX",
    "wof:name":"Wagon Yard",
    "wof:placetype":"venue"
},
  "geometry": {"coordinates":[-94.342511,32.200019],"type":"Point"}
}