{
  "type": "Feature",
  "properties": {
    "iso:country":"US",
    "sg:address":"820 Ferris Ave",
    "sg:city":"Waxahachie",
    "sg:classifiers":[
        {
            "category":"Banks & Credit Unions",
            "subcategory":"Bank",
            "type":"Services"
        }
    ],
    "sg:phone":"+1 214 630 3030",
    "sg:postcode":"75165",
    "sg:province":"TX",
    "wof:name":"Comerica Bank",
    "wof:placetype":"venue"
},
  "geometry": {"coordinates":[-96.846014,32.395117],"type":"Point"}
}