{
  "type": "Feature",
  "properties": {
    "iso:country":"US",
    "sg:address":"3205 E Houston St",
    "sg:city":"Paris",
    "sg:classifiers":[
        {
            "category":"Professional",
            "subcategory":"Business Services",
            "type":"Services"
        }
    ],
    "sg:phone":"+1 903 785 0063",
    "sg:postcode":"75460",
    "sg:province":"TX",
    "wof:name":"Spoken Emotion",
    "wof:placetype":"venue"
},
  "geometry": {"coordinates":[-95.513988,33.662249],"type":"Point"}
}