{
  "type": "Feature",
  "properties": {
    "iso:country":"US",
    "sg:address":"423 E Davis St",
    "sg:city":"Luling",
    "sg:classifiers":[
        {
            "category":"Shopping",
            "subcategory":"Discount & Variety Stores",
            "type":"Retail Goods"
        }
    ],
    "sg:phone":"+1 830 875 2504",
    "sg:postcode":"78648",
    "sg:province":"TX",
    "sg:tags":[
        "department"
    ],
    "wof:name":"Family Dollar Stores",
    "wof:placetype":"venue"
},
  "geometry": {"coordinates":[-97.639563,29.680041],"type":"Point"}
}