{
  "type": "Feature",
  "properties": {
    "iso:country":"US",
    "sg:address":"306 Grandview Dr",
    "sg:city":"Brownwood",
    "sg:classifiers":[
        {
            "category":"Travel",
            "subcategory":"Hotels & Motels",
            "type":"Entertainment"
        }
    ],
    "sg:phone":"+1 325 643 3145",
    "sg:postcode":"76802",
    "sg:province":"TX",
    "sg:tags":[
        "operation"
    ],
    "wof:name":"Early Lodging LLC",
    "wof:placetype":"venue"
},
  "geometry": {"coordinates":[-98.942787,31.746275],"type":"Point"}
}