{
  "type": "Feature",
  "properties": {
    "iso:country":"US",
    "sg:address":"700 Main St",
    "sg:city":"Marble Falls",
    "sg:classifiers":[
        {
            "category":"Real Estate",
            "subcategory":"Real Estate Agent",
            "type":"Services"
        }
    ],
    "sg:phone":"+1 830 693 8401",
    "sg:postcode":"78654",
    "sg:province":"TX",
    "wof:name":"Janie Spear Properties",
    "wof:placetype":"venue"
},
  "geometry": {"coordinates":[-98.27434100000001,30.576566],"type":"Point"}
}