{
  "type": "Feature",
  "properties": {
    "iso:country":"US",
    "sg:address":"3190 Sikes Dr",
    "sg:city":"Kempner",
    "sg:classifiers":[
        {
            "category":"Real Estate",
            "subcategory":"Real Estate Agent",
            "type":"Services"
        }
    ],
    "sg:phone":"+1 254 542 5140",
    "sg:postcode":"76539",
    "sg:province":"TX",
    "wof:name":"Soldiers Real Estate",
    "wof:placetype":"venue"
},
  "geometry": {"coordinates":[-97.900453,31.064889],"type":"Point"}
}