{
  "type": "Feature",
  "properties": {
    "iso:country":"US",
    "sg:address":"1560 Belvidere St",
    "sg:city":"El Paso",
    "sg:classifiers":[
        {
            "category":"Building & Trades",
            "subcategory":"Construction",
            "type":"Services"
        }
    ],
    "sg:phone":"+1 915 585 7667",
    "sg:postcode":"79912",
    "sg:province":"TX",
    "sg:tags":[
        "home",
        "builder"
    ],
    "wof:name":"Roma Homes Inc",
    "wof:placetype":"venue"
},
  "geometry": {"coordinates":[-106.518624,31.857041],"type":"Point"}
}