{
  "type": "Feature",
  "properties": {
    "iso:country":"US",
    "sg:address":"125 Maria Aly",
    "sg:city":"San Antonio",
    "sg:classifiers":[
        {
            "category":"Professional",
            "type":"Services"
        }
    ],
    "sg:phone":"+1 210 342 8338",
    "sg:postcode":"78207",
    "sg:province":"TX",
    "sg:tags":[
        "nonphysical",
        "commercial",
        "research"
    ],
    "wof:name":"Integrator Inc",
    "wof:placetype":"venue"
},
  "geometry": {"coordinates":[-98.514752,29.429628],"type":"Point"}
}