{
  "type": "Feature",
  "properties": {
    "iso:country":"US",
    "sg:address":"913 S Port Ave",
    "sg:city":"Corpus Christi",
    "sg:classifiers":[
        {
            "category":"Shopping",
            "subcategory":"Pharmacy",
            "type":"Retail Goods"
        }
    ],
    "sg:phone":"+1 361 883 8551",
    "sg:postcode":"78405",
    "sg:province":"TX",
    "wof:name":"Port Avenue Drug",
    "wof:placetype":"venue"
},
  "geometry": {"coordinates":[-97.42049799999999,27.780624],"type":"Point"}
}