{
  "type": "Feature",
  "properties": {
    "iso:country":"US",
    "sg:address":"300 Roe St",
    "sg:city":"Azle",
    "sg:classifiers":[
        {
            "category":"Food & Beverages",
            "subcategory":"Groceries & Convenience Stores",
            "type":"Retail Goods"
        }
    ],
    "sg:phone":"+1 817 444 5115",
    "sg:postcode":"76020",
    "sg:province":"TX",
    "wof:name":"Food Service",
    "wof:placetype":"venue"
},
  "geometry": {"coordinates":[-97.54347799999999,32.896566],"type":"Point"}
}