{
  "type": "Feature",
  "properties": {
    "iso:country":"US",
    "sg:address":"307 E Ave E",
    "sg:city":"Alpine",
    "sg:classifiers":[
        {
            "category":"Professional",
            "subcategory":"Computer Services",
            "type":"Services"
        }
    ],
    "sg:phone":"+1 432 837 2300",
    "sg:postcode":"79830",
    "sg:province":"TX",
    "sg:tags":[
        "repair"
    ],
    "wof:name":"Mountain Zone TV Systems",
    "wof:placetype":"venue"
},
  "geometry": {"coordinates":[-103.658765,30.359456],"type":"Point"}
}