{
  "type": "Feature",
  "properties": {
    "iso:country":"US",
    "sg:address":"4800 Turnback",
    "sg:city":"Leander",
    "sg:classifiers":[
        {
            "category":"Real Estate",
            "subcategory":"Surveying",
            "type":"Services"
        }
    ],
    "sg:phone":"+1 512 267 1235",
    "sg:postcode":"78645",
    "sg:province":"TX",
    "sg:tags":[
        "surveyor"
    ],
    "wof:name":"Lago Vista Surveyors",
    "wof:placetype":"venue"
},
  "geometry": {"coordinates":[-98.002213,30.446216],"type":"Point"}
}