{
  "type": "Feature",
  "properties": {
    "iso:country":"US",
    "sg:address":"4812 Dozier Rd",
    "sg:city":"Carrollton",
    "sg:classifiers":[
        {
            "category":"Building & Trades",
            "subcategory":"Construction",
            "type":"Services"
        }
    ],
    "sg:phone":"+1 972 939 1871",
    "sg:postcode":"75010",
    "sg:province":"TX",
    "sg:tags":[
        "concrete",
        "contractor"
    ],
    "wof:name":"Titan Concrete",
    "wof:placetype":"venue"
},
  "geometry": {"coordinates":[-96.862144,33.042397],"type":"Point"}
}