{
  "type": "Feature",
  "properties": {
    "iso:country":"US",
    "sg:address":"111 W Ave D",
    "sg:city":"Copperas Cove",
    "sg:classifiers":[
        {
            "category":"Cinema",
            "subcategory":"Movie Theater",
            "type":"Entertainment"
        }
    ],
    "sg:phone":"+1 254 547 2210",
    "sg:postcode":"76522",
    "sg:province":"TX",
    "sg:tags":[
        "motion",
        "picture"
    ],
    "wof:name":"Cove Theatre",
    "wof:placetype":"venue"
},
  "geometry": {"coordinates":[-97.90353500000001,31.124163],"type":"Point"}
}