{
  "type": "Feature",
  "properties": {
    "iso:country":"US",
    "sg:address":"506 Miramar Pl",
    "sg:city":"Corpus Christi",
    "sg:classifiers":[
        {
            "category":"Banks & Credit Unions",
            "subcategory":"Financial Services",
            "type":"Services"
        }
    ],
    "sg:phone":"+1 361 851 9519",
    "sg:postcode":"78411",
    "sg:province":"TX",
    "sg:tags":[
        "company",
        "holding"
    ],
    "wof:name":"Briscoe Holdings LTD",
    "wof:placetype":"venue"
},
  "geometry": {"coordinates":[-97.377402,27.733394],"type":"Point"}
}