{
  "type": "Feature",
  "properties": {
    "iso:country":"US",
    "sg:address":"110 E Vaughan St",
    "sg:city":"Bertram",
    "sg:classifiers":[
        {
            "category":"Banks & Credit Unions",
            "subcategory":"Bank",
            "type":"Services"
        }
    ],
    "sg:phone":"+1 512 355 2121",
    "sg:postcode":"78605",
    "sg:province":"TX",
    "wof:name":"Farmers State Bank",
    "wof:placetype":"venue"
},
  "geometry": {"coordinates":[-98.055854,30.743097],"type":"Point"}
}