{
  "type": "Feature",
  "properties": {
    "iso:country":"US",
    "sg:address":"13010 Abrams Rd",
    "sg:city":"Dallas",
    "sg:classifiers":[
        {
            "category":"Autos & Motor Vehicles",
            "subcategory":"Fuel & Gas Station",
            "type":"Retail Goods"
        }
    ],
    "sg:phone":"+1 972 699 8323",
    "sg:postcode":"75243",
    "sg:province":"TX",
    "wof:name":"Mobil Corp",
    "wof:placetype":"venue"
},
  "geometry": {"coordinates":[-96.73583499999999,32.924275],"type":"Point"}
}