{
  "type": "Feature",
  "properties": {
    "iso:country":"US",
    "sg:address":"4609 Orchid Ln",
    "sg:city":"Corpus Christi",
    "sg:classifiers":[
        {
            "category":"Building & Trades",
            "subcategory":"Electrical",
            "type":"Services"
        }
    ],
    "sg:phone":"+1 361 855 8932",
    "sg:postcode":"78416",
    "sg:province":"TX",
    "sg:tags":[
        "electrical",
        "contractor"
    ],
    "wof:name":"Santos Electric",
    "wof:placetype":"venue"
},
  "geometry": {"coordinates":[-97.428436,27.746744],"type":"Point"}
}