{
  "type": "Feature",
  "properties": {
    "iso:country":"US",
    "sg:address":"417 S Pacific St",
    "sg:city":"Mineola",
    "sg:classifiers":[
        {
            "category":"Shopping",
            "subcategory":"Used Merchandise",
            "type":"Retail Goods"
        }
    ],
    "sg:phone":"+1 903 569 2480",
    "sg:postcode":"75773",
    "sg:province":"TX",
    "sg:tags":[
        "pawnbroker"
    ],
    "wof:name":"Barney's Pawn & Gun",
    "wof:placetype":"venue"
},
  "geometry": {"coordinates":[-95.488771,32.660801],"type":"Point"}
}