{
  "type": "Feature",
  "properties": {
    "iso:country":"US",
    "sg:address":"2721 Southmore Ave",
    "sg:city":"Pasadena",
    "sg:classifiers":[
        {
            "category":"Shopping",
            "subcategory":"Department Store",
            "type":"Retail Goods"
        }
    ],
    "sg:phone":"+1 713 636 9021",
    "sg:postcode":"77502",
    "sg:province":"TX",
    "wof:name":"Christian Army Outlet",
    "wof:placetype":"venue"
},
  "geometry": {"coordinates":[-95.174014,29.691905],"type":"Point"}
}