{
  "type": "Feature",
  "properties": {
    "iso:country":"US",
    "sg:address":"1702 W US Hwy 287 Byp",
    "sg:city":"Waxahachie",
    "sg:classifiers":[
        {
            "category":"Organizations",
            "subcategory":"Religious Organization",
            "type":"Services"
        }
    ],
    "sg:phone":"+1 972 923 1443",
    "sg:postcode":"75165",
    "sg:province":"TX",
    "wof:name":"Harvest Baptist Church",
    "wof:placetype":"venue"
},
  "geometry": {"coordinates":[-96.85588,32.4246],"type":"Point"}
}