{
  "type": "Feature",
  "properties": {
    "iso:country":"US",
    "sg:address":"1026 Commercial Ave",
    "sg:city":"Anson",
    "sg:classifiers":[
        {
            "category":"Insurance",
            "subcategory":"Insurance Agent",
            "type":"Services"
        }
    ],
    "sg:phone":"+1 325 793 0231",
    "sg:postcode":"79501",
    "sg:province":"TX",
    "wof:name":"West Texas Insurance Svc",
    "wof:placetype":"venue"
},
  "geometry": {"coordinates":[-99.896852,32.757779],"type":"Point"}
}