{
  "type": "Feature",
  "properties": {
    "iso:country":"US",
    "sg:address":"1210 Wilston Ct",
    "sg:city":"Houston",
    "sg:classifiers":[
        {
            "category":"Local Transit",
            "type":"Transportation"
        }
    ],
    "sg:phone":"+1 281 759 8988",
    "sg:postcode":"77077",
    "sg:province":"TX",
    "sg:tags":[
        "limousine"
    ],
    "wof:name":"Lone Star Luimosine Svc",
    "wof:placetype":"venue"
},
  "geometry": {"coordinates":[-95.589904,29.757201],"type":"Point"}
}