{
  "type": "Feature",
  "properties": {
    "iso:country":"US",
    "sg:address":"135 Navasota Dr",
    "sg:city":"Bastrop",
    "sg:classifiers":[
        {
            "category":"Real Estate",
            "subcategory":"Real Estate Operator",
            "type":"Services"
        }
    ],
    "sg:phone":"+1 512 308 1030",
    "sg:postcode":"78602",
    "sg:province":"TX",
    "sg:tags":[
        "mobile",
        "home",
        "community"
    ],
    "wof:name":"Riverchase Mobile Home Park",
    "wof:placetype":"venue"
},
  "geometry": {"coordinates":[-97.29806499999999,30.19805],"type":"Point"}
}