{
  "type": "Feature",
  "properties": {
    "iso:country":"US",
    "sg:address":"10425 Sunflower Dr",
    "sg:city":"Waco",
    "sg:classifiers":[
        {
            "category":"Professional",
            "subcategory":"Computer Services",
            "type":"Services"
        }
    ],
    "sg:phone":"+1 254 836 8200",
    "sg:postcode":"76708",
    "sg:province":"TX",
    "sg:tags":[
        "website",
        "design"
    ],
    "wof:name":"Inovative Internet Solutions",
    "wof:placetype":"venue"
},
  "geometry": {"coordinates":[-97.246624,31.628143],"type":"Point"}
}