{
  "type": "Feature",
  "properties": {
    "iso:country":"US",
    "sg:address":"211 SW Military Dr",
    "sg:city":"San Antonio",
    "sg:classifiers":[
        {
            "category":"Restaurant",
            "type":"Food & Drink"
        }
    ],
    "sg:menulink":"http://www.allmenus.com/tx/san-antonio/218090-burger-king/menu/",
    "sg:phone":"+1 210 923 1135",
    "sg:postcode":"78221",
    "sg:province":"TX",
    "sg:tags":[
        "american"
    ],
    "wof:name":"Burger King",
    "wof:placetype":"venue"
},
  "geometry": {"coordinates":[-98.49370500000001,29.356863],"type":"Point"}
}