{
  "type": "Feature",
  "properties": {
    "iso:country":"US",
    "sg:address":"600 Travis St",
    "sg:city":"Houston",
    "sg:classifiers":[
        {
            "category":"Professional",
            "subcategory":"Lawyer & Legal Services",
            "type":"Services"
        }
    ],
    "sg:phone":"+1 713 220 3993",
    "sg:postcode":"77002",
    "sg:province":"TX",
    "sg:tags":[
        "information",
        "attorney",
        "referral"
    ],
    "wof:name":"Ervin Courtney",
    "wof:placetype":"venue"
},
  "geometry": {"coordinates":[-95.36348,29.760509],"type":"Point"}
}