{
  "type": "Feature",
  "properties": {
    "iso:country":"US",
    "sg:address":"9603 Wickenburg Dr",
    "sg:city":"Houston",
    "sg:classifiers":[
        {
            "category":"Wholesale",
            "subcategory":"Durable Goods & Equipment",
            "type":"Manufacturing & Wholesale Goods"
        }
    ],
    "sg:phone":"+1 281 495 4829",
    "sg:postcode":"77031",
    "sg:province":"TX",
    "wof:name":"Lyu Enterprises",
    "wof:placetype":"venue"
},
  "geometry": {"coordinates":[-95.548254,29.642155],"type":"Point"}
}