{
  "type": "Feature",
  "properties": {
    "iso:country":"US",
    "sg:address":"10121 FM 1097 W",
    "sg:city":"Willis",
    "sg:classifiers":[
        {
            "category":"Autos & Motor Vehicles",
            "subcategory":"Boat Sales",
            "type":"Retail Goods"
        }
    ],
    "sg:phone":"+1 936 856 2628",
    "sg:postcode":"77318",
    "sg:province":"TX",
    "sg:tags":[
        "equipment",
        "marine",
        "supply"
    ],
    "wof:name":"C & M Marine",
    "wof:placetype":"venue"
},
  "geometry": {"coordinates":[-95.505494,30.418669],"type":"Point"}
}