{
  "type": "Feature",
  "properties": {
    "iso:country":"US",
    "sg:address":"8207 N Loop Fwy",
    "sg:city":"Houston",
    "sg:classifiers":[
        {
            "category":"Wholesale",
            "subcategory":"Auto Parts",
            "type":"Manufacturing & Wholesale Goods"
        }
    ],
    "sg:phone":"+1 713 672 2100",
    "sg:postcode":"77029",
    "sg:province":"TX",
    "sg:tags":[
        "automobile",
        "rebuilt"
    ],
    "wof:name":"Certi-Fit Auto Body Parts",
    "wof:placetype":"venue"
},
  "geometry": {"coordinates":[-95.279433,29.802273],"type":"Point"}
}