{
  "type": "Feature",
  "properties": {
    "iso:country":"US",
    "sg:address":"2008 Castleberry Cut Off Rd",
    "sg:city":"Fort Worth",
    "sg:classifiers":[
        {
            "category":"Personal",
            "subcategory":"Beauty Salon",
            "type":"Services"
        }
    ],
    "sg:phone":"+1 817 624 9031",
    "sg:postcode":"76114",
    "sg:province":"TX",
    "sg:tags":[
        "shop"
    ],
    "wof:name":"Sonnier's Hair Care",
    "wof:placetype":"venue"
},
  "geometry": {"coordinates":[-97.39979200000001,32.790404],"type":"Point"}
}