{
  "type": "Feature",
  "properties": {
    "iso:country":"US",
    "sg:address":"2027 Peters Colony Rd E",
    "sg:city":"Carrollton",
    "sg:classifiers":[
        {
            "category":"Manufacturing",
            "subcategory":"Textiles",
            "type":"Manufacturing & Wholesale Goods"
        }
    ],
    "sg:phone":"+1 972 492 8507",
    "sg:postcode":"75007",
    "sg:province":"TX",
    "sg:tags":[
        "mill",
        "fabric"
    ],
    "wof:name":"Quality Quilting",
    "wof:placetype":"venue"
},
  "geometry": {"coordinates":[-96.88007899999999,33.00573],"type":"Point"}
}