{
  "type": "Feature",
  "properties": {
    "iso:country":"US",
    "sg:address":"13603 San Pedro Ave",
    "sg:city":"San Antonio",
    "sg:classifiers":[
        {
            "category":"Retail",
            "subcategory":"Auto Repair",
            "type":"Services"
        }
    ],
    "sg:phone":"+1 210 496 5408",
    "sg:postcode":"78232",
    "sg:province":"TX",
    "sg:tags":[
        "brake"
    ],
    "wof:name":"Brake Works",
    "wof:placetype":"venue"
},
  "geometry": {"coordinates":[-98.48235699999999,29.566155],"type":"Point"}
}