{
  "type": "Feature",
  "properties": {
    "iso:country":"US",
    "sg:address":"807 N Columbia St",
    "sg:city":"Plainview",
    "sg:classifiers":[
        {
            "category":"Professional",
            "type":"Services"
        }
    ],
    "sg:phone":"+1 806 293 3213",
    "sg:postcode":"79072",
    "sg:province":"TX",
    "sg:tags":[
        "establishment"
    ],
    "wof:name":"Uniting Parents",
    "wof:placetype":"venue"
},
  "geometry": {"coordinates":[-101.706925,34.189482],"type":"Point"}
}