{
  "type": "Feature",
  "properties": {
    "iso:country":"US",
    "sg:address":"5409 1st St",
    "sg:city":"Katy",
    "sg:classifiers":[
        {
            "category":"Building & Trades",
            "subcategory":"Construction",
            "type":"Services"
        }
    ],
    "sg:phone":"+1 281 391 2990",
    "sg:postcode":"77493",
    "sg:province":"TX",
    "sg:tags":[
        "automotive",
        "contractor",
        "repair"
    ],
    "wof:name":"Sturm Welding",
    "wof:placetype":"venue"
},
  "geometry": {"coordinates":[-95.81721,29.786412],"type":"Point"}
}