{
  "type": "Feature",
  "properties": {
    "iso:country":"US",
    "sg:address":"701 Hidden Woods Dr",
    "sg:city":"Keller",
    "sg:classifiers":[
        {
            "category":"Wholesale",
            "subcategory":"Photographic Equipment",
            "type":"Manufacturing & Wholesale Goods"
        }
    ],
    "sg:phone":"+1 817 788 9591",
    "sg:postcode":"76248",
    "sg:province":"TX",
    "sg:tags":[
        "audio"
    ],
    "wof:name":"Us Magnetics",
    "wof:placetype":"venue"
},
  "geometry": {"coordinates":[-97.20981500000001,32.920563],"type":"Point"}
}