{
  "type": "Feature",
  "properties": {
    "iso:country":"US",
    "sg:address":"12701 Veterans Memorial Dr",
    "sg:city":"Houston",
    "sg:classifiers":[
        {
            "category":"Banks & Credit Unions",
            "subcategory":"Bank",
            "type":"Services"
        }
    ],
    "sg:phone":"+1 281 880 6227",
    "sg:postcode":"77014",
    "sg:province":"TX",
    "sg:tags":[
        "mortgage"
    ],
    "wof:name":"Plainscapital McAfee Mortgage",
    "wof:placetype":"venue"
},
  "geometry": {"coordinates":[-95.486994,29.972657],"type":"Point"}
}