{
  "type": "Feature",
  "properties": {
    "iso:country":"US",
    "sg:address":"5000 Westheimer Rd",
    "sg:city":"Houston",
    "sg:classifiers":[
        {
            "category":"Shopping",
            "subcategory":"Clothing, Apparel, & Fashions",
            "type":"Retail Goods"
        }
    ],
    "sg:phone":"+1 713 840 7060",
    "sg:postcode":"77056",
    "sg:province":"TX",
    "sg:tags":[
        "ready",
        "accessory"
    ],
    "wof:name":"Caruggi's",
    "wof:placetype":"venue"
},
  "geometry": {"coordinates":[-95.461304,29.7409],"type":"Point"}
}