{
  "type": "Feature",
  "properties": {
    "iso:country":"US",
    "sg:address":"3301 Commerce St",
    "sg:city":"Houston",
    "sg:classifiers":[
        {
            "category":"Wholesale",
            "subcategory":"Hardware",
            "type":"Manufacturing & Wholesale Goods"
        }
    ],
    "sg:phone":"+1 713 225 1086",
    "sg:postcode":"77003",
    "sg:province":"TX",
    "sg:tags":[
        "plumbing",
        "supply"
    ],
    "wof:name":"Tipton Company",
    "wof:placetype":"venue"
},
  "geometry": {"coordinates":[-95.339794,29.751897],"type":"Point"}
}