{
  "type": "Feature",
  "properties": {
    "iso:country":"US",
    "sg:address":"5151 San Felipe St",
    "sg:city":"Houston",
    "sg:classifiers":[
        {
            "category":"Mining & Drilling",
            "type":"Manufacturing & Wholesale Goods"
        }
    ],
    "sg:phone":"+1 713 622 5420",
    "sg:postcode":"77056",
    "sg:province":"TX",
    "sg:tags":[
        "crude",
        "production",
        "gas"
    ],
    "wof:name":"Maralo LLC",
    "wof:placetype":"venue"
},
  "geometry": {"coordinates":[-95.46614700000001,29.750144],"type":"Point"}
}