{
  "type": "Feature",
  "properties": {
    "iso:country":"US",
    "sg:address":"5506 Greenwich Dr",
    "sg:city":"Arlington",
    "sg:classifiers":[
        {
            "category":"Shopping",
            "subcategory":"Jewelry",
            "type":"Retail Goods"
        }
    ],
    "sg:phone":"+1 817 557 2737",
    "sg:postcode":"76018",
    "sg:province":"TX",
    "wof:name":"Anitex Imports",
    "wof:placetype":"venue"
},
  "geometry": {"coordinates":[-97.09903,32.653746],"type":"Point"}
}