{
  "type": "Feature",
  "properties": {
    "iso:country":"US",
    "sg:address":"13529 Skinner Rd",
    "sg:city":"Cypress",
    "sg:classifiers":[
        {
            "category":"Wholesale",
            "subcategory":"Machinery & Supplies",
            "type":"Manufacturing & Wholesale Goods"
        }
    ],
    "sg:phone":"+1 281 213 9622",
    "sg:postcode":"77429",
    "sg:province":"TX",
    "sg:tags":[
        "equipment",
        "industrial"
    ],
    "wof:name":"Spray-On Products",
    "wof:placetype":"venue"
},
  "geometry": {"coordinates":[-95.687208,29.971349],"type":"Point"}
}