{
  "type": "Feature",
  "properties": {
    "iso:country":"US",
    "sg:address":"223 W 5th St",
    "sg:city":"Irving",
    "sg:classifiers":[
        {
            "category":"Real Estate",
            "subcategory":"Real Estate Operator",
            "type":"Services"
        }
    ],
    "sg:phone":"+1 972 254 9787",
    "sg:postcode":"75060",
    "sg:province":"TX",
    "sg:tags":[
        "building",
        "apartment"
    ],
    "wof:name":"Chellmont Apartments",
    "wof:placetype":"venue"
},
  "geometry": {"coordinates":[-96.94993599999999,32.809621],"type":"Point"}
}