{
  "type": "Feature",
  "properties": {
    "iso:country":"US",
    "sg:address":"4804 Martin Luther King Jr Blvd",
    "sg:city":"Houston",
    "sg:classifiers":[
        {
            "category":"Shopping",
            "subcategory":"Florist",
            "type":"Retail Goods"
        }
    ],
    "sg:phone":"+1 713 741 6647",
    "sg:postcode":"77021",
    "sg:province":"TX",
    "wof:name":"Flowers By Dorice",
    "wof:placetype":"venue"
},
  "geometry": {"coordinates":[-95.336716,29.708737],"type":"Point"}
}