{
  "type": "Feature",
  "properties": {
    "iso:country":"US",
    "sg:address":"2605 Crystal Falls Dr",
    "sg:city":"Mesquite",
    "sg:classifiers":[
        {
            "category":"Wholesale",
            "subcategory":"Medical Equipment & Supplies",
            "type":"Manufacturing & Wholesale Goods"
        }
    ],
    "sg:phone":"+1 972 222 9720",
    "sg:postcode":"75181",
    "sg:province":"TX",
    "sg:tags":[
        "physician",
        "surgeon"
    ],
    "wof:name":"National Medical Equipment",
    "wof:placetype":"venue"
},
  "geometry": {"coordinates":[-96.54194,32.741359],"type":"Point"}
}