{
  "type": "Feature",
  "properties": {
    "iso:country":"US",
    "sg:address":"813 Saddleback Ln",
    "sg:city":"Flower Mound",
    "sg:classifiers":[
        {
            "category":"Shopping",
            "subcategory":"Catalog Store",
            "type":"Retail Goods"
        }
    ],
    "sg:phone":"+1 972 691 4142",
    "sg:postcode":"75028",
    "sg:province":"TX",
    "sg:tags":[
        "house",
        "mail"
    ],
    "wof:name":"Unique Products Inc",
    "wof:placetype":"venue"
},
  "geometry": {"coordinates":[-97.040014,33.018093],"type":"Point"}
}