{
  "type": "Feature",
  "properties": {
    "iso:country":"US",
    "sg:address":"1607 E 8th St",
    "sg:city":"Odessa",
    "sg:classifiers":[
        {
            "category":"Health Services",
            "subcategory":"Chiropractor",
            "type":"Services"
        }
    ],
    "sg:phone":"+1 432 550 8875",
    "sg:postcode":"79761",
    "sg:province":"TX",
    "sg:tags":[
        "chiropractic"
    ],
    "wof:name":"Chiropractic Associates",
    "wof:placetype":"venue"
},
  "geometry": {"coordinates":[-102.351641,31.85975],"type":"Point"}
}