{
  "type": "Feature",
  "properties": {
    "iso:country":"US",
    "sg:address":"626 E Richard Ave",
    "sg:city":"Kingsville",
    "sg:classifiers":[
        {
            "category":"Restaurant",
            "type":"Food & Drink"
        }
    ],
    "sg:phone":"+1 361 516 0839",
    "sg:postcode":"78363",
    "sg:province":"TX",
    "sg:tags":[
        "eating"
    ],
    "wof:name":"James D Shiver Jr",
    "wof:placetype":"venue"
},
  "geometry": {"coordinates":[-97.861552,27.521872],"type":"Point"}
}