{
  "type": "Feature",
  "properties": {
    "iso:country":"US",
    "sg:address":"807 Hutchins Rd",
    "sg:city":"Dallas",
    "sg:classifiers":[
        {
            "category":"Professional",
            "subcategory":"Engineering",
            "type":"Services"
        }
    ],
    "sg:phone":"+1 214 941 8871",
    "sg:postcode":"75203",
    "sg:province":"TX",
    "sg:tags":[
        "steel",
        "detailing",
        "structural"
    ],
    "wof:name":"North Texas Detailers Inc",
    "wof:placetype":"venue"
},
  "geometry": {"coordinates":[-96.795406,32.739993],"type":"Point"}
}