{
  "type": "Feature",
  "properties": {
    "iso:country":"US",
    "sg:address":"5123 Bayou Timber Ln",
    "sg:city":"Houston",
    "sg:classifiers":[
        {
            "category":"Professional",
            "subcategory":"Business Services",
            "type":"Services"
        }
    ],
    "sg:phone":"+1 713 621 2395",
    "sg:postcode":"77056",
    "sg:province":"TX",
    "sg:tags":[
        "interior",
        "freelance",
        "designer"
    ],
    "wof:name":"Kay Ebert Design",
    "wof:placetype":"venue"
},
  "geometry": {"coordinates":[-95.467197,29.767051],"type":"Point"}
}