{
  "type": "Feature",
  "properties": {
    "iso:country":"US",
    "sg:address":"601 S Klein Ave",
    "sg:city":"Dumas",
    "sg:classifiers":[
        {
            "category":"Freight",
            "type":"Transportation"
        }
    ],
    "sg:phone":"+1 806 935 6701",
    "sg:postcode":"79029",
    "sg:province":"TX",
    "sg:tags":[
        "hauling",
        "trucking"
    ],
    "wof:name":"Thomas & Watson Trucking",
    "wof:placetype":"venue"
},
  "geometry": {"coordinates":[-101.977311,35.859885],"type":"Point"}
}