{
  "type": "Feature",
  "properties": {
    "iso:country":"US",
    "sg:address":"2010 Clinton Dr",
    "sg:city":"Galena Park",
    "sg:classifiers":[
        {
            "category":"Shopping",
            "subcategory":"Discount & Variety Stores",
            "type":"Retail Goods"
        },
        {
            "category":"Shopping",
            "subcategory":"Department Store",
            "type":"Retail Goods"
        }
    ],
    "sg:phone":"+1 713 676 0262",
    "sg:postcode":"77547",
    "sg:province":"TX",
    "sg:tags":[
        "shop"
    ],
    "sg:website":"www.familydollar.com",
    "wof:name":"Family Dollar Stores",
    "wof:placetype":"venue"
},
  "geometry": {"coordinates":[-95.24240500000001,29.732519],"type":"Point"}
}