{
  "type": "Feature",
  "properties": {
    "iso:country":"US",
    "sg:address":"2344 Farrington St",
    "sg:city":"Dallas",
    "sg:classifiers":[
        {
            "category":"Food & Beverages",
            "subcategory":"Groceries & Convenience Stores",
            "type":"Retail Goods"
        }
    ],
    "sg:phone":"+1 214 688 1300",
    "sg:postcode":"75207",
    "sg:province":"TX",
    "sg:tags":[
        "product"
    ],
    "wof:name":"Mojave Foods",
    "wof:placetype":"venue"
},
  "geometry": {"coordinates":[-96.83842799999999,32.799431],"type":"Point"}
}