{
  "type": "Feature",
  "properties": {
    "iso:country":"US",
    "sg:address":"4008 US Hwy 59",
    "sg:city":"Victoria",
    "sg:classifiers":[
        {
            "category":"Food & Beverages",
            "subcategory":"Groceries & Convenience Stores",
            "type":"Retail Goods"
        }
    ],
    "sg:phone":"+1 361 576 1741",
    "sg:postcode":"77905",
    "sg:province":"TX",
    "wof:name":"Fastop Food Stores Store No 5",
    "wof:placetype":"venue"
},
  "geometry": {"coordinates":[-97.041687,28.730266],"type":"Point"}
}