{
  "type": "Feature",
  "properties": {
    "iso:country":"US",
    "sg:address":"7540 Lassiter Ln",
    "sg:city":"San Antonio",
    "sg:classifiers":[
        {
            "category":"Health Services",
            "subcategory":"Medical Lab",
            "type":"Services"
        }
    ],
    "sg:phone":"+1 210 836 0040",
    "sg:postcode":"78250",
    "sg:province":"TX",
    "sg:tags":[
        "laboratory"
    ],
    "wof:name":"Esoterix Inc",
    "wof:placetype":"venue"
},
  "geometry": {"coordinates":[-98.65725999999999,29.511733],"type":"Point"}
}