{
  "type": "Feature",
  "properties": {
    "iso:country":"US",
    "sg:address":"105 Phalarope Dr",
    "sg:city":"Buda",
    "sg:classifiers":[
        {
            "category":"Building & Trades",
            "subcategory":"Construction",
            "type":"Services"
        }
    ],
    "sg:phone":"+1 512 554 7449",
    "sg:postcode":"78610",
    "sg:province":"TX",
    "sg:tags":[
        "house"
    ],
    "wof:name":"Braxton Custom Homes & Remodel",
    "wof:placetype":"venue"
},
  "geometry": {"coordinates":[-97.86548999999999,30.122079],"type":"Point"}
}