{
  "type": "Feature",
  "properties": {
    "iso:country":"US",
    "sg:address":"8105 N Belt Line Rd",
    "sg:city":"Irving",
    "sg:classifiers":[
        {
            "category":"Wholesale",
            "subcategory":"Electrical",
            "type":"Manufacturing & Wholesale Goods"
        }
    ],
    "sg:phone":"+1 972 915 1350",
    "sg:postcode":"75063",
    "sg:province":"TX",
    "wof:name":"Panasonic Factory Automation",
    "wof:placetype":"venue"
},
  "geometry": {"coordinates":[-96.993891,32.918821],"type":"Point"}
}