{
  "type": "Feature",
  "properties": {
    "iso:country":"US",
    "sg:address":"600 Gulf Fwy",
    "sg:city":"Texas City",
    "sg:classifiers":[
        {
            "category":"Freight",
            "type":"Transportation"
        }
    ],
    "sg:phone":"+1 409 944 3506",
    "sg:postcode":"77591",
    "sg:province":"TX",
    "sg:tags":[
        "warehouse"
    ],
    "wof:name":"Aimcor",
    "wof:placetype":"venue"
},
  "geometry": {"coordinates":[-95.01851499999999,29.388512],"type":"Point"}
}