{
  "type": "Feature",
  "properties": {
    "iso:country":"US",
    "sg:address":"5000 Rowlett Rd Ste 109",
    "sg:city":"Rowlett",
    "sg:classifiers":[
        {
            "category":"Shopping",
            "subcategory":"Stationery & Office Supplies",
            "type":"Retail Goods"
        },
        {
            "category":"Professional",
            "subcategory":"Printing & Photocopies",
            "type":"Services"
        }
    ],
    "sg:phone":"+1 972 475 4240",
    "sg:postcode":"75088",
    "sg:province":"TX",
    "sg:tags":[
        "equipment"
    ],
    "wof:name":"Rowlett Office Supply",
    "wof:placetype":"venue"
},
  "geometry": {"coordinates":[-96.569298,32.9058],"type":"Point"}
}