{
  "type": "Feature",
  "properties": {
    "iso:country":"US",
    "sg:address":"2607 W Freddy Gonzalez Dr",
    "sg:city":"Edinburg",
    "sg:classifiers":[
        {
            "category":"Social Services",
            "type":"Services"
        }
    ],
    "sg:phone":"+1 956 383 4935",
    "sg:postcode":"78539",
    "sg:province":"TX",
    "wof:name":"Unique Kare Children Services",
    "wof:placetype":"venue"
},
  "geometry": {"coordinates":[-98.19301299999999,26.290927],"type":"Point"}
}