{
  "type": "Feature",
  "properties": {
    "iso:country":"US",
    "sg:address":"306 S Old Betsy Rd",
    "sg:city":"Keene",
    "sg:classifiers":[
        {
            "category":"Personal",
            "subcategory":"Beauty Salon",
            "type":"Services"
        }
    ],
    "sg:phone":"+1 817 641 9145",
    "sg:postcode":"76059",
    "sg:province":"TX",
    "sg:tags":[
        "wig",
        "hair",
        "piece"
    ],
    "wof:name":"Dolly's Wig & Beauty Salon",
    "wof:placetype":"venue"
},
  "geometry": {"coordinates":[-97.33295099999999,32.392248],"type":"Point"}
}