{
  "type": "Feature",
  "properties": {
    "iso:country":"US",
    "sg:address":"2018 Marina Bay Dr",
    "sg:city":"Kemah",
    "sg:classifiers":[
        {
            "category":"Health Services",
            "subcategory":"Podiatrist",
            "type":"Services"
        }
    ],
    "sg:phone":"+1 281 535 3800",
    "sg:postcode":"77565",
    "sg:province":"TX",
    "wof:name":"Self Shore Podiatry Assoc",
    "wof:placetype":"venue"
},
  "geometry": {"coordinates":[-95.05021600000001,29.541998],"type":"Point"}
}