{
  "type": "Feature",
  "properties": {
    "iso:country":"US",
    "sg:address":"1901 John McCain Rd",
    "sg:city":"Colleyville",
    "sg:classifiers":[
        {
            "category":"Manufacturing",
            "subcategory":"Printing",
            "type":"Manufacturing & Wholesale Goods"
        }
    ],
    "sg:phone":"+1 817 329 0341",
    "sg:postcode":"76034",
    "sg:province":"TX",
    "sg:tags":[
        "lithographic",
        "printer",
        "commercial"
    ],
    "wof:name":"Comprint Inc",
    "wof:placetype":"venue"
},
  "geometry": {"coordinates":[-97.138884,32.911657],"type":"Point"}
}