{
  "type": "Feature",
  "properties": {
    "iso:country":"US",
    "sg:address":"2930 Chestnut Ridge Dr",
    "sg:city":"Huffman",
    "sg:classifiers":[
        {
            "category":"Building & Trades",
            "subcategory":"Construction",
            "type":"Services"
        }
    ],
    "sg:phone":"+1 281 324 1766",
    "sg:postcode":"77339",
    "sg:province":"TX",
    "sg:tags":[
        "repairing",
        "remodeling",
        "contractor"
    ],
    "wof:name":"A Ffordable Remodeling Co",
    "wof:placetype":"venue"
},
  "geometry": {"coordinates":[-95.239846,30.052113],"type":"Point"}
}