{
  "type": "Feature",
  "properties": {
    "iso:country":"US",
    "sg:address":"5217 Runnin River Dr",
    "sg:city":"Plano",
    "sg:classifiers":[
        {
            "category":"Professional",
            "subcategory":"Business Services",
            "type":"Services"
        }
    ],
    "sg:phone":"+1 972 312 0411",
    "sg:postcode":"75093",
    "sg:province":"TX",
    "wof:name":"Neuronatin Partners Ltd",
    "wof:placetype":"venue"
},
  "geometry": {"coordinates":[-96.802751,33.049092],"type":"Point"}
}