{
  "type": "Feature",
  "properties": {
    "iso:country":"US",
    "sg:address":"516 Holley St",
    "sg:city":"Fort Worth",
    "sg:classifiers":[
        {
            "category":"Retail",
            "subcategory":"Laundry & Dry Cleaning",
            "type":"Services"
        }
    ],
    "sg:phone":"+1 817 293 0006",
    "sg:postcode":"76140",
    "sg:province":"TX",
    "sg:tags":[
        "cleaners",
        "rug",
        "carpet"
    ],
    "wof:name":"Daddy Rays Carpet Care",
    "wof:placetype":"venue"
},
  "geometry": {"coordinates":[-97.284751,32.637789],"type":"Point"}
}