{
  "type": "Feature",
  "properties": {
    "iso:country":"US",
    "sg:address":"10371 Briar Forest Dr",
    "sg:city":"Houston",
    "sg:classifiers":[
        {
            "category":"Professional",
            "type":"Services"
        }
    ],
    "sg:phone":"+1 713 917 0411",
    "sg:postcode":"77042",
    "sg:province":"TX",
    "wof:name":"Ginger A Titus",
    "wof:placetype":"venue"
},
  "geometry": {"coordinates":[-95.556663,29.747483],"type":"Point"}
}