{
  "type": "Feature",
  "properties": {
    "iso:country":"US",
    "sg:address":"4200 Irving Blvd",
    "sg:city":"Dallas",
    "sg:classifiers":[
        {
            "category":"Autos & Motor Vehicles",
            "subcategory":"Auto Supplies",
            "type":"Retail Goods"
        }
    ],
    "sg:phone":"+1 214 905 9457",
    "sg:postcode":"75247",
    "sg:province":"TX",
    "sg:tags":[
        "tire"
    ],
    "wof:name":"World Wide Tires",
    "wof:placetype":"venue"
},
  "geometry": {"coordinates":[-96.888262,32.808056],"type":"Point"}
}