{
  "type": "Feature",
  "properties": {
    "iso:country":"US",
    "sg:address":"2110 Aberdeen Dr",
    "sg:city":"League City",
    "sg:classifiers":[
        {
            "category":"Professional",
            "subcategory":"Computer Services",
            "type":"Services"
        }
    ],
    "sg:phone":"+1 281 338 2974",
    "sg:postcode":"77573",
    "sg:province":"TX",
    "sg:tags":[
        "design",
        "integrated",
        "system"
    ],
    "wof:name":"Workbook Software",
    "wof:placetype":"venue"
},
  "geometry": {"coordinates":[-95.119404,29.48861],"type":"Point"}
}