{
  "type": "Feature",
  "properties": {
    "iso:country":"US",
    "sg:address":"2510 NW 3rd Ave",
    "sg:city":"Amarillo",
    "sg:classifiers":[
        {
            "category":"Utilities",
            "subcategory":"Electric",
            "type":"Services"
        },
        {
            "category":"Manufacturing",
            "subcategory":"Electronics",
            "type":"Manufacturing & Wholesale Goods"
        },
        {
            "category":"Building & Trades",
            "subcategory":"Electrical",
            "type":"Services"
        }
    ],
    "sg:phone":"+1 806 331 4014",
    "sg:postcode":"79106",
    "sg:province":"TX",
    "sg:tags":[
        "industrial",
        "electrician",
        "contractors-commercial",
        "equipment-testing"
    ],
    "wof:name":"Baneco Electric",
    "wof:placetype":"venue"
},
  "geometry": {"coordinates":[-101.86316600000001,35.219627],"type":"Point"}
}