{
  "type": "Feature",
  "properties": {
    "iso:country":"US",
    "sg:address":"2728 Welborn St",
    "sg:city":"Dallas",
    "sg:classifiers":[
        {
            "category":"Utilities",
            "subcategory":"Telephone",
            "type":"Services"
        }
    ],
    "sg:phone":"+1 469 916 6991",
    "sg:postcode":"75219",
    "sg:province":"TX",
    "sg:tags":[
        "it"
    ],
    "wof:name":"Mad Labz Inc",
    "wof:placetype":"venue"
},
  "geometry": {"coordinates":[-96.81044900000001,32.805964],"type":"Point"}
}