{
  "type": "Feature",
  "properties": {
    "iso:country":"US",
    "sg:address":"311 W US Hwy 83",
    "sg:city":"Pharr",
    "sg:classifiers":[
        {
            "category":"Autos & Motor Vehicles",
            "subcategory":"Automobile Sales",
            "type":"Retail Goods"
        }
    ],
    "sg:phone":"+1 956 783 5991",
    "sg:postcode":"78577",
    "sg:province":"TX",
    "sg:tags":[
        "car",
        "dealer"
    ],
    "wof:name":"Pharr Auto Sales",
    "wof:placetype":"venue"
},
  "geometry": {"coordinates":[-98.187895,26.207068],"type":"Point"}
}