{
  "type": "Feature",
  "properties": {
    "iso:country":"US",
    "sg:address":"8619 Wall St",
    "sg:city":"Austin",
    "sg:classifiers":[
        {
            "category":"Transit Center",
            "subcategory":"Freight",
            "type":"Transportation"
        }
    ],
    "sg:phone":"+1 512 490 0069",
    "sg:postcode":"78754",
    "sg:province":"TX",
    "sg:tags":[
        "trucking-light",
        "hauling"
    ],
    "wof:name":"L2 Cartage",
    "wof:placetype":"venue"
},
  "geometry": {"coordinates":[-97.674147,30.338535],"type":"Point"}
}