{
  "type": "Feature",
  "properties": {
    "iso:country":"US",
    "sg:address":"3023 Routh St",
    "sg:city":"Dallas",
    "sg:classifiers":[
        {
            "category":"Personal",
            "subcategory":"Skin Care",
            "type":"Services"
        }
    ],
    "sg:phone":"+1 214 904 1723",
    "sg:postcode":"75201",
    "sg:province":"TX",
    "wof:name":"Thomas Cheryl Skin Care",
    "wof:placetype":"venue"
},
  "geometry": {"coordinates":[-96.806223,32.799703],"type":"Point"}
}