{
  "type": "Feature",
  "properties": {
    "iso:country":"US",
    "sg:address":"11415 Chimney Rock Rd",
    "sg:city":"Houston",
    "sg:classifiers":[
        {
            "category":"Professional",
            "type":"Services"
        }
    ],
    "sg:phone":"+1 713 728 1739",
    "sg:postcode":"77035",
    "sg:province":"TX",
    "wof:name":"Skyliss Bus Fith Frver Fndtons",
    "wof:placetype":"venue"
},
  "geometry": {"coordinates":[-95.477171,29.656822],"type":"Point"}
}