{
  "type": "Feature",
  "properties": {
    "iso:country":"US",
    "sg:address":"603 Shady Ln",
    "sg:city":"Copperas Cove",
    "sg:classifiers":[
        {
            "category":"Insurance",
            "subcategory":"Insurance Agent",
            "type":"Services"
        }
    ],
    "sg:phone":"+1 254 547 5019",
    "sg:postcode":"76522",
    "sg:province":"TX",
    "wof:name":"American Gen Lf Accident Insur",
    "wof:placetype":"venue"
},
  "geometry": {"coordinates":[-97.899265,31.117295],"type":"Point"}
}