{
  "type": "Feature",
  "properties": {
    "iso:country":"US",
    "sg:address":"7618 Hollow Glen Ln",
    "sg:city":"Houston",
    "sg:classifiers":[
        {
            "category":"Professional",
            "subcategory":"Art Services",
            "type":"Services"
        }
    ],
    "sg:phone":"+1 281 495 2336",
    "sg:postcode":"77072",
    "sg:province":"TX",
    "sg:tags":[
        "graphic",
        "designer"
    ],
    "wof:name":"Elite Images",
    "wof:placetype":"venue"
},
  "geometry": {"coordinates":[-95.60906199999999,29.692877],"type":"Point"}
}