{
  "type": "Feature",
  "properties": {
    "iso:country":"US",
    "sg:address":"2610 Oak Ln",
    "sg:city":"Paris",
    "sg:classifiers":[
        {
            "category":"Professional",
            "subcategory":"Management & Consulting",
            "type":"Services"
        }
    ],
    "sg:phone":"+1 903 784 3747",
    "sg:postcode":"75462",
    "sg:province":"TX",
    "wof:name":"Ellis Properties",
    "wof:placetype":"venue"
},
  "geometry": {"coordinates":[-95.493347,33.689953],"type":"Point"}
}