{
  "type": "Feature",
  "properties": {
    "iso:country":"US",
    "sg:address":"514 Briar Hill Dr",
    "sg:city":"Houston",
    "sg:classifiers":[
        {
            "category":"Building & Trades",
            "subcategory":"Construction",
            "type":"Services"
        }
    ],
    "sg:phone":"+1 713 789 5014",
    "sg:postcode":"77042",
    "sg:province":"TX",
    "sg:tags":[
        "house"
    ],
    "wof:name":"L&H Custom Homes LLC",
    "wof:placetype":"venue"
},
  "geometry": {"coordinates":[-95.556855,29.755246],"type":"Point"}
}