{
  "type": "Feature",
  "properties": {
    "iso:country":"US",
    "sg:address":"206 E 26th St",
    "sg:city":"Bryan",
    "sg:classifiers":[
        {
            "category":"Building & Trades",
            "subcategory":"Construction",
            "type":"Services"
        }
    ],
    "sg:phone":"+1 979 775 3400",
    "sg:postcode":"77803",
    "sg:province":"TX",
    "sg:tags":[
        "foundation"
    ],
    "wof:name":"Lifetime Foundation Repair Inc",
    "wof:placetype":"venue"
},
  "geometry": {"coordinates":[-96.37121,30.673594],"type":"Point"}
}