{
  "type": "Feature",
  "properties": {
    "iso:country":"US",
    "sg:address":"900 Cedarwood Dr",
    "sg:city":"Friendswood",
    "sg:classifiers":[
        {
            "category":"Recreation",
            "type":"Entertainment"
        }
    ],
    "sg:phone":"+1 281 482 0936",
    "sg:postcode":"77546",
    "sg:province":"TX",
    "sg:tags":[
        "pool",
        "swimming"
    ],
    "wof:name":"Swimming Pool",
    "wof:placetype":"venue"
},
  "geometry": {"coordinates":[-95.200236,29.525427],"type":"Point"}
}