{
  "type": "Feature",
  "properties": {
    "iso:country":"US",
    "sg:address":"115 N Roberts Rd",
    "sg:city":"Cedar Hill",
    "sg:classifiers":[
        {
            "category":"Social Services",
            "type":"Services"
        }
    ],
    "sg:phone":"+1 214 348 5025",
    "sg:postcode":"75104",
    "sg:province":"TX",
    "sg:tags":[
        "counselor",
        "marriage",
        "family"
    ],
    "wof:name":"Stephanie Maglisceau",
    "wof:placetype":"venue"
},
  "geometry": {"coordinates":[-96.958466,32.590194],"type":"Point"}
}