{
  "type": "Feature",
  "properties": {
    "iso:country":"US",
    "sg:address":"5700 Velma Jeter Dr",
    "sg:city":"Orange",
    "sg:classifiers":[
        {
            "category":"Building & Trades",
            "subcategory":"Cleaning & Sanitation",
            "type":"Services"
        }
    ],
    "sg:phone":"+1 409 670 0588",
    "sg:postcode":"77632",
    "sg:province":"TX",
    "sg:tags":[
        "janitor"
    ],
    "wof:name":"J L Janitorial Svc",
    "wof:placetype":"venue"
},
  "geometry": {"coordinates":[-93.76130499999999,30.143029],"type":"Point"}
}