{
  "type": "Feature",
  "properties": {
    "iso:country":"US",
    "sg:address":"135 Palo Pinto St",
    "sg:city":"San Antonio",
    "sg:classifiers":[
        {
            "category":"Shopping",
            "subcategory":"Used Merchandise",
            "type":"Retail Goods"
        }
    ],
    "sg:phone":"+1 210 494 3967",
    "sg:postcode":"78232",
    "sg:province":"TX",
    "wof:name":"CN Rodriguez Antiques",
    "wof:placetype":"venue"
},
  "geometry": {"coordinates":[-98.465397,29.587017],"type":"Point"}
}