{
  "type": "Feature",
  "properties": {
    "iso:country":"US",
    "sg:address":"2727 LBJ Fwy Ste 140",
    "sg:city":"Farmer's Branch",
    "sg:classifiers":[
        {
            "category":"Professional",
            "type":"Services"
        }
    ],
    "sg:phone":"+1 972 462 7470",
    "sg:postcode":"75234",
    "sg:province":"TX",
    "sg:tags":[
        "caterer"
    ],
    "sg:website":"www.remarkableaffairs.com",
    "wof:name":"Remarkable Affairs Catering",
    "wof:placetype":"venue"
},
  "geometry": {"coordinates":[-96.88589,32.911131],"type":"Point"}
}