{
  "type": "Feature",
  "properties": {
    "iso:country":"US",
    "sg:address":"7400 Cooper Ln",
    "sg:city":"Austin",
    "sg:classifiers":[
        {
            "category":"Building & Trades",
            "subcategory":"Construction",
            "type":"Services"
        }
    ],
    "sg:phone":"+1 512 441 7100",
    "sg:postcode":"78745",
    "sg:province":"TX",
    "sg:tags":[
        "contractor",
        "mechanical"
    ],
    "sg:website":"http://www.beardmech.com",
    "wof:name":"Beard Mechanical Contractors Inc",
    "wof:placetype":"venue"
},
  "geometry": {"coordinates":[-97.794133,30.189631],"type":"Point"}
}