{
  "type": "Feature",
  "properties": {
    "iso:country":"US",
    "sg:address":"8700 Fallbrook Dr",
    "sg:city":"Houston",
    "sg:classifiers":[
        {
            "category":"Wholesale",
            "subcategory":"Electrical",
            "type":"Manufacturing & Wholesale Goods"
        }
    ],
    "sg:phone":"+1 713 460 9500",
    "sg:postcode":"77064",
    "sg:province":"TX",
    "sg:tags":[
        "major",
        "appliance"
    ],
    "wof:name":"Factory Builder Stores Ltd",
    "wof:placetype":"venue"
},
  "geometry": {"coordinates":[-95.556432,29.924529],"type":"Point"}
}