{
  "type": "Feature",
  "properties": {
    "iso:country":"US",
    "sg:address":"411 Hamby Rd",
    "sg:city":"Clyde",
    "sg:classifiers":[
        {
            "category":"Manufacturing",
            "subcategory":"Tools & Machinery",
            "type":"Manufacturing & Wholesale Goods"
        },
        {
            "category":"Professional",
            "type":"Services"
        },
        {
            "category":"Retail",
            "subcategory":"Repair Shop",
            "type":"Services"
        }
    ],
    "sg:phone":"+1 325 893 4409",
    "sg:postcode":"79510",
    "sg:province":"TX",
    "sg:tags":[
        "repairing",
        "mowers-sharpening",
        "lawn",
        "saws-sharpen",
        "sharpening"
    ],
    "wof:name":"Bill's Sharpening Shop",
    "wof:placetype":"venue"
},
  "geometry": {"coordinates":[-99.502724,32.409404],"type":"Point"}
}