{
  "type": "Feature",
  "properties": {
    "iso:country":"US",
    "sg:address":"403 E University Dr # 517",
    "sg:city":"Edinburg",
    "sg:classifiers":[
        {
            "category":"Autos & Motor Vehicles",
            "subcategory":"Auto Supplies",
            "type":"Retail Goods"
        }
    ],
    "sg:phone":"+1 956 287 1045",
    "sg:postcode":"78539",
    "sg:province":"TX",
    "sg:tags":[
        "apparel",
        "western"
    ],
    "wof:name":"Gavel Western Wear",
    "wof:placetype":"venue"
},
  "geometry": {"coordinates":[-98.158998,26.300917],"type":"Point"}
}