{
  "type": "Feature",
  "properties": {
    "iso:country":"US",
    "sg:address":"101 Pine Manor Dr",
    "sg:city":"Conroe",
    "sg:classifiers":[
        {
            "category":"Organizations",
            "subcategory":"Non-profit Organization",
            "type":"Services"
        },
        {
            "category":"Health Services",
            "subcategory":"Clinic",
            "type":"Services"
        }
    ],
    "sg:phone":"+1 281 364 7889",
    "sg:postcode":"77385",
    "sg:province":"TX",
    "sg:tags":[
        "welfare",
        "agency",
        "social"
    ],
    "wof:name":"Community Clinic The",
    "wof:placetype":"venue"
},
  "geometry": {"coordinates":[-95.44750500000001,30.166897],"type":"Point"}
}