{
  "type": "Feature",
  "properties": {
    "iso:country":"US",
    "sg:address":"9801 W Parmer Ln Apt 2035",
    "sg:city":"Austin",
    "sg:classifiers":[
        {
            "category":"Wholesale",
            "subcategory":"Home Furnishings",
            "type":"Manufacturing & Wholesale Goods"
        }
    ],
    "sg:phone":"+1 512 246 7319",
    "sg:postcode":"78717",
    "sg:province":"TX",
    "sg:tags":[
        "manufacturer",
        "baskets-wholesale"
    ],
    "wof:name":"La Bella Baskets",
    "wof:placetype":"venue"
},
  "geometry": {"coordinates":[-97.77063699999999,30.486165],"type":"Point"}
}