{
  "type": "Feature",
  "properties": {
    "iso:country":"US",
    "sg:address":"814 W Texas St",
    "sg:city":"Stratford",
    "sg:classifiers":[
        {
            "category":"Retail",
            "subcategory":"Auto Repair",
            "type":"Services"
        }
    ],
    "sg:phone":"+1 806 396 2141",
    "sg:postcode":"79084",
    "sg:province":"TX",
    "sg:tags":[
        "body",
        "automobile",
        "painting",
        "repairing"
    ],
    "wof:name":"C & D Body Shop Inc",
    "wof:placetype":"venue"
},
  "geometry": {"coordinates":[-102.067172,36.335655],"type":"Point"}
}