{
  "type": "Feature",
  "properties": {
    "iso:country":"US",
    "sg:address":"104 Mockingbird Ln",
    "sg:city":"Livingston",
    "sg:classifiers":[
        {
            "category":"Banks & Credit Unions",
            "subcategory":"Financial Services",
            "type":"Services"
        }
    ],
    "sg:phone":"+1 936 327 8332",
    "sg:postcode":"77351",
    "sg:province":"TX",
    "sg:tags":[
        "trust"
    ],
    "wof:name":"Cook Burnett 2002 Trust",
    "wof:placetype":"venue"
},
  "geometry": {"coordinates":[-94.937594,30.703544],"type":"Point"}
}