{
  "type": "Feature",
  "properties": {
    "iso:country":"US",
    "sg:address":"12455 Research Blvd",
    "sg:city":"Austin",
    "sg:classifiers":[
        {
            "category":"Professional",
            "subcategory":"Computer Services",
            "type":"Services"
        }
    ],
    "sg:phone":"+1 512 836 4005",
    "sg:postcode":"78759",
    "sg:province":"TX",
    "sg:tags":[
        "programing",
        "custom"
    ],
    "wof:name":"Premier Semiconductor Svcs LLC",
    "wof:placetype":"venue"
},
  "geometry": {"coordinates":[-97.756784,30.428465],"type":"Point"}
}