{
  "type": "Feature",
  "properties": {
    "iso:country":"US",
    "sg:address":"8214 Westchester Dr",
    "sg:city":"Dallas",
    "sg:classifiers":[
        {
            "category":"Wholesale",
            "subcategory":"Machinery & Supplies",
            "type":"Manufacturing & Wholesale Goods"
        },
        {
            "category":"Home & Garden",
            "subcategory":"Garden Supply",
            "type":"Retail Goods"
        }
    ],
    "sg:phone":"+1 214 369 7576",
    "sg:postcode":"75225",
    "sg:province":"TX",
    "sg:tags":[
        "tie",
        "railroad",
        "equipment"
    ],
    "wof:name":"Somerville Tie Co",
    "wof:placetype":"venue"
},
  "geometry": {"coordinates":[-96.806494,32.863415],"type":"Point"}
}