{
  "type": "Feature",
  "properties": {
    "iso:country":"US",
    "sg:address":"2306 Firnat St",
    "sg:city":"Houston",
    "sg:classifiers":[
        {
            "category":"Manufacturing",
            "subcategory":"Signs",
            "type":"Manufacturing & Wholesale Goods"
        }
    ],
    "sg:phone":"+1 713 695 9730",
    "sg:postcode":"77093",
    "sg:province":"TX",
    "sg:tags":[
        "specialty",
        "mfg"
    ],
    "wof:name":"Joes Neon Shack",
    "wof:placetype":"venue"
},
  "geometry": {"coordinates":[-95.348167,29.842222],"type":"Point"}
}