{
  "type": "Feature",
  "properties": {
    "iso:country":"US",
    "sg:address":"508 S Texas St",
    "sg:city":"Shamrock",
    "sg:phone":"+1 806 256 5166",
    "sg:postcode":"79079",
    "sg:province":"TX",
    "sg:tags":[
        "farm",
        "field",
        "crop"
    ],
    "wof:name":"Robinson AG",
    "wof:placetype":"venue"
},
  "geometry": {"coordinates":[-100.244687,35.208145],"type":"Point"}
}