{
  "type": "Feature",
  "properties": {
    "iso:country":"US",
    "sg:address":"555 W Bitters Rd",
    "sg:city":"San Antonio",
    "sg:classifiers":[
        {
            "category":"Home & Garden",
            "subcategory":"Home Furnishings",
            "type":"Retail Goods"
        }
    ],
    "sg:phone":"+1 830 230 5020",
    "sg:postcode":"78216",
    "sg:province":"TX",
    "sg:tags":[
        "quilting"
    ],
    "wof:name":"Plain Jane's",
    "wof:placetype":"venue"
},
  "geometry": {"coordinates":[-98.49924300000001,29.578071],"type":"Point"}
}