{
  "type": "Feature",
  "properties": {
    "iso:country":"US",
    "sg:address":"5000 N 23rd St",
    "sg:city":"Mcallen",
    "sg:classifiers":[
        {
            "category":"Cinema",
            "subcategory":"Movie Rental",
            "type":"Entertainment"
        }
    ],
    "sg:phone":"+1 956 661 0336",
    "sg:postcode":"78504",
    "sg:province":"TX",
    "sg:tags":[
        "leasing",
        "video",
        "disc",
        "tape"
    ],
    "wof:name":"Super Video",
    "wof:placetype":"venue"
},
  "geometry": {"coordinates":[-98.237666,26.250179],"type":"Point"}
}