{
  "type": "Feature",
  "properties": {
    "iso:country":"US",
    "sg:address":"2530 Electronic Ln",
    "sg:city":"Dallas",
    "sg:classifiers":[
        {
            "category":"Manufacturing",
            "subcategory":"Printing",
            "type":"Manufacturing & Wholesale Goods"
        }
    ],
    "sg:phone":"+1 214 956 7545",
    "sg:postcode":"75220",
    "sg:province":"TX",
    "sg:tags":[
        "lithographic",
        "commercial"
    ],
    "wof:name":"Lonestar Printing",
    "wof:placetype":"venue"
},
  "geometry": {"coordinates":[-96.895141,32.878819],"type":"Point"}
}