{
  "type": "Feature",
  "properties": {
    "iso:country":"US",
    "sg:address":"2102 Ave K",
    "sg:city":"Lubbock",
    "sg:classifiers":[
        {
            "category":"Professional",
            "subcategory":"Printing & Photocopies",
            "type":"Services"
        }
    ],
    "sg:phone":"+1 806 763 7770",
    "sg:postcode":"79411",
    "sg:province":"TX",
    "sg:tags":[
        "duplicating",
        "copying"
    ],
    "wof:name":"Reproduction Co",
    "wof:placetype":"venue"
},
  "geometry": {"coordinates":[-101.847855,33.574999],"type":"Point"}
}