{
  "type": "Feature",
  "properties": {
    "iso:country":"US",
    "sg:address":"600 Kenrick Dr Ste D2",
    "sg:city":"Houston",
    "sg:classifiers":[
        {
            "category":"Building & Trades",
            "subcategory":"Pest Control",
            "type":"Services"
        }
    ],
    "sg:phone":"+1 281 741 8828",
    "sg:postcode":"77060",
    "sg:province":"TX",
    "sg:website":"www.reliantpest.com",
    "wof:name":"Reliant Pest Management",
    "wof:placetype":"venue"
},
  "geometry": {"coordinates":[-95.38906299999999,29.941802],"type":"Point"}
}