{
  "type": "Feature",
  "properties": {
    "iso:country":"US",
    "sg:address":"6130 Bandera Ave",
    "sg:city":"Dallas",
    "sg:classifiers":[
        {
            "category":"Professional",
            "subcategory":"Management & Consulting",
            "type":"Services"
        }
    ],
    "sg:phone":"+1 214 696 3070",
    "sg:postcode":"75225",
    "sg:province":"TX",
    "sg:tags":[
        "business"
    ],
    "wof:name":"Sheinberg Associates",
    "wof:placetype":"venue"
},
  "geometry": {"coordinates":[-96.801292,32.867398],"type":"Point"}
}