{
  "type": "Feature",
  "properties": {
    "iso:country":"US",
    "sg:address":"6009 Waterway Dr",
    "sg:city":"Garland",
    "sg:classifiers":[
        {
            "category":"Insurance",
            "subcategory":"Insurance Agent",
            "type":"Services"
        }
    ],
    "sg:phone":"+1 972 226 1646",
    "sg:postcode":"75043",
    "sg:province":"TX",
    "sg:tags":[
        "brokerage"
    ],
    "wof:name":"Lem Insurance Services",
    "wof:placetype":"venue"
},
  "geometry": {"coordinates":[-96.563866,32.842246],"type":"Point"}
}