{
  "type": "Feature",
  "properties": {
    "iso:country":"US",
    "sg:address":"1108 Pack Ave",
    "sg:city":"Copperas Cove",
    "sg:classifiers":[
        {
            "category":"Professional",
            "type":"Services"
        }
    ],
    "sg:phone":"+1 254 547 4006",
    "sg:postcode":"76522",
    "sg:province":"TX",
    "wof:name":"Beverage Masters",
    "wof:placetype":"venue"
},
  "geometry": {"coordinates":[-97.876316,31.118047],"type":"Point"}
}