{
  "type": "Feature",
  "properties": {
    "iso:country":"US",
    "sg:address":"3817 Rau Dr",
    "sg:city":"Dickinson",
    "sg:classifiers":[
        {
            "category":"Building & Trades",
            "subcategory":"Construction",
            "type":"Services"
        }
    ],
    "sg:phone":"+1 281 337 2159",
    "sg:postcode":"77539",
    "sg:province":"TX",
    "sg:tags":[
        "house"
    ],
    "wof:name":"J&B Builders",
    "wof:placetype":"venue"
},
  "geometry": {"coordinates":[-95.086726,29.440071],"type":"Point"}
}