{
  "type": "Feature",
  "properties": {
    "iso:country":"US",
    "sg:address":"5403 Tallow Ln",
    "sg:city":"Houston",
    "sg:classifiers":[
        {
            "category":"Personal",
            "type":"Services"
        }
    ],
    "sg:phone":"+1 713 741 2573",
    "sg:postcode":"77021",
    "sg:province":"TX",
    "wof:name":"Mosley Kymbrel",
    "wof:placetype":"venue"
},
  "geometry": {"coordinates":[-95.336855,29.701823],"type":"Point"}
}