{
  "type": "Feature",
  "properties": {
    "iso:country":"US",
    "sg:address":"122 Colebrook Dr",
    "sg:city":"San Antonio",
    "sg:classifiers":[
        {
            "category":"Professional",
            "subcategory":"Research",
            "type":"Services"
        }
    ],
    "sg:phone":"+1 210 434 6096",
    "sg:postcode":"78228",
    "sg:province":"TX",
    "sg:tags":[
        "commercial",
        "physical"
    ],
    "wof:name":"Custom Craft Products",
    "wof:placetype":"venue"
},
  "geometry": {"coordinates":[-98.579217,29.478787],"type":"Point"}
}