{
  "type": "Feature",
  "properties": {
    "iso:country":"US",
    "sg:address":"215 W Jefferson Blvd",
    "sg:city":"Dallas",
    "sg:classifiers":[
        {
            "category":"Personal",
            "subcategory":"Beauty Salon",
            "type":"Services"
        }
    ],
    "sg:phone":"+1 214 948 9963",
    "sg:postcode":"75208",
    "sg:province":"TX",
    "wof:name":"Roxlind Beauty Salon",
    "wof:placetype":"venue"
},
  "geometry": {"coordinates":[-96.826241,32.743186],"type":"Point"}
}