{
  "type": "Feature",
  "properties": {
    "iso:country":"US",
    "sg:address":"1111 Jupiter Rd",
    "sg:city":"Plano",
    "sg:classifiers":[
        {
            "category":"Banks & Credit Unions",
            "subcategory":"Investment Brokerage",
            "type":"Services"
        }
    ],
    "sg:phone":"+1 972 423 7247",
    "sg:postcode":"75074",
    "sg:province":"TX",
    "sg:tags":[
        "security"
    ],
    "wof:name":"Vantage Investment Corp",
    "wof:placetype":"venue"
},
  "geometry": {"coordinates":[-96.68262799999999,33.014249],"type":"Point"}
}