{
  "type": "Feature",
  "properties": {
    "iso:country":"US",
    "sg:address":"500 N Water St",
    "sg:city":"Corpus Christi",
    "sg:classifiers":[
        {
            "category":"Professional",
            "subcategory":"Lawyer & Legal Services",
            "type":"Services"
        }
    ],
    "sg:phone":"+1 361 887 9900",
    "sg:postcode":"78471",
    "sg:province":"TX",
    "sg:tags":[
        "attorney"
    ],
    "wof:name":"Arnold Gonzales Jr",
    "wof:placetype":"venue"
},
  "geometry": {"coordinates":[-97.392715,27.796796],"type":"Point"}
}