{
  "type": "Feature",
  "properties": {
    "iso:country":"US",
    "sg:address":"1105 Plum",
    "sg:city":"Lockhart",
    "sg:classifiers":[
        {
            "category":"Professional",
            "type":"Services"
        }
    ],
    "sg:phone":"+1 512 398 5011",
    "sg:postcode":"78644",
    "sg:province":"TX",
    "wof:name":"Linda Cole",
    "wof:placetype":"venue"
},
  "geometry": {"coordinates":[-97.683044,29.877002],"type":"Point"}
}