{
  "type": "Feature",
  "properties": {
    "iso:country":"US",
    "sg:address":"1217 Meadowbend Ct",
    "sg:city":"Allen",
    "sg:classifiers":[
        {
            "category":"Professional",
            "subcategory":"Business Services",
            "type":"Services"
        }
    ],
    "sg:phone":"+1 972 390 8677",
    "sg:postcode":"75002",
    "sg:province":"TX",
    "wof:name":"Allen Police Assoc",
    "wof:placetype":"venue"
},
  "geometry": {"coordinates":[-96.64715,33.116319],"type":"Point"}
}