{
  "type": "Feature",
  "properties": {
    "iso:country":"US",
    "sg:address":"2015 N State Line Ave",
    "sg:city":"Texarkana",
    "sg:classifiers":[
        {
            "category":"Retail",
            "subcategory":"Auto Repair",
            "type":"Services"
        }
    ],
    "sg:phone":"+1 903 792 5999",
    "sg:postcode":"75501",
    "sg:province":"TX",
    "sg:tags":[
        "repairing",
        "automobile"
    ],
    "wof:name":"State Line Automotive",
    "wof:placetype":"venue"
},
  "geometry": {"coordinates":[-94.043181,33.436101],"type":"Point"}
}