{
  "type": "Feature",
  "properties": {
    "iso:country":"US",
    "sg:address":"19914 Sapphire Cir",
    "sg:city":"Magnolia",
    "sg:classifiers":[
        {
            "category":"Professional",
            "subcategory":"Computer Services",
            "type":"Services"
        }
    ],
    "sg:phone":"+1 281 252 5515",
    "sg:postcode":"77355",
    "sg:province":"TX",
    "sg:tags":[
        "related"
    ],
    "wof:name":"Pharaoh Development Group Inc",
    "wof:placetype":"venue"
},
  "geometry": {"coordinates":[-95.77168399999999,30.15009],"type":"Point"}
}