{
  "type": "Feature",
  "properties": {
    "iso:country":"US",
    "sg:address":"1616 S Friendswood Dr",
    "sg:city":"Friendswood",
    "sg:classifiers":[
        {
            "category":"Restaurant",
            "type":"Food & Drink"
        }
    ],
    "sg:phone":"+1 281 482 8700",
    "sg:postcode":"77546",
    "sg:province":"TX",
    "sg:tags":[
        "eating"
    ],
    "wof:name":"Papa Johns",
    "wof:placetype":"venue"
},
  "geometry": {"coordinates":[-95.188372,29.509001],"type":"Point"}
}