{
  "type": "Feature",
  "properties": {
    "iso:country":"US",
    "sg:address":"10315 W Airport Blvd",
    "sg:city":"Stafford",
    "sg:classifiers":[
        {
            "category":"Bars & Pubs",
            "type":"Food & Drink"
        }
    ],
    "sg:phone":"+1 281 561 7687",
    "sg:postcode":"77477",
    "sg:province":"TX",
    "wof:name":"The Pour House Pub",
    "wof:placetype":"venue"
},
  "geometry": {"coordinates":[-95.55932300000001,29.641201],"type":"Point"}
}