{
  "type": "Feature",
  "properties": {
    "iso:country":"US",
    "sg:address":"108 W Main St",
    "sg:city":"Denison",
    "sg:classifiers":[
        {
            "category":"Government",
            "subcategory":"Fire Station",
            "type":"Public Place"
        }
    ],
    "sg:phone":"+1 903 465 2720",
    "sg:postcode":"75021",
    "sg:province":"TX",
    "sg:tags":[
        "department"
    ],
    "wof:name":"Denison Fire Dept",
    "wof:placetype":"venue"
},
  "geometry": {"coordinates":[-96.53677,33.755271],"type":"Point"}
}