{
  "type": "Feature",
  "properties": {
    "iso:country":"US",
    "sg:address":"1700 Vera St",
    "sg:city":"Fort Worth",
    "sg:classifiers":[
        {
            "category":"Organizations",
            "subcategory":"Religious Organization",
            "type":"Services"
        }
    ],
    "sg:phone":"+1 817 536 5040",
    "sg:postcode":"76105",
    "sg:province":"TX",
    "sg:tags":[
        "church"
    ],
    "wof:name":"Sunshine Church God In Christ",
    "wof:placetype":"venue"
},
  "geometry": {"coordinates":[-97.246844,32.727134],"type":"Point"}
}