{
  "type": "Feature",
  "properties": {
    "iso:country":"US",
    "sg:address":"3600 Gaston Ave Ste 609",
    "sg:city":"Dallas",
    "sg:classifiers":[
        {
            "category":"Health Services",
            "subcategory":"Optometrist",
            "type":"Services"
        }
    ],
    "sg:phone":"+1 214 826 8201",
    "sg:postcode":"75246",
    "sg:province":"TX",
    "sg:tags":[
        "ophthalmologist"
    ],
    "wof:name":"Milner Michael S MD",
    "wof:placetype":"venue"
},
  "geometry": {"coordinates":[-96.78040300000001,32.791],"type":"Point"}
}