{
  "type": "Feature",
  "properties": {
    "iso:country":"US",
    "sg:address":"6700 S Flores St",
    "sg:city":"San Antonio",
    "sg:classifiers":[
        {
            "category":"Cinema",
            "subcategory":"Movie Rental",
            "type":"Entertainment"
        }
    ],
    "sg:phone":"+1 210 921 0111",
    "sg:postcode":"78221",
    "sg:province":"TX",
    "sg:tags":[
        "video",
        "tape"
    ],
    "wof:name":"Blockbuster",
    "wof:placetype":"venue"
},
  "geometry": {"coordinates":[-98.49018,29.354825],"type":"Point"}
}