{
  "type": "Feature",
  "properties": {
    "iso:country":"US",
    "sg:address":"2951 Shadow Trail Dr",
    "sg:city":"Houston",
    "sg:classifiers":[
        {
            "category":"Real Estate",
            "subcategory":"Real Estate Operator",
            "type":"Services"
        }
    ],
    "sg:phone":"+1 281 870 1961",
    "sg:postcode":"77082",
    "sg:province":"TX",
    "sg:tags":[
        "building",
        "nonresidential"
    ],
    "wof:name":"Windchase Property LLC",
    "wof:placetype":"venue"
},
  "geometry": {"coordinates":[-95.628373,29.730749],"type":"Point"}
}