{
  "type": "Feature",
  "properties": {
    "iso:country":"US",
    "sg:address":"3425 US Hwy 385",
    "sg:city":"Hereford",
    "sg:classifiers":[
        {
            "category":"Real Estate",
            "subcategory":"Real Estate Agent",
            "type":"Services"
        }
    ],
    "sg:phone":"+1 806 364 3331",
    "sg:postcode":"79045",
    "sg:province":"TX",
    "sg:tags":[
        "cooperative"
    ],
    "wof:name":"West Texas Rural Phone Co Op",
    "wof:placetype":"venue"
},
  "geometry": {"coordinates":[-102.40569499999999,34.791049],"type":"Point"}
}