{
  "type": "Feature",
  "properties": {
    "iso:country":"US",
    "sg:address":"3101 S 23rd St",
    "sg:city":"Mcallen",
    "sg:classifiers":[
        {
            "category":"Autos & Motor Vehicles",
            "subcategory":"Automobile Sales",
            "type":"Retail Goods"
        }
    ],
    "sg:phone":"+1 956 618 1609",
    "sg:postcode":"78503",
    "sg:province":"TX",
    "sg:tags":[
        "new",
        "used",
        "car"
    ],
    "wof:name":"E & A Motors",
    "wof:placetype":"venue"
},
  "geometry": {"coordinates":[-98.24981699999999,26.177139],"type":"Point"}
}