{
  "type": "Feature",
  "properties": {
    "iso:country":"US",
    "sg:address":"2618 Bomar Ave",
    "sg:city":"Dallas",
    "sg:classifiers":[
        {
            "category":"Professional",
            "subcategory":"Business Services",
            "type":"Services"
        }
    ],
    "sg:phone":"+1 469 916 3975",
    "sg:postcode":"75235",
    "sg:province":"TX",
    "wof:name":"Industrial Products & Solution",
    "wof:placetype":"venue"
},
  "geometry": {"coordinates":[-96.83835000000001,32.827177],"type":"Point"}
}