{
  "type": "Feature",
  "properties": {
    "iso:country":"US",
    "sg:address":"1550 Langham Rd",
    "sg:city":"Beaumont",
    "sg:classifiers":[
        {
            "category":"Building & Trades",
            "subcategory":"Electrical",
            "type":"Services"
        }
    ],
    "sg:phone":"+1 409 860 5211",
    "sg:postcode":"77707",
    "sg:province":"TX",
    "sg:tags":[
        "electrical",
        "contractor"
    ],
    "wof:name":"Electrical Specialties Inc",
    "wof:placetype":"venue"
},
  "geometry": {"coordinates":[-94.165182,30.056473],"type":"Point"}
}