{
  "type": "Feature",
  "properties": {
    "iso:country":"US",
    "sg:address":"12000 Network Blvd",
    "sg:city":"San Antonio",
    "sg:classifiers":[
        {
            "category":"Professional",
            "subcategory":"Management & Consulting",
            "type":"Services"
        }
    ],
    "sg:phone":"+1 210 558 9955",
    "sg:postcode":"78249",
    "sg:province":"TX",
    "wof:name":"Affinitas Corporation",
    "wof:placetype":"venue"
},
  "geometry": {"coordinates":[-98.589068,29.548727],"type":"Point"}
}