{
  "type": "Feature",
  "properties": {
    "iso:country":"US",
    "sg:address":"15418 Ashburton Dr",
    "sg:city":"Jersey Village",
    "sg:classifiers":[
        {
            "category":"Banks & Credit Unions",
            "subcategory":"Investment Brokerage",
            "type":"Services"
        }
    ],
    "sg:phone":"+1 713 466 3739",
    "sg:postcode":"77040",
    "sg:province":"TX",
    "sg:tags":[
        "investing"
    ],
    "wof:name":"J C And Associates",
    "wof:placetype":"venue"
},
  "geometry": {"coordinates":[-95.55286099999999,29.8901],"type":"Point"}
}