{
  "type": "Feature",
  "properties": {
    "iso:country":"US",
    "sg:address":"606 W 29th St",
    "sg:city":"Austin",
    "sg:classifiers":[
        {
            "category":"Retail",
            "subcategory":"Laundry & Dry Cleaning",
            "type":"Services"
        }
    ],
    "sg:postcode":"78705",
    "sg:province":"TX",
    "wof:name":"Neighborhood Laundromat",
    "wof:placetype":"venue"
},
  "geometry": {"coordinates":[-97.74292699999999,30.295485],"type":"Point"}
}