{
  "type": "Feature",
  "properties": {
    "iso:country":"US",
    "sg:address":"1412 Lost Creek Dr",
    "sg:city":"De Soto",
    "sg:classifiers":[
        {
            "category":"Retail",
            "subcategory":"Repair Shop",
            "type":"Services"
        }
    ],
    "sg:phone":"+1 972 230 8312",
    "sg:postcode":"75115",
    "sg:province":"TX",
    "wof:name":"Cleaning Dude",
    "wof:placetype":"venue"
},
  "geometry": {"coordinates":[-96.895318,32.592309],"type":"Point"}
}