{
  "type": "Feature",
  "properties": {
    "iso:country":"US",
    "sg:address":"5847 San Felipe St",
    "sg:city":"Houston",
    "sg:classifiers":[
        {
            "category":"Professional",
            "subcategory":"Lawyer & Legal Services",
            "type":"Services"
        }
    ],
    "sg:phone":"+1 713 781 2889",
    "sg:postcode":"77057",
    "sg:province":"TX",
    "wof:name":"Kathleen Crouch",
    "wof:placetype":"venue"
},
  "geometry": {"coordinates":[-95.48191199999999,29.749061],"type":"Point"}
}