{
  "type": "Feature",
  "properties": {
    "iso:country":"US",
    "sg:address":"414 Fannin St",
    "sg:city":"Houston",
    "sg:classifiers":[
        {
            "category":"Parking",
            "type":"Transportation"
        }
    ],
    "sg:phone":"+1 713 223 3911",
    "sg:postcode":"77002",
    "sg:province":"TX",
    "sg:tags":[
        "automobile"
    ],
    "wof:name":"Classified Parking System Inc",
    "wof:placetype":"venue"
},
  "geometry": {"coordinates":[-95.361042,29.760374],"type":"Point"}
}