{
  "type": "Feature",
  "properties": {
    "iso:country":"US",
    "sg:address":"9090 Skillman St",
    "sg:city":"Dallas",
    "sg:classifiers":[
        {
            "category":"Coffee & Tea",
            "type":"Food & Drink"
        }
    ],
    "sg:menulink":"http://www.allmenus.com/tx/northeast/112816-starbucks-coffee/menu/",
    "sg:phone":"+1 214 221 0060",
    "sg:postcode":"75243",
    "sg:province":"TX",
    "sg:tags":[
        "american"
    ],
    "wof:name":"Starbucks Coffee",
    "wof:placetype":"venue"
},
  "geometry": {"coordinates":[-96.71953600000001,32.896924],"type":"Point"}
}