{
  "type": "Feature",
  "properties": {
    "iso:country":"US",
    "sg:address":"3435 Greystone Dr Suite 107",
    "sg:city":"Austin",
    "sg:classifiers":[
        {
            "category":"Personal",
            "subcategory":"Massage",
            "type":"Services"
        }
    ],
    "sg:phone":"+1 512 422 2680",
    "sg:postcode":"78731",
    "sg:province":"TX",
    "sg:website":"charlotteshealinghands.com/",
    "wof:name":"Charlotte's Healing Hands",
    "wof:placetype":"venue"
},
  "geometry": {"coordinates":[-97.748457,30.357151],"type":"Point"}
}