{
  "type": "Feature",
  "properties": {
    "iso:country":"US",
    "sg:address":"8506 Hunters Village Dr",
    "sg:city":"Humble",
    "sg:classifiers":[
        {
            "category":"Real Estate",
            "subcategory":"Real Estate Operator",
            "type":"Services"
        }
    ],
    "sg:phone":"+1 281 852 2063",
    "sg:postcode":"77346",
    "sg:province":"TX",
    "sg:tags":[
        "building",
        "nonresidential"
    ],
    "wof:name":"Cni Properties LLC",
    "wof:placetype":"venue"
},
  "geometry": {"coordinates":[-95.149236,29.986814],"type":"Point"}
}