{
  "type": "Feature",
  "properties": {
    "iso:country":"US",
    "sg:address":"16351 Calvert Rd",
    "sg:city":"Forney",
    "sg:classifiers":[
        {
            "category":"Wholesale",
            "subcategory":"Non-durable Goods",
            "type":"Manufacturing & Wholesale Goods"
        }
    ],
    "sg:phone":"+1 972 564 4192",
    "sg:postcode":"75126",
    "sg:province":"TX",
    "wof:name":"Little Feet Little Tails",
    "wof:placetype":"venue"
},
  "geometry": {"coordinates":[-96.397648,32.794993],"type":"Point"}
}