{
  "type": "Feature",
  "properties": {
    "iso:country":"US",
    "sg:address":"2060 Lamar Ave",
    "sg:city":"Paris",
    "sg:classifiers":[
        {
            "category":"Building & Trades",
            "subcategory":"Equipment Rental",
            "type":"Services"
        }
    ],
    "sg:phone":"+1 903 784 3309",
    "sg:postcode":"75460",
    "sg:province":"TX",
    "sg:tags":[
        "appliance"
    ],
    "wof:name":"Color Tyme",
    "wof:placetype":"venue"
},
  "geometry": {"coordinates":[-95.53486100000001,33.661159],"type":"Point"}
}