{
  "type": "Feature",
  "properties": {
    "iso:country":"US",
    "sg:address":"14019 Denton Dr",
    "sg:city":"Dallas",
    "sg:classifiers":[
        {
            "category":"Autos & Motor Vehicles",
            "subcategory":"Automobile Sales",
            "type":"Retail Goods"
        }
    ],
    "sg:phone":"+1 972 243 7350",
    "sg:postcode":"75234",
    "sg:province":"TX",
    "sg:tags":[
        "car",
        "used",
        "dealer"
    ],
    "wof:name":"Metrocrest Sales",
    "wof:placetype":"venue"
},
  "geometry": {"coordinates":[-96.900696,32.935358],"type":"Point"}
}