{
  "type": "Feature",
  "properties": {
    "iso:country":"US",
    "sg:address":"8705 Kingsway Dr",
    "sg:city":"Canutillo",
    "sg:classifiers":[
        {
            "category":"Freight",
            "type":"Transportation"
        }
    ],
    "sg:phone":"+1 915 886 2023",
    "sg:postcode":"79835",
    "sg:province":"TX",
    "wof:name":"Torres Freight",
    "wof:placetype":"venue"
},
  "geometry": {"coordinates":[-106.580975,31.964758],"type":"Point"}
}