{
  "type": "Feature",
  "properties": {
    "iso:country":"US",
    "sg:address":"524 W Corsicana St",
    "sg:city":"Athens",
    "sg:classifiers":[
        {
            "category":"Autos & Motor Vehicles",
            "subcategory":"Fuel & Gas Station",
            "type":"Retail Goods"
        }
    ],
    "sg:phone":"+1 903 675 9488",
    "sg:postcode":"75751",
    "sg:province":"TX",
    "sg:tags":[
        "station",
        "gasoline"
    ],
    "wof:name":"Texaco",
    "wof:placetype":"venue"
},
  "geometry": {"coordinates":[-95.86335099999999,32.204398],"type":"Point"}
}