{
  "type": "Feature",
  "properties": {
    "iso:country":"US",
    "sg:address":"160 Deer Park Dr",
    "sg:city":"Waskom",
    "sg:classifiers":[
        {
            "category":"Shopping",
            "subcategory":"Hobbies, Toys, & Games",
            "type":"Retail Goods"
        }
    ],
    "sg:phone":"+1 903 667 2626",
    "sg:postcode":"75692",
    "sg:province":"TX",
    "sg:tags":[
        "shop"
    ],
    "wof:name":"Sdn Communications",
    "wof:placetype":"venue"
},
  "geometry": {"coordinates":[-94.10908999999999,32.484509],"type":"Point"}
}