{
  "type": "Feature",
  "properties": {
    "iso:country":"US",
    "sg:address":"1117 E Henderson St",
    "sg:city":"Cleburne",
    "sg:classifiers":[
        {
            "category":"Autos & Motor Vehicles",
            "subcategory":"Automobile Sales",
            "type":"Retail Goods"
        }
    ],
    "sg:phone":"+1 817 645 6660",
    "sg:postcode":"76031",
    "sg:province":"TX",
    "sg:tags":[
        "car",
        "dealer"
    ],
    "wof:name":"Carl Giles Auto Sales",
    "wof:placetype":"venue"
},
  "geometry": {"coordinates":[-97.371419,32.35199],"type":"Point"}
}