{
  "type": "Feature",
  "properties": {
    "iso:country":"US",
    "sg:address":"7511 Kathy Ln",
    "sg:city":"Benbrook",
    "sg:classifiers":[
        {
            "category":"Building & Trades",
            "subcategory":"Landscaping Services",
            "type":"Services"
        }
    ],
    "sg:phone":"+1 817 249 1070",
    "sg:postcode":"76126",
    "sg:province":"TX",
    "sg:tags":[
        "machinery",
        "landscape",
        "contractor"
    ],
    "sg:website":"www.grasseaters.com",
    "wof:name":"Grasseaters Lawn Maintenance",
    "wof:placetype":"venue"
},
  "geometry": {"coordinates":[-97.445779,32.690485],"type":"Point"}
}