{
  "type": "Feature",
  "properties": {
    "iso:country":"US",
    "sg:address":"22557 Aldine Westfield Rd",
    "sg:city":"Spring",
    "sg:classifiers":[
        {
            "category":"Personal",
            "type":"Services"
        }
    ],
    "sg:phone":"+1 281 651 0900",
    "sg:postcode":"77373",
    "sg:province":"TX",
    "wof:name":"Day Dreams Spa & Salon",
    "wof:placetype":"venue"
},
  "geometry": {"coordinates":[-95.382963,30.041688],"type":"Point"}
}