{
  "type": "Feature",
  "properties": {
    "iso:country":"US",
    "sg:address":"945 2nd St NE",
    "sg:city":"Paris",
    "sg:classifiers":[
        {
            "category":"Retail",
            "subcategory":"Auto Repair",
            "type":"Services"
        }
    ],
    "sg:phone":"+1 903 785 6049",
    "sg:postcode":"75460",
    "sg:province":"TX",
    "sg:tags":[
        "repairing",
        "automobile"
    ],
    "wof:name":"Smooth Automotive Brake Repair",
    "wof:placetype":"venue"
},
  "geometry": {"coordinates":[-95.554822,33.669241],"type":"Point"}
}