{
  "type": "Feature",
  "properties": {
    "iso:country":"US",
    "sg:address":"22 US Hwy 87",
    "sg:city":"Comfort",
    "sg:classifiers":[
        {
            "category":"Shopping",
            "subcategory":"Used Merchandise",
            "type":"Retail Goods"
        }
    ],
    "sg:phone":"+1 830 995 4192",
    "sg:postcode":"78013",
    "sg:province":"TX",
    "wof:name":"Highbrow and Hicks LLC",
    "wof:placetype":"venue"
},
  "geometry": {"coordinates":[-98.904101,29.971507],"type":"Point"}
}