{
  "type": "Feature",
  "properties": {
    "iso:country":"US",
    "sg:address":"581 W Campbell Rd",
    "sg:city":"Richardson",
    "sg:classifiers":[
        {
            "category":"Restaurant",
            "type":"Food & Drink"
        }
    ],
    "sg:phone":"+1 972 437 9727",
    "sg:postcode":"75080",
    "sg:province":"TX",
    "wof:name":"Suprabhath",
    "wof:placetype":"venue"
},
  "geometry": {"coordinates":[-96.737459,32.976726],"type":"Point"}
}