{
  "type": "Feature",
  "properties": {
    "iso:country":"US",
    "sg:address":"2525 Wallingwood Dr # 500",
    "sg:city":"Austin",
    "sg:classifiers":[
        {
            "category":"Organizations",
            "subcategory":"Labor Organization",
            "type":"Services"
        }
    ],
    "sg:phone":"+1 512 328 1144",
    "sg:postcode":"78746",
    "sg:province":"TX",
    "wof:name":"Alliance Work Partners",
    "wof:placetype":"venue"
},
  "geometry": {"coordinates":[-97.785397,30.264018],"type":"Point"}
}