{
  "type": "Feature",
  "properties": {
    "iso:country":"US",
    "sg:address":"5414 Stormy Autumn",
    "sg:city":"San Antonio",
    "sg:classifiers":[
        {
            "category":"Professional",
            "type":"Services"
        }
    ],
    "sg:phone":"+1 210 590 7631",
    "sg:postcode":"78247",
    "sg:province":"TX",
    "wof:name":"Carthago Foods Internatio",
    "wof:placetype":"venue"
},
  "geometry": {"coordinates":[-98.38589899999999,29.588737],"type":"Point"}
}