{
  "type": "Feature",
  "properties": {
    "iso:country":"US",
    "sg:address":"10720 N Loop Dr",
    "sg:city":"El Paso",
    "sg:classifiers":[
        {
            "category":"Food & Beverages",
            "subcategory":"Groceries & Convenience Stores",
            "type":"Retail Goods"
        }
    ],
    "sg:phone":"+1 915 858 4011",
    "sg:postcode":"79927",
    "sg:province":"TX",
    "sg:tags":[
        "grocer"
    ],
    "wof:name":"Horizon Big 8",
    "wof:placetype":"venue"
},
  "geometry": {"coordinates":[-106.268945,31.653293],"type":"Point"}
}