{
  "type": "Feature",
  "properties": {
    "iso:country":"US",
    "sg:address":"27318 Buttercup Ln",
    "sg:city":"Magnolia",
    "sg:classifiers":[
        {
            "category":"Building & Trades",
            "subcategory":"Construction",
            "type":"Services"
        }
    ],
    "sg:phone":"+1 281 356 9465",
    "sg:postcode":"77354",
    "sg:province":"TX",
    "sg:tags":[
        "contractor"
    ],
    "wof:name":"Anderson Roofing & Sheet Metal",
    "wof:placetype":"venue"
},
  "geometry": {"coordinates":[-95.640533,30.163743],"type":"Point"}
}