{
  "type": "Feature",
  "properties": {
    "iso:country":"US",
    "sg:address":"815 N 4th St",
    "sg:city":"Longview",
    "sg:classifiers":[
        {
            "category":"Health Services",
            "subcategory":"Medical Lab",
            "type":"Services"
        }
    ],
    "sg:phone":"+1 903 236 0887",
    "sg:postcode":"75601",
    "sg:province":"TX",
    "sg:tags":[
        "laboratory"
    ],
    "wof:name":"Laboratory Corp Of America",
    "wof:placetype":"venue"
},
  "geometry": {"coordinates":[-94.731144,32.506065],"type":"Point"}
}