{
  "type": "Feature",
  "properties": {
    "iso:country":"US",
    "sg:address":"1702 S Jackson St",
    "sg:city":"Jacksonville",
    "sg:classifiers":[
        {
            "category":"Restaurant",
            "type":"Food & Drink"
        }
    ],
    "sg:phone":"+1 903 541 2121",
    "sg:postcode":"75766",
    "sg:province":"TX",
    "sg:tags":[
        "eating"
    ],
    "wof:name":"Chubby's Grill & Bar Inc",
    "wof:placetype":"venue"
},
  "geometry": {"coordinates":[-95.26182900000001,31.94951],"type":"Point"}
}