{
  "type": "Feature",
  "properties": {
    "iso:country":"US",
    "sg:address":"12800 Jupiter Rd",
    "sg:city":"Dallas",
    "sg:classifiers":[
        {
            "category":"Real Estate",
            "subcategory":"Real Estate Operator",
            "type":"Services"
        }
    ],
    "sg:phone":"+1 214 348 9397",
    "sg:postcode":"75238",
    "sg:province":"TX",
    "sg:tags":[
        "apartment"
    ],
    "wof:name":"Madison",
    "wof:placetype":"venue"
},
  "geometry": {"coordinates":[-96.683133,32.868784],"type":"Point"}
}