{
  "type": "Feature",
  "properties": {
    "iso:country":"US",
    "sg:address":"1424 G Ave",
    "sg:city":"Plano",
    "sg:classifiers":[
        {
            "category":"Shopping",
            "subcategory":"Tobacco",
            "type":"Retail Goods"
        }
    ],
    "sg:phone":"+1 972 424 7272",
    "sg:postcode":"75074",
    "sg:province":"TX",
    "sg:tags":[
        "product"
    ],
    "wof:name":"Two Brothers Cigars",
    "wof:placetype":"venue"
},
  "geometry": {"coordinates":[-96.70496799999999,33.019409],"type":"Point"}
}