{
  "type": "Feature",
  "properties": {
    "iso:country":"US",
    "sg:address":"817 Merribrook Ln",
    "sg:city":"Friendswood",
    "sg:classifiers":[
        {
            "category":"Retail",
            "subcategory":"Repair Shop",
            "type":"Services"
        }
    ],
    "sg:phone":"+1 281 482 7680",
    "sg:postcode":"77546",
    "sg:province":"TX",
    "sg:tags":[
        "refrigeration"
    ],
    "wof:name":"Hop Air",
    "wof:placetype":"venue"
},
  "geometry": {"coordinates":[-95.21829099999999,29.538161],"type":"Point"}
}