{
  "type": "Feature",
  "properties": {
    "iso:country":"US",
    "sg:address":"1200 Chestnut St",
    "sg:city":"Waco",
    "sg:classifiers":[
        {
            "category":"Organizations",
            "subcategory":"Religious Organization",
            "type":"Services"
        }
    ],
    "sg:phone":"+1 254 754 8703",
    "sg:postcode":"76704",
    "sg:province":"TX",
    "wof:name":"Christ Is Answer Baptist Churc",
    "wof:placetype":"venue"
},
  "geometry": {"coordinates":[-97.119918,31.576891],"type":"Point"}
}