{
  "type": "Feature",
  "properties": {
    "iso:country":"US",
    "sg:address":"8775 Flagship Dr",
    "sg:city":"Houston",
    "sg:classifiers":[
        {
            "category":"Organizations",
            "subcategory":"Religious Organization",
            "type":"Services"
        }
    ],
    "sg:phone":"+1 713 674 4435",
    "sg:postcode":"77029",
    "sg:province":"TX",
    "sg:tags":[
        "baptist",
        "center",
        "church",
        "child",
        "day",
        "care"
    ],
    "wof:name":"Gethsemane Learning Center",
    "wof:placetype":"venue"
},
  "geometry": {"coordinates":[-95.267414,29.758582],"type":"Point"}
}