{
  "type": "Feature",
  "properties": {
    "iso:country":"US",
    "sg:address":"523 24th St Ste 5",
    "sg:city":"Galveston",
    "sg:classifiers":[
        {
            "category":"Travel",
            "subcategory":"Hotels & Motels",
            "type":"Entertainment"
        }
    ],
    "sg:phone":"+1 409 763 8678",
    "sg:postcode":"77550",
    "sg:province":"TX",
    "wof:name":"Galveston Carriage Place",
    "wof:placetype":"venue"
},
  "geometry": {"coordinates":[-94.794538,29.304041],"type":"Point"}
}