{
  "type": "Feature",
  "properties": {
    "iso:country":"US",
    "sg:address":"8500 Almeda Genoa Rd Ste 102",
    "sg:city":"Houston",
    "sg:classifiers":[
        {
            "category":"Restaurant",
            "type":"Food & Drink"
        }
    ],
    "sg:phone":"+1 713 991 4411",
    "sg:postcode":"77075",
    "sg:province":"TX",
    "sg:tags":[
        "mexican"
    ],
    "wof:name":"LA SILLA POLLOS ASADOS",
    "wof:placetype":"venue"
},
  "geometry": {"coordinates":[-95.26664100000001,29.626183],"type":"Point"}
}