{
  "type": "Feature",
  "properties": {
    "iso:country":"US",
    "sg:address":"1202 Ralph St",
    "sg:city":"Grand Prairie",
    "sg:classifiers":[
        {
            "category":"Organizations",
            "subcategory":"Religious Organization",
            "type":"Services"
        }
    ],
    "sg:phone":"+1 972 264 7629",
    "sg:postcode":"75051",
    "sg:province":"TX",
    "wof:name":"Love In Christ Foundation",
    "wof:placetype":"venue"
},
  "geometry": {"coordinates":[-97.01021900000001,32.728776],"type":"Point"}
}