{
  "type": "Feature",
  "properties": {
    "iso:country":"US",
    "sg:address":"602 Main St",
    "sg:city":"Mt Vernon",
    "sg:classifiers":[
        {
            "category":"Autos & Motor Vehicles",
            "subcategory":"Auto Supplies",
            "type":"Retail Goods"
        }
    ],
    "sg:phone":"+1 903 537 4445",
    "sg:postcode":"75457",
    "sg:province":"TX",
    "sg:tags":[
        "tire"
    ],
    "wof:name":"Longhorn Tire Svc",
    "wof:placetype":"venue"
},
  "geometry": {"coordinates":[-95.22716800000001,33.188806],"type":"Point"}
}