{
  "type": "Feature",
  "properties": {
    "iso:country":"US",
    "sg:address":"702 US Hwy 77 Alt",
    "sg:city":"Yoakum",
    "sg:classifiers":[
        {
            "category":"Autos & Motor Vehicles",
            "subcategory":"Automobile Sales",
            "type":"Retail Goods"
        }
    ],
    "sg:phone":"+1 361 293 9118",
    "sg:postcode":"77995",
    "sg:province":"TX",
    "sg:tags":[
        "car",
        "dealer"
    ],
    "wof:name":"Triple R Motors",
    "wof:placetype":"venue"
},
  "geometry": {"coordinates":[-97.161737,29.294519],"type":"Point"}
}