{
  "type": "Feature",
  "properties": {
    "iso:country":"US",
    "sg:address":"8502 Wileyvale Rd",
    "sg:city":"Houston",
    "sg:classifiers":[
        {
            "category":"Professional",
            "type":"Services"
        }
    ],
    "sg:phone":"+1 713 491 7320",
    "sg:postcode":"77016",
    "sg:province":"TX",
    "wof:name":"Anthony Hallman",
    "wof:placetype":"venue"
},
  "geometry": {"coordinates":[-95.316671,29.839344],"type":"Point"}
}