{
  "type": "Feature",
  "properties": {
    "iso:country":"US",
    "sg:address":"2943 Oak Ct",
    "sg:city":"Granbury",
    "sg:classifiers":[
        {
            "category":"Recreation",
            "type":"Entertainment"
        }
    ],
    "sg:phone":"+1 817 578 3044",
    "sg:postcode":"76048",
    "sg:province":"TX",
    "wof:name":"Cross Timbers Gymnastics Inc",
    "wof:placetype":"venue"
},
  "geometry": {"coordinates":[-97.81460199999999,32.375942],"type":"Point"}
}