{
  "type": "Feature",
  "properties": {
    "iso:country":"US",
    "sg:address":"4609 Hogan Dr",
    "sg:city":"Corpus Christi",
    "sg:classifiers":[
        {
            "category":"Building & Trades",
            "subcategory":"Landscaping Services",
            "type":"Services"
        }
    ],
    "sg:phone":"+1 361 992 8165",
    "sg:postcode":"78413",
    "sg:province":"TX",
    "sg:tags":[
        "lawn"
    ],
    "wof:name":"Trotter Landscape",
    "wof:placetype":"venue"
},
  "geometry": {"coordinates":[-97.403637,27.689966],"type":"Point"}
}