{
  "type": "Feature",
  "properties": {
    "iso:country":"US",
    "sg:address":"1112 N Grant St",
    "sg:city":"Amarillo",
    "sg:classifiers":[
        {
            "category":"Organizations",
            "subcategory":"Religious Organization",
            "type":"Services"
        }
    ],
    "sg:phone":"+1 806 383 3005",
    "sg:postcode":"79107",
    "sg:province":"TX",
    "sg:tags":[
        "church"
    ],
    "wof:name":"Ebenezer AME Church",
    "wof:placetype":"venue"
},
  "geometry": {"coordinates":[-101.82505399999999,35.226044],"type":"Point"}
}