{
  "type": "Feature",
  "properties": {
    "iso:country":"US",
    "sg:address":"10802 Riverview Dr",
    "sg:city":"Houston",
    "sg:classifiers":[
        {
            "category":"Cinema",
            "subcategory":"Movie Theater",
            "type":"Entertainment"
        }
    ],
    "sg:phone":"+1 713 972 1333",
    "sg:postcode":"77042",
    "sg:province":"TX",
    "sg:tags":[
        "motion",
        "picture"
    ],
    "wof:name":"Shalimar Entertainment",
    "wof:placetype":"venue"
},
  "geometry": {"coordinates":[-95.569513,29.758679],"type":"Point"}
}