{
  "type": "Feature",
  "properties": {
    "iso:country":"US",
    "sg:address":"217 Anthony St",
    "sg:city":"Canutillo",
    "sg:classifiers":[
        {
            "category":"Food & Beverages",
            "subcategory":"Groceries & Convenience Stores",
            "type":"Retail Goods"
        }
    ],
    "sg:phone":"+1 915 877 3638",
    "sg:postcode":"79835",
    "sg:province":"TX",
    "wof:name":"Angel Mary Rivera",
    "wof:placetype":"venue"
},
  "geometry": {"coordinates":[-106.598916,31.920372],"type":"Point"}
}