{
  "type": "Feature",
  "properties": {
    "iso:country":"US",
    "sg:address":"1306 Guadalupe St",
    "sg:city":"Austin",
    "sg:classifiers":[
        {
            "category":"Professional",
            "subcategory":"Lawyer & Legal Services",
            "type":"Services"
        }
    ],
    "sg:phone":"+1 512 473 8903",
    "sg:postcode":"78701",
    "sg:province":"TX",
    "sg:tags":[
        "attorney"
    ],
    "wof:name":"Burton W Amon Jr",
    "wof:placetype":"venue"
},
  "geometry": {"coordinates":[-97.743426,30.276908],"type":"Point"}
}