{
  "type": "Feature",
  "properties": {
    "iso:country":"US",
    "sg:address":"1029 N New Braunfels Ave",
    "sg:city":"San Antonio",
    "sg:classifiers":[
        {
            "category":"Retail",
            "subcategory":"Repair Shop",
            "type":"Services"
        }
    ],
    "sg:phone":"+1 210 224 4634",
    "sg:postcode":"78202",
    "sg:province":"TX",
    "sg:tags":[
        "upholsterer"
    ],
    "wof:name":"Luna's Upholstery",
    "wof:placetype":"venue"
},
  "geometry": {"coordinates":[-98.461057,29.431466],"type":"Point"}
}