{
  "type": "Feature",
  "properties": {
    "iso:country":"US",
    "sg:address":"8804 Summit Point Ct",
    "sg:city":"Fort Worth",
    "sg:classifiers":[
        {
            "category":"Banks & Credit Unions",
            "subcategory":"Financial Services",
            "type":"Services"
        }
    ],
    "sg:phone":"+1 817 236 7751",
    "sg:postcode":"76179",
    "sg:province":"TX",
    "sg:tags":[
        "trust",
        "investment",
        "real estate"
    ],
    "wof:name":"Jerri L Thomas Inc",
    "wof:placetype":"venue"
},
  "geometry": {"coordinates":[-97.43592599999999,32.875543],"type":"Point"}
}