{
  "type": "Feature",
  "properties": {
    "iso:country":"US",
    "sg:address":"1178 Co Rd 250",
    "sg:city":"Weimar",
    "sg:classifiers":[
        {
            "category":"Retail",
            "subcategory":"Portrait Studio",
            "type":"Services"
        }
    ],
    "sg:phone":"+1 979 725 8812",
    "sg:postcode":"78962",
    "sg:province":"TX",
    "sg:tags":[
        "photo"
    ],
    "wof:name":"Diane Kocurek Photography",
    "wof:placetype":"venue"
},
  "geometry": {"coordinates":[-96.796531,29.67201],"type":"Point"}
}