{
  "type": "Feature",
  "properties": {
    "iso:country":"US",
    "sg:address":"15007 Burning Creek",
    "sg:city":"San Antonio",
    "sg:classifiers":[
        {
            "category":"Personal",
            "subcategory":"Beauty Salon",
            "type":"Services"
        }
    ],
    "sg:phone":"+1 210 637 1196",
    "sg:postcode":"78217",
    "sg:province":"TX",
    "wof:name":"Braids & Locs",
    "wof:placetype":"venue"
},
  "geometry": {"coordinates":[-98.39926699999999,29.577524],"type":"Point"}
}