{
  "type": "Feature",
  "properties": {
    "iso:country":"US",
    "sg:address":"1421 Ave F",
    "sg:city":"Bay City",
    "sg:classifiers":[
        {
            "category":"Wholesale",
            "subcategory":"Electrical",
            "type":"Manufacturing & Wholesale Goods"
        }
    ],
    "sg:phone":"+1 979 245 2058",
    "sg:postcode":"77414",
    "sg:province":"TX",
    "sg:tags":[
        "electric",
        "motor"
    ],
    "wof:name":"T-3 Distribution",
    "wof:placetype":"venue"
},
  "geometry": {"coordinates":[-95.970196,28.99009],"type":"Point"}
}