{
  "type": "Feature",
  "properties": {
    "iso:country":"US",
    "sg:address":"201MAGNOLIA LN.",
    "sg:city":"Conroe",
    "sg:classifiers":[
        {
            "category":"Building & Trades",
            "subcategory":"Construction",
            "type":"Services"
        }
    ],
    "sg:phone":"+1 936 441 8377",
    "sg:postcode":"77304",
    "sg:province":"TX",
    "sg:tags":[
        "industrial",
        "contractors-commercial"
    ],
    "wof:name":"Northwest Z-TEK Sand & Gravel",
    "wof:placetype":"venue"
},
  "geometry": {"coordinates":[-95.503967,30.315941],"type":"Point"}
}