{
  "type": "Feature",
  "properties": {
    "iso:country":"US",
    "sg:address":"3103 Knox St",
    "sg:city":"Dallas",
    "sg:classifiers":[
        {
            "category":"Professional",
            "subcategory":"Engineering",
            "type":"Services"
        },
        {
            "category":"Home & Garden",
            "subcategory":"Building Materials",
            "type":"Retail Goods"
        }
    ],
    "sg:phone":"+1 469 533 7600",
    "sg:postcode":"75205",
    "sg:province":"TX",
    "sg:tags":[
        "insulation",
        "consultant",
        "product",
        "conservation",
        "energy"
    ],
    "wof:name":"Current Energy Store",
    "wof:placetype":"venue"
},
  "geometry": {"coordinates":[-96.787588,32.822681],"type":"Point"}
}