{
  "type": "Feature",
  "properties": {
    "iso:country":"US",
    "sg:address":"2220 San Jacinto Blvd",
    "sg:city":"Denton",
    "sg:classifiers":[
        {
            "category":"Professional",
            "subcategory":"Lawyer & Legal Services",
            "type":"Services"
        }
    ],
    "sg:phone":"+1 940 383 9300",
    "sg:postcode":"76205",
    "sg:province":"TX",
    "sg:tags":[
        "litigation",
        "attorney",
        "criminal",
        "personal",
        "civil",
        "practice",
        "trial",
        "injury",
        "law"
    ],
    "wof:name":"Hammerle Finley Law Firm",
    "wof:placetype":"venue"
},
  "geometry": {"coordinates":[-97.109453,33.192267],"type":"Point"}
}