{
  "type": "Feature",
  "properties": {
    "iso:country":"US",
    "sg:address":"1901 Schulze Cir",
    "sg:city":"Killeen",
    "sg:classifiers":[
        {
            "category":"Retail",
            "subcategory":"Repair Shop",
            "type":"Services"
        }
    ],
    "sg:phone":"+1 254 634 9353",
    "sg:postcode":"76549",
    "sg:province":"TX",
    "sg:tags":[
        "welding"
    ],
    "wof:name":"John Bridenstine Welding Co",
    "wof:placetype":"venue"
},
  "geometry": {"coordinates":[-97.764359,31.102949],"type":"Point"}
}