{
  "type": "Feature",
  "properties": {
    "iso:country":"US",
    "sg:address":"139 Park Dr",
    "sg:city":"San Antonio",
    "sg:classifiers":[
        {
            "category":"Professional",
            "type":"Services"
        }
    ],
    "sg:phone":"+1 210 822 9651",
    "sg:postcode":"78212",
    "sg:province":"TX",
    "wof:name":"Oscar Ehrenberg",
    "wof:placetype":"venue"
},
  "geometry": {"coordinates":[-98.485799,29.469888],"type":"Point"}
}