{
  "type": "Feature",
  "properties": {
    "iso:country":"US",
    "sg:address":"4655 Sweetwater Blvd",
    "sg:city":"Sugar Land",
    "sg:classifiers":[
        {
            "category":"Freight",
            "type":"Transportation"
        },
        {
            "category":"Professional",
            "subcategory":"Business Services",
            "type":"Services"
        }
    ],
    "sg:phone":"+1 281 804 2024",
    "sg:postcode":"77479",
    "sg:province":"TX",
    "sg:tags":[
        "packaging",
        "agent",
        "shipping"
    ],
    "wof:name":"Executive Shipping Svcs USA",
    "wof:placetype":"venue"
},
  "geometry": {"coordinates":[-95.63104199999999,29.583542],"type":"Point"}
}