{
  "type": "Feature",
  "properties": {
    "iso:country":"US",
    "sg:address":"114 W 83rd St",
    "sg:city":"Odessa",
    "sg:classifiers":[
        {
            "category":"Wholesale",
            "subcategory":"Machinery & Supplies",
            "type":"Manufacturing & Wholesale Goods"
        }
    ],
    "sg:phone":"+1 432 362 6600",
    "sg:postcode":"79764",
    "sg:province":"TX",
    "sg:tags":[
        "compressor",
        "gas"
    ],
    "wof:name":"Ironsmith Compression Inc",
    "wof:placetype":"venue"
},
  "geometry": {"coordinates":[-102.400818,31.927134],"type":"Point"}
}