{
  "type": "Feature",
  "properties": {
    "iso:country":"US",
    "sg:address":"615 Wilson Rd",
    "sg:city":"Humble",
    "sg:classifiers":[
        {
            "category":"Food & Beverages",
            "subcategory":"Bakery",
            "type":"Retail Goods"
        }
    ],
    "sg:phone":"+1 281 446 1813",
    "sg:postcode":"77338",
    "sg:province":"TX",
    "sg:tags":[
        "baking"
    ],
    "wof:name":"Momma Dees Sweets",
    "wof:placetype":"venue"
},
  "geometry": {"coordinates":[-95.249683,29.990449],"type":"Point"}
}