{
  "type": "Feature",
  "properties": {
    "iso:country":"US",
    "sg:address":"636 S Rivershire Dr",
    "sg:city":"Conroe",
    "sg:classifiers":[
        {
            "category":"Professional",
            "subcategory":"Management & Consulting",
            "type":"Services"
        }
    ],
    "sg:phone":"+1 936 539 3738",
    "sg:postcode":"77304",
    "sg:province":"TX",
    "sg:tags":[
        "business"
    ],
    "wof:name":"Omega Business Solutions",
    "wof:placetype":"venue"
},
  "geometry": {"coordinates":[-95.479353,30.285103],"type":"Point"}
}