{
  "type": "Feature",
  "properties": {
    "iso:country":"US",
    "sg:address":"118 W 10th St",
    "sg:city":"San Juan",
    "sg:classifiers":[
        {
            "category":"Recreation",
            "type":"Entertainment"
        }
    ],
    "sg:phone":"+1 956 787 9676",
    "sg:postcode":"78589",
    "sg:province":"TX",
    "wof:name":"Hell Raiser Paint Ball",
    "wof:placetype":"venue"
},
  "geometry": {"coordinates":[-98.157653,26.184841],"type":"Point"}
}