{
  "type": "Feature",
  "properties": {
    "iso:country":"US",
    "sg:address":"437 Quarry St",
    "sg:city":"Eagle Pass",
    "sg:classifiers":[
        {
            "category":"Professional",
            "subcategory":"Business Services",
            "type":"Services"
        }
    ],
    "sg:phone":"+1 830 752 1829",
    "sg:postcode":"78852",
    "sg:province":"TX",
    "wof:name":"Rose Maria Saldana",
    "wof:placetype":"venue"
},
  "geometry": {"coordinates":[-100.50219300000001,28.70937],"type":"Point"}
}