{
  "type": "Feature",
  "properties": {
    "iso:country":"US",
    "sg:address":"2112 Kennedy Ln",
    "sg:city":"Texarkana",
    "sg:classifiers":[
        {
            "category":"Education",
            "subcategory":"School",
            "type":"Public Place"
        }
    ],
    "sg:phone":"+1 903 794 3891",
    "sg:postcode":"75503",
    "sg:province":"TX",
    "wof:name":"Texas High School",
    "wof:placetype":"venue"
},
  "geometry": {"coordinates":[-94.06782,33.453858],"type":"Point"}
}