{
  "type": "Feature",
  "properties": {
    "iso:country":"US",
    "sg:address":"1910 Stonebrook Dr",
    "sg:city":"Arlington",
    "sg:classifiers":[
        {
            "category":"Shopping",
            "subcategory":"Books",
            "type":"Retail Goods"
        }
    ],
    "sg:phone":"+1 817 861 0205",
    "sg:postcode":"76012",
    "sg:province":"TX",
    "wof:name":"Myers Larry Books & Miscellany",
    "wof:placetype":"venue"
},
  "geometry": {"coordinates":[-97.14181600000001,32.766982],"type":"Point"}
}