{
  "type": "Feature",
  "properties": {
    "iso:country":"US",
    "sg:address":"910 S Highway 377",
    "sg:city":"Aubrey",
    "sg:classifiers":[
        {
            "category":"Social Services",
            "subcategory":"Child Care",
            "type":"Services"
        }
    ],
    "sg:phone":"+1 940 365 9481",
    "sg:postcode":"76227",
    "sg:province":"TX",
    "wof:name":"Simplee ABC",
    "wof:placetype":"venue"
},
  "geometry": {"coordinates":[-96.984917,33.294762],"type":"Point"}
}