{
  "type": "Feature",
  "properties": {
    "iso:country":"US",
    "sg:address":"4205 Woodland Park Ct",
    "sg:city":"Arlington",
    "sg:classifiers":[
        {
            "category":"Professional",
            "type":"Services"
        }
    ],
    "sg:phone":"+1 817 457 6620",
    "sg:postcode":"76013",
    "sg:province":"TX",
    "wof:name":"Moto Glasi",
    "wof:placetype":"venue"
},
  "geometry": {"coordinates":[-97.174696,32.712382],"type":"Point"}
}