{
  "type": "Feature",
  "properties": {
    "iso:country":"US",
    "sg:address":"6924 Council Dr",
    "sg:city":"Plano",
    "sg:classifiers":[
        {
            "category":"Professional",
            "type":"Services"
        }
    ],
    "sg:phone":"+1 972 618 4499",
    "sg:postcode":"75023",
    "sg:province":"TX",
    "sg:tags":[
        "investor"
    ],
    "wof:name":"Jaccar International",
    "wof:placetype":"venue"
},
  "geometry": {"coordinates":[-96.76444499999999,33.071658],"type":"Point"}
}