{
  "type": "Feature",
  "properties": {
    "iso:country":"US",
    "sg:address":"824 Maple St",
    "sg:city":"Uvalde",
    "sg:classifiers":[
        {
            "category":"Building & Trades",
            "subcategory":"Electrical",
            "type":"Services"
        }
    ],
    "sg:phone":"+1 830 261 9620",
    "sg:postcode":"78801",
    "sg:province":"TX",
    "sg:tags":[
        "electrician"
    ],
    "wof:name":"Everett's Electric",
    "wof:placetype":"venue"
},
  "geometry": {"coordinates":[-99.774851,29.217652],"type":"Point"}
}