{
  "type": "Feature",
  "properties": {
    "iso:country":"US",
    "sg:address":"4400 W Pleasant Ridge Rd",
    "sg:city":"Arlington",
    "sg:classifiers":[
        {
            "category":"Social Services",
            "subcategory":"Child Care",
            "type":"Services"
        }
    ],
    "sg:phone":"+1 817 478 7733",
    "sg:postcode":"76016",
    "sg:province":"TX",
    "sg:tags":[
        "kindergarten",
        "academic",
        "school",
        "day"
    ],
    "wof:name":"Children's Courtyard",
    "wof:placetype":"venue"
},
  "geometry": {"coordinates":[-97.17876800000001,32.682273],"type":"Point"}
}