{
  "type": "Feature",
  "properties": {
    "iso:country":"US",
    "sg:address":"612 W Gibson St",
    "sg:city":"Jasper",
    "sg:classifiers":[
        {
            "category":"Professional",
            "subcategory":"Management & Consulting",
            "type":"Services"
        }
    ],
    "sg:phone":"+1 409 383 0509",
    "sg:postcode":"75951",
    "sg:province":"TX",
    "wof:name":"Starlight Motel",
    "wof:placetype":"venue"
},
  "geometry": {"coordinates":[-94.01258300000001,30.906551],"type":"Point"}
}