{
  "type": "Feature",
  "properties": {
    "iso:country":"US",
    "sg:address":"4045 Pine St",
    "sg:city":"Beaumont",
    "sg:classifiers":[
        {
            "category":"Organizations",
            "subcategory":"Religious Organization",
            "type":"Services"
        }
    ],
    "sg:phone":"+1 409 832 4430",
    "sg:postcode":"77703",
    "sg:province":"TX",
    "wof:name":"Lacys Temple Church of God In",
    "wof:placetype":"venue"
},
  "geometry": {"coordinates":[-94.107901,30.118498],"type":"Point"}
}