{
  "type": "Feature",
  "properties": {
    "iso:country":"US",
    "sg:address":"13122 Creekside Park Dr",
    "sg:city":"Houston",
    "sg:classifiers":[
        {
            "category":"Professional",
            "subcategory":"Art Services",
            "type":"Services"
        }
    ],
    "sg:phone":"+1 281 752 9437",
    "sg:postcode":"77082",
    "sg:province":"TX",
    "sg:tags":[
        "commercial",
        "design"
    ],
    "wof:name":"Stump F Creativity",
    "wof:placetype":"venue"
},
  "geometry": {"coordinates":[-95.619839,29.724076],"type":"Point"}
}