{
  "type": "Feature",
  "properties": {
    "iso:country":"US",
    "sg:address":"9903 N Houston Rosslyn Rd",
    "sg:city":"Houston",
    "sg:classifiers":[
        {
            "category":"Food & Beverages",
            "subcategory":"Groceries & Convenience Stores",
            "type":"Retail Goods"
        }
    ],
    "sg:phone":"+1 713 937 1073",
    "sg:postcode":"77088",
    "sg:province":"TX",
    "wof:name":"E-Z 7 Food Store",
    "wof:placetype":"venue"
},
  "geometry": {"coordinates":[-95.494698,29.886101],"type":"Point"}
}