{
  "type": "Feature",
  "properties": {
    "iso:country":"US",
    "sg:address":"4906 Birch Bough Ct",
    "sg:city":"Humble",
    "sg:classifiers":[
        {
            "category":"Travel",
            "subcategory":"Travel Agent",
            "type":"Entertainment"
        }
    ],
    "sg:phone":"+1 281 360 1845",
    "sg:postcode":"77345",
    "sg:province":"TX",
    "sg:tags":[
        "operator",
        "tour"
    ],
    "wof:name":"Heliana Ford Travel & Tours",
    "wof:placetype":"venue"
},
  "geometry": {"coordinates":[-95.16784,30.078704],"type":"Point"}
}