{
  "type": "Feature",
  "properties": {
    "iso:country":"US",
    "sg:address":"13720 Midway Rd",
    "sg:city":"Dallas",
    "sg:classifiers":[
        {
            "category":"Professional",
            "type":"Services"
        }
    ],
    "sg:phone":"+1 972 702 8434",
    "sg:postcode":"75244",
    "sg:province":"TX",
    "sg:tags":[
        "establishment"
    ],
    "wof:name":"Spectrapharm Inc",
    "wof:placetype":"venue"
},
  "geometry": {"coordinates":[-96.83899700000001,32.933508],"type":"Point"}
}