{
  "type": "Feature",
  "properties": {
    "iso:country":"US",
    "sg:address":"21108 S US Hwy 277",
    "sg:city":"Christoval",
    "sg:classifiers":[
        {
            "category":"Building & Trades",
            "subcategory":"Construction",
            "type":"Services"
        }
    ],
    "sg:phone":"+1 325 255 2525",
    "sg:postcode":"76935",
    "sg:province":"TX",
    "sg:tags":[
        "general",
        "contractor"
    ],
    "wof:name":"Tres Amigos Convenience Store",
    "wof:placetype":"venue"
},
  "geometry": {"coordinates":[-100.51078099999999,31.174159],"type":"Point"}
}