{
  "type": "Feature",
  "properties": {
    "iso:country":"US",
    "sg:address":"2210 I- 45 N",
    "sg:city":"Conroe",
    "sg:classifiers":[
        {
            "category":"Food & Beverages",
            "subcategory":"Liquor & Beverages",
            "type":"Retail Goods"
        }
    ],
    "sg:phone":"+1 936 441 6696",
    "sg:postcode":"77301",
    "sg:province":"TX",
    "wof:name":"Beverage Market",
    "wof:placetype":"venue"
},
  "geometry": {"coordinates":[-95.48045999999999,30.340244],"type":"Point"}
}