{
  "type": "Feature",
  "properties": {
    "iso:country":"US",
    "sg:address":"1910 E Belt Line Rd",
    "sg:city":"Carrollton",
    "sg:classifiers":[
        {
            "category":"Insurance",
            "subcategory":"Insurance Agent",
            "type":"Services"
        }
    ],
    "sg:phone":"+1 972 478 2629",
    "sg:postcode":"75006",
    "sg:province":"TX",
    "wof:name":"A-Max Auto Insurance",
    "wof:placetype":"venue"
},
  "geometry": {"coordinates":[-96.887046,32.953597],"type":"Point"}
}