{
  "type": "Feature",
  "properties": {
    "iso:country":"US",
    "sg:address":"3702 Merrick St",
    "sg:city":"Houston",
    "sg:classifiers":[
        {
            "category":"Professional",
            "subcategory":"Management & Consulting",
            "type":"Services"
        }
    ],
    "sg:phone":"+1 713 668 0438",
    "sg:postcode":"77025",
    "sg:province":"TX",
    "sg:tags":[
        "marketing",
        "full",
        "sales"
    ],
    "wof:name":"Carest Associates",
    "wof:placetype":"venue"
},
  "geometry": {"coordinates":[-95.43723799999999,29.696925],"type":"Point"}
}