{
  "type": "Feature",
  "properties": {
    "iso:country":"US",
    "sg:address":"1000 S New Rd Ste 180",
    "sg:city":"Waco",
    "sg:classifiers":[
        {
            "category":"Insurance",
            "subcategory":"Hazard Insurance",
            "type":"Services"
        }
    ],
    "sg:phone":"+1 254 752 2022",
    "sg:postcode":"76711",
    "sg:province":"TX",
    "sg:website":"http://statefarm.mqgroup.com/url.asp?usr=437882",
    "wof:name":"State Farm Insurance Agent-Travis Clark",
    "wof:placetype":"venue"
},
  "geometry": {"coordinates":[-97.163223,31.51478],"type":"Point"}
}