{
  "type": "Feature",
  "properties": {
    "iso:country":"US",
    "sg:address":"6325 Bandera Rd",
    "sg:city":"San Antonio",
    "sg:classifiers":[
        {
            "category":"Autos & Motor Vehicles",
            "subcategory":"Fuel & Gas Station",
            "type":"Retail Goods"
        }
    ],
    "sg:phone":"+1 210 521 6266",
    "sg:postcode":"78238",
    "sg:province":"TX",
    "sg:tags":[
        "oil"
    ],
    "wof:name":"Sunny Chevron",
    "wof:placetype":"venue"
},
  "geometry": {"coordinates":[-98.610438,29.489461],"type":"Point"}
}