{
  "type": "Feature",
  "properties": {
    "iso:country":"US",
    "sg:address":"406 S 12th St",
    "sg:city":"Mcallen",
    "sg:classifiers":[
        {
            "category":"Government",
            "subcategory":"Post Office",
            "type":"Public Place"
        }
    ],
    "sg:phone":"+1 956 971 1716",
    "sg:postcode":"78501",
    "sg:province":"TX",
    "wof:name":"US Post Office",
    "wof:placetype":"venue"
},
  "geometry": {"coordinates":[-98.23306700000001,26.199299],"type":"Point"}
}