{
  "type": "Feature",
  "properties": {
    "iso:country":"US",
    "sg:address":"3404 Wiley Post Rd",
    "sg:city":"Carrollton",
    "sg:classifiers":[
        {
            "category":"Professional",
            "subcategory":"Business Services",
            "type":"Services"
        }
    ],
    "sg:phone":"+1 972 788 8000",
    "sg:postcode":"75006",
    "sg:province":"TX",
    "sg:tags":[
        "interior",
        "consultant",
        "design",
        "decorator"
    ],
    "wof:name":"Spaces Interiors Inc",
    "wof:placetype":"venue"
},
  "geometry": {"coordinates":[-96.83902399999999,32.96022],"type":"Point"}
}