{
  "type": "Feature",
  "properties": {
    "iso:country":"US",
    "sg:address":"30111 W Geneva Dr",
    "sg:city":"Spring",
    "sg:classifiers":[
        {
            "category":"Manufacturing",
            "subcategory":"Tools & Machinery",
            "type":"Manufacturing & Wholesale Goods"
        }
    ],
    "sg:phone":"+1 281 367 2066",
    "sg:postcode":"77386",
    "sg:province":"TX",
    "sg:tags":[
        "industrial",
        "business",
        "mfg"
    ],
    "wof:name":"Rite Tool Inc",
    "wof:placetype":"venue"
},
  "geometry": {"coordinates":[-95.41892799999999,30.127692],"type":"Point"}
}