{
  "type": "Feature",
  "properties": {
    "iso:country":"US",
    "sg:address":"1020 Lockwood Drive",
    "sg:city":"Houston",
    "sg:classifiers":[
        {
            "category":"Transit Center",
            "subcategory":"Freight",
            "type":"Transportation"
        }
    ],
    "sg:phone":"+1 713 860 0343",
    "sg:postcode":"77020",
    "sg:province":"TX",
    "sg:tags":[
        "trucking-motor"
    ],
    "sg:website":"http://www.pioneerfrt.com",
    "wof:name":"Pioneer Freight",
    "wof:placetype":"venue"
},
  "geometry": {"coordinates":[-95.315437,29.764727],"type":"Point"}
}