{
  "type": "Feature",
  "properties": {
    "iso:country":"US",
    "sg:address":"5929 Northwest Dr",
    "sg:city":"Mesquite",
    "sg:classifiers":[
        {
            "category":"Education",
            "subcategory":"Preschool",
            "type":"Public Place"
        },
        {
            "category":"Education",
            "subcategory":"School",
            "type":"Public Place"
        }
    ],
    "sg:phone":"+1 972 270 2660",
    "sg:postcode":"75150",
    "sg:province":"TX",
    "sg:tags":[
        "elementary"
    ],
    "wof:name":"Cornerstone Learning Center",
    "wof:placetype":"venue"
},
  "geometry": {"coordinates":[-96.623561,32.840392],"type":"Point"}
}