{
  "type": "Feature",
  "properties": {
    "iso:country":"US",
    "sg:address":"4925 Everhart Rd",
    "sg:city":"Corpus Christi",
    "sg:classifiers":[
        {
            "category":"Building & Trades",
            "subcategory":"Construction",
            "type":"Services"
        }
    ],
    "sg:phone":"+1 361 334 1057",
    "sg:postcode":"78411",
    "sg:province":"TX",
    "sg:tags":[
        "home",
        "builder"
    ],
    "wof:name":"Angela's Home Impressions",
    "wof:placetype":"venue"
},
  "geometry": {"coordinates":[-97.383073,27.716778],"type":"Point"}
}