{
  "type": "Feature",
  "properties": {
    "iso:country":"US",
    "sg:address":"1900 Alcock St",
    "sg:city":"Pampa",
    "sg:classifiers":[
        {
            "category":"Autos & Motor Vehicles",
            "subcategory":"Auto Supplies",
            "type":"Retail Goods"
        }
    ],
    "sg:phone":"+1 806 688 0033",
    "sg:postcode":"79065",
    "sg:province":"TX",
    "wof:name":"Jays Randy New & Used Tires",
    "wof:placetype":"venue"
},
  "geometry": {"coordinates":[-100.984132,35.533159],"type":"Point"}
}