{
  "type": "Feature",
  "properties": {
    "iso:country":"US",
    "sg:address":"2235 Lockhill Selma Rd",
    "sg:city":"San Antonio",
    "sg:classifiers":[
        {
            "category":"Restaurant",
            "type":"Food & Drink"
        }
    ],
    "sg:phone":"+1 210 344 2400",
    "sg:postcode":"78230",
    "sg:province":"TX",
    "sg:tags":[
        "family"
    ],
    "wof:name":"Sarita's Restaurant Inc",
    "wof:placetype":"venue"
},
  "geometry": {"coordinates":[-98.52895700000001,29.541672],"type":"Point"}
}