{
  "type": "Feature",
  "properties": {
    "iso:country":"US",
    "sg:address":"7309 Fulton St",
    "sg:city":"Houston",
    "sg:classifiers":[
        {
            "category":"Bars & Pubs",
            "type":"Food & Drink"
        }
    ],
    "sg:phone":"+1 713 699 0131",
    "sg:postcode":"77022",
    "sg:province":"TX",
    "sg:tags":[
        "club",
        "night"
    ],
    "wof:name":"Ice Cream Castle",
    "wof:placetype":"venue"
},
  "geometry": {"coordinates":[-95.37627999999999,29.82816],"type":"Point"}
}