{
  "type": "Feature",
  "properties": {
    "iso:country":"US",
    "sg:address":"915 N Jefferson Ave",
    "sg:city":"Mount Pleasant",
    "sg:classifiers":[
        {
            "category":"Professional",
            "subcategory":"Accounting & Tax Preparation",
            "type":"Services"
        }
    ],
    "sg:phone":"+1 903 572 6606",
    "sg:postcode":"75455",
    "sg:province":"TX",
    "wof:name":"Arnold Bob J",
    "wof:placetype":"venue"
},
  "geometry": {"coordinates":[-94.96903500000001,33.163633],"type":"Point"}
}