{
  "type": "Feature",
  "properties": {
    "iso:country":"US",
    "sg:address":"7516 Scenic Dr",
    "sg:city":"Lone Oak",
    "sg:classifiers":[
        {
            "category":"Manufacturing",
            "subcategory":"Tools & Machinery",
            "type":"Manufacturing & Wholesale Goods"
        }
    ],
    "sg:phone":"+1 903 447 3619",
    "sg:postcode":"75453",
    "sg:province":"TX",
    "sg:tags":[
        "electrical",
        "mfg"
    ],
    "wof:name":"Personal Protection Plus",
    "wof:placetype":"venue"
},
  "geometry": {"coordinates":[-95.97801,32.943014],"type":"Point"}
}