{
  "type": "Feature",
  "properties": {
    "iso:country":"US",
    "sg:address":"24110 Cougar St",
    "sg:city":"Magnolia",
    "sg:classifiers":[
        {
            "category":"Building & Trades",
            "subcategory":"Construction",
            "type":"Services"
        }
    ],
    "sg:phone":"+1 281 356 7746",
    "sg:postcode":"77355",
    "sg:province":"TX",
    "sg:tags":[
        "house"
    ],
    "wof:name":"Russell Strokes Builders",
    "wof:placetype":"venue"
},
  "geometry": {"coordinates":[-95.69595099999999,30.112548],"type":"Point"}
}