{
  "type": "Feature",
  "properties": {
    "iso:country":"US",
    "sg:address":"10100 Sharon Dr",
    "sg:city":"Amarillo",
    "sg:classifiers":[
        {
            "category":"Home & Garden",
            "subcategory":"Garden Supply",
            "type":"Retail Goods"
        },
        {
            "category":"Building & Trades",
            "subcategory":"Landscaping Services",
            "type":"Services"
        }
    ],
    "sg:phone":"+1 806 622 1202",
    "sg:postcode":"79118",
    "sg:province":"TX",
    "sg:tags":[
        "sprinkler"
    ],
    "wof:name":"Milburn Landsscape & Sprinkler",
    "wof:placetype":"venue"
},
  "geometry": {"coordinates":[-101.876456,35.104531],"type":"Point"}
}