{
  "type": "Feature",
  "properties": {
    "iso:country":"US",
    "sg:address":"9706 Logans Ridge Dr",
    "sg:city":"Converse",
    "sg:classifiers":[
        {
            "category":"Professional",
            "subcategory":"Management & Consulting",
            "type":"Services"
        }
    ],
    "sg:phone":"+1 210 655 4091",
    "sg:postcode":"78109",
    "sg:province":"TX",
    "sg:tags":[
        "communications",
        "consultant"
    ],
    "wof:name":"Go Tell Communications",
    "wof:placetype":"venue"
},
  "geometry": {"coordinates":[-98.34864,29.528913],"type":"Point"}
}