{
  "type": "Feature",
  "properties": {
    "iso:country":"US",
    "sg:address":"9837 Martha Rd",
    "sg:city":"San Angelo",
    "sg:phone":"+1 325 658 6966",
    "sg:postcode":"76901",
    "sg:province":"TX",
    "sg:tags":[
        "fuel",
        "product",
        "oil",
        "petroleum",
        "dealer"
    ],
    "wof:name":"Keith Covey Enterprises",
    "wof:placetype":"venue"
},
  "geometry": {"coordinates":[-100.549533,31.581872],"type":"Point"}
}