{
  "type": "Feature",
  "properties": {
    "iso:country":"US",
    "sg:address":"2031 Rufe Snow Dr",
    "sg:city":"Keller",
    "sg:classifiers":[
        {
            "category":"Banks & Credit Unions",
            "subcategory":"Bank",
            "type":"Services"
        }
    ],
    "sg:phone":"+1 817 514 5550",
    "sg:postcode":"76248",
    "sg:province":"TX",
    "wof:name":"Compass Bank",
    "wof:placetype":"venue"
},
  "geometry": {"coordinates":[-97.23853800000001,32.89795],"type":"Point"}
}