{
  "type": "Feature",
  "properties": {
    "iso:country":"US",
    "sg:address":"8550 Fair Oaks Xing",
    "sg:city":"Dallas",
    "sg:classifiers":[
        {
            "category":"Banks & Credit Unions",
            "subcategory":"Financial Services",
            "type":"Services"
        }
    ],
    "sg:phone":"+1 214 341 5722",
    "sg:postcode":"75243",
    "sg:province":"TX",
    "sg:tags":[
        "investor"
    ],
    "wof:name":"United Trans Capital LLC",
    "wof:placetype":"venue"
},
  "geometry": {"coordinates":[-96.728268,32.895573],"type":"Point"}
}