{
  "type": "Feature",
  "properties": {
    "iso:country":"US",
    "sg:address":"21800 I- 45",
    "sg:city":"Spring",
    "sg:classifiers":[
        {
            "category":"Mining & Drilling",
            "type":"Manufacturing & Wholesale Goods"
        }
    ],
    "sg:phone":"+1 281 414 8172",
    "sg:postcode":"77373",
    "sg:province":"TX",
    "sg:tags":[
        "gas",
        "oil",
        "exploration"
    ],
    "wof:name":"Nehi Petroleum",
    "wof:placetype":"venue"
},
  "geometry": {"coordinates":[-95.43561699999999,30.099192],"type":"Point"}
}