{
  "type": "Feature",
  "properties": {
    "iso:country":"US",
    "sg:address":"2606 E 5th St",
    "sg:city":"Tyler",
    "sg:classifiers":[
        {
            "category":"Wholesale",
            "subcategory":"Hardware",
            "type":"Manufacturing & Wholesale Goods"
        },
        {
            "category":"Wholesale",
            "subcategory":"Home Furnishings",
            "type":"Manufacturing & Wholesale Goods"
        }
    ],
    "sg:phone":"+1 903 592 5836",
    "sg:postcode":"75701",
    "sg:province":"TX",
    "sg:tags":[
        "air",
        "parts",
        "conditioning",
        "supply"
    ],
    "wof:name":"U Fix It Appliance Parts",
    "wof:placetype":"venue"
},
  "geometry": {"coordinates":[-95.267262,32.33243],"type":"Point"}
}