{
  "type": "Feature",
  "properties": {
    "iso:country":"US",
    "sg:address":"2105 W Northwest Hwy",
    "sg:city":"Grapevine",
    "sg:classifiers":[
        {
            "category":"Shopping",
            "subcategory":"Pharmacy",
            "type":"Retail Goods"
        }
    ],
    "sg:phone":"+1 817 416 2501",
    "sg:postcode":"76051",
    "sg:province":"TX",
    "sg:website":"http://www.cvs.com",
    "wof:name":"CVS/pharmacy",
    "wof:placetype":"venue"
},
  "geometry": {"coordinates":[-97.099355,32.94109],"type":"Point"}
}