{
  "type": "Feature",
  "properties": {
    "iso:country":"US",
    "sg:address":"985 19th St",
    "sg:city":"Beaumont",
    "sg:classifiers":[
        {
            "category":"Food & Beverages",
            "subcategory":"Specialty",
            "type":"Retail Goods"
        }
    ],
    "sg:phone":"+1 409 892 1290",
    "sg:postcode":"77706",
    "sg:province":"TX",
    "wof:name":"Nutrition By Design",
    "wof:placetype":"venue"
},
  "geometry": {"coordinates":[-94.13907500000001,30.092644],"type":"Point"}
}