{
  "type": "Feature",
  "properties": {
    "iso:country":"US",
    "sg:address":"9550 N Loop Fwy",
    "sg:city":"Houston",
    "sg:classifiers":[
        {
            "category":"Autos & Motor Vehicles",
            "subcategory":"Automobile Sales",
            "type":"Retail Goods"
        },
        {
            "category":"Retail",
            "subcategory":"Auto Repair",
            "type":"Services"
        },
        {
            "category":"Wholesale",
            "subcategory":"Auto Parts",
            "type":"Manufacturing & Wholesale Goods"
        }
    ],
    "sg:phone":"+1 713 672 8668",
    "sg:postcode":"77029",
    "sg:province":"TX",
    "sg:tags":[
        "equipment",
        "truck"
    ],
    "wof:name":"Houston Freightliner Inc Parts",
    "wof:placetype":"venue"
},
  "geometry": {"coordinates":[-95.26712000000001,29.78894],"type":"Point"}
}