{
  "type": "Feature",
  "properties": {
    "iso:country":"US",
    "sg:address":"912 Wedgewood Way",
    "sg:city":"Richardson",
    "sg:classifiers":[
        {
            "category":"Shopping",
            "type":"Retail Goods"
        }
    ],
    "sg:phone":"+1 972 235 3796",
    "sg:postcode":"75080",
    "sg:province":"TX",
    "sg:tags":[
        "miscellaneous",
        "store"
    ],
    "wof:name":"Arciart Inc",
    "wof:placetype":"venue"
},
  "geometry": {"coordinates":[-96.755385,32.963044],"type":"Point"}
}