{
  "type": "Feature",
  "properties": {
    "iso:country":"US",
    "sg:address":"8501 Mosley Rd",
    "sg:city":"Houston",
    "sg:classifiers":[
        {
            "category":"Wholesale",
            "subcategory":"Machinery & Supplies",
            "type":"Manufacturing & Wholesale Goods"
        }
    ],
    "sg:phone":"+1 281 998 2288",
    "sg:postcode":"77075",
    "sg:province":"TX",
    "sg:tags":[
        "equipment",
        "safety",
        "clothing"
    ],
    "wof:name":"Bay Area Safety & Supply",
    "wof:placetype":"venue"
},
  "geometry": {"coordinates":[-95.25353800000001,29.646004],"type":"Point"}
}