{
  "type": "Feature",
  "properties": {
    "iso:country":"US",
    "sg:address":"2725 Marigold Ave",
    "sg:city":"Fort Worth",
    "sg:classifiers":[
        {
            "category":"Professional",
            "type":"Services"
        }
    ],
    "sg:phone":"+1 817 222 2924",
    "sg:postcode":"76111",
    "sg:province":"TX",
    "wof:name":"Davis Backflow Services",
    "wof:placetype":"venue"
},
  "geometry": {"coordinates":[-97.307196,32.78287],"type":"Point"}
}