{
  "type": "Feature",
  "properties": {
    "iso:country":"US",
    "sg:address":"223 N C M Allen Pkwy",
    "sg:city":"San Marcos",
    "sg:classifiers":[
        {
            "category":"Personal",
            "subcategory":"Beauty Salon",
            "type":"Services"
        }
    ],
    "sg:phone":"+1 512 392 6074",
    "sg:postcode":"78666",
    "sg:province":"TX",
    "wof:name":"Haircuts Etc",
    "wof:placetype":"venue"
},
  "geometry": {"coordinates":[-97.937488,29.884496],"type":"Point"}
}