{
  "type": "Feature",
  "properties": {
    "iso:country":"US",
    "sg:address":"1112 Smith Dr",
    "sg:city":"Alvin",
    "sg:classifiers":[
        {
            "category":"Health Services",
            "subcategory":"Nursing And Care Facility",
            "type":"Services"
        }
    ],
    "sg:phone":"+1 281 331 6125",
    "sg:postcode":"77511",
    "sg:province":"TX",
    "sg:tags":[
        "skilled"
    ],
    "wof:name":"Winchester Lodge",
    "wof:placetype":"venue"
},
  "geometry": {"coordinates":[-95.242339,29.434128],"type":"Point"}
}