{
  "type": "Feature",
  "properties": {
    "iso:country":"US",
    "sg:address":"208 S Ector Dr",
    "sg:city":"Euless",
    "sg:classifiers":[
        {
            "category":"Professional",
            "subcategory":"Research",
            "type":"Services"
        }
    ],
    "sg:phone":"+1 817 318 1900",
    "sg:postcode":"76040",
    "sg:province":"TX",
    "sg:tags":[
        "environmental",
        "ecological"
    ],
    "wof:name":"Accurate Environmental Svc",
    "wof:placetype":"venue"
},
  "geometry": {"coordinates":[-97.090777,32.835869],"type":"Point"}
}