{
  "type": "Feature",
  "properties": {
    "iso:country":"US",
    "sg:address":"11715 Gallant Ridge Ln",
    "sg:city":"Houston",
    "sg:classifiers":[
        {
            "category":"Professional",
            "subcategory":"Computer Services",
            "type":"Services"
        }
    ],
    "sg:phone":"+1 281 759 3338",
    "sg:postcode":"77082",
    "sg:province":"TX",
    "sg:tags":[
        "datum"
    ],
    "wof:name":"Brunner Medical",
    "wof:placetype":"venue"
},
  "geometry": {"coordinates":[-95.58421800000001,29.725375],"type":"Point"}
}