{
  "type": "Feature",
  "properties": {
    "iso:country":"US",
    "sg:address":"2995 Merrell Rd",
    "sg:city":"Dallas",
    "sg:classifiers":[
        {
            "category":"Shopping",
            "subcategory":"Clothing, Apparel, & Fashions",
            "type":"Retail Goods"
        }
    ],
    "sg:phone":"+1 214 904 0426",
    "sg:postcode":"75229",
    "sg:province":"TX",
    "sg:tags":[
        "tailor"
    ],
    "wof:name":"Melba's Tailor Made Apparel",
    "wof:placetype":"venue"
},
  "geometry": {"coordinates":[-96.87740700000001,32.88788],"type":"Point"}
}