{
  "type": "Feature",
  "properties": {
    "iso:country":"US",
    "sg:address":"3144 S Grove St",
    "sg:city":"Fort Worth",
    "sg:classifiers":[
        {
            "category":"Retail",
            "subcategory":"Auto Repair",
            "type":"Services"
        }
    ],
    "sg:phone":"+1 817 923 1402",
    "sg:postcode":"76110",
    "sg:province":"TX",
    "sg:tags":[
        "repairing",
        "automobile"
    ],
    "wof:name":"BBC Automotive",
    "wof:placetype":"venue"
},
  "geometry": {"coordinates":[-97.322307,32.7053],"type":"Point"}
}