{
  "type": "Feature",
  "properties": {
    "iso:country":"US",
    "sg:address":"3914 Upper Passage Ln",
    "sg:city":"Round Rock",
    "sg:classifiers":[
        {
            "category":"Building & Trades",
            "subcategory":"Construction",
            "type":"Services"
        }
    ],
    "sg:phone":"+1 512 388 1767",
    "sg:postcode":"78681",
    "sg:province":"TX",
    "sg:tags":[
        "house"
    ],
    "wof:name":"Park At Stone Oak",
    "wof:placetype":"venue"
},
  "geometry": {"coordinates":[-97.736074,30.557297],"type":"Point"}
}