{
  "type": "Feature",
  "properties": {
    "iso:country":"US",
    "sg:address":"25980 FM 2090",
    "sg:city":"Splendora",
    "sg:classifiers":[
        {
            "category":"Organizations",
            "subcategory":"Religious Organization",
            "type":"Services"
        }
    ],
    "sg:phone":"+1 281 689 3727",
    "sg:postcode":"77372",
    "sg:province":"TX",
    "sg:tags":[
        "church"
    ],
    "sg:website":"www.fbcsplendora.org",
    "wof:name":"First Baptist Church-Splendora",
    "wof:placetype":"venue"
},
  "geometry": {"coordinates":[-95.159676,30.233013],"type":"Point"}
}