{
  "type": "Feature",
  "properties": {
    "iso:country":"US",
    "sg:address":"7800 Fannin St Ste 201",
    "sg:city":"Houston",
    "sg:classifiers":[
        {
            "category":"Health Services",
            "subcategory":"Doctor",
            "type":"Services"
        }
    ],
    "sg:phone":"+1 713 795 4884",
    "sg:postcode":"77054",
    "sg:province":"TX",
    "sg:tags":[
        "practice",
        "family"
    ],
    "wof:name":"Medical Center Family Practice Association",
    "wof:placetype":"venue"
},
  "geometry": {"coordinates":[-95.403198,29.691099],"type":"Point"}
}