{
  "type": "Feature",
  "properties": {
    "iso:country":"US",
    "sg:address":"1116 Mason St",
    "sg:city":"Hurst",
    "sg:classifiers":[
        {
            "category":"Building & Trades",
            "subcategory":"Construction",
            "type":"Services"
        }
    ],
    "sg:phone":"+1 817 268 6511",
    "sg:postcode":"76053",
    "sg:province":"TX",
    "sg:tags":[
        "painting",
        "contractor"
    ],
    "wof:name":"Cox Custom Painting",
    "wof:placetype":"venue"
},
  "geometry": {"coordinates":[-97.170959,32.829782],"type":"Point"}
}