{
  "type": "Feature",
  "properties": {
    "iso:country":"US",
    "sg:address":"910 E State St",
    "sg:city":"Eagle Lake",
    "sg:classifiers":[
        {
            "category":"Wholesale",
            "subcategory":"Chemicals & Plastics",
            "type":"Manufacturing & Wholesale Goods"
        }
    ],
    "sg:phone":"+1 979 234 2695",
    "sg:postcode":"77434",
    "sg:province":"TX",
    "wof:name":"D R Wintermann Warehouse",
    "wof:placetype":"venue"
},
  "geometry": {"coordinates":[-96.32476,29.585516],"type":"Point"}
}