{
  "type": "Feature",
  "properties": {
    "iso:country":"US",
    "sg:address":"217 Mary Ave",
    "sg:city":"Waco",
    "sg:classifiers":[
        {
            "category":"Real Estate",
            "subcategory":"Real Estate Agent",
            "type":"Services"
        }
    ],
    "sg:phone":"+1 254 757 2871",
    "sg:postcode":"76701",
    "sg:province":"TX",
    "sg:tags":[
        "commercial"
    ],
    "wof:name":"River Square Center",
    "wof:placetype":"venue"
},
  "geometry": {"coordinates":[-97.127961,31.556976],"type":"Point"}
}