{
  "type": "Feature",
  "properties": {
    "iso:country":"US",
    "sg:address":"817 W Pioneer Pkwy",
    "sg:city":"Grand Prairie",
    "sg:classifiers":[
        {
            "category":"Organizations",
            "subcategory":"Religious Organization",
            "type":"Services"
        }
    ],
    "sg:phone":"+1 972 602 8959",
    "sg:postcode":"75051",
    "sg:province":"TX",
    "sg:tags":[
        "church"
    ],
    "wof:name":"RCCG House On The Rock",
    "wof:placetype":"venue"
},
  "geometry": {"coordinates":[-97.01702400000001,32.709596],"type":"Point"}
}