{
  "type": "Feature",
  "properties": {
    "iso:country":"US",
    "sg:address":"1015 N Edgefield Ave",
    "sg:city":"Dallas",
    "sg:classifiers":[
        {
            "category":"Government",
            "subcategory":"Office",
            "type":"Public Place"
        }
    ],
    "sg:phone":"+1 214 946 3602",
    "sg:postcode":"75208",
    "sg:province":"TX",
    "sg:tags":[
        "housing",
        "program",
        "stone"
    ],
    "wof:name":"Tipi American Indian House",
    "wof:placetype":"venue"
},
  "geometry": {"coordinates":[-96.842787,32.75703],"type":"Point"}
}