{
  "type": "Feature",
  "properties": {
    "iso:country":"US",
    "sg:address":"3606 Durness Way",
    "sg:city":"Houston",
    "sg:classifiers":[
        {
            "category":"Health Services",
            "subcategory":"Doctor",
            "type":"Services"
        }
    ],
    "sg:phone":"+1 281 980 0412",
    "sg:postcode":"77025",
    "sg:province":"TX",
    "wof:name":"John A Suchina",
    "wof:placetype":"venue"
},
  "geometry": {"coordinates":[-95.433393,29.694755],"type":"Point"}
}