{
  "type": "Feature",
  "properties": {
    "iso:country":"US",
    "sg:address":"2301 Roberts Cir",
    "sg:city":"Arlington",
    "sg:classifiers":[
        {
            "category":"Professional",
            "subcategory":"Printing & Photocopies",
            "type":"Services"
        }
    ],
    "sg:phone":"+1 817 504 2874",
    "sg:postcode":"76010",
    "sg:province":"TX",
    "sg:tags":[
        "duplicating",
        "copying"
    ],
    "wof:name":"Dfw Copiers",
    "wof:placetype":"venue"
},
  "geometry": {"coordinates":[-97.06817599999999,32.73214],"type":"Point"}
}