{
  "type": "Feature",
  "properties": {
    "iso:country":"US",
    "sg:address":"2921 Meandering Way",
    "sg:city":"Granbury",
    "sg:classifiers":[
        {
            "category":"Professional",
            "subcategory":"Business Services",
            "type":"Services"
        }
    ],
    "sg:phone":"+1 817 243 5655",
    "sg:postcode":"76049",
    "sg:province":"TX",
    "sg:tags":[
        "lobbyist"
    ],
    "wof:name":"Shelton Political Consultants",
    "wof:placetype":"venue"
},
  "geometry": {"coordinates":[-97.746094,32.466561],"type":"Point"}
}