{
  "type": "Feature",
  "properties": {
    "iso:country":"US",
    "sg:address":"2822 N Beach St",
    "sg:city":"Haltom City",
    "sg:classifiers":[
        {
            "category":"Professional",
            "type":"Services"
        }
    ],
    "sg:phone":"+1 817 834 3411",
    "sg:postcode":"76111",
    "sg:province":"TX",
    "sg:tags":[
        "establishment"
    ],
    "wof:name":"Bill Hames Show Inc",
    "wof:placetype":"venue"
},
  "geometry": {"coordinates":[-97.29048400000001,32.798945],"type":"Point"}
}