{
  "type": "Feature",
  "properties": {
    "iso:country":"US",
    "sg:address":"4630 W Fuqua St",
    "sg:city":"Houston",
    "sg:classifiers":[
        {
            "category":"Retail",
            "subcategory":"Auto Repair",
            "type":"Services"
        }
    ],
    "sg:phone":"+1 713 413 9737",
    "sg:postcode":"77045",
    "sg:province":"TX",
    "sg:tags":[
        "repairing",
        "automobile"
    ],
    "wof:name":"Gonzalez Auto Care",
    "wof:placetype":"venue"
},
  "geometry": {"coordinates":[-95.448196,29.613501],"type":"Point"}
}