{
  "type": "Feature",
  "properties": {
    "iso:country":"US",
    "sg:address":"16321 Loch Katrine Ln",
    "sg:city":"Houston",
    "sg:classifiers":[
        {
            "category":"Autos & Motor Vehicles",
            "subcategory":"Auto Supplies",
            "type":"Retail Goods"
        },
        {
            "category":"Retail",
            "subcategory":"Auto Repair",
            "type":"Services"
        }
    ],
    "sg:phone":"+1 281 463 9009",
    "sg:postcode":"77084",
    "sg:province":"TX",
    "sg:tags":[
        "transmission",
        "automobile",
        "equipment-service",
        "air conditioning"
    ],
    "sg:website":"http://www.a1transmissionspecialists.com",
    "wof:name":"A1 Transmission Specialists",
    "wof:placetype":"venue"
},
  "geometry": {"coordinates":[-95.64854800000001,29.845942],"type":"Point"}
}