{
  "type": "Feature",
  "properties": {
    "iso:country":"US",
    "sg:address":"928 Chimney Rock Rd",
    "sg:city":"Houston",
    "sg:classifiers":[
        {
            "category":"Real Estate",
            "subcategory":"Real Estate Agent",
            "type":"Services"
        }
    ],
    "sg:phone":"+1 713 781 5497",
    "sg:postcode":"77056",
    "sg:province":"TX",
    "wof:name":"Meredith Cox Realtors",
    "wof:placetype":"venue"
},
  "geometry": {"coordinates":[-95.477429,29.756995],"type":"Point"}
}