{
  "type": "Feature",
  "properties": {
    "iso:country":"US",
    "sg:address":"7011 Barker Cypress Rd",
    "sg:city":"Cypress",
    "sg:classifiers":[
        {
            "category":"Restaurant",
            "type":"Food & Drink"
        }
    ],
    "sg:menulink":"http://www.allmenus.com/tx/northwest-harris/217854-burger-king/menu/",
    "sg:phone":"+1 281 859 4005",
    "sg:postcode":"77433",
    "sg:province":"TX",
    "sg:tags":[
        "american"
    ],
    "wof:name":"Burger King",
    "wof:placetype":"venue"
},
  "geometry": {"coordinates":[-95.683922,29.88081],"type":"Point"}
}