{
  "type": "Feature",
  "properties": {
    "iso:country":"US",
    "sg:address":"512 Bryant Rd",
    "sg:city":"Conroe",
    "sg:classifiers":[
        {
            "category":"Professional",
            "type":"Services"
        }
    ],
    "sg:phone":"+1 936 539 5229",
    "sg:postcode":"77303",
    "sg:province":"TX",
    "sg:tags":[
        "establishment"
    ],
    "wof:name":"Trico Enterprises",
    "wof:placetype":"venue"
},
  "geometry": {"coordinates":[-95.46361899999999,30.341976],"type":"Point"}
}