{
  "type": "Feature",
  "properties": {
    "iso:country":"US",
    "sg:address":"2720 N Stemmons Fwy",
    "sg:city":"Dallas",
    "sg:classifiers":[
        {
            "category":"Real Estate",
            "subcategory":"Architect",
            "type":"Services"
        }
    ],
    "sg:phone":"+1 214 634 0234",
    "sg:postcode":"75207",
    "sg:province":"TX",
    "wof:name":"Plan Arc Inc",
    "wof:placetype":"venue"
},
  "geometry": {"coordinates":[-96.84392699999999,32.808812],"type":"Point"}
}