{
  "type": "Feature",
  "properties": {
    "iso:country":"US",
    "sg:address":"1001 E Adoue St",
    "sg:city":"Alvin",
    "sg:classifiers":[
        {
            "category":"Organizations",
            "subcategory":"Religious Organization",
            "type":"Services"
        }
    ],
    "sg:phone":"+1 281 824 8046",
    "sg:postcode":"77511",
    "sg:province":"TX",
    "wof:name":"J Gilligan Ministries",
    "wof:placetype":"venue"
},
  "geometry": {"coordinates":[-95.235258,29.420993],"type":"Point"}
}