{
  "type": "Feature",
  "properties": {
    "iso:country":"US",
    "sg:address":"1904 Blackfoot Trl",
    "sg:city":"Mesquite",
    "sg:classifiers":[
        {
            "category":"Banks & Credit Unions",
            "subcategory":"Bank",
            "type":"Services"
        }
    ],
    "sg:phone":"+1 972 222 5167",
    "sg:postcode":"75149",
    "sg:province":"TX",
    "sg:tags":[
        "mortgage"
    ],
    "wof:name":"Kelly  Kathy Theloanstar",
    "wof:placetype":"venue"
},
  "geometry": {"coordinates":[-96.570049,32.752253],"type":"Point"}
}