{
  "type": "Feature",
  "properties": {
    "iso:country":"US",
    "sg:address":"7070 W 43rd St Ste 114",
    "sg:city":"Houston",
    "sg:classifiers":[
        {
            "category":"Building & Trades",
            "subcategory":"Pest Control",
            "type":"Services"
        }
    ],
    "sg:phone":"+1 888 298 1524",
    "sg:postcode":"77092",
    "sg:province":"TX",
    "sg:website":"bowenexterminators.net?n=t&ubl=true",
    "wof:name":"Bowen Exterminators Inc.",
    "wof:placetype":"venue"
},
  "geometry": {"coordinates":[-95.49808,29.835685],"type":"Point"}
}