{
  "type": "Feature",
  "properties": {
    "iso:country":"US",
    "sg:address":"1615 Buckwheat",
    "sg:city":"Tow",
    "sg:classifiers":[
        {
            "category":"Retail",
            "subcategory":"Auto Repair",
            "type":"Services"
        }
    ],
    "sg:phone":"+1 325 379 1237",
    "sg:postcode":"78672",
    "sg:province":"TX",
    "sg:tags":[
        "automotive"
    ],
    "wof:name":"Tow Valley Nursery",
    "wof:placetype":"venue"
},
  "geometry": {"coordinates":[-98.44357100000001,30.852585],"type":"Point"}
}