{
  "type": "Feature",
  "properties": {
    "iso:country":"US",
    "sg:address":"2310 Chalk Hill Rd",
    "sg:city":"Dallas",
    "sg:classifiers":[
        {
            "category":"Wholesale",
            "subcategory":"Construction Materials",
            "type":"Manufacturing & Wholesale Goods"
        }
    ],
    "sg:phone":"+1 214 630 8936",
    "sg:postcode":"75212",
    "sg:province":"TX",
    "sg:tags":[
        "stucco"
    ],
    "wof:name":"Synthetic Textures Inc",
    "wof:placetype":"venue"
},
  "geometry": {"coordinates":[-96.90336499999999,32.771345],"type":"Point"}
}