{
  "type": "Feature",
  "properties": {
    "iso:country":"US",
    "sg:address":"1009 Laguna Vista Ct",
    "sg:city":"Granbury",
    "sg:classifiers":[
        {
            "category":"Shopping",
            "subcategory":"Used Merchandise",
            "type":"Retail Goods"
        }
    ],
    "sg:phone":"+1 817 279 6609",
    "sg:postcode":"76048",
    "sg:province":"TX",
    "wof:name":"Paula Schirman",
    "wof:placetype":"venue"
},
  "geometry": {"coordinates":[-97.793137,32.417663],"type":"Point"}
}