{
  "type": "Feature",
  "properties": {
    "iso:country":"US",
    "sg:address":"4821 Alicia Dr",
    "sg:city":"Fort Worth",
    "sg:classifiers":[
        {
            "category":"Organizations",
            "subcategory":"Religious Organization",
            "type":"Services"
        }
    ],
    "sg:phone":"+1 817 346 0070",
    "sg:postcode":"76133",
    "sg:province":"TX",
    "sg:tags":[
        "church"
    ],
    "wof:name":"Believers Tabernacle Church",
    "wof:placetype":"venue"
},
  "geometry": {"coordinates":[-97.395729,32.629632],"type":"Point"}
}