{
  "type": "Feature",
  "properties": {
    "iso:country":"US",
    "sg:address":"6211 W Northwest Hwy",
    "sg:city":"Dallas",
    "sg:classifiers":[
        {
            "category":"Health Services",
            "subcategory":"Doctor",
            "type":"Services"
        }
    ],
    "sg:phone":"+1 214 739 5080",
    "sg:postcode":"75225",
    "sg:province":"TX",
    "wof:name":"Miranda Francis & Ann MD",
    "wof:placetype":"venue"
},
  "geometry": {"coordinates":[-96.80041900000001,32.865882],"type":"Point"}
}