{
  "type": "Feature",
  "properties": {
    "iso:country":"US",
    "sg:address":"695 Woodrow St",
    "sg:city":"Silsbee",
    "sg:classifiers":[
        {
            "category":"Education",
            "subcategory":"School",
            "type":"Public Place"
        }
    ],
    "sg:phone":"+1 409 385 6472",
    "sg:postcode":"77656",
    "sg:province":"TX",
    "sg:website":"www.silsbeeisd.com",
    "wof:name":"Laura Reeves Elementary School",
    "wof:placetype":"venue"
},
  "geometry": {"coordinates":[-94.186753,30.346229],"type":"Point"}
}