{
  "type": "Feature",
  "properties": {
    "iso:country":"US",
    "sg:address":"310 E Wallisville Rd",
    "sg:city":"Highlands",
    "sg:classifiers":[
        {
            "category":"Retail",
            "subcategory":"Auto Repair",
            "type":"Services"
        }
    ],
    "sg:phone":"+1 281 426 3012",
    "sg:postcode":"77562",
    "sg:province":"TX",
    "sg:tags":[
        "repairing",
        "automobile"
    ],
    "wof:name":"Joe Hausberger's Auto Svc",
    "wof:placetype":"venue"
},
  "geometry": {"coordinates":[-95.053766,29.818983],"type":"Point"}
}