{
  "type": "Feature",
  "properties": {
    "iso:country":"US",
    "sg:address":"4444 W Illinois Ave",
    "sg:city":"Dallas",
    "sg:classifiers":[
        {
            "category":"Shopping",
            "type":"Retail Goods"
        }
    ],
    "sg:phone":"+1 214 339 4704",
    "sg:postcode":"75211",
    "sg:province":"TX",
    "sg:tags":[
        "cosmetic",
        "perfume"
    ],
    "wof:name":"Best 4-You",
    "wof:placetype":"venue"
},
  "geometry": {"coordinates":[-96.893309,32.720243],"type":"Point"}
}