{
  "type": "Feature",
  "properties": {
    "iso:country":"US",
    "sg:address":"1237 Blalock Rd",
    "sg:city":"Houston",
    "sg:classifiers":[
        {
            "category":"Autos & Motor Vehicles",
            "subcategory":"Fuel & Gas Station",
            "type":"Retail Goods"
        },
        {
            "category":"Manufacturing",
            "subcategory":"Petroleum Products",
            "type":"Manufacturing & Wholesale Goods"
        },
        {
            "category":"Utilities",
            "subcategory":"Fuel Oil & Lpg",
            "type":"Services"
        }
    ],
    "sg:phone":"+1 713 463 5959",
    "sg:postcode":"77055",
    "sg:province":"TX",
    "sg:tags":[
        "oils-fuel",
        "oils-petroleum"
    ],
    "wof:name":"Noxxe Oil And Gas",
    "wof:placetype":"venue"
},
  "geometry": {"coordinates":[-95.52185799999999,29.791637],"type":"Point"}
}