{
  "type": "Feature",
  "properties": {
    "iso:country":"US",
    "sg:address":"901 S Mo-Pac Expy",
    "sg:city":"Austin",
    "sg:classifiers":[
        {
            "category":"Organizations",
            "subcategory":"Non-profit Organization",
            "type":"Services"
        }
    ],
    "sg:phone":"+1 512 477 3221",
    "sg:postcode":"78746",
    "sg:province":"TX",
    "sg:tags":[
        "fund",
        "raising"
    ],
    "wof:name":"March Dmes Brth Dfcts Fndation",
    "wof:placetype":"venue"
},
  "geometry": {"coordinates":[-97.783118,30.26624],"type":"Point"}
}