{
  "type": "Feature",
  "properties": {
    "iso:country":"US",
    "sg:address":"2009 Post Office St",
    "sg:city":"Galveston",
    "sg:classifiers":[
        {
            "category":"Personal",
            "type":"Services"
        },
        {
            "category":"Sports & Exercise",
            "subcategory":"Gym",
            "type":"Entertainment"
        },
        {
            "category":"Arena",
            "subcategory":"Sports Club",
            "type":"Entertainment"
        }
    ],
    "sg:phone":"+1 409 621 2878",
    "sg:postcode":"77550",
    "sg:province":"TX",
    "sg:tags":[
        "trainer",
        "image",
        "gymnasium",
        "consultants-personal",
        "program",
        "health",
        "fitness",
        "physical"
    ],
    "sg:website":"http://www.urbanfitnessgalveston.com",
    "wof:name":"Urban Health and Fitness",
    "wof:placetype":"venue"
},
  "geometry": {"coordinates":[-94.790104,29.305416],"type":"Point"}
}