{
  "type": "Feature",
  "properties": {
    "iso:country":"US",
    "sg:address":"1541 John Ben Shepperd Pkwy",
    "sg:city":"Odessa",
    "sg:classifiers":[
        {
            "category":"Health Services",
            "subcategory":"Optometrist",
            "type":"Services"
        }
    ],
    "sg:phone":"+1 432 550 4245",
    "sg:postcode":"79761",
    "sg:province":"TX",
    "wof:name":"Maria G Ceballos OD",
    "wof:placetype":"venue"
},
  "geometry": {"coordinates":[-102.32860100000001,31.876192],"type":"Point"}
}