{
  "type": "Feature",
  "properties": {
    "iso:country":"US",
    "sg:address":"730 Skyline Dr",
    "sg:city":"Hutchins",
    "sg:classifiers":[
        {
            "category":"Manufacturing",
            "subcategory":"Glass & Minerals",
            "type":"Manufacturing & Wholesale Goods"
        }
    ],
    "sg:phone":"+1 972 225 9124",
    "sg:postcode":"75141",
    "sg:province":"TX",
    "sg:tags":[
        "concrete",
        "product",
        "mfg"
    ],
    "wof:name":"D & D Concrete Products",
    "wof:placetype":"venue"
},
  "geometry": {"coordinates":[-96.69933399999999,32.638212],"type":"Point"}
}