{
  "type": "Feature",
  "properties": {
    "iso:country":"US",
    "sg:address":"15118 Jones Maltsberger Rd",
    "sg:city":"San Antonio",
    "sg:classifiers":[
        {
            "category":"Retail",
            "subcategory":"Laundry & Dry Cleaning",
            "type":"Services"
        }
    ],
    "sg:phone":"+1 210 490 5177",
    "sg:postcode":"78247",
    "sg:province":"TX",
    "wof:name":"Acme Alterations and Sewing",
    "wof:placetype":"venue"
},
  "geometry": {"coordinates":[-98.43999599999999,29.580033],"type":"Point"}
}