{
  "type": "Feature",
  "properties": {
    "iso:country":"US",
    "sg:address":"10155 Plano Rd",
    "sg:city":"Dallas",
    "sg:classifiers":[
        {
            "category":"Professional",
            "subcategory":"Testing Lab",
            "type":"Services"
        },
        {
            "category":"Health Services",
            "subcategory":"Medical Lab",
            "type":"Services"
        }
    ],
    "sg:phone":"+1 214 553 2500",
    "sg:postcode":"75238",
    "sg:province":"TX",
    "sg:tags":[
        "laboratory"
    ],
    "wof:name":"Reliable Dental Laboratory",
    "wof:placetype":"venue"
},
  "geometry": {"coordinates":[-96.700535,32.887662],"type":"Point"}
}