{
  "type": "Feature",
  "properties": {
    "iso:country":"US",
    "sg:address":"5151 Belt Line Rd",
    "sg:city":"Dallas",
    "sg:classifiers":[
        {
            "category":"Banks & Credit Unions",
            "subcategory":"Investment Brokerage",
            "type":"Services"
        }
    ],
    "sg:phone":"+1 214 526 2274",
    "sg:postcode":"75254",
    "sg:province":"TX",
    "wof:name":"Scentera Capital",
    "wof:placetype":"venue"
},
  "geometry": {"coordinates":[-96.81884700000001,32.954064],"type":"Point"}
}