{
  "type": "Feature",
  "properties": {
    "iso:country":"US",
    "sg:address":"1011 W Brooklyn Ave",
    "sg:city":"Dallas",
    "sg:classifiers":[
        {
            "category":"Real Estate",
            "subcategory":"Real Estate Operator",
            "type":"Services"
        }
    ],
    "sg:phone":"+1 214 942 9600",
    "sg:postcode":"75208",
    "sg:province":"TX",
    "sg:tags":[
        "retail",
        "leasing",
        "space"
    ],
    "wof:name":"Ice House Arts Plaza",
    "wof:placetype":"venue"
},
  "geometry": {"coordinates":[-96.839141,32.739324],"type":"Point"}
}