{
  "type": "Feature",
  "properties": {
    "iso:country":"US",
    "sg:address":"825 E Sarah Dewitt Dr",
    "sg:city":"Gonzales",
    "sg:classifiers":[
        {
            "category":"Professional",
            "subcategory":"Computer Services",
            "type":"Services"
        }
    ],
    "sg:phone":"+1 830 857 1201",
    "sg:postcode":"78629",
    "sg:province":"TX",
    "sg:tags":[
        "internet"
    ],
    "sg:website":"www.gvec.net",
    "wof:name":"GVEC.NET",
    "wof:placetype":"venue"
},
  "geometry": {"coordinates":[-97.43255000000001,29.519178],"type":"Point"}
}