{
  "type": "Feature",
  "properties": {
    "iso:country":"US",
    "sg:address":"2632 Century Park Blvd",
    "sg:city":"Austin",
    "sg:classifiers":[
        {
            "category":"Real Estate",
            "subcategory":"Real Estate Agent",
            "type":"Services"
        }
    ],
    "sg:phone":"+1 512 341 7444",
    "sg:postcode":"78727",
    "sg:province":"TX",
    "wof:name":"Condominiums At Cntury Pk Blvd",
    "wof:placetype":"venue"
},
  "geometry": {"coordinates":[-97.69192700000001,30.432821],"type":"Point"}
}