{
  "type": "Feature",
  "properties": {
    "iso:country":"US",
    "sg:address":"4800 Esco Dr",
    "sg:city":"Fort Worth",
    "sg:classifiers":[
        {
            "category":"Manufacturing",
            "subcategory":"Metals",
            "type":"Manufacturing & Wholesale Goods"
        }
    ],
    "sg:phone":"+1 817 478 4848",
    "sg:postcode":"76140",
    "sg:province":"TX",
    "sg:tags":[
        "foundry"
    ],
    "sg:website":"www.midland-midco.com",
    "wof:name":"Midland Manufacturing Co",
    "wof:placetype":"venue"
},
  "geometry": {"coordinates":[-97.250277,32.650913],"type":"Point"}
}