{
  "type": "Feature",
  "properties": {
    "iso:country":"US",
    "sg:address":"4210 Elderwood Dr",
    "sg:city":"Seabrook",
    "sg:classifiers":[
        {
            "category":"Professional",
            "subcategory":"Research",
            "type":"Services"
        }
    ],
    "sg:phone":"+1 281 280 7521",
    "sg:postcode":"77586",
    "sg:province":"TX",
    "sg:tags":[
        "commercial",
        "physical"
    ],
    "wof:name":"Desert Research Internati",
    "wof:placetype":"venue"
},
  "geometry": {"coordinates":[-95.061697,29.573696],"type":"Point"}
}