{
  "type": "Feature",
  "properties": {
    "iso:country":"US",
    "sg:address":"7701 Canyon Dr",
    "sg:city":"Amarillo",
    "sg:classifiers":[
        {
            "category":"Retail",
            "subcategory":"Veterinary Services",
            "type":"Services"
        }
    ],
    "sg:phone":"+1 806 352 7701",
    "sg:postcode":"79110",
    "sg:province":"TX",
    "sg:tags":[
        "veterinarian"
    ],
    "wof:name":"Yarbrough Veterinary Clinic",
    "wof:placetype":"venue"
},
  "geometry": {"coordinates":[-101.900353,35.130188],"type":"Point"}
}