{
  "type": "Feature",
  "properties": {
    "iso:country":"US",
    "sg:address":"4386 E FM 1673",
    "sg:city":"Snyder",
    "sg:classifiers":[
        {
            "category":"Freight",
            "type":"Transportation"
        }
    ],
    "sg:phone":"+1 325 573 1230",
    "sg:postcode":"79549",
    "sg:province":"TX",
    "sg:tags":[
        "trucking"
    ],
    "wof:name":"Hang'In S Trucking",
    "wof:placetype":"venue"
},
  "geometry": {"coordinates":[-100.83543299999999,32.733243],"type":"Point"}
}