{
  "type": "Feature",
  "properties": {
    "iso:country":"US",
    "sg:address":"12925 Valley Branch Ln.",
    "sg:city":"Farmers Branch",
    "sg:classifiers":[
        {
            "category":"Personal",
            "type":"Services"
        }
    ],
    "sg:phone":"+1 214 254 3222",
    "sg:postcode":"75234",
    "sg:province":"TX",
    "sg:tags":[
        "mover"
    ],
    "sg:website":"www.orionmoving.com",
    "wof:name":"Orion Moving and Storage",
    "wof:placetype":"venue"
},
  "geometry": {"coordinates":[-96.905372,32.918709],"type":"Point"}
}