{
  "type": "Feature",
  "properties": {
    "iso:country":"US",
    "sg:address":"5656 Alpha Rd",
    "sg:city":"Dallas",
    "sg:classifiers":[
        {
            "category":"Shopping",
            "subcategory":"Gifts & Souvenirs",
            "type":"Retail Goods"
        }
    ],
    "sg:phone":"+1 972 392 0114",
    "sg:postcode":"75240",
    "sg:province":"TX",
    "sg:tags":[
        "novelty"
    ],
    "wof:name":"J M 900 Inc Novelty Depot",
    "wof:placetype":"venue"
},
  "geometry": {"coordinates":[-96.809645,32.932802],"type":"Point"}
}