{
  "type": "Feature",
  "properties": {
    "iso:country":"US",
    "sg:address":"2936 Bison Ridge Dr",
    "sg:city":"Bulverde",
    "sg:classifiers":[
        {
            "category":"Building & Trades",
            "subcategory":"Landscaping Services",
            "type":"Services"
        }
    ],
    "sg:phone":"+1 830 438 9085",
    "sg:postcode":"78163",
    "sg:province":"TX",
    "sg:tags":[
        "landscape",
        "contractor"
    ],
    "wof:name":"Ghlm Inc",
    "wof:placetype":"venue"
},
  "geometry": {"coordinates":[-98.44000800000001,29.749658],"type":"Point"}
}