{
  "type": "Feature",
  "properties": {
    "iso:country":"US",
    "sg:address":"3000 Montgomery St",
    "sg:city":"Fort Worth",
    "sg:classifiers":[
        {
            "category":"Home & Garden",
            "subcategory":"Mobile Homes",
            "type":"Retail Goods"
        }
    ],
    "sg:phone":"+1 817 745 5399",
    "sg:postcode":"76107",
    "sg:province":"TX",
    "wof:name":"Lexington Place",
    "wof:placetype":"venue"
},
  "geometry": {"coordinates":[-97.370058,32.730052],"type":"Point"}
}