{
  "type": "Feature",
  "properties": {
    "iso:country":"US",
    "sg:address":"908 Congress St",
    "sg:city":"Houston",
    "sg:classifiers":[
        {
            "category":"Restaurant",
            "type":"Food & Drink"
        }
    ],
    "sg:phone":"+1 713 226 7210",
    "sg:postcode":"77002",
    "sg:province":"TX",
    "sg:tags":[
        "eating"
    ],
    "wof:name":"Wasabi Japanese",
    "wof:placetype":"venue"
},
  "geometry": {"coordinates":[-95.360831,29.762249],"type":"Point"}
}