{
  "type": "Feature",
  "properties": {
    "iso:country":"US",
    "sg:address":"1100 Whitehall Ln",
    "sg:city":"Greenville",
    "sg:classifiers":[
        {
            "category":"Shopping",
            "subcategory":"Bicycles & Sporting Goods",
            "type":"Retail Goods"
        }
    ],
    "sg:phone":"+1 903 454 0731",
    "sg:postcode":"75402",
    "sg:province":"TX",
    "wof:name":"Cedar Creek Sporting Supplies",
    "wof:placetype":"venue"
},
  "geometry": {"coordinates":[-96.09471499999999,33.065937],"type":"Point"}
}