{
  "type": "Feature",
  "properties": {
    "iso:country":"US",
    "sg:address":"14637 Memorial Dr",
    "sg:city":"Houston",
    "sg:classifiers":[
        {
            "category":"Restaurant",
            "type":"Food & Drink"
        }
    ],
    "sg:menulink":"http://www.allmenus.com/tx/houston/64512-chuck-e-cheeses/menu/",
    "sg:phone":"+1 281 531 7066",
    "sg:postcode":"77079",
    "sg:province":"TX",
    "sg:tags":[
        "american",
        "pizza"
    ],
    "wof:name":"Chuck E. Cheese's",
    "wof:placetype":"venue"
},
  "geometry": {"coordinates":[-95.607981,29.770062],"type":"Point"}
}