{
  "type": "Feature",
  "properties": {
    "iso:country":"US",
    "sg:address":"195 Quail Run St",
    "sg:city":"New Braunfels",
    "sg:classifiers":[
        {
            "category":"Building & Trades",
            "subcategory":"Construction",
            "type":"Services"
        }
    ],
    "sg:phone":"+1 830 620 8016",
    "sg:postcode":"78133",
    "sg:province":"TX",
    "sg:tags":[
        "heavy"
    ],
    "wof:name":"Dennis Russ McClanahan",
    "wof:placetype":"venue"
},
  "geometry": {"coordinates":[-98.29795799999999,29.858037],"type":"Point"}
}