{
  "type": "Feature",
  "properties": {
    "iso:country":"US",
    "sg:address":"106 del Ct",
    "sg:city":"Laredo",
    "sg:classifiers":[
        {
            "category":"Real Estate",
            "subcategory":"Developer",
            "type":"Services"
        }
    ],
    "sg:phone":"+1 956 791 0057",
    "sg:postcode":"78041",
    "sg:province":"TX",
    "wof:name":"Awa Development Corporation",
    "wof:placetype":"venue"
},
  "geometry": {"coordinates":[-99.499217,27.56507],"type":"Point"}
}