{
  "type": "Feature",
  "properties": {
    "iso:country":"US",
    "sg:address":"744 International Blvd",
    "sg:city":"Houston",
    "sg:classifiers":[
        {
            "category":"Professional",
            "subcategory":"Accounting & Tax Preparation",
            "type":"Services"
        }
    ],
    "sg:phone":"+1 713 263 0009",
    "sg:postcode":"77024",
    "sg:province":"TX",
    "sg:tags":[
        "accountant"
    ],
    "wof:name":"Jim W Lehmberg & Associates",
    "wof:placetype":"venue"
},
  "geometry": {"coordinates":[-95.477892,29.78308],"type":"Point"}
}