{
  "type": "Feature",
  "properties": {
    "iso:country":"US",
    "sg:address":"12623 Silverglen Estates Dr",
    "sg:city":"Houston",
    "sg:classifiers":[
        {
            "category":"Communications",
            "subcategory":"Film & Video Production",
            "type":"Services"
        }
    ],
    "sg:phone":"+1 281 880 9556",
    "sg:postcode":"77014",
    "sg:province":"TX",
    "sg:tags":[
        "motion"
    ],
    "wof:name":"Wyzeman Production",
    "wof:placetype":"venue"
},
  "geometry": {"coordinates":[-95.457334,29.969625],"type":"Point"}
}