{
  "type": "Feature",
  "properties": {
    "iso:country":"US",
    "sg:address":"31018 N Cripple Creek Dr",
    "sg:city":"Magnolia",
    "sg:classifiers":[
        {
            "category":"Building & Trades",
            "subcategory":"Construction",
            "type":"Services"
        }
    ],
    "sg:phone":"+1 281 259 5328",
    "sg:postcode":"77354",
    "sg:province":"TX",
    "sg:tags":[
        "system",
        "contractor",
        "air conditioning"
    ],
    "wof:name":"Condair",
    "wof:placetype":"venue"
},
  "geometry": {"coordinates":[-95.714708,30.193512],"type":"Point"}
}