{
  "type": "Feature",
  "properties": {
    "iso:country":"US",
    "sg:address":"5849 Holly Rd",
    "sg:city":"Corpus Christi",
    "sg:classifiers":[
        {
            "category":"Freight",
            "type":"Transportation"
        },
        {
            "category":"Professional",
            "subcategory":"Business Services",
            "type":"Services"
        }
    ],
    "sg:phone":"+1 361 991 6700",
    "sg:postcode":"78412",
    "sg:province":"TX",
    "sg:tags":[
        "drafting",
        "general"
    ],
    "wof:name":"A-1 Holly Storage",
    "wof:placetype":"venue"
},
  "geometry": {"coordinates":[-97.371799,27.696186],"type":"Point"}
}