{
  "type": "Feature",
  "properties": {
    "iso:country":"US",
    "sg:address":"401 Exposition Ave",
    "sg:city":"Dallas",
    "sg:classifiers":[
        {
            "category":"Professional",
            "subcategory":"Management & Consulting",
            "type":"Services"
        },
        {
            "category":"Building & Trades",
            "subcategory":"Landscaping Services",
            "type":"Services"
        }
    ],
    "sg:phone":"+1 214 824 7949",
    "sg:postcode":"75226",
    "sg:province":"TX",
    "sg:tags":[
        "planning",
        "business",
        "land"
    ],
    "wof:name":"Baldwin Associates LLC",
    "wof:placetype":"venue"
},
  "geometry": {"coordinates":[-96.771804,32.783577],"type":"Point"}
}