{
  "type": "Feature",
  "properties": {
    "iso:country":"US",
    "sg:address":"323 S Ohio Ave",
    "sg:city":"Mercedes",
    "sg:classifiers":[
        {
            "category":"Professional",
            "type":"Services"
        }
    ],
    "sg:phone":"+1 956 565 7755",
    "sg:postcode":"78570",
    "sg:province":"TX",
    "sg:tags":[
        "establishment"
    ],
    "wof:name":"Mercedes Fire Stationhouse Non",
    "wof:placetype":"venue"
},
  "geometry": {"coordinates":[-97.912255,26.148752],"type":"Point"}
}