{
  "type": "Feature",
  "properties": {
    "iso:country":"US",
    "sg:address":"1740 Dulles Ave",
    "sg:city":"Sugar Land",
    "sg:classifiers":[
        {
            "category":"Autos & Motor Vehicles",
            "subcategory":"Fuel & Gas Station",
            "type":"Retail Goods"
        }
    ],
    "sg:phone":"+1 281 494 4313",
    "sg:postcode":"77478",
    "sg:province":"TX",
    "sg:tags":[
        "station",
        "gasoline"
    ],
    "wof:name":"First Colony Chevron",
    "wof:placetype":"venue"
},
  "geometry": {"coordinates":[-95.58213499999999,29.599356],"type":"Point"}
}