{
  "type": "Feature",
  "properties": {
    "iso:country":"US",
    "sg:address":"318 Kelly Dr",
    "sg:city":"Victoria",
    "sg:classifiers":[
        {
            "category":"Shopping",
            "subcategory":"Gifts & Souvenirs",
            "type":"Retail Goods"
        }
    ],
    "sg:phone":"+1 361 575 4223",
    "sg:postcode":"77904",
    "sg:province":"TX",
    "sg:tags":[
        "shop"
    ],
    "wof:name":"Lone Star Designs",
    "wof:placetype":"venue"
},
  "geometry": {"coordinates":[-96.999728,28.860388],"type":"Point"}
}