{
  "type": "Feature",
  "properties": {
    "iso:country":"US",
    "sg:address":"1865 College St",
    "sg:city":"Beaumont",
    "sg:classifiers":[
        {
            "category":"Bars & Pubs",
            "type":"Food & Drink"
        },
        {
            "category":"Food & Beverages",
            "subcategory":"Groceries & Convenience Stores",
            "type":"Retail Goods"
        },
        {
            "category":"Restaurant",
            "type":"Food & Drink"
        },
        {
            "category":"Bars & Pubs",
            "subcategory":"Lounge",
            "type":"Food & Drink"
        },
        {
            "category":"Professional",
            "type":"Services"
        }
    ],
    "sg:phone":"+1 409 832 1203",
    "sg:postcode":"77701",
    "sg:province":"TX",
    "sg:tags":[
        "american",
        "latin",
        "mexican",
        "cocktail",
        "caterer"
    ],
    "wof:name":"Elena's Mexican Restaurant",
    "wof:placetype":"venue"
},
  "geometry": {"coordinates":[-94.108649,30.069936],"type":"Point"}
}