{
  "type": "Feature",
  "properties": {
    "iso:country":"US",
    "sg:address":"17804 Dickerson St",
    "sg:city":"Dallas",
    "sg:classifiers":[
        {
            "category":"Retail",
            "subcategory":"Auto Rental",
            "type":"Services"
        }
    ],
    "sg:phone":"+1 972 248 6305",
    "sg:postcode":"75252",
    "sg:province":"TX",
    "sg:tags":[
        "passenger",
        "leasing",
        "car"
    ],
    "wof:name":"Bsfr Enterprises LLC",
    "wof:placetype":"venue"
},
  "geometry": {"coordinates":[-96.775144,32.99227],"type":"Point"}
}