{
  "type": "Feature",
  "properties": {
    "iso:country":"US",
    "sg:address":"5150 Howcher St",
    "sg:city":"Houston",
    "sg:classifiers":[
        {
            "category":"Organizations",
            "subcategory":"Religious Organization",
            "type":"Services"
        }
    ],
    "sg:phone":"+1 713 723 9870",
    "sg:postcode":"77048",
    "sg:province":"TX",
    "sg:tags":[
        "church"
    ],
    "wof:name":"Gracious Hope Ministries",
    "wof:placetype":"venue"
},
  "geometry": {"coordinates":[-95.346959,29.63714],"type":"Point"}
}