{
  "type": "Feature",
  "properties": {
    "iso:country":"US",
    "sg:address":"12625 Memorial Dr",
    "sg:city":"Houston",
    "sg:classifiers":[
        {
            "category":"Shopping",
            "type":"Retail Goods"
        }
    ],
    "sg:phone":"+1 713 464 8157",
    "sg:postcode":"77024",
    "sg:province":"TX",
    "sg:tags":[
        "merchandise"
    ],
    "wof:name":"Grace S Chen",
    "wof:placetype":"venue"
},
  "geometry": {"coordinates":[-95.555336,29.766099],"type":"Point"}
}