{
  "type": "Feature",
  "properties": {
    "iso:country":"US",
    "sg:address":"3816 San Jacinto St",
    "sg:city":"Dallas",
    "sg:classifiers":[
        {
            "category":"Organizations",
            "subcategory":"Professional Association",
            "type":"Services"
        }
    ],
    "sg:phone":"+1 214 824 3314",
    "sg:postcode":"75204",
    "sg:province":"TX",
    "wof:name":"Texas State Teachers Assn",
    "wof:placetype":"venue"
},
  "geometry": {"coordinates":[-96.78424099999999,32.797958],"type":"Point"}
}