{
  "type": "Feature",
  "properties": {
    "iso:country":"US",
    "sg:address":"26840 I- 45",
    "sg:city":"Spring",
    "sg:classifiers":[
        {
            "category":"Restaurant",
            "type":"Food & Drink"
        }
    ],
    "sg:phone":"+1 281 363 3290",
    "sg:postcode":"77386",
    "sg:province":"TX",
    "sg:tags":[
        "eating"
    ],
    "wof:name":"Pitts & Spitts",
    "wof:placetype":"venue"
},
  "geometry": {"coordinates":[-95.44745500000001,30.150444],"type":"Point"}
}