{
  "type": "Feature",
  "properties": {
    "iso:country":"US",
    "sg:address":"1579 G Ave",
    "sg:city":"Plano",
    "sg:classifiers":[
        {
            "category":"Insurance",
            "subcategory":"Insurance Agent",
            "type":"Services"
        }
    ],
    "sg:phone":"+1 972 423 7864",
    "sg:postcode":"75074",
    "sg:province":"TX",
    "wof:name":"Aniobi Insurance Agency Inc",
    "wof:placetype":"venue"
},
  "geometry": {"coordinates":[-96.70509699999999,33.02004],"type":"Point"}
}