{
  "type": "Feature",
  "properties": {
    "iso:country":"US",
    "sg:address":"74 Boca Chica Blvd",
    "sg:city":"Brownsville",
    "sg:classifiers":[
        {
            "category":"Personal",
            "subcategory":"Barber",
            "type":"Services"
        }
    ],
    "sg:phone":"+1 956 546 1059",
    "sg:postcode":"78520",
    "sg:province":"TX",
    "sg:tags":[
        "shop"
    ],
    "wof:name":"Triangle Barber Shop",
    "wof:placetype":"venue"
},
  "geometry": {"coordinates":[-97.518852,25.926501],"type":"Point"}
}