{
  "type": "Feature",
  "properties": {
    "iso:country":"US",
    "sg:address":"5308 Flamingo Rd",
    "sg:city":"Fort Worth",
    "sg:classifiers":[
        {
            "category":"Building & Trades",
            "subcategory":"Construction",
            "type":"Services"
        }
    ],
    "sg:phone":"+1 817 531 3768",
    "sg:postcode":"76119",
    "sg:province":"TX",
    "sg:tags":[
        "project"
    ],
    "wof:name":"Tizoc's Construction",
    "wof:placetype":"venue"
},
  "geometry": {"coordinates":[-97.262156,32.679004],"type":"Point"}
}