{
  "type": "Feature",
  "properties": {
    "iso:country":"US",
    "sg:address":"11310 Plano Rd",
    "sg:city":"Dallas",
    "sg:classifiers":[
        {
            "category":"Professional",
            "type":"Services"
        }
    ],
    "sg:phone":"+1 214 343 6932",
    "sg:postcode":"75243",
    "sg:province":"TX",
    "wof:name":"Dallas Convertible Top Svc",
    "wof:placetype":"venue"
},
  "geometry": {"coordinates":[-96.700524,32.901733],"type":"Point"}
}