{
  "type": "Feature",
  "properties": {
    "iso:country":"US",
    "sg:address":"900 W Dallas St",
    "sg:city":"Conroe",
    "sg:classifiers":[
        {
            "category":"Shopping",
            "type":"Retail Goods"
        }
    ],
    "sg:phone":"+1 936 539 2713",
    "sg:postcode":"77301",
    "sg:province":"TX",
    "sg:tags":[
        "cosmetic",
        "perfume"
    ],
    "wof:name":"Wake Up With Make Up By Lisa",
    "wof:placetype":"venue"
},
  "geometry": {"coordinates":[-95.46723299999999,30.317631],"type":"Point"}
}