{
  "type": "Feature",
  "properties": {
    "iso:country":"US",
    "sg:address":"14403 Ella Blvd",
    "sg:city":"Houston",
    "sg:classifiers":[
        {
            "category":"Real Estate",
            "subcategory":"Real Estate Agent",
            "type":"Services"
        }
    ],
    "sg:phone":"+1 281 872 5075",
    "sg:postcode":"77014",
    "sg:province":"TX",
    "sg:tags":[
        "mgr"
    ],
    "wof:name":"Bayberry Tree",
    "wof:placetype":"venue"
},
  "geometry": {"coordinates":[-95.438115,29.976693],"type":"Point"}
}