{
  "type": "Feature",
  "properties": {
    "iso:country":"US",
    "sg:address":"308 US Hwy 83",
    "sg:city":"Zapata",
    "sg:phone":"+1 956 765 3919",
    "sg:postcode":"78076",
    "sg:province":"TX",
    "sg:tags":[
        "product",
        "petroleum"
    ],
    "wof:name":"Chevron Texaco",
    "wof:placetype":"venue"
},
  "geometry": {"coordinates":[-99.26512099999999,26.898948],"type":"Point"}
}