{
  "type": "Feature",
  "properties": {
    "iso:country":"US",
    "sg:address":"566 Ash St",
    "sg:city":"Brownsville",
    "sg:classifiers":[
        {
            "category":"Social Services",
            "subcategory":"Child Care",
            "type":"Services"
        }
    ],
    "sg:phone":"+1 956 574 9928",
    "sg:postcode":"78521",
    "sg:province":"TX",
    "wof:name":"Poinsettia Learning Ctr",
    "wof:placetype":"venue"
},
  "geometry": {"coordinates":[-97.482669,25.920383],"type":"Point"}
}