{
  "type": "Feature",
  "properties": {
    "iso:country":"US",
    "sg:address":"7125 Northpointe Dr",
    "sg:city":"Lewisville",
    "sg:classifiers":[
        {
            "category":"Building & Trades",
            "subcategory":"Construction",
            "type":"Services"
        }
    ],
    "sg:phone":"+1 469 384 0843",
    "sg:postcode":"75056",
    "sg:province":"TX",
    "sg:tags":[
        "general",
        "contractor"
    ],
    "wof:name":"Cripple Creek Contractors",
    "wof:placetype":"venue"
},
  "geometry": {"coordinates":[-96.85996400000001,33.100562],"type":"Point"}
}