{
  "type": "Feature",
  "properties": {
    "iso:country":"US",
    "sg:address":"19506 US Hwy 59",
    "sg:city":"Humble",
    "sg:classifiers":[
        {
            "category":"Insurance",
            "subcategory":"Life Insurance",
            "type":"Services"
        }
    ],
    "sg:phone":"+1 281 540 4437",
    "sg:postcode":"77338",
    "sg:province":"TX",
    "sg:tags":[
        "carrier"
    ],
    "wof:name":"AFLAC",
    "wof:placetype":"venue"
},
  "geometry": {"coordinates":[-95.26951800000001,30.000176],"type":"Point"}
}