{
  "type": "Feature",
  "properties": {
    "iso:country":"US",
    "sg:address":"5446 US Hwy 290",
    "sg:city":"Austin",
    "sg:classifiers":[
        {
            "category":"Education",
            "subcategory":"Special Training",
            "type":"Public Place"
        }
    ],
    "sg:phone":"+1 512 892 5975",
    "sg:postcode":"78735",
    "sg:province":"TX",
    "sg:tags":[
        "instruction",
        "music"
    ],
    "wof:name":"Calusio School Of Music",
    "wof:placetype":"venue"
},
  "geometry": {"coordinates":[-97.84148500000001,30.236374],"type":"Point"}
}