{
  "type": "Feature",
  "properties": {
    "iso:country":"US",
    "sg:address":"626 W 27th St",
    "sg:city":"Houston",
    "sg:classifiers":[
        {
            "category":"Building & Trades",
            "subcategory":"Construction",
            "type":"Services"
        }
    ],
    "sg:phone":"+1 713 922 6905",
    "sg:postcode":"77008",
    "sg:province":"TX",
    "sg:tags":[
        "resurfacing",
        "laying",
        "refinishing",
        "floor"
    ],
    "wof:name":"Extravaganza Tile",
    "wof:placetype":"venue"
},
  "geometry": {"coordinates":[-95.409792,29.81085],"type":"Point"}
}