{
  "type": "Feature",
  "properties": {
    "iso:country":"US",
    "sg:address":"13018 Ocean Glade",
    "sg:city":"San Antonio",
    "sg:classifiers":[
        {
            "category":"Wholesale",
            "subcategory":"Groceries",
            "type":"Manufacturing & Wholesale Goods"
        }
    ],
    "sg:phone":"+1 210 696 3872",
    "sg:postcode":"78249",
    "sg:province":"TX",
    "sg:tags":[
        "beverage",
        "concentrate"
    ],
    "wof:name":"Alamo City Distributing Co",
    "wof:placetype":"venue"
},
  "geometry": {"coordinates":[-98.637339,29.562361],"type":"Point"}
}