{
  "type": "Feature",
  "properties": {
    "iso:country":"US",
    "sg:address":"5728 67th St",
    "sg:city":"Lubbock",
    "sg:classifiers":[
        {
            "category":"Organizations",
            "subcategory":"Membership Organization",
            "type":"Services"
        }
    ],
    "sg:phone":"+1 806 794 8991",
    "sg:postcode":"79424",
    "sg:province":"TX",
    "sg:tags":[
        "member"
    ],
    "wof:name":"American Counicl of The Blind",
    "wof:placetype":"venue"
},
  "geometry": {"coordinates":[-101.93726700000001,33.533344],"type":"Point"}
}