{
  "type": "Feature",
  "properties": {
    "iso:country":"US",
    "sg:address":"1617 Richmond Ave",
    "sg:city":"Houston",
    "sg:classifiers":[
        {
            "category":"Restaurant",
            "type":"Food & Drink"
        }
    ],
    "sg:phone":"+1 713 528 4920",
    "sg:postcode":"77006",
    "sg:province":"TX",
    "sg:tags":[
        "mexican"
    ],
    "sg:website":"www.mariaselma.com/",
    "wof:name":"Maria Selma Restaurant",
    "wof:placetype":"venue"
},
  "geometry": {"coordinates":[-95.400597,29.734301],"type":"Point"}
}