{
  "type": "Feature",
  "properties": {
    "iso:country":"US",
    "sg:address":"501 W President George Bush Hwy",
    "sg:city":"Richardson",
    "sg:classifiers":[
        {
            "category":"Banks & Credit Unions",
            "subcategory":"Financial Services",
            "type":"Services"
        },
        {
            "category":"Professional",
            "subcategory":"Research",
            "type":"Services"
        },
        {
            "category":"Insurance",
            "subcategory":"Hazard Insurance",
            "type":"Services"
        },
        {
            "category":"Insurance",
            "subcategory":"Title Insurance",
            "type":"Services"
        },
        {
            "category":"Real Estate",
            "subcategory":"Real Estate Services",
            "type":"Services"
        }
    ],
    "sg:phone":"+1 972 437 1536",
    "sg:postcode":"75080",
    "sg:province":"TX",
    "sg:tags":[
        "abstracter",
        "mortgage",
        "escrow"
    ],
    "sg:website":"http://www.firstam.com",
    "wof:name":"First American Title Insurance Company",
    "wof:placetype":"venue"
},
  "geometry": {"coordinates":[-96.726448,33.0033],"type":"Point"}
}