{
  "type": "Feature",
  "properties": {
    "iso:country":"US",
    "sg:address":"3418 Reveille St",
    "sg:city":"Houston",
    "sg:classifiers":[
        {
            "category":"Food & Beverages",
            "subcategory":"Groceries & Convenience Stores",
            "type":"Retail Goods"
        }
    ],
    "sg:phone":"+1 713 643 8733",
    "sg:postcode":"77087",
    "sg:province":"TX",
    "wof:name":"No 1 Reveille Food Store",
    "wof:placetype":"venue"
},
  "geometry": {"coordinates":[-95.29119900000001,29.6938],"type":"Point"}
}