{
  "type": "Feature",
  "properties": {
    "iso:country":"US",
    "sg:address":"6815 Caravel Ln",
    "sg:city":"Missouri City",
    "sg:classifiers":[
        {
            "category":"Food & Beverages",
            "subcategory":"Groceries & Convenience Stores",
            "type":"Retail Goods"
        }
    ],
    "sg:phone":"+1 281 208 2557",
    "sg:postcode":"77459",
    "sg:province":"TX",
    "wof:name":"Cullen Stop N Go",
    "wof:placetype":"venue"
},
  "geometry": {"coordinates":[-95.567425,29.554154],"type":"Point"}
}