{
  "type": "Feature",
  "properties": {
    "iso:country":"US",
    "sg:address":"306 Prince of Wales St",
    "sg:city":"Conroe",
    "sg:classifiers":[
        {
            "category":"Manufacturing",
            "subcategory":"Signs",
            "type":"Manufacturing & Wholesale Goods"
        }
    ],
    "sg:phone":"+1 936 788 2568",
    "sg:postcode":"77304",
    "sg:province":"TX",
    "sg:tags":[
        "specialty",
        "mfg"
    ],
    "wof:name":"Excell Signs",
    "wof:placetype":"venue"
},
  "geometry": {"coordinates":[-95.47144299999999,30.286458],"type":"Point"}
}