{
  "type": "Feature",
  "properties": {
    "iso:country":"US",
    "sg:address":"4011 Commerce St",
    "sg:city":"Dallas",
    "sg:classifiers":[
        {
            "category":"Parking",
            "type":"Transportation"
        }
    ],
    "sg:phone":"+1 214 874 0468",
    "sg:postcode":"75226",
    "sg:province":"TX",
    "sg:tags":[
        "operator",
        "public",
        "lot"
    ],
    "wof:name":"Parking Company of America-Dallas Inc",
    "wof:placetype":"venue"
},
  "geometry": {"coordinates":[-96.769302,32.783901],"type":"Point"}
}