{
  "type": "Feature",
  "properties": {
    "iso:country":"US",
    "sg:address":"2029 E Shady Grove Rd",
    "sg:city":"Irving",
    "sg:classifiers":[
        {
            "category":"Wholesale",
            "subcategory":"Machinery & Supplies",
            "type":"Manufacturing & Wholesale Goods"
        }
    ],
    "sg:phone":"+1 972 554 8534",
    "sg:postcode":"75060",
    "sg:province":"TX",
    "sg:tags":[
        "equipment",
        "welding"
    ],
    "wof:name":"Metroplex Welding Supply",
    "wof:placetype":"venue"
},
  "geometry": {"coordinates":[-96.914624,32.801331],"type":"Point"}
}