{
  "type": "Feature",
  "properties": {
    "iso:country":"US",
    "sg:address":"3511 66th Dr",
    "sg:city":"Lubbock",
    "sg:classifiers":[
        {
            "category":"Real Estate",
            "subcategory":"Real Estate Agent",
            "type":"Services"
        }
    ],
    "sg:phone":"+1 806 797 2049",
    "sg:postcode":"79413",
    "sg:province":"TX",
    "wof:name":"Winnland Realtors",
    "wof:placetype":"venue"
},
  "geometry": {"coordinates":[-101.890815,33.532573],"type":"Point"}
}