{
  "type": "Feature",
  "properties": {
    "iso:country":"US",
    "sg:address":"3310 Rosemary Ln",
    "sg:city":"Houston",
    "sg:classifiers":[
        {
            "category":"Freight",
            "type":"Transportation"
        }
    ],
    "sg:phone":"+1 281 449 8247",
    "sg:postcode":"77093",
    "sg:province":"TX",
    "sg:tags":[
        "delivery",
        "contract"
    ],
    "wof:name":"Zamora Refugio Cisneros & Let",
    "wof:placetype":"venue"
},
  "geometry": {"coordinates":[-95.338365,29.876904],"type":"Point"}
}