{
  "type": "Feature",
  "properties": {
    "iso:country":"US",
    "sg:address":"2125 Limrick Dr",
    "sg:city":"Pearland",
    "sg:classifiers":[
        {
            "category":"Shopping",
            "type":"Retail Goods"
        }
    ],
    "sg:phone":"+1 281 484 2003",
    "sg:postcode":"77581",
    "sg:province":"TX",
    "sg:tags":[
        "merchandise"
    ],
    "wof:name":"Pride Graphix Productionz",
    "wof:placetype":"venue"
},
  "geometry": {"coordinates":[-95.231303,29.572577],"type":"Point"}
}