{
  "type": "Feature",
  "properties": {
    "iso:country":"US",
    "sg:address":"12723 Aspen Dr",
    "sg:city":"Pinehurst",
    "sg:classifiers":[
        {
            "category":"Shopping",
            "subcategory":"Used Merchandise",
            "type":"Retail Goods"
        }
    ],
    "sg:phone":"+1 281 356 2065",
    "sg:postcode":"77362",
    "sg:province":"TX",
    "wof:name":"Helen L Savage",
    "wof:placetype":"venue"
},
  "geometry": {"coordinates":[-95.660793,30.142122],"type":"Point"}
}