{
  "type": "Feature",
  "properties": {
    "iso:country":"US",
    "sg:address":"2535 E Commerce St",
    "sg:city":"San Antonio",
    "sg:classifiers":[
        {
            "category":"Shopping",
            "subcategory":"Gifts & Souvenirs",
            "type":"Retail Goods"
        }
    ],
    "sg:phone":"+1 210 277 6514",
    "sg:postcode":"78203",
    "sg:province":"TX",
    "sg:tags":[
        "shop"
    ],
    "wof:name":"Hearts Strings Greetings",
    "wof:placetype":"venue"
},
  "geometry": {"coordinates":[-98.45295299999999,29.419522],"type":"Point"}
}