{
  "type": "Feature",
  "properties": {
    "iso:country":"US",
    "sg:address":"601 W US Hwy 83",
    "sg:city":"Mcallen",
    "sg:classifiers":[
        {
            "category":"Wholesale",
            "subcategory":"Motor Vehicles",
            "type":"Manufacturing & Wholesale Goods"
        }
    ],
    "sg:phone":"+1 956 686 0112",
    "sg:postcode":"78501",
    "sg:province":"TX",
    "sg:tags":[
        "automobile"
    ],
    "wof:name":"R T Sparks Autos Inc",
    "wof:placetype":"venue"
},
  "geometry": {"coordinates":[-98.22682399999999,26.202786],"type":"Point"}
}