{
  "type": "Feature",
  "properties": {
    "iso:country":"US",
    "sg:address":"1812 Avenue D Ste 205",
    "sg:city":"Katy",
    "sg:classifiers":[
        {
            "category":"Place Of Worship",
            "subcategory":"Church",
            "type":"Public Place"
        },
        {
            "category":"Place Of Worship",
            "type":"Public Place"
        },
        {
            "category":"Organizations",
            "subcategory":"Religious Organization",
            "type":"Services"
        }
    ],
    "sg:phone":"+1 281 391 0099",
    "sg:postcode":"77493",
    "sg:province":"TX",
    "sg:tags":[
        "churches-interdenominational",
        "churches-non-denominational",
        "churches-various",
        "denomination"
    ],
    "sg:website":"http://www.katyfellowship.com",
    "wof:name":"Katy Community Fellowship",
    "wof:placetype":"venue"
},
  "geometry": {"coordinates":[-95.824983,29.798609],"type":"Point"}
}