{
  "type": "Feature",
  "properties": {
    "iso:country":"US",
    "sg:address":"1415 Stinson Rd",
    "sg:city":"Allen",
    "sg:classifiers":[
        {
            "category":"Shopping",
            "subcategory":"Florist",
            "type":"Retail Goods"
        }
    ],
    "sg:phone":"+1 972 442 3437",
    "sg:postcode":"75002",
    "sg:province":"TX",
    "wof:name":"H&A Flowers Management LL",
    "wof:placetype":"venue"
},
  "geometry": {"coordinates":[-96.585436,33.064489],"type":"Point"}
}