{
  "type": "Feature",
  "properties": {
    "iso:country":"US",
    "sg:address":"211 E Commerce St",
    "sg:city":"Webster",
    "sg:classifiers":[
        {
            "category":"Building & Trades",
            "subcategory":"Construction",
            "type":"Services"
        }
    ],
    "sg:phone":"+1 281 290 7906",
    "sg:postcode":"77598",
    "sg:province":"TX",
    "sg:tags":[
        "contractor"
    ],
    "wof:name":"Jims Roofing & Remodeling",
    "wof:placetype":"venue"
},
  "geometry": {"coordinates":[-95.11980200000001,29.540535],"type":"Point"}
}