{
  "type": "Feature",
  "properties": {
    "iso:country":"US",
    "sg:address":"20518 Broadsky Dr",
    "sg:city":"Katy",
    "sg:classifiers":[
        {
            "category":"Building & Trades",
            "subcategory":"Construction",
            "type":"Services"
        }
    ],
    "sg:phone":"+1 281 398 9406",
    "sg:postcode":"77449",
    "sg:province":"TX",
    "sg:tags":[
        "hanging",
        "contractor"
    ],
    "wof:name":"Cleto S Painting",
    "wof:placetype":"venue"
},
  "geometry": {"coordinates":[-95.73736100000001,29.788697],"type":"Point"}
}