{
  "type": "Feature",
  "properties": {
    "iso:country":"US",
    "sg:address":"4522 Leopard St",
    "sg:city":"Corpus Christi",
    "sg:classifiers":[
        {
            "category":"Food & Beverages",
            "subcategory":"Bakery",
            "type":"Retail Goods"
        }
    ],
    "sg:phone":"+1 361 887 6022",
    "sg:postcode":"78408",
    "sg:province":"TX",
    "sg:tags":[
        "baker"
    ],
    "wof:name":"Dolly Madison Cakes",
    "wof:placetype":"venue"
},
  "geometry": {"coordinates":[-97.444266,27.797208],"type":"Point"}
}