{
  "type": "Feature",
  "properties": {
    "iso:country":"US",
    "sg:address":"2219 N Frazier St",
    "sg:city":"Conroe",
    "sg:classifiers":[
        {
            "category":"Retail",
            "subcategory":"Auto Repair",
            "type":"Services"
        }
    ],
    "sg:phone":"+1 936 756 4874",
    "sg:postcode":"77303",
    "sg:province":"TX",
    "sg:tags":[
        "repairing",
        "automobile"
    ],
    "wof:name":"Speedy's Auto Svc",
    "wof:placetype":"venue"
},
  "geometry": {"coordinates":[-95.46813400000001,30.337497],"type":"Point"}
}