{
  "type": "Feature",
  "properties": {
    "iso:country":"US",
    "sg:address":"14160 Dallas Pkwy Ste 120",
    "sg:city":"Dallas",
    "sg:classifiers":[
        {
            "category":"Professional",
            "subcategory":"Employment Agencies",
            "type":"Services"
        }
    ],
    "sg:phone":"+1 972 392 1144",
    "sg:postcode":"75254",
    "sg:province":"TX",
    "wof:name":"Innovative Solutions Advisors LLC",
    "wof:placetype":"venue"
},
  "geometry": {"coordinates":[-96.821585,32.940675],"type":"Point"}
}