{
  "type": "Feature",
  "properties": {
    "iso:country":"US",
    "sg:address":"1759 Co Rd 5710",
    "sg:city":"Devine",
    "sg:classifiers":[
        {
            "category":"Professional",
            "type":"Services"
        }
    ],
    "sg:phone":"+1 830 665 4521",
    "sg:postcode":"78016",
    "sg:province":"TX",
    "wof:name":"Devine Educationl Services",
    "wof:placetype":"venue"
},
  "geometry": {"coordinates":[-98.924791,29.162806],"type":"Point"}
}