{
  "type": "Feature",
  "properties": {
    "iso:country":"US",
    "sg:address":"475 E Church St",
    "sg:city":"Beaumont",
    "sg:classifiers":[
        {
            "category":"Building & Trades",
            "subcategory":"Construction",
            "type":"Services"
        }
    ],
    "sg:phone":"+1 409 813 3131",
    "sg:postcode":"77705",
    "sg:province":"TX",
    "sg:tags":[
        "contractor"
    ],
    "wof:name":"CRS Contractors",
    "wof:placetype":"venue"
},
  "geometry": {"coordinates":[-94.082629,30.051588],"type":"Point"}
}