{
  "type": "Feature",
  "properties": {
    "iso:country":"US",
    "sg:address":"3815 Sunstone Dr",
    "sg:city":"Houston",
    "sg:classifiers":[
        {
            "category":"Professional",
            "subcategory":"Management & Consulting",
            "type":"Services"
        }
    ],
    "sg:phone":"+1 281 580 4886",
    "sg:postcode":"77068",
    "sg:province":"TX",
    "wof:name":"R R S and Associates",
    "wof:placetype":"venue"
},
  "geometry": {"coordinates":[-95.500033,30.006431],"type":"Point"}
}