{
  "type": "Feature",
  "properties": {
    "iso:country":"US",
    "sg:address":"1707 Susan Dr",
    "sg:city":"Arlington",
    "sg:classifiers":[
        {
            "category":"Building & Trades",
            "subcategory":"Electrical",
            "type":"Services"
        }
    ],
    "sg:phone":"+1 817 261 1400",
    "sg:postcode":"76010",
    "sg:province":"TX",
    "sg:tags":[
        "electrical",
        "contractor"
    ],
    "wof:name":"D C Communications",
    "wof:placetype":"venue"
},
  "geometry": {"coordinates":[-97.05712200000001,32.717717],"type":"Point"}
}