{
  "type": "Feature",
  "properties": {
    "iso:country":"US",
    "sg:address":"2005 N Zarzamora",
    "sg:city":"San Antonio",
    "sg:classifiers":[
        {
            "category":"Shopping",
            "subcategory":"Florist",
            "type":"Retail Goods"
        }
    ],
    "sg:phone":"+1 210 496 0901",
    "sg:postcode":"78201",
    "sg:province":"TX",
    "wof:name":"Blossoms",
    "wof:placetype":"venue"
},
  "geometry": {"coordinates":[-98.524478,29.44949],"type":"Point"}
}