{
  "type": "Feature",
  "properties": {
    "iso:country":"US",
    "sg:address":"14235 Alderson St",
    "sg:city":"Houston",
    "sg:classifiers":[
        {
            "category":"Insurance",
            "subcategory":"Insurance Agent",
            "type":"Services"
        }
    ],
    "sg:phone":"+1 713 451 8272",
    "sg:postcode":"77015",
    "sg:province":"TX",
    "wof:name":"Alinas Kwick Klaims",
    "wof:placetype":"venue"
},
  "geometry": {"coordinates":[-95.17061099999999,29.788249],"type":"Point"}
}