{
  "type": "Feature",
  "properties": {
    "iso:country":"US",
    "sg:address":"2237 Joe Field Rd",
    "sg:city":"Dallas",
    "sg:classifiers":[
        {
            "category":"Building & Trades",
            "subcategory":"Landscaping Services",
            "type":"Services"
        }
    ],
    "sg:phone":"+1 972 247 0141",
    "sg:postcode":"75229",
    "sg:province":"TX",
    "sg:tags":[
        "landscape",
        "contractor"
    ],
    "sg:website":"www.plantcareco.com",
    "wof:name":"Plant Care Co",
    "wof:placetype":"venue"
},
  "geometry": {"coordinates":[-96.89962199999999,32.893022],"type":"Point"}
}