{
  "type": "Feature",
  "properties": {
    "iso:country":"US",
    "sg:address":"806 Pecan Blvd",
    "sg:city":"Mcallen",
    "sg:classifiers":[
        {
            "category":"Professional",
            "subcategory":"Lawyer & Legal Services",
            "type":"Services"
        }
    ],
    "sg:phone":"+1 956 682 8316",
    "sg:postcode":"78501",
    "sg:province":"TX",
    "sg:tags":[
        "attorney"
    ],
    "wof:name":"Mark Freeland Law Office",
    "wof:placetype":"venue"
},
  "geometry": {"coordinates":[-98.22650299999999,26.217718],"type":"Point"}
}