{
  "type": "Feature",
  "properties": {
    "iso:country":"US",
    "sg:address":"1502 E Lane St",
    "sg:city":"Laredo",
    "sg:classifiers":[
        {
            "category":"Restaurant",
            "type":"Food & Drink"
        }
    ],
    "sg:phone":"+1 956 722 1576",
    "sg:postcode":"78040",
    "sg:province":"TX",
    "sg:tags":[
        "eating"
    ],
    "wof:name":"Operation Pretzel",
    "wof:placetype":"venue"
},
  "geometry": {"coordinates":[-99.480366,27.513065],"type":"Point"}
}