{
  "type": "Feature",
  "properties": {
    "iso:country":"US",
    "sg:address":"6801 John T White Rd",
    "sg:city":"Fort Worth",
    "sg:classifiers":[
        {
            "category":"Food & Beverages",
            "subcategory":"Groceries & Convenience Stores",
            "type":"Retail Goods"
        }
    ],
    "sg:phone":"+1 817 457 8874",
    "sg:postcode":"76120",
    "sg:province":"TX",
    "wof:name":"Shell",
    "wof:placetype":"venue"
},
  "geometry": {"coordinates":[-97.210852,32.766225],"type":"Point"}
}