{
  "type": "Feature",
  "properties": {
    "iso:country":"US",
    "sg:address":"18777 Midway Rd",
    "sg:city":"Dallas",
    "sg:classifiers":[
        {
            "category":"Professional",
            "subcategory":"Management & Consulting",
            "type":"Services"
        }
    ],
    "sg:phone":"+1 972 306 9454",
    "sg:postcode":"75287",
    "sg:province":"TX",
    "wof:name":"Philipbar Management Co L",
    "wof:placetype":"venue"
},
  "geometry": {"coordinates":[-96.843863,33.006587],"type":"Point"}
}