{
  "type": "Feature",
  "properties": {
    "iso:country":"US",
    "sg:address":"201 Esters Rd",
    "sg:city":"Irving",
    "sg:classifiers":[
        {
            "category":"Building & Trades",
            "subcategory":"Construction",
            "type":"Services"
        }
    ],
    "sg:phone":"+1 972 986 6573",
    "sg:postcode":"75061",
    "sg:province":"TX",
    "sg:tags":[
        "control",
        "flood",
        "equipment"
    ],
    "wof:name":"Dallas County Flood Control",
    "wof:placetype":"venue"
},
  "geometry": {"coordinates":[-97.00815,32.816604],"type":"Point"}
}