{
  "type": "Feature",
  "properties": {
    "iso:country":"US",
    "sg:address":"5706 Springfield Ave",
    "sg:city":"Laredo",
    "sg:classifiers":[
        {
            "category":"Shopping",
            "type":"Retail Goods"
        }
    ],
    "sg:phone":"+1 956 724 1972",
    "sg:postcode":"78041",
    "sg:province":"TX",
    "sg:tags":[
        "merchandise"
    ],
    "wof:name":"Printing Materials Inc",
    "wof:placetype":"venue"
},
  "geometry": {"coordinates":[-99.490061,27.551434],"type":"Point"}
}