{
  "type": "Feature",
  "properties": {
    "iso:country":"US",
    "sg:address":"202 W Expy 83",
    "sg:city":"Pharr",
    "sg:classifiers":[
        {
            "category":"Bars & Pubs",
            "type":"Food & Drink"
        }
    ],
    "sg:phone":"+1 956 782 9040",
    "sg:postcode":"78577",
    "sg:province":"TX",
    "wof:name":"Ramirez Bar",
    "wof:placetype":"venue"
},
  "geometry": {"coordinates":[-98.182514,26.207274],"type":"Point"}
}