{
  "type": "Feature",
  "properties": {
    "iso:country":"US",
    "sg:address":"8573 W 12th St",
    "sg:city":"Odessa",
    "sg:classifiers":[
        {
            "category":"Professional",
            "type":"Services"
        }
    ],
    "sg:phone":"+1 915 631 5641",
    "sg:postcode":"79763",
    "sg:province":"TX",
    "wof:name":"Delta Services",
    "wof:placetype":"venue"
},
  "geometry": {"coordinates":[-102.471807,31.829622],"type":"Point"}
}