{
  "type": "Feature",
  "properties": {
    "iso:country":"US",
    "sg:address":"128 E Main St",
    "sg:city":"Post",
    "sg:classifiers":[
        {
            "category":"Insurance",
            "subcategory":"Insurance Agent",
            "type":"Services"
        }
    ],
    "sg:phone":"+1 806 495 2894",
    "sg:postcode":"79356",
    "sg:province":"TX",
    "sg:tags":[
        "consultant"
    ],
    "wof:name":"Hoover Bookkeeping & Tax Svc",
    "wof:placetype":"venue"
},
  "geometry": {"coordinates":[-101.377944,33.191076],"type":"Point"}
}