{
  "type": "Feature",
  "properties": {
    "iso:country":"US",
    "sg:address":"12403 Shawwood Ct",
    "sg:city":"Houston",
    "sg:classifiers":[
        {
            "category":"Manufacturing",
            "subcategory":"Electronics",
            "type":"Manufacturing & Wholesale Goods"
        },
        {
            "category":"Shopping",
            "subcategory":"Computers & Home Electronics",
            "type":"Retail Goods"
        }
    ],
    "sg:phone":"+1 281 807 6348",
    "sg:postcode":"77070",
    "sg:province":"TX",
    "sg:tags":[
        "radio-wholesale",
        "television",
        "radio",
        "store",
        "manufacturer"
    ],
    "wof:name":"Telecom Multi Systems",
    "wof:placetype":"venue"
},
  "geometry": {"coordinates":[-95.560371,29.953672],"type":"Point"}
}