{
  "type": "Feature",
  "properties": {
    "iso:country":"US",
    "sg:address":"112 N Frazier St",
    "sg:city":"Conroe",
    "sg:classifiers":[
        {
            "category":"Retail",
            "subcategory":"Repair Shop",
            "type":"Services"
        }
    ],
    "sg:phone":"+1 936 539 4718",
    "sg:postcode":"77301",
    "sg:province":"TX",
    "sg:tags":[
        "equipment",
        "electronic",
        "supply"
    ],
    "wof:name":"Nicho's Auto Stereo Sound",
    "wof:placetype":"venue"
},
  "geometry": {"coordinates":[-95.460503,30.308639],"type":"Point"}
}