{
  "type": "Feature",
  "properties": {
    "iso:country":"US",
    "sg:address":"317 Wolschlaeger Dr",
    "sg:city":"Boerne",
    "sg:classifiers":[
        {
            "category":"Professional",
            "subcategory":"Management & Consulting",
            "type":"Services"
        }
    ],
    "sg:phone":"+1 830 249 0004",
    "sg:postcode":"78006",
    "sg:province":"TX",
    "sg:tags":[
        "business"
    ],
    "wof:name":"Realty Marketing & Consulting",
    "wof:placetype":"venue"
},
  "geometry": {"coordinates":[-98.745153,29.824896],"type":"Point"}
}