{
  "type": "Feature",
  "properties": {
    "iso:country":"US",
    "sg:address":"1090 Redfish St",
    "sg:city":"Hitchcock",
    "sg:classifiers":[
        {
            "category":"Wholesale",
            "subcategory":"Stationery",
            "type":"Manufacturing & Wholesale Goods"
        }
    ],
    "sg:phone":"+1 409 933 0747",
    "sg:postcode":"77563",
    "sg:province":"TX",
    "sg:tags":[
        "business",
        "form",
        "advertising"
    ],
    "wof:name":"South Shore Promotions",
    "wof:placetype":"venue"
},
  "geometry": {"coordinates":[-94.93871,29.322851],"type":"Point"}
}