{
  "type": "Feature",
  "properties": {
    "iso:country":"US",
    "sg:address":"5095 E 14th St",
    "sg:city":"Brownsville",
    "sg:classifiers":[
        {
            "category":"Insurance",
            "subcategory":"Insurance Agent",
            "type":"Services"
        }
    ],
    "sg:phone":"+1 956 831 4806",
    "sg:postcode":"78521",
    "sg:province":"TX",
    "wof:name":"Insurance Central Agency",
    "wof:placetype":"venue"
},
  "geometry": {"coordinates":[-97.460688,25.92394],"type":"Point"}
}