{
  "type": "Feature",
  "properties": {
    "iso:country":"US",
    "sg:address":"4019 Belle Grove St",
    "sg:city":"San Antonio",
    "sg:classifiers":[
        {
            "category":"Real Estate",
            "subcategory":"Real Estate Agent",
            "type":"Services"
        }
    ],
    "sg:phone":"+1 210 696 4409",
    "sg:postcode":"78230",
    "sg:province":"TX",
    "wof:name":"T C F Services and Texas Realt",
    "wof:placetype":"venue"
},
  "geometry": {"coordinates":[-98.566119,29.544501],"type":"Point"}
}