{
  "type": "Feature",
  "properties": {
    "iso:country":"US",
    "sg:address":"205 S Spruce St",
    "sg:city":"Vivian",
    "sg:classifiers":[
        {
            "category":"Mining & Drilling",
            "type":"Manufacturing & Wholesale Goods"
        }
    ],
    "sg:phone":"+1 318 375 2375",
    "sg:postcode":"71082",
    "sg:province":"TX",
    "sg:tags":[
        "oil",
        "gas",
        "producer"
    ],
    "wof:name":"Dempsey Oil Co",
    "wof:placetype":"venue"
},
  "geometry": {"coordinates":[-93.98842399999999,32.871531],"type":"Point"}
}