{
  "type": "Feature",
  "properties": {
    "iso:country":"US",
    "sg:address":"101 W Goodwin Ave",
    "sg:city":"Victoria",
    "sg:classifiers":[
        {
            "category":"Health Services",
            "subcategory":"Health Practitioner",
            "type":"Services"
        },
        {
            "category":"Social Services",
            "type":"Services"
        }
    ],
    "sg:phone":"+1 361 575 1049",
    "sg:postcode":"77901",
    "sg:province":"TX",
    "sg:tags":[
        "counseling"
    ],
    "wof:name":"Sharon Stubblefield PHD",
    "wof:placetype":"venue"
},
  "geometry": {"coordinates":[-97.005865,28.800952],"type":"Point"}
}