{
  "type": "Feature",
  "properties": {
    "iso:country":"US",
    "sg:address":"8103 Broadway",
    "sg:city":"San Antonio",
    "sg:classifiers":[
        {
            "category":"Retail",
            "subcategory":"Laundry & Dry Cleaning",
            "type":"Services"
        },
        {
            "category":"Shopping",
            "subcategory":"Clothing, Apparel, & Fashions",
            "type":"Retail Goods"
        }
    ],
    "sg:phone":"+1 210 826 7871",
    "sg:postcode":"78209",
    "sg:province":"TX",
    "sg:tags":[
        "tailor"
    ],
    "wof:name":"Chicago Custom Tailor Shop",
    "wof:placetype":"venue"
},
  "geometry": {"coordinates":[-98.466264,29.510761],"type":"Point"}
}