{
  "type": "Feature",
  "properties": {
    "iso:country":"US",
    "sg:address":"1554 S Alabama St",
    "sg:city":"Amarillo",
    "sg:classifiers":[
        {
            "category":"Shopping",
            "subcategory":"Computers & Home Electronics",
            "type":"Retail Goods"
        }
    ],
    "sg:phone":"+1 806 359 1072",
    "sg:postcode":"79102",
    "sg:province":"TX",
    "sg:tags":[
        "consulting",
        "management"
    ],
    "wof:name":"Lmv Management",
    "wof:placetype":"venue"
},
  "geometry": {"coordinates":[-101.870543,35.198292],"type":"Point"}
}