{
  "type": "Feature",
  "properties": {
    "iso:country":"US",
    "sg:address":"15502 Silver Ridge Dr",
    "sg:city":"Houston",
    "sg:classifiers":[
        {
            "category":"Health Services",
            "subcategory":"Clinic",
            "type":"Services"
        }
    ],
    "sg:phone":"+1 281 586 0375",
    "sg:postcode":"77090",
    "sg:province":"TX",
    "sg:tags":[
        "information",
        "mental"
    ],
    "wof:name":"Silver Ridge CMHC",
    "wof:placetype":"venue"
},
  "geometry": {"coordinates":[-95.454741,30.006685],"type":"Point"}
}