{
  "type": "Feature",
  "properties": {
    "iso:country":"US",
    "sg:address":"32531 Hepplewhite Dr",
    "sg:city":"Brookshire",
    "sg:classifiers":[
        {
            "category":"Farming",
            "subcategory":"Orchard",
            "type":"Manufacturing & Wholesale Goods"
        }
    ],
    "sg:phone":"+1 281 346 1123",
    "sg:postcode":"77423",
    "sg:province":"TX",
    "sg:tags":[
        "fruit",
        "tree"
    ],
    "wof:name":"Paul Lueder",
    "wof:placetype":"venue"
},
  "geometry": {"coordinates":[-95.939615,29.730157],"type":"Point"}
}