{
  "type": "Feature",
  "properties": {
    "iso:country":"US",
    "sg:address":"12203 Arrowwood Dr",
    "sg:city":"Austin",
    "sg:classifiers":[
        {
            "category":"Banks & Credit Unions",
            "subcategory":"Bank",
            "type":"Services"
        }
    ],
    "sg:phone":"+1 512 491 6071",
    "sg:postcode":"78727",
    "sg:province":"TX",
    "sg:tags":[
        "mortgage"
    ],
    "wof:name":"Beacon Innovative Mortgage Fin",
    "wof:placetype":"venue"
},
  "geometry": {"coordinates":[-97.726176,30.421679],"type":"Point"}
}