{
  "type": "Feature",
  "properties": {
    "iso:country":"US",
    "sg:address":"2428 Woodlawn Blvd",
    "sg:city":"Denison",
    "sg:classifiers":[
        {
            "category":"Autos & Motor Vehicles",
            "subcategory":"Auto Supplies",
            "type":"Retail Goods"
        }
    ],
    "sg:phone":"+1 903 465 5799",
    "sg:postcode":"75020",
    "sg:province":"TX",
    "wof:name":"Affordable Parts",
    "wof:placetype":"venue"
},
  "geometry": {"coordinates":[-96.555421,33.730102],"type":"Point"}
}