{
  "type": "Feature",
  "properties": {
    "iso:country":"US",
    "sg:address":"6700 Ingram Rd",
    "sg:city":"San Antonio",
    "sg:classifiers":[
        {
            "category":"Retail",
            "subcategory":"Auto Repair",
            "type":"Services"
        }
    ],
    "sg:phone":"+1 210 681 7428",
    "sg:postcode":"78238",
    "sg:province":"TX",
    "sg:tags":[
        "lubrication"
    ],
    "wof:name":"Jiffy Lube",
    "wof:placetype":"venue"
},
  "geometry": {"coordinates":[-98.622878,29.465221],"type":"Point"}
}