{
  "type": "Feature",
  "properties": {
    "iso:country":"US",
    "sg:address":"4614 Gessner Dr",
    "sg:city":"Houston",
    "sg:classifiers":[
        {
            "category":"Shopping",
            "subcategory":"Gifts & Souvenirs",
            "type":"Retail Goods"
        }
    ],
    "sg:phone":"+1 281 895 6250",
    "sg:postcode":"77041",
    "sg:province":"TX",
    "wof:name":"Gifts By Sherri",
    "wof:placetype":"venue"
},
  "geometry": {"coordinates":[-95.54499,29.839618],"type":"Point"}
}