{
  "type": "Feature",
  "properties": {
    "iso:country":"US",
    "sg:address":"315 Capitol St Ste 120",
    "sg:city":"Houston",
    "sg:classifiers":[
        {
            "category":"Professional",
            "subcategory":"Employment Agencies",
            "type":"Services"
        }
    ],
    "sg:phone":"+1 713 520 0155",
    "sg:postcode":"77002",
    "sg:province":"TX",
    "sg:tags":[
        "employer"
    ],
    "wof:name":"Houston Chapter American Institute Of Architects",
    "wof:placetype":"venue"
},
  "geometry": {"coordinates":[-95.36913,29.76244],"type":"Point"}
}