{
  "type": "Feature",
  "properties": {
    "iso:country":"US",
    "sg:address":"5008 Sand Beach Rd",
    "sg:city":"Wichita Falls",
    "sg:classifiers":[
        {
            "category":"Manufacturing",
            "subcategory":"Tools & Machinery",
            "type":"Manufacturing & Wholesale Goods"
        },
        {
            "category":"Manufacturing",
            "subcategory":"Toys & Sporting Goods",
            "type":"Manufacturing & Wholesale Goods"
        }
    ],
    "sg:phone":"+1 940 692 4475",
    "sg:postcode":"76310",
    "sg:province":"TX",
    "sg:tags":[
        "supply",
        "mfg",
        "accessory",
        "machine",
        "hobby",
        "model"
    ],
    "wof:name":"Ray Nor Products Inc",
    "wof:placetype":"venue"
},
  "geometry": {"coordinates":[-98.56777099999999,33.846033],"type":"Point"}
}