{
  "type": "Feature",
  "properties": {
    "iso:country":"US",
    "sg:address":"12403 Mellow Meadow Drive Ofc",
    "sg:city":"Austin",
    "sg:classifiers":[
        {
            "category":"Real Estate",
            "subcategory":"Real Estate Operator",
            "type":"Services"
        }
    ],
    "sg:phone":"+1 512 331 5872",
    "sg:postcode":"78750",
    "sg:province":"TX",
    "sg:tags":[
        "apartment"
    ],
    "wof:name":"Westwood Apartments",
    "wof:placetype":"venue"
},
  "geometry": {"coordinates":[-97.796909,30.456936],"type":"Point"}
}