{
  "type": "Feature",
  "properties": {
    "iso:country":"US",
    "sg:address":"2345 Dalworth St",
    "sg:city":"Grand Prairie",
    "sg:classifiers":[
        {
            "category":"Building & Trades",
            "subcategory":"Construction",
            "type":"Services"
        }
    ],
    "sg:phone":"+1 817 961 0083",
    "sg:postcode":"75050",
    "sg:province":"TX",
    "sg:tags":[
        "industrial"
    ],
    "wof:name":"Lauren & Mathew Price",
    "wof:placetype":"venue"
},
  "geometry": {"coordinates":[-97.037481,32.744622],"type":"Point"}
}