{
  "type": "Feature",
  "properties": {
    "iso:country":"US",
    "sg:address":"4407 Monterey Oaks Boulevard",
    "sg:city":"Austin",
    "sg:classifiers":[
        {
            "category":"Restaurant",
            "type":"Food & Drink"
        }
    ],
    "sg:phone":"+1 512 892 1482",
    "sg:postcode":"78749",
    "sg:province":"TX",
    "sg:website":"www.fuddruckers.com",
    "wof:name":"Fuddruckers",
    "wof:placetype":"venue"
},
  "geometry": {"coordinates":[-97.836609,30.230371],"type":"Point"}
}