{
  "type": "Feature",
  "properties": {
    "iso:country":"US",
    "sg:address":"12850 Memorial Dr",
    "sg:city":"Houston",
    "sg:classifiers":[
        {
            "category":"Food & Beverages",
            "subcategory":"Groceries & Convenience Stores",
            "type":"Retail Goods"
        }
    ],
    "sg:phone":"+1 713 365 6700",
    "sg:postcode":"77024",
    "sg:province":"TX",
    "wof:name":"Randall's",
    "wof:placetype":"venue"
},
  "geometry": {"coordinates":[-95.56082000000001,29.772852],"type":"Point"}
}