{
  "type": "Feature",
  "properties": {
    "iso:country":"US",
    "sg:address":"323 Elaine St",
    "sg:city":"La Marque",
    "sg:classifiers":[
        {
            "category":"Professional",
            "type":"Services"
        }
    ],
    "sg:phone":"+1 409 938 7703",
    "sg:postcode":"77568",
    "sg:province":"TX",
    "wof:name":"Aerotec Services",
    "wof:placetype":"venue"
},
  "geometry": {"coordinates":[-94.95553,29.371487],"type":"Point"}
}