{
  "type": "Feature",
  "properties": {
    "iso:country":"US",
    "sg:address":"919 W Northwest Hwy",
    "sg:city":"Grapevine",
    "sg:classifiers":[
        {
            "category":"Professional",
            "subcategory":"Management & Consulting",
            "type":"Services"
        }
    ],
    "sg:phone":"+1 817 329 7744",
    "sg:postcode":"76051",
    "sg:province":"TX",
    "wof:name":"Casey Land Management Inc",
    "wof:placetype":"venue"
},
  "geometry": {"coordinates":[-97.086692,32.941006],"type":"Point"}
}