{
  "type": "Feature",
  "properties": {
    "iso:country":"US",
    "sg:address":"3230 Sylvan Ave",
    "sg:city":"Dallas",
    "sg:classifiers":[
        {
            "category":"Shopping",
            "subcategory":"Music",
            "type":"Retail Goods"
        }
    ],
    "sg:phone":"+1 214 749 1282",
    "sg:postcode":"75212",
    "sg:province":"TX",
    "wof:name":"Morales Cassettes",
    "wof:placetype":"venue"
},
  "geometry": {"coordinates":[-96.835723,32.781189],"type":"Point"}
}