{
  "type": "Feature",
  "properties": {
    "iso:country":"US",
    "sg:address":"2300 Bill Owens Pkwy",
    "sg:city":"Longview",
    "sg:classifiers":[
        {
            "category":"Building & Trades",
            "subcategory":"Landscaping Services",
            "type":"Services"
        }
    ],
    "sg:phone":"+1 903 297 6522",
    "sg:postcode":"75604",
    "sg:province":"TX",
    "sg:tags":[
        "lawn",
        "maintenance",
        "grounds"
    ],
    "wof:name":"C & B Lawn Svc",
    "wof:placetype":"venue"
},
  "geometry": {"coordinates":[-94.764814,32.527806],"type":"Point"}
}