{
  "type": "Feature",
  "properties": {
    "iso:country":"US",
    "sg:address":"220 Co Rd 470",
    "sg:city":"De Leon",
    "sg:classifiers":[
        {
            "category":"Professional",
            "subcategory":"Engineering",
            "type":"Services"
        },
        {
            "category":"Professional",
            "type":"Services"
        }
    ],
    "sg:phone":"+1 254 893 2327",
    "sg:postcode":"76444",
    "sg:province":"TX",
    "sg:tags":[
        "establishment",
        "engineer"
    ],
    "wof:name":"RRLM Strategies Inc",
    "wof:placetype":"venue"
},
  "geometry": {"coordinates":[-98.487177,32.096998],"type":"Point"}
}