{
  "type": "Feature",
  "properties": {
    "iso:country":"US",
    "sg:address":"805 Dumont St",
    "sg:city":"South Houston",
    "sg:classifiers":[
        {
            "category":"Retail",
            "subcategory":"Repair Shop",
            "type":"Services"
        }
    ],
    "sg:phone":"+1 713 943 0658",
    "sg:postcode":"77587",
    "sg:province":"TX",
    "sg:tags":[
        "satellite",
        "system"
    ],
    "wof:name":"Digistar Broadban",
    "wof:placetype":"venue"
},
  "geometry": {"coordinates":[-95.238513,29.667494],"type":"Point"}
}