{
  "type": "Feature",
  "properties": {
    "iso:country":"US",
    "sg:address":"6757 Arapaho Rd",
    "sg:city":"Dallas",
    "sg:classifiers":[
        {
            "category":"Arts & Performance",
            "subcategory":"Theater",
            "type":"Entertainment"
        }
    ],
    "sg:phone":"+1 972 416 0251",
    "sg:postcode":"75248",
    "sg:province":"TX",
    "sg:tags":[
        "group"
    ],
    "wof:name":"Mecca Management",
    "wof:placetype":"venue"
},
  "geometry": {"coordinates":[-96.792644,32.962783],"type":"Point"}
}