{
  "type": "Feature",
  "properties": {
    "iso:country":"US",
    "sg:address":"3609 Old Post Rd",
    "sg:city":"San Angelo",
    "sg:classifiers":[
        {
            "category":"Building & Trades",
            "subcategory":"Construction",
            "type":"Services"
        }
    ],
    "sg:phone":"+1 325 944 8078",
    "sg:postcode":"76904",
    "sg:province":"TX",
    "sg:tags":[
        "hanging",
        "contractor"
    ],
    "wof:name":"Mike Adams Painting",
    "wof:placetype":"venue"
},
  "geometry": {"coordinates":[-100.485302,31.433747],"type":"Point"}
}