{
  "type": "Feature",
  "properties": {
    "iso:country":"US",
    "sg:address":"2217 Lake Haven Ln",
    "sg:city":"Denton",
    "sg:classifiers":[
        {
            "category":"Professional",
            "subcategory":"Accounting & Tax Preparation",
            "type":"Services"
        }
    ],
    "sg:phone":"+1 940 387 1047",
    "sg:postcode":"76208",
    "sg:province":"TX",
    "wof:name":"Corporate Finan MGT Small Bus",
    "wof:placetype":"venue"
},
  "geometry": {"coordinates":[-97.049165,33.196626],"type":"Point"}
}