{
  "type": "Feature",
  "properties": {
    "iso:country":"US",
    "sg:address":"3858 South Fwy",
    "sg:city":"Fort Worth",
    "sg:classifiers":[
        {
            "category":"Personal",
            "subcategory":"Barber",
            "type":"Services"
        }
    ],
    "sg:phone":"+1 817 923 7702",
    "sg:postcode":"76110",
    "sg:province":"TX",
    "sg:tags":[
        "shop"
    ],
    "wof:name":"Casino's Hair Cut & Style",
    "wof:placetype":"venue"
},
  "geometry": {"coordinates":[-97.321034,32.691193],"type":"Point"}
}