{
  "type": "Feature",
  "properties": {
    "iso:country":"US",
    "sg:address":"4410 Devon Dr",
    "sg:city":"Corpus Christi",
    "sg:classifiers":[
        {
            "category":"Building & Trades",
            "subcategory":"Plumbing",
            "type":"Services"
        }
    ],
    "sg:phone":"+1 361 857 5893",
    "sg:postcode":"78415",
    "sg:province":"TX",
    "sg:tags":[
        "refrigeration",
        "contractor"
    ],
    "wof:name":"Rangel Placido Air Cond & Htg",
    "wof:placetype":"venue"
},
  "geometry": {"coordinates":[-97.413358,27.741542],"type":"Point"}
}