{
  "type": "Feature",
  "properties": {
    "iso:country":"US",
    "sg:address":"10875 Shady Trl Ste 105",
    "sg:city":"Dallas",
    "sg:classifiers":[
        {
            "category":"Autos & Motor Vehicles",
            "subcategory":"Motorcycle Sales",
            "type":"Retail Goods"
        }
    ],
    "sg:phone":"+1 214 351 4555",
    "sg:postcode":"75220",
    "sg:province":"TX",
    "wof:name":"Sabin Performance Cycles",
    "wof:placetype":"venue"
},
  "geometry": {"coordinates":[-96.890297,32.8778],"type":"Point"}
}