{
  "type": "Feature",
  "properties": {
    "iso:country":"US",
    "sg:address":"813 Santa Fe Dr",
    "sg:city":"Weatherford",
    "sg:classifiers":[
        {
            "category":"Wholesale",
            "subcategory":"Medical Equipment & Supplies",
            "type":"Manufacturing & Wholesale Goods"
        }
    ],
    "sg:phone":"+1 817 341 7551",
    "sg:postcode":"76086",
    "sg:province":"TX",
    "sg:tags":[
        "physician",
        "surgeon"
    ],
    "wof:name":"Healthline",
    "wof:placetype":"venue"
},
  "geometry": {"coordinates":[-97.78569899999999,32.750622],"type":"Point"}
}