{
  "type": "Feature",
  "properties": {
    "iso:country":"US",
    "sg:address":"210 Bluffcrest",
    "sg:city":"San Antonio",
    "sg:classifiers":[
        {
            "category":"Professional",
            "type":"Services"
        },
        {
            "category":"Building & Trades",
            "subcategory":"Construction",
            "type":"Services"
        }
    ],
    "sg:phone":"+1 210 402 3746",
    "sg:postcode":"78216",
    "sg:province":"TX",
    "sg:tags":[
        "hanging",
        "contractor"
    ],
    "wof:name":"Annabelle's Painted Finish",
    "wof:placetype":"venue"
},
  "geometry": {"coordinates":[-98.500552,29.5647],"type":"Point"}
}