{
  "type": "Feature",
  "properties": {
    "iso:country":"US",
    "sg:address":"501 Porter St",
    "sg:city":"San Antonio",
    "sg:classifiers":[
        {
            "category":"Wholesale",
            "subcategory":"Auto Parts",
            "type":"Manufacturing & Wholesale Goods"
        }
    ],
    "sg:phone":"+1 210 532 2216",
    "sg:postcode":"78210",
    "sg:province":"TX",
    "sg:tags":[
        "tire"
    ],
    "wof:name":"Flores Tire Shop",
    "wof:placetype":"venue"
},
  "geometry": {"coordinates":[-98.458984,29.405901],"type":"Point"}
}