{
  "type": "Feature",
  "properties": {
    "iso:country":"US",
    "sg:address":"13301 Beaumont Hwy",
    "sg:city":"Houston",
    "sg:classifiers":[
        {
            "category":"Freight",
            "type":"Transportation"
        }
    ],
    "sg:phone":"+1 281 458 8202",
    "sg:postcode":"77049",
    "sg:province":"TX",
    "sg:tags":[
        "general"
    ],
    "wof:name":"Chen International Corp",
    "wof:placetype":"venue"
},
  "geometry": {"coordinates":[-95.18912899999999,29.841632],"type":"Point"}
}