{
  "type": "Feature",
  "properties": {
    "iso:country":"US",
    "sg:address":"8773 W Bellfort St",
    "sg:city":"Houston",
    "sg:classifiers":[
        {
            "category":"Professional",
            "subcategory":"Accounting & Tax Preparation",
            "type":"Services"
        }
    ],
    "sg:phone":"+1 713 271 2226",
    "sg:postcode":"77031",
    "sg:province":"TX",
    "sg:tags":[
        "return",
        "filing"
    ],
    "wof:name":"H & R Block Tax Svc",
    "wof:placetype":"venue"
},
  "geometry": {"coordinates":[-95.53107900000001,29.656051],"type":"Point"}
}