{
  "type": "Feature",
  "properties": {
    "iso:country":"US",
    "sg:address":"624 Pasadena Blvd",
    "sg:city":"Pasadena",
    "sg:classifiers":[
        {
            "category":"Organizations",
            "subcategory":"Community Association",
            "type":"Services"
        }
    ],
    "sg:phone":"+1 713 477 3563",
    "sg:postcode":"77506",
    "sg:province":"TX",
    "wof:name":"Katyrotary",
    "wof:placetype":"venue"
},
  "geometry": {"coordinates":[-95.20106199999999,29.701812],"type":"Point"}
}