{
  "type": "Feature",
  "properties": {
    "iso:country":"US",
    "sg:address":"3530 Forest Ln",
    "sg:city":"Dallas",
    "sg:classifiers":[
        {
            "category":"Personal",
            "type":"Services"
        },
        {
            "category":"Shopping",
            "subcategory":"Clothing, Apparel, & Fashions",
            "type":"Retail Goods"
        }
    ],
    "sg:phone":"+1 214 366 3996",
    "sg:postcode":"75234",
    "sg:province":"TX",
    "sg:tags":[
        "hair",
        "supply",
        "replacement"
    ],
    "wof:name":"Hair Center Of Texas & Hair",
    "wof:placetype":"venue"
},
  "geometry": {"coordinates":[-96.860592,32.90964],"type":"Point"}
}