{
  "type": "Feature",
  "properties": {
    "iso:country":"US",
    "sg:address":"7786 Riley Rd",
    "sg:city":"Bryan",
    "sg:classifiers":[
        {
            "category":"Retail",
            "subcategory":"Animal Services",
            "type":"Services"
        }
    ],
    "sg:phone":"+1 979 589 1638",
    "sg:postcode":"77808",
    "sg:province":"TX",
    "sg:tags":[
        "breeder",
        "horse"
    ],
    "sg:website":"www.royallegend.com",
    "wof:name":"Royal Legend Arabian Horse Fms",
    "wof:placetype":"venue"
},
  "geometry": {"coordinates":[-96.223755,30.735311],"type":"Point"}
}