{
  "type": "Feature",
  "properties": {
    "iso:country":"US",
    "sg:address":"6434 Maple Ave",
    "sg:city":"Dallas",
    "sg:classifiers":[
        {
            "category":"Government",
            "subcategory":"Court House",
            "type":"Public Place"
        }
    ],
    "sg:phone":"+1 214 630 8887",
    "sg:postcode":"75235",
    "sg:province":"TX",
    "sg:tags":[
        "state",
        "counsel"
    ],
    "wof:name":"Attorney General",
    "wof:placetype":"venue"
},
  "geometry": {"coordinates":[-96.842448,32.826353],"type":"Point"}
}