{
  "type": "Feature",
  "properties": {
    "iso:country":"US",
    "sg:address":"1101 State Hwy 87",
    "sg:city":"Port Bolivar",
    "sg:classifiers":[
        {
            "category":"Restaurant",
            "type":"Food & Drink"
        }
    ],
    "sg:phone":"+1 409 684 4095",
    "sg:postcode":"77650",
    "sg:province":"TX",
    "sg:tags":[
        "eating"
    ],
    "wof:name":"Newtons Burger Shack",
    "wof:placetype":"venue"
},
  "geometry": {"coordinates":[-94.66779200000001,29.441222],"type":"Point"}
}