{
  "type": "Feature",
  "properties": {
    "iso:country":"US",
    "sg:address":"7401 E Ben White Blvd",
    "sg:city":"Austin",
    "sg:classifiers":[
        {
            "category":"Professional",
            "subcategory":"Business Services",
            "type":"Services"
        }
    ],
    "sg:phone":"+1 512 356 1000",
    "sg:postcode":"78741",
    "sg:province":"TX",
    "wof:name":"G M Sitel",
    "wof:placetype":"venue"
},
  "geometry": {"coordinates":[-97.688149,30.219462],"type":"Point"}
}