{
  "type": "Feature",
  "properties": {
    "iso:country":"US",
    "sg:address":"5107 Fairmont Dr",
    "sg:city":"Arlington",
    "sg:classifiers":[
        {
            "category":"Wholesale",
            "subcategory":"Vending Machines",
            "type":"Manufacturing & Wholesale Goods"
        }
    ],
    "sg:phone":"+1 817 468 8265",
    "sg:postcode":"76017",
    "sg:province":"TX",
    "sg:tags":[
        "operator"
    ],
    "wof:name":"ECL Services",
    "wof:placetype":"venue"
},
  "geometry": {"coordinates":[-97.165997,32.664436],"type":"Point"}
}