{
  "type": "Feature",
  "properties": {
    "iso:country":"US",
    "sg:address":"1501 NE 28th St",
    "sg:city":"Fort Worth",
    "sg:classifiers":[
        {
            "category":"Travel",
            "subcategory":"Hotels & Motels",
            "type":"Entertainment"
        }
    ],
    "sg:phone":"+1 817 625 9741",
    "sg:postcode":"76106",
    "sg:province":"TX",
    "wof:name":"Peppermint Motel",
    "wof:placetype":"venue"
},
  "geometry": {"coordinates":[-97.336004,32.795164],"type":"Point"}
}