{
  "type": "Feature",
  "properties": {
    "iso:country":"US",
    "sg:address":"12618 Cardiff Rd",
    "sg:city":"Houston",
    "sg:classifiers":[
        {
            "category":"Professional",
            "subcategory":"Business Services",
            "type":"Services"
        }
    ],
    "sg:phone":"+1 832 216 7518",
    "sg:postcode":"77037",
    "sg:province":"TX",
    "sg:tags":[
        "notary"
    ],
    "wof:name":"Maria's Notary & Multi Svc",
    "wof:placetype":"venue"
},
  "geometry": {"coordinates":[-95.369703,29.883086],"type":"Point"}
}