{
  "type": "Feature",
  "properties": {
    "iso:country":"US",
    "sg:address":"96 N 7th St",
    "sg:city":"Beaumont",
    "sg:classifiers":[
        {
            "category":"Building & Trades",
            "subcategory":"Construction",
            "type":"Services"
        }
    ],
    "sg:phone":"+1 409 832 7296",
    "sg:postcode":"77702",
    "sg:province":"TX",
    "sg:tags":[
        "contractor",
        "hanging"
    ],
    "wof:name":"Anderson",
    "wof:placetype":"venue"
},
  "geometry": {"coordinates":[-94.119927,30.080986],"type":"Point"}
}