{
  "type": "Feature",
  "properties": {
    "iso:country":"US",
    "sg:address":"1925 E Belt Line Rd",
    "sg:city":"Carrollton",
    "sg:classifiers":[
        {
            "category":"Building & Trades",
            "subcategory":"Plumbing",
            "type":"Services"
        }
    ],
    "sg:phone":"+1 972 418 9388",
    "sg:postcode":"75006",
    "sg:province":"TX",
    "sg:tags":[
        "contractor"
    ],
    "wof:name":"Climatrol Systems",
    "wof:placetype":"venue"
},
  "geometry": {"coordinates":[-96.88746,32.95375],"type":"Point"}
}