{
  "type": "Feature",
  "properties": {
    "iso:country":"US",
    "sg:address":"1427 Branard St",
    "sg:city":"Houston",
    "sg:classifiers":[
        {
            "category":"Museum",
            "type":"Entertainment"
        }
    ],
    "sg:phone":"+1 713 524 5050",
    "sg:postcode":"77006",
    "sg:province":"TX",
    "sg:tags":[
        "information",
        "performing",
        "art"
    ],
    "sg:website":"www.dacamera.com",
    "wof:name":"Da Camera",
    "wof:placetype":"venue"
},
  "geometry": {"coordinates":[-95.397301,29.736799],"type":"Point"}
}