{
  "type": "Feature",
  "properties": {
    "iso:country":"US",
    "sg:address":"1301 S Alice Ave",
    "sg:city":"Monahans",
    "sg:classifiers":[
        {
            "category":"Social Services",
            "subcategory":"Child Care",
            "type":"Services"
        }
    ],
    "sg:phone":"+1 432 943 4433",
    "sg:postcode":"79756",
    "sg:province":"TX",
    "sg:tags":[
        "day"
    ],
    "wof:name":"Little Rugrats",
    "wof:placetype":"venue"
},
  "geometry": {"coordinates":[-102.88964799999999,31.582672],"type":"Point"}
}