{
  "type": "Feature",
  "properties": {
    "iso:country":"US",
    "sg:address":"3501 N Macarthur Blvd # 350",
    "sg:city":"Irving",
    "sg:classifiers":[
        {
            "category":"Community Center",
            "subcategory":"Senior",
            "type":"Public Place"
        },
        {
            "category":"Social Services",
            "subcategory":"Adult Care",
            "type":"Services"
        }
    ],
    "sg:phone":"+1 972 257 5300",
    "sg:postcode":"75062",
    "sg:province":"TX",
    "sg:tags":[
        "counseling",
        "citizen"
    ],
    "wof:name":"Senior Simplicity Care",
    "wof:placetype":"venue"
},
  "geometry": {"coordinates":[-96.95910600000001,32.851557],"type":"Point"}
}