{
  "type": "Feature",
  "properties": {
    "iso:country":"US",
    "sg:address":"3965 Phelan Blvd",
    "sg:city":"Beaumont",
    "sg:classifiers":[
        {
            "category":"Health Services",
            "subcategory":"Chiropractor",
            "type":"Services"
        }
    ],
    "sg:phone":"+1 409 835 7676",
    "sg:postcode":"77707",
    "sg:province":"TX",
    "wof:name":"Complete Care Chiropractic",
    "wof:placetype":"venue"
},
  "geometry": {"coordinates":[-94.143833,30.084536],"type":"Point"}
}