{
  "type": "Feature",
  "properties": {
    "iso:country":"US",
    "sg:address":"1313 N Fry Rd",
    "sg:city":"Katy",
    "sg:classifiers":[
        {
            "category":"Shopping",
            "subcategory":"Department Store",
            "type":"Retail Goods"
        }
    ],
    "sg:phone":"+1 281 577 7007",
    "sg:postcode":"77449",
    "sg:province":"TX",
    "sg:tags":[
        "grocery"
    ],
    "wof:name":"Wal-Mart",
    "wof:placetype":"venue"
},
  "geometry": {"coordinates":[-95.71899500000001,29.786548],"type":"Point"}
}