{
  "type": "Feature",
  "properties": {
    "iso:country":"US",
    "sg:address":"126 Meadowside Dr",
    "sg:city":"Hutto",
    "sg:classifiers":[
        {
            "category":"Professional",
            "subcategory":"Management & Consulting",
            "type":"Services"
        }
    ],
    "sg:phone":"+1 512 759 2281",
    "sg:postcode":"78634",
    "sg:province":"TX",
    "sg:tags":[
        "business"
    ],
    "wof:name":"Weis Miller Consultant",
    "wof:placetype":"venue"
},
  "geometry": {"coordinates":[-97.540631,30.535107],"type":"Point"}
}