{
  "type": "Feature",
  "properties": {
    "iso:country":"US",
    "sg:address":"1000 Lydia Street",
    "sg:city":"Austin",
    "sg:classifiers":[
        {
            "category":"Organizations",
            "subcategory":"Non-profit Organization",
            "type":"Services"
        }
    ],
    "sg:phone":"+1 512 479 6275",
    "sg:postcode":"78702",
    "sg:province":"TX",
    "sg:tags":[
        "service/non-profit",
        "community"
    ],
    "wof:name":"Guadalupe Neighborhood Development Corporation",
    "wof:placetype":"venue"
},
  "geometry": {"coordinates":[-97.72796700000001,30.268098],"type":"Point"}
}