{
  "type": "Feature",
  "properties": {
    "iso:country":"US",
    "sg:address":"527 Texas Ave",
    "sg:city":"Texas City",
    "sg:classifiers":[
        {
            "category":"Bars & Pubs",
            "type":"Food & Drink"
        }
    ],
    "sg:phone":"+1 409 948 8335",
    "sg:postcode":"77590",
    "sg:province":"TX",
    "sg:tags":[
        "drinking"
    ],
    "wof:name":"Little Doggie",
    "wof:placetype":"venue"
},
  "geometry": {"coordinates":[-94.902199,29.383973],"type":"Point"}
}