{
  "type": "Feature",
  "properties": {
    "iso:country":"US",
    "sg:address":"735 Pebble Creek Ln",
    "sg:city":"Mesquite",
    "sg:classifiers":[
        {
            "category":"Shopping",
            "subcategory":"Computers & Home Electronics",
            "type":"Retail Goods"
        }
    ],
    "sg:phone":"+1 972 285 0976",
    "sg:postcode":"75149",
    "sg:province":"TX",
    "sg:tags":[
        "software"
    ],
    "wof:name":"Creative Software Design",
    "wof:placetype":"venue"
},
  "geometry": {"coordinates":[-96.60302900000001,32.773898],"type":"Point"}
}