{
  "type": "Feature",
  "properties": {
    "iso:country":"US",
    "sg:address":"14665 Midway Rd",
    "sg:city":"Addison",
    "sg:classifiers":[
        {
            "category":"Health Services",
            "subcategory":"Nursing And Care Facility",
            "type":"Services"
        },
        {
            "category":"Health Services",
            "subcategory":"Clinic",
            "type":"Services"
        }
    ],
    "sg:phone":"+1 972 233 5504",
    "sg:postcode":"75001",
    "sg:province":"TX",
    "sg:tags":[
        "hospice",
        "home",
        "medical"
    ],
    "wof:name":"Total Concepts Hospice",
    "wof:placetype":"venue"
},
  "geometry": {"coordinates":[-96.839067,32.946697],"type":"Point"}
}