{
  "type": "Feature",
  "properties": {
    "iso:country":"US",
    "sg:address":"2513 Concord Ave",
    "sg:city":"Midland",
    "sg:classifiers":[
        {
            "category":"Shopping",
            "type":"Retail Goods"
        }
    ],
    "sg:phone":"+1 432 684 8250",
    "sg:postcode":"79705",
    "sg:province":"TX",
    "sg:tags":[
        "merchandise"
    ],
    "wof:name":"E R Grant",
    "wof:placetype":"venue"
},
  "geometry": {"coordinates":[-102.108828,32.009498],"type":"Point"}
}