{
  "type": "Feature",
  "properties": {
    "iso:country":"US",
    "sg:address":"4607 E Juan Linn St",
    "sg:city":"Victoria",
    "sg:classifiers":[
        {
            "category":"Wholesale",
            "subcategory":"Machinery & Supplies",
            "type":"Manufacturing & Wholesale Goods"
        }
    ],
    "sg:phone":"+1 361 576 2613",
    "sg:postcode":"77901",
    "sg:province":"TX",
    "sg:tags":[
        "equipment",
        "industrial"
    ],
    "wof:name":"J W Measurment",
    "wof:placetype":"venue"
},
  "geometry": {"coordinates":[-96.962158,28.782576],"type":"Point"}
}