{
  "type": "Feature",
  "properties": {
    "iso:country":"US",
    "sg:address":"508 Horizon Ct",
    "sg:city":"Plano",
    "sg:classifiers":[
        {
            "category":"Building & Trades",
            "subcategory":"Construction",
            "type":"Services"
        }
    ],
    "sg:phone":"+1 972 423 6025",
    "sg:postcode":"75094",
    "sg:province":"TX",
    "sg:tags":[
        "house"
    ],
    "wof:name":"Parrent Engineering Const",
    "wof:placetype":"venue"
},
  "geometry": {"coordinates":[-96.60086800000001,32.99566],"type":"Point"}
}