{
  "type": "Feature",
  "properties": {
    "iso:country":"US",
    "sg:address":"808 Lakebridge Dr",
    "sg:city":"Lake Dallas",
    "sg:classifiers":[
        {
            "category":"Shopping",
            "subcategory":"Discount & Variety Stores",
            "type":"Retail Goods"
        }
    ],
    "sg:phone":"+1 940 321 2414",
    "sg:postcode":"75065",
    "sg:province":"TX",
    "sg:tags":[
        "merchandise",
        "general"
    ],
    "wof:name":"Melissa Parker",
    "wof:placetype":"venue"
},
  "geometry": {"coordinates":[-97.017167,33.117302],"type":"Point"}
}