{
  "type": "Feature",
  "properties": {
    "iso:country":"US",
    "sg:address":"3330 N Galloway Ave Ste 158",
    "sg:city":"Mesquite",
    "sg:classifiers":[
        {
            "category":"Health Services",
            "subcategory":"Dentist",
            "type":"Services"
        }
    ],
    "sg:phone":"+1 972 613 0004",
    "sg:postcode":"75150",
    "sg:province":"TX",
    "sg:website":"craighays.dentistryonline.com",
    "wof:name":"Craig Hays, \u00a0DDS",
    "wof:placetype":"venue"
},
  "geometry": {"coordinates":[-96.609853,32.810644],"type":"Point"}
}