{
  "type": "Feature",
  "properties": {
    "iso:country":"US",
    "sg:address":"8105 Culebra Rd",
    "sg:city":"San Antonio",
    "sg:classifiers":[
        {
            "category":"Health Services",
            "subcategory":"Doctor",
            "type":"Services"
        }
    ],
    "sg:phone":"+1 210 681 9780",
    "sg:postcode":"78251",
    "sg:province":"TX",
    "sg:tags":[
        "dentist"
    ],
    "wof:name":"Family Dentistry",
    "wof:placetype":"venue"
},
  "geometry": {"coordinates":[-98.64694799999999,29.4667],"type":"Point"}
}