{
  "type": "Feature",
  "properties": {
    "iso:country":"US",
    "sg:address":"4928 Sigmond Dr",
    "sg:city":"Arlington",
    "sg:classifiers":[
        {
            "category":"Retail",
            "subcategory":"Repair Shop",
            "type":"Services"
        }
    ],
    "sg:phone":"+1 817 478 1675",
    "sg:postcode":"76017",
    "sg:province":"TX",
    "sg:tags":[
        "equipment",
        "medical"
    ],
    "wof:name":"Labserv Inc",
    "wof:placetype":"venue"
},
  "geometry": {"coordinates":[-97.21317000000001,32.66722],"type":"Point"}
}