{
  "type": "Feature",
  "properties": {
    "iso:country":"US",
    "sg:address":"7317 Vinson St",
    "sg:city":"Houston",
    "sg:classifiers":[
        {
            "category":"Organizations",
            "subcategory":"Religious Organization",
            "type":"Services"
        }
    ],
    "sg:phone":"+1 281 847 3370",
    "sg:postcode":"77088",
    "sg:province":"TX",
    "sg:tags":[
        "church"
    ],
    "wof:name":"Christ's Way Missionary Church",
    "wof:placetype":"venue"
},
  "geometry": {"coordinates":[-95.44275500000001,29.866833],"type":"Point"}
}