{
  "type": "Feature",
  "properties": {
    "iso:country":"US",
    "sg:address":"323 Old San Antonio Rd",
    "sg:city":"Cuero",
    "sg:classifiers":[
        {
            "category":"Wholesale",
            "subcategory":"Non-durable Goods",
            "type":"Manufacturing & Wholesale Goods"
        }
    ],
    "sg:phone":"+1 361 277 9416",
    "sg:postcode":"77954",
    "sg:province":"TX",
    "wof:name":"Haak Distributing Co",
    "wof:placetype":"venue"
},
  "geometry": {"coordinates":[-97.349486,29.089926],"type":"Point"}
}