{
  "type": "Feature",
  "properties": {
    "iso:country":"US",
    "sg:address":"1005 Howeth Dr",
    "sg:city":"Pflugerville",
    "sg:classifiers":[
        {
            "category":"Building & Trades",
            "subcategory":"Construction",
            "type":"Services"
        }
    ],
    "sg:phone":"+1 512 252 2056",
    "sg:postcode":"78660",
    "sg:province":"TX",
    "sg:tags":[
        "contractor"
    ],
    "wof:name":"Awesome Cleaning Services",
    "wof:placetype":"venue"
},
  "geometry": {"coordinates":[-97.634593,30.473193],"type":"Point"}
}