{
  "type": "Feature",
  "properties": {
    "iso:country":"US",
    "sg:address":"920 State Hwy 105",
    "sg:city":"Sour Lake",
    "sg:classifiers":[
        {
            "category":"Food & Beverages",
            "subcategory":"Liquor & Beverages",
            "type":"Retail Goods"
        }
    ],
    "sg:phone":"+1 409 287 3390",
    "sg:postcode":"77659",
    "sg:province":"TX",
    "wof:name":"Buddy's Package Store",
    "wof:placetype":"venue"
},
  "geometry": {"coordinates":[-94.390412,30.139544],"type":"Point"}
}