{
  "type": "Feature",
  "properties": {
    "iso:country":"US",
    "sg:address":"522 W Harwood Rd",
    "sg:city":"Hurst",
    "sg:classifiers":[
        {
            "category":"Recreation",
            "type":"Entertainment"
        }
    ],
    "sg:phone":"+1 817 788 2817",
    "sg:postcode":"76054",
    "sg:province":"TX",
    "wof:name":"Dynamic Tae KWON Do",
    "wof:placetype":"venue"
},
  "geometry": {"coordinates":[-97.179479,32.847122],"type":"Point"}
}