{
  "type": "Feature",
  "properties": {
    "iso:country":"US",
    "sg:address":"11972 Willowmist Ave",
    "sg:city":"El Paso",
    "sg:classifiers":[
        {
            "category":"Retail",
            "subcategory":"Laundry & Dry Cleaning",
            "type":"Services"
        }
    ],
    "sg:phone":"+1 915 921 0047",
    "sg:postcode":"79936",
    "sg:province":"TX",
    "wof:name":"I&L Clean Carpet",
    "wof:placetype":"venue"
},
  "geometry": {"coordinates":[-106.276166,31.797489],"type":"Point"}
}