{
  "type": "Feature",
  "properties": {
    "iso:country":"US",
    "sg:address":"119 N Texas Blvd",
    "sg:city":"Weslaco",
    "sg:classifiers":[
        {
            "category":"Building & Trades",
            "subcategory":"Construction",
            "type":"Services"
        }
    ],
    "sg:phone":"+1 956 969 0165",
    "sg:postcode":"78596",
    "sg:province":"TX",
    "sg:tags":[
        "contractor"
    ],
    "wof:name":"Reyna Construction",
    "wof:placetype":"venue"
},
  "geometry": {"coordinates":[-97.99066500000001,26.162726],"type":"Point"}
}