{
  "type": "Feature",
  "properties": {
    "iso:country":"US",
    "sg:address":"507 S Louise St",
    "sg:city":"Atlanta",
    "sg:classifiers":[
        {
            "category":"Personal",
            "subcategory":"Beauty Salon",
            "type":"Services"
        }
    ],
    "sg:phone":"+1 903 799 6717",
    "sg:postcode":"75551",
    "sg:province":"TX",
    "wof:name":"Sylvia's",
    "wof:placetype":"venue"
},
  "geometry": {"coordinates":[-94.171244,33.109995],"type":"Point"}
}