{
  "type": "Feature",
  "properties": {
    "iso:country":"US",
    "sg:address":"2701 Live Oak Rd",
    "sg:city":"Santo",
    "sg:classifiers":[
        {
            "category":"Wholesale",
            "subcategory":"Construction Materials",
            "type":"Manufacturing & Wholesale Goods"
        }
    ],
    "sg:phone":"+1 254 646 3601",
    "sg:postcode":"76472",
    "sg:province":"TX",
    "sg:tags":[
        "concrete",
        "product"
    ],
    "wof:name":"Decorative Concrete Finishes",
    "wof:placetype":"venue"
},
  "geometry": {"coordinates":[-98.09007,32.596457],"type":"Point"}
}