{
  "type": "Feature",
  "properties": {
    "iso:country":"US",
    "sg:address":"1287 Common St",
    "sg:city":"New Braunfels",
    "sg:classifiers":[
        {
            "category":"Banks & Credit Unions",
            "subcategory":"Bank",
            "type":"Services"
        }
    ],
    "sg:phone":"+1 830 606 4177",
    "sg:postcode":"78130",
    "sg:province":"TX",
    "sg:tags":[
        "mortgage"
    ],
    "wof:name":"P R Mortgage",
    "wof:placetype":"venue"
},
  "geometry": {"coordinates":[-98.105385,29.718959],"type":"Point"}
}