{
  "type": "Feature",
  "properties": {
    "iso:country":"US",
    "sg:address":"1430 N Main St",
    "sg:city":"Borger",
    "sg:classifiers":[
        {
            "category":"Building & Trades",
            "subcategory":"Construction",
            "type":"Services"
        }
    ],
    "sg:phone":"+1 806 273 7614",
    "sg:postcode":"79007",
    "sg:province":"TX",
    "sg:tags":[
        "contractor"
    ],
    "wof:name":"Service Abatement Co Inc",
    "wof:placetype":"venue"
},
  "geometry": {"coordinates":[-101.38981800000001,35.682933],"type":"Point"}
}