{
  "type": "Feature",
  "properties": {
    "iso:country":"US",
    "sg:address":"1734 Bethel Rd",
    "sg:city":"Weatherford",
    "sg:classifiers":[
        {
            "category":"Organizations",
            "subcategory":"Community Association",
            "type":"Services"
        }
    ],
    "sg:phone":"+1 817 613 1763",
    "sg:postcode":"76086",
    "sg:province":"TX",
    "sg:tags":[
        "club"
    ],
    "wof:name":"Live Oak Country Club",
    "wof:placetype":"venue"
},
  "geometry": {"coordinates":[-97.798694,32.737699],"type":"Point"}
}