{
  "type": "Feature",
  "properties": {
    "iso:country":"US",
    "sg:address":"6721 FM 1346",
    "sg:city":"San Antonio",
    "sg:classifiers":[
        {
            "category":"Food & Beverages",
            "subcategory":"Groceries & Convenience Stores",
            "type":"Retail Goods"
        }
    ],
    "sg:phone":"+1 210 661 0804",
    "sg:postcode":"78220",
    "sg:province":"TX",
    "wof:name":"Mr Kan Grocery",
    "wof:placetype":"venue"
},
  "geometry": {"coordinates":[-98.351479,29.418039],"type":"Point"}
}