{
  "type": "Feature",
  "properties": {
    "iso:country":"US",
    "sg:address":"8229 Meadow Hill Dr",
    "sg:city":"Frisco",
    "sg:classifiers":[
        {
            "category":"Shopping",
            "type":"Retail Goods"
        }
    ],
    "sg:phone":"+1 972 377 2749",
    "sg:postcode":"75034",
    "sg:province":"TX",
    "sg:tags":[
        "merchandise"
    ],
    "wof:name":"Bob T Dunfield",
    "wof:placetype":"venue"
},
  "geometry": {"coordinates":[-96.811938,33.162405],"type":"Point"}
}