{
  "type": "Feature",
  "properties": {
    "iso:country":"US",
    "sg:address":"8500 Cypresswood Dr 201B Ste 201 B",
    "sg:city":"Spring",
    "sg:classifiers":[
        {
            "category":"Manufacturing",
            "subcategory":"Metals",
            "type":"Manufacturing & Wholesale Goods"
        }
    ],
    "sg:phone":"+1 281 374 0099",
    "sg:postcode":"77379",
    "sg:province":"TX",
    "sg:tags":[
        "work",
        "iron"
    ],
    "wof:name":"Suncoast Steel",
    "wof:placetype":"venue"
},
  "geometry": {"coordinates":[-95.531981,30.001962],"type":"Point"}
}