{
  "type": "Feature",
  "properties": {
    "iso:country":"US",
    "sg:address":"14403 Wickhurst Pl",
    "sg:city":"Cypress",
    "sg:classifiers":[
        {
            "category":"Shopping",
            "subcategory":"Jewelry",
            "type":"Retail Goods"
        }
    ],
    "sg:phone":"+1 281 304 8718",
    "sg:postcode":"77429",
    "sg:province":"TX",
    "wof:name":"K Adornments",
    "wof:placetype":"venue"
},
  "geometry": {"coordinates":[-95.64379099999999,29.978192],"type":"Point"}
}