{
  "type": "Feature",
  "properties": {
    "iso:country":"US",
    "sg:address":"1056 Valle Vista Ln",
    "sg:city":"Keller",
    "sg:classifiers":[
        {
            "category":"Food & Beverages",
            "subcategory":"Candy",
            "type":"Retail Goods"
        }
    ],
    "sg:phone":"+1 817 431 2629",
    "sg:postcode":"76248",
    "sg:province":"TX",
    "wof:name":"Fudge James J Etux Kimber",
    "wof:placetype":"venue"
},
  "geometry": {"coordinates":[-97.236289,32.951725],"type":"Point"}
}