{
  "type": "Feature",
  "properties": {
    "iso:country":"US",
    "sg:address":"3110 Pinemont",
    "sg:city":"Houston",
    "sg:classifiers":[
        {
            "category":"Banks & Credit Unions",
            "subcategory":"Financial Services",
            "type":"Services"
        }
    ],
    "sg:phone":"+1 713 688 5866",
    "sg:postcode":"77002",
    "sg:province":"TX",
    "sg:tags":[
        "broker",
        "mortgage"
    ],
    "wof:name":"Allied Mortgage Corp",
    "wof:placetype":"venue"
},
  "geometry": {"coordinates":[-95.428731,29.841054],"type":"Point"}
}