{
  "type": "Feature",
  "properties": {
    "iso:country":"US",
    "sg:address":"7033 Clubgate Dr",
    "sg:city":"Corpus Christi",
    "sg:classifiers":[
        {
            "category":"Wholesale",
            "subcategory":"Drugs",
            "type":"Manufacturing & Wholesale Goods"
        }
    ],
    "sg:phone":"+1 361 992 9644",
    "sg:postcode":"78413",
    "sg:province":"TX",
    "wof:name":"Ritaavoncom",
    "wof:placetype":"venue"
},
  "geometry": {"coordinates":[-97.394364,27.675358],"type":"Point"}
}