{
  "type": "Feature",
  "properties": {
    "iso:country":"US",
    "sg:address":"3831 Glenheather Dr",
    "sg:city":"Houston",
    "sg:classifiers":[
        {
            "category":"Professional",
            "subcategory":"Business Services",
            "type":"Services"
        }
    ],
    "sg:phone":"+1 281 444 5216",
    "sg:postcode":"77068",
    "sg:province":"TX",
    "sg:tags":[
        "interior",
        "designer",
        "decorator"
    ],
    "wof:name":"Martha Brooks Interior Design",
    "wof:placetype":"venue"
},
  "geometry": {"coordinates":[-95.49051799999999,29.998221],"type":"Point"}
}