{
  "type": "Feature",
  "properties": {
    "iso:country":"US",
    "sg:address":"2514 Incline Dr",
    "sg:city":"Carrollton",
    "sg:classifiers":[
        {
            "category":"Professional",
            "subcategory":"Computer Services",
            "type":"Services"
        }
    ],
    "sg:phone":"+1 972 416 8268",
    "sg:postcode":"75006",
    "sg:province":"TX",
    "sg:tags":[
        "related"
    ],
    "wof:name":"Rosa Computer Solutions",
    "wof:placetype":"venue"
},
  "geometry": {"coordinates":[-96.869984,32.974515],"type":"Point"}
}