{
  "type": "Feature",
  "properties": {
    "iso:country":"US",
    "sg:address":"3434 5th St",
    "sg:city":"Stafford",
    "sg:classifiers":[
        {
            "category":"Wholesale",
            "subcategory":"Machinery & Supplies",
            "type":"Manufacturing & Wholesale Goods"
        }
    ],
    "sg:phone":"+1 281 499 5400",
    "sg:postcode":"77477",
    "sg:province":"TX",
    "sg:tags":[
        "material"
    ],
    "wof:name":"Texas Soil",
    "wof:placetype":"venue"
},
  "geometry": {"coordinates":[-95.559978,29.594498],"type":"Point"}
}