{
  "type": "Feature",
  "properties": {
    "iso:country":"US",
    "sg:address":"622 Maple Way",
    "sg:city":"Houston",
    "sg:classifiers":[
        {
            "category":"Manufacturing",
            "subcategory":"Tools & Machinery",
            "type":"Manufacturing & Wholesale Goods"
        }
    ],
    "sg:phone":"+1 713 455 4554",
    "sg:postcode":"77015",
    "sg:province":"TX",
    "sg:tags":[
        "electric",
        "mfg"
    ],
    "wof:name":"J & J Products of Houston",
    "wof:placetype":"venue"
},
  "geometry": {"coordinates":[-95.200693,29.777639],"type":"Point"}
}