{
  "type": "Feature",
  "properties": {
    "iso:country":"US",
    "sg:address":"19221 Lockwood Rd",
    "sg:city":"Manor",
    "sg:classifiers":[
        {
            "category":"Professional",
            "type":"Services"
        }
    ],
    "sg:phone":"+1 512 272 9265",
    "sg:postcode":"78653",
    "sg:province":"TX",
    "wof:name":"Ann M Wissman",
    "wof:placetype":"venue"
},
  "geometry": {"coordinates":[-97.514133,30.308618],"type":"Point"}
}