{
  "type": "Feature",
  "properties": {
    "iso:country":"US",
    "sg:address":"2692 State Highway 16 S",
    "sg:city":"Bandera",
    "sg:classifiers":[
        {
            "category":"Autos & Motor Vehicles",
            "subcategory":"Auto Supplies",
            "type":"Retail Goods"
        },
        {
            "category":"Retail",
            "subcategory":"Auto Repair",
            "type":"Services"
        }
    ],
    "sg:phone":"+1 830 796 4004",
    "sg:postcode":"78003",
    "sg:province":"TX",
    "sg:tags":[
        "body",
        "lettering",
        "automobile",
        "truck",
        "painting",
        "repairing"
    ],
    "wof:name":"Bandera Paint & Body",
    "wof:placetype":"venue"
},
  "geometry": {"coordinates":[-99.04570099999999,29.734636],"type":"Point"}
}