{
  "type": "Feature",
  "properties": {
    "iso:country":"US",
    "sg:address":"4314 Hill Forest Dr",
    "sg:city":"Humble",
    "sg:classifiers":[
        {
            "category":"Real Estate",
            "subcategory":"Real Estate Agent",
            "type":"Services"
        }
    ],
    "sg:phone":"+1 281 360 3768",
    "sg:postcode":"77345",
    "sg:province":"TX",
    "wof:name":"Clamphaven LLC",
    "wof:placetype":"venue"
},
  "geometry": {"coordinates":[-95.17130400000001,30.055157],"type":"Point"}
}