{
  "type": "Feature",
  "properties": {
    "iso:country":"US",
    "sg:address":"243 Wildrose Ave",
    "sg:city":"San Antonio",
    "sg:classifiers":[
        {
            "category":"Real Estate",
            "subcategory":"Real Estate Agent",
            "type":"Services"
        }
    ],
    "sg:phone":"+1 210 820 3311",
    "sg:postcode":"78209",
    "sg:province":"TX",
    "wof:name":"James R Ploetz Inc",
    "wof:placetype":"venue"
},
  "geometry": {"coordinates":[-98.462519,29.486068],"type":"Point"}
}