{
  "type": "Feature",
  "properties": {
    "iso:country":"US",
    "sg:address":"810 N 3rd St",
    "sg:city":"Iowa Park",
    "sg:classifiers":[
        {
            "category":"Social Services",
            "type":"Services"
        }
    ],
    "sg:phone":"+1 940 592 9311",
    "sg:postcode":"76367",
    "sg:province":"TX",
    "wof:name":"Friendly Door Sr Citzn Enter",
    "wof:placetype":"venue"
},
  "geometry": {"coordinates":[-98.679901,33.958626],"type":"Point"}
}