{
  "type": "Feature",
  "properties": {
    "iso:country":"US",
    "sg:address":"2605 Country Pl",
    "sg:city":"Carrollton",
    "sg:classifiers":[
        {
            "category":"Professional",
            "subcategory":"Computer Services",
            "type":"Services"
        }
    ],
    "sg:phone":"+1 972 478 5588",
    "sg:postcode":"75006",
    "sg:province":"TX",
    "sg:tags":[
        "programing",
        "custom"
    ],
    "wof:name":"Digispan Communications",
    "wof:placetype":"venue"
},
  "geometry": {"coordinates":[-96.85813899999999,32.959809],"type":"Point"}
}