{
  "type": "Feature",
  "properties": {
    "iso:country":"US",
    "sg:address":"1718 Homewood Pl",
    "sg:city":"Dallas",
    "sg:classifiers":[
        {
            "category":"Professional",
            "subcategory":"Business Services",
            "type":"Services"
        }
    ],
    "sg:phone":"+1 214 370 3936",
    "sg:postcode":"75224",
    "sg:province":"TX",
    "wof:name":"Met Design Group Inc",
    "wof:placetype":"venue"
},
  "geometry": {"coordinates":[-96.84671,32.728833],"type":"Point"}
}