{
  "type": "Feature",
  "properties": {
    "iso:country":"US",
    "sg:address":"719 Gale St",
    "sg:city":"Laredo",
    "sg:classifiers":[
        {
            "category":"Wholesale",
            "subcategory":"Auto Parts",
            "type":"Manufacturing & Wholesale Goods"
        }
    ],
    "sg:phone":"+1 956 791 0922",
    "sg:postcode":"78041",
    "sg:province":"TX",
    "sg:tags":[
        "truck"
    ],
    "wof:name":"C & H Parts and Supplies",
    "wof:placetype":"venue"
},
  "geometry": {"coordinates":[-99.482457,27.554716],"type":"Point"}
}