{
  "type": "Feature",
  "properties": {
    "iso:country":"US",
    "sg:address":"601 S 15th St",
    "sg:city":"Hidalgo",
    "sg:classifiers":[
        {
            "category":"Wholesale",
            "subcategory":"Machinery & Supplies",
            "type":"Manufacturing & Wholesale Goods"
        }
    ],
    "sg:phone":"+1 956 843 6860",
    "sg:postcode":"78580",
    "sg:province":"TX",
    "sg:tags":[
        "rubber",
        "product"
    ],
    "sg:website":"www.my.quadeon.com",
    "wof:name":"Minnesota Rubber",
    "wof:placetype":"venue"
},
  "geometry": {"coordinates":[-97.77269,26.476983],"type":"Point"}
}