{
  "type": "Feature",
  "properties": {
    "iso:country":"US",
    "sg:address":"236 College St",
    "sg:city":"Schulenburg",
    "sg:classifiers":[
        {
            "category":"Food & Beverages",
            "subcategory":"Groceries & Convenience Stores",
            "type":"Retail Goods"
        }
    ],
    "sg:phone":"+1 979 743 3159",
    "sg:postcode":"78956",
    "sg:province":"TX",
    "wof:name":"Harlans 8",
    "wof:placetype":"venue"
},
  "geometry": {"coordinates":[-96.90022500000001,29.68452],"type":"Point"}
}