{
  "type": "Feature",
  "properties": {
    "iso:country":"US",
    "sg:address":"14657 FM 849",
    "sg:city":"Lindale",
    "sg:classifiers":[
        {
            "category":"Building & Trades",
            "subcategory":"Plumbing",
            "type":"Services"
        }
    ],
    "sg:phone":"+1 903 881 9119",
    "sg:postcode":"75771",
    "sg:province":"TX",
    "sg:tags":[
        "conditioning",
        "air",
        "system",
        "contractor"
    ],
    "wof:name":"Etex Air Conditioning",
    "wof:placetype":"venue"
},
  "geometry": {"coordinates":[-95.446791,32.473481],"type":"Point"}
}