{
  "type": "Feature",
  "properties": {
    "iso:country":"US",
    "sg:address":"7920 Co Rd 1233",
    "sg:city":"Godley",
    "sg:classifiers":[
        {
            "category":"Shopping",
            "subcategory":"Bicycles & Sporting Goods",
            "type":"Retail Goods"
        }
    ],
    "sg:phone":"+1 817 309 2223",
    "sg:postcode":"76044",
    "sg:province":"TX",
    "wof:name":"Lake Country Golf Carts Inc",
    "wof:placetype":"venue"
},
  "geometry": {"coordinates":[-97.59286400000001,32.441469],"type":"Point"}
}