{
  "type": "Feature",
  "properties": {
    "iso:country":"US",
    "sg:address":"4200 S Alameda St",
    "sg:city":"Corpus Christi",
    "sg:classifiers":[
        {
            "category":"Home & Garden",
            "subcategory":"Carpets & Floor Coverings",
            "type":"Retail Goods"
        }
    ],
    "sg:phone":"+1 361 857 7847",
    "sg:postcode":"78412",
    "sg:province":"TX",
    "wof:name":"G Sterling Watson & Webb LLC",
    "wof:placetype":"venue"
},
  "geometry": {"coordinates":[-97.37215399999999,27.730273],"type":"Point"}
}