{
  "type": "Feature",
  "properties": {
    "iso:country":"US",
    "sg:address":"8450 Bigwood St",
    "sg:city":"Houston",
    "sg:classifiers":[
        {
            "category":"Professional",
            "subcategory":"Business Services",
            "type":"Services"
        }
    ],
    "sg:phone":"+1 713 631 1758",
    "sg:postcode":"77078",
    "sg:province":"TX",
    "wof:name":"Ktd Hotshot",
    "wof:placetype":"venue"
},
  "geometry": {"coordinates":[-95.27014800000001,29.856176],"type":"Point"}
}