{
  "type": "Feature",
  "properties": {
    "iso:country":"US",
    "sg:address":"104 Elaine Dr",
    "sg:city":"Lorena",
    "sg:classifiers":[
        {
            "category":"Shopping",
            "type":"Retail Goods"
        }
    ],
    "sg:phone":"+1 254 857 9836",
    "sg:postcode":"76655",
    "sg:province":"TX",
    "sg:tags":[
        "miscellaneous",
        "store"
    ],
    "wof:name":"Pet Express",
    "wof:placetype":"venue"
},
  "geometry": {"coordinates":[-97.261867,31.418478],"type":"Point"}
}