{
  "type": "Feature",
  "properties": {
    "iso:country":"US",
    "sg:address":"576 el Dorado Blvd",
    "sg:city":"Houston",
    "sg:classifiers":[
        {
            "category":"Restaurant",
            "type":"Food & Drink"
        }
    ],
    "sg:phone":"+1 281 461 1888",
    "sg:postcode":"77598",
    "sg:province":"TX",
    "wof:name":"J B's Chinese Cafe",
    "wof:placetype":"venue"
},
  "geometry": {"coordinates":[-95.141874,29.561117],"type":"Point"}
}