{
  "type": "Feature",
  "properties": {
    "iso:country":"US",
    "sg:address":"2937 S Treadaway Blvd",
    "sg:city":"Abilene",
    "sg:classifiers":[
        {
            "category":"Building & Trades",
            "subcategory":"Plumbing",
            "type":"Services"
        },
        {
            "category":"Building & Trades",
            "subcategory":"Construction",
            "type":"Services"
        },
        {
            "category":"Sports & Exercise",
            "subcategory":"Ski Resort",
            "type":"Entertainment"
        }
    ],
    "sg:phone":"+1 325 692 9889",
    "sg:postcode":"79602",
    "sg:province":"TX",
    "sg:tags":[
        "plumber",
        "industrial",
        "radiators-heating",
        "supply",
        "sales",
        "pipe",
        "fitting",
        "contractors-commercial"
    ],
    "wof:name":"Plastic Whlse. Plumbing Inc.",
    "wof:placetype":"venue"
},
  "geometry": {"coordinates":[-99.74240899999999,32.414849],"type":"Point"}
}