{
  "type": "Feature",
  "properties": {
    "iso:country":"US",
    "sg:address":"5214 Lake Forest Dr",
    "sg:city":"Rowlett",
    "sg:classifiers":[
        {
            "category":"Professional",
            "subcategory":"Management & Consulting",
            "type":"Services"
        }
    ],
    "sg:phone":"+1 972 475 8267",
    "sg:postcode":"75088",
    "sg:province":"TX",
    "sg:tags":[
        "business"
    ],
    "wof:name":"Project Assist Consultants",
    "wof:placetype":"venue"
},
  "geometry": {"coordinates":[-96.550887,32.893955],"type":"Point"}
}