{
  "type": "Feature",
  "properties": {
    "iso:country":"US",
    "sg:address":"103 Llano Dr",
    "sg:city":"Portland",
    "sg:classifiers":[
        {
            "category":"Banks & Credit Unions",
            "subcategory":"Financial Services",
            "type":"Services"
        }
    ],
    "sg:phone":"+1 361 643 8854",
    "sg:postcode":"78374",
    "sg:province":"TX",
    "sg:tags":[
        "trust",
        "investment",
        "real estate"
    ],
    "wof:name":"Vincent Heard Family LLC",
    "wof:placetype":"venue"
},
  "geometry": {"coordinates":[-97.313057,27.882684],"type":"Point"}
}