{
  "type": "Feature",
  "properties": {
    "iso:country":"US",
    "sg:address":"310 Hockaday Ave",
    "sg:city":"Garland",
    "sg:classifiers":[
        {
            "category":"Travel",
            "subcategory":"Hotels & Motels",
            "type":"Entertainment"
        }
    ],
    "sg:phone":"+1 972 412 4311",
    "sg:postcode":"75043",
    "sg:province":"TX",
    "sg:tags":[
        "operation"
    ],
    "wof:name":"Blanche Carte Casino & Entrmt",
    "wof:placetype":"venue"
},
  "geometry": {"coordinates":[-96.623763,32.870678],"type":"Point"}
}