{
  "type": "Feature",
  "properties": {
    "iso:country":"US",
    "sg:address":"5055 W Park Blvd Ste 300",
    "sg:city":"Plano",
    "sg:classifiers":[
        {
            "category":"Banks & Credit Unions",
            "subcategory":"Financial Services",
            "type":"Services"
        }
    ],
    "sg:phone":"+1 972 599 5210",
    "sg:postcode":"75093",
    "sg:province":"TX",
    "sg:tags":[
        "broker",
        "mortgage"
    ],
    "sg:website":"www.wrstarkey.com",
    "wof:name":"Wr Starkey Mortgage",
    "wof:placetype":"venue"
},
  "geometry": {"coordinates":[-96.797203,33.027699],"type":"Point"}
}