{
  "type": "Feature",
  "properties": {
    "iso:country":"US",
    "sg:address":"5290 Beltline Rd",
    "sg:city":"Dallas",
    "sg:classifiers":[
        {
            "category":"Food & Beverages",
            "subcategory":"Bakery",
            "type":"Retail Goods"
        }
    ],
    "sg:phone":"+1 972 233 3958",
    "sg:postcode":"75254",
    "sg:province":"TX",
    "sg:tags":[
        "sandwich"
    ],
    "sg:website":"www.greatoutdoorsubs.com",
    "wof:name":"The Great Outdoors Sub Shop",
    "wof:placetype":"venue"
},
  "geometry": {"coordinates":[-97.014376,32.64574],"type":"Point"}
}