{
  "type": "Feature",
  "properties": {
    "iso:country":"US",
    "sg:address":"101 W 14th St",
    "sg:city":"Houston",
    "sg:classifiers":[
        {
            "category":"Personal",
            "subcategory":"Beauty Salon",
            "type":"Services"
        },
        {
            "category":"Personal",
            "subcategory":"Barber",
            "type":"Services"
        },
        {
            "category":"Personal",
            "subcategory":"Day Spa",
            "type":"Services"
        },
        {
            "category":"Personal",
            "subcategory":"Skin Care",
            "type":"Services"
        },
        {
            "category":"Personal",
            "subcategory":"Nail Salon",
            "type":"Services"
        }
    ],
    "sg:phone":"+1 713 581 8280",
    "sg:postcode":"77008",
    "sg:province":"TX",
    "sg:website":"http://houston.citysearch.com/profile/external/45600714/houston_tx/la_paz_day_spa.html?publisher=yellowpages&reference_id=1&placement=ypwebsitemip",
    "wof:name":"La Paz Day Spa",
    "wof:placetype":"venue"
},
  "geometry": {"coordinates":[-95.397942,29.7962],"type":"Point"}
}