{
  "type": "Feature",
  "properties": {
    "iso:country":"US",
    "sg:address":"7929 Alameda Ave",
    "sg:city":"El Paso",
    "sg:classifiers":[
        {
            "category":"Autos & Motor Vehicles",
            "subcategory":"Automobile Sales",
            "type":"Retail Goods"
        }
    ],
    "sg:phone":"+1 915 860 8607",
    "sg:postcode":"79915",
    "sg:province":"TX",
    "sg:tags":[
        "used"
    ],
    "wof:name":"Richys Auto Center",
    "wof:placetype":"venue"
},
  "geometry": {"coordinates":[-106.360935,31.728601],"type":"Point"}
}