{
  "type": "Feature",
  "properties": {
    "iso:country":"US",
    "sg:address":"2301 Westheimer Rd",
    "sg:city":"Houston",
    "sg:classifiers":[
        {
            "category":"Wholesale",
            "subcategory":"Machinery & Supplies",
            "type":"Manufacturing & Wholesale Goods"
        }
    ],
    "sg:phone":"+1 832 590 2301",
    "sg:postcode":"77098",
    "sg:province":"TX",
    "sg:tags":[
        "valve"
    ],
    "wof:name":"Dresser Flow Control",
    "wof:placetype":"venue"
},
  "geometry": {"coordinates":[-95.41551699999999,29.742428],"type":"Point"}
}