{
  "type": "Feature",
  "properties": {
    "iso:country":"US",
    "sg:address":"5 S 11th St",
    "sg:city":"Mcallen",
    "sg:classifiers":[
        {
            "category":"Professional",
            "type":"Services"
        }
    ],
    "sg:phone":"+1 956 682 3226",
    "sg:postcode":"78501",
    "sg:province":"TX",
    "sg:tags":[
        "establishment"
    ],
    "wof:name":"Mcallen Perfusion Assoc Inc",
    "wof:placetype":"venue"
},
  "geometry": {"coordinates":[-98.23116899999999,26.202879],"type":"Point"}
}