{
  "type": "Feature",
  "properties": {
    "iso:country":"US",
    "sg:address":"2202 Monte Cristo Dr",
    "sg:city":"Sherman",
    "sg:classifiers":[
        {
            "category":"Retail",
            "subcategory":"Laundry & Dry Cleaning",
            "type":"Services"
        }
    ],
    "sg:phone":"+1 903 870 7012",
    "sg:postcode":"75092",
    "sg:province":"TX",
    "sg:tags":[
        "cleaner",
        "rug",
        "carpet"
    ],
    "wof:name":"Duraclean",
    "wof:placetype":"venue"
},
  "geometry": {"coordinates":[-96.64058300000001,33.656066],"type":"Point"}
}