{
  "type": "Feature",
  "properties": {
    "iso:country":"US",
    "sg:address":"3500 Co Rd 2",
    "sg:city":"Nacogdoches",
    "sg:classifiers":[
        {
            "category":"Shopping",
            "type":"Retail Goods"
        }
    ],
    "sg:phone":"+1 936 564 3279",
    "sg:postcode":"75969",
    "sg:province":"TX",
    "sg:tags":[
        "pet",
        "shop"
    ],
    "wof:name":"Discovery Realm Aquatics",
    "wof:placetype":"venue"
},
  "geometry": {"coordinates":[-94.9265,31.469609],"type":"Point"}
}