{
  "type": "Feature",
  "properties": {
    "iso:country":"US",
    "sg:address":"2012 Raul Longoria Rd",
    "sg:city":"San Juan",
    "sg:classifiers":[
        {
            "category":"Professional",
            "type":"Services"
        }
    ],
    "sg:phone":"+1 956 781 8283",
    "sg:postcode":"78589",
    "sg:province":"TX",
    "wof:name":"ADT Aus",
    "wof:placetype":"venue"
},
  "geometry": {"coordinates":[-98.15080399999999,26.216506],"type":"Point"}
}