{
  "type": "Feature",
  "properties": {
    "iso:country":"US",
    "sg:address":"12301 S Ih 35 W",
    "sg:city":"Burleson",
    "sg:classifiers":[
        {
            "category":"Retail",
            "subcategory":"Funeral Services",
            "type":"Services"
        }
    ],
    "sg:phone":"+1 817 568 8836",
    "sg:postcode":"76028",
    "sg:province":"TX",
    "sg:tags":[
        "cemetery"
    ],
    "wof:name":"Crosier-Pearson-Mayfield Funeral Home",
    "wof:placetype":"venue"
},
  "geometry": {"coordinates":[-97.300003,32.535099],"type":"Point"}
}