{
  "type": "Feature",
  "properties": {
    "iso:country":"US",
    "sg:address":"825 Overhill Dr",
    "sg:city":"Hurst",
    "sg:classifiers":[
        {
            "category":"Freight",
            "type":"Transportation"
        }
    ],
    "sg:phone":"+1 817 595 3272",
    "sg:postcode":"76053",
    "sg:province":"TX",
    "sg:tags":[
        "operator",
        "local",
        "trucking"
    ],
    "wof:name":"Extreme Delivery Inc",
    "wof:placetype":"venue"
},
  "geometry": {"coordinates":[-97.18891600000001,32.836074],"type":"Point"}
}