{
  "type": "Feature",
  "properties": {
    "iso:country":"US",
    "sg:address":"1402 Springside Dr",
    "sg:city":"Garland",
    "sg:classifiers":[
        {
            "category":"Building & Trades",
            "subcategory":"Construction",
            "type":"Services"
        }
    ],
    "sg:phone":"+1 972 240 7672",
    "sg:postcode":"75043",
    "sg:province":"TX",
    "sg:tags":[
        "residential"
    ],
    "wof:name":"Mercedez Homes",
    "wof:placetype":"venue"
},
  "geometry": {"coordinates":[-96.586558,32.866749],"type":"Point"}
}