{
  "type": "Feature",
  "properties": {
    "iso:country":"US",
    "sg:address":"142 Lynn Loop",
    "sg:city":"Laredo",
    "sg:classifiers":[
        {
            "category":"Building & Trades",
            "subcategory":"Equipment Rental",
            "type":"Services"
        }
    ],
    "sg:phone":"+1 956 726 1857",
    "sg:postcode":"78045",
    "sg:province":"TX",
    "wof:name":"Romeros Party Rentals",
    "wof:placetype":"venue"
},
  "geometry": {"coordinates":[-99.52494299999999,27.580573],"type":"Point"}
}