{
  "type": "Feature",
  "properties": {
    "iso:country":"US",
    "sg:address":"1920 Wenneca Ave",
    "sg:city":"Fort Worth",
    "sg:classifiers":[
        {
            "category":"Manufacturing",
            "subcategory":"Printing",
            "type":"Manufacturing & Wholesale Goods"
        }
    ],
    "sg:phone":"+1 817 332 2842",
    "sg:postcode":"76102",
    "sg:province":"TX",
    "sg:tags":[
        "lithographic",
        "letterpress"
    ],
    "wof:name":"Cooksey Printing Inc",
    "wof:placetype":"venue"
},
  "geometry": {"coordinates":[-97.348575,32.740991],"type":"Point"}
}