{
  "type": "Feature",
  "properties": {
    "iso:country":"US",
    "sg:address":"1109 North St",
    "sg:city":"Jefferson",
    "sg:classifiers":[
        {
            "category":"Organizations",
            "subcategory":"Religious Organization",
            "type":"Services"
        }
    ],
    "sg:phone":"+1 903 665 8848",
    "sg:postcode":"75657",
    "sg:province":"TX",
    "sg:tags":[
        "church"
    ],
    "wof:name":"Mt Ira Baptist Church",
    "wof:placetype":"venue"
},
  "geometry": {"coordinates":[-94.34165299999999,32.771494],"type":"Point"}
}