{
  "type": "Feature",
  "properties": {
    "iso:country":"US",
    "sg:address":"1480 W Buckingham Rd",
    "sg:city":"Garland",
    "sg:classifiers":[
        {
            "category":"Restaurant",
            "type":"Food & Drink"
        }
    ],
    "sg:phone":"+1 972 276 0045",
    "sg:postcode":"75042",
    "sg:province":"TX",
    "sg:tags":[
        "eating"
    ],
    "wof:name":"Pancho's Mexican Buffet Inc",
    "wof:placetype":"venue"
},
  "geometry": {"coordinates":[-96.65033699999999,32.930521],"type":"Point"}
}