{
  "type": "Feature",
  "properties": {
    "iso:country":"US",
    "sg:address":"4316 Ashmore Dr",
    "sg:city":"Fort Worth",
    "sg:classifiers":[
        {
            "category":"Arts & Performance",
            "subcategory":"Theater",
            "type":"Entertainment"
        }
    ],
    "sg:phone":"+1 817 595 1527",
    "sg:postcode":"76180",
    "sg:province":"TX",
    "sg:tags":[
        "group"
    ],
    "wof:name":"Ashmore Rocks",
    "wof:placetype":"venue"
},
  "geometry": {"coordinates":[-97.210247,32.828134],"type":"Point"}
}