{
  "type": "Feature",
  "properties": {
    "iso:country":"US",
    "sg:address":"6703 Ridge Place St",
    "sg:city":"San Antonio",
    "sg:classifiers":[
        {
            "category":"Building & Trades",
            "subcategory":"Construction",
            "type":"Services"
        }
    ],
    "sg:phone":"+1 210 433 8119",
    "sg:postcode":"78250",
    "sg:province":"TX",
    "sg:tags":[
        "contractor"
    ],
    "wof:name":"Santex Roofing",
    "wof:placetype":"venue"
},
  "geometry": {"coordinates":[-98.67274500000001,29.496523],"type":"Point"}
}