{
  "type": "Feature",
  "properties": {
    "iso:country":"US",
    "sg:address":"1002 N Duncanville Rd",
    "sg:city":"Duncanville",
    "sg:classifiers":[
        {
            "category":"Retail",
            "subcategory":"Auto Repair",
            "type":"Services"
        }
    ],
    "sg:phone":"+1 972 709 8958",
    "sg:postcode":"75116",
    "sg:province":"TX",
    "sg:tags":[
        "body",
        "shop"
    ],
    "wof:name":"Earl Scheib Paint & & Body",
    "wof:placetype":"venue"
},
  "geometry": {"coordinates":[-96.908203,32.666698],"type":"Point"}
}