{
  "type": "Feature",
  "properties": {
    "iso:country":"US",
    "sg:address":"1924 Old Denton Rd",
    "sg:city":"Carrollton",
    "sg:classifiers":[
        {
            "category":"Wholesale",
            "subcategory":"Electrical",
            "type":"Manufacturing & Wholesale Goods"
        }
    ],
    "sg:phone":"+1 972 242 3979",
    "sg:postcode":"75006",
    "sg:province":"TX",
    "sg:tags":[
        "alarm",
        "sprinkler",
        "system"
    ],
    "wof:name":"Champion Automatic Fire",
    "wof:placetype":"venue"
},
  "geometry": {"coordinates":[-96.912104,32.966548],"type":"Point"}
}