{
  "type": "Feature",
  "properties": {
    "iso:country":"US",
    "sg:address":"1102 Mc Callum Dr",
    "sg:city":"Garland",
    "sg:classifiers":[
        {
            "category":"Building & Trades",
            "subcategory":"Construction",
            "type":"Services"
        }
    ],
    "sg:phone":"+1 972 494 5661",
    "sg:postcode":"75042",
    "sg:province":"TX",
    "sg:tags":[
        "contractor"
    ],
    "wof:name":"Budget Fence Co",
    "wof:placetype":"venue"
},
  "geometry": {"coordinates":[-96.675282,32.922674],"type":"Point"}
}