{
  "type": "Feature",
  "properties": {
    "iso:country":"US",
    "sg:address":"3720 N 16th St",
    "sg:city":"Orange",
    "sg:classifiers":[
        {
            "category":"Building & Trades",
            "subcategory":"Equipment Rental",
            "type":"Services"
        }
    ],
    "sg:phone":"+1 409 882 0354",
    "sg:postcode":"77632",
    "sg:province":"TX",
    "sg:tags":[
        "photofinishing",
        "courier"
    ],
    "wof:name":"Public Netxchange",
    "wof:placetype":"venue"
},
  "geometry": {"coordinates":[-93.74754299999999,30.122864],"type":"Point"}
}