{
  "type": "Feature",
  "properties": {
    "iso:country":"US",
    "sg:address":"2008 Hemphill St",
    "sg:city":"Fort Worth",
    "sg:classifiers":[
        {
            "category":"Real Estate",
            "subcategory":"Real Estate Operator",
            "type":"Services"
        }
    ],
    "sg:phone":"+1 817 923 9864",
    "sg:postcode":"76110",
    "sg:province":"TX",
    "sg:tags":[
        "building",
        "apartment"
    ],
    "wof:name":"Mary Elizabeth Apartments",
    "wof:placetype":"venue"
},
  "geometry": {"coordinates":[-97.33165200000001,32.721324],"type":"Point"}
}