{
  "type": "Feature",
  "properties": {
    "iso:country":"US",
    "sg:address":"2012 W Nathan Lowe Rd",
    "sg:city":"Arlington",
    "sg:classifiers":[
        {
            "category":"Real Estate",
            "subcategory":"Real Estate Agent",
            "type":"Services"
        }
    ],
    "sg:phone":"+1 817 468 5695",
    "sg:postcode":"76017",
    "sg:province":"TX",
    "wof:name":"E J Harbin Realtors",
    "wof:placetype":"venue"
},
  "geometry": {"coordinates":[-97.138289,32.655101],"type":"Point"}
}