{
  "type": "Feature",
  "properties": {
    "iso:country":"US",
    "sg:address":"262 Beach Airport Rd",
    "sg:city":"Conroe",
    "sg:classifiers":[
        {
            "category":"Manufacturing",
            "subcategory":"Tools & Machinery",
            "type":"Manufacturing & Wholesale Goods"
        }
    ],
    "sg:phone":"+1 936 539 5544",
    "sg:postcode":"77301",
    "sg:province":"TX",
    "sg:tags":[
        "physician",
        "surgeon"
    ],
    "sg:website":"www.jensonmedical.com",
    "wof:name":"Jenson Medical Intl",
    "wof:placetype":"venue"
},
  "geometry": {"coordinates":[-95.419635,30.323679],"type":"Point"}
}