{
  "type": "Feature",
  "properties": {
    "iso:country":"US",
    "sg:address":"6969 Pastor Bailey Dr Ste 110",
    "sg:city":"Dallas",
    "sg:classifiers":[
        {
            "category":"Banks & Credit Unions",
            "subcategory":"Financial Services",
            "type":"Services"
        }
    ],
    "sg:phone":"+1 972 572 0011",
    "sg:postcode":"75237",
    "sg:province":"TX",
    "sg:tags":[
        "broker",
        "mortgage"
    ],
    "wof:name":"First American Financial Service",
    "wof:placetype":"venue"
},
  "geometry": {"coordinates":[-96.87476700000001,32.664349],"type":"Point"}
}