{
  "type": "Feature",
  "properties": {
    "iso:country":"US",
    "sg:address":"8215 Pioneer Dr",
    "sg:city":"Frisco",
    "sg:classifiers":[
        {
            "category":"Professional",
            "subcategory":"Art Services",
            "type":"Services"
        }
    ],
    "sg:phone":"+1 972 712 0610",
    "sg:postcode":"75034",
    "sg:province":"TX",
    "sg:tags":[
        "commercial",
        "design"
    ],
    "wof:name":"Deko Dezine",
    "wof:placetype":"venue"
},
  "geometry": {"coordinates":[-96.81125900000001,33.168255],"type":"Point"}
}