{
  "type": "Feature",
  "properties": {
    "iso:country":"US",
    "sg:address":"5908 Fairdale Ln",
    "sg:city":"Houston",
    "sg:classifiers":[
        {
            "category":"Health Services",
            "subcategory":"Clinic",
            "type":"Services"
        }
    ],
    "sg:phone":"+1 713 781 1905",
    "sg:postcode":"77057",
    "sg:province":"TX",
    "sg:tags":[
        "loss",
        "weight"
    ],
    "sg:website":"www.houstonmedicalweightlossclin...",
    "wof:name":"Houston Medical Weight Loss Clinic",
    "wof:placetype":"venue"
},
  "geometry": {"coordinates":[-95.482449,29.733219],"type":"Point"}
}