{
  "type": "Feature",
  "properties": {
    "iso:country":"US",
    "sg:address":"1210 E Parker Rd",
    "sg:city":"Plano",
    "sg:classifiers":[
        {
            "category":"Wholesale",
            "subcategory":"Machinery & Supplies",
            "type":"Manufacturing & Wholesale Goods"
        },
        {
            "category":"Shopping",
            "type":"Retail Goods"
        }
    ],
    "sg:phone":"+1 972 943 0934",
    "sg:postcode":"75074",
    "sg:province":"TX",
    "sg:tags":[
        "equipment",
        "establishment",
        "cosmetic",
        "perfume"
    ],
    "wof:name":"National Beauty Supply",
    "wof:placetype":"venue"
},
  "geometry": {"coordinates":[-96.697275,33.037578],"type":"Point"}
}