{
  "type": "Feature",
  "properties": {
    "iso:country":"US",
    "sg:address":"11534 Lazy Meadows Dr",
    "sg:city":"Houston",
    "sg:classifiers":[
        {
            "category":"Professional",
            "subcategory":"Management & Consulting",
            "type":"Services"
        }
    ],
    "sg:phone":"+1 281 955 1752",
    "sg:postcode":"77064",
    "sg:province":"TX",
    "wof:name":"Dream Work Marketing",
    "wof:placetype":"venue"
},
  "geometry": {"coordinates":[-95.580528,29.930496],"type":"Point"}
}