{
  "type": "Feature",
  "properties": {
    "iso:country":"US",
    "sg:address":"3444 Parham Dr",
    "sg:city":"Grand Prairie",
    "sg:classifiers":[
        {
            "category":"Professional",
            "subcategory":"Business Services",
            "type":"Services"
        }
    ],
    "sg:phone":"+1 972 606 8880",
    "sg:postcode":"75052",
    "sg:province":"TX",
    "wof:name":"Boss Technologies",
    "wof:placetype":"venue"
},
  "geometry": {"coordinates":[-97.05856,32.686677],"type":"Point"}
}