{
  "type": "Feature",
  "properties": {
    "iso:country":"US",
    "sg:address":"2626 S Loop Fwy",
    "sg:city":"Houston",
    "sg:classifiers":[
        {
            "category":"Government",
            "subcategory":"Office",
            "type":"Public Place"
        }
    ],
    "sg:phone":"+1 281 726 1273",
    "sg:postcode":"77054",
    "sg:province":"TX",
    "sg:tags":[
        "housing",
        "program"
    ],
    "wof:name":"Navigating Affordable Places F",
    "wof:placetype":"venue"
},
  "geometry": {"coordinates":[-95.419211,29.678122],"type":"Point"}
}