{
  "type": "Feature",
  "properties": {
    "iso:country":"US",
    "sg:address":"817 W Murphy St",
    "sg:city":"Odessa",
    "sg:classifiers":[
        {
            "category":"Manufacturing",
            "subcategory":"Glass & Minerals",
            "type":"Manufacturing & Wholesale Goods"
        }
    ],
    "sg:phone":"+1 432 580 5161",
    "sg:postcode":"79763",
    "sg:province":"TX",
    "sg:tags":[
        "fabricator",
        "fiber"
    ],
    "sg:website":"www.grecianspas.com",
    "wof:name":"Odessa Fiber Glass Factory",
    "wof:placetype":"venue"
},
  "geometry": {"coordinates":[-102.37417000000001,31.83993],"type":"Point"}
}