{
  "type": "Feature",
  "properties": {
    "iso:country":"US",
    "sg:address":"375 Liana Ct",
    "sg:city":"El Paso",
    "sg:classifiers":[
        {
            "category":"Building & Trades",
            "subcategory":"Construction",
            "type":"Services"
        }
    ],
    "sg:phone":"+1 915 584 8644",
    "sg:postcode":"79932",
    "sg:province":"TX",
    "sg:tags":[
        "contractor"
    ],
    "wof:name":"Tejeda & Sons Masonry",
    "wof:placetype":"venue"
},
  "geometry": {"coordinates":[-106.586879,31.868766],"type":"Point"}
}