{
  "type": "Feature",
  "properties": {
    "iso:country":"US",
    "sg:address":"10715 Gulf Fwy",
    "sg:city":"Houston",
    "sg:classifiers":[
        {
            "category":"Banks & Credit Unions",
            "subcategory":"Bank",
            "type":"Services"
        }
    ],
    "sg:phone":"+1 713 910 2885",
    "sg:postcode":"77034",
    "sg:province":"TX",
    "sg:tags":[
        "institution",
        "business"
    ],
    "wof:name":"Star Loans of Texas",
    "wof:placetype":"venue"
},
  "geometry": {"coordinates":[-95.239226,29.637826],"type":"Point"}
}