{
  "type": "Feature",
  "properties": {
    "iso:country":"US",
    "sg:address":"2527 Wilderness Hill",
    "sg:city":"San Antonio",
    "sg:classifiers":[
        {
            "category":"Wholesale",
            "subcategory":"Non-durable Goods",
            "type":"Manufacturing & Wholesale Goods"
        }
    ],
    "sg:phone":"+1 210 493 5980",
    "sg:postcode":"78231",
    "sg:province":"TX",
    "sg:tags":[
        "advertising"
    ],
    "wof:name":"Leap'n Logos",
    "wof:placetype":"venue"
},
  "geometry": {"coordinates":[-98.53520899999999,29.56237],"type":"Point"}
}