{
  "type": "Feature",
  "properties": {
    "iso:country":"US",
    "sg:address":"14700 Marsh Ln Ofc",
    "sg:city":"Addison",
    "sg:classifiers":[
        {
            "category":"Real Estate",
            "subcategory":"Real Estate Operator",
            "type":"Services"
        }
    ],
    "sg:phone":"+1 972 488 7500",
    "sg:postcode":"75001",
    "sg:province":"TX",
    "sg:tags":[
        "apartment"
    ],
    "wof:name":"Waterford Court Apt Homes",
    "wof:placetype":"venue"
},
  "geometry": {"coordinates":[-96.855598,32.945499],"type":"Point"}
}