{
  "type": "Feature",
  "properties": {
    "iso:country":"US",
    "sg:address":"117 N Stanton St",
    "sg:city":"El Paso",
    "sg:classifiers":[
        {
            "category":"Food & Beverages",
            "subcategory":"Bakery",
            "type":"Retail Goods"
        }
    ],
    "sg:phone":"+1 915 351 1014",
    "sg:postcode":"79901",
    "sg:province":"TX",
    "sg:tags":[
        "baker"
    ],
    "wof:name":"Vanderpool's Bakery",
    "wof:placetype":"venue"
},
  "geometry": {"coordinates":[-106.486351,31.759292],"type":"Point"}
}