{
  "type": "Feature",
  "properties": {
    "iso:country":"US",
    "sg:address":"4111 North Fwy",
    "sg:city":"Houston",
    "sg:classifiers":[
        {
            "category":"Professional",
            "subcategory":"Detective & Security Services",
            "type":"Services"
        }
    ],
    "sg:phone":"+1 713 229 0200",
    "sg:postcode":"77022",
    "sg:province":"TX",
    "sg:tags":[
        "guard",
        "patrol"
    ],
    "wof:name":"En Garde Protective Svc",
    "wof:placetype":"venue"
},
  "geometry": {"coordinates":[-95.38055300000001,29.824737],"type":"Point"}
}