{
  "type": "Feature",
  "properties": {
    "iso:country":"US",
    "sg:address":"116 N Ave A",
    "sg:city":"Crystal City",
    "sg:classifiers":[
        {
            "category":"Building & Trades",
            "subcategory":"Construction",
            "type":"Services"
        }
    ],
    "sg:phone":"+1 940 684 1215",
    "sg:postcode":"78839",
    "sg:province":"TX",
    "sg:tags":[
        "contractor"
    ],
    "wof:name":"Crowell Contract & Design Inc",
    "wof:placetype":"venue"
},
  "geometry": {"coordinates":[-99.83050799999999,28.677932],"type":"Point"}
}