{
  "type": "Feature",
  "properties": {
    "iso:country":"US",
    "sg:address":"10106 Jockey Club Dr",
    "sg:city":"Houston",
    "sg:classifiers":[
        {
            "category":"Manufacturing",
            "subcategory":"Tools & Machinery",
            "type":"Manufacturing & Wholesale Goods"
        }
    ],
    "sg:phone":"+1 713 306 2789",
    "sg:postcode":"77065",
    "sg:province":"TX",
    "sg:tags":[
        "industrial",
        "mfg"
    ],
    "wof:name":"Promill Cnc Inc",
    "wof:placetype":"venue"
},
  "geometry": {"coordinates":[-95.590214,29.92117],"type":"Point"}
}