{
  "type": "Feature",
  "properties": {
    "iso:country":"US",
    "sg:address":"2802 Lindenwood Dr",
    "sg:city":"San Angelo",
    "sg:classifiers":[
        {
            "category":"Real Estate",
            "subcategory":"Real Estate Agent",
            "type":"Services"
        },
        {
            "category":"Professional",
            "subcategory":"Business Services",
            "type":"Services"
        }
    ],
    "sg:phone":"+1 325 942 5678",
    "sg:postcode":"76904",
    "sg:province":"TX",
    "sg:tags":[
        "appraiser"
    ],
    "wof:name":"David Johanson Appraisal Co",
    "wof:placetype":"venue"
},
  "geometry": {"coordinates":[-100.47780400000001,31.423078],"type":"Point"}
}