{
  "type": "Feature",
  "properties": {
    "iso:country":"US",
    "sg:address":"1200 US Hwy 77",
    "sg:city":"Waxahachie",
    "sg:classifiers":[
        {
            "category":"Personal",
            "subcategory":"Beauty Salon",
            "type":"Services"
        }
    ],
    "sg:phone":"+1 972 923 1984",
    "sg:postcode":"75165",
    "sg:province":"TX",
    "wof:name":"Smart Style Family Hair Salon",
    "wof:placetype":"venue"
},
  "geometry": {"coordinates":[-96.84048,32.419224],"type":"Point"}
}