{
  "type": "Feature",
  "properties": {
    "iso:country":"US",
    "sg:address":"2816 N 19th St",
    "sg:city":"Waco",
    "sg:classifiers":[
        {
            "category":"Food & Beverages",
            "subcategory":"Liquor & Beverages",
            "type":"Retail Goods"
        }
    ],
    "sg:phone":"+1 254 753 0456",
    "sg:postcode":"76708",
    "sg:province":"TX",
    "sg:tags":[
        "alcoholic"
    ],
    "wof:name":"N 19th St Liquor Store",
    "wof:placetype":"venue"
},
  "geometry": {"coordinates":[-97.16623300000001,31.570866],"type":"Point"}
}