{
  "type": "Feature",
  "properties": {
    "iso:country":"US",
    "sg:address":"4018 Burning Tree Ln",
    "sg:city":"Garland",
    "sg:classifiers":[
        {
            "category":"Wholesale",
            "subcategory":"Machinery & Supplies",
            "type":"Manufacturing & Wholesale Goods"
        }
    ],
    "sg:phone":"+1 972 276 3871",
    "sg:postcode":"75042",
    "sg:province":"TX",
    "sg:tags":[
        "industrial"
    ],
    "wof:name":"Per Co",
    "wof:placetype":"venue"
},
  "geometry": {"coordinates":[-96.695165,32.925273],"type":"Point"}
}