{
  "type": "Feature",
  "properties": {
    "iso:country":"US",
    "sg:address":"1908 4th Ave",
    "sg:city":"Canyon",
    "sg:classifiers":[
        {
            "category":"Banks & Credit Unions",
            "subcategory":"Financial Services",
            "type":"Services"
        }
    ],
    "sg:phone":"+1 806 359 7737",
    "sg:postcode":"79015",
    "sg:province":"TX",
    "sg:tags":[
        "broker",
        "mortgage"
    ],
    "wof:name":"First State Bank",
    "wof:placetype":"venue"
},
  "geometry": {"coordinates":[-101.922997,34.979599],"type":"Point"}
}