{
  "type": "Feature",
  "properties": {
    "iso:country":"US",
    "sg:address":"5841 Co Rd 157",
    "sg:city":"Iola",
    "sg:classifiers":[
        {
            "category":"Farming",
            "subcategory":"Livestock Farm",
            "type":"Manufacturing & Wholesale Goods"
        }
    ],
    "sg:phone":"+1 936 394 5101",
    "sg:postcode":"77861",
    "sg:province":"TX",
    "sg:tags":[
        "beef",
        "feedlot",
        "cattle"
    ],
    "wof:name":"J Howard",
    "wof:placetype":"venue"
},
  "geometry": {"coordinates":[-96.049575,30.693981],"type":"Point"}
}