{
  "type": "Feature",
  "properties": {
    "iso:country":"US",
    "sg:address":"421 State Hwy 7",
    "sg:city":"Center",
    "sg:classifiers":[
        {
            "category":"Retail",
            "subcategory":"Repair Shop",
            "type":"Services"
        }
    ],
    "sg:phone":"+1 936 598 9591",
    "sg:postcode":"75935",
    "sg:province":"TX",
    "sg:tags":[
        "welding"
    ],
    "wof:name":"Harris Welding & Fabrication",
    "wof:placetype":"venue"
},
  "geometry": {"coordinates":[-94.17800800000001,31.798774],"type":"Point"}
}