{
  "type": "Feature",
  "properties": {
    "iso:country":"US",
    "sg:address":"1018 N Mound St",
    "sg:city":"Nacogdoches",
    "sg:classifiers":[
        {
            "category":"Health Services",
            "subcategory":"Clinic",
            "type":"Services"
        }
    ],
    "sg:phone":"+1 936 564 4611",
    "sg:postcode":"75961",
    "sg:province":"TX",
    "sg:tags":[
        "occupational",
        "rehabilitation"
    ],
    "wof:name":"Elliot Building The",
    "wof:placetype":"venue"
},
  "geometry": {"coordinates":[-94.649372,31.614175],"type":"Point"}
}