{
  "type": "Feature",
  "properties": {
    "iso:country":"US",
    "sg:address":"440 N Eastman Rd",
    "sg:city":"Longview",
    "sg:classifiers":[
        {
            "category":"Building & Trades",
            "subcategory":"Electrical",
            "type":"Services"
        }
    ],
    "sg:phone":"+1 903 753 3507",
    "sg:postcode":"75601",
    "sg:province":"TX",
    "sg:tags":[
        "electrical",
        "contractor"
    ],
    "wof:name":"Stark Electric",
    "wof:placetype":"venue"
},
  "geometry": {"coordinates":[-94.709627,32.500603],"type":"Point"}
}