{
  "type": "Feature",
  "properties": {
    "iso:country":"US",
    "sg:address":"7718 Bellfort St",
    "sg:city":"Houston",
    "sg:classifiers":[
        {
            "category":"Social Services",
            "type":"Services"
        }
    ],
    "sg:phone":"+1 713 641 5187",
    "sg:postcode":"77061",
    "sg:province":"TX",
    "sg:tags":[
        "counseling"
    ],
    "wof:name":"Counseling Center",
    "wof:placetype":"venue"
},
  "geometry": {"coordinates":[-95.281446,29.672282],"type":"Point"}
}