{
  "type": "Feature",
  "properties": {
    "iso:country":"US",
    "sg:address":"912 W Jefferson Blvd Ste B",
    "sg:city":"Dallas",
    "sg:classifiers":[
        {
            "category":"Cinema",
            "subcategory":"Movie Rental",
            "type":"Entertainment"
        }
    ],
    "sg:phone":"+1 214 941 0996",
    "sg:postcode":"75208",
    "sg:province":"TX",
    "sg:tags":[
        "game",
        "video"
    ],
    "wof:name":"Video Arte",
    "wof:placetype":"venue"
},
  "geometry": {"coordinates":[-96.837799,32.743099],"type":"Point"}
}