{
  "type": "Feature",
  "properties": {
    "iso:country":"US",
    "sg:address":"University of Texas at Austin 2101 Speedway",
    "sg:city":"Austin",
    "sg:classifiers":[
        {
            "category":"Sports & Exercise",
            "subcategory":"Gym",
            "type":"Entertainment"
        }
    ],
    "sg:postcode":"78712",
    "sg:province":"TX",
    "sg:website":"www.utrecsports.org/facilities/l...",
    "wof:name":"Gregory Gym",
    "wof:placetype":"venue"
},
  "geometry": {"coordinates":[-97.737433,30.283481],"type":"Point"}
}