{
  "type": "Feature",
  "properties": {
    "iso:country":"US",
    "sg:address":"203 E Northwest Hwy",
    "sg:city":"Grapevine",
    "sg:classifiers":[
        {
            "category":"Insurance",
            "subcategory":"Insurance Agent",
            "type":"Services"
        }
    ],
    "sg:phone":"+1 817 424 0877",
    "sg:postcode":"76051",
    "sg:province":"TX",
    "wof:name":"Prudential Insurance Co",
    "wof:placetype":"venue"
},
  "geometry": {"coordinates":[-97.077057,32.941119],"type":"Point"}
}