{
  "type": "Feature",
  "properties": {
    "iso:country":"US",
    "sg:address":"1624 E Whaley St",
    "sg:city":"Longview",
    "sg:classifiers":[
        {
            "category":"Wholesale",
            "subcategory":"Machinery & Supplies",
            "type":"Manufacturing & Wholesale Goods"
        }
    ],
    "sg:phone":"+1 903 234 2895",
    "sg:postcode":"75601",
    "sg:province":"TX",
    "sg:tags":[
        "industrial",
        "equipment",
        "used",
        "machinery-new",
        "supplies-wholesale"
    ],
    "wof:name":"Industrial Mill & Maintenance Supply",
    "wof:placetype":"venue"
},
  "geometry": {"coordinates":[-94.715507,32.499344],"type":"Point"}
}