{
  "type": "Feature",
  "properties": {
    "iso:country":"US",
    "sg:address":"4608 Clay Court Ln",
    "sg:city":"Arlington",
    "sg:classifiers":[
        {
            "category":"Wholesale",
            "subcategory":"Medical Equipment & Supplies",
            "type":"Manufacturing & Wholesale Goods"
        }
    ],
    "sg:phone":"+1 817 557 5578",
    "sg:postcode":"76017",
    "sg:province":"TX",
    "wof:name":"McTronics",
    "wof:placetype":"venue"
},
  "geometry": {"coordinates":[-97.14094299999999,32.670586],"type":"Point"}
}