{
  "type": "Feature",
  "properties": {
    "iso:country":"US",
    "sg:address":"2208 N Oregon St",
    "sg:city":"El Paso",
    "sg:classifiers":[
        {
            "category":"Banks & Credit Unions",
            "subcategory":"Bank",
            "type":"Services"
        }
    ],
    "sg:phone":"+1 915 593 5866",
    "sg:postcode":"79902",
    "sg:province":"TX",
    "wof:name":"El Paso Employees Federal CU",
    "wof:placetype":"venue"
},
  "geometry": {"coordinates":[-106.50132499999999,31.773497],"type":"Point"}
}