{
  "type": "Feature",
  "properties": {
    "iso:country":"US",
    "sg:address":"2122 E Crosby Rd",
    "sg:city":"Carrollton",
    "sg:classifiers":[
        {
            "category":"Shopping",
            "subcategory":"Computers & Home Electronics",
            "type":"Retail Goods"
        }
    ],
    "sg:phone":"+1 972 416 4162",
    "sg:postcode":"75006",
    "sg:province":"TX",
    "wof:name":"Personal Computer Assistance",
    "wof:placetype":"venue"
},
  "geometry": {"coordinates":[-96.881908,32.950526],"type":"Point"}
}