{
  "type": "Feature",
  "properties": {
    "iso:country":"US",
    "sg:address":"433 S Main St",
    "sg:city":"Kermit",
    "sg:classifiers":[
        {
            "category":"Building & Trades",
            "subcategory":"Construction",
            "type":"Services"
        }
    ],
    "sg:phone":"+1 432 586 3689",
    "sg:postcode":"79745",
    "sg:province":"TX",
    "sg:tags":[
        "general",
        "contractor"
    ],
    "wof:name":"Rodriguez General Contractor",
    "wof:placetype":"venue"
},
  "geometry": {"coordinates":[-103.097701,31.852276],"type":"Point"}
}