{
  "type": "Feature",
  "properties": {
    "iso:country":"US",
    "sg:address":"4700 Seton Center Pkwy Ste. 200",
    "sg:city":"Austin",
    "sg:classifiers":[
        {
            "category":"Health Services",
            "subcategory":"Doctor",
            "type":"Services"
        }
    ],
    "sg:phone":"+1 512 439 1000",
    "sg:postcode":"78759",
    "sg:province":"TX",
    "sg:tags":[
        "medicine",
        "sport",
        "orthopedist"
    ],
    "sg:website":"www.txortho.com",
    "wof:name":"Smoot J Brannan MD",
    "wof:placetype":"venue"
},
  "geometry": {"coordinates":[-97.742546,30.402911],"type":"Point"}
}