{
  "type": "Feature",
  "properties": {
    "iso:country":"US",
    "sg:address":"3141 Wilson Valley Rd",
    "sg:city":"Little River",
    "sg:phone":"+1 254 982 4390",
    "sg:postcode":"76554",
    "sg:province":"TX",
    "sg:tags":[
        "farm",
        "corn"
    ],
    "wof:name":"Richard Cortese",
    "wof:placetype":"venue"
},
  "geometry": {"coordinates":[-97.36908,30.983899],"type":"Point"}
}