{
  "type": "Feature",
  "properties": {
    "iso:country":"US",
    "sg:address":"3033 US Hwy 77",
    "sg:city":"La Grange",
    "sg:classifiers":[
        {
            "category":"Real Estate",
            "subcategory":"Real Estate Operator",
            "type":"Services"
        }
    ],
    "sg:phone":"+1 979 968 6868",
    "sg:postcode":"78945",
    "sg:province":"TX",
    "sg:tags":[
        "mobile",
        "site",
        "track",
        "home",
        "operation",
        "racing",
        "or"
    ],
    "wof:name":"Campbell R V Park",
    "wof:placetype":"venue"
},
  "geometry": {"coordinates":[-96.884535,29.874516],"type":"Point"}
}