{
  "type": "Feature",
  "properties": {
    "iso:country":"US",
    "sg:address":"2613 Potomac Dr",
    "sg:city":"Houston",
    "sg:classifiers":[
        {
            "category":"Personal",
            "subcategory":"Day Spa",
            "type":"Services"
        }
    ],
    "sg:phone":"+1 713 244 0070",
    "sg:postcode":"77057",
    "sg:province":"TX",
    "sg:website":"www.fiorispa.com",
    "wof:name":"Fiori Spa",
    "wof:placetype":"venue"
},
  "geometry": {"coordinates":[-95.488573,29.739104],"type":"Point"}
}