{
  "type": "Feature",
  "properties": {
    "iso:country":"US",
    "sg:address":"2910 Lazy Lake Dr",
    "sg:city":"Harlingen",
    "sg:classifiers":[
        {
            "category":"Professional",
            "subcategory":"Lawyer & Legal Services",
            "type":"Services"
        }
    ],
    "sg:phone":"+1 956 440 9455",
    "sg:postcode":"78550",
    "sg:province":"TX",
    "sg:tags":[
        "attorney"
    ],
    "wof:name":"Richard Bilbie",
    "wof:placetype":"venue"
},
  "geometry": {"coordinates":[-97.658821,26.180798],"type":"Point"}
}