{
  "type": "Feature",
  "properties": {
    "iso:country":"US",
    "sg:address":"7500 San Felipe St",
    "sg:city":"Houston",
    "sg:classifiers":[
        {
            "category":"Building & Trades",
            "subcategory":"Plumbing",
            "type":"Services"
        }
    ],
    "sg:phone":"+1 713 243 8550",
    "sg:postcode":"77063",
    "sg:province":"TX",
    "sg:tags":[
        "product",
        "management",
        "energy",
        "system"
    ],
    "wof:name":"Landmark Energy",
    "wof:placetype":"venue"
},
  "geometry": {"coordinates":[-95.50182599999999,29.750431],"type":"Point"}
}