{
  "type": "Feature",
  "properties": {
    "iso:country":"US",
    "sg:address":"222 Avenue E",
    "sg:city":"Alvin",
    "sg:classifiers":[
        {
            "category":"Place Of Worship",
            "subcategory":"Church",
            "type":"Public Place"
        },
        {
            "category":"Place Of Worship",
            "type":"Public Place"
        },
        {
            "category":"Place Of Worship",
            "subcategory":"Temple",
            "type":"Public Place"
        }
    ],
    "sg:phone":"+1 281 585 4176",
    "sg:postcode":"77511",
    "sg:province":"TX",
    "sg:tags":[
        "churches-pentecostal"
    ],
    "wof:name":"Templo El Calvario Church",
    "wof:placetype":"venue"
},
  "geometry": {"coordinates":[-95.245611,29.431022],"type":"Point"}
}