{
  "type": "Feature",
  "properties": {
    "iso:country":"US",
    "sg:address":"6209 Tiffany Oaks Ln",
    "sg:city":"Arlington",
    "sg:classifiers":[
        {
            "category":"Manufacturing",
            "subcategory":"Aerospace",
            "type":"Manufacturing & Wholesale Goods"
        }
    ],
    "sg:phone":"+1 817 446 5220",
    "sg:postcode":"76016",
    "sg:province":"TX",
    "sg:tags":[
        "helicopter"
    ],
    "wof:name":"Transportation Solutions-Texas",
    "wof:placetype":"venue"
},
  "geometry": {"coordinates":[-97.20383099999999,32.696253],"type":"Point"}
}