{
  "type": "Feature",
  "properties": {
    "iso:country":"US",
    "sg:address":"2053 W Northwest Hwy",
    "sg:city":"Dallas",
    "sg:classifiers":[
        {
            "category":"Restaurant",
            "type":"Food & Drink"
        }
    ],
    "sg:phone":"+1 972 506 7561",
    "sg:postcode":"75220",
    "sg:province":"TX",
    "sg:tags":[
        "barbecue"
    ],
    "wof:name":"B & J BBQ",
    "wof:placetype":"venue"
},
  "geometry": {"coordinates":[-96.90719799999999,32.866938],"type":"Point"}
}