{
  "type": "Feature",
  "properties": {
    "iso:country":"US",
    "sg:address":"806 50th St",
    "sg:city":"Lubbock",
    "sg:classifiers":[
        {
            "category":"Retail",
            "subcategory":"Auto Repair",
            "type":"Services"
        }
    ],
    "sg:phone":"+1 806 747 3459",
    "sg:postcode":"79404",
    "sg:province":"TX",
    "sg:tags":[
        "body",
        "shop",
        "painting",
        "automobile"
    ],
    "wof:name":"Hub City Body Works Inc",
    "wof:placetype":"venue"
},
  "geometry": {"coordinates":[-101.843625,33.548858],"type":"Point"}
}