{
  "type": "Feature",
  "properties": {
    "iso:country":"US",
    "sg:address":"500 Ameron Rd",
    "sg:city":"Burkburnett",
    "sg:classifiers":[
        {
            "category":"Professional",
            "subcategory":"Business Services",
            "type":"Services"
        }
    ],
    "sg:phone":"+1 940 569 5025",
    "sg:postcode":"76354",
    "sg:province":"TX",
    "wof:name":"Farriers",
    "wof:placetype":"venue"
},
  "geometry": {"coordinates":[-98.570153,34.077699],"type":"Point"}
}