{
  "type": "Feature",
  "properties": {
    "iso:country":"US",
    "sg:address":"16011 Shalamar Dr",
    "sg:city":"Magnolia",
    "sg:classifiers":[
        {
            "category":"Shopping",
            "type":"Retail Goods"
        }
    ],
    "sg:phone":"+1 281 356 5479",
    "sg:postcode":"77354",
    "sg:province":"TX",
    "sg:tags":[
        "merchandise"
    ],
    "wof:name":"Delightful Lites",
    "wof:placetype":"venue"
},
  "geometry": {"coordinates":[-95.71755899999999,30.2304],"type":"Point"}
}