{
  "type": "Feature",
  "properties": {
    "iso:country":"US",
    "sg:address":"615 Perez St",
    "sg:city":"San Antonio",
    "sg:classifiers":[
        {
            "category":"Manufacturing",
            "subcategory":"Rubber & Plastics",
            "type":"Manufacturing & Wholesale Goods"
        }
    ],
    "sg:phone":"+1 210 223 1071",
    "sg:postcode":"78207",
    "sg:province":"TX",
    "sg:tags":[
        "product"
    ],
    "wof:name":"Koozle Co",
    "wof:placetype":"venue"
},
  "geometry": {"coordinates":[-98.50786100000001,29.432621],"type":"Point"}
}