{
  "type": "Feature",
  "properties": {
    "iso:country":"US",
    "sg:address":"814 Vine St",
    "sg:city":"Cleveland",
    "sg:classifiers":[
        {
            "category":"Organizations",
            "subcategory":"Religious Organization",
            "type":"Services"
        }
    ],
    "sg:phone":"+1 281 593 1997",
    "sg:postcode":"77327",
    "sg:province":"TX",
    "wof:name":"New Bethel A M E Church",
    "wof:placetype":"venue"
},
  "geometry": {"coordinates":[-95.079058,30.350407],"type":"Point"}
}