{
  "type": "Feature",
  "properties": {
    "iso:country":"US",
    "sg:address":"4051 Hampshire Blvd",
    "sg:city":"Fort Worth",
    "sg:classifiers":[
        {
            "category":"Real Estate",
            "subcategory":"Real Estate Agent",
            "type":"Services"
        }
    ],
    "sg:phone":"+1 817 536 0344",
    "sg:postcode":"76103",
    "sg:province":"TX",
    "wof:name":"Elvis Morris",
    "wof:placetype":"venue"
},
  "geometry": {"coordinates":[-97.26364599999999,32.736554],"type":"Point"}
}