{
  "type": "Feature",
  "properties": {
    "iso:country":"US",
    "sg:address":"508 S Elm St Ste J",
    "sg:city":"Denton",
    "sg:classifiers":[
        {
            "category":"Personal",
            "subcategory":"Beauty Salon",
            "type":"Services"
        }
    ],
    "sg:phone":"+1 940 387 2800",
    "sg:postcode":"76201",
    "sg:province":"TX",
    "wof:name":"Mia's Hair Salon",
    "wof:placetype":"venue"
},
  "geometry": {"coordinates":[-97.133754,33.210566],"type":"Point"}
}