{
  "type": "Feature",
  "properties": {
    "iso:country":"US",
    "sg:address":"11116 N Stemmons Fwy",
    "sg:city":"Dallas",
    "sg:classifiers":[
        {
            "category":"Shopping",
            "subcategory":"Bicycles & Sporting Goods",
            "type":"Retail Goods"
        }
    ],
    "sg:phone":"+1 972 527 6494",
    "sg:postcode":"75229",
    "sg:province":"TX",
    "sg:tags":[
        "equipment",
        "exercise"
    ],
    "wof:name":"Fitness Clearing House",
    "wof:placetype":"venue"
},
  "geometry": {"coordinates":[-96.897884,32.887412],"type":"Point"}
}