{
  "type": "Feature",
  "properties": {
    "iso:country":"US",
    "sg:address":"4909 Enchanted Ln",
    "sg:city":"Austin",
    "sg:classifiers":[
        {
            "category":"Professional",
            "subcategory":"Accounting & Tax Preparation",
            "type":"Services"
        }
    ],
    "sg:phone":"+1 512 442 8374",
    "sg:postcode":"78745",
    "sg:province":"TX",
    "sg:tags":[
        "return"
    ],
    "wof:name":"Izzys Tax & Fin Services",
    "wof:placetype":"venue"
},
  "geometry": {"coordinates":[-97.789001,30.221988],"type":"Point"}
}