{
  "type": "Feature",
  "properties": {
    "iso:country":"US",
    "sg:address":"1126 Alametos",
    "sg:city":"San Antonio",
    "sg:classifiers":[
        {
            "category":"Organizations",
            "subcategory":"Membership Organization",
            "type":"Services"
        }
    ],
    "sg:phone":"+1 210 734 6189",
    "sg:postcode":"78201",
    "sg:province":"TX",
    "wof:name":"Predators Football Team",
    "wof:placetype":"venue"
},
  "geometry": {"coordinates":[-98.51253699999999,29.476867],"type":"Point"}
}