{
  "type": "Feature",
  "properties": {
    "iso:country":"US",
    "sg:address":"131 Memory Ln",
    "sg:city":"Palestine",
    "sg:classifiers":[
        {
            "category":"Real Estate",
            "subcategory":"Real Estate Operator",
            "type":"Services"
        }
    ],
    "sg:phone":"+1 903 729 5020",
    "sg:postcode":"75801",
    "sg:province":"TX",
    "sg:tags":[
        "building",
        "apartment"
    ],
    "wof:name":"Oak Hill Apartments",
    "wof:placetype":"venue"
},
  "geometry": {"coordinates":[-95.604218,31.732496],"type":"Point"}
}