{
  "type": "Feature",
  "properties": {
    "iso:country":"US",
    "sg:address":"439 Edmonds Way",
    "sg:city":"De Soto",
    "sg:classifiers":[
        {
            "category":"Shopping",
            "subcategory":"Music",
            "type":"Retail Goods"
        }
    ],
    "sg:phone":"+1 972 223 0709",
    "sg:postcode":"75115",
    "sg:province":"TX",
    "wof:name":"Tiger Paw Productions",
    "wof:placetype":"venue"
},
  "geometry": {"coordinates":[-96.86069000000001,32.583386],"type":"Point"}
}