{
  "type": "Feature",
  "properties": {
    "iso:country":"US",
    "sg:address":"1910 N Carroll Ave",
    "sg:city":"Dallas",
    "sg:classifiers":[
        {
            "category":"Professional",
            "subcategory":"Management & Consulting",
            "type":"Services"
        }
    ],
    "sg:phone":"+1 214 826 2409",
    "sg:postcode":"75204",
    "sg:province":"TX",
    "sg:tags":[
        "public",
        "relations"
    ],
    "wof:name":"Hal Perkinson Consultants",
    "wof:placetype":"venue"
},
  "geometry": {"coordinates":[-96.781944,32.804161],"type":"Point"}
}