{
  "type": "Feature",
  "properties": {
    "iso:country":"US",
    "sg:address":"1714 NE 16th Ave",
    "sg:city":"Amarillo",
    "sg:classifiers":[
        {
            "category":"Home & Garden",
            "subcategory":"Garden Supply",
            "type":"Retail Goods"
        }
    ],
    "sg:phone":"+1 806 383 1917",
    "sg:postcode":"79107",
    "sg:province":"TX",
    "sg:tags":[
        "ornament"
    ],
    "wof:name":"Willard W Davis",
    "wof:placetype":"venue"
},
  "geometry": {"coordinates":[-101.812825,35.231209],"type":"Point"}
}