{
  "type": "Feature",
  "properties": {
    "iso:country":"US",
    "sg:address":"2523 E Pearl St",
    "sg:city":"Odessa",
    "sg:classifiers":[
        {
            "category":"Freight",
            "type":"Transportation"
        }
    ],
    "sg:phone":"+1 432 334 8055",
    "sg:postcode":"79761",
    "sg:province":"TX",
    "sg:tags":[
        "trucking"
    ],
    "wof:name":"Old Dominion Freight Line",
    "wof:placetype":"venue"
},
  "geometry": {"coordinates":[-102.331423,31.860513],"type":"Point"}
}