{
  "type": "Feature",
  "properties": {
    "iso:country":"US",
    "sg:address":"1919 W Sam Houston Pkwy N # 312",
    "sg:city":"Houston",
    "sg:classifiers":[
        {
            "category":"Museum",
            "subcategory":"Aquarium",
            "type":"Entertainment"
        }
    ],
    "sg:phone":"+1 281 652 6331",
    "sg:postcode":"77043",
    "sg:province":"TX",
    "sg:tags":[
        "public"
    ],
    "wof:name":"Aquarium Outfitters",
    "wof:placetype":"venue"
},
  "geometry": {"coordinates":[-95.56403400000001,29.807287],"type":"Point"}
}