{
  "type": "Feature",
  "properties": {
    "iso:country":"US",
    "sg:address":"203 W Olmos Dr",
    "sg:city":"San Antonio",
    "sg:classifiers":[
        {
            "category":"Health Services",
            "subcategory":"Doctor",
            "type":"Services"
        }
    ],
    "sg:phone":"+1 210 826 2300",
    "sg:postcode":"78212",
    "sg:province":"TX",
    "sg:tags":[
        "physician",
        "surgeon"
    ],
    "wof:name":"Cynthia L Hoyler MD",
    "wof:placetype":"venue"
},
  "geometry": {"coordinates":[-98.495502,29.471015],"type":"Point"}
}