{
  "type": "Feature",
  "properties": {
    "iso:country":"US",
    "sg:address":"1515 S Buckner Blvd",
    "sg:city":"Dallas",
    "sg:classifiers":[
        {
            "category":"Food & Beverages",
            "subcategory":"Groceries & Convenience Stores",
            "type":"Retail Goods"
        }
    ],
    "sg:phone":"+1 214 391 1200",
    "sg:postcode":"75217",
    "sg:province":"TX",
    "sg:website":"www.elranchoinc.com/el/index.html",
    "wof:name":"El Rancho",
    "wof:placetype":"venue"
},
  "geometry": {"coordinates":[-96.682429,32.796248],"type":"Point"}
}