{
  "type": "Feature",
  "properties": {
    "iso:country":"US",
    "sg:address":"1012 Mark Twain Dr",
    "sg:city":"Allen",
    "sg:classifiers":[
        {
            "category":"Retail",
            "subcategory":"Animal Services",
            "type":"Services"
        }
    ],
    "sg:phone":"+1 972 396 1217",
    "sg:postcode":"75002",
    "sg:province":"TX",
    "sg:tags":[
        "pet"
    ],
    "wof:name":"Mr Pooper Scooper",
    "wof:placetype":"venue"
},
  "geometry": {"coordinates":[-96.65005499999999,33.079243],"type":"Point"}
}