{
  "type": "Feature",
  "properties": {
    "iso:country":"US",
    "sg:address":"1816 Valerie Dr",
    "sg:city":"Eagle Pass",
    "sg:classifiers":[
        {
            "category":"Organizations",
            "subcategory":"Religious Organization",
            "type":"Services"
        }
    ],
    "sg:phone":"+1 830 773 1364",
    "sg:postcode":"78852",
    "sg:province":"TX",
    "wof:name":"Jesus Morales Delgado",
    "wof:placetype":"venue"
},
  "geometry": {"coordinates":[-100.49057500000001,28.750382],"type":"Point"}
}