{
  "type": "Feature",
  "properties": {
    "iso:country":"US",
    "sg:address":"412 North Rd",
    "sg:city":"Kennedale",
    "sg:classifiers":[
        {
            "category":"Wholesale",
            "subcategory":"Non-durable Goods",
            "type":"Manufacturing & Wholesale Goods"
        }
    ],
    "sg:phone":"+1 817 483 5256",
    "sg:postcode":"76060",
    "sg:province":"TX",
    "wof:name":"Betty J Guerrero Goods",
    "wof:placetype":"venue"
},
  "geometry": {"coordinates":[-97.22932299999999,32.646207],"type":"Point"}
}