{
  "type": "Feature",
  "properties": {
    "iso:country":"US",
    "sg:address":"7318 Bennington Dr",
    "sg:city":"Dallas",
    "sg:classifiers":[
        {
            "category":"Social Services",
            "subcategory":"Job Training",
            "type":"Services"
        }
    ],
    "sg:phone":"+1 214 341 2756",
    "sg:postcode":"75214",
    "sg:province":"TX",
    "sg:tags":[
        "personnel",
        "management"
    ],
    "wof:name":"Peter Dickson",
    "wof:placetype":"venue"
},
  "geometry": {"coordinates":[-96.73865600000001,32.850405],"type":"Point"}
}