{
  "type": "Feature",
  "properties": {
    "iso:country":"US",
    "sg:address":"2606 Martin Luther King Jr Blvd Ste 212",
    "sg:city":"Dallas",
    "sg:classifiers":[
        {
            "category":"Communications",
            "subcategory":"Newspaper",
            "type":"Services"
        }
    ],
    "sg:phone":"+1 214 565 8582",
    "sg:postcode":"75215",
    "sg:province":"TX",
    "sg:tags":[
        "print",
        "medium"
    ],
    "sg:website":"www.rollingout.com",
    "wof:name":"Rolling Out",
    "wof:placetype":"venue"
},
  "geometry": {"coordinates":[-96.770563,32.767046],"type":"Point"}
}