{
  "type": "Feature",
  "properties": {
    "iso:country":"US",
    "sg:address":"3907 Spinnaker Run Pt",
    "sg:city":"Little Elm",
    "sg:classifiers":[
        {
            "category":"Building & Trades",
            "subcategory":"Construction",
            "type":"Services"
        }
    ],
    "sg:phone":"+1 972 292 3483",
    "sg:postcode":"75068",
    "sg:province":"TX",
    "sg:tags":[
        "contractor"
    ],
    "wof:name":"Landers Pools Inc",
    "wof:placetype":"venue"
},
  "geometry": {"coordinates":[-96.970456,33.145849],"type":"Point"}
}