{
  "type": "Feature",
  "properties": {
    "iso:country":"US",
    "sg:address":"2765 Valencia Ln",
    "sg:city":"Schertz",
    "sg:classifiers":[
        {
            "category":"Government",
            "subcategory":"Police Station",
            "type":"Public Place"
        }
    ],
    "sg:phone":"+1 210 207 3983",
    "sg:postcode":"78154",
    "sg:province":"TX",
    "sg:tags":[
        "protection"
    ],
    "wof:name":"San Antonio Police Department",
    "wof:placetype":"venue"
},
  "geometry": {"coordinates":[-98.26302099999999,29.58279],"type":"Point"}
}