{
  "type": "Feature",
  "properties": {
    "iso:country":"US",
    "sg:address":"17780 Preston Rd Ste 130",
    "sg:city":"Dallas",
    "sg:classifiers":[
        {
            "category":"Banks & Credit Unions",
            "subcategory":"Financial Services",
            "type":"Services"
        }
    ],
    "sg:phone":"+1 972 818 6100",
    "sg:postcode":"75252",
    "sg:province":"TX",
    "sg:tags":[
        "broker",
        "mortgage"
    ],
    "wof:name":"C M I Mortgage",
    "wof:placetype":"venue"
},
  "geometry": {"coordinates":[-96.799471,32.994121],"type":"Point"}
}