{
  "type": "Feature",
  "properties": {
    "iso:country":"US",
    "sg:address":"313 N Commerce St",
    "sg:city":"Gainesville",
    "sg:classifiers":[
        {
            "category":"Shopping",
            "subcategory":"Computers & Home Electronics",
            "type":"Retail Goods"
        }
    ],
    "sg:phone":"+1 940 665 6076",
    "sg:postcode":"76240",
    "sg:province":"TX",
    "sg:tags":[
        "equipment",
        "dealer"
    ],
    "wof:name":"Leeper's Computer Works",
    "wof:placetype":"venue"
},
  "geometry": {"coordinates":[-97.14622900000001,33.626947],"type":"Point"}
}