{
  "type": "Feature",
  "properties": {
    "iso:country":"US",
    "sg:address":"311 S Lamar St",
    "sg:city":"Eastland",
    "sg:classifiers":[
        {
            "category":"Organizations",
            "subcategory":"Religious Organization",
            "type":"Services"
        }
    ],
    "sg:phone":"+1 254 631 0608",
    "sg:postcode":"76448",
    "sg:province":"TX",
    "wof:name":"Kingdom Builders Fellowship",
    "wof:placetype":"venue"
},
  "geometry": {"coordinates":[-98.819107,32.400156],"type":"Point"}
}