{
  "type": "Feature",
  "properties": {
    "iso:country":"US",
    "sg:address":"3000 Yellowstone Blvd",
    "sg:city":"Houston",
    "sg:classifiers":[
        {
            "category":"Building & Trades",
            "subcategory":"Construction",
            "type":"Services"
        }
    ],
    "sg:phone":"+1 713 748 3580",
    "sg:postcode":"77021",
    "sg:province":"TX",
    "sg:tags":[
        "woodworker"
    ],
    "wof:name":"Architectural Woodwork Corp",
    "wof:placetype":"venue"
},
  "geometry": {"coordinates":[-95.381321,29.699844],"type":"Point"}
}