{
  "type": "Feature",
  "properties": {
    "iso:country":"US",
    "sg:address":"7138 Cano Ln",
    "sg:city":"Corpus Christi",
    "sg:classifiers":[
        {
            "category":"Professional",
            "subcategory":"Engineering",
            "type":"Services"
        }
    ],
    "sg:phone":"+1 361 882 0300",
    "sg:postcode":"78414",
    "sg:province":"TX",
    "sg:tags":[
        "engineer"
    ],
    "wof:name":"Mann Consulting Corp",
    "wof:placetype":"venue"
},
  "geometry": {"coordinates":[-97.351023,27.680417],"type":"Point"}
}