{
  "type": "Feature",
  "properties": {
    "iso:country":"US",
    "sg:address":"3103 Pleasant Grove Rd",
    "sg:city":"Texarkana",
    "sg:classifiers":[
        {
            "category":"Health Services",
            "subcategory":"Medical Lab",
            "type":"Services"
        }
    ],
    "sg:phone":"+1 903 832 3979",
    "sg:postcode":"75503",
    "sg:province":"TX",
    "sg:tags":[
        "laboratory",
        "dental"
    ],
    "wof:name":"Dental Designs",
    "wof:placetype":"venue"
},
  "geometry": {"coordinates":[-94.120464,33.464018],"type":"Point"}
}