{
  "type": "Feature",
  "properties": {
    "iso:country":"US",
    "sg:address":"415 Houston Ave",
    "sg:city":"Pasadena",
    "sg:classifiers":[
        {
            "category":"Manufacturing",
            "subcategory":"Printing",
            "type":"Manufacturing & Wholesale Goods"
        }
    ],
    "sg:phone":"+1 713 473 0930",
    "sg:postcode":"77502",
    "sg:province":"TX",
    "sg:tags":[
        "screen"
    ],
    "wof:name":"Courier Screen Printing",
    "wof:placetype":"venue"
},
  "geometry": {"coordinates":[-95.214799,29.686798],"type":"Point"}
}