{
  "type": "Feature",
  "properties": {
    "iso:country":"US",
    "sg:address":"2317 Pruett St",
    "sg:city":"Austin",
    "sg:classifiers":[
        {
            "category":"Professional",
            "type":"Services"
        }
    ],
    "sg:phone":"+1 512 473 8551",
    "sg:postcode":"78703",
    "sg:province":"TX",
    "wof:name":"Accesorios De San Miguel",
    "wof:placetype":"venue"
},
  "geometry": {"coordinates":[-97.77382799999999,30.282258],"type":"Point"}
}