{
  "type": "Feature",
  "properties": {
    "iso:country":"US",
    "sg:address":"106 Hopkins St",
    "sg:city":"Alba",
    "sg:classifiers":[
        {
            "category":"Food & Beverages",
            "subcategory":"Bakery",
            "type":"Retail Goods"
        }
    ],
    "sg:phone":"+1 903 765 9144",
    "sg:postcode":"75410",
    "sg:province":"TX",
    "sg:tags":[
        "bank"
    ],
    "sg:website":"http://www.mowaa.org",
    "wof:name":"Meals On Wheels",
    "wof:placetype":"venue"
},
  "geometry": {"coordinates":[-95.637468,32.793],"type":"Point"}
}