{
  "type": "Feature",
  "properties": {
    "iso:country":"US",
    "sg:address":"14905 Southwest Fwy",
    "sg:city":"Sugar Land",
    "sg:classifiers":[
        {
            "category":"Insurance",
            "subcategory":"Insurance Agent",
            "type":"Services"
        }
    ],
    "sg:phone":"+1 281 242 8880",
    "sg:postcode":"77478",
    "sg:province":"TX",
    "wof:name":"Don Turner Insurance Agency",
    "wof:placetype":"venue"
},
  "geometry": {"coordinates":[-95.611721,29.608548],"type":"Point"}
}