{
  "type": "Feature",
  "properties": {
    "iso:country":"US",
    "sg:address":"3084 Martin Luther King Dr",
    "sg:city":"San Antonio",
    "sg:classifiers":[
        {
            "category":"Insurance",
            "subcategory":"Hazard Insurance",
            "type":"Services"
        }
    ],
    "sg:phone":"+1 210 212 2294",
    "sg:postcode":"78220",
    "sg:province":"TX",
    "sg:tags":[
        "bond"
    ],
    "wof:name":"Mitchell Bail Bonds",
    "wof:placetype":"venue"
},
  "geometry": {"coordinates":[-98.436756,29.413432],"type":"Point"}
}