{
  "type": "Feature",
  "properties": {
    "iso:country":"US",
    "sg:address":"14001 State Hwy 29",
    "sg:city":"Liberty Hill",
    "sg:classifiers":[
        {
            "category":"Education",
            "subcategory":"School",
            "type":"Public Place"
        }
    ],
    "sg:phone":"+1 512 260 5590",
    "sg:postcode":"78642",
    "sg:province":"TX",
    "wof:name":"Liberty Hill Special Education",
    "wof:placetype":"venue"
},
  "geometry": {"coordinates":[-97.916224,30.670369],"type":"Point"}
}