{
  "type": "Feature",
  "properties": {
    "iso:country":"US",
    "sg:address":"400 E 13th St",
    "sg:city":"Brownsville",
    "sg:classifiers":[
        {
            "category":"Wholesale",
            "subcategory":"Metals & Minerals",
            "type":"Manufacturing & Wholesale Goods"
        }
    ],
    "sg:phone":"+1 956 542 7865",
    "sg:postcode":"78520",
    "sg:province":"TX",
    "sg:tags":[
        "center"
    ],
    "wof:name":"Rio Bravo Alloys Ltd",
    "wof:placetype":"venue"
},
  "geometry": {"coordinates":[-97.497334,25.900302],"type":"Point"}
}