{
  "type": "Feature",
  "properties": {
    "iso:country":"US",
    "sg:address":"2929 Irving Blvd",
    "sg:city":"Dallas",
    "sg:classifiers":[
        {
            "category":"Farming",
            "subcategory":"Livestock Farm",
            "type":"Manufacturing & Wholesale Goods"
        }
    ],
    "sg:phone":"+1 214 638 7320",
    "sg:postcode":"75247",
    "sg:province":"TX",
    "sg:tags":[
        "general"
    ],
    "wof:name":"Briggs Ranch Genetics",
    "wof:placetype":"venue"
},
  "geometry": {"coordinates":[-96.852407,32.809346],"type":"Point"}
}