{
  "type": "Feature",
  "properties": {
    "iso:country":"US",
    "sg:address":"182 River Hills Dr",
    "sg:city":"Denison",
    "sg:classifiers":[
        {
            "category":"Organizations",
            "subcategory":"Community Association",
            "type":"Services"
        }
    ],
    "sg:phone":"+1 903 327 8718",
    "sg:postcode":"75020",
    "sg:province":"TX",
    "wof:name":"River Hills Owners Assoc",
    "wof:placetype":"venue"
},
  "geometry": {"coordinates":[-96.60804400000001,33.709353],"type":"Point"}
}