{
  "type": "Feature",
  "properties": {
    "iso:country":"US",
    "sg:address":"8080 Park Ln Ste 700",
    "sg:city":"Dallas",
    "sg:classifiers":[
        {
            "category":"Real Estate",
            "subcategory":"Real Estate Services",
            "type":"Services"
        },
        {
            "category":"Professional",
            "subcategory":"Lawyer & Legal Services",
            "type":"Services"
        }
    ],
    "sg:phone":"+1 214 691 5088",
    "sg:postcode":"75231",
    "sg:province":"TX",
    "sg:website":"www.cthmlaw.com",
    "wof:name":"Condon David N Atty",
    "wof:placetype":"venue"
},
  "geometry": {"coordinates":[-96.767967,32.870892],"type":"Point"}
}