{
  "type": "Feature",
  "properties": {
    "iso:country":"US",
    "sg:address":"3509 Dennis St",
    "sg:city":"Rowlett",
    "sg:classifiers":[
        {
            "category":"Organizations",
            "subcategory":"Religious Organization",
            "type":"Services"
        }
    ],
    "sg:phone":"+1 972 463 5499",
    "sg:postcode":"75088",
    "sg:province":"TX",
    "sg:tags":[
        "church"
    ],
    "wof:name":"Friendly Wayside Church Of God",
    "wof:placetype":"venue"
},
  "geometry": {"coordinates":[-96.56955600000001,32.901742],"type":"Point"}
}