{
  "type": "Feature",
  "properties": {
    "iso:country":"US",
    "sg:address":"4520 21st St",
    "sg:city":"Lubbock",
    "sg:classifiers":[
        {
            "category":"Real Estate",
            "subcategory":"Real Estate Agent",
            "type":"Services"
        }
    ],
    "sg:phone":"+1 806 795 8561",
    "sg:postcode":"79407",
    "sg:province":"TX",
    "wof:name":"Homevestors-Providence Interes",
    "wof:placetype":"venue"
},
  "geometry": {"coordinates":[-101.910217,33.5752],"type":"Point"}
}