{
  "type": "Feature",
  "properties": {
    "iso:country":"US",
    "sg:address":"10101 Mula Rd",
    "sg:city":"Stafford",
    "sg:classifiers":[
        {
            "category":"Mining & Drilling",
            "type":"Manufacturing & Wholesale Goods"
        }
    ],
    "sg:phone":"+1 281 495 1828",
    "sg:postcode":"77477",
    "sg:province":"TX",
    "sg:tags":[
        "oil",
        "well"
    ],
    "sg:website":"www.foglemfg.com",
    "wof:name":"Fogle Manufacturing Co",
    "wof:placetype":"venue"
},
  "geometry": {"coordinates":[-95.554722,29.632755],"type":"Point"}
}