{
  "type": "Feature",
  "properties": {
    "iso:country":"US",
    "sg:address":"8110 Broken Branch Dr",
    "sg:city":"Round Rock",
    "sg:classifiers":[
        {
            "category":"Shopping",
            "subcategory":"Gifts & Souvenirs",
            "type":"Retail Goods"
        }
    ],
    "sg:phone":"+1 512 671 6765",
    "sg:postcode":"78681",
    "sg:province":"TX",
    "sg:tags":[
        "shop"
    ],
    "wof:name":"Life's A Gift",
    "wof:placetype":"venue"
},
  "geometry": {"coordinates":[-97.72450499999999,30.512622],"type":"Point"}
}