{
  "type": "Feature",
  "properties": {
    "iso:country":"US",
    "sg:address":"700 N San Jacinto St",
    "sg:city":"Conroe",
    "sg:classifiers":[
        {
            "category":"Professional",
            "subcategory":"Lawyer & Legal Services",
            "type":"Services"
        }
    ],
    "sg:phone":"+1 936 760 2777",
    "sg:postcode":"77301",
    "sg:province":"TX",
    "sg:tags":[
        "attorney"
    ],
    "wof:name":"J Timothy Sisk PC",
    "wof:placetype":"venue"
},
  "geometry": {"coordinates":[-95.459143,30.315738],"type":"Point"}
}