{
  "type": "Feature",
  "properties": {
    "iso:country":"US",
    "sg:address":"3117 E Yvonne",
    "sg:city":"Edinburg",
    "sg:classifiers":[
        {
            "category":"Building & Trades",
            "subcategory":"Plumbing",
            "type":"Services"
        }
    ],
    "sg:phone":"+1 956 316 1961",
    "sg:postcode":"78539",
    "sg:province":"TX",
    "sg:tags":[
        "plumbing",
        "contractor"
    ],
    "wof:name":"JOA Plumbing",
    "wof:placetype":"venue"
},
  "geometry": {"coordinates":[-98.12075299999999,26.344766],"type":"Point"}
}