{
  "type": "Feature",
  "properties": {
    "iso:country":"US",
    "sg:address":"1100 Felton St",
    "sg:city":"Baytown",
    "sg:classifiers":[
        {
            "category":"Professional",
            "type":"Services"
        }
    ],
    "sg:phone":"+1 281 427 2872",
    "sg:postcode":"77520",
    "sg:province":"TX",
    "wof:name":"Alfred B OBrien Jr",
    "wof:placetype":"venue"
},
  "geometry": {"coordinates":[-94.97295099999999,29.742275],"type":"Point"}
}