{
  "type": "Feature",
  "properties": {
    "iso:country":"US",
    "sg:address":"3319 W Walnut Hill Ln",
    "sg:city":"Irving",
    "sg:classifiers":[
        {
            "category":"Restaurant",
            "type":"Food & Drink"
        }
    ],
    "sg:menulink":"http://www.allmenus.com/tx/southwest/94524-dominos-pizza/menu/",
    "sg:phone":"+1 972 255 2257",
    "sg:postcode":"75038",
    "sg:province":"TX",
    "sg:tags":[
        "american",
        "wing",
        "pizza"
    ],
    "wof:name":"Domino's Pizza",
    "wof:placetype":"venue"
},
  "geometry": {"coordinates":[-96.990596,32.86548],"type":"Point"}
}