{
  "type": "Feature",
  "properties": {
    "iso:country":"US",
    "sg:address":"5860 9th Ave",
    "sg:city":"Port Arthur",
    "sg:classifiers":[
        {
            "category":"Government",
            "subcategory":"Office",
            "type":"Public Place"
        }
    ],
    "sg:phone":"+1 409 962 8984",
    "sg:postcode":"77642",
    "sg:province":"TX",
    "sg:tags":[
        "state",
        "program"
    ],
    "wof:name":"Rehabilitation Commission",
    "wof:placetype":"venue"
},
  "geometry": {"coordinates":[-93.959954,29.935914],"type":"Point"}
}