{
  "type": "Feature",
  "properties": {
    "iso:country":"US",
    "sg:address":"505 W Main",
    "sg:city":"Tomball",
    "sg:classifiers":[
        {
            "category":"Health Services",
            "subcategory":"Doctor",
            "type":"Services"
        }
    ],
    "sg:phone":"+1 281 351 0039",
    "sg:postcode":"77375",
    "sg:province":"TX",
    "sg:tags":[
        "dentist"
    ],
    "wof:name":"Dave K Dorrah DDS",
    "wof:placetype":"venue"
},
  "geometry": {"coordinates":[-95.61802299999999,30.096255],"type":"Point"}
}