{
  "type": "Feature",
  "properties": {
    "iso:country":"US",
    "sg:address":"4647 Leston St",
    "sg:city":"Dallas",
    "sg:classifiers":[
        {
            "category":"Shopping",
            "subcategory":"Music",
            "type":"Retail Goods"
        }
    ],
    "sg:phone":"+1 214 634 2534",
    "sg:postcode":"75247",
    "sg:province":"TX",
    "sg:tags":[
        "compact",
        "record",
        "disc",
        "tape"
    ],
    "wof:name":"Virgin Entertainment",
    "wof:placetype":"venue"
},
  "geometry": {"coordinates":[-96.893947,32.810446],"type":"Point"}
}