{
  "type": "Feature",
  "properties": {
    "iso:country":"US",
    "sg:address":"2110 Stonegate Dr",
    "sg:city":"Carrollton",
    "sg:classifiers":[
        {
            "category":"Professional",
            "subcategory":"Computer Services",
            "type":"Services"
        }
    ],
    "sg:phone":"+1 972 492 4811",
    "sg:postcode":"75010",
    "sg:province":"TX",
    "sg:tags":[
        "related"
    ],
    "wof:name":"Emerging Entp Solutions LLC",
    "wof:placetype":"venue"
},
  "geometry": {"coordinates":[-96.87207600000001,33.025266],"type":"Point"}
}