{
  "type": "Feature",
  "properties": {
    "iso:country":"US",
    "sg:address":"4110 Paseo Dr",
    "sg:city":"Austin",
    "sg:classifiers":[
        {
            "category":"Real Estate",
            "subcategory":"Real Estate Agent",
            "type":"Services"
        }
    ],
    "sg:phone":"+1 512 282 7595",
    "sg:postcode":"78739",
    "sg:province":"TX",
    "wof:name":"Matt Ikard Real Estate",
    "wof:placetype":"venue"
},
  "geometry": {"coordinates":[-97.870217,30.170297],"type":"Point"}
}