{
  "type": "Feature",
  "properties": {
    "iso:country":"US",
    "sg:address":"3511 McNiel Ave",
    "sg:city":"Wichita Falls",
    "sg:classifiers":[
        {
            "category":"Food & Beverages",
            "subcategory":"Specialty",
            "type":"Retail Goods"
        }
    ],
    "sg:phone":"+1 940 692 2143",
    "sg:postcode":"76308",
    "sg:province":"TX",
    "sg:tags":[
        "vitamin"
    ],
    "wof:name":"B & B Assoc",
    "wof:placetype":"venue"
},
  "geometry": {"coordinates":[-98.547848,33.873827],"type":"Point"}
}