{
  "type": "Feature",
  "properties": {
    "iso:country":"US",
    "sg:address":"6838 Loch Bruceray Dr",
    "sg:city":"Houston",
    "sg:classifiers":[
        {
            "category":"Building & Trades",
            "subcategory":"Construction",
            "type":"Services"
        }
    ],
    "sg:phone":"+1 281 345 0226",
    "sg:postcode":"77084",
    "sg:province":"TX",
    "sg:tags":[
        "house"
    ],
    "wof:name":"HB Custom Design",
    "wof:placetype":"venue"
},
  "geometry": {"coordinates":[-95.67881,29.877948],"type":"Point"}
}