{
  "type": "Feature",
  "properties": {
    "iso:country":"US",
    "sg:address":"3708 London Ln",
    "sg:city":"Richland Hills",
    "sg:classifiers":[
        {
            "category":"Manufacturing",
            "subcategory":"Metals",
            "type":"Manufacturing & Wholesale Goods"
        }
    ],
    "sg:phone":"+1 817 595 0505",
    "sg:postcode":"76118",
    "sg:province":"TX",
    "sg:tags":[
        "fence"
    ],
    "wof:name":"TKO Svc",
    "wof:placetype":"venue"
},
  "geometry": {"coordinates":[-97.221749,32.820109],"type":"Point"}
}