{
  "type": "Feature",
  "properties": {
    "iso:country":"US",
    "sg:address":"403 Houston St",
    "sg:city":"Pottsboro",
    "sg:classifiers":[
        {
            "category":"Restaurant",
            "type":"Food & Drink"
        }
    ],
    "sg:phone":"+1 903 421 3894",
    "sg:postcode":"75076",
    "sg:province":"TX",
    "sg:website":"http://hstrial-VPetree.homestead.com",
    "wof:name":"Trophy Catfish Adventures",
    "wof:placetype":"venue"
},
  "geometry": {"coordinates":[-96.66747700000001,33.759556],"type":"Point"}
}