{
  "type": "Feature",
  "properties": {
    "iso:country":"US",
    "sg:address":"2202 Caplin St",
    "sg:city":"Houston",
    "sg:classifiers":[
        {
            "category":"Building & Trades",
            "subcategory":"Landscaping Services",
            "type":"Services"
        }
    ],
    "sg:phone":"+1 713 697 3500",
    "sg:postcode":"77026",
    "sg:province":"TX",
    "sg:tags":[
        "lawn",
        "maintenance",
        "grounds"
    ],
    "wof:name":"Dependable Lawn Care",
    "wof:placetype":"venue"
},
  "geometry": {"coordinates":[-95.34602,29.8158],"type":"Point"}
}