{
  "type": "Feature",
  "properties": {
    "iso:country":"US",
    "sg:address":"16410 Parkway Dr",
    "sg:city":"Pflugerville",
    "sg:classifiers":[
        {
            "category":"Wholesale",
            "subcategory":"Auto Parts",
            "type":"Manufacturing & Wholesale Goods"
        }
    ],
    "sg:phone":"+1 512 251 3879",
    "sg:postcode":"78660",
    "sg:province":"TX",
    "sg:tags":[
        "used"
    ],
    "wof:name":"David Greathouse",
    "wof:placetype":"venue"
},
  "geometry": {"coordinates":[-97.642016,30.453844],"type":"Point"}
}