{
  "type": "Feature",
  "properties": {
    "iso:country":"US",
    "sg:address":"3609 Vilbig Rd",
    "sg:city":"Dallas",
    "sg:classifiers":[
        {
            "category":"Organizations",
            "subcategory":"Religious Organization",
            "type":"Services"
        }
    ],
    "sg:phone":"+1 214 741 2490",
    "sg:postcode":"75212",
    "sg:province":"TX",
    "wof:name":"St Phillips Missionary Baptist Church",
    "wof:placetype":"venue"
},
  "geometry": {"coordinates":[-96.848072,32.786553],"type":"Point"}
}