{
  "type": "Feature",
  "properties": {
    "iso:country":"US",
    "sg:address":"3325 Woodlawn Blvd",
    "sg:city":"Denison",
    "sg:classifiers":[
        {
            "category":"Food & Beverages",
            "subcategory":"Groceries & Convenience Stores",
            "type":"Retail Goods"
        }
    ],
    "sg:phone":"+1 903 463 2051",
    "sg:postcode":"75020",
    "sg:province":"TX",
    "wof:name":"Market Place",
    "wof:placetype":"venue"
},
  "geometry": {"coordinates":[-96.55670000000001,33.724057],"type":"Point"}
}