{
  "type": "Feature",
  "properties": {
    "iso:country":"US",
    "sg:address":"715 Brooks St",
    "sg:city":"Houston",
    "sg:classifiers":[
        {
            "category":"Manufacturing",
            "subcategory":"Furniture",
            "type":"Manufacturing & Wholesale Goods"
        }
    ],
    "sg:phone":"+1 713 222 0478",
    "sg:postcode":"77009",
    "sg:province":"TX",
    "sg:tags":[
        "mfg"
    ],
    "wof:name":"A MRC Corp",
    "wof:placetype":"venue"
},
  "geometry": {"coordinates":[-95.35885399999999,29.773953],"type":"Point"}
}