{
  "type": "Feature",
  "properties": {
    "iso:country":"US",
    "sg:address":"5301 W 7th St",
    "sg:city":"Texarkana",
    "sg:classifiers":[
        {
            "category":"Freight",
            "type":"Transportation"
        }
    ],
    "sg:phone":"+1 903 223 9467",
    "sg:postcode":"75501",
    "sg:province":"TX",
    "sg:tags":[
        "mover"
    ],
    "wof:name":"Portable Building Movers",
    "wof:placetype":"venue"
},
  "geometry": {"coordinates":[-94.119186,33.415653],"type":"Point"}
}