{
  "type": "Feature",
  "properties": {
    "iso:country":"US",
    "sg:address":"810 SE Military Dr",
    "sg:city":"San Antonio",
    "sg:classifiers":[
        {
            "category":"Health Services",
            "subcategory":"Doctor",
            "type":"Services"
        }
    ],
    "sg:phone":"+1 210 921 4204",
    "sg:postcode":"78214",
    "sg:province":"TX",
    "sg:tags":[
        "physician",
        "surgeon"
    ],
    "wof:name":"Val Verde Health Ctr",
    "wof:placetype":"venue"
},
  "geometry": {"coordinates":[-98.486411,29.356638],"type":"Point"}
}