{
  "type": "Feature",
  "properties": {
    "iso:country":"US",
    "sg:address":"1519 Royalwood Cir",
    "sg:city":"Joshua",
    "sg:classifiers":[
        {
            "category":"Ferry Terminal",
            "type":"Transportation"
        },
        {
            "category":"Sports & Exercise",
            "subcategory":"Race Track",
            "type":"Entertainment"
        }
    ],
    "sg:phone":"+1 817 291 7400",
    "sg:postcode":"76058",
    "sg:province":"TX",
    "sg:tags":[
        "equipment",
        "horseshoer",
        "horse"
    ],
    "sg:website":"http://www.rodneycarthelhorseshoeing.com",
    "wof:name":"Rodney Carthel Horseshoeing",
    "wof:placetype":"venue"
},
  "geometry": {"coordinates":[-97.348401,32.449598],"type":"Point"}
}