{
  "type": "Feature",
  "properties": {
    "iso:country":"US",
    "sg:address":"1710 Hillwood Dr",
    "sg:city":"Mesquite",
    "sg:classifiers":[
        {
            "category":"Shopping",
            "subcategory":"Florist",
            "type":"Retail Goods"
        }
    ],
    "sg:phone":"+1 972 289 3900",
    "sg:postcode":"75149",
    "sg:province":"TX",
    "wof:name":"Design By Charles",
    "wof:placetype":"venue"
},
  "geometry": {"coordinates":[-96.573351,32.755596],"type":"Point"}
}