{
  "type": "Feature",
  "properties": {
    "iso:country":"US",
    "sg:address":"201 Hwy 86",
    "sg:city":"Hereford",
    "sg:classifiers":[
        {
            "category":"Home & Garden",
            "subcategory":"Garden Supply",
            "type":"Retail Goods"
        }
    ],
    "sg:phone":"+1 806 647 4374",
    "sg:postcode":"79009",
    "sg:province":"TX",
    "wof:name":"C&T Fertilizer Inc",
    "wof:placetype":"venue"
},
  "geometry": {"coordinates":[-102.882323,34.514139],"type":"Point"}
}