{
  "type": "Feature",
  "properties": {
    "iso:country":"US",
    "sg:address":"1800 Augusta Dr Ste 109",
    "sg:city":"Houston",
    "sg:classifiers":[
        {
            "category":"Health Services",
            "subcategory":"Doctor",
            "type":"Services"
        },
        {
            "category":"Health Services",
            "subcategory":"Clinic",
            "type":"Services"
        }
    ],
    "sg:phone":"+1 713 781 1669",
    "sg:postcode":"77057",
    "sg:province":"TX",
    "sg:tags":[
        "counseling",
        "mental"
    ],
    "wof:name":"Benson Virginia Penn PHD",
    "wof:placetype":"venue"
},
  "geometry": {"coordinates":[-95.483363,29.748253],"type":"Point"}
}