{
  "type": "Feature",
  "properties": {
    "iso:country":"US",
    "sg:address":"22400 Westheimer Pkwy",
    "sg:city":"Katy",
    "sg:classifiers":[
        {
            "category":"Professional",
            "subcategory":"Detective & Security Services",
            "type":"Services"
        }
    ],
    "sg:phone":"+1 281 395 5954",
    "sg:postcode":"77450",
    "sg:province":"TX",
    "sg:tags":[
        "investigator"
    ],
    "wof:name":"All State Investigations",
    "wof:placetype":"venue"
},
  "geometry": {"coordinates":[-95.75940199999999,29.734616],"type":"Point"}
}