{
  "type": "Feature",
  "properties": {
    "iso:country":"US",
    "sg:address":"17054 Upper Bay Rd",
    "sg:city":"Addison",
    "sg:classifiers":[
        {
            "category":"Professional",
            "type":"Services"
        }
    ],
    "sg:phone":"+1 972 380 5557",
    "sg:postcode":"75001",
    "sg:province":"TX",
    "wof:name":"Garice P Schneider",
    "wof:placetype":"venue"
},
  "geometry": {"coordinates":[-96.83671200000001,32.984233],"type":"Point"}
}