{
  "type": "Feature",
  "properties": {
    "iso:country":"US",
    "sg:address":"13820 Country Side Dr",
    "sg:city":"Santa Fe",
    "sg:classifiers":[
        {
            "category":"Building & Trades",
            "subcategory":"Landscaping Services",
            "type":"Services"
        }
    ],
    "sg:phone":"+1 409 925 4579",
    "sg:postcode":"77517",
    "sg:province":"TX",
    "wof:name":"Countryside Sweeping Service",
    "wof:placetype":"venue"
},
  "geometry": {"coordinates":[-95.119044,29.418964],"type":"Point"}
}