{
  "type": "Feature",
  "properties": {
    "iso:country":"US",
    "sg:address":"516 Vicki Ln",
    "sg:city":"Wylie",
    "sg:classifiers":[
        {
            "category":"Building & Trades",
            "subcategory":"Construction",
            "type":"Services"
        }
    ],
    "sg:phone":"+1 972 442 1181",
    "sg:postcode":"75098",
    "sg:province":"TX",
    "sg:tags":[
        "carpentry",
        "contractor"
    ],
    "wof:name":"Wigington Construction",
    "wof:placetype":"venue"
},
  "geometry": {"coordinates":[-96.544995,33.019397],"type":"Point"}
}