{
  "type": "Feature",
  "properties": {
    "iso:country":"US",
    "sg:address":"4416 Jefferson Ave",
    "sg:city":"Texarkana",
    "sg:classifiers":[
        {
            "category":"Organizations",
            "subcategory":"Religious Organization",
            "type":"Services"
        }
    ],
    "sg:phone":"+1 870 772 2064",
    "sg:postcode":"71854",
    "sg:province":"TX",
    "wof:name":"First Assembly of God Church",
    "wof:placetype":"venue"
},
  "geometry": {"coordinates":[-94.028943,33.466053],"type":"Point"}
}