{
  "type": "Feature",
  "properties": {
    "iso:country":"US",
    "sg:address":"610 Lawrence St",
    "sg:city":"Tomball",
    "sg:classifiers":[
        {
            "category":"Health Services",
            "subcategory":"Clinic",
            "type":"Services"
        }
    ],
    "sg:phone":"+1 281 516 4650",
    "sg:postcode":"77375",
    "sg:province":"TX",
    "sg:tags":[
        "welfare"
    ],
    "wof:name":"Vivere Health",
    "wof:placetype":"venue"
},
  "geometry": {"coordinates":[-95.625203,30.091027],"type":"Point"}
}