{
  "type": "Feature",
  "properties": {
    "iso:country":"US",
    "sg:address":"4655 Sweetwater Blvd",
    "sg:city":"Sugar Land",
    "sg:classifiers":[
        {
            "category":"Autos & Motor Vehicles",
            "subcategory":"Automobile Sales",
            "type":"Retail Goods"
        },
        {
            "category":"Manufacturing",
            "subcategory":"Aerospace",
            "type":"Manufacturing & Wholesale Goods"
        }
    ],
    "sg:phone":"+1 281 313 7532",
    "sg:postcode":"77479",
    "sg:province":"TX",
    "sg:tags":[
        "helicopter",
        "aircraft",
        "mfg"
    ],
    "wof:name":"Petroleum Helicopters",
    "wof:placetype":"venue"
},
  "geometry": {"coordinates":[-95.63104199999999,29.583542],"type":"Point"}
}