{
  "type": "Feature",
  "properties": {
    "iso:country":"US",
    "sg:address":"5000 Heather Rd",
    "sg:city":"Midland",
    "sg:classifiers":[
        {
            "category":"Health Services",
            "subcategory":"Doctor",
            "type":"Services"
        }
    ],
    "sg:phone":"+1 432 686 7777",
    "sg:postcode":"79705",
    "sg:province":"TX",
    "sg:tags":[
        "physician",
        "surgeon"
    ],
    "wof:name":"West Texas Orthopedics",
    "wof:placetype":"venue"
},
  "geometry": {"coordinates":[-102.102294,32.044902],"type":"Point"}
}