{
  "type": "Feature",
  "properties": {
    "iso:country":"US",
    "sg:address":"2916 W T C Jester Blvd",
    "sg:city":"Houston",
    "sg:classifiers":[
        {
            "category":"Communications",
            "type":"Services"
        }
    ],
    "sg:phone":"+1 713 686 3443",
    "sg:postcode":"77018",
    "sg:province":"TX",
    "sg:tags":[
        "datum"
    ],
    "wof:name":"Petrolink",
    "wof:placetype":"venue"
},
  "geometry": {"coordinates":[-95.44541700000001,29.815867],"type":"Point"}
}