{
  "type": "Feature",
  "properties": {
    "iso:country":"US",
    "sg:address":"330 Municipal Drive Suite 104",
    "sg:city":"Richardson",
    "sg:classifiers":[
        {
            "category":"Personal",
            "subcategory":"Skin Care",
            "type":"Services"
        },
        {
            "category":"Community Center",
            "type":"Public Place"
        }
    ],
    "sg:phone":"+1 972 608 0000",
    "sg:postcode":"75080",
    "sg:province":"TX",
    "sg:tags":[
        "medical"
    ],
    "sg:website":"www.robertscosmeticsurgery.com",
    "wof:name":"Roberts Cosmetic Surgery Center",
    "wof:placetype":"venue"
},
  "geometry": {"coordinates":[-96.72259099999999,32.973954],"type":"Point"}
}