{
  "type": "Feature",
  "properties": {
    "iso:country":"US",
    "sg:address":"4312 32nd St",
    "sg:city":"Lubbock",
    "sg:classifiers":[
        {
            "category":"Shopping",
            "type":"Retail Goods"
        }
    ],
    "sg:phone":"+1 806 791 5795",
    "sg:postcode":"79410",
    "sg:province":"TX",
    "sg:tags":[
        "wedding",
        "supply"
    ],
    "wof:name":"Kings Ransom Ministries",
    "wof:placetype":"venue"
},
  "geometry": {"coordinates":[-101.904096,33.56515],"type":"Point"}
}