{
  "type": "Feature",
  "properties": {
    "iso:country":"US",
    "sg:address":"4706 N Main St",
    "sg:city":"Houston",
    "sg:classifiers":[
        {
            "category":"Shopping",
            "subcategory":"Clothing, Apparel, & Fashions",
            "type":"Retail Goods"
        }
    ],
    "sg:phone":"+1 713 869 0166",
    "sg:postcode":"77009",
    "sg:province":"TX",
    "sg:tags":[
        "bridal"
    ],
    "wof:name":"Salinas Bridal Boutique",
    "wof:placetype":"venue"
},
  "geometry": {"coordinates":[-95.382103,29.797701],"type":"Point"}
}