{
  "type": "Feature",
  "properties": {
    "iso:country":"US",
    "sg:address":"2431 Westlake Dr",
    "sg:city":"Austin",
    "sg:phone":"+1 512 327 1443",
    "sg:postcode":"78746",
    "sg:province":"TX",
    "wof:name":"Snappy Snacks Vending",
    "wof:placetype":"venue"
},
  "geometry": {"coordinates":[-97.784599,30.303033],"type":"Point"}
}