{
  "type": "Feature",
  "properties": {
    "iso:country":"US",
    "sg:address":"4103 Marathon Blvd",
    "sg:city":"Austin",
    "sg:classifiers":[
        {
            "category":"Organizations",
            "subcategory":"Non-profit Organization",
            "type":"Services"
        }
    ],
    "sg:phone":"+1 512 323 9037",
    "sg:postcode":"78756",
    "sg:province":"TX",
    "sg:tags":[
        "information",
        "treatment",
        "center",
        "smoker"
    ],
    "wof:name":"Quitsmart",
    "wof:placetype":"venue"
},
  "geometry": {"coordinates":[-97.74102000000001,30.310368],"type":"Point"}
}