{
  "type": "Feature",
  "properties": {
    "iso:country":"US",
    "sg:address":"21540 Provincial Blvd",
    "sg:city":"Katy",
    "sg:classifiers":[
        {
            "category":"Personal",
            "subcategory":"Beauty Salon",
            "type":"Services"
        }
    ],
    "sg:phone":"+1 281 578 5470",
    "sg:postcode":"77450",
    "sg:province":"TX",
    "sg:tags":[
        "shop"
    ],
    "wof:name":"A Cut Above Tree Service",
    "wof:placetype":"venue"
},
  "geometry": {"coordinates":[-95.748875,29.779865],"type":"Point"}
}