{
  "type": "Feature",
  "properties": {
    "iso:country":"US",
    "sg:address":"427 Pasadena Pl",
    "sg:city":"Corpus Christi",
    "sg:classifiers":[
        {
            "category":"Education",
            "subcategory":"Special Training",
            "type":"Public Place"
        }
    ],
    "sg:phone":"+1 361 857 7879",
    "sg:postcode":"78411",
    "sg:province":"TX",
    "wof:name":"French Teacher",
    "wof:placetype":"venue"
},
  "geometry": {"coordinates":[-97.37788399999999,27.739868],"type":"Point"}
}