{
  "type": "Feature",
  "properties": {
    "iso:country":"US",
    "sg:address":"604 Singleton Blvd",
    "sg:city":"Dallas",
    "sg:classifiers":[
        {
            "category":"Personal",
            "subcategory":"Beauty Salon",
            "type":"Services"
        }
    ],
    "sg:phone":"+1 214 651 9214",
    "sg:postcode":"75212",
    "sg:province":"TX",
    "sg:tags":[
        "shop"
    ],
    "wof:name":"Monarcas Solon Familiar",
    "wof:placetype":"venue"
},
  "geometry": {"coordinates":[-96.83338500000001,32.778493],"type":"Point"}
}