{
  "type": "Feature",
  "properties": {
    "iso:country":"US",
    "sg:address":"1301 Clarksville St",
    "sg:city":"Paris",
    "sg:classifiers":[
        {
            "category":"Professional",
            "subcategory":"Accounting & Tax Preparation",
            "type":"Services"
        }
    ],
    "sg:phone":"+1 903 785 0037",
    "sg:postcode":"75460",
    "sg:province":"TX",
    "sg:tags":[
        "return",
        "filing"
    ],
    "wof:name":"Jackson Hewitt Tax Svc",
    "wof:placetype":"venue"
},
  "geometry": {"coordinates":[-95.54227299999999,33.6588],"type":"Point"}
}