{
  "type": "Feature",
  "properties": {
    "iso:country":"US",
    "sg:address":"2330 N Main St",
    "sg:city":"Houston",
    "sg:classifiers":[
        {
            "category":"Professional",
            "subcategory":"Detective & Security Services",
            "type":"Services"
        }
    ],
    "sg:phone":"+1 713 225 1454",
    "sg:postcode":"77009",
    "sg:province":"TX",
    "sg:tags":[
        "investigator"
    ],
    "wof:name":"API Training Institute",
    "wof:placetype":"venue"
},
  "geometry": {"coordinates":[-95.36434199999999,29.78196],"type":"Point"}
}