{
  "type": "Feature",
  "properties": {
    "iso:country":"US",
    "sg:address":"12 Lombardy Ter",
    "sg:city":"Benbrook",
    "sg:classifiers":[
        {
            "category":"Real Estate",
            "subcategory":"Real Estate Agent",
            "type":"Services"
        }
    ],
    "sg:phone":"+1 817 737 6888",
    "sg:postcode":"76132",
    "sg:province":"TX",
    "sg:tags":[
        "appraiser"
    ],
    "wof:name":"Durham Appraisal Svc",
    "wof:placetype":"venue"
},
  "geometry": {"coordinates":[-97.423323,32.68638],"type":"Point"}
}