{
  "type": "Feature",
  "properties": {
    "iso:country":"US",
    "sg:address":"399 N Beach St",
    "sg:city":"Fort Worth",
    "sg:classifiers":[
        {
            "category":"Wholesale",
            "subcategory":"Hardware",
            "type":"Manufacturing & Wholesale Goods"
        }
    ],
    "sg:phone":"+1 817 834 5542",
    "sg:postcode":"76111",
    "sg:province":"TX",
    "sg:tags":[
        "air",
        "parts",
        "conditioning",
        "supply"
    ],
    "wof:name":"Insco Distributing Inc",
    "wof:placetype":"venue"
},
  "geometry": {"coordinates":[-97.287644,32.767151],"type":"Point"}
}