{
  "type": "Feature",
  "properties": {
    "iso:country":"US",
    "sg:address":"1304 Central Blvd",
    "sg:city":"Brownsville",
    "sg:classifiers":[
        {
            "category":"Shopping",
            "subcategory":"Department Store",
            "type":"Retail Goods"
        },
        {
            "category":"Shopping",
            "subcategory":"Discount & Variety Stores",
            "type":"Retail Goods"
        },
        {
            "category":"Shopping",
            "type":"Retail Goods"
        },
        {
            "category":"Food & Beverages",
            "subcategory":"Groceries & Convenience Stores",
            "type":"Retail Goods"
        }
    ],
    "sg:phone":"+1 956 574 9376",
    "sg:postcode":"78520",
    "sg:province":"TX",
    "sg:tags":[
        "merchandise"
    ],
    "sg:website":"http://www.dollargeneral.com",
    "wof:name":"Dollar General",
    "wof:placetype":"venue"
},
  "geometry": {"coordinates":[-97.511543,25.924602],"type":"Point"}
}