{
  "type": "Feature",
  "properties": {
    "iso:country":"US",
    "sg:address":"3629 Dutton Dr",
    "sg:city":"Dallas",
    "sg:classifiers":[
        {
            "category":"Home & Garden",
            "subcategory":"Carpets & Floor Coverings",
            "type":"Retail Goods"
        }
    ],
    "sg:phone":"+1 214 330 0067",
    "sg:postcode":"75211",
    "sg:province":"TX",
    "sg:tags":[
        "installs",
        "tile",
        "ceramic"
    ],
    "wof:name":"Polish Power Floor Covering",
    "wof:placetype":"venue"
},
  "geometry": {"coordinates":[-96.88016399999999,32.725482],"type":"Point"}
}