{
  "type": "Feature",
  "properties": {
    "iso:country":"US",
    "sg:address":"801 San Pedro Ave",
    "sg:city":"San Antonio",
    "sg:classifiers":[
        {
            "category":"Restaurant",
            "type":"Food & Drink"
        }
    ],
    "sg:phone":"+1 210 212 5656",
    "sg:postcode":"78212",
    "sg:province":"TX",
    "sg:tags":[
        "eating"
    ],
    "wof:name":"Cypress Street Grill",
    "wof:placetype":"venue"
},
  "geometry": {"coordinates":[-98.499185,29.441722],"type":"Point"}
}