{
  "type": "Feature",
  "properties": {
    "iso:country":"US",
    "sg:address":"107 Chapel Hill",
    "sg:city":"Boerne",
    "sg:classifiers":[
        {
            "category":"Professional",
            "subcategory":"Computer Services",
            "type":"Services"
        }
    ],
    "sg:phone":"+1 830 537 3177",
    "sg:postcode":"78006",
    "sg:province":"TX",
    "sg:tags":[
        "repair"
    ],
    "wof:name":"Computer Services Inc",
    "wof:placetype":"venue"
},
  "geometry": {"coordinates":[-98.725489,29.881994],"type":"Point"}
}