{
  "type": "Feature",
  "properties": {
    "iso:country":"US",
    "sg:address":"144 Landons Way",
    "sg:city":"Georgetown",
    "sg:classifiers":[
        {
            "category":"Building & Trades",
            "subcategory":"Electrical",
            "type":"Services"
        }
    ],
    "sg:phone":"+1 512 869 1348",
    "sg:postcode":"78633",
    "sg:province":"TX",
    "sg:tags":[
        "industrial",
        "electrician",
        "contractors-commercial",
        "electric"
    ],
    "wof:name":"Infinity Electric Svc",
    "wof:placetype":"venue"
},
  "geometry": {"coordinates":[-97.788707,30.707177],"type":"Point"}
}