{
  "type": "Feature",
  "properties": {
    "iso:country":"US",
    "sg:address":"1210 W Hill St",
    "sg:city":"Brownfield",
    "sg:classifiers":[
        {
            "category":"Professional",
            "type":"Services"
        }
    ],
    "sg:phone":"+1 806 637 3885",
    "sg:postcode":"79316",
    "sg:province":"TX",
    "wof:name":"E & S Answering Svc",
    "wof:placetype":"venue"
},
  "geometry": {"coordinates":[-102.289783,33.180115],"type":"Point"}
}