{
  "type": "Feature",
  "properties": {
    "iso:country":"US",
    "sg:address":"4004 Schley Ct",
    "sg:city":"Fort Worth",
    "sg:classifiers":[
        {
            "category":"Organizations",
            "subcategory":"Membership Organization",
            "type":"Services"
        }
    ],
    "sg:phone":"+1 817 244 5005",
    "sg:postcode":"76116",
    "sg:province":"TX",
    "wof:name":"Nam Pows",
    "wof:placetype":"venue"
},
  "geometry": {"coordinates":[-97.47296799999999,32.71278],"type":"Point"}
}