{
  "type": "Feature",
  "properties": {
    "iso:country":"US",
    "sg:address":"3211 Spring Stuebner Rd",
    "sg:city":"Spring",
    "sg:classifiers":[
        {
            "category":"Real Estate",
            "subcategory":"Developer",
            "type":"Services"
        }
    ],
    "sg:phone":"+1 281 812 4610",
    "sg:postcode":"77389",
    "sg:province":"TX",
    "sg:tags":[
        "cemetery"
    ],
    "wof:name":"CEM Logistics",
    "wof:placetype":"venue"
},
  "geometry": {"coordinates":[-95.467496,30.082752],"type":"Point"}
}