{
  "type": "Feature",
  "properties": {
    "iso:country":"US",
    "sg:address":"104 N Lavaca",
    "sg:city":"Moulton",
    "sg:classifiers":[
        {
            "category":"Wholesale",
            "subcategory":"Hardware",
            "type":"Manufacturing & Wholesale Goods"
        },
        {
            "category":"Home & Garden",
            "subcategory":"Garden Supply",
            "type":"Retail Goods"
        },
        {
            "category":"Retail",
            "subcategory":"Repair Shop",
            "type":"Services"
        }
    ],
    "sg:phone":"+1 512 476 2401",
    "sg:postcode":"77975",
    "sg:province":"TX",
    "sg:tags":[
        "renting",
        "lawn",
        "outdoor",
        "power",
        "landscaping",
        "equipment-sales",
        "equipment",
        "saw"
    ],
    "sg:website":"http://www.stihldealer.net/default-dealer-043011.aspx",
    "wof:name":"A-Line Auto Parts",
    "wof:placetype":"venue"
},
  "geometry": {"coordinates":[-97.142943,29.574906],"type":"Point"}
}