{
  "type": "Feature",
  "properties": {
    "iso:country":"US",
    "sg:address":"733 Grandview Dr",
    "sg:city":"Corsicana",
    "sg:classifiers":[
        {
            "category":"Government",
            "subcategory":"Office",
            "type":"Public Place"
        }
    ],
    "sg:phone":"+1 903 874 4404",
    "sg:postcode":"75109",
    "sg:province":"TX",
    "sg:tags":[
        "parish",
        "government-county"
    ],
    "wof:name":"Navarro County Wholesale Ratepayers",
    "wof:placetype":"venue"
},
  "geometry": {"coordinates":[-96.239115,31.985638],"type":"Point"}
}