{
  "type": "Feature",
  "properties": {
    "iso:country":"US",
    "sg:address":"3333 Red Bluff Rd",
    "sg:city":"Pasadena",
    "sg:classifiers":[
        {
            "category":"Restaurant",
            "type":"Food & Drink"
        }
    ],
    "sg:menulink":"http://www.allmenus.com/tx/pasadena/177680-jack-in-the-box/menu/",
    "sg:phone":"+1 713 473 7232",
    "sg:postcode":"77503",
    "sg:province":"TX",
    "sg:tags":[
        "burger",
        "american"
    ],
    "wof:name":"Jack in the Box",
    "wof:placetype":"venue"
},
  "geometry": {"coordinates":[-95.16468500000001,29.689878],"type":"Point"}
}