{
  "type": "Feature",
  "properties": {
    "iso:country":"US",
    "sg:address":"1781 S Avondale St",
    "sg:city":"Amarillo",
    "sg:classifiers":[
        {
            "category":"Retail",
            "subcategory":"Self-service Laundry",
            "type":"Services"
        }
    ],
    "sg:phone":"+1 806 355 1181",
    "sg:postcode":"79106",
    "sg:province":"TX",
    "sg:tags":[
        "garment",
        "coin",
        "agent"
    ],
    "wof:name":"Avondale Polyclean",
    "wof:placetype":"venue"
},
  "geometry": {"coordinates":[-101.893247,35.19603],"type":"Point"}
}