{
  "type": "Feature",
  "properties": {
    "iso:country":"US",
    "sg:address":"214 E Red Bird Ln",
    "sg:city":"Duncanville",
    "sg:classifiers":[
        {
            "category":"Professional",
            "subcategory":"Business Services",
            "type":"Services"
        }
    ],
    "sg:phone":"+1 972 572 9473",
    "sg:postcode":"75116",
    "sg:province":"TX",
    "sg:tags":[
        "repossessing"
    ],
    "wof:name":"Interstate Adjusters",
    "wof:placetype":"venue"
},
  "geometry": {"coordinates":[-96.900398,32.676507],"type":"Point"}
}