{
  "type": "Feature",
  "properties": {
    "iso:country":"US",
    "sg:address":"5526 Leopard St",
    "sg:city":"Corpus Christi",
    "sg:classifiers":[
        {
            "category":"Freight",
            "type":"Transportation"
        }
    ],
    "sg:phone":"+1 361 289 6873",
    "sg:postcode":"78408",
    "sg:province":"TX",
    "sg:tags":[
        "commercial",
        "storage",
        "special"
    ],
    "wof:name":"Mike's Mini Storage",
    "wof:placetype":"venue"
},
  "geometry": {"coordinates":[-97.46413699999999,27.797584],"type":"Point"}
}