{
  "type": "Feature",
  "properties": {
    "iso:country":"US",
    "sg:address":"1392 Co Rd 4945",
    "sg:city":"Leonard",
    "sg:classifiers":[
        {
            "category":"Building & Trades",
            "subcategory":"Construction",
            "type":"Services"
        }
    ],
    "sg:phone":"+1 903 587 3491",
    "sg:postcode":"75452",
    "sg:province":"TX",
    "sg:tags":[
        "home",
        "builder"
    ],
    "wof:name":"Silver Plumbline Custom Homes",
    "wof:placetype":"venue"
},
  "geometry": {"coordinates":[-96.30359199999999,33.380607],"type":"Point"}
}