{
  "type": "Feature",
  "properties": {
    "iso:country":"US",
    "sg:address":"8000 Centre Park Drive Suite 330",
    "sg:city":"Austin",
    "sg:classifiers":[
        {
            "category":"Professional",
            "subcategory":"Lawyer & Legal Services",
            "type":"Services"
        }
    ],
    "sg:phone":"+1 512 467 0600",
    "sg:postcode":"78754",
    "sg:province":"TX",
    "wof:name":"Komie & Melendez",
    "wof:placetype":"venue"
},
  "geometry": {"coordinates":[-97.67819900000001,30.333756],"type":"Point"}
}