{
  "type": "Feature",
  "properties": {
    "iso:country":"US",
    "sg:address":"941 S Treadaway Blvd",
    "sg:city":"Abilene",
    "sg:classifiers":[
        {
            "category":"Mining & Drilling",
            "type":"Manufacturing & Wholesale Goods"
        }
    ],
    "sg:phone":"+1 325 673 1128",
    "sg:postcode":"79602",
    "sg:province":"TX",
    "sg:tags":[
        "field",
        "oil"
    ],
    "wof:name":"D & H Rig Svc",
    "wof:placetype":"venue"
},
  "geometry": {"coordinates":[-99.72851799999999,32.437466],"type":"Point"}
}