{
  "type": "Feature",
  "properties": {
    "iso:country":"US",
    "sg:address":"30118 State Highway 249",
    "sg:city":"Tomball",
    "sg:phone":"+1 281 255 6344",
    "sg:postcode":"77375",
    "sg:province":"TX",
    "wof:name":"Ken's Auto Repair",
    "wof:placetype":"venue"
},
  "geometry": {"coordinates":[-95.638559,30.103002],"type":"Point"}
}