{
  "type": "Feature",
  "properties": {
    "iso:country":"US",
    "sg:address":"3500 W 7th Ave",
    "sg:city":"Corsicana",
    "sg:classifiers":[
        {
            "category":"Health Services",
            "subcategory":"Doctor",
            "type":"Services"
        },
        {
            "category":"Health Services",
            "subcategory":"Clinic",
            "type":"Services"
        },
        {
            "category":"Health Services",
            "subcategory":"Chiropractor",
            "type":"Services"
        }
    ],
    "sg:phone":"+1 903 874 5866",
    "sg:postcode":"75110",
    "sg:province":"TX",
    "sg:tags":[
        "physician",
        "medical",
        "surgeons",
        "surgery-general",
        "chiropractic"
    ],
    "wof:name":"Medical & Surgical Associates",
    "wof:placetype":"venue"
},
  "geometry": {"coordinates":[-96.50157900000001,32.0723],"type":"Point"}
}