{
  "type": "Feature",
  "properties": {
    "iso:country":"US",
    "sg:address":"1900 Long Prairie Rd",
    "sg:city":"Flower Mound",
    "sg:classifiers":[
        {
            "category":"Restaurant",
            "type":"Food & Drink"
        }
    ],
    "sg:phone":"+1 972 874 7892",
    "sg:postcode":"75022",
    "sg:province":"TX",
    "sg:website":"www.anamias.com",
    "wof:name":"Anamia's Tex-Mex",
    "wof:placetype":"venue"
},
  "geometry": {"coordinates":[-97.070729,33.010438],"type":"Point"}
}