{
  "type": "Feature",
  "properties": {
    "iso:country":"US",
    "sg:address":"2527 Royal Ln",
    "sg:city":"Dallas",
    "sg:classifiers":[
        {
            "category":"Shopping",
            "subcategory":"Clothing, Apparel, & Fashions",
            "type":"Retail Goods"
        }
    ],
    "sg:phone":"+1 972 620 2471",
    "sg:postcode":"75229",
    "sg:province":"TX",
    "sg:tags":[
        "infant",
        "wear"
    ],
    "wof:name":"Kid",
    "wof:placetype":"venue"
},
  "geometry": {"coordinates":[-96.893091,32.896187],"type":"Point"}
}