{
  "type": "Feature",
  "properties": {
    "iso:country":"US",
    "sg:address":"207 Eggar St",
    "sg:city":"Waxahachie",
    "sg:classifiers":[
        {
            "category":"Organizations",
            "subcategory":"Religious Organization",
            "type":"Services"
        }
    ],
    "sg:phone":"+1 972 937 4615",
    "sg:postcode":"75165",
    "sg:province":"TX",
    "sg:tags":[
        "church"
    ],
    "wof:name":"Greater New Mt Zion Missionary",
    "wof:placetype":"venue"
},
  "geometry": {"coordinates":[-96.835837,32.385322],"type":"Point"}
}