{
  "type": "Feature",
  "properties": {
    "iso:country":"US",
    "sg:address":"1033 N Willis St",
    "sg:city":"Abilene",
    "sg:classifiers":[
        {
            "category":"Retail",
            "subcategory":"Laundry & Dry Cleaning",
            "type":"Services"
        }
    ],
    "sg:phone":"+1 325 676 2258",
    "sg:postcode":"79603",
    "sg:province":"TX",
    "sg:tags":[
        "cleaners"
    ],
    "wof:name":"Classic Cleaners & Tuxedo Rntl",
    "wof:placetype":"venue"
},
  "geometry": {"coordinates":[-99.764037,32.462832],"type":"Point"}
}