{
  "type": "Feature",
  "properties": {
    "iso:country":"US",
    "sg:address":"1412 Medina Hwy",
    "sg:city":"Kerrville",
    "sg:classifiers":[
        {
            "category":"Building & Trades",
            "subcategory":"Construction",
            "type":"Services"
        }
    ],
    "sg:phone":"+1 830 257 7154",
    "sg:postcode":"78028",
    "sg:province":"TX",
    "sg:tags":[
        "tile",
        "dealer"
    ],
    "wof:name":"Danny's Tile Svc",
    "wof:placetype":"venue"
},
  "geometry": {"coordinates":[-99.144246,30.02745],"type":"Point"}
}