{
  "type": "Feature",
  "properties": {
    "iso:country":"US",
    "sg:address":"218 W 51st St",
    "sg:city":"Austin",
    "sg:classifiers":[
        {
            "category":"Professional",
            "type":"Services"
        }
    ],
    "sg:phone":"+1 512 323 5737",
    "sg:postcode":"78751",
    "sg:province":"TX",
    "wof:name":"Elaine Robbins",
    "wof:placetype":"venue"
},
  "geometry": {"coordinates":[-97.726095,30.316715],"type":"Point"}
}