{
  "type": "Feature",
  "properties": {
    "iso:country":"US",
    "sg:address":"4610 San Bernardo Ave",
    "sg:city":"Laredo",
    "sg:classifiers":[
        {
            "category":"Manufacturing",
            "subcategory":"Chemicals & Compounds",
            "type":"Manufacturing & Wholesale Goods"
        },
        {
            "category":"Building & Trades",
            "subcategory":"Pest Control",
            "type":"Services"
        }
    ],
    "sg:phone":"+1 956 218 8041",
    "sg:postcode":"78041",
    "sg:province":"TX",
    "sg:tags":[
        "equipment",
        "supply"
    ],
    "wof:name":"ON Time Pest Control",
    "wof:placetype":"venue"
},
  "geometry": {"coordinates":[-99.504316,27.5402],"type":"Point"}
}