{
  "type": "Feature",
  "properties": {
    "iso:country":"US",
    "sg:address":"16603 El Camino Real",
    "sg:city":"Houston",
    "sg:classifiers":[
        {
            "category":"Autos & Motor Vehicles",
            "subcategory":"Auto Supplies",
            "type":"Retail Goods"
        },
        {
            "category":"Retail",
            "subcategory":"Auto Repair",
            "type":"Services"
        }
    ],
    "sg:phone":"+1 281 488 6835",
    "sg:postcode":"77062",
    "sg:province":"TX",
    "sg:tags":[
        "lube",
        "oil",
        "tire"
    ],
    "sg:website":"http://www.firestonecompleteautocare.com/?s_kwcid=IYP_NTL",
    "wof:name":"Firestone Complete Auto Care Store",
    "wof:placetype":"venue"
},
  "geometry": {"coordinates":[-95.12246500000001,29.557223],"type":"Point"}
}