{
  "type": "Feature",
  "properties": {
    "iso:country":"US",
    "sg:address":"4300 N Lamar Blvd",
    "sg:city":"Austin",
    "sg:classifiers":[
        {
            "category":"Health Services",
            "subcategory":"Medical Lab",
            "type":"Services"
        }
    ],
    "sg:phone":"+1 512 467 5200",
    "sg:postcode":"78756",
    "sg:province":"TX",
    "wof:name":"Medical Service Bureau",
    "wof:placetype":"venue"
},
  "geometry": {"coordinates":[-97.73951,30.311081],"type":"Point"}
}