{
  "type": "Feature",
  "properties": {
    "iso:country":"US",
    "sg:address":"6080 Circle R Rd S",
    "sg:city":"Fort Worth",
    "sg:classifiers":[
        {
            "category":"Building & Trades",
            "subcategory":"Construction",
            "type":"Services"
        }
    ],
    "sg:phone":"+1 817 483 1633",
    "sg:postcode":"76140",
    "sg:province":"TX",
    "wof:name":"D & S Sand & Grading",
    "wof:placetype":"venue"
},
  "geometry": {"coordinates":[-97.23253699999999,32.58157],"type":"Point"}
}