{
  "type": "Feature",
  "properties": {
    "iso:country":"US",
    "sg:address":"10515 Nacogdoches Rd",
    "sg:city":"San Antonio",
    "sg:classifiers":[
        {
            "category":"Retail",
            "subcategory":"Auto Repair",
            "type":"Services"
        }
    ],
    "sg:phone":"+1 210 654 1104",
    "sg:postcode":"78217",
    "sg:province":"TX",
    "sg:tags":[
        "body",
        "supply"
    ],
    "wof:name":"Star Body & Paint Works Inc",
    "wof:placetype":"venue"
},
  "geometry": {"coordinates":[-98.42519900000001,29.537003],"type":"Point"}
}