{
  "type": "Feature",
  "properties": {
    "iso:country":"US",
    "sg:address":"5658 Co Rd 4061",
    "sg:city":"Scurry",
    "sg:classifiers":[
        {
            "category":"Wholesale",
            "subcategory":"Vending Machines",
            "type":"Manufacturing & Wholesale Goods"
        }
    ],
    "sg:phone":"+1 903 498 2920",
    "sg:postcode":"75143",
    "sg:province":"TX",
    "wof:name":"Kellys Jellys",
    "wof:placetype":"venue"
},
  "geometry": {"coordinates":[-96.328817,32.449614],"type":"Point"}
}