{
  "type": "Feature",
  "properties": {
    "iso:country":"US",
    "sg:address":"4601 S Loop 289",
    "sg:city":"Lubbock",
    "sg:classifiers":[
        {
            "category":"Manufacturing",
            "subcategory":"Retail Goods",
            "type":"Manufacturing & Wholesale Goods"
        }
    ],
    "sg:phone":"+1 806 792 6102",
    "sg:postcode":"79424",
    "sg:province":"TX",
    "sg:tags":[
        "product",
        "mfg"
    ],
    "wof:name":"Always Baseball",
    "wof:placetype":"venue"
},
  "geometry": {"coordinates":[-101.913332,33.532339],"type":"Point"}
}