{
  "type": "Feature",
  "properties": {
    "iso:country":"US",
    "sg:address":"17831 Tall Cypress Dr",
    "sg:city":"Spring",
    "sg:classifiers":[
        {
            "category":"Real Estate",
            "subcategory":"Real Estate Agent",
            "type":"Services"
        }
    ],
    "sg:phone":"+1 281 355 5710",
    "sg:postcode":"77388",
    "sg:province":"TX",
    "wof:name":"Ed Cheek Enterprises",
    "wof:placetype":"venue"
},
  "geometry": {"coordinates":[-95.47820900000001,30.034572],"type":"Point"}
}