{
  "type": "Feature",
  "properties": {
    "iso:country":"US",
    "sg:address":"16240 San Pedro Ave",
    "sg:city":"San Antonio",
    "sg:classifiers":[
        {
            "category":"Home & Garden",
            "subcategory":"Building Materials",
            "type":"Retail Goods"
        }
    ],
    "sg:phone":"+1 210 495 3667",
    "sg:postcode":"78232",
    "sg:province":"TX",
    "sg:tags":[
        "door"
    ],
    "wof:name":"Overhead Garage Door Svc",
    "wof:placetype":"venue"
},
  "geometry": {"coordinates":[-98.47404299999999,29.590121],"type":"Point"}
}