{
  "type": "Feature",
  "properties": {
    "iso:country":"US",
    "sg:address":"15692 FM 2493",
    "sg:city":"Tyler",
    "sg:classifiers":[
        {
            "category":"Manufacturing",
            "subcategory":"Metals",
            "type":"Manufacturing & Wholesale Goods"
        }
    ],
    "sg:phone":"+1 903 561 2290",
    "sg:postcode":"75762",
    "sg:province":"TX",
    "sg:tags":[
        "steel"
    ],
    "wof:name":"Petrofac",
    "wof:placetype":"venue"
},
  "geometry": {"coordinates":[-95.34805,32.252319],"type":"Point"}
}