{
  "type": "Feature",
  "properties": {
    "iso:country":"US",
    "sg:address":"12707 Trinity St",
    "sg:city":"Stafford",
    "sg:classifiers":[
        {
            "category":"Professional",
            "subcategory":"Research",
            "type":"Services"
        }
    ],
    "sg:phone":"+1 281 240 5227",
    "sg:postcode":"77477",
    "sg:province":"TX",
    "sg:tags":[
        "organization",
        "noncommercial"
    ],
    "wof:name":"Burzynski Research Labs",
    "wof:placetype":"venue"
},
  "geometry": {"coordinates":[-95.574814,29.63577],"type":"Point"}
}