{
  "type": "Feature",
  "properties": {
    "iso:country":"US",
    "sg:address":"10807 Baxter Cir",
    "sg:city":"Austin",
    "sg:classifiers":[
        {
            "category":"Wholesale",
            "subcategory":"Drugs",
            "type":"Manufacturing & Wholesale Goods"
        }
    ],
    "sg:phone":"+1 512 288 1960",
    "sg:postcode":"78736",
    "sg:province":"TX",
    "sg:tags":[
        "pharmaceutical",
        "products-wholesale",
        "manufacturer"
    ],
    "sg:website":"http://www.pfizer.com",
    "wof:name":"Pfizer",
    "wof:placetype":"venue"
},
  "geometry": {"coordinates":[-97.946845,30.229374],"type":"Point"}
}