{
  "type": "Feature",
  "properties": {
    "iso:country":"US",
    "sg:address":"18649 FM 1431",
    "sg:city":"Jonestown",
    "sg:classifiers":[
        {
            "category":"Professional",
            "type":"Services"
        }
    ],
    "sg:phone":"+1 512 267 9059",
    "sg:postcode":"78645",
    "sg:province":"TX",
    "sg:tags":[
        "establishment"
    ],
    "wof:name":"Capital Area Work Force",
    "wof:placetype":"venue"
},
  "geometry": {"coordinates":[-97.92446200000001,30.494409],"type":"Point"}
}