{
  "type": "Feature",
  "properties": {
    "iso:country":"US",
    "sg:address":"2609 S 4th St",
    "sg:city":"Austin",
    "sg:classifiers":[
        {
            "category":"Professional",
            "type":"Services"
        }
    ],
    "sg:phone":"+1 512 326 9097",
    "sg:postcode":"78704",
    "sg:province":"TX",
    "sg:tags":[
        "arts",
        "artist"
    ],
    "wof:name":"W R A Heartworks",
    "wof:placetype":"venue"
},
  "geometry": {"coordinates":[-97.765218,30.239554],"type":"Point"}
}