{
  "type": "Feature",
  "properties": {
    "iso:country":"US",
    "sg:address":"5530 Brookfield Dr",
    "sg:city":"Houston",
    "sg:classifiers":[
        {
            "category":"Retail",
            "subcategory":"Repair Shop",
            "type":"Services"
        }
    ],
    "sg:phone":"+1 713 723 8409",
    "sg:postcode":"77085",
    "sg:province":"TX",
    "sg:tags":[
        "locksmith"
    ],
    "wof:name":"High Security Solution",
    "wof:placetype":"venue"
},
  "geometry": {"coordinates":[-95.46943,29.615071],"type":"Point"}
}