{
  "type": "Feature",
  "properties": {
    "iso:country":"US",
    "sg:address":"3200 Southwest Fwy",
    "sg:city":"Houston",
    "sg:classifiers":[
        {
            "category":"Professional",
            "subcategory":"Lawyer & Legal Services",
            "type":"Services"
        }
    ],
    "sg:phone":"+1 713 629 0670",
    "sg:postcode":"77027",
    "sg:province":"TX",
    "wof:name":"Radoff Perry J Atty",
    "wof:placetype":"venue"
},
  "geometry": {"coordinates":[-95.428918,29.730802],"type":"Point"}
}