{
  "type": "Feature",
  "properties": {
    "iso:country":"US",
    "sg:address":"4621 S Cooper St",
    "sg:city":"Arlington",
    "sg:classifiers":[
        {
            "category":"Professional",
            "subcategory":"Business Services",
            "type":"Services"
        },
        {
            "category":"Professional",
            "subcategory":"Computer Services",
            "type":"Services"
        }
    ],
    "sg:phone":"+1 817 268 0257",
    "sg:postcode":"76017",
    "sg:province":"TX",
    "sg:tags":[
        "repair"
    ],
    "wof:name":"G & K Networking Associates",
    "wof:placetype":"venue"
},
  "geometry": {"coordinates":[-97.134271,32.670714],"type":"Point"}
}