{
  "type": "Feature",
  "properties": {
    "iso:country":"US",
    "sg:address":"1508 Colony Cir",
    "sg:city":"Longview",
    "sg:classifiers":[
        {
            "category":"Shopping",
            "subcategory":"Jewelry",
            "type":"Retail Goods"
        },
        {
            "category":"Manufacturing",
            "subcategory":"Jewelry",
            "type":"Manufacturing & Wholesale Goods"
        }
    ],
    "sg:phone":"+1 903 757 6595",
    "sg:postcode":"75604",
    "sg:province":"TX",
    "sg:tags":[
        "designer",
        "jeweler"
    ],
    "wof:name":"Barbe John D Grad. Sales",
    "wof:placetype":"venue"
},
  "geometry": {"coordinates":[-94.770849,32.51108],"type":"Point"}
}