{
  "type": "Feature",
  "properties": {
    "iso:country":"US",
    "sg:address":"5255 Woodrow Bean Transmountain Rd",
    "sg:city":"El Paso",
    "sg:classifiers":[
        {
            "category":"Professional",
            "type":"Services"
        }
    ],
    "sg:phone":"+1 915 755 1870",
    "sg:postcode":"79924",
    "sg:province":"TX",
    "sg:tags":[
        "establishment"
    ],
    "wof:name":"LA Dona",
    "wof:placetype":"venue"
},
  "geometry": {"coordinates":[-106.41853999999999,31.899195],"type":"Point"}
}