{
  "type": "Feature",
  "properties": {
    "iso:country":"US",
    "sg:address":"1521 Lea Ln",
    "sg:city":"Corpus Christi",
    "sg:classifiers":[
        {
            "category":"Building & Trades",
            "subcategory":"Construction",
            "type":"Services"
        }
    ],
    "sg:phone":"+1 361 855 8071",
    "sg:postcode":"78415",
    "sg:province":"TX",
    "sg:tags":[
        "house"
    ],
    "wof:name":"Authentic Texas Construction",
    "wof:placetype":"venue"
},
  "geometry": {"coordinates":[-97.40666299999999,27.74684],"type":"Point"}
}