{
  "type": "Feature",
  "properties": {
    "iso:country":"US",
    "sg:address":"722 Tenison Memorial Dr",
    "sg:city":"Dallas",
    "sg:classifiers":[
        {
            "category":"Education",
            "subcategory":"School",
            "type":"Public Place"
        }
    ],
    "sg:phone":"+1 214 321 9155",
    "sg:postcode":"75223",
    "sg:province":"TX",
    "sg:tags":[
        "elementary"
    ],
    "wof:name":"Lindsley Park Community School",
    "wof:placetype":"venue"
},
  "geometry": {"coordinates":[-96.739403,32.808102],"type":"Point"}
}