{
  "type": "Feature",
  "properties": {
    "iso:country":"US",
    "sg:address":"112 W Ridgewood Ct",
    "sg:city":"San Antonio",
    "sg:classifiers":[
        {
            "category":"Banks & Credit Unions",
            "subcategory":"Financial Services",
            "type":"Services"
        }
    ],
    "sg:phone":"+1 210 822 5433",
    "sg:postcode":"78212",
    "sg:province":"TX",
    "sg:tags":[
        "trust",
        "management"
    ],
    "wof:name":"Marjorie Walthall Charitable T",
    "wof:placetype":"venue"
},
  "geometry": {"coordinates":[-98.495369,29.466939],"type":"Point"}
}