{
  "type": "Feature",
  "properties": {
    "iso:country":"US",
    "sg:address":"7403 Theisswood Rd",
    "sg:city":"Spring",
    "sg:classifiers":[
        {
            "category":"Taxi",
            "type":"Transportation"
        }
    ],
    "sg:phone":"+1 281 923 1746",
    "sg:postcode":"77379",
    "sg:province":"TX",
    "sg:tags":[
        "taxicab"
    ],
    "wof:name":"Taxi Houston TX",
    "wof:placetype":"venue"
},
  "geometry": {"coordinates":[-95.532492,30.029956],"type":"Point"}
}