{
  "type": "Feature",
  "properties": {
    "iso:country":"US",
    "sg:address":"11804 Inwood Rd",
    "sg:city":"Dallas",
    "sg:classifiers":[
        {
            "category":"Autos & Motor Vehicles",
            "subcategory":"Fuel & Gas Station",
            "type":"Retail Goods"
        }
    ],
    "sg:phone":"+1 972 239 3271",
    "sg:postcode":"75244",
    "sg:province":"TX",
    "sg:tags":[
        "repair",
        "oil"
    ],
    "sg:website":"www.dunlapswain.com",
    "wof:name":"Dunlap-Swain Tire Co",
    "wof:placetype":"venue"
},
  "geometry": {"coordinates":[-96.81819900000001,32.909801],"type":"Point"}
}