{
  "type": "Feature",
  "properties": {
    "iso:country":"US",
    "sg:address":"8885 W Bellfort St",
    "sg:city":"Houston",
    "sg:classifiers":[
        {
            "category":"Shopping",
            "subcategory":"Pharmacy",
            "type":"Retail Goods"
        }
    ],
    "sg:phone":"+1 713 774 3331",
    "sg:postcode":"77031",
    "sg:province":"TX",
    "sg:tags":[
        "drugstore"
    ],
    "wof:name":"Farmacia Del Pueblo",
    "wof:placetype":"venue"
},
  "geometry": {"coordinates":[-95.533331,29.65611],"type":"Point"}
}