{
  "type": "Feature",
  "properties": {
    "iso:country":"US",
    "sg:address":"219 US Hwy 69",
    "sg:city":"Celeste",
    "sg:classifiers":[
        {
            "category":"Shopping",
            "subcategory":"Bicycles & Sporting Goods",
            "type":"Retail Goods"
        }
    ],
    "sg:phone":"+1 903 450 0978",
    "sg:postcode":"75423",
    "sg:province":"TX",
    "sg:tags":[
        "saddlery",
        "harness"
    ],
    "wof:name":"Bandalero Enterprises",
    "wof:placetype":"venue"
},
  "geometry": {"coordinates":[-96.19123399999999,33.292004],"type":"Point"}
}