{
  "type": "Feature",
  "properties": {
    "iso:country":"US",
    "sg:address":"4881 Saratoga Blvd",
    "sg:city":"Corpus Christi",
    "sg:classifiers":[
        {
            "category":"Banks & Credit Unions",
            "subcategory":"Bank",
            "type":"Services"
        }
    ],
    "sg:phone":"+1 361 884 3051",
    "sg:postcode":"78413",
    "sg:province":"TX",
    "sg:tags":[
        "national",
        "commercial"
    ],
    "wof:name":"Wells Fargo",
    "wof:placetype":"venue"
},
  "geometry": {"coordinates":[-97.396258,27.6917],"type":"Point"}
}