{
  "type": "Feature",
  "properties": {
    "iso:country":"US",
    "sg:address":"4001 I- 35 Svc Rd",
    "sg:city":"Round Rock",
    "sg:classifiers":[
        {
            "category":"Manufacturing",
            "subcategory":"Chemicals & Compounds",
            "type":"Manufacturing & Wholesale Goods"
        }
    ],
    "sg:phone":"+1 512 248 4680",
    "sg:postcode":"78664",
    "sg:province":"TX",
    "sg:tags":[
        "preparation",
        "pharmaceutical",
        "mfg"
    ],
    "wof:name":"McNeil-Ppc Inc",
    "wof:placetype":"venue"
},
  "geometry": {"coordinates":[-97.69195000000001,30.558186],"type":"Point"}
}