{
  "type": "Feature",
  "properties": {
    "iso:country":"US",
    "sg:address":"202 Center St",
    "sg:city":"San Antonio",
    "sg:classifiers":[
        {
            "category":"Sports & Exercise",
            "subcategory":"Golf",
            "type":"Entertainment"
        }
    ],
    "sg:phone":"+1 210 226 6721",
    "sg:postcode":"78202",
    "sg:province":"TX",
    "sg:tags":[
        "course"
    ],
    "wof:name":"Willow Springs Golf Course",
    "wof:placetype":"venue"
},
  "geometry": {"coordinates":[-98.47951399999999,29.42249],"type":"Point"}
}