{
  "type": "Feature",
  "properties": {
    "iso:country":"US",
    "sg:address":"660 Franklin",
    "sg:city":"Lewisville",
    "sg:classifiers":[
        {
            "category":"Manufacturing",
            "subcategory":"Chemicals & Compounds",
            "type":"Manufacturing & Wholesale Goods"
        }
    ],
    "sg:phone":"+1 972 436 4191",
    "sg:postcode":"75057",
    "sg:province":"TX",
    "sg:tags":[
        "supply",
        "printing",
        "industrial",
        "mfg",
        "ink"
    ],
    "wof:name":"Accuratus Ink Co",
    "wof:placetype":"venue"
},
  "geometry": {"coordinates":[-97.016412,33.069508],"type":"Point"}
}