{
  "type": "Feature",
  "properties": {
    "iso:country":"US",
    "sg:address":"400 W Davilla Ave",
    "sg:city":"Rockdale",
    "sg:classifiers":[
        {
            "category":"Place Of Worship",
            "type":"Public Place"
        }
    ],
    "sg:phone":"+1 512 446 2886",
    "sg:postcode":"76567",
    "sg:province":"TX",
    "sg:tags":[
        "church"
    ],
    "wof:name":"Apostolic Faith Chruch",
    "wof:placetype":"venue"
},
  "geometry": {"coordinates":[-97.00567599999999,30.65592],"type":"Point"}
}