{
  "type": "Feature",
  "properties": {
    "iso:country":"US",
    "sg:address":"15402 Vantage Pkwy E",
    "sg:city":"Houston",
    "sg:classifiers":[
        {
            "category":"Freight",
            "type":"Transportation"
        }
    ],
    "sg:phone":"+1 281 590 6804",
    "sg:postcode":"77032",
    "sg:province":"TX",
    "sg:tags":[
        "arrangement"
    ],
    "wof:name":"AOT Gulf Ltd",
    "wof:placetype":"venue"
},
  "geometry": {"coordinates":[-95.36647600000001,29.943337],"type":"Point"}
}