{
  "type": "Feature",
  "properties": {
    "iso:country":"US",
    "sg:address":"13123 Birch Grove Dr",
    "sg:city":"Houston",
    "sg:classifiers":[
        {
            "category":"Wholesale",
            "subcategory":"Groceries",
            "type":"Manufacturing & Wholesale Goods"
        }
    ],
    "sg:phone":"+1 281 933 9981",
    "sg:postcode":"77099",
    "sg:province":"TX",
    "sg:tags":[
        "general"
    ],
    "wof:name":"Teresita A Sarmiento",
    "wof:placetype":"venue"
},
  "geometry": {"coordinates":[-95.613435,29.675823],"type":"Point"}
}