{
  "type": "Feature",
  "properties": {
    "iso:country":"US",
    "sg:address":"12202 Wilderness Trl",
    "sg:city":"Live Oak",
    "sg:classifiers":[
        {
            "category":"Building & Trades",
            "subcategory":"Construction",
            "type":"Services"
        }
    ],
    "sg:phone":"+1 210 650 3925",
    "sg:postcode":"78233",
    "sg:province":"TX",
    "sg:tags":[
        "maker",
        "cabinet"
    ],
    "wof:name":"A-Site Counter Tops",
    "wof:placetype":"venue"
},
  "geometry": {"coordinates":[-98.343272,29.551866],"type":"Point"}
}