{
  "type": "Feature",
  "properties": {
    "iso:country":"US",
    "sg:address":"613 Matlock Centre Cir",
    "sg:city":"Arlington",
    "sg:classifiers":[
        {
            "category":"Health Services",
            "subcategory":"Clinic",
            "type":"Services"
        },
        {
            "category":"Health Services",
            "subcategory":"Health Practitioner",
            "type":"Services"
        }
    ],
    "sg:phone":"+1 817 299 8080",
    "sg:postcode":"76015",
    "sg:province":"TX",
    "sg:tags":[
        "therapist",
        "therapy",
        "physical"
    ],
    "wof:name":"Summit Peak Physical Therapy",
    "wof:placetype":"venue"
},
  "geometry": {"coordinates":[-97.114228,32.701374],"type":"Point"}
}