{
  "type": "Feature",
  "properties": {
    "iso:country":"US",
    "sg:address":"5944 Luther Ln",
    "sg:city":"Dallas",
    "sg:classifiers":[
        {
            "category":"Personal",
            "subcategory":"Beauty Salon",
            "type":"Services"
        }
    ],
    "sg:phone":"+1 214 890 9799",
    "sg:postcode":"75225",
    "sg:province":"TX",
    "sg:tags":[
        "shop"
    ],
    "wof:name":"Preston Ctr Residential I LP",
    "wof:placetype":"venue"
},
  "geometry": {"coordinates":[-96.809702,32.863514],"type":"Point"}
}