{
  "type": "Feature",
  "properties": {
    "iso:country":"US",
    "sg:address":"4711 Kelley St",
    "sg:city":"Houston",
    "sg:classifiers":[
        {
            "category":"Organizations",
            "subcategory":"Religious Organization",
            "type":"Services"
        }
    ],
    "sg:phone":"+1 713 635 1955",
    "sg:postcode":"77026",
    "sg:province":"TX",
    "sg:tags":[
        "church"
    ],
    "sg:website":"www.nmcbc.org",
    "wof:name":"New Mount Calvary Baptist Chr",
    "wof:placetype":"venue"
},
  "geometry": {"coordinates":[-95.33744900000001,29.813372],"type":"Point"}
}