{
  "type": "Feature",
  "properties": {
    "iso:country":"US",
    "sg:address":"303 Scarlet Maple Dr",
    "sg:city":"Sugar Land",
    "sg:classifiers":[
        {
            "category":"Professional",
            "subcategory":"Business Services",
            "type":"Services"
        }
    ],
    "sg:phone":"+1 281 565 4940",
    "sg:postcode":"77479",
    "sg:province":"TX",
    "wof:name":"Y&P Investors Group LLC",
    "wof:placetype":"venue"
},
  "geometry": {"coordinates":[-95.66085200000001,29.603528],"type":"Point"}
}