{
  "type": "Feature",
  "properties": {
    "iso:country":"US",
    "sg:address":"214 W 12th St",
    "sg:city":"Dallas",
    "sg:classifiers":[
        {
            "category":"Professional",
            "subcategory":"Lawyer & Legal Services",
            "type":"Services"
        }
    ],
    "sg:phone":"+1 214 942 1150",
    "sg:postcode":"75208",
    "sg:province":"TX",
    "wof:name":"Antonio A Lopez P C",
    "wof:placetype":"venue"
},
  "geometry": {"coordinates":[-96.826247,32.741195],"type":"Point"}
}