{
  "type": "Feature",
  "properties": {
    "iso:country":"US",
    "sg:address":"3100 S Gessner Rd Ste 315",
    "sg:city":"Houston",
    "sg:classifiers":[
        {
            "category":"Professional",
            "subcategory":"Employment Agencies",
            "type":"Services"
        }
    ],
    "sg:phone":"+1 713 974 3800",
    "sg:postcode":"77063",
    "sg:province":"TX",
    "wof:name":"Corbett Personnel Services Inc",
    "wof:placetype":"venue"
},
  "geometry": {"coordinates":[-95.53939800000001,29.7323],"type":"Point"}
}