{
  "type": "Feature",
  "properties": {
    "iso:country":"US",
    "sg:address":"1107 Central St",
    "sg:city":"Houston",
    "sg:classifiers":[
        {
            "category":"Bars & Pubs",
            "subcategory":"Sports Bar",
            "type":"Food & Drink"
        }
    ],
    "sg:phone":"+1 713 926 7333",
    "sg:postcode":"77012",
    "sg:province":"TX",
    "wof:name":"Kelly's Sports Bar",
    "wof:placetype":"venue"
},
  "geometry": {"coordinates":[-95.259899,29.717074],"type":"Point"}
}