{
  "type": "Feature",
  "properties": {
    "iso:country":"US",
    "sg:address":"1101 Taylor St",
    "sg:city":"Laredo",
    "sg:classifiers":[
        {
            "category":"Cinema",
            "subcategory":"Movie Rental",
            "type":"Entertainment"
        }
    ],
    "sg:phone":"+1 956 724 4837",
    "sg:postcode":"78041",
    "sg:province":"TX",
    "sg:tags":[
        "electrical",
        "video",
        "tape",
        "repair"
    ],
    "wof:name":"Star Ship Vacuum Cleaners",
    "wof:placetype":"venue"
},
  "geometry": {"coordinates":[-99.48434399999999,27.536942],"type":"Point"}
}