{
  "type": "Feature",
  "properties": {
    "iso:country":"US",
    "sg:address":"5307 Mockingbird Ln",
    "sg:city":"Dallas",
    "sg:classifiers":[
        {
            "category":"Professional",
            "subcategory":"Lawyer & Legal Services",
            "type":"Services"
        }
    ],
    "sg:phone":"+1 214 828 1672",
    "sg:postcode":"75206",
    "sg:province":"TX",
    "sg:tags":[
        "attorney"
    ],
    "wof:name":"Jones Law Firm",
    "wof:placetype":"venue"
},
  "geometry": {"coordinates":[-96.77866299999999,32.836585],"type":"Point"}
}