{
  "type": "Feature",
  "properties": {
    "iso:country":"US",
    "sg:address":"6351 Westheimer Rd",
    "sg:city":"Houston",
    "sg:classifiers":[
        {
            "category":"Shopping",
            "subcategory":"Clothing, Apparel, & Fashions",
            "type":"Retail Goods"
        }
    ],
    "sg:phone":"+1 832 242 6037",
    "sg:postcode":"77057",
    "sg:province":"TX",
    "wof:name":"Tassel Boutique",
    "wof:placetype":"venue"
},
  "geometry": {"coordinates":[-95.49633799999999,29.737557],"type":"Point"}
}