{
  "type": "Feature",
  "properties": {
    "iso:country":"US",
    "sg:address":"425 W Lamar St",
    "sg:city":"Sherman",
    "sg:classifiers":[
        {
            "category":"Education",
            "subcategory":"Dance Studio",
            "type":"Public Place"
        },
        {
            "category":"Shopping",
            "subcategory":"Clothing, Apparel, & Fashions",
            "type":"Retail Goods"
        }
    ],
    "sg:phone":"+1 903 813 8444",
    "sg:postcode":"75090",
    "sg:province":"TX",
    "sg:tags":[
        "instruction",
        "dancing"
    ],
    "wof:name":"Shermans Center Stage Dance A",
    "wof:placetype":"venue"
},
  "geometry": {"coordinates":[-96.614938,33.634471],"type":"Point"}
}