{
  "type": "Feature",
  "properties": {
    "iso:country":"US",
    "sg:address":"601 S Poplar St",
    "sg:city":"Kermit",
    "sg:classifiers":[
        {
            "category":"Education",
            "subcategory":"School",
            "type":"Public Place"
        }
    ],
    "sg:phone":"+1 432 586 1000",
    "sg:postcode":"79745",
    "sg:province":"TX",
    "wof:name":"Kermit Isd School District",
    "wof:placetype":"venue"
},
  "geometry": {"coordinates":[-103.089868,31.851402],"type":"Point"}
}