{
  "type": "Feature",
  "properties": {
    "iso:country":"US",
    "sg:address":"10801 Airport Blvd",
    "sg:city":"Amarillo",
    "sg:classifiers":[
        {
            "category":"Government",
            "subcategory":"Office",
            "type":"Public Place"
        }
    ],
    "sg:phone":"+1 806 335 3533",
    "sg:postcode":"79111",
    "sg:province":"TX",
    "sg:tags":[
        "federal",
        "taxation"
    ],
    "wof:name":"US Customs Svc",
    "wof:placetype":"venue"
},
  "geometry": {"coordinates":[-101.702133,35.216446],"type":"Point"}
}