{
  "type": "Feature",
  "properties": {
    "iso:country":"US",
    "sg:address":"610 E Cross St",
    "sg:city":"Muenster",
    "sg:classifiers":[
        {
            "category":"Mining & Drilling",
            "type":"Manufacturing & Wholesale Goods"
        }
    ],
    "sg:phone":"+1 940 759 4266",
    "sg:postcode":"76252",
    "sg:province":"TX",
    "sg:tags":[
        "oil",
        "gas",
        "producer"
    ],
    "wof:name":"Powell & Brown Oil Co",
    "wof:placetype":"venue"
},
  "geometry": {"coordinates":[-97.36709999999999,33.6465],"type":"Point"}
}