{
  "type": "Feature",
  "properties": {
    "iso:country":"US",
    "sg:address":"6836 Bee Caves Rd",
    "sg:city":"Austin",
    "sg:classifiers":[
        {
            "category":"Professional",
            "subcategory":"Art Services",
            "type":"Services"
        }
    ],
    "sg:phone":"+1 512 705 3813",
    "sg:postcode":"78746",
    "sg:province":"TX",
    "sg:tags":[
        "photographer"
    ],
    "wof:name":"Click Photo",
    "wof:placetype":"venue"
},
  "geometry": {"coordinates":[-97.83698,30.300562],"type":"Point"}
}