{
  "type": "Feature",
  "properties": {
    "iso:country":"US",
    "sg:address":"502 E Main St",
    "sg:city":"Madisonville",
    "sg:classifiers":[
        {
            "category":"Shopping",
            "subcategory":"Used Merchandise",
            "type":"Retail Goods"
        }
    ],
    "sg:phone":"+1 936 348 5866",
    "sg:postcode":"77864",
    "sg:province":"TX",
    "sg:tags":[
        "antique"
    ],
    "wof:name":"Shady Creek Antiques",
    "wof:placetype":"venue"
},
  "geometry": {"coordinates":[-95.91002400000001,30.950767],"type":"Point"}
}