{
  "type": "Feature",
  "properties": {
    "iso:country":"US",
    "sg:address":"6796 FM 1818 E",
    "sg:city":"Diboll",
    "sg:classifiers":[
        {
            "category":"Wholesale",
            "subcategory":"Petroleum",
            "type":"Manufacturing & Wholesale Goods"
        }
    ],
    "sg:phone":"+1 936 829 3900",
    "sg:postcode":"75941",
    "sg:province":"TX",
    "sg:tags":[
        "pipe",
        "line",
        "company"
    ],
    "wof:name":"Sun Pipe Line Co",
    "wof:placetype":"venue"
},
  "geometry": {"coordinates":[-94.67948800000001,31.159446],"type":"Point"}
}