{
  "type": "Feature",
  "properties": {
    "iso:country":"US",
    "sg:address":"805 8th St",
    "sg:city":"Honey Grove",
    "sg:classifiers":[
        {
            "category":"Food & Beverages",
            "subcategory":"Groceries & Convenience Stores",
            "type":"Retail Goods"
        }
    ],
    "sg:phone":"+1 903 378 3616",
    "sg:postcode":"75446",
    "sg:province":"TX",
    "wof:name":"Pennis",
    "wof:placetype":"venue"
},
  "geometry": {"coordinates":[-95.90769400000001,33.586421],"type":"Point"}
}