{
  "type": "Feature",
  "properties": {
    "iso:country":"US",
    "sg:address":"1924 N Grand Ave",
    "sg:city":"Sherman",
    "sg:classifiers":[
        {
            "category":"Insurance",
            "subcategory":"Insurance Agent",
            "type":"Services"
        }
    ],
    "sg:phone":"+1 903 891 4646",
    "sg:postcode":"75090",
    "sg:province":"TX",
    "wof:name":"Nationwide Mutual Insurance",
    "wof:placetype":"venue"
},
  "geometry": {"coordinates":[-96.601488,33.656208],"type":"Point"}
}