{
  "type": "Feature",
  "properties": {
    "iso:country":"US",
    "sg:address":"3415 Custer Rd",
    "sg:city":"Plano",
    "sg:classifiers":[
        {
            "category":"Building & Trades",
            "subcategory":"Construction",
            "type":"Services"
        }
    ],
    "sg:phone":"+1 972 596 6001",
    "sg:postcode":"75023",
    "sg:province":"TX",
    "sg:tags":[
        "roofing",
        "contractor"
    ],
    "wof:name":"Burtis Roofing Co",
    "wof:placetype":"venue"
},
  "geometry": {"coordinates":[-96.73347699999999,33.042206],"type":"Point"}
}