{
  "type": "Feature",
  "properties": {
    "iso:country":"US",
    "sg:address":"3401 Kirby Dr",
    "sg:city":"Houston",
    "sg:classifiers":[
        {
            "category":"Restaurant",
            "type":"Food & Drink"
        }
    ],
    "sg:phone":"+1 713 528 8998",
    "sg:postcode":"77098",
    "sg:province":"TX",
    "sg:tags":[
        "sushi",
        "bar",
        "japanese"
    ],
    "sg:website":"www.sushiking.us",
    "wof:name":"Sushi King",
    "wof:placetype":"venue"
},
  "geometry": {"coordinates":[-95.418646,29.734854],"type":"Point"}
}