{
  "type": "Feature",
  "properties": {
    "iso:country":"US",
    "sg:address":"20543 Cypress Gully Dr",
    "sg:city":"Cypress",
    "sg:classifiers":[
        {
            "category":"Place Of Worship",
            "type":"Public Place"
        }
    ],
    "sg:phone":"+1 281 861 7953",
    "sg:postcode":"77433",
    "sg:province":"TX",
    "sg:tags":[
        "church"
    ],
    "wof:name":"Iglesia Evangelica Cristo",
    "wof:placetype":"venue"
},
  "geometry": {"coordinates":[-95.72466900000001,29.882474],"type":"Point"}
}