{
  "type": "Feature",
  "properties": {
    "iso:country":"US",
    "sg:address":"615 S Ave H",
    "sg:city":"Clifton",
    "sg:classifiers":[
        {
            "category":"Home & Garden",
            "subcategory":"Mobile Homes",
            "type":"Retail Goods"
        }
    ],
    "sg:phone":"+1 254 675 6318",
    "sg:postcode":"76634",
    "sg:province":"TX",
    "wof:name":"Action Mobile Glass",
    "wof:placetype":"venue"
},
  "geometry": {"coordinates":[-97.575363,31.777057],"type":"Point"}
}