{
  "type": "Feature",
  "properties": {
    "iso:country":"US",
    "sg:address":"8014 Cantura Mills",
    "sg:city":"Converse",
    "sg:classifiers":[
        {
            "category":"Professional",
            "subcategory":"Management & Consulting",
            "type":"Services"
        }
    ],
    "sg:phone":"+1 210 566 6163",
    "sg:postcode":"78109",
    "sg:province":"TX",
    "sg:tags":[
        "logistics",
        "consultant"
    ],
    "wof:name":"Milspec Associates",
    "wof:placetype":"venue"
},
  "geometry": {"coordinates":[-98.32661,29.506059],"type":"Point"}
}