{
  "type": "Feature",
  "properties": {
    "iso:country":"US",
    "sg:address":"3509 Forest Ln",
    "sg:city":"Garland",
    "sg:classifiers":[
        {
            "category":"Autos & Motor Vehicles",
            "subcategory":"Automobile Sales",
            "type":"Retail Goods"
        }
    ],
    "sg:phone":"+1 972 272 0299",
    "sg:postcode":"75042",
    "sg:province":"TX",
    "sg:tags":[
        "dealers-used",
        "car",
        "used",
        "cars-wholesale"
    ],
    "wof:name":"Bedard Motor Co",
    "wof:placetype":"venue"
},
  "geometry": {"coordinates":[-96.68319,32.909318],"type":"Point"}
}