{
  "type": "Feature",
  "properties": {
    "iso:country":"US",
    "sg:address":"2800 Texas Ave",
    "sg:city":"Texas City",
    "sg:classifiers":[
        {
            "category":"Banks & Credit Unions",
            "subcategory":"Bank",
            "type":"Services"
        }
    ],
    "sg:phone":"+1 409 965 8344",
    "sg:postcode":"77590",
    "sg:province":"TX",
    "sg:tags":[
        "federal"
    ],
    "wof:name":"Texas Dow Employees Credit Un",
    "wof:placetype":"venue"
},
  "geometry": {"coordinates":[-94.93527400000001,29.383872],"type":"Point"}
}