{
  "type": "Feature",
  "properties": {
    "iso:country":"US",
    "sg:address":"4825 Sweetwater Blvd",
    "sg:city":"Sugar Land",
    "sg:classifiers":[
        {
            "category":"Banks & Credit Unions",
            "subcategory":"Bank",
            "type":"Services"
        }
    ],
    "sg:phone":"+1 713 578 3750",
    "sg:postcode":"77479",
    "sg:province":"TX",
    "wof:name":"Bank Of Texas",
    "wof:placetype":"venue"
},
  "geometry": {"coordinates":[-95.63168,29.585452],"type":"Point"}
}