{
  "type": "Feature",
  "properties": {
    "iso:country":"US",
    "sg:address":"6116 Breen Dr",
    "sg:city":"Houston",
    "sg:classifiers":[
        {
            "category":"Personal",
            "subcategory":"Beauty Salon",
            "type":"Services"
        }
    ],
    "sg:phone":"+1 281 820 9667",
    "sg:postcode":"77086",
    "sg:province":"TX",
    "sg:tags":[
        "shop"
    ],
    "wof:name":"Breens Hair & Nail Skin Care",
    "wof:placetype":"venue"
},
  "geometry": {"coordinates":[-95.48449599999999,29.899795],"type":"Point"}
}