{
  "type": "Feature",
  "properties": {
    "iso:country":"US",
    "sg:address":"107 Sunny Creek Dr",
    "sg:city":"Georgetown",
    "sg:classifiers":[
        {
            "category":"Building & Trades",
            "subcategory":"Construction",
            "type":"Services"
        }
    ],
    "sg:phone":"+1 512 863 7914",
    "sg:postcode":"78626",
    "sg:province":"TX",
    "sg:tags":[
        "repair",
        "handyman",
        "maintenance",
        "home"
    ],
    "wof:name":"Pts Handyman",
    "wof:placetype":"venue"
},
  "geometry": {"coordinates":[-97.593613,30.643709],"type":"Point"}
}