{
  "type": "Feature",
  "properties": {
    "iso:country":"US",
    "sg:address":"2802 Tanglewood Dr",
    "sg:city":"Commerce",
    "sg:classifiers":[
        {
            "category":"Education",
            "subcategory":"School",
            "type":"Public Place"
        }
    ],
    "sg:phone":"+1 903 886 2834",
    "sg:postcode":"75428",
    "sg:province":"TX",
    "wof:name":"Academy of Musical Arts",
    "wof:placetype":"venue"
},
  "geometry": {"coordinates":[-95.89767000000001,33.234158],"type":"Point"}
}