{
  "type": "Feature",
  "properties": {
    "iso:country":"US",
    "sg:address":"124 W Main St",
    "sg:city":"Eagle Lake",
    "sg:classifiers":[
        {
            "category":"Wholesale",
            "subcategory":"Groceries",
            "type":"Manufacturing & Wholesale Goods"
        }
    ],
    "sg:phone":"+1 979 234 2561",
    "sg:postcode":"77434",
    "sg:province":"TX",
    "sg:tags":[
        "rice"
    ],
    "wof:name":"Area Rice Marketing",
    "wof:placetype":"venue"
},
  "geometry": {"coordinates":[-96.335204,29.589626],"type":"Point"}
}