{
  "type": "Feature",
  "properties": {
    "iso:country":"US",
    "sg:address":"1430 Laurie St",
    "sg:city":"Vernon",
    "sg:classifiers":[
        {
            "category":"Professional",
            "subcategory":"Management & Consulting",
            "type":"Services"
        }
    ],
    "sg:phone":"+1 940 553 3543",
    "sg:postcode":"76384",
    "sg:province":"TX",
    "sg:tags":[
        "agricultural",
        "consultant"
    ],
    "wof:name":"Texas Boll Weevil Eradication",
    "wof:placetype":"venue"
},
  "geometry": {"coordinates":[-99.271393,34.156285],"type":"Point"}
}