{
  "type": "Feature",
  "properties": {
    "iso:country":"US",
    "sg:address":"100 Oak Hill Dr",
    "sg:city":"New Braunfels",
    "sg:classifiers":[
        {
            "category":"Retail",
            "subcategory":"Laundry & Dry Cleaning",
            "type":"Services"
        }
    ],
    "sg:phone":"+1 830 625 2551",
    "sg:postcode":"78132",
    "sg:province":"TX",
    "sg:tags":[
        "coin",
        "power"
    ],
    "wof:name":"Wash House",
    "wof:placetype":"venue"
},
  "geometry": {"coordinates":[-98.179332,29.750152],"type":"Point"}
}