{
  "type": "Feature",
  "properties": {
    "iso:country":"US",
    "sg:address":"11857 Brooks Rd",
    "sg:city":"Beaumont",
    "sg:classifiers":[
        {
            "category":"Recreation",
            "type":"Entertainment"
        }
    ],
    "sg:phone":"+1 409 866 9927",
    "sg:postcode":"77713",
    "sg:province":"TX",
    "wof:name":"Sennets Prston J Hndgun Acdemy",
    "wof:placetype":"venue"
},
  "geometry": {"coordinates":[-94.244868,30.023417],"type":"Point"}
}