{
  "type": "Feature",
  "properties": {
    "iso:country":"US",
    "sg:address":"20502 Riverside Pines Dr",
    "sg:city":"Humble",
    "sg:classifiers":[
        {
            "category":"Professional",
            "type":"Services"
        }
    ],
    "sg:phone":"+1 281 812 4892",
    "sg:postcode":"77346",
    "sg:province":"TX",
    "wof:name":"Mgc Designs",
    "wof:placetype":"venue"
},
  "geometry": {"coordinates":[-95.153747,30.019899],"type":"Point"}
}