{
  "type": "Feature",
  "properties": {
    "iso:country":"US",
    "sg:address":"19700 Hickory Twig Way",
    "sg:city":"Spring",
    "sg:classifiers":[
        {
            "category":"Professional",
            "subcategory":"Management & Consulting",
            "type":"Services"
        }
    ],
    "sg:phone":"+1 281 288 1981",
    "sg:postcode":"77388",
    "sg:province":"TX",
    "wof:name":"Barrett Marketing",
    "wof:placetype":"venue"
},
  "geometry": {"coordinates":[-95.43955,30.05349],"type":"Point"}
}