{
  "type": "Feature",
  "properties": {
    "iso:country":"US",
    "sg:address":"14005 N Highway 183 Ste 300",
    "sg:city":"Austin",
    "sg:classifiers":[
        {
            "category":"Restaurant",
            "type":"Food & Drink"
        }
    ],
    "sg:phone":"+1 512 506 8300",
    "sg:postcode":"78717",
    "sg:province":"TX",
    "wof:name":"Hannah D's",
    "wof:placetype":"venue"
},
  "geometry": {"coordinates":[-97.689091,30.240839],"type":"Point"}
}