{
  "type": "Feature",
  "properties": {
    "iso:country":"US",
    "sg:address":"22638 Black Willow Dr",
    "sg:city":"Tomball",
    "sg:classifiers":[
        {
            "category":"Shopping",
            "subcategory":"Hobbies, Toys, & Games",
            "type":"Retail Goods"
        }
    ],
    "sg:phone":"+1 281 379 5795",
    "sg:postcode":"77375",
    "sg:province":"TX",
    "sg:tags":[
        "craft",
        "supply"
    ],
    "wof:name":"Fayvorite",
    "wof:placetype":"venue"
},
  "geometry": {"coordinates":[-95.54631999999999,30.094839],"type":"Point"}
}