{
  "type": "Feature",
  "properties": {
    "iso:country":"US",
    "sg:address":"107 N Highway 77",
    "sg:city":"Waxahachie",
    "sg:classifiers":[
        {
            "category":"Real Estate",
            "subcategory":"Real Estate Operator",
            "type":"Services"
        }
    ],
    "sg:phone":"+1 972 937 2143",
    "sg:postcode":"75165",
    "sg:province":"TX",
    "sg:tags":[
        "apartment"
    ],
    "wof:name":"Kitchenett Apartments",
    "wof:placetype":"venue"
},
  "geometry": {"coordinates":[-96.843546,32.399802],"type":"Point"}
}