{
  "type": "Feature",
  "properties": {
    "iso:country":"US",
    "sg:address":"620 Curtis Rd",
    "sg:city":"Burleson",
    "sg:classifiers":[
        {
            "category":"Mining & Drilling",
            "type":"Manufacturing & Wholesale Goods"
        }
    ],
    "sg:phone":"+1 817 426 3939",
    "sg:postcode":"76028",
    "sg:province":"TX",
    "sg:tags":[
        "field"
    ],
    "wof:name":"H/H Consultants",
    "wof:placetype":"venue"
},
  "geometry": {"coordinates":[-97.26649399999999,32.51672],"type":"Point"}
}