{
  "type": "Feature",
  "properties": {
    "iso:country":"US",
    "sg:address":"1961 Martin Luther King Jr Blvd",
    "sg:city":"Corsicana",
    "sg:classifiers":[
        {
            "category":"Fast Food",
            "type":"Food & Drink"
        },
        {
            "category":"Restaurant",
            "type":"Food & Drink"
        },
        {
            "category":"Food & Beverages",
            "subcategory":"Groceries & Convenience Stores",
            "type":"Retail Goods"
        }
    ],
    "sg:phone":"+1 903 874 1232",
    "sg:postcode":"75110",
    "sg:province":"TX",
    "sg:tags":[
        "shop",
        "american",
        "sandwich",
        "take"
    ],
    "sg:website":"http://www.subway.com",
    "wof:name":"Subway",
    "wof:placetype":"venue"
},
  "geometry": {"coordinates":[-96.41244399999999,32.101206],"type":"Point"}
}