{
  "type": "Feature",
  "properties": {
    "iso:country":"US",
    "sg:address":"109 S Main St",
    "sg:city":"Mcallen",
    "sg:classifiers":[
        {
            "category":"Shopping",
            "subcategory":"Shoes",
            "type":"Retail Goods"
        }
    ],
    "sg:phone":"+1 956 928 1868",
    "sg:postcode":"78501",
    "sg:province":"TX",
    "wof:name":"America & Asia",
    "wof:placetype":"venue"
},
  "geometry": {"coordinates":[-98.234638,26.202465],"type":"Point"}
}