{
  "type": "Feature",
  "properties": {
    "iso:country":"US",
    "sg:address":"1044 Blaylock Cir S",
    "sg:city":"Irving",
    "sg:classifiers":[
        {
            "category":"Professional",
            "subcategory":"Employment Agencies",
            "type":"Services"
        }
    ],
    "sg:phone":"+1 972 259 2535",
    "sg:postcode":"75061",
    "sg:province":"TX",
    "sg:tags":[
        "help",
        "supply"
    ],
    "wof:name":"Michael W Arnett",
    "wof:placetype":"venue"
},
  "geometry": {"coordinates":[-96.957825,32.82291],"type":"Point"}
}