{
  "type": "Feature",
  "properties": {
    "iso:country":"US",
    "sg:address":"1196 Town East Mall",
    "sg:city":"Mesquite",
    "sg:classifiers":[
        {
            "category":"Shopping",
            "subcategory":"Beauty & Cosmetics",
            "type":"Retail Goods"
        }
    ],
    "sg:phone":"+1 972 682 5776",
    "sg:postcode":"75150",
    "sg:province":"TX",
    "sg:tags":[
        "merchandise"
    ],
    "wof:name":"Origins",
    "wof:placetype":"venue"
},
  "geometry": {"coordinates":[-96.626833,32.808647],"type":"Point"}
}