{
  "type": "Feature",
  "properties": {
    "iso:country":"US",
    "sg:address":"4531 McKinney Ave",
    "sg:city":"Dallas",
    "sg:classifiers":[
        {
            "category":"Professional",
            "type":"Services"
        },
        {
            "category":"Education",
            "subcategory":"Vocational School",
            "type":"Public Place"
        },
        {
            "category":"Retail",
            "subcategory":"Event Space",
            "type":"Services"
        }
    ],
    "sg:phone":"+1 214 217 2807",
    "sg:postcode":"75205",
    "sg:province":"TX",
    "sg:tags":[
        "cooking",
        "venue",
        "caterer"
    ],
    "sg:website":"www.milestoneculinary.com",
    "wof:name":"Milestone Culinary Arts Center",
    "wof:placetype":"venue"
},
  "geometry": {"coordinates":[-96.788144,32.821535],"type":"Point"}
}