{
  "type": "Feature",
  "properties": {
    "iso:country":"US",
    "sg:address":"2424 N Henderson Ave",
    "sg:city":"Dallas",
    "sg:classifiers":[
        {
            "category":"Building & Trades",
            "subcategory":"Landscaping Services",
            "type":"Services"
        }
    ],
    "sg:phone":"+1 214 821 4979",
    "sg:postcode":"75206",
    "sg:province":"TX",
    "sg:tags":[
        "lawn",
        "maintenance",
        "grounds"
    ],
    "wof:name":"Thomas Lawn Care",
    "wof:placetype":"venue"
},
  "geometry": {"coordinates":[-96.779287,32.815592],"type":"Point"}
}