{
  "type": "Feature",
  "properties": {
    "iso:country":"US",
    "sg:address":"22318 I- 45",
    "sg:city":"Spring",
    "sg:classifiers":[
        {
            "category":"Shopping",
            "type":"Retail Goods"
        }
    ],
    "sg:phone":"+1 281 350 0818",
    "sg:postcode":"77373",
    "sg:province":"TX",
    "sg:tags":[
        "spa",
        "hot",
        "tub"
    ],
    "wof:name":"Island Mist Spas & Pools",
    "wof:placetype":"venue"
},
  "geometry": {"coordinates":[-95.435711,30.103876],"type":"Point"}
}