{
  "type": "Feature",
  "properties": {
    "iso:country":"US",
    "sg:address":"306 Mary Lou Dr",
    "sg:city":"Del Rio",
    "sg:classifiers":[
        {
            "category":"Retail",
            "subcategory":"Repair Shop",
            "type":"Services"
        }
    ],
    "sg:phone":"+1 830 775 1701",
    "sg:postcode":"78840",
    "sg:province":"TX",
    "sg:tags":[
        "sporting"
    ],
    "wof:name":"D & D Reel Service",
    "wof:placetype":"venue"
},
  "geometry": {"coordinates":[-100.911484,29.39056],"type":"Point"}
}