{
  "type": "Feature",
  "properties": {
    "iso:country":"US",
    "sg:address":"4536 Major Sprague Ave",
    "sg:city":"El Paso",
    "sg:classifiers":[
        {
            "category":"Shopping",
            "subcategory":"Gifts & Souvenirs",
            "type":"Retail Goods"
        }
    ],
    "sg:phone":"+1 915 757 3212",
    "sg:postcode":"79924",
    "sg:province":"TX",
    "wof:name":"Joans Lil Gift Shop",
    "wof:placetype":"venue"
},
  "geometry": {"coordinates":[-106.438052,31.874335],"type":"Point"}
}