{
  "type": "Feature",
  "properties": {
    "iso:country":"US",
    "sg:address":"1125 Wilma St",
    "sg:city":"Tyler",
    "sg:classifiers":[
        {
            "category":"Real Estate",
            "subcategory":"Real Estate Agent",
            "type":"Services"
        }
    ],
    "sg:phone":"+1 903 579 0711",
    "sg:postcode":"75701",
    "sg:province":"TX",
    "wof:name":"Sun West Realty",
    "wof:placetype":"venue"
},
  "geometry": {"coordinates":[-95.28639800000001,32.320616],"type":"Point"}
}