{
  "type": "Feature",
  "properties": {
    "iso:country":"US",
    "sg:address":"211 Legendary Ln",
    "sg:city":"Gun Barrel City",
    "sg:classifiers":[
        {
            "category":"Retail",
            "subcategory":"Auto Repair",
            "type":"Services"
        }
    ],
    "sg:phone":"+1 903 887 4036",
    "sg:postcode":"75156",
    "sg:province":"TX",
    "sg:tags":[
        "exchanging",
        "engine"
    ],
    "wof:name":"Pro Machine Svc",
    "wof:placetype":"venue"
},
  "geometry": {"coordinates":[-96.151174,32.324448],"type":"Point"}
}