{
  "type": "Feature",
  "properties": {
    "iso:country":"US",
    "sg:address":"6103 Inway Dr",
    "sg:city":"Spring",
    "sg:classifiers":[
        {
            "category":"Professional",
            "type":"Services"
        }
    ],
    "sg:phone":"+1 281 257 1546",
    "sg:postcode":"77389",
    "sg:province":"TX",
    "wof:name":"Klein Oak Area Swim Team",
    "wof:placetype":"venue"
},
  "geometry": {"coordinates":[-95.512576,30.109735],"type":"Point"}
}