{
  "type": "Feature",
  "properties": {
    "iso:country":"US",
    "sg:address":"111 E Canal Rd",
    "sg:city":"Highlands",
    "sg:classifiers":[
        {
            "category":"Organizations",
            "subcategory":"Religious Organization",
            "type":"Services"
        }
    ],
    "sg:phone":"+1 281 426 2470",
    "sg:postcode":"77562",
    "sg:province":"TX",
    "sg:tags":[
        "church"
    ],
    "wof:name":"Highlands Baptist",
    "wof:placetype":"venue"
},
  "geometry": {"coordinates":[-95.056212,29.82691],"type":"Point"}
}