{
  "type": "Feature",
  "properties": {
    "iso:country":"US",
    "sg:address":"1319 Castroville Rd",
    "sg:city":"San Antonio",
    "sg:classifiers":[
        {
            "category":"Insurance",
            "subcategory":"Insurance Agent",
            "type":"Services"
        }
    ],
    "sg:phone":"+1 210 434 2311",
    "sg:postcode":"78237",
    "sg:province":"TX",
    "wof:name":"A & A Insurance",
    "wof:placetype":"venue"
},
  "geometry": {"coordinates":[-98.56030699999999,29.415135],"type":"Point"}
}