{
  "type": "Feature",
  "properties": {
    "iso:country":"US",
    "sg:address":"14665 N Loop Dr",
    "sg:city":"Clint",
    "sg:classifiers":[
        {
            "category":"Farming",
            "subcategory":"Dairy Farm",
            "type":"Manufacturing & Wholesale Goods"
        }
    ],
    "sg:phone":"+1 915 851 2697",
    "sg:postcode":"79836",
    "sg:province":"TX",
    "wof:name":"Juan Escobar Dairy",
    "wof:placetype":"venue"
},
  "geometry": {"coordinates":[-106.185675,31.553849],"type":"Point"}
}