{
  "type": "Feature",
  "properties": {
    "iso:country":"US",
    "sg:address":"4724 S Parkway St",
    "sg:city":"Conroe",
    "sg:classifiers":[
        {
            "category":"Government",
            "subcategory":"Office",
            "type":"Public Place"
        }
    ],
    "sg:phone":"+1 936 539 5060",
    "sg:postcode":"77303",
    "sg:province":"TX",
    "sg:tags":[
        "armed",
        "force",
        "recruiting"
    ],
    "wof:name":"USARC-Retention",
    "wof:placetype":"venue"
},
  "geometry": {"coordinates":[-95.424859,30.347944],"type":"Point"}
}