{
  "type": "Feature",
  "properties": {
    "iso:country":"US",
    "sg:address":"18023 Firecrest Ct",
    "sg:city":"Dallas",
    "sg:classifiers":[
        {
            "category":"Manufacturing",
            "subcategory":"Textiles",
            "type":"Manufacturing & Wholesale Goods"
        }
    ],
    "sg:phone":"+1 972 387 4545",
    "sg:postcode":"75252",
    "sg:province":"TX",
    "sg:tags":[
        "mill",
        "fabric",
        "cotton"
    ],
    "wof:name":"Galey & Lord Inc",
    "wof:placetype":"venue"
},
  "geometry": {"coordinates":[-96.801737,32.997663],"type":"Point"}
}