{
  "type": "Feature",
  "properties": {
    "iso:country":"US",
    "sg:address":"2602 Bear Trl",
    "sg:city":"Orange",
    "sg:classifiers":[
        {
            "category":"Professional",
            "subcategory":"Engineering",
            "type":"Services"
        }
    ],
    "sg:phone":"+1 409 883 9095",
    "sg:postcode":"77632",
    "sg:province":"TX",
    "sg:tags":[
        "engineer"
    ],
    "wof:name":"Recon Engineering",
    "wof:placetype":"venue"
},
  "geometry": {"coordinates":[-93.765297,30.157985],"type":"Point"}
}