{
  "type": "Feature",
  "properties": {
    "iso:country":"US",
    "sg:address":"1009 Hospital Dr",
    "sg:city":"Tyler",
    "sg:classifiers":[
        {
            "category":"Health Services",
            "subcategory":"Dentist",
            "type":"Services"
        }
    ],
    "sg:phone":"+1 903 593 6585",
    "sg:postcode":"75701",
    "sg:province":"TX",
    "sg:tags":[
        "product",
        "dentists-cosmetic",
        "denture",
        "dental",
        "teeth",
        "dentists-periodontists",
        "clinic",
        "whitening",
        "dentistry",
        "implant",
        "dentists-prosthodontists",
        "dentists-implantology"
    ],
    "sg:website":"http://www.azaleadentalcare.com",
    "wof:name":"Azalea Dental",
    "wof:placetype":"venue"
},
  "geometry": {"coordinates":[-95.291389,32.337506],"type":"Point"}
}