{
  "type": "Feature",
  "properties": {
    "iso:country":"US",
    "sg:address":"4503 N Mesa St",
    "sg:city":"El Paso",
    "sg:classifiers":[
        {
            "category":"Banks & Credit Unions",
            "subcategory":"Investment Brokerage",
            "type":"Services"
        }
    ],
    "sg:phone":"+1 915 544 4921",
    "sg:postcode":"79912",
    "sg:province":"TX",
    "sg:tags":[
        "stock"
    ],
    "wof:name":"Citigroup Global Markets Inc",
    "wof:placetype":"venue"
},
  "geometry": {"coordinates":[-106.509995,31.802205],"type":"Point"}
}