{
  "type": "Feature",
  "properties": {
    "iso:country":"US",
    "sg:address":"3717 Lafferty Ln",
    "sg:city":"Mcallen",
    "sg:classifiers":[
        {
            "category":"Wholesale",
            "subcategory":"Durable Goods & Equipment",
            "type":"Manufacturing & Wholesale Goods"
        }
    ],
    "sg:phone":"+1 956 630 2495",
    "sg:postcode":"78504",
    "sg:province":"TX",
    "wof:name":"Campbell Fence & Supply",
    "wof:placetype":"venue"
},
  "geometry": {"coordinates":[-98.245964,26.293276],"type":"Point"}
}