{
  "type": "Feature",
  "properties": {
    "iso:country":"US",
    "sg:address":"4100 N 27th St",
    "sg:city":"Waco",
    "sg:classifiers":[
        {
            "category":"Real Estate",
            "subcategory":"Developer",
            "type":"Services"
        }
    ],
    "sg:phone":"+1 254 754 4382",
    "sg:postcode":"76708",
    "sg:province":"TX",
    "sg:tags":[
        "cemetery"
    ],
    "wof:name":"Liberty Grove Cemetery Assn",
    "wof:placetype":"venue"
},
  "geometry": {"coordinates":[-97.186396,31.581581],"type":"Point"}
}