{
  "type": "Feature",
  "properties": {
    "iso:country":"US",
    "sg:address":"106 E Weaver Ave",
    "sg:city":"Alvarado",
    "sg:classifiers":[
        {
            "category":"Recreation",
            "subcategory":"Amusement Park",
            "type":"Entertainment"
        }
    ],
    "sg:phone":"+1 817 790 0330",
    "sg:postcode":"76009",
    "sg:province":"TX",
    "wof:name":"Harly's Family Amusement Ctr",
    "wof:placetype":"venue"
},
  "geometry": {"coordinates":[-97.211406,32.40617],"type":"Point"}
}