{
  "type": "Feature",
  "properties": {
    "iso:country":"US",
    "sg:address":"900 Round Rock Ave",
    "sg:city":"Round Rock",
    "sg:classifiers":[
        {
            "category":"Banks & Credit Unions",
            "subcategory":"Bank",
            "type":"Services"
        }
    ],
    "sg:phone":"+1 512 733 0600",
    "sg:postcode":"78681",
    "sg:province":"TX",
    "sg:tags":[
        "loan",
        "real estate"
    ],
    "wof:name":"Allied Home Mortgage Capital",
    "wof:placetype":"venue"
},
  "geometry": {"coordinates":[-97.69152699999999,30.511574],"type":"Point"}
}