{
  "type": "Feature",
  "properties": {
    "iso:country":"US",
    "sg:address":"4819 Waynesboro Dr",
    "sg:city":"Houston",
    "sg:classifiers":[
        {
            "category":"Building & Trades",
            "subcategory":"Construction",
            "type":"Services"
        }
    ],
    "sg:phone":"+1 713 465 1800",
    "sg:postcode":"77035",
    "sg:province":"TX",
    "sg:tags":[
        "interior",
        "design"
    ],
    "wof:name":"Staged Right",
    "wof:placetype":"venue"
},
  "geometry": {"coordinates":[-95.459627,29.669669],"type":"Point"}
}