{
  "type": "Feature",
  "properties": {
    "iso:country":"US",
    "sg:address":"5615 High Point Dr",
    "sg:city":"Irving",
    "sg:classifiers":[
        {
            "category":"Local Transit",
            "type":"Transportation"
        }
    ],
    "sg:phone":"+1 972 751 4100",
    "sg:postcode":"75038",
    "sg:province":"TX",
    "wof:name":"Verizon",
    "wof:placetype":"venue"
},
  "geometry": {"coordinates":[-96.971557,32.889289],"type":"Point"}
}