{
  "type": "Feature",
  "properties": {
    "iso:country":"US",
    "sg:address":"4260 Robertson Dr",
    "sg:city":"Dallas",
    "sg:classifiers":[
        {
            "category":"Shopping",
            "subcategory":"Clothing, Apparel, & Fashions",
            "type":"Retail Goods"
        }
    ],
    "sg:phone":"+1 972 225 8883",
    "sg:postcode":"75241",
    "sg:province":"TX",
    "sg:tags":[
        "item",
        "boutique"
    ],
    "wof:name":"Butterfly Boutique",
    "wof:placetype":"venue"
},
  "geometry": {"coordinates":[-96.7496,32.673816],"type":"Point"}
}