{
  "type": "Feature",
  "properties": {
    "iso:country":"US",
    "sg:address":"12808 FM 901",
    "sg:city":"Sadler",
    "sg:classifiers":[
        {
            "category":"Retail",
            "subcategory":"Animal Services",
            "type":"Services"
        }
    ],
    "sg:phone":"+1 903 564 7336",
    "sg:postcode":"76264",
    "sg:province":"TX",
    "wof:name":"Hedges Cactus Kennel",
    "wof:placetype":"venue"
},
  "geometry": {"coordinates":[-96.851095,33.730065],"type":"Point"}
}