{
  "type": "Feature",
  "properties": {
    "iso:country":"US",
    "sg:address":"110 Ave H",
    "sg:city":"Marble Falls",
    "sg:classifiers":[
        {
            "category":"Health Services",
            "subcategory":"Doctor",
            "type":"Services"
        }
    ],
    "sg:phone":"+1 830 798 8844",
    "sg:postcode":"78654",
    "sg:province":"TX",
    "sg:tags":[
        "dentist"
    ],
    "wof:name":"Robert C English DDS Inc",
    "wof:placetype":"venue"
},
  "geometry": {"coordinates":[-98.27737500000001,30.569575],"type":"Point"}
}