{
  "type": "Feature",
  "properties": {
    "iso:country":"US",
    "sg:address":"4545 S Riverside Dr",
    "sg:city":"Fort Worth",
    "sg:classifiers":[
        {
            "category":"Organizations",
            "subcategory":"Religious Organization",
            "type":"Services"
        }
    ],
    "sg:phone":"+1 817 536 6921",
    "sg:postcode":"76119",
    "sg:province":"TX",
    "sg:tags":[
        "church"
    ],
    "wof:name":"Rolling Hills Church Of God",
    "wof:placetype":"venue"
},
  "geometry": {"coordinates":[-97.30517999999999,32.699186],"type":"Point"}
}