{
  "type": "Feature",
  "properties": {
    "iso:country":"US",
    "sg:address":"4563 N O Connor Rd",
    "sg:city":"Irving",
    "sg:classifiers":[
        {
            "category":"Professional",
            "subcategory":"Art Services",
            "type":"Services"
        }
    ],
    "sg:phone":"+1 972 650 9151",
    "sg:postcode":"75062",
    "sg:province":"TX",
    "sg:tags":[
        "graphic",
        "designer"
    ],
    "wof:name":"Fine Line Graphics",
    "wof:placetype":"venue"
},
  "geometry": {"coordinates":[-96.950728,32.860834],"type":"Point"}
}