{
  "type": "Feature",
  "properties": {
    "iso:country":"US",
    "sg:address":"605 Valencia St",
    "sg:city":"Dallas",
    "sg:classifiers":[
        {
            "category":"Professional",
            "subcategory":"Business Services",
            "type":"Services"
        }
    ],
    "sg:phone":"+1 214 827 2094",
    "sg:postcode":"75223",
    "sg:province":"TX",
    "wof:name":"Maxwell Design",
    "wof:placetype":"venue"
},
  "geometry": {"coordinates":[-96.743977,32.802734],"type":"Point"}
}