{
  "type": "Feature",
  "properties": {
    "iso:country":"US",
    "sg:address":"7601 N Macarthur Blvd",
    "sg:city":"Irving",
    "sg:classifiers":[
        {
            "category":"Recreation",
            "type":"Entertainment"
        }
    ],
    "sg:phone":"+1 972 868 9996",
    "sg:postcode":"75063",
    "sg:province":"TX",
    "wof:name":"Bogart Texas LLC",
    "wof:placetype":"venue"
},
  "geometry": {"coordinates":[-96.958873,32.909759],"type":"Point"}
}