{
  "type": "Feature",
  "properties": {
    "iso:country":"US",
    "sg:address":"5265 Shelby Rd",
    "sg:city":"Fort Worth",
    "sg:classifiers":[
        {
            "category":"Building & Trades",
            "subcategory":"Construction",
            "type":"Services"
        }
    ],
    "sg:phone":"+1 817 561 2091",
    "sg:postcode":"76140",
    "sg:province":"TX",
    "sg:tags":[
        "contractor"
    ],
    "wof:name":"R L T Construction",
    "wof:placetype":"venue"
},
  "geometry": {"coordinates":[-97.24780699999999,32.610468],"type":"Point"}
}