{
  "type": "Feature",
  "properties": {
    "iso:country":"US",
    "sg:address":"2906 Dabney Dr",
    "sg:city":"Pasadena",
    "sg:classifiers":[
        {
            "category":"Education",
            "subcategory":"School",
            "type":"Public Place"
        }
    ],
    "sg:phone":"+1 713 948 4374",
    "sg:postcode":"77502",
    "sg:province":"TX",
    "sg:tags":[
        "athletic",
        "department",
        "district"
    ],
    "wof:name":"Athletic Department",
    "wof:placetype":"venue"
},
  "geometry": {"coordinates":[-95.18365900000001,29.668336],"type":"Point"}
}