{
  "type": "Feature",
  "properties": {
    "iso:country":"US",
    "sg:address":"17711 Clay Rd Ste A",
    "sg:city":"Houston",
    "sg:classifiers":[
        {
            "category":"Professional",
            "subcategory":"Employment Agencies",
            "type":"Services"
        }
    ],
    "sg:phone":"+1 281 560 3010",
    "sg:postcode":"77084",
    "sg:province":"TX",
    "wof:name":"Dwell Staffing",
    "wof:placetype":"venue"
},
  "geometry": {"coordinates":[-95.669049,29.831012],"type":"Point"}
}