{
  "type": "Feature",
  "properties": {
    "iso:country":"US",
    "sg:address":"115 Linda Ln",
    "sg:city":"Freeport",
    "sg:classifiers":[
        {
            "category":"Manufacturing",
            "subcategory":"Rubber & Plastics",
            "type":"Manufacturing & Wholesale Goods"
        }
    ],
    "sg:phone":"+1 979 239 1201",
    "sg:postcode":"77541",
    "sg:province":"TX",
    "sg:tags":[
        "grease",
        "seal"
    ],
    "sg:website":"www.johncrane.com",
    "wof:name":"John Crane Inc",
    "wof:placetype":"venue"
},
  "geometry": {"coordinates":[-95.327125,28.999001],"type":"Point"}
}