{
  "type": "Feature",
  "properties": {
    "iso:country":"US",
    "sg:address":"2211 Strand St",
    "sg:city":"Galveston",
    "sg:classifiers":[
        {
            "category":"Real Estate",
            "subcategory":"Real Estate Agent",
            "type":"Services"
        }
    ],
    "sg:phone":"+1 409 750 8402",
    "sg:postcode":"77550",
    "sg:province":"TX",
    "wof:name":"Centex Destination Properties",
    "wof:placetype":"venue"
},
  "geometry": {"coordinates":[-94.794254,29.307113],"type":"Point"}
}