{
  "type": "Feature",
  "properties": {
    "iso:country":"US",
    "sg:address":"11903 Haley Hollow",
    "sg:city":"Richmond",
    "sg:classifiers":[
        {
            "category":"Autos & Motor Vehicles",
            "subcategory":"Auto Supplies",
            "type":"Retail Goods"
        }
    ],
    "sg:phone":"+1 281 277 0721",
    "sg:postcode":"77469",
    "sg:province":"TX",
    "wof:name":"Car Care Cosmetics",
    "wof:placetype":"venue"
},
  "geometry": {"coordinates":[-95.68564600000001,29.644565],"type":"Point"}
}