{
  "type": "Feature",
  "properties": {
    "iso:country":"US",
    "sg:address":"2319 McKinney St",
    "sg:city":"Vernon",
    "sg:classifiers":[
        {
            "category":"Social Services",
            "type":"Services"
        }
    ],
    "sg:phone":"+1 940 552 2433",
    "sg:postcode":"76384",
    "sg:province":"TX",
    "wof:name":"Booker T Washington Safe Haven",
    "wof:placetype":"venue"
},
  "geometry": {"coordinates":[-99.291102,34.16007],"type":"Point"}
}