{
  "type": "Feature",
  "properties": {
    "iso:country":"US",
    "sg:address":"618 Country Ln",
    "sg:city":"Grand Prairie",
    "sg:classifiers":[
        {
            "category":"Professional",
            "type":"Services"
        }
    ],
    "sg:phone":"+1 972 264 6849",
    "sg:postcode":"75052",
    "sg:province":"TX",
    "wof:name":"Mrk Installation & Services",
    "wof:placetype":"venue"
},
  "geometry": {"coordinates":[-96.996011,32.691986],"type":"Point"}
}