{
  "type": "Feature",
  "properties": {
    "iso:country":"US",
    "sg:address":"1863 W Division St",
    "sg:city":"Arlington",
    "sg:classifiers":[
        {
            "category":"Professional",
            "subcategory":"Detective & Security Services",
            "type":"Services"
        }
    ],
    "sg:phone":"+1 817 261 6089",
    "sg:postcode":"76012",
    "sg:province":"TX",
    "sg:tags":[
        "system"
    ],
    "wof:name":"Commercial Residential Elect",
    "wof:placetype":"venue"
},
  "geometry": {"coordinates":[-97.136726,32.735936],"type":"Point"}
}