{
  "type": "Feature",
  "properties": {
    "iso:country":"US",
    "sg:address":"1512 Louise St",
    "sg:city":"Rosenberg",
    "sg:classifiers":[
        {
            "category":"Organizations",
            "subcategory":"Religious Organization",
            "type":"Services"
        }
    ],
    "sg:phone":"+1 281 341 1451",
    "sg:postcode":"77471",
    "sg:province":"TX",
    "sg:tags":[
        "church"
    ],
    "wof:name":"Trinity Lutheran Church",
    "wof:placetype":"venue"
},
  "geometry": {"coordinates":[-95.794045,29.552994],"type":"Point"}
}