{
  "type": "Feature",
  "properties": {
    "iso:country":"US",
    "sg:address":"44 Alabama Ave",
    "sg:city":"Victoria",
    "sg:classifiers":[
        {
            "category":"Shopping",
            "subcategory":"Used Merchandise",
            "type":"Retail Goods"
        }
    ],
    "sg:phone":"+1 361 578 6461",
    "sg:postcode":"77905",
    "sg:province":"TX",
    "sg:tags":[
        "antique"
    ],
    "wof:name":"Rainy Day Antiques",
    "wof:placetype":"venue"
},
  "geometry": {"coordinates":[-96.950356,28.712867],"type":"Point"}
}