{
  "type": "Feature",
  "properties": {
    "iso:country":"US",
    "sg:address":"712 E Newman St",
    "sg:city":"Cuero",
    "sg:classifiers":[
        {
            "category":"Farming",
            "subcategory":"Livestock Farm",
            "type":"Manufacturing & Wholesale Goods"
        }
    ],
    "sg:phone":"+1 361 275 3608",
    "sg:postcode":"77954",
    "sg:province":"TX",
    "sg:tags":[
        "beef",
        "feedlot",
        "cattle"
    ],
    "wof:name":"Bar Hl Ranch",
    "wof:placetype":"venue"
},
  "geometry": {"coordinates":[-97.287166,29.0846],"type":"Point"}
}