{
  "type": "Feature",
  "properties": {
    "iso:country":"US",
    "sg:address":"315 Douglas St",
    "sg:city":"Hereford",
    "sg:classifiers":[
        {
            "category":"Manufacturing",
            "subcategory":"Apparel",
            "type":"Manufacturing & Wholesale Goods"
        }
    ],
    "sg:phone":"+1 806 364 8785",
    "sg:postcode":"79045",
    "sg:province":"TX",
    "wof:name":"Texas Threads",
    "wof:placetype":"venue"
},
  "geometry": {"coordinates":[-102.41578699999999,34.832797],"type":"Point"}
}