{
  "type": "Feature",
  "properties": {
    "iso:country":"US",
    "sg:address":"16734 FM 2964",
    "sg:city":"Whitehouse",
    "sg:classifiers":[
        {
            "category":"Building & Trades",
            "subcategory":"Construction",
            "type":"Services"
        }
    ],
    "sg:phone":"+1 903 530 4475",
    "sg:postcode":"75791",
    "sg:province":"TX",
    "sg:tags":[
        "interior"
    ],
    "wof:name":"Benco Interior Construction",
    "wof:placetype":"venue"
},
  "geometry": {"coordinates":[-95.250417,32.235081],"type":"Point"}
}