{
  "type": "Feature",
  "properties": {
    "iso:country":"US",
    "sg:address":"1505 Luna Rd",
    "sg:city":"Carrollton",
    "sg:classifiers":[
        {
            "category":"Professional",
            "subcategory":"Management & Consulting",
            "type":"Services"
        }
    ],
    "sg:phone":"+1 972 242 0059",
    "sg:postcode":"75006",
    "sg:province":"TX",
    "wof:name":"Area Financial Services",
    "wof:placetype":"venue"
},
  "geometry": {"coordinates":[-96.92527,32.945127],"type":"Point"}
}