{
  "type": "Feature",
  "properties": {
    "iso:country":"US",
    "sg:address":"3611 Clearview Dr",
    "sg:city":"Corinth",
    "sg:classifiers":[
        {
            "category":"Shopping",
            "subcategory":"Used Merchandise",
            "type":"Retail Goods"
        }
    ],
    "sg:phone":"+1 940 497 2100",
    "sg:postcode":"76210",
    "sg:province":"TX",
    "sg:tags":[
        "antique"
    ],
    "wof:name":"Jam She",
    "wof:placetype":"venue"
},
  "geometry": {"coordinates":[-97.051295,33.135022],"type":"Point"}
}