{
  "type": "Feature",
  "properties": {
    "iso:country":"US",
    "sg:address":"15825 Quorum Ste 2106",
    "sg:city":"Addison",
    "sg:classifiers":[
        {
            "category":"Professional",
            "subcategory":"Computer Services",
            "type":"Services"
        }
    ],
    "sg:phone":"+1 682 325 9569",
    "sg:postcode":"75001",
    "sg:province":"TX",
    "sg:tags":[
        "dvd",
        "slideshow",
        "photo-slideshow",
        "dvd-photo-slideshow"
    ],
    "sg:website":"http://3boost.com",
    "wof:name":"3Boost",
    "wof:placetype":"venue"
},
  "geometry": {"coordinates":[-96.825857,32.964152],"type":"Point"}
}