{
  "type": "Feature",
  "properties": {
    "iso:country":"US",
    "sg:address":"5124 la Vista Ct",
    "sg:city":"Granbury",
    "sg:classifiers":[
        {
            "category":"Retail",
            "subcategory":"Laundry & Dry Cleaning",
            "type":"Services"
        }
    ],
    "sg:phone":"+1 817 326 1168",
    "sg:postcode":"76049",
    "sg:province":"TX",
    "sg:tags":[
        "cleaner",
        "rug",
        "carpet"
    ],
    "wof:name":"Hurriclean Carpet Care, Inc.",
    "wof:placetype":"venue"
},
  "geometry": {"coordinates":[-97.695165,32.426973],"type":"Point"}
}