{
  "type": "Feature",
  "properties": {
    "iso:country":"US",
    "sg:address":"3506 Walden Dr",
    "sg:city":"Pearland",
    "sg:classifiers":[
        {
            "category":"Wholesale",
            "subcategory":"Medical Equipment & Supplies",
            "type":"Manufacturing & Wholesale Goods"
        }
    ],
    "sg:phone":"+1 281 412 9103",
    "sg:postcode":"77584",
    "sg:province":"TX",
    "wof:name":"1st General Medical Supplies I",
    "wof:placetype":"venue"
},
  "geometry": {"coordinates":[-95.364525,29.573556],"type":"Point"}
}