{
  "type": "Feature",
  "properties": {
    "iso:country":"US",
    "sg:address":"31004 I- 10 W",
    "sg:city":"Boerne",
    "sg:classifiers":[
        {
            "category":"Recreation",
            "type":"Entertainment"
        }
    ],
    "sg:phone":"+1 830 249 5515",
    "sg:postcode":"78006",
    "sg:province":"TX",
    "sg:tags":[
        "paint",
        "ball",
        "sport"
    ],
    "wof:name":"Boerne Paintball",
    "wof:placetype":"venue"
},
  "geometry": {"coordinates":[-98.697013,29.746816],"type":"Point"}
}