{
  "type": "Feature",
  "properties": {
    "iso:country":"US",
    "sg:address":"3848 N 9th St",
    "sg:city":"Abilene",
    "sg:classifiers":[
        {
            "category":"Professional",
            "subcategory":"Art Services",
            "type":"Services"
        }
    ],
    "sg:phone":"+1 325 675 0935",
    "sg:postcode":"79603",
    "sg:province":"TX",
    "sg:tags":[
        "commercial",
        "photography",
        "design"
    ],
    "wof:name":"Miller Tome Photography",
    "wof:placetype":"venue"
},
  "geometry": {"coordinates":[-99.77323699999999,32.460138],"type":"Point"}
}