{
  "type": "Feature",
  "properties": {
    "iso:country":"US",
    "sg:address":"305 N May St",
    "sg:city":"Madisonville",
    "sg:classifiers":[
        {
            "category":"Insurance",
            "subcategory":"Insurance Agent",
            "type":"Services"
        },
        {
            "category":"Insurance",
            "subcategory":"Hazard Insurance",
            "type":"Services"
        }
    ],
    "sg:phone":"+1 877 331 8260",
    "sg:postcode":"77864",
    "sg:province":"TX",
    "sg:tags":[
        "auto"
    ],
    "wof:name":"State Farm",
    "wof:placetype":"venue"
},
  "geometry": {"coordinates":[-95.91227000000001,30.95159],"type":"Point"}
}