{
  "type": "Feature",
  "properties": {
    "iso:country":"US",
    "sg:address":"1110 Ave H E",
    "sg:city":"Arlington",
    "sg:phone":"+1 817 640 7930",
    "sg:postcode":"76011",
    "sg:province":"TX",
    "sg:tags":[
        "food",
        "equipment",
        "processing"
    ],
    "wof:name":"Winberg & Co",
    "wof:placetype":"venue"
},
  "geometry": {"coordinates":[-97.04588699999999,32.762188],"type":"Point"}
}