{
  "type": "Feature",
  "properties": {
    "iso:country":"US",
    "sg:address":"3675 South Loop W",
    "sg:city":"Houston",
    "sg:classifiers":[
        {
            "category":"Travel",
            "subcategory":"Hotels & Motels",
            "type":"Entertainment"
        }
    ],
    "sg:phone":"+1 713 661 7200",
    "sg:postcode":"77025",
    "sg:province":"TX",
    "sg:website":"www.raintreeinn.net",
    "wof:name":"Raintree Inn & Suites",
    "wof:placetype":"venue"
},
  "geometry": {"coordinates":[-95.43489,29.678635],"type":"Point"}
}