{
  "type": "Feature",
  "properties": {
    "iso:country":"US",
    "sg:address":"819 W 11th St",
    "sg:city":"Austin",
    "sg:classifiers":[
        {
            "category":"Professional",
            "subcategory":"Lawyer & Legal Services",
            "type":"Services"
        }
    ],
    "sg:phone":"+1 512 499 0793",
    "sg:postcode":"78701",
    "sg:province":"TX",
    "wof:name":"Barton Hugh M Atty",
    "wof:placetype":"venue"
},
  "geometry": {"coordinates":[-97.750057,30.27514],"type":"Point"}
}