{
  "type": "Feature",
  "properties": {
    "iso:country":"US",
    "sg:address":"5710 Johnson Ln",
    "sg:city":"Dallas",
    "sg:classifiers":[
        {
            "category":"Wholesale",
            "subcategory":"Hardware",
            "type":"Manufacturing & Wholesale Goods"
        }
    ],
    "sg:phone":"+1 972 387 3339",
    "sg:postcode":"75241",
    "sg:province":"TX",
    "sg:tags":[
        "water",
        "mfg",
        "waste",
        "purification"
    ],
    "wof:name":"Hydronics Inc",
    "wof:placetype":"venue"
},
  "geometry": {"coordinates":[-96.774207,32.67847],"type":"Point"}
}