{
  "type": "Feature",
  "properties": {
    "iso:country":"US",
    "sg:address":"1121 Rising Star Ct",
    "sg:city":"Aledo",
    "sg:classifiers":[
        {
            "category":"Professional",
            "subcategory":"Printing & Photocopies",
            "type":"Services"
        }
    ],
    "sg:phone":"+1 817 441 6009",
    "sg:postcode":"76008",
    "sg:province":"TX",
    "sg:tags":[
        "engraving"
    ],
    "wof:name":"Nsi Gunworks & Engraving",
    "wof:placetype":"venue"
},
  "geometry": {"coordinates":[-97.62539599999999,32.716131],"type":"Point"}
}