{
  "type": "Feature",
  "properties": {
    "iso:country":"US",
    "sg:address":"202 E Main St",
    "sg:city":"Port Lavaca",
    "sg:classifiers":[
        {
            "category":"Recreation",
            "type":"Entertainment"
        }
    ],
    "sg:phone":"+1 361 552 7170",
    "sg:postcode":"77979",
    "sg:province":"TX",
    "sg:tags":[
        "center"
    ],
    "wof:name":"YMCA Teen Ctr",
    "wof:placetype":"venue"
},
  "geometry": {"coordinates":[-96.624717,28.61583],"type":"Point"}
}