{
  "type": "Feature",
  "properties": {
    "iso:country":"US",
    "sg:address":"8448 State Hwy 6",
    "sg:city":"Waco",
    "sg:classifiers":[
        {
            "category":"Retail",
            "subcategory":"Auto Repair",
            "type":"Services"
        }
    ],
    "sg:phone":"+1 254 848 9166",
    "sg:postcode":"76712",
    "sg:province":"TX",
    "sg:tags":[
        "truck"
    ],
    "wof:name":"Moon's Mechanical Svc",
    "wof:placetype":"venue"
},
  "geometry": {"coordinates":[-97.300335,31.578859],"type":"Point"}
}