{
  "type": "Feature",
  "properties": {
    "iso:country":"US",
    "sg:address":"117 W Texas St",
    "sg:city":"Marfa",
    "sg:classifiers":[
        {
            "category":"Farming",
            "subcategory":"Livestock Farm",
            "type":"Manufacturing & Wholesale Goods"
        }
    ],
    "sg:phone":"+1 432 358 4472",
    "sg:postcode":"79843",
    "sg:province":"TX",
    "sg:tags":[
        "ranch"
    ],
    "wof:name":"Hammond Ranch",
    "wof:placetype":"venue"
},
  "geometry": {"coordinates":[-104.02157,30.312041],"type":"Point"}
}