{
  "type": "Feature",
  "properties": {
    "iso:country":"US",
    "sg:address":"807 Keller Pkwy",
    "sg:city":"Keller",
    "sg:classifiers":[
        {
            "category":"Restaurant",
            "type":"Food & Drink"
        }
    ],
    "sg:phone":"+1 817 355 8888",
    "sg:postcode":"76248",
    "sg:province":"TX",
    "sg:tags":[
        "eating"
    ],
    "wof:name":"Domino's Pizza",
    "wof:placetype":"venue"
},
  "geometry": {"coordinates":[-97.23574600000001,32.934434],"type":"Point"}
}