{
  "type": "Feature",
  "properties": {
    "iso:country":"US",
    "sg:address":"1214 Commercial Ave",
    "sg:city":"San Antonio",
    "sg:classifiers":[
        {
            "category":"Organizations",
            "subcategory":"Religious Organization",
            "type":"Services"
        }
    ],
    "sg:phone":"+1 210 927 3882",
    "sg:postcode":"78221",
    "sg:province":"TX",
    "sg:tags":[
        "church"
    ],
    "wof:name":"Commercial Church Of Christ",
    "wof:placetype":"venue"
},
  "geometry": {"coordinates":[-98.516836,29.370027],"type":"Point"}
}