{
  "type": "Feature",
  "properties": {
    "iso:country":"US",
    "sg:address":"213 E Heritage Dr",
    "sg:city":"Friendswood",
    "sg:classifiers":[
        {
            "category":"Health Services",
            "subcategory":"Nursing And Care Facility",
            "type":"Services"
        }
    ],
    "sg:phone":"+1 281 993 5129",
    "sg:postcode":"77546",
    "sg:province":"TX",
    "sg:tags":[
        "home",
        "skilled",
        "convalescent"
    ],
    "wof:name":"Friendswood Health Care Center",
    "wof:placetype":"venue"
},
  "geometry": {"coordinates":[-95.201622,29.534756],"type":"Point"}
}