{
  "type": "Feature",
  "properties": {
    "iso:country":"US",
    "sg:address":"402 30th St NE",
    "sg:city":"Paris",
    "sg:classifiers":[
        {
            "category":"Social Services",
            "subcategory":"Child Care",
            "type":"Services"
        }
    ],
    "sg:phone":"+1 903 784 4855",
    "sg:postcode":"75460",
    "sg:province":"TX",
    "wof:name":"Almost Home Child Care",
    "wof:placetype":"venue"
},
  "geometry": {"coordinates":[-95.52274800000001,33.665224],"type":"Point"}
}