{
  "type": "Feature",
  "properties": {
    "iso:country":"US",
    "sg:address":"3819 W Wisteria Cir",
    "sg:city":"Sugar Land",
    "sg:classifiers":[
        {
            "category":"Professional",
            "subcategory":"Management & Consulting",
            "type":"Services"
        }
    ],
    "sg:phone":"+1 281 265 2555",
    "sg:postcode":"77479",
    "sg:province":"TX",
    "sg:tags":[
        "business"
    ],
    "wof:name":"Martin D Clemmons",
    "wof:placetype":"venue"
},
  "geometry": {"coordinates":[-95.59383699999999,29.570936],"type":"Point"}
}