{
  "type": "Feature",
  "properties": {
    "iso:country":"US",
    "sg:address":"810 E Hattie St",
    "sg:city":"Fort Worth",
    "sg:classifiers":[
        {
            "category":"Retail",
            "subcategory":"Repair Shop",
            "type":"Services"
        }
    ],
    "sg:phone":"+1 817 348 8388",
    "sg:postcode":"76104",
    "sg:province":"TX",
    "sg:tags":[
        "bathtub",
        "sink",
        "refinishing"
    ],
    "wof:name":"Prestine Porcelain Refinishing",
    "wof:placetype":"venue"
},
  "geometry": {"coordinates":[-97.317832,32.737812],"type":"Point"}
}