{
  "type": "Feature",
  "properties": {
    "iso:country":"US",
    "sg:address":"3134 Old Spanish Trl",
    "sg:city":"Houston",
    "sg:classifiers":[
        {
            "category":"Autos & Motor Vehicles",
            "subcategory":"Boat Sales",
            "type":"Retail Goods"
        }
    ],
    "sg:phone":"+1 713 747 4300",
    "sg:postcode":"77054",
    "sg:province":"TX",
    "sg:tags":[
        "outboard"
    ],
    "wof:name":"Helton Boat Works Inc",
    "wof:placetype":"venue"
},
  "geometry": {"coordinates":[-95.37765899999999,29.70055],"type":"Point"}
}