{
  "type": "Feature",
  "properties": {
    "iso:country":"US",
    "sg:address":"710 Winifred Dr",
    "sg:city":"Garland",
    "sg:classifiers":[
        {
            "category":"Travel",
            "subcategory":"Travel Agent",
            "type":"Entertainment"
        }
    ],
    "sg:phone":"+1 972 278 2498",
    "sg:postcode":"75041",
    "sg:province":"TX",
    "sg:tags":[
        "agency"
    ],
    "wof:name":"Magic Carpet Travel",
    "wof:placetype":"venue"
},
  "geometry": {"coordinates":[-96.641936,32.875267],"type":"Point"}
}