{
  "type": "Feature",
  "properties": {
    "iso:country":"US",
    "sg:address":"2030 Rowlett Rd",
    "sg:city":"Garland",
    "sg:classifiers":[
        {
            "category":"Organizations",
            "subcategory":"Religious Organization",
            "type":"Services"
        }
    ],
    "sg:phone":"+1 972 303 0123",
    "sg:postcode":"75043",
    "sg:province":"TX",
    "wof:name":"Trinity Life Baptist Church",
    "wof:placetype":"venue"
},
  "geometry": {"coordinates":[-96.57687799999999,32.861438],"type":"Point"}
}