{
  "type": "Feature",
  "properties": {
    "iso:country":"US",
    "sg:address":"12012 Wickchester Ln",
    "sg:city":"Houston",
    "sg:classifiers":[
        {
            "category":"Professional",
            "subcategory":"Business Services",
            "type":"Services"
        }
    ],
    "sg:phone":"+1 281 497 1020",
    "sg:postcode":"77079",
    "sg:province":"TX",
    "wof:name":"Outsource Professionals",
    "wof:placetype":"venue"
},
  "geometry": {"coordinates":[-95.59954,29.788568],"type":"Point"}
}