{
  "type": "Feature",
  "properties": {
    "iso:country":"US",
    "sg:address":"823 Astaire Ave",
    "sg:city":"Duncanville",
    "sg:classifiers":[
        {
            "category":"Real Estate",
            "subcategory":"Real Estate Services",
            "type":"Services"
        },
        {
            "category":"Real Estate",
            "subcategory":"Real Estate Agent",
            "type":"Services"
        }
    ],
    "sg:phone":"+1 214 938 0327",
    "sg:postcode":"75137",
    "sg:province":"TX",
    "sg:tags":[
        "management"
    ],
    "wof:name":"Sparrow Enterprises",
    "wof:placetype":"venue"
},
  "geometry": {"coordinates":[-96.887961,32.641064],"type":"Point"}
}