{
  "type": "Feature",
  "properties": {
    "iso:country":"US",
    "sg:address":"750 Linda Ave",
    "sg:city":"El Paso",
    "sg:classifiers":[
        {
            "category":"Professional",
            "subcategory":"Advertising",
            "type":"Services"
        }
    ],
    "sg:phone":"+1 915 727 2804",
    "sg:postcode":"79922",
    "sg:province":"TX",
    "wof:name":"Logo Ideas",
    "wof:placetype":"venue"
},
  "geometry": {"coordinates":[-106.599448,31.838971],"type":"Point"}
}