{
  "type": "Feature",
  "properties": {
    "iso:country":"US",
    "sg:address":"8222 Airline Dr.",
    "sg:city":"Houston",
    "sg:classifiers":[
        {
            "category":"Restaurant",
            "type":"Food & Drink"
        }
    ],
    "sg:phone":"+1 281 931 0220",
    "sg:postcode":"77037",
    "sg:province":"TX",
    "sg:tags":[
        "barbeque"
    ],
    "wof:name":"Hungry Farmer BBQ",
    "wof:placetype":"venue"
},
  "geometry": {"coordinates":[-95.38709,29.879931],"type":"Point"}
}