{
  "type": "Feature",
  "properties": {
    "iso:country":"US",
    "sg:address":"1201 E Elmira St",
    "sg:city":"San Antonio",
    "sg:classifiers":[
        {
            "category":"Shopping",
            "type":"Retail Goods"
        }
    ],
    "sg:phone":"+1 210 299 1111",
    "sg:postcode":"78212",
    "sg:province":"TX",
    "sg:tags":[
        "candle"
    ],
    "wof:name":"Soular Therapy",
    "wof:placetype":"venue"
},
  "geometry": {"coordinates":[-98.48264,29.442858],"type":"Point"}
}