{
  "type": "Feature",
  "properties": {
    "iso:country":"US",
    "sg:address":"6625 Quail Ridge Dr",
    "sg:city":"Fort Worth",
    "sg:classifiers":[
        {
            "category":"Wholesale",
            "subcategory":"Electrical",
            "type":"Manufacturing & Wholesale Goods"
        }
    ],
    "sg:phone":"+1 817 281 7776",
    "sg:postcode":"76180",
    "sg:province":"TX",
    "sg:tags":[
        "electronic"
    ],
    "wof:name":"Maxim Integrated Products",
    "wof:placetype":"venue"
},
  "geometry": {"coordinates":[-97.23975299999999,32.834029],"type":"Point"}
}