{
  "type": "Feature",
  "properties": {
    "iso:country":"US",
    "sg:address":"4011 Chaparral Rd",
    "sg:city":"Big Spring",
    "sg:classifiers":[
        {
            "category":"Shopping",
            "subcategory":"Hobbies, Toys, & Games",
            "type":"Retail Goods"
        }
    ],
    "sg:phone":"+1 432 264 9976",
    "sg:postcode":"79720",
    "sg:province":"TX",
    "wof:name":"Wyrm Hole",
    "wof:placetype":"venue"
},
  "geometry": {"coordinates":[-101.456962,32.196452],"type":"Point"}
}