{
  "type": "Feature",
  "properties": {
    "iso:country":"US",
    "sg:address":"13717 North Mopac Expwy Ste #300",
    "sg:city":"Austin",
    "sg:classifiers":[
        {
            "category":"Restaurant",
            "type":"Food & Drink"
        }
    ],
    "sg:phone":"+1 512 694 2828",
    "sg:postcode":"78728",
    "sg:province":"TX",
    "sg:tags":[
        "pakistani",
        "indian"
    ],
    "wof:name":"Hyderabad House",
    "wof:placetype":"venue"
},
  "geometry": {"coordinates":[-97.69860799999999,30.438084],"type":"Point"}
}