{
  "type": "Feature",
  "properties": {
    "iso:country":"US",
    "sg:address":"1201 N Hobart St",
    "sg:city":"Pampa",
    "sg:classifiers":[
        {
            "category":"Shopping",
            "subcategory":"Stationery & Office Supplies",
            "type":"Retail Goods"
        }
    ],
    "sg:phone":"+1 806 669 2324",
    "sg:postcode":"79065",
    "sg:province":"TX",
    "wof:name":"Sav-On Ltd",
    "wof:placetype":"venue"
},
  "geometry": {"coordinates":[-100.97192,35.545666],"type":"Point"}
}