{
  "type": "Feature",
  "properties": {
    "iso:country":"US",
    "sg:address":"5102 Rapido Rd",
    "sg:city":"Houston",
    "sg:classifiers":[
        {
            "category":"Building & Trades",
            "subcategory":"Construction",
            "type":"Services"
        }
    ],
    "sg:phone":"+1 713 264 0675",
    "sg:postcode":"77033",
    "sg:province":"TX",
    "sg:tags":[
        "plastering",
        "contractor"
    ],
    "wof:name":"A C Plastering Specializing",
    "wof:placetype":"venue"
},
  "geometry": {"coordinates":[-95.339461,29.681799],"type":"Point"}
}