{
  "type": "Feature",
  "properties": {
    "iso:country":"US",
    "sg:address":"3530 Elk Cliff Pass Dr",
    "sg:city":"San Antonio",
    "sg:classifiers":[
        {
            "category":"Arts & Performance",
            "subcategory":"Theater",
            "type":"Entertainment"
        }
    ],
    "sg:phone":"+1 210 490 0280",
    "sg:postcode":"78247",
    "sg:province":"TX",
    "sg:tags":[
        "group"
    ],
    "wof:name":"Gladys Demoras",
    "wof:placetype":"venue"
},
  "geometry": {"coordinates":[-98.429014,29.592208],"type":"Point"}
}