{
  "type": "Feature",
  "properties": {
    "iso:country":"US",
    "sg:address":"106 Royal St",
    "sg:city":"Liberty",
    "sg:classifiers":[
        {
            "category":"Professional",
            "subcategory":"Computer Services",
            "type":"Services"
        }
    ],
    "sg:phone":"+1 936 336 1122",
    "sg:postcode":"77575",
    "sg:province":"TX",
    "sg:tags":[
        "repair",
        "design",
        "system",
        "network"
    ],
    "sg:website":"www.libertysys.com",
    "wof:name":"Liberty Systems",
    "wof:placetype":"venue"
},
  "geometry": {"coordinates":[-94.783075,30.069049],"type":"Point"}
}