{
  "type": "Feature",
  "properties": {
    "iso:country":"US",
    "sg:address":"301 S Key Ave",
    "sg:city":"Lampasas",
    "sg:classifiers":[
        {
            "category":"Professional",
            "subcategory":"Accounting & Tax Preparation",
            "type":"Services"
        }
    ],
    "sg:phone":"+1 512 556 6259",
    "sg:postcode":"76550",
    "sg:province":"TX",
    "sg:tags":[
        "accountant"
    ],
    "wof:name":"Freemon Shapard & Story",
    "wof:placetype":"venue"
},
  "geometry": {"coordinates":[-98.18279699999999,31.065489],"type":"Point"}
}