{
  "type": "Feature",
  "properties": {
    "iso:country":"US",
    "sg:address":"4101 W Spring Creek Pkwy",
    "sg:city":"Plano",
    "sg:phone":"+1 972 867 7070",
    "sg:postcode":"75024",
    "sg:province":"TX",
    "wof:name":"Balachandar, Gowri, Md - Lone Star Gastroenterology",
    "wof:placetype":"venue"
},
  "geometry": {"coordinates":[-96.773833,33.056353],"type":"Point"}
}