{
  "type": "Feature",
  "properties": {
    "iso:country":"US",
    "sg:address":"636 Melba St",
    "sg:city":"Dallas",
    "sg:classifiers":[
        {
            "category":"Retail",
            "subcategory":"Repair Shop",
            "type":"Services"
        }
    ],
    "sg:phone":"+1 214 948 3334",
    "sg:postcode":"75208",
    "sg:province":"TX",
    "sg:tags":[
        "lock",
        "locksmith"
    ],
    "wof:name":"Lucky Locks",
    "wof:placetype":"venue"
},
  "geometry": {"coordinates":[-96.833377,32.747156],"type":"Point"}
}