{
  "type": "Feature",
  "properties": {
    "iso:country":"US",
    "sg:address":"2500 Guerrero Dr",
    "sg:city":"Carrollton",
    "sg:classifiers":[
        {
            "category":"Professional",
            "subcategory":"Business Services",
            "type":"Services"
        }
    ],
    "sg:phone":"+1 972 245 0238",
    "sg:postcode":"75006",
    "sg:province":"TX",
    "wof:name":"Wardrobe Inc",
    "wof:placetype":"venue"
},
  "geometry": {"coordinates":[-96.88002299999999,32.984628],"type":"Point"}
}