{
  "type": "Feature",
  "properties": {
    "iso:country":"US",
    "sg:address":"2212 Shadydale Dr",
    "sg:city":"Arlington",
    "sg:classifiers":[
        {
            "category":"Professional",
            "type":"Services"
        }
    ],
    "sg:phone":"+1 817 314 0841",
    "sg:postcode":"76012",
    "sg:province":"TX",
    "wof:name":"Hotraude Comm",
    "wof:placetype":"venue"
},
  "geometry": {"coordinates":[-97.13514000000001,32.773336],"type":"Point"}
}