{
  "type": "Feature",
  "properties": {
    "iso:country":"US",
    "sg:address":"116 S Beckham Ave",
    "sg:city":"Tyler",
    "sg:classifiers":[
        {
            "category":"Professional",
            "subcategory":"Art Services",
            "type":"Services"
        }
    ],
    "sg:phone":"+1 903 597 7467",
    "sg:postcode":"75702",
    "sg:province":"TX",
    "sg:tags":[
        "artist"
    ],
    "sg:website":"www.etxe.com",
    "wof:name":"East Texas Engraving Co",
    "wof:placetype":"venue"
},
  "geometry": {"coordinates":[-95.29415299999999,32.350809],"type":"Point"}
}