{
  "type": "Feature",
  "properties": {
    "iso:country":"US",
    "sg:address":"8162 State Hwy 258",
    "sg:city":"Kamay",
    "sg:classifiers":[
        {
            "category":"Government",
            "subcategory":"Post Office",
            "type":"Public Place"
        }
    ],
    "sg:phone":"+1 940 438 2423",
    "sg:postcode":"76367",
    "sg:province":"TX",
    "wof:name":"US Post Office",
    "wof:placetype":"venue"
},
  "geometry": {"coordinates":[-98.807113,33.857768],"type":"Point"}
}