{
  "type": "Feature",
  "properties": {
    "iso:country":"US",
    "sg:address":"4907 Fern St",
    "sg:city":"Bellaire",
    "sg:classifiers":[
        {
            "category":"Professional",
            "subcategory":"Art Services",
            "type":"Services"
        }
    ],
    "sg:phone":"+1 713 666 8653",
    "sg:postcode":"77401",
    "sg:province":"TX",
    "sg:tags":[
        "commercial",
        "design"
    ],
    "wof:name":"Wrapped & Delivered",
    "wof:placetype":"venue"
},
  "geometry": {"coordinates":[-95.46570800000001,29.700593],"type":"Point"}
}