{
  "type": "Feature",
  "properties": {
    "iso:country":"US",
    "sg:address":"102 I-45 N",
    "sg:city":"Huntsville",
    "sg:classifiers":[
        {
            "category":"Restaurant",
            "type":"Food & Drink"
        }
    ],
    "sg:menulink":"http://www.allmenus.com/tx/huntsville/93994-bandera-grill/menu/",
    "sg:phone":"+1 936 291 3500",
    "sg:postcode":"77320",
    "sg:province":"TX",
    "sg:tags":[
        "american"
    ],
    "wof:name":"Bandera Grill",
    "wof:placetype":"venue"
},
  "geometry": {"coordinates":[-95.747739,30.859163],"type":"Point"}
}