{
  "type": "Feature",
  "properties": {
    "iso:country":"US",
    "sg:address":"181 Med Davis Rd",
    "sg:city":"Orange",
    "sg:classifiers":[
        {
            "category":"Communications",
            "type":"Services"
        }
    ],
    "sg:phone":"+1 409 745 4543",
    "sg:postcode":"77632",
    "sg:province":"TX",
    "sg:tags":[
        "communication"
    ],
    "wof:name":"S & C Communications",
    "wof:placetype":"venue"
},
  "geometry": {"coordinates":[-93.825204,30.118794],"type":"Point"}
}