{
  "type": "Feature",
  "properties": {
    "iso:country":"US",
    "sg:address":"4011 S Main St",
    "sg:city":"Stafford",
    "sg:classifiers":[
        {
            "category":"Restaurant",
            "type":"Food & Drink"
        }
    ],
    "sg:phone":"+1 281 499 9651",
    "sg:postcode":"77477",
    "sg:province":"TX",
    "sg:tags":[
        "eating"
    ],
    "wof:name":"Regal Ranch",
    "wof:placetype":"venue"
},
  "geometry": {"coordinates":[-95.573492,29.623114],"type":"Point"}
}