{
  "type": "Feature",
  "properties": {
    "iso:country":"US",
    "sg:address":"1000 S Esplanade St",
    "sg:city":"Cuero",
    "sg:classifiers":[
        {
            "category":"Restaurant",
            "type":"Food & Drink"
        }
    ],
    "sg:phone":"+1 361 275 9696",
    "sg:postcode":"77954",
    "sg:province":"TX",
    "sg:tags":[
        "mexican"
    ],
    "wof:name":"Maya Mexican Restaurant",
    "wof:placetype":"venue"
},
  "geometry": {"coordinates":[-97.296387,29.081432],"type":"Point"}
}