{
  "type": "Feature",
  "properties": {
    "iso:country":"US",
    "sg:address":"4120 34th St",
    "sg:city":"Lubbock",
    "sg:classifiers":[
        {
            "category":"Building & Trades",
            "subcategory":"Plumbing",
            "type":"Services"
        }
    ],
    "sg:phone":"+1 806 548 4822",
    "sg:postcode":"79410",
    "sg:province":"TX",
    "sg:tags":[
        "conditioning",
        "air",
        "system",
        "contractor"
    ],
    "wof:name":"Leinad Limited Heating & Air",
    "wof:placetype":"venue"
},
  "geometry": {"coordinates":[-101.901432,33.563338],"type":"Point"}
}