{
  "type": "Feature",
  "properties": {
    "iso:country":"US",
    "sg:address":"7441 Marvin D Love Fwy",
    "sg:city":"Dallas",
    "sg:classifiers":[
        {
            "category":"Shopping",
            "subcategory":"Stationery & Office Supplies",
            "type":"Retail Goods"
        }
    ],
    "sg:phone":"+1 972 296 4376",
    "sg:postcode":"75237",
    "sg:province":"TX",
    "sg:tags":[
        "equipment"
    ],
    "sg:website":"www.target.com",
    "wof:name":"On Target Supplies Inc",
    "wof:placetype":"venue"
},
  "geometry": {"coordinates":[-96.875401,32.657544],"type":"Point"}
}