{
  "type": "Feature",
  "properties": {
    "iso:country":"US",
    "sg:address":"5101 Gold Crest Ct",
    "sg:city":"Austin",
    "sg:classifiers":[
        {
            "category":"Wholesale",
            "subcategory":"Computers",
            "type":"Manufacturing & Wholesale Goods"
        }
    ],
    "sg:phone":"+1 512 418 9824",
    "sg:postcode":"78730",
    "sg:province":"TX",
    "wof:name":"Optin Stratagy",
    "wof:placetype":"venue"
},
  "geometry": {"coordinates":[-97.85090099999999,30.375342],"type":"Point"}
}