{
  "type": "Feature",
  "properties": {
    "iso:country":"US",
    "sg:address":"1011 Hardwood Ln",
    "sg:city":"College Station",
    "sg:classifiers":[
        {
            "category":"Utilities",
            "subcategory":"Telephone",
            "type":"Services"
        }
    ],
    "sg:phone":"+1 979 764 1984",
    "sg:postcode":"77840",
    "sg:province":"TX",
    "sg:tags":[
        "communications"
    ],
    "wof:name":"Poeco",
    "wof:placetype":"venue"
},
  "geometry": {"coordinates":[-96.310759,30.626777],"type":"Point"}
}