{
  "type": "Feature",
  "properties": {
    "iso:country":"US",
    "sg:address":"1880 S Main St",
    "sg:city":"Vidor",
    "sg:classifiers":[
        {
            "category":"Food & Beverages",
            "subcategory":"Liquor & Beverages",
            "type":"Retail Goods"
        }
    ],
    "sg:phone":"+1 409 768 1041",
    "sg:postcode":"77662",
    "sg:province":"TX",
    "sg:tags":[
        "alcoholic"
    ],
    "wof:name":"Johnny's Package Store",
    "wof:placetype":"venue"
},
  "geometry": {"coordinates":[-94.006927,30.104375],"type":"Point"}
}