{
  "type": "Feature",
  "properties": {
    "iso:country":"US",
    "sg:address":"7115 Woodrow Ave",
    "sg:city":"Austin",
    "sg:classifiers":[
        {
            "category":"Manufacturing",
            "subcategory":"Metals",
            "type":"Manufacturing & Wholesale Goods"
        },
        {
            "category":"Shopping",
            "subcategory":"Jewelry",
            "type":"Retail Goods"
        },
        {
            "category":"Manufacturing",
            "subcategory":"Jewelry",
            "type":"Manufacturing & Wholesale Goods"
        }
    ],
    "sg:phone":"+1 512 467 6131",
    "sg:postcode":"78757",
    "sg:province":"TX",
    "sg:tags":[
        "designer",
        "jewelers-wholesale",
        "watch",
        "metals-precious",
        "jeweler",
        "manufacturer"
    ],
    "sg:website":"www.rwilsonmfg.com",
    "wof:name":"Ricky Wilson Manufacturing",
    "wof:placetype":"venue"
},
  "geometry": {"coordinates":[-97.724912,30.342629],"type":"Point"}
}