{
  "type": "Feature",
  "properties": {
    "iso:country":"US",
    "sg:address":"10850 West Rd",
    "sg:city":"Houston",
    "sg:classifiers":[
        {
            "category":"Retail",
            "subcategory":"Laundry & Dry Cleaning",
            "type":"Services"
        }
    ],
    "sg:phone":"+1 281 477 6444",
    "sg:postcode":"77064",
    "sg:province":"TX",
    "sg:tags":[
        "cleaners"
    ],
    "wof:name":"Best Cleaner",
    "wof:placetype":"venue"
},
  "geometry": {"coordinates":[-95.579284,29.909697],"type":"Point"}
}