{
  "type": "Feature",
  "properties": {
    "iso:country":"US",
    "sg:address":"409 Cannon Dr",
    "sg:city":"Hurst",
    "sg:classifiers":[
        {
            "category":"Building & Trades",
            "subcategory":"Cleaning & Sanitation",
            "type":"Services"
        }
    ],
    "sg:phone":"+1 817 514 0320",
    "sg:postcode":"76054",
    "sg:province":"TX",
    "wof:name":"Bioclean",
    "wof:placetype":"venue"
},
  "geometry": {"coordinates":[-97.17559199999999,32.852714],"type":"Point"}
}