{
  "type": "Feature",
  "properties": {
    "iso:country":"US",
    "sg:address":"7111 Hillcroft St",
    "sg:city":"Houston",
    "sg:classifiers":[
        {
            "category":"Shopping",
            "type":"Retail Goods"
        }
    ],
    "sg:phone":"+1 713 272 9612",
    "sg:postcode":"77081",
    "sg:province":"TX",
    "sg:tags":[
        "merchandise"
    ],
    "wof:name":"Gonzalez Consuelo",
    "wof:placetype":"venue"
},
  "geometry": {"coordinates":[-95.492964,29.701921],"type":"Point"}
}