{
  "type": "Feature",
  "properties": {
    "iso:country":"US",
    "sg:address":"424 E Avenue E A",
    "sg:city":"Robstown",
    "sg:classifiers":[
        {
            "category":"Restaurant",
            "type":"Food & Drink"
        }
    ],
    "sg:phone":"+1 361 387 3132",
    "sg:postcode":"78380",
    "sg:province":"TX",
    "sg:tags":[
        "mexican"
    ],
    "wof:name":"Taqueria Guadalajara 2",
    "wof:placetype":"venue"
},
  "geometry": {"coordinates":[-97.66385200000001,27.793464],"type":"Point"}
}