{
  "type": "Feature",
  "properties": {
    "iso:country":"US",
    "sg:address":"804 6th St",
    "sg:city":"Marble Falls",
    "sg:classifiers":[
        {
            "category":"Restaurant",
            "type":"Food & Drink"
        }
    ],
    "sg:phone":"+1 830 693 7719",
    "sg:postcode":"78654",
    "sg:province":"TX",
    "sg:tags":[
        "eating"
    ],
    "wof:name":"Cater To You",
    "wof:placetype":"venue"
},
  "geometry": {"coordinates":[-98.27551800000001,30.574639],"type":"Point"}
}