{
  "type": "Feature",
  "properties": {
    "iso:country":"US",
    "sg:address":"9120 FM 1518",
    "sg:city":"Schertz",
    "sg:classifiers":[
        {
            "category":"Professional",
            "type":"Services"
        }
    ],
    "sg:phone":"+1 210 656 3540",
    "sg:postcode":"78154",
    "sg:province":"TX",
    "wof:name":"Dahle M Ichael",
    "wof:placetype":"venue"
},
  "geometry": {"coordinates":[-98.245723,29.522102],"type":"Point"}
}