{
  "type": "Feature",
  "properties": {
    "iso:country":"US",
    "sg:address":"1995 Neches St",
    "sg:city":"Beaumont",
    "sg:classifiers":[
        {
            "category":"Wholesale",
            "subcategory":"Machinery & Supplies",
            "type":"Manufacturing & Wholesale Goods"
        }
    ],
    "sg:phone":"+1 409 838 3040",
    "sg:postcode":"77701",
    "sg:province":"TX",
    "sg:tags":[
        "janitor"
    ],
    "wof:name":"J R Parsley Co Inc",
    "wof:placetype":"venue"
},
  "geometry": {"coordinates":[-94.094919,30.069603],"type":"Point"}
}