{
  "type": "Feature",
  "properties": {
    "iso:country":"US",
    "sg:address":"6932 Church Park Dr",
    "sg:city":"Fort Worth",
    "sg:classifiers":[
        {
            "category":"Autos & Motor Vehicles",
            "subcategory":"Automobile Sales",
            "type":"Retail Goods"
        }
    ],
    "sg:phone":"+1 817 920 0013",
    "sg:postcode":"76133",
    "sg:province":"TX",
    "sg:tags":[
        "used"
    ],
    "wof:name":"Curtis Sales Assoc",
    "wof:placetype":"venue"
},
  "geometry": {"coordinates":[-97.381601,32.642749],"type":"Point"}
}