{
  "type": "Feature",
  "properties": {
    "iso:country":"US",
    "sg:address":"5700 Median Way",
    "sg:city":"Arlington",
    "sg:classifiers":[
        {
            "category":"Real Estate",
            "subcategory":"Real Estate Operator",
            "type":"Services"
        }
    ],
    "sg:phone":"+1 866 404 6642",
    "sg:postcode":"76017",
    "sg:province":"TX",
    "sg:tags":[
        "building",
        "apartment"
    ],
    "sg:website":"http://local.ingenio.com/Listings/Details.aspx?NUM=a%3a10238145%3a13%3a4859924%3a14%3a0%3a7",
    "wof:name":"Chesterfield Apartments",
    "wof:placetype":"venue"
},
  "geometry": {"coordinates":[-97.19422900000001,32.656609],"type":"Point"}
}