{
  "type": "Feature",
  "properties": {
    "iso:country":"US",
    "sg:address":"104 N Ave E",
    "sg:city":"Olney",
    "sg:classifiers":[
        {
            "category":"Utilities",
            "subcategory":"Telephone",
            "type":"Services"
        }
    ],
    "sg:phone":"+1 940 564 8050",
    "sg:postcode":"76374",
    "sg:province":"TX",
    "sg:tags":[
        "communications"
    ],
    "wof:name":"Brazos Internet",
    "wof:placetype":"venue"
},
  "geometry": {"coordinates":[-98.756016,33.370569],"type":"Point"}
}