{
  "type": "Feature",
  "properties": {
    "iso:country":"US",
    "sg:address":"2155 FM 1960 W",
    "sg:city":"Houston",
    "sg:classifiers":[
        {
            "category":"Organizations",
            "subcategory":"Non-profit Organization",
            "type":"Services"
        },
        {
            "category":"Health Services",
            "subcategory":"Clinic",
            "type":"Services"
        }
    ],
    "sg:phone":"+1 281 444 5115",
    "sg:postcode":"77090",
    "sg:province":"TX",
    "sg:tags":[
        "breastfeeding",
        "information",
        "supply"
    ],
    "sg:website":"www.breastfeedingservices.com",
    "wof:name":"Breastfeeding Consultants Svcs",
    "wof:placetype":"venue"
},
  "geometry": {"coordinates":[-95.459081,30.009601],"type":"Point"}
}