{
  "type": "Feature",
  "properties": {
    "iso:country":"US",
    "sg:address":"2319 Okane St",
    "sg:city":"Laredo",
    "sg:classifiers":[
        {
            "category":"Professional",
            "subcategory":"Management & Consulting",
            "type":"Services"
        }
    ],
    "sg:phone":"+1 956 727 1975",
    "sg:postcode":"78043",
    "sg:province":"TX",
    "wof:name":"Knc Management Co LLC",
    "wof:placetype":"venue"
},
  "geometry": {"coordinates":[-99.472281,27.517589],"type":"Point"}
}