{
  "type": "Feature",
  "properties": {
    "iso:country":"US",
    "sg:address":"5701 Crowley Rd",
    "sg:city":"Fort Worth",
    "sg:classifiers":[
        {
            "category":"Recreation",
            "type":"Entertainment"
        }
    ],
    "sg:phone":"+1 817 568 2112",
    "sg:postcode":"76134",
    "sg:province":"TX",
    "sg:tags":[
        "bingo",
        "game"
    ],
    "wof:name":"Monte Carlo Bingo",
    "wof:placetype":"venue"
},
  "geometry": {"coordinates":[-97.348354,32.662658],"type":"Point"}
}