{
  "type": "Feature",
  "properties": {
    "iso:country":"US",
    "sg:address":"2627 Magnolia Ave",
    "sg:city":"Port Neches",
    "sg:classifiers":[
        {
            "category":"Home & Garden",
            "subcategory":"Building Materials",
            "type":"Retail Goods"
        }
    ],
    "sg:phone":"+1 409 735 9479",
    "sg:postcode":"77651",
    "sg:province":"TX",
    "sg:tags":[
        "door"
    ],
    "wof:name":"Beaty Overhead Door Inc",
    "wof:placetype":"venue"
},
  "geometry": {"coordinates":[-93.97885100000001,29.988796],"type":"Point"}
}