{
  "type": "Feature",
  "properties": {
    "iso:country":"US",
    "sg:address":"1431 Park Pl",
    "sg:city":"Southlake",
    "sg:classifiers":[
        {
            "category":"Restaurant",
            "type":"Food & Drink"
        }
    ],
    "sg:menulink":"http://www.allmenus.com/tx/northeast-tarrant/9960-brio-italian-grille/menu/",
    "sg:phone":"+1 817 310 3136",
    "sg:postcode":"76092",
    "sg:province":"TX",
    "sg:tags":[
        "italian"
    ],
    "wof:name":"Brio Italian Grille",
    "wof:placetype":"venue"
},
  "geometry": {"coordinates":[-97.17617300000001,32.935736],"type":"Point"}
}