{
  "type": "Feature",
  "properties": {
    "iso:country":"US",
    "sg:address":"5857 N Mesa St Ste 10",
    "sg:city":"El Paso",
    "sg:classifiers":[
        {
            "category":"Shopping",
            "subcategory":"Mobile Phones",
            "type":"Retail Goods"
        }
    ],
    "sg:phone":"+1 915 834 4400",
    "sg:postcode":"79912",
    "sg:province":"TX",
    "sg:website":"www.t-mobile.com",
    "wof:name":"T Mobile",
    "wof:placetype":"venue"
},
  "geometry": {"coordinates":[-106.527,31.8277],"type":"Point"}
}