{
  "type": "Feature",
  "properties": {
    "iso:country":"US",
    "sg:address":"4008 Vista Rd Ste A201",
    "sg:city":"Pasadena",
    "sg:classifiers":[
        {
            "category":"Professional",
            "subcategory":"Lawyer & Legal Services",
            "type":"Services"
        }
    ],
    "sg:phone":"+1 713 944 6337",
    "sg:postcode":"77504",
    "sg:province":"TX",
    "wof:name":"Curtis Rosalind Atty",
    "wof:placetype":"venue"
},
  "geometry": {"coordinates":[-95.183601,29.658501],"type":"Point"}
}