{
  "type": "Feature",
  "properties": {
    "iso:country":"US",
    "sg:address":"85 Rainey St",
    "sg:city":"Austin",
    "sg:classifiers":[
        {
            "category":"Restaurant",
            "type":"Food & Drink"
        },
        {
            "category":"Food Court",
            "type":"Food & Drink"
        }
    ],
    "sg:phone":"+1 512 474 2776",
    "sg:postcode":"78701",
    "sg:province":"TX",
    "sg:tags":[
        "mexican",
        "stand"
    ],
    "wof:name":"El Naranjo",
    "wof:placetype":"venue"
},
  "geometry": {"coordinates":[-97.73818300000001,30.25952],"type":"Point"}
}