{
  "type": "Feature",
  "properties": {
    "iso:country":"US",
    "sg:address":"1600 Speight Ave",
    "sg:city":"Waco",
    "sg:classifiers":[
        {
            "category":"Restaurant",
            "type":"Food & Drink"
        }
    ],
    "sg:phone":"+1 254 752 7591",
    "sg:postcode":"76706",
    "sg:province":"TX",
    "sg:tags":[
        "barbecue"
    ],
    "wof:name":"Vitek's Bar-B-Q",
    "wof:placetype":"venue"
},
  "geometry": {"coordinates":[-97.12893200000001,31.536185],"type":"Point"}
}