{
  "type": "Feature",
  "properties": {
    "iso:country":"US",
    "sg:address":"2409 Inglewood Dr",
    "sg:city":"Wichita Falls",
    "sg:classifiers":[
        {
            "category":"Building & Trades",
            "subcategory":"Construction",
            "type":"Services"
        }
    ],
    "sg:phone":"+1 940 723 0461",
    "sg:postcode":"76301",
    "sg:province":"TX",
    "sg:tags":[
        "house"
    ],
    "wof:name":"Bills Handyman Service",
    "wof:placetype":"venue"
},
  "geometry": {"coordinates":[-98.517732,33.913666],"type":"Point"}
}