{
  "type": "Feature",
  "properties": {
    "iso:country":"US",
    "sg:address":"17726 Red Wolf Dr",
    "sg:city":"Houston",
    "sg:classifiers":[
        {
            "category":"Building & Trades",
            "subcategory":"Construction",
            "type":"Services"
        }
    ],
    "sg:phone":"+1 281 550 3742",
    "sg:postcode":"77084",
    "sg:province":"TX",
    "sg:tags":[
        "contractor"
    ],
    "wof:name":"Edwards Drywall",
    "wof:placetype":"venue"
},
  "geometry": {"coordinates":[-95.67907200000001,29.872991],"type":"Point"}
}