{
  "type": "Feature",
  "properties": {
    "iso:country":"US",
    "sg:address":"1010 S Staples St",
    "sg:city":"Corpus Christi",
    "sg:classifiers":[
        {
            "category":"Autos & Motor Vehicles",
            "subcategory":"Automobile Sales",
            "type":"Retail Goods"
        }
    ],
    "sg:phone":"+1 361 882 3541",
    "sg:postcode":"78404",
    "sg:province":"TX",
    "sg:tags":[
        "car",
        "used",
        "dealer"
    ],
    "wof:name":"Keetch Motors Inc",
    "wof:placetype":"venue"
},
  "geometry": {"coordinates":[-97.401698,27.78161],"type":"Point"}
}