{
  "type": "Feature",
  "properties": {
    "iso:country":"US",
    "sg:address":"14811 Medusa",
    "sg:city":"Universal City",
    "sg:classifiers":[
        {
            "category":"Manufacturing",
            "subcategory":"Tools & Machinery",
            "type":"Manufacturing & Wholesale Goods"
        }
    ],
    "sg:phone":"+1 210 658 8678",
    "sg:postcode":"78154",
    "sg:province":"TX",
    "sg:tags":[
        "measuring",
        "instrument",
        "electrical",
        "mfg"
    ],
    "wof:name":"Teradyne Inc",
    "wof:placetype":"venue"
},
  "geometry": {"coordinates":[-98.319154,29.574322],"type":"Point"}
}