{
  "type": "Feature",
  "properties": {
    "iso:country":"US",
    "sg:address":"3458 Gulf Fwy",
    "sg:city":"Dickinson",
    "sg:classifiers":[
        {
            "category":"Retail",
            "subcategory":"Veterinary Services",
            "type":"Services"
        }
    ],
    "sg:phone":"+1 281 337 3635",
    "sg:postcode":"77539",
    "sg:province":"TX",
    "sg:tags":[
        "veterinarian",
        "merchandise",
        "animal"
    ],
    "wof:name":"Animal Care Clinic Dickinson",
    "wof:placetype":"venue"
},
  "geometry": {"coordinates":[-95.07818,29.449876],"type":"Point"}
}