{
  "type": "Feature",
  "properties": {
    "iso:country":"US",
    "sg:address":"2206 S 3rd St",
    "sg:city":"Austin",
    "sg:classifiers":[
        {
            "category":"Shopping",
            "subcategory":"Gifts & Souvenirs",
            "type":"Retail Goods"
        }
    ],
    "sg:phone":"+1 512 917 1879",
    "sg:postcode":"78704",
    "sg:province":"TX",
    "sg:tags":[
        "shop",
        "beauty"
    ],
    "wof:name":"Above Average Fun Creations",
    "wof:placetype":"venue"
},
  "geometry": {"coordinates":[-97.76129400000001,30.24429],"type":"Point"}
}