{
  "type": "Feature",
  "properties": {
    "iso:country":"US",
    "sg:address":"208 W Pasadena Blvd",
    "sg:city":"Deer Park",
    "sg:classifiers":[
        {
            "category":"Building & Trades",
            "subcategory":"Pest Control",
            "type":"Services"
        }
    ],
    "sg:phone":"+1 281 479 1352",
    "sg:postcode":"77536",
    "sg:province":"TX",
    "wof:name":"A-Tex Exterminating",
    "wof:placetype":"venue"
},
  "geometry": {"coordinates":[-95.12452399999999,29.679139],"type":"Point"}
}