{
  "type": "Feature",
  "properties": {
    "iso:country":"US",
    "sg:address":"305 Lakewood Dr",
    "sg:city":"Waxahachie",
    "sg:classifiers":[
        {
            "category":"Wholesale",
            "subcategory":"Durable Goods & Equipment",
            "type":"Manufacturing & Wholesale Goods"
        }
    ],
    "sg:phone":"+1 903 872 1436",
    "sg:postcode":"75165",
    "sg:province":"TX",
    "sg:tags":[
        "fire",
        "extinguisher"
    ],
    "wof:name":"Total & Fire Safety",
    "wof:placetype":"venue"
},
  "geometry": {"coordinates":[-96.83647499999999,32.339567],"type":"Point"}
}