{
  "type": "Feature",
  "properties": {
    "iso:country":"US",
    "sg:address":"848 Summit Pointe",
    "sg:city":"Lewisville",
    "sg:classifiers":[
        {
            "category":"Banks & Credit Unions",
            "subcategory":"Investment Brokerage",
            "type":"Services"
        }
    ],
    "sg:phone":"+1 972 434 3645",
    "sg:postcode":"75077",
    "sg:province":"TX",
    "sg:tags":[
        "security"
    ],
    "wof:name":"Edward Jones 27532",
    "wof:placetype":"venue"
},
  "geometry": {"coordinates":[-97.020313,33.05339],"type":"Point"}
}