{
  "type": "Feature",
  "properties": {
    "iso:country":"US",
    "sg:address":"520 Oleander St",
    "sg:city":"Lake Jackson",
    "sg:classifiers":[
        {
            "category":"Autos & Motor Vehicles",
            "subcategory":"Automobile Sales",
            "type":"Retail Goods"
        }
    ],
    "sg:phone":"+1 979 297 2334",
    "sg:postcode":"77566",
    "sg:province":"TX",
    "wof:name":"Klear Autos",
    "wof:placetype":"venue"
},
  "geometry": {"coordinates":[-95.446997,29.024563],"type":"Point"}
}