{
  "type": "Feature",
  "properties": {
    "iso:country":"US",
    "sg:address":"407 W Rochelle Rd",
    "sg:city":"Irving",
    "sg:classifiers":[
        {
            "category":"Personal",
            "subcategory":"Beauty Salon",
            "type":"Services"
        }
    ],
    "sg:phone":"+1 972 594 7833",
    "sg:postcode":"75062",
    "sg:province":"TX",
    "wof:name":"Jeanet's Beauty Salon",
    "wof:placetype":"venue"
},
  "geometry": {"coordinates":[-96.951217,32.844393],"type":"Point"}
}