{
  "type": "Feature",
  "properties": {
    "iso:country":"US",
    "sg:address":"205 Dee Ln",
    "sg:city":"Arlington",
    "sg:classifiers":[
        {
            "category":"Professional",
            "subcategory":"Computer Services",
            "type":"Services"
        }
    ],
    "sg:phone":"+1 817 860 9040",
    "sg:postcode":"76011",
    "sg:province":"TX",
    "sg:tags":[
        "datum"
    ],
    "wof:name":"Webtimedesign Inc",
    "wof:placetype":"venue"
},
  "geometry": {"coordinates":[-97.107437,32.757061],"type":"Point"}
}