{
  "type": "Feature",
  "properties": {
    "iso:country":"US",
    "sg:address":"518 N New Rd",
    "sg:city":"Waco",
    "sg:classifiers":[
        {
            "category":"Shopping",
            "type":"Retail Goods"
        }
    ],
    "sg:phone":"+1 254 776 4674",
    "sg:postcode":"76710",
    "sg:province":"TX",
    "sg:tags":[
        "merchandise"
    ],
    "wof:name":"Frame Shop & Gallery",
    "wof:placetype":"venue"
},
  "geometry": {"coordinates":[-97.17375199999999,31.528779],"type":"Point"}
}