{
  "type": "Feature",
  "properties": {
    "iso:country":"US",
    "sg:address":"214 E 5th St",
    "sg:city":"Tyler",
    "sg:classifiers":[
        {
            "category":"Banks & Credit Unions",
            "subcategory":"Investment Brokerage",
            "type":"Services"
        }
    ],
    "sg:phone":"+1 903 534 5790",
    "sg:postcode":"75701",
    "sg:province":"TX",
    "sg:tags":[
        "security"
    ],
    "wof:name":"Edward Jones 19809",
    "wof:placetype":"venue"
},
  "geometry": {"coordinates":[-95.29780100000001,32.330519],"type":"Point"}
}