{
  "type": "Feature",
  "properties": {
    "iso:country":"US",
    "sg:address":"4911 Jade Dr",
    "sg:city":"Dallas",
    "sg:classifiers":[
        {
            "category":"Arts & Performance",
            "subcategory":"Theater",
            "type":"Entertainment"
        }
    ],
    "sg:phone":"+1 214 374 6998",
    "sg:postcode":"75232",
    "sg:province":"TX",
    "sg:tags":[
        "theatrical"
    ],
    "wof:name":"North Texas Cultural Assn",
    "wof:placetype":"venue"
},
  "geometry": {"coordinates":[-96.840715,32.684221],"type":"Point"}
}