{
  "type": "Feature",
  "properties": {
    "iso:country":"US",
    "sg:address":"13683 State Hwy 364",
    "sg:city":"Tyler",
    "sg:classifiers":[
        {
            "category":"Manufacturing",
            "subcategory":"Chemicals & Compounds",
            "type":"Manufacturing & Wholesale Goods"
        }
    ],
    "sg:phone":"+1 903 592 6029",
    "sg:postcode":"75709",
    "sg:province":"TX",
    "sg:tags":[
        "preparation",
        "mfg"
    ],
    "wof:name":"Pappys Fireworks",
    "wof:placetype":"venue"
},
  "geometry": {"coordinates":[-95.393969,32.321354],"type":"Point"}
}