{
  "type": "Feature",
  "properties": {
    "iso:country":"US",
    "sg:address":"2139 Ave G",
    "sg:city":"Bay City",
    "sg:classifiers":[
        {
            "category":"Professional",
            "subcategory":"Computer Services",
            "type":"Services"
        }
    ],
    "sg:phone":"+1 979 244 3166",
    "sg:postcode":"77414",
    "sg:province":"TX",
    "sg:tags":[
        "internet"
    ],
    "wof:name":"Ashwood Data Systems",
    "wof:placetype":"venue"
},
  "geometry": {"coordinates":[-95.968692,28.9826],"type":"Point"}
}