{
  "type": "Feature",
  "properties": {
    "iso:country":"US",
    "sg:address":"1923 N 10th St",
    "sg:city":"Mcallen",
    "sg:classifiers":[
        {
            "category":"Food & Beverages",
            "subcategory":"Bakery",
            "type":"Retail Goods"
        }
    ],
    "sg:phone":"+1 956 686 7201",
    "sg:postcode":"78501",
    "sg:province":"TX",
    "wof:name":"B & D Bakery",
    "wof:placetype":"venue"
},
  "geometry": {"coordinates":[-98.22703,26.221237],"type":"Point"}
}