{
  "type": "Feature",
  "properties": {
    "iso:country":"US",
    "sg:address":"3420 S Hill St",
    "sg:city":"Amarillo",
    "sg:classifiers":[
        {
            "category":"Social Services",
            "subcategory":"Adult Care",
            "type":"Services"
        }
    ],
    "sg:phone":"+1 806 352 4133",
    "sg:postcode":"79103",
    "sg:province":"TX",
    "sg:tags":[
        "home",
        "residential"
    ],
    "wof:name":"Best Care",
    "wof:placetype":"venue"
},
  "geometry": {"coordinates":[-101.792648,35.177965],"type":"Point"}
}