{
  "type": "Feature",
  "properties": {
    "iso:country":"US",
    "sg:address":"12424 Fairfax Ridge Pl",
    "sg:city":"Austin",
    "sg:classifiers":[
        {
            "category":"Retail",
            "subcategory":"Portrait Studio",
            "type":"Services"
        }
    ],
    "sg:phone":"+1 512 263 8181",
    "sg:postcode":"78738",
    "sg:province":"TX",
    "sg:tags":[
        "photo"
    ],
    "wof:name":"Lallo Photography",
    "wof:placetype":"venue"
},
  "geometry": {"coordinates":[-97.93066899999999,30.313538],"type":"Point"}
}