{
  "type": "Feature",
  "properties": {
    "iso:country":"US",
    "sg:address":"3800 Gulfway Dr",
    "sg:city":"Port Arthur",
    "sg:classifiers":[
        {
            "category":"Personal",
            "subcategory":"Beauty Salon",
            "type":"Services"
        }
    ],
    "sg:phone":"+1 409 983 5515",
    "sg:postcode":"77642",
    "sg:province":"TX",
    "sg:tags":[
        "shop",
        "manicuring"
    ],
    "wof:name":"Expo Nails",
    "wof:placetype":"venue"
},
  "geometry": {"coordinates":[-93.919048,29.909137],"type":"Point"}
}