{
  "type": "Feature",
  "properties": {
    "iso:country":"US",
    "sg:address":"12001 S Freeway",
    "sg:city":"Fort Worth",
    "sg:classifiers":[
        {
            "category":"Health Services",
            "subcategory":"Doctor",
            "type":"Services"
        }
    ],
    "sg:phone":"+1 817 568 0500",
    "sg:postcode":"76102",
    "sg:province":"TX",
    "sg:website":"www.dermsw.com",
    "wof:name":"M Basem Dermatology",
    "wof:placetype":"venue"
},
  "geometry": {"coordinates":[-97.320172,32.584199],"type":"Point"}
}