{
  "type": "Feature",
  "properties": {
    "iso:country":"US",
    "sg:address":"1995 N Central Ave",
    "sg:city":"Brownsville",
    "sg:classifiers":[
        {
            "category":"Autos & Motor Vehicles",
            "subcategory":"Fuel & Gas Station",
            "type":"Retail Goods"
        }
    ],
    "sg:phone":"+1 956 838 1046",
    "sg:postcode":"78521",
    "sg:province":"TX",
    "sg:tags":[
        "gasoline",
        "station",
        "truck",
        "stops",
        "plaza"
    ],
    "wof:name":"American Truck Stop & Service",
    "wof:placetype":"venue"
},
  "geometry": {"coordinates":[-97.44590599999999,25.941023],"type":"Point"}
}