{
  "type": "Feature",
  "properties": {
    "iso:country":"US",
    "sg:address":"676 Cobre St",
    "sg:city":"El Paso",
    "sg:classifiers":[
        {
            "category":"Building & Trades",
            "subcategory":"Plumbing",
            "type":"Services"
        }
    ],
    "sg:phone":"+1 915 329 0745",
    "sg:postcode":"79928",
    "sg:province":"TX",
    "sg:tags":[
        "plumbing",
        "contractor"
    ],
    "wof:name":"Carrasco Plumbing",
    "wof:placetype":"venue"
},
  "geometry": {"coordinates":[-106.179289,31.665417],"type":"Point"}
}