{
  "type": "Feature",
  "properties": {
    "iso:country":"US",
    "sg:address":"1230 N Main St",
    "sg:city":"Vidor",
    "sg:classifiers":[
        {
            "category":"Home & Garden",
            "subcategory":"Hardware",
            "type":"Retail Goods"
        }
    ],
    "sg:phone":"+1 409 769 0281",
    "sg:postcode":"77662",
    "sg:province":"TX",
    "wof:name":"M & D Supply Ace Hardware",
    "wof:placetype":"venue"
},
  "geometry": {"coordinates":[-94.015562,30.141378],"type":"Point"}
}