{
  "type": "Feature",
  "properties": {
    "iso:country":"US",
    "sg:address":"11218 Saginaw Dr",
    "sg:city":"Houston",
    "sg:classifiers":[
        {
            "category":"Freight",
            "type":"Transportation"
        }
    ],
    "sg:phone":"+1 713 699 8813",
    "sg:postcode":"77076",
    "sg:province":"TX",
    "sg:tags":[
        "operator",
        "local",
        "trucking"
    ],
    "wof:name":"Total Care Delivery",
    "wof:placetype":"venue"
},
  "geometry": {"coordinates":[-95.380297,29.867107],"type":"Point"}
}