{
  "type": "Feature",
  "properties": {
    "iso:country":"US",
    "sg:address":"1501 S Polk St",
    "sg:city":"Amarillo",
    "sg:classifiers":[
        {
            "category":"Health Services",
            "subcategory":"Hospital",
            "type":"Services"
        }
    ],
    "sg:phone":"+1 806 337 1000",
    "sg:postcode":"79101",
    "sg:province":"AR",
    "sg:tags":[
        "mental"
    ],
    "sg:website":"www.tpmhmr.org",
    "wof:name":"Texas Panhandle Mental Health",
    "wof:placetype":"venue"
},
  "geometry": {"coordinates":[-101.838967,35.197258],"type":"Point"}
}