{
  "type": "Feature",
  "properties": {
    "iso:country":"US",
    "sg:address":"10210 N Ave P",
    "sg:city":"La Porte",
    "sg:classifiers":[
        {
            "category":"Social Services",
            "type":"Services"
        }
    ],
    "sg:phone":"+1 281 867 1341",
    "sg:postcode":"77571",
    "sg:province":"TX",
    "sg:tags":[
        "youth",
        "organization",
        "center"
    ],
    "wof:name":"Laporte Youth Soccer Asso",
    "wof:placetype":"venue"
},
  "geometry": {"coordinates":[-95.07738000000001,29.685253],"type":"Point"}
}