{
  "type": "Feature",
  "properties": {
    "iso:country":"US",
    "sg:address":"5351 Basswood Blvd",
    "sg:city":"Fort Worth",
    "sg:classifiers":[
        {
            "category":"Autos & Motor Vehicles",
            "subcategory":"Fuel & Gas Station",
            "type":"Retail Goods"
        }
    ],
    "sg:phone":"+1 817 605 9394",
    "sg:postcode":"76137",
    "sg:province":"TX",
    "sg:tags":[
        "station",
        "gasoline"
    ],
    "wof:name":"Murphy Oil USA Inc",
    "wof:placetype":"venue"
},
  "geometry": {"coordinates":[-97.270814,32.874258],"type":"Point"}
}