{
  "type": "Feature",
  "properties": {
    "iso:country":"US",
    "sg:address":"2505 W Murphy St",
    "sg:city":"Odessa",
    "sg:classifiers":[
        {
            "category":"Retail",
            "subcategory":"Auto Repair",
            "type":"Services"
        }
    ],
    "sg:phone":"+1 432 337 0821",
    "sg:postcode":"79763",
    "sg:province":"TX",
    "sg:tags":[
        "repairing",
        "automobile"
    ],
    "wof:name":"Willy Owens Svc Ctr",
    "wof:placetype":"venue"
},
  "geometry": {"coordinates":[-102.392118,31.831346],"type":"Point"}
}