{
  "type": "Feature",
  "properties": {
    "iso:country":"US",
    "sg:address":"1945 N Port Ct",
    "sg:city":"Grapevine",
    "sg:classifiers":[
        {
            "category":"Professional",
            "subcategory":"Computer Services",
            "type":"Services"
        }
    ],
    "sg:phone":"+1 817 488 6240",
    "sg:postcode":"76051",
    "sg:province":"TX",
    "sg:tags":[
        "consultant",
        "designer"
    ],
    "wof:name":"Tulsys Inc",
    "wof:placetype":"venue"
},
  "geometry": {"coordinates":[-97.095032,32.897195],"type":"Point"}
}