{
  "type": "Feature",
  "properties": {
    "iso:country":"US",
    "sg:address":"2405 34th St",
    "sg:city":"Lubbock",
    "sg:classifiers":[
        {
            "category":"Wholesale",
            "subcategory":"Electrical",
            "type":"Manufacturing & Wholesale Goods"
        }
    ],
    "sg:phone":"+1 806 792 1662",
    "sg:postcode":"79411",
    "sg:province":"TX",
    "sg:tags":[
        "sound",
        "equipment",
        "system"
    ],
    "wof:name":"Cisco Sound",
    "wof:placetype":"venue"
},
  "geometry": {"coordinates":[-101.87044400000001,33.563202],"type":"Point"}
}