{
  "type": "Feature",
  "properties": {
    "iso:country":"US",
    "sg:address":"5107 Madden Ln",
    "sg:city":"Houston",
    "sg:classifiers":[
        {
            "category":"Shopping",
            "subcategory":"Music",
            "type":"Retail Goods"
        }
    ],
    "sg:phone":"+1 713 738 3515",
    "sg:postcode":"77048",
    "sg:province":"TX",
    "wof:name":"Treehouse Records Inc",
    "wof:placetype":"venue"
},
  "geometry": {"coordinates":[-95.347613,29.632733],"type":"Point"}
}