{
  "type": "Feature",
  "properties": {
    "iso:country":"US",
    "sg:address":"1808 Jacquelyn Dr",
    "sg:city":"Houston",
    "sg:classifiers":[
        {
            "category":"Retail",
            "subcategory":"Auto Repair",
            "type":"Services"
        }
    ],
    "sg:phone":"+1 713 680 2277",
    "sg:postcode":"77055",
    "sg:province":"TX",
    "sg:tags":[
        "body",
        "shop"
    ],
    "wof:name":"Maaco Auto Painting & Bodyworks",
    "wof:placetype":"venue"
},
  "geometry": {"coordinates":[-95.480698,29.8032],"type":"Point"}
}