{
  "type": "Feature",
  "properties": {
    "iso:country":"US",
    "sg:address":"16534 Gold Ridge Ln",
    "sg:city":"Houston",
    "sg:classifiers":[
        {
            "category":"Professional",
            "subcategory":"Detective & Security Services",
            "type":"Services"
        }
    ],
    "sg:phone":"+1 281 868 1977",
    "sg:postcode":"77053",
    "sg:province":"TX",
    "sg:tags":[
        "car"
    ],
    "wof:name":"Countywide Ptrol Invstigations",
    "wof:placetype":"venue"
},
  "geometry": {"coordinates":[-95.468616,29.584489],"type":"Point"}
}