{
  "type": "Feature",
  "properties": {
    "iso:country":"US",
    "sg:address":"2919 Foley Rd",
    "sg:city":"Crosby",
    "sg:classifiers":[
        {
            "category":"Retail",
            "subcategory":"Repair Shop",
            "type":"Services"
        }
    ],
    "sg:phone":"+1 281 462 0717",
    "sg:postcode":"77532",
    "sg:province":"TX",
    "sg:tags":[
        "welding"
    ],
    "wof:name":"Reilly Services",
    "wof:placetype":"venue"
},
  "geometry": {"coordinates":[-95.129192,29.948123],"type":"Point"}
}