{
  "type": "Feature",
  "properties": {
    "iso:country":"US",
    "sg:address":"201 S Magnolia St",
    "sg:city":"Crowley",
    "sg:classifiers":[
        {
            "category":"Manufacturing",
            "subcategory":"Rubber & Plastics",
            "type":"Manufacturing & Wholesale Goods"
        },
        {
            "category":"Wholesale",
            "subcategory":"Chemicals & Plastics",
            "type":"Manufacturing & Wholesale Goods"
        }
    ],
    "sg:phone":"+1 817 297 4341",
    "sg:postcode":"76036",
    "sg:province":"TX",
    "sg:tags":[
        "bag",
        "product"
    ],
    "wof:name":"Poulos B N",
    "wof:placetype":"venue"
},
  "geometry": {"coordinates":[-97.36005400000001,32.577129],"type":"Point"}
}