{
  "type": "Feature",
  "properties": {
    "iso:country":"US",
    "sg:address":"10650 North Fwy",
    "sg:city":"Houston",
    "sg:classifiers":[
        {
            "category":"Education",
            "subcategory":"School",
            "type":"Public Place"
        }
    ],
    "sg:phone":"+1 281 878 6800",
    "sg:postcode":"77037",
    "sg:province":"TX",
    "sg:tags":[
        "high",
        "middle",
        "elementary"
    ],
    "sg:website":"www.aldine.k12.tx.us",
    "wof:name":"Aldine Independent School District",
    "wof:placetype":"venue"
},
  "geometry": {"coordinates":[-95.411869,29.920219],"type":"Point"}
}