{
  "type": "Feature",
  "properties": {
    "iso:country":"US",
    "sg:address":"709 E Ben White Blvd",
    "sg:city":"Austin",
    "sg:classifiers":[
        {
            "category":"Bars & Pubs",
            "type":"Food & Drink"
        }
    ],
    "sg:menulink":"http://www.allmenus.com/tx/austin/14583-bill-miller-bar-b-q/menu/",
    "sg:phone":"+1 512 443 3533",
    "sg:postcode":"78704",
    "sg:province":"TX",
    "sg:tags":[
        "american"
    ],
    "wof:name":"Bill Miller Bar-B-Q",
    "wof:placetype":"venue"
},
  "geometry": {"coordinates":[-97.771443,30.227023],"type":"Point"}
}