{
  "type": "Feature",
  "properties": {
    "iso:country":"US",
    "sg:address":"2325 Webb Lynn Rd",
    "sg:city":"Arlington",
    "sg:classifiers":[
        {
            "category":"Building & Trades",
            "subcategory":"Construction",
            "type":"Services"
        }
    ],
    "sg:phone":"+1 817 265 2760",
    "sg:postcode":"76002",
    "sg:province":"TX",
    "sg:tags":[
        "utility",
        "contractor"
    ],
    "wof:name":"John B Cox Inc",
    "wof:placetype":"venue"
},
  "geometry": {"coordinates":[-97.066165,32.635556],"type":"Point"}
}