{
  "type": "Feature",
  "properties": {
    "iso:country":"US",
    "sg:address":"517 Idlewild Rd",
    "sg:city":"Grand Prairie",
    "sg:classifiers":[
        {
            "category":"Education",
            "subcategory":"Vocational School",
            "type":"Public Place"
        }
    ],
    "sg:phone":"+1 972 263 1536",
    "sg:postcode":"75051",
    "sg:province":"TX",
    "wof:name":"Texas Lborers Training Tr Fund",
    "wof:placetype":"venue"
},
  "geometry": {"coordinates":[-96.953284,32.745243],"type":"Point"}
}