{
  "type": "Feature",
  "properties": {
    "iso:country":"US",
    "sg:address":"1501 William D Tate Ave",
    "sg:city":"Grapevine",
    "sg:classifiers":[
        {
            "category":"Restaurant",
            "type":"Food & Drink"
        }
    ],
    "sg:menulink":"http://www.allmenus.com/tx/northeast-tarrant/147488-boston-market/menu/",
    "sg:phone":"+1 817 488 0666",
    "sg:postcode":"76051",
    "sg:province":"TX",
    "sg:tags":[
        "barbecue",
        "american",
        "soup"
    ],
    "wof:name":"Boston Market",
    "wof:placetype":"venue"
},
  "geometry": {"coordinates":[-97.089077,32.92456],"type":"Point"}
}