{
  "type": "Feature",
  "properties": {
    "iso:country":"US",
    "sg:address":"207 Wildcat Dr",
    "sg:city":"Del Rio",
    "sg:classifiers":[
        {
            "category":"Education",
            "subcategory":"Junior College",
            "type":"Public Place"
        }
    ],
    "sg:phone":"+1 830 775 1612",
    "sg:postcode":"78840",
    "sg:province":"TX",
    "wof:name":"Southwest Texas Junior College",
    "wof:placetype":"venue"
},
  "geometry": {"coordinates":[-100.9217,29.376769],"type":"Point"}
}