{
  "type": "Feature",
  "properties": {
    "iso:country":"US",
    "sg:address":"1150 Industrial Blvd",
    "sg:city":"Lone Star",
    "sg:classifiers":[
        {
            "category":"Freight",
            "type":"Transportation"
        }
    ],
    "sg:phone":"+1 903 656 1116",
    "sg:postcode":"75668",
    "sg:province":"TX",
    "sg:tags":[
        "field",
        "oil",
        "hauling"
    ],
    "wof:name":"J H Walker Trucking",
    "wof:placetype":"venue"
},
  "geometry": {"coordinates":[-94.703256,32.939012],"type":"Point"}
}