{
  "type": "Feature",
  "properties": {
    "iso:country":"US",
    "sg:address":"4511 N Midkiff Rd",
    "sg:city":"Midland",
    "sg:classifiers":[
        {
            "category":"Autos & Motor Vehicles",
            "subcategory":"Auto Supplies",
            "type":"Retail Goods"
        },
        {
            "category":"Retail",
            "subcategory":"Auto Repair",
            "type":"Services"
        }
    ],
    "sg:phone":"+1 432 699 8590",
    "sg:postcode":"79705",
    "sg:province":"TX",
    "sg:tags":[
        "oil",
        "tire",
        "automobile",
        "accessory",
        "lube",
        "part",
        "supplies-used",
        "brake",
        "rebuilt"
    ],
    "sg:website":"http://www.sears.com/shc/s/v_10153_12605_Automotive?adCell=AH",
    "wof:name":"Sears Auto Center",
    "wof:placetype":"venue"
},
  "geometry": {"coordinates":[-102.12876,32.031689],"type":"Point"}
}