{
  "type": "Feature",
  "properties": {
    "iso:country":"US",
    "sg:address":"230 N Denton Tap Rd Ste 102",
    "sg:city":"Coppell",
    "sg:classifiers":[
        {
            "category":"Banks & Credit Unions",
            "subcategory":"Bank",
            "type":"Services"
        }
    ],
    "sg:phone":"+1 972 692 9900",
    "sg:postcode":"75019",
    "sg:province":"TX",
    "sg:website":"www.tcbtexas.com",
    "wof:name":"Town Center Bank",
    "wof:placetype":"venue"
},
  "geometry": {"coordinates":[-96.99340599999999,32.97387],"type":"Point"}
}