{
  "type": "Feature",
  "properties": {
    "iso:country":"US",
    "sg:address":"6822 Middlefield Dr",
    "sg:city":"Pasadena",
    "sg:classifiers":[
        {
            "category":"Shopping",
            "subcategory":"Hobbies, Toys, & Games",
            "type":"Retail Goods"
        }
    ],
    "sg:phone":"+1 281 487 4668",
    "sg:postcode":"77505",
    "sg:province":"TX",
    "wof:name":"Angels Anonymous",
    "wof:placetype":"venue"
},
  "geometry": {"coordinates":[-95.134889,29.642112],"type":"Point"}
}