{
  "type": "Feature",
  "properties": {
    "iso:country":"US",
    "sg:address":"5363 Apple Blossom Ln",
    "sg:city":"Friendswood",
    "sg:classifiers":[
        {
            "category":"Building & Trades",
            "subcategory":"Construction",
            "type":"Services"
        }
    ],
    "sg:phone":"+1 281 482 0595",
    "sg:postcode":"77546",
    "sg:province":"TX",
    "sg:tags":[
        "material",
        "contractor"
    ],
    "wof:name":"David Tile Co",
    "wof:placetype":"venue"
},
  "geometry": {"coordinates":[-95.187752,29.530305],"type":"Point"}
}