{
  "type": "Feature",
  "properties": {
    "iso:country":"US",
    "sg:address":"416 Bridlewood N",
    "sg:city":"Colleyville",
    "sg:classifiers":[
        {
            "category":"Professional",
            "subcategory":"Computer Services",
            "type":"Services"
        }
    ],
    "sg:phone":"+1 469 524 8888",
    "sg:postcode":"76034",
    "sg:province":"TX",
    "sg:tags":[
        "integration",
        "software"
    ],
    "wof:name":"Dallas Objectworks Inc",
    "wof:placetype":"venue"
},
  "geometry": {"coordinates":[-97.16095199999999,32.871327],"type":"Point"}
}