{
  "type": "Feature",
  "properties": {
    "iso:country":"US",
    "sg:address":"120 E Main St",
    "sg:city":"Humble",
    "sg:phone":"+1 281 540 3170",
    "sg:postcode":"77338",
    "sg:province":"TX",
    "sg:tags":[
        "oil"
    ],
    "wof:name":"Fuel",
    "wof:placetype":"venue"
},
  "geometry": {"coordinates":[-95.26490200000001,29.997964],"type":"Point"}
}