{
  "type": "Feature",
  "properties": {
    "iso:country":"US",
    "sg:address":"221 Quamasia Ave",
    "sg:city":"Mcallen",
    "sg:classifiers":[
        {
            "category":"Wholesale",
            "subcategory":"Home Furnishings",
            "type":"Manufacturing & Wholesale Goods"
        }
    ],
    "sg:phone":"+1 956 682 7340",
    "sg:postcode":"78504",
    "sg:province":"TX",
    "wof:name":"Monals Custom Windows Design",
    "wof:placetype":"venue"
},
  "geometry": {"coordinates":[-98.21532000000001,26.240501],"type":"Point"}
}