{
  "type": "Feature",
  "properties": {
    "iso:country":"US",
    "sg:address":"2624 E Park Blvd",
    "sg:city":"Plano",
    "sg:classifiers":[
        {
            "category":"Retail",
            "subcategory":"Portrait Studio",
            "type":"Services"
        },
        {
            "category":"Professional",
            "subcategory":"Art Services",
            "type":"Services"
        }
    ],
    "sg:phone":"+1 972 578 8255",
    "sg:postcode":"75074",
    "sg:province":"TX",
    "sg:tags":[
        "rental",
        "photographers-portrait",
        "photographic",
        "darkroom"
    ],
    "wof:name":"Julie Barrett",
    "wof:placetype":"venue"
},
  "geometry": {"coordinates":[-96.678815,33.031026],"type":"Point"}
}