{
  "type": "Feature",
  "properties": {
    "iso:country":"US",
    "sg:address":"4113 Sunflower Ln",
    "sg:city":"Temple",
    "sg:classifiers":[
        {
            "category":"Real Estate",
            "subcategory":"Real Estate Agent",
            "type":"Services"
        }
    ],
    "sg:phone":"+1 254 899 2222",
    "sg:postcode":"76502",
    "sg:province":"TX",
    "wof:name":"Wildflower Real Estate",
    "wof:placetype":"venue"
},
  "geometry": {"coordinates":[-97.396196,31.106162],"type":"Point"}
}