{
  "type": "Feature",
  "properties": {
    "iso:country":"US",
    "sg:address":"801 Hebron Pkwy",
    "sg:city":"Lewisville",
    "sg:classifiers":[
        {
            "category":"Professional",
            "type":"Services"
        }
    ],
    "sg:phone":"+1 972 459 3562",
    "sg:postcode":"75057",
    "sg:province":"TX",
    "sg:tags":[
        "establishment"
    ],
    "wof:name":"Shortall & Shortall",
    "wof:placetype":"venue"
},
  "geometry": {"coordinates":[-96.96396300000001,33.012575],"type":"Point"}
}