{
  "type": "Feature",
  "properties": {
    "iso:country":"US",
    "sg:address":"200 N Loraine St",
    "sg:city":"Midland",
    "sg:classifiers":[
        {
            "category":"Banks & Credit Unions",
            "subcategory":"Investment Brokerage",
            "type":"Services"
        }
    ],
    "sg:phone":"+1 432 686 9814",
    "sg:postcode":"79701",
    "sg:province":"TX",
    "sg:tags":[
        "firm",
        "brokerage",
        "stock",
        "bond"
    ],
    "wof:name":"Charles Schwab & Co",
    "wof:placetype":"venue"
},
  "geometry": {"coordinates":[-102.07566,31.999575],"type":"Point"}
}