{
  "type": "Feature",
  "properties": {
    "iso:country":"US",
    "sg:address":"10642 Aldine Westfield Rd",
    "sg:city":"Houston",
    "sg:classifiers":[
        {
            "category":"Autos & Motor Vehicles",
            "subcategory":"Auto Supplies",
            "type":"Retail Goods"
        }
    ],
    "sg:phone":"+1 713 699 0516",
    "sg:postcode":"77093",
    "sg:province":"TX",
    "wof:name":"Park Auto Parts Company Inc",
    "wof:placetype":"venue"
},
  "geometry": {"coordinates":[-95.35089499999999,29.86921],"type":"Point"}
}