{
  "type": "Feature",
  "properties": {
    "iso:country":"US",
    "sg:address":"911 Ave C",
    "sg:city":"El Campo",
    "sg:classifiers":[
        {
            "category":"Personal",
            "subcategory":"Beauty Salon",
            "type":"Services"
        }
    ],
    "sg:phone":"+1 979 543 4362",
    "sg:postcode":"77437",
    "sg:province":"TX",
    "sg:tags":[
        "shop"
    ],
    "wof:name":"La Blons",
    "wof:placetype":"venue"
},
  "geometry": {"coordinates":[-96.27825900000001,29.198634],"type":"Point"}
}