{
  "type": "Feature",
  "properties": {
    "iso:country":"US",
    "sg:address":"13728 Mark Dr",
    "sg:city":"Tyler",
    "sg:classifiers":[
        {
            "category":"Retail",
            "subcategory":"Repair Shop",
            "type":"Services"
        }
    ],
    "sg:phone":"+1 903 561 5786",
    "sg:postcode":"75709",
    "sg:province":"TX",
    "sg:tags":[
        "refrigeration"
    ],
    "wof:name":"Spurlocks Refrigeration",
    "wof:placetype":"venue"
},
  "geometry": {"coordinates":[-95.39605299999999,32.305615],"type":"Point"}
}