{
  "type": "Feature",
  "properties": {
    "iso:country":"US",
    "sg:address":"5546 Cavalcade St",
    "sg:city":"Houston",
    "sg:classifiers":[
        {
            "category":"Food & Beverages",
            "subcategory":"Groceries & Convenience Stores",
            "type":"Retail Goods"
        }
    ],
    "sg:phone":"+1 713 672 8874",
    "sg:postcode":"77026",
    "sg:province":"TX",
    "wof:name":"Queen Saver",
    "wof:placetype":"venue"
},
  "geometry": {"coordinates":[-95.313593,29.800217],"type":"Point"}
}