{
  "type": "Feature",
  "properties": {
    "iso:country":"US",
    "sg:address":"26118 I- 45",
    "sg:city":"Spring",
    "sg:classifiers":[
        {
            "category":"Wholesale",
            "subcategory":"Machinery & Supplies",
            "type":"Manufacturing & Wholesale Goods"
        }
    ],
    "sg:phone":"+1 281 367 5699",
    "sg:postcode":"77386",
    "sg:province":"TX",
    "sg:tags":[
        "plate",
        "industrial",
        "mfg",
        "work",
        "fabricated",
        "equipment",
        "heat",
        "exchanger"
    ],
    "wof:name":"Master's Process Equipment Co",
    "wof:placetype":"venue"
},
  "geometry": {"coordinates":[-95.446026,30.14363],"type":"Point"}
}