{
  "type": "Feature",
  "properties": {
    "iso:country":"US",
    "sg:address":"10540 Walnut St",
    "sg:city":"Dallas",
    "sg:classifiers":[
        {
            "category":"Freight",
            "type":"Transportation"
        }
    ],
    "sg:phone":"+1 972 272 6988",
    "sg:postcode":"75243",
    "sg:province":"TX",
    "sg:tags":[
        "commercial",
        "storage"
    ],
    "wof:name":"Public Storage Inc",
    "wof:placetype":"venue"
},
  "geometry": {"coordinates":[-96.705664,32.916598],"type":"Point"}
}