{
  "type": "Feature",
  "properties": {
    "iso:country":"US",
    "sg:address":"216 S 16th St",
    "sg:city":"La Porte",
    "sg:classifiers":[
        {
            "category":"Retail",
            "subcategory":"Repair Shop",
            "type":"Services"
        }
    ],
    "sg:phone":"+1 281 471 8129",
    "sg:postcode":"77571",
    "sg:province":"TX",
    "sg:tags":[
        "industrial",
        "valve"
    ],
    "wof:name":"Valsource International  L L C",
    "wof:placetype":"venue"
},
  "geometry": {"coordinates":[-95.035996,29.663688],"type":"Point"}
}