{
  "type": "Feature",
  "properties": {
    "iso:country":"US",
    "sg:address":"100 E San Antonio St",
    "sg:city":"San Marcos",
    "sg:classifiers":[
        {
            "category":"Professional",
            "subcategory":"Engineering",
            "type":"Services"
        },
        {
            "category":"Real Estate",
            "subcategory":"Surveying",
            "type":"Services"
        }
    ],
    "sg:phone":"+1 512 353 3335",
    "sg:postcode":"78666",
    "sg:province":"TX",
    "sg:tags":[
        "surveyor",
        "consulting",
        "land",
        "engineer"
    ],
    "sg:website":"www.pro-techengr.com",
    "wof:name":"Pro-Tech Engineering Group Inc",
    "wof:placetype":"venue"
},
  "geometry": {"coordinates":[-97.940011,29.882306],"type":"Point"}
}