{
  "type": "Feature",
  "properties": {
    "iso:country":"US",
    "sg:address":"1303 N Ash Ave",
    "sg:city":"Lubbock",
    "sg:classifiers":[
        {
            "category":"Professional",
            "subcategory":"Detective & Security Services",
            "type":"Services"
        },
        {
            "category":"Professional",
            "subcategory":"Business Services",
            "type":"Services"
        }
    ],
    "sg:phone":"+1 806 747 2362",
    "sg:postcode":"79403",
    "sg:province":"TX",
    "sg:tags":[
        "car"
    ],
    "wof:name":"Loomis Fargo & Co",
    "wof:placetype":"venue"
},
  "geometry": {"coordinates":[-101.83598499999999,33.615386],"type":"Point"}
}