{
  "type": "Feature",
  "properties": {
    "iso:country":"US",
    "sg:address":"933 Studewood St",
    "sg:city":"Houston",
    "sg:classifiers":[
        {
            "category":"Professional",
            "subcategory":"Lawyer & Legal Services",
            "type":"Services"
        }
    ],
    "sg:phone":"+1 713 426 5600",
    "sg:postcode":"77008",
    "sg:province":"TX",
    "sg:tags":[
        "attorney",
        "death",
        "personal",
        "medical",
        "damage",
        "wrongful",
        "accident",
        "malpractice",
        "injury",
        "property",
        "law"
    ],
    "sg:website":"http://www.agtriallaw.com",
    "wof:name":"Aversano & Gold LLP",
    "wof:placetype":"venue"
},
  "geometry": {"coordinates":[-95.38779,29.788222],"type":"Point"}
}