{
  "type": "Feature",
  "properties": {
    "iso:country":"US",
    "sg:address":"200 Pitchford Ln",
    "sg:city":"Millsap",
    "sg:classifiers":[
        {
            "category":"Building & Trades",
            "subcategory":"Pest Control",
            "type":"Services"
        }
    ],
    "sg:phone":"+1 817 596 3874",
    "sg:postcode":"76066",
    "sg:province":"TX",
    "wof:name":"Pitchford Pest Control",
    "wof:placetype":"venue"
},
  "geometry": {"coordinates":[-97.91247300000001,32.748754],"type":"Point"}
}