{
  "type": "Feature",
  "properties": {
    "iso:country":"US",
    "sg:address":"2323 Texas St",
    "sg:city":"Pecos",
    "sg:classifiers":[
        {
            "category":"Health Services",
            "subcategory":"Medical Lab",
            "type":"Services"
        }
    ],
    "sg:phone":"+1 432 447 0519",
    "sg:postcode":"79772",
    "sg:province":"TX",
    "sg:tags":[
        "laboratory"
    ],
    "wof:name":"Quest Diagnostics Inc",
    "wof:placetype":"venue"
},
  "geometry": {"coordinates":[-103.512753,31.401566],"type":"Point"}
}