{
  "type": "Feature",
  "properties": {
    "iso:country":"US",
    "sg:address":"212 E Polk St",
    "sg:city":"Harlingen",
    "sg:classifiers":[
        {
            "category":"Social Services",
            "subcategory":"Child Care",
            "type":"Services"
        }
    ],
    "sg:phone":"+1 956 412 5067",
    "sg:postcode":"78550",
    "sg:province":"TX",
    "sg:tags":[
        "nursery",
        "day"
    ],
    "wof:name":"Maryanns Child Care",
    "wof:placetype":"venue"
},
  "geometry": {"coordinates":[-97.69447099999999,26.188537],"type":"Point"}
}