{
  "type": "Feature",
  "properties": {
    "iso:country":"US",
    "sg:address":"6318 Camp Bowie Blvd",
    "sg:city":"Fort Worth",
    "sg:classifiers":[
        {
            "category":"Personal",
            "subcategory":"Beauty Salon",
            "type":"Services"
        }
    ],
    "sg:phone":"+1 817 732 3733",
    "sg:postcode":"76116",
    "sg:province":"TX",
    "wof:name":"Salon Moda",
    "wof:placetype":"venue"
},
  "geometry": {"coordinates":[-97.419206,32.727261],"type":"Point"}
}