{
  "type": "Feature",
  "properties": {
    "iso:country":"US",
    "sg:address":"136 Ruby Dell Ln",
    "sg:city":"Waco",
    "sg:classifiers":[
        {
            "category":"Shopping",
            "type":"Retail Goods"
        }
    ],
    "sg:phone":"+1 254 867 8011",
    "sg:postcode":"76705",
    "sg:province":"TX",
    "sg:tags":[
        "merchandise"
    ],
    "wof:name":"Scrubs Outlet",
    "wof:placetype":"venue"
},
  "geometry": {"coordinates":[-97.126563,31.624858],"type":"Point"}
}