{
  "type": "Feature",
  "properties": {
    "iso:country":"US",
    "sg:address":"219 N Comanche St",
    "sg:city":"San Marcos",
    "sg:classifiers":[
        {
            "category":"Real Estate",
            "subcategory":"Real Estate Agent",
            "type":"Services"
        }
    ],
    "sg:phone":"+1 512 392 3602",
    "sg:postcode":"78666",
    "sg:province":"TX",
    "wof:name":"Indigo Development",
    "wof:placetype":"venue"
},
  "geometry": {"coordinates":[-97.944006,29.883663],"type":"Point"}
}