{
  "type": "Feature",
  "properties": {
    "iso:country":"US",
    "sg:address":"21714 Hardy Oak Blvd",
    "sg:city":"San Antonio",
    "sg:classifiers":[
        {
            "category":"Health Services",
            "subcategory":"Chiropractor",
            "type":"Services"
        }
    ],
    "sg:phone":"+1 210 494 9355",
    "sg:postcode":"78258",
    "sg:province":"TX",
    "wof:name":"English Family Chiropractic",
    "wof:placetype":"venue"
},
  "geometry": {"coordinates":[-98.489715,29.642954],"type":"Point"}
}