{
  "type": "Feature",
  "properties": {
    "iso:country":"US",
    "sg:address":"2401 Line Ave",
    "sg:city":"Amarillo",
    "sg:classifiers":[
        {
            "category":"Professional",
            "subcategory":"Business Services",
            "type":"Services"
        }
    ],
    "sg:phone":"+1 806 342 0843",
    "sg:postcode":"79106",
    "sg:province":"TX",
    "wof:name":"Joppa Design",
    "wof:placetype":"venue"
},
  "geometry": {"coordinates":[-101.865408,35.207467],"type":"Point"}
}