{
  "type": "Feature",
  "properties": {
    "iso:country":"US",
    "sg:address":"3894 Fm 1200",
    "sg:city":"Gainesville",
    "sg:classifiers":[
        {
            "category":"Farming",
            "subcategory":"Livestock Farm",
            "type":"Manufacturing & Wholesale Goods"
        }
    ],
    "sg:phone":"+1 940 665 2226",
    "sg:postcode":"76240",
    "sg:province":"TX",
    "sg:tags":[
        "ranch"
    ],
    "wof:name":"Bengfort, Leonard Construction",
    "wof:placetype":"venue"
},
  "geometry": {"coordinates":[-97.251839,33.735488],"type":"Point"}
}