{
  "type": "Feature",
  "properties": {
    "iso:country":"US",
    "sg:address":"7086 4th St",
    "sg:city":"Canutillo",
    "sg:classifiers":[
        {
            "category":"Professional",
            "type":"Services"
        }
    ],
    "sg:phone":"+1 915 920 8346",
    "sg:postcode":"79835",
    "sg:province":"TX",
    "wof:name":"Aggresssive Process Service",
    "wof:placetype":"venue"
},
  "geometry": {"coordinates":[-106.59626799999999,31.914298],"type":"Point"}
}