{
  "type": "Feature",
  "properties": {
    "iso:country":"US",
    "sg:address":"111 E Marshall Ave",
    "sg:city":"Longview",
    "sg:classifiers":[
        {
            "category":"Autos & Motor Vehicles",
            "subcategory":"Automobile Sales",
            "type":"Retail Goods"
        }
    ],
    "sg:phone":"+1 903 295 2121",
    "sg:postcode":"75601",
    "sg:province":"TX",
    "sg:tags":[
        "car",
        "dealer"
    ],
    "sg:website":"www.crsautosales.com",
    "wof:name":"CRS Auto Sales",
    "wof:placetype":"venue"
},
  "geometry": {"coordinates":[-94.737182,32.500661],"type":"Point"}
}