{
  "type": "Feature",
  "properties": {
    "iso:country":"US",
    "sg:address":"122 Venice St",
    "sg:city":"San Antonio",
    "sg:classifiers":[
        {
            "category":"Manufacturing",
            "subcategory":"Tools & Machinery",
            "type":"Manufacturing & Wholesale Goods"
        }
    ],
    "sg:phone":"+1 210 834 2824",
    "sg:postcode":"78201",
    "sg:province":"TX",
    "sg:tags":[
        "machine",
        "parts"
    ],
    "wof:name":"Clockworks",
    "wof:placetype":"venue"
},
  "geometry": {"coordinates":[-98.51043,29.487627],"type":"Point"}
}