{
  "type": "Feature",
  "properties": {
    "iso:country":"US",
    "sg:address":"2413 Market St",
    "sg:city":"Galveston",
    "sg:classifiers":[
        {
            "category":"Shopping",
            "subcategory":"Jewelry",
            "type":"Retail Goods"
        }
    ],
    "sg:phone":"+1 409 762 5792",
    "sg:postcode":"77550",
    "sg:province":"TX",
    "wof:name":"Vics Jewelry",
    "wof:placetype":"venue"
},
  "geometry": {"coordinates":[-94.795984,29.304763],"type":"Point"}
}