{
  "type": "Feature",
  "properties": {
    "iso:country":"US",
    "sg:address":"110 W Jefferson St",
    "sg:city":"Port Isabel",
    "sg:classifiers":[
        {
            "category":"Recreation",
            "type":"Entertainment"
        }
    ],
    "sg:phone":"+1 956 943 8438",
    "sg:postcode":"78578",
    "sg:province":"TX",
    "sg:tags":[
        "party",
        "fishing"
    ],
    "sg:website":"www.tift.org",
    "wof:name":"Texas International Fishing",
    "wof:placetype":"venue"
},
  "geometry": {"coordinates":[-97.207717,26.072071],"type":"Point"}
}