{
  "type": "Feature",
  "properties": {
    "iso:country":"US",
    "sg:address":"2815 Prestige Rd",
    "sg:city":"Keller",
    "sg:classifiers":[
        {
            "category":"Banks & Credit Unions",
            "subcategory":"Financial Services",
            "type":"Services"
        }
    ],
    "sg:phone":"+1 817 337 5800",
    "sg:postcode":"76248",
    "sg:province":"TX",
    "sg:tags":[
        "investor"
    ],
    "wof:name":"Four C Real Estate Investments",
    "wof:placetype":"venue"
},
  "geometry": {"coordinates":[-97.300101,32.928269],"type":"Point"}
}