{
  "type": "Feature",
  "properties": {
    "iso:country":"US",
    "sg:address":"219 Edwards Rd",
    "sg:city":"Van Alstyne",
    "sg:classifiers":[
        {
            "category":"Utilities",
            "subcategory":"Refuse",
            "type":"Services"
        }
    ],
    "sg:phone":"+1 903 482 6696",
    "sg:postcode":"75495",
    "sg:province":"TX",
    "sg:tags":[
        "garbage",
        "collection"
    ],
    "wof:name":"Jerry's Trash Svc Inc",
    "wof:placetype":"venue"
},
  "geometry": {"coordinates":[-96.519505,33.444931],"type":"Point"}
}