{
  "type": "Feature",
  "properties": {
    "iso:country":"US",
    "sg:address":"12032 Homestead Rd",
    "sg:city":"Houston",
    "sg:classifiers":[
        {
            "category":"Shopping",
            "subcategory":"Computers & Home Electronics",
            "type":"Retail Goods"
        }
    ],
    "sg:phone":"+1 281 449 5632",
    "sg:postcode":"77050",
    "sg:province":"TX",
    "wof:name":"Sound Quest Car Stereo",
    "wof:placetype":"venue"
},
  "geometry": {"coordinates":[-95.300822,29.899735],"type":"Point"}
}