{
  "type": "Feature",
  "properties": {
    "iso:country":"US",
    "sg:address":"326 Co Rd 345",
    "sg:city":"Merkel",
    "sg:classifiers":[
        {
            "category":"Farming",
            "subcategory":"Livestock Farm",
            "type":"Manufacturing & Wholesale Goods"
        }
    ],
    "sg:phone":"+1 325 846 4533",
    "sg:postcode":"79536",
    "sg:province":"TX",
    "sg:tags":[
        "animal",
        "general"
    ],
    "wof:name":"Massey Farms",
    "wof:placetype":"venue"
},
  "geometry": {"coordinates":[-100.101973,32.378072],"type":"Point"}
}