{
  "type": "Feature",
  "properties": {
    "iso:country":"US",
    "sg:address":"2380 I- 35D Bus",
    "sg:city":"Pearsall",
    "sg:classifiers":[
        {
            "category":"Wholesale",
            "subcategory":"Machinery & Supplies",
            "type":"Manufacturing & Wholesale Goods"
        }
    ],
    "sg:phone":"+1 830 334 4445",
    "sg:postcode":"78061",
    "sg:province":"TX",
    "sg:tags":[
        "farm",
        "equipment"
    ],
    "wof:name":"Southern Implement Co",
    "wof:placetype":"venue"
},
  "geometry": {"coordinates":[-99.16107700000001,28.698607],"type":"Point"}
}