{
  "type": "Feature",
  "properties": {
    "iso:country":"US",
    "sg:address":"2008 W Taylor St",
    "sg:city":"Sherman",
    "sg:classifiers":[
        {
            "category":"Home & Garden",
            "subcategory":"Building Materials",
            "type":"Retail Goods"
        }
    ],
    "sg:phone":"+1 903 892 6128",
    "sg:postcode":"75092",
    "sg:province":"TX",
    "sg:tags":[
        "lumber"
    ],
    "wof:name":"Foxworth-Galbraith Lumber Co",
    "wof:placetype":"venue"
},
  "geometry": {"coordinates":[-96.645567,33.651604],"type":"Point"}
}