{
  "type": "Feature",
  "properties": {
    "iso:country":"US",
    "sg:address":"1720 Lanice Ave",
    "sg:city":"Bridgeport",
    "sg:classifiers":[
        {
            "category":"Museum",
            "type":"Entertainment"
        }
    ],
    "sg:phone":"+1 940 683 4341",
    "sg:postcode":"76426",
    "sg:province":"TX",
    "sg:tags":[
        "gallery"
    ],
    "wof:name":"Bridgeport Heritage Museum",
    "wof:placetype":"venue"
},
  "geometry": {"coordinates":[-97.746988,33.208239],"type":"Point"}
}