{
  "type": "Feature",
  "properties": {
    "iso:country":"US",
    "sg:address":"1606 Marshall St",
    "sg:city":"Houston",
    "sg:classifiers":[
        {
            "category":"Professional",
            "subcategory":"Computer Services",
            "type":"Services"
        }
    ],
    "sg:phone":"+1 713 298 5844",
    "sg:postcode":"77006",
    "sg:province":"TX",
    "sg:tags":[
        "programing",
        "custom"
    ],
    "wof:name":"Intelligent Business Solutions",
    "wof:placetype":"venue"
},
  "geometry": {"coordinates":[-95.401866,29.73959],"type":"Point"}
}