{
  "type": "Feature",
  "properties": {
    "iso:country":"US",
    "sg:address":"5200 N 10th St",
    "sg:city":"Mcallen",
    "sg:classifiers":[
        {
            "category":"Restaurant",
            "type":"Food & Drink"
        }
    ],
    "sg:menulink":"http://www.allmenus.com/tx/mcallen-pharr/130834-subway/menu/",
    "sg:phone":"+1 956 618 0813",
    "sg:postcode":"78504",
    "sg:province":"TX",
    "sg:tags":[
        "american",
        "sandwich"
    ],
    "wof:name":"Subway",
    "wof:placetype":"venue"
},
  "geometry": {"coordinates":[-98.222065,26.250155],"type":"Point"}
}