{
  "type": "Feature",
  "properties": {
    "iso:country":"US",
    "sg:address":"3836 S Lancaster Rd",
    "sg:city":"Dallas",
    "sg:classifiers":[
        {
            "category":"Restaurant",
            "type":"Food & Drink"
        }
    ],
    "sg:phone":"+1 214 374 8660",
    "sg:postcode":"75216",
    "sg:province":"TX",
    "wof:name":"Harrell's Catfish & Jumbo Shrimp Take Home",
    "wof:placetype":"venue"
},
  "geometry": {"coordinates":[-96.79769899999999,32.7019],"type":"Point"}
}