{
  "type": "Feature",
  "properties": {
    "iso:country":"US",
    "sg:address":"304 Swisher Rd",
    "sg:city":"Lake Dallas",
    "sg:classifiers":[
        {
            "category":"Food & Beverages",
            "subcategory":"Liquor & Beverages",
            "type":"Retail Goods"
        }
    ],
    "sg:phone":"+1 940 498 4888",
    "sg:postcode":"75065",
    "sg:province":"TX",
    "sg:tags":[
        "alcoholic"
    ],
    "wof:name":"K J's Fine Wine & Spirits",
    "wof:placetype":"venue"
},
  "geometry": {"coordinates":[-97.03385400000001,33.129769],"type":"Point"}
}