{
  "type": "Feature",
  "properties": {
    "iso:country":"US",
    "sg:address":"2401 Pecan Ave",
    "sg:city":"Mcallen",
    "sg:classifiers":[
        {
            "category":"Personal",
            "subcategory":"Beauty Salon",
            "type":"Services"
        }
    ],
    "sg:phone":"+1 956 618 5220",
    "sg:postcode":"78501",
    "sg:province":"TX",
    "sg:tags":[
        "manicuring"
    ],
    "wof:name":"Nice Nails",
    "wof:placetype":"venue"
},
  "geometry": {"coordinates":[-98.24818999999999,26.219717],"type":"Point"}
}