{
  "type": "Feature",
  "properties": {
    "iso:country":"US",
    "sg:address":"1293 State Hwy 19",
    "sg:city":"Emory",
    "sg:classifiers":[
        {
            "category":"Government",
            "subcategory":"Office",
            "type":"Public Place"
        }
    ],
    "sg:phone":"+1 903 473 8783",
    "sg:postcode":"75440",
    "sg:province":"TX",
    "wof:name":"Rains County Precinct 1",
    "wof:placetype":"venue"
},
  "geometry": {"coordinates":[-95.768238,32.871227],"type":"Point"}
}