{
  "type": "Feature",
  "properties": {
    "iso:country":"US",
    "sg:address":"213 Alamogordo Dr",
    "sg:city":"Victoria",
    "sg:classifiers":[
        {
            "category":"Real Estate",
            "subcategory":"Real Estate Agent",
            "type":"Services"
        }
    ],
    "sg:phone":"+1 361 578 0011",
    "sg:postcode":"77904",
    "sg:province":"TX",
    "wof:name":"Moody Farm & Ranch Real Estate",
    "wof:placetype":"venue"
},
  "geometry": {"coordinates":[-96.95904400000001,28.837778],"type":"Point"}
}