{
  "type": "Feature",
  "properties": {
    "iso:country":"US",
    "sg:address":"4527 Nenana Dr",
    "sg:city":"Houston",
    "sg:classifiers":[
        {
            "category":"Real Estate",
            "subcategory":"Real Estate Agent",
            "type":"Services"
        }
    ],
    "sg:phone":"+1 713 729 7853",
    "sg:postcode":"77035",
    "sg:province":"TX",
    "wof:name":"Spica",
    "wof:placetype":"venue"
},
  "geometry": {"coordinates":[-95.454182,29.669911],"type":"Point"}
}