{
  "type": "Feature",
  "properties": {
    "iso:country":"US",
    "sg:address":"6812 K Ave",
    "sg:city":"Plano",
    "sg:classifiers":[
        {
            "category":"Real Estate",
            "subcategory":"Real Estate Agent",
            "type":"Services"
        }
    ],
    "sg:phone":"+1 972 423 0012",
    "sg:postcode":"75074",
    "sg:province":"TX",
    "wof:name":"Michael J Barr Inc",
    "wof:placetype":"venue"
},
  "geometry": {"coordinates":[-96.687314,33.066404],"type":"Point"}
}