{
  "type": "Feature",
  "properties": {
    "iso:country":"US",
    "sg:address":"5327 Marvin D Love Fwy",
    "sg:city":"Dallas",
    "sg:classifiers":[
        {
            "category":"Professional",
            "type":"Services"
        }
    ],
    "sg:phone":"+1 214 330 6021",
    "sg:postcode":"75232",
    "sg:province":"TX",
    "wof:name":"Misty Arterberry",
    "wof:placetype":"venue"
},
  "geometry": {"coordinates":[-96.856742,32.677739],"type":"Point"}
}