{
  "type": "Feature",
  "properties": {
    "iso:country":"US",
    "sg:address":"2024 Greenbriar Ln",
    "sg:city":"Plano",
    "sg:classifiers":[
        {
            "category":"Shopping",
            "subcategory":"Clothing, Apparel, & Fashions",
            "type":"Retail Goods"
        }
    ],
    "sg:phone":"+1 972 516 0806",
    "sg:postcode":"75074",
    "sg:province":"TX",
    "sg:tags":[
        "family"
    ],
    "wof:name":"Chudneys",
    "wof:placetype":"venue"
},
  "geometry": {"coordinates":[-96.670956,33.02779],"type":"Point"}
}