{
  "type": "Feature",
  "properties": {
    "iso:country":"US",
    "sg:address":"700 E 14th St",
    "sg:city":"Littlefield",
    "sg:classifiers":[
        {
            "category":"Social Services",
            "subcategory":"Child Care",
            "type":"Services"
        }
    ],
    "sg:phone":"+1 806 385 5667",
    "sg:postcode":"79339",
    "sg:province":"TX",
    "sg:tags":[
        "day"
    ],
    "wof:name":"Cox Janice Group Day Care",
    "wof:placetype":"venue"
},
  "geometry": {"coordinates":[-102.32884300000001,33.913415],"type":"Point"}
}