{
  "type": "Feature",
  "properties": {
    "iso:country":"US",
    "sg:address":"10655 Richmond Ave",
    "sg:city":"Houston",
    "sg:classifiers":[
        {
            "category":"Building & Trades",
            "subcategory":"Construction",
            "type":"Services"
        }
    ],
    "sg:phone":"+1 713 785 4141",
    "sg:postcode":"77042",
    "sg:province":"TX",
    "sg:tags":[
        "steel",
        "piping",
        "investment"
    ],
    "wof:name":"Mc 5 Operating Group LLC",
    "wof:placetype":"venue"
},
  "geometry": {"coordinates":[-95.563219,29.72771],"type":"Point"}
}