{
  "type": "Feature",
  "properties": {
    "iso:country":"US",
    "sg:address":"4909 Lakawana St",
    "sg:city":"Dallas",
    "sg:classifiers":[
        {
            "category":"Manufacturing",
            "subcategory":"Furniture",
            "type":"Manufacturing & Wholesale Goods"
        },
        {
            "category":"Manufacturing",
            "subcategory":"Rubber & Plastics",
            "type":"Manufacturing & Wholesale Goods"
        }
    ],
    "sg:phone":"+1 214 631 1460",
    "sg:postcode":"75247",
    "sg:province":"TX",
    "sg:tags":[
        "packaging",
        "fabricator",
        "foam",
        "bed"
    ],
    "wof:name":"American Foam Rubber LP",
    "wof:placetype":"venue"
},
  "geometry": {"coordinates":[-96.863257,32.806441],"type":"Point"}
}