{
  "type": "Feature",
  "properties": {
    "iso:country":"US",
    "sg:address":"10890 Sabo Rd",
    "sg:city":"Houston",
    "sg:classifiers":[
        {
            "category":"Building & Trades",
            "subcategory":"Construction",
            "type":"Services"
        }
    ],
    "sg:phone":"+1 281 484 7712",
    "sg:postcode":"77089",
    "sg:province":"TX",
    "sg:tags":[
        "contractor"
    ],
    "wof:name":"Willies Trash Hauling",
    "wof:placetype":"venue"
},
  "geometry": {"coordinates":[-95.22320999999999,29.612423],"type":"Point"}
}