{
  "type": "Feature",
  "properties": {
    "iso:country":"US",
    "sg:address":"3501 Palmer Hwy",
    "sg:city":"Texas City",
    "sg:classifiers":[
        {
            "category":"Restaurant",
            "type":"Food & Drink"
        }
    ],
    "sg:phone":"+1 409 945 3934",
    "sg:postcode":"77590",
    "sg:province":"TX",
    "sg:tags":[
        "eating"
    ],
    "wof:name":"China Border Restaurant Inc",
    "wof:placetype":"venue"
},
  "geometry": {"coordinates":[-94.94977400000001,29.395253],"type":"Point"}
}