{
  "type": "Feature",
  "properties": {
    "iso:country":"US",
    "sg:address":"13119 Rincon Dr",
    "sg:city":"Houston",
    "sg:classifiers":[
        {
            "category":"Professional",
            "subcategory":"Management & Consulting",
            "type":"Services"
        }
    ],
    "sg:phone":"+1 281 759 8068",
    "sg:postcode":"77077",
    "sg:province":"TX",
    "sg:tags":[
        "business"
    ],
    "wof:name":"Sorlen Healthcare Recruiting &",
    "wof:placetype":"venue"
},
  "geometry": {"coordinates":[-95.619455,29.741541],"type":"Point"}
}