{
  "type": "Feature",
  "properties": {
    "iso:country":"US",
    "sg:address":"614 Jerrys Ln",
    "sg:city":"Buda",
    "sg:classifiers":[
        {
            "category":"Manufacturing",
            "subcategory":"Electronics",
            "type":"Manufacturing & Wholesale Goods"
        }
    ],
    "sg:phone":"+1 512 312 1177",
    "sg:postcode":"78610",
    "sg:province":"TX",
    "sg:tags":[
        "printed",
        "mfg",
        "boards",
        "circuit",
        "etched"
    ],
    "wof:name":"HI-Tech Applications",
    "wof:placetype":"venue"
},
  "geometry": {"coordinates":[-97.88260099999999,30.110779],"type":"Point"}
}