{
  "type": "Feature",
  "properties": {
    "iso:country":"US",
    "sg:address":"131 Teal Ridge",
    "sg:city":"Canyon Lake",
    "sg:classifiers":[
        {
            "category":"Retail",
            "subcategory":"Repair Shop",
            "type":"Services"
        },
        {
            "category":"Building & Trades",
            "subcategory":"Plumbing",
            "type":"Services"
        }
    ],
    "sg:phone":"+1 830 907 2665",
    "sg:postcode":"78133",
    "sg:province":"TX",
    "sg:tags":[
        "equipment",
        "air",
        "conditioning",
        "contractor"
    ],
    "wof:name":"Blue Star Air Conditioning",
    "wof:placetype":"venue"
},
  "geometry": {"coordinates":[-98.11903,29.857949],"type":"Point"}
}