{
  "type": "Feature",
  "properties": {
    "iso:country":"US",
    "sg:address":"9817 Bissonnet St",
    "sg:city":"Houston",
    "sg:classifiers":[
        {
            "category":"Restaurant",
            "type":"Food & Drink"
        }
    ],
    "sg:phone":"+1 713 272 0022",
    "sg:postcode":"77036",
    "sg:province":"TX",
    "wof:name":"Al Bustan Restaurant & Club",
    "wof:placetype":"venue"
},
  "geometry": {"coordinates":[-95.551787,29.675143],"type":"Point"}
}