{
  "type": "Feature",
  "properties": {
    "iso:country":"US",
    "sg:address":"1509 Quartet Dr",
    "sg:city":"Dallas",
    "sg:classifiers":[
        {
            "category":"Insurance",
            "subcategory":"Insurance Agent",
            "type":"Services"
        }
    ],
    "sg:phone":"+1 214 372 6247",
    "sg:postcode":"75241",
    "sg:province":"TX",
    "wof:name":"Noel & Co Insurance Agency",
    "wof:placetype":"venue"
},
  "geometry": {"coordinates":[-96.80042899999999,32.66666],"type":"Point"}
}