{
  "type": "Feature",
  "properties": {
    "iso:country":"US",
    "sg:address":"221 State Hwy 243",
    "sg:city":"Canton",
    "sg:classifiers":[
        {
            "category":"Building & Trades",
            "subcategory":"Equipment Rental",
            "type":"Services"
        }
    ],
    "sg:phone":"+1 903 567 2266",
    "sg:postcode":"75103",
    "sg:province":"TX",
    "wof:name":"Ace Rental Place",
    "wof:placetype":"venue"
},
  "geometry": {"coordinates":[-95.86546199999999,32.544178],"type":"Point"}
}