{
  "type": "Feature",
  "properties": {
    "iso:country":"US",
    "sg:address":"8421 Industrial Dr",
    "sg:city":"Pearland",
    "sg:classifiers":[
        {
            "category":"Mining & Drilling",
            "type":"Manufacturing & Wholesale Goods"
        }
    ],
    "sg:phone":"+1 281 648 1560",
    "sg:postcode":"77584",
    "sg:province":"TX",
    "sg:tags":[
        "field"
    ],
    "wof:name":"Key Energy Services Inc",
    "wof:placetype":"venue"
},
  "geometry": {"coordinates":[-95.269924,29.528647],"type":"Point"}
}