{
  "type": "Feature",
  "properties": {
    "iso:country":"US",
    "sg:address":"9811 Slide Rd",
    "sg:city":"Lubbock",
    "sg:classifiers":[
        {
            "category":"Autos & Motor Vehicles",
            "subcategory":"Automobile Sales",
            "type":"Retail Goods"
        },
        {
            "category":"Manufacturing",
            "subcategory":"Glass & Minerals",
            "type":"Manufacturing & Wholesale Goods"
        },
        {
            "category":"Retail",
            "subcategory":"Auto Repair",
            "type":"Services"
        }
    ],
    "sg:phone":"+1 806 794 5500",
    "sg:postcode":"79424",
    "sg:province":"TX",
    "sg:tags":[
        "plate",
        "automotive",
        "equipment-service",
        "window",
        "equipment",
        "glass-auto",
        "balancing",
        "wheels-aligning",
        "brake",
        "air conditioning",
        "tune"
    ],
    "sg:website":"http://www.daltonsautomotiveandtire.com",
    "wof:name":"Dalton's Automotive & Tire Center",
    "wof:placetype":"venue"
},
  "geometry": {"coordinates":[-101.92234500000001,33.502912],"type":"Point"}
}