{
  "type": "Feature",
  "properties": {
    "iso:country":"US",
    "sg:address":"108 S Austin Dr",
    "sg:city":"Pharr",
    "sg:classifiers":[
        {
            "category":"Transit Center",
            "subcategory":"Freight",
            "type":"Transportation"
        }
    ],
    "sg:phone":"+1 956 223 2566",
    "sg:postcode":"78577",
    "sg:province":"TX",
    "sg:tags":[
        "forklift",
        "truck"
    ],
    "wof:name":"Pharr South",
    "wof:placetype":"venue"
},
  "geometry": {"coordinates":[-98.20137,26.104549],"type":"Point"}
}