{
  "type": "Feature",
  "properties": {
    "iso:country":"US",
    "sg:address":"1020 E 7th St",
    "sg:city":"Houston",
    "sg:classifiers":[
        {
            "category":"Professional",
            "type":"Services"
        }
    ],
    "sg:phone":"+1 713 426 5009",
    "sg:postcode":"77009",
    "sg:province":"TX",
    "wof:name":"Seagate Townhomes Tract 3",
    "wof:placetype":"venue"
},
  "geometry": {"coordinates":[-95.38566899999999,29.783406],"type":"Point"}
}