{
  "type": "Feature",
  "properties": {
    "iso:country":"US",
    "sg:address":"830 Marimba Dr",
    "sg:city":"El Paso",
    "sg:classifiers":[
        {
            "category":"Professional",
            "subcategory":"Business Services",
            "type":"Services"
        }
    ],
    "sg:phone":"+1 915 584 2988",
    "sg:postcode":"79912",
    "sg:province":"TX",
    "wof:name":"Safety Management Solutions",
    "wof:placetype":"venue"
},
  "geometry": {"coordinates":[-106.55410500000001,31.82369],"type":"Point"}
}