{
  "type": "Feature",
  "properties": {
    "iso:country":"US",
    "sg:address":"17524 Bishopsgate Dr",
    "sg:city":"Pflugerville",
    "sg:classifiers":[
        {
            "category":"Personal",
            "type":"Services"
        }
    ],
    "sg:phone":"+1 512 422 2535",
    "sg:postcode":"78660",
    "sg:province":"TX",
    "wof:name":"Austin Wedding & Events",
    "wof:placetype":"venue"
},
  "geometry": {"coordinates":[-97.640587,30.464585],"type":"Point"}
}