{
  "type": "Feature",
  "properties": {
    "iso:country":"US",
    "sg:address":"2617 Commerce Street",
    "sg:city":"Dallas",
    "sg:classifiers":[
        {
            "category":"Arts & Performance",
            "subcategory":"Jazz & Blues",
            "type":"Entertainment"
        }
    ],
    "sg:phone":"+1 214 744 2583",
    "sg:postcode":"75226",
    "sg:province":"TX",
    "wof:name":"Tuckers' Blues",
    "wof:placetype":"venue"
},
  "geometry": {"coordinates":[-96.785432,32.782787],"type":"Point"}
}