{
  "type": "Feature",
  "properties": {
    "iso:country":"US",
    "sg:address":"782 E I- 30",
    "sg:city":"Rockwall",
    "sg:classifiers":[
        {
            "category":"Health Services",
            "subcategory":"Optometrist",
            "type":"Services"
        }
    ],
    "sg:phone":"+1 972 772 6189",
    "sg:postcode":"75043",
    "sg:province":"TX",
    "wof:name":"Yeh Doctor & Assoc",
    "wof:placetype":"venue"
},
  "geometry": {"coordinates":[-96.56616099999999,32.852017],"type":"Point"}
}