{
  "type": "Feature",
  "properties": {
    "iso:country":"US",
    "sg:address":"1128 Rhonda Lee St",
    "sg:city":"Copperas Cove",
    "sg:classifiers":[
        {
            "category":"Building & Trades",
            "subcategory":"Landscaping Services",
            "type":"Services"
        }
    ],
    "sg:phone":"+1 254 542 8725",
    "sg:postcode":"76522",
    "sg:province":"TX",
    "wof:name":"Carters Lawn Service",
    "wof:placetype":"venue"
},
  "geometry": {"coordinates":[-97.931594,31.117022],"type":"Point"}
}