{
  "type": "Feature",
  "properties": {
    "iso:country":"US",
    "sg:address":"2009 McKenzie Dr Ste 130",
    "sg:city":"Carrollton",
    "sg:classifiers":[
        {
            "category":"Shopping",
            "subcategory":"Mobile Phones",
            "type":"Retail Goods"
        }
    ],
    "sg:phone":"+1 214 295 2000",
    "sg:postcode":"75006",
    "sg:province":"TX",
    "wof:name":"Pyramid Comm",
    "wof:placetype":"venue"
},
  "geometry": {"coordinates":[-96.91814599999999,32.937607],"type":"Point"}
}