{
  "type": "Feature",
  "properties": {
    "iso:country":"US",
    "sg:address":"5019 McKinney Ave",
    "sg:city":"Dallas",
    "sg:classifiers":[
        {
            "category":"Wholesale",
            "subcategory":"Machinery & Supplies",
            "type":"Manufacturing & Wholesale Goods"
        }
    ],
    "sg:phone":"+1 214 522 4755",
    "sg:postcode":"75205",
    "sg:province":"TX",
    "sg:tags":[
        "field",
        "oil",
        "equipment"
    ],
    "sg:website":"www.hri-rig.com",
    "wof:name":"Heartland Rig",
    "wof:placetype":"venue"
},
  "geometry": {"coordinates":[-96.784283,32.828119],"type":"Point"}
}