{
  "type": "Feature",
  "properties": {
    "iso:country":"US",
    "sg:address":"2116 Windrock St",
    "sg:city":"El Paso",
    "sg:classifiers":[
        {
            "category":"Professional",
            "type":"Services"
        }
    ],
    "sg:phone":"+1 915 598 0807",
    "sg:postcode":"79925",
    "sg:province":"TX",
    "wof:name":"Pat Denham Artist",
    "wof:placetype":"venue"
},
  "geometry": {"coordinates":[-106.346913,31.772248],"type":"Point"}
}