{
  "type": "Feature",
  "properties": {
    "iso:country":"US",
    "sg:address":"15157 Fm 2015",
    "sg:city":"Tyler",
    "sg:classifiers":[
        {
            "category":"Shopping",
            "subcategory":"Beauty & Cosmetics",
            "type":"Retail Goods"
        }
    ],
    "sg:phone":"+1 903 877 9234",
    "sg:postcode":"75706",
    "sg:province":"TX",
    "sg:tags":[
        "salons-equipment",
        "supply"
    ],
    "wof:name":"Sally Wade",
    "wof:placetype":"venue"
},
  "geometry": {"coordinates":[-95.21781300000001,32.484872],"type":"Point"}
}