{
  "type": "Feature",
  "properties": {
    "iso:country":"US",
    "sg:address":"7444 Calhoun Rd",
    "sg:city":"Houston",
    "sg:classifiers":[
        {
            "category":"Wholesale",
            "subcategory":"Machinery & Supplies",
            "type":"Manufacturing & Wholesale Goods"
        }
    ],
    "sg:phone":"+1 713 733 5700",
    "sg:postcode":"77033",
    "sg:province":"TX",
    "sg:tags":[
        "hardware",
        "industrial",
        "marine"
    ],
    "wof:name":"Samco Sales  Inc",
    "wof:placetype":"venue"
},
  "geometry": {"coordinates":[-95.352692,29.677169],"type":"Point"}
}