{
  "type": "Feature",
  "properties": {
    "iso:country":"US",
    "sg:address":"4703 Burnet Rd",
    "sg:city":"Austin",
    "sg:classifiers":[
        {
            "category":"Retail",
            "subcategory":"Repair Shop",
            "type":"Services"
        }
    ],
    "sg:phone":"+1 512 791 9673",
    "sg:postcode":"78756",
    "sg:province":"TX",
    "sg:tags":[
        "related"
    ],
    "wof:name":"Grambo Sharpening Systems",
    "wof:placetype":"venue"
},
  "geometry": {"coordinates":[-97.73957,30.318416],"type":"Point"}
}