{
  "type": "Feature",
  "properties": {
    "iso:country":"US",
    "sg:address":"3803 Kermit Hwy",
    "sg:city":"Odessa",
    "sg:classifiers":[
        {
            "category":"Professional",
            "subcategory":"Management & Consulting",
            "type":"Services"
        }
    ],
    "sg:phone":"+1 432 334 8523",
    "sg:postcode":"79764",
    "sg:province":"TX",
    "sg:tags":[
        "establishment",
        "business"
    ],
    "wof:name":"Donaldson Fire & Safety Inc",
    "wof:placetype":"venue"
},
  "geometry": {"coordinates":[-102.41281499999999,31.872475],"type":"Point"}
}