{
  "type": "Feature",
  "properties": {
    "iso:country":"US",
    "sg:address":"12180 N Mo Pac Expy",
    "sg:city":"Austin",
    "sg:classifiers":[
        {
            "category":"Health Services",
            "subcategory":"Doctor",
            "type":"Services"
        }
    ],
    "sg:phone":"+1 512 617 6767",
    "sg:postcode":"78758",
    "sg:province":"TX",
    "wof:name":"NESC",
    "wof:placetype":"venue"
},
  "geometry": {"coordinates":[-97.708761,30.413199],"type":"Point"}
}