{
  "type": "Feature",
  "properties": {
    "iso:country":"US",
    "sg:address":"1101 Southmore Blvd",
    "sg:city":"Houston",
    "sg:classifiers":[
        {
            "category":"Shopping",
            "subcategory":"Jewelry",
            "type":"Retail Goods"
        }
    ],
    "sg:phone":"+1 713 477 4786",
    "sg:postcode":"77004",
    "sg:province":"TX",
    "wof:name":"Silver Time",
    "wof:placetype":"venue"
},
  "geometry": {"coordinates":[-95.38571899999999,29.727477],"type":"Point"}
}