{
  "type": "Feature",
  "properties": {
    "iso:country":"US",
    "sg:address":"1505 Avenue E",
    "sg:city":"Levelland",
    "sg:classifiers":[
        {
            "category":"Personal",
            "subcategory":"Beauty Salon",
            "type":"Services"
        }
    ],
    "sg:phone":"+1 806 897 4728",
    "sg:postcode":"79336",
    "sg:province":"TX",
    "sg:tags":[
        "shop"
    ],
    "wof:name":"Leanns",
    "wof:placetype":"venue"
},
  "geometry": {"coordinates":[-102.374061,33.577331],"type":"Point"}
}