{
  "type": "Feature",
  "properties": {
    "iso:country":"US",
    "sg:address":"507 Grindstone Rd",
    "sg:city":"Weatherford",
    "sg:classifiers":[
        {
            "category":"Wholesale",
            "subcategory":"Machinery & Supplies",
            "type":"Manufacturing & Wholesale Goods"
        }
    ],
    "sg:phone":"+1 817 599 8130",
    "sg:postcode":"76462",
    "sg:province":"TX",
    "sg:tags":[
        "industrial"
    ],
    "wof:name":"Frank Howeth",
    "wof:placetype":"venue"
},
  "geometry": {"coordinates":[-97.953317,32.668047],"type":"Point"}
}