{
  "type": "Feature",
  "properties": {
    "iso:country":"US",
    "sg:address":"16643 Castle Fraser Dr",
    "sg:city":"Houston",
    "sg:classifiers":[
        {
            "category":"Building & Trades",
            "subcategory":"Cleaning & Sanitation",
            "type":"Services"
        }
    ],
    "sg:phone":"+1 281 550 8903",
    "sg:postcode":"77084",
    "sg:province":"TX",
    "sg:tags":[
        "maintenance"
    ],
    "wof:name":"McPs Commercial Cleaning Serv",
    "wof:placetype":"venue"
},
  "geometry": {"coordinates":[-95.653181,29.851583],"type":"Point"}
}