{
  "type": "Feature",
  "properties": {
    "iso:country":"US",
    "sg:address":"700 Quail Creek Dr",
    "sg:city":"Amarillo",
    "sg:classifiers":[
        {
            "category":"Health Services",
            "subcategory":"Doctor",
            "type":"Services"
        }
    ],
    "sg:phone":"+1 806 353 6691",
    "sg:postcode":"79124",
    "sg:province":"TX",
    "sg:tags":[
        "physician",
        "surgeon",
        "medical"
    ],
    "wof:name":"Pan Handle Eye Group",
    "wof:placetype":"venue"
},
  "geometry": {"coordinates":[-101.911315,35.212171],"type":"Point"}
}