{
  "type": "Feature",
  "properties": {
    "iso:country":"US",
    "sg:address":"6911 Burgess St",
    "sg:city":"Houston",
    "sg:classifiers":[
        {
            "category":"Building & Trades",
            "subcategory":"Construction",
            "type":"Services"
        }
    ],
    "sg:phone":"+1 713 748 6314",
    "sg:postcode":"77021",
    "sg:province":"TX",
    "sg:tags":[
        "marble",
        "terrazzo"
    ],
    "wof:name":"F Ketner & Co",
    "wof:placetype":"venue"
},
  "geometry": {"coordinates":[-95.383855,29.70121],"type":"Point"}
}