{
  "type": "Feature",
  "properties": {
    "iso:country":"US",
    "sg:address":"9902 Emmett F Lowry Expy",
    "sg:city":"Texas City",
    "sg:classifiers":[
        {
            "category":"Food & Beverages",
            "subcategory":"Groceries & Convenience Stores",
            "type":"Retail Goods"
        }
    ],
    "sg:phone":"+1 409 986 9210",
    "sg:postcode":"77591",
    "sg:province":"TX",
    "wof:name":"Chevron Apsi No 650 Inc",
    "wof:placetype":"venue"
},
  "geometry": {"coordinates":[-95.01858199999999,29.401537],"type":"Point"}
}