{
  "type": "Feature",
  "properties": {
    "iso:country":"US",
    "sg:address":"114 N Zaragoza Rd",
    "sg:city":"El Paso",
    "sg:classifiers":[
        {
            "category":"Wholesale",
            "subcategory":"Electrical",
            "type":"Manufacturing & Wholesale Goods"
        }
    ],
    "sg:phone":"+1 915 860 0644",
    "sg:postcode":"79907",
    "sg:province":"TX",
    "sg:tags":[
        "control",
        "security",
        "system"
    ],
    "wof:name":"Azar Security Svc",
    "wof:placetype":"venue"
},
  "geometry": {"coordinates":[-106.327887,31.692857],"type":"Point"}
}