{
  "type": "Feature",
  "properties": {
    "iso:country":"US",
    "sg:address":"4130 Apollo St",
    "sg:city":"Houston",
    "sg:classifiers":[
        {
            "category":"Communications",
            "subcategory":"Radio Station",
            "type":"Services"
        }
    ],
    "sg:phone":"+1 713 683 0051",
    "sg:postcode":"77018",
    "sg:province":"TX",
    "sg:tags":[
        "broadcast"
    ],
    "wof:name":"FM Black Athletic Booster",
    "wof:placetype":"venue"
},
  "geometry": {"coordinates":[-95.428325,29.825644],"type":"Point"}
}