{
  "type": "Feature",
  "properties": {
    "iso:country":"US",
    "sg:address":"7809 Summerglen Rd",
    "sg:city":"Fort Worth",
    "sg:classifiers":[
        {
            "category":"Communications",
            "subcategory":"Film & Video Production",
            "type":"Services"
        }
    ],
    "sg:phone":"+1 817 346 6345",
    "sg:postcode":"76133",
    "sg:province":"TX",
    "sg:tags":[
        "taping"
    ],
    "wof:name":"Mew West Screenworks",
    "wof:placetype":"venue"
},
  "geometry": {"coordinates":[-97.38413799999999,32.629312],"type":"Point"}
}