{
  "type": "Feature",
  "properties": {
    "iso:country":"US",
    "sg:address":"401 S Starkweather St",
    "sg:city":"Pampa",
    "sg:classifiers":[
        {
            "category":"Freight",
            "type":"Transportation"
        }
    ],
    "sg:phone":"+1 806 665 1045",
    "sg:postcode":"79065",
    "sg:province":"TX",
    "sg:tags":[
        "commercial",
        "storage"
    ],
    "wof:name":"Triangle Mini-Storage",
    "wof:placetype":"venue"
},
  "geometry": {"coordinates":[-100.95486,35.535221],"type":"Point"}
}