{
  "type": "Feature",
  "properties": {
    "iso:country":"US",
    "sg:address":"20131 US Hwy 59",
    "sg:city":"Humble",
    "sg:classifiers":[
        {
            "category":"Restaurant",
            "type":"Food & Drink"
        }
    ],
    "sg:phone":"+1 281 446 4275",
    "sg:postcode":"77338",
    "sg:province":"TX",
    "sg:tags":[
        "delicatessen"
    ],
    "wof:name":"Frullati",
    "wof:placetype":"venue"
},
  "geometry": {"coordinates":[-95.26742,30.007204],"type":"Point"}
}