{
  "type": "Feature",
  "properties": {
    "iso:country":"US",
    "sg:address":"5100 Oshea St",
    "sg:city":"El Paso",
    "sg:classifiers":[
        {
            "category":"Home & Garden",
            "subcategory":"Building Materials",
            "type":"Retail Goods"
        }
    ],
    "sg:phone":"+1 915 852 0634",
    "sg:postcode":"79938",
    "sg:province":"TX",
    "sg:tags":[
        "shutter"
    ],
    "sg:website":"www.jcshutters.com",
    "wof:name":"J C & Co",
    "wof:placetype":"venue"
},
  "geometry": {"coordinates":[-106.157815,31.829741],"type":"Point"}
}