{
  "type": "Feature",
  "properties": {
    "iso:country":"US",
    "sg:address":"6627 Snider Plz",
    "sg:city":"Dallas",
    "sg:classifiers":[
        {
            "category":"Food & Beverages",
            "subcategory":"Bakery",
            "type":"Retail Goods"
        }
    ],
    "sg:phone":"+1 214 373 6455",
    "sg:postcode":"75205",
    "sg:province":"TX",
    "wof:name":"Dough Kids Inc",
    "wof:placetype":"venue"
},
  "geometry": {"coordinates":[-96.787843,32.847348],"type":"Point"}
}