{
  "type": "Feature",
  "properties": {
    "iso:country":"US",
    "sg:address":"143 Valley Dr",
    "sg:city":"Huntsville",
    "sg:classifiers":[
        {
            "category":"Building & Trades",
            "subcategory":"Plumbing",
            "type":"Services"
        }
    ],
    "sg:phone":"+1 936 435 0641",
    "sg:postcode":"77320",
    "sg:province":"TX",
    "sg:tags":[
        "repair",
        "electrical"
    ],
    "wof:name":"D Ws Cool Air",
    "wof:placetype":"venue"
},
  "geometry": {"coordinates":[-95.458,30.762537],"type":"Point"}
}