{
  "type": "Feature",
  "properties": {
    "iso:country":"US",
    "sg:address":"42 Hideaway Dr",
    "sg:city":"Friendswood",
    "sg:classifiers":[
        {
            "category":"Building & Trades",
            "subcategory":"Construction",
            "type":"Services"
        }
    ],
    "sg:phone":"+1 281 482 1220",
    "sg:postcode":"77546",
    "sg:province":"TX",
    "sg:tags":[
        "equipment",
        "installing"
    ],
    "wof:name":"Technical Installation MA",
    "wof:placetype":"venue"
},
  "geometry": {"coordinates":[-95.19138700000001,29.517418],"type":"Point"}
}