{
  "type": "Feature",
  "properties": {
    "iso:country":"US",
    "sg:address":"7 Marina Dr",
    "sg:city":"Montgomery",
    "sg:classifiers":[
        {
            "category":"Real Estate",
            "subcategory":"Developer",
            "type":"Services"
        }
    ],
    "sg:phone":"+1 936 447 4664",
    "sg:postcode":"77356",
    "sg:province":"TX",
    "wof:name":"Benchmark Development Co",
    "wof:placetype":"venue"
},
  "geometry": {"coordinates":[-95.59175,30.36345],"type":"Point"}
}