{
  "type": "Feature",
  "properties": {
    "iso:country":"US",
    "sg:address":"7031 Kingston Cove Ln",
    "sg:city":"Willis",
    "sg:classifiers":[
        {
            "category":"Professional",
            "type":"Services"
        }
    ],
    "sg:phone":"+1 936 890 1279",
    "sg:postcode":"77318",
    "sg:province":"TX",
    "wof:name":"Milestone Energy Capital LLC",
    "wof:placetype":"venue"
},
  "geometry": {"coordinates":[-95.568071,30.403247],"type":"Point"}
}