{
  "type": "Feature",
  "properties": {
    "iso:country":"US",
    "sg:address":"309 NW 1st St",
    "sg:city":"Morton",
    "sg:classifiers":[
        {
            "category":"Wholesale",
            "subcategory":"Farm Supplies",
            "type":"Manufacturing & Wholesale Goods"
        },
        {
            "category":"Shopping",
            "type":"Retail Goods"
        }
    ],
    "sg:phone":"+1 806 266 5461",
    "sg:postcode":"79346",
    "sg:province":"TX",
    "sg:tags":[
        "feed",
        "lumber",
        "merchandise"
    ],
    "wof:name":"Lewis Farm & Ranch",
    "wof:placetype":"venue"
},
  "geometry": {"coordinates":[-102.760406,33.728161],"type":"Point"}
}