{
  "type": "Feature",
  "properties": {
    "iso:country":"US",
    "sg:address":"7604 Oak St",
    "sg:city":"Frisco",
    "sg:classifiers":[
        {
            "category":"Professional",
            "subcategory":"Business Services",
            "type":"Services"
        }
    ],
    "sg:phone":"+1 972 335 0032",
    "sg:postcode":"75034",
    "sg:province":"TX",
    "wof:name":"Abx Assoc Business Xchange",
    "wof:placetype":"venue"
},
  "geometry": {"coordinates":[-96.82064699999999,33.151056],"type":"Point"}
}