{
  "type": "Feature",
  "properties": {
    "iso:country":"US",
    "sg:address":"208 Henry St",
    "sg:city":"Dallas",
    "sg:classifiers":[
        {
            "category":"Food & Beverages",
            "subcategory":"Groceries & Convenience Stores",
            "type":"Retail Goods"
        }
    ],
    "sg:phone":"+1 214 939 3663",
    "sg:postcode":"75226",
    "sg:province":"TX",
    "wof:name":"Henry Street Market",
    "wof:placetype":"venue"
},
  "geometry": {"coordinates":[-96.784513,32.78254],"type":"Point"}
}