{
  "type": "Feature",
  "properties": {
    "iso:country":"US",
    "sg:address":"707 15th St",
    "sg:city":"Shallowater",
    "sg:classifiers":[
        {
            "category":"Building & Trades",
            "subcategory":"Construction",
            "type":"Services"
        }
    ],
    "sg:phone":"+1 806 786 0468",
    "sg:postcode":"79363",
    "sg:province":"TX",
    "sg:tags":[
        "house"
    ],
    "wof:name":"T G C Home Builders",
    "wof:placetype":"venue"
},
  "geometry": {"coordinates":[-101.996208,33.696531],"type":"Point"}
}