{
  "type": "Feature",
  "properties": {
    "iso:country":"US",
    "sg:address":"3352 E T C Jester Blvd",
    "sg:city":"Houston",
    "sg:classifiers":[
        {
            "category":"Restaurant",
            "type":"Food & Drink"
        }
    ],
    "sg:phone":"+1 713 688 6467",
    "sg:postcode":"77018",
    "sg:province":"TX",
    "wof:name":"Subway Sandwiches & Salads",
    "wof:placetype":"venue"
},
  "geometry": {"coordinates":[-95.444199,29.8186],"type":"Point"}
}