{
  "type": "Feature",
  "properties": {
    "iso:country":"US",
    "sg:address":"247 Circle Way St",
    "sg:city":"Lake Jackson",
    "sg:classifiers":[
        {
            "category":"Professional",
            "subcategory":"Art Services",
            "type":"Services"
        },
        {
            "category":"Manufacturing",
            "subcategory":"Printing",
            "type":"Manufacturing & Wholesale Goods"
        }
    ],
    "sg:phone":"+1 979 297 9494",
    "sg:postcode":"77566",
    "sg:province":"TX",
    "sg:tags":[
        "printer",
        "commercial",
        "specialty",
        "offset",
        "advertising"
    ],
    "wof:name":"Foto Grafics",
    "wof:placetype":"venue"
},
  "geometry": {"coordinates":[-95.447402,29.038572],"type":"Point"}
}