{
  "type": "Feature",
  "properties": {
    "iso:country":"US",
    "sg:address":"5911 Tuskegee St",
    "sg:city":"Houston",
    "sg:classifiers":[
        {
            "category":"Freight",
            "type":"Transportation"
        }
    ],
    "sg:phone":"+1 713 697 4332",
    "sg:postcode":"77091",
    "sg:province":"TX",
    "sg:tags":[
        "operator",
        "local",
        "trucking"
    ],
    "wof:name":"Burnell Assured Delivery",
    "wof:placetype":"venue"
},
  "geometry": {"coordinates":[-95.426092,29.852374],"type":"Point"}
}