{
  "type": "Feature",
  "properties": {
    "iso:country":"US",
    "sg:address":"6810 W University Blvd",
    "sg:city":"Odessa",
    "sg:classifiers":[
        {
            "category":"Autos & Motor Vehicles",
            "subcategory":"Automobile Sales",
            "type":"Retail Goods"
        }
    ],
    "sg:phone":"+1 432 381 2232",
    "sg:postcode":"79764",
    "sg:province":"TX",
    "sg:tags":[
        "car",
        "dealer"
    ],
    "wof:name":"Jame's Auto Sales",
    "wof:placetype":"venue"
},
  "geometry": {"coordinates":[-102.459457,31.850705],"type":"Point"}
}