{
  "type": "Feature",
  "properties": {
    "iso:country":"US",
    "sg:address":"3903 E Jasmine St",
    "sg:city":"Pearland",
    "sg:classifiers":[
        {
            "category":"Professional",
            "subcategory":"Detective & Security Services",
            "type":"Services"
        }
    ],
    "sg:phone":"+1 281 485 0055",
    "sg:postcode":"77581",
    "sg:province":"TX",
    "sg:tags":[
        "investigator"
    ],
    "wof:name":"Jim A Mckendree & Assoc Rl Est",
    "wof:placetype":"venue"
},
  "geometry": {"coordinates":[-95.286046,29.565689],"type":"Point"}
}