{
  "type": "Feature",
  "properties": {
    "iso:country":"US",
    "sg:address":"16222 Cairnway Dr",
    "sg:city":"Houston",
    "sg:classifiers":[
        {
            "category":"Recreation",
            "type":"Entertainment"
        }
    ],
    "sg:phone":"+1 281 859 0108",
    "sg:postcode":"77084",
    "sg:province":"TX",
    "sg:tags":[
        "pool",
        "swimming"
    ],
    "wof:name":"Glencairn Community Improvemnt",
    "wof:placetype":"venue"
},
  "geometry": {"coordinates":[-95.645894,29.841299],"type":"Point"}
}