{
  "type": "Feature",
  "properties": {
    "iso:country":"US",
    "sg:address":"2401 Hawthorne Dr",
    "sg:city":"Amarillo",
    "sg:classifiers":[
        {
            "category":"Professional",
            "type":"Services"
        }
    ],
    "sg:phone":"+1 806 353 5495",
    "sg:postcode":"79109",
    "sg:province":"TX",
    "wof:name":"Pat Menke",
    "wof:placetype":"venue"
},
  "geometry": {"coordinates":[-101.862877,35.182711],"type":"Point"}
}