{
  "type": "Feature",
  "properties": {
    "iso:country":"US",
    "sg:address":"3316 Westwind Dr",
    "sg:city":"Plano",
    "sg:classifiers":[
        {
            "category":"Professional",
            "subcategory":"Management & Consulting",
            "type":"Services"
        }
    ],
    "sg:phone":"+1 972 398 2727",
    "sg:postcode":"75093",
    "sg:province":"TX",
    "sg:tags":[
        "business"
    ],
    "wof:name":"Gemini Trdg & Consulting LLC",
    "wof:placetype":"venue"
},
  "geometry": {"coordinates":[-96.835679,33.046009],"type":"Point"}
}