{
  "type": "Feature",
  "properties": {
    "iso:country":"US",
    "sg:address":"516 W Hopkins St",
    "sg:city":"San Marcos",
    "sg:classifiers":[
        {
            "category":"Real Estate",
            "subcategory":"Surveying",
            "type":"Services"
        }
    ],
    "sg:phone":"+1 512 392 1719",
    "sg:postcode":"78666",
    "sg:province":"TX",
    "sg:tags":[
        "surveyor"
    ],
    "wof:name":"Ash & Assoc Surveying & Mappin",
    "wof:placetype":"venue"
},
  "geometry": {"coordinates":[-97.94625499999999,29.881995],"type":"Point"}
}