{
  "type": "Feature",
  "properties": {
    "iso:country":"US",
    "sg:address":"701 SW Georgia Ave",
    "sg:city":"Sweetwater",
    "sg:classifiers":[
        {
            "category":"Organizations",
            "subcategory":"Community Association",
            "type":"Services"
        }
    ],
    "sg:phone":"+1 325 236 8158",
    "sg:postcode":"79556",
    "sg:province":"TX",
    "sg:tags":[
        "club"
    ],
    "wof:name":"5 O'Clock Somewhere Club",
    "wof:placetype":"venue"
},
  "geometry": {"coordinates":[-100.41026100000001,32.447397],"type":"Point"}
}