{
  "type": "Feature",
  "properties": {
    "iso:country":"US",
    "sg:address":"2123 W Colorado Blvd",
    "sg:city":"Dallas",
    "sg:classifiers":[
        {
            "category":"Personal",
            "subcategory":"Barber",
            "type":"Services"
        }
    ],
    "sg:phone":"+1 214 941 1201",
    "sg:postcode":"75211",
    "sg:province":"TX",
    "wof:name":"Frank's Barber Shop",
    "wof:placetype":"venue"
},
  "geometry": {"coordinates":[-96.85838,32.76083],"type":"Point"}
}