{
  "type": "Feature",
  "properties": {
    "iso:country":"US",
    "sg:address":"7701 N Stemmons Fwy",
    "sg:city":"Dallas",
    "sg:classifiers":[
        {
            "category":"Government",
            "subcategory":"Office",
            "type":"Public Place"
        }
    ],
    "sg:phone":"+1 214 905 5277",
    "sg:postcode":"75247",
    "sg:province":"TX",
    "sg:tags":[
        "general"
    ],
    "wof:name":"Acd",
    "wof:placetype":"venue"
},
  "geometry": {"coordinates":[-96.87204300000001,32.824248],"type":"Point"}
}