{
  "type": "Feature",
  "properties": {
    "iso:country":"US",
    "sg:address":"3901 Liberty Rd",
    "sg:city":"Houston",
    "sg:classifiers":[
        {
            "category":"Personal",
            "subcategory":"Barber",
            "type":"Services"
        }
    ],
    "sg:phone":"+1 713 675 1243",
    "sg:postcode":"77026",
    "sg:province":"TX",
    "sg:tags":[
        "shop"
    ],
    "wof:name":"Heavenly Hands Barber Shop",
    "wof:placetype":"venue"
},
  "geometry": {"coordinates":[-95.33103,29.784916],"type":"Point"}
}