{
  "type": "Feature",
  "properties": {
    "iso:country":"US",
    "sg:address":"805 Washington Ter",
    "sg:city":"Fort Worth",
    "sg:classifiers":[
        {
            "category":"Government",
            "subcategory":"Office",
            "type":"Public Place"
        }
    ],
    "sg:phone":"+1 817 543 1000",
    "sg:postcode":"76107",
    "sg:province":"TX",
    "wof:name":"Congressman Joe Barton",
    "wof:placetype":"venue"
},
  "geometry": {"coordinates":[-97.379295,32.750658],"type":"Point"}
}