{
  "type": "Feature",
  "properties": {
    "iso:country":"US",
    "sg:address":"611 E Tyler St",
    "sg:city":"Athens",
    "sg:classifiers":[
        {
            "category":"Professional",
            "subcategory":"Accounting & Tax Preparation",
            "type":"Services"
        }
    ],
    "sg:phone":"+1 903 677 6221",
    "sg:postcode":"75751",
    "sg:province":"TX",
    "sg:website":"http://www.txuenergyservices.com",
    "wof:name":"Txu",
    "wof:placetype":"venue"
},
  "geometry": {"coordinates":[-95.8467,32.205769],"type":"Point"}
}