{
  "type": "Feature",
  "properties": {
    "iso:country":"US",
    "sg:address":"55 Lyerly St",
    "sg:city":"Houston",
    "sg:classifiers":[
        {
            "category":"Manufacturing",
            "subcategory":"Signs",
            "type":"Manufacturing & Wholesale Goods"
        }
    ],
    "sg:phone":"+1 713 694 0665",
    "sg:postcode":"77022",
    "sg:province":"TX",
    "sg:tags":[
        "specialty",
        "mfg"
    ],
    "wof:name":"Sign Concepts",
    "wof:placetype":"venue"
},
  "geometry": {"coordinates":[-95.37786800000001,29.834795],"type":"Point"}
}