{
  "type": "Feature",
  "properties": {
    "iso:country":"US",
    "sg:address":"3713 Finley Rd",
    "sg:city":"Irving",
    "sg:classifiers":[
        {
            "category":"Professional",
            "type":"Services"
        }
    ],
    "sg:phone":"+1 214 441 0105",
    "sg:postcode":"75062",
    "sg:province":"TX",
    "wof:name":"Exonicle Corp",
    "wof:placetype":"venue"
},
  "geometry": {"coordinates":[-96.99606300000001,32.851334],"type":"Point"}
}