{
  "type": "Feature",
  "properties": {
    "iso:country":"US",
    "sg:address":"5406 NE 24th Ave",
    "sg:city":"Amarillo",
    "sg:classifiers":[
        {
            "category":"Wholesale",
            "subcategory":"Construction Materials",
            "type":"Manufacturing & Wholesale Goods"
        }
    ],
    "sg:phone":"+1 806 381 9981",
    "sg:postcode":"79107",
    "sg:province":"TX",
    "sg:tags":[
        "fence"
    ],
    "wof:name":"Ennis Fence Co",
    "wof:placetype":"venue"
},
  "geometry": {"coordinates":[-101.771928,35.236334],"type":"Point"}
}