{
  "type": "Feature",
  "properties": {
    "iso:country":"US",
    "sg:address":"5800 Granite Pkwy",
    "sg:city":"Plano",
    "sg:classifiers":[
        {
            "category":"Building & Trades",
            "subcategory":"Plumbing",
            "type":"Services"
        }
    ],
    "sg:phone":"+1 972 731 2610",
    "sg:postcode":"75024",
    "sg:province":"TX",
    "sg:tags":[
        "product",
        "management",
        "energy",
        "system"
    ],
    "wof:name":"Energy Comparisions",
    "wof:placetype":"venue"
},
  "geometry": {"coordinates":[-96.817476,33.087017],"type":"Point"}
}