{
  "type": "Feature",
  "properties": {
    "iso:country":"US",
    "sg:address":"5220 Canal St",
    "sg:city":"Houston",
    "sg:classifiers":[
        {
            "category":"Professional",
            "subcategory":"Management & Consulting",
            "type":"Services"
        }
    ],
    "sg:phone":"+1 713 923 6182",
    "sg:postcode":"77011",
    "sg:province":"TX",
    "sg:tags":[
        "consultant",
        "real estate"
    ],
    "wof:name":"Tid Syphrett",
    "wof:placetype":"venue"
},
  "geometry": {"coordinates":[-95.321707,29.7464],"type":"Point"}
}