{
  "type": "Feature",
  "properties": {
    "iso:country":"US",
    "sg:address":"401 4th St",
    "sg:city":"Graham",
    "sg:classifiers":[
        {
            "category":"Building & Trades",
            "subcategory":"Equipment Rental",
            "type":"Services"
        }
    ],
    "sg:phone":"+1 940 549 0206",
    "sg:postcode":"76450",
    "sg:province":"TX",
    "sg:tags":[
        "field",
        "oil"
    ],
    "wof:name":"Graham Equipment Manufacturing",
    "wof:placetype":"venue"
},
  "geometry": {"coordinates":[-98.592918,33.106972],"type":"Point"}
}