{
  "type": "Feature",
  "properties": {
    "iso:country":"US",
    "sg:address":"201 Garvon St",
    "sg:city":"Garland",
    "sg:classifiers":[
        {
            "category":"Retail",
            "subcategory":"Auto Repair",
            "type":"Services"
        }
    ],
    "sg:phone":"+1 972 276 2630",
    "sg:postcode":"75040",
    "sg:province":"TX",
    "sg:tags":[
        "machine",
        "shop",
        "custom",
        "automotive"
    ],
    "wof:name":"Kart Connection",
    "wof:placetype":"venue"
},
  "geometry": {"coordinates":[-96.62692699999999,32.913559],"type":"Point"}
}