{
  "type": "Feature",
  "properties": {
    "iso:country":"US",
    "sg:address":"600 Congress Ave",
    "sg:city":"Austin",
    "sg:classifiers":[
        {
            "category":"Professional",
            "subcategory":"Lawyer & Legal Services",
            "type":"Services"
        }
    ],
    "sg:phone":"+1 512 495 8521",
    "sg:postcode":"78701",
    "sg:province":"TX",
    "sg:tags":[
        "attorney"
    ],
    "wof:name":"Drew Di Novo",
    "wof:placetype":"venue"
},
  "geometry": {"coordinates":[-97.74247099999999,30.268966],"type":"Point"}
}