{
  "type": "Feature",
  "properties": {
    "iso:country":"US",
    "sg:address":"1122 E 51st Street",
    "sg:city":"Austin",
    "sg:classifiers":[
        {
            "category":"Shopping",
            "subcategory":"Crafts & Fabrics",
            "type":"Retail Goods"
        }
    ],
    "sg:phone":"+1 512 380 9929",
    "sg:postcode":"78723",
    "sg:province":"TX",
    "sg:tags":[
        "store"
    ],
    "wof:name":"High Fashion Decorative Fabrics",
    "wof:placetype":"venue"
},
  "geometry": {"coordinates":[-97.70893,30.308541],"type":"Point"}
}