{
  "type": "Feature",
  "properties": {
    "iso:country":"US",
    "sg:address":"1112 W Walker St",
    "sg:city":"Breckenridge",
    "sg:classifiers":[
        {
            "category":"Professional",
            "subcategory":"Accounting & Tax Preparation",
            "type":"Services"
        }
    ],
    "sg:phone":"+1 254 559 1756",
    "sg:postcode":"76424",
    "sg:province":"TX",
    "sg:tags":[
        "return"
    ],
    "wof:name":"A-Quick Refund",
    "wof:placetype":"venue"
},
  "geometry": {"coordinates":[-98.915554,32.755455],"type":"Point"}
}