{
  "type": "Feature",
  "properties": {
    "iso:country":"US",
    "sg:address":"4229 Creekdale Dr",
    "sg:city":"Dallas",
    "sg:classifiers":[
        {
            "category":"Banks & Credit Unions",
            "subcategory":"Financial Services",
            "type":"Services"
        }
    ],
    "sg:phone":"+1 214 350 0352",
    "sg:postcode":"75229",
    "sg:province":"TX",
    "sg:tags":[
        "investor"
    ],
    "wof:name":"Creekdale Investments Inc",
    "wof:placetype":"venue"
},
  "geometry": {"coordinates":[-96.83708900000001,32.891073],"type":"Point"}
}