{
  "type": "Feature",
  "properties": {
    "iso:country":"US",
    "sg:address":"6526 Ashton",
    "sg:city":"Houston",
    "sg:classifiers":[
        {
            "category":"Retail",
            "subcategory":"Repair Shop",
            "type":"Services"
        }
    ],
    "sg:phone":"+1 713 686 8726",
    "sg:postcode":"77091",
    "sg:province":"TX",
    "wof:name":"McCoys Irrigation & Drai",
    "wof:placetype":"venue"
},
  "geometry": {"coordinates":[-95.45997800000001,29.857439],"type":"Point"}
}