{
  "type": "Feature",
  "properties": {
    "iso:country":"US",
    "sg:address":"2402 Wilkes Dr",
    "sg:city":"Colleyville",
    "sg:classifiers":[
        {
            "category":"Wholesale",
            "subcategory":"Stationery",
            "type":"Manufacturing & Wholesale Goods"
        },
        {
            "category":"Manufacturing",
            "subcategory":"Printing",
            "type":"Manufacturing & Wholesale Goods"
        }
    ],
    "sg:phone":"+1 817 251 8528",
    "sg:postcode":"76034",
    "sg:province":"TX",
    "sg:tags":[
        "cards",
        "commercial",
        "greeting",
        "supply"
    ],
    "wof:name":"Portal Publications Ltd",
    "wof:placetype":"venue"
},
  "geometry": {"coordinates":[-97.130295,32.907734],"type":"Point"}
}