{
  "type": "Feature",
  "properties": {
    "iso:country":"US",
    "sg:address":"103 S Beaton St",
    "sg:city":"Corsicana",
    "sg:classifiers":[
        {
            "category":"Wholesale",
            "subcategory":"Machinery & Supplies",
            "type":"Manufacturing & Wholesale Goods"
        }
    ],
    "sg:phone":"+1 903 872 2541",
    "sg:postcode":"75110",
    "sg:province":"TX",
    "sg:tags":[
        "janitor"
    ],
    "wof:name":"Corsicana Chemical Co",
    "wof:placetype":"venue"
},
  "geometry": {"coordinates":[-96.463531,32.09363],"type":"Point"}
}