{
  "type": "Feature",
  "properties": {
    "iso:country":"US",
    "sg:address":"3610 W Jefferson Blvd",
    "sg:city":"Dallas",
    "sg:classifiers":[
        {
            "category":"Restaurant",
            "type":"Food & Drink"
        }
    ],
    "sg:phone":"+1 214 331 9202",
    "sg:postcode":"75211",
    "sg:province":"TX",
    "sg:tags":[
        "chinese"
    ],
    "wof:name":"China Express",
    "wof:placetype":"venue"
},
  "geometry": {"coordinates":[-96.87949999999999,32.740002],"type":"Point"}
}