{
  "type": "Feature",
  "properties": {
    "iso:country":"US",
    "sg:address":"5151 US Hwy 290",
    "sg:city":"Austin",
    "sg:classifiers":[
        {
            "category":"Shopping",
            "type":"Retail Goods"
        }
    ],
    "sg:phone":"+1 512 891 0896",
    "sg:postcode":"78735",
    "sg:province":"TX",
    "sg:tags":[
        "merchandise"
    ],
    "wof:name":"B A Framer",
    "wof:placetype":"venue"
},
  "geometry": {"coordinates":[-97.83130800000001,30.236361],"type":"Point"}
}