{
  "type": "Feature",
  "properties": {
    "iso:country":"US",
    "sg:address":"15532 East Fwy",
    "sg:city":"Channelview",
    "sg:classifiers":[
        {
            "category":"Retail",
            "subcategory":"Auto Repair",
            "type":"Services"
        }
    ],
    "sg:phone":"+1 281 452 9200",
    "sg:postcode":"77530",
    "sg:province":"TX",
    "sg:tags":[
        "body",
        "shop"
    ],
    "wof:name":"Competition Collision",
    "wof:placetype":"venue"
},
  "geometry": {"coordinates":[-95.131897,29.775801],"type":"Point"}
}