{
  "type": "Feature",
  "properties": {
    "iso:country":"US",
    "sg:address":"7870 Woodsman Trl",
    "sg:city":"Houston",
    "sg:classifiers":[
        {
            "category":"Freight",
            "type":"Transportation"
        }
    ],
    "sg:phone":"+1 713 466 4984",
    "sg:postcode":"77040",
    "sg:province":"TX",
    "sg:tags":[
        "trucking"
    ],
    "wof:name":"Zavala David Reyes & Frances",
    "wof:placetype":"venue"
},
  "geometry": {"coordinates":[-95.510654,29.885164],"type":"Point"}
}