{
  "type": "Feature",
  "properties": {
    "iso:country":"US",
    "sg:address":"9703 Village Basin",
    "sg:city":"San Antonio",
    "sg:classifiers":[
        {
            "category":"Restaurant",
            "type":"Food & Drink"
        }
    ],
    "sg:phone":"+1 210 523 5124",
    "sg:postcode":"78250",
    "sg:province":"TX",
    "sg:tags":[
        "tanner",
        "eating"
    ],
    "wof:name":"Wallhangers Taxidermy Studio",
    "wof:placetype":"venue"
},
  "geometry": {"coordinates":[-98.689892,29.503625],"type":"Point"}
}