{
  "type": "Feature",
  "properties": {
    "iso:country":"US",
    "sg:address":"110 W Main St",
    "sg:city":"Madisonville",
    "sg:classifiers":[
        {
            "category":"Shopping",
            "subcategory":"Bicycles & Sporting Goods",
            "type":"Retail Goods"
        }
    ],
    "sg:phone":"+1 936 348 9600",
    "sg:postcode":"77864",
    "sg:province":"TX",
    "sg:tags":[
        "repair"
    ],
    "wof:name":"Sportsman Guns Ammo",
    "wof:placetype":"venue"
},
  "geometry": {"coordinates":[-95.91378899999999,30.949084],"type":"Point"}
}