{
  "type": "Feature",
  "properties": {
    "iso:country":"US",
    "sg:address":"4508 San Pedro Ave",
    "sg:city":"San Antonio",
    "sg:classifiers":[
        {
            "category":"Wholesale",
            "subcategory":"Motor Vehicles",
            "type":"Manufacturing & Wholesale Goods"
        }
    ],
    "sg:phone":"+1 210 732 8188",
    "sg:postcode":"78212",
    "sg:province":"TX",
    "sg:tags":[
        "auto"
    ],
    "wof:name":"Montalbo Auto Sales Inc",
    "wof:placetype":"venue"
},
  "geometry": {"coordinates":[-98.499222,29.475145],"type":"Point"}
}