{
  "type": "Feature",
  "properties": {
    "iso:country":"US",
    "sg:address":"6729 Braeburn Dr",
    "sg:city":"Dallas",
    "sg:classifiers":[
        {
            "category":"Manufacturing",
            "subcategory":"Metals",
            "type":"Manufacturing & Wholesale Goods"
        }
    ],
    "sg:phone":"+1 214 887 8481",
    "sg:postcode":"75214",
    "sg:province":"TX",
    "sg:tags":[
        "specialty"
    ],
    "wof:name":"Square J Industries",
    "wof:placetype":"venue"
},
  "geometry": {"coordinates":[-96.74489699999999,32.840898],"type":"Point"}
}