{
  "type": "Feature",
  "properties": {
    "iso:country":"US",
    "sg:address":"1128 N Galloway Ave",
    "sg:city":"Mesquite",
    "sg:classifiers":[
        {
            "category":"Health Services",
            "subcategory":"Optometrist",
            "type":"Services"
        }
    ],
    "sg:phone":"+1 972 288 4427",
    "sg:postcode":"75149",
    "sg:province":"TX",
    "wof:name":"Park Suzan Od",
    "wof:placetype":"venue"
},
  "geometry": {"coordinates":[-96.599926,32.779459],"type":"Point"}
}