{
  "type": "Feature",
  "properties": {
    "iso:country":"US",
    "sg:address":"1737 Pat Booker Rd",
    "sg:city":"Universal City",
    "sg:classifiers":[
        {
            "category":"Wholesale",
            "subcategory":"Electrical",
            "type":"Manufacturing & Wholesale Goods"
        }
    ],
    "sg:phone":"+1 210 659 1971",
    "sg:postcode":"78148",
    "sg:province":"TX",
    "sg:tags":[
        "electric",
        "motor"
    ],
    "wof:name":"Chadwell Motors Co",
    "wof:placetype":"venue"
},
  "geometry": {"coordinates":[-98.30891699999999,29.553339],"type":"Point"}
}