{
  "type": "Feature",
  "properties": {
    "iso:country":"US",
    "sg:address":"3711 Pear Meadow Ln",
    "sg:city":"Houston",
    "sg:classifiers":[
        {
            "category":"Restaurant",
            "type":"Food & Drink"
        }
    ],
    "sg:phone":"+1 281 590 5353",
    "sg:postcode":"77039",
    "sg:province":"TX",
    "sg:tags":[
        "eating"
    ],
    "wof:name":"19th Hole Pub & Grill",
    "wof:placetype":"venue"
},
  "geometry": {"coordinates":[-95.33441999999999,29.896952],"type":"Point"}
}