{
  "type": "Feature",
  "properties": {
    "iso:country":"US",
    "sg:address":"3559 Williams Rd",
    "sg:city":"Fort Worth",
    "sg:classifiers":[
        {
            "category":"Organizations",
            "subcategory":"Religious Organization",
            "type":"Services"
        }
    ],
    "sg:phone":"+1 817 560 7518",
    "sg:postcode":"76116",
    "sg:province":"TX",
    "wof:name":"Bethel Christian Fellowship",
    "wof:placetype":"venue"
},
  "geometry": {"coordinates":[-97.450965,32.722529],"type":"Point"}
}