{
  "type": "Feature",
  "properties": {
    "iso:country":"US",
    "sg:address":"4309 S Co Rd 1290",
    "sg:city":"Odessa",
    "sg:classifiers":[
        {
            "category":"Wholesale",
            "subcategory":"Machinery & Supplies",
            "type":"Manufacturing & Wholesale Goods"
        }
    ],
    "sg:phone":"+1 432 563 8004",
    "sg:postcode":"79765",
    "sg:province":"TX",
    "wof:name":"Accent Granite & Marble",
    "wof:placetype":"venue"
},
  "geometry": {"coordinates":[-102.231207,31.904234],"type":"Point"}
}