{
  "type": "Feature",
  "properties": {
    "iso:country":"US",
    "sg:address":"2675 Tranquil Trl",
    "sg:city":"Brownsville",
    "sg:classifiers":[
        {
            "category":"Professional",
            "subcategory":"Business Services",
            "type":"Services"
        }
    ],
    "sg:phone":"+1 956 371 9990",
    "sg:postcode":"78521",
    "sg:province":"TX",
    "sg:tags":[
        "consultant",
        "coach"
    ],
    "wof:name":"Viceroy Consulting",
    "wof:placetype":"venue"
},
  "geometry": {"coordinates":[-97.47693,25.943204],"type":"Point"}
}