{
  "type": "Feature",
  "properties": {
    "iso:country":"US",
    "sg:address":"1406 Opal Rd",
    "sg:city":"Killeen",
    "sg:classifiers":[
        {
            "category":"Personal",
            "type":"Services"
        }
    ],
    "sg:phone":"+1 254 699 5520",
    "sg:postcode":"76543",
    "sg:province":"TX",
    "wof:name":"Dove Productions",
    "wof:placetype":"venue"
},
  "geometry": {"coordinates":[-97.711883,31.096878],"type":"Point"}
}