{
  "type": "Feature",
  "properties": {
    "iso:country":"US",
    "sg:address":"828 Highland Village Rd",
    "sg:city":"Lewisville",
    "sg:classifiers":[
        {
            "category":"Real Estate",
            "subcategory":"Real Estate Agent",
            "type":"Services"
        }
    ],
    "sg:phone":"+1 972 317 1200",
    "sg:postcode":"75077",
    "sg:province":"TX",
    "wof:name":"Testa Annette Real Estate",
    "wof:placetype":"venue"
},
  "geometry": {"coordinates":[-97.046741,33.093627],"type":"Point"}
}