{
  "type": "Feature",
  "properties": {
    "iso:country":"US",
    "sg:address":"2141 N Josey Ln",
    "sg:city":"Carrollton",
    "sg:classifiers":[
        {
            "category":"Retail",
            "subcategory":"Portrait Studio",
            "type":"Services"
        },
        {
            "category":"Shopping",
            "subcategory":"Pharmacy",
            "type":"Retail Goods"
        }
    ],
    "sg:phone":"+1 972 323 1115",
    "sg:postcode":"75006",
    "sg:province":"TX",
    "sg:tags":[
        "photography",
        "drugstore",
        "store"
    ],
    "wof:name":"Walgreens the Pharmacy America Trusts",
    "wof:placetype":"venue"
},
  "geometry": {"coordinates":[-96.89009900000001,32.9762],"type":"Point"}
}