{
  "type": "Feature",
  "properties": {
    "iso:country":"US",
    "sg:address":"75 Cottonwood Rd",
    "sg:city":"Trinity",
    "sg:classifiers":[
        {
            "category":"Utilities",
            "subcategory":"Water",
            "type":"Services"
        }
    ],
    "sg:phone":"+1 936 594 3411",
    "sg:postcode":"75862",
    "sg:province":"TX",
    "sg:tags":[
        "company-utility",
        "system",
        "supply"
    ],
    "wof:name":"Westwood Shores Municipal Utility District",
    "wof:placetype":"venue"
},
  "geometry": {"coordinates":[-95.324944,30.94741],"type":"Point"}
}