{
  "type": "Feature",
  "properties": {
    "iso:country":"US",
    "sg:address":"1802 US Hwy 281 Bus",
    "sg:city":"Edinburg",
    "sg:classifiers":[
        {
            "category":"Building & Trades",
            "subcategory":"Construction",
            "type":"Services"
        }
    ],
    "sg:phone":"+1 956 386 1742",
    "sg:postcode":"78541",
    "sg:province":"TX",
    "sg:tags":[
        "builder",
        "operative",
        "contractor"
    ],
    "wof:name":"Commercial Roofing Systems",
    "wof:placetype":"venue"
},
  "geometry": {"coordinates":[-98.15897099999999,26.320581],"type":"Point"}
}