{
  "type": "Feature",
  "properties": {
    "iso:country":"US",
    "sg:address":"1508 Sheridan Trl",
    "sg:city":"Cedar Park",
    "sg:classifiers":[
        {
            "category":"Professional",
            "type":"Services"
        }
    ],
    "sg:phone":"+1 512 258 2699",
    "sg:postcode":"78613",
    "sg:province":"TX",
    "wof:name":"Sundog Studio",
    "wof:placetype":"venue"
},
  "geometry": {"coordinates":[-97.82026,30.472167],"type":"Point"}
}