{
  "type": "Feature",
  "properties": {
    "iso:country":"US",
    "sg:address":"1192 Lazar Dr",
    "sg:city":"Eagle Pass",
    "sg:classifiers":[
        {
            "category":"Shopping",
            "subcategory":"Jewelry",
            "type":"Retail Goods"
        }
    ],
    "sg:phone":"+1 830 758 1209",
    "sg:postcode":"78852",
    "sg:province":"TX",
    "wof:name":"Touch of Gold",
    "wof:placetype":"venue"
},
  "geometry": {"coordinates":[-100.48339199999999,28.690675],"type":"Point"}
}