{
  "type": "Feature",
  "properties": {
    "iso:country":"US",
    "sg:address":"1713 Quebec Ave",
    "sg:city":"Mcallen",
    "sg:classifiers":[
        {
            "category":"Home & Garden",
            "subcategory":"Furniture",
            "type":"Retail Goods"
        }
    ],
    "sg:phone":"+1 956 686 8963",
    "sg:postcode":"78503",
    "sg:province":"TX",
    "wof:name":"Designers Warehouse",
    "wof:placetype":"venue"
},
  "geometry": {"coordinates":[-98.240928,26.190034],"type":"Point"}
}