{
  "type": "Feature",
  "properties": {
    "iso:country":"US",
    "sg:address":"7318 Foxway Ln",
    "sg:city":"Humble",
    "sg:classifiers":[
        {
            "category":"Personal",
            "type":"Services"
        }
    ],
    "sg:phone":"+1 281 548 0080",
    "sg:postcode":"77338",
    "sg:province":"TX",
    "wof:name":"Event Coordinating By Divinity",
    "wof:placetype":"venue"
},
  "geometry": {"coordinates":[-95.31287399999999,30.010946],"type":"Point"}
}