{
  "type": "Feature",
  "properties": {
    "iso:country":"US",
    "sg:address":"1313 Campbell Rd",
    "sg:city":"Houston",
    "sg:classifiers":[
        {
            "category":"Banks & Credit Unions",
            "subcategory":"Bank",
            "type":"Services"
        }
    ],
    "sg:phone":"+1 713 365 9104",
    "sg:postcode":"77055",
    "sg:province":"TX",
    "sg:tags":[
        "correspondent",
        "banker",
        "mortgage"
    ],
    "wof:name":"Southwest Guaranty",
    "wof:placetype":"venue"
},
  "geometry": {"coordinates":[-95.513993,29.79192],"type":"Point"}
}