{
  "type": "Feature",
  "properties": {
    "iso:country":"US",
    "sg:address":"947 Green Castle Dr",
    "sg:city":"Dallas",
    "sg:classifiers":[
        {
            "category":"Shopping",
            "subcategory":"Clothing, Apparel, & Fashions",
            "type":"Retail Goods"
        }
    ],
    "sg:phone":"+1 214 372 5005",
    "sg:postcode":"75232",
    "sg:province":"TX",
    "sg:tags":[
        "family"
    ],
    "wof:name":"M Andretti",
    "wof:placetype":"venue"
},
  "geometry": {"coordinates":[-96.837926,32.689078],"type":"Point"}
}