{
  "type": "Feature",
  "properties": {
    "iso:country":"US",
    "sg:address":"16801 Westgrove Dr",
    "sg:city":"Addison",
    "sg:classifiers":[
        {
            "category":"Government",
            "subcategory":"Office",
            "type":"Public Place"
        }
    ],
    "sg:phone":"+1 972 450 2840",
    "sg:postcode":"75001",
    "sg:province":"TX",
    "sg:tags":[
        "township",
        "government-city",
        "village"
    ],
    "sg:website":"http://www.addisonairport.net",
    "wof:name":"Street Dept",
    "wof:placetype":"venue"
},
  "geometry": {"coordinates":[-96.838882,32.980014],"type":"Point"}
}