{
  "type": "Feature",
  "properties": {
    "iso:country":"US",
    "sg:address":"500 E Alexander St",
    "sg:city":"Three Rivers",
    "sg:classifiers":[
        {
            "category":"Home & Garden",
            "subcategory":"Building Materials",
            "type":"Retail Goods"
        }
    ],
    "sg:phone":"+1 361 786 3886",
    "sg:postcode":"78071",
    "sg:province":"TX",
    "sg:tags":[
        "lumber"
    ],
    "wof:name":"Stapleton Construction",
    "wof:placetype":"venue"
},
  "geometry": {"coordinates":[-98.17779400000001,28.460752],"type":"Point"}
}