{
  "type": "Feature",
  "properties": {
    "iso:country":"US",
    "sg:address":"1014 Timber Elm",
    "sg:city":"Seguin",
    "sg:classifiers":[
        {
            "category":"Building & Trades",
            "subcategory":"Landscaping Services",
            "type":"Services"
        }
    ],
    "sg:phone":"+1 830 560 2114",
    "sg:postcode":"78155",
    "sg:province":"TX",
    "wof:name":"Dd Enterprises",
    "wof:placetype":"venue"
},
  "geometry": {"coordinates":[-98.03833299999999,29.621659],"type":"Point"}
}