{
  "type": "Feature",
  "properties": {
    "iso:country":"US",
    "sg:address":"1201 W American Blvd",
    "sg:city":"Muleshoe",
    "sg:classifiers":[
        {
            "category":"Restaurant",
            "type":"Food & Drink"
        }
    ],
    "sg:phone":"+1 806 272 4333",
    "sg:postcode":"79347",
    "sg:province":"TX",
    "wof:name":"Taqueria Guadalajara",
    "wof:placetype":"venue"
},
  "geometry": {"coordinates":[-102.73616,34.233247],"type":"Point"}
}