{
  "type": "Feature",
  "properties": {
    "iso:country":"US",
    "sg:address":"809 Olympic Dr",
    "sg:city":"Pflugerville",
    "sg:classifiers":[
        {
            "category":"Professional",
            "subcategory":"Management & Consulting",
            "type":"Services"
        }
    ],
    "sg:phone":"+1 512 670 2479",
    "sg:postcode":"78660",
    "sg:province":"TX",
    "sg:tags":[
        "retail",
        "direct",
        "sales"
    ],
    "wof:name":"L2r2 Company",
    "wof:placetype":"venue"
},
  "geometry": {"coordinates":[-97.631409,30.432508],"type":"Point"}
}