{
  "type": "Feature",
  "properties": {
    "iso:country":"US",
    "sg:address":"240 Harper Rd",
    "sg:city":"Kerrville",
    "sg:classifiers":[
        {
            "category":"Professional",
            "subcategory":"Accounting & Tax Preparation",
            "type":"Services"
        }
    ],
    "sg:phone":"+1 830 896 7736",
    "sg:postcode":"78028",
    "sg:province":"TX",
    "sg:tags":[
        "bookkeeping",
        "general"
    ],
    "wof:name":"Bookkeeping Plus",
    "wof:placetype":"venue"
},
  "geometry": {"coordinates":[-99.160865,30.06313],"type":"Point"}
}