{
  "type": "Feature",
  "properties": {
    "iso:country":"US",
    "sg:address":"1906 Canyon Springs Dr",
    "sg:city":"Belton",
    "sg:classifiers":[
        {
            "category":"Professional",
            "subcategory":"Management & Consulting",
            "type":"Services"
        }
    ],
    "sg:phone":"+1 254 939 3604",
    "sg:postcode":"76513",
    "sg:province":"TX",
    "wof:name":"Delegram & Assoc",
    "wof:placetype":"venue"
},
  "geometry": {"coordinates":[-97.467963,31.101892],"type":"Point"}
}