{
  "type": "Feature",
  "properties": {
    "iso:country":"US",
    "sg:address":"7919 Gulf Fwy",
    "sg:city":"Houston",
    "sg:classifiers":[
        {
            "category":"Home & Garden",
            "subcategory":"Carpets & Floor Coverings",
            "type":"Retail Goods"
        }
    ],
    "sg:phone":"+1 713 644 8453",
    "sg:postcode":"77017",
    "sg:province":"TX",
    "sg:tags":[
        "material"
    ],
    "wof:name":"Budget Tile",
    "wof:placetype":"venue"
},
  "geometry": {"coordinates":[-95.254724,29.657163],"type":"Point"}
}