{
  "type": "Feature",
  "properties": {
    "iso:country":"US",
    "sg:address":"970 N Coit Rd",
    "sg:city":"Richardson",
    "sg:classifiers":[
        {
            "category":"Health Services",
            "subcategory":"Doctor",
            "type":"Services"
        }
    ],
    "sg:phone":"+1 972 235 2459",
    "sg:postcode":"75080",
    "sg:province":"TX",
    "sg:tags":[
        "physician",
        "surgeon"
    ],
    "wof:name":"Grace Medical Assoc",
    "wof:placetype":"venue"
},
  "geometry": {"coordinates":[-96.76886500000001,32.959803],"type":"Point"}
}