{
  "type": "Feature",
  "properties": {
    "iso:country":"US",
    "sg:address":"1275 N Main St",
    "sg:city":"Mansfield",
    "sg:classifiers":[
        {
            "category":"Building & Trades",
            "subcategory":"Plumbing",
            "type":"Services"
        }
    ],
    "sg:phone":"+1 817 473 3531",
    "sg:postcode":"76063",
    "sg:province":"TX",
    "sg:tags":[
        "contractor"
    ],
    "wof:name":"Baughman Plumbing Co Inc",
    "wof:placetype":"venue"
},
  "geometry": {"coordinates":[-97.151173,32.580365],"type":"Point"}
}