{
  "type": "Feature",
  "properties": {
    "iso:country":"US",
    "sg:address":"300 Early Blvd",
    "sg:city":"Brownwood",
    "sg:classifiers":[
        {
            "category":"Cinema",
            "subcategory":"Movie Rental",
            "type":"Entertainment"
        }
    ],
    "sg:phone":"+1 325 649 9640",
    "sg:postcode":"76802",
    "sg:province":"TX",
    "sg:tags":[
        "video",
        "game",
        "leasing"
    ],
    "wof:name":"F X Video Game Exchange",
    "wof:placetype":"venue"
},
  "geometry": {"coordinates":[-98.961753,31.735778],"type":"Point"}
}