{
  "type": "Feature",
  "properties": {
    "iso:country":"US",
    "sg:address":"4949 W Orem Dr",
    "sg:city":"Houston",
    "sg:classifiers":[
        {
            "category":"Health Services",
            "subcategory":"Doctor",
            "type":"Services"
        }
    ],
    "sg:phone":"+1 713 433 4177",
    "sg:postcode":"77045",
    "sg:province":"TX",
    "sg:tags":[
        "medical"
    ],
    "wof:name":"Medcare Urgent Care System",
    "wof:placetype":"venue"
},
  "geometry": {"coordinates":[-95.456459,29.627299],"type":"Point"}
}