{
  "type": "Feature",
  "properties": {
    "iso:country":"US",
    "sg:address":"1237 County Road 219",
    "sg:city":"Cameron",
    "sg:classifiers":[
        {
            "category":"Professional",
            "subcategory":"Detective & Security Services",
            "type":"Services"
        }
    ],
    "sg:phone":"+1 254 697 4130",
    "sg:postcode":"76520",
    "sg:province":"TX",
    "sg:tags":[
        "information",
        "bureau"
    ],
    "wof:name":"Mine Service Cameron Plant",
    "wof:placetype":"venue"
},
  "geometry": {"coordinates":[-97.018186,30.801071],"type":"Point"}
}