{
  "type": "Feature",
  "properties": {
    "iso:country":"US",
    "sg:address":"5757 Guhn Rd",
    "sg:city":"Houston",
    "sg:classifiers":[
        {
            "category":"Arts & Performance",
            "subcategory":"Theater",
            "type":"Entertainment"
        }
    ],
    "sg:phone":"+1 713 895 8789",
    "sg:postcode":"77040",
    "sg:province":"TX",
    "sg:tags":[
        "bureau"
    ],
    "wof:name":"NAS Productions",
    "wof:placetype":"venue"
},
  "geometry": {"coordinates":[-95.51518900000001,29.85004],"type":"Point"}
}