{
  "type": "Feature",
  "properties": {
    "iso:country":"US",
    "sg:address":"2603 Woodlands Dr",
    "sg:city":"Killeen",
    "sg:classifiers":[
        {
            "category":"Food & Beverages",
            "subcategory":"Specialty",
            "type":"Retail Goods"
        }
    ],
    "sg:phone":"+1 254 290 1909",
    "sg:postcode":"76549",
    "sg:province":"TX",
    "sg:tags":[
        "child",
        "day",
        "care"
    ],
    "wof:name":"Tiny Bubbles",
    "wof:placetype":"venue"
},
  "geometry": {"coordinates":[-97.766237,31.104889],"type":"Point"}
}