{
  "type": "Feature",
  "properties": {
    "iso:country":"US",
    "sg:address":"13510 Carruth Ln",
    "sg:city":"Houston",
    "sg:classifiers":[
        {
            "category":"Professional",
            "subcategory":"Management & Consulting",
            "type":"Services"
        }
    ],
    "sg:phone":"+1 281 983 5330",
    "sg:postcode":"77083",
    "sg:province":"TX",
    "wof:name":"Digital Connections",
    "wof:placetype":"venue"
},
  "geometry": {"coordinates":[-95.622281,29.70575],"type":"Point"}
}