{
  "type": "Feature",
  "properties": {
    "iso:country":"US",
    "sg:address":"402 W Travis St",
    "sg:city":"Holland",
    "sg:classifiers":[
        {
            "category":"Education",
            "subcategory":"Library",
            "type":"Public Place"
        }
    ],
    "sg:phone":"+1 254 657 2884",
    "sg:postcode":"76534",
    "sg:province":"TX",
    "wof:name":"B J Hill Library",
    "wof:placetype":"venue"
},
  "geometry": {"coordinates":[-97.40879099999999,30.880484],"type":"Point"}
}