{
  "type": "Feature",
  "properties": {
    "iso:country":"US",
    "sg:address":"3010 Whisper Lark St",
    "sg:city":"San Antonio",
    "sg:classifiers":[
        {
            "category":"Health Services",
            "subcategory":"Clinic",
            "type":"Services"
        }
    ],
    "sg:phone":"+1 210 692 1268",
    "sg:postcode":"78230",
    "sg:province":"TX",
    "sg:tags":[
        "organization",
        "medical",
        "surgical"
    ],
    "wof:name":"International Horizons",
    "wof:placetype":"venue"
},
  "geometry": {"coordinates":[-98.543626,29.542263],"type":"Point"}
}