{
  "type": "Feature",
  "properties": {
    "iso:country":"US",
    "sg:address":"15730 State Hwy 29",
    "sg:city":"Liberty Hill",
    "sg:classifiers":[
        {
            "category":"Manufacturing",
            "subcategory":"Building Materials",
            "type":"Manufacturing & Wholesale Goods"
        },
        {
            "category":"Home & Garden",
            "subcategory":"Furniture",
            "type":"Retail Goods"
        }
    ],
    "sg:phone":"+1 512 778 5540",
    "sg:postcode":"78642",
    "sg:province":"TX",
    "sg:tags":[
        "cabinet",
        "wood",
        "kitchen",
        "mfg"
    ],
    "wof:name":"Eric Hanson Cabinets & Woodwor",
    "wof:placetype":"venue"
},
  "geometry": {"coordinates":[-97.94237099999999,30.677047],"type":"Point"}
}