{
  "type": "Feature",
  "properties": {
    "iso:country":"US",
    "sg:address":"203 This Way",
    "sg:city":"Lake Jackson",
    "sg:classifiers":[
        {
            "category":"Banks & Credit Unions",
            "subcategory":"Bank",
            "type":"Services"
        }
    ],
    "sg:phone":"+1 979 233 4401",
    "sg:postcode":"77566",
    "sg:province":"TX",
    "wof:name":"Texas Gulf Bank",
    "wof:placetype":"venue"
},
  "geometry": {"coordinates":[-95.450429,29.040433],"type":"Point"}
}