{
  "type": "Feature",
  "properties": {
    "iso:country":"US",
    "sg:address":"905 River Oaks Dr",
    "sg:city":"Austin",
    "sg:classifiers":[
        {
            "category":"Banks & Credit Unions",
            "subcategory":"Investment Brokerage",
            "type":"Services"
        }
    ],
    "sg:phone":"+1 512 821 1794",
    "sg:postcode":"78753",
    "sg:province":"TX",
    "sg:tags":[
        "security"
    ],
    "wof:name":"Northeast Securities Inc",
    "wof:placetype":"venue"
},
  "geometry": {"coordinates":[-97.66749799999999,30.385218],"type":"Point"}
}