{
  "type": "Feature",
  "properties": {
    "iso:country":"US",
    "sg:address":"3314 Forest Village Dr",
    "sg:city":"Kingwood",
    "sg:classifiers":[
        {
            "category":"Professional",
            "subcategory":"Management & Consulting",
            "type":"Services"
        }
    ],
    "sg:phone":"+1 281 358 3226",
    "sg:postcode":"77339",
    "sg:province":"TX",
    "sg:tags":[
        "promotion",
        "relation",
        "sale",
        "public"
    ],
    "wof:name":"Amos Sales",
    "wof:placetype":"venue"
},
  "geometry": {"coordinates":[-95.210618,30.057693],"type":"Point"}
}