{
  "type": "Feature",
  "properties": {
    "iso:country":"US",
    "sg:address":"7528 Le Conte Dr",
    "sg:city":"El Paso",
    "sg:classifiers":[
        {
            "category":"Wholesale",
            "subcategory":"Machinery & Supplies",
            "type":"Manufacturing & Wholesale Goods"
        }
    ],
    "sg:phone":"+1 915 833 6767",
    "sg:postcode":"79912",
    "sg:province":"TX",
    "sg:tags":[
        "machine",
        "equipment",
        "parts"
    ],
    "wof:name":"Cgm Industrial Inc",
    "wof:placetype":"venue"
},
  "geometry": {"coordinates":[-106.56477700000001,31.846904],"type":"Point"}
}