{
  "type": "Feature",
  "properties": {
    "iso:country":"US",
    "sg:address":"12141 Perry Rd",
    "sg:city":"Houston",
    "sg:classifiers":[
        {
            "category":"Autos & Motor Vehicles",
            "subcategory":"Automobile Sales",
            "type":"Retail Goods"
        },
        {
            "category":"Wholesale",
            "subcategory":"Motor Vehicles",
            "type":"Manufacturing & Wholesale Goods"
        }
    ],
    "sg:phone":"+1 281 477 9833",
    "sg:postcode":"77070",
    "sg:province":"TX",
    "sg:tags":[
        "car",
        "dealer"
    ],
    "wof:name":"Everybody Auto Broker & Sales",
    "wof:placetype":"venue"
},
  "geometry": {"coordinates":[-95.563942,29.950847],"type":"Point"}
}