{
  "type": "Feature",
  "properties": {
    "iso:country":"US",
    "sg:address":"441 Francis St",
    "sg:city":"Lancaster",
    "sg:classifiers":[
        {
            "category":"Education",
            "subcategory":"Special Training",
            "type":"Public Place"
        }
    ],
    "sg:phone":"+1 972 227 6130",
    "sg:postcode":"75146",
    "sg:province":"TX",
    "sg:tags":[
        "field",
        "reader"
    ],
    "wof:name":"Brenda Carter-Crawford",
    "wof:placetype":"venue"
},
  "geometry": {"coordinates":[-96.761381,32.594146],"type":"Point"}
}