{
  "type": "Feature",
  "properties": {
    "iso:country":"US",
    "sg:address":"2615 Overland Dr",
    "sg:city":"Dallas",
    "sg:classifiers":[
        {
            "category":"Retail",
            "subcategory":"Repair Shop",
            "type":"Services"
        }
    ],
    "sg:phone":"+1 972 241 7165",
    "sg:postcode":"75234",
    "sg:province":"TX",
    "wof:name":"AA Auto Radio Service",
    "wof:placetype":"venue"
},
  "geometry": {"coordinates":[-96.890788,32.935918],"type":"Point"}
}