{
  "type": "Feature",
  "properties": {
    "iso:country":"US",
    "sg:address":"2316 Tinker Trl",
    "sg:city":"Wichita Falls",
    "sg:classifiers":[
        {
            "category":"Organizations",
            "subcategory":"Religious Organization",
            "type":"Services"
        }
    ],
    "sg:phone":"+1 940 855 8228",
    "sg:postcode":"76306",
    "sg:province":"TX",
    "wof:name":"Agape House of Prayer Fo",
    "wof:placetype":"venue"
},
  "geometry": {"coordinates":[-98.53057099999999,33.988335],"type":"Point"}
}