{
  "type": "Feature",
  "properties": {
    "iso:country":"US",
    "sg:address":"14101 North Fwy",
    "sg:city":"Houston",
    "sg:classifiers":[
        {
            "category":"Retail",
            "subcategory":"Auto Rental",
            "type":"Services"
        }
    ],
    "sg:phone":"+1 281 872 5241",
    "sg:postcode":"77090",
    "sg:province":"TX",
    "sg:tags":[
        "passenger",
        "car"
    ],
    "wof:name":"Enterprise Rent-A-Car",
    "wof:placetype":"venue"
},
  "geometry": {"coordinates":[-95.420484,29.969391],"type":"Point"}
}