{
  "type": "Feature",
  "properties": {
    "iso:country":"US",
    "sg:address":"4434 Fm 1960 Rd W",
    "sg:city":"Houston",
    "sg:classifiers":[
        {
            "category":"Travel",
            "subcategory":"Hotels & Motels",
            "type":"Entertainment"
        }
    ],
    "sg:phone":"+1 877 574 2464",
    "sg:postcode":"77068",
    "sg:province":"TX",
    "sg:tags":[
        "lodging"
    ],
    "sg:website":"http://book.bestwestern.com/bestwestern/priceAvail.do?propertyCode=44480&cm_mmc=IYP-_-YP-_-property-_-44480",
    "wof:name":"Best Western Executive Suites Hotel",
    "wof:placetype":"venue"
},
  "geometry": {"coordinates":[-95.497513,29.988335],"type":"Point"}
}