{
  "type": "Feature",
  "properties": {
    "iso:country":"US",
    "sg:address":"6101 Pinemont Dr",
    "sg:city":"Houston",
    "sg:classifiers":[
        {
            "category":"Professional",
            "subcategory":"Management & Consulting",
            "type":"Services"
        }
    ],
    "sg:phone":"+1 713 686 0032",
    "sg:postcode":"77092",
    "sg:province":"TX",
    "sg:tags":[
        "industrial",
        "sales"
    ],
    "wof:name":"Rafco Sales",
    "wof:placetype":"venue"
},
  "geometry": {"coordinates":[-95.47973399999999,29.84036],"type":"Point"}
}