{
  "type": "Feature",
  "properties": {
    "iso:country":"US",
    "sg:address":"5819 Indian Trl",
    "sg:city":"Houston",
    "sg:classifiers":[
        {
            "category":"Farming",
            "subcategory":"Livestock Farm",
            "type":"Manufacturing & Wholesale Goods"
        }
    ],
    "sg:phone":"+1 713 783 5388",
    "sg:postcode":"77057",
    "sg:province":"TX",
    "sg:tags":[
        "ranch"
    ],
    "wof:name":"Pfeffer & Son",
    "wof:placetype":"venue"
},
  "geometry": {"coordinates":[-95.480594,29.76825],"type":"Point"}
}