{
  "type": "Feature",
  "properties": {
    "iso:country":"US",
    "sg:address":"1018 Herkimer St",
    "sg:city":"Houston",
    "sg:classifiers":[
        {
            "category":"Organizations",
            "subcategory":"Religious Organization",
            "type":"Services"
        }
    ],
    "sg:phone":"+1 713 861 6784",
    "sg:postcode":"77008",
    "sg:province":"TX",
    "sg:tags":[
        "church"
    ],
    "wof:name":"Mt Calvary Baptist Church",
    "wof:placetype":"venue"
},
  "geometry": {"coordinates":[-95.406069,29.790225],"type":"Point"}
}