{
  "type": "Feature",
  "properties": {
    "iso:country":"US",
    "sg:address":"8702 Five Palms Dr",
    "sg:city":"San Antonio",
    "sg:classifiers":[
        {
            "category":"Personal",
            "subcategory":"Beauty Salon",
            "type":"Services"
        }
    ],
    "sg:phone":"+1 210 623 5390",
    "sg:postcode":"78242",
    "sg:province":"TX",
    "sg:tags":[
        "shop"
    ],
    "wof:name":"Mats Cut Co & Trimming",
    "wof:placetype":"venue"
},
  "geometry": {"coordinates":[-98.610356,29.342687],"type":"Point"}
}