{
  "type": "Feature",
  "properties": {
    "iso:country":"US",
    "sg:address":"2521 Meadowpark Cir",
    "sg:city":"Bedford",
    "sg:classifiers":[
        {
            "category":"Building & Trades",
            "subcategory":"Landscaping Services",
            "type":"Services"
        }
    ],
    "sg:phone":"+1 817 571 3553",
    "sg:postcode":"76021",
    "sg:province":"TX",
    "wof:name":"AC Lawn Service",
    "wof:placetype":"venue"
},
  "geometry": {"coordinates":[-97.132144,32.849132],"type":"Point"}
}