{
  "type": "Feature",
  "properties": {
    "iso:country":"US",
    "sg:address":"11500 Bingham Ct",
    "sg:city":"El Paso",
    "sg:classifiers":[
        {
            "category":"Organizations",
            "subcategory":"Labor Organization",
            "type":"Services"
        }
    ],
    "sg:phone":"+1 915 855 1420",
    "sg:postcode":"79936",
    "sg:province":"TX",
    "wof:name":"Carpenters Works",
    "wof:placetype":"venue"
},
  "geometry": {"coordinates":[-106.292609,31.777569],"type":"Point"}
}