{
  "type": "Feature",
  "properties": {
    "iso:country":"US",
    "sg:address":"2121 Baylor Dr",
    "sg:city":"Lubbock",
    "sg:classifiers":[
        {
            "category":"Wholesale",
            "subcategory":"Electrical",
            "type":"Manufacturing & Wholesale Goods"
        }
    ],
    "sg:phone":"+1 806 762 1830",
    "sg:postcode":"79415",
    "sg:province":"TX",
    "sg:tags":[
        "equipment",
        "electric",
        "supply"
    ],
    "wof:name":"Chase Lighting & Electrical",
    "wof:placetype":"venue"
},
  "geometry": {"coordinates":[-101.86306399999999,33.602251],"type":"Point"}
}