{
  "type": "Feature",
  "properties": {
    "iso:country":"US",
    "sg:address":"11610 Fm 2244",
    "sg:city":"Austin",
    "sg:classifiers":[
        {
            "category":"Building & Trades",
            "subcategory":"Construction",
            "type":"Services"
        }
    ],
    "sg:phone":"+1 512 328 2502",
    "sg:postcode":"78738",
    "sg:province":"TX",
    "sg:tags":[
        "contractor"
    ],
    "wof:name":"Bailey Brian A Homes",
    "wof:placetype":"venue"
},
  "geometry": {"coordinates":[-97.916995,30.309742],"type":"Point"}
}