{
  "type": "Feature",
  "properties": {
    "iso:country":"US",
    "sg:address":"404 E Green Ave",
    "sg:city":"Killeen",
    "sg:classifiers":[
        {
            "category":"Health Services",
            "subcategory":"Clinic",
            "type":"Services"
        }
    ],
    "sg:phone":"+1 254 634 8424",
    "sg:postcode":"76541",
    "sg:province":"TX",
    "wof:name":"McCurrin Services",
    "wof:placetype":"venue"
},
  "geometry": {"coordinates":[-97.723992,31.123817],"type":"Point"}
}