{
  "type": "Feature",
  "properties": {
    "iso:country":"US",
    "sg:address":"103 Matlock Meadow Dr",
    "sg:city":"Arlington",
    "sg:classifiers":[
        {
            "category":"Real Estate",
            "subcategory":"Real Estate Agent",
            "type":"Services"
        }
    ],
    "sg:phone":"+1 817 466 2500",
    "sg:postcode":"76002",
    "sg:province":"TX",
    "wof:name":"Sheridan Homes-Meadow Vista",
    "wof:placetype":"venue"
},
  "geometry": {"coordinates":[-97.11532099999999,32.628707],"type":"Point"}
}