{
  "type": "Feature",
  "properties": {
    "iso:country":"US",
    "sg:address":"612 E Main St",
    "sg:city":"Alice",
    "sg:classifiers":[
        {
            "category":"Professional",
            "subcategory":"Management & Consulting",
            "type":"Services"
        }
    ],
    "sg:phone":"+1 361 661 1119",
    "sg:postcode":"78332",
    "sg:province":"TX",
    "sg:tags":[
        "consultant",
        "business"
    ],
    "wof:name":"City Of Alice Chamber-Commerce",
    "wof:placetype":"venue"
},
  "geometry": {"coordinates":[-98.07010099999999,27.750085],"type":"Point"}
}