{
  "type": "Feature",
  "properties": {
    "iso:country":"US",
    "sg:address":"3913 75th St",
    "sg:city":"Lubbock",
    "sg:classifiers":[
        {
            "category":"Professional",
            "type":"Services"
        }
    ],
    "sg:phone":"+1 806 793 9826",
    "sg:postcode":"79423",
    "sg:province":"TX",
    "wof:name":"Southwest Fab Inc",
    "wof:placetype":"venue"
},
  "geometry": {"coordinates":[-101.898582,33.526393],"type":"Point"}
}