{
  "type": "Feature",
  "properties": {
    "iso:country":"US",
    "sg:address":"4815 Castle Prince Dr",
    "sg:city":"San Antonio",
    "sg:classifiers":[
        {
            "category":"Professional",
            "subcategory":"Management & Consulting",
            "type":"Services"
        }
    ],
    "sg:phone":"+1 210 650 8109",
    "sg:postcode":"78218",
    "sg:province":"TX",
    "sg:tags":[
        "retail",
        "direct",
        "sales"
    ],
    "wof:name":"Angels Silver",
    "wof:placetype":"venue"
},
  "geometry": {"coordinates":[-98.377011,29.488778],"type":"Point"}
}