{
  "type": "Feature",
  "properties": {
    "iso:country":"US",
    "sg:address":"101 Ocotillo",
    "sg:city":"Kingsland",
    "sg:classifiers":[
        {
            "category":"Building & Trades",
            "subcategory":"Landscaping Services",
            "type":"Services"
        }
    ],
    "sg:phone":"+1 325 388 0440",
    "sg:postcode":"78639",
    "sg:province":"TX",
    "sg:tags":[
        "lawn",
        "maintenance"
    ],
    "wof:name":"Trinity Lawn Services",
    "wof:placetype":"venue"
},
  "geometry": {"coordinates":[-98.443459,30.66349],"type":"Point"}
}