{
  "type": "Feature",
  "properties": {
    "iso:country":"US",
    "sg:address":"2704 Bonnie Rd",
    "sg:city":"Austin",
    "sg:classifiers":[
        {
            "category":"Personal",
            "subcategory":"Beauty Salon",
            "type":"Services"
        }
    ],
    "sg:phone":"+1 512 327 4999",
    "sg:postcode":"78703",
    "sg:province":"TX",
    "sg:tags":[
        "shop"
    ],
    "wof:name":"Glow Skin Care Inc",
    "wof:placetype":"venue"
},
  "geometry": {"coordinates":[-97.773301,30.292566],"type":"Point"}
}