{
  "type": "Feature",
  "properties": {
    "iso:country":"US",
    "sg:address":"101 W Locust St",
    "sg:city":"Collinsville",
    "sg:classifiers":[
        {
            "category":"Real Estate",
            "subcategory":"Real Estate Agent",
            "type":"Services"
        }
    ],
    "sg:phone":"+1 903 429 6190",
    "sg:postcode":"76233",
    "sg:province":"TX",
    "wof:name":"Signature Co",
    "wof:placetype":"venue"
},
  "geometry": {"coordinates":[-96.911552,33.556833],"type":"Point"}
}