{
  "type": "Feature",
  "properties": {
    "iso:country":"US",
    "sg:address":"116 Riverside Vw",
    "sg:city":"Kingsland",
    "sg:classifiers":[
        {
            "category":"Travel",
            "subcategory":"Hotels & Motels",
            "type":"Entertainment"
        }
    ],
    "sg:phone":"+1 325 388 4521",
    "sg:postcode":"78639",
    "sg:province":"TX",
    "sg:tags":[
        "breakfast",
        "accommodation",
        "bed"
    ],
    "wof:name":"Sandyland Resort & Marina",
    "wof:placetype":"venue"
},
  "geometry": {"coordinates":[-98.418705,30.648525],"type":"Point"}
}