{
  "type": "Feature",
  "properties": {
    "iso:country":"US",
    "sg:address":"12527 I- 10",
    "sg:city":"Baytown",
    "sg:classifiers":[
        {
            "category":"Manufacturing",
            "subcategory":"Motor Vehicles & Parts",
            "type":"Manufacturing & Wholesale Goods"
        }
    ],
    "sg:phone":"+1 281 576 4662",
    "sg:postcode":"77520",
    "sg:province":"TX",
    "sg:tags":[
        "mfg"
    ],
    "wof:name":"Kts Cycle Service",
    "wof:placetype":"venue"
},
  "geometry": {"coordinates":[-94.810615,29.829408],"type":"Point"}
}