{
  "type": "Feature",
  "properties": {
    "iso:country":"US",
    "sg:address":"1434 Springwood Dr",
    "sg:city":"Mesquite",
    "sg:classifiers":[
        {
            "category":"Professional",
            "type":"Services"
        }
    ],
    "sg:phone":"+1 972 222 2036",
    "sg:postcode":"75181",
    "sg:province":"TX",
    "wof:name":"Susans Creations",
    "wof:placetype":"venue"
},
  "geometry": {"coordinates":[-96.54403000000001,32.746084],"type":"Point"}
}