{
  "type": "Feature",
  "properties": {
    "iso:country":"US",
    "sg:address":"3430 Copeland Dr",
    "sg:city":"San Antonio",
    "sg:classifiers":[
        {
            "category":"Building & Trades",
            "subcategory":"Construction",
            "type":"Services"
        }
    ],
    "sg:phone":"+1 210 270 9510",
    "sg:postcode":"78219",
    "sg:province":"TX",
    "sg:tags":[
        "maker",
        "cabinet"
    ],
    "wof:name":"Tomco Inc",
    "wof:placetype":"venue"
},
  "geometry": {"coordinates":[-98.42712,29.44529],"type":"Point"}
}