{
  "type": "Feature",
  "properties": {
    "iso:country":"US",
    "sg:address":"450 Crosstimber Dr",
    "sg:city":"Hurst",
    "sg:classifiers":[
        {
            "category":"Building & Trades",
            "subcategory":"Construction",
            "type":"Services"
        }
    ],
    "sg:phone":"+1 817 430 9798",
    "sg:postcode":"76053",
    "sg:province":"TX",
    "sg:tags":[
        "contractor"
    ],
    "wof:name":"Devtex Eng",
    "wof:placetype":"venue"
},
  "geometry": {"coordinates":[-97.17948,32.815459],"type":"Point"}
}