{
  "type": "Feature",
  "properties": {
    "iso:country":"US",
    "sg:address":"712 Earl Garrett St",
    "sg:city":"Kerrville",
    "sg:classifiers":[
        {
            "category":"Real Estate",
            "subcategory":"Real Estate Services",
            "type":"Services"
        }
    ],
    "sg:phone":"+1 830 257 5151",
    "sg:postcode":"78028",
    "sg:province":"TX",
    "sg:tags":[
        "company",
        "title"
    ],
    "sg:website":"www.kerrtitle.com",
    "wof:name":"KERR County Abstract Co",
    "wof:placetype":"venue"
},
  "geometry": {"coordinates":[-99.13495500000001,30.05059],"type":"Point"}
}