{
  "type": "Feature",
  "properties": {
    "iso:country":"US",
    "sg:address":"7139 Kings Dr",
    "sg:city":"Baytown",
    "sg:classifiers":[
        {
            "category":"Shopping",
            "subcategory":"Discount & Variety Stores",
            "type":"Retail Goods"
        }
    ],
    "sg:phone":"+1 281 426 8170",
    "sg:postcode":"77521",
    "sg:province":"TX",
    "sg:tags":[
        "merchandise",
        "general"
    ],
    "wof:name":"His & Hers Furniture & Clothe",
    "wof:placetype":"venue"
},
  "geometry": {"coordinates":[-95.014188,29.801432],"type":"Point"}
}