{
  "type": "Feature",
  "properties": {
    "iso:country":"US",
    "sg:address":"6021 Morriss Rd",
    "sg:city":"Flower Mound",
    "sg:classifiers":[
        {
            "category":"Professional",
            "subcategory":"Employment Agencies",
            "type":"Services"
        }
    ],
    "sg:phone":"+1 469 549 4785",
    "sg:postcode":"75028",
    "sg:province":"TX",
    "sg:tags":[
        "help",
        "supply"
    ],
    "wof:name":"Family Staffing Solutions",
    "wof:placetype":"venue"
},
  "geometry": {"coordinates":[-97.06188899999999,33.066634],"type":"Point"}
}