{
  "type": "Feature",
  "properties": {
    "iso:country":"US",
    "sg:address":"24402 Katex Blvd",
    "sg:city":"Katy",
    "sg:classifiers":[
        {
            "category":"Building & Trades",
            "subcategory":"Landscaping Services",
            "type":"Services"
        }
    ],
    "sg:phone":"+1 281 391 8931",
    "sg:postcode":"77493",
    "sg:province":"TX",
    "sg:tags":[
        "landscape"
    ],
    "wof:name":"Lawn Star",
    "wof:placetype":"venue"
},
  "geometry": {"coordinates":[-95.79710300000001,29.806184],"type":"Point"}
}