{
  "type": "Feature",
  "properties": {
    "iso:country":"US",
    "sg:address":"6700 Oliver Dr",
    "sg:city":"N Richland Hills",
    "sg:classifiers":[
        {
            "category":"Building & Trades",
            "subcategory":"Construction",
            "type":"Services"
        }
    ],
    "sg:phone":"+1 817 427 3535",
    "sg:postcode":"76180",
    "sg:province":"TX",
    "sg:tags":[
        "repairing",
        "remodeling",
        "contractor"
    ],
    "wof:name":"Key Renovations",
    "wof:placetype":"venue"
},
  "geometry": {"coordinates":[-97.23819899999999,32.832754],"type":"Point"}
}