{
  "type": "Feature",
  "properties": {
    "iso:country":"US",
    "sg:address":"826 del Oro Ln",
    "sg:city":"Pharr",
    "sg:classifiers":[
        {
            "category":"Education",
            "subcategory":"Special Training",
            "type":"Public Place"
        }
    ],
    "sg:phone":"+1 956 781 7200",
    "sg:postcode":"78577",
    "sg:province":"TX",
    "sg:tags":[
        "career",
        "counseling",
        "vocational"
    ],
    "wof:name":"Alberto Cano",
    "wof:placetype":"venue"
},
  "geometry": {"coordinates":[-98.192078,26.21427],"type":"Point"}
}