{
  "type": "Feature",
  "properties": {
    "iso:country":"US",
    "sg:address":"801 18th St",
    "sg:city":"Plano",
    "sg:classifiers":[
        {
            "category":"Retail",
            "subcategory":"Auto Repair",
            "type":"Services"
        }
    ],
    "sg:phone":"+1 972 424 8997",
    "sg:postcode":"75074",
    "sg:province":"TX",
    "sg:tags":[
        "repairing",
        "automobile"
    ],
    "wof:name":"Plano Truck & Auto",
    "wof:placetype":"venue"
},
  "geometry": {"coordinates":[-96.70279499999999,33.023891],"type":"Point"}
}