{
  "type": "Feature",
  "properties": {
    "iso:country":"US",
    "sg:address":"23118 Burcan Ct",
    "sg:city":"Spring",
    "sg:classifiers":[
        {
            "category":"Shopping",
            "subcategory":"Gifts & Souvenirs",
            "type":"Retail Goods"
        }
    ],
    "sg:phone":"+1 281 350 5302",
    "sg:postcode":"77373",
    "sg:province":"TX",
    "wof:name":"Emileighs Candles & Gifts",
    "wof:placetype":"venue"
},
  "geometry": {"coordinates":[-95.426337,30.097285],"type":"Point"}
}