{
  "type": "Feature",
  "properties": {
    "iso:country":"US",
    "sg:address":"1005 W Jefferson Blvd",
    "sg:city":"Dallas",
    "sg:classifiers":[
        {
            "category":"Real Estate",
            "subcategory":"Real Estate Agent",
            "type":"Services"
        }
    ],
    "sg:phone":"+1 214 943 1354",
    "sg:postcode":"75208",
    "sg:province":"TX",
    "wof:name":"Alba Realty",
    "wof:placetype":"venue"
},
  "geometry": {"coordinates":[-96.84039900000001,32.743326],"type":"Point"}
}