{
  "type": "Feature",
  "properties": {
    "iso:country":"US",
    "sg:address":"1410 Cypress Creek Rd",
    "sg:city":"Cedar Park",
    "sg:classifiers":[
        {
            "category":"Restaurant",
            "type":"Food & Drink"
        }
    ],
    "sg:phone":"+1 512 336 1999",
    "sg:postcode":"78613",
    "sg:province":"TX",
    "wof:name":"Mc Donald's",
    "wof:placetype":"venue"
},
  "geometry": {"coordinates":[-97.828441,30.491766],"type":"Point"}
}