{
  "type": "Feature",
  "properties": {
    "iso:country":"US",
    "sg:address":"451 E Alton Gloor Blvd",
    "sg:city":"Brownsville",
    "sg:classifiers":[
        {
            "category":"Health Services",
            "subcategory":"Doctor",
            "type":"Services"
        }
    ],
    "sg:phone":"+1 956 350 0600",
    "sg:postcode":"78521",
    "sg:province":"TX",
    "sg:tags":[
        "clinic"
    ],
    "wof:name":"Arthritis & Osteoporosis Ctr",
    "wof:placetype":"venue"
},
  "geometry": {"coordinates":[-97.510214,25.979816],"type":"Point"}
}