{
  "type": "Feature",
  "properties": {
    "iso:country":"US",
    "sg:address":"1409 Lucille Dr",
    "sg:city":"Mesquite",
    "sg:classifiers":[
        {
            "category":"Health Services",
            "subcategory":"Health Practitioner",
            "type":"Services"
        }
    ],
    "sg:phone":"+1 972 288 8372",
    "sg:postcode":"75149",
    "sg:province":"TX",
    "wof:name":"Edwards Johanna Inc",
    "wof:placetype":"venue"
},
  "geometry": {"coordinates":[-96.63414299999999,32.781673],"type":"Point"}
}