{
  "type": "Feature",
  "properties": {
    "iso:country":"US",
    "sg:address":"208 Flushing Quail Dr",
    "sg:city":"Arlington",
    "sg:classifiers":[
        {
            "category":"Building & Trades",
            "subcategory":"Construction",
            "type":"Services"
        }
    ],
    "sg:phone":"+1 817 375 0726",
    "sg:postcode":"76002",
    "sg:province":"TX",
    "sg:tags":[
        "residential"
    ],
    "wof:name":"Terrance Construction LLC",
    "wof:placetype":"venue"
},
  "geometry": {"coordinates":[-97.111182,32.626939],"type":"Point"}
}