{
  "type": "Feature",
  "properties": {
    "iso:country":"US",
    "sg:address":"2061 Birchwood Ct",
    "sg:city":"Lewisville",
    "sg:classifiers":[
        {
            "category":"Building & Trades",
            "subcategory":"Cleaning & Sanitation",
            "type":"Services"
        }
    ],
    "sg:phone":"+1 972 459 6947",
    "sg:postcode":"75067",
    "sg:province":"TX",
    "wof:name":"Lewisville Cleaning Services",
    "wof:placetype":"venue"
},
  "geometry": {"coordinates":[-97.008281,33.01224],"type":"Point"}
}