{
  "type": "Feature",
  "properties": {
    "iso:country":"US",
    "sg:address":"6301 Overton Ridge Blvd",
    "sg:city":"Fort Worth",
    "sg:classifiers":[
        {
            "category":"Health Services",
            "subcategory":"Nursing And Care Facility",
            "type":"Services"
        }
    ],
    "sg:phone":"+1 817 292 5600",
    "sg:postcode":"76132",
    "sg:province":"TX",
    "sg:tags":[
        "home",
        "retirement",
        "community"
    ],
    "wof:name":"Franklin Park At City View",
    "wof:placetype":"venue"
},
  "geometry": {"coordinates":[-97.420115,32.679862],"type":"Point"}
}