{
  "type": "Feature",
  "properties": {
    "iso:country":"US",
    "sg:address":"12012 Cherie Dr",
    "sg:city":"Austin",
    "sg:classifiers":[
        {
            "category":"Shopping",
            "subcategory":"Beauty & Cosmetics",
            "type":"Retail Goods"
        }
    ],
    "sg:phone":"+1 512 835 1518",
    "sg:postcode":"78758",
    "sg:province":"TX",
    "sg:tags":[
        "merchandise"
    ],
    "wof:name":"Jeanie Talley",
    "wof:placetype":"venue"
},
  "geometry": {"coordinates":[-97.694779,30.399987],"type":"Point"}
}