{
  "type": "Feature",
  "properties": {
    "iso:country":"US",
    "sg:address":"1515 Highland Dr",
    "sg:city":"Alvin",
    "sg:classifiers":[
        {
            "category":"Professional",
            "subcategory":"Business Services",
            "type":"Services"
        }
    ],
    "sg:phone":"+1 281 331 7132",
    "sg:postcode":"77511",
    "sg:province":"TX",
    "wof:name":"Maj Design",
    "wof:placetype":"venue"
},
  "geometry": {"coordinates":[-95.25900300000001,29.412645],"type":"Point"}
}