{
  "type": "Feature",
  "properties": {
    "iso:country":"US",
    "sg:address":"2507 Galveston Rd",
    "sg:city":"Houston",
    "sg:classifiers":[
        {
            "category":"Organizations",
            "subcategory":"Labor Organization",
            "type":"Services"
        }
    ],
    "sg:phone":"+1 713 649 0201",
    "sg:postcode":"77017",
    "sg:province":"TX",
    "wof:name":"JATC",
    "wof:placetype":"venue"
},
  "geometry": {"coordinates":[-95.272274,29.703626],"type":"Point"}
}