{
  "type": "Feature",
  "properties": {
    "iso:country":"US",
    "sg:address":"9835 Kempwood Dr",
    "sg:city":"Houston",
    "sg:classifiers":[
        {
            "category":"Organizations",
            "subcategory":"Religious Organization",
            "type":"Services"
        }
    ],
    "sg:phone":"+1 713 460 4366",
    "sg:postcode":"77080",
    "sg:province":"TX",
    "sg:tags":[
        "church"
    ],
    "sg:website":"www.watchtower.org",
    "wof:name":"Jehovah Witness",
    "wof:placetype":"venue"
},
  "geometry": {"coordinates":[-95.536017,29.822122],"type":"Point"}
}