{
  "type": "Feature",
  "properties": {
    "iso:country":"US",
    "sg:address":"33 S Central Ave",
    "sg:city":"Hamlin",
    "sg:classifiers":[
        {
            "category":"Autos & Motor Vehicles",
            "subcategory":"Fuel & Gas Station",
            "type":"Retail Goods"
        }
    ],
    "sg:phone":"+1 325 576 3781",
    "sg:postcode":"79520",
    "sg:province":"TX",
    "sg:tags":[
        "station",
        "gasoline"
    ],
    "wof:name":"Texaco",
    "wof:placetype":"venue"
},
  "geometry": {"coordinates":[-100.126385,32.884438],"type":"Point"}
}