{
  "type": "Feature",
  "properties": {
    "iso:country":"US",
    "sg:address":"703 Riverlawn Dr",
    "sg:city":"Round Rock",
    "sg:classifiers":[
        {
            "category":"Restaurant",
            "type":"Food & Drink"
        }
    ],
    "sg:phone":"+1 512 310 8331",
    "sg:postcode":"78681",
    "sg:province":"TX",
    "sg:tags":[
        "eating"
    ],
    "wof:name":"Slam Dawg Sports",
    "wof:placetype":"venue"
},
  "geometry": {"coordinates":[-97.704291,30.500021],"type":"Point"}
}