{
  "type": "Feature",
  "properties": {
    "iso:country":"US",
    "sg:address":"907 S Mason Rd",
    "sg:city":"Katy",
    "sg:classifiers":[
        {
            "category":"Real Estate",
            "subcategory":"Real Estate Services",
            "type":"Services"
        },
        {
            "category":"Real Estate",
            "subcategory":"Real Estate Agent",
            "type":"Services"
        }
    ],
    "sg:phone":"+1 281 829 1265",
    "sg:postcode":"77450",
    "sg:province":"TX",
    "sg:tags":[
        "buyer",
        "broker"
    ],
    "wof:name":"Katy Signature Realty",
    "wof:placetype":"venue"
},
  "geometry": {"coordinates":[-95.751599,29.769468],"type":"Point"}
}