{
  "type": "Feature",
  "properties": {
    "iso:country":"US",
    "sg:address":"7742 Baltimore St",
    "sg:city":"Houston",
    "sg:classifiers":[
        {
            "category":"Social Services",
            "subcategory":"Child Care",
            "type":"Services"
        }
    ],
    "sg:phone":"+1 713 923 6273",
    "sg:postcode":"77012",
    "sg:province":"TX",
    "wof:name":"Gloria Rodriguez",
    "wof:placetype":"venue"
},
  "geometry": {"coordinates":[-95.287218,29.730113],"type":"Point"}
}