{
  "type": "Feature",
  "properties": {
    "iso:country":"US",
    "sg:address":"600 Meadow View Ln",
    "sg:city":"Kerrville",
    "sg:classifiers":[
        {
            "category":"Real Estate",
            "subcategory":"Real Estate Operator",
            "type":"Services"
        }
    ],
    "sg:phone":"+1 830 257 4485",
    "sg:postcode":"78028",
    "sg:province":"TX",
    "sg:tags":[
        "apartment"
    ],
    "wof:name":"Chimney Forest Apartment",
    "wof:placetype":"venue"
},
  "geometry": {"coordinates":[-99.120931,30.02742],"type":"Point"}
}