{
  "type": "Feature",
  "properties": {
    "iso:country":"US",
    "sg:address":"707 E Main St",
    "sg:city":"Allen",
    "sg:classifiers":[
        {
            "category":"Restaurant",
            "type":"Food & Drink"
        }
    ],
    "sg:menulink":"http://www.allmenus.com/tx/plano/203658-sonic/menu/",
    "sg:phone":"+1 972 727 4218",
    "sg:postcode":"75002",
    "sg:province":"TX",
    "sg:tags":[
        "burger",
        "american"
    ],
    "wof:name":"Sonic",
    "wof:placetype":"venue"
},
  "geometry": {"coordinates":[-96.65590400000001,33.101088],"type":"Point"}
}