{
  "type": "Feature",
  "properties": {
    "iso:country":"US",
    "sg:address":"3318 19th St",
    "sg:city":"Port Arthur",
    "sg:classifiers":[
        {
            "category":"Food & Beverages",
            "subcategory":"Groceries & Convenience Stores",
            "type":"Retail Goods"
        }
    ],
    "sg:phone":"+1 409 983 4659",
    "sg:postcode":"77642",
    "sg:province":"TX",
    "wof:name":"Smv Market Co",
    "wof:placetype":"venue"
},
  "geometry": {"coordinates":[-93.926421,29.905922],"type":"Point"}
}