{
  "type": "Feature",
  "properties": {
    "iso:country":"US",
    "sg:address":"335 Crestview",
    "sg:city":"Red Oak",
    "sg:classifiers":[
        {
            "category":"Freight",
            "type":"Transportation"
        }
    ],
    "sg:phone":"+1 972 617 5487",
    "sg:postcode":"75154",
    "sg:province":"TX",
    "sg:tags":[
        "operator",
        "local",
        "trucking"
    ],
    "wof:name":"Sil Mar Trucking Inc",
    "wof:placetype":"venue"
},
  "geometry": {"coordinates":[-96.7907,32.511017],"type":"Point"}
}