{
  "type": "Feature",
  "properties": {
    "iso:country":"US",
    "sg:address":"8803 Brae Acres Rd",
    "sg:city":"Houston",
    "sg:classifiers":[
        {
            "category":"Retail",
            "subcategory":"Veterinary Services",
            "type":"Services"
        }
    ],
    "sg:phone":"+1 713 777 7387",
    "sg:postcode":"77074",
    "sg:province":"TX",
    "sg:tags":[
        "veterinarian"
    ],
    "wof:name":"Northshore Animal Hospital",
    "wof:placetype":"venue"
},
  "geometry": {"coordinates":[-95.521593,29.683455],"type":"Point"}
}