{
  "type": "Feature",
  "properties": {
    "iso:country":"US",
    "sg:address":"540 Madison Oak Dr",
    "sg:city":"San Antonio",
    "sg:classifiers":[
        {
            "category":"Health Services",
            "subcategory":"Doctor",
            "type":"Services"
        }
    ],
    "sg:phone":"+1 210 402 3101",
    "sg:postcode":"78258",
    "sg:province":"TX",
    "sg:tags":[
        "medical"
    ],
    "wof:name":"Gpr Family Medical Group",
    "wof:placetype":"venue"
},
  "geometry": {"coordinates":[-98.491793,29.6211],"type":"Point"}
}