{
  "type": "Feature",
  "properties": {
    "iso:country":"US",
    "sg:address":"6524 Basswood Dr",
    "sg:city":"Fort Worth",
    "sg:classifiers":[
        {
            "category":"Shopping",
            "subcategory":"Discount & Variety Stores",
            "type":"Retail Goods"
        }
    ],
    "sg:phone":"+1 817 237 6420",
    "sg:postcode":"76135",
    "sg:province":"TX",
    "sg:tags":[
        "merchandise",
        "general"
    ],
    "wof:name":"Rosa E Tijerina Gen Mdse",
    "wof:placetype":"venue"
},
  "geometry": {"coordinates":[-97.427677,32.827321],"type":"Point"}
}