{
  "type": "Feature",
  "properties": {
    "iso:country":"US",
    "sg:address":"702 San Antonio St",
    "sg:city":"Austin",
    "sg:classifiers":[
        {
            "category":"Wholesale",
            "subcategory":"Non-durable Goods",
            "type":"Manufacturing & Wholesale Goods"
        }
    ],
    "sg:phone":"+1 512 478 2257",
    "sg:postcode":"78701",
    "sg:province":"TX",
    "wof:name":"Freefall Promotions",
    "wof:placetype":"venue"
},
  "geometry": {"coordinates":[-97.746742,30.27118],"type":"Point"}
}