{
  "type": "Feature",
  "properties": {
    "iso:country":"US",
    "sg:address":"3177 E University Blvd",
    "sg:city":"Odessa",
    "sg:classifiers":[
        {
            "category":"Shopping",
            "subcategory":"Bicycles & Sporting Goods",
            "type":"Retail Goods"
        }
    ],
    "sg:phone":"+1 432 550 6664",
    "sg:postcode":"79762",
    "sg:province":"TX",
    "sg:tags":[
        "equipment",
        "exercise",
        "fitness"
    ],
    "wof:name":"Fitness & Golf Specialist",
    "wof:placetype":"venue"
},
  "geometry": {"coordinates":[-102.35410899999999,31.873767],"type":"Point"}
}