{
  "type": "Feature",
  "properties": {
    "iso:country":"US",
    "sg:address":"8601 Sovereign Row",
    "sg:city":"Dallas",
    "sg:classifiers":[
        {
            "category":"Wholesale",
            "subcategory":"Hardware",
            "type":"Manufacturing & Wholesale Goods"
        }
    ],
    "sg:phone":"+1 214 678 9866",
    "sg:postcode":"75247",
    "sg:province":"TX",
    "sg:tags":[
        "distributor",
        "water",
        "processing",
        "manufacturer"
    ],
    "wof:name":"Global Water Technologies",
    "wof:placetype":"venue"
},
  "geometry": {"coordinates":[-96.884749,32.818822],"type":"Point"}
}