{
  "type": "Feature",
  "properties": {
    "iso:country":"US",
    "sg:address":"9791 Westheimer Rd",
    "sg:city":"Houston",
    "sg:classifiers":[
        {
            "category":"Local Transit",
            "type":"Transportation"
        }
    ],
    "sg:phone":"+1 713 781 3900",
    "sg:postcode":"77042",
    "sg:province":"TX",
    "sg:tags":[
        "passenger"
    ],
    "wof:name":"Houston Limousine Network",
    "wof:placetype":"venue"
},
  "geometry": {"coordinates":[-95.540752,29.737023],"type":"Point"}
}