{
  "type": "Feature",
  "properties": {
    "iso:country":"US",
    "sg:address":"305 Cedar St",
    "sg:city":"Cedar Hill",
    "sg:classifiers":[
        {
            "category":"Professional",
            "type":"Services"
        }
    ],
    "sg:phone":"+1 972 293 7162",
    "sg:postcode":"75104",
    "sg:province":"TX",
    "wof:name":"Scott J Spurgeon",
    "wof:placetype":"venue"
},
  "geometry": {"coordinates":[-96.953186,32.58878],"type":"Point"}
}