{
  "type": "Feature",
  "properties": {
    "iso:country":"US",
    "sg:address":"3403 McKinney St",
    "sg:city":"Melissa",
    "sg:classifiers":[
        {
            "category":"Food & Beverages",
            "subcategory":"Liquor & Beverages",
            "type":"Retail Goods"
        }
    ],
    "sg:phone":"+1 972 837 2561",
    "sg:postcode":"75454",
    "sg:province":"TX",
    "sg:tags":[
        "beer",
        "ale"
    ],
    "wof:name":"Haley's Beer & Wine",
    "wof:placetype":"venue"
},
  "geometry": {"coordinates":[-96.57061299999999,33.293188],"type":"Point"}
}