{
  "type": "Feature",
  "properties": {
    "iso:country":"US",
    "sg:address":"2625 Ridge Oak Pl",
    "sg:city":"Garland",
    "sg:classifiers":[
        {
            "category":"Manufacturing",
            "subcategory":"Printing",
            "type":"Manufacturing & Wholesale Goods"
        }
    ],
    "sg:phone":"+1 972 414 8099",
    "sg:postcode":"75044",
    "sg:province":"TX",
    "sg:tags":[
        "lithographic",
        "commercial"
    ],
    "wof:name":"English Printing Services",
    "wof:placetype":"venue"
},
  "geometry": {"coordinates":[-96.681066,32.940394],"type":"Point"}
}