{
  "type": "Feature",
  "properties": {
    "iso:country":"US",
    "sg:address":"1309 Madison St",
    "sg:city":"Weatherford",
    "sg:classifiers":[
        {
            "category":"Wholesale",
            "subcategory":"Hardware",
            "type":"Manufacturing & Wholesale Goods"
        }
    ],
    "sg:phone":"+1 817 594 6935",
    "sg:postcode":"76086",
    "sg:province":"TX",
    "wof:name":"K A A Company",
    "wof:placetype":"venue"
},
  "geometry": {"coordinates":[-97.793763,32.774926],"type":"Point"}
}