{
  "type": "Feature",
  "properties": {
    "iso:country":"US",
    "sg:address":"661 Aldine Mail Rd",
    "sg:city":"Houston",
    "sg:classifiers":[
        {
            "category":"Education",
            "subcategory":"School",
            "type":"Public Place"
        }
    ],
    "sg:phone":"+1 281 448 7650",
    "sg:postcode":"77037",
    "sg:province":"TX",
    "wof:name":"Church of God of Prophecy",
    "wof:placetype":"venue"
},
  "geometry": {"coordinates":[-95.387604,29.902201],"type":"Point"}
}