{
  "type": "Feature",
  "properties": {
    "iso:country":"US",
    "sg:address":"4550 N 1st St",
    "sg:city":"Abilene",
    "sg:classifiers":[
        {
            "category":"Professional",
            "type":"Services"
        }
    ],
    "sg:phone":"+1 325 673 8347",
    "sg:postcode":"79603",
    "sg:province":"TX",
    "sg:tags":[
        "establishment"
    ],
    "wof:name":"Ur Money Store",
    "wof:placetype":"venue"
},
  "geometry": {"coordinates":[-99.78110100000001,32.453118],"type":"Point"}
}