{
  "type": "Feature",
  "properties": {
    "iso:country":"US",
    "sg:address":"5717 W 49th Ave",
    "sg:city":"Amarillo",
    "sg:classifiers":[
        {
            "category":"Retail",
            "subcategory":"Portrait Studio",
            "type":"Services"
        }
    ],
    "sg:phone":"+1 806 359 9319",
    "sg:postcode":"79109",
    "sg:province":"TX",
    "sg:tags":[
        "photo"
    ],
    "wof:name":"Portraits In Watercolor",
    "wof:placetype":"venue"
},
  "geometry": {"coordinates":[-101.900235,35.156493],"type":"Point"}
}