{
  "type": "Feature",
  "properties": {
    "iso:country":"US",
    "sg:address":"4119 Las Palmas St",
    "sg:city":"Galveston",
    "sg:classifiers":[
        {
            "category":"Real Estate",
            "subcategory":"Real Estate Operator",
            "type":"Services"
        }
    ],
    "sg:phone":"+1 409 737 5799",
    "sg:postcode":"77554",
    "sg:province":"TX",
    "sg:tags":[
        "building",
        "nonresidential"
    ],
    "wof:name":"Galvan Properties Inc",
    "wof:placetype":"venue"
},
  "geometry": {"coordinates":[-94.944695,29.201891],"type":"Point"}
}