{
  "type": "Feature",
  "properties": {
    "iso:country":"US",
    "sg:address":"3207 S Sam Houston Rd",
    "sg:city":"Mesquite",
    "sg:classifiers":[
        {
            "category":"Retail",
            "subcategory":"Auto Repair",
            "type":"Services"
        }
    ],
    "sg:phone":"+1 972 288 3661",
    "sg:postcode":"75227",
    "sg:province":"TX",
    "sg:tags":[
        "wrecker"
    ],
    "wof:name":"Ricky's Towing & Recovery",
    "wof:placetype":"venue"
},
  "geometry": {"coordinates":[-96.64404500000001,32.762519],"type":"Point"}
}