{
  "type": "Feature",
  "properties": {
    "iso:country":"US",
    "sg:address":"2209 Rio Grande St",
    "sg:city":"Austin",
    "sg:classifiers":[
        {
            "category":"Real Estate",
            "subcategory":"Real Estate Agent",
            "type":"Services"
        }
    ],
    "sg:phone":"+1 512 531 0211",
    "sg:postcode":"78705",
    "sg:province":"TX",
    "sg:tags":[
        "management"
    ],
    "wof:name":"San Miguel Management",
    "wof:placetype":"venue"
},
  "geometry": {"coordinates":[-97.744839,30.285437],"type":"Point"}
}