{
  "type": "Feature",
  "properties": {
    "iso:country":"US",
    "sg:address":"225 N US Hwy 77",
    "sg:city":"Robstown",
    "sg:classifiers":[
        {
            "category":"Travel",
            "subcategory":"Hotels & Motels",
            "type":"Entertainment"
        }
    ],
    "sg:phone":"+1 361 387 9444",
    "sg:postcode":"78380",
    "sg:province":"TX",
    "wof:name":"Best Value Inn",
    "wof:placetype":"venue"
},
  "geometry": {"coordinates":[-97.65464799999999,27.78973],"type":"Point"}
}