{
  "type": "Feature",
  "properties": {
    "iso:country":"US",
    "sg:address":"5829 Sam Houston Pkwy",
    "sg:city":"Houston",
    "sg:classifiers":[
        {
            "category":"Professional",
            "subcategory":"Management & Consulting",
            "type":"Services"
        }
    ],
    "sg:phone":"+1 832 467 9090",
    "sg:postcode":"77049",
    "sg:province":"TX",
    "sg:tags":[
        "fire",
        "consultant",
        "protection"
    ],
    "sg:website":"www.firedsi.com",
    "wof:name":"Detection & Suppression Intl",
    "wof:placetype":"venue"
},
  "geometry": {"coordinates":[-95.163325,29.809375],"type":"Point"}
}