{
  "type": "Feature",
  "properties": {
    "iso:country":"US",
    "sg:address":"8023 Abramshire Ave",
    "sg:city":"Dallas",
    "sg:classifiers":[
        {
            "category":"Professional",
            "subcategory":"Computer Services",
            "type":"Services"
        }
    ],
    "sg:phone":"+1 214 348 2922",
    "sg:postcode":"75231",
    "sg:province":"TX",
    "sg:tags":[
        "consultant",
        "designer"
    ],
    "wof:name":"Miller Computer Technologies",
    "wof:placetype":"venue"
},
  "geometry": {"coordinates":[-96.743673,32.883494],"type":"Point"}
}