{
  "type": "Feature",
  "properties": {
    "iso:country":"US",
    "sg:address":"307 John Adams Dr",
    "sg:city":"San Antonio",
    "sg:classifiers":[
        {
            "category":"Education",
            "subcategory":"School",
            "type":"Public Place"
        }
    ],
    "sg:phone":"+1 210 732 2741",
    "sg:postcode":"78228",
    "sg:province":"TX",
    "sg:website":"www.sapaulschool.com",
    "wof:name":"St Paul's Catholic Elementary",
    "wof:placetype":"venue"
},
  "geometry": {"coordinates":[-98.548517,29.469744],"type":"Point"}
}