{
  "type": "Feature",
  "properties": {
    "iso:country":"US",
    "sg:address":"606 Oriole Blvd",
    "sg:city":"Duncanville",
    "sg:classifiers":[
        {
            "category":"Building & Trades",
            "subcategory":"Construction",
            "type":"Services"
        }
    ],
    "sg:phone":"+1 972 780 2545",
    "sg:postcode":"75116",
    "sg:province":"TX",
    "sg:tags":[
        "designer"
    ],
    "wof:name":"Power Breakthrough Inc",
    "wof:placetype":"venue"
},
  "geometry": {"coordinates":[-96.901436,32.659097],"type":"Point"}
}