{
  "type": "Feature",
  "properties": {
    "iso:country":"US",
    "sg:address":"4318 Harry Hines Blvd",
    "sg:city":"Dallas",
    "sg:classifiers":[
        {
            "category":"Travel",
            "subcategory":"Hotels & Motels",
            "type":"Entertainment"
        }
    ],
    "sg:phone":"+1 214 528 0955",
    "sg:postcode":"75219",
    "sg:province":"TX",
    "sg:tags":[
        "operation",
        "eating"
    ],
    "wof:name":"Park Crest Motel",
    "wof:placetype":"venue"
},
  "geometry": {"coordinates":[-96.82613499999999,32.805259],"type":"Point"}
}