{
  "type": "Feature",
  "properties": {
    "iso:country":"US",
    "sg:address":"24231 Pepperrell Place St",
    "sg:city":"Katy",
    "sg:classifiers":[
        {
            "category":"Professional",
            "subcategory":"Computer Services",
            "type":"Services"
        }
    ],
    "sg:phone":"+1 281 347 3344",
    "sg:postcode":"77493",
    "sg:province":"TX",
    "sg:tags":[
        "design",
        "system"
    ],
    "wof:name":"Sharon Tech Inc",
    "wof:placetype":"venue"
},
  "geometry": {"coordinates":[-95.786017,29.797532],"type":"Point"}
}