{
  "type": "Feature",
  "properties": {
    "iso:country":"US",
    "sg:address":"202 Donley Ct",
    "sg:city":"Southlake",
    "sg:classifiers":[
        {
            "category":"Shopping",
            "subcategory":"Clothing, Apparel, & Fashions",
            "type":"Retail Goods"
        }
    ],
    "sg:phone":"+1 817 481 6629",
    "sg:postcode":"76092",
    "sg:province":"TX",
    "wof:name":"Pearson Pam Natural Fabrics",
    "wof:placetype":"venue"
},
  "geometry": {"coordinates":[-97.17612099999999,32.943925],"type":"Point"}
}