{
  "type": "Feature",
  "properties": {
    "iso:country":"US",
    "sg:address":"1906 Easton Dr",
    "sg:city":"Round Rock",
    "sg:classifiers":[
        {
            "category":"Personal",
            "type":"Services"
        }
    ],
    "sg:phone":"+1 512 238 0829",
    "sg:postcode":"78664",
    "sg:province":"TX",
    "wof:name":"Lakeline Massage Associates",
    "wof:placetype":"venue"
},
  "geometry": {"coordinates":[-97.681292,30.528717],"type":"Point"}
}