{
  "type": "Feature",
  "properties": {
    "iso:country":"US",
    "sg:address":"13493 Brian Blvd",
    "sg:city":"Splendora",
    "sg:classifiers":[
        {
            "category":"Airport",
            "type":"Transportation"
        }
    ],
    "sg:phone":"+1 281 689 7257",
    "sg:postcode":"77372",
    "sg:province":"TX",
    "wof:name":"Superior Svc Tech",
    "wof:placetype":"venue"
},
  "geometry": {"coordinates":[-95.136934,30.245615],"type":"Point"}
}