{
  "type": "Feature",
  "properties": {
    "iso:country":"US",
    "sg:address":"1407 W Moore Ave",
    "sg:city":"Terrell",
    "sg:classifiers":[
        {
            "category":"Autos & Motor Vehicles",
            "subcategory":"Auto Supplies",
            "type":"Retail Goods"
        },
        {
            "category":"Building & Trades",
            "subcategory":"Plumbing",
            "type":"Services"
        },
        {
            "category":"Retail",
            "subcategory":"Auto Repair",
            "type":"Services"
        }
    ],
    "sg:phone":"+1 972 551 3999",
    "sg:postcode":"75160",
    "sg:province":"TX",
    "sg:tags":[
        "radiators-repairing",
        "rebuilding",
        "absorber",
        "transmission",
        "automobile",
        "shock",
        "equipment-service",
        "diagnostic",
        "automotive",
        "strut",
        "air conditioning",
        "tune"
    ],
    "sg:website":"http://www.aclasstransmission.com/",
    "wof:name":"A Class Transmission & Service",
    "wof:placetype":"venue"
},
  "geometry": {"coordinates":[-96.298362,32.737866],"type":"Point"}
}