{
  "type": "Feature",
  "properties": {
    "iso:country":"US",
    "sg:address":"1728 Northridge Dr",
    "sg:city":"Hurst",
    "sg:classifiers":[
        {
            "category":"Autos & Motor Vehicles",
            "subcategory":"Auto Supplies",
            "type":"Retail Goods"
        }
    ],
    "sg:phone":"+1 817 282 5161",
    "sg:postcode":"76054",
    "sg:province":"TX",
    "wof:name":"Stolen Dreams Car Club",
    "wof:placetype":"venue"
},
  "geometry": {"coordinates":[-97.162569,32.847762],"type":"Point"}
}