{
  "type": "Feature",
  "properties": {
    "iso:country":"US",
    "sg:address":"3550 S Fielder Rd",
    "sg:city":"Arlington",
    "sg:classifiers":[
        {
            "category":"Personal",
            "type":"Services"
        }
    ],
    "sg:phone":"+1 817 784 8850",
    "sg:postcode":"76015",
    "sg:province":"TX",
    "wof:name":"Euphoria Massage",
    "wof:placetype":"venue"
},
  "geometry": {"coordinates":[-97.134905,32.688339],"type":"Point"}
}