{
  "type": "Feature",
  "properties": {
    "iso:country":"US",
    "sg:address":"1715 Post Oak Blvd",
    "sg:city":"Houston",
    "sg:classifiers":[
        {
            "category":"Fast Food",
            "type":"Food & Drink"
        }
    ],
    "sg:phone":"+1 713 960 1525",
    "sg:postcode":"77056",
    "sg:province":"TX",
    "sg:tags":[
        "burger"
    ],
    "sg:website":"www.fiveguys.com",
    "wof:name":"Five Guys Burger and Fries",
    "wof:placetype":"venue"
},
  "geometry": {"coordinates":[-95.45956,29.749515],"type":"Point"}
}