{
  "type": "Feature",
  "properties": {
    "iso:country":"US",
    "sg:address":"5401 Northcrest Rd",
    "sg:city":"Fort Worth",
    "sg:classifiers":[
        {
            "category":"Wholesale",
            "subcategory":"Electrical",
            "type":"Manufacturing & Wholesale Goods"
        }
    ],
    "sg:phone":"+1 817 377 1576",
    "sg:postcode":"76107",
    "sg:province":"TX",
    "sg:tags":[
        "equipment"
    ],
    "wof:name":"McMillen DW & Assoc Inc",
    "wof:placetype":"venue"
},
  "geometry": {"coordinates":[-97.40180599999999,32.745694],"type":"Point"}
}