{
  "type": "Feature",
  "properties": {
    "iso:country":"US",
    "sg:address":"1180 Hallie St",
    "sg:city":"Vidor",
    "sg:classifiers":[
        {
            "category":"Freight",
            "type":"Transportation"
        }
    ],
    "sg:phone":"+1 409 769 9419",
    "sg:postcode":"77662",
    "sg:province":"TX",
    "sg:tags":[
        "operator",
        "trucking"
    ],
    "wof:name":"Fred W Shockome",
    "wof:placetype":"venue"
},
  "geometry": {"coordinates":[-93.99744099999999,30.124778],"type":"Point"}
}