{
  "type": "Feature",
  "properties": {
    "iso:country":"US",
    "sg:address":"703 N Wisconsin Ave",
    "sg:city":"League City",
    "sg:classifiers":[
        {
            "category":"Government",
            "subcategory":"Office",
            "type":"Public Place"
        }
    ],
    "sg:phone":"+1 281 338 4100",
    "sg:postcode":"77573",
    "sg:province":"TX",
    "sg:tags":[
        "village"
    ],
    "wof:name":"Dallas Salmon Wastewater Plant",
    "wof:placetype":"venue"
},
  "geometry": {"coordinates":[-95.09013899999999,29.51769],"type":"Point"}
}