{
  "type": "Feature",
  "properties": {
    "iso:country":"US",
    "sg:address":"10700 Stancliff Rd",
    "sg:city":"Houston",
    "sg:classifiers":[
        {
            "category":"Professional",
            "subcategory":"Computer Services",
            "type":"Services"
        }
    ],
    "sg:phone":"+1 281 437 6550",
    "sg:postcode":"77099",
    "sg:province":"TX",
    "sg:tags":[
        "repair"
    ],
    "wof:name":"Dykon Computers",
    "wof:placetype":"venue"
},
  "geometry": {"coordinates":[-95.56789499999999,29.659041],"type":"Point"}
}