{
  "type": "Feature",
  "properties": {
    "iso:country":"US",
    "sg:address":"119 Turtle Dove Dr",
    "sg:city":"Universal City",
    "sg:classifiers":[
        {
            "category":"Shopping",
            "subcategory":"Used Merchandise",
            "type":"Retail Goods"
        }
    ],
    "sg:phone":"+1 210 658 2019",
    "sg:postcode":"78148",
    "sg:province":"TX",
    "wof:name":"Memories & Morsels",
    "wof:placetype":"venue"
},
  "geometry": {"coordinates":[-98.31143299999999,29.550338],"type":"Point"}
}