{
  "type": "Feature",
  "properties": {
    "iso:country":"US",
    "sg:address":"1000 N I- 35",
    "sg:city":"Gainesville",
    "sg:classifiers":[
        {
            "category":"Wholesale",
            "subcategory":"Furniture",
            "type":"Manufacturing & Wholesale Goods"
        }
    ],
    "sg:phone":"+1 940 665 6014",
    "sg:postcode":"76240",
    "sg:province":"TX",
    "sg:tags":[
        "furnishing",
        "church"
    ],
    "sg:website":"www.gochairs.com",
    "wof:name":"Chancellor Manufacturing",
    "wof:placetype":"venue"
},
  "geometry": {"coordinates":[-97.162684,33.593051],"type":"Point"}
}