{
  "type": "Feature",
  "properties": {
    "iso:country":"US",
    "sg:address":"11967 FM 3265",
    "sg:city":"Cisco",
    "sg:classifiers":[
        {
            "category":"Shopping",
            "subcategory":"Computers & Home Electronics",
            "type":"Retail Goods"
        }
    ],
    "sg:phone":"+1 254 725 6806",
    "sg:postcode":"76437",
    "sg:province":"TX",
    "wof:name":"Personalized Computer Systems",
    "wof:placetype":"venue"
},
  "geometry": {"coordinates":[-99.157073,32.247504],"type":"Point"}
}