{
  "type": "Feature",
  "properties": {
    "iso:country":"US",
    "sg:address":"8512 Adirondack Trl",
    "sg:city":"Austin",
    "sg:classifiers":[
        {
            "category":"Retail",
            "subcategory":"Veterinary Services",
            "type":"Services"
        }
    ],
    "sg:phone":"+1 512 502 1000",
    "sg:postcode":"78759",
    "sg:province":"TX",
    "sg:tags":[
        "veterinarian"
    ],
    "wof:name":"Mobile Cat & Dog Vet",
    "wof:placetype":"venue"
},
  "geometry": {"coordinates":[-97.76226,30.383243],"type":"Point"}
}