{
  "type": "Feature",
  "properties": {
    "iso:country":"US",
    "sg:address":"3421 Harwood Dr",
    "sg:city":"Tyler",
    "sg:classifiers":[
        {
            "category":"Communications",
            "type":"Services"
        }
    ],
    "sg:phone":"+1 903 595 0826",
    "sg:postcode":"75701",
    "sg:province":"TX",
    "wof:name":"Contes Communications",
    "wof:placetype":"venue"
},
  "geometry": {"coordinates":[-95.31103299999999,32.31113],"type":"Point"}
}