{
  "type": "Feature",
  "properties": {
    "iso:country":"US",
    "sg:address":"5315 Pine St",
    "sg:city":"Bellaire",
    "sg:classifiers":[
        {
            "category":"Professional",
            "type":"Services"
        }
    ],
    "sg:phone":"+1 713 735 8568",
    "sg:postcode":"77401",
    "sg:province":"TX",
    "wof:name":"Shirley & David Toomim Foundat",
    "wof:placetype":"venue"
},
  "geometry": {"coordinates":[-95.47977899999999,29.69463],"type":"Point"}
}