{
  "type": "Feature",
  "properties": {
    "iso:country":"US",
    "sg:address":"901 Co Rd 425",
    "sg:city":"Taylor",
    "sg:classifiers":[
        {
            "category":"Restaurant",
            "type":"Food & Drink"
        }
    ],
    "sg:phone":"+1 512 365 7287",
    "sg:postcode":"76574",
    "sg:province":"TX",
    "sg:tags":[
        "eating"
    ],
    "wof:name":"Marthas Sandoval Cafe",
    "wof:placetype":"venue"
},
  "geometry": {"coordinates":[-97.29078199999999,30.640183],"type":"Point"}
}