{
  "type": "Feature",
  "properties": {
    "iso:country":"US",
    "sg:address":"9 Torrey Pines Dr",
    "sg:city":"Port Isabel",
    "sg:classifiers":[
        {
            "category":"Building & Trades",
            "subcategory":"Equipment Rental",
            "type":"Services"
        }
    ],
    "sg:phone":"+1 956 943 9431",
    "sg:postcode":"78578",
    "sg:province":"TX",
    "wof:name":"Brown & Brown Rentals",
    "wof:placetype":"venue"
},
  "geometry": {"coordinates":[-97.31131999999999,26.108351],"type":"Point"}
}