{
  "type": "Feature",
  "properties": {
    "iso:country":"US",
    "sg:address":"8312 Louetta Rd",
    "sg:city":"Spring",
    "sg:classifiers":[
        {
            "category":"Cinema",
            "subcategory":"Movie Rental",
            "type":"Entertainment"
        }
    ],
    "sg:phone":"+1 281 379 5572",
    "sg:postcode":"77379",
    "sg:province":"TX",
    "sg:tags":[
        "video",
        "tape"
    ],
    "wof:name":"Hollywood Video",
    "wof:placetype":"venue"
},
  "geometry": {"coordinates":[-95.53851899999999,30.012937],"type":"Point"}
}