{
  "type": "Feature",
  "properties": {
    "iso:country":"US",
    "sg:address":"15943 Booth Cir",
    "sg:city":"Leander",
    "sg:classifiers":[
        {
            "category":"Social Services",
            "type":"Services"
        }
    ],
    "sg:phone":"+1 512 258 1288",
    "sg:postcode":"78641",
    "sg:province":"TX",
    "wof:name":"Progressive Rehabilation Inc",
    "wof:placetype":"venue"
},
  "geometry": {"coordinates":[-97.91257899999999,30.439407],"type":"Point"}
}