{
  "type": "Feature",
  "properties": {
    "iso:country":"US",
    "sg:address":"718 Serenade Dr",
    "sg:city":"San Antonio",
    "sg:classifiers":[
        {
            "category":"Professional",
            "subcategory":"Lawyer & Legal Services",
            "type":"Services"
        }
    ],
    "sg:phone":"+1 210 525 1458",
    "sg:postcode":"78216",
    "sg:province":"TX",
    "wof:name":"Jeffery R Schaub",
    "wof:placetype":"venue"
},
  "geometry": {"coordinates":[-98.506154,29.543258],"type":"Point"}
}