{
  "type": "Feature",
  "properties": {
    "iso:country":"US",
    "sg:address":"1600 E Loop 304",
    "sg:city":"Crockett",
    "sg:classifiers":[
        {
            "category":"Travel",
            "subcategory":"Hotels & Motels",
            "type":"Entertainment"
        },
        {
            "category":"Travel",
            "subcategory":"Bed & Breakfast",
            "type":"Entertainment"
        }
    ],
    "sg:phone":"+1 936 544 5611",
    "sg:postcode":"75835",
    "sg:province":"TX",
    "sg:tags":[
        "inn",
        "lodging"
    ],
    "wof:name":"Crockett Inn",
    "wof:placetype":"venue"
},
  "geometry": {"coordinates":[-95.44746000000001,31.298919],"type":"Point"}
}