{
  "type": "Feature",
  "properties": {
    "iso:country":"US",
    "sg:address":"2332 Guadalupe St",
    "sg:city":"Austin",
    "sg:classifiers":[
        {
            "category":"Shopping",
            "subcategory":"Clothing, Apparel, & Fashions",
            "type":"Retail Goods"
        },
        {
            "category":"Shopping",
            "subcategory":"Jewelry",
            "type":"Retail Goods"
        }
    ],
    "sg:phone":"+1 512 391 9009",
    "sg:postcode":"78705",
    "sg:province":"TX",
    "sg:tags":[
        "apparel",
        "women's"
    ],
    "sg:website":"www.ishopaac.com",
    "wof:name":"Wish",
    "wof:placetype":"venue"
},
  "geometry": {"coordinates":[-97.74165600000001,30.286894],"type":"Point"}
}