{
  "type": "Feature",
  "properties": {
    "iso:country":"US",
    "sg:address":"1600 Western Oaks Dr",
    "sg:city":"Waco",
    "sg:classifiers":[
        {
            "category":"Sports & Exercise",
            "subcategory":"Golf",
            "type":"Entertainment"
        },
        {
            "category":"Recreation",
            "type":"Entertainment"
        }
    ],
    "sg:phone":"+1 254 772 8100",
    "sg:postcode":"76712",
    "sg:province":"TX",
    "sg:tags":[
        "course",
        "public"
    ],
    "wof:name":"Rolling Oaks Gulf Club",
    "wof:placetype":"venue"
},
  "geometry": {"coordinates":[-97.23032600000001,31.515933],"type":"Point"}
}