{
  "type": "Feature",
  "properties": {
    "iso:country":"US",
    "sg:address":"15570 Kilowatt Rd",
    "sg:city":"Elmendorf",
    "sg:classifiers":[
        {
            "category":"Manufacturing",
            "subcategory":"Tools & Machinery",
            "type":"Manufacturing & Wholesale Goods"
        }
    ],
    "sg:phone":"+1 210 635 8232",
    "sg:postcode":"78112",
    "sg:province":"TX",
    "sg:tags":[
        "machine",
        "shop"
    ],
    "wof:name":"Leach Equipment",
    "wof:placetype":"venue"
},
  "geometry": {"coordinates":[-98.327145,29.264299],"type":"Point"}
}