{
  "type": "Feature",
  "properties": {
    "iso:country":"US",
    "sg:address":"2224 W Park Row Dr",
    "sg:city":"Pantego",
    "sg:classifiers":[
        {
            "category":"Wholesale",
            "subcategory":"Medical Equipment & Supplies",
            "type":"Manufacturing & Wholesale Goods"
        }
    ],
    "sg:phone":"+1 817 460 7800",
    "sg:postcode":"76013",
    "sg:province":"TX",
    "sg:tags":[
        "physician",
        "surgeon"
    ],
    "wof:name":"Pantego Medical",
    "wof:placetype":"venue"
},
  "geometry": {"coordinates":[-97.142481,32.721204],"type":"Point"}
}