{
  "type": "Feature",
  "properties": {
    "iso:country":"US",
    "sg:address":"1400 N Main St",
    "sg:city":"Baytown",
    "sg:classifiers":[
        {
            "category":"Autos & Motor Vehicles",
            "subcategory":"Automobile Sales",
            "type":"Retail Goods"
        }
    ],
    "sg:phone":"+1 281 422 5055",
    "sg:postcode":"77520",
    "sg:province":"TX",
    "sg:tags":[
        "used",
        "truck"
    ],
    "wof:name":"Country Club Motors",
    "wof:placetype":"venue"
},
  "geometry": {"coordinates":[-94.96366500000001,29.742952],"type":"Point"}
}