{
  "type": "Feature",
  "properties": {
    "iso:country":"US",
    "sg:address":"308 W 2nd St",
    "sg:city":"Weatherford",
    "sg:classifiers":[
        {
            "category":"Personal",
            "subcategory":"Beauty Salon",
            "type":"Services"
        }
    ],
    "sg:phone":"+1 817 613 9737",
    "sg:postcode":"76086",
    "sg:province":"TX",
    "wof:name":"Steel Magnolias",
    "wof:placetype":"venue"
},
  "geometry": {"coordinates":[-97.801385,32.771189],"type":"Point"}
}