{
  "type": "Feature",
  "properties": {
    "iso:country":"US",
    "sg:address":"206 Dolomita St",
    "sg:city":"Borger",
    "sg:classifiers":[
        {
            "category":"Retail",
            "subcategory":"Laundry & Dry Cleaning",
            "type":"Services"
        }
    ],
    "sg:phone":"+1 806 273 7271",
    "sg:postcode":"79007",
    "sg:province":"TX",
    "wof:name":"Something Fitting",
    "wof:placetype":"venue"
},
  "geometry": {"coordinates":[-101.44943499999999,35.652122],"type":"Point"}
}