{
  "type": "Feature",
  "properties": {
    "iso:country":"US",
    "sg:address":"5715 Monterey St",
    "sg:city":"San Antonio",
    "sg:classifiers":[
        {
            "category":"Building & Trades",
            "subcategory":"Construction",
            "type":"Services"
        }
    ],
    "sg:phone":"+1 210 435 5779",
    "sg:postcode":"78237",
    "sg:province":"TX",
    "sg:tags":[
        "concrete",
        "contractor"
    ],
    "wof:name":"D M Readymix",
    "wof:placetype":"venue"
},
  "geometry": {"coordinates":[-98.567374,29.430137],"type":"Point"}
}