{
  "type": "Feature",
  "properties": {
    "iso:country":"US",
    "sg:address":"201 College Main",
    "sg:city":"College Station",
    "sg:classifiers":[
        {
            "category":"Restaurant",
            "type":"Food & Drink"
        }
    ],
    "sg:phone":"+1 512 845 3319",
    "sg:postcode":"77840",
    "sg:province":"TX",
    "sg:tags":[
        "bar"
    ],
    "wof:name":"Logans On Campus",
    "wof:placetype":"venue"
},
  "geometry": {"coordinates":[-96.346425,30.619201],"type":"Point"}
}