{
  "type": "Feature",
  "properties": {
    "iso:country":"US",
    "sg:address":"745 Jones St",
    "sg:city":"Bridge City",
    "sg:classifiers":[
        {
            "category":"Professional",
            "type":"Services"
        }
    ],
    "sg:phone":"+1 409 735 2900",
    "sg:postcode":"77611",
    "sg:province":"TX",
    "sg:tags":[
        "establishment"
    ],
    "wof:name":"Industrial Bike Shop",
    "wof:placetype":"venue"
},
  "geometry": {"coordinates":[-93.819091,30.025665],"type":"Point"}
}