{
  "type": "Feature",
  "properties": {
    "iso:country":"US",
    "sg:address":"2624 Beeman Dr",
    "sg:city":"Mesquite",
    "sg:classifiers":[
        {
            "category":"Wholesale",
            "subcategory":"Machinery & Supplies",
            "type":"Manufacturing & Wholesale Goods"
        }
    ],
    "sg:phone":"+1 972 222 1687",
    "sg:postcode":"75181",
    "sg:province":"TX",
    "sg:tags":[
        "equipment",
        "establishment"
    ],
    "wof:name":"Mr Fabulous Beauty Supply",
    "wof:placetype":"venue"
},
  "geometry": {"coordinates":[-96.559663,32.757761],"type":"Point"}
}