{
  "type": "Feature",
  "properties": {
    "iso:country":"US",
    "sg:address":"5808 New Territory Blvd",
    "sg:city":"Sugar Land",
    "sg:classifiers":[
        {
            "category":"Shopping",
            "subcategory":"Jewelry",
            "type":"Retail Goods"
        }
    ],
    "sg:phone":"+1 281 491 6060",
    "sg:postcode":"77479",
    "sg:province":"TX",
    "wof:name":"Jimmys Fine Jewelers",
    "wof:placetype":"venue"
},
  "geometry": {"coordinates":[-95.661833,29.589914],"type":"Point"}
}