{
  "type": "Feature",
  "properties": {
    "iso:country":"US",
    "sg:address":"604 Brazos St",
    "sg:city":"Austin",
    "sg:classifiers":[
        {
            "category":"Restaurant",
            "type":"Food & Drink"
        }
    ],
    "sg:phone":"+1 512 474 5625",
    "sg:postcode":"78701",
    "sg:province":"TX",
    "wof:name":"Scandals Restaurant",
    "wof:placetype":"venue"
},
  "geometry": {"coordinates":[-97.741193,30.268588],"type":"Point"}
}