{
  "type": "Feature",
  "properties": {
    "iso:country":"US",
    "sg:address":"3008 Tampico Ave",
    "sg:city":"Hidalgo",
    "sg:classifiers":[
        {
            "category":"Personal",
            "subcategory":"Adult",
            "type":"Services"
        }
    ],
    "sg:phone":"+1 956 843 4911",
    "sg:postcode":"78557",
    "sg:province":"TX",
    "sg:tags":[
        "escort"
    ],
    "wof:name":"Special Moments",
    "wof:placetype":"venue"
},
  "geometry": {"coordinates":[-98.229086,26.102362],"type":"Point"}
}