{
  "type": "Feature",
  "properties": {
    "iso:country":"US",
    "sg:address":"327 Maple St",
    "sg:city":"Richardson",
    "sg:classifiers":[
        {
            "category":"Building & Trades",
            "subcategory":"Cleaning & Sanitation",
            "type":"Services"
        }
    ],
    "sg:phone":"+1 214 553 4231",
    "sg:postcode":"75081",
    "sg:province":"TX",
    "sg:tags":[
        "maintenance"
    ],
    "wof:name":"Dailely Cleaning Team",
    "wof:placetype":"venue"
},
  "geometry": {"coordinates":[-96.72962800000001,32.94132],"type":"Point"}
}