{
  "type": "Feature",
  "properties": {
    "iso:country":"US",
    "sg:address":"517 W 22nd St",
    "sg:city":"Houston",
    "sg:classifiers":[
        {
            "category":"Building & Trades",
            "subcategory":"Construction",
            "type":"Services"
        }
    ],
    "sg:phone":"+1 713 426 0355",
    "sg:postcode":"77008",
    "sg:province":"TX",
    "sg:tags":[
        "repairing",
        "remodeling",
        "contractor"
    ],
    "wof:name":"Kelley & King",
    "wof:placetype":"venue"
},
  "geometry": {"coordinates":[-95.407768,29.805945],"type":"Point"}
}