{
  "type": "Feature",
  "properties": {
    "iso:country":"US",
    "sg:address":"711 Gabriel Dr",
    "sg:city":"Tyler",
    "sg:classifiers":[
        {
            "category":"Real Estate",
            "subcategory":"Real Estate Agent",
            "type":"Services"
        }
    ],
    "sg:phone":"+1 903 561 8236",
    "sg:postcode":"75701",
    "sg:province":"TX",
    "wof:name":"Dynamic Properties",
    "wof:placetype":"venue"
},
  "geometry": {"coordinates":[-95.310394,32.309619],"type":"Point"}
}