{
  "type": "Feature",
  "properties": {
    "iso:country":"US",
    "sg:address":"2025 Proctor Ave",
    "sg:city":"Waco",
    "sg:classifiers":[
        {
            "category":"Restaurant",
            "type":"Food & Drink"
        }
    ],
    "sg:phone":"+1 254 756 4554",
    "sg:postcode":"76708",
    "sg:province":"TX",
    "sg:tags":[
        "eating"
    ],
    "wof:name":"Red Barn Inc",
    "wof:placetype":"venue"
},
  "geometry": {"coordinates":[-97.164267,31.564272],"type":"Point"}
}