{
  "type": "Feature",
  "properties": {
    "iso:country":"US",
    "sg:address":"2039 S Wheeler St",
    "sg:city":"Jasper",
    "sg:classifiers":[
        {
            "category":"Restaurant",
            "type":"Food & Drink"
        }
    ],
    "sg:phone":"+1 409 384 3224",
    "sg:postcode":"75951",
    "sg:province":"TX",
    "wof:name":"LA Herradura",
    "wof:placetype":"venue"
},
  "geometry": {"coordinates":[-93.99299499999999,30.897926],"type":"Point"}
}