{
  "type": "Feature",
  "properties": {
    "iso:country":"US",
    "sg:address":"12267 Veterans Memorial Dr",
    "sg:city":"Houston",
    "sg:classifiers":[
        {
            "category":"Utilities",
            "subcategory":"Mobile Phone",
            "type":"Services"
        }
    ],
    "sg:phone":"+1 832 375 0303",
    "sg:postcode":"77067",
    "sg:province":"TX",
    "sg:tags":[
        "telephone",
        "cellular"
    ],
    "wof:name":"Best Connections Wireless",
    "wof:placetype":"venue"
},
  "geometry": {"coordinates":[-95.481083,29.964941],"type":"Point"}
}