{
  "type": "Feature",
  "properties": {
    "iso:country":"US",
    "sg:address":"9103 Summer Glen Ln",
    "sg:city":"Dallas",
    "sg:classifiers":[
        {
            "category":"Professional",
            "subcategory":"Art Services",
            "type":"Services"
        }
    ],
    "sg:phone":"+1 214 341 1911",
    "sg:postcode":"75243",
    "sg:province":"TX",
    "sg:tags":[
        "artist"
    ],
    "sg:website":"www.scobiemusic.com",
    "wof:name":"WSA Artist Management",
    "wof:placetype":"venue"
},
  "geometry": {"coordinates":[-96.744501,32.895379],"type":"Point"}
}