{
  "type": "Feature",
  "properties": {
    "iso:country":"US",
    "sg:address":"108 Professional Park Dr",
    "sg:city":"Victoria",
    "sg:classifiers":[
        {
            "category":"Health Services",
            "subcategory":"Doctor",
            "type":"Services"
        }
    ],
    "sg:phone":"+1 361 573 7464",
    "sg:postcode":"77904",
    "sg:province":"TX",
    "sg:tags":[
        "clinic"
    ],
    "wof:name":"H Ellwood Ernst Inc",
    "wof:placetype":"venue"
},
  "geometry": {"coordinates":[-96.98681999999999,28.841407],"type":"Point"}
}