{
  "type": "Feature",
  "properties": {
    "iso:country":"US",
    "sg:address":"9750 S Padre Island Dr",
    "sg:city":"Corpus Christi",
    "sg:classifiers":[
        {
            "category":"Real Estate",
            "subcategory":"Real Estate Agent",
            "type":"Services"
        }
    ],
    "sg:phone":"+1 361 937 9180",
    "sg:postcode":"78418",
    "sg:province":"TX",
    "wof:name":"Jjg Properties",
    "wof:placetype":"venue"
},
  "geometry": {"coordinates":[-97.29476099999999,27.674742],"type":"Point"}
}