{
  "type": "Feature",
  "properties": {
    "iso:country":"US",
    "sg:address":"2500 US Hwy 281 Bus",
    "sg:city":"Edinburg",
    "sg:classifiers":[
        {
            "category":"Personal",
            "subcategory":"Beauty Salon",
            "type":"Services"
        }
    ],
    "sg:phone":"+1 956 383 4444",
    "sg:postcode":"78539",
    "sg:province":"TX",
    "wof:name":"Main Street Hair Co",
    "wof:placetype":"venue"
},
  "geometry": {"coordinates":[-98.169439,26.277284],"type":"Point"}
}