{
  "type": "Feature",
  "properties": {
    "iso:country":"US",
    "sg:address":"902 Market St",
    "sg:city":"Portland",
    "sg:classifiers":[
        {
            "category":"Retail",
            "subcategory":"Auto Rental",
            "type":"Services"
        }
    ],
    "sg:phone":"+1 361 643 6850",
    "sg:postcode":"78374",
    "sg:province":"TX",
    "sg:tags":[
        "renting",
        "automobile"
    ],
    "wof:name":"Hertz Rent A Car",
    "wof:placetype":"venue"
},
  "geometry": {"coordinates":[-97.321523,27.877346],"type":"Point"}
}