{
  "type": "Feature",
  "properties": {
    "iso:country":"US",
    "sg:address":"906 W Randol Mill Rd",
    "sg:city":"Arlington",
    "sg:classifiers":[
        {
            "category":"Health Services",
            "subcategory":"Doctor",
            "type":"Services"
        },
        {
            "category":"Health Services",
            "subcategory":"Clinic",
            "type":"Services"
        }
    ],
    "sg:phone":"+1 817 261 4906",
    "sg:postcode":"76012",
    "sg:province":"TX",
    "sg:tags":[
        "physician",
        "oncology",
        "cancer",
        "medical",
        "surgeons",
        "treatment"
    ],
    "sg:website":"http://www.acc-tx.com",
    "wof:name":"Arlington Cancer Center",
    "wof:placetype":"venue"
},
  "geometry": {"coordinates":[-97.118526,32.75016],"type":"Point"}
}