{
  "type": "Feature",
  "properties": {
    "iso:country":"US",
    "sg:address":"231 N I Rd",
    "sg:city":"Pharr",
    "sg:classifiers":[
        {
            "category":"Social Services",
            "subcategory":"Child Care",
            "type":"Services"
        }
    ],
    "sg:phone":"+1 956 702 7176",
    "sg:postcode":"78577",
    "sg:province":"TX",
    "sg:tags":[
        "day"
    ],
    "wof:name":"Kids Care & Development",
    "wof:placetype":"venue"
},
  "geometry": {"coordinates":[-98.16723500000001,26.194855],"type":"Point"}
}