{
  "type": "Feature",
  "properties": {
    "iso:country":"US",
    "sg:address":"13215 Veterans Memorial Dr",
    "sg:city":"Houston",
    "sg:classifiers":[
        {
            "category":"Retail",
            "subcategory":"Self-service Laundry",
            "type":"Services"
        }
    ],
    "sg:phone":"+1 281 583 9773",
    "sg:postcode":"77014",
    "sg:province":"TX",
    "wof:name":"Klein Laundromat",
    "wof:placetype":"venue"
},
  "geometry": {"coordinates":[-95.492035,29.97932],"type":"Point"}
}