{
  "type": "Feature",
  "properties": {
    "iso:country":"US",
    "sg:address":"22206 Saddlewood",
    "sg:city":"Katy",
    "sg:classifiers":[
        {
            "category":"Freight",
            "type":"Transportation"
        }
    ],
    "sg:phone":"+1 281 371 3689",
    "sg:postcode":"77449",
    "sg:province":"TX",
    "sg:tags":[
        "operator",
        "local",
        "trucking"
    ],
    "wof:name":"RE Trucking",
    "wof:placetype":"venue"
},
  "geometry": {"coordinates":[-95.761807,29.857355],"type":"Point"}
}