{
  "type": "Feature",
  "properties": {
    "iso:country":"US",
    "sg:address":"108 W County Line Rd",
    "sg:city":"Royse City",
    "sg:classifiers":[
        {
            "category":"Building & Trades",
            "subcategory":"Construction",
            "type":"Services"
        }
    ],
    "sg:phone":"+1 214 563 0523",
    "sg:postcode":"75189",
    "sg:province":"TX",
    "sg:tags":[
        "utility"
    ],
    "wof:name":"Oktex Utility Contsruction Inc",
    "wof:placetype":"venue"
},
  "geometry": {"coordinates":[-96.37084400000001,32.98216],"type":"Point"}
}