{
  "type": "Feature",
  "properties": {
    "iso:country":"US",
    "sg:address":"5131 Lakeshore Dr",
    "sg:city":"Wichita Falls",
    "sg:classifiers":[
        {
            "category":"Building & Trades",
            "subcategory":"Landscaping Services",
            "type":"Services"
        }
    ],
    "sg:phone":"+1 940 691 6025",
    "sg:postcode":"76310",
    "sg:province":"TX",
    "wof:name":"Henrys Lawn Care",
    "wof:placetype":"venue"
},
  "geometry": {"coordinates":[-98.575396,33.842425],"type":"Point"}
}