{
  "type": "Feature",
  "properties": {
    "iso:country":"US",
    "sg:address":"1806 Stone Rd",
    "sg:city":"Pearland",
    "sg:classifiers":[
        {
            "category":"Retail",
            "subcategory":"Auto Repair",
            "type":"Services"
        }
    ],
    "sg:phone":"+1 281 997 1441",
    "sg:postcode":"77581",
    "sg:province":"TX",
    "sg:tags":[
        "body",
        "automobile",
        "painting"
    ],
    "wof:name":"Eric's Custom Finishes",
    "wof:placetype":"venue"
},
  "geometry": {"coordinates":[-95.340439,29.578644],"type":"Point"}
}