{
  "type": "Feature",
  "properties": {
    "iso:country":"US",
    "sg:address":"3803 Hitchrock Dr",
    "sg:city":"Killeen",
    "sg:classifiers":[
        {
            "category":"Retail",
            "subcategory":"Portrait Studio",
            "type":"Services"
        }
    ],
    "sg:phone":"+1 254 526 0101",
    "sg:postcode":"76549",
    "sg:province":"TX",
    "sg:tags":[
        "photo"
    ],
    "wof:name":"Art Vision Photography",
    "wof:placetype":"venue"
},
  "geometry": {"coordinates":[-97.77294500000001,31.092044],"type":"Point"}
}