{
  "type": "Feature",
  "properties": {
    "iso:country":"US",
    "sg:address":"1613 Judson Rd",
    "sg:city":"Longview",
    "sg:classifiers":[
        {
            "category":"Wholesale",
            "subcategory":"Machinery & Supplies",
            "type":"Manufacturing & Wholesale Goods"
        },
        {
            "category":"Retail",
            "subcategory":"Veterinary Services",
            "type":"Services"
        }
    ],
    "sg:phone":"+1 903 757 5543",
    "sg:postcode":"75601",
    "sg:province":"TX",
    "sg:tags":[
        "equipment",
        "hospital",
        "clinic",
        "kennel"
    ],
    "wof:name":"Kimbrough Animal Hospital",
    "wof:placetype":"venue"
},
  "geometry": {"coordinates":[-94.74241600000001,32.523067],"type":"Point"}
}