{
  "type": "Feature",
  "properties": {
    "iso:country":"US",
    "sg:address":"5618 Magnolia Ln",
    "sg:city":"Rowlett",
    "sg:classifiers":[
        {
            "category":"Restaurant",
            "type":"Food & Drink"
        }
    ],
    "sg:phone":"+1 214 607 0250",
    "sg:postcode":"75089",
    "sg:province":"TX",
    "sg:tags":[
        "eating"
    ],
    "wof:name":"Kitchen Magician",
    "wof:placetype":"venue"
},
  "geometry": {"coordinates":[-96.570294,32.91141],"type":"Point"}
}