{
  "type": "Feature",
  "properties": {
    "iso:country":"US",
    "sg:address":"5620 Colusa Dr",
    "sg:city":"Fort Worth",
    "sg:classifiers":[
        {
            "category":"Professional",
            "subcategory":"Business Services",
            "type":"Services"
        }
    ],
    "sg:phone":"+1 817 292 5756",
    "sg:postcode":"76133",
    "sg:province":"TX",
    "sg:tags":[
        "inspection"
    ],
    "wof:name":"Rollins Welding Consulting Inc",
    "wof:placetype":"venue"
},
  "geometry": {"coordinates":[-97.36688100000001,32.662594],"type":"Point"}
}