{
  "type": "Feature",
  "properties": {
    "iso:country":"US",
    "sg:address":"212 Moore Ave",
    "sg:city":"Moulton",
    "sg:classifiers":[
        {
            "category":"Real Estate",
            "subcategory":"Real Estate Agent",
            "type":"Services"
        }
    ],
    "sg:phone":"+1 361 596 8282",
    "sg:postcode":"77975",
    "sg:province":"TX",
    "wof:name":"Peach Creek Realty",
    "wof:placetype":"venue"
},
  "geometry": {"coordinates":[-97.142816,29.57482],"type":"Point"}
}