{
  "type": "Feature",
  "properties": {
    "iso:country":"US",
    "sg:address":"12885 US Hwy 281",
    "sg:city":"Perrin",
    "sg:classifiers":[
        {
            "category":"Retail",
            "subcategory":"Repair Shop",
            "type":"Services"
        }
    ],
    "sg:phone":"+1 940 798 2351",
    "sg:postcode":"76486",
    "sg:province":"TX",
    "wof:name":"Burton Cornish Septic Service",
    "wof:placetype":"venue"
},
  "geometry": {"coordinates":[-98.06414100000001,32.980789],"type":"Point"}
}