{
  "type": "Feature",
  "properties": {
    "iso:country":"US",
    "sg:address":"546 Johnson Dr",
    "sg:city":"Duncanville",
    "sg:classifiers":[
        {
            "category":"Building & Trades",
            "subcategory":"Construction",
            "type":"Services"
        }
    ],
    "sg:phone":"+1 972 296 4479",
    "sg:postcode":"75116",
    "sg:province":"TX",
    "sg:tags":[
        "residential"
    ],
    "wof:name":"Sandidge Construction Co",
    "wof:placetype":"venue"
},
  "geometry": {"coordinates":[-96.89923,32.656749],"type":"Point"}
}