{
  "type": "Feature",
  "properties": {
    "iso:country":"US",
    "sg:address":"1045 Dewalt St",
    "sg:city":"Houston",
    "sg:classifiers":[
        {
            "category":"Shopping",
            "subcategory":"Gifts & Souvenirs",
            "type":"Retail Goods"
        }
    ],
    "sg:phone":"+1 281 272 9558",
    "sg:postcode":"77088",
    "sg:province":"TX",
    "wof:name":"Elite Social Stationary",
    "wof:placetype":"venue"
},
  "geometry": {"coordinates":[-95.42477100000001,29.882283],"type":"Point"}
}