{
  "type": "Feature",
  "properties": {
    "iso:country":"US",
    "sg:address":"7008 N Co Rd 1298",
    "sg:city":"Midland",
    "sg:classifiers":[
        {
            "category":"Building & Trades",
            "subcategory":"Landscaping Services",
            "type":"Services"
        }
    ],
    "sg:phone":"+1 432 561 8802",
    "sg:postcode":"79707",
    "sg:province":"TX",
    "sg:tags":[
        "landscape"
    ],
    "wof:name":"Kut Rite Tree & Lawn",
    "wof:placetype":"venue"
},
  "geometry": {"coordinates":[-102.285127,32.030503],"type":"Point"}
}