{
  "type": "Feature",
  "properties": {
    "iso:country":"US",
    "sg:address":"10538 Lakebrook Dr",
    "sg:city":"Houston",
    "sg:classifiers":[
        {
            "category":"Shopping",
            "subcategory":"Discount & Variety Stores",
            "type":"Retail Goods"
        }
    ],
    "sg:phone":"+1 281 820 3174",
    "sg:postcode":"77038",
    "sg:province":"TX",
    "sg:tags":[
        "merchandise",
        "general"
    ],
    "wof:name":"Jiles Internet Shopping",
    "wof:placetype":"venue"
},
  "geometry": {"coordinates":[-95.442853,29.925052],"type":"Point"}
}