{
  "type": "Feature",
  "properties": {
    "iso:country":"US",
    "sg:address":"130 W Ave B",
    "sg:city":"Garland",
    "sg:classifiers":[
        {
            "category":"Autos & Motor Vehicles",
            "subcategory":"Automobile Sales",
            "type":"Retail Goods"
        }
    ],
    "sg:phone":"+1 972 494 5677",
    "sg:postcode":"75040",
    "sg:province":"TX",
    "sg:tags":[
        "car",
        "used",
        "dealer"
    ],
    "wof:name":"R & M Auto Sales  Inc",
    "wof:placetype":"venue"
},
  "geometry": {"coordinates":[-96.63329400000001,32.91072],"type":"Point"}
}