{
  "type": "Feature",
  "properties": {
    "iso:country":"US",
    "sg:address":"5612 Reiger Ave",
    "sg:city":"Dallas",
    "sg:classifiers":[
        {
            "category":"Professional",
            "subcategory":"Business Services",
            "type":"Services"
        }
    ],
    "sg:phone":"+1 972 475 1446",
    "sg:postcode":"75214",
    "sg:province":"TX",
    "wof:name":"Touchstone Realty",
    "wof:placetype":"venue"
},
  "geometry": {"coordinates":[-96.75630700000001,32.802789],"type":"Point"}
}