{
  "type": "Feature",
  "properties": {
    "iso:country":"US",
    "sg:address":"110 E Main St",
    "sg:city":"Henderson",
    "sg:classifiers":[
        {
            "category":"Restaurant",
            "type":"Food & Drink"
        }
    ],
    "sg:phone":"+1 903 655 1565",
    "sg:postcode":"75652",
    "sg:province":"TX",
    "sg:tags":[
        "eating"
    ],
    "wof:name":"Blessings",
    "wof:placetype":"venue"
},
  "geometry": {"coordinates":[-94.79939899999999,32.153167],"type":"Point"}
}