{
  "type": "Feature",
  "properties": {
    "iso:country":"US",
    "sg:address":"1610 Club Cir",
    "sg:city":"Salado",
    "sg:classifiers":[
        {
            "category":"Restaurant",
            "type":"Food & Drink"
        }
    ],
    "sg:phone":"+1 254 947 5141",
    "sg:postcode":"76571",
    "sg:province":"TX",
    "sg:website":"www.millcreekgolfresort.com",
    "wof:name":"Mill Creek Inn & Country Club",
    "wof:placetype":"venue"
},
  "geometry": {"coordinates":[-97.51588,30.954853],"type":"Point"}
}