{
  "type": "Feature",
  "properties": {
    "iso:country":"US",
    "sg:address":"713 Hebron Parkway, Suite #290",
    "sg:city":"Lewisville",
    "sg:classifiers":[
        {
            "category":"Food & Beverages",
            "subcategory":"Bakery",
            "type":"Retail Goods"
        }
    ],
    "sg:phone":"+1 214 488 8900",
    "sg:postcode":"75057",
    "sg:province":"TX",
    "sg:tags":[
        "sandwich"
    ],
    "sg:website":"www.dagwoods.us.com",
    "wof:name":"Dagwood's Sandwich Shoppe",
    "wof:placetype":"venue"
},
  "geometry": {"coordinates":[-96.96936599999999,33.009495],"type":"Point"}
}