{
  "type": "Feature",
  "properties": {
    "iso:country":"US",
    "sg:address":"425 W Main St",
    "sg:city":"Baytown",
    "sg:classifiers":[
        {
            "category":"Utilities",
            "subcategory":"Refuse",
            "type":"Services"
        },
        {
            "category":"Wholesale",
            "subcategory":"Scrap",
            "type":"Manufacturing & Wholesale Goods"
        }
    ],
    "sg:phone":"+1 281 427 6180",
    "sg:postcode":"77520",
    "sg:province":"TX",
    "sg:tags":[
        "recycling",
        "center",
        "system"
    ],
    "wof:name":"A Baytown Recycling Center",
    "wof:placetype":"venue"
},
  "geometry": {"coordinates":[-94.975782,29.721347],"type":"Point"}
}