{
  "type": "Feature",
  "properties": {
    "iso:country":"US",
    "sg:address":"605 3rd St",
    "sg:city":"Graham",
    "sg:classifiers":[
        {
            "category":"Professional",
            "type":"Services"
        }
    ],
    "sg:phone":"+1 940 549 8210",
    "sg:postcode":"76450",
    "sg:province":"TX",
    "sg:tags":[
        "consultant",
        "geological"
    ],
    "wof:name":"Bob Antle",
    "wof:placetype":"venue"
},
  "geometry": {"coordinates":[-98.58950299999999,33.105963],"type":"Point"}
}