{
  "type": "Feature",
  "properties": {
    "iso:country":"US",
    "sg:address":"4821 Honeysuckle Dr",
    "sg:city":"Mesquite",
    "sg:classifiers":[
        {
            "category":"Building & Trades",
            "subcategory":"Construction",
            "type":"Services"
        }
    ],
    "sg:phone":"+1 972 557 7504",
    "sg:postcode":"75180",
    "sg:province":"TX",
    "sg:tags":[
        "resurfacing",
        "laying",
        "refinishing",
        "floor"
    ],
    "wof:name":"Floorco",
    "wof:placetype":"venue"
},
  "geometry": {"coordinates":[-96.61371800000001,32.702892],"type":"Point"}
}