{
  "type": "Feature",
  "properties": {
    "iso:country":"US",
    "sg:address":"105 Reina Esther Dr",
    "sg:city":"Brownsville",
    "sg:classifiers":[
        {
            "category":"Professional",
            "type":"Services"
        }
    ],
    "sg:phone":"+1 956 544 5287",
    "sg:postcode":"78521",
    "sg:province":"TX",
    "wof:name":"Doors & Doors",
    "wof:placetype":"venue"
},
  "geometry": {"coordinates":[-97.464496,25.918299],"type":"Point"}
}