{
  "type": "Feature",
  "properties": {
    "iso:country":"US",
    "sg:address":"2158 Portsmouth St",
    "sg:city":"Houston",
    "sg:classifiers":[
        {
            "category":"Health Services",
            "subcategory":"Health Practitioner",
            "type":"Services"
        }
    ],
    "sg:phone":"+1 713 529 4990",
    "sg:postcode":"77098",
    "sg:province":"TX",
    "sg:tags":[
        "therapy",
        "physical"
    ],
    "wof:name":"Select Physical Therapy",
    "wof:placetype":"venue"
},
  "geometry": {"coordinates":[-95.412217,29.733576],"type":"Point"}
}