{
  "type": "Feature",
  "properties": {
    "iso:country":"US",
    "sg:address":"2411 E Mlk J",
    "sg:city":"Austin",
    "sg:classifiers":[
        {
            "category":"Food & Beverages",
            "subcategory":"Meat & Fish",
            "type":"Retail Goods"
        }
    ],
    "sg:phone":"+1 512 476 5223",
    "sg:postcode":"78702",
    "sg:province":"TX",
    "sg:tags":[
        "shop"
    ],
    "wof:name":"Long Horn Meat Market",
    "wof:placetype":"venue"
},
  "geometry": {"coordinates":[-97.71630999999999,30.264019],"type":"Point"}
}