{
  "type": "Feature",
  "properties": {
    "iso:country":"US",
    "sg:address":"17123 FM 442",
    "sg:city":"Needville",
    "sg:classifiers":[
        {
            "category":"Organizations",
            "subcategory":"Religious Organization",
            "type":"Services"
        }
    ],
    "sg:phone":"+1 979 793 7217",
    "sg:postcode":"77461",
    "sg:province":"TX",
    "wof:name":"New Prospect Baptist Church",
    "wof:placetype":"venue"
},
  "geometry": {"coordinates":[-95.855689,29.338875],"type":"Point"}
}