{
  "type": "Feature",
  "properties": {
    "iso:country":"US",
    "sg:address":"1904 Pappas St",
    "sg:city":"Laredo",
    "sg:classifiers":[
        {
            "category":"Government",
            "subcategory":"Office",
            "type":"Public Place"
        }
    ],
    "sg:phone":"+1 956 722 3242",
    "sg:postcode":"78044",
    "sg:province":"TX",
    "sg:tags":[
        "federal"
    ],
    "wof:name":"Us Faa",
    "wof:placetype":"venue"
},
  "geometry": {"coordinates":[-99.475533,27.536226],"type":"Point"}
}