{
  "type": "Feature",
  "properties": {
    "iso:country":"US",
    "sg:address":"904 Essex Dr",
    "sg:city":"Friendswood",
    "sg:classifiers":[
        {
            "category":"Retail",
            "subcategory":"Portrait Studio",
            "type":"Services"
        }
    ],
    "sg:phone":"+1 281 482 8496",
    "sg:postcode":"77546",
    "sg:province":"TX",
    "sg:tags":[
        "photo"
    ],
    "wof:name":"Michaels Photography",
    "wof:placetype":"venue"
},
  "geometry": {"coordinates":[-95.198913,29.510099],"type":"Point"}
}