{
  "type": "Feature",
  "properties": {
    "iso:country":"US",
    "sg:address":"10100 Clay Rd",
    "sg:city":"Houston",
    "sg:classifiers":[
        {
            "category":"Shopping",
            "type":"Retail Goods"
        }
    ],
    "sg:phone":"+1 713 462 6464",
    "sg:postcode":"77080",
    "sg:province":"TX",
    "sg:tags":[
        "merchandise"
    ],
    "wof:name":"Texas Security Systems",
    "wof:placetype":"venue"
},
  "geometry": {"coordinates":[-95.545536,29.832312],"type":"Point"}
}