{
  "type": "Feature",
  "properties": {
    "iso:country":"US",
    "sg:address":"9030 Seawall Blvd",
    "sg:city":"Galveston",
    "sg:classifiers":[
        {
            "category":"Recreation",
            "subcategory":"Amusement Park",
            "type":"Entertainment"
        }
    ],
    "sg:phone":"+1 409 741 2786",
    "sg:postcode":"77554",
    "sg:province":"TX",
    "sg:tags":[
        "park"
    ],
    "wof:name":"Bungee Fun",
    "wof:placetype":"venue"
},
  "geometry": {"coordinates":[-94.84889699999999,29.253732],"type":"Point"}
}