{
  "type": "Feature",
  "properties": {
    "iso:country":"US",
    "sg:address":"1235 E Pleasant Run Rd",
    "sg:city":"De Soto",
    "sg:classifiers":[
        {
            "category":"Restaurant",
            "type":"Food & Drink"
        }
    ],
    "sg:phone":"+1 972 224 5760",
    "sg:postcode":"75115",
    "sg:province":"TX",
    "sg:tags":[
        "eating"
    ],
    "wof:name":"Taco Bueno 3054",
    "wof:placetype":"venue"
},
  "geometry": {"coordinates":[-96.82342199999999,32.604301],"type":"Point"}
}