{
  "type": "Feature",
  "properties": {
    "iso:country":"US",
    "sg:address":"2121 Red Bluff Rd",
    "sg:city":"Pasadena",
    "sg:classifiers":[
        {
            "category":"Recreation",
            "type":"Entertainment"
        }
    ],
    "sg:phone":"+1 713 473 0333",
    "sg:postcode":"77506",
    "sg:province":"TX",
    "sg:tags":[
        "bingo",
        "game"
    ],
    "wof:name":"Beltway Bingo",
    "wof:placetype":"venue"
},
  "geometry": {"coordinates":[-95.182856,29.700649],"type":"Point"}
}