{
  "type": "Feature",
  "properties": {
    "iso:country":"US",
    "sg:address":"3526 Chatwood Dr",
    "sg:city":"Pearland",
    "sg:classifiers":[
        {
            "category":"Wholesale",
            "subcategory":"Durable Goods & Equipment",
            "type":"Manufacturing & Wholesale Goods"
        }
    ],
    "sg:phone":"+1 281 485 4498",
    "sg:postcode":"77584",
    "sg:province":"TX",
    "wof:name":"Unlimited Supplies",
    "wof:placetype":"venue"
},
  "geometry": {"coordinates":[-95.365712,29.572844],"type":"Point"}
}