{
  "type": "Feature",
  "properties": {
    "iso:country":"US",
    "sg:address":"115 NW Newton Dr",
    "sg:city":"Burleson",
    "sg:classifiers":[
        {
            "category":"Banks & Credit Unions",
            "subcategory":"Bank",
            "type":"Services"
        }
    ],
    "sg:phone":"+1 817 447 3333",
    "sg:postcode":"76028",
    "sg:province":"TX",
    "sg:tags":[
        "loan",
        "real estate"
    ],
    "wof:name":"PNL Burleson",
    "wof:placetype":"venue"
},
  "geometry": {"coordinates":[-97.330586,32.541518],"type":"Point"}
}