{
  "type": "Feature",
  "properties": {
    "iso:country":"US",
    "sg:address":"2102 N Main St",
    "sg:city":"Houston",
    "sg:classifiers":[
        {
            "category":"Autos & Motor Vehicles",
            "subcategory":"Fuel & Gas Station",
            "type":"Retail Goods"
        }
    ],
    "sg:phone":"+1 713 224 4599",
    "sg:postcode":"77009",
    "sg:province":"TX",
    "sg:tags":[
        "station",
        "gasoline"
    ],
    "wof:name":"Chevron",
    "wof:placetype":"venue"
},
  "geometry": {"coordinates":[-95.36293499999999,29.779027],"type":"Point"}
}