{
  "type": "Feature",
  "properties": {
    "iso:country":"US",
    "sg:address":"7015 E 14th St",
    "sg:city":"Brownsville",
    "sg:classifiers":[
        {
            "category":"Personal",
            "subcategory":"Beauty Salon",
            "type":"Services"
        }
    ],
    "sg:phone":"+1 956 831 5777",
    "sg:postcode":"78521",
    "sg:province":"TX",
    "wof:name":"Hair Crafters",
    "wof:placetype":"venue"
},
  "geometry": {"coordinates":[-97.435163,25.939078],"type":"Point"}
}