{
  "type": "Feature",
  "properties": {
    "iso:country":"US",
    "sg:address":"631 S Main St",
    "sg:city":"La Grange",
    "sg:classifiers":[
        {
            "category":"Health Services",
            "subcategory":"Doctor",
            "type":"Services"
        }
    ],
    "sg:phone":"+1 979 968 8035",
    "sg:postcode":"78945",
    "sg:province":"TX",
    "sg:tags":[
        "medical"
    ],
    "wof:name":"Jhaled W Jabboury MD",
    "wof:placetype":"venue"
},
  "geometry": {"coordinates":[-96.875748,29.900139],"type":"Point"}
}