{
  "type": "Feature",
  "properties": {
    "iso:country":"US",
    "sg:address":"1800 Haltom Rd",
    "sg:city":"Fort Worth",
    "sg:classifiers":[
        {
            "category":"Shopping",
            "subcategory":"Florist",
            "type":"Retail Goods"
        }
    ],
    "sg:phone":"+1 817 831 0281",
    "sg:postcode":"76117",
    "sg:province":"TX",
    "wof:name":"Paul's Flower Boutique",
    "wof:placetype":"venue"
},
  "geometry": {"coordinates":[-97.273247,32.784076],"type":"Point"}
}