{
  "type": "Feature",
  "properties": {
    "iso:country":"US",
    "sg:address":"2015 Peters Colony Rd E",
    "sg:city":"Carrollton",
    "sg:classifiers":[
        {
            "category":"Organizations",
            "subcategory":"Religious Organization",
            "type":"Services"
        }
    ],
    "sg:phone":"+1 972 492 1190",
    "sg:postcode":"75007",
    "sg:province":"TX",
    "wof:name":"Woodlake Baptist Church",
    "wof:placetype":"venue"
},
  "geometry": {"coordinates":[-96.87973599999999,33.005721],"type":"Point"}
}