{
  "type": "Feature",
  "properties": {
    "iso:country":"US",
    "sg:address":"4980 Roy Richard Dr",
    "sg:city":"Schertz",
    "sg:classifiers":[
        {
            "category":"Banks & Credit Unions",
            "subcategory":"Bank",
            "type":"Services"
        }
    ],
    "sg:phone":"+1 210 945 1190",
    "sg:postcode":"78154",
    "sg:province":"TX",
    "wof:name":"Randolph-Brooks Federal Credit Union",
    "wof:placetype":"venue"
},
  "geometry": {"coordinates":[-98.276169,29.599108],"type":"Point"}
}