{
  "type": "Feature",
  "properties": {
    "iso:country":"US",
    "sg:address":"502 Meadowcreek Cir",
    "sg:city":"Round Rock",
    "sg:classifiers":[
        {
            "category":"Shopping",
            "subcategory":"Gifts & Souvenirs",
            "type":"Retail Goods"
        }
    ],
    "sg:phone":"+1 512 388 6500",
    "sg:postcode":"78664",
    "sg:province":"TX",
    "sg:tags":[
        "shop"
    ],
    "wof:name":"Aspen House Arts & Gifts",
    "wof:placetype":"venue"
},
  "geometry": {"coordinates":[-97.665626,30.505451],"type":"Point"}
}