{
  "type": "Feature",
  "properties": {
    "iso:country":"US",
    "sg:address":"1247 Mount Gilead Rd",
    "sg:city":"Roanoke",
    "sg:classifiers":[
        {
            "category":"Manufacturing",
            "subcategory":"Retail Goods",
            "type":"Manufacturing & Wholesale Goods"
        }
    ],
    "sg:phone":"+1 817 379 5102",
    "sg:postcode":"76262",
    "sg:province":"TX",
    "sg:tags":[
        "product",
        "mfg"
    ],
    "wof:name":"Puppets With Personality",
    "wof:placetype":"venue"
},
  "geometry": {"coordinates":[-97.22457199999999,32.951973],"type":"Point"}
}