{
  "type": "Feature",
  "properties": {
    "iso:country":"US",
    "sg:address":"16621 Bratton Ln",
    "sg:city":"Austin",
    "sg:classifiers":[
        {
            "category":"Wholesale",
            "subcategory":"Auto Parts",
            "type":"Manufacturing & Wholesale Goods"
        }
    ],
    "sg:phone":"+1 512 218 1735",
    "sg:postcode":"78728",
    "sg:province":"TX",
    "sg:tags":[
        "truck",
        "accessory"
    ],
    "wof:name":"Stone's Truck Covers & Trailer",
    "wof:placetype":"venue"
},
  "geometry": {"coordinates":[-97.67499100000001,30.469478],"type":"Point"}
}