{
  "type": "Feature",
  "properties": {
    "iso:country":"US",
    "sg:address":"3400 Bissonnet St",
    "sg:city":"Houston",
    "sg:classifiers":[
        {
            "category":"Health Services",
            "subcategory":"Doctor",
            "type":"Services"
        }
    ],
    "sg:phone":"+1 713 668 2996",
    "sg:postcode":"77005",
    "sg:province":"TX",
    "sg:tags":[
        "medical"
    ],
    "wof:name":"Joan Rose Gordon Center",
    "wof:placetype":"venue"
},
  "geometry": {"coordinates":[-95.430961,29.725288],"type":"Point"}
}