{
  "type": "Feature",
  "properties": {
    "iso:country":"US",
    "sg:address":"2623 E Hwy 190",
    "sg:city":"Copperas Cove",
    "sg:classifiers":[
        {
            "category":"Retail",
            "subcategory":"Auto Repair",
            "type":"Services"
        }
    ],
    "sg:phone":"+1 254 547 6326",
    "sg:postcode":"76522",
    "sg:province":"TX",
    "sg:tags":[
        "automobile",
        "general"
    ],
    "wof:name":"B Y Mithsibishi",
    "wof:placetype":"venue"
},
  "geometry": {"coordinates":[-97.872027,31.120688],"type":"Point"}
}