{
  "type": "Feature",
  "properties": {
    "iso:country":"US",
    "sg:address":"4226 Ross Ave",
    "sg:city":"Dallas",
    "sg:classifiers":[
        {
            "category":"Retail",
            "subcategory":"Auto Repair",
            "type":"Services"
        }
    ],
    "sg:phone":"+1 214 821 5626",
    "sg:postcode":"75204",
    "sg:province":"TX",
    "sg:tags":[
        "body",
        "towing"
    ],
    "wof:name":"Budget Auto Wrecker Service",
    "wof:placetype":"venue"
},
  "geometry": {"coordinates":[-96.782402,32.8009],"type":"Point"}
}