{
  "type": "Feature",
  "properties": {
    "iso:country":"US",
    "sg:address":"2329 56th St",
    "sg:city":"Lubbock",
    "sg:classifiers":[
        {
            "category":"Building & Trades",
            "subcategory":"Plumbing",
            "type":"Services"
        }
    ],
    "sg:phone":"+1 806 548 3273",
    "sg:postcode":"79412",
    "sg:province":"TX",
    "sg:tags":[
        "conditioning",
        "air",
        "system",
        "contractor"
    ],
    "wof:name":"Elite Air Svc",
    "wof:placetype":"venue"
},
  "geometry": {"coordinates":[-101.86974600000001,33.543248],"type":"Point"}
}