{
  "type": "Feature",
  "properties": {
    "iso:country":"US",
    "sg:address":"2220 Laurel St",
    "sg:city":"Amarillo",
    "sg:classifiers":[
        {
            "category":"Real Estate",
            "subcategory":"Real Estate Agent",
            "type":"Services"
        }
    ],
    "sg:phone":"+1 806 359 5356",
    "sg:postcode":"79109",
    "sg:province":"TX",
    "wof:name":"Goligowski Rentals",
    "wof:placetype":"venue"
},
  "geometry": {"coordinates":[-101.86479799999999,35.185767],"type":"Point"}
}