{
  "type": "Feature",
  "properties": {
    "iso:country":"US",
    "sg:address":"201 Hackberry St",
    "sg:city":"Clute",
    "sg:classifiers":[
        {
            "category":"Real Estate",
            "subcategory":"Real Estate Operator",
            "type":"Services"
        }
    ],
    "sg:phone":"+1 979 265 1496",
    "sg:postcode":"77531",
    "sg:province":"TX",
    "sg:tags":[
        "building",
        "apartment"
    ],
    "wof:name":"Ashton Oaks Apartments",
    "wof:placetype":"venue"
},
  "geometry": {"coordinates":[-95.39490000000001,29.032669],"type":"Point"}
}