{
  "type": "Feature",
  "properties": {
    "iso:country":"US",
    "sg:address":"909 Lee Dr",
    "sg:city":"Bedford",
    "sg:classifiers":[
        {
            "category":"Real Estate",
            "subcategory":"Real Estate Services",
            "type":"Services"
        },
        {
            "category":"Real Estate",
            "subcategory":"Real Estate Agent",
            "type":"Services"
        }
    ],
    "sg:phone":"+1 817 268 2077",
    "sg:postcode":"76022",
    "sg:province":"TX",
    "sg:tags":[
        "management"
    ],
    "wof:name":"Hord Ridge Properties Inc",
    "wof:placetype":"venue"
},
  "geometry": {"coordinates":[-97.156638,32.827905],"type":"Point"}
}