{
  "type": "Feature",
  "properties": {
    "iso:country":"US",
    "sg:address":"2877 W Walnut Hill Ln",
    "sg:city":"Irving",
    "sg:classifiers":[
        {
            "category":"Real Estate",
            "subcategory":"Real Estate Services",
            "type":"Services"
        },
        {
            "category":"Real Estate",
            "subcategory":"Real Estate Operator",
            "type":"Services"
        }
    ],
    "sg:phone":"+1 972 256 1564",
    "sg:postcode":"75038",
    "sg:province":"TX",
    "sg:tags":[
        "vacancy",
        "apartment",
        "rental",
        "finder",
        "listing"
    ],
    "sg:website":"http://www.orchardterrace.com",
    "wof:name":"Oak Tree Apartments",
    "wof:placetype":"venue"
},
  "geometry": {"coordinates":[-96.983028,32.866963],"type":"Point"}
}