{
  "type": "Feature",
  "properties": {
    "iso:country":"US",
    "sg:address":"5100 E Paisano Dr",
    "sg:city":"El Paso",
    "sg:classifiers":[
        {
            "category":"Autos & Motor Vehicles",
            "subcategory":"Automobile Sales",
            "type":"Retail Goods"
        }
    ],
    "sg:phone":"+1 915 779 6323",
    "sg:postcode":"79905",
    "sg:province":"TX",
    "sg:tags":[
        "car",
        "used",
        "dealer"
    ],
    "wof:name":"Rainbow Motors Corp",
    "wof:placetype":"venue"
},
  "geometry": {"coordinates":[-106.430612,31.768277],"type":"Point"}
}