{
  "type": "Feature",
  "properties": {
    "iso:country":"US",
    "sg:address":"7606 Westheimer Rd",
    "sg:city":"Houston",
    "sg:classifiers":[
        {
            "category":"Restaurant",
            "type":"Food & Drink"
        }
    ],
    "sg:phone":"+1 713 785 7606",
    "sg:postcode":"77063",
    "sg:province":"TX",
    "wof:name":"McDonald's Restaurant",
    "wof:placetype":"venue"
},
  "geometry": {"coordinates":[-95.50430299999999,29.737801],"type":"Point"}
}