{
  "type": "Feature",
  "properties": {
    "iso:country":"US",
    "sg:address":"1114 Austin Hwy",
    "sg:city":"San Antonio",
    "sg:classifiers":[
        {
            "category":"Health Services",
            "subcategory":"Doctor",
            "type":"Services"
        }
    ],
    "sg:phone":"+1 210 824 4621",
    "sg:postcode":"78209",
    "sg:province":"TX",
    "sg:tags":[
        "dentist"
    ],
    "wof:name":"Professional Denture Clinic",
    "wof:placetype":"venue"
},
  "geometry": {"coordinates":[-98.448927,29.486479],"type":"Point"}
}