{
  "type": "Feature",
  "properties": {
    "iso:country":"US",
    "sg:address":"1075 Kingwood Dr",
    "sg:city":"Humble",
    "sg:classifiers":[
        {
            "category":"Mining & Drilling",
            "type":"Manufacturing & Wholesale Goods"
        }
    ],
    "sg:phone":"+1 281 359 1266",
    "sg:postcode":"77336",
    "sg:province":"TX",
    "sg:tags":[
        "oil",
        "gas",
        "producer"
    ],
    "wof:name":"Mash Oil Tool",
    "wof:placetype":"venue"
},
  "geometry": {"coordinates":[-95.237382,30.049345],"type":"Point"}
}