{
  "type": "Feature",
  "properties": {
    "iso:country":"US",
    "sg:address":"7004 Cherrybark Cir",
    "sg:city":"Texarkana",
    "sg:classifiers":[
        {
            "category":"Professional",
            "type":"Services"
        }
    ],
    "sg:phone":"+1 870 774 1702",
    "sg:postcode":"71854",
    "sg:province":"TX",
    "sg:tags":[
        "establishment"
    ],
    "wof:name":"Yelverton",
    "wof:placetype":"venue"
},
  "geometry": {"coordinates":[-93.99870799999999,33.489305],"type":"Point"}
}