{
  "type": "Feature",
  "properties": {
    "iso:country":"US",
    "sg:address":"2209 N Parkwood St",
    "sg:city":"Harlingen",
    "sg:classifiers":[
        {
            "category":"Organizations",
            "subcategory":"Community Association",
            "type":"Services"
        }
    ],
    "sg:phone":"+1 956 423 9328",
    "sg:postcode":"78550",
    "sg:province":"TX",
    "wof:name":"Harlinger Area Council",
    "wof:placetype":"venue"
},
  "geometry": {"coordinates":[-97.672488,26.18623],"type":"Point"}
}