{
  "type": "Feature",
  "properties": {
    "iso:country":"US",
    "sg:address":"1016 W Blucher St",
    "sg:city":"Falfurrias",
    "sg:classifiers":[
        {
            "category":"Professional",
            "type":"Services"
        }
    ],
    "sg:phone":"+1 361 396 2332",
    "sg:postcode":"78355",
    "sg:province":"TX",
    "wof:name":"Albert Salinas",
    "wof:placetype":"venue"
},
  "geometry": {"coordinates":[-98.15888099999999,27.225439],"type":"Point"}
}