{
  "type": "Feature",
  "properties": {
    "iso:country":"US",
    "sg:address":"766 Bateswood Dr",
    "sg:city":"Houston",
    "sg:classifiers":[
        {
            "category":"Professional",
            "subcategory":"Business Services",
            "type":"Services"
        }
    ],
    "sg:phone":"+1 281 558 5707",
    "sg:postcode":"77079",
    "sg:province":"TX",
    "wof:name":"Cargo & Product Recovery",
    "wof:placetype":"venue"
},
  "geometry": {"coordinates":[-95.594577,29.770419],"type":"Point"}
}