{
  "type": "Feature",
  "properties": {
    "iso:country":"US",
    "sg:address":"7900 San Felipe Rd",
    "sg:city":"Austin",
    "sg:classifiers":[
        {
            "category":"Real Estate",
            "subcategory":"Real Estate Operator",
            "type":"Services"
        }
    ],
    "sg:phone":"+1 512 331 1533",
    "sg:postcode":"78729",
    "sg:province":"TX",
    "sg:tags":[
        "apartment"
    ],
    "wof:name":"Summit Creek Apartments",
    "wof:placetype":"venue"
},
  "geometry": {"coordinates":[-97.767037,30.438125],"type":"Point"}
}