{
  "type": "Feature",
  "properties": {
    "iso:country":"US",
    "sg:address":"4637 Bonnell Ave",
    "sg:city":"Fort Worth",
    "sg:classifiers":[
        {
            "category":"Professional",
            "subcategory":"Lawyer & Legal Services",
            "type":"Services"
        }
    ],
    "sg:phone":"+1 817 989 7281",
    "sg:postcode":"76107",
    "sg:province":"TX",
    "sg:tags":[
        "attorney"
    ],
    "wof:name":"Patrick S Dohoney Law Office",
    "wof:placetype":"venue"
},
  "geometry": {"coordinates":[-97.389262,32.723407],"type":"Point"}
}