{
  "type": "Feature",
  "properties": {
    "iso:country":"US",
    "sg:address":"1410 S Southwest Loop 323",
    "sg:city":"Tyler",
    "sg:classifiers":[
        {
            "category":"Restaurant",
            "type":"Food & Drink"
        }
    ],
    "sg:menulink":"http://www.allmenus.com/tx/tyler/14757-rudys-bbq/menu/",
    "sg:phone":"+1 903 597 8391",
    "sg:postcode":"75701",
    "sg:province":"TX",
    "sg:tags":[
        "american"
    ],
    "wof:name":"Rudy's BBQ",
    "wof:placetype":"venue"
},
  "geometry": {"coordinates":[-95.34039,32.334659],"type":"Point"}
}