{
  "type": "Feature",
  "properties": {
    "iso:country":"US",
    "sg:address":"7918 Kirby Dr",
    "sg:city":"Houston",
    "sg:classifiers":[
        {
            "category":"Restaurant",
            "type":"Food & Drink"
        }
    ],
    "sg:phone":"+1 713 665 7500",
    "sg:postcode":"77027",
    "sg:province":"TX",
    "sg:tags":[
        "mediterranean"
    ],
    "wof:name":"Mo's Knockout Grill & Mediterranean Food",
    "wof:placetype":"venue"
},
  "geometry": {"coordinates":[-95.413657,29.693298],"type":"Point"}
}