{
  "type": "Feature",
  "properties": {
    "iso:country":"US",
    "sg:address":"6506 Wesley St",
    "sg:city":"Greenville",
    "sg:classifiers":[
        {
            "category":"Restaurant",
            "type":"Food & Drink"
        }
    ],
    "sg:menulink":"http://www.allmenus.com/tx/greenville/37856-cicis-pizza-buffet/menu/",
    "sg:phone":"+1 903 454 2166",
    "sg:postcode":"75402",
    "sg:province":"TX",
    "sg:tags":[
        "american",
        "pizza"
    ],
    "wof:name":"CiCi's Pizza Buffet",
    "wof:placetype":"venue"
},
  "geometry": {"coordinates":[-96.109724,33.10345],"type":"Point"}
}