{
  "type": "Feature",
  "properties": {
    "iso:country":"US",
    "sg:address":"5217 82nd St",
    "sg:city":"Lubbock",
    "sg:classifiers":[
        {
            "category":"Shopping",
            "subcategory":"Crafts & Fabrics",
            "type":"Retail Goods"
        }
    ],
    "sg:phone":"+1 806 798 8414",
    "sg:postcode":"79424",
    "sg:province":"TX",
    "sg:tags":[
        "shop",
        "sewing"
    ],
    "wof:name":"Jo-Ann Fabrics & Crafts",
    "wof:placetype":"venue"
},
  "geometry": {"coordinates":[-101.92458499999999,33.519611],"type":"Point"}
}