{
  "type": "Feature",
  "properties": {
    "iso:country":"US",
    "sg:address":"5209 E Parker Rd",
    "sg:city":"Allen",
    "sg:classifiers":[
        {
            "category":"Retail",
            "subcategory":"Auto Repair",
            "type":"Services"
        }
    ],
    "sg:phone":"+1 972 509 9746",
    "sg:postcode":"75002",
    "sg:province":"TX",
    "sg:tags":[
        "repairing",
        "automobile"
    ],
    "wof:name":"Country Automotive",
    "wof:placetype":"venue"
},
  "geometry": {"coordinates":[-96.62202499999999,33.055421],"type":"Point"}
}