{
  "type": "Feature",
  "properties": {
    "iso:country":"US",
    "sg:address":"6219 Masters Rd",
    "sg:city":"Manvel",
    "sg:classifiers":[
        {
            "category":"Retail",
            "subcategory":"Animal Services",
            "type":"Services"
        }
    ],
    "sg:phone":"+1 281 489 1967",
    "sg:postcode":"77578",
    "sg:province":"TX",
    "sg:tags":[
        "pet",
        "boarding",
        "sitting"
    ],
    "wof:name":"A G's Happy Dog Inn",
    "wof:placetype":"venue"
},
  "geometry": {"coordinates":[-95.350661,29.487484],"type":"Point"}
}