{
  "type": "Feature",
  "properties": {
    "iso:country":"US",
    "sg:address":"1801 N Lamar Boulevard",
    "sg:city":"Austin",
    "sg:classifiers":[
        {
            "category":"Real Estate",
            "subcategory":"Architect",
            "type":"Services"
        }
    ],
    "sg:phone":"+1 512 583 0300",
    "sg:postcode":"78701",
    "sg:province":"TX",
    "wof:name":"Moore-Anderson Architects",
    "wof:placetype":"venue"
},
  "geometry": {"coordinates":[-97.751284,30.282876],"type":"Point"}
}