{
  "type": "Feature",
  "properties": {
    "iso:country":"US",
    "sg:address":"9705 Shirland Ln",
    "sg:city":"Frisco",
    "sg:classifiers":[
        {
            "category":"Professional",
            "subcategory":"Business Services",
            "type":"Services"
        }
    ],
    "sg:phone":"+1 972 335 0161",
    "sg:postcode":"75035",
    "sg:province":"TX",
    "sg:tags":[
        "interior",
        "consultant",
        "design",
        "decorator"
    ],
    "wof:name":"Old Town Interiors",
    "wof:placetype":"venue"
},
  "geometry": {"coordinates":[-96.79805500000001,33.11041],"type":"Point"}
}