{
  "type": "Feature",
  "properties": {
    "iso:country":"US",
    "sg:address":"246 Flaming Oak Dr",
    "sg:city":"Bastrop",
    "sg:classifiers":[
        {
            "category":"Professional",
            "type":"Services"
        }
    ],
    "sg:phone":"+1 512 303 2972",
    "sg:postcode":"78602",
    "sg:province":"TX",
    "wof:name":"Patrick King",
    "wof:placetype":"venue"
},
  "geometry": {"coordinates":[-97.279831,30.223194],"type":"Point"}
}