{
  "type": "Feature",
  "properties": {
    "iso:country":"US",
    "sg:address":"2710 W Ashby Pl",
    "sg:city":"San Antonio",
    "sg:classifiers":[
        {
            "category":"Real Estate",
            "subcategory":"Real Estate Operator",
            "type":"Services"
        }
    ],
    "sg:phone":"+1 210 733 8210",
    "sg:postcode":"78201",
    "sg:province":"TX",
    "sg:tags":[
        "building",
        "apartment"
    ],
    "wof:name":"Salvation Army",
    "wof:placetype":"venue"
},
  "geometry": {"coordinates":[-98.53837799999999,29.451819],"type":"Point"}
}