{
  "type": "Feature",
  "properties": {
    "iso:country":"US",
    "sg:address":"25350 Budde Rd",
    "sg:city":"Spring",
    "sg:classifiers":[
        {
            "category":"Manufacturing",
            "subcategory":"Printing",
            "type":"Manufacturing & Wholesale Goods"
        }
    ],
    "sg:phone":"+1 281 364 9540",
    "sg:postcode":"77380",
    "sg:province":"TX",
    "sg:tags":[
        "publisher",
        "guide"
    ],
    "wof:name":"Antiquing Texas",
    "wof:placetype":"venue"
},
  "geometry": {"coordinates":[-95.449504,30.129486],"type":"Point"}
}