{
  "type": "Feature",
  "properties": {
    "iso:country":"US",
    "sg:address":"6437 Spicewood Springs Rd",
    "sg:city":"Austin",
    "sg:classifiers":[
        {
            "category":"Building & Trades",
            "subcategory":"Electrical",
            "type":"Services"
        }
    ],
    "sg:phone":"+1 512 349 9473",
    "sg:postcode":"78759",
    "sg:province":"TX",
    "sg:tags":[
        "electric",
        "industrial",
        "contractors-commercial",
        "contractor"
    ],
    "wof:name":"Dondlinger Electric",
    "wof:placetype":"venue"
},
  "geometry": {"coordinates":[-97.777963,30.392841],"type":"Point"}
}