{
  "type": "Feature",
  "properties": {
    "iso:country":"US",
    "sg:address":"1703 Centerville Rd",
    "sg:city":"Dallas",
    "sg:classifiers":[
        {
            "category":"Wholesale",
            "subcategory":"Durable Goods & Equipment",
            "type":"Manufacturing & Wholesale Goods"
        }
    ],
    "sg:phone":"+1 214 563 8622",
    "sg:postcode":"75228",
    "sg:province":"TX",
    "wof:name":"Df Wholesalers",
    "wof:placetype":"venue"
},
  "geometry": {"coordinates":[-96.68107999999999,32.843055],"type":"Point"}
}