{
  "type": "Feature",
  "properties": {
    "iso:country":"US",
    "sg:address":"7502 Shaddock Dr",
    "sg:city":"Houston",
    "sg:classifiers":[
        {
            "category":"Retail",
            "subcategory":"Animal Services",
            "type":"Services"
        }
    ],
    "sg:phone":"+1 713 937 7089",
    "sg:postcode":"77041",
    "sg:province":"TX",
    "wof:name":"Longhorn Kennels & Guide",
    "wof:placetype":"venue"
},
  "geometry": {"coordinates":[-95.613223,29.890477],"type":"Point"}
}