{
  "type": "Feature",
  "properties": {
    "iso:country":"US",
    "sg:address":"8610 Irvington Blvd",
    "sg:city":"Houston",
    "sg:classifiers":[
        {
            "category":"Recreation",
            "type":"Entertainment"
        }
    ],
    "sg:phone":"+1 713 457 2455",
    "sg:postcode":"77022",
    "sg:province":"TX",
    "wof:name":"Deportes Nuno",
    "wof:placetype":"venue"
},
  "geometry": {"coordinates":[-95.361485,29.838655],"type":"Point"}
}