{
  "type": "Feature",
  "properties": {
    "iso:country":"US",
    "sg:address":"5760 S Central Expy",
    "sg:city":"Mckinney",
    "sg:classifiers":[
        {
            "category":"Home & Garden",
            "subcategory":"Furniture",
            "type":"Retail Goods"
        }
    ],
    "sg:phone":"+1 972 369 1130",
    "sg:postcode":"75069",
    "sg:province":"TX",
    "sg:tags":[
        "store"
    ],
    "wof:name":"Texas Star Furniture",
    "wof:placetype":"venue"
},
  "geometry": {"coordinates":[-96.65200900000001,33.139141],"type":"Point"}
}