{
  "type": "Feature",
  "properties": {
    "iso:country":"US",
    "sg:address":"105 Kathryn Dr",
    "sg:city":"Lewisville",
    "sg:classifiers":[
        {
            "category":"Health Services",
            "subcategory":"Doctor",
            "type":"Services"
        }
    ],
    "sg:phone":"+1 972 221 7722",
    "sg:postcode":"75067",
    "sg:province":"TX",
    "sg:tags":[
        "physician",
        "surgeon"
    ],
    "wof:name":"Lisa Y Pierce MD Psychiatrist",
    "wof:placetype":"venue"
},
  "geometry": {"coordinates":[-97.032095,33.042056],"type":"Point"}
}