{
  "type": "Feature",
  "properties": {
    "iso:country":"US",
    "sg:address":"1511 Heritage Blvd",
    "sg:city":"Red Oak",
    "sg:classifiers":[
        {
            "category":"Communications",
            "subcategory":"Film & Video Production",
            "type":"Services"
        }
    ],
    "sg:phone":"+1 972 230 0227",
    "sg:postcode":"75154",
    "sg:province":"TX",
    "wof:name":"Grassroots Filmworks",
    "wof:placetype":"venue"
},
  "geometry": {"coordinates":[-96.86329000000001,32.563468],"type":"Point"}
}