{
  "type": "Feature",
  "properties": {
    "iso:country":"US",
    "sg:address":"6200 Savoy Ste 226",
    "sg:city":"Houston",
    "sg:classifiers":[
        {
            "category":"Banks & Credit Unions",
            "subcategory":"Financial Services",
            "type":"Services"
        }
    ],
    "sg:phone":"+1 713 590 9070",
    "sg:postcode":"77036",
    "sg:province":"TX",
    "sg:tags":[
        "broker",
        "mortgage"
    ],
    "sg:website":"www.lending2all.com/",
    "wof:name":"Network Funding",
    "wof:placetype":"venue"
},
  "geometry": {"coordinates":[-95.505191,29.715367],"type":"Point"}
}