{
  "type": "Feature",
  "properties": {
    "iso:country":"US",
    "sg:address":"313 Lancashire Dr",
    "sg:city":"Flower Mound",
    "sg:classifiers":[
        {
            "category":"Building & Trades",
            "subcategory":"Construction",
            "type":"Services"
        }
    ],
    "sg:phone":"+1 972 874 8064",
    "sg:postcode":"75028",
    "sg:province":"TX",
    "sg:tags":[
        "contractor"
    ],
    "wof:name":"Cochran Services",
    "wof:placetype":"venue"
},
  "geometry": {"coordinates":[-97.03304799999999,33.0107],"type":"Point"}
}