{
  "type": "Feature",
  "properties": {
    "iso:country":"US",
    "sg:address":"195 Southbelt Industrial Dr",
    "sg:city":"Houston",
    "sg:classifiers":[
        {
            "category":"Professional",
            "subcategory":"Research",
            "type":"Services"
        },
        {
            "category":"Professional",
            "subcategory":"Management & Consulting",
            "type":"Services"
        }
    ],
    "sg:phone":"+1 713 784 9393",
    "sg:postcode":"77047",
    "sg:province":"TX",
    "sg:tags":[
        "environmental",
        "ecological"
    ],
    "wof:name":"Edc Environmental Services",
    "wof:placetype":"venue"
},
  "geometry": {"coordinates":[-95.417428,29.585716],"type":"Point"}
}