{
  "type": "Feature",
  "properties": {
    "iso:country":"US",
    "sg:address":"9103 Herts Rd",
    "sg:city":"Spring",
    "sg:classifiers":[
        {
            "category":"Shopping",
            "type":"Retail Goods"
        }
    ],
    "sg:phone":"+1 281 320 8642",
    "sg:postcode":"77379",
    "sg:province":"TX",
    "sg:tags":[
        "merchandise"
    ],
    "wof:name":"Partysport",
    "wof:placetype":"venue"
},
  "geometry": {"coordinates":[-95.543935,30.001956],"type":"Point"}
}