{
  "type": "Feature",
  "properties": {
    "iso:country":"US",
    "sg:address":"2022 Hudspeth Ave",
    "sg:city":"Dallas",
    "sg:classifiers":[
        {
            "category":"Organizations",
            "subcategory":"Religious Organization",
            "type":"Services"
        }
    ],
    "sg:phone":"+1 214 376 3628",
    "sg:postcode":"75216",
    "sg:province":"TX",
    "sg:tags":[
        "church"
    ],
    "wof:name":"Greater Memorial Baptst Church",
    "wof:placetype":"venue"
},
  "geometry": {"coordinates":[-96.79522,32.703881],"type":"Point"}
}