{
  "type": "Feature",
  "properties": {
    "iso:country":"US",
    "sg:address":"2425 S Robertson Ave",
    "sg:city":"Tyler",
    "sg:classifiers":[
        {
            "category":"Wholesale",
            "subcategory":"Machinery & Supplies",
            "type":"Manufacturing & Wholesale Goods"
        }
    ],
    "sg:phone":"+1 903 597 1205",
    "sg:postcode":"75701",
    "sg:province":"TX",
    "sg:tags":[
        "equipment",
        "material",
        "handling"
    ],
    "wof:name":"Flexion Material Handling Inc",
    "wof:placetype":"venue"
},
  "geometry": {"coordinates":[-95.310281,32.32317],"type":"Point"}
}