{
  "type": "Feature",
  "properties": {
    "iso:country":"US",
    "sg:address":"413 E Pine St",
    "sg:city":"Jacksonville",
    "sg:classifiers":[
        {
            "category":"Personal",
            "subcategory":"Beauty Salon",
            "type":"Services"
        }
    ],
    "sg:phone":"+1 903 541 0955",
    "sg:postcode":"75766",
    "sg:province":"TX",
    "sg:tags":[
        "shop"
    ],
    "wof:name":"Kut -N- Dry",
    "wof:placetype":"venue"
},
  "geometry": {"coordinates":[-95.27126,31.967664],"type":"Point"}
}