{
  "type": "Feature",
  "properties": {
    "iso:country":"US",
    "sg:address":"200 Clement Ct",
    "sg:city":"Pottsboro",
    "sg:classifiers":[
        {
            "category":"Real Estate",
            "subcategory":"Real Estate Operator",
            "type":"Services"
        }
    ],
    "sg:phone":"+1 903 786 9040",
    "sg:postcode":"75076",
    "sg:province":"TX",
    "sg:tags":[
        "apartment"
    ],
    "wof:name":"Lakewood Terrace Apartments",
    "wof:placetype":"venue"
},
  "geometry": {"coordinates":[-96.673469,33.764275],"type":"Point"}
}