{
  "type": "Feature",
  "properties": {
    "iso:country":"US",
    "sg:address":"154 E Sunnyside St",
    "sg:city":"Houston",
    "sg:classifiers":[
        {
            "category":"Building & Trades",
            "subcategory":"Cleaning & Sanitation",
            "type":"Services"
        }
    ],
    "sg:phone":"+1 713 694 8406",
    "sg:postcode":"77076",
    "sg:province":"TX",
    "sg:tags":[
        "maintenance"
    ],
    "wof:name":"Best Building Janitorial",
    "wof:placetype":"venue"
},
  "geometry": {"coordinates":[-95.377921,29.856854],"type":"Point"}
}