{
  "type": "Feature",
  "properties": {
    "iso:country":"US",
    "sg:address":"9684 Baker Rd",
    "sg:city":"Weatherford",
    "sg:classifiers":[
        {
            "category":"Professional",
            "subcategory":"Management & Consulting",
            "type":"Services"
        }
    ],
    "sg:phone":"+1 817 596 0685",
    "sg:postcode":"76087",
    "sg:province":"TX",
    "wof:name":"Hmh Construction MGT LLC",
    "wof:placetype":"venue"
},
  "geometry": {"coordinates":[-97.724794,32.623207],"type":"Point"}
}