{
  "type": "Feature",
  "properties": {
    "iso:country":"US",
    "sg:address":"222 W Broadway Ave",
    "sg:city":"Tulia",
    "sg:classifiers":[
        {
            "category":"Restaurant",
            "type":"Food & Drink"
        }
    ],
    "sg:phone":"+1 806 995 3368",
    "sg:postcode":"79088",
    "sg:province":"TX",
    "wof:name":"El Sarape",
    "wof:placetype":"venue"
},
  "geometry": {"coordinates":[-101.766121,34.53717],"type":"Point"}
}