{
  "type": "Feature",
  "properties": {
    "iso:country":"US",
    "sg:address":"2044 Cedar Grove Cove",
    "sg:city":"Round Rock",
    "sg:classifiers":[
        {
            "category":"Professional",
            "subcategory":"Business Services",
            "type":"Services"
        }
    ],
    "sg:phone":"+1 512 310 1076",
    "sg:postcode":"78681",
    "sg:province":"TX",
    "wof:name":"R Stephens Family Partnership",
    "wof:placetype":"venue"
},
  "geometry": {"coordinates":[-97.713579,30.531067],"type":"Point"}
}