{
  "type": "Feature",
  "properties": {
    "iso:country":"US",
    "sg:address":"405 Sunset Blvd",
    "sg:city":"Breckenridge",
    "sg:classifiers":[
        {
            "category":"Place Of Worship",
            "subcategory":"Church",
            "type":"Public Place"
        },
        {
            "category":"Place Of Worship",
            "type":"Public Place"
        }
    ],
    "sg:phone":"+1 254 559 6500",
    "sg:postcode":"76424",
    "sg:province":"TX",
    "sg:tags":[
        "churches-interdenominational",
        "churches-various",
        "denomination"
    ],
    "wof:name":"Covenant Tabernacle",
    "wof:placetype":"venue"
},
  "geometry": {"coordinates":[-98.92778,32.75198],"type":"Point"}
}