{
  "type": "Feature",
  "properties": {
    "iso:country":"US",
    "sg:address":"316 S Goliad St",
    "sg:city":"Rockwall",
    "sg:classifiers":[
        {
            "category":"Professional",
            "subcategory":"Employment Agencies",
            "type":"Services"
        }
    ],
    "sg:phone":"+1 972 771 5100",
    "sg:postcode":"75087",
    "sg:province":"TX",
    "sg:tags":[
        "help",
        "supply"
    ],
    "wof:name":"Manpower",
    "wof:placetype":"venue"
},
  "geometry": {"coordinates":[-96.460418,32.927732],"type":"Point"}
}