{
  "type": "Feature",
  "properties": {
    "iso:country":"US",
    "sg:address":"975 Fm 1959 Rd",
    "sg:city":"Houston",
    "sg:classifiers":[
        {
            "category":"Food & Beverages",
            "subcategory":"Groceries & Convenience Stores",
            "type":"Retail Goods"
        }
    ],
    "sg:phone":"+1 281 484 3654",
    "sg:postcode":"77034",
    "sg:province":"TX",
    "wof:name":"New Ellington Food Store",
    "wof:placetype":"venue"
},
  "geometry": {"coordinates":[-95.1819,29.5886],"type":"Point"}
}