{
  "type": "Feature",
  "properties": {
    "iso:country":"US",
    "sg:address":"3000 E Rosedale St",
    "sg:city":"Fort Worth",
    "sg:classifiers":[
        {
            "category":"Recreation",
            "type":"Entertainment"
        }
    ],
    "sg:phone":"+1 817 534 6877",
    "sg:postcode":"76105",
    "sg:province":"TX",
    "wof:name":"Double Duece Lounge",
    "wof:placetype":"venue"
},
  "geometry": {"coordinates":[-97.28106699999999,32.730742],"type":"Point"}
}