{
  "type": "Feature",
  "properties": {
    "iso:country":"US",
    "sg:address":"1798 Lake Breeze Dr",
    "sg:city":"Rockwall",
    "sg:classifiers":[
        {
            "category":"Sports & Exercise",
            "subcategory":"Swimming Pool",
            "type":"Entertainment"
        }
    ],
    "sg:phone":"+1 214 205 4611",
    "sg:postcode":"75087",
    "sg:province":"TX",
    "sg:tags":[
        "repair"
    ],
    "wof:name":"Aqua. Tech Pool Service",
    "wof:placetype":"venue"
},
  "geometry": {"coordinates":[-96.47986899999999,32.939027],"type":"Point"}
}