{
  "type": "Feature",
  "properties": {
    "iso:country":"US",
    "sg:address":"2909 Gregg Ln",
    "sg:city":"Manor",
    "sg:classifiers":[
        {
            "category":"Farming",
            "subcategory":"Livestock Farm",
            "type":"Manufacturing & Wholesale Goods"
        }
    ],
    "sg:phone":"+1 512 990 9788",
    "sg:postcode":"78653",
    "sg:province":"TX",
    "sg:tags":[
        "ranch"
    ],
    "wof:name":"Freedom Trail Ranch",
    "wof:placetype":"venue"
},
  "geometry": {"coordinates":[-97.62853800000001,30.394225],"type":"Point"}
}