{
  "type": "Feature",
  "properties": {
    "iso:country":"US",
    "sg:address":"1740 W 27th St",
    "sg:city":"Houston",
    "sg:classifiers":[
        {
            "category":"Health Services",
            "subcategory":"Optometrist",
            "type":"Services"
        }
    ],
    "sg:phone":"+1 713 864 8652",
    "sg:postcode":"77008",
    "sg:province":"TX",
    "sg:website":"www.northwesteye.com",
    "wof:name":"Sanchez Amador Jr OD",
    "wof:placetype":"venue"
},
  "geometry": {"coordinates":[-95.429782,29.8103],"type":"Point"}
}