{
  "type": "Feature",
  "properties": {
    "iso:country":"US",
    "sg:address":"9438 Valley Rock Dr",
    "sg:city":"San Antonio",
    "sg:classifiers":[
        {
            "category":"Building & Trades",
            "subcategory":"Construction",
            "type":"Services"
        }
    ],
    "sg:phone":"+1 210 522 9476",
    "sg:postcode":"78250",
    "sg:province":"TX",
    "sg:tags":[
        "contractor"
    ],
    "wof:name":"Felans Tile & More",
    "wof:placetype":"venue"
},
  "geometry": {"coordinates":[-98.68801000000001,29.5005],"type":"Point"}
}