{
  "type": "Feature",
  "properties": {
    "iso:country":"US",
    "sg:address":"303 US Hwy 59",
    "sg:city":"Atlanta",
    "sg:classifiers":[
        {
            "category":"Restaurant",
            "type":"Food & Drink"
        }
    ],
    "sg:phone":"+1 903 796 9825",
    "sg:postcode":"75551",
    "sg:province":"TX",
    "wof:name":"Pitt Grill",
    "wof:placetype":"venue"
},
  "geometry": {"coordinates":[-94.18207200000001,33.116205],"type":"Point"}
}