{
  "type": "Feature",
  "properties": {
    "iso:country":"US",
    "sg:address":"25510 I- 45",
    "sg:city":"Spring",
    "sg:classifiers":[
        {
            "category":"Restaurant",
            "type":"Food & Drink"
        }
    ],
    "sg:phone":"+1 281 292 5640",
    "sg:postcode":"77386",
    "sg:province":"TX",
    "sg:tags":[
        "seafood"
    ],
    "wof:name":"Long John Silver's",
    "wof:placetype":"venue"
},
  "geometry": {"coordinates":[-95.443387,30.130525],"type":"Point"}
}