{
  "type": "Feature",
  "properties": {
    "iso:country":"US",
    "sg:address":"440 Tayman Dr",
    "sg:city":"Midlothian",
    "sg:classifiers":[
        {
            "category":"Utilities",
            "subcategory":"Water",
            "type":"Services"
        }
    ],
    "sg:phone":"+1 972 775 6663",
    "sg:postcode":"76065",
    "sg:province":"TX",
    "sg:tags":[
        "company",
        "sewage"
    ],
    "wof:name":"Midlothian Water Treatment",
    "wof:placetype":"venue"
},
  "geometry": {"coordinates":[-96.99074899999999,32.532032],"type":"Point"}
}