{
  "type": "Feature",
  "properties": {
    "iso:country":"US",
    "sg:address":"300 Dexter St",
    "sg:city":"Hillsboro",
    "sg:classifiers":[
        {
            "category":"Food & Beverages",
            "subcategory":"Groceries & Convenience Stores",
            "type":"Retail Goods"
        }
    ],
    "sg:phone":"+1 254 582 1299",
    "sg:postcode":"76645",
    "sg:province":"TX",
    "sg:tags":[
        "grocer"
    ],
    "wof:name":"Country Market",
    "wof:placetype":"venue"
},
  "geometry": {"coordinates":[-97.132868,32.000541],"type":"Point"}
}