{
  "type": "Feature",
  "properties": {
    "iso:country":"US",
    "sg:address":"7202 Rolling Meadow Dr",
    "sg:city":"Richmond",
    "sg:classifiers":[
        {
            "category":"Professional",
            "type":"Services"
        }
    ],
    "sg:phone":"+1 281 344 8372",
    "sg:postcode":"77469",
    "sg:province":"TX",
    "wof:name":"M&M Media Services Inc",
    "wof:placetype":"venue"
},
  "geometry": {"coordinates":[-95.71174600000001,29.524143],"type":"Point"}
}