{
  "type": "Feature",
  "properties": {
    "iso:country":"US",
    "sg:address":"1715 Spurlock Rd",
    "sg:city":"Nederland",
    "sg:classifiers":[
        {
            "category":"Professional",
            "subcategory":"Research",
            "type":"Services"
        }
    ],
    "sg:phone":"+1 409 722 7828",
    "sg:postcode":"77627",
    "sg:province":"TX",
    "sg:tags":[
        "environmental",
        "ecological"
    ],
    "wof:name":"Assured Environmental Quality",
    "wof:placetype":"venue"
},
  "geometry": {"coordinates":[-94.012795,29.983878],"type":"Point"}
}