{
  "type": "Feature",
  "properties": {
    "iso:country":"US",
    "sg:address":"312 4th St",
    "sg:city":"Graham",
    "sg:classifiers":[
        {
            "category":"Mining & Drilling",
            "type":"Manufacturing & Wholesale Goods"
        }
    ],
    "sg:phone":"+1 940 549 0661",
    "sg:postcode":"76450",
    "sg:province":"TX",
    "sg:tags":[
        "field"
    ],
    "wof:name":"Rogers Construction",
    "wof:placetype":"venue"
},
  "geometry": {"coordinates":[-98.594466,33.106989],"type":"Point"}
}