{
  "type": "Feature",
  "properties": {
    "iso:country":"US",
    "sg:address":"301 Salinas Ave",
    "sg:city":"Laredo",
    "sg:classifiers":[
        {
            "category":"Manufacturing",
            "subcategory":"Tools & Machinery",
            "type":"Manufacturing & Wholesale Goods"
        }
    ],
    "sg:phone":"+1 956 723 8181",
    "sg:postcode":"78040",
    "sg:province":"TX",
    "sg:tags":[
        "watchmaker"
    ],
    "wof:name":"Luxury International",
    "wof:placetype":"venue"
},
  "geometry": {"coordinates":[-99.508495,27.50358],"type":"Point"}
}