{
  "type": "Feature",
  "properties": {
    "iso:country":"US",
    "sg:address":"150 W Ann Arbor Ave",
    "sg:city":"Dallas",
    "sg:classifiers":[
        {
            "category":"Travel",
            "subcategory":"Hotels & Motels",
            "type":"Entertainment"
        }
    ],
    "sg:phone":"+1 214 372 3053",
    "sg:postcode":"75224",
    "sg:province":"TX",
    "sg:tags":[
        "operation"
    ],
    "wof:name":"Sunbelt Motel",
    "wof:placetype":"venue"
},
  "geometry": {"coordinates":[-96.8246,32.691399],"type":"Point"}
}