{
  "type": "Feature",
  "properties": {
    "iso:country":"US",
    "sg:address":"812 E Hubbard St",
    "sg:city":"Lindale",
    "sg:classifiers":[
        {
            "category":"Manufacturing",
            "subcategory":"Tools & Machinery",
            "type":"Manufacturing & Wholesale Goods"
        }
    ],
    "sg:phone":"+1 903 882 5464",
    "sg:postcode":"75771",
    "sg:province":"TX",
    "sg:tags":[
        "machine",
        "shop"
    ],
    "sg:website":"www.kingmanufacturing.com",
    "wof:name":"King Manufacturing",
    "wof:placetype":"venue"
},
  "geometry": {"coordinates":[-95.40128199999999,32.516407],"type":"Point"}
}