{
  "type": "Feature",
  "properties": {
    "iso:country":"US",
    "sg:address":"1525 Woodcrest Dr",
    "sg:city":"Mesquite",
    "sg:classifiers":[
        {
            "category":"Retail",
            "subcategory":"Repair Shop",
            "type":"Services"
        }
    ],
    "sg:phone":"+1 972 285 8414",
    "sg:postcode":"75149",
    "sg:province":"TX",
    "wof:name":"Baggett Appliance",
    "wof:placetype":"venue"
},
  "geometry": {"coordinates":[-96.62121999999999,32.743529],"type":"Point"}
}