{
  "type": "Feature",
  "properties": {
    "iso:country":"US",
    "sg:address":"5502 Ceran Dr",
    "sg:city":"Arlington",
    "sg:classifiers":[
        {
            "category":"Shopping",
            "type":"Retail Goods"
        }
    ],
    "sg:phone":"+1 817 457 5355",
    "sg:postcode":"76016",
    "sg:province":"TX",
    "sg:tags":[
        "merchandise"
    ],
    "wof:name":"Linda P Henley",
    "wof:placetype":"venue"
},
  "geometry": {"coordinates":[-97.18865599999999,32.688111],"type":"Point"}
}