{
  "type": "Feature",
  "properties": {
    "iso:country":"US",
    "sg:address":"15055 Inwood Rd",
    "sg:city":"Addison",
    "sg:classifiers":[
        {
            "category":"Food & Beverages",
            "subcategory":"Liquor & Beverages",
            "type":"Retail Goods"
        }
    ],
    "sg:phone":"+1 972 239 5891",
    "sg:postcode":"75001",
    "sg:province":"TX",
    "sg:tags":[
        "beer",
        "spirit",
        "wine"
    ],
    "sg:website":"www.centennialwines.com",
    "wof:name":"Centennial Fine Wine and Spirits",
    "wof:placetype":"venue"
},
  "geometry": {"coordinates":[-96.830943,32.953677],"type":"Point"}
}