{
  "type": "Feature",
  "properties": {
    "iso:country":"US",
    "sg:address":"101 W Spring Creek Pkwy",
    "sg:city":"Plano",
    "sg:classifiers":[
        {
            "category":"Home & Garden",
            "subcategory":"Building Materials",
            "type":"Retail Goods"
        }
    ],
    "sg:phone":"+1 972 527 0001",
    "sg:postcode":"75023",
    "sg:province":"TX",
    "sg:tags":[
        "paint"
    ],
    "wof:name":"Kelley-Moore Paint Co",
    "wof:placetype":"venue"
},
  "geometry": {"coordinates":[-96.69441399999999,33.057417],"type":"Point"}
}