{
  "type": "Feature",
  "properties": {
    "iso:country":"US",
    "sg:address":"34 Crestwood Cir",
    "sg:city":"Sugar Land",
    "sg:classifiers":[
        {
            "category":"Professional",
            "subcategory":"Management & Consulting",
            "type":"Services"
        }
    ],
    "sg:phone":"+1 281 494 9097",
    "sg:postcode":"77478",
    "sg:province":"TX",
    "sg:tags":[
        "fuel"
    ],
    "wof:name":"D & J Ellis Management",
    "wof:placetype":"venue"
},
  "geometry": {"coordinates":[-95.602627,29.608247],"type":"Point"}
}