{
  "type": "Feature",
  "properties": {
    "iso:country":"US",
    "sg:address":"7807 Main St",
    "sg:city":"Houston",
    "sg:classifiers":[
        {
            "category":"Shopping",
            "subcategory":"Clothing, Apparel, & Fashions",
            "type":"Retail Goods"
        }
    ],
    "sg:phone":"+1 713 791 1888",
    "sg:postcode":"77030",
    "sg:province":"TX",
    "sg:tags":[
        "tuxedo"
    ],
    "sg:website":"www.alsformal.com",
    "wof:name":"Al's Formal Wear Houston LTD",
    "wof:placetype":"venue"
},
  "geometry": {"coordinates":[-95.414068,29.69476],"type":"Point"}
}