{
  "type": "Feature",
  "properties": {
    "iso:country":"US",
    "sg:address":"132 Commerce St",
    "sg:city":"Clute",
    "sg:classifiers":[
        {
            "category":"Shopping",
            "subcategory":"Gifts & Souvenirs",
            "type":"Retail Goods"
        }
    ],
    "sg:phone":"+1 979 265 2720",
    "sg:postcode":"77531",
    "sg:province":"TX",
    "sg:tags":[
        "party",
        "supply"
    ],
    "sg:website":"www.arcsupply.com",
    "wof:name":"ARC Supply",
    "wof:placetype":"venue"
},
  "geometry": {"coordinates":[-95.404719,29.01462],"type":"Point"}
}