{
  "type": "Feature",
  "properties": {
    "iso:country":"US",
    "sg:address":"841 Lakeview Dr",
    "sg:city":"Sugar Land",
    "sg:classifiers":[
        {
            "category":"Shopping",
            "subcategory":"Clothing, Apparel, & Fashions",
            "type":"Retail Goods"
        }
    ],
    "sg:phone":"+1 281 242 8772",
    "sg:postcode":"77478",
    "sg:province":"TX",
    "wof:name":"Mom & ME Accessories",
    "wof:placetype":"venue"
},
  "geometry": {"coordinates":[-95.61947499999999,29.627276],"type":"Point"}
}