{
  "type": "Feature",
  "properties": {
    "iso:country":"US",
    "sg:address":"25900 US Highway 281 N",
    "sg:city":"Bulverde",
    "sg:classifiers":[
        {
            "category":"Arts & Performance",
            "subcategory":"Comedy Club",
            "type":"Entertainment"
        }
    ],
    "sg:phone":"+1 830 980 5173",
    "sg:postcode":"78163",
    "sg:province":"TX",
    "wof:name":"Off Road Innovations",
    "wof:placetype":"venue"
},
  "geometry": {"coordinates":[-98.41978400000001,29.795365],"type":"Point"}
}