{
  "type": "Feature",
  "properties": {
    "iso:country":"US",
    "sg:address":"428 W Main St",
    "sg:city":"Nacogdoches",
    "sg:classifiers":[
        {
            "category":"Food & Beverages",
            "subcategory":"Groceries & Convenience Stores",
            "type":"Retail Goods"
        }
    ],
    "sg:phone":"+1 936 560 1333",
    "sg:postcode":"75961",
    "sg:province":"TX",
    "wof:name":"Depot Chevron",
    "wof:placetype":"venue"
},
  "geometry": {"coordinates":[-94.65877999999999,31.604982],"type":"Point"}
}