{
  "type": "Feature",
  "properties": {
    "iso:country":"US",
    "sg:address":"1752 Redd Rd",
    "sg:city":"Howe",
    "sg:classifiers":[
        {
            "category":"Building & Trades",
            "subcategory":"Construction",
            "type":"Services"
        }
    ],
    "sg:phone":"+1 903 546 6985",
    "sg:postcode":"75459",
    "sg:province":"TX",
    "wof:name":"Pratt Construction",
    "wof:placetype":"venue"
},
  "geometry": {"coordinates":[-96.54095599999999,33.490789],"type":"Point"}
}