{
  "type": "Feature",
  "properties": {
    "iso:country":"US",
    "sg:address":"201 Ball Dr",
    "sg:city":"Kerrville",
    "sg:classifiers":[
        {
            "category":"Farming",
            "subcategory":"Livestock Farm",
            "type":"Manufacturing & Wholesale Goods"
        }
    ],
    "sg:phone":"+1 830 895 7742",
    "sg:postcode":"78028",
    "sg:province":"TX",
    "sg:tags":[
        "ranch"
    ],
    "wof:name":"C 4 Ranch",
    "wof:placetype":"venue"
},
  "geometry": {"coordinates":[-99.16642299999999,30.029062],"type":"Point"}
}