{
  "type": "Feature",
  "properties": {
    "iso:country":"US",
    "sg:address":"114 Pinecrest",
    "sg:city":"White Oak",
    "sg:classifiers":[
        {
            "category":"Building & Trades",
            "subcategory":"Plumbing",
            "type":"Services"
        }
    ],
    "sg:phone":"+1 903 759 8228",
    "sg:postcode":"75693",
    "sg:province":"TX",
    "sg:tags":[
        "plumbing",
        "contractor"
    ],
    "wof:name":"Bill's Plumbing",
    "wof:placetype":"venue"
},
  "geometry": {"coordinates":[-94.866373,32.546898],"type":"Point"}
}