{
  "type": "Feature",
  "properties": {
    "iso:country":"US",
    "sg:address":"14311 FM 2326",
    "sg:city":"Electra",
    "sg:classifiers":[
        {
            "category":"Farming",
            "subcategory":"Farm",
            "type":"Manufacturing & Wholesale Goods"
        }
    ],
    "sg:phone":"+1 505 392 7645",
    "sg:postcode":"76360",
    "sg:province":"TX",
    "sg:tags":[
        "crop",
        "general"
    ],
    "wof:name":"Cedar Hill Farm Inc",
    "wof:placetype":"venue"
},
  "geometry": {"coordinates":[-98.90490200000001,33.906391],"type":"Point"}
}