{
  "type": "Feature",
  "properties": {
    "iso:country":"US",
    "sg:address":"6799 Granbury Rd",
    "sg:city":"Fort Worth",
    "sg:classifiers":[
        {
            "category":"Real Estate",
            "subcategory":"Real Estate Agent",
            "type":"Services"
        }
    ],
    "sg:phone":"+1 817 926 8537",
    "sg:postcode":"76133",
    "sg:province":"TX",
    "sg:website":"www.dalworthprop.com",
    "wof:name":"Dalworth Properties Inc",
    "wof:placetype":"venue"
},
  "geometry": {"coordinates":[-97.409683,32.649371],"type":"Point"}
}