{
  "type": "Feature",
  "properties": {
    "iso:country":"US",
    "sg:address":"3636 Executive Center Dr Ste G18",
    "sg:city":"Austin",
    "sg:classifiers":[
        {
            "category":"Communications",
            "type":"Services"
        }
    ],
    "sg:phone":"+1 512 346 9988",
    "sg:postcode":"78731",
    "sg:province":"TX",
    "sg:tags":[
        "pathologist",
        "speech-language"
    ],
    "wof:name":"Stuttering and Language Treatment Services",
    "wof:placetype":"venue"
},
  "geometry": {"coordinates":[-97.74820200000001,30.360893],"type":"Point"}
}