{
  "type": "Feature",
  "properties": {
    "iso:country":"US",
    "sg:address":"2929 Briarpark Dr",
    "sg:city":"Houston",
    "sg:classifiers":[
        {
            "category":"Professional",
            "subcategory":"Business Services",
            "type":"Services"
        }
    ],
    "sg:phone":"+1 832 242 5459",
    "sg:postcode":"77042",
    "sg:province":"TX",
    "wof:name":"Fei Enterprises",
    "wof:placetype":"venue"
},
  "geometry": {"coordinates":[-95.54899,29.733633],"type":"Point"}
}