{
  "type": "Feature",
  "properties": {
    "iso:country":"US",
    "sg:address":"3311 Elm St",
    "sg:city":"Dallas",
    "sg:classifiers":[
        {
            "category":"Professional",
            "type":"Services"
        }
    ],
    "sg:phone":"+1 214 747 1254",
    "sg:postcode":"75226",
    "sg:province":"TX",
    "wof:name":"Exclusive Concierge",
    "wof:placetype":"venue"
},
  "geometry": {"coordinates":[-96.777963,32.785884],"type":"Point"}
}