{
  "type": "Feature",
  "properties": {
    "iso:country":"US",
    "sg:address":"6607 Fernshaw Dr",
    "sg:city":"Dallas",
    "sg:classifiers":[
        {
            "category":"Recreation",
            "type":"Entertainment"
        }
    ],
    "sg:phone":"+1 972 267 4757",
    "sg:postcode":"75248",
    "sg:province":"TX",
    "wof:name":"Holden Tennis Inc",
    "wof:placetype":"venue"
},
  "geometry": {"coordinates":[-96.79171599999999,32.986632],"type":"Point"}
}