{
  "type": "Feature",
  "properties": {
    "iso:country":"US",
    "sg:address":"201 E Johnson St",
    "sg:city":"Denison",
    "sg:classifiers":[
        {
            "category":"Building & Trades",
            "subcategory":"Construction",
            "type":"Services"
        }
    ],
    "sg:phone":"+1 903 815 8910",
    "sg:postcode":"75021",
    "sg:province":"TX",
    "sg:tags":[
        "demolition",
        "contractor"
    ],
    "wof:name":"Red Barron",
    "wof:placetype":"venue"
},
  "geometry": {"coordinates":[-96.532044,33.762619],"type":"Point"}
}