{
  "type": "Feature",
  "properties": {
    "iso:country":"US",
    "sg:address":"2804 S Main St",
    "sg:city":"Pearland",
    "sg:classifiers":[
        {
            "category":"Restaurant",
            "type":"Food & Drink"
        }
    ],
    "sg:phone":"+1 281 997 6233",
    "sg:postcode":"77581",
    "sg:province":"TX",
    "sg:tags":[
        "eating"
    ],
    "wof:name":"Ixtapa House Tex Mex",
    "wof:placetype":"venue"
},
  "geometry": {"coordinates":[-95.28455099999999,29.557635],"type":"Point"}
}