{
  "type": "Feature",
  "properties": {
    "iso:country":"US",
    "sg:address":"808 Travis St",
    "sg:city":"Houston",
    "sg:classifiers":[
        {
            "category":"Banks & Credit Unions",
            "subcategory":"Financial Services",
            "type":"Services"
        },
        {
            "category":"Mining & Drilling",
            "type":"Manufacturing & Wholesale Goods"
        }
    ],
    "sg:phone":"+1 713 229 9899",
    "sg:postcode":"77002",
    "sg:province":"TX",
    "sg:tags":[
        "producer",
        "property",
        "gas",
        "investment",
        "oil"
    ],
    "wof:name":"Kerrco Inc",
    "wof:placetype":"venue"
},
  "geometry": {"coordinates":[-95.365234,29.75833],"type":"Point"}
}