{
  "type": "Feature",
  "properties": {
    "iso:country":"US",
    "sg:address":"6341 Prospect Ave",
    "sg:city":"Dallas",
    "sg:classifiers":[
        {
            "category":"Professional",
            "subcategory":"Management & Consulting",
            "type":"Services"
        }
    ],
    "sg:phone":"+1 214 841 4703",
    "sg:postcode":"75214",
    "sg:province":"TX",
    "sg:tags":[
        "break",
        "coffee",
        "supply"
    ],
    "wof:name":"Specialty Coffees Of Dallas",
    "wof:placetype":"venue"
},
  "geometry": {"coordinates":[-96.753117,32.815097],"type":"Point"}
}