{
  "type": "Feature",
  "properties": {
    "iso:country":"US",
    "sg:address":"11716 Ferguson Rd",
    "sg:city":"Dallas",
    "sg:classifiers":[
        {
            "category":"Restaurant",
            "type":"Food & Drink"
        }
    ],
    "sg:phone":"+1 972 682 0522",
    "sg:postcode":"75228",
    "sg:province":"TX",
    "wof:name":"Seafood and Hotwings",
    "wof:placetype":"venue"
},
  "geometry": {"coordinates":[-96.64949799999999,32.855],"type":"Point"}
}