{
  "type": "Feature",
  "properties": {
    "iso:country":"US",
    "sg:address":"800 Waite Dr",
    "sg:city":"Lewisville",
    "sg:classifiers":[
        {
            "category":"Building & Trades",
            "subcategory":"Electrical",
            "type":"Services"
        }
    ],
    "sg:phone":"+1 972 241 2452",
    "sg:postcode":"75077",
    "sg:province":"TX",
    "sg:tags":[
        "electrical",
        "contractor"
    ],
    "wof:name":"Texas Star Alarms Inc",
    "wof:placetype":"venue"
},
  "geometry": {"coordinates":[-97.08772500000001,33.084327],"type":"Point"}
}