{
  "type": "Feature",
  "properties": {
    "iso:country":"US",
    "sg:address":"2 E Main St",
    "sg:city":"Bellville",
    "sg:classifiers":[
        {
            "category":"Banks & Credit Unions",
            "subcategory":"Bank",
            "type":"Services"
        },
        {
            "category":"Banks & Credit Unions",
            "subcategory":"Financial Services",
            "type":"Services"
        }
    ],
    "sg:phone":"+1 979 865 3153",
    "sg:postcode":"77418",
    "sg:province":"TX",
    "sg:tags":[
        "commercial",
        "loan",
        "saving"
    ],
    "sg:website":"http://www.wellsfargo.com",
    "wof:name":"Wells Fargo Bank, National Association",
    "wof:placetype":"venue"
},
  "geometry": {"coordinates":[-96.257668,29.95048],"type":"Point"}
}