{
  "type": "Feature",
  "properties": {
    "iso:country":"US",
    "sg:address":"4406 Arbor Brook Ct",
    "sg:city":"Pasadena",
    "sg:classifiers":[
        {
            "category":"Professional",
            "subcategory":"Lawyer & Legal Services",
            "type":"Services"
        }
    ],
    "sg:phone":"+1 281 487 1529",
    "sg:postcode":"77505",
    "sg:province":"TX",
    "wof:name":"Lw Spiller Inc",
    "wof:placetype":"venue"
},
  "geometry": {"coordinates":[-95.136895,29.643419],"type":"Point"}
}