{
  "type": "Feature",
  "properties": {
    "iso:country":"US",
    "sg:address":"13812 N Highway 183 Ste. B-1",
    "sg:city":"Austin",
    "sg:classifiers":[
        {
            "category":"Restaurant",
            "type":"Food & Drink"
        }
    ],
    "sg:phone":"+1 512 257 1200",
    "sg:postcode":"78750",
    "sg:province":"TX",
    "sg:tags":[
        "pizza"
    ],
    "wof:name":"Saccone's",
    "wof:placetype":"venue"
},
  "geometry": {"coordinates":[-97.796143,30.465001],"type":"Point"}
}