{
  "type": "Feature",
  "properties": {
    "iso:country":"US",
    "sg:address":"1011 Downridge Dr",
    "sg:city":"Leander",
    "sg:classifiers":[
        {
            "category":"Manufacturing",
            "subcategory":"Buildings",
            "type":"Manufacturing & Wholesale Goods"
        },
        {
            "category":"Home & Garden",
            "subcategory":"Home Furnishings",
            "type":"Retail Goods"
        },
        {
            "category":"Building & Trades",
            "subcategory":"Construction",
            "type":"Services"
        }
    ],
    "sg:phone":"+1 512 539 0979",
    "sg:postcode":"78641",
    "sg:province":"TX",
    "sg:tags":[
        "sunroom",
        "altering",
        "solarium",
        "contractor",
        "remodeling",
        "builder"
    ],
    "sg:website":"http://austin.citysearch.com/profile/external/604412112/leander_tx/4_c_home_rebuilders.html?publisher=yellowpages&reference_id=1&placement=ypwebsitemip",
    "wof:name":"4-C Home Rebuilders",
    "wof:placetype":"venue"
},
  "geometry": {"coordinates":[-97.82993500000001,30.558917],"type":"Point"}
}