{
  "type": "Feature",
  "properties": {
    "iso:country":"US",
    "sg:address":"1501 Scottsdale Dr",
    "sg:city":"Plano",
    "sg:classifiers":[
        {
            "category":"Professional",
            "subcategory":"Computer Services",
            "type":"Services"
        }
    ],
    "sg:phone":"+1 972 612 6276",
    "sg:postcode":"75023",
    "sg:province":"TX",
    "sg:tags":[
        "related"
    ],
    "wof:name":"Venatec Corporation",
    "wof:placetype":"venue"
},
  "geometry": {"coordinates":[-96.725568,33.041589],"type":"Point"}
}