{
  "type": "Feature",
  "properties": {
    "iso:country":"US",
    "sg:address":"903 N Loop 336 W",
    "sg:city":"Conroe",
    "sg:classifiers":[
        {
            "category":"Restaurant",
            "type":"Food & Drink"
        }
    ],
    "sg:menulink":"http://www.allmenus.com/tx/southeast-montgomery/60477-dominos-pizza/menu/",
    "sg:phone":"+1 936 539 2288",
    "sg:postcode":"77301",
    "sg:province":"TX",
    "sg:tags":[
        "american",
        "wing",
        "pizza"
    ],
    "wof:name":"Domino's Pizza",
    "wof:placetype":"venue"
},
  "geometry": {"coordinates":[-95.471464,30.335126],"type":"Point"}
}