{
  "type": "Feature",
  "properties": {
    "iso:country":"US",
    "sg:address":"1901 Heritage Ln",
    "sg:city":"Conroe",
    "sg:classifiers":[
        {
            "category":"Wholesale",
            "subcategory":"Farm Supplies",
            "type":"Manufacturing & Wholesale Goods"
        }
    ],
    "sg:phone":"+1 936 588 4168",
    "sg:postcode":"77304",
    "sg:province":"TX",
    "wof:name":"Novartis",
    "wof:placetype":"venue"
},
  "geometry": {"coordinates":[-95.56948199999999,30.35254],"type":"Point"}
}