{
  "type": "Feature",
  "properties": {
    "iso:country":"US",
    "sg:address":"1602 S FM 116",
    "sg:city":"Copperas Cove",
    "sg:classifiers":[
        {
            "category":"Organizations",
            "subcategory":"Religious Organization",
            "type":"Services"
        }
    ],
    "sg:phone":"+1 254 547 0331",
    "sg:postcode":"76522",
    "sg:province":"TX",
    "sg:tags":[
        "church"
    ],
    "sg:website":"www.stmartins-episcopal.org",
    "wof:name":"Saint Martins Episcopal Church",
    "wof:placetype":"venue"
},
  "geometry": {"coordinates":[-97.90745099999999,31.105541],"type":"Point"}
}