{
  "type": "Feature",
  "properties": {
    "iso:country":"US",
    "sg:address":"8687 N Central Expy",
    "sg:city":"Dallas",
    "sg:classifiers":[
        {
            "category":"Cinema",
            "subcategory":"Movie Theater",
            "type":"Entertainment"
        }
    ],
    "sg:phone":"+1 214 360 4262",
    "sg:postcode":"75225",
    "sg:province":"TX",
    "sg:website":"www.moviewatcher.com/theatres/th...",
    "wof:name":"AMC Northpark 15",
    "wof:placetype":"venue"
},
  "geometry": {"coordinates":[-96.770723,32.868641],"type":"Point"}
}