{
  "type": "Feature",
  "properties": {
    "iso:country":"US",
    "sg:address":"205 Lum Ln",
    "sg:city":"Denison",
    "sg:classifiers":[
        {
            "category":"Professional",
            "type":"Services"
        }
    ],
    "sg:phone":"+1 903 465 2313",
    "sg:postcode":"75020",
    "sg:province":"TX",
    "sg:tags":[
        "establishment"
    ],
    "wof:name":"River Of Life Fellowship",
    "wof:placetype":"venue"
},
  "geometry": {"coordinates":[-96.570994,33.755556],"type":"Point"}
}