{
  "type": "Feature",
  "properties": {
    "iso:country":"US",
    "sg:address":"681 Summit Ridge",
    "sg:city":"Lewisville",
    "sg:classifiers":[
        {
            "category":"Retail",
            "subcategory":"Car Wash",
            "type":"Services"
        }
    ],
    "sg:phone":"+1 972 436 5239",
    "sg:postcode":"75077",
    "sg:province":"TX",
    "sg:tags":[
        "carwash"
    ],
    "wof:name":"Carwash I Southridge",
    "wof:placetype":"venue"
},
  "geometry": {"coordinates":[-97.020263,33.049904],"type":"Point"}
}