{
  "type": "Feature",
  "properties": {
    "iso:country":"US",
    "sg:address":"118 Pawnee Trl",
    "sg:city":"Gainesville",
    "sg:classifiers":[
        {
            "category":"Professional",
            "subcategory":"Business Services",
            "type":"Services"
        }
    ],
    "sg:phone":"+1 940 665 8717",
    "sg:postcode":"76240",
    "sg:province":"TX",
    "wof:name":"Biggerstaff Ventures",
    "wof:placetype":"venue"
},
  "geometry": {"coordinates":[-97.018092,33.589043],"type":"Point"}
}