{
  "type": "Feature",
  "properties": {
    "iso:country":"US",
    "sg:address":"4913 Colleyville Blvd",
    "sg:city":"Colleyville",
    "sg:phone":"+1 817 788 4553",
    "sg:postcode":"76034",
    "sg:province":"TX",
    "wof:name":"Red Barn Bar-B-Que",
    "wof:placetype":"venue"
},
  "geometry": {"coordinates":[-97.15570700000001,32.880868],"type":"Point"}
}