{
  "type": "Feature",
  "properties": {
    "iso:country":"US",
    "sg:address":"1226 Brenham Dr",
    "sg:city":"Allen",
    "sg:classifiers":[
        {
            "category":"Wholesale",
            "subcategory":"Machinery & Supplies",
            "type":"Manufacturing & Wholesale Goods"
        }
    ],
    "sg:phone":"+1 972 727 0755",
    "sg:postcode":"75013",
    "sg:province":"TX",
    "wof:name":"Scott Renshaw Co",
    "wof:placetype":"venue"
},
  "geometry": {"coordinates":[-96.697097,33.110161],"type":"Point"}
}