{
  "type": "Feature",
  "properties": {
    "iso:country":"US",
    "sg:address":"7431 FM 346 E",
    "sg:city":"Whitehouse",
    "sg:classifiers":[
        {
            "category":"Shopping",
            "subcategory":"Florist",
            "type":"Retail Goods"
        }
    ],
    "sg:phone":"+1 903 839 3490",
    "sg:postcode":"75791",
    "sg:province":"TX",
    "wof:name":"Always Unique LLC",
    "wof:placetype":"venue"
},
  "geometry": {"coordinates":[-95.260608,32.220364],"type":"Point"}
}