{
  "type": "Feature",
  "properties": {
    "iso:country":"US",
    "sg:address":"9330 Lyndon B Johnson Fwy",
    "sg:city":"Dallas",
    "sg:classifiers":[
        {
            "category":"Insurance",
            "subcategory":"Insurance Agent",
            "type":"Services"
        }
    ],
    "sg:phone":"+1 972 234 1451",
    "sg:postcode":"75243",
    "sg:province":"TX",
    "wof:name":"Farmers Insurance",
    "wof:placetype":"venue"
},
  "geometry": {"coordinates":[-96.73576,32.910847],"type":"Point"}
}