{
  "type": "Feature",
  "properties": {
    "iso:country":"US",
    "sg:address":"13321 Lime Creek Rd",
    "sg:city":"Cedar Park",
    "sg:classifiers":[
        {
            "category":"Manufacturing",
            "subcategory":"Glass & Minerals",
            "type":"Manufacturing & Wholesale Goods"
        }
    ],
    "sg:phone":"+1 512 258 1601",
    "sg:postcode":"78641",
    "sg:province":"TX",
    "sg:tags":[
        "stone",
        "cut",
        "product"
    ],
    "wof:name":"M E Ruby Jr Inc",
    "wof:placetype":"venue"
},
  "geometry": {"coordinates":[-97.856936,30.508017],"type":"Point"}
}