{
  "type": "Feature",
  "properties": {
    "iso:country":"US",
    "sg:address":"7171 Harwin Dr",
    "sg:city":"Houston",
    "sg:classifiers":[
        {
            "category":"Real Estate",
            "subcategory":"Real Estate Agent",
            "type":"Services"
        }
    ],
    "sg:phone":"+1 713 783 9359",
    "sg:postcode":"77036",
    "sg:province":"TX",
    "wof:name":"Insco Realty Group",
    "wof:placetype":"venue"
},
  "geometry": {"coordinates":[-95.50825399999999,29.718039],"type":"Point"}
}