{
  "type": "Feature",
  "properties": {
    "iso:country":"US",
    "sg:address":"6202 FM 50",
    "sg:city":"Brenham",
    "sg:classifiers":[
        {
            "category":"Professional",
            "type":"Services"
        }
    ],
    "sg:phone":"+1 979 836 5151",
    "sg:postcode":"77833",
    "sg:province":"TX",
    "wof:name":"P C P Brazos Valley",
    "wof:placetype":"venue"
},
  "geometry": {"coordinates":[-96.36295,30.252027],"type":"Point"}
}