{
  "type": "Feature",
  "properties": {
    "iso:country":"US",
    "sg:address":"10402 Airline Dr",
    "sg:city":"Houston",
    "sg:classifiers":[
        {
            "category":"Retail",
            "subcategory":"Auto Repair",
            "type":"Services"
        }
    ],
    "sg:phone":"+1 281 847 5357",
    "sg:postcode":"77037",
    "sg:province":"TX",
    "sg:tags":[
        "body"
    ],
    "wof:name":"Elias Collision",
    "wof:placetype":"venue"
},
  "geometry": {"coordinates":[-95.401672,29.906074],"type":"Point"}
}