{
  "type": "Feature",
  "properties": {
    "iso:country":"US",
    "sg:address":"11411 Willow Field Dr",
    "sg:city":"Cypress",
    "sg:classifiers":[
        {
            "category":"Building & Trades",
            "subcategory":"Construction",
            "type":"Services"
        }
    ],
    "sg:phone":"+1 713 201 9087",
    "sg:postcode":"77429",
    "sg:province":"TX",
    "sg:tags":[
        "general",
        "contractor"
    ],
    "wof:name":"New Kingdom Builders Inc",
    "wof:placetype":"venue"
},
  "geometry": {"coordinates":[-95.59295400000001,29.954521],"type":"Point"}
}