{
  "type": "Feature",
  "properties": {
    "iso:country":"US",
    "sg:address":"18547 Old Hwy 105 W",
    "sg:city":"Montgomery",
    "sg:classifiers":[
        {
            "category":"Food & Beverages",
            "subcategory":"Groceries & Convenience Stores",
            "type":"Retail Goods"
        }
    ],
    "sg:phone":"+1 936 582 6786",
    "sg:postcode":"77356",
    "sg:province":"TX",
    "wof:name":"Valero Energy Corporation",
    "wof:placetype":"venue"
},
  "geometry": {"coordinates":[-95.79328599999999,30.345535],"type":"Point"}
}