{
  "type": "Feature",
  "properties": {
    "iso:country":"US",
    "sg:address":"1912 Texas Ave S",
    "sg:city":"College Station",
    "sg:classifiers":[
        {
            "category":"Restaurant",
            "type":"Food & Drink"
        }
    ],
    "sg:phone":"+1 979 764 4044",
    "sg:postcode":"77840",
    "sg:province":"TX",
    "sg:tags":[
        "eating"
    ],
    "wof:name":"El Chico Restaurant",
    "wof:placetype":"venue"
},
  "geometry": {"coordinates":[-96.31618400000001,30.612839],"type":"Point"}
}