{
  "type": "Feature",
  "properties": {
    "iso:country":"US",
    "sg:address":"10720 Preston Rd",
    "sg:city":"Dallas",
    "sg:classifiers":[
        {
            "category":"Retail",
            "subcategory":"Photofinishing",
            "type":"Services"
        }
    ],
    "sg:phone":"+1 214 369 2580",
    "sg:postcode":"75230",
    "sg:province":"TX",
    "sg:tags":[
        "photo",
        "finishing"
    ],
    "wof:name":"Ritz Camera Ctr",
    "wof:placetype":"venue"
},
  "geometry": {"coordinates":[-96.80391400000001,32.892753],"type":"Point"}
}