{
  "type": "Feature",
  "properties": {
    "iso:country":"US",
    "sg:address":"12169 FM 1180",
    "sg:city":"Electra",
    "sg:classifiers":[
        {
            "category":"Mining & Drilling",
            "type":"Manufacturing & Wholesale Goods"
        }
    ],
    "sg:phone":"+1 940 438 2915",
    "sg:postcode":"76360",
    "sg:province":"TX",
    "sg:tags":[
        "operator",
        "oil"
    ],
    "wof:name":"Stephens & Johnson Operating",
    "wof:placetype":"venue"
},
  "geometry": {"coordinates":[-98.878058,33.840495],"type":"Point"}
}