{
  "type": "Feature",
  "properties": {
    "iso:country":"US",
    "sg:address":"641 Old US Hwy 90 W",
    "sg:city":"San Antonio",
    "sg:classifiers":[
        {
            "category":"Autos & Motor Vehicles",
            "subcategory":"Automobile Sales",
            "type":"Retail Goods"
        }
    ],
    "sg:phone":"+1 210 438 9090",
    "sg:postcode":"78237",
    "sg:province":"TX",
    "sg:tags":[
        "car",
        "dealer"
    ],
    "wof:name":"R A Wholesale Motors",
    "wof:placetype":"venue"
},
  "geometry": {"coordinates":[-98.573314,29.426491],"type":"Point"}
}