{
  "type": "Feature",
  "properties": {
    "iso:country":"US",
    "sg:address":"4317 Rosser Sq",
    "sg:city":"Dallas",
    "sg:classifiers":[
        {
            "category":"Education",
            "subcategory":"Dance Studio",
            "type":"Public Place"
        }
    ],
    "sg:phone":"+1 972 247 8380",
    "sg:postcode":"75244",
    "sg:province":"TX",
    "wof:name":"Dick Chaplin Cotillion",
    "wof:placetype":"venue"
},
  "geometry": {"coordinates":[-96.84562099999999,32.92157],"type":"Point"}
}