{
  "type": "Feature",
  "properties": {
    "iso:country":"US",
    "sg:address":"6816 Camp Bowie Blvd",
    "sg:city":"Fort Worth",
    "sg:classifiers":[
        {
            "category":"Real Estate",
            "subcategory":"Real Estate Agent",
            "type":"Services"
        }
    ],
    "sg:phone":"+1 817 732 2700",
    "sg:postcode":"76116",
    "sg:province":"TX",
    "wof:name":"Leggett Properties",
    "wof:placetype":"venue"
},
  "geometry": {"coordinates":[-97.432315,32.721704],"type":"Point"}
}