{
  "type": "Feature",
  "properties": {
    "iso:country":"US",
    "sg:address":"2902 W Irving Blvd",
    "sg:city":"Irving",
    "sg:classifiers":[
        {
            "category":"Home & Garden",
            "subcategory":"Home Furnishings",
            "type":"Retail Goods"
        }
    ],
    "sg:phone":"+1 972 313 3507",
    "sg:postcode":"75061",
    "sg:province":"TX",
    "wof:name":"J D Sales",
    "wof:placetype":"venue"
},
  "geometry": {"coordinates":[-96.986602,32.832188],"type":"Point"}
}