{
  "type": "Feature",
  "properties": {
    "iso:country":"US",
    "sg:address":"6852 Skillman St",
    "sg:city":"Dallas",
    "sg:classifiers":[
        {
            "category":"Personal",
            "subcategory":"Beauty Salon",
            "type":"Services"
        }
    ],
    "sg:phone":"+1 214 341 9377",
    "sg:postcode":"75231",
    "sg:province":"TX",
    "wof:name":"B's Hair Cuts",
    "wof:placetype":"venue"
},
  "geometry": {"coordinates":[-96.739169,32.867685],"type":"Point"}
}