{
  "type": "Feature",
  "properties": {
    "iso:country":"US",
    "sg:address":"6556 Peerless St Ste B",
    "sg:city":"Houston",
    "sg:classifiers":[
        {
            "category":"Bars & Pubs",
            "subcategory":"Sports Bar",
            "type":"Food & Drink"
        }
    ],
    "sg:phone":"+1 713 747 0512",
    "sg:postcode":"77021",
    "sg:province":"TX",
    "wof:name":"Tk Sports Bar",
    "wof:placetype":"venue"
},
  "geometry": {"coordinates":[-95.370499,29.702101],"type":"Point"}
}