{
  "type": "Feature",
  "properties": {
    "iso:country":"US",
    "sg:address":"2309 Rio Grande St",
    "sg:city":"Austin",
    "sg:classifiers":[
        {
            "category":"Professional",
            "subcategory":"Business Services",
            "type":"Services"
        }
    ],
    "sg:phone":"+1 512 542 0050",
    "sg:postcode":"78705",
    "sg:province":"TX",
    "sg:tags":[
        "organizing",
        "services-household"
    ],
    "wof:name":"Blys Enterprises",
    "wof:placetype":"venue"
},
  "geometry": {"coordinates":[-97.74472,30.28722],"type":"Point"}
}