{
  "type": "Feature",
  "properties": {
    "iso:country":"US",
    "sg:address":"917 Markowsky Ave",
    "sg:city":"Harlingen",
    "sg:classifiers":[
        {
            "category":"Organizations",
            "subcategory":"Religious Organization",
            "type":"Services"
        }
    ],
    "sg:phone":"+1 956 421 2054",
    "sg:postcode":"78550",
    "sg:province":"TX",
    "wof:name":"Valley Peoples Church & Center",
    "wof:placetype":"venue"
},
  "geometry": {"coordinates":[-97.706481,26.210445],"type":"Point"}
}