{
  "type": "Feature",
  "properties": {
    "iso:country":"US",
    "sg:address":"2031 Texas Ave S",
    "sg:city":"Bryan",
    "sg:classifiers":[
        {
            "category":"Food & Beverages",
            "subcategory":"Groceries & Convenience Stores",
            "type":"Retail Goods"
        }
    ],
    "sg:phone":"+1 979 775 3088",
    "sg:postcode":"77802",
    "sg:province":"TX",
    "wof:name":"H-E-B Pantry Foods 2",
    "wof:placetype":"venue"
},
  "geometry": {"coordinates":[-96.36076799999999,30.650264],"type":"Point"}
}