{
  "type": "Feature",
  "properties": {
    "iso:country":"US",
    "sg:address":"4 Riverway",
    "sg:city":"Houston",
    "sg:classifiers":[
        {
            "category":"Shopping",
            "subcategory":"Gifts & Souvenirs",
            "type":"Retail Goods"
        }
    ],
    "sg:phone":"+1 713 621 1350",
    "sg:postcode":"77056",
    "sg:province":"TX",
    "wof:name":"W H Smith Gift Shoppe",
    "wof:placetype":"venue"
},
  "geometry": {"coordinates":[-95.462169,29.761489],"type":"Point"}
}