{
  "type": "Feature",
  "properties": {
    "iso:country":"US",
    "sg:address":"3420 W Walnut St",
    "sg:city":"Allen",
    "sg:classifiers":[
        {
            "category":"Autos & Motor Vehicles",
            "subcategory":"Fuel & Gas Station",
            "type":"Retail Goods"
        }
    ],
    "sg:phone":"+1 972 487 0708",
    "sg:postcode":"75042",
    "sg:province":"TX",
    "sg:tags":[
        "convenience",
        "station",
        "store"
    ],
    "wof:name":"Citgo",
    "wof:placetype":"venue"
},
  "geometry": {"coordinates":[-96.680223,32.916647],"type":"Point"}
}