{
  "type": "Feature",
  "properties": {
    "iso:country":"US",
    "sg:address":"1307 Wells Branch Pkwy",
    "sg:city":"Pflugerville",
    "sg:classifiers":[
        {
            "category":"Building & Trades",
            "subcategory":"Pest Control",
            "type":"Services"
        }
    ],
    "sg:phone":"+1 512 251 0035",
    "sg:postcode":"78660",
    "sg:province":"TX",
    "sg:website":"www.orkin.com",
    "wof:name":"Orkin Exterminating Co",
    "wof:placetype":"venue"
},
  "geometry": {"coordinates":[-97.664879,30.441057],"type":"Point"}
}