{
  "type": "Feature",
  "properties": {
    "iso:country":"US",
    "sg:address":"3103 Colonial Ave",
    "sg:city":"Dallas",
    "sg:classifiers":[
        {
            "category":"Retail",
            "subcategory":"Repair Shop",
            "type":"Services"
        }
    ],
    "sg:phone":"+1 214 428 9299",
    "sg:postcode":"75215",
    "sg:province":"TX",
    "wof:name":"Locksmith Locks & Locksmith",
    "wof:placetype":"venue"
},
  "geometry": {"coordinates":[-96.7752,32.760602],"type":"Point"}
}