{
  "type": "Feature",
  "properties": {
    "iso:country":"US",
    "sg:address":"204 W Bedford Euless Rd",
    "sg:city":"Hurst",
    "sg:classifiers":[
        {
            "category":"Building & Trades",
            "subcategory":"Cleaning & Sanitation",
            "type":"Services"
        }
    ],
    "sg:phone":"+1 817 282 3934",
    "sg:postcode":"76053",
    "sg:province":"TX",
    "sg:tags":[
        "janitor"
    ],
    "wof:name":"North Texas Cleaning Systems",
    "wof:placetype":"venue"
},
  "geometry": {"coordinates":[-97.17065100000001,32.834022],"type":"Point"}
}