{
  "type": "Feature",
  "properties": {
    "iso:country":"US",
    "sg:address":"301 Lamont Ave",
    "sg:city":"San Antonio",
    "sg:classifiers":[
        {
            "category":"Professional",
            "subcategory":"Art Services",
            "type":"Services"
        }
    ],
    "sg:phone":"+1 210 824 8791",
    "sg:postcode":"78209",
    "sg:province":"TX",
    "sg:tags":[
        "commercial",
        "design"
    ],
    "wof:name":"Mgw Communications",
    "wof:placetype":"venue"
},
  "geometry": {"coordinates":[-98.47265,29.489219],"type":"Point"}
}