{
  "type": "Feature",
  "properties": {
    "iso:country":"US",
    "sg:address":"4620 N Shepherd Dr",
    "sg:city":"Houston",
    "sg:classifiers":[
        {
            "category":"Food & Beverages",
            "subcategory":"Liquor & Beverages",
            "type":"Retail Goods"
        }
    ],
    "sg:phone":"+1 713 697 4041",
    "sg:postcode":"77018",
    "sg:province":"TX",
    "sg:tags":[
        "beer",
        "wine",
        "spirit",
        "alcoholic"
    ],
    "wof:name":"Speedy Liquor",
    "wof:placetype":"venue"
},
  "geometry": {"coordinates":[-95.410599,29.832399],"type":"Point"}
}