{
  "type": "Feature",
  "properties": {
    "iso:country":"US",
    "sg:address":"2544 Bitters Rd",
    "sg:city":"San Antonio",
    "sg:classifiers":[
        {
            "category":"Manufacturing",
            "subcategory":"Tools & Machinery",
            "type":"Manufacturing & Wholesale Goods"
        }
    ],
    "sg:phone":"+1 210 804 1007",
    "sg:postcode":"78217",
    "sg:province":"TX",
    "sg:tags":[
        "equipment",
        "system",
        "automation"
    ],
    "sg:website":"www.megatrak.com",
    "wof:name":"Megatronics International Corp",
    "wof:placetype":"venue"
},
  "geometry": {"coordinates":[-98.448689,29.5332],"type":"Point"}
}