{
  "type": "Feature",
  "properties": {
    "iso:country":"US",
    "sg:address":"6944 Ridgmar Meadow Rd",
    "sg:city":"Fort Worth",
    "sg:classifiers":[
        {
            "category":"Restaurant",
            "type":"Food & Drink"
        }
    ],
    "sg:menulink":"http://www.allmenus.com/tx/fort-worth/130915-subway/menu/",
    "sg:phone":"+1 817 763 0016",
    "sg:postcode":"76116",
    "sg:province":"TX",
    "sg:tags":[
        "american",
        "sandwich"
    ],
    "wof:name":"Subway",
    "wof:placetype":"venue"
},
  "geometry": {"coordinates":[-97.435794,32.745482],"type":"Point"}
}