{
  "type": "Feature",
  "properties": {
    "iso:country":"US",
    "sg:address":"612 Pecos Dr",
    "sg:city":"Euless",
    "sg:classifiers":[
        {
            "category":"Real Estate",
            "subcategory":"Real Estate Services",
            "type":"Services"
        },
        {
            "category":"Real Estate",
            "subcategory":"Real Estate Agent",
            "type":"Services"
        }
    ],
    "sg:phone":"+1 817 283 5300",
    "sg:postcode":"76039",
    "sg:province":"TX",
    "sg:tags":[
        "buyer",
        "management",
        "broker"
    ],
    "wof:name":"Main Street Realty & Management",
    "wof:placetype":"venue"
},
  "geometry": {"coordinates":[-97.091673,32.845002],"type":"Point"}
}