{
  "type": "Feature",
  "properties": {
    "iso:country":"US",
    "sg:address":"3103 Astor Ct",
    "sg:city":"Sugar Land",
    "sg:classifiers":[
        {
            "category":"Building & Trades",
            "subcategory":"Plumbing",
            "type":"Services"
        }
    ],
    "sg:phone":"+1 281 277 3339",
    "sg:postcode":"77478",
    "sg:province":"TX",
    "sg:tags":[
        "contractor"
    ],
    "wof:name":"C&K Mechanical & Controls Inc",
    "wof:placetype":"venue"
},
  "geometry": {"coordinates":[-95.676096,29.634847],"type":"Point"}
}