{
  "type": "Feature",
  "properties": {
    "iso:country":"US",
    "sg:address":"7421 Chula Vista Dr",
    "sg:city":"Dallas",
    "sg:classifiers":[
        {
            "category":"Manufacturing",
            "subcategory":"Apparel",
            "type":"Manufacturing & Wholesale Goods"
        }
    ],
    "sg:phone":"+1 214 275 4298",
    "sg:postcode":"75227",
    "sg:province":"TX",
    "sg:tags":[
        "apparel-wholesale",
        "manufacturer",
        "women's"
    ],
    "wof:name":"Just To Flirt",
    "wof:placetype":"venue"
},
  "geometry": {"coordinates":[-96.694626,32.759418],"type":"Point"}
}