{
  "type": "Feature",
  "properties": {
    "iso:country":"US",
    "sg:address":"16500 FM 969",
    "sg:city":"Manor",
    "sg:classifiers":[
        {
            "category":"Home & Garden",
            "subcategory":"Garden Supply",
            "type":"Retail Goods"
        },
        {
            "category":"Building & Trades",
            "subcategory":"Landscaping Services",
            "type":"Services"
        }
    ],
    "sg:phone":"+1 512 276 7446",
    "sg:postcode":"78653",
    "sg:province":"TX",
    "sg:tags":[
        "sod",
        "landscape",
        "sodding"
    ],
    "wof:name":"Southwest Turf & Erosion Prod",
    "wof:placetype":"venue"
},
  "geometry": {"coordinates":[-97.557588,30.253082],"type":"Point"}
}