{
  "type": "Feature",
  "properties": {
    "iso:country":"US",
    "sg:address":"133 Pembroke Ln",
    "sg:city":"Wichita Falls",
    "sg:classifiers":[
        {
            "category":"Cinema",
            "subcategory":"Movie Rental",
            "type":"Entertainment"
        }
    ],
    "sg:phone":"+1 940 322 4902",
    "sg:postcode":"76301",
    "sg:province":"TX",
    "sg:tags":[
        "video",
        "tape"
    ],
    "wof:name":"All Occassion Video Albums",
    "wof:placetype":"venue"
},
  "geometry": {"coordinates":[-98.524868,33.907601],"type":"Point"}
}