{
  "type": "Feature",
  "properties": {
    "iso:country":"US",
    "sg:address":"109 W Church St",
    "sg:city":"Weatherford",
    "sg:classifiers":[
        {
            "category":"Banks & Credit Unions",
            "subcategory":"Investment Brokerage",
            "type":"Services"
        }
    ],
    "sg:phone":"+1 817 596 0255",
    "sg:postcode":"76086",
    "sg:province":"TX",
    "sg:tags":[
        "land",
        "oil",
        "lease"
    ],
    "wof:name":"Dave Deison",
    "wof:placetype":"venue"
},
  "geometry": {"coordinates":[-97.79915699999999,32.758286],"type":"Point"}
}