{
  "type": "Feature",
  "properties": {
    "iso:country":"US",
    "sg:address":"917 S Mason Rd",
    "sg:city":"Katy",
    "sg:classifiers":[
        {
            "category":"Banks & Credit Unions",
            "subcategory":"Bank",
            "type":"Services"
        }
    ],
    "sg:phone":"+1 281 398 9900",
    "sg:postcode":"77450",
    "sg:province":"TX",
    "wof:name":"Members Choice Credit Union",
    "wof:placetype":"venue"
},
  "geometry": {"coordinates":[-95.751614,29.768995],"type":"Point"}
}