{
  "type": "Feature",
  "properties": {
    "iso:country":"US",
    "sg:address":"2610 Pittsburgh St",
    "sg:city":"Houston",
    "sg:classifiers":[
        {
            "category":"Arena",
            "subcategory":"Sports Club",
            "type":"Entertainment"
        }
    ],
    "sg:phone":"+1 713 805 8736",
    "sg:postcode":"77005",
    "sg:province":"TX",
    "sg:tags":[
        "park",
        "baseball"
    ],
    "wof:name":"Baseball's Pro System Inc",
    "wof:placetype":"venue"
},
  "geometry": {"coordinates":[-95.418516,29.711107],"type":"Point"}
}