{
  "type": "Feature",
  "properties": {
    "iso:country":"US",
    "sg:address":"415 W San Antonio St",
    "sg:city":"Fredericksburg",
    "sg:classifiers":[
        {
            "category":"Shopping",
            "subcategory":"Florist",
            "type":"Retail Goods"
        }
    ],
    "sg:phone":"+1 830 997 7237",
    "sg:postcode":"78624",
    "sg:province":"TX",
    "wof:name":"Maggies Flowers",
    "wof:placetype":"venue"
},
  "geometry": {"coordinates":[-98.879921,30.278669],"type":"Point"}
}