{
  "type": "Feature",
  "properties": {
    "iso:country":"US",
    "sg:address":"1631 84th St",
    "sg:city":"Lubbock",
    "sg:classifiers":[
        {
            "category":"Government",
            "subcategory":"Office",
            "type":"Public Place"
        }
    ],
    "sg:phone":"+1 806 775 2491",
    "sg:postcode":"79423",
    "sg:province":"TX",
    "sg:tags":[
        "village"
    ],
    "wof:name":"Lubbock Recycling",
    "wof:placetype":"venue"
},
  "geometry": {"coordinates":[-101.85507200000001,33.5177],"type":"Point"}
}