{
  "type": "Feature",
  "properties": {
    "iso:country":"US",
    "sg:address":"14410 Traceton Cir",
    "sg:city":"Cypress",
    "sg:classifiers":[
        {
            "category":"Professional",
            "subcategory":"Business Services",
            "type":"Services"
        }
    ],
    "sg:phone":"+1 281 373 5989",
    "sg:postcode":"77429",
    "sg:province":"TX",
    "wof:name":"Delta Flow Technologies Co",
    "wof:placetype":"venue"
},
  "geometry": {"coordinates":[-95.640986,29.980548],"type":"Point"}
}