{
  "type": "Feature",
  "properties": {
    "iso:country":"US",
    "sg:address":"1410 Tanglewood Dr",
    "sg:city":"Commerce",
    "sg:classifiers":[
        {
            "category":"Real Estate",
            "subcategory":"Real Estate Agent",
            "type":"Services"
        }
    ],
    "sg:phone":"+1 903 886 7926",
    "sg:postcode":"75428",
    "sg:province":"TX",
    "wof:name":"Valentine Properties",
    "wof:placetype":"venue"
},
  "geometry": {"coordinates":[-95.901634,33.234112],"type":"Point"}
}