{
  "type": "Feature",
  "properties": {
    "iso:country":"US",
    "sg:address":"3539 Pinemont Dr",
    "sg:city":"Houston",
    "sg:classifiers":[
        {
            "category":"Autos & Motor Vehicles",
            "subcategory":"Automobile Sales",
            "type":"Retail Goods"
        }
    ],
    "sg:phone":"+1 713 681 1446",
    "sg:postcode":"77018",
    "sg:province":"TX",
    "sg:tags":[
        "automotive"
    ],
    "wof:name":"Adco Power Steering Products Inc",
    "wof:placetype":"venue"
},
  "geometry": {"coordinates":[-95.434928,29.841098],"type":"Point"}
}