{
  "type": "Feature",
  "properties": {
    "iso:country":"US",
    "sg:address":"609 E Mitchell St",
    "sg:city":"Calvert",
    "sg:classifiers":[
        {
            "category":"Building & Trades",
            "subcategory":"Plumbing",
            "type":"Services"
        }
    ],
    "sg:phone":"+1 979 364 2244",
    "sg:postcode":"77837",
    "sg:province":"TX",
    "sg:tags":[
        "plumbing-drain",
        "plumber",
        "sewer",
        "cleaning"
    ],
    "wof:name":"Country Wide Plumbing",
    "wof:placetype":"venue"
},
  "geometry": {"coordinates":[-96.67070200000001,30.982195],"type":"Point"}
}