{
  "type": "Feature",
  "properties": {
    "iso:country":"US",
    "sg:address":"24 Shady Grove Ln",
    "sg:city":"Wimberley",
    "sg:classifiers":[
        {
            "category":"Professional",
            "subcategory":"Management & Consulting",
            "type":"Services"
        }
    ],
    "sg:phone":"+1 512 847 9026",
    "sg:postcode":"78676",
    "sg:province":"TX",
    "wof:name":"Affordable Hsing Solutions LLC",
    "wof:placetype":"venue"
},
  "geometry": {"coordinates":[-98.11129,30.029905],"type":"Point"}
}