{
  "type": "Feature",
  "properties": {
    "iso:country":"US",
    "sg:address":"2630 Custer Pkwy",
    "sg:city":"Richardson",
    "sg:classifiers":[
        {
            "category":"Banks & Credit Unions",
            "subcategory":"Bank",
            "type":"Services"
        }
    ],
    "sg:phone":"+1 972 664 1648",
    "sg:postcode":"75080",
    "sg:province":"TX",
    "sg:tags":[
        "personal",
        "institution"
    ],
    "wof:name":"American Express",
    "wof:placetype":"venue"
},
  "geometry": {"coordinates":[-96.726687,32.98934],"type":"Point"}
}