{
  "type": "Feature",
  "properties": {
    "iso:country":"US",
    "sg:address":"18300 Upper Bay Rd",
    "sg:city":"Houston",
    "sg:classifiers":[
        {
            "category":"Organizations",
            "subcategory":"Religious Organization",
            "type":"Services"
        }
    ],
    "sg:phone":"+1 281 333 2384",
    "sg:postcode":"77058",
    "sg:province":"TX",
    "wof:name":"St Thomas Apostile Church",
    "wof:placetype":"venue"
},
  "geometry": {"coordinates":[-95.08802,29.546315],"type":"Point"}
}