{
  "type": "Feature",
  "properties": {
    "iso:country":"US",
    "sg:address":"894 FM 237",
    "sg:city":"Victoria",
    "sg:classifiers":[
        {
            "category":"Building & Trades",
            "subcategory":"Construction",
            "type":"Services"
        }
    ],
    "sg:phone":"+1 361 575 3319",
    "sg:postcode":"77905",
    "sg:province":"TX",
    "sg:tags":[
        "heavy"
    ],
    "wof:name":"Carter Dozer Service Inc",
    "wof:placetype":"venue"
},
  "geometry": {"coordinates":[-97.216525,28.896537],"type":"Point"}
}