{
  "type": "Feature",
  "properties": {
    "iso:country":"US",
    "sg:address":"15106 Leafy Ln",
    "sg:city":"Dallas",
    "sg:classifiers":[
        {
            "category":"Professional",
            "subcategory":"Management & Consulting",
            "type":"Services"
        }
    ],
    "sg:phone":"+1 972 392 2367",
    "sg:postcode":"75248",
    "sg:province":"TX",
    "sg:tags":[
        "consultant"
    ],
    "wof:name":"DNL Consultant",
    "wof:placetype":"venue"
},
  "geometry": {"coordinates":[-96.798857,32.955726],"type":"Point"}
}