{
  "type": "Feature",
  "properties": {
    "iso:country":"US",
    "sg:address":"808 W 10th St",
    "sg:city":"Austin",
    "sg:classifiers":[
        {
            "category":"Professional",
            "subcategory":"Management & Consulting",
            "type":"Services"
        }
    ],
    "sg:phone":"+1 512 494 1107",
    "sg:postcode":"78701",
    "sg:province":"TX",
    "sg:tags":[
        "consultant",
        "business"
    ],
    "wof:name":"Pepper's & Rogers Group",
    "wof:placetype":"venue"
},
  "geometry": {"coordinates":[-97.751373,30.274765],"type":"Point"}
}