{
  "type": "Feature",
  "properties": {
    "iso:country":"US",
    "sg:address":"4506 Banister Ln",
    "sg:city":"Austin",
    "sg:classifiers":[
        {
            "category":"Freight",
            "type":"Transportation"
        }
    ],
    "sg:phone":"+1 512 448 4881",
    "sg:postcode":"78745",
    "sg:province":"TX",
    "wof:name":"Millennium Freight Svc",
    "wof:placetype":"venue"
},
  "geometry": {"coordinates":[-97.782635,30.222114],"type":"Point"}
}