{
  "type": "Feature",
  "properties": {
    "iso:country":"US",
    "sg:address":"1127 Cedar Oaks Ln",
    "sg:city":"Harker Heights",
    "sg:classifiers":[
        {
            "category":"Building & Trades",
            "subcategory":"Construction",
            "type":"Services"
        }
    ],
    "sg:phone":"+1 254 698 3330",
    "sg:postcode":"76548",
    "sg:province":"TX",
    "sg:tags":[
        "house"
    ],
    "wof:name":"English Construction MGT LLC",
    "wof:placetype":"venue"
},
  "geometry": {"coordinates":[-97.64507999999999,31.073602],"type":"Point"}
}