{
  "type": "Feature",
  "properties": {
    "iso:country":"US",
    "sg:address":"1123 Craig St",
    "sg:city":"Corpus Christi",
    "sg:classifiers":[
        {
            "category":"Freight",
            "type":"Transportation"
        }
    ],
    "sg:phone":"+1 361 884 7151",
    "sg:postcode":"78404",
    "sg:province":"TX",
    "sg:tags":[
        "mover"
    ],
    "wof:name":"Tony's Transfer",
    "wof:placetype":"venue"
},
  "geometry": {"coordinates":[-97.40253,27.780209],"type":"Point"}
}