{
  "type": "Feature",
  "properties": {
    "iso:country":"US",
    "sg:address":"7900 FM 1826",
    "sg:city":"Austin",
    "sg:classifiers":[
        {
            "category":"Health Services",
            "subcategory":"Doctor",
            "type":"Services"
        }
    ],
    "sg:phone":"+1 512 301 1045",
    "sg:postcode":"78737",
    "sg:province":"TX",
    "sg:tags":[
        "physician",
        "surgeon",
        "medical"
    ],
    "wof:name":"Austin Southwest Obgyn",
    "wof:placetype":"venue"
},
  "geometry": {"coordinates":[-97.889184,30.227742],"type":"Point"}
}