{
  "type": "Feature",
  "properties": {
    "iso:country":"US",
    "sg:address":"703 Santa Maria St",
    "sg:city":"Sugar Land",
    "sg:classifiers":[
        {
            "category":"Shopping",
            "subcategory":"Florist",
            "type":"Retail Goods"
        }
    ],
    "sg:phone":"+1 281 242 9320",
    "sg:postcode":"77478",
    "sg:province":"TX",
    "wof:name":"Floral Memories",
    "wof:placetype":"venue"
},
  "geometry": {"coordinates":[-95.626077,29.617216],"type":"Point"}
}