{
  "type": "Feature",
  "properties": {
    "iso:country":"US",
    "sg:address":"118 W Ave F",
    "sg:city":"Temple",
    "sg:classifiers":[
        {
            "category":"Bars & Pubs",
            "type":"Food & Drink"
        }
    ],
    "sg:phone":"+1 254 778 9644",
    "sg:postcode":"76504",
    "sg:province":"TX",
    "sg:tags":[
        "drinking"
    ],
    "wof:name":"Lisas Dance Commission",
    "wof:placetype":"venue"
},
  "geometry": {"coordinates":[-97.345209,31.091245],"type":"Point"}
}