{
  "type": "Feature",
  "properties": {
    "iso:country":"US",
    "sg:address":"14 Gate Hill Dr",
    "sg:city":"Spring",
    "sg:classifiers":[
        {
            "category":"Shopping",
            "subcategory":"Jewelry",
            "type":"Retail Goods"
        }
    ],
    "sg:phone":"+1 281 298 1500",
    "sg:postcode":"77381",
    "sg:province":"TX",
    "wof:name":"Annies Things",
    "wof:placetype":"venue"
},
  "geometry": {"coordinates":[-95.51626899999999,30.16384],"type":"Point"}
}