{
  "type": "Feature",
  "properties": {
    "iso:country":"US",
    "sg:address":"2861 Ridge Rd",
    "sg:city":"Rockwall",
    "sg:classifiers":[
        {
            "category":"Shopping",
            "subcategory":"Optical Goods",
            "type":"Retail Goods"
        }
    ],
    "sg:phone":"+1 972 772 9597",
    "sg:postcode":"75032",
    "sg:province":"TX",
    "wof:name":"Eyecare & Laser of Rockwall",
    "wof:placetype":"venue"
},
  "geometry": {"coordinates":[-96.473221,32.883994],"type":"Point"}
}