{
  "type": "Feature",
  "properties": {
    "iso:country":"US",
    "sg:address":"1019 E Saint Elmo Rd",
    "sg:city":"Austin",
    "sg:classifiers":[
        {
            "category":"Organizations",
            "subcategory":"Labor Organization",
            "type":"Services"
        }
    ],
    "sg:phone":"+1 512 441 4222",
    "sg:postcode":"78745",
    "sg:province":"TX",
    "wof:name":"L & L Enterprises",
    "wof:placetype":"venue"
},
  "geometry": {"coordinates":[-97.75414000000001,30.213503],"type":"Point"}
}