{
  "type": "Feature",
  "properties": {
    "iso:country":"US",
    "sg:address":"507 Sabine St",
    "sg:city":"Austin",
    "sg:classifiers":[
        {
            "category":"Travel",
            "subcategory":"Hotels & Motels",
            "type":"Entertainment"
        }
    ],
    "sg:phone":"+1 512 494 0875",
    "sg:postcode":"78701",
    "sg:province":"TX",
    "wof:name":"Sheraton",
    "wof:placetype":"venue"
},
  "geometry": {"coordinates":[-97.736074,30.266095],"type":"Point"}
}