{
  "type": "Feature",
  "properties": {
    "iso:country":"US",
    "sg:address":"1008 W Erwin Ave",
    "sg:city":"Mckinney",
    "sg:phone":"+1 972 548 0808",
    "sg:postcode":"75069",
    "sg:province":"TX",
    "wof:name":"Victory Christian Church",
    "wof:placetype":"venue"
},
  "geometry": {"coordinates":[-96.623817,33.208149],"type":"Point"}
}