{
  "type": "Feature",
  "properties": {
    "iso:country":"US",
    "sg:address":"358 Summers Rd",
    "sg:city":"Copperas Cove",
    "sg:classifiers":[
        {
            "category":"Farming",
            "subcategory":"Livestock Farm",
            "type":"Manufacturing & Wholesale Goods"
        }
    ],
    "sg:phone":"+1 254 542 7461",
    "sg:postcode":"76522",
    "sg:province":"TX",
    "sg:tags":[
        "equine"
    ],
    "wof:name":"Buffalo Ridge Ranch",
    "wof:placetype":"venue"
},
  "geometry": {"coordinates":[-97.93210000000001,31.146697],"type":"Point"}
}