{
  "type": "Feature",
  "properties": {
    "iso:country":"US",
    "sg:address":"407 16th St",
    "sg:city":"Wellington",
    "sg:classifiers":[
        {
            "category":"Farming",
            "subcategory":"Farm",
            "type":"Manufacturing & Wholesale Goods"
        }
    ],
    "sg:phone":"+1 806 447 2141",
    "sg:postcode":"79095",
    "sg:province":"TX",
    "sg:tags":[
        "crop",
        "general"
    ],
    "wof:name":"Wischkaemper Farms Ltd",
    "wof:placetype":"venue"
},
  "geometry": {"coordinates":[-100.21682699999999,34.847404],"type":"Point"}
}