{
  "type": "Feature",
  "properties": {
    "iso:country":"US",
    "sg:address":"6701 Indiana Ave",
    "sg:city":"Lubbock",
    "sg:classifiers":[
        {
            "category":"Shopping",
            "subcategory":"Bicycles & Sporting Goods",
            "type":"Retail Goods"
        }
    ],
    "sg:phone":"+1 806 796 2453",
    "sg:postcode":"79413",
    "sg:province":"TX",
    "sg:tags":[
        "equipment",
        "exercise"
    ],
    "sg:website":"www.dfccyclesandfitness.com",
    "wof:name":"DFC Cycles & Fitness",
    "wof:placetype":"venue"
},
  "geometry": {"coordinates":[-101.887739,33.532956],"type":"Point"}
}