{
  "type": "Feature",
  "properties": {
    "iso:country":"US",
    "sg:address":"14315 Lee Rd",
    "sg:city":"Houston",
    "sg:classifiers":[
        {
            "category":"Retail",
            "subcategory":"Auto Repair",
            "type":"Services"
        }
    ],
    "sg:phone":"+1 281 987 0367",
    "sg:postcode":"77032",
    "sg:province":"TX",
    "wof:name":"Campbell & Sons Automotive Repair",
    "wof:placetype":"venue"
},
  "geometry": {"coordinates":[-95.302902,29.926399],"type":"Point"}
}