{
  "type": "Feature",
  "properties": {
    "iso:country":"US",
    "sg:address":"111 S Mill Trace Dr",
    "sg:city":"Spring",
    "sg:classifiers":[
        {
            "category":"Restaurant",
            "type":"Food & Drink"
        }
    ],
    "sg:phone":"+1 281 367 8337",
    "sg:postcode":"77381",
    "sg:province":"TX",
    "sg:tags":[
        "eating"
    ],
    "wof:name":"Highlander Home Run Club",
    "wof:placetype":"venue"
},
  "geometry": {"coordinates":[-95.495364,30.180099],"type":"Point"}
}