{
  "type": "Feature",
  "properties": {
    "iso:country":"US",
    "sg:address":"2001 Parker Ln",
    "sg:city":"Austin",
    "sg:classifiers":[
        {
            "category":"Arts & Performance",
            "subcategory":"Theater",
            "type":"Entertainment"
        }
    ],
    "sg:phone":"+1 512 441 4720",
    "sg:postcode":"78741",
    "sg:province":"TX",
    "sg:tags":[
        "theatrical"
    ],
    "wof:name":"Gary Payne Productions",
    "wof:placetype":"venue"
},
  "geometry": {"coordinates":[-97.735812,30.234045],"type":"Point"}
}