{
  "type": "Feature",
  "properties": {
    "iso:country":"US",
    "sg:address":"7005 Weaver Rd",
    "sg:city":"Houston",
    "sg:classifiers":[
        {
            "category":"Retail",
            "subcategory":"Auto Repair",
            "type":"Services"
        }
    ],
    "sg:phone":"+1 713 635 5576",
    "sg:postcode":"77028",
    "sg:province":"TX",
    "sg:tags":[
        "general"
    ],
    "wof:name":"Charles Car Care",
    "wof:placetype":"venue"
},
  "geometry": {"coordinates":[-95.303607,29.831434],"type":"Point"}
}