{
  "type": "Feature",
  "properties": {
    "iso:country":"US",
    "sg:address":"3129 Executive Dr",
    "sg:city":"San Angelo",
    "sg:classifiers":[
        {
            "category":"Insurance",
            "subcategory":"Insurance Agent",
            "type":"Services"
        }
    ],
    "sg:phone":"+1 325 223 9210",
    "sg:postcode":"76904",
    "sg:province":"TX",
    "sg:website":"www.primerica.com",
    "wof:name":"Primerica Financial Svc",
    "wof:placetype":"venue"
},
  "geometry": {"coordinates":[-100.463022,31.422902],"type":"Point"}
}