{
  "type": "Feature",
  "properties": {
    "iso:country":"US",
    "sg:address":"3501 Hwy 67",
    "sg:city":"Mesquite",
    "sg:classifiers":[
        {
            "category":"Restaurant",
            "type":"Food & Drink"
        }
    ],
    "sg:phone":"+1 972 613 9288",
    "sg:postcode":"75150",
    "sg:province":"TX",
    "sg:tags":[
        "eating"
    ],
    "wof:name":"Castillo's Mexican Restaurant",
    "wof:placetype":"venue"
},
  "geometry": {"coordinates":[-96.653412,32.811227],"type":"Point"}
}