{
  "type": "Feature",
  "properties": {
    "iso:country":"US",
    "sg:address":"5328 E Lancaster Ave",
    "sg:city":"Fort Worth",
    "sg:classifiers":[
        {
            "category":"Shopping",
            "subcategory":"Department Store",
            "type":"Retail Goods"
        }
    ],
    "sg:phone":"+1 817 457 8200",
    "sg:postcode":"76112",
    "sg:province":"TX",
    "wof:name":"Kmart",
    "wof:placetype":"venue"
},
  "geometry": {"coordinates":[-97.241075,32.740413],"type":"Point"}
}