{
  "type": "Feature",
  "properties": {
    "iso:country":"US",
    "sg:address":"2205 Llano Ct",
    "sg:city":"Conroe",
    "sg:classifiers":[
        {
            "category":"Building & Trades",
            "subcategory":"Construction",
            "type":"Services"
        }
    ],
    "sg:phone":"+1 936 273 9733",
    "sg:postcode":"77384",
    "sg:province":"TX",
    "sg:tags":[
        "house"
    ],
    "wof:name":"ABS Handyman Services",
    "wof:placetype":"venue"
},
  "geometry": {"coordinates":[-95.502152,30.263952],"type":"Point"}
}