{
  "type": "Feature",
  "properties": {
    "iso:country":"US",
    "sg:address":"3320 Custer Rd",
    "sg:city":"Plano",
    "sg:classifiers":[
        {
            "category":"Autos & Motor Vehicles",
            "subcategory":"Auto Supplies",
            "type":"Retail Goods"
        }
    ],
    "sg:phone":"+1 972 612 1424",
    "sg:postcode":"75023",
    "sg:province":"TX",
    "sg:tags":[
        "tire"
    ],
    "wof:name":"Parker Custer Tire Svc",
    "wof:placetype":"venue"
},
  "geometry": {"coordinates":[-96.73331899999999,33.041064],"type":"Point"}
}