{
  "type": "Feature",
  "properties": {
    "iso:country":"US",
    "sg:address":"2400 Coit Rd",
    "sg:city":"Plano",
    "sg:classifiers":[
        {
            "category":"Cafe",
            "type":"Food & Drink"
        }
    ],
    "sg:menulink":"http://www.allmenus.com/tx/plano/49332-indus-cafe/menu/",
    "sg:phone":"+1 469 467 9525",
    "sg:postcode":"75075",
    "sg:province":"TX",
    "sg:tags":[
        "indian",
        "asian"
    ],
    "wof:name":"Indus Cafe",
    "wof:placetype":"venue"
},
  "geometry": {"coordinates":[-96.77015400000001,33.03097],"type":"Point"}
}