{
  "type": "Feature",
  "properties": {
    "iso:country":"US",
    "sg:address":"1745 N Fry Rd",
    "sg:city":"Katy",
    "sg:classifiers":[
        {
            "category":"Shopping",
            "subcategory":"Shoes",
            "type":"Retail Goods"
        }
    ],
    "sg:phone":"+1 281 578 6426",
    "sg:postcode":"77449",
    "sg:province":"TX",
    "sg:tags":[
        "shoe",
        "store"
    ],
    "wof:name":"Famous Footwear 393",
    "wof:placetype":"venue"
},
  "geometry": {"coordinates":[-95.718817,29.790238],"type":"Point"}
}