{
  "type": "Feature",
  "properties": {
    "iso:country":"US",
    "sg:address":"1359 Hugh Rd",
    "sg:city":"Houston",
    "sg:classifiers":[
        {
            "category":"Retail",
            "subcategory":"Auto Repair",
            "type":"Services"
        }
    ],
    "sg:phone":"+1 281 875 8224",
    "sg:postcode":"77067",
    "sg:province":"TX",
    "sg:tags":[
        "general"
    ],
    "wof:name":"Car Guys",
    "wof:placetype":"venue"
},
  "geometry": {"coordinates":[-95.439623,29.959833],"type":"Point"}
}