{
  "type": "Feature",
  "properties": {
    "iso:country":"US",
    "sg:address":"2803 W Illinois Ave",
    "sg:city":"Dallas",
    "sg:classifiers":[
        {
            "category":"Real Estate",
            "subcategory":"Real Estate Services",
            "type":"Services"
        },
        {
            "category":"Real Estate",
            "subcategory":"Real Estate Operator",
            "type":"Services"
        }
    ],
    "sg:phone":"+1 214 337 8682",
    "sg:postcode":"75233",
    "sg:province":"TX",
    "sg:tags":[
        "vacancy",
        "apartment",
        "rental",
        "listing"
    ],
    "wof:name":"Oakridge Apartments",
    "wof:placetype":"venue"
},
  "geometry": {"coordinates":[-96.865754,32.720379],"type":"Point"}
}