{
  "type": "Feature",
  "properties": {
    "iso:country":"US",
    "sg:address":"8515 Spring Cypress Rd Ste 100",
    "sg:city":"Spring",
    "sg:classifiers":[
        {
            "category":"Insurance",
            "subcategory":"Insurance Agent",
            "type":"Services"
        },
        {
            "category":"Insurance",
            "subcategory":"Hazard Insurance",
            "type":"Services"
        }
    ],
    "sg:phone":"+1 866 332 5508",
    "sg:postcode":"77379",
    "sg:province":"TX",
    "sg:tags":[
        "auto",
        "truck",
        "motorcycle"
    ],
    "wof:name":"Nationwide Insurance",
    "wof:placetype":"venue"
},
  "geometry": {"coordinates":[-95.554216,30.034707],"type":"Point"}
}