{
  "type": "Feature",
  "properties": {
    "iso:country":"US",
    "sg:address":"301 Butternut St",
    "sg:city":"Abilene",
    "sg:classifiers":[
        {
            "category":"Autos & Motor Vehicles",
            "subcategory":"Automobile Sales",
            "type":"Retail Goods"
        }
    ],
    "sg:phone":"+1 325 677 1164",
    "sg:postcode":"79602",
    "sg:province":"TX",
    "sg:tags":[
        "car",
        "used"
    ],
    "wof:name":"Baccus Jim Motors",
    "wof:placetype":"venue"
},
  "geometry": {"coordinates":[-99.73764,32.446739],"type":"Point"}
}