{
  "type": "Feature",
  "properties": {
    "iso:country":"US",
    "sg:address":"505 University Dr",
    "sg:city":"College Station",
    "sg:classifiers":[
        {
            "category":"Personal",
            "subcategory":"Beauty Salon",
            "type":"Services"
        }
    ],
    "sg:phone":"+1 979 846 3299",
    "sg:postcode":"77840",
    "sg:province":"TX",
    "wof:name":"Zydeco",
    "wof:placetype":"venue"
},
  "geometry": {"coordinates":[-96.344088,30.619679],"type":"Point"}
}