{
  "type": "Feature",
  "properties": {
    "iso:country":"US",
    "sg:address":"4625 Ridgelawn Dr",
    "sg:city":"Dallas",
    "sg:classifiers":[
        {
            "category":"Professional",
            "type":"Services"
        }
    ],
    "sg:phone":"+1 214 342 0066",
    "sg:postcode":"75214",
    "sg:province":"TX",
    "wof:name":"Inforay Inc",
    "wof:placetype":"venue"
},
  "geometry": {"coordinates":[-96.756215,32.84484],"type":"Point"}
}