{
  "type": "Feature",
  "properties": {
    "iso:country":"US",
    "sg:address":"1520 Hickory Tree Rd",
    "sg:city":"Mesquite",
    "sg:classifiers":[
        {
            "category":"Shopping",
            "subcategory":"Florist",
            "type":"Retail Goods"
        }
    ],
    "sg:phone":"+1 972 285 7508",
    "sg:postcode":"75149",
    "sg:province":"TX",
    "wof:name":"Alpha Flowerland",
    "wof:placetype":"venue"
},
  "geometry": {"coordinates":[-96.622474,32.750651],"type":"Point"}
}