{
  "type": "Feature",
  "properties": {
    "iso:country":"US",
    "sg:address":"509 Kasberg Dr",
    "sg:city":"Temple",
    "sg:classifiers":[
        {
            "category":"Organizations",
            "subcategory":"Labor Organization",
            "type":"Services"
        }
    ],
    "sg:phone":"+1 254 773 2485",
    "sg:postcode":"76502",
    "sg:province":"TX",
    "wof:name":"Rmsj Investments Management",
    "wof:placetype":"venue"
},
  "geometry": {"coordinates":[-97.406904,31.120765],"type":"Point"}
}