{
  "type": "Feature",
  "properties": {
    "iso:country":"US",
    "sg:address":"909 Little Creek Trl",
    "sg:city":"Red Oak",
    "sg:classifiers":[
        {
            "category":"Building & Trades",
            "subcategory":"Construction",
            "type":"Services"
        }
    ],
    "sg:phone":"+1 972 617 2004",
    "sg:postcode":"75154",
    "sg:province":"TX",
    "sg:tags":[
        "contractor"
    ],
    "wof:name":"All American Roofing",
    "wof:placetype":"venue"
},
  "geometry": {"coordinates":[-96.847251,32.525499],"type":"Point"}
}