{
  "type": "Feature",
  "properties": {
    "iso:country":"US",
    "sg:address":"4809 Oak Valley Dr",
    "sg:city":"Orange",
    "sg:classifiers":[
        {
            "category":"Building & Trades",
            "subcategory":"Landscaping Services",
            "type":"Services"
        }
    ],
    "sg:phone":"+1 409 883 2411",
    "sg:postcode":"77632",
    "sg:province":"TX",
    "sg:tags":[
        "landscape"
    ],
    "wof:name":"Kens Ldscpg Yard & Lawn Svc",
    "wof:placetype":"venue"
},
  "geometry": {"coordinates":[-93.75636799999999,30.132472],"type":"Point"}
}