{
  "type": "Feature",
  "properties": {
    "iso:country":"US",
    "sg:address":"1742 Berkoff Dr",
    "sg:city":"Sugar Land",
    "sg:classifiers":[
        {
            "category":"Professional",
            "type":"Services"
        }
    ],
    "sg:phone":"+1 281 277 6723",
    "sg:postcode":"77479",
    "sg:province":"TX",
    "wof:name":"Andy Montez",
    "wof:placetype":"venue"
},
  "geometry": {"coordinates":[-95.665187,29.585933],"type":"Point"}
}