{
  "type": "Feature",
  "properties": {
    "iso:country":"US",
    "sg:address":"6909 Trapper Ct",
    "sg:city":"Arlington",
    "sg:classifiers":[
        {
            "category":"Building & Trades",
            "subcategory":"Construction",
            "type":"Services"
        }
    ],
    "sg:phone":"+1 817 561 9136",
    "sg:postcode":"76001",
    "sg:province":"TX",
    "sg:tags":[
        "house",
        "nonresidential"
    ],
    "wof:name":"Cbc Construction Co Inc",
    "wof:placetype":"venue"
},
  "geometry": {"coordinates":[-97.15992199999999,32.63237],"type":"Point"}
}