{
  "type": "Feature",
  "properties": {
    "iso:country":"US",
    "sg:address":"2100 N Breckenridge St",
    "sg:city":"Ennis",
    "sg:classifiers":[
        {
            "category":"Building & Trades",
            "subcategory":"Cleaning & Sanitation",
            "type":"Services"
        }
    ],
    "sg:phone":"+1 972 878 8922",
    "sg:postcode":"75119",
    "sg:province":"TX",
    "sg:tags":[
        "maintenance"
    ],
    "wof:name":"McGowan Janitorial Services",
    "wof:placetype":"venue"
},
  "geometry": {"coordinates":[-96.636105,32.343967],"type":"Point"}
}