{
  "type": "Feature",
  "properties": {
    "iso:country":"US",
    "sg:address":"4106 Sherwood Way",
    "sg:city":"San Angelo",
    "sg:classifiers":[
        {
            "category":"Shopping",
            "type":"Retail Goods"
        }
    ],
    "sg:phone":"+1 325 223 9800",
    "sg:postcode":"76901",
    "sg:province":"TX",
    "sg:tags":[
        "cosmetic",
        "perfume"
    ],
    "wof:name":"Avon & Gift Shop",
    "wof:placetype":"venue"
},
  "geometry": {"coordinates":[-100.489672,31.44014],"type":"Point"}
}