{
  "type": "Feature",
  "properties": {
    "iso:country":"US",
    "sg:address":"913 W Loop 281",
    "sg:city":"Longview",
    "sg:classifiers":[
        {
            "category":"Sports & Exercise",
            "subcategory":"Gym",
            "type":"Entertainment"
        }
    ],
    "sg:phone":"+1 903 297 4919",
    "sg:postcode":"75604",
    "sg:province":"TX",
    "sg:tags":[
        "gymnasium"
    ],
    "wof:name":"Four Minute Fitness",
    "wof:placetype":"venue"
},
  "geometry": {"coordinates":[-94.765781,32.537091],"type":"Point"}
}