{
  "type": "Feature",
  "properties": {
    "iso:country":"US",
    "sg:address":"2809 Clendenen St",
    "sg:city":"Longview",
    "sg:classifiers":[
        {
            "category":"Social Services",
            "subcategory":"Job Training",
            "type":"Services"
        }
    ],
    "sg:phone":"+1 903 758 6801",
    "sg:postcode":"75605",
    "sg:province":"TX",
    "sg:tags":[
        "disabled",
        "developmentally"
    ],
    "wof:name":"Glenn Community Home",
    "wof:placetype":"venue"
},
  "geometry": {"coordinates":[-94.75963900000001,32.532678],"type":"Point"}
}