{
  "type": "Feature",
  "properties": {
    "iso:country":"US",
    "sg:address":"1617 Summit Ridge",
    "sg:city":"Garland",
    "sg:classifiers":[
        {
            "category":"Freight",
            "type":"Transportation"
        }
    ],
    "sg:phone":"+1 972 989 0167",
    "sg:postcode":"75043",
    "sg:province":"TX",
    "sg:tags":[
        "delivery"
    ],
    "wof:name":"Asapp Courier Svc",
    "wof:placetype":"venue"
},
  "geometry": {"coordinates":[-96.593643,32.871839],"type":"Point"}
}