{
  "type": "Feature",
  "properties": {
    "iso:country":"US",
    "sg:address":"9898 Bissonnet St",
    "sg:city":"Houston",
    "sg:classifiers":[
        {
            "category":"Professional",
            "subcategory":"Advertising",
            "type":"Services"
        }
    ],
    "sg:phone":"+1 713 272 0003",
    "sg:postcode":"77036",
    "sg:province":"TX",
    "sg:tags":[
        "agency"
    ],
    "wof:name":"Rent-A-Center",
    "wof:placetype":"venue"
},
  "geometry": {"coordinates":[-95.55271500000001,29.675152],"type":"Point"}
}