{
  "type": "Feature",
  "properties": {
    "iso:country":"US",
    "sg:address":"7847 Chinon Cir",
    "sg:city":"Houston",
    "sg:classifiers":[
        {
            "category":"Building & Trades",
            "subcategory":"Landscaping Services",
            "type":"Services"
        }
    ],
    "sg:phone":"+1 713 726 8093",
    "sg:postcode":"77071",
    "sg:province":"TX",
    "wof:name":"Cristobal Lawn Service",
    "wof:placetype":"venue"
},
  "geometry": {"coordinates":[-95.51358,29.637128],"type":"Point"}
}