{
  "type": "Feature",
  "properties": {
    "iso:country":"US",
    "sg:address":"684 S Mill St",
    "sg:city":"Lewisville",
    "sg:classifiers":[
        {
            "category":"Autos & Motor Vehicles",
            "subcategory":"Recreational Vehicle Sales",
            "type":"Retail Goods"
        }
    ],
    "sg:phone":"+1 972 353 4240",
    "sg:postcode":"75057",
    "sg:province":"TX",
    "wof:name":"Texas Truck & Trailer",
    "wof:placetype":"venue"
},
  "geometry": {"coordinates":[-96.992831,33.039846],"type":"Point"}
}