{
  "type": "Feature",
  "properties": {
    "iso:country":"US",
    "sg:address":"490 N Crockett St",
    "sg:city":"San Benito",
    "sg:classifiers":[
        {
            "category":"Organizations",
            "subcategory":"Religious Organization",
            "type":"Services"
        }
    ],
    "sg:phone":"+1 956 399 5094",
    "sg:postcode":"78586",
    "sg:province":"TX",
    "sg:tags":[
        "church"
    ],
    "wof:name":"First Church Of The Nazarene",
    "wof:placetype":"venue"
},
  "geometry": {"coordinates":[-97.627768,26.132826],"type":"Point"}
}