{
  "type": "Feature",
  "properties": {
    "iso:country":"US",
    "sg:address":"854 E Van Buren St",
    "sg:city":"Brownsville",
    "sg:classifiers":[
        {
            "category":"Professional",
            "subcategory":"Lawyer & Legal Services",
            "type":"Services"
        }
    ],
    "sg:phone":"+1 956 544 2911",
    "sg:postcode":"78520",
    "sg:province":"TX",
    "wof:name":"Noe D Garza Jr",
    "wof:placetype":"venue"
},
  "geometry": {"coordinates":[-97.495846,25.907557],"type":"Point"}
}