{
  "type": "Feature",
  "properties": {
    "iso:country":"US",
    "sg:address":"612 N Resident St",
    "sg:city":"Wharton",
    "sg:classifiers":[
        {
            "category":"Travel",
            "subcategory":"Hotels & Motels",
            "type":"Entertainment"
        }
    ],
    "sg:phone":"+1 979 532 0242",
    "sg:postcode":"77488",
    "sg:province":"TX",
    "sg:tags":[
        "operation"
    ],
    "wof:name":"Birdsong Inn",
    "wof:placetype":"venue"
},
  "geometry": {"coordinates":[-96.095721,29.315604],"type":"Point"}
}