{
  "type": "Feature",
  "properties": {
    "iso:country":"US",
    "sg:address":"7305 Lance Ave",
    "sg:city":"Pasadena",
    "sg:classifiers":[
        {
            "category":"Professional",
            "subcategory":"Credit Reporting & Collection",
            "type":"Services"
        }
    ],
    "sg:phone":"+1 713 472 4706",
    "sg:postcode":"77505",
    "sg:province":"TX",
    "sg:tags":[
        "establishment",
        "class"
    ],
    "wof:name":"Sams Distributing",
    "wof:placetype":"venue"
},
  "geometry": {"coordinates":[-95.127078,29.661725],"type":"Point"}
}