{
  "type": "Feature",
  "properties": {
    "iso:country":"US",
    "sg:address":"414 Manor Rd",
    "sg:city":"Laredo",
    "sg:classifiers":[
        {
            "category":"Real Estate",
            "subcategory":"Real Estate Services",
            "type":"Services"
        },
        {
            "category":"Banks & Credit Unions",
            "subcategory":"Financial Services",
            "type":"Services"
        }
    ],
    "sg:phone":"+1 956 727 5661",
    "sg:postcode":"78041",
    "sg:province":"TX",
    "sg:tags":[
        "loan",
        "processing"
    ],
    "wof:name":"Mba Mortgage Services",
    "wof:placetype":"venue"
},
  "geometry": {"coordinates":[-99.47805,27.56451],"type":"Point"}
}