{
  "type": "Feature",
  "properties": {
    "iso:country":"US",
    "sg:address":"424 US Hwy 84",
    "sg:city":"Fairfield",
    "sg:classifiers":[
        {
            "category":"Building & Trades",
            "subcategory":"Construction",
            "type":"Services"
        }
    ],
    "sg:phone":"+1 903 389 6253",
    "sg:postcode":"75840",
    "sg:province":"TX",
    "sg:tags":[
        "house"
    ],
    "wof:name":"Quality Builders Ron Fren",
    "wof:placetype":"venue"
},
  "geometry": {"coordinates":[-96.17229500000001,31.720729],"type":"Point"}
}