{
  "type": "Feature",
  "properties": {
    "iso:country":"US",
    "sg:address":"1855 Frankford Rd W",
    "sg:city":"Carrollton",
    "sg:classifiers":[
        {
            "category":"Restaurant",
            "type":"Food & Drink"
        }
    ],
    "sg:phone":"+1 972 492 1474",
    "sg:postcode":"75007",
    "sg:province":"TX",
    "sg:tags":[
        "pizza"
    ],
    "wof:name":"Joe's Pizza Pasta & Subs",
    "wof:placetype":"venue"
},
  "geometry": {"coordinates":[-96.941654,32.992961],"type":"Point"}
}