{
  "type": "Feature",
  "properties": {
    "iso:country":"US",
    "sg:address":"815 Main St",
    "sg:city":"Houston",
    "sg:classifiers":[
        {
            "category":"Restaurant",
            "type":"Food & Drink"
        }
    ],
    "sg:phone":"+1 713 227 0608",
    "sg:postcode":"77002",
    "sg:province":"TX",
    "sg:tags":[
        "eating"
    ],
    "wof:name":"Metro Restaurant",
    "wof:placetype":"venue"
},
  "geometry": {"coordinates":[-95.36418999999999,29.757747],"type":"Point"}
}