{
  "type": "Feature",
  "properties": {
    "iso:country":"US",
    "sg:address":"720 Hospital Dr",
    "sg:city":"Andrews",
    "sg:classifiers":[
        {
            "category":"Health Services",
            "subcategory":"Health Practitioner",
            "type":"Services"
        }
    ],
    "sg:phone":"+1 432 464 2125",
    "sg:postcode":"79714",
    "sg:province":"TX",
    "sg:tags":[
        "therapist",
        "physical"
    ],
    "wof:name":"PRMC Physical Therapy",
    "wof:placetype":"venue"
},
  "geometry": {"coordinates":[-102.545973,32.33703],"type":"Point"}
}