{
  "type": "Feature",
  "properties": {
    "iso:country":"US",
    "sg:address":"417 Elam",
    "sg:city":"Lewisville",
    "sg:classifiers":[
        {
            "category":"Shopping",
            "subcategory":"Discount & Variety Stores",
            "type":"Retail Goods"
        }
    ],
    "sg:phone":"+1 972 219 5499",
    "sg:postcode":"75067",
    "sg:province":"TX",
    "sg:tags":[
        "merchandise",
        "general"
    ],
    "wof:name":"Diverse Business Group",
    "wof:placetype":"venue"
},
  "geometry": {"coordinates":[-97.000485,33.023936],"type":"Point"}
}