{
  "type": "Feature",
  "properties": {
    "iso:country":"US",
    "sg:address":"600 SW 19th St",
    "sg:city":"San Antonio",
    "sg:classifiers":[
        {
            "category":"Social Services",
            "type":"Services"
        }
    ],
    "sg:phone":"+1 210 436 0686",
    "sg:postcode":"78207",
    "sg:province":"TX",
    "sg:tags":[
        "youth",
        "development",
        "center"
    ],
    "wof:name":"Boys & Girls Clubs San Antonio",
    "wof:placetype":"venue"
},
  "geometry": {"coordinates":[-98.53685,29.423109],"type":"Point"}
}