{
  "type": "Feature",
  "properties": {
    "iso:country":"US",
    "sg:address":"14207 Poneal Ct",
    "sg:city":"Houston",
    "sg:classifiers":[
        {
            "category":"Organizations",
            "subcategory":"Religious Organization",
            "type":"Services"
        }
    ],
    "sg:phone":"+1 281 859 7839",
    "sg:postcode":"77084",
    "sg:province":"TX",
    "wof:name":"First Indonesian Baptist CHR",
    "wof:placetype":"venue"
},
  "geometry": {"coordinates":[-95.623582,29.85841],"type":"Point"}
}