{
  "type": "Feature",
  "properties": {
    "iso:country":"US",
    "sg:address":"2231 Old Bullard Rd",
    "sg:city":"Tyler",
    "sg:classifiers":[
        {
            "category":"Professional",
            "subcategory":"Lawyer & Legal Services",
            "type":"Services"
        }
    ],
    "sg:phone":"+1 903 593 6749",
    "sg:postcode":"75701",
    "sg:province":"TX",
    "sg:tags":[
        "attorney",
        "practice"
    ],
    "wof:name":"Flock, Jack W",
    "wof:placetype":"venue"
},
  "geometry": {"coordinates":[-95.303207,32.325516],"type":"Point"}
}