{
  "type": "Feature",
  "properties": {
    "iso:country":"US",
    "sg:address":"991 W Nasa Rd 1",
    "sg:city":"Webster",
    "sg:classifiers":[
        {
            "category":"Banks & Credit Unions",
            "subcategory":"Bank",
            "type":"Services"
        }
    ],
    "sg:phone":"+1 281 990 6630",
    "sg:postcode":"77598",
    "sg:province":"TX",
    "sg:tags":[
        "loan"
    ],
    "wof:name":"Advance America",
    "wof:placetype":"venue"
},
  "geometry": {"coordinates":[-95.126041,29.531889],"type":"Point"}
}