{
  "type": "Feature",
  "properties": {
    "iso:country":"US",
    "sg:address":"2401 Fountain View Dr",
    "sg:city":"Houston",
    "sg:classifiers":[
        {
            "category":"Marine",
            "type":"Transportation"
        }
    ],
    "sg:phone":"+1 713 780 9926",
    "sg:postcode":"77057",
    "sg:province":"TX",
    "sg:tags":[
        "water",
        "transport"
    ],
    "wof:name":"Trico Marine Operators Inc",
    "wof:placetype":"venue"
},
  "geometry": {"coordinates":[-95.485069,29.741034],"type":"Point"}
}