{
  "type": "Feature",
  "properties": {
    "iso:country":"US",
    "sg:address":"603 Avondale St",
    "sg:city":"Houston",
    "sg:classifiers":[
        {
            "category":"Social Services",
            "type":"Services"
        }
    ],
    "sg:phone":"+1 713 522 5428",
    "sg:postcode":"77006",
    "sg:province":"TX",
    "wof:name":"People With Aids Coalition Hou",
    "wof:placetype":"venue"
},
  "geometry": {"coordinates":[-95.388834,29.74546],"type":"Point"}
}