{
  "type": "Feature",
  "properties": {
    "iso:country":"US",
    "sg:address":"7706 Meadow Park Rd",
    "sg:city":"Dallas",
    "sg:classifiers":[
        {
            "category":"Retail",
            "subcategory":"Repair Shop",
            "type":"Services"
        }
    ],
    "sg:phone":"+1 214 891 3761",
    "sg:postcode":"75230",
    "sg:province":"TX",
    "wof:name":"Ticos Cleaning Co",
    "wof:placetype":"venue"
},
  "geometry": {"coordinates":[-96.77413799999999,32.884298],"type":"Point"}
}