{
  "type": "Feature",
  "properties": {
    "iso:country":"US",
    "sg:address":"27906 FM 2978",
    "sg:city":"Magnolia",
    "sg:phone":"+1 281 356 6675",
    "sg:postcode":"77354",
    "sg:province":"TX",
    "sg:tags":[
        "fuel",
        "diesel"
    ],
    "wof:name":"Air Cooled Diesel",
    "wof:placetype":"venue"
},
  "geometry": {"coordinates":[-95.59792,30.166009],"type":"Point"}
}