{
  "type": "Feature",
  "properties": {
    "iso:country":"US",
    "sg:address":"1201 Main St",
    "sg:city":"Vernon",
    "sg:classifiers":[
        {
            "category":"Retail",
            "subcategory":"Repair Shop",
            "type":"Services"
        }
    ],
    "sg:phone":"+1 940 552 2951",
    "sg:postcode":"76384",
    "sg:province":"TX",
    "sg:tags":[
        "dealers-used",
        "automobile",
        "cars-wholesale"
    ],
    "wof:name":"Riggins Brothers Used Cars",
    "wof:placetype":"venue"
},
  "geometry": {"coordinates":[-99.284538,34.158321],"type":"Point"}
}