{
  "type": "Feature",
  "properties": {
    "iso:country":"US",
    "sg:address":"10003 San Luis Trl",
    "sg:city":"Austin",
    "sg:classifiers":[
        {
            "category":"Real Estate",
            "subcategory":"Real Estate Agent",
            "type":"Services"
        }
    ],
    "sg:phone":"+1 512 402 0467",
    "sg:postcode":"78733",
    "sg:province":"TX",
    "wof:name":"Lakehills Real Estate",
    "wof:placetype":"venue"
},
  "geometry": {"coordinates":[-97.862452,30.3489],"type":"Point"}
}