{
  "type": "Feature",
  "properties": {
    "iso:country":"US",
    "sg:address":"9500 W Parmer Ln",
    "sg:city":"Austin",
    "sg:phone":"+1 866 500 3963",
    "sg:postcode":"78717",
    "sg:province":"TX",
    "sg:website":"http://local.ingenio.com/Listings/Details.aspx?NUM=a%3a10243032%3a13%3a4859924%3a14%3a0%3a7",
    "wof:name":"Ventana Oaks",
    "wof:placetype":"venue"
},
  "geometry": {"coordinates":[-97.767014,30.48172],"type":"Point"}
}