{
  "type": "Feature",
  "properties": {
    "iso:country":"US",
    "sg:address":"11739 Wurzbach Rd",
    "sg:city":"San Antonio",
    "sg:classifiers":[
        {
            "category":"Organizations",
            "subcategory":"Professional Association",
            "type":"Services"
        }
    ],
    "sg:phone":"+1 210 492 3425",
    "sg:postcode":"78230",
    "sg:province":"TX",
    "wof:name":"Elm Creek Owners Assn Security",
    "wof:placetype":"venue"
},
  "geometry": {"coordinates":[-98.54414300000001,29.548727],"type":"Point"}
}