{
  "type": "Feature",
  "properties": {
    "iso:country":"US",
    "sg:address":"11401 Elam Rd",
    "sg:city":"Mesquite",
    "sg:classifiers":[
        {
            "category":"Personal",
            "subcategory":"Nail Salon",
            "type":"Services"
        }
    ],
    "sg:phone":"+1 972 913 0558",
    "sg:postcode":"75180",
    "sg:province":"TX",
    "wof:name":"Nice Nails",
    "wof:placetype":"venue"
},
  "geometry": {"coordinates":[-96.631203,32.719501],"type":"Point"}
}