{
  "type": "Feature",
  "properties": {
    "iso:country":"US",
    "sg:address":"1112 S Concho St",
    "sg:city":"Coleman",
    "sg:classifiers":[
        {
            "category":"Building & Trades",
            "subcategory":"Plumbing",
            "type":"Services"
        }
    ],
    "sg:phone":"+1 325 625 2494",
    "sg:postcode":"76834",
    "sg:province":"TX",
    "sg:tags":[
        "plumbing",
        "contractor"
    ],
    "wof:name":"Steven Hinds Plumbing",
    "wof:placetype":"venue"
},
  "geometry": {"coordinates":[-99.424221,31.821848],"type":"Point"}
}