{
  "type": "Feature",
  "properties": {
    "iso:country":"US",
    "sg:address":"4131 Brookport Dr",
    "sg:city":"Dallas",
    "sg:classifiers":[
        {
            "category":"Banks & Credit Unions",
            "subcategory":"Bank",
            "type":"Services"
        }
    ],
    "sg:phone":"+1 214 654 9680",
    "sg:postcode":"75229",
    "sg:province":"TX",
    "sg:tags":[
        "mortgage"
    ],
    "wof:name":"Quorum Mortgage",
    "wof:placetype":"venue"
},
  "geometry": {"coordinates":[-96.839707,32.893636],"type":"Point"}
}