{
  "type": "Feature",
  "properties": {
    "iso:country":"US",
    "sg:address":"6363 Forest Park Ste 400",
    "sg:city":"Dallas",
    "sg:classifiers":[
        {
            "category":"Building & Trades",
            "subcategory":"Construction",
            "type":"Services"
        }
    ],
    "sg:phone":"+1 866 428 9370",
    "sg:postcode":"75235",
    "sg:province":"TX",
    "sg:tags":[
        "contractor"
    ],
    "sg:website":"www.efficientattic.com",
    "wof:name":"Efficient Attic Systems",
    "wof:placetype":"venue"
},
  "geometry": {"coordinates":[-96.84554199999999,32.823948],"type":"Point"}
}