{
  "type": "Feature",
  "properties": {
    "iso:country":"US",
    "sg:address":"2209 Ella Blvd",
    "sg:city":"Houston",
    "sg:classifiers":[
        {
            "category":"Personal",
            "subcategory":"Beauty Salon",
            "type":"Services"
        }
    ],
    "sg:phone":"+1 713 869 5809",
    "sg:postcode":"77008",
    "sg:province":"TX",
    "sg:tags":[
        "shop"
    ],
    "wof:name":"Hair Conductors",
    "wof:placetype":"venue"
},
  "geometry": {"coordinates":[-95.429254,29.805446],"type":"Point"}
}