{
  "type": "Feature",
  "properties": {
    "iso:country":"US",
    "sg:address":"608 S Columbia Dr",
    "sg:city":"West Columbia",
    "sg:classifiers":[
        {
            "category":"Freight",
            "type":"Transportation"
        }
    ],
    "sg:phone":"+1 979 345 3531",
    "sg:postcode":"77486",
    "sg:province":"TX",
    "sg:tags":[
        "commercial",
        "storage"
    ],
    "wof:name":"Ad Self Storage",
    "wof:placetype":"venue"
},
  "geometry": {"coordinates":[-95.654218,29.139799],"type":"Point"}
}