{
  "type": "Feature",
  "properties": {
    "iso:country":"US",
    "sg:address":"505 San Jacinto Blvd",
    "sg:city":"Austin",
    "sg:classifiers":[
        {
            "category":"Banks & Credit Unions",
            "subcategory":"Bank",
            "type":"Services"
        }
    ],
    "sg:phone":"+1 512 476 0550",
    "sg:postcode":"78701",
    "sg:province":"TX",
    "sg:tags":[
        "loan"
    ],
    "wof:name":"Toledo Finance Loan Office",
    "wof:placetype":"venue"
},
  "geometry": {"coordinates":[-97.74031600000001,30.267332],"type":"Point"}
}