{
  "type": "Feature",
  "properties": {
    "iso:country":"US",
    "sg:address":"1820 Broadway St",
    "sg:city":"Houston",
    "sg:classifiers":[
        {
            "category":"Autos & Motor Vehicles",
            "subcategory":"Automobile Sales",
            "type":"Retail Goods"
        }
    ],
    "sg:phone":"+1 713 923 3134",
    "sg:postcode":"77012",
    "sg:province":"TX",
    "sg:tags":[
        "used"
    ],
    "wof:name":"Sergios Used Cars",
    "wof:placetype":"venue"
},
  "geometry": {"coordinates":[-95.278155,29.709183],"type":"Point"}
}