{
  "type": "Feature",
  "properties": {
    "iso:country":"US",
    "sg:address":"7515 E Houston Rd",
    "sg:city":"Houston",
    "sg:classifiers":[
        {
            "category":"Organizations",
            "subcategory":"Religious Organization",
            "type":"Services"
        }
    ],
    "sg:phone":"+1 713 631 7435",
    "sg:postcode":"77028",
    "sg:province":"TX",
    "sg:tags":[
        "church"
    ],
    "wof:name":"East Houston Church Of Christ",
    "wof:placetype":"venue"
},
  "geometry": {"coordinates":[-95.270162,29.831222],"type":"Point"}
}