{
  "type": "Feature",
  "properties": {
    "iso:country":"US",
    "sg:address":"11316 Farmhaven Rd",
    "sg:city":"Austin",
    "sg:classifiers":[
        {
            "category":"Education",
            "subcategory":"School",
            "type":"Public Place"
        }
    ],
    "sg:phone":"+1 512 278 4125",
    "sg:postcode":"78754",
    "sg:province":"TX",
    "sg:website":"www.manorisd.net",
    "wof:name":"Bluebonnet Trail Elementary",
    "wof:placetype":"venue"
},
  "geometry": {"coordinates":[-97.617923,30.350653],"type":"Point"}
}