{
  "type": "Feature",
  "properties": {
    "iso:country":"US",
    "sg:address":"14021 Cresent Dr",
    "sg:city":"Tomball",
    "sg:classifiers":[
        {
            "category":"Health Services",
            "subcategory":"Hospital",
            "type":"Services"
        }
    ],
    "sg:phone":"+1 281 351 7599",
    "sg:postcode":"77375",
    "sg:province":"TX",
    "sg:tags":[
        "mental"
    ],
    "wof:name":"Cadwalder Behavior Clinics",
    "wof:placetype":"venue"
},
  "geometry": {"coordinates":[-95.629986,30.119315],"type":"Point"}
}