{
  "type": "Feature",
  "properties": {
    "iso:country":"US",
    "sg:address":"1011 Hayden Way",
    "sg:city":"Round Rock",
    "sg:classifiers":[
        {
            "category":"Professional",
            "subcategory":"Business Services",
            "type":"Services"
        }
    ],
    "sg:phone":"+1 512 388 0176",
    "sg:postcode":"78664",
    "sg:province":"TX",
    "wof:name":"Bee Jay Enterprises",
    "wof:placetype":"venue"
},
  "geometry": {"coordinates":[-97.672949,30.500952],"type":"Point"}
}