{
  "type": "Feature",
  "properties": {
    "iso:country":"US",
    "sg:address":"820 Wilcrest Dr",
    "sg:city":"Houston",
    "sg:classifiers":[
        {
            "category":"Manufacturing",
            "subcategory":"Jewelry",
            "type":"Manufacturing & Wholesale Goods"
        }
    ],
    "sg:phone":"+1 281 568 2229",
    "sg:postcode":"77042",
    "sg:province":"TX",
    "sg:tags":[
        "precious",
        "metal",
        "mfg"
    ],
    "wof:name":"Thanh Tin Jewelry",
    "wof:placetype":"venue"
},
  "geometry": {"coordinates":[-95.576376,29.757792],"type":"Point"}
}