{
  "type": "Feature",
  "properties": {
    "iso:country":"US",
    "sg:address":"7400 San Pedro Ave",
    "sg:city":"San Antonio",
    "sg:classifiers":[
        {
            "category":"Restaurant",
            "type":"Food & Drink"
        }
    ],
    "sg:phone":"+1 210 344 2561",
    "sg:postcode":"78216",
    "sg:province":"TX",
    "wof:name":"Luby's Cafeteria",
    "wof:placetype":"venue"
},
  "geometry": {"coordinates":[-98.49925399999999,29.518131],"type":"Point"}
}