{
  "type": "Feature",
  "properties": {
    "iso:country":"US",
    "sg:address":"9302 Jaywood Dr",
    "sg:city":"Houston",
    "sg:classifiers":[
        {
            "category":"Retail",
            "subcategory":"Auto Repair",
            "type":"Services"
        }
    ],
    "sg:phone":"+1 281 999 0877",
    "sg:postcode":"77040",
    "sg:province":"TX",
    "sg:tags":[
        "body"
    ],
    "wof:name":"Angeliques Paint & Blast",
    "wof:placetype":"venue"
},
  "geometry": {"coordinates":[-95.502223,29.878944],"type":"Point"}
}