{
  "type": "Feature",
  "properties": {
    "iso:country":"US",
    "sg:address":"2728 Osborn Ln",
    "sg:city":"Bryan",
    "sg:classifiers":[
        {
            "category":"Real Estate",
            "subcategory":"Real Estate Operator",
            "type":"Services"
        }
    ],
    "sg:phone":"+1 979 774 5222",
    "sg:postcode":"77803",
    "sg:province":"TX",
    "sg:tags":[
        "apartment"
    ],
    "wof:name":"Midtowne Apartments",
    "wof:placetype":"venue"
},
  "geometry": {"coordinates":[-96.35008999999999,30.67885],"type":"Point"}
}