{
  "type": "Feature",
  "properties": {
    "iso:country":"US",
    "sg:address":"5017 Erik Ave",
    "sg:city":"Amarillo",
    "sg:classifiers":[
        {
            "category":"Building & Trades",
            "subcategory":"Construction",
            "type":"Services"
        }
    ],
    "sg:phone":"+1 806 677 7378",
    "sg:postcode":"79106",
    "sg:province":"TX",
    "sg:tags":[
        "handyman"
    ],
    "wof:name":"Bills Repair",
    "wof:placetype":"venue"
},
  "geometry": {"coordinates":[-101.89176399999999,35.188296],"type":"Point"}
}