{
  "type": "Feature",
  "properties": {
    "iso:country":"US",
    "sg:address":"103 E Viser St",
    "sg:city":"Madisonville",
    "sg:classifiers":[
        {
            "category":"Social Services",
            "subcategory":"Adult Care",
            "type":"Services"
        }
    ],
    "sg:phone":"+1 936 348 9252",
    "sg:postcode":"77864",
    "sg:province":"TX",
    "sg:tags":[
        "home",
        "group"
    ],
    "wof:name":"Martin Luther Homes",
    "wof:placetype":"venue"
},
  "geometry": {"coordinates":[-95.916493,30.962385],"type":"Point"}
}