{
  "type": "Feature",
  "properties": {
    "iso:country":"US",
    "sg:address":"10581 Co Rd 2300",
    "sg:city":"Quinlan",
    "sg:classifiers":[
        {
            "category":"Wholesale",
            "subcategory":"Durable Goods & Equipment",
            "type":"Manufacturing & Wholesale Goods"
        }
    ],
    "sg:phone":"+1 903 356 3775",
    "sg:postcode":"75474",
    "sg:province":"TX",
    "sg:tags":[
        "representative",
        "manufacturer"
    ],
    "wof:name":"Hennen & Assoc",
    "wof:placetype":"venue"
},
  "geometry": {"coordinates":[-96.170153,32.888541],"type":"Point"}
}