{
  "type": "Feature",
  "properties": {
    "iso:country":"US",
    "sg:address":"10910 Dennis Rd",
    "sg:city":"Dallas",
    "sg:classifiers":[
        {
            "category":"Retail",
            "subcategory":"Auto Repair",
            "type":"Services"
        }
    ],
    "sg:phone":"+1 972 247 4966",
    "sg:postcode":"75229",
    "sg:province":"TX",
    "wof:name":"One Stop Automotive Inc",
    "wof:placetype":"venue"
},
  "geometry": {"coordinates":[-96.88130200000001,32.897301],"type":"Point"}
}