{
  "type": "Feature",
  "properties": {
    "iso:country":"US",
    "sg:address":"2091 Mc Gee Ln",
    "sg:city":"Lewisville",
    "sg:classifiers":[
        {
            "category":"Marine",
            "type":"Transportation"
        }
    ],
    "sg:phone":"+1 972 317 3988",
    "sg:postcode":"75077",
    "sg:province":"TX",
    "sg:tags":[
        "water",
        "boat",
        "transporting",
        "transport"
    ],
    "wof:name":"Landlock Marine Transportation",
    "wof:placetype":"venue"
},
  "geometry": {"coordinates":[-97.027103,33.077945],"type":"Point"}
}