{
  "type": "Feature",
  "properties": {
    "iso:country":"US",
    "sg:address":"1513 5th Ave",
    "sg:city":"Canyon",
    "sg:classifiers":[
        {
            "category":"Government",
            "subcategory":"Office",
            "type":"Public Place"
        }
    ],
    "sg:phone":"+1 806 655 2041",
    "sg:postcode":"79015",
    "sg:province":"TX",
    "sg:tags":[
        "county",
        "safety",
        "order"
    ],
    "wof:name":"Public Safety Dept",
    "wof:placetype":"venue"
},
  "geometry": {"coordinates":[-101.928684,34.978924],"type":"Point"}
}