{
  "type": "Feature",
  "properties": {
    "iso:country":"US",
    "sg:address":"331 Monticello Dr",
    "sg:city":"Springtown",
    "sg:classifiers":[
        {
            "category":"Health Services",
            "subcategory":"Chiropractor",
            "type":"Services"
        }
    ],
    "sg:phone":"+1 817 221 2205",
    "sg:postcode":"76082",
    "sg:province":"TX",
    "sg:tags":[
        "chiropractic"
    ],
    "wof:name":"George Calvin Cearley Jr",
    "wof:placetype":"venue"
},
  "geometry": {"coordinates":[-97.634342,32.940899],"type":"Point"}
}