{
  "type": "Feature",
  "properties": {
    "iso:country":"US",
    "sg:address":"5025 NE 28th St",
    "sg:city":"Fort Worth",
    "sg:classifiers":[
        {
            "category":"Professional",
            "type":"Services"
        }
    ],
    "sg:phone":"+1 682 647 1003",
    "sg:postcode":"76117",
    "sg:province":"TX",
    "wof:name":"Liquidations Unlimited",
    "wof:placetype":"venue"
},
  "geometry": {"coordinates":[-97.275042,32.795028],"type":"Point"}
}