{
  "type": "Feature",
  "properties": {
    "iso:country":"US",
    "sg:address":"1713 Boca Chica Blvd",
    "sg:city":"Brownsville",
    "sg:classifiers":[
        {
            "category":"Professional",
            "subcategory":"Lawyer & Legal Services",
            "type":"Services"
        }
    ],
    "sg:phone":"+1 956 544 6571",
    "sg:postcode":"78520",
    "sg:province":"TX",
    "sg:tags":[
        "attorney"
    ],
    "wof:name":"Magallanes & Hinojosa",
    "wof:placetype":"venue"
},
  "geometry": {"coordinates":[-97.49232499999999,25.922382],"type":"Point"}
}