{
  "type": "Feature",
  "properties": {
    "iso:country":"US",
    "sg:address":"5618 Rowlett Rd",
    "sg:city":"Rowlett",
    "sg:classifiers":[
        {
            "category":"Building & Trades",
            "subcategory":"Construction",
            "type":"Services"
        }
    ],
    "sg:phone":"+1 972 463 2071",
    "sg:postcode":"75089",
    "sg:province":"TX",
    "sg:tags":[
        "repairing",
        "remodeling",
        "contractor"
    ],
    "wof:name":"Gelco Specialists Inc",
    "wof:placetype":"venue"
},
  "geometry": {"coordinates":[-96.56958299999999,32.911891],"type":"Point"}
}