{
  "type": "Feature",
  "properties": {
    "iso:country":"US",
    "sg:address":"828 Lakeview Blvd",
    "sg:city":"New Braunfels",
    "sg:classifiers":[
        {
            "category":"Building & Trades",
            "subcategory":"Plumbing",
            "type":"Services"
        }
    ],
    "sg:phone":"+1 830 606 4323",
    "sg:postcode":"78130",
    "sg:province":"TX",
    "sg:tags":[
        "fire",
        "installation",
        "sprinkler",
        "system"
    ],
    "wof:name":"Standard Automatic Fire Entps",
    "wof:placetype":"venue"
},
  "geometry": {"coordinates":[-98.122067,29.719822],"type":"Point"}
}