{
  "type": "Feature",
  "properties": {
    "iso:country":"US",
    "sg:address":"10610 American Dr",
    "sg:city":"Amarillo",
    "sg:classifiers":[
        {
            "category":"Freight",
            "type":"Transportation"
        }
    ],
    "sg:phone":"+1 806 335 1770",
    "sg:postcode":"79111",
    "sg:province":"TX",
    "sg:tags":[
        "operator",
        "local",
        "trucking"
    ],
    "wof:name":"Telesis Express Inc",
    "wof:placetype":"venue"
},
  "geometry": {"coordinates":[-101.71301200000001,35.213296],"type":"Point"}
}