{
  "type": "Feature",
  "properties": {
    "iso:country":"US",
    "sg:address":"3800 Sandshell Dr",
    "sg:city":"Fort Worth",
    "sg:classifiers":[
        {
            "category":"Professional",
            "subcategory":"Engineering",
            "type":"Services"
        }
    ],
    "sg:phone":"+1 817 232 0244",
    "sg:postcode":"76137",
    "sg:province":"TX",
    "sg:tags":[
        "engineer"
    ],
    "wof:name":"Wendy Lopez & Assoc Inc",
    "wof:placetype":"venue"
},
  "geometry": {"coordinates":[-97.301177,32.842174],"type":"Point"}
}