{
  "type": "Feature",
  "properties": {
    "iso:country":"US",
    "sg:address":"1710 Eagle Meadow",
    "sg:city":"San Antonio",
    "sg:classifiers":[
        {
            "category":"Manufacturing",
            "subcategory":"Printing",
            "type":"Manufacturing & Wholesale Goods"
        }
    ],
    "sg:phone":"+1 210 764 1367",
    "sg:postcode":"78248",
    "sg:province":"TX",
    "sg:tags":[
        "publishing"
    ],
    "wof:name":"Darco Publishing Co",
    "wof:placetype":"venue"
},
  "geometry": {"coordinates":[-98.52103200000001,29.588779],"type":"Point"}
}