{
  "type": "Feature",
  "properties": {
    "iso:country":"US",
    "sg:address":"610 Elm St",
    "sg:city":"Mc Kinney",
    "sg:classifiers":[
        {
            "category":"Wholesale",
            "subcategory":"Construction Materials",
            "type":"Manufacturing & Wholesale Goods"
        }
    ],
    "sg:phone":"+1 972 562 1677",
    "sg:postcode":"75069",
    "sg:province":"TX",
    "wof:name":"Triangle Pacific Cabinet",
    "wof:placetype":"venue"
},
  "geometry": {"coordinates":[-96.612155,33.185103],"type":"Point"}
}