{
  "type": "Feature",
  "properties": {
    "iso:country":"US",
    "sg:address":"4900 McCarty Blvd",
    "sg:city":"Amarillo",
    "sg:classifiers":[
        {
            "category":"Retail",
            "subcategory":"Auto Repair",
            "type":"Services"
        }
    ],
    "sg:phone":"+1 806 463 7879",
    "sg:postcode":"79110",
    "sg:province":"TX",
    "sg:tags":[
        "repairing",
        "automobile"
    ],
    "wof:name":"Drury Automotive",
    "wof:placetype":"venue"
},
  "geometry": {"coordinates":[-101.872601,35.160124],"type":"Point"}
}