{
  "type": "Feature",
  "properties": {
    "iso:country":"US",
    "sg:address":"12407 N Mo Pac Expressway Suite 575",
    "sg:city":"Austin",
    "sg:classifiers":[
        {
            "category":"Health Services",
            "subcategory":"Chiropractor",
            "type":"Services"
        }
    ],
    "sg:phone":"+1 512 821 2221",
    "sg:postcode":"78758",
    "sg:province":"TX",
    "wof:name":"Dr Joshua Adam West",
    "wof:placetype":"venue"
},
  "geometry": {"coordinates":[-97.70716299999999,30.385437],"type":"Point"}
}