{
  "type": "Feature",
  "properties": {
    "iso:country":"US",
    "sg:address":"1002 Glouchester Ln",
    "sg:city":"Houston",
    "sg:classifiers":[
        {
            "category":"Manufacturing",
            "subcategory":"Metals",
            "type":"Manufacturing & Wholesale Goods"
        }
    ],
    "sg:phone":"+1 281 443 7471",
    "sg:postcode":"77073",
    "sg:province":"TX",
    "sg:tags":[
        "industrial",
        "container"
    ],
    "wof:name":"BWAY Corp",
    "wof:placetype":"venue"
},
  "geometry": {"coordinates":[-95.414689,30.031814],"type":"Point"}
}