{
  "type": "Feature",
  "properties": {
    "iso:country":"US",
    "sg:address":"114 E Saner Ave",
    "sg:city":"Dallas",
    "sg:classifiers":[
        {
            "category":"Wholesale",
            "subcategory":"Groceries",
            "type":"Manufacturing & Wholesale Goods"
        }
    ],
    "sg:phone":"+1 214 948 2992",
    "sg:postcode":"75216",
    "sg:province":"TX",
    "sg:tags":[
        "tortilla"
    ],
    "wof:name":"Taqueria Banda's",
    "wof:placetype":"venue"
},
  "geometry": {"coordinates":[-96.821899,32.713083],"type":"Point"}
}