{
  "type": "Feature",
  "properties": {
    "iso:country":"US",
    "sg:address":"3012 University Ave",
    "sg:city":"Austin",
    "sg:classifiers":[
        {
            "category":"Organizations",
            "subcategory":"Religious Organization",
            "type":"Services"
        }
    ],
    "sg:phone":"+1 512 708 0151",
    "sg:postcode":"78705",
    "sg:province":"TX",
    "wof:name":"King David School Of Austin",
    "wof:placetype":"venue"
},
  "geometry": {"coordinates":[-97.73707400000001,30.295112],"type":"Point"}
}