{
  "type": "Feature",
  "properties": {
    "iso:country":"US",
    "sg:address":"1521 Rice Rd",
    "sg:city":"Tyler",
    "sg:classifiers":[
        {
            "category":"Real Estate",
            "subcategory":"Real Estate Operator",
            "type":"Services"
        }
    ],
    "sg:phone":"+1 903 561 6000",
    "sg:postcode":"75703",
    "sg:province":"TX",
    "sg:tags":[
        "condominium"
    ],
    "wof:name":"Hamilton West Condominiums",
    "wof:placetype":"venue"
},
  "geometry": {"coordinates":[-95.32333800000001,32.291834],"type":"Point"}
}