{
  "type": "Feature",
  "properties": {
    "iso:country":"US",
    "sg:address":"10106 Technology Blvd W Apt 918",
    "sg:city":"Dallas",
    "sg:classifiers":[
        {
            "category":"Recreation",
            "subcategory":"Arcade",
            "type":"Entertainment"
        }
    ],
    "sg:phone":"+1 214 459 0394",
    "sg:postcode":"75220",
    "sg:province":"TX",
    "sg:tags":[
        "game",
        "video"
    ],
    "wof:name":"Cruse Amusements",
    "wof:placetype":"venue"
},
  "geometry": {"coordinates":[-96.90145200000001,32.85816],"type":"Point"}
}