{
  "type": "Feature",
  "properties": {
    "iso:country":"US",
    "sg:address":"101 N Interurban St",
    "sg:city":"Richardson",
    "sg:classifiers":[
        {
            "category":"Retail",
            "subcategory":"Auto Repair",
            "type":"Services"
        }
    ],
    "sg:phone":"+1 972 437 1096",
    "sg:postcode":"75081",
    "sg:province":"TX",
    "sg:website":"www.allstatetransmissionsinc.com",
    "wof:name":"Allstate Transmissions",
    "wof:placetype":"venue"
},
  "geometry": {"coordinates":[-96.732315,32.95003],"type":"Point"}
}