{
  "type": "Feature",
  "properties": {
    "iso:country":"US",
    "sg:address":"9357 Forest Ln",
    "sg:city":"Dallas",
    "sg:classifiers":[
        {
            "category":"Personal",
            "subcategory":"Barber",
            "type":"Services"
        }
    ],
    "sg:phone":"+1 214 360 9570",
    "sg:postcode":"75243",
    "sg:province":"TX",
    "sg:tags":[
        "school"
    ],
    "sg:website":"www.dallasbarberandstylistcollege.com",
    "wof:name":"Dallas Barber & Stylist Clg",
    "wof:placetype":"venue"
},
  "geometry": {"coordinates":[-96.735784,32.909307],"type":"Point"}
}