{
  "type": "Feature",
  "properties": {
    "iso:country":"US",
    "sg:address":"8822 W Valley Palms Dr",
    "sg:city":"Spring",
    "sg:classifiers":[
        {
            "category":"Professional",
            "subcategory":"Computer Services",
            "type":"Services"
        }
    ],
    "sg:phone":"+1 281 379 7076",
    "sg:postcode":"77379",
    "sg:province":"TX",
    "sg:tags":[
        "related"
    ],
    "wof:name":"Icue Systems Inc",
    "wof:placetype":"venue"
},
  "geometry": {"coordinates":[-95.554528,30.022922],"type":"Point"}
}