{
  "type": "Feature",
  "properties": {
    "iso:country":"US",
    "sg:address":"773 E Torrey St",
    "sg:city":"New Braunfels",
    "sg:classifiers":[
        {
            "category":"Autos & Motor Vehicles",
            "subcategory":"Auto Supplies",
            "type":"Retail Goods"
        }
    ],
    "sg:phone":"+1 830 629 2429",
    "sg:postcode":"78130",
    "sg:province":"TX",
    "sg:tags":[
        "repair",
        "r",
        "general",
        "automotive"
    ],
    "wof:name":"D J Automotive Repair",
    "wof:placetype":"venue"
},
  "geometry": {"coordinates":[-98.120484,29.720728],"type":"Point"}
}