{
  "type": "Feature",
  "properties": {
    "iso:country":"US",
    "sg:address":"8550 Huebner Rd",
    "sg:city":"San Antonio",
    "sg:classifiers":[
        {
            "category":"Social Services",
            "type":"Services"
        }
    ],
    "sg:phone":"+1 210 568 8500",
    "sg:postcode":"78240",
    "sg:province":"TX",
    "sg:tags":[
        "youth",
        "organization",
        "center"
    ],
    "wof:name":"Texas Adolescent Treatment Ctr",
    "wof:placetype":"venue"
},
  "geometry": {"coordinates":[-98.604275,29.518981],"type":"Point"}
}