{
  "type": "Feature",
  "properties": {
    "iso:country":"US",
    "sg:address":"2025 S Belt Line Rd",
    "sg:city":"Dallas",
    "sg:classifiers":[
        {
            "category":"Building & Trades",
            "subcategory":"Electrical",
            "type":"Services"
        }
    ],
    "sg:phone":"+1 972 389 7925",
    "sg:postcode":"75253",
    "sg:province":"TX",
    "sg:tags":[
        "electrician"
    ],
    "wof:name":"Qualified Contractors, Inc.",
    "wof:placetype":"venue"
},
  "geometry": {"coordinates":[-96.604625,32.674444],"type":"Point"}
}