{
  "type": "Feature",
  "properties": {
    "iso:country":"US",
    "sg:address":"6715 Bandera Rd",
    "sg:city":"San Antonio",
    "sg:classifiers":[
        {
            "category":"Government",
            "subcategory":"Court House",
            "type":"Public Place"
        }
    ],
    "sg:phone":"+1 210 684 9665",
    "sg:postcode":"78238",
    "sg:province":"TX",
    "sg:tags":[
        "state",
        "system"
    ],
    "wof:name":"Bexar County Justice of The Pe",
    "wof:placetype":"venue"
},
  "geometry": {"coordinates":[-98.61975200000001,29.496333],"type":"Point"}
}