{
  "type": "Feature",
  "properties": {
    "iso:country":"US",
    "sg:address":"11923 Barrett Brae Dr",
    "sg:city":"Houston",
    "sg:classifiers":[
        {
            "category":"Restaurant",
            "type":"Food & Drink"
        }
    ],
    "sg:phone":"+1 713 541 0238",
    "sg:postcode":"77072",
    "sg:province":"TX",
    "sg:tags":[
        "eating"
    ],
    "wof:name":"Lupita Sales",
    "wof:placetype":"venue"
},
  "geometry": {"coordinates":[-95.59105599999999,29.686404],"type":"Point"}
}