{
  "type": "Feature",
  "properties": {
    "iso:country":"US",
    "sg:address":"1302 W Harris Ave",
    "sg:city":"Pasadena",
    "sg:classifiers":[
        {
            "category":"Organizations",
            "subcategory":"Religious Organization",
            "type":"Services"
        }
    ],
    "sg:phone":"+1 713 920 0114",
    "sg:postcode":"77506",
    "sg:province":"TX",
    "sg:tags":[
        "church"
    ],
    "wof:name":"Centro Cristiano Shalom",
    "wof:placetype":"venue"
},
  "geometry": {"coordinates":[-95.228033,29.697985],"type":"Point"}
}