{
  "type": "Feature",
  "properties": {
    "iso:country":"US",
    "sg:address":"3555 Pinnacle Dr",
    "sg:city":"San Antonio",
    "sg:classifiers":[
        {
            "category":"Travel",
            "subcategory":"Hotels & Motels",
            "type":"Entertainment"
        }
    ],
    "sg:phone":"+1 210 481 9312",
    "sg:postcode":"78261",
    "sg:province":"TX",
    "wof:name":"Cibolo Canyon Resort",
    "wof:placetype":"venue"
},
  "geometry": {"coordinates":[-98.426841,29.660259],"type":"Point"}
}