{
  "type": "Feature",
  "properties": {
    "iso:country":"US",
    "sg:address":"7925 Cook Rd",
    "sg:city":"Houston",
    "sg:classifiers":[
        {
            "category":"Retail",
            "subcategory":"Animal Services",
            "type":"Services"
        }
    ],
    "sg:phone":"+1 281 879 9821",
    "sg:postcode":"77072",
    "sg:province":"TX",
    "wof:name":"Houston Pet Cemetery",
    "wof:placetype":"venue"
},
  "geometry": {"coordinates":[-95.59585800000001,29.691273],"type":"Point"}
}