{
  "type": "Feature",
  "properties": {
    "iso:country":"US",
    "sg:address":"6207 Southwest Fwy",
    "sg:city":"Houston",
    "sg:classifiers":[
        {
            "category":"Health Services",
            "subcategory":"Doctor",
            "type":"Services"
        }
    ],
    "sg:phone":"+1 713 655 1432",
    "sg:postcode":"77074",
    "sg:province":"TX",
    "sg:tags":[
        "physician",
        "surgeon"
    ],
    "wof:name":"Lonestar Orthopedics",
    "wof:placetype":"venue"
},
  "geometry": {"coordinates":[-95.491519,29.72308],"type":"Point"}
}