{
  "type": "Feature",
  "properties": {
    "iso:country":"US",
    "sg:address":"216 Wyatt St",
    "sg:city":"Waxahachie",
    "sg:classifiers":[
        {
            "category":"Place Of Worship",
            "subcategory":"Church",
            "type":"Public Place"
        },
        {
            "category":"Place Of Worship",
            "type":"Public Place"
        }
    ],
    "sg:phone":"+1 972 937 6724",
    "sg:postcode":"75165",
    "sg:province":"TX",
    "sg:tags":[
        "churches-seventh-day",
        "adventist",
        "christian",
        "churches-advent"
    ],
    "sg:website":"http://www.adventist.org",
    "wof:name":"Wyatt Street Seventh Day Adventist Church",
    "wof:placetype":"venue"
},
  "geometry": {"coordinates":[-96.840174,32.384847],"type":"Point"}
}