{
  "type": "Feature",
  "properties": {
    "iso:country":"US",
    "sg:address":"10901 Mist Ln",
    "sg:city":"Houston",
    "sg:classifiers":[
        {
            "category":"Shopping",
            "subcategory":"Gifts & Souvenirs",
            "type":"Retail Goods"
        }
    ],
    "sg:phone":"+1 281 890 2097",
    "sg:postcode":"77070",
    "sg:province":"TX",
    "wof:name":"German House of Gifts",
    "wof:placetype":"venue"
},
  "geometry": {"coordinates":[-95.58453,29.959192],"type":"Point"}
}