{
  "type": "Feature",
  "properties": {
    "iso:country":"US",
    "sg:address":"11420 Fm 2244",
    "sg:city":"Austin",
    "sg:classifiers":[
        {
            "category":"Health Services",
            "subcategory":"Doctor",
            "type":"Services"
        }
    ],
    "sg:phone":"+1 512 472 4714",
    "sg:postcode":"78738",
    "sg:province":"TX",
    "sg:tags":[
        "practice",
        "family"
    ],
    "wof:name":"Caterbone Philip W DO",
    "wof:placetype":"venue"
},
  "geometry": {"coordinates":[-97.894088,30.307765],"type":"Point"}
}