{
  "type": "Feature",
  "properties": {
    "iso:country":"US",
    "sg:address":"863 Savage Ln",
    "sg:city":"Corpus Christi",
    "sg:classifiers":[
        {
            "category":"Freight",
            "type":"Transportation"
        }
    ],
    "sg:phone":"+1 361 888 7777",
    "sg:postcode":"78408",
    "sg:province":"TX",
    "sg:tags":[
        "commercial",
        "storage"
    ],
    "wof:name":"Safeguard Mini-Storage",
    "wof:placetype":"venue"
},
  "geometry": {"coordinates":[-97.449789,27.800573],"type":"Point"}
}