{
  "type": "Feature",
  "properties": {
    "iso:country":"US",
    "sg:address":"713 Rio Grande Ct",
    "sg:city":"Mission",
    "sg:classifiers":[
        {
            "category":"Professional",
            "subcategory":"Business Services",
            "type":"Services"
        }
    ],
    "sg:phone":"+1 956 583 5448",
    "sg:postcode":"78572",
    "sg:province":"TX",
    "wof:name":"Stephanie Kinzelmansala",
    "wof:placetype":"venue"
},
  "geometry": {"coordinates":[-98.302162,26.183291],"type":"Point"}
}