{
  "type": "Feature",
  "properties": {
    "iso:country":"US",
    "sg:address":"1203 Texas Blvd",
    "sg:city":"Texarkana",
    "sg:classifiers":[
        {
            "category":"Retail",
            "subcategory":"Auto Repair",
            "type":"Services"
        }
    ],
    "sg:phone":"+1 903 794 5252",
    "sg:postcode":"75501",
    "sg:province":"TX",
    "sg:tags":[
        "exhaust"
    ],
    "wof:name":"Boos Mufflers",
    "wof:placetype":"venue"
},
  "geometry": {"coordinates":[-94.051248,33.430464],"type":"Point"}
}