{
  "type": "Feature",
  "properties": {
    "iso:country":"US",
    "sg:address":"206 E 8th St",
    "sg:city":"Fort Worth",
    "sg:classifiers":[
        {
            "category":"Professional",
            "type":"Services"
        }
    ],
    "sg:phone":"+1 817 877 4475",
    "sg:postcode":"76102",
    "sg:province":"TX",
    "sg:tags":[
        "establishment"
    ],
    "wof:name":"Enrisk",
    "wof:placetype":"venue"
},
  "geometry": {"coordinates":[-97.327883,32.752704],"type":"Point"}
}