{
  "type": "Feature",
  "properties": {
    "iso:country":"US",
    "sg:address":"612 Berkley Rd",
    "sg:city":"Laredo",
    "sg:classifiers":[
        {
            "category":"Professional",
            "type":"Services"
        }
    ],
    "sg:phone":"+1 956 723 2253",
    "sg:postcode":"78045",
    "sg:province":"TX",
    "wof:name":"Roel Gonyaley",
    "wof:placetype":"venue"
},
  "geometry": {"coordinates":[-99.48148,27.572798],"type":"Point"}
}