{
  "type": "Feature",
  "properties": {
    "iso:country":"US",
    "sg:address":"10311 Paintbrush Ln",
    "sg:city":"Sugar Land",
    "sg:classifiers":[
        {
            "category":"Wholesale",
            "subcategory":"Vending Machines",
            "type":"Manufacturing & Wholesale Goods"
        }
    ],
    "sg:phone":"+1 281 494 4227",
    "sg:postcode":"77478",
    "sg:province":"TX",
    "sg:tags":[
        "operator"
    ],
    "wof:name":"La Monas Vending",
    "wof:placetype":"venue"
},
  "geometry": {"coordinates":[-95.638926,29.666299],"type":"Point"}
}