{
  "type": "Feature",
  "properties": {
    "iso:country":"US",
    "sg:address":"5175 Westheimer Rd",
    "sg:city":"Houston",
    "sg:classifiers":[
        {
            "category":"Shopping",
            "subcategory":"Gifts & Souvenirs",
            "type":"Retail Goods"
        }
    ],
    "sg:phone":"+1 713 627 0830",
    "sg:postcode":"77056",
    "sg:province":"TX",
    "sg:tags":[
        "shop"
    ],
    "wof:name":"Element",
    "wof:placetype":"venue"
},
  "geometry": {"coordinates":[-95.464159,29.740613],"type":"Point"}
}