{
  "type": "Feature",
  "properties": {
    "iso:country":"US",
    "sg:address":"111 Magnolia St",
    "sg:city":"League City",
    "sg:classifiers":[
        {
            "category":"Personal",
            "type":"Services"
        },
        {
            "category":"Personal",
            "subcategory":"Beauty Salon",
            "type":"Services"
        }
    ],
    "sg:phone":"+1 281 557 1001",
    "sg:postcode":"77573",
    "sg:province":"TX",
    "wof:name":"Ultra Tans & Waxing Salon Plus",
    "wof:placetype":"venue"
},
  "geometry": {"coordinates":[-95.09334200000001,29.507883],"type":"Point"}
}