{
  "type": "Feature",
  "properties": {
    "iso:country":"US",
    "sg:address":"101 N Hwy 146",
    "sg:city":"Baytown",
    "sg:classifiers":[
        {
            "category":"Building & Trades",
            "subcategory":"Plumbing",
            "type":"Services"
        }
    ],
    "sg:phone":"+1 713 473 8881",
    "sg:postcode":"77520",
    "sg:province":"TX",
    "sg:tags":[
        "boiler",
        "cleaning"
    ],
    "sg:website":"www.furnaceandtube.com",
    "wof:name":"Furnace & Tube Svc",
    "wof:placetype":"venue"
},
  "geometry": {"coordinates":[-94.916618,29.77027],"type":"Point"}
}