{
  "type": "Feature",
  "properties": {
    "iso:country":"US",
    "sg:address":"2611 Jacksboro Hwy",
    "sg:city":"Fort Worth",
    "sg:classifiers":[
        {
            "category":"Real Estate",
            "subcategory":"Real Estate Operator",
            "type":"Services"
        }
    ],
    "sg:phone":"+1 817 626 5517",
    "sg:postcode":"76114",
    "sg:province":"TX",
    "sg:tags":[
        "building",
        "nonresidential"
    ],
    "wof:name":"M3 Properties",
    "wof:placetype":"venue"
},
  "geometry": {"coordinates":[-97.38745400000001,32.788796],"type":"Point"}
}