{
  "type": "Feature",
  "properties": {
    "iso:country":"US",
    "sg:address":"187 Giant Cedar Trl",
    "sg:city":"Whitney",
    "sg:classifiers":[
        {
            "category":"Real Estate",
            "subcategory":"Developer",
            "type":"Services"
        }
    ],
    "sg:phone":"+1 254 694 6188",
    "sg:postcode":"76692",
    "sg:province":"TX",
    "wof:name":"Vista Grande Development",
    "wof:placetype":"venue"
},
  "geometry": {"coordinates":[-97.38663,31.961571],"type":"Point"}
}