{
  "type": "Feature",
  "properties": {
    "iso:country":"US",
    "sg:address":"669 Co Rd 21",
    "sg:city":"Muleshoe",
    "sg:phone":"+1 806 965 2619",
    "sg:postcode":"79347",
    "sg:province":"TX",
    "sg:tags":[
        "farm",
        "cotton"
    ],
    "wof:name":"Lloyd Bradshaw",
    "wof:placetype":"venue"
},
  "geometry": {"coordinates":[-102.681375,34.392597],"type":"Point"}
}