{
  "type": "Feature",
  "properties": {
    "iso:country":"US",
    "sg:address":"1001 Moy St",
    "sg:city":"Houston",
    "sg:classifiers":[
        {
            "category":"Food & Beverages",
            "subcategory":"Groceries & Convenience Stores",
            "type":"Retail Goods"
        }
    ],
    "sg:phone":"+1 713 864 5317",
    "sg:postcode":"77007",
    "sg:province":"TX",
    "sg:tags":[
        "grocer"
    ],
    "wof:name":"D F Food Store",
    "wof:placetype":"venue"
},
  "geometry": {"coordinates":[-95.414497,29.7707],"type":"Point"}
}