{
  "type": "Feature",
  "properties": {
    "iso:country":"US",
    "sg:address":"12586 FM 853",
    "sg:city":"San Angelo",
    "sg:classifiers":[
        {
            "category":"Local Transit",
            "type":"Transportation"
        }
    ],
    "sg:phone":"+1 325 949 6108",
    "sg:postcode":"76901",
    "sg:province":"TX",
    "sg:tags":[
        "passenger"
    ],
    "wof:name":"Rentabuggy",
    "wof:placetype":"venue"
},
  "geometry": {"coordinates":[-100.626115,31.439656],"type":"Point"}
}