{
  "type": "Feature",
  "properties": {
    "iso:country":"US",
    "sg:address":"110 N Montclair Ave",
    "sg:city":"Dallas",
    "sg:classifiers":[
        {
            "category":"Personal",
            "subcategory":"Beauty Salon",
            "type":"Services"
        }
    ],
    "sg:phone":"+1 214 460 2105",
    "sg:postcode":"75208",
    "sg:province":"TX",
    "sg:tags":[
        "shop"
    ],
    "wof:name":"Flores Studio & Assoc",
    "wof:placetype":"venue"
},
  "geometry": {"coordinates":[-96.84648,32.746318],"type":"Point"}
}