{
  "type": "Feature",
  "properties": {
    "iso:country":"US",
    "sg:address":"14041 Chrisman Rd",
    "sg:city":"Houston",
    "sg:classifiers":[
        {
            "category":"Building & Trades",
            "subcategory":"Construction",
            "type":"Services"
        }
    ],
    "sg:phone":"+1 281 449 7882",
    "sg:postcode":"77039",
    "sg:province":"TX",
    "sg:tags":[
        "roofing",
        "contractor"
    ],
    "wof:name":"Excalibur Roofing",
    "wof:placetype":"venue"
},
  "geometry": {"coordinates":[-95.363652,29.920016],"type":"Point"}
}