{
  "type": "Feature",
  "properties": {
    "iso:country":"US",
    "sg:address":"1501 N Dallas Ave",
    "sg:city":"Lamesa",
    "sg:classifiers":[
        {
            "category":"Wholesale",
            "subcategory":"Meat",
            "type":"Manufacturing & Wholesale Goods"
        }
    ],
    "sg:phone":"+1 806 872 3436",
    "sg:postcode":"79331",
    "sg:province":"TX",
    "sg:tags":[
        "packer"
    ],
    "wof:name":"Drennan Meat Co",
    "wof:placetype":"venue"
},
  "geometry": {"coordinates":[-101.951921,32.746505],"type":"Point"}
}