{
  "type": "Feature",
  "properties": {
    "iso:country":"US",
    "sg:address":"305 E Maxan St",
    "sg:city":"Port Isabel",
    "sg:classifiers":[
        {
            "category":"Government",
            "subcategory":"Office",
            "type":"Public Place"
        }
    ],
    "sg:phone":"+1 956 943 2682",
    "sg:postcode":"78578",
    "sg:province":"TX",
    "sg:tags":[
        "executive"
    ],
    "wof:name":"City of Port Isabel",
    "wof:placetype":"venue"
},
  "geometry": {"coordinates":[-97.208068,26.077798],"type":"Point"}
}