{
  "type": "Feature",
  "properties": {
    "iso:country":"US",
    "sg:address":"2111 Pasadena Blvd",
    "sg:city":"Pasadena",
    "sg:classifiers":[
        {
            "category":"Health Services",
            "subcategory":"Hospital",
            "type":"Services"
        }
    ],
    "sg:phone":"+1 713 473 3177",
    "sg:postcode":"77502",
    "sg:province":"TX",
    "sg:tags":[
        "specialty"
    ],
    "wof:name":"Narcotics Anonymous",
    "wof:placetype":"venue"
},
  "geometry": {"coordinates":[-95.183646,29.682196],"type":"Point"}
}