{
  "type": "Feature",
  "properties": {
    "iso:country":"US",
    "sg:address":"15333 John F Kennedy Blvd",
    "sg:city":"Houston",
    "sg:classifiers":[
        {
            "category":"Wholesale",
            "subcategory":"Computers",
            "type":"Manufacturing & Wholesale Goods"
        },
        {
            "category":"Professional",
            "subcategory":"Computer Services",
            "type":"Services"
        }
    ],
    "sg:phone":"+1 281 219 1234",
    "sg:postcode":"77032",
    "sg:province":"TX",
    "sg:tags":[
        "consultant",
        "designer",
        "software"
    ],
    "wof:name":"M D C Technology Inc",
    "wof:placetype":"venue"
},
  "geometry": {"coordinates":[-95.33179800000001,29.939831],"type":"Point"}
}