{
  "type": "Feature",
  "properties": {
    "iso:country":"US",
    "sg:address":"1151 W Walnut Hill Ln",
    "sg:city":"Irving",
    "sg:classifiers":[
        {
            "category":"Cinema",
            "subcategory":"Movie Rental",
            "type":"Entertainment"
        }
    ],
    "sg:phone":"+1 972 550 8484",
    "sg:postcode":"75038",
    "sg:province":"TX",
    "sg:tags":[
        "leasing",
        "video",
        "disc",
        "tape"
    ],
    "wof:name":"On Commmand Video",
    "wof:placetype":"venue"
},
  "geometry": {"coordinates":[-96.96702399999999,32.885118],"type":"Point"}
}