{
  "type": "Feature",
  "properties": {
    "iso:country":"US",
    "sg:address":"401 NW 28th St",
    "sg:city":"Fort Worth",
    "sg:classifiers":[
        {
            "category":"Food & Beverages",
            "subcategory":"Groceries & Convenience Stores",
            "type":"Retail Goods"
        }
    ],
    "sg:phone":"+1 817 626 3310",
    "sg:postcode":"76106",
    "sg:province":"TX",
    "wof:name":"Speedy Sacks N Packs",
    "wof:placetype":"venue"
},
  "geometry": {"coordinates":[-97.353802,32.795339],"type":"Point"}
}