{
  "type": "Feature",
  "properties": {
    "iso:country":"US",
    "sg:address":"272 W Wildwood Dr",
    "sg:city":"San Antonio",
    "sg:classifiers":[
        {
            "category":"Shopping",
            "subcategory":"Jewelry",
            "type":"Retail Goods"
        }
    ],
    "sg:phone":"+1 210 824 8256",
    "sg:postcode":"78212",
    "sg:province":"TX",
    "wof:name":"Michael D Hyatt",
    "wof:placetype":"venue"
},
  "geometry": {"coordinates":[-98.496773,29.479377],"type":"Point"}
}