{
  "type": "Feature",
  "properties": {
    "iso:country":"US",
    "sg:address":"4212 Juniper Ln",
    "sg:city":"Carrollton",
    "sg:classifiers":[
        {
            "category":"Shopping",
            "subcategory":"Clothing, Apparel, & Fashions",
            "type":"Retail Goods"
        }
    ],
    "sg:phone":"+1 972 492 1450",
    "sg:postcode":"75010",
    "sg:province":"TX",
    "wof:name":"R & J Consulting Inc",
    "wof:placetype":"venue"
},
  "geometry": {"coordinates":[-96.910168,33.026259],"type":"Point"}
}