{
  "type": "Feature",
  "properties": {
    "iso:country":"US",
    "sg:address":"1106 S Shepherd Dr",
    "sg:city":"Houston",
    "sg:classifiers":[
        {
            "category":"Arts & Performance",
            "subcategory":"Art Gallery",
            "type":"Entertainment"
        }
    ],
    "sg:phone":"+1 713 523 4300",
    "sg:postcode":"77019",
    "sg:province":"TX",
    "wof:name":"Gerhard Wurzer Gallery",
    "wof:placetype":"venue"
},
  "geometry": {"coordinates":[-95.40894,29.75598],"type":"Point"}
}