{
  "type": "Feature",
  "properties": {
    "iso:country":"US",
    "sg:address":"651 S Walnut Ave",
    "sg:city":"New Braunfels",
    "sg:classifiers":[
        {
            "category":"Banks & Credit Unions",
            "subcategory":"Bank",
            "type":"Services"
        }
    ],
    "sg:phone":"+1 830 625 6216",
    "sg:postcode":"78130",
    "sg:province":"TX",
    "sg:tags":[
        "personal",
        "financing",
        "short",
        "institution",
        "business"
    ],
    "wof:name":"Citi Financial",
    "wof:placetype":"venue"
},
  "geometry": {"coordinates":[-98.12682,29.688376],"type":"Point"}
}