{
  "type": "Feature",
  "properties": {
    "iso:country":"US",
    "sg:address":"204 Crooked Creek Dr",
    "sg:city":"Richardson",
    "sg:classifiers":[
        {
            "category":"Manufacturing",
            "subcategory":"Rubber & Plastics",
            "type":"Manufacturing & Wholesale Goods"
        }
    ],
    "sg:phone":"+1 972 783 1123",
    "sg:postcode":"75080",
    "sg:province":"TX",
    "sg:tags":[
        "product"
    ],
    "wof:name":"Ropak Southwest",
    "wof:placetype":"venue"
},
  "geometry": {"coordinates":[-96.71435,32.993366],"type":"Point"}
}