{
  "type": "Feature",
  "properties": {
    "iso:country":"US",
    "sg:address":"2411 Park Ave",
    "sg:city":"Kemah",
    "sg:classifiers":[
        {
            "category":"Wholesale",
            "subcategory":"Computers",
            "type":"Manufacturing & Wholesale Goods"
        }
    ],
    "sg:phone":"+1 281 339 1659",
    "sg:postcode":"77565",
    "sg:province":"TX",
    "sg:tags":[
        "equipment"
    ],
    "wof:name":"Texas Computer Hub LTD",
    "wof:placetype":"venue"
},
  "geometry": {"coordinates":[-95.005673,29.525558],"type":"Point"}
}