{
  "type": "Feature",
  "properties": {
    "iso:country":"US",
    "sg:address":"2083 Hwy 97 E",
    "sg:city":"Pleasanton",
    "sg:classifiers":[
        {
            "category":"Personal",
            "subcategory":"Beauty Salon",
            "type":"Services"
        }
    ],
    "sg:phone":"+1 830 569 2004",
    "sg:postcode":"78064",
    "sg:province":"TX",
    "wof:name":"Curl Up With A Good Look Hair",
    "wof:placetype":"venue"
},
  "geometry": {"coordinates":[-98.46758199999999,28.978033],"type":"Point"}
}