{
  "type": "Feature",
  "properties": {
    "iso:country":"US",
    "sg:address":"222 Milwaukee St",
    "sg:city":"Houston",
    "sg:classifiers":[
        {
            "category":"Building & Trades",
            "subcategory":"Construction",
            "type":"Services"
        }
    ],
    "sg:phone":"+1 713 694 1474",
    "sg:postcode":"77009",
    "sg:province":"TX",
    "sg:tags":[
        "roofing",
        "contractor",
        "industrial",
        "contractors-commercial",
        "consultant"
    ],
    "wof:name":"Black Diamond Roofing",
    "wof:placetype":"venue"
},
  "geometry": {"coordinates":[-95.3693,29.809325],"type":"Point"}
}