{
  "type": "Feature",
  "properties": {
    "iso:country":"US",
    "sg:address":"7412 Hour Glass Cir",
    "sg:city":"Dallas",
    "sg:classifiers":[
        {
            "category":"Shopping",
            "subcategory":"Pharmacy",
            "type":"Retail Goods"
        }
    ],
    "sg:phone":"+1 214 658 3108",
    "sg:postcode":"75252",
    "sg:province":"TX",
    "wof:name":"Richard A Genovese",
    "wof:placetype":"venue"
},
  "geometry": {"coordinates":[-96.77570900000001,32.99704],"type":"Point"}
}