{
  "type": "Feature",
  "properties": {
    "iso:country":"US",
    "sg:address":"110 Oak Hills Ln",
    "sg:city":"Boerne",
    "sg:classifiers":[
        {
            "category":"Building & Trades",
            "subcategory":"Construction",
            "type":"Services"
        }
    ],
    "sg:phone":"+1 830 230 5109",
    "sg:postcode":"78006",
    "sg:province":"TX",
    "sg:tags":[
        "contractor"
    ],
    "wof:name":"Building Concepts",
    "wof:placetype":"venue"
},
  "geometry": {"coordinates":[-98.697056,29.831441],"type":"Point"}
}