{
  "type": "Feature",
  "properties": {
    "iso:country":"US",
    "sg:address":"315 Gilmer St",
    "sg:city":"Sulphur Springs",
    "sg:classifiers":[
        {
            "category":"Professional",
            "subcategory":"Lawyer & Legal Services",
            "type":"Services"
        }
    ],
    "sg:phone":"+1 903 885 3116",
    "sg:postcode":"75482",
    "sg:province":"TX",
    "sg:tags":[
        "attorney"
    ],
    "sg:website":"www.easttexaslaw.com",
    "wof:name":"Smith Mc Dowell Ginn Mc Dowell",
    "wof:placetype":"venue"
},
  "geometry": {"coordinates":[-95.601578,33.134984],"type":"Point"}
}