{
  "type": "Feature",
  "properties": {
    "iso:country":"US",
    "sg:address":"208 E Henderson St",
    "sg:city":"Cleburne",
    "sg:classifiers":[
        {
            "category":"Shopping",
            "subcategory":"Used Merchandise",
            "type":"Retail Goods"
        }
    ],
    "sg:phone":"+1 817 645 2939",
    "sg:postcode":"76031",
    "sg:province":"TX",
    "sg:tags":[
        "antique"
    ],
    "wof:name":"Udderly Unique Antiques",
    "wof:placetype":"venue"
},
  "geometry": {"coordinates":[-97.38423,32.348029],"type":"Point"}
}