{
  "type": "Feature",
  "properties": {
    "iso:country":"US",
    "sg:address":"10738 Perrin Beitel Rd",
    "sg:city":"San Antonio",
    "sg:classifiers":[
        {
            "category":"Professional",
            "subcategory":"Business Services",
            "type":"Services"
        }
    ],
    "sg:phone":"+1 210 590 3934",
    "sg:postcode":"78217",
    "sg:province":"TX",
    "wof:name":"Bubbles & More",
    "wof:placetype":"venue"
},
  "geometry": {"coordinates":[-98.41097000000001,29.537377],"type":"Point"}
}