{
  "type": "Feature",
  "properties": {
    "iso:country":"US",
    "sg:address":"425 N Hancock St",
    "sg:city":"Angleton",
    "sg:classifiers":[
        {
            "category":"Organizations",
            "subcategory":"Religious Organization",
            "type":"Services"
        }
    ],
    "sg:phone":"+1 979 848 0438",
    "sg:postcode":"77515",
    "sg:province":"TX",
    "wof:name":"Ward Chapel Methodist Church",
    "wof:placetype":"venue"
},
  "geometry": {"coordinates":[-95.43438999999999,29.168064],"type":"Point"}
}