{
  "type": "Feature",
  "properties": {
    "iso:country":"US",
    "sg:address":"11210 Wilcrest Green Dr",
    "sg:city":"Houston",
    "sg:classifiers":[
        {
            "category":"Professional",
            "subcategory":"Detective & Security Services",
            "type":"Services"
        }
    ],
    "sg:phone":"+1 713 339 8280",
    "sg:postcode":"77042",
    "sg:province":"TX",
    "sg:tags":[
        "system"
    ],
    "wof:name":"Brinks Home Security Inc",
    "wof:placetype":"venue"
},
  "geometry": {"coordinates":[-95.56869,29.723794],"type":"Point"}
}