{
  "type": "Feature",
  "properties": {
    "iso:country":"US",
    "sg:address":"140 Glass St",
    "sg:city":"Dallas",
    "sg:classifiers":[
        {
            "category":"Wholesale",
            "subcategory":"Hardware",
            "type":"Manufacturing & Wholesale Goods"
        },
        {
            "category":"Wholesale",
            "subcategory":"Home Furnishings",
            "type":"Manufacturing & Wholesale Goods"
        }
    ],
    "sg:phone":"+1 214 653 1733",
    "sg:postcode":"75207",
    "sg:province":"TX",
    "sg:tags":[
        "curtain",
        "drapery"
    ],
    "sg:website":"www.antiquedraperyrod.com",
    "wof:name":"Antique Drapery Rod Co Inc",
    "wof:placetype":"venue"
},
  "geometry": {"coordinates":[-96.822327,32.790089],"type":"Point"}
}