{
  "type": "Feature",
  "properties": {
    "iso:country":"US",
    "sg:address":"14029 Northwest Fwy",
    "sg:city":"Houston",
    "sg:classifiers":[
        {
            "category":"Travel",
            "subcategory":"Hotels & Motels",
            "type":"Entertainment"
        }
    ],
    "sg:phone":"+1 713 462 3272",
    "sg:postcode":"77040",
    "sg:province":"TX",
    "wof:name":"Aiden Lodging Group Llc",
    "wof:placetype":"venue"
},
  "geometry": {"coordinates":[-95.521282,29.857689],"type":"Point"}
}