{
  "type": "Feature",
  "properties": {
    "iso:country":"US",
    "sg:address":"5848 Highway 78 Ste 118",
    "sg:city":"Sachse",
    "sg:classifiers":[
        {
            "category":"Professional",
            "subcategory":"Computer Services",
            "type":"Services"
        }
    ],
    "sg:phone":"+1 972 675 8708",
    "sg:postcode":"75048",
    "sg:province":"TX",
    "sg:tags":[
        "repair"
    ],
    "wof:name":"S & J ELECTRONICS",
    "wof:placetype":"venue"
},
  "geometry": {"coordinates":[-96.596011,32.975638],"type":"Point"}
}