{
  "type": "Feature",
  "properties": {
    "iso:country":"US",
    "sg:address":"1700 S 23rd St",
    "sg:city":"Mcallen",
    "sg:classifiers":[
        {
            "category":"Shopping",
            "subcategory":"Department Store",
            "type":"Retail Goods"
        }
    ],
    "sg:phone":"+1 956 631 3395",
    "sg:postcode":"78503",
    "sg:province":"TX",
    "wof:name":"National Stores",
    "wof:placetype":"venue"
},
  "geometry": {"coordinates":[-98.24768,26.190234],"type":"Point"}
}