{
  "type": "Feature",
  "properties": {
    "iso:country":"US",
    "sg:address":"11616 Sonnet Dr",
    "sg:city":"Dallas",
    "sg:classifiers":[
        {
            "category":"Manufacturing",
            "subcategory":"Building Materials",
            "type":"Manufacturing & Wholesale Goods"
        }
    ],
    "sg:phone":"+1 214 357 7126",
    "sg:postcode":"75229",
    "sg:province":"TX",
    "sg:tags":[
        "mfg",
        "wood",
        "kitchen",
        "cabinet"
    ],
    "wof:name":"Dinkles Cabinetry & Wdwkg",
    "wof:placetype":"venue"
},
  "geometry": {"coordinates":[-96.859877,32.907796],"type":"Point"}
}