{
  "type": "Feature",
  "properties": {
    "iso:country":"US",
    "sg:address":"3807 Deerfield Dr",
    "sg:city":"San Antonio",
    "sg:classifiers":[
        {
            "category":"Building & Trades",
            "subcategory":"Landscaping Services",
            "type":"Services"
        }
    ],
    "sg:phone":"+1 210 599 6392",
    "sg:postcode":"78218",
    "sg:province":"TX",
    "wof:name":"J & R Lawn Service",
    "wof:placetype":"venue"
},
  "geometry": {"coordinates":[-98.418306,29.51523],"type":"Point"}
}