{
  "type": "Feature",
  "properties": {
    "iso:country":"US",
    "sg:address":"5210 Tower Dr",
    "sg:city":"Wichita Falls",
    "sg:classifiers":[
        {
            "category":"Banks & Credit Unions",
            "subcategory":"Bank",
            "type":"Services"
        }
    ],
    "sg:phone":"+1 940 689 8834",
    "sg:postcode":"76310",
    "sg:province":"TX",
    "sg:tags":[
        "federal",
        "savings",
        "institution"
    ],
    "wof:name":"Mbm Security Loan Inc",
    "wof:placetype":"venue"
},
  "geometry": {"coordinates":[-98.573671,33.853784],"type":"Point"}
}