{
  "type": "Feature",
  "properties": {
    "iso:country":"US",
    "sg:address":"3003 Beaumont Ave",
    "sg:city":"Snyder",
    "sg:classifiers":[
        {
            "category":"Manufacturing",
            "subcategory":"Printing",
            "type":"Manufacturing & Wholesale Goods"
        }
    ],
    "sg:phone":"+1 325 573 4146",
    "sg:postcode":"79549",
    "sg:province":"TX",
    "sg:tags":[
        "lithographic",
        "commercial"
    ],
    "wof:name":"MGM Printing",
    "wof:placetype":"venue"
},
  "geometry": {"coordinates":[-100.929496,32.712107],"type":"Point"}
}