{
  "type": "Feature",
  "properties": {
    "iso:country":"US",
    "sg:address":"7915 FM 1960 W",
    "sg:city":"Houston",
    "sg:classifiers":[
        {
            "category":"Professional",
            "subcategory":"Accounting & Tax Preparation",
            "type":"Services"
        }
    ],
    "sg:phone":"+1 281 890 1000",
    "sg:postcode":"77070",
    "sg:province":"TX",
    "sg:tags":[
        "return"
    ],
    "wof:name":"Daniel Offutt",
    "wof:placetype":"venue"
},
  "geometry": {"coordinates":[-95.547076,29.961301],"type":"Point"}
}