{
  "type": "Feature",
  "properties": {
    "iso:country":"US",
    "sg:address":"2111 Austin Ave",
    "sg:city":"Waco",
    "sg:classifiers":[
        {
            "category":"Health Services",
            "subcategory":"Clinic",
            "type":"Services"
        }
    ],
    "sg:phone":"+1 254 757 0091",
    "sg:postcode":"76701",
    "sg:province":"TX",
    "sg:tags":[
        "specialty",
        "outpatient"
    ],
    "wof:name":"Independent Program",
    "wof:placetype":"venue"
},
  "geometry": {"coordinates":[-97.147593,31.543145],"type":"Point"}
}