{
  "type": "Feature",
  "properties": {
    "iso:country":"US",
    "sg:address":"720 S Belt Line Rd",
    "sg:city":"Irving",
    "sg:classifiers":[
        {
            "category":"Manufacturing",
            "subcategory":"Apparel",
            "type":"Manufacturing & Wholesale Goods"
        }
    ],
    "sg:phone":"+1 972 790 1501",
    "sg:postcode":"75060",
    "sg:province":"TX",
    "sg:tags":[
        "canvas",
        "mfg",
        "cover",
        "product",
        "other",
        "boat"
    ],
    "wof:name":"Texas Canvas Products",
    "wof:placetype":"venue"
},
  "geometry": {"coordinates":[-96.994427,32.805265],"type":"Point"}
}