{
  "type": "Feature",
  "properties": {
    "iso:country":"US",
    "sg:address":"6909 One Oak Rd",
    "sg:city":"Austin",
    "sg:classifiers":[
        {
            "category":"Professional",
            "subcategory":"Lawyer & Legal Services",
            "type":"Services"
        }
    ],
    "sg:phone":"+1 512 892 5700",
    "sg:postcode":"78749",
    "sg:province":"TX",
    "wof:name":"Legal Connection Inc The",
    "wof:placetype":"venue"
},
  "geometry": {"coordinates":[-97.845214,30.221561],"type":"Point"}
}