{
  "type": "Feature",
  "properties": {
    "iso:country":"US",
    "sg:address":"130 N Brownlee Blvd",
    "sg:city":"Corpus Christi",
    "sg:classifiers":[
        {
            "category":"Building & Trades",
            "subcategory":"Plumbing",
            "type":"Services"
        }
    ],
    "sg:phone":"+1 361 882 5926",
    "sg:postcode":"78401",
    "sg:province":"TX",
    "sg:tags":[
        "plumbing",
        "contractor"
    ],
    "wof:name":"Mokry Plumbing & Utility",
    "wof:placetype":"venue"
},
  "geometry": {"coordinates":[-97.408328,27.790262],"type":"Point"}
}