{
  "type": "Feature",
  "properties": {
    "iso:country":"US",
    "sg:address":"3 Sunnybrook St",
    "sg:city":"Angleton",
    "sg:classifiers":[
        {
            "category":"Professional",
            "subcategory":"Detective & Security Services",
            "type":"Services"
        }
    ],
    "sg:phone":"+1 713 314 6310",
    "sg:postcode":"77515",
    "sg:province":"TX",
    "sg:tags":[
        "information",
        "bureau"
    ],
    "wof:name":"Mpm Snacks Cakes Service",
    "wof:placetype":"venue"
},
  "geometry": {"coordinates":[-95.420197,29.189359],"type":"Point"}
}