{
  "type": "Feature",
  "properties": {
    "iso:country":"US",
    "sg:address":"17763 S Cypress Villas Dr",
    "sg:city":"Spring",
    "sg:classifiers":[
        {
            "category":"Education",
            "subcategory":"School",
            "type":"Public Place"
        }
    ],
    "sg:phone":"+1 281 320 9047",
    "sg:postcode":"77379",
    "sg:province":"TX",
    "wof:name":"Gateway Christian Outreach Ctr",
    "wof:placetype":"venue"
},
  "geometry": {"coordinates":[-95.48275599999999,30.028496],"type":"Point"}
}