{
  "type": "Feature",
  "properties": {
    "iso:country":"US",
    "sg:address":"318 Arnold Blvd",
    "sg:city":"Abilene",
    "sg:classifiers":[
        {
            "category":"Real Estate",
            "subcategory":"Real Estate Operator",
            "type":"Services"
        }
    ],
    "sg:phone":"+1 325 691 0795",
    "sg:postcode":"79605",
    "sg:province":"TX",
    "sg:tags":[
        "mobile",
        "home",
        "community"
    ],
    "wof:name":"Village Mobile Home Park",
    "wof:placetype":"venue"
},
  "geometry": {"coordinates":[-99.808921,32.448743],"type":"Point"}
}