{
  "type": "Feature",
  "properties": {
    "iso:country":"US",
    "sg:address":"1915 Windlea Dr",
    "sg:city":"Euless",
    "sg:classifiers":[
        {
            "category":"Professional",
            "subcategory":"Business Services",
            "type":"Services"
        }
    ],
    "sg:phone":"+1 817 267 0864",
    "sg:postcode":"76040",
    "sg:province":"TX",
    "wof:name":"Razach Enterprises Inc",
    "wof:placetype":"venue"
},
  "geometry": {"coordinates":[-97.116231,32.831146],"type":"Point"}
}