{
  "type": "Feature",
  "properties": {
    "iso:country":"US",
    "sg:address":"321 N Beatty Ave",
    "sg:city":"Livingston",
    "sg:classifiers":[
        {
            "category":"Shopping",
            "type":"Retail Goods"
        }
    ],
    "sg:phone":"+1 936 327 5540",
    "sg:postcode":"77351",
    "sg:province":"TX",
    "sg:tags":[
        "hearing",
        "equipment",
        "supply",
        "impaired"
    ],
    "wof:name":"Miracle-Ear",
    "wof:placetype":"venue"
},
  "geometry": {"coordinates":[-94.93490300000001,30.710473],"type":"Point"}
}