{
  "type": "Feature",
  "properties": {
    "iso:country":"US",
    "sg:address":"1412 Redbud Trl",
    "sg:city":"Austin",
    "sg:classifiers":[
        {
            "category":"Professional",
            "subcategory":"Business Services",
            "type":"Services"
        }
    ],
    "sg:phone":"+1 512 327 7684",
    "sg:postcode":"78746",
    "sg:province":"TX",
    "wof:name":"J & S Group Ltd",
    "wof:placetype":"venue"
},
  "geometry": {"coordinates":[-97.820695,30.299401],"type":"Point"}
}