{
  "type": "Feature",
  "properties": {
    "iso:country":"US",
    "sg:address":"3504 Ginger Ct",
    "sg:city":"Mckinney",
    "sg:classifiers":[
        {
            "category":"Home & Garden",
            "subcategory":"Carpets & Floor Coverings",
            "type":"Retail Goods"
        }
    ],
    "sg:phone":"+1 972 529 9879",
    "sg:postcode":"75070",
    "sg:province":"TX",
    "sg:tags":[
        "material"
    ],
    "wof:name":"Magdalena Cuestas",
    "wof:placetype":"venue"
},
  "geometry": {"coordinates":[-96.68715400000001,33.16972],"type":"Point"}
}