{
  "type": "Feature",
  "properties": {
    "iso:country":"US",
    "sg:address":"4045 Morgan Dr",
    "sg:city":"Mesquite",
    "sg:classifiers":[
        {
            "category":"Home & Garden",
            "subcategory":"Household Appliances",
            "type":"Retail Goods"
        }
    ],
    "sg:phone":"+1 972 270 7138",
    "sg:postcode":"75150",
    "sg:province":"TX",
    "wof:name":"Reasors Sewing Machines",
    "wof:placetype":"venue"
},
  "geometry": {"coordinates":[-96.646558,32.817571],"type":"Point"}
}