{
  "type": "Feature",
  "properties": {
    "iso:country":"US",
    "sg:address":"306 Yukon Ter",
    "sg:city":"Georgetown",
    "sg:classifiers":[
        {
            "category":"Professional",
            "subcategory":"Lawyer & Legal Services",
            "type":"Services"
        }
    ],
    "sg:phone":"+1 512 864 9084",
    "sg:postcode":"78633",
    "sg:province":"TX",
    "sg:tags":[
        "attorney"
    ],
    "wof:name":"Stephen E Best Iii",
    "wof:placetype":"venue"
},
  "geometry": {"coordinates":[-97.712468,30.727662],"type":"Point"}
}