{
  "type": "Feature",
  "properties": {
    "iso:country":"US",
    "sg:address":"1720 Nederland Ave",
    "sg:city":"Nederland",
    "sg:classifiers":[
        {
            "category":"Personal",
            "subcategory":"Beauty Salon",
            "type":"Services"
        }
    ],
    "sg:phone":"+1 409 727 6561",
    "sg:postcode":"77627",
    "sg:province":"TX",
    "sg:tags":[
        "shop"
    ],
    "wof:name":"Skin Salon",
    "wof:placetype":"venue"
},
  "geometry": {"coordinates":[-93.99310800000001,29.970668],"type":"Point"}
}