{
  "type": "Feature",
  "properties": {
    "iso:country":"US",
    "sg:address":"6500 River Place Blvd Building 2, Suite 101",
    "sg:city":"Austin",
    "sg:classifiers":[
        {
            "category":"Professional",
            "subcategory":"Computer Services",
            "type":"Services"
        }
    ],
    "sg:phone":"+1 512 532 3500",
    "sg:postcode":"78730",
    "sg:province":"TX",
    "sg:tags":[
        "identity-resolution",
        "similarity-search",
        "entity-analysis-and-resolution",
        "entity-resolution",
        "data-matching",
        "name-matching",
        "master-data-management",
        "customer-data-integration",
        "product-information-management",
        "data-quality"
    ],
    "sg:website":"http://www.infoglide.com",
    "wof:name":"Infoglide Software Corporation",
    "wof:placetype":"venue"
},
  "geometry": {"coordinates":[-97.847492,30.391762],"type":"Point"}
}