{
  "type": "Feature",
  "properties": {
    "iso:country":"US",
    "sg:address":"1233 S Danville Dr",
    "sg:city":"Abilene",
    "sg:classifiers":[
        {
            "category":"Wholesale",
            "subcategory":"Medical Equipment & Supplies",
            "type":"Manufacturing & Wholesale Goods"
        }
    ],
    "sg:phone":"+1 325 692 0359",
    "sg:postcode":"79605",
    "sg:province":"TX",
    "wof:name":"Sourceone Healthcare Tech",
    "wof:placetype":"venue"
},
  "geometry": {"coordinates":[-99.786582,32.436681],"type":"Point"}
}