{
  "type": "Feature",
  "properties": {
    "iso:country":"US",
    "sg:address":"905 Sweetgum Creek",
    "sg:city":"Plano",
    "sg:classifiers":[
        {
            "category":"Professional",
            "subcategory":"Secretarial Services",
            "type":"Services"
        }
    ],
    "sg:phone":"+1 972 527 1049",
    "sg:postcode":"75023",
    "sg:province":"TX",
    "sg:tags":[
        "reporting"
    ],
    "wof:name":"V&M Services",
    "wof:placetype":"venue"
},
  "geometry": {"coordinates":[-96.71094100000001,33.068058],"type":"Point"}
}