{
  "type": "Feature",
  "properties": {
    "iso:country":"US",
    "sg:address":"3122 W Main St",
    "sg:city":"Ingleside",
    "sg:classifiers":[
        {
            "category":"Home & Garden",
            "subcategory":"Garden Supply",
            "type":"Retail Goods"
        }
    ],
    "sg:phone":"+1 361 776 9500",
    "sg:postcode":"78362",
    "sg:province":"TX",
    "sg:tags":[
        "fountain",
        "display"
    ],
    "wof:name":"Natures Garden",
    "wof:placetype":"venue"
},
  "geometry": {"coordinates":[-97.217259,27.883648],"type":"Point"}
}