{
  "type": "Feature",
  "properties": {
    "iso:country":"US",
    "sg:address":"1514 Holly St",
    "sg:city":"Austin",
    "sg:classifiers":[
        {
            "category":"Food & Beverages",
            "subcategory":"Groceries & Convenience Stores",
            "type":"Retail Goods"
        }
    ],
    "sg:phone":"+1 512 474 2077",
    "sg:postcode":"78702",
    "sg:province":"TX",
    "sg:tags":[
        "product"
    ],
    "wof:name":"Bread Basket Food Store",
    "wof:placetype":"venue"
},
  "geometry": {"coordinates":[-97.731123,30.255193],"type":"Point"}
}