{
  "type": "Feature",
  "properties": {
    "iso:country":"US",
    "sg:address":"10649 Leopard St",
    "sg:city":"Corpus Christi",
    "sg:classifiers":[
        {
            "category":"Retail",
            "subcategory":"Auto Repair",
            "type":"Services"
        }
    ],
    "sg:phone":"+1 361 241 6212",
    "sg:postcode":"78410",
    "sg:province":"TX",
    "sg:tags":[
        "repairing",
        "automobile"
    ],
    "wof:name":"VIP Super Lube",
    "wof:placetype":"venue"
},
  "geometry": {"coordinates":[-97.576745,27.840199],"type":"Point"}
}