{
  "type": "Feature",
  "properties": {
    "iso:country":"US",
    "sg:address":"5 Founders Blvd",
    "sg:city":"El Paso",
    "sg:classifiers":[
        {
            "category":"Wholesale",
            "subcategory":"Electrical",
            "type":"Manufacturing & Wholesale Goods"
        }
    ],
    "sg:phone":"+1 915 771 8727",
    "sg:postcode":"79906",
    "sg:province":"TX",
    "sg:tags":[
        "equipment",
        "electric",
        "supply"
    ],
    "wof:name":"Lear Mexican Operations",
    "wof:placetype":"venue"
},
  "geometry": {"coordinates":[-106.402644,31.817569],"type":"Point"}
}