{
  "type": "Feature",
  "properties": {
    "iso:country":"US",
    "sg:address":"764 Willow Xing",
    "sg:city":"New Braunfels",
    "sg:classifiers":[
        {
            "category":"Building & Trades",
            "subcategory":"Construction",
            "type":"Services"
        }
    ],
    "sg:phone":"+1 830 626 2918",
    "sg:postcode":"78130",
    "sg:province":"TX",
    "sg:tags":[
        "home",
        "builder"
    ],
    "wof:name":"KB Home",
    "wof:placetype":"venue"
},
  "geometry": {"coordinates":[-98.093101,29.730156],"type":"Point"}
}