{
  "type": "Feature",
  "properties": {
    "iso:country":"US",
    "sg:address":"2636 Taner Cir",
    "sg:city":"Haslet",
    "sg:classifiers":[
        {
            "category":"Retail",
            "subcategory":"Laundry & Dry Cleaning",
            "type":"Services"
        }
    ],
    "sg:phone":"+1 817 980 9897",
    "sg:postcode":"76052",
    "sg:province":"TX",
    "sg:tags":[
        "cleaner",
        "rug",
        "carpet"
    ],
    "wof:name":"Philip D. Blackmon Enterprises",
    "wof:placetype":"venue"
},
  "geometry": {"coordinates":[-97.41278800000001,32.941034],"type":"Point"}
}