{
  "type": "Feature",
  "properties": {
    "iso:country":"US",
    "sg:address":"3000 N Hibiscus St",
    "sg:city":"Pharr",
    "sg:classifiers":[
        {
            "category":"Professional",
            "subcategory":"Engineering",
            "type":"Services"
        },
        {
            "category":"Wholesale",
            "subcategory":"Machinery & Supplies",
            "type":"Manufacturing & Wholesale Goods"
        },
        {
            "category":"Wholesale",
            "subcategory":"Electrical",
            "type":"Manufacturing & Wholesale Goods"
        }
    ],
    "sg:phone":"+1 956 781 0091",
    "sg:postcode":"78577",
    "sg:province":"TX",
    "sg:tags":[
        "major",
        "appliance",
        "system",
        "systems-wholesale",
        "equipment",
        "part",
        "air conditioning",
        "manufacturer"
    ],
    "wof:name":"Carrier Enterprise, Llc",
    "wof:placetype":"venue"
},
  "geometry": {"coordinates":[-98.18791,26.23152],"type":"Point"}
}