{
  "type": "Feature",
  "properties": {
    "iso:country":"US",
    "sg:address":"2002 N Conway Ave",
    "sg:city":"Mission",
    "sg:classifiers":[
        {
            "category":"Utilities",
            "subcategory":"Mobile Phone",
            "type":"Services"
        },
        {
            "category":"Shopping",
            "type":"Retail Goods"
        }
    ],
    "sg:phone":"+1 956 424 1171",
    "sg:postcode":"78572",
    "sg:province":"TX",
    "sg:tags":[
        "communication",
        "radiotelephone",
        "cellular",
        "telephone"
    ],
    "sg:website":"www.ianddwireless.com",
    "wof:name":"I & D Wireless",
    "wof:placetype":"venue"
},
  "geometry": {"coordinates":[-98.323593,26.22752],"type":"Point"}
}