{
  "type": "Feature",
  "properties": {
    "iso:country":"US",
    "sg:address":"15950 N. Dallas Parkway  Suite 400 (972) 361.8141",
    "sg:city":"Dallas",
    "sg:classifiers":[
        {
            "category":"Professional",
            "subcategory":"Advertising",
            "type":"Services"
        }
    ],
    "sg:phone":"+1 650 595 1300",
    "sg:province":"TX",
    "sg:tags":[
        "online-advertising",
        "ad-network",
        "hybrid-ad-network",
        "targeting",
        "demand-side-platform",
        "display-ad-optimization"
    ],
    "sg:website":"http://www.rocketfuel.com/",
    "wof:name":"Rocket Fuel",
    "wof:placetype":"venue"
},
  "geometry": {"coordinates":[-96.821212,32.967911],"type":"Point"}
}