{
  "type": "Feature",
  "properties": {
    "iso:country":"US",
    "sg:address":"14242 Kittydale Dr",
    "sg:city":"Humble",
    "sg:classifiers":[
        {
            "category":"Retail",
            "subcategory":"Repair Shop",
            "type":"Services"
        }
    ],
    "sg:phone":"+1 281 441 9751",
    "sg:postcode":"77396",
    "sg:province":"TX",
    "wof:name":"Personal Touch Cleaning Svc",
    "wof:placetype":"venue"
},
  "geometry": {"coordinates":[-95.29616799999999,29.925952],"type":"Point"}
}