{
  "type": "Feature",
  "properties": {
    "iso:country":"US",
    "sg:address":"12222 Quail Dr",
    "sg:city":"Balch Springs",
    "sg:classifiers":[
        {
            "category":"Professional",
            "type":"Services"
        }
    ],
    "sg:phone":"+1 972 557 0286",
    "sg:postcode":"75180",
    "sg:province":"TX",
    "sg:tags":[
        "establishment"
    ],
    "wof:name":"Killing",
    "wof:placetype":"venue"
},
  "geometry": {"coordinates":[-96.616974,32.724632],"type":"Point"}
}