{
  "type": "Feature",
  "properties": {
    "iso:country":"US",
    "sg:address":"32853 Monica Vw",
    "sg:city":"Bulverde",
    "sg:classifiers":[
        {
            "category":"Professional",
            "subcategory":"Business Services",
            "type":"Services"
        }
    ],
    "sg:phone":"+1 830 980 2707",
    "sg:postcode":"78163",
    "sg:province":"TX",
    "wof:name":"Frank Lanfranco Jr",
    "wof:placetype":"venue"
},
  "geometry": {"coordinates":[-98.44484199999999,29.779858],"type":"Point"}
}