{
  "type": "Feature",
  "properties": {
    "iso:country":"US",
    "sg:address":"2808 Trinity Square Dr",
    "sg:city":"Carrollton",
    "sg:classifiers":[
        {
            "category":"Social Services",
            "subcategory":"Child Care",
            "type":"Services"
        },
        {
            "category":"Education",
            "subcategory":"Preschool",
            "type":"Public Place"
        },
        {
            "category":"Education",
            "subcategory":"School",
            "type":"Public Place"
        }
    ],
    "sg:phone":"+1 972 416 8449",
    "sg:postcode":"75006",
    "sg:province":"TX",
    "sg:tags":[
        "elementary",
        "day"
    ],
    "wof:name":"Today's Child Montessori School",
    "wof:placetype":"venue"
},
  "geometry": {"coordinates":[-96.85459899999999,32.983501],"type":"Point"}
}