{
  "type": "Feature",
  "properties": {
    "iso:country":"US",
    "sg:address":"7124 Longo Dr",
    "sg:city":"Lewisville",
    "sg:classifiers":[
        {
            "category":"Professional",
            "subcategory":"Management & Consulting",
            "type":"Services"
        }
    ],
    "sg:phone":"+1 972 625 7045",
    "sg:postcode":"75056",
    "sg:province":"TX",
    "wof:name":"Bbg Management",
    "wof:placetype":"venue"
},
  "geometry": {"coordinates":[-96.86206199999999,33.100659],"type":"Point"}
}