{
  "type": "Feature",
  "properties": {
    "iso:country":"US",
    "sg:address":"7502 Long Point Rd",
    "sg:city":"Houston",
    "sg:classifiers":[
        {
            "category":"Restaurant",
            "type":"Food & Drink"
        }
    ],
    "sg:phone":"+1 713 688 3318",
    "sg:postcode":"77055",
    "sg:province":"TX",
    "sg:tags":[
        "seafood"
    ],
    "wof:name":"Connie's Seafood & Oyster Bar",
    "wof:placetype":"venue"
},
  "geometry": {"coordinates":[-95.4785,29.802999],"type":"Point"}
}