{
  "type": "Feature",
  "properties": {
    "iso:country":"US",
    "sg:address":"13204 FM 1826",
    "sg:city":"Austin",
    "sg:classifiers":[
        {
            "category":"Food & Beverages",
            "subcategory":"Meat & Fish",
            "type":"Retail Goods"
        }
    ],
    "sg:phone":"+1 512 301 9814",
    "sg:postcode":"78737",
    "sg:province":"TX",
    "sg:tags":[
        "seafood"
    ],
    "wof:name":"BMI Of Oakhill",
    "wof:placetype":"venue"
},
  "geometry": {"coordinates":[-97.93538599999999,30.171964],"type":"Point"}
}