{
  "type": "Feature",
  "properties": {
    "iso:country":"US",
    "sg:address":"12708 Azalea Cir",
    "sg:city":"Buda",
    "sg:classifiers":[
        {
            "category":"Banks & Credit Unions",
            "subcategory":"Financial Services",
            "type":"Services"
        }
    ],
    "sg:phone":"+1 512 295 2005",
    "sg:postcode":"78610",
    "sg:province":"TX",
    "sg:tags":[
        "investor"
    ],
    "wof:name":"5 D Investments Inc",
    "wof:placetype":"venue"
},
  "geometry": {"coordinates":[-97.85702000000001,30.111342],"type":"Point"}
}