{
  "type": "Feature",
  "properties": {
    "iso:country":"US",
    "sg:address":"733 Sunset Dr",
    "sg:city":"Irving",
    "sg:classifiers":[
        {
            "category":"Building & Trades",
            "subcategory":"Construction",
            "type":"Services"
        }
    ],
    "sg:phone":"+1 972 254 2054",
    "sg:postcode":"75061",
    "sg:province":"TX",
    "sg:tags":[
        "house"
    ],
    "wof:name":"Colonial Remodeling",
    "wof:placetype":"venue"
},
  "geometry": {"coordinates":[-96.95645,32.816629],"type":"Point"}
}