{
  "type": "Feature",
  "properties": {
    "iso:country":"US",
    "sg:address":"3408 Forrester Ln",
    "sg:city":"Waco",
    "sg:classifiers":[
        {
            "category":"Retail",
            "subcategory":"Auto Rental",
            "type":"Services"
        }
    ],
    "sg:phone":"+1 254 757 2823",
    "sg:postcode":"76708",
    "sg:province":"TX",
    "sg:tags":[
        "truck"
    ],
    "wof:name":"Anderson Leasing LLC",
    "wof:placetype":"venue"
},
  "geometry": {"coordinates":[-97.187555,31.566596],"type":"Point"}
}