{
  "type": "Feature",
  "properties": {
    "iso:country":"US",
    "sg:address":"611 N Texas St",
    "sg:city":"Rio Grande City",
    "sg:classifiers":[
        {
            "category":"Professional",
            "type":"Services"
        }
    ],
    "sg:phone":"+1 956 488 0806",
    "sg:postcode":"78582",
    "sg:province":"TX",
    "sg:tags":[
        "establishment"
    ],
    "wof:name":"Combined Governmental Drug",
    "wof:placetype":"venue"
},
  "geometry": {"coordinates":[-98.81982499999999,26.38413],"type":"Point"}
}