{
  "type": "Feature",
  "properties": {
    "iso:country":"US",
    "sg:address":"16821 Buccaneer Ln",
    "sg:city":"Houston",
    "sg:classifiers":[
        {
            "category":"Professional",
            "subcategory":"Business Services",
            "type":"Services"
        }
    ],
    "sg:phone":"+1 281 488 1474",
    "sg:postcode":"77058",
    "sg:province":"TX",
    "sg:tags":[
        "interior",
        "consultant",
        "design",
        "decorator"
    ],
    "wof:name":"Decorative Design",
    "wof:placetype":"venue"
},
  "geometry": {"coordinates":[-95.114526,29.555201],"type":"Point"}
}