{
  "type": "Feature",
  "properties": {
    "iso:country":"US",
    "sg:address":"4806 Palm St",
    "sg:city":"Bellaire",
    "sg:classifiers":[
        {
            "category":"Shopping",
            "subcategory":"Computers & Home Electronics",
            "type":"Retail Goods"
        }
    ],
    "sg:phone":"+1 713 664 8949",
    "sg:postcode":"77401",
    "sg:province":"TX",
    "wof:name":"Damico Computer Works",
    "wof:placetype":"venue"
},
  "geometry": {"coordinates":[-95.46200399999999,29.699873],"type":"Point"}
}