{
  "type": "Feature",
  "properties": {
    "iso:country":"US",
    "sg:address":"400 S Concho St",
    "sg:city":"Coleman",
    "sg:classifiers":[
        {
            "category":"Retail",
            "subcategory":"Auto Repair",
            "type":"Services"
        }
    ],
    "sg:phone":"+1 325 625 9925",
    "sg:postcode":"76834",
    "sg:province":"TX",
    "sg:tags":[
        "repairing",
        "automobile"
    ],
    "wof:name":"Miller's Automotive Ctr",
    "wof:placetype":"venue"
},
  "geometry": {"coordinates":[-99.424161,31.828155],"type":"Point"}
}