{
  "type": "Feature",
  "properties": {
    "iso:country":"US",
    "sg:address":"615 W Main St",
    "sg:city":"Whitesboro",
    "sg:classifiers":[
        {
            "category":"Home & Garden",
            "subcategory":"Garden Supply",
            "type":"Retail Goods"
        }
    ],
    "sg:phone":"+1 903 564 7722",
    "sg:postcode":"76273",
    "sg:province":"TX",
    "wof:name":"Hedges Nursery",
    "wof:placetype":"venue"
},
  "geometry": {"coordinates":[-96.91442499999999,33.656088],"type":"Point"}
}