{
  "type": "Feature",
  "properties": {
    "iso:country":"US",
    "sg:address":"1615 John West Rd",
    "sg:city":"Dallas",
    "sg:classifiers":[
        {
            "category":"Retail",
            "subcategory":"Auto Repair",
            "type":"Services"
        }
    ],
    "sg:phone":"+1 214 321 9977",
    "sg:postcode":"75228",
    "sg:province":"TX",
    "sg:tags":[
        "repairing",
        "automobile"
    ],
    "wof:name":"Complete Auto Care",
    "wof:placetype":"venue"
},
  "geometry": {"coordinates":[-96.687622,32.807025],"type":"Point"}
}