{
  "type": "Feature",
  "properties": {
    "iso:country":"US",
    "sg:address":"3200 Fierro Dr",
    "sg:city":"El Paso",
    "sg:classifiers":[
        {
            "category":"Government",
            "subcategory":"Office",
            "type":"Public Place"
        }
    ],
    "sg:phone":"+1 915 591 4292",
    "sg:postcode":"79935",
    "sg:province":"TX",
    "sg:tags":[
        "social"
    ],
    "wof:name":"Eastside Senior Citizen Center",
    "wof:placetype":"venue"
},
  "geometry": {"coordinates":[-106.32737899999999,31.787186],"type":"Point"}
}