{
  "type": "Feature",
  "properties": {
    "iso:country":"US",
    "sg:address":"120 Circle Way St",
    "sg:city":"Lake Jackson",
    "sg:classifiers":[
        {
            "category":"Shopping",
            "subcategory":"Clothing, Apparel, & Fashions",
            "type":"Retail Goods"
        }
    ],
    "sg:phone":"+1 979 297 2799",
    "sg:postcode":"77566",
    "sg:province":"TX",
    "sg:tags":[
        "beauty",
        "supply"
    ],
    "wof:name":"US Communications",
    "wof:placetype":"venue"
},
  "geometry": {"coordinates":[-95.448671,29.03846],"type":"Point"}
}