{
  "type": "Feature",
  "properties": {
    "iso:country":"US",
    "sg:address":"1831 N Main St",
    "sg:city":"Pearland",
    "sg:classifiers":[
        {
            "category":"Insurance",
            "subcategory":"Insurance Agent",
            "type":"Services"
        }
    ],
    "sg:phone":"+1 281 412 9696",
    "sg:postcode":"77581",
    "sg:province":"TX",
    "wof:name":"Amco Insurance Agency",
    "wof:placetype":"venue"
},
  "geometry": {"coordinates":[-95.28609899999999,29.571661],"type":"Point"}
}