{
  "type": "Feature",
  "properties": {
    "iso:country":"US",
    "sg:address":"1213 Hermann Dr",
    "sg:city":"Houston",
    "sg:classifiers":[
        {
            "category":"Health Services",
            "subcategory":"Doctor",
            "type":"Services"
        }
    ],
    "sg:phone":"+1 713 520 1241",
    "sg:postcode":"77004",
    "sg:province":"TX",
    "sg:tags":[
        "physician",
        "surgeon"
    ],
    "wof:name":"Timothy P Bohan MD",
    "wof:placetype":"venue"
},
  "geometry": {"coordinates":[-95.388378,29.722678],"type":"Point"}
}