{
  "type": "Feature",
  "properties": {
    "iso:country":"US",
    "sg:address":"20 Lake Dr",
    "sg:city":"Round Rock",
    "sg:classifiers":[
        {
            "category":"Building & Trades",
            "subcategory":"Construction",
            "type":"Services"
        }
    ],
    "sg:phone":"+1 512 255 3015",
    "sg:postcode":"78665",
    "sg:province":"TX",
    "sg:tags":[
        "excavation",
        "contractor"
    ],
    "wof:name":"Adams Truck and Backhoe Svc",
    "wof:placetype":"venue"
},
  "geometry": {"coordinates":[-97.67240099999999,30.544448],"type":"Point"}
}