{
  "type": "Feature",
  "properties": {
    "iso:country":"US",
    "sg:address":"3511 Black Locust Dr",
    "sg:city":"Sugar Land",
    "sg:classifiers":[
        {
            "category":"Professional",
            "subcategory":"Business Services",
            "type":"Services"
        }
    ],
    "sg:phone":"+1 281 265 4345",
    "sg:postcode":"77479",
    "sg:province":"TX",
    "wof:name":"Taichong Corporation",
    "wof:placetype":"venue"
},
  "geometry": {"coordinates":[-95.596811,29.570073],"type":"Point"}
}