{
  "type": "Feature",
  "properties": {
    "iso:country":"US",
    "sg:address":"7308 Mcneil Dr",
    "sg:city":"Austin",
    "sg:classifiers":[
        {
            "category":"Autos & Motor Vehicles",
            "subcategory":"Auto Supplies",
            "type":"Retail Goods"
        },
        {
            "category":"Wholesale",
            "subcategory":"Electrical",
            "type":"Manufacturing & Wholesale Goods"
        },
        {
            "category":"Wholesale",
            "subcategory":"Auto Parts",
            "type":"Manufacturing & Wholesale Goods"
        },
        {
            "category":"Retail",
            "subcategory":"Auto Repair",
            "type":"Services"
        }
    ],
    "sg:phone":"+1 512 996 0504",
    "sg:postcode":"78729",
    "sg:province":"TX",
    "sg:tags":[
        "engines-rebuild",
        "exchange",
        "battery",
        "automobile",
        "accessory",
        "equipment",
        "supplies-used",
        "truck",
        "rebuilt",
        "batteries-storage"
    ],
    "sg:website":"http://www.advanceautoparts.com",
    "wof:name":"Advance Auto Parts",
    "wof:placetype":"venue"
},
  "geometry": {"coordinates":[-97.76658500000001,30.435338],"type":"Point"}
}