{
  "type": "Feature",
  "properties": {
    "iso:country":"US",
    "sg:address":"604 Hurst St",
    "sg:city":"Center",
    "sg:classifiers":[
        {
            "category":"Health Services",
            "subcategory":"Doctor",
            "type":"Services"
        },
        {
            "category":"Health Services",
            "subcategory":"Clinic",
            "type":"Services"
        }
    ],
    "sg:phone":"+1 936 598 5633",
    "sg:postcode":"75935",
    "sg:province":"TX",
    "sg:tags":[
        "physician",
        "family",
        "medical",
        "practice",
        "surgeons",
        "medicine",
        "surgery-general"
    ],
    "wof:name":"Memorial Clinic",
    "wof:placetype":"venue"
},
  "geometry": {"coordinates":[-94.18996,31.795905],"type":"Point"}
}