{
  "type": "Feature",
  "properties": {
    "iso:country":"US",
    "sg:address":"2907 Elsbury Ln",
    "sg:city":"Pearland",
    "sg:classifiers":[
        {
            "category":"Banks & Credit Unions",
            "subcategory":"Financial Services",
            "type":"Services"
        }
    ],
    "sg:phone":"+1 281 997 1807",
    "sg:postcode":"77584",
    "sg:province":"TX",
    "sg:tags":[
        "investor"
    ],
    "wof:name":"RCM Investment Group LLC",
    "wof:placetype":"venue"
},
  "geometry": {"coordinates":[-95.360319,29.542772],"type":"Point"}
}