{
  "type": "Feature",
  "properties": {
    "iso:country":"US",
    "sg:address":"1615 Anton Stade Rd",
    "sg:city":"Rosenberg",
    "sg:classifiers":[
        {
            "category":"Travel",
            "subcategory":"Travel Agent",
            "type":"Entertainment"
        }
    ],
    "sg:phone":"+1 281 342 3598",
    "sg:postcode":"77471",
    "sg:province":"TX",
    "sg:tags":[
        "agency"
    ],
    "wof:name":"Classic Travel & Tours",
    "wof:placetype":"venue"
},
  "geometry": {"coordinates":[-95.899323,29.534879],"type":"Point"}
}