{
  "type": "Feature",
  "properties": {
    "iso:country":"US",
    "sg:address":"900 Wood Hollow Ln",
    "sg:city":"Burleson",
    "sg:classifiers":[
        {
            "category":"Banks & Credit Unions",
            "subcategory":"Investment Brokerage",
            "type":"Services"
        }
    ],
    "sg:phone":"+1 817 578 5514",
    "sg:postcode":"76028",
    "sg:province":"TX",
    "sg:tags":[
        "advisory"
    ],
    "wof:name":"B J Gould Financial Services",
    "wof:placetype":"venue"
},
  "geometry": {"coordinates":[-97.29730000000001,32.531081],"type":"Point"}
}