{
  "type": "Feature",
  "properties": {
    "iso:country":"US",
    "sg:address":"1616 San Pedro Ave",
    "sg:city":"San Antonio",
    "sg:classifiers":[
        {
            "category":"Professional",
            "subcategory":"Lawyer & Legal Services",
            "type":"Services"
        }
    ],
    "sg:phone":"+1 210 923 1234",
    "sg:postcode":"78212",
    "sg:province":"TX",
    "wof:name":"Law Offices of Ed Goldner",
    "wof:placetype":"venue"
},
  "geometry": {"coordinates":[-98.49926000000001,29.449928],"type":"Point"}
}