{
  "type": "Feature",
  "properties": {
    "iso:country":"US",
    "sg:address":"6008 Fir Ct",
    "sg:city":"Mc Kinney",
    "sg:classifiers":[
        {
            "category":"Professional",
            "subcategory":"Computer Services",
            "type":"Services"
        }
    ],
    "sg:phone":"+1 972 549 0258",
    "sg:postcode":"75070",
    "sg:province":"TX",
    "sg:tags":[
        "datum"
    ],
    "wof:name":"Datarunner",
    "wof:placetype":"venue"
},
  "geometry": {"coordinates":[-96.69416200000001,33.163663],"type":"Point"}
}