{
  "type": "Feature",
  "properties": {
    "iso:country":"US",
    "sg:address":"1517 E Main St",
    "sg:city":"La Porte",
    "sg:classifiers":[
        {
            "category":"Retail",
            "subcategory":"Auto Repair",
            "type":"Services"
        }
    ],
    "sg:phone":"+1 281 471 7890",
    "sg:postcode":"77571",
    "sg:province":"TX",
    "sg:tags":[
        "body",
        "automobile",
        "painting",
        "shop"
    ],
    "wof:name":"J & I Auto Body Repair Inc",
    "wof:placetype":"venue"
},
  "geometry": {"coordinates":[-95.005753,29.671973],"type":"Point"}
}