{
  "type": "Feature",
  "properties": {
    "iso:country":"US",
    "sg:address":"3900 W Plano Pkwy",
    "sg:city":"Plano",
    "sg:classifiers":[
        {
            "category":"Building & Trades",
            "subcategory":"Equipment Rental",
            "type":"Services"
        }
    ],
    "sg:phone":"+1 972 964 4737",
    "sg:postcode":"75075",
    "sg:province":"TX",
    "sg:tags":[
        "leasing"
    ],
    "sg:website":"www.ryder.com",
    "wof:name":"Ryder Integrated Logistics Inc",
    "wof:placetype":"venue"
},
  "geometry": {"coordinates":[-96.764781,33.009948],"type":"Point"}
}