{
  "type": "Feature",
  "properties": {
    "iso:country":"US",
    "sg:address":"8007 Fair Oaks Pkwy",
    "sg:city":"Boerne",
    "sg:classifiers":[
        {
            "category":"Professional",
            "subcategory":"Computer Services",
            "type":"Services"
        }
    ],
    "sg:phone":"+1 210 366 1191",
    "sg:postcode":"78015",
    "sg:province":"TX",
    "sg:tags":[
        "programing",
        "custom"
    ],
    "wof:name":"E N 5",
    "wof:placetype":"venue"
},
  "geometry": {"coordinates":[-98.643233,29.733884],"type":"Point"}
}