{
  "type": "Feature",
  "properties": {
    "iso:country":"US",
    "sg:address":"4306 Tolbert St",
    "sg:city":"Dallas",
    "sg:classifiers":[
        {
            "category":"Organizations",
            "subcategory":"Religious Organization",
            "type":"Services"
        }
    ],
    "sg:phone":"+1 214 388 3308",
    "sg:postcode":"75227",
    "sg:province":"TX",
    "wof:name":"Urban Indp Meth Ch",
    "wof:placetype":"venue"
},
  "geometry": {"coordinates":[-96.69197200000001,32.775248],"type":"Point"}
}