{
  "type": "Feature",
  "properties": {
    "iso:country":"US",
    "sg:address":"4526 O'Casey Dr",
    "sg:city":"Corpus Christi",
    "sg:classifiers":[
        {
            "category":"Professional",
            "subcategory":"Management & Consulting",
            "type":"Services"
        }
    ],
    "sg:phone":"+1 361 857 8584",
    "sg:postcode":"78413",
    "sg:province":"TX",
    "sg:tags":[
        "information",
        "support",
        "technology"
    ],
    "wof:name":"Stanley F Bull",
    "wof:placetype":"venue"
},
  "geometry": {"coordinates":[-97.595472,27.841801],"type":"Point"}
}