{
  "type": "Feature",
  "properties": {
    "iso:country":"US",
    "sg:address":"3610 Durazno Ave",
    "sg:city":"El Paso",
    "sg:classifiers":[
        {
            "category":"Wholesale",
            "subcategory":"Machinery & Supplies",
            "type":"Manufacturing & Wholesale Goods"
        }
    ],
    "sg:phone":"+1 915 532 9131",
    "sg:postcode":"79905",
    "sg:province":"TX",
    "sg:tags":[
        "industrial"
    ],
    "wof:name":"All-Pro Fastners Inc",
    "wof:placetype":"venue"
},
  "geometry": {"coordinates":[-106.449737,31.776406],"type":"Point"}
}