{
  "type": "Feature",
  "properties": {
    "iso:country":"US",
    "sg:address":"232 E Cottonwood Ave",
    "sg:city":"Amarillo",
    "sg:classifiers":[
        {
            "category":"Organizations",
            "subcategory":"Religious Organization",
            "type":"Services"
        }
    ],
    "sg:phone":"+1 806 383 6878",
    "sg:postcode":"79108",
    "sg:province":"TX",
    "sg:tags":[
        "church"
    ],
    "sg:website":"www.bqcc.org",
    "wof:name":"Bishop Quarterman Conference",
    "wof:placetype":"venue"
},
  "geometry": {"coordinates":[-101.82277999999999,35.304011],"type":"Point"}
}