{
  "type": "Feature",
  "properties": {
    "iso:country":"US",
    "sg:address":"1101 Farragut St",
    "sg:city":"Laredo",
    "sg:classifiers":[
        {
            "category":"Professional",
            "type":"Services"
        }
    ],
    "sg:phone":"+1 956 723 5360",
    "sg:postcode":"78040",
    "sg:province":"TX",
    "sg:tags":[
        "establishment"
    ],
    "wof:name":"Chic LA Vie Design",
    "wof:placetype":"venue"
},
  "geometry": {"coordinates":[-99.50749999999999,27.505661],"type":"Point"}
}