{
  "type": "Feature",
  "properties": {
    "iso:country":"US",
    "sg:address":"13130 Humphrey Dr",
    "sg:city":"Austin",
    "sg:classifiers":[
        {
            "category":"Professional",
            "subcategory":"Employment Agencies",
            "type":"Services"
        }
    ],
    "sg:phone":"+1 512 258 2060",
    "sg:postcode":"78729",
    "sg:province":"TX",
    "sg:tags":[
        "help",
        "contractor"
    ],
    "wof:name":"Secretaries Plus Inc",
    "wof:placetype":"venue"
},
  "geometry": {"coordinates":[-97.761611,30.450519],"type":"Point"}
}