{
  "type": "Feature",
  "properties": {
    "iso:country":"US",
    "sg:address":"2409 NW 36th St",
    "sg:city":"San Antonio",
    "sg:classifiers":[
        {
            "category":"Food & Beverages",
            "subcategory":"Groceries & Convenience Stores",
            "type":"Retail Goods"
        }
    ],
    "sg:phone":"+1 210 432 3050",
    "sg:postcode":"78228",
    "sg:province":"TX",
    "wof:name":"Stop & Go 2129",
    "wof:placetype":"venue"
},
  "geometry": {"coordinates":[-98.568485,29.459333],"type":"Point"}
}