{
  "type": "Feature",
  "properties": {
    "iso:country":"US",
    "sg:address":"10661 Rockley Rd",
    "sg:city":"Houston",
    "sg:classifiers":[
        {
            "category":"Professional",
            "subcategory":"Computer Services",
            "type":"Services"
        }
    ],
    "sg:phone":"+1 281 983 9955",
    "sg:postcode":"77099",
    "sg:province":"TX",
    "sg:tags":[
        "repair"
    ],
    "sg:website":"www.nwnit.com",
    "wof:name":"NWN Corporation",
    "wof:placetype":"venue"
},
  "geometry": {"coordinates":[-95.56529500000001,29.663368],"type":"Point"}
}