{
  "type": "Feature",
  "properties": {
    "iso:country":"US",
    "sg:address":"9852 Monroe Dr",
    "sg:city":"Dallas",
    "sg:classifiers":[
        {
            "category":"Retail",
            "subcategory":"Repair Shop",
            "type":"Services"
        }
    ],
    "sg:phone":"+1 214 358 1496",
    "sg:postcode":"75220",
    "sg:province":"TX",
    "sg:tags":[
        "electrical"
    ],
    "wof:name":"Appliance Parts Supply",
    "wof:placetype":"venue"
},
  "geometry": {"coordinates":[-96.877985,32.875506],"type":"Point"}
}