{
  "type": "Feature",
  "properties": {
    "iso:country":"US",
    "sg:address":"9111 Tavistock Dr",
    "sg:city":"Houston",
    "sg:classifiers":[
        {
            "category":"Real Estate",
            "subcategory":"Real Estate Agent",
            "type":"Services"
        }
    ],
    "sg:phone":"+1 713 541 3125",
    "sg:postcode":"77031",
    "sg:province":"TX",
    "wof:name":"A Able Real Estate Appraisa",
    "wof:placetype":"venue"
},
  "geometry": {"coordinates":[-95.540161,29.64949],"type":"Point"}
}