{
  "type": "Feature",
  "properties": {
    "iso:country":"US",
    "sg:address":"1400 Highway 69 N",
    "sg:city":"Nederland",
    "sg:classifiers":[
        {
            "category":"Autos & Motor Vehicles",
            "subcategory":"Automobile Sales",
            "type":"Retail Goods"
        }
    ],
    "sg:phone":"+1 866 453 6059",
    "sg:postcode":"77627",
    "sg:province":"TX",
    "sg:tags":[
        "new",
        "used",
        "car"
    ],
    "wof:name":"Philpott Pre-Owned Super Center",
    "wof:placetype":"venue"
},
  "geometry": {"coordinates":[-94.018506,29.966295],"type":"Point"}
}