{
  "type": "Feature",
  "properties": {
    "iso:country":"US",
    "sg:address":"300 N Louise St",
    "sg:city":"Atlanta",
    "sg:classifiers":[
        {
            "category":"Personal",
            "subcategory":"Barber",
            "type":"Services"
        }
    ],
    "sg:phone":"+1 903 799 7400",
    "sg:postcode":"75551",
    "sg:province":"TX",
    "sg:tags":[
        "shop"
    ],
    "wof:name":"Hooked Barber Shop",
    "wof:placetype":"venue"
},
  "geometry": {"coordinates":[-94.166541,33.119493],"type":"Point"}
}