{
  "type": "Feature",
  "properties": {
    "iso:country":"US",
    "sg:address":"301 North St",
    "sg:city":"New Boston",
    "sg:classifiers":[
        {
            "category":"Government",
            "subcategory":"Office",
            "type":"Public Place"
        }
    ],
    "sg:phone":"+1 903 628 5596",
    "sg:postcode":"75570",
    "sg:province":"TX",
    "sg:tags":[
        "city"
    ],
    "wof:name":"New Boston City Hall",
    "wof:placetype":"venue"
},
  "geometry": {"coordinates":[-94.41336,33.462317],"type":"Point"}
}