{
  "type": "Feature",
  "properties": {
    "iso:country":"US",
    "sg:address":"1250 E Cliff Dr",
    "sg:city":"El Paso",
    "sg:classifiers":[
        {
            "category":"Real Estate",
            "subcategory":"Real Estate Operator",
            "type":"Services"
        }
    ],
    "sg:phone":"+1 915 533 4933",
    "sg:postcode":"79902",
    "sg:province":"TX",
    "sg:tags":[
        "building",
        "professional"
    ],
    "wof:name":"Cliff Medical Ctr Joint Ventr",
    "wof:placetype":"venue"
},
  "geometry": {"coordinates":[-106.48773,31.774319],"type":"Point"}
}