{
  "type": "Feature",
  "properties": {
    "iso:country":"US",
    "sg:address":"808 W Main St",
    "sg:city":"Rio Grande City",
    "sg:classifiers":[
        {
            "category":"Food & Beverages",
            "subcategory":"Groceries & Convenience Stores",
            "type":"Retail Goods"
        }
    ],
    "sg:phone":"+1 956 487 0883",
    "sg:postcode":"78582",
    "sg:province":"TX",
    "wof:name":"Kramers Kwick Stop 2",
    "wof:placetype":"venue"
},
  "geometry": {"coordinates":[-98.828248,26.380521],"type":"Point"}
}