{
  "type": "Feature",
  "properties": {
    "iso:country":"US",
    "sg:address":"1521 Cimarron Ridge",
    "sg:city":"El Paso",
    "sg:classifiers":[
        {
            "category":"Communications",
            "subcategory":"Film & Video Production",
            "type":"Services"
        }
    ],
    "sg:phone":"+1 915 584 9966",
    "sg:postcode":"79912",
    "sg:province":"TX",
    "sg:tags":[
        "taping"
    ],
    "wof:name":"Intelia Group",
    "wof:placetype":"venue"
},
  "geometry": {"coordinates":[-106.53927299999999,31.87689],"type":"Point"}
}