{
  "type": "Feature",
  "properties": {
    "iso:country":"US",
    "sg:address":"307 S Dwight Ave",
    "sg:city":"Dallas",
    "sg:classifiers":[
        {
            "category":"Building & Trades",
            "subcategory":"Construction",
            "type":"Services"
        }
    ],
    "sg:phone":"+1 214 330 5767",
    "sg:postcode":"75211",
    "sg:province":"TX",
    "sg:tags":[
        "contractor"
    ],
    "wof:name":"Narvaez Masonry",
    "wof:placetype":"venue"
},
  "geometry": {"coordinates":[-96.90749099999999,32.744499],"type":"Point"}
}