{
  "type": "Feature",
  "properties": {
    "iso:country":"US",
    "sg:address":"1103 Farr St",
    "sg:city":"San Angelo",
    "sg:classifiers":[
        {
            "category":"Recreation",
            "type":"Entertainment"
        }
    ],
    "sg:phone":"+1 325 657 4483",
    "sg:postcode":"76903",
    "sg:province":"TX",
    "sg:tags":[
        "executive",
        "center"
    ],
    "wof:name":"Carl Ray Johnson Rec Center",
    "wof:placetype":"venue"
},
  "geometry": {"coordinates":[-100.446366,31.472034],"type":"Point"}
}