{
  "type": "Feature",
  "properties": {
    "iso:country":"US",
    "sg:address":"5116 Maryland Ave",
    "sg:city":"Dallas",
    "sg:classifiers":[
        {
            "category":"Professional",
            "type":"Services"
        }
    ],
    "sg:phone":"+1 214 374 3018",
    "sg:postcode":"75241",
    "sg:province":"TX",
    "wof:name":"Eunice Ruth Morehouse",
    "wof:placetype":"venue"
},
  "geometry": {"coordinates":[-96.813192,32.681522],"type":"Point"}
}