{
  "type": "Feature",
  "properties": {
    "iso:country":"US",
    "sg:address":"2001 N MacArthur Blvd Ste 540",
    "sg:city":"Irving",
    "sg:classifiers":[
        {
            "category":"Health Services",
            "subcategory":"Doctor",
            "type":"Services"
        }
    ],
    "sg:phone":"+1 972 253 5000",
    "sg:postcode":"75061",
    "sg:province":"TX",
    "wof:name":"Fanous Elia MD",
    "wof:placetype":"venue"
},
  "geometry": {"coordinates":[-96.95937600000001,32.834846],"type":"Point"}
}