{
  "type": "Feature",
  "properties": {
    "iso:country":"US",
    "sg:address":"8065 State Hwy 97",
    "sg:city":"Bebe",
    "sg:classifiers":[
        {
            "category":"Professional",
            "subcategory":"Management & Consulting",
            "type":"Services"
        },
        {
            "category":"Professional",
            "subcategory":"Computer Services",
            "type":"Services"
        }
    ],
    "sg:phone":"+1 830 437 2424",
    "sg:postcode":"78614",
    "sg:province":"TX",
    "sg:tags":[
        "consultant",
        "designer",
        "business"
    ],
    "wof:name":"Cyte Consulting Group LLC",
    "wof:placetype":"venue"
},
  "geometry": {"coordinates":[-97.65649999999999,29.401051],"type":"Point"}
}