{
  "type": "Feature",
  "properties": {
    "iso:country":"US",
    "sg:address":"4401 N Elm St",
    "sg:city":"Denton",
    "sg:classifiers":[
        {
            "category":"Manufacturing",
            "subcategory":"Metals",
            "type":"Manufacturing & Wholesale Goods"
        },
        {
            "category":"Manufacturing",
            "subcategory":"Retail Goods",
            "type":"Manufacturing & Wholesale Goods"
        },
        {
            "category":"Manufacturing",
            "subcategory":"Building Materials",
            "type":"Manufacturing & Wholesale Goods"
        }
    ],
    "sg:phone":"+1 940 243 4491",
    "sg:postcode":"76207",
    "sg:province":"TX",
    "sg:tags":[
        "product",
        "manufacturer",
        "aluminum",
        "aluminum-wholesale"
    ],
    "sg:website":"http://www.alcoa.com",
    "wof:name":"Alcoa",
    "wof:placetype":"venue"
},
  "geometry": {"coordinates":[-97.16397600000001,33.256662],"type":"Point"}
}