{
  "type": "Feature",
  "properties": {
    "iso:country":"US",
    "sg:address":"6100 Western Pl",
    "sg:city":"Fort Worth",
    "sg:classifiers":[
        {
            "category":"Health Services",
            "subcategory":"Clinic",
            "type":"Services"
        }
    ],
    "sg:phone":"+1 817 870 2795",
    "sg:postcode":"76107",
    "sg:province":"TX",
    "sg:tags":[
        "hospice"
    ],
    "wof:name":"Saint Pauls Hospice",
    "wof:placetype":"venue"
},
  "geometry": {"coordinates":[-97.41663699999999,32.735051],"type":"Point"}
}