{
  "type": "Feature",
  "properties": {
    "iso:country":"US",
    "sg:address":"700 Center St",
    "sg:city":"Deer Park",
    "sg:classifiers":[
        {
            "category":"Local Transit",
            "type":"Transportation"
        }
    ],
    "sg:phone":"+1 281 479 0288",
    "sg:postcode":"77536",
    "sg:province":"TX",
    "sg:tags":[
        "limousine"
    ],
    "wof:name":"Antique Bentley Rental",
    "wof:placetype":"venue"
},
  "geometry": {"coordinates":[-95.123914,29.705792],"type":"Point"}
}