{
  "type": "Feature",
  "properties": {
    "iso:country":"US",
    "sg:address":"6138 Sunset Haven St",
    "sg:city":"San Antonio",
    "sg:classifiers":[
        {
            "category":"Retail",
            "subcategory":"Auto Repair",
            "type":"Services"
        }
    ],
    "sg:phone":"+1 210 690 8843",
    "sg:postcode":"78249",
    "sg:province":"TX",
    "sg:tags":[
        "general"
    ],
    "wof:name":"Direct Current Automotive Elec",
    "wof:placetype":"venue"
},
  "geometry": {"coordinates":[-98.607478,29.556717],"type":"Point"}
}