{
  "type": "Feature",
  "properties": {
    "iso:country":"US",
    "sg:address":"3035 Knickerbocker Rd",
    "sg:city":"San Angelo",
    "sg:classifiers":[
        {
            "category":"Organizations",
            "subcategory":"Community Association",
            "type":"Services"
        }
    ],
    "sg:phone":"+1 325 947 5906",
    "sg:postcode":"76904",
    "sg:province":"TX",
    "sg:tags":[
        "club"
    ],
    "wof:name":"Club Hypnotic",
    "wof:placetype":"venue"
},
  "geometry": {"coordinates":[-100.46401299999999,31.424828],"type":"Point"}
}