{
  "type": "Feature",
  "properties": {
    "iso:country":"US",
    "sg:address":"201 S 23rd St",
    "sg:city":"Mcallen",
    "sg:classifiers":[
        {
            "category":"Personal",
            "subcategory":"Beauty Salon",
            "type":"Services"
        }
    ],
    "sg:phone":"+1 956 682 6073",
    "sg:postcode":"78501",
    "sg:province":"TX",
    "sg:tags":[
        "shop"
    ],
    "wof:name":"Modern Style Beauty Salon",
    "wof:placetype":"venue"
},
  "geometry": {"coordinates":[-98.24560099999999,26.203053],"type":"Point"}
}