{
  "type": "Feature",
  "properties": {
    "iso:country":"US",
    "sg:address":"6 Green Slope Pl",
    "sg:city":"Spring",
    "sg:classifiers":[
        {
            "category":"Arts & Performance",
            "subcategory":"Theater",
            "type":"Entertainment"
        }
    ],
    "sg:phone":"+1 281 367 8431",
    "sg:postcode":"77381",
    "sg:province":"TX",
    "sg:tags":[
        "group"
    ],
    "wof:name":"Pegasus Ix",
    "wof:placetype":"venue"
},
  "geometry": {"coordinates":[-95.51594,30.178664],"type":"Point"}
}