{
  "type": "Feature",
  "properties": {
    "iso:country":"US",
    "sg:address":"3808 S 1st Street",
    "sg:city":"Austin",
    "sg:classifiers":[
        {
            "category":"Professional",
            "subcategory":"Lawyer & Legal Services",
            "type":"Services"
        }
    ],
    "sg:phone":"+1 512 322 0707",
    "sg:postcode":"78704",
    "sg:province":"TX",
    "wof:name":"Law Office of Travis Williamson & Associates",
    "wof:placetype":"venue"
},
  "geometry": {"coordinates":[-97.768652,30.22806],"type":"Point"}
}