{
  "type": "Feature",
  "properties": {
    "iso:country":"US",
    "sg:address":"941 Overdowns Dr",
    "sg:city":"Plano",
    "sg:classifiers":[
        {
            "category":"Professional",
            "subcategory":"Art Services",
            "type":"Services"
        }
    ],
    "sg:phone":"+1 972 423 6472",
    "sg:postcode":"75023",
    "sg:province":"TX",
    "sg:tags":[
        "commercial",
        "graphic",
        "design"
    ],
    "wof:name":"Tom Galiardo Illustration",
    "wof:placetype":"venue"
},
  "geometry": {"coordinates":[-96.71253299999999,33.053145],"type":"Point"}
}