{
  "type": "Feature",
  "properties": {
    "iso:country":"US",
    "sg:address":"9575 Katy Fwy Ste 100",
    "sg:city":"Houston",
    "sg:classifiers":[
        {
            "category":"Professional",
            "subcategory":"Accounting & Tax Preparation",
            "type":"Services"
        }
    ],
    "sg:phone":"+1 713 827 8184",
    "sg:postcode":"77024",
    "sg:province":"TX",
    "sg:tags":[
        "accountant"
    ],
    "wof:name":"Pittman Travis Dale CPA",
    "wof:placetype":"venue"
},
  "geometry": {"coordinates":[-95.53029600000001,29.7838],"type":"Point"}
}