{
  "type": "Feature",
  "properties": {
    "iso:country":"US",
    "sg:address":"2777 Irving Blvd",
    "sg:city":"Dallas",
    "sg:classifiers":[
        {
            "category":"Professional",
            "subcategory":"Secretarial Services",
            "type":"Services"
        },
        {
            "category":"Professional",
            "subcategory":"Employment Agencies",
            "type":"Services"
        }
    ],
    "sg:phone":"+1 214 741 4944",
    "sg:postcode":"75207",
    "sg:province":"TX",
    "sg:tags":[
        "typing"
    ],
    "wof:name":"Dallas Secretaries",
    "wof:placetype":"venue"
},
  "geometry": {"coordinates":[-96.845698,32.805946],"type":"Point"}
}