{
  "type": "Feature",
  "properties": {
    "iso:country":"US",
    "sg:address":"1816 Double Barrel Rd",
    "sg:city":"Bronte",
    "sg:classifiers":[
        {
            "category":"Wholesale",
            "subcategory":"Construction Materials",
            "type":"Manufacturing & Wholesale Goods"
        }
    ],
    "sg:phone":"+1 325 473 2090",
    "sg:postcode":"76933",
    "sg:province":"TX",
    "sg:tags":[
        "sand",
        "gravel"
    ],
    "wof:name":"Sanco Materials",
    "wof:placetype":"venue"
},
  "geometry": {"coordinates":[-100.365166,31.876783],"type":"Point"}
}