{
  "type": "Feature",
  "properties": {
    "iso:country":"US",
    "sg:address":"316 S Travis St",
    "sg:city":"Amarillo",
    "sg:classifiers":[
        {
            "category":"Home & Garden",
            "subcategory":"Building Materials",
            "type":"Retail Goods"
        }
    ],
    "sg:phone":"+1 806 373 0820",
    "sg:postcode":"79106",
    "sg:province":"TX",
    "sg:tags":[
        "glass",
        "window",
        "plate"
    ],
    "wof:name":"Glass Inc",
    "wof:placetype":"venue"
},
  "geometry": {"coordinates":[-101.854283,35.212179],"type":"Point"}
}