{
  "type": "Feature",
  "properties": {
    "iso:country":"US",
    "sg:address":"1704 Seamist Dr Ste 450",
    "sg:city":"Houston",
    "sg:classifiers":[
        {
            "category":"Professional",
            "subcategory":"Accounting & Tax Preparation",
            "type":"Services"
        }
    ],
    "sg:phone":"+1 713 863 7599",
    "sg:postcode":"77008",
    "sg:province":"TX",
    "sg:tags":[
        "accountant"
    ],
    "wof:name":"Lindsay Richard P PC CPA",
    "wof:placetype":"venue"
},
  "geometry": {"coordinates":[-95.43789700000001,29.7999],"type":"Point"}
}