{
  "type": "Feature",
  "properties": {
    "iso:country":"US",
    "sg:address":"3829 Old College Rd",
    "sg:city":"Bryan",
    "sg:classifiers":[
        {
            "category":"Building & Trades",
            "subcategory":"Construction",
            "type":"Services"
        }
    ],
    "sg:phone":"+1 979 846 7606",
    "sg:postcode":"77801",
    "sg:province":"TX",
    "sg:tags":[
        "water",
        "control",
        "pollution"
    ],
    "wof:name":"American Backflow Prev Assoc",
    "wof:placetype":"venue"
},
  "geometry": {"coordinates":[-96.354309,30.632294],"type":"Point"}
}