{
  "type": "Feature",
  "properties": {
    "iso:country":"US",
    "sg:address":"103 Gilvin St",
    "sg:city":"Fort Worth",
    "sg:classifiers":[
        {
            "category":"Wholesale",
            "subcategory":"Construction Materials",
            "type":"Manufacturing & Wholesale Goods"
        }
    ],
    "sg:phone":"+1 817 332 2056",
    "sg:postcode":"76102",
    "sg:province":"TX",
    "sg:tags":[
        "brick",
        "stone"
    ],
    "wof:name":"Trinity Materials Inc",
    "wof:placetype":"venue"
},
  "geometry": {"coordinates":[-97.320446,32.763003],"type":"Point"}
}