{
  "type": "Feature",
  "properties": {
    "iso:country":"US",
    "sg:address":"1721 Heron Dr",
    "sg:city":"Aubrey",
    "sg:classifiers":[
        {
            "category":"Professional",
            "subcategory":"Business Services",
            "type":"Services"
        }
    ],
    "sg:phone":"+1 972 347 1144",
    "sg:postcode":"76227",
    "sg:province":"TX",
    "sg:tags":[
        "consultant",
        "coach"
    ],
    "wof:name":"Innov8 Consulting",
    "wof:placetype":"venue"
},
  "geometry": {"coordinates":[-96.933148,33.2264],"type":"Point"}
}