{
  "type": "Feature",
  "properties": {
    "iso:country":"US",
    "sg:address":"106 Woodmont Dr",
    "sg:city":"Georgetown",
    "sg:classifiers":[
        {
            "category":"Retail",
            "subcategory":"Laundry & Dry Cleaning",
            "type":"Services"
        }
    ],
    "sg:phone":"+1 512 863 7733",
    "sg:postcode":"78628",
    "sg:province":"TX",
    "sg:tags":[
        "cleaners"
    ],
    "wof:name":"Dollars & Sense Cleaners",
    "wof:placetype":"venue"
},
  "geometry": {"coordinates":[-97.693546,30.619809],"type":"Point"}
}