{
  "type": "Feature",
  "properties": {
    "iso:country":"US",
    "sg:address":"513 South Rd",
    "sg:city":"Baytown",
    "sg:classifiers":[
        {
            "category":"Recreation",
            "type":"Entertainment"
        }
    ],
    "sg:phone":"+1 281 421 9570",
    "sg:postcode":"77521",
    "sg:province":"TX",
    "wof:name":"Baytown Batting Cages",
    "wof:placetype":"venue"
},
  "geometry": {"coordinates":[-94.96984399999999,29.784368],"type":"Point"}
}