{
  "type": "Feature",
  "properties": {
    "iso:country":"US",
    "sg:address":"5402 S 7th St",
    "sg:city":"Abilene",
    "sg:classifiers":[
        {
            "category":"Home & Garden",
            "subcategory":"Garden Supply",
            "type":"Retail Goods"
        }
    ],
    "sg:phone":"+1 325 695 7368",
    "sg:postcode":"79605",
    "sg:province":"TX",
    "wof:name":"Scj Enterprises Inc",
    "wof:placetype":"venue"
},
  "geometry": {"coordinates":[-99.796915,32.444199],"type":"Point"}
}