{
  "type": "Feature",
  "properties": {
    "iso:country":"US",
    "sg:address":"5950 Colwell Blvd",
    "sg:city":"Irving",
    "sg:classifiers":[
        {
            "category":"Professional",
            "type":"Services"
        }
    ],
    "sg:phone":"+1 972 969 3001",
    "sg:postcode":"75039",
    "sg:province":"TX",
    "sg:tags":[
        "establishment"
    ],
    "wof:name":"Trifles",
    "wof:placetype":"venue"
},
  "geometry": {"coordinates":[-96.941607,32.888926],"type":"Point"}
}