{
  "type": "Feature",
  "properties": {
    "iso:country":"US",
    "sg:address":"1805 Old Cuero Rd",
    "sg:city":"Yoakum",
    "sg:classifiers":[
        {
            "category":"Building & Trades",
            "subcategory":"Pest Control",
            "type":"Services"
        }
    ],
    "sg:phone":"+1 361 293 7823",
    "sg:postcode":"77995",
    "sg:province":"TX",
    "wof:name":"County Wide Pest Services",
    "wof:placetype":"venue"
},
  "geometry": {"coordinates":[-97.176987,29.25461],"type":"Point"}
}