{
  "type": "Feature",
  "properties": {
    "iso:country":"US",
    "sg:address":"814 Pine Valley Dr",
    "sg:city":"College Station",
    "sg:classifiers":[
        {
            "category":"Professional",
            "subcategory":"Management & Consulting",
            "type":"Services"
        }
    ],
    "sg:phone":"+1 979 690 0780",
    "sg:postcode":"77845",
    "sg:province":"TX",
    "sg:tags":[
        "business"
    ],
    "wof:name":"GK Consulting LLC",
    "wof:placetype":"venue"
},
  "geometry": {"coordinates":[-96.23685999999999,30.556483],"type":"Point"}
}