{
  "type": "Feature",
  "properties": {
    "iso:country":"US",
    "sg:address":"8801 Honeycomb Dr",
    "sg:city":"Austin",
    "sg:classifiers":[
        {
            "category":"Social Services",
            "type":"Services"
        }
    ],
    "sg:phone":"+1 512 288 1655",
    "sg:postcode":"78737",
    "sg:province":"TX",
    "sg:tags":[
        "consulting",
        "management"
    ],
    "wof:name":"Programs of Heart",
    "wof:placetype":"venue"
},
  "geometry": {"coordinates":[-97.91825799999999,30.219717],"type":"Point"}
}