{
  "type": "Feature",
  "properties": {
    "iso:country":"US",
    "sg:address":"8820 Old County Dr",
    "sg:city":"El Paso",
    "sg:classifiers":[
        {
            "category":"Real Estate",
            "subcategory":"Real Estate Operator",
            "type":"Services"
        }
    ],
    "sg:phone":"+1 915 858 2080",
    "sg:postcode":"79907",
    "sg:province":"TX",
    "sg:tags":[
        "apartment"
    ],
    "wof:name":"Graham Apartments",
    "wof:placetype":"venue"
},
  "geometry": {"coordinates":[-106.33414,31.69605],"type":"Point"}
}