{
  "type": "Feature",
  "properties": {
    "iso:country":"US",
    "sg:address":"17950 Preston Rd Ste 700",
    "sg:city":"Dallas",
    "sg:classifiers":[
        {
            "category":"Building & Trades",
            "subcategory":"Construction",
            "type":"Services"
        }
    ],
    "sg:phone":"+1 972 732 7800",
    "sg:postcode":"75252",
    "sg:province":"TX",
    "sg:tags":[
        "contractor"
    ],
    "wof:name":"Taylor Paul Homes",
    "wof:placetype":"venue"
},
  "geometry": {"coordinates":[-96.7985,32.9963],"type":"Point"}
}