{
  "type": "Feature",
  "properties": {
    "iso:country":"US",
    "sg:address":"763 Co Rd 123",
    "sg:city":"Alice",
    "sg:classifiers":[
        {
            "category":"Retail",
            "subcategory":"Auto Repair",
            "type":"Services"
        }
    ],
    "sg:phone":"+1 361 668 1873",
    "sg:postcode":"78332",
    "sg:province":"TX",
    "sg:tags":[
        "body",
        "automobile",
        "painting"
    ],
    "wof:name":"Cantu Paint & Body & Auto Svc",
    "wof:placetype":"venue"
},
  "geometry": {"coordinates":[-98.115572,27.889993],"type":"Point"}
}