{
  "type": "Feature",
  "properties": {
    "iso:country":"US",
    "sg:address":"4641 Ratliff Ln",
    "sg:city":"Addison",
    "sg:classifiers":[
        {
            "category":"Manufacturing",
            "subcategory":"Tools & Machinery",
            "type":"Manufacturing & Wholesale Goods"
        }
    ],
    "sg:phone":"+1 972 931 2010",
    "sg:postcode":"75001",
    "sg:province":"TX",
    "sg:tags":[
        "pneumatic",
        "parts",
        "hydraulic",
        "mfg"
    ],
    "wof:name":"Applied Assembly Services",
    "wof:placetype":"venue"
},
  "geometry": {"coordinates":[-96.831498,32.971249],"type":"Point"}
}