{
  "type": "Feature",
  "properties": {
    "iso:country":"US",
    "sg:address":"1207 S White Chapel Blvd",
    "sg:city":"Southlake",
    "sg:classifiers":[
        {
            "category":"Real Estate",
            "subcategory":"Real Estate Services",
            "type":"Services"
        }
    ],
    "sg:phone":"+1 817 416 0197",
    "sg:postcode":"76092",
    "sg:province":"TX",
    "sg:tags":[
        "company",
        "title"
    ],
    "wof:name":"Reunion Title",
    "wof:placetype":"venue"
},
  "geometry": {"coordinates":[-97.155896,32.926305],"type":"Point"}
}