{
  "type": "Feature",
  "properties": {
    "iso:country":"US",
    "sg:address":"3928 Coronado Dr",
    "sg:city":"Plano",
    "sg:classifiers":[
        {
            "category":"Education",
            "subcategory":"Special Training",
            "type":"Public Place"
        }
    ],
    "sg:phone":"+1 972 578 9202",
    "sg:postcode":"75074",
    "sg:province":"TX",
    "sg:tags":[
        "center"
    ],
    "wof:name":"Creative Learning Svc",
    "wof:placetype":"venue"
},
  "geometry": {"coordinates":[-96.655861,33.019888],"type":"Point"}
}