{
  "type": "Feature",
  "properties": {
    "iso:country":"US",
    "sg:address":"512 US Hwy 90",
    "sg:city":"Castroville",
    "sg:classifiers":[
        {
            "category":"Insurance",
            "subcategory":"Insurance Agent",
            "type":"Services"
        }
    ],
    "sg:phone":"+1 830 538 2232",
    "sg:postcode":"78009",
    "sg:province":"TX",
    "wof:name":"Stein Insurance",
    "wof:placetype":"venue"
},
  "geometry": {"coordinates":[-98.914632,29.348243],"type":"Point"}
}