{
  "type": "Feature",
  "properties": {
    "iso:country":"US",
    "sg:address":"2943 Oates Dr",
    "sg:city":"Dallas",
    "sg:classifiers":[
        {
            "category":"Professional",
            "subcategory":"Accounting & Tax Preparation",
            "type":"Services"
        }
    ],
    "sg:phone":"+1 972 682 1770",
    "sg:postcode":"75228",
    "sg:province":"TX",
    "sg:tags":[
        "bookkeeping",
        "general"
    ],
    "wof:name":"Professional Bookkeeping Inc",
    "wof:placetype":"venue"
},
  "geometry": {"coordinates":[-96.664349,32.821468],"type":"Point"}
}