{
  "type": "Feature",
  "properties": {
    "iso:country":"US",
    "sg:address":"1711 Canterbury St",
    "sg:city":"Austin",
    "sg:classifiers":[
        {
            "category":"Real Estate",
            "subcategory":"Architect",
            "type":"Services"
        }
    ],
    "sg:phone":"+1 512 542 9930",
    "sg:postcode":"78702",
    "sg:province":"TX",
    "sg:website":"www.bartushdesign.com",
    "wof:name":"Bartush Design",
    "wof:placetype":"venue"
},
  "geometry": {"coordinates":[-97.726645,30.255438],"type":"Point"}
}