{
  "type": "Feature",
  "properties": {
    "iso:country":"US",
    "sg:address":"510 Co Rd 403",
    "sg:city":"Mc Kinney",
    "sg:classifiers":[
        {
            "category":"Shopping",
            "subcategory":"Catalog Store",
            "type":"Retail Goods"
        }
    ],
    "sg:phone":"+1 972 562 2543",
    "sg:postcode":"75069",
    "sg:province":"TX",
    "sg:tags":[
        "mail",
        "house"
    ],
    "wof:name":"Eccollections",
    "wof:placetype":"venue"
},
  "geometry": {"coordinates":[-96.54806499999999,33.182367],"type":"Point"}
}