{
  "type": "Feature",
  "properties": {
    "iso:country":"US",
    "sg:address":"11118 Dessau Rd",
    "sg:city":"Austin",
    "sg:classifiers":[
        {
            "category":"Organizations",
            "subcategory":"Religious Organization",
            "type":"Services"
        }
    ],
    "sg:phone":"+1 512 339 8675",
    "sg:postcode":"78754",
    "sg:province":"TX",
    "wof:name":"Austin Chinese Church",
    "wof:placetype":"venue"
},
  "geometry": {"coordinates":[-97.66664,30.371472],"type":"Point"}
}