{
  "type": "Feature",
  "properties": {
    "iso:country":"US",
    "sg:address":"1001 Texas St",
    "sg:city":"Houston",
    "sg:classifiers":[
        {
            "category":"Restaurant",
            "type":"Food & Drink"
        }
    ],
    "sg:menulink":"http://www.allmenus.com/tx/houston/139510-quiznos-sub/menu/",
    "sg:phone":"+1 713 226 8265",
    "sg:postcode":"77002",
    "sg:province":"TX",
    "sg:tags":[
        "wrap",
        "american",
        "sandwich"
    ],
    "wof:name":"Quiznos Sub",
    "wof:placetype":"venue"
},
  "geometry": {"coordinates":[-95.362115,29.760047],"type":"Point"}
}