{
  "type": "Feature",
  "properties": {
    "iso:country":"US",
    "sg:address":"320 W 7th St",
    "sg:city":"Dallas",
    "sg:classifiers":[
        {
            "category":"Manufacturing",
            "subcategory":"Food",
            "type":"Manufacturing & Wholesale Goods"
        }
    ],
    "sg:phone":"+1 214 943 8334",
    "sg:postcode":"75208",
    "sg:province":"TX",
    "sg:tags":[
        "candy",
        "mfg"
    ],
    "wof:name":"Plantation Hse Dining & Tea Rm",
    "wof:placetype":"venue"
},
  "geometry": {"coordinates":[-96.82756500000001,32.74886],"type":"Point"}
}