{
  "type": "Feature",
  "properties": {
    "iso:country":"US",
    "sg:address":"7815 Mainland Dr",
    "sg:city":"San Antonio",
    "sg:classifiers":[
        {
            "category":"Wholesale",
            "subcategory":"Durable Goods & Equipment",
            "type":"Manufacturing & Wholesale Goods"
        }
    ],
    "sg:phone":"+1 210 521 4753",
    "sg:postcode":"78250",
    "sg:province":"TX",
    "wof:name":"Vinyl Expressions",
    "wof:placetype":"venue"
},
  "geometry": {"coordinates":[-98.640896,29.510908],"type":"Point"}
}