{
  "type": "Feature",
  "properties": {
    "iso:country":"US",
    "sg:address":"8816 Directors Row",
    "sg:city":"Dallas",
    "sg:classifiers":[
        {
            "category":"Shopping",
            "subcategory":"Crafts & Fabrics",
            "type":"Retail Goods"
        }
    ],
    "sg:phone":"+1 214 630 9616",
    "sg:postcode":"75247",
    "sg:province":"TX",
    "sg:tags":[
        "art",
        "supply"
    ],
    "wof:name":"Rotex Company",
    "wof:placetype":"venue"
},
  "geometry": {"coordinates":[-96.887901,32.8167],"type":"Point"}
}