{
  "type": "Feature",
  "properties": {
    "iso:country":"US",
    "sg:address":"260 Sunday Cir",
    "sg:city":"Fredericksburg",
    "sg:classifiers":[
        {
            "category":"Professional",
            "type":"Services"
        }
    ],
    "sg:phone":"+1 830 990 4341",
    "sg:postcode":"78624",
    "sg:province":"TX",
    "wof:name":"Kirk Designs",
    "wof:placetype":"venue"
},
  "geometry": {"coordinates":[-98.850638,30.243799],"type":"Point"}
}