{
  "type": "Feature",
  "properties": {
    "iso:country":"US",
    "sg:address":"4400 N Fwy Spc B200",
    "sg:city":"Houston",
    "sg:classifiers":[
        {
            "category":"Shopping",
            "subcategory":"Clothing, Apparel, & Fashions",
            "type":"Retail Goods"
        }
    ],
    "sg:phone":"+1 713 692 6051",
    "sg:postcode":"77022",
    "sg:province":"TX",
    "sg:tags":[
        "men's",
        "clothing"
    ],
    "sg:website":"www.alsformalwear.com",
    "wof:name":"Al's Formal Wear",
    "wof:placetype":"venue"
},
  "geometry": {"coordinates":[-95.38308499999999,29.831326],"type":"Point"}
}