{
  "type": "Feature",
  "properties": {
    "iso:country":"US",
    "sg:address":"717 W Lamar St",
    "sg:city":"Sherman",
    "sg:classifiers":[
        {
            "category":"Manufacturing",
            "subcategory":"Food",
            "type":"Manufacturing & Wholesale Goods"
        },
        {
            "category":"Food & Beverages",
            "subcategory":"Bakery",
            "type":"Retail Goods"
        }
    ],
    "sg:phone":"+1 903 893 1061",
    "sg:postcode":"75092",
    "sg:province":"TX",
    "sg:tags":[
        "product",
        "restaurant",
        "doughnut",
        "mfg"
    ],
    "wof:name":"Hot & Creamy Donuts",
    "wof:placetype":"venue"
},
  "geometry": {"coordinates":[-96.616567,33.634016],"type":"Point"}
}