{
  "type": "Feature",
  "properties": {
    "iso:country":"US",
    "sg:address":"213 Turtle Creek Dr",
    "sg:city":"Belton",
    "sg:classifiers":[
        {
            "category":"Wholesale",
            "subcategory":"Chemicals & Plastics",
            "type":"Manufacturing & Wholesale Goods"
        }
    ],
    "sg:phone":"+1 254 939 7577",
    "sg:postcode":"76513",
    "sg:province":"TX",
    "wof:name":"Sharon Ellis",
    "wof:placetype":"venue"
},
  "geometry": {"coordinates":[-97.454708,31.072863],"type":"Point"}
}