{
  "type": "Feature",
  "properties": {
    "iso:country":"US",
    "sg:address":"1601 Elm St",
    "sg:city":"Dallas",
    "sg:classifiers":[
        {
            "category":"Restaurant",
            "type":"Food & Drink"
        }
    ],
    "sg:phone":"+1 214 220 9008",
    "sg:postcode":"75201",
    "sg:province":"TX",
    "sg:tags":[
        "delicatessen"
    ],
    "wof:name":"Murphy's Deli",
    "wof:placetype":"venue"
},
  "geometry": {"coordinates":[-96.79733299999999,32.781836],"type":"Point"}
}