{
  "type": "Feature",
  "properties": {
    "iso:country":"US",
    "sg:address":"1303 Taymouth Dr",
    "sg:city":"Spring",
    "sg:classifiers":[
        {
            "category":"Professional",
            "type":"Services"
        }
    ],
    "sg:phone":"+1 281 363 4420",
    "sg:postcode":"77386",
    "sg:province":"TX",
    "wof:name":"Infinet Web Works LLC",
    "wof:placetype":"venue"
},
  "geometry": {"coordinates":[-95.42191699999999,30.138339],"type":"Point"}
}