{
  "type": "Feature",
  "properties": {
    "iso:country":"US",
    "sg:address":"815 Palm Grove Cir",
    "sg:city":"Sugar Land",
    "sg:classifiers":[
        {
            "category":"Professional",
            "subcategory":"Engineering",
            "type":"Services"
        }
    ],
    "sg:phone":"+1 281 491 4770",
    "sg:postcode":"77478",
    "sg:province":"TX",
    "wof:name":"F & S Consulting",
    "wof:placetype":"venue"
},
  "geometry": {"coordinates":[-95.624664,29.631867],"type":"Point"}
}