{
  "type": "Feature",
  "properties": {
    "iso:country":"US",
    "sg:address":"3500 Maple Ave Ste 210",
    "sg:city":"Dallas",
    "sg:classifiers":[
        {
            "category":"Communications",
            "subcategory":"Newspaper",
            "type":"Services"
        }
    ],
    "sg:phone":"+1 214 526 1983",
    "sg:postcode":"75219",
    "sg:province":"TX",
    "sg:website":"http://www.nytco.com",
    "wof:name":"The New York Times Company",
    "wof:placetype":"venue"
},
  "geometry": {"coordinates":[-96.811722,32.801899],"type":"Point"}
}