{
  "type": "Feature",
  "properties": {
    "iso:country":"US",
    "sg:address":"1723 Hidden Villas Dr",
    "sg:city":"Humble",
    "sg:classifiers":[
        {
            "category":"Professional",
            "type":"Services"
        }
    ],
    "sg:phone":"+1 281 358 8386",
    "sg:postcode":"77339",
    "sg:province":"TX",
    "wof:name":"Bohdana",
    "wof:placetype":"venue"
},
  "geometry": {"coordinates":[-95.221079,30.041565],"type":"Point"}
}