{
  "type": "Feature",
  "properties": {
    "iso:country":"US",
    "sg:address":"2307 Spencer Hwy",
    "sg:city":"Pasadena",
    "sg:classifiers":[
        {
            "category":"Education",
            "subcategory":"Special Training",
            "type":"Public Place"
        }
    ],
    "sg:phone":"+1 832 386 9722",
    "sg:postcode":"77504",
    "sg:province":"TX",
    "sg:tags":[
        "school",
        "language"
    ],
    "wof:name":"Ingles Individual Pasadena",
    "wof:placetype":"venue"
},
  "geometry": {"coordinates":[-95.205399,29.6649],"type":"Point"}
}