{
  "type": "Feature",
  "properties": {
    "iso:country":"US",
    "sg:address":"104 Bluebonnet Cir",
    "sg:city":"Mesquite",
    "sg:classifiers":[
        {
            "category":"Insurance",
            "subcategory":"Insurance Agent",
            "type":"Services"
        }
    ],
    "sg:phone":"+1 972 203 1724",
    "sg:postcode":"75182",
    "sg:province":"TX",
    "wof:name":"Brazos Risk Consulting",
    "wof:placetype":"venue"
},
  "geometry": {"coordinates":[-96.578048,32.792288],"type":"Point"}
}