{
  "type": "Feature",
  "properties": {
    "iso:country":"US",
    "sg:address":"718 NE 29th St",
    "sg:city":"Grand Prairie",
    "sg:classifiers":[
        {
            "category":"Building & Trades",
            "subcategory":"Cleaning & Sanitation",
            "type":"Services"
        }
    ],
    "sg:phone":"+1 972 264 6284",
    "sg:postcode":"75050",
    "sg:province":"TX",
    "sg:tags":[
        "maintenance"
    ],
    "wof:name":"Eagle Custodial",
    "wof:placetype":"venue"
},
  "geometry": {"coordinates":[-96.961398,32.757801],"type":"Point"}
}