{
  "type": "Feature",
  "properties": {
    "iso:country":"US",
    "sg:address":"2607 Blue Ridge Dr",
    "sg:city":"Edinburg",
    "sg:classifiers":[
        {
            "category":"Professional",
            "subcategory":"Detective & Security Services",
            "type":"Services"
        }
    ],
    "sg:phone":"+1 956 451 3165",
    "sg:postcode":"78539",
    "sg:province":"TX",
    "sg:tags":[
        "information",
        "bureau"
    ],
    "wof:name":"Servin Enterprises",
    "wof:placetype":"venue"
},
  "geometry": {"coordinates":[-98.17234500000001,26.277646],"type":"Point"}
}