{
  "type": "Feature",
  "properties": {
    "iso:country":"US",
    "sg:address":"8400 N Mo Pac Expy",
    "sg:city":"Austin",
    "sg:classifiers":[
        {
            "category":"Professional",
            "type":"Services"
        }
    ],
    "sg:phone":"+1 512 346 1382",
    "sg:postcode":"78759",
    "sg:province":"TX",
    "wof:name":"Bean Kimes & Moseley",
    "wof:placetype":"venue"
},
  "geometry": {"coordinates":[-97.741778,30.371303],"type":"Point"}
}