{
  "type": "Feature",
  "properties": {
    "iso:country":"US",
    "sg:address":"6512 Co Rd 4061",
    "sg:city":"Scurry",
    "sg:classifiers":[
        {
            "category":"Building & Trades",
            "subcategory":"Electrical",
            "type":"Services"
        }
    ],
    "sg:phone":"+1 972 452 3460",
    "sg:postcode":"75158",
    "sg:province":"TX",
    "sg:tags":[
        "electrical",
        "contractor"
    ],
    "wof:name":"Erb S Electric",
    "wof:placetype":"venue"
},
  "geometry": {"coordinates":[-96.35243199999999,32.449755],"type":"Point"}
}