{
  "type": "Feature",
  "properties": {
    "iso:country":"US",
    "sg:address":"1806 Avenue L",
    "sg:city":"Galveston",
    "sg:classifiers":[
        {
            "category":"Manufacturing",
            "subcategory":"Jewelry",
            "type":"Manufacturing & Wholesale Goods"
        },
        {
            "category":"Retail",
            "subcategory":"Repair Shop",
            "type":"Services"
        },
        {
            "category":"Shopping",
            "subcategory":"Jewelry",
            "type":"Retail Goods"
        }
    ],
    "sg:phone":"+1 409 763 2707",
    "sg:postcode":"77550",
    "sg:province":"TX",
    "sg:tags":[
        "repairing",
        "jeweler",
        "designer",
        "watch",
        "clock"
    ],
    "wof:name":"Gregory's Clock & Watch Repair",
    "wof:placetype":"venue"
},
  "geometry": {"coordinates":[-94.78569400000001,29.299731],"type":"Point"}
}