{
  "type": "Feature",
  "properties": {
    "iso:country":"US",
    "sg:address":"15707 Knollpoint",
    "sg:city":"San Antonio",
    "sg:classifiers":[
        {
            "category":"Wholesale",
            "subcategory":"Non-durable Goods",
            "type":"Manufacturing & Wholesale Goods"
        }
    ],
    "sg:phone":"+1 210 241 6127",
    "sg:postcode":"78247",
    "sg:province":"TX",
    "sg:tags":[
        "advertising"
    ],
    "wof:name":"Specialty Printing",
    "wof:placetype":"venue"
},
  "geometry": {"coordinates":[-98.414276,29.584287],"type":"Point"}
}