{
  "type": "Feature",
  "properties": {
    "iso:country":"US",
    "sg:address":"8706 Airport Fwy",
    "sg:city":"Hurst",
    "sg:classifiers":[
        {
            "category":"Personal",
            "subcategory":"Nail Salon",
            "type":"Services"
        }
    ],
    "sg:phone":"+1 817 788 0551",
    "sg:postcode":"76053",
    "sg:province":"TX",
    "wof:name":"Nail 1",
    "wof:placetype":"venue"
},
  "geometry": {"coordinates":[-97.19542300000001,32.836726],"type":"Point"}
}