{
  "type": "Feature",
  "properties": {
    "iso:country":"US",
    "sg:address":"116 W Church St",
    "sg:city":"Livingston",
    "sg:classifiers":[
        {
            "category":"Shopping",
            "subcategory":"Computers & Home Electronics",
            "type":"Retail Goods"
        }
    ],
    "sg:phone":"+1 936 327 4145",
    "sg:postcode":"77351",
    "sg:province":"TX",
    "sg:tags":[
        "equipment",
        "dealer"
    ],
    "wof:name":"Computer Store",
    "wof:placetype":"venue"
},
  "geometry": {"coordinates":[-94.93364099999999,30.711085],"type":"Point"}
}