{
  "type": "Feature",
  "properties": {
    "iso:country":"US",
    "sg:address":"3201 E Pioneer Pkwy",
    "sg:city":"Arlington",
    "sg:classifiers":[
        {
            "category":"Freight",
            "type":"Transportation"
        }
    ],
    "sg:phone":"+1 817 652 1604",
    "sg:postcode":"76010",
    "sg:province":"TX",
    "sg:tags":[
        "operator",
        "local",
        "trucking"
    ],
    "wof:name":"Zekes Trucking",
    "wof:placetype":"venue"
},
  "geometry": {"coordinates":[-97.04882499999999,32.712159],"type":"Point"}
}