{
  "type": "Feature",
  "properties": {
    "iso:country":"US",
    "sg:address":"300 Bridlewood Ct",
    "sg:city":"Irving",
    "sg:classifiers":[
        {
            "category":"Professional",
            "subcategory":"Lawyer & Legal Services",
            "type":"Services"
        }
    ],
    "sg:phone":"+1 972 506 9266",
    "sg:postcode":"75063",
    "sg:province":"TX",
    "wof:name":"Law Office of Rsmary C Prlmter",
    "wof:placetype":"venue"
},
  "geometry": {"coordinates":[-96.979249,32.908938],"type":"Point"}
}