{
  "type": "Feature",
  "properties": {
    "iso:country":"US",
    "sg:address":"600 Santa Isabel Blvd",
    "sg:city":"Port Isabel",
    "sg:classifiers":[
        {
            "category":"Utilities",
            "subcategory":"Refuse",
            "type":"Services"
        }
    ],
    "sg:phone":"+1 956 943 4556",
    "sg:postcode":"78578",
    "sg:province":"TX",
    "sg:tags":[
        "disposal",
        "janitorial",
        "collection",
        "l"
    ],
    "wof:name":"Inland Service Corporation",
    "wof:placetype":"venue"
},
  "geometry": {"coordinates":[-97.29095100000001,26.101568],"type":"Point"}
}