{
  "type": "Feature",
  "properties": {
    "iso:country":"US",
    "sg:address":"137 E Houston St",
    "sg:city":"Jasper",
    "sg:classifiers":[
        {
            "category":"Shopping",
            "subcategory":"Department Store",
            "type":"Retail Goods"
        },
        {
            "category":"Shopping",
            "subcategory":"Clothing, Apparel, & Fashions",
            "type":"Retail Goods"
        },
        {
            "category":"Shopping",
            "subcategory":"Shoes",
            "type":"Retail Goods"
        }
    ],
    "sg:phone":"+1 409 384 4332",
    "sg:postcode":"75951",
    "sg:province":"TX",
    "sg:tags":[
        "clothing"
    ],
    "wof:name":"Ashy P N Store",
    "wof:placetype":"venue"
},
  "geometry": {"coordinates":[-94.000165,30.920766],"type":"Point"}
}