{
  "type": "Feature",
  "properties": {
    "iso:country":"US",
    "sg:address":"3919 Washington Ave",
    "sg:city":"Houston",
    "sg:classifiers":[
        {
            "category":"Wholesale",
            "subcategory":"Motor Vehicles",
            "type":"Manufacturing & Wholesale Goods"
        }
    ],
    "sg:phone":"+1 713 862 3062",
    "sg:postcode":"77007",
    "sg:province":"TX",
    "sg:tags":[
        "automobile",
        "used"
    ],
    "wof:name":"Scheffler Motor Sales",
    "wof:placetype":"venue"
},
  "geometry": {"coordinates":[-95.400645,29.769846],"type":"Point"}
}