{
  "type": "Feature",
  "properties": {
    "iso:country":"US",
    "sg:address":"105 Market St",
    "sg:city":"Louise",
    "sg:classifiers":[
        {
            "category":"Food & Beverages",
            "subcategory":"Groceries & Convenience Stores",
            "type":"Retail Goods"
        }
    ],
    "sg:phone":"+1 979 648 2222",
    "sg:postcode":"77455",
    "sg:province":"TX",
    "sg:tags":[
        "grocer"
    ],
    "wof:name":"Sablatura's Food Craft Grocery",
    "wof:placetype":"venue"
},
  "geometry": {"coordinates":[-96.410325,29.108417],"type":"Point"}
}