{
  "type": "Feature",
  "properties": {
    "iso:country":"US",
    "sg:address":"108 Jasmine St",
    "sg:city":"Bridge City",
    "sg:classifiers":[
        {
            "category":"Shopping",
            "subcategory":"Discount & Variety Stores",
            "type":"Retail Goods"
        }
    ],
    "sg:phone":"+1 409 735 2345",
    "sg:postcode":"77611",
    "sg:province":"TX",
    "sg:tags":[
        "merchandise",
        "general"
    ],
    "wof:name":"Cjs Treasures",
    "wof:placetype":"venue"
},
  "geometry": {"coordinates":[-93.84045500000001,30.009026],"type":"Point"}
}