{
  "type": "Feature",
  "properties": {
    "iso:country":"US",
    "sg:address":"2432 Randolph St",
    "sg:city":"Dallas",
    "sg:classifiers":[
        {
            "category":"Professional",
            "subcategory":"Employment Agencies",
            "type":"Services"
        }
    ],
    "sg:phone":"+1 214 559 9888",
    "sg:postcode":"75241",
    "sg:province":"TX",
    "sg:tags":[
        "consultant"
    ],
    "wof:name":"Green & Assoc",
    "wof:placetype":"venue"
},
  "geometry": {"coordinates":[-96.781898,32.685573],"type":"Point"}
}