{
  "type": "Feature",
  "properties": {
    "iso:country":"US",
    "sg:address":"1316 State Hwy 42 S",
    "sg:city":"White Oak",
    "sg:classifiers":[
        {
            "category":"Building & Trades",
            "subcategory":"Cleaning & Sanitation",
            "type":"Services"
        }
    ],
    "sg:phone":"+1 903 572 7033",
    "sg:postcode":"75693",
    "sg:province":"TX",
    "wof:name":"Service Master Services",
    "wof:placetype":"venue"
},
  "geometry": {"coordinates":[-94.850874,32.517303],"type":"Point"}
}