{
  "type": "Feature",
  "properties": {
    "iso:country":"US",
    "sg:address":"4807 13th St",
    "sg:city":"Lubbock",
    "sg:classifiers":[
        {
            "category":"Shopping",
            "subcategory":"Clothing, Apparel, & Fashions",
            "type":"Retail Goods"
        }
    ],
    "sg:phone":"+1 806 792 3664",
    "sg:postcode":"79416",
    "sg:province":"TX",
    "sg:tags":[
        "clothing",
        "store"
    ],
    "wof:name":"Brenda Mcneil Amway",
    "wof:placetype":"venue"
},
  "geometry": {"coordinates":[-101.915038,33.584382],"type":"Point"}
}