{
  "type": "Feature",
  "properties": {
    "iso:country":"US",
    "sg:address":"6308 Co Rd 7440",
    "sg:city":"Lubbock",
    "sg:classifiers":[
        {
            "category":"Professional",
            "subcategory":"Business Services",
            "type":"Services"
        }
    ],
    "sg:phone":"+1 806 794 1755",
    "sg:postcode":"79424",
    "sg:province":"TX",
    "wof:name":"Capital Appraisal Group",
    "wof:placetype":"venue"
},
  "geometry": {"coordinates":[-101.953248,33.467694],"type":"Point"}
}