{
  "type": "Feature",
  "properties": {
    "iso:country":"US",
    "sg:address":"6719 Stella Link Rd",
    "sg:city":"Houston",
    "sg:classifiers":[
        {
            "category":"Manufacturing",
            "subcategory":"Wood Products",
            "type":"Manufacturing & Wholesale Goods"
        }
    ],
    "sg:phone":"+1 713 664 0330",
    "sg:postcode":"77005",
    "sg:province":"TX",
    "sg:tags":[
        "mfg"
    ],
    "wof:name":"Speedy Picture Framing",
    "wof:placetype":"venue"
},
  "geometry": {"coordinates":[-95.440147,29.706971],"type":"Point"}
}