{
  "type": "Feature",
  "properties": {
    "iso:country":"US",
    "sg:address":"3468 Co Rd 304",
    "sg:city":"Elgin",
    "sg:classifiers":[
        {
            "category":"Retail",
            "subcategory":"Portrait Studio",
            "type":"Services"
        }
    ],
    "sg:phone":"+1 512 856 2855",
    "sg:postcode":"78621",
    "sg:province":"TX",
    "sg:tags":[
        "photographer"
    ],
    "wof:name":"John Adamek Photography",
    "wof:placetype":"venue"
},
  "geometry": {"coordinates":[-97.238519,30.427784],"type":"Point"}
}