{
  "type": "Feature",
  "properties": {
    "iso:country":"US",
    "sg:address":"250 W Jefferson Blvd",
    "sg:city":"Dallas",
    "sg:classifiers":[
        {
            "category":"Shopping",
            "subcategory":"Optical Goods",
            "type":"Retail Goods"
        },
        {
            "category":"Health Services",
            "subcategory":"Doctor",
            "type":"Services"
        }
    ],
    "sg:phone":"+1 214 946 8131",
    "sg:postcode":"75208",
    "sg:province":"TX",
    "sg:tags":[
        "medical",
        "optician",
        "eyewear"
    ],
    "wof:name":"Optical Clinic",
    "wof:placetype":"venue"
},
  "geometry": {"coordinates":[-96.82620199999999,32.743198],"type":"Point"}
}