{
  "type": "Feature",
  "properties": {
    "iso:country":"US",
    "sg:address":"10300 N Central Expy",
    "sg:city":"Dallas",
    "sg:classifiers":[
        {
            "category":"Personal",
            "subcategory":"Massage",
            "type":"Services"
        }
    ],
    "sg:phone":"+1 214 360 4768",
    "sg:postcode":"75231",
    "sg:province":"TX",
    "sg:tags":[
        "therapist"
    ],
    "wof:name":"Massage By Design",
    "wof:placetype":"venue"
},
  "geometry": {"coordinates":[-96.769682,32.885975],"type":"Point"}
}