{
  "type": "Feature",
  "properties": {
    "iso:country":"US",
    "sg:address":"10429 Cobb Rd",
    "sg:city":"Bryan",
    "sg:classifiers":[
        {
            "category":"Farming",
            "subcategory":"Livestock Farm",
            "type":"Manufacturing & Wholesale Goods"
        }
    ],
    "sg:phone":"+1 979 589 2464",
    "sg:postcode":"77808",
    "sg:province":"TX",
    "sg:tags":[
        "beef",
        "feedlot",
        "cattle"
    ],
    "wof:name":"Winn Cattle Co",
    "wof:placetype":"venue"
},
  "geometry": {"coordinates":[-96.20697,30.72501],"type":"Point"}
}