{
  "type": "Feature",
  "properties": {
    "iso:country":"US",
    "sg:address":"819 S 3rd St",
    "sg:city":"Richmond",
    "sg:classifiers":[
        {
            "category":"Building & Trades",
            "subcategory":"Construction",
            "type":"Services"
        }
    ],
    "sg:phone":"+1 281 344 0366",
    "sg:postcode":"77469",
    "sg:province":"TX",
    "sg:tags":[
        "house"
    ],
    "wof:name":"American Home & Patio",
    "wof:placetype":"venue"
},
  "geometry": {"coordinates":[-95.75885599999999,29.57857],"type":"Point"}
}