{
  "type": "Feature",
  "properties": {
    "iso:country":"US",
    "sg:address":"2417 Market St",
    "sg:city":"Galveston",
    "sg:classifiers":[
        {
            "category":"Professional",
            "subcategory":"Lawyer & Legal Services",
            "type":"Services"
        }
    ],
    "sg:phone":"+1 409 621 1876",
    "sg:postcode":"77550",
    "sg:province":"TX",
    "sg:tags":[
        "attorney"
    ],
    "sg:website":"www.bertinilaw.com",
    "wof:name":"Bertini & Assoc",
    "wof:placetype":"venue"
},
  "geometry": {"coordinates":[-94.795942,29.304776],"type":"Point"}
}