{
  "type": "Feature",
  "properties": {
    "iso:country":"US",
    "sg:address":"307 E Chestnut St",
    "sg:city":"Sonora",
    "sg:classifiers":[
        {
            "category":"Building & Trades",
            "subcategory":"Plumbing",
            "type":"Services"
        }
    ],
    "sg:phone":"+1 325 387 3154",
    "sg:postcode":"76950",
    "sg:province":"TX",
    "sg:tags":[
        "septic"
    ],
    "wof:name":"Adkins Septic Svc",
    "wof:placetype":"venue"
},
  "geometry": {"coordinates":[-100.642143,30.568677],"type":"Point"}
}