{
  "type": "Feature",
  "properties": {
    "iso:country":"US",
    "sg:address":"703 N Penelope St",
    "sg:city":"Belton",
    "sg:classifiers":[
        {
            "category":"Professional",
            "subcategory":"Business Services",
            "type":"Services"
        }
    ],
    "sg:phone":"+1 254 939 5668",
    "sg:postcode":"76513",
    "sg:province":"TX",
    "sg:tags":[
        "interpreter",
        "language",
        "sign"
    ],
    "wof:name":"Visual Communications",
    "wof:placetype":"venue"
},
  "geometry": {"coordinates":[-97.459137,31.062793],"type":"Point"}
}