{
  "type": "Feature",
  "properties": {
    "iso:country":"US",
    "sg:address":"621 S Fannin Ave",
    "sg:city":"Tyler",
    "sg:classifiers":[
        {
            "category":"Building & Trades",
            "subcategory":"Construction",
            "type":"Services"
        }
    ],
    "sg:phone":"+1 903 597 2584",
    "sg:postcode":"75701",
    "sg:province":"TX",
    "sg:tags":[
        "roofing",
        "contractor"
    ],
    "wof:name":"Bo One Red River Syrup",
    "wof:placetype":"venue"
},
  "geometry": {"coordinates":[-95.298502,32.343477],"type":"Point"}
}