{
  "type": "Feature",
  "properties": {
    "iso:country":"US",
    "sg:address":"4500 Duval St",
    "sg:city":"Austin",
    "sg:classifiers":[
        {
            "category":"Retail",
            "subcategory":"Auto Repair",
            "type":"Services"
        }
    ],
    "sg:phone":"+1 512 473 2317",
    "sg:postcode":"78751",
    "sg:province":"TX",
    "sg:tags":[
        "repairing",
        "automobile"
    ],
    "wof:name":"Unlimited Auto Repair Svc",
    "wof:placetype":"venue"
},
  "geometry": {"coordinates":[-97.723485,30.308742],"type":"Point"}
}