{
  "type": "Feature",
  "properties": {
    "iso:country":"US",
    "sg:address":"102 Lakeridge Dr",
    "sg:city":"Dallas",
    "sg:classifiers":[
        {
            "category":"Retail",
            "subcategory":"Animal Services",
            "type":"Services"
        }
    ],
    "sg:phone":"+1 214 348 6010",
    "sg:postcode":"75218",
    "sg:province":"TX",
    "sg:tags":[
        "shop",
        "pet",
        "grooming",
        "washing",
        "beauty"
    ],
    "wof:name":"Showtime Dog Grooming Salon",
    "wof:placetype":"venue"
},
  "geometry": {"coordinates":[-96.711456,32.86217],"type":"Point"}
}