{
  "type": "Feature",
  "properties": {
    "iso:country":"US",
    "sg:address":"1398 Eastwood Dr",
    "sg:city":"Seguin",
    "sg:classifiers":[
        {
            "category":"Autos & Motor Vehicles",
            "subcategory":"Fuel & Gas Station",
            "type":"Retail Goods"
        }
    ],
    "sg:phone":"+1 830 379 4868",
    "sg:postcode":"78155",
    "sg:province":"TX",
    "sg:tags":[
        "station",
        "gasoline"
    ],
    "wof:name":"Murphy Oil Usa Inc",
    "wof:placetype":"venue"
},
  "geometry": {"coordinates":[-97.941929,29.563819],"type":"Point"}
}