{
  "type": "Feature",
  "properties": {
    "iso:country":"US",
    "sg:address":"2618 Jorent Dr",
    "sg:city":"Houston",
    "sg:classifiers":[
        {
            "category":"Shopping",
            "subcategory":"Gifts & Souvenirs",
            "type":"Retail Goods"
        }
    ],
    "sg:phone":"+1 281 447 6165",
    "sg:postcode":"77088",
    "sg:province":"TX",
    "wof:name":"Sallies Flower & Gifts E",
    "wof:placetype":"venue"
},
  "geometry": {"coordinates":[-95.45313299999999,29.890791],"type":"Point"}
}