{
  "type": "Feature",
  "properties": {
    "iso:country":"US",
    "sg:address":"10000 Wallisville Rd",
    "sg:city":"Houston",
    "sg:classifiers":[
        {
            "category":"Freight",
            "type":"Transportation"
        }
    ],
    "sg:phone":"+1 713 673 6383",
    "sg:postcode":"77013",
    "sg:province":"TX",
    "sg:tags":[
        "local",
        "business",
        "trucking"
    ],
    "wof:name":"Trans-Texas Intermodal West",
    "wof:placetype":"venue"
},
  "geometry": {"coordinates":[-95.254239,29.793516],"type":"Point"}
}