{
  "type": "Feature",
  "properties": {
    "iso:country":"US",
    "sg:address":"1200 W Wheeler St",
    "sg:city":"Breckenridge",
    "sg:classifiers":[
        {
            "category":"Personal",
            "subcategory":"Beauty Salon",
            "type":"Services"
        }
    ],
    "sg:phone":"+1 254 559 8406",
    "sg:postcode":"76424",
    "sg:province":"TX",
    "sg:tags":[
        "shop"
    ],
    "wof:name":"Jacque's Cut & Curl",
    "wof:placetype":"venue"
},
  "geometry": {"coordinates":[-98.918362,32.752594],"type":"Point"}
}