{
  "type": "Feature",
  "properties": {
    "iso:country":"US",
    "sg:address":"1416 Westover Ln",
    "sg:city":"Fort Worth",
    "sg:classifiers":[
        {
            "category":"Mining & Drilling",
            "type":"Manufacturing & Wholesale Goods"
        }
    ],
    "sg:phone":"+1 817 735 1408",
    "sg:postcode":"76107",
    "sg:province":"TX",
    "sg:tags":[
        "development",
        "gas",
        "oil",
        "exploration"
    ],
    "wof:name":"Vortt Exploration Co Inc",
    "wof:placetype":"venue"
},
  "geometry": {"coordinates":[-97.41821299999999,32.745423],"type":"Point"}
}