{
  "type": "Feature",
  "properties": {
    "iso:country":"US",
    "sg:address":"2509 Oak Manor Ct",
    "sg:city":"Arlington",
    "sg:classifiers":[
        {
            "category":"Shopping",
            "type":"Retail Goods"
        }
    ],
    "sg:phone":"+1 817 719 0046",
    "sg:postcode":"76012",
    "sg:province":"TX",
    "sg:tags":[
        "mystery",
        "comparison"
    ],
    "wof:name":"3n1 Promotions",
    "wof:placetype":"venue"
},
  "geometry": {"coordinates":[-97.14921099999999,32.742678],"type":"Point"}
}