{
  "type": "Feature",
  "properties": {
    "iso:country":"US",
    "sg:address":"307 S Locust St",
    "sg:city":"Denton",
    "sg:classifiers":[
        {
            "category":"Recreation",
            "type":"Entertainment"
        }
    ],
    "sg:phone":"+1 940 591 9104",
    "sg:postcode":"76201",
    "sg:province":"TX",
    "wof:name":"Aikido of Denton",
    "wof:placetype":"venue"
},
  "geometry": {"coordinates":[-97.132403,33.210743],"type":"Point"}
}