{
  "type": "Feature",
  "properties": {
    "iso:country":"US",
    "sg:address":"3757 W State Highway 21",
    "sg:city":"Nacogdoches",
    "sg:classifiers":[
        {
            "category":"Utilities",
            "subcategory":"Electric",
            "type":"Services"
        },
        {
            "category":"Manufacturing",
            "subcategory":"Electronics",
            "type":"Manufacturing & Wholesale Goods"
        }
    ],
    "sg:phone":"+1 936 560 2585",
    "sg:postcode":"75964",
    "sg:province":"TX",
    "sg:tags":[
        "equipment-testing"
    ],
    "wof:name":"Robert W Mccarty Jr",
    "wof:placetype":"venue"
},
  "geometry": {"coordinates":[-94.738435,31.62879],"type":"Point"}
}