{
  "type": "Feature",
  "properties": {
    "iso:country":"US",
    "sg:address":"8627 Greiner Dr",
    "sg:city":"Houston",
    "sg:classifiers":[
        {
            "category":"Retail",
            "subcategory":"Repair Shop",
            "type":"Services"
        }
    ],
    "sg:phone":"+1 713 468 6532",
    "sg:postcode":"77080",
    "sg:province":"TX",
    "sg:tags":[
        "refrigeration"
    ],
    "wof:name":"Refrigeration Equipment Co",
    "wof:placetype":"venue"
},
  "geometry": {"coordinates":[-95.504873,29.823173],"type":"Point"}
}