{
  "type": "Feature",
  "properties": {
    "iso:country":"US",
    "sg:address":"806 Ange St",
    "sg:city":"El Paso",
    "sg:classifiers":[
        {
            "category":"Professional",
            "subcategory":"Accounting & Tax Preparation",
            "type":"Services"
        }
    ],
    "sg:phone":"+1 915 532 8454",
    "sg:postcode":"79902",
    "sg:province":"TX",
    "sg:tags":[
        "auditing",
        "bookkeeping"
    ],
    "wof:name":"Manuel Calanche Jr A Prof Corp",
    "wof:placetype":"venue"
},
  "geometry": {"coordinates":[-106.484752,31.768275],"type":"Point"}
}