{
  "type": "Feature",
  "properties": {
    "iso:country":"US",
    "sg:address":"200 N Aquilla St",
    "sg:city":"Itasca",
    "sg:classifiers":[
        {
            "category":"Place Of Worship",
            "subcategory":"Church",
            "type":"Public Place"
        },
        {
            "category":"Place Of Worship",
            "type":"Public Place"
        }
    ],
    "sg:phone":"+1 254 687 2774",
    "sg:postcode":"76055",
    "sg:province":"TX",
    "sg:tags":[
        "testament",
        "churches-church",
        "christ",
        "christ-new"
    ],
    "wof:name":"Church of Christ",
    "wof:placetype":"venue"
},
  "geometry": {"coordinates":[-97.14917,32.161419],"type":"Point"}
}