{
  "type": "Feature",
  "properties": {
    "iso:country":"US",
    "sg:address":"4321 General Aviation Ave",
    "sg:city":"Austin",
    "sg:classifiers":[
        {
            "category":"Shopping",
            "subcategory":"Department Store",
            "type":"Retail Goods"
        },
        {
            "category":"Airline",
            "type":"Transportation"
        },
        {
            "category":"Building & Trades",
            "subcategory":"Equipment Rental",
            "type":"Services"
        }
    ],
    "sg:phone":"+1 512 530 8030",
    "sg:postcode":"78719",
    "sg:province":"TX",
    "sg:tags":[
        "leasing",
        "storage",
        "sale",
        "aircraft",
        "aircraft-charter",
        "aircraft-hangars-rental"
    ],
    "wof:name":"Azlon",
    "wof:placetype":"venue"
},
  "geometry": {"coordinates":[-97.66357000000001,30.18841],"type":"Point"}
}