{
  "type": "Feature",
  "properties": {
    "iso:country":"US",
    "sg:address":"812 N Stemmons Fwy",
    "sg:city":"Dallas",
    "sg:classifiers":[
        {
            "category":"Restaurant",
            "type":"Food & Drink"
        }
    ],
    "sg:phone":"+1 214 221 3312",
    "sg:postcode":"75207",
    "sg:province":"TX",
    "sg:tags":[
        "parlor",
        "ice",
        "cream"
    ],
    "wof:name":"Braum's Ice Cream & Dairy",
    "wof:placetype":"venue"
},
  "geometry": {"coordinates":[-96.813785,32.790595],"type":"Point"}
}