{
  "type": "Feature",
  "properties": {
    "iso:country":"US",
    "sg:address":"1101 Waco St",
    "sg:city":"Corpus Christi",
    "sg:classifiers":[
        {
            "category":"Organizations",
            "subcategory":"Religious Organization",
            "type":"Services"
        }
    ],
    "sg:phone":"+1 361 884 4121",
    "sg:postcode":"78401",
    "sg:province":"TX",
    "sg:tags":[
        "church"
    ],
    "wof:name":"Saint Matthew Baptist Church",
    "wof:placetype":"venue"
},
  "geometry": {"coordinates":[-97.400266,27.800967],"type":"Point"}
}