{
  "type": "Feature",
  "properties": {
    "iso:country":"US",
    "sg:address":"4 Dewthread",
    "sg:city":"Spring",
    "sg:classifiers":[
        {
            "category":"Building & Trades",
            "subcategory":"Construction",
            "type":"Services"
        }
    ],
    "sg:phone":"+1 281 367 2309",
    "sg:postcode":"77380",
    "sg:province":"TX",
    "sg:tags":[
        "home",
        "builder"
    ],
    "wof:name":"D & G Eagles Nest Homes",
    "wof:placetype":"venue"
},
  "geometry": {"coordinates":[-95.472221,30.154335],"type":"Point"}
}