{
  "type": "Feature",
  "properties": {
    "iso:country":"US",
    "sg:address":"14470 N Loop Dr",
    "sg:city":"Clint",
    "sg:classifiers":[
        {
            "category":"Farming",
            "subcategory":"Livestock Farm",
            "type":"Manufacturing & Wholesale Goods"
        }
    ],
    "sg:phone":"+1 915 851 1960",
    "sg:postcode":"79836",
    "sg:province":"TX",
    "sg:tags":[
        "animal",
        "general"
    ],
    "wof:name":"Red Eagle Ranch",
    "wof:placetype":"venue"
},
  "geometry": {"coordinates":[-106.189502,31.55897],"type":"Point"}
}