{
  "type": "Feature",
  "properties": {
    "iso:country":"US",
    "sg:address":"515 N Perry Ave",
    "sg:city":"Denison",
    "sg:classifiers":[
        {
            "category":"Building & Trades",
            "subcategory":"Electrical",
            "type":"Services"
        }
    ],
    "sg:phone":"+1 903 465 9362",
    "sg:postcode":"75020",
    "sg:province":"TX",
    "sg:tags":[
        "electrical",
        "contractor"
    ],
    "wof:name":"Joe Torres",
    "wof:placetype":"venue"
},
  "geometry": {"coordinates":[-96.552198,33.760981],"type":"Point"}
}