{
  "type": "Feature",
  "properties": {
    "iso:country":"US",
    "sg:address":"215 S Watson Rd",
    "sg:city":"Arlington",
    "sg:classifiers":[
        {
            "category":"Restaurant",
            "type":"Food & Drink"
        }
    ],
    "sg:menulink":"http://www.allmenus.com/tx/arlington/193261-taco-bell/menu/",
    "sg:postcode":"76010",
    "sg:province":"TX",
    "sg:tags":[
        "mexican"
    ],
    "wof:name":"Taco Bell",
    "wof:placetype":"venue"
},
  "geometry": {"coordinates":[-97.061379,32.734126],"type":"Point"}
}