{
  "type": "Feature",
  "properties": {
    "iso:country":"US",
    "sg:address":"1030 N Zaragoza Rd",
    "sg:city":"El Paso",
    "sg:classifiers":[
        {
            "category":"Banks & Credit Unions",
            "subcategory":"Bank",
            "type":"Services"
        }
    ],
    "sg:phone":"+1 915 860 8086",
    "sg:postcode":"79907",
    "sg:province":"TX",
    "sg:tags":[
        "financing"
    ],
    "wof:name":"Beneficial Finance",
    "wof:placetype":"venue"
},
  "geometry": {"coordinates":[-106.309562,31.714088],"type":"Point"}
}