{
  "type": "Feature",
  "properties": {
    "iso:country":"US",
    "sg:address":"16797 Co Rd 138 W",
    "sg:city":"Vernon",
    "sg:classifiers":[
        {
            "category":"Manufacturing",
            "subcategory":"Apparel",
            "type":"Manufacturing & Wholesale Goods"
        },
        {
            "category":"Shopping",
            "subcategory":"Shoes",
            "type":"Retail Goods"
        }
    ],
    "sg:phone":"+1 940 552 7247",
    "sg:postcode":"76384",
    "sg:province":"TX",
    "sg:tags":[
        "textile",
        "product",
        "boot",
        "fabricated",
        "mfg"
    ],
    "wof:name":"Dew's Custom Handmade Boots",
    "wof:placetype":"venue"
},
  "geometry": {"coordinates":[-99.431104,34.002275],"type":"Point"}
}