{
  "type": "Feature",
  "properties": {
    "iso:country":"US",
    "sg:address":"4221 SW 45th Ave",
    "sg:city":"Amarillo",
    "sg:classifiers":[
        {
            "category":"Shopping",
            "subcategory":"Department Store",
            "type":"Retail Goods"
        }
    ],
    "sg:phone":"+1 806 358 7525",
    "sg:postcode":"79109",
    "sg:province":"TX",
    "sg:website":"http://www.bealls.com/",
    "wof:name":"Bealls Department Store",
    "wof:placetype":"venue"
},
  "geometry": {"coordinates":[-101.884534,35.16383],"type":"Point"}
}