{
  "type": "Feature",
  "properties": {
    "iso:country":"US",
    "sg:address":"1612 Fm 2127",
    "sg:city":"Chico",
    "sg:phone":"+1 940 644 5210",
    "sg:postcode":"76431",
    "sg:province":"TX",
    "wof:name":"Northside Church Of Christ",
    "wof:placetype":"venue"
},
  "geometry": {"coordinates":[-97.88208,33.356255],"type":"Point"}
}