{
  "type": "Feature",
  "properties": {
    "iso:country":"US",
    "sg:address":"4116 Clay Ave",
    "sg:city":"Haltom City",
    "sg:classifiers":[
        {
            "category":"Utilities",
            "subcategory":"Cable",
            "type":"Services"
        }
    ],
    "sg:phone":"+1 817 485 4639",
    "sg:postcode":"76117",
    "sg:province":"TX",
    "sg:tags":[
        "television"
    ],
    "sg:website":"www.generalfiber.com",
    "wof:name":"General Fiber",
    "wof:placetype":"venue"
},
  "geometry": {"coordinates":[-97.28497,32.829074],"type":"Point"}
}