{
  "type": "Feature",
  "properties": {
    "iso:country":"US",
    "sg:address":"5110 Smokey River Dr",
    "sg:city":"Katy",
    "sg:classifiers":[
        {
            "category":"Communications",
            "type":"Services"
        }
    ],
    "sg:phone":"+1 281 463 7765",
    "sg:postcode":"77449",
    "sg:province":"TX",
    "sg:tags":[
        "communication"
    ],
    "wof:name":"Click Communications",
    "wof:placetype":"venue"
},
  "geometry": {"coordinates":[-95.727841,29.846987],"type":"Point"}
}