{
  "type": "Feature",
  "properties": {
    "iso:country":"US",
    "sg:address":"245 Hulett St",
    "sg:city":"Vidor",
    "sg:classifiers":[
        {
            "category":"Manufacturing",
            "subcategory":"Glass & Minerals",
            "type":"Manufacturing & Wholesale Goods"
        }
    ],
    "sg:phone":"+1 409 786 3353",
    "sg:postcode":"77662",
    "sg:province":"TX",
    "sg:tags":[
        "product",
        "mfg"
    ],
    "wof:name":"East Texas Glass & Mirror",
    "wof:placetype":"venue"
},
  "geometry": {"coordinates":[-94.03452299999999,30.176397],"type":"Point"}
}