{
  "type": "Feature",
  "properties": {
    "iso:country":"US",
    "sg:address":"911 N Grandview Ave",
    "sg:city":"Odessa",
    "sg:classifiers":[
        {
            "category":"Home & Garden",
            "subcategory":"Building Materials",
            "type":"Retail Goods"
        }
    ],
    "sg:phone":"+1 432 332 0179",
    "sg:postcode":"79761",
    "sg:province":"TX",
    "sg:tags":[
        "paint",
        "floor",
        "covering"
    ],
    "wof:name":"Sherwin-Williams Paints",
    "wof:placetype":"venue"
},
  "geometry": {"coordinates":[-102.346041,31.861245],"type":"Point"}
}