{
  "type": "Feature",
  "properties": {
    "iso:country":"US",
    "sg:address":"310 N McKinney St",
    "sg:city":"Sweeny",
    "sg:classifiers":[
        {
            "category":"Organizations",
            "subcategory":"Religious Organization",
            "type":"Services"
        }
    ],
    "sg:phone":"+1 979 548 2020",
    "sg:postcode":"77480",
    "sg:province":"TX",
    "sg:tags":[
        "church"
    ],
    "wof:name":"Our Lady Perpetual Help Church",
    "wof:placetype":"venue"
},
  "geometry": {"coordinates":[-95.691469,29.048616],"type":"Point"}
}