{
  "type": "Feature",
  "properties": {
    "iso:country":"US",
    "sg:address":"122 W 7th St",
    "sg:city":"Friona",
    "sg:classifiers":[
        {
            "category":"Manufacturing",
            "subcategory":"Apparel",
            "type":"Manufacturing & Wholesale Goods"
        }
    ],
    "sg:phone":"+1 806 250 3038",
    "sg:postcode":"79035",
    "sg:province":"TX",
    "sg:tags":[
        "mfg"
    ],
    "wof:name":"Campbell Drapery",
    "wof:placetype":"venue"
},
  "geometry": {"coordinates":[-102.71972599999999,34.637537],"type":"Point"}
}