{
  "type": "Feature",
  "properties": {
    "iso:country":"US",
    "sg:address":"810 Cherry St",
    "sg:city":"Fort Worth",
    "sg:classifiers":[
        {
            "category":"Professional",
            "subcategory":"Lawyer & Legal Services",
            "type":"Services"
        }
    ],
    "sg:phone":"+1 817 878 3333",
    "sg:postcode":"76102",
    "sg:province":"TX",
    "sg:tags":[
        "attorney"
    ],
    "wof:name":"Patrick H O'Neill Law Offices",
    "wof:placetype":"venue"
},
  "geometry": {"coordinates":[-97.334901,32.750108],"type":"Point"}
}