{
  "type": "Feature",
  "properties": {
    "iso:country":"US",
    "sg:address":"2600 Paramount Blvd",
    "sg:city":"Amarillo",
    "sg:classifiers":[
        {
            "category":"Banks & Credit Unions",
            "subcategory":"Bank",
            "type":"Services"
        }
    ],
    "sg:phone":"+1 806 236 4464",
    "sg:postcode":"79109",
    "sg:province":"TX",
    "sg:tags":[
        "loan",
        "real estate"
    ],
    "wof:name":"Mortgage Home Loans",
    "wof:placetype":"venue"
},
  "geometry": {"coordinates":[-101.875348,35.184534],"type":"Point"}
}