{
  "type": "Feature",
  "properties": {
    "iso:country":"US",
    "sg:address":"48 W Spicer Dr",
    "sg:city":"Kerrville",
    "sg:classifiers":[
        {
            "category":"Professional",
            "type":"Services"
        }
    ],
    "sg:phone":"+1 830 257 8874",
    "sg:postcode":"78028",
    "sg:province":"TX",
    "wof:name":"Marlin N McDougall",
    "wof:placetype":"venue"
},
  "geometry": {"coordinates":[-99.21144,29.983722],"type":"Point"}
}