{
  "type": "Feature",
  "properties": {
    "iso:country":"US",
    "sg:address":"3817 Southwestern St",
    "sg:city":"Houston",
    "sg:classifiers":[
        {
            "category":"Building & Trades",
            "subcategory":"Construction",
            "type":"Services"
        }
    ],
    "sg:phone":"+1 713 668 2460",
    "sg:postcode":"77005",
    "sg:province":"TX",
    "sg:tags":[
        "home",
        "builder"
    ],
    "wof:name":"Lacon Homes",
    "wof:placetype":"venue"
},
  "geometry": {"coordinates":[-95.439184,29.709335],"type":"Point"}
}