{
  "type": "Feature",
  "properties": {
    "iso:country":"US",
    "sg:address":"8920 Bus Park Dr",
    "sg:city":"Austin",
    "sg:classifiers":[
        {
            "category":"Shopping",
            "subcategory":"Computers & Home Electronics",
            "type":"Retail Goods"
        }
    ],
    "sg:phone":"+1 512 651 4220",
    "sg:postcode":"78759",
    "sg:province":"TX",
    "sg:tags":[
        "software"
    ],
    "wof:name":"Journee Software",
    "wof:placetype":"venue"
},
  "geometry": {"coordinates":[-97.741276,30.379132],"type":"Point"}
}