{
  "type": "Feature",
  "properties": {
    "iso:country":"US",
    "sg:address":"1525 Chapman St",
    "sg:city":"Cedar Hill",
    "sg:classifiers":[
        {
            "category":"Social Services",
            "type":"Services"
        }
    ],
    "sg:phone":"+1 972 291 9963",
    "sg:postcode":"75104",
    "sg:province":"TX",
    "wof:name":"Miracle Chldren Counseling Ctr",
    "wof:placetype":"venue"
},
  "geometry": {"coordinates":[-96.95138799999999,32.621396],"type":"Point"}
}