{
  "type": "Feature",
  "properties": {
    "iso:country":"US",
    "sg:address":"6815 Honey Ridge Ln",
    "sg:city":"San Antonio",
    "sg:classifiers":[
        {
            "category":"Professional",
            "type":"Services"
        }
    ],
    "sg:phone":"+1 210 657 9689",
    "sg:postcode":"78239",
    "sg:province":"TX",
    "wof:name":"Just General Service",
    "wof:placetype":"venue"
},
  "geometry": {"coordinates":[-98.354928,29.523139],"type":"Point"}
}