{
  "type": "Feature",
  "properties": {
    "iso:country":"US",
    "sg:address":"9065 Jollyville Rd",
    "sg:city":"Austin",
    "sg:classifiers":[
        {
            "category":"Shopping",
            "subcategory":"Computers & Home Electronics",
            "type":"Retail Goods"
        }
    ],
    "sg:phone":"+1 512 241 1808",
    "sg:postcode":"78759",
    "sg:province":"TX",
    "sg:tags":[
        "software"
    ],
    "wof:name":"Topaz Software",
    "wof:placetype":"venue"
},
  "geometry": {"coordinates":[-97.743381,30.381643],"type":"Point"}
}