{
  "type": "Feature",
  "properties": {
    "iso:country":"US",
    "sg:address":"1201 Main St",
    "sg:city":"Dallas",
    "sg:classifiers":[
        {
            "category":"Restaurant",
            "type":"Food & Drink"
        }
    ],
    "sg:postcode":"75242",
    "sg:province":"TX",
    "sg:tags":[
        "southern"
    ],
    "sg:website":"www.treebeards.com/",
    "wof:name":"Treebeards",
    "wof:placetype":"venue"
},
  "geometry": {"coordinates":[-96.801846,32.780068],"type":"Point"}
}