{
  "type": "Feature",
  "properties": {
    "iso:country":"US",
    "sg:address":"210 E Live Oak St",
    "sg:city":"Seguin",
    "sg:classifiers":[
        {
            "category":"Government",
            "subcategory":"Office",
            "type":"Public Place"
        }
    ],
    "sg:phone":"+1 830 379 0931",
    "sg:postcode":"78155",
    "sg:province":"TX",
    "sg:tags":[
        "federal"
    ],
    "wof:name":"US Consolidated Farm Svc Agcy",
    "wof:placetype":"venue"
},
  "geometry": {"coordinates":[-97.962953,29.566024],"type":"Point"}
}