{
  "type": "Feature",
  "properties": {
    "iso:country":"US",
    "sg:address":"102 W 2nd St",
    "sg:city":"Deer Park",
    "sg:classifiers":[
        {
            "category":"Recreation",
            "type":"Entertainment"
        }
    ],
    "sg:phone":"+1 281 476 9172",
    "sg:postcode":"77536",
    "sg:province":"TX",
    "sg:tags":[
        "party",
        "fishing"
    ],
    "wof:name":"Kingfisher Of Texas",
    "wof:placetype":"venue"
},
  "geometry": {"coordinates":[-95.124444,29.70915],"type":"Point"}
}