{
  "type": "Feature",
  "properties": {
    "iso:country":"US",
    "sg:address":"3913 E Lancaster Ave",
    "sg:city":"Fort Worth",
    "sg:classifiers":[
        {
            "category":"Health Services",
            "subcategory":"Doctor",
            "type":"Services"
        }
    ],
    "sg:phone":"+1 817 536 1976",
    "sg:postcode":"76103",
    "sg:province":"TX",
    "sg:tags":[
        "dentist"
    ],
    "wof:name":"Meadowbrook Dental Office",
    "wof:placetype":"venue"
},
  "geometry": {"coordinates":[-97.266944,32.741057],"type":"Point"}
}