{
  "type": "Feature",
  "properties": {
    "iso:country":"US",
    "sg:address":"225 S Charles St",
    "sg:city":"Lewisville",
    "sg:classifiers":[
        {
            "category":"Food & Beverages",
            "subcategory":"Groceries & Convenience Stores",
            "type":"Retail Goods"
        }
    ],
    "sg:phone":"+1 972 221 1626",
    "sg:postcode":"75057",
    "sg:province":"TX",
    "wof:name":"Piggly Wiggly",
    "wof:placetype":"venue"
},
  "geometry": {"coordinates":[-96.996545,33.044564],"type":"Point"}
}