{
  "type": "Feature",
  "properties": {
    "iso:country":"US",
    "sg:address":"901 S Madison Ave",
    "sg:city":"Dallas",
    "sg:classifiers":[
        {
            "category":"Organizations",
            "subcategory":"Religious Organization",
            "type":"Services"
        }
    ],
    "sg:phone":"+1 214 943 6585",
    "sg:postcode":"75208",
    "sg:province":"TX",
    "sg:tags":[
        "church"
    ],
    "wof:name":"Catholic Conference Ctr",
    "wof:placetype":"venue"
},
  "geometry": {"coordinates":[-96.82651799999999,32.738279],"type":"Point"}
}