{
  "type": "Feature",
  "properties": {
    "iso:country":"US",
    "sg:address":"6633 Cahoba Dr",
    "sg:city":"Fort Worth",
    "sg:classifiers":[
        {
            "category":"Professional",
            "subcategory":"Business Services",
            "type":"Services"
        }
    ],
    "sg:phone":"+1 817 237 2798",
    "sg:postcode":"76135",
    "sg:province":"TX",
    "wof:name":"Shope & Ryan Commercial LLC",
    "wof:placetype":"venue"
},
  "geometry": {"coordinates":[-97.429984,32.794257],"type":"Point"}
}