{
  "type": "Feature",
  "properties": {
    "iso:country":"US",
    "sg:address":"2332 Jordon Rd",
    "sg:city":"Mcallen",
    "sg:classifiers":[
        {
            "category":"Social Services",
            "type":"Services"
        }
    ],
    "sg:phone":"+1 956 994 3319",
    "sg:postcode":"78503",
    "sg:province":"TX",
    "sg:tags":[
        "organization",
        "welfare"
    ],
    "wof:name":"Hope Medical Clinic",
    "wof:placetype":"venue"
},
  "geometry": {"coordinates":[-98.25333500000001,26.18147],"type":"Point"}
}