{
  "type": "Feature",
  "properties": {
    "iso:country":"US",
    "sg:address":"1602 Concord St",
    "sg:city":"Deer Park",
    "sg:classifiers":[
        {
            "category":"Building & Trades",
            "subcategory":"Landscaping Services",
            "type":"Services"
        }
    ],
    "sg:phone":"+1 281 476 4417",
    "sg:postcode":"77536",
    "sg:province":"TX",
    "sg:tags":[
        "landscape"
    ],
    "wof:name":"Turf of Texas",
    "wof:placetype":"venue"
},
  "geometry": {"coordinates":[-95.137333,29.684961],"type":"Point"}
}