{
  "type": "Feature",
  "properties": {
    "iso:country":"US",
    "sg:address":"2801 N Navarro St",
    "sg:city":"Victoria",
    "sg:classifiers":[
        {
            "category":"Autos & Motor Vehicles",
            "subcategory":"Fuel & Gas Station",
            "type":"Retail Goods"
        }
    ],
    "sg:phone":"+1 361 575 1177",
    "sg:postcode":"77901",
    "sg:province":"TX",
    "sg:tags":[
        "oil"
    ],
    "wof:name":"Zarbock Phillips 66",
    "wof:placetype":"venue"
},
  "geometry": {"coordinates":[-97.000508,28.821396],"type":"Point"}
}