{
  "type": "Feature",
  "properties": {
    "iso:country":"US",
    "sg:address":"4809 Nautilus Ct",
    "sg:city":"Flower Mound",
    "sg:classifiers":[
        {
            "category":"Professional",
            "subcategory":"Management & Consulting",
            "type":"Services"
        }
    ],
    "sg:phone":"+1 972 355 1221",
    "sg:postcode":"75022",
    "sg:province":"TX",
    "sg:tags":[
        "consultant",
        "business"
    ],
    "wof:name":"Retail Credit Solutions  Inc",
    "wof:placetype":"venue"
},
  "geometry": {"coordinates":[-97.10545999999999,33.018795],"type":"Point"}
}