{
  "type": "Feature",
  "properties": {
    "iso:country":"US",
    "sg:address":"1827 Clover Spring Dr",
    "sg:city":"Humble",
    "sg:classifiers":[
        {
            "category":"Professional",
            "subcategory":"Business Services",
            "type":"Services"
        }
    ],
    "sg:phone":"+1 281 358 5675",
    "sg:postcode":"77339",
    "sg:province":"TX",
    "wof:name":"Wil Star Partners For Success",
    "wof:placetype":"venue"
},
  "geometry": {"coordinates":[-95.225145,30.05544],"type":"Point"}
}