{
  "type": "Feature",
  "properties": {
    "iso:country":"US",
    "sg:address":"11910 Edwards Hollow Run",
    "sg:city":"Austin",
    "sg:classifiers":[
        {
            "category":"Health Services",
            "subcategory":"Hospice",
            "type":"Services"
        }
    ],
    "sg:phone":"+1 512 280 3776",
    "sg:postcode":"78739",
    "sg:province":"TX",
    "wof:name":"Vitas Jacob",
    "wof:placetype":"venue"
},
  "geometry": {"coordinates":[-97.860474,30.15828],"type":"Point"}
}