{
  "type": "Feature",
  "properties": {
    "iso:country":"US",
    "sg:address":"6906 Elmwood Ave",
    "sg:city":"Lubbock",
    "sg:classifiers":[
        {
            "category":"Professional",
            "type":"Services"
        }
    ],
    "sg:phone":"+1 806 783 9637",
    "sg:postcode":"79424",
    "sg:province":"TX",
    "wof:name":"Mathew W Howard",
    "wof:placetype":"venue"
},
  "geometry": {"coordinates":[-101.936554,33.531539],"type":"Point"}
}