{
  "type": "Feature",
  "properties": {
    "iso:country":"US",
    "sg:address":"30001 US Highway 281 N",
    "sg:city":"Bulverde",
    "sg:classifiers":[
        {
            "category":"Home & Garden",
            "subcategory":"Furniture",
            "type":"Retail Goods"
        }
    ],
    "sg:phone":"+1 830 438 4660",
    "sg:postcode":"78163",
    "sg:province":"TX",
    "sg:tags":[
        "store"
    ],
    "wof:name":"Rustic Unlimited",
    "wof:placetype":"venue"
},
  "geometry": {"coordinates":[-98.438969,29.737846],"type":"Point"}
}