{
  "type": "Feature",
  "properties": {
    "iso:country":"US",
    "sg:address":"7817 Millstone Dr",
    "sg:city":"Dallas",
    "sg:classifiers":[
        {
            "category":"Freight",
            "type":"Transportation"
        }
    ],
    "sg:phone":"+1 214 328 4993",
    "sg:postcode":"75228",
    "sg:province":"TX",
    "sg:tags":[
        "broker",
        "trucking"
    ],
    "wof:name":"Harry's Brokerage Inc",
    "wof:placetype":"venue"
},
  "geometry": {"coordinates":[-96.71093999999999,32.797924],"type":"Point"}
}