{
  "type": "Feature",
  "properties": {
    "iso:country":"US",
    "sg:address":"1912 Tarrant Pl",
    "sg:city":"Dallas",
    "sg:classifiers":[
        {
            "category":"Manufacturing",
            "subcategory":"Printing",
            "type":"Manufacturing & Wholesale Goods"
        }
    ],
    "sg:phone":"+1 214 942 3575",
    "sg:postcode":"75208",
    "sg:province":"TX",
    "sg:tags":[
        "publishing"
    ],
    "wof:name":"Nigredo Music Publishing",
    "wof:placetype":"venue"
},
  "geometry": {"coordinates":[-96.85286499999999,32.763658],"type":"Point"}
}