{
  "type": "Feature",
  "properties": {
    "iso:country":"US",
    "sg:address":"1805 Trail Vw",
    "sg:city":"Friendswood",
    "sg:classifiers":[
        {
            "category":"Real Estate",
            "subcategory":"Real Estate Agent",
            "type":"Services"
        }
    ],
    "sg:phone":"+1 281 993 1612",
    "sg:postcode":"77546",
    "sg:province":"TX",
    "wof:name":"Abbott Team Management LLC",
    "wof:placetype":"venue"
},
  "geometry": {"coordinates":[-95.194193,29.492584],"type":"Point"}
}