{
  "type": "Feature",
  "properties": {
    "iso:country":"US",
    "sg:address":"2806 Pleasant Green Dr",
    "sg:city":"Victoria",
    "sg:classifiers":[
        {
            "category":"Arts & Performance",
            "subcategory":"Theater",
            "type":"Entertainment"
        }
    ],
    "sg:phone":"+1 361 575 6669",
    "sg:postcode":"77901",
    "sg:province":"TX",
    "sg:tags":[
        "group"
    ],
    "wof:name":"Hard Time Entertainment",
    "wof:placetype":"venue"
},
  "geometry": {"coordinates":[-96.970997,28.778701],"type":"Point"}
}