{
  "type": "Feature",
  "properties": {
    "iso:country":"US",
    "sg:address":"4734 Purdue Ave",
    "sg:city":"Dallas",
    "sg:classifiers":[
        {
            "category":"Professional",
            "type":"Services"
        }
    ],
    "sg:phone":"+1 214 352 4429",
    "sg:postcode":"75209",
    "sg:province":"TX",
    "wof:name":"Elite Etc",
    "wof:placetype":"venue"
},
  "geometry": {"coordinates":[-96.82840899999999,32.854148],"type":"Point"}
}