{
  "type": "Feature",
  "properties": {
    "iso:country":"US",
    "sg:address":"17772 Preston Rd",
    "sg:city":"Dallas",
    "sg:classifiers":[
        {
            "category":"Personal",
            "type":"Services"
        }
    ],
    "sg:phone":"+1 972 931 6100",
    "sg:postcode":"75252",
    "sg:province":"TX",
    "sg:tags":[
        "debt",
        "adjuster"
    ],
    "wof:name":"Fuselier Francising",
    "wof:placetype":"venue"
},
  "geometry": {"coordinates":[-96.800093,32.993736],"type":"Point"}
}