{
  "type": "Feature",
  "properties": {
    "iso:country":"US",
    "sg:address":"902 Broadway St",
    "sg:city":"Galveston",
    "sg:classifiers":[
        {
            "category":"Food & Beverages",
            "subcategory":"Liquor & Beverages",
            "type":"Retail Goods"
        }
    ],
    "sg:phone":"+1 409 763 4668",
    "sg:postcode":"77550",
    "sg:province":"TX",
    "sg:tags":[
        "beer",
        "ale"
    ],
    "wof:name":"Huggy Bears",
    "wof:placetype":"venue"
},
  "geometry": {"coordinates":[-94.777111,29.304055],"type":"Point"}
}