{
  "type": "Feature",
  "properties": {
    "iso:country":"US",
    "sg:address":"3609 S Harrison St",
    "sg:city":"Amarillo",
    "sg:classifiers":[
        {
            "category":"Shopping",
            "type":"Retail Goods"
        }
    ],
    "sg:phone":"+1 806 374 1993",
    "sg:postcode":"79110",
    "sg:province":"TX",
    "sg:tags":[
        "merchandise"
    ],
    "wof:name":"Fintastic Discount",
    "wof:placetype":"venue"
},
  "geometry": {"coordinates":[-101.843305,35.175489],"type":"Point"}
}