{
  "type": "Feature",
  "properties": {
    "iso:country":"US",
    "sg:address":"3714 Long Leaf Ln",
    "sg:city":"Porter",
    "sg:classifiers":[
        {
            "category":"Building & Trades",
            "subcategory":"Construction",
            "type":"Services"
        },
        {
            "category":"Manufacturing",
            "subcategory":"Building Materials",
            "type":"Manufacturing & Wholesale Goods"
        }
    ],
    "sg:phone":"+1 281 360 8470",
    "sg:postcode":"77365",
    "sg:province":"TX",
    "sg:tags":[
        "cabinetmakers-commercial",
        "industrial",
        "maker",
        "cabinet"
    ],
    "wof:name":"William Motl",
    "wof:placetype":"venue"
},
  "geometry": {"coordinates":[-95.177423,30.066893],"type":"Point"}
}