{
  "type": "Feature",
  "properties": {
    "iso:country":"US",
    "sg:address":"5231 Broadway",
    "sg:city":"San Antonio",
    "sg:classifiers":[
        {
            "category":"Home & Garden",
            "subcategory":"Furniture",
            "type":"Retail Goods"
        }
    ],
    "sg:phone":"+1 210 832 9117",
    "sg:postcode":"78209",
    "sg:province":"TX",
    "sg:tags":[
        "builder",
        "custom"
    ],
    "wof:name":"Gefe Gallery",
    "wof:placetype":"venue"
},
  "geometry": {"coordinates":[-98.46282100000001,29.475949],"type":"Point"}
}