{
  "type": "Feature",
  "properties": {
    "iso:country":"US",
    "sg:address":"3141 Hood St",
    "sg:city":"Dallas",
    "sg:classifiers":[
        {
            "category":"Banks & Credit Unions",
            "subcategory":"Financial Services",
            "type":"Services"
        }
    ],
    "sg:phone":"+1 214 521 8700",
    "sg:postcode":"75219",
    "sg:province":"TX",
    "sg:tags":[
        "who",
        "real estate",
        "security",
        "trust",
        "investment"
    ],
    "wof:name":"Dixon Trust Co",
    "wof:placetype":"venue"
},
  "geometry": {"coordinates":[-96.80549000000001,32.808153],"type":"Point"}
}