{
  "type": "Feature",
  "properties": {
    "iso:country":"US",
    "sg:address":"4412 Morningside Dr",
    "sg:city":"Houston",
    "sg:classifiers":[
        {
            "category":"Wholesale",
            "subcategory":"Home Furnishings",
            "type":"Manufacturing & Wholesale Goods"
        }
    ],
    "sg:phone":"+1 713 522 2216",
    "sg:postcode":"77098",
    "sg:province":"TX",
    "wof:name":"Unika Deco",
    "wof:placetype":"venue"
},
  "geometry": {"coordinates":[-95.415105,29.725627],"type":"Point"}
}