{
  "type": "Feature",
  "properties": {
    "iso:country":"US",
    "sg:address":"310 Ellen Ave",
    "sg:city":"League City",
    "sg:classifiers":[
        {
            "category":"Retail",
            "subcategory":"Animal Services",
            "type":"Services"
        }
    ],
    "sg:phone":"+1 281 554 2068",
    "sg:postcode":"77573",
    "sg:province":"TX",
    "wof:name":"Anchors Kitty Kabins",
    "wof:placetype":"venue"
},
  "geometry": {"coordinates":[-95.07450900000001,29.514043],"type":"Point"}
}