{
  "type": "Feature",
  "properties": {
    "iso:country":"US",
    "sg:address":"3409 Glenwood Ave",
    "sg:city":"Wichita Falls",
    "sg:classifiers":[
        {
            "category":"Real Estate",
            "subcategory":"Real Estate Operator",
            "type":"Services"
        }
    ],
    "sg:phone":"+1 940 692 0760",
    "sg:postcode":"76308",
    "sg:province":"TX",
    "sg:tags":[
        "building",
        "nonresidential"
    ],
    "wof:name":"Ead Properties LLC",
    "wof:placetype":"venue"
},
  "geometry": {"coordinates":[-98.52542800000001,33.875548],"type":"Point"}
}