{
  "type": "Feature",
  "properties": {
    "iso:country":"US",
    "sg:address":"1012 Steeplewood Dr",
    "sg:city":"Grapevine",
    "sg:classifiers":[
        {
            "category":"Professional",
            "type":"Services"
        }
    ],
    "sg:phone":"+1 817 410 2344",
    "sg:postcode":"76051",
    "sg:province":"TX",
    "wof:name":"Cowgirl Studio & Gallery",
    "wof:placetype":"venue"
},
  "geometry": {"coordinates":[-97.099238,32.949532],"type":"Point"}
}