{
  "type": "Feature",
  "properties": {
    "iso:country":"US",
    "sg:address":"1140 W Main",
    "sg:city":"Tomball",
    "sg:classifiers":[
        {
            "category":"Retail",
            "subcategory":"Auto Repair",
            "type":"Services"
        }
    ],
    "sg:phone":"+1 281 290 8200",
    "sg:postcode":"77375",
    "sg:province":"TX",
    "sg:tags":[
        "maintenance"
    ],
    "wof:name":"Kwik Kar Lube & Tune",
    "wof:placetype":"venue"
},
  "geometry": {"coordinates":[-95.626817,30.092182],"type":"Point"}
}