{
  "type": "Feature",
  "properties": {
    "iso:country":"US",
    "sg:address":"15918 Beechnut St",
    "sg:city":"Houston",
    "sg:classifiers":[
        {
            "category":"Organizations",
            "subcategory":"Community Association",
            "type":"Services"
        }
    ],
    "sg:phone":"+1 281 277 2149",
    "sg:postcode":"77083",
    "sg:province":"TX",
    "wof:name":"Sigma PI Frat International",
    "wof:placetype":"venue"
},
  "geometry": {"coordinates":[-95.668288,29.688876],"type":"Point"}
}