{
  "type": "Feature",
  "properties": {
    "iso:country":"US",
    "sg:address":"715 Indian St",
    "sg:city":"Vernon",
    "sg:classifiers":[
        {
            "category":"Organizations",
            "subcategory":"Religious Organization",
            "type":"Services"
        }
    ],
    "sg:phone":"+1 940 553 3478",
    "sg:postcode":"76384",
    "sg:province":"TX",
    "sg:tags":[
        "church"
    ],
    "wof:name":"Igl Bau Nueva Vida Baptist Ch",
    "wof:placetype":"venue"
},
  "geometry": {"coordinates":[-99.272104,34.146305],"type":"Point"}
}