{
  "type": "Feature",
  "properties": {
    "iso:country":"US",
    "sg:address":"607 Ferris Ave",
    "sg:city":"Waxahachie",
    "sg:classifiers":[
        {
            "category":"Shopping",
            "subcategory":"Clothing, Apparel, & Fashions",
            "type":"Retail Goods"
        }
    ],
    "sg:phone":"+1 972 937 6391",
    "sg:postcode":"75165",
    "sg:province":"TX",
    "sg:tags":[
        "alteration"
    ],
    "wof:name":"Carla's Alteration Shoppe",
    "wof:placetype":"venue"
},
  "geometry": {"coordinates":[-96.84710099999999,32.393536],"type":"Point"}
}