{
  "type": "Feature",
  "properties": {
    "iso:country":"US",
    "sg:address":"711 W 38th St",
    "sg:city":"Austin",
    "sg:classifiers":[
        {
            "category":"Health Services",
            "subcategory":"Clinic",
            "type":"Services"
        }
    ],
    "sg:phone":"+1 512 454 1206",
    "sg:postcode":"78705",
    "sg:province":"TX",
    "sg:tags":[
        "specialty",
        "outpatient"
    ],
    "wof:name":"Anc Neuro Cognitive Rehab",
    "wof:placetype":"venue"
},
  "geometry": {"coordinates":[-97.74132299999999,30.304274],"type":"Point"}
}