{
  "type": "Feature",
  "properties": {
    "iso:country":"US",
    "sg:address":"807 8th St",
    "sg:city":"Wichita Falls",
    "sg:classifiers":[
        {
            "category":"Professional",
            "subcategory":"Lawyer & Legal Services",
            "type":"Services"
        }
    ],
    "sg:phone":"+1 940 322 2929",
    "sg:postcode":"76301",
    "sg:province":"TX",
    "sg:tags":[
        "attorney"
    ],
    "wof:name":"Morrison & Shelton",
    "wof:placetype":"venue"
},
  "geometry": {"coordinates":[-98.493095,33.911256],"type":"Point"}
}