{
  "type": "Feature",
  "properties": {
    "iso:country":"US",
    "sg:address":"2926 Linn Rd",
    "sg:city":"San Antonio",
    "sg:classifiers":[
        {
            "category":"Professional",
            "subcategory":"Business Services",
            "type":"Services"
        }
    ],
    "sg:phone":"+1 210 381 7815",
    "sg:postcode":"78223",
    "sg:province":"TX",
    "wof:name":"Murdakill Corp",
    "wof:placetype":"venue"
},
  "geometry": {"coordinates":[-98.44385200000001,29.357328],"type":"Point"}
}