{
  "type": "Feature",
  "properties": {
    "iso:country":"US",
    "sg:address":"11 E Louis Ave",
    "sg:city":"Eldorado",
    "sg:classifiers":[
        {
            "category":"Shopping",
            "subcategory":"Used Merchandise",
            "type":"Retail Goods"
        }
    ],
    "sg:phone":"+1 325 853 3736",
    "sg:postcode":"76936",
    "sg:province":"TX",
    "wof:name":"Rose Second Hand",
    "wof:placetype":"venue"
},
  "geometry": {"coordinates":[-100.602806,30.856666],"type":"Point"}
}