{
  "type": "Feature",
  "properties": {
    "iso:country":"US",
    "sg:address":"3721 Shenandoah St",
    "sg:city":"Dallas",
    "sg:classifiers":[
        {
            "category":"Professional",
            "type":"Services"
        }
    ],
    "sg:phone":"+1 214 526 3733",
    "sg:postcode":"75205",
    "sg:province":"TX",
    "wof:name":"Ohioheadquarters Ltd",
    "wof:placetype":"venue"
},
  "geometry": {"coordinates":[-96.795215,32.839952],"type":"Point"}
}