{
  "type": "Feature",
  "properties": {
    "iso:country":"US",
    "sg:address":"935 Nature Dr",
    "sg:city":"Duncanville",
    "sg:classifiers":[
        {
            "category":"Professional",
            "subcategory":"Business Services",
            "type":"Services"
        }
    ],
    "sg:phone":"+1 972 780 8068",
    "sg:postcode":"75116",
    "sg:province":"TX",
    "wof:name":"Bpt Enterprises",
    "wof:placetype":"venue"
},
  "geometry": {"coordinates":[-96.920703,32.666374],"type":"Point"}
}