{
  "type": "Feature",
  "properties": {
    "iso:country":"US",
    "sg:address":"1314 Nolan St",
    "sg:city":"San Antonio",
    "sg:classifiers":[
        {
            "category":"Professional",
            "subcategory":"Detective & Security Services",
            "type":"Services"
        }
    ],
    "sg:phone":"+1 210 241 6830",
    "sg:postcode":"78202",
    "sg:province":"TX",
    "sg:tags":[
        "guard",
        "patrol"
    ],
    "wof:name":"Ortiz Security & Patrol",
    "wof:placetype":"venue"
},
  "geometry": {"coordinates":[-98.463397,29.427516],"type":"Point"}
}