{
  "type": "Feature",
  "properties": {
    "iso:country":"US",
    "sg:address":"1104 N I H 35",
    "sg:city":"Austin",
    "sg:classifiers":[
        {
            "category":"Retail",
            "subcategory":"Auto Rental",
            "type":"Services"
        }
    ],
    "sg:phone":"+1 512 482 9173",
    "sg:postcode":"78701",
    "sg:province":"TX",
    "sg:tags":[
        "car"
    ],
    "wof:name":"Avis",
    "wof:placetype":"venue"
},
  "geometry": {"coordinates":[-97.733417,30.270641],"type":"Point"}
}