{
  "type": "Feature",
  "properties": {
    "iso:country":"US",
    "sg:address":"700 Hwy 365",
    "sg:city":"Port Arthur",
    "sg:classifiers":[
        {
            "category":"Mining & Drilling",
            "type":"Manufacturing & Wholesale Goods"
        }
    ],
    "sg:phone":"+1 409 736 2833",
    "sg:postcode":"77640",
    "sg:province":"TX",
    "sg:tags":[
        "inspector",
        "oil"
    ],
    "wof:name":"Inspectorate America Inc",
    "wof:placetype":"venue"
},
  "geometry": {"coordinates":[-94.019419,29.919394],"type":"Point"}
}