{
  "type": "Feature",
  "properties": {
    "iso:country":"US",
    "sg:address":"2604 Mount View Dr",
    "sg:city":"Dallas",
    "sg:classifiers":[
        {
            "category":"Building & Trades",
            "subcategory":"Landscaping Services",
            "type":"Services"
        }
    ],
    "sg:phone":"+1 972 241 0072",
    "sg:postcode":"75234",
    "sg:province":"TX",
    "sg:tags":[
        "lawn",
        "maintenance",
        "grounds"
    ],
    "wof:name":"Ron's Lawn Svc",
    "wof:placetype":"venue"
},
  "geometry": {"coordinates":[-96.887658,32.920232],"type":"Point"}
}