{
  "type": "Feature",
  "properties": {
    "iso:country":"US",
    "sg:address":"2016 W Main St",
    "sg:city":"Port Lavaca",
    "sg:classifiers":[
        {
            "category":"Travel",
            "subcategory":"Hotels & Motels",
            "type":"Entertainment"
        }
    ],
    "sg:phone":"+1 361 552 9755",
    "sg:postcode":"77979",
    "sg:province":"TX",
    "sg:tags":[
        "operation"
    ],
    "wof:name":"Surf Motel",
    "wof:placetype":"venue"
},
  "geometry": {"coordinates":[-96.642921,28.609985],"type":"Point"}
}