{
  "type": "Feature",
  "properties": {
    "iso:country":"US",
    "sg:address":"2006 N Main St",
    "sg:city":"Del Rio",
    "sg:classifiers":[
        {
            "category":"Professional",
            "type":"Services"
        }
    ],
    "sg:phone":"+1 830 774 2191",
    "sg:postcode":"78840",
    "sg:province":"TX",
    "sg:tags":[
        "establishment"
    ],
    "wof:name":"Val Verde 4 H Horseclub",
    "wof:placetype":"venue"
},
  "geometry": {"coordinates":[-100.912217,29.381862],"type":"Point"}
}