{
  "type": "Feature",
  "properties": {
    "iso:country":"US",
    "sg:address":"222 Raymac St",
    "sg:city":"Houston",
    "sg:classifiers":[
        {
            "category":"Education",
            "subcategory":"School",
            "type":"Public Place"
        }
    ],
    "sg:phone":"+1 281 878 6900",
    "sg:postcode":"77037",
    "sg:province":"TX",
    "sg:tags":[
        "high",
        "middle",
        "elementary"
    ],
    "wof:name":"Aldine Independent School District",
    "wof:placetype":"venue"
},
  "geometry": {"coordinates":[-95.402866,29.902218],"type":"Point"}
}