{
  "type": "Feature",
  "properties": {
    "iso:country":"US",
    "sg:address":"9864 Harwin Dr",
    "sg:city":"Houston",
    "sg:classifiers":[
        {
            "category":"Health Services",
            "subcategory":"Doctor",
            "type":"Services"
        }
    ],
    "sg:phone":"+1 713 975 6765",
    "sg:postcode":"77036",
    "sg:province":"TX",
    "sg:tags":[
        "physician",
        "surgeon"
    ],
    "wof:name":"D N Intl",
    "wof:placetype":"venue"
},
  "geometry": {"coordinates":[-95.536294,29.717816],"type":"Point"}
}