{
  "type": "Feature",
  "properties": {
    "iso:country":"US",
    "sg:address":"3211 N Navarro St",
    "sg:city":"Victoria",
    "sg:classifiers":[
        {
            "category":"Autos & Motor Vehicles",
            "subcategory":"Automobile Sales",
            "type":"Retail Goods"
        }
    ],
    "sg:phone":"+1 361 578 0181",
    "sg:postcode":"77901",
    "sg:province":"TX",
    "sg:tags":[
        "car",
        "dealer"
    ],
    "sg:website":"www.atzenhoffer.com",
    "wof:name":"Atzenhoffer Chevrolet Cadillac",
    "wof:placetype":"venue"
},
  "geometry": {"coordinates":[-97.000821,28.824981],"type":"Point"}
}