{
  "type": "Feature",
  "properties": {
    "iso:country":"US",
    "sg:address":"500 N Texas St",
    "sg:city":"De Leon",
    "sg:classifiers":[
        {
            "category":"Museum",
            "type":"Entertainment"
        }
    ],
    "sg:phone":"+1 254 893 3773",
    "sg:postcode":"76444",
    "sg:province":"TX",
    "wof:name":"Terrill Antique Car Museum",
    "wof:placetype":"venue"
},
  "geometry": {"coordinates":[-98.535912,32.114056],"type":"Point"}
}