{
  "type": "Feature",
  "properties": {
    "iso:country":"US",
    "sg:address":"11127 Shady Trl",
    "sg:city":"Dallas",
    "sg:classifiers":[
        {
            "category":"Manufacturing",
            "subcategory":"Printing",
            "type":"Manufacturing & Wholesale Goods"
        }
    ],
    "sg:phone":"+1 972 243 3645",
    "sg:postcode":"75229",
    "sg:province":"TX",
    "sg:tags":[
        "off"
    ],
    "wof:name":"J T Graphics Inc",
    "wof:placetype":"venue"
},
  "geometry": {"coordinates":[-96.89052100000001,32.88449],"type":"Point"}
}