{
  "type": "Feature",
  "properties": {
    "iso:country":"US",
    "sg:address":"409 W Kellis St",
    "sg:city":"Fort Worth",
    "sg:classifiers":[
        {
            "category":"Social Services",
            "subcategory":"Child Care",
            "type":"Services"
        }
    ],
    "sg:phone":"+1 817 923 5768",
    "sg:postcode":"76115",
    "sg:province":"TX",
    "wof:name":"Charity Church Childcare Ctr",
    "wof:placetype":"venue"
},
  "geometry": {"coordinates":[-97.327639,32.684193],"type":"Point"}
}