{
  "type": "Feature",
  "properties": {
    "iso:country":"US",
    "sg:address":"12603 Conklin Ln",
    "sg:city":"Houston",
    "sg:classifiers":[
        {
            "category":"Banks & Credit Unions",
            "subcategory":"Bank",
            "type":"Services"
        }
    ],
    "sg:phone":"+1 281 929 2913",
    "sg:postcode":"77034",
    "sg:province":"TX",
    "wof:name":"Chase",
    "wof:placetype":"venue"
},
  "geometry": {"coordinates":[-95.206766,29.609121],"type":"Point"}
}