{
  "type": "Feature",
  "properties": {
    "iso:country":"US",
    "sg:address":"1175 Adkins Rd",
    "sg:city":"Houston",
    "sg:classifiers":[
        {
            "category":"Professional",
            "type":"Services"
        }
    ],
    "sg:phone":"+1 713 465 4995",
    "sg:postcode":"77055",
    "sg:province":"TX",
    "sg:tags":[
        "establishment"
    ],
    "wof:name":"Beatek",
    "wof:placetype":"venue"
},
  "geometry": {"coordinates":[-95.520123,29.786381],"type":"Point"}
}