{
  "type": "Feature",
  "properties": {
    "iso:country":"US",
    "sg:address":"2495 Northline Rd",
    "sg:city":"Conroe",
    "sg:classifiers":[
        {
            "category":"Building & Trades",
            "subcategory":"Construction",
            "type":"Services"
        }
    ],
    "sg:phone":"+1 936 321 2785",
    "sg:postcode":"77384",
    "sg:province":"TX",
    "sg:tags":[
        "contractor"
    ],
    "wof:name":"Garry Weatherly Contracting SE",
    "wof:placetype":"venue"
},
  "geometry": {"coordinates":[-95.473204,30.198558],"type":"Point"}
}