{
  "type": "Feature",
  "properties": {
    "iso:country":"US",
    "sg:address":"2626 Mountain View Dr",
    "sg:city":"Mc Kinney",
    "sg:classifiers":[
        {
            "category":"Retail",
            "subcategory":"Funeral Services",
            "type":"Services"
        }
    ],
    "sg:phone":"+1 972 569 8355",
    "sg:postcode":"75071",
    "sg:province":"TX",
    "wof:name":"S E Mid-Atlantic Inc",
    "wof:placetype":"venue"
},
  "geometry": {"coordinates":[-96.64630699999999,33.227759],"type":"Point"}
}