{
  "type": "Feature",
  "properties": {
    "iso:country":"US",
    "sg:address":"4201 Hahn Blvd",
    "sg:city":"Fort Worth",
    "sg:classifiers":[
        {
            "category":"Home & Garden",
            "subcategory":"Building Materials",
            "type":"Retail Goods"
        }
    ],
    "sg:phone":"+1 817 577 3837",
    "sg:postcode":"76117",
    "sg:province":"TX",
    "sg:tags":[
        "ornamental",
        "fencing",
        "iron",
        "gates"
    ],
    "wof:name":"South West Center Inc",
    "wof:placetype":"venue"
},
  "geometry": {"coordinates":[-97.283237,32.826694],"type":"Point"}
}