{
  "type": "Feature",
  "properties": {
    "iso:country":"US",
    "sg:address":"600 S Ohio Ave",
    "sg:city":"Mercedes",
    "sg:classifiers":[
        {
            "category":"Education",
            "subcategory":"School",
            "type":"Public Place"
        }
    ],
    "sg:phone":"+1 956 514 2034",
    "sg:postcode":"78570",
    "sg:province":"TX",
    "sg:website":"www.mercedes.k12.tx.us",
    "wof:name":"Mercedes Special Education",
    "wof:placetype":"venue"
},
  "geometry": {"coordinates":[-97.912137,26.145954],"type":"Point"}
}