{
  "type": "Feature",
  "properties": {
    "iso:country":"US",
    "sg:address":"1707 S Houston Rd",
    "sg:city":"Houston",
    "sg:classifiers":[
        {
            "category":"Professional",
            "subcategory":"Lawyer & Legal Services",
            "type":"Services"
        }
    ],
    "sg:phone":"+1 713 624 1000",
    "sg:postcode":"77502",
    "sg:province":"TX",
    "wof:name":"Dovalina & Eureslellt Atty",
    "wof:placetype":"venue"
},
  "geometry": {"coordinates":[-95.221225,29.685846],"type":"Point"}
}