{
  "type": "Feature",
  "properties": {
    "iso:country":"US",
    "sg:address":"5807 W 45th Ave",
    "sg:city":"Amarillo",
    "sg:classifiers":[
        {
            "category":"Retail",
            "subcategory":"Laundry & Dry Cleaning",
            "type":"Services"
        }
    ],
    "sg:phone":"+1 806 358 2844",
    "sg:postcode":"79109",
    "sg:province":"TX",
    "sg:tags":[
        "cleaners"
    ],
    "wof:name":"Us 1 99 Cleaners",
    "wof:placetype":"venue"
},
  "geometry": {"coordinates":[-101.90105699999999,35.161489],"type":"Point"}
}