{
  "type": "Feature",
  "properties": {
    "iso:country":"US",
    "sg:address":"303 Sherwood Ct",
    "sg:city":"Spring",
    "sg:classifiers":[
        {
            "category":"Building & Trades",
            "subcategory":"Construction",
            "type":"Services"
        }
    ],
    "sg:phone":"+1 281 292 0090",
    "sg:postcode":"77381",
    "sg:province":"TX",
    "sg:tags":[
        "painter"
    ],
    "wof:name":"Leco Electro Painting",
    "wof:placetype":"venue"
},
  "geometry": {"coordinates":[-95.456908,30.179935],"type":"Point"}
}