{
  "type": "Feature",
  "properties": {
    "iso:country":"US",
    "sg:address":"7301 Cherrylaurel Cv",
    "sg:city":"Tyler",
    "sg:classifiers":[
        {
            "category":"Retail",
            "subcategory":"Car Wash",
            "type":"Services"
        }
    ],
    "sg:phone":"+1 903 581 1710",
    "sg:postcode":"75703",
    "sg:province":"TX",
    "wof:name":"In Detail",
    "wof:placetype":"venue"
},
  "geometry": {"coordinates":[-95.326904,32.268677],"type":"Point"}
}