{
  "type": "Feature",
  "properties": {
    "iso:country":"US",
    "sg:address":"20329 State Highway 249 Suite 350",
    "sg:city":"Houston",
    "sg:classifiers":[
        {
            "category":"Professional",
            "subcategory":"Research",
            "type":"Services"
        }
    ],
    "sg:postcode":"77070",
    "sg:province":"TX",
    "sg:tags":[
        "houston",
        "bioenergy",
        "desalination",
        "tech-transfer",
        "texas-am"
    ],
    "sg:website":"http://www.terrabon.com",
    "wof:name":"Terrabon",
    "wof:placetype":"venue"
},
  "geometry": {"coordinates":[-95.56734,29.981178],"type":"Point"}
}