{
  "type": "Feature",
  "properties": {
    "iso:country":"US",
    "sg:address":"2151 Irving Blvd",
    "sg:city":"Dallas",
    "sg:classifiers":[
        {
            "category":"Building & Trades",
            "subcategory":"Construction",
            "type":"Services"
        }
    ],
    "sg:phone":"+1 214 571 9226",
    "sg:postcode":"75247",
    "sg:province":"TX",
    "sg:tags":[
        "contractor"
    ],
    "wof:name":"Center Point Builders",
    "wof:placetype":"venue"
},
  "geometry": {"coordinates":[-96.832353,32.795678],"type":"Point"}
}