{
  "type": "Feature",
  "properties": {
    "iso:country":"US",
    "sg:address":"1005 West Ave",
    "sg:city":"San Antonio",
    "sg:classifiers":[
        {
            "category":"Shopping",
            "subcategory":"Pharmacy",
            "type":"Retail Goods"
        }
    ],
    "sg:phone":"+1 210 733 3103",
    "sg:postcode":"78201",
    "sg:province":"TX",
    "wof:name":"Parker Pharmacy Iv Svc",
    "wof:placetype":"venue"
},
  "geometry": {"coordinates":[-98.52601,29.471183],"type":"Point"}
}