{
  "type": "Feature",
  "properties": {
    "iso:country":"US",
    "sg:address":"5005 Riverway Dr",
    "sg:city":"Houston",
    "sg:classifiers":[
        {
            "category":"Farming",
            "subcategory":"Livestock Farm",
            "type":"Manufacturing & Wholesale Goods"
        }
    ],
    "sg:phone":"+1 713 627 3884",
    "sg:postcode":"77056",
    "sg:province":"TX",
    "sg:tags":[
        "ranch"
    ],
    "wof:name":"74 Ranch",
    "wof:placetype":"venue"
},
  "geometry": {"coordinates":[-95.465597,29.761211],"type":"Point"}
}