{
  "type": "Feature",
  "properties": {
    "iso:country":"US",
    "sg:address":"8707 Cadawac Rd",
    "sg:city":"Houston",
    "sg:classifiers":[
        {
            "category":"Manufacturing",
            "subcategory":"Tools & Machinery",
            "type":"Manufacturing & Wholesale Goods"
        },
        {
            "category":"Professional",
            "type":"Services"
        },
        {
            "category":"Animal Shelter",
            "type":"Public Place"
        },
        {
            "category":"Building & Trades",
            "subcategory":"Pest Control",
            "type":"Services"
        },
        {
            "category":"Manufacturing",
            "subcategory":"Chemicals & Compounds",
            "type":"Manufacturing & Wholesale Goods"
        },
        {
            "category":"Building & Trades",
            "subcategory":"Landscaping Services",
            "type":"Services"
        }
    ],
    "sg:phone":"+1 713 777 8512",
    "sg:postcode":"77074",
    "sg:province":"TX",
    "sg:tags":[
        "lawn",
        "spraying",
        "supply",
        "termite",
        "removal",
        "equipment",
        "fertilizing",
        "maintenance"
    ],
    "sg:website":"http://www.pioneerexterminating.com",
    "wof:name":"Pioneer Exterminating Co",
    "wof:placetype":"venue"
},
  "geometry": {"coordinates":[-95.511867,29.685033],"type":"Point"}
}