{
  "type": "Feature",
  "properties": {
    "iso:country":"US",
    "sg:address":"3544 Ranch Rd 620 S",
    "sg:city":"Bee Cave",
    "sg:classifiers":[
        {
            "category":"Building & Trades",
            "subcategory":"Construction",
            "type":"Services"
        }
    ],
    "sg:phone":"+1 512 263 2184",
    "sg:postcode":"78738",
    "sg:province":"TX",
    "sg:tags":[
        "home",
        "builder"
    ],
    "wof:name":"Falconhead",
    "wof:placetype":"venue"
},
  "geometry": {"coordinates":[-97.95084199999999,30.318456],"type":"Point"}
}