{
  "type": "Feature",
  "properties": {
    "iso:country":"US",
    "sg:address":"13 Auburn Ct",
    "sg:city":"Midland",
    "sg:classifiers":[
        {
            "category":"Professional",
            "subcategory":"Business Services",
            "type":"Services"
        }
    ],
    "sg:phone":"+1 432 686 0450",
    "sg:postcode":"79705",
    "sg:province":"TX",
    "wof:name":"Air Compressor Solutions Inc",
    "wof:placetype":"venue"
},
  "geometry": {"coordinates":[-102.116727,32.027374],"type":"Point"}
}