{
  "type": "Feature",
  "properties": {
    "iso:country":"US",
    "sg:address":"1816 Singleton Blvd",
    "sg:city":"Dallas",
    "sg:classifiers":[
        {
            "category":"Building & Trades",
            "subcategory":"Electrical",
            "type":"Services"
        },
        {
            "category":"Retail",
            "subcategory":"Auto Repair",
            "type":"Services"
        }
    ],
    "sg:phone":"+1 214 744 3022",
    "sg:postcode":"75212",
    "sg:province":"TX",
    "sg:tags":[
        "automobile",
        "electrician",
        "electric"
    ],
    "wof:name":"Sierra Auto Electric",
    "wof:placetype":"venue"
},
  "geometry": {"coordinates":[-96.848338,32.778544],"type":"Point"}
}