{
  "type": "Feature",
  "properties": {
    "iso:country":"US",
    "sg:address":"1806 Lee St",
    "sg:city":"New Braunfels",
    "sg:classifiers":[
        {
            "category":"Organizations",
            "subcategory":"Religious Organization",
            "type":"Services"
        }
    ],
    "sg:phone":"+1 830 625 4704",
    "sg:postcode":"78130",
    "sg:province":"TX",
    "sg:tags":[
        "church"
    ],
    "wof:name":"Pentecostal Jerusalem Church",
    "wof:placetype":"venue"
},
  "geometry": {"coordinates":[-98.13713300000001,29.687147],"type":"Point"}
}