{
  "type": "Feature",
  "properties": {
    "iso:country":"US",
    "sg:address":"5829 Belmont Ave",
    "sg:city":"Dallas",
    "sg:classifiers":[
        {
            "category":"Banks & Credit Unions",
            "subcategory":"Bank",
            "type":"Services"
        }
    ],
    "sg:phone":"+1 214 887 8400",
    "sg:postcode":"75206",
    "sg:province":"TX",
    "sg:tags":[
        "personal",
        "institution"
    ],
    "wof:name":"First United Lending",
    "wof:placetype":"venue"
},
  "geometry": {"coordinates":[-96.766358,32.817422],"type":"Point"}
}