{
  "type": "Feature",
  "properties": {
    "iso:country":"US",
    "sg:address":"198 Texas Ave",
    "sg:city":"Deweyville",
    "sg:classifiers":[
        {
            "category":"Utilities",
            "subcategory":"Water",
            "type":"Services"
        }
    ],
    "sg:phone":"+1 409 746 2271",
    "sg:postcode":"77627",
    "sg:province":"TX",
    "sg:tags":[
        "system",
        "supply"
    ],
    "wof:name":"South Newton Water Supply Corp",
    "wof:placetype":"venue"
},
  "geometry": {"coordinates":[-93.97692000000001,29.985393],"type":"Point"}
}