{
  "type": "Feature",
  "properties": {
    "iso:country":"US",
    "sg:address":"6666 Gateway Blvd E",
    "sg:city":"El Paso",
    "sg:classifiers":[
        {
            "category":"Autos & Motor Vehicles",
            "subcategory":"Fuel & Gas Station",
            "type":"Retail Goods"
        }
    ],
    "sg:phone":"+1 915 772 1441",
    "sg:postcode":"79915",
    "sg:province":"TX",
    "sg:tags":[
        "plaza",
        "truck",
        "stops"
    ],
    "wof:name":"El Paso Truck Terminal Inc",
    "wof:placetype":"venue"
},
  "geometry": {"coordinates":[-106.39366800000001,31.778656],"type":"Point"}
}