{
  "type": "Feature",
  "properties": {
    "iso:country":"US",
    "sg:address":"425 S Carroll St Ste 3",
    "sg:city":"Athens",
    "sg:classifiers":[
        {
            "category":"Health Services",
            "subcategory":"Doctor",
            "type":"Services"
        }
    ],
    "sg:phone":"+1 903 677 8471",
    "sg:postcode":"75751",
    "sg:province":"TX",
    "sg:tags":[
        "physician",
        "surgeon"
    ],
    "wof:name":"Renal Care Group-Athens",
    "wof:placetype":"venue"
},
  "geometry": {"coordinates":[-95.852306,32.199378],"type":"Point"}
}