{
  "type": "Feature",
  "properties": {
    "iso:country":"US",
    "sg:address":"2960 Wesley Way",
    "sg:city":"Fort Worth",
    "sg:classifiers":[
        {
            "category":"Building & Trades",
            "subcategory":"Construction",
            "type":"Services"
        }
    ],
    "sg:phone":"+1 817 284 2100",
    "sg:postcode":"76118",
    "sg:province":"TX",
    "sg:tags":[
        "floor",
        "laying",
        "contractor"
    ],
    "wof:name":"Dupont",
    "wof:placetype":"venue"
},
  "geometry": {"coordinates":[-97.216285,32.805516],"type":"Point"}
}