{
  "type": "Feature",
  "properties": {
    "iso:country":"US",
    "sg:address":"14302 Juniper Cove",
    "sg:city":"Dallas",
    "sg:classifiers":[
        {
            "category":"Wholesale",
            "subcategory":"Apparel",
            "type":"Manufacturing & Wholesale Goods"
        }
    ],
    "sg:phone":"+1 972 243 4164",
    "sg:postcode":"75234",
    "sg:province":"TX",
    "sg:tags":[
        "piece"
    ],
    "wof:name":"Butons Fantaise",
    "wof:placetype":"venue"
},
  "geometry": {"coordinates":[-96.869195,32.943726],"type":"Point"}
}