{
  "type": "Feature",
  "properties": {
    "iso:country":"US",
    "sg:address":"333 N Midkiff Rd",
    "sg:city":"Midland",
    "sg:classifiers":[
        {
            "category":"Personal",
            "subcategory":"Beauty Salon",
            "type":"Services"
        }
    ],
    "sg:phone":"+1 432 689 3703",
    "sg:postcode":"79701",
    "sg:province":"TX",
    "sg:tags":[
        "shop"
    ],
    "wof:name":"Michael's Hair Factory",
    "wof:placetype":"venue"
},
  "geometry": {"coordinates":[-102.11622,31.992479],"type":"Point"}
}