{
  "type": "Feature",
  "properties": {
    "iso:country":"US",
    "sg:address":"5245 Chessie Cir",
    "sg:city":"Fort Worth",
    "sg:classifiers":[
        {
            "category":"Manufacturing",
            "subcategory":"Food",
            "type":"Manufacturing & Wholesale Goods"
        }
    ],
    "sg:phone":"+1 817 498 7672",
    "sg:postcode":"76137",
    "sg:province":"TX",
    "sg:tags":[
        "mfg"
    ],
    "wof:name":"Sweet Ideas",
    "wof:placetype":"venue"
},
  "geometry": {"coordinates":[-97.27668799999999,32.850403],"type":"Point"}
}