{
  "type": "Feature",
  "properties": {
    "iso:country":"US",
    "sg:address":"16026 Miller Road 1",
    "sg:city":"Houston",
    "sg:classifiers":[
        {
            "category":"Mining & Drilling",
            "type":"Manufacturing & Wholesale Goods"
        }
    ],
    "sg:phone":"+1 281 457 6617",
    "sg:postcode":"77049",
    "sg:province":"TX",
    "sg:tags":[
        "natural",
        "gas"
    ],
    "wof:name":"Lone Star Hydril & Maintenance",
    "wof:placetype":"venue"
},
  "geometry": {"coordinates":[-95.127697,29.835936],"type":"Point"}
}