{
  "type": "Feature",
  "properties": {
    "iso:country":"US",
    "sg:address":"2402 Stone Pine Ct",
    "sg:city":"Harlingen",
    "sg:classifiers":[
        {
            "category":"Utilities",
            "subcategory":"Telephone",
            "type":"Services"
        }
    ],
    "sg:phone":"+1 956 428 8311",
    "sg:postcode":"78550",
    "sg:province":"TX",
    "sg:tags":[
        "telecommunication"
    ],
    "wof:name":"Rio Marketing & Communications",
    "wof:placetype":"venue"
},
  "geometry": {"coordinates":[-97.65919599999999,26.173864],"type":"Point"}
}