{
  "type": "Feature",
  "properties": {
    "iso:country":"US",
    "sg:address":"5407 Everhart Rd",
    "sg:city":"Corpus Christi",
    "sg:classifiers":[
        {
            "category":"Retail",
            "subcategory":"Portrait Studio",
            "type":"Services"
        }
    ],
    "sg:phone":"+1 361 857 8068",
    "sg:postcode":"78411",
    "sg:province":"TX",
    "sg:tags":[
        "photo",
        "photographer"
    ],
    "wof:name":"Ward John Photography",
    "wof:placetype":"venue"
},
  "geometry": {"coordinates":[-97.388087,27.708511],"type":"Point"}
}