{
  "type": "Feature",
  "properties": {
    "iso:country":"US",
    "sg:address":"5927 Gateway Blvd W",
    "sg:city":"El Paso",
    "sg:classifiers":[
        {
            "category":"Professional",
            "subcategory":"Management & Consulting",
            "type":"Services"
        }
    ],
    "sg:phone":"+1 915 544 5698",
    "sg:postcode":"79935",
    "sg:province":"TX",
    "sg:tags":[
        "consultant",
        "resource",
        "human"
    ],
    "sg:website":"www.humanelement.biz",
    "wof:name":"Human Element Of Business Inc",
    "wof:placetype":"venue"
},
  "geometry": {"coordinates":[-106.41725,31.780643],"type":"Point"}
}