{
  "type": "Feature",
  "properties": {
    "iso:country":"US",
    "sg:address":"319 State Hwy 100",
    "sg:city":"Port Isabel",
    "sg:classifiers":[
        {
            "category":"Local Transit",
            "type":"Transportation"
        }
    ],
    "sg:phone":"+1 956 943 1961",
    "sg:postcode":"78578",
    "sg:province":"TX",
    "sg:tags":[
        "bus",
        "line"
    ],
    "wof:name":"Valley Transit Co Inc",
    "wof:placetype":"venue"
},
  "geometry": {"coordinates":[-97.212374,26.07446],"type":"Point"}
}