{
  "type": "Feature",
  "properties": {
    "iso:country":"US",
    "sg:address":"1611 Main Blvd",
    "sg:city":"Brownwood",
    "sg:classifiers":[
        {
            "category":"Retail",
            "subcategory":"Auto Repair",
            "type":"Services"
        }
    ],
    "sg:phone":"+1 325 646 0068",
    "sg:postcode":"76801",
    "sg:province":"TX",
    "sg:tags":[
        "machinist"
    ],
    "wof:name":"Rhonda Gail Goins",
    "wof:placetype":"venue"
},
  "geometry": {"coordinates":[-98.991367,31.7359],"type":"Point"}
}