{
  "type": "Feature",
  "properties": {
    "iso:country":"US",
    "sg:address":"12613 State Hwy 6",
    "sg:city":"Santa Fe",
    "sg:classifiers":[
        {
            "category":"Retail",
            "subcategory":"Repair Shop",
            "type":"Services"
        }
    ],
    "sg:phone":"+1 409 925 1379",
    "sg:postcode":"77510",
    "sg:province":"TX",
    "sg:tags":[
        "welding"
    ],
    "wof:name":"Mc Guire Welding Svc",
    "wof:placetype":"venue"
},
  "geometry": {"coordinates":[-95.097638,29.3755],"type":"Point"}
}