{
  "type": "Feature",
  "properties": {
    "iso:country":"US",
    "sg:address":"916 Palestine St",
    "sg:city":"Conroe",
    "sg:classifiers":[
        {
            "category":"Building & Trades",
            "subcategory":"Landscaping Services",
            "type":"Services"
        }
    ],
    "sg:phone":"+1 936 788 2003",
    "sg:postcode":"77301",
    "sg:province":"TX",
    "sg:tags":[
        "landscape",
        "contractor"
    ],
    "wof:name":"Buenavista Landscaping",
    "wof:placetype":"venue"
},
  "geometry": {"coordinates":[-95.461297,30.317293],"type":"Point"}
}