{
  "type": "Feature",
  "properties": {
    "iso:country":"US",
    "sg:address":"4760 Sherwood Ln",
    "sg:city":"Houston",
    "sg:classifiers":[
        {
            "category":"Travel",
            "subcategory":"Hotels & Motels",
            "type":"Entertainment"
        }
    ],
    "sg:phone":"+1 713 686 5525",
    "sg:postcode":"77092",
    "sg:province":"TX",
    "sg:website":"www.choicehotels.com",
    "wof:name":"Comfort Inn Brookhollow",
    "wof:placetype":"venue"
},
  "geometry": {"coordinates":[-95.462402,29.814199],"type":"Point"}
}