{
  "type": "Feature",
  "properties": {
    "iso:country":"US",
    "sg:address":"306 N Market St",
    "sg:city":"Dallas",
    "sg:classifiers":[
        {
            "category":"Restaurant",
            "type":"Food & Drink"
        }
    ],
    "sg:menulink":"http://www.allmenus.com/tx/northeast/20661-landrys-seafood-house/menu/",
    "sg:phone":"+1 214 698 1010",
    "sg:postcode":"75202",
    "sg:province":"TX",
    "sg:tags":[
        "seafood",
        "american"
    ],
    "wof:name":"Landry's Seafood House",
    "wof:placetype":"venue"
},
  "geometry": {"coordinates":[-96.806512,32.780755],"type":"Point"}
}