{
  "type": "Feature",
  "properties": {
    "iso:country":"US",
    "sg:address":"8851 Bruton Rd",
    "sg:city":"Dallas",
    "sg:classifiers":[
        {
            "category":"Organizations",
            "subcategory":"Religious Organization",
            "type":"Services"
        }
    ],
    "sg:phone":"+1 214 381 6193",
    "sg:postcode":"75217",
    "sg:province":"TX",
    "sg:tags":[
        "church"
    ],
    "wof:name":"Bruton Terrace Chr-Nazarene",
    "wof:placetype":"venue"
},
  "geometry": {"coordinates":[-96.672104,32.748678],"type":"Point"}
}