{
  "type": "Feature",
  "properties": {
    "iso:country":"US",
    "sg:address":"2525 N Main St",
    "sg:city":"Belton",
    "sg:classifiers":[
        {
            "category":"Retail",
            "subcategory":"Funeral Services",
            "type":"Services"
        }
    ],
    "sg:phone":"+1 254 933 2525",
    "sg:postcode":"76513",
    "sg:province":"TX",
    "sg:tags":[
        "director"
    ],
    "sg:website":"www.dossmanfh.com",
    "wof:name":"Dossman Funeral Home",
    "wof:placetype":"venue"
},
  "geometry": {"coordinates":[-97.45745700000001,31.080025],"type":"Point"}
}