{
  "type": "Feature",
  "properties": {
    "iso:country":"US",
    "sg:address":"801 Quince Ave",
    "sg:city":"Mcallen",
    "sg:classifiers":[
        {
            "category":"Wholesale",
            "subcategory":"Electrical",
            "type":"Manufacturing & Wholesale Goods"
        }
    ],
    "sg:phone":"+1 956 843 8187",
    "sg:postcode":"78501",
    "sg:province":"TX",
    "sg:tags":[
        "comm",
        "system",
        "microwave"
    ],
    "wof:name":"Bordercomm Inc",
    "wof:placetype":"venue"
},
  "geometry": {"coordinates":[-98.226412,26.218776],"type":"Point"}
}