{
  "type": "Feature",
  "properties": {
    "iso:country":"US",
    "sg:address":"410 E Irving Blvd",
    "sg:city":"Irving",
    "sg:classifiers":[
        {
            "category":"Manufacturing",
            "subcategory":"Apparel",
            "type":"Manufacturing & Wholesale Goods"
        }
    ],
    "sg:phone":"+1 972 721 9961",
    "sg:postcode":"75060",
    "sg:province":"TX",
    "sg:tags":[
        "sewing",
        "contractor"
    ],
    "wof:name":"B & L Sewing",
    "wof:placetype":"venue"
},
  "geometry": {"coordinates":[-96.94037899999999,32.81375],"type":"Point"}
}