{
  "type": "Feature",
  "properties": {
    "iso:country":"US",
    "sg:address":"307 N Louise St",
    "sg:city":"Atlanta",
    "sg:classifiers":[
        {
            "category":"Wholesale",
            "subcategory":"Construction Materials",
            "type":"Manufacturing & Wholesale Goods"
        },
        {
            "category":"Manufacturing",
            "subcategory":"Lumber",
            "type":"Manufacturing & Wholesale Goods"
        }
    ],
    "sg:phone":"+1 903 796 7691",
    "sg:postcode":"75551",
    "sg:province":"TX",
    "sg:tags":[
        "timberland",
        "company",
        "contractor",
        "pulpwood",
        "timber"
    ],
    "wof:name":"Douglassville Timber Company",
    "wof:placetype":"venue"
},
  "geometry": {"coordinates":[-94.166657,33.119383],"type":"Point"}
}