{
  "type": "Feature",
  "properties": {
    "iso:country":"US",
    "sg:address":"16415 Addison Rd",
    "sg:city":"Addison",
    "sg:classifiers":[
        {
            "category":"Insurance",
            "subcategory":"Insurance Agent",
            "type":"Services"
        }
    ],
    "sg:phone":"+1 972 588 2000",
    "sg:postcode":"75001",
    "sg:province":"TX",
    "wof:name":"Midlands Management of Texas",
    "wof:placetype":"venue"
},
  "geometry": {"coordinates":[-96.83040800000001,32.975172],"type":"Point"}
}