{
  "type": "Feature",
  "properties": {
    "iso:country":"US",
    "sg:address":"129 2nd St",
    "sg:city":"La Joya",
    "sg:classifiers":[
        {
            "category":"Organizations",
            "subcategory":"Religious Organization",
            "type":"Services"
        }
    ],
    "sg:phone":"+1 956 580 1555",
    "sg:postcode":"78560",
    "sg:province":"TX",
    "wof:name":"Living Word Assembly",
    "wof:placetype":"venue"
},
  "geometry": {"coordinates":[-98.481587,26.246636],"type":"Point"}
}