{
  "type": "Feature",
  "properties": {
    "iso:country":"US",
    "sg:address":"6331 Maple Dr",
    "sg:city":"Humble",
    "sg:classifiers":[
        {
            "category":"Manufacturing",
            "subcategory":"Printing",
            "type":"Manufacturing & Wholesale Goods"
        }
    ],
    "sg:phone":"+1 281 446 3966",
    "sg:postcode":"77338",
    "sg:province":"TX",
    "sg:tags":[
        "scanning",
        "supply",
        "lithographic",
        "commercial",
        "equipment",
        "plotting"
    ],
    "sg:website":"http://www.thorntonsprinters.com",
    "wof:name":"Thornton Printers",
    "wof:placetype":"venue"
},
  "geometry": {"coordinates":[-95.32962000000001,30.014702],"type":"Point"}
}