{
  "type": "Feature",
  "properties": {
    "iso:country":"US",
    "sg:address":"9303 Kay Ln",
    "sg:city":"Houston",
    "sg:classifiers":[
        {
            "category":"Retail",
            "subcategory":"Repair Shop",
            "type":"Services"
        }
    ],
    "sg:phone":"+1 713 466 7551",
    "sg:postcode":"77064",
    "sg:province":"TX",
    "sg:tags":[
        "welding"
    ],
    "wof:name":"Harvey's Alloy Welding Svc",
    "wof:placetype":"venue"
},
  "geometry": {"coordinates":[-95.531524,29.910271],"type":"Point"}
}