{
  "type": "Feature",
  "properties": {
    "iso:country":"US",
    "sg:address":"406 Preston Ave",
    "sg:city":"Pasadena",
    "sg:classifiers":[
        {
            "category":"Wholesale",
            "subcategory":"Auto Parts",
            "type":"Manufacturing & Wholesale Goods"
        }
    ],
    "sg:phone":"+1 713 477 0219",
    "sg:postcode":"77503",
    "sg:province":"TX",
    "sg:tags":[
        "body",
        "automobile",
        "shop"
    ],
    "wof:name":"Finish Master",
    "wof:placetype":"venue"
},
  "geometry": {"coordinates":[-95.171334,29.704955],"type":"Point"}
}