{
  "type": "Feature",
  "properties": {
    "iso:country":"US",
    "sg:address":"5270 Meadowbrook Dr",
    "sg:city":"Fort Worth",
    "sg:classifiers":[
        {
            "category":"Professional",
            "subcategory":"Business Services",
            "type":"Services"
        }
    ],
    "sg:phone":"+1 817 496 0585",
    "sg:postcode":"76112",
    "sg:province":"TX",
    "wof:name":"Bijoux",
    "wof:placetype":"venue"
},
  "geometry": {"coordinates":[-97.23980899999999,32.745619],"type":"Point"}
}