{
  "type": "Feature",
  "properties": {
    "iso:country":"US",
    "sg:address":"12469 Twin Lakes Ln",
    "sg:city":"San Angelo",
    "sg:classifiers":[
        {
            "category":"Building & Trades",
            "subcategory":"Electrical",
            "type":"Services"
        }
    ],
    "sg:phone":"+1 325 651 4143",
    "sg:postcode":"76906",
    "sg:province":"TX",
    "sg:tags":[
        "electric",
        "contractor"
    ],
    "wof:name":"M D Hudgens Electric",
    "wof:placetype":"venue"
},
  "geometry": {"coordinates":[-100.623092,31.306881],"type":"Point"}
}