{
  "type": "Feature",
  "properties": {
    "iso:country":"US",
    "sg:address":"10914 Glenwolde Dr",
    "sg:city":"Houston",
    "sg:classifiers":[
        {
            "category":"Professional",
            "subcategory":"Business Services",
            "type":"Services"
        }
    ],
    "sg:phone":"+1 281 879 8349",
    "sg:postcode":"77099",
    "sg:province":"TX",
    "wof:name":"Creations By M E E",
    "wof:placetype":"venue"
},
  "geometry": {"coordinates":[-95.571335,29.679945],"type":"Point"}
}