{
  "type": "Feature",
  "properties": {
    "iso:country":"US",
    "sg:address":"1 Woods Estates Dr",
    "sg:city":"Conroe",
    "sg:classifiers":[
        {
            "category":"Sports & Exercise",
            "subcategory":"Golf",
            "type":"Entertainment"
        }
    ],
    "sg:phone":"+1 936 760 1988",
    "sg:postcode":"77304",
    "sg:province":"TX",
    "sg:tags":[
        "course"
    ],
    "wof:name":"Wedgewood Golf Course Mntnc",
    "wof:placetype":"venue"
},
  "geometry": {"coordinates":[-95.516976,30.346873],"type":"Point"}
}