{
  "type": "Feature",
  "properties": {
    "iso:country":"US",
    "sg:address":"627 State Hwy 70",
    "sg:city":"Spur",
    "sg:classifiers":[
        {
            "category":"Personal",
            "subcategory":"Beauty Salon",
            "type":"Services"
        }
    ],
    "sg:phone":"+1 806 271 4040",
    "sg:postcode":"79370",
    "sg:province":"TX",
    "wof:name":"Debbe's Cut Ups",
    "wof:placetype":"venue"
},
  "geometry": {"coordinates":[-100.84638,33.475503],"type":"Point"}
}