{
  "type": "Feature",
  "properties": {
    "iso:country":"US",
    "sg:address":"4617 Nett St",
    "sg:city":"Houston",
    "sg:classifiers":[
        {
            "category":"Building & Trades",
            "subcategory":"Equipment Rental",
            "type":"Services"
        }
    ],
    "sg:phone":"+1 713 699 9911",
    "sg:postcode":"77007",
    "sg:province":"TX",
    "sg:tags":[
        "party",
        "supply"
    ],
    "wof:name":"A Finer Event",
    "wof:placetype":"venue"
},
  "geometry": {"coordinates":[-95.408203,29.771873],"type":"Point"}
}