{
  "type": "Feature",
  "properties": {
    "iso:country":"US",
    "sg:address":"18121 Whitewater Cove",
    "sg:city":"Round Rock",
    "sg:classifiers":[
        {
            "category":"Professional",
            "subcategory":"Management & Consulting",
            "type":"Services"
        }
    ],
    "sg:phone":"+1 512 341 3521",
    "sg:postcode":"78681",
    "sg:province":"TX",
    "sg:tags":[
        "business"
    ],
    "wof:name":"Anthony A McKenzie Consulting",
    "wof:placetype":"venue"
},
  "geometry": {"coordinates":[-97.72028400000001,30.521169],"type":"Point"}
}