{
  "type": "Feature",
  "properties": {
    "iso:country":"US",
    "sg:address":"4050 Creek Rd",
    "sg:city":"Temple",
    "sg:classifiers":[
        {
            "category":"Building & Trades",
            "subcategory":"Landscaping Services",
            "type":"Services"
        }
    ],
    "sg:phone":"+1 254 984 2425",
    "sg:postcode":"76501",
    "sg:province":"TX",
    "wof:name":"Seasons Best Lawn Care",
    "wof:placetype":"venue"
},
  "geometry": {"coordinates":[-97.23318399999999,31.10279],"type":"Point"}
}