{
  "type": "Feature",
  "properties": {
    "iso:country":"US",
    "sg:address":"2675 Brenner Dr",
    "sg:city":"Dallas",
    "sg:classifiers":[
        {
            "category":"Wholesale",
            "subcategory":"Auto Parts",
            "type":"Manufacturing & Wholesale Goods"
        }
    ],
    "sg:phone":"+1 214 351 5754",
    "sg:postcode":"75220",
    "sg:province":"TX",
    "sg:tags":[
        "repair",
        "automotive"
    ],
    "wof:name":"Just Brake",
    "wof:placetype":"venue"
},
  "geometry": {"coordinates":[-96.887176,32.872116],"type":"Point"}
}