{
  "type": "Feature",
  "properties": {
    "iso:country":"US",
    "sg:address":"3809 Carey St",
    "sg:city":"Fort Worth",
    "sg:classifiers":[
        {
            "category":"Professional",
            "subcategory":"Business Services",
            "type":"Services"
        }
    ],
    "sg:phone":"+1 817 457 1739",
    "sg:postcode":"76119",
    "sg:province":"TX",
    "wof:name":"Be Blessed Enterprises",
    "wof:placetype":"venue"
},
  "geometry": {"coordinates":[-97.243262,32.707421],"type":"Point"}
}