{
  "type": "Feature",
  "properties": {
    "iso:country":"US",
    "sg:address":"200 Congress Ave",
    "sg:city":"Austin",
    "sg:classifiers":[
        {
            "category":"Retail",
            "subcategory":"Auto Repair",
            "type":"Services"
        }
    ],
    "sg:phone":"+1 512 322 9666",
    "sg:postcode":"78701",
    "sg:province":"TX",
    "wof:name":"Cobb Mechanical",
    "wof:placetype":"venue"
},
  "geometry": {"coordinates":[-97.744327,30.26438],"type":"Point"}
}