{
  "type": "Feature",
  "properties": {
    "iso:country":"US",
    "sg:address":"2515 Avila Dr",
    "sg:city":"Houston",
    "sg:classifiers":[
        {
            "category":"Building & Trades",
            "subcategory":"Pest Control",
            "type":"Services"
        }
    ],
    "sg:phone":"+1 281 820 0468",
    "sg:postcode":"77038",
    "sg:province":"TX",
    "wof:name":"Sudden Death Pest Control",
    "wof:placetype":"venue"
},
  "geometry": {"coordinates":[-95.448477,29.901397],"type":"Point"}
}