{
  "type": "Feature",
  "properties": {
    "iso:country":"US",
    "sg:address":"8502 Braeburn Valley Dr",
    "sg:city":"Houston",
    "sg:classifiers":[
        {
            "category":"Arts & Performance",
            "subcategory":"Theater",
            "type":"Entertainment"
        }
    ],
    "sg:phone":"+1 832 875 1831",
    "sg:postcode":"77074",
    "sg:province":"TX",
    "sg:tags":[
        "group"
    ],
    "wof:name":"Kiss Tribute Band",
    "wof:placetype":"venue"
},
  "geometry": {"coordinates":[-95.517724,29.68568],"type":"Point"}
}