{
  "type": "Feature",
  "properties": {
    "iso:country":"US",
    "sg:address":"208 E X St",
    "sg:city":"Deer Park",
    "sg:classifiers":[
        {
            "category":"Freight",
            "type":"Transportation"
        }
    ],
    "sg:phone":"+1 281 476 9209",
    "sg:postcode":"77536",
    "sg:province":"TX",
    "sg:tags":[
        "specialist",
        "repair",
        "consultant",
        "industry",
        "car",
        "railroad"
    ],
    "wof:name":"Allrail Services LTD",
    "wof:placetype":"venue"
},
  "geometry": {"coordinates":[-95.12207100000001,29.694672],"type":"Point"}
}