{
  "type": "Feature",
  "properties": {
    "iso:country":"US",
    "sg:address":"4800 Fournace Pl",
    "sg:city":"Bellaire",
    "sg:classifiers":[
        {
            "category":"Mining & Drilling",
            "type":"Manufacturing & Wholesale Goods"
        }
    ],
    "sg:phone":"+1 713 432 8000",
    "sg:postcode":"77401",
    "sg:province":"TX",
    "sg:tags":[
        "gas",
        "oil",
        "exploration"
    ],
    "wof:name":"Texas Exploration Myanmar",
    "wof:placetype":"venue"
},
  "geometry": {"coordinates":[-95.462265,29.716708],"type":"Point"}
}