{
  "type": "Feature",
  "properties": {
    "iso:country":"US",
    "sg:address":"6300 Glenview Dr",
    "sg:city":"Fort Worth",
    "sg:classifiers":[
        {
            "category":"Manufacturing",
            "subcategory":"Tools & Machinery",
            "type":"Manufacturing & Wholesale Goods"
        }
    ],
    "sg:phone":"+1 817 589 1211",
    "sg:postcode":"76180",
    "sg:province":"TX",
    "sg:tags":[
        "mfg"
    ],
    "wof:name":"Randys Die Cast &",
    "wof:placetype":"venue"
},
  "geometry": {"coordinates":[-97.248932,32.82624],"type":"Point"}
}