{
  "type": "Feature",
  "properties": {
    "iso:country":"US",
    "sg:address":"146 Out Look Dr",
    "sg:city":"Houston",
    "sg:classifiers":[
        {
            "category":"Farming",
            "subcategory":"Nursery",
            "type":"Manufacturing & Wholesale Goods"
        }
    ],
    "sg:phone":"+1 713 947 7482",
    "sg:postcode":"77034",
    "sg:province":"TX",
    "sg:tags":[
        "ornamental"
    ],
    "wof:name":"Jessicas Plants",
    "wof:placetype":"venue"
},
  "geometry": {"coordinates":[-95.215064,29.647677],"type":"Point"}
}