{
  "type": "Feature",
  "properties": {
    "iso:country":"US",
    "sg:address":"16111 Chimney Rock Rd",
    "sg:city":"Houston",
    "sg:classifiers":[
        {
            "category":"Government",
            "subcategory":"Fire Station",
            "type":"Public Place"
        }
    ],
    "sg:phone":"+1 713 222 7643",
    "sg:postcode":"77053",
    "sg:province":"TX",
    "sg:tags":[
        "protection"
    ],
    "wof:name":"Fire Dept-Station 80",
    "wof:placetype":"venue"
},
  "geometry": {"coordinates":[-95.483632,29.591689],"type":"Point"}
}