{
  "type": "Feature",
  "properties": {
    "iso:country":"US",
    "sg:address":"400 W Bay Area Blvd",
    "sg:city":"Webster",
    "sg:classifiers":[
        {
            "category":"Personal",
            "subcategory":"Beauty Salon",
            "type":"Services"
        }
    ],
    "sg:phone":"+1 281 338 0968",
    "sg:postcode":"77598",
    "sg:province":"TX",
    "wof:name":"Manetamers",
    "wof:placetype":"venue"
},
  "geometry": {"coordinates":[-95.131531,29.546749],"type":"Point"}
}