{
  "type": "Feature",
  "properties": {
    "iso:country":"US",
    "sg:address":"5105 S Western St",
    "sg:city":"Amarillo",
    "sg:classifiers":[
        {
            "category":"Shopping",
            "subcategory":"Computers & Home Electronics",
            "type":"Retail Goods"
        }
    ],
    "sg:phone":"+1 806 353 9357",
    "sg:postcode":"79109",
    "sg:province":"TX",
    "sg:tags":[
        "equipment",
        "dealer"
    ],
    "wof:name":"Amarillo Tech Inc",
    "wof:placetype":"venue"
},
  "geometry": {"coordinates":[-101.883848,35.152211],"type":"Point"}
}