{
  "type": "Feature",
  "properties": {
    "iso:country":"US",
    "sg:address":"2000 N Plano Rd",
    "sg:city":"Richardson",
    "sg:classifiers":[
        {
            "category":"Professional",
            "type":"Services"
        }
    ],
    "sg:phone":"+1 972 437 3003",
    "sg:postcode":"75082",
    "sg:province":"TX",
    "wof:name":"Otg Inc",
    "wof:placetype":"venue"
},
  "geometry": {"coordinates":[-96.69991,32.975066],"type":"Point"}
}