{
  "type": "Feature",
  "properties": {
    "iso:country":"US",
    "sg:address":"9050 Oakpath Ln",
    "sg:city":"Dallas",
    "sg:classifiers":[
        {
            "category":"Professional",
            "subcategory":"Management & Consulting",
            "type":"Services"
        }
    ],
    "sg:phone":"+1 214 349 5937",
    "sg:postcode":"75243",
    "sg:province":"TX",
    "wof:name":"Bootheel Consulting Inc",
    "wof:placetype":"venue"
},
  "geometry": {"coordinates":[-96.74679999999999,32.902468],"type":"Point"}
}