{
  "type": "Feature",
  "properties": {
    "iso:country":"US",
    "sg:address":"7322 SW Fwy Ste 1010",
    "sg:city":"Houston",
    "sg:classifiers":[
        {
            "category":"Personal",
            "type":"Services"
        }
    ],
    "sg:phone":"+1 877 669 7683",
    "sg:postcode":"77074",
    "sg:province":"TX",
    "sg:tags":[
        "home"
    ],
    "sg:website":"potentiaenergy.com/",
    "wof:name":"Potentia Energy",
    "wof:placetype":"venue"
},
  "geometry": {"coordinates":[-95.516497,29.701923],"type":"Point"}
}