{
  "type": "Feature",
  "properties": {
    "iso:country":"US",
    "sg:address":"9950 Westpark Dr",
    "sg:city":"Houston",
    "sg:classifiers":[
        {
            "category":"Professional",
            "subcategory":"Lawyer & Legal Services",
            "type":"Services"
        }
    ],
    "sg:phone":"+1 713 532 0336",
    "sg:postcode":"77063",
    "sg:province":"TX",
    "wof:name":"McKey & Williams PLLC",
    "wof:placetype":"venue"
},
  "geometry": {"coordinates":[-95.537265,29.72128],"type":"Point"}
}