{
  "type": "Feature",
  "properties": {
    "iso:country":"US",
    "sg:address":"100 Cedar Springs Rd",
    "sg:city":"Ingram",
    "sg:classifiers":[
        {
            "category":"Travel",
            "subcategory":"Campground",
            "type":"Entertainment"
        }
    ],
    "sg:phone":"+1 830 367 4769",
    "sg:postcode":"78025",
    "sg:province":"TX",
    "sg:tags":[
        "trailer"
    ],
    "wof:name":"Ingram Lake Rv Park",
    "wof:placetype":"venue"
},
  "geometry": {"coordinates":[-99.260069,30.075922],"type":"Point"}
}