{
  "type": "Feature",
  "properties": {
    "iso:country":"US",
    "sg:address":"12845 Murphy Rd",
    "sg:city":"Stafford",
    "sg:classifiers":[
        {
            "category":"Travel",
            "subcategory":"Hotels & Motels",
            "type":"Entertainment"
        }
    ],
    "sg:phone":"+1 281 568 1214",
    "sg:postcode":"77477",
    "sg:province":"TX",
    "sg:tags":[
        "lodging"
    ],
    "sg:website":"http://www.super8.com",
    "wof:name":"Super 8 Motel",
    "wof:placetype":"venue"
},
  "geometry": {"coordinates":[-95.565046,29.636862],"type":"Point"}
}