{
  "type": "Feature",
  "properties": {
    "iso:country":"US",
    "sg:address":"4125 Kevin Dr",
    "sg:city":"Corpus Christi",
    "sg:classifiers":[
        {
            "category":"Building & Trades",
            "subcategory":"Construction",
            "type":"Services"
        }
    ],
    "sg:phone":"+1 361 853 8866",
    "sg:postcode":"78413",
    "sg:province":"TX",
    "sg:tags":[
        "hanging",
        "contractor"
    ],
    "wof:name":"JB S House Painting Service",
    "wof:placetype":"venue"
},
  "geometry": {"coordinates":[-97.406353,27.705778],"type":"Point"}
}