{
  "type": "Feature",
  "properties": {
    "iso:country":"US",
    "sg:address":"407 Baylor St",
    "sg:city":"Austin",
    "sg:classifiers":[
        {
            "category":"Wholesale",
            "subcategory":"Electrical",
            "type":"Manufacturing & Wholesale Goods"
        }
    ],
    "sg:phone":"+1 512 320 0900",
    "sg:postcode":"78703",
    "sg:province":"TX",
    "sg:tags":[
        "light",
        "fitting",
        "tube",
        "bulb"
    ],
    "wof:name":"Southwestern Electric and Sup",
    "wof:placetype":"venue"
},
  "geometry": {"coordinates":[-97.756017,30.270718],"type":"Point"}
}