{
  "type": "Feature",
  "properties": {
    "iso:country":"US",
    "sg:address":"3525 International Blvd",
    "sg:city":"Brownsville",
    "sg:classifiers":[
        {
            "category":"Shopping",
            "subcategory":"Department Store",
            "type":"Retail Goods"
        }
    ],
    "sg:phone":"+1 956 542 9257",
    "sg:postcode":"78521",
    "sg:province":"TX",
    "sg:tags":[
        "shop"
    ],
    "wof:name":"Dollar General",
    "wof:placetype":"venue"
},
  "geometry": {"coordinates":[-97.470741,25.916387],"type":"Point"}
}