{
  "type": "Feature",
  "properties": {
    "iso:country":"US",
    "sg:address":"13657 Jupiter Rd",
    "sg:city":"Dallas",
    "sg:classifiers":[
        {
            "category":"Health Services",
            "subcategory":"Medical Lab",
            "type":"Services"
        }
    ],
    "sg:phone":"+1 214 349 8880",
    "sg:postcode":"75238",
    "sg:province":"TX",
    "sg:tags":[
        "control",
        "pain"
    ],
    "wof:name":"STS Pain Clinic",
    "wof:placetype":"venue"
},
  "geometry": {"coordinates":[-96.68324,32.883823],"type":"Point"}
}