{
  "type": "Feature",
  "properties": {
    "iso:country":"US",
    "sg:address":"777 S R L Thornton Fwy",
    "sg:city":"Dallas",
    "sg:classifiers":[
        {
            "category":"Shopping",
            "subcategory":"Bicycles & Sporting Goods",
            "type":"Retail Goods"
        }
    ],
    "sg:phone":"+1 214 946 4780",
    "sg:postcode":"75203",
    "sg:province":"TX",
    "wof:name":"Jay Dee Gun Shop",
    "wof:placetype":"venue"
},
  "geometry": {"coordinates":[-96.81863800000001,32.742531],"type":"Point"}
}