{
  "type": "Feature",
  "properties": {
    "iso:country":"US",
    "sg:address":"1421 W Buckingham Rd",
    "sg:city":"Garland",
    "sg:classifiers":[
        {
            "category":"Personal",
            "subcategory":"Tanning Parlor",
            "type":"Services"
        }
    ],
    "sg:phone":"+1 972 496 1555",
    "sg:postcode":"75042",
    "sg:province":"TX",
    "sg:tags":[
        "salon"
    ],
    "wof:name":"Tanz-N Handz",
    "wof:placetype":"venue"
},
  "geometry": {"coordinates":[-96.651158,32.930664],"type":"Point"}
}