{
  "type": "Feature",
  "properties": {
    "iso:country":"US",
    "sg:address":"805 N Ave F",
    "sg:city":"Post",
    "sg:classifiers":[
        {
            "category":"Social Services",
            "subcategory":"Job Training",
            "type":"Services"
        }
    ],
    "sg:phone":"+1 806 495 2175",
    "sg:postcode":"79356",
    "sg:province":"TX",
    "sg:tags":[
        "rehabilitation"
    ],
    "wof:name":"W Dalby Giles Correctional",
    "wof:placetype":"venue"
},
  "geometry": {"coordinates":[-101.370127,33.203898],"type":"Point"}
}