{
  "type": "Feature",
  "properties": {
    "iso:country":"US",
    "sg:address":"8109 Valdemorillo Dr",
    "sg:city":"Corpus Christi",
    "sg:classifiers":[
        {
            "category":"Professional",
            "subcategory":"Engineering",
            "type":"Services"
        }
    ],
    "sg:phone":"+1 361 852 7788",
    "sg:postcode":"78414",
    "sg:province":"TX",
    "sg:tags":[
        "petroleum",
        "engineer"
    ],
    "wof:name":"Sol Energy Inc",
    "wof:placetype":"venue"
},
  "geometry": {"coordinates":[-97.39988099999999,27.654794],"type":"Point"}
}