{
  "type": "Feature",
  "properties": {
    "iso:country":"US",
    "sg:address":"4002 Easy St",
    "sg:city":"Dickinson",
    "sg:classifiers":[
        {
            "category":"Building & Trades",
            "subcategory":"Construction",
            "type":"Services"
        }
    ],
    "sg:phone":"+1 281 534 2372",
    "sg:postcode":"77539",
    "sg:province":"TX",
    "sg:tags":[
        "house"
    ],
    "wof:name":"S&V Affordable Remodeling",
    "wof:placetype":"venue"
},
  "geometry": {"coordinates":[-95.050361,29.469109],"type":"Point"}
}