{
  "type": "Feature",
  "properties": {
    "iso:country":"US",
    "sg:address":"3611 Texas St",
    "sg:city":"Greenville",
    "sg:classifiers":[
        {
            "category":"Education",
            "subcategory":"School",
            "type":"Public Place"
        }
    ],
    "sg:phone":"+1 903 457 2621",
    "sg:postcode":"75401",
    "sg:province":"TX",
    "sg:tags":[
        "association"
    ],
    "wof:name":"Greenville Middle School",
    "wof:placetype":"venue"
},
  "geometry": {"coordinates":[-96.119426,33.13204],"type":"Point"}
}