{
  "type": "Feature",
  "properties": {
    "iso:country":"US",
    "sg:address":"120 Vantage Dr",
    "sg:city":"Cleburne",
    "sg:classifiers":[
        {
            "category":"Professional",
            "subcategory":"Business Services",
            "type":"Services"
        }
    ],
    "sg:phone":"+1 817 645 8809",
    "sg:postcode":"76031",
    "sg:province":"TX",
    "wof:name":"Johnson County Bail Bonds",
    "wof:placetype":"venue"
},
  "geometry": {"coordinates":[-97.389365,32.374799],"type":"Point"}
}