{
  "type": "Feature",
  "properties": {
    "iso:country":"US",
    "sg:address":"8521 Stella Link Rd",
    "sg:city":"Houston",
    "sg:classifiers":[
        {
            "category":"Autos & Motor Vehicles",
            "subcategory":"Fuel & Gas Station",
            "type":"Retail Goods"
        }
    ],
    "sg:phone":"+1 713 661 1897",
    "sg:postcode":"77025",
    "sg:province":"TX",
    "wof:name":"Braeswood Texaco",
    "wof:placetype":"venue"
},
  "geometry": {"coordinates":[-95.440102,29.691299],"type":"Point"}
}