{
  "type": "Feature",
  "properties": {
    "iso:country":"US",
    "sg:address":"1122 Lauder Rd",
    "sg:city":"Houston",
    "sg:classifiers":[
        {
            "category":"Manufacturing",
            "subcategory":"Signs",
            "type":"Manufacturing & Wholesale Goods"
        },
        {
            "category":"Retail",
            "subcategory":"Repair Shop",
            "type":"Services"
        }
    ],
    "sg:phone":"+1 281 987 0339",
    "sg:postcode":"77039",
    "sg:province":"TX",
    "sg:tags":[
        "electrical"
    ],
    "sg:website":"www.neonelectric.net",
    "wof:name":"Neon Electric Corporation",
    "wof:placetype":"venue"
},
  "geometry": {"coordinates":[-95.37101,29.913932],"type":"Point"}
}