{
  "type": "Feature",
  "properties": {
    "iso:country":"US",
    "sg:address":"702 Hopi Cir",
    "sg:city":"Temple",
    "sg:classifiers":[
        {
            "category":"Professional",
            "subcategory":"Business Services",
            "type":"Services"
        }
    ],
    "sg:phone":"+1 254 774 9117",
    "sg:postcode":"76504",
    "sg:province":"TX",
    "wof:name":"Doran Marketing Group",
    "wof:placetype":"venue"
},
  "geometry": {"coordinates":[-97.385009,31.101208],"type":"Point"}
}