{
  "type": "Feature",
  "properties": {
    "iso:country":"US",
    "sg:address":"2020 Old Montgomery Rd",
    "sg:city":"Conroe",
    "sg:classifiers":[
        {
            "category":"Organizations",
            "subcategory":"Religious Organization",
            "type":"Services"
        }
    ],
    "sg:phone":"+1 936 756 9334",
    "sg:postcode":"77304",
    "sg:province":"TX",
    "wof:name":"Kingdom Hall Jhovahs Witnesses",
    "wof:placetype":"venue"
},
  "geometry": {"coordinates":[-95.498936,30.310443],"type":"Point"}
}