{
  "type": "Feature",
  "properties": {
    "iso:country":"US",
    "sg:address":"2927 Pershing Dr",
    "sg:city":"El Paso",
    "sg:classifiers":[
        {
            "category":"Banks & Credit Unions",
            "subcategory":"Bank",
            "type":"Services"
        }
    ],
    "sg:phone":"+1 915 565 6000",
    "sg:postcode":"79903",
    "sg:province":"TX",
    "sg:tags":[
        "institution",
        "business"
    ],
    "wof:name":"Five Points Signature Loans",
    "wof:placetype":"venue"
},
  "geometry": {"coordinates":[-106.46138000000001,31.784833],"type":"Point"}
}