{
  "type": "Feature",
  "properties": {
    "iso:country":"US",
    "sg:address":"1850 Mc Gee Ln",
    "sg:city":"Lewisville",
    "sg:classifiers":[
        {
            "category":"Retail",
            "subcategory":"Auto Rental",
            "type":"Services"
        }
    ],
    "sg:phone":"+1 972 317 9190",
    "sg:postcode":"75077",
    "sg:province":"TX",
    "sg:tags":[
        "truck"
    ],
    "wof:name":"Auto Lane",
    "wof:placetype":"venue"
},
  "geometry": {"coordinates":[-97.027064,33.070029],"type":"Point"}
}