{
  "type": "Feature",
  "properties": {
    "iso:country":"US",
    "sg:address":"914 15 St",
    "sg:city":"Centerville",
    "sg:classifiers":[
        {
            "category":"Food & Beverages",
            "subcategory":"Groceries & Convenience Stores",
            "type":"Retail Goods"
        }
    ],
    "sg:phone":"+1 903 536 2205",
    "sg:postcode":"75833",
    "sg:province":"TX",
    "wof:name":"Texan Food Mart",
    "wof:placetype":"venue"
},
  "geometry": {"coordinates":[-96.644311,32.859209],"type":"Point"}
}