{
  "type": "Feature",
  "properties": {
    "iso:country":"US",
    "sg:address":"3651 Weslayan Ste 110",
    "sg:city":"Houston",
    "sg:classifiers":[
        {
            "category":"Health Services",
            "subcategory":"Health Practitioner",
            "type":"Services"
        }
    ],
    "sg:phone":"+1 713 580 8472",
    "sg:postcode":"77027",
    "sg:province":"TX",
    "sg:tags":[
        "therapy",
        "physical"
    ],
    "wof:name":"Memorial Hermann Sports Medicine and Rehabilitation",
    "wof:placetype":"venue"
},
  "geometry": {"coordinates":[-95.441423,29.733179],"type":"Point"}
}