{
  "type": "Feature",
  "properties": {
    "iso:country":"US",
    "sg:address":"7200 N Mo Pac Expy Ste 225",
    "sg:city":"Austin",
    "sg:classifiers":[
        {
            "category":"Banks & Credit Unions",
            "subcategory":"Financial Services",
            "type":"Services"
        }
    ],
    "sg:phone":"+1 512 794 9783",
    "sg:postcode":"78731",
    "sg:province":"TX",
    "sg:tags":[
        "broker",
        "mortgage"
    ],
    "wof:name":"Elite Mortgage",
    "wof:placetype":"venue"
},
  "geometry": {"coordinates":[-97.74807699999999,30.354768],"type":"Point"}
}