{
  "type": "Feature",
  "properties": {
    "iso:country":"US",
    "sg:address":"2615 W Colorado Blvd",
    "sg:city":"Dallas",
    "sg:classifiers":[
        {
            "category":"Education",
            "subcategory":"School",
            "type":"Public Place"
        }
    ],
    "sg:phone":"+1 972 794 4200",
    "sg:postcode":"75211",
    "sg:province":"TX",
    "sg:website":"www.dallasisd.org",
    "wof:name":"Dallas Independent School District",
    "wof:placetype":"venue"
},
  "geometry": {"coordinates":[-96.86408299999999,32.759952],"type":"Point"}
}