{
  "type": "Feature",
  "properties": {
    "iso:country":"US",
    "sg:address":"2611 N Belt Line Rd",
    "sg:city":"Mesquite",
    "sg:classifiers":[
        {
            "category":"Professional",
            "subcategory":"Business Services",
            "type":"Services"
        }
    ],
    "sg:phone":"+1 972 226 5601",
    "sg:postcode":"75182",
    "sg:province":"TX",
    "sg:tags":[
        "recording",
        "studio"
    ],
    "wof:name":"Pelican Studios",
    "wof:placetype":"venue"
},
  "geometry": {"coordinates":[-96.595977,32.798013],"type":"Point"}
}