{
  "type": "Feature",
  "properties": {
    "iso:country":"US",
    "sg:address":"1323 County Road 37100",
    "sg:city":"Sumner",
    "sg:classifiers":[
        {
            "category":"Farming",
            "subcategory":"Livestock Farm",
            "type":"Manufacturing & Wholesale Goods"
        },
        {
            "category":"Farming",
            "subcategory":"Farm",
            "type":"Manufacturing & Wholesale Goods"
        }
    ],
    "sg:phone":"+1 903 784 8946",
    "sg:postcode":"75486",
    "sg:province":"TX",
    "sg:tags":[
        "feeding"
    ],
    "wof:name":"Billy Beshirs",
    "wof:placetype":"venue"
},
  "geometry": {"coordinates":[-95.843841,33.78426],"type":"Point"}
}