{
  "type": "Feature",
  "properties": {
    "iso:country":"US",
    "sg:address":"2038 Forest Hills Rd",
    "sg:city":"Grapevine",
    "sg:classifiers":[
        {
            "category":"Building & Trades",
            "subcategory":"Equipment Rental",
            "type":"Services"
        }
    ],
    "sg:phone":"+1 817 689 8785",
    "sg:postcode":"76051",
    "sg:province":"TX",
    "wof:name":"Cool Freeze",
    "wof:placetype":"venue"
},
  "geometry": {"coordinates":[-97.098175,32.973542],"type":"Point"}
}