{
  "type": "Feature",
  "properties": {
    "iso:country":"US",
    "sg:address":"2202 E Lyon St",
    "sg:city":"Laredo",
    "sg:classifiers":[
        {
            "category":"Personal",
            "type":"Services"
        }
    ],
    "sg:phone":"+1 956 723 3933",
    "sg:postcode":"78043",
    "sg:province":"TX",
    "wof:name":"Georgia G Pchot Thmas E Pichot",
    "wof:placetype":"venue"
},
  "geometry": {"coordinates":[-99.473161,27.522343],"type":"Point"}
}