{
  "type": "Feature",
  "properties": {
    "iso:country":"US",
    "sg:address":"408 N 3rd St",
    "sg:city":"Mabank",
    "sg:classifiers":[
        {
            "category":"Bars & Pubs",
            "type":"Food & Drink"
        }
    ],
    "sg:phone":"+1 903 887 3995",
    "sg:postcode":"75147",
    "sg:province":"TX",
    "sg:tags":[
        "drinking"
    ],
    "wof:name":"Hudgins Yard Sale",
    "wof:placetype":"venue"
},
  "geometry": {"coordinates":[-96.099298,32.370283],"type":"Point"}
}