{
  "type": "Feature",
  "properties": {
    "iso:country":"US",
    "sg:address":"116 Nueces St",
    "sg:city":"Hereford",
    "sg:classifiers":[
        {
            "category":"Real Estate",
            "subcategory":"Real Estate Agent",
            "type":"Services"
        }
    ],
    "sg:phone":"+1 806 364 7953",
    "sg:postcode":"79045",
    "sg:province":"TX",
    "wof:name":"Act Enterprises",
    "wof:placetype":"venue"
},
  "geometry": {"coordinates":[-102.427221,34.825383],"type":"Point"}
}