{
  "type": "Feature",
  "properties": {
    "iso:country":"US",
    "sg:address":"2014 Eclipse Cove",
    "sg:city":"Cedar Park",
    "sg:classifiers":[
        {
            "category":"Social Services",
            "subcategory":"Child Care",
            "type":"Services"
        }
    ],
    "sg:phone":"+1 512 258 2858",
    "sg:postcode":"78613",
    "sg:province":"TX",
    "sg:tags":[
        "day"
    ],
    "wof:name":"Jelly Bean Haven LLC",
    "wof:placetype":"venue"
},
  "geometry": {"coordinates":[-97.844346,30.483009],"type":"Point"}
}