{
  "type": "Feature",
  "properties": {
    "iso:country":"US",
    "sg:address":"1105 Shaver St",
    "sg:city":"Pasadena",
    "sg:classifiers":[
        {
            "category":"Banks & Credit Unions",
            "subcategory":"Bank",
            "type":"Services"
        }
    ],
    "sg:phone":"+1 713 473 5850",
    "sg:postcode":"77506",
    "sg:province":"TX",
    "sg:website":"www.wachovia.com",
    "wof:name":"Wachovia",
    "wof:placetype":"venue"
},
  "geometry": {"coordinates":[-95.21122200000001,29.692302],"type":"Point"}
}