{
  "type": "Feature",
  "properties": {
    "iso:country":"US",
    "sg:address":"324 Island Oak Dr",
    "sg:city":"Austin",
    "sg:classifiers":[
        {
            "category":"Organizations",
            "subcategory":"Religious Organization",
            "type":"Services"
        }
    ],
    "sg:phone":"+1 512 294 2815",
    "sg:postcode":"78748",
    "sg:province":"TX",
    "sg:website":"www.emmausaustin.com",
    "wof:name":"Emmaus Austin",
    "wof:placetype":"venue"
},
  "geometry": {"coordinates":[-97.802301,30.15848],"type":"Point"}
}