{
  "type": "Feature",
  "properties": {
    "iso:country":"US",
    "sg:address":"3804 John Stockbauer Dr",
    "sg:city":"Victoria",
    "sg:classifiers":[
        {
            "category":"Shopping",
            "subcategory":"Computers & Home Electronics",
            "type":"Retail Goods"
        }
    ],
    "sg:phone":"+1 361 576 7638",
    "sg:postcode":"77904",
    "sg:province":"TX",
    "wof:name":"Nbs",
    "wof:placetype":"venue"
},
  "geometry": {"coordinates":[-96.94687999999999,28.817815],"type":"Point"}
}