{
  "type": "Feature",
  "properties": {
    "iso:country":"US",
    "sg:address":"7949 Sunmount Dr",
    "sg:city":"El Paso",
    "sg:classifiers":[
        {
            "category":"Social Services",
            "subcategory":"Adult Care",
            "type":"Services"
        }
    ],
    "sg:phone":"+1 915 772 4036",
    "sg:postcode":"79925",
    "sg:province":"TX",
    "sg:tags":[
        "home",
        "residential"
    ],
    "wof:name":"Village Oaks At Cielo Vista",
    "wof:placetype":"venue"
},
  "geometry": {"coordinates":[-106.383995,31.781911],"type":"Point"}
}