{
  "type": "Feature",
  "properties": {
    "iso:country":"US",
    "sg:address":"104 Cibolo Tolle Rd",
    "sg:city":"Cibolo",
    "sg:classifiers":[
        {
            "category":"Freight",
            "type":"Transportation"
        }
    ],
    "sg:phone":"+1 210 945 8407",
    "sg:postcode":"78108",
    "sg:province":"TX",
    "wof:name":"Arnold Transport Services",
    "wof:placetype":"venue"
},
  "geometry": {"coordinates":[-98.208805,29.578234],"type":"Point"}
}