{
  "type": "Feature",
  "properties": {
    "iso:country":"US",
    "sg:address":"391 Upper Turtle Creek Rd",
    "sg:city":"Kerrville",
    "sg:classifiers":[
        {
            "category":"Professional",
            "type":"Services"
        }
    ],
    "sg:phone":"+1 830 257 3060",
    "sg:postcode":"78028",
    "sg:province":"TX",
    "sg:tags":[
        "establishment"
    ],
    "wof:name":"Monarch House",
    "wof:placetype":"venue"
},
  "geometry": {"coordinates":[-99.214676,29.972944],"type":"Point"}
}