{
  "type": "Feature",
  "properties": {
    "iso:country":"US",
    "sg:address":"1106 N Jupiter Rd",
    "sg:city":"Garland",
    "sg:classifiers":[
        {
            "category":"Organizations",
            "subcategory":"Religious Organization",
            "type":"Services"
        }
    ],
    "sg:phone":"+1 972 487 0025",
    "sg:postcode":"75042",
    "sg:province":"TX",
    "sg:tags":[
        "church"
    ],
    "wof:name":"Ethiopian Orthodox St Michael Church",
    "wof:placetype":"venue"
},
  "geometry": {"coordinates":[-96.6828,32.922901],"type":"Point"}
}