{
  "type": "Feature",
  "properties": {
    "iso:country":"US",
    "sg:address":"402 W Wheatland Rd",
    "sg:city":"Duncanville",
    "sg:classifiers":[
        {
            "category":"Banks & Credit Unions",
            "subcategory":"Bank",
            "type":"Services"
        }
    ],
    "sg:phone":"+1 972 283 3200",
    "sg:postcode":"75116",
    "sg:province":"TX",
    "sg:tags":[
        "mortgage"
    ],
    "wof:name":"Classic Mortgage",
    "wof:placetype":"venue"
},
  "geometry": {"coordinates":[-96.91574799999999,32.645939],"type":"Point"}
}