{
  "type": "Feature",
  "properties": {
    "iso:country":"US",
    "sg:address":"1825 Kramer Ln",
    "sg:city":"Austin",
    "sg:classifiers":[
        {
            "category":"Manufacturing",
            "subcategory":"Motor Vehicles & Parts",
            "type":"Manufacturing & Wholesale Goods"
        }
    ],
    "sg:phone":"+1 310 768 2017",
    "sg:postcode":"78758",
    "sg:province":"TX",
    "sg:tags":[
        "machine",
        "addressing",
        "supply"
    ],
    "wof:name":"Pitney Bowes",
    "wof:placetype":"venue"
},
  "geometry": {"coordinates":[-97.706439,30.386813],"type":"Point"}
}