{
  "type": "Feature",
  "properties": {
    "iso:country":"US",
    "sg:address":"1804 S I- 35",
    "sg:city":"Round Rock",
    "sg:classifiers":[
        {
            "category":"Retail",
            "subcategory":"Auto Repair",
            "type":"Services"
        }
    ],
    "sg:phone":"+1 512 244 2671",
    "sg:postcode":"78666",
    "sg:province":"TX",
    "sg:tags":[
        "body",
        "automobile",
        "painting"
    ],
    "wof:name":"Signature Auto Body",
    "wof:placetype":"venue"
},
  "geometry": {"coordinates":[-97.948847,29.8612],"type":"Point"}
}