{
  "type": "Feature",
  "properties": {
    "iso:country":"US",
    "sg:address":"1520 Allston St",
    "sg:city":"Houston",
    "sg:classifiers":[
        {
            "category":"Professional",
            "subcategory":"Business Services",
            "type":"Services"
        }
    ],
    "sg:phone":"+1 713 863 8422",
    "sg:postcode":"77008",
    "sg:province":"TX",
    "wof:name":"Jag Technologies",
    "wof:placetype":"venue"
},
  "geometry": {"coordinates":[-95.400166,29.799494],"type":"Point"}
}