{
  "type": "Feature",
  "properties": {
    "iso:country":"US",
    "sg:address":"9827 Almeda Genoa Rd",
    "sg:city":"Houston",
    "sg:classifiers":[
        {
            "category":"Shopping",
            "subcategory":"Antiques",
            "type":"Retail Goods"
        }
    ],
    "sg:phone":"+1 713 941 7744",
    "sg:postcode":"77075",
    "sg:province":"TX",
    "sg:website":"www.aamalls.com",
    "wof:name":"Almeda Antique Mall",
    "wof:placetype":"venue"
},
  "geometry": {"coordinates":[-95.24250000000001,29.6276],"type":"Point"}
}