{
  "type": "Feature",
  "properties": {
    "iso:country":"US",
    "sg:address":"11534 Harwin Dr",
    "sg:city":"Houston",
    "sg:classifiers":[
        {
            "category":"Autos & Motor Vehicles",
            "subcategory":"Auto Supplies",
            "type":"Retail Goods"
        },
        {
            "category":"Retail",
            "subcategory":"Auto Repair",
            "type":"Services"
        }
    ],
    "sg:phone":"+1 281 575 9340",
    "sg:postcode":"77072",
    "sg:province":"TX",
    "sg:tags":[
        "body",
        "lettering",
        "automobile",
        "truck",
        "painting",
        "repairing"
    ],
    "wof:name":"Long's Auto Body Shop",
    "wof:placetype":"venue"
},
  "geometry": {"coordinates":[-95.576525,29.715327],"type":"Point"}
}