{
  "type": "Feature",
  "properties": {
    "iso:country":"US",
    "sg:address":"804 S Main St",
    "sg:city":"Cleburne",
    "sg:classifiers":[
        {
            "category":"Professional",
            "subcategory":"Advertising",
            "type":"Services"
        },
        {
            "category":"Professional",
            "subcategory":"Printing & Photocopies",
            "type":"Services"
        },
        {
            "category":"Manufacturing",
            "subcategory":"Signs",
            "type":"Manufacturing & Wholesale Goods"
        }
    ],
    "sg:phone":"+1 817 641 0000",
    "sg:postcode":"76033",
    "sg:province":"TX",
    "sg:tags":[
        "banners",
        "flag",
        "specialty",
        "pennant"
    ],
    "wof:name":"Cleburne Sign & Graphics",
    "wof:placetype":"venue"
},
  "geometry": {"coordinates":[-97.38713799999999,32.39677],"type":"Point"}
}