{
  "type": "Feature",
  "properties": {
    "iso:country":"US",
    "sg:address":"344 Junction Hwy",
    "sg:city":"Kerrville",
    "sg:classifiers":[
        {
            "category":"Professional",
            "type":"Services"
        }
    ],
    "sg:phone":"+1 830 896 2155",
    "sg:postcode":"78028",
    "sg:province":"TX",
    "sg:tags":[
        "establishment"
    ],
    "wof:name":"Tidy Car",
    "wof:placetype":"venue"
},
  "geometry": {"coordinates":[-99.150834,30.054499],"type":"Point"}
}