{
  "type": "Feature",
  "properties": {
    "iso:country":"US",
    "sg:address":"502 Hilltop Pl",
    "sg:city":"Joshua",
    "sg:classifiers":[
        {
            "category":"Mining & Drilling",
            "type":"Manufacturing & Wholesale Goods"
        }
    ],
    "sg:phone":"+1 817 295 6602",
    "sg:postcode":"76058",
    "sg:province":"TX",
    "sg:tags":[
        "field"
    ],
    "wof:name":"Servicios De Venezuela",
    "wof:placetype":"venue"
},
  "geometry": {"coordinates":[-97.371337,32.484252],"type":"Point"}
}