{
  "type": "Feature",
  "properties": {
    "iso:country":"US",
    "sg:address":"853 W Little York Rd",
    "sg:city":"Houston",
    "sg:classifiers":[
        {
            "category":"Shopping",
            "subcategory":"Music",
            "type":"Retail Goods"
        }
    ],
    "sg:phone":"+1 713 692 4577",
    "sg:postcode":"77091",
    "sg:province":"TX",
    "wof:name":"Knoccoff Records",
    "wof:placetype":"venue"
},
  "geometry": {"coordinates":[-95.42153399999999,29.86591],"type":"Point"}
}