{
  "type": "Feature",
  "properties": {
    "iso:country":"US",
    "sg:address":"4011 Memorial Blvd",
    "sg:city":"Port Arthur",
    "sg:classifiers":[
        {
            "category":"Organizations",
            "subcategory":"Religious Organization",
            "type":"Services"
        }
    ],
    "sg:phone":"+1 409 983 5654",
    "sg:postcode":"77640",
    "sg:province":"TX",
    "wof:name":"Memorial Baptist Church",
    "wof:placetype":"venue"
},
  "geometry": {"coordinates":[-93.947985,29.912524],"type":"Point"}
}