{
  "type": "Feature",
  "properties": {
    "iso:country":"US",
    "sg:address":"1541 Stetson Dr",
    "sg:city":"Weatherford",
    "sg:classifiers":[
        {
            "category":"Building & Trades",
            "subcategory":"Landscaping Services",
            "type":"Services"
        }
    ],
    "sg:phone":"+1 817 594 2540",
    "sg:postcode":"76087",
    "sg:province":"TX",
    "sg:tags":[
        "lawn"
    ],
    "wof:name":"Phillips Landscaping",
    "wof:placetype":"venue"
},
  "geometry": {"coordinates":[-97.722168,32.774977],"type":"Point"}
}