{
  "type": "Feature",
  "properties": {
    "iso:country":"US",
    "sg:address":"3220 W Pinecrest Dr",
    "sg:city":"Marshall",
    "sg:classifiers":[
        {
            "category":"Retail",
            "subcategory":"Repair Shop",
            "type":"Services"
        }
    ],
    "sg:phone":"+1 903 935 2885",
    "sg:postcode":"75670",
    "sg:province":"TX",
    "sg:tags":[
        "vinyl"
    ],
    "sg:website":"www.natesrestoration.com",
    "wof:name":"Nate's Restoration Systems",
    "wof:placetype":"venue"
},
  "geometry": {"coordinates":[-94.39791,32.516004],"type":"Point"}
}