{
  "type": "Feature",
  "properties": {
    "iso:country":"US",
    "sg:address":"200 E Tom Landry St",
    "sg:city":"Mission",
    "sg:classifiers":[
        {
            "category":"Government",
            "subcategory":"Police Station",
            "type":"Public Place"
        }
    ],
    "sg:phone":"+1 956 581 8477",
    "sg:postcode":"78572",
    "sg:province":"TX",
    "sg:tags":[
        "car",
        "protection"
    ],
    "wof:name":"Mission Crime Stoppers Inc",
    "wof:placetype":"venue"
},
  "geometry": {"coordinates":[-98.32339899999999,26.215622],"type":"Point"}
}