{
  "type": "Feature",
  "properties": {
    "iso:country":"US",
    "sg:address":"601 Pleasant Ridge Dr",
    "sg:city":"Mansfield",
    "sg:classifiers":[
        {
            "category":"Shopping",
            "subcategory":"Used Merchandise",
            "type":"Retail Goods"
        }
    ],
    "sg:phone":"+1 817 473 6650",
    "sg:postcode":"76063",
    "sg:province":"TX",
    "wof:name":"Thrift Shop",
    "wof:placetype":"venue"
},
  "geometry": {"coordinates":[-97.13594399999999,32.576265],"type":"Point"}
}