{
  "type": "Feature",
  "properties": {
    "iso:country":"US",
    "sg:address":"25325 Borough Park Dr",
    "sg:city":"The Woodlands",
    "sg:classifiers":[
        {
            "category":"Insurance",
            "subcategory":"Insurance Agent",
            "type":"Services"
        }
    ],
    "sg:phone":"+1 281 364 1494",
    "sg:postcode":"77380",
    "sg:province":"TX",
    "wof:name":"Allstate Insurance",
    "wof:placetype":"venue"
},
  "geometry": {"coordinates":[-95.446831,30.134261],"type":"Point"}
}