{
  "type": "Feature",
  "properties": {
    "iso:country":"US",
    "sg:address":"2218 Atkinson Dr",
    "sg:city":"Lufkin",
    "sg:classifiers":[
        {
            "category":"Professional",
            "subcategory":"Business Services",
            "type":"Services"
        },
        {
            "category":"Utilities",
            "type":"Services"
        }
    ],
    "sg:phone":"+1 936 634 0445",
    "sg:postcode":"75901",
    "sg:province":"TX",
    "sg:tags":[
        "consultant",
        "petroleum",
        "sanitary"
    ],
    "wof:name":"MCS Technologies LLC",
    "wof:placetype":"venue"
},
  "geometry": {"coordinates":[-94.69918,31.351448],"type":"Point"}
}