{
  "type": "Feature",
  "properties": {
    "iso:country":"US",
    "sg:address":"2016 Keller Springs Rd",
    "sg:city":"Carrollton",
    "sg:classifiers":[
        {
            "category":"Retail",
            "subcategory":"Auto Repair",
            "type":"Services"
        }
    ],
    "sg:phone":"+1 972 446 1400",
    "sg:postcode":"75006",
    "sg:province":"TX",
    "sg:tags":[
        "body"
    ],
    "wof:name":"Just Dents",
    "wof:placetype":"venue"
},
  "geometry": {"coordinates":[-96.889814,32.973605],"type":"Point"}
}