{
  "type": "Feature",
  "properties": {
    "iso:country":"US",
    "sg:address":"9836 Lavera Dr",
    "sg:city":"Austin",
    "sg:classifiers":[
        {
            "category":"Shopping",
            "subcategory":"Clothing, Apparel, & Fashions",
            "type":"Retail Goods"
        }
    ],
    "sg:phone":"+1 512 996 0030",
    "sg:postcode":"78726",
    "sg:province":"TX",
    "wof:name":"Creative Shirts Intl",
    "wof:placetype":"venue"
},
  "geometry": {"coordinates":[-97.831029,30.434724],"type":"Point"}
}