{
  "type": "Feature",
  "properties": {
    "iso:country":"US",
    "sg:address":"6615 Irvington Blvd",
    "sg:city":"Houston",
    "sg:classifiers":[
        {
            "category":"Organizations",
            "subcategory":"Religious Organization",
            "type":"Services"
        }
    ],
    "sg:phone":"+1 713 695 3604",
    "sg:postcode":"77022",
    "sg:province":"TX",
    "sg:tags":[
        "church"
    ],
    "wof:name":"Lindale Baptist Church SBC",
    "wof:placetype":"venue"
},
  "geometry": {"coordinates":[-95.361233,29.818747],"type":"Point"}
}