{
  "type": "Feature",
  "properties": {
    "iso:country":"US",
    "sg:address":"5513 Naaman Forest Blvd",
    "sg:city":"Garland",
    "sg:classifiers":[
        {
            "category":"Professional",
            "type":"Services"
        }
    ],
    "sg:phone":"+1 972 414 5039",
    "sg:postcode":"75044",
    "sg:province":"TX",
    "wof:name":"Intellisoft",
    "wof:placetype":"venue"
},
  "geometry": {"coordinates":[-96.649603,32.960035],"type":"Point"}
}