{
  "type": "Feature",
  "properties": {
    "iso:country":"US",
    "sg:address":"686 Ave C",
    "sg:city":"Palestine",
    "sg:classifiers":[
        {
            "category":"Building & Trades",
            "subcategory":"Cleaning & Sanitation",
            "type":"Services"
        }
    ],
    "sg:phone":"+1 903 538 0142",
    "sg:postcode":"75803",
    "sg:province":"TX",
    "sg:tags":[
        "window"
    ],
    "wof:name":"Triple J Window Cleaning",
    "wof:placetype":"venue"
},
  "geometry": {"coordinates":[-95.65940399999999,31.744787],"type":"Point"}
}