{
  "type": "Feature",
  "properties": {
    "iso:country":"US",
    "sg:address":"9254 US Hwy 87",
    "sg:city":"San Antonio",
    "sg:classifiers":[
        {
            "category":"Retail",
            "subcategory":"Auto Repair",
            "type":"Services"
        }
    ],
    "sg:phone":"+1 210 649 4230",
    "sg:postcode":"78263",
    "sg:province":"TX",
    "sg:tags":[
        "repairing",
        "automobile",
        "general"
    ],
    "wof:name":"Gembler Automotive",
    "wof:placetype":"venue"
},
  "geometry": {"coordinates":[-98.304609,29.377125],"type":"Point"}
}