{
  "type": "Feature",
  "properties": {
    "iso:country":"US",
    "sg:address":"1707 Cumberland St",
    "sg:city":"Vernon",
    "sg:classifiers":[
        {
            "category":"Restaurant",
            "type":"Food & Drink"
        }
    ],
    "sg:phone":"+1 940 552 6689",
    "sg:postcode":"76384",
    "sg:province":"TX",
    "sg:tags":[
        "eating"
    ],
    "wof:name":"Spillway Drink Haus",
    "wof:placetype":"venue"
},
  "geometry": {"coordinates":[-99.28326300000001,34.153643],"type":"Point"}
}