{
  "type": "Feature",
  "properties": {
    "iso:country":"US",
    "sg:address":"100 Gaston Ct",
    "sg:city":"Breckenridge",
    "sg:classifiers":[
        {
            "category":"Building & Trades",
            "subcategory":"Construction",
            "type":"Services"
        }
    ],
    "sg:phone":"+1 254 559 9713",
    "sg:postcode":"76424",
    "sg:province":"TX",
    "sg:tags":[
        "contractor"
    ],
    "wof:name":"Tom Thompson Builder",
    "wof:placetype":"venue"
},
  "geometry": {"coordinates":[-98.939746,32.761071],"type":"Point"}
}