{
  "type": "Feature",
  "properties": {
    "iso:country":"US",
    "sg:address":"14717 Sunset Dr",
    "sg:city":"Conroe",
    "sg:classifiers":[
        {
            "category":"Professional",
            "type":"Services"
        }
    ],
    "sg:phone":"+1 936 446 1386",
    "sg:postcode":"77306",
    "sg:province":"TX",
    "wof:name":"Blue Chryslis Crtive Endeavors",
    "wof:placetype":"venue"
},
  "geometry": {"coordinates":[-95.344762,30.302138],"type":"Point"}
}