{
  "type": "Feature",
  "properties": {
    "iso:country":"US",
    "sg:address":"6547 Fm 954",
    "sg:city":"Fayetteville",
    "sg:classifiers":[
        {
            "category":"Insurance",
            "subcategory":"Hazard Insurance",
            "type":"Services"
        }
    ],
    "sg:phone":"+1 979 249 3010",
    "sg:postcode":"78940",
    "sg:province":"TX",
    "wof:name":"Meinen, Lacelle",
    "wof:placetype":"venue"
},
  "geometry": {"coordinates":[-96.686812,30.008073],"type":"Point"}
}