{
  "type": "Feature",
  "properties": {
    "iso:country":"US",
    "sg:address":"805 Estate Dr",
    "sg:city":"Athens",
    "sg:classifiers":[
        {
            "category":"Professional",
            "type":"Services"
        }
    ],
    "sg:phone":"+1 903 677 1069",
    "sg:postcode":"75751",
    "sg:province":"TX",
    "wof:name":"Carlton Rizer",
    "wof:placetype":"venue"
},
  "geometry": {"coordinates":[-95.844992,32.191951],"type":"Point"}
}