{
  "type": "Feature",
  "properties": {
    "iso:country":"US",
    "sg:address":"11480 Hillguard Rd",
    "sg:city":"Dallas",
    "sg:classifiers":[
        {
            "category":"Wholesale",
            "subcategory":"Home Furnishings",
            "type":"Manufacturing & Wholesale Goods"
        }
    ],
    "sg:phone":"+1 214 261 1050",
    "sg:postcode":"75243",
    "sg:province":"TX",
    "sg:tags":[
        "plumbing",
        "supplies-wholesale",
        "part",
        "fixture",
        "manufacturer"
    ],
    "wof:name":"Arizona Partsmaster, Inc.",
    "wof:placetype":"venue"
},
  "geometry": {"coordinates":[-96.70558800000001,32.903017],"type":"Point"}
}