{
  "type": "Feature",
  "properties": {
    "iso:country":"US",
    "sg:address":"1902 Texas Ave",
    "sg:city":"Texas City",
    "sg:classifiers":[
        {
            "category":"Travel",
            "subcategory":"Hotels & Motels",
            "type":"Entertainment"
        }
    ],
    "sg:phone":"+1 409 945 7727",
    "sg:postcode":"77590",
    "sg:province":"TX",
    "wof:name":"Econo Lodge",
    "wof:placetype":"venue"
},
  "geometry": {"coordinates":[-94.923366,29.383995],"type":"Point"}
}