{
  "type": "Feature",
  "properties": {
    "iso:country":"US",
    "sg:address":"12633 Gholson Rd",
    "sg:city":"Waco",
    "sg:classifiers":[
        {
            "category":"Food & Beverages",
            "subcategory":"Candy",
            "type":"Retail Goods"
        }
    ],
    "sg:phone":"+1 254 829 1834",
    "sg:postcode":"76705",
    "sg:province":"TX",
    "wof:name":"Russells Pecans & Fine C",
    "wof:placetype":"venue"
},
  "geometry": {"coordinates":[-97.186829,31.685239],"type":"Point"}
}