{
  "type": "Feature",
  "properties": {
    "iso:country":"US",
    "sg:address":"1925 E Belt Line Rd",
    "sg:city":"Carrollton",
    "sg:classifiers":[
        {
            "category":"Health Services",
            "subcategory":"Doctor",
            "type":"Services"
        }
    ],
    "sg:phone":"+1 972 416 2002",
    "sg:postcode":"75006",
    "sg:province":"TX",
    "wof:name":"Marc R Dandois DDS",
    "wof:placetype":"venue"
},
  "geometry": {"coordinates":[-96.88746,32.95375],"type":"Point"}
}