{
  "type": "Feature",
  "properties": {
    "iso:country":"US",
    "sg:address":"1131 Oak Hill Cir",
    "sg:city":"Dallas",
    "sg:classifiers":[
        {
            "category":"Freight",
            "type":"Transportation"
        }
    ],
    "sg:phone":"+1 214 391 8529",
    "sg:postcode":"75217",
    "sg:province":"TX",
    "sg:tags":[
        "operator",
        "local",
        "trucking"
    ],
    "wof:name":"J Ruedas Trucking",
    "wof:placetype":"venue"
},
  "geometry": {"coordinates":[-96.671235,32.733729],"type":"Point"}
}