{
  "type": "Feature",
  "properties": {
    "iso:country":"US",
    "sg:address":"6150 Valley Forge Dr",
    "sg:city":"Houston",
    "sg:classifiers":[
        {
            "category":"Professional",
            "type":"Services"
        }
    ],
    "sg:phone":"+1 713 932 1416",
    "sg:postcode":"77057",
    "sg:province":"TX",
    "wof:name":"Paul E Brill",
    "wof:placetype":"venue"
},
  "geometry": {"coordinates":[-95.491285,29.753624],"type":"Point"}
}