{
  "type": "Feature",
  "properties": {
    "iso:country":"US",
    "sg:address":"5106 35th St",
    "sg:city":"Lubbock",
    "sg:classifiers":[
        {
            "category":"Communications",
            "subcategory":"Film & Video Production",
            "type":"Services"
        }
    ],
    "sg:phone":"+1 806 796 0025",
    "sg:postcode":"79414",
    "sg:province":"TX",
    "sg:tags":[
        "motion",
        "picture",
        "distribution"
    ],
    "wof:name":"Floris Landscaping",
    "wof:placetype":"venue"
},
  "geometry": {"coordinates":[-101.922369,33.562398],"type":"Point"}
}