{
  "type": "Feature",
  "properties": {
    "iso:country":"US",
    "sg:address":"12100 Preston Rd",
    "sg:city":"Dallas",
    "sg:classifiers":[
        {
            "category":"Health Services",
            "subcategory":"Health Practitioner",
            "type":"Services"
        },
        {
            "category":"Personal",
            "subcategory":"Beauty Salon",
            "type":"Services"
        }
    ],
    "sg:phone":"+1 972 392 7729",
    "sg:postcode":"75230",
    "sg:province":"TX",
    "sg:tags":[
        "spa",
        "fitness",
        "physical",
        "day",
        "facility"
    ],
    "sg:website":"www.cooperspa.com",
    "wof:name":"Spa At The Cooper Aerobics Ctr",
    "wof:placetype":"venue"
},
  "geometry": {"coordinates":[-96.80355,32.914239],"type":"Point"}
}