{
  "type": "Feature",
  "properties": {
    "iso:country":"US",
    "sg:address":"131 Degan Ave",
    "sg:city":"Lewisville",
    "sg:classifiers":[
        {
            "category":"Banks & Credit Unions",
            "subcategory":"Investment Brokerage",
            "type":"Services"
        }
    ],
    "sg:phone":"+1 972 353 9977",
    "sg:postcode":"75057",
    "sg:province":"TX",
    "sg:tags":[
        "advisory",
        "financial"
    ],
    "wof:name":"Witte Investment Svc",
    "wof:placetype":"venue"
},
  "geometry": {"coordinates":[-97.00698,33.046777],"type":"Point"}
}