{
  "type": "Feature",
  "properties": {
    "iso:country":"US",
    "sg:address":"101 S Jennings Ave",
    "sg:city":"Fort Worth",
    "sg:classifiers":[
        {
            "category":"Manufacturing",
            "subcategory":"Apparel",
            "type":"Manufacturing & Wholesale Goods"
        }
    ],
    "sg:phone":"+1 817 332 8604",
    "sg:postcode":"76104",
    "sg:province":"TX",
    "sg:tags":[
        "sewing",
        "contractor"
    ],
    "wof:name":"Milliken & Co",
    "wof:placetype":"venue"
},
  "geometry": {"coordinates":[-97.329945,32.742731],"type":"Point"}
}