{
  "type": "Feature",
  "properties": {
    "iso:country":"US",
    "sg:address":"3222 Cockrell Ave",
    "sg:city":"Fort Worth",
    "sg:classifiers":[
        {
            "category":"Utilities",
            "type":"Services"
        }
    ],
    "sg:phone":"+1 817 927 0000",
    "sg:postcode":"76109",
    "sg:province":"TX",
    "sg:tags":[
        "sanitary"
    ],
    "wof:name":"Mister Sweeper",
    "wof:placetype":"venue"
},
  "geometry": {"coordinates":[-97.359386,32.702372],"type":"Point"}
}