{
  "type": "Feature",
  "properties": {
    "iso:country":"US",
    "sg:address":"123 N 24th St",
    "sg:city":"Lamesa",
    "sg:classifiers":[
        {
            "category":"Retail",
            "subcategory":"Auto Repair",
            "type":"Services"
        }
    ],
    "sg:phone":"+1 806 872 7561",
    "sg:postcode":"79331",
    "sg:province":"TX",
    "sg:tags":[
        "automotive"
    ],
    "wof:name":"Lamesa Wrecker Service",
    "wof:placetype":"venue"
},
  "geometry": {"coordinates":[-101.951359,32.757107],"type":"Point"}
}