{
  "type": "Feature",
  "properties": {
    "iso:country":"US",
    "sg:address":"8406 Banquo Dr",
    "sg:city":"Dallas",
    "sg:classifiers":[
        {
            "category":"Food & Beverages",
            "subcategory":"Groceries & Convenience Stores",
            "type":"Retail Goods"
        }
    ],
    "sg:phone":"+1 214 324 3595",
    "sg:postcode":"75228",
    "sg:province":"TX",
    "sg:tags":[
        "notion"
    ],
    "wof:name":"Betta Threads",
    "wof:placetype":"venue"
},
  "geometry": {"coordinates":[-96.70533399999999,32.805663],"type":"Point"}
}