{
  "type": "Feature",
  "properties": {
    "iso:country":"US",
    "sg:address":"4313 Lone Star Trl",
    "sg:city":"Temple",
    "sg:classifiers":[
        {
            "category":"Restaurant",
            "type":"Food & Drink"
        }
    ],
    "sg:phone":"+1 254 771 3302",
    "sg:postcode":"76502",
    "sg:province":"TX",
    "sg:tags":[
        "eating"
    ],
    "wof:name":"Chuck Wagon Cafe",
    "wof:placetype":"venue"
},
  "geometry": {"coordinates":[-97.377385,31.057945],"type":"Point"}
}