{
  "type": "Feature",
  "properties": {
    "iso:country":"US",
    "sg:address":"2020 19th St NW",
    "sg:city":"Paris",
    "sg:classifiers":[
        {
            "category":"Manufacturing",
            "subcategory":"Food",
            "type":"Manufacturing & Wholesale Goods"
        }
    ],
    "sg:phone":"+1 903 785 6401",
    "sg:postcode":"75460",
    "sg:province":"TX",
    "sg:tags":[
        "bakery",
        "prod",
        "cookie"
    ],
    "wof:name":"Sara Lee Bakery Group",
    "wof:placetype":"venue"
},
  "geometry": {"coordinates":[-95.57700699999999,33.679703],"type":"Point"}
}