{
  "type": "Feature",
  "properties": {
    "iso:country":"US",
    "sg:address":"1601 N Davis Dr",
    "sg:city":"Arlington",
    "sg:classifiers":[
        {
            "category":"Social Services",
            "type":"Services"
        }
    ],
    "sg:phone":"+1 817 459 4950",
    "sg:postcode":"76012",
    "sg:province":"TX",
    "wof:name":"Hearts & Hands",
    "wof:placetype":"venue"
},
  "geometry": {"coordinates":[-97.123054,32.757922],"type":"Point"}
}