{
  "type": "Feature",
  "properties": {
    "iso:country":"US",
    "sg:address":"201 Iris Ln",
    "sg:city":"Cedar Hill",
    "sg:classifiers":[
        {
            "category":"Personal",
            "type":"Services"
        }
    ],
    "sg:phone":"+1 972 293 9169",
    "sg:postcode":"75104",
    "sg:province":"TX",
    "wof:name":"Elegant Times 2 Remember",
    "wof:placetype":"venue"
},
  "geometry": {"coordinates":[-96.94448800000001,32.575862],"type":"Point"}
}