{
  "type": "Feature",
  "properties": {
    "iso:country":"US",
    "sg:address":"3525 Sage Rd",
    "sg:city":"Houston",
    "sg:classifiers":[
        {
            "category":"Social Services",
            "subcategory":"Job Training",
            "type":"Services"
        }
    ],
    "sg:phone":"+1 713 807 9902",
    "sg:postcode":"77056",
    "sg:province":"TX",
    "wof:name":"Discover U2",
    "wof:placetype":"venue"
},
  "geometry": {"coordinates":[-95.466511,29.729652],"type":"Point"}
}