{
  "type": "Feature",
  "properties": {
    "iso:country":"US",
    "sg:address":"4639 State Hwy 6",
    "sg:city":"Sugar Land",
    "sg:classifiers":[
        {
            "category":"Banks & Credit Unions",
            "subcategory":"Bank",
            "type":"Services"
        }
    ],
    "sg:phone":"+1 281 276 8100",
    "sg:postcode":"77478",
    "sg:province":"TX",
    "sg:tags":[
        "commercial"
    ],
    "wof:name":"Metrobank N A",
    "wof:placetype":"venue"
},
  "geometry": {"coordinates":[-95.58406600000001,29.581171],"type":"Point"}
}