{
  "type": "Feature",
  "properties": {
    "iso:country":"US",
    "sg:address":"13395 Stafford Rd",
    "sg:city":"Stafford",
    "sg:classifiers":[
        {
            "category":"Wholesale",
            "subcategory":"Machinery & Supplies",
            "type":"Manufacturing & Wholesale Goods"
        }
    ],
    "sg:phone":"+1 281 261 7580",
    "sg:postcode":"77477",
    "sg:province":"TX",
    "sg:tags":[
        "equipment"
    ],
    "wof:name":"Tex-AM",
    "wof:placetype":"venue"
},
  "geometry": {"coordinates":[-95.55069899999999,29.627988],"type":"Point"}
}