{
  "type": "Feature",
  "properties": {
    "iso:country":"US",
    "sg:address":"545 S 11th St",
    "sg:city":"Beaumont",
    "sg:classifiers":[
        {
            "category":"Restaurant",
            "type":"Food & Drink"
        }
    ],
    "sg:phone":"+1 409 212 9420",
    "sg:postcode":"77701",
    "sg:province":"TX",
    "sg:tags":[
        "eating"
    ],
    "wof:name":"El Rodeo Mexican Restaurant",
    "wof:placetype":"venue"
},
  "geometry": {"coordinates":[-94.12948799999999,30.074103],"type":"Point"}
}