{
  "type": "Feature",
  "properties": {
    "iso:country":"US",
    "sg:address":"13550 Dallas Pkwy",
    "sg:city":"Dallas",
    "sg:classifiers":[
        {
            "category":"Shopping",
            "type":"Retail Goods"
        }
    ],
    "sg:phone":"+1 972 458 7000",
    "sg:postcode":"75240",
    "sg:province":"TX",
    "sg:website":"saksfifthavenue.com",
    "wof:name":"Saks Fifth Avenue",
    "wof:placetype":"venue"
},
  "geometry": {"coordinates":[-96.822739,32.931885],"type":"Point"}
}