{
  "type": "Feature",
  "properties": {
    "iso:country":"US",
    "sg:address":"103 Circle Way St",
    "sg:city":"Lake Jackson",
    "sg:classifiers":[
        {
            "category":"Real Estate",
            "subcategory":"Real Estate Agent",
            "type":"Services"
        }
    ],
    "sg:phone":"+1 979 285 9000",
    "sg:postcode":"77566",
    "sg:province":"TX",
    "wof:name":"Keller Williams Realty",
    "wof:placetype":"venue"
},
  "geometry": {"coordinates":[-95.451814,29.040632],"type":"Point"}
}