{
  "type": "Feature",
  "properties": {
    "iso:country":"US",
    "sg:address":"4710 Gulfway Dr",
    "sg:city":"Port Arthur",
    "sg:classifiers":[
        {
            "category":"Autos & Motor Vehicles",
            "subcategory":"Auto Supplies",
            "type":"Retail Goods"
        }
    ],
    "sg:phone":"+1 409 983 7811",
    "sg:postcode":"77642",
    "sg:province":"TX",
    "sg:tags":[
        "parts"
    ],
    "wof:name":"Autozone",
    "wof:placetype":"venue"
},
  "geometry": {"coordinates":[-93.910404,29.918426],"type":"Point"}
}