{
  "type": "Feature",
  "properties": {
    "iso:country":"US",
    "sg:address":"2001 Fort Davis Hwy Apt 1",
    "sg:city":"Alpine",
    "sg:classifiers":[
        {
            "category":"Real Estate",
            "subcategory":"Real Estate Services",
            "type":"Services"
        },
        {
            "category":"Real Estate",
            "subcategory":"Real Estate Operator",
            "type":"Services"
        }
    ],
    "sg:phone":"+1 432 837 7400",
    "sg:postcode":"79830",
    "sg:province":"TX",
    "sg:tags":[
        "vacancy",
        "apartment",
        "rental",
        "listing"
    ],
    "sg:website":"http://www.hallmarktownhouses.com",
    "wof:name":"Hallmark Townhouse",
    "wof:placetype":"venue"
},
  "geometry": {"coordinates":[-103.667526,30.374397],"type":"Point"}
}