{
  "type": "Feature",
  "properties": {
    "iso:country":"US",
    "sg:address":"19122 Co Rd 178",
    "sg:city":"Flint",
    "sg:classifiers":[
        {
            "category":"Building & Trades",
            "subcategory":"Construction",
            "type":"Services"
        }
    ],
    "sg:phone":"+1 903 894 3510",
    "sg:postcode":"75762",
    "sg:province":"TX",
    "sg:tags":[
        "builder",
        "cabinet"
    ],
    "wof:name":"Spillers Cabinet Shop",
    "wof:placetype":"venue"
},
  "geometry": {"coordinates":[-95.375715,32.203335],"type":"Point"}
}