{
  "type": "Feature",
  "properties": {
    "iso:country":"US",
    "sg:address":"811 N Central Expy",
    "sg:city":"Plano",
    "sg:classifiers":[
        {
            "category":"Restaurant",
            "type":"Food & Drink"
        }
    ],
    "sg:menulink":"http://www.allmenus.com/tx/plano/72659-sbarro/menu/",
    "sg:phone":"+1 972 422 0590",
    "sg:postcode":"75075",
    "sg:province":"TX",
    "sg:tags":[
        "american",
        "pizza"
    ],
    "wof:name":"Sbarro",
    "wof:placetype":"venue"
},
  "geometry": {"coordinates":[-96.708707,33.010649],"type":"Point"}
}