{
  "type": "Feature",
  "properties": {
    "iso:country":"US",
    "sg:address":"400 Hemlock Dr",
    "sg:city":"Arlington",
    "sg:classifiers":[
        {
            "category":"Education",
            "subcategory":"Special Training",
            "type":"Public Place"
        }
    ],
    "sg:phone":"+1 817 467 6035",
    "sg:postcode":"76018",
    "sg:province":"TX",
    "wof:name":"Johns Esl Tutoring",
    "wof:placetype":"venue"
},
  "geometry": {"coordinates":[-97.108301,32.656552],"type":"Point"}
}