{
  "type": "Feature",
  "properties": {
    "iso:country":"US",
    "sg:address":"5711 Abilene Trl",
    "sg:city":"Austin",
    "sg:classifiers":[
        {
            "category":"Building & Trades",
            "subcategory":"Construction",
            "type":"Services"
        }
    ],
    "sg:phone":"+1 512 892 4994",
    "sg:postcode":"78749",
    "sg:province":"TX",
    "sg:tags":[
        "tennis",
        "court"
    ],
    "wof:name":"Dobbs Tennis Courts Inc",
    "wof:placetype":"venue"
},
  "geometry": {"coordinates":[-97.861723,30.223777],"type":"Point"}
}