{
  "type": "Feature",
  "properties": {
    "iso:country":"US",
    "sg:address":"1818 Cedar Bayou Rd",
    "sg:city":"Baytown",
    "sg:classifiers":[
        {
            "category":"Restaurant",
            "type":"Food & Drink"
        }
    ],
    "sg:phone":"+1 281 427 2790",
    "sg:postcode":"77520",
    "sg:province":"TX",
    "wof:name":"Rooty Tooty, Inc.",
    "wof:placetype":"venue"
},
  "geometry": {"coordinates":[-94.943691,29.750797],"type":"Point"}
}