{
  "type": "Feature",
  "properties": {
    "iso:country":"US",
    "sg:address":"918 Houston St",
    "sg:city":"Levelland",
    "sg:classifiers":[
        {
            "category":"Shopping",
            "subcategory":"Gifts & Souvenirs",
            "type":"Retail Goods"
        },
        {
            "category":"Shopping",
            "subcategory":"Antiques",
            "type":"Retail Goods"
        }
    ],
    "sg:phone":"+1 806 894 4186",
    "sg:postcode":"79336",
    "sg:province":"TX",
    "sg:tags":[
        "shop"
    ],
    "wof:name":"Mary's Fine Gifts",
    "wof:placetype":"venue"
},
  "geometry": {"coordinates":[-102.40273999999999,33.587099],"type":"Point"}
}