{
  "type": "Feature",
  "properties": {
    "iso:country":"US",
    "sg:address":"4351 Donnybrook Pl",
    "sg:city":"El Paso",
    "sg:classifiers":[
        {
            "category":"Professional",
            "subcategory":"Management & Consulting",
            "type":"Services"
        }
    ],
    "sg:phone":"+1 915 543 9343",
    "sg:postcode":"79902",
    "sg:province":"TX",
    "sg:tags":[
        "business"
    ],
    "wof:name":"Zib Consulting",
    "wof:placetype":"venue"
},
  "geometry": {"coordinates":[-106.501549,31.799186],"type":"Point"}
}