{
  "type": "Feature",
  "properties": {
    "iso:country":"US",
    "sg:address":"7119 Burns St",
    "sg:city":"Richland Hills",
    "sg:classifiers":[
        {
            "category":"Autos & Motor Vehicles",
            "subcategory":"Motorcycle Sales",
            "type":"Retail Goods"
        }
    ],
    "sg:phone":"+1 817 624 7861",
    "sg:postcode":"76118",
    "sg:province":"TX",
    "sg:tags":[
        "scooter"
    ],
    "wof:name":"Mr Motorcycle",
    "wof:placetype":"venue"
},
  "geometry": {"coordinates":[-97.22635200000001,32.797149],"type":"Point"}
}