{
  "type": "Feature",
  "properties": {
    "iso:country":"US",
    "sg:address":"1346 Brazos St",
    "sg:city":"Hempstead",
    "sg:classifiers":[
        {
            "category":"Personal",
            "type":"Services"
        }
    ],
    "sg:phone":"+1 979 826 2215",
    "sg:postcode":"77445",
    "sg:province":"TX",
    "wof:name":"Body Shop",
    "wof:placetype":"venue"
},
  "geometry": {"coordinates":[-96.082621,30.101287],"type":"Point"}
}