{
  "type": "Feature",
  "properties": {
    "iso:country":"US",
    "sg:address":"5473 Blair Rd",
    "sg:city":"Dallas",
    "sg:classifiers":[
        {
            "category":"Banks & Credit Unions",
            "subcategory":"Investment Brokerage",
            "type":"Services"
        }
    ],
    "sg:phone":"+1 214 368 1550",
    "sg:postcode":"75231",
    "sg:province":"TX",
    "sg:tags":[
        "security"
    ],
    "wof:name":"Terry Operating L L C",
    "wof:placetype":"venue"
},
  "geometry": {"coordinates":[-96.765956,32.885081],"type":"Point"}
}