{
  "type": "Feature",
  "properties": {
    "iso:country":"US",
    "sg:address":"8801 Urbana Ave",
    "sg:city":"Lubbock",
    "sg:classifiers":[
        {
            "category":"Home & Garden",
            "subcategory":"Household Appliances",
            "type":"Retail Goods"
        },
        {
            "category":"Building & Trades",
            "subcategory":"Plumbing",
            "type":"Services"
        },
        {
            "category":"Building & Trades",
            "subcategory":"Construction",
            "type":"Services"
        }
    ],
    "sg:phone":"+1 806 794 3760",
    "sg:postcode":"79424",
    "sg:province":"TX",
    "sg:tags":[
        "plumber",
        "industrial",
        "specialty",
        "heating",
        "appliances-small",
        "system",
        "major",
        "contractor",
        "air conditioning",
        "contractors-commercial"
    ],
    "sg:website":"http://www.comfortmaker.com",
    "wof:name":"Ameritech Plumbing Heating & Air Inc.-Jack Adams",
    "wof:placetype":"venue"
},
  "geometry": {"coordinates":[-101.97699,33.514011],"type":"Point"}
}