{
  "type": "Feature",
  "properties": {
    "iso:country":"US",
    "sg:address":"2140 Hutton Dr",
    "sg:city":"Carrollton",
    "sg:classifiers":[
        {
            "category":"Wholesale",
            "subcategory":"Apparel",
            "type":"Manufacturing & Wholesale Goods"
        }
    ],
    "sg:phone":"+1 214 459 1054",
    "sg:postcode":"75006",
    "sg:province":"TX",
    "sg:tags":[
        "importer",
        "medical",
        "uniform"
    ],
    "wof:name":"Dickies Medical Uniforms",
    "wof:placetype":"venue"
},
  "geometry": {"coordinates":[-96.915353,32.934848],"type":"Point"}
}