{
  "type": "Feature",
  "properties": {
    "iso:country":"US",
    "sg:address":"4815 W Braker Ln At US Hw N",
    "sg:city":"Austin",
    "sg:classifiers":[
        {
            "category":"Shopping",
            "subcategory":"Optician",
            "type":"Retail Goods"
        }
    ],
    "sg:phone":"+1 512 338 9774",
    "sg:postcode":"78701",
    "sg:province":"TX",
    "sg:tags":[
        "eyewear"
    ],
    "wof:name":"Michael Mooney",
    "wof:placetype":"venue"
},
  "geometry": {"coordinates":[-97.74779599999999,30.400621],"type":"Point"}
}