{
  "type": "Feature",
  "properties": {
    "iso:country":"US",
    "sg:address":"1488 E Main St",
    "sg:city":"Eastland",
    "sg:classifiers":[
        {
            "category":"Food & Beverages",
            "subcategory":"Groceries & Convenience Stores",
            "type":"Retail Goods"
        }
    ],
    "sg:phone":"+1 254 629 1427",
    "sg:postcode":"76448",
    "sg:province":"TX",
    "wof:name":"Skinnys Convenience Stores 58",
    "wof:placetype":"venue"
},
  "geometry": {"coordinates":[-98.79106899999999,32.40162],"type":"Point"}
}