{
  "type": "Feature",
  "properties": {
    "iso:country":"US",
    "sg:address":"1112 Town East Mall",
    "sg:city":"Mesquite",
    "sg:classifiers":[
        {
            "category":"Shopping",
            "subcategory":"Shoes",
            "type":"Retail Goods"
        }
    ],
    "sg:phone":"+1 972 698 8696",
    "sg:postcode":"75150",
    "sg:province":"TX",
    "sg:tags":[
        "store"
    ],
    "sg:website":"www.master-shoes.com",
    "wof:name":"Master Shoes",
    "wof:placetype":"venue"
},
  "geometry": {"coordinates":[-96.62636999999999,32.80866],"type":"Point"}
}