{
  "type": "Feature",
  "properties": {
    "iso:country":"US",
    "sg:address":"4264 Kellway Cir",
    "sg:city":"Addison",
    "sg:classifiers":[
        {
            "category":"Professional",
            "subcategory":"Computer Services",
            "type":"Services"
        }
    ],
    "sg:phone":"+1 972 239 8850",
    "sg:postcode":"75001",
    "sg:province":"TX",
    "sg:tags":[
        "website",
        "design"
    ],
    "sg:website":"www.dfwwebpages.com",
    "wof:name":"DFW Web",
    "wof:placetype":"venue"
},
  "geometry": {"coordinates":[-96.8417,32.970602],"type":"Point"}
}