{
  "type": "Feature",
  "properties": {
    "iso:country":"US",
    "sg:address":"325 E Bob Jones Rd",
    "sg:city":"Roanoke",
    "sg:classifiers":[
        {
            "category":"Shopping",
            "subcategory":"Clothing, Apparel, & Fashions",
            "type":"Retail Goods"
        }
    ],
    "sg:phone":"+1 817 430 1518",
    "sg:postcode":"76262",
    "sg:province":"TX",
    "sg:tags":[
        "western"
    ],
    "wof:name":"T Bar M Ranch",
    "wof:placetype":"venue"
},
  "geometry": {"coordinates":[-97.141902,32.999661],"type":"Point"}
}