{
  "type": "Feature",
  "properties": {
    "iso:country":"US",
    "sg:address":"307 N Main St",
    "sg:city":"Jacksonville",
    "sg:classifiers":[
        {
            "category":"Retail",
            "subcategory":"Auto Repair",
            "type":"Services"
        }
    ],
    "sg:phone":"+1 903 586 9044",
    "sg:postcode":"75766",
    "sg:province":"TX",
    "sg:tags":[
        "body",
        "shop",
        "top",
        "paint"
    ],
    "wof:name":"Ray Rays Auto Trim Shop",
    "wof:placetype":"venue"
},
  "geometry": {"coordinates":[-95.275265,31.968995],"type":"Point"}
}