{
  "type": "Feature",
  "properties": {
    "iso:country":"US",
    "sg:address":"1595 Calder Ave",
    "sg:city":"Beaumont",
    "sg:classifiers":[
        {
            "category":"Restaurant",
            "type":"Food & Drink"
        }
    ],
    "sg:phone":"+1 409 813 1444",
    "sg:postcode":"77701",
    "sg:province":"TX",
    "wof:name":"Pig Stands Co Inc",
    "wof:placetype":"venue"
},
  "geometry": {"coordinates":[-94.110927,30.085891],"type":"Point"}
}