{
  "type": "Feature",
  "properties": {
    "iso:country":"US",
    "sg:address":"31 Windmill Cir Ste A",
    "sg:city":"Abilene",
    "sg:classifiers":[
        {
            "category":"Building & Trades",
            "subcategory":"Construction",
            "type":"Services"
        }
    ],
    "sg:phone":"+1 325 692 5632",
    "sg:postcode":"79606",
    "sg:province":"TX",
    "sg:tags":[
        "industrial",
        "wallcoverings-installation",
        "wallpaper",
        "contractor",
        "contractors-commercial",
        "painting"
    ],
    "wof:name":"Pickens Painting Contractors Inc",
    "wof:placetype":"venue"
},
  "geometry": {"coordinates":[-99.74649599999999,32.37748],"type":"Point"}
}