{
  "type": "Feature",
  "properties": {
    "iso:country":"US",
    "sg:address":"412 S Terrell St",
    "sg:city":"Midland",
    "sg:phone":"+1 432 570 1000",
    "sg:postcode":"79701",
    "sg:province":"TX",
    "sg:tags":[
        "equipment",
        "wholesale",
        "retail",
        "commercial",
        "supply"
    ],
    "wof:name":"Hill & Hill Restaurant Supply",
    "wof:placetype":"venue"
},
  "geometry": {"coordinates":[-102.0682,31.993576],"type":"Point"}
}