{
  "type": "Feature",
  "properties": {
    "iso:country":"US",
    "sg:address":"3101 Race St",
    "sg:city":"Fort Worth",
    "sg:classifiers":[
        {
            "category":"Education",
            "subcategory":"School",
            "type":"Public Place"
        }
    ],
    "sg:phone":"+1 817 834 1966",
    "sg:postcode":"76111",
    "sg:province":"TX",
    "wof:name":"Science Etc",
    "wof:placetype":"venue"
},
  "geometry": {"coordinates":[-97.30211199999999,32.773106],"type":"Point"}
}