{
  "type": "Feature",
  "properties": {
    "iso:country":"US",
    "sg:address":"28677 I- 45 N",
    "sg:city":"Spring",
    "sg:classifiers":[
        {
            "category":"Autos & Motor Vehicles",
            "subcategory":"Fuel & Gas Station",
            "type":"Retail Goods"
        }
    ],
    "sg:phone":"+1 281 444 2266",
    "sg:postcode":"77381",
    "sg:province":"TX",
    "sg:tags":[
        "station",
        "gasoline"
    ],
    "wof:name":"Sunmart No 144",
    "wof:placetype":"venue"
},
  "geometry": {"coordinates":[-95.452247,30.178243],"type":"Point"}
}