{
  "type": "Feature",
  "properties": {
    "iso:country":"US",
    "sg:address":"1515 S Chestnut St",
    "sg:city":"Lufkin",
    "sg:classifiers":[
        {
            "category":"Retail",
            "subcategory":"Funeral Services",
            "type":"Services"
        }
    ],
    "sg:phone":"+1 936 634 4411",
    "sg:postcode":"75901",
    "sg:province":"TX",
    "sg:tags":[
        "director"
    ],
    "wof:name":"Gipson-Metcalf Funeral Drctrs",
    "wof:placetype":"venue"
},
  "geometry": {"coordinates":[-94.71352,31.322251],"type":"Point"}
}