{
  "type": "Feature",
  "properties": {
    "iso:country":"US",
    "sg:address":"18931 Timber Trace Dr",
    "sg:city":"Humble",
    "sg:classifiers":[
        {
            "category":"Professional",
            "subcategory":"Computer Services",
            "type":"Services"
        }
    ],
    "sg:phone":"+1 281 852 0810",
    "sg:postcode":"77346",
    "sg:province":"TX",
    "sg:tags":[
        "programing",
        "custom"
    ],
    "wof:name":"Ezramp Solutions",
    "wof:placetype":"venue"
},
  "geometry": {"coordinates":[-95.17039200000001,29.993326],"type":"Point"}
}