{
  "type": "Feature",
  "properties": {
    "iso:country":"US",
    "sg:address":"11015 Wainfleet Ln",
    "sg:city":"Houston",
    "sg:classifiers":[
        {
            "category":"Home & Garden",
            "subcategory":"Furniture",
            "type":"Retail Goods"
        }
    ],
    "sg:phone":"+1 281 924 5007",
    "sg:postcode":"77096",
    "sg:province":"TX",
    "wof:name":"Monique Bargain Center",
    "wof:placetype":"venue"
},
  "geometry": {"coordinates":[-95.50157400000001,29.658586],"type":"Point"}
}