{
  "type": "Feature",
  "properties": {
    "iso:country":"US",
    "sg:address":"4502 Woodside St",
    "sg:city":"Houston",
    "sg:classifiers":[
        {
            "category":"Education",
            "subcategory":"School",
            "type":"Public Place"
        }
    ],
    "sg:phone":"+1 713 926 2580",
    "sg:postcode":"77023",
    "sg:province":"TX",
    "wof:name":"Houston Project Docc",
    "wof:placetype":"venue"
},
  "geometry": {"coordinates":[-95.332815,29.739805],"type":"Point"}
}