{
  "type": "Feature",
  "properties": {
    "iso:country":"US",
    "sg:address":"11618 Sahara Way",
    "sg:city":"Dallas",
    "sg:classifiers":[
        {
            "category":"Building & Trades",
            "subcategory":"Construction",
            "type":"Services"
        }
    ],
    "sg:phone":"+1 214 328 6002",
    "sg:postcode":"75218",
    "sg:province":"TX",
    "sg:tags":[
        "roofing",
        "contractor"
    ],
    "wof:name":"Wayne Boule Roofing",
    "wof:placetype":"venue"
},
  "geometry": {"coordinates":[-96.69055899999999,32.855025],"type":"Point"}
}