{
  "type": "Feature",
  "properties": {
    "iso:country":"US",
    "sg:address":"36405 Marshall Hutts Rd",
    "sg:city":"Rio Hondo",
    "sg:classifiers":[
        {
            "category":"Shopping",
            "subcategory":"Bicycles & Sporting Goods",
            "type":"Retail Goods"
        }
    ],
    "sg:phone":"+1 956 748 2406",
    "sg:postcode":"78583",
    "sg:province":"TX",
    "wof:name":"Sanchez Bait Stand",
    "wof:placetype":"venue"
},
  "geometry": {"coordinates":[-97.426497,26.342026],"type":"Point"}
}