{
  "type": "Feature",
  "properties": {
    "iso:country":"US",
    "sg:address":"3517 Rogers Ave",
    "sg:city":"Fort Worth",
    "sg:classifiers":[
        {
            "category":"Real Estate",
            "subcategory":"Real Estate Agent",
            "type":"Services"
        }
    ],
    "sg:phone":"+1 817 927 8844",
    "sg:postcode":"76109",
    "sg:province":"TX",
    "sg:tags":[
        "management"
    ],
    "wof:name":"Ba Da Management Corp",
    "wof:placetype":"venue"
},
  "geometry": {"coordinates":[-97.36371,32.697265],"type":"Point"}
}