{
  "type": "Feature",
  "properties": {
    "iso:country":"US",
    "sg:address":"519 S Armstrong Ave",
    "sg:city":"Denison",
    "sg:classifiers":[
        {
            "category":"Autos & Motor Vehicles",
            "subcategory":"Automobile Sales",
            "type":"Retail Goods"
        }
    ],
    "sg:phone":"+1 903 465 5022",
    "sg:postcode":"75020",
    "sg:province":"TX",
    "sg:tags":[
        "car",
        "used"
    ],
    "wof:name":"Gladen Roy Auto Sales",
    "wof:placetype":"venue"
},
  "geometry": {"coordinates":[-96.546352,33.751658],"type":"Point"}
}