{
  "type": "Feature",
  "properties": {
    "iso:country":"US",
    "sg:address":"3801 N MacGregor Way",
    "sg:city":"Houston",
    "sg:classifiers":[
        {
            "category":"Retail",
            "subcategory":"Laundry & Dry Cleaning",
            "type":"Services"
        }
    ],
    "sg:phone":"+1 713 524 3127",
    "sg:postcode":"77004",
    "sg:province":"TX",
    "wof:name":"Bayou Cleaners",
    "wof:placetype":"venue"
},
  "geometry": {"coordinates":[-95.3563,29.710199],"type":"Point"}
}