{
  "type": "Feature",
  "properties": {
    "iso:country":"US",
    "sg:address":"7400 San Pedro Ave",
    "sg:city":"San Antonio",
    "sg:classifiers":[
        {
            "category":"Restaurant",
            "type":"Food & Drink"
        },
        {
            "category":"Ice Cream",
            "type":"Food & Drink"
        }
    ],
    "sg:menulink":"http://www.allmenus.com/tx/san-antonio/230064-marble-slab-creamery/menu/",
    "sg:phone":"+1 210 366 1900",
    "sg:postcode":"78216",
    "sg:province":"TX",
    "sg:tags":[
        "american",
        "ice",
        "cream"
    ],
    "wof:name":"Marble Slab Creamery",
    "wof:placetype":"venue"
},
  "geometry": {"coordinates":[-98.4992,29.51792],"type":"Point"}
}