{
  "type": "Feature",
  "properties": {
    "iso:country":"US",
    "sg:address":"6347 Deloache Ave",
    "sg:city":"Dallas",
    "sg:classifiers":[
        {
            "category":"Utilities",
            "subcategory":"Telephone",
            "type":"Services"
        }
    ],
    "sg:phone":"+1 214 750 8947",
    "sg:postcode":"75225",
    "sg:province":"TX",
    "sg:tags":[
        "host",
        "internet"
    ],
    "wof:name":"Titlelink  LLC",
    "wof:placetype":"venue"
},
  "geometry": {"coordinates":[-96.80202199999999,32.870805],"type":"Point"}
}