{
  "type": "Feature",
  "properties": {
    "iso:country":"US",
    "sg:address":"1551 E Spring Valley Rd",
    "sg:city":"Richardson",
    "sg:classifiers":[
        {
            "category":"Sports & Exercise",
            "subcategory":"Gym",
            "type":"Entertainment"
        }
    ],
    "sg:phone":"+1 972 671 2644",
    "sg:postcode":"75081",
    "sg:province":"TX",
    "sg:tags":[
        "facility",
        "club",
        "gymnasium",
        "health",
        "fitness",
        "studio",
        "physical"
    ],
    "wof:name":"Weightperfect Women's Fitness",
    "wof:placetype":"venue"
},
  "geometry": {"coordinates":[-96.695595,32.938639],"type":"Point"}
}