{
  "type": "Feature",
  "properties": {
    "iso:country":"US",
    "sg:address":"10635 State Hwy 1604",
    "sg:city":"San Antonio",
    "sg:classifiers":[
        {
            "category":"Home & Garden",
            "subcategory":"Garden Supply",
            "type":"Retail Goods"
        }
    ],
    "sg:phone":"+1 210 622 3936",
    "sg:postcode":"78252",
    "sg:province":"TX",
    "wof:name":"Tapia Tree Sales",
    "wof:placetype":"venue"
},
  "geometry": {"coordinates":[-98.684628,29.323259],"type":"Point"}
}