{
  "type": "Feature",
  "properties": {
    "iso:country":"US",
    "sg:address":"1710 Foxfire Dr",
    "sg:city":"Round Rock",
    "sg:classifiers":[
        {
            "category":"Professional",
            "type":"Services"
        }
    ],
    "sg:phone":"+1 512 246 6298",
    "sg:postcode":"78681",
    "sg:province":"TX",
    "wof:name":"Daniel Schneider",
    "wof:placetype":"venue"
},
  "geometry": {"coordinates":[-97.71464,30.526037],"type":"Point"}
}