{
  "type": "Feature",
  "properties": {
    "iso:country":"US",
    "sg:address":"2294 Starwood Cir",
    "sg:city":"Dallas",
    "sg:classifiers":[
        {
            "category":"Utilities",
            "subcategory":"Refuse",
            "type":"Services"
        },
        {
            "category":"Utilities",
            "subcategory":"Recycling",
            "type":"Services"
        },
        {
            "category":"Freight",
            "type":"Transportation"
        }
    ],
    "sg:phone":"+1 972 836 8772",
    "sg:postcode":"75253",
    "sg:province":"TX",
    "sg:tags":[
        "garbage",
        "disposal",
        "collection",
        "trucking",
        "equipment",
        "waste"
    ],
    "sg:website":"http://www.junkhaulsdallas.com",
    "wof:name":"Junk Hauls Dallas",
    "wof:placetype":"venue"
},
  "geometry": {"coordinates":[-96.625229,32.683797],"type":"Point"}
}