{
  "type": "Feature",
  "properties": {
    "iso:country":"US",
    "sg:address":"937 Mockingbird Dr",
    "sg:city":"Fort Worth",
    "sg:classifiers":[
        {
            "category":"Building & Trades",
            "subcategory":"Construction",
            "type":"Services"
        }
    ],
    "sg:phone":"+1 817 847 7680",
    "sg:postcode":"76131",
    "sg:province":"TX",
    "sg:tags":[
        "house"
    ],
    "wof:name":"Kimball Hill Homes",
    "wof:placetype":"venue"
},
  "geometry": {"coordinates":[-97.352982,32.872318],"type":"Point"}
}