{
  "type": "Feature",
  "properties": {
    "iso:country":"US",
    "sg:address":"2555 W South St",
    "sg:city":"Alvin",
    "sg:classifiers":[
        {
            "category":"Professional",
            "subcategory":"Management & Consulting",
            "type":"Services"
        }
    ],
    "sg:phone":"+1 281 331 4343",
    "sg:postcode":"77511",
    "sg:province":"TX",
    "wof:name":"Senior Marketing Services",
    "wof:placetype":"venue"
},
  "geometry": {"coordinates":[-95.26866800000001,29.405258],"type":"Point"}
}