{
  "type": "Feature",
  "properties": {
    "iso:country":"US",
    "sg:address":"16602 Cairnway Dr",
    "sg:city":"Houston",
    "sg:classifiers":[
        {
            "category":"Building & Trades",
            "subcategory":"Construction",
            "type":"Services"
        }
    ],
    "sg:phone":"+1 281 463 6690",
    "sg:postcode":"77084",
    "sg:province":"TX",
    "sg:tags":[
        "nonresidential"
    ],
    "wof:name":"Tusk Enterprize",
    "wof:placetype":"venue"
},
  "geometry": {"coordinates":[-95.653098,29.84114],"type":"Point"}
}