{
  "type": "Feature",
  "properties": {
    "iso:country":"US",
    "sg:address":"1810 W Anderson Ln",
    "sg:city":"Austin",
    "sg:classifiers":[
        {
            "category":"Shopping",
            "subcategory":"Clothing, Apparel, & Fashions",
            "type":"Retail Goods"
        }
    ],
    "sg:phone":"+1 512 323 0900",
    "sg:postcode":"78757",
    "sg:province":"TX",
    "sg:tags":[
        "shop",
        "bridal"
    ],
    "wof:name":"Bridal Shop",
    "wof:placetype":"venue"
},
  "geometry": {"coordinates":[-97.725442,30.35361],"type":"Point"}
}