{
  "type": "Feature",
  "properties": {
    "iso:country":"US",
    "sg:address":"430 E Kent St",
    "sg:city":"Slaton",
    "sg:classifiers":[
        {
            "category":"Wholesale",
            "subcategory":"Construction Materials",
            "type":"Manufacturing & Wholesale Goods"
        }
    ],
    "sg:phone":"+1 806 828 6203",
    "sg:postcode":"79364",
    "sg:province":"TX",
    "sg:tags":[
        "sand",
        "gravel"
    ],
    "wof:name":"R E Janes Gravel Co",
    "wof:placetype":"venue"
},
  "geometry": {"coordinates":[-101.637095,33.434785],"type":"Point"}
}