{
  "type": "Feature",
  "properties": {
    "iso:country":"US",
    "sg:address":"472 Shade Tree Cir",
    "sg:city":"Hurst",
    "sg:classifiers":[
        {
            "category":"Food & Beverages",
            "subcategory":"Groceries & Convenience Stores",
            "type":"Retail Goods"
        }
    ],
    "sg:phone":"+1 817 498 6530",
    "sg:postcode":"76054",
    "sg:province":"TX",
    "wof:name":"Housewarmers of Heb",
    "wof:placetype":"venue"
},
  "geometry": {"coordinates":[-97.17518,32.849021],"type":"Point"}
}