{
  "type": "Feature",
  "properties": {
    "iso:country":"US",
    "sg:address":"5500 Tesoro Plz",
    "sg:city":"Laredo",
    "sg:classifiers":[
        {
            "category":"Professional",
            "subcategory":"Business Services",
            "type":"Services"
        }
    ],
    "sg:phone":"+1 956 717 8583",
    "sg:postcode":"78041",
    "sg:province":"TX",
    "wof:name":"Ortiz Management Group Inc",
    "wof:placetype":"venue"
},
  "geometry": {"coordinates":[-99.50705000000001,27.546803],"type":"Point"}
}