{
  "type": "Feature",
  "properties": {
    "iso:country":"US",
    "sg:address":"7143 Bramlett Dr",
    "sg:city":"Dallas",
    "sg:classifiers":[
        {
            "category":"Building & Trades",
            "subcategory":"Landscaping Services",
            "type":"Services"
        }
    ],
    "sg:phone":"+1 214 391 6016",
    "sg:postcode":"75217",
    "sg:province":"TX",
    "wof:name":"Palomares Lawn Services",
    "wof:placetype":"venue"
},
  "geometry": {"coordinates":[-96.697112,32.729225],"type":"Point"}
}