{
  "type": "Feature",
  "properties": {
    "iso:country":"US",
    "sg:address":"1428 Kirnwood Dr",
    "sg:city":"Dallas",
    "sg:classifiers":[
        {
            "category":"Building & Trades",
            "subcategory":"Landscaping Services",
            "type":"Services"
        }
    ],
    "sg:phone":"+1 972 991 8733",
    "sg:postcode":"75232",
    "sg:province":"TX",
    "sg:tags":[
        "tree"
    ],
    "wof:name":"A C Expert Tree Care & Lndscp",
    "wof:placetype":"venue"
},
  "geometry": {"coordinates":[-96.843796,32.654365],"type":"Point"}
}