{
  "type": "Feature",
  "properties": {
    "iso:country":"US",
    "sg:address":"4926 Burnside Ave",
    "sg:city":"Dallas",
    "sg:classifiers":[
        {
            "category":"Shopping",
            "subcategory":"Gifts & Souvenirs",
            "type":"Retail Goods"
        }
    ],
    "sg:phone":"+1 214 458 5983",
    "sg:postcode":"75216",
    "sg:province":"TX",
    "sg:tags":[
        "basket",
        "parcel"
    ],
    "wof:name":"Ayon's Special Occasions",
    "wof:placetype":"venue"
},
  "geometry": {"coordinates":[-96.795303,32.686706],"type":"Point"}
}