{
  "type": "Feature",
  "properties": {
    "iso:country":"US",
    "sg:address":"219 E Laurel Ave",
    "sg:city":"Lufkin",
    "sg:classifiers":[
        {
            "category":"Professional",
            "subcategory":"Advertising",
            "type":"Services"
        }
    ],
    "sg:phone":"+1 936 632 1515",
    "sg:postcode":"75901",
    "sg:province":"TX",
    "sg:website":"www.peddlernet.com",
    "wof:name":"Peddler",
    "wof:placetype":"venue"
},
  "geometry": {"coordinates":[-94.724435,31.346331],"type":"Point"}
}