{
  "type": "Feature",
  "properties": {
    "iso:country":"US",
    "sg:address":"4424 E 33rd Ave",
    "sg:city":"Amarillo",
    "sg:classifiers":[
        {
            "category":"Building & Trades",
            "subcategory":"Construction",
            "type":"Services"
        }
    ],
    "sg:phone":"+1 806 376 5709",
    "sg:postcode":"79103",
    "sg:province":"TX",
    "sg:tags":[
        "house"
    ],
    "wof:name":"Burleson Contracting",
    "wof:placetype":"venue"
},
  "geometry": {"coordinates":[-101.782757,35.17889],"type":"Point"}
}