{
  "type": "Feature",
  "properties": {
    "iso:country":"US",
    "sg:address":"8926 Laura Koppe Rd",
    "sg:city":"Houston",
    "sg:classifiers":[
        {
            "category":"Building & Trades",
            "subcategory":"Cleaning & Sanitation",
            "type":"Services"
        }
    ],
    "sg:phone":"+1 281 583 1963",
    "sg:postcode":"77078",
    "sg:province":"TX",
    "sg:tags":[
        "repair",
        "maintenance"
    ],
    "wof:name":"Ds Quality Cleaning",
    "wof:placetype":"venue"
},
  "geometry": {"coordinates":[-95.26061900000001,29.840522],"type":"Point"}
}