{
  "type": "Feature",
  "properties": {
    "iso:country":"US",
    "sg:address":"1340 Longfellow Dr",
    "sg:city":"Beaumont",
    "sg:classifiers":[
        {
            "category":"Professional",
            "subcategory":"Engineering",
            "type":"Services"
        }
    ],
    "sg:phone":"+1 409 892 2828",
    "sg:postcode":"77706",
    "sg:province":"TX",
    "sg:tags":[
        "good"
    ],
    "wof:name":"A B D Enterprises Inc",
    "wof:placetype":"venue"
},
  "geometry": {"coordinates":[-94.137325,30.096375],"type":"Point"}
}