{
  "type": "Feature",
  "properties": {
    "iso:country":"US",
    "sg:address":"1591 Staree Ln",
    "sg:city":"Fort Worth",
    "sg:classifiers":[
        {
            "category":"Wholesale",
            "subcategory":"Durable Goods & Equipment",
            "type":"Manufacturing & Wholesale Goods"
        }
    ],
    "sg:phone":"+1 817 237 7230",
    "sg:postcode":"76179",
    "sg:province":"TX",
    "wof:name":"Texas Gaming Supply",
    "wof:placetype":"venue"
},
  "geometry": {"coordinates":[-97.392303,32.864058],"type":"Point"}
}