{
  "type": "Feature",
  "properties": {
    "iso:country":"US",
    "sg:address":"1901 W Trimmier Rd",
    "sg:city":"Killeen",
    "sg:classifiers":[
        {
            "category":"Professional",
            "subcategory":"Art Services",
            "type":"Services"
        }
    ],
    "sg:phone":"+1 254 526 5776",
    "sg:postcode":"76541",
    "sg:province":"TX",
    "sg:tags":[
        "artist"
    ],
    "wof:name":"Jones Tanna Lee Artist",
    "wof:placetype":"venue"
},
  "geometry": {"coordinates":[-97.73060099999999,31.099785],"type":"Point"}
}