{
  "type": "Feature",
  "properties": {
    "iso:country":"US",
    "sg:address":"8401 Gateway Blvd W",
    "sg:city":"El Paso",
    "sg:classifiers":[
        {
            "category":"Shopping",
            "subcategory":"Jewelry",
            "type":"Retail Goods"
        }
    ],
    "sg:phone":"+1 915 772 2527",
    "sg:postcode":"79935",
    "sg:province":"TX",
    "sg:tags":[
        "jeweler"
    ],
    "wof:name":"Helzberg Diamonds 146",
    "wof:placetype":"venue"
},
  "geometry": {"coordinates":[-106.382199,31.774207],"type":"Point"}
}