{
  "type": "Feature",
  "properties": {
    "iso:country":"US",
    "sg:address":"909 Doddridge St",
    "sg:city":"Corpus Christi",
    "sg:classifiers":[
        {
            "category":"Building & Trades",
            "subcategory":"Landscaping Services",
            "type":"Services"
        }
    ],
    "sg:phone":"+1 361 854 5750",
    "sg:postcode":"78411",
    "sg:province":"TX",
    "wof:name":"A & R Lawn Maintenance",
    "wof:placetype":"venue"
},
  "geometry": {"coordinates":[-97.384378,27.742578],"type":"Point"}
}