{
  "type": "Feature",
  "properties": {
    "iso:country":"US",
    "sg:address":"11807 Westheimer Rd",
    "sg:city":"Houston",
    "sg:classifiers":[
        {
            "category":"Professional",
            "subcategory":"Advertising",
            "type":"Services"
        }
    ],
    "sg:phone":"+1 281 752 8252",
    "sg:postcode":"77077",
    "sg:province":"TX",
    "sg:tags":[
        "mail",
        "direct"
    ],
    "wof:name":"Postal Connections of America",
    "wof:placetype":"venue"
},
  "geometry": {"coordinates":[-95.58668,29.736348],"type":"Point"}
}