{
  "type": "Feature",
  "properties": {
    "iso:country":"US",
    "sg:address":"11127 Shady Trl",
    "sg:city":"Dallas",
    "sg:classifiers":[
        {
            "category":"Building & Trades",
            "subcategory":"Cleaning & Sanitation",
            "type":"Services"
        }
    ],
    "sg:phone":"+1 972 620 7338",
    "sg:postcode":"75229",
    "sg:province":"TX",
    "sg:tags":[
        "janitorial"
    ],
    "wof:name":"Gylan Building Services Inc",
    "wof:placetype":"venue"
},
  "geometry": {"coordinates":[-96.89052100000001,32.88449],"type":"Point"}
}