{
  "type": "Feature",
  "properties": {
    "iso:country":"US",
    "sg:address":"4245 Kemp Blvd",
    "sg:city":"Wichita Falls",
    "sg:classifiers":[
        {
            "category":"Mining & Drilling",
            "type":"Manufacturing & Wholesale Goods"
        }
    ],
    "sg:phone":"+1 940 692 6626",
    "sg:postcode":"76308",
    "sg:province":"TX",
    "sg:tags":[
        "operator",
        "oil",
        "gas",
        "producer"
    ],
    "wof:name":"Medders Oil Company",
    "wof:placetype":"venue"
},
  "geometry": {"coordinates":[-98.535905,33.869751],"type":"Point"}
}