{
  "type": "Feature",
  "properties": {
    "iso:country":"US",
    "sg:address":"12579 Richmond Ave",
    "sg:city":"Houston",
    "sg:classifiers":[
        {
            "category":"Personal",
            "subcategory":"Nail Salon",
            "type":"Services"
        }
    ],
    "sg:phone":"+1 281 497 7889",
    "sg:postcode":"77082",
    "sg:province":"TX",
    "wof:name":"Elegant Nails & Facial",
    "wof:placetype":"venue"
},
  "geometry": {"coordinates":[-95.606728,29.729691],"type":"Point"}
}