{
  "type": "Feature",
  "properties": {
    "iso:country":"US",
    "sg:address":"675 S M L King Jr Pkwy",
    "sg:city":"Beaumont",
    "sg:classifiers":[
        {
            "category":"Retail",
            "subcategory":"Repair Shop",
            "type":"Services"
        }
    ],
    "sg:phone":"+1 409 832 7409",
    "sg:postcode":"77701",
    "sg:province":"TX",
    "sg:tags":[
        "refrigerator",
        "freezer"
    ],
    "wof:name":"Johnstone Supply",
    "wof:placetype":"venue"
},
  "geometry": {"coordinates":[-94.104095,30.077105],"type":"Point"}
}