{
  "type": "Feature",
  "properties": {
    "iso:country":"US",
    "sg:address":"4800 Columbia Ave",
    "sg:city":"Dallas",
    "sg:classifiers":[
        {
            "category":"Shopping",
            "subcategory":"Mobile Phones",
            "type":"Retail Goods"
        }
    ],
    "sg:phone":"+1 214 370 3477",
    "sg:postcode":"75226",
    "sg:province":"TX",
    "wof:name":"Communicaciones Latinas",
    "wof:placetype":"venue"
},
  "geometry": {"coordinates":[-96.76448600000001,32.794144],"type":"Point"}
}