{
  "type": "Feature",
  "properties": {
    "iso:country":"US",
    "sg:address":"2501 Oak Lawn Ave",
    "sg:city":"Dallas",
    "sg:classifiers":[
        {
            "category":"Professional",
            "subcategory":"Business Services",
            "type":"Services"
        }
    ],
    "sg:phone":"+1 214 521 2080",
    "sg:postcode":"75219",
    "sg:province":"TX",
    "sg:tags":[
        "arbitration"
    ],
    "wof:name":"Victoria F Welcome Attorney",
    "wof:placetype":"venue"
},
  "geometry": {"coordinates":[-96.814181,32.804311],"type":"Point"}
}