{
  "type": "Feature",
  "properties": {
    "iso:country":"US",
    "sg:address":"701 E Bedford St",
    "sg:city":"Dimmitt",
    "sg:classifiers":[
        {
            "category":"Organizations",
            "subcategory":"Religious Organization",
            "type":"Services"
        }
    ],
    "sg:phone":"+1 806 647 4263",
    "sg:postcode":"79027",
    "sg:province":"TX",
    "sg:tags":[
        "place",
        "worship",
        "church"
    ],
    "wof:name":"Rose Of Sharon Temple",
    "wof:placetype":"venue"
},
  "geometry": {"coordinates":[-102.304337,34.55077],"type":"Point"}
}