{
  "type": "Feature",
  "properties": {
    "iso:country":"US",
    "sg:address":"4727 Winnetka St",
    "sg:city":"Houston",
    "sg:classifiers":[
        {
            "category":"Professional",
            "type":"Services"
        }
    ],
    "sg:phone":"+1 713 747 9835",
    "sg:postcode":"77021",
    "sg:province":"TX",
    "wof:name":"Tirzah",
    "wof:placetype":"venue"
},
  "geometry": {"coordinates":[-95.340433,29.706193],"type":"Point"}
}