{
  "type": "Feature",
  "properties": {
    "iso:country":"US",
    "sg:address":"2802 Bee Caves Rd",
    "sg:city":"Austin",
    "sg:classifiers":[
        {
            "category":"Restaurant",
            "type":"Food & Drink"
        }
    ],
    "sg:phone":"+1 512 459 2222",
    "sg:postcode":"78746",
    "sg:province":"TX",
    "wof:name":"Mr Gatti's Pizza",
    "wof:placetype":"venue"
},
  "geometry": {"coordinates":[-97.791104,30.270778],"type":"Point"}
}