{
  "type": "Feature",
  "properties": {
    "iso:country":"US",
    "sg:address":"605 Plantation Dr",
    "sg:city":"Angleton",
    "sg:classifiers":[
        {
            "category":"Restaurant",
            "type":"Food & Drink"
        }
    ],
    "sg:phone":"+1 979 848 9812",
    "sg:postcode":"77515",
    "sg:province":"TX",
    "sg:tags":[
        "eating"
    ],
    "wof:name":"Papa Johns",
    "wof:placetype":"venue"
},
  "geometry": {"coordinates":[-95.42613900000001,29.185175],"type":"Point"}
}