{
  "type": "Feature",
  "properties": {
    "iso:country":"US",
    "sg:address":"9513 Burnet Road",
    "sg:city":"Austin",
    "sg:classifiers":[
        {
            "category":"Wholesale",
            "subcategory":"Computers",
            "type":"Manufacturing & Wholesale Goods"
        },
        {
            "category":"Professional",
            "subcategory":"Computer Services",
            "type":"Services"
        }
    ],
    "sg:phone":"+1 512 719 4263",
    "sg:postcode":"78758",
    "sg:province":"TX",
    "sg:tags":[
        "repair"
    ],
    "sg:website":"www.startechpc.com",
    "wof:name":"Startechpccom",
    "wof:placetype":"venue"
},
  "geometry": {"coordinates":[-97.725067,30.379112],"type":"Point"}
}