{
  "type": "Feature",
  "properties": {
    "iso:country":"US",
    "sg:address":"707 Lehman St",
    "sg:city":"Houston",
    "sg:classifiers":[
        {
            "category":"Mining & Drilling",
            "type":"Manufacturing & Wholesale Goods"
        },
        {
            "category":"Utilities",
            "subcategory":"Water",
            "type":"Services"
        }
    ],
    "sg:phone":"+1 713 742 9404",
    "sg:postcode":"77018",
    "sg:province":"TX",
    "sg:tags":[
        "boring",
        "pump",
        "well",
        "contractor"
    ],
    "wof:name":"Well Flow Drilling Services",
    "wof:placetype":"venue"
},
  "geometry": {"coordinates":[-95.410876,29.8388],"type":"Point"}
}