{
  "type": "Feature",
  "properties": {
    "iso:country":"US",
    "sg:address":"6501 Boeing Dr",
    "sg:city":"El Paso",
    "sg:classifiers":[
        {
            "category":"Social Services",
            "type":"Services"
        }
    ],
    "sg:phone":"+1 915 772 0674",
    "sg:postcode":"79925",
    "sg:province":"TX",
    "sg:tags":[
        "organization",
        "welfare"
    ],
    "wof:name":"LEAP",
    "wof:placetype":"venue"
},
  "geometry": {"coordinates":[-106.39918400000001,31.791777],"type":"Point"}
}