{
  "type": "Feature",
  "properties": {
    "iso:country":"US",
    "sg:address":"4119 Co Rd 3159",
    "sg:city":"Mount Enterprise",
    "sg:classifiers":[
        {
            "category":"Shopping",
            "subcategory":"Catalog Store",
            "type":"Retail Goods"
        }
    ],
    "sg:phone":"+1 903 863 5630",
    "sg:postcode":"75681",
    "sg:province":"TX",
    "sg:tags":[
        "mail",
        "house"
    ],
    "wof:name":"Hoover House",
    "wof:placetype":"venue"
},
  "geometry": {"coordinates":[-94.749583,31.961086],"type":"Point"}
}