{
  "type": "Feature",
  "properties": {
    "iso:country":"US",
    "sg:address":"16633 Dallas Pkwy",
    "sg:city":"Addison",
    "sg:classifiers":[
        {
            "category":"Professional",
            "subcategory":"Lawyer & Legal Services",
            "type":"Services"
        }
    ],
    "sg:phone":"+1 972 588 3343",
    "sg:postcode":"75001",
    "sg:province":"TX",
    "wof:name":"Law Offices of Derer Gary J",
    "wof:placetype":"venue"
},
  "geometry": {"coordinates":[-96.82857799999999,32.97928],"type":"Point"}
}