{
  "type": "Feature",
  "properties": {
    "iso:country":"US",
    "sg:address":"100 Corsicana Hwy",
    "sg:city":"Hillsboro",
    "sg:classifiers":[
        {
            "category":"Travel",
            "subcategory":"Hotels & Motels",
            "type":"Entertainment"
        }
    ],
    "sg:phone":"+1 254 582 5546",
    "sg:postcode":"76645",
    "sg:province":"TX",
    "wof:name":"81 Motel",
    "wof:placetype":"venue"
},
  "geometry": {"coordinates":[-97.12855999999999,32.004224],"type":"Point"}
}