{
  "type": "Feature",
  "properties": {
    "iso:country":"US",
    "sg:address":"8529 Ferndale Rd",
    "sg:city":"Dallas",
    "sg:classifiers":[
        {
            "category":"Professional",
            "subcategory":"Accounting & Tax Preparation",
            "type":"Services"
        }
    ],
    "sg:phone":"+1 214 340 1234",
    "sg:postcode":"75238",
    "sg:province":"TX",
    "sg:tags":[
        "billing"
    ],
    "wof:name":"Medsolutions",
    "wof:placetype":"venue"
},
  "geometry": {"coordinates":[-96.710819,32.865644],"type":"Point"}
}