{
  "type": "Feature",
  "properties": {
    "iso:country":"US",
    "sg:address":"902 Penny Wayne",
    "sg:city":"Friendswood",
    "sg:classifiers":[
        {
            "category":"Real Estate",
            "subcategory":"Real Estate Agent",
            "type":"Services"
        }
    ],
    "sg:phone":"+1 281 992 7174",
    "sg:postcode":"77546",
    "sg:province":"TX",
    "wof:name":"Fire Dog Realty",
    "wof:placetype":"venue"
},
  "geometry": {"coordinates":[-95.22365600000001,29.527958],"type":"Point"}
}