{
  "type": "Feature",
  "properties": {
    "iso:country":"US",
    "sg:address":"538 Bondstone Dr",
    "sg:city":"Dallas",
    "sg:classifiers":[
        {
            "category":"Professional",
            "subcategory":"Art Services",
            "type":"Services"
        }
    ],
    "sg:phone":"+1 214 503 0979",
    "sg:postcode":"75218",
    "sg:province":"TX",
    "sg:tags":[
        "commercial",
        "design"
    ],
    "wof:name":"Icono Creative LLC",
    "wof:placetype":"venue"
},
  "geometry": {"coordinates":[-96.70628000000001,32.854467],"type":"Point"}
}