{
  "type": "Feature",
  "properties": {
    "iso:country":"US",
    "sg:address":"702 Colorado Street",
    "sg:city":"Austin",
    "sg:classifiers":[
        {
            "category":"Education",
            "subcategory":"University",
            "type":"Public Place"
        }
    ],
    "sg:phone":"+1 512 472 4034",
    "sg:postcode":"78701",
    "sg:province":"TX",
    "sg:tags":[
        "college"
    ],
    "wof:name":"Gudalupe Valley Ventures",
    "wof:placetype":"venue"
},
  "geometry": {"coordinates":[-97.743803,30.269377],"type":"Point"}
}