{
  "type": "Feature",
  "properties": {
    "iso:country":"US",
    "sg:address":"2923 Pershing Dr",
    "sg:city":"El Paso",
    "sg:classifiers":[
        {
            "category":"Restaurant",
            "type":"Food & Drink"
        }
    ],
    "sg:phone":"+1 915 565 4041",
    "sg:postcode":"79903",
    "sg:province":"TX",
    "sg:tags":[
        "drinking",
        "eating"
    ],
    "wof:name":"Italian Kitchen",
    "wof:placetype":"venue"
},
  "geometry": {"coordinates":[-106.461308,31.784907],"type":"Point"}
}