{
  "type": "Feature",
  "properties": {
    "iso:country":"US",
    "sg:address":"9717 Summerwood Cir",
    "sg:city":"Dallas",
    "sg:classifiers":[
        {
            "category":"Shopping",
            "type":"Retail Goods"
        }
    ],
    "sg:phone":"+1 214 340 7076",
    "sg:postcode":"75243",
    "sg:province":"TX",
    "sg:tags":[
        "merchandise"
    ],
    "wof:name":"Clarole International Rel",
    "wof:placetype":"venue"
},
  "geometry": {"coordinates":[-96.71867899999999,32.904456],"type":"Point"}
}