{
  "type": "Feature",
  "properties": {
    "iso:country":"US",
    "sg:address":"3820 Richland Rd",
    "sg:city":"Flower Mound",
    "sg:classifiers":[
        {
            "category":"Wholesale",
            "subcategory":"Construction Materials",
            "type":"Manufacturing & Wholesale Goods"
        }
    ],
    "sg:phone":"+1 972 724 1252",
    "sg:postcode":"75022",
    "sg:province":"TX",
    "wof:name":"Alcoa",
    "wof:placetype":"venue"
},
  "geometry": {"coordinates":[-97.090069,33.022282],"type":"Point"}
}