{
  "type": "Feature",
  "properties": {
    "iso:country":"US",
    "sg:address":"305 E Pheasant Dr",
    "sg:city":"Austin",
    "sg:classifiers":[
        {
            "category":"Transit Center",
            "subcategory":"Freight",
            "type":"Transportation"
        },
        {
            "category":"Professional",
            "subcategory":"Business Services",
            "type":"Services"
        }
    ],
    "sg:phone":"+1 512 845 0228",
    "sg:postcode":"78753",
    "sg:province":"TX",
    "sg:tags":[
        "broker",
        "shipping"
    ],
    "wof:name":"Yoel Suarez & Alexander Fourni",
    "wof:placetype":"venue"
},
  "geometry": {"coordinates":[-97.689123,30.364236],"type":"Point"}
}