{
  "type": "Feature",
  "properties": {
    "iso:country":"US",
    "sg:address":"3330 N Galloway Ave Suite 270",
    "sg:city":"Mesquite",
    "sg:classifiers":[
        {
            "category":"Insurance",
            "subcategory":"Insurance Agent",
            "type":"Services"
        },
        {
            "category":"Insurance",
            "subcategory":"Hazard Insurance",
            "type":"Services"
        }
    ],
    "sg:phone":"+1 972 682 6494",
    "sg:postcode":"75150",
    "sg:province":"TX",
    "sg:tags":[
        "auto",
        "recreational",
        "motorcycle",
        "vehicle",
        "marine",
        "boat"
    ],
    "wof:name":"ABC INSURANCE",
    "wof:placetype":"venue"
},
  "geometry": {"coordinates":[-96.611107,32.81064],"type":"Point"}
}