{
  "type": "Feature",
  "properties": {
    "iso:country":"US",
    "sg:address":"5300 Glenmont Dr",
    "sg:city":"Houston",
    "sg:classifiers":[
        {
            "category":"Autos & Motor Vehicles",
            "subcategory":"Auto Supplies",
            "type":"Retail Goods"
        }
    ],
    "sg:phone":"+1 713 974 1362",
    "sg:postcode":"77081",
    "sg:province":"TX",
    "sg:tags":[
        "part",
        "trailer",
        "hitch"
    ],
    "wof:name":"Master Hitch",
    "wof:placetype":"venue"
},
  "geometry": {"coordinates":[-95.472702,29.720301],"type":"Point"}
}