{
  "type": "Feature",
  "properties": {
    "iso:country":"US",
    "sg:address":"2807 Justin Rd",
    "sg:city":"Flower Mound",
    "sg:classifiers":[
        {
            "category":"Building & Trades",
            "subcategory":"Construction",
            "type":"Services"
        }
    ],
    "sg:phone":"+1 940 498 7888",
    "sg:postcode":"75028",
    "sg:province":"TX",
    "sg:tags":[
        "designer",
        "dealer",
        "pool",
        "swimming"
    ],
    "wof:name":"Lakeview Custom Pools",
    "wof:placetype":"venue"
},
  "geometry": {"coordinates":[-97.072658,33.073715],"type":"Point"}
}