{
  "type": "Feature",
  "properties": {
    "iso:country":"US",
    "sg:address":"1900 N Galloway Ave",
    "sg:city":"Mesquite",
    "sg:classifiers":[
        {
            "category":"Restaurant",
            "type":"Food & Drink"
        }
    ],
    "sg:phone":"+1 972 288 5033",
    "sg:postcode":"75149",
    "sg:province":"TX",
    "wof:name":"Sonic-Drive In",
    "wof:placetype":"venue"
},
  "geometry": {"coordinates":[-96.60880299999999,32.789398],"type":"Point"}
}