{
  "type": "Feature",
  "properties": {
    "iso:country":"US",
    "sg:address":"301 N Lake Creek Dr",
    "sg:city":"Round Rock",
    "sg:classifiers":[
        {
            "category":"Social Services",
            "subcategory":"Child Care",
            "type":"Services"
        },
        {
            "category":"Education",
            "subcategory":"School",
            "type":"Public Place"
        }
    ],
    "sg:phone":"+1 512 255 4491",
    "sg:postcode":"78681",
    "sg:province":"TX",
    "sg:tags":[
        "day"
    ],
    "sg:website":"www.rrca-tx.org",
    "wof:name":"Round Rock Christian Academy",
    "wof:placetype":"venue"
},
  "geometry": {"coordinates":[-97.695156,30.511142],"type":"Point"}
}