{
  "type": "Feature",
  "properties": {
    "iso:country":"US",
    "sg:address":"4101 Holly Glen Dr",
    "sg:city":"Bay City",
    "sg:classifiers":[
        {
            "category":"Organizations",
            "subcategory":"Non-profit Organization",
            "type":"Services"
        }
    ],
    "sg:phone":"+1 979 245 6785",
    "sg:postcode":"77414",
    "sg:province":"TX",
    "sg:tags":[
        "social"
    ],
    "wof:name":"Assoc For Retarded Citize",
    "wof:placetype":"venue"
},
  "geometry": {"coordinates":[-95.940591,28.968681],"type":"Point"}
}