{
  "type": "Feature",
  "properties": {
    "iso:country":"US",
    "sg:address":"2205 North St",
    "sg:city":"Nacogdoches",
    "sg:classifiers":[
        {
            "category":"Manufacturing",
            "subcategory":"Printing",
            "type":"Manufacturing & Wholesale Goods"
        }
    ],
    "sg:phone":"+1 936 569 6093",
    "sg:postcode":"75965",
    "sg:province":"TX",
    "sg:tags":[
        "screen"
    ],
    "wof:name":"Fredonia Graphics",
    "wof:placetype":"venue"
},
  "geometry": {"coordinates":[-94.652393,31.624082],"type":"Point"}
}