{
  "type": "Feature",
  "properties": {
    "iso:country":"US",
    "sg:address":"11102 Cherry Park Dr",
    "sg:city":"San Antonio",
    "sg:classifiers":[
        {
            "category":"Social Services",
            "subcategory":"Child Care",
            "type":"Services"
        }
    ],
    "sg:phone":"+1 210 697 0818",
    "sg:postcode":"78249",
    "sg:province":"TX",
    "sg:tags":[
        "day"
    ],
    "wof:name":"Marthas Daycare",
    "wof:placetype":"venue"
},
  "geometry": {"coordinates":[-98.641032,29.551221],"type":"Point"}
}