{
  "type": "Feature",
  "properties": {
    "iso:country":"US",
    "sg:address":"7630 N Hwy 146",
    "sg:city":"Baytown",
    "sg:classifiers":[
        {
            "category":"Retail",
            "subcategory":"Animal Services",
            "type":"Services"
        }
    ],
    "sg:phone":"+1 281 573 7387",
    "sg:postcode":"77520",
    "sg:province":"TX",
    "wof:name":"Pet Manor Inc",
    "wof:placetype":"venue"
},
  "geometry": {"coordinates":[-94.90151400000001,29.813445],"type":"Point"}
}