{
  "type": "Feature",
  "properties": {
    "iso:country":"US",
    "sg:address":"9213 Evening Primrose Path",
    "sg:city":"Austin",
    "sg:classifiers":[
        {
            "category":"Shopping",
            "subcategory":"Computers & Home Electronics",
            "type":"Retail Goods"
        }
    ],
    "sg:phone":"+1 512 249 5255",
    "sg:postcode":"78750",
    "sg:province":"TX",
    "sg:tags":[
        "equipment",
        "electronic",
        "supply"
    ],
    "wof:name":"BMI",
    "wof:placetype":"venue"
},
  "geometry": {"coordinates":[-97.79307,30.434906],"type":"Point"}
}