{
  "type": "Feature",
  "properties": {
    "iso:country":"US",
    "sg:address":"5902 Walpole Pl",
    "sg:city":"Amarillo",
    "sg:classifiers":[
        {
            "category":"Building & Trades",
            "subcategory":"Landscaping Services",
            "type":"Services"
        }
    ],
    "sg:phone":"+1 806 352 7116",
    "sg:postcode":"79109",
    "sg:province":"TX",
    "sg:tags":[
        "lawn",
        "maintenance",
        "grounds"
    ],
    "wof:name":"Allied Tree & Landscape",
    "wof:placetype":"venue"
},
  "geometry": {"coordinates":[-101.909195,35.147528],"type":"Point"}
}