{
  "type": "Feature",
  "properties": {
    "iso:country":"US",
    "sg:address":"5366 Acton Hwy",
    "sg:city":"Granbury",
    "sg:classifiers":[
        {
            "category":"Personal",
            "subcategory":"Beauty Salon",
            "type":"Services"
        }
    ],
    "sg:phone":"+1 817 326 3067",
    "sg:postcode":"76049",
    "sg:province":"TX",
    "sg:tags":[
        "shop"
    ],
    "wof:name":"A Nu You Salon",
    "wof:placetype":"venue"
},
  "geometry": {"coordinates":[-97.69444300000001,32.447027],"type":"Point"}
}