{
  "type": "Feature",
  "properties": {
    "iso:country":"US",
    "sg:address":"714 Central Ave",
    "sg:city":"Forney",
    "sg:classifiers":[
        {
            "category":"Professional",
            "subcategory":"Accounting & Tax Preparation",
            "type":"Services"
        }
    ],
    "sg:phone":"+1 972 564 1039",
    "sg:postcode":"75126",
    "sg:province":"TX",
    "wof:name":"Linda Atchison Medical Billing",
    "wof:placetype":"venue"
},
  "geometry": {"coordinates":[-96.459074,32.747204],"type":"Point"}
}