{
  "type": "Feature",
  "properties": {
    "iso:country":"US",
    "sg:address":"29602 Nichols Sawmill Rd",
    "sg:city":"Magnolia",
    "sg:classifiers":[
        {
            "category":"Shopping",
            "subcategory":"Bicycles & Sporting Goods",
            "type":"Retail Goods"
        }
    ],
    "sg:phone":"+1 713 896 4867",
    "sg:postcode":"77355",
    "sg:province":"TX",
    "sg:tags":[
        "gun",
        "gunsmith"
    ],
    "sg:website":"www.andysarmshouse.com",
    "wof:name":"Andy's Arms House",
    "wof:placetype":"venue"
},
  "geometry": {"coordinates":[-95.752835,30.175887],"type":"Point"}
}