{
  "type": "Feature",
  "properties": {
    "iso:country":"US",
    "sg:address":"600 Scenic Dr",
    "sg:city":"Baytown",
    "sg:classifiers":[
        {
            "category":"Real Estate",
            "subcategory":"Architect",
            "type":"Services"
        }
    ],
    "sg:phone":"+1 281 420 3408",
    "sg:postcode":"77521",
    "sg:province":"TX",
    "sg:tags":[
        "architectural"
    ],
    "wof:name":"William T Burge",
    "wof:placetype":"venue"
},
  "geometry": {"coordinates":[-94.97337899999999,29.757426],"type":"Point"}
}