{
  "type": "Feature",
  "properties": {
    "iso:country":"US",
    "sg:address":"6601 Wesley St",
    "sg:city":"Greenville",
    "sg:classifiers":[
        {
            "category":"Banks & Credit Unions",
            "subcategory":"Bank",
            "type":"Services"
        }
    ],
    "sg:phone":"+1 903 455 2835",
    "sg:postcode":"75402",
    "sg:province":"TX",
    "sg:tags":[
        "bus"
    ],
    "wof:name":"Federal Land Bank Association",
    "wof:placetype":"venue"
},
  "geometry": {"coordinates":[-96.109567,33.103074],"type":"Point"}
}