{
  "type": "Feature",
  "properties": {
    "iso:country":"US",
    "sg:address":"18065 Upper Bay Rd",
    "sg:city":"Houston",
    "sg:classifiers":[
        {
            "category":"Building & Trades",
            "subcategory":"Construction",
            "type":"Services"
        }
    ],
    "sg:phone":"+1 281 333 1010",
    "sg:postcode":"77058",
    "sg:province":"TX",
    "sg:tags":[
        "siding",
        "contractor"
    ],
    "wof:name":"Affordable Siding & Const",
    "wof:placetype":"venue"
},
  "geometry": {"coordinates":[-95.089738,29.550305],"type":"Point"}
}