{
  "type": "Feature",
  "properties": {
    "iso:country":"US",
    "sg:address":"11404 Shiloh Rd Ste 106",
    "sg:city":"Dallas",
    "sg:classifiers":[
        {
            "category":"Donuts",
            "subcategory":"None",
            "type":"Food & Drink"
        }
    ],
    "sg:phone":"+1 972 686 0468",
    "sg:postcode":"75228",
    "sg:province":"TX",
    "wof:name":"Good Donuts",
    "wof:placetype":"venue"
},
  "geometry": {"coordinates":[-96.66570299999999,32.849899],"type":"Point"}
}