{
  "type": "Feature",
  "properties": {
    "iso:country":"US",
    "sg:address":"17066 State Hwy 3",
    "sg:city":"Webster",
    "sg:classifiers":[
        {
            "category":"Retail",
            "subcategory":"Portrait Studio",
            "type":"Services"
        },
        {
            "category":"Professional",
            "subcategory":"Art Services",
            "type":"Services"
        }
    ],
    "sg:phone":"+1 281 332 5559",
    "sg:postcode":"77598",
    "sg:province":"TX",
    "sg:tags":[
        "photographer",
        "photo"
    ],
    "wof:name":"Mike S Calf Photography",
    "wof:placetype":"venue"
},
  "geometry": {"coordinates":[-95.126126,29.546096],"type":"Point"}
}