{
  "type": "Feature",
  "properties": {
    "iso:country":"US",
    "sg:address":"2515 Irving Blvd",
    "sg:city":"Dallas",
    "sg:classifiers":[
        {
            "category":"Autos & Motor Vehicles",
            "subcategory":"Automobile Sales",
            "type":"Retail Goods"
        }
    ],
    "sg:phone":"+1 214 630 5085",
    "sg:postcode":"75247",
    "sg:province":"TX",
    "sg:tags":[
        "used"
    ],
    "wof:name":"Mirage Auto Sales",
    "wof:placetype":"venue"
},
  "geometry": {"coordinates":[-96.842629,32.801306],"type":"Point"}
}