{
  "type": "Feature",
  "properties": {
    "iso:country":"US",
    "sg:address":"5558 Buffalo Gap Rd",
    "sg:city":"Abilene",
    "sg:classifiers":[
        {
            "category":"Travel",
            "subcategory":"Hotels & Motels",
            "type":"Entertainment"
        }
    ],
    "sg:phone":"+1 325 572 4381",
    "sg:postcode":"79606",
    "sg:province":"TX",
    "sg:tags":[
        "breakfast",
        "accommodation",
        "bed"
    ],
    "sg:website":"www.harvesthomebb.com",
    "wof:name":"Harvest Home Bed & Breakfast",
    "wof:placetype":"venue"
},
  "geometry": {"coordinates":[-99.769975,32.382063],"type":"Point"}
}