{
  "type": "Feature",
  "properties": {
    "iso:country":"US",
    "sg:address":"19707 Encino Knoll St",
    "sg:city":"San Antonio",
    "sg:classifiers":[
        {
            "category":"Professional",
            "subcategory":"Business Services",
            "type":"Services"
        }
    ],
    "sg:phone":"+1 210 497 7966",
    "sg:postcode":"78259",
    "sg:province":"TX",
    "sg:tags":[
        "transcribing",
        "disc"
    ],
    "wof:name":"Angel Secretarial Svc",
    "wof:placetype":"venue"
},
  "geometry": {"coordinates":[-98.454036,29.626201],"type":"Point"}
}