{
  "type": "Feature",
  "properties": {
    "iso:country":"US",
    "sg:address":"1822 Barker Cypress Rd",
    "sg:city":"Houston",
    "sg:classifiers":[
        {
            "category":"Real Estate",
            "subcategory":"Real Estate Agent",
            "type":"Services"
        }
    ],
    "sg:phone":"+1 281 578 8973",
    "sg:postcode":"77084",
    "sg:province":"TX",
    "wof:name":"Enclave At Cypress Park",
    "wof:placetype":"venue"
},
  "geometry": {"coordinates":[-95.688198,29.794239],"type":"Point"}
}