{
  "type": "Feature",
  "properties": {
    "iso:country":"US",
    "sg:address":"8506 Heraldry St",
    "sg:city":"San Antonio",
    "sg:classifiers":[
        {
            "category":"Building & Trades",
            "subcategory":"Electrical",
            "type":"Services"
        }
    ],
    "sg:phone":"+1 210 681 0872",
    "sg:postcode":"78254",
    "sg:province":"TX",
    "sg:tags":[
        "electrical",
        "contractor"
    ],
    "wof:name":"Blackmon Electric",
    "wof:placetype":"venue"
},
  "geometry": {"coordinates":[-98.653521,29.525906],"type":"Point"}
}