{
  "type": "Feature",
  "properties": {
    "iso:country":"US",
    "sg:address":"1220 E Main St",
    "sg:city":"League City",
    "sg:classifiers":[
        {
            "category":"Retail",
            "subcategory":"Auto Repair",
            "type":"Services"
        }
    ],
    "sg:phone":"+1 281 332 1668",
    "sg:postcode":"77573",
    "sg:province":"TX",
    "sg:tags":[
        "automotive",
        "general"
    ],
    "wof:name":"Expert Automotive Services",
    "wof:placetype":"venue"
},
  "geometry": {"coordinates":[-95.084683,29.515612],"type":"Point"}
}