{
  "type": "Feature",
  "properties": {
    "iso:country":"US",
    "sg:address":"503 Town North Dr",
    "sg:city":"Arlington",
    "sg:classifiers":[
        {
            "category":"Shopping",
            "subcategory":"Bicycles & Sporting Goods",
            "type":"Retail Goods"
        }
    ],
    "sg:phone":"+1 817 275 7905",
    "sg:postcode":"76011",
    "sg:province":"TX",
    "sg:tags":[
        "gun",
        "gunsmith"
    ],
    "wof:name":"Pellet Gun Repair",
    "wof:placetype":"venue"
},
  "geometry": {"coordinates":[-97.11400500000001,32.74658],"type":"Point"}
}