{
  "type": "Feature",
  "properties": {
    "iso:country":"US",
    "sg:address":"200 Brookhaven Dr",
    "sg:city":"Grand Prairie",
    "sg:classifiers":[
        {
            "category":"Wholesale",
            "subcategory":"Hardware",
            "type":"Manufacturing & Wholesale Goods"
        }
    ],
    "sg:phone":"+1 972 642 9722",
    "sg:postcode":"75052",
    "sg:province":"TX",
    "wof:name":"Best Bet Supply",
    "wof:placetype":"venue"
},
  "geometry": {"coordinates":[-97.00722500000001,32.660801],"type":"Point"}
}