{
  "type": "Feature",
  "properties": {
    "iso:country":"US",
    "sg:address":"1209 Nortman Dr",
    "sg:city":"Gainesville",
    "sg:classifiers":[
        {
            "category":"Professional",
            "subcategory":"Business Services",
            "type":"Services"
        }
    ],
    "sg:phone":"+1 940 668 7274",
    "sg:postcode":"76240",
    "sg:province":"TX",
    "wof:name":"Rocket Technologies Inc",
    "wof:placetype":"venue"
},
  "geometry": {"coordinates":[-97.211484,33.640975],"type":"Point"}
}