{
  "type": "Feature",
  "properties": {
    "iso:country":"US",
    "sg:address":"1408 Circle Ln",
    "sg:city":"Bedford",
    "sg:classifiers":[
        {
            "category":"Building & Trades",
            "subcategory":"Landscaping Services",
            "type":"Services"
        }
    ],
    "sg:phone":"+1 817 355 1013",
    "sg:postcode":"76022",
    "sg:province":"TX",
    "sg:tags":[
        "landscape",
        "contractor"
    ],
    "wof:name":"Landscape By Design",
    "wof:placetype":"venue"
},
  "geometry": {"coordinates":[-97.149073,32.834352],"type":"Point"}
}