{
  "type": "Feature",
  "properties": {
    "iso:country":"US",
    "sg:address":"4803 Charter Oak Dr",
    "sg:city":"Temple",
    "sg:classifiers":[
        {
            "category":"Professional",
            "type":"Services"
        }
    ],
    "sg:phone":"+1 254 933 9128",
    "sg:postcode":"76502",
    "sg:province":"TX",
    "wof:name":"A I W Relaxation Therapy",
    "wof:placetype":"venue"
},
  "geometry": {"coordinates":[-97.43169399999999,31.071863],"type":"Point"}
}