{
  "type": "Feature",
  "properties": {
    "iso:country":"US",
    "sg:address":"14621 Beechnut St",
    "sg:city":"Houston",
    "sg:classifiers":[
        {
            "category":"Health Services",
            "subcategory":"Optometrist",
            "type":"Services"
        }
    ],
    "sg:phone":"+1 281 498 1381",
    "sg:postcode":"77083",
    "sg:province":"TX",
    "sg:tags":[
        "optical",
        "good"
    ],
    "wof:name":"Vision Corner",
    "wof:placetype":"venue"
},
  "geometry": {"coordinates":[-95.64648800000001,29.689567],"type":"Point"}
}