{
  "type": "Feature",
  "properties": {
    "iso:country":"US",
    "sg:address":"717 S 12th St",
    "sg:city":"Mcallen",
    "sg:classifiers":[
        {
            "category":"Professional",
            "subcategory":"Secretarial Services",
            "type":"Services"
        }
    ],
    "sg:phone":"+1 956 630 0160",
    "sg:postcode":"78501",
    "sg:province":"TX",
    "sg:tags":[
        "transcription"
    ],
    "wof:name":"Hinojosa Betty",
    "wof:placetype":"venue"
},
  "geometry": {"coordinates":[-98.23338699999999,26.196506],"type":"Point"}
}