{
  "type": "Feature",
  "properties": {
    "iso:country":"US",
    "sg:address":"9183 Katy Fwy Ste 102",
    "sg:city":"Houston",
    "sg:classifiers":[
        {
            "category":"Health Services",
            "subcategory":"Doctor",
            "type":"Services"
        }
    ],
    "sg:phone":"+1 713 932 6456",
    "sg:postcode":"77024",
    "sg:province":"TX",
    "sg:tags":[
        "surgeon",
        "oral"
    ],
    "wof:name":"Couvillion Steven DDS",
    "wof:placetype":"venue"
},
  "geometry": {"coordinates":[-95.516899,29.783701],"type":"Point"}
}