{
  "type": "Feature",
  "properties": {
    "iso:country":"US",
    "sg:address":"7125 Meadow Lake Ave",
    "sg:city":"Dallas",
    "sg:classifiers":[
        {
            "category":"Building & Trades",
            "subcategory":"Construction",
            "type":"Services"
        }
    ],
    "sg:phone":"+1 214 321 5076",
    "sg:postcode":"75214",
    "sg:province":"TX",
    "sg:tags":[
        "house"
    ],
    "wof:name":"Dann Rust Inc",
    "wof:placetype":"venue"
},
  "geometry": {"coordinates":[-96.735557,32.825079],"type":"Point"}
}