{
  "type": "Feature",
  "properties": {
    "iso:country":"US",
    "sg:address":"3702 Beauregard Dr",
    "sg:city":"Corpus Christi",
    "sg:classifiers":[
        {
            "category":"Building & Trades",
            "subcategory":"Landscaping Services",
            "type":"Services"
        }
    ],
    "sg:phone":"+1 361 851 1851",
    "sg:postcode":"78415",
    "sg:province":"TX",
    "wof:name":"Skyline Tree Surgeons",
    "wof:placetype":"venue"
},
  "geometry": {"coordinates":[-97.40996699999999,27.714405],"type":"Point"}
}