{
  "type": "Feature",
  "properties": {
    "iso:country":"US",
    "sg:address":"2301 Midwestern Pkwy",
    "sg:city":"Wichita Falls",
    "sg:classifiers":[
        {
            "category":"Health Services",
            "subcategory":"Doctor",
            "type":"Services"
        }
    ],
    "sg:phone":"+1 940 692 0494",
    "sg:postcode":"76308",
    "sg:province":"TX",
    "sg:tags":[
        "physician",
        "surgeon"
    ],
    "wof:name":"Blair P Coleman MD",
    "wof:placetype":"venue"
},
  "geometry": {"coordinates":[-98.518523,33.87047],"type":"Point"}
}