{
  "type": "Feature",
  "properties": {
    "iso:country":"US",
    "sg:address":"35 FM 1621",
    "sg:city":"Comfort",
    "sg:classifiers":[
        {
            "category":"Sports & Exercise",
            "subcategory":"Gym",
            "type":"Entertainment"
        }
    ],
    "sg:phone":"+1 830 995 3901",
    "sg:postcode":"78013",
    "sg:province":"TX",
    "sg:tags":[
        "fitness",
        "physical",
        "facility"
    ],
    "wof:name":"Soothing Waters",
    "wof:placetype":"venue"
},
  "geometry": {"coordinates":[-98.876282,29.953937],"type":"Point"}
}