{
  "type": "Feature",
  "properties": {
    "iso:country":"US",
    "sg:address":"80 Old Spanish Trl",
    "sg:city":"Kyle",
    "sg:classifiers":[
        {
            "category":"Organizations",
            "subcategory":"Religious Organization",
            "type":"Services"
        }
    ],
    "sg:phone":"+1 512 398 7475",
    "sg:postcode":"78640",
    "sg:province":"TX",
    "sg:tags":[
        "church"
    ],
    "wof:name":"St Michael's Church",
    "wof:placetype":"venue"
},
  "geometry": {"coordinates":[-97.757064,29.959699],"type":"Point"}
}