{
  "type": "Feature",
  "properties": {
    "iso:country":"US",
    "sg:address":"516 New Laredo Hwy",
    "sg:city":"San Antonio",
    "sg:classifiers":[
        {
            "category":"Manufacturing",
            "subcategory":"Printing",
            "type":"Manufacturing & Wholesale Goods"
        }
    ],
    "sg:phone":"+1 210 923 8373",
    "sg:postcode":"78211",
    "sg:province":"TX",
    "sg:tags":[
        "printer"
    ],
    "wof:name":"Multicopy Printing Co Inc",
    "wof:placetype":"venue"
},
  "geometry": {"coordinates":[-98.54774999999999,29.366546],"type":"Point"}
}