{
  "type": "Feature",
  "properties": {
    "iso:country":"US",
    "sg:address":"1001 Mckinney St",
    "sg:city":"Houston",
    "sg:classifiers":[
        {
            "category":"Professional",
            "subcategory":"Management & Consulting",
            "type":"Services"
        }
    ],
    "sg:phone":"+1 713 383 0090",
    "sg:postcode":"77002",
    "sg:province":"TX",
    "sg:tags":[
        "counselor",
        "relation",
        "public"
    ],
    "sg:website":"http://www.legalpr.com",
    "wof:name":"Androvett Legal Media",
    "wof:placetype":"venue"
},
  "geometry": {"coordinates":[-95.364906,29.756929],"type":"Point"}
}