{
  "type": "Feature",
  "properties": {
    "iso:country":"US",
    "sg:address":"270 E 29th St Ste 100",
    "sg:city":"Bryan",
    "sg:classifiers":[
        {
            "category":"Health Services",
            "subcategory":"Doctor",
            "type":"Services"
        }
    ],
    "sg:phone":"+1 979 731 8888",
    "sg:postcode":"77803",
    "sg:province":"TX",
    "sg:tags":[
        "physician",
        "pediatrics-orthopedic",
        "surgeons",
        "orthopedics",
        "surgery",
        "surgeon"
    ],
    "wof:name":"Orthopedic Assoc Inc",
    "wof:placetype":"venue"
},
  "geometry": {"coordinates":[-96.371798,30.670664],"type":"Point"}
}