{
  "type": "Feature",
  "properties": {
    "iso:country":"US",
    "sg:address":"523 24th St",
    "sg:city":"Galveston",
    "sg:classifiers":[
        {
            "category":"Professional",
            "subcategory":"Advertising",
            "type":"Services"
        }
    ],
    "sg:phone":"+1 409 763 8680",
    "sg:postcode":"77550",
    "sg:province":"TX",
    "wof:name":"Galveston Coml Ht Reservation",
    "wof:placetype":"venue"
},
  "geometry": {"coordinates":[-94.794633,29.303998],"type":"Point"}
}