{
  "type": "Feature",
  "properties": {
    "iso:country":"US",
    "sg:address":"433 Kristen Ln",
    "sg:city":"Harper",
    "sg:classifiers":[
        {
            "category":"Professional",
            "subcategory":"Art Services",
            "type":"Services"
        }
    ],
    "sg:phone":"+1 830 864 5915",
    "sg:postcode":"78631",
    "sg:province":"TX",
    "sg:tags":[
        "taxidermist"
    ],
    "wof:name":"Jeff Jones Taxidermy",
    "wof:placetype":"venue"
},
  "geometry": {"coordinates":[-99.250536,30.265882],"type":"Point"}
}