{
  "type": "Feature",
  "properties": {
    "iso:country":"US",
    "sg:address":"511 Hemphill St",
    "sg:city":"Fort Worth",
    "sg:classifiers":[
        {
            "category":"Bars & Pubs",
            "type":"Food & Drink"
        }
    ],
    "sg:phone":"+1 817 332 2737",
    "sg:postcode":"76104",
    "sg:province":"TX",
    "wof:name":"Maw's Place",
    "wof:placetype":"venue"
},
  "geometry": {"coordinates":[-97.331694,32.73945],"type":"Point"}
}