{
  "type": "Feature",
  "properties": {
    "iso:country":"US",
    "sg:address":"1625 Crescent Cir Ste 115",
    "sg:city":"Carrollton",
    "sg:classifiers":[
        {
            "category":"Building & Trades",
            "subcategory":"Pest Control",
            "type":"Services"
        }
    ],
    "sg:phone":"+1 972 512 0270",
    "sg:postcode":"75006",
    "sg:province":"TX",
    "wof:name":"Breathe Easy Inc",
    "wof:placetype":"venue"
},
  "geometry": {"coordinates":[-96.917801,32.959999],"type":"Point"}
}