{
  "type": "Feature",
  "properties": {
    "iso:country":"US",
    "sg:address":"6205 W 34th St",
    "sg:city":"Houston",
    "sg:classifiers":[
        {
            "category":"Building & Trades",
            "subcategory":"Electrical",
            "type":"Services"
        }
    ],
    "sg:phone":"+1 713 681 4444",
    "sg:postcode":"77092",
    "sg:province":"TX",
    "sg:tags":[
        "specialist",
        "cabling",
        "datum",
        "general",
        "electrical",
        "contractor"
    ],
    "wof:name":"McBride Electric Inc",
    "wof:placetype":"venue"
},
  "geometry": {"coordinates":[-95.479617,29.819154],"type":"Point"}
}