{
  "type": "Feature",
  "properties": {
    "iso:country":"US",
    "sg:address":"12019 Naughton St",
    "sg:city":"Houston",
    "sg:classifiers":[
        {
            "category":"Shopping",
            "subcategory":"Computers & Home Electronics",
            "type":"Retail Goods"
        }
    ],
    "sg:phone":"+1 713 661 2920",
    "sg:postcode":"77024",
    "sg:province":"TX",
    "sg:tags":[
        "software"
    ],
    "wof:name":"I D Systems Inc",
    "wof:placetype":"venue"
},
  "geometry": {"coordinates":[-95.540183,29.754915],"type":"Point"}
}