{
  "type": "Feature",
  "properties": {
    "iso:country":"US",
    "sg:address":"1007 S Congress Ave",
    "sg:city":"Austin",
    "sg:classifiers":[
        {
            "category":"Coffee & Tea",
            "type":"Food & Drink"
        }
    ],
    "sg:menulink":"http://www.allmenus.com/tx/austin/112712-starbucks-coffee/menu/",
    "sg:phone":"+1 512 447 9770",
    "sg:postcode":"78704",
    "sg:province":"TX",
    "sg:tags":[
        "american"
    ],
    "wof:name":"Starbucks Coffee",
    "wof:placetype":"venue"
},
  "geometry": {"coordinates":[-97.747534,30.254448],"type":"Point"}
}