{
  "type": "Feature",
  "properties": {
    "iso:country":"US",
    "sg:address":"2107 E Main St",
    "sg:city":"Gatesville",
    "sg:classifiers":[
        {
            "category":"Shopping",
            "type":"Retail Goods"
        }
    ],
    "sg:phone":"+1 254 865 9149",
    "sg:postcode":"76528",
    "sg:province":"TX",
    "sg:tags":[
        "sporting",
        "merchandise"
    ],
    "wof:name":"Poco Cellular",
    "wof:placetype":"venue"
},
  "geometry": {"coordinates":[-97.734803,31.434934],"type":"Point"}
}