{
  "type": "Feature",
  "properties": {
    "iso:country":"US",
    "sg:address":"5935 Dacy Ln",
    "sg:city":"Buda",
    "sg:classifiers":[
        {
            "category":"Building & Trades",
            "subcategory":"Cleaning & Sanitation",
            "type":"Services"
        }
    ],
    "sg:phone":"+1 877 534 8822",
    "sg:postcode":"78610",
    "sg:province":"TX",
    "sg:tags":[
        "maintenance"
    ],
    "wof:name":"Uniclean Cleaning Service",
    "wof:placetype":"venue"
},
  "geometry": {"coordinates":[-97.82874200000001,30.05564],"type":"Point"}
}