{
  "type": "Feature",
  "properties": {
    "iso:country":"US",
    "sg:address":"18421 Shallow Pool Dr",
    "sg:city":"Pflugerville",
    "sg:classifiers":[
        {
            "category":"Building & Trades",
            "subcategory":"Construction",
            "type":"Services"
        }
    ],
    "sg:phone":"+1 512 444 7987",
    "sg:postcode":"78660",
    "sg:province":"TX",
    "sg:tags":[
        "handyman",
        "painting",
        "contractor"
    ],
    "sg:website":"http://www.youvegotitmadepainting.com",
    "wof:name":"You've Got it Made Painting & More",
    "wof:placetype":"venue"
},
  "geometry": {"coordinates":[-97.573334,30.45348],"type":"Point"}
}