{
  "type": "Feature",
  "properties": {
    "iso:country":"US",
    "sg:address":"5613 Edgemere Cir",
    "sg:city":"Garland",
    "sg:classifiers":[
        {
            "category":"Professional",
            "subcategory":"Business Services",
            "type":"Services"
        }
    ],
    "sg:phone":"+1 972 279 0101",
    "sg:postcode":"75043",
    "sg:province":"TX",
    "wof:name":"Virgin Couriers",
    "wof:placetype":"venue"
},
  "geometry": {"coordinates":[-96.61928899999999,32.847994],"type":"Point"}
}