{
  "type": "Feature",
  "properties": {
    "iso:country":"US",
    "sg:address":"4111 Jacksboro Hwy",
    "sg:city":"Wichita Falls",
    "sg:classifiers":[
        {
            "category":"Freight",
            "type":"Transportation"
        }
    ],
    "sg:phone":"+1 940 766 6833",
    "sg:postcode":"76302",
    "sg:province":"TX",
    "sg:tags":[
        "general"
    ],
    "wof:name":"Allsize Storages",
    "wof:placetype":"venue"
},
  "geometry": {"coordinates":[-98.49437399999999,33.872515],"type":"Point"}
}