{
  "type": "Feature",
  "properties": {
    "iso:country":"US",
    "sg:address":"341 W Mockingbird Ln",
    "sg:city":"Dallas",
    "sg:classifiers":[
        {
            "category":"Wholesale",
            "subcategory":"Groceries",
            "type":"Manufacturing & Wholesale Goods"
        }
    ],
    "sg:phone":"+1 214 951 9778",
    "sg:postcode":"75247",
    "sg:province":"TX",
    "wof:name":"Guatelinda Bakery",
    "wof:placetype":"venue"
},
  "geometry": {"coordinates":[-96.87365699999999,32.806652],"type":"Point"}
}