{
  "type": "Feature",
  "properties": {
    "iso:country":"US",
    "sg:address":"3402 Wiley Post Rd",
    "sg:city":"Carrollton",
    "sg:classifiers":[
        {
            "category":"Professional",
            "type":"Services"
        }
    ],
    "sg:phone":"+1 972 386 3210",
    "sg:postcode":"75006",
    "sg:province":"TX",
    "wof:name":"Bdn Creative",
    "wof:placetype":"venue"
},
  "geometry": {"coordinates":[-96.838894,32.960186],"type":"Point"}
}