{
  "type": "Feature",
  "properties": {
    "iso:country":"US",
    "sg:address":"417 W Ohio Ave",
    "sg:city":"Dallas",
    "sg:classifiers":[
        {
            "category":"Social Services",
            "subcategory":"Child Care",
            "type":"Services"
        }
    ],
    "sg:phone":"+1 214 941 6577",
    "sg:postcode":"75224",
    "sg:province":"TX",
    "sg:tags":[
        "day"
    ],
    "wof:name":"Ratcliff's Learning & Development Center",
    "wof:placetype":"venue"
},
  "geometry": {"coordinates":[-96.828632,32.719622],"type":"Point"}
}