{
  "type": "Feature",
  "properties": {
    "iso:country":"US",
    "sg:address":"637 S Ww White Rd",
    "sg:city":"San Antonio",
    "sg:classifiers":[
        {
            "category":"Manufacturing",
            "subcategory":"Wood Products",
            "type":"Manufacturing & Wholesale Goods"
        }
    ],
    "sg:phone":"+1 210 359 1500",
    "sg:postcode":"78220",
    "sg:province":"TX",
    "sg:tags":[
        "mfg"
    ],
    "wof:name":"Aztec Sawdust",
    "wof:placetype":"venue"
},
  "geometry": {"coordinates":[-98.405626,29.420686],"type":"Point"}
}