{
  "type": "Feature",
  "properties": {
    "iso:country":"US",
    "sg:address":"220 Duncan St",
    "sg:city":"Hillsboro",
    "sg:classifiers":[
        {
            "category":"Social Services",
            "subcategory":"Child Care",
            "type":"Services"
        }
    ],
    "sg:phone":"+1 254 582 0870",
    "sg:postcode":"76645",
    "sg:province":"TX",
    "sg:tags":[
        "day"
    ],
    "wof:name":"Firm Foundation Learning Cente",
    "wof:placetype":"venue"
},
  "geometry": {"coordinates":[-97.136898,32.009103],"type":"Point"}
}