{
  "type": "Feature",
  "properties": {
    "iso:country":"US",
    "sg:address":"2015 S Cherry Ln",
    "sg:city":"Fort Worth",
    "sg:classifiers":[
        {
            "category":"Restaurant",
            "type":"Food & Drink"
        }
    ],
    "sg:menulink":"http://www.allmenus.com/tx/fort-worth/95259-ihop/menu/",
    "sg:phone":"+1 817 246 5401",
    "sg:postcode":"76108",
    "sg:province":"TX",
    "sg:tags":[
        "sandwich",
        "salad",
        "burger",
        "soup",
        "american",
        "steakhouse",
        "wrap"
    ],
    "wof:name":"IHOP",
    "wof:placetype":"venue"
},
  "geometry": {"coordinates":[-97.451751,32.739636],"type":"Point"}
}