{
  "type": "Feature",
  "properties": {
    "iso:country":"US",
    "sg:address":"116 N Ave C",
    "sg:city":"Denver City",
    "sg:classifiers":[
        {
            "category":"Food & Beverages",
            "subcategory":"Candy",
            "type":"Retail Goods"
        }
    ],
    "sg:phone":"+1 806 592 3403",
    "sg:postcode":"79323",
    "sg:province":"TX",
    "sg:tags":[
        "confectionery"
    ],
    "wof:name":"CANDYBARCAKE.COM",
    "wof:placetype":"venue"
},
  "geometry": {"coordinates":[-102.83171400000001,32.965549],"type":"Point"}
}