{
  "type": "Feature",
  "properties": {
    "iso:country":"US",
    "sg:address":"2438 Stewart Dr",
    "sg:city":"Mesquite",
    "sg:classifiers":[
        {
            "category":"Building & Trades",
            "subcategory":"Construction",
            "type":"Services"
        }
    ],
    "sg:phone":"+1 972 271 3142",
    "sg:postcode":"75181",
    "sg:province":"TX",
    "sg:tags":[
        "contractor"
    ],
    "wof:name":"Garcia Fence Co",
    "wof:placetype":"venue"
},
  "geometry": {"coordinates":[-96.557495,32.745659],"type":"Point"}
}