{
  "type": "Feature",
  "properties": {
    "iso:country":"US",
    "sg:address":"11530 Garland Rd",
    "sg:city":"Dallas",
    "sg:classifiers":[
        {
            "category":"Building & Trades",
            "subcategory":"Construction",
            "type":"Services"
        }
    ],
    "sg:phone":"+1 972 984 1245",
    "sg:postcode":"75218",
    "sg:province":"TX",
    "sg:tags":[
        "insulation",
        "heat",
        "contractor"
    ],
    "wof:name":"Southern Insulation Co",
    "wof:placetype":"venue"
},
  "geometry": {"coordinates":[-96.68039,32.851647],"type":"Point"}
}