{
  "type": "Feature",
  "properties": {
    "iso:country":"US",
    "sg:address":"3102 Miller Park S",
    "sg:city":"Garland",
    "sg:classifiers":[
        {
            "category":"Wholesale",
            "subcategory":"Construction Materials",
            "type":"Manufacturing & Wholesale Goods"
        }
    ],
    "sg:phone":"+1 972 276 1700",
    "sg:postcode":"75042",
    "sg:province":"TX",
    "sg:tags":[
        "equipment",
        "caulking"
    ],
    "wof:name":"DAP Inc",
    "wof:placetype":"venue"
},
  "geometry": {"coordinates":[-96.675427,32.903797],"type":"Point"}
}