{
  "type": "Feature",
  "properties": {
    "iso:country":"US",
    "sg:address":"8314 Spaulding St",
    "sg:city":"Houston",
    "sg:classifiers":[
        {
            "category":"Shopping",
            "subcategory":"Clothing, Apparel, & Fashions",
            "type":"Retail Goods"
        }
    ],
    "sg:phone":"+1 713 633 6391",
    "sg:postcode":"77016",
    "sg:province":"TX",
    "wof:name":"Deblaw Dress Shop",
    "wof:placetype":"venue"
},
  "geometry": {"coordinates":[-95.30622200000001,29.836517],"type":"Point"}
}