{
  "type": "Feature",
  "properties": {
    "iso:country":"US",
    "sg:address":"906 W Loop 281",
    "sg:city":"Longview",
    "sg:classifiers":[
        {
            "category":"Autos & Motor Vehicles",
            "subcategory":"Automobile Sales",
            "type":"Retail Goods"
        }
    ],
    "sg:phone":"+1 903 291 0600",
    "sg:postcode":"75604",
    "sg:province":"TX",
    "sg:tags":[
        "used"
    ],
    "wof:name":"Classic Certified Used Cars",
    "wof:placetype":"venue"
},
  "geometry": {"coordinates":[-94.764465,32.537827],"type":"Point"}
}