{
  "type": "Feature",
  "properties": {
    "iso:country":"US",
    "sg:address":"609 Starnes St",
    "sg:city":"Gladewater",
    "sg:classifiers":[
        {
            "category":"Mining & Drilling",
            "type":"Manufacturing & Wholesale Goods"
        }
    ],
    "sg:phone":"+1 903 845 4202",
    "sg:postcode":"75647",
    "sg:province":"TX",
    "sg:tags":[
        "field",
        "oil"
    ],
    "wof:name":"Mathews Production Svc",
    "wof:placetype":"venue"
},
  "geometry": {"coordinates":[-94.955827,32.530927],"type":"Point"}
}