{
  "type": "Feature",
  "properties": {
    "iso:country":"US",
    "sg:address":"821 Speight Ave",
    "sg:city":"Waco",
    "sg:classifiers":[
        {
            "category":"Recreation",
            "type":"Entertainment"
        }
    ],
    "sg:phone":"+1 254 753 6917",
    "sg:postcode":"76706",
    "sg:province":"TX",
    "sg:tags":[
        "center"
    ],
    "wof:name":"Methodist Student Ctr",
    "wof:placetype":"venue"
},
  "geometry": {"coordinates":[-97.121886,31.542514],"type":"Point"}
}