{
  "type": "Feature",
  "properties": {
    "iso:country":"US",
    "sg:address":"1301 Old Jacksboro Rd",
    "sg:city":"Graham",
    "sg:classifiers":[
        {
            "category":"Insurance",
            "subcategory":"Hazard Insurance",
            "type":"Services"
        }
    ],
    "sg:phone":"+1 940 549 2663",
    "sg:postcode":"76450",
    "sg:province":"TX",
    "sg:tags":[
        "bond"
    ],
    "wof:name":"All Bail Bonds",
    "wof:placetype":"venue"
},
  "geometry": {"coordinates":[-98.575294,33.112484],"type":"Point"}
}