{
  "type": "Feature",
  "properties": {
    "iso:country":"US",
    "sg:address":"808 S Lamar St",
    "sg:city":"Weatherford",
    "sg:classifiers":[
        {
            "category":"Travel",
            "subcategory":"Hotels & Motels",
            "type":"Entertainment"
        }
    ],
    "sg:phone":"+1 817 594 1455",
    "sg:postcode":"76086",
    "sg:province":"TX",
    "sg:tags":[
        "breakfast",
        "accommodation",
        "bed"
    ],
    "wof:name":"St Botolph Inn Bed & Breakfast",
    "wof:placetype":"venue"
},
  "geometry": {"coordinates":[-97.80409,32.750184],"type":"Point"}
}