{
  "type": "Feature",
  "properties": {
    "iso:country":"US",
    "sg:address":"1700 S Cedar St",
    "sg:city":"Borger",
    "sg:classifiers":[
        {
            "category":"Professional",
            "type":"Services"
        }
    ],
    "sg:phone":"+1 806 273 7443",
    "sg:postcode":"79007",
    "sg:province":"TX",
    "wof:name":"J M Sears",
    "wof:placetype":"venue"
},
  "geometry": {"coordinates":[-101.39913,35.649826],"type":"Point"}
}