{
  "type": "Feature",
  "properties": {
    "iso:country":"US",
    "sg:address":"6102 Dartmouth St",
    "sg:city":"Amarillo",
    "sg:classifiers":[
        {
            "category":"Manufacturing",
            "subcategory":"Printing",
            "type":"Manufacturing & Wholesale Goods"
        }
    ],
    "sg:phone":"+1 806 355 7856",
    "sg:postcode":"79109",
    "sg:province":"TX",
    "sg:tags":[
        "book"
    ],
    "wof:name":"Rohrs Etc",
    "wof:placetype":"venue"
},
  "geometry": {"coordinates":[-101.896593,35.143756],"type":"Point"}
}