{
  "type": "Feature",
  "properties": {
    "iso:country":"US",
    "sg:address":"305 E Elms Rd",
    "sg:city":"Killeen",
    "sg:classifiers":[
        {
            "category":"Professional",
            "type":"Services"
        }
    ],
    "sg:phone":"+1 254 200 2521",
    "sg:postcode":"76542",
    "sg:province":"TX",
    "sg:tags":[
        "establishment"
    ],
    "wof:name":"To Get 2U",
    "wof:placetype":"venue"
},
  "geometry": {"coordinates":[-97.745456,31.083573],"type":"Point"}
}