{
  "type": "Feature",
  "properties": {
    "iso:country":"US",
    "sg:address":"1601 Park Place Ave",
    "sg:city":"Fort Worth",
    "sg:classifiers":[
        {
            "category":"Restaurant",
            "type":"Food & Drink"
        }
    ],
    "sg:phone":"+1 817 923 2299",
    "sg:postcode":"76110",
    "sg:province":"TX",
    "sg:tags":[
        "eating"
    ],
    "wof:name":"Ho Ho Chinese Restaurant",
    "wof:placetype":"venue"
},
  "geometry": {"coordinates":[-97.342541,32.725361],"type":"Point"}
}