{
  "type": "Feature",
  "properties": {
    "iso:country":"US",
    "sg:address":"1504 Cliffwood Rd",
    "sg:city":"Euless",
    "sg:classifiers":[
        {
            "category":"Professional",
            "subcategory":"Engineering",
            "type":"Services"
        }
    ],
    "sg:phone":"+1 817 571 6163",
    "sg:postcode":"76040",
    "sg:province":"TX",
    "sg:tags":[
        "engineer"
    ],
    "wof:name":"Reb Technologies Inc",
    "wof:placetype":"venue"
},
  "geometry": {"coordinates":[-97.149277,32.81843],"type":"Point"}
}