{
  "type": "Feature",
  "properties": {
    "iso:country":"US",
    "sg:address":"9442 N Capital of Texas Hwy",
    "sg:city":"Austin",
    "sg:classifiers":[
        {
            "category":"Professional",
            "subcategory":"Lawyer & Legal Services",
            "type":"Services"
        }
    ],
    "sg:phone":"+1 512 343 6248",
    "sg:postcode":"78759",
    "sg:province":"TX",
    "wof:name":"Davis and Davis P C",
    "wof:placetype":"venue"
},
  "geometry": {"coordinates":[-97.748508,30.388795],"type":"Point"}
}