{
  "type": "Feature",
  "properties": {
    "iso:country":"US",
    "sg:address":"2309 Ola Ln",
    "sg:city":"Haltom City",
    "sg:classifiers":[
        {
            "category":"Building & Trades",
            "subcategory":"Plumbing",
            "type":"Services"
        }
    ],
    "sg:phone":"+1 817 759 0003",
    "sg:postcode":"76111",
    "sg:province":"TX",
    "sg:tags":[
        "tank",
        "septic"
    ],
    "wof:name":"Melton's Septic",
    "wof:placetype":"venue"
},
  "geometry": {"coordinates":[-97.292,32.793605],"type":"Point"}
}