{
  "type": "Feature",
  "properties": {
    "iso:country":"US",
    "sg:address":"2218 I- 45 N",
    "sg:city":"Conroe",
    "sg:classifiers":[
        {
            "category":"Shopping",
            "subcategory":"Hobbies, Toys, & Games",
            "type":"Retail Goods"
        }
    ],
    "sg:phone":"+1 936 539 9630",
    "sg:postcode":"77301",
    "sg:province":"TX",
    "sg:tags":[
        "craft",
        "supply"
    ],
    "sg:website":"www.michaels.com",
    "wof:name":"Michaels Arts & Crafts Store",
    "wof:placetype":"venue"
},
  "geometry": {"coordinates":[-95.480312,30.339786],"type":"Point"}
}