{
  "type": "Feature",
  "properties": {
    "iso:country":"US",
    "sg:address":"104 W Myrtle St",
    "sg:city":"Angleton",
    "sg:classifiers":[
        {
            "category":"Personal",
            "type":"Services"
        }
    ],
    "sg:phone":"+1 979 848 7079",
    "sg:postcode":"77515",
    "sg:province":"TX",
    "sg:tags":[
        "therapist",
        "massage"
    ],
    "wof:name":"Wishing Well Massage & Body Wk",
    "wof:placetype":"venue"
},
  "geometry": {"coordinates":[-95.431856,29.165569],"type":"Point"}
}