{
  "type": "Feature",
  "properties": {
    "iso:country":"US",
    "sg:address":"164 S Main St",
    "sg:city":"Keller",
    "sg:classifiers":[
        {
            "category":"Retail",
            "subcategory":"Auto Repair",
            "type":"Services"
        }
    ],
    "sg:phone":"+1 817 431 1888",
    "sg:postcode":"76248",
    "sg:province":"TX",
    "sg:tags":[
        "automobile",
        "restoration",
        "classic"
    ],
    "wof:name":"Performance Restorations",
    "wof:placetype":"venue"
},
  "geometry": {"coordinates":[-97.253788,32.933422],"type":"Point"}
}