{
  "type": "Feature",
  "properties": {
    "iso:country":"US",
    "sg:address":"2914 Country Club Blvd",
    "sg:city":"Sugar Land",
    "sg:classifiers":[
        {
            "category":"Professional",
            "subcategory":"Business Services",
            "type":"Services"
        }
    ],
    "sg:phone":"+1 281 494 1698",
    "sg:postcode":"77478",
    "sg:province":"TX",
    "wof:name":"Lisse Maralyn Interiors",
    "wof:placetype":"venue"
},
  "geometry": {"coordinates":[-95.59217599999999,29.624818],"type":"Point"}
}