{
  "type": "Feature",
  "properties": {
    "iso:country":"US",
    "sg:address":"14200 Ranch Road 620 N",
    "sg:city":"Austin",
    "sg:classifiers":[
        {
            "category":"Autos & Motor Vehicles",
            "subcategory":"Fuel & Gas Station",
            "type":"Retail Goods"
        },
        {
            "category":"Retail",
            "subcategory":"Car Wash",
            "type":"Services"
        },
        {
            "category":"Food & Beverages",
            "subcategory":"Groceries & Convenience Stores",
            "type":"Retail Goods"
        }
    ],
    "sg:phone":"+1 512 219 5339",
    "sg:postcode":"78750",
    "sg:province":"TX",
    "sg:website":"http://www.tetcorewards.com",
    "wof:name":"TETCO - Chevron - Store 58",
    "wof:placetype":"venue"
},
  "geometry": {"coordinates":[-97.77543300000001,30.473729],"type":"Point"}
}