{
  "type": "Feature",
  "properties": {
    "iso:country":"US",
    "sg:address":"6881 Co Rd 3163",
    "sg:city":"Ira",
    "sg:classifiers":[
        {
            "category":"Health Services",
            "subcategory":"Nursing And Care Facility",
            "type":"Services"
        }
    ],
    "sg:phone":"+1 325 573 5563",
    "sg:postcode":"79527",
    "sg:province":"TX",
    "wof:name":"L & W Elder Care",
    "wof:placetype":"venue"
},
  "geometry": {"coordinates":[-101.102496,32.648544],"type":"Point"}
}