{
  "type": "Feature",
  "properties": {
    "iso:country":"US",
    "sg:address":"1811 Parkway Dr",
    "sg:city":"Lubbock",
    "sg:classifiers":[
        {
            "category":"Social Services",
            "type":"Services"
        }
    ],
    "sg:phone":"+1 806 747 0182",
    "sg:postcode":"79403",
    "sg:province":"TX",
    "sg:tags":[
        "organization",
        "welfare"
    ],
    "wof:name":"WIC Clinic",
    "wof:placetype":"venue"
},
  "geometry": {"coordinates":[-101.812764,33.595748],"type":"Point"}
}