{
  "type": "Feature",
  "properties": {
    "iso:country":"US",
    "sg:address":"1618 Port Neches Ave",
    "sg:city":"Port Neches",
    "sg:classifiers":[
        {
            "category":"Retail",
            "subcategory":"Portrait Studio",
            "type":"Services"
        }
    ],
    "sg:phone":"+1 409 722 0944",
    "sg:postcode":"77651",
    "sg:province":"TX",
    "sg:tags":[
        "photographer"
    ],
    "wof:name":"Lumpkin's Photography",
    "wof:placetype":"venue"
},
  "geometry": {"coordinates":[-93.96457700000001,29.990837],"type":"Point"}
}