{
  "type": "Feature",
  "properties": {
    "iso:country":"US",
    "sg:address":"9239 Skillman St",
    "sg:city":"Dallas",
    "sg:classifiers":[
        {
            "category":"Personal",
            "subcategory":"Nail Salon",
            "type":"Services"
        }
    ],
    "sg:phone":"+1 214 341 8500",
    "sg:postcode":"75243",
    "sg:province":"TX",
    "wof:name":"California Nails",
    "wof:placetype":"venue"
},
  "geometry": {"coordinates":[-96.714401,32.903301],"type":"Point"}
}