{
  "type": "Feature",
  "properties": {
    "iso:country":"US",
    "sg:address":"5833 Weber Rd",
    "sg:city":"Corpus Christi",
    "sg:classifiers":[
        {
            "category":"Retail",
            "subcategory":"Laundry & Dry Cleaning",
            "type":"Services"
        }
    ],
    "sg:phone":"+1 361 855 4796",
    "sg:postcode":"78413",
    "sg:province":"TX",
    "sg:tags":[
        "garment",
        "agent"
    ],
    "wof:name":"Zoic Corporation",
    "wof:placetype":"venue"
},
  "geometry": {"coordinates":[-97.405286,27.711203],"type":"Point"}
}