{
  "type": "Feature",
  "properties": {
    "iso:country":"US",
    "sg:address":"98 Springhill Dr",
    "sg:city":"Palestine",
    "sg:classifiers":[
        {
            "category":"Place Of Worship",
            "type":"Public Place"
        }
    ],
    "sg:phone":"+1 903 723 0299",
    "sg:postcode":"75801",
    "sg:province":"TX",
    "sg:tags":[
        "church"
    ],
    "wof:name":"Grace Bible Church Of Palestine, Texas",
    "wof:placetype":"venue"
},
  "geometry": {"coordinates":[-95.624025,31.713433],"type":"Point"}
}