{
  "type": "Feature",
  "properties": {
    "iso:country":"US",
    "sg:address":"2110 S Coulter St",
    "sg:city":"Amarillo",
    "sg:classifiers":[
        {
            "category":"Restaurant",
            "type":"Food & Drink"
        }
    ],
    "sg:menulink":"http://www.allmenus.com/tx/amarillo/141936-waffle-house/menu/",
    "sg:phone":"+1 806 359 1125",
    "sg:postcode":"79106",
    "sg:province":"TX",
    "sg:tags":[
        "american"
    ],
    "wof:name":"Waffle House",
    "wof:placetype":"venue"
},
  "geometry": {"coordinates":[-101.920349,35.185708],"type":"Point"}
}