{
  "type": "Feature",
  "properties": {
    "iso:country":"US",
    "sg:address":"5733 Airport Fwy",
    "sg:city":"Fort Worth",
    "sg:classifiers":[
        {
            "category":"Mining & Drilling",
            "type":"Manufacturing & Wholesale Goods"
        }
    ],
    "sg:phone":"+1 817 831 1701",
    "sg:postcode":"76117",
    "sg:province":"TX",
    "sg:tags":[
        "field"
    ],
    "wof:name":"Prater Tong Service",
    "wof:placetype":"venue"
},
  "geometry": {"coordinates":[-97.260715,32.787208],"type":"Point"}
}