{
  "type": "Feature",
  "properties": {
    "iso:country":"US",
    "sg:address":"2601 Geiberger Dr",
    "sg:city":"Plano",
    "sg:classifiers":[
        {
            "category":"Professional",
            "type":"Services"
        }
    ],
    "sg:phone":"+1 972 390 0959",
    "sg:postcode":"75025",
    "sg:province":"TX",
    "sg:tags":[
        "establishment"
    ],
    "wof:name":"Netlogic Microsystems",
    "wof:placetype":"venue"
},
  "geometry": {"coordinates":[-96.742232,33.109474],"type":"Point"}
}