{
  "type": "Feature",
  "properties": {
    "iso:country":"US",
    "sg:address":"9735 Cymbal Dr",
    "sg:city":"Stafford",
    "sg:classifiers":[
        {
            "category":"Building & Trades",
            "subcategory":"Plumbing",
            "type":"Services"
        }
    ],
    "sg:phone":"+1 281 498 0080",
    "sg:postcode":"77477",
    "sg:province":"TX",
    "sg:tags":[
        "system",
        "contractor",
        "air conditioning"
    ],
    "wof:name":"Diamond Air Services",
    "wof:placetype":"venue"
},
  "geometry": {"coordinates":[-95.546958,29.640339],"type":"Point"}
}