{
  "type": "Feature",
  "properties": {
    "iso:country":"US",
    "sg:address":"2118 S Hayden St",
    "sg:city":"Amarillo",
    "sg:classifiers":[
        {
            "category":"Shopping",
            "type":"Retail Goods"
        }
    ],
    "sg:phone":"+1 806 379 9477",
    "sg:postcode":"79109",
    "sg:province":"TX",
    "sg:tags":[
        "merchandise"
    ],
    "wof:name":"Fun By Susan",
    "wof:placetype":"venue"
},
  "geometry": {"coordinates":[-101.85100799999999,35.189549],"type":"Point"}
}