{
  "type": "Feature",
  "properties": {
    "iso:country":"US",
    "sg:address":"2731 S Flores St",
    "sg:city":"San Antonio",
    "sg:classifiers":[
        {
            "category":"Shopping",
            "subcategory":"Used Merchandise",
            "type":"Retail Goods"
        }
    ],
    "sg:phone":"+1 210 271 0377",
    "sg:postcode":"78204",
    "sg:province":"TX",
    "sg:tags":[
        "shop",
        "thrift"
    ],
    "wof:name":"Elisa's Thrift Store",
    "wof:placetype":"venue"
},
  "geometry": {"coordinates":[-98.504515,29.398049],"type":"Point"}
}