{
  "type": "Feature",
  "properties": {
    "iso:country":"US",
    "sg:address":"234 Bentwood Dr",
    "sg:city":"Boerne",
    "sg:classifiers":[
        {
            "category":"Professional",
            "subcategory":"Engineering",
            "type":"Services"
        }
    ],
    "sg:phone":"+1 830 249 1778",
    "sg:postcode":"78006",
    "sg:province":"TX",
    "wof:name":"John H Key",
    "wof:placetype":"venue"
},
  "geometry": {"coordinates":[-98.70364600000001,29.799881],"type":"Point"}
}