{
  "type": "Feature",
  "properties": {
    "iso:country":"US",
    "sg:address":"8505 Freeport Pkwy",
    "sg:city":"Irving",
    "sg:classifiers":[
        {
            "category":"Manufacturing",
            "subcategory":"Glass & Minerals",
            "type":"Manufacturing & Wholesale Goods"
        },
        {
            "category":"Building & Trades",
            "subcategory":"Construction",
            "type":"Services"
        }
    ],
    "sg:phone":"+1 972 621 0999",
    "sg:postcode":"75063",
    "sg:province":"TX",
    "sg:tags":[
        "ready",
        "concrete",
        "contractor",
        "mfg"
    ],
    "sg:website":"www.southernstarconcrete.com",
    "wof:name":"Southern Star Concrete Inc",
    "wof:placetype":"venue"
},
  "geometry": {"coordinates":[-97.018519,32.923518],"type":"Point"}
}