{
  "type": "Feature",
  "properties": {
    "iso:country":"US",
    "sg:address":"1520 Dumas Dr",
    "sg:city":"Amarillo",
    "sg:classifiers":[
        {
            "category":"Professional",
            "type":"Services"
        }
    ],
    "sg:phone":"+1 806 383 0425",
    "sg:postcode":"79107",
    "sg:province":"TX",
    "wof:name":"Active Screening",
    "wof:placetype":"venue"
},
  "geometry": {"coordinates":[-101.830421,35.23047],"type":"Point"}
}