{
  "type": "Feature",
  "properties": {
    "iso:country":"US",
    "sg:address":"2420 Valwood Pkwy",
    "sg:city":"Dallas",
    "sg:classifiers":[
        {
            "category":"Retail",
            "subcategory":"Auto Repair",
            "type":"Services"
        }
    ],
    "sg:phone":"+1 972 241 3343",
    "sg:postcode":"75234",
    "sg:province":"TX",
    "wof:name":"Salas Auto Repair & Sales",
    "wof:placetype":"venue"
},
  "geometry": {"coordinates":[-96.89945,32.938392],"type":"Point"}
}