{
  "type": "Feature",
  "properties": {
    "iso:country":"US",
    "sg:address":"2921 Fairmount St",
    "sg:city":"Dallas",
    "sg:classifiers":[
        {
            "category":"Health Services",
            "subcategory":"Clinic",
            "type":"Services"
        }
    ],
    "sg:phone":"+1 214 742 9310",
    "sg:postcode":"75201",
    "sg:province":"TX",
    "sg:tags":[
        "information",
        "abortion"
    ],
    "sg:website":"www.fairmountcenter.com",
    "wof:name":"Fairmount Center",
    "wof:placetype":"venue"
},
  "geometry": {"coordinates":[-96.80632900000001,32.798492],"type":"Point"}
}