{
  "type": "Feature",
  "properties": {
    "iso:country":"US",
    "sg:address":"5110-B Ashbrook Dr",
    "sg:city":"Houston",
    "sg:classifiers":[
        {
            "category":"Personal",
            "type":"Services"
        },
        {
            "category":"Sports & Exercise",
            "subcategory":"Gym",
            "type":"Entertainment"
        },
        {
            "category":"Sports & Exercise",
            "subcategory":"Playing Field",
            "type":"Entertainment"
        },
        {
            "category":"Arena",
            "subcategory":"Sports Club",
            "type":"Entertainment"
        }
    ],
    "sg:phone":"+1 713 927 8301",
    "sg:postcode":"77081",
    "sg:province":"TX",
    "sg:tags":[
        "trainer",
        "consultant",
        "instruction",
        "health",
        "fitness",
        "physical"
    ],
    "sg:website":"www.tropazumba.com",
    "wof:name":"Studio Tropa",
    "wof:placetype":"venue"
},
  "geometry": {"coordinates":[-95.46879199999999,29.714909],"type":"Point"}
}