{
  "type": "Feature",
  "properties": {
    "iso:country":"US",
    "sg:address":"408 W Kilpatrick St",
    "sg:city":"Cleburne",
    "sg:classifiers":[
        {
            "category":"Manufacturing",
            "subcategory":"Printing",
            "type":"Manufacturing & Wholesale Goods"
        },
        {
            "category":"Professional",
            "subcategory":"Computer Services",
            "type":"Services"
        }
    ],
    "sg:phone":"+1 817 517 7696",
    "sg:postcode":"76033",
    "sg:province":"TX",
    "sg:tags":[
        "repair",
        "support",
        "sales"
    ],
    "sg:website":"www.cdipress.com",
    "wof:name":"Creative Digital Inc",
    "wof:placetype":"venue"
},
  "geometry": {"coordinates":[-97.40178,32.366325],"type":"Point"}
}