{
  "type": "Feature",
  "properties": {
    "iso:country":"US",
    "sg:address":"209 S Danville Dr",
    "sg:city":"Abilene",
    "sg:classifiers":[
        {
            "category":"Banks & Credit Unions",
            "subcategory":"Financial Services",
            "type":"Services"
        }
    ],
    "sg:phone":"+1 325 437 2572",
    "sg:postcode":"79605",
    "sg:province":"TX",
    "sg:tags":[
        "company",
        "holding"
    ],
    "wof:name":"Osmose Holdings Inc",
    "wof:placetype":"venue"
},
  "geometry": {"coordinates":[-99.78466299999999,32.450701],"type":"Point"}
}