{
  "type": "Feature",
  "properties": {
    "iso:country":"US",
    "sg:address":"4500 S Lancaster Rd",
    "sg:city":"Dallas",
    "sg:classifiers":[
        {
            "category":"Health Services",
            "subcategory":"Hospital",
            "type":"Services"
        }
    ],
    "sg:phone":"+1 214 742 8387",
    "sg:postcode":"75216",
    "sg:province":"TX",
    "wof:name":"Veterans Affairs Medical Center",
    "wof:placetype":"venue"
},
  "geometry": {"coordinates":[-96.792801,32.693401],"type":"Point"}
}