{
  "type": "Feature",
  "properties": {
    "iso:country":"US",
    "sg:address":"2726 Samuell Blvd",
    "sg:city":"Dallas",
    "sg:classifiers":[
        {
            "category":"Home & Garden",
            "subcategory":"Furniture",
            "type":"Retail Goods"
        }
    ],
    "sg:phone":"+1 214 823 8770",
    "sg:postcode":"75223",
    "sg:province":"TX",
    "wof:name":"J C Furniture",
    "wof:placetype":"venue"
},
  "geometry": {"coordinates":[-96.746847,32.792893],"type":"Point"}
}