{
  "type": "Feature",
  "properties": {
    "iso:country":"US",
    "sg:address":"768 Airway Ave",
    "sg:city":"Tyler",
    "sg:classifiers":[
        {
            "category":"Shopping",
            "subcategory":"Used Merchandise",
            "type":"Retail Goods"
        }
    ],
    "sg:phone":"+1 903 592 6643",
    "sg:postcode":"75704",
    "sg:province":"TX",
    "sg:tags":[
        "clothing"
    ],
    "wof:name":"Twice Blessed",
    "wof:placetype":"venue"
},
  "geometry": {"coordinates":[-95.381409,32.357693],"type":"Point"}
}