{
  "type": "Feature",
  "properties": {
    "iso:country":"US",
    "sg:address":"1720 Regal Row",
    "sg:city":"Dallas",
    "sg:classifiers":[
        {
            "category":"Freight",
            "type":"Transportation"
        }
    ],
    "sg:phone":"+1 214 631 8054",
    "sg:postcode":"75235",
    "sg:province":"TX",
    "sg:tags":[
        "delivery",
        "operator",
        "local",
        "legal",
        "trucking"
    ],
    "sg:website":"www.gxcourier.com",
    "wof:name":"Guaranteed Express Inc",
    "wof:placetype":"venue"
},
  "geometry": {"coordinates":[-96.873673,32.836067],"type":"Point"}
}