{
  "type": "Feature",
  "properties": {
    "iso:country":"US",
    "sg:address":"4303 W Illinois Ave",
    "sg:city":"Midland",
    "sg:classifiers":[
        {
            "category":"Social Services",
            "subcategory":"Child Care",
            "type":"Services"
        }
    ],
    "sg:phone":"+1 432 699 7992",
    "sg:postcode":"79703",
    "sg:province":"TX",
    "wof:name":"Peppermint Plantation",
    "wof:placetype":"venue"
},
  "geometry": {"coordinates":[-102.132316,31.987748],"type":"Point"}
}