{
  "type": "Feature",
  "properties": {
    "iso:country":"US",
    "sg:address":"690 S Stemmons Fwy",
    "sg:city":"Lewisville",
    "sg:classifiers":[
        {
            "category":"Building & Trades",
            "subcategory":"Pest Control",
            "type":"Services"
        }
    ],
    "sg:phone":"+1 972 434 6200",
    "sg:postcode":"75067",
    "sg:province":"TX",
    "sg:website":"www.adamspest.com",
    "wof:name":"Adams Exterminating Co Inc",
    "wof:placetype":"venue"
},
  "geometry": {"coordinates":[-97.004177,33.040848],"type":"Point"}
}