{
  "type": "Feature",
  "properties": {
    "iso:country":"US",
    "sg:address":"3855 Belt Line Rd",
    "sg:city":"Addison",
    "sg:classifiers":[
        {
            "category":"Bars & Pubs",
            "subcategory":"Sports Bar",
            "type":"Food & Drink"
        },
        {
            "category":"Restaurant",
            "type":"Food & Drink"
        }
    ],
    "sg:phone":"+1 972 247 0306",
    "sg:postcode":"75001",
    "sg:province":"TX",
    "sg:tags":[
        "mexican"
    ],
    "sg:website":"www.loslupes.com",
    "wof:name":"Los Lupes Restaurant",
    "wof:placetype":"venue"
},
  "geometry": {"coordinates":[-96.850481,32.953934],"type":"Point"}
}