{
  "type": "Feature",
  "properties": {
    "iso:country":"US",
    "sg:address":"523 W Schunior St",
    "sg:city":"Edinburg",
    "sg:classifiers":[
        {
            "category":"Food & Beverages",
            "subcategory":"Groceries & Convenience Stores",
            "type":"Retail Goods"
        }
    ],
    "sg:phone":"+1 956 381 8140",
    "sg:postcode":"78541",
    "sg:province":"TX",
    "wof:name":"Vasquez Grocery",
    "wof:placetype":"venue"
},
  "geometry": {"coordinates":[-98.166628,26.309212],"type":"Point"}
}