{
  "type": "Feature",
  "properties": {
    "iso:country":"US",
    "sg:address":"11005 North Fwy",
    "sg:city":"Houston",
    "sg:classifiers":[
        {
            "category":"Shopping",
            "subcategory":"Mobile Phones",
            "type":"Retail Goods"
        }
    ],
    "sg:phone":"+1 281 591 2226",
    "sg:postcode":"77037",
    "sg:province":"TX",
    "wof:name":"Wireless Access",
    "wof:placetype":"venue"
},
  "geometry": {"coordinates":[-95.412947,29.925672],"type":"Point"}
}