{
  "type": "Feature",
  "properties": {
    "iso:country":"US",
    "sg:address":"13802 Hempstead Rd",
    "sg:city":"Houston",
    "sg:classifiers":[
        {
            "category":"Travel",
            "subcategory":"Hotels & Motels",
            "type":"Entertainment"
        }
    ],
    "sg:phone":"+1 713 934 8080",
    "sg:postcode":"77040",
    "sg:province":"TX",
    "sg:tags":[
        "operation"
    ],
    "wof:name":"Lodge The",
    "wof:placetype":"venue"
},
  "geometry": {"coordinates":[-95.527143,29.849714],"type":"Point"}
}