{
  "type": "Feature",
  "properties": {
    "iso:country":"US",
    "sg:address":"108 Picea Dr",
    "sg:city":"Lakeway",
    "sg:classifiers":[
        {
            "category":"Personal",
            "type":"Services"
        }
    ],
    "sg:phone":"+1 512 608 6616",
    "sg:postcode":"78734",
    "sg:province":"TX",
    "sg:tags":[
        "program",
        "physical",
        "exercise",
        "fitness"
    ],
    "wof:name":"Body Works Fitness",
    "wof:placetype":"venue"
},
  "geometry": {"coordinates":[-97.96933,30.377971],"type":"Point"}
}