{
  "type": "Feature",
  "properties": {
    "iso:country":"US",
    "sg:address":"14120 Cornerstone Village Dr",
    "sg:city":"Houston",
    "sg:classifiers":[
        {
            "category":"Place Of Worship",
            "type":"Public Place"
        }
    ],
    "sg:phone":"+1 281 397 0016",
    "sg:postcode":"77014",
    "sg:province":"TX",
    "sg:tags":[
        "church"
    ],
    "wof:name":"Iglesia Bautista Cristo Es La",
    "wof:placetype":"venue"
},
  "geometry": {"coordinates":[-95.47965600000001,29.987831],"type":"Point"}
}