{
  "type": "Feature",
  "properties": {
    "iso:country":"US",
    "sg:address":"405 N Gray St",
    "sg:city":"Pampa",
    "sg:classifiers":[
        {
            "category":"Organizations",
            "subcategory":"Community Association",
            "type":"Services"
        }
    ],
    "sg:phone":"+1 806 669 7934",
    "sg:postcode":"79065",
    "sg:province":"TX",
    "wof:name":"Pampa Community Concert Association Inc",
    "wof:placetype":"venue"
},
  "geometry": {"coordinates":[-100.96730100000001,35.536932],"type":"Point"}
}