{
  "type": "Feature",
  "properties": {
    "iso:country":"US",
    "sg:address":"2760 Rolling Meadows Dr",
    "sg:city":"Rockwall",
    "sg:classifiers":[
        {
            "category":"Banks & Credit Unions",
            "subcategory":"Investment Brokerage",
            "type":"Services"
        }
    ],
    "sg:phone":"+1 972 772 4106",
    "sg:postcode":"75087",
    "sg:province":"TX",
    "sg:tags":[
        "advisory"
    ],
    "wof:name":"Ll & Mn Investments",
    "wof:placetype":"venue"
},
  "geometry": {"coordinates":[-96.419169,32.930838],"type":"Point"}
}