{
  "type": "Feature",
  "properties": {
    "iso:country":"US",
    "sg:address":"10401 Lynnhaven Pl",
    "sg:city":"Lubbock",
    "sg:classifiers":[
        {
            "category":"Manufacturing",
            "subcategory":"Printing",
            "type":"Manufacturing & Wholesale Goods"
        }
    ],
    "sg:phone":"+1 806 771 2697",
    "sg:postcode":"79423",
    "sg:province":"TX",
    "sg:tags":[
        "multimedia"
    ],
    "wof:name":"Crayne Media",
    "wof:placetype":"venue"
},
  "geometry": {"coordinates":[-101.89524299999999,33.499218],"type":"Point"}
}