{
  "type": "Feature",
  "properties": {
    "iso:country":"US",
    "sg:address":"801 Wood St",
    "sg:city":"Texarkana",
    "sg:classifiers":[
        {
            "category":"Utilities",
            "subcategory":"Water",
            "type":"Services"
        }
    ],
    "sg:phone":"+1 903 798 3800",
    "sg:postcode":"75501",
    "sg:province":"TX",
    "sg:tags":[
        "company",
        "sewage"
    ],
    "sg:website":"www.txkusa.org",
    "wof:name":"Texarkana Water Utilities",
    "wof:placetype":"venue"
},
  "geometry": {"coordinates":[-94.04456999999999,33.428851],"type":"Point"}
}