{
  "type": "Feature",
  "properties": {
    "iso:country":"US",
    "sg:address":"11105 Shady Trl",
    "sg:city":"Dallas",
    "sg:classifiers":[
        {
            "category":"Shopping",
            "type":"Retail Goods"
        },
        {
            "category":"Professional",
            "subcategory":"Business Services",
            "type":"Services"
        },
        {
            "category":"Wholesale",
            "subcategory":"Non-durable Goods",
            "type":"Manufacturing & Wholesale Goods"
        }
    ],
    "sg:phone":"+1 972 488 6080",
    "sg:postcode":"75229",
    "sg:province":"TX",
    "sg:tags":[
        "badge",
        "merchandise"
    ],
    "wof:name":"Badges Plus",
    "wof:placetype":"venue"
},
  "geometry": {"coordinates":[-96.89051000000001,32.885316],"type":"Point"}
}