{
  "type": "Feature",
  "properties": {
    "iso:country":"US",
    "sg:address":"403 N Jupiter Rd",
    "sg:city":"Garland",
    "sg:classifiers":[
        {
            "category":"Professional",
            "type":"Services"
        }
    ],
    "sg:phone":"+1 972 494 4646",
    "sg:postcode":"75042",
    "sg:province":"TX",
    "sg:tags":[
        "establishment"
    ],
    "wof:name":"Mexico Express Inc",
    "wof:placetype":"venue"
},
  "geometry": {"coordinates":[-96.683155,32.917095],"type":"Point"}
}