{
  "type": "Feature",
  "properties": {
    "iso:country":"US",
    "sg:address":"27 Canoe Birch Pl",
    "sg:city":"Spring",
    "sg:classifiers":[
        {
            "category":"Professional",
            "subcategory":"Management & Consulting",
            "type":"Services"
        }
    ],
    "sg:phone":"+1 281 419 2219",
    "sg:postcode":"77382",
    "sg:province":"TX",
    "wof:name":"Clifton Marketing",
    "wof:placetype":"venue"
},
  "geometry": {"coordinates":[-95.543165,30.210212],"type":"Point"}
}