{
  "type": "Feature",
  "properties": {
    "iso:country":"US",
    "sg:address":"16219 Leigh Canyon Dr",
    "sg:city":"Friendswood",
    "sg:classifiers":[
        {
            "category":"Shopping",
            "subcategory":"Jewelry",
            "type":"Retail Goods"
        }
    ],
    "sg:phone":"+1 281 992 4922",
    "sg:postcode":"77546",
    "sg:province":"TX",
    "wof:name":"Anthony Nguyen Jewelry",
    "wof:placetype":"venue"
},
  "geometry": {"coordinates":[-95.18057,29.535889],"type":"Point"}
}