{
  "type": "Feature",
  "properties": {
    "iso:country":"US",
    "sg:address":"901 16th St",
    "sg:city":"Colorado City",
    "sg:classifiers":[
        {
            "category":"Wholesale",
            "subcategory":"Non-durable Goods",
            "type":"Manufacturing & Wholesale Goods"
        }
    ],
    "sg:phone":"+1 325 728 5982",
    "sg:postcode":"79512",
    "sg:province":"TX",
    "wof:name":"Lone Star Trading Co",
    "wof:placetype":"venue"
},
  "geometry": {"coordinates":[-100.85306300000001,32.404274],"type":"Point"}
}