{
  "type": "Feature",
  "properties": {
    "iso:country":"US",
    "sg:address":"2706 Valley Forest Dr",
    "sg:city":"Missouri City",
    "sg:classifiers":[
        {
            "category":"Manufacturing",
            "subcategory":"Metals",
            "type":"Manufacturing & Wholesale Goods"
        }
    ],
    "sg:phone":"+1 281 437 1509",
    "sg:postcode":"77489",
    "sg:province":"TX",
    "sg:tags":[
        "mining",
        "construction",
        "machinery"
    ],
    "wof:name":"Wheeler Industries",
    "wof:placetype":"venue"
},
  "geometry": {"coordinates":[-95.536689,29.580625],"type":"Point"}
}