{
  "type": "Feature",
  "properties": {
    "iso:country":"US",
    "sg:address":"922 W Donovan St",
    "sg:city":"Houston",
    "sg:classifiers":[
        {
            "category":"Wholesale",
            "subcategory":"Construction Materials",
            "type":"Manufacturing & Wholesale Goods"
        }
    ],
    "sg:phone":"+1 713 691 6291",
    "sg:postcode":"77091",
    "sg:province":"TX",
    "wof:name":"Pauls Ornametal Iron Works",
    "wof:placetype":"venue"
},
  "geometry": {"coordinates":[-95.416549,29.844113],"type":"Point"}
}