{
  "type": "Feature",
  "properties": {
    "iso:country":"US",
    "sg:address":"8065 Callaghan Rd",
    "sg:city":"San Antonio",
    "sg:classifiers":[
        {
            "category":"Retail",
            "subcategory":"Repair Shop",
            "type":"Services"
        }
    ],
    "sg:phone":"+1 210 699 8353",
    "sg:postcode":"78230",
    "sg:province":"TX",
    "sg:tags":[
        "equipment",
        "telephone",
        "system"
    ],
    "wof:name":"Tbc Communications",
    "wof:placetype":"venue"
},
  "geometry": {"coordinates":[-98.551759,29.512005],"type":"Point"}
}