{
  "type": "Feature",
  "properties": {
    "iso:country":"US",
    "sg:address":"3249 Story Rd W",
    "sg:city":"Irving",
    "sg:classifiers":[
        {
            "category":"Wholesale",
            "subcategory":"Machinery & Supplies",
            "type":"Manufacturing & Wholesale Goods"
        }
    ],
    "sg:phone":"+1 972 252 6201",
    "sg:postcode":"75038",
    "sg:province":"TX",
    "sg:tags":[
        "fire",
        "residential",
        "top",
        "system",
        "range",
        "suppression"
    ],
    "wof:name":"21st Cntury Intl Fire Equipmen",
    "wof:placetype":"venue"
},
  "geometry": {"coordinates":[-96.989886,32.871481],"type":"Point"}
}