{
  "type": "Feature",
  "properties": {
    "iso:country":"US",
    "sg:address":"621 Stagecoach Dr",
    "sg:city":"Little Elm",
    "sg:classifiers":[
        {
            "category":"Professional",
            "type":"Services"
        }
    ],
    "sg:phone":"+1 972 294 8018",
    "sg:postcode":"75068",
    "sg:province":"TX",
    "wof:name":"Johnson John Etal",
    "wof:placetype":"venue"
},
  "geometry": {"coordinates":[-96.997281,33.188952],"type":"Point"}
}