{
  "type": "Feature",
  "properties": {
    "iso:country":"US",
    "sg:address":"358 E Harding Blvd",
    "sg:city":"San Antonio",
    "sg:classifiers":[
        {
            "category":"Retail",
            "subcategory":"Auto Repair",
            "type":"Services"
        }
    ],
    "sg:phone":"+1 210 627 9555",
    "sg:postcode":"78214",
    "sg:province":"TX",
    "sg:tags":[
        "body"
    ],
    "wof:name":"Prime Auto Body",
    "wof:placetype":"venue"
},
  "geometry": {"coordinates":[-98.477642,29.351726],"type":"Point"}
}