{
  "type": "Feature",
  "properties": {
    "iso:country":"US",
    "sg:address":"2329 Tiffany Dr",
    "sg:city":"Copperas Cove",
    "sg:classifiers":[
        {
            "category":"Building & Trades",
            "subcategory":"Landscaping Services",
            "type":"Services"
        }
    ],
    "sg:phone":"+1 254 547 1657",
    "sg:postcode":"76522",
    "sg:province":"TX",
    "wof:name":"Gibson Lawn Service",
    "wof:placetype":"venue"
},
  "geometry": {"coordinates":[-97.904523,31.099725],"type":"Point"}
}