{
  "type": "Feature",
  "properties": {
    "iso:country":"US",
    "sg:address":"7051 Deer Ridge Dr",
    "sg:city":"Fort Worth",
    "sg:classifiers":[
        {
            "category":"Professional",
            "type":"Services"
        }
    ],
    "sg:phone":"+1 817 656 8197",
    "sg:postcode":"76137",
    "sg:province":"TX",
    "wof:name":"Legend Electronics",
    "wof:placetype":"venue"
},
  "geometry": {"coordinates":[-97.27301199999999,32.868164],"type":"Point"}
}