{
  "type": "Feature",
  "properties": {
    "iso:country":"US",
    "sg:address":"5700 Creekfront Ct",
    "sg:city":"Arlington",
    "sg:classifiers":[
        {
            "category":"Professional",
            "subcategory":"Computer Services",
            "type":"Services"
        }
    ],
    "sg:phone":"+1 817 465 2328",
    "sg:postcode":"76018",
    "sg:province":"TX",
    "sg:tags":[
        "related"
    ],
    "wof:name":"Harold L Brooks Inc",
    "wof:placetype":"venue"
},
  "geometry": {"coordinates":[-97.079216,32.652996],"type":"Point"}
}