{
  "type": "Feature",
  "properties": {
    "iso:country":"US",
    "sg:address":"190 Fm 2570",
    "sg:city":"Fairfield",
    "sg:classifiers":[
        {
            "category":"Restaurant",
            "type":"Food & Drink"
        }
    ],
    "sg:phone":"+1 903 389 3319",
    "sg:postcode":"75840",
    "sg:province":"TX",
    "wof:name":"Fred W Galley",
    "wof:placetype":"venue"
},
  "geometry": {"coordinates":[-96.132192,31.74836],"type":"Point"}
}