{
  "type": "Feature",
  "properties": {
    "iso:country":"US",
    "sg:address":"11132 FM 3005",
    "sg:city":"Galveston",
    "sg:classifiers":[
        {
            "category":"Building & Trades",
            "subcategory":"Construction",
            "type":"Services"
        }
    ],
    "sg:phone":"+1 409 737 2816",
    "sg:postcode":"77554",
    "sg:province":"TX",
    "sg:tags":[
        "house",
        "concrete",
        "contractor"
    ],
    "wof:name":"Golden Yarn Carpet & Cnstr",
    "wof:placetype":"venue"
},
  "geometry": {"coordinates":[-94.87950499999999,29.239403],"type":"Point"}
}