{
  "type": "Feature",
  "properties": {
    "iso:country":"US",
    "sg:address":"1907 SW 34th St",
    "sg:city":"San Antonio",
    "sg:classifiers":[
        {
            "category":"Home & Garden",
            "subcategory":"Building Materials",
            "type":"Retail Goods"
        },
        {
            "category":"Building & Trades",
            "subcategory":"Construction",
            "type":"Services"
        }
    ],
    "sg:phone":"+1 210 435 1892",
    "sg:postcode":"78237",
    "sg:province":"TX",
    "sg:tags":[
        "glass",
        "window",
        "contractor",
        "plate"
    ],
    "wof:name":"Donel Glass Works Inc",
    "wof:placetype":"venue"
},
  "geometry": {"coordinates":[-98.570549,29.408547],"type":"Point"}
}