{
  "type": "Feature",
  "properties": {
    "iso:country":"US",
    "sg:address":"5071 Cedar Creek Dr",
    "sg:city":"Houston",
    "sg:classifiers":[
        {
            "category":"Professional",
            "subcategory":"Engineering",
            "type":"Services"
        }
    ],
    "sg:phone":"+1 713 961 3935",
    "sg:postcode":"77056",
    "sg:province":"TX",
    "sg:tags":[
        "engineer"
    ],
    "wof:name":"Ben A Reid Consulting Group",
    "wof:placetype":"venue"
},
  "geometry": {"coordinates":[-95.466607,29.753371],"type":"Point"}
}