{
  "type": "Feature",
  "properties": {
    "iso:country":"US",
    "sg:address":"1504 S Main St",
    "sg:city":"Weatherford",
    "sg:classifiers":[
        {
            "category":"Autos & Motor Vehicles",
            "subcategory":"Auto Supplies",
            "type":"Retail Goods"
        }
    ],
    "sg:phone":"+1 817 599 9455",
    "sg:postcode":"76086",
    "sg:province":"TX",
    "sg:tags":[
        "automobile",
        "part"
    ],
    "sg:website":"http://www.autozone.com",
    "wof:name":"AutoZone",
    "wof:placetype":"venue"
},
  "geometry": {"coordinates":[-97.797691,32.74099],"type":"Point"}
}