{
  "type": "Feature",
  "properties": {
    "iso:country":"US",
    "sg:address":"3728 Irving Mall",
    "sg:city":"Irving",
    "sg:classifiers":[
        {
            "category":"Food & Beverages",
            "subcategory":"Specialty",
            "type":"Retail Goods"
        }
    ],
    "sg:phone":"+1 972 257 1077",
    "sg:postcode":"75062",
    "sg:province":"TX",
    "sg:tags":[
        "tea",
        "coffee"
    ],
    "wof:name":"Gloria Jean Coffees",
    "wof:placetype":"venue"
},
  "geometry": {"coordinates":[-96.993651,32.84078],"type":"Point"}
}