{
  "type": "Feature",
  "properties": {
    "iso:country":"US",
    "sg:address":"1822 Carlotta Ln",
    "sg:city":"Austin",
    "sg:classifiers":[
        {
            "category":"Banks & Credit Unions",
            "subcategory":"Financial Services",
            "type":"Services"
        }
    ],
    "sg:phone":"+1 512 263 4272",
    "sg:postcode":"78733",
    "sg:province":"TX",
    "sg:tags":[
        "investor"
    ],
    "wof:name":"Lakehills Investments Inc",
    "wof:placetype":"venue"
},
  "geometry": {"coordinates":[-97.870437,30.344978],"type":"Point"}
}