{
  "type": "Feature",
  "properties": {
    "iso:country":"US",
    "sg:address":"2910 Ruder St",
    "sg:city":"Dallas",
    "sg:classifiers":[
        {
            "category":"Food & Beverages",
            "subcategory":"Groceries & Convenience Stores",
            "type":"Retail Goods"
        }
    ],
    "sg:phone":"+1 214 631 1639",
    "sg:postcode":"75212",
    "sg:province":"TX",
    "wof:name":"Whip In No 105",
    "wof:placetype":"venue"
},
  "geometry": {"coordinates":[-96.91860200000001,32.777699],"type":"Point"}
}