{
  "type": "Feature",
  "properties": {
    "iso:country":"US",
    "sg:address":"15213 Southwest Fwy",
    "sg:city":"Sugar Land",
    "sg:classifiers":[
        {
            "category":"Building & Trades",
            "subcategory":"Cleaning & Sanitation",
            "type":"Services"
        }
    ],
    "sg:phone":"+1 281 499 6981",
    "sg:postcode":"77478",
    "sg:province":"TX",
    "sg:tags":[
        "maintenance"
    ],
    "wof:name":"Advanced Building Maintenance",
    "wof:placetype":"venue"
},
  "geometry": {"coordinates":[-95.61366099999999,29.60673],"type":"Point"}
}