{
  "type": "Feature",
  "properties": {
    "iso:country":"US",
    "sg:address":"19420 Norfolk Dr",
    "sg:city":"Flint",
    "sg:classifiers":[
        {
            "category":"Professional",
            "subcategory":"Lawyer & Legal Services",
            "type":"Services"
        },
        {
            "category":"Professional",
            "subcategory":"Secretarial Services",
            "type":"Services"
        }
    ],
    "sg:phone":"+1 903 530 9930",
    "sg:postcode":"75762",
    "sg:province":"TX",
    "sg:tags":[
        "reporting",
        "court"
    ],
    "wof:name":"Summarize This",
    "wof:placetype":"venue"
},
  "geometry": {"coordinates":[-95.337166,32.197573],"type":"Point"}
}