{
  "type": "Feature",
  "properties": {
    "iso:country":"US",
    "sg:address":"1519 34th St",
    "sg:city":"Lubbock",
    "sg:classifiers":[
        {
            "category":"Restaurant",
            "type":"Food & Drink"
        }
    ],
    "sg:phone":"+1 806 744 9151",
    "sg:postcode":"79411",
    "sg:province":"TX",
    "sg:tags":[
        "eating"
    ],
    "wof:name":"La Fiesta Restaurant",
    "wof:placetype":"venue"
},
  "geometry": {"coordinates":[-101.85279300000001,33.563205],"type":"Point"}
}