{
  "type": "Feature",
  "properties": {
    "iso:country":"US",
    "sg:address":"3704 County Road 1200",
    "sg:city":"Lubbock",
    "sg:classifiers":[
        {
            "category":"Building & Trades",
            "subcategory":"Landscaping Services",
            "type":"Services"
        }
    ],
    "sg:phone":"+1 806 548 1278",
    "sg:postcode":"79407",
    "sg:province":"TX",
    "sg:tags":[
        "lawn",
        "maintenance"
    ],
    "wof:name":"L & L Custom Lawn Care",
    "wof:placetype":"venue"
},
  "geometry": {"coordinates":[-102.043735,33.560414],"type":"Point"}
}