{
  "type": "Feature",
  "properties": {
    "iso:country":"US",
    "sg:address":"1349 Meadow Creek Dr",
    "sg:city":"Irving",
    "sg:classifiers":[
        {
            "category":"Professional",
            "type":"Services"
        }
    ],
    "sg:phone":"+1 972 580 0493",
    "sg:postcode":"75038",
    "sg:province":"TX",
    "wof:name":"Y2k LLC",
    "wof:placetype":"venue"
},
  "geometry": {"coordinates":[-96.969435,32.882482],"type":"Point"}
}