{
  "type": "Feature",
  "properties": {
    "iso:country":"US",
    "sg:address":"17545 Huffmeister Rd",
    "sg:city":"Cypress",
    "sg:classifiers":[
        {
            "category":"Manufacturing",
            "subcategory":"Tools & Machinery",
            "type":"Manufacturing & Wholesale Goods"
        }
    ],
    "sg:phone":"+1 281 304 9800",
    "sg:postcode":"77429",
    "sg:province":"TX",
    "sg:tags":[
        "industrial",
        "mfg"
    ],
    "wof:name":"CL Industries Co",
    "wof:placetype":"venue"
},
  "geometry": {"coordinates":[-95.69583799999999,29.996993],"type":"Point"}
}