{
  "type": "Feature",
  "properties": {
    "iso:country":"US",
    "sg:address":"2026 E Abram St",
    "sg:city":"Arlington",
    "sg:classifiers":[
        {
            "category":"Autos & Motor Vehicles",
            "subcategory":"Automobile Sales",
            "type":"Retail Goods"
        }
    ],
    "sg:phone":"+1 817 795 5139",
    "sg:postcode":"76010",
    "sg:province":"TX",
    "sg:tags":[
        "car",
        "dealer"
    ],
    "wof:name":"Chucklink Inc",
    "wof:placetype":"venue"
},
  "geometry": {"coordinates":[-97.077012,32.735173],"type":"Point"}
}