{
  "type": "Feature",
  "properties": {
    "iso:country":"US",
    "sg:address":"2933 Carver Dr",
    "sg:city":"Corpus Christi",
    "sg:classifiers":[
        {
            "category":"Organizations",
            "subcategory":"Religious Organization",
            "type":"Services"
        }
    ],
    "sg:phone":"+1 361 888 9177",
    "sg:postcode":"78405",
    "sg:province":"TX",
    "sg:tags":[
        "church"
    ],
    "wof:name":"Thompson Chapel",
    "wof:placetype":"venue"
},
  "geometry": {"coordinates":[-97.427402,27.771545],"type":"Point"}
}