{
  "type": "Feature",
  "properties": {
    "iso:country":"US",
    "sg:address":"2608 Tulane Dr",
    "sg:city":"Lufkin",
    "sg:classifiers":[
        {
            "category":"Fast Food",
            "type":"Food & Drink"
        }
    ],
    "sg:phone":"+1 936 634 3664",
    "sg:postcode":"75901",
    "sg:province":"TX",
    "sg:tags":[
        "restaurant"
    ],
    "wof:name":"Wendy Cartlidge Rn",
    "wof:placetype":"venue"
},
  "geometry": {"coordinates":[-94.72078,31.296251],"type":"Point"}
}