{
  "type": "Feature",
  "properties": {
    "iso:country":"US",
    "sg:address":"506 W Dallas Rd",
    "sg:city":"Grapevine",
    "sg:classifiers":[
        {
            "category":"Wholesale",
            "subcategory":"Machinery & Supplies",
            "type":"Manufacturing & Wholesale Goods"
        }
    ],
    "sg:phone":"+1 817 421 3157",
    "sg:postcode":"76051",
    "sg:province":"TX",
    "sg:tags":[
        "equipment",
        "industrial"
    ],
    "wof:name":"Tri-J Tool & Fastener",
    "wof:placetype":"venue"
},
  "geometry": {"coordinates":[-97.083682,32.932402],"type":"Point"}
}