{
  "type": "Feature",
  "properties": {
    "iso:country":"US",
    "sg:address":"720 Golder Ave",
    "sg:city":"Odessa",
    "sg:classifiers":[
        {
            "category":"Health Services",
            "subcategory":"Doctor",
            "type":"Services"
        }
    ],
    "sg:phone":"+1 432 580 8880",
    "sg:postcode":"79761",
    "sg:province":"TX",
    "sg:tags":[
        "physician",
        "surgeon"
    ],
    "wof:name":"Odessa Heart Clinic",
    "wof:placetype":"venue"
},
  "geometry": {"coordinates":[-102.377622,31.847665],"type":"Point"}
}