{
  "type": "Feature",
  "properties": {
    "iso:country":"US",
    "sg:address":"3609 Kelly Ln",
    "sg:city":"Pflugerville",
    "sg:classifiers":[
        {
            "category":"Building & Trades",
            "subcategory":"Construction",
            "type":"Services"
        }
    ],
    "sg:phone":"+1 512 989 8767",
    "sg:postcode":"78660",
    "sg:province":"TX",
    "sg:tags":[
        "house"
    ],
    "wof:name":"Village Builders At Hidden Lk",
    "wof:placetype":"venue"
},
  "geometry": {"coordinates":[-97.573318,30.46231],"type":"Point"}
}