{
  "type": "Feature",
  "properties": {
    "iso:country":"US",
    "sg:address":"5355 Avie Ln",
    "sg:city":"Beaumont",
    "sg:classifiers":[
        {
            "category":"Education",
            "subcategory":"School",
            "type":"Public Place"
        }
    ],
    "sg:phone":"+1 409 898 2070",
    "sg:postcode":"77708",
    "sg:province":"TX",
    "wof:name":"Family of Faith Christian",
    "wof:placetype":"venue"
},
  "geometry": {"coordinates":[-94.16389599999999,30.139709],"type":"Point"}
}