{
  "type": "Feature",
  "properties": {
    "iso:country":"US",
    "sg:address":"5210 I-35 S",
    "sg:city":"Austin",
    "sg:classifiers":[
        {
            "category":"Autos & Motor Vehicles",
            "subcategory":"Automobile Sales",
            "type":"Retail Goods"
        }
    ],
    "sg:phone":"+1 512 442 9333",
    "sg:postcode":"78745",
    "sg:province":"TX",
    "sg:tags":[
        "car"
    ],
    "wof:name":"Bill Munday's Texas South Point Chrysler, Dodge, Jeep Dealership",
    "wof:placetype":"venue"
},
  "geometry": {"coordinates":[-97.761887,30.204253],"type":"Point"}
}