{
  "type": "Feature",
  "properties": {
    "iso:country":"US",
    "sg:address":"1926 Laurel Oaks Dr",
    "sg:city":"Houston",
    "sg:classifiers":[
        {
            "category":"Banks & Credit Unions",
            "subcategory":"Investment Brokerage",
            "type":"Services"
        }
    ],
    "sg:phone":"+1 281 580 1080",
    "sg:postcode":"77014",
    "sg:province":"TX",
    "sg:tags":[
        "consultant",
        "planning",
        "financial"
    ],
    "wof:name":"American Express Financial Adv",
    "wof:placetype":"venue"
},
  "geometry": {"coordinates":[-95.44802199999999,29.968674],"type":"Point"}
}