{
  "type": "Feature",
  "properties": {
    "iso:country":"US",
    "sg:address":"6807 Spring Manor St",
    "sg:city":"San Antonio",
    "sg:classifiers":[
        {
            "category":"Professional",
            "subcategory":"Art Services",
            "type":"Services"
        }
    ],
    "sg:phone":"+1 210 641 9898",
    "sg:postcode":"78249",
    "sg:province":"TX",
    "sg:tags":[
        "commercial",
        "design"
    ],
    "wof:name":"Howie Designs",
    "wof:placetype":"venue"
},
  "geometry": {"coordinates":[-98.62244200000001,29.550104],"type":"Point"}
}