{
  "type": "Feature",
  "properties": {
    "iso:country":"US",
    "sg:address":"301 W Pearce St",
    "sg:city":"Baytown",
    "sg:classifiers":[
        {
            "category":"Real Estate",
            "subcategory":"Real Estate Operator",
            "type":"Services"
        }
    ],
    "sg:phone":"+1 281 428 1233",
    "sg:postcode":"77520",
    "sg:province":"TX",
    "sg:tags":[
        "building",
        "apartment"
    ],
    "wof:name":"Shady Creek Apartments",
    "wof:placetype":"venue"
},
  "geometry": {"coordinates":[-94.97097599999999,29.732377],"type":"Point"}
}