{
  "type": "Feature",
  "properties": {
    "iso:country":"US",
    "sg:address":"1200 Cedar Bayou Rd",
    "sg:city":"Baytown",
    "sg:classifiers":[
        {
            "category":"Building & Trades",
            "subcategory":"Construction",
            "type":"Services"
        }
    ],
    "sg:phone":"+1 281 837 1129",
    "sg:postcode":"77520",
    "sg:province":"TX",
    "sg:tags":[
        "system",
        "contractor",
        "air conditioning"
    ],
    "wof:name":"Derryberry's, L.P.",
    "wof:placetype":"venue"
},
  "geometry": {"coordinates":[-94.94989700000001,29.7498],"type":"Point"}
}