{
  "type": "Feature",
  "properties": {
    "iso:country":"US",
    "sg:address":"1401 S Broadway St",
    "sg:city":"Aspermont",
    "sg:classifiers":[
        {
            "category":"Wholesale",
            "subcategory":"Machinery & Supplies",
            "type":"Manufacturing & Wholesale Goods"
        }
    ],
    "sg:phone":"+1 940 989 3563",
    "sg:postcode":"79502",
    "sg:province":"TX",
    "sg:tags":[
        "field",
        "oil",
        "equipment"
    ],
    "wof:name":"KNOX Oil Field Supply Inc",
    "wof:placetype":"venue"
},
  "geometry": {"coordinates":[-100.227234,33.131457],"type":"Point"}
}