{
  "type": "Feature",
  "properties": {
    "iso:country":"US",
    "sg:address":"5845 S Padre Island Hwy",
    "sg:city":"Brownsville",
    "sg:classifiers":[
        {
            "category":"Wholesale",
            "subcategory":"Painting Supplies",
            "type":"Manufacturing & Wholesale Goods"
        }
    ],
    "sg:phone":"+1 956 838 5451",
    "sg:postcode":"78521",
    "sg:province":"TX",
    "wof:name":"Red Spot Paint & Varnish Co",
    "wof:placetype":"venue"
},
  "geometry": {"coordinates":[-97.447062,25.932112],"type":"Point"}
}