{
  "type": "Feature",
  "properties": {
    "iso:country":"US",
    "sg:address":"2400 Bayport Blvd",
    "sg:city":"Seabrook",
    "sg:classifiers":[
        {
            "category":"Restaurant",
            "type":"Food & Drink"
        }
    ],
    "sg:menulink":"http://www.allmenus.com/tx/southeast-harris/204438-sonic/menu/",
    "sg:phone":"+1 281 474 4031",
    "sg:postcode":"77586",
    "sg:province":"TX",
    "sg:tags":[
        "burger",
        "american"
    ],
    "wof:name":"Sonic",
    "wof:placetype":"venue"
},
  "geometry": {"coordinates":[-95.027078,29.573708],"type":"Point"}
}