{
  "type": "Feature",
  "properties": {
    "iso:country":"US",
    "sg:address":"1104 E Mulberry St",
    "sg:city":"Angleton",
    "sg:classifiers":[
        {
            "category":"Insurance",
            "subcategory":"Insurance Agent",
            "type":"Services"
        }
    ],
    "sg:phone":"+1 979 848 9800",
    "sg:postcode":"77515",
    "sg:province":"TX",
    "wof:name":"Insurance Plus Agencies",
    "wof:placetype":"venue"
},
  "geometry": {"coordinates":[-95.417923,29.169939],"type":"Point"}
}