{
  "type": "Feature",
  "properties": {
    "iso:country":"US",
    "sg:address":"4412 Southwest Blvd",
    "sg:city":"Fort Worth",
    "sg:classifiers":[
        {
            "category":"Professional",
            "subcategory":"Advertising",
            "type":"Services"
        }
    ],
    "sg:phone":"+1 817 569 8225",
    "sg:postcode":"76116",
    "sg:province":"TX",
    "sg:tags":[
        "agency",
        "gift"
    ],
    "wof:name":"Sunbelt Ceramics",
    "wof:placetype":"venue"
},
  "geometry": {"coordinates":[-97.437983,32.708315],"type":"Point"}
}