{
  "type": "Feature",
  "properties": {
    "iso:country":"US",
    "sg:address":"8314 Ridge Ter",
    "sg:city":"San Antonio",
    "sg:classifiers":[
        {
            "category":"Organizations",
            "subcategory":"Religious Organization",
            "type":"Services"
        }
    ],
    "sg:phone":"+1 210 681 0341",
    "sg:postcode":"78251",
    "sg:province":"TX",
    "wof:name":"MRS Adorn",
    "wof:placetype":"venue"
},
  "geometry": {"coordinates":[-98.660303,29.468637],"type":"Point"}
}