{
  "type": "Feature",
  "properties": {
    "iso:country":"US",
    "sg:address":"5201 S Colony Blvd",
    "sg:city":"The Colony",
    "sg:classifiers":[
        {
            "category":"Recreation",
            "type":"Entertainment"
        }
    ],
    "sg:phone":"+1 972 370 1400",
    "sg:postcode":"75056",
    "sg:province":"TX",
    "sg:tags":[
        "instruction",
        "gymnastic"
    ],
    "wof:name":"Colony Gymnastics & Dance Acad",
    "wof:placetype":"venue"
},
  "geometry": {"coordinates":[-96.87915099999999,33.084243],"type":"Point"}
}