{
  "type": "Feature",
  "properties": {
    "iso:country":"US",
    "sg:address":"453 Lewis St",
    "sg:city":"Shepherd",
    "sg:classifiers":[
        {
            "category":"Organizations",
            "subcategory":"Religious Organization",
            "type":"Services"
        }
    ],
    "sg:phone":"+1 936 628 6376",
    "sg:postcode":"77371",
    "sg:province":"TX",
    "wof:name":"Jesus Hes Alive Ministry",
    "wof:placetype":"venue"
},
  "geometry": {"coordinates":[-95.00024999999999,30.466654],"type":"Point"}
}