{
  "type": "Feature",
  "properties": {
    "iso:country":"US",
    "sg:address":"8620 Las Cruces Dr",
    "sg:city":"Laredo",
    "sg:classifiers":[
        {
            "category":"Freight",
            "type":"Transportation"
        }
    ],
    "sg:phone":"+1 956 724 5763",
    "sg:postcode":"78045",
    "sg:province":"TX",
    "sg:tags":[
        "operator",
        "trucking"
    ],
    "wof:name":"Melton Truck Lines Inc",
    "wof:placetype":"venue"
},
  "geometry": {"coordinates":[-99.498769,27.587393],"type":"Point"}
}