{
  "type": "Feature",
  "properties": {
    "iso:country":"US",
    "sg:address":"122 Shepherds Glen Rd",
    "sg:city":"Rockwall",
    "sg:classifiers":[
        {
            "category":"Professional",
            "subcategory":"Business Services",
            "type":"Services"
        }
    ],
    "sg:phone":"+1 972 772 5418",
    "sg:postcode":"75032",
    "sg:province":"TX",
    "wof:name":"Baumann Enterprises Inc",
    "wof:placetype":"venue"
},
  "geometry": {"coordinates":[-96.476623,32.868851],"type":"Point"}
}