{
  "type": "Feature",
  "properties": {
    "iso:country":"US",
    "sg:address":"11740 S Hausman Rd",
    "sg:city":"San Antonio",
    "sg:classifiers":[
        {
            "category":"Building & Trades",
            "subcategory":"Construction",
            "type":"Services"
        }
    ],
    "sg:phone":"+1 210 684 3695",
    "sg:postcode":"78249",
    "sg:province":"TX",
    "sg:tags":[
        "underground",
        "utility",
        "contractor"
    ],
    "wof:name":"A & L Underground Inc",
    "wof:placetype":"venue"
},
  "geometry": {"coordinates":[-98.655677,29.553387],"type":"Point"}
}