{
  "type": "Feature",
  "properties": {
    "iso:country":"US",
    "sg:address":"1500 W 3rd Ave",
    "sg:city":"Amarillo",
    "sg:classifiers":[
        {
            "category":"Building & Trades",
            "subcategory":"Construction",
            "type":"Services"
        }
    ],
    "sg:phone":"+1 806 373 6801",
    "sg:postcode":"79106",
    "sg:province":"TX",
    "sg:tags":[
        "contractor",
        "floor",
        "flooring",
        "covering"
    ],
    "wof:name":"Quality Carpets & Flooring",
    "wof:placetype":"venue"
},
  "geometry": {"coordinates":[-101.85404699999999,35.213023],"type":"Point"}
}