{
  "type": "Feature",
  "properties": {
    "iso:country":"US",
    "sg:address":"2222 E Oltorf St",
    "sg:city":"Austin",
    "sg:classifiers":[
        {
            "category":"Food & Beverages",
            "subcategory":"Groceries & Convenience Stores",
            "type":"Retail Goods"
        }
    ],
    "sg:phone":"+1 512 444 8429",
    "sg:postcode":"78741",
    "sg:province":"TX",
    "sg:tags":[
        "station",
        "gasoline"
    ],
    "wof:name":"Diamond Shamrock",
    "wof:placetype":"venue"
},
  "geometry": {"coordinates":[-97.73100700000001,30.22983],"type":"Point"}
}