{
  "type": "Feature",
  "properties": {
    "iso:country":"US",
    "sg:address":"3400 W Marshall Ave",
    "sg:city":"Longview",
    "sg:classifiers":[
        {
            "category":"Professional",
            "subcategory":"Business Services",
            "type":"Services"
        }
    ],
    "sg:phone":"+1 903 753 1751",
    "sg:postcode":"75604",
    "sg:province":"TX",
    "sg:tags":[
        "consultant",
        "coach"
    ],
    "wof:name":"Munn & Associates",
    "wof:placetype":"venue"
},
  "geometry": {"coordinates":[-94.79097,32.506882],"type":"Point"}
}