{
  "type": "Feature",
  "properties": {
    "iso:country":"US",
    "sg:address":"1000 E 41st St",
    "sg:city":"Austin",
    "sg:classifiers":[
        {
            "category":"Shopping",
            "type":"Retail Goods"
        }
    ],
    "sg:phone":"+1 512 419 0311",
    "sg:postcode":"78751",
    "sg:province":"TX",
    "sg:tags":[
        "merchandise",
        "animal"
    ],
    "wof:name":"Petco 482",
    "wof:placetype":"venue"
},
  "geometry": {"coordinates":[-97.719942,30.298744],"type":"Point"}
}