{
  "type": "Feature",
  "properties": {
    "iso:country":"US",
    "sg:address":"3313 Harbourtown",
    "sg:city":"Grand Prairie",
    "sg:classifiers":[
        {
            "category":"Shopping",
            "subcategory":"Catalog Store",
            "type":"Retail Goods"
        }
    ],
    "sg:phone":"+1 972 602 8673",
    "sg:postcode":"75052",
    "sg:province":"TX",
    "sg:tags":[
        "house",
        "mail"
    ],
    "wof:name":"Forster & Lloyd Corpporat",
    "wof:placetype":"venue"
},
  "geometry": {"coordinates":[-97.05596,32.690105],"type":"Point"}
}