{
  "type": "Feature",
  "properties": {
    "iso:country":"US",
    "sg:address":"5910 Lyons Ave",
    "sg:city":"Houston",
    "sg:classifiers":[
        {
            "category":"Food & Beverages",
            "subcategory":"Meat & Fish",
            "type":"Retail Goods"
        }
    ],
    "sg:phone":"+1 713 674 0064",
    "sg:postcode":"77020",
    "sg:province":"TX",
    "sg:tags":[
        "shop"
    ],
    "wof:name":"Burt's Meat Market & Cajun Foods",
    "wof:placetype":"venue"
},
  "geometry": {"coordinates":[-95.31120300000001,29.7764],"type":"Point"}
}