{
  "type": "Feature",
  "properties": {
    "iso:country":"US",
    "sg:address":"6446 FM 1488",
    "sg:city":"Magnolia",
    "sg:classifiers":[
        {
            "category":"Insurance",
            "subcategory":"Insurance Agent",
            "type":"Services"
        }
    ],
    "sg:phone":"+1 281 252 3276",
    "sg:postcode":"77384",
    "sg:province":"TX",
    "wof:name":"Brian Arceneaux Insurance",
    "wof:placetype":"venue"
},
  "geometry": {"coordinates":[-95.497304,30.231807],"type":"Point"}
}