{
  "type": "Feature",
  "properties": {
    "iso:country":"US",
    "sg:address":"3120 Harwell Lake Rd",
    "sg:city":"Weatherford",
    "sg:classifiers":[
        {
            "category":"Building & Trades",
            "subcategory":"Construction",
            "type":"Services"
        }
    ],
    "sg:phone":"+1 817 613 6416",
    "sg:postcode":"76088",
    "sg:province":"TX",
    "sg:tags":[
        "clearing",
        "land",
        "leveling"
    ],
    "wof:name":"Dobbs Excavation",
    "wof:placetype":"venue"
},
  "geometry": {"coordinates":[-97.85015199999999,32.862682],"type":"Point"}
}