{
  "type": "Feature",
  "properties": {
    "iso:country":"US",
    "sg:address":"2400 S Harrison St",
    "sg:city":"Amarillo",
    "sg:classifiers":[
        {
            "category":"Building & Trades",
            "subcategory":"Construction",
            "type":"Services"
        }
    ],
    "sg:phone":"+1 806 374 0924",
    "sg:postcode":"79109",
    "sg:province":"TX",
    "sg:tags":[
        "house"
    ],
    "wof:name":"George Thomas Renovators",
    "wof:placetype":"venue"
},
  "geometry": {"coordinates":[-101.843515,35.186505],"type":"Point"}
}