{
  "type": "Feature",
  "properties": {
    "iso:country":"US",
    "sg:address":"722 Front St",
    "sg:city":"Comfort",
    "sg:classifiers":[
        {
            "category":"Professional",
            "type":"Services"
        }
    ],
    "sg:phone":"+1 830 995 5576",
    "sg:postcode":"78013",
    "sg:province":"TX",
    "wof:name":"H20 Specialists",
    "wof:placetype":"venue"
},
  "geometry": {"coordinates":[-98.906868,29.968164],"type":"Point"}
}