{
  "type": "Feature",
  "properties": {
    "iso:country":"US",
    "sg:address":"411 Nita Ln",
    "sg:city":"Euless",
    "sg:classifiers":[
        {
            "category":"Communications",
            "subcategory":"Film & Video Production",
            "type":"Services"
        }
    ],
    "sg:phone":"+1 817 545 1482",
    "sg:postcode":"76040",
    "sg:province":"TX",
    "sg:tags":[
        "motion"
    ],
    "wof:name":"Sebastian Pictures",
    "wof:placetype":"venue"
},
  "geometry": {"coordinates":[-97.104535,32.833201],"type":"Point"}
}