{
  "type": "Feature",
  "properties": {
    "iso:country":"US",
    "sg:address":"8440 Walnut Hill Ln Ste 110",
    "sg:city":"Dallas",
    "sg:classifiers":[
        {
            "category":"Health Services",
            "subcategory":"Doctor",
            "type":"Services"
        }
    ],
    "sg:phone":"+1 214 265 7175",
    "sg:postcode":"75231",
    "sg:province":"TX",
    "sg:tags":[
        "podiatrist"
    ],
    "sg:website":"www.orthopedicspecialists.com",
    "wof:name":"Orthopedic Specialist",
    "wof:placetype":"venue"
},
  "geometry": {"coordinates":[-96.75748299999999,32.883242],"type":"Point"}
}