{
  "type": "Feature",
  "properties": {
    "iso:country":"US",
    "sg:address":"901 Hall Ave",
    "sg:city":"Littlefield",
    "sg:classifiers":[
        {
            "category":"Autos & Motor Vehicles",
            "subcategory":"Fuel & Gas Station",
            "type":"Retail Goods"
        }
    ],
    "sg:phone":"+1 806 385 5561",
    "sg:postcode":"79339",
    "sg:province":"TX",
    "sg:tags":[
        "station",
        "gasoline"
    ],
    "wof:name":"Jennings Conoco & Auto",
    "wof:placetype":"venue"
},
  "geometry": {"coordinates":[-102.32536399999999,33.917362],"type":"Point"}
}