{
  "type": "Feature",
  "properties": {
    "iso:country":"US",
    "sg:address":"1009 NW 7th St",
    "sg:city":"Grand Prairie",
    "sg:classifiers":[
        {
            "category":"Freight",
            "type":"Transportation"
        }
    ],
    "sg:phone":"+1 972 642 3805",
    "sg:postcode":"75050",
    "sg:province":"TX",
    "sg:tags":[
        "operator",
        "local",
        "trucking"
    ],
    "wof:name":"CNG Trucking Co",
    "wof:placetype":"venue"
},
  "geometry": {"coordinates":[-97.012265,32.755041],"type":"Point"}
}