{
  "type": "Feature",
  "properties": {
    "iso:country":"US",
    "sg:address":"1418 Brittmoore Rd",
    "sg:city":"Houston",
    "sg:classifiers":[
        {
            "category":"Wholesale",
            "subcategory":"Hardware",
            "type":"Manufacturing & Wholesale Goods"
        }
    ],
    "sg:phone":"+1 713 932 9852",
    "sg:postcode":"77043",
    "sg:province":"TX",
    "sg:tags":[
        "builder"
    ],
    "wof:name":"Maintenance Builders",
    "wof:placetype":"venue"
},
  "geometry": {"coordinates":[-95.569833,29.798035],"type":"Point"}
}