{
  "type": "Feature",
  "properties": {
    "iso:country":"US",
    "sg:address":"2613 S General Bruce Dr",
    "sg:city":"Temple",
    "sg:classifiers":[
        {
            "category":"Retail",
            "subcategory":"Auto Repair",
            "type":"Services"
        }
    ],
    "sg:phone":"+1 254 778 9609",
    "sg:postcode":"76504",
    "sg:province":"TX",
    "sg:tags":[
        "repairing",
        "automobile"
    ],
    "wof:name":"Slim Kotrla Auto Repair",
    "wof:placetype":"venue"
},
  "geometry": {"coordinates":[-97.373251,31.094594],"type":"Point"}
}