{
  "type": "Feature",
  "properties": {
    "iso:country":"US",
    "sg:address":"521 N Las Vegas Trl",
    "sg:city":"Fort Worth",
    "sg:classifiers":[
        {
            "category":"Building & Trades",
            "subcategory":"Plumbing",
            "type":"Services"
        }
    ],
    "sg:phone":"+1 817 246 2823",
    "sg:postcode":"76108",
    "sg:province":"TX",
    "sg:tags":[
        "contractor"
    ],
    "wof:name":"Terry Lynn Bantex",
    "wof:placetype":"venue"
},
  "geometry": {"coordinates":[-97.469004,32.766143],"type":"Point"}
}