{
  "type": "Feature",
  "properties": {
    "iso:country":"US",
    "sg:address":"303 Anderson St",
    "sg:city":"College Station",
    "sg:classifiers":[
        {
            "category":"Insurance",
            "subcategory":"Insurance Agent",
            "type":"Services"
        }
    ],
    "sg:phone":"+1 979 846 3369",
    "sg:postcode":"77840",
    "sg:province":"TX",
    "wof:name":"Jefferson-Pilot Life Ins Co",
    "wof:placetype":"venue"
},
  "geometry": {"coordinates":[-96.32464299999999,30.612033],"type":"Point"}
}