{
  "type": "Feature",
  "properties": {
    "iso:country":"US",
    "sg:address":"502 N Colorado St",
    "sg:city":"Whitney",
    "sg:classifiers":[
        {
            "category":"Organizations",
            "subcategory":"Religious Organization",
            "type":"Services"
        }
    ],
    "sg:phone":"+1 254 694 8689",
    "sg:postcode":"76692",
    "sg:province":"TX",
    "sg:tags":[
        "church"
    ],
    "sg:website":"www.kingmemorialumc.org",
    "wof:name":"Methodist Church",
    "wof:placetype":"venue"
},
  "geometry": {"coordinates":[-97.32246600000001,31.954603],"type":"Point"}
}