{
  "type": "Feature",
  "properties": {
    "iso:country":"US",
    "sg:address":"418 Grayson St",
    "sg:city":"Hutchins",
    "sg:classifiers":[
        {
            "category":"Professional",
            "subcategory":"Management & Consulting",
            "type":"Services"
        }
    ],
    "sg:phone":"+1 972 225 6525",
    "sg:postcode":"75141",
    "sg:province":"TX",
    "sg:tags":[
        "business"
    ],
    "wof:name":"Beckman Consulting",
    "wof:placetype":"venue"
},
  "geometry": {"coordinates":[-96.71666999999999,32.650494],"type":"Point"}
}