{
  "type": "Feature",
  "properties": {
    "iso:country":"US",
    "sg:address":"520 Atascocita Rd",
    "sg:city":"Humble",
    "sg:classifiers":[
        {
            "category":"Home & Garden",
            "subcategory":"Building Materials",
            "type":"Retail Goods"
        }
    ],
    "sg:phone":"+1 281 441 5126",
    "sg:postcode":"77396",
    "sg:province":"TX",
    "sg:tags":[
        "door"
    ],
    "wof:name":"Humble Garage Door Svc",
    "wof:placetype":"venue"
},
  "geometry": {"coordinates":[-95.260058,29.958698],"type":"Point"}
}