{
  "type": "Feature",
  "properties": {
    "iso:country":"US",
    "sg:address":"7718 Bellerive Dr",
    "sg:city":"Houston",
    "sg:classifiers":[
        {
            "category":"Restaurant",
            "type":"Food & Drink"
        }
    ],
    "sg:phone":"+1 281 499 4646",
    "sg:postcode":"77036",
    "sg:province":"TX",
    "sg:tags":[
        "eating"
    ],
    "wof:name":"New Uncle Tongs",
    "wof:placetype":"venue"
},
  "geometry": {"coordinates":[-95.524034,29.713677],"type":"Point"}
}