{
  "type": "Feature",
  "properties": {
    "iso:country":"US",
    "sg:address":"415 W Erwin St",
    "sg:city":"Tyler",
    "sg:classifiers":[
        {
            "category":"Banks & Credit Unions",
            "subcategory":"Bank",
            "type":"Services"
        }
    ],
    "sg:phone":"+1 903 593 8416",
    "sg:postcode":"75702",
    "sg:province":"TX",
    "sg:tags":[
        "loan"
    ],
    "wof:name":"Atlas Credit Co",
    "wof:placetype":"venue"
},
  "geometry": {"coordinates":[-95.304097,32.350817],"type":"Point"}
}