{
  "type": "Feature",
  "properties": {
    "iso:country":"US",
    "sg:address":"3058 Pine St",
    "sg:city":"Abilene",
    "sg:classifiers":[
        {
            "category":"Wholesale",
            "subcategory":"Motor Vehicles",
            "type":"Manufacturing & Wholesale Goods"
        }
    ],
    "sg:phone":"+1 325 677 7211",
    "sg:postcode":"79601",
    "sg:province":"TX",
    "wof:name":"Auto Brokers",
    "wof:placetype":"venue"
},
  "geometry": {"coordinates":[-99.73126499999999,32.487087],"type":"Point"}
}