{
  "type": "Feature",
  "properties": {
    "iso:country":"US",
    "sg:address":"8948 Chatsworth Dr",
    "sg:city":"Houston",
    "sg:classifiers":[
        {
            "category":"Professional",
            "subcategory":"Lawyer & Legal Services",
            "type":"Services"
        }
    ],
    "sg:phone":"+1 713 682 8882",
    "sg:postcode":"77024",
    "sg:province":"TX",
    "wof:name":"Marietta M Maxfield",
    "wof:placetype":"venue"
},
  "geometry": {"coordinates":[-95.46107600000001,29.780222],"type":"Point"}
}