{
  "type": "Feature",
  "properties": {
    "iso:country":"US",
    "sg:address":"2033 Mangum Rd",
    "sg:city":"Houston",
    "sg:classifiers":[
        {
            "category":"Personal",
            "subcategory":"Tattoo Parlor",
            "type":"Services"
        }
    ],
    "sg:phone":"+1 713 869 8282",
    "sg:postcode":"77092",
    "sg:province":"TX",
    "sg:tags":[
        "tattooing"
    ],
    "wof:name":"Another Extreme",
    "wof:placetype":"venue"
},
  "geometry": {"coordinates":[-95.458895,29.806264],"type":"Point"}
}