{
  "type": "Feature",
  "properties": {
    "iso:country":"US",
    "sg:address":"15134 Eagle Grove St",
    "sg:city":"San Antonio",
    "sg:classifiers":[
        {
            "category":"Autos & Motor Vehicles",
            "subcategory":"Auto Supplies",
            "type":"Retail Goods"
        }
    ],
    "sg:phone":"+1 210 494 2742",
    "sg:postcode":"78232",
    "sg:province":"TX",
    "wof:name":"Ev Communtech",
    "wof:placetype":"venue"
},
  "geometry": {"coordinates":[-98.457385,29.580718],"type":"Point"}
}