{
  "type": "Feature",
  "properties": {
    "iso:country":"US",
    "sg:address":"126 E Parker Rd",
    "sg:city":"Houston",
    "sg:classifiers":[
        {
            "category":"Personal",
            "subcategory":"Beauty Salon",
            "type":"Services"
        }
    ],
    "sg:phone":"+1 713 694 2350",
    "sg:postcode":"77076",
    "sg:province":"TX",
    "wof:name":"Karla's Beauty Salon",
    "wof:placetype":"venue"
},
  "geometry": {"coordinates":[-95.39688599999999,29.859555],"type":"Point"}
}