{
  "type": "Feature",
  "properties": {
    "iso:country":"US",
    "sg:address":"141 Canna Ln",
    "sg:city":"Lake Jackson",
    "sg:classifiers":[
        {
            "category":"Animal Shelter",
            "type":"Public Place"
        },
        {
            "category":"Shopping",
            "subcategory":"Pets & Pet Supplies",
            "type":"Retail Goods"
        }
    ],
    "sg:phone":"+1 979 285 2340",
    "sg:postcode":"77566",
    "sg:province":"TX",
    "sg:tags":[
        "store"
    ],
    "wof:name":"City of Lake Jackson",
    "wof:placetype":"venue"
},
  "geometry": {"coordinates":[-95.453017,29.686073],"type":"Point"}
}