{
  "type": "Feature",
  "properties": {
    "iso:country":"US",
    "sg:address":"25820 Boerne Stage Rd",
    "sg:city":"San Antonio",
    "sg:classifiers":[
        {
            "category":"Sports & Exercise",
            "subcategory":"Golf",
            "type":"Entertainment"
        }
    ],
    "sg:phone":"+1 210 698 5000",
    "sg:postcode":"78006",
    "sg:province":"TX",
    "sg:tags":[
        "course",
        "public"
    ],
    "wof:name":"Tourmaline Hills",
    "wof:placetype":"venue"
},
  "geometry": {"coordinates":[-98.67585200000001,29.685124],"type":"Point"}
}