{
  "type": "Feature",
  "properties": {
    "iso:country":"US",
    "sg:address":"491 Churchill Rd",
    "sg:city":"Fort Worth",
    "sg:classifiers":[
        {
            "category":"Personal",
            "subcategory":"Barber",
            "type":"Services"
        }
    ],
    "sg:phone":"+1 817 737 9935",
    "sg:postcode":"76114",
    "sg:province":"TX",
    "sg:tags":[
        "shop"
    ],
    "wof:name":"Phillip A Key Etux Barbar",
    "wof:placetype":"venue"
},
  "geometry": {"coordinates":[-97.390941,32.766241],"type":"Point"}
}