{
  "type": "Feature",
  "properties": {
    "iso:country":"US",
    "sg:address":"1208 S FM 51",
    "sg:city":"Decatur",
    "sg:classifiers":[
        {
            "category":"Shopping",
            "type":"Retail Goods"
        }
    ],
    "sg:phone":"+1 940 627 4900",
    "sg:postcode":"76234",
    "sg:province":"TX",
    "sg:tags":[
        "cellular",
        "merchandise",
        "telephone"
    ],
    "wof:name":"Cellular Warehouse",
    "wof:placetype":"venue"
},
  "geometry": {"coordinates":[-97.593763,33.227366],"type":"Point"}
}