{
  "type": "Feature",
  "properties": {
    "iso:country":"US",
    "sg:address":"520 S Dumas Ave",
    "sg:city":"Dumas",
    "sg:classifiers":[
        {
            "category":"Shopping",
            "subcategory":"Clothing, Apparel, & Fashions",
            "type":"Retail Goods"
        }
    ],
    "sg:phone":"+1 806 934 0673",
    "sg:postcode":"79029",
    "sg:province":"TX",
    "wof:name":"La Moda Boutique",
    "wof:placetype":"venue"
},
  "geometry": {"coordinates":[-101.97334600000001,35.860732],"type":"Point"}
}