{
  "type": "Feature",
  "properties": {
    "iso:country":"US",
    "sg:address":"2626 Park Row Ave",
    "sg:city":"Dallas",
    "sg:classifiers":[
        {
            "category":"Shopping",
            "subcategory":"Clothing, Apparel, & Fashions",
            "type":"Retail Goods"
        }
    ],
    "sg:phone":"+1 214 428 7063",
    "sg:postcode":"75215",
    "sg:province":"TX",
    "wof:name":"Dollies Bonnets Inc",
    "wof:placetype":"venue"
},
  "geometry": {"coordinates":[-96.770768,32.77055],"type":"Point"}
}