{
  "type": "Feature",
  "properties": {
    "iso:country":"US",
    "sg:address":"190 Moreland St",
    "sg:city":"Vidor",
    "sg:classifiers":[
        {
            "category":"Restaurant",
            "type":"Food & Drink"
        }
    ],
    "sg:phone":"+1 409 783 1900",
    "sg:postcode":"77662",
    "sg:province":"TX",
    "sg:tags":[
        "eating"
    ],
    "wof:name":"Accoladz",
    "wof:placetype":"venue"
},
  "geometry": {"coordinates":[-94.018146,30.119188],"type":"Point"}
}