{
  "type": "Feature",
  "properties": {
    "iso:country":"US",
    "sg:address":"4307 Angus Rd",
    "sg:city":"Odessa",
    "sg:classifiers":[
        {
            "category":"Real Estate",
            "subcategory":"Real Estate Operator",
            "type":"Services"
        }
    ],
    "sg:phone":"+1 432 366 7025",
    "sg:postcode":"79764",
    "sg:province":"TX",
    "sg:tags":[
        "mobile",
        "home",
        "site"
    ],
    "wof:name":"Williams Trailer Court",
    "wof:placetype":"venue"
},
  "geometry": {"coordinates":[-102.415809,31.878897],"type":"Point"}
}