{
  "type": "Feature",
  "properties": {
    "iso:country":"US",
    "sg:address":"382 Forest Ln",
    "sg:city":"Huntsville",
    "sg:classifiers":[
        {
            "category":"Utilities",
            "subcategory":"Telephone",
            "type":"Services"
        }
    ],
    "sg:phone":"+1 936 291 9574",
    "sg:postcode":"77340",
    "sg:province":"TX",
    "sg:tags":[
        "communications"
    ],
    "wof:name":"Wolftel Communications",
    "wof:placetype":"venue"
},
  "geometry": {"coordinates":[-95.59073100000001,30.697571],"type":"Point"}
}