{
  "type": "Feature",
  "properties": {
    "iso:country":"US",
    "sg:address":"3407 Haynie Ave",
    "sg:city":"Dallas",
    "sg:classifiers":[
        {
            "category":"Professional",
            "subcategory":"Lawyer & Legal Services",
            "type":"Services"
        }
    ],
    "sg:phone":"+1 214 526 4306",
    "sg:postcode":"75205",
    "sg:province":"TX",
    "sg:tags":[
        "attorney"
    ],
    "wof:name":"James C Tubb",
    "wof:placetype":"venue"
},
  "geometry": {"coordinates":[-96.789849,32.846047],"type":"Point"}
}