{
  "type": "Feature",
  "properties": {
    "iso:country":"US",
    "sg:address":"1706 Garth Dr",
    "sg:city":"Killeen",
    "sg:classifiers":[
        {
            "category":"Shopping",
            "type":"Retail Goods"
        }
    ],
    "sg:phone":"+1 254 526 5560",
    "sg:postcode":"76541",
    "sg:province":"TX",
    "sg:tags":[
        "merchandise"
    ],
    "wof:name":"M & R Macrame Etc",
    "wof:placetype":"venue"
},
  "geometry": {"coordinates":[-97.729849,31.132148],"type":"Point"}
}