{
  "type": "Feature",
  "properties": {
    "iso:country":"US",
    "sg:address":"3700 S Cooper St",
    "sg:city":"Arlington",
    "sg:classifiers":[
        {
            "category":"Restaurant",
            "type":"Food & Drink"
        }
    ],
    "sg:menulink":"http://www.allmenus.com/tx/arlington/215475-atlanta-bread-company/menu/",
    "sg:phone":"+1 817 557 4455",
    "sg:postcode":"76015",
    "sg:province":"TX",
    "sg:tags":[
        "american"
    ],
    "wof:name":"Atlanta Bread Company",
    "wof:placetype":"venue"
},
  "geometry": {"coordinates":[-97.132296,32.685846],"type":"Point"}
}