{
  "type": "Feature",
  "properties": {
    "iso:country":"US",
    "sg:address":"1408 Los Colinos Ct",
    "sg:city":"Graham",
    "sg:classifiers":[
        {
            "category":"Wholesale",
            "subcategory":"Farm Supplies",
            "type":"Manufacturing & Wholesale Goods"
        }
    ],
    "sg:phone":"+1 940 549 7833",
    "sg:postcode":"76450",
    "sg:province":"TX",
    "sg:tags":[
        "livestock"
    ],
    "wof:name":"Albert Hamlin",
    "wof:placetype":"venue"
},
  "geometry": {"coordinates":[-98.57260100000001,33.090138],"type":"Point"}
}