{
  "type": "Feature",
  "properties": {
    "iso:country":"US",
    "sg:address":"5202 Carew St",
    "sg:city":"Houston",
    "sg:classifiers":[
        {
            "category":"Building & Trades",
            "subcategory":"Cleaning & Sanitation",
            "type":"Services"
        }
    ],
    "sg:phone":"+1 713 665 6673",
    "sg:postcode":"77096",
    "sg:province":"TX",
    "sg:tags":[
        "maintenance"
    ],
    "wof:name":"Herbst Cleaning Services LLC",
    "wof:placetype":"venue"
},
  "geometry": {"coordinates":[-95.474923,29.688297],"type":"Point"}
}