{
  "type": "Feature",
  "properties": {
    "iso:country":"US",
    "sg:address":"1008 SW 10th Ave",
    "sg:city":"Amarillo",
    "sg:classifiers":[
        {
            "category":"Professional",
            "subcategory":"Lawyer & Legal Services",
            "type":"Services"
        }
    ],
    "sg:phone":"+1 806 373 5054",
    "sg:postcode":"79101",
    "sg:province":"TX",
    "sg:tags":[
        "attorney",
        "law",
        "estate",
        "family",
        "practice",
        "planning",
        "criminal",
        "bankruptcy"
    ],
    "wof:name":"Morales Jerry-Attorney at Law",
    "wof:placetype":"venue"
},
  "geometry": {"coordinates":[-101.847926,35.204871],"type":"Point"}
}