{
  "type": "Feature",
  "properties": {
    "iso:country":"US",
    "sg:address":"357 Belle Cir",
    "sg:city":"Aledo",
    "sg:classifiers":[
        {
            "category":"Banks & Credit Unions",
            "subcategory":"Financial Services",
            "type":"Services"
        }
    ],
    "sg:phone":"+1 817 441 7734",
    "sg:postcode":"76008",
    "sg:province":"TX",
    "sg:tags":[
        "management",
        "open",
        "investment"
    ],
    "wof:name":"Landlords Enterprises Inc",
    "wof:placetype":"venue"
},
  "geometry": {"coordinates":[-97.6358,32.721903],"type":"Point"}
}