{
  "type": "Feature",
  "properties": {
    "iso:country":"US",
    "sg:address":"1510 Rio Hondo Rd",
    "sg:city":"Harlingen",
    "sg:classifiers":[
        {
            "category":"Professional",
            "type":"Services"
        }
    ],
    "sg:phone":"+1 956 399 4174",
    "sg:postcode":"78550",
    "sg:province":"TX",
    "wof:name":"Muchos Mundos Inc",
    "wof:placetype":"venue"
},
  "geometry": {"coordinates":[-97.68021,26.212484],"type":"Point"}
}