{
  "type": "Feature",
  "properties": {
    "iso:country":"US",
    "sg:address":"138 Meadow Glen Dr",
    "sg:city":"San Antonio",
    "sg:classifiers":[
        {
            "category":"Building & Trades",
            "subcategory":"Construction",
            "type":"Services"
        }
    ],
    "sg:phone":"+1 210 673 1003",
    "sg:postcode":"78227",
    "sg:province":"TX",
    "sg:tags":[
        "repairing",
        "remodeling",
        "contractor"
    ],
    "wof:name":"DNI Houseware's",
    "wof:placetype":"venue"
},
  "geometry": {"coordinates":[-98.64231700000001,29.424768],"type":"Point"}
}