{
  "type": "Feature",
  "properties": {
    "iso:country":"US",
    "sg:address":"2300 W Wadley Ave",
    "sg:city":"Midland",
    "sg:classifiers":[
        {
            "category":"Personal",
            "subcategory":"Beauty Salon",
            "type":"Services"
        }
    ],
    "sg:phone":"+1 432 689 8022",
    "sg:postcode":"79705",
    "sg:province":"TX",
    "wof:name":"Ambiance-Hair & Nail Studio",
    "wof:placetype":"venue"
},
  "geometry": {"coordinates":[-102.109695,32.023356],"type":"Point"}
}