{
  "type": "Feature",
  "properties": {
    "iso:country":"US",
    "sg:address":"9813 Broadway",
    "sg:city":"San Antonio",
    "sg:classifiers":[
        {
            "category":"Real Estate",
            "subcategory":"Real Estate Agent",
            "type":"Services"
        }
    ],
    "sg:phone":"+1 210 828 3517",
    "sg:postcode":"78217",
    "sg:province":"TX",
    "wof:name":"Industrial Properties Corporat",
    "wof:placetype":"venue"
},
  "geometry": {"coordinates":[-98.45052,29.530778],"type":"Point"}
}