{
  "type": "Feature",
  "properties": {
    "iso:country":"US",
    "sg:address":"205 E Main St",
    "sg:city":"Johnson City",
    "sg:classifiers":[
        {
            "category":"Shopping",
            "subcategory":"Used Merchandise",
            "type":"Retail Goods"
        }
    ],
    "sg:phone":"+1 830 868 4422",
    "sg:postcode":"78636",
    "sg:province":"TX",
    "sg:tags":[
        "antique"
    ],
    "wof:name":"Five Angels Antiques",
    "wof:placetype":"venue"
},
  "geometry": {"coordinates":[-98.41085099999999,30.276806],"type":"Point"}
}