{
  "type": "Feature",
  "properties": {
    "iso:country":"US",
    "sg:address":"1821 Fort Worth Hwy",
    "sg:city":"Weatherford",
    "sg:classifiers":[
        {
            "category":"Retail",
            "subcategory":"Auto Repair",
            "type":"Services"
        }
    ],
    "sg:phone":"+1 817 594 0840",
    "sg:postcode":"76086",
    "sg:province":"TX",
    "sg:tags":[
        "body",
        "painting",
        "repairing",
        "automobile"
    ],
    "wof:name":"Brooks Automotive Rebuild",
    "wof:placetype":"venue"
},
  "geometry": {"coordinates":[-97.756083,32.756922],"type":"Point"}
}