{
  "type": "Feature",
  "properties": {
    "iso:country":"US",
    "sg:address":"1664 Keller Pkwy",
    "sg:city":"Keller",
    "sg:classifiers":[
        {
            "category":"Mining & Drilling",
            "type":"Manufacturing & Wholesale Goods"
        }
    ],
    "sg:phone":"+1 817 337 0032",
    "sg:postcode":"76248",
    "sg:province":"TX",
    "sg:tags":[
        "field"
    ],
    "wof:name":"Tiorco Inc",
    "wof:placetype":"venue"
},
  "geometry": {"coordinates":[-97.21335500000001,32.934452],"type":"Point"}
}