{
  "type": "Feature",
  "properties": {
    "iso:country":"US",
    "sg:address":"2500 Mustang Dr",
    "sg:city":"Grapevine",
    "sg:classifiers":[
        {
            "category":"Building & Trades",
            "subcategory":"Landscaping Services",
            "type":"Services"
        }
    ],
    "sg:phone":"+1 817 488 1221",
    "sg:postcode":"76051",
    "sg:province":"TX",
    "wof:name":"Domingos Lawn Service",
    "wof:placetype":"venue"
},
  "geometry": {"coordinates":[-97.104625,32.92007],"type":"Point"}
}