{
  "type": "Feature",
  "properties": {
    "iso:country":"US",
    "sg:address":"7227 Crooked Oak Dr",
    "sg:city":"Dallas",
    "sg:classifiers":[
        {
            "category":"Professional",
            "subcategory":"Computer Services",
            "type":"Services"
        }
    ],
    "sg:phone":"+1 972 250 3811",
    "sg:postcode":"75248",
    "sg:province":"TX",
    "sg:tags":[
        "prepackaged",
        "software"
    ],
    "wof:name":"Universal Developing Systems",
    "wof:placetype":"venue"
},
  "geometry": {"coordinates":[-96.779269,32.977371],"type":"Point"}
}