{
  "type": "Feature",
  "properties": {
    "iso:country":"US",
    "sg:address":"31407 Falling Shadows Dr",
    "sg:city":"Bulverde",
    "sg:classifiers":[
        {
            "category":"Travel",
            "subcategory":"Travel Agent",
            "type":"Entertainment"
        }
    ],
    "sg:phone":"+1 830 980 5527",
    "sg:postcode":"78163",
    "sg:province":"TX",
    "sg:tags":[
        "operator",
        "tour"
    ],
    "wof:name":"Hill Country Wine Tours",
    "wof:placetype":"venue"
},
  "geometry": {"coordinates":[-98.395329,29.758716],"type":"Point"}
}