{
  "type": "Feature",
  "properties": {
    "iso:country":"US",
    "sg:address":"5714 W Gulf Bank Rd",
    "sg:city":"Houston",
    "sg:classifiers":[
        {
            "category":"Organizations",
            "subcategory":"Religious Organization",
            "type":"Services"
        }
    ],
    "sg:phone":"+1 281 847 4017",
    "sg:postcode":"77088",
    "sg:province":"TX",
    "wof:name":"New Faith Community Cente",
    "wof:placetype":"venue"
},
  "geometry": {"coordinates":[-95.47815799999999,29.884906],"type":"Point"}
}