{
  "type": "Feature",
  "properties": {
    "iso:country":"US",
    "sg:address":"10610 Nobility Dr",
    "sg:city":"Houston",
    "sg:classifiers":[
        {
            "category":"Shopping",
            "subcategory":"Gifts & Souvenirs",
            "type":"Retail Goods"
        }
    ],
    "sg:phone":"+1 281 561 6222",
    "sg:postcode":"77099",
    "sg:province":"TX",
    "sg:tags":[
        "shop"
    ],
    "wof:name":"Cal Cal Creations",
    "wof:placetype":"venue"
},
  "geometry": {"coordinates":[-95.58694300000001,29.664046],"type":"Point"}
}