{
  "type": "Feature",
  "properties": {
    "iso:country":"US",
    "sg:address":"3838 S Franklin St",
    "sg:city":"Dallas",
    "sg:classifiers":[
        {
            "category":"Professional",
            "subcategory":"Business Services",
            "type":"Services"
        }
    ],
    "sg:phone":"+1 214 333 9499",
    "sg:postcode":"75233",
    "sg:province":"TX",
    "wof:name":"Smith Russell Lexis Nexis",
    "wof:placetype":"venue"
},
  "geometry": {"coordinates":[-96.86007499999999,32.696455],"type":"Point"}
}