{
  "type": "Feature",
  "properties": {
    "iso:country":"US",
    "sg:address":"5012 Sharp St",
    "sg:city":"Dallas",
    "sg:classifiers":[
        {
            "category":"Education",
            "subcategory":"Junior College",
            "type":"Public Place"
        }
    ],
    "sg:phone":"+1 214 905 1457",
    "sg:postcode":"75247",
    "sg:province":"TX",
    "sg:tags":[
        "doll"
    ],
    "wof:name":"Dallas Doll House",
    "wof:placetype":"venue"
},
  "geometry": {"coordinates":[-96.871685,32.808433],"type":"Point"}
}