{
  "type": "Feature",
  "properties": {
    "iso:country":"US",
    "sg:address":"132 E Lamar St",
    "sg:city":"Jasper",
    "sg:classifiers":[
        {
            "category":"Real Estate",
            "subcategory":"Real Estate Services",
            "type":"Services"
        }
    ],
    "sg:phone":"+1 409 384 2571",
    "sg:postcode":"75951",
    "sg:province":"TX",
    "sg:tags":[
        "company",
        "title"
    ],
    "wof:name":"Garland Smith Abstract Co",
    "wof:placetype":"venue"
},
  "geometry": {"coordinates":[-94.000244,30.921905],"type":"Point"}
}