{
  "type": "Feature",
  "properties": {
    "iso:country":"US",
    "sg:address":"109 W Ave G",
    "sg:city":"Temple",
    "sg:classifiers":[
        {
            "category":"Shopping",
            "subcategory":"Music",
            "type":"Retail Goods"
        }
    ],
    "sg:phone":"+1 254 773 4986",
    "sg:postcode":"76504",
    "sg:province":"TX",
    "sg:tags":[
        "compact",
        "record",
        "disc",
        "tape"
    ],
    "wof:name":"C & C Tapes & Cd's",
    "wof:placetype":"venue"
},
  "geometry": {"coordinates":[-97.34569999999999,31.090125],"type":"Point"}
}