{
  "type": "Feature",
  "properties": {
    "iso:country":"US",
    "sg:address":"2329 Glencrest Dr",
    "sg:city":"Fort Worth",
    "sg:classifiers":[
        {
            "category":"Professional",
            "subcategory":"Computer Services",
            "type":"Services"
        }
    ],
    "sg:phone":"+1 817 784 1530",
    "sg:postcode":"76119",
    "sg:province":"TX",
    "sg:tags":[
        "consulting",
        "network",
        "related"
    ],
    "wof:name":"Intellectkey Systems",
    "wof:placetype":"venue"
},
  "geometry": {"coordinates":[-97.29738399999999,32.695899],"type":"Point"}
}