{
  "type": "Feature",
  "properties": {
    "iso:country":"US",
    "sg:address":"3601 S Shiloh Rd",
    "sg:city":"Garland",
    "sg:classifiers":[
        {
            "category":"Retail",
            "subcategory":"Auto Rental",
            "type":"Services"
        }
    ],
    "sg:phone":"+1 972 271 0801",
    "sg:postcode":"75041",
    "sg:province":"TX",
    "sg:tags":[
        "passenger",
        "car"
    ],
    "wof:name":"Hertz",
    "wof:placetype":"venue"
},
  "geometry": {"coordinates":[-96.665648,32.874232],"type":"Point"}
}