{
  "type": "Feature",
  "properties": {
    "iso:country":"US",
    "sg:address":"7715 Highway 6 S",
    "sg:city":"Houston",
    "sg:classifiers":[
        {
            "category":"Manufacturing",
            "subcategory":"Rubber & Plastics",
            "type":"Manufacturing & Wholesale Goods"
        },
        {
            "category":"Autos & Motor Vehicles",
            "subcategory":"Auto Supplies",
            "type":"Retail Goods"
        },
        {
            "category":"Retail",
            "subcategory":"Auto Repair",
            "type":"Services"
        }
    ],
    "sg:phone":"+1 281 568 4747",
    "sg:postcode":"77083",
    "sg:province":"TX",
    "sg:tags":[
        "recap",
        "retread",
        "tires-wholesale",
        "tire",
        "manufacturer"
    ],
    "sg:website":"http://www.coopertire.com/html/",
    "wof:name":"Cartronix #3",
    "wof:placetype":"venue"
},
  "geometry": {"coordinates":[-95.643799,29.694633],"type":"Point"}
}