{
  "type": "Feature",
  "properties": {
    "iso:country":"US",
    "sg:address":"1313 Ferndale Ave",
    "sg:city":"Dallas",
    "sg:classifiers":[
        {
            "category":"Building & Trades",
            "subcategory":"Pest Control",
            "type":"Services"
        }
    ],
    "sg:phone":"+1 214 942 4100",
    "sg:postcode":"75224",
    "sg:province":"TX",
    "wof:name":"Samples Exterminators",
    "wof:placetype":"venue"
},
  "geometry": {"coordinates":[-96.84449499999999,32.726251],"type":"Point"}
}