{
  "type": "Feature",
  "properties": {
    "iso:country":"US",
    "sg:address":"1126 Bandera Rd",
    "sg:city":"San Antonio",
    "sg:classifiers":[
        {
            "category":"Shopping",
            "subcategory":"Computers & Home Electronics",
            "type":"Retail Goods"
        }
    ],
    "sg:phone":"+1 210 433 8544",
    "sg:postcode":"78228",
    "sg:province":"TX",
    "sg:tags":[
        "equipment",
        "dealer"
    ],
    "wof:name":"Computer TV Repair",
    "wof:placetype":"venue"
},
  "geometry": {"coordinates":[-98.56081,29.461686],"type":"Point"}
}