{
  "type": "Feature",
  "properties": {
    "iso:country":"US",
    "sg:address":"1050 Vigortone Dr",
    "sg:city":"Weatherford",
    "sg:classifiers":[
        {
            "category":"Wholesale",
            "subcategory":"Farm Supplies",
            "type":"Manufacturing & Wholesale Goods"
        }
    ],
    "sg:phone":"+1 817 594 9628",
    "sg:postcode":"76086",
    "sg:province":"TX",
    "sg:tags":[
        "feed"
    ],
    "sg:website":"www.vigortone.com",
    "wof:name":"Vigortone Ag Products",
    "wof:placetype":"venue"
},
  "geometry": {"coordinates":[-97.812293,32.778777],"type":"Point"}
}