{
  "type": "Feature",
  "properties": {
    "iso:country":"US",
    "sg:address":"711 W Broad St",
    "sg:city":"Forney",
    "sg:classifiers":[
        {
            "category":"Building & Trades",
            "subcategory":"Electrical",
            "type":"Services"
        }
    ],
    "sg:phone":"+1 972 288 8041",
    "sg:postcode":"75126",
    "sg:province":"TX",
    "sg:tags":[
        "electric",
        "contractor"
    ],
    "sg:website":"www.intexelectric.com",
    "wof:name":"Intex Electrical Contractors",
    "wof:placetype":"venue"
},
  "geometry": {"coordinates":[-96.477385,32.75765],"type":"Point"}
}