{
  "type": "Feature",
  "properties": {
    "iso:country":"US",
    "sg:address":"4601 Fairview Dr",
    "sg:city":"Austin",
    "sg:classifiers":[
        {
            "category":"Government",
            "subcategory":"Office",
            "type":"Public Place"
        }
    ],
    "sg:phone":"+1 512 459 7486",
    "sg:postcode":"78731",
    "sg:province":"TX",
    "wof:name":"United States Government",
    "wof:placetype":"venue"
},
  "geometry": {"coordinates":[-97.760165,30.32735],"type":"Point"}
}