{
  "type": "Feature",
  "properties": {
    "iso:country":"US",
    "sg:address":"908 Lakeshore Blvd",
    "sg:city":"Little Elm",
    "sg:classifiers":[
        {
            "category":"Building & Trades",
            "subcategory":"Construction",
            "type":"Services"
        }
    ],
    "sg:phone":"+1 972 292 2588",
    "sg:postcode":"75068",
    "sg:province":"TX",
    "sg:tags":[
        "contractor"
    ],
    "wof:name":"American Dream Cleaning Team",
    "wof:placetype":"venue"
},
  "geometry": {"coordinates":[-96.99947899999999,33.189],"type":"Point"}
}