{
  "type": "Feature",
  "properties": {
    "iso:country":"US",
    "sg:address":"1601 Rio Grande St",
    "sg:city":"Austin",
    "sg:classifiers":[
        {
            "category":"Education",
            "subcategory":"College",
            "type":"Public Place"
        }
    ],
    "sg:phone":"+1 512 542 9525",
    "sg:postcode":"78701",
    "sg:province":"TX",
    "sg:tags":[
        "academic",
        "school"
    ],
    "wof:name":"U T Medical Branch-Austin",
    "wof:placetype":"venue"
},
  "geometry": {"coordinates":[-97.74555599999999,30.28069],"type":"Point"}
}