{
  "type": "Feature",
  "properties": {
    "iso:country":"US",
    "sg:address":"3333 Darilek Rd",
    "sg:city":"Flatonia",
    "sg:classifiers":[
        {
            "category":"Professional",
            "type":"Services"
        }
    ],
    "sg:phone":"+1 361 865 3769",
    "sg:postcode":"78941",
    "sg:province":"TX",
    "wof:name":"Ruth Flores",
    "wof:placetype":"venue"
},
  "geometry": {"coordinates":[-97.05673400000001,29.636702],"type":"Point"}
}