{
  "type": "Feature",
  "properties": {
    "iso:country":"US",
    "sg:address":"3432 34th St",
    "sg:city":"Lubbock",
    "sg:classifiers":[
        {
            "category":"Shopping",
            "subcategory":"Clothing, Apparel, & Fashions",
            "type":"Retail Goods"
        }
    ],
    "sg:phone":"+1 806 797 2773",
    "sg:postcode":"79410",
    "sg:province":"TX",
    "wof:name":"Colorful Creations Embroidery",
    "wof:placetype":"venue"
},
  "geometry": {"coordinates":[-101.889354,33.56334],"type":"Point"}
}