{
  "type": "Feature",
  "properties": {
    "iso:country":"US",
    "sg:address":"2610 Barksdale Dr",
    "sg:city":"Big Spring",
    "sg:classifiers":[
        {
            "category":"Real Estate",
            "subcategory":"Real Estate Agent",
            "type":"Services"
        }
    ],
    "sg:phone":"+1 432 714 4910",
    "sg:postcode":"79720",
    "sg:province":"TX",
    "wof:name":"Bis Spring McDonald Realty",
    "wof:placetype":"venue"
},
  "geometry": {"coordinates":[-101.500666,32.221932],"type":"Point"}
}