{
  "type": "Feature",
  "properties": {
    "iso:country":"US",
    "sg:address":"1320 S Elm St",
    "sg:city":"Kemp",
    "sg:classifiers":[
        {
            "category":"Place Of Worship",
            "subcategory":"Church",
            "type":"Public Place"
        },
        {
            "category":"Place Of Worship",
            "type":"Public Place"
        }
    ],
    "sg:phone":"+1 903 498 4971",
    "sg:postcode":"75143",
    "sg:province":"TX",
    "sg:tags":[
        "churches-baptist-general",
        "churches-baptist"
    ],
    "wof:name":"First Baptist Church Of Kemp",
    "wof:placetype":"venue"
},
  "geometry": {"coordinates":[-96.218504,32.429885],"type":"Point"}
}