{
  "type": "Feature",
  "properties": {
    "iso:country":"US",
    "sg:address":"12826 Veterans Memorial Dr",
    "sg:city":"Houston",
    "sg:classifiers":[
        {
            "category":"Autos & Motor Vehicles",
            "subcategory":"Automobile Sales",
            "type":"Retail Goods"
        }
    ],
    "sg:phone":"+1 281 587 2160",
    "sg:postcode":"77014",
    "sg:province":"TX",
    "sg:tags":[
        "car",
        "dealer"
    ],
    "wof:name":"Houston's Best Auto Sales",
    "wof:placetype":"venue"
},
  "geometry": {"coordinates":[-95.487182,29.972898],"type":"Point"}
}