{
  "type": "Feature",
  "properties": {
    "iso:country":"US",
    "sg:address":"14643 Dallas Pkwy Ste 570",
    "sg:city":"Dallas",
    "sg:classifiers":[
        {
            "category":"Banks & Credit Unions",
            "subcategory":"Investment Brokerage",
            "type":"Services"
        }
    ],
    "sg:phone":"+1 214 265 9400",
    "sg:postcode":"75254",
    "sg:province":"TX",
    "sg:tags":[
        "investing"
    ],
    "wof:name":"Shamrock Asset Management Llc",
    "wof:placetype":"venue"
},
  "geometry": {"coordinates":[-96.823808,32.94459],"type":"Point"}
}