{
  "type": "Feature",
  "properties": {
    "iso:country":"US",
    "sg:address":"515 Congress Ave",
    "sg:city":"Austin",
    "sg:classifiers":[
        {
            "category":"Professional",
            "subcategory":"Lawyer & Legal Services",
            "type":"Services"
        }
    ],
    "sg:phone":"+1 512 480 5755",
    "sg:postcode":"78701",
    "sg:province":"TX",
    "sg:tags":[
        "attorney"
    ],
    "wof:name":"Grace Doughery",
    "wof:placetype":"venue"
},
  "geometry": {"coordinates":[-97.742786,30.267906],"type":"Point"}
}