{
  "type": "Feature",
  "properties": {
    "iso:country":"US",
    "sg:address":"502 N 1st St",
    "sg:city":"Carrizo Springs",
    "sg:classifiers":[
        {
            "category":"Restaurant",
            "type":"Food & Drink"
        }
    ],
    "sg:menulink":"http://www.allmenus.com/tx/carrizo-springs/203783-sonic/menu/",
    "sg:phone":"+1 830 876 3535",
    "sg:postcode":"78834",
    "sg:province":"TX",
    "sg:tags":[
        "burger",
        "american"
    ],
    "wof:name":"Sonic",
    "wof:placetype":"venue"
},
  "geometry": {"coordinates":[-99.85604499999999,28.524048],"type":"Point"}
}