{
  "type": "Feature",
  "properties": {
    "iso:country":"US",
    "sg:address":"2215 Grand Avenue Pkwy",
    "sg:city":"Austin",
    "sg:classifiers":[
        {
            "category":"Professional",
            "type":"Services"
        }
    ],
    "sg:phone":"+1 512 251 1401",
    "sg:postcode":"78728",
    "sg:province":"TX",
    "sg:tags":[
        "establishment"
    ],
    "wof:name":"Envirotech Measurements",
    "wof:placetype":"venue"
},
  "geometry": {"coordinates":[-97.67733800000001,30.458039],"type":"Point"}
}