{
  "type": "Feature",
  "properties": {
    "iso:country":"US",
    "sg:address":"3402 Montana Ave",
    "sg:city":"El Paso",
    "sg:classifiers":[
        {
            "category":"Professional",
            "subcategory":"Lawyer & Legal Services",
            "type":"Services"
        }
    ],
    "sg:phone":"+1 915 566 5000",
    "sg:postcode":"79903",
    "sg:province":"TX",
    "sg:tags":[
        "attorney"
    ],
    "wof:name":"Juan Carlos Garay",
    "wof:placetype":"venue"
},
  "geometry": {"coordinates":[-106.452378,31.783618],"type":"Point"}
}