{
  "type": "Feature",
  "properties": {
    "iso:country":"US",
    "sg:address":"1107 Shaw St",
    "sg:city":"Quanah",
    "sg:classifiers":[
        {
            "category":"Personal",
            "subcategory":"Beauty Salon",
            "type":"Services"
        }
    ],
    "sg:phone":"+1 940 663 5202",
    "sg:postcode":"79252",
    "sg:province":"TX",
    "sg:tags":[
        "shop"
    ],
    "wof:name":"Bushwackers",
    "wof:placetype":"venue"
},
  "geometry": {"coordinates":[-99.74728500000001,34.290685],"type":"Point"}
}