{
  "type": "Feature",
  "properties": {
    "iso:country":"US",
    "sg:address":"200 Stadium Dr",
    "sg:city":"Seymour",
    "sg:classifiers":[
        {
            "category":"Health Services",
            "subcategory":"Hospital",
            "type":"Services"
        }
    ],
    "sg:phone":"+1 940 888 5572",
    "sg:postcode":"76380",
    "sg:province":"TX",
    "wof:name":"Seymour Hospital",
    "wof:placetype":"venue"
},
  "geometry": {"coordinates":[-99.24705400000001,33.592993],"type":"Point"}
}