{
  "type": "Feature",
  "properties": {
    "iso:country":"US",
    "sg:address":"1105 Amur St",
    "sg:city":"Mesquite",
    "sg:classifiers":[
        {
            "category":"Real Estate",
            "subcategory":"Real Estate Agent",
            "type":"Services"
        }
    ],
    "sg:phone":"+1 972 270 5068",
    "sg:postcode":"75150",
    "sg:province":"TX",
    "wof:name":"Weed Property Management Co",
    "wof:placetype":"venue"
},
  "geometry": {"coordinates":[-96.614047,32.820236],"type":"Point"}
}