{
  "type": "Feature",
  "properties": {
    "iso:country":"US",
    "sg:address":"5900 N Braeswood Blvd",
    "sg:city":"Houston",
    "sg:classifiers":[
        {
            "category":"Wholesale",
            "subcategory":"Electrical",
            "type":"Manufacturing & Wholesale Goods"
        }
    ],
    "sg:phone":"+1 713 240 4434",
    "sg:postcode":"77074",
    "sg:province":"TX",
    "sg:tags":[
        "television"
    ],
    "wof:name":"Icu Solutions",
    "wof:placetype":"venue"
},
  "geometry": {"coordinates":[-95.49747499999999,29.679299],"type":"Point"}
}