{
  "type": "Feature",
  "properties": {
    "iso:country":"US",
    "sg:address":"8541 West Fwy",
    "sg:city":"Fort Worth",
    "sg:classifiers":[
        {
            "category":"Autos & Motor Vehicles",
            "subcategory":"Fuel & Gas Station",
            "type":"Retail Goods"
        }
    ],
    "sg:phone":"+1 817 244 8387",
    "sg:postcode":"76116",
    "sg:province":"TX",
    "sg:tags":[
        "oil"
    ],
    "wof:name":"Shell Food Mart",
    "wof:placetype":"venue"
},
  "geometry": {"coordinates":[-97.467984,32.737738],"type":"Point"}
}