{
  "type": "Feature",
  "properties": {
    "iso:country":"US",
    "sg:address":"3617 Devon Ct",
    "sg:city":"Bedford",
    "sg:classifiers":[
        {
            "category":"Professional",
            "subcategory":"Management & Consulting",
            "type":"Services"
        }
    ],
    "sg:phone":"+1 817 581 4254",
    "sg:postcode":"76021",
    "sg:province":"TX",
    "wof:name":"Thomas A Knittle",
    "wof:placetype":"venue"
},
  "geometry": {"coordinates":[-97.149548,32.863893],"type":"Point"}
}