{
  "type": "Feature",
  "properties": {
    "iso:country":"US",
    "sg:address":"1743 Bandera Rd",
    "sg:city":"San Antonio",
    "sg:classifiers":[
        {
            "category":"Restaurant",
            "type":"Food & Drink"
        }
    ],
    "sg:phone":"+1 210 432 2955",
    "sg:postcode":"78228",
    "sg:province":"TX",
    "sg:tags":[
        "eating"
    ],
    "wof:name":"Totis Cafe & Bakery",
    "wof:placetype":"venue"
},
  "geometry": {"coordinates":[-98.572326,29.470194],"type":"Point"}
}