{
  "type": "Feature",
  "properties": {
    "iso:country":"US",
    "sg:address":"321 N Creek Ln",
    "sg:city":"Temple",
    "sg:classifiers":[
        {
            "category":"Professional",
            "type":"Services"
        }
    ],
    "sg:phone":"+1 254 791 8653",
    "sg:postcode":"76504",
    "sg:province":"TX",
    "wof:name":"Patient Services Exam",
    "wof:placetype":"venue"
},
  "geometry": {"coordinates":[-97.375894,31.110788],"type":"Point"}
}