{
  "type": "Feature",
  "properties": {
    "iso:country":"US",
    "sg:address":"10611 Research Blvd",
    "sg:city":"Austin",
    "sg:classifiers":[
        {
            "category":"Utilities",
            "subcategory":"Mobile Phone",
            "type":"Services"
        }
    ],
    "sg:phone":"+1 512 447 4659",
    "sg:postcode":"78759",
    "sg:province":"TX",
    "sg:tags":[
        "telephone",
        "cellular"
    ],
    "wof:name":"Pinky's Wireless",
    "wof:placetype":"venue"
},
  "geometry": {"coordinates":[-97.74551599999999,30.399334],"type":"Point"}
}