{
  "type": "Feature",
  "properties": {
    "iso:country":"US",
    "sg:address":"4615 W Commerce St",
    "sg:city":"San Antonio",
    "sg:classifiers":[
        {
            "category":"Insurance",
            "subcategory":"Insurance Agent",
            "type":"Services"
        }
    ],
    "sg:phone":"+1 210 436 4366",
    "sg:postcode":"78237",
    "sg:province":"TX",
    "wof:name":"Payless Auto Insurance Agency",
    "wof:placetype":"venue"
},
  "geometry": {"coordinates":[-98.553878,29.430805],"type":"Point"}
}