{
  "type": "Feature",
  "properties": {
    "iso:country":"US",
    "sg:address":"5201 Blue Mound Rd",
    "sg:city":"Fort Worth",
    "sg:classifiers":[
        {
            "category":"Wholesale",
            "subcategory":"Groceries",
            "type":"Manufacturing & Wholesale Goods"
        }
    ],
    "sg:phone":"+1 817 625 4101",
    "sg:postcode":"76106",
    "sg:province":"TX",
    "sg:tags":[
        "drink",
        "soft"
    ],
    "wof:name":"Pepsico",
    "wof:placetype":"venue"
},
  "geometry": {"coordinates":[-97.34281300000001,32.825904],"type":"Point"}
}