{
  "type": "Feature",
  "properties": {
    "iso:country":"US",
    "sg:address":"315 W Pleasant St",
    "sg:city":"Mt Pleasant",
    "sg:classifiers":[
        {
            "category":"Shopping",
            "subcategory":"Stationery & Office Supplies",
            "type":"Retail Goods"
        }
    ],
    "sg:phone":"+1 903 572 4447",
    "sg:postcode":"75455",
    "sg:province":"TX",
    "wof:name":"Office Products Of East Texas",
    "wof:placetype":"venue"
},
  "geometry": {"coordinates":[-94.970962,33.143595],"type":"Point"}
}