{
  "type": "Feature",
  "properties": {
    "iso:country":"US",
    "sg:address":"507 Lubbock Rd",
    "sg:city":"Brownfield",
    "sg:classifiers":[
        {
            "category":"Restaurant",
            "type":"Food & Drink"
        }
    ],
    "sg:menulink":"http://www.allmenus.com/tx/brownfield/203762-sonic/menu/",
    "sg:phone":"+1 806 637 7703",
    "sg:postcode":"79316",
    "sg:province":"TX",
    "sg:tags":[
        "burger",
        "american"
    ],
    "wof:name":"Sonic",
    "wof:placetype":"venue"
},
  "geometry": {"coordinates":[-102.274237,33.183459],"type":"Point"}
}