{
  "type": "Feature",
  "properties": {
    "iso:country":"US",
    "sg:address":"1515 Lloyds Hall Ct",
    "sg:city":"Mansfield",
    "sg:classifiers":[
        {
            "category":"Professional",
            "type":"Services"
        }
    ],
    "sg:phone":"+1 817 453 1265",
    "sg:postcode":"76063",
    "sg:province":"TX",
    "wof:name":"Mono-Pull LLC",
    "wof:placetype":"venue"
},
  "geometry": {"coordinates":[-97.11135,32.591589],"type":"Point"}
}