{
  "type": "Feature",
  "properties": {
    "iso:country":"US",
    "sg:address":"7011 Marvin D Love Fwy",
    "sg:city":"Dallas",
    "sg:classifiers":[
        {
            "category":"Freight",
            "type":"Transportation"
        }
    ],
    "sg:phone":"+1 214 337 8444",
    "sg:postcode":"75237",
    "sg:province":"TX",
    "sg:tags":[
        "commercial",
        "storage"
    ],
    "wof:name":"Alamo Self Storage",
    "wof:placetype":"venue"
},
  "geometry": {"coordinates":[-96.872058,32.659719],"type":"Point"}
}