{
  "type": "Feature",
  "properties": {
    "iso:country":"US",
    "sg:address":"303 Dubose Dr",
    "sg:city":"Devine",
    "sg:classifiers":[
        {
            "category":"Building & Trades",
            "subcategory":"Construction",
            "type":"Services"
        }
    ],
    "sg:phone":"+1 830 665 9268",
    "sg:postcode":"78016",
    "sg:province":"TX",
    "sg:tags":[
        "house"
    ],
    "wof:name":"HH&f Homes Ltd",
    "wof:placetype":"venue"
},
  "geometry": {"coordinates":[-98.900874,29.160059],"type":"Point"}
}