{
  "type": "Feature",
  "properties": {
    "iso:country":"US",
    "sg:address":"2327 Briar Branch Dr",
    "sg:city":"Houston",
    "sg:classifiers":[
        {
            "category":"Recreation",
            "type":"Entertainment"
        }
    ],
    "sg:phone":"+1 832 251 3500",
    "sg:postcode":"77042",
    "sg:province":"TX",
    "sg:tags":[
        "course",
        "golf"
    ],
    "wof:name":"Caddie Club",
    "wof:placetype":"venue"
},
  "geometry": {"coordinates":[-95.55543,29.741253],"type":"Point"}
}