{
  "type": "Feature",
  "properties": {
    "iso:country":"US",
    "sg:address":"712 Southwynd St",
    "sg:city":"Mesquite",
    "sg:classifiers":[
        {
            "category":"Wholesale",
            "subcategory":"Non-durable Goods",
            "type":"Manufacturing & Wholesale Goods"
        }
    ],
    "sg:phone":"+1 972 279 4528",
    "sg:postcode":"75150",
    "sg:province":"TX",
    "wof:name":"Mae Day Sales",
    "wof:placetype":"venue"
},
  "geometry": {"coordinates":[-96.606798,32.808958],"type":"Point"}
}