{
  "type": "Feature",
  "properties": {
    "iso:country":"US",
    "sg:address":"500 E Stassney Ln",
    "sg:city":"Austin",
    "sg:classifiers":[
        {
            "category":"Home & Garden",
            "subcategory":"Garden Supply",
            "type":"Retail Goods"
        },
        {
            "category":"Building & Trades",
            "subcategory":"Landscaping Services",
            "type":"Services"
        }
    ],
    "sg:phone":"+1 512 440 1355",
    "sg:postcode":"78745",
    "sg:province":"TX",
    "sg:tags":[
        "sprinkler"
    ],
    "wof:name":"Exterior Landscaping Services",
    "wof:placetype":"venue"
},
  "geometry": {"coordinates":[-97.77122799999999,30.202411],"type":"Point"}
}