{
  "type": "Feature",
  "properties": {
    "iso:country":"US",
    "sg:address":"250 Gessner Rd",
    "sg:city":"Houston",
    "sg:classifiers":[
        {
            "category":"Professional",
            "subcategory":"Management & Consulting",
            "type":"Services"
        }
    ],
    "sg:phone":"+1 713 468 6020",
    "sg:postcode":"77024",
    "sg:province":"TX",
    "sg:tags":[
        "business"
    ],
    "wof:name":"Kitty Cobb Design Consultant",
    "wof:placetype":"venue"
},
  "geometry": {"coordinates":[-95.54468799999999,29.763038],"type":"Point"}
}