{
  "type": "Feature",
  "properties": {
    "iso:country":"US",
    "sg:address":"619 Matlock Centre Cir",
    "sg:city":"Arlington",
    "sg:classifiers":[
        {
            "category":"Health Services",
            "subcategory":"Doctor",
            "type":"Services"
        }
    ],
    "sg:phone":"+1 817 860 9936",
    "sg:postcode":"76015",
    "sg:province":"TX",
    "sg:tags":[
        "medical"
    ],
    "wof:name":"Connie A Concepcion-Maileg",
    "wof:placetype":"venue"
},
  "geometry": {"coordinates":[-97.11335699999999,32.702033],"type":"Point"}
}