{
  "type": "Feature",
  "properties": {
    "iso:country":"US",
    "sg:address":"2730 N Stemmons Fwy",
    "sg:city":"Dallas",
    "sg:classifiers":[
        {
            "category":"Professional",
            "subcategory":"Accounting & Tax Preparation",
            "type":"Services"
        }
    ],
    "sg:phone":"+1 214 634 7555",
    "sg:postcode":"75207",
    "sg:province":"TX",
    "sg:tags":[
        "accountant"
    ],
    "wof:name":"Bryant Lori CPA",
    "wof:placetype":"venue"
},
  "geometry": {"coordinates":[-96.844002,32.8088],"type":"Point"}
}