{
  "type": "Feature",
  "properties": {
    "iso:country":"US",
    "sg:address":"1001 N Main St",
    "sg:city":"Andrews",
    "sg:classifiers":[
        {
            "category":"Professional",
            "type":"Services"
        }
    ],
    "sg:phone":"+1 432 523 4196",
    "sg:postcode":"79714",
    "sg:province":"TX",
    "wof:name":"El Potrillo",
    "wof:placetype":"venue"
},
  "geometry": {"coordinates":[-102.549992,32.329634],"type":"Point"}
}