{
  "type": "Feature",
  "properties": {
    "iso:country":"US",
    "sg:address":"19202 Huebner Rd",
    "sg:city":"San Antonio",
    "sg:classifiers":[
        {
            "category":"Real Estate",
            "subcategory":"Real Estate Agent",
            "type":"Services"
        }
    ],
    "sg:phone":"+1 210 403 3399",
    "sg:postcode":"78258",
    "sg:province":"TX",
    "wof:name":"Brambletye Inc",
    "wof:placetype":"venue"
},
  "geometry": {"coordinates":[-98.511572,29.622637],"type":"Point"}
}