{
  "type": "Feature",
  "properties": {
    "iso:country":"US",
    "sg:address":"2020 S Chadbourne St",
    "sg:city":"San Angelo",
    "sg:classifiers":[
        {
            "category":"Wholesale",
            "subcategory":"Auto Parts",
            "type":"Manufacturing & Wholesale Goods"
        }
    ],
    "sg:phone":"+1 325 655 6417",
    "sg:postcode":"76903",
    "sg:province":"TX",
    "sg:tags":[
        "automobile",
        "wrecking"
    ],
    "wof:name":"Auto Wrecking",
    "wof:placetype":"venue"
},
  "geometry": {"coordinates":[-100.434603,31.439746],"type":"Point"}
}