{
  "type": "Feature",
  "properties": {
    "iso:country":"US",
    "sg:address":"13998 W Hwy 80 E",
    "sg:city":"Odessa",
    "sg:classifiers":[
        {
            "category":"Shopping",
            "subcategory":"Shoes",
            "type":"Retail Goods"
        }
    ],
    "sg:phone":"+1 432 563 4262",
    "sg:postcode":"79765",
    "sg:province":"TX",
    "sg:tags":[
        "apparel",
        "boot",
        "western"
    ],
    "wof:name":"Pee Wee Daltons Boots",
    "wof:placetype":"venue"
},
  "geometry": {"coordinates":[-102.273956,31.893209],"type":"Point"}
}