{
  "type": "Feature",
  "properties": {
    "iso:country":"US",
    "sg:address":"7917 Simpson Dr",
    "sg:city":"Amarillo",
    "sg:classifiers":[
        {
            "category":"Shopping",
            "type":"Retail Goods"
        }
    ],
    "sg:phone":"+1 806 353 5686",
    "sg:postcode":"79121",
    "sg:province":"TX",
    "sg:tags":[
        "pet",
        "shop"
    ],
    "wof:name":"Bubbles Aquariums",
    "wof:placetype":"venue"
},
  "geometry": {"coordinates":[-101.933633,35.182799],"type":"Point"}
}