{
  "type": "Feature",
  "properties": {
    "iso:country":"US",
    "sg:address":"3184 E Hwy 199",
    "sg:city":"Springtown",
    "sg:classifiers":[
        {
            "category":"Freight",
            "type":"Transportation"
        }
    ],
    "sg:phone":"+1 817 221 3737",
    "sg:postcode":"76082",
    "sg:province":"TX",
    "sg:tags":[
        "commercial",
        "storage"
    ],
    "wof:name":"A & S Roundup Storage",
    "wof:placetype":"venue"
},
  "geometry": {"coordinates":[-97.630015,32.93628],"type":"Point"}
}