{
  "type": "Feature",
  "properties": {
    "iso:country":"US",
    "sg:address":"1504 Chapman St",
    "sg:city":"Houston",
    "sg:classifiers":[
        {
            "category":"Manufacturing",
            "subcategory":"Furniture",
            "type":"Manufacturing & Wholesale Goods"
        }
    ],
    "sg:phone":"+1 713 223 5106",
    "sg:postcode":"77009",
    "sg:province":"TX",
    "sg:tags":[
        "household",
        "wood",
        "mfg"
    ],
    "wof:name":"Hands Pottery",
    "wof:placetype":"venue"
},
  "geometry": {"coordinates":[-95.353711,29.775473],"type":"Point"}
}