{
  "type": "Feature",
  "properties": {
    "iso:country":"US",
    "sg:address":"2808 Clearmeadow St",
    "sg:city":"Bedford",
    "sg:classifiers":[
        {
            "category":"Communications",
            "subcategory":"Film & Video Production",
            "type":"Services"
        }
    ],
    "sg:phone":"+1 817 358 7956",
    "sg:postcode":"76021",
    "sg:province":"TX",
    "sg:tags":[
        "motion"
    ],
    "wof:name":"End Time Productions & Ministr",
    "wof:placetype":"venue"
},
  "geometry": {"coordinates":[-97.135419,32.851403],"type":"Point"}
}