{
  "type": "Feature",
  "properties": {
    "iso:country":"US",
    "sg:address":"8830 Cainwood Ln",
    "sg:city":"Austin",
    "sg:classifiers":[
        {
            "category":"Social Services",
            "subcategory":"Child Care",
            "type":"Services"
        }
    ],
    "sg:phone":"+1 512 250 5117",
    "sg:postcode":"78729",
    "sg:province":"TX",
    "sg:tags":[
        "day"
    ],
    "sg:website":"www.northoakscountry.com",
    "wof:name":"North Oaks Country Child Development Center",
    "wof:placetype":"venue"
},
  "geometry": {"coordinates":[-97.773321,30.455771],"type":"Point"}
}