{
  "type": "Feature",
  "properties": {
    "iso:country":"US",
    "sg:address":"4700 E Belknap St",
    "sg:city":"Fort Worth",
    "sg:classifiers":[
        {
            "category":"Personal",
            "subcategory":"Beauty Salon",
            "type":"Services"
        }
    ],
    "sg:phone":"+1 817 222 1646",
    "sg:postcode":"76117",
    "sg:province":"TX",
    "sg:tags":[
        "shop"
    ],
    "wof:name":"Expo Hair Salon & Spa",
    "wof:placetype":"venue"
},
  "geometry": {"coordinates":[-97.27743599999999,32.790497],"type":"Point"}
}