{
  "type": "Feature",
  "properties": {
    "iso:country":"US",
    "sg:address":"200 E Sunset Rd",
    "sg:city":"El Paso",
    "sg:classifiers":[
        {
            "category":"Insurance",
            "subcategory":"Insurance Agent",
            "type":"Services"
        }
    ],
    "sg:phone":"+1 915 581 8133",
    "sg:postcode":"79922",
    "sg:province":"TX",
    "wof:name":"Prudential Overall Supply",
    "wof:placetype":"venue"
},
  "geometry": {"coordinates":[-106.57216099999999,31.837194],"type":"Point"}
}