{
  "type": "Feature",
  "properties": {
    "iso:country":"US",
    "sg:address":"3935 S Co Rd 1292",
    "sg:city":"Odessa",
    "sg:classifiers":[
        {
            "category":"Wholesale",
            "subcategory":"Machinery & Supplies",
            "type":"Manufacturing & Wholesale Goods"
        }
    ],
    "sg:phone":"+1 432 530 2747",
    "sg:postcode":"79765",
    "sg:province":"TX",
    "sg:tags":[
        "field",
        "oil",
        "equipment"
    ],
    "wof:name":"Weatherford GEMOCO",
    "wof:placetype":"venue"
},
  "geometry": {"coordinates":[-102.2358,31.910803],"type":"Point"}
}