{
  "type": "Feature",
  "properties": {
    "iso:country":"US",
    "sg:address":"3119 Wilbarger St",
    "sg:city":"Vernon",
    "sg:classifiers":[
        {
            "category":"Real Estate",
            "subcategory":"Real Estate Agent",
            "type":"Services"
        }
    ],
    "sg:phone":"+1 940 552 0000",
    "sg:postcode":"76384",
    "sg:province":"TX",
    "sg:website":"www.wilbargerrealty.com",
    "wof:name":"Wilbarger Realty Inc",
    "wof:placetype":"venue"
},
  "geometry": {"coordinates":[-99.299543,34.152489],"type":"Point"}
}