{
  "type": "Feature",
  "properties": {
    "iso:country":"US",
    "sg:address":"15415 W Little York Rd",
    "sg:city":"Houston",
    "sg:classifiers":[
        {
            "category":"Building & Trades",
            "subcategory":"Electrical",
            "type":"Services"
        }
    ],
    "sg:phone":"+1 281 858 9542",
    "sg:postcode":"77084",
    "sg:province":"TX",
    "sg:tags":[
        "electrical",
        "contractor"
    ],
    "wof:name":"Molina Electrical Contractors",
    "wof:placetype":"venue"
},
  "geometry": {"coordinates":[-95.643899,29.867613],"type":"Point"}
}