{
  "type": "Feature",
  "properties": {
    "iso:country":"US",
    "sg:address":"1120 Metrocrest Dr",
    "sg:city":"Carrollton",
    "sg:classifiers":[
        {
            "category":"Professional",
            "type":"Services"
        }
    ],
    "sg:phone":"+1 972 418 5100",
    "sg:postcode":"75006",
    "sg:province":"TX",
    "sg:tags":[
        "establishment"
    ],
    "wof:name":"USPAC Inc",
    "wof:placetype":"venue"
},
  "geometry": {"coordinates":[-96.886351,32.955784],"type":"Point"}
}