{
  "type": "Feature",
  "properties": {
    "iso:country":"US",
    "sg:address":"6825 Charlmont Cir",
    "sg:city":"Dallas",
    "sg:classifiers":[
        {
            "category":"Home & Garden",
            "subcategory":"Home Furnishings",
            "type":"Retail Goods"
        }
    ],
    "sg:phone":"+1 972 931 1601",
    "sg:postcode":"75248",
    "sg:province":"TX",
    "sg:tags":[
        "venetian",
        "blind"
    ],
    "wof:name":"Vicki L Tavenner Houswares",
    "wof:placetype":"venue"
},
  "geometry": {"coordinates":[-96.788839,32.979711],"type":"Point"}
}