{
  "type": "Feature",
  "properties": {
    "iso:country":"US",
    "sg:address":"2007 Kinney Ave",
    "sg:city":"Austin",
    "sg:classifiers":[
        {
            "category":"Building & Trades",
            "subcategory":"Landscaping Services",
            "type":"Services"
        }
    ],
    "sg:phone":"+1 512 445 5202",
    "sg:postcode":"78704",
    "sg:province":"TX",
    "sg:tags":[
        "landscape"
    ],
    "wof:name":"Eleanor McKinney Landscaping",
    "wof:placetype":"venue"
},
  "geometry": {"coordinates":[-97.76978699999999,30.249718],"type":"Point"}
}