{
  "type": "Feature",
  "properties": {
    "iso:country":"US",
    "sg:address":"4124 Castor St",
    "sg:city":"Houston",
    "sg:classifiers":[
        {
            "category":"Building & Trades",
            "subcategory":"Construction",
            "type":"Services"
        }
    ],
    "sg:phone":"+1 713 742 5346",
    "sg:postcode":"77022",
    "sg:province":"TX",
    "sg:tags":[
        "contractor"
    ],
    "wof:name":"Texas Construction & Roofing",
    "wof:placetype":"venue"
},
  "geometry": {"coordinates":[-95.38808299999999,29.823921],"type":"Point"}
}