{
  "type": "Feature",
  "properties": {
    "iso:country":"US",
    "sg:address":"1548 Slocum St",
    "sg:city":"Dallas",
    "sg:classifiers":[
        {
            "category":"Shopping",
            "subcategory":"Used Merchandise",
            "type":"Retail Goods"
        }
    ],
    "sg:phone":"+1 214 747 9100",
    "sg:postcode":"75207",
    "sg:province":"TX",
    "sg:tags":[
        "antique"
    ],
    "sg:website":"www.bellaitalialtd.com",
    "wof:name":"Bella Italia Ltd",
    "wof:placetype":"venue"
},
  "geometry": {"coordinates":[-96.81850300000001,32.794141],"type":"Point"}
}