{
  "type": "Feature",
  "properties": {
    "iso:country":"US",
    "sg:address":"1330 SW H K Dodgen Loop",
    "sg:city":"Temple",
    "sg:classifiers":[
        {
            "category":"Shopping",
            "subcategory":"Tobacco",
            "type":"Retail Goods"
        }
    ],
    "sg:phone":"+1 254 773 3103",
    "sg:postcode":"76504",
    "sg:province":"TX",
    "sg:tags":[
        "product"
    ],
    "wof:name":"Tobacco Junction VII",
    "wof:placetype":"venue"
},
  "geometry": {"coordinates":[-97.36967300000001,31.07464],"type":"Point"}
}