{
  "type": "Feature",
  "properties": {
    "iso:country":"US",
    "sg:address":"12724 Fountain Lake Cir",
    "sg:city":"Stafford",
    "sg:classifiers":[
        {
            "category":"Retail",
            "subcategory":"Photofinishing",
            "type":"Services"
        }
    ],
    "sg:phone":"+1 281 494 6161",
    "sg:postcode":"77477",
    "sg:province":"TX",
    "sg:tags":[
        "photo",
        "finishing"
    ],
    "wof:name":"Wolf Camera & Video",
    "wof:placetype":"venue"
},
  "geometry": {"coordinates":[-95.58678500000001,29.636113],"type":"Point"}
}