{
  "type": "Feature",
  "properties": {
    "iso:country":"US",
    "sg:address":"5409 N Jim Miller Rd Ste 105",
    "sg:city":"Dallas",
    "sg:classifiers":[
        {
            "category":"Health Services",
            "subcategory":"Dentist",
            "type":"Services"
        }
    ],
    "sg:phone":"+1 214 381 1272",
    "sg:postcode":"75227",
    "sg:province":"TX",
    "sg:website":"www.exquisitefamilydentistry.com",
    "wof:name":"Exquisite Family Dentistry",
    "wof:placetype":"venue"
},
  "geometry": {"coordinates":[-96.700281,32.789676],"type":"Point"}
}