{
  "type": "Feature",
  "properties": {
    "iso:country":"US",
    "sg:address":"1710 Strawberry Rd Ste 100",
    "sg:city":"Pasadena",
    "sg:classifiers":[
        {
            "category":"Professional",
            "subcategory":"Lawyer & Legal Services",
            "type":"Services"
        }
    ],
    "sg:phone":"+1 713 472 7166",
    "sg:postcode":"77502",
    "sg:province":"TX",
    "sg:tags":[
        "notary"
    ],
    "wof:name":"Garza Richard Atty",
    "wof:placetype":"venue"
},
  "geometry": {"coordinates":[-95.19319900000001,29.6866],"type":"Point"}
}