{
  "type": "Feature",
  "properties": {
    "iso:country":"US",
    "sg:address":"4107 Somerset Ct",
    "sg:city":"Grapevine",
    "sg:classifiers":[
        {
            "category":"Professional",
            "subcategory":"Management & Consulting",
            "type":"Services"
        }
    ],
    "sg:phone":"+1 817 424 3336",
    "sg:postcode":"76051",
    "sg:province":"TX",
    "sg:tags":[
        "business"
    ],
    "wof:name":"Noonan Communications Group",
    "wof:placetype":"venue"
},
  "geometry": {"coordinates":[-97.118555,32.895786],"type":"Point"}
}