{
  "type": "Feature",
  "properties": {
    "iso:country":"US",
    "sg:address":"1026 Pinewood Blvd",
    "sg:city":"Sour Lake",
    "sg:classifiers":[
        {
            "category":"Shopping",
            "subcategory":"Clothing, Apparel, & Fashions",
            "type":"Retail Goods"
        }
    ],
    "sg:phone":"+1 409 753 1244",
    "sg:postcode":"77659",
    "sg:province":"TX",
    "wof:name":"Worth Collection",
    "wof:placetype":"venue"
},
  "geometry": {"coordinates":[-94.31689299999999,30.153099],"type":"Point"}
}