{
  "type": "Feature",
  "properties": {
    "iso:country":"US",
    "sg:address":"24818 House Mountain Rd",
    "sg:city":"San Antonio",
    "sg:classifiers":[
        {
            "category":"Building & Trades",
            "subcategory":"Cleaning & Sanitation",
            "type":"Services"
        }
    ],
    "sg:phone":"+1 210 698 5254",
    "sg:postcode":"78255",
    "sg:province":"TX",
    "sg:tags":[
        "window",
        "maintenance"
    ],
    "wof:name":"David's Window Cleaning",
    "wof:placetype":"venue"
},
  "geometry": {"coordinates":[-98.66321499999999,29.667801],"type":"Point"}
}