{
  "type": "Feature",
  "properties": {
    "iso:country":"US",
    "sg:address":"300 Litsey Rd",
    "sg:city":"Roanoke",
    "sg:classifiers":[
        {
            "category":"Building & Trades",
            "subcategory":"Construction",
            "type":"Services"
        }
    ],
    "sg:phone":"+1 817 490 1875",
    "sg:postcode":"76262",
    "sg:province":"TX",
    "wof:name":"Best Texas Metal Buildings Inc",
    "wof:placetype":"venue"
},
  "geometry": {"coordinates":[-97.244918,33.008047],"type":"Point"}
}