{
  "type": "Feature",
  "properties": {
    "iso:country":"US",
    "sg:address":"409 de Vargas Dr",
    "sg:city":"El Paso",
    "sg:classifiers":[
        {
            "category":"Building & Trades",
            "subcategory":"Construction",
            "type":"Services"
        }
    ],
    "sg:phone":"+1 915 778 4961",
    "sg:postcode":"79905",
    "sg:province":"TX",
    "sg:tags":[
        "marking",
        "maintenance",
        "parking"
    ],
    "wof:name":"Steamclean",
    "wof:placetype":"venue"
},
  "geometry": {"coordinates":[-106.42818200000001,31.764266],"type":"Point"}
}