{
  "type": "Feature",
  "properties": {
    "iso:country":"US",
    "sg:address":"5567 W Lovers Ln",
    "sg:city":"Dallas",
    "sg:classifiers":[
        {
            "category":"Shopping",
            "subcategory":"Mobile Phones",
            "type":"Retail Goods"
        }
    ],
    "sg:phone":"+1 214 350 8995",
    "sg:postcode":"75209",
    "sg:province":"TX",
    "wof:name":"Cellular World",
    "wof:placetype":"venue"
},
  "geometry": {"coordinates":[-96.817802,32.851299],"type":"Point"}
}