{
  "type": "Feature",
  "properties": {
    "iso:country":"US",
    "sg:address":"200 E 4th St",
    "sg:city":"Sweetwater",
    "sg:classifiers":[
        {
            "category":"Utilities",
            "subcategory":"Water",
            "type":"Services"
        }
    ],
    "sg:phone":"+1 325 236 6315",
    "sg:postcode":"79556",
    "sg:province":"TX",
    "sg:tags":[
        "company",
        "sewage"
    ],
    "wof:name":"Sweetwater Water Office",
    "wof:placetype":"venue"
},
  "geometry": {"coordinates":[-100.40745200000001,32.472938],"type":"Point"}
}