{
  "type": "Feature",
  "properties": {
    "iso:country":"US",
    "sg:address":"1616 Bevis St",
    "sg:city":"Houston",
    "sg:classifiers":[
        {
            "category":"Home & Garden",
            "subcategory":"Furniture",
            "type":"Retail Goods"
        }
    ],
    "sg:phone":"+1 713 864 0633",
    "sg:postcode":"77008",
    "sg:province":"TX",
    "wof:name":"Quazi In",
    "wof:placetype":"venue"
},
  "geometry": {"coordinates":[-95.422329,29.799071],"type":"Point"}
}