{
  "type": "Feature",
  "properties": {
    "iso:country":"US",
    "sg:address":"1101 Cotton St",
    "sg:city":"Carrollton",
    "sg:classifiers":[
        {
            "category":"Wholesale",
            "subcategory":"Non-durable Goods",
            "type":"Manufacturing & Wholesale Goods"
        }
    ],
    "sg:phone":"+1 972 446 9760",
    "sg:postcode":"75006",
    "sg:province":"TX",
    "sg:tags":[
        "distributor",
        "advertising",
        "specialty"
    ],
    "wof:name":"Pescado Entertainment",
    "wof:placetype":"venue"
},
  "geometry": {"coordinates":[-96.90579700000001,32.958841],"type":"Point"}
}