{
  "type": "Feature",
  "properties": {
    "iso:country":"US",
    "sg:address":"1717 S Hwy 287",
    "sg:city":"Decatur",
    "sg:classifiers":[
        {
            "category":"Organizations",
            "subcategory":"Religious Organization",
            "type":"Services"
        }
    ],
    "sg:phone":"+1 940 627 6776",
    "sg:postcode":"76234",
    "sg:province":"TX",
    "wof:name":"Community Baptist Church",
    "wof:placetype":"venue"
},
  "geometry": {"coordinates":[-97.589744,33.221219],"type":"Point"}
}