{
  "type": "Feature",
  "properties": {
    "iso:country":"US",
    "sg:address":"808 S Shary Rd",
    "sg:city":"Mission",
    "sg:classifiers":[
        {
            "category":"Shopping",
            "subcategory":"Mobile Phones",
            "type":"Retail Goods"
        }
    ],
    "sg:phone":"+1 956 581 3943",
    "sg:postcode":"78572",
    "sg:province":"TX",
    "sg:tags":[
        "equipment",
        "telephone",
        "cellular",
        "supply"
    ],
    "wof:name":"Tmobile",
    "wof:placetype":"venue"
},
  "geometry": {"coordinates":[-98.289387,26.189908],"type":"Point"}
}