{
  "type": "Feature",
  "properties": {
    "iso:country":"US",
    "sg:address":"2714 Whetstone Dr",
    "sg:city":"Corinth",
    "sg:classifiers":[
        {
            "category":"Building & Trades",
            "subcategory":"Construction",
            "type":"Services"
        }
    ],
    "sg:phone":"+1 940 498 1068",
    "sg:postcode":"76210",
    "sg:province":"TX",
    "sg:tags":[
        "contractor",
        "grading"
    ],
    "wof:name":"E & H Custom Builders",
    "wof:placetype":"venue"
},
  "geometry": {"coordinates":[-97.068511,33.13576],"type":"Point"}
}