{
  "type": "Feature",
  "properties": {
    "iso:country":"US",
    "sg:address":"16069 Central Commerce Dr",
    "sg:city":"Pflugerville",
    "sg:classifiers":[
        {
            "category":"Building & Trades",
            "subcategory":"Plumbing",
            "type":"Services"
        }
    ],
    "sg:phone":"+1 512 832 8069",
    "sg:postcode":"78660",
    "sg:province":"TX",
    "sg:tags":[
        "fire",
        "protection",
        "system"
    ],
    "wof:name":"Western States Fire Protection",
    "wof:placetype":"venue"
},
  "geometry": {"coordinates":[-97.65910599999999,30.454401],"type":"Point"}
}