{
  "type": "Feature",
  "properties": {
    "iso:country":"US",
    "sg:address":"1682 Spindletop Ave",
    "sg:city":"Beaumont",
    "sg:classifiers":[
        {
            "category":"Building & Trades",
            "subcategory":"Construction",
            "type":"Services"
        }
    ],
    "sg:phone":"+1 409 832 3030",
    "sg:postcode":"77705",
    "sg:province":"TX",
    "sg:tags":[
        "excavating",
        "contractor"
    ],
    "wof:name":"NTS Mikedon",
    "wof:placetype":"venue"
},
  "geometry": {"coordinates":[-94.061691,30.031101],"type":"Point"}
}