{
  "type": "Feature",
  "properties": {
    "iso:country":"US",
    "sg:address":"7610 Roebourne Ln",
    "sg:city":"Houston",
    "sg:classifiers":[
        {
            "category":"Shopping",
            "subcategory":"Hobbies, Toys, & Games",
            "type":"Retail Goods"
        }
    ],
    "sg:phone":"+1 281 955 9186",
    "sg:postcode":"77070",
    "sg:province":"TX",
    "wof:name":"Jackie E Adams",
    "wof:placetype":"venue"
},
  "geometry": {"coordinates":[-95.550504,29.983688],"type":"Point"}
}