{
  "type": "Feature",
  "properties": {
    "iso:country":"US",
    "sg:address":"4002 S Cedar St",
    "sg:city":"Pecos",
    "sg:classifiers":[
        {
            "category":"Travel",
            "subcategory":"Hotels & Motels",
            "type":"Entertainment"
        }
    ],
    "sg:phone":"+1 432 445 5404",
    "sg:postcode":"79772",
    "sg:province":"TX",
    "sg:tags":[
        "lodging"
    ],
    "sg:website":"http://www.qualityinn.com/hotel-pecos-texas-TX367",
    "wof:name":"Quality Inn Pecos",
    "wof:placetype":"venue"
},
  "geometry": {"coordinates":[-103.471817,31.388228],"type":"Point"}
}