{
  "type": "Feature",
  "properties": {
    "iso:country":"US",
    "sg:address":"7609 Ave I",
    "sg:city":"Houston",
    "sg:classifiers":[
        {
            "category":"Food & Beverages",
            "subcategory":"Dairy",
            "type":"Retail Goods"
        }
    ],
    "sg:phone":"+1 713 921 1066",
    "sg:postcode":"77012",
    "sg:province":"TX",
    "sg:tags":[
        "product"
    ],
    "wof:name":"La Sabrocita Ice Cream",
    "wof:placetype":"venue"
},
  "geometry": {"coordinates":[-95.286045,29.736888],"type":"Point"}
}