{
  "type": "Feature",
  "properties": {
    "iso:country":"US",
    "sg:address":"207 N Main St",
    "sg:city":"Shamrock",
    "sg:classifiers":[
        {
            "category":"Building & Trades",
            "subcategory":"Construction",
            "type":"Services"
        }
    ],
    "sg:phone":"+1 806 256 3298",
    "sg:postcode":"79079",
    "sg:province":"TX",
    "sg:tags":[
        "house",
        "roofing",
        "contractor"
    ],
    "wof:name":"Integrity National Constr",
    "wof:placetype":"venue"
},
  "geometry": {"coordinates":[-100.249213,35.216451],"type":"Point"}
}