{
  "type": "Feature",
  "properties": {
    "iso:country":"US",
    "sg:address":"1717 Belle Pl",
    "sg:city":"Fort Worth",
    "sg:classifiers":[
        {
            "category":"Professional",
            "subcategory":"Business Services",
            "type":"Services"
        }
    ],
    "sg:phone":"+1 817 732 3911",
    "sg:postcode":"76107",
    "sg:province":"TX",
    "sg:tags":[
        "event"
    ],
    "wof:name":"Alliance Audio Visual",
    "wof:placetype":"venue"
},
  "geometry": {"coordinates":[-97.37629099999999,32.742511],"type":"Point"}
}