{
  "type": "Feature",
  "properties": {
    "iso:country":"US",
    "sg:address":"4503 Eby Ln",
    "sg:city":"Austin",
    "sg:classifiers":[
        {
            "category":"Insurance",
            "subcategory":"Insurance Agent",
            "type":"Services"
        }
    ],
    "sg:phone":"+1 512 459 8500",
    "sg:postcode":"78731",
    "sg:province":"TX",
    "wof:name":"Maislin Co Inc",
    "wof:placetype":"venue"
},
  "geometry": {"coordinates":[-97.780064,30.338482],"type":"Point"}
}