{
  "type": "Feature",
  "properties": {
    "iso:country":"US",
    "sg:address":"300 W Main St",
    "sg:city":"Post",
    "sg:classifiers":[
        {
            "category":"Government",
            "subcategory":"Office",
            "type":"Public Place"
        }
    ],
    "sg:phone":"+1 806 495 4448",
    "sg:postcode":"79356",
    "sg:province":"TX",
    "sg:tags":[
        "county",
        "taxation"
    ],
    "wof:name":"Garza County Tax Assessor",
    "wof:placetype":"venue"
},
  "geometry": {"coordinates":[-101.38086800000001,33.191474],"type":"Point"}
}