{
  "type": "Feature",
  "properties": {
    "iso:country":"US",
    "sg:address":"6831 Maple Spring",
    "sg:city":"San Antonio",
    "sg:classifiers":[
        {
            "category":"Professional",
            "type":"Services"
        }
    ],
    "sg:phone":"+1 210 696 5764",
    "sg:postcode":"78249",
    "sg:province":"TX",
    "wof:name":"Rebeca Gonzalez Martinez",
    "wof:placetype":"venue"
},
  "geometry": {"coordinates":[-98.626513,29.556292],"type":"Point"}
}