{
  "type": "Feature",
  "properties": {
    "iso:country":"US",
    "sg:address":"7128 Oaklawn Dr",
    "sg:city":"San Antonio",
    "sg:classifiers":[
        {
            "category":"Building & Trades",
            "subcategory":"Construction",
            "type":"Services"
        }
    ],
    "sg:phone":"+1 210 366 4716",
    "sg:postcode":"78229",
    "sg:province":"TX",
    "sg:tags":[
        "painter"
    ],
    "wof:name":"Rainbow Painting",
    "wof:placetype":"venue"
},
  "geometry": {"coordinates":[-98.555553,29.500089],"type":"Point"}
}