{
  "type": "Feature",
  "properties": {
    "iso:country":"US",
    "sg:address":"2510 Crockett Dr",
    "sg:city":"Brownwood",
    "sg:classifiers":[
        {
            "category":"Health Services",
            "subcategory":"Doctor",
            "type":"Services"
        }
    ],
    "sg:phone":"+1 325 643 3576",
    "sg:postcode":"76801",
    "sg:province":"TX",
    "sg:tags":[
        "medical"
    ],
    "wof:name":"Moore Richard MD PC",
    "wof:placetype":"venue"
},
  "geometry": {"coordinates":[-98.993359,31.68002],"type":"Point"}
}