{
  "type": "Feature",
  "properties": {
    "iso:country":"US",
    "sg:address":"402 E Harrison Ave",
    "sg:city":"Harlingen",
    "sg:classifiers":[
        {
            "category":"Wholesale",
            "subcategory":"Stationery",
            "type":"Manufacturing & Wholesale Goods"
        },
        {
            "category":"Professional",
            "subcategory":"Accounting & Tax Preparation",
            "type":"Services"
        }
    ],
    "sg:phone":"+1 956 428 6945",
    "sg:postcode":"78550",
    "sg:province":"TX",
    "sg:tags":[
        "return",
        "filing",
        "supply"
    ],
    "wof:name":"Stms Income Tax",
    "wof:placetype":"venue"
},
  "geometry": {"coordinates":[-97.691288,26.190601],"type":"Point"}
}