{
  "type": "Feature",
  "properties": {
    "iso:country":"US",
    "sg:address":"3008 Moss Ave",
    "sg:city":"Midland",
    "sg:classifiers":[
        {
            "category":"Farming",
            "subcategory":"Farm",
            "type":"Manufacturing & Wholesale Goods"
        }
    ],
    "sg:phone":"+1 432 689 8438",
    "sg:postcode":"79705",
    "sg:province":"TX",
    "sg:tags":[
        "crop",
        "general"
    ],
    "wof:name":"Jo Ann Urbanovsky",
    "wof:placetype":"venue"
},
  "geometry": {"coordinates":[-102.12733900000001,32.027716],"type":"Point"}
}