{
  "type": "Feature",
  "properties": {
    "iso:country":"US",
    "sg:address":"2409 W Bogey Dr",
    "sg:city":"Mission",
    "sg:classifiers":[
        {
            "category":"Recreation",
            "subcategory":"Campground",
            "type":"Entertainment"
        }
    ],
    "sg:phone":"+1 956 584 3738",
    "sg:postcode":"78572",
    "sg:province":"TX",
    "sg:tags":[
        "recreational",
        "park",
        "vehicle"
    ],
    "wof:name":"Gerald F Schneider",
    "wof:placetype":"venue"
},
  "geometry": {"coordinates":[-98.412369,26.25231],"type":"Point"}
}