{
  "type": "Feature",
  "properties": {
    "iso:country":"US",
    "sg:address":"1015 White Dove Dr",
    "sg:city":"Arlington",
    "sg:classifiers":[
        {
            "category":"Food & Beverages",
            "subcategory":"Specialty",
            "type":"Retail Goods"
        }
    ],
    "sg:phone":"+1 817 472 0930",
    "sg:postcode":"76017",
    "sg:province":"TX",
    "wof:name":"Market America",
    "wof:placetype":"venue"
},
  "geometry": {"coordinates":[-97.127033,32.65319],"type":"Point"}
}