{
  "type": "Feature",
  "properties": {
    "iso:country":"US",
    "sg:address":"5413 Bandera Rd",
    "sg:city":"San Antonio",
    "sg:classifiers":[
        {
            "category":"Building & Trades",
            "subcategory":"Electrical",
            "type":"Services"
        },
        {
            "category":"Communications",
            "type":"Services"
        }
    ],
    "sg:phone":"+1 210 341 3738",
    "sg:postcode":"78238",
    "sg:province":"TX",
    "sg:tags":[
        "carrier",
        "electrical",
        "contractor"
    ],
    "sg:website":"www.go-ict.com",
    "wof:name":"Integrated Communications Tech",
    "wof:placetype":"venue"
},
  "geometry": {"coordinates":[-98.591917,29.479709],"type":"Point"}
}