{
  "type": "Feature",
  "properties": {
    "iso:country":"US",
    "sg:address":"200 W Lang St",
    "sg:city":"Alvin",
    "sg:classifiers":[
        {
            "category":"Organizations",
            "subcategory":"Religious Organization",
            "type":"Services"
        }
    ],
    "sg:phone":"+1 281 331 5657",
    "sg:postcode":"77511",
    "sg:province":"TX",
    "wof:name":"Grace Episcopal Church",
    "wof:placetype":"venue"
},
  "geometry": {"coordinates":[-95.24577499999999,29.421146],"type":"Point"}
}