{
  "type": "Feature",
  "properties": {
    "iso:country":"US",
    "sg:address":"4700 Eastpark Dr",
    "sg:city":"Houston",
    "sg:classifiers":[
        {
            "category":"Freight",
            "type":"Transportation"
        }
    ],
    "sg:phone":"+1 713 675 2573",
    "sg:postcode":"77028",
    "sg:province":"TX",
    "sg:tags":[
        "herbicide",
        "petrochemical",
        "store"
    ],
    "wof:name":"Sidney Service Corporation",
    "wof:placetype":"venue"
},
  "geometry": {"coordinates":[-95.29904399999999,29.8024],"type":"Point"}
}