{
  "type": "Feature",
  "properties": {
    "iso:country":"US",
    "sg:address":"612 N Polk St",
    "sg:city":"Amarillo",
    "sg:classifiers":[
        {
            "category":"Utilities",
            "subcategory":"Natural Gas",
            "type":"Services"
        }
    ],
    "sg:phone":"+1 918 831 8291",
    "sg:postcode":"79107",
    "sg:province":"TX",
    "sg:tags":[
        "gathering"
    ],
    "wof:name":"Oneok Westex Transmission Inc",
    "wof:placetype":"venue"
},
  "geometry": {"coordinates":[-101.834452,35.219936],"type":"Point"}
}