{
  "type": "Feature",
  "properties": {
    "iso:country":"US",
    "sg:address":"2907 High Valley Dr",
    "sg:city":"Humble",
    "sg:classifiers":[
        {
            "category":"Government",
            "subcategory":"Fire Station",
            "type":"Public Place"
        }
    ],
    "sg:phone":"+1 281 360 2147",
    "sg:postcode":"77345",
    "sg:province":"TX",
    "sg:tags":[
        "department"
    ],
    "wof:name":"Houston City Of Fire Station",
    "wof:placetype":"venue"
},
  "geometry": {"coordinates":[-95.158959,30.060072],"type":"Point"}
}