{
  "type": "Feature",
  "properties": {
    "iso:country":"US",
    "sg:address":"306 Hillside Dr",
    "sg:city":"Gainesville",
    "sg:classifiers":[
        {
            "category":"Farming",
            "subcategory":"Livestock Farm",
            "type":"Manufacturing & Wholesale Goods"
        }
    ],
    "sg:phone":"+1 940 668 8984",
    "sg:postcode":"76240",
    "sg:province":"TX",
    "sg:tags":[
        "beef",
        "feedlot",
        "cattle"
    ],
    "wof:name":"Tommy Davidson",
    "wof:placetype":"venue"
},
  "geometry": {"coordinates":[-97.12233000000001,33.627884],"type":"Point"}
}