{
  "type": "Feature",
  "properties": {
    "iso:country":"US",
    "sg:address":"605 Santa Clara Rd",
    "sg:city":"Salado",
    "sg:classifiers":[
        {
            "category":"Personal",
            "type":"Services"
        }
    ],
    "sg:phone":"+1 254 947 9494",
    "sg:postcode":"76571",
    "sg:province":"TX",
    "sg:tags":[
        "consultant",
        "program",
        "health",
        "fitness"
    ],
    "wof:name":"Seniorcise With Ruth",
    "wof:placetype":"venue"
},
  "geometry": {"coordinates":[-97.533304,30.935145],"type":"Point"}
}