{
  "type": "Feature",
  "properties": {
    "iso:country":"US",
    "sg:address":"187 W Dyna Dr",
    "sg:city":"Houston",
    "sg:classifiers":[
        {
            "category":"Restaurant",
            "type":"Food & Drink"
        }
    ],
    "sg:phone":"+1 281 448 3193",
    "sg:postcode":"77037",
    "sg:province":"TX",
    "sg:website":"www.burgerking.com",
    "wof:name":"Burger King",
    "wof:placetype":"venue"
},
  "geometry": {"coordinates":[-95.411598,29.9216],"type":"Point"}
}