{
  "type": "Feature",
  "properties": {
    "iso:country":"US",
    "sg:address":"10616 Hempstead Rd",
    "sg:city":"Houston",
    "sg:classifiers":[
        {
            "category":"Home & Garden",
            "subcategory":"Home Furnishings",
            "type":"Retail Goods"
        },
        {
            "category":"Shopping",
            "subcategory":"Crafts & Fabrics",
            "type":"Retail Goods"
        },
        {
            "category":"Wholesale",
            "subcategory":"Home Furnishings",
            "type":"Manufacturing & Wholesale Goods"
        }
    ],
    "sg:phone":"+1 713 956 2630",
    "sg:postcode":"77092",
    "sg:province":"TX",
    "sg:tags":[
        "draperies",
        "vertical",
        "etc-wholesale",
        "blinds-venetian",
        "curtain",
        "shades-wholesale",
        "drapery",
        "manufacturer"
    ],
    "wof:name":"Fabri-Co Drapery And Textile",
    "wof:placetype":"venue"
},
  "geometry": {"coordinates":[-95.46944499999999,29.808281],"type":"Point"}
}