{
  "type": "Feature",
  "properties": {
    "iso:country":"US",
    "sg:address":"3315 Center St",
    "sg:city":"Houston",
    "sg:classifiers":[
        {
            "category":"Retail",
            "subcategory":"Laundry & Dry Cleaning",
            "type":"Services"
        }
    ],
    "sg:phone":"+1 713 861 3695",
    "sg:postcode":"77007",
    "sg:province":"TX",
    "sg:tags":[
        "uniform",
        "supply"
    ],
    "sg:website":"www.admiralservices.com",
    "wof:name":"Admiral Linen & Uniform Fleet",
    "wof:placetype":"venue"
},
  "geometry": {"coordinates":[-95.39390299999999,29.76997],"type":"Point"}
}