{
  "type": "Feature",
  "properties": {
    "iso:country":"US",
    "sg:address":"7407 Hardesty",
    "sg:city":"San Antonio",
    "sg:classifiers":[
        {
            "category":"Retail",
            "subcategory":"Car Wash",
            "type":"Services"
        }
    ],
    "sg:phone":"+1 210 523 7500",
    "sg:postcode":"78250",
    "sg:province":"TX",
    "sg:tags":[
        "carwash"
    ],
    "wof:name":"Cyclone Power Wash",
    "wof:placetype":"venue"
},
  "geometry": {"coordinates":[-98.687151,29.508812],"type":"Point"}
}