{
  "type": "Feature",
  "properties": {
    "iso:country":"US",
    "sg:address":"1707 Wildgrove Dr",
    "sg:city":"Pasadena",
    "sg:classifiers":[
        {
            "category":"Professional",
            "type":"Services"
        }
    ],
    "sg:phone":"+1 281 998 1821",
    "sg:postcode":"77504",
    "sg:province":"TX",
    "wof:name":"B&B Residential Services",
    "wof:placetype":"venue"
},
  "geometry": {"coordinates":[-95.185531,29.641783],"type":"Point"}
}