{
  "type": "Feature",
  "properties": {
    "iso:country":"US",
    "sg:address":"9900 Westpark Dr Ste 120",
    "sg:city":"Houston",
    "sg:classifiers":[
        {
            "category":"Education",
            "subcategory":"Special Training",
            "type":"Public Place"
        }
    ],
    "sg:phone":"+1 713 244 9842",
    "sg:postcode":"77063",
    "sg:province":"TX",
    "sg:tags":[
        "educational"
    ],
    "sg:website":"http://northstar-chs.com/Home_Page.php",
    "wof:name":"North Star Christian High School",
    "wof:placetype":"venue"
},
  "geometry": {"coordinates":[-95.535332,29.720409],"type":"Point"}
}