{
  "type": "Feature",
  "properties": {
    "iso:country":"US",
    "sg:address":"3623 McCann Rd",
    "sg:city":"Longview",
    "sg:classifiers":[
        {
            "category":"Education",
            "subcategory":"School",
            "type":"Public Place"
        }
    ],
    "sg:phone":"+1 903 663 7151",
    "sg:postcode":"75605",
    "sg:province":"TX",
    "wof:name":"Longview High School",
    "wof:placetype":"venue"
},
  "geometry": {"coordinates":[-94.754504,32.54678],"type":"Point"}
}