{
  "type": "Feature",
  "properties": {
    "iso:country":"US",
    "sg:address":"270 20th St NE",
    "sg:city":"Paris",
    "sg:classifiers":[
        {
            "category":"Organizations",
            "subcategory":"Religious Organization",
            "type":"Services"
        }
    ],
    "sg:phone":"+1 903 784 4806",
    "sg:postcode":"75460",
    "sg:province":"TX",
    "sg:tags":[
        "church"
    ],
    "wof:name":"Faith Presbyterian Church Inc",
    "wof:placetype":"venue"
},
  "geometry": {"coordinates":[-95.535584,33.66401],"type":"Point"}
}