{
  "type": "Feature",
  "properties": {
    "iso:country":"US",
    "sg:address":"1203 Lake St",
    "sg:city":"Fort Worth",
    "sg:classifiers":[
        {
            "category":"Banks & Credit Unions",
            "subcategory":"Bank",
            "type":"Services"
        }
    ],
    "sg:phone":"+1 817 878 4220",
    "sg:postcode":"76102",
    "sg:province":"TX",
    "sg:tags":[
        "loan",
        "real estate"
    ],
    "wof:name":"Acceptance Home Mortgage",
    "wof:placetype":"venue"
},
  "geometry": {"coordinates":[-97.338954,32.746059],"type":"Point"}
}