{
  "type": "Feature",
  "properties": {
    "iso:country":"US",
    "sg:address":"108 Duval Dr",
    "sg:city":"Levelland",
    "sg:phone":"+1 806 894 4223",
    "sg:postcode":"79336",
    "sg:province":"TX",
    "sg:tags":[
        "farm",
        "cotton"
    ],
    "wof:name":"Methco Inc",
    "wof:placetype":"venue"
},
  "geometry": {"coordinates":[-102.34225499999999,33.586197],"type":"Point"}
}