{
  "type": "Feature",
  "properties": {
    "iso:country":"US",
    "sg:address":"508 E Front St",
    "sg:city":"Tyler",
    "sg:classifiers":[
        {
            "category":"Health Services",
            "subcategory":"Chiropractor",
            "type":"Services"
        }
    ],
    "sg:phone":"+1 903 593 4206",
    "sg:postcode":"75702",
    "sg:province":"TX",
    "wof:name":"Smith County Heatlh Care Syst",
    "wof:placetype":"venue"
},
  "geometry": {"coordinates":[-95.294381,32.346772],"type":"Point"}
}