{
  "type": "Feature",
  "properties": {
    "iso:country":"US",
    "sg:address":"6058 Black Oak Ln",
    "sg:city":"Fort Worth",
    "sg:classifiers":[
        {
            "category":"Building & Trades",
            "subcategory":"Construction",
            "type":"Services"
        }
    ],
    "sg:phone":"+1 817 737 4792",
    "sg:postcode":"76114",
    "sg:province":"TX",
    "sg:tags":[
        "drywall",
        "finisher"
    ],
    "wof:name":"Viola Ruby Maxwell",
    "wof:placetype":"venue"
},
  "geometry": {"coordinates":[-97.412404,32.773113],"type":"Point"}
}