{
  "type": "Feature",
  "properties": {
    "iso:country":"US",
    "sg:address":"2025 Gumwood Ave",
    "sg:city":"Mcallen",
    "sg:classifiers":[
        {
            "category":"Professional",
            "subcategory":"Engineering",
            "type":"Services"
        }
    ],
    "sg:phone":"+1 956 971 9302",
    "sg:postcode":"78501",
    "sg:province":"TX",
    "wof:name":"Cargut Engineering",
    "wof:placetype":"venue"
},
  "geometry": {"coordinates":[-98.24047899999999,26.211216],"type":"Point"}
}