{
  "type": "Feature",
  "properties": {
    "iso:country":"US",
    "sg:address":"3400 Olton Rd",
    "sg:city":"Plainview",
    "sg:classifiers":[
        {
            "category":"Restaurant",
            "type":"Food & Drink"
        }
    ],
    "sg:phone":"+1 806 291 8888",
    "sg:postcode":"79072",
    "sg:province":"TX",
    "sg:tags":[
        "eating"
    ],
    "wof:name":"China Dragon",
    "wof:placetype":"venue"
},
  "geometry": {"coordinates":[-101.749376,34.187487],"type":"Point"}
}