{
  "type": "Feature",
  "properties": {
    "iso:country":"US",
    "sg:address":"2007 108th St",
    "sg:city":"Grand Prairie",
    "sg:classifiers":[
        {
            "category":"Professional",
            "subcategory":"Management & Consulting",
            "type":"Services"
        }
    ],
    "sg:phone":"+1 972 647 8484",
    "sg:postcode":"75050",
    "sg:province":"TX",
    "sg:tags":[
        "consultant",
        "automation"
    ],
    "wof:name":"Scada Co",
    "wof:placetype":"venue"
},
  "geometry": {"coordinates":[-97.055966,32.78274],"type":"Point"}
}