{
  "type": "Feature",
  "properties": {
    "iso:country":"US",
    "sg:address":"6506 Carver Rd",
    "sg:city":"Houston",
    "sg:classifiers":[
        {
            "category":"Personal",
            "subcategory":"Beauty Salon",
            "type":"Services"
        }
    ],
    "sg:phone":"+1 713 686 4709",
    "sg:postcode":"77091",
    "sg:province":"TX",
    "sg:tags":[
        "shop"
    ],
    "wof:name":"Willie BS Beauty Nook",
    "wof:placetype":"venue"
},
  "geometry": {"coordinates":[-95.445565,29.858291],"type":"Point"}
}