{
  "type": "Feature",
  "properties": {
    "iso:country":"US",
    "sg:address":"1009 Ruthven St",
    "sg:city":"Houston",
    "sg:classifiers":[
        {
            "category":"Social Services",
            "type":"Services"
        }
    ],
    "sg:phone":"+1 713 655 1086",
    "sg:postcode":"77019",
    "sg:province":"TX",
    "sg:tags":[
        "youth",
        "organization",
        "center"
    ],
    "wof:name":"Centers For Youth",
    "wof:placetype":"venue"
},
  "geometry": {"coordinates":[-95.378615,29.755092],"type":"Point"}
}