{
  "type": "Feature",
  "properties": {
    "iso:country":"US",
    "sg:address":"2908 Preston Ave",
    "sg:city":"Pasadena",
    "sg:classifiers":[
        {
            "category":"Freight",
            "type":"Transportation"
        },
        {
            "category":"Local Transit",
            "type":"Transportation"
        }
    ],
    "sg:phone":"+1 713 910 9200",
    "sg:postcode":"77503",
    "sg:province":"TX",
    "sg:tags":[
        "company",
        "trucking"
    ],
    "wof:name":"Mr Gails Transportation Inc",
    "wof:placetype":"venue"
},
  "geometry": {"coordinates":[-95.172392,29.669087],"type":"Point"}
}