{
  "type": "Feature",
  "properties": {
    "iso:country":"US",
    "sg:address":"1122 Pine St",
    "sg:city":"Gilmer",
    "sg:classifiers":[
        {
            "category":"Organizations",
            "subcategory":"Religious Organization",
            "type":"Services"
        }
    ],
    "sg:phone":"+1 903 843 3307",
    "sg:postcode":"75644",
    "sg:province":"TX",
    "sg:tags":[
        "church"
    ],
    "wof:name":"Church Of Jesus Christ Of Lds",
    "wof:placetype":"venue"
},
  "geometry": {"coordinates":[-94.957352,32.737951],"type":"Point"}
}