{
  "type": "Feature",
  "properties": {
    "iso:country":"US",
    "sg:address":"5601 Whitman Ave",
    "sg:city":"Fort Worth",
    "sg:classifiers":[
        {
            "category":"Professional",
            "subcategory":"Research",
            "type":"Services"
        }
    ],
    "sg:phone":"+1 817 292 7789",
    "sg:postcode":"76133",
    "sg:province":"TX",
    "sg:tags":[
        "organization",
        "noncommercial"
    ],
    "wof:name":"301st Veterans Association",
    "wof:placetype":"venue"
},
  "geometry": {"coordinates":[-97.38637199999999,32.66033],"type":"Point"}
}