{
  "type": "Feature",
  "properties": {
    "iso:country":"US",
    "sg:address":"303 W Wall St",
    "sg:city":"Midland",
    "sg:classifiers":[
        {
            "category":"Farming",
            "subcategory":"Livestock Farm",
            "type":"Manufacturing & Wholesale Goods"
        }
    ],
    "sg:phone":"+1 432 684 6357",
    "sg:postcode":"79701",
    "sg:province":"TX",
    "sg:tags":[
        "ranch"
    ],
    "wof:name":"Scharbauer Cattle Co",
    "wof:placetype":"venue"
},
  "geometry": {"coordinates":[-102.078033,31.997358],"type":"Point"}
}