{
  "type": "Feature",
  "properties": {
    "iso:country":"US",
    "sg:address":"3718 Grennoch Ln",
    "sg:city":"Houston",
    "sg:classifiers":[
        {
            "category":"Professional",
            "subcategory":"Management & Consulting",
            "type":"Services"
        }
    ],
    "sg:phone":"+1 713 661 9056",
    "sg:postcode":"77025",
    "sg:province":"TX",
    "sg:tags":[
        "business"
    ],
    "wof:name":"Philippe Eddy & Associates",
    "wof:placetype":"venue"
},
  "geometry": {"coordinates":[-95.436654,29.695237],"type":"Point"}
}