{
  "type": "Feature",
  "properties": {
    "iso:country":"US",
    "sg:address":"6900 N 10th St",
    "sg:city":"Mcallen",
    "sg:classifiers":[
        {
            "category":"Shopping",
            "subcategory":"Pharmacy",
            "type":"Retail Goods"
        }
    ],
    "sg:phone":"+1 956 928 0911",
    "sg:postcode":"78504",
    "sg:province":"TX",
    "sg:tags":[
        "equipment"
    ],
    "wof:name":"Saenz Medical Pharmacy",
    "wof:placetype":"venue"
},
  "geometry": {"coordinates":[-98.21971600000001,26.26309],"type":"Point"}
}