{
  "type": "Feature",
  "properties": {
    "iso:country":"US",
    "sg:address":"2521 Spring Ln",
    "sg:city":"Austin",
    "sg:classifiers":[
        {
            "category":"Professional",
            "subcategory":"Management & Consulting",
            "type":"Services"
        }
    ],
    "sg:phone":"+1 512 478 4704",
    "sg:postcode":"78703",
    "sg:province":"TX",
    "sg:tags":[
        "direct",
        "sales",
        "real estate",
        "retail"
    ],
    "wof:name":"Evonne Atlas Realtor",
    "wof:placetype":"venue"
},
  "geometry": {"coordinates":[-97.76499,30.299821],"type":"Point"}
}