{
  "type": "Feature",
  "properties": {
    "iso:country":"US",
    "sg:address":"5803 Thunderbird St",
    "sg:city":"Leander",
    "sg:classifiers":[
        {
            "category":"Wholesale",
            "subcategory":"Furniture",
            "type":"Manufacturing & Wholesale Goods"
        }
    ],
    "sg:phone":"+1 512 267 7101",
    "sg:postcode":"78645",
    "sg:province":"TX",
    "wof:name":"Headset Innovations LP",
    "wof:placetype":"venue"
},
  "geometry": {"coordinates":[-97.98798600000001,30.452469],"type":"Point"}
}