{
  "type": "Feature",
  "properties": {
    "iso:country":"US",
    "sg:address":"12217 Red Sun Dr",
    "sg:city":"El Paso",
    "sg:classifiers":[
        {
            "category":"Shopping",
            "subcategory":"Computers & Home Electronics",
            "type":"Retail Goods"
        }
    ],
    "sg:phone":"+1 915 921 1896",
    "sg:postcode":"79938",
    "sg:province":"TX",
    "sg:tags":[
        "equipment",
        "dealer"
    ],
    "wof:name":"O'Brien Enterprises",
    "wof:placetype":"venue"
},
  "geometry": {"coordinates":[-106.26391,31.773099],"type":"Point"}
}