{
  "type": "Feature",
  "properties": {
    "iso:country":"US",
    "sg:address":"7037 State Hwy 186",
    "sg:city":"Raymondville",
    "sg:phone":"+1 956 248 5297",
    "sg:postcode":"78580",
    "sg:province":"TX",
    "sg:tags":[
        "farm",
        "corn",
        "grain",
        "cash",
        "cotton"
    ],
    "wof:name":"David Shewmaker",
    "wof:placetype":"venue"
},
  "geometry": {"coordinates":[-97.76997299999999,26.482054],"type":"Point"}
}