{
  "type": "Feature",
  "properties": {
    "iso:country":"US",
    "sg:address":"3999 Ballymena Dr",
    "sg:city":"Frisco",
    "sg:classifiers":[
        {
            "category":"Professional",
            "type":"Services"
        },
        {
            "category":"Professional",
            "subcategory":"Computer Services",
            "type":"Services"
        }
    ],
    "sg:phone":"+1 972 668 5888",
    "sg:postcode":"75034",
    "sg:province":"TX",
    "sg:tags":[
        "internet"
    ],
    "wof:name":"Globe Speed Internet",
    "wof:placetype":"venue"
},
  "geometry": {"coordinates":[-96.850898,33.115482],"type":"Point"}
}