{
  "type": "Feature",
  "properties": {
    "iso:country":"US",
    "sg:address":"804 9th St",
    "sg:city":"Terrell",
    "sg:classifiers":[
        {
            "category":"Farming",
            "subcategory":"Livestock Farm",
            "type":"Manufacturing & Wholesale Goods"
        }
    ],
    "sg:phone":"+1 972 563 6220",
    "sg:postcode":"75160",
    "sg:province":"TX",
    "sg:tags":[
        "beef",
        "feedlot",
        "cattle"
    ],
    "wof:name":"Clarence Coffman",
    "wof:placetype":"venue"
},
  "geometry": {"coordinates":[-96.28233299999999,32.751187],"type":"Point"}
}