{
  "type": "Feature",
  "properties": {
    "iso:country":"US",
    "sg:address":"128 W Corral Ave",
    "sg:city":"Kingsville",
    "sg:classifiers":[
        {
            "category":"Food & Beverages",
            "subcategory":"Groceries & Convenience Stores",
            "type":"Retail Goods"
        }
    ],
    "sg:phone":"+1 361 516 0728",
    "sg:postcode":"78363",
    "sg:province":"TX",
    "wof:name":"K-2 Food Mart",
    "wof:placetype":"venue"
},
  "geometry": {"coordinates":[-97.868394,27.530539],"type":"Point"}
}