{
  "type": "Feature",
  "properties": {
    "iso:country":"US",
    "sg:address":"1201 Pine St",
    "sg:city":"Bastrop",
    "sg:classifiers":[
        {
            "category":"Food & Beverages",
            "subcategory":"Bakery",
            "type":"Retail Goods"
        }
    ],
    "sg:phone":"+1 512 321 0317",
    "sg:postcode":"78602",
    "sg:province":"TX",
    "sg:tags":[
        "bank"
    ],
    "sg:website":"http://www.bastropfoodpantry.org",
    "wof:name":"Bastrop County Emergency Food Pantry And Support Center, Inc",
    "wof:placetype":"venue"
},
  "geometry": {"coordinates":[-97.31382000000001,30.109489],"type":"Point"}
}