{
  "type": "Feature",
  "properties": {
    "iso:country":"US",
    "sg:address":"3118 McDonald Rd",
    "sg:city":"Tyler",
    "sg:classifiers":[
        {
            "category":"Professional",
            "subcategory":"Accounting & Tax Preparation",
            "type":"Services"
        }
    ],
    "sg:phone":"+1 903 566 8114",
    "sg:postcode":"75701",
    "sg:province":"TX",
    "wof:name":"Christi Dennard CPA",
    "wof:placetype":"venue"
},
  "geometry": {"coordinates":[-95.255821,32.32282],"type":"Point"}
}