{
  "type": "Feature",
  "properties": {
    "iso:country":"US",
    "sg:address":"4418 Mowery Rd",
    "sg:city":"Houston",
    "sg:classifiers":[
        {
            "category":"Education",
            "subcategory":"Special Training",
            "type":"Public Place"
        }
    ],
    "sg:phone":"+1 713 734 8740",
    "sg:postcode":"77047",
    "sg:province":"TX",
    "wof:name":"Nell Cheer Inc",
    "wof:placetype":"venue"
},
  "geometry": {"coordinates":[-95.358587,29.63604],"type":"Point"}
}