{
  "type": "Feature",
  "properties": {
    "iso:country":"US",
    "sg:address":"1900 S Loop W Suite 540",
    "sg:city":"Houston",
    "sg:classifiers":[
        {
            "category":"Organizations",
            "subcategory":"Community Association",
            "type":"Services"
        }
    ],
    "sg:phone":"+1 713 864 2925",
    "sg:postcode":"77054",
    "sg:province":"TX",
    "wof:name":"Houston Police Patrolmen's Union",
    "wof:placetype":"venue"
},
  "geometry": {"coordinates":[-95.407661,29.678511],"type":"Point"}
}