{
  "type": "Feature",
  "properties": {
    "iso:country":"US",
    "sg:address":"5003 Live Oak St",
    "sg:city":"Dallas",
    "sg:classifiers":[
        {
            "category":"Building & Trades",
            "subcategory":"Cleaning & Sanitation",
            "type":"Services"
        }
    ],
    "sg:phone":"+1 214 205 7911",
    "sg:postcode":"75206",
    "sg:province":"TX",
    "sg:tags":[
        "home"
    ],
    "sg:website":"www.rosebudwoodfloors.com",
    "wof:name":"Rosebud Wood Floors",
    "wof:placetype":"venue"
},
  "geometry": {"coordinates":[-96.771434,32.804136],"type":"Point"}
}