{
  "type": "Feature",
  "properties": {
    "iso:country":"US",
    "sg:address":"1611 Lake Arbor Dr",
    "sg:city":"Seabrook",
    "sg:classifiers":[
        {
            "category":"Professional",
            "type":"Services"
        }
    ],
    "sg:phone":"+1 281 326 3188",
    "sg:postcode":"77586",
    "sg:province":"TX",
    "wof:name":"NASA Oil Inc",
    "wof:placetype":"venue"
},
  "geometry": {"coordinates":[-95.044749,29.577111],"type":"Point"}
}