{
  "type": "Feature",
  "properties": {
    "iso:country":"US",
    "sg:address":"4263 Boca Bay Dr",
    "sg:city":"Dallas",
    "sg:classifiers":[
        {
            "category":"Shopping",
            "subcategory":"Clothing, Apparel, & Fashions",
            "type":"Retail Goods"
        }
    ],
    "sg:phone":"+1 972 247 6350",
    "sg:postcode":"75244",
    "sg:province":"TX",
    "wof:name":"Ritas Scarf Shop",
    "wof:placetype":"venue"
},
  "geometry": {"coordinates":[-96.84121399999999,32.916452],"type":"Point"}
}