{
  "type": "Feature",
  "properties": {
    "iso:country":"US",
    "sg:address":"12725 Danvers Dr",
    "sg:city":"Houston",
    "sg:classifiers":[
        {
            "category":"Home & Garden",
            "subcategory":"Building Materials",
            "type":"Retail Goods"
        }
    ],
    "sg:phone":"+1 281 458 7090",
    "sg:postcode":"77049",
    "sg:province":"TX",
    "wof:name":"Td Supply",
    "wof:placetype":"venue"
},
  "geometry": {"coordinates":[-95.204459,29.832565],"type":"Point"}
}