{
  "type": "Feature",
  "properties": {
    "iso:country":"US",
    "sg:address":"9160 FM 78",
    "sg:city":"Converse",
    "sg:classifiers":[
        {
            "category":"Shopping",
            "subcategory":"Discount & Variety Stores",
            "type":"Retail Goods"
        }
    ],
    "sg:phone":"+1 210 566 7121",
    "sg:postcode":"78109",
    "sg:province":"TX",
    "sg:tags":[
        "department"
    ],
    "wof:name":"Dollar General",
    "wof:placetype":"venue"
},
  "geometry": {"coordinates":[-98.308357,29.513707],"type":"Point"}
}