{
  "type": "Feature",
  "properties": {
    "iso:country":"US",
    "sg:address":"3708 Audubon Pl",
    "sg:city":"Houston",
    "sg:classifiers":[
        {
            "category":"Banks & Credit Unions",
            "subcategory":"Investment Brokerage",
            "type":"Services"
        }
    ],
    "sg:phone":"+1 713 224 1317",
    "sg:postcode":"77006",
    "sg:province":"TX",
    "sg:tags":[
        "advisory",
        "financial"
    ],
    "wof:name":"Maddox Interests",
    "wof:placetype":"venue"
},
  "geometry": {"coordinates":[-95.386556,29.738927],"type":"Point"}
}