{
  "type": "Feature",
  "properties": {
    "iso:country":"US",
    "sg:address":"308 Campbell Dr",
    "sg:city":"Canyon Lake",
    "sg:classifiers":[
        {
            "category":"Building & Trades",
            "subcategory":"Construction",
            "type":"Services"
        }
    ],
    "sg:phone":"+1 830 899 4222",
    "sg:postcode":"78133",
    "sg:province":"TX",
    "sg:tags":[
        "carpenter"
    ],
    "wof:name":"Austin Carpentry",
    "wof:placetype":"venue"
},
  "geometry": {"coordinates":[-98.26603,29.844397],"type":"Point"}
}