{
  "type": "Feature",
  "properties": {
    "iso:country":"US",
    "sg:address":"1008 W Airport Fwy",
    "sg:city":"Irving",
    "sg:classifiers":[
        {
            "category":"Food & Beverages",
            "subcategory":"Groceries & Convenience Stores",
            "type":"Retail Goods"
        }
    ],
    "sg:phone":"+1 972 438 6865",
    "sg:postcode":"75062",
    "sg:province":"TX",
    "wof:name":"India Mart",
    "wof:placetype":"venue"
},
  "geometry": {"coordinates":[-96.957802,32.8368],"type":"Point"}
}