{
  "type": "Feature",
  "properties": {
    "iso:country":"US",
    "sg:address":"9008 Dyer St",
    "sg:city":"El Paso",
    "sg:classifiers":[
        {
            "category":"Autos & Motor Vehicles",
            "subcategory":"Automobile Sales",
            "type":"Retail Goods"
        }
    ],
    "sg:phone":"+1 915 755 1116",
    "sg:postcode":"79904",
    "sg:province":"TX",
    "sg:tags":[
        "car",
        "dealer"
    ],
    "wof:name":"Direct Auto Sales",
    "wof:placetype":"venue"
},
  "geometry": {"coordinates":[-106.429197,31.867889],"type":"Point"}
}