{
  "type": "Feature",
  "properties": {
    "iso:country":"US",
    "sg:address":"205 Hwy 35 N",
    "sg:city":"Rockport",
    "sg:classifiers":[
        {
            "category":"Restaurant",
            "type":"Food & Drink"
        }
    ],
    "sg:phone":"+1 361 729 4985",
    "sg:postcode":"78382",
    "sg:province":"TX",
    "sg:tags":[
        "eating"
    ],
    "wof:name":"The Diner",
    "wof:placetype":"venue"
},
  "geometry": {"coordinates":[-97.052513,28.027367],"type":"Point"}
}