{
  "type": "Feature",
  "properties": {
    "iso:country":"US",
    "sg:address":"1300 Hogan Ln",
    "sg:city":"Waco",
    "sg:classifiers":[
        {
            "category":"Food & Beverages",
            "subcategory":"Bakery",
            "type":"Retail Goods"
        }
    ],
    "sg:phone":"+1 254 799 4421",
    "sg:postcode":"76705",
    "sg:province":"TX",
    "sg:tags":[
        "baker"
    ],
    "wof:name":"Mrs Baird's Bakeries Inc",
    "wof:placetype":"venue"
},
  "geometry": {"coordinates":[-97.10866799999999,31.595387],"type":"Point"}
}