{
  "type": "Feature",
  "properties": {
    "iso:country":"US",
    "sg:address":"528 S Dooley St",
    "sg:city":"Grapevine",
    "sg:classifiers":[
        {
            "category":"Mining & Drilling",
            "type":"Manufacturing & Wholesale Goods"
        }
    ],
    "sg:phone":"+1 817 912 0250",
    "sg:postcode":"76051",
    "sg:province":"TX",
    "sg:tags":[
        "stone"
    ],
    "wof:name":"Stone & Glazing Consulting",
    "wof:placetype":"venue"
},
  "geometry": {"coordinates":[-97.073493,32.935897],"type":"Point"}
}