{
  "type": "Feature",
  "properties": {
    "iso:country":"US",
    "sg:address":"705 Valley Mills Dr",
    "sg:city":"Wylie",
    "sg:classifiers":[
        {
            "category":"Professional",
            "subcategory":"Printing & Photocopies",
            "type":"Services"
        }
    ],
    "sg:phone":"+1 972 429 0756",
    "sg:postcode":"75098",
    "sg:province":"TX",
    "sg:tags":[
        "lithographer"
    ],
    "wof:name":"Rhodes Giclee Prints",
    "wof:placetype":"venue"
},
  "geometry": {"coordinates":[-96.54257200000001,33.02623],"type":"Point"}
}