{
  "type": "Feature",
  "properties": {
    "iso:country":"US",
    "sg:address":"1425 Elizabeth St",
    "sg:city":"Hurst",
    "sg:classifiers":[
        {
            "category":"Insurance",
            "subcategory":"Insurance Agent",
            "type":"Services"
        }
    ],
    "sg:phone":"+1 817 285 7878",
    "sg:postcode":"76053",
    "sg:province":"TX",
    "sg:tags":[
        "accident"
    ],
    "wof:name":"Preferred Senior Health Care",
    "wof:placetype":"venue"
},
  "geometry": {"coordinates":[-97.174907,32.838934],"type":"Point"}
}