{
  "type": "Feature",
  "properties": {
    "iso:country":"US",
    "sg:address":"1120 Medical Dr",
    "sg:city":"Tyler",
    "sg:classifiers":[
        {
            "category":"Health Services",
            "subcategory":"Health Practitioner",
            "type":"Services"
        }
    ],
    "sg:phone":"+1 903 597 2086",
    "sg:postcode":"75701",
    "sg:province":"TX",
    "sg:tags":[
        "nursing"
    ],
    "wof:name":"Texas Home Health America LP",
    "wof:placetype":"venue"
},
  "geometry": {"coordinates":[-95.288404,32.338023],"type":"Point"}
}