{
  "type": "Feature",
  "properties": {
    "iso:country":"US",
    "sg:address":"402 Logan Ave",
    "sg:city":"Laredo",
    "sg:classifiers":[
        {
            "category":"Freight",
            "type":"Transportation"
        },
        {
            "category":"Professional",
            "subcategory":"Business Services",
            "type":"Services"
        }
    ],
    "sg:phone":"+1 956 722 8487",
    "sg:postcode":"78040",
    "sg:province":"TX",
    "sg:tags":[
        "packaging",
        "arrangement"
    ],
    "wof:name":"Frontier Logistics LLC",
    "wof:placetype":"venue"
},
  "geometry": {"coordinates":[-99.48920099999999,27.499721],"type":"Point"}
}