{
  "type": "Feature",
  "properties": {
    "iso:country":"US",
    "sg:address":"3114 Martin Luther King Jr Blvd",
    "sg:city":"Dallas",
    "sg:classifiers":[
        {
            "category":"Retail",
            "subcategory":"Funeral Services",
            "type":"Services"
        }
    ],
    "sg:phone":"+1 214 421 9774",
    "sg:postcode":"75215",
    "sg:province":"TX",
    "sg:tags":[
        "director",
        "embalmer",
        "plans-pre-arranged"
    ],
    "wof:name":"Cooper",
    "wof:placetype":"venue"
},
  "geometry": {"coordinates":[-96.76465899999999,32.772426],"type":"Point"}
}