{
  "type": "Feature",
  "properties": {
    "iso:country":"US",
    "sg:address":"2251 Vantage St",
    "sg:city":"Dallas",
    "sg:classifiers":[
        {
            "category":"Wholesale",
            "subcategory":"Groceries",
            "type":"Manufacturing & Wholesale Goods"
        }
    ],
    "sg:phone":"+1 214 630 8713",
    "sg:postcode":"75207",
    "sg:province":"TX",
    "sg:tags":[
        "specializing",
        "eastern",
        "food",
        "french",
        "middle",
        "italian"
    ],
    "wof:name":"Culinary Imports",
    "wof:placetype":"venue"
},
  "geometry": {"coordinates":[-96.835015,32.799361],"type":"Point"}
}