{
  "type": "Feature",
  "properties": {
    "iso:country":"US",
    "sg:address":"1023 E Wintergreen Rd",
    "sg:city":"Duncanville",
    "sg:classifiers":[
        {
            "category":"Building & Trades",
            "subcategory":"Construction",
            "type":"Services"
        }
    ],
    "sg:phone":"+1 972 296 1156",
    "sg:postcode":"75137",
    "sg:province":"TX",
    "sg:tags":[
        "contractor"
    ],
    "wof:name":"McCasland",
    "wof:placetype":"venue"
},
  "geometry": {"coordinates":[-96.922314,32.619036],"type":"Point"}
}