{
  "type": "Feature",
  "properties": {
    "iso:country":"US",
    "sg:address":"500 W Fm 1382",
    "sg:city":"Cedar Hill",
    "sg:classifiers":[
        {
            "category":"Shopping",
            "subcategory":"Clothing, Apparel, & Fashions",
            "type":"Retail Goods"
        }
    ],
    "sg:phone":"+1 469 272 0223",
    "sg:postcode":"75104",
    "sg:province":"TX",
    "sg:tags":[
        "accessory",
        "clothing",
        "women's"
    ],
    "wof:name":"Exquisite Lady",
    "wof:placetype":"venue"
},
  "geometry": {"coordinates":[-96.95177,32.605272],"type":"Point"}
}