{
  "type": "Feature",
  "properties": {
    "iso:country":"US",
    "sg:address":"18327 Blanchmont Ln",
    "sg:city":"Houston",
    "sg:classifiers":[
        {
            "category":"Professional",
            "subcategory":"Computer Services",
            "type":"Services"
        }
    ],
    "sg:phone":"+1 281 734 2462",
    "sg:postcode":"77058",
    "sg:province":"TX",
    "sg:tags":[
        "related"
    ],
    "wof:name":"Burknett",
    "wof:placetype":"venue"
},
  "geometry": {"coordinates":[-95.09468200000001,29.544145],"type":"Point"}
}