{
  "type": "Feature",
  "properties": {
    "iso:country":"US",
    "sg:address":"940 Payton Gin Rd",
    "sg:city":"Austin",
    "sg:classifiers":[
        {
            "category":"Health Services",
            "subcategory":"Doctor",
            "type":"Services"
        }
    ],
    "sg:phone":"+1 512 836 5250",
    "sg:postcode":"78758",
    "sg:province":"TX",
    "wof:name":"Bayne H Mark",
    "wof:placetype":"venue"
},
  "geometry": {"coordinates":[-97.702956,30.359054],"type":"Point"}
}