{
  "type": "Feature",
  "properties": {
    "iso:country":"US",
    "sg:address":"15305 N Dallas Pkwy Ste 125",
    "sg:city":"Addison",
    "sg:classifiers":[
        {
            "category":"Retail",
            "subcategory":"Event Space",
            "type":"Services"
        }
    ],
    "sg:phone":"+1 469 438 4038",
    "sg:postcode":"75001",
    "sg:province":"TX",
    "sg:tags":[
        "venue"
    ],
    "wof:name":"Colonnade Atrium",
    "wof:placetype":"venue"
},
  "geometry": {"coordinates":[-96.82164,32.958294],"type":"Point"}
}