{
  "type": "Feature",
  "properties": {
    "iso:country":"US",
    "sg:address":"408 N Texas Blvd",
    "sg:city":"Alice",
    "sg:classifiers":[
        {
            "category":"Social Services",
            "subcategory":"Child Care",
            "type":"Services"
        }
    ],
    "sg:phone":"+1 361 664 2310",
    "sg:postcode":"78332",
    "sg:province":"TX",
    "wof:name":"A Brighter Child Daycare",
    "wof:placetype":"venue"
},
  "geometry": {"coordinates":[-98.064684,27.755054],"type":"Point"}
}