{
  "type": "Feature",
  "properties": {
    "iso:country":"US",
    "sg:address":"138 Grant Ave",
    "sg:city":"San Antonio",
    "sg:classifiers":[
        {
            "category":"Professional",
            "subcategory":"Management & Consulting",
            "type":"Services"
        }
    ],
    "sg:phone":"+1 210 824 6547",
    "sg:postcode":"78209",
    "sg:province":"TX",
    "wof:name":"Malco Management LLC",
    "wof:placetype":"venue"
},
  "geometry": {"coordinates":[-98.468498,29.474055],"type":"Point"}
}