{
  "type": "Feature",
  "properties": {
    "iso:country":"US",
    "sg:address":"7503 Willow Oak Dr",
    "sg:city":"Baytown",
    "sg:classifiers":[
        {
            "category":"Professional",
            "subcategory":"Business Services",
            "type":"Services"
        }
    ],
    "sg:phone":"+1 281 383 2793",
    "sg:postcode":"77521",
    "sg:province":"TX",
    "wof:name":"Camo Country",
    "wof:placetype":"venue"
},
  "geometry": {"coordinates":[-94.91148800000001,29.801441],"type":"Point"}
}