{
  "type": "Feature",
  "properties": {
    "iso:country":"US",
    "sg:address":"1740 Central Blvd",
    "sg:city":"Brownsville",
    "sg:classifiers":[
        {
            "category":"Restaurant",
            "type":"Food & Drink"
        }
    ],
    "sg:phone":"+1 956 542 8838",
    "sg:postcode":"78520",
    "sg:province":"TX",
    "sg:tags":[
        "eating"
    ],
    "wof:name":"Toddle Inn",
    "wof:placetype":"venue"
},
  "geometry": {"coordinates":[-97.51093,25.929594],"type":"Point"}
}