{
  "type": "Feature",
  "properties": {
    "iso:country":"US",
    "sg:address":"2200 Southwest Fwy",
    "sg:city":"Houston",
    "sg:classifiers":[
        {
            "category":"Real Estate",
            "subcategory":"Architect",
            "type":"Services"
        }
    ],
    "sg:phone":"+1 713 522 1851",
    "sg:postcode":"77098",
    "sg:province":"TX",
    "sg:tags":[
        "architectural"
    ],
    "wof:name":"Clifton D Thomason",
    "wof:placetype":"venue"
},
  "geometry": {"coordinates":[-95.414344,29.731036],"type":"Point"}
}