{
  "type": "Feature",
  "properties": {
    "iso:country":"US",
    "sg:address":"107 E Pearl St",
    "sg:city":"Granbury",
    "sg:classifiers":[
        {
            "category":"Professional",
            "subcategory":"Lawyer & Legal Services",
            "type":"Services"
        }
    ],
    "sg:phone":"+1 817 573 8872",
    "sg:postcode":"76048",
    "sg:province":"TX",
    "wof:name":"Brown & Walton PC",
    "wof:placetype":"venue"
},
  "geometry": {"coordinates":[-97.787586,32.442282],"type":"Point"}
}