{
  "type": "Feature",
  "properties": {
    "iso:country":"US",
    "sg:address":"12463 Plum Dr",
    "sg:city":"Lindale",
    "sg:classifiers":[
        {
            "category":"Building & Trades",
            "subcategory":"Electrical",
            "type":"Services"
        }
    ],
    "sg:phone":"+1 903 881 8262",
    "sg:postcode":"75771",
    "sg:province":"TX",
    "sg:tags":[
        "electric",
        "contractor"
    ],
    "wof:name":"B C Electric",
    "wof:placetype":"venue"
},
  "geometry": {"coordinates":[-95.373282,32.53723],"type":"Point"}
}