{
  "type": "Feature",
  "properties": {
    "iso:country":"US",
    "sg:address":"582 S Belt Line Rd",
    "sg:city":"Irving",
    "sg:classifiers":[
        {
            "category":"Restaurant",
            "type":"Food & Drink"
        }
    ],
    "sg:phone":"+1 972 313 9290",
    "sg:postcode":"75060",
    "sg:province":"TX",
    "sg:tags":[
        "eating"
    ],
    "wof:name":"Ciros Pizzeria",
    "wof:placetype":"venue"
},
  "geometry": {"coordinates":[-96.99384000000001,32.810762],"type":"Point"}
}