{
  "type": "Feature",
  "properties": {
    "iso:country":"US",
    "sg:address":"10314 Meadow Lake Ln",
    "sg:city":"Houston",
    "sg:classifiers":[
        {
            "category":"Communications",
            "type":"Services"
        }
    ],
    "sg:phone":"+1 713 784 3870",
    "sg:postcode":"77042",
    "sg:province":"TX",
    "sg:tags":[
        "web",
        "design"
    ],
    "sg:website":"www.jm-solutions.com",
    "wof:name":"J M SOLUTIONS",
    "wof:placetype":"venue"
},
  "geometry": {"coordinates":[-95.55574799999999,29.74278],"type":"Point"}
}