{
  "type": "Feature",
  "properties": {
    "iso:country":"US",
    "sg:address":"505 Root Ave",
    "sg:city":"Killeen",
    "sg:classifiers":[
        {
            "category":"Retail",
            "subcategory":"Repair Shop",
            "type":"Services"
        }
    ],
    "sg:phone":"+1 254 200 2800",
    "sg:postcode":"76541",
    "sg:province":"TX",
    "wof:name":"D & D Rental & Repair",
    "wof:placetype":"venue"
},
  "geometry": {"coordinates":[-97.73259,31.124267],"type":"Point"}
}