{
  "type": "Feature",
  "properties": {
    "iso:country":"US",
    "sg:address":"4006 S Lamar Blvd",
    "sg:city":"Austin",
    "sg:classifiers":[
        {
            "category":"Utilities",
            "subcategory":"Mobile Phone",
            "type":"Services"
        }
    ],
    "sg:phone":"+1 512 443 4484",
    "sg:postcode":"78704",
    "sg:province":"TX",
    "sg:tags":[
        "communication",
        "radiotelephone"
    ],
    "wof:name":"S W B Wireless",
    "wof:placetype":"venue"
},
  "geometry": {"coordinates":[-97.791077,30.237181],"type":"Point"}
}