{
  "type": "Feature",
  "properties": {
    "iso:country":"US",
    "sg:address":"12042 Blanco Rd",
    "sg:city":"San Antonio",
    "sg:classifiers":[
        {
            "category":"Banks & Credit Unions",
            "subcategory":"Investment Brokerage",
            "type":"Services"
        }
    ],
    "sg:phone":"+1 210 349 8517",
    "sg:postcode":"78216",
    "sg:province":"TX",
    "sg:tags":[
        "consultant",
        "planning",
        "financial"
    ],
    "sg:website":"www.wssonline.com",
    "wof:name":"Wall Street Svc Inc",
    "wof:placetype":"venue"
},
  "geometry": {"coordinates":[-98.510735,29.549153],"type":"Point"}
}