{
  "type": "Feature",
  "properties": {
    "iso:country":"US",
    "sg:address":"150 Arizona St",
    "sg:city":"Van",
    "sg:classifiers":[
        {
            "category":"Manufacturing",
            "subcategory":"Printing",
            "type":"Manufacturing & Wholesale Goods"
        }
    ],
    "sg:phone":"+1 903 833 9295",
    "sg:postcode":"75790",
    "sg:province":"TX",
    "sg:tags":[
        "commercial"
    ],
    "wof:name":"Print House",
    "wof:placetype":"venue"
},
  "geometry": {"coordinates":[-95.625514,32.526435],"type":"Point"}
}