{
  "type": "Feature",
  "properties": {
    "iso:country":"US",
    "sg:address":"699 Lady Of The Lake Blvd",
    "sg:city":"Lewisville",
    "sg:classifiers":[
        {
            "category":"Sports & Exercise",
            "subcategory":"Golf",
            "type":"Entertainment"
        }
    ],
    "sg:phone":"+1 972 899 2750",
    "sg:postcode":"75056",
    "sg:province":"TX",
    "sg:tags":[
        "instruction"
    ],
    "wof:name":"Performax Golf Academy",
    "wof:placetype":"venue"
},
  "geometry": {"coordinates":[-96.90634900000001,33.042709],"type":"Point"}
}