{
  "type": "Feature",
  "properties": {
    "iso:country":"US",
    "sg:address":"2417 Trellis Ln",
    "sg:city":"Plano",
    "sg:classifiers":[
        {
            "category":"Communications",
            "subcategory":"Film & Video Production",
            "type":"Services"
        }
    ],
    "sg:phone":"+1 972 596 3801",
    "sg:postcode":"75075",
    "sg:province":"TX",
    "sg:tags":[
        "motion",
        "picture",
        "taping"
    ],
    "wof:name":"Electronic Systems",
    "wof:placetype":"venue"
},
  "geometry": {"coordinates":[-96.76777199999999,33.032669],"type":"Point"}
}