{
  "type": "Feature",
  "properties": {
    "iso:country":"US",
    "sg:address":"1793 N Fry Rd",
    "sg:city":"Katy",
    "sg:classifiers":[
        {
            "category":"Professional",
            "type":"Services"
        },
        {
            "category":"Deli",
            "type":"Food & Drink"
        },
        {
            "category":"Restaurant",
            "type":"Food & Drink"
        }
    ],
    "sg:phone":"+1 281 578 6653",
    "sg:postcode":"77449",
    "sg:province":"TX",
    "sg:tags":[
        "delicatessen",
        "lunch",
        "american",
        "caterer",
        "brunch",
        "breakfast"
    ],
    "wof:name":"Murphy's Deli",
    "wof:placetype":"venue"
},
  "geometry": {"coordinates":[-95.720062,29.8602],"type":"Point"}
}