{
  "type": "Feature",
  "properties": {
    "iso:country":"US",
    "sg:address":"186 Stratton Ln",
    "sg:city":"Beaumont",
    "sg:classifiers":[
        {
            "category":"Utilities",
            "subcategory":"Telephone",
            "type":"Services"
        }
    ],
    "sg:phone":"+1 409 860 3700",
    "sg:postcode":"77707",
    "sg:province":"TX",
    "sg:tags":[
        "communications"
    ],
    "wof:name":"Impact Telephone & Data",
    "wof:placetype":"venue"
},
  "geometry": {"coordinates":[-94.149586,30.077226],"type":"Point"}
}