{
  "type": "Feature",
  "properties": {
    "iso:country":"US",
    "sg:address":"2012 Towne View Blvd",
    "sg:city":"Flower Mound",
    "sg:classifiers":[
        {
            "category":"Retail",
            "subcategory":"Repair Shop",
            "type":"Services"
        }
    ],
    "sg:phone":"+1 972 255 2399",
    "sg:postcode":"75028",
    "sg:province":"TX",
    "sg:tags":[
        "refrigeration"
    ],
    "wof:name":"Alejandrino Bear",
    "wof:placetype":"venue"
},
  "geometry": {"coordinates":[-97.066875,33.012848],"type":"Point"}
}