{
  "type": "Feature",
  "properties": {
    "iso:country":"US",
    "sg:address":"220 E 5th St",
    "sg:city":"Bonham",
    "sg:classifiers":[
        {
            "category":"Government",
            "subcategory":"Fire Station",
            "type":"Public Place"
        }
    ],
    "sg:phone":"+1 903 583 3731",
    "sg:postcode":"75418",
    "sg:province":"TX",
    "sg:tags":[
        "department"
    ],
    "wof:name":"Bonham Fire Hall",
    "wof:placetype":"venue"
},
  "geometry": {"coordinates":[-96.177733,33.577986],"type":"Point"}
}