{
  "type": "Feature",
  "properties": {
    "iso:country":"US",
    "sg:address":"1205 Morse Cove",
    "sg:city":"Georgetown",
    "sg:classifiers":[
        {
            "category":"Government",
            "subcategory":"Office",
            "type":"Public Place"
        }
    ],
    "sg:phone":"+1 254 287 7757",
    "sg:postcode":"78628",
    "sg:province":"TX",
    "sg:tags":[
        "national",
        "security"
    ],
    "wof:name":"21st Cav Brigade",
    "wof:placetype":"venue"
},
  "geometry": {"coordinates":[-97.69610299999999,30.656375],"type":"Point"}
}