{
  "type": "Feature",
  "properties": {
    "iso:country":"US",
    "sg:address":"3601 N Abram Rd",
    "sg:city":"Palmview",
    "sg:classifiers":[
        {
            "category":"Wholesale",
            "subcategory":"Hardware",
            "type":"Manufacturing & Wholesale Goods"
        },
        {
            "category":"Home & Garden",
            "subcategory":"Hardware",
            "type":"Retail Goods"
        },
        {
            "category":"Home & Garden",
            "subcategory":"Building Materials",
            "type":"Retail Goods"
        },
        {
            "category":"Manufacturing",
            "subcategory":"Building Materials",
            "type":"Manufacturing & Wholesale Goods"
        }
    ],
    "sg:phone":"+1 956 581 0672",
    "sg:postcode":"78572",
    "sg:province":"TX",
    "sg:tags":[
        "sand",
        "gravel",
        "hardware-builders",
        "store",
        "asphalt"
    ],
    "sg:website":"http://www.fordyceco.com",
    "wof:name":"Fordyce Holdings Inc",
    "wof:placetype":"venue"
},
  "geometry": {"coordinates":[-98.39317,26.26866],"type":"Point"}
}