{
  "type": "Feature",
  "properties": {
    "iso:country":"US",
    "sg:address":"13740 Research Blvd Ste L8E",
    "sg:city":"Austin",
    "sg:classifiers":[
        {
            "category":"Personal",
            "subcategory":"Massage",
            "type":"Services"
        }
    ],
    "sg:phone":"+1 512 695 5980",
    "sg:postcode":"78750",
    "sg:province":"TX",
    "sg:website":"www.austinhealingmassage.com",
    "wof:name":"Austin Healing Massage",
    "wof:placetype":"venue"
},
  "geometry": {"coordinates":[-97.794946,30.459258],"type":"Point"}
}