{
  "type": "Feature",
  "properties": {
    "iso:country":"US",
    "sg:address":"1850 Hickory St",
    "sg:city":"Abilene",
    "sg:classifiers":[
        {
            "category":"Health Services",
            "subcategory":"Doctor",
            "type":"Services"
        }
    ],
    "sg:phone":"+1 325 677 2801",
    "sg:postcode":"79601",
    "sg:province":"TX",
    "sg:tags":[
        "physician",
        "surgeon"
    ],
    "wof:name":"Professional Association-Peds",
    "wof:placetype":"venue"
},
  "geometry": {"coordinates":[-99.73496,32.470429],"type":"Point"}
}