{
  "type": "Feature",
  "properties": {
    "iso:country":"US",
    "sg:address":"2203 Timberloch Pl",
    "sg:city":"Spring",
    "sg:classifiers":[
        {
            "category":"Insurance",
            "subcategory":"Insurance Agent",
            "type":"Services"
        }
    ],
    "sg:phone":"+1 281 363 2444",
    "sg:postcode":"77380",
    "sg:province":"TX",
    "sg:tags":[
        "agency"
    ],
    "wof:name":"Allstate",
    "wof:placetype":"venue"
},
  "geometry": {"coordinates":[-95.46060799999999,30.158441],"type":"Point"}
}