{
  "type": "Feature",
  "properties": {
    "iso:country":"US",
    "sg:address":"312 W Pacific Ave",
    "sg:city":"Gladewater",
    "sg:classifiers":[
        {
            "category":"Education",
            "subcategory":"Library",
            "type":"Public Place"
        }
    ],
    "sg:phone":"+1 903 845 2640",
    "sg:postcode":"75647",
    "sg:province":"TX",
    "wof:name":"Lee Public Library",
    "wof:placetype":"venue"
},
  "geometry": {"coordinates":[-94.946577,32.536314],"type":"Point"}
}