{
  "type": "Feature",
  "properties": {
    "iso:country":"US",
    "sg:address":"3045 Lackland Rd",
    "sg:city":"Fort Worth",
    "sg:classifiers":[
        {
            "category":"Insurance",
            "subcategory":"Insurance Agent",
            "type":"Services"
        }
    ],
    "sg:phone":"+1 817 732 7492",
    "sg:postcode":"76116",
    "sg:province":"TX",
    "sg:tags":[
        "agency"
    ],
    "wof:name":"Primerica",
    "wof:placetype":"venue"
},
  "geometry": {"coordinates":[-97.434556,32.730664],"type":"Point"}
}