{
  "type": "Feature",
  "properties": {
    "iso:country":"US",
    "sg:address":"2444 Settlers Way Blvd",
    "sg:city":"Sugar Land",
    "sg:classifiers":[
        {
            "category":"Professional",
            "type":"Services"
        }
    ],
    "sg:phone":"+1 281 980 8617",
    "sg:postcode":"77479",
    "sg:province":"TX",
    "sg:tags":[
        "establishment"
    ],
    "wof:name":"A 1 Dry Cleaners",
    "wof:placetype":"venue"
},
  "geometry": {"coordinates":[-95.597272,29.588426],"type":"Point"}
}