{
  "type": "Feature",
  "properties": {
    "iso:country":"US",
    "sg:address":"3522 Irvington Blvd",
    "sg:city":"Houston",
    "sg:classifiers":[
        {
            "category":"Restaurant",
            "type":"Food & Drink"
        }
    ],
    "sg:phone":"+1 713 622 8007",
    "sg:postcode":"77009",
    "sg:province":"TX",
    "sg:tags":[
        "eating"
    ],
    "wof:name":"Victorias Secret",
    "wof:placetype":"venue"
},
  "geometry": {"coordinates":[-95.360866,29.792123],"type":"Point"}
}