{
  "type": "Feature",
  "properties": {
    "iso:country":"US",
    "sg:address":"5507 Druid Ln",
    "sg:city":"Dallas",
    "sg:classifiers":[
        {
            "category":"Building & Trades",
            "subcategory":"Construction",
            "type":"Services"
        }
    ],
    "sg:phone":"+1 214 683 9702",
    "sg:postcode":"75209",
    "sg:province":"TX",
    "sg:tags":[
        "nonresidential"
    ],
    "wof:name":"Dmg Services",
    "wof:placetype":"venue"
},
  "geometry": {"coordinates":[-96.814421,32.848319],"type":"Point"}
}