{
  "type": "Feature",
  "properties": {
    "iso:country":"US",
    "sg:address":"1955 Dowlen Rd",
    "sg:city":"Beaumont",
    "sg:classifiers":[
        {
            "category":"Banks & Credit Unions",
            "subcategory":"Bank",
            "type":"Services"
        }
    ],
    "sg:phone":"+1 409 861 4957",
    "sg:postcode":"77706",
    "sg:province":"TX",
    "wof:name":"Neches Credit Union",
    "wof:placetype":"venue"
},
  "geometry": {"coordinates":[-94.17152900000001,30.096163],"type":"Point"}
}