{
  "type": "Feature",
  "properties": {
    "iso:country":"US",
    "sg:address":"7615 Spring Cypress Rd",
    "sg:city":"Spring",
    "sg:classifiers":[
        {
            "category":"Retail",
            "subcategory":"Laundry & Dry Cleaning",
            "type":"Services"
        }
    ],
    "sg:phone":"+1 281 376 8673",
    "sg:postcode":"77379",
    "sg:province":"TX",
    "wof:name":"Diaperz",
    "wof:placetype":"venue"
},
  "geometry": {"coordinates":[-95.54051,30.044909],"type":"Point"}
}