{
  "type": "Feature",
  "properties": {
    "iso:country":"US",
    "sg:address":"1833 Timbercreek Rd",
    "sg:city":"Benbrook",
    "sg:classifiers":[
        {
            "category":"Health Services",
            "subcategory":"Doctor",
            "type":"Services"
        }
    ],
    "sg:phone":"+1 817 249 7744",
    "sg:postcode":"76126",
    "sg:province":"TX",
    "sg:tags":[
        "dentist"
    ],
    "wof:name":"James W Young DDS",
    "wof:placetype":"venue"
},
  "geometry": {"coordinates":[-97.437162,32.675759],"type":"Point"}
}