{
  "type": "Feature",
  "properties": {
    "iso:country":"US",
    "sg:address":"14647 Walters Rd",
    "sg:city":"Houston",
    "sg:classifiers":[
        {
            "category":"Social Services",
            "subcategory":"Child Care",
            "type":"Services"
        }
    ],
    "sg:phone":"+1 281 537 1631",
    "sg:postcode":"77068",
    "sg:province":"TX",
    "wof:name":"Kid Fit Champions",
    "wof:placetype":"venue"
},
  "geometry": {"coordinates":[-95.486091,29.995804],"type":"Point"}
}