{
  "type": "Feature",
  "properties": {
    "iso:country":"US",
    "sg:address":"4669 Southwest Fwy Ste 800",
    "sg:city":"Houston",
    "sg:classifiers":[
        {
            "category":"Real Estate",
            "subcategory":"Architect",
            "type":"Services"
        }
    ],
    "sg:phone":"+1 713 783 5900",
    "sg:postcode":"77027",
    "sg:province":"TX",
    "wof:name":"Cdi Space Planners",
    "wof:placetype":"venue"
},
  "geometry": {"coordinates":[-95.454903,29.7297],"type":"Point"}
}