{
  "type": "Feature",
  "properties": {
    "iso:country":"US",
    "sg:address":"1820 Pearce Ct",
    "sg:city":"San Marcos",
    "sg:classifiers":[
        {
            "category":"Shopping",
            "subcategory":"Hobbies, Toys, & Games",
            "type":"Retail Goods"
        }
    ],
    "sg:phone":"+1 512 392 4154",
    "sg:postcode":"78666",
    "sg:province":"TX",
    "wof:name":"Discovery Toys",
    "wof:placetype":"venue"
},
  "geometry": {"coordinates":[-97.96646,29.891453],"type":"Point"}
}