{
  "type": "Feature",
  "properties": {
    "iso:country":"US",
    "sg:address":"1801 E 50th St",
    "sg:city":"Odessa",
    "sg:classifiers":[
        {
            "category":"Building & Trades",
            "subcategory":"Construction",
            "type":"Services"
        }
    ],
    "sg:phone":"+1 432 362 8376",
    "sg:postcode":"79762",
    "sg:province":"TX",
    "sg:tags":[
        "concrete",
        "contractor"
    ],
    "wof:name":"Smith Masonry",
    "wof:placetype":"venue"
},
  "geometry": {"coordinates":[-102.360539,31.89632],"type":"Point"}
}