{
  "type": "Feature",
  "properties": {
    "iso:country":"US",
    "sg:address":"1504 Fredericksburg Rd",
    "sg:city":"San Antonio",
    "sg:classifiers":[
        {
            "category":"Retail",
            "subcategory":"Repair Shop",
            "type":"Services"
        }
    ],
    "sg:phone":"+1 210 731 9060",
    "sg:postcode":"78201",
    "sg:province":"TX",
    "wof:name":"Model Upholstery",
    "wof:placetype":"venue"
},
  "geometry": {"coordinates":[-98.52048499999999,29.458954],"type":"Point"}
}