{
  "type": "Feature",
  "properties": {
    "iso:country":"US",
    "sg:address":"14250 Marsh Ln",
    "sg:city":"Addison",
    "sg:classifiers":[
        {
            "category":"Banks & Credit Unions",
            "subcategory":"Bank",
            "type":"Services"
        }
    ],
    "sg:phone":"+1 972 488 0067",
    "sg:postcode":"75001",
    "sg:province":"TX",
    "wof:name":"Chase",
    "wof:placetype":"venue"
},
  "geometry": {"coordinates":[-96.855563,32.938109],"type":"Point"}
}