{
  "type": "Feature",
  "properties": {
    "iso:country":"US",
    "sg:address":"2600 W Freddy Gonzalez Dr",
    "sg:city":"Edinburg",
    "sg:classifiers":[
        {
            "category":"Manufacturing",
            "subcategory":"Printing",
            "type":"Manufacturing & Wholesale Goods"
        }
    ],
    "sg:phone":"+1 956 380 1122",
    "sg:postcode":"78539",
    "sg:province":"TX",
    "sg:tags":[
        "screen"
    ],
    "wof:name":"Ruiz & Oliver Art & Design",
    "wof:placetype":"venue"
},
  "geometry": {"coordinates":[-98.190299,26.290539],"type":"Point"}
}