{
  "type": "Feature",
  "properties": {
    "iso:country":"US",
    "sg:address":"734 N Pierce St",
    "sg:city":"Amarillo",
    "sg:classifiers":[
        {
            "category":"Restaurant",
            "type":"Food & Drink"
        }
    ],
    "sg:menulink":"http://www.allmenus.com/tx/amarillo/156983-whataburger/menu/",
    "sg:phone":"+1 806 376 7726",
    "sg:postcode":"79107",
    "sg:province":"TX",
    "sg:tags":[
        "burger",
        "american"
    ],
    "wof:name":"Whataburger",
    "wof:placetype":"venue"
},
  "geometry": {"coordinates":[-101.830613,35.220416],"type":"Point"}
}