{
  "type": "Feature",
  "properties": {
    "iso:country":"US",
    "sg:address":"404 W 5th St",
    "sg:city":"Friona",
    "sg:classifiers":[
        {
            "category":"Organizations",
            "subcategory":"Religious Organization",
            "type":"Services"
        }
    ],
    "sg:phone":"+1 806 250 3933",
    "sg:postcode":"79035",
    "sg:province":"TX",
    "wof:name":"First Baptist Church",
    "wof:placetype":"venue"
},
  "geometry": {"coordinates":[-102.723457,34.635402],"type":"Point"}
}