{
  "type": "Feature",
  "properties": {
    "iso:country":"US",
    "sg:address":"7401 Sweet Meadows Dr",
    "sg:city":"Fort Worth",
    "sg:classifiers":[
        {
            "category":"Building & Trades",
            "subcategory":"Construction",
            "type":"Services"
        }
    ],
    "sg:phone":"+1 817 370 2997",
    "sg:postcode":"76123",
    "sg:province":"TX",
    "sg:tags":[
        "house"
    ],
    "wof:name":"First Texas Homes",
    "wof:placetype":"venue"
},
  "geometry": {"coordinates":[-97.403875,32.636249],"type":"Point"}
}