{
  "type": "Feature",
  "properties": {
    "iso:country":"US",
    "sg:address":"1211 Reynolds St",
    "sg:city":"Goldthwaite",
    "sg:classifiers":[
        {
            "category":"Real Estate",
            "subcategory":"Architect",
            "type":"Services"
        }
    ],
    "sg:phone":"+1 325 648 3598",
    "sg:postcode":"76844",
    "sg:province":"TX",
    "wof:name":"Richard Little",
    "wof:placetype":"venue"
},
  "geometry": {"coordinates":[-98.571928,31.451021],"type":"Point"}
}