{
  "type": "Feature",
  "properties": {
    "iso:country":"US",
    "sg:address":"25 Flounder Cir",
    "sg:city":"Freeport",
    "sg:classifiers":[
        {
            "category":"Organizations",
            "subcategory":"Labor Organization",
            "type":"Services"
        }
    ],
    "sg:phone":"+1 979 233 2336",
    "sg:postcode":"77541",
    "sg:province":"TX",
    "wof:name":"Double D Assoc Lc",
    "wof:placetype":"venue"
},
  "geometry": {"coordinates":[-95.279432,29.086796],"type":"Point"}
}