{
  "type": "Feature",
  "properties": {
    "iso:country":"US",
    "sg:address":"402 Gillmore Ave",
    "sg:city":"San Antonio",
    "sg:classifiers":[
        {
            "category":"Real Estate",
            "subcategory":"Real Estate Operator",
            "type":"Services"
        }
    ],
    "sg:phone":"+1 210 433 1425",
    "sg:postcode":"78226",
    "sg:province":"TX",
    "sg:tags":[
        "apartment"
    ],
    "wof:name":"Mitchell Village Apts",
    "wof:placetype":"venue"
},
  "geometry": {"coordinates":[-98.55945199999999,29.386682],"type":"Point"}
}