{
  "type": "Feature",
  "properties": {
    "iso:country":"US",
    "sg:address":"8 Glenview Ct",
    "sg:city":"Lufkin",
    "sg:classifiers":[
        {
            "category":"Government",
            "subcategory":"Office",
            "type":"Public Place"
        }
    ],
    "sg:phone":"+1 936 632 8343",
    "sg:postcode":"75901",
    "sg:province":"TX",
    "wof:name":"Lee, Rong Ming",
    "wof:placetype":"venue"
},
  "geometry": {"coordinates":[-94.72224799999999,31.284389],"type":"Point"}
}