{
  "type": "Feature",
  "properties": {
    "iso:country":"US",
    "sg:address":"912 E Erwin St",
    "sg:city":"Tyler",
    "sg:classifiers":[
        {
            "category":"Wholesale",
            "subcategory":"Groceries",
            "type":"Manufacturing & Wholesale Goods"
        }
    ],
    "sg:phone":"+1 903 533 1687",
    "sg:postcode":"75702",
    "sg:province":"TX",
    "sg:tags":[
        "confectionery"
    ],
    "wof:name":"Kitos Specialtys",
    "wof:placetype":"venue"
},
  "geometry": {"coordinates":[-95.290648,32.351291],"type":"Point"}
}