{
  "type": "Feature",
  "properties": {
    "iso:country":"US",
    "sg:address":"3464 Bevann Dr",
    "sg:city":"Dallas",
    "sg:classifiers":[
        {
            "category":"Shopping",
            "type":"Retail Goods"
        }
    ],
    "sg:phone":"+1 972 241 6009",
    "sg:postcode":"75234",
    "sg:province":"TX",
    "sg:tags":[
        "merchandise"
    ],
    "wof:name":"Eliseo",
    "wof:placetype":"venue"
},
  "geometry": {"coordinates":[-96.863168,32.923521],"type":"Point"}
}