{
  "type": "Feature",
  "properties": {
    "iso:country":"US",
    "sg:address":"1701 N Market St",
    "sg:city":"Dallas",
    "sg:classifiers":[
        {
            "category":"Parking",
            "type":"Transportation"
        }
    ],
    "sg:phone":"+1 214 747 7275",
    "sg:postcode":"75202",
    "sg:province":"TX",
    "sg:tags":[
        "automobile",
        "consulting",
        "business"
    ],
    "wof:name":"Premier Parking Management",
    "wof:placetype":"venue"
},
  "geometry": {"coordinates":[-96.80694099999999,32.782185],"type":"Point"}
}