{
  "type": "Feature",
  "properties": {
    "iso:country":"US",
    "sg:address":"933 Egyptian Dr",
    "sg:city":"Corpus Christi",
    "sg:classifiers":[
        {
            "category":"Shopping",
            "subcategory":"Clothing, Apparel, & Fashions",
            "type":"Retail Goods"
        }
    ],
    "sg:phone":"+1 361 881 8214",
    "sg:postcode":"78412",
    "sg:province":"TX",
    "wof:name":"T JMJ Shirts and More",
    "wof:placetype":"venue"
},
  "geometry": {"coordinates":[-97.348052,27.707121],"type":"Point"}
}