{
  "type": "Feature",
  "properties": {
    "iso:country":"US",
    "sg:address":"5002 Firestone Dr",
    "sg:city":"Harlingen",
    "sg:classifiers":[
        {
            "category":"Organizations",
            "subcategory":"Non-profit Organization",
            "type":"Services"
        }
    ],
    "sg:phone":"+1 956 423 2766",
    "sg:postcode":"78552",
    "sg:province":"TX",
    "sg:tags":[
        "association",
        "social"
    ],
    "wof:name":"Health Envmtl & Lrng Program",
    "wof:placetype":"venue"
},
  "geometry": {"coordinates":[-97.75003,26.208322],"type":"Point"}
}