{
  "type": "Feature",
  "properties": {
    "iso:country":"US",
    "sg:address":"1707 Woodcreek Dr",
    "sg:city":"Richardson",
    "sg:classifiers":[
        {
            "category":"Shopping",
            "subcategory":"Books",
            "type":"Retail Goods"
        }
    ],
    "sg:phone":"+1 972 231 6011",
    "sg:postcode":"75082",
    "sg:province":"TX",
    "wof:name":"Leo Baca",
    "wof:placetype":"venue"
},
  "geometry": {"coordinates":[-96.69240000000001,32.980751],"type":"Point"}
}