{
  "type": "Feature",
  "properties": {
    "iso:country":"US",
    "sg:address":"10111 Woodland Village Dr",
    "sg:city":"Austin",
    "sg:classifiers":[
        {
            "category":"Building & Trades",
            "subcategory":"Construction",
            "type":"Services"
        }
    ],
    "sg:phone":"+1 512 257 2807",
    "sg:postcode":"78750",
    "sg:province":"TX",
    "sg:tags":[
        "roofing",
        "commercial"
    ],
    "wof:name":"Longhorn Commercial Roofing",
    "wof:placetype":"venue"
},
  "geometry": {"coordinates":[-97.798857,30.44964],"type":"Point"}
}