{
  "type": "Feature",
  "properties": {
    "iso:country":"US",
    "sg:address":"1810 Wirt Rd",
    "sg:city":"Houston",
    "sg:classifiers":[
        {
            "category":"Communications",
            "subcategory":"Film & Video Production",
            "type":"Services"
        }
    ],
    "sg:phone":"+1 713 680 1135",
    "sg:postcode":"77055",
    "sg:province":"TX",
    "wof:name":"Popular Video",
    "wof:placetype":"venue"
},
  "geometry": {"coordinates":[-95.484793,29.804544],"type":"Point"}
}