{
  "type": "Feature",
  "properties": {
    "iso:country":"US",
    "sg:address":"6939 Robin Willow Dr",
    "sg:city":"Dallas",
    "sg:classifiers":[
        {
            "category":"Real Estate",
            "subcategory":"Real Estate Agent",
            "type":"Services"
        }
    ],
    "sg:phone":"+1 972 701 8023",
    "sg:postcode":"75248",
    "sg:province":"TX",
    "wof:name":"14 Karat Cake",
    "wof:placetype":"venue"
},
  "geometry": {"coordinates":[-96.787863,32.968729],"type":"Point"}
}