{
  "type": "Feature",
  "properties": {
    "iso:country":"US",
    "sg:address":"3405 Idalou Rd",
    "sg:city":"Lubbock",
    "sg:classifiers":[
        {
            "category":"Retail",
            "subcategory":"Auto Repair",
            "type":"Services"
        }
    ],
    "sg:phone":"+1 806 763 5641",
    "sg:postcode":"79403",
    "sg:province":"TX",
    "sg:tags":[
        "repairing",
        "automobile"
    ],
    "wof:name":"Bluhm Auto Electric",
    "wof:placetype":"venue"
},
  "geometry": {"coordinates":[-101.79950100000001,33.593796],"type":"Point"}
}