{
  "type": "Feature",
  "properties": {
    "iso:country":"US",
    "sg:address":"1302 FM 1092",
    "sg:city":"Missouri City",
    "sg:classifiers":[
        {
            "category":"Shopping",
            "subcategory":"Pharmacy",
            "type":"Retail Goods"
        }
    ],
    "sg:phone":"+1 281 499 3214",
    "sg:postcode":"77459",
    "sg:province":"TX",
    "wof:name":"Cvs Pharmacy",
    "wof:placetype":"venue"
},
  "geometry": {"coordinates":[-95.564381,29.600737],"type":"Point"}
}