{
  "type": "Feature",
  "properties": {
    "iso:country":"US",
    "sg:address":"1947 S Llewellyn Ave",
    "sg:city":"Dallas",
    "sg:classifiers":[
        {
            "category":"Retail",
            "subcategory":"Auto Repair",
            "type":"Services"
        }
    ],
    "sg:phone":"+1 214 944 5543",
    "sg:postcode":"75224",
    "sg:province":"TX",
    "sg:tags":[
        "repairing",
        "automobile"
    ],
    "wof:name":"Joey's Automotive Svc",
    "wof:placetype":"venue"
},
  "geometry": {"coordinates":[-96.831309,32.724156],"type":"Point"}
}