{
  "type": "Feature",
  "properties": {
    "iso:country":"US",
    "sg:address":"601 I- 20D Bus",
    "sg:city":"Monahans",
    "sg:classifiers":[
        {
            "category":"Food & Beverages",
            "subcategory":"Groceries & Convenience Stores",
            "type":"Retail Goods"
        }
    ],
    "sg:phone":"+1 432 943 8567",
    "sg:postcode":"79756",
    "sg:province":"TX",
    "sg:tags":[
        "grocer"
    ],
    "wof:name":"Lowe's Marketplace",
    "wof:placetype":"venue"
},
  "geometry": {"coordinates":[-102.900598,31.592651],"type":"Point"}
}