{
  "type": "Feature",
  "properties": {
    "iso:country":"US",
    "sg:address":"869 Burn Ct",
    "sg:city":"Granbury",
    "sg:classifiers":[
        {
            "category":"Building & Trades",
            "subcategory":"Construction",
            "type":"Services"
        }
    ],
    "sg:phone":"+1 817 573 5296",
    "sg:postcode":"76049",
    "sg:province":"TX",
    "sg:tags":[
        "house",
        "residential"
    ],
    "wof:name":"Omar Keeton",
    "wof:placetype":"venue"
},
  "geometry": {"coordinates":[-97.66848299999999,32.347408],"type":"Point"}
}