{
  "type": "Feature",
  "properties": {
    "iso:country":"US",
    "sg:address":"2911 Texas Ave S",
    "sg:city":"College Station",
    "sg:classifiers":[
        {
            "category":"Health Services",
            "subcategory":"Doctor",
            "type":"Services"
        }
    ],
    "sg:phone":"+1 979 690 2103",
    "sg:postcode":"77845",
    "sg:province":"TX",
    "wof:name":"Curtis Kaiser DDS",
    "wof:placetype":"venue"
},
  "geometry": {"coordinates":[-96.297274,30.59776],"type":"Point"}
}