{
  "type": "Feature",
  "properties": {
    "iso:country":"US",
    "sg:address":"7717 Sand St",
    "sg:city":"Fort Worth",
    "sg:classifiers":[
        {
            "category":"Building & Trades",
            "subcategory":"Construction",
            "type":"Services"
        }
    ],
    "sg:phone":"+1 817 595 2492",
    "sg:postcode":"76118",
    "sg:province":"TX",
    "sg:tags":[
        "hanging",
        "painter",
        "contractor"
    ],
    "wof:name":"Wright Painting Co",
    "wof:placetype":"venue"
},
  "geometry": {"coordinates":[-97.215476,32.796139],"type":"Point"}
}