{
  "type": "Feature",
  "properties": {
    "iso:country":"US",
    "sg:address":"505 Bruns St",
    "sg:city":"El Campo",
    "sg:classifiers":[
        {
            "category":"Education",
            "subcategory":"School",
            "type":"Public Place"
        }
    ],
    "sg:phone":"+1 979 543 7056",
    "sg:postcode":"77437",
    "sg:province":"TX",
    "wof:name":"Head Start Program Of El Campo",
    "wof:placetype":"venue"
},
  "geometry": {"coordinates":[-96.263003,29.193729],"type":"Point"}
}