{
  "type": "Feature",
  "properties": {
    "iso:country":"US",
    "sg:address":"4502 S Staples St",
    "sg:city":"Corpus Christi",
    "sg:classifiers":[
        {
            "category":"Real Estate",
            "subcategory":"Real Estate Agent",
            "type":"Services"
        }
    ],
    "sg:phone":"+1 361 993 9093",
    "sg:postcode":"78411",
    "sg:province":"TX",
    "sg:tags":[
        "appraiser"
    ],
    "wof:name":"Callaway & Co",
    "wof:placetype":"venue"
},
  "geometry": {"coordinates":[-97.373189,27.717699],"type":"Point"}
}