{
  "type": "Feature",
  "properties": {
    "iso:country":"US",
    "sg:address":"112 N Railroad St",
    "sg:city":"Aransas Pass",
    "sg:classifiers":[
        {
            "category":"Wholesale",
            "subcategory":"Auto Parts",
            "type":"Manufacturing & Wholesale Goods"
        }
    ],
    "sg:phone":"+1 361 758 7872",
    "sg:postcode":"78336",
    "sg:province":"TX",
    "sg:tags":[
        "truck"
    ],
    "wof:name":"T T Wrecker Svc",
    "wof:placetype":"venue"
},
  "geometry": {"coordinates":[-97.14062699999999,27.904519],"type":"Point"}
}