{
  "type": "Feature",
  "properties": {
    "iso:country":"US",
    "sg:address":"4303 Hwy 214",
    "sg:city":"Hereford",
    "sg:classifiers":[
        {
            "category":"Retail",
            "subcategory":"Veterinary Services",
            "type":"Services"
        }
    ],
    "sg:phone":"+1 806 289 5546",
    "sg:postcode":"79045",
    "sg:province":"TX",
    "wof:name":"Walcott Veterinary Clinic",
    "wof:placetype":"venue"
},
  "geometry": {"coordinates":[-102.815743,34.944689],"type":"Point"}
}