{
  "type": "Feature",
  "properties": {
    "iso:country":"US",
    "sg:address":"6702 Dalrock Rd",
    "sg:city":"Rowlett",
    "sg:classifiers":[
        {
            "category":"Personal",
            "subcategory":"Beauty Salon",
            "type":"Services"
        }
    ],
    "sg:phone":"+1 214 607 4247",
    "sg:postcode":"75089",
    "sg:province":"TX",
    "wof:name":"Supercuts",
    "wof:placetype":"venue"
},
  "geometry": {"coordinates":[-96.517911,32.919956],"type":"Point"}
}