{
  "type": "Feature",
  "properties": {
    "iso:country":"US",
    "sg:address":"1202 Sailfish St",
    "sg:city":"Hitchcock",
    "sg:classifiers":[
        {
            "category":"Manufacturing",
            "subcategory":"Textiles",
            "type":"Manufacturing & Wholesale Goods"
        }
    ],
    "sg:phone":"+1 409 938 0744",
    "sg:postcode":"77563",
    "sg:province":"TX",
    "sg:tags":[
        "mill",
        "fabric",
        "cotton"
    ],
    "wof:name":"Sailfish Enterprises",
    "wof:placetype":"venue"
},
  "geometry": {"coordinates":[-94.939475,29.321137],"type":"Point"}
}