{
  "type": "Feature",
  "properties": {
    "iso:country":"US",
    "sg:address":"1913 Cervin Blvd",
    "sg:city":"Austin",
    "sg:classifiers":[
        {
            "category":"Professional",
            "subcategory":"Detective & Security Services",
            "type":"Services"
        }
    ],
    "sg:phone":"+1 512 454 1005",
    "sg:postcode":"78728",
    "sg:province":"TX",
    "sg:tags":[
        "guard",
        "patrol",
        "system"
    ],
    "wof:name":"Detech Fire & Security",
    "wof:placetype":"venue"
},
  "geometry": {"coordinates":[-97.675888,30.44236],"type":"Point"}
}