{
  "type": "Feature",
  "properties": {
    "iso:country":"US",
    "sg:address":"3612 N Fitzhugh Ave",
    "sg:city":"Dallas",
    "sg:classifiers":[
        {
            "category":"Shopping",
            "subcategory":"Clothing, Apparel, & Fashions",
            "type":"Retail Goods"
        }
    ],
    "sg:phone":"+1 214 219 0204",
    "sg:postcode":"75204",
    "sg:province":"TX",
    "wof:name":"Origin Clothing",
    "wof:placetype":"venue"
},
  "geometry": {"coordinates":[-96.79705800000001,32.818583],"type":"Point"}
}