{
  "type": "Feature",
  "properties": {
    "iso:country":"US",
    "sg:address":"1001 Barrett Ave",
    "sg:city":"Odessa",
    "sg:classifiers":[
        {
            "category":"Organizations",
            "subcategory":"Religious Organization",
            "type":"Services"
        }
    ],
    "sg:phone":"+1 432 333 1368",
    "sg:postcode":"79761",
    "sg:province":"TX",
    "wof:name":"Shiloh Mssionary Baptst Church",
    "wof:placetype":"venue"
},
  "geometry": {"coordinates":[-102.34265600000001,31.839018],"type":"Point"}
}