{
  "type": "Feature",
  "properties": {
    "iso:country":"US",
    "sg:address":"910 Victoria St",
    "sg:city":"Taylor",
    "sg:classifiers":[
        {
            "category":"Government",
            "subcategory":"Fire Station",
            "type":"Public Place"
        }
    ],
    "sg:phone":"+1 512 352 5283",
    "sg:postcode":"76574",
    "sg:province":"TX",
    "sg:tags":[
        "department"
    ],
    "wof:name":"Taylor Fire Dept",
    "wof:placetype":"venue"
},
  "geometry": {"coordinates":[-97.422616,30.574215],"type":"Point"}
}