{
  "type": "Feature",
  "properties": {
    "iso:country":"US",
    "sg:address":"104 N Montgomery St",
    "sg:city":"Gilmer",
    "sg:classifiers":[
        {
            "category":"Organizations",
            "subcategory":"Non-profit Organization",
            "type":"Services"
        }
    ],
    "sg:phone":"+1 903 843 6203",
    "sg:postcode":"75644",
    "sg:province":"TX",
    "sg:tags":[
        "charity",
        "foundations-educational",
        "philanthropic",
        "research"
    ],
    "wof:name":"Refuge International",
    "wof:placetype":"venue"
},
  "geometry": {"coordinates":[-94.948752,32.728784],"type":"Point"}
}