{
  "type": "Feature",
  "properties": {
    "iso:country":"US",
    "sg:address":"5610 Royal Palms St",
    "sg:city":"Houston",
    "sg:classifiers":[
        {
            "category":"Real Estate",
            "subcategory":"Real Estate Operator",
            "type":"Services"
        }
    ],
    "sg:phone":"+1 713 641 0500",
    "sg:postcode":"77021",
    "sg:province":"TX",
    "sg:tags":[
        "apartment"
    ],
    "wof:name":"Garden Oaks Apartments",
    "wof:placetype":"venue"
},
  "geometry": {"coordinates":[-95.332182,29.696486],"type":"Point"}
}