{
  "type": "Feature",
  "properties": {
    "iso:country":"US",
    "sg:address":"127 N 16th St",
    "sg:city":"Junction",
    "sg:classifiers":[
        {
            "category":"Utilities",
            "type":"Services"
        }
    ],
    "sg:phone":"+1 325 446 4274",
    "sg:postcode":"76849",
    "sg:province":"TX",
    "sg:tags":[
        "sanitary"
    ],
    "wof:name":"Native American Seed",
    "wof:placetype":"venue"
},
  "geometry": {"coordinates":[-99.776624,30.490288],"type":"Point"}
}