{
  "type": "Feature",
  "properties": {
    "iso:country":"US",
    "sg:address":"10200 Buckwood Ave",
    "sg:city":"El Paso",
    "sg:classifiers":[
        {
            "category":"Building & Trades",
            "subcategory":"Construction",
            "type":"Services"
        }
    ],
    "sg:phone":"+1 915 549 1129",
    "sg:postcode":"79925",
    "sg:province":"TX",
    "sg:tags":[
        "contractor"
    ],
    "wof:name":"Unaldi",
    "wof:placetype":"venue"
},
  "geometry": {"coordinates":[-106.344872,31.765803],"type":"Point"}
}