{
  "type": "Feature",
  "properties": {
    "iso:country":"US",
    "sg:address":"15 Windstar Ct",
    "sg:city":"Spring",
    "sg:classifiers":[
        {
            "category":"Professional",
            "subcategory":"Management & Consulting",
            "type":"Services"
        }
    ],
    "sg:phone":"+1 281 419 8319",
    "sg:postcode":"77381",
    "sg:province":"TX",
    "sg:tags":[
        "business"
    ],
    "wof:name":"G T Associates",
    "wof:placetype":"venue"
},
  "geometry": {"coordinates":[-95.501684,30.177916],"type":"Point"}
}