{
  "type": "Feature",
  "properties": {
    "iso:country":"US",
    "sg:address":"407 Ramblewood Rd",
    "sg:city":"Houston",
    "sg:classifiers":[
        {
            "category":"Professional",
            "subcategory":"Business Services",
            "type":"Services"
        }
    ],
    "sg:phone":"+1 281 493 6491",
    "sg:postcode":"77079",
    "sg:province":"TX",
    "sg:tags":[
        "interior",
        "consultant",
        "design",
        "decorator"
    ],
    "wof:name":"Iva Ann King Interiors",
    "wof:placetype":"venue"
},
  "geometry": {"coordinates":[-95.58914799999999,29.769385],"type":"Point"}
}