{
  "type": "Feature",
  "properties": {
    "iso:country":"US",
    "sg:address":"11211 Katy Fwy",
    "sg:city":"Houston",
    "sg:classifiers":[
        {
            "category":"Mining & Drilling",
            "type":"Manufacturing & Wholesale Goods"
        }
    ],
    "sg:phone":"+1 713 465 6130",
    "sg:postcode":"77079",
    "sg:province":"TX",
    "sg:tags":[
        "exploration"
    ],
    "wof:name":"Robert M Curtis",
    "wof:placetype":"venue"
},
  "geometry": {"coordinates":[-95.57907400000001,29.784021],"type":"Point"}
}