{
  "type": "Feature",
  "properties": {
    "iso:country":"US",
    "sg:address":"1201 Alicia Ann Dr",
    "sg:city":"Wylie",
    "sg:classifiers":[
        {
            "category":"Real Estate",
            "subcategory":"Real Estate Operator",
            "type":"Services"
        }
    ],
    "sg:phone":"+1 972 475 1278",
    "sg:postcode":"75098",
    "sg:province":"TX",
    "sg:tags":[
        "mobile",
        "home",
        "site"
    ],
    "wof:name":"CMH",
    "wof:placetype":"venue"
},
  "geometry": {"coordinates":[-96.51558900000001,32.977447],"type":"Point"}
}