{
  "type": "Feature",
  "properties": {
    "iso:country":"US",
    "sg:address":"4151 Callaghan Rd",
    "sg:city":"San Antonio",
    "sg:classifiers":[
        {
            "category":"Health Services",
            "subcategory":"Doctor",
            "type":"Services"
        }
    ],
    "sg:phone":"+1 210 647 1195",
    "sg:postcode":"78228",
    "sg:province":"TX",
    "sg:tags":[
        "physician",
        "surgeon"
    ],
    "wof:name":"Southwest Texas Nephrology",
    "wof:placetype":"venue"
},
  "geometry": {"coordinates":[-98.60257300000001,29.465194],"type":"Point"}
}