{
  "type": "Feature",
  "properties": {
    "iso:country":"US",
    "sg:address":"1509 Spring St",
    "sg:city":"Houston",
    "sg:classifiers":[
        {
            "category":"Insurance",
            "subcategory":"Health Insurance",
            "type":"Services"
        }
    ],
    "sg:phone":"+1 713 222 2177",
    "sg:postcode":"77007",
    "sg:province":"TX",
    "sg:tags":[
        "market"
    ],
    "wof:name":"JDM Food Group Inc",
    "wof:placetype":"venue"
},
  "geometry": {"coordinates":[-95.372497,29.775061],"type":"Point"}
}