{
  "type": "Feature",
  "properties": {
    "iso:country":"US",
    "sg:address":"1904 Mulberry Ct",
    "sg:city":"San Marcos",
    "sg:classifiers":[
        {
            "category":"Professional",
            "subcategory":"Management & Consulting",
            "type":"Services"
        }
    ],
    "sg:phone":"+1 512 353 6382",
    "sg:postcode":"78666",
    "sg:province":"TX",
    "sg:tags":[
        "enforcement",
        "law",
        "consultant"
    ],
    "wof:name":"Quint C Thurman PHD",
    "wof:placetype":"venue"
},
  "geometry": {"coordinates":[-98.02453199999999,29.844095],"type":"Point"}
}