{
  "type": "Feature",
  "properties": {
    "iso:country":"US",
    "sg:address":"204 E 16th St",
    "sg:city":"Mt Pleasant",
    "sg:classifiers":[
        {
            "category":"Autos & Motor Vehicles",
            "subcategory":"Automobile Sales",
            "type":"Retail Goods"
        }
    ],
    "sg:phone":"+1 903 572 3656",
    "sg:postcode":"75455",
    "sg:province":"TX",
    "sg:tags":[
        "car",
        "dealer"
    ],
    "wof:name":"Sandlin Motors Inc",
    "wof:placetype":"venue"
},
  "geometry": {"coordinates":[-94.96659099999999,33.171749],"type":"Point"}
}