{
  "type": "Feature",
  "properties": {
    "iso:country":"US",
    "sg:address":"120 E McClung Ave",
    "sg:city":"Aransas Pass",
    "sg:classifiers":[
        {
            "category":"Food & Beverages",
            "subcategory":"Groceries & Convenience Stores",
            "type":"Retail Goods"
        }
    ],
    "sg:phone":"+1 361 758 0829",
    "sg:postcode":"78336",
    "sg:province":"TX",
    "wof:name":"Circle K",
    "wof:placetype":"venue"
},
  "geometry": {"coordinates":[-97.149798,27.896717],"type":"Point"}
}