{
  "type": "Feature",
  "properties": {
    "iso:country":"US",
    "sg:address":"423 Grand Ave",
    "sg:city":"Southlake",
    "sg:classifiers":[
        {
            "category":"Restaurant",
            "type":"Food & Drink"
        }
    ],
    "sg:menulink":"http://www.allmenus.com/tx/northeast-tarrant/40731-taco-diner/menu/",
    "sg:phone":"+1 682 651 6427",
    "sg:postcode":"76092",
    "sg:province":"TX",
    "sg:tags":[
        "mexican"
    ],
    "wof:name":"Taco Diner",
    "wof:placetype":"venue"
},
  "geometry": {"coordinates":[-97.130636,32.943395],"type":"Point"}
}