{
  "type": "Feature",
  "properties": {
    "iso:country":"US",
    "sg:address":"1404 Avenue E",
    "sg:city":"Seagraves",
    "sg:classifiers":[
        {
            "category":"Recreation",
            "type":"Entertainment"
        }
    ],
    "sg:phone":"+1 806 387 2926",
    "sg:postcode":"79359",
    "sg:province":"TX",
    "wof:name":"City of Seagraves",
    "wof:placetype":"venue"
},
  "geometry": {"coordinates":[-102.56323399999999,32.947855],"type":"Point"}
}