{
  "type": "Feature",
  "properties": {
    "iso:country":"US",
    "sg:address":"437 Coit Rd",
    "sg:city":"Plano",
    "sg:classifiers":[
        {
            "category":"Banks & Credit Unions",
            "subcategory":"Bank",
            "type":"Services"
        }
    ],
    "sg:phone":"+1 972 309 0082",
    "sg:postcode":"75075",
    "sg:province":"TX",
    "wof:name":"Hibernia National Bank",
    "wof:placetype":"venue"
},
  "geometry": {"coordinates":[-96.767844,33.006186],"type":"Point"}
}