{
  "type": "Feature",
  "properties": {
    "iso:country":"US",
    "sg:address":"2707 S 37th St",
    "sg:city":"Temple",
    "sg:classifiers":[
        {
            "category":"Personal",
            "subcategory":"Beauty Salon",
            "type":"Services"
        }
    ],
    "sg:phone":"+1 254 742 2570",
    "sg:postcode":"76504",
    "sg:province":"TX",
    "sg:tags":[
        "shop"
    ],
    "wof:name":"L A Nail Salon",
    "wof:placetype":"venue"
},
  "geometry": {"coordinates":[-97.370897,31.075559],"type":"Point"}
}