{
  "type": "Feature",
  "properties": {
    "iso:country":"US",
    "sg:address":"1306 Pennsylvania St",
    "sg:city":"South Houston",
    "sg:classifiers":[
        {
            "category":"Retail",
            "subcategory":"Auto Rental",
            "type":"Services"
        }
    ],
    "sg:phone":"+1 713 910 1617",
    "sg:postcode":"77587",
    "sg:province":"TX",
    "sg:tags":[
        "automobile",
        "leasing"
    ],
    "wof:name":"Gold Motor Diesel Repair",
    "wof:placetype":"venue"
},
  "geometry": {"coordinates":[-95.246458,29.656608],"type":"Point"}
}