{
  "type": "Feature",
  "properties": {
    "iso:country":"US",
    "sg:address":"2300 Old Spanish Trl",
    "sg:city":"Houston",
    "sg:classifiers":[
        {
            "category":"Cinema",
            "subcategory":"Movie Rental",
            "type":"Entertainment"
        }
    ],
    "sg:phone":"+1 713 799 2952",
    "sg:postcode":"77054",
    "sg:province":"TX",
    "sg:tags":[
        "leasing",
        "video",
        "disc",
        "tape"
    ],
    "wof:name":"Desipadam",
    "wof:placetype":"venue"
},
  "geometry": {"coordinates":[-95.392537,29.697672],"type":"Point"}
}