{
  "type": "Feature",
  "properties": {
    "iso:country":"US",
    "sg:address":"2047 S High St",
    "sg:city":"Longview",
    "sg:classifiers":[
        {
            "category":"Personal",
            "subcategory":"Beauty Salon",
            "type":"Services"
        }
    ],
    "sg:phone":"+1 903 757 9365",
    "sg:postcode":"75602",
    "sg:province":"TX",
    "sg:tags":[
        "shop"
    ],
    "wof:name":"Nails By Sue",
    "wof:placetype":"venue"
},
  "geometry": {"coordinates":[-94.739285,32.467249],"type":"Point"}
}