{
  "type": "Feature",
  "properties": {
    "iso:country":"US",
    "sg:address":"1807 Garden St",
    "sg:city":"Austin",
    "sg:classifiers":[
        {
            "category":"Shopping",
            "type":"Retail Goods"
        }
    ],
    "sg:phone":"+1 512 261 0125",
    "sg:postcode":"78702",
    "sg:province":"TX",
    "sg:tags":[
        "merchandise"
    ],
    "wof:name":"Riki L Dunn",
    "wof:placetype":"venue"
},
  "geometry": {"coordinates":[-97.726812,30.254671],"type":"Point"}
}