{
  "type": "Feature",
  "properties": {
    "iso:country":"US",
    "sg:address":"413 W Main",
    "sg:city":"Tomball",
    "sg:classifiers":[
        {
            "category":"Professional",
            "subcategory":"Advertising",
            "type":"Services"
        }
    ],
    "sg:phone":"+1 281 255 5507",
    "sg:postcode":"77375",
    "sg:province":"TX",
    "sg:tags":[
        "guide"
    ],
    "wof:name":"Malfer & Assoc",
    "wof:placetype":"venue"
},
  "geometry": {"coordinates":[-95.61706,30.096672],"type":"Point"}
}