{
  "type": "Feature",
  "properties": {
    "iso:country":"US",
    "sg:address":"2708 Hedgeway Dr",
    "sg:city":"Arlington",
    "sg:classifiers":[
        {
            "category":"Restaurant",
            "type":"Food & Drink"
        }
    ],
    "sg:phone":"+1 817 492 8711",
    "sg:postcode":"76016",
    "sg:province":"TX",
    "sg:tags":[
        "eating"
    ],
    "wof:name":"At Your Door Neighborhood Pet",
    "wof:placetype":"venue"
},
  "geometry": {"coordinates":[-97.19101499999999,32.699973],"type":"Point"}
}