{
  "type": "Feature",
  "properties": {
    "iso:country":"US",
    "sg:address":"100 Oak Ct",
    "sg:city":"Mc Kinney",
    "sg:classifiers":[
        {
            "category":"Real Estate",
            "subcategory":"Real Estate Agent",
            "type":"Services"
        }
    ],
    "sg:phone":"+1 972 540 2468",
    "sg:postcode":"75069",
    "sg:province":"TX",
    "wof:name":"Eagle's Nest Homes",
    "wof:placetype":"venue"
},
  "geometry": {"coordinates":[-96.572318,33.206637],"type":"Point"}
}