{
  "type": "Feature",
  "properties": {
    "iso:country":"US",
    "sg:address":"78 E Stockbridge Landing Cir",
    "sg:city":"Spring",
    "sg:classifiers":[
        {
            "category":"Mining & Drilling",
            "type":"Manufacturing & Wholesale Goods"
        }
    ],
    "sg:phone":"+1 936 273 0810",
    "sg:postcode":"77382",
    "sg:province":"TX",
    "sg:tags":[
        "development",
        "gas",
        "oil",
        "exploration"
    ],
    "wof:name":"Great Explorations",
    "wof:placetype":"venue"
},
  "geometry": {"coordinates":[-95.51497999999999,30.224466],"type":"Point"}
}