{
  "type": "Feature",
  "properties": {
    "iso:country":"US",
    "sg:address":"405 N Graham St",
    "sg:city":"Henrietta",
    "sg:classifiers":[
        {
            "category":"Building & Trades",
            "subcategory":"Construction",
            "type":"Services"
        }
    ],
    "sg:phone":"+1 940 538 4837",
    "sg:postcode":"76365",
    "sg:province":"TX",
    "sg:tags":[
        "excavation",
        "contractor"
    ],
    "wof:name":"Hill Backhoe Service",
    "wof:placetype":"venue"
},
  "geometry": {"coordinates":[-98.197396,33.818972],"type":"Point"}
}