{
  "type": "Feature",
  "properties": {
    "iso:country":"US",
    "sg:address":"1501 S Staples St",
    "sg:city":"Corpus Christi",
    "sg:classifiers":[
        {
            "category":"Autos & Motor Vehicles",
            "subcategory":"Automobile Sales",
            "type":"Retail Goods"
        }
    ],
    "sg:phone":"+1 361 884 5556",
    "sg:postcode":"78404",
    "sg:province":"TX",
    "sg:tags":[
        "used"
    ],
    "wof:name":"Easy Street Motors",
    "wof:placetype":"venue"
},
  "geometry": {"coordinates":[-97.401324,27.775427],"type":"Point"}
}