{
  "type": "Feature",
  "properties": {
    "iso:country":"US",
    "sg:address":"9001 Chancellor Row",
    "sg:city":"Dallas",
    "sg:classifiers":[
        {
            "category":"Manufacturing",
            "subcategory":"Food",
            "type":"Manufacturing & Wholesale Goods"
        }
    ],
    "sg:phone":"+1 214 631 7970",
    "sg:postcode":"75247",
    "sg:province":"TX",
    "sg:tags":[
        "preparation",
        "frozen",
        "specialty",
        "mfg"
    ],
    "wof:name":"Bridgford Foods Corporation",
    "wof:placetype":"venue"
},
  "geometry": {"coordinates":[-96.89077399999999,32.820794],"type":"Point"}
}