{
  "type": "Feature",
  "properties": {
    "iso:country":"US",
    "sg:address":"9501 San Pedro Ave",
    "sg:city":"San Antonio",
    "sg:classifiers":[
        {
            "category":"Restaurant",
            "type":"Food & Drink"
        }
    ],
    "sg:menulink":"http://www.allmenus.com/tx/san-antonio/166002-arbys/menu/",
    "sg:phone":"+1 210 344 7573",
    "sg:postcode":"78216",
    "sg:province":"TX",
    "sg:tags":[
        "burger",
        "american"
    ],
    "wof:name":"Arby's",
    "wof:placetype":"venue"
},
  "geometry": {"coordinates":[-98.49906900000001,29.52685],"type":"Point"}
}