{
  "type": "Feature",
  "properties": {
    "iso:country":"US",
    "sg:address":"207 Tilden St",
    "sg:city":"Cotulla",
    "sg:classifiers":[
        {
            "category":"Health Services",
            "subcategory":"Doctor",
            "type":"Services"
        }
    ],
    "sg:phone":"+1 830 879 2358",
    "sg:postcode":"78014",
    "sg:province":"TX",
    "sg:tags":[
        "physician",
        "surgeon"
    ],
    "wof:name":"Hood Medical Clinic",
    "wof:placetype":"venue"
},
  "geometry": {"coordinates":[-99.23521700000001,28.436718],"type":"Point"}
}