{
  "type": "Feature",
  "properties": {
    "iso:country":"US",
    "sg:address":"10606 Horn Blvd",
    "sg:city":"San Antonio",
    "sg:classifiers":[
        {
            "category":"Social Services",
            "subcategory":"Child Care",
            "type":"Services"
        }
    ],
    "sg:phone":"+1 210 696 4253",
    "sg:postcode":"78240",
    "sg:province":"TX",
    "sg:tags":[
        "day"
    ],
    "wof:name":"Cindy Urbanek Presch",
    "wof:placetype":"venue"
},
  "geometry": {"coordinates":[-98.619795,29.54055],"type":"Point"}
}