{
  "type": "Feature",
  "properties": {
    "iso:country":"US",
    "sg:address":"1907 Guadalupe St",
    "sg:city":"San Antonio",
    "sg:classifiers":[
        {
            "category":"Home & Garden",
            "subcategory":"Building Materials",
            "type":"Retail Goods"
        }
    ],
    "sg:phone":"+1 210 227 8695",
    "sg:postcode":"78207",
    "sg:province":"TX",
    "sg:tags":[
        "screen",
        "window"
    ],
    "wof:name":"Joe S Aluminum Shop",
    "wof:placetype":"venue"
},
  "geometry": {"coordinates":[-98.52234199999999,29.419093],"type":"Point"}
}