{
  "type": "Feature",
  "properties": {
    "iso:country":"US",
    "sg:address":"8508 State Hwy 6",
    "sg:city":"Houston",
    "sg:classifiers":[
        {
            "category":"Organizations",
            "subcategory":"Professional Association",
            "type":"Services"
        }
    ],
    "sg:phone":"+1 281 859 4188",
    "sg:postcode":"77095",
    "sg:province":"TX",
    "wof:name":"American Automobile Assoc",
    "wof:placetype":"venue"
},
  "geometry": {"coordinates":[-95.633906,29.90245],"type":"Point"}
}