{
  "type": "Feature",
  "properties": {
    "iso:country":"US",
    "sg:address":"4610 Devonshire Dr",
    "sg:city":"Grand Prairie",
    "sg:classifiers":[
        {
            "category":"Building & Trades",
            "subcategory":"Construction",
            "type":"Services"
        }
    ],
    "sg:phone":"+1 972 264 7684",
    "sg:postcode":"75052",
    "sg:province":"TX",
    "sg:tags":[
        "house"
    ],
    "wof:name":"V & M General Construction",
    "wof:placetype":"venue"
},
  "geometry": {"coordinates":[-97.009209,32.656893],"type":"Point"}
}