{
  "type": "Feature",
  "properties": {
    "iso:country":"US",
    "sg:address":"26107 I- 45",
    "sg:city":"Spring",
    "sg:classifiers":[
        {
            "category":"Professional",
            "subcategory":"Business Services",
            "type":"Services"
        }
    ],
    "sg:phone":"+1 281 298 8200",
    "sg:postcode":"77380",
    "sg:province":"TX",
    "sg:tags":[
        "interior",
        "consultant",
        "design",
        "decorator"
    ],
    "wof:name":"Awesome Interiors",
    "wof:placetype":"venue"
},
  "geometry": {"coordinates":[-95.44777999999999,30.147057],"type":"Point"}
}