{
  "type": "Feature",
  "properties": {
    "iso:country":"US",
    "sg:address":"1007 Valley View Dr",
    "sg:city":"Weslaco",
    "sg:classifiers":[
        {
            "category":"Arts & Performance",
            "subcategory":"Theater",
            "type":"Entertainment"
        }
    ],
    "sg:phone":"+1 956 969 1614",
    "sg:postcode":"78596",
    "sg:province":"TX",
    "sg:tags":[
        "bureau"
    ],
    "wof:name":"Bauhaus Productions",
    "wof:placetype":"venue"
},
  "geometry": {"coordinates":[-98.001749,26.159679],"type":"Point"}
}