{
  "type": "Feature",
  "properties": {
    "iso:country":"US",
    "sg:address":"1401 S Main St",
    "sg:city":"Baytown",
    "sg:classifiers":[
        {
            "category":"Restaurant",
            "type":"Food & Drink"
        }
    ],
    "sg:phone":"+1 281 426 2595",
    "sg:postcode":"77520",
    "sg:province":"TX",
    "wof:name":"Jose's Mexican Restaurant",
    "wof:placetype":"venue"
},
  "geometry": {"coordinates":[-94.97166,29.723285],"type":"Point"}
}