{
  "type": "Feature",
  "properties": {
    "iso:country":"US",
    "sg:address":"2422 Garden Valley Rd",
    "sg:city":"Tyler",
    "sg:classifiers":[
        {
            "category":"Building & Trades",
            "subcategory":"Pest Control",
            "type":"Services"
        }
    ],
    "sg:phone":"+1 903 592 2246",
    "sg:postcode":"75702",
    "sg:province":"TX",
    "wof:name":"Azalea Termite & Pest Control",
    "wof:placetype":"venue"
},
  "geometry": {"coordinates":[-95.32866799999999,32.361409],"type":"Point"}
}