{
  "type": "Feature",
  "properties": {
    "iso:country":"US",
    "sg:address":"104 E North St",
    "sg:city":"Uvalde",
    "sg:phone":"+1 830 591 2494",
    "sg:postcode":"78801",
    "sg:province":"TX",
    "sg:website":"http://www.cutloosehairemporium.com",
    "wof:name":"Cut Loose Hair Emporium Inc",
    "wof:placetype":"venue"
},
  "geometry": {"coordinates":[-99.786278,29.210317],"type":"Point"}
}