{
  "type": "Feature",
  "properties": {
    "iso:country":"US",
    "sg:address":"3014 Oak Forest Dr",
    "sg:city":"San Angelo",
    "sg:classifiers":[
        {
            "category":"Recreation",
            "subcategory":"Marina",
            "type":"Entertainment"
        }
    ],
    "sg:phone":"+1 325 234 7432",
    "sg:postcode":"76904",
    "sg:province":"TX",
    "sg:tags":[
        "operation"
    ],
    "wof:name":"87 S R V & Boat Storage",
    "wof:placetype":"venue"
},
  "geometry": {"coordinates":[-100.476287,31.425486],"type":"Point"}
}