{
  "type": "Feature",
  "properties": {
    "iso:country":"US",
    "sg:address":"2706 Bishop St",
    "sg:city":"Fort Worth",
    "sg:classifiers":[
        {
            "category":"Shopping",
            "subcategory":"Shoes",
            "type":"Retail Goods"
        }
    ],
    "sg:phone":"+1 817 531 3031",
    "sg:postcode":"76105",
    "sg:province":"TX",
    "wof:name":"Shine VIP Shoe",
    "wof:placetype":"venue"
},
  "geometry": {"coordinates":[-97.276701,32.718203],"type":"Point"}
}