{
  "type": "Feature",
  "properties": {
    "iso:country":"US",
    "sg:address":"502 Starkstone Ct",
    "sg:city":"Spring",
    "sg:classifiers":[
        {
            "category":"Manufacturing",
            "subcategory":"Tools & Machinery",
            "type":"Manufacturing & Wholesale Goods"
        }
    ],
    "sg:phone":"+1 281 419 9444",
    "sg:postcode":"77386",
    "sg:province":"TX",
    "sg:tags":[
        "shop",
        "par",
        "for",
        "mfg",
        "rep",
        "government",
        "contract",
        "machine"
    ],
    "wof:name":"Airdale Express LLC",
    "wof:placetype":"venue"
},
  "geometry": {"coordinates":[-95.435371,30.135025],"type":"Point"}
}