{
  "type": "Feature",
  "properties": {
    "iso:country":"US",
    "sg:address":"11261 Meador Rd",
    "sg:city":"Conroe",
    "sg:classifiers":[
        {
            "category":"Wholesale",
            "subcategory":"Construction Materials",
            "type":"Manufacturing & Wholesale Goods"
        }
    ],
    "sg:phone":"+1 936 890 5500",
    "sg:postcode":"77303",
    "sg:province":"TX",
    "sg:tags":[
        "concrete",
        "product"
    ],
    "sg:website":"http://www.ctcprecast.com",
    "wof:name":"Coast To Coast Precast LLC",
    "wof:placetype":"venue"
},
  "geometry": {"coordinates":[-95.472199,30.402717],"type":"Point"}
}