{
  "type": "Feature",
  "properties": {
    "iso:country":"US",
    "sg:address":"2916 Story Rd W",
    "sg:city":"Irving",
    "sg:classifiers":[
        {
            "category":"Real Estate",
            "subcategory":"Real Estate Services",
            "type":"Services"
        }
    ],
    "sg:phone":"+1 972 256 3767",
    "sg:postcode":"75038",
    "sg:province":"TX",
    "sg:tags":[
        "management",
        "property"
    ],
    "wof:name":"Epms-Ellis Property Management Services",
    "wof:placetype":"venue"
},
  "geometry": {"coordinates":[-96.984802,32.871601],"type":"Point"}
}