{
  "type": "Feature",
  "properties": {
    "iso:country":"US",
    "sg:address":"1308 Hackberry St",
    "sg:city":"Beeville",
    "sg:classifiers":[
        {
            "category":"Professional",
            "subcategory":"Business Services",
            "type":"Services"
        }
    ],
    "sg:phone":"+1 361 358 7463",
    "sg:postcode":"78102",
    "sg:province":"TX",
    "wof:name":"Terry Ann Armstrong",
    "wof:placetype":"venue"
},
  "geometry": {"coordinates":[-97.743713,28.417836],"type":"Point"}
}