{
  "type": "Feature",
  "properties": {
    "iso:country":"US",
    "sg:address":"1003 Evergreen St",
    "sg:city":"Longview",
    "sg:classifiers":[
        {
            "category":"Retail",
            "subcategory":"Repair Shop",
            "type":"Services"
        }
    ],
    "sg:phone":"+1 903 295 4757",
    "sg:postcode":"75604",
    "sg:province":"TX",
    "wof:name":"Tejas Mechanical Maintenance",
    "wof:placetype":"venue"
},
  "geometry": {"coordinates":[-94.789991,32.533375],"type":"Point"}
}