{
  "type": "Feature",
  "properties": {
    "iso:country":"US",
    "sg:address":"150 S Main St",
    "sg:city":"Euless",
    "sg:classifiers":[
        {
            "category":"Real Estate",
            "subcategory":"Real Estate Operator",
            "type":"Services"
        }
    ],
    "sg:phone":"+1 817 399 1766",
    "sg:postcode":"76040",
    "sg:province":"TX",
    "sg:tags":[
        "apartment"
    ],
    "wof:name":"Vienna Terrace Apartments",
    "wof:placetype":"venue"
},
  "geometry": {"coordinates":[-97.082677,32.836506],"type":"Point"}
}