{
  "type": "Feature",
  "properties": {
    "iso:country":"US",
    "sg:address":"5013 Walzem Rd",
    "sg:city":"San Antonio",
    "sg:classifiers":[
        {
            "category":"Restaurant",
            "type":"Food & Drink"
        }
    ],
    "sg:phone":"+1 210 653 8606",
    "sg:postcode":"78218",
    "sg:province":"TX",
    "sg:tags":[
        "fast"
    ],
    "wof:name":"KFC",
    "wof:placetype":"venue"
},
  "geometry": {"coordinates":[-98.39005899999999,29.510313],"type":"Point"}
}