{
  "type": "Feature",
  "properties": {
    "iso:country":"US",
    "sg:address":"254 Sawdust Rd",
    "sg:city":"Spring",
    "sg:classifiers":[
        {
            "category":"Shopping",
            "subcategory":"Used Merchandise",
            "type":"Retail Goods"
        },
        {
            "category":"Shopping",
            "subcategory":"Clothing, Apparel, & Fashions",
            "type":"Retail Goods"
        }
    ],
    "sg:phone":"+1 281 363 1350",
    "sg:postcode":"77380",
    "sg:province":"TX",
    "wof:name":"My Best Friend's Closet",
    "wof:placetype":"venue"
},
  "geometry": {"coordinates":[-95.448835,30.126787],"type":"Point"}
}