{
  "type": "Feature",
  "properties": {
    "iso:country":"US",
    "sg:address":"13974 State Hwy 16",
    "sg:city":"Medina",
    "sg:classifiers":[
        {
            "category":"Social Services",
            "type":"Services"
        }
    ],
    "sg:phone":"+1 830 589 7224",
    "sg:postcode":"78055",
    "sg:province":"TX",
    "sg:tags":[
        "organization",
        "welfare"
    ],
    "wof:name":"Medina Texas Development Corp",
    "wof:placetype":"venue"
},
  "geometry": {"coordinates":[-99.24608499999999,29.796361],"type":"Point"}
}