{
  "type": "Feature",
  "properties": {
    "iso:country":"US",
    "sg:address":"10417 Fossil Hill Dr",
    "sg:city":"Fort Worth",
    "sg:classifiers":[
        {
            "category":"Building & Trades",
            "subcategory":"Construction",
            "type":"Services"
        }
    ],
    "sg:phone":"+1 682 286 1242",
    "sg:postcode":"76131",
    "sg:province":"TX",
    "sg:tags":[
        "house"
    ],
    "wof:name":"Covenant Remodeling",
    "wof:placetype":"venue"
},
  "geometry": {"coordinates":[-97.36903599999999,32.919427],"type":"Point"}
}