{
  "type": "Feature",
  "properties": {
    "iso:country":"US",
    "sg:address":"10710 Research Blvd",
    "sg:city":"Austin",
    "sg:classifiers":[
        {
            "category":"Restaurant",
            "type":"Food & Drink"
        }
    ],
    "sg:phone":"+1 512 343 0807",
    "sg:postcode":"78759",
    "sg:province":"TX",
    "sg:tags":[
        "traditional",
        "american"
    ],
    "sg:website":"www.soupersalad.com",
    "wof:name":"Souper Salad",
    "wof:placetype":"venue"
},
  "geometry": {"coordinates":[-97.745796,30.4055],"type":"Point"}
}