{
  "type": "Feature",
  "properties": {
    "iso:country":"US",
    "sg:address":"220 8th St",
    "sg:city":"Moody",
    "sg:classifiers":[
        {
            "category":"Retail",
            "subcategory":"Auto Repair",
            "type":"Services"
        }
    ],
    "sg:phone":"+1 254 853 3836",
    "sg:postcode":"76557",
    "sg:province":"TX",
    "sg:tags":[
        "repairing",
        "automobile"
    ],
    "wof:name":"Moody Care Ctr",
    "wof:placetype":"venue"
},
  "geometry": {"coordinates":[-97.359669,31.307971],"type":"Point"}
}