{
  "type": "Feature",
  "properties": {
    "iso:country":"US",
    "sg:address":"202 S Dixon St",
    "sg:city":"Gainesville",
    "sg:classifiers":[
        {
            "category":"Professional",
            "subcategory":"Lawyer & Legal Services",
            "type":"Services"
        }
    ],
    "sg:phone":"+1 940 668 7817",
    "sg:postcode":"76240",
    "sg:province":"TX",
    "sg:tags":[
        "attorney"
    ],
    "wof:name":"Kenneth K Kaye",
    "wof:placetype":"venue"
},
  "geometry": {"coordinates":[-97.14524900000001,33.623578],"type":"Point"}
}