{
  "type": "Feature",
  "properties": {
    "iso:country":"US",
    "sg:address":"14 Big Oak Ln",
    "sg:city":"Texarkana",
    "sg:classifiers":[
        {
            "category":"Shopping",
            "subcategory":"Bicycles & Sporting Goods",
            "type":"Retail Goods"
        }
    ],
    "sg:phone":"+1 903 831 5362",
    "sg:postcode":"75503",
    "sg:province":"TX",
    "sg:tags":[
        "tackle",
        "shop",
        "grocery",
        "bait"
    ],
    "wof:name":"Sulphur Point Bait & Tackle",
    "wof:placetype":"venue"
},
  "geometry": {"coordinates":[-94.114722,33.489486],"type":"Point"}
}