{
  "type": "Feature",
  "properties": {
    "iso:country":"US",
    "sg:address":"3506 Charleston Dr",
    "sg:city":"Richardson",
    "sg:classifiers":[
        {
            "category":"Manufacturing",
            "subcategory":"Glass & Minerals",
            "type":"Manufacturing & Wholesale Goods"
        }
    ],
    "sg:phone":"+1 972 235 7833",
    "sg:postcode":"75082",
    "sg:province":"TX",
    "sg:tags":[
        "ready",
        "concrete",
        "mfg"
    ],
    "wof:name":"Larry Ready",
    "wof:placetype":"venue"
},
  "geometry": {"coordinates":[-96.619574,32.998834],"type":"Point"}
}