{
  "type": "Feature",
  "properties": {
    "iso:country":"US",
    "sg:address":"12317 Technology Boulevard Suite 300",
    "sg:city":"Austin",
    "sg:classifiers":[
        {
            "category":"Shopping",
            "subcategory":"Used Merchandise",
            "type":"Retail Goods"
        }
    ],
    "sg:phone":"+1 512 928 8832",
    "sg:postcode":"78727",
    "sg:province":"TX",
    "sg:tags":[
        "vintage",
        "consignment"
    ],
    "wof:name":"Goodwill",
    "wof:placetype":"venue"
},
  "geometry": {"coordinates":[-97.759861,30.434806],"type":"Point"}
}