{
  "type": "Feature",
  "properties": {
    "iso:country":"US",
    "sg:address":"152 E Pecan St",
    "sg:city":"San Antonio",
    "sg:classifiers":[
        {
            "category":"Restaurant",
            "type":"Food & Drink"
        }
    ],
    "sg:menulink":"http://www.allmenus.com/tx/san-antonio/259339-restaurant-le-reve/menu/",
    "sg:phone":"+1 210 212 2221",
    "sg:postcode":"78205",
    "sg:province":"TX",
    "sg:tags":[
        "new",
        "american"
    ],
    "wof:name":"Restaurant Le Reve",
    "wof:placetype":"venue"
},
  "geometry": {"coordinates":[-98.492262,29.428496],"type":"Point"}
}