{
  "type": "Feature",
  "properties": {
    "iso:country":"US",
    "sg:address":"1324 S Beckham Ave",
    "sg:city":"Tyler",
    "sg:classifiers":[
        {
            "category":"Professional",
            "subcategory":"Credit Reporting & Collection",
            "type":"Services"
        }
    ],
    "sg:phone":"+1 903 593 3778",
    "sg:postcode":"75701",
    "sg:province":"TX",
    "sg:tags":[
        "adjustment"
    ],
    "wof:name":"Hospital Solutions Inc",
    "wof:placetype":"venue"
},
  "geometry": {"coordinates":[-95.29087800000001,32.334317],"type":"Point"}
}