{
  "type": "Feature",
  "properties": {
    "iso:country":"US",
    "sg:address":"7660 Woodway Dr",
    "sg:city":"Houston",
    "sg:classifiers":[
        {
            "category":"Professional",
            "subcategory":"Engineering",
            "type":"Services"
        }
    ],
    "sg:phone":"+1 713 977 3430",
    "sg:postcode":"77063",
    "sg:province":"TX",
    "sg:tags":[
        "engineer"
    ],
    "sg:website":"www.chpengr.com",
    "wof:name":"C H P A Consulting Engineers",
    "wof:placetype":"venue"
},
  "geometry": {"coordinates":[-95.50287400000001,29.752429],"type":"Point"}
}