{
  "type": "Feature",
  "properties": {
    "iso:country":"US",
    "sg:address":"603 Greenville Ave",
    "sg:city":"Mineola",
    "sg:classifiers":[
        {
            "category":"Autos & Motor Vehicles",
            "subcategory":"Automobile Sales",
            "type":"Retail Goods"
        }
    ],
    "sg:phone":"+1 903 569 5636",
    "sg:postcode":"75773",
    "sg:province":"TX",
    "sg:tags":[
        "truck"
    ],
    "wof:name":"J & J Truck Sales",
    "wof:placetype":"venue"
},
  "geometry": {"coordinates":[-95.490325,32.679867],"type":"Point"}
}