{
  "type": "Feature",
  "properties": {
    "iso:country":"US",
    "sg:address":"301 W Parker Rd",
    "sg:city":"Plano",
    "sg:classifiers":[
        {
            "category":"Shopping",
            "subcategory":"Shoes",
            "type":"Retail Goods"
        }
    ],
    "sg:phone":"+1 972 398 2828",
    "sg:postcode":"75023",
    "sg:province":"TX",
    "wof:name":"Red Wing Shoe Store",
    "wof:placetype":"venue"
},
  "geometry": {"coordinates":[-96.70710699999999,33.038899],"type":"Point"}
}