{
  "type": "Feature",
  "properties": {
    "iso:country":"US",
    "sg:address":"24120 Northwest Fwy",
    "sg:city":"Cypress",
    "sg:classifiers":[
        {
            "category":"Personal",
            "subcategory":"Beauty Salon",
            "type":"Services"
        }
    ],
    "sg:phone":"+1 281 758 4888",
    "sg:postcode":"77429",
    "sg:province":"TX",
    "wof:name":"Today's Cut",
    "wof:placetype":"venue"
},
  "geometry": {"coordinates":[-95.681865,29.958416],"type":"Point"}
}