{
  "type": "Feature",
  "properties": {
    "iso:country":"US",
    "sg:address":"250 Oaks Crossing Rd",
    "sg:city":"Mineral Wells",
    "sg:classifiers":[
        {
            "category":"Manufacturing",
            "subcategory":"Retail Goods",
            "type":"Manufacturing & Wholesale Goods"
        },
        {
            "category":"Building & Trades",
            "subcategory":"Construction",
            "type":"Services"
        }
    ],
    "sg:phone":"+1 940 325 1210",
    "sg:postcode":"76067",
    "sg:province":"TX",
    "sg:tags":[
        "home",
        "product",
        "builder",
        "mfg"
    ],
    "wof:name":"Larry's Handiworks",
    "wof:placetype":"venue"
},
  "geometry": {"coordinates":[-98.11718399999999,32.756188],"type":"Point"}
}