{
  "type": "Feature",
  "properties": {
    "iso:country":"US",
    "sg:address":"327 Bryan Ave",
    "sg:city":"Fort Worth",
    "sg:classifiers":[
        {
            "category":"Manufacturing",
            "subcategory":"Paper Products",
            "type":"Manufacturing & Wholesale Goods"
        }
    ],
    "sg:phone":"+1 817 332 9258",
    "sg:postcode":"76104",
    "sg:province":"TX",
    "sg:tags":[
        "coated",
        "laminated"
    ],
    "sg:website":"www.universalblue.com",
    "wof:name":"Universal Blueprint Paper Co",
    "wof:placetype":"venue"
},
  "geometry": {"coordinates":[-97.32494800000001,32.74029],"type":"Point"}
}