{
  "type": "Feature",
  "properties": {
    "iso:country":"US",
    "sg:address":"3704 Meadow Run",
    "sg:city":"The Colony",
    "sg:classifiers":[
        {
            "category":"Professional",
            "subcategory":"Business Services",
            "type":"Services"
        }
    ],
    "sg:phone":"+1 972 370 6603",
    "sg:postcode":"75056",
    "sg:province":"TX",
    "sg:tags":[
        "fund",
        "promotion",
        "raising"
    ],
    "wof:name":"Promotions To Go",
    "wof:placetype":"venue"
},
  "geometry": {"coordinates":[-96.918227,33.085265],"type":"Point"}
}