{
  "type": "Feature",
  "properties": {
    "iso:country":"US",
    "sg:address":"16366 Cedar Cir",
    "sg:city":"Conroe",
    "sg:classifiers":[
        {
            "category":"Freight",
            "type":"Transportation"
        }
    ],
    "sg:phone":"+1 281 572 2017",
    "sg:postcode":"77302",
    "sg:province":"TX",
    "wof:name":"Moving World Transportation Co",
    "wof:placetype":"venue"
},
  "geometry": {"coordinates":[-95.40056800000001,30.234796],"type":"Point"}
}