{
  "type": "Feature",
  "properties": {
    "iso:country":"US",
    "sg:address":"2531 Brighton Oaks",
    "sg:city":"San Antonio",
    "sg:classifiers":[
        {
            "category":"Professional",
            "type":"Services"
        }
    ],
    "sg:phone":"+1 210 479 3055",
    "sg:postcode":"78231",
    "sg:province":"TX",
    "wof:name":"Days Gone By",
    "wof:placetype":"venue"
},
  "geometry": {"coordinates":[-98.53254699999999,29.563942],"type":"Point"}
}