{
  "type": "Feature",
  "properties": {
    "iso:country":"US",
    "sg:address":"1518 Comanche Dr",
    "sg:city":"Allen",
    "sg:classifiers":[
        {
            "category":"Building & Trades",
            "subcategory":"Construction",
            "type":"Services"
        }
    ],
    "sg:phone":"+1 214 509 9006",
    "sg:postcode":"75013",
    "sg:province":"TX",
    "sg:tags":[
        "industrial",
        "contractor"
    ],
    "wof:name":"Okla Chahta Enterprises Inc",
    "wof:placetype":"venue"
},
  "geometry": {"coordinates":[-96.70764,33.109142],"type":"Point"}
}