{
  "type": "Feature",
  "properties": {
    "iso:country":"US",
    "sg:address":"10201 Plano Rd",
    "sg:city":"Dallas",
    "sg:classifiers":[
        {
            "category":"Retail",
            "subcategory":"Auto Repair",
            "type":"Services"
        }
    ],
    "sg:phone":"+1 214 349 4242",
    "sg:postcode":"75238",
    "sg:province":"TX",
    "sg:tags":[
        "repairing",
        "automobile"
    ],
    "wof:name":"All-Tech Foreign Luxury Dmstc",
    "wof:placetype":"venue"
},
  "geometry": {"coordinates":[-96.700535,32.887566],"type":"Point"}
}