{
  "type": "Feature",
  "properties": {
    "iso:country":"US",
    "sg:address":"2903 Capital St",
    "sg:city":"Wylie",
    "sg:classifiers":[
        {
            "category":"Building & Trades",
            "subcategory":"Electrical",
            "type":"Services"
        }
    ],
    "sg:phone":"+1 972 442 5738",
    "sg:postcode":"75098",
    "sg:province":"TX",
    "sg:tags":[
        "industrial",
        "electrician",
        "contractors-commercial",
        "electric"
    ],
    "sg:website":"http://www.whfelectrical.com",
    "wof:name":"Whf Electrical Contractors, Inc.",
    "wof:placetype":"venue"
},
  "geometry": {"coordinates":[-96.58473499999999,33.005898],"type":"Point"}
}