{
  "type": "Feature",
  "properties": {
    "iso:country":"US",
    "sg:address":"20669 Fm 1804",
    "sg:city":"Lindale",
    "sg:classifiers":[
        {
            "category":"Home & Garden",
            "subcategory":"Building Materials",
            "type":"Retail Goods"
        },
        {
            "category":"Building & Trades",
            "subcategory":"Construction",
            "type":"Services"
        }
    ],
    "sg:phone":"+1 903 882 5250",
    "sg:postcode":"75771",
    "sg:province":"TX",
    "sg:tags":[
        "concrete",
        "staining",
        "contractor"
    ],
    "sg:website":"http://www.vandvfootings.com",
    "wof:name":"V & V Footings",
    "wof:placetype":"venue"
},
  "geometry": {"coordinates":[-95.39699899999999,32.576508],"type":"Point"}
}