{
  "type": "Feature",
  "properties": {
    "iso:country":"US",
    "sg:address":"2405 S Garland Ave",
    "sg:city":"Garland",
    "sg:classifiers":[
        {
            "category":"Autos & Motor Vehicles",
            "subcategory":"Automobile Sales",
            "type":"Retail Goods"
        }
    ],
    "sg:phone":"+1 972 271 3089",
    "sg:postcode":"75041",
    "sg:province":"TX",
    "sg:tags":[
        "car",
        "dealer"
    ],
    "wof:name":"Ov Auto Sales",
    "wof:placetype":"venue"
},
  "geometry": {"coordinates":[-96.65316900000001,32.888952],"type":"Point"}
}