{
  "type": "Feature",
  "properties": {
    "iso:country":"US",
    "sg:address":"700 N Zaragoza Rd",
    "sg:city":"El Paso",
    "sg:classifiers":[
        {
            "category":"Bagels",
            "type":"Food & Drink"
        },
        {
            "category":"Coffee & Tea",
            "type":"Food & Drink"
        },
        {
            "category":"Food & Beverages",
            "subcategory":"Bakery",
            "type":"Retail Goods"
        },
        {
            "category":"Bakery",
            "type":"Food & Drink"
        },
        {
            "category":"Donuts",
            "type":"Food & Drink"
        }
    ],
    "sg:menulink":"http://www.allmenus.com/tx/el-paso/138942-dunkin-donuts/menu/",
    "sg:phone":"+1 915 860 0100",
    "sg:postcode":"79907",
    "sg:province":"TX",
    "sg:tags":[
        "coffee",
        "tea",
        "american",
        "bagel",
        "bakery",
        "pastry"
    ],
    "wof:name":"Dunkin' Donuts",
    "wof:placetype":"venue"
},
  "geometry": {"coordinates":[-106.31974,31.703629],"type":"Point"}
}