{
  "type": "Feature",
  "properties": {
    "iso:country":"US",
    "sg:address":"2028 Oak Bluff Dr",
    "sg:city":"Carrollton",
    "sg:classifiers":[
        {
            "category":"Building & Trades",
            "subcategory":"Plumbing",
            "type":"Services"
        }
    ],
    "sg:phone":"+1 972 323 1789",
    "sg:postcode":"75007",
    "sg:province":"TX",
    "sg:tags":[
        "plumbing",
        "contractor"
    ],
    "wof:name":"Starnes Plumbing Co",
    "wof:placetype":"venue"
},
  "geometry": {"coordinates":[-96.87795699999999,33.021439],"type":"Point"}
}