{
  "type": "Feature",
  "properties": {
    "iso:country":"US",
    "sg:address":"431 Monssen Dr",
    "sg:city":"Dallas",
    "sg:classifiers":[
        {
            "category":"Real Estate",
            "subcategory":"Real Estate Agent",
            "type":"Services"
        }
    ],
    "sg:phone":"+1 214 943 3242",
    "sg:postcode":"75224",
    "sg:province":"TX",
    "wof:name":"Brad & Assoc Trustee",
    "wof:placetype":"venue"
},
  "geometry": {"coordinates":[-96.82909600000001,32.731605],"type":"Point"}
}