{
  "type": "Feature",
  "properties": {
    "iso:country":"US",
    "sg:address":"486 Elkins Lake",
    "sg:city":"Huntsville",
    "sg:classifiers":[
        {
            "category":"Professional",
            "subcategory":"Business Services",
            "type":"Services"
        }
    ],
    "sg:phone":"+1 936 291 0810",
    "sg:postcode":"77340",
    "sg:province":"TX",
    "wof:name":"Applications Group",
    "wof:placetype":"venue"
},
  "geometry": {"coordinates":[-95.520022,30.66615],"type":"Point"}
}