{
  "type": "Feature",
  "properties": {
    "iso:country":"US",
    "sg:address":"9201 Jamaica Beach",
    "sg:city":"Galveston",
    "sg:classifiers":[
        {
            "category":"Building & Trades",
            "subcategory":"Pest Control",
            "type":"Services"
        }
    ],
    "sg:phone":"+1 409 737 3329",
    "sg:postcode":"77554",
    "sg:province":"TX",
    "wof:name":"Sarex Pest Control",
    "wof:placetype":"venue"
},
  "geometry": {"coordinates":[-94.977189,29.17888],"type":"Point"}
}