{
  "type": "Feature",
  "properties": {
    "iso:country":"US",
    "sg:address":"5105 Spr 581",
    "sg:city":"Pearsall",
    "sg:classifiers":[
        {
            "category":"Farming",
            "subcategory":"Farm & Veterinary Services",
            "type":"Manufacturing & Wholesale Goods"
        }
    ],
    "sg:phone":"+1 830 334 9365",
    "sg:postcode":"78061",
    "sg:province":"TX",
    "sg:tags":[
        "crop"
    ],
    "wof:name":"Smith Company Flying Service",
    "wof:placetype":"venue"
},
  "geometry": {"coordinates":[-99.114974,28.827608],"type":"Point"}
}