{
  "type": "Feature",
  "properties": {
    "iso:country":"US",
    "sg:address":"4608 Deal Dr",
    "sg:city":"Fort Worth",
    "sg:classifiers":[
        {
            "category":"Manufacturing",
            "subcategory":"Toys & Sporting Goods",
            "type":"Manufacturing & Wholesale Goods"
        }
    ],
    "sg:phone":"+1 817 237 2797",
    "sg:postcode":"76135",
    "sg:province":"TX",
    "sg:tags":[
        "mfg"
    ],
    "wof:name":"Craft Friendzy",
    "wof:placetype":"venue"
},
  "geometry": {"coordinates":[-97.43161600000001,32.822069],"type":"Point"}
}