{
  "type": "Feature",
  "properties": {
    "iso:country":"US",
    "sg:address":"2412 E Cesar Chavez St",
    "sg:city":"Austin",
    "sg:classifiers":[
        {
            "category":"Autos & Motor Vehicles",
            "subcategory":"Automobile Sales",
            "type":"Retail Goods"
        }
    ],
    "sg:phone":"+1 512 480 9040",
    "sg:postcode":"78702",
    "sg:province":"TX",
    "sg:tags":[
        "car",
        "dealer"
    ],
    "wof:name":"Express Anaya Auto",
    "wof:placetype":"venue"
},
  "geometry": {"coordinates":[-97.716824,30.2545],"type":"Point"}
}