{
  "type": "Feature",
  "properties": {
    "iso:country":"US",
    "sg:address":"114 Halmar Cove",
    "sg:city":"Georgetown",
    "sg:classifiers":[
        {
            "category":"Manufacturing",
            "subcategory":"Toys & Sporting Goods",
            "type":"Manufacturing & Wholesale Goods"
        }
    ],
    "sg:phone":"+1 512 819 0656",
    "sg:postcode":"78628",
    "sg:province":"TX",
    "sg:tags":[
        "athletic"
    ],
    "sg:website":"www.stiguns.com",
    "wof:name":"STI Intl",
    "wof:placetype":"venue"
},
  "geometry": {"coordinates":[-97.673207,30.683602],"type":"Point"}
}