{
  "type": "Feature",
  "properties": {
    "iso:country":"US",
    "sg:address":"9640 White Wing Loop",
    "sg:city":"Laredo",
    "sg:classifiers":[
        {
            "category":"Retail",
            "subcategory":"Laundry & Dry Cleaning",
            "type":"Services"
        }
    ],
    "sg:phone":"+1 956 726 6504",
    "sg:postcode":"78045",
    "sg:province":"TX",
    "wof:name":"Ultra Carpet Care",
    "wof:placetype":"venue"
},
  "geometry": {"coordinates":[-99.520296,27.587322],"type":"Point"}
}