{
  "type": "Feature",
  "properties": {
    "iso:country":"US",
    "sg:address":"110 W Cedar Creek Pkwy",
    "sg:city":"Kemp",
    "sg:classifiers":[
        {
            "category":"Ice Cream",
            "type":"Food & Drink"
        }
    ],
    "sg:menulink":"http://www.allmenus.com/tx/cedar-creek-lake/162513-dairy-queen/menu/",
    "sg:phone":"+1 903 432 3076",
    "sg:postcode":"75143",
    "sg:province":"TX",
    "sg:tags":[
        "burger",
        "american"
    ],
    "wof:name":"Dairy Queen",
    "wof:placetype":"venue"
},
  "geometry": {"coordinates":[-96.21372599999999,32.320684],"type":"Point"}
}