{
  "type": "Feature",
  "properties": {
    "iso:country":"US",
    "sg:address":"13000 Jones Rd",
    "sg:city":"Houston",
    "sg:classifiers":[
        {
            "category":"Organizations",
            "subcategory":"Religious Organization",
            "type":"Services"
        }
    ],
    "sg:phone":"+1 281 890 1900",
    "sg:postcode":"77070",
    "sg:province":"TX",
    "sg:tags":[
        "baptist",
        "church"
    ],
    "wof:name":"The Met Family Life Center",
    "wof:placetype":"venue"
},
  "geometry": {"coordinates":[-95.585055,29.961257],"type":"Point"}
}