{
  "type": "Feature",
  "properties": {
    "iso:country":"US",
    "sg:address":"11323 Fuqua St",
    "sg:city":"Houston",
    "sg:classifiers":[
        {
            "category":"Restaurant",
            "type":"Food & Drink"
        }
    ],
    "sg:menulink":"http://www.allmenus.com/tx/houston/48664-boston-market/menu/",
    "sg:phone":"+1 713 910 4956",
    "sg:postcode":"77089",
    "sg:province":"TX",
    "sg:tags":[
        "barbecue",
        "american",
        "soup"
    ],
    "wof:name":"Boston Market",
    "wof:placetype":"venue"
},
  "geometry": {"coordinates":[-95.218986,29.613798],"type":"Point"}
}