{
  "type": "Feature",
  "properties": {
    "iso:country":"US",
    "sg:address":"1030 Wyoming Ave",
    "sg:city":"El Paso",
    "sg:classifiers":[
        {
            "category":"Utilities",
            "subcategory":"Mobile Phone",
            "type":"Services"
        }
    ],
    "sg:phone":"+1 915 751 5559",
    "sg:postcode":"79902",
    "sg:province":"TX",
    "sg:tags":[
        "telephone",
        "cellular"
    ],
    "wof:name":"Payless Wireless",
    "wof:placetype":"venue"
},
  "geometry": {"coordinates":[-106.48263,31.767305],"type":"Point"}
}