{
  "type": "Feature",
  "properties": {
    "iso:country":"US",
    "sg:address":"4101 Oates Rd",
    "sg:city":"Houston",
    "sg:classifiers":[
        {
            "category":"Building & Trades",
            "subcategory":"Plumbing",
            "type":"Services"
        }
    ],
    "sg:phone":"+1 832 519 2000",
    "sg:postcode":"77013",
    "sg:province":"TX",
    "sg:tags":[
        "pipe",
        "line",
        "contractor"
    ],
    "wof:name":"BJ Process & Pipeline Services",
    "wof:placetype":"venue"
},
  "geometry": {"coordinates":[-95.240514,29.79999],"type":"Point"}
}