{
  "type": "Feature",
  "properties": {
    "iso:country":"US",
    "sg:address":"2820 N Fulton St",
    "sg:city":"Wharton",
    "sg:classifiers":[
        {
            "category":"Organizations",
            "subcategory":"Community Association",
            "type":"Services"
        },
        {
            "category":"Organizations",
            "subcategory":"Membership Organization",
            "type":"Services"
        }
    ],
    "sg:phone":"+1 979 532 1522",
    "sg:postcode":"77488",
    "sg:province":"TX",
    "sg:tags":[
        "club",
        "fraternal"
    ],
    "sg:website":"http://www.kofc.org",
    "wof:name":"Knights Of Columbus Supreme Council (Inc)",
    "wof:placetype":"venue"
},
  "geometry": {"coordinates":[-96.089799,29.337083],"type":"Point"}
}