{
  "type": "Feature",
  "properties": {
    "iso:country":"US",
    "sg:address":"1200 Soldiers Field Dr",
    "sg:city":"Sugar Land",
    "sg:classifiers":[
        {
            "category":"Professional",
            "subcategory":"Lawyer & Legal Services",
            "type":"Services"
        }
    ],
    "sg:phone":"+1 281 265 2522",
    "sg:postcode":"77479",
    "sg:province":"TX",
    "wof:name":"George R Willy PC",
    "wof:placetype":"venue"
},
  "geometry": {"coordinates":[-95.63709799999999,29.601946],"type":"Point"}
}