{
  "type": "Feature",
  "properties": {
    "iso:country":"US",
    "sg:address":"806 W Arkansas Ln",
    "sg:city":"Arlington",
    "sg:classifiers":[
        {
            "category":"Insurance",
            "subcategory":"Insurance Agent",
            "type":"Services"
        }
    ],
    "sg:phone":"+1 817 469 9906",
    "sg:postcode":"76013",
    "sg:province":"TX",
    "wof:name":"Direct General Ins Agency",
    "wof:placetype":"venue"
},
  "geometry": {"coordinates":[-97.116107,32.706348],"type":"Point"}
}