{
  "type": "Feature",
  "properties": {
    "iso:country":"US",
    "sg:address":"3710 Ridgemont Dr",
    "sg:city":"Abilene",
    "sg:phone":"+1 325 695 4470",
    "sg:postcode":"79606",
    "sg:province":"TX",
    "sg:website":"http://clickserve.dartsearch.net/link/click?lid=43000000308049899",
    "wof:name":"T-Mobile",
    "wof:placetype":"venue"
},
  "geometry": {"coordinates":[-99.765635,32.405807],"type":"Point"}
}