{
  "type": "Feature",
  "properties": {
    "iso:country":"US",
    "sg:address":"6210 Viva Max Dr",
    "sg:city":"San Antonio",
    "sg:classifiers":[
        {
            "category":"Building & Trades",
            "subcategory":"Construction",
            "type":"Services"
        }
    ],
    "sg:phone":"+1 210 680 2549",
    "sg:postcode":"78238",
    "sg:province":"TX",
    "sg:tags":[
        "hanging",
        "co",
        "contractor"
    ],
    "wof:name":"Olympia Painting",
    "wof:placetype":"venue"
},
  "geometry": {"coordinates":[-98.609776,29.45774],"type":"Point"}
}