{
  "type": "Feature",
  "properties": {
    "iso:country":"US",
    "sg:address":"27620 Tomball Pkwy",
    "sg:city":"Tomball",
    "sg:classifiers":[
        {
            "category":"Professional",
            "type":"Services"
        }
    ],
    "sg:phone":"+1 281 255 8043",
    "sg:postcode":"77375",
    "sg:province":"TX",
    "wof:name":"V B Teaching Tools",
    "wof:placetype":"venue"
},
  "geometry": {"coordinates":[-95.625243,30.07062],"type":"Point"}
}