{
  "type": "Feature",
  "properties": {
    "iso:country":"US",
    "sg:address":"127 N 1st St",
    "sg:city":"Lufkin",
    "sg:classifiers":[
        {
            "category":"Professional",
            "type":"Services"
        }
    ],
    "sg:phone":"+1 936 634 5751",
    "sg:postcode":"75901",
    "sg:province":"TX",
    "sg:tags":[
        "establishment"
    ],
    "wof:name":"Deep East Texas Regl Council",
    "wof:placetype":"venue"
},
  "geometry": {"coordinates":[-94.728583,31.339835],"type":"Point"}
}