{
  "type": "Feature",
  "properties": {
    "iso:country":"US",
    "sg:address":"5177 Richmond Ave Ste 1230",
    "sg:city":"Houston",
    "sg:classifiers":[
        {
            "category":"Education",
            "subcategory":"Kindergarten",
            "type":"Public Place"
        },
        {
            "category":"Professional",
            "subcategory":"Lawyer & Legal Services",
            "type":"Services"
        }
    ],
    "sg:phone":"+1 713 521 7568",
    "sg:postcode":"77056",
    "sg:province":"TX",
    "sg:tags":[
        "school",
        "driving"
    ],
    "sg:website":"www.scottmarkowitz.com",
    "wof:name":"Markowitz Scott Atty",
    "wof:placetype":"venue"
},
  "geometry": {"coordinates":[-95.465964,29.730856],"type":"Point"}
}