{
  "type": "Feature",
  "properties": {
    "iso:country":"US",
    "sg:address":"1315 Vera Cruz",
    "sg:city":"San Antonio",
    "sg:classifiers":[
        {
            "category":"Arts & Performance",
            "subcategory":"Theater",
            "type":"Entertainment"
        }
    ],
    "sg:phone":"+1 210 222 2920",
    "sg:postcode":"78207",
    "sg:province":"TX",
    "wof:name":"Jonathan P Benavides",
    "wof:placetype":"venue"
},
  "geometry": {"coordinates":[-98.517734,29.416686],"type":"Point"}
}