{
  "type": "Feature",
  "properties": {
    "iso:country":"US",
    "sg:address":"4703 Singleton Blvd",
    "sg:city":"Dallas",
    "sg:classifiers":[
        {
            "category":"Retail",
            "subcategory":"Auto Repair",
            "type":"Services"
        }
    ],
    "sg:phone":"+1 214 638 2656",
    "sg:postcode":"75212",
    "sg:province":"TX",
    "sg:tags":[
        "automotive",
        "carburetor"
    ],
    "wof:name":"Carburadotes Del Norte 2",
    "wof:placetype":"venue"
},
  "geometry": {"coordinates":[-96.897261,32.778569],"type":"Point"}
}