{
  "type": "Feature",
  "properties": {
    "iso:country":"US",
    "sg:address":"170 E Circuit Dr",
    "sg:city":"Beaumont",
    "sg:classifiers":[
        {
            "category":"Shopping",
            "type":"Retail Goods"
        }
    ],
    "sg:phone":"+1 409 892 9527",
    "sg:postcode":"77706",
    "sg:province":"TX",
    "sg:tags":[
        "merchandise"
    ],
    "wof:name":"Nadine Casa",
    "wof:placetype":"venue"
},
  "geometry": {"coordinates":[-94.15091200000001,30.086199],"type":"Point"}
}