{
  "type": "Feature",
  "properties": {
    "iso:country":"US",
    "sg:address":"2317 Coit Rd",
    "sg:city":"Plano",
    "sg:classifiers":[
        {
            "category":"Professional",
            "type":"Services"
        }
    ],
    "sg:phone":"+1 972 599 2130",
    "sg:postcode":"75075",
    "sg:province":"TX",
    "sg:tags":[
        "establishment"
    ],
    "wof:name":"Electra Reps",
    "wof:placetype":"venue"
},
  "geometry": {"coordinates":[-96.77024400000001,33.030072],"type":"Point"}
}