{
  "type": "Feature",
  "properties": {
    "iso:country":"US",
    "sg:address":"9896 Bissonnet St",
    "sg:city":"Houston",
    "sg:classifiers":[
        {
            "category":"Health Services",
            "subcategory":"Clinic",
            "type":"Services"
        }
    ],
    "sg:phone":"+1 713 270 5055",
    "sg:postcode":"77036",
    "sg:province":"TX",
    "sg:tags":[
        "agency",
        "welfare"
    ],
    "wof:name":"M P Totalcare",
    "wof:placetype":"venue"
},
  "geometry": {"coordinates":[-95.55289500000001,29.675223],"type":"Point"}
}