{
  "type": "Feature",
  "properties": {
    "iso:country":"US",
    "sg:address":"203 E 8th St",
    "sg:city":"Cisco",
    "sg:classifiers":[
        {
            "category":"Place Of Worship",
            "type":"Public Place"
        }
    ],
    "sg:phone":"+1 254 442 1909",
    "sg:postcode":"76437",
    "sg:province":"TX",
    "sg:tags":[
        "church"
    ],
    "wof:name":"Victory Assembly Church",
    "wof:placetype":"venue"
},
  "geometry": {"coordinates":[-98.97801,32.388732],"type":"Point"}
}