{
  "type": "Feature",
  "properties": {
    "iso:country":"US",
    "sg:address":"311 W Wilbarger St",
    "sg:city":"Bowie",
    "sg:classifiers":[
        {
            "category":"Place Of Worship",
            "subcategory":"Church",
            "type":"Public Place"
        },
        {
            "category":"Place Of Worship",
            "type":"Public Place"
        },
        {
            "category":"Organizations",
            "subcategory":"Religious Organization",
            "type":"Services"
        }
    ],
    "sg:phone":"+1 940 872 2793",
    "sg:postcode":"76230",
    "sg:province":"TX",
    "sg:tags":[
        "churches-baptist-general",
        "churches-baptist-southern",
        "churches-baptist"
    ],
    "wof:name":"Southside Baptist Church",
    "wof:placetype":"venue"
},
  "geometry": {"coordinates":[-97.852694,33.556588],"type":"Point"}
}