{
  "type": "Feature",
  "properties": {
    "iso:country":"US",
    "sg:address":"5271 Barker Cypress Rd",
    "sg:city":"Houston",
    "sg:classifiers":[
        {
            "category":"Home & Garden",
            "subcategory":"Home Furnishings",
            "type":"Retail Goods"
        }
    ],
    "sg:phone":"+1 281 858 4645",
    "sg:postcode":"77084",
    "sg:province":"TX",
    "sg:tags":[
        "venetian",
        "blind"
    ],
    "wof:name":"Alpha Blinds Distribution",
    "wof:placetype":"venue"
},
  "geometry": {"coordinates":[-95.68330400000001,29.849822],"type":"Point"}
}