{
  "type": "Feature",
  "properties": {
    "iso:country":"US",
    "sg:address":"17835 Kuykendahl Rd",
    "sg:city":"Spring",
    "sg:classifiers":[
        {
            "category":"Wholesale",
            "subcategory":"Petroleum",
            "type":"Manufacturing & Wholesale Goods"
        }
    ],
    "sg:phone":"+1 281 257 1109",
    "sg:postcode":"77379",
    "sg:province":"TX",
    "sg:tags":[
        "pipe",
        "line",
        "company"
    ],
    "wof:name":"Mc Gehee WB Wes Pipeline Engr",
    "wof:placetype":"venue"
},
  "geometry": {"coordinates":[-95.48145599999999,30.030546],"type":"Point"}
}