{
  "type": "Feature",
  "properties": {
    "iso:country":"US",
    "sg:address":"4848 Lemmon Avenue 100-138",
    "sg:city":"Dallas",
    "sg:classifiers":[
        {
            "category":"Retail",
            "subcategory":"Animal Services",
            "type":"Services"
        }
    ],
    "sg:phone":"+1 214 351 3181",
    "sg:postcode":"75209",
    "sg:province":"TX",
    "sg:tags":[
        "pet"
    ],
    "wof:name":"Companion Pet Services, Inc.",
    "wof:placetype":"venue"
},
  "geometry": {"coordinates":[-96.817728,32.822769],"type":"Point"}
}