{
  "type": "Feature",
  "properties": {
    "iso:country":"US",
    "sg:address":"12106 Cabana Ln",
    "sg:city":"Austin",
    "sg:classifiers":[
        {
            "category":"Shopping",
            "subcategory":"Computers & Home Electronics",
            "type":"Retail Goods"
        }
    ],
    "sg:phone":"+1 512 835 0136",
    "sg:postcode":"78727",
    "sg:province":"TX",
    "sg:tags":[
        "software"
    ],
    "wof:name":"Spectrum Software Consulting",
    "wof:placetype":"venue"
},
  "geometry": {"coordinates":[-97.723624,30.416818],"type":"Point"}
}