{
  "type": "Feature",
  "properties": {
    "iso:country":"US",
    "sg:address":"213 S General McMullen Dr",
    "sg:city":"San Antonio",
    "sg:classifiers":[
        {
            "category":"Insurance",
            "subcategory":"Insurance Agent",
            "type":"Services"
        }
    ],
    "sg:phone":"+1 210 434 6325",
    "sg:postcode":"78237",
    "sg:province":"TX",
    "wof:name":"Alamo Auto Insurance",
    "wof:placetype":"venue"
},
  "geometry": {"coordinates":[-98.554377,29.429092],"type":"Point"}
}