{
  "type": "Feature",
  "properties": {
    "iso:country":"US",
    "sg:address":"2010 S Bonham St",
    "sg:city":"Amarillo",
    "sg:classifiers":[
        {
            "category":"Health Services",
            "subcategory":"Health Practitioner",
            "type":"Services"
        }
    ],
    "sg:phone":"+1 806 358 2765",
    "sg:postcode":"79109",
    "sg:province":"TX",
    "sg:tags":[
        "consulting"
    ],
    "wof:name":"Whipple Carol PHD",
    "wof:placetype":"venue"
},
  "geometry": {"coordinates":[-101.859111,35.189998],"type":"Point"}
}