{
  "type": "Feature",
  "properties": {
    "iso:country":"US",
    "sg:address":"219 Alicia Dr",
    "sg:city":"El Paso",
    "sg:classifiers":[
        {
            "category":"Professional",
            "subcategory":"Business Services",
            "type":"Services"
        }
    ],
    "sg:phone":"+1 915 778 3792",
    "sg:postcode":"79905",
    "sg:province":"TX",
    "wof:name":"Club Recuerdo",
    "wof:placetype":"venue"
},
  "geometry": {"coordinates":[-106.43095,31.766453],"type":"Point"}
}