{
  "type": "Feature",
  "properties": {
    "iso:country":"US",
    "sg:address":"201 Corinth St",
    "sg:city":"Dallas",
    "sg:classifiers":[
        {
            "category":"Food & Beverages",
            "subcategory":"Liquor & Beverages",
            "type":"Retail Goods"
        }
    ],
    "sg:phone":"+1 214 426 2456",
    "sg:postcode":"75207",
    "sg:province":"TX",
    "sg:tags":[
        "beer",
        "spirit",
        "wine"
    ],
    "wof:name":"Metro Cost Plus Beer & Grocery",
    "wof:placetype":"venue"
},
  "geometry": {"coordinates":[-96.793999,32.760101],"type":"Point"}
}