{
  "type": "Feature",
  "properties": {
    "iso:country":"US",
    "sg:address":"106 W 5th St",
    "sg:city":"Crane",
    "sg:classifiers":[
        {
            "category":"Government",
            "subcategory":"Office",
            "type":"Public Place"
        }
    ],
    "sg:phone":"+1 432 558 7381",
    "sg:postcode":"79731",
    "sg:province":"TX",
    "wof:name":"Texas Tech Rural Clinic",
    "wof:placetype":"venue"
},
  "geometry": {"coordinates":[-102.350656,31.398482],"type":"Point"}
}