{
  "type": "Feature",
  "properties": {
    "iso:country":"US",
    "sg:address":"1815 Weldon Dr",
    "sg:city":"Houston",
    "sg:classifiers":[
        {
            "category":"Manufacturing",
            "subcategory":"Furniture",
            "type":"Manufacturing & Wholesale Goods"
        }
    ],
    "sg:phone":"+1 281 443 3066",
    "sg:postcode":"77073",
    "sg:province":"TX",
    "sg:tags":[
        "building",
        "body",
        "public",
        "auto",
        "mfg"
    ],
    "wof:name":"Pikes Pro Stripes",
    "wof:placetype":"venue"
},
  "geometry": {"coordinates":[-95.365388,29.979482],"type":"Point"}
}