{
  "type": "Feature",
  "properties": {
    "iso:country":"US",
    "sg:address":"9925 Carnegie Ave",
    "sg:city":"El Paso",
    "sg:classifiers":[
        {
            "category":"Wholesale",
            "subcategory":"Metals & Minerals",
            "type":"Manufacturing & Wholesale Goods"
        }
    ],
    "sg:phone":"+1 915 594 8263",
    "sg:postcode":"79925",
    "sg:province":"TX",
    "sg:tags":[
        "steel",
        "warehouse"
    ],
    "sg:website":"www.aarmormetal.com",
    "wof:name":"Aarmor Metals & Supply Inc",
    "wof:placetype":"venue"
},
  "geometry": {"coordinates":[-106.349591,31.796719],"type":"Point"}
}