{
  "type": "Feature",
  "properties": {
    "iso:country":"US",
    "sg:address":"409 N Fredonia St",
    "sg:city":"Longview",
    "sg:classifiers":[
        {
            "category":"Insurance",
            "subcategory":"Hazard Insurance",
            "type":"Services"
        }
    ],
    "sg:phone":"+1 903 753 3416",
    "sg:postcode":"75601",
    "sg:province":"TX",
    "sg:tags":[
        "bond"
    ],
    "wof:name":"Preferred Bail Bonds",
    "wof:placetype":"venue"
},
  "geometry": {"coordinates":[-94.737354,32.497939],"type":"Point"}
}