{
  "type": "Feature",
  "properties": {
    "iso:country":"US",
    "sg:address":"4338 Kevinkay Dr",
    "sg:city":"Houston",
    "sg:classifiers":[
        {
            "category":"Building & Trades",
            "subcategory":"Construction",
            "type":"Services"
        }
    ],
    "sg:phone":"+1 281 345 1565",
    "sg:postcode":"77084",
    "sg:province":"TX",
    "sg:tags":[
        "contractor"
    ],
    "wof:name":"Jac Solid Surface Design",
    "wof:placetype":"venue"
},
  "geometry": {"coordinates":[-95.65681600000001,29.836631],"type":"Point"}
}