{
  "type": "Feature",
  "properties": {
    "iso:country":"US",
    "sg:address":"2902 S Robinson Dr",
    "sg:city":"Lorena",
    "sg:classifiers":[
        {
            "category":"Professional",
            "subcategory":"Detective & Security Services",
            "type":"Services"
        }
    ],
    "sg:phone":"+1 254 881 7283",
    "sg:postcode":"76655",
    "sg:province":"TX",
    "sg:tags":[
        "information",
        "bureau"
    ],
    "wof:name":"Grisham Bass A/C Solutions",
    "wof:placetype":"venue"
},
  "geometry": {"coordinates":[-97.092094,31.394976],"type":"Point"}
}