{
  "type": "Feature",
  "properties": {
    "iso:country":"US",
    "sg:address":"1018 Lauren Ln",
    "sg:city":"Plano",
    "sg:classifiers":[
        {
            "category":"Manufacturing",
            "subcategory":"Tools & Machinery",
            "type":"Manufacturing & Wholesale Goods"
        }
    ],
    "sg:phone":"+1 972 384 2184",
    "sg:postcode":"75094",
    "sg:province":"TX",
    "sg:tags":[
        "equipment",
        "mfg"
    ],
    "wof:name":"Administrative Plus Suppo",
    "wof:placetype":"venue"
},
  "geometry": {"coordinates":[-96.615962,33.032749],"type":"Point"}
}