{
  "type": "Feature",
  "properties": {
    "iso:country":"US",
    "sg:address":"1210 S Saddle Lakes Dr",
    "sg:city":"Abilene",
    "sg:classifiers":[
        {
            "category":"Insurance",
            "subcategory":"Insurance Agent",
            "type":"Services"
        }
    ],
    "sg:phone":"+1 325 695 8016",
    "sg:postcode":"79602",
    "sg:province":"TX",
    "wof:name":"National Marketing Insurance G",
    "wof:placetype":"venue"
},
  "geometry": {"coordinates":[-99.738119,32.344],"type":"Point"}
}