{
  "type": "Feature",
  "properties": {
    "iso:country":"US",
    "sg:address":"413 Hardy Cir",
    "sg:city":"El Paso",
    "sg:classifiers":[
        {
            "category":"Professional",
            "subcategory":"Business Services",
            "type":"Services"
        }
    ],
    "sg:phone":"+1 915 779 1077",
    "sg:postcode":"79905",
    "sg:province":"TX",
    "wof:name":"Edmundo B Arzola",
    "wof:placetype":"venue"
},
  "geometry": {"coordinates":[-106.410394,31.772174],"type":"Point"}
}