{
  "type": "Feature",
  "properties": {
    "iso:country":"US",
    "sg:address":"402 S 10th St",
    "sg:city":"Orange",
    "sg:classifiers":[
        {
            "category":"Government",
            "subcategory":"Office",
            "type":"Public Place"
        }
    ],
    "sg:phone":"+1 409 883 1901",
    "sg:postcode":"77630",
    "sg:province":"TX",
    "sg:tags":[
        "village"
    ],
    "wof:name":"Jackson Street Wastewater Plnt",
    "wof:placetype":"venue"
},
  "geometry": {"coordinates":[-93.74164500000001,30.085814],"type":"Point"}
}