{
  "type": "Feature",
  "properties": {
    "iso:country":"US",
    "sg:address":"3313 Vintage Dr",
    "sg:city":"Round Rock",
    "sg:classifiers":[
        {
            "category":"Professional",
            "type":"Services"
        }
    ],
    "sg:phone":"+1 512 255 2665",
    "sg:postcode":"78664",
    "sg:province":"TX",
    "sg:tags":[
        "arts",
        "artist"
    ],
    "wof:name":"Carla Stevens Hobbies",
    "wof:placetype":"venue"
},
  "geometry": {"coordinates":[-97.608919,30.519833],"type":"Point"}
}