{
  "type": "Feature",
  "properties": {
    "iso:country":"US",
    "sg:address":"5103 Randolph Blvd",
    "sg:city":"San Antonio",
    "sg:classifiers":[
        {
            "category":"Bars & Pubs",
            "type":"Food & Drink"
        }
    ],
    "sg:phone":"+1 210 590 9737",
    "sg:postcode":"78233",
    "sg:province":"TX",
    "sg:tags":[
        "club",
        "night"
    ],
    "wof:name":"Spanky's",
    "wof:placetype":"venue"
},
  "geometry": {"coordinates":[-98.386483,29.527367],"type":"Point"}
}