{
  "type": "Feature",
  "properties": {
    "iso:country":"US",
    "sg:address":"808 Teague St",
    "sg:city":"Navasota",
    "sg:classifiers":[
        {
            "category":"Building & Trades",
            "subcategory":"Cleaning & Sanitation",
            "type":"Services"
        }
    ],
    "sg:phone":"+1 936 825 3895",
    "sg:postcode":"77868",
    "sg:province":"TX",
    "sg:tags":[
        "maintenance"
    ],
    "wof:name":"Jacobs Janitorial Services",
    "wof:placetype":"venue"
},
  "geometry": {"coordinates":[-96.079437,30.385628],"type":"Point"}
}