{
  "type": "Feature",
  "properties": {
    "iso:country":"US",
    "sg:address":"1614 Raul Longoria Rd",
    "sg:city":"San Juan",
    "sg:classifiers":[
        {
            "category":"Shopping",
            "subcategory":"Discount & Variety Stores",
            "type":"Retail Goods"
        },
        {
            "category":"Shopping",
            "subcategory":"Department Store",
            "type":"Retail Goods"
        }
    ],
    "sg:phone":"+1 956 782 1349",
    "sg:postcode":"78589",
    "sg:province":"TX",
    "sg:tags":[
        "shop"
    ],
    "wof:name":"Family Dollar Stores",
    "wof:placetype":"venue"
},
  "geometry": {"coordinates":[-98.152512,26.207416],"type":"Point"}
}