{
  "type": "Feature",
  "properties": {
    "iso:country":"US",
    "sg:address":"2021 Nuches Ln",
    "sg:city":"Bryan",
    "sg:classifiers":[
        {
            "category":"Building & Trades",
            "subcategory":"Cleaning & Sanitation",
            "type":"Services"
        }
    ],
    "sg:phone":"+1 979 778 3643",
    "sg:postcode":"77803",
    "sg:province":"TX",
    "sg:tags":[
        "maintenance"
    ],
    "wof:name":"Casey Maintenance Co",
    "wof:placetype":"venue"
},
  "geometry": {"coordinates":[-96.366095,30.699564],"type":"Point"}
}