{
  "type": "Feature",
  "properties": {
    "iso:country":"US",
    "sg:address":"12733 Lyndon B Johnson Fwy",
    "sg:city":"Dallas",
    "sg:classifiers":[
        {
            "category":"Restaurant",
            "type":"Food & Drink"
        }
    ],
    "sg:postcode":"75240",
    "sg:province":"TX",
    "sg:tags":[
        "diner"
    ],
    "wof:name":"Denny's",
    "wof:placetype":"venue"
},
  "geometry": {"coordinates":[-96.763436,32.926052],"type":"Point"}
}