{
  "type": "Feature",
  "properties": {
    "iso:country":"US",
    "sg:address":"516 Shelbyville St",
    "sg:city":"Center",
    "sg:classifiers":[
        {
            "category":"Personal",
            "subcategory":"Beauty Salon",
            "type":"Services"
        }
    ],
    "sg:phone":"+1 936 598 9750",
    "sg:postcode":"75935",
    "sg:province":"TX",
    "sg:tags":[
        "manicuring"
    ],
    "wof:name":"Nail Couture",
    "wof:placetype":"venue"
},
  "geometry": {"coordinates":[-94.175588,31.793748],"type":"Point"}
}