{
  "type": "Feature",
  "properties": {
    "iso:country":"US",
    "sg:address":"3005 C R 175",
    "sg:city":"Leander",
    "sg:classifiers":[
        {
            "category":"Sports & Exercise",
            "subcategory":"Tennis Court",
            "type":"Entertainment"
        }
    ],
    "sg:phone":"+1 512 246 1807",
    "sg:postcode":"78641",
    "sg:province":"TX",
    "wof:name":"Williamson County Tennis Center",
    "wof:placetype":"venue"
},
  "geometry": {"coordinates":[-97.8741,30.5495],"type":"Point"}
}