{
  "type": "Feature",
  "properties": {
    "iso:country":"US",
    "sg:address":"412 E Main St",
    "sg:city":"Eastland",
    "sg:classifiers":[
        {
            "category":"Restaurant",
            "type":"Food & Drink"
        }
    ],
    "sg:phone":"+1 254 629 1461",
    "sg:postcode":"76448",
    "sg:province":"TX",
    "sg:tags":[
        "eating"
    ],
    "wof:name":"End of Trail Restaurant",
    "wof:placetype":"venue"
},
  "geometry": {"coordinates":[-98.81453999999999,32.401841],"type":"Point"}
}