{
  "type": "Feature",
  "properties": {
    "iso:country":"US",
    "sg:address":"311 Spring Hollow Dr",
    "sg:city":"Cedar Hill",
    "sg:classifiers":[
        {
            "category":"Professional",
            "type":"Services"
        }
    ],
    "sg:phone":"+1 972 291 9871",
    "sg:postcode":"75104",
    "sg:province":"TX",
    "sg:tags":[
        "establishment"
    ],
    "wof:name":"Deutsch Engineered Connecting",
    "wof:placetype":"venue"
},
  "geometry": {"coordinates":[-96.937263,32.564398],"type":"Point"}
}