{
  "type": "Feature",
  "properties": {
    "iso:country":"US",
    "sg:address":"1907 Lubbock St",
    "sg:city":"Harlingen",
    "sg:classifiers":[
        {
            "category":"Health Services",
            "subcategory":"Doctor",
            "type":"Services"
        }
    ],
    "sg:phone":"+1 956 421 2229",
    "sg:postcode":"78550",
    "sg:province":"TX",
    "sg:tags":[
        "physician",
        "surgeon"
    ],
    "wof:name":"Harlingen Infectious Disease",
    "wof:placetype":"venue"
},
  "geometry": {"coordinates":[-97.671161,26.17698],"type":"Point"}
}