{
  "type": "Feature",
  "properties": {
    "iso:country":"US",
    "sg:address":"409 S Midway Rd",
    "sg:city":"Big Spring",
    "sg:classifiers":[
        {
            "category":"Wholesale",
            "subcategory":"Auto Parts",
            "type":"Manufacturing & Wholesale Goods"
        }
    ],
    "sg:phone":"+1 432 268 1064",
    "sg:postcode":"79720",
    "sg:province":"TX",
    "sg:tags":[
        "automotive"
    ],
    "wof:name":"Henson Wrecker Service",
    "wof:placetype":"venue"
},
  "geometry": {"coordinates":[-101.403464,32.266802],"type":"Point"}
}