{
  "type": "Feature",
  "properties": {
    "iso:country":"US",
    "sg:address":"1519 Hi Line Dr",
    "sg:city":"Dallas",
    "sg:classifiers":[
        {
            "category":"Shopping",
            "subcategory":"Used Merchandise",
            "type":"Retail Goods"
        }
    ],
    "sg:phone":"+1 214 651 0100",
    "sg:postcode":"75207",
    "sg:province":"TX",
    "sg:tags":[
        "antique"
    ],
    "wof:name":"Byron Nathaniel",
    "wof:placetype":"venue"
},
  "geometry": {"coordinates":[-96.81683200000001,32.794677],"type":"Point"}
}