{
  "type": "Feature",
  "properties": {
    "iso:country":"US",
    "sg:address":"1410 Austin St",
    "sg:city":"Wichita Falls",
    "sg:classifiers":[
        {
            "category":"Building & Trades",
            "subcategory":"Construction",
            "type":"Services"
        }
    ],
    "sg:phone":"+1 940 767 4601",
    "sg:postcode":"76301",
    "sg:province":"TX",
    "sg:tags":[
        "awning",
        "windows",
        "siding"
    ],
    "wof:name":"Cool-Temp Siding Co",
    "wof:placetype":"venue"
},
  "geometry": {"coordinates":[-98.489993,33.903222],"type":"Point"}
}