{
  "type": "Feature",
  "properties": {
    "iso:country":"US",
    "sg:address":"10926 Garland Rd",
    "sg:city":"Dallas",
    "sg:classifiers":[
        {
            "category":"Home & Garden",
            "subcategory":"Building Materials",
            "type":"Retail Goods"
        }
    ],
    "sg:phone":"+1 214 328 6181",
    "sg:postcode":"75218",
    "sg:province":"TX",
    "sg:tags":[
        "paint"
    ],
    "wof:name":"Kelley-Moore Paint Co",
    "wof:placetype":"venue"
},
  "geometry": {"coordinates":[-96.68658499999999,32.846369],"type":"Point"}
}