{
  "type": "Feature",
  "properties": {
    "iso:country":"US",
    "sg:address":"3407 Azle Ave",
    "sg:city":"Fort Worth",
    "sg:classifiers":[
        {
            "category":"Building & Trades",
            "subcategory":"Landscaping Services",
            "type":"Services"
        }
    ],
    "sg:phone":"+1 817 624 4440",
    "sg:postcode":"76106",
    "sg:province":"TX",
    "wof:name":"Tree Surgeon",
    "wof:placetype":"venue"
},
  "geometry": {"coordinates":[-97.390345,32.807187],"type":"Point"}
}