{
  "type": "Feature",
  "properties": {
    "iso:country":"US",
    "sg:address":"950 Echo Ln",
    "sg:city":"Houston",
    "sg:classifiers":[
        {
            "category":"Professional",
            "subcategory":"Lawyer & Legal Services",
            "type":"Services"
        }
    ],
    "sg:phone":"+1 713 932 1540",
    "sg:postcode":"77024",
    "sg:province":"TX",
    "wof:name":"Givens Robert T Atty",
    "wof:placetype":"venue"
},
  "geometry": {"coordinates":[-95.521202,29.7806],"type":"Point"}
}