{
  "type": "Feature",
  "properties": {
    "iso:country":"US",
    "sg:address":"1719 W Ave C",
    "sg:city":"Temple",
    "sg:classifiers":[
        {
            "category":"Shopping",
            "subcategory":"Bicycles & Sporting Goods",
            "type":"Retail Goods"
        }
    ],
    "sg:phone":"+1 254 771 2004",
    "sg:postcode":"76504",
    "sg:province":"TX",
    "sg:tags":[
        "repair"
    ],
    "wof:name":"Sun Country Bicycles",
    "wof:placetype":"venue"
},
  "geometry": {"coordinates":[-97.360865,31.098704],"type":"Point"}
}