{
  "type": "Feature",
  "properties": {
    "iso:country":"US",
    "sg:address":"3901 Willowbrook Dr",
    "sg:city":"Austin",
    "sg:classifiers":[
        {
            "category":"Building & Trades",
            "subcategory":"Construction",
            "type":"Services"
        }
    ],
    "sg:phone":"+1 512 482 9232",
    "sg:postcode":"78722",
    "sg:province":"TX",
    "sg:tags":[
        "dry wall",
        "contractor"
    ],
    "wof:name":"Chase Drywall",
    "wof:placetype":"venue"
},
  "geometry": {"coordinates":[-97.711212,30.291687],"type":"Point"}
}