{
  "type": "Feature",
  "properties": {
    "iso:country":"US",
    "sg:address":"4450 Ridgemont Dr",
    "sg:city":"Abilene",
    "sg:classifiers":[
        {
            "category":"Real Estate",
            "subcategory":"Real Estate Operator",
            "type":"Services"
        }
    ],
    "sg:phone":"+1 325 695 6920",
    "sg:postcode":"79606",
    "sg:province":"TX",
    "sg:tags":[
        "building",
        "apartment"
    ],
    "wof:name":"Country Club Villas Apts  Inc",
    "wof:placetype":"venue"
},
  "geometry": {"coordinates":[-99.765136,32.396018],"type":"Point"}
}