{
  "type": "Feature",
  "properties": {
    "iso:country":"US",
    "sg:address":"110 W 6th Ave",
    "sg:city":"Corsicana",
    "sg:classifiers":[
        {
            "category":"Retail",
            "subcategory":"Auto Repair",
            "type":"Services"
        }
    ],
    "sg:phone":"+1 903 874 3881",
    "sg:postcode":"75110",
    "sg:province":"TX",
    "sg:tags":[
        "exchanging",
        "automotive",
        "engine"
    ],
    "wof:name":"Buddy's Garage & Wrecker Svc",
    "wof:placetype":"venue"
},
  "geometry": {"coordinates":[-96.463213,32.092825],"type":"Point"}
}