{
  "type": "Feature",
  "properties": {
    "iso:country":"US",
    "sg:address":"5807 Edmond Ave",
    "sg:city":"Waco",
    "sg:classifiers":[
        {
            "category":"Health Services",
            "subcategory":"Health Practitioner",
            "type":"Services"
        }
    ],
    "sg:phone":"+1 254 399 8933",
    "sg:postcode":"76710",
    "sg:province":"TX",
    "sg:tags":[
        "nurse",
        "registry"
    ],
    "wof:name":"WACO Independent Nurses Svc",
    "wof:placetype":"venue"
},
  "geometry": {"coordinates":[-97.194862,31.52828],"type":"Point"}
}