{
  "type": "Feature",
  "properties": {
    "iso:country":"US",
    "sg:address":"1610 S Fort Hood St",
    "sg:city":"Killeen",
    "sg:classifiers":[
        {
            "category":"Restaurant",
            "type":"Food & Drink"
        }
    ],
    "sg:menulink":"http://www.allmenus.com/tx/killeen/229082-golden-chick/menu/",
    "sg:phone":"+1 254 554 7939",
    "sg:postcode":"76542",
    "sg:province":"TX",
    "sg:tags":[
        "american"
    ],
    "wof:name":"Golden Chick",
    "wof:placetype":"venue"
},
  "geometry": {"coordinates":[-97.75120099999999,31.099501],"type":"Point"}
}