{
  "type": "Feature",
  "properties": {
    "iso:country":"US",
    "sg:address":"2209 Anita Dr",
    "sg:city":"Mesquite",
    "sg:classifiers":[
        {
            "category":"Banks & Credit Unions",
            "subcategory":"Financial Services",
            "type":"Services"
        }
    ],
    "sg:phone":"+1 972 288 4290",
    "sg:postcode":"75149",
    "sg:province":"TX",
    "sg:tags":[
        "trust",
        "investment",
        "real estate"
    ],
    "wof:name":"R&E Investments",
    "wof:placetype":"venue"
},
  "geometry": {"coordinates":[-96.633348,32.790739],"type":"Point"}
}