{
  "type": "Feature",
  "properties": {
    "iso:country":"US",
    "sg:address":"404 San Jacinto Ln",
    "sg:city":"Bryan",
    "sg:classifiers":[
        {
            "category":"Building & Trades",
            "subcategory":"Landscaping Services",
            "type":"Services"
        }
    ],
    "sg:phone":"+1 979 575 9251",
    "sg:postcode":"77803",
    "sg:province":"TX",
    "wof:name":"Complete Lawn Service",
    "wof:placetype":"venue"
},
  "geometry": {"coordinates":[-96.386298,30.679498],"type":"Point"}
}