{
  "type": "Feature",
  "properties": {
    "iso:country":"US",
    "sg:address":"5705 Northcrest Dr",
    "sg:city":"Flower Mound",
    "sg:classifiers":[
        {
            "category":"Professional",
            "subcategory":"Research",
            "type":"Services"
        }
    ],
    "sg:phone":"+1 972 691 9636",
    "sg:postcode":"75028",
    "sg:province":"TX",
    "sg:tags":[
        "nonphysical",
        "commercial",
        "business"
    ],
    "wof:name":"R Overshown & Co",
    "wof:placetype":"venue"
},
  "geometry": {"coordinates":[-97.055671,33.064286],"type":"Point"}
}