{
  "type": "Feature",
  "properties": {
    "iso:country":"US",
    "sg:address":"111 Shannon Dr",
    "sg:city":"Allen",
    "sg:classifiers":[
        {
            "category":"Shopping",
            "subcategory":"Bicycles & Sporting Goods",
            "type":"Retail Goods"
        }
    ],
    "sg:phone":"+1 972 727 9553",
    "sg:postcode":"75002",
    "sg:province":"TX",
    "wof:name":"GP Firearms",
    "wof:placetype":"venue"
},
  "geometry": {"coordinates":[-96.624844,33.099262],"type":"Point"}
}