{
  "type": "Feature",
  "properties": {
    "iso:country":"US",
    "sg:address":"1307 Uhland Rd",
    "sg:city":"San Marcos",
    "sg:classifiers":[
        {
            "category":"Education",
            "subcategory":"College",
            "type":"Public Place"
        }
    ],
    "sg:phone":"+1 512 393 7377",
    "sg:postcode":"78666",
    "sg:province":"TX",
    "sg:tags":[
        "university"
    ],
    "wof:name":"Youth Group",
    "wof:placetype":"venue"
},
  "geometry": {"coordinates":[-97.905907,29.895991],"type":"Point"}
}