{
  "type": "Feature",
  "properties": {
    "iso:country":"US",
    "sg:address":"1407 Alma St",
    "sg:city":"Victoria",
    "sg:classifiers":[
        {
            "category":"Manufacturing",
            "subcategory":"Signs",
            "type":"Manufacturing & Wholesale Goods"
        }
    ],
    "sg:phone":"+1 361 572 4131",
    "sg:postcode":"77901",
    "sg:province":"TX",
    "sg:tags":[
        "specialty",
        "mfg"
    ],
    "wof:name":"Advanced Signs & Graphics",
    "wof:placetype":"venue"
},
  "geometry": {"coordinates":[-96.990661,28.80089],"type":"Point"}
}