{
  "type": "Feature",
  "properties": {
    "iso:country":"US",
    "sg:address":"150 Bennington St",
    "sg:city":"Houston",
    "sg:classifiers":[
        {
            "category":"Banks & Credit Unions",
            "subcategory":"Investment Brokerage",
            "type":"Services"
        }
    ],
    "sg:phone":"+1 713 691 0271",
    "sg:postcode":"77022",
    "sg:province":"TX",
    "sg:tags":[
        "trade",
        "barter",
        "exchange"
    ],
    "wof:name":"American Trading Co",
    "wof:placetype":"venue"
},
  "geometry": {"coordinates":[-95.374489,29.821464],"type":"Point"}
}