{
  "type": "Feature",
  "properties": {
    "iso:country":"US",
    "sg:address":"3206 W Salinas St",
    "sg:city":"San Antonio",
    "sg:classifiers":[
        {
            "category":"Building & Trades",
            "subcategory":"Plumbing",
            "type":"Services"
        }
    ],
    "sg:phone":"+1 210 438 8555",
    "sg:postcode":"78207",
    "sg:province":"TX",
    "sg:tags":[
        "plumbing",
        "contractor"
    ],
    "wof:name":"J R Chavez Plumbing",
    "wof:placetype":"venue"
},
  "geometry": {"coordinates":[-98.531069,29.431324],"type":"Point"}
}