{
  "type": "Feature",
  "properties": {
    "iso:country":"US",
    "sg:address":"852 W Bedford Euless Rd",
    "sg:city":"Hurst",
    "sg:classifiers":[
        {
            "category":"Social Services",
            "subcategory":"Child Care",
            "type":"Services"
        },
        {
            "category":"Organizations",
            "subcategory":"Religious Organization",
            "type":"Services"
        }
    ],
    "sg:phone":"+1 817 284 2636",
    "sg:postcode":"76053",
    "sg:province":"TX",
    "sg:tags":[
        "kindergarten",
        "academic",
        "school"
    ],
    "wof:name":"Rainbow Christian Preschool",
    "wof:placetype":"venue"
},
  "geometry": {"coordinates":[-97.19233699999999,32.833278],"type":"Point"}
}