{
  "type": "Feature",
  "properties": {
    "iso:country":"US",
    "sg:address":"5430 Easthampton Dr",
    "sg:city":"Houston",
    "sg:classifiers":[
        {
            "category":"Building & Trades",
            "subcategory":"Construction",
            "type":"Services"
        }
    ],
    "sg:phone":"+1 281 227 0003",
    "sg:postcode":"77039",
    "sg:province":"TX",
    "sg:tags":[
        "roofing",
        "contractor"
    ],
    "wof:name":"Cardinal Roofing Inc",
    "wof:placetype":"venue"
},
  "geometry": {"coordinates":[-95.31018400000001,29.901032],"type":"Point"}
}