{
  "type": "Feature",
  "properties": {
    "iso:country":"US",
    "sg:address":"496 National Dr",
    "sg:city":"Rockwall",
    "sg:classifiers":[
        {
            "category":"Retail",
            "subcategory":"Auto Repair",
            "type":"Services"
        }
    ],
    "sg:phone":"+1 972 722 6722",
    "sg:postcode":"75032",
    "sg:province":"TX",
    "sg:tags":[
        "automotive"
    ],
    "wof:name":"Todds Towning Inc",
    "wof:placetype":"venue"
},
  "geometry": {"coordinates":[-96.442035,32.890833],"type":"Point"}
}