{
  "type": "Feature",
  "properties": {
    "iso:country":"US",
    "sg:address":"1849 Airline Dr",
    "sg:city":"Houston",
    "sg:classifiers":[
        {
            "category":"Autos & Motor Vehicles",
            "subcategory":"Fuel & Gas Station",
            "type":"Retail Goods"
        }
    ],
    "sg:phone":"+1 713 862 6703",
    "sg:postcode":"77009",
    "sg:province":"TX",
    "sg:tags":[
        "oil"
    ],
    "wof:name":"Foster's Service Station",
    "wof:placetype":"venue"
},
  "geometry": {"coordinates":[-95.38200399999999,29.804496],"type":"Point"}
}