{
  "type": "Feature",
  "properties": {
    "iso:country":"US",
    "sg:address":"15065 Inwood Rd",
    "sg:city":"Addison",
    "sg:classifiers":[
        {
            "category":"Food & Beverages",
            "subcategory":"Groceries & Convenience Stores",
            "type":"Retail Goods"
        }
    ],
    "sg:phone":"+1 972 239 6150",
    "sg:postcode":"75001",
    "sg:province":"TX",
    "wof:name":"Centennial Quikshop Q-5",
    "wof:placetype":"venue"
},
  "geometry": {"coordinates":[-96.830185,32.952219],"type":"Point"}
}