{
  "type": "Feature",
  "properties": {
    "iso:country":"US",
    "sg:address":"183 Tank Destroyer Blvd",
    "sg:city":"Killeen",
    "sg:classifiers":[
        {
            "category":"Government",
            "subcategory":"Office",
            "type":"Public Place"
        }
    ],
    "sg:phone":"+1 254 288 7044",
    "sg:postcode":"76544",
    "sg:province":"TX",
    "sg:tags":[
        "national",
        "security"
    ],
    "wof:name":"Ft Hood",
    "wof:placetype":"venue"
},
  "geometry": {"coordinates":[-97.760088,31.13367],"type":"Point"}
}