{
  "type": "Feature",
  "properties": {
    "iso:country":"US",
    "sg:address":"13354 Water Oak Ln",
    "sg:city":"Austin",
    "sg:classifiers":[
        {
            "category":"Building & Trades",
            "subcategory":"Landscaping Services",
            "type":"Services"
        }
    ],
    "sg:phone":"+1 512 336 7930",
    "sg:postcode":"78729",
    "sg:province":"TX",
    "sg:tags":[
        "landscape"
    ],
    "wof:name":"All Purpose Landscaping",
    "wof:placetype":"venue"
},
  "geometry": {"coordinates":[-97.76712000000001,30.460754],"type":"Point"}
}