{
  "type": "Feature",
  "properties": {
    "iso:country":"US",
    "sg:address":"3609 Fieldwood Dr",
    "sg:city":"San Angelo",
    "sg:classifiers":[
        {
            "category":"Professional",
            "type":"Services"
        }
    ],
    "sg:phone":"+1 325 949 5686",
    "sg:postcode":"76904",
    "sg:province":"TX",
    "wof:name":"Norma R Brawner",
    "wof:placetype":"venue"
},
  "geometry": {"coordinates":[-100.491225,31.423438],"type":"Point"}
}