{
  "type": "Feature",
  "properties": {
    "iso:country":"US",
    "sg:address":"1608 N University Ave",
    "sg:city":"Lubbock",
    "sg:classifiers":[
        {
            "category":"Manufacturing",
            "subcategory":"Signs",
            "type":"Manufacturing & Wholesale Goods"
        }
    ],
    "sg:phone":"+1 806 747 8890",
    "sg:postcode":"79415",
    "sg:province":"TX",
    "wof:name":"Neon Art & Design",
    "wof:placetype":"venue"
},
  "geometry": {"coordinates":[-101.87038,33.616713],"type":"Point"}
}