{
  "type": "Feature",
  "properties": {
    "iso:country":"US",
    "sg:address":"340 Paredes Line Rd",
    "sg:city":"Brownsville",
    "sg:classifiers":[
        {
            "category":"Food & Beverages",
            "subcategory":"Bakery",
            "type":"Retail Goods"
        }
    ],
    "sg:phone":"+1 956 544 5276",
    "sg:postcode":"78521",
    "sg:province":"TX",
    "wof:name":"Los Ebanos Bakery",
    "wof:placetype":"venue"
},
  "geometry": {"coordinates":[-97.489107,25.926062],"type":"Point"}
}