{
  "type": "Feature",
  "properties": {
    "iso:country":"US",
    "sg:address":"23608 Highway 36",
    "sg:city":"Damon",
    "sg:classifiers":[
        {
            "category":"Food & Beverages",
            "subcategory":"Groceries & Convenience Stores",
            "type":"Retail Goods"
        }
    ],
    "sg:phone":"+1 979 742 3371",
    "sg:postcode":"77430",
    "sg:province":"TX",
    "wof:name":"Wrights Drive In Grocery",
    "wof:placetype":"venue"
},
  "geometry": {"coordinates":[-95.729919,29.291259],"type":"Point"}
}