{
  "type": "Feature",
  "properties": {
    "iso:country":"US",
    "sg:address":"520 S 1st St",
    "sg:city":"Lufkin",
    "sg:classifiers":[
        {
            "category":"Banks & Credit Unions",
            "subcategory":"Bank",
            "type":"Services"
        }
    ],
    "sg:phone":"+1 936 634 4343",
    "sg:postcode":"75901",
    "sg:province":"TX",
    "sg:tags":[
        "loan",
        "real estate"
    ],
    "wof:name":"Parmann Mortgage",
    "wof:placetype":"venue"
},
  "geometry": {"coordinates":[-94.73035400000001,31.334956],"type":"Point"}
}