{
  "type": "Feature",
  "properties": {
    "iso:country":"US",
    "sg:address":"601 N Cesar Chavez Blvd",
    "sg:city":"Houston",
    "sg:classifiers":[
        {
            "category":"Shopping",
            "type":"Retail Goods"
        }
    ],
    "sg:phone":"+1 713 923 7371",
    "sg:postcode":"77011",
    "sg:province":"TX",
    "sg:tags":[
        "telephone",
        "cellular"
    ],
    "wof:name":"Beta Page Inc",
    "wof:placetype":"venue"
},
  "geometry": {"coordinates":[-95.306558,29.741671],"type":"Point"}
}