{
  "type": "Feature",
  "properties": {
    "iso:country":"US",
    "sg:address":"4649 Westgrove Dr",
    "sg:city":"Addison",
    "sg:classifiers":[
        {
            "category":"Professional",
            "subcategory":"Detective & Security Services",
            "type":"Services"
        }
    ],
    "sg:phone":"+1 972 980 7878",
    "sg:postcode":"75001",
    "sg:province":"TX",
    "sg:tags":[
        "system"
    ],
    "wof:name":"Spectrum Alarm Systems",
    "wof:placetype":"venue"
},
  "geometry": {"coordinates":[-96.826887,32.975438],"type":"Point"}
}