{
  "type": "Feature",
  "properties": {
    "iso:country":"US",
    "sg:address":"1803 S Houston Rd",
    "sg:city":"Pasadena",
    "sg:classifiers":[
        {
            "category":"Retail",
            "subcategory":"Auto Repair",
            "type":"Services"
        }
    ],
    "sg:phone":"+1 713 472 5490",
    "sg:postcode":"77502",
    "sg:province":"TX",
    "sg:tags":[
        "automotive"
    ],
    "wof:name":"Juniors Place",
    "wof:placetype":"venue"
},
  "geometry": {"coordinates":[-95.221503,29.686063],"type":"Point"}
}