{
  "type": "Feature",
  "properties": {
    "iso:country":"US",
    "sg:address":"2438 Co Rd 137",
    "sg:city":"Floresville",
    "sg:classifiers":[
        {
            "category":"Farming",
            "subcategory":"Farm & Veterinary Services",
            "type":"Manufacturing & Wholesale Goods"
        }
    ],
    "sg:phone":"+1 830 393 2397",
    "sg:postcode":"78114",
    "sg:province":"TX",
    "sg:tags":[
        "crop"
    ],
    "wof:name":"Boening Bros Dusting Spraying",
    "wof:placetype":"venue"
},
  "geometry": {"coordinates":[-98.25949199999999,29.029412],"type":"Point"}
}