{
  "type": "Feature",
  "properties": {
    "iso:country":"US",
    "sg:address":"2223 Singleton Blvd",
    "sg:city":"Dallas",
    "sg:classifiers":[
        {
            "category":"Shopping",
            "subcategory":"Clothing, Apparel, & Fashions",
            "type":"Retail Goods"
        }
    ],
    "sg:phone":"+1 214 634 0154",
    "sg:postcode":"75212",
    "sg:province":"TX",
    "sg:tags":[
        "hair",
        "supply"
    ],
    "wof:name":"Wig Palace Of Texas",
    "wof:placetype":"venue"
},
  "geometry": {"coordinates":[-96.860516,32.778772],"type":"Point"}
}