{
  "type": "Feature",
  "properties": {
    "iso:country":"US",
    "sg:address":"5610 Brookview Ct",
    "sg:city":"Garland",
    "sg:classifiers":[
        {
            "category":"Professional",
            "subcategory":"Business Services",
            "type":"Services"
        }
    ],
    "sg:phone":"+1 972 496 9238",
    "sg:postcode":"75048",
    "sg:province":"TX",
    "wof:name":"Brookview Pool Care",
    "wof:placetype":"venue"
},
  "geometry": {"coordinates":[-96.596653,32.973617],"type":"Point"}
}