{
  "type": "Feature",
  "properties": {
    "iso:country":"US",
    "sg:address":"602 Green Valley Dr",
    "sg:city":"Abilene",
    "sg:classifiers":[
        {
            "category":"Place Of Worship",
            "type":"Public Place"
        }
    ],
    "sg:phone":"+1 325 677 7032",
    "sg:postcode":"79601",
    "sg:province":"TX",
    "sg:tags":[
        "church"
    ],
    "wof:name":"Mission Church Of Christ",
    "wof:placetype":"venue"
},
  "geometry": {"coordinates":[-99.71455,32.453345],"type":"Point"}
}