{
  "type": "Feature",
  "properties": {
    "iso:country":"US",
    "sg:address":"5555 N Jim Miller Rd",
    "sg:city":"Dallas",
    "sg:classifiers":[
        {
            "category":"Restaurant",
            "type":"Food & Drink"
        }
    ],
    "sg:phone":"+1 214 381 5157",
    "sg:postcode":"75228",
    "sg:province":"TX",
    "wof:name":"Wendy's Old Fashioned Hamburgers",
    "wof:placetype":"venue"
},
  "geometry": {"coordinates":[-96.700203,32.792],"type":"Point"}
}