{
  "type": "Feature",
  "properties": {
    "iso:country":"US",
    "sg:address":"800 E California St",
    "sg:city":"Gainesville",
    "sg:classifiers":[
        {
            "category":"Social Services",
            "type":"Services"
        }
    ],
    "sg:phone":"+1 940 668 1292",
    "sg:postcode":"76240",
    "sg:province":"TX",
    "wof:name":"Outreach Health Services-Wic Clinic",
    "wof:placetype":"venue"
},
  "geometry": {"coordinates":[-97.138023,33.624249],"type":"Point"}
}