{
  "type": "Feature",
  "properties": {
    "iso:country":"US",
    "sg:address":"755 S 11th St",
    "sg:city":"Beaumont",
    "sg:classifiers":[
        {
            "category":"Health Services",
            "subcategory":"Clinic",
            "type":"Services"
        }
    ],
    "sg:phone":"+1 409 832 5000",
    "sg:postcode":"77701",
    "sg:province":"TX",
    "sg:tags":[
        "home",
        "care"
    ],
    "wof:name":"Americare Professionals",
    "wof:placetype":"venue"
},
  "geometry": {"coordinates":[-94.12939799999999,30.070662],"type":"Point"}
}