{
  "type": "Feature",
  "properties": {
    "iso:country":"US",
    "sg:address":"2901 Terrell Ave",
    "sg:city":"Beaumont",
    "sg:classifiers":[
        {
            "category":"Real Estate",
            "subcategory":"Real Estate Agent",
            "type":"Services"
        }
    ],
    "sg:phone":"+1 409 835 4673",
    "sg:postcode":"77701",
    "sg:province":"TX",
    "sg:tags":[
        "authorities",
        "housing"
    ],
    "wof:name":"Beaumont Housing Authority",
    "wof:placetype":"venue"
},
  "geometry": {"coordinates":[-94.11781999999999,30.05782],"type":"Point"}
}