{
  "type": "Feature",
  "properties": {
    "iso:country":"US",
    "sg:address":"2120 Welch St",
    "sg:city":"Houston",
    "sg:classifiers":[
        {
            "category":"Professional",
            "subcategory":"Lawyer & Legal Services",
            "type":"Services"
        }
    ],
    "sg:phone":"+1 713 523 7878",
    "sg:postcode":"77019",
    "sg:province":"TX",
    "wof:name":"Ramsey & Tyson",
    "wof:placetype":"venue"
},
  "geometry": {"coordinates":[-95.410797,29.748199],"type":"Point"}
}