{
  "type": "Feature",
  "properties": {
    "iso:country":"US",
    "sg:address":"7717 Lockheed Dr",
    "sg:city":"El Paso",
    "sg:classifiers":[
        {
            "category":"Professional",
            "subcategory":"Business Services",
            "type":"Services"
        },
        {
            "category":"Professional",
            "subcategory":"Management & Consulting",
            "type":"Services"
        }
    ],
    "sg:phone":"+1 915 771 7337",
    "sg:postcode":"79925",
    "sg:province":"TX",
    "sg:tags":[
        "promotion",
        "sales"
    ],
    "wof:name":"Millenium Sales Of El Paso",
    "wof:placetype":"venue"
},
  "geometry": {"coordinates":[-106.384196,31.791556],"type":"Point"}
}