{
  "type": "Feature",
  "properties": {
    "iso:country":"US",
    "sg:address":"501 Guadalupe St",
    "sg:city":"Laredo",
    "sg:classifiers":[
        {
            "category":"Food & Beverages",
            "subcategory":"Specialty",
            "type":"Retail Goods"
        }
    ],
    "sg:phone":"+1 956 753 6677",
    "sg:postcode":"78040",
    "sg:province":"TX",
    "wof:name":"Synergy Health",
    "wof:placetype":"venue"
},
  "geometry": {"coordinates":[-99.490754,27.506574],"type":"Point"}
}