{
  "type": "Feature",
  "properties": {
    "iso:country":"US",
    "sg:address":"1313 W Buckingham Rd",
    "sg:city":"Garland",
    "sg:classifiers":[
        {
            "category":"Autos & Motor Vehicles",
            "subcategory":"Auto Supplies",
            "type":"Retail Goods"
        },
        {
            "category":"Wholesale",
            "subcategory":"Electrical",
            "type":"Manufacturing & Wholesale Goods"
        },
        {
            "category":"Wholesale",
            "subcategory":"Auto Parts",
            "type":"Manufacturing & Wholesale Goods"
        }
    ],
    "sg:phone":"+1 972 495 5484",
    "sg:postcode":"75040",
    "sg:province":"TX",
    "sg:tags":[
        "body",
        "battery",
        "automobile",
        "accessory",
        "equipment",
        "truck"
    ],
    "sg:website":"http://www.oreillyauto.com?utm_source=yellowpages&utm_medium=iyp&utm_campaign=560",
    "wof:name":"O'Reilly Auto Parts",
    "wof:placetype":"venue"
},
  "geometry": {"coordinates":[-96.646445,32.931132],"type":"Point"}
}