{
  "type": "Feature",
  "properties": {
    "iso:country":"US",
    "sg:address":"5512 W Plano Pkwy",
    "sg:city":"Plano",
    "sg:classifiers":[
        {
            "category":"Professional",
            "type":"Services"
        },
        {
            "category":"Banks & Credit Unions",
            "subcategory":"Financial Services",
            "type":"Services"
        }
    ],
    "sg:phone":"+1 972 867 3997",
    "sg:postcode":"75093",
    "sg:province":"TX",
    "sg:tags":[
        "establishment",
        "investment",
        "closed"
    ],
    "sg:website":"www.munsent.com",
    "wof:name":"Muns Enterprises Ltd",
    "wof:placetype":"venue"
},
  "geometry": {"coordinates":[-96.812805,33.015892],"type":"Point"}
}