{
  "type": "Feature",
  "properties": {
    "iso:country":"US",
    "sg:address":"3644 Chimney Corner Dr",
    "sg:city":"Waco",
    "sg:classifiers":[
        {
            "category":"Building & Trades",
            "subcategory":"Construction",
            "type":"Services"
        }
    ],
    "sg:phone":"+1 254 756 1165",
    "sg:postcode":"76708",
    "sg:province":"TX",
    "sg:tags":[
        "contractor"
    ],
    "wof:name":"Ronnie Ives Company",
    "wof:placetype":"venue"
},
  "geometry": {"coordinates":[-97.185193,31.560206],"type":"Point"}
}