{
  "type": "Feature",
  "properties": {
    "iso:country":"US",
    "sg:address":"1111 San Jacinto St",
    "sg:city":"Houston",
    "sg:classifiers":[
        {
            "category":"Parking",
            "type":"Transportation"
        }
    ],
    "sg:phone":"+1 713 654 9005",
    "sg:postcode":"77002",
    "sg:province":"TX",
    "sg:website":"www.standardparking.com",
    "wof:name":"Standard Parking Inc",
    "wof:placetype":"venue"
},
  "geometry": {"coordinates":[-95.3638,29.7551],"type":"Point"}
}