{
  "type": "Feature",
  "properties": {
    "iso:country":"US",
    "sg:address":"13000 William Dodson Pkwy",
    "sg:city":"Farmers Branch",
    "sg:classifiers":[
        {
            "category":"Government",
            "subcategory":"Office",
            "type":"Public Place"
        }
    ],
    "sg:phone":"+1 972 919 2588",
    "sg:postcode":"75234",
    "sg:province":"TX",
    "sg:tags":[
        "village"
    ],
    "sg:website":"www.farmersbranch.com",
    "wof:name":"Farmers Branch Engineering",
    "wof:placetype":"venue"
},
  "geometry": {"coordinates":[-96.893389,32.922615],"type":"Point"}
}