{
  "type": "Feature",
  "properties": {
    "iso:country":"US",
    "sg:address":"2104 Fisk Ave",
    "sg:city":"Brownwood",
    "sg:classifiers":[
        {
            "category":"Manufacturing",
            "subcategory":"Wood Products",
            "type":"Manufacturing & Wholesale Goods"
        }
    ],
    "sg:phone":"+1 325 646 2915",
    "sg:postcode":"76801",
    "sg:province":"TX",
    "wof:name":"Indian Creek Mesquite Inc",
    "wof:placetype":"venue"
},
  "geometry": {"coordinates":[-98.993127,31.708303],"type":"Point"}
}