{
  "type": "Feature",
  "properties": {
    "iso:country":"US",
    "sg:address":"1455 Buckingham Rd",
    "sg:city":"Richardson",
    "sg:classifiers":[
        {
            "category":"Shopping",
            "type":"Retail Goods"
        }
    ],
    "sg:phone":"+1 972 664 1455",
    "sg:postcode":"75081",
    "sg:province":"TX",
    "sg:tags":[
        "cosmetic",
        "perfume"
    ],
    "wof:name":"Beauty Supply 4U",
    "wof:placetype":"venue"
},
  "geometry": {"coordinates":[-96.72410000000001,32.934844],"type":"Point"}
}