{
  "type": "Feature",
  "properties": {
    "iso:country":"US",
    "sg:address":"6060 N Central Expy Ste 5",
    "sg:city":"Dallas",
    "sg:classifiers":[
        {
            "category":"Professional",
            "subcategory":"Business Services",
            "type":"Services"
        }
    ],
    "sg:phone":"+1 214 800 3498",
    "sg:postcode":"75206",
    "sg:province":"TX",
    "sg:tags":[
        "broker"
    ],
    "wof:name":"B & D Business Ventures",
    "wof:placetype":"venue"
},
  "geometry": {"coordinates":[-96.776143,32.839951],"type":"Point"}
}