{
  "type": "Feature",
  "properties": {
    "iso:country":"US",
    "sg:address":"5830 Cliffmont Dr",
    "sg:city":"San Antonio",
    "sg:classifiers":[
        {
            "category":"Professional",
            "subcategory":"Business Services",
            "type":"Services"
        }
    ],
    "sg:phone":"+1 210 684 2464",
    "sg:postcode":"78250",
    "sg:province":"TX",
    "wof:name":"AB Group",
    "wof:placetype":"venue"
},
  "geometry": {"coordinates":[-98.68228499999999,29.494649],"type":"Point"}
}