{
  "type": "Feature",
  "properties": {
    "iso:country":"US",
    "sg:address":"503 S Mechanic St",
    "sg:city":"El Campo",
    "sg:classifiers":[
        {
            "category":"Restaurant",
            "type":"Food & Drink"
        }
    ],
    "sg:phone":"+1 979 543 6482",
    "sg:postcode":"77437",
    "sg:province":"TX",
    "wof:name":"Schulze's Family Restaurant",
    "wof:placetype":"venue"
},
  "geometry": {"coordinates":[-96.26583599999999,29.191968],"type":"Point"}
}