{
  "type": "Feature",
  "properties": {
    "iso:country":"US",
    "sg:address":"205 W Windcrest St # 340",
    "sg:city":"Fredericksburg",
    "sg:classifiers":[
        {
            "category":"Health Services",
            "subcategory":"Doctor",
            "type":"Services"
        }
    ],
    "sg:phone":"+1 830 997 1010",
    "sg:postcode":"78624",
    "sg:province":"TX",
    "sg:tags":[
        "physician",
        "pulmonary",
        "surgeon",
        "surgeons",
        "disease"
    ],
    "wof:name":"Terrell Kenneth Dr",
    "wof:placetype":"venue"
},
  "geometry": {"coordinates":[-98.88050699999999,30.264009],"type":"Point"}
}