{
  "type": "Feature",
  "properties": {
    "iso:country":"US",
    "sg:address":"2015 Thomas St",
    "sg:city":"Houston",
    "sg:classifiers":[
        {
            "category":"Health Services",
            "subcategory":"Hospital",
            "type":"Services"
        }
    ],
    "sg:phone":"+1 713 873 4000",
    "sg:postcode":"77009",
    "sg:province":"TX",
    "wof:name":"Harris County Hospital District",
    "wof:placetype":"venue"
},
  "geometry": {"coordinates":[-95.365303,29.7771],"type":"Point"}
}