{
  "type": "Feature",
  "properties": {
    "iso:country":"US",
    "sg:address":"5158 Nolan St",
    "sg:city":"Fort Worth",
    "sg:classifiers":[
        {
            "category":"Building & Trades",
            "subcategory":"Construction",
            "type":"Services"
        }
    ],
    "sg:phone":"+1 817 536 0939",
    "sg:postcode":"76119",
    "sg:province":"TX",
    "sg:tags":[
        "contractor"
    ],
    "wof:name":"O & C Drywall",
    "wof:placetype":"venue"
},
  "geometry": {"coordinates":[-97.274485,32.683376],"type":"Point"}
}