{
  "type": "Feature",
  "properties": {
    "iso:country":"US",
    "sg:address":"527 Main St",
    "sg:city":"Irving",
    "sg:classifiers":[
        {
            "category":"Manufacturing",
            "subcategory":"Motor Vehicles & Parts",
            "type":"Manufacturing & Wholesale Goods"
        }
    ],
    "sg:phone":"+1 972 251 1388",
    "sg:postcode":"75061",
    "sg:province":"TX",
    "sg:tags":[
        "carburetor"
    ],
    "wof:name":"Carburetor Service Co",
    "wof:placetype":"venue"
},
  "geometry": {"coordinates":[-96.94634499999999,32.820948],"type":"Point"}
}