{
  "type": "Feature",
  "properties": {
    "iso:country":"US",
    "sg:address":"12924 Park Xing",
    "sg:city":"San Antonio",
    "sg:classifiers":[
        {
            "category":"Insurance",
            "subcategory":"Insurance Agent",
            "type":"Services"
        }
    ],
    "sg:phone":"+1 210 496 6412",
    "sg:postcode":"78217",
    "sg:province":"TX",
    "wof:name":"Allstate Insurance",
    "wof:placetype":"venue"
},
  "geometry": {"coordinates":[-98.416642,29.55835],"type":"Point"}
}