{
  "type": "Feature",
  "properties": {
    "iso:country":"US",
    "sg:address":"1700 Central St",
    "sg:city":"Houston",
    "sg:classifiers":[
        {
            "category":"Retail",
            "subcategory":"Repair Shop",
            "type":"Services"
        }
    ],
    "sg:phone":"+1 713 926 3577",
    "sg:postcode":"77017",
    "sg:province":"TX",
    "wof:name":"Delta Trailer",
    "wof:placetype":"venue"
},
  "geometry": {"coordinates":[-95.263796,29.707898],"type":"Point"}
}