{
  "type": "Feature",
  "properties": {
    "iso:country":"US",
    "sg:address":"9341 Loma Vista Dr",
    "sg:city":"Dallas",
    "sg:classifiers":[
        {
            "category":"Building & Trades",
            "subcategory":"Construction",
            "type":"Services"
        }
    ],
    "sg:phone":"+1 214 340 9606",
    "sg:postcode":"75243",
    "sg:province":"TX",
    "sg:tags":[
        "home",
        "builder"
    ],
    "wof:name":"Rustown Homes Inc",
    "wof:placetype":"venue"
},
  "geometry": {"coordinates":[-96.743351,32.897045],"type":"Point"}
}