{
  "type": "Feature",
  "properties": {
    "iso:country":"US",
    "sg:address":"2809 Thousand Oaks Dr",
    "sg:city":"San Antonio",
    "sg:classifiers":[
        {
            "category":"Insurance",
            "subcategory":"Insurance Agent",
            "type":"Services"
        }
    ],
    "sg:phone":"+1 210 494 6939",
    "sg:postcode":"78232",
    "sg:province":"TX",
    "wof:name":"State Farm Insurance",
    "wof:placetype":"venue"
},
  "geometry": {"coordinates":[-98.44705,29.582459],"type":"Point"}
}