{
  "type": "Feature",
  "properties": {
    "iso:country":"US",
    "sg:address":"2804 Turnberry Dr",
    "sg:city":"Arlington",
    "sg:classifiers":[
        {
            "category":"Professional",
            "subcategory":"Employment Agencies",
            "type":"Services"
        }
    ],
    "sg:phone":"+1 817 657 9542",
    "sg:postcode":"76006",
    "sg:province":"TX",
    "wof:name":"Home Employment",
    "wof:placetype":"venue"
},
  "geometry": {"coordinates":[-97.09231200000001,32.784633],"type":"Point"}
}