{
  "type": "Feature",
  "properties": {
    "iso:country":"US",
    "sg:address":"816 S I Rd",
    "sg:city":"Pharr",
    "sg:classifiers":[
        {
            "category":"Restaurant",
            "type":"Food & Drink"
        }
    ],
    "sg:phone":"+1 956 702 0155",
    "sg:postcode":"78577",
    "sg:province":"TX",
    "sg:tags":[
        "eating"
    ],
    "wof:name":"Irenes Mexican Restaurant",
    "wof:placetype":"venue"
},
  "geometry": {"coordinates":[-98.168508,26.187566],"type":"Point"}
}