{
  "type": "Feature",
  "properties": {
    "iso:country":"US",
    "sg:address":"1438 E Hwy 377",
    "sg:city":"Granbury",
    "sg:classifiers":[
        {
            "category":"Retail",
            "subcategory":"Laundry & Dry Cleaning",
            "type":"Services"
        }
    ],
    "sg:phone":"+1 817 579 2629",
    "sg:postcode":"76048",
    "sg:province":"TX",
    "sg:tags":[
        "drycleaning",
        "plant"
    ],
    "wof:name":"A Plus Cleaners",
    "wof:placetype":"venue"
},
  "geometry": {"coordinates":[-97.763375,32.438548],"type":"Point"}
}