{
  "type": "Feature",
  "properties": {
    "iso:country":"US",
    "sg:address":"3211 Plainview St",
    "sg:city":"Pasadena",
    "sg:classifiers":[
        {
            "category":"Professional",
            "subcategory":"Accounting & Tax Preparation",
            "type":"Services"
        }
    ],
    "sg:phone":"+1 713 910 6567",
    "sg:postcode":"77504",
    "sg:province":"TX",
    "sg:tags":[
        "billing"
    ],
    "wof:name":"Columbia Baysore Medical",
    "wof:placetype":"venue"
},
  "geometry": {"coordinates":[-95.18224600000001,29.660287],"type":"Point"}
}