{
  "type": "Feature",
  "properties": {
    "iso:country":"US",
    "sg:address":"11895 S Profit Row",
    "sg:city":"Forney",
    "sg:classifiers":[
        {
            "category":"Wholesale",
            "subcategory":"Construction Materials",
            "type":"Manufacturing & Wholesale Goods"
        },
        {
            "category":"Professional",
            "subcategory":"Art Services",
            "type":"Services"
        },
        {
            "category":"Building & Trades",
            "subcategory":"Construction",
            "type":"Services"
        }
    ],
    "sg:phone":"+1 972 552 5000",
    "sg:postcode":"75126",
    "sg:province":"TX",
    "sg:tags":[
        "coatings-protective",
        "finisher",
        "metal",
        "painting-production"
    ],
    "wof:name":"Apex Industrial Coating Corp",
    "wof:placetype":"venue"
},
  "geometry": {"coordinates":[-96.43952400000001,32.731307],"type":"Point"}
}