{
  "type": "Feature",
  "properties": {
    "iso:country":"US",
    "sg:address":"8717 Overland Dr",
    "sg:city":"Fort Worth",
    "sg:classifiers":[
        {
            "category":"Professional",
            "subcategory":"Detective & Security Services",
            "type":"Services"
        }
    ],
    "sg:phone":"+1 817 236 8675",
    "sg:postcode":"76179",
    "sg:province":"TX",
    "sg:tags":[
        "car"
    ],
    "wof:name":"Cal Tech Investigations",
    "wof:placetype":"venue"
},
  "geometry": {"coordinates":[-97.438406,32.88521],"type":"Point"}
}