{
  "type": "Feature",
  "properties": {
    "iso:country":"US",
    "sg:address":"3001 Airport Fwy",
    "sg:city":"Bedford",
    "sg:classifiers":[
        {
            "category":"Health Services",
            "subcategory":"Doctor",
            "type":"Services"
        }
    ],
    "sg:phone":"+1 817 571 6863",
    "sg:postcode":"76021",
    "sg:province":"TX",
    "sg:tags":[
        "a",
        "physician",
        "surgeon",
        "as",
        "operates"
    ],
    "sg:website":"www.thecosmeticlasercenter.com",
    "wof:name":"Stephen J Farmer Inc",
    "wof:placetype":"venue"
},
  "geometry": {"coordinates":[-97.117239,32.838194],"type":"Point"}
}