{
  "type": "Feature",
  "properties": {
    "iso:country":"US",
    "sg:address":"310 N 25 Mile Ave",
    "sg:city":"Hereford",
    "sg:classifiers":[
        {
            "category":"Building & Trades",
            "subcategory":"Equipment Rental",
            "type":"Services"
        }
    ],
    "sg:phone":"+1 806 364 8881",
    "sg:postcode":"79045",
    "sg:province":"TX",
    "sg:tags":[
        "yard"
    ],
    "wof:name":"Color Tyme",
    "wof:placetype":"venue"
},
  "geometry": {"coordinates":[-102.405402,34.830901],"type":"Point"}
}