{
  "type": "Feature",
  "properties": {
    "iso:country":"US",
    "sg:address":"314 W Hollywood Ave",
    "sg:city":"San Antonio",
    "sg:classifiers":[
        {
            "category":"Real Estate",
            "subcategory":"Real Estate Operator",
            "type":"Services"
        }
    ],
    "sg:phone":"+1 210 732 1184",
    "sg:postcode":"78212",
    "sg:province":"TX",
    "sg:tags":[
        "building",
        "nonresidential"
    ],
    "wof:name":"Equitech Lc",
    "wof:placetype":"venue"
},
  "geometry": {"coordinates":[-98.499059,29.464049],"type":"Point"}
}