{
  "type": "Feature",
  "properties": {
    "iso:country":"US",
    "sg:address":"600 Topeka Dr",
    "sg:city":"Woodway",
    "sg:classifiers":[
        {
            "category":"Professional",
            "subcategory":"Printing & Photocopies",
            "type":"Services"
        }
    ],
    "sg:phone":"+1 254 772 1258",
    "sg:postcode":"76712",
    "sg:province":"TX",
    "sg:tags":[
        "lithographer"
    ],
    "wof:name":"Traylor Printing",
    "wof:placetype":"venue"
},
  "geometry": {"coordinates":[-97.207317,31.512524],"type":"Point"}
}