{
  "type": "Feature",
  "properties": {
    "iso:country":"US",
    "sg:address":"112 Bedford Rd",
    "sg:city":"Bedford",
    "sg:classifiers":[
        {
            "category":"Professional",
            "subcategory":"Accounting & Tax Preparation",
            "type":"Services"
        }
    ],
    "sg:phone":"+1 817 280 0446",
    "sg:postcode":"76022",
    "sg:province":"TX",
    "sg:tags":[
        "bookkeeping",
        "billing"
    ],
    "wof:name":"Alexander & Assoc",
    "wof:placetype":"venue"
},
  "geometry": {"coordinates":[-97.167061,32.833988],"type":"Point"}
}