{
  "type": "Feature",
  "properties": {
    "iso:country":"US",
    "sg:address":"1996 Olive Branch Rd",
    "sg:city":"Axtell",
    "sg:classifiers":[
        {
            "category":"Organizations",
            "subcategory":"Religious Organization",
            "type":"Services"
        }
    ],
    "sg:phone":"+1 254 822 1950",
    "sg:postcode":"76624",
    "sg:province":"TX",
    "sg:tags":[
        "church"
    ],
    "wof:name":"Olive Branch Baptist Church",
    "wof:placetype":"venue"
},
  "geometry": {"coordinates":[-96.989819,31.702448],"type":"Point"}
}