{
  "type": "Feature",
  "properties": {
    "iso:country":"US",
    "sg:address":"911 W Anderson Ln",
    "sg:city":"Austin",
    "sg:classifiers":[
        {
            "category":"Communications",
            "subcategory":"Television Station",
            "type":"Services"
        }
    ],
    "sg:phone":"+1 512 329 0514",
    "sg:postcode":"78757",
    "sg:province":"TX",
    "sg:tags":[
        "broadcast",
        "representative"
    ],
    "sg:website":"http://www.aztecamex.com",
    "wof:name":"Azteca America",
    "wof:placetype":"venue"
},
  "geometry": {"coordinates":[-97.714653,30.34841],"type":"Point"}
}