{
  "type": "Feature",
  "properties": {
    "iso:country":"US",
    "sg:address":"210 Dwire Dr",
    "sg:city":"La Porte",
    "sg:classifiers":[
        {
            "category":"Retail",
            "subcategory":"Laundry & Dry Cleaning",
            "type":"Services"
        }
    ],
    "sg:phone":"+1 281 470 1237",
    "sg:postcode":"77571",
    "sg:province":"TX",
    "wof:name":"Extensive Carpet Care",
    "wof:placetype":"venue"
},
  "geometry": {"coordinates":[-95.01370900000001,29.625397],"type":"Point"}
}