{
  "type": "Feature",
  "properties": {
    "iso:country":"US",
    "sg:address":"17194 Preston Rd",
    "sg:city":"Dallas",
    "sg:classifiers":[
        {
            "category":"Professional",
            "type":"Services"
        }
    ],
    "sg:phone":"+1 214 264 3482",
    "sg:postcode":"75248",
    "sg:province":"TX",
    "sg:tags":[
        "reseller",
        "communication",
        "system",
        "value"
    ],
    "wof:name":"Ip Telecommnet",
    "wof:placetype":"venue"
},
  "geometry": {"coordinates":[-96.80433600000001,32.983491],"type":"Point"}
}