{
  "type": "Feature",
  "properties": {
    "iso:country":"US",
    "sg:address":"11758 Quailbrook",
    "sg:city":"San Antonio",
    "sg:classifiers":[
        {
            "category":"Professional",
            "subcategory":"Business Services",
            "type":"Services"
        }
    ],
    "sg:phone":"+1 210 679 8158",
    "sg:postcode":"78253",
    "sg:province":"TX",
    "wof:name":"Business Trouble Shooting Svcs",
    "wof:placetype":"venue"
},
  "geometry": {"coordinates":[-98.722731,29.439034],"type":"Point"}
}