{
  "type": "Feature",
  "properties": {
    "iso:country":"US",
    "sg:address":"2720 Manor Way",
    "sg:city":"Dallas",
    "sg:classifiers":[
        {
            "category":"Wholesale",
            "subcategory":"Apparel",
            "type":"Manufacturing & Wholesale Goods"
        },
        {
            "category":"Manufacturing",
            "subcategory":"Printing",
            "type":"Manufacturing & Wholesale Goods"
        }
    ],
    "sg:phone":"+1 214 350 2440",
    "sg:postcode":"75235",
    "sg:province":"TX",
    "sg:tags":[
        "screen",
        "uniform"
    ],
    "sg:website":"www.leonardsloan.com",
    "wof:name":"Leonard Sloan & Associates Inc",
    "wof:placetype":"venue"
},
  "geometry": {"coordinates":[-96.840261,32.826557],"type":"Point"}
}