{
  "type": "Feature",
  "properties": {
    "iso:country":"US",
    "sg:address":"9203 North Fwy",
    "sg:city":"Houston",
    "sg:classifiers":[
        {
            "category":"Retail",
            "subcategory":"Auto Rental",
            "type":"Services"
        }
    ],
    "sg:phone":"+1 281 760 3253",
    "sg:postcode":"77037",
    "sg:province":"TX",
    "sg:tags":[
        "car"
    ],
    "wof:name":"Enterprise Rent-A-Car",
    "wof:placetype":"venue"
},
  "geometry": {"coordinates":[-95.41269699999999,29.8941],"type":"Point"}
}