{
  "type": "Feature",
  "properties": {
    "iso:country":"US",
    "sg:address":"4907 Blanco Rd",
    "sg:city":"San Antonio",
    "sg:classifiers":[
        {
            "category":"Retail",
            "subcategory":"Auto Repair",
            "type":"Services"
        }
    ],
    "sg:phone":"+1 210 344 3473",
    "sg:postcode":"78212",
    "sg:province":"TX",
    "sg:tags":[
        "body",
        "automobile",
        "painting"
    ],
    "wof:name":"Caliber Collision Ctr",
    "wof:placetype":"venue"
},
  "geometry": {"coordinates":[-98.50789399999999,29.493724],"type":"Point"}
}