{
  "type": "Feature",
  "properties": {
    "iso:country":"US",
    "sg:address":"8921 Railwood Dr",
    "sg:city":"Houston",
    "sg:classifiers":[
        {
            "category":"Building & Trades",
            "subcategory":"Construction",
            "type":"Services"
        }
    ],
    "sg:phone":"+1 713 635 2555",
    "sg:postcode":"77078",
    "sg:province":"TX",
    "sg:tags":[
        "dry wall",
        "contractor"
    ],
    "sg:website":"www.bakerdrywall.com",
    "wof:name":"Baker Drywall",
    "wof:placetype":"venue"
},
  "geometry": {"coordinates":[-95.260312,29.825864],"type":"Point"}
}