{
  "type": "Feature",
  "properties": {
    "iso:country":"US",
    "sg:address":"208 W Main St",
    "sg:city":"Post",
    "sg:classifiers":[
        {
            "category":"Government",
            "subcategory":"Office",
            "type":"Public Place"
        }
    ],
    "sg:phone":"+1 806 495 2801",
    "sg:postcode":"79356",
    "sg:province":"TX",
    "sg:tags":[
        "federal"
    ],
    "wof:name":"US Consolidated Farm Svc Agcy",
    "wof:placetype":"venue"
},
  "geometry": {"coordinates":[-101.38076700000001,33.191051],"type":"Point"}
}