{
  "type": "Feature",
  "properties": {
    "iso:country":"US",
    "sg:address":"10251 Carolina Oaks Dr",
    "sg:city":"Dallas",
    "sg:classifiers":[
        {
            "category":"Home & Garden",
            "subcategory":"Building Materials",
            "type":"Retail Goods"
        },
        {
            "category":"Building & Trades",
            "subcategory":"Construction",
            "type":"Services"
        },
        {
            "category":"Home & Garden",
            "subcategory":"Carpets & Floor Coverings",
            "type":"Retail Goods"
        }
    ],
    "sg:phone":"+1 214 605 5708",
    "sg:postcode":"75227",
    "sg:province":"TX",
    "sg:tags":[
        "flooring",
        "deck",
        "builder",
        "contractor",
        "concrete",
        "staining",
        "pool",
        "swimming"
    ],
    "sg:website":"http://unitedfamilydecks.com",
    "wof:name":"United Family Decks",
    "wof:placetype":"venue"
},
  "geometry": {"coordinates":[-96.64662199999999,32.752696],"type":"Point"}
}