{
  "type": "Feature",
  "properties": {
    "iso:country":"US",
    "sg:address":"667 Woodland Way",
    "sg:city":"Rockwall",
    "sg:classifiers":[
        {
            "category":"Building & Trades",
            "subcategory":"Landscaping Services",
            "type":"Services"
        }
    ],
    "sg:phone":"+1 972 771 7245",
    "sg:postcode":"75087",
    "sg:province":"TX",
    "sg:tags":[
        "landscape",
        "contractor"
    ],
    "wof:name":"Earth Art Inc",
    "wof:placetype":"venue"
},
  "geometry": {"coordinates":[-96.470144,32.90393],"type":"Point"}
}