{
  "type": "Feature",
  "properties": {
    "iso:country":"US",
    "sg:address":"14519 Texarkana St",
    "sg:city":"Houston",
    "sg:classifiers":[
        {
            "category":"Autos & Motor Vehicles",
            "subcategory":"Automobile Sales",
            "type":"Retail Goods"
        }
    ],
    "sg:phone":"+1 713 330 0004",
    "sg:postcode":"77015",
    "sg:province":"TX",
    "sg:tags":[
        "operator",
        "used",
        "local",
        "trucking"
    ],
    "wof:name":"A Tex Professional Movers Inc",
    "wof:placetype":"venue"
},
  "geometry": {"coordinates":[-95.163639,29.785455],"type":"Point"}
}