{
  "type": "Feature",
  "properties": {
    "iso:country":"US",
    "sg:address":"1406 E Lantrip St",
    "sg:city":"Kilgore",
    "sg:classifiers":[
        {
            "category":"Building & Trades",
            "subcategory":"Landscaping Services",
            "type":"Services"
        }
    ],
    "sg:phone":"+1 903 984 4959",
    "sg:postcode":"75662",
    "sg:province":"TX",
    "sg:tags":[
        "landscape",
        "contractor"
    ],
    "wof:name":"Andrews Lawn Svc",
    "wof:placetype":"venue"
},
  "geometry": {"coordinates":[-94.862921,32.384383],"type":"Point"}
}