{
  "type": "Feature",
  "properties": {
    "iso:country":"US",
    "sg:address":"120 Cardinal St",
    "sg:city":"Lake Jackson",
    "sg:classifiers":[
        {
            "category":"Arts & Performance",
            "subcategory":"Theater",
            "type":"Entertainment"
        }
    ],
    "sg:phone":"+1 979 297 7903",
    "sg:postcode":"77566",
    "sg:province":"TX",
    "sg:tags":[
        "group"
    ],
    "wof:name":"Stovall Music Inc",
    "wof:placetype":"venue"
},
  "geometry": {"coordinates":[-95.42448899999999,29.046107],"type":"Point"}
}