{
  "type": "Feature",
  "properties": {
    "iso:country":"US",
    "sg:address":"7526 Eastern Ave",
    "sg:city":"Dallas",
    "sg:classifiers":[
        {
            "category":"Professional",
            "subcategory":"Computer Services",
            "type":"Services"
        }
    ],
    "sg:phone":"+1 214 350 0410",
    "sg:postcode":"75209",
    "sg:province":"TX",
    "sg:tags":[
        "website",
        "design"
    ],
    "wof:name":"2xcreations",
    "wof:placetype":"venue"
},
  "geometry": {"coordinates":[-96.81423100000001,32.848112],"type":"Point"}
}