{
  "type": "Feature",
  "properties": {
    "iso:country":"US",
    "sg:address":"1610 S Cherry Ln",
    "sg:city":"Fort Worth",
    "sg:classifiers":[
        {
            "category":"Personal",
            "subcategory":"Beauty Salon",
            "type":"Services"
        }
    ],
    "sg:phone":"+1 817 246 6904",
    "sg:postcode":"76108",
    "sg:province":"TX",
    "sg:tags":[
        "hair",
        "center",
        "family",
        "care"
    ],
    "wof:name":"Pro-Cuts",
    "wof:placetype":"venue"
},
  "geometry": {"coordinates":[-97.45181100000001,32.743818],"type":"Point"}
}