{
  "type": "Feature",
  "properties": {
    "iso:country":"US",
    "sg:address":"1010 Decker Dr",
    "sg:city":"Baytown",
    "sg:classifiers":[
        {
            "category":"Wholesale",
            "subcategory":"Medical Equipment & Supplies",
            "type":"Manufacturing & Wholesale Goods"
        },
        {
            "category":"Shopping",
            "subcategory":"Pharmacy",
            "type":"Retail Goods"
        }
    ],
    "sg:phone":"+1 281 422 6191",
    "sg:postcode":"77520",
    "sg:province":"TX",
    "sg:tags":[
        "home",
        "health",
        "care"
    ],
    "wof:name":"Manuel Perez",
    "wof:placetype":"venue"
},
  "geometry": {"coordinates":[-94.978302,29.737225],"type":"Point"}
}