{
  "type": "Feature",
  "properties": {
    "iso:country":"US",
    "sg:address":"804 W Abram St",
    "sg:city":"Arlington",
    "sg:classifiers":[
        {
            "category":"Personal",
            "subcategory":"Beauty Salon",
            "type":"Services"
        }
    ],
    "sg:phone":"+1 817 274 8844",
    "sg:postcode":"76013",
    "sg:province":"TX",
    "sg:tags":[
        "shop"
    ],
    "wof:name":"Donna Folta Skin Care",
    "wof:placetype":"venue"
},
  "geometry": {"coordinates":[-97.118146,32.735708],"type":"Point"}
}