{
  "type": "Feature",
  "properties": {
    "iso:country":"US",
    "sg:address":"2041 S Wheeler St",
    "sg:city":"Jasper",
    "sg:classifiers":[
        {
            "category":"Health Services",
            "subcategory":"Doctor",
            "type":"Services"
        }
    ],
    "sg:phone":"+1 409 384 8171",
    "sg:postcode":"75951",
    "sg:province":"TX",
    "sg:tags":[
        "medicine",
        "physician",
        "practice",
        "surgeons",
        "family"
    ],
    "wof:name":"Jasper Area Family Pediatric And Maternity Clinic, Pllc",
    "wof:placetype":"venue"
},
  "geometry": {"coordinates":[-93.992878,30.896037],"type":"Point"}
}