{
  "type": "Feature",
  "properties": {
    "iso:country":"US",
    "sg:address":"1353 Milam Ave",
    "sg:city":"Brownsville",
    "sg:classifiers":[
        {
            "category":"Wholesale",
            "subcategory":"Machinery & Supplies",
            "type":"Manufacturing & Wholesale Goods"
        },
        {
            "category":"Wholesale",
            "subcategory":"Electrical",
            "type":"Manufacturing & Wholesale Goods"
        }
    ],
    "sg:phone":"+1 956 831 8201",
    "sg:postcode":"78521",
    "sg:province":"TX",
    "sg:tags":[
        "equipment",
        "industrial",
        "electric",
        "motor"
    ],
    "wof:name":"A & H Enterprises Inc",
    "wof:placetype":"venue"
},
  "geometry": {"coordinates":[-97.44490999999999,25.930455],"type":"Point"}
}