{
  "type": "Feature",
  "properties": {
    "iso:country":"US",
    "sg:address":"3421 Ruby Red Dr",
    "sg:city":"Austin",
    "sg:classifiers":[
        {
            "category":"Professional",
            "subcategory":"Business Services",
            "type":"Services"
        }
    ],
    "sg:phone":"+1 512 828 5220",
    "sg:postcode":"78728",
    "sg:province":"TX",
    "wof:name":"Liquid Systems LLC",
    "wof:placetype":"venue"
},
  "geometry": {"coordinates":[-97.68294899999999,30.459329],"type":"Point"}
}