{
  "type": "Feature",
  "properties": {
    "iso:country":"US",
    "sg:address":"2316 Loon Lake Rd",
    "sg:city":"Denton",
    "sg:classifiers":[
        {
            "category":"Professional",
            "subcategory":"Management & Consulting",
            "type":"Services"
        }
    ],
    "sg:phone":"+1 940 898 1916",
    "sg:postcode":"76210",
    "sg:province":"TX",
    "sg:tags":[
        "business"
    ],
    "wof:name":"Great Prairie Business Cons",
    "wof:placetype":"venue"
},
  "geometry": {"coordinates":[-97.103601,33.174263],"type":"Point"}
}