{
  "type": "Feature",
  "properties": {
    "iso:country":"US",
    "sg:address":"30215 Bramblevine Dr",
    "sg:city":"Magnolia",
    "sg:classifiers":[
        {
            "category":"Restaurant",
            "type":"Food & Drink"
        }
    ],
    "sg:phone":"+1 281 252 6600",
    "sg:postcode":"77355",
    "sg:province":"TX",
    "sg:tags":[
        "eating"
    ],
    "wof:name":"It Doesnt Take A Therapist",
    "wof:placetype":"venue"
},
  "geometry": {"coordinates":[-95.78184899999999,30.136013],"type":"Point"}
}