{
  "type": "Feature",
  "properties": {
    "iso:country":"US",
    "sg:address":"4435 Mansion",
    "sg:city":"Von Ormy",
    "sg:classifiers":[
        {
            "category":"Building & Trades",
            "subcategory":"Construction",
            "type":"Services"
        }
    ],
    "sg:phone":"+1 210 624 2632",
    "sg:postcode":"78073",
    "sg:province":"TX",
    "sg:tags":[
        "contractor"
    ],
    "wof:name":"Brown House Moving",
    "wof:placetype":"venue"
},
  "geometry": {"coordinates":[-98.59219299999999,29.191561],"type":"Point"}
}