{
  "type": "Feature",
  "properties": {
    "iso:country":"US",
    "sg:address":"7059 Bandera Rd",
    "sg:city":"San Antonio",
    "sg:classifiers":[
        {
            "category":"Health Services",
            "subcategory":"Chiropractor",
            "type":"Services"
        }
    ],
    "sg:phone":"+1 210 684 3200",
    "sg:postcode":"78238",
    "sg:province":"TX",
    "wof:name":"C R White DC",
    "wof:placetype":"venue"
},
  "geometry": {"coordinates":[-98.62504300000001,29.501186],"type":"Point"}
}