{
  "type": "Feature",
  "properties": {
    "iso:country":"US",
    "sg:address":"100 S Main St",
    "sg:city":"Floydada",
    "sg:classifiers":[
        {
            "category":"Social Services",
            "type":"Services"
        }
    ],
    "sg:phone":"+1 806 983 2584",
    "sg:postcode":"79235",
    "sg:province":"TX",
    "wof:name":"Floydada Outpatient Clinic",
    "wof:placetype":"venue"
},
  "geometry": {"coordinates":[-101.33480900000001,33.985557],"type":"Point"}
}