{
  "type": "Feature",
  "properties": {
    "iso:country":"US",
    "sg:address":"240 Wise Ave",
    "sg:city":"Orange Grove",
    "sg:classifiers":[
        {
            "category":"Wholesale",
            "subcategory":"Non-durable Goods",
            "type":"Manufacturing & Wholesale Goods"
        }
    ],
    "sg:phone":"+1 361 384 0845",
    "sg:postcode":"78372",
    "sg:province":"TX",
    "wof:name":"Tres Rosales Distribution",
    "wof:placetype":"venue"
},
  "geometry": {"coordinates":[-97.937442,27.966966],"type":"Point"}
}