{
  "type": "Feature",
  "properties": {
    "iso:country":"US",
    "sg:address":"5250 Kent Dr",
    "sg:city":"Pasadena",
    "sg:classifiers":[
        {
            "category":"Professional",
            "subcategory":"Business Services",
            "type":"Services"
        }
    ],
    "sg:phone":"+1 281 998 9568",
    "sg:postcode":"77505",
    "sg:province":"TX",
    "wof:name":"Ed Co Enterprises",
    "wof:placetype":"venue"
},
  "geometry": {"coordinates":[-95.161103,29.653421],"type":"Point"}
}