{
  "type": "Feature",
  "properties": {
    "iso:country":"US",
    "sg:address":"2644 Old Port Isabel Rd",
    "sg:city":"Brownsville",
    "sg:classifiers":[
        {
            "category":"Autos & Motor Vehicles",
            "subcategory":"Automobile Sales",
            "type":"Retail Goods"
        }
    ],
    "sg:phone":"+1 956 546 3673",
    "sg:postcode":"78526",
    "sg:province":"TX",
    "sg:tags":[
        "equipment",
        "wrecker"
    ],
    "wof:name":"Mario's Wrecker Svc",
    "wof:placetype":"venue"
},
  "geometry": {"coordinates":[-97.460854,25.956579],"type":"Point"}
}