{
  "type": "Feature",
  "properties": {
    "iso:country":"US",
    "sg:address":"14180 Dallas Pkwy Ste 101",
    "sg:city":"Dallas",
    "sg:classifiers":[
        {
            "category":"Food & Beverages",
            "subcategory":"Bakery",
            "type":"Retail Goods"
        }
    ],
    "sg:phone":"+1 972 233 1938",
    "sg:postcode":"75254",
    "sg:province":"TX",
    "sg:tags":[
        "sandwich"
    ],
    "wof:name":"Pacific Center Sandwich Shop",
    "wof:placetype":"venue"
},
  "geometry": {"coordinates":[-96.803596,32.944],"type":"Point"}
}