{
  "type": "Feature",
  "properties": {
    "iso:country":"US",
    "sg:address":"115 de Boll St",
    "sg:city":"Houston",
    "sg:classifiers":[
        {
            "category":"Professional",
            "subcategory":"Secretarial Services",
            "type":"Services"
        }
    ],
    "sg:phone":"+1 713 694 8377",
    "sg:postcode":"77022",
    "sg:province":"TX",
    "sg:tags":[
        "reporting",
        "court"
    ],
    "wof:name":"Chumley's Legal Video Svc",
    "wof:placetype":"venue"
},
  "geometry": {"coordinates":[-95.374627,29.842674],"type":"Point"}
}