{
  "type": "Feature",
  "properties": {
    "iso:country":"US",
    "sg:address":"11121 Bauman Rd",
    "sg:city":"Houston",
    "sg:classifiers":[
        {
            "category":"Autos & Motor Vehicles",
            "subcategory":"Auto Supplies",
            "type":"Retail Goods"
        }
    ],
    "sg:phone":"+1 713 694 6942",
    "sg:postcode":"77076",
    "sg:province":"TX",
    "sg:tags":[
        "tire"
    ],
    "wof:name":"El Mante Tire Shop",
    "wof:placetype":"venue"
},
  "geometry": {"coordinates":[-95.372238,29.86372],"type":"Point"}
}