{
  "type": "Feature",
  "properties": {
    "iso:country":"US",
    "sg:address":"200 Travertine Ln",
    "sg:city":"San Antonio",
    "sg:classifiers":[
        {
            "category":"Professional",
            "type":"Services"
        }
    ],
    "sg:phone":"+1 210 340 1045",
    "sg:postcode":"78213",
    "sg:province":"TX",
    "wof:name":"Intellihome Inc",
    "wof:placetype":"venue"
},
  "geometry": {"coordinates":[-98.520117,29.513237],"type":"Point"}
}