{
  "type": "Feature",
  "properties": {
    "iso:country":"US",
    "sg:address":"1290 River Rd",
    "sg:city":"New Braunfels",
    "sg:classifiers":[
        {
            "category":"Travel",
            "subcategory":"Campground",
            "type":"Entertainment"
        }
    ],
    "sg:phone":"+1 830 625 1766",
    "sg:postcode":"78130",
    "sg:province":"TX",
    "sg:tags":[
        "trailer"
    ],
    "wof:name":"Jerry's Too",
    "wof:placetype":"venue"
},
  "geometry": {"coordinates":[-98.12508200000001,29.727277],"type":"Point"}
}