{
  "type": "Feature",
  "properties": {
    "iso:country":"US",
    "sg:address":"13939 Northwest Fwy",
    "sg:city":"Houston",
    "sg:classifiers":[
        {
            "category":"Professional",
            "subcategory":"Lawyer & Legal Services",
            "type":"Services"
        }
    ],
    "sg:phone":"+1 713 863 0611",
    "sg:postcode":"77040",
    "sg:province":"TX",
    "wof:name":"Markantonis Frank Atty",
    "wof:placetype":"venue"
},
  "geometry": {"coordinates":[-95.51647699999999,29.854249],"type":"Point"}
}