{
  "type": "Feature",
  "properties": {
    "iso:country":"US",
    "sg:address":"1811 Mayfield Ave",
    "sg:city":"Garland",
    "sg:classifiers":[
        {
            "category":"Education",
            "subcategory":"School",
            "type":"Public Place"
        }
    ],
    "sg:phone":"+1 972 494 8342",
    "sg:postcode":"75041",
    "sg:province":"TX",
    "sg:tags":[
        "stationery"
    ],
    "wof:name":"South Gate Elem",
    "wof:placetype":"venue"
},
  "geometry": {"coordinates":[-96.653886,32.866711],"type":"Point"}
}