{
  "type": "Feature",
  "properties": {
    "iso:country":"US",
    "sg:address":"203 E Cedar St",
    "sg:city":"Angleton",
    "sg:classifiers":[
        {
            "category":"Professional",
            "subcategory":"Lawyer & Legal Services",
            "type":"Services"
        }
    ],
    "sg:phone":"+1 979 849 4387",
    "sg:postcode":"77515",
    "sg:province":"TX",
    "wof:name":"Terry & Terry",
    "wof:placetype":"venue"
},
  "geometry": {"coordinates":[-95.42945899999999,29.16973],"type":"Point"}
}