{
  "type": "Feature",
  "properties": {
    "iso:country":"US",
    "sg:address":"2041 San Sebastian Ct",
    "sg:city":"Houston",
    "sg:classifiers":[
        {
            "category":"Professional",
            "type":"Services"
        }
    ],
    "sg:phone":"+1 281 333 9040",
    "sg:postcode":"77058",
    "sg:province":"TX",
    "wof:name":"Phone Nurse Inc",
    "wof:placetype":"venue"
},
  "geometry": {"coordinates":[-95.086077,29.547146],"type":"Point"}
}