{
  "type": "Feature",
  "properties": {
    "iso:country":"US",
    "sg:address":"103 W Palito Blanco Rd",
    "sg:city":"Rio Grande City",
    "sg:classifiers":[
        {
            "category":"Real Estate",
            "subcategory":"Developer",
            "type":"Services"
        }
    ],
    "sg:phone":"+1 956 239 2212",
    "sg:postcode":"78582",
    "sg:province":"TX",
    "wof:name":"Adam Gardens Subdivision",
    "wof:placetype":"venue"
},
  "geometry": {"coordinates":[-98.84160199999999,26.37843],"type":"Point"}
}