{
  "type": "Feature",
  "properties": {
    "iso:country":"US",
    "sg:address":"4337 Lindbergh Dr",
    "sg:city":"Addison",
    "sg:classifiers":[
        {
            "category":"Banks & Credit Unions",
            "subcategory":"Financial Services",
            "type":"Services"
        }
    ],
    "sg:phone":"+1 972 985 0000",
    "sg:postcode":"75001",
    "sg:province":"TX",
    "sg:tags":[
        "broker",
        "mortgage"
    ],
    "wof:name":"Bank Source Mortgage",
    "wof:placetype":"venue"
},
  "geometry": {"coordinates":[-96.832379,32.957877],"type":"Point"}
}