{
  "type": "Feature",
  "properties": {
    "iso:country":"US",
    "sg:address":"5350 Pt Lavista",
    "sg:city":"Malakoff",
    "sg:classifiers":[
        {
            "category":"Home & Garden",
            "subcategory":"Mobile Homes",
            "type":"Retail Goods"
        }
    ],
    "sg:phone":"+1 903 489 3257",
    "sg:postcode":"75148",
    "sg:province":"TX",
    "wof:name":"Dmar Home Sales Inc",
    "wof:placetype":"venue"
},
  "geometry": {"coordinates":[-96.03945299999999,32.223521],"type":"Point"}
}