{
  "type": "Feature",
  "properties": {
    "iso:country":"US",
    "sg:address":"986 Chapparal Rd",
    "sg:city":"Whitesboro",
    "sg:classifiers":[
        {
            "category":"Farming",
            "subcategory":"Livestock Farm",
            "type":"Manufacturing & Wholesale Goods"
        }
    ],
    "sg:phone":"+1 903 564 7070",
    "sg:postcode":"76273",
    "sg:province":"TX",
    "sg:tags":[
        "horse",
        "quarter",
        "raising"
    ],
    "wof:name":"Russ Smith Quarter Horses",
    "wof:placetype":"venue"
},
  "geometry": {"coordinates":[-96.94050799999999,33.605599],"type":"Point"}
}