{
  "type": "Feature",
  "properties": {
    "iso:country":"US",
    "sg:address":"1501 Newland Dr",
    "sg:city":"Gainesville",
    "sg:classifiers":[
        {
            "category":"Real Estate",
            "subcategory":"Real Estate Operator",
            "type":"Services"
        }
    ],
    "sg:phone":"+1 940 665 0501",
    "sg:postcode":"76240",
    "sg:province":"TX",
    "sg:tags":[
        "building",
        "apartment"
    ],
    "wof:name":"Willowick Apartments",
    "wof:placetype":"venue"
},
  "geometry": {"coordinates":[-97.12285,33.643858],"type":"Point"}
}