{
  "type": "Feature",
  "properties": {
    "iso:country":"US",
    "sg:address":"918 Fabulous Dr",
    "sg:city":"San Antonio",
    "sg:classifiers":[
        {
            "category":"Organizations",
            "subcategory":"Religious Organization",
            "type":"Services"
        }
    ],
    "sg:phone":"+1 210 341 1284",
    "sg:postcode":"78213",
    "sg:province":"TX",
    "wof:name":"Cross Health Ministries",
    "wof:placetype":"venue"
},
  "geometry": {"coordinates":[-98.50946,29.54209],"type":"Point"}
}