{
  "type": "Feature",
  "properties": {
    "iso:country":"US",
    "sg:address":"1504 Weiler Blvd",
    "sg:city":"Fort Worth",
    "sg:classifiers":[
        {
            "category":"Education",
            "subcategory":"Special Training",
            "type":"Public Place"
        }
    ],
    "sg:phone":"+1 817 451 1830",
    "sg:postcode":"76112",
    "sg:province":"TX",
    "wof:name":"Joes Shows",
    "wof:placetype":"venue"
},
  "geometry": {"coordinates":[-97.235032,32.756299],"type":"Point"}
}