{
  "type": "Feature",
  "properties": {
    "iso:country":"US",
    "sg:address":"413 9th St",
    "sg:city":"San Antonio",
    "sg:classifiers":[
        {
            "category":"Retail",
            "subcategory":"Auto Repair",
            "type":"Services"
        }
    ],
    "sg:phone":"+1 210 224 9099",
    "sg:postcode":"78215",
    "sg:province":"TX",
    "sg:tags":[
        "body",
        "automotive",
        "painting",
        "automobile"
    ],
    "wof:name":"Strom's Paint & Body Shop Inc",
    "wof:placetype":"venue"
},
  "geometry": {"coordinates":[-98.47984599999999,29.431928],"type":"Point"}
}