{
  "type": "Feature",
  "properties": {
    "iso:country":"US",
    "sg:address":"2937 Dyer St",
    "sg:city":"Dallas",
    "sg:classifiers":[
        {
            "category":"Professional",
            "type":"Services"
        }
    ],
    "sg:phone":"+1 214 891 0446",
    "sg:postcode":"75205",
    "sg:province":"TX",
    "wof:name":"Doak Walker Foundation",
    "wof:placetype":"venue"
},
  "geometry": {"coordinates":[-96.77871,32.843084],"type":"Point"}
}