{
  "type": "Feature",
  "properties": {
    "iso:country":"US",
    "sg:address":"1301 FM 407",
    "sg:city":"Lewisville",
    "sg:classifiers":[
        {
            "category":"Professional",
            "subcategory":"Accounting & Tax Preparation",
            "type":"Services"
        }
    ],
    "sg:phone":"+1 972 317 3555",
    "sg:postcode":"75077",
    "sg:province":"TX",
    "sg:tags":[
        "return",
        "filing"
    ],
    "wof:name":"Jackson Hewitt Tax Svc",
    "wof:placetype":"venue"
},
  "geometry": {"coordinates":[-97.031559,33.071368],"type":"Point"}
}