{
  "type": "Feature",
  "properties": {
    "iso:country":"US",
    "sg:address":"20811 Dawn Dr",
    "sg:city":"Lago Vista",
    "sg:classifiers":[
        {
            "category":"Manufacturing",
            "subcategory":"Printing",
            "type":"Manufacturing & Wholesale Goods"
        }
    ],
    "sg:phone":"+1 512 267 4449",
    "sg:postcode":"78645",
    "sg:province":"TX",
    "sg:tags":[
        "newspaper"
    ],
    "wof:name":"North Lake Travis Log",
    "wof:placetype":"venue"
},
  "geometry": {"coordinates":[-97.9909,30.455683],"type":"Point"}
}