{
  "type": "Feature",
  "properties": {
    "iso:country":"US",
    "sg:address":"703 Monarch Ave.",
    "sg:city":"Cedar Park",
    "sg:classifiers":[
        {
            "category":"Building & Trades",
            "subcategory":"Construction",
            "type":"Services"
        }
    ],
    "sg:phone":"+1 512 380 1501",
    "sg:postcode":"78613",
    "sg:province":"TX",
    "sg:tags":[
        "contractor"
    ],
    "sg:website":"raymondjames.fx3tech.com",
    "wof:name":"Raymond James, Residential Construction Svcs.",
    "wof:placetype":"venue"
},
  "geometry": {"coordinates":[-97.838855,30.512937],"type":"Point"}
}