{
  "type": "Feature",
  "properties": {
    "iso:country":"US",
    "sg:address":"749 Oriole St",
    "sg:city":"Corpus Christi",
    "sg:classifiers":[
        {
            "category":"Professional",
            "type":"Services"
        }
    ],
    "sg:phone":"+1 361 939 7308",
    "sg:postcode":"78418",
    "sg:province":"TX",
    "wof:name":"Ralph S Gomez",
    "wof:placetype":"venue"
},
  "geometry": {"coordinates":[-97.297304,27.682092],"type":"Point"}
}