{
  "type": "Feature",
  "properties": {
    "iso:country":"US",
    "sg:address":"6221 N Lamar Blvd",
    "sg:city":"Austin",
    "sg:classifiers":[
        {
            "category":"Home & Garden",
            "subcategory":"Home Furnishings",
            "type":"Retail Goods"
        }
    ],
    "sg:phone":"+1 512 459 6561",
    "sg:postcode":"78752",
    "sg:province":"TX",
    "sg:tags":[
        "venetian",
        "blind",
        "window",
        "shades",
        "drapery"
    ],
    "wof:name":"A B C Blind & Drapery Co",
    "wof:placetype":"venue"
},
  "geometry": {"coordinates":[-97.722829,30.331349],"type":"Point"}
}