{
  "type": "Feature",
  "properties": {
    "iso:country":"US",
    "sg:address":"1202 Pulliam St",
    "sg:city":"San Angelo",
    "sg:classifiers":[
        {
            "category":"Retail",
            "subcategory":"Auto Repair",
            "type":"Services"
        }
    ],
    "sg:phone":"+1 325 655 6614",
    "sg:postcode":"76903",
    "sg:province":"TX",
    "sg:tags":[
        "transmission",
        "automotive"
    ],
    "wof:name":"Grays Transmission",
    "wof:placetype":"venue"
},
  "geometry": {"coordinates":[-100.41741500000001,31.470809],"type":"Point"}
}