{
  "type": "Feature",
  "properties": {
    "iso:country":"US",
    "sg:address":"519 N Walnut St",
    "sg:city":"Sherman",
    "sg:classifiers":[
        {
            "category":"Real Estate",
            "subcategory":"Real Estate Agent",
            "type":"Services"
        }
    ],
    "sg:phone":"+1 903 868 1511",
    "sg:postcode":"75090",
    "sg:province":"TX",
    "wof:name":"Sher-Den Realty Inc",
    "wof:placetype":"venue"
},
  "geometry": {"coordinates":[-96.609268,33.640771],"type":"Point"}
}