{
  "type": "Feature",
  "properties": {
    "iso:country":"US",
    "sg:address":"1100 Venture Ct",
    "sg:city":"Carrollton",
    "sg:classifiers":[
        {
            "category":"Manufacturing",
            "subcategory":"Paper Products",
            "type":"Manufacturing & Wholesale Goods"
        }
    ],
    "sg:phone":"+1 972 478 6400",
    "sg:postcode":"75006",
    "sg:province":"TX",
    "sg:tags":[
        "printing",
        "commercial",
        "mfg"
    ],
    "wof:name":"Diversco Cstm Label Converter",
    "wof:placetype":"venue"
},
  "geometry": {"coordinates":[-96.858752,32.955927],"type":"Point"}
}