{
  "type": "Feature",
  "properties": {
    "iso:country":"US",
    "sg:address":"6365 US Hwy 59 S",
    "sg:city":"Marshall",
    "sg:classifiers":[
        {
            "category":"Mining & Drilling",
            "type":"Manufacturing & Wholesale Goods"
        }
    ],
    "sg:phone":"+1 903 935 9200",
    "sg:postcode":"75672",
    "sg:province":"TX",
    "sg:tags":[
        "field",
        "oil"
    ],
    "wof:name":"Mosley Wireline Service LLC",
    "wof:placetype":"venue"
},
  "geometry": {"coordinates":[-94.359442,32.482346],"type":"Point"}
}