{
  "type": "Feature",
  "properties": {
    "iso:country":"US",
    "sg:address":"1106 State Hwy 16",
    "sg:city":"Graham",
    "sg:classifiers":[
        {
            "category":"Home & Garden",
            "subcategory":"Household Appliances",
            "type":"Retail Goods"
        }
    ],
    "sg:phone":"+1 940 549 8877",
    "sg:postcode":"76450",
    "sg:province":"TX",
    "wof:name":"Sears Retail",
    "wof:placetype":"venue"
},
  "geometry": {"coordinates":[-98.589705,33.095277],"type":"Point"}
}