{
  "type": "Feature",
  "properties": {
    "iso:country":"US",
    "sg:address":"1005 Baker St",
    "sg:city":"Mc Kinney",
    "sg:classifiers":[
        {
            "category":"Shopping",
            "subcategory":"Used Merchandise",
            "type":"Retail Goods"
        }
    ],
    "sg:phone":"+1 972 544 3592",
    "sg:postcode":"75069",
    "sg:province":"TX",
    "wof:name":"Carriage House Antiques",
    "wof:placetype":"venue"
},
  "geometry": {"coordinates":[-96.627427,33.18822],"type":"Point"}
}