{
  "type": "Feature",
  "properties": {
    "iso:country":"US",
    "sg:address":"3030 Shane Rd",
    "sg:city":"San Antonio",
    "sg:classifiers":[
        {
            "category":"Recreation",
            "type":"Entertainment"
        }
    ],
    "sg:phone":"+1 210 633 2080",
    "sg:postcode":"78223",
    "sg:province":"TX",
    "sg:tags":[
        "range",
        "baseball",
        "batting"
    ],
    "wof:name":"Alamo City Sports Complex",
    "wof:placetype":"venue"
},
  "geometry": {"coordinates":[-98.437174,29.318318],"type":"Point"}
}