{
  "type": "Feature",
  "properties": {
    "iso:country":"US",
    "sg:address":"3900 Singleton Blvd",
    "sg:city":"Dallas",
    "sg:classifiers":[
        {
            "category":"Wholesale",
            "subcategory":"Petroleum",
            "type":"Manufacturing & Wholesale Goods"
        }
    ],
    "sg:phone":"+1 214 631 6193",
    "sg:postcode":"75212",
    "sg:province":"TX",
    "sg:tags":[
        "gasoline-wholesale"
    ],
    "sg:website":"http://www.motivaenterprises.com",
    "wof:name":"Motiva Sales Terminal",
    "wof:placetype":"venue"
},
  "geometry": {"coordinates":[-96.88605200000001,32.778839],"type":"Point"}
}