{
  "type": "Feature",
  "properties": {
    "iso:country":"US",
    "sg:address":"807 Courtland Dr",
    "sg:city":"Mesquite",
    "sg:classifiers":[
        {
            "category":"Manufacturing",
            "subcategory":"Electronics",
            "type":"Manufacturing & Wholesale Goods"
        },
        {
            "category":"Wholesale",
            "subcategory":"Electrical",
            "type":"Manufacturing & Wholesale Goods"
        }
    ],
    "sg:phone":"+1 972 613 9443",
    "sg:postcode":"75150",
    "sg:province":"TX",
    "sg:tags":[
        "sound",
        "equipment",
        "mfg",
        "system",
        "home"
    ],
    "wof:name":"Elite Integrated Solutions Inc",
    "wof:placetype":"venue"
},
  "geometry": {"coordinates":[-96.606679,32.830321],"type":"Point"}
}