{
  "type": "Feature",
  "properties": {
    "iso:country":"US",
    "sg:address":"810 N Date St",
    "sg:city":"Plainview",
    "sg:classifiers":[
        {
            "category":"Autos & Motor Vehicles",
            "subcategory":"Fuel & Gas Station",
            "type":"Retail Goods"
        }
    ],
    "sg:phone":"+1 806 296 6666",
    "sg:postcode":"79072",
    "sg:province":"TX",
    "sg:tags":[
        "oil"
    ],
    "wof:name":"West Texas Gas Inc",
    "wof:placetype":"venue"
},
  "geometry": {"coordinates":[-101.69793300000001,34.189543],"type":"Point"}
}