{
  "type": "Feature",
  "properties": {
    "iso:country":"US",
    "sg:address":"508 Crown Colony Dr",
    "sg:city":"Arlington",
    "sg:classifiers":[
        {
            "category":"Professional",
            "type":"Services"
        }
    ],
    "sg:phone":"+1 817 460 0636",
    "sg:postcode":"76006",
    "sg:province":"TX",
    "wof:name":"Rasmussen Beaux Arts",
    "wof:placetype":"venue"
},
  "geometry": {"coordinates":[-97.106728,32.775982],"type":"Point"}
}