{
  "type": "Feature",
  "properties": {
    "iso:country":"US",
    "sg:address":"4315 James Casey St",
    "sg:city":"Austin",
    "sg:classifiers":[
        {
            "category":"Health Services",
            "subcategory":"Doctor",
            "type":"Services"
        }
    ],
    "sg:phone":"+1 512 460 3403",
    "sg:postcode":"78745",
    "sg:province":"TX",
    "wof:name":"Debehnke Richard MD",
    "wof:placetype":"venue"
},
  "geometry": {"coordinates":[-97.77510100000001,30.2232],"type":"Point"}
}