{
  "type": "Feature",
  "properties": {
    "iso:country":"US",
    "sg:address":"211 Drew St",
    "sg:city":"Houston",
    "sg:classifiers":[
        {
            "category":"Shopping",
            "subcategory":"Used Merchandise",
            "type":"Retail Goods"
        }
    ],
    "sg:phone":"+1 713 807 8667",
    "sg:postcode":"77006",
    "sg:province":"TX",
    "wof:name":"Old Bell Undercover Squeegee",
    "wof:placetype":"venue"
},
  "geometry": {"coordinates":[-95.38106000000001,29.747812],"type":"Point"}
}