{
  "type": "Feature",
  "properties": {
    "iso:country":"US",
    "sg:address":"6615 E Rosedale St",
    "sg:city":"Fort Worth",
    "sg:classifiers":[
        {
            "category":"Building & Trades",
            "subcategory":"Construction",
            "type":"Services"
        }
    ],
    "sg:phone":"+1 817 451 6435",
    "sg:postcode":"76105",
    "sg:province":"TX",
    "sg:tags":[
        "roofing",
        "commercial",
        "metal",
        "sheet"
    ],
    "wof:name":"Zapata Roofing Corporation",
    "wof:placetype":"venue"
},
  "geometry": {"coordinates":[-97.21772300000001,32.730767],"type":"Point"}
}