{
  "type": "Feature",
  "properties": {
    "iso:country":"US",
    "sg:address":"2603 Parvia Ave",
    "sg:city":"Dallas",
    "sg:classifiers":[
        {
            "category":"Manufacturing",
            "subcategory":"Glass & Minerals",
            "type":"Manufacturing & Wholesale Goods"
        }
    ],
    "sg:phone":"+1 214 941 7411",
    "sg:postcode":"75212",
    "sg:province":"TX",
    "sg:tags":[
        "concrete",
        "product",
        "mfg"
    ],
    "wof:name":"Architectural Decorating Svc",
    "wof:placetype":"venue"
},
  "geometry": {"coordinates":[-96.83336799999999,32.776232],"type":"Point"}
}