{
  "type": "Feature",
  "properties": {
    "iso:country":"US",
    "sg:address":"235 Beach St",
    "sg:city":"Port Aransas",
    "sg:classifiers":[
        {
            "category":"Restaurant",
            "type":"Food & Drink"
        }
    ],
    "sg:phone":"+1 361 749 6157",
    "sg:postcode":"78373",
    "sg:province":"TX",
    "sg:tags":[
        "eating"
    ],
    "wof:name":"Seals Bbq",
    "wof:placetype":"venue"
},
  "geometry": {"coordinates":[-97.059285,27.833447],"type":"Point"}
}