{
  "type": "Feature",
  "properties": {
    "iso:country":"US",
    "sg:address":"16945 Northchase Dr",
    "sg:city":"Houston",
    "sg:classifiers":[
        {
            "category":"Banks & Credit Unions",
            "subcategory":"Investment Brokerage",
            "type":"Services"
        }
    ],
    "sg:phone":"+1 281 875 9100",
    "sg:postcode":"77060",
    "sg:province":"TX",
    "sg:tags":[
        "trust"
    ],
    "wof:name":"J R Parten Ranch Trust",
    "wof:placetype":"venue"
},
  "geometry": {"coordinates":[-95.406701,29.948071],"type":"Point"}
}