{
  "type": "Feature",
  "properties": {
    "iso:country":"US",
    "sg:address":"11472 Cude Cemetery Rd",
    "sg:city":"Willis",
    "sg:classifiers":[
        {
            "category":"Autos & Motor Vehicles",
            "subcategory":"Boat Sales",
            "type":"Retail Goods"
        }
    ],
    "sg:phone":"+1 936 890 0676",
    "sg:postcode":"77318",
    "sg:province":"TX",
    "sg:tags":[
        "repair",
        "maintenance"
    ],
    "wof:name":"Lake Conroe Marine",
    "wof:placetype":"venue"
},
  "geometry": {"coordinates":[-95.552126,30.408351],"type":"Point"}
}