{
  "type": "Feature",
  "properties": {
    "iso:country":"US",
    "sg:address":"3435 W Loop 820 S",
    "sg:city":"Fort Worth",
    "sg:classifiers":[
        {
            "category":"Autos & Motor Vehicles",
            "subcategory":"Automobile Sales",
            "type":"Retail Goods"
        }
    ],
    "sg:phone":"+1 817 696 4000",
    "sg:postcode":"76116",
    "sg:province":"TX",
    "sg:tags":[
        "car",
        "dealer"
    ],
    "sg:website":"www.frankkentcars.com",
    "wof:name":"Frank Kent Honda",
    "wof:placetype":"venue"
},
  "geometry": {"coordinates":[-97.47924,32.725083],"type":"Point"}
}