{
  "type": "Feature",
  "properties": {
    "iso:country":"US",
    "sg:address":"4801 Vista Rd",
    "sg:city":"Pasadena",
    "sg:classifiers":[
        {
            "category":"Shopping",
            "subcategory":"Bicycles & Sporting Goods",
            "type":"Retail Goods"
        }
    ],
    "sg:phone":"+1 281 487 4007",
    "sg:postcode":"77505",
    "sg:province":"TX",
    "wof:name":"Pasadena Service Center",
    "wof:placetype":"venue"
},
  "geometry": {"coordinates":[-95.16788699999999,29.658961],"type":"Point"}
}