{
  "type": "Feature",
  "properties": {
    "iso:country":"US",
    "sg:address":"1310 Ranch Rd 620 S",
    "sg:city":"Lakeway",
    "sg:classifiers":[
        {
            "category":"Building & Trades",
            "subcategory":"Construction",
            "type":"Services"
        }
    ],
    "sg:phone":"+1 512 402 9222",
    "sg:postcode":"78734",
    "sg:province":"TX",
    "sg:tags":[
        "home",
        "builder"
    ],
    "wof:name":"Jenkins Custom Homes",
    "wof:placetype":"venue"
},
  "geometry": {"coordinates":[-97.96316899999999,30.351303],"type":"Point"}
}