{
  "type": "Feature",
  "properties": {
    "iso:country":"US",
    "sg:address":"3500 McCann Rd",
    "sg:city":"Longview",
    "sg:classifiers":[
        {
            "category":"Shopping",
            "subcategory":"Clothing, Apparel, & Fashions",
            "type":"Retail Goods"
        }
    ],
    "sg:phone":"+1 903 236 3335",
    "sg:postcode":"75605",
    "sg:province":"TX",
    "sg:tags":[
        "sportswear"
    ],
    "wof:name":"American Eagle Outfitters",
    "wof:placetype":"venue"
},
  "geometry": {"coordinates":[-94.75432499999999,32.538447],"type":"Point"}
}