{
  "type": "Feature",
  "properties": {
    "iso:country":"US",
    "sg:address":"708 Dr Fermin Calderon Blvd",
    "sg:city":"Del Rio",
    "sg:classifiers":[
        {
            "category":"Autos & Motor Vehicles",
            "subcategory":"Automobile Sales",
            "type":"Retail Goods"
        }
    ],
    "sg:phone":"+1 830 768 0735",
    "sg:postcode":"78840",
    "sg:province":"TX",
    "sg:tags":[
        "car",
        "dealer"
    ],
    "wof:name":"Marco Motors",
    "wof:placetype":"venue"
},
  "geometry": {"coordinates":[-100.878422,29.361217],"type":"Point"}
}