{
  "type": "Feature",
  "properties": {
    "iso:country":"US",
    "sg:address":"905 S Bridge St",
    "sg:city":"Victoria",
    "sg:classifiers":[
        {
            "category":"Shopping",
            "type":"Retail Goods"
        }
    ],
    "sg:phone":"+1 361 572 0825",
    "sg:postcode":"77901",
    "sg:province":"TX",
    "sg:tags":[
        "art",
        "gallery",
        "dealer"
    ],
    "wof:name":"Victoria Art League Inc",
    "wof:placetype":"venue"
},
  "geometry": {"coordinates":[-97.010362,28.791748],"type":"Point"}
}