{
  "type": "Feature",
  "properties": {
    "iso:country":"US",
    "sg:address":"603 Greenfield Cove",
    "sg:city":"Pflugerville",
    "sg:classifiers":[
        {
            "category":"Retail",
            "subcategory":"Laundry & Dry Cleaning",
            "type":"Services"
        }
    ],
    "sg:phone":"+1 512 825 3087",
    "sg:postcode":"78660",
    "sg:province":"TX",
    "sg:tags":[
        "building",
        "maintenance"
    ],
    "wof:name":"Superior Crpt Care & Maid Svc",
    "wof:placetype":"venue"
},
  "geometry": {"coordinates":[-97.623794,30.446421],"type":"Point"}
}