{
  "type": "Feature",
  "properties": {
    "iso:country":"US",
    "sg:address":"238 Dinn Dr",
    "sg:city":"San Antonio",
    "sg:classifiers":[
        {
            "category":"Building & Trades",
            "subcategory":"Construction",
            "type":"Services"
        }
    ],
    "sg:phone":"+1 210 650 9948",
    "sg:postcode":"78218",
    "sg:province":"TX",
    "sg:tags":[
        "general",
        "contractor"
    ],
    "wof:name":"Earl P Forbrich Jr Inc",
    "wof:placetype":"venue"
},
  "geometry": {"coordinates":[-98.395467,29.491989],"type":"Point"}
}