{
  "type": "Feature",
  "properties": {
    "iso:country":"US",
    "sg:address":"732 FM 2824",
    "sg:city":"Beeville",
    "sg:classifiers":[
        {
            "category":"Banks & Credit Unions",
            "subcategory":"Bank",
            "type":"Services"
        }
    ],
    "sg:phone":"+1 361 358 4121",
    "sg:postcode":"78102",
    "sg:province":"TX",
    "sg:tags":[
        "financing"
    ],
    "wof:name":"Deere Credit Inc",
    "wof:placetype":"venue"
},
  "geometry": {"coordinates":[-97.78335199999999,28.460824],"type":"Point"}
}