{
  "type": "Feature",
  "properties": {
    "iso:country":"US",
    "sg:address":"1619 Center St",
    "sg:city":"Deer Park",
    "sg:classifiers":[
        {
            "category":"Personal",
            "subcategory":"Beauty Salon",
            "type":"Services"
        }
    ],
    "sg:phone":"+1 281 479 5107",
    "sg:postcode":"77536",
    "sg:province":"TX",
    "sg:tags":[
        "nail"
    ],
    "wof:name":"Carols Nails",
    "wof:placetype":"venue"
},
  "geometry": {"coordinates":[-95.123621,29.697319],"type":"Point"}
}