{
  "type": "Feature",
  "properties": {
    "iso:country":"US",
    "sg:address":"1411 Covewood Dr",
    "sg:city":"Tyler",
    "sg:classifiers":[
        {
            "category":"Professional",
            "subcategory":"Business Services",
            "type":"Services"
        }
    ],
    "sg:phone":"+1 903 561 4421",
    "sg:postcode":"75703",
    "sg:province":"TX",
    "sg:tags":[
        "consultant",
        "coach"
    ],
    "wof:name":"Barclay Kendall Wedding Consul",
    "wof:placetype":"venue"
},
  "geometry": {"coordinates":[-95.286725,32.289618],"type":"Point"}
}