{
  "type": "Feature",
  "properties": {
    "iso:country":"US",
    "sg:address":"3986 W Vickery Blvd",
    "sg:city":"Fort Worth",
    "sg:classifiers":[
        {
            "category":"Building & Trades",
            "subcategory":"Cleaning & Sanitation",
            "type":"Services"
        }
    ],
    "sg:phone":"+1 817 377 0318",
    "sg:postcode":"76107",
    "sg:province":"TX",
    "sg:tags":[
        "maintenance"
    ],
    "wof:name":"Home To Garden",
    "wof:placetype":"venue"
},
  "geometry": {"coordinates":[-97.374807,32.728857],"type":"Point"}
}