{
  "type": "Feature",
  "properties": {
    "iso:country":"US",
    "sg:address":"400 Byrne St",
    "sg:city":"Smithville",
    "sg:classifiers":[
        {
            "category":"Building & Trades",
            "subcategory":"Landscaping Services",
            "type":"Services"
        }
    ],
    "sg:phone":"+1 512 360 2389",
    "sg:postcode":"78957",
    "sg:province":"TX",
    "sg:tags":[
        "lawn",
        "maintenance",
        "grounds"
    ],
    "wof:name":"Cemetery Lawn Svc",
    "wof:placetype":"venue"
},
  "geometry": {"coordinates":[-97.148944,30.006017],"type":"Point"}
}