{
  "type": "Feature",
  "properties": {
    "iso:country":"US",
    "sg:address":"11714 Advance Dr",
    "sg:city":"Houston",
    "sg:classifiers":[
        {
            "category":"Shopping",
            "subcategory":"Catalog Store",
            "type":"Retail Goods"
        }
    ],
    "sg:phone":"+1 281 807 1228",
    "sg:postcode":"77065",
    "sg:province":"TX",
    "sg:tags":[
        "house",
        "mail"
    ],
    "wof:name":"Rkj Enterprises",
    "wof:placetype":"venue"
},
  "geometry": {"coordinates":[-95.597015,29.944712],"type":"Point"}
}