{
  "type": "Feature",
  "properties": {
    "iso:country":"US",
    "sg:address":"12212 Wycliff Ln",
    "sg:city":"Austin",
    "sg:classifiers":[
        {
            "category":"Professional",
            "subcategory":"Computer Services",
            "type":"Services"
        }
    ],
    "sg:phone":"+1 512 835 5827",
    "sg:postcode":"78727",
    "sg:province":"TX",
    "sg:tags":[
        "related"
    ],
    "wof:name":"Future First Technologies",
    "wof:placetype":"venue"
},
  "geometry": {"coordinates":[-97.725775,30.420093],"type":"Point"}
}