{
  "type": "Feature",
  "properties": {
    "iso:country":"US",
    "sg:address":"310 Deerwood Dr",
    "sg:city":"San Marcos",
    "sg:classifiers":[
        {
            "category":"Recreation",
            "type":"Entertainment"
        }
    ],
    "sg:phone":"+1 512 396 1231",
    "sg:postcode":"78666",
    "sg:province":"TX",
    "wof:name":"Johnson Lake Management",
    "wof:placetype":"venue"
},
  "geometry": {"coordinates":[-98.00864,29.829304],"type":"Point"}
}