{
  "type": "Feature",
  "properties": {
    "iso:country":"US",
    "sg:address":"200 Muller Garden Rd",
    "sg:city":"Tyler",
    "sg:classifiers":[
        {
            "category":"Real Estate",
            "subcategory":"Real Estate Operator",
            "type":"Services"
        }
    ],
    "sg:phone":"+1 903 561 0460",
    "sg:postcode":"75703",
    "sg:province":"TX",
    "sg:tags":[
        "apartment"
    ],
    "wof:name":"Arbor Wood Apartments",
    "wof:placetype":"venue"
},
  "geometry": {"coordinates":[-95.30821,32.270207],"type":"Point"}
}