{
  "type": "Feature",
  "properties": {
    "iso:country":"US",
    "sg:address":"23208 Co Rd 460",
    "sg:city":"Mineola",
    "sg:classifiers":[
        {
            "category":"Farming",
            "subcategory":"Livestock Farm",
            "type":"Manufacturing & Wholesale Goods"
        },
        {
            "category":"Local Transit",
            "type":"Transportation"
        }
    ],
    "sg:phone":"+1 903 569 2502",
    "sg:postcode":"75773",
    "sg:province":"TX",
    "sg:tags":[
        "ranch"
    ],
    "wof:name":"Myers Ranch Co Inc",
    "wof:placetype":"venue"
},
  "geometry": {"coordinates":[-95.55774700000001,32.635962],"type":"Point"}
}