{
  "type": "Feature",
  "properties": {
    "iso:country":"US",
    "sg:address":"6484 Provincial Dr",
    "sg:city":"El Paso",
    "sg:classifiers":[
        {
            "category":"Professional",
            "subcategory":"Detective & Security Services",
            "type":"Services"
        }
    ],
    "sg:phone":"+1 915 534 6779",
    "sg:postcode":"79932",
    "sg:province":"TX",
    "sg:tags":[
        "guard"
    ],
    "wof:name":"Robert Torres",
    "wof:placetype":"venue"
},
  "geometry": {"coordinates":[-106.613739,31.88688],"type":"Point"}
}