{
  "type": "Feature",
  "properties": {
    "iso:country":"US",
    "sg:address":"201 S Dewey Ave",
    "sg:city":"Sherman",
    "sg:classifiers":[
        {
            "category":"Food & Beverages",
            "subcategory":"Groceries & Convenience Stores",
            "type":"Retail Goods"
        }
    ],
    "sg:phone":"+1 903 892 9551",
    "sg:postcode":"75090",
    "sg:province":"TX",
    "wof:name":"Sunshine Food",
    "wof:placetype":"venue"
},
  "geometry": {"coordinates":[-96.588274,33.638131],"type":"Point"}
}