{
  "type": "Feature",
  "properties": {
    "iso:country":"US",
    "sg:address":"403 Powerhouse Ste 309",
    "sg:city":"Mckinney",
    "sg:classifiers":[
        {
            "category":"Home & Garden",
            "subcategory":"Furniture",
            "type":"Retail Goods"
        }
    ],
    "sg:phone":"+1 800 910 1446",
    "sg:postcode":"75071",
    "sg:province":"TX",
    "sg:tags":[
        "equipment-household",
        "kitchen",
        "cabinet"
    ],
    "wof:name":"Soci, Inc.",
    "wof:placetype":"venue"
},
  "geometry": {"coordinates":[-96.618636,33.229387],"type":"Point"}
}