{
  "type": "Feature",
  "properties": {
    "iso:country":"US",
    "sg:address":"366 San Augustine St",
    "sg:city":"Center",
    "sg:classifiers":[
        {
            "category":"Retail",
            "subcategory":"Repair Shop",
            "type":"Services"
        }
    ],
    "sg:phone":"+1 936 598 3438",
    "sg:postcode":"75935",
    "sg:province":"TX",
    "sg:tags":[
        "appliance"
    ],
    "wof:name":"Hufferd's Appliance Svc",
    "wof:placetype":"venue"
},
  "geometry": {"coordinates":[-94.18225,31.792267],"type":"Point"}
}