{
  "type": "Feature",
  "properties": {
    "iso:country":"US",
    "sg:address":"2006 S Goliad St",
    "sg:city":"Rockwall",
    "sg:classifiers":[
        {
            "category":"Shopping",
            "subcategory":"Optical Goods",
            "type":"Retail Goods"
        }
    ],
    "sg:phone":"+1 972 772 7711",
    "sg:postcode":"75032",
    "sg:province":"TX",
    "sg:tags":[
        "store"
    ],
    "wof:name":"Vision Center of Heath",
    "wof:placetype":"venue"
},
  "geometry": {"coordinates":[-96.450334,32.909501],"type":"Point"}
}