{
  "type": "Feature",
  "properties": {
    "iso:country":"US",
    "sg:address":"2420 S Stemmons Fwy",
    "sg:city":"Lewisville",
    "sg:classifiers":[
        {
            "category":"Personal",
            "subcategory":"Beauty Salon",
            "type":"Services"
        }
    ],
    "sg:phone":"+1 972 459 0900",
    "sg:postcode":"75067",
    "sg:province":"TX",
    "sg:tags":[
        "manicuring"
    ],
    "wof:name":"Gold Nails & Spa",
    "wof:placetype":"venue"
},
  "geometry": {"coordinates":[-96.967476,33.004886],"type":"Point"}
}