{
  "type": "Feature",
  "properties": {
    "iso:country":"US",
    "sg:address":"875 Ascot Cir",
    "sg:city":"Beaumont",
    "sg:classifiers":[
        {
            "category":"Professional",
            "subcategory":"Business Services",
            "type":"Services"
        }
    ],
    "sg:phone":"+1 409 866 4507",
    "sg:postcode":"77706",
    "sg:province":"TX",
    "wof:name":"Nivek Enterprises Inc",
    "wof:placetype":"venue"
},
  "geometry": {"coordinates":[-94.17732700000001,30.080518],"type":"Point"}
}