{
  "type": "Feature",
  "properties": {
    "iso:country":"US",
    "sg:address":"20045 FM 306",
    "sg:city":"New Braunfels",
    "sg:classifiers":[
        {
            "category":"Wholesale",
            "subcategory":"Vending Machines",
            "type":"Manufacturing & Wholesale Goods"
        }
    ],
    "sg:phone":"+1 830 935 2040",
    "sg:postcode":"78133",
    "sg:province":"TX",
    "sg:tags":[
        "operator"
    ],
    "wof:name":"Mc Rae Vending",
    "wof:placetype":"venue"
},
  "geometry": {"coordinates":[-98.233088,29.930231],"type":"Point"}
}