{
  "type": "Feature",
  "properties": {
    "iso:country":"US",
    "sg:address":"4730 N Lindhurst Ave",
    "sg:city":"Dallas",
    "sg:classifiers":[
        {
            "category":"Mining & Drilling",
            "type":"Manufacturing & Wholesale Goods"
        }
    ],
    "sg:phone":"+1 214 361 6658",
    "sg:postcode":"75229",
    "sg:province":"TX",
    "sg:tags":[
        "exploration",
        "production",
        "gas",
        "oil"
    ],
    "wof:name":"Noble Cantrell Exploration Co",
    "wof:placetype":"venue"
},
  "geometry": {"coordinates":[-96.830287,32.882689],"type":"Point"}
}