{
  "type": "Feature",
  "properties": {
    "iso:country":"US",
    "sg:address":"1733 Stanford Ave",
    "sg:city":"Brownsville",
    "sg:classifiers":[
        {
            "category":"Professional",
            "subcategory":"Business Services",
            "type":"Services"
        }
    ],
    "sg:phone":"+1 956 592 5604",
    "sg:postcode":"78520",
    "sg:province":"TX",
    "sg:tags":[
        "translation"
    ],
    "wof:name":"Elda M Espinoza",
    "wof:placetype":"venue"
},
  "geometry": {"coordinates":[-97.492771,25.926051],"type":"Point"}
}