{
  "type": "Feature",
  "properties": {
    "iso:country":"US",
    "sg:address":"5302 Barcelona Dr",
    "sg:city":"Georgetown",
    "sg:classifiers":[
        {
            "category":"Building & Trades",
            "subcategory":"Construction",
            "type":"Services"
        }
    ],
    "sg:phone":"+1 512 635 4376",
    "sg:postcode":"78628",
    "sg:province":"TX",
    "sg:tags":[
        "wallcoverings-installation",
        "wallpaper",
        "painting",
        "contractor"
    ],
    "wof:name":"Vera Montesi",
    "wof:placetype":"venue"
},
  "geometry": {"coordinates":[-97.675538,30.692879],"type":"Point"}
}