{
  "type": "Feature",
  "properties": {
    "iso:country":"US",
    "sg:address":"2866 State Highway 19",
    "sg:city":"Huntsville",
    "sg:classifiers":[
        {
            "category":"Building & Trades",
            "subcategory":"Landscaping Services",
            "type":"Services"
        },
        {
            "category":"Mining & Drilling",
            "type":"Manufacturing & Wholesale Goods"
        },
        {
            "category":"Building & Trades",
            "subcategory":"Construction",
            "type":"Services"
        }
    ],
    "sg:phone":"+1 936 581 5416",
    "sg:postcode":"77320",
    "sg:province":"TX",
    "sg:tags":[
        "stump",
        "excavation",
        "boring",
        "tree",
        "grinding",
        "contractor",
        "removal",
        "landscape"
    ],
    "wof:name":"Trees Included",
    "wof:placetype":"venue"
},
  "geometry": {"coordinates":[-95.464793,30.792019],"type":"Point"}
}