{
  "type": "Feature",
  "properties": {
    "iso:country":"US",
    "sg:address":"13102 Lookout Rd",
    "sg:city":"San Antonio",
    "sg:classifiers":[
        {
            "category":"Building & Trades",
            "subcategory":"Plumbing",
            "type":"Services"
        }
    ],
    "sg:phone":"+1 210 656 1066",
    "sg:postcode":"78233",
    "sg:province":"TX",
    "sg:tags":[
        "sheet",
        "work",
        "metal",
        "contractor"
    ],
    "wof:name":"Yama Manufacturing Co",
    "wof:placetype":"venue"
},
  "geometry": {"coordinates":[-98.375215,29.559127],"type":"Point"}
}