{
  "type": "Feature",
  "properties": {
    "iso:country":"US",
    "sg:address":"204 Nettletree St",
    "sg:city":"Arlington",
    "sg:classifiers":[
        {
            "category":"Shopping",
            "subcategory":"Clothing, Apparel, & Fashions",
            "type":"Retail Goods"
        }
    ],
    "sg:phone":"+1 817 468 2531",
    "sg:postcode":"76018",
    "sg:province":"TX",
    "wof:name":"Carlisles Boutique",
    "wof:placetype":"venue"
},
  "geometry": {"coordinates":[-97.110062,32.660045],"type":"Point"}
}