{
  "type": "Feature",
  "properties": {
    "iso:country":"US",
    "sg:address":"1798 S Loop 360",
    "sg:city":"Austin",
    "sg:classifiers":[
        {
            "category":"Health Services",
            "subcategory":"Doctor",
            "type":"Services"
        }
    ],
    "sg:phone":"+1 512 327 3533",
    "sg:postcode":"78746",
    "sg:province":"TX",
    "wof:name":"Howerton Ernest E MD",
    "wof:placetype":"venue"
},
  "geometry": {"coordinates":[-97.804199,30.2911],"type":"Point"}
}