{
  "type": "Feature",
  "properties": {
    "iso:country":"US",
    "sg:address":"630 Crestview Dr",
    "sg:city":"San Antonio",
    "sg:classifiers":[
        {
            "category":"Education",
            "subcategory":"School",
            "type":"Public Place"
        }
    ],
    "sg:phone":"+1 210 735 5921",
    "sg:postcode":"78201",
    "sg:province":"TX",
    "wof:name":"Baskin Mildred Elementary Schl",
    "wof:placetype":"venue"
},
  "geometry": {"coordinates":[-98.562308,29.486724],"type":"Point"}
}