{
  "type": "Feature",
  "properties": {
    "iso:country":"US",
    "sg:address":"102 N Main St",
    "sg:city":"Weatherford",
    "sg:classifiers":[
        {
            "category":"Banks & Credit Unions",
            "subcategory":"Financial Services",
            "type":"Services"
        }
    ],
    "sg:phone":"+1 817 594 8721",
    "sg:postcode":"76086",
    "sg:province":"TX",
    "sg:tags":[
        "company",
        "holding"
    ],
    "wof:name":"Texas Banc Holding Co",
    "wof:placetype":"venue"
},
  "geometry": {"coordinates":[-97.797202,32.760536],"type":"Point"}
}