{
  "type": "Feature",
  "properties": {
    "iso:country":"US",
    "sg:address":"16633 Holly Trail Dr",
    "sg:city":"Houston",
    "sg:classifiers":[
        {
            "category":"Utilities",
            "subcategory":"Telephone",
            "type":"Services"
        }
    ],
    "sg:phone":"+1 281 488 3743",
    "sg:postcode":"77058",
    "sg:province":"TX",
    "sg:tags":[
        "phones-equipment",
        "pay"
    ],
    "wof:name":"Extra Effort Payphone",
    "wof:placetype":"venue"
},
  "geometry": {"coordinates":[-95.110617,29.562079],"type":"Point"}
}