{
  "type": "Feature",
  "properties": {
    "iso:country":"US",
    "sg:address":"20802 Rhodes Rd",
    "sg:city":"Spring",
    "sg:classifiers":[
        {
            "category":"Social Services",
            "subcategory":"Child Care",
            "type":"Services"
        }
    ],
    "sg:phone":"+1 281 353 7131",
    "sg:postcode":"77388",
    "sg:province":"TX",
    "sg:tags":[
        "day"
    ],
    "wof:name":"Alphabet Soup Early Lrng Ctr",
    "wof:placetype":"venue"
},
  "geometry": {"coordinates":[-95.496756,30.069018],"type":"Point"}
}