{
  "type": "Feature",
  "properties": {
    "iso:country":"US",
    "sg:address":"9035 Cullen Blvd",
    "sg:city":"Houston",
    "sg:classifiers":[
        {
            "category":"Personal",
            "subcategory":"Barber",
            "type":"Services"
        }
    ],
    "sg:phone":"+1 713 733 6618",
    "sg:postcode":"77051",
    "sg:province":"TX",
    "sg:tags":[
        "shop"
    ],
    "wof:name":"Elite Barber Shop",
    "wof:placetype":"venue"
},
  "geometry": {"coordinates":[-95.35544400000001,29.658454],"type":"Point"}
}