{
  "type": "Feature",
  "properties": {
    "iso:country":"US",
    "sg:address":"1009 Ave M",
    "sg:city":"Hondo",
    "sg:classifiers":[
        {
            "category":"Travel",
            "subcategory":"Campground",
            "type":"Entertainment"
        }
    ],
    "sg:phone":"+1 830 426 3882",
    "sg:postcode":"78861",
    "sg:province":"TX",
    "sg:tags":[
        "trailer"
    ],
    "wof:name":"Rambling-Rec R V Park",
    "wof:placetype":"venue"
},
  "geometry": {"coordinates":[-99.141884,29.355341],"type":"Point"}
}