{
  "type": "Feature",
  "properties": {
    "iso:country":"US",
    "sg:address":"1010 W Miller Rd",
    "sg:city":"Garland",
    "sg:classifiers":[
        {
            "category":"Recreation",
            "type":"Entertainment"
        },
        {
            "category":"Shopping",
            "subcategory":"Bicycles & Sporting Goods",
            "type":"Retail Goods"
        }
    ],
    "sg:phone":"+1 972 205 2778",
    "sg:postcode":"75041",
    "sg:province":"TX",
    "sg:tags":[
        "executive",
        "tennis",
        "court"
    ],
    "wof:name":"Garland Tennis Center",
    "wof:placetype":"venue"
},
  "geometry": {"coordinates":[-96.642083,32.894395],"type":"Point"}
}