{
  "type": "Feature",
  "properties": {
    "iso:country":"US",
    "sg:address":"5687 Doliver Dr",
    "sg:city":"Houston",
    "sg:classifiers":[
        {
            "category":"Professional",
            "type":"Services"
        }
    ],
    "sg:phone":"+1 713 622 2680",
    "sg:postcode":"77056",
    "sg:province":"TX",
    "wof:name":"Ocs Containers",
    "wof:placetype":"venue"
},
  "geometry": {"coordinates":[-95.47441499999999,29.752225],"type":"Point"}
}