{
  "type": "Feature",
  "properties": {
    "iso:country":"US",
    "sg:address":"903 E Kent St",
    "sg:city":"Lubbock",
    "sg:classifiers":[
        {
            "category":"Retail",
            "subcategory":"Repair Shop",
            "type":"Services"
        }
    ],
    "sg:phone":"+1 806 747 0448",
    "sg:postcode":"79403",
    "sg:province":"TX",
    "sg:tags":[
        "refrigeration"
    ],
    "wof:name":"Smokey & Sons",
    "wof:placetype":"venue"
},
  "geometry": {"coordinates":[-101.824614,33.635966],"type":"Point"}
}