{
  "type": "Feature",
  "properties": {
    "iso:country":"US",
    "sg:address":"5700 Tennyson Pkwy",
    "sg:city":"Plano",
    "sg:classifiers":[
        {
            "category":"Banks & Credit Unions",
            "subcategory":"Investment Brokerage",
            "type":"Services"
        }
    ],
    "sg:phone":"+1 972 943 7222",
    "sg:postcode":"75024",
    "sg:province":"TX",
    "sg:tags":[
        "security"
    ],
    "wof:name":"Citigroup Global Markets Inc",
    "wof:placetype":"venue"
},
  "geometry": {"coordinates":[-96.819148,33.071435],"type":"Point"}
}