{
  "type": "Feature",
  "properties": {
    "iso:country":"US",
    "sg:address":"2714 Apache Dr",
    "sg:city":"Montgomery",
    "sg:classifiers":[
        {
            "category":"Real Estate",
            "subcategory":"Real Estate Agent",
            "type":"Services"
        }
    ],
    "sg:phone":"+1 936 588 3987",
    "sg:postcode":"77316",
    "sg:province":"TX",
    "wof:name":"McMinn  B B Property LLC",
    "wof:placetype":"venue"
},
  "geometry": {"coordinates":[-95.60295000000001,30.344336],"type":"Point"}
}