{
  "type": "Feature",
  "properties": {
    "iso:country":"US",
    "sg:address":"3106 Gilmer Rd",
    "sg:city":"Longview",
    "sg:classifiers":[
        {
            "category":"Organizations",
            "subcategory":"Religious Organization",
            "type":"Services"
        }
    ],
    "sg:phone":"+1 903 297 0228",
    "sg:postcode":"75604",
    "sg:province":"TX",
    "wof:name":"Unitarian Fellowship Longview",
    "wof:placetype":"venue"
},
  "geometry": {"coordinates":[-94.795678,32.543573],"type":"Point"}
}