{
  "type": "Feature",
  "properties": {
    "iso:country":"US",
    "sg:address":"11441 N Stemmons Fwy",
    "sg:city":"Dallas",
    "sg:classifiers":[
        {
            "category":"Home & Garden",
            "subcategory":"Building Materials",
            "type":"Retail Goods"
        }
    ],
    "sg:phone":"+1 972 620 9300",
    "sg:postcode":"75229",
    "sg:province":"TX",
    "sg:tags":[
        "tile",
        "installation"
    ],
    "wof:name":"Tile Designs",
    "wof:placetype":"venue"
},
  "geometry": {"coordinates":[-96.898039,32.896333],"type":"Point"}
}