{
  "type": "Feature",
  "properties": {
    "iso:country":"US",
    "sg:address":"37 Alan A Dale St",
    "sg:city":"Brownsville",
    "sg:classifiers":[
        {
            "category":"Home & Garden",
            "subcategory":"Building Materials",
            "type":"Retail Goods"
        }
    ],
    "sg:phone":"+1 956 542 5056",
    "sg:postcode":"78521",
    "sg:province":"TX",
    "wof:name":"A1 Express Electric",
    "wof:placetype":"venue"
},
  "geometry": {"coordinates":[-97.474659,25.928846],"type":"Point"}
}