{
  "type": "Feature",
  "properties": {
    "iso:country":"US",
    "sg:address":"9667 State Hwy 198",
    "sg:city":"Mabank",
    "sg:classifiers":[
        {
            "category":"Organizations",
            "subcategory":"Religious Organization",
            "type":"Services"
        }
    ],
    "sg:phone":"+1 903 451 2978",
    "sg:postcode":"75156",
    "sg:province":"TX",
    "sg:tags":[
        "church"
    ],
    "wof:name":"Payne Springs Methodist Church",
    "wof:placetype":"venue"
},
  "geometry": {"coordinates":[-96.067381,32.278199],"type":"Point"}
}