{
  "type": "Feature",
  "properties": {
    "iso:country":"US",
    "sg:address":"1801 E Henderson St",
    "sg:city":"Cleburne",
    "sg:classifiers":[
        {
            "category":"Personal",
            "type":"Services"
        }
    ],
    "sg:phone":"+1 817 645 1160",
    "sg:postcode":"76031",
    "sg:province":"TX",
    "sg:tags":[
        "wedding",
        "chapel"
    ],
    "wof:name":"Hitchin' Post Chapel",
    "wof:placetype":"venue"
},
  "geometry": {"coordinates":[-97.354246,32.366032],"type":"Point"}
}