{
  "type": "Feature",
  "properties": {
    "iso:country":"US",
    "sg:address":"1219 Chihuahua St",
    "sg:city":"Laredo",
    "sg:classifiers":[
        {
            "category":"Personal",
            "subcategory":"Beauty Salon",
            "type":"Services"
        }
    ],
    "sg:phone":"+1 956 717 3044",
    "sg:postcode":"78040",
    "sg:province":"TX",
    "sg:tags":[
        "shop"
    ],
    "wof:name":"Perfect Cuts",
    "wof:placetype":"venue"
},
  "geometry": {"coordinates":[-99.48362400000001,27.505586],"type":"Point"}
}