{
  "type": "Feature",
  "properties": {
    "iso:country":"US",
    "sg:address":"717 Via Bravo",
    "sg:city":"Mesquite",
    "sg:classifiers":[
        {
            "category":"Building & Trades",
            "subcategory":"Construction",
            "type":"Services"
        }
    ],
    "sg:phone":"+1 972 270 7382",
    "sg:postcode":"75150",
    "sg:province":"TX",
    "sg:tags":[
        "contractor"
    ],
    "wof:name":"Mosaic Silkscreen & Embroidery",
    "wof:placetype":"venue"
},
  "geometry": {"coordinates":[-96.609725,32.825858],"type":"Point"}
}