{
  "type": "Feature",
  "properties": {
    "iso:country":"US",
    "sg:address":"4329 Presto Cir",
    "sg:city":"Grand Prairie",
    "sg:classifiers":[
        {
            "category":"Professional",
            "subcategory":"Business Services",
            "type":"Services"
        }
    ],
    "sg:phone":"+1 972 660 4847",
    "sg:postcode":"75052",
    "sg:province":"TX",
    "wof:name":"T&T Assoc",
    "wof:placetype":"venue"
},
  "geometry": {"coordinates":[-97.05559599999999,32.665998],"type":"Point"}
}