{
  "type": "Feature",
  "properties": {
    "iso:country":"US",
    "sg:address":"1118 Crestview Dr",
    "sg:city":"Kaufman",
    "sg:classifiers":[
        {
            "category":"Wholesale",
            "subcategory":"Non-durable Goods",
            "type":"Manufacturing & Wholesale Goods"
        }
    ],
    "sg:phone":"+1 972 932 7594",
    "sg:postcode":"75142",
    "sg:province":"TX",
    "wof:name":"Unicorn International Inc",
    "wof:placetype":"venue"
},
  "geometry": {"coordinates":[-96.30635599999999,32.576912],"type":"Point"}
}