{
  "type": "Feature",
  "properties": {
    "iso:country":"US",
    "sg:address":"400 Taylor St",
    "sg:city":"Texline",
    "sg:classifiers":[
        {
            "category":"Professional",
            "type":"Services"
        }
    ],
    "sg:phone":"+1 806 362 4382",
    "sg:postcode":"79087",
    "sg:province":"TX",
    "sg:tags":[
        "establishment"
    ],
    "wof:name":"Bojo Enterprises",
    "wof:placetype":"venue"
},
  "geometry": {"coordinates":[-103.022763,36.380995],"type":"Point"}
}