{
  "type": "Feature",
  "properties": {
    "iso:country":"US",
    "sg:address":"4131 Fawnhollow Dr",
    "sg:city":"Dallas",
    "sg:classifiers":[
        {
            "category":"Manufacturing",
            "subcategory":"Printing",
            "type":"Manufacturing & Wholesale Goods"
        }
    ],
    "sg:phone":"+1 972 620 2489",
    "sg:postcode":"75244",
    "sg:province":"TX",
    "sg:tags":[
        "print",
        "publisher",
        "medium"
    ],
    "sg:website":"www.scor-report.com",
    "wof:name":"Stewart-Gordon Associates Inc",
    "wof:placetype":"venue"
},
  "geometry": {"coordinates":[-96.84020200000001,32.914799],"type":"Point"}
}