{
  "type": "Feature",
  "properties": {
    "iso:country":"US",
    "sg:address":"332 Durr St",
    "sg:city":"Marlin",
    "sg:classifiers":[
        {
            "category":"Social Services",
            "type":"Services"
        }
    ],
    "sg:phone":"+1 254 883 2360",
    "sg:postcode":"76661",
    "sg:province":"TX",
    "wof:name":"Falconer Stamps Community Ctr",
    "wof:placetype":"venue"
},
  "geometry": {"coordinates":[-96.89415700000001,31.302194],"type":"Point"}
}