{
  "type": "Feature",
  "properties": {
    "iso:country":"US",
    "sg:address":"2013 Holford Rd",
    "sg:city":"Garland",
    "sg:classifiers":[
        {
            "category":"Building & Trades",
            "subcategory":"Landscaping Services",
            "type":"Services"
        }
    ],
    "sg:phone":"+1 972 530 8005",
    "sg:postcode":"75044",
    "sg:province":"TX",
    "sg:tags":[
        "landscape",
        "contractor"
    ],
    "sg:website":"www.koodaexteriors.com",
    "wof:name":"Kooda Exteriors Inc",
    "wof:placetype":"venue"
},
  "geometry": {"coordinates":[-96.660855,32.960289],"type":"Point"}
}