{
  "type": "Feature",
  "properties": {
    "iso:country":"US",
    "sg:address":"16259 Fm 529 Rd",
    "sg:city":"Houston",
    "sg:phone":"+1 281 345 4450",
    "sg:postcode":"77095",
    "sg:province":"TX",
    "wof:name":"Discover Chiropractic",
    "wof:placetype":"venue"
},
  "geometry": {"coordinates":[-95.654561,29.878987],"type":"Point"}
}