{
  "type": "Feature",
  "properties": {
    "iso:country":"US",
    "sg:address":"9711 Co Rd 1109",
    "sg:city":"Princeton",
    "sg:classifiers":[
        {
            "category":"Organizations",
            "subcategory":"Religious Organization",
            "type":"Services"
        }
    ],
    "sg:phone":"+1 972 734 8512",
    "sg:postcode":"75407",
    "sg:province":"TX",
    "wof:name":"7 Day Pool Co",
    "wof:placetype":"venue"
},
  "geometry": {"coordinates":[-96.49163900000001,33.138444],"type":"Point"}
}