{
  "type": "Feature",
  "properties": {
    "iso:country":"US",
    "sg:address":"7307 US Hwy 77",
    "sg:city":"La Grange",
    "sg:classifiers":[
        {
            "category":"Manufacturing",
            "subcategory":"Petroleum Products",
            "type":"Manufacturing & Wholesale Goods"
        }
    ],
    "sg:phone":"+1 979 242 3012",
    "sg:postcode":"78945",
    "sg:province":"TX",
    "sg:tags":[
        "refiner"
    ],
    "wof:name":"Energy Transfer Group LLC",
    "wof:placetype":"venue"
},
  "geometry": {"coordinates":[-96.91042899999999,29.823021],"type":"Point"}
}