{
  "type": "Feature",
  "properties": {
    "iso:country":"US",
    "sg:address":"2127 Crown Rd",
    "sg:city":"Dallas",
    "sg:classifiers":[
        {
            "category":"Retail",
            "subcategory":"Auto Repair",
            "type":"Services"
        }
    ],
    "sg:phone":"+1 972 243 0440",
    "sg:postcode":"75229",
    "sg:province":"TX",
    "sg:tags":[
        "automobile",
        "restoration",
        "classic"
    ],
    "sg:website":"www.kipmotor.com",
    "wof:name":"Kip Motor Co",
    "wof:placetype":"venue"
},
  "geometry": {"coordinates":[-96.90679,32.900542],"type":"Point"}
}