{
  "type": "Feature",
  "properties": {
    "iso:country":"US",
    "sg:address":"29 Hacienda",
    "sg:city":"Pottsboro",
    "sg:classifiers":[
        {
            "category":"Professional",
            "type":"Services"
        }
    ],
    "sg:phone":"+1 903 786 7073",
    "sg:postcode":"75076",
    "sg:province":"TX",
    "wof:name":"Nancys",
    "wof:placetype":"venue"
},
  "geometry": {"coordinates":[-96.716909,33.816145],"type":"Point"}
}