{
  "type": "Feature",
  "properties": {
    "iso:country":"US",
    "sg:address":"712 Buckner Blvd",
    "sg:city":"Dallas",
    "sg:classifiers":[
        {
            "category":"Insurance",
            "subcategory":"Insurance Agent",
            "type":"Services"
        }
    ],
    "sg:phone":"+1 214 398 8680",
    "sg:postcode":"75217",
    "sg:province":"TX",
    "sg:tags":[
        "processing"
    ],
    "wof:name":"DFW Adjusters Inc",
    "wof:placetype":"venue"
},
  "geometry": {"coordinates":[-96.682811,32.724934],"type":"Point"}
}