{
  "type": "Feature",
  "properties": {
    "iso:country":"US",
    "sg:address":"260 Cape Aron Dr",
    "sg:city":"Corpus Christi",
    "sg:classifiers":[
        {
            "category":"Professional",
            "type":"Services"
        }
    ],
    "sg:phone":"+1 361 991 1118",
    "sg:postcode":"78412",
    "sg:province":"TX",
    "sg:tags":[
        "physician",
        "ranch"
    ],
    "wof:name":"Lawrence & Helen K Wilk MD",
    "wof:placetype":"venue"
},
  "geometry": {"coordinates":[-97.35547099999999,27.724666],"type":"Point"}
}