{
  "type": "Feature",
  "properties": {
    "iso:country":"US",
    "sg:address":"712 Railroad Ave",
    "sg:city":"Portland",
    "sg:classifiers":[
        {
            "category":"Personal",
            "subcategory":"Beauty Salon",
            "type":"Services"
        }
    ],
    "sg:phone":"+1 361 643 6942",
    "sg:postcode":"78374",
    "sg:province":"TX",
    "sg:tags":[
        "shop"
    ],
    "wof:name":"Guerra Paulaann",
    "wof:placetype":"venue"
},
  "geometry": {"coordinates":[-97.32167699999999,27.875134],"type":"Point"}
}