{
  "type": "Feature",
  "properties": {
    "iso:country":"US",
    "sg:address":"3610 Canterbury Dr",
    "sg:city":"Baytown",
    "sg:classifiers":[
        {
            "category":"Social Services",
            "type":"Services"
        }
    ],
    "sg:phone":"+1 281 427 9337",
    "sg:postcode":"77521",
    "sg:province":"TX",
    "wof:name":"Habitats For Youth",
    "wof:placetype":"venue"
},
  "geometry": {"coordinates":[-94.923385,29.769008],"type":"Point"}
}