{
  "type": "Feature",
  "properties": {
    "iso:country":"US",
    "sg:address":"6807 Avenue E",
    "sg:city":"Houston",
    "sg:classifiers":[
        {
            "category":"Wholesale",
            "subcategory":"Painting Supplies",
            "type":"Manufacturing & Wholesale Goods"
        }
    ],
    "sg:phone":"+1 713 921 3915",
    "sg:postcode":"77011",
    "sg:province":"TX",
    "sg:tags":[
        "paint-wholesale",
        "manufacturer"
    ],
    "wof:name":"Sanchez Paint",
    "wof:placetype":"venue"
},
  "geometry": {"coordinates":[-95.300014,29.751692],"type":"Point"}
}