{
  "type": "Feature",
  "properties": {
    "iso:country":"US",
    "sg:address":"26906 I- 45",
    "sg:city":"Spring",
    "sg:classifiers":[
        {
            "category":"Food & Beverages",
            "subcategory":"Groceries & Convenience Stores",
            "type":"Retail Goods"
        }
    ],
    "sg:phone":"+1 281 367 5178",
    "sg:postcode":"77386",
    "sg:province":"TX",
    "wof:name":"Diamond Shamrock",
    "wof:placetype":"venue"
},
  "geometry": {"coordinates":[-95.448553,30.156162],"type":"Point"}
}