{
  "type": "Feature",
  "properties": {
    "iso:country":"US",
    "sg:address":"6125 Sam Houston Pkwy",
    "sg:city":"Houston",
    "sg:classifiers":[
        {
            "category":"Wholesale",
            "subcategory":"Machinery & Supplies",
            "type":"Manufacturing & Wholesale Goods"
        }
    ],
    "sg:phone":"+1 713 856 9090",
    "sg:postcode":"77032",
    "sg:province":"TX",
    "sg:tags":[
        "pump"
    ],
    "wof:name":"Champion Power Products Inc",
    "wof:placetype":"venue"
},
  "geometry": {"coordinates":[-95.29708100000001,29.940501],"type":"Point"}
}