{
  "type": "Feature",
  "properties": {
    "iso:country":"US",
    "sg:address":"1550 W. Mockingbird Lane",
    "sg:city":"Dallas",
    "sg:classifiers":[
        {
            "category":"Professional",
            "type":"Services"
        }
    ],
    "sg:phone":"+1 214 637 2800",
    "sg:postcode":"75235",
    "sg:province":"TX",
    "sg:website":"www.taylorpub.com",
    "wof:name":"Taylor Publishing",
    "wof:placetype":"venue"
},
  "geometry": {"coordinates":[-96.85885,32.82077],"type":"Point"}
}