{
  "type": "Feature",
  "properties": {
    "iso:country":"US",
    "sg:address":"114 N FM 369",
    "sg:city":"Iowa Park",
    "sg:classifiers":[
        {
            "category":"Wholesale",
            "subcategory":"Machinery & Supplies",
            "type":"Manufacturing & Wholesale Goods"
        }
    ],
    "sg:phone":"+1 940 855 1218",
    "sg:postcode":"76367",
    "sg:province":"TX",
    "sg:tags":[
        "car"
    ],
    "wof:name":"Auto Wax Supply Co",
    "wof:placetype":"venue"
},
  "geometry": {"coordinates":[-98.60324900000001,33.94469],"type":"Point"}
}