{
  "type": "Feature",
  "properties": {
    "iso:country":"US",
    "sg:address":"801 E Lamar Blvd",
    "sg:city":"Arlington",
    "sg:classifiers":[
        {
            "category":"Food & Beverages",
            "subcategory":"Groceries & Convenience Stores",
            "type":"Retail Goods"
        }
    ],
    "sg:phone":"+1 817 461 8324",
    "sg:postcode":"76011",
    "sg:province":"TX",
    "sg:tags":[
        "grocer"
    ],
    "sg:website":"www.wholefoodsmarket.com",
    "wof:name":"Whole Foods Market",
    "wof:placetype":"venue"
},
  "geometry": {"coordinates":[-97.098028,32.765718],"type":"Point"}
}