{
  "type": "Feature",
  "properties": {
    "iso:country":"US",
    "sg:address":"741 Mc Daniel St",
    "sg:city":"Houston",
    "sg:classifiers":[
        {
            "category":"Manufacturing",
            "subcategory":"Tools & Machinery",
            "type":"Manufacturing & Wholesale Goods"
        }
    ],
    "sg:phone":"+1 713 694 3172",
    "sg:postcode":"77022",
    "sg:province":"TX",
    "sg:tags":[
        "machine",
        "shop"
    ],
    "wof:name":"Val Nu Machine",
    "wof:placetype":"venue"
},
  "geometry": {"coordinates":[-95.364093,29.831309],"type":"Point"}
}