{
  "type": "Feature",
  "properties": {
    "iso:country":"US",
    "sg:address":"11910 Research Blvd",
    "sg:city":"Austin",
    "sg:classifiers":[
        {
            "category":"Professional",
            "type":"Services"
        },
        {
            "category":"Restaurant",
            "type":"Food & Drink"
        },
        {
            "category":"Retail",
            "subcategory":"Event Space",
            "type":"Services"
        },
        {
            "category":"Food & Beverages",
            "subcategory":"Meat & Fish",
            "type":"Retail Goods"
        }
    ],
    "sg:phone":"+1 512 258 1853",
    "sg:postcode":"78759",
    "sg:province":"TX",
    "sg:tags":[
        "style",
        "family",
        "facility",
        "seafood",
        "hall",
        "reception",
        "caterer",
        "banquet",
        "market"
    ],
    "sg:website":"http://www.catfishparlour.com",
    "wof:name":"Catfish Parlour",
    "wof:placetype":"venue"
},
  "geometry": {"coordinates":[-97.750175,30.424258],"type":"Point"}
}