{
  "type": "Feature",
  "properties": {
    "iso:country":"US",
    "sg:address":"227 N Brazos St",
    "sg:city":"Eagle Pass",
    "sg:classifiers":[
        {
            "category":"Building & Trades",
            "subcategory":"Cleaning & Sanitation",
            "type":"Services"
        }
    ],
    "sg:phone":"+1 830 773 6532",
    "sg:postcode":"78852",
    "sg:province":"TX",
    "sg:tags":[
        "maintenance"
    ],
    "wof:name":"Industrial Janitorial Svc",
    "wof:placetype":"venue"
},
  "geometry": {"coordinates":[-100.487714,28.708057],"type":"Point"}
}