{
  "type": "Feature",
  "properties": {
    "iso:country":"US",
    "sg:address":"4 Ivanhoe Ter",
    "sg:city":"Wichita Falls",
    "sg:classifiers":[
        {
            "category":"Arts & Performance",
            "subcategory":"Theater",
            "type":"Entertainment"
        }
    ],
    "sg:phone":"+1 940 855 5837",
    "sg:postcode":"76306",
    "sg:province":"TX",
    "sg:tags":[
        "music",
        "presentation",
        "church"
    ],
    "wof:name":"CM Enterprise",
    "wof:placetype":"venue"
},
  "geometry": {"coordinates":[-98.526618,33.987534],"type":"Point"}
}