{
  "type": "Feature",
  "properties": {
    "iso:country":"US",
    "sg:address":"3110 Ave Q",
    "sg:city":"Galveston",
    "sg:classifiers":[
        {
            "category":"Professional",
            "subcategory":"Business Services",
            "type":"Services"
        }
    ],
    "sg:phone":"+1 409 763 6093",
    "sg:postcode":"77550",
    "sg:province":"TX",
    "sg:tags":[
        "notary"
    ],
    "wof:name":"Marie Pines Notary Svc",
    "wof:placetype":"venue"
},
  "geometry": {"coordinates":[-94.799001,29.2878],"type":"Point"}
}