{
  "type": "Feature",
  "properties": {
    "iso:country":"US",
    "sg:address":"1029 E Fulton St",
    "sg:city":"Sinton",
    "sg:classifiers":[
        {
            "category":"Building & Trades",
            "subcategory":"Construction",
            "type":"Services"
        }
    ],
    "sg:phone":"+1 361 364 5040",
    "sg:postcode":"78387",
    "sg:province":"TX",
    "sg:tags":[
        "home",
        "improvement"
    ],
    "wof:name":"Home Helpers",
    "wof:placetype":"venue"
},
  "geometry": {"coordinates":[-97.49889899999999,28.0389],"type":"Point"}
}