{
  "type": "Feature",
  "properties": {
    "iso:country":"US",
    "sg:address":"6209 Kenosha Dr",
    "sg:city":"Lubbock",
    "sg:classifiers":[
        {
            "category":"Health Services",
            "subcategory":"Doctor",
            "type":"Services"
        }
    ],
    "sg:phone":"+1 806 784 0444",
    "sg:postcode":"79413",
    "sg:province":"TX",
    "sg:tags":[
        "dentist"
    ],
    "wof:name":"John F Moeller",
    "wof:placetype":"venue"
},
  "geometry": {"coordinates":[-101.88987400000001,33.535676],"type":"Point"}
}