{
  "type": "Feature",
  "properties": {
    "iso:country":"US",
    "sg:address":"314 Blue Heron Blvd",
    "sg:city":"Boerne",
    "sg:classifiers":[
        {
            "category":"Travel",
            "subcategory":"Hotels & Motels",
            "type":"Entertainment"
        }
    ],
    "sg:phone":"+1 210 698 3539",
    "sg:postcode":"78006",
    "sg:province":"TX",
    "sg:tags":[
        "resort"
    ],
    "wof:name":"Tapatio Springs",
    "wof:placetype":"venue"
},
  "geometry": {"coordinates":[-98.808948,29.775303],"type":"Point"}
}