{
  "type": "Feature",
  "properties": {
    "iso:country":"US",
    "sg:address":"20933 Co Rd 145",
    "sg:city":"Tyler",
    "sg:classifiers":[
        {
            "category":"Manufacturing",
            "subcategory":"Printing",
            "type":"Manufacturing & Wholesale Goods"
        }
    ],
    "sg:phone":"+1 903 894 5990",
    "sg:postcode":"75703",
    "sg:province":"TX",
    "sg:tags":[
        "lithographic",
        "commercial"
    ],
    "wof:name":"CCC Printing & Graphics",
    "wof:placetype":"venue"
},
  "geometry": {"coordinates":[-95.317025,32.174698],"type":"Point"}
}