{
  "type": "Feature",
  "properties": {
    "iso:country":"US",
    "sg:address":"1100 Stone Rd",
    "sg:city":"Kilgore",
    "sg:classifiers":[
        {
            "category":"Professional",
            "subcategory":"Accounting & Tax Preparation",
            "type":"Services"
        },
        {
            "category":"Professional",
            "subcategory":"Computer Services",
            "type":"Services"
        }
    ],
    "sg:phone":"+1 903 983 2734",
    "sg:postcode":"75662",
    "sg:province":"TX",
    "sg:tags":[
        "datum",
        "billing"
    ],
    "wof:name":"Accuclaims Medical Billing",
    "wof:placetype":"venue"
},
  "geometry": {"coordinates":[-94.86657700000001,32.391981],"type":"Point"}
}