{
  "type": "Feature",
  "properties": {
    "iso:country":"US",
    "sg:address":"5711 E Yandell Dr",
    "sg:city":"El Paso",
    "sg:classifiers":[
        {
            "category":"Restaurant",
            "type":"Food & Drink"
        }
    ],
    "sg:phone":"+1 915 774 0521",
    "sg:postcode":"79925",
    "sg:province":"TX",
    "sg:tags":[
        "fast"
    ],
    "wof:name":"Newman Poultry Company",
    "wof:placetype":"venue"
},
  "geometry": {"coordinates":[-106.42080300000001,31.780155],"type":"Point"}
}