{
  "type": "Feature",
  "properties": {
    "iso:country":"US",
    "sg:address":"138 Aldrich Dr",
    "sg:city":"San Antonio",
    "sg:classifiers":[
        {
            "category":"Insurance",
            "subcategory":"Insurance Agent",
            "type":"Services"
        }
    ],
    "sg:phone":"+1 210 645 6850",
    "sg:postcode":"78227",
    "sg:province":"TX",
    "wof:name":"Rmp Enterprises",
    "wof:placetype":"venue"
},
  "geometry": {"coordinates":[-98.635689,29.379128],"type":"Point"}
}