{
  "type": "Feature",
  "properties": {
    "iso:country":"US",
    "sg:address":"1419 Lakeshore Dr",
    "sg:city":"Irving",
    "sg:classifiers":[
        {
            "category":"Wholesale",
            "subcategory":"Machinery & Supplies",
            "type":"Manufacturing & Wholesale Goods"
        }
    ],
    "sg:phone":"+1 972 790 8149",
    "sg:postcode":"75060",
    "sg:province":"TX",
    "wof:name":"American Eagle Sprinkler Co",
    "wof:placetype":"venue"
},
  "geometry": {"coordinates":[-96.965869,32.788891],"type":"Point"}
}