{
  "type": "Feature",
  "properties": {
    "iso:country":"US",
    "sg:address":"1104 S Westmoreland Rd",
    "sg:city":"Dallas",
    "sg:classifiers":[
        {
            "category":"Shopping",
            "subcategory":"Pharmacy",
            "type":"Retail Goods"
        }
    ],
    "sg:phone":"+1 214 467 3540",
    "sg:postcode":"75211",
    "sg:province":"TX",
    "sg:tags":[
        "photofinishing",
        "drugstore",
        "laboratory"
    ],
    "sg:website":"www.walgreens.com/",
    "wof:name":"Walgreens",
    "wof:placetype":"venue"
},
  "geometry": {"coordinates":[-96.873521,32.733998],"type":"Point"}
}