{
  "type": "Feature",
  "properties": {
    "iso:country":"US",
    "sg:address":"1501 W US Hwy 83",
    "sg:city":"Mcallen",
    "sg:classifiers":[
        {
            "category":"Local Transit",
            "type":"Transportation"
        }
    ],
    "sg:phone":"+1 956 994 9386",
    "sg:postcode":"78501",
    "sg:province":"TX",
    "sg:tags":[
        "passenger"
    ],
    "wof:name":"Autobuses Adame Inc",
    "wof:placetype":"venue"
},
  "geometry": {"coordinates":[-98.23662,26.204603],"type":"Point"}
}