{
  "type": "Feature",
  "properties": {
    "iso:country":"US",
    "sg:address":"13822 Swan Hollow Ln",
    "sg:city":"Houston",
    "sg:classifiers":[
        {
            "category":"Food & Beverages",
            "subcategory":"Bakery",
            "type":"Retail Goods"
        }
    ],
    "sg:phone":"+1 713 466 5667",
    "sg:postcode":"77041",
    "sg:province":"TX",
    "sg:tags":[
        "doughnut"
    ],
    "wof:name":"Mr K Donut & Kolaches",
    "wof:placetype":"venue"
},
  "geometry": {"coordinates":[-95.617968,29.894979],"type":"Point"}
}