{
  "type": "Feature",
  "properties": {
    "iso:country":"US",
    "sg:address":"5129 Goodwin Ave",
    "sg:city":"Dallas",
    "sg:classifiers":[
        {
            "category":"Building & Trades",
            "subcategory":"Landscaping Services",
            "type":"Services"
        }
    ],
    "sg:phone":"+1 214 824 7337",
    "sg:postcode":"75206",
    "sg:province":"TX",
    "wof:name":"Marvins Lawn Service",
    "wof:placetype":"venue"
},
  "geometry": {"coordinates":[-96.783815,32.823504],"type":"Point"}
}