{
  "type": "Feature",
  "properties": {
    "iso:country":"US",
    "sg:address":"1400 N Harborth Ave",
    "sg:city":"Three Rivers",
    "sg:classifiers":[
        {
            "category":"Organizations",
            "subcategory":"Community Association",
            "type":"Services"
        }
    ],
    "sg:phone":"+1 361 786 4440",
    "sg:postcode":"78071",
    "sg:province":"TX",
    "sg:tags":[
        "fraternal"
    ],
    "wof:name":"Live Oak Lodging",
    "wof:placetype":"venue"
},
  "geometry": {"coordinates":[-98.17844599999999,28.475189],"type":"Point"}
}