{
  "type": "Feature",
  "properties": {
    "iso:country":"US",
    "sg:address":"1631 McQueeney Rd",
    "sg:city":"New Braunfels",
    "sg:classifiers":[
        {
            "category":"Insurance",
            "subcategory":"Insurance Agent",
            "type":"Services"
        }
    ],
    "sg:phone":"+1 830 620 6077",
    "sg:postcode":"78130",
    "sg:province":"TX",
    "wof:name":"Allstate",
    "wof:placetype":"venue"
},
  "geometry": {"coordinates":[-98.114963,29.68803],"type":"Point"}
}