{
  "type": "Feature",
  "properties": {
    "iso:country":"US",
    "sg:address":"108 S 21st St",
    "sg:city":"Temple",
    "sg:classifiers":[
        {
            "category":"Building & Trades",
            "subcategory":"Landscaping Services",
            "type":"Services"
        }
    ],
    "sg:phone":"+1 254 770 0564",
    "sg:postcode":"76504",
    "sg:province":"TX",
    "sg:tags":[
        "mowing"
    ],
    "wof:name":"H & H Mowing",
    "wof:placetype":"venue"
},
  "geometry": {"coordinates":[-97.352684,31.097737],"type":"Point"}
}