{
  "type": "Feature",
  "properties": {
    "iso:country":"US",
    "sg:address":"401 N Mesquite St",
    "sg:city":"Pearsall",
    "sg:classifiers":[
        {
            "category":"Travel",
            "subcategory":"Campground",
            "type":"Entertainment"
        }
    ],
    "sg:phone":"+1 830 334 2431",
    "sg:postcode":"78061",
    "sg:province":"TX",
    "sg:tags":[
        "camp"
    ],
    "wof:name":"Sid J Williams",
    "wof:placetype":"venue"
},
  "geometry": {"coordinates":[-99.087659,28.894367],"type":"Point"}
}