{
  "type": "Feature",
  "properties": {
    "iso:country":"US",
    "sg:address":"3227 E Euless Blvd",
    "sg:city":"Euless",
    "sg:classifiers":[
        {
            "category":"Home & Garden",
            "subcategory":"Carpets & Floor Coverings",
            "type":"Retail Goods"
        }
    ],
    "sg:phone":"+1 817 868 1332",
    "sg:postcode":"76040",
    "sg:province":"TX",
    "sg:tags":[
        "blind",
        "mini"
    ],
    "wof:name":"Carpet Plus",
    "wof:placetype":"venue"
},
  "geometry": {"coordinates":[-97.13466099999999,32.816317],"type":"Point"}
}