{
  "type": "Feature",
  "properties": {
    "iso:country":"US",
    "sg:address":"3113 Pinewood Dr",
    "sg:city":"Garland",
    "sg:classifiers":[
        {
            "category":"Professional",
            "subcategory":"Business Services",
            "type":"Services"
        }
    ],
    "sg:phone":"+1 972 530 0626",
    "sg:postcode":"75044",
    "sg:province":"TX",
    "wof:name":"Clean N Clear Pool Service",
    "wof:placetype":"venue"
},
  "geometry": {"coordinates":[-96.675738,32.957652],"type":"Point"}
}