{
  "type": "Feature",
  "properties": {
    "iso:country":"US",
    "sg:address":"1004 NW 8th Pl",
    "sg:city":"Andrews",
    "sg:classifiers":[
        {
            "category":"Professional",
            "type":"Services"
        }
    ],
    "sg:phone":"+1 432 524 3109",
    "sg:postcode":"79714",
    "sg:province":"TX",
    "wof:name":"Colvin Enterprises",
    "wof:placetype":"venue"
},
  "geometry": {"coordinates":[-102.559912,32.327349],"type":"Point"}
}