{
  "type": "Feature",
  "properties": {
    "iso:country":"US",
    "sg:address":"2701 Yorkshire Dr",
    "sg:city":"Sherman",
    "sg:classifiers":[
        {
            "category":"Health Services",
            "subcategory":"Clinic",
            "type":"Services"
        }
    ],
    "sg:phone":"+1 903 892 4574",
    "sg:postcode":"75092",
    "sg:province":"TX",
    "sg:tags":[
        "agency",
        "welfare"
    ],
    "wof:name":"CIGNA Health Care",
    "wof:placetype":"venue"
},
  "geometry": {"coordinates":[-96.62821,33.661105],"type":"Point"}
}