{
  "type": "Feature",
  "properties": {
    "iso:country":"US",
    "sg:address":"3149 Southmost Rd",
    "sg:city":"Brownsville",
    "sg:classifiers":[
        {
            "category":"Food & Beverages",
            "subcategory":"Bakery",
            "type":"Retail Goods"
        }
    ],
    "sg:phone":"+1 956 982 2220",
    "sg:postcode":"78521",
    "sg:province":"TX",
    "sg:tags":[
        "baker"
    ],
    "wof:name":"Las Palmas Bakery",
    "wof:placetype":"venue"
},
  "geometry": {"coordinates":[-97.45976899999999,25.904971],"type":"Point"}
}