{
  "type": "Feature",
  "properties": {
    "iso:country":"US",
    "sg:address":"1005 W Little York Rd",
    "sg:city":"Houston",
    "sg:classifiers":[
        {
            "category":"Organizations",
            "subcategory":"Religious Organization",
            "type":"Services"
        }
    ],
    "sg:phone":"+1 713 694 7976",
    "sg:postcode":"77091",
    "sg:province":"TX",
    "sg:tags":[
        "church"
    ],
    "wof:name":"Highland Heights Church Christ",
    "wof:placetype":"venue"
},
  "geometry": {"coordinates":[-95.42612,29.86426],"type":"Point"}
}