{
  "type": "Feature",
  "properties": {
    "iso:country":"US",
    "sg:address":"3612 Dunvale Rd",
    "sg:city":"Houston",
    "sg:classifiers":[
        {
            "category":"Home & Garden",
            "subcategory":"Garden Supply",
            "type":"Retail Goods"
        }
    ],
    "sg:phone":"+1 713 334 1157",
    "sg:postcode":"77063",
    "sg:province":"TX",
    "sg:tags":[
        "equipment",
        "cleaning",
        "pressure"
    ],
    "sg:website":"http://www.texasstorm.com",
    "wof:name":"Texas Storm Of Houston",
    "wof:placetype":"venue"
},
  "geometry": {"coordinates":[-95.514028,29.726386],"type":"Point"}
}