{
  "type": "Feature",
  "properties": {
    "iso:country":"US",
    "sg:address":"513 Sycamore Ln",
    "sg:city":"Fort Worth",
    "sg:classifiers":[
        {
            "category":"Manufacturing",
            "subcategory":"Signs",
            "type":"Manufacturing & Wholesale Goods"
        }
    ],
    "sg:phone":"+1 682 286 9061",
    "sg:postcode":"76179",
    "sg:province":"TX",
    "sg:tags":[
        "specialty",
        "mfg"
    ],
    "wof:name":"Lewis H Lowe",
    "wof:placetype":"venue"
},
  "geometry": {"coordinates":[-97.38200000000001,32.864774],"type":"Point"}
}