{
  "type": "Feature",
  "properties": {
    "iso:country":"US",
    "sg:address":"9720 Beechnut St",
    "sg:city":"Houston",
    "sg:classifiers":[
        {
            "category":"Banks & Credit Unions",
            "subcategory":"Financial Services",
            "type":"Services"
        }
    ],
    "sg:phone":"+1 713 484 6400",
    "sg:postcode":"77036",
    "sg:province":"TX",
    "sg:tags":[
        "broker",
        "mortgage"
    ],
    "wof:name":"Mortgage Funding LLC",
    "wof:placetype":"venue"
},
  "geometry": {"coordinates":[-95.553431,29.689733],"type":"Point"}
}