{
  "type": "Feature",
  "properties": {
    "iso:country":"US",
    "sg:address":"4711 S Western St",
    "sg:city":"Amarillo",
    "sg:classifiers":[
        {
            "category":"Shopping",
            "subcategory":"Bicycles & Sporting Goods",
            "type":"Retail Goods"
        }
    ],
    "sg:phone":"+1 806 352 5201",
    "sg:postcode":"79109",
    "sg:province":"TX",
    "sg:tags":[
        "new",
        "used"
    ],
    "wof:name":"Play It Again Sports",
    "wof:placetype":"venue"
},
  "geometry": {"coordinates":[-101.883869,35.158826],"type":"Point"}
}