{
  "type": "Feature",
  "properties": {
    "iso:country":"US",
    "sg:address":"731 SE Military Dr",
    "sg:city":"San Antonio",
    "sg:classifiers":[
        {
            "category":"Autos & Motor Vehicles",
            "subcategory":"Automobile Sales",
            "type":"Retail Goods"
        }
    ],
    "sg:phone":"+1 210 928 3707",
    "sg:postcode":"78214",
    "sg:province":"TX",
    "sg:tags":[
        "car",
        "used",
        "dealer"
    ],
    "wof:name":"Mary's Motors",
    "wof:placetype":"venue"
},
  "geometry": {"coordinates":[-98.48843599999999,29.35672],"type":"Point"}
}