{
  "type": "Feature",
  "properties": {
    "iso:country":"US",
    "sg:address":"746 Sonora Ave",
    "sg:city":"Raymondville",
    "sg:classifiers":[
        {
            "category":"Organizations",
            "subcategory":"Religious Organization",
            "type":"Services"
        }
    ],
    "sg:phone":"+1 956 689 3297",
    "sg:postcode":"78580",
    "sg:province":"TX",
    "sg:tags":[
        "church"
    ],
    "wof:name":"Calvario Assembly Of God Chr",
    "wof:placetype":"venue"
},
  "geometry": {"coordinates":[-97.790733,26.490826],"type":"Point"}
}