{
  "type": "Feature",
  "properties": {
    "iso:country":"US",
    "sg:address":"1814 Pease St",
    "sg:city":"Vernon",
    "sg:classifiers":[
        {
            "category":"Shopping",
            "subcategory":"Discount & Variety Stores",
            "type":"Retail Goods"
        }
    ],
    "sg:phone":"+1 940 552 2146",
    "sg:postcode":"76384",
    "sg:province":"TX",
    "wof:name":"Dollar General",
    "wof:placetype":"venue"
},
  "geometry": {"coordinates":[-99.284603,34.153759],"type":"Point"}
}