{
  "type": "Feature",
  "properties": {
    "iso:country":"US",
    "sg:address":"6031 Pineland Dr",
    "sg:city":"Dallas",
    "sg:classifiers":[
        {
            "category":"Professional",
            "subcategory":"Lawyer & Legal Services",
            "type":"Services"
        }
    ],
    "sg:phone":"+1 214 363 0672",
    "sg:postcode":"75231",
    "sg:province":"TX",
    "wof:name":"Heart House",
    "wof:placetype":"venue"
},
  "geometry": {"coordinates":[-96.752848,32.873063],"type":"Point"}
}