{
  "type": "Feature",
  "properties": {
    "iso:country":"US",
    "sg:address":"8700 Cleaver Ln",
    "sg:city":"Terrell",
    "sg:classifiers":[
        {
            "category":"Wholesale",
            "subcategory":"Non-durable Goods",
            "type":"Manufacturing & Wholesale Goods"
        }
    ],
    "sg:phone":"+1 972 564 4105",
    "sg:postcode":"75160",
    "sg:province":"TX",
    "wof:name":"Wild West Trading Co",
    "wof:placetype":"venue"
},
  "geometry": {"coordinates":[-96.381604,32.691639],"type":"Point"}
}