{
  "type": "Feature",
  "properties": {
    "iso:country":"US",
    "sg:address":"11921 FM 2338",
    "sg:city":"Florence",
    "sg:classifiers":[
        {
            "category":"Professional",
            "subcategory":"Management & Consulting",
            "type":"Services"
        }
    ],
    "sg:phone":"+1 512 577 9066",
    "sg:postcode":"76527",
    "sg:province":"TX",
    "wof:name":"James Kennedy",
    "wof:placetype":"venue"
},
  "geometry": {"coordinates":[-97.8121,30.763937],"type":"Point"}
}