{
  "type": "Feature",
  "properties": {
    "iso:country":"US",
    "sg:address":"15206 Dawn Meadows Dr",
    "sg:city":"Houston",
    "sg:classifiers":[
        {
            "category":"Professional",
            "type":"Services"
        }
    ],
    "sg:phone":"+1 281 893 1957",
    "sg:postcode":"77068",
    "sg:province":"TX",
    "wof:name":"Ansaar Inc",
    "wof:placetype":"venue"
},
  "geometry": {"coordinates":[-95.488265,30.005277],"type":"Point"}
}