{
  "type": "Feature",
  "properties": {
    "iso:country":"US",
    "sg:address":"3924 Wymess Dr",
    "sg:city":"Garland",
    "sg:classifiers":[
        {
            "category":"Professional",
            "subcategory":"Business Services",
            "type":"Services"
        }
    ],
    "sg:phone":"+1 972 303 2931",
    "sg:postcode":"75043",
    "sg:province":"TX",
    "wof:name":"Victorias Enterprise",
    "wof:placetype":"venue"
},
  "geometry": {"coordinates":[-96.608532,32.863846],"type":"Point"}
}