{
  "type": "Feature",
  "properties": {
    "iso:country":"US",
    "sg:address":"15226 Ripplewind Ln",
    "sg:city":"Houston",
    "sg:classifiers":[
        {
            "category":"Professional",
            "subcategory":"Business Services",
            "type":"Services"
        }
    ],
    "sg:phone":"+1 281 866 0739",
    "sg:postcode":"77068",
    "sg:province":"TX",
    "wof:name":"Indefinite Solutions",
    "wof:placetype":"venue"
},
  "geometry": {"coordinates":[-95.488518,30.007068],"type":"Point"}
}