{
  "type": "Feature",
  "properties": {
    "iso:country":"US",
    "sg:address":"3050 Sentinal Butte",
    "sg:city":"Grapevine",
    "sg:classifiers":[
        {
            "category":"Professional",
            "subcategory":"Management & Consulting",
            "type":"Services"
        }
    ],
    "sg:phone":"+1 817 488 6023",
    "sg:postcode":"76051",
    "sg:province":"TX",
    "sg:tags":[
        "marketing",
        "consultant"
    ],
    "wof:name":"Front Line Sales & Mktg Inc",
    "wof:placetype":"venue"
},
  "geometry": {"coordinates":[-97.11444299999999,32.897442],"type":"Point"}
}