{
  "type": "Feature",
  "properties": {
    "iso:country":"US",
    "sg:address":"1999 E Mulberry St",
    "sg:city":"Angleton",
    "sg:classifiers":[
        {
            "category":"Shopping",
            "subcategory":"Clothing, Apparel, & Fashions",
            "type":"Retail Goods"
        }
    ],
    "sg:phone":"+1 979 864 4402",
    "sg:postcode":"77515",
    "sg:province":"TX",
    "sg:tags":[
        "equipment",
        "medical",
        "rent",
        "uniform"
    ],
    "wof:name":"Mediscript",
    "wof:placetype":"venue"
},
  "geometry": {"coordinates":[-95.41354200000001,29.176687],"type":"Point"}
}