{
  "type": "Feature",
  "properties": {
    "iso:country":"US",
    "sg:address":"6161 Savoy Dr Ste 801",
    "sg:city":"Houston",
    "sg:classifiers":[
        {
            "category":"Banks & Credit Unions",
            "subcategory":"Financial Services",
            "type":"Services"
        }
    ],
    "sg:phone":"+1 713 587 0088",
    "sg:postcode":"77036",
    "sg:province":"TX",
    "sg:tags":[
        "broker",
        "mortgage"
    ],
    "wof:name":"Lendata Resources",
    "wof:placetype":"venue"
},
  "geometry": {"coordinates":[-95.504553,29.716081],"type":"Point"}
}