{
  "type": "Feature",
  "properties": {
    "iso:country":"US",
    "sg:address":"403 FM 3013 W",
    "sg:city":"Eagle Lake",
    "sg:classifiers":[
        {
            "category":"Food & Beverages",
            "subcategory":"Groceries & Convenience Stores",
            "type":"Retail Goods"
        }
    ],
    "sg:phone":"+1 979 234 5223",
    "sg:postcode":"77434",
    "sg:province":"TX",
    "sg:tags":[
        "grocer"
    ],
    "wof:name":"D & V Town & Country Store",
    "wof:placetype":"venue"
},
  "geometry": {"coordinates":[-96.32204400000001,29.577502],"type":"Point"}
}