{
  "type": "Feature",
  "properties": {
    "iso:country":"US",
    "sg:address":"8226 Douglas Ave Ste 753",
    "sg:city":"Dallas",
    "sg:classifiers":[
        {
            "category":"Health Services",
            "subcategory":"Dentist",
            "type":"Services"
        }
    ],
    "sg:phone":"+1 214 368 2434",
    "sg:postcode":"75225",
    "sg:province":"TX",
    "wof:name":"Alhadef Gary E",
    "wof:placetype":"venue"
},
  "geometry": {"coordinates":[-96.808436,32.862811],"type":"Point"}
}