{
  "type": "Feature",
  "properties": {
    "iso:country":"US",
    "sg:address":"4718 Sea Island Dr",
    "sg:city":"Corpus Christi",
    "sg:classifiers":[
        {
            "category":"Health Services",
            "subcategory":"Doctor",
            "type":"Services"
        }
    ],
    "sg:phone":"+1 361 852 8708",
    "sg:postcode":"78413",
    "sg:province":"TX",
    "sg:tags":[
        "dentist"
    ],
    "wof:name":"W C Caldwell DDS",
    "wof:placetype":"venue"
},
  "geometry": {"coordinates":[-97.396869,27.696688],"type":"Point"}
}