{
  "type": "Feature",
  "properties": {
    "iso:country":"US",
    "sg:address":"4302 Blanco Rd",
    "sg:city":"San Antonio",
    "sg:classifiers":[
        {
            "category":"Manufacturing",
            "subcategory":"Signs",
            "type":"Manufacturing & Wholesale Goods"
        }
    ],
    "sg:phone":"+1 210 733 0190",
    "sg:postcode":"78212",
    "sg:province":"TX",
    "wof:name":"Ready Signs",
    "wof:placetype":"venue"
},
  "geometry": {"coordinates":[-98.50776,29.486821],"type":"Point"}
}