{
  "type": "Feature",
  "properties": {
    "iso:country":"US",
    "sg:address":"612 4th St N",
    "sg:city":"Texas City",
    "sg:classifiers":[
        {
            "category":"Restaurant",
            "type":"Food & Drink"
        }
    ],
    "sg:phone":"+1 409 938 3597",
    "sg:postcode":"77590",
    "sg:province":"TX",
    "sg:tags":[
        "eating"
    ],
    "wof:name":"Sonnys",
    "wof:placetype":"venue"
},
  "geometry": {"coordinates":[-94.899456,29.39085],"type":"Point"}
}