{
  "type": "Feature",
  "properties": {
    "iso:country":"US",
    "sg:address":"5010 Pinemont Dr",
    "sg:city":"Houston",
    "sg:classifiers":[
        {
            "category":"Wholesale",
            "subcategory":"Motor Vehicles",
            "type":"Manufacturing & Wholesale Goods"
        }
    ],
    "sg:phone":"+1 713 681 8283",
    "sg:postcode":"77092",
    "sg:province":"TX",
    "wof:name":"S L Auto",
    "wof:placetype":"venue"
},
  "geometry": {"coordinates":[-95.46687900000001,29.841043],"type":"Point"}
}