{
  "type": "Feature",
  "properties": {
    "iso:country":"US",
    "sg:address":"1004 N 9th St",
    "sg:city":"Alpine",
    "sg:classifiers":[
        {
            "category":"Manufacturing",
            "subcategory":"Buildings",
            "type":"Manufacturing & Wholesale Goods"
        },
        {
            "category":"Building & Trades",
            "subcategory":"Construction",
            "type":"Services"
        }
    ],
    "sg:phone":"+1 432 837 5629",
    "sg:postcode":"79830",
    "sg:province":"TX",
    "sg:tags":[
        "home",
        "builder",
        "contractor"
    ],
    "wof:name":"Hendryx Construction",
    "wof:placetype":"venue"
},
  "geometry": {"coordinates":[-103.66850100000001,30.363653],"type":"Point"}
}