{
  "type": "Feature",
  "properties": {
    "iso:country":"US",
    "sg:address":"6339 Beverlyhill St",
    "sg:city":"Houston",
    "sg:classifiers":[
        {
            "category":"Real Estate",
            "subcategory":"Real Estate Agent",
            "type":"Services"
        }
    ],
    "sg:phone":"+1 713 785 7572",
    "sg:postcode":"77057",
    "sg:province":"TX",
    "wof:name":"B M C Rental Properties",
    "wof:placetype":"venue"
},
  "geometry": {"coordinates":[-95.49506100000001,29.730476],"type":"Point"}
}