{
  "type": "Feature",
  "properties": {
    "iso:country":"US",
    "sg:address":"100 Hyline Dr",
    "sg:city":"Cleburne",
    "sg:classifiers":[
        {
            "category":"Building & Trades",
            "subcategory":"Construction",
            "type":"Services"
        }
    ],
    "sg:phone":"+1 817 558 8495",
    "sg:postcode":"76031",
    "sg:province":"TX",
    "sg:tags":[
        "system",
        "specialty",
        "heating",
        "contractor",
        "air conditioning"
    ],
    "wof:name":"Garners Temp Control",
    "wof:placetype":"venue"
},
  "geometry": {"coordinates":[-97.31944300000001,32.419922],"type":"Point"}
}