{
  "type": "Feature",
  "properties": {
    "iso:country":"US",
    "sg:address":"5317 Dora St",
    "sg:city":"Houston",
    "sg:classifiers":[
        {
            "category":"Wholesale",
            "subcategory":"Electrical",
            "type":"Manufacturing & Wholesale Goods"
        }
    ],
    "sg:phone":"+1 713 661 5656",
    "sg:postcode":"77005",
    "sg:province":"TX",
    "sg:tags":[
        "connector"
    ],
    "wof:name":"J A Davenport Co",
    "wof:placetype":"venue"
},
  "geometry": {"coordinates":[-95.39664500000001,29.723204],"type":"Point"}
}