{
  "type": "Feature",
  "properties": {
    "iso:country":"US",
    "sg:address":"800 George Bush Dr",
    "sg:city":"College Station",
    "sg:classifiers":[
        {
            "category":"Organizations",
            "subcategory":"Religious Organization",
            "type":"Services"
        }
    ],
    "sg:phone":"+1 979 696 7313",
    "sg:postcode":"77840",
    "sg:province":"TX",
    "sg:tags":[
        "synagogue"
    ],
    "wof:name":"Hillel Foundation-B'Nai B'Rith",
    "wof:placetype":"venue"
},
  "geometry": {"coordinates":[-96.33235500000001,30.610664],"type":"Point"}
}