{
  "type": "Feature",
  "properties": {
    "iso:country":"US",
    "sg:address":"9343 North Loop E",
    "sg:city":"Houston",
    "sg:classifiers":[
        {
            "category":"Local Transit",
            "type":"Transportation"
        }
    ],
    "sg:phone":"+1 832 369 9997",
    "sg:postcode":"77029",
    "sg:province":"TX",
    "sg:tags":[
        "shuttle",
        "public"
    ],
    "wof:name":"J T Loredo Shuttle Service",
    "wof:placetype":"venue"
},
  "geometry": {"coordinates":[-95.265754,29.788242],"type":"Point"}
}