{
  "type": "Feature",
  "properties": {
    "iso:country":"US",
    "sg:address":"1195 S Major Dr",
    "sg:city":"Beaumont",
    "sg:classifiers":[
        {
            "category":"Wholesale",
            "subcategory":"Electrical",
            "type":"Manufacturing & Wholesale Goods"
        }
    ],
    "sg:phone":"+1 409 866 8845",
    "sg:postcode":"77707",
    "sg:province":"TX",
    "sg:tags":[
        "sound",
        "equipment",
        "system"
    ],
    "sg:website":"www.mscsound.com",
    "wof:name":"Msc Systems",
    "wof:placetype":"venue"
},
  "geometry": {"coordinates":[-94.189464,30.059858],"type":"Point"}
}