{
  "type": "Feature",
  "properties": {
    "iso:country":"US",
    "sg:address":"6000 Messenger Stakes",
    "sg:city":"Austin",
    "sg:classifiers":[
        {
            "category":"Building & Trades",
            "subcategory":"Construction",
            "type":"Services"
        }
    ],
    "sg:phone":"+1 512 327 3030",
    "sg:postcode":"78746",
    "sg:province":"TX",
    "sg:tags":[
        "contractor"
    ],
    "wof:name":"Magnum Drywall Co Inc",
    "wof:placetype":"venue"
},
  "geometry": {"coordinates":[-97.801473,30.338604],"type":"Point"}
}