{
  "type": "Feature",
  "properties": {
    "iso:country":"US",
    "sg:address":"101 Saint Joseph St",
    "sg:city":"Palacios",
    "sg:classifiers":[
        {
            "category":"Autos & Motor Vehicles",
            "subcategory":"Boat Sales",
            "type":"Retail Goods"
        }
    ],
    "sg:phone":"+1 361 972 3478",
    "sg:postcode":"77465",
    "sg:province":"TX",
    "sg:tags":[
        "equipment",
        "marine",
        "supply"
    ],
    "wof:name":"Lynn's Marine Supplies",
    "wof:placetype":"venue"
},
  "geometry": {"coordinates":[-96.210251,28.731659],"type":"Point"}
}