{
  "type": "Feature",
  "properties": {
    "iso:country":"US",
    "sg:address":"3850 Bethel Rd",
    "sg:city":"Weatherford",
    "sg:classifiers":[
        {
            "category":"Professional",
            "subcategory":"Detective & Security Services",
            "type":"Services"
        }
    ],
    "sg:phone":"+1 817 594 2948",
    "sg:postcode":"76087",
    "sg:province":"TX",
    "sg:tags":[
        "information",
        "bureau"
    ],
    "wof:name":"C O Welch Land Services",
    "wof:placetype":"venue"
},
  "geometry": {"coordinates":[-97.830466,32.679816],"type":"Point"}
}