{
  "type": "Feature",
  "properties": {
    "iso:country":"US",
    "sg:address":"300 Asbury Cir",
    "sg:city":"Euless",
    "sg:classifiers":[
        {
            "category":"Professional",
            "subcategory":"Business Services",
            "type":"Services"
        }
    ],
    "sg:phone":"+1 817 858 9772",
    "sg:postcode":"76039",
    "sg:province":"TX",
    "wof:name":"Vineyard Group",
    "wof:placetype":"venue"
},
  "geometry": {"coordinates":[-97.07755,32.841436],"type":"Point"}
}