{
  "type": "Feature",
  "properties": {
    "iso:country":"US",
    "sg:address":"1800 Teague Dr",
    "sg:city":"Sherman",
    "sg:classifiers":[
        {
            "category":"Professional",
            "subcategory":"Accounting & Tax Preparation",
            "type":"Services"
        }
    ],
    "sg:phone":"+1 903 893 0041",
    "sg:postcode":"75090",
    "sg:province":"TX",
    "sg:tags":[
        "accountant"
    ],
    "wof:name":"Dale W Garner CPA",
    "wof:placetype":"venue"
},
  "geometry": {"coordinates":[-96.599915,33.657401],"type":"Point"}
}