{
  "type": "Feature",
  "properties": {
    "iso:country":"US",
    "sg:address":"10206 Homestead Rd",
    "sg:city":"Houston",
    "sg:classifiers":[
        {
            "category":"Social Services",
            "subcategory":"Child Care",
            "type":"Services"
        }
    ],
    "sg:phone":"+1 281 449 2828",
    "sg:postcode":"77016",
    "sg:province":"TX",
    "wof:name":"Boys To Men",
    "wof:placetype":"venue"
},
  "geometry": {"coordinates":[-95.300444,29.859092],"type":"Point"}
}