{
  "type": "Feature",
  "properties": {
    "iso:country":"US",
    "sg:address":"5025 N Central Expy",
    "sg:city":"Dallas",
    "sg:classifiers":[
        {
            "category":"Real Estate",
            "subcategory":"Real Estate Services",
            "type":"Services"
        }
    ],
    "sg:phone":"+1 214 526 6269",
    "sg:postcode":"75205",
    "sg:province":"TX",
    "wof:name":"Thomas Robert Howe rltr",
    "wof:placetype":"venue"
},
  "geometry": {"coordinates":[-96.78376799999999,32.827655],"type":"Point"}
}