{
  "type": "Feature",
  "properties": {
    "iso:country":"US",
    "sg:address":"9522 Chelmsford",
    "sg:city":"San Antonio",
    "sg:classifiers":[
        {
            "category":"Building & Trades",
            "subcategory":"Construction",
            "type":"Services"
        }
    ],
    "sg:phone":"+1 210 590 0428",
    "sg:postcode":"78239",
    "sg:province":"TX",
    "sg:tags":[
        "contractor"
    ],
    "wof:name":"Elmore & Sons Drywall",
    "wof:placetype":"venue"
},
  "geometry": {"coordinates":[-98.351619,29.52341],"type":"Point"}
}