{
  "type": "Feature",
  "properties": {
    "iso:country":"US",
    "sg:address":"1401 Rosewood Ave",
    "sg:city":"Austin",
    "sg:classifiers":[
        {
            "category":"Restaurant",
            "type":"Food & Drink"
        }
    ],
    "sg:phone":"+1 512 322 9777",
    "sg:postcode":"78702",
    "sg:province":"TX",
    "wof:name":"Fish R Us",
    "wof:placetype":"venue"
},
  "geometry": {"coordinates":[-97.72371,30.268964],"type":"Point"}
}