{
  "type": "Feature",
  "properties": {
    "iso:country":"US",
    "sg:address":"901 N Goliad St",
    "sg:city":"Alice",
    "sg:classifiers":[
        {
            "category":"Wholesale",
            "subcategory":"Petroleum",
            "type":"Manufacturing & Wholesale Goods"
        }
    ],
    "sg:phone":"+1 361 664 6381",
    "sg:postcode":"78332",
    "sg:province":"TX",
    "sg:tags":[
        "pipe",
        "line",
        "company"
    ],
    "wof:name":"Exxon Mobil Pipeline Co",
    "wof:placetype":"venue"
},
  "geometry": {"coordinates":[-98.08623299999999,27.759942],"type":"Point"}
}