{
  "type": "Feature",
  "properties": {
    "iso:country":"US",
    "sg:address":"5445 Almeda Rd",
    "sg:city":"Houston",
    "sg:classifiers":[
        {
            "category":"Shopping",
            "subcategory":"Music",
            "type":"Retail Goods"
        }
    ],
    "sg:phone":"+1 713 942 9669",
    "sg:postcode":"77004",
    "sg:province":"TX",
    "wof:name":"Rythm & Rhyme Records",
    "wof:placetype":"venue"
},
  "geometry": {"coordinates":[-95.37923000000001,29.721241],"type":"Point"}
}