{
  "type": "Feature",
  "properties": {
    "iso:country":"US",
    "sg:address":"1809 Shenandoah Dr",
    "sg:city":"Euless",
    "sg:classifiers":[
        {
            "category":"Health Services",
            "subcategory":"Doctor",
            "type":"Services"
        }
    ],
    "sg:phone":"+1 817 267 0747",
    "sg:postcode":"76039",
    "sg:province":"TX",
    "sg:tags":[
        "osteopathic"
    ],
    "wof:name":"Eugene F Dunham Od",
    "wof:placetype":"venue"
},
  "geometry": {"coordinates":[-97.08737600000001,32.865388],"type":"Point"}
}