{
  "type": "Feature",
  "properties": {
    "iso:country":"US",
    "sg:address":"440 N Mehnert St",
    "sg:city":"Yorktown",
    "sg:classifiers":[
        {
            "category":"Food & Beverages",
            "subcategory":"Groceries & Convenience Stores",
            "type":"Retail Goods"
        }
    ],
    "sg:phone":"+1 361 564 4294",
    "sg:postcode":"78164",
    "sg:province":"TX",
    "wof:name":"A&L One Stop Grocery 2",
    "wof:placetype":"venue"
},
  "geometry": {"coordinates":[-97.510868,28.985048],"type":"Point"}
}