{
  "type": "Feature",
  "properties": {
    "iso:country":"US",
    "sg:address":"3130 Walnut Bend Ln",
    "sg:city":"Houston",
    "sg:classifiers":[
        {
            "category":"Building & Trades",
            "subcategory":"Plumbing",
            "type":"Services"
        }
    ],
    "sg:phone":"+1 713 780 9227",
    "sg:postcode":"77042",
    "sg:province":"TX",
    "sg:tags":[
        "plumbing",
        "contractor"
    ],
    "wof:name":"PAR Plumbing",
    "wof:placetype":"venue"
},
  "geometry": {"coordinates":[-95.568034,29.728894],"type":"Point"}
}