{
  "type": "Feature",
  "properties": {
    "iso:country":"US",
    "sg:address":"1407 E Belt Line Rd",
    "sg:city":"Richardson",
    "sg:classifiers":[
        {
            "category":"Banks & Credit Unions",
            "subcategory":"Bank",
            "type":"Services"
        }
    ],
    "sg:phone":"+1 972 235 4571",
    "sg:postcode":"75081",
    "sg:province":"TX",
    "sg:tags":[
        "federal",
        "savings",
        "institution"
    ],
    "wof:name":"Guaranty Bank",
    "wof:placetype":"venue"
},
  "geometry": {"coordinates":[-96.69994699999999,32.945321],"type":"Point"}
}