{
  "type": "Feature",
  "properties": {
    "iso:country":"US",
    "sg:address":"4002 Stonecroft Dr",
    "sg:city":"Austin",
    "sg:classifiers":[
        {
            "category":"Building & Trades",
            "subcategory":"Electrical",
            "type":"Services"
        }
    ],
    "sg:phone":"+1 512 326 1583",
    "sg:postcode":"78749",
    "sg:province":"TX",
    "sg:tags":[
        "electrician"
    ],
    "wof:name":"Reyna Electric",
    "wof:placetype":"venue"
},
  "geometry": {"coordinates":[-97.841795,30.209061],"type":"Point"}
}