{
  "type": "Feature",
  "properties": {
    "iso:country":"US",
    "sg:address":"8205 Martin L King Blvd",
    "sg:city":"Lubbock",
    "sg:classifiers":[
        {
            "category":"Retail",
            "subcategory":"Repair Shop",
            "type":"Services"
        }
    ],
    "sg:phone":"+1 806 745 9313",
    "sg:postcode":"79404",
    "sg:province":"TX",
    "sg:tags":[
        "taxidermist"
    ],
    "wof:name":"All Star Taxidermy",
    "wof:placetype":"venue"
},
  "geometry": {"coordinates":[-101.81835,33.5216],"type":"Point"}
}