{
  "type": "Feature",
  "properties": {
    "iso:country":"US",
    "sg:address":"1475 Greg Rd",
    "sg:city":"El Paso",
    "sg:classifiers":[
        {
            "category":"Restaurant",
            "type":"Food & Drink"
        }
    ],
    "sg:phone":"+1 915 633 6175",
    "sg:postcode":"79938",
    "sg:province":"TX",
    "sg:tags":[
        "eating"
    ],
    "wof:name":"El Ciros",
    "wof:placetype":"venue"
},
  "geometry": {"coordinates":[-106.18480700000001,31.798242],"type":"Point"}
}