{
  "type": "Feature",
  "properties": {
    "iso:country":"US",
    "sg:address":"6051 Azle Ave",
    "sg:city":"Fort Worth",
    "sg:classifiers":[
        {
            "category":"Organizations",
            "subcategory":"Religious Organization",
            "type":"Services"
        }
    ],
    "sg:phone":"+1 817 237 2201",
    "sg:postcode":"76135",
    "sg:province":"TX",
    "wof:name":"Metropolitan Baptist Church",
    "wof:placetype":"venue"
},
  "geometry": {"coordinates":[-97.417259,32.814747],"type":"Point"}
}