{
  "type": "Feature",
  "properties": {
    "iso:country":"US",
    "sg:address":"16200 E Lake Shore Dr",
    "sg:city":"Austin",
    "sg:classifiers":[
        {
            "category":"Real Estate",
            "subcategory":"Real Estate Agent",
            "type":"Services"
        }
    ],
    "sg:phone":"+1 512 266 0592",
    "sg:postcode":"78734",
    "sg:province":"TX",
    "wof:name":"Est Of Nascent Solutions C",
    "wof:placetype":"venue"
},
  "geometry": {"coordinates":[-97.924629,30.428619],"type":"Point"}
}