{
  "type": "Feature",
  "properties": {
    "iso:country":"US",
    "sg:address":"13202 Vacek St",
    "sg:city":"Santa Fe",
    "sg:classifiers":[
        {
            "category":"Shopping",
            "subcategory":"Discount & Variety Stores",
            "type":"Retail Goods"
        },
        {
            "category":"Farming",
            "subcategory":"Livestock Farm",
            "type":"Manufacturing & Wholesale Goods"
        }
    ],
    "sg:phone":"+1 409 925 2457",
    "sg:postcode":"77517",
    "sg:province":"TX",
    "sg:tags":[
        "beef",
        "general",
        "refrigeration",
        "feedlot",
        "cattle",
        "merchandise"
    ],
    "wof:name":"Dazey Farm's",
    "wof:placetype":"venue"
},
  "geometry": {"coordinates":[-95.116839,29.32894],"type":"Point"}
}