{
  "type": "Feature",
  "properties": {
    "iso:country":"US",
    "sg:address":"1800 W Broadway St",
    "sg:city":"Sweetwater",
    "sg:classifiers":[
        {
            "category":"Utilities",
            "subcategory":"Fuel Oil & Lpg",
            "type":"Services"
        }
    ],
    "sg:phone":"+1 325 235 8606",
    "sg:postcode":"79556",
    "sg:province":"TX",
    "sg:tags":[
        "propane",
        "gas"
    ],
    "wof:name":"West Texas Gas Inc",
    "wof:placetype":"venue"
},
  "geometry": {"coordinates":[-100.43762700000001,32.459989],"type":"Point"}
}