{
  "type": "Feature",
  "properties": {
    "iso:country":"US",
    "sg:address":"6515 Ave B",
    "sg:city":"Houston",
    "sg:classifiers":[
        {
            "category":"Autos & Motor Vehicles",
            "subcategory":"Auto Supplies",
            "type":"Retail Goods"
        }
    ],
    "sg:phone":"+1 713 926 7273",
    "sg:postcode":"77011",
    "sg:province":"TX",
    "sg:tags":[
        "filter",
        "gas"
    ],
    "wof:name":"Air Filter",
    "wof:placetype":"venue"
},
  "geometry": {"coordinates":[-95.310012,29.739165],"type":"Point"}
}