{
  "type": "Feature",
  "properties": {
    "iso:country":"US",
    "sg:address":"3713 Temecula Creek Trl",
    "sg:city":"Mckinney",
    "sg:classifiers":[
        {
            "category":"Real Estate",
            "subcategory":"Real Estate Services",
            "type":"Services"
        },
        {
            "category":"Home & Garden",
            "subcategory":"Building Materials",
            "type":"Retail Goods"
        },
        {
            "category":"Building & Trades",
            "subcategory":"Construction",
            "type":"Services"
        }
    ],
    "sg:phone":"+1 972 248 9137",
    "sg:postcode":"75070",
    "sg:province":"TX",
    "sg:tags":[
        "roofing",
        "industrial",
        "consultant",
        "contractor",
        "contractors-commercial",
        "maintenance",
        "improvement"
    ],
    "sg:website":"http://www.DynRoofing.com",
    "wof:name":"Dynamic Roofing",
    "wof:placetype":"venue"
},
  "geometry": {"coordinates":[-96.71735200000001,33.161817],"type":"Point"}
}