{
  "type": "Feature",
  "properties": {
    "iso:country":"US",
    "sg:address":"1004 Pin Oak Dr",
    "sg:city":"Belton",
    "sg:classifiers":[
        {
            "category":"Professional",
            "type":"Services"
        }
    ],
    "sg:phone":"+1 254 933 3922",
    "sg:postcode":"76513",
    "sg:province":"TX",
    "wof:name":"H O T Distribution Services",
    "wof:placetype":"venue"
},
  "geometry": {"coordinates":[-97.47193300000001,31.092234],"type":"Point"}
}