{
  "type": "Feature",
  "properties": {
    "iso:country":"US",
    "sg:address":"605 Riva Ridge Dr",
    "sg:city":"Leander",
    "sg:classifiers":[
        {
            "category":"Social Services",
            "subcategory":"Child Care",
            "type":"Services"
        }
    ],
    "sg:phone":"+1 512 259 3652",
    "sg:postcode":"78641",
    "sg:province":"TX",
    "sg:tags":[
        "day"
    ],
    "wof:name":"Jaimers Inc",
    "wof:placetype":"venue"
},
  "geometry": {"coordinates":[-97.86019899999999,30.615692],"type":"Point"}
}