{
  "type": "Feature",
  "properties": {
    "iso:country":"US",
    "sg:address":"306 W Wall St",
    "sg:city":"Midland",
    "sg:classifiers":[
        {
            "category":"Professional",
            "subcategory":"Management & Consulting",
            "type":"Services"
        }
    ],
    "sg:phone":"+1 432 617 0230",
    "sg:postcode":"79701",
    "sg:province":"TX",
    "wof:name":"Clary Asset Management LLC",
    "wof:placetype":"venue"
},
  "geometry": {"coordinates":[-102.077994,31.997509],"type":"Point"}
}