{
  "type": "Feature",
  "properties": {
    "iso:country":"US",
    "sg:address":"1213 Brush Creek Dr",
    "sg:city":"Richardson",
    "sg:classifiers":[
        {
            "category":"Shopping",
            "subcategory":"Used Merchandise",
            "type":"Retail Goods"
        }
    ],
    "sg:phone":"+1 972 644 7708",
    "sg:postcode":"75081",
    "sg:province":"TX",
    "wof:name":"US Texas Antique Inc",
    "wof:placetype":"venue"
},
  "geometry": {"coordinates":[-96.682783,32.962729],"type":"Point"}
}