{
  "type": "Feature",
  "properties": {
    "iso:country":"US",
    "sg:address":"877 7th St",
    "sg:city":"Cushing",
    "sg:classifiers":[
        {
            "category":"Banks & Credit Unions",
            "subcategory":"Bank",
            "type":"Services"
        }
    ],
    "sg:phone":"+1 936 326 4261",
    "sg:postcode":"75760",
    "sg:province":"TX",
    "sg:tags":[
        "saving",
        "commercial"
    ],
    "sg:website":"http://www.texasbankandtrust.com",
    "wof:name":"Cushing Banking Center",
    "wof:placetype":"venue"
},
  "geometry": {"coordinates":[-94.841089,31.815271],"type":"Point"}
}