{
  "type": "Feature",
  "properties": {
    "iso:country":"US",
    "sg:address":"120 Country Lane Dr",
    "sg:city":"Lumberton",
    "sg:classifiers":[
        {
            "category":"Health Services",
            "subcategory":"Dentist",
            "type":"Services"
        }
    ],
    "sg:phone":"+1 409 755 4444",
    "sg:postcode":"77657",
    "sg:province":"TX",
    "sg:tags":[
        "dentists-oral",
        "product",
        "dentists-cosmetic",
        "maxillofacial",
        "denture",
        "dentists-prosthodontists",
        "dentistry",
        "whitening",
        "teeth",
        "surgery"
    ],
    "wof:name":"Lumberton Dental Center PA",
    "wof:placetype":"venue"
},
  "geometry": {"coordinates":[-94.198452,30.24283],"type":"Point"}
}