{
  "type": "Feature",
  "properties": {
    "iso:country":"US",
    "sg:address":"1903 Laurel Hill Dr",
    "sg:city":"Humble",
    "sg:classifiers":[
        {
            "category":"Education",
            "subcategory":"School",
            "type":"Public Place"
        }
    ],
    "sg:phone":"+1 281 358 8844",
    "sg:postcode":"77339",
    "sg:province":"TX",
    "wof:name":"Cybortex",
    "wof:placetype":"venue"
},
  "geometry": {"coordinates":[-95.223558,30.048854],"type":"Point"}
}