{
  "type": "Feature",
  "properties": {
    "iso:country":"US",
    "sg:address":"2290 State Hwy 6",
    "sg:city":"Houston",
    "sg:classifiers":[
        {
            "category":"Home & Garden",
            "subcategory":"Furniture",
            "type":"Retail Goods"
        }
    ],
    "sg:phone":"+1 281 293 9077",
    "sg:postcode":"77077",
    "sg:province":"TX",
    "sg:tags":[
        "mattress"
    ],
    "wof:name":"Mattress Giant",
    "wof:placetype":"venue"
},
  "geometry": {"coordinates":[-95.644203,29.738955],"type":"Point"}
}