{
  "type": "Feature",
  "properties": {
    "iso:country":"US",
    "sg:address":"1101 Sycamore Ave",
    "sg:city":"Huntsville",
    "sg:classifiers":[
        {
            "category":"Food & Beverages",
            "subcategory":"Groceries & Convenience Stores",
            "type":"Retail Goods"
        }
    ],
    "sg:phone":"+1 936 291 3241",
    "sg:postcode":"77340",
    "sg:province":"TX",
    "wof:name":"Zipps Food Mart",
    "wof:placetype":"venue"
},
  "geometry": {"coordinates":[-95.540413,30.723723],"type":"Point"}
}