{
  "type": "Feature",
  "properties": {
    "iso:country":"US",
    "sg:address":"3220 North Fwy",
    "sg:city":"Fort Worth",
    "sg:classifiers":[
        {
            "category":"Professional",
            "subcategory":"Management & Consulting",
            "type":"Services"
        }
    ],
    "sg:phone":"+1 817 625 9396",
    "sg:postcode":"76111",
    "sg:province":"TX",
    "sg:tags":[
        "business"
    ],
    "wof:name":"John L Anderson",
    "wof:placetype":"venue"
},
  "geometry": {"coordinates":[-97.318253,32.802709],"type":"Point"}
}