{
  "type": "Feature",
  "properties": {
    "iso:country":"US",
    "sg:address":"1359 Baybrook Mall",
    "sg:city":"Friendswood",
    "sg:classifiers":[
        {
            "category":"Shopping",
            "subcategory":"Jewelry",
            "type":"Retail Goods"
        }
    ],
    "sg:phone":"+1 281 461 4033",
    "sg:postcode":"77546",
    "sg:province":"TX",
    "sg:tags":[
        "watch"
    ],
    "wof:name":"Watch World Intl",
    "wof:placetype":"venue"
},
  "geometry": {"coordinates":[-95.151799,29.543565],"type":"Point"}
}