{
  "type": "Feature",
  "properties": {
    "iso:country":"US",
    "sg:address":"2125 109th St",
    "sg:city":"Grand Prairie",
    "sg:classifiers":[
        {
            "category":"Building & Trades",
            "subcategory":"Electrical",
            "type":"Services"
        }
    ],
    "sg:phone":"+1 972 263 4072",
    "sg:postcode":"75050",
    "sg:province":"TX",
    "sg:tags":[
        "electric",
        "contractor"
    ],
    "wof:name":"Pro Tech Inc",
    "wof:placetype":"venue"
},
  "geometry": {"coordinates":[-97.053026,32.786854],"type":"Point"}
}