{
  "type": "Feature",
  "properties": {
    "iso:country":"US",
    "sg:address":"3800 Lake Rd",
    "sg:city":"Killeen",
    "sg:classifiers":[
        {
            "category":"Retail",
            "subcategory":"Funeral Services",
            "type":"Services"
        }
    ],
    "sg:phone":"+1 254 634 0575",
    "sg:postcode":"76543",
    "sg:province":"TX",
    "sg:tags":[
        "director"
    ],
    "sg:website":"www.killeenmemorialpark.com",
    "wof:name":"Killeen Memorial Funeral Home",
    "wof:placetype":"venue"
},
  "geometry": {"coordinates":[-97.688441,31.121762],"type":"Point"}
}