{
  "type": "Feature",
  "properties": {
    "iso:country":"US",
    "sg:address":"3626 N Hall St",
    "sg:city":"Dallas",
    "sg:classifiers":[
        {
            "category":"Wholesale",
            "subcategory":"Hardware",
            "type":"Manufacturing & Wholesale Goods"
        }
    ],
    "sg:phone":"+1 214 520 0517",
    "sg:postcode":"75219",
    "sg:province":"TX",
    "sg:tags":[
        "tool"
    ],
    "wof:name":"Pinpoint Tools",
    "wof:placetype":"venue"
},
  "geometry": {"coordinates":[-96.80628900000001,32.809184],"type":"Point"}
}