{
  "type": "Feature",
  "properties": {
    "iso:country":"US",
    "sg:address":"15810 Park Ten Pl",
    "sg:city":"Houston",
    "sg:classifiers":[
        {
            "category":"Insurance",
            "subcategory":"Insurance Agent",
            "type":"Services"
        }
    ],
    "sg:phone":"+1 281 492 2626",
    "sg:postcode":"77084",
    "sg:province":"TX",
    "wof:name":"Allstate Insurance",
    "wof:placetype":"venue"
},
  "geometry": {"coordinates":[-95.658376,29.786747],"type":"Point"}
}