{
  "type": "Feature",
  "properties": {
    "iso:country":"US",
    "sg:address":"2016 Co Rd 220",
    "sg:city":"Angleton",
    "sg:classifiers":[
        {
            "category":"Recreation",
            "type":"Entertainment"
        }
    ],
    "sg:phone":"+1 979 849 2984",
    "sg:postcode":"77515",
    "sg:province":"TX",
    "sg:tags":[
        "range",
        "practice",
        "golf"
    ],
    "wof:name":"Double Eagle Golf Practice",
    "wof:placetype":"venue"
},
  "geometry": {"coordinates":[-95.41280500000001,29.119448],"type":"Point"}
}