{
  "type": "Feature",
  "properties": {
    "iso:country":"US",
    "sg:address":"3316 Fondren Rd",
    "sg:city":"Houston",
    "sg:classifiers":[
        {
            "category":"Home & Garden",
            "subcategory":"Home Furnishings",
            "type":"Retail Goods"
        }
    ],
    "sg:phone":"+1 713 914 9724",
    "sg:postcode":"77063",
    "sg:province":"TX",
    "sg:tags":[
        "equipment",
        "fixture",
        "lighting"
    ],
    "wof:name":"Chandlier International Inc",
    "wof:placetype":"venue"
},
  "geometry": {"coordinates":[-95.520798,29.728701],"type":"Point"}
}