{
  "type": "Feature",
  "properties": {
    "iso:country":"US",
    "sg:address":"3015 E 19th St",
    "sg:city":"Texarkana",
    "sg:classifiers":[
        {
            "category":"Social Services",
            "subcategory":"Job Training",
            "type":"Services"
        }
    ],
    "sg:phone":"+1 870 774 9675",
    "sg:postcode":"71854",
    "sg:province":"TX",
    "sg:tags":[
        "rehabilitation"
    ],
    "wof:name":"Texarkana Resources-Disabled",
    "wof:placetype":"venue"
},
  "geometry": {"coordinates":[-94.00842799999999,33.44063],"type":"Point"}
}