{
  "type": "Feature",
  "properties": {
    "iso:country":"US",
    "sg:address":"639 Riding Club Rd",
    "sg:city":"Rockwall",
    "sg:classifiers":[
        {
            "category":"Home & Garden",
            "subcategory":"Mobile Homes",
            "type":"Retail Goods"
        }
    ],
    "sg:phone":"+1 972 722 2807",
    "sg:postcode":"75087",
    "sg:province":"TX",
    "wof:name":"Nash Construction",
    "wof:placetype":"venue"
},
  "geometry": {"coordinates":[-96.409667,32.926469],"type":"Point"}
}