{
  "type": "Feature",
  "properties": {
    "iso:country":"US",
    "sg:address":"1102 Paul Quinn St",
    "sg:city":"Waco",
    "sg:classifiers":[
        {
            "category":"Education",
            "subcategory":"School",
            "type":"Public Place"
        }
    ],
    "sg:phone":"+1 254 753 1362",
    "sg:postcode":"76704",
    "sg:province":"TX",
    "wof:name":"J H Hines Elementary School",
    "wof:placetype":"venue"
},
  "geometry": {"coordinates":[-97.119969,31.573753],"type":"Point"}
}