{
  "type": "Feature",
  "properties": {
    "iso:country":"US",
    "sg:address":"207 Ave A S",
    "sg:city":"Farwell",
    "sg:classifiers":[
        {
            "category":"Professional",
            "type":"Services"
        },
        {
            "category":"Personal",
            "subcategory":"Beauty Salon",
            "type":"Services"
        }
    ],
    "sg:phone":"+1 806 481 2768",
    "sg:postcode":"79325",
    "sg:province":"TX",
    "wof:name":"New You",
    "wof:placetype":"venue"
},
  "geometry": {"coordinates":[-103.041586,34.388662],"type":"Point"}
}