{
  "type": "Feature",
  "properties": {
    "iso:country":"US",
    "sg:address":"12402 Waterton Parke Cir",
    "sg:city":"Austin",
    "sg:classifiers":[
        {
            "category":"Building & Trades",
            "subcategory":"Construction",
            "type":"Services"
        }
    ],
    "sg:phone":"+1 512 918 3136",
    "sg:postcode":"78726",
    "sg:province":"TX",
    "sg:tags":[
        "contractor"
    ],
    "wof:name":"McElderry Builders-Drywall",
    "wof:placetype":"venue"
},
  "geometry": {"coordinates":[-97.85975000000001,30.419899],"type":"Point"}
}