{
  "type": "Feature",
  "properties": {
    "iso:country":"US",
    "sg:address":"1105 Wake Dr",
    "sg:city":"Richardson",
    "sg:classifiers":[
        {
            "category":"Professional",
            "subcategory":"Business Services",
            "type":"Services"
        }
    ],
    "sg:phone":"+1 972 234 4896",
    "sg:postcode":"75081",
    "sg:province":"TX",
    "wof:name":"Lines Designs",
    "wof:placetype":"venue"
},
  "geometry": {"coordinates":[-96.705145,32.947724],"type":"Point"}
}