{
  "type": "Feature",
  "properties": {
    "iso:country":"US",
    "sg:address":"945 Palma Sola Dr",
    "sg:city":"El Paso",
    "sg:classifiers":[
        {
            "category":"Retail",
            "subcategory":"Repair Shop",
            "type":"Services"
        }
    ],
    "sg:phone":"+1 915 592 8833",
    "sg:postcode":"79907",
    "sg:province":"TX",
    "wof:name":"Richards TV Service Co",
    "wof:placetype":"venue"
},
  "geometry": {"coordinates":[-106.30602,31.7019],"type":"Point"}
}