{
  "type": "Feature",
  "properties": {
    "iso:country":"US",
    "sg:address":"2415 Willow Lake Dr",
    "sg:city":"Houston",
    "sg:classifiers":[
        {
            "category":"Professional",
            "subcategory":"Business Services",
            "type":"Services"
        }
    ],
    "sg:phone":"+1 281 870 0987",
    "sg:postcode":"77077",
    "sg:province":"TX",
    "wof:name":"Interior Works",
    "wof:placetype":"venue"
},
  "geometry": {"coordinates":[-95.59459099999999,29.738613],"type":"Point"}
}