{
  "type": "Feature",
  "properties": {
    "iso:country":"US",
    "sg:address":"1200 Binz St",
    "sg:city":"Houston",
    "sg:classifiers":[
        {
            "category":"Professional",
            "subcategory":"Lawyer & Legal Services",
            "type":"Services"
        }
    ],
    "sg:phone":"+1 713 523 5052",
    "sg:postcode":"77004",
    "sg:province":"TX",
    "wof:name":"Sponsel Thane T Jr Atty",
    "wof:placetype":"venue"
},
  "geometry": {"coordinates":[-95.38690200000001,29.7243],"type":"Point"}
}