{
  "type": "Feature",
  "properties": {
    "iso:country":"US",
    "sg:address":"2206 Johnson St",
    "sg:city":"Big Spring",
    "sg:classifiers":[
        {
            "category":"Organizations",
            "subcategory":"Religious Organization",
            "type":"Services"
        }
    ],
    "sg:phone":"+1 432 263 1188",
    "sg:postcode":"79720",
    "sg:province":"TX",
    "wof:name":"Jehovahs Witnesses",
    "wof:placetype":"venue"
},
  "geometry": {"coordinates":[-101.46679399999999,32.234199],"type":"Point"}
}