{
  "type": "Feature",
  "properties": {
    "iso:country":"US",
    "sg:address":"1421 E Pike Blvd",
    "sg:city":"Weslaco",
    "sg:classifiers":[
        {
            "category":"Shopping",
            "subcategory":"Computers & Home Electronics",
            "type":"Retail Goods"
        }
    ],
    "sg:phone":"+1 956 447 8440",
    "sg:postcode":"78596",
    "sg:province":"TX",
    "sg:tags":[
        "parts",
        "electronic"
    ],
    "wof:name":"Tri-County Communications LTD",
    "wof:placetype":"venue"
},
  "geometry": {"coordinates":[-97.97769700000001,26.170237],"type":"Point"}
}