{
  "type": "Feature",
  "properties": {
    "iso:country":"US",
    "sg:address":"413 Shiloh Rd",
    "sg:city":"Tyler",
    "sg:classifiers":[
        {
            "category":"Retail",
            "subcategory":"Laundry & Dry Cleaning",
            "type":"Services"
        }
    ],
    "sg:phone":"+1 903 567 4574",
    "sg:postcode":"75703",
    "sg:province":"TX",
    "sg:tags":[
        "garment",
        "plant",
        "commercial",
        "agent",
        "drycleaning"
    ],
    "wof:name":"Bell Cleaners",
    "wof:placetype":"venue"
},
  "geometry": {"coordinates":[-95.297709,32.29488],"type":"Point"}
}