{
  "type": "Feature",
  "properties": {
    "iso:country":"US",
    "sg:address":"4026 Song Heights Dr",
    "sg:city":"San Antonio",
    "sg:classifiers":[
        {
            "category":"Building & Trades",
            "subcategory":"Construction",
            "type":"Services"
        }
    ],
    "sg:phone":"+1 210 493 3095",
    "sg:postcode":"78230",
    "sg:province":"TX",
    "sg:tags":[
        "house"
    ],
    "wof:name":"JC-Eb Ltd",
    "wof:placetype":"venue"
},
  "geometry": {"coordinates":[-98.56469199999999,29.56704],"type":"Point"}
}