{
  "type": "Feature",
  "properties": {
    "iso:country":"US",
    "sg:address":"1212 Columbia Dr",
    "sg:city":"Longview",
    "sg:classifiers":[
        {
            "category":"Building & Trades",
            "subcategory":"Construction",
            "type":"Services"
        }
    ],
    "sg:phone":"+1 903 553 9706",
    "sg:postcode":"75601",
    "sg:province":"TX",
    "sg:tags":[
        "general",
        "contractor"
    ],
    "wof:name":"Smith & Simmons Construction",
    "wof:placetype":"venue"
},
  "geometry": {"coordinates":[-94.755764,32.509108],"type":"Point"}
}