{
  "type": "Feature",
  "properties": {
    "iso:country":"US",
    "sg:address":"4930 S Congress Ave",
    "sg:city":"Austin",
    "sg:classifiers":[
        {
            "category":"Autos & Motor Vehicles",
            "subcategory":"Auto Supplies",
            "type":"Retail Goods"
        }
    ],
    "sg:phone":"+1 512 441 3773",
    "sg:postcode":"78745",
    "sg:province":"TX",
    "sg:tags":[
        "body",
        "shop",
        "equipment",
        "automobile"
    ],
    "wof:name":"Tasco Auto Color Corporation",
    "wof:placetype":"venue"
},
  "geometry": {"coordinates":[-97.771317,30.211303],"type":"Point"}
}