{
  "type": "Feature",
  "properties": {
    "iso:country":"US",
    "sg:address":"11540 Northwest Fwy",
    "sg:city":"Houston",
    "sg:classifiers":[
        {
            "category":"Professional",
            "subcategory":"Business Services",
            "type":"Services"
        },
        {
            "category":"Real Estate",
            "subcategory":"Real Estate Services",
            "type":"Services"
        }
    ],
    "sg:phone":"+1 713 681 4477",
    "sg:postcode":"77092",
    "sg:province":"TX",
    "sg:tags":[
        "company",
        "title"
    ],
    "wof:name":"Inwood Auto Title Co",
    "wof:placetype":"venue"
},
  "geometry": {"coordinates":[-95.47167399999999,29.822712],"type":"Point"}
}