{
  "type": "Feature",
  "properties": {
    "iso:country":"US",
    "sg:address":"1512 Lowes Blvd Ste 106",
    "sg:city":"Killeen",
    "sg:classifiers":[
        {
            "category":"Personal",
            "subcategory":"Nail Salon",
            "type":"Services"
        }
    ],
    "sg:phone":"+1 254 634 6522",
    "sg:postcode":"76542",
    "sg:province":"TX",
    "wof:name":"T S Nails",
    "wof:placetype":"venue"
},
  "geometry": {"coordinates":[-97.72321700000001,31.088934],"type":"Point"}
}