{
  "type": "Feature",
  "properties": {
    "iso:country":"US",
    "sg:address":"3452 Webb Chapel Exn",
    "sg:city":"Dallas",
    "sg:classifiers":[
        {
            "category":"Cinema",
            "subcategory":"Movie Rental",
            "type":"Entertainment"
        }
    ],
    "sg:phone":"+1 214 350 3230",
    "sg:postcode":"75220",
    "sg:province":"TX",
    "sg:tags":[
        "video",
        "tape"
    ],
    "wof:name":"Movie Store International",
    "wof:placetype":"venue"
},
  "geometry": {"coordinates":[-96.86473100000001,32.865314],"type":"Point"}
}