{
  "type": "Feature",
  "properties": {
    "iso:country":"US",
    "sg:address":"2804 Marburg St",
    "sg:city":"Dallas",
    "sg:classifiers":[
        {
            "category":"Restaurant",
            "type":"Food & Drink"
        }
    ],
    "sg:phone":"+1 214 428 4111",
    "sg:postcode":"75215",
    "sg:province":"TX",
    "sg:tags":[
        "eating"
    ],
    "wof:name":"Henderson Chicken Shack South",
    "wof:placetype":"venue"
},
  "geometry": {"coordinates":[-96.7529,32.75831],"type":"Point"}
}