{
  "type": "Feature",
  "properties": {
    "iso:country":"US",
    "sg:address":"1 Park Ten Pl",
    "sg:city":"Houston",
    "sg:classifiers":[
        {
            "category":"Professional",
            "subcategory":"Lawyer & Legal Services",
            "type":"Services"
        }
    ],
    "sg:phone":"+1 281 578 8800",
    "sg:postcode":"77084",
    "sg:province":"TX",
    "sg:tags":[
        "plan"
    ],
    "sg:website":"www.itisinc.com",
    "wof:name":"It-Is Inc",
    "wof:placetype":"venue"
},
  "geometry": {"coordinates":[-95.668289,29.786814],"type":"Point"}
}