{
  "type": "Feature",
  "properties": {
    "iso:country":"US",
    "sg:address":"1515 Seley Ave",
    "sg:city":"Waco",
    "sg:classifiers":[
        {
            "category":"Retail",
            "subcategory":"Auto Repair",
            "type":"Services"
        }
    ],
    "sg:phone":"+1 254 754 2301",
    "sg:postcode":"76704",
    "sg:province":"TX",
    "sg:tags":[
        "body",
        "automobile",
        "painting"
    ],
    "wof:name":"Bebrick Collision Ctr",
    "wof:placetype":"venue"
},
  "geometry": {"coordinates":[-97.119517,31.584381],"type":"Point"}
}