{
  "type": "Feature",
  "properties": {
    "iso:country":"US",
    "sg:address":"7933 N Mesa St Ste L",
    "sg:city":"El Paso",
    "sg:classifiers":[
        {
            "category":"Shopping",
            "subcategory":"Mobile Phones",
            "type":"Retail Goods"
        }
    ],
    "sg:phone":"+1 915 842 0978",
    "sg:postcode":"79932",
    "sg:province":"TX",
    "wof:name":"Airone Wireless",
    "wof:placetype":"venue"
},
  "geometry": {"coordinates":[-106.575996,31.8405],"type":"Point"}
}