{
  "type": "Feature",
  "properties": {
    "iso:country":"US",
    "sg:address":"10822 Ambergate Dr",
    "sg:city":"Humble",
    "sg:classifiers":[
        {
            "category":"Shopping",
            "subcategory":"Hobbies, Toys, & Games",
            "type":"Retail Goods"
        }
    ],
    "sg:phone":"+1 281 741 9562",
    "sg:postcode":"77396",
    "sg:province":"TX",
    "sg:tags":[
        "shop",
        "hobby",
        "supply"
    ],
    "wof:name":"BMWE",
    "wof:placetype":"venue"
},
  "geometry": {"coordinates":[-95.224861,29.938078],"type":"Point"}
}