{
  "type": "Feature",
  "properties": {
    "iso:country":"US",
    "sg:address":"7322 N Loop Dr",
    "sg:city":"El Paso",
    "sg:classifiers":[
        {
            "category":"Bars & Pubs",
            "type":"Food & Drink"
        }
    ],
    "sg:phone":"+1 915 779 0770",
    "sg:postcode":"79915",
    "sg:province":"TX",
    "sg:tags":[
        "lounge",
        "cocktail"
    ],
    "wof:name":"Classroom Lounge",
    "wof:placetype":"venue"
},
  "geometry": {"coordinates":[-106.37591500000001,31.751794],"type":"Point"}
}