{
  "type": "Feature",
  "properties": {
    "iso:country":"US",
    "sg:address":"11438 Cypress North Houston Rd",
    "sg:city":"Cypress",
    "sg:classifiers":[
        {
            "category":"Professional",
            "subcategory":"Business Services",
            "type":"Services"
        }
    ],
    "sg:phone":"+1 281 844 7107",
    "sg:postcode":"77429",
    "sg:province":"TX",
    "wof:name":"Power Edge Enterprises Ltd",
    "wof:placetype":"venue"
},
  "geometry": {"coordinates":[-95.591757,29.952561],"type":"Point"}
}