{
  "type": "Feature",
  "properties": {
    "iso:country":"US",
    "sg:address":"1600 Floral Dr",
    "sg:city":"Gainesville",
    "sg:classifiers":[
        {
            "category":"Autos & Motor Vehicles",
            "subcategory":"Auto Supplies",
            "type":"Retail Goods"
        }
    ],
    "sg:phone":"+1 940 668 8622",
    "sg:postcode":"76240",
    "sg:province":"TX",
    "sg:tags":[
        "automobile",
        "part",
        "accessory"
    ],
    "wof:name":"Bob Smith Coachworks",
    "wof:placetype":"venue"
},
  "geometry": {"coordinates":[-97.164658,33.640831],"type":"Point"}
}