{
  "type": "Feature",
  "properties": {
    "iso:country":"US",
    "sg:address":"301 S Meadow Ave",
    "sg:city":"Odessa",
    "sg:classifiers":[
        {
            "category":"Manufacturing",
            "subcategory":"Petroleum Products",
            "type":"Manufacturing & Wholesale Goods"
        }
    ],
    "sg:phone":"+1 432 580 7493",
    "sg:postcode":"79761",
    "sg:province":"TX",
    "sg:tags":[
        "oil",
        "recovery"
    ],
    "wof:name":"Recon Systems",
    "wof:placetype":"venue"
},
  "geometry": {"coordinates":[-102.336286,31.848027],"type":"Point"}
}