{
  "type": "Feature",
  "properties": {
    "iso:country":"US",
    "sg:address":"7226 Westbranch Dr",
    "sg:city":"Houston",
    "sg:classifiers":[
        {
            "category":"Shopping",
            "subcategory":"Florist",
            "type":"Retail Goods"
        }
    ],
    "sg:phone":"+1 281 561 9427",
    "sg:postcode":"77072",
    "sg:province":"TX",
    "wof:name":"Power Flower Florist",
    "wof:placetype":"venue"
},
  "geometry": {"coordinates":[-95.606571,29.69911],"type":"Point"}
}