{
  "type": "Feature",
  "properties": {
    "iso:country":"US",
    "sg:address":"8500 Whitney Dr",
    "sg:city":"Fort Worth",
    "sg:classifiers":[
        {
            "category":"Real Estate",
            "subcategory":"Real Estate Agent",
            "type":"Services"
        }
    ],
    "sg:phone":"+1 817 246 6595",
    "sg:postcode":"76108",
    "sg:province":"TX",
    "wof:name":"Home Buyer Solutions",
    "wof:placetype":"venue"
},
  "geometry": {"coordinates":[-97.467051,32.753448],"type":"Point"}
}