{
  "type": "Feature",
  "properties": {
    "iso:country":"US",
    "sg:address":"2682 Myrtle Springs Ave",
    "sg:city":"Dallas",
    "sg:classifiers":[
        {
            "category":"Retail",
            "subcategory":"Auto Repair",
            "type":"Services"
        }
    ],
    "sg:phone":"+1 214 353 3955",
    "sg:postcode":"75220",
    "sg:province":"TX",
    "sg:tags":[
        "body",
        "shop"
    ],
    "wof:name":"Chava Body Shop",
    "wof:placetype":"venue"
},
  "geometry": {"coordinates":[-96.883904,32.8685],"type":"Point"}
}