{
  "type": "Feature",
  "properties": {
    "iso:country":"US",
    "sg:address":"5330 Vista Rd",
    "sg:city":"Pasadena",
    "sg:classifiers":[
        {
            "category":"Professional",
            "subcategory":"Management & Consulting",
            "type":"Services"
        }
    ],
    "sg:phone":"+1 281 998 7546",
    "sg:postcode":"77505",
    "sg:province":"TX",
    "sg:tags":[
        "consultant",
        "business"
    ],
    "wof:name":"ITC",
    "wof:placetype":"venue"
},
  "geometry": {"coordinates":[-95.16132399999999,29.657927],"type":"Point"}
}