{
  "type": "Feature",
  "properties": {
    "iso:country":"US",
    "sg:address":"4880 Fm 2264",
    "sg:city":"Decatur",
    "sg:classifiers":[
        {
            "category":"Food & Beverages",
            "subcategory":"Groceries & Convenience Stores",
            "type":"Retail Goods"
        }
    ],
    "sg:phone":"+1 940 627 5184",
    "sg:postcode":"76234",
    "sg:province":"TX",
    "wof:name":"Oliver Creek Store",
    "wof:placetype":"venue"
},
  "geometry": {"coordinates":[-97.43860599999999,33.146754],"type":"Point"}
}