{
  "type": "Feature",
  "properties": {
    "iso:country":"US",
    "sg:address":"215 Greenlawn Dr",
    "sg:city":"San Antonio",
    "sg:classifiers":[
        {
            "category":"Retail",
            "subcategory":"Auto Repair",
            "type":"Services"
        }
    ],
    "sg:phone":"+1 210 736 2463",
    "sg:postcode":"78201",
    "sg:province":"TX",
    "sg:tags":[
        "automotive"
    ],
    "wof:name":"Bear Wheel Aligning Co Inc",
    "wof:placetype":"venue"
},
  "geometry": {"coordinates":[-98.530554,29.481121],"type":"Point"}
}