{
  "type": "Feature",
  "properties": {
    "iso:country":"US",
    "sg:address":"5335 Green Pines Dr",
    "sg:city":"Houston",
    "sg:classifiers":[
        {
            "category":"Organizations",
            "subcategory":"Non-profit Organization",
            "type":"Services"
        }
    ],
    "sg:phone":"+1 281 893 5966",
    "sg:postcode":"77066",
    "sg:province":"TX",
    "wof:name":"Harris County Emergency Svc",
    "wof:placetype":"venue"
},
  "geometry": {"coordinates":[-95.503699,29.948424],"type":"Point"}
}