{
  "type": "Feature",
  "properties": {
    "iso:country":"US",
    "sg:address":"1618 S Mechanic St",
    "sg:city":"El Campo",
    "sg:classifiers":[
        {
            "category":"Restaurant",
            "type":"Food & Drink"
        }
    ],
    "sg:phone":"+1 979 543 3518",
    "sg:postcode":"77437",
    "sg:province":"TX",
    "wof:name":"Taqueria Fernandez",
    "wof:placetype":"venue"
},
  "geometry": {"coordinates":[-96.260971,29.18101],"type":"Point"}
}