{
  "type": "Feature",
  "properties": {
    "iso:country":"US",
    "sg:address":"1126 River Bend Dr",
    "sg:city":"Houston",
    "sg:classifiers":[
        {
            "category":"Real Estate",
            "subcategory":"Developer",
            "type":"Services"
        }
    ],
    "sg:phone":"+1 713 464 9359",
    "sg:postcode":"77063",
    "sg:province":"TX",
    "wof:name":"Riverton Development Company",
    "wof:placetype":"venue"
},
  "geometry": {"coordinates":[-95.503145,29.753816],"type":"Point"}
}