{
  "type": "Feature",
  "properties": {
    "iso:country":"US",
    "sg:address":"415 N Central Expy",
    "sg:city":"Richardson",
    "sg:classifiers":[
        {
            "category":"Local Transit",
            "type":"Transportation"
        }
    ],
    "sg:phone":"+1 972 820 9722",
    "sg:postcode":"75080",
    "sg:province":"TX",
    "sg:tags":[
        "limousine"
    ],
    "wof:name":"Arrowhead Autoplex",
    "wof:placetype":"venue"
},
  "geometry": {"coordinates":[-96.73066799999999,32.956022],"type":"Point"}
}