{
  "type": "Feature",
  "properties": {
    "iso:country":"US",
    "sg:address":"2106 S Cockrell Hill Rd",
    "sg:city":"Dallas",
    "sg:classifiers":[
        {
            "category":"Restaurant",
            "type":"Food & Drink"
        }
    ],
    "sg:phone":"+1 214 331 1219",
    "sg:postcode":"75211",
    "sg:province":"TX",
    "sg:tags":[
        "catering"
    ],
    "wof:name":"Lao Thai Catering",
    "wof:placetype":"venue"
},
  "geometry": {"coordinates":[-96.891482,32.722409],"type":"Point"}
}