{
  "type": "Feature",
  "properties": {
    "iso:country":"US",
    "sg:address":"319 E Co Rd 5719",
    "sg:city":"Natalia",
    "sg:classifiers":[
        {
            "category":"Home & Garden",
            "subcategory":"Garden Supply",
            "type":"Retail Goods"
        }
    ],
    "sg:phone":"+1 830 709 9932",
    "sg:postcode":"78059",
    "sg:province":"TX",
    "sg:tags":[
        "landscape"
    ],
    "wof:name":"Flores Nursery Landscape",
    "wof:placetype":"venue"
},
  "geometry": {"coordinates":[-98.86677299999999,29.255961],"type":"Point"}
}