{
  "type": "Feature",
  "properties": {
    "iso:country":"US",
    "sg:address":"38 Meandering Way",
    "sg:city":"Round Rock",
    "sg:classifiers":[
        {
            "category":"Mining & Drilling",
            "type":"Manufacturing & Wholesale Goods"
        }
    ],
    "sg:phone":"+1 512 388 9592",
    "sg:postcode":"78664",
    "sg:province":"TX",
    "sg:tags":[
        "development",
        "gas",
        "oil",
        "exploration"
    ],
    "wof:name":"Hees Interest",
    "wof:placetype":"venue"
},
  "geometry": {"coordinates":[-97.606596,30.522137],"type":"Point"}
}