{
  "type": "Feature",
  "properties": {
    "iso:country":"US",
    "sg:address":"2520 Reynolds St",
    "sg:city":"Laredo",
    "sg:classifiers":[
        {
            "category":"Professional",
            "type":"Services"
        }
    ],
    "sg:phone":"+1 956 729 8484",
    "sg:postcode":"78043",
    "sg:province":"TX",
    "wof:name":"Guillermo Benavides Garza",
    "wof:placetype":"venue"
},
  "geometry": {"coordinates":[-99.470264,27.518652],"type":"Point"}
}