{
  "type": "Feature",
  "properties": {
    "iso:country":"US",
    "sg:address":"11555 Preston Estates Dr",
    "sg:city":"Celina",
    "sg:classifiers":[
        {
            "category":"Farming",
            "subcategory":"Farm",
            "type":"Manufacturing & Wholesale Goods"
        }
    ],
    "sg:phone":"+1 214 868 5428",
    "sg:postcode":"75009",
    "sg:province":"TX",
    "wof:name":"3d Adriatico",
    "wof:placetype":"venue"
},
  "geometry": {"coordinates":[-96.78801300000001,33.346771],"type":"Point"}
}