{
  "type": "Feature",
  "properties": {
    "iso:country":"US",
    "sg:address":"3735 Highland Ave",
    "sg:city":"Beaumont",
    "sg:classifiers":[
        {
            "category":"Professional",
            "subcategory":"Advertising",
            "type":"Services"
        }
    ],
    "sg:phone":"+1 409 833 3534",
    "sg:postcode":"77705",
    "sg:province":"TX",
    "sg:tags":[
        "agency"
    ],
    "wof:name":"Creative Ad Ventures",
    "wof:placetype":"venue"
},
  "geometry": {"coordinates":[-94.08585600000001,30.04992],"type":"Point"}
}