{
  "type": "Feature",
  "properties": {
    "iso:country":"US",
    "sg:address":"15702 Beechnut St",
    "sg:city":"Houston",
    "sg:classifiers":[
        {
            "category":"Fast Food",
            "type":"Food & Drink"
        },
        {
            "category":"Restaurant",
            "type":"Food & Drink"
        }
    ],
    "sg:phone":"+1 832 279 3018",
    "sg:postcode":"77083",
    "sg:province":"TX",
    "sg:tags":[
        "chicken",
        "take"
    ],
    "sg:website":"http://www.wingstop.com",
    "wof:name":"Wingstop Restaurant",
    "wof:placetype":"venue"
},
  "geometry": {"coordinates":[-95.662004,29.688989],"type":"Point"}
}