{
  "type": "Feature",
  "properties": {
    "iso:country":"US",
    "sg:address":"7426 Airline Dr",
    "sg:city":"Houston",
    "sg:classifiers":[
        {
            "category":"Food & Beverages",
            "subcategory":"Groceries & Convenience Stores",
            "type":"Retail Goods"
        }
    ],
    "sg:phone":"+1 713 691 1336",
    "sg:postcode":"77076",
    "sg:province":"TX",
    "wof:name":"Gerland's Food Fair Inc",
    "wof:placetype":"venue"
},
  "geometry": {"coordinates":[-95.384697,29.869301],"type":"Point"}
}