{
  "type": "Feature",
  "properties": {
    "iso:country":"US",
    "sg:address":"100 Rienhardt Ct",
    "sg:city":"Georgetown",
    "sg:classifiers":[
        {
            "category":"Professional",
            "subcategory":"Computer Services",
            "type":"Services"
        }
    ],
    "sg:phone":"+1 512 863 4118",
    "sg:postcode":"78626",
    "sg:province":"TX",
    "sg:tags":[
        "datum"
    ],
    "wof:name":"Wja Design",
    "wof:placetype":"venue"
},
  "geometry": {"coordinates":[-97.639293,30.632209],"type":"Point"}
}