{
  "type": "Feature",
  "properties": {
    "iso:country":"US",
    "sg:address":"16507 Quail Prairie Dr",
    "sg:city":"Missouri City",
    "sg:classifiers":[
        {
            "category":"Building & Trades",
            "subcategory":"Landscaping Services",
            "type":"Services"
        }
    ],
    "sg:phone":"+1 281 438 7658",
    "sg:postcode":"77489",
    "sg:province":"TX",
    "wof:name":"Lawns Unlimited",
    "wof:placetype":"venue"
},
  "geometry": {"coordinates":[-95.51396,29.585726],"type":"Point"}
}