{
  "type": "Feature",
  "properties": {
    "iso:country":"US",
    "sg:address":"2219 Webb Lynn Rd",
    "sg:city":"Arlington",
    "sg:classifiers":[
        {
            "category":"Building & Trades",
            "subcategory":"Construction",
            "type":"Services"
        }
    ],
    "sg:phone":"+1 817 417 4591",
    "sg:postcode":"76002",
    "sg:province":"TX",
    "sg:tags":[
        "consulting",
        "business",
        "contractor"
    ],
    "wof:name":"American Envmtl Specialities",
    "wof:placetype":"venue"
},
  "geometry": {"coordinates":[-97.072703,32.633374],"type":"Point"}
}