{
  "type": "Feature",
  "properties": {
    "iso:country":"US",
    "sg:address":"900 N Coit Rd",
    "sg:city":"Richardson",
    "sg:classifiers":[
        {
            "category":"Shopping",
            "subcategory":"Mobile Phones",
            "type":"Retail Goods"
        }
    ],
    "sg:phone":"+1 972 234 3171",
    "sg:postcode":"75080",
    "sg:province":"TX",
    "wof:name":"Cellular Sales",
    "wof:placetype":"venue"
},
  "geometry": {"coordinates":[-96.768626,32.960071],"type":"Point"}
}