{
  "type": "Feature",
  "properties": {
    "iso:country":"US",
    "sg:address":"508 10th St",
    "sg:city":"Floresville",
    "sg:classifiers":[
        {
            "category":"Building & Trades",
            "subcategory":"Plumbing",
            "type":"Services"
        }
    ],
    "sg:phone":"+1 830 393 2854",
    "sg:postcode":"78114",
    "sg:province":"TX",
    "sg:tags":[
        "plumber",
        "industrial",
        "contractors-commercial"
    ],
    "wof:name":"Poth Plumbing",
    "wof:placetype":"venue"
},
  "geometry": {"coordinates":[-98.146511,29.134795],"type":"Point"}
}