{
  "type": "Feature",
  "properties": {
    "iso:country":"US",
    "sg:address":"4605 Oak Ridge Dr",
    "sg:city":"Brownwood",
    "sg:classifiers":[
        {
            "category":"Manufacturing",
            "subcategory":"Apparel",
            "type":"Manufacturing & Wholesale Goods"
        }
    ],
    "sg:phone":"+1 325 646 7721",
    "sg:postcode":"76801",
    "sg:province":"TX",
    "sg:tags":[
        "top",
        "upholstery",
        "cover",
        "boat"
    ],
    "wof:name":"Brownwood Canvas",
    "wof:placetype":"venue"
},
  "geometry": {"coordinates":[-98.94739199999999,31.669586],"type":"Point"}
}