{
  "type": "Feature",
  "properties": {
    "iso:country":"US",
    "sg:address":"205 Johnson St",
    "sg:city":"Queen City",
    "sg:classifiers":[
        {
            "category":"Shopping",
            "subcategory":"Books",
            "type":"Retail Goods"
        }
    ],
    "sg:phone":"+1 903 796 0707",
    "sg:postcode":"75572",
    "sg:province":"TX",
    "sg:tags":[
        "dealer"
    ],
    "wof:name":"Judy's Books N Things",
    "wof:placetype":"venue"
},
  "geometry": {"coordinates":[-94.151116,33.155369],"type":"Point"}
}