{
  "type": "Feature",
  "properties": {
    "iso:country":"US",
    "sg:address":"3333 Coulter St",
    "sg:city":"Amarillo",
    "sg:classifiers":[
        {
            "category":"Restaurant",
            "type":"Food & Drink"
        }
    ],
    "sg:phone":"+1 806 355 2620",
    "sg:postcode":"79106",
    "sg:province":"TX",
    "sg:tags":[
        "eating"
    ],
    "wof:name":"Subway",
    "wof:placetype":"venue"
},
  "geometry": {"coordinates":[-101.920208,35.17735],"type":"Point"}
}