{
  "type": "Feature",
  "properties": {
    "iso:country":"US",
    "sg:address":"714 Baldwin Ct",
    "sg:city":"Allen",
    "sg:classifiers":[
        {
            "category":"Manufacturing",
            "subcategory":"Printing",
            "type":"Manufacturing & Wholesale Goods"
        }
    ],
    "sg:phone":"+1 214 547 1100",
    "sg:postcode":"75013",
    "sg:province":"TX",
    "sg:tags":[
        "book"
    ],
    "wof:name":"Brookwood Designs",
    "wof:placetype":"venue"
},
  "geometry": {"coordinates":[-96.71935000000001,33.086502],"type":"Point"}
}