{
  "type": "Feature",
  "properties": {
    "iso:country":"US",
    "sg:address":"4024 Shadow Cir",
    "sg:city":"Denison",
    "sg:classifiers":[
        {
            "category":"Retail",
            "subcategory":"Repair Shop",
            "type":"Services"
        }
    ],
    "sg:phone":"+1 903 463 2522",
    "sg:postcode":"75020",
    "sg:province":"TX",
    "wof:name":"Clark Garner Television",
    "wof:placetype":"venue"
},
  "geometry": {"coordinates":[-96.59714700000001,33.753147],"type":"Point"}
}