{
  "type": "Feature",
  "properties": {
    "iso:country":"US",
    "sg:address":"4105 Tulane St",
    "sg:city":"Flower Mound",
    "sg:classifiers":[
        {
            "category":"Building & Trades",
            "subcategory":"Construction",
            "type":"Services"
        }
    ],
    "sg:phone":"+1 972 899 0325",
    "sg:postcode":"75022",
    "sg:province":"TX",
    "sg:tags":[
        "housing"
    ],
    "wof:name":"Abros Contracting Inc",
    "wof:placetype":"venue"
},
  "geometry": {"coordinates":[-97.096278,33.022075],"type":"Point"}
}