{
  "type": "Feature",
  "properties": {
    "iso:country":"US",
    "sg:address":"705 Willowbrook Dr",
    "sg:city":"Mesquite",
    "sg:classifiers":[
        {
            "category":"Personal",
            "subcategory":"Tanning Parlor",
            "type":"Services"
        }
    ],
    "sg:phone":"+1 972 913 9914",
    "sg:postcode":"75149",
    "sg:province":"TX",
    "sg:tags":[
        "salon"
    ],
    "wof:name":"Tan 2002",
    "wof:placetype":"venue"
},
  "geometry": {"coordinates":[-96.608577,32.777637],"type":"Point"}
}