{
  "type": "Feature",
  "properties": {
    "iso:country":"US",
    "sg:address":"127 Main St",
    "sg:city":"Italy",
    "sg:classifiers":[
        {
            "category":"Insurance",
            "subcategory":"Insurance Agent",
            "type":"Services"
        }
    ],
    "sg:phone":"+1 972 493 3500",
    "sg:postcode":"76651",
    "sg:province":"TX",
    "wof:name":"Germania Insurance",
    "wof:placetype":"venue"
},
  "geometry": {"coordinates":[-96.886613,32.183873],"type":"Point"}
}