{
  "type": "Feature",
  "properties": {
    "iso:country":"US",
    "sg:address":"310 Dominique Dr",
    "sg:city":"Laredo",
    "sg:classifiers":[
        {
            "category":"Professional",
            "subcategory":"Accounting & Tax Preparation",
            "type":"Services"
        }
    ],
    "sg:phone":"+1 956 795 1710",
    "sg:postcode":"78041",
    "sg:province":"TX",
    "sg:tags":[
        "accountant"
    ],
    "wof:name":"Pablo Valencia CPA",
    "wof:placetype":"venue"
},
  "geometry": {"coordinates":[-99.490211,27.55944],"type":"Point"}
}