{
  "type": "Feature",
  "properties": {
    "iso:country":"US",
    "sg:address":"402 N Front St",
    "sg:city":"Cotulla",
    "sg:classifiers":[
        {
            "category":"Government",
            "subcategory":"Office",
            "type":"Public Place"
        }
    ],
    "sg:phone":"+1 830 879 2621",
    "sg:postcode":"78014",
    "sg:province":"TX",
    "sg:tags":[
        "federal"
    ],
    "wof:name":"Natural Resources Conservation",
    "wof:placetype":"venue"
},
  "geometry": {"coordinates":[-99.234679,28.440375],"type":"Point"}
}