{
  "type": "Feature",
  "properties": {
    "iso:country":"US",
    "sg:address":"1418 Waterside Village Dr",
    "sg:city":"Richmond",
    "sg:classifiers":[
        {
            "category":"Place Of Worship",
            "type":"Public Place"
        }
    ],
    "sg:phone":"+1 281 725 9169",
    "sg:postcode":"77407",
    "sg:province":"TX",
    "sg:tags":[
        "church"
    ],
    "wof:name":"The River Um Church",
    "wof:placetype":"venue"
},
  "geometry": {"coordinates":[-95.72668899999999,29.662154],"type":"Point"}
}