{
  "type": "Feature",
  "properties": {
    "iso:country":"US",
    "sg:address":"801 W Kearney St",
    "sg:city":"Mesquite",
    "sg:classifiers":[
        {
            "category":"Shopping",
            "subcategory":"Musical Instruments",
            "type":"Retail Goods"
        }
    ],
    "sg:phone":"+1 972 285 8320",
    "sg:postcode":"75149",
    "sg:province":"TX",
    "sg:tags":[
        "violin"
    ],
    "wof:name":"Brady Violin Shop",
    "wof:placetype":"venue"
},
  "geometry": {"coordinates":[-96.61107199999999,32.770767],"type":"Point"}
}