{
  "type": "Feature",
  "properties": {
    "iso:country":"US",
    "sg:address":"8220 Westchester Dr",
    "sg:city":"Dallas",
    "sg:classifiers":[
        {
            "category":"Shopping",
            "subcategory":"Beauty & Cosmetics",
            "type":"Retail Goods"
        }
    ],
    "sg:phone":"+1 214 361 4442",
    "sg:postcode":"75225",
    "sg:province":"TX",
    "sg:tags":[
        "merchandise"
    ],
    "wof:name":"Rainbow Dallas Colour Academy",
    "wof:placetype":"venue"
},
  "geometry": {"coordinates":[-96.806493,32.863325],"type":"Point"}
}