{
  "type": "Feature",
  "properties": {
    "iso:country":"US",
    "sg:address":"1316 W University Dr",
    "sg:city":"Edinburg",
    "sg:classifiers":[
        {
            "category":"Personal",
            "subcategory":"Beauty Salon",
            "type":"Services"
        }
    ],
    "sg:phone":"+1 956 383 9083",
    "sg:postcode":"78539",
    "sg:province":"TX",
    "sg:tags":[
        "shop"
    ],
    "wof:name":"Vogue's Hair Fashions",
    "wof:placetype":"venue"
},
  "geometry": {"coordinates":[-98.175619,26.303364],"type":"Point"}
}