{
  "type": "Feature",
  "properties": {
    "iso:country":"US",
    "sg:address":"2545 Shropshire St",
    "sg:city":"Fort Worth",
    "sg:classifiers":[
        {
            "category":"Building & Trades",
            "subcategory":"Construction",
            "type":"Services"
        }
    ],
    "sg:phone":"+1 817 536 2746",
    "sg:postcode":"76105",
    "sg:province":"TX",
    "sg:tags":[
        "contractor"
    ],
    "wof:name":"Polks Perfect Paint & Paper",
    "wof:placetype":"venue"
},
  "geometry": {"coordinates":[-97.290029,32.711189],"type":"Point"}
}