{
  "type": "Feature",
  "properties": {
    "iso:country":"US",
    "sg:address":"3262 S 27th St",
    "sg:city":"Abilene",
    "sg:classifiers":[
        {
            "category":"Travel",
            "subcategory":"Travel Agent",
            "type":"Entertainment"
        }
    ],
    "sg:phone":"+1 325 692 1308",
    "sg:postcode":"79605",
    "sg:province":"TX",
    "sg:tags":[
        "tours",
        "promoter"
    ],
    "sg:website":"www.bilbreytours.com",
    "wof:name":"Bilbrey Tours Inc",
    "wof:placetype":"venue"
},
  "geometry": {"coordinates":[-99.762299,32.417902],"type":"Point"}
}