{
  "type": "Feature",
  "properties": {
    "iso:country":"US",
    "sg:address":"5210 Maulding Pass",
    "sg:city":"Austin",
    "sg:classifiers":[
        {
            "category":"Communications",
            "subcategory":"Film & Video Production",
            "type":"Services"
        }
    ],
    "sg:phone":"+1 512 892 2139",
    "sg:postcode":"78749",
    "sg:province":"TX",
    "sg:tags":[
        "motion"
    ],
    "wof:name":"Forever On Video",
    "wof:placetype":"venue"
},
  "geometry": {"coordinates":[-97.849371,30.228076],"type":"Point"}
}