{
  "type": "Feature",
  "properties": {
    "iso:country":"US",
    "sg:address":"2792 Skalak Rd",
    "sg:city":"New Ulm",
    "sg:classifiers":[
        {
            "category":"Building & Trades",
            "subcategory":"Equipment Rental",
            "type":"Services"
        }
    ],
    "sg:phone":"+1 979 865 8939",
    "sg:postcode":"77418",
    "sg:province":"TX",
    "wof:name":"Patricia Doran",
    "wof:placetype":"venue"
},
  "geometry": {"coordinates":[-96.397262,29.949131],"type":"Point"}
}