{
  "type": "Feature",
  "properties": {
    "iso:country":"US",
    "sg:address":"4509 Cimmaron Ave",
    "sg:city":"Midland",
    "sg:classifiers":[
        {
            "category":"Professional",
            "subcategory":"Business Services",
            "type":"Services"
        }
    ],
    "sg:phone":"+1 432 689 2644",
    "sg:postcode":"79707",
    "sg:province":"TX",
    "wof:name":"Vance Assoc",
    "wof:placetype":"venue"
},
  "geometry": {"coordinates":[-102.143275,32.009572],"type":"Point"}
}