{
  "type": "Feature",
  "properties": {
    "iso:country":"US",
    "sg:address":"14631 Hargrave Rd",
    "sg:city":"Houston",
    "sg:classifiers":[
        {
            "category":"Building & Trades",
            "subcategory":"Pest Control",
            "type":"Services"
        }
    ],
    "sg:phone":"+1 281 537 5053",
    "sg:postcode":"77070",
    "sg:province":"TX",
    "wof:name":"West Rd Pest Control",
    "wof:placetype":"venue"
},
  "geometry": {"coordinates":[-95.54384400000001,29.979464],"type":"Point"}
}