{
  "type": "Feature",
  "properties": {
    "iso:country":"US",
    "sg:address":"201 Cherylton Dr",
    "sg:city":"Red Rock",
    "sg:classifiers":[
        {
            "category":"Manufacturing",
            "subcategory":"Retail Goods",
            "type":"Manufacturing & Wholesale Goods"
        }
    ],
    "sg:phone":"+1 512 601 1213",
    "sg:postcode":"78662",
    "sg:province":"TX",
    "sg:tags":[
        "product",
        "merchandise",
        "mfg"
    ],
    "wof:name":"Our Family Creations",
    "wof:placetype":"venue"
},
  "geometry": {"coordinates":[-97.50152799999999,29.982026],"type":"Point"}
}