{
  "type": "Feature",
  "properties": {
    "iso:country":"US",
    "sg:address":"206 Page Ln",
    "sg:city":"Huffman",
    "sg:classifiers":[
        {
            "category":"Freight",
            "type":"Transportation"
        }
    ],
    "sg:phone":"+1 281 324 9112",
    "sg:postcode":"77336",
    "sg:province":"TX",
    "sg:tags":[
        "operator",
        "local",
        "trucking"
    ],
    "wof:name":"K & T Trucking",
    "wof:placetype":"venue"
},
  "geometry": {"coordinates":[-95.116293,30.015363],"type":"Point"}
}