{
  "type": "Feature",
  "properties": {
    "iso:country":"US",
    "sg:address":"606 E Royal Ln",
    "sg:city":"Irving",
    "sg:classifiers":[
        {
            "category":"Education",
            "subcategory":"School",
            "type":"Public Place"
        }
    ],
    "sg:phone":"+1 972 501 0645",
    "sg:postcode":"75039",
    "sg:province":"TX",
    "wof:name":"The North Hills School",
    "wof:placetype":"venue"
},
  "geometry": {"coordinates":[-96.933701,32.8955],"type":"Point"}
}