{
  "type": "Feature",
  "properties": {
    "iso:country":"US",
    "sg:address":"4914 Lakawana St",
    "sg:city":"Dallas",
    "sg:classifiers":[
        {
            "category":"Retail",
            "subcategory":"Auto Repair",
            "type":"Services"
        }
    ],
    "sg:phone":"+1 214 634 7860",
    "sg:postcode":"75247",
    "sg:province":"TX",
    "sg:tags":[
        "exhaust"
    ],
    "wof:name":"Midas Realty Corporation",
    "wof:placetype":"venue"
},
  "geometry": {"coordinates":[-96.863108,32.806322],"type":"Point"}
}