{
  "type": "Feature",
  "properties": {
    "iso:country":"US",
    "sg:address":"20766 Oakhurst Creek Dr",
    "sg:city":"Porter",
    "sg:classifiers":[
        {
            "category":"Building & Trades",
            "subcategory":"Construction",
            "type":"Services"
        }
    ],
    "sg:phone":"+1 281 360 7882",
    "sg:postcode":"77365",
    "sg:province":"TX",
    "sg:tags":[
        "handyman"
    ],
    "wof:name":"Modern Foundation Repair",
    "wof:placetype":"venue"
},
  "geometry": {"coordinates":[-95.257935,30.077725],"type":"Point"}
}