{
  "type": "Feature",
  "properties": {
    "iso:country":"US",
    "sg:address":"4101 Webb St",
    "sg:city":"Santa Fe",
    "sg:classifiers":[
        {
            "category":"Freight",
            "type":"Transportation"
        }
    ],
    "sg:phone":"+1 409 925 3919",
    "sg:postcode":"77517",
    "sg:province":"TX",
    "sg:tags":[
        "operator",
        "trucking"
    ],
    "wof:name":"Jacks Mobile Home Service",
    "wof:placetype":"venue"
},
  "geometry": {"coordinates":[-95.155725,29.397449],"type":"Point"}
}