{
  "type": "Feature",
  "properties": {
    "iso:country":"US",
    "sg:address":"9079 Old Hwy 62",
    "sg:city":"Orange",
    "sg:classifiers":[
        {
            "category":"Organizations",
            "subcategory":"Religious Organization",
            "type":"Services"
        }
    ],
    "sg:phone":"+1 409 745 4060",
    "sg:postcode":"77632",
    "sg:province":"TX",
    "sg:tags":[
        "church"
    ],
    "wof:name":"St Maurice Catholic Church",
    "wof:placetype":"venue"
},
  "geometry": {"coordinates":[-93.851529,30.178637],"type":"Point"}
}