{
  "type": "Feature",
  "properties": {
    "iso:country":"US",
    "sg:address":"1202 Tarpon Ave",
    "sg:city":"Port Isabel",
    "sg:classifiers":[
        {
            "category":"Professional",
            "type":"Services"
        }
    ],
    "sg:phone":"+1 956 943 3690",
    "sg:postcode":"78578",
    "sg:province":"TX",
    "wof:name":"Jeffery Chow",
    "wof:placetype":"venue"
},
  "geometry": {"coordinates":[-97.21590999999999,26.076338],"type":"Point"}
}