{
  "type": "Feature",
  "properties": {
    "iso:country":"US",
    "sg:address":"2850 N Main St",
    "sg:city":"Mansfield",
    "sg:classifiers":[
        {
            "category":"Manufacturing",
            "subcategory":"Metals",
            "type":"Manufacturing & Wholesale Goods"
        },
        {
            "category":"Autos & Motor Vehicles",
            "subcategory":"Auto Supplies",
            "type":"Retail Goods"
        }
    ],
    "sg:phone":"+1 817 483 2190",
    "sg:postcode":"76063",
    "sg:province":"TX",
    "sg:tags":[
        "plate",
        "mfg",
        "automobile",
        "work",
        "fabricated",
        "accessory"
    ],
    "wof:name":"Aluminum Tank & Truck",
    "wof:placetype":"venue"
},
  "geometry": {"coordinates":[-97.177498,32.605196],"type":"Point"}
}