{
  "type": "Feature",
  "properties": {
    "iso:country":"US",
    "sg:address":"760 N Hwy 67",
    "sg:city":"Cedar Hill",
    "sg:classifiers":[
        {
            "category":"Building & Trades",
            "subcategory":"Construction",
            "type":"Services"
        }
    ],
    "sg:phone":"+1 972 291 4048",
    "sg:postcode":"75104",
    "sg:province":"TX",
    "sg:tags":[
        "house"
    ],
    "wof:name":"Choice Homes Warranty Office",
    "wof:placetype":"venue"
},
  "geometry": {"coordinates":[-96.934614,32.60026],"type":"Point"}
}