{
  "type": "Feature",
  "properties": {
    "iso:country":"US",
    "sg:address":"5001 Natchez Dr",
    "sg:city":"Sachse",
    "sg:classifiers":[
        {
            "category":"Restaurant",
            "type":"Food & Drink"
        }
    ],
    "sg:phone":"+1 972 494 2160",
    "sg:postcode":"75048",
    "sg:province":"TX",
    "sg:tags":[
        "barbeque"
    ],
    "wof:name":"Moore's Barbeque House",
    "wof:placetype":"venue"
},
  "geometry": {"coordinates":[-96.608498,32.971401],"type":"Point"}
}