{
  "type": "Feature",
  "properties": {
    "iso:country":"US",
    "sg:address":"1537 N Durham Dr",
    "sg:city":"Houston",
    "sg:classifiers":[
        {
            "category":"Autos & Motor Vehicles",
            "subcategory":"Automobile Sales",
            "type":"Retail Goods"
        }
    ],
    "sg:phone":"+1 713 880 0304",
    "sg:postcode":"77008",
    "sg:province":"TX",
    "sg:tags":[
        "car",
        "dealer"
    ],
    "wof:name":"Luxury Auto Sales",
    "wof:placetype":"venue"
},
  "geometry": {"coordinates":[-95.411765,29.799396],"type":"Point"}
}