{
  "type": "Feature",
  "properties": {
    "iso:country":"US",
    "sg:address":"502 Doral Pl",
    "sg:city":"Garland",
    "sg:classifiers":[
        {
            "category":"Arts & Performance",
            "subcategory":"Theater",
            "type":"Entertainment"
        }
    ],
    "sg:phone":"+1 972 613 9942",
    "sg:postcode":"75043",
    "sg:province":"TX",
    "wof:name":"Metro Musical Productions",
    "wof:placetype":"venue"
},
  "geometry": {"coordinates":[-96.621802,32.847867],"type":"Point"}
}