{
  "type": "Feature",
  "properties": {
    "iso:country":"US",
    "sg:address":"406 Grandview Dr",
    "sg:city":"Gatesville",
    "sg:classifiers":[
        {
            "category":"Professional",
            "subcategory":"Management & Consulting",
            "type":"Services"
        }
    ],
    "sg:phone":"+1 254 865 2638",
    "sg:postcode":"76528",
    "sg:province":"TX",
    "wof:name":"Goodall Management Company",
    "wof:placetype":"venue"
},
  "geometry": {"coordinates":[-97.730982,31.427077],"type":"Point"}
}