{
  "type": "Feature",
  "properties": {
    "iso:country":"US",
    "sg:address":"120 N Wills St",
    "sg:city":"Wills Point",
    "sg:classifiers":[
        {
            "category":"Personal",
            "subcategory":"Barber",
            "type":"Services"
        }
    ],
    "sg:phone":"+1 903 873 2142",
    "sg:postcode":"75169",
    "sg:province":"TX",
    "sg:tags":[
        "shop"
    ],
    "wof:name":"City Barber Shop",
    "wof:placetype":"venue"
},
  "geometry": {"coordinates":[-96.011169,32.709199],"type":"Point"}
}