{
  "type": "Feature",
  "properties": {
    "iso:country":"US",
    "sg:address":"730 Linden St",
    "sg:city":"Fresno",
    "sg:classifiers":[
        {
            "category":"Building & Trades",
            "subcategory":"Construction",
            "type":"Services"
        }
    ],
    "sg:phone":"+1 281 431 5780",
    "sg:postcode":"77545",
    "sg:province":"TX",
    "sg:tags":[
        "contractor"
    ],
    "wof:name":"Tristan Drywall",
    "wof:placetype":"venue"
},
  "geometry": {"coordinates":[-95.462945,29.543052],"type":"Point"}
}