{
  "type": "Feature",
  "properties": {
    "iso:country":"US",
    "sg:address":"5515 Allen St",
    "sg:city":"Houston",
    "sg:classifiers":[
        {
            "category":"Manufacturing",
            "subcategory":"Building Materials",
            "type":"Manufacturing & Wholesale Goods"
        }
    ],
    "sg:phone":"+1 713 861 2081",
    "sg:postcode":"77007",
    "sg:province":"TX",
    "sg:tags":[
        "product",
        "wood",
        "mfg"
    ],
    "wof:name":"Weavers Woodshoppe",
    "wof:placetype":"venue"
},
  "geometry": {"coordinates":[-95.41543799999999,29.774057],"type":"Point"}
}