{
  "type": "Feature",
  "properties": {
    "iso:country":"US",
    "sg:address":"414 Vera Cruz",
    "sg:city":"San Antonio",
    "sg:classifiers":[
        {
            "category":"Wholesale",
            "subcategory":"Tobacco Products",
            "type":"Manufacturing & Wholesale Goods"
        }
    ],
    "sg:phone":"+1 210 226 4191",
    "sg:postcode":"78207",
    "sg:province":"TX",
    "sg:tags":[
        "cigarette",
        "cigar",
        "dealer"
    ],
    "sg:website":"www.finckcigar.com",
    "wof:name":"Finck Cigar Co",
    "wof:placetype":"venue"
},
  "geometry": {"coordinates":[-98.506851,29.415402],"type":"Point"}
}