{
  "type": "Feature",
  "properties": {
    "iso:country":"US",
    "sg:address":"9409 Shady Oaks Dr",
    "sg:city":"Austin",
    "sg:classifiers":[
        {
            "category":"Shopping",
            "subcategory":"Clothing, Apparel, & Fashions",
            "type":"Retail Goods"
        }
    ],
    "sg:phone":"+1 512 335 3655",
    "sg:postcode":"78729",
    "sg:province":"TX",
    "sg:tags":[
        "alteration"
    ],
    "wof:name":"Alterations & Veils-Beatrice",
    "wof:placetype":"venue"
},
  "geometry": {"coordinates":[-97.784662,30.455463],"type":"Point"}
}