{
  "type": "Feature",
  "properties": {
    "iso:country":"US",
    "sg:address":"11126 Shady Trl",
    "sg:city":"Dallas",
    "sg:classifiers":[
        {
            "category":"Professional",
            "subcategory":"Advertising",
            "type":"Services"
        }
    ],
    "sg:phone":"+1 469 522 7444",
    "sg:postcode":"75229",
    "sg:province":"TX",
    "sg:tags":[
        "distribution"
    ],
    "wof:name":"Empire Distributors Inc",
    "wof:placetype":"venue"
},
  "geometry": {"coordinates":[-96.890371,32.884435],"type":"Point"}
}