{
  "type": "Feature",
  "properties": {
    "iso:country":"US",
    "sg:address":"1529 Westfield Ln",
    "sg:city":"Pearland",
    "sg:classifiers":[
        {
            "category":"Building & Trades",
            "subcategory":"Construction",
            "type":"Services"
        }
    ],
    "sg:phone":"+1 281 482 4798",
    "sg:postcode":"77581",
    "sg:province":"TX",
    "sg:tags":[
        "house"
    ],
    "wof:name":"Bfr & Associates",
    "wof:placetype":"venue"
},
  "geometry": {"coordinates":[-95.23921900000001,29.536329],"type":"Point"}
}