{
  "type": "Feature",
  "properties": {
    "iso:country":"US",
    "sg:address":"3540 Hunt Ln",
    "sg:city":"San Antonio",
    "sg:classifiers":[
        {
            "category":"Freight",
            "type":"Transportation"
        }
    ],
    "sg:phone":"+1 210 674 1990",
    "sg:postcode":"78227",
    "sg:province":"TX",
    "sg:tags":[
        "special"
    ],
    "wof:name":"Central Self Storage",
    "wof:placetype":"venue"
},
  "geometry": {"coordinates":[-98.659826,29.394385],"type":"Point"}
}