{
  "type": "Feature",
  "properties": {
    "iso:country":"US",
    "sg:address":"619 W 29th St",
    "sg:city":"San Angelo",
    "sg:classifiers":[
        {
            "category":"Health Services",
            "subcategory":"Doctor",
            "type":"Services"
        }
    ],
    "sg:phone":"+1 325 653 7916",
    "sg:postcode":"76903",
    "sg:province":"TX",
    "sg:tags":[
        "medical"
    ],
    "wof:name":"Mendoza Pascual MD Ofc",
    "wof:placetype":"venue"
},
  "geometry": {"coordinates":[-100.46245500000001,31.48427],"type":"Point"}
}