{
  "type": "Feature",
  "properties": {
    "iso:country":"US",
    "sg:address":"207 E Main St",
    "sg:city":"Bellville",
    "sg:classifiers":[
        {
            "category":"Insurance",
            "subcategory":"Insurance Agent",
            "type":"Services"
        }
    ],
    "sg:phone":"+1 979 865 1742",
    "sg:postcode":"77418",
    "sg:province":"TX",
    "wof:name":"Pathfinder LL & D Ins Group",
    "wof:placetype":"venue"
},
  "geometry": {"coordinates":[-96.24606,29.94494],"type":"Point"}
}