{
  "type": "Feature",
  "properties": {
    "iso:country":"US",
    "sg:address":"5718 Mary Dell Dr",
    "sg:city":"Amarillo",
    "sg:classifiers":[
        {
            "category":"Professional",
            "type":"Services"
        }
    ],
    "sg:phone":"+1 806 359 6250",
    "sg:postcode":"79119",
    "sg:province":"TX",
    "sg:tags":[
        "establishment"
    ],
    "wof:name":"Avocompanies",
    "wof:placetype":"venue"
},
  "geometry": {"coordinates":[-101.9166,35.150476],"type":"Point"}
}