{
  "type": "Feature",
  "properties": {
    "iso:country":"US",
    "sg:address":"1123 W Tucker Blvd",
    "sg:city":"Arlington",
    "sg:classifiers":[
        {
            "category":"Professional",
            "subcategory":"Business Services",
            "type":"Services"
        }
    ],
    "sg:phone":"+1 817 275 3901",
    "sg:postcode":"76013",
    "sg:province":"TX",
    "wof:name":"Steve Joiner",
    "wof:placetype":"venue"
},
  "geometry": {"coordinates":[-97.122649,32.713547],"type":"Point"}
}