{
  "type": "Feature",
  "properties": {
    "iso:country":"US",
    "sg:address":"2301 N O Connor Rd",
    "sg:city":"Irving",
    "sg:classifiers":[
        {
            "category":"Shopping",
            "subcategory":"Gifts & Souvenirs",
            "type":"Retail Goods"
        }
    ],
    "sg:phone":"+1 972 255 0220",
    "sg:postcode":"75062",
    "sg:province":"TX",
    "wof:name":"Just Imagine",
    "wof:placetype":"venue"
},
  "geometry": {"coordinates":[-96.951308,32.839328],"type":"Point"}
}