{
  "type": "Feature",
  "properties": {
    "iso:country":"US",
    "sg:address":"4305 N Garfield St",
    "sg:city":"Midland",
    "sg:classifiers":[
        {
            "category":"Manufacturing",
            "subcategory":"Tools & Machinery",
            "type":"Manufacturing & Wholesale Goods"
        }
    ],
    "sg:phone":"+1 432 580 8085",
    "sg:postcode":"79705",
    "sg:province":"TX",
    "sg:tags":[
        "machine",
        "shop"
    ],
    "wof:name":"Farley Machine Works",
    "wof:placetype":"venue"
},
  "geometry": {"coordinates":[-102.11134300000001,32.032592],"type":"Point"}
}