{
  "type": "Feature",
  "properties": {
    "iso:country":"US",
    "sg:address":"703 E Gibbs St",
    "sg:city":"Del Rio",
    "sg:classifiers":[
        {
            "category":"Restaurant",
            "type":"Food & Drink"
        }
    ],
    "sg:phone":"+1 830 775 2696",
    "sg:postcode":"78840",
    "sg:province":"TX",
    "sg:tags":[
        "eating"
    ],
    "wof:name":"Seoul Restaurant",
    "wof:placetype":"venue"
},
  "geometry": {"coordinates":[-100.894756,29.366779],"type":"Point"}
}