{
  "type": "Feature",
  "properties": {
    "iso:country":"US",
    "sg:address":"1601 Rio Grande St",
    "sg:city":"Austin",
    "sg:classifiers":[
        {
            "category":"Professional",
            "type":"Services"
        }
    ],
    "sg:phone":"+1 512 474 2120",
    "sg:postcode":"78701",
    "sg:province":"TX",
    "sg:tags":[
        "establishment"
    ],
    "wof:name":"Patman William N Ofc",
    "wof:placetype":"venue"
},
  "geometry": {"coordinates":[-97.74555599999999,30.28069],"type":"Point"}
}