{
  "type": "Feature",
  "properties": {
    "iso:country":"US",
    "sg:address":"607 Ave K",
    "sg:city":"South Houston",
    "sg:classifiers":[
        {
            "category":"Bus Charters",
            "type":"Transportation"
        }
    ],
    "sg:phone":"+1 832 878 1461",
    "sg:postcode":"77587",
    "sg:province":"TX",
    "sg:tags":[
        "rental"
    ],
    "wof:name":"Freedom Tours",
    "wof:placetype":"venue"
},
  "geometry": {"coordinates":[-95.223259,29.656422],"type":"Point"}
}