{
  "type": "Feature",
  "properties": {
    "iso:country":"US",
    "sg:address":"10134 Red Wolf Ln",
    "sg:city":"Houston",
    "sg:classifiers":[
        {
            "category":"Retail",
            "subcategory":"Auto Repair",
            "type":"Services"
        }
    ],
    "sg:phone":"+1 281 469 6377",
    "sg:postcode":"77064",
    "sg:province":"TX",
    "sg:tags":[
        "automotive"
    ],
    "wof:name":"Big H Electric",
    "wof:placetype":"venue"
},
  "geometry": {"coordinates":[-95.56801900000001,29.918567],"type":"Point"}
}