{
  "type": "Feature",
  "properties": {
    "iso:country":"US",
    "sg:address":"1313 W San Antonio St",
    "sg:city":"New Braunfels",
    "sg:classifiers":[
        {
            "category":"Wholesale",
            "subcategory":"Durable Goods & Equipment",
            "type":"Manufacturing & Wholesale Goods"
        }
    ],
    "sg:phone":"+1 830 606 6801",
    "sg:postcode":"78130",
    "sg:province":"TX",
    "wof:name":"Five Crazy Broads",
    "wof:placetype":"venue"
},
  "geometry": {"coordinates":[-98.135183,29.691955],"type":"Point"}
}