{
  "type": "Feature",
  "properties": {
    "iso:country":"US",
    "sg:address":"228 Earl Garrett St",
    "sg:city":"Kerrville",
    "sg:classifiers":[
        {
            "category":"Museum",
            "type":"Entertainment"
        }
    ],
    "sg:phone":"+1 830 895 2911",
    "sg:postcode":"78028",
    "sg:province":"TX",
    "sg:tags":[
        "gallery"
    ],
    "wof:name":"Kerr Arts & Cultural Cent",
    "wof:placetype":"venue"
},
  "geometry": {"coordinates":[-99.139787,30.046294],"type":"Point"}
}