{
  "type": "Feature",
  "properties": {
    "iso:country":"US",
    "sg:address":"7402 Eastex Fwy",
    "sg:city":"Houston",
    "sg:classifiers":[
        {
            "category":"Wholesale",
            "subcategory":"Auto Parts",
            "type":"Manufacturing & Wholesale Goods"
        }
    ],
    "sg:phone":"+1 713 692 4471",
    "sg:postcode":"77093",
    "sg:province":"TX",
    "sg:tags":[
        "retail",
        "truck",
        "ne",
        "trailer"
    ],
    "wof:name":"Wabash National Trailer Ctrs",
    "wof:placetype":"venue"
},
  "geometry": {"coordinates":[-95.334616,29.829015],"type":"Point"}
}