{
  "type": "Feature",
  "properties": {
    "iso:country":"US",
    "sg:address":"4107 Naco Perrin Blvd",
    "sg:city":"San Antonio",
    "sg:classifiers":[
        {
            "category":"Restaurant",
            "type":"Food & Drink"
        }
    ],
    "sg:phone":"+1 210 646 0939",
    "sg:postcode":"78217",
    "sg:province":"TX",
    "sg:tags":[
        "eating"
    ],
    "wof:name":"China Sun Restaurant",
    "wof:placetype":"venue"
},
  "geometry": {"coordinates":[-98.41097499999999,29.544584],"type":"Point"}
}