{
  "type": "Feature",
  "properties": {
    "iso:country":"US",
    "sg:address":"334 Towne Oaks Dr",
    "sg:city":"Waco",
    "sg:classifiers":[
        {
            "category":"Professional",
            "subcategory":"Lawyer & Legal Services",
            "type":"Services"
        }
    ],
    "sg:phone":"+1 254 751 9133",
    "sg:postcode":"76710",
    "sg:province":"TX",
    "wof:name":"Flowers Davis Menard WITT",
    "wof:placetype":"venue"
},
  "geometry": {"coordinates":[-97.177796,31.523102],"type":"Point"}
}