{
  "type": "Feature",
  "properties": {
    "iso:country":"US",
    "sg:address":"112 Morningside Dr",
    "sg:city":"San Antonio",
    "sg:classifiers":[
        {
            "category":"Shopping",
            "subcategory":"Computers & Home Electronics",
            "type":"Retail Goods"
        }
    ],
    "sg:phone":"+1 210 240 6992",
    "sg:postcode":"78209",
    "sg:province":"TX",
    "wof:name":"Dealer Services",
    "wof:placetype":"venue"
},
  "geometry": {"coordinates":[-98.45504699999999,29.483589],"type":"Point"}
}