{
  "type": "Feature",
  "properties": {
    "iso:country":"US",
    "sg:address":"8329 Lenore St",
    "sg:city":"Houston",
    "sg:classifiers":[
        {
            "category":"Building & Trades",
            "subcategory":"Construction",
            "type":"Services"
        }
    ],
    "sg:phone":"+1 713 645 7270",
    "sg:postcode":"77017",
    "sg:province":"TX",
    "sg:tags":[
        "hanging",
        "contractor"
    ],
    "wof:name":"Lopez J Painting & Finishing",
    "wof:placetype":"venue"
},
  "geometry": {"coordinates":[-95.257074,29.68128],"type":"Point"}
}