{
  "type": "Feature",
  "properties": {
    "iso:country":"US",
    "sg:address":"1701 W US Hwy 287 Byp",
    "sg:city":"Waxahachie",
    "sg:classifiers":[
        {
            "category":"Retail",
            "subcategory":"Auto Rental",
            "type":"Services"
        }
    ],
    "sg:phone":"+1 972 923 2850",
    "sg:postcode":"75165",
    "sg:province":"TX",
    "sg:tags":[
        "car"
    ],
    "wof:name":"Hertz",
    "wof:placetype":"venue"
},
  "geometry": {"coordinates":[-96.855903,32.424606],"type":"Point"}
}