{
  "type": "Feature",
  "properties": {
    "iso:country":"US",
    "sg:address":"1661 Twin Cv",
    "sg:city":"Kyle",
    "sg:classifiers":[
        {
            "category":"Wholesale",
            "subcategory":"Medical Equipment & Supplies",
            "type":"Manufacturing & Wholesale Goods"
        }
    ],
    "sg:phone":"+1 512 787 8675",
    "sg:postcode":"78640",
    "sg:province":"TX",
    "wof:name":"Mtls Medical Technology Lift",
    "wof:placetype":"venue"
},
  "geometry": {"coordinates":[-97.842355,29.979444],"type":"Point"}
}