{
  "type": "Feature",
  "properties": {
    "iso:country":"US",
    "sg:address":"1010 Shady Oak Trl",
    "sg:city":"Mansfield",
    "sg:classifiers":[
        {
            "category":"Building & Trades",
            "subcategory":"Plumbing",
            "type":"Services"
        }
    ],
    "sg:phone":"+1 817 473 3554",
    "sg:postcode":"76063",
    "sg:province":"TX",
    "sg:tags":[
        "product",
        "management",
        "energy",
        "system"
    ],
    "wof:name":"Blue Ridge Energy",
    "wof:placetype":"venue"
},
  "geometry": {"coordinates":[-97.15024099999999,32.606741],"type":"Point"}
}