{
  "type": "Feature",
  "properties": {
    "iso:country":"US",
    "sg:address":"8608 Croydon Loop",
    "sg:city":"Austin",
    "sg:classifiers":[
        {
            "category":"Building & Trades",
            "subcategory":"Cleaning & Sanitation",
            "type":"Services"
        }
    ],
    "sg:phone":"+1 512 292 3135",
    "sg:postcode":"78748",
    "sg:province":"TX",
    "sg:tags":[
        "janitor"
    ],
    "wof:name":"Detail Floor Specialist",
    "wof:placetype":"venue"
},
  "geometry": {"coordinates":[-97.802285,30.179005],"type":"Point"}
}