{
  "type": "Feature",
  "properties": {
    "iso:country":"US",
    "sg:address":"320 E Tres Palacios Ave",
    "sg:city":"Palacios",
    "sg:classifiers":[
        {
            "category":"Building & Trades",
            "subcategory":"Plumbing",
            "type":"Services"
        }
    ],
    "sg:phone":"+1 361 972 0955",
    "sg:postcode":"77465",
    "sg:province":"TX",
    "sg:tags":[
        "contractor"
    ],
    "wof:name":"Ward Heating & AC",
    "wof:placetype":"venue"
},
  "geometry": {"coordinates":[-96.20737,28.721186],"type":"Point"}
}