{
  "type": "Feature",
  "properties": {
    "iso:country":"US",
    "sg:address":"1818 Waugh Dr",
    "sg:city":"Houston",
    "sg:classifiers":[
        {
            "category":"Retail",
            "subcategory":"Repair Shop",
            "type":"Services"
        }
    ],
    "sg:phone":"+1 832 202 0186",
    "sg:postcode":"77006",
    "sg:province":"TX",
    "wof:name":"1 Hour Emergency Locksmith",
    "wof:placetype":"venue"
},
  "geometry": {"coordinates":[-95.397156,29.751086],"type":"Point"}
}