{
  "type": "Feature",
  "properties": {
    "iso:country":"US",
    "sg:address":"2001 Deepwood Dr",
    "sg:city":"Round Rock",
    "sg:classifiers":[
        {
            "category":"Retail",
            "subcategory":"Repair Shop",
            "type":"Services"
        }
    ],
    "sg:phone":"+1 512 671 9349",
    "sg:postcode":"78681",
    "sg:province":"TX",
    "sg:tags":[
        "electronic"
    ],
    "wof:name":"Darrcorp Inc",
    "wof:placetype":"venue"
},
  "geometry": {"coordinates":[-97.69490399999999,30.492057],"type":"Point"}
}