{
  "type": "Feature",
  "properties": {
    "iso:country":"US",
    "sg:address":"3135 Garth Rd",
    "sg:city":"Baytown",
    "sg:classifiers":[
        {
            "category":"Professional",
            "type":"Services"
        }
    ],
    "sg:phone":"+1 281 422 4095",
    "sg:postcode":"77521",
    "sg:province":"TX",
    "wof:name":"Dcm International LLC",
    "wof:placetype":"venue"
},
  "geometry": {"coordinates":[-94.977276,29.755029],"type":"Point"}
}