{
  "type": "Feature",
  "properties": {
    "iso:country":"US",
    "sg:address":"7117 Belgold St",
    "sg:city":"Houston",
    "sg:classifiers":[
        {
            "category":"Manufacturing",
            "subcategory":"Tools & Machinery",
            "type":"Manufacturing & Wholesale Goods"
        },
        {
            "category":"Wholesale",
            "subcategory":"Electrical",
            "type":"Manufacturing & Wholesale Goods"
        },
        {
            "category":"Manufacturing",
            "subcategory":"Retail Goods",
            "type":"Manufacturing & Wholesale Goods"
        },
        {
            "category":"Building & Trades",
            "subcategory":"Electrical",
            "type":"Services"
        },
        {
            "category":"Wholesale",
            "subcategory":"Home Furnishings",
            "type":"Manufacturing & Wholesale Goods"
        }
    ],
    "sg:phone":"+1 281 866 0095",
    "sg:postcode":"77066",
    "sg:province":"TX",
    "sg:tags":[
        "industrial",
        "electrician",
        "electric",
        "supply",
        "household",
        "appliances-small-wholesale",
        "equipment",
        "fan",
        "contractors-commercial",
        "supplies-wholesale",
        "manufacturer"
    ],
    "wof:name":"Electrical Discount Supplier",
    "wof:placetype":"venue"
},
  "geometry": {"coordinates":[-95.53089,29.9618],"type":"Point"}
}