{
  "type": "Feature",
  "properties": {
    "iso:country":"US",
    "sg:address":"2309 Gus Thomasson Rd",
    "sg:city":"Dallas",
    "sg:classifiers":[
        {
            "category":"Airline",
            "type":"Transportation"
        }
    ],
    "sg:phone":"+1 214 320 1391",
    "sg:postcode":"75228",
    "sg:province":"TX",
    "sg:tags":[
        "grocery",
        "courier",
        "air"
    ],
    "wof:name":"Super Guanaco Express",
    "wof:placetype":"venue"
},
  "geometry": {"coordinates":[-96.674797,32.8349],"type":"Point"}
}