{
  "type": "Feature",
  "properties": {
    "iso:country":"US",
    "sg:address":"9531 Fallbrook Dr",
    "sg:city":"Houston",
    "sg:classifiers":[
        {
            "category":"Home & Garden",
            "subcategory":"Building Materials",
            "type":"Retail Goods"
        }
    ],
    "sg:phone":"+1 281 807 5554",
    "sg:postcode":"77064",
    "sg:province":"TX",
    "sg:tags":[
        "glass",
        "window",
        "plate"
    ],
    "wof:name":"Achieva Discount Glass",
    "wof:placetype":"venue"
},
  "geometry": {"coordinates":[-95.56715800000001,29.927439],"type":"Point"}
}