{
  "type": "Feature",
  "properties": {
    "iso:country":"US",
    "sg:address":"5425 S Padre Island Dr",
    "sg:city":"Corpus Christi",
    "sg:classifiers":[
        {
            "category":"Shopping",
            "subcategory":"Hobbies, Toys, & Games",
            "type":"Retail Goods"
        }
    ],
    "sg:phone":"+1 361 985 2552",
    "sg:postcode":"78411",
    "sg:province":"TX",
    "sg:tags":[
        "craft",
        "supply"
    ],
    "sg:website":"www.hobbylobby.com",
    "wof:name":"Hobby Lobby Creative Ctr",
    "wof:placetype":"venue"
},
  "geometry": {"coordinates":[-97.37392699999999,27.709031],"type":"Point"}
}