{
  "type": "Feature",
  "properties": {
    "iso:country":"US",
    "sg:address":"22016 Highland Knolls Dr",
    "sg:city":"Katy",
    "sg:classifiers":[
        {
            "category":"Travel",
            "subcategory":"Travel Agent",
            "type":"Entertainment"
        }
    ],
    "sg:phone":"+1 281 579 3535",
    "sg:postcode":"77450",
    "sg:province":"TX",
    "sg:tags":[
        "agency",
        "services-commercial"
    ],
    "wof:name":"Cole Travel Services Inc",
    "wof:placetype":"venue"
},
  "geometry": {"coordinates":[-95.753953,29.758474],"type":"Point"}
}