{
  "type": "Feature",
  "properties": {
    "iso:country":"US",
    "sg:address":"421 Eagle Dr",
    "sg:city":"Denton",
    "sg:classifiers":[
        {
            "category":"Retail",
            "subcategory":"Auto Repair",
            "type":"Services"
        }
    ],
    "sg:phone":"+1 940 383 1786",
    "sg:postcode":"76201",
    "sg:province":"TX",
    "sg:tags":[
        "transmission"
    ],
    "wof:name":"KWIK Kar Kare",
    "wof:placetype":"venue"
},
  "geometry": {"coordinates":[-97.136921,33.206438],"type":"Point"}
}