{
  "type": "Feature",
  "properties": {
    "iso:country":"US",
    "sg:address":"11806 Montebello Ct",
    "sg:city":"Tomball",
    "sg:classifiers":[
        {
            "category":"Retail",
            "subcategory":"Animal Services",
            "type":"Services"
        }
    ],
    "sg:phone":"+1 281 370 8025",
    "sg:postcode":"77377",
    "sg:province":"TX",
    "wof:name":"Dog Gone Realty Inc",
    "wof:placetype":"venue"
},
  "geometry": {"coordinates":[-95.596897,29.999786],"type":"Point"}
}