{
  "type": "Feature",
  "properties": {
    "iso:country":"US",
    "sg:address":"10748 Co Rd 571",
    "sg:city":"Blue Ridge",
    "sg:classifiers":[
        {
            "category":"Building & Trades",
            "subcategory":"Plumbing",
            "type":"Services"
        }
    ],
    "sg:phone":"+1 972 736 3220",
    "sg:postcode":"75424",
    "sg:province":"TX",
    "sg:tags":[
        "contractor"
    ],
    "wof:name":"Air Cndtning Innvtive Slutions",
    "wof:placetype":"venue"
},
  "geometry": {"coordinates":[-96.436162,33.246568],"type":"Point"}
}