{
  "type": "Feature",
  "properties": {
    "iso:country":"US",
    "sg:address":"1610 Buddy Holly Ave",
    "sg:city":"Lubbock",
    "sg:classifiers":[
        {
            "category":"Wholesale",
            "subcategory":"Apparel",
            "type":"Manufacturing & Wholesale Goods"
        }
    ],
    "sg:phone":"+1 806 744 4742",
    "sg:postcode":"79401",
    "sg:province":"TX",
    "sg:tags":[
        "farm",
        "raw",
        "product",
        "piece",
        "material"
    ],
    "wof:name":"Garner Cotton Co",
    "wof:placetype":"venue"
},
  "geometry": {"coordinates":[-101.84447299999999,33.579948],"type":"Point"}
}