{
  "type": "Feature",
  "properties": {
    "iso:country":"US",
    "sg:address":"2806 Mayfair Dr",
    "sg:city":"San Antonio",
    "sg:classifiers":[
        {
            "category":"Recreation",
            "type":"Entertainment"
        }
    ],
    "sg:phone":"+1 210 653 7718",
    "sg:postcode":"78217",
    "sg:province":"TX",
    "sg:tags":[
        "pool",
        "swimming"
    ],
    "wof:name":"Regency Swim Club",
    "wof:placetype":"venue"
},
  "geometry": {"coordinates":[-98.444148,29.530246],"type":"Point"}
}