{
  "type": "Feature",
  "properties": {
    "iso:country":"US",
    "sg:address":"4633 State St",
    "sg:city":"Abilene",
    "sg:classifiers":[
        {
            "category":"Professional",
            "subcategory":"Secretarial Services",
            "type":"Services"
        }
    ],
    "sg:phone":"+1 325 676 3016",
    "sg:postcode":"79603",
    "sg:province":"TX",
    "sg:tags":[
        "hearing",
        "reporter"
    ],
    "wof:name":"Stuart Sammye",
    "wof:placetype":"venue"
},
  "geometry": {"coordinates":[-99.78264,32.458644],"type":"Point"}
}