{
  "type": "Feature",
  "properties": {
    "iso:country":"US",
    "sg:address":"434 Billy B Dr",
    "sg:city":"Killeen",
    "sg:classifiers":[
        {
            "category":"Building & Trades",
            "subcategory":"Construction",
            "type":"Services"
        }
    ],
    "sg:phone":"+1 254 681 7391",
    "sg:postcode":"76542",
    "sg:province":"TX",
    "sg:tags":[
        "house"
    ],
    "wof:name":"Star B Enterprices",
    "wof:placetype":"venue"
},
  "geometry": {"coordinates":[-97.67111300000001,30.998864],"type":"Point"}
}