{
  "type": "Feature",
  "properties": {
    "iso:country":"US",
    "sg:address":"5930 Westgrove Dr",
    "sg:city":"Dallas",
    "sg:classifiers":[
        {
            "category":"Real Estate",
            "subcategory":"Real Estate Operator",
            "type":"Services"
        }
    ],
    "sg:phone":"+1 214 353 7500",
    "sg:postcode":"75248",
    "sg:province":"TX",
    "sg:tags":[
        "building",
        "nonresidential"
    ],
    "wof:name":"Texas Industrial Properties",
    "wof:placetype":"venue"
},
  "geometry": {"coordinates":[-96.808074,32.974318],"type":"Point"}
}