{
  "type": "Feature",
  "properties": {
    "iso:country":"US",
    "sg:address":"511 Neal St",
    "sg:city":"Baytown",
    "sg:classifiers":[
        {
            "category":"Professional",
            "type":"Services"
        }
    ],
    "sg:phone":"+1 281 422 8412",
    "sg:postcode":"77520",
    "sg:province":"TX",
    "wof:name":"Silverlil",
    "wof:placetype":"venue"
},
  "geometry": {"coordinates":[-94.97540600000001,29.722335],"type":"Point"}
}