{
  "type": "Feature",
  "properties": {
    "iso:country":"US",
    "sg:address":"302 Denver Ave",
    "sg:city":"Dalhart",
    "sg:classifiers":[
        {
            "category":"Farming",
            "subcategory":"Farm & Veterinary Services",
            "type":"Manufacturing & Wholesale Goods"
        }
    ],
    "sg:phone":"+1 806 249 5872",
    "sg:postcode":"79022",
    "sg:province":"TX",
    "sg:tags":[
        "breeder",
        "livestock"
    ],
    "wof:name":"Snead Cattle Co",
    "wof:placetype":"venue"
},
  "geometry": {"coordinates":[-102.33184799999999,35.689184],"type":"Point"}
}