{
  "type": "Feature",
  "properties": {
    "iso:country":"US",
    "sg:address":"817 Camino De Paz Ct",
    "sg:city":"El Paso",
    "sg:classifiers":[
        {
            "category":"Retail",
            "subcategory":"Veterinary Services",
            "type":"Services"
        }
    ],
    "sg:phone":"+1 915 833 1414",
    "sg:postcode":"79922",
    "sg:province":"TX",
    "sg:tags":[
        "veterinarian"
    ],
    "wof:name":"Mark Cox",
    "wof:placetype":"venue"
},
  "geometry": {"coordinates":[-106.602369,31.83178],"type":"Point"}
}