{
  "type": "Feature",
  "properties": {
    "iso:country":"US",
    "sg:address":"3417 Lawnwood St",
    "sg:city":"Fort Worth",
    "sg:classifiers":[
        {
            "category":"Manufacturing",
            "subcategory":"Rubber & Plastics",
            "type":"Manufacturing & Wholesale Goods"
        }
    ],
    "sg:phone":"+1 817 654 2917",
    "sg:postcode":"76111",
    "sg:province":"TX",
    "sg:tags":[
        "product",
        "foam",
        "mfg"
    ],
    "wof:name":"Foam Source",
    "wof:placetype":"venue"
},
  "geometry": {"coordinates":[-97.298323,32.761302],"type":"Point"}
}