{
  "type": "Feature",
  "properties": {
    "iso:country":"US",
    "sg:address":"8126 Lake June Rd",
    "sg:city":"Dallas",
    "sg:classifiers":[
        {
            "category":"Restaurant",
            "type":"Food & Drink"
        }
    ],
    "sg:phone":"+1 214 391 9109",
    "sg:postcode":"75217",
    "sg:province":"TX",
    "wof:name":"Sonic-Drive In",
    "wof:placetype":"venue"
},
  "geometry": {"coordinates":[-96.682198,32.734001],"type":"Point"}
}