{
  "type": "Feature",
  "properties": {
    "iso:country":"US",
    "sg:address":"302 Lorenaly Dr",
    "sg:city":"Brownsville",
    "sg:classifiers":[
        {
            "category":"Health Services",
            "subcategory":"Clinic",
            "type":"Services"
        }
    ],
    "sg:phone":"+1 956 350 2684",
    "sg:postcode":"78526",
    "sg:province":"TX",
    "sg:tags":[
        "welfare"
    ],
    "wof:name":"Center For Medical Genetics P",
    "wof:placetype":"venue"
},
  "geometry": {"coordinates":[-97.514568,25.971776],"type":"Point"}
}