{
  "type": "Feature",
  "properties": {
    "iso:country":"US",
    "sg:address":"350 N 37th St",
    "sg:city":"Orange",
    "sg:classifiers":[
        {
            "category":"Shopping",
            "subcategory":"Gifts & Souvenirs",
            "type":"Retail Goods"
        }
    ],
    "sg:phone":"+1 409 886 7649",
    "sg:postcode":"77630",
    "sg:province":"TX",
    "sg:tags":[
        "shop"
    ],
    "wof:name":"Thrift & Gift Shop",
    "wof:placetype":"venue"
},
  "geometry": {"coordinates":[-93.777036,30.092929],"type":"Point"}
}