{
  "type": "Feature",
  "properties": {
    "iso:country":"US",
    "sg:address":"1039 Roundrock Dr",
    "sg:city":"Saginaw",
    "sg:classifiers":[
        {
            "category":"Professional",
            "subcategory":"Management & Consulting",
            "type":"Services"
        }
    ],
    "sg:phone":"+1 817 232 4463",
    "sg:postcode":"76179",
    "sg:province":"TX",
    "sg:tags":[
        "organizing",
        "business",
        "services-household"
    ],
    "wof:name":"Frontier Management Co",
    "wof:placetype":"venue"
},
  "geometry": {"coordinates":[-97.384331,32.855141],"type":"Point"}
}