{
  "type": "Feature",
  "properties": {
    "iso:country":"US",
    "sg:address":"4016 Co Rd 1205",
    "sg:city":"Cleburne",
    "sg:classifiers":[
        {
            "category":"Building & Trades",
            "subcategory":"Construction",
            "type":"Services"
        }
    ],
    "sg:phone":"+1 817 556 2045",
    "sg:postcode":"76031",
    "sg:province":"TX",
    "sg:tags":[
        "excavation",
        "contractor"
    ],
    "wof:name":"RC Construction",
    "wof:placetype":"venue"
},
  "geometry": {"coordinates":[-97.380014,32.285396],"type":"Point"}
}