{
  "type": "Feature",
  "properties": {
    "iso:country":"US",
    "sg:address":"1309 W 1st St",
    "sg:city":"Austin",
    "sg:classifiers":[
        {
            "category":"Professional",
            "type":"Services"
        }
    ],
    "sg:phone":"+1 512 494 1371",
    "sg:postcode":"78703",
    "sg:province":"TX",
    "sg:tags":[
        "arts",
        "artist"
    ],
    "wof:name":"Marjorie Moore Studio",
    "wof:placetype":"venue"
},
  "geometry": {"coordinates":[-97.76099000000001,30.269064],"type":"Point"}
}