{
  "type": "Feature",
  "properties": {
    "iso:country":"US",
    "sg:address":"3000 S 31st St",
    "sg:city":"Temple",
    "sg:classifiers":[
        {
            "category":"Real Estate",
            "subcategory":"Real Estate Agent",
            "type":"Services"
        }
    ],
    "sg:phone":"+1 254 773 9958",
    "sg:postcode":"76502",
    "sg:province":"TX",
    "sg:tags":[
        "management"
    ],
    "wof:name":"Maupin Development Company Inc",
    "wof:placetype":"venue"
},
  "geometry": {"coordinates":[-97.36850699999999,31.072041],"type":"Point"}
}