{
  "type": "Feature",
  "properties": {
    "iso:country":"US",
    "sg:address":"2327 SW Military Dr",
    "sg:city":"San Antonio",
    "sg:classifiers":[
        {
            "category":"Banks & Credit Unions",
            "subcategory":"Bank",
            "type":"Services"
        }
    ],
    "sg:phone":"+1 210 341 9602",
    "sg:postcode":"78224",
    "sg:province":"TX",
    "wof:name":"Firstmark Credit Union",
    "wof:placetype":"venue"
},
  "geometry": {"coordinates":[-98.53048099999999,29.356733],"type":"Point"}
}