{
  "type": "Feature",
  "properties": {
    "iso:country":"US",
    "sg:address":"4708 Pewter Ln",
    "sg:city":"Austin",
    "sg:classifiers":[
        {
            "category":"Organizations",
            "subcategory":"Religious Organization",
            "type":"Services"
        }
    ],
    "sg:phone":"+1 512 524 0097",
    "sg:postcode":"78744",
    "sg:province":"TX",
    "sg:website":"www.newlifeec.com",
    "wof:name":"New Life Evangelistic Center",
    "wof:placetype":"venue"
},
  "geometry": {"coordinates":[-97.739913,30.200734],"type":"Point"}
}