{
  "type": "Feature",
  "properties": {
    "iso:country":"US",
    "sg:address":"560 W Lyndon B Johnson Fwy",
    "sg:city":"Irving",
    "sg:classifiers":[
        {
            "category":"Restaurant",
            "type":"Food & Drink"
        }
    ],
    "sg:phone":"+1 972 373 9944",
    "sg:postcode":"75063",
    "sg:province":"TX",
    "sg:tags":[
        "house",
        "steak"
    ],
    "sg:website":"www.saltgrass.com/",
    "wof:name":"Saltgrass Steakhouse",
    "wof:placetype":"venue"
},
  "geometry": {"coordinates":[-96.95543499999999,32.913858],"type":"Point"}
}