{
  "type": "Feature",
  "properties": {
    "iso:country":"US",
    "sg:address":"21407 Park Wick Ln",
    "sg:city":"Katy",
    "sg:classifiers":[
        {
            "category":"Personal",
            "subcategory":"Beauty Salon",
            "type":"Services"
        }
    ],
    "sg:phone":"+1 281 398 6098",
    "sg:postcode":"77450",
    "sg:province":"TX",
    "sg:tags":[
        "shop"
    ],
    "wof:name":"Beverly Boon",
    "wof:placetype":"venue"
},
  "geometry": {"coordinates":[-95.742564,29.768044],"type":"Point"}
}