{
  "type": "Feature",
  "properties": {
    "iso:country":"US",
    "sg:address":"622 Spring Lakes Haven",
    "sg:city":"Spring",
    "sg:classifiers":[
        {
            "category":"Professional",
            "subcategory":"Business Services",
            "type":"Services"
        }
    ],
    "sg:phone":"+1 281 353 1094",
    "sg:postcode":"77373",
    "sg:province":"TX",
    "wof:name":"Simple Steel Solutions",
    "wof:placetype":"venue"
},
  "geometry": {"coordinates":[-95.422771,30.064954],"type":"Point"}
}