{
  "type": "Feature",
  "properties": {
    "iso:country":"US",
    "sg:address":"15119 Coral Oak Ct",
    "sg:city":"Houston",
    "sg:classifiers":[
        {
            "category":"Professional",
            "subcategory":"Business Services",
            "type":"Services"
        }
    ],
    "sg:phone":"+1 281 218 6211",
    "sg:postcode":"77059",
    "sg:province":"TX",
    "wof:name":"Elcarim Interests",
    "wof:placetype":"venue"
},
  "geometry": {"coordinates":[-95.11999299999999,29.585756],"type":"Point"}
}