{
  "type": "Feature",
  "properties": {
    "iso:country":"US",
    "sg:address":"606 S Friendswood Dr",
    "sg:city":"Friendswood",
    "sg:classifiers":[
        {
            "category":"Retail",
            "subcategory":"Self-service Laundry",
            "type":"Services"
        }
    ],
    "sg:phone":"+1 281 482 4124",
    "sg:postcode":"77546",
    "sg:province":"TX",
    "sg:tags":[
        "coin"
    ],
    "wof:name":"Stones Throw Washateria",
    "wof:placetype":"venue"
},
  "geometry": {"coordinates":[-95.199297,29.527892],"type":"Point"}
}