{
  "type": "Feature",
  "properties": {
    "iso:country":"US",
    "sg:address":"501 E Mahl St",
    "sg:city":"Edinburg",
    "sg:classifiers":[
        {
            "category":"Building & Trades",
            "subcategory":"Landscaping Services",
            "type":"Services"
        }
    ],
    "sg:phone":"+1 956 316 2599",
    "sg:postcode":"78539",
    "sg:province":"TX",
    "wof:name":"Landscaping Etc",
    "wof:placetype":"venue"
},
  "geometry": {"coordinates":[-98.15722100000001,26.298558],"type":"Point"}
}