{
  "type": "Feature",
  "properties": {
    "iso:country":"US",
    "sg:address":"1110 Lolita St",
    "sg:city":"Corpus Christi",
    "sg:classifiers":[
        {
            "category":"Retail",
            "subcategory":"Repair Shop",
            "type":"Services"
        }
    ],
    "sg:phone":"+1 361 851 1440",
    "sg:postcode":"78416",
    "sg:province":"TX",
    "sg:tags":[
        "refrigeration"
    ],
    "wof:name":"Carlos Escamilla Jr",
    "wof:placetype":"venue"
},
  "geometry": {"coordinates":[-97.438265,27.759625],"type":"Point"}
}