{
  "type": "Feature",
  "properties": {
    "iso:country":"US",
    "sg:address":"8200 Cameron Rd",
    "sg:city":"Austin",
    "sg:classifiers":[
        {
            "category":"Building & Trades",
            "subcategory":"Electrical",
            "type":"Services"
        }
    ],
    "sg:phone":"+1 512 326 5100",
    "sg:postcode":"78754",
    "sg:province":"TX",
    "sg:tags":[
        "electrician"
    ],
    "wof:name":"Prism Electric",
    "wof:placetype":"venue"
},
  "geometry": {"coordinates":[-97.6825,30.338608],"type":"Point"}
}