{
  "type": "Feature",
  "properties": {
    "iso:country":"US",
    "sg:address":"2015 McKenzie Dr Ste 115",
    "sg:city":"Carrollton",
    "sg:classifiers":[
        {
            "category":"Education",
            "subcategory":"Vocational School",
            "type":"Public Place"
        }
    ],
    "sg:phone":"+1 972 620 2818",
    "sg:postcode":"75006",
    "sg:province":"TX",
    "sg:tags":[
        "cosmetology"
    ],
    "wof:name":"Demaur Cosmetic",
    "wof:placetype":"venue"
},
  "geometry": {"coordinates":[-96.917267,32.936709],"type":"Point"}
}