{
  "type": "Feature",
  "properties": {
    "iso:country":"US",
    "sg:address":"2314 Island Wood Rd",
    "sg:city":"Austin",
    "sg:classifiers":[
        {
            "category":"Professional",
            "subcategory":"Business Services",
            "type":"Services"
        }
    ],
    "sg:phone":"+1 512 263 0188",
    "sg:postcode":"78733",
    "sg:province":"TX",
    "wof:name":"Emodl Partnership Ltd",
    "wof:placetype":"venue"
},
  "geometry": {"coordinates":[-97.847308,30.337469],"type":"Point"}
}