{
  "type": "Feature",
  "properties": {
    "iso:country":"US",
    "sg:address":"110 Elizabeth St E",
    "sg:city":"Austin",
    "sg:classifiers":[
        {
            "category":"Shopping",
            "subcategory":"Clothing, Apparel, & Fashions",
            "type":"Retail Goods"
        }
    ],
    "sg:phone":"+1 512 447 7600",
    "sg:postcode":"78704",
    "sg:province":"TX",
    "wof:name":"Service Menswear",
    "wof:placetype":"venue"
},
  "geometry": {"coordinates":[-97.74885399999999,30.248685],"type":"Point"}
}