{
  "type": "Feature",
  "properties": {
    "iso:country":"US",
    "sg:address":"9705 Burnet Rd",
    "sg:city":"Austin",
    "sg:classifiers":[
        {
            "category":"Home & Garden",
            "subcategory":"Building Materials",
            "type":"Retail Goods"
        },
        {
            "category":"Building & Trades",
            "subcategory":"Construction",
            "type":"Services"
        }
    ],
    "sg:phone":"+1 512 336 1777",
    "sg:postcode":"78758",
    "sg:province":"TX",
    "sg:tags":[
        "screen",
        "window",
        "contractor"
    ],
    "wof:name":"Travelin Screens & More LLC",
    "wof:placetype":"venue"
},
  "geometry": {"coordinates":[-97.72449400000001,30.38122],"type":"Point"}
}