{
  "type": "Feature",
  "properties": {
    "iso:country":"US",
    "sg:address":"1180 N Dick Dowling St",
    "sg:city":"San Benito",
    "sg:classifiers":[
        {
            "category":"Shopping",
            "subcategory":"Computers & Home Electronics",
            "type":"Retail Goods"
        }
    ],
    "sg:phone":"+1 956 399 8046",
    "sg:postcode":"78586",
    "sg:province":"TX",
    "sg:tags":[
        "equipment",
        "satellite",
        "system"
    ],
    "wof:name":"F M Satellite",
    "wof:placetype":"venue"
},
  "geometry": {"coordinates":[-97.621764,26.137888],"type":"Point"}
}