{
  "type": "Feature",
  "properties": {
    "iso:country":"US",
    "sg:address":"2411 N Galloway Ave Ste 128",
    "sg:city":"Mesquite",
    "sg:classifiers":[
        {
            "category":"Health Services",
            "subcategory":"Doctor",
            "type":"Services"
        }
    ],
    "sg:phone":"+1 972 279 4411",
    "sg:postcode":"75150",
    "sg:province":"TX",
    "sg:tags":[
        "surgeon",
        "oral"
    ],
    "wof:name":"Tran Timmie DDS",
    "wof:placetype":"venue"
},
  "geometry": {"coordinates":[-96.61190000000001,32.797401],"type":"Point"}
}