{
  "type": "Feature",
  "properties": {
    "iso:country":"US",
    "sg:address":"375 Rabbit Run",
    "sg:city":"Waco",
    "sg:classifiers":[
        {
            "category":"Manufacturing",
            "subcategory":"Metals",
            "type":"Manufacturing & Wholesale Goods"
        }
    ],
    "sg:phone":"+1 254 666 2183",
    "sg:postcode":"76712",
    "sg:province":"TX",
    "sg:tags":[
        "fabricator",
        "sheet"
    ],
    "wof:name":"Specialty Sheet Metal Inc",
    "wof:placetype":"venue"
},
  "geometry": {"coordinates":[-97.293194,31.554815],"type":"Point"}
}