{
  "type": "Feature",
  "properties": {
    "iso:country":"US",
    "sg:address":"153 Hst Town Sq",
    "sg:city":"Lancaster",
    "sg:classifiers":[
        {
            "category":"Shopping",
            "subcategory":"Discount & Variety Stores",
            "type":"Retail Goods"
        }
    ],
    "sg:phone":"+1 972 227 7955",
    "sg:postcode":"75146",
    "sg:province":"TX",
    "sg:tags":[
        "merchandise",
        "general"
    ],
    "wof:name":"Lit'l Bit Of Texas",
    "wof:placetype":"venue"
},
  "geometry": {"coordinates":[-96.75574,32.592193],"type":"Point"}
}