{
  "type": "Feature",
  "properties": {
    "iso:country":"US",
    "sg:address":"312 Pearl St",
    "sg:city":"Denton",
    "sg:classifiers":[
        {
            "category":"Organizations",
            "subcategory":"Religious Organization",
            "type":"Services"
        }
    ],
    "sg:phone":"+1 940 387 3531",
    "sg:postcode":"76201",
    "sg:province":"TX",
    "wof:name":"Pearl Street Church of Christ",
    "wof:placetype":"venue"
},
  "geometry": {"coordinates":[-97.137007,33.217171],"type":"Point"}
}