{
  "type": "Feature",
  "properties": {
    "iso:country":"US",
    "sg:address":"211 Tyler Ave",
    "sg:city":"Lorenzo",
    "sg:classifiers":[
        {
            "category":"Organizations",
            "subcategory":"Religious Organization",
            "type":"Services"
        }
    ],
    "sg:phone":"+1 806 634 5601",
    "sg:postcode":"79343",
    "sg:province":"TX",
    "sg:tags":[
        "church"
    ],
    "wof:name":"First Baptist Church",
    "wof:placetype":"venue"
},
  "geometry": {"coordinates":[-101.53401100000001,33.673465],"type":"Point"}
}