{
  "type": "Feature",
  "properties": {
    "iso:country":"US",
    "sg:address":"519 N Main St",
    "sg:city":"Taylor",
    "sg:classifiers":[
        {
            "category":"Shopping",
            "subcategory":"Clothing, Apparel, & Fashions",
            "type":"Retail Goods"
        }
    ],
    "sg:phone":"+1 512 352 6963",
    "sg:postcode":"76574",
    "sg:province":"TX",
    "sg:tags":[
        "ready",
        "cosmetic"
    ],
    "wof:name":"Merle Norman Cosmetics",
    "wof:placetype":"venue"
},
  "geometry": {"coordinates":[-97.409953,30.572376],"type":"Point"}
}