{
  "type": "Feature",
  "properties": {
    "iso:country":"US",
    "sg:address":"3800 Camp Bowie Blvd",
    "sg:city":"Fort Worth",
    "sg:classifiers":[
        {
            "category":"Health Services",
            "subcategory":"Doctor",
            "type":"Services"
        }
    ],
    "sg:phone":"+1 817 348 8000",
    "sg:postcode":"76107",
    "sg:province":"TX",
    "sg:tags":[
        "medical",
        "osteopathic"
    ],
    "wof:name":"Weldon Medical Clinic",
    "wof:placetype":"venue"
},
  "geometry": {"coordinates":[-97.374707,32.745675],"type":"Point"}
}