{
  "type": "Feature",
  "properties": {
    "iso:country":"US",
    "sg:address":"938 Bar X Trl",
    "sg:city":"Angleton",
    "sg:classifiers":[
        {
            "category":"Building & Trades",
            "subcategory":"Construction",
            "type":"Services"
        }
    ],
    "sg:phone":"+1 979 849 3397",
    "sg:postcode":"77515",
    "sg:province":"TX",
    "sg:tags":[
        "insulation",
        "heat",
        "contractor"
    ],
    "wof:name":"Mutina Insulation",
    "wof:placetype":"venue"
},
  "geometry": {"coordinates":[-95.552173,29.137092],"type":"Point"}
}