{
  "type": "Feature",
  "properties": {
    "iso:country":"US",
    "sg:address":"1820 S Oak St",
    "sg:city":"Pearsall",
    "sg:classifiers":[
        {
            "category":"Retail",
            "subcategory":"Auto Repair",
            "type":"Services"
        }
    ],
    "sg:phone":"+1 830 334 4091",
    "sg:postcode":"78061",
    "sg:province":"TX",
    "sg:tags":[
        "wrecker"
    ],
    "wof:name":"Telles Towing & Storage Fclty",
    "wof:placetype":"venue"
},
  "geometry": {"coordinates":[-99.101246,28.875504],"type":"Point"}
}