{
  "type": "Feature",
  "properties": {
    "iso:country":"US",
    "sg:address":"19349 Old Wiederstein Rd",
    "sg:city":"Cibolo",
    "sg:classifiers":[
        {
            "category":"Professional",
            "subcategory":"Management & Consulting",
            "type":"Services"
        }
    ],
    "sg:phone":"+1 210 659 4747",
    "sg:postcode":"78108",
    "sg:province":"TX",
    "sg:tags":[
        "business"
    ],
    "wof:name":"Etc Information Services",
    "wof:placetype":"venue"
},
  "geometry": {"coordinates":[-98.25641299999999,29.604686],"type":"Point"}
}