{
  "type": "Feature",
  "properties": {
    "iso:country":"US",
    "sg:address":"1100 E Fm 150",
    "sg:city":"Kyle",
    "sg:classifiers":[
        {
            "category":"Farming",
            "subcategory":"Farm",
            "type":"Manufacturing & Wholesale Goods"
        }
    ],
    "sg:phone":"+1 512 268 2424",
    "sg:postcode":"78640",
    "sg:province":"TX",
    "wof:name":"Wiegand Farms",
    "wof:placetype":"venue"
},
  "geometry": {"coordinates":[-97.859123,29.972632],"type":"Point"}
}