{
  "type": "Feature",
  "properties": {
    "iso:country":"US",
    "sg:address":"5410 County Road 7350",
    "sg:city":"Lubbock",
    "sg:classifiers":[
        {
            "category":"Retail",
            "subcategory":"Car Wash",
            "type":"Services"
        }
    ],
    "sg:phone":"+1 806 786 3287",
    "sg:postcode":"79424",
    "sg:province":"TX",
    "wof:name":"R L Wash And Dry",
    "wof:placetype":"venue"
},
  "geometry": {"coordinates":[-101.926726,33.481191],"type":"Point"}
}