{
  "type": "Feature",
  "properties": {
    "iso:country":"US",
    "sg:address":"4811 Likins Cir",
    "sg:city":"Wichita Falls",
    "sg:classifiers":[
        {
            "category":"Building & Trades",
            "subcategory":"Landscaping Services",
            "type":"Services"
        }
    ],
    "sg:phone":"+1 940 696 5740",
    "sg:postcode":"76308",
    "sg:province":"TX",
    "sg:tags":[
        "lawn",
        "maintenance",
        "grounds"
    ],
    "wof:name":"O'Neil Mowing",
    "wof:placetype":"venue"
},
  "geometry": {"coordinates":[-98.56101200000001,33.853354],"type":"Point"}
}