{
  "type": "Feature",
  "properties": {
    "iso:country":"US",
    "sg:address":"356 N Belknap St",
    "sg:city":"Stephenville",
    "sg:classifiers":[
        {
            "category":"Government",
            "subcategory":"Police Station",
            "type":"Public Place"
        }
    ],
    "sg:phone":"+1 254 965 4111",
    "sg:postcode":"76401",
    "sg:province":"TX",
    "sg:tags":[
        "protection"
    ],
    "wof:name":"Police Department",
    "wof:placetype":"venue"
},
  "geometry": {"coordinates":[-98.203997,32.221725],"type":"Point"}
}