{
  "type": "Feature",
  "properties": {
    "iso:country":"US",
    "sg:address":"1115 Barkdull St",
    "sg:city":"Houston",
    "sg:classifiers":[
        {
            "category":"Personal",
            "type":"Services"
        },
        {
            "category":"Health Services",
            "subcategory":"Health Practitioner",
            "type":"Services"
        }
    ],
    "sg:phone":"+1 713 523 4118",
    "sg:postcode":"77006",
    "sg:province":"TX",
    "sg:tags":[
        "therapist",
        "massage"
    ],
    "wof:name":"Merric Elise Bartosch",
    "wof:placetype":"venue"
},
  "geometry": {"coordinates":[-95.393615,29.728458],"type":"Point"}
}