{
  "type": "Feature",
  "properties": {
    "iso:country":"US",
    "sg:address":"495 Spr 156",
    "sg:city":"Waskom",
    "sg:classifiers":[
        {
            "category":"Freight",
            "type":"Transportation"
        }
    ],
    "sg:phone":"+1 903 687 3301",
    "sg:postcode":"75692",
    "sg:province":"TX",
    "sg:tags":[
        "hauling",
        "trucking"
    ],
    "wof:name":"We Haul Of Minden Inc",
    "wof:placetype":"venue"
},
  "geometry": {"coordinates":[-94.05376200000001,32.473242],"type":"Point"}
}