{
  "type": "Feature",
  "properties": {
    "iso:country":"US",
    "sg:address":"313 NE 35th St",
    "sg:city":"Grand Prairie",
    "sg:classifiers":[
        {
            "category":"Building & Trades",
            "subcategory":"Construction",
            "type":"Services"
        }
    ],
    "sg:phone":"+1 972 721 1003",
    "sg:postcode":"75050",
    "sg:province":"TX",
    "sg:tags":[
        "repairing",
        "house",
        "remodeling",
        "contractor"
    ],
    "wof:name":"A-1 Lightfoot Construction",
    "wof:placetype":"venue"
},
  "geometry": {"coordinates":[-96.95410200000001,32.7514],"type":"Point"}
}