{
  "type": "Feature",
  "properties": {
    "iso:country":"US",
    "sg:address":"2210 N Story Rd",
    "sg:city":"Irving",
    "sg:classifiers":[
        {
            "category":"Airline",
            "type":"Transportation"
        }
    ],
    "sg:phone":"+1 800 238 5355",
    "sg:postcode":"75062",
    "sg:province":"TX",
    "sg:tags":[
        "courier",
        "air"
    ],
    "wof:name":"Fedex",
    "wof:placetype":"venue"
},
  "geometry": {"coordinates":[-96.976399,32.837352],"type":"Point"}
}