{
  "type": "Feature",
  "properties": {
    "iso:country":"US",
    "sg:address":"6301 Rehburg Rd",
    "sg:city":"Burton",
    "sg:classifiers":[
        {
            "category":"Travel",
            "subcategory":"Campground",
            "type":"Entertainment"
        }
    ],
    "sg:phone":"+1 979 289 3752",
    "sg:postcode":"77835",
    "sg:province":"TX",
    "sg:tags":[
        "camp"
    ],
    "sg:website":"www.campforall.org",
    "wof:name":"Camp For All",
    "wof:placetype":"venue"
},
  "geometry": {"coordinates":[-96.572878,30.246048],"type":"Point"}
}