{
  "type": "Feature",
  "properties": {
    "iso:country":"US",
    "sg:address":"439 Wildwood Trl",
    "sg:city":"Lorena",
    "sg:classifiers":[
        {
            "category":"Building & Trades",
            "subcategory":"Construction",
            "type":"Services"
        }
    ],
    "sg:phone":"+1 254 881 7454",
    "sg:postcode":"76655",
    "sg:province":"TX",
    "sg:tags":[
        "roofing",
        "contractor"
    ],
    "wof:name":"Flores Roofing & Remodeling",
    "wof:placetype":"venue"
},
  "geometry": {"coordinates":[-97.08821399999999,31.409416],"type":"Point"}
}