{
  "type": "Feature",
  "properties": {
    "iso:country":"US",
    "sg:address":"1313 Valwood Pkwy",
    "sg:city":"Carrollton",
    "sg:classifiers":[
        {
            "category":"Wholesale",
            "subcategory":"Electrical",
            "type":"Manufacturing & Wholesale Goods"
        }
    ],
    "sg:phone":"+1 972 484 9228",
    "sg:postcode":"75006",
    "sg:province":"TX",
    "sg:tags":[
        "equipment",
        "ultrasonic",
        "supply"
    ],
    "sg:website":"www.bransonultrasonics.com",
    "wof:name":"Branson Ultrasonics",
    "wof:placetype":"venue"
},
  "geometry": {"coordinates":[-96.91345,32.939257],"type":"Point"}
}