{
  "type": "Feature",
  "properties": {
    "iso:country":"US",
    "sg:address":"26035 Tomball Pkwy",
    "sg:city":"Tomball",
    "sg:classifiers":[
        {
            "category":"Building & Trades",
            "subcategory":"Landscaping Services",
            "type":"Services"
        }
    ],
    "sg:phone":"+1 281 255 2022",
    "sg:postcode":"77375",
    "sg:province":"TX",
    "sg:tags":[
        "contractor"
    ],
    "wof:name":"All American Stone & Turf",
    "wof:placetype":"venue"
},
  "geometry": {"coordinates":[-95.616874,30.056322],"type":"Point"}
}