{
  "type": "Feature",
  "properties": {
    "iso:country":"US",
    "sg:address":"3811 Turtle Creek Blvd",
    "sg:city":"Dallas",
    "sg:classifiers":[
        {
            "category":"Professional",
            "subcategory":"Lawyer & Legal Services",
            "type":"Services"
        }
    ],
    "sg:phone":"+1 214 651 6100",
    "sg:postcode":"75219",
    "sg:province":"TX",
    "wof:name":"Law Offices of Jeffrey H Rasanky PC",
    "wof:placetype":"venue"
},
  "geometry": {"coordinates":[-96.80059799999999,32.8134],"type":"Point"}
}