{
  "type": "Feature",
  "properties": {
    "iso:country":"US",
    "sg:address":"10134 Apple Creek Dr",
    "sg:city":"Dallas",
    "sg:classifiers":[
        {
            "category":"Health Services",
            "subcategory":"Clinic",
            "type":"Services"
        }
    ],
    "sg:phone":"+1 972 234 0686",
    "sg:postcode":"75243",
    "sg:province":"TX",
    "sg:tags":[
        "home",
        "care"
    ],
    "wof:name":"Wellness Matters",
    "wof:placetype":"venue"
},
  "geometry": {"coordinates":[-96.72072300000001,32.914565],"type":"Point"}
}