{
  "type": "Feature",
  "properties": {
    "iso:country":"US",
    "sg:address":"225 N Hamilton St",
    "sg:city":"Lueders",
    "sg:classifiers":[
        {
            "category":"Building & Trades",
            "subcategory":"Construction",
            "type":"Services"
        }
    ],
    "sg:phone":"+1 325 228 4647",
    "sg:postcode":"79533",
    "sg:province":"TX",
    "sg:tags":[
        "dry wall",
        "contractor"
    ],
    "wof:name":"Walcott Drywall & Paint",
    "wof:placetype":"venue"
},
  "geometry": {"coordinates":[-99.622362,32.803309],"type":"Point"}
}