{
  "type": "Feature",
  "properties": {
    "iso:country":"US",
    "sg:address":"66 N Acacia Park Cir",
    "sg:city":"Spring",
    "sg:classifiers":[
        {
            "category":"Recreation",
            "type":"Entertainment"
        }
    ],
    "sg:phone":"+1 281 356 5466",
    "sg:postcode":"77382",
    "sg:province":"TX",
    "wof:name":"Aerobics Design By Caroline",
    "wof:placetype":"venue"
},
  "geometry": {"coordinates":[-95.531029,30.218793],"type":"Point"}
}