{
  "type": "Feature",
  "properties": {
    "iso:country":"US",
    "sg:address":"231 W 3rd St",
    "sg:city":"Alice",
    "sg:classifiers":[
        {
            "category":"Food & Beverages",
            "subcategory":"Specialty",
            "type":"Retail Goods"
        }
    ],
    "sg:phone":"+1 361 668 4115",
    "sg:postcode":"78332",
    "sg:province":"TX",
    "wof:name":"A Leap of Faith Herbal Shop",
    "wof:placetype":"venue"
},
  "geometry": {"coordinates":[-98.078851,27.753168],"type":"Point"}
}