{
  "type": "Feature",
  "properties": {
    "iso:country":"US",
    "sg:address":"25201 Decker Prairie Rosehl Rd",
    "sg:city":"Magnolia",
    "sg:classifiers":[
        {
            "category":"Professional",
            "subcategory":"Business Services",
            "type":"Services"
        }
    ],
    "sg:phone":"+1 281 356 1714",
    "sg:postcode":"77355",
    "sg:province":"TX",
    "sg:tags":[
        "environmental",
        "ecological",
        "product"
    ],
    "wof:name":"Five JAB Environmental Service",
    "wof:placetype":"venue"
},
  "geometry": {"coordinates":[-95.683998,30.117229],"type":"Point"}
}