{
  "type": "Feature",
  "properties": {
    "iso:country":"US",
    "sg:address":"1961 Live Oak Cir",
    "sg:city":"Azle",
    "sg:classifiers":[
        {
            "category":"Structure",
            "subcategory":"Office Building",
            "type":"Public Place"
        }
    ],
    "sg:phone":"+1 817 237 5372",
    "sg:postcode":"76020",
    "sg:province":"TX",
    "sg:tags":[
        "park"
    ],
    "wof:name":"Mrl Properties",
    "wof:placetype":"venue"
},
  "geometry": {"coordinates":[-97.52375600000001,32.856799],"type":"Point"}
}