{
  "type": "Feature",
  "properties": {
    "iso:country":"US",
    "sg:address":"1212 E Anderson Ln Ste 100",
    "sg:city":"Austin",
    "sg:phone":"+1 512 873 8333",
    "sg:postcode":"78752",
    "sg:province":"TX",
    "wof:name":"Classic Soft Trim",
    "wof:placetype":"venue"
},
  "geometry": {"coordinates":[-97.686306,30.332105],"type":"Point"}
}