{
  "type": "Feature",
  "properties": {
    "iso:country":"US",
    "sg:address":"5206 S General Bruce Dr",
    "sg:city":"Temple",
    "sg:classifiers":[
        {
            "category":"Building & Trades",
            "subcategory":"Construction",
            "type":"Services"
        }
    ],
    "sg:phone":"+1 254 773 0765",
    "sg:postcode":"76502",
    "sg:province":"TX",
    "sg:tags":[
        "designer",
        "contractor",
        "concrete",
        "dealer",
        "pool",
        "swimming"
    ],
    "sg:website":"www.ramirezpools.com",
    "wof:name":"Ramirez Swimming Pools",
    "wof:placetype":"venue"
},
  "geometry": {"coordinates":[-97.40845899999999,31.083911],"type":"Point"}
}