{
  "type": "Feature",
  "properties": {
    "iso:country":"US",
    "sg:address":"500 E Round Grove Rd",
    "sg:city":"Lewisville",
    "sg:classifiers":[
        {
            "category":"Manufacturing",
            "subcategory":"Printing",
            "type":"Manufacturing & Wholesale Goods"
        }
    ],
    "sg:phone":"+1 972 316 0016",
    "sg:postcode":"75067",
    "sg:province":"TX",
    "sg:tags":[
        "printer"
    ],
    "wof:name":"Alpha Graphics",
    "wof:placetype":"venue"
},
  "geometry": {"coordinates":[-96.9756,33.00464],"type":"Point"}
}