{
  "type": "Feature",
  "properties": {
    "iso:country":"US",
    "sg:address":"12007 E Circle Dr",
    "sg:city":"Houston",
    "sg:classifiers":[
        {
            "category":"Shopping",
            "subcategory":"Clothing, Apparel, & Fashions",
            "type":"Retail Goods"
        }
    ],
    "sg:phone":"+1 713 779 7805",
    "sg:postcode":"77071",
    "sg:province":"TX",
    "wof:name":"Ilya International",
    "wof:placetype":"venue"
},
  "geometry": {"coordinates":[-95.51953,29.647867],"type":"Point"}
}