{
  "type": "Feature",
  "properties": {
    "iso:country":"US",
    "sg:address":"7707 Sandpiper Dr",
    "sg:city":"Houston",
    "sg:classifiers":[
        {
            "category":"Professional",
            "subcategory":"Computer Services",
            "type":"Services"
        }
    ],
    "sg:phone":"+1 281 855 9203",
    "sg:postcode":"77074",
    "sg:province":"TX",
    "sg:tags":[
        "related"
    ],
    "wof:name":"AC Tek Inc",
    "wof:placetype":"venue"
},
  "geometry": {"coordinates":[-95.50608699999999,29.69459],"type":"Point"}
}