{
  "type": "Feature",
  "properties": {
    "iso:country":"US",
    "sg:address":"9459 Maverick Pass",
    "sg:city":"San Antonio",
    "sg:classifiers":[
        {
            "category":"Building & Trades",
            "subcategory":"Pest Control",
            "type":"Services"
        }
    ],
    "sg:phone":"+1 210 694 5242",
    "sg:postcode":"78240",
    "sg:province":"TX",
    "wof:name":"Chaparral Pest Control & Spray",
    "wof:placetype":"venue"
},
  "geometry": {"coordinates":[-98.629778,29.52744],"type":"Point"}
}