{
  "type": "Feature",
  "properties": {
    "iso:country":"US",
    "sg:address":"3415 Bell St",
    "sg:city":"Amarillo",
    "sg:classifiers":[
        {
            "category":"Personal",
            "type":"Services"
        },
        {
            "category":"Personal",
            "subcategory":"Beauty Salon",
            "type":"Services"
        }
    ],
    "sg:phone":"+1 806 359 3830",
    "sg:postcode":"79109",
    "sg:province":"TX",
    "sg:tags":[
        "shop"
    ],
    "wof:name":"Super Tan",
    "wof:placetype":"venue"
},
  "geometry": {"coordinates":[-101.902197,35.17401],"type":"Point"}
}