{
  "type": "Feature",
  "properties": {
    "iso:country":"US",
    "sg:address":"2035 Feather Ln",
    "sg:city":"Lewisville",
    "sg:classifiers":[
        {
            "category":"Building & Trades",
            "subcategory":"Construction",
            "type":"Services"
        }
    ],
    "sg:phone":"+1 214 654 0800",
    "sg:postcode":"75077",
    "sg:province":"TX",
    "sg:tags":[
        "floor",
        "laying",
        "contractor"
    ],
    "wof:name":"Integrity Floors",
    "wof:placetype":"venue"
},
  "geometry": {"coordinates":[-97.03425,33.074368],"type":"Point"}
}