{
  "type": "Feature",
  "properties": {
    "iso:country":"US",
    "sg:address":"135 S Bay Dr",
    "sg:city":"Bullard",
    "sg:classifiers":[
        {
            "category":"Building & Trades",
            "subcategory":"Construction",
            "type":"Services"
        }
    ],
    "sg:phone":"+1 903 825 6704",
    "sg:postcode":"75757",
    "sg:province":"TX",
    "sg:tags":[
        "house"
    ],
    "wof:name":"Smart Construction",
    "wof:placetype":"venue"
},
  "geometry": {"coordinates":[-95.429498,32.158308],"type":"Point"}
}