{
  "type": "Feature",
  "properties": {
    "iso:country":"US",
    "sg:address":"2539 W Davis St",
    "sg:city":"Dallas",
    "sg:classifiers":[
        {
            "category":"Shopping",
            "subcategory":"Clothing, Apparel, & Fashions",
            "type":"Retail Goods"
        }
    ],
    "sg:phone":"+1 214 946 2087",
    "sg:postcode":"75211",
    "sg:province":"TX",
    "wof:name":"Taesung Inc",
    "wof:placetype":"venue"
},
  "geometry": {"coordinates":[-96.860572,32.749542],"type":"Point"}
}