{
  "type": "Feature",
  "properties": {
    "iso:country":"US",
    "sg:address":"14122 Greenranch Dr",
    "sg:city":"Houston",
    "sg:classifiers":[
        {
            "category":"Building & Trades",
            "subcategory":"Construction",
            "type":"Services"
        }
    ],
    "sg:phone":"+1 281 987 3833",
    "sg:postcode":"77039",
    "sg:province":"TX",
    "wof:name":"J J Davila Home Cnstr Co",
    "wof:placetype":"venue"
},
  "geometry": {"coordinates":[-95.347809,29.921097],"type":"Point"}
}