{
  "type": "Feature",
  "properties": {
    "iso:country":"US",
    "sg:address":"2526 Charter Oak Dr",
    "sg:city":"Temple",
    "sg:classifiers":[
        {
            "category":"Autos & Motor Vehicles",
            "subcategory":"Auto Supplies",
            "type":"Retail Goods"
        }
    ],
    "sg:phone":"+1 254 771 8100",
    "sg:postcode":"76502",
    "sg:province":"TX",
    "sg:tags":[
        "automobile",
        "parts"
    ],
    "sg:website":"www.advance-auto.com",
    "wof:name":"Advance Auto Parts Inc",
    "wof:placetype":"venue"
},
  "geometry": {"coordinates":[-97.40418,31.085974],"type":"Point"}
}