{
  "type": "Feature",
  "properties": {
    "iso:country":"US",
    "sg:address":"7280 Langtry St",
    "sg:city":"Houston",
    "sg:classifiers":[
        {
            "category":"Professional",
            "subcategory":"Advertising",
            "type":"Services"
        }
    ],
    "sg:phone":"+1 713 934 7917",
    "sg:postcode":"77040",
    "sg:province":"TX",
    "wof:name":"Flour Promotional Products Ctr",
    "wof:placetype":"venue"
},
  "geometry": {"coordinates":[-95.501216,29.83849],"type":"Point"}
}