{
  "type": "Feature",
  "properties": {
    "iso:country":"US",
    "sg:address":"326 Valley Cove Dr",
    "sg:city":"Richardson",
    "sg:classifiers":[
        {
            "category":"Organizations",
            "subcategory":"Religious Organization",
            "type":"Services"
        }
    ],
    "sg:phone":"+1 972 690 0373",
    "sg:postcode":"75080",
    "sg:province":"TX",
    "wof:name":"Sharing Our Life Inc",
    "wof:placetype":"venue"
},
  "geometry": {"coordinates":[-96.720715,32.993048],"type":"Point"}
}