{
  "type": "Feature",
  "properties": {
    "iso:country":"US",
    "sg:address":"1223 Gentle Bend Dr",
    "sg:city":"Missouri City",
    "sg:classifiers":[
        {
            "category":"Retail",
            "subcategory":"Repair Shop",
            "type":"Services"
        }
    ],
    "sg:phone":"+1 281 652 0059",
    "sg:postcode":"77489",
    "sg:province":"TX",
    "sg:tags":[
        "equipment",
        "medical"
    ],
    "wof:name":"Acceltek Inc",
    "wof:placetype":"venue"
},
  "geometry": {"coordinates":[-95.520439,29.597959],"type":"Point"}
}