{
  "type": "Feature",
  "properties": {
    "iso:country":"US",
    "sg:address":"18067 Forest Cedars Dr",
    "sg:city":"Houston",
    "sg:classifiers":[
        {
            "category":"Building & Trades",
            "subcategory":"Plumbing",
            "type":"Services"
        }
    ],
    "sg:phone":"+1 281 550 3991",
    "sg:postcode":"77084",
    "sg:province":"TX",
    "sg:tags":[
        "air",
        "heating",
        "conditioning",
        "contractor"
    ],
    "wof:name":"R & B Mechanical Inc",
    "wof:placetype":"venue"
},
  "geometry": {"coordinates":[-95.67674,29.854893],"type":"Point"}
}