{
  "type": "Feature",
  "properties": {
    "iso:country":"US",
    "sg:address":"16639 Village View Trl",
    "sg:city":"Sugar Land",
    "sg:classifiers":[
        {
            "category":"Professional",
            "subcategory":"Computer Services",
            "type":"Services"
        }
    ],
    "sg:phone":"+1 832 567 6836",
    "sg:postcode":"77478",
    "sg:province":"TX",
    "sg:tags":[
        "development",
        "software"
    ],
    "wof:name":"Kadsys Solutions LLC",
    "wof:placetype":"venue"
},
  "geometry": {"coordinates":[-95.669921,29.645676],"type":"Point"}
}