{
  "type": "Feature",
  "properties": {
    "iso:country":"US",
    "sg:address":"9219 Summer Wind St",
    "sg:city":"San Antonio",
    "sg:classifiers":[
        {
            "category":"Building & Trades",
            "subcategory":"Cleaning & Sanitation",
            "type":"Services"
        }
    ],
    "sg:phone":"+1 210 657 9747",
    "sg:postcode":"78217",
    "sg:province":"TX",
    "sg:tags":[
        "maintenance"
    ],
    "wof:name":"A Busy Bee Hot Water Pres",
    "wof:placetype":"venue"
},
  "geometry": {"coordinates":[-98.402846,29.524182],"type":"Point"}
}