{
  "type": "Feature",
  "properties": {
    "iso:country":"US",
    "sg:address":"6190 Lyndon B Johnson Fwy",
    "sg:city":"Dallas",
    "sg:classifiers":[
        {
            "category":"Health Services",
            "subcategory":"Doctor",
            "type":"Services"
        }
    ],
    "sg:phone":"+1 972 851 0055",
    "sg:postcode":"75240",
    "sg:province":"TX",
    "sg:tags":[
        "physician",
        "surgeon"
    ],
    "wof:name":"David Brehm Pa",
    "wof:placetype":"venue"
},
  "geometry": {"coordinates":[-96.803578,32.924998],"type":"Point"}
}