{
  "type": "Feature",
  "properties": {
    "iso:country":"US",
    "sg:address":"1202 Pine Fork Ct",
    "sg:city":"Houston",
    "sg:classifiers":[
        {
            "category":"Professional",
            "subcategory":"Computer Services",
            "type":"Services"
        }
    ],
    "sg:phone":"+1 281 461 1988",
    "sg:postcode":"77062",
    "sg:province":"TX",
    "sg:tags":[
        "programing",
        "custom"
    ],
    "wof:name":"Suretutorcom",
    "wof:placetype":"venue"
},
  "geometry": {"coordinates":[-95.13829,29.581094],"type":"Point"}
}