{
  "type": "Feature",
  "properties": {
    "iso:country":"US",
    "sg:address":"3902 Ave A",
    "sg:city":"Lubbock",
    "sg:classifiers":[
        {
            "category":"Wholesale",
            "subcategory":"Chemicals & Plastics",
            "type":"Manufacturing & Wholesale Goods"
        }
    ],
    "sg:phone":"+1 806 749 1332",
    "sg:postcode":"79404",
    "sg:province":"TX",
    "wof:name":"Lubbock Oxygen & Medical Gases",
    "wof:placetype":"venue"
},
  "geometry": {"coordinates":[-101.835711,33.557851],"type":"Point"}
}