{
  "type": "Feature",
  "properties": {
    "iso:country":"US",
    "sg:address":"137 Taylor St",
    "sg:city":"Keller",
    "sg:classifiers":[
        {
            "category":"Government",
            "subcategory":"Fire Station",
            "type":"Public Place"
        }
    ],
    "sg:phone":"+1 817 431 3371",
    "sg:postcode":"76248",
    "sg:province":"TX",
    "sg:tags":[
        "protection"
    ],
    "wof:name":"Keller Fire Administration",
    "wof:placetype":"venue"
},
  "geometry": {"coordinates":[-97.253063,32.933806],"type":"Point"}
}