{
  "type": "Feature",
  "properties": {
    "iso:country":"US",
    "sg:address":"521 Bardfield Ave",
    "sg:city":"Garland",
    "sg:classifiers":[
        {
            "category":"Wholesale",
            "subcategory":"Computers",
            "type":"Manufacturing & Wholesale Goods"
        },
        {
            "category":"Professional",
            "subcategory":"Computer Services",
            "type":"Services"
        }
    ],
    "sg:phone":"+1 972 271 6898",
    "sg:postcode":"75041",
    "sg:province":"TX",
    "sg:tags":[
        "publisher",
        "software",
        "developer",
        "equipment"
    ],
    "sg:website":"http://www.quantrac.com",
    "wof:name":"Quantrac Corp",
    "wof:placetype":"venue"
},
  "geometry": {"coordinates":[-96.63596,32.870713],"type":"Point"}
}