{
  "type": "Feature",
  "properties": {
    "iso:country":"US",
    "sg:address":"11530 Edgemere Blvd",
    "sg:city":"El Paso",
    "sg:classifiers":[
        {
            "category":"Education",
            "subcategory":"School",
            "type":"Public Place"
        }
    ],
    "sg:phone":"+1 915 937 4400",
    "sg:postcode":"79936",
    "sg:province":"TX",
    "wof:name":"Bill Sybert School",
    "wof:placetype":"venue"
},
  "geometry": {"coordinates":[-106.29061299999999,31.791319],"type":"Point"}
}