{
  "type": "Feature",
  "properties": {
    "iso:country":"US",
    "sg:address":"1004 Donna Dr",
    "sg:city":"Hallettsville",
    "sg:classifiers":[
        {
            "category":"Home & Garden",
            "subcategory":"Furniture",
            "type":"Retail Goods"
        }
    ],
    "sg:phone":"+1 361 798 4805",
    "sg:postcode":"77964",
    "sg:province":"TX",
    "wof:name":"MBC Furniture Sources",
    "wof:placetype":"venue"
},
  "geometry": {"coordinates":[-96.95603199999999,29.443537],"type":"Point"}
}