{
  "type": "Feature",
  "properties": {
    "iso:country":"US",
    "sg:address":"105 10th Ave",
    "sg:city":"Canyon",
    "sg:classifiers":[
        {
            "category":"Autos & Motor Vehicles",
            "subcategory":"Automobile Sales",
            "type":"Retail Goods"
        }
    ],
    "sg:phone":"+1 806 655 3339",
    "sg:postcode":"79015",
    "sg:province":"TX",
    "sg:tags":[
        "used"
    ],
    "wof:name":"Canyon Motors",
    "wof:placetype":"venue"
},
  "geometry": {"coordinates":[-101.944311,34.973804],"type":"Point"}
}