{
  "type": "Feature",
  "properties": {
    "iso:country":"US",
    "sg:address":"3765 Acorn Circuit",
    "sg:city":"Beaumont",
    "sg:classifiers":[
        {
            "category":"Building & Trades",
            "subcategory":"Construction",
            "type":"Services"
        }
    ],
    "sg:phone":"+1 409 924 8723",
    "sg:postcode":"77703",
    "sg:province":"TX",
    "sg:tags":[
        "house"
    ],
    "wof:name":"Rjs Trinity Home Improvement",
    "wof:placetype":"venue"
},
  "geometry": {"coordinates":[-94.138108,30.12064],"type":"Point"}
}