{
  "type": "Feature",
  "properties": {
    "iso:country":"US",
    "sg:address":"1927 E 8th St",
    "sg:city":"Odessa",
    "sg:classifiers":[
        {
            "category":"Restaurant",
            "type":"Food & Drink"
        }
    ],
    "sg:phone":"+1 432 580 0483",
    "sg:postcode":"79761",
    "sg:province":"TX",
    "wof:name":"Jumburrito Mexican Food Rstrnt",
    "wof:placetype":"venue"
},
  "geometry": {"coordinates":[-102.346031,31.86107],"type":"Point"}
}