{
  "type": "Feature",
  "properties": {
    "iso:country":"US",
    "sg:address":"18502 Purdy Ct",
    "sg:city":"Houston",
    "sg:classifiers":[
        {
            "category":"Professional",
            "subcategory":"Management & Consulting",
            "type":"Services"
        }
    ],
    "sg:phone":"+1 281 578 7544",
    "sg:postcode":"77084",
    "sg:province":"TX",
    "sg:tags":[
        "database",
        "computer",
        "software"
    ],
    "wof:name":"V/Soft Software",
    "wof:placetype":"venue"
},
  "geometry": {"coordinates":[-95.69257399999999,29.817987],"type":"Point"}
}