{
  "type": "Feature",
  "properties": {
    "iso:country":"US",
    "sg:address":"11258 Cedar Park",
    "sg:city":"San Antonio",
    "sg:classifiers":[
        {
            "category":"Professional",
            "type":"Services"
        }
    ],
    "sg:phone":"+1 210 690 5927",
    "sg:postcode":"78249",
    "sg:province":"TX",
    "wof:name":"Felix S Lopez 3 Vc11627",
    "wof:placetype":"venue"
},
  "geometry": {"coordinates":[-98.641569,29.553903],"type":"Point"}
}