{
  "type": "Feature",
  "properties": {
    "iso:country":"US",
    "sg:address":"425 Cooper Ln",
    "sg:city":"Coppell",
    "sg:classifiers":[
        {
            "category":"Professional",
            "type":"Services"
        }
    ],
    "sg:phone":"+1 972 462 9533",
    "sg:postcode":"75019",
    "sg:province":"TX",
    "wof:name":"B G Aviation Svc",
    "wof:placetype":"venue"
},
  "geometry": {"coordinates":[-97.00191100000001,32.959503],"type":"Point"}
}