{
  "type": "Feature",
  "properties": {
    "iso:country":"US",
    "sg:address":"302 N Jackson St",
    "sg:city":"Jacksonville",
    "sg:classifiers":[
        {
            "category":"Autos & Motor Vehicles",
            "subcategory":"Auto Supplies",
            "type":"Retail Goods"
        }
    ],
    "sg:phone":"+1 903 589 8000",
    "sg:postcode":"75766",
    "sg:province":"TX",
    "wof:name":"Discount Wheel & Tire",
    "wof:placetype":"venue"
},
  "geometry": {"coordinates":[-95.272774,31.967945],"type":"Point"}
}