{
  "type": "Feature",
  "properties": {
    "iso:country":"US",
    "sg:address":"5017 Garth Rd",
    "sg:city":"Baytown",
    "sg:classifiers":[
        {
            "category":"Restaurant",
            "type":"Food & Drink"
        }
    ],
    "sg:menulink":"http://www.allmenus.com/tx/baytown/94570-dominos-pizza/menu/",
    "sg:phone":"+1 281 427 8813",
    "sg:postcode":"77521",
    "sg:province":"TX",
    "sg:tags":[
        "american",
        "wing",
        "pizza"
    ],
    "wof:name":"Domino's Pizza",
    "wof:placetype":"venue"
},
  "geometry": {"coordinates":[-94.977812,29.779082],"type":"Point"}
}