{
  "type": "Feature",
  "properties": {
    "iso:country":"US",
    "sg:address":"332 E Ave D",
    "sg:city":"Killeen",
    "sg:classifiers":[
        {
            "category":"Restaurant",
            "type":"Food & Drink"
        }
    ],
    "sg:phone":"+1 254 526 3065",
    "sg:postcode":"76541",
    "sg:province":"TX",
    "sg:tags":[
        "eating"
    ],
    "wof:name":"Koba Wood Restaurant",
    "wof:placetype":"venue"
},
  "geometry": {"coordinates":[-97.727053,31.119826],"type":"Point"}
}