{
  "type": "Feature",
  "properties": {
    "iso:country":"US",
    "sg:address":"9500 S Ih-35 Ste H",
    "sg:city":"Austin",
    "sg:classifiers":[
        {
            "category":"Shopping",
            "subcategory":"Baby Store",
            "type":"Retail Goods"
        },
        {
            "category":"Shopping",
            "subcategory":"Department Store",
            "type":"Retail Goods"
        },
        {
            "category":"Shopping",
            "subcategory":"Clothing, Apparel, & Fashions",
            "type":"Retail Goods"
        }
    ],
    "sg:phone":"+1 512 280 3872",
    "sg:postcode":"78748",
    "sg:province":"TX",
    "sg:tags":[
        "furniture",
        "clothing",
        "gear",
        "women's"
    ],
    "sg:website":"www.JCPenney.com",
    "wof:name":"JCPenney",
    "wof:placetype":"venue"
},
  "geometry": {"coordinates":[-97.790065,30.160954],"type":"Point"}
}