{
  "type": "Feature",
  "properties": {
    "iso:country":"US",
    "sg:address":"4902 Russet Hill Dr",
    "sg:city":"Austin",
    "sg:classifiers":[
        {
            "category":"Building & Trades",
            "subcategory":"Cleaning & Sanitation",
            "type":"Services"
        }
    ],
    "sg:phone":"+1 512 758 0530",
    "sg:postcode":"78723",
    "sg:province":"TX",
    "sg:tags":[
        "home"
    ],
    "wof:name":"Maids R Us",
    "wof:placetype":"venue"
},
  "geometry": {"coordinates":[-97.67267,30.289452],"type":"Point"}
}