{
  "type": "Feature",
  "properties": {
    "iso:country":"US",
    "sg:address":"402 S New Mexico Dr",
    "sg:city":"Celina",
    "sg:classifiers":[
        {
            "category":"Organizations",
            "subcategory":"Religious Organization",
            "type":"Services"
        }
    ],
    "sg:phone":"+1 972 382 2333",
    "sg:postcode":"75009",
    "sg:province":"TX",
    "sg:tags":[
        "church"
    ],
    "wof:name":"St Philip's Baptist Church",
    "wof:placetype":"venue"
},
  "geometry": {"coordinates":[-96.782895,33.319221],"type":"Point"}
}