{
  "type": "Feature",
  "properties": {
    "iso:country":"US",
    "sg:address":"1441 Baffin Bay Dr",
    "sg:city":"Plano",
    "sg:classifiers":[
        {
            "category":"Professional",
            "subcategory":"Management & Consulting",
            "type":"Services"
        }
    ],
    "sg:phone":"+1 972 516 1177",
    "sg:postcode":"75075",
    "sg:province":"TX",
    "wof:name":"WJP Enterprises",
    "wof:placetype":"venue"
},
  "geometry": {"coordinates":[-96.72246699999999,33.0339],"type":"Point"}
}