{
  "type": "Feature",
  "properties": {
    "iso:country":"US",
    "sg:address":"1909 Clinton Dr",
    "sg:city":"Galena Park",
    "sg:classifiers":[
        {
            "category":"Wholesale",
            "subcategory":"Electrical",
            "type":"Manufacturing & Wholesale Goods"
        }
    ],
    "sg:phone":"+1 713 676 1666",
    "sg:postcode":"77547",
    "sg:province":"TX",
    "sg:tags":[
        "electronics"
    ],
    "wof:name":"Sammys Trade",
    "wof:placetype":"venue"
},
  "geometry": {"coordinates":[-95.24082,29.732519],"type":"Point"}
}