{
  "type": "Feature",
  "properties": {
    "iso:country":"US",
    "sg:address":"12505 Reed Rd",
    "sg:city":"Sugar Land",
    "sg:classifiers":[
        {
            "category":"Wholesale",
            "subcategory":"Sporting Goods",
            "type":"Manufacturing & Wholesale Goods"
        }
    ],
    "sg:phone":"+1 281 491 4653",
    "sg:postcode":"77478",
    "sg:province":"TX",
    "wof:name":"Re-Load Recycled Golf Balls",
    "wof:placetype":"venue"
},
  "geometry": {"coordinates":[-95.601178,29.635144],"type":"Point"}
}