{
  "type": "Feature",
  "properties": {
    "iso:country":"US",
    "sg:address":"16635 Seawolf Dr",
    "sg:city":"Houston",
    "sg:classifiers":[
        {
            "category":"Social Services",
            "subcategory":"Child Care",
            "type":"Services"
        }
    ],
    "sg:phone":"+1 281 280 0988",
    "sg:postcode":"77062",
    "sg:province":"TX",
    "wof:name":"Cradle and Crayon",
    "wof:placetype":"venue"
},
  "geometry": {"coordinates":[-95.12740700000001,29.552295],"type":"Point"}
}