{
  "type": "Feature",
  "properties": {
    "iso:country":"US",
    "sg:address":"318 E College St",
    "sg:city":"Stephenville",
    "sg:classifiers":[
        {
            "category":"Real Estate",
            "subcategory":"Real Estate Agent",
            "type":"Services"
        }
    ],
    "sg:phone":"+1 254 965 5212",
    "sg:postcode":"76401",
    "sg:province":"TX",
    "sg:tags":[
        "appraiser"
    ],
    "wof:name":"Skipper Real Estate",
    "wof:placetype":"venue"
},
  "geometry": {"coordinates":[-98.199602,32.220917],"type":"Point"}
}