{
  "type": "Feature",
  "properties": {
    "iso:country":"US",
    "sg:address":"1601 S Gregg St",
    "sg:city":"Big Spring",
    "sg:classifiers":[
        {
            "category":"Restaurant",
            "type":"Food & Drink"
        }
    ],
    "sg:phone":"+1 432 267 3281",
    "sg:postcode":"79720",
    "sg:province":"TX",
    "wof:name":"Hermans Restaurant",
    "wof:placetype":"venue"
},
  "geometry": {"coordinates":[-101.47322699999999,32.23905],"type":"Point"}
}