{
  "type": "Feature",
  "properties": {
    "iso:country":"US",
    "sg:address":"709 Retriever Ln",
    "sg:city":"Mesquite",
    "sg:classifiers":[
        {
            "category":"Professional",
            "subcategory":"Business Services",
            "type":"Services"
        }
    ],
    "sg:phone":"+1 972 613 1620",
    "sg:postcode":"75150",
    "sg:province":"TX",
    "wof:name":"Maximus Digital Design",
    "wof:placetype":"venue"
},
  "geometry": {"coordinates":[-96.606627,32.799947],"type":"Point"}
}