{
  "type": "Feature",
  "properties": {
    "iso:country":"US",
    "sg:address":"1044 W Craig Pl",
    "sg:city":"San Antonio",
    "sg:classifiers":[
        {
            "category":"Professional",
            "subcategory":"Art Services",
            "type":"Services"
        }
    ],
    "sg:phone":"+1 210 735 4399",
    "sg:postcode":"78201",
    "sg:province":"TX",
    "sg:tags":[
        "commercial",
        "design"
    ],
    "wof:name":"Castor and Pollux Fine AR",
    "wof:placetype":"venue"
},
  "geometry": {"coordinates":[-98.51114099999999,29.451841],"type":"Point"}
}