{
  "type": "Feature",
  "properties": {
    "iso:country":"US",
    "sg:address":"8452 Hunnicut Rd",
    "sg:city":"Dallas",
    "sg:classifiers":[
        {
            "category":"Shopping",
            "subcategory":"Clothing, Apparel, & Fashions",
            "type":"Retail Goods"
        }
    ],
    "sg:phone":"+1 214 327 9097",
    "sg:postcode":"75228",
    "sg:province":"TX",
    "sg:tags":[
        "family"
    ],
    "wof:name":"Atomic Airbrush Division",
    "wof:placetype":"venue"
},
  "geometry": {"coordinates":[-96.698594,32.803743],"type":"Point"}
}