{
  "type": "Feature",
  "properties": {
    "iso:country":"US",
    "sg:address":"4300 US Hwy 183",
    "sg:city":"Austin",
    "sg:classifiers":[
        {
            "category":"Building & Trades",
            "subcategory":"Construction",
            "type":"Services"
        }
    ],
    "sg:phone":"+1 512 386 5852",
    "sg:postcode":"78744",
    "sg:province":"TX",
    "sg:tags":[
        "painter"
    ],
    "wof:name":"Huitron Painting Corp",
    "wof:placetype":"venue"
},
  "geometry": {"coordinates":[-97.686274,30.188031],"type":"Point"}
}