{
  "type": "Feature",
  "properties": {
    "iso:country":"US",
    "sg:address":"6506 Stefani Dr",
    "sg:city":"Dallas",
    "sg:classifiers":[
        {
            "category":"Professional",
            "subcategory":"Engineering",
            "type":"Services"
        }
    ],
    "sg:phone":"+1 214 361 7977",
    "sg:postcode":"75225",
    "sg:province":"TX",
    "sg:tags":[
        "engineer"
    ],
    "wof:name":"Cecil H Smith PE",
    "wof:placetype":"venue"
},
  "geometry": {"coordinates":[-96.794894,32.878022],"type":"Point"}
}