{
  "type": "Feature",
  "properties": {
    "iso:country":"US",
    "sg:address":"1666 N Hampton Rd",
    "sg:city":"Dallas",
    "sg:classifiers":[
        {
            "category":"Health Services",
            "subcategory":"Clinic",
            "type":"Services"
        }
    ],
    "sg:phone":"+1 972 228 0011",
    "sg:postcode":"75208",
    "sg:province":"TX",
    "sg:tags":[
        "home",
        "care"
    ],
    "wof:name":"D C P Health Care Solutions",
    "wof:placetype":"venue"
},
  "geometry": {"coordinates":[-96.85639399999999,32.767378],"type":"Point"}
}