{
  "type": "Feature",
  "properties": {
    "iso:country":"US",
    "sg:address":"23851 State Hwy 46",
    "sg:city":"Spring Branch",
    "sg:classifiers":[
        {
            "category":"Retail",
            "subcategory":"Animal Services",
            "type":"Services"
        }
    ],
    "sg:phone":"+1 830 980 8444",
    "sg:postcode":"78070",
    "sg:province":"TX",
    "sg:tags":[
        "pet",
        "boarding",
        "sitting"
    ],
    "wof:name":"Rover's Ranch Pet Resort",
    "wof:placetype":"venue"
},
  "geometry": {"coordinates":[-98.479332,29.798219],"type":"Point"}
}