{
  "type": "Feature",
  "properties": {
    "iso:country":"US",
    "sg:address":"4444 Cullen Blvd Apt 510",
    "sg:city":"Houston",
    "sg:classifiers":[
        {
            "category":"Education",
            "subcategory":"University",
            "type":"Public Place"
        }
    ],
    "sg:phone":"+1 713 748 3179",
    "sg:postcode":"77004",
    "sg:province":"TX",
    "sg:tags":[
        "college"
    ],
    "wof:name":"University of Houston",
    "wof:placetype":"venue"
},
  "geometry": {"coordinates":[-95.34918999999999,29.714329],"type":"Point"}
}