{
  "type": "Feature",
  "properties": {
    "iso:country":"US",
    "sg:address":"382 W Main St",
    "sg:city":"League City",
    "sg:classifiers":[
        {
            "category":"Wholesale",
            "subcategory":"Hardware",
            "type":"Manufacturing & Wholesale Goods"
        }
    ],
    "sg:phone":"+1 281 554 5887",
    "sg:postcode":"77573",
    "sg:province":"TX",
    "sg:tags":[
        "air",
        "electrical",
        "heating",
        "conditioning"
    ],
    "wof:name":"Graham Alton Gary",
    "wof:placetype":"venue"
},
  "geometry": {"coordinates":[-95.097639,29.507037],"type":"Point"}
}