{
  "type": "Feature",
  "properties": {
    "iso:country":"US",
    "sg:address":"12802 State Hwy 7 W",
    "sg:city":"Joaquin",
    "sg:classifiers":[
        {
            "category":"Building & Trades",
            "subcategory":"Construction",
            "type":"Services"
        }
    ],
    "sg:phone":"+1 936 269 3612",
    "sg:postcode":"75964",
    "sg:province":"TX",
    "sg:tags":[
        "maintenance",
        "contractor"
    ],
    "wof:name":"Joaquin Isd Bus Barn Maint Dpt",
    "wof:placetype":"venue"
},
  "geometry": {"coordinates":[-94.80536499999999,31.501341],"type":"Point"}
}