{
  "type": "Feature",
  "properties": {
    "iso:country":"US",
    "sg:address":"1560 Bay Area Blvd",
    "sg:city":"Houston",
    "sg:classifiers":[
        {
            "category":"Social Services",
            "type":"Services"
        }
    ],
    "sg:phone":"+1 281 480 7788",
    "sg:postcode":"77058",
    "sg:province":"TX",
    "sg:tags":[
        "counseling"
    ],
    "wof:name":"Baybrook Counseling",
    "wof:placetype":"venue"
},
  "geometry": {"coordinates":[-95.115247,29.561459],"type":"Point"}
}