{
  "type": "Feature",
  "properties": {
    "iso:country":"US",
    "sg:address":"3204 Landershire Ln",
    "sg:city":"Plano",
    "sg:classifiers":[
        {
            "category":"Education",
            "subcategory":"Dance Studio",
            "type":"Public Place"
        }
    ],
    "sg:phone":"+1 972 985 6191",
    "sg:postcode":"75023",
    "sg:province":"TX",
    "wof:name":"Dance Club 2000",
    "wof:placetype":"venue"
},
  "geometry": {"coordinates":[-96.75452900000001,33.045734],"type":"Point"}
}