{
  "type": "Feature",
  "properties": {
    "iso:country":"US",
    "sg:address":"2665 Villa Creek Dr",
    "sg:city":"Dallas",
    "sg:classifiers":[
        {
            "category":"Professional",
            "type":"Services"
        },
        {
            "category":"Shopping",
            "subcategory":"Pharmacy",
            "type":"Retail Goods"
        }
    ],
    "sg:phone":"+1 214 239 1500",
    "sg:postcode":"75234",
    "sg:province":"TX",
    "wof:name":"Pharmastaff USA Inc",
    "wof:placetype":"venue"
},
  "geometry": {"coordinates":[-96.881972,32.912127],"type":"Point"}
}