{
  "type": "Feature",
  "properties": {
    "iso:country":"US",
    "sg:address":"2533 Waits Ave",
    "sg:city":"Fort Worth",
    "sg:classifiers":[
        {
            "category":"Manufacturing",
            "subcategory":"Aerospace",
            "type":"Manufacturing & Wholesale Goods"
        }
    ],
    "sg:phone":"+1 817 266 7980",
    "sg:postcode":"76109",
    "sg:province":"TX",
    "wof:name":"Grace Aerospace Inc",
    "wof:placetype":"venue"
},
  "geometry": {"coordinates":[-97.35713699999999,32.71507],"type":"Point"}
}