{
  "type": "Feature",
  "properties": {
    "iso:country":"US",
    "sg:address":"6442 Chesley Ln",
    "sg:city":"Dallas",
    "sg:classifiers":[
        {
            "category":"Personal",
            "type":"Services"
        }
    ],
    "sg:phone":"+1 214 746 8889",
    "sg:postcode":"75214",
    "sg:province":"TX",
    "sg:tags":[
        "party",
        "planning",
        "event"
    ],
    "sg:website":"www.bicknerdancefloors.com",
    "wof:name":"Bickner Dance Floor Rentals",
    "wof:placetype":"venue"
},
  "geometry": {"coordinates":[-96.752002,32.846427],"type":"Point"}
}