{
  "type": "Feature",
  "properties": {
    "iso:country":"US",
    "sg:address":"9401 S. Main St.",
    "sg:city":"Houston",
    "sg:classifiers":[
        {
            "category":"Restaurant",
            "type":"Food & Drink"
        }
    ],
    "sg:phone":"+1 713 432 0212",
    "sg:postcode":"77025",
    "sg:province":"TX",
    "sg:tags":[
        "mexican"
    ],
    "sg:website":"www.taqueriasarandas.com",
    "wof:name":"Taquerias Arandas #33",
    "wof:placetype":"venue"
},
  "geometry": {"coordinates":[-95.423765,29.6823],"type":"Point"}
}