{
  "type": "Feature",
  "properties": {
    "iso:country":"US",
    "sg:address":"3200 Winchester Dr",
    "sg:city":"Plano",
    "sg:classifiers":[
        {
            "category":"Professional",
            "subcategory":"Management & Consulting",
            "type":"Services"
        }
    ],
    "sg:phone":"+1 972 867 0768",
    "sg:postcode":"75075",
    "sg:province":"TX",
    "sg:tags":[
        "business"
    ],
    "wof:name":"Dispute Management Services",
    "wof:placetype":"venue"
},
  "geometry": {"coordinates":[-96.75615500000001,33.032375],"type":"Point"}
}