{
  "type": "Feature",
  "properties": {
    "iso:country":"US",
    "sg:address":"637 N Town East Blvd",
    "sg:city":"Mesquite",
    "sg:classifiers":[
        {
            "category":"Shopping",
            "subcategory":"Books",
            "type":"Retail Goods"
        },
        {
            "category":"Wholesale",
            "subcategory":"Books, Periodicals, & Newspapers",
            "type":"Manufacturing & Wholesale Goods"
        }
    ],
    "sg:phone":"+1 972 681 8281",
    "sg:postcode":"75150",
    "sg:province":"TX",
    "sg:tags":[
        "books-wholesale",
        "store",
        "manufacturer"
    ],
    "wof:name":"Itty Bitty's Books",
    "wof:placetype":"venue"
},
  "geometry": {"coordinates":[-96.606009,32.813894],"type":"Point"}
}