{
  "type": "Feature",
  "properties": {
    "iso:country":"US",
    "sg:address":"1332 Belt Line Rd",
    "sg:city":"Garland",
    "sg:classifiers":[
        {
            "category":"Personal",
            "subcategory":"Beauty Salon",
            "type":"Services"
        }
    ],
    "sg:phone":"+1 972 675 1439",
    "sg:postcode":"75040",
    "sg:province":"TX",
    "wof:name":"Hair Creations",
    "wof:placetype":"venue"
},
  "geometry": {"coordinates":[-96.64554099999999,32.944524],"type":"Point"}
}