{
  "type": "Feature",
  "properties": {
    "iso:country":"US",
    "sg:address":"6317 Bee Caves Road Suite 300",
    "sg:city":"Austin",
    "sg:classifiers":[
        {
            "category":"Shopping",
            "type":"Retail Goods"
        }
    ],
    "sg:phone":"+1 512 327 5002",
    "sg:postcode":"78746",
    "sg:province":"TX",
    "sg:website":"batteriesplus.com",
    "wof:name":"Batteries Plus",
    "wof:placetype":"venue"
},
  "geometry": {"coordinates":[-97.83208999999999,30.296657],"type":"Point"}
}