{
  "type": "Feature",
  "properties": {
    "iso:country":"US",
    "sg:address":"209 Majestic Grove",
    "sg:city":"San Antonio",
    "sg:classifiers":[
        {
            "category":"Professional",
            "subcategory":"Business Services",
            "type":"Services"
        }
    ],
    "sg:phone":"+1 210 481 1478",
    "sg:postcode":"78258",
    "sg:province":"TX",
    "wof:name":"Ba Enterprises LLC",
    "wof:placetype":"venue"
},
  "geometry": {"coordinates":[-98.497282,29.660436],"type":"Point"}
}