{
  "type": "Feature",
  "properties": {
    "iso:country":"US",
    "sg:address":"2307 Bellechasse Ct",
    "sg:city":"Midland",
    "sg:classifiers":[
        {
            "category":"Banks & Credit Unions",
            "subcategory":"Investment Brokerage",
            "type":"Services"
        }
    ],
    "sg:phone":"+1 432 620 8201",
    "sg:postcode":"79705",
    "sg:province":"TX",
    "sg:tags":[
        "advisory"
    ],
    "wof:name":"Cain Financial",
    "wof:placetype":"venue"
},
  "geometry": {"coordinates":[-102.114227,32.040736],"type":"Point"}
}