{
  "type": "Feature",
  "properties": {
    "iso:country":"US",
    "sg:address":"504 Co Rd 304",
    "sg:city":"Bertram",
    "sg:classifiers":[
        {
            "category":"Building & Trades",
            "subcategory":"Pest Control",
            "type":"Services"
        }
    ],
    "sg:phone":"+1 512 715 9313",
    "sg:postcode":"78605",
    "sg:province":"TX",
    "wof:name":"Circle S Pest Control",
    "wof:placetype":"venue"
},
  "geometry": {"coordinates":[-98.13220099999999,30.751808],"type":"Point"}
}