{
  "type": "Feature",
  "properties": {
    "iso:country":"US",
    "sg:address":"3801 Lakeview Pkwy",
    "sg:city":"Garland",
    "sg:classifiers":[
        {
            "category":"Real Estate",
            "subcategory":"Real Estate Services",
            "type":"Services"
        }
    ],
    "sg:phone":"+1 469 326 1200",
    "sg:postcode":"75074",
    "sg:province":"TX",
    "sg:tags":[
        "management",
        "property"
    ],
    "wof:name":"Real Estate Expo",
    "wof:placetype":"venue"
},
  "geometry": {"coordinates":[-96.567001,32.907998],"type":"Point"}
}