{
  "type": "Feature",
  "properties": {
    "iso:country":"US",
    "sg:address":"2050 Regal Pkwy",
    "sg:city":"Euless",
    "sg:classifiers":[
        {
            "category":"Wholesale",
            "subcategory":"Machinery & Supplies",
            "type":"Manufacturing & Wholesale Goods"
        },
        {
            "category":"Freight",
            "type":"Transportation"
        }
    ],
    "sg:phone":"+1 817 355 0262",
    "sg:postcode":"76040",
    "sg:province":"TX",
    "sg:tags":[
        "casket",
        "establishment",
        "general"
    ],
    "wof:name":"Aurora Casket Company",
    "wof:placetype":"venue"
},
  "geometry": {"coordinates":[-97.118371,32.817666],"type":"Point"}
}