{
  "type": "Feature",
  "properties": {
    "iso:country":"US",
    "sg:address":"1302 Boyles St",
    "sg:city":"Houston",
    "sg:classifiers":[
        {
            "category":"Retail",
            "subcategory":"Laundry & Dry Cleaning",
            "type":"Services"
        }
    ],
    "sg:phone":"+1 713 678 7910",
    "sg:postcode":"77020",
    "sg:province":"TX",
    "sg:tags":[
        "linen",
        "supply"
    ],
    "wof:name":"Shepherds Uniform",
    "wof:placetype":"venue"
},
  "geometry": {"coordinates":[-95.299542,29.764582],"type":"Point"}
}