{
  "type": "Feature",
  "properties": {
    "iso:country":"US",
    "sg:address":"530 Wells Fargo Dr",
    "sg:city":"Houston",
    "sg:classifiers":[
        {
            "category":"Health Services",
            "subcategory":"Health Practitioner",
            "type":"Services"
        }
    ],
    "sg:phone":"+1 713 522 3045",
    "sg:postcode":"77090",
    "sg:province":"TX",
    "sg:tags":[
        "psychotherapist"
    ],
    "wof:name":"Bonnie Headington",
    "wof:placetype":"venue"
},
  "geometry": {"coordinates":[-95.434408,30.014504],"type":"Point"}
}