{
  "type": "Feature",
  "properties": {
    "iso:country":"US",
    "sg:address":"306 N Cedar Dr",
    "sg:city":"Allen",
    "sg:classifiers":[
        {
            "category":"Professional",
            "type":"Services"
        }
    ],
    "sg:phone":"+1 972 727 9693",
    "sg:postcode":"75002",
    "sg:province":"TX",
    "sg:tags":[
        "establishment"
    ],
    "wof:name":"Moores Memorial Sanctuary",
    "wof:placetype":"venue"
},
  "geometry": {"coordinates":[-96.66628,33.105845],"type":"Point"}
}