{
  "type": "Feature",
  "properties": {
    "iso:country":"US",
    "sg:address":"3514 156th St",
    "sg:city":"Lubbock",
    "sg:classifiers":[
        {
            "category":"Real Estate",
            "subcategory":"Real Estate Operator",
            "type":"Services"
        }
    ],
    "sg:phone":"+1 806 863 4376",
    "sg:postcode":"79423",
    "sg:province":"TX",
    "sg:tags":[
        "building",
        "nonresidential"
    ],
    "wof:name":"C&R Properties",
    "wof:placetype":"venue"
},
  "geometry": {"coordinates":[-101.89102099999999,33.452903],"type":"Point"}
}