{
  "type": "Feature",
  "properties": {
    "iso:country":"US",
    "sg:address":"400 Porter St",
    "sg:city":"Taylor",
    "sg:classifiers":[
        {
            "category":"Government",
            "subcategory":"Office",
            "type":"Public Place"
        }
    ],
    "sg:phone":"+1 512 352 3675",
    "sg:postcode":"76574",
    "sg:province":"TX",
    "sg:tags":[
        "city"
    ],
    "wof:name":"City of Taylor",
    "wof:placetype":"venue"
},
  "geometry": {"coordinates":[-97.40866699999999,30.571683],"type":"Point"}
}