{
  "type": "Feature",
  "properties": {
    "iso:country":"US",
    "sg:address":"819 Krenek Tap Rd",
    "sg:city":"College Station",
    "sg:classifiers":[
        {
            "category":"Real Estate",
            "subcategory":"Real Estate Operator",
            "type":"Services"
        }
    ],
    "sg:phone":"+1 979 695 9889",
    "sg:postcode":"77840",
    "sg:province":"TX",
    "sg:tags":[
        "apartment"
    ],
    "wof:name":"Terrace Pines Apartments",
    "wof:placetype":"venue"
},
  "geometry": {"coordinates":[-96.296926,30.61224],"type":"Point"}
}