{
  "type": "Feature",
  "properties": {
    "iso:country":"US",
    "sg:address":"2425 Gus Thomasson Rd",
    "sg:city":"Dallas",
    "sg:classifiers":[
        {
            "category":"Wholesale",
            "subcategory":"Medical Equipment & Supplies",
            "type":"Manufacturing & Wholesale Goods"
        },
        {
            "category":"Building & Trades",
            "subcategory":"Equipment Rental",
            "type":"Services"
        },
        {
            "category":"Health Services",
            "subcategory":"Hospital",
            "type":"Services"
        }
    ],
    "sg:phone":"+1 214 328 0712",
    "sg:postcode":"75228",
    "sg:province":"TX",
    "sg:tags":[
        "physician",
        "surgeon",
        "rent"
    ],
    "sg:website":"www.afrmed.com",
    "wof:name":"Aids For Recovery Medical Eqpt",
    "wof:placetype":"venue"
},
  "geometry": {"coordinates":[-96.675152,32.83484],"type":"Point"}
}