{
  "type": "Feature",
  "properties": {
    "iso:country":"US",
    "sg:address":"4223 Richmond Ave Ste 100",
    "sg:city":"Houston",
    "sg:classifiers":[
        {
            "category":"Health Services",
            "subcategory":"Doctor",
            "type":"Services"
        }
    ],
    "sg:phone":"+1 713 351 0630",
    "sg:postcode":"77027",
    "sg:province":"TX",
    "wof:name":"Houston Metro Urology",
    "wof:placetype":"venue"
},
  "geometry": {"coordinates":[-95.446175,29.732283],"type":"Point"}
}