{
  "type": "Feature",
  "properties": {
    "iso:country":"US",
    "sg:address":"6823 Amposta Dr",
    "sg:city":"El Paso",
    "sg:classifiers":[
        {
            "category":"Building & Trades",
            "subcategory":"Equipment Rental",
            "type":"Services"
        }
    ],
    "sg:phone":"+1 915 355 1951",
    "sg:postcode":"79912",
    "sg:province":"TX",
    "sg:tags":[
        "medical"
    ],
    "wof:name":"Mobility Matters",
    "wof:placetype":"venue"
},
  "geometry": {"coordinates":[-106.545759,31.851363],"type":"Point"}
}