{
  "type": "Feature",
  "properties": {
    "iso:country":"US",
    "sg:address":"6128 Birdwood Rd",
    "sg:city":"Houston",
    "sg:classifiers":[
        {
            "category":"Professional",
            "subcategory":"Computer Services",
            "type":"Services"
        }
    ],
    "sg:phone":"+1 713 271 0279",
    "sg:postcode":"77074",
    "sg:province":"TX",
    "sg:tags":[
        "consultant",
        "designer"
    ],
    "wof:name":"Alu Technology Svc",
    "wof:placetype":"venue"
},
  "geometry": {"coordinates":[-95.49972699999999,29.681829],"type":"Point"}
}