{
  "type": "Feature",
  "properties": {
    "iso:country":"US",
    "sg:address":"1809 Northcrest Dr",
    "sg:city":"Plano",
    "sg:classifiers":[
        {
            "category":"Health Services",
            "subcategory":"Clinic",
            "type":"Services"
        }
    ],
    "sg:phone":"+1 972 516 0171",
    "sg:postcode":"75075",
    "sg:province":"TX",
    "wof:name":"Plano Lactation Assoc",
    "wof:placetype":"venue"
},
  "geometry": {"coordinates":[-96.728049,33.009853],"type":"Point"}
}