{
  "type": "Feature",
  "properties": {
    "iso:country":"US",
    "sg:address":"105 Timber Trl",
    "sg:city":"Longview",
    "sg:classifiers":[
        {
            "category":"Manufacturing",
            "subcategory":"Retail Goods",
            "type":"Manufacturing & Wholesale Goods"
        }
    ],
    "sg:phone":"+1 903 759 0502",
    "sg:postcode":"75605",
    "sg:province":"TX",
    "sg:tags":[
        "product",
        "mfg"
    ],
    "wof:name":"Scents D-Light",
    "wof:placetype":"venue"
},
  "geometry": {"coordinates":[-94.792013,32.544276],"type":"Point"}
}