{
  "type": "Feature",
  "properties": {
    "iso:country":"US",
    "sg:address":"13260 Josey Ln",
    "sg:city":"Dallas",
    "sg:classifiers":[
        {
            "category":"Shopping",
            "subcategory":"Computers & Home Electronics",
            "type":"Retail Goods"
        },
        {
            "category":"Banks & Credit Unions",
            "subcategory":"Bank",
            "type":"Services"
        }
    ],
    "sg:phone":"+1 972 620 1825",
    "sg:postcode":"75234",
    "sg:province":"TX",
    "sg:tags":[
        "personal",
        "equipment",
        "institution",
        "dealer"
    ],
    "wof:name":"Advance America",
    "wof:placetype":"venue"
},
  "geometry": {"coordinates":[-96.88144,32.925981],"type":"Point"}
}