{
  "type": "Feature",
  "properties": {
    "iso:country":"US",
    "sg:address":"609 Bayou Bend Dr",
    "sg:city":"Deer Park",
    "sg:classifiers":[
        {
            "category":"Retail",
            "subcategory":"Laundry & Dry Cleaning",
            "type":"Services"
        }
    ],
    "sg:phone":"+1 281 542 9282",
    "sg:postcode":"77536",
    "sg:province":"TX",
    "wof:name":"Jet Clean Services",
    "wof:placetype":"venue"
},
  "geometry": {"coordinates":[-95.129085,29.674036],"type":"Point"}
}