{
  "type": "Feature",
  "properties": {
    "iso:country":"US",
    "sg:address":"200 N Britain Rd",
    "sg:city":"Irving",
    "sg:classifiers":[
        {
            "category":"Professional",
            "type":"Services"
        }
    ],
    "sg:phone":"+1 972 554 0272",
    "sg:postcode":"75061",
    "sg:province":"TX",
    "sg:tags":[
        "establishment"
    ],
    "wof:name":"Younes",
    "wof:placetype":"venue"
},
  "geometry": {"coordinates":[-96.942427,32.815551],"type":"Point"}
}