{
  "type": "Feature",
  "properties": {
    "iso:country":"US",
    "sg:address":"6560 Montana Ave",
    "sg:city":"El Paso",
    "sg:classifiers":[
        {
            "category":"Home & Garden",
            "subcategory":"Carpets & Floor Coverings",
            "type":"Retail Goods"
        }
    ],
    "sg:phone":"+1 915 778 7049",
    "sg:postcode":"79925",
    "sg:province":"TX",
    "sg:tags":[
        "dealer",
        "rug"
    ],
    "wof:name":"Celebrity Carpets",
    "wof:placetype":"venue"
},
  "geometry": {"coordinates":[-106.400869,31.788896],"type":"Point"}
}