{
  "type": "Feature",
  "properties": {
    "iso:country":"US",
    "sg:address":"1015 S Guadalupe St",
    "sg:city":"Seguin",
    "sg:classifiers":[
        {
            "category":"Education",
            "subcategory":"Dance Studio",
            "type":"Public Place"
        }
    ],
    "sg:phone":"+1 830 379 0602",
    "sg:postcode":"78155",
    "sg:province":"TX",
    "sg:tags":[
        "ballroom"
    ],
    "wof:name":"Seguin Columbus Club",
    "wof:placetype":"venue"
},
  "geometry": {"coordinates":[-97.969295,29.558021],"type":"Point"}
}