{
  "type": "Feature",
  "properties": {
    "iso:country":"US",
    "sg:address":"1202 E Ailsie Ave",
    "sg:city":"Kingsville",
    "sg:classifiers":[
        {
            "category":"Wholesale",
            "subcategory":"Jewelry",
            "type":"Manufacturing & Wholesale Goods"
        }
    ],
    "sg:phone":"+1 361 592 0485",
    "sg:postcode":"78363",
    "sg:province":"TX",
    "sg:tags":[
        "stone"
    ],
    "wof:name":"Lucys Fashion Jewelry",
    "wof:placetype":"venue"
},
  "geometry": {"coordinates":[-97.852992,27.499132],"type":"Point"}
}