{
  "type": "Feature",
  "properties": {
    "iso:country":"US",
    "sg:address":"5017 33rd St",
    "sg:city":"Groves",
    "sg:classifiers":[
        {
            "category":"Manufacturing",
            "subcategory":"Retail Goods",
            "type":"Manufacturing & Wholesale Goods"
        }
    ],
    "sg:phone":"+1 409 962 6561",
    "sg:postcode":"77619",
    "sg:province":"TX",
    "sg:tags":[
        "house",
        "product",
        "mfg",
        "mail"
    ],
    "wof:name":"Brush Strokes By DOT Chauvin",
    "wof:placetype":"venue"
},
  "geometry": {"coordinates":[-93.924612,29.931408],"type":"Point"}
}