{
  "type": "Feature",
  "properties": {
    "iso:country":"US",
    "sg:address":"2646 Sam School Rd",
    "sg:city":"Roanoke",
    "sg:classifiers":[
        {
            "category":"Building & Trades",
            "subcategory":"Landscaping Services",
            "type":"Services"
        }
    ],
    "sg:phone":"+1 817 430 2095",
    "sg:postcode":"76262",
    "sg:province":"TX",
    "sg:tags":[
        "landscape",
        "contractor"
    ],
    "wof:name":"Precision Exteriors",
    "wof:placetype":"venue"
},
  "geometry": {"coordinates":[-97.167314,32.970906],"type":"Point"}
}