{
  "type": "Feature",
  "properties": {
    "iso:country":"US",
    "sg:address":"15104 Mallard Green Ln",
    "sg:city":"Austin",
    "sg:classifiers":[
        {
            "category":"Professional",
            "subcategory":"Business Services",
            "type":"Services"
        }
    ],
    "sg:phone":"+1 512 246 1259",
    "sg:postcode":"78728",
    "sg:province":"TX",
    "wof:name":"Education Solutions",
    "wof:placetype":"venue"
},
  "geometry": {"coordinates":[-97.681805,30.449784],"type":"Point"}
}