{
  "type": "Feature",
  "properties": {
    "iso:country":"US",
    "sg:address":"1 Snow Aly",
    "sg:city":"San Antonio",
    "sg:classifiers":[
        {
            "category":"Wholesale",
            "subcategory":"Electrical",
            "type":"Manufacturing & Wholesale Goods"
        }
    ],
    "sg:phone":"+1 210 647 6903",
    "sg:postcode":"78207",
    "sg:province":"TX",
    "sg:tags":[
        "electronic"
    ],
    "wof:name":"Hitachi High Technologies Amer",
    "wof:placetype":"venue"
},
  "geometry": {"coordinates":[-98.52591700000001,29.422655],"type":"Point"}
}