{
  "type": "Feature",
  "properties": {
    "iso:country":"US",
    "sg:address":"4601 Bosque Blvd",
    "sg:city":"Waco",
    "sg:classifiers":[
        {
            "category":"Recreation",
            "type":"Entertainment"
        }
    ],
    "sg:phone":"+1 254 776 1660",
    "sg:postcode":"76710",
    "sg:province":"TX",
    "sg:tags":[
        "fairground"
    ],
    "sg:website":"www.hotfair.com",
    "wof:name":"Heart O' Texas Fair & Coliseum",
    "wof:placetype":"venue"
},
  "geometry": {"coordinates":[-97.186927,31.536338],"type":"Point"}
}