{
  "type": "Feature",
  "properties": {
    "iso:country":"US",
    "sg:address":"601 Castano Ave",
    "sg:city":"San Antonio",
    "sg:classifiers":[
        {
            "category":"Professional",
            "type":"Services"
        }
    ],
    "sg:phone":"+1 210 824 6209",
    "sg:postcode":"78209",
    "sg:province":"TX",
    "wof:name":"Karen Harrison",
    "wof:placetype":"venue"
},
  "geometry": {"coordinates":[-98.477386,29.489963],"type":"Point"}
}