{
  "type": "Feature",
  "properties": {
    "iso:country":"US",
    "sg:address":"117 Huron Trl",
    "sg:city":"Gainesville",
    "sg:classifiers":[
        {
            "category":"Professional",
            "type":"Services"
        }
    ],
    "sg:phone":"+1 940 668 8803",
    "sg:postcode":"76240",
    "sg:province":"TX",
    "wof:name":"Arnold P Head",
    "wof:placetype":"venue"
},
  "geometry": {"coordinates":[-97.01566200000001,33.568757],"type":"Point"}
}