{
  "type": "Feature",
  "properties": {
    "iso:country":"US",
    "sg:address":"4414 Hwy 190 W",
    "sg:city":"Livingston",
    "sg:classifiers":[
        {
            "category":"Freight",
            "type":"Transportation"
        }
    ],
    "sg:phone":"+1 936 967 8897",
    "sg:postcode":"77351",
    "sg:province":"TX",
    "sg:tags":[
        "commercial",
        "storage"
    ],
    "wof:name":"Livingston Security Storage",
    "wof:placetype":"venue"
},
  "geometry": {"coordinates":[-94.959041,30.716321],"type":"Point"}
}