{
  "type": "Feature",
  "properties": {
    "iso:country":"US",
    "sg:address":"109 Main St",
    "sg:city":"Hart",
    "sg:classifiers":[
        {
            "category":"Retail",
            "subcategory":"Funeral Services",
            "type":"Services"
        }
    ],
    "sg:phone":"+1 806 938 2521",
    "sg:postcode":"79043",
    "sg:province":"TX",
    "sg:tags":[
        "director"
    ],
    "wof:name":"Mason Funeral Home",
    "wof:placetype":"venue"
},
  "geometry": {"coordinates":[-102.10984999999999,34.377673],"type":"Point"}
}