{
  "type": "Feature",
  "properties": {
    "iso:country":"US",
    "sg:address":"414 N Main St",
    "sg:city":"Grapevine",
    "sg:classifiers":[
        {
            "category":"Personal",
            "subcategory":"Beauty Salon",
            "type":"Services"
        }
    ],
    "sg:phone":"+1 817 488 3453",
    "sg:postcode":"76051",
    "sg:province":"TX",
    "sg:tags":[
        "shop"
    ],
    "wof:name":"Nail Gallery",
    "wof:placetype":"venue"
},
  "geometry": {"coordinates":[-97.077646,32.943995],"type":"Point"}
}