{
  "type": "Feature",
  "properties": {
    "iso:country":"US",
    "sg:address":"5217 Village Creek Dr",
    "sg:city":"Plano",
    "sg:classifiers":[
        {
            "category":"Shopping",
            "type":"Retail Goods"
        }
    ],
    "sg:phone":"+1 972 931 2180",
    "sg:postcode":"75093",
    "sg:province":"TX",
    "sg:tags":[
        "merchandise"
    ],
    "wof:name":"Charles P Wright",
    "wof:placetype":"venue"
},
  "geometry": {"coordinates":[-96.809622,33.013952],"type":"Point"}
}