{
  "type": "Feature",
  "properties": {
    "iso:country":"US",
    "sg:address":"5026 Hanover Ave",
    "sg:city":"Dallas",
    "sg:classifiers":[
        {
            "category":"Building & Trades",
            "subcategory":"Landscaping Services",
            "type":"Services"
        }
    ],
    "sg:phone":"+1 214 358 1981",
    "sg:postcode":"75209",
    "sg:province":"TX",
    "sg:tags":[
        "landscape",
        "contractor"
    ],
    "wof:name":"Bock Landscaping",
    "wof:placetype":"venue"
},
  "geometry": {"coordinates":[-96.823069,32.855099],"type":"Point"}
}