{
  "type": "Feature",
  "properties": {
    "iso:country":"US",
    "sg:address":"1342 Ceralvo St",
    "sg:city":"San Antonio",
    "sg:classifiers":[
        {
            "category":"Organizations",
            "subcategory":"Religious Organization",
            "type":"Services"
        }
    ],
    "sg:phone":"+1 210 433 3843",
    "sg:postcode":"78207",
    "sg:province":"TX",
    "sg:tags":[
        "church"
    ],
    "wof:name":"Seventh Day Church Of God",
    "wof:placetype":"venue"
},
  "geometry": {"coordinates":[-98.543751,29.408064],"type":"Point"}
}