{
  "type": "Feature",
  "properties": {
    "iso:country":"US",
    "sg:address":"2330 N 10th St",
    "sg:city":"Mcallen",
    "sg:classifiers":[
        {
            "category":"Wholesale",
            "subcategory":"Sporting Goods",
            "type":"Manufacturing & Wholesale Goods"
        }
    ],
    "sg:phone":"+1 956 631 9081",
    "sg:postcode":"78501",
    "sg:province":"TX",
    "sg:tags":[
        "tennis"
    ],
    "wof:name":"Cdx",
    "wof:placetype":"venue"
},
  "geometry": {"coordinates":[-98.226283,26.224735],"type":"Point"}
}