{
  "type": "Feature",
  "properties": {
    "iso:country":"US",
    "sg:address":"812 Hwy 3 N",
    "sg:city":"League City",
    "sg:classifiers":[
        {
            "category":"Professional",
            "type":"Services"
        }
    ],
    "sg:phone":"+1 281 557 7784",
    "sg:postcode":"77573",
    "sg:province":"TX",
    "wof:name":"Aussie Naturals",
    "wof:placetype":"venue"
},
  "geometry": {"coordinates":[-95.09980899999999,29.512649],"type":"Point"}
}