{
  "type": "Feature",
  "properties": {
    "iso:country":"US",
    "sg:address":"213 Davis Rd",
    "sg:city":"Big Spring",
    "sg:classifiers":[
        {
            "category":"Restaurant",
            "type":"Food & Drink"
        }
    ],
    "sg:phone":"+1 432 263 5342",
    "sg:postcode":"79720",
    "sg:province":"TX",
    "sg:tags":[
        "eating"
    ],
    "wof:name":"City Cafe",
    "wof:placetype":"venue"
},
  "geometry": {"coordinates":[-101.473291,32.301381],"type":"Point"}
}