{
  "type": "Feature",
  "properties": {
    "iso:country":"US",
    "sg:address":"1575 Dunnam Dr",
    "sg:city":"Abilene",
    "sg:classifiers":[
        {
            "category":"Manufacturing",
            "subcategory":"Metals",
            "type":"Manufacturing & Wholesale Goods"
        }
    ],
    "sg:phone":"+1 325 690 9599",
    "sg:postcode":"79602",
    "sg:province":"TX",
    "sg:tags":[
        "plumbing",
        "fitting",
        "fixture",
        "mfg"
    ],
    "wof:name":"Ewing Irrigation & Indus Pdts",
    "wof:placetype":"venue"
},
  "geometry": {"coordinates":[-99.741474,32.391878],"type":"Point"}
}