{
  "type": "Feature",
  "properties": {
    "iso:country":"US",
    "sg:address":"1117 Loma Verde Dr",
    "sg:city":"El Paso",
    "sg:classifiers":[
        {
            "category":"Local Transit",
            "type":"Transportation"
        }
    ],
    "sg:phone":"+1 915 872 0002",
    "sg:postcode":"79936",
    "sg:province":"TX",
    "sg:tags":[
        "shuttle"
    ],
    "wof:name":"Angel Care Shuttle Svc",
    "wof:placetype":"venue"
},
  "geometry": {"coordinates":[-106.28340900000001,31.715736],"type":"Point"}
}