{
  "type": "Feature",
  "properties": {
    "iso:country":"US",
    "sg:address":"2501 Gravel Dr",
    "sg:city":"Fort Worth",
    "sg:classifiers":[
        {
            "category":"Real Estate",
            "subcategory":"Real Estate Agent",
            "type":"Services"
        }
    ],
    "sg:phone":"+1 817 589 7458",
    "sg:postcode":"76118",
    "sg:province":"TX",
    "wof:name":"Riverbend Business Park",
    "wof:placetype":"venue"
},
  "geometry": {"coordinates":[-97.217119,32.795238],"type":"Point"}
}