{
  "type": "Feature",
  "properties": {
    "iso:country":"US",
    "sg:address":"3924 Creek Crossing Dr",
    "sg:city":"Plano",
    "sg:classifiers":[
        {
            "category":"Shopping",
            "subcategory":"Books",
            "type":"Retail Goods"
        }
    ],
    "sg:phone":"+1 972 398 8052",
    "sg:postcode":"75093",
    "sg:province":"TX",
    "wof:name":"Chan Edmondson",
    "wof:placetype":"venue"
},
  "geometry": {"coordinates":[-96.785944,33.050471],"type":"Point"}
}