{
  "type": "Feature",
  "properties": {
    "iso:country":"US",
    "sg:address":"5700 Wales Ave",
    "sg:city":"Fort Worth",
    "sg:classifiers":[
        {
            "category":"Manufacturing",
            "subcategory":"Chemicals & Compounds",
            "type":"Manufacturing & Wholesale Goods"
        }
    ],
    "sg:phone":"+1 817 294 1808",
    "sg:postcode":"76133",
    "sg:province":"TX",
    "sg:tags":[
        "preparation",
        "mfg"
    ],
    "wof:name":"Old West Seasoning",
    "wof:placetype":"venue"
},
  "geometry": {"coordinates":[-97.386819,32.662932],"type":"Point"}
}