{
  "type": "Feature",
  "properties": {
    "iso:country":"US",
    "sg:address":"220 W Hillside Rd",
    "sg:city":"Laredo",
    "sg:classifiers":[
        {
            "category":"Personal",
            "subcategory":"Beauty Salon",
            "type":"Services"
        }
    ],
    "sg:phone":"+1 956 795 1808",
    "sg:postcode":"78041",
    "sg:province":"TX",
    "sg:tags":[
        "shop"
    ],
    "wof:name":"Anitas Unique Styling Salon",
    "wof:placetype":"venue"
},
  "geometry": {"coordinates":[-99.49726200000001,27.547063],"type":"Point"}
}