{
  "type": "Feature",
  "properties": {
    "iso:country":"US",
    "sg:address":"2167 Post Oak Cir",
    "sg:city":"College Station",
    "sg:classifiers":[
        {
            "category":"Real Estate",
            "subcategory":"Surveying",
            "type":"Services"
        }
    ],
    "sg:phone":"+1 979 690 3378",
    "sg:postcode":"77845",
    "sg:province":"TX",
    "sg:tags":[
        "civil",
        "engineer"
    ],
    "wof:name":"Joe Orr Inc",
    "wof:placetype":"venue"
},
  "geometry": {"coordinates":[-96.253184,30.589432],"type":"Point"}
}