{
  "type": "Feature",
  "properties": {
    "iso:country":"US",
    "sg:address":"427 S Irving St",
    "sg:city":"San Angelo",
    "sg:classifiers":[
        {
            "category":"Building & Trades",
            "subcategory":"Construction",
            "type":"Services"
        }
    ],
    "sg:phone":"+1 325 947 3119",
    "sg:postcode":"76903",
    "sg:province":"TX",
    "sg:tags":[
        "contractor"
    ],
    "wof:name":"Galindo Roofing Services",
    "wof:placetype":"venue"
},
  "geometry": {"coordinates":[-100.436221,31.456596],"type":"Point"}
}