{
  "type": "Feature",
  "properties": {
    "iso:country":"US",
    "sg:address":"3017 Southwestern Blvd",
    "sg:city":"Dallas",
    "sg:classifiers":[
        {
            "category":"Banks & Credit Unions",
            "subcategory":"Financial Services",
            "type":"Services"
        }
    ],
    "sg:phone":"+1 214 368 7242",
    "sg:postcode":"75225",
    "sg:province":"TX",
    "sg:tags":[
        "investment",
        "real estate"
    ],
    "wof:name":"John R Brougher Jr Enterprises",
    "wof:placetype":"venue"
},
  "geometry": {"coordinates":[-96.778504,32.857],"type":"Point"}
}