{
  "type": "Feature",
  "properties": {
    "iso:country":"US",
    "sg:address":"2908 Macarthur Dr",
    "sg:city":"Orange",
    "sg:classifiers":[
        {
            "category":"Personal",
            "subcategory":"Beauty Salon",
            "type":"Services"
        }
    ],
    "sg:phone":"+1 409 883 8600",
    "sg:postcode":"77630",
    "sg:province":"TX",
    "sg:tags":[
        "shop"
    ],
    "wof:name":"All About Hair",
    "wof:placetype":"venue"
},
  "geometry": {"coordinates":[-93.75788300000001,30.094569],"type":"Point"}
}