{
  "type": "Feature",
  "properties": {
    "iso:country":"US",
    "sg:address":"1060 Guadalupe St",
    "sg:city":"Kerrville",
    "sg:classifiers":[
        {
            "category":"Government",
            "subcategory":"Office",
            "type":"Public Place"
        }
    ],
    "sg:phone":"+1 800 772 1213",
    "sg:postcode":"78028",
    "sg:province":"TX",
    "sg:tags":[
        "program",
        "administrative"
    ],
    "wof:name":"Social Security Administration",
    "wof:placetype":"venue"
},
  "geometry": {"coordinates":[-99.16579900000001,30.058091],"type":"Point"}
}