{
  "type": "Feature",
  "properties": {
    "iso:country":"US",
    "sg:address":"3205 Ranch Road 620 N",
    "sg:city":"Austin",
    "sg:classifiers":[
        {
            "category":"Retail",
            "subcategory":"Repair Shop",
            "type":"Services"
        }
    ],
    "sg:phone":"+1 512 266 1812",
    "sg:postcode":"78734",
    "sg:province":"TX",
    "sg:tags":[
        "reupholstery",
        "furniture"
    ],
    "wof:name":"Blanchard's Upholstery",
    "wof:placetype":"venue"
},
  "geometry": {"coordinates":[-97.93522299999999,30.393331],"type":"Point"}
}