{
  "type": "Feature",
  "properties": {
    "iso:country":"US",
    "sg:address":"3233 Silkgrass Bend",
    "sg:city":"Austin",
    "sg:classifiers":[
        {
            "category":"Banks & Credit Unions",
            "subcategory":"Financial Services",
            "type":"Services"
        }
    ],
    "sg:phone":"+1 512 282 7777",
    "sg:postcode":"78748",
    "sg:province":"TX",
    "sg:tags":[
        "company",
        "holding"
    ],
    "wof:name":"Najjar Inc",
    "wof:placetype":"venue"
},
  "geometry": {"coordinates":[-97.841161,30.185437],"type":"Point"}
}