{
  "type": "Feature",
  "properties": {
    "iso:country":"US",
    "sg:address":"3003 Franciscan Dr",
    "sg:city":"Arlington",
    "sg:classifiers":[
        {
            "category":"Shopping",
            "type":"Retail Goods"
        }
    ],
    "sg:phone":"+1 972 871 8865",
    "sg:postcode":"76015",
    "sg:province":"TX",
    "sg:tags":[
        "merchandise"
    ],
    "wof:name":"Gel Candle Factory",
    "wof:placetype":"venue"
},
  "geometry": {"coordinates":[-97.11744400000001,32.695807],"type":"Point"}
}