{
  "type": "Feature",
  "properties": {
    "iso:country":"US",
    "sg:address":"10855 Spiller Rd",
    "sg:city":"San Antonio",
    "sg:classifiers":[
        {
            "category":"Utilities",
            "subcategory":"Telephone",
            "type":"Services"
        }
    ],
    "sg:phone":"+1 210 688 3411",
    "sg:postcode":"78254",
    "sg:province":"TX",
    "sg:tags":[
        "communications"
    ],
    "wof:name":"Advanced Network Services",
    "wof:placetype":"venue"
},
  "geometry": {"coordinates":[-98.706492,29.539907],"type":"Point"}
}