{
  "type": "Feature",
  "properties": {
    "iso:country":"US",
    "sg:address":"203 E Tyler St",
    "sg:city":"Athens",
    "sg:classifiers":[
        {
            "category":"Personal",
            "subcategory":"Beauty Salon",
            "type":"Services"
        }
    ],
    "sg:phone":"+1 903 675 5222",
    "sg:postcode":"75751",
    "sg:province":"TX",
    "sg:tags":[
        "nail"
    ],
    "wof:name":"Dawns Nails",
    "wof:placetype":"venue"
},
  "geometry": {"coordinates":[-95.85248199999999,32.205451],"type":"Point"}
}