{
  "type": "Feature",
  "properties": {
    "iso:country":"US",
    "sg:address":"406 W Hillcrest St",
    "sg:city":"Keene",
    "sg:classifiers":[
        {
            "category":"Professional",
            "type":"Services"
        }
    ],
    "sg:phone":"+1 817 338 0220",
    "sg:postcode":"76059",
    "sg:province":"TX",
    "sg:tags":[
        "establishment"
    ],
    "wof:name":"Disabled Crime Victims",
    "wof:placetype":"venue"
},
  "geometry": {"coordinates":[-97.331906,32.396518],"type":"Point"}
}