{
  "type": "Feature",
  "properties": {
    "iso:country":"US",
    "sg:address":"12712 Darryl Dr",
    "sg:city":"Buda",
    "sg:classifiers":[
        {
            "category":"Restaurant",
            "type":"Food & Drink"
        }
    ],
    "sg:phone":"+1 512 295 2626",
    "sg:postcode":"78610",
    "sg:province":"TX",
    "sg:tags":[
        "house",
        "steak",
        "barbecue"
    ],
    "wof:name":"Mr Bar B Que",
    "wof:placetype":"venue"
},
  "geometry": {"coordinates":[-97.858797,30.117965],"type":"Point"}
}