{
  "type": "Feature",
  "properties": {
    "iso:country":"US",
    "sg:address":"9720 Edge School House Rd",
    "sg:city":"Hearne",
    "sg:classifiers":[
        {
            "category":"Professional",
            "type":"Services"
        }
    ],
    "sg:phone":"+1 979 589 2824",
    "sg:postcode":"77808",
    "sg:province":"TX",
    "wof:name":"Bcs 409ers",
    "wof:placetype":"venue"
},
  "geometry": {"coordinates":[-96.299753,30.93372],"type":"Point"}
}