{
  "type": "Feature",
  "properties": {
    "iso:country":"US",
    "sg:address":"12121 Coit Rd",
    "sg:city":"Dallas",
    "sg:classifiers":[
        {
            "category":"Professional",
            "type":"Services"
        }
    ],
    "sg:phone":"+1 972 276 4738",
    "sg:postcode":"75251",
    "sg:province":"TX",
    "wof:name":"Richard A Calvert",
    "wof:placetype":"venue"
},
  "geometry": {"coordinates":[-96.769233,32.918124],"type":"Point"}
}