{
  "type": "Feature",
  "properties": {
    "iso:country":"US",
    "sg:address":"3603 Ridgeview Dr",
    "sg:city":"Missouri City",
    "sg:classifiers":[
        {
            "category":"Professional",
            "subcategory":"Accounting & Tax Preparation",
            "type":"Services"
        }
    ],
    "sg:phone":"+1 281 403 0009",
    "sg:postcode":"77459",
    "sg:province":"TX",
    "wof:name":"Smith & Smith CPA",
    "wof:placetype":"venue"
},
  "geometry": {"coordinates":[-95.560298,29.56763],"type":"Point"}
}