{
  "type": "Feature",
  "properties": {
    "iso:country":"US",
    "sg:address":"7501 Sleepy Hollow Blvd",
    "sg:city":"Amarillo",
    "sg:classifiers":[
        {
            "category":"Professional",
            "subcategory":"Business Services",
            "type":"Services"
        }
    ],
    "sg:phone":"+1 806 358 0868",
    "sg:postcode":"79121",
    "sg:province":"TX",
    "wof:name":"Interiors By Lacoda",
    "wof:placetype":"venue"
},
  "geometry": {"coordinates":[-101.92838999999999,35.168917],"type":"Point"}
}