{
  "type": "Feature",
  "properties": {
    "iso:country":"US",
    "sg:address":"9434 Viscount Blvd",
    "sg:city":"El Paso",
    "sg:classifiers":[
        {
            "category":"Professional",
            "subcategory":"Accounting & Tax Preparation",
            "type":"Services"
        }
    ],
    "sg:phone":"+1 915 594 3919",
    "sg:postcode":"79925",
    "sg:province":"TX",
    "wof:name":"Castillo Bookkeeping Tax Svcs",
    "wof:placetype":"venue"
},
  "geometry": {"coordinates":[-106.3643,31.76864],"type":"Point"}
}