{
  "type": "Feature",
  "properties": {
    "iso:country":"US",
    "sg:address":"8603 Delaware Ct",
    "sg:city":"Austin",
    "sg:classifiers":[
        {
            "category":"Restaurant",
            "type":"Food & Drink"
        }
    ],
    "sg:phone":"+1 512 339 6740",
    "sg:postcode":"78758",
    "sg:province":"TX",
    "sg:tags":[
        "eating"
    ],
    "wof:name":"Freskusia Best Taste",
    "wof:placetype":"venue"
},
  "geometry": {"coordinates":[-97.70495099999999,30.357721],"type":"Point"}
}