{
  "type": "Feature",
  "properties": {
    "iso:country":"US",
    "sg:address":"6422 Phelan Blvd",
    "sg:city":"Beaumont",
    "sg:classifiers":[
        {
            "category":"Personal",
            "subcategory":"Beauty Salon",
            "type":"Services"
        }
    ],
    "sg:phone":"+1 409 861 1666",
    "sg:postcode":"77706",
    "sg:province":"TX",
    "sg:tags":[
        "shop"
    ],
    "wof:name":"Lamirage Salon & Spa",
    "wof:placetype":"venue"
},
  "geometry": {"coordinates":[-94.169636,30.078077],"type":"Point"}
}