{
  "type": "Feature",
  "properties": {
    "iso:country":"US",
    "sg:address":"5213 Kirby Dr",
    "sg:city":"Houston",
    "sg:classifiers":[
        {
            "category":"Wholesale",
            "subcategory":"Plants",
            "type":"Manufacturing & Wholesale Goods"
        }
    ],
    "sg:phone":"+1 713 521 5999",
    "sg:postcode":"77098",
    "sg:province":"TX",
    "sg:tags":[
        "florist",
        "supply"
    ],
    "wof:name":"Wilde Flower Co",
    "wof:placetype":"venue"
},
  "geometry": {"coordinates":[-95.418521,29.726214],"type":"Point"}
}