{
  "type": "Feature",
  "properties": {
    "iso:country":"US",
    "sg:address":"1803 Rhodes Rd",
    "sg:city":"Austin",
    "sg:classifiers":[
        {
            "category":"Organizations",
            "subcategory":"Membership Organization",
            "type":"Services"
        }
    ],
    "sg:phone":"+1 512 926 3509",
    "sg:postcode":"78721",
    "sg:province":"TX",
    "wof:name":"Traveler Golf Association Inc",
    "wof:placetype":"venue"
},
  "geometry": {"coordinates":[-97.68045100000001,30.283057],"type":"Point"}
}