{
  "type": "Feature",
  "properties": {
    "iso:country":"US",
    "sg:address":"8910 Bent Spur Ln",
    "sg:city":"Houston",
    "sg:classifiers":[
        {
            "category":"Personal",
            "subcategory":"Barber",
            "type":"Services"
        }
    ],
    "sg:phone":"+1 281 469 8781",
    "sg:postcode":"77064",
    "sg:province":"TX",
    "sg:tags":[
        "shop"
    ],
    "wof:name":"Dixon Barber Shop",
    "wof:placetype":"venue"
},
  "geometry": {"coordinates":[-95.576896,29.902925],"type":"Point"}
}