{
  "type": "Feature",
  "properties": {
    "iso:country":"US",
    "sg:address":"157 Padre Ln",
    "sg:city":"Victoria",
    "sg:classifiers":[
        {
            "category":"Building & Trades",
            "subcategory":"Construction",
            "type":"Services"
        }
    ],
    "sg:phone":"+1 361 573 2122",
    "sg:postcode":"77905",
    "sg:province":"TX",
    "sg:tags":[
        "contractor"
    ],
    "wof:name":"Jollys Welding",
    "wof:placetype":"venue"
},
  "geometry": {"coordinates":[-97.17277900000001,28.895938],"type":"Point"}
}