{
  "type": "Feature",
  "properties": {
    "iso:country":"US",
    "sg:address":"5310 Railroad St",
    "sg:city":"Deer Park",
    "sg:classifiers":[
        {
            "category":"Wholesale",
            "subcategory":"Machinery & Supplies",
            "type":"Manufacturing & Wholesale Goods"
        }
    ],
    "sg:phone":"+1 281 476 9729",
    "sg:postcode":"77536",
    "sg:province":"TX",
    "sg:tags":[
        "equipment",
        "welding"
    ],
    "sg:website":"www.airgas.com",
    "wof:name":"Airgas Southwest",
    "wof:placetype":"venue"
},
  "geometry": {"coordinates":[-95.131125,29.710718],"type":"Point"}
}