{
  "type": "Feature",
  "properties": {
    "iso:country":"US",
    "sg:address":"304 Whaley Ave",
    "sg:city":"Marshall",
    "sg:classifiers":[
        {
            "category":"Building & Trades",
            "subcategory":"Construction",
            "type":"Services"
        }
    ],
    "sg:phone":"+1 903 938 8034",
    "sg:postcode":"75672",
    "sg:province":"TX",
    "sg:tags":[
        "wallcoverings-installation",
        "wallpaper",
        "painting",
        "contractor"
    ],
    "wof:name":"Ronny Summerlin Painting & Decorating",
    "wof:placetype":"venue"
},
  "geometry": {"coordinates":[-94.330355,32.545375],"type":"Point"}
}