{
  "type": "Feature",
  "properties": {
    "iso:country":"US",
    "sg:address":"15031 Burning Creek",
    "sg:city":"San Antonio",
    "sg:classifiers":[
        {
            "category":"Professional",
            "subcategory":"Lawyer & Legal Services",
            "type":"Services"
        }
    ],
    "sg:phone":"+1 210 655 5744",
    "sg:postcode":"78217",
    "sg:province":"TX",
    "sg:tags":[
        "attorney"
    ],
    "wof:name":"Keith A Needels",
    "wof:placetype":"venue"
},
  "geometry": {"coordinates":[-98.399929,29.578676],"type":"Point"}
}