{
  "type": "Feature",
  "properties": {
    "iso:country":"US",
    "sg:address":"2109 S Beckley Ave",
    "sg:city":"Dallas",
    "sg:classifiers":[
        {
            "category":"Organizations",
            "subcategory":"Religious Organization",
            "type":"Services"
        }
    ],
    "sg:phone":"+1 214 942 2227",
    "sg:postcode":"75224",
    "sg:province":"TX",
    "sg:tags":[
        "church"
    ],
    "wof:name":"Shekinah Tabernacle Baptist",
    "wof:placetype":"venue"
},
  "geometry": {"coordinates":[-96.82291499999999,32.721566],"type":"Point"}
}