{
  "type": "Feature",
  "properties": {
    "iso:country":"US",
    "sg:address":"1111 N Sam Houston Pkwy E",
    "sg:city":"Houston",
    "sg:classifiers":[
        {
            "category":"Home & Garden",
            "subcategory":"Garden Supply",
            "type":"Retail Goods"
        }
    ],
    "sg:phone":"+1 888 456 4560",
    "sg:postcode":"77032",
    "sg:province":"TX",
    "sg:website":"http://sunstateequip.com",
    "wof:name":"Sunstate Equipment Co",
    "wof:placetype":"venue"
},
  "geometry": {"coordinates":[-95.371444,29.939199],"type":"Point"}
}