{
  "type": "Feature",
  "properties": {
    "iso:country":"US",
    "sg:address":"5200 Andalusia Trl",
    "sg:city":"Arlington",
    "sg:classifiers":[
        {
            "category":"Professional",
            "subcategory":"Computer Services",
            "type":"Services"
        }
    ],
    "sg:phone":"+1 817 516 7236",
    "sg:postcode":"76017",
    "sg:province":"TX",
    "sg:tags":[
        "development",
        "banking",
        "medical",
        "software",
        "utility"
    ],
    "wof:name":"Compu Source Inc",
    "wof:placetype":"venue"
},
  "geometry": {"coordinates":[-97.188517,32.655547],"type":"Point"}
}