{
  "type": "Feature",
  "properties": {
    "iso:country":"US",
    "sg:address":"201 Spruce St",
    "sg:city":"Dickinson",
    "sg:classifiers":[
        {
            "category":"Shopping",
            "subcategory":"Clothing, Apparel, & Fashions",
            "type":"Retail Goods"
        }
    ],
    "sg:phone":"+1 281 534 8907",
    "sg:postcode":"77539",
    "sg:province":"TX",
    "wof:name":"Cheer Power Store & More",
    "wof:placetype":"venue"
},
  "geometry": {"coordinates":[-95.07147500000001,29.477938],"type":"Point"}
}