{
  "type": "Feature",
  "properties": {
    "iso:country":"US",
    "sg:address":"1008 S 4th St",
    "sg:city":"Crockett",
    "sg:classifiers":[
        {
            "category":"Government",
            "subcategory":"Office",
            "type":"Public Place"
        }
    ],
    "sg:phone":"+1 936 544 3759",
    "sg:postcode":"75835",
    "sg:province":"TX",
    "sg:tags":[
        "federal"
    ],
    "wof:name":"Natural Resources Conservation",
    "wof:placetype":"venue"
},
  "geometry": {"coordinates":[-95.459417,31.303936],"type":"Point"}
}