{
  "type": "Feature",
  "properties": {
    "iso:country":"US",
    "sg:address":"1640 Brittmoore Rd",
    "sg:city":"Houston",
    "sg:classifiers":[
        {
            "category":"Building & Trades",
            "subcategory":"Electrical",
            "type":"Services"
        }
    ],
    "sg:phone":"+1 713 659 7786",
    "sg:postcode":"77043",
    "sg:province":"TX",
    "sg:tags":[
        "electrical",
        "electric",
        "contractor"
    ],
    "sg:website":"www.hwe.com",
    "wof:name":"Harper Wood Electric Company",
    "wof:placetype":"venue"
},
  "geometry": {"coordinates":[-95.569793,29.80424],"type":"Point"}
}