{
  "type": "Feature",
  "properties": {
    "iso:country":"US",
    "sg:address":"1578 Pioneer Dr",
    "sg:city":"Navasota",
    "sg:classifiers":[
        {
            "category":"Shopping",
            "subcategory":"Catalog Store",
            "type":"Retail Goods"
        }
    ],
    "sg:phone":"+1 936 825 0836",
    "sg:postcode":"77868",
    "sg:province":"TX",
    "sg:tags":[
        "mail",
        "house"
    ],
    "wof:name":"Donnastrinketsandtreasurescom",
    "wof:placetype":"venue"
},
  "geometry": {"coordinates":[-96.162829,30.46402],"type":"Point"}
}