{
  "type": "Feature",
  "properties": {
    "iso:country":"US",
    "sg:address":"12609 Silver Spr",
    "sg:city":"Austin",
    "sg:classifiers":[
        {
            "category":"Building & Trades",
            "subcategory":"Construction",
            "type":"Services"
        }
    ],
    "sg:phone":"+1 512 267 3546",
    "sg:postcode":"78727",
    "sg:province":"TX",
    "sg:tags":[
        "steel",
        "erection",
        "structural"
    ],
    "wof:name":"Texsteel International Inc",
    "wof:placetype":"venue"
},
  "geometry": {"coordinates":[-97.698145,30.418993],"type":"Point"}
}