{
  "type": "Feature",
  "properties": {
    "iso:country":"US",
    "sg:address":"110 W 7th St",
    "sg:city":"Fort Worth",
    "sg:classifiers":[
        {
            "category":"Professional",
            "type":"Services"
        }
    ],
    "sg:phone":"+1 817 332 9397",
    "sg:postcode":"76102",
    "sg:province":"TX",
    "sg:tags":[
        "establishment"
    ],
    "wof:name":"Mc Ibtna",
    "wof:placetype":"venue"
},
  "geometry": {"coordinates":[-97.330646,32.752403],"type":"Point"}
}