{
  "type": "Feature",
  "properties": {
    "iso:country":"US",
    "sg:address":"2300 Coit Rd",
    "sg:city":"Plano",
    "sg:classifiers":[
        {
            "category":"Wholesale",
            "subcategory":"Hardware",
            "type":"Manufacturing & Wholesale Goods"
        },
        {
            "category":"Shopping",
            "subcategory":"Clothing, Apparel, & Fashions",
            "type":"Retail Goods"
        }
    ],
    "sg:phone":"+1 972 596 2188",
    "sg:postcode":"75075",
    "sg:province":"TX",
    "sg:tags":[
        "aquatic",
        "supply",
        "marketing",
        "direct",
        "swimwear",
        "accessory"
    ],
    "wof:name":"Kiefer Swim Shop",
    "wof:placetype":"venue"
},
  "geometry": {"coordinates":[-96.76993,33.029228],"type":"Point"}
}