{
  "type": "Feature",
  "properties": {
    "iso:country":"US",
    "sg:address":"4300 Teckla Blvd",
    "sg:city":"Amarillo",
    "sg:classifiers":[
        {
            "category":"Professional",
            "subcategory":"Management & Consulting",
            "type":"Services"
        }
    ],
    "sg:phone":"+1 806 322 0505",
    "sg:postcode":"79109",
    "sg:province":"TX",
    "sg:tags":[
        "fuel"
    ],
    "wof:name":"Llano Estacado Account Mgmt",
    "wof:placetype":"venue"
},
  "geometry": {"coordinates":[-101.8874,35.164688],"type":"Point"}
}