{
  "type": "Feature",
  "properties": {
    "iso:country":"US",
    "sg:address":"6404 W Hwy 80",
    "sg:city":"Midland",
    "sg:classifiers":[
        {
            "category":"Professional",
            "type":"Services"
        }
    ],
    "sg:phone":"+1 432 520 0048",
    "sg:postcode":"79706",
    "sg:province":"TX",
    "sg:tags":[
        "establishment"
    ],
    "wof:name":"Beaver Express",
    "wof:placetype":"venue"
},
  "geometry": {"coordinates":[-102.164276,31.949955],"type":"Point"}
}