{
  "type": "Feature",
  "properties": {
    "iso:country":"US",
    "sg:address":"501 Cheyenne St",
    "sg:city":"Corpus Christi",
    "sg:classifiers":[
        {
            "category":"Professional",
            "type":"Services"
        }
    ],
    "sg:phone":"+1 361 884 3224",
    "sg:postcode":"78405",
    "sg:province":"TX",
    "wof:name":"Americans Finest Products",
    "wof:placetype":"venue"
},
  "geometry": {"coordinates":[-97.42984300000001,27.778181],"type":"Point"}
}