{
  "type": "Feature",
  "properties": {
    "iso:country":"US",
    "sg:address":"404 W Powell Ln",
    "sg:city":"Austin",
    "sg:classifiers":[
        {
            "category":"Professional",
            "subcategory":"Printing & Photocopies",
            "type":"Services"
        }
    ],
    "sg:phone":"+1 512 836 6902",
    "sg:postcode":"78753",
    "sg:province":"TX",
    "sg:website":"http://www.abpcreative.com",
    "wof:name":"Austin Business Printing",
    "wof:placetype":"venue"
},
  "geometry": {"coordinates":[-97.706998,30.349498],"type":"Point"}
}