{
  "type": "Feature",
  "properties": {
    "iso:country":"US",
    "sg:address":"401 E Garfield Ave",
    "sg:city":"Morton",
    "sg:phone":"+1 806 266 5107",
    "sg:postcode":"79346",
    "sg:province":"TX",
    "sg:tags":[
        "farm",
        "cotton"
    ],
    "wof:name":"Doug Zuber",
    "wof:placetype":"venue"
},
  "geometry": {"coordinates":[-102.75575600000001,33.717245],"type":"Point"}
}