{
  "type": "Feature",
  "properties": {
    "iso:country":"US",
    "sg:address":"2776 Beechmont Dr",
    "sg:city":"Dallas",
    "sg:classifiers":[
        {
            "category":"Professional",
            "type":"Services"
        }
    ],
    "sg:phone":"+1 214 321 6945",
    "sg:postcode":"75228",
    "sg:province":"TX",
    "wof:name":"Gerald R Horne",
    "wof:placetype":"venue"
},
  "geometry": {"coordinates":[-96.685956,32.816625],"type":"Point"}
}