{
  "type": "Feature",
  "properties": {
    "iso:country":"US",
    "sg:address":"2830 W Washington St",
    "sg:city":"Stephenville",
    "sg:classifiers":[
        {
            "category":"Restaurant",
            "type":"Food & Drink"
        }
    ],
    "sg:menulink":"http://www.allmenus.com/tx/stephenville/157464-whataburger/menu/",
    "sg:phone":"+1 254 968 6285",
    "sg:postcode":"76401",
    "sg:province":"TX",
    "sg:tags":[
        "burger",
        "american"
    ],
    "wof:name":"Whataburger",
    "wof:placetype":"venue"
},
  "geometry": {"coordinates":[-98.229243,32.207945],"type":"Point"}
}