{
  "type": "Feature",
  "properties": {
    "iso:country":"US",
    "sg:address":"1905 Guadalupe St",
    "sg:city":"Laredo",
    "sg:classifiers":[
        {
            "category":"Autos & Motor Vehicles",
            "subcategory":"Auto Supplies",
            "type":"Retail Goods"
        }
    ],
    "sg:phone":"+1 956 796 9993",
    "sg:postcode":"78043",
    "sg:province":"TX",
    "sg:tags":[
        "wheel",
        "on",
        "own",
        "tire",
        "basis",
        "to",
        "a",
        "rent"
    ],
    "wof:name":"Rent A Tire Inc",
    "wof:placetype":"venue"
},
  "geometry": {"coordinates":[-99.47629499999999,27.506499],"type":"Point"}
}