{
  "type": "Feature",
  "properties": {
    "iso:country":"US",
    "sg:address":"7323 Seton Lake Dr",
    "sg:city":"Houston",
    "sg:classifiers":[
        {
            "category":"Building & Trades",
            "subcategory":"Construction",
            "type":"Services"
        }
    ],
    "sg:phone":"+1 281 999 6806",
    "sg:postcode":"77086",
    "sg:province":"TX",
    "sg:tags":[
        "house"
    ],
    "wof:name":"Eagle Power",
    "wof:placetype":"venue"
},
  "geometry": {"coordinates":[-95.495029,29.927782],"type":"Point"}
}