{
  "type": "Feature",
  "properties": {
    "iso:country":"US",
    "sg:address":"19206 Habitat Cove",
    "sg:city":"San Antonio",
    "sg:classifiers":[
        {
            "category":"Professional",
            "subcategory":"Business Services",
            "type":"Services"
        }
    ],
    "sg:phone":"+1 210 492 6787",
    "sg:postcode":"78258",
    "sg:province":"TX",
    "wof:name":"Lariat Loop Enterprises",
    "wof:placetype":"venue"
},
  "geometry": {"coordinates":[-98.515314,29.621499],"type":"Point"}
}