{
  "type": "Feature",
  "properties": {
    "iso:country":"US",
    "sg:address":"2040 N Loop Fwy",
    "sg:city":"Houston",
    "sg:classifiers":[
        {
            "category":"Professional",
            "type":"Services"
        }
    ],
    "sg:phone":"+1 713 316 4500",
    "sg:postcode":"77018",
    "sg:province":"TX",
    "sg:tags":[
        "establishment"
    ],
    "wof:name":"Gill Records",
    "wof:placetype":"venue"
},
  "geometry": {"coordinates":[-95.434821,29.812053],"type":"Point"}
}