{
  "type": "Feature",
  "properties": {
    "iso:country":"US",
    "sg:address":"815A Brazos Suite 175",
    "sg:city":"Austin",
    "sg:classifiers":[
        {
            "category":"Personal",
            "type":"Services"
        }
    ],
    "sg:phone":"+1 512 389 3000",
    "sg:postcode":"78701",
    "sg:province":"TX",
    "sg:tags":[
        "mover"
    ],
    "sg:website":"www.austintexasmovers.com",
    "wof:name":"Aardvark Movers Inc",
    "wof:placetype":"venue"
},
  "geometry": {"coordinates":[-97.740461,30.270319],"type":"Point"}
}