{
  "type": "Feature",
  "properties": {
    "iso:country":"US",
    "sg:address":"1001 Fuller Wiser Rd # 814",
    "sg:city":"Euless",
    "sg:classifiers":[
        {
            "category":"Fast Food",
            "type":"Food & Drink"
        },
        {
            "category":"Restaurant",
            "type":"Food & Drink"
        }
    ],
    "sg:phone":"+1 214 585 3577",
    "sg:postcode":"76039",
    "sg:province":"TX",
    "wof:name":"Wing Zone",
    "wof:placetype":"venue"
},
  "geometry": {"coordinates":[-97.072709,32.850232],"type":"Point"}
}