{
  "type": "Feature",
  "properties": {
    "iso:country":"US",
    "sg:address":"2712 Quail Valley St",
    "sg:city":"Irving",
    "sg:classifiers":[
        {
            "category":"Social Services",
            "subcategory":"Child Care",
            "type":"Services"
        }
    ],
    "sg:phone":"+1 972 790 2955",
    "sg:postcode":"75060",
    "sg:province":"TX",
    "sg:tags":[
        "day"
    ],
    "wof:name":"Jane Ellen Chase",
    "wof:placetype":"venue"
},
  "geometry": {"coordinates":[-96.981651,32.795276],"type":"Point"}
}