{
  "type": "Feature",
  "properties": {
    "iso:country":"US",
    "sg:address":"1317 Brookside Dr",
    "sg:city":"Hurst",
    "sg:classifiers":[
        {
            "category":"Travel",
            "subcategory":"Travel Agent",
            "type":"Entertainment"
        }
    ],
    "sg:phone":"+1 817 282 1328",
    "sg:postcode":"76053",
    "sg:province":"TX",
    "sg:tags":[
        "agency"
    ],
    "wof:name":"B2b Travel Store",
    "wof:placetype":"venue"
},
  "geometry": {"coordinates":[-97.179132,32.835825],"type":"Point"}
}