{
  "type": "Feature",
  "properties": {
    "iso:country":"US",
    "sg:address":"8205 Cardinal Ln",
    "sg:city":"Fort Worth",
    "sg:classifiers":[
        {
            "category":"Retail",
            "subcategory":"Auto Repair",
            "type":"Services"
        }
    ],
    "sg:phone":"+1 817 788 0045",
    "sg:postcode":"76180",
    "sg:province":"TX",
    "sg:tags":[
        "body",
        "automobile",
        "painting"
    ],
    "wof:name":"Maximum Auto Collision Inc",
    "wof:placetype":"venue"
},
  "geometry": {"coordinates":[-97.20474400000001,32.863322],"type":"Point"}
}