{
  "type": "Feature",
  "properties": {
    "iso:country":"US",
    "sg:address":"10721 Gulf Fwy",
    "sg:city":"Houston",
    "sg:classifiers":[
        {
            "category":"Health Services",
            "subcategory":"Doctor",
            "type":"Services"
        }
    ],
    "sg:phone":"+1 713 946 9600",
    "sg:postcode":"77034",
    "sg:province":"TX",
    "wof:name":"Edgebrook Clinic",
    "wof:placetype":"venue"
},
  "geometry": {"coordinates":[-95.240146,29.638762],"type":"Point"}
}