{
  "type": "Feature",
  "properties": {
    "iso:country":"US",
    "sg:address":"104 S Little Flower Rd",
    "sg:city":"El Paso",
    "sg:classifiers":[
        {
            "category":"Home & Garden",
            "subcategory":"Household Appliances",
            "type":"Retail Goods"
        }
    ],
    "sg:phone":"+1 915 778 2454",
    "sg:postcode":"79915",
    "sg:province":"TX",
    "sg:tags":[
        "repair"
    ],
    "wof:name":"A&A Sewing Machine Center",
    "wof:placetype":"venue"
},
  "geometry": {"coordinates":[-106.396293,31.755035],"type":"Point"}
}