{
  "type": "Feature",
  "properties": {
    "iso:country":"US",
    "sg:address":"4206 Thousand Oaks Dr",
    "sg:city":"San Antonio",
    "sg:classifiers":[
        {
            "category":"Professional",
            "type":"Services"
        }
    ],
    "sg:phone":"+1 210 590 4547",
    "sg:postcode":"78217",
    "sg:province":"TX",
    "sg:tags":[
        "establishment"
    ],
    "wof:name":"Jenny's",
    "wof:placetype":"venue"
},
  "geometry": {"coordinates":[-98.40989999999999,29.552217],"type":"Point"}
}