{
  "type": "Feature",
  "properties": {
    "iso:country":"US",
    "sg:address":"629 Palo Pinto St",
    "sg:city":"Weatherford",
    "sg:classifiers":[
        {
            "category":"Organizations",
            "subcategory":"Religious Organization",
            "type":"Services"
        }
    ],
    "sg:phone":"+1 817 594 0266",
    "sg:postcode":"76086",
    "sg:province":"TX",
    "sg:tags":[
        "church"
    ],
    "wof:name":"Center Of Hope",
    "wof:placetype":"venue"
},
  "geometry": {"coordinates":[-97.806855,32.758862],"type":"Point"}
}