{
  "type": "Feature",
  "properties": {
    "iso:country":"US",
    "sg:address":"3810 Altamesa Blvd",
    "sg:city":"Fort Worth",
    "sg:classifiers":[
        {
            "category":"Organizations",
            "subcategory":"Religious Organization",
            "type":"Services"
        }
    ],
    "sg:phone":"+1 817 293 6868",
    "sg:postcode":"76133",
    "sg:province":"TX",
    "wof:name":"Spirit Of Prayer Ministry",
    "wof:placetype":"venue"
},
  "geometry": {"coordinates":[-97.375623,32.650467],"type":"Point"}
}