{
  "type": "Feature",
  "properties": {
    "iso:country":"US",
    "sg:address":"1602 State St",
    "sg:city":"Houston",
    "sg:classifiers":[
        {
            "category":"Social Services",
            "type":"Services"
        }
    ],
    "sg:phone":"+1 713 223 4286",
    "sg:postcode":"77007",
    "sg:province":"TX",
    "sg:tags":[
        "organization",
        "welfare"
    ],
    "wof:name":"Assist The Officer",
    "wof:placetype":"venue"
},
  "geometry": {"coordinates":[-95.375506,29.764782],"type":"Point"}
}