{
  "type": "Feature",
  "properties": {
    "iso:country":"US",
    "sg:address":"3300 Sage Rd",
    "sg:city":"Houston",
    "sg:classifiers":[
        {
            "category":"Real Estate",
            "subcategory":"Real Estate Agent",
            "type":"Services"
        }
    ],
    "sg:phone":"+1 713 840 2500",
    "sg:postcode":"77056",
    "sg:province":"TX",
    "sg:tags":[
        "property",
        "management"
    ],
    "wof:name":"Metropolitan Uptown",
    "wof:placetype":"venue"
},
  "geometry": {"coordinates":[-95.466674,29.732473],"type":"Point"}
}