{
  "type": "Feature",
  "properties": {
    "iso:country":"US",
    "sg:address":"2330 Knighthood Ln",
    "sg:city":"Garland",
    "sg:classifiers":[
        {
            "category":"Professional",
            "type":"Services"
        }
    ],
    "sg:phone":"+1 972 496 9306",
    "sg:postcode":"75044",
    "sg:province":"TX",
    "wof:name":"Huy Pham Co",
    "wof:placetype":"venue"
},
  "geometry": {"coordinates":[-96.663532,32.955989],"type":"Point"}
}