{
  "type": "Feature",
  "properties": {
    "iso:country":"US",
    "sg:address":"609 E Lufkin Ave",
    "sg:city":"Lufkin",
    "sg:classifiers":[
        {
            "category":"Health Services",
            "subcategory":"Health Practitioner",
            "type":"Services"
        }
    ],
    "sg:phone":"+1 936 632 2252",
    "sg:postcode":"75901",
    "sg:province":"TX",
    "wof:name":"Sally E Muhlbach Ms",
    "wof:placetype":"venue"
},
  "geometry": {"coordinates":[-94.72359400000001,31.337574],"type":"Point"}
}