{
  "type": "Feature",
  "properties": {
    "iso:country":"US",
    "sg:address":"2001 Bering Dr",
    "sg:city":"Houston",
    "sg:classifiers":[
        {
            "category":"Arts & Performance",
            "subcategory":"Theater",
            "type":"Entertainment"
        }
    ],
    "sg:phone":"+1 713 977 5022",
    "sg:postcode":"77057",
    "sg:province":"TX",
    "sg:tags":[
        "entertainer"
    ],
    "wof:name":"A-Bash Singing Telegrams",
    "wof:placetype":"venue"
},
  "geometry": {"coordinates":[-95.47941,29.74486],"type":"Point"}
}