{
  "type": "Feature",
  "properties": {
    "iso:country":"US",
    "sg:address":"5601 Brodie Ln",
    "sg:city":"Austin",
    "sg:classifiers":[
        {
            "category":"Restaurant",
            "type":"Food & Drink"
        }
    ],
    "sg:menulink":"http://www.allmenus.com/tx/austin/105067-carinos-italian-grill/menu/",
    "sg:phone":"+1 512 899 0572",
    "sg:postcode":"78745",
    "sg:province":"TX",
    "sg:tags":[
        "american",
        "italian"
    ],
    "wof:name":"Carino's Italian Grill",
    "wof:placetype":"venue"
},
  "geometry": {"coordinates":[-97.82151,30.226863],"type":"Point"}
}