{
  "type": "Feature",
  "properties": {
    "iso:country":"US",
    "sg:address":"2711 Lyndon B Johnson Fwy Ste 1036",
    "sg:city":"Dallas",
    "sg:classifiers":[
        {
            "category":"Professional",
            "subcategory":"Lawyer & Legal Services",
            "type":"Services"
        }
    ],
    "sg:phone":"+1 214 866 0001",
    "sg:postcode":"75234",
    "sg:province":"TX",
    "sg:website":"www.chalkerflores.com",
    "wof:name":"Chalker Flores Llp",
    "wof:placetype":"venue"
},
  "geometry": {"coordinates":[-96.887623,32.910478],"type":"Point"}
}