{
  "type": "Feature",
  "properties": {
    "iso:country":"US",
    "sg:address":"12508 Memorial Dr",
    "sg:city":"Houston",
    "sg:classifiers":[
        {
            "category":"Shopping",
            "subcategory":"Clothing, Apparel, & Fashions",
            "type":"Retail Goods"
        }
    ],
    "sg:phone":"+1 713 984 2746",
    "sg:postcode":"77024",
    "sg:province":"TX",
    "sg:tags":[
        "accessory"
    ],
    "wof:name":"Trina Morgan",
    "wof:placetype":"venue"
},
  "geometry": {"coordinates":[-95.550276,29.766351],"type":"Point"}
}