{
  "type": "Feature",
  "properties": {
    "iso:country":"US",
    "sg:address":"3904 John Stockbauer Dr",
    "sg:city":"Victoria",
    "sg:classifiers":[
        {
            "category":"Professional",
            "subcategory":"Business Services",
            "type":"Services"
        }
    ],
    "sg:phone":"+1 361 575 1460",
    "sg:postcode":"77904",
    "sg:province":"TX",
    "sg:tags":[
        "animal"
    ],
    "wof:name":"Kleinen Zwinger",
    "wof:placetype":"venue"
},
  "geometry": {"coordinates":[-96.946563,28.817501],"type":"Point"}
}