{
  "type": "Feature",
  "properties": {
    "iso:country":"US",
    "sg:address":"9545 Goldenrod Cir",
    "sg:city":"San Antonio",
    "sg:classifiers":[
        {
            "category":"Building & Trades",
            "subcategory":"Construction",
            "type":"Services"
        }
    ],
    "sg:phone":"+1 210 651 9249",
    "sg:postcode":"78266",
    "sg:province":"TX",
    "sg:tags":[
        "roofing",
        "contractor"
    ],
    "wof:name":"Yuras Roofing Co",
    "wof:placetype":"venue"
},
  "geometry": {"coordinates":[-98.30412200000001,29.639848],"type":"Point"}
}