{
  "type": "Feature",
  "properties": {
    "iso:country":"US",
    "sg:address":"106 S Beaton St",
    "sg:city":"Corsicana",
    "sg:classifiers":[
        {
            "category":"Shopping",
            "subcategory":"Computers & Home Electronics",
            "type":"Retail Goods"
        }
    ],
    "sg:phone":"+1 903 872 5269",
    "sg:postcode":"75110",
    "sg:province":"TX",
    "sg:tags":[
        "equipment",
        "dealer"
    ],
    "wof:name":"P C Docs",
    "wof:placetype":"venue"
},
  "geometry": {"coordinates":[-96.46364199999999,32.093523],"type":"Point"}
}