{
  "type": "Feature",
  "properties": {
    "iso:country":"US",
    "sg:address":"939 Far Paddock Rd",
    "sg:city":"Waco",
    "sg:classifiers":[
        {
            "category":"Building & Trades",
            "subcategory":"Construction",
            "type":"Services"
        }
    ],
    "sg:phone":"+1 214 951 0062",
    "sg:postcode":"76705",
    "sg:province":"TX",
    "sg:tags":[
        "contractor"
    ],
    "wof:name":"Renard Products Inc",
    "wof:placetype":"venue"
},
  "geometry": {"coordinates":[-97.15803200000001,31.665892],"type":"Point"}
}