{
  "type": "Feature",
  "properties": {
    "iso:country":"US",
    "sg:address":"11613 Coleta Creek Dr",
    "sg:city":"Corpus Christi",
    "sg:classifiers":[
        {
            "category":"Organizations",
            "subcategory":"Religious Organization",
            "type":"Services"
        }
    ],
    "sg:phone":"+1 361 241 6899",
    "sg:postcode":"78410",
    "sg:province":"TX",
    "wof:name":"Desktop Designs By Christ",
    "wof:placetype":"venue"
},
  "geometry": {"coordinates":[-97.596711,27.846276],"type":"Point"}
}