{
  "type": "Feature",
  "properties": {
    "iso:country":"US",
    "sg:address":"12310 Capistrano St",
    "sg:city":"Houston",
    "sg:classifiers":[
        {
            "category":"Education",
            "subcategory":"Vocational School",
            "type":"Public Place"
        }
    ],
    "sg:phone":"+1 713 455 4664",
    "sg:postcode":"77015",
    "sg:province":"TX",
    "wof:name":"Alkim Training Services I",
    "wof:placetype":"venue"
},
  "geometry": {"coordinates":[-95.219409,29.763928],"type":"Point"}
}