{
  "type": "Feature",
  "properties": {
    "iso:country":"US",
    "sg:address":"12834 Veterans Memorial Dr",
    "sg:city":"Houston",
    "sg:classifiers":[
        {
            "category":"Autos & Motor Vehicles",
            "subcategory":"Automobile Sales",
            "type":"Retail Goods"
        }
    ],
    "sg:phone":"+1 281 397 6788",
    "sg:postcode":"77014",
    "sg:province":"TX",
    "sg:tags":[
        "car",
        "dealer"
    ],
    "wof:name":"Mccullough Enterprises",
    "wof:placetype":"venue"
},
  "geometry": {"coordinates":[-95.487657,29.97361],"type":"Point"}
}