{
  "type": "Feature",
  "properties": {
    "iso:country":"US",
    "sg:address":"165 N Ave Q",
    "sg:city":"Clifton",
    "sg:classifiers":[
        {
            "category":"Professional",
            "subcategory":"Management & Consulting",
            "type":"Services"
        }
    ],
    "sg:phone":"+1 254 675 4695",
    "sg:postcode":"76634",
    "sg:province":"TX",
    "sg:tags":[
        "fuel"
    ],
    "wof:name":"Pasture-Wise Mgmt Svc",
    "wof:placetype":"venue"
},
  "geometry": {"coordinates":[-97.586337,31.77913],"type":"Point"}
}