{
  "type": "Feature",
  "properties": {
    "iso:country":"US",
    "sg:address":"116 SW Johnson Ave",
    "sg:city":"Burleson",
    "sg:classifiers":[
        {
            "category":"Shopping",
            "subcategory":"Used Merchandise",
            "type":"Retail Goods"
        }
    ],
    "sg:phone":"+1 817 295 5507",
    "sg:postcode":"76028",
    "sg:province":"TX",
    "sg:tags":[
        "antique"
    ],
    "wof:name":"Lambert's Antiques & Gifts",
    "wof:placetype":"venue"
},
  "geometry": {"coordinates":[-97.325461,32.542177],"type":"Point"}
}