{
  "type": "Feature",
  "properties": {
    "iso:country":"US",
    "sg:address":"7729 Garland Rd",
    "sg:city":"Dallas",
    "sg:classifiers":[
        {
            "category":"Food & Beverages",
            "subcategory":"Liquor & Beverages",
            "type":"Retail Goods"
        }
    ],
    "sg:phone":"+1 214 321 4035",
    "sg:postcode":"75218",
    "sg:province":"TX",
    "sg:tags":[
        "alcoholic"
    ],
    "wof:name":"Payless Liquors",
    "wof:placetype":"venue"
},
  "geometry": {"coordinates":[-96.72774699999999,32.812297],"type":"Point"}
}