{
  "type": "Feature",
  "properties": {
    "iso:country":"US",
    "sg:address":"1104 W Comal St",
    "sg:city":"Pearsall",
    "sg:classifiers":[
        {
            "category":"Autos & Motor Vehicles",
            "subcategory":"Fuel & Gas Station",
            "type":"Retail Goods"
        },
        {
            "category":"Food & Beverages",
            "subcategory":"Groceries & Convenience Stores",
            "type":"Retail Goods"
        }
    ],
    "sg:phone":"+1 830 334 2944",
    "sg:postcode":"78061",
    "sg:province":"TX",
    "wof:name":"Brothers Self Serve",
    "wof:placetype":"venue"
},
  "geometry": {"coordinates":[-99.105631,28.892447],"type":"Point"}
}