{
  "type": "Feature",
  "properties": {
    "iso:country":"US",
    "sg:address":"1300 Post Oak Blvd",
    "sg:city":"Houston",
    "sg:classifiers":[
        {
            "category":"Professional",
            "subcategory":"Employment Agencies",
            "type":"Services"
        }
    ],
    "sg:phone":"+1 713 223 7200",
    "sg:postcode":"77056",
    "sg:province":"TX",
    "sg:tags":[
        "help",
        "supply"
    ],
    "wof:name":"Interim Services",
    "wof:placetype":"venue"
},
  "geometry": {"coordinates":[-95.458884,29.753128],"type":"Point"}
}