{
  "type": "Feature",
  "properties": {
    "iso:country":"US",
    "sg:address":"500 W William Cannon Dr",
    "sg:city":"Austin",
    "sg:classifiers":[
        {
            "category":"Wholesale",
            "subcategory":"Machinery & Supplies",
            "type":"Manufacturing & Wholesale Goods"
        },
        {
            "category":"Retail",
            "subcategory":"Repair Shop",
            "type":"Services"
        }
    ],
    "sg:phone":"+1 512 477 4477",
    "sg:postcode":"78745",
    "sg:province":"TX",
    "sg:tags":[
        "lock",
        "road",
        "locksmith"
    ],
    "wof:name":"America's Locksmith-Austin",
    "wof:placetype":"venue"
},
  "geometry": {"coordinates":[-97.78683700000001,30.196775],"type":"Point"}
}