{
  "type": "Feature",
  "properties": {
    "iso:country":"US",
    "sg:address":"416 Dasher Dr",
    "sg:city":"Austin",
    "sg:classifiers":[
        {
            "category":"Professional",
            "type":"Services"
        }
    ],
    "sg:phone":"+1 512 261 7769",
    "sg:postcode":"78734",
    "sg:province":"TX",
    "wof:name":"Aperture Works",
    "wof:placetype":"venue"
},
  "geometry": {"coordinates":[-97.996436,30.360387],"type":"Point"}
}