{
  "type": "Feature",
  "properties": {
    "iso:country":"US",
    "sg:address":"726 E Lake St",
    "sg:city":"Crystal City",
    "sg:classifiers":[
        {
            "category":"Food & Beverages",
            "subcategory":"Groceries & Convenience Stores",
            "type":"Retail Goods"
        }
    ],
    "sg:phone":"+1 830 374 5785",
    "sg:postcode":"78839",
    "sg:province":"TX",
    "sg:tags":[
        "grocer"
    ],
    "wof:name":"Uncle Sam's",
    "wof:placetype":"venue"
},
  "geometry": {"coordinates":[-99.82092900000001,28.6797],"type":"Point"}
}