{
  "type": "Feature",
  "properties": {
    "iso:country":"US",
    "sg:address":"14510 Grisby Rd",
    "sg:city":"Houston",
    "sg:classifiers":[
        {
            "category":"Bars & Pubs",
            "type":"Food & Drink"
        },
        {
            "category":"Restaurant",
            "type":"Food & Drink"
        }
    ],
    "sg:phone":"+1 281 496 0030",
    "sg:postcode":"77079",
    "sg:province":"TX",
    "sg:tags":[
        "style",
        "family",
        "lunch",
        "american",
        "brunch",
        "breakfast",
        "italian"
    ],
    "sg:website":"http://www.pastalomonte.com",
    "wof:name":"Lomonte's Italian Restaurant",
    "wof:placetype":"venue"
},
  "geometry": {"coordinates":[-95.641898,29.782562],"type":"Point"}
}