{
  "type": "Feature",
  "properties": {
    "iso:country":"US",
    "sg:address":"622 S Oakes St",
    "sg:city":"San Angelo",
    "sg:classifiers":[
        {
            "category":"Government",
            "subcategory":"Office",
            "type":"Public Place"
        },
        {
            "category":"Health Services",
            "subcategory":"Clinic",
            "type":"Services"
        }
    ],
    "sg:phone":"+1 325 659 7900",
    "sg:postcode":"76903",
    "sg:province":"TX",
    "sg:tags":[
        "state",
        "resource"
    ],
    "wof:name":"Aged & Disabled Svc",
    "wof:placetype":"venue"
},
  "geometry": {"coordinates":[-100.431583,31.454802],"type":"Point"}
}