{
  "type": "Feature",
  "properties": {
    "iso:country":"US",
    "sg:address":"2920 Kendale Dr",
    "sg:city":"Dallas",
    "sg:classifiers":[
        {
            "category":"Real Estate",
            "subcategory":"Real Estate Operator",
            "type":"Services"
        }
    ],
    "sg:phone":"+1 214 358 1427",
    "sg:postcode":"75220",
    "sg:province":"TX",
    "sg:tags":[
        "building",
        "apartment"
    ],
    "wof:name":"In Place Apartments",
    "wof:placetype":"venue"
},
  "geometry": {"coordinates":[-96.874458,32.859064],"type":"Point"}
}