{
  "type": "Feature",
  "properties": {
    "iso:country":"US",
    "sg:address":"803 Laverne Ave",
    "sg:city":"Pasadena",
    "sg:classifiers":[
        {
            "category":"Professional",
            "subcategory":"Management & Consulting",
            "type":"Services"
        }
    ],
    "sg:phone":"+1 713 477 3219",
    "sg:postcode":"77502",
    "sg:province":"TX",
    "sg:tags":[
        "business"
    ],
    "wof:name":"Livesay Service",
    "wof:placetype":"venue"
},
  "geometry": {"coordinates":[-95.202896,29.676806],"type":"Point"}
}