{
  "type": "Feature",
  "properties": {
    "iso:country":"US",
    "sg:address":"11333 Fountain Lake Dr",
    "sg:city":"Stafford",
    "sg:classifiers":[
        {
            "category":"Personal",
            "subcategory":"Beauty Salon",
            "type":"Services"
        }
    ],
    "sg:phone":"+1 281 340 2245",
    "sg:postcode":"77477",
    "sg:province":"TX",
    "sg:tags":[
        "shop"
    ],
    "wof:name":"Pam Flores",
    "wof:placetype":"venue"
},
  "geometry": {"coordinates":[-95.584582,29.638921],"type":"Point"}
}