{
  "type": "Feature",
  "properties": {
    "iso:country":"US",
    "sg:address":"10045 Aeronca Ln",
    "sg:city":"Mc Kinney",
    "sg:classifiers":[
        {
            "category":"Banks & Credit Unions",
            "subcategory":"Investment Brokerage",
            "type":"Services"
        }
    ],
    "sg:phone":"+1 972 346 9117",
    "sg:postcode":"75071",
    "sg:province":"TX",
    "wof:name":"Altus Investments Inc",
    "wof:placetype":"venue"
},
  "geometry": {"coordinates":[-96.743274,33.204058],"type":"Point"}
}