{
  "type": "Feature",
  "properties": {
    "iso:country":"US",
    "sg:address":"211 Roundup Trl",
    "sg:city":"Kerrville",
    "sg:classifiers":[
        {
            "category":"Professional",
            "subcategory":"Detective & Security Services",
            "type":"Services"
        }
    ],
    "sg:phone":"+1 830 895 0743",
    "sg:postcode":"78028",
    "sg:province":"TX",
    "sg:tags":[
        "information",
        "bureau"
    ],
    "wof:name":"Hunting Services Unlimited",
    "wof:placetype":"venue"
},
  "geometry": {"coordinates":[-99.20007200000001,30.052833],"type":"Point"}
}