{
  "type": "Feature",
  "properties": {
    "iso:country":"US",
    "sg:address":"17800 Davenport Rd",
    "sg:city":"Dallas",
    "sg:classifiers":[
        {
            "category":"Building & Trades",
            "subcategory":"Construction",
            "type":"Services"
        }
    ],
    "sg:phone":"+1 972 818 8588",
    "sg:postcode":"75252",
    "sg:province":"TX",
    "sg:tags":[
        "general",
        "contractor"
    ],
    "wof:name":"D K Merk Construction Co",
    "wof:placetype":"venue"
},
  "geometry": {"coordinates":[-96.793685,32.993952],"type":"Point"}
}