{
  "type": "Feature",
  "properties": {
    "iso:country":"US",
    "sg:address":"800 W Airport Fwy Ste 1015",
    "sg:city":"Irving",
    "sg:classifiers":[
        {
            "category":"Health Services",
            "subcategory":"Doctor",
            "type":"Services"
        }
    ],
    "sg:phone":"+1 972 445 0086",
    "sg:postcode":"75062",
    "sg:province":"TX",
    "sg:tags":[
        "psychiatrist"
    ],
    "wof:name":"Brophy Michael H MD",
    "wof:placetype":"venue"
},
  "geometry": {"coordinates":[-96.95639799999999,32.837299],"type":"Point"}
}