{
  "type": "Feature",
  "properties": {
    "iso:country":"US",
    "sg:address":"7908 Bow Ct",
    "sg:city":"Frisco",
    "sg:classifiers":[
        {
            "category":"Shopping",
            "subcategory":"Discount & Variety Stores",
            "type":"Retail Goods"
        }
    ],
    "sg:phone":"+1 469 633 0710",
    "sg:postcode":"75035",
    "sg:province":"TX",
    "sg:tags":[
        "item",
        "miscellaneous",
        "gift"
    ],
    "wof:name":"Golf Collections",
    "wof:placetype":"venue"
},
  "geometry": {"coordinates":[-96.78278299999999,33.143887],"type":"Point"}
}