{
  "type": "Feature",
  "properties": {
    "iso:country":"US",
    "sg:address":"17300 Dallas Pkwy",
    "sg:city":"Dallas",
    "sg:classifiers":[
        {
            "category":"Organizations",
            "subcategory":"Religious Organization",
            "type":"Services"
        }
    ],
    "sg:phone":"+1 972 381 1471",
    "sg:postcode":"75248",
    "sg:province":"TX",
    "wof:name":"Corp Prayer Resource",
    "wof:placetype":"venue"
},
  "geometry": {"coordinates":[-96.82820100000001,32.986],"type":"Point"}
}