{
  "type": "Feature",
  "properties": {
    "iso:country":"US",
    "sg:address":"404 S Main St",
    "sg:city":"Cotulla",
    "sg:classifiers":[
        {
            "category":"Personal",
            "subcategory":"Beauty Salon",
            "type":"Services"
        }
    ],
    "sg:phone":"+1 830 879 3505",
    "sg:postcode":"78014",
    "sg:province":"TX",
    "sg:tags":[
        "shop",
        "clothing"
    ],
    "wof:name":"Catas Hair & Nail Salon",
    "wof:placetype":"venue"
},
  "geometry": {"coordinates":[-99.23469799999999,28.431826],"type":"Point"}
}