{
  "type": "Feature",
  "properties": {
    "iso:country":"US",
    "sg:address":"722 Briar Way",
    "sg:city":"Garland",
    "sg:classifiers":[
        {
            "category":"Building & Trades",
            "subcategory":"Pest Control",
            "type":"Services"
        }
    ],
    "sg:phone":"+1 214 587 6720",
    "sg:postcode":"75043",
    "sg:province":"TX",
    "wof:name":"Williams Pest Control",
    "wof:placetype":"venue"
},
  "geometry": {"coordinates":[-96.63155500000001,32.849656],"type":"Point"}
}