{
  "type": "Feature",
  "properties": {
    "iso:country":"US",
    "sg:address":"12551 Steeple Way Blvd",
    "sg:city":"Houston",
    "sg:classifiers":[
        {
            "category":"Health Services",
            "subcategory":"Clinic",
            "type":"Services"
        }
    ],
    "sg:phone":"+1 281 894 0505",
    "sg:postcode":"77065",
    "sg:province":"TX",
    "wof:name":"Health Priority Homecare",
    "wof:placetype":"venue"
},
  "geometry": {"coordinates":[-95.587429,29.902041],"type":"Point"}
}