{
  "type": "Feature",
  "properties": {
    "iso:country":"US",
    "sg:address":"8710 Wood Glen Dr",
    "sg:city":"Rowlett",
    "sg:classifiers":[
        {
            "category":"Shopping",
            "subcategory":"Used Merchandise",
            "type":"Retail Goods"
        }
    ],
    "sg:phone":"+1 972 475 6214",
    "sg:postcode":"75088",
    "sg:province":"TX",
    "wof:name":"Two Kats",
    "wof:placetype":"venue"
},
  "geometry": {"coordinates":[-96.515351,32.903987],"type":"Point"}
}