{
  "type": "Feature",
  "properties": {
    "iso:country":"US",
    "sg:address":"1530 Clinton Dr",
    "sg:city":"Galena Park",
    "sg:classifiers":[
        {
            "category":"Food & Beverages",
            "subcategory":"Groceries & Convenience Stores",
            "type":"Retail Goods"
        }
    ],
    "sg:phone":"+1 713 450 2986",
    "sg:postcode":"77547",
    "sg:province":"TX",
    "wof:name":"Quick Stop",
    "wof:placetype":"venue"
},
  "geometry": {"coordinates":[-95.236099,29.732599],"type":"Point"}
}