{
  "type": "Feature",
  "properties": {
    "iso:country":"US",
    "sg:address":"723 Donaldson Ave",
    "sg:city":"San Antonio",
    "sg:classifiers":[
        {
            "category":"Education",
            "subcategory":"School",
            "type":"Public Place"
        }
    ],
    "sg:phone":"+1 210 736 1981",
    "sg:postcode":"78201",
    "sg:province":"TX",
    "wof:name":"Jefferson High School",
    "wof:placetype":"venue"
},
  "geometry": {"coordinates":[-98.537171,29.463787],"type":"Point"}
}