{
  "type": "Feature",
  "properties": {
    "iso:country":"US",
    "sg:address":"905 Stephens St",
    "sg:city":"Clyde",
    "sg:classifiers":[
        {
            "category":"Freight",
            "type":"Transportation"
        }
    ],
    "sg:phone":"+1 325 893 1240",
    "sg:postcode":"79510",
    "sg:province":"TX",
    "sg:tags":[
        "trucking"
    ],
    "wof:name":"Action Transport",
    "wof:placetype":"venue"
},
  "geometry": {"coordinates":[-99.48992200000001,32.39443],"type":"Point"}
}