{
  "type": "Feature",
  "properties": {
    "iso:country":"US",
    "sg:address":"1521 I- 35 N",
    "sg:city":"Waco",
    "sg:classifiers":[
        {
            "category":"Restaurant",
            "type":"Food & Drink"
        }
    ],
    "sg:phone":"+1 254 867 6621",
    "sg:postcode":"76705",
    "sg:province":"TX",
    "wof:name":"Mc Donald's",
    "wof:placetype":"venue"
},
  "geometry": {"coordinates":[-97.10878099999999,31.600535],"type":"Point"}
}