{
  "type": "Feature",
  "properties": {
    "iso:country":"US",
    "sg:address":"3333 W Alabama St",
    "sg:city":"Houston",
    "sg:classifiers":[
        {
            "category":"Professional",
            "subcategory":"Advertising",
            "type":"Services"
        },
        {
            "category":"Professional",
            "subcategory":"Computer Services",
            "type":"Services"
        }
    ],
    "sg:phone":"+1 713 942 7600",
    "sg:postcode":"77098",
    "sg:province":"TX",
    "sg:tags":[
        "counselor",
        "printing",
        "commercial",
        "related"
    ],
    "wof:name":"Locklin Agency",
    "wof:placetype":"venue"
},
  "geometry": {"coordinates":[-95.42997,29.738336],"type":"Point"}
}