{
  "type": "Feature",
  "properties": {
    "iso:country":"US",
    "sg:address":"1341 E Mulberry St",
    "sg:city":"Angleton",
    "sg:classifiers":[
        {
            "category":"Restaurant",
            "type":"Food & Drink"
        }
    ],
    "sg:phone":"+1 979 849 3572",
    "sg:postcode":"77515",
    "sg:province":"TX",
    "sg:tags":[
        "eating"
    ],
    "wof:name":"Church's Chicken",
    "wof:placetype":"venue"
},
  "geometry": {"coordinates":[-95.416434,29.172443],"type":"Point"}
}