{
  "type": "Feature",
  "properties": {
    "iso:country":"US",
    "sg:address":"257 Burger St",
    "sg:city":"Abilene",
    "sg:classifiers":[
        {
            "category":"Retail",
            "subcategory":"Laundry & Dry Cleaning",
            "type":"Services"
        }
    ],
    "sg:phone":"+1 325 677 7090",
    "sg:postcode":"79603",
    "sg:province":"TX",
    "sg:tags":[
        "drycleaning",
        "plant"
    ],
    "wof:name":"Eagle Cleaners",
    "wof:placetype":"venue"
},
  "geometry": {"coordinates":[-99.755737,32.452352],"type":"Point"}
}