{
  "type": "Feature",
  "properties": {
    "iso:country":"US",
    "sg:address":"804 Quail Park Ln",
    "sg:city":"Cleburne",
    "sg:classifiers":[
        {
            "category":"Manufacturing",
            "subcategory":"Retail Goods",
            "type":"Manufacturing & Wholesale Goods"
        }
    ],
    "sg:phone":"+1 817 999 5105",
    "sg:postcode":"76031",
    "sg:province":"TX",
    "sg:tags":[
        "manufacturer"
    ],
    "wof:name":"Shue Rack",
    "wof:placetype":"venue"
},
  "geometry": {"coordinates":[-97.370777,32.411535],"type":"Point"}
}