{
  "type": "Feature",
  "properties": {
    "iso:country":"US",
    "sg:address":"829 W Main St",
    "sg:city":"Crosbyton",
    "sg:classifiers":[
        {
            "category":"Food & Beverages",
            "subcategory":"Groceries & Convenience Stores",
            "type":"Retail Goods"
        }
    ],
    "sg:phone":"+1 806 675 0161",
    "sg:postcode":"79322",
    "sg:province":"TX",
    "wof:name":"Ampride",
    "wof:placetype":"venue"
},
  "geometry": {"coordinates":[-101.250818,33.659963],"type":"Point"}
}