{
  "type": "Feature",
  "properties": {
    "iso:country":"US",
    "sg:address":"1302 Guildford St",
    "sg:city":"Garland",
    "sg:classifiers":[
        {
            "category":"Real Estate",
            "subcategory":"Real Estate Agent",
            "type":"Services"
        }
    ],
    "sg:phone":"+1 972 271 7777",
    "sg:postcode":"75040",
    "sg:province":"TX",
    "wof:name":"North Texas Realtors",
    "wof:placetype":"venue"
},
  "geometry": {"coordinates":[-96.648143,32.937283],"type":"Point"}
}