{
  "type": "Feature",
  "properties": {
    "iso:country":"US",
    "sg:address":"7625 Parkhurst Dr",
    "sg:city":"Houston",
    "sg:classifiers":[
        {
            "category":"Manufacturing",
            "subcategory":"Glass & Minerals",
            "type":"Manufacturing & Wholesale Goods"
        }
    ],
    "sg:phone":"+1 713 633 0982",
    "sg:postcode":"77028",
    "sg:province":"TX",
    "sg:tags":[
        "fabricator",
        "fiber"
    ],
    "wof:name":"International Grating Inc",
    "wof:placetype":"venue"
},
  "geometry": {"coordinates":[-95.287008,29.832941],"type":"Point"}
}