{
  "type": "Feature",
  "properties": {
    "iso:country":"US",
    "sg:address":"504 Burleson St",
    "sg:city":"San Marcos",
    "sg:classifiers":[
        {
            "category":"Real Estate",
            "subcategory":"Real Estate Agent",
            "type":"Services"
        }
    ],
    "sg:phone":"+1 512 396 1027",
    "sg:postcode":"78666",
    "sg:province":"TX",
    "wof:name":"Forrreal Ltd",
    "wof:placetype":"venue"
},
  "geometry": {"coordinates":[-97.94773000000001,29.883597],"type":"Point"}
}