{
  "type": "Feature",
  "properties": {
    "iso:country":"US",
    "sg:address":"4620 S Cooper St",
    "sg:city":"Arlington",
    "sg:classifiers":[
        {
            "category":"Shopping",
            "subcategory":"Bicycles & Sporting Goods",
            "type":"Retail Goods"
        }
    ],
    "sg:phone":"+1 817 467 0090",
    "sg:postcode":"76017",
    "sg:province":"TX",
    "sg:website":"www.oshmans.com",
    "wof:name":"Sports Authority",
    "wof:placetype":"venue"
},
  "geometry": {"coordinates":[-97.13441899999999,32.670653],"type":"Point"}
}