{
  "type": "Feature",
  "properties": {
    "iso:country":"US",
    "sg:address":"20333 State Highway 249",
    "sg:city":"Houston",
    "sg:classifiers":[
        {
            "category":"Professional",
            "subcategory":"Business Services",
            "type":"Services"
        }
    ],
    "sg:phone":"+1 281 378 8057",
    "sg:postcode":"77070",
    "sg:province":"TX",
    "sg:tags":[
        "broker"
    ],
    "wof:name":"Resolute Business Advisors",
    "wof:placetype":"venue"
},
  "geometry": {"coordinates":[-95.57235,29.987992],"type":"Point"}
}