{
  "type": "Feature",
  "properties": {
    "iso:country":"US",
    "sg:address":"1015 9th St",
    "sg:city":"Lubbock",
    "sg:classifiers":[
        {
            "category":"Government",
            "subcategory":"Office",
            "type":"Public Place"
        }
    ],
    "sg:phone":"+1 806 775 2464",
    "sg:postcode":"79401",
    "sg:province":"TX",
    "sg:tags":[
        "village"
    ],
    "wof:name":"Lubbock City Prosecutor",
    "wof:placetype":"venue"
},
  "geometry": {"coordinates":[-101.846666,33.587305],"type":"Point"}
}