{
  "type": "Feature",
  "properties": {
    "iso:country":"US",
    "sg:address":"601 US Hwy 77",
    "sg:city":"Waxahachie",
    "sg:classifiers":[
        {
            "category":"Restaurant",
            "type":"Food & Drink"
        }
    ],
    "sg:phone":"+1 972 937 9422",
    "sg:postcode":"75165",
    "sg:province":"TX",
    "sg:tags":[
        "eating"
    ],
    "wof:name":"Applebees",
    "wof:placetype":"venue"
},
  "geometry": {"coordinates":[-96.85226299999999,32.380524],"type":"Point"}
}