{
  "type": "Feature",
  "properties": {
    "iso:country":"US",
    "sg:address":"5688 Randolph Blvd",
    "sg:city":"San Antonio",
    "sg:classifiers":[
        {
            "category":"Professional",
            "subcategory":"Advertising",
            "type":"Services"
        }
    ],
    "sg:phone":"+1 210 590 6339",
    "sg:postcode":"78233",
    "sg:province":"TX",
    "sg:tags":[
        "distribution"
    ],
    "wof:name":"Pepperidge Farm Bread Sales",
    "wof:placetype":"venue"
},
  "geometry": {"coordinates":[-98.378756,29.533184],"type":"Point"}
}