{
  "type": "Feature",
  "properties": {
    "iso:country":"US",
    "sg:address":"301 US Hwy 82",
    "sg:city":"New Boston",
    "sg:classifiers":[
        {
            "category":"Retail",
            "subcategory":"Auto Rental",
            "type":"Services"
        }
    ],
    "sg:phone":"+1 903 628 0011",
    "sg:postcode":"75571",
    "sg:province":"TX",
    "sg:tags":[
        "renting",
        "automobile"
    ],
    "wof:name":"Shoot Spray Rent LTD",
    "wof:placetype":"venue"
},
  "geometry": {"coordinates":[-94.426035,33.461565],"type":"Point"}
}