{
  "type": "Feature",
  "properties": {
    "iso:country":"US",
    "sg:address":"103 N Cedar Ridge Dr",
    "sg:city":"Duncanville",
    "sg:classifiers":[
        {
            "category":"Banks & Credit Unions",
            "subcategory":"Bank",
            "type":"Services"
        }
    ],
    "sg:phone":"+1 972 296 5263",
    "sg:postcode":"75116",
    "sg:province":"TX",
    "sg:tags":[
        "federal",
        "savings",
        "institution"
    ],
    "wof:name":"Washington Mutual",
    "wof:placetype":"venue"
},
  "geometry": {"coordinates":[-96.925825,32.652631],"type":"Point"}
}