{
  "type": "Feature",
  "properties": {
    "iso:country":"US",
    "sg:address":"676 Olde Oaks Dr",
    "sg:city":"Temple",
    "sg:classifiers":[
        {
            "category":"Professional",
            "type":"Services"
        }
    ],
    "sg:phone":"+1 254 982 4630",
    "sg:postcode":"76502",
    "sg:province":"TX",
    "wof:name":"Michael D Moon",
    "wof:placetype":"venue"
},
  "geometry": {"coordinates":[-97.378942,31.02075],"type":"Point"}
}