{
  "type": "Feature",
  "properties": {
    "iso:country":"US",
    "sg:address":"201 Valley View Mall",
    "sg:city":"Dallas",
    "sg:classifiers":[
        {
            "category":"Utilities",
            "subcategory":"Mobile Phone",
            "type":"Services"
        }
    ],
    "sg:phone":"+1 972 239 2960",
    "sg:postcode":"75240",
    "sg:province":"TX",
    "sg:tags":[
        "telephone",
        "cellular"
    ],
    "wof:name":"Nextel Retail",
    "wof:placetype":"venue"
},
  "geometry": {"coordinates":[-96.81061099999999,32.930645],"type":"Point"}
}