{
  "type": "Feature",
  "properties": {
    "iso:country":"US",
    "sg:address":"2008 34th St",
    "sg:city":"Lubbock",
    "sg:classifiers":[
        {
            "category":"Shopping",
            "subcategory":"Hobbies, Toys, & Games",
            "type":"Retail Goods"
        }
    ],
    "sg:phone":"+1 806 763 4054",
    "sg:postcode":"79411",
    "sg:province":"TX",
    "sg:tags":[
        "supply"
    ],
    "wof:name":"Mad Hatter's House Of Games",
    "wof:placetype":"venue"
},
  "geometry": {"coordinates":[-101.86076799999999,33.563357],"type":"Point"}
}