{
  "type": "Feature",
  "properties": {
    "iso:country":"US",
    "sg:address":"3748 Ashford Dr",
    "sg:city":"Bedford",
    "sg:classifiers":[
        {
            "category":"Restaurant",
            "type":"Food & Drink"
        }
    ],
    "sg:phone":"+1 817 283 3875",
    "sg:postcode":"76021",
    "sg:province":"TX",
    "sg:tags":[
        "eating"
    ],
    "wof:name":"Lonestar Drive In",
    "wof:placetype":"venue"
},
  "geometry": {"coordinates":[-97.107682,32.862377],"type":"Point"}
}