{
  "type": "Feature",
  "properties": {
    "iso:country":"US",
    "sg:address":"10100 Clay Rd",
    "sg:city":"Houston",
    "sg:classifiers":[
        {
            "category":"Manufacturing",
            "subcategory":"Printing",
            "type":"Manufacturing & Wholesale Goods"
        }
    ],
    "sg:phone":"+1 713 681 9000",
    "sg:postcode":"77080",
    "sg:province":"TX",
    "sg:tags":[
        "lithographic",
        "commercial"
    ],
    "wof:name":"Sprint Digital Print",
    "wof:placetype":"venue"
},
  "geometry": {"coordinates":[-95.545536,29.832312],"type":"Point"}
}