{
  "type": "Feature",
  "properties": {
    "iso:country":"US",
    "sg:address":"2801 N Fir St",
    "sg:city":"La Feria",
    "sg:classifiers":[
        {
            "category":"Autos & Motor Vehicles",
            "subcategory":"Auto Supplies",
            "type":"Retail Goods"
        }
    ],
    "sg:phone":"+1 956 797 3143",
    "sg:postcode":"78577",
    "sg:province":"TX",
    "sg:tags":[
        "equipment",
        "air",
        "conditioning",
        "automobile"
    ],
    "wof:name":"Auto Bus Air",
    "wof:placetype":"venue"
},
  "geometry": {"coordinates":[-98.172427,26.217121],"type":"Point"}
}