{
  "type": "Feature",
  "properties": {
    "iso:country":"US",
    "sg:address":"612 W 4th St",
    "sg:city":"Austin",
    "sg:classifiers":[
        {
            "category":"Arts & Performance",
            "subcategory":"Music",
            "type":"Entertainment"
        }
    ],
    "sg:phone":"+1 512 472 2293",
    "sg:postcode":"78701",
    "sg:province":"TX",
    "sg:tags":[
        "venue"
    ],
    "sg:website":"www.lazonarosa.com",
    "wof:name":"La Zona Rosa",
    "wof:placetype":"venue"
},
  "geometry": {"coordinates":[-97.74949599999999,30.268],"type":"Point"}
}