{
  "type": "Feature",
  "properties": {
    "iso:country":"US",
    "sg:address":"1803 Baylor Dr",
    "sg:city":"Richardson",
    "sg:classifiers":[
        {
            "category":"Professional",
            "type":"Services"
        }
    ],
    "sg:phone":"+1 972 669 2430",
    "sg:postcode":"75081",
    "sg:province":"TX",
    "sg:tags":[
        "establishment"
    ],
    "wof:name":"Inhouse Imaging Inc",
    "wof:placetype":"venue"
},
  "geometry": {"coordinates":[-96.687505,32.931881],"type":"Point"}
}