{
  "type": "Feature",
  "properties": {
    "iso:country":"US",
    "sg:address":"8550 Fireside Dr",
    "sg:city":"Dallas",
    "sg:classifiers":[
        {
            "category":"Freight",
            "type":"Transportation"
        }
    ],
    "sg:phone":"+1 214 398 9206",
    "sg:postcode":"75217",
    "sg:province":"TX",
    "sg:tags":[
        "operator",
        "local",
        "trucking"
    ],
    "wof:name":"Cash Trucking",
    "wof:placetype":"venue"
},
  "geometry": {"coordinates":[-96.670361,32.697818],"type":"Point"}
}