{
  "type": "Feature",
  "properties": {
    "iso:country":"US",
    "sg:address":"8694 Rolling Acres Trl",
    "sg:city":"Fair Oaks Ranch",
    "sg:classifiers":[
        {
            "category":"Professional",
            "type":"Services"
        }
    ],
    "sg:phone":"+1 830 981 8505",
    "sg:postcode":"78015",
    "sg:province":"TX",
    "sg:tags":[
        "establishment"
    ],
    "wof:name":"Awbrey & Stuart",
    "wof:placetype":"venue"
},
  "geometry": {"coordinates":[-98.65469899999999,29.763754],"type":"Point"}
}