{
  "type": "Feature",
  "properties": {
    "iso:country":"US",
    "sg:address":"8221 Grapevine Hwy",
    "sg:city":"Fort Worth",
    "sg:classifiers":[
        {
            "category":"Building & Trades",
            "subcategory":"Construction",
            "type":"Services"
        }
    ],
    "sg:phone":"+1 817 485 5685",
    "sg:postcode":"76180",
    "sg:province":"TX",
    "sg:tags":[
        "contractor"
    ],
    "wof:name":"M S T Constructors Inc",
    "wof:placetype":"venue"
},
  "geometry": {"coordinates":[-97.204837,32.840756],"type":"Point"}
}