{
  "type": "Feature",
  "properties": {
    "iso:country":"US",
    "sg:address":"7441 Vanessa Dr",
    "sg:city":"Fort Worth",
    "sg:classifiers":[
        {
            "category":"Professional",
            "subcategory":"Business Services",
            "type":"Services"
        }
    ],
    "sg:phone":"+1 817 429 9097",
    "sg:postcode":"76112",
    "sg:province":"TX",
    "wof:name":"Brivirich",
    "wof:placetype":"venue"
},
  "geometry": {"coordinates":[-97.19648100000001,32.753082],"type":"Point"}
}