{
  "type": "Feature",
  "properties": {
    "iso:country":"US",
    "sg:address":"4411 N Central Expy",
    "sg:city":"Dallas",
    "sg:classifiers":[
        {
            "category":"Professional",
            "subcategory":"Lawyer & Legal Services",
            "type":"Services"
        }
    ],
    "sg:phone":"+1 214 521 8000",
    "sg:postcode":"75205",
    "sg:province":"TX",
    "wof:name":"Perry Lydia L Atty",
    "wof:placetype":"venue"
},
  "geometry": {"coordinates":[-96.78800200000001,32.819099],"type":"Point"}
}