{
  "type": "Feature",
  "properties": {
    "iso:country":"US",
    "sg:address":"960 W Roundbunch Rd",
    "sg:city":"Bridge City",
    "sg:classifiers":[
        {
            "category":"Health Services",
            "subcategory":"Doctor",
            "type":"Services"
        }
    ],
    "sg:phone":"+1 409 738 2828",
    "sg:postcode":"77611",
    "sg:province":"TX",
    "sg:tags":[
        "physician",
        "surgeon"
    ],
    "wof:name":"Daniel Crain DO",
    "wof:placetype":"venue"
},
  "geometry": {"coordinates":[-93.850008,30.034667],"type":"Point"}
}