{
  "type": "Feature",
  "properties": {
    "iso:country":"US",
    "sg:address":"241 W Commerce St",
    "sg:city":"Dallas",
    "sg:classifiers":[
        {
            "category":"Shopping",
            "type":"Retail Goods"
        }
    ],
    "sg:phone":"+1 214 744 2886",
    "sg:postcode":"75208",
    "sg:province":"TX",
    "sg:tags":[
        "merchandise"
    ],
    "wof:name":"Car Donation Program",
    "wof:placetype":"venue"
},
  "geometry": {"coordinates":[-96.825684,32.774276],"type":"Point"}
}