{
  "type": "Feature",
  "properties": {
    "iso:country":"US",
    "sg:address":"1400 Congress Ave",
    "sg:city":"Austin",
    "sg:classifiers":[
        {
            "category":"Government",
            "subcategory":"Office",
            "type":"Public Place"
        }
    ],
    "sg:phone":"+1 512 463 0117",
    "sg:postcode":"78701",
    "sg:province":"TX",
    "sg:website":"www.senate.state.tx.us",
    "wof:name":"Senator Kyle Janek",
    "wof:placetype":"venue"
},
  "geometry": {"coordinates":[-97.73946100000001,30.276961],"type":"Point"}
}