{
  "type": "Feature",
  "properties": {
    "iso:country":"US",
    "sg:address":"16227 Southampton Dr",
    "sg:city":"Spring",
    "sg:classifiers":[
        {
            "category":"Manufacturing",
            "subcategory":"Tools & Machinery",
            "type":"Manufacturing & Wholesale Goods"
        }
    ],
    "sg:phone":"+1 281 320 9965",
    "sg:postcode":"77379",
    "sg:province":"TX",
    "sg:tags":[
        "mfg",
        "industrial",
        "general"
    ],
    "wof:name":"Condatex",
    "wof:placetype":"venue"
},
  "geometry": {"coordinates":[-95.515956,30.01487],"type":"Point"}
}