{
  "type": "Feature",
  "properties": {
    "iso:country":"US",
    "sg:address":"224 Larga Vista Dr",
    "sg:city":"Laredo",
    "sg:classifiers":[
        {
            "category":"Freight",
            "type":"Transportation"
        }
    ],
    "sg:phone":"+1 956 712 2270",
    "sg:postcode":"78043",
    "sg:province":"TX",
    "sg:tags":[
        "operator",
        "local",
        "trucking"
    ],
    "wof:name":"Rt Trucking",
    "wof:placetype":"venue"
},
  "geometry": {"coordinates":[-99.430438,27.498568],"type":"Point"}
}