{
  "type": "Feature",
  "properties": {
    "iso:country":"US",
    "sg:address":"7606 Boeing Dr",
    "sg:city":"El Paso",
    "sg:classifiers":[
        {
            "category":"Building & Trades",
            "subcategory":"Construction",
            "type":"Services"
        }
    ],
    "sg:phone":"+1 915 731 3120",
    "sg:postcode":"79925",
    "sg:province":"TX",
    "sg:tags":[
        "coping",
        "plastering",
        "tiling",
        "pool",
        "swimming"
    ],
    "wof:name":"Wanagel Pools",
    "wof:placetype":"venue"
},
  "geometry": {"coordinates":[-106.378721,31.793459],"type":"Point"}
}