{
  "type": "Feature",
  "properties": {
    "iso:country":"US",
    "sg:address":"1403 Westgreen Blvd",
    "sg:city":"Katy",
    "sg:classifiers":[
        {
            "category":"Professional",
            "subcategory":"Computer Services",
            "type":"Services"
        }
    ],
    "sg:phone":"+1 281 492 8501",
    "sg:postcode":"77450",
    "sg:province":"TX",
    "sg:tags":[
        "prepackaged",
        "software"
    ],
    "wof:name":"H3 Software LLC",
    "wof:placetype":"venue"
},
  "geometry": {"coordinates":[-95.73477699999999,29.763474],"type":"Point"}
}