{
  "type": "Feature",
  "properties": {
    "iso:country":"US",
    "sg:address":"14288 Co Rd 21",
    "sg:city":"Perryton",
    "sg:phone":"+1 806 435 6169",
    "sg:postcode":"79070",
    "sg:province":"TX",
    "sg:tags":[
        "farm",
        "wheat"
    ],
    "wof:name":"Duane Pshigoda",
    "wof:placetype":"venue"
},
  "geometry": {"coordinates":[-100.710407,36.362065],"type":"Point"}
}