{
  "type": "Feature",
  "properties": {
    "iso:country":"US",
    "sg:address":"2602 FM 1960 W",
    "sg:city":"Houston",
    "sg:classifiers":[
        {
            "category":"Personal",
            "subcategory":"Beauty Salon",
            "type":"Services"
        }
    ],
    "sg:phone":"+1 281 444 0114",
    "sg:postcode":"77068",
    "sg:province":"TX",
    "wof:name":"Fashion Hair By Alf",
    "wof:placetype":"venue"
},
  "geometry": {"coordinates":[-95.46387900000001,30.007068],"type":"Point"}
}