{
  "type": "Feature",
  "properties": {
    "iso:country":"US",
    "sg:address":"168 Park 35 Cove N",
    "sg:city":"Buda",
    "sg:classifiers":[
        {
            "category":"Building & Trades",
            "subcategory":"Construction",
            "type":"Services"
        }
    ],
    "sg:phone":"+1 512 312 5100",
    "sg:postcode":"78610",
    "sg:province":"TX",
    "sg:tags":[
        "tile",
        "dealer"
    ],
    "wof:name":"Sun Tile Corp",
    "wof:placetype":"venue"
},
  "geometry": {"coordinates":[-97.833449,30.069236],"type":"Point"}
}