{
  "type": "Feature",
  "properties": {
    "iso:country":"US",
    "sg:address":"1907 Quincy St",
    "sg:city":"Plainview",
    "sg:classifiers":[
        {
            "category":"Home & Garden",
            "subcategory":"Furniture",
            "type":"Retail Goods"
        }
    ],
    "sg:phone":"+1 806 288 2828",
    "sg:postcode":"79072",
    "sg:province":"TX",
    "sg:tags":[
        "store"
    ],
    "wof:name":"Garner & Assoc.",
    "wof:placetype":"venue"
},
  "geometry": {"coordinates":[-101.724732,34.200879],"type":"Point"}
}