{
  "type": "Feature",
  "properties": {
    "iso:country":"US",
    "sg:address":"2070 Green Oaks Rd",
    "sg:city":"Fort Worth",
    "sg:classifiers":[
        {
            "category":"Food & Beverages",
            "subcategory":"Bakery",
            "type":"Retail Goods"
        },
        {
            "category":"Bakery",
            "type":"Food & Drink"
        }
    ],
    "sg:menulink":"http://www.allmenus.com/tx/fort-worth/230597-great-american-cookies/menu/",
    "sg:phone":"+1 817 377 8515",
    "sg:postcode":"76116",
    "sg:province":"TX",
    "sg:tags":[
        "american",
        "bakery",
        "pastry"
    ],
    "wof:name":"Great American Cookies",
    "wof:placetype":"venue"
},
  "geometry": {"coordinates":[-97.434004,32.737908],"type":"Point"}
}