{
  "type": "Feature",
  "properties": {
    "iso:country":"US",
    "sg:address":"5643 Drakestone Blvd",
    "sg:city":"Houston",
    "sg:classifiers":[
        {
            "category":"Restaurant",
            "type":"Food & Drink"
        }
    ],
    "sg:phone":"+1 713 434 8878",
    "sg:postcode":"77053",
    "sg:province":"TX",
    "wof:name":"Mi Lindo Huetano 2",
    "wof:placetype":"venue"
},
  "geometry": {"coordinates":[-95.46762099999999,29.60389],"type":"Point"}
}