{
  "type": "Feature",
  "properties": {
    "iso:country":"US",
    "sg:address":"708 Ballard St",
    "sg:city":"Cedar Hill",
    "sg:classifiers":[
        {
            "category":"Communications",
            "subcategory":"Film & Video Production",
            "type":"Services"
        }
    ],
    "sg:phone":"+1 972 293 3724",
    "sg:postcode":"75104",
    "sg:province":"TX",
    "sg:tags":[
        "motion"
    ],
    "wof:name":"Fat Asss Beats Productions",
    "wof:placetype":"venue"
},
  "geometry": {"coordinates":[-96.932783,32.577491],"type":"Point"}
}