{
  "type": "Feature",
  "properties": {
    "iso:country":"US",
    "sg:address":"614 Lanai Dr",
    "sg:city":"Bridgeport",
    "sg:classifiers":[
        {
            "category":"Manufacturing",
            "subcategory":"Signs",
            "type":"Manufacturing & Wholesale Goods"
        }
    ],
    "sg:phone":"+1 940 575 2554",
    "sg:postcode":"76426",
    "sg:province":"TX",
    "sg:tags":[
        "mfg",
        "s",
        "outdoor",
        "advertising",
        "specialty"
    ],
    "wof:name":"Bridgeport Sign Shop",
    "wof:placetype":"venue"
},
  "geometry": {"coordinates":[-97.876068,33.162342],"type":"Point"}
}