{
  "type": "Feature",
  "properties": {
    "iso:country":"US",
    "sg:address":"1816 Rolling Rdg Dr",
    "sg:city":"Grapevine",
    "sg:classifiers":[
        {
            "category":"Professional",
            "subcategory":"Engineering",
            "type":"Services"
        }
    ],
    "sg:phone":"+1 817 251 9691",
    "sg:postcode":"76051",
    "sg:province":"TX",
    "wof:name":"Aerospace Services Intl",
    "wof:placetype":"venue"
},
  "geometry": {"coordinates":[-97.094188,32.887392],"type":"Point"}
}