{
  "type": "Feature",
  "properties": {
    "iso:country":"US",
    "sg:address":"2204 Woodland Avenue",
    "sg:city":"Austin",
    "sg:classifiers":[
        {
            "category":"Food & Beverages",
            "subcategory":"Groceries & Convenience Stores",
            "type":"Retail Goods"
        }
    ],
    "sg:phone":"+1 512 447 5052",
    "sg:postcode":"78741",
    "sg:province":"TX",
    "sg:website":"www.shopnsave.com",
    "wof:name":"Shop N Save",
    "wof:placetype":"venue"
},
  "geometry": {"coordinates":[-97.727762,30.235508],"type":"Point"}
}