{
  "type": "Feature",
  "properties": {
    "iso:country":"US",
    "sg:address":"204 N Crockett St",
    "sg:city":"Sherman",
    "sg:classifiers":[
        {
            "category":"Shopping",
            "subcategory":"Jewelry",
            "type":"Retail Goods"
        }
    ],
    "sg:phone":"+1 903 892 8422",
    "sg:postcode":"75090",
    "sg:province":"TX",
    "sg:tags":[
        "repair",
        "watch"
    ],
    "wof:name":"Johnston Jewelry",
    "wof:placetype":"venue"
},
  "geometry": {"coordinates":[-96.611144,33.638258],"type":"Point"}
}