{
  "type": "Feature",
  "properties": {
    "iso:country":"US",
    "sg:address":"2417 Sir Lovel Ln",
    "sg:city":"Lewisville",
    "sg:classifiers":[
        {
            "category":"Social Services",
            "type":"Services"
        },
        {
            "category":"Professional",
            "subcategory":"Employment Agencies",
            "type":"Services"
        }
    ],
    "sg:phone":"+1 972 899 2349",
    "sg:postcode":"75056",
    "sg:province":"TX",
    "sg:tags":[
        "workers'",
        "placement",
        "volunteer"
    ],
    "wof:name":"His Chase Foundation Inc",
    "wof:placetype":"venue"
},
  "geometry": {"coordinates":[-96.911293,33.042599],"type":"Point"}
}