{
  "type": "Feature",
  "properties": {
    "iso:country":"US",
    "sg:address":"3217 E Pioneer Pkwy",
    "sg:city":"Arlington",
    "sg:classifiers":[
        {
            "category":"Retail",
            "subcategory":"Auto Repair",
            "type":"Services"
        }
    ],
    "sg:phone":"+1 817 652 3101",
    "sg:postcode":"76010",
    "sg:province":"TX",
    "sg:tags":[
        "body",
        "automobile",
        "painting"
    ],
    "wof:name":"Sun Rise Automotive Body Shop",
    "wof:placetype":"venue"
},
  "geometry": {"coordinates":[-97.049198,32.712244],"type":"Point"}
}