{
  "type": "Feature",
  "properties": {
    "iso:country":"US",
    "sg:address":"2231 S Ferrisburg Ct",
    "sg:city":"Sugar Land",
    "sg:phone":"+1 281 240 5081",
    "sg:postcode":"77478",
    "sg:province":"TX",
    "sg:tags":[
        "farm",
        "corn"
    ],
    "wof:name":"Betty A Blackwell",
    "wof:placetype":"venue"
},
  "geometry": {"coordinates":[-95.60937699999999,29.656],"type":"Point"}
}