{
  "type": "Feature",
  "properties": {
    "iso:country":"US",
    "sg:address":"1701 Falmouth Dr",
    "sg:city":"Plano",
    "sg:classifiers":[
        {
            "category":"Building & Trades",
            "subcategory":"Construction",
            "type":"Services"
        }
    ],
    "sg:phone":"+1 469 241 9188",
    "sg:postcode":"75025",
    "sg:province":"TX",
    "sg:tags":[
        "roofing",
        "contractor"
    ],
    "wof:name":"Commercial Roofing",
    "wof:placetype":"venue"
},
  "geometry": {"coordinates":[-96.725053,33.07295],"type":"Point"}
}