{
  "type": "Feature",
  "properties": {
    "iso:country":"US",
    "sg:address":"4811 Saratoga Blvd",
    "sg:city":"Corpus Christi",
    "sg:classifiers":[
        {
            "category":"Insurance",
            "subcategory":"Insurance Agent",
            "type":"Services"
        }
    ],
    "sg:phone":"+1 361 993 4530",
    "sg:postcode":"78413",
    "sg:province":"TX",
    "wof:name":"Susan York Hierholzer",
    "wof:placetype":"venue"
},
  "geometry": {"coordinates":[-97.395235,27.691179],"type":"Point"}
}