{
  "type": "Feature",
  "properties": {
    "iso:country":"US",
    "sg:address":"2611 FM 1960 W",
    "sg:city":"Houston",
    "sg:classifiers":[
        {
            "category":"Sports & Exercise",
            "subcategory":"Golf",
            "type":"Entertainment"
        }
    ],
    "sg:phone":"+1 281 580 2085",
    "sg:postcode":"77068",
    "sg:province":"TX",
    "sg:tags":[
        "course",
        "public"
    ],
    "wof:name":"Replica Golf Interests LLC",
    "wof:placetype":"venue"
},
  "geometry": {"coordinates":[-95.46396900000001,30.007014],"type":"Point"}
}