{
  "type": "Feature",
  "properties": {
    "iso:country":"US",
    "sg:address":"8203 Woodcreek Dr",
    "sg:city":"Waco",
    "sg:classifiers":[
        {
            "category":"Professional",
            "subcategory":"Accounting & Tax Preparation",
            "type":"Services"
        }
    ],
    "sg:phone":"+1 254 741 9461",
    "sg:postcode":"76712",
    "sg:province":"TX",
    "sg:tags":[
        "bookkeeping",
        "general"
    ],
    "wof:name":"Padgett Business Svc",
    "wof:placetype":"venue"
},
  "geometry": {"coordinates":[-97.217488,31.508942],"type":"Point"}
}