{
  "type": "Feature",
  "properties": {
    "iso:country":"US",
    "sg:address":"1371 Lakeview Dr",
    "sg:city":"Southlake",
    "sg:classifiers":[
        {
            "category":"Professional",
            "subcategory":"Management & Consulting",
            "type":"Services"
        }
    ],
    "sg:phone":"+1 817 329 8934",
    "sg:postcode":"76092",
    "sg:province":"TX",
    "wof:name":"SL Carder",
    "wof:placetype":"venue"
},
  "geometry": {"coordinates":[-97.18056900000001,32.953254],"type":"Point"}
}