{
  "type": "Feature",
  "properties": {
    "iso:country":"US",
    "sg:address":"4001 Old Denton Rd",
    "sg:city":"Haltom City",
    "sg:classifiers":[
        {
            "category":"Utilities",
            "subcategory":"Refuse",
            "type":"Services"
        }
    ],
    "sg:phone":"+1 817 222 2221",
    "sg:postcode":"76117",
    "sg:province":"TX",
    "sg:tags":[
        "garbage",
        "collection"
    ],
    "sg:website":"www.isi.com",
    "wof:name":"IESI",
    "wof:placetype":"venue"
},
  "geometry": {"coordinates":[-97.284525,32.821434],"type":"Point"}
}