{
  "type": "Feature",
  "properties": {
    "iso:country":"US",
    "sg:address":"231 Loop 820",
    "sg:city":"Fort Worth",
    "sg:classifiers":[
        {
            "category":"Real Estate",
            "subcategory":"Architect",
            "type":"Services"
        }
    ],
    "sg:phone":"+1 817 590 2772",
    "sg:postcode":"76112",
    "sg:province":"TX",
    "sg:tags":[
        "architectural"
    ],
    "wof:name":"Lane & Associates",
    "wof:placetype":"venue"
},
  "geometry": {"coordinates":[-97.213038,32.775337],"type":"Point"}
}