{
  "type": "Feature",
  "properties": {
    "iso:country":"US",
    "sg:address":"3511 E 12th Ave",
    "sg:city":"Amarillo",
    "sg:classifiers":[
        {
            "category":"Wholesale",
            "subcategory":"Vending Machines",
            "type":"Manufacturing & Wholesale Goods"
        }
    ],
    "sg:phone":"+1 806 373 3131",
    "sg:postcode":"79104",
    "sg:province":"TX",
    "wof:name":"Jim Culwell",
    "wof:placetype":"venue"
},
  "geometry": {"coordinates":[-101.795559,35.198264],"type":"Point"}
}