{
  "type": "Feature",
  "properties": {
    "iso:country":"US",
    "sg:address":"1208 Tator Brown Rd",
    "sg:city":"Red Oak",
    "sg:classifiers":[
        {
            "category":"Building & Trades",
            "subcategory":"Construction",
            "type":"Services"
        }
    ],
    "sg:phone":"+1 972 617 3703",
    "sg:postcode":"75154",
    "sg:province":"TX",
    "sg:tags":[
        "carpentry",
        "contractor"
    ],
    "wof:name":"Vince Garza Inc",
    "wof:placetype":"venue"
},
  "geometry": {"coordinates":[-96.819374,32.546267],"type":"Point"}
}