{
  "type": "Feature",
  "properties": {
    "iso:country":"US",
    "sg:address":"5818 S Staples St",
    "sg:city":"Corpus Christi",
    "sg:classifiers":[
        {
            "category":"Education",
            "subcategory":"Special Training",
            "type":"Public Place"
        }
    ],
    "sg:phone":"+1 361 993 3793",
    "sg:postcode":"78413",
    "sg:province":"TX",
    "wof:name":"Sylvan Learning Centers",
    "wof:placetype":"venue"
},
  "geometry": {"coordinates":[-97.376938,27.696462],"type":"Point"}
}