{
  "type": "Feature",
  "properties": {
    "iso:country":"US",
    "sg:address":"5525 N Stanton St",
    "sg:city":"El Paso",
    "sg:classifiers":[
        {
            "category":"Professional",
            "subcategory":"Accounting & Tax Preparation",
            "type":"Services"
        }
    ],
    "sg:phone":"+1 915 581 0099",
    "sg:postcode":"79912",
    "sg:province":"TX",
    "sg:tags":[
        "auditing",
        "bookkeeping"
    ],
    "wof:name":"Samuel Creighton",
    "wof:placetype":"venue"
},
  "geometry": {"coordinates":[-106.506861,31.824454],"type":"Point"}
}