{
  "type": "Feature",
  "properties": {
    "iso:country":"US",
    "sg:address":"2601 W Wall St",
    "sg:city":"Midland",
    "sg:classifiers":[
        {
            "category":"Autos & Motor Vehicles",
            "subcategory":"Automobile Sales",
            "type":"Retail Goods"
        }
    ],
    "sg:phone":"+1 432 683 6222",
    "sg:postcode":"79701",
    "sg:province":"TX",
    "sg:tags":[
        "car",
        "dealer"
    ],
    "wof:name":"B & B Auto Sales",
    "wof:placetype":"venue"
},
  "geometry": {"coordinates":[-102.10314099999999,31.989227],"type":"Point"}
}