{
  "type": "Feature",
  "properties": {
    "iso:country":"US",
    "sg:address":"1702 Lamar Ave",
    "sg:city":"Paris",
    "sg:classifiers":[
        {
            "category":"Banks & Credit Unions",
            "subcategory":"Bank",
            "type":"Services"
        }
    ],
    "sg:phone":"+1 903 737 0777",
    "sg:postcode":"75460",
    "sg:province":"TX",
    "sg:tags":[
        "cashing",
        "check"
    ],
    "wof:name":"ACE Cash Express",
    "wof:placetype":"venue"
},
  "geometry": {"coordinates":[-95.538922,33.6612],"type":"Point"}
}