{
  "type": "Feature",
  "properties": {
    "iso:country":"US",
    "sg:address":"3921 Fairwood Ct",
    "sg:city":"Midland",
    "sg:classifiers":[
        {
            "category":"Professional",
            "subcategory":"Business Services",
            "type":"Services"
        }
    ],
    "sg:phone":"+1 432 699 0375",
    "sg:postcode":"79707",
    "sg:province":"TX",
    "wof:name":"Ann Wall Enterprises",
    "wof:placetype":"venue"
},
  "geometry": {"coordinates":[-102.143463,32.048285],"type":"Point"}
}