{
  "type": "Feature",
  "properties": {
    "iso:country":"US",
    "sg:address":"124 W 8th St",
    "sg:city":"Austin",
    "sg:classifiers":[
        {
            "category":"Real Estate",
            "subcategory":"Real Estate Services",
            "type":"Services"
        },
        {
            "category":"Building & Trades",
            "subcategory":"Cleaning & Sanitation",
            "type":"Services"
        }
    ],
    "sg:phone":"+1 512 480 8141",
    "sg:postcode":"78701",
    "sg:province":"TX",
    "sg:tags":[
        "janitorial",
        "maintenance",
        "cleaners-interior"
    ],
    "wof:name":"Coa Building Svc",
    "wof:placetype":"venue"
},
  "geometry": {"coordinates":[-97.742434,30.270009],"type":"Point"}
}