{
  "type": "Feature",
  "properties": {
    "iso:country":"US",
    "sg:address":"5219 North Fwy",
    "sg:city":"Houston",
    "sg:classifiers":[
        {
            "category":"Autos & Motor Vehicles",
            "subcategory":"Automobile Sales",
            "type":"Retail Goods"
        }
    ],
    "sg:phone":"+1 713 692 8700",
    "sg:postcode":"77022",
    "sg:province":"TX",
    "sg:tags":[
        "car",
        "used",
        "dealer"
    ],
    "wof:name":"Tex Star Motors",
    "wof:placetype":"venue"
},
  "geometry": {"coordinates":[-95.391668,29.843092],"type":"Point"}
}