{
  "type": "Feature",
  "properties": {
    "iso:country":"US",
    "sg:address":"1885 Sawmill Dr",
    "sg:city":"Allen",
    "sg:classifiers":[
        {
            "category":"Professional",
            "subcategory":"Engineering",
            "type":"Services"
        }
    ],
    "sg:phone":"+1 214 495 3965",
    "sg:postcode":"75002",
    "sg:province":"TX",
    "sg:tags":[
        "engineer"
    ],
    "wof:name":"Metavisix Engineering",
    "wof:placetype":"venue"
},
  "geometry": {"coordinates":[-96.588122,33.111752],"type":"Point"}
}