{
  "type": "Feature",
  "properties": {
    "iso:country":"US",
    "sg:address":"129 Cedar Springs Blvd",
    "sg:city":"Sulphur Springs",
    "sg:classifiers":[
        {
            "category":"Manufacturing",
            "subcategory":"Chemicals & Compounds",
            "type":"Manufacturing & Wholesale Goods"
        }
    ],
    "sg:phone":"+1 903 885 4635",
    "sg:postcode":"75482",
    "sg:province":"TX",
    "sg:tags":[
        "preparation",
        "toilet",
        "mfg"
    ],
    "wof:name":"Mary Kay Inc",
    "wof:placetype":"venue"
},
  "geometry": {"coordinates":[-95.594583,33.112008],"type":"Point"}
}