{
  "type": "Feature",
  "properties": {
    "iso:country":"US",
    "sg:address":"6914 Webster St",
    "sg:city":"Dallas",
    "sg:classifiers":[
        {
            "category":"Personal",
            "subcategory":"Beauty Salon",
            "type":"Services"
        }
    ],
    "sg:phone":"+1 214 904 0649",
    "sg:postcode":"75209",
    "sg:province":"TX",
    "wof:name":"Sally Morgan",
    "wof:placetype":"venue"
},
  "geometry": {"coordinates":[-96.833152,32.841918],"type":"Point"}
}