{
  "type": "Feature",
  "properties": {
    "iso:country":"US",
    "sg:address":"4672 FM 68",
    "sg:city":"Gober",
    "sg:classifiers":[
        {
            "category":"Government",
            "subcategory":"Post Office",
            "type":"Public Place"
        }
    ],
    "sg:phone":"+1 903 583 5604",
    "sg:postcode":"75496",
    "sg:province":"TX",
    "wof:name":"US Post Office",
    "wof:placetype":"venue"
},
  "geometry": {"coordinates":[-96.09369700000001,33.468747],"type":"Point"}
}