{
  "type": "Feature",
  "properties": {
    "iso:country":"US",
    "sg:address":"9314 Cross Mountain Trl",
    "sg:city":"San Antonio",
    "sg:classifiers":[
        {
            "category":"Professional",
            "subcategory":"Management & Consulting",
            "type":"Services"
        }
    ],
    "sg:phone":"+1 210 698 1994",
    "sg:postcode":"78255",
    "sg:province":"TX",
    "sg:tags":[
        "business"
    ],
    "wof:name":"BAS Promotions Inc",
    "wof:placetype":"venue"
},
  "geometry": {"coordinates":[-98.672071,29.66085],"type":"Point"}
}