{
  "type": "Feature",
  "properties": {
    "iso:country":"US",
    "sg:address":"12476 Bellaire Blvd",
    "sg:city":"Houston",
    "sg:classifiers":[
        {
            "category":"Shopping",
            "subcategory":"Clothing, Apparel, & Fashions",
            "type":"Retail Goods"
        }
    ],
    "sg:phone":"+1 281 495 9589",
    "sg:postcode":"77072",
    "sg:province":"TX",
    "wof:name":"Karlas Formal Wear Etc",
    "wof:placetype":"venue"
},
  "geometry": {"coordinates":[-95.601356,29.703605],"type":"Point"}
}