{
  "type": "Feature",
  "properties": {
    "iso:country":"US",
    "sg:address":"5309 Wharton St",
    "sg:city":"Corpus Christi",
    "sg:classifiers":[
        {
            "category":"Arts & Performance",
            "subcategory":"Theater",
            "type":"Entertainment"
        }
    ],
    "sg:phone":"+1 361 992 3803",
    "sg:postcode":"78415",
    "sg:province":"TX",
    "sg:tags":[
        "live",
        "music"
    ],
    "wof:name":"Tony Gee's Mobile Djs",
    "wof:placetype":"venue"
},
  "geometry": {"coordinates":[-97.42101599999999,27.726517],"type":"Point"}
}