{
  "type": "Feature",
  "properties": {
    "iso:country":"US",
    "sg:address":"408 W Belt Line Rd",
    "sg:city":"Desoto",
    "sg:classifiers":[
        {
            "category":"Shopping",
            "subcategory":"Florist",
            "type":"Retail Goods"
        }
    ],
    "sg:phone":"+1 972 291 9331",
    "sg:postcode":"75115",
    "sg:province":"TX",
    "wof:name":"Designing Woman Florist",
    "wof:placetype":"venue"
},
  "geometry": {"coordinates":[-96.864277,32.589667],"type":"Point"}
}