{
  "type": "Feature",
  "properties": {
    "iso:country":"US",
    "sg:address":"4314 Hwy 365",
    "sg:city":"Port Arthur",
    "sg:classifiers":[
        {
            "category":"Food & Beverages",
            "subcategory":"Groceries & Convenience Stores",
            "type":"Retail Goods"
        }
    ],
    "sg:phone":"+1 409 726 8166",
    "sg:postcode":"77642",
    "sg:province":"TX",
    "wof:name":"Handi-Spot",
    "wof:placetype":"venue"
},
  "geometry": {"coordinates":[-93.980327,29.961167],"type":"Point"}
}