{
  "type": "Feature",
  "properties": {
    "iso:country":"US",
    "sg:address":"5128 Cedar Springs Rd",
    "sg:city":"Dallas",
    "sg:classifiers":[
        {
            "category":"Building & Trades",
            "subcategory":"Plumbing",
            "type":"Services"
        }
    ],
    "sg:phone":"+1 214 559 4990",
    "sg:postcode":"75235",
    "sg:province":"TX",
    "sg:tags":[
        "plumber",
        "industrial",
        "contractors-commercial"
    ],
    "wof:name":"Ernies Plumbing Service",
    "wof:placetype":"venue"
},
  "geometry": {"coordinates":[-96.824404,32.821373],"type":"Point"}
}