{
  "type": "Feature",
  "properties": {
    "iso:country":"US",
    "sg:address":"6125 E Houston Rd",
    "sg:city":"Houston",
    "sg:classifiers":[
        {
            "category":"Manufacturing",
            "subcategory":"Metals",
            "type":"Manufacturing & Wholesale Goods"
        },
        {
            "category":"Building & Trades",
            "subcategory":"Construction",
            "type":"Services"
        }
    ],
    "sg:phone":"+1 713 672 6694",
    "sg:postcode":"77028",
    "sg:province":"TX",
    "sg:tags":[
        "installation",
        "fence",
        "contractor"
    ],
    "wof:name":"Colonial Fence Co Inc",
    "wof:placetype":"venue"
},
  "geometry": {"coordinates":[-95.269983,29.822038],"type":"Point"}
}