{
  "type": "Feature",
  "properties": {
    "iso:country":"US",
    "sg:address":"2462 Co Rd 551",
    "sg:city":"Farmersville",
    "sg:classifiers":[
        {
            "category":"Farming",
            "subcategory":"Livestock Farm",
            "type":"Manufacturing & Wholesale Goods"
        }
    ],
    "sg:phone":"+1 972 784 2008",
    "sg:postcode":"75442",
    "sg:province":"TX",
    "sg:tags":[
        "specialty",
        "animal"
    ],
    "wof:name":"Lake Country Farms Inc",
    "wof:placetype":"venue"
},
  "geometry": {"coordinates":[-96.41992500000001,33.130305],"type":"Point"}
}