{
  "type": "Feature",
  "properties": {
    "iso:country":"US",
    "sg:address":"2900 Knight Ct",
    "sg:city":"Southlake",
    "sg:phone":"+1 817 431 6664",
    "sg:postcode":"76092",
    "sg:province":"TX",
    "sg:tags":[
        "oil"
    ],
    "wof:name":"Amsoil Dealer",
    "wof:placetype":"venue"
},
  "geometry": {"coordinates":[-97.197563,32.94449],"type":"Point"}
}