{
  "type": "Feature",
  "properties": {
    "iso:country":"US",
    "sg:address":"516 Conrad Hilton Blvd",
    "sg:city":"Cisco",
    "sg:classifiers":[
        {
            "category":"Shopping",
            "subcategory":"Jewelry",
            "type":"Retail Goods"
        }
    ],
    "sg:phone":"+1 254 442 2752",
    "sg:postcode":"76437",
    "sg:province":"TX",
    "sg:tags":[
        "repair",
        "watch"
    ],
    "wof:name":"Andersons Jewelry and Music",
    "wof:placetype":"venue"
},
  "geometry": {"coordinates":[-98.980897,32.390362],"type":"Point"}
}