{
  "type": "Feature",
  "properties": {
    "iso:country":"US",
    "sg:address":"2406 Commercial Ave",
    "sg:city":"San Antonio",
    "sg:classifiers":[
        {
            "category":"Health Services",
            "subcategory":"Doctor",
            "type":"Services"
        }
    ],
    "sg:phone":"+1 210 922 0621",
    "sg:postcode":"78221",
    "sg:province":"TX",
    "sg:tags":[
        "medical"
    ],
    "wof:name":"South Side Ortho Rehav Assoc",
    "wof:placetype":"venue"
},
  "geometry": {"coordinates":[-98.516169,29.352671],"type":"Point"}
}