{
  "type": "Feature",
  "properties": {
    "iso:country":"US",
    "sg:address":"13007 Jones Maltsberger Rd",
    "sg:city":"San Antonio",
    "sg:classifiers":[
        {
            "category":"Organizations",
            "subcategory":"Religious Organization",
            "type":"Services"
        }
    ],
    "sg:phone":"+1 210 490 7729",
    "sg:postcode":"78247",
    "sg:province":"TX",
    "sg:tags":[
        "church"
    ],
    "wof:name":"Thousand Oaks Christian Church",
    "wof:placetype":"venue"
},
  "geometry": {"coordinates":[-98.45994899999999,29.560669],"type":"Point"}
}