{
  "type": "Feature",
  "properties": {
    "iso:country":"US",
    "sg:address":"233 Athenian Dr",
    "sg:city":"Universal City",
    "sg:classifiers":[
        {
            "category":"Personal",
            "subcategory":"Beauty Salon",
            "type":"Services"
        }
    ],
    "sg:phone":"+1 210 658 5211",
    "sg:postcode":"78148",
    "sg:province":"TX",
    "wof:name":"Ace-Vidal Beauty Shop",
    "wof:placetype":"venue"
},
  "geometry": {"coordinates":[-98.324866,29.561743],"type":"Point"}
}