{
  "type": "Feature",
  "properties": {
    "iso:country":"US",
    "sg:address":"2923 Magnolia Hill Ct",
    "sg:city":"Dallas",
    "sg:classifiers":[
        {
            "category":"Utilities",
            "subcategory":"Electric",
            "type":"Services"
        }
    ],
    "sg:phone":"+1 214 742 1545",
    "sg:postcode":"75201",
    "sg:province":"TX",
    "sg:tags":[
        "development",
        "power",
        "facility",
        "generation",
        "water",
        "sewage"
    ],
    "wof:name":"Middle East Trading Company",
    "wof:placetype":"venue"
},
  "geometry": {"coordinates":[-96.810074,32.792777],"type":"Point"}
}