{
  "type": "Feature",
  "properties": {
    "iso:country":"US",
    "sg:address":"5700 Choctaw Dr",
    "sg:city":"Granbury",
    "sg:classifiers":[
        {
            "category":"Mining & Drilling",
            "type":"Manufacturing & Wholesale Goods"
        }
    ],
    "sg:phone":"+1 817 326 1491",
    "sg:postcode":"76049",
    "sg:province":"TX",
    "sg:tags":[
        "well"
    ],
    "wof:name":"Granbury Exploration & Dev LLC",
    "wof:placetype":"venue"
},
  "geometry": {"coordinates":[-97.687865,32.428463],"type":"Point"}
}