{
  "type": "Feature",
  "properties": {
    "iso:country":"US",
    "sg:address":"908 S 21st Ave",
    "sg:city":"Edinburg",
    "sg:classifiers":[
        {
            "category":"Shopping",
            "subcategory":"Computers & Home Electronics",
            "type":"Retail Goods"
        }
    ],
    "sg:phone":"+1 956 287 7499",
    "sg:postcode":"78539",
    "sg:province":"TX",
    "wof:name":"Rays Satellites",
    "wof:placetype":"venue"
},
  "geometry": {"coordinates":[-98.152373,26.291771],"type":"Point"}
}