{
  "type": "Feature",
  "properties": {
    "iso:country":"US",
    "sg:address":"1400 Meadowlark Ln",
    "sg:city":"Lancaster",
    "sg:classifiers":[
        {
            "category":"Home & Garden",
            "subcategory":"Hardware",
            "type":"Retail Goods"
        }
    ],
    "sg:phone":"+1 972 223 5533",
    "sg:postcode":"75146",
    "sg:province":"TX",
    "sg:website":"www.swivleze.com",
    "wof:name":"Swivl-Eze Marine Hardware",
    "wof:placetype":"venue"
},
  "geometry": {"coordinates":[-96.81972500000001,32.566348],"type":"Point"}
}