{
  "type": "Feature",
  "properties": {
    "iso:country":"US",
    "sg:address":"22564 Community Dr",
    "sg:city":"New Caney",
    "sg:classifiers":[
        {
            "category":"Organizations",
            "subcategory":"Non-profit Organization",
            "type":"Services"
        }
    ],
    "sg:phone":"+1 281 354 7667",
    "sg:postcode":"77357",
    "sg:province":"TX",
    "wof:name":"New Horizons Inc",
    "wof:placetype":"venue"
},
  "geometry": {"coordinates":[-95.226986,30.128936],"type":"Point"}
}