{
  "type": "Feature",
  "properties": {
    "iso:country":"US",
    "sg:address":"2 S Koenigheim St",
    "sg:city":"San Angelo",
    "sg:classifiers":[
        {
            "category":"Professional",
            "subcategory":"Lawyer & Legal Services",
            "type":"Services"
        }
    ],
    "sg:phone":"+1 325 653 3291",
    "sg:postcode":"76903",
    "sg:province":"TX",
    "sg:tags":[
        "attorney"
    ],
    "wof:name":"Gossett Harrison",
    "wof:placetype":"venue"
},
  "geometry": {"coordinates":[-100.442154,31.460865],"type":"Point"}
}