{
  "type": "Feature",
  "properties": {
    "iso:country":"US",
    "sg:address":"2901 Galleria Dr",
    "sg:city":"Arlington",
    "sg:classifiers":[
        {
            "category":"Manufacturing",
            "subcategory":"Tools & Machinery",
            "type":"Manufacturing & Wholesale Goods"
        }
    ],
    "sg:phone":"+1 817 649 1986",
    "sg:postcode":"76011",
    "sg:province":"TX",
    "sg:tags":[
        "equipment",
        "peripheral",
        "computer",
        "mfg"
    ],
    "wof:name":"Reycomp Inc",
    "wof:placetype":"venue"
},
  "geometry": {"coordinates":[-97.057029,32.746458],"type":"Point"}
}