{
  "type": "Feature",
  "properties": {
    "iso:country":"US",
    "sg:address":"5013 Copperbend Blvd",
    "sg:city":"Austin",
    "sg:classifiers":[
        {
            "category":"Building & Trades",
            "subcategory":"Construction",
            "type":"Services"
        }
    ],
    "sg:phone":"+1 512 350 9264",
    "sg:postcode":"78744",
    "sg:province":"TX",
    "sg:tags":[
        "concrete",
        "contractor"
    ],
    "wof:name":"E-Con Contractors",
    "wof:placetype":"venue"
},
  "geometry": {"coordinates":[-97.74104800000001,30.19557],"type":"Point"}
}