{
  "type": "Feature",
  "properties": {
    "iso:country":"US",
    "sg:address":"10921 Foy Ln",
    "sg:city":"Houston",
    "sg:classifiers":[
        {
            "category":"Organizations",
            "subcategory":"Religious Organization",
            "type":"Services"
        }
    ],
    "sg:phone":"+1 713 697 3515",
    "sg:postcode":"77093",
    "sg:province":"TX",
    "wof:name":"New Beginning Baptist Fellowship",
    "wof:placetype":"venue"
},
  "geometry": {"coordinates":[-95.339607,29.874431],"type":"Point"}
}