{
  "type": "Feature",
  "properties": {
    "iso:country":"US",
    "sg:address":"2312 Claridge Cir",
    "sg:city":"Plano",
    "sg:classifiers":[
        {
            "category":"Professional",
            "subcategory":"Art Services",
            "type":"Services"
        }
    ],
    "sg:phone":"+1 972 867 0999",
    "sg:postcode":"75075",
    "sg:province":"TX",
    "sg:tags":[
        "graphic",
        "designer"
    ],
    "wof:name":"Cutting Edge Graphics & Design",
    "wof:placetype":"venue"
},
  "geometry": {"coordinates":[-96.73693900000001,33.02094],"type":"Point"}
}