{
  "type": "Feature",
  "properties": {
    "iso:country":"US",
    "sg:address":"101 Lee St",
    "sg:city":"Wichita Falls",
    "sg:classifiers":[
        {
            "category":"Building & Trades",
            "subcategory":"Cleaning & Sanitation",
            "type":"Services"
        }
    ],
    "sg:phone":"+1 940 322 4120",
    "sg:postcode":"76301",
    "sg:province":"TX",
    "sg:tags":[
        "maintenance"
    ],
    "wof:name":"Tl Housekeeping Service",
    "wof:placetype":"venue"
},
  "geometry": {"coordinates":[-98.492268,33.920389],"type":"Point"}
}