{
  "type": "Feature",
  "properties": {
    "iso:country":"US",
    "sg:address":"6603 Beauford Dr",
    "sg:city":"Austin",
    "sg:classifiers":[
        {
            "category":"Government",
            "subcategory":"Police Station",
            "type":"Public Place"
        }
    ],
    "sg:phone":"+1 512 346 7334",
    "sg:postcode":"78750",
    "sg:province":"TX",
    "sg:tags":[
        "department"
    ],
    "wof:name":"Tx Board Of Pardons And Paroles",
    "wof:placetype":"venue"
},
  "geometry": {"coordinates":[-97.79091,30.376912],"type":"Point"}
}