{
  "type": "Feature",
  "properties": {
    "iso:country":"US",
    "sg:address":"4110 Felter Ln",
    "sg:city":"Austin",
    "sg:classifiers":[
        {
            "category":"Retail",
            "subcategory":"Auto Repair",
            "type":"Services"
        }
    ],
    "sg:phone":"+1 512 385 0509",
    "sg:postcode":"78744",
    "sg:province":"TX",
    "sg:tags":[
        "body",
        "shop"
    ],
    "wof:name":"Austins Collision & Body Works",
    "wof:placetype":"venue"
},
  "geometry": {"coordinates":[-97.70549800000001,30.196899],"type":"Point"}
}