{
  "type": "Feature",
  "properties": {
    "iso:country":"US",
    "sg:address":"17934 Loring Ln",
    "sg:city":"Spring",
    "sg:classifiers":[
        {
            "category":"Travel",
            "subcategory":"Travel Agent",
            "type":"Entertainment"
        }
    ],
    "sg:phone":"+1 281 288 0901",
    "sg:postcode":"77388",
    "sg:province":"TX",
    "sg:tags":[
        "agency"
    ],
    "wof:name":"Web Pro Travel Agency",
    "wof:placetype":"venue"
},
  "geometry": {"coordinates":[-95.476705,30.035262],"type":"Point"}
}