{
  "type": "Feature",
  "properties": {
    "iso:country":"US",
    "sg:address":"8224 Teakwood Dr",
    "sg:city":"Waco",
    "sg:classifiers":[
        {
            "category":"Health Services",
            "subcategory":"Doctor",
            "type":"Services"
        }
    ],
    "sg:phone":"+1 254 772 9293",
    "sg:postcode":"76712",
    "sg:province":"TX",
    "sg:tags":[
        "medical"
    ],
    "wof:name":"Mark Norwid MD",
    "wof:placetype":"venue"
},
  "geometry": {"coordinates":[-97.22604699999999,31.516437],"type":"Point"}
}