{
  "type": "Feature",
  "properties": {
    "iso:country":"US",
    "sg:address":"9013 Kingswood Pl",
    "sg:city":"Waco",
    "sg:classifiers":[
        {
            "category":"Wholesale",
            "subcategory":"Electrical",
            "type":"Manufacturing & Wholesale Goods"
        },
        {
            "category":"Manufacturing",
            "subcategory":"Tools & Machinery",
            "type":"Manufacturing & Wholesale Goods"
        }
    ],
    "sg:phone":"+1 254 776 9234",
    "sg:postcode":"76712",
    "sg:province":"TX",
    "sg:tags":[
        "control",
        "devices",
        "mfg"
    ],
    "wof:name":"Power Control Systems Eng Inc",
    "wof:placetype":"venue"
},
  "geometry": {"coordinates":[-97.234549,31.51258],"type":"Point"}
}