{
  "type": "Feature",
  "properties": {
    "iso:country":"US",
    "sg:address":"9634 Audelia Rd",
    "sg:city":"Dallas",
    "sg:classifiers":[
        {
            "category":"Banks & Credit Unions",
            "subcategory":"Bank",
            "type":"Services"
        }
    ],
    "sg:phone":"+1 214 340 1236",
    "sg:postcode":"75238",
    "sg:province":"TX",
    "sg:website":"www.chase.com",
    "wof:name":"Chase",
    "wof:placetype":"venue"
},
  "geometry": {"coordinates":[-96.717651,32.877277],"type":"Point"}
}