{
  "type": "Feature",
  "properties": {
    "iso:country":"US",
    "sg:address":"524 Centre St",
    "sg:city":"San Marcos",
    "sg:classifiers":[
        {
            "category":"Organizations",
            "subcategory":"Religious Organization",
            "type":"Services"
        }
    ],
    "sg:phone":"+1 512 392 6525",
    "sg:postcode":"78666",
    "sg:province":"TX",
    "sg:tags":[
        "church"
    ],
    "wof:name":"Jackson Chapel Umc",
    "wof:placetype":"venue"
},
  "geometry": {"coordinates":[-97.943673,29.878771],"type":"Point"}
}