{
  "type": "Feature",
  "properties": {
    "iso:country":"US",
    "sg:address":"311 E California St",
    "sg:city":"Gainesville",
    "sg:classifiers":[
        {
            "category":"Shopping",
            "subcategory":"Optical Goods",
            "type":"Retail Goods"
        },
        {
            "category":"Health Services",
            "subcategory":"Optometrist",
            "type":"Services"
        }
    ],
    "sg:phone":"+1 940 668 7254",
    "sg:postcode":"76240",
    "sg:province":"TX",
    "sg:tags":[
        "optician",
        "dispensing"
    ],
    "wof:name":"Texas State Optical",
    "wof:placetype":"venue"
},
  "geometry": {"coordinates":[-97.14354299999999,33.624368],"type":"Point"}
}