{
  "type": "Feature",
  "properties": {
    "iso:country":"US",
    "sg:address":"8552 Katy Fwy",
    "sg:city":"Houston",
    "sg:classifiers":[
        {
            "category":"Social Services",
            "type":"Services"
        }
    ],
    "sg:phone":"+1 713 681 6900",
    "sg:postcode":"77024",
    "sg:province":"TX",
    "sg:tags":[
        "individual",
        "family"
    ],
    "wof:name":"Spauding For Children",
    "wof:placetype":"venue"
},
  "geometry": {"coordinates":[-95.49335600000001,29.784277],"type":"Point"}
}