{
  "type": "Feature",
  "properties": {
    "iso:country":"US",
    "sg:address":"306 Hawthorne St",
    "sg:city":"Houston",
    "sg:classifiers":[
        {
            "category":"Communications",
            "subcategory":"Film & Video Production",
            "type":"Services"
        }
    ],
    "sg:phone":"+1 713 526 6543",
    "sg:postcode":"77006",
    "sg:province":"TX",
    "sg:tags":[
        "web",
        "e",
        "commerce",
        "solution",
        "custom",
        "design",
        "provider"
    ],
    "wof:name":"Around Houston Web Design",
    "wof:placetype":"venue"
},
  "geometry": {"coordinates":[-95.382656,29.74244],"type":"Point"}
}