{
  "type": "Feature",
  "properties": {
    "iso:country":"US",
    "sg:address":"29 Cherokee Trl",
    "sg:city":"Henderson",
    "sg:classifiers":[
        {
            "category":"Banks & Credit Unions",
            "subcategory":"Financial Services",
            "type":"Services"
        }
    ],
    "sg:phone":"+1 903 836 6578",
    "sg:postcode":"75652",
    "sg:province":"TX",
    "sg:tags":[
        "investment",
        "closed"
    ],
    "wof:name":"Roseyville Investments",
    "wof:placetype":"venue"
},
  "geometry": {"coordinates":[-94.669462,32.362165],"type":"Point"}
}