{
  "type": "Feature",
  "properties": {
    "iso:country":"US",
    "sg:address":"2840 Woodhollow Ct",
    "sg:city":"Lewisville",
    "sg:classifiers":[
        {
            "category":"Professional",
            "subcategory":"Business Services",
            "type":"Services"
        }
    ],
    "sg:phone":"+1 972 317 2731",
    "sg:postcode":"75077",
    "sg:province":"TX",
    "wof:name":"Celebration Management LLC",
    "wof:placetype":"venue"
},
  "geometry": {"coordinates":[-97.06834499999999,33.089649],"type":"Point"}
}