{
  "type": "Feature",
  "properties": {
    "iso:country":"US",
    "sg:address":"2203 W Park Row Dr",
    "sg:city":"Arlington",
    "sg:classifiers":[
        {
            "category":"Organizations",
            "subcategory":"Religious Organization",
            "type":"Services"
        }
    ],
    "sg:phone":"+1 817 275 5959",
    "sg:postcode":"76013",
    "sg:province":"TX",
    "sg:tags":[
        "church"
    ],
    "sg:website":"www.woodlandwestbc.org",
    "wof:name":"Woodland West Baptist Church",
    "wof:placetype":"venue"
},
  "geometry": {"coordinates":[-97.142584,32.721355],"type":"Point"}
}