{
  "type": "Feature",
  "properties": {
    "iso:country":"US",
    "sg:address":"6201 Bordeaux Ave",
    "sg:city":"Dallas",
    "sg:classifiers":[
        {
            "category":"Shopping",
            "subcategory":"Clothing, Apparel, & Fashions",
            "type":"Retail Goods"
        }
    ],
    "sg:phone":"+1 214 366 2880",
    "sg:postcode":"75209",
    "sg:province":"TX",
    "wof:name":"Designer Gypsy James Cost",
    "wof:placetype":"venue"
},
  "geometry": {"coordinates":[-96.82403600000001,32.833743],"type":"Point"}
}