{
  "type": "Feature",
  "properties": {
    "iso:country":"US",
    "sg:address":"14202 Blue Falls Dr",
    "sg:city":"Sugar Land",
    "sg:classifiers":[
        {
            "category":"Professional",
            "subcategory":"Business Services",
            "type":"Services"
        }
    ],
    "sg:phone":"+1 281 491 2403",
    "sg:postcode":"77478",
    "sg:province":"TX",
    "wof:name":"Byrd Crest Power Solutions",
    "wof:placetype":"venue"
},
  "geometry": {"coordinates":[-95.637086,29.66016],"type":"Point"}
}