{
  "type": "Feature",
  "properties": {
    "iso:country":"US",
    "sg:address":"1411 Norwalk Ln",
    "sg:city":"Austin",
    "sg:classifiers":[
        {
            "category":"Banks & Credit Unions",
            "subcategory":"Bank",
            "type":"Services"
        }
    ],
    "sg:phone":"+1 512 481 8492",
    "sg:postcode":"78703",
    "sg:province":"TX",
    "sg:tags":[
        "mortgage"
    ],
    "wof:name":"Eric Peterson Inc",
    "wof:placetype":"venue"
},
  "geometry": {"coordinates":[-97.77198300000001,30.288961],"type":"Point"}
}