{
  "type": "Feature",
  "properties": {
    "iso:country":"US",
    "sg:address":"1614 Hazelwood St",
    "sg:city":"Conroe",
    "sg:classifiers":[
        {
            "category":"Professional",
            "subcategory":"Business Services",
            "type":"Services"
        }
    ],
    "sg:phone":"+1 936 441 9508",
    "sg:postcode":"77301",
    "sg:province":"TX",
    "sg:tags":[
        "real estate"
    ],
    "wof:name":"Teegray Enterprises LLC",
    "wof:placetype":"venue"
},
  "geometry": {"coordinates":[-95.430003,30.308777],"type":"Point"}
}