{
  "type": "Feature",
  "properties": {
    "iso:country":"US",
    "sg:address":"7705 Bateman Ln",
    "sg:city":"Houston",
    "sg:classifiers":[
        {
            "category":"Real Estate",
            "subcategory":"Real Estate Agent",
            "type":"Services"
        }
    ],
    "sg:phone":"+1 281 445 1270",
    "sg:postcode":"77088",
    "sg:province":"TX",
    "wof:name":"Shepley Properties",
    "wof:placetype":"venue"
},
  "geometry": {"coordinates":[-95.477428,29.879546],"type":"Point"}
}