{
  "type": "Feature",
  "properties": {
    "iso:country":"US",
    "sg:address":"3101 Technology Dr",
    "sg:city":"Plano",
    "sg:classifiers":[
        {
            "category":"Manufacturing",
            "subcategory":"Rubber & Plastics",
            "type":"Manufacturing & Wholesale Goods"
        }
    ],
    "sg:phone":"+1 469 241 1877",
    "sg:postcode":"75074",
    "sg:province":"TX",
    "sg:tags":[
        "product"
    ],
    "wof:name":"Lamination Center",
    "wof:placetype":"venue"
},
  "geometry": {"coordinates":[-96.671164,33.012275],"type":"Point"}
}