{
  "type": "Feature",
  "properties": {
    "iso:country":"US",
    "sg:address":"2020 Rowlett Rd",
    "sg:city":"Garland",
    "sg:classifiers":[
        {
            "category":"Recreation",
            "type":"Entertainment"
        }
    ],
    "sg:phone":"+1 972 240 6455",
    "sg:postcode":"75043",
    "sg:province":"TX",
    "sg:tags":[
        "skating",
        "park",
        "amusement",
        "rink"
    ],
    "wof:name":"Texas Skatium Inc",
    "wof:placetype":"venue"
},
  "geometry": {"coordinates":[-96.576401,32.8615],"type":"Point"}
}