{
  "type": "Feature",
  "properties": {
    "iso:country":"US",
    "sg:address":"1601 N Central Expy",
    "sg:city":"Richardson",
    "sg:classifiers":[
        {
            "category":"Restaurant",
            "type":"Food & Drink"
        }
    ],
    "sg:phone":"+1 972 690 4867",
    "sg:postcode":"75080",
    "sg:province":"TX",
    "sg:website":"www.humperdinks.com",
    "wof:name":"Humperdinks Restaurant",
    "wof:placetype":"venue"
},
  "geometry": {"coordinates":[-96.71959699999999,32.970901],"type":"Point"}
}