{
  "type": "Feature",
  "properties": {
    "iso:country":"US",
    "sg:address":"7850 Woodshire Dr",
    "sg:city":"Dallas",
    "sg:classifiers":[
        {
            "category":"Wholesale",
            "subcategory":"Vending Machines",
            "type":"Manufacturing & Wholesale Goods"
        }
    ],
    "sg:phone":"+1 972 224 8443",
    "sg:postcode":"75232",
    "sg:province":"TX",
    "sg:tags":[
        "operator"
    ],
    "wof:name":"Kelley Vending Co",
    "wof:placetype":"venue"
},
  "geometry": {"coordinates":[-96.83927799999999,32.650964],"type":"Point"}
}