{
  "type": "Feature",
  "properties": {
    "iso:country":"US",
    "sg:address":"6448 E Hwy 290",
    "sg:city":"Austin",
    "sg:classifiers":[
        {
            "category":"Professional",
            "subcategory":"Computer Services",
            "type":"Services"
        }
    ],
    "sg:phone":"+1 512 339 0664",
    "sg:postcode":"78723",
    "sg:province":"TX",
    "sg:tags":[
        "networking",
        "custom"
    ],
    "wof:name":"Netgineer Data Systems Inc",
    "wof:placetype":"venue"
},
  "geometry": {"coordinates":[-97.69853999999999,30.322222],"type":"Point"}
}