{
  "type": "Feature",
  "properties": {
    "iso:country":"US",
    "sg:address":"6431 Belton Rd",
    "sg:city":"El Paso",
    "sg:classifiers":[
        {
            "category":"Professional",
            "subcategory":"Management & Consulting",
            "type":"Services"
        }
    ],
    "sg:phone":"+1 915 833 0220",
    "sg:postcode":"79912",
    "sg:province":"TX",
    "sg:tags":[
        "business"
    ],
    "wof:name":"Janet L Jackson",
    "wof:placetype":"venue"
},
  "geometry": {"coordinates":[-106.55004599999999,31.826406],"type":"Point"}
}