{
  "type": "Feature",
  "properties": {
    "iso:country":"US",
    "sg:address":"173 I- 35",
    "sg:city":"Devine",
    "sg:classifiers":[
        {
            "category":"Food & Beverages",
            "subcategory":"Groceries & Convenience Stores",
            "type":"Retail Goods"
        }
    ],
    "sg:phone":"+1 830 663 5692",
    "sg:postcode":"78057",
    "sg:province":"TX",
    "wof:name":"Calames 3",
    "wof:placetype":"venue"
},
  "geometry": {"coordinates":[-99.11484900000001,28.898847],"type":"Point"}
}