{
  "type": "Feature",
  "properties": {
    "iso:country":"US",
    "sg:address":"2404 N Dixie Blvd",
    "sg:city":"Odessa",
    "sg:classifiers":[
        {
            "category":"Retail",
            "subcategory":"Animal Services",
            "type":"Services"
        }
    ],
    "sg:phone":"+1 432 334 6828",
    "sg:postcode":"79761",
    "sg:province":"TX",
    "sg:tags":[
        "business"
    ],
    "wof:name":"Clip-N-Dip",
    "wof:placetype":"venue"
},
  "geometry": {"coordinates":[-102.36908,31.870649],"type":"Point"}
}