{
  "type": "Feature",
  "properties": {
    "iso:country":"US",
    "sg:address":"1303 Coryell St",
    "sg:city":"League City",
    "sg:classifiers":[
        {
            "category":"Wholesale",
            "subcategory":"Machinery & Supplies",
            "type":"Manufacturing & Wholesale Goods"
        }
    ],
    "sg:phone":"+1 281 554 9081",
    "sg:postcode":"77573",
    "sg:province":"TX",
    "sg:tags":[
        "electronic",
        "navigation",
        "equipment"
    ],
    "wof:name":"Novatel Inc",
    "wof:placetype":"venue"
},
  "geometry": {"coordinates":[-95.086629,29.518983],"type":"Point"}
}