{
  "type": "Feature",
  "properties": {
    "iso:country":"US",
    "sg:address":"409 Ridge Country Rd",
    "sg:city":"Haslet",
    "sg:classifiers":[
        {
            "category":"Building & Trades",
            "subcategory":"Electrical",
            "type":"Services"
        }
    ],
    "sg:phone":"+1 817 439 1669",
    "sg:postcode":"76052",
    "sg:province":"TX",
    "sg:tags":[
        "electrical",
        "contractor"
    ],
    "wof:name":"Hentzen",
    "wof:placetype":"venue"
},
  "geometry": {"coordinates":[-97.353398,32.932881],"type":"Point"}
}