{
  "type": "Feature",
  "properties": {
    "iso:country":"US",
    "sg:address":"6121 W Park Blvd",
    "sg:city":"Plano",
    "sg:classifiers":[
        {
            "category":"Shopping",
            "subcategory":"Shoes",
            "type":"Retail Goods"
        }
    ],
    "sg:phone":"+1 469 366 1098",
    "sg:postcode":"75093",
    "sg:province":"TX",
    "sg:tags":[
        "store"
    ],
    "wof:name":"Aldo",
    "wof:placetype":"venue"
},
  "geometry": {"coordinates":[-96.831703,33.027699],"type":"Point"}
}