{
  "type": "Feature",
  "properties": {
    "iso:country":"US",
    "sg:address":"2715 Cobblestone Dr",
    "sg:city":"Grapevine",
    "sg:classifiers":[
        {
            "category":"Building & Trades",
            "subcategory":"Construction",
            "type":"Services"
        }
    ],
    "sg:phone":"+1 817 481 3061",
    "sg:postcode":"76051",
    "sg:province":"TX",
    "sg:tags":[
        "builder",
        "operative"
    ],
    "wof:name":"Lakeside Estates",
    "wof:placetype":"venue"
},
  "geometry": {"coordinates":[-97.10923099999999,32.964433],"type":"Point"}
}