{
  "type": "Feature",
  "properties": {
    "iso:country":"US",
    "sg:address":"500 W Borden St",
    "sg:city":"Sinton",
    "sg:classifiers":[
        {
            "category":"Restaurant",
            "type":"Food & Drink"
        }
    ],
    "sg:phone":"+1 361 364 1920",
    "sg:postcode":"78387",
    "sg:province":"TX",
    "wof:name":"Just Four Me Accessories",
    "wof:placetype":"venue"
},
  "geometry": {"coordinates":[-97.51532,28.035641],"type":"Point"}
}