{
  "type": "Feature",
  "properties": {
    "iso:country":"US",
    "sg:address":"2307 Yale Ave",
    "sg:city":"Wichita Falls",
    "sg:classifiers":[
        {
            "category":"Building & Trades",
            "subcategory":"Plumbing",
            "type":"Services"
        }
    ],
    "sg:phone":"+1 940 761 2110",
    "sg:postcode":"76301",
    "sg:province":"TX",
    "sg:tags":[
        "contractor"
    ],
    "wof:name":"Brooks Payne Plumbing",
    "wof:placetype":"venue"
},
  "geometry": {"coordinates":[-98.493127,33.890251],"type":"Point"}
}