{
  "type": "Feature",
  "properties": {
    "iso:country":"US",
    "sg:address":"5021 Justin St",
    "sg:city":"Nacogdoches",
    "sg:classifiers":[
        {
            "category":"Professional",
            "type":"Services"
        }
    ],
    "sg:phone":"+1 936 560 6134",
    "sg:postcode":"75965",
    "sg:province":"TX",
    "sg:tags":[
        "establishment"
    ],
    "wof:name":"Systems Leap Inc",
    "wof:placetype":"venue"
},
  "geometry": {"coordinates":[-94.66236499999999,31.653417],"type":"Point"}
}