{
  "type": "Feature",
  "properties": {
    "iso:country":"US",
    "sg:address":"706 Starr Rd",
    "sg:city":"Denison",
    "sg:classifiers":[
        {
            "category":"Shopping",
            "subcategory":"Gifts & Souvenirs",
            "type":"Retail Goods"
        }
    ],
    "sg:phone":"+1 903 465 2197",
    "sg:postcode":"75021",
    "sg:province":"TX",
    "sg:tags":[
        "basket",
        "parcel"
    ],
    "wof:name":"Baskets Of Enchantment",
    "wof:placetype":"venue"
},
  "geometry": {"coordinates":[-96.473384,33.70696],"type":"Point"}
}