{
  "type": "Feature",
  "properties": {
    "iso:country":"US",
    "sg:address":"1508 Harvey Rd",
    "sg:city":"College Station",
    "sg:classifiers":[
        {
            "category":"Shopping",
            "subcategory":"Department Store",
            "type":"Retail Goods"
        }
    ],
    "sg:phone":"+1 409 764 3258",
    "sg:postcode":"77840",
    "sg:province":"TX",
    "wof:name":"Foleys Department Store",
    "wof:placetype":"venue"
},
  "geometry": {"coordinates":[-96.30416200000001,30.627841],"type":"Point"}
}