{
  "type": "Feature",
  "properties": {
    "iso:country":"US",
    "sg:address":"2320 Gene Littler Dr",
    "sg:city":"El Paso",
    "sg:classifiers":[
        {
            "category":"Manufacturing",
            "subcategory":"Chemicals & Compounds",
            "type":"Manufacturing & Wholesale Goods"
        }
    ],
    "sg:phone":"+1 915 593 3226",
    "sg:postcode":"79936",
    "sg:province":"TX",
    "sg:tags":[
        "product",
        "engineering",
        "mfg"
    ],
    "wof:name":"Productos Stevens SA",
    "wof:placetype":"venue"
},
  "geometry": {"coordinates":[-106.319424,31.776149],"type":"Point"}
}