{
  "type": "Feature",
  "properties": {
    "iso:country":"US",
    "sg:address":"124 Sunset Blvd",
    "sg:city":"Hewitt",
    "sg:classifiers":[
        {
            "category":"Building & Trades",
            "subcategory":"Plumbing",
            "type":"Services"
        }
    ],
    "sg:phone":"+1 254 722 1891",
    "sg:postcode":"76643",
    "sg:province":"TX",
    "sg:tags":[
        "conditioning",
        "air",
        "system",
        "contractor"
    ],
    "wof:name":"Apache Heating & Air Cond",
    "wof:placetype":"venue"
},
  "geometry": {"coordinates":[-97.19546200000001,31.464226],"type":"Point"}
}