{
  "type": "Feature",
  "properties": {
    "iso:country":"US",
    "sg:address":"8015 De Priest St # B",
    "sg:city":"Houston",
    "sg:classifiers":[
        {
            "category":"Food & Beverages",
            "subcategory":"Groceries & Convenience Stores",
            "type":"Retail Goods"
        }
    ],
    "sg:phone":"+1 281 448 5141",
    "sg:postcode":"77088",
    "sg:province":"TX",
    "wof:name":"Sunco Marketplace No 1",
    "wof:placetype":"venue"
},
  "geometry": {"coordinates":[-95.42130299999999,29.8748],"type":"Point"}
}