{
  "type": "Feature",
  "properties": {
    "iso:country":"US",
    "sg:address":"1700 7th St",
    "sg:city":"Bay City",
    "sg:classifiers":[
        {
            "category":"Government",
            "subcategory":"Office",
            "type":"Public Place"
        }
    ],
    "sg:phone":"+1 979 244 7691",
    "sg:postcode":"77414",
    "sg:province":"TX",
    "sg:tags":[
        "affairs",
        "administrative"
    ],
    "wof:name":"Veterans Service Officer",
    "wof:placetype":"venue"
},
  "geometry": {"coordinates":[-95.968796,28.983027],"type":"Point"}
}