{
  "type": "Feature",
  "properties": {
    "iso:country":"US",
    "sg:address":"200 E Dallas Ave",
    "sg:city":"Cooper",
    "sg:classifiers":[
        {
            "category":"Social Services",
            "type":"Services"
        }
    ],
    "sg:phone":"+1 903 395 4466",
    "sg:postcode":"75432",
    "sg:province":"TX",
    "sg:tags":[
        "counseling"
    ],
    "wof:name":"Family Haven Star Program",
    "wof:placetype":"venue"
},
  "geometry": {"coordinates":[-95.686956,33.373841],"type":"Point"}
}