{
  "type": "Feature",
  "properties": {
    "iso:country":"US",
    "sg:address":"12221 Merit Dr",
    "sg:city":"Dallas",
    "sg:classifiers":[
        {
            "category":"Restaurant",
            "type":"Food & Drink"
        }
    ],
    "sg:phone":"+1 972 385 8080",
    "sg:postcode":"75251",
    "sg:province":"TX",
    "wof:name":"High Five Cafe",
    "wof:placetype":"venue"
},
  "geometry": {"coordinates":[-96.772301,32.914001],"type":"Point"}
}