{
  "type": "Feature",
  "properties": {
    "iso:country":"US",
    "sg:address":"8619 Honeysuckle Trl",
    "sg:city":"Austin",
    "sg:classifiers":[
        {
            "category":"Real Estate",
            "subcategory":"Real Estate Agent",
            "type":"Services"
        }
    ],
    "sg:phone":"+1 512 346 5452",
    "sg:postcode":"78759",
    "sg:province":"TX",
    "sg:tags":[
        "appraisal"
    ],
    "wof:name":"Cox Fellows Associates",
    "wof:placetype":"venue"
},
  "geometry": {"coordinates":[-97.744091,30.376747],"type":"Point"}
}