{
  "type": "Feature",
  "properties": {
    "iso:country":"US",
    "sg:address":"6031 Village Glen Dr",
    "sg:city":"Dallas",
    "sg:classifiers":[
        {
            "category":"Retail",
            "subcategory":"Laundry & Dry Cleaning",
            "type":"Services"
        }
    ],
    "sg:phone":"+1 214 520 9894",
    "sg:postcode":"75206",
    "sg:province":"TX",
    "wof:name":"Flormax Carpet Cleaning",
    "wof:placetype":"venue"
},
  "geometry": {"coordinates":[-96.76008299999999,32.85987],"type":"Point"}
}