{
  "type": "Feature",
  "properties": {
    "iso:country":"US",
    "sg:address":"917 Darnel Dr",
    "sg:city":"Mesquite",
    "sg:classifiers":[
        {
            "category":"Building & Trades",
            "subcategory":"Plumbing",
            "type":"Services"
        }
    ],
    "sg:phone":"+1 972 289 0043",
    "sg:postcode":"75149",
    "sg:province":"TX",
    "sg:tags":[
        "contractor"
    ],
    "wof:name":"Pipe Works Plumbing",
    "wof:placetype":"venue"
},
  "geometry": {"coordinates":[-96.578973,32.755741],"type":"Point"}
}