{
  "type": "Feature",
  "properties": {
    "iso:country":"US",
    "sg:address":"5115 Gilmer Rd",
    "sg:city":"Longview",
    "sg:classifiers":[
        {
            "category":"Organizations",
            "subcategory":"Religious Organization",
            "type":"Services"
        }
    ],
    "sg:phone":"+1 903 759 0700",
    "sg:postcode":"75604",
    "sg:province":"TX",
    "sg:tags":[
        "church"
    ],
    "wof:name":"Spring Hill Assembly Of God",
    "wof:placetype":"venue"
},
  "geometry": {"coordinates":[-94.809923,32.576163],"type":"Point"}
}