{
  "type": "Feature",
  "properties": {
    "iso:country":"US",
    "sg:address":"2517 Fairmount St",
    "sg:city":"Dallas",
    "sg:classifiers":[
        {
            "category":"Shopping",
            "type":"Retail Goods"
        }
    ],
    "sg:phone":"+1 214 754 0055",
    "sg:postcode":"75201",
    "sg:province":"TX",
    "sg:tags":[
        "merchandise"
    ],
    "wof:name":"Fairmount Gallery",
    "wof:placetype":"venue"
},
  "geometry": {"coordinates":[-96.803258,32.79589],"type":"Point"}
}