{
  "type": "Feature",
  "properties": {
    "iso:country":"US",
    "sg:address":"750 Pine Bluff St",
    "sg:city":"Paris",
    "sg:classifiers":[
        {
            "category":"Building & Trades",
            "subcategory":"Construction",
            "type":"Services"
        }
    ],
    "sg:phone":"+1 903 785 3500",
    "sg:postcode":"75460",
    "sg:province":"TX",
    "sg:tags":[
        "painting",
        "contractor"
    ],
    "wof:name":"C Taylor",
    "wof:placetype":"venue"
},
  "geometry": {"coordinates":[-95.548768,33.663962],"type":"Point"}
}