{
  "type": "Feature",
  "properties": {
    "iso:country":"US",
    "sg:address":"13618 Charwell Xing",
    "sg:city":"Houston",
    "sg:classifiers":[
        {
            "category":"Professional",
            "subcategory":"Business Services",
            "type":"Services"
        }
    ],
    "sg:phone":"+1 281 866 0091",
    "sg:postcode":"77069",
    "sg:province":"TX",
    "sg:tags":[
        "training",
        "management",
        "consulting"
    ],
    "wof:name":"Your Training Solutions LP",
    "wof:placetype":"venue"
},
  "geometry": {"coordinates":[-95.51987800000001,29.989779],"type":"Point"}
}