{
  "type": "Feature",
  "properties": {
    "iso:country":"US",
    "sg:address":"5401 Southwest Pkwy",
    "sg:city":"Wichita Falls",
    "sg:classifiers":[
        {
            "category":"Organizations",
            "subcategory":"Membership Organization",
            "type":"Services"
        }
    ],
    "sg:phone":"+1 940 692 0693",
    "sg:postcode":"76310",
    "sg:province":"TX",
    "wof:name":"Sunrise Optimist Girls Sftball",
    "wof:placetype":"venue"
},
  "geometry": {"coordinates":[-98.58248399999999,33.858083],"type":"Point"}
}