{
  "type": "Feature",
  "properties": {
    "iso:country":"US",
    "sg:address":"3709 Reagan St",
    "sg:city":"Houston",
    "sg:classifiers":[
        {
            "category":"Communications",
            "subcategory":"Film & Video Production",
            "type":"Services"
        }
    ],
    "sg:phone":"+1 713 426 6662",
    "sg:postcode":"77009",
    "sg:province":"TX",
    "sg:tags":[
        "taping"
    ],
    "wof:name":"Moviestuff",
    "wof:placetype":"venue"
},
  "geometry": {"coordinates":[-95.37944400000001,29.791465],"type":"Point"}
}