{
  "type": "Feature",
  "properties": {
    "iso:country":"US",
    "sg:address":"9311 San Pedro Ave",
    "sg:city":"San Antonio",
    "sg:classifiers":[
        {
            "category":"Health Services",
            "subcategory":"Clinic",
            "type":"Services"
        }
    ],
    "sg:phone":"+1 210 259 0276",
    "sg:postcode":"78216",
    "sg:province":"TX",
    "wof:name":"Health Care Administration",
    "wof:placetype":"venue"
},
  "geometry": {"coordinates":[-98.498611,29.52677],"type":"Point"}
}