{
  "type": "Feature",
  "properties": {
    "iso:country":"US",
    "sg:address":"1132 Pin Oak Dr",
    "sg:city":"Dickinson",
    "sg:classifiers":[
        {
            "category":"Professional",
            "type":"Services"
        }
    ],
    "sg:phone":"+1 281 337 7689",
    "sg:postcode":"77539",
    "sg:province":"TX",
    "wof:name":"Broadway Bound",
    "wof:placetype":"venue"
},
  "geometry": {"coordinates":[-95.077265,29.465274],"type":"Point"}
}