{
  "type": "Feature",
  "properties": {
    "iso:country":"US",
    "sg:address":"106 N 23rd St",
    "sg:city":"Temple",
    "sg:classifiers":[
        {
            "category":"Restaurant",
            "type":"Food & Drink"
        }
    ],
    "sg:phone":"+1 254 771 2959",
    "sg:postcode":"76504",
    "sg:province":"TX",
    "sg:tags":[
        "eating"
    ],
    "wof:name":"Shrimp Shack",
    "wof:placetype":"venue"
},
  "geometry": {"coordinates":[-97.35220200000001,31.102115],"type":"Point"}
}