{
  "type": "Feature",
  "properties": {
    "iso:country":"US",
    "sg:address":"767 N Main St",
    "sg:city":"Cleburne",
    "sg:classifiers":[
        {
            "category":"Wholesale",
            "subcategory":"Groceries",
            "type":"Manufacturing & Wholesale Goods"
        }
    ],
    "sg:phone":"+1 817 641 9023",
    "sg:postcode":"76033",
    "sg:province":"TX",
    "sg:tags":[
        "general"
    ],
    "wof:name":"Mobile",
    "wof:placetype":"venue"
},
  "geometry": {"coordinates":[-97.38928300000001,32.356287],"type":"Point"}
}