{
  "type": "Feature",
  "properties": {
    "iso:country":"US",
    "sg:address":"2745 S Hulen St",
    "sg:city":"Fort Worth",
    "sg:classifiers":[
        {
            "category":"Retail",
            "subcategory":"Laundry & Dry Cleaning",
            "type":"Services"
        }
    ],
    "sg:phone":"+1 817 731 6866",
    "sg:postcode":"76109",
    "sg:province":"TX",
    "sg:tags":[
        "cleaners"
    ],
    "wof:name":"Laundry",
    "wof:placetype":"venue"
},
  "geometry": {"coordinates":[-97.386914,32.709686],"type":"Point"}
}