{
  "type": "Feature",
  "properties": {
    "iso:country":"US",
    "sg:address":"5610 Southwest Fwy",
    "sg:city":"Houston",
    "sg:classifiers":[
        {
            "category":"Shopping",
            "subcategory":"Optician",
            "type":"Retail Goods"
        }
    ],
    "sg:phone":"+1 713 622 9992",
    "sg:postcode":"77057",
    "sg:province":"TX",
    "sg:tags":[
        "eyewear"
    ],
    "wof:name":"All American Eye Glass Repair",
    "wof:placetype":"venue"
},
  "geometry": {"coordinates":[-95.47725800000001,29.726615],"type":"Point"}
}