{
  "type": "Feature",
  "properties": {
    "iso:country":"US",
    "sg:address":"5302 Crossvalley Dr",
    "sg:city":"Corpus Christi",
    "sg:classifiers":[
        {
            "category":"Professional",
            "type":"Services"
        }
    ],
    "sg:phone":"+1 361 993 4624",
    "sg:postcode":"78413",
    "sg:province":"TX",
    "wof:name":"Handy Man Can",
    "wof:placetype":"venue"
},
  "geometry": {"coordinates":[-97.394897,27.6761],"type":"Point"}
}