{
  "type": "Feature",
  "properties": {
    "iso:country":"US",
    "sg:address":"7415 Colby Run Ct",
    "sg:city":"Richmond",
    "sg:classifiers":[
        {
            "category":"Place Of Worship",
            "type":"Public Place"
        }
    ],
    "sg:phone":"+1 281 325 0039",
    "sg:postcode":"77407",
    "sg:province":"TX",
    "sg:tags":[
        "church"
    ],
    "wof:name":"Mirada De Fe Iglesia Evangelic",
    "wof:placetype":"venue"
},
  "geometry": {"coordinates":[-95.69228,29.697603],"type":"Point"}
}