{
  "type": "Feature",
  "properties": {
    "iso:country":"US",
    "sg:address":"5023 Clark Ave",
    "sg:city":"San Antonio",
    "sg:classifiers":[
        {
            "category":"Social Services",
            "type":"Services"
        }
    ],
    "sg:phone":"+1 210 333 9487",
    "sg:postcode":"78223",
    "sg:province":"TX",
    "wof:name":"Catholic Fmly Frtnrl Txas Kjzt",
    "wof:placetype":"venue"
},
  "geometry": {"coordinates":[-98.44802,29.363039],"type":"Point"}
}