{
  "type": "Feature",
  "properties": {
    "iso:country":"US",
    "sg:address":"2674 N Belt Line Rd",
    "sg:city":"Irving",
    "sg:classifiers":[
        {
            "category":"Personal",
            "type":"Services"
        }
    ],
    "sg:phone":"+1 972 258 7900",
    "sg:postcode":"75062",
    "sg:province":"TX",
    "sg:tags":[
        "control",
        "weight"
    ],
    "wof:name":"Hi Energy Weight Control Ctr",
    "wof:placetype":"venue"
},
  "geometry": {"coordinates":[-96.993044,32.841132],"type":"Point"}
}