{
  "type": "Feature",
  "properties": {
    "iso:country":"US",
    "sg:address":"301 Chisholm Trl",
    "sg:city":"Round Rock",
    "sg:classifiers":[
        {
            "category":"Travel",
            "subcategory":"Campground",
            "type":"Entertainment"
        }
    ],
    "sg:phone":"+1 512 218 1228",
    "sg:postcode":"78681",
    "sg:province":"TX",
    "sg:tags":[
        "camp"
    ],
    "wof:name":"Baseball Academy Of Texas",
    "wof:placetype":"venue"
},
  "geometry": {"coordinates":[-97.689429,30.510226],"type":"Point"}
}