{
  "type": "Feature",
  "properties": {
    "iso:country":"US",
    "sg:address":"2611 Cedar Springs Rd",
    "sg:city":"Dallas",
    "sg:classifiers":[
        {
            "category":"Organizations",
            "subcategory":"Professional Association",
            "type":"Services"
        }
    ],
    "sg:phone":"+1 214 468 8942",
    "sg:postcode":"75201",
    "sg:province":"TX",
    "sg:tags":[
        "business"
    ],
    "wof:name":"Texas Golf Association",
    "wof:placetype":"venue"
},
  "geometry": {"coordinates":[-96.805632,32.800475],"type":"Point"}
}