{
  "type": "Feature",
  "properties": {
    "iso:country":"US",
    "sg:address":"2017 N Frazier St",
    "sg:city":"Conroe",
    "sg:classifiers":[
        {
            "category":"Organizations",
            "subcategory":"Community Association",
            "type":"Services"
        }
    ],
    "sg:phone":"+1 936 756 0515",
    "sg:postcode":"77301",
    "sg:province":"TX",
    "sg:tags":[
        "club"
    ],
    "wof:name":"Johnny B Dalton's",
    "wof:placetype":"venue"
},
  "geometry": {"coordinates":[-95.467055,30.333708],"type":"Point"}
}