{
  "type": "Feature",
  "properties": {
    "iso:country":"US",
    "sg:address":"415 Pecos Trl",
    "sg:city":"Irving",
    "sg:classifiers":[
        {
            "category":"Professional",
            "subcategory":"Business Services",
            "type":"Services"
        }
    ],
    "sg:phone":"+1 972 506 7591",
    "sg:postcode":"75063",
    "sg:province":"TX",
    "wof:name":"Mp Supply",
    "wof:placetype":"venue"
},
  "geometry": {"coordinates":[-96.95158600000001,32.930887],"type":"Point"}
}