{
  "type": "Feature",
  "properties": {
    "iso:country":"US",
    "sg:address":"2910 W Kingsbury St",
    "sg:city":"Seguin",
    "sg:classifiers":[
        {
            "category":"Food & Beverages",
            "subcategory":"Meat & Fish",
            "type":"Retail Goods"
        }
    ],
    "sg:phone":"+1 830 303 5095",
    "sg:postcode":"78155",
    "sg:province":"TX",
    "wof:name":"Charlie's Meat Market",
    "wof:placetype":"venue"
},
  "geometry": {"coordinates":[-98.027675,29.555425],"type":"Point"}
}