{
  "type": "Feature",
  "properties": {
    "iso:country":"US",
    "sg:address":"241 E Ovilla Rd",
    "sg:city":"Red Oak",
    "sg:classifiers":[
        {
            "category":"Restaurant",
            "type":"Food & Drink"
        }
    ],
    "sg:phone":"+1 972 617 8788",
    "sg:postcode":"75154",
    "sg:province":"TX",
    "sg:tags":[
        "eating"
    ],
    "wof:name":"Paramos Mexican Restaurant",
    "wof:placetype":"venue"
},
  "geometry": {"coordinates":[-96.859816,32.531813],"type":"Point"}
}