{
  "type": "Feature",
  "properties": {
    "iso:country":"US",
    "sg:address":"8616 Jordan Dr",
    "sg:city":"Lubbock",
    "sg:classifiers":[
        {
            "category":"Professional",
            "subcategory":"Accounting & Tax Preparation",
            "type":"Services"
        }
    ],
    "sg:phone":"+1 806 792 5481",
    "sg:postcode":"79423",
    "sg:province":"TX",
    "sg:tags":[
        "auditing",
        "bookkeeping"
    ],
    "wof:name":"Alice Ann Price",
    "wof:placetype":"venue"
},
  "geometry": {"coordinates":[-101.89027400000001,33.513836],"type":"Point"}
}