{
  "type": "Feature",
  "properties": {
    "iso:country":"US",
    "sg:address":"117 E Haning St",
    "sg:city":"Howe",
    "sg:classifiers":[
        {
            "category":"Government",
            "subcategory":"Office",
            "type":"Public Place"
        }
    ],
    "sg:phone":"+1 903 532 6027",
    "sg:postcode":"75459",
    "sg:province":"TX",
    "sg:tags":[
        "village"
    ],
    "wof:name":"Howe SNAP Ctr",
    "wof:placetype":"venue"
},
  "geometry": {"coordinates":[-96.612797,33.5061],"type":"Point"}
}