{
  "type": "Feature",
  "properties": {
    "iso:country":"US",
    "sg:address":"2023 de Milo Dr",
    "sg:city":"Houston",
    "sg:classifiers":[
        {
            "category":"Shopping",
            "subcategory":"Gifts & Souvenirs",
            "type":"Retail Goods"
        }
    ],
    "sg:phone":"+1 713 957 2652",
    "sg:postcode":"77018",
    "sg:province":"TX",
    "sg:tags":[
        "basket",
        "parcel"
    ],
    "wof:name":"F Cubed Enterprises LLC",
    "wof:placetype":"venue"
},
  "geometry": {"coordinates":[-95.449579,29.834527],"type":"Point"}
}