{
  "type": "Feature",
  "properties": {
    "iso:country":"US",
    "sg:address":"12574 Research Boulevard",
    "sg:city":"Austin",
    "sg:classifiers":[
        {
            "category":"Banks & Credit Unions",
            "subcategory":"Bank",
            "type":"Services"
        }
    ],
    "sg:phone":"+1 512 335 4900",
    "sg:postcode":"78759",
    "sg:province":"TX",
    "sg:website":"www.bankofamerica.com",
    "wof:name":"Bank of America",
    "wof:placetype":"venue"
},
  "geometry": {"coordinates":[-97.761109,30.429776],"type":"Point"}
}