{
  "type": "Feature",
  "properties": {
    "iso:country":"US",
    "sg:address":"7928 Hillcroft St",
    "sg:city":"Houston",
    "sg:classifiers":[
        {
            "category":"Health Services",
            "subcategory":"Clinic",
            "type":"Services"
        }
    ],
    "sg:phone":"+1 713 272 8331",
    "sg:postcode":"77081",
    "sg:province":"TX",
    "wof:name":"Leaders Health Svc",
    "wof:placetype":"venue"
},
  "geometry": {"coordinates":[-95.493039,29.692465],"type":"Point"}
}