{
  "type": "Feature",
  "properties": {
    "iso:country":"US",
    "sg:address":"1500 N Arkansas Ave",
    "sg:city":"Laredo",
    "sg:classifiers":[
        {
            "category":"Government",
            "subcategory":"Office",
            "type":"Public Place"
        }
    ],
    "sg:phone":"+1 956 728 7383",
    "sg:postcode":"78043",
    "sg:province":"TX",
    "sg:tags":[
        "state",
        "resource"
    ],
    "wof:name":"Child Protective Svc",
    "wof:placetype":"venue"
},
  "geometry": {"coordinates":[-99.468008,27.51022],"type":"Point"}
}