{
  "type": "Feature",
  "properties": {
    "iso:country":"US",
    "sg:address":"2200 Gravel Dr",
    "sg:city":"Fort Worth",
    "sg:classifiers":[
        {
            "category":"Professional",
            "subcategory":"Engineering",
            "type":"Services"
        }
    ],
    "sg:phone":"+1 817 284 7755",
    "sg:postcode":"76118",
    "sg:province":"TX",
    "sg:tags":[
        "engineer"
    ],
    "sg:website":"www.mactec.com",
    "wof:name":"Mactec Engineering & Consult",
    "wof:placetype":"venue"
},
  "geometry": {"coordinates":[-97.21725000000001,32.792944],"type":"Point"}
}