{
  "type": "Feature",
  "properties": {
    "iso:country":"US",
    "sg:address":"14833 Southwest Fwy",
    "sg:city":"Sugar Land",
    "sg:classifiers":[
        {
            "category":"Health Services",
            "subcategory":"Doctor",
            "type":"Services"
        }
    ],
    "sg:phone":"+1 281 242 2719",
    "sg:postcode":"77478",
    "sg:province":"TX",
    "sg:tags":[
        "medical"
    ],
    "wof:name":"Chow Clement Inc",
    "wof:placetype":"venue"
},
  "geometry": {"coordinates":[-95.611341,29.608965],"type":"Point"}
}