{
  "type": "Feature",
  "properties": {
    "iso:country":"US",
    "sg:address":"5372 Doniphan Dr",
    "sg:city":"El Paso",
    "sg:classifiers":[
        {
            "category":"Building & Trades",
            "subcategory":"Construction",
            "type":"Services"
        }
    ],
    "sg:phone":"+1 915 584 7861",
    "sg:postcode":"79932",
    "sg:province":"TX",
    "sg:tags":[
        "contractor",
        "work",
        "carpet"
    ],
    "wof:name":"Carpets West",
    "wof:placetype":"venue"
},
  "geometry": {"coordinates":[-106.583382,31.850532],"type":"Point"}
}