{
  "type": "Feature",
  "properties": {
    "iso:country":"US",
    "sg:address":"421 N Denton St",
    "sg:city":"Gainesville",
    "sg:classifiers":[
        {
            "category":"Education",
            "subcategory":"School",
            "type":"Public Place"
        }
    ],
    "sg:phone":"+1 940 665 4062",
    "sg:postcode":"76240",
    "sg:province":"TX",
    "sg:tags":[
        "middle"
    ],
    "wof:name":"Gainesville Junior High School",
    "wof:placetype":"venue"
},
  "geometry": {"coordinates":[-97.1427,33.62738],"type":"Point"}
}