{
  "type": "Feature",
  "properties": {
    "iso:country":"US",
    "sg:address":"4701 Ayers St",
    "sg:city":"Corpus Christi",
    "sg:classifiers":[
        {
            "category":"Health Services",
            "subcategory":"Medical Lab",
            "type":"Services"
        }
    ],
    "sg:phone":"+1 361 225 2218",
    "sg:postcode":"78415",
    "sg:province":"TX",
    "sg:tags":[
        "detection",
        "equipment",
        "drug"
    ],
    "wof:name":"Pinnacle Medical Management",
    "wof:placetype":"venue"
},
  "geometry": {"coordinates":[-97.424246,27.740426],"type":"Point"}
}