{
  "type": "Feature",
  "properties": {
    "iso:country":"US",
    "sg:address":"1346 N Lee Trevino Dr",
    "sg:city":"El Paso",
    "sg:classifiers":[
        {
            "category":"Restaurant",
            "type":"Food & Drink"
        }
    ],
    "sg:phone":"+1 915 629 9114",
    "sg:postcode":"79936",
    "sg:province":"TX",
    "wof:name":"Wing It Wings & Things",
    "wof:placetype":"venue"
},
  "geometry": {"coordinates":[-106.32038799999999,31.74458],"type":"Point"}
}