{
  "type": "Feature",
  "properties": {
    "iso:country":"US",
    "sg:address":"1950 W Gray St Ste 6",
    "sg:city":"Houston",
    "sg:classifiers":[
        {
            "category":"Sports & Exercise",
            "subcategory":"Gym",
            "type":"Entertainment"
        }
    ],
    "sg:phone":"+1 713 529 9601",
    "sg:postcode":"77019",
    "sg:province":"TX",
    "sg:website":"www.myfitgym.com/",
    "wof:name":"River Oaks Fitness",
    "wof:placetype":"venue"
},
  "geometry": {"coordinates":[-95.40571,29.753868],"type":"Point"}
}