{
  "type": "Feature",
  "properties": {
    "iso:country":"US",
    "sg:address":"2302 E Expy 83",
    "sg:city":"Weslaco",
    "sg:classifiers":[
        {
            "category":"Shopping",
            "subcategory":"Used Merchandise",
            "type":"Retail Goods"
        }
    ],
    "sg:phone":"+1 956 968 0733",
    "sg:postcode":"78596",
    "sg:province":"TX",
    "wof:name":"Next-Too-New",
    "wof:placetype":"venue"
},
  "geometry": {"coordinates":[-97.969418,26.166785],"type":"Point"}
}