{
  "type": "Feature",
  "properties": {
    "iso:country":"US",
    "sg:address":"207 River St",
    "sg:city":"Hallettsville",
    "sg:classifiers":[
        {
            "category":"Wholesale",
            "subcategory":"Sporting Goods",
            "type":"Manufacturing & Wholesale Goods"
        }
    ],
    "sg:phone":"+1 361 798 1530",
    "sg:postcode":"77964",
    "sg:province":"TX",
    "wof:name":"Foreverlast Hunting Products",
    "wof:placetype":"venue"
},
  "geometry": {"coordinates":[-96.943343,29.439076],"type":"Point"}
}