{
  "type": "Feature",
  "properties": {
    "iso:country":"US",
    "sg:address":"2613 Forest Ln",
    "sg:city":"Garland",
    "sg:classifiers":[
        {
            "category":"Restaurant",
            "type":"Food & Drink"
        }
    ],
    "sg:phone":"+1 972 494 2160",
    "sg:postcode":"75042",
    "sg:province":"TX",
    "sg:tags":[
        "barbeque"
    ],
    "wof:name":"Moore's Bar-B-Cue House",
    "wof:placetype":"venue"
},
  "geometry": {"coordinates":[-96.668701,32.9091],"type":"Point"}
}