{
  "type": "Feature",
  "properties": {
    "iso:country":"US",
    "sg:address":"4900 S Collins St",
    "sg:city":"Arlington",
    "sg:classifiers":[
        {
            "category":"Wholesale",
            "subcategory":"Machinery & Supplies",
            "type":"Manufacturing & Wholesale Goods"
        }
    ],
    "sg:phone":"+1 817 468 7788",
    "sg:postcode":"76018",
    "sg:province":"TX",
    "sg:tags":[
        "equipment",
        "transportation"
    ],
    "wof:name":"Van Bortel Aircraft Inc",
    "wof:placetype":"venue"
},
  "geometry": {"coordinates":[-97.090599,32.66473],"type":"Point"}
}