{
  "type": "Feature",
  "properties": {
    "iso:country":"US",
    "sg:address":"214 S Bois D'Arc St",
    "sg:city":"Hillsboro",
    "sg:classifiers":[
        {
            "category":"Social Services",
            "type":"Services"
        }
    ],
    "sg:phone":"+1 254 582 3403",
    "sg:postcode":"76645",
    "sg:province":"TX",
    "sg:tags":[
        "information",
        "planning",
        "center",
        "family"
    ],
    "wof:name":"Family Planning",
    "wof:placetype":"venue"
},
  "geometry": {"coordinates":[-97.132524,32.008295],"type":"Point"}
}