{
  "type": "Feature",
  "properties": {
    "iso:country":"US",
    "sg:address":"2525 Wallingwood Dr 1300A",
    "sg:city":"Austin",
    "sg:classifiers":[
        {
            "category":"Professional",
            "subcategory":"Business Services",
            "type":"Services"
        }
    ],
    "sg:phone":"+1 512 220 4160",
    "sg:postcode":"78746",
    "sg:province":"TX",
    "sg:tags":[
        "organizing",
        "services-household"
    ],
    "wof:name":"Austin Texas Property Management",
    "wof:placetype":"venue"
},
  "geometry": {"coordinates":[-97.785397,30.264018],"type":"Point"}
}