{
  "type": "Feature",
  "properties": {
    "iso:country":"US",
    "sg:address":"3741 Atlanta St",
    "sg:city":"Dallas",
    "sg:classifiers":[
        {
            "category":"Banks & Credit Unions",
            "subcategory":"Bank",
            "type":"Services"
        }
    ],
    "sg:phone":"+1 214 421 7224",
    "sg:postcode":"75215",
    "sg:province":"TX",
    "sg:tags":[
        "state"
    ],
    "wof:name":"Common Ground Community Econom",
    "wof:placetype":"venue"
},
  "geometry": {"coordinates":[-96.764185,32.760437],"type":"Point"}
}