{
  "type": "Feature",
  "properties": {
    "iso:country":"US",
    "sg:address":"1222 N Main Ave",
    "sg:city":"San Antonio",
    "sg:classifiers":[
        {
            "category":"Banks & Credit Unions",
            "subcategory":"Bank",
            "type":"Services"
        }
    ],
    "sg:phone":"+1 210 386 3393",
    "sg:postcode":"78212",
    "sg:province":"TX",
    "sg:tags":[
        "financing",
        "factoring"
    ],
    "wof:name":"Terra Factor Funding Inc",
    "wof:placetype":"venue"
},
  "geometry": {"coordinates":[-98.494119,29.440406],"type":"Point"}
}