{
  "type": "Feature",
  "properties": {
    "iso:country":"US",
    "sg:address":"5264 Beechnut St",
    "sg:city":"Houston",
    "sg:classifiers":[
        {
            "category":"Health Services",
            "subcategory":"Doctor",
            "type":"Services"
        }
    ],
    "sg:phone":"+1 713 981 4600",
    "sg:postcode":"77096",
    "sg:province":"TX",
    "sg:tags":[
        "surgeon",
        "oral"
    ],
    "wof:name":"Silberman David DDS",
    "wof:placetype":"venue"
},
  "geometry": {"coordinates":[-95.47517499999999,29.6894],"type":"Point"}
}