{
  "type": "Feature",
  "properties": {
    "iso:country":"US",
    "sg:address":"2102 W Business 83",
    "sg:city":"Mercedes",
    "sg:classifiers":[
        {
            "category":"Autos & Motor Vehicles",
            "subcategory":"Automobile Sales",
            "type":"Retail Goods"
        },
        {
            "category":"Retail",
            "subcategory":"Auto Rental",
            "type":"Services"
        }
    ],
    "sg:phone":"+1 956 514 0162",
    "sg:postcode":"78570",
    "sg:province":"TX",
    "sg:tags":[
        "renting",
        "used",
        "leasing",
        "car",
        "truck",
        "trailer"
    ],
    "wof:name":"U-Haul Neighborhood Dealer - Mercedes Motors",
    "wof:placetype":"venue"
},
  "geometry": {"coordinates":[-97.87382100000001,26.151519],"type":"Point"}
}