{
  "type": "Feature",
  "properties": {
    "iso:country":"US",
    "sg:address":"6021 Canyon Dr",
    "sg:city":"Amarillo",
    "sg:classifiers":[
        {
            "category":"Retail",
            "subcategory":"Auto Repair",
            "type":"Services"
        }
    ],
    "sg:phone":"+1 806 468 6453",
    "sg:postcode":"79110",
    "sg:province":"TX",
    "sg:tags":[
        "shop",
        "automotive",
        "general"
    ],
    "wof:name":"Mike Biele Automotive",
    "wof:placetype":"venue"
},
  "geometry": {"coordinates":[-101.886617,35.145993],"type":"Point"}
}