{
  "type": "Feature",
  "properties": {
    "iso:country":"US",
    "sg:address":"1715 H Ave",
    "sg:city":"Plano",
    "sg:classifiers":[
        {
            "category":"Insurance",
            "subcategory":"Insurance Agent",
            "type":"Services"
        }
    ],
    "sg:phone":"+1 972 881 5511",
    "sg:postcode":"75074",
    "sg:province":"TX",
    "wof:name":"Uni Care",
    "wof:placetype":"venue"
},
  "geometry": {"coordinates":[-96.702878,33.023715],"type":"Point"}
}