{
  "type": "Feature",
  "properties": {
    "iso:country":"US",
    "sg:address":"327 W Tyler Ave",
    "sg:city":"Longview",
    "sg:classifiers":[
        {
            "category":"Home & Garden",
            "subcategory":"Furniture",
            "type":"Retail Goods"
        }
    ],
    "sg:phone":"+1 903 753 7263",
    "sg:postcode":"75601",
    "sg:province":"TX",
    "sg:website":"www.collierfurniture.com",
    "wof:name":"Collier Furniture",
    "wof:placetype":"venue"
},
  "geometry": {"coordinates":[-94.747401,32.499148],"type":"Point"}
}