{
  "type": "Feature",
  "properties": {
    "iso:country":"US",
    "sg:address":"14060 Dallas Pkwy",
    "sg:city":"Dallas",
    "sg:classifiers":[
        {
            "category":"Shopping",
            "subcategory":"Computers & Home Electronics",
            "type":"Retail Goods"
        }
    ],
    "sg:postcode":"75254",
    "sg:province":"TX",
    "sg:website":"www.tigerdirect.com",
    "wof:name":"TigerDirect",
    "wof:placetype":"venue"
},
  "geometry": {"coordinates":[-96.820953,32.938565],"type":"Point"}
}