{
  "type": "Feature",
  "properties": {
    "iso:country":"US",
    "sg:address":"5177 Richmond Ave",
    "sg:city":"Houston",
    "sg:classifiers":[
        {
            "category":"Professional",
            "subcategory":"Accounting & Tax Preparation",
            "type":"Services"
        }
    ],
    "sg:phone":"+1 713 993 7113",
    "sg:postcode":"77056",
    "sg:province":"TX",
    "sg:tags":[
        "accountant"
    ],
    "wof:name":"Selwyn L Blanchard CPA",
    "wof:placetype":"venue"
},
  "geometry": {"coordinates":[-95.468002,29.731456],"type":"Point"}
}