{
  "type": "Feature",
  "properties": {
    "iso:country":"US",
    "sg:address":"12403 Alexandria St",
    "sg:city":"San Antonio",
    "sg:classifiers":[
        {
            "category":"Wholesale",
            "subcategory":"Durable Goods & Equipment",
            "type":"Manufacturing & Wholesale Goods"
        }
    ],
    "sg:phone":"+1 210 656 8707",
    "sg:postcode":"78233",
    "sg:province":"TX",
    "sg:tags":[
        "real estate"
    ],
    "wof:name":"Whippet Inc",
    "wof:placetype":"venue"
},
  "geometry": {"coordinates":[-98.369884,29.552838],"type":"Point"}
}