{
  "type": "Feature",
  "properties": {
    "iso:country":"US",
    "sg:address":"6909 State Hwy 1604",
    "sg:city":"San Antonio",
    "sg:classifiers":[
        {
            "category":"Shopping",
            "subcategory":"Optical Goods",
            "type":"Retail Goods"
        }
    ],
    "sg:phone":"+1 210 599 7645",
    "sg:postcode":"78232",
    "sg:province":"TX",
    "wof:name":"Lens Crafters",
    "wof:placetype":"venue"
},
  "geometry": {"coordinates":[-98.352693,29.593082],"type":"Point"}
}