{
  "type": "Feature",
  "properties": {
    "iso:country":"US",
    "sg:address":"1644 Richmond Ave",
    "sg:city":"Houston",
    "sg:classifiers":[
        {
            "category":"Retail",
            "subcategory":"Repair Shop",
            "type":"Services"
        },
        {
            "category":"Shopping",
            "type":"Retail Goods"
        }
    ],
    "sg:phone":"+1 713 527 0802",
    "sg:postcode":"77006",
    "sg:province":"TX",
    "sg:tags":[
        "picture",
        "frame",
        "custom"
    ],
    "wof:name":"Framemaker's Gallery Inc",
    "wof:placetype":"venue"
},
  "geometry": {"coordinates":[-95.39948099999999,29.73442],"type":"Point"}
}