{
  "type": "Feature",
  "properties": {
    "iso:country":"US",
    "sg:address":"15035 Kirkfield Ln",
    "sg:city":"Houston",
    "sg:classifiers":[
        {
            "category":"Professional",
            "subcategory":"Management & Consulting",
            "type":"Services"
        }
    ],
    "sg:phone":"+1 281 445 3417",
    "sg:postcode":"77060",
    "sg:province":"TX",
    "sg:tags":[
        "business"
    ],
    "wof:name":"Educational Consultant/Diagnos",
    "wof:placetype":"venue"
},
  "geometry": {"coordinates":[-95.40370299999999,29.919314],"type":"Point"}
}