{
  "type": "Feature",
  "properties": {
    "iso:country":"US",
    "sg:address":"100 N Main St",
    "sg:city":"Corsicana",
    "sg:classifiers":[
        {
            "category":"Government",
            "subcategory":"Office",
            "type":"Public Place"
        }
    ],
    "sg:phone":"+1 903 874 0760",
    "sg:postcode":"75110",
    "sg:province":"TX",
    "sg:tags":[
        "executive"
    ],
    "wof:name":"Congressman Martin Frost",
    "wof:placetype":"venue"
},
  "geometry": {"coordinates":[-96.46541499999999,32.093911],"type":"Point"}
}