{
  "type": "Feature",
  "properties": {
    "iso:country":"US",
    "sg:address":"4022 Wingren Dr",
    "sg:city":"Irving",
    "sg:classifiers":[
        {
            "category":"Retail",
            "subcategory":"Car Wash",
            "type":"Services"
        }
    ],
    "sg:phone":"+1 972 650 0343",
    "sg:postcode":"75062",
    "sg:province":"TX",
    "sg:tags":[
        "carwash"
    ],
    "wof:name":"Auto Splash Car Care Center",
    "wof:placetype":"venue"
},
  "geometry": {"coordinates":[-96.9418,32.856937],"type":"Point"}
}