{
  "type": "Feature",
  "properties": {
    "iso:country":"US",
    "sg:address":"9801 Co Rd 400",
    "sg:city":"Brazoria",
    "sg:classifiers":[
        {
            "category":"Retail",
            "subcategory":"Animal Services",
            "type":"Services"
        }
    ],
    "sg:phone":"+1 979 798 1326",
    "sg:postcode":"77422",
    "sg:province":"TX",
    "wof:name":"Town & Country Grooming",
    "wof:placetype":"venue"
},
  "geometry": {"coordinates":[-95.54143999999999,29.039717],"type":"Point"}
}