{
  "type": "Feature",
  "properties": {
    "iso:country":"US",
    "sg:address":"913 W Lynn St",
    "sg:city":"Austin",
    "sg:classifiers":[
        {
            "category":"Health Services",
            "subcategory":"Doctor",
            "type":"Services"
        },
        {
            "category":"Social Services",
            "type":"Services"
        },
        {
            "category":"Health Services",
            "subcategory":"Health Practitioner",
            "type":"Services"
        }
    ],
    "sg:phone":"+1 512 347 8920",
    "sg:postcode":"78703",
    "sg:province":"TX",
    "sg:tags":[
        "psychotherapist",
        "psychologist",
        "worker"
    ],
    "wof:name":"Littlefield Josephine",
    "wof:placetype":"venue"
},
  "geometry": {"coordinates":[-97.760277,30.27849],"type":"Point"}
}