{
  "type": "Feature",
  "properties": {
    "iso:country":"US",
    "sg:address":"8909 Chalk Knoll Dr",
    "sg:city":"Austin",
    "sg:classifiers":[
        {
            "category":"Banks & Credit Unions",
            "subcategory":"Financial Services",
            "type":"Services"
        }
    ],
    "sg:phone":"+1 512 328 2187",
    "sg:postcode":"78735",
    "sg:province":"TX",
    "sg:tags":[
        "investor"
    ],
    "wof:name":"Capital Hockey GP LLC",
    "wof:placetype":"venue"
},
  "geometry": {"coordinates":[-97.867132,30.2978],"type":"Point"}
}