{
  "type": "Feature",
  "properties": {
    "iso:country":"US",
    "sg:address":"17550 W Little York Rd",
    "sg:city":"Houston",
    "sg:classifiers":[
        {
            "category":"Personal",
            "subcategory":"Beauty Salon",
            "type":"Services"
        }
    ],
    "sg:phone":"+1 281 345 9168",
    "sg:postcode":"77084",
    "sg:province":"TX",
    "sg:tags":[
        "shop"
    ],
    "wof:name":"Ultimate Hair & Nails",
    "wof:placetype":"venue"
},
  "geometry": {"coordinates":[-95.67684,29.865452],"type":"Point"}
}