{
  "type": "Feature",
  "properties": {
    "iso:country":"US",
    "sg:address":"6010 Canyon Springs Rd",
    "sg:city":"Dallas",
    "sg:classifiers":[
        {
            "category":"Shopping",
            "subcategory":"Jewelry",
            "type":"Retail Goods"
        }
    ],
    "sg:phone":"+1 972 380 2483",
    "sg:postcode":"75248",
    "sg:province":"TX",
    "wof:name":"Natalie S Jewelry Gifts",
    "wof:placetype":"venue"
},
  "geometry": {"coordinates":[-96.801604,32.977616],"type":"Point"}
}