{
  "type": "Feature",
  "properties": {
    "iso:country":"US",
    "sg:address":"3110 Gayle St",
    "sg:city":"Victoria",
    "sg:classifiers":[
        {
            "category":"Building & Trades",
            "subcategory":"Construction",
            "type":"Services"
        }
    ],
    "sg:phone":"+1 361 676 0960",
    "sg:postcode":"77901",
    "sg:province":"TX",
    "sg:tags":[
        "house"
    ],
    "wof:name":"Battles Company",
    "wof:placetype":"venue"
},
  "geometry": {"coordinates":[-96.971085,28.795107],"type":"Point"}
}