{
  "type": "Feature",
  "properties": {
    "iso:country":"US",
    "sg:address":"413 W Southmore Ave",
    "sg:city":"Pasadena",
    "sg:classifiers":[
        {
            "category":"Autos & Motor Vehicles",
            "subcategory":"Automobile Sales",
            "type":"Retail Goods"
        }
    ],
    "sg:phone":"+1 713 928 5428",
    "sg:postcode":"77502",
    "sg:province":"TX",
    "sg:tags":[
        "car",
        "dealer"
    ],
    "wof:name":"CMG Auto Sales",
    "wof:placetype":"venue"
},
  "geometry": {"coordinates":[-95.215943,29.690714],"type":"Point"}
}