{
  "type": "Feature",
  "properties": {
    "iso:country":"US",
    "sg:address":"3122 21st St",
    "sg:city":"Lubbock",
    "sg:classifiers":[
        {
            "category":"Professional",
            "subcategory":"Computer Services",
            "type":"Services"
        }
    ],
    "sg:phone":"+1 806 797 0212",
    "sg:postcode":"79410",
    "sg:province":"TX",
    "sg:tags":[
        "consultant",
        "designer"
    ],
    "wof:name":"Data Collectors",
    "wof:placetype":"venue"
},
  "geometry": {"coordinates":[-101.88303399999999,33.575637],"type":"Point"}
}