{
  "type": "Feature",
  "properties": {
    "iso:country":"US",
    "sg:address":"308 Handell Ln",
    "sg:city":"Pasadena",
    "sg:classifiers":[
        {
            "category":"Building & Trades",
            "subcategory":"Construction",
            "type":"Services"
        }
    ],
    "sg:phone":"+1 713 944 1816",
    "sg:postcode":"77502",
    "sg:province":"TX",
    "sg:tags":[
        "contractor"
    ],
    "wof:name":"Escobar Roofing",
    "wof:placetype":"venue"
},
  "geometry": {"coordinates":[-95.215052,29.670959],"type":"Point"}
}