{
  "type": "Feature",
  "properties": {
    "iso:country":"US",
    "sg:address":"2901 S Lancaster Rd",
    "sg:city":"Dallas",
    "sg:classifiers":[
        {
            "category":"Restaurant",
            "type":"Food & Drink"
        }
    ],
    "sg:phone":"+1 214 302 3000",
    "sg:postcode":"75216",
    "sg:province":"TX",
    "sg:tags":[
        "barbeque"
    ],
    "sg:website":"www.dallasobserver.com/2009-10-2...",
    "wof:name":"CT's Real Deal BBQ",
    "wof:placetype":"venue"
},
  "geometry": {"coordinates":[-96.804835,32.712161],"type":"Point"}
}