{
  "type": "Feature",
  "properties": {
    "iso:country":"US",
    "sg:address":"4417 N McColl Rd",
    "sg:city":"Mcallen",
    "sg:classifiers":[
        {
            "category":"Building & Trades",
            "subcategory":"Construction",
            "type":"Services"
        }
    ],
    "sg:phone":"+1 956 664 8151",
    "sg:postcode":"78504",
    "sg:province":"TX",
    "sg:tags":[
        "contractor"
    ],
    "wof:name":"Option Enterprises",
    "wof:placetype":"venue"
},
  "geometry": {"coordinates":[-98.206621,26.237757],"type":"Point"}
}