{
  "type": "Feature",
  "properties": {
    "iso:country":"US",
    "sg:address":"8930 San Patrico Court",
    "sg:city":"Houston",
    "sg:classifiers":[
        {
            "category":"Professional",
            "subcategory":"Computer Services",
            "type":"Services"
        }
    ],
    "sg:phone":"+1 713 594 9489",
    "sg:postcode":"77064",
    "sg:province":"TX",
    "sg:tags":[
        "repair"
    ],
    "sg:website":"pcgeeksrus.com",
    "wof:name":"PC Geeks 'R Us",
    "wof:placetype":"venue"
},
  "geometry": {"coordinates":[-95.568405,29.90311],"type":"Point"}
}