{
  "type": "Feature",
  "properties": {
    "iso:country":"US",
    "sg:address":"1105 Valley View Dr",
    "sg:city":"Weslaco",
    "sg:classifiers":[
        {
            "category":"Organizations",
            "subcategory":"Non-profit Organization",
            "type":"Services"
        }
    ],
    "sg:phone":"+1 956 968 2465",
    "sg:postcode":"78596",
    "sg:province":"TX",
    "sg:tags":[
        "association",
        "social"
    ],
    "wof:name":"Narfe",
    "wof:placetype":"venue"
},
  "geometry": {"coordinates":[-98.001963,26.159716],"type":"Point"}
}