{
  "type": "Feature",
  "properties": {
    "iso:country":"US",
    "sg:address":"3510 Bobbie Ln",
    "sg:city":"Garland",
    "sg:classifiers":[
        {
            "category":"Building & Trades",
            "subcategory":"Construction",
            "type":"Services"
        }
    ],
    "sg:phone":"+1 972 494 0695",
    "sg:postcode":"75042",
    "sg:province":"TX",
    "sg:tags":[
        "contractor"
    ],
    "wof:name":"Moto General Contractors",
    "wof:placetype":"venue"
},
  "geometry": {"coordinates":[-96.68520700000001,32.920954],"type":"Point"}
}