{
  "type": "Feature",
  "properties": {
    "iso:country":"US",
    "sg:address":"5104 White Hills Dr",
    "sg:city":"Fort Worth",
    "sg:classifiers":[
        {
            "category":"Retail",
            "subcategory":"Portrait Studio",
            "type":"Services"
        }
    ],
    "sg:phone":"+1 817 427 2011",
    "sg:postcode":"76137",
    "sg:province":"TX",
    "sg:tags":[
        "photo"
    ],
    "wof:name":"In The Blink of An Eye",
    "wof:placetype":"venue"
},
  "geometry": {"coordinates":[-97.273493,32.871367],"type":"Point"}
}