{
  "type": "Feature",
  "properties": {
    "iso:country":"US",
    "sg:address":"7605 Rice Dr",
    "sg:city":"Rowlett",
    "sg:classifiers":[
        {
            "category":"Building & Trades",
            "subcategory":"Construction",
            "type":"Services"
        }
    ],
    "sg:phone":"+1 972 475 4425",
    "sg:postcode":"75088",
    "sg:province":"TX",
    "sg:tags":[
        "nonresidential"
    ],
    "wof:name":"Mickey Construction",
    "wof:placetype":"venue"
},
  "geometry": {"coordinates":[-96.52920399999999,32.88854],"type":"Point"}
}