{
  "type": "Feature",
  "properties": {
    "iso:country":"US",
    "sg:address":"5428 Jacksboro Hwy",
    "sg:city":"Fort Worth",
    "sg:classifiers":[
        {
            "category":"Retail",
            "subcategory":"Auto Repair",
            "type":"Services"
        }
    ],
    "sg:phone":"+1 817 625 4851",
    "sg:postcode":"76114",
    "sg:province":"TX",
    "sg:tags":[
        "repairing",
        "automobile"
    ],
    "wof:name":"Clint's Transmission Svc",
    "wof:placetype":"venue"
},
  "geometry": {"coordinates":[-97.402447,32.79752],"type":"Point"}
}