{
  "type": "Feature",
  "properties": {
    "iso:country":"US",
    "sg:address":"3327 Broadway Blvd",
    "sg:city":"Garland",
    "sg:classifiers":[
        {
            "category":"Restaurant",
            "type":"Food & Drink"
        }
    ],
    "sg:menulink":"http://www.allmenus.com/tx/northeast/203999-sonic/menu/",
    "sg:phone":"+1 972 271 5462",
    "sg:postcode":"75043",
    "sg:province":"TX",
    "sg:tags":[
        "burger",
        "american"
    ],
    "wof:name":"Sonic",
    "wof:placetype":"venue"
},
  "geometry": {"coordinates":[-96.617701,32.874863],"type":"Point"}
}