{
  "type": "Feature",
  "properties": {
    "iso:country":"US",
    "sg:address":"1313 Daily Rd",
    "sg:city":"Rosenberg",
    "sg:classifiers":[
        {
            "category":"Wholesale",
            "subcategory":"Metals & Minerals",
            "type":"Manufacturing & Wholesale Goods"
        }
    ],
    "sg:phone":"+1 281 342 3250",
    "sg:postcode":"77471",
    "sg:province":"TX",
    "sg:tags":[
        "steel",
        "warehouse"
    ],
    "wof:name":"Custom Flame Cutting Inc",
    "wof:placetype":"venue"
},
  "geometry": {"coordinates":[-95.89697,29.514159],"type":"Point"}
}