{
  "type": "Feature",
  "properties": {
    "iso:country":"US",
    "sg:address":"4318 Oak Creek Dr",
    "sg:city":"Nacogdoches",
    "sg:classifiers":[
        {
            "category":"Shopping",
            "subcategory":"Jewelry",
            "type":"Retail Goods"
        }
    ],
    "sg:phone":"+1 936 559 7621",
    "sg:postcode":"75965",
    "sg:province":"TX",
    "wof:name":"Jack & Carolyns Fabulous",
    "wof:placetype":"venue"
},
  "geometry": {"coordinates":[-94.606849,31.650775],"type":"Point"}
}