{
  "type": "Feature",
  "properties": {
    "iso:country":"US",
    "sg:address":"19360 Allen Ranch Rd",
    "sg:city":"Eustace",
    "sg:classifiers":[
        {
            "category":"Professional",
            "subcategory":"Detective & Security Services",
            "type":"Services"
        }
    ],
    "sg:phone":"+1 972 365 4413",
    "sg:postcode":"75124",
    "sg:province":"TX",
    "sg:tags":[
        "information",
        "bureau"
    ],
    "wof:name":"Supreme Steam Services",
    "wof:placetype":"venue"
},
  "geometry": {"coordinates":[-96.08965999999999,32.302378],"type":"Point"}
}