{
  "type": "Feature",
  "properties": {
    "iso:country":"US",
    "sg:address":"254 Brightwood Pl",
    "sg:city":"San Antonio",
    "sg:classifiers":[
        {
            "category":"Health Services",
            "subcategory":"Doctor",
            "type":"Services"
        }
    ],
    "sg:phone":"+1 210 826 5384",
    "sg:postcode":"78209",
    "sg:province":"TX",
    "sg:tags":[
        "physician",
        "surgeon"
    ],
    "wof:name":"Jay Reid MD",
    "wof:placetype":"venue"
},
  "geometry": {"coordinates":[-98.459266,29.496509],"type":"Point"}
}