{
  "type": "Feature",
  "properties": {
    "iso:country":"US",
    "sg:address":"417 Co Rd 1143",
    "sg:city":"Tyler",
    "sg:classifiers":[
        {
            "category":"Organizations",
            "subcategory":"Religious Organization",
            "type":"Services"
        }
    ],
    "sg:phone":"+1 903 592 7183",
    "sg:postcode":"75704",
    "sg:province":"TX",
    "sg:tags":[
        "church"
    ],
    "wof:name":"Pleasant Retreat United Meth",
    "wof:placetype":"venue"
},
  "geometry": {"coordinates":[-95.391267,32.361213],"type":"Point"}
}