{
  "type": "Feature",
  "properties": {
    "iso:country":"US",
    "sg:address":"2307 California St",
    "sg:city":"Wichita Falls",
    "sg:classifiers":[
        {
            "category":"Professional",
            "subcategory":"Management & Consulting",
            "type":"Services"
        }
    ],
    "sg:phone":"+1 940 761 4534",
    "sg:postcode":"76301",
    "sg:province":"TX",
    "sg:tags":[
        "public",
        "relations"
    ],
    "wof:name":"Saw Buddy Inc",
    "wof:placetype":"venue"
},
  "geometry": {"coordinates":[-98.481208,33.890184],"type":"Point"}
}