{
  "type": "Feature",
  "properties": {
    "iso:country":"US",
    "sg:address":"7101 N Mesa St",
    "sg:city":"El Paso",
    "sg:classifiers":[
        {
            "category":"Retail",
            "subcategory":"Auto Rental",
            "type":"Services"
        }
    ],
    "sg:phone":"+1 915 833 3168",
    "sg:postcode":"79912",
    "sg:province":"TX",
    "sg:tags":[
        "truck"
    ],
    "wof:name":"Geary Ltd",
    "wof:placetype":"venue"
},
  "geometry": {"coordinates":[-106.556538,31.836748],"type":"Point"}
}