{
  "type": "Feature",
  "properties": {
    "iso:country":"US",
    "sg:address":"1115 Overland Stage Rd",
    "sg:city":"Dripping Springs",
    "sg:classifiers":[
        {
            "category":"Building & Trades",
            "subcategory":"Electrical",
            "type":"Services"
        }
    ],
    "sg:phone":"+1 512 264 2292",
    "sg:postcode":"78620",
    "sg:province":"TX",
    "sg:tags":[
        "electrical",
        "contractor"
    ],
    "wof:name":"Austin Advance Technology",
    "wof:placetype":"venue"
},
  "geometry": {"coordinates":[-98.13211200000001,30.303353],"type":"Point"}
}