{
  "type": "Feature",
  "properties": {
    "iso:country":"US",
    "sg:address":"1604 Senator St",
    "sg:city":"Texarkana",
    "sg:classifiers":[
        {
            "category":"Professional",
            "subcategory":"Management & Consulting",
            "type":"Services"
        }
    ],
    "sg:phone":"+1 870 773 1175",
    "sg:postcode":"71854",
    "sg:province":"TX",
    "sg:tags":[
        "business"
    ],
    "wof:name":"Political Conslt Specialists",
    "wof:placetype":"venue"
},
  "geometry": {"coordinates":[-94.031721,33.439078],"type":"Point"}
}