{
  "type": "Feature",
  "properties": {
    "iso:country":"US",
    "sg:address":"2505 Seagoville Rd",
    "sg:city":"Seagoville",
    "sg:classifiers":[
        {
            "category":"Building & Trades",
            "subcategory":"Construction",
            "type":"Services"
        }
    ],
    "sg:phone":"+1 972 287 6206",
    "sg:postcode":"75159",
    "sg:province":"TX",
    "sg:tags":[
        "general",
        "contractor"
    ],
    "wof:name":"Dale Anderson Construction Inc",
    "wof:placetype":"venue"
},
  "geometry": {"coordinates":[-96.567554,32.667806],"type":"Point"}
}