{
  "type": "Feature",
  "properties": {
    "iso:country":"US",
    "sg:address":"15106 Lakewood Forest Dr",
    "sg:city":"Houston",
    "sg:classifiers":[
        {
            "category":"Manufacturing",
            "subcategory":"Tools & Machinery",
            "type":"Manufacturing & Wholesale Goods"
        }
    ],
    "sg:phone":"+1 281 370 8010",
    "sg:postcode":"77070",
    "sg:province":"TX",
    "sg:tags":[
        "photographic",
        "mfg"
    ],
    "wof:name":"Lemker & Harris Enterprises",
    "wof:placetype":"venue"
},
  "geometry": {"coordinates":[-95.592004,29.993055],"type":"Point"}
}