{
  "type": "Feature",
  "properties": {
    "iso:country":"US",
    "sg:address":"2407 Cambridge St",
    "sg:city":"Odessa",
    "sg:classifiers":[
        {
            "category":"Autos & Motor Vehicles",
            "subcategory":"Automobile Sales",
            "type":"Retail Goods"
        }
    ],
    "sg:phone":"+1 432 366 7708",
    "sg:postcode":"79761",
    "sg:province":"TX",
    "sg:tags":[
        "used"
    ],
    "wof:name":"Handy Andy New & Used",
    "wof:placetype":"venue"
},
  "geometry": {"coordinates":[-102.34427599999999,31.865919],"type":"Point"}
}