{
  "type": "Feature",
  "properties": {
    "iso:country":"US",
    "sg:address":"8108 Double St",
    "sg:city":"Houston",
    "sg:classifiers":[
        {
            "category":"Organizations",
            "subcategory":"Religious Organization",
            "type":"Services"
        }
    ],
    "sg:phone":"+1 281 820 3053",
    "sg:postcode":"77088",
    "sg:province":"TX",
    "sg:tags":[
        "church"
    ],
    "wof:name":"Greater True Vine Baptist Chr",
    "wof:placetype":"venue"
},
  "geometry": {"coordinates":[-95.429073,29.87613],"type":"Point"}
}