{
  "type": "Feature",
  "properties": {
    "iso:country":"US",
    "sg:address":"4046 Clover Ln",
    "sg:city":"Dallas",
    "sg:classifiers":[
        {
            "category":"Shopping",
            "subcategory":"Photographic Equipment",
            "type":"Retail Goods"
        }
    ],
    "sg:phone":"+1 214 352 5692",
    "sg:postcode":"75220",
    "sg:province":"TX",
    "sg:tags":[
        "film"
    ],
    "wof:name":"The Check Room",
    "wof:placetype":"venue"
},
  "geometry": {"coordinates":[-96.843507,32.870925],"type":"Point"}
}