{
  "type": "Feature",
  "properties": {
    "iso:country":"US",
    "sg:address":"701 N Post Oak Rd",
    "sg:city":"Houston",
    "sg:classifiers":[
        {
            "category":"Insurance",
            "subcategory":"Insurance Agent",
            "type":"Services"
        }
    ],
    "sg:phone":"+1 713 812 9006",
    "sg:postcode":"77024",
    "sg:province":"TX",
    "wof:name":"LRC Insurance",
    "wof:placetype":"venue"
},
  "geometry": {"coordinates":[-95.456734,29.780143],"type":"Point"}
}