{
  "type": "Feature",
  "properties": {
    "iso:country":"US",
    "sg:address":"1304 E Euless Blvd",
    "sg:city":"Euless",
    "sg:classifiers":[
        {
            "category":"Banks & Credit Unions",
            "subcategory":"Bank",
            "type":"Services"
        }
    ],
    "sg:phone":"+1 817 283 6000",
    "sg:postcode":"76040",
    "sg:province":"TX",
    "sg:tags":[
        "loan"
    ],
    "wof:name":"Cars N Cash Inc",
    "wof:placetype":"venue"
},
  "geometry": {"coordinates":[-97.10360799999999,32.82739],"type":"Point"}
}