{
  "type": "Feature",
  "properties": {
    "iso:country":"US",
    "sg:address":"413 Georgetown Dr",
    "sg:city":"Richardson",
    "sg:classifiers":[
        {
            "category":"Building & Trades",
            "subcategory":"Cleaning & Sanitation",
            "type":"Services"
        }
    ],
    "sg:phone":"+1 972 690 9533",
    "sg:postcode":"75081",
    "sg:province":"TX",
    "sg:tags":[
        "maintenance"
    ],
    "wof:name":"Black Hat Chimney Sweep",
    "wof:placetype":"venue"
},
  "geometry": {"coordinates":[-96.695104,32.953779],"type":"Point"}
}