{
  "type": "Feature",
  "properties": {
    "iso:country":"US",
    "sg:address":"6262 Wilcrest Dr",
    "sg:city":"Houston",
    "sg:classifiers":[
        {
            "category":"Professional",
            "subcategory":"Art Services",
            "type":"Services"
        }
    ],
    "sg:phone":"+1 281 224 9338",
    "sg:postcode":"77072",
    "sg:province":"TX",
    "sg:tags":[
        "commercial",
        "printing",
        "graphic",
        "design"
    ],
    "wof:name":"Tg Printing LLC",
    "wof:placetype":"venue"
},
  "geometry": {"coordinates":[-95.57146400000001,29.714117],"type":"Point"}
}