{
  "type": "Feature",
  "properties": {
    "iso:country":"US",
    "sg:address":"547 E Division St",
    "sg:city":"Pilot Point",
    "sg:classifiers":[
        {
            "category":"Shopping",
            "type":"Retail Goods"
        }
    ],
    "sg:phone":"+1 940 686 8083",
    "sg:postcode":"76258",
    "sg:province":"TX",
    "sg:tags":[
        "trophy",
        "medal",
        "award"
    ],
    "wof:name":"George & David's Trophies",
    "wof:placetype":"venue"
},
  "geometry": {"coordinates":[-96.95249699999999,33.394598],"type":"Point"}
}