{
  "type": "Feature",
  "properties": {
    "iso:country":"US",
    "sg:address":"564 Northwest Mall",
    "sg:city":"Houston",
    "sg:classifiers":[
        {
            "category":"Health Services",
            "subcategory":"Optometrist",
            "type":"Services"
        }
    ],
    "sg:phone":"+1 713 681 7110",
    "sg:postcode":"77092",
    "sg:province":"TX",
    "wof:name":"TSO",
    "wof:placetype":"venue"
},
  "geometry": {"coordinates":[-95.453102,29.797807],"type":"Point"}
}