{
  "type": "Feature",
  "properties": {
    "iso:country":"US",
    "sg:address":"21940 Kingsland Blvd",
    "sg:city":"Katy",
    "sg:classifiers":[
        {
            "category":"Bars & Pubs",
            "type":"Food & Drink"
        },
        {
            "category":"Organizations",
            "subcategory":"Community Association",
            "type":"Services"
        }
    ],
    "sg:phone":"+1 281 392 3499",
    "sg:postcode":"77450",
    "sg:province":"TX",
    "sg:tags":[
        "club",
        "drinking"
    ],
    "sg:website":"www.mosplace.net",
    "wof:name":"Mo's Place",
    "wof:placetype":"venue"
},
  "geometry": {"coordinates":[-95.752674,29.774768],"type":"Point"}
}