{
  "type": "Feature",
  "properties": {
    "iso:country":"US",
    "sg:address":"3068 Forest Ln",
    "sg:city":"Dallas",
    "sg:classifiers":[
        {
            "category":"Retail",
            "subcategory":"Auto Repair",
            "type":"Services"
        }
    ],
    "sg:phone":"+1 972 241 8488",
    "sg:postcode":"75234",
    "sg:province":"TX",
    "sg:tags":[
        "automotive",
        "brake"
    ],
    "wof:name":"Just Brakes",
    "wof:placetype":"venue"
},
  "geometry": {"coordinates":[-96.87369700000001,32.909697],"type":"Point"}
}