{
  "type": "Feature",
  "properties": {
    "iso:country":"US",
    "sg:address":"6600 Jamaica Ct",
    "sg:city":"Austin",
    "sg:classifiers":[
        {
            "category":"Real Estate",
            "subcategory":"Real Estate Agent",
            "type":"Services"
        }
    ],
    "sg:phone":"+1 512 371 0049",
    "sg:postcode":"78757",
    "sg:province":"TX",
    "sg:tags":[
        "inspection"
    ],
    "wof:name":"T Sterling & Assoc",
    "wof:placetype":"venue"
},
  "geometry": {"coordinates":[-97.74890499999999,30.347558],"type":"Point"}
}