{
  "type": "Feature",
  "properties": {
    "iso:country":"US",
    "sg:address":"2017 E Lamar Blvd",
    "sg:city":"Arlington",
    "sg:classifiers":[
        {
            "category":"Personal",
            "subcategory":"Beauty Salon",
            "type":"Services"
        }
    ],
    "sg:phone":"+1 817 226 4247",
    "sg:postcode":"76006",
    "sg:province":"TX",
    "wof:name":"Millennium Designs",
    "wof:placetype":"venue"
},
  "geometry": {"coordinates":[-97.077473,32.762957],"type":"Point"}
}