{
  "type": "Feature",
  "properties": {
    "iso:country":"US",
    "sg:address":"6511 S I H 35",
    "sg:city":"Austin",
    "sg:classifiers":[
        {
            "category":"Restaurant",
            "type":"Food & Drink"
        }
    ],
    "sg:phone":"+1 512 448 2351",
    "sg:postcode":"78744",
    "sg:province":"TX",
    "wof:name":"Taco Bell",
    "wof:placetype":"venue"
},
  "geometry": {"coordinates":[-97.769206,30.191127],"type":"Point"}
}