{
  "type": "Feature",
  "properties": {
    "iso:country":"US",
    "sg:address":"302 E Springdale Ln",
    "sg:city":"Grand Prairie",
    "sg:classifiers":[
        {
            "category":"Professional",
            "type":"Services"
        }
    ],
    "sg:phone":"+1 972 642 4797",
    "sg:postcode":"75052",
    "sg:province":"TX",
    "wof:name":"O AG Co",
    "wof:placetype":"venue"
},
  "geometry": {"coordinates":[-97.000685,32.703983],"type":"Point"}
}