{
  "type": "Feature",
  "properties": {
    "iso:country":"US",
    "sg:address":"601 Co Rd 325",
    "sg:city":"Norton",
    "sg:phone":"+1 325 786 4417",
    "sg:postcode":"76865",
    "sg:province":"TX",
    "sg:tags":[
        "farm",
        "cotton"
    ],
    "wof:name":"Schaefer Brothers",
    "wof:placetype":"venue"
},
  "geometry": {"coordinates":[-100.10235900000001,31.857039],"type":"Point"}
}