{
  "type": "Feature",
  "properties": {
    "iso:country":"US",
    "sg:address":"688 FM 292",
    "sg:city":"Farwell",
    "sg:classifiers":[
        {
            "category":"Government",
            "subcategory":"Office",
            "type":"Public Place"
        }
    ],
    "sg:phone":"+1 806 481 9238",
    "sg:postcode":"79325",
    "sg:province":"NM",
    "sg:tags":[
        "conservation"
    ],
    "wof:name":"Tharp Drag Line Service",
    "wof:placetype":"venue"
},
  "geometry": {"coordinates":[-103.032636,34.381039],"type":"Point"}
}