{
  "type": "Feature",
  "properties": {
    "iso:country":"US",
    "sg:address":"14466 Twisted Oak Ln",
    "sg:city":"Houston",
    "sg:classifiers":[
        {
            "category":"Mining & Drilling",
            "type":"Manufacturing & Wholesale Goods"
        }
    ],
    "sg:phone":"+1 281 558 0100",
    "sg:postcode":"77079",
    "sg:province":"TX",
    "sg:tags":[
        "oil",
        "gas",
        "producer"
    ],
    "wof:name":"McCleskey Oil & Gas LLC",
    "wof:placetype":"venue"
},
  "geometry": {"coordinates":[-95.601652,29.764333],"type":"Point"}
}