{
  "type": "Feature",
  "properties": {
    "iso:country":"US",
    "sg:address":"2415 Arkansas Blvd",
    "sg:city":"Texarkana",
    "sg:classifiers":[
        {
            "category":"Restaurant",
            "type":"Food & Drink"
        }
    ],
    "sg:phone":"+1 870 772 1888",
    "sg:postcode":"71854",
    "sg:province":"TX",
    "sg:tags":[
        "eating"
    ],
    "wof:name":"Splashs Seafood Inc",
    "wof:placetype":"venue"
},
  "geometry": {"coordinates":[-94.01847600000001,33.4606],"type":"Point"}
}