{
  "type": "Feature",
  "properties": {
    "iso:country":"US",
    "sg:address":"132 E Main St",
    "sg:city":"Port Lavaca",
    "sg:classifiers":[
        {
            "category":"Shopping",
            "subcategory":"Computers & Home Electronics",
            "type":"Retail Goods"
        }
    ],
    "sg:phone":"+1 361 552 5066",
    "sg:postcode":"77979",
    "sg:province":"TX",
    "sg:tags":[
        "equipment",
        "dealer"
    ],
    "wof:name":"Computer Place",
    "wof:placetype":"venue"
},
  "geometry": {"coordinates":[-96.62558799999999,28.615153],"type":"Point"}
}