{
  "type": "Feature",
  "properties": {
    "iso:country":"US",
    "sg:address":"3614 Avenue Q",
    "sg:city":"Lubbock",
    "sg:classifiers":[
        {
            "category":"Autos & Motor Vehicles",
            "subcategory":"Automobile Sales",
            "type":"Retail Goods"
        }
    ],
    "sg:phone":"+1 806 749 3425",
    "sg:postcode":"79412",
    "sg:province":"TX",
    "sg:tags":[
        "dealers-used",
        "car",
        "used",
        "cars-wholesale",
        "new"
    ],
    "wof:name":"Furr Auto Sales",
    "wof:placetype":"venue"
},
  "geometry": {"coordinates":[-101.8554,33.561511],"type":"Point"}
}