{
  "type": "Feature",
  "properties": {
    "iso:country":"US",
    "sg:address":"828 S Ave B",
    "sg:city":"Kermit",
    "sg:classifiers":[
        {
            "category":"Building & Trades",
            "subcategory":"Plumbing",
            "type":"Services"
        }
    ],
    "sg:phone":"+1 432 586 9135",
    "sg:postcode":"79745",
    "sg:province":"TX",
    "sg:tags":[
        "contractor"
    ],
    "wof:name":"Electric Heating N Cooling",
    "wof:placetype":"venue"
},
  "geometry": {"coordinates":[-103.085307,31.84941],"type":"Point"}
}