{
  "type": "Feature",
  "properties": {
    "iso:country":"US",
    "sg:address":"5600 North Fwy",
    "sg:city":"Houston",
    "sg:classifiers":[
        {
            "category":"Real Estate",
            "subcategory":"Real Estate Operator",
            "type":"Services"
        }
    ],
    "sg:phone":"+1 713 692 5918",
    "sg:postcode":"77076",
    "sg:province":"TX",
    "sg:tags":[
        "apartment"
    ],
    "wof:name":"Nordling Chateau Apartments",
    "wof:placetype":"venue"
},
  "geometry": {"coordinates":[-95.394218,29.848088],"type":"Point"}
}