{
  "type": "Feature",
  "properties": {
    "iso:country":"US",
    "sg:address":"2118 N Main Ave",
    "sg:city":"San Antonio",
    "sg:classifiers":[
        {
            "category":"Professional",
            "subcategory":"Lawyer & Legal Services",
            "type":"Services"
        }
    ],
    "sg:phone":"+1 210 320 7650",
    "sg:postcode":"78212",
    "sg:province":"TX",
    "sg:tags":[
        "attorney"
    ],
    "wof:name":"V Gonzalez & Assoc",
    "wof:placetype":"venue"
},
  "geometry": {"coordinates":[-98.493971,29.449912],"type":"Point"}
}