{
  "type": "Feature",
  "properties": {
    "iso:country":"US",
    "sg:address":"4560 Belt Line Rd Ste 430",
    "sg:city":"Addison",
    "sg:classifiers":[
        {
            "category":"Professional",
            "subcategory":"Accounting & Tax Preparation",
            "type":"Services"
        }
    ],
    "sg:phone":"+1 972 233 5198",
    "sg:postcode":"75001",
    "sg:province":"TX",
    "sg:tags":[
        "accountant"
    ],
    "wof:name":"Vannoy David R",
    "wof:placetype":"venue"
},
  "geometry": {"coordinates":[-96.833,32.953999],"type":"Point"}
}