{
  "type": "Feature",
  "properties": {
    "iso:country":"US",
    "sg:address":"9715 Brockbank Dr",
    "sg:city":"Dallas",
    "sg:classifiers":[
        {
            "category":"Organizations",
            "subcategory":"Membership Organization",
            "type":"Services"
        }
    ],
    "sg:phone":"+1 214 350 6666",
    "sg:postcode":"75220",
    "sg:province":"TX",
    "wof:name":"National Krean Amrcn Soc Dllas",
    "wof:placetype":"venue"
},
  "geometry": {"coordinates":[-96.875432,32.867641],"type":"Point"}
}