{
  "type": "Feature",
  "properties": {
    "iso:country":"US",
    "sg:address":"2923 Belt Line Rd",
    "sg:city":"Garland",
    "sg:classifiers":[
        {
            "category":"Personal",
            "subcategory":"Beauty Salon",
            "type":"Services"
        }
    ],
    "sg:phone":"+1 972 675 8285",
    "sg:postcode":"75044",
    "sg:province":"TX",
    "sg:tags":[
        "hair"
    ],
    "wof:name":"Family Barber Stylist",
    "wof:placetype":"venue"
},
  "geometry": {"coordinates":[-96.672237,32.944945],"type":"Point"}
}