{
  "type": "Feature",
  "properties": {
    "iso:country":"US",
    "sg:address":"1100 Dallas Dr",
    "sg:city":"Denton",
    "sg:classifiers":[
        {
            "category":"Restaurant",
            "type":"Food & Drink"
        }
    ],
    "sg:phone":"+1 940 243 0835",
    "sg:postcode":"76205",
    "sg:province":"TX",
    "sg:tags":[
        "eating"
    ],
    "wof:name":"Polos Pasta & Pizza",
    "wof:placetype":"venue"
},
  "geometry": {"coordinates":[-97.123142,33.198341],"type":"Point"}
}