{
  "type": "Feature",
  "properties": {
    "iso:country":"US",
    "sg:address":"1225 E Seminary Dr",
    "sg:city":"Fort Worth",
    "sg:classifiers":[
        {
            "category":"Building & Trades",
            "subcategory":"Construction",
            "type":"Services"
        }
    ],
    "sg:phone":"+1 817 926 3381",
    "sg:postcode":"76115",
    "sg:province":"TX",
    "sg:tags":[
        "glass",
        "contractor"
    ],
    "wof:name":"Layne Glass Company Inc",
    "wof:placetype":"venue"
},
  "geometry": {"coordinates":[-97.310767,32.684506],"type":"Point"}
}