{
  "type": "Feature",
  "properties": {
    "iso:country":"US",
    "sg:address":"2213 Padre Blvd",
    "sg:city":"S Padre Island",
    "sg:classifiers":[
        {
            "category":"Home & Garden",
            "subcategory":"Hardware",
            "type":"Retail Goods"
        }
    ],
    "sg:phone":"+1 956 761 2670",
    "sg:postcode":"78597",
    "sg:province":"TX",
    "wof:name":"Island Ace Hardware",
    "wof:placetype":"venue"
},
  "geometry": {"coordinates":[-97.16672,26.100583],"type":"Point"}
}