{
  "type": "Feature",
  "properties": {
    "iso:country":"US",
    "sg:address":"4814 State Hwy 6",
    "sg:city":"Houston",
    "sg:classifiers":[
        {
            "category":"Autos & Motor Vehicles",
            "subcategory":"Fuel & Gas Station",
            "type":"Retail Goods"
        }
    ],
    "sg:phone":"+1 281 345 1504",
    "sg:postcode":"77084",
    "sg:province":"TX",
    "sg:tags":[
        "oil"
    ],
    "wof:name":"Murphy Oil USA Inc",
    "wof:placetype":"venue"
},
  "geometry": {"coordinates":[-95.645804,29.846046],"type":"Point"}
}