{
  "type": "Feature",
  "properties": {
    "iso:country":"US",
    "sg:address":"1918 Monte Cristo Way",
    "sg:city":"Sherman",
    "sg:classifiers":[
        {
            "category":"Building & Trades",
            "subcategory":"Construction",
            "type":"Services"
        }
    ],
    "sg:phone":"+1 903 891 8485",
    "sg:postcode":"75092",
    "sg:province":"TX",
    "sg:tags":[
        "house"
    ],
    "wof:name":"D and G Philips Enter",
    "wof:placetype":"venue"
},
  "geometry": {"coordinates":[-96.64003,33.652445],"type":"Point"}
}