{
  "type": "Feature",
  "properties": {
    "iso:country":"US",
    "sg:address":"1411 Don Haskins Dr",
    "sg:city":"El Paso",
    "sg:classifiers":[
        {
            "category":"Freight",
            "type":"Transportation"
        }
    ],
    "sg:phone":"+1 915 921 9314",
    "sg:postcode":"79936",
    "sg:province":"TX",
    "wof:name":"Seko Worldwide",
    "wof:placetype":"venue"
},
  "geometry": {"coordinates":[-106.288478,31.72818],"type":"Point"}
}