{
  "type": "Feature",
  "properties": {
    "iso:country":"US",
    "sg:address":"6600 Campus Circle Dr E",
    "sg:city":"Irving",
    "sg:classifiers":[
        {
            "category":"Insurance",
            "subcategory":"Insurance Agent",
            "type":"Services"
        }
    ],
    "sg:phone":"+1 972 465 7621",
    "sg:postcode":"75063",
    "sg:province":"TX",
    "wof:name":"Casualty Claims",
    "wof:placetype":"venue"
},
  "geometry": {"coordinates":[-96.982208,32.898796],"type":"Point"}
}