{
  "type": "Feature",
  "properties": {
    "iso:country":"US",
    "sg:address":"1418 N 5th St",
    "sg:city":"Silsbee",
    "sg:classifiers":[
        {
            "category":"Wholesale",
            "subcategory":"Construction Materials",
            "type":"Manufacturing & Wholesale Goods"
        },
        {
            "category":"Wholesale",
            "subcategory":"Motor Vehicles",
            "type":"Manufacturing & Wholesale Goods"
        }
    ],
    "sg:phone":"+1 409 386 0551",
    "sg:postcode":"77656",
    "sg:province":"TX",
    "sg:tags":[
        "building",
        "hitched",
        "carrier",
        "mounted"
    ],
    "wof:name":"Cowboy Carriers L P",
    "wof:placetype":"venue"
},
  "geometry": {"coordinates":[-94.173017,30.362017],"type":"Point"}
}