{
  "type": "Feature",
  "properties": {
    "iso:country":"US",
    "sg:address":"3050 Post Oak Blvd",
    "sg:city":"Houston",
    "sg:classifiers":[
        {
            "category":"Banks & Credit Unions",
            "subcategory":"Bank",
            "type":"Services"
        }
    ],
    "sg:phone":"+1 713 355 8980",
    "sg:postcode":"77056",
    "sg:province":"TX",
    "sg:tags":[
        "loan",
        "mortgage",
        "real estate"
    ],
    "wof:name":"New Century Mortgage Corp",
    "wof:placetype":"venue"
},
  "geometry": {"coordinates":[-95.46064200000001,29.733931],"type":"Point"}
}