{
  "type": "Feature",
  "properties": {
    "iso:country":"US",
    "sg:address":"1346 Chemical St",
    "sg:city":"Dallas",
    "sg:classifiers":[
        {
            "category":"Wholesale",
            "subcategory":"Painting Supplies",
            "type":"Manufacturing & Wholesale Goods"
        }
    ],
    "sg:phone":"+1 214 631 4655",
    "sg:postcode":"75207",
    "sg:province":"TX",
    "sg:tags":[
        "wallpaper",
        "wallcoverings-wholesale",
        "manufacturer"
    ],
    "sg:website":"http://www.menuboards.net",
    "wof:name":"Greensteel Chalkboards",
    "wof:placetype":"venue"
},
  "geometry": {"coordinates":[-96.839647,32.802175],"type":"Point"}
}