{
  "type": "Feature",
  "properties": {
    "iso:country":"US",
    "sg:address":"915 S Crockett St",
    "sg:city":"Sherman",
    "sg:classifiers":[
        {
            "category":"Organizations",
            "subcategory":"Membership Organization",
            "type":"Services"
        }
    ],
    "sg:phone":"+1 903 893 4067",
    "sg:postcode":"75090",
    "sg:province":"TX",
    "sg:tags":[
        "historical"
    ],
    "sg:website":"www.shermanpreservationleague.net",
    "wof:name":"Sherman Preservation League",
    "wof:placetype":"venue"
},
  "geometry": {"coordinates":[-96.60821199999999,33.627835],"type":"Point"}
}