{
  "type": "Feature",
  "properties": {
    "iso:country":"US",
    "sg:address":"11711 Whisper Dew St",
    "sg:city":"San Antonio",
    "sg:classifiers":[
        {
            "category":"Wholesale",
            "subcategory":"Computers",
            "type":"Manufacturing & Wholesale Goods"
        }
    ],
    "sg:phone":"+1 210 408 6142",
    "sg:postcode":"78230",
    "sg:province":"TX",
    "sg:tags":[
        "equipment",
        "processing",
        "datum"
    ],
    "wof:name":"MCPC",
    "wof:placetype":"venue"
},
  "geometry": {"coordinates":[-98.54333099999999,29.548686],"type":"Point"}
}