{
  "type": "Feature",
  "properties": {
    "iso:country":"US",
    "sg:address":"320 Magnolia Blvd",
    "sg:city":"Magnolia",
    "sg:classifiers":[
        {
            "category":"Bars & Pubs",
            "type":"Food & Drink"
        }
    ],
    "sg:menulink":"http://www.allmenus.com/tx/magnolia/63740-bar-b-que-hut/menu/",
    "sg:phone":"+1 281 259 7706",
    "sg:postcode":"77355",
    "sg:province":"TX",
    "sg:tags":[
        "barbecue",
        "american"
    ],
    "wof:name":"Bar-b-que Hut",
    "wof:placetype":"venue"
},
  "geometry": {"coordinates":[-95.74887699999999,30.208286],"type":"Point"}
}