{
  "type": "Feature",
  "properties": {
    "iso:country":"US",
    "sg:address":"4801 Katy Fwy",
    "sg:city":"Houston",
    "sg:classifiers":[
        {
            "category":"Insurance",
            "subcategory":"Hazard Insurance",
            "type":"Services"
        }
    ],
    "sg:phone":"+1 713 229 8330",
    "sg:postcode":"77007",
    "sg:province":"TX",
    "sg:tags":[
        "bond"
    ],
    "wof:name":"Aachen Bail Bond Co",
    "wof:placetype":"venue"
},
  "geometry": {"coordinates":[-95.410707,29.777046],"type":"Point"}
}