{
  "type": "Feature",
  "properties": {
    "iso:country":"US",
    "sg:address":"116 S Stanton St",
    "sg:city":"El Paso",
    "sg:classifiers":[
        {
            "category":"Shopping",
            "subcategory":"Crafts & Fabrics",
            "type":"Retail Goods"
        }
    ],
    "sg:phone":"+1 915 542 3449",
    "sg:postcode":"79901",
    "sg:province":"TX",
    "sg:tags":[
        "sewing"
    ],
    "wof:name":"La Cubana Telas 15",
    "wof:placetype":"venue"
},
  "geometry": {"coordinates":[-106.48558300000001,31.757776],"type":"Point"}
}