{
  "type": "Feature",
  "properties": {
    "iso:country":"US",
    "sg:address":"5002 Morningside Dr",
    "sg:city":"Houston",
    "sg:classifiers":[
        {
            "category":"Wholesale",
            "subcategory":"Computers",
            "type":"Manufacturing & Wholesale Goods"
        },
        {
            "category":"Professional",
            "subcategory":"Computer Services",
            "type":"Services"
        }
    ],
    "sg:phone":"+1 713 520 0033",
    "sg:postcode":"77005",
    "sg:province":"TX",
    "sg:tags":[
        "repair"
    ],
    "wof:name":"Hewlett Packard Sales & Service",
    "wof:placetype":"venue"
},
  "geometry": {"coordinates":[-95.4151,29.7213],"type":"Point"}
}