{
  "type": "Feature",
  "properties": {
    "iso:country":"US",
    "sg:address":"1911 Liberty St",
    "sg:city":"League City",
    "sg:classifiers":[
        {
            "category":"Personal",
            "type":"Services"
        }
    ],
    "sg:phone":"+1 281 332 1749",
    "sg:postcode":"77573",
    "sg:province":"TX",
    "wof:name":"Odor No More",
    "wof:placetype":"venue"
},
  "geometry": {"coordinates":[-95.077361,29.512386],"type":"Point"}
}