{
  "type": "Feature",
  "properties": {
    "iso:country":"US",
    "sg:address":"1007 Westcrest",
    "sg:city":"Floresville",
    "sg:classifiers":[
        {
            "category":"Freight",
            "type":"Transportation"
        }
    ],
    "sg:phone":"+1 830 393 8361",
    "sg:postcode":"78114",
    "sg:province":"TX",
    "sg:tags":[
        "operator",
        "local",
        "trucking"
    ],
    "wof:name":"Sendejo Trucking",
    "wof:placetype":"venue"
},
  "geometry": {"coordinates":[-98.174172,29.148709],"type":"Point"}
}