{
  "type": "Feature",
  "properties": {
    "iso:country":"US",
    "sg:address":"910 Cedar Dr",
    "sg:city":"La Marque",
    "sg:classifiers":[
        {
            "category":"Building & Trades",
            "subcategory":"Plumbing",
            "type":"Services"
        }
    ],
    "sg:phone":"+1 409 938 4021",
    "sg:postcode":"77568",
    "sg:province":"TX",
    "sg:tags":[
        "air",
        "heating",
        "conditioning",
        "contractor"
    ],
    "wof:name":"Gamblina AC & Htg",
    "wof:placetype":"venue"
},
  "geometry": {"coordinates":[-94.962341,29.373352],"type":"Point"}
}