{
  "type": "Feature",
  "properties": {
    "iso:country":"US",
    "sg:address":"17425 Dallas Pkwy Ste 159",
    "sg:city":"Dallas",
    "sg:classifiers":[
        {
            "category":"Building & Trades",
            "subcategory":"Locksmith",
            "type":"Services"
        }
    ],
    "sg:phone":"+1 469 532 2768",
    "sg:postcode":"75287",
    "sg:province":"TX",
    "sg:tags":[
        "key"
    ],
    "wof:name":"The Dallas Locksmith",
    "wof:placetype":"venue"
},
  "geometry": {"coordinates":[-96.82933300000001,32.98758],"type":"Point"}
}