{
  "type": "Feature",
  "properties": {
    "iso:country":"US",
    "sg:address":"1001 N Beckley Ave",
    "sg:city":"Desoto",
    "sg:classifiers":[
        {
            "category":"Shopping",
            "subcategory":"Stationery & Office Supplies",
            "type":"Retail Goods"
        }
    ],
    "sg:phone":"+1 972 228 9990",
    "sg:postcode":"75115",
    "sg:province":"TX",
    "sg:website":"www.officedepot.com",
    "wof:name":"Office Depot",
    "wof:placetype":"venue"
},
  "geometry": {"coordinates":[-96.823487,32.605514],"type":"Point"}
}