{
  "type": "Feature",
  "properties": {
    "iso:country":"US",
    "sg:address":"3744 W Ledbetter Dr",
    "sg:city":"Dallas",
    "sg:classifiers":[
        {
            "category":"Real Estate",
            "subcategory":"Real Estate Agent",
            "type":"Services"
        }
    ],
    "sg:phone":"+1 214 333 3334",
    "sg:postcode":"75233",
    "sg:province":"TX",
    "wof:name":"Group 12 Realty Co",
    "wof:placetype":"venue"
},
  "geometry": {"coordinates":[-96.881325,32.691213],"type":"Point"}
}