{
  "type": "Feature",
  "properties": {
    "iso:country":"US",
    "sg:address":"10300 Wilcrest Dr",
    "sg:city":"Houston",
    "sg:classifiers":[
        {
            "category":"Autos & Motor Vehicles",
            "subcategory":"Automobile Sales",
            "type":"Retail Goods"
        }
    ],
    "sg:phone":"+1 281 274 8585",
    "sg:postcode":"77099",
    "sg:province":"TX",
    "sg:tags":[
        "used"
    ],
    "wof:name":"Taxes Auto Field",
    "wof:placetype":"venue"
},
  "geometry": {"coordinates":[-95.57034899999999,29.671996],"type":"Point"}
}