{
  "type": "Feature",
  "properties": {
    "iso:country":"US",
    "sg:address":"1411 W 18th St",
    "sg:city":"Weslaco",
    "sg:classifiers":[
        {
            "category":"Shopping",
            "subcategory":"Bicycles & Sporting Goods",
            "type":"Retail Goods"
        }
    ],
    "sg:phone":"+1 956 968 1142",
    "sg:postcode":"78596",
    "sg:province":"TX",
    "wof:name":"Stokes Gun Repair",
    "wof:placetype":"venue"
},
  "geometry": {"coordinates":[-98.001311,26.140631],"type":"Point"}
}