{
  "type": "Feature",
  "properties": {
    "iso:country":"US",
    "sg:address":"5463 Beechnut St",
    "sg:city":"Houston",
    "sg:classifiers":[
        {
            "category":"Professional",
            "subcategory":"Lawyer & Legal Services",
            "type":"Services"
        }
    ],
    "sg:phone":"+1 713 667 2554",
    "sg:postcode":"77096",
    "sg:province":"TX",
    "wof:name":"Lw Offc of Mark B Levin",
    "wof:placetype":"venue"
},
  "geometry": {"coordinates":[-95.48157500000001,29.689004],"type":"Point"}
}