{
  "type": "Feature",
  "properties": {
    "iso:country":"US",
    "sg:address":"12680 Fountain Lake Cir",
    "sg:city":"Stafford",
    "sg:classifiers":[
        {
            "category":"Shopping",
            "subcategory":"Hobbies, Toys, & Games",
            "type":"Retail Goods"
        }
    ],
    "sg:phone":"+1 281 240 2122",
    "sg:postcode":"77477",
    "sg:province":"TX",
    "sg:tags":[
        "craft",
        "supply"
    ],
    "wof:name":"Hobby Lobby Creative Center",
    "wof:placetype":"venue"
},
  "geometry": {"coordinates":[-95.58672900000001,29.636795],"type":"Point"}
}