{
  "type": "Feature",
  "properties": {
    "iso:country":"US",
    "sg:address":"404 N Columbia St",
    "sg:city":"Angleton",
    "sg:classifiers":[
        {
            "category":"Organizations",
            "subcategory":"Religious Organization",
            "type":"Services"
        }
    ],
    "sg:phone":"+1 979 549 0959",
    "sg:postcode":"77515",
    "sg:province":"TX",
    "sg:tags":[
        "church"
    ],
    "wof:name":"First Missionary Baptist Chr",
    "wof:placetype":"venue"
},
  "geometry": {"coordinates":[-95.43852699999999,29.168216],"type":"Point"}
}