{
  "type": "Feature",
  "properties": {
    "iso:country":"US",
    "sg:address":"5304 Kayanne Ln",
    "sg:city":"Denton",
    "sg:classifiers":[
        {
            "category":"Professional",
            "type":"Services"
        }
    ],
    "sg:phone":"+1 940 387 4716",
    "sg:postcode":"76208",
    "sg:province":"TX",
    "sg:tags":[
        "field",
        "oil"
    ],
    "wof:name":"Griffin Lease Works",
    "wof:placetype":"venue"
},
  "geometry": {"coordinates":[-97.075344,33.202938],"type":"Point"}
}