{
  "type": "Feature",
  "properties": {
    "iso:country":"US",
    "sg:address":"3702 La Reunion Pkwy",
    "sg:city":"Dallas",
    "sg:classifiers":[
        {
            "category":"Cinema",
            "subcategory":"Movie Rental",
            "type":"Entertainment"
        }
    ],
    "sg:phone":"+1 214 239 2880",
    "sg:postcode":"75212",
    "sg:province":"TX",
    "sg:tags":[
        "game",
        "video"
    ],
    "wof:name":"Movie Trading Company",
    "wof:placetype":"venue"
},
  "geometry": {"coordinates":[-96.882651,32.77087],"type":"Point"}
}