{
  "type": "Feature",
  "properties": {
    "iso:country":"US",
    "sg:address":"901 Main St",
    "sg:city":"Dallas",
    "sg:classifiers":[
        {
            "category":"Personal",
            "subcategory":"Beauty Salon",
            "type":"Services"
        }
    ],
    "sg:phone":"+1 214 760 9085",
    "sg:postcode":"75202",
    "sg:province":"TX",
    "wof:name":"Michael Raymond Salon",
    "wof:placetype":"venue"
},
  "geometry": {"coordinates":[-96.802984,32.779835],"type":"Point"}
}