{
  "type": "Feature",
  "properties": {
    "iso:country":"US",
    "sg:address":"2308 Fuzz Fairway",
    "sg:city":"Austin",
    "sg:classifiers":[
        {
            "category":"Utilities",
            "subcategory":"Electric",
            "type":"Services"
        }
    ],
    "sg:phone":"+1 512 989 0956",
    "sg:postcode":"78728",
    "sg:province":"TX",
    "wof:name":"Enterpri E Triton",
    "wof:placetype":"venue"
},
  "geometry": {"coordinates":[-97.675417,30.450256],"type":"Point"}
}