{
  "type": "Feature",
  "properties": {
    "iso:country":"US",
    "sg:address":"124 W Castellano Dr",
    "sg:city":"El Paso",
    "sg:classifiers":[
        {
            "category":"Professional",
            "subcategory":"Lawyer & Legal Services",
            "type":"Services"
        }
    ],
    "sg:phone":"+1 915 838 0310",
    "sg:postcode":"79912",
    "sg:province":"TX",
    "sg:tags":[
        "attorney"
    ],
    "wof:name":"James L Carroll Law Office",
    "wof:placetype":"venue"
},
  "geometry": {"coordinates":[-106.510046,31.806849],"type":"Point"}
}