{
  "type": "Feature",
  "properties": {
    "iso:country":"US",
    "sg:address":"14038 Woodstream",
    "sg:city":"San Antonio",
    "sg:classifiers":[
        {
            "category":"Real Estate",
            "subcategory":"Real Estate Agent",
            "type":"Services"
        }
    ],
    "sg:phone":"+1 210 601 1201",
    "sg:postcode":"78231",
    "sg:province":"TX",
    "wof:name":"Gina Grafblack Realtor LLC",
    "wof:placetype":"venue"
},
  "geometry": {"coordinates":[-98.533378,29.574664],"type":"Point"}
}