{
  "type": "Feature",
  "properties": {
    "iso:country":"US",
    "sg:address":"275 W Campbell Rd",
    "sg:city":"Richardson",
    "sg:classifiers":[
        {
            "category":"Utilities",
            "subcategory":"Telephone",
            "type":"Services"
        },
        {
            "category":"Communications",
            "type":"Services"
        }
    ],
    "sg:phone":"+1 972 907 8882",
    "sg:postcode":"75080",
    "sg:province":"TX",
    "sg:tags":[
        "equipment",
        "consultant",
        "telecommunication",
        "system"
    ],
    "wof:name":"Telecommunications Techniques",
    "wof:placetype":"venue"
},
  "geometry": {"coordinates":[-96.720944,32.975357],"type":"Point"}
}