{
  "type": "Feature",
  "properties": {
    "iso:country":"US",
    "sg:address":"115 Meadowview Dr",
    "sg:city":"Justin",
    "sg:classifiers":[
        {
            "category":"Building & Trades",
            "subcategory":"Construction",
            "type":"Services"
        }
    ],
    "sg:phone":"+1 817 489 3409",
    "sg:postcode":"76247",
    "sg:province":"TX",
    "sg:tags":[
        "industrial"
    ],
    "wof:name":"Steel Tek Buildings",
    "wof:placetype":"venue"
},
  "geometry": {"coordinates":[-97.28752900000001,33.085504],"type":"Point"}
}