{
  "type": "Feature",
  "properties": {
    "iso:country":"US",
    "sg:address":"3922 Broadway St",
    "sg:city":"Houston",
    "sg:classifiers":[
        {
            "category":"Insurance",
            "subcategory":"Insurance Agent",
            "type":"Services"
        }
    ],
    "sg:phone":"+1 713 649 2629",
    "sg:postcode":"77087",
    "sg:province":"TX",
    "wof:name":"Amco Insurance Agency",
    "wof:placetype":"venue"
},
  "geometry": {"coordinates":[-95.277474,29.683953],"type":"Point"}
}