{
  "type": "Feature",
  "properties": {
    "iso:country":"US",
    "sg:address":"33002 Tract 43 Rd",
    "sg:city":"Los Fresnos",
    "sg:classifiers":[
        {
            "category":"Building & Trades",
            "subcategory":"Construction",
            "type":"Services"
        }
    ],
    "sg:phone":"+1 956 233 5495",
    "sg:postcode":"78566",
    "sg:province":"TX",
    "sg:tags":[
        "contractor"
    ],
    "wof:name":"Sanchez Construction Inc",
    "wof:placetype":"venue"
},
  "geometry": {"coordinates":[-97.444265,26.080595],"type":"Point"}
}