{
  "type": "Feature",
  "properties": {
    "iso:country":"US",
    "sg:address":"3902 Thomason Dr",
    "sg:city":"Midland",
    "sg:classifiers":[
        {
            "category":"Professional",
            "subcategory":"Management & Consulting",
            "type":"Services"
        }
    ],
    "sg:phone":"+1 432 689 6092",
    "sg:postcode":"79703",
    "sg:province":"TX",
    "sg:tags":[
        "business"
    ],
    "wof:name":"Mongo Consulting",
    "wof:placetype":"venue"
},
  "geometry": {"coordinates":[-102.122356,31.980189],"type":"Point"}
}