{
  "type": "Feature",
  "properties": {
    "iso:country":"US",
    "sg:address":"9 Grants Lake",
    "sg:city":"San Antonio",
    "sg:classifiers":[
        {
            "category":"Banks & Credit Unions",
            "subcategory":"Financial Services",
            "type":"Services"
        }
    ],
    "sg:phone":"+1 210 492 5985",
    "sg:postcode":"78248",
    "sg:province":"TX",
    "sg:tags":[
        "company",
        "holding"
    ],
    "wof:name":"Severson Assoc I LLC",
    "wof:placetype":"venue"
},
  "geometry": {"coordinates":[-98.536891,29.596468],"type":"Point"}
}