{
  "type": "Feature",
  "properties": {
    "iso:country":"US",
    "sg:address":"1502 Austin St",
    "sg:city":"South Houston",
    "sg:classifiers":[
        {
            "category":"Wholesale",
            "subcategory":"Construction Materials",
            "type":"Manufacturing & Wholesale Goods"
        }
    ],
    "sg:phone":"+1 713 946 8444",
    "sg:postcode":"77587",
    "sg:province":"TX",
    "sg:tags":[
        "fiberglass",
        "building"
    ],
    "wof:name":"Johnson Fiberglass Company",
    "wof:placetype":"venue"
},
  "geometry": {"coordinates":[-95.242459,29.656081],"type":"Point"}
}