{
  "type": "Feature",
  "properties": {
    "iso:country":"US",
    "sg:address":"7931 Masterson St",
    "sg:city":"Houston",
    "sg:classifiers":[
        {
            "category":"Freight",
            "type":"Transportation"
        }
    ],
    "sg:phone":"+1 713 673 3591",
    "sg:postcode":"77029",
    "sg:province":"TX",
    "sg:tags":[
        "truck",
        "hauling",
        "dump"
    ],
    "wof:name":"Garcia Trucking",
    "wof:placetype":"venue"
},
  "geometry": {"coordinates":[-95.28556,29.754324],"type":"Point"}
}