{
  "type": "Feature",
  "properties": {
    "iso:country":"US",
    "sg:address":"6460 Las Colinas Blvd",
    "sg:city":"Irving",
    "sg:classifiers":[
        {
            "category":"Banks & Credit Unions",
            "subcategory":"Bank",
            "type":"Services"
        }
    ],
    "sg:phone":"+1 972 869 1456",
    "sg:postcode":"75039",
    "sg:province":"TX",
    "wof:name":"Citi",
    "wof:placetype":"venue"
},
  "geometry": {"coordinates":[-96.95187,32.902838],"type":"Point"}
}