{
  "type": "Feature",
  "properties": {
    "iso:country":"US",
    "sg:address":"2218 Bird Island Dr",
    "sg:city":"Corpus Christi",
    "sg:classifiers":[
        {
            "category":"Building & Trades",
            "subcategory":"Construction",
            "type":"Services"
        }
    ],
    "sg:phone":"+1 361 937 0099",
    "sg:postcode":"78418",
    "sg:province":"TX",
    "sg:tags":[
        "equipment",
        "installation"
    ],
    "wof:name":"Ortega Belvia",
    "wof:placetype":"venue"
},
  "geometry": {"coordinates":[-97.28855,27.647037],"type":"Point"}
}