{
  "type": "Feature",
  "properties": {
    "iso:country":"US",
    "sg:address":"22906 US Highway 281 N",
    "sg:city":"San Antonio",
    "sg:classifiers":[
        {
            "category":"Shopping",
            "subcategory":"Optician",
            "type":"Retail Goods"
        }
    ],
    "sg:phone":"+1 210 495 7483",
    "sg:postcode":"78258",
    "sg:province":"TX",
    "sg:tags":[
        "eyewear"
    ],
    "wof:name":"Leesang's Eyesite",
    "wof:placetype":"venue"
},
  "geometry": {"coordinates":[-98.449313,29.656057],"type":"Point"}
}