{
  "type": "Feature",
  "properties": {
    "iso:country":"US",
    "sg:address":"6121 W Park Blvd",
    "sg:city":"Plano",
    "sg:classifiers":[
        {
            "category":"Shopping",
            "type":"Retail Goods"
        }
    ],
    "sg:postcode":"75093",
    "sg:province":"TX",
    "sg:website":"www.dichosbooks.com",
    "wof:name":"Dicho's Books & More",
    "wof:placetype":"venue"
},
  "geometry": {"coordinates":[-96.83336799999999,33.031383],"type":"Point"}
}