{
  "type": "Feature",
  "properties": {
    "iso:country":"US",
    "sg:address":"9300 Hammerly Blvd",
    "sg:city":"Houston",
    "sg:classifiers":[
        {
            "category":"Organizations",
            "subcategory":"Religious Organization",
            "type":"Services"
        }
    ],
    "sg:phone":"+1 713 467 2763",
    "sg:postcode":"77080",
    "sg:province":"TX",
    "wof:name":"Westside Baptist Church",
    "wof:placetype":"venue"
},
  "geometry": {"coordinates":[-95.519459,29.809856],"type":"Point"}
}