{
  "type": "Feature",
  "properties": {
    "iso:country":"US",
    "sg:address":"209 NW 12th St",
    "sg:city":"Andrews",
    "sg:classifiers":[
        {
            "category":"Mining & Drilling",
            "type":"Manufacturing & Wholesale Goods"
        }
    ],
    "sg:phone":"+1 432 524 2277",
    "sg:postcode":"79714",
    "sg:province":"TX",
    "sg:tags":[
        "oil",
        "gas",
        "producer"
    ],
    "sg:website":"www.apachecorp.com",
    "wof:name":"Apache Corp",
    "wof:placetype":"venue"
},
  "geometry": {"coordinates":[-102.561502,32.317424],"type":"Point"}
}