{
  "type": "Feature",
  "properties": {
    "iso:country":"US",
    "sg:address":"13911 Cambourne Dr",
    "sg:city":"Pflugerville",
    "sg:classifiers":[
        {
            "category":"Professional",
            "subcategory":"Business Services",
            "type":"Services"
        }
    ],
    "sg:phone":"+1 512 989 0929",
    "sg:postcode":"78660",
    "sg:province":"TX",
    "wof:name":"Ravei Business Services & Mana",
    "wof:placetype":"venue"
},
  "geometry": {"coordinates":[-97.649162,30.415127],"type":"Point"}
}