{
  "type": "Feature",
  "properties": {
    "iso:country":"US",
    "sg:address":"7006 University Ave",
    "sg:city":"Lubbock",
    "sg:classifiers":[
        {
            "category":"Shopping",
            "subcategory":"Discount & Variety Stores",
            "type":"Retail Goods"
        }
    ],
    "sg:phone":"+1 806 748 6043",
    "sg:postcode":"79413",
    "sg:province":"TX",
    "sg:tags":[
        "merchandise",
        "general"
    ],
    "wof:name":"Dollar Deals LLC",
    "wof:placetype":"venue"
},
  "geometry": {"coordinates":[-101.870482,33.530442],"type":"Point"}
}