{
  "type": "Feature",
  "properties": {
    "iso:country":"US",
    "sg:address":"2238 Woodwind Way",
    "sg:city":"League City",
    "sg:classifiers":[
        {
            "category":"Professional",
            "subcategory":"Business Services",
            "type":"Services"
        }
    ],
    "sg:phone":"+1 281 332 9070",
    "sg:postcode":"77573",
    "sg:province":"TX",
    "wof:name":"Suncatcher Enterprises",
    "wof:placetype":"venue"
},
  "geometry": {"coordinates":[-95.076756,29.525672],"type":"Point"}
}