{
  "type": "Feature",
  "properties": {
    "iso:country":"US",
    "sg:address":"506 Medical Center Blvd",
    "sg:city":"Conroe",
    "sg:classifiers":[
        {
            "category":"Health Services",
            "subcategory":"Doctor",
            "type":"Services"
        }
    ],
    "sg:phone":"+1 936 760 4435",
    "sg:postcode":"77304",
    "sg:province":"TX",
    "sg:tags":[
        "clinic",
        "medical"
    ],
    "wof:name":"Schulte Jayne R MD",
    "wof:placetype":"venue"
},
  "geometry": {"coordinates":[-95.46510499999999,30.285905],"type":"Point"}
}