{
  "type": "Feature",
  "properties": {
    "iso:country":"US",
    "sg:address":"1300 Patricia Dr",
    "sg:city":"San Antonio",
    "sg:classifiers":[
        {
            "category":"Professional",
            "type":"Services"
        }
    ],
    "sg:phone":"+1 210 366 2499",
    "sg:postcode":"78213",
    "sg:province":"TX",
    "wof:name":"Fish Guy",
    "wof:placetype":"venue"
},
  "geometry": {"coordinates":[-98.51718200000001,29.547682],"type":"Point"}
}