{
  "type": "Feature",
  "properties": {
    "iso:country":"US",
    "sg:address":"425 Sunrise Ln",
    "sg:city":"Coleman",
    "sg:classifiers":[
        {
            "category":"Freight",
            "type":"Transportation"
        }
    ],
    "sg:phone":"+1 325 625 5050",
    "sg:postcode":"76834",
    "sg:province":"TX",
    "sg:tags":[
        "operator",
        "local",
        "trucking"
    ],
    "wof:name":"James E Priddy",
    "wof:placetype":"venue"
},
  "geometry": {"coordinates":[-99.42402199999999,31.862946],"type":"Point"}
}