{
  "type": "Feature",
  "properties": {
    "iso:country":"US",
    "sg:address":"3007 Sierra Ct",
    "sg:city":"Mission",
    "sg:classifiers":[
        {
            "category":"Building & Trades",
            "subcategory":"Construction",
            "type":"Services"
        }
    ],
    "sg:phone":"+1 956 583 3576",
    "sg:postcode":"78574",
    "sg:province":"TX",
    "sg:tags":[
        "home",
        "builder"
    ],
    "wof:name":"Obra Homes Inc",
    "wof:placetype":"venue"
},
  "geometry": {"coordinates":[-98.313517,26.236782],"type":"Point"}
}