{
  "type": "Feature",
  "properties": {
    "iso:country":"US",
    "sg:address":"7800 N Navarro St Ste 149",
    "sg:city":"Victoria",
    "sg:classifiers":[
        {
            "category":"Shopping",
            "subcategory":"Jewelry",
            "type":"Retail Goods"
        },
        {
            "category":"Manufacturing",
            "subcategory":"Jewelry",
            "type":"Manufacturing & Wholesale Goods"
        }
    ],
    "sg:phone":"+1 361 576 3126",
    "sg:postcode":"77904",
    "sg:province":"TX",
    "sg:tags":[
        "stone",
        "designer",
        "semi-precious",
        "precious",
        "jeweler"
    ],
    "sg:website":"http://www.zales.com",
    "wof:name":"Zales Jewelers",
    "wof:placetype":"venue"
},
  "geometry": {"coordinates":[-96.997372,28.866763],"type":"Point"}
}