{
  "type": "Feature",
  "properties": {
    "iso:country":"US",
    "sg:address":"17820 Campbell Rd",
    "sg:city":"Dallas",
    "sg:classifiers":[
        {
            "category":"Education",
            "subcategory":"School",
            "type":"Public Place"
        }
    ],
    "sg:phone":"+1 469 752 1400",
    "sg:postcode":"75252",
    "sg:province":"TX",
    "wof:name":"Plano Isd",
    "wof:placetype":"venue"
},
  "geometry": {"coordinates":[-96.80619799999999,32.994202],"type":"Point"}
}