{
  "type": "Feature",
  "properties": {
    "iso:country":"US",
    "sg:address":"304 E 11th St",
    "sg:city":"Friona",
    "sg:classifiers":[
        {
            "category":"Health Services",
            "subcategory":"Health Practitioner",
            "type":"Services"
        }
    ],
    "sg:phone":"+1 806 247 0057",
    "sg:postcode":"79035",
    "sg:province":"TX",
    "sg:tags":[
        "home"
    ],
    "wof:name":"Bluebonnet Home Health & Hospices",
    "wof:placetype":"venue"
},
  "geometry": {"coordinates":[-102.73101,34.641729],"type":"Point"}
}