{
  "type": "Feature",
  "properties": {
    "iso:country":"US",
    "sg:address":"8430 White Settlement Rd",
    "sg:city":"Fort Worth",
    "sg:classifiers":[
        {
            "category":"Personal",
            "subcategory":"Beauty Salon",
            "type":"Services"
        }
    ],
    "sg:phone":"+1 817 246 7001",
    "sg:postcode":"76108",
    "sg:province":"TX",
    "sg:tags":[
        "shop"
    ],
    "wof:name":"City Care Salon",
    "wof:placetype":"venue"
},
  "geometry": {"coordinates":[-97.465321,32.759889],"type":"Point"}
}