{
  "type": "Feature",
  "properties": {
    "iso:country":"US",
    "sg:address":"2923 Gladiolus Ln",
    "sg:city":"Dallas",
    "sg:classifiers":[
        {
            "category":"Social Services",
            "type":"Services"
        }
    ],
    "sg:phone":"+1 214 331 3086",
    "sg:postcode":"75233",
    "sg:province":"TX",
    "wof:name":"Roosevelt Handicap Homeun",
    "wof:placetype":"venue"
},
  "geometry": {"coordinates":[-96.864476,32.695147],"type":"Point"}
}