{
  "type": "Feature",
  "properties": {
    "iso:country":"US",
    "sg:address":"1120 N Ross Ave",
    "sg:city":"Mexia",
    "sg:classifiers":[
        {
            "category":"Education",
            "subcategory":"School",
            "type":"Public Place"
        }
    ],
    "sg:phone":"+1 254 562 4010",
    "sg:postcode":"76667",
    "sg:province":"TX",
    "sg:website":"www.mexia.k12.tx.us",
    "wof:name":"Mexia High School",
    "wof:placetype":"venue"
},
  "geometry": {"coordinates":[-96.474895,31.693684],"type":"Point"}
}