{
  "type": "Feature",
  "properties": {
    "iso:country":"US",
    "sg:address":"7510 Frenchton St",
    "sg:city":"San Antonio",
    "sg:classifiers":[
        {
            "category":"Retail",
            "subcategory":"Auto Repair",
            "type":"Services"
        }
    ],
    "sg:phone":"+1 210 520 5379",
    "sg:postcode":"78251",
    "sg:province":"TX",
    "sg:tags":[
        "body"
    ],
    "wof:name":"Taiym Enterprises Inc",
    "wof:placetype":"venue"
},
  "geometry": {"coordinates":[-98.63830799999999,29.455315],"type":"Point"}
}