{
  "type": "Feature",
  "properties": {
    "iso:country":"US",
    "sg:address":"13301 East Fwy",
    "sg:city":"Houston",
    "sg:classifiers":[
        {
            "category":"Professional",
            "subcategory":"Lawyer & Legal Services",
            "type":"Services"
        }
    ],
    "sg:phone":"+1 713 453 6339",
    "sg:postcode":"77015",
    "sg:province":"TX",
    "wof:name":"Haddad Carl D Atty",
    "wof:placetype":"venue"
},
  "geometry": {"coordinates":[-95.182503,29.7864],"type":"Point"}
}