{
  "type": "Feature",
  "properties": {
    "iso:country":"US",
    "sg:address":"3144 Fm 528 Rd",
    "sg:city":"Webster",
    "sg:classifiers":[
        {
            "category":"Personal",
            "subcategory":"Nail Salon",
            "type":"Services"
        }
    ],
    "sg:phone":"+1 281 992 2177",
    "sg:postcode":"77598",
    "sg:province":"TX",
    "wof:name":"La Rosa Nail Salon",
    "wof:placetype":"venue"
},
  "geometry": {"coordinates":[-95.160906,29.52241],"type":"Point"}
}