{
  "type": "Feature",
  "properties": {
    "iso:country":"US",
    "sg:address":"701 Hanover Dr Ste 450",
    "sg:city":"Grapevine",
    "sg:classifiers":[
        {
            "category":"Transit Center",
            "subcategory":"Freight",
            "type":"Transportation"
        }
    ],
    "sg:phone":"+1 817 442 1012",
    "sg:postcode":"76051",
    "sg:province":"TX",
    "sg:tags":[
        "container",
        "broker"
    ],
    "wof:name":"Mt Global Freight Solutions Inc",
    "wof:placetype":"venue"
},
  "geometry": {"coordinates":[-97.06953900000001,32.926616],"type":"Point"}
}