{
  "type": "Feature",
  "properties": {
    "iso:country":"US",
    "sg:address":"1116 Dobie Dr",
    "sg:city":"Plano",
    "sg:classifiers":[
        {
            "category":"Professional",
            "subcategory":"Accounting & Tax Preparation",
            "type":"Services"
        }
    ],
    "sg:phone":"+1 972 424 7596",
    "sg:postcode":"75074",
    "sg:province":"TX",
    "sg:tags":[
        "accountant"
    ],
    "wof:name":"Donald R Barker CPA",
    "wof:placetype":"venue"
},
  "geometry": {"coordinates":[-96.697424,33.035556],"type":"Point"}
}