{
  "type": "Feature",
  "properties": {
    "iso:country":"US",
    "sg:address":"16103 April Ridge Dr",
    "sg:city":"Houston",
    "sg:classifiers":[
        {
            "category":"Manufacturing",
            "subcategory":"Leather Goods",
            "type":"Manufacturing & Wholesale Goods"
        }
    ],
    "sg:phone":"+1 281 277 3515",
    "sg:postcode":"77083",
    "sg:province":"TX",
    "sg:tags":[
        "mfg"
    ],
    "wof:name":"Handbags R US",
    "wof:placetype":"venue"
},
  "geometry": {"coordinates":[-95.670378,29.683481],"type":"Point"}
}