{
  "type": "Feature",
  "properties": {
    "iso:country":"US",
    "sg:address":"2107 Clover Ln",
    "sg:city":"Fort Worth",
    "sg:classifiers":[
        {
            "category":"Retail",
            "subcategory":"Repair Shop",
            "type":"Services"
        }
    ],
    "sg:phone":"+1 817 926 8812",
    "sg:postcode":"76107",
    "sg:province":"TX",
    "sg:tags":[
        "upholsterer"
    ],
    "wof:name":"Best Upholstery & Headliner",
    "wof:placetype":"venue"
},
  "geometry": {"coordinates":[-97.378438,32.739452],"type":"Point"}
}