{
  "type": "Feature",
  "properties": {
    "iso:country":"US",
    "sg:address":"134 N 8th St",
    "sg:city":"Midlothian",
    "sg:classifiers":[
        {
            "category":"Personal",
            "subcategory":"Massage",
            "type":"Services"
        },
        {
            "category":"Personal",
            "subcategory":"Beauty Salon",
            "type":"Services"
        },
        {
            "category":"Personal",
            "subcategory":"Day Spa",
            "type":"Services"
        }
    ],
    "sg:phone":"+1 972 775 2404",
    "sg:postcode":"76065",
    "sg:province":"TX",
    "sg:tags":[
        "body",
        "hair",
        "therapist",
        "stylist",
        "wrap"
    ],
    "sg:website":"http://www.spa-vita.com",
    "wof:name":"Spa Vita",
    "wof:placetype":"venue"
},
  "geometry": {"coordinates":[-96.994482,32.482587],"type":"Point"}
}