{
  "type": "Feature",
  "properties": {
    "iso:country":"US",
    "sg:address":"4553 Jimmy Doolittle Dr",
    "sg:city":"Addison",
    "sg:classifiers":[
        {
            "category":"Airport",
            "type":"Transportation"
        }
    ],
    "sg:phone":"+1 972 385 8088",
    "sg:postcode":"75001",
    "sg:province":"TX",
    "sg:tags":[
        "aircraft",
        "upholsterer"
    ],
    "wof:name":"JBS Interiors",
    "wof:placetype":"venue"
},
  "geometry": {"coordinates":[-96.83244999999999,32.967798],"type":"Point"}
}