{
  "type": "Feature",
  "properties": {
    "iso:country":"US",
    "sg:address":"13420 Preston Rd",
    "sg:city":"Dallas",
    "sg:classifiers":[
        {
            "category":"Shopping",
            "subcategory":"Computers & Home Electronics",
            "type":"Retail Goods"
        }
    ],
    "sg:phone":"+1 972 661 1443",
    "sg:postcode":"75240",
    "sg:province":"TX",
    "sg:tags":[
        "high",
        "fidelity",
        "stereophonic"
    ],
    "sg:website":"www.stereoeast.com",
    "wof:name":"Stereo East",
    "wof:placetype":"venue"
},
  "geometry": {"coordinates":[-96.803489,32.931713],"type":"Point"}
}