{
  "type": "Feature",
  "properties": {
    "iso:country":"US",
    "sg:address":"3038 Ravine Trl",
    "sg:city":"Carrollton",
    "sg:classifiers":[
        {
            "category":"Wholesale",
            "subcategory":"Machinery & Supplies",
            "type":"Manufacturing & Wholesale Goods"
        }
    ],
    "sg:phone":"+1 972 242 6203",
    "sg:postcode":"75007",
    "sg:province":"TX",
    "sg:tags":[
        "industrial"
    ],
    "wof:name":"Core Industrial Supply",
    "wof:placetype":"venue"
},
  "geometry": {"coordinates":[-96.875174,32.999176],"type":"Point"}
}