{
  "type": "Feature",
  "properties": {
    "iso:country":"US",
    "sg:address":"5610 Rowlett Rd",
    "sg:city":"Rowlett",
    "sg:classifiers":[
        {
            "category":"Shopping",
            "subcategory":"Discount & Variety Stores",
            "type":"Retail Goods"
        }
    ],
    "sg:phone":"+1 972 463 3709",
    "sg:postcode":"75089",
    "sg:province":"TX",
    "wof:name":"Dollar General",
    "wof:placetype":"venue"
},
  "geometry": {"coordinates":[-96.56958299999999,32.91205],"type":"Point"}
}