{
  "type": "Feature",
  "properties": {
    "iso:country":"US",
    "sg:address":"5230 Abercreek St",
    "sg:city":"Friendswood",
    "sg:classifiers":[
        {
            "category":"Recreation",
            "type":"Entertainment"
        }
    ],
    "sg:phone":"+1 281 992 4952",
    "sg:postcode":"77546",
    "sg:province":"TX",
    "sg:tags":[
        "guide"
    ],
    "wof:name":"Jeff's Guide Svc",
    "wof:placetype":"venue"
},
  "geometry": {"coordinates":[-95.183205,29.531833],"type":"Point"}
}