{
  "type": "Feature",
  "properties": {
    "iso:country":"US",
    "sg:address":"2101 E Renner Rd",
    "sg:city":"Richardson",
    "sg:classifiers":[
        {
            "category":"Social Services",
            "subcategory":"Child Care",
            "type":"Services"
        }
    ],
    "sg:phone":"+1 214 570 5608",
    "sg:postcode":"75082",
    "sg:province":"TX",
    "sg:tags":[
        "day"
    ],
    "wof:name":"Promiseland Learning Center",
    "wof:placetype":"venue"
},
  "geometry": {"coordinates":[-96.685288,32.997292],"type":"Point"}
}