{
  "type": "Feature",
  "properties": {
    "iso:country":"US",
    "sg:address":"7721 Helmers St",
    "sg:city":"Houston",
    "sg:classifiers":[
        {
            "category":"Organizations",
            "subcategory":"Religious Organization",
            "type":"Services"
        }
    ],
    "sg:phone":"+1 713 692 3281",
    "sg:postcode":"77022",
    "sg:province":"TX",
    "sg:tags":[
        "baptist",
        "church"
    ],
    "wof:name":"Helmers Street Baptist Church",
    "wof:placetype":"venue"
},
  "geometry": {"coordinates":[-95.365843,29.830207],"type":"Point"}
}