{
  "type": "Feature",
  "properties": {
    "iso:country":"US",
    "sg:address":"312 Legion Dr W",
    "sg:city":"Converse",
    "sg:classifiers":[
        {
            "category":"Organizations",
            "subcategory":"Religious Organization",
            "type":"Services"
        }
    ],
    "sg:phone":"+1 210 658 8093",
    "sg:postcode":"78109",
    "sg:province":"TX",
    "wof:name":"Northast Hspanic Baptst Church",
    "wof:placetype":"venue"
},
  "geometry": {"coordinates":[-98.317882,29.513482],"type":"Point"}
}