{
  "type": "Feature",
  "properties": {
    "iso:country":"US",
    "sg:address":"301 Milligan Dr",
    "sg:city":"Pittsburg",
    "sg:classifiers":[
        {
            "category":"Retail",
            "subcategory":"Auto Repair",
            "type":"Services"
        }
    ],
    "sg:phone":"+1 903 856 5513",
    "sg:postcode":"75686",
    "sg:province":"TX",
    "sg:tags":[
        "repairing",
        "automobile",
        "station",
        "gasoline",
        "general"
    ],
    "wof:name":"Blount's Garage",
    "wof:placetype":"venue"
},
  "geometry": {"coordinates":[-94.964507,32.989996],"type":"Point"}
}