{
  "type": "Feature",
  "properties": {
    "iso:country":"US",
    "sg:address":"1914 N Forest St",
    "sg:city":"Amarillo",
    "sg:classifiers":[
        {
            "category":"Building & Trades",
            "subcategory":"Construction",
            "type":"Services"
        }
    ],
    "sg:phone":"+1 806 342 5777",
    "sg:postcode":"79106",
    "sg:province":"TX",
    "sg:tags":[
        "contractor"
    ],
    "wof:name":"Melvin R Fowler Builder",
    "wof:placetype":"venue"
},
  "geometry": {"coordinates":[-101.881833,35.227881],"type":"Point"}
}