{
  "type": "Feature",
  "properties": {
    "iso:country":"US",
    "sg:address":"2001 N State Highway 16 A",
    "sg:city":"Llano",
    "sg:classifiers":[
        {
            "category":"Organizations",
            "subcategory":"Membership Organization",
            "type":"Services"
        }
    ],
    "sg:phone":"+1 325 247 1072",
    "sg:postcode":"78643",
    "sg:province":"TX",
    "sg:tags":[
        "environmental",
        "ecological",
        "conservation"
    ],
    "sg:website":"http://www.thc.state.tx.us",
    "wof:name":"Texas Department Of Parks And Wildlife",
    "wof:placetype":"venue"
},
  "geometry": {"coordinates":[-98.678032,30.73658],"type":"Point"}
}