{
  "type": "Feature",
  "properties": {
    "iso:country":"US",
    "sg:address":"1302 Doonesbury Drive",
    "sg:city":"Austin",
    "sg:classifiers":[
        {
            "category":"Food & Beverages",
            "subcategory":"Groceries & Convenience Stores",
            "type":"Retail Goods"
        }
    ],
    "sg:phone":"+1 512 821 1950",
    "sg:postcode":"78758",
    "sg:province":"TX",
    "wof:name":"Community Choice",
    "wof:placetype":"venue"
},
  "geometry": {"coordinates":[-97.691401,30.392655],"type":"Point"}
}