{
  "type": "Feature",
  "properties": {
    "iso:country":"US",
    "sg:address":"16027 Pinyon Creek Dr",
    "sg:city":"Houston",
    "sg:classifiers":[
        {
            "category":"Professional",
            "subcategory":"Business Services",
            "type":"Services"
        },
        {
            "category":"Building & Trades",
            "subcategory":"Construction",
            "type":"Services"
        }
    ],
    "sg:phone":"+1 713 781 7946",
    "sg:postcode":"77095",
    "sg:province":"TX",
    "sg:tags":[
        "coping",
        "plastering",
        "tiling",
        "pool",
        "swimming"
    ],
    "wof:name":"Dual Divinity Aquatics",
    "wof:placetype":"venue"
},
  "geometry": {"coordinates":[-95.65158,29.90018],"type":"Point"}
}