{
  "type": "Feature",
  "properties": {
    "iso:country":"US",
    "sg:address":"712 S Walton Walker Blvd",
    "sg:city":"Dallas",
    "sg:classifiers":[
        {
            "category":"Restaurant",
            "type":"Food & Drink"
        }
    ],
    "sg:phone":"+1 214 467 4567",
    "sg:postcode":"75211",
    "sg:province":"TX",
    "sg:tags":[
        "pizza"
    ],
    "wof:name":"Little Caesars Pizza",
    "wof:placetype":"venue"
},
  "geometry": {"coordinates":[-96.91864,32.739415],"type":"Point"}
}