{
  "type": "Feature",
  "properties": {
    "iso:country":"US",
    "sg:address":"917 Franklin St",
    "sg:city":"Houston",
    "sg:classifiers":[
        {
            "category":"Real Estate",
            "subcategory":"Real Estate Agent",
            "type":"Services"
        }
    ],
    "sg:phone":"+1 713 227 2570",
    "sg:postcode":"77002",
    "sg:province":"TX",
    "wof:name":"New Hyde Park Inc",
    "wof:placetype":"venue"
},
  "geometry": {"coordinates":[-95.36022800000001,29.763145],"type":"Point"}
}