{
  "type": "Feature",
  "properties": {
    "iso:country":"US",
    "sg:address":"7110 Alameda Ave",
    "sg:city":"El Paso",
    "sg:classifiers":[
        {
            "category":"Banks & Credit Unions",
            "subcategory":"Bank",
            "type":"Services"
        }
    ],
    "sg:phone":"+1 915 771 7953",
    "sg:postcode":"79915",
    "sg:province":"TX",
    "sg:tags":[
        "institution",
        "business"
    ],
    "wof:name":"World Acceptance",
    "wof:placetype":"venue"
},
  "geometry": {"coordinates":[-106.39010399999999,31.751793],"type":"Point"}
}