{
  "type": "Feature",
  "properties": {
    "iso:country":"US",
    "sg:address":"4525 Production Dr",
    "sg:city":"Dallas",
    "sg:classifiers":[
        {
            "category":"Manufacturing",
            "subcategory":"Retail Goods",
            "type":"Manufacturing & Wholesale Goods"
        },
        {
            "category":"Manufacturing",
            "subcategory":"Electronics",
            "type":"Manufacturing & Wholesale Goods"
        }
    ],
    "sg:phone":"+1 214 638 8886",
    "sg:postcode":"75235",
    "sg:province":"TX",
    "sg:tags":[
        "equipment",
        "manufacturer",
        "electronic",
        "supply"
    ],
    "wof:name":"F P D Technologies Inc",
    "wof:placetype":"venue"
},
  "geometry": {"coordinates":[-96.82993399999999,32.809345],"type":"Point"}
}