{
  "type": "Feature",
  "properties": {
    "iso:country":"US",
    "sg:address":"3112 Skelly Rd",
    "sg:city":"Bay City",
    "sg:classifiers":[
        {
            "category":"Shopping",
            "subcategory":"Used Merchandise",
            "type":"Retail Goods"
        }
    ],
    "sg:phone":"+1 979 245 2116",
    "sg:postcode":"77414",
    "sg:province":"TX",
    "wof:name":"Emporium The",
    "wof:placetype":"venue"
},
  "geometry": {"coordinates":[-95.953362,28.991775],"type":"Point"}
}