{
  "type": "Feature",
  "properties": {
    "iso:country":"US",
    "sg:address":"303 Woodway Ln",
    "sg:city":"Longview",
    "sg:classifiers":[
        {
            "category":"Manufacturing",
            "subcategory":"Tools & Machinery",
            "type":"Manufacturing & Wholesale Goods"
        }
    ],
    "sg:phone":"+1 903 759 2905",
    "sg:postcode":"75605",
    "sg:province":"TX",
    "sg:tags":[
        "machine",
        "mfg"
    ],
    "wof:name":"Gladen Machine Tool",
    "wof:placetype":"venue"
},
  "geometry": {"coordinates":[-94.791957,32.544229],"type":"Point"}
}