{
  "type": "Feature",
  "properties": {
    "iso:country":"US",
    "sg:address":"101 Pine Place St",
    "sg:city":"Dayton",
    "sg:classifiers":[
        {
            "category":"Retail",
            "subcategory":"Laundry & Dry Cleaning",
            "type":"Services"
        },
        {
            "category":"Building & Trades",
            "subcategory":"Cleaning & Sanitation",
            "type":"Services"
        }
    ],
    "sg:phone":"+1 936 681 8061",
    "sg:postcode":"77535",
    "sg:province":"TX",
    "sg:tags":[
        "cleaner",
        "house"
    ],
    "wof:name":"Cinderellas Cleaning Service",
    "wof:placetype":"venue"
},
  "geometry": {"coordinates":[-94.89812499999999,30.071846],"type":"Point"}
}