{
  "type": "Feature",
  "properties": {
    "iso:country":"US",
    "sg:address":"7435 Burnet Rd",
    "sg:city":"Austin",
    "sg:classifiers":[
        {
            "category":"Professional",
            "subcategory":"Business Services",
            "type":"Services"
        }
    ],
    "sg:phone":"+1 512 583 0646",
    "sg:postcode":"78757",
    "sg:province":"TX",
    "sg:tags":[
        "computer"
    ],
    "wof:name":"American Business Computers",
    "wof:placetype":"venue"
},
  "geometry": {"coordinates":[-97.734497,30.3505],"type":"Point"}
}