{
  "type": "Feature",
  "properties": {
    "iso:country":"US",
    "sg:address":"950 Sylvania Dr",
    "sg:city":"Dallas",
    "sg:classifiers":[
        {
            "category":"Building & Trades",
            "subcategory":"Construction",
            "type":"Services"
        }
    ],
    "sg:phone":"+1 972 896 6813",
    "sg:postcode":"75218",
    "sg:province":"TX",
    "sg:tags":[
        "nonresidential"
    ],
    "wof:name":"Down Construction Services",
    "wof:placetype":"venue"
},
  "geometry": {"coordinates":[-96.69667800000001,32.84368],"type":"Point"}
}