{
  "type": "Feature",
  "properties": {
    "iso:country":"US",
    "sg:address":"5632 Willow Wood Ln",
    "sg:city":"Dallas",
    "sg:classifiers":[
        {
            "category":"Professional",
            "subcategory":"Advertising",
            "type":"Services"
        }
    ],
    "sg:phone":"+1 972 732 7327",
    "sg:postcode":"75252",
    "sg:province":"TX",
    "wof:name":"On Time Promotions",
    "wof:placetype":"venue"
},
  "geometry": {"coordinates":[-96.81238399999999,33.011268],"type":"Point"}
}