{
  "type": "Feature",
  "properties": {
    "iso:country":"US",
    "sg:address":"8910 Leader St",
    "sg:city":"Houston",
    "sg:classifiers":[
        {
            "category":"Wholesale",
            "subcategory":"Apparel",
            "type":"Manufacturing & Wholesale Goods"
        }
    ],
    "sg:phone":"+1 713 779 3817",
    "sg:postcode":"77036",
    "sg:province":"TX",
    "sg:tags":[
        "clothing"
    ],
    "wof:name":"Dynavest Development Corp",
    "wof:placetype":"venue"
},
  "geometry": {"coordinates":[-95.54249,29.703979],"type":"Point"}
}