{
  "type": "Feature",
  "properties": {
    "iso:country":"US",
    "sg:address":"5647 Westheimer Rd",
    "sg:city":"Houston",
    "sg:classifiers":[
        {
            "category":"Shopping",
            "subcategory":"Tobacco",
            "type":"Retail Goods"
        }
    ],
    "sg:phone":"+1 713 629 6200",
    "sg:postcode":"77056",
    "sg:province":"TX",
    "sg:tags":[
        "product",
        "bar"
    ],
    "sg:website":"www.treasureshouston.com/",
    "wof:name":"Treasures",
    "wof:placetype":"venue"
},
  "geometry": {"coordinates":[-95.47519699999999,29.7377],"type":"Point"}
}