{
  "type": "Feature",
  "properties": {
    "iso:country":"US",
    "sg:address":"109 N Kilgore St",
    "sg:city":"Kilgore",
    "sg:classifiers":[
        {
            "category":"Organizations",
            "subcategory":"Religious Organization",
            "type":"Services"
        }
    ],
    "sg:phone":"+1 903 247 7283",
    "sg:postcode":"75662",
    "sg:province":"TX",
    "wof:name":"Save Our Nation Ministry",
    "wof:placetype":"venue"
},
  "geometry": {"coordinates":[-94.87583600000001,32.386505],"type":"Point"}
}