{
  "type": "Feature",
  "properties": {
    "iso:country":"US",
    "sg:address":"4452 Voss Hills Pl",
    "sg:city":"Dallas",
    "sg:classifiers":[
        {
            "category":"Utilities",
            "subcategory":"Telephone",
            "type":"Services"
        }
    ],
    "sg:phone":"+1 972 931 9190",
    "sg:postcode":"75287",
    "sg:province":"TX",
    "sg:tags":[
        "communications"
    ],
    "wof:name":"Encompass Telecom Services",
    "wof:placetype":"venue"
},
  "geometry": {"coordinates":[-96.833837,33.010077],"type":"Point"}
}