{
  "type": "Feature",
  "properties": {
    "iso:country":"US",
    "sg:address":"7268 Alameda Ave",
    "sg:city":"El Paso",
    "sg:classifiers":[
        {
            "category":"Autos & Motor Vehicles",
            "subcategory":"Automobile Sales",
            "type":"Retail Goods"
        }
    ],
    "sg:phone":"+1 915 775 0047",
    "sg:postcode":"79915",
    "sg:province":"TX",
    "sg:tags":[
        "car",
        "used",
        "dealer"
    ],
    "wof:name":"Pete's Motors",
    "wof:placetype":"venue"
},
  "geometry": {"coordinates":[-106.383003,31.746175],"type":"Point"}
}