{
  "type": "Feature",
  "properties": {
    "iso:country":"US",
    "sg:address":"33418 Egypt Ln",
    "sg:city":"Magnolia",
    "sg:classifiers":[
        {
            "category":"Cafe",
            "type":"Food & Drink"
        }
    ],
    "sg:menulink":"http://www.allmenus.com/tx/southeast-montgomery/63726-eden-cafe/menu/",
    "sg:phone":"+1 832 934 2800",
    "sg:postcode":"77354",
    "sg:province":"TX",
    "sg:tags":[
        "american"
    ],
    "wof:name":"Eden Cafe",
    "wof:placetype":"venue"
},
  "geometry": {"coordinates":[-95.56307,30.2154],"type":"Point"}
}