{
  "type": "Feature",
  "properties": {
    "iso:country":"US",
    "sg:address":"243 Castlebar",
    "sg:city":"Gordonville",
    "sg:classifiers":[
        {
            "category":"Building & Trades",
            "subcategory":"Construction",
            "type":"Services"
        }
    ],
    "sg:phone":"+1 940 300 7020",
    "sg:postcode":"76245",
    "sg:province":"TX",
    "sg:tags":[
        "drywall",
        "painting",
        "contractor"
    ],
    "wof:name":"JM Drywall and Paint",
    "wof:placetype":"venue"
},
  "geometry": {"coordinates":[-96.826297,33.85203],"type":"Point"}
}