{
  "type": "Feature",
  "properties": {
    "iso:country":"US",
    "sg:address":"2115 Pineloch Dr",
    "sg:city":"Houston",
    "sg:classifiers":[
        {
            "category":"Professional",
            "subcategory":"Advertising",
            "type":"Services"
        }
    ],
    "sg:phone":"+1 281 286 8866",
    "sg:postcode":"77062",
    "sg:province":"TX",
    "sg:tags":[
        "agency"
    ],
    "wof:name":"A D S & P R Corporation",
    "wof:placetype":"venue"
},
  "geometry": {"coordinates":[-95.126946,29.586816],"type":"Point"}
}