{
  "type": "Feature",
  "properties": {
    "iso:country":"US",
    "sg:address":"22762 Cypresswood Dr",
    "sg:city":"Spring",
    "sg:classifiers":[
        {
            "category":"Professional",
            "subcategory":"Business Services",
            "type":"Services"
        }
    ],
    "sg:phone":"+1 281 443 1222",
    "sg:postcode":"77373",
    "sg:province":"TX",
    "wof:name":"Mail Center Etc",
    "wof:placetype":"venue"
},
  "geometry": {"coordinates":[-95.345799,30.044036],"type":"Point"}
}