{
  "type": "Feature",
  "properties": {
    "iso:country":"US",
    "sg:address":"447 Sandau Rd",
    "sg:city":"San Antonio",
    "sg:classifiers":[
        {
            "category":"Airline",
            "type":"Transportation"
        }
    ],
    "sg:phone":"+1 210 341 5387",
    "sg:postcode":"78216",
    "sg:province":"TX",
    "sg:tags":[
        "nonscheduled",
        "air"
    ],
    "wof:name":"Alamo Jet Inc",
    "wof:placetype":"venue"
},
  "geometry": {"coordinates":[-98.48492899999999,29.537175],"type":"Point"}
}