{
  "type": "Feature",
  "properties": {
    "iso:country":"US",
    "sg:address":"2830 Kenross St",
    "sg:city":"Houston",
    "sg:classifiers":[
        {
            "category":"Professional",
            "subcategory":"Computer Services",
            "type":"Services"
        }
    ],
    "sg:phone":"+1 713 223 4219",
    "sg:postcode":"77043",
    "sg:province":"TX",
    "sg:tags":[
        "programing",
        "custom"
    ],
    "wof:name":"Infinet Storage LLC",
    "wof:placetype":"venue"
},
  "geometry": {"coordinates":[-95.551114,29.824095],"type":"Point"}
}