{
  "type": "Feature",
  "properties": {
    "iso:country":"US",
    "sg:address":"1920 Marx St",
    "sg:city":"San Angelo",
    "sg:classifiers":[
        {
            "category":"Retail",
            "subcategory":"Repair Shop",
            "type":"Services"
        }
    ],
    "sg:phone":"+1 325 658 2900",
    "sg:postcode":"76903",
    "sg:province":"TX",
    "sg:tags":[
        "appliance"
    ],
    "wof:name":"Lakeview Appliance Repair",
    "wof:placetype":"venue"
},
  "geometry": {"coordinates":[-100.44168500000001,31.482973],"type":"Point"}
}