{
  "type": "Feature",
  "properties": {
    "iso:country":"US",
    "sg:address":"2829 Shaver St",
    "sg:city":"Pasadena",
    "sg:classifiers":[
        {
            "category":"Retail",
            "subcategory":"Auto Repair",
            "type":"Services"
        }
    ],
    "sg:phone":"+1 713 941 4511",
    "sg:postcode":"77502",
    "sg:province":"TX",
    "sg:tags":[
        "transmission"
    ],
    "wof:name":"Mario's Transmission",
    "wof:placetype":"venue"
},
  "geometry": {"coordinates":[-95.207864,29.667756],"type":"Point"}
}