{
  "type": "Feature",
  "properties": {
    "iso:country":"US",
    "sg:address":"3812 Osage St",
    "sg:city":"Houston",
    "sg:classifiers":[
        {
            "category":"Wholesale",
            "subcategory":"Home Furnishings",
            "type":"Manufacturing & Wholesale Goods"
        }
    ],
    "sg:phone":"+1 713 783 6875",
    "sg:postcode":"77063",
    "sg:province":"TX",
    "sg:tags":[
        "plumbing",
        "supplies-wholesale",
        "part",
        "fixture",
        "manufacturer"
    ],
    "wof:name":"Sewer Jet Technology",
    "wof:placetype":"venue"
},
  "geometry": {"coordinates":[-95.526578,29.72292],"type":"Point"}
}