{
  "type": "Feature",
  "properties": {
    "iso:country":"US",
    "sg:address":"7423 Nicholforest Ln",
    "sg:city":"Spring",
    "sg:classifiers":[
        {
            "category":"Wholesale",
            "subcategory":"Stationery",
            "type":"Manufacturing & Wholesale Goods"
        }
    ],
    "sg:phone":"+1 281 255 2243",
    "sg:postcode":"77389",
    "sg:province":"TX",
    "sg:tags":[
        "supply"
    ],
    "wof:name":"Gonzalez & Assoc",
    "wof:placetype":"venue"
},
  "geometry": {"coordinates":[-95.538161,30.13554],"type":"Point"}
}