{
  "type": "Feature",
  "properties": {
    "iso:country":"US",
    "sg:address":"405 E San Pedro St",
    "sg:city":"Laredo",
    "sg:classifiers":[
        {
            "category":"Manufacturing",
            "subcategory":"Printing",
            "type":"Manufacturing & Wholesale Goods"
        }
    ],
    "sg:phone":"+1 956 727 4556",
    "sg:postcode":"78041",
    "sg:province":"TX",
    "sg:tags":[
        "commercial"
    ],
    "wof:name":"More Printing Service",
    "wof:placetype":"venue"
},
  "geometry": {"coordinates":[-99.49170599999999,27.53235],"type":"Point"}
}