{
  "type": "Feature",
  "properties": {
    "iso:country":"US",
    "sg:address":"406 S Gary Ave",
    "sg:city":"Monahans",
    "sg:classifiers":[
        {
            "category":"Health Services",
            "subcategory":"Hospital",
            "type":"Services"
        }
    ],
    "sg:phone":"+1 432 943 2511",
    "sg:postcode":"79756",
    "sg:province":"TX",
    "wof:name":"Ward Memorial Hospital",
    "wof:placetype":"venue"
},
  "geometry": {"coordinates":[-102.884654,31.593966],"type":"Point"}
}