{
  "type": "Feature",
  "properties": {
    "iso:country":"US",
    "sg:address":"201 N Preston St",
    "sg:city":"Ennis",
    "sg:classifiers":[
        {
            "category":"Real Estate",
            "subcategory":"Real Estate Agent",
            "type":"Services"
        },
        {
            "category":"Banks & Credit Unions",
            "subcategory":"Financial Services",
            "type":"Services"
        }
    ],
    "sg:phone":"+1 972 878 2907",
    "sg:postcode":"75119",
    "sg:province":"TX",
    "sg:tags":[
        "investor",
        "investment"
    ],
    "wof:name":"Tenpenny Investments LLC",
    "wof:placetype":"venue"
},
  "geometry": {"coordinates":[-96.63141400000001,32.326783],"type":"Point"}
}