{
  "type": "Feature",
  "properties": {
    "iso:country":"US",
    "sg:address":"8090 Pat Booker Rd",
    "sg:city":"Live Oak",
    "sg:classifiers":[
        {
            "category":"Retail",
            "subcategory":"Laundry & Dry Cleaning",
            "type":"Services"
        },
        {
            "category":"Personal",
            "subcategory":"Beauty Salon",
            "type":"Services"
        }
    ],
    "sg:phone":"+1 210 590 7927",
    "sg:postcode":"78233",
    "sg:province":"TX",
    "sg:tags":[
        "manicuring"
    ],
    "wof:name":"Nails Tanning & Alterations",
    "wof:placetype":"venue"
},
  "geometry": {"coordinates":[-98.33249000000001,29.562656],"type":"Point"}
}