{
  "type": "Feature",
  "properties": {
    "iso:country":"US",
    "sg:address":"3509 Andrea Ln",
    "sg:city":"Rowlett",
    "sg:classifiers":[
        {
            "category":"Professional",
            "type":"Services"
        }
    ],
    "sg:phone":"+1 972 412 8199",
    "sg:postcode":"75088",
    "sg:province":"TX",
    "wof:name":"Concho Products",
    "wof:placetype":"venue"
},
  "geometry": {"coordinates":[-96.56954399999999,32.887301],"type":"Point"}
}