{
  "type": "Feature",
  "properties": {
    "iso:country":"US",
    "sg:address":"7801 N Lamar Blvd",
    "sg:city":"Austin",
    "sg:classifiers":[
        {
            "category":"Shopping",
            "type":"Retail Goods"
        }
    ],
    "sg:phone":"+1 512 302 3689",
    "sg:postcode":"78752",
    "sg:province":"TX",
    "sg:tags":[
        "orthopedic",
        "appliance"
    ],
    "wof:name":"Applied Orthotics LLC",
    "wof:placetype":"venue"
},
  "geometry": {"coordinates":[-97.714338,30.344467],"type":"Point"}
}