{
  "type": "Feature",
  "properties": {
    "iso:country":"US",
    "sg:address":"404 Turkey Creek Trl",
    "sg:city":"Bridgeport",
    "sg:classifiers":[
        {
            "category":"Building & Trades",
            "subcategory":"Construction",
            "type":"Services"
        }
    ],
    "sg:phone":"+1 940 683 8387",
    "sg:postcode":"76426",
    "sg:province":"TX",
    "sg:tags":[
        "contractor"
    ],
    "wof:name":"Ellithorpes Custom Trim",
    "wof:placetype":"venue"
},
  "geometry": {"coordinates":[-97.765809,33.214787],"type":"Point"}
}