{
  "type": "Feature",
  "properties": {
    "iso:country":"US",
    "sg:address":"13915 Ella Lee Ln",
    "sg:city":"Houston",
    "sg:classifiers":[
        {
            "category":"Shopping",
            "subcategory":"Florist",
            "type":"Retail Goods"
        }
    ],
    "sg:phone":"+1 832 379 0900",
    "sg:postcode":"77077",
    "sg:province":"TX",
    "wof:name":"Gaylord Designs",
    "wof:placetype":"venue"
},
  "geometry": {"coordinates":[-95.639141,29.739533],"type":"Point"}
}