{
  "type": "Feature",
  "properties": {
    "iso:country":"US",
    "sg:address":"672 Scenic Ranch Cir",
    "sg:city":"Mckinney",
    "sg:classifiers":[
        {
            "category":"Professional",
            "subcategory":"Business Services",
            "type":"Services"
        }
    ],
    "sg:phone":"+1 972 886 0766",
    "sg:postcode":"75069",
    "sg:province":"TX",
    "sg:tags":[
        "consultant",
        "coach"
    ],
    "wof:name":"Richard Harting",
    "wof:placetype":"venue"
},
  "geometry": {"coordinates":[-96.590493,33.142376],"type":"Point"}
}