{
  "type": "Feature",
  "properties": {
    "iso:country":"US",
    "sg:address":"7430 Westville Dr",
    "sg:city":"San Antonio",
    "sg:classifiers":[
        {
            "category":"Organizations",
            "subcategory":"Community Association",
            "type":"Services"
        }
    ],
    "sg:phone":"+1 210 655 2293",
    "sg:postcode":"78227",
    "sg:province":"TX",
    "wof:name":"San Antonio Chapter 1",
    "wof:placetype":"venue"
},
  "geometry": {"coordinates":[-98.637849,29.412315],"type":"Point"}
}