{
  "type": "Feature",
  "properties": {
    "iso:country":"US",
    "sg:address":"2119 E US Hwy 83",
    "sg:city":"Rio Grande City",
    "sg:classifiers":[
        {
            "category":"Restaurant",
            "type":"Food & Drink"
        }
    ],
    "sg:phone":"+1 956 488 9087",
    "sg:postcode":"78582",
    "sg:province":"TX",
    "wof:name":"Subway Sandwiches & Salads",
    "wof:placetype":"venue"
},
  "geometry": {"coordinates":[-98.803138,26.375763],"type":"Point"}
}