{
  "type": "Feature",
  "properties": {
    "iso:country":"US",
    "sg:address":"1010 Trundy St",
    "sg:city":"Merkel",
    "sg:classifiers":[
        {
            "category":"Professional",
            "subcategory":"Management & Consulting",
            "type":"Services"
        }
    ],
    "sg:phone":"+1 325 928 5110",
    "sg:postcode":"79536",
    "sg:province":"TX",
    "sg:tags":[
        "retail",
        "direct",
        "sales"
    ],
    "wof:name":"K-Par Marketing",
    "wof:placetype":"venue"
},
  "geometry": {"coordinates":[-100.019644,32.460307],"type":"Point"}
}