{
  "type": "Feature",
  "properties": {
    "iso:country":"US",
    "sg:address":"3151 Sandalwood Dr",
    "sg:city":"Port Neches",
    "sg:classifiers":[
        {
            "category":"Education",
            "subcategory":"Dance Studio",
            "type":"Public Place"
        }
    ],
    "sg:phone":"+1 409 735 8900",
    "sg:postcode":"77651",
    "sg:province":"TX",
    "wof:name":"Studio C Dance Center",
    "wof:placetype":"venue"
},
  "geometry": {"coordinates":[-93.966587,29.963123],"type":"Point"}
}