{
  "type": "Feature",
  "properties": {
    "iso:country":"US",
    "sg:address":"1730 S Wheeler St",
    "sg:city":"Jasper",
    "sg:classifiers":[
        {
            "category":"Food & Beverages",
            "subcategory":"Groceries & Convenience Stores",
            "type":"Retail Goods"
        }
    ],
    "sg:phone":"+1 409 489 0541",
    "sg:postcode":"75951",
    "sg:province":"TX",
    "wof:name":"Discount Grocery",
    "wof:placetype":"venue"
},
  "geometry": {"coordinates":[-93.99306799999999,30.903517],"type":"Point"}
}