{
  "type": "Feature",
  "properties": {
    "iso:country":"US",
    "sg:address":"2607 Old Humble Rd",
    "sg:city":"Humble",
    "sg:classifiers":[
        {
            "category":"Shopping",
            "subcategory":"Florist",
            "type":"Retail Goods"
        }
    ],
    "sg:phone":"+1 281 441 1126",
    "sg:postcode":"77396",
    "sg:province":"TX",
    "wof:name":"Danell's Gifts & Florals",
    "wof:placetype":"venue"
},
  "geometry": {"coordinates":[-95.26386599999999,29.966723],"type":"Point"}
}