{
  "type": "Feature",
  "properties": {
    "iso:country":"US",
    "sg:address":"2211 Carter Ave",
    "sg:city":"Midland",
    "sg:classifiers":[
        {
            "category":"Freight",
            "type":"Transportation"
        }
    ],
    "sg:phone":"+1 432 688 5183",
    "sg:postcode":"79701",
    "sg:province":"TX",
    "sg:tags":[
        "special"
    ],
    "wof:name":"Iron Mountain Information MGT",
    "wof:placetype":"venue"
},
  "geometry": {"coordinates":[-102.093468,31.981701],"type":"Point"}
}