{
  "type": "Feature",
  "properties": {
    "iso:country":"US",
    "sg:address":"1825 Banks Dr",
    "sg:city":"Weatherford",
    "sg:classifiers":[
        {
            "category":"Building & Trades",
            "subcategory":"Construction",
            "type":"Services"
        }
    ],
    "sg:phone":"+1 817 613 8255",
    "sg:postcode":"76087",
    "sg:province":"TX",
    "sg:tags":[
        "acoustical",
        "contractor"
    ],
    "wof:name":"Amerson Acoustical Co",
    "wof:placetype":"venue"
},
  "geometry": {"coordinates":[-97.743967,32.741173],"type":"Point"}
}