{
  "type": "Feature",
  "properties": {
    "iso:country":"US",
    "sg:address":"808 W Grant Ave",
    "sg:city":"Harlingen",
    "sg:classifiers":[
        {
            "category":"Organizations",
            "subcategory":"Religious Organization",
            "type":"Services"
        }
    ],
    "sg:phone":"+1 956 423 9108",
    "sg:postcode":"78550",
    "sg:province":"TX",
    "wof:name":"El Buen Smritan Methdst Church",
    "wof:placetype":"venue"
},
  "geometry": {"coordinates":[-97.70431600000001,26.181638],"type":"Point"}
}