{
  "type": "Feature",
  "properties": {
    "iso:country":"US",
    "sg:address":"7302 Ridge Beach Rd",
    "sg:city":"Converse",
    "sg:classifiers":[
        {
            "category":"Food & Beverages",
            "subcategory":"Groceries & Convenience Stores",
            "type":"Retail Goods"
        }
    ],
    "sg:phone":"+1 210 650 3105",
    "sg:postcode":"78109",
    "sg:province":"TX",
    "sg:tags":[
        "product"
    ],
    "wof:name":"Home Grown Design",
    "wof:placetype":"venue"
},
  "geometry": {"coordinates":[-98.34138799999999,29.531351],"type":"Point"}
}