{
  "type": "Feature",
  "properties": {
    "iso:country":"US",
    "sg:address":"5602 Rittiman Plz",
    "sg:city":"San Antonio",
    "sg:classifiers":[
        {
            "category":"Real Estate",
            "subcategory":"Real Estate Agent",
            "type":"Services"
        }
    ],
    "sg:phone":"+1 210 828 3742",
    "sg:postcode":"78218",
    "sg:province":"TX",
    "wof:name":"Utah Retirement Systems",
    "wof:placetype":"venue"
},
  "geometry": {"coordinates":[-98.406779,29.482384],"type":"Point"}
}