{
  "type": "Feature",
  "properties": {
    "iso:country":"US",
    "sg:address":"4055 FM 51",
    "sg:city":"Gainesville",
    "sg:classifiers":[
        {
            "category":"Farming",
            "subcategory":"Dairy Farm",
            "type":"Manufacturing & Wholesale Goods"
        }
    ],
    "sg:phone":"+1 940 665 8982",
    "sg:postcode":"76240",
    "sg:province":"TX",
    "wof:name":"Reiter's Dairy",
    "wof:placetype":"venue"
},
  "geometry": {"coordinates":[-97.19541599999999,33.587824],"type":"Point"}
}