{
  "type": "Feature",
  "properties": {
    "iso:country":"US",
    "sg:address":"13819 Terlin St",
    "sg:city":"Houston",
    "sg:classifiers":[
        {
            "category":"Shopping",
            "subcategory":"Gifts & Souvenirs",
            "type":"Retail Goods"
        }
    ],
    "sg:phone":"+1 281 449 5072",
    "sg:postcode":"77039",
    "sg:province":"TX",
    "wof:name":"Timeless Gifts Clothing &",
    "wof:placetype":"venue"
},
  "geometry": {"coordinates":[-95.300477,29.918364],"type":"Point"}
}