{
  "type": "Feature",
  "properties": {
    "iso:country":"US",
    "sg:address":"3804 Avenue F",
    "sg:city":"Austin",
    "sg:classifiers":[
        {
            "category":"Shopping",
            "subcategory":"Musical Instruments",
            "type":"Retail Goods"
        }
    ],
    "sg:phone":"+1 512 826 5129",
    "sg:postcode":"78751",
    "sg:province":"TX",
    "sg:tags":[
        "guitar",
        "amplifier"
    ],
    "wof:name":"Howler Brothers",
    "wof:placetype":"venue"
},
  "geometry": {"coordinates":[-97.73267300000001,30.300127],"type":"Point"}
}