{
  "type": "Feature",
  "properties": {
    "iso:country":"US",
    "sg:address":"208 Small Hill Dr",
    "sg:city":"Grand Prairie",
    "sg:classifiers":[
        {
            "category":"Education",
            "subcategory":"Dance Studio",
            "type":"Public Place"
        }
    ],
    "sg:phone":"+1 972 263 1114",
    "sg:postcode":"75050",
    "sg:province":"TX",
    "sg:tags":[
        "instruction",
        "dancing"
    ],
    "wof:name":"Freestyle Show Productions Dnc",
    "wof:placetype":"venue"
},
  "geometry": {"coordinates":[-97.00093099999999,32.749834],"type":"Point"}
}