{
  "type": "Feature",
  "properties": {
    "iso:country":"US",
    "sg:address":"5907 Fort Sumter Ln",
    "sg:city":"Houston",
    "sg:classifiers":[
        {
            "category":"Building & Trades",
            "subcategory":"Landscaping Services",
            "type":"Services"
        }
    ],
    "sg:phone":"+1 713 973 7851",
    "sg:postcode":"77084",
    "sg:province":"TX",
    "sg:tags":[
        "landscape"
    ],
    "wof:name":"Integrated Landscape Systems",
    "wof:placetype":"venue"
},
  "geometry": {"coordinates":[-95.627751,29.860614],"type":"Point"}
}