{
  "type": "Feature",
  "properties": {
    "iso:country":"US",
    "sg:address":"2408 Garden Park Ct",
    "sg:city":"Arlington",
    "sg:classifiers":[
        {
            "category":"Real Estate",
            "subcategory":"Real Estate Agent",
            "type":"Services"
        }
    ],
    "sg:phone":"+1 817 274 8000",
    "sg:postcode":"76013",
    "sg:province":"TX",
    "wof:name":"Karen P C Cushman",
    "wof:placetype":"venue"
},
  "geometry": {"coordinates":[-97.14900799999999,32.726347],"type":"Point"}
}