{
  "type": "Feature",
  "properties": {
    "iso:country":"US",
    "sg:address":"720 Lancaster Hutchins Rd",
    "sg:city":"Hutchins",
    "sg:classifiers":[
        {
            "category":"Government",
            "subcategory":"Post Office",
            "type":"Public Place"
        }
    ],
    "sg:phone":"+1 972 225 1204",
    "sg:postcode":"75141",
    "sg:province":"TX",
    "wof:name":"US Post Office",
    "wof:placetype":"venue"
},
  "geometry": {"coordinates":[-96.733737,32.622739],"type":"Point"}
}