{
  "type": "Feature",
  "properties": {
    "iso:country":"US",
    "sg:address":"916 Roberts Cut Off Rd",
    "sg:city":"Fort Worth",
    "sg:classifiers":[
        {
            "category":"Freight",
            "type":"Transportation"
        },
        {
            "category":"Professional",
            "subcategory":"Advertising",
            "type":"Services"
        }
    ],
    "sg:phone":"+1 817 731 3339",
    "sg:postcode":"76114",
    "sg:province":"TX",
    "sg:tags":[
        "mailing",
        "shipping"
    ],
    "wof:name":"In & Out Shipping & Sports",
    "wof:placetype":"venue"
},
  "geometry": {"coordinates":[-97.399749,32.774206],"type":"Point"}
}