{
  "type": "Feature",
  "properties": {
    "iso:country":"US",
    "sg:address":"9460 N Macarthur Blvd",
    "sg:city":"Irving",
    "sg:classifiers":[
        {
            "category":"Shopping",
            "subcategory":"Florist",
            "type":"Retail Goods"
        }
    ],
    "sg:phone":"+1 972 432 0090",
    "sg:postcode":"75063",
    "sg:province":"TX",
    "wof:name":"Touch Love Flowers and Gifts",
    "wof:placetype":"venue"
},
  "geometry": {"coordinates":[-96.95212100000001,32.935123],"type":"Point"}
}