{
  "type": "Feature",
  "properties": {
    "iso:country":"US",
    "sg:address":"5920 Shirley Ln",
    "sg:city":"Humble",
    "sg:classifiers":[
        {
            "category":"Building & Trades",
            "subcategory":"Plumbing",
            "type":"Services"
        }
    ],
    "sg:phone":"+1 713 695 6473",
    "sg:postcode":"77396",
    "sg:province":"TX",
    "sg:tags":[
        "plumbing",
        "contractor"
    ],
    "wof:name":"Keaton Plumbing Co Inc",
    "wof:placetype":"venue"
},
  "geometry": {"coordinates":[-95.30208500000001,29.944795],"type":"Point"}
}