{
  "type": "Feature",
  "properties": {
    "iso:country":"US",
    "sg:address":"147 N Ave G",
    "sg:city":"Haskell",
    "sg:phone":"+1 940 864 3154",
    "sg:postcode":"79521",
    "sg:province":"TX",
    "sg:tags":[
        "farm",
        "cotton"
    ],
    "wof:name":"Joe A Cothron",
    "wof:placetype":"venue"
},
  "geometry": {"coordinates":[-99.736457,33.15822],"type":"Point"}
}