{
  "type": "Feature",
  "properties": {
    "iso:country":"US",
    "sg:address":"13506 Purple Sage Rd",
    "sg:city":"Dallas",
    "sg:classifiers":[
        {
            "category":"Shopping",
            "subcategory":"Used Merchandise",
            "type":"Retail Goods"
        }
    ],
    "sg:phone":"+1 972 233 6764",
    "sg:postcode":"75240",
    "sg:province":"TX",
    "sg:tags":[
        "antique"
    ],
    "wof:name":"Harlowe's Web",
    "wof:placetype":"venue"
},
  "geometry": {"coordinates":[-96.772903,32.932491],"type":"Point"}
}