{
  "type": "Feature",
  "properties": {
    "iso:country":"US",
    "sg:address":"8310 C F Hawn Fwy",
    "sg:city":"Dallas",
    "sg:classifiers":[
        {
            "category":"Freight",
            "type":"Transportation"
        },
        {
            "category":"Manufacturing",
            "subcategory":"Apparel",
            "type":"Manufacturing & Wholesale Goods"
        }
    ],
    "sg:phone":"+1 214 391 4426",
    "sg:postcode":"75217",
    "sg:province":"TX",
    "sg:tags":[
        "operator",
        "mfr",
        "mattress",
        "trucking"
    ],
    "wof:name":"Mattress World Inc",
    "wof:placetype":"venue"
},
  "geometry": {"coordinates":[-96.674864,32.708179],"type":"Point"}
}