{
  "type": "Feature",
  "properties": {
    "iso:country":"US",
    "sg:address":"3301 Airport Fwy",
    "sg:city":"Bedford",
    "sg:classifiers":[
        {
            "category":"Banks & Credit Unions",
            "subcategory":"Bank",
            "type":"Services"
        }
    ],
    "sg:phone":"+1 817 858 0446",
    "sg:postcode":"76021",
    "sg:province":"TX",
    "sg:tags":[
        "technology"
    ],
    "wof:name":"One Hour Acceptance",
    "wof:placetype":"venue"
},
  "geometry": {"coordinates":[-97.107782,32.838084],"type":"Point"}
}