{
  "type": "Feature",
  "properties": {
    "iso:country":"US",
    "sg:address":"3503 Northeast Pkwy",
    "sg:city":"San Antonio",
    "sg:classifiers":[
        {
            "category":"Home & Garden",
            "subcategory":"Home Furnishings",
            "type":"Retail Goods"
        },
        {
            "category":"Wholesale",
            "subcategory":"Home Furnishings",
            "type":"Manufacturing & Wholesale Goods"
        }
    ],
    "sg:phone":"+1 210 822 6569",
    "sg:postcode":"78218",
    "sg:province":"TX",
    "sg:tags":[
        "curtain",
        "drapery",
        "custom"
    ],
    "wof:name":"Story's Custom Draperies",
    "wof:placetype":"venue"
},
  "geometry": {"coordinates":[-98.429124,29.492718],"type":"Point"}
}