{
  "type": "Feature",
  "properties": {
    "iso:country":"US",
    "sg:address":"5330 N Braeswood Blvd",
    "sg:city":"Houston",
    "sg:classifiers":[
        {
            "category":"Autos & Motor Vehicles",
            "subcategory":"Fuel & Gas Station",
            "type":"Retail Goods"
        }
    ],
    "sg:postcode":"77096",
    "sg:province":"TX",
    "wof:name":"Valero",
    "wof:placetype":"venue"
},
  "geometry": {"coordinates":[-95.47904800000001,29.677716],"type":"Point"}
}