{
  "type": "Feature",
  "properties": {
    "iso:country":"US",
    "sg:address":"1812 Locksford St",
    "sg:city":"Houston",
    "sg:classifiers":[
        {
            "category":"Professional",
            "subcategory":"Art Services",
            "type":"Services"
        }
    ],
    "sg:phone":"+1 713 869 3273",
    "sg:postcode":"77008",
    "sg:province":"TX",
    "sg:tags":[
        "photography",
        "commercial"
    ],
    "wof:name":"Pics By Judie",
    "wof:placetype":"venue"
},
  "geometry": {"coordinates":[-95.445986,29.803582],"type":"Point"}
}