{
  "type": "Feature",
  "properties": {
    "iso:country":"US",
    "sg:address":"703 E 11th St",
    "sg:city":"Georgetown",
    "sg:classifiers":[
        {
            "category":"Insurance",
            "subcategory":"Insurance Agent",
            "type":"Services"
        }
    ],
    "sg:phone":"+1 512 869 1499",
    "sg:postcode":"78626",
    "sg:province":"TX",
    "sg:tags":[
        "consultant"
    ],
    "wof:name":"H & H Systems Inc",
    "wof:placetype":"venue"
},
  "geometry": {"coordinates":[-97.67049400000001,30.634246],"type":"Point"}
}