{
  "type": "Feature",
  "properties": {
    "iso:country":"US",
    "sg:address":"713 Mc Arthur Dr",
    "sg:city":"Killeen",
    "sg:classifiers":[
        {
            "category":"Personal",
            "subcategory":"Barber",
            "type":"Services"
        }
    ],
    "sg:phone":"+1 254 526 6490",
    "sg:postcode":"76541",
    "sg:province":"TX",
    "wof:name":"Corey's Barber Shop",
    "wof:placetype":"venue"
},
  "geometry": {"coordinates":[-97.735626,31.12516],"type":"Point"}
}