{
  "type": "Feature",
  "properties": {
    "iso:country":"US",
    "sg:address":"10433 Doc Holliday Trl",
    "sg:city":"Austin",
    "sg:classifiers":[
        {
            "category":"Building & Trades",
            "subcategory":"Construction",
            "type":"Services"
        }
    ],
    "sg:phone":"+1 512 835 5151",
    "sg:postcode":"78753",
    "sg:province":"TX",
    "sg:tags":[
        "system",
        "specialty",
        "heating",
        "contractor",
        "air conditioning"
    ],
    "wof:name":"Osso Air Conditioning",
    "wof:placetype":"venue"
},
  "geometry": {"coordinates":[-97.68678300000001,30.37047],"type":"Point"}
}