{
  "type": "Feature",
  "properties": {
    "iso:country":"US",
    "sg:address":"1834 Palm Blvd",
    "sg:city":"Brownsville",
    "sg:classifiers":[
        {
            "category":"Banks & Credit Unions",
            "subcategory":"Financial Services",
            "type":"Services"
        }
    ],
    "sg:phone":"+1 956 544 4217",
    "sg:postcode":"78520",
    "sg:province":"TX",
    "sg:tags":[
        "investor"
    ],
    "wof:name":"Farias Investments Inc",
    "wof:placetype":"venue"
},
  "geometry": {"coordinates":[-97.497029,25.917481],"type":"Point"}
}