{
  "type": "Feature",
  "properties": {
    "iso:country":"US",
    "sg:address":"4200 Lake Breeze Dr",
    "sg:city":"Fort Worth",
    "sg:classifiers":[
        {
            "category":"Professional",
            "subcategory":"Business Services",
            "type":"Services"
        }
    ],
    "sg:phone":"+1 817 732 6563",
    "sg:postcode":"76132",
    "sg:province":"TX",
    "wof:name":"Ford Resource Group Inc",
    "wof:placetype":"venue"
},
  "geometry": {"coordinates":[-97.422729,32.691626],"type":"Point"}
}