{
  "type": "Feature",
  "properties": {
    "iso:country":"US",
    "sg:address":"1420 Brazos Trl",
    "sg:city":"Plano",
    "sg:classifiers":[
        {
            "category":"Banks & Credit Unions",
            "subcategory":"Investment Brokerage",
            "type":"Services"
        }
    ],
    "sg:phone":"+1 972 516 0873",
    "sg:postcode":"75075",
    "sg:province":"TX",
    "wof:name":"Plano Components",
    "wof:placetype":"venue"
},
  "geometry": {"coordinates":[-96.720309,33.020786],"type":"Point"}
}