{
  "type": "Feature",
  "properties": {
    "iso:country":"US",
    "sg:address":"3210 Eastside St",
    "sg:city":"Houston",
    "sg:classifiers":[
        {
            "category":"Social Services",
            "type":"Services"
        }
    ],
    "sg:phone":"+1 713 942 9500",
    "sg:postcode":"77098",
    "sg:province":"TX",
    "sg:tags":[
        "abused",
        "counseling",
        "center",
        "for",
        "child"
    ],
    "wof:name":"Escape Center",
    "wof:placetype":"venue"
},
  "geometry": {"coordinates":[-95.424848,29.737012],"type":"Point"}
}