{
  "type": "Feature",
  "properties": {
    "iso:country":"US",
    "sg:address":"2803 Inridge Dr",
    "sg:city":"Austin",
    "sg:classifiers":[
        {
            "category":"Professional",
            "subcategory":"Lawyer & Legal Services",
            "type":"Services"
        }
    ],
    "sg:phone":"+1 512 899 8038",
    "sg:postcode":"78745",
    "sg:province":"TX",
    "sg:tags":[
        "attorney"
    ],
    "wof:name":"Patrick Stellitano",
    "wof:placetype":"venue"
},
  "geometry": {"coordinates":[-97.82245,30.202212],"type":"Point"}
}