{
  "type": "Feature",
  "properties": {
    "iso:country":"US",
    "sg:address":"201 N Kenwood Rd",
    "sg:city":"Texarkana",
    "sg:classifiers":[
        {
            "category":"Building & Trades",
            "subcategory":"Cleaning & Sanitation",
            "type":"Services"
        }
    ],
    "sg:phone":"+1 903 334 7043",
    "sg:postcode":"75501",
    "sg:province":"TX",
    "sg:tags":[
        "janitor",
        "maintenance"
    ],
    "wof:name":"Mc Lemore Building Maintenance",
    "wof:placetype":"venue"
},
  "geometry": {"coordinates":[-94.08958800000001,33.444795],"type":"Point"}
}