{
  "type": "Feature",
  "properties": {
    "iso:country":"US",
    "sg:address":"107 Highway 71 W Bastrop",
    "sg:city":"Bastrop",
    "sg:classifiers":[
        {
            "category":"Professional",
            "type":"Services"
        },
        {
            "category":"Restaurant",
            "type":"Food & Drink"
        },
        {
            "category":"Fast Food",
            "type":"Food & Drink"
        }
    ],
    "sg:phone":"+1 512 321 2598",
    "sg:postcode":"78602",
    "sg:province":"TX",
    "sg:tags":[
        "delivery",
        "take",
        "pizza"
    ],
    "sg:website":"http://www.pizzahut.com",
    "wof:name":"Pizza Hut",
    "wof:placetype":"venue"
},
  "geometry": {"coordinates":[-97.324983,30.105122],"type":"Point"}
}