{
  "type": "Feature",
  "properties": {
    "iso:country":"US",
    "sg:address":"1901 5th Ave N",
    "sg:city":"Texas City",
    "sg:classifiers":[
        {
            "category":"Retail",
            "subcategory":"Repair Shop",
            "type":"Services"
        }
    ],
    "sg:phone":"+1 409 945 3542",
    "sg:postcode":"77590",
    "sg:province":"TX",
    "sg:tags":[
        "equipment",
        "industrial"
    ],
    "wof:name":"A1 Sewing Machine Repair",
    "wof:placetype":"venue"
},
  "geometry": {"coordinates":[-94.92349900000001,29.389215],"type":"Point"}
}