{
  "type": "Feature",
  "properties": {
    "iso:country":"US",
    "sg:address":"507 82nd St",
    "sg:city":"Lubbock",
    "sg:classifiers":[
        {
            "category":"Autos & Motor Vehicles",
            "subcategory":"Fuel & Gas Station",
            "type":"Retail Goods"
        }
    ],
    "sg:phone":"+1 806 687 3953",
    "sg:postcode":"79404",
    "sg:province":"TX",
    "sg:tags":[
        "oil"
    ],
    "wof:name":"Wylie LP Gas Inc Offices",
    "wof:placetype":"venue"
},
  "geometry": {"coordinates":[-101.840192,33.519696],"type":"Point"}
}