{
  "type": "Feature",
  "properties": {
    "iso:country":"US",
    "sg:address":"409 N Briery Rd",
    "sg:city":"Irving",
    "sg:classifiers":[
        {
            "category":"Manufacturing",
            "subcategory":"Food",
            "type":"Manufacturing & Wholesale Goods"
        }
    ],
    "sg:phone":"+1 972 313 2138",
    "sg:postcode":"75061",
    "sg:province":"TX",
    "sg:tags":[
        "dessert",
        "supply"
    ],
    "wof:name":"Dessert Dreams Inc",
    "wof:placetype":"venue"
},
  "geometry": {"coordinates":[-96.989525,32.820703],"type":"Point"}
}