{
  "type": "Feature",
  "properties": {
    "iso:country":"US",
    "sg:address":"2050 N Stemmons Fwy",
    "sg:city":"Dallas",
    "sg:classifiers":[
        {
            "category":"Wholesale",
            "subcategory":"Jewelry",
            "type":"Manufacturing & Wholesale Goods"
        }
    ],
    "sg:phone":"+1 214 905 7506",
    "sg:postcode":"75207",
    "sg:province":"TX",
    "sg:tags":[
        "jeweler"
    ],
    "wof:name":"Final Touch Jewelry Inc",
    "wof:placetype":"venue"
},
  "geometry": {"coordinates":[-96.82226,32.799989],"type":"Point"}
}