{
  "type": "Feature",
  "properties": {
    "iso:country":"US",
    "sg:address":"11810 Queenspoint Dr",
    "sg:city":"San Antonio",
    "sg:classifiers":[
        {
            "category":"Real Estate",
            "subcategory":"Real Estate Agent",
            "type":"Services"
        }
    ],
    "sg:phone":"+1 210 520 5755",
    "sg:postcode":"78251",
    "sg:province":"TX",
    "wof:name":"Mejia Realty",
    "wof:placetype":"venue"
},
  "geometry": {"coordinates":[-98.708248,29.449505],"type":"Point"}
}