{
  "type": "Feature",
  "properties": {
    "iso:country":"US",
    "sg:address":"5302 Chandler St",
    "sg:city":"Houston",
    "sg:classifiers":[
        {
            "category":"Wholesale",
            "subcategory":"Machinery & Supplies",
            "type":"Manufacturing & Wholesale Goods"
        }
    ],
    "sg:phone":"+1 713 467 9922",
    "sg:postcode":"77007",
    "sg:province":"TX",
    "sg:tags":[
        "equipment",
        "industrial"
    ],
    "wof:name":"Metallurgical Systems Inc",
    "wof:placetype":"venue"
},
  "geometry": {"coordinates":[-95.414945,29.763827],"type":"Point"}
}