{
  "type": "Feature",
  "properties": {
    "iso:country":"US",
    "sg:address":"7309 San Dario Ave",
    "sg:city":"Laredo",
    "sg:classifiers":[
        {
            "category":"Shopping",
            "subcategory":"Discount & Variety Stores",
            "type":"Retail Goods"
        }
    ],
    "sg:phone":"+1 956 712 2060",
    "sg:postcode":"78045",
    "sg:province":"TX",
    "wof:name":"J C Twiss Inc",
    "wof:placetype":"venue"
},
  "geometry": {"coordinates":[-99.50214,27.571959],"type":"Point"}
}