{
  "type": "Feature",
  "properties": {
    "iso:country":"US",
    "sg:address":"664 S Columbia Dr",
    "sg:city":"West Columbia",
    "sg:classifiers":[
        {
            "category":"Personal",
            "subcategory":"Tanning Parlor",
            "type":"Services"
        }
    ],
    "sg:phone":"+1 979 345 6711",
    "sg:postcode":"77486",
    "sg:province":"TX",
    "sg:tags":[
        "salon"
    ],
    "wof:name":"Design On A Dime Beauty Supply",
    "wof:placetype":"venue"
},
  "geometry": {"coordinates":[-95.653953,29.139204],"type":"Point"}
}