{
  "type": "Feature",
  "properties": {
    "iso:country":"US",
    "sg:address":"16200 Garden Oaks St",
    "sg:city":"San Antonio",
    "sg:classifiers":[
        {
            "category":"Real Estate",
            "subcategory":"Real Estate Agent",
            "type":"Services"
        }
    ],
    "sg:phone":"+1 210 403 9150",
    "sg:postcode":"78232",
    "sg:province":"TX",
    "wof:name":"Falcon Properties",
    "wof:placetype":"venue"
},
  "geometry": {"coordinates":[-98.453457,29.590494],"type":"Point"}
}