{
  "type": "Feature",
  "properties": {
    "iso:country":"US",
    "sg:address":"4118 FM 621",
    "sg:city":"San Marcos",
    "sg:classifiers":[
        {
            "category":"Personal",
            "subcategory":"Beauty Salon",
            "type":"Services"
        }
    ],
    "sg:phone":"+1 512 392 2889",
    "sg:postcode":"78666",
    "sg:province":"TX",
    "sg:tags":[
        "shop"
    ],
    "wof:name":"Anita's Cutz 4 You",
    "wof:placetype":"venue"
},
  "geometry": {"coordinates":[-97.893326,29.823435],"type":"Point"}
}