{
  "type": "Feature",
  "properties": {
    "iso:country":"US",
    "sg:address":"530 Sam Houston Pkwy",
    "sg:city":"Houston",
    "sg:classifiers":[
        {
            "category":"Health Services",
            "subcategory":"Clinic",
            "type":"Services"
        }
    ],
    "sg:phone":"+1 281 931 8887",
    "sg:postcode":"77060",
    "sg:province":"TX",
    "sg:tags":[
        "care"
    ],
    "wof:name":"National Helathcare System",
    "wof:placetype":"venue"
},
  "geometry": {"coordinates":[-95.39033999999999,29.938306],"type":"Point"}
}