{
  "type": "Feature",
  "properties": {
    "iso:country":"US",
    "sg:address":"7152 W FM 1431",
    "sg:city":"Marble Falls",
    "sg:classifiers":[
        {
            "category":"Building & Trades",
            "subcategory":"Construction",
            "type":"Services"
        }
    ],
    "sg:phone":"+1 830 598 1259",
    "sg:postcode":"78654",
    "sg:province":"TX",
    "sg:tags":[
        "contractor"
    ],
    "wof:name":"Rosban Shop",
    "wof:placetype":"venue"
},
  "geometry": {"coordinates":[-98.356149,30.602782],"type":"Point"}
}