{
  "type": "Feature",
  "properties": {
    "iso:country":"US",
    "sg:address":"501 NW 1st Ave",
    "sg:city":"Mineral Wells",
    "sg:classifiers":[
        {
            "category":"Retail",
            "subcategory":"Car Wash",
            "type":"Services"
        }
    ],
    "sg:phone":"+1 940 325 8921",
    "sg:postcode":"76067",
    "sg:province":"TX",
    "sg:tags":[
        "carwash"
    ],
    "wof:name":"Self Service Car Wash",
    "wof:placetype":"venue"
},
  "geometry": {"coordinates":[-98.11383499999999,32.813024],"type":"Point"}
}