{
  "type": "Feature",
  "properties": {
    "iso:country":"US",
    "sg:address":"500 W Paisano Dr",
    "sg:city":"El Paso",
    "sg:classifiers":[
        {
            "category":"Professional",
            "subcategory":"Engineering",
            "type":"Services"
        }
    ],
    "sg:phone":"+1 915 577 9044",
    "sg:postcode":"79901",
    "sg:province":"TX",
    "sg:tags":[
        "engineer"
    ],
    "wof:name":"Texas Electronics Engineering",
    "wof:placetype":"venue"
},
  "geometry": {"coordinates":[-106.49405899999999,31.755414],"type":"Point"}
}