{
  "type": "Feature",
  "properties": {
    "iso:country":"US",
    "sg:address":"3720 Shenandoah St",
    "sg:city":"Dallas",
    "sg:classifiers":[
        {
            "category":"Shopping",
            "subcategory":"Clothing, Apparel, & Fashions",
            "type":"Retail Goods"
        }
    ],
    "sg:phone":"+1 214 520 1487",
    "sg:postcode":"75205",
    "sg:province":"TX",
    "wof:name":"Robin Cook Collection",
    "wof:placetype":"venue"
},
  "geometry": {"coordinates":[-96.795219,32.840102],"type":"Point"}
}