{
  "type": "Feature",
  "properties": {
    "iso:country":"US",
    "sg:address":"3105 Brockbank Dr",
    "sg:city":"Irving",
    "sg:classifiers":[
        {
            "category":"Manufacturing",
            "subcategory":"Building Materials",
            "type":"Manufacturing & Wholesale Goods"
        }
    ],
    "sg:phone":"+1 972 255 0832",
    "sg:postcode":"75062",
    "sg:province":"TX",
    "sg:tags":[
        "mfg"
    ],
    "wof:name":"Norris P Dinger",
    "wof:placetype":"venue"
},
  "geometry": {"coordinates":[-96.94843299999999,32.84809],"type":"Point"}
}