{
  "type": "Feature",
  "properties": {
    "iso:country":"US",
    "sg:address":"2402 S Stemmons Fwy",
    "sg:city":"Lewisville",
    "sg:classifiers":[
        {
            "category":"Restaurant",
            "type":"Food & Drink"
        }
    ],
    "sg:menulink":"http://www.allmenus.com/tx/lewisville/64518-chuck-e-cheeses/menu/",
    "sg:phone":"+1 972 315 6260",
    "sg:postcode":"75067",
    "sg:province":"TX",
    "sg:tags":[
        "american",
        "pizza"
    ],
    "wof:name":"Chuck E. Cheese's",
    "wof:placetype":"venue"
},
  "geometry": {"coordinates":[-96.967285,33.004705],"type":"Point"}
}