{
  "type": "Feature",
  "properties": {
    "iso:country":"US",
    "sg:address":"2006 S 57th St",
    "sg:city":"Temple",
    "sg:classifiers":[
        {
            "category":"Organizations",
            "subcategory":"Religious Organization",
            "type":"Services"
        }
    ],
    "sg:phone":"+1 254 773 0703",
    "sg:postcode":"76504",
    "sg:province":"TX",
    "sg:tags":[
        "church"
    ],
    "sg:website":"www.agudatbris.com",
    "wof:name":"Covenant Fellowship",
    "wof:placetype":"venue"
},
  "geometry": {"coordinates":[-97.380124,31.083623],"type":"Point"}
}