{
  "type": "Feature",
  "properties": {
    "iso:country":"US",
    "sg:address":"106 Bennie St",
    "sg:city":"Houston",
    "sg:classifiers":[
        {
            "category":"Freight",
            "type":"Transportation"
        }
    ],
    "sg:phone":"+1 713 695 4951",
    "sg:postcode":"77022",
    "sg:province":"TX",
    "sg:tags":[
        "mover"
    ],
    "wof:name":"A Anytime Movers",
    "wof:placetype":"venue"
},
  "geometry": {"coordinates":[-95.376255,29.823456],"type":"Point"}
}