{
  "type": "Feature",
  "properties": {
    "iso:country":"US",
    "sg:address":"2616 Little York Rd",
    "sg:city":"Houston",
    "sg:classifiers":[
        {
            "category":"Shopping",
            "subcategory":"Used Merchandise",
            "type":"Retail Goods"
        },
        {
            "category":"Professional",
            "subcategory":"Computer Services",
            "type":"Services"
        }
    ],
    "sg:phone":"+1 713 695 6415",
    "sg:postcode":"77093",
    "sg:province":"TX",
    "sg:tags":[
        "repair"
    ],
    "wof:name":"Carrol's Trading Post",
    "wof:placetype":"venue"
},
  "geometry": {"coordinates":[-95.34281300000001,29.870988],"type":"Point"}
}