{
  "type": "Feature",
  "properties": {
    "iso:country":"US",
    "sg:address":"3000 Research Drive",
    "sg:city":"Richardson",
    "sg:classifiers":[
        {
            "category":"Professional",
            "subcategory":"Computer Services",
            "type":"Services"
        }
    ],
    "sg:phone":"+1 469 624 7400",
    "sg:postcode":"75082 ",
    "sg:province":"TX",
    "sg:website":"http://www.amx.com/",
    "wof:name":"AMX",
    "wof:placetype":"venue"
},
  "geometry": {"coordinates":[-96.659318,32.9869],"type":"Point"}
}