{
  "type": "Feature",
  "properties": {
    "iso:country":"US",
    "sg:address":"13906 Sableridge Dr",
    "sg:city":"Houston",
    "sg:classifiers":[
        {
            "category":"Organizations",
            "subcategory":"Religious Organization",
            "type":"Services"
        }
    ],
    "sg:phone":"+1 281 580 7204",
    "sg:postcode":"77014",
    "sg:province":"TX",
    "sg:tags":[
        "church"
    ],
    "wof:name":"A Ray Of Hope",
    "wof:placetype":"venue"
},
  "geometry": {"coordinates":[-95.482383,29.978247],"type":"Point"}
}