{
  "type": "Feature",
  "properties": {
    "iso:country":"US",
    "sg:address":"7401 Lohmans Crossing Rd",
    "sg:city":"Lago Vista",
    "sg:classifiers":[
        {
            "category":"Home & Garden",
            "subcategory":"Hardware",
            "type":"Retail Goods"
        }
    ],
    "sg:phone":"+1 512 267 2451",
    "sg:postcode":"78645",
    "sg:province":"TX",
    "wof:name":"Lago Vista Sun Hardware",
    "wof:placetype":"venue"
},
  "geometry": {"coordinates":[-97.97756099999999,30.467789],"type":"Point"}
}