{
  "type": "Feature",
  "properties": {
    "iso:country":"US",
    "sg:address":"6521 Ember Ct",
    "sg:city":"Plano",
    "sg:classifiers":[
        {
            "category":"Manufacturing",
            "subcategory":"Printing",
            "type":"Manufacturing & Wholesale Goods"
        }
    ],
    "sg:phone":"+1 972 517 2360",
    "sg:postcode":"75023",
    "sg:province":"TX",
    "sg:tags":[
        "commercial"
    ],
    "wof:name":"David Leo Henry",
    "wof:placetype":"venue"
},
  "geometry": {"coordinates":[-96.72563599999999,33.062346],"type":"Point"}
}