{
  "type": "Feature",
  "properties": {
    "iso:country":"US",
    "sg:address":"12930 Lake Center Run Ct",
    "sg:city":"Houston",
    "sg:classifiers":[
        {
            "category":"Utilities",
            "subcategory":"Electric",
            "type":"Services"
        }
    ],
    "sg:phone":"+1 832 473 4582",
    "sg:postcode":"77041",
    "sg:province":"TX",
    "wof:name":"Kenergy Petroleum",
    "wof:placetype":"venue"
},
  "geometry": {"coordinates":[-95.60315,29.843009],"type":"Point"}
}