{
  "type": "Feature",
  "properties": {
    "iso:country":"US",
    "sg:address":"6699 Chimney Rock Rd Ste 104",
    "sg:city":"Houston",
    "sg:classifiers":[
        {
            "category":"Health Services",
            "subcategory":"Optometrist",
            "type":"Services"
        }
    ],
    "sg:phone":"+1 713 661 6500",
    "sg:postcode":"77081",
    "sg:province":"TX",
    "sg:website":"www.bellaireeye.com",
    "wof:name":"Bellaire Eye & Laser Center",
    "wof:placetype":"venue"
},
  "geometry": {"coordinates":[-95.476072,29.707429],"type":"Point"}
}