{
  "type": "Feature",
  "properties": {
    "iso:country":"US",
    "sg:address":"828 Barkridge Trl",
    "sg:city":"Burleson",
    "sg:classifiers":[
        {
            "category":"Building & Trades",
            "subcategory":"Landscaping Services",
            "type":"Services"
        }
    ],
    "sg:phone":"+1 817 295 3914",
    "sg:postcode":"76028",
    "sg:province":"TX",
    "wof:name":"Randy Total Lawn Care",
    "wof:placetype":"venue"
},
  "geometry": {"coordinates":[-97.342433,32.538457],"type":"Point"}
}