{
  "type": "Feature",
  "properties": {
    "iso:country":"US",
    "sg:address":"310 W Lake Dr",
    "sg:city":"Hamlin",
    "sg:classifiers":[
        {
            "category":"Restaurant",
            "type":"Food & Drink"
        }
    ],
    "sg:menulink":"http://www.allmenus.com/tx/hamlin/66911-pizza-pro/menu/",
    "sg:phone":"+1 915 576 3183",
    "sg:postcode":"79520",
    "sg:province":"TX",
    "sg:tags":[
        "american",
        "pizza"
    ],
    "wof:name":"Pizza Pro",
    "wof:placetype":"venue"
},
  "geometry": {"coordinates":[-100.13023699999999,32.883948],"type":"Point"}
}