{
  "type": "Feature",
  "properties": {
    "iso:country":"US",
    "sg:address":"1101 Southmore Ave",
    "sg:city":"Pasadena",
    "sg:classifiers":[
        {
            "category":"Wholesale",
            "subcategory":"Apparel",
            "type":"Manufacturing & Wholesale Goods"
        }
    ],
    "sg:phone":"+1 713 477 5500",
    "sg:postcode":"77502",
    "sg:province":"TX",
    "sg:tags":[
        "cap"
    ],
    "wof:name":"Caps & More",
    "wof:placetype":"venue"
},
  "geometry": {"coordinates":[-95.20039800000001,29.690859],"type":"Point"}
}