{
  "type": "Feature",
  "properties": {
    "iso:country":"US",
    "sg:address":"30738 Beyette Rd",
    "sg:city":"Magnolia",
    "sg:classifiers":[
        {
            "category":"Building & Trades",
            "subcategory":"Construction",
            "type":"Services"
        }
    ],
    "sg:phone":"+1 281 660 6871",
    "sg:postcode":"77355",
    "sg:province":"TX",
    "sg:tags":[
        "glazier"
    ],
    "wof:name":"All Around Glass & Mirror Inc",
    "wof:placetype":"venue"
},
  "geometry": {"coordinates":[-95.72122299999999,30.190634],"type":"Point"}
}