{
  "type": "Feature",
  "properties": {
    "iso:country":"US",
    "sg:address":"4135 Buena Vista St",
    "sg:city":"Dallas",
    "sg:classifiers":[
        {
            "category":"Restaurant",
            "type":"Food & Drink"
        }
    ],
    "sg:phone":"+1 214 528 5059",
    "sg:postcode":"75204",
    "sg:province":"TX",
    "sg:tags":[
        "eating"
    ],
    "wof:name":"Porcino Inc",
    "wof:placetype":"venue"
},
  "geometry": {"coordinates":[-96.79501500000001,32.817161],"type":"Point"}
}