{
  "type": "Feature",
  "properties": {
    "iso:country":"US",
    "sg:address":"309 Borroum St",
    "sg:city":"Del Rio",
    "sg:classifiers":[
        {
            "category":"Social Services",
            "subcategory":"Child Care",
            "type":"Services"
        }
    ],
    "sg:phone":"+1 830 774 3160",
    "sg:postcode":"78840",
    "sg:province":"TX",
    "sg:tags":[
        "day"
    ],
    "wof:name":"Taylors Day Care Center",
    "wof:placetype":"venue"
},
  "geometry": {"coordinates":[-100.892717,29.363194],"type":"Point"}
}