{
  "type": "Feature",
  "properties": {
    "iso:country":"US",
    "sg:address":"6140 Yaqui Way",
    "sg:city":"El Paso",
    "sg:classifiers":[
        {
            "category":"Retail",
            "subcategory":"Auto Repair",
            "type":"Services"
        }
    ],
    "sg:phone":"+1 915 772 9414",
    "sg:postcode":"79925",
    "sg:province":"TX",
    "sg:tags":[
        "repairing",
        "automobile",
        "general"
    ],
    "wof:name":"Rebel Automotive",
    "wof:placetype":"venue"
},
  "geometry": {"coordinates":[-106.41244,31.78847],"type":"Point"}
}