{
  "type": "Feature",
  "properties": {
    "iso:country":"US",
    "sg:address":"233 N Pecos St",
    "sg:city":"San Antonio",
    "sg:classifiers":[
        {
            "category":"Government",
            "subcategory":"Office",
            "type":"Public Place"
        }
    ],
    "sg:phone":"+1 210 335 6581",
    "sg:postcode":"78207",
    "sg:province":"TX",
    "sg:website":"www.bexar.org",
    "wof:name":"Bexar County Infrastructure",
    "wof:placetype":"venue"
},
  "geometry": {"coordinates":[-98.501296,29.427778],"type":"Point"}
}