{
  "type": "Feature",
  "properties": {
    "iso:country":"US",
    "sg:address":"3904 Dallas Pkwy",
    "sg:city":"Plano",
    "sg:classifiers":[
        {
            "category":"Restaurant",
            "type":"Food & Drink"
        }
    ],
    "sg:menulink":"http://www.allmenus.com/tx/plano/15045-razzoos/menu/",
    "sg:phone":"+1 972 473 9248",
    "sg:postcode":"75093",
    "sg:province":"TX",
    "sg:tags":[
        "american",
        "creole",
        "cajun"
    ],
    "wof:name":"Razzoo's",
    "wof:placetype":"venue"
},
  "geometry": {"coordinates":[-96.830198,33.049743],"type":"Point"}
}