{
  "type": "Feature",
  "properties": {
    "iso:country":"US",
    "sg:address":"6901 Green Oaks Rd",
    "sg:city":"Fort Worth",
    "sg:classifiers":[
        {
            "category":"Home & Garden",
            "subcategory":"Furniture",
            "type":"Retail Goods"
        }
    ],
    "sg:phone":"+1 817 377 2446",
    "sg:postcode":"76116",
    "sg:province":"TX",
    "sg:tags":[
        "mattress"
    ],
    "wof:name":"Mattress Giant",
    "wof:placetype":"venue"
},
  "geometry": {"coordinates":[-97.43425000000001,32.735934],"type":"Point"}
}