{
  "type": "Feature",
  "properties": {
    "iso:country":"US",
    "sg:address":"7402 New Laredo Hwy",
    "sg:city":"San Antonio",
    "sg:classifiers":[
        {
            "category":"Professional",
            "subcategory":"Accounting & Tax Preparation",
            "type":"Services"
        }
    ],
    "sg:phone":"+1 210 922 5511",
    "sg:postcode":"78211",
    "sg:province":"TX",
    "sg:tags":[
        "bookkeeping",
        "general"
    ],
    "wof:name":"A V Tony Rodriguez Bookkeeping",
    "wof:placetype":"venue"
},
  "geometry": {"coordinates":[-98.56365700000001,29.355076],"type":"Point"}
}