{
  "type": "Feature",
  "properties": {
    "iso:country":"US",
    "sg:address":"2002 W 24th St",
    "sg:city":"Plainview",
    "sg:classifiers":[
        {
            "category":"Autos & Motor Vehicles",
            "subcategory":"Auto Supplies",
            "type":"Retail Goods"
        },
        {
            "category":"Retail",
            "subcategory":"Auto Repair",
            "type":"Services"
        }
    ],
    "sg:phone":"+1 806 293 1414",
    "sg:postcode":"79072",
    "sg:province":"TX",
    "sg:tags":[
        "repairing",
        "automobile"
    ],
    "wof:name":"J C's Auto & Transmission",
    "wof:placetype":"venue"
},
  "geometry": {"coordinates":[-101.7274,34.204971],"type":"Point"}
}