{
  "type": "Feature",
  "properties": {
    "iso:country":"US",
    "sg:address":"280 E Corporate Dr",
    "sg:city":"Lewisville",
    "sg:classifiers":[
        {
            "category":"Sports & Exercise",
            "subcategory":"Golf",
            "type":"Entertainment"
        }
    ],
    "sg:phone":"+1 972 219 0550",
    "sg:postcode":"75067",
    "sg:province":"TX",
    "wof:name":"Timber Creek Golf Center",
    "wof:placetype":"venue"
},
  "geometry": {"coordinates":[-96.98521700000001,33.014544],"type":"Point"}
}