{
  "type": "Feature",
  "properties": {
    "iso:country":"US",
    "sg:address":"12009 W Co Rd 129",
    "sg:city":"Odessa",
    "sg:classifiers":[
        {
            "category":"Wholesale",
            "subcategory":"Machinery & Supplies",
            "type":"Manufacturing & Wholesale Goods"
        }
    ],
    "sg:phone":"+1 432 563 2080",
    "sg:postcode":"79765",
    "sg:province":"TX",
    "sg:tags":[
        "equipment",
        "oil",
        "well"
    ],
    "wof:name":"Rico Packer Svc",
    "wof:placetype":"venue"
},
  "geometry": {"coordinates":[-102.241542,31.902206],"type":"Point"}
}