{
  "type": "Feature",
  "properties": {
    "iso:country":"US",
    "sg:address":"9150 N Royal Ln",
    "sg:city":"Irving",
    "sg:classifiers":[
        {
            "category":"Wholesale",
            "subcategory":"Electrical",
            "type":"Manufacturing & Wholesale Goods"
        }
    ],
    "sg:phone":"+1 972 417 7001",
    "sg:postcode":"75063",
    "sg:province":"TX",
    "sg:tags":[
        "control",
        "security",
        "system"
    ],
    "wof:name":"Prostar Security Svc",
    "wof:placetype":"venue"
},
  "geometry": {"coordinates":[-97.019777,32.93278],"type":"Point"}
}