{
  "type": "Feature",
  "properties": {
    "iso:country":"US",
    "sg:address":"11401 Ranch Rd 2222",
    "sg:city":"Austin",
    "sg:classifiers":[
        {
            "category":"Shopping",
            "subcategory":"Bicycles & Sporting Goods",
            "type":"Retail Goods"
        }
    ],
    "sg:phone":"+1 512 258 6646",
    "sg:postcode":"78730",
    "sg:province":"TX",
    "wof:name":"Pisces Scuba",
    "wof:placetype":"venue"
},
  "geometry": {"coordinates":[-97.845468,30.394537],"type":"Point"}
}