{
  "type": "Feature",
  "properties": {
    "iso:country":"US",
    "sg:address":"10978 Grant Rd",
    "sg:city":"Houston",
    "sg:classifiers":[
        {
            "category":"Restaurant",
            "type":"Food & Drink"
        },
        {
            "category":"Ice Cream",
            "type":"Food & Drink"
        }
    ],
    "sg:menulink":"http://www.allmenus.com/tx/northwest-harris/209366-tcby/menu/",
    "sg:phone":"+1 281 469 9190",
    "sg:postcode":"77070",
    "sg:province":"TX",
    "sg:tags":[
        "smoothy",
        "juice",
        "american",
        "ice",
        "cream"
    ],
    "wof:name":"TCBY",
    "wof:placetype":"venue"
},
  "geometry": {"coordinates":[-95.58471,29.967225],"type":"Point"}
}