{
  "type": "Feature",
  "properties": {
    "iso:country":"US",
    "sg:address":"12001 N Central Expy",
    "sg:city":"Dallas",
    "sg:classifiers":[
        {
            "category":"Banks & Credit Unions",
            "subcategory":"Investment Brokerage",
            "type":"Services"
        }
    ],
    "sg:phone":"+1 972 387 0660",
    "sg:postcode":"75243",
    "sg:province":"TX",
    "sg:tags":[
        "consultant",
        "planning",
        "financial"
    ],
    "sg:website":"www.icmc.com",
    "wof:name":"International Capital Mgmt",
    "wof:placetype":"venue"
},
  "geometry": {"coordinates":[-96.76815999999999,32.911146],"type":"Point"}
}