{
  "type": "Feature",
  "properties": {
    "iso:country":"US",
    "sg:address":"3101 Durazno Ave",
    "sg:city":"El Paso",
    "sg:classifiers":[
        {
            "category":"Home & Garden",
            "subcategory":"Building Materials",
            "type":"Retail Goods"
        }
    ],
    "sg:phone":"+1 915 544 8539",
    "sg:postcode":"79905",
    "sg:province":"TX",
    "sg:tags":[
        "screen",
        "window"
    ],
    "wof:name":"Long's Screen Svc",
    "wof:placetype":"venue"
},
  "geometry": {"coordinates":[-106.456948,31.776526],"type":"Point"}
}