{
  "type": "Feature",
  "properties": {
    "iso:country":"US",
    "sg:address":"1307 W Wallace St",
    "sg:city":"San Saba",
    "sg:classifiers":[
        {
            "category":"Shopping",
            "subcategory":"Used Merchandise",
            "type":"Retail Goods"
        }
    ],
    "sg:phone":"+1 325 372 5684",
    "sg:postcode":"76877",
    "sg:province":"TX",
    "sg:tags":[
        "antique"
    ],
    "wof:name":"Front Porch Antiques",
    "wof:placetype":"venue"
},
  "geometry": {"coordinates":[-98.73238000000001,31.195618],"type":"Point"}
}