{
  "type": "Feature",
  "properties": {
    "iso:country":"US",
    "sg:address":"4390 Sam Houston Pkwy",
    "sg:city":"Houston",
    "sg:classifiers":[
        {
            "category":"Restaurant",
            "type":"Food & Drink"
        }
    ],
    "sg:phone":"+1 713 466 1095",
    "sg:postcode":"77015",
    "sg:province":"TX",
    "wof:name":"Mc Donald's",
    "wof:placetype":"venue"
},
  "geometry": {"coordinates":[-95.15119900000001,29.769088],"type":"Point"}
}