{
  "type": "Feature",
  "properties": {
    "iso:country":"US",
    "sg:address":"2501 N Frazier St",
    "sg:city":"Conroe",
    "sg:classifiers":[
        {
            "category":"Manufacturing",
            "subcategory":"Metals",
            "type":"Manufacturing & Wholesale Goods"
        }
    ],
    "sg:phone":"+1 936 539 5401",
    "sg:postcode":"77303",
    "sg:province":"TX",
    "sg:tags":[
        "can"
    ],
    "wof:name":"Crown Cork & Seal Co",
    "wof:placetype":"venue"
},
  "geometry": {"coordinates":[-95.471569,30.349953],"type":"Point"}
}