{
  "type": "Feature",
  "properties": {
    "iso:country":"US",
    "sg:address":"1334 Wahini St",
    "sg:city":"Galveston",
    "sg:classifiers":[
        {
            "category":"Sports & Exercise",
            "subcategory":"Gym",
            "type":"Entertainment"
        }
    ],
    "sg:phone":"+1 409 933 3228",
    "sg:postcode":"77554",
    "sg:province":"TX",
    "sg:tags":[
        "fitness",
        "physical",
        "merchandise",
        "facility"
    ],
    "wof:name":"Rodco Spa Service",
    "wof:placetype":"venue"
},
  "geometry": {"coordinates":[-94.916371,29.299034],"type":"Point"}
}