{
  "type": "Feature",
  "properties": {
    "iso:country":"US",
    "sg:address":"3200 Oakdale Dr",
    "sg:city":"Amarillo",
    "sg:classifiers":[
        {
            "category":"Organizations",
            "subcategory":"Religious Organization",
            "type":"Services"
        }
    ],
    "sg:phone":"+1 806 374 0192",
    "sg:postcode":"79103",
    "sg:province":"TX",
    "sg:tags":[
        "clergy"
    ],
    "wof:name":"Otis Garrison",
    "wof:placetype":"venue"
},
  "geometry": {"coordinates":[-101.78585099999999,35.178933],"type":"Point"}
}