{
  "type": "Feature",
  "properties": {
    "iso:country":"US",
    "sg:address":"1001 W H St",
    "sg:city":"La Porte",
    "sg:classifiers":[
        {
            "category":"Building & Trades",
            "subcategory":"Construction",
            "type":"Services"
        }
    ],
    "sg:phone":"+1 281 470 1331",
    "sg:postcode":"77571",
    "sg:province":"TX",
    "sg:tags":[
        "house",
        "builder",
        "home"
    ],
    "wof:name":"Agile Homes LLC",
    "wof:placetype":"venue"
},
  "geometry": {"coordinates":[-95.027936,29.654967],"type":"Point"}
}