{
  "type": "Feature",
  "properties": {
    "iso:country":"US",
    "sg:address":"2220 Hickory Ln",
    "sg:city":"Pasadena",
    "sg:classifiers":[
        {
            "category":"Wholesale",
            "subcategory":"Machinery & Supplies",
            "type":"Manufacturing & Wholesale Goods"
        }
    ],
    "sg:phone":"+1 713 473 4499",
    "sg:postcode":"77502",
    "sg:province":"TX",
    "sg:tags":[
        "cleaning"
    ],
    "wof:name":"A-1 Hot Shot",
    "wof:placetype":"venue"
},
  "geometry": {"coordinates":[-95.187224,29.677226],"type":"Point"}
}