{
  "type": "Feature",
  "properties": {
    "iso:country":"US",
    "sg:address":"2054 Oday Rd",
    "sg:city":"Pearland",
    "sg:classifiers":[
        {
            "category":"Manufacturing",
            "subcategory":"Tools & Machinery",
            "type":"Manufacturing & Wholesale Goods"
        }
    ],
    "sg:phone":"+1 281 412 2244",
    "sg:postcode":"77581",
    "sg:province":"TX",
    "sg:tags":[
        "machine",
        "shop"
    ],
    "wof:name":"Merit Machine Inc",
    "wof:placetype":"venue"
},
  "geometry": {"coordinates":[-95.314797,29.5862],"type":"Point"}
}