{
  "type": "Feature",
  "properties": {
    "iso:country":"US",
    "sg:address":"105 E Walnut St",
    "sg:city":"Hillsboro",
    "sg:classifiers":[
        {
            "category":"Shopping",
            "subcategory":"Used Merchandise",
            "type":"Retail Goods"
        }
    ],
    "sg:phone":"+1 254 582 3981",
    "sg:postcode":"76645",
    "sg:province":"TX",
    "sg:tags":[
        "pawnbroker"
    ],
    "wof:name":"Hill Country Pawn",
    "wof:placetype":"venue"
},
  "geometry": {"coordinates":[-97.130107,32.008768],"type":"Point"}
}