{
  "type": "Feature",
  "properties": {
    "iso:country":"US",
    "sg:address":"301 Stone Hill Dr",
    "sg:city":"Brenham",
    "sg:classifiers":[
        {
            "category":"Professional",
            "subcategory":"Detective & Security Services",
            "type":"Services"
        }
    ],
    "sg:phone":"+1 979 251 8580",
    "sg:postcode":"77833",
    "sg:province":"TX",
    "sg:tags":[
        "information",
        "bureau"
    ],
    "wof:name":"Schretenthaler Anesthesia Services Pllc",
    "wof:placetype":"venue"
},
  "geometry": {"coordinates":[-96.390953,30.147221],"type":"Point"}
}