{
  "type": "Feature",
  "properties": {
    "iso:country":"US",
    "sg:address":"5519 S Hulen St",
    "sg:city":"Fort Worth",
    "sg:classifiers":[
        {
            "category":"Utilities",
            "subcategory":"Telephone",
            "type":"Services"
        },
        {
            "category":"Professional",
            "subcategory":"Computer Services",
            "type":"Services"
        }
    ],
    "sg:phone":"+1 817 370 1601",
    "sg:postcode":"76132",
    "sg:province":"TX",
    "sg:tags":[
        "communications",
        "internet"
    ],
    "wof:name":"Gaming Center The",
    "wof:placetype":"venue"
},
  "geometry": {"coordinates":[-97.400083,32.668485],"type":"Point"}
}