{
  "type": "Feature",
  "properties": {
    "iso:country":"US",
    "sg:address":"3950 Loop 306",
    "sg:city":"San Angelo",
    "sg:classifiers":[
        {
            "category":"Restaurant",
            "type":"Food & Drink"
        }
    ],
    "sg:menulink":"http://www.allmenus.com/tx/san-angelo/115023-chilis/menu/",
    "sg:phone":"915944988",
    "sg:postcode":"76904",
    "sg:province":"TX",
    "sg:tags":[
        "burger",
        "american",
        "sandwich",
        "tex-mex",
        "soup"
    ],
    "wof:name":"Chili's",
    "wof:placetype":"venue"
},
  "geometry": {"coordinates":[-100.497956,31.425189],"type":"Point"}
}