{
  "type": "Feature",
  "properties": {
    "iso:country":"US",
    "sg:address":"850 N Glenville Dr",
    "sg:city":"Richardson",
    "sg:classifiers":[
        {
            "category":"Wholesale",
            "subcategory":"Machinery & Supplies",
            "type":"Manufacturing & Wholesale Goods"
        }
    ],
    "sg:phone":"+1 972 231 0314",
    "sg:postcode":"75081",
    "sg:province":"TX",
    "sg:tags":[
        "equipment",
        "industrial",
        "including",
        "meter"
    ],
    "wof:name":"Egc Instruments & Controls",
    "wof:placetype":"venue"
},
  "geometry": {"coordinates":[-96.70528299999999,32.958679],"type":"Point"}
}