{
  "type": "Feature",
  "properties": {
    "iso:country":"US",
    "sg:address":"414 W Texas Ave",
    "sg:city":"Midland",
    "sg:classifiers":[
        {
            "category":"Banks & Credit Unions",
            "subcategory":"Investment Brokerage",
            "type":"Services"
        }
    ],
    "sg:phone":"+1 432 683 3071",
    "sg:postcode":"79701",
    "sg:province":"TX",
    "sg:tags":[
        "land",
        "oil",
        "lease"
    ],
    "wof:name":"Michael S Braun",
    "wof:placetype":"venue"
},
  "geometry": {"coordinates":[-102.079168,31.998537],"type":"Point"}
}