{
  "type": "Feature",
  "properties": {
    "iso:country":"US",
    "sg:address":"6117 Greenville Ave",
    "sg:city":"Dallas",
    "sg:classifiers":[
        {
            "category":"Shopping",
            "subcategory":"Optical Goods",
            "type":"Retail Goods"
        }
    ],
    "sg:phone":"+1 214 750 0004",
    "sg:postcode":"75206",
    "sg:province":"TX",
    "sg:tags":[
        "optician",
        "eyewear"
    ],
    "wof:name":"Payrite Optical",
    "wof:placetype":"venue"
},
  "geometry": {"coordinates":[-96.768097,32.860401],"type":"Point"}
}