{
  "type": "Feature",
  "properties": {
    "iso:country":"US",
    "sg:address":"409 E Centerville Rd",
    "sg:city":"Garland",
    "sg:classifiers":[
        {
            "category":"Health Services",
            "subcategory":"Clinic",
            "type":"Services"
        }
    ],
    "sg:phone":"+1 972 203 1466",
    "sg:postcode":"75041",
    "sg:province":"TX",
    "sg:tags":[
        "home"
    ],
    "wof:name":"Vision Home Health Care Inc",
    "wof:placetype":"venue"
},
  "geometry": {"coordinates":[-96.623856,32.877032],"type":"Point"}
}