{
  "type": "Feature",
  "properties": {
    "iso:country":"US",
    "sg:address":"13365 Kuykendall Mountain Rd",
    "sg:city":"Temple",
    "sg:classifiers":[
        {
            "category":"Shopping",
            "subcategory":"Used Merchandise",
            "type":"Retail Goods"
        }
    ],
    "sg:phone":"+1 254 986 2994",
    "sg:postcode":"76502",
    "sg:province":"TX",
    "wof:name":"Roy D Harmon",
    "wof:placetype":"venue"
},
  "geometry": {"coordinates":[-97.462676,31.191297],"type":"Point"}
}