{
  "type": "Feature",
  "properties": {
    "iso:country":"US",
    "sg:address":"1103 University Ave",
    "sg:city":"Lubbock",
    "sg:classifiers":[
        {
            "category":"Shopping",
            "subcategory":"Books",
            "type":"Retail Goods"
        }
    ],
    "sg:phone":"+1 806 744 0888",
    "sg:postcode":"79401",
    "sg:province":"TX",
    "sg:tags":[
        "dealer"
    ],
    "wof:name":"Double T Bookstore",
    "wof:placetype":"venue"
},
  "geometry": {"coordinates":[-101.87055599999999,33.584535],"type":"Point"}
}