{
  "type": "Feature",
  "properties": {
    "iso:country":"US",
    "sg:address":"1406 NW 19th St",
    "sg:city":"Grand Prairie",
    "sg:classifiers":[
        {
            "category":"Restaurant",
            "type":"Food & Drink"
        }
    ],
    "sg:menulink":"http://www.allmenus.com/tx/southwest/11728-dennys/menu/",
    "sg:phone":"+1 972 988 6121",
    "sg:postcode":"75050",
    "sg:province":"TX",
    "sg:tags":[
        "american",
        "diner"
    ],
    "wof:name":"Denny's",
    "wof:placetype":"venue"
},
  "geometry": {"coordinates":[-97.028274,32.757377],"type":"Point"}
}