{
  "type": "Feature",
  "properties": {
    "iso:country":"US",
    "sg:address":"6301 Manchaca Rd",
    "sg:city":"Austin",
    "sg:classifiers":[
        {
            "category":"Health Services",
            "subcategory":"Clinic",
            "type":"Services"
        }
    ],
    "sg:phone":"+1 512 444 9346",
    "sg:postcode":"78745",
    "sg:province":"TX",
    "sg:tags":[
        "examination",
        "insurance"
    ],
    "wof:name":"Exam One World Wide Inc",
    "wof:placetype":"venue"
},
  "geometry": {"coordinates":[-97.804126,30.209699],"type":"Point"}
}