{
  "type": "Feature",
  "properties": {
    "iso:country":"US",
    "sg:address":"5811 Everglade Rd",
    "sg:city":"Dallas",
    "sg:phone":"+1 214 388 3550",
    "sg:postcode":"75227",
    "sg:province":"TX",
    "wof:name":"Sharon's Playground Day Care",
    "wof:placetype":"venue"
},
  "geometry": {"coordinates":[-96.702016,32.785412],"type":"Point"}
}