{
  "type": "Feature",
  "properties": {
    "iso:country":"US",
    "sg:address":"1007 N Earl Rudder Fwy",
    "sg:city":"Bryan",
    "sg:classifiers":[
        {
            "category":"Building & Trades",
            "subcategory":"Construction",
            "type":"Services"
        }
    ],
    "sg:phone":"+1 979 776 5700",
    "sg:postcode":"77802",
    "sg:province":"TX",
    "sg:tags":[
        "general",
        "contractor"
    ],
    "wof:name":"Tex Lan-Co Construction Svc",
    "wof:placetype":"venue"
},
  "geometry": {"coordinates":[-96.34584599999999,30.681866],"type":"Point"}
}