{
  "type": "Feature",
  "properties": {
    "iso:country":"US",
    "sg:address":"431 Abiso Ave",
    "sg:city":"San Antonio",
    "sg:classifiers":[
        {
            "category":"Professional",
            "subcategory":"Business Services",
            "type":"Services"
        }
    ],
    "sg:phone":"+1 210 828 0295",
    "sg:postcode":"78209",
    "sg:province":"TX",
    "wof:name":"Lisa W Graham Interior Design",
    "wof:placetype":"venue"
},
  "geometry": {"coordinates":[-98.472973,29.481604],"type":"Point"}
}