{
  "type": "Feature",
  "properties": {
    "iso:country":"US",
    "sg:address":"3008 W Division St",
    "sg:city":"Arlington",
    "sg:classifiers":[
        {
            "category":"Personal",
            "type":"Services"
        }
    ],
    "sg:phone":"+1 682 323 5163",
    "sg:postcode":"76012",
    "sg:province":"TX",
    "sg:tags":[
        "consultant",
        "planning",
        "wedding"
    ],
    "wof:name":"Inspired Touch Event Solutions",
    "wof:placetype":"venue"
},
  "geometry": {"coordinates":[-97.15772200000001,32.735889],"type":"Point"}
}