{
  "type": "Feature",
  "properties": {
    "iso:country":"US",
    "sg:address":"4042 Doniphan Dr",
    "sg:city":"El Paso",
    "sg:classifiers":[
        {
            "category":"Professional",
            "subcategory":"Detective & Security Services",
            "type":"Services"
        }
    ],
    "sg:phone":"+1 915 585 8190",
    "sg:postcode":"79922",
    "sg:province":"TX",
    "sg:tags":[
        "fire",
        "installation",
        "alarm",
        "monitoring",
        "intrusion"
    ],
    "wof:name":"Sonitrol of El Paso",
    "wof:placetype":"venue"
},
  "geometry": {"coordinates":[-106.56137200000001,31.816562],"type":"Point"}
}