{
  "type": "Feature",
  "properties": {
    "iso:country":"US",
    "sg:address":"841 US Hwy 90 Alt",
    "sg:city":"Richmond",
    "sg:classifiers":[
        {
            "category":"Home & Garden",
            "subcategory":"Building Materials",
            "type":"Retail Goods"
        }
    ],
    "sg:phone":"+1 281 344 9123",
    "sg:postcode":"77469",
    "sg:province":"TX",
    "sg:tags":[
        "paint"
    ],
    "wof:name":"Hausler's Paint & Decorating",
    "wof:placetype":"venue"
},
  "geometry": {"coordinates":[-95.751469,29.586871],"type":"Point"}
}