{
  "type": "Feature",
  "properties": {
    "iso:country":"US",
    "sg:address":"2308 S 2nd Ave",
    "sg:city":"Dallas",
    "sg:classifiers":[
        {
            "category":"Autos & Motor Vehicles",
            "subcategory":"Auto Supplies",
            "type":"Retail Goods"
        }
    ],
    "sg:phone":"+1 214 421 1168",
    "sg:postcode":"75210",
    "sg:province":"TX",
    "sg:tags":[
        "equipment",
        "air",
        "conditioning",
        "automobile"
    ],
    "wof:name":"Hunt Air Cond & Radiator Rpr",
    "wof:placetype":"venue"
},
  "geometry": {"coordinates":[-96.754564,32.769758],"type":"Point"}
}