{
  "type": "Feature",
  "properties": {
    "iso:country":"US",
    "sg:address":"5210 N Lamar Blvd",
    "sg:city":"Austin",
    "sg:classifiers":[
        {
            "category":"Wholesale",
            "subcategory":"Medical Equipment & Supplies",
            "type":"Manufacturing & Wholesale Goods"
        }
    ],
    "sg:phone":"+1 512 407 8002",
    "sg:postcode":"78751",
    "sg:province":"TX",
    "sg:tags":[
        "physician",
        "surgeon"
    ],
    "wof:name":"Rotech Healthcare",
    "wof:placetype":"venue"
},
  "geometry": {"coordinates":[-97.729856,30.320365],"type":"Point"}
}