{
  "type": "Feature",
  "properties": {
    "iso:country":"US",
    "sg:address":"3209 Knickerbocker Rd",
    "sg:city":"San Angelo",
    "sg:classifiers":[
        {
            "category":"Retail",
            "subcategory":"Veterinary Services",
            "type":"Services"
        }
    ],
    "sg:phone":"+1 325 944 9444",
    "sg:postcode":"76904",
    "sg:province":"TX",
    "wof:name":"All Caring Animal Clinic",
    "wof:placetype":"venue"
},
  "geometry": {"coordinates":[-100.464803,31.424219],"type":"Point"}
}