{
  "type": "Feature",
  "properties": {
    "iso:country":"US",
    "sg:address":"7190 Edgewater Dr",
    "sg:city":"Willis",
    "sg:classifiers":[
        {
            "category":"Banks & Credit Unions",
            "subcategory":"Financial Services",
            "type":"Services"
        }
    ],
    "sg:phone":"+1 936 856 7274",
    "sg:postcode":"77318",
    "sg:province":"TX",
    "sg:tags":[
        "investment",
        "closed"
    ],
    "wof:name":"Rskt LLC",
    "wof:placetype":"venue"
},
  "geometry": {"coordinates":[-95.570418,30.41017],"type":"Point"}
}