{
  "type": "Feature",
  "properties": {
    "iso:country":"US",
    "sg:address":"8611 Meadville St",
    "sg:city":"Houston",
    "sg:classifiers":[
        {
            "category":"Restaurant",
            "type":"Food & Drink"
        }
    ],
    "sg:phone":"+1 713 643 1115",
    "sg:postcode":"77061",
    "sg:province":"TX",
    "sg:tags":[
        "eating"
    ],
    "wof:name":"Nicos Snacks Etc",
    "wof:placetype":"venue"
},
  "geometry": {"coordinates":[-95.26492500000001,29.660534],"type":"Point"}
}