{
  "type": "Feature",
  "properties": {
    "iso:country":"US",
    "sg:address":"6438 Kury Ln",
    "sg:city":"Houston",
    "sg:classifiers":[
        {
            "category":"Banks & Credit Unions",
            "subcategory":"Investment Brokerage",
            "type":"Services"
        }
    ],
    "sg:phone":"+1 713 869 2860",
    "sg:postcode":"77008",
    "sg:province":"TX",
    "wof:name":"Len-K Investments",
    "wof:placetype":"venue"
},
  "geometry": {"coordinates":[-95.427632,29.797403],"type":"Point"}
}