{
  "type": "Feature",
  "properties": {
    "iso:country":"US",
    "sg:address":"3776 Arapaho Rd",
    "sg:city":"Addison",
    "sg:classifiers":[
        {
            "category":"Shopping",
            "subcategory":"Computers & Home Electronics",
            "type":"Retail Goods"
        }
    ],
    "sg:phone":"+1 214 572 6631",
    "sg:postcode":"75001",
    "sg:province":"TX",
    "sg:website":"www.vicav.com",
    "wof:name":"Visual Innovations",
    "wof:placetype":"venue"
},
  "geometry": {"coordinates":[-96.852501,32.955898],"type":"Point"}
}