{
  "type": "Feature",
  "properties": {
    "iso:country":"US",
    "sg:address":"5501 W Rosedale St",
    "sg:city":"Fort Worth",
    "sg:classifiers":[
        {
            "category":"Travel",
            "subcategory":"Travel Agent",
            "type":"Entertainment"
        }
    ],
    "sg:phone":"+1 817 731 0836",
    "sg:postcode":"76107",
    "sg:province":"TX",
    "sg:tags":[
        "agency",
        "bureau"
    ],
    "sg:website":"www.pegasustravel.com",
    "wof:name":"Pegasus Travel Inc",
    "wof:placetype":"venue"
},
  "geometry": {"coordinates":[-97.406064,32.73231],"type":"Point"}
}