{
  "type": "Feature",
  "properties": {
    "iso:country":"US",
    "sg:address":"2115 Whiteback Dr",
    "sg:city":"Houston",
    "sg:classifiers":[
        {
            "category":"Building & Trades",
            "subcategory":"Construction",
            "type":"Services"
        }
    ],
    "sg:phone":"+1 281 578 6560",
    "sg:postcode":"77084",
    "sg:province":"TX",
    "sg:tags":[
        "concrete",
        "contractor"
    ],
    "wof:name":"J P Southwest Concrete Inc",
    "wof:placetype":"venue"
},
  "geometry": {"coordinates":[-95.71350099999999,29.797025],"type":"Point"}
}