{
  "type": "Feature",
  "properties": {
    "iso:country":"US",
    "sg:address":"2400 Quaker Ave",
    "sg:city":"Lubbock",
    "sg:classifiers":[
        {
            "category":"Health Services",
            "subcategory":"Nursing And Care Facility",
            "type":"Services"
        }
    ],
    "sg:phone":"+1 806 792 2831",
    "sg:postcode":"79410",
    "sg:province":"TX",
    "sg:tags":[
        "home",
        "convalescent"
    ],
    "wof:name":"Mi Casita Care Center",
    "wof:placetype":"venue"
},
  "geometry": {"coordinates":[-101.905113,33.5723],"type":"Point"}
}