{
  "type": "Feature",
  "properties": {
    "iso:country":"US",
    "sg:address":"9818 Whithorn Dr Ste B",
    "sg:city":"Houston",
    "sg:classifiers":[
        {
            "category":"Real Estate",
            "subcategory":"Real Estate Services",
            "type":"Services"
        },
        {
            "category":"Real Estate",
            "subcategory":"Real Estate Agent",
            "type":"Services"
        }
    ],
    "sg:phone":"+1 281 550 7000",
    "sg:postcode":"77095",
    "sg:province":"TX",
    "sg:tags":[
        "buyer",
        "broker"
    ],
    "wof:name":"Southwest Realty Consultants",
    "wof:placetype":"venue"
},
  "geometry": {"coordinates":[-95.647524,29.927424],"type":"Point"}
}