{
  "type": "Feature",
  "properties": {
    "iso:country":"US",
    "sg:address":"3908 Spring River Dr",
    "sg:city":"Pearland",
    "sg:classifiers":[
        {
            "category":"Shopping",
            "subcategory":"Gifts & Souvenirs",
            "type":"Retail Goods"
        }
    ],
    "sg:phone":"+1 281 489 7096",
    "sg:postcode":"77584",
    "sg:province":"TX",
    "sg:tags":[
        "basket"
    ],
    "wof:name":"A Basket Full Of Texas",
    "wof:placetype":"venue"
},
  "geometry": {"coordinates":[-95.304579,29.537441],"type":"Point"}
}