{
  "type": "Feature",
  "properties": {
    "iso:country":"US",
    "sg:address":"525 N Sam Houston Pkwy E #390",
    "sg:city":"Houston",
    "sg:classifiers":[
        {
            "category":"Professional",
            "subcategory":"Computer Services",
            "type":"Services"
        }
    ],
    "sg:phone":"+1 281 445 3600",
    "sg:postcode":"77060",
    "sg:province":"TX",
    "sg:tags":[
        "repair"
    ],
    "sg:website":"www.deltabsolutions.com",
    "wof:name":"Delta Business Solutions",
    "wof:placetype":"venue"
},
  "geometry": {"coordinates":[-95.391227,29.939797],"type":"Point"}
}