{
  "type": "Feature",
  "properties": {
    "iso:country":"US",
    "sg:address":"110 Truly Plz",
    "sg:city":"Cleveland",
    "sg:classifiers":[
        {
            "category":"Insurance",
            "subcategory":"Hazard Insurance",
            "type":"Services"
        }
    ],
    "sg:phone":"+1 281 593 3878",
    "sg:postcode":"77327",
    "sg:province":"TX",
    "wof:name":"Insure Auto",
    "wof:placetype":"venue"
},
  "geometry": {"coordinates":[-95.09613299999999,30.334332],"type":"Point"}
}