{
  "type": "Feature",
  "properties": {
    "iso:country":"US",
    "sg:address":"50 Briar Hollow Ln Ste 245W",
    "sg:city":"Houston",
    "sg:classifiers":[
        {
            "category":"Health Services",
            "subcategory":"Dentist",
            "type":"Services"
        }
    ],
    "sg:phone":"+1 713 840 8501",
    "sg:postcode":"77027",
    "sg:province":"TX",
    "wof:name":"ORAL RECONSTRUCTION AND COSMETIC",
    "wof:placetype":"venue"
},
  "geometry": {"coordinates":[-95.451852,29.754837],"type":"Point"}
}