{
  "type": "Feature",
  "properties": {
    "iso:country":"US",
    "sg:address":"541 Ryan Ave",
    "sg:city":"Odessa",
    "sg:classifiers":[
        {
            "category":"Home & Garden",
            "subcategory":"Building Materials",
            "type":"Retail Goods"
        }
    ],
    "sg:phone":"+1 432 580 7430",
    "sg:postcode":"79761",
    "sg:province":"TX",
    "wof:name":"Alpha Overhead Door",
    "wof:placetype":"venue"
},
  "geometry": {"coordinates":[-102.342876,31.857451],"type":"Point"}
}