{
  "type": "Feature",
  "properties": {
    "iso:country":"US",
    "sg:address":"6502 Mohawk St",
    "sg:city":"Houston",
    "sg:classifiers":[
        {
            "category":"Recreation",
            "type":"Entertainment"
        }
    ],
    "sg:phone":"+1 281 987 9964",
    "sg:postcode":"77016",
    "sg:province":"TX",
    "sg:tags":[
        "amusement"
    ],
    "wof:name":"Bartender's For Hire",
    "wof:placetype":"venue"
},
  "geometry": {"coordinates":[-95.290536,29.877649],"type":"Point"}
}