{
  "type": "Feature",
  "properties": {
    "iso:country":"US",
    "sg:address":"9600 Harrell Rd",
    "sg:city":"Grandview",
    "sg:classifiers":[
        {
            "category":"Building & Trades",
            "subcategory":"Construction",
            "type":"Services"
        }
    ],
    "sg:phone":"+1 682 429 9099",
    "sg:postcode":"76050",
    "sg:province":"TX",
    "sg:tags":[
        "painter"
    ],
    "wof:name":"Brigandi Custom Painting",
    "wof:placetype":"venue"
},
  "geometry": {"coordinates":[-97.24686199999999,32.262439],"type":"Point"}
}