{
  "type": "Feature",
  "properties": {
    "iso:country":"US",
    "sg:address":"3923 Fry Ave",
    "sg:city":"Tyler",
    "sg:classifiers":[
        {
            "category":"Real Estate",
            "subcategory":"Real Estate Agent",
            "type":"Services"
        }
    ],
    "sg:phone":"+1 903 534 9122",
    "sg:postcode":"75701",
    "sg:province":"TX",
    "sg:tags":[
        "property",
        "management"
    ],
    "wof:name":"J & A Properties",
    "wof:placetype":"venue"
},
  "geometry": {"coordinates":[-95.293502,32.305466],"type":"Point"}
}