{
  "type": "Feature",
  "properties": {
    "iso:country":"US",
    "sg:address":"258 Old Orchard Ln",
    "sg:city":"Bandera",
    "sg:classifiers":[
        {
            "category":"Professional",
            "subcategory":"Management & Consulting",
            "type":"Services"
        }
    ],
    "sg:phone":"+1 830 460 8188",
    "sg:postcode":"78003",
    "sg:province":"TX",
    "wof:name":"Jaw Management LLC",
    "wof:placetype":"venue"
},
  "geometry": {"coordinates":[-99.02534199999999,29.738133],"type":"Point"}
}