{
  "type": "Feature",
  "properties": {
    "iso:country":"US",
    "sg:address":"2000 I- 35 Bus",
    "sg:city":"Round Rock",
    "sg:classifiers":[
        {
            "category":"Restaurant",
            "type":"Food & Drink"
        }
    ],
    "sg:phone":"+1 512 388 4068",
    "sg:postcode":"78626",
    "sg:province":"TX",
    "sg:tags":[
        "eating"
    ],
    "wof:name":"Lubys Inc",
    "wof:placetype":"venue"
},
  "geometry": {"coordinates":[-97.668013,30.6618],"type":"Point"}
}