{
  "type": "Feature",
  "properties": {
    "iso:country":"US",
    "sg:address":"10039 Bissonnet St",
    "sg:city":"Houston",
    "sg:classifiers":[
        {
            "category":"Health Services",
            "subcategory":"Doctor",
            "type":"Services"
        }
    ],
    "sg:phone":"+1 832 484 6900",
    "sg:postcode":"77036",
    "sg:province":"TX",
    "sg:tags":[
        "clinic"
    ],
    "wof:name":"Evangel Health Svc",
    "wof:placetype":"venue"
},
  "geometry": {"coordinates":[-95.555432,29.674896],"type":"Point"}
}