{
  "type": "Feature",
  "properties": {
    "iso:country":"US",
    "sg:address":"6455 Wister Ln",
    "sg:city":"Houston",
    "sg:classifiers":[
        {
            "category":"Building & Trades",
            "subcategory":"Construction",
            "type":"Services"
        }
    ],
    "sg:phone":"+1 281 933 3724",
    "sg:postcode":"77008",
    "sg:province":"TX",
    "sg:tags":[
        "house"
    ],
    "wof:name":"Nest Construction",
    "wof:placetype":"venue"
},
  "geometry": {"coordinates":[-95.42626799999999,29.791688],"type":"Point"}
}