{
  "type": "Feature",
  "properties": {
    "iso:country":"US",
    "sg:address":"516 E Main Ave",
    "sg:city":"Robstown",
    "sg:classifiers":[
        {
            "category":"Retail",
            "subcategory":"Repair Shop",
            "type":"Services"
        }
    ],
    "sg:phone":"+1 361 387 4593",
    "sg:postcode":"78380",
    "sg:province":"TX",
    "wof:name":"Rtronix",
    "wof:placetype":"venue"
},
  "geometry": {"coordinates":[-97.662347,27.789114],"type":"Point"}
}