{
  "type": "Feature",
  "properties": {
    "iso:country":"US",
    "sg:address":"6638 Harrisburg Blvd",
    "sg:city":"Houston",
    "sg:classifiers":[
        {
            "category":"Personal",
            "type":"Services"
        }
    ],
    "sg:phone":"+1 713 923 3091",
    "sg:postcode":"77011",
    "sg:province":"TX",
    "wof:name":"Higher Image",
    "wof:placetype":"venue"
},
  "geometry": {"coordinates":[-95.30895599999999,29.737709],"type":"Point"}
}