{
  "type": "Feature",
  "properties": {
    "iso:country":"US",
    "sg:address":"5909 W Loop Fwy",
    "sg:city":"Bellaire",
    "sg:classifiers":[
        {
            "category":"Real Estate",
            "subcategory":"Architect",
            "type":"Services"
        }
    ],
    "sg:phone":"+1 713 666 2185",
    "sg:postcode":"77401",
    "sg:province":"TX",
    "wof:name":"Cameron Architects Inc",
    "wof:placetype":"venue"
},
  "geometry": {"coordinates":[-95.459672,29.717959],"type":"Point"}
}