{
  "type": "Feature",
  "properties": {
    "iso:country":"US",
    "sg:address":"724 W Fm 1626",
    "sg:city":"Austin",
    "sg:classifiers":[
        {
            "category":"Social Services",
            "type":"Services"
        },
        {
            "category":"Building & Trades",
            "subcategory":"Construction",
            "type":"Services"
        },
        {
            "category":"Home & Garden",
            "subcategory":"Mobile Homes",
            "type":"Retail Goods"
        }
    ],
    "sg:phone":"+1 512 282 7188",
    "sg:postcode":"78748",
    "sg:province":"TX",
    "sg:tags":[
        "manufactured",
        "housing-communities",
        "park"
    ],
    "wof:name":"Forest Oaks Village Mfd Home",
    "wof:placetype":"venue"
},
  "geometry": {"coordinates":[-97.824797,30.140615],"type":"Point"}
}