{
  "type": "Feature",
  "properties": {
    "iso:country":"US",
    "sg:address":"15314 Tadworth Dr",
    "sg:city":"Houston",
    "sg:classifiers":[
        {
            "category":"Manufacturing",
            "subcategory":"Food",
            "type":"Manufacturing & Wholesale Goods"
        }
    ],
    "sg:phone":"+1 281 286 4313",
    "sg:postcode":"77062",
    "sg:province":"TX",
    "sg:tags":[
        "drink",
        "soft",
        "mfg"
    ],
    "wof:name":"Bubble Island LLC",
    "wof:placetype":"venue"
},
  "geometry": {"coordinates":[-95.143461,29.567122],"type":"Point"}
}