{
  "type": "Feature",
  "properties": {
    "iso:country":"US",
    "sg:address":"217 S Alamo St",
    "sg:city":"Refugio",
    "sg:classifiers":[
        {
            "category":"Restaurant",
            "type":"Food & Drink"
        }
    ],
    "sg:menulink":"http://www.allmenus.com/tx/refugio/130581-subway/menu/",
    "sg:phone":"+1 361 526 1720",
    "sg:postcode":"78377",
    "sg:province":"TX",
    "sg:tags":[
        "american",
        "sandwich"
    ],
    "wof:name":"Subway",
    "wof:placetype":"venue"
},
  "geometry": {"coordinates":[-97.275463,28.303949],"type":"Point"}
}