{
  "type": "Feature",
  "properties": {
    "iso:country":"US",
    "sg:address":"3504 Bordeaux Ln",
    "sg:city":"Hurst",
    "sg:classifiers":[
        {
            "category":"Professional",
            "subcategory":"Business Services",
            "type":"Services"
        }
    ],
    "sg:phone":"+1 877 528 5497",
    "sg:postcode":"76054",
    "sg:province":"TX",
    "wof:name":"A & Notable Enterprises",
    "wof:placetype":"venue"
},
  "geometry": {"coordinates":[-97.176501,32.885695],"type":"Point"}
}