{
  "type": "Feature",
  "properties": {
    "iso:country":"US",
    "sg:address":"3615 Duncaster Dr",
    "sg:city":"Missouri City",
    "sg:classifiers":[
        {
            "category":"Professional",
            "subcategory":"Business Services",
            "type":"Services"
        }
    ],
    "sg:phone":"+1 281 499 5437",
    "sg:postcode":"77459",
    "sg:province":"TX",
    "wof:name":"Roy C Logan Tax & Accntng S",
    "wof:placetype":"venue"
},
  "geometry": {"coordinates":[-95.562533,29.571358],"type":"Point"}
}