{
  "type": "Feature",
  "properties": {
    "iso:country":"US",
    "sg:address":"307 E Main St",
    "sg:city":"Eagle Lake",
    "sg:classifiers":[
        {
            "category":"Home & Garden",
            "subcategory":"Furniture",
            "type":"Retail Goods"
        }
    ],
    "sg:phone":"+1 979 234 2534",
    "sg:postcode":"77434",
    "sg:province":"TX",
    "sg:tags":[
        "appliance"
    ],
    "wof:name":"Furniture Shoppe",
    "wof:placetype":"venue"
},
  "geometry": {"coordinates":[-96.333342,29.587643],"type":"Point"}
}