{
  "type": "Feature",
  "properties": {
    "iso:country":"US",
    "sg:address":"8622 Blossom Ln",
    "sg:city":"Dallas",
    "sg:classifiers":[
        {
            "category":"Building & Trades",
            "subcategory":"Plumbing",
            "type":"Services"
        }
    ],
    "sg:phone":"+1 214 388 3934",
    "sg:postcode":"75227",
    "sg:province":"TX",
    "sg:tags":[
        "conditioning",
        "air",
        "system",
        "contractor"
    ],
    "wof:name":"Myers Air Conditioning & Htg",
    "wof:placetype":"venue"
},
  "geometry": {"coordinates":[-96.67180399999999,32.758664],"type":"Point"}
}