{
  "type": "Feature",
  "properties": {
    "iso:country":"US",
    "sg:address":"5033 Saunders Rd",
    "sg:city":"Fort Worth",
    "sg:classifiers":[
        {
            "category":"Wholesale",
            "subcategory":"Machinery & Supplies",
            "type":"Manufacturing & Wholesale Goods"
        }
    ],
    "sg:phone":"+1 817 538 1217",
    "sg:postcode":"76119",
    "sg:province":"TX",
    "wof:name":"Decherts Ldscpg & Irrigation",
    "wof:placetype":"venue"
},
  "geometry": {"coordinates":[-97.24485300000001,32.676704],"type":"Point"}
}