{
  "type": "Feature",
  "properties": {
    "iso:country":"US",
    "sg:address":"3801 E Interstate 20 Svc Rd",
    "sg:city":"Alvarado",
    "sg:classifiers":[
        {
            "category":"Autos & Motor Vehicles",
            "subcategory":"Automobile Sales",
            "type":"Retail Goods"
        }
    ],
    "sg:phone":"+1 817 783 3709",
    "sg:postcode":"76087",
    "sg:province":"TX",
    "sg:tags":[
        "used"
    ],
    "wof:name":"Exotic Sporty Cars",
    "wof:placetype":"venue"
},
  "geometry": {"coordinates":[-97.634399,32.734519],"type":"Point"}
}