{
  "type": "Feature",
  "properties": {
    "iso:country":"US",
    "sg:address":"2409 S Collins St",
    "sg:city":"Arlington",
    "sg:classifiers":[
        {
            "category":"Personal",
            "subcategory":"Beauty Salon",
            "type":"Services"
        }
    ],
    "sg:phone":"+1 817 795 2499",
    "sg:postcode":"76014",
    "sg:province":"TX",
    "sg:tags":[
        "shop"
    ],
    "wof:name":"Styles On The One",
    "wof:placetype":"venue"
},
  "geometry": {"coordinates":[-97.097471,32.705036],"type":"Point"}
}