{
  "type": "Feature",
  "properties": {
    "iso:country":"US",
    "sg:address":"906 Laird St",
    "sg:city":"Pasadena",
    "sg:classifiers":[
        {
            "category":"Building & Trades",
            "subcategory":"Landscaping Services",
            "type":"Services"
        }
    ],
    "sg:phone":"+1 713 477 4972",
    "sg:postcode":"77506",
    "sg:province":"TX",
    "sg:tags":[
        "tree"
    ],
    "wof:name":"Noel Tree Service",
    "wof:placetype":"venue"
},
  "geometry": {"coordinates":[-95.20308799999999,29.703931],"type":"Point"}
}