{
  "type": "Feature",
  "properties": {
    "iso:country":"US",
    "sg:address":"4124 W Vickery Blvd",
    "sg:city":"Fort Worth",
    "sg:classifiers":[
        {
            "category":"Professional",
            "subcategory":"Business Services",
            "type":"Services"
        }
    ],
    "sg:phone":"+1 817 738 0097",
    "sg:postcode":"76107",
    "sg:province":"TX",
    "sg:tags":[
        "interior",
        "designer",
        "decorator"
    ],
    "wof:name":"Accent Wallcoverings Interiors",
    "wof:placetype":"venue"
},
  "geometry": {"coordinates":[-97.37826099999999,32.72649],"type":"Point"}
}