{
  "type": "Feature",
  "properties": {
    "iso:country":"US",
    "sg:address":"435 US Hwy 281",
    "sg:city":"Mercedes",
    "sg:classifiers":[
        {
            "category":"Food & Beverages",
            "subcategory":"Groceries & Convenience Stores",
            "type":"Retail Goods"
        }
    ],
    "sg:phone":"+1 956 514 1765",
    "sg:postcode":"78520",
    "sg:province":"TX",
    "sg:tags":[
        "grocer"
    ],
    "wof:name":"Circle K",
    "wof:placetype":"venue"
},
  "geometry": {"coordinates":[-97.513993,25.926185],"type":"Point"}
}