{
  "type": "Feature",
  "properties": {
    "iso:country":"US",
    "sg:address":"1355 N Glenville Dr",
    "sg:city":"Richardson",
    "sg:classifiers":[
        {
            "category":"Professional",
            "type":"Services"
        }
    ],
    "sg:phone":"+1 972 907 0011",
    "sg:postcode":"75081",
    "sg:province":"TX",
    "wof:name":"TSR Silicon Resources Inc",
    "wof:placetype":"venue"
},
  "geometry": {"coordinates":[-96.70545,32.96227],"type":"Point"}
}