{
  "type": "Feature",
  "properties": {
    "iso:country":"US",
    "sg:address":"3300 N 22nd St",
    "sg:city":"Waco",
    "sg:classifiers":[
        {
            "category":"Organizations",
            "subcategory":"Religious Organization",
            "type":"Services"
        }
    ],
    "sg:phone":"+1 254 754 4248",
    "sg:postcode":"76708",
    "sg:province":"TX",
    "wof:name":"WACO Bible Chapel",
    "wof:placetype":"venue"
},
  "geometry": {"coordinates":[-97.173086,31.57388],"type":"Point"}
}