{
  "type": "Feature",
  "properties": {
    "iso:country":"US",
    "sg:address":"2003 E Scott Ave",
    "sg:city":"Wichita Falls",
    "sg:classifiers":[
        {
            "category":"Wholesale",
            "subcategory":"Hardware",
            "type":"Manufacturing & Wholesale Goods"
        }
    ],
    "sg:phone":"+1 940 322 1853",
    "sg:postcode":"76301",
    "sg:province":"TX",
    "sg:tags":[
        "plumbing"
    ],
    "wof:name":"Marta Co",
    "wof:placetype":"venue"
},
  "geometry": {"coordinates":[-98.449242,33.89665],"type":"Point"}
}