{
  "type": "Feature",
  "properties": {
    "iso:country":"US",
    "sg:address":"3508 Buckholt St",
    "sg:city":"Pearland",
    "sg:classifiers":[
        {
            "category":"Personal",
            "subcategory":"Beauty Salon",
            "type":"Services"
        }
    ],
    "sg:phone":"+1 281 996 0083",
    "sg:postcode":"77581",
    "sg:province":"TX",
    "wof:name":"The Inside Affair",
    "wof:placetype":"venue"
},
  "geometry": {"coordinates":[-95.23925800000001,29.536339],"type":"Point"}
}