{
  "type": "Feature",
  "properties": {
    "iso:country":"US",
    "sg:address":"624 N Main St",
    "sg:city":"Boerne",
    "sg:classifiers":[
        {
            "category":"Social Services",
            "type":"Services"
        }
    ],
    "sg:phone":"+1 830 249 8273",
    "sg:postcode":"78006",
    "sg:province":"TX",
    "sg:tags":[
        "counseling"
    ],
    "wof:name":"Kathy Heard Counseling",
    "wof:placetype":"venue"
},
  "geometry": {"coordinates":[-98.73468200000001,29.799261],"type":"Point"}
}