{
  "type": "Feature",
  "properties": {
    "iso:country":"US",
    "sg:address":"302 Cullum Dr",
    "sg:city":"Euless",
    "sg:classifiers":[
        {
            "category":"Building & Trades",
            "subcategory":"Landscaping Services",
            "type":"Services"
        }
    ],
    "sg:phone":"+1 817 368 9783",
    "sg:postcode":"76040",
    "sg:province":"TX",
    "sg:tags":[
        "landscape"
    ],
    "wof:name":"Gails Gardens & Designs",
    "wof:placetype":"venue"
},
  "geometry": {"coordinates":[-97.079402,32.831629],"type":"Point"}
}