{
  "type": "Feature",
  "properties": {
    "iso:country":"US",
    "sg:address":"1645 Pat Booker Rd",
    "sg:city":"Universal City",
    "sg:classifiers":[
        {
            "category":"Professional",
            "subcategory":"Accounting & Tax Preparation",
            "type":"Services"
        }
    ],
    "sg:phone":"+1 210 659 8500",
    "sg:postcode":"78148",
    "sg:province":"TX",
    "sg:tags":[
        "return",
        "filing"
    ],
    "wof:name":"Liberty Tax Svc",
    "wof:placetype":"venue"
},
  "geometry": {"coordinates":[-98.30580500000001,29.552479],"type":"Point"}
}