{
  "type": "Feature",
  "properties": {
    "iso:country":"US",
    "sg:address":"5600 Colleyville Blvd",
    "sg:city":"Colleyville",
    "sg:classifiers":[
        {
            "category":"Personal",
            "subcategory":"Beauty Salon",
            "type":"Services"
        }
    ],
    "sg:phone":"+1 817 788 0502",
    "sg:postcode":"76034",
    "sg:province":"TX",
    "sg:tags":[
        "shop",
        "manicuring"
    ],
    "wof:name":"Nail Trix",
    "wof:placetype":"venue"
},
  "geometry": {"coordinates":[-97.14943700000001,32.89002],"type":"Point"}
}