{
  "type": "Feature",
  "properties": {
    "iso:country":"US",
    "sg:address":"2425 Evergreen Dr",
    "sg:city":"Pearland",
    "sg:classifiers":[
        {
            "category":"Building & Trades",
            "subcategory":"Landscaping Services",
            "type":"Services"
        }
    ],
    "sg:phone":"+1 281 993 9179",
    "sg:postcode":"77581",
    "sg:province":"TX",
    "wof:name":"Fernandez Lawn Service",
    "wof:placetype":"venue"
},
  "geometry": {"coordinates":[-95.223973,29.553246],"type":"Point"}
}