{
  "type": "Feature",
  "properties": {
    "iso:country":"US",
    "sg:address":"500 E Olmos Dr",
    "sg:city":"San Antonio",
    "sg:classifiers":[
        {
            "category":"Banks & Credit Unions",
            "subcategory":"Financial Services",
            "type":"Services"
        }
    ],
    "sg:phone":"+1 210 829 8983",
    "sg:postcode":"78212",
    "sg:province":"TX",
    "sg:tags":[
        "company",
        "holding"
    ],
    "wof:name":"Sycamore Holdings Inc",
    "wof:placetype":"venue"
},
  "geometry": {"coordinates":[-98.48584,29.470858],"type":"Point"}
}