{
  "type": "Feature",
  "properties": {
    "iso:country":"US",
    "sg:address":"2310 Northshore Dr",
    "sg:city":"Humble",
    "sg:classifiers":[
        {
            "category":"Real Estate",
            "subcategory":"Developer",
            "type":"Services"
        }
    ],
    "sg:phone":"+1 281 358 7646",
    "sg:postcode":"77339",
    "sg:province":"TX",
    "sg:tags":[
        "cemetery"
    ],
    "wof:name":"New Hope Cemetery Association",
    "wof:placetype":"venue"
},
  "geometry": {"coordinates":[-95.22259200000001,30.026619],"type":"Point"}
}