{
  "type": "Feature",
  "properties": {
    "iso:country":"US",
    "sg:address":"449 W Kansas St",
    "sg:city":"Van",
    "sg:classifiers":[
        {
            "category":"Retail",
            "subcategory":"Laundry & Dry Cleaning",
            "type":"Services"
        }
    ],
    "sg:phone":"+1 903 963 8675",
    "sg:postcode":"75790",
    "sg:province":"TX",
    "wof:name":"Big Sky Carpet & Fiber Care",
    "wof:placetype":"venue"
},
  "geometry": {"coordinates":[-95.64310399999999,32.521543],"type":"Point"}
}