{
  "type": "Feature",
  "properties": {
    "iso:country":"US",
    "sg:address":"3420 FM 1461",
    "sg:city":"Mc Kinney",
    "sg:classifiers":[
        {
            "category":"Professional",
            "type":"Services"
        }
    ],
    "sg:phone":"+1 972 685 0952",
    "sg:postcode":"75071",
    "sg:province":"TX",
    "wof:name":"N Nortel Corp",
    "wof:placetype":"venue"
},
  "geometry": {"coordinates":[-96.67988699999999,33.25215],"type":"Point"}
}