{
  "type": "Feature",
  "properties": {
    "iso:country":"US",
    "sg:address":"7920 E Parker Rd",
    "sg:city":"Allen",
    "sg:classifiers":[
        {
            "category":"Retail",
            "subcategory":"Auto Repair",
            "type":"Services"
        }
    ],
    "sg:phone":"+1 972 442 4439",
    "sg:postcode":"75002",
    "sg:province":"TX",
    "sg:tags":[
        "body"
    ],
    "wof:name":"Kurts Collision Center",
    "wof:placetype":"venue"
},
  "geometry": {"coordinates":[-96.57821800000001,33.054923],"type":"Point"}
}