{
  "type": "Feature",
  "properties": {
    "iso:country":"US",
    "sg:address":"6726 N Martin Luther King Ave",
    "sg:city":"Hitchcock",
    "sg:classifiers":[
        {
            "category":"Retail",
            "subcategory":"Car Wash",
            "type":"Services"
        }
    ],
    "sg:phone":"+1 409 316 0415",
    "sg:postcode":"77563",
    "sg:province":"TX",
    "sg:tags":[
        "carwash"
    ],
    "wof:name":"Woodard Detailing",
    "wof:placetype":"venue"
},
  "geometry": {"coordinates":[-95.00308699999999,29.342761],"type":"Point"}
}