{
  "type": "Feature",
  "properties": {
    "iso:country":"US",
    "sg:address":"913 Parker Dr",
    "sg:city":"Coppell",
    "sg:classifiers":[
        {
            "category":"Professional",
            "subcategory":"Computer Services",
            "type":"Services"
        }
    ],
    "sg:phone":"+1 972 462 9066",
    "sg:postcode":"75019",
    "sg:province":"TX",
    "sg:tags":[
        "related"
    ],
    "wof:name":"Excellence In Computing Inc",
    "wof:placetype":"venue"
},
  "geometry": {"coordinates":[-96.961676,32.980637],"type":"Point"}
}