{
  "type": "Feature",
  "properties": {
    "iso:country":"US",
    "sg:address":"1830 Waco Ave",
    "sg:city":"Port Arthur",
    "sg:classifiers":[
        {
            "category":"Personal",
            "subcategory":"Beauty Salon",
            "type":"Services"
        }
    ],
    "sg:phone":"+1 409 983 3332",
    "sg:postcode":"77640",
    "sg:province":"TX",
    "sg:tags":[
        "shop"
    ],
    "wof:name":"Marcella's Clip Or Curl",
    "wof:placetype":"venue"
},
  "geometry": {"coordinates":[-93.947332,29.881684],"type":"Point"}
}