{
  "type": "Feature",
  "properties": {
    "iso:country":"US",
    "sg:address":"2006 Round Spring Dr",
    "sg:city":"Humble",
    "sg:classifiers":[
        {
            "category":"Professional",
            "subcategory":"Accounting & Tax Preparation",
            "type":"Services"
        }
    ],
    "sg:phone":"+1 281 359 8003",
    "sg:postcode":"77339",
    "sg:province":"TX",
    "wof:name":"Jim Stafford Accounting S",
    "wof:placetype":"venue"
},
  "geometry": {"coordinates":[-95.21987300000001,30.057895],"type":"Point"}
}