{
  "type": "Feature",
  "properties": {
    "iso:country":"US",
    "sg:address":"404 W Texas Ave",
    "sg:city":"Mart",
    "sg:classifiers":[
        {
            "category":"Autos & Motor Vehicles",
            "subcategory":"Auto Supplies",
            "type":"Retail Goods"
        }
    ],
    "sg:phone":"+1 254 876 3999",
    "sg:postcode":"76664",
    "sg:province":"TX",
    "sg:tags":[
        "tire"
    ],
    "wof:name":"Kubitza Tire & Auto",
    "wof:placetype":"venue"
},
  "geometry": {"coordinates":[-96.840503,31.538973],"type":"Point"}
}