{
  "type": "Feature",
  "properties": {
    "iso:country":"US",
    "sg:address":"1125 Regal Row",
    "sg:city":"Austin",
    "sg:classifiers":[
        {
            "category":"Autos & Motor Vehicles",
            "subcategory":"Motorcycle Sales",
            "type":"Retail Goods"
        }
    ],
    "sg:phone":"+1 512 291 4604",
    "sg:postcode":"78748",
    "sg:province":"TX",
    "wof:name":"Austin Moto Classics",
    "wof:placetype":"venue"
},
  "geometry": {"coordinates":[-97.83005,30.146789],"type":"Point"}
}