{
  "type": "Feature",
  "properties": {
    "iso:country":"US",
    "sg:address":"400 Homeyer Mountain Rd",
    "sg:city":"Burton",
    "sg:classifiers":[
        {
            "category":"Manufacturing",
            "subcategory":"Buildings",
            "type":"Manufacturing & Wholesale Goods"
        },
        {
            "category":"Building & Trades",
            "subcategory":"Construction",
            "type":"Services"
        }
    ],
    "sg:phone":"+1 979 278 3336",
    "sg:postcode":"77835",
    "sg:province":"TX",
    "sg:tags":[
        "home",
        "builder",
        "contractor"
    ],
    "wof:name":"Noel Builders",
    "wof:placetype":"venue"
},
  "geometry": {"coordinates":[-96.652416,30.1512],"type":"Point"}
}