{
  "type": "Feature",
  "properties": {
    "iso:country":"US",
    "sg:address":"2206 Rachel Ridge",
    "sg:city":"Cedar Park",
    "sg:classifiers":[
        {
            "category":"Building & Trades",
            "subcategory":"Construction",
            "type":"Services"
        }
    ],
    "sg:phone":"+1 512 251 3012",
    "sg:postcode":"78613",
    "sg:province":"TX",
    "sg:tags":[
        "repairing",
        "remodeling",
        "contractor"
    ],
    "wof:name":"Mike Shaw Construction",
    "wof:placetype":"venue"
},
  "geometry": {"coordinates":[-97.851089,30.487078],"type":"Point"}
}