{
  "type": "Feature",
  "properties": {
    "iso:country":"US",
    "sg:address":"523 E Court St",
    "sg:city":"Seguin",
    "sg:classifiers":[
        {
            "category":"Insurance",
            "subcategory":"Hazard Insurance",
            "type":"Services"
        },
        {
            "category":"Insurance",
            "subcategory":"Insurance Agent",
            "type":"Services"
        },
        {
            "category":"Insurance",
            "subcategory":"Life Insurance",
            "type":"Services"
        },
        {
            "category":"Insurance",
            "subcategory":"Title Insurance",
            "type":"Services"
        }
    ],
    "sg:phone":"+1 830 379 8231",
    "sg:postcode":"78155",
    "sg:province":"TX",
    "sg:tags":[
        "auto",
        "commercial",
        "business",
        "homeowner"
    ],
    "sg:website":"http://www.farmersagent.com/ctarver/",
    "wof:name":"Carolyn Tarver - Farmers Insurance",
    "wof:placetype":"venue"
},
  "geometry": {"coordinates":[-97.96095099999999,29.568911],"type":"Point"}
}