{
  "type": "Feature",
  "properties": {
    "iso:country":"US",
    "sg:address":"4100 W 15th St Ste",
    "sg:city":"Dallas",
    "sg:classifiers":[
        {
            "category":"Health Services",
            "subcategory":"Doctor",
            "type":"Services"
        }
    ],
    "sg:phone":"+1 972 620 1700",
    "sg:postcode":"75234",
    "sg:province":"TX",
    "sg:tags":[
        "surgeon",
        "cosmetic"
    ],
    "wof:name":"Plastic & Cosmetic Surgery Center of Texas",
    "wof:placetype":"venue"
},
  "geometry": {"coordinates":[-96.879402,32.932098],"type":"Point"}
}