{
  "type": "Feature",
  "properties": {
    "iso:country":"US",
    "sg:address":"14129 Memorial Dr",
    "sg:city":"Houston",
    "sg:classifiers":[
        {
            "category":"Shopping",
            "subcategory":"Florist",
            "type":"Retail Goods"
        }
    ],
    "sg:phone":"+1 281 920 3500",
    "sg:postcode":"77079",
    "sg:province":"TX",
    "wof:name":"D'Elegance Florist",
    "wof:placetype":"venue"
},
  "geometry": {"coordinates":[-95.59342599999999,29.769969],"type":"Point"}
}