{
  "type": "Feature",
  "properties": {
    "iso:country":"US",
    "sg:address":"2854 Everett Dr",
    "sg:city":"Friendswood",
    "sg:classifiers":[
        {
            "category":"Shopping",
            "subcategory":"Clothing, Apparel, & Fashions",
            "type":"Retail Goods"
        }
    ],
    "sg:phone":"+1 281 331 6840",
    "sg:postcode":"77546",
    "sg:province":"TX",
    "wof:name":"Todays Window Fashion",
    "wof:placetype":"venue"
},
  "geometry": {"coordinates":[-95.22295699999999,29.472689],"type":"Point"}
}