{
  "type": "Feature",
  "properties": {
    "iso:country":"US",
    "sg:address":"912 10th St",
    "sg:city":"Floresville",
    "sg:classifiers":[
        {
            "category":"Insurance",
            "subcategory":"Insurance Agent",
            "type":"Services"
        }
    ],
    "sg:phone":"+1 830 216 7855",
    "sg:postcode":"78114",
    "sg:province":"TX",
    "wof:name":"Jarzombek General Insurance",
    "wof:placetype":"venue"
},
  "geometry": {"coordinates":[-98.156644,29.145232],"type":"Point"}
}