{
  "type": "Feature",
  "properties": {
    "iso:country":"US",
    "sg:address":"816 N Estrella St",
    "sg:city":"El Paso",
    "sg:classifiers":[
        {
            "category":"Shopping",
            "subcategory":"Computers & Home Electronics",
            "type":"Retail Goods"
        }
    ],
    "sg:phone":"+1 915 562 1621",
    "sg:postcode":"79903",
    "sg:province":"TX",
    "sg:tags":[
        "equipment",
        "dealer"
    ],
    "wof:name":"Jemm Computer Parts",
    "wof:placetype":"venue"
},
  "geometry": {"coordinates":[-106.45682100000001,31.782541],"type":"Point"}
}