{
  "type": "Feature",
  "properties": {
    "iso:country":"US",
    "sg:address":"5232 Village Creek Dr",
    "sg:city":"Plano",
    "sg:classifiers":[
        {
            "category":"Health Services",
            "subcategory":"Health Practitioner",
            "type":"Services"
        }
    ],
    "sg:phone":"+1 972 818 3993",
    "sg:postcode":"75093",
    "sg:province":"TX",
    "sg:tags":[
        "psychologist"
    ],
    "wof:name":"William C Whitehead",
    "wof:placetype":"venue"
},
  "geometry": {"coordinates":[-96.800529,33.016458],"type":"Point"}
}