{
  "type": "Feature",
  "properties": {
    "iso:country":"US",
    "sg:address":"1501 E Texano Dr",
    "sg:city":"Hidalgo",
    "sg:classifiers":[
        {
            "category":"Freight",
            "type":"Transportation"
        },
        {
            "category":"Local Transit",
            "type":"Transportation"
        }
    ],
    "sg:phone":"+1 956 843 8500",
    "sg:postcode":"78557",
    "sg:province":"TX",
    "sg:tags":[
        "transfer",
        "express"
    ],
    "wof:name":"Air Road Express Inc",
    "wof:placetype":"venue"
},
  "geometry": {"coordinates":[-98.24421,26.102791],"type":"Point"}
}