{
  "type": "Feature",
  "properties": {
    "iso:country":"US",
    "sg:address":"3 Kiowa Lance St",
    "sg:city":"Crowley",
    "sg:classifiers":[
        {
            "category":"Building & Trades",
            "subcategory":"Construction",
            "type":"Services"
        }
    ],
    "sg:phone":"+1 817 297 7244",
    "sg:postcode":"76036",
    "sg:province":"TX",
    "sg:tags":[
        "roofing",
        "contractor"
    ],
    "wof:name":"C R Roofing Co",
    "wof:placetype":"venue"
},
  "geometry": {"coordinates":[-97.380471,32.574635],"type":"Point"}
}