{
  "type": "Feature",
  "properties": {
    "iso:country":"US",
    "sg:address":"1326 Easthaven Dr",
    "sg:city":"Corpus Christi",
    "sg:classifiers":[
        {
            "category":"Food & Beverages",
            "subcategory":"Meat & Fish",
            "type":"Retail Goods"
        }
    ],
    "sg:phone":"+1 361 991 1489",
    "sg:postcode":"78412",
    "sg:province":"TX",
    "sg:tags":[
        "sporting"
    ],
    "wof:name":"Trainers Bait & Tackle",
    "wof:placetype":"venue"
},
  "geometry": {"coordinates":[-97.344151,27.697279],"type":"Point"}
}