{
  "type": "Feature",
  "properties": {
    "iso:country":"US",
    "sg:address":"210 Dallas Dr",
    "sg:city":"Denton",
    "sg:classifiers":[
        {
            "category":"Retail",
            "subcategory":"Auto Repair",
            "type":"Services"
        }
    ],
    "sg:phone":"+1 940 382 8942",
    "sg:postcode":"76205",
    "sg:province":"TX",
    "sg:tags":[
        "shop",
        "repairing",
        "automobile"
    ],
    "wof:name":"Calvert Automotive Inc",
    "wof:placetype":"venue"
},
  "geometry": {"coordinates":[-97.130957,33.205019],"type":"Point"}
}