{
  "type": "Feature",
  "properties": {
    "iso:country":"US",
    "sg:address":"5906 Broadway St",
    "sg:city":"Pearland",
    "sg:classifiers":[
        {
            "category":"Wholesale",
            "subcategory":"Electrical",
            "type":"Manufacturing & Wholesale Goods"
        }
    ],
    "sg:phone":"+1 281 485 8800",
    "sg:postcode":"77581",
    "sg:province":"TX",
    "sg:tags":[
        "communication",
        "radio",
        "system"
    ],
    "sg:website":"www.ablecommunications.com",
    "wof:name":"Able Communications Co Inc",
    "wof:placetype":"venue"
},
  "geometry": {"coordinates":[-95.313096,29.559389],"type":"Point"}
}