{
  "type": "Feature",
  "properties": {
    "iso:country":"US",
    "sg:address":"3425 Martin St",
    "sg:city":"Orange",
    "sg:classifiers":[
        {
            "category":"Personal",
            "subcategory":"Beauty Salon",
            "type":"Services"
        }
    ],
    "sg:phone":"+1 409 883 8600",
    "sg:postcode":"77630",
    "sg:province":"TX",
    "wof:name":"All About Hair & Nails",
    "wof:placetype":"venue"
},
  "geometry": {"coordinates":[-93.774384,30.10305],"type":"Point"}
}