{
  "type": "Feature",
  "properties": {
    "iso:country":"US",
    "sg:address":"1645 E Price Rd",
    "sg:city":"Brownsville",
    "sg:classifiers":[
        {
            "category":"Real Estate",
            "subcategory":"Real Estate Agent",
            "type":"Services"
        }
    ],
    "sg:phone":"+1 956 541 9161",
    "sg:postcode":"78521",
    "sg:province":"TX",
    "wof:name":"Dela Group Inc",
    "wof:placetype":"venue"
},
  "geometry": {"coordinates":[-97.495502,25.93602],"type":"Point"}
}