{
  "type": "Feature",
  "properties": {
    "iso:country":"US",
    "sg:address":"3420 Hebron Pkwy E",
    "sg:city":"Carrollton",
    "sg:classifiers":[
        {
            "category":"Restaurant",
            "type":"Food & Drink"
        }
    ],
    "sg:phone":"+1 972 930 0906",
    "sg:postcode":"75010",
    "sg:province":"TX",
    "wof:name":"KFC",
    "wof:placetype":"venue"
},
  "geometry": {"coordinates":[-96.84820499999999,33.025688],"type":"Point"}
}