{
  "type": "Feature",
  "properties": {
    "iso:country":"US",
    "sg:address":"5515 Poundstone Ct",
    "sg:city":"Sugar Land",
    "sg:classifiers":[
        {
            "category":"Professional",
            "subcategory":"Management & Consulting",
            "type":"Services"
        }
    ],
    "sg:phone":"+1 281 494 5845",
    "sg:postcode":"77479",
    "sg:province":"TX",
    "wof:name":"Jwb Enterprises",
    "wof:placetype":"venue"
},
  "geometry": {"coordinates":[-95.680243,29.590628],"type":"Point"}
}