{
  "type": "Feature",
  "properties": {
    "iso:country":"US",
    "sg:address":"6205 W Broadway Ave",
    "sg:city":"Fort Worth",
    "sg:classifiers":[
        {
            "category":"School Buses",
            "type":"Transportation"
        }
    ],
    "sg:phone":"+1 817 547 5830",
    "sg:postcode":"76117",
    "sg:province":"TX",
    "sg:website":"www.birdville.k12.tx.us",
    "wof:name":"Birdville School Dist Trnsprtn",
    "wof:placetype":"venue"
},
  "geometry": {"coordinates":[-97.25093200000001,32.809174],"type":"Point"}
}