{
  "type": "Feature",
  "properties": {
    "iso:country":"US",
    "sg:address":"27 S Lake Shore Dr",
    "sg:city":"Ransom Canyon",
    "sg:classifiers":[
        {
            "category":"Manufacturing",
            "subcategory":"Printing",
            "type":"Manufacturing & Wholesale Goods"
        }
    ],
    "sg:phone":"+1 806 797 7330",
    "sg:postcode":"79366",
    "sg:province":"TX",
    "sg:tags":[
        "publisher"
    ],
    "wof:name":"Home & Family Magazine",
    "wof:placetype":"venue"
},
  "geometry": {"coordinates":[-101.692088,33.528442],"type":"Point"}
}