{
  "type": "Feature",
  "properties": {
    "iso:country":"US",
    "sg:address":"3800 S Congress Ave Ste F",
    "sg:city":"Austin",
    "sg:classifiers":[
        {
            "category":"Professional",
            "subcategory":"Printing & Photocopies",
            "type":"Services"
        }
    ],
    "sg:phone":"+1 512 382 6079",
    "sg:postcode":"78704",
    "sg:province":"TX",
    "sg:website":"www.cowboyprint.com",
    "wof:name":"Cowboy Printing and Graphics",
    "wof:placetype":"venue"
},
  "geometry": {"coordinates":[-97.762269,30.22588],"type":"Point"}
}