{
  "type": "Feature",
  "properties": {
    "iso:country":"US",
    "sg:address":"718 N Buckner Blvd",
    "sg:city":"Dallas",
    "sg:classifiers":[
        {
            "category":"Bars & Pubs",
            "subcategory":"Sports Bar",
            "type":"Food & Drink"
        }
    ],
    "sg:phone":"+1 214 321 6979",
    "sg:postcode":"75218",
    "sg:province":"TX",
    "wof:name":"White Rock Sports Bar",
    "wof:placetype":"venue"
},
  "geometry": {"coordinates":[-96.71215599999999,32.845545],"type":"Point"}
}