{
  "type": "Feature",
  "properties": {
    "iso:country":"US",
    "sg:address":"833 Marimba Dr",
    "sg:city":"El Paso",
    "sg:classifiers":[
        {
            "category":"Wholesale",
            "subcategory":"Durable Goods & Equipment",
            "type":"Manufacturing & Wholesale Goods"
        }
    ],
    "sg:phone":"+1 915 584 4729",
    "sg:postcode":"79912",
    "sg:province":"TX",
    "sg:tags":[
        "product"
    ],
    "wof:name":"Gelvin B Wholesalers",
    "wof:placetype":"venue"
},
  "geometry": {"coordinates":[-106.553921,31.824143],"type":"Point"}
}