{
  "type": "Feature",
  "properties": {
    "iso:country":"US",
    "sg:address":"5441 Walzem Rd",
    "sg:city":"San Antonio",
    "sg:classifiers":[
        {
            "category":"Organizations",
            "subcategory":"Religious Organization",
            "type":"Services"
        }
    ],
    "sg:phone":"+1 210 967 8408",
    "sg:postcode":"78218",
    "sg:province":"TX",
    "wof:name":"World Deliverance Ministries",
    "wof:placetype":"venue"
},
  "geometry": {"coordinates":[-98.384505,29.510362],"type":"Point"}
}