{
  "type": "Feature",
  "properties": {
    "iso:country":"US",
    "sg:address":"705 Reveille Rd",
    "sg:city":"Fort Worth",
    "sg:classifiers":[
        {
            "category":"Communications",
            "subcategory":"Film & Video Production",
            "type":"Services"
        }
    ],
    "sg:phone":"+1 817 367 3170",
    "sg:postcode":"76108",
    "sg:province":"TX",
    "sg:tags":[
        "taping"
    ],
    "wof:name":"Visionary Video",
    "wof:placetype":"venue"
},
  "geometry": {"coordinates":[-97.498841,32.748786],"type":"Point"}
}