{
  "type": "Feature",
  "properties": {
    "iso:country":"US",
    "sg:address":"2114 N 3rd St",
    "sg:city":"Temple",
    "sg:classifiers":[
        {
            "category":"Shopping",
            "subcategory":"Discount & Variety Stores",
            "type":"Retail Goods"
        },
        {
            "category":"Shopping",
            "subcategory":"Department Store",
            "type":"Retail Goods"
        }
    ],
    "sg:phone":"+1 254 742 2193",
    "sg:postcode":"76501",
    "sg:province":"TX",
    "sg:tags":[
        "shop"
    ],
    "wof:name":"Family Dollar Stores",
    "wof:placetype":"venue"
},
  "geometry": {"coordinates":[-97.336878,31.117123],"type":"Point"}
}