{
  "type": "Feature",
  "properties": {
    "iso:country":"US",
    "sg:address":"661 Louis Henna Blvd",
    "sg:city":"Round Rock",
    "sg:classifiers":[
        {
            "category":"Restaurant",
            "type":"Food & Drink"
        }
    ],
    "sg:phone":"+1 512 733 5553",
    "sg:postcode":"78664",
    "sg:province":"TX",
    "wof:name":"Austin's Pizza",
    "wof:placetype":"venue"
},
  "geometry": {"coordinates":[-97.67247,30.481042],"type":"Point"}
}