{
  "type": "Feature",
  "properties": {
    "iso:country":"US",
    "sg:address":"634 E Highland Rd",
    "sg:city":"Red Oak",
    "sg:classifiers":[
        {
            "category":"Shopping",
            "subcategory":"Gifts & Souvenirs",
            "type":"Retail Goods"
        }
    ],
    "sg:phone":"+1 972 617 6687",
    "sg:postcode":"75154",
    "sg:province":"TX",
    "sg:tags":[
        "antique"
    ],
    "wof:name":"Southern Celebrations",
    "wof:placetype":"venue"
},
  "geometry": {"coordinates":[-96.88633799999999,32.508809],"type":"Point"}
}