{
  "type": "Feature",
  "properties": {
    "iso:country":"US",
    "sg:address":"335 Country Club Rd",
    "sg:city":"Hillsboro",
    "sg:classifiers":[
        {
            "category":"Communications",
            "subcategory":"Radio Station",
            "type":"Services"
        }
    ],
    "sg:phone":"+1 254 582 3431",
    "sg:postcode":"76645",
    "sg:province":"TX",
    "sg:tags":[
        "company",
        "broadcasting"
    ],
    "sg:website":"www.khbr.com",
    "wof:name":"KHBR",
    "wof:placetype":"venue"
},
  "geometry": {"coordinates":[-97.113167,32.013677],"type":"Point"}
}