{
  "type": "Feature",
  "properties": {
    "iso:country":"US",
    "sg:address":"2601 Preston Rd",
    "sg:city":"Frisco",
    "sg:classifiers":[
        {
            "category":"Sports & Exercise",
            "subcategory":"Gym",
            "type":"Entertainment"
        }
    ],
    "sg:phone":"+1 972 712 1959",
    "sg:postcode":"75034",
    "sg:province":"TX",
    "sg:tags":[
        "club",
        "health",
        "studio",
        "gymnasium"
    ],
    "wof:name":"L A Fitness Sports Club",
    "wof:placetype":"venue"
},
  "geometry": {"coordinates":[-96.805673,33.099351],"type":"Point"}
}