{
  "type": "Feature",
  "properties": {
    "iso:country":"US",
    "sg:address":"5203 S Co Rd 1065",
    "sg:city":"Midland",
    "sg:classifiers":[
        {
            "category":"Shopping",
            "type":"Retail Goods"
        }
    ],
    "sg:phone":"+1 432 685 9294",
    "sg:postcode":"79706",
    "sg:province":"TX",
    "sg:tags":[
        "cosmetic",
        "perfume"
    ],
    "wof:name":"Mary Kay Cosmetics",
    "wof:placetype":"venue"
},
  "geometry": {"coordinates":[-101.85518500000001,31.985713],"type":"Point"}
}