{
  "type": "Feature",
  "properties": {
    "iso:country":"US",
    "sg:address":"2201 S I- 35 E",
    "sg:city":"Denton",
    "sg:classifiers":[
        {
            "category":"Food & Beverages",
            "subcategory":"Specialty",
            "type":"Retail Goods"
        }
    ],
    "sg:phone":"+1 940 382 9890",
    "sg:postcode":"76205",
    "sg:province":"TX",
    "sg:tags":[
        "health",
        "diet"
    ],
    "wof:name":"General Nutrition Ctr",
    "wof:placetype":"venue"
},
  "geometry": {"coordinates":[-97.10888,33.187669],"type":"Point"}
}