{
  "type": "Feature",
  "properties": {
    "iso:country":"US",
    "sg:address":"1217 W State Hwy 114",
    "sg:city":"Grapevine",
    "sg:classifiers":[
        {
            "category":"Shopping",
            "subcategory":"Books",
            "type":"Retail Goods"
        }
    ],
    "sg:phone":"+1 817 251 1997",
    "sg:postcode":"76051",
    "sg:province":"TX",
    "wof:name":"Barnes & Noble",
    "wof:placetype":"venue"
},
  "geometry": {"coordinates":[-97.09317900000001,32.928124],"type":"Point"}
}