{
  "type": "Feature",
  "properties": {
    "iso:country":"US",
    "sg:address":"8419 Speedway Dr",
    "sg:city":"San Antonio",
    "sg:classifiers":[
        {
            "category":"Professional",
            "type":"Services"
        },
        {
            "category":"Professional",
            "subcategory":"Business Services",
            "type":"Services"
        }
    ],
    "sg:phone":"+1 210 524 9848",
    "sg:postcode":"78230",
    "sg:province":"TX",
    "sg:tags":[
        "establishment"
    ],
    "wof:name":"Gandi Innovations Corp",
    "wof:placetype":"venue"
},
  "geometry": {"coordinates":[-98.531727,29.517069],"type":"Point"}
}