{
  "type": "Feature",
  "properties": {
    "iso:country":"US",
    "sg:address":"809 Sidney Baker St",
    "sg:city":"Kerrville",
    "sg:classifiers":[
        {
            "category":"Restaurant",
            "type":"Food & Drink"
        }
    ],
    "sg:phone":"+1 830 257 2634",
    "sg:postcode":"78028",
    "sg:province":"TX",
    "wof:name":"Valentinos Italian Cafe",
    "wof:placetype":"venue"
},
  "geometry": {"coordinates":[-99.135486,30.051649],"type":"Point"}
}