{
  "type": "Feature",
  "properties": {
    "iso:country":"US",
    "sg:address":"4436 Pack Saddle Pass",
    "sg:city":"Austin",
    "sg:classifiers":[
        {
            "category":"Health Services",
            "subcategory":"Optometrist",
            "type":"Services"
        }
    ],
    "sg:phone":"+1 512 444 7200",
    "sg:postcode":"78745",
    "sg:province":"TX",
    "wof:name":"Lakehills Vision Care",
    "wof:placetype":"venue"
},
  "geometry": {"coordinates":[-97.79263400000001,30.230442],"type":"Point"}
}