{
  "type": "Feature",
  "properties": {
    "iso:country":"US",
    "sg:address":"406 N Clark Rd",
    "sg:city":"Duncanville",
    "sg:classifiers":[
        {
            "category":"Building & Trades",
            "subcategory":"Construction",
            "type":"Services"
        }
    ],
    "sg:phone":"+1 972 296 7735",
    "sg:postcode":"75116",
    "sg:province":"TX",
    "sg:tags":[
        "contractor"
    ],
    "wof:name":"De Leon Construction Inc",
    "wof:placetype":"venue"
},
  "geometry": {"coordinates":[-96.94314799999999,32.658816],"type":"Point"}
}