{
  "type": "Feature",
  "properties": {
    "iso:country":"US",
    "sg:address":"426 Schley Ave",
    "sg:city":"Hereford",
    "sg:classifiers":[
        {
            "category":"Wholesale",
            "subcategory":"Durable Goods & Equipment",
            "type":"Manufacturing & Wholesale Goods"
        }
    ],
    "sg:phone":"+1 806 364 0008",
    "sg:postcode":"79045",
    "sg:province":"TX",
    "wof:name":"Goheen Pipe & Supply",
    "wof:placetype":"venue"
},
  "geometry": {"coordinates":[-102.398218,34.819377],"type":"Point"}
}