{
  "type": "Feature",
  "properties": {
    "iso:country":"US",
    "sg:address":"7816 County Road 1016A",
    "sg:city":"Burleson",
    "sg:classifiers":[
        {
            "category":"Autos & Motor Vehicles",
            "subcategory":"Motorcycle Sales",
            "type":"Retail Goods"
        }
    ],
    "sg:phone":"+1 817 447 3416",
    "sg:postcode":"76028",
    "sg:province":"TX",
    "wof:name":"Tommy's Lawnmower & Small Engine Repair",
    "wof:placetype":"venue"
},
  "geometry": {"coordinates":[-97.403603,32.490002],"type":"Point"}
}