{
  "type": "Feature",
  "properties": {
    "iso:country":"US",
    "sg:address":"6914 Oakwood Glen Cir",
    "sg:city":"Spring",
    "sg:classifiers":[
        {
            "category":"Building & Trades",
            "subcategory":"Pest Control",
            "type":"Services"
        }
    ],
    "sg:phone":"+1 281 374 7770",
    "sg:postcode":"77379",
    "sg:province":"TX",
    "wof:name":"Pest Arrest",
    "wof:placetype":"venue"
},
  "geometry": {"coordinates":[-95.525227,30.032525],"type":"Point"}
}