{
  "type": "Feature",
  "properties": {
    "iso:country":"US",
    "sg:address":"8800 Sam Houston Pkwy",
    "sg:city":"Houston",
    "sg:classifiers":[
        {
            "category":"Building & Trades",
            "subcategory":"Landscaping Services",
            "type":"Services"
        }
    ],
    "sg:phone":"+1 713 649 6659",
    "sg:postcode":"77099",
    "sg:province":"TX",
    "sg:tags":[
        "tree"
    ],
    "wof:name":"Douglas Fir Tree Co",
    "wof:placetype":"venue"
},
  "geometry": {"coordinates":[-95.559055,29.683429],"type":"Point"}
}