{
  "type": "Feature",
  "properties": {
    "iso:country":"US",
    "sg:address":"2722 W Gentry Pkwy",
    "sg:city":"Tyler",
    "sg:classifiers":[
        {
            "category":"Shopping",
            "subcategory":"Pharmacy",
            "type":"Retail Goods"
        }
    ],
    "sg:phone":"+1 903 593 2533",
    "sg:postcode":"75702",
    "sg:province":"TX",
    "wof:name":"Woody Weaver Pharmacy Inc",
    "wof:placetype":"venue"
},
  "geometry": {"coordinates":[-95.331464,32.369903],"type":"Point"}
}