{
  "type": "Feature",
  "properties": {
    "iso:country":"US",
    "sg:address":"210 W 5th St",
    "sg:city":"Clifton",
    "sg:classifiers":[
        {
            "category":"Autos & Motor Vehicles",
            "subcategory":"Fuel & Gas Station",
            "type":"Retail Goods"
        }
    ],
    "sg:phone":"+1 254 675 3219",
    "sg:postcode":"76634",
    "sg:province":"TX",
    "sg:tags":[
        "station",
        "gasoline"
    ],
    "wof:name":"Barners Km Station",
    "wof:placetype":"venue"
},
  "geometry": {"coordinates":[-97.57349000000001,31.783611],"type":"Point"}
}