{
  "type": "Feature",
  "properties": {
    "iso:country":"US",
    "sg:address":"14505 Torrey Chase Blvd",
    "sg:city":"Houston",
    "sg:classifiers":[
        {
            "category":"Professional",
            "subcategory":"Employment Agencies",
            "type":"Services"
        }
    ],
    "sg:phone":"+1 281 893 1044",
    "sg:postcode":"77014",
    "sg:province":"TX",
    "sg:tags":[
        "opportunity",
        "temporary",
        "contractor"
    ],
    "sg:website":"http://www.atppersonnel.com",
    "wof:name":"Atp Personnel Consultants",
    "wof:placetype":"venue"
},
  "geometry": {"coordinates":[-95.492622,29.98732],"type":"Point"}
}