{
  "type": "Feature",
  "properties": {
    "iso:country":"US",
    "sg:address":"307 Hill Rd",
    "sg:city":"Houston",
    "sg:classifiers":[
        {
            "category":"Organizations",
            "subcategory":"Religious Organization",
            "type":"Services"
        }
    ],
    "sg:phone":"+1 281 931 8567",
    "sg:postcode":"77037",
    "sg:province":"TX",
    "sg:tags":[
        "church"
    ],
    "wof:name":"Monte Sinai Church",
    "wof:placetype":"venue"
},
  "geometry": {"coordinates":[-95.39361,29.895652],"type":"Point"}
}