{
  "type": "Feature",
  "properties": {
    "iso:country":"US",
    "sg:address":"201 Fm 685",
    "sg:city":"Pflugerville",
    "sg:classifiers":[
        {
            "category":"Shopping",
            "subcategory":"Pharmacy",
            "type":"Retail Goods"
        }
    ],
    "sg:phone":"+1 512 251 9037",
    "sg:postcode":"78660",
    "sg:province":"TX",
    "wof:name":"Round Rock 4",
    "wof:placetype":"venue"
},
  "geometry": {"coordinates":[-97.61299,30.43806],"type":"Point"}
}