{
  "type": "Feature",
  "properties": {
    "iso:country":"US",
    "sg:address":"5104 Partridge Rd",
    "sg:city":"Fort Worth",
    "sg:classifiers":[
        {
            "category":"Arts & Performance",
            "subcategory":"Theater",
            "type":"Entertainment"
        }
    ],
    "sg:phone":"+1 817 370 7121",
    "sg:postcode":"76132",
    "sg:province":"TX",
    "sg:tags":[
        "talent",
        "agency",
        "casting"
    ],
    "wof:name":"Entertainment Texas",
    "wof:placetype":"venue"
},
  "geometry": {"coordinates":[-97.39205800000001,32.67407],"type":"Point"}
}