{
  "type": "Feature",
  "properties": {
    "iso:country":"US",
    "sg:address":"11610 Bickwood Dr",
    "sg:city":"Houston",
    "sg:classifiers":[
        {
            "category":"Shopping",
            "subcategory":"Catalog Store",
            "type":"Retail Goods"
        }
    ],
    "sg:phone":"+1 281 481 0955",
    "sg:postcode":"77089",
    "sg:province":"TX",
    "sg:tags":[
        "house",
        "mail"
    ],
    "wof:name":"Simply Out of Stress",
    "wof:placetype":"venue"
},
  "geometry": {"coordinates":[-95.206885,29.590749],"type":"Point"}
}