{
  "type": "Feature",
  "properties": {
    "iso:country":"US",
    "sg:address":"311 Avenue E",
    "sg:city":"Marble Falls",
    "sg:classifiers":[
        {
            "category":"Recreation",
            "type":"Entertainment"
        }
    ],
    "sg:phone":"+1 866 733 8687",
    "sg:postcode":"78654",
    "sg:province":"TX",
    "sg:tags":[
        "tour",
        "virtual",
        "provider"
    ],
    "wof:name":"Wwwhomeviewnet",
    "wof:placetype":"venue"
},
  "geometry": {"coordinates":[-98.272255,30.570599],"type":"Point"}
}