{
  "type": "Feature",
  "properties": {
    "iso:country":"US",
    "sg:address":"1 Ysleta Ct",
    "sg:city":"Odessa",
    "sg:classifiers":[
        {
            "category":"Retail",
            "subcategory":"Portrait Studio",
            "type":"Services"
        }
    ],
    "sg:phone":"+1 432 561 5382",
    "sg:postcode":"79765",
    "sg:province":"TX",
    "sg:tags":[
        "photographer"
    ],
    "wof:name":"Paws Prints Portraits",
    "wof:placetype":"venue"
},
  "geometry": {"coordinates":[-102.279899,31.916224],"type":"Point"}
}