{
  "type": "Feature",
  "properties": {
    "iso:country":"US",
    "sg:address":"622 N New Braunfels Ave",
    "sg:city":"San Antonio",
    "sg:classifiers":[
        {
            "category":"Retail",
            "subcategory":"Repair Shop",
            "type":"Services"
        }
    ],
    "sg:phone":"+1 210 320 9114",
    "sg:postcode":"78202",
    "sg:province":"TX",
    "sg:tags":[
        "upholsterer"
    ],
    "wof:name":"Brown's Upholstery",
    "wof:placetype":"venue"
},
  "geometry": {"coordinates":[-98.461039,29.427598],"type":"Point"}
}