{
  "type": "Feature",
  "properties": {
    "iso:country":"US",
    "sg:address":"20523 Apache Lake Dr",
    "sg:city":"Katy",
    "sg:classifiers":[
        {
            "category":"Manufacturing",
            "subcategory":"Wood Products",
            "type":"Manufacturing & Wholesale Goods"
        }
    ],
    "sg:phone":"+1 281 599 1057",
    "sg:postcode":"77449",
    "sg:province":"TX",
    "sg:tags":[
        "mfg"
    ],
    "wof:name":"All Texas Designs",
    "wof:placetype":"venue"
},
  "geometry": {"coordinates":[-95.730278,29.81436],"type":"Point"}
}