{
  "type": "Feature",
  "properties": {
    "iso:country":"US",
    "sg:address":"804 Lavender Dr",
    "sg:city":"Keller",
    "sg:classifiers":[
        {
            "category":"Building & Trades",
            "subcategory":"Plumbing",
            "type":"Services"
        }
    ],
    "sg:phone":"+1 817 337 0775",
    "sg:postcode":"76248",
    "sg:province":"TX",
    "sg:tags":[
        "heating",
        "contractor"
    ],
    "wof:name":"Hilti's Heating & Air",
    "wof:placetype":"venue"
},
  "geometry": {"coordinates":[-97.29617399999999,32.946761],"type":"Point"}
}