{
  "type": "Feature",
  "properties": {
    "iso:country":"US",
    "sg:address":"5225 Garth Rd",
    "sg:city":"Baytown",
    "sg:classifiers":[
        {
            "category":"Professional",
            "subcategory":"Accounting & Tax Preparation",
            "type":"Services"
        }
    ],
    "sg:phone":"+1 281 428 8299",
    "sg:postcode":"77521",
    "sg:province":"TX",
    "sg:tags":[
        "return",
        "filing"
    ],
    "wof:name":"First Tax",
    "wof:placetype":"venue"
},
  "geometry": {"coordinates":[-94.97836700000001,29.78111],"type":"Point"}
}