{
  "type": "Feature",
  "properties": {
    "iso:country":"US",
    "sg:address":"15114 Galveston Rd",
    "sg:city":"Webster",
    "sg:classifiers":[
        {
            "category":"Retail",
            "subcategory":"Auto Rental",
            "type":"Services"
        }
    ],
    "sg:phone":"+1 281 486 8222",
    "sg:postcode":"77598",
    "sg:province":"TX",
    "sg:tags":[
        "truck"
    ],
    "wof:name":"Penske",
    "wof:placetype":"venue"
},
  "geometry": {"coordinates":[-95.147971,29.569651],"type":"Point"}
}