{
  "type": "Feature",
  "properties": {
    "iso:country":"US",
    "sg:address":"13313 Perthshire St",
    "sg:city":"Austin",
    "sg:classifiers":[
        {
            "category":"Recreation",
            "type":"Entertainment"
        }
    ],
    "sg:phone":"+1 512 219 1355",
    "sg:postcode":"78729",
    "sg:province":"TX",
    "sg:tags":[
        "entertainers-family",
        "business"
    ],
    "wof:name":"Pendragon Entertainment Group",
    "wof:placetype":"venue"
},
  "geometry": {"coordinates":[-97.77797700000001,30.464361],"type":"Point"}
}