{
  "type": "Feature",
  "properties": {
    "iso:country":"US",
    "sg:address":"3600 Golden Triangle Blvd",
    "sg:city":"Keller",
    "sg:classifiers":[
        {
            "category":"Insurance",
            "subcategory":"Insurance Agent",
            "type":"Services"
        }
    ],
    "sg:phone":"+1 817 337 4629",
    "sg:postcode":"76248",
    "sg:province":"TX",
    "wof:name":"Farmers Insurance Group",
    "wof:placetype":"venue"
},
  "geometry": {"coordinates":[-97.304768,32.932334],"type":"Point"}
}