{
  "type": "Feature",
  "properties": {
    "iso:country":"US",
    "sg:address":"125 N Clark Rd Ste 106",
    "sg:city":"Cedar Hill",
    "sg:classifiers":[
        {
            "category":"Restaurant",
            "type":"Food & Drink"
        }
    ],
    "sg:phone":"+1 469 272 3700",
    "sg:postcode":"75104",
    "sg:province":"TX",
    "sg:tags":[
        "pizza"
    ],
    "wof:name":"Little Caesars",
    "wof:placetype":"venue"
},
  "geometry": {"coordinates":[-96.942662,32.590353],"type":"Point"}
}