{
  "type": "Feature",
  "properties": {
    "iso:country":"US",
    "sg:address":"1000 Lone Star Dr",
    "sg:city":"Houston",
    "sg:classifiers":[
        {
            "category":"Professional",
            "subcategory":"Lawyer & Legal Services",
            "type":"Services"
        }
    ],
    "sg:phone":"+1 713 653 7805",
    "sg:postcode":"77055",
    "sg:province":"TX",
    "sg:tags":[
        "attorney"
    ],
    "wof:name":"Crane Franci Neeley",
    "wof:placetype":"venue"
},
  "geometry": {"coordinates":[-95.51286899999999,29.788418],"type":"Point"}
}