{
  "type": "Feature",
  "properties": {
    "iso:country":"US",
    "sg:address":"3200 Woodridge Ste Ste 1350",
    "sg:city":"Houston",
    "sg:classifiers":[
        {
            "category":"Banks & Credit Unions",
            "subcategory":"Bank",
            "type":"Services"
        }
    ],
    "sg:phone":"+1 713 285 2266",
    "sg:postcode":"77002",
    "sg:province":"TX",
    "wof:name":"IBC Bank",
    "wof:placetype":"venue"
},
  "geometry": {"coordinates":[-95.297685,29.697912],"type":"Point"}
}