{
  "type": "Feature",
  "properties": {
    "iso:country":"US",
    "sg:address":"402 Teal Ln",
    "sg:city":"Kyle",
    "sg:classifiers":[
        {
            "category":"Wholesale",
            "subcategory":"Electrical",
            "type":"Manufacturing & Wholesale Goods"
        }
    ],
    "sg:phone":"+1 512 268 1103",
    "sg:postcode":"78640",
    "sg:province":"TX",
    "sg:tags":[
        "equipment"
    ],
    "wof:name":"D&D Security Services",
    "wof:placetype":"venue"
},
  "geometry": {"coordinates":[-97.953427,30.048573],"type":"Point"}
}