{
  "type": "Feature",
  "properties": {
    "iso:country":"US",
    "sg:address":"113 Glendale Dr",
    "sg:city":"Del Rio",
    "sg:classifiers":[
        {
            "category":"Professional",
            "subcategory":"Secretarial Services",
            "type":"Services"
        }
    ],
    "sg:phone":"+1 830 774 0232",
    "sg:postcode":"78840",
    "sg:province":"TX",
    "sg:tags":[
        "reporting"
    ],
    "wof:name":"John Price",
    "wof:placetype":"venue"
},
  "geometry": {"coordinates":[-100.892087,29.376903],"type":"Point"}
}