{
  "type": "Feature",
  "properties": {
    "iso:country":"US",
    "sg:address":"14102 N Hills Village Dr",
    "sg:city":"San Antonio",
    "sg:classifiers":[
        {
            "category":"Shopping",
            "subcategory":"Hobbies, Toys, & Games",
            "type":"Retail Goods"
        }
    ],
    "sg:phone":"+1 210 641 5977",
    "sg:postcode":"78249",
    "sg:province":"TX",
    "sg:tags":[
        "craft",
        "supply"
    ],
    "wof:name":"Favour Media",
    "wof:placetype":"venue"
},
  "geometry": {"coordinates":[-98.63717699999999,29.580043],"type":"Point"}
}