{
  "type": "Feature",
  "properties": {
    "iso:country":"US",
    "sg:address":"2910 Spruce Park Dr",
    "sg:city":"Fort Worth",
    "sg:classifiers":[
        {
            "category":"Manufacturing",
            "subcategory":"Printing",
            "type":"Manufacturing & Wholesale Goods"
        }
    ],
    "sg:phone":"+1 817 284 8157",
    "sg:postcode":"76118",
    "sg:province":"TX",
    "sg:tags":[
        "publishing"
    ],
    "wof:name":"Vj Design Services",
    "wof:placetype":"venue"
},
  "geometry": {"coordinates":[-97.230328,32.804612],"type":"Point"}
}