{
  "type": "Feature",
  "properties": {
    "iso:country":"US",
    "sg:address":"4001 Steepleridge Dr",
    "sg:city":"Lewisville",
    "sg:classifiers":[
        {
            "category":"Health Services",
            "subcategory":"Doctor",
            "type":"Services"
        }
    ],
    "sg:phone":"+1 469 384 4230",
    "sg:postcode":"75056",
    "sg:province":"TX",
    "sg:tags":[
        "medical"
    ],
    "wof:name":"Fang Ye LI Yiming",
    "wof:placetype":"venue"
},
  "geometry": {"coordinates":[-96.90188999999999,33.072648],"type":"Point"}
}