{
  "type": "Feature",
  "properties": {
    "iso:country":"US",
    "sg:address":"710 Ave J",
    "sg:city":"Lubbock",
    "sg:classifiers":[
        {
            "category":"Professional",
            "type":"Services"
        }
    ],
    "sg:phone":"+1 806 762 8855",
    "sg:postcode":"79401",
    "sg:province":"TX",
    "sg:tags":[
        "establishment"
    ],
    "wof:name":"Avalanche Journal Subscription",
    "wof:placetype":"venue"
},
  "geometry": {"coordinates":[-101.84688199999999,33.588389],"type":"Point"}
}