{
  "type": "Feature",
  "properties": {
    "iso:country":"US",
    "sg:address":"4327 Birchcroft Dr",
    "sg:city":"Houston",
    "sg:classifiers":[
        {
            "category":"Building & Trades",
            "subcategory":"Construction",
            "type":"Services"
        }
    ],
    "sg:phone":"+1 281 931 7269",
    "sg:postcode":"77088",
    "sg:province":"TX",
    "sg:tags":[
        "hanging",
        "contractor"
    ],
    "wof:name":"Sr Farias",
    "wof:placetype":"venue"
},
  "geometry": {"coordinates":[-95.467608,29.869398],"type":"Point"}
}