{
  "type": "Feature",
  "properties": {
    "iso:country":"US",
    "sg:address":"104 Bassett St",
    "sg:city":"Sealy",
    "sg:classifiers":[
        {
            "category":"Restaurant",
            "type":"Food & Drink"
        }
    ],
    "sg:phone":"+1 979 885 3423",
    "sg:postcode":"77474",
    "sg:province":"TX",
    "sg:tags":[
        "eating"
    ],
    "wof:name":"Annies Bar B Que House",
    "wof:placetype":"venue"
},
  "geometry": {"coordinates":[-96.14599200000001,29.78385],"type":"Point"}
}