{
  "type": "Feature",
  "properties": {
    "iso:country":"US",
    "sg:address":"1717 S Lakeshore Blvd",
    "sg:city":"Austin",
    "sg:classifiers":[
        {
            "category":"Retail",
            "subcategory":"Self-service Laundry",
            "type":"Services"
        }
    ],
    "sg:phone":"+1 512 447 9236",
    "sg:postcode":"78741",
    "sg:province":"TX",
    "sg:tags":[
        "coin",
        "establishment"
    ],
    "wof:name":"B-Gem Laundry Care",
    "wof:placetype":"venue"
},
  "geometry": {"coordinates":[-97.730216,30.244785],"type":"Point"}
}