{
  "type": "Feature",
  "properties": {
    "iso:country":"US",
    "sg:address":"1215 Spruce",
    "sg:city":"Lockhart",
    "sg:classifiers":[
        {
            "category":"Farming",
            "subcategory":"Livestock Farm",
            "type":"Manufacturing & Wholesale Goods"
        }
    ],
    "sg:phone":"+1 512 398 5505",
    "sg:postcode":"78644",
    "sg:province":"TX",
    "sg:tags":[
        "beef",
        "feedlot",
        "cattle"
    ],
    "wof:name":"R C Armstrong Ranch",
    "wof:placetype":"venue"
},
  "geometry": {"coordinates":[-97.687096,29.880284],"type":"Point"}
}