{
  "type": "Feature",
  "properties": {
    "iso:country":"US",
    "sg:address":"1731 W 25th St",
    "sg:city":"Odessa",
    "sg:classifiers":[
        {
            "category":"Shopping",
            "subcategory":"Bicycles & Sporting Goods",
            "type":"Retail Goods"
        }
    ],
    "sg:phone":"+1 432 580 9525",
    "sg:postcode":"79763",
    "sg:province":"TX",
    "wof:name":"Moya Baseball & Softball",
    "wof:placetype":"venue"
},
  "geometry": {"coordinates":[-102.40354499999999,31.859097],"type":"Point"}
}