{
  "type": "Feature",
  "properties": {
    "iso:country":"US",
    "sg:address":"800 Hwy 59 N",
    "sg:city":"Bowie",
    "sg:classifiers":[
        {
            "category":"Professional",
            "subcategory":"Accounting & Tax Preparation",
            "type":"Services"
        }
    ],
    "sg:phone":"+1 940 872 2711",
    "sg:postcode":"76230",
    "sg:province":"TX",
    "sg:tags":[
        "accountant"
    ],
    "wof:name":"Mathis West Huffines & Co P C",
    "wof:placetype":"venue"
},
  "geometry": {"coordinates":[-97.842479,33.563997],"type":"Point"}
}