{
  "type": "Feature",
  "properties": {
    "iso:country":"US",
    "sg:address":"7122 Wood Hollow Dr",
    "sg:city":"Austin",
    "sg:classifiers":[
        {
            "category":"Manufacturing",
            "subcategory":"Glass & Minerals",
            "type":"Manufacturing & Wholesale Goods"
        }
    ],
    "sg:phone":"+1 512 345 6083",
    "sg:postcode":"78731",
    "sg:province":"TX",
    "sg:tags":[
        "tile",
        "mfg"
    ],
    "wof:name":"Catalonia Trading Co",
    "wof:placetype":"venue"
},
  "geometry": {"coordinates":[-97.751513,30.356185],"type":"Point"}
}