{
  "type": "Feature",
  "properties": {
    "iso:country":"US",
    "sg:address":"1120 Magoffin Ave",
    "sg:city":"El Paso",
    "sg:classifiers":[
        {
            "category":"Organizations",
            "subcategory":"Membership Organization",
            "type":"Services"
        },
        {
            "category":"Museum",
            "type":"Entertainment"
        }
    ],
    "sg:phone":"+1 915 533 5222",
    "sg:postcode":"79901",
    "sg:province":"TX",
    "sg:tags":[
        "gallery",
        "historical"
    ],
    "wof:name":"Historic Organizations Informa",
    "wof:placetype":"venue"
},
  "geometry": {"coordinates":[-106.47795600000001,31.762383],"type":"Point"}
}