{
  "type": "Feature",
  "properties": {
    "iso:country":"US",
    "sg:address":"629 E Main St",
    "sg:city":"Uvalde",
    "sg:classifiers":[
        {
            "category":"Restaurant",
            "type":"Food & Drink"
        }
    ],
    "sg:phone":"+1 830 278 1911",
    "sg:postcode":"78801",
    "sg:province":"TX",
    "sg:tags":[
        "eating"
    ],
    "wof:name":"Kettle Restaurant",
    "wof:placetype":"venue"
},
  "geometry": {"coordinates":[-99.77561799999999,29.212969],"type":"Point"}
}