{
  "type": "Feature",
  "properties": {
    "iso:country":"US",
    "sg:address":"11117 Lochwood Blvd",
    "sg:city":"Dallas",
    "sg:classifiers":[
        {
            "category":"Real Estate",
            "subcategory":"Real Estate Operator",
            "type":"Services"
        }
    ],
    "sg:phone":"+1 214 321 3381",
    "sg:postcode":"75218",
    "sg:province":"TX",
    "sg:tags":[
        "building",
        "apartment"
    ],
    "wof:name":"Lochwood Apartments",
    "wof:placetype":"venue"
},
  "geometry": {"coordinates":[-96.686385,32.847345],"type":"Point"}
}