{
  "type": "Feature",
  "properties": {
    "iso:country":"US",
    "sg:address":"8041 Callaghan Rd",
    "sg:city":"San Antonio",
    "sg:classifiers":[
        {
            "category":"Travel",
            "subcategory":"Travel Agent",
            "type":"Entertainment"
        }
    ],
    "sg:phone":"+1 210 349 2583",
    "sg:postcode":"78230",
    "sg:province":"TX",
    "sg:tags":[
        "cruise"
    ],
    "wof:name":"Cruises Etc",
    "wof:placetype":"venue"
},
  "geometry": {"coordinates":[-98.551574,29.512213],"type":"Point"}
}