{
  "type": "Feature",
  "properties": {
    "iso:country":"US",
    "sg:address":"1801 Blossom Ln",
    "sg:city":"Tyler",
    "sg:classifiers":[
        {
            "category":"Banks & Credit Unions",
            "subcategory":"Bureau De Change",
            "type":"Services"
        },
        {
            "category":"Wholesale",
            "subcategory":"Office Equipment",
            "type":"Manufacturing & Wholesale Goods"
        },
        {
            "category":"Professional",
            "subcategory":"Business Services",
            "type":"Services"
        },
        {
            "category":"Professional",
            "subcategory":"Printing & Photocopies",
            "type":"Services"
        },
        {
            "category":"Shopping",
            "subcategory":"Computers & Home Electronics",
            "type":"Retail Goods"
        }
    ],
    "sg:phone":"+1 936 639 5945",
    "sg:postcode":"75701",
    "sg:province":"TX",
    "sg:tags":[
        "scanning",
        "printer",
        "form",
        "supply",
        "services-commercial",
        "duplicating",
        "shipping",
        "printers-business",
        "copying",
        "mail",
        "plotting",
        "card"
    ],
    "sg:website":"http://www.kwikkopy.com",
    "wof:name":"Kwik Kopy Printing",
    "wof:placetype":"venue"
},
  "geometry": {"coordinates":[-95.280518,32.310791],"type":"Point"}
}