{
  "type": "Feature",
  "properties": {
    "iso:country":"US",
    "sg:address":"5709 Charleston Dr",
    "sg:city":"Frisco",
    "sg:classifiers":[
        {
            "category":"Professional",
            "subcategory":"Management & Consulting",
            "type":"Services"
        }
    ],
    "sg:phone":"+1 469 867 5358",
    "sg:postcode":"75035",
    "sg:province":"TX",
    "sg:tags":[
        "business"
    ],
    "wof:name":"Stm Consulting",
    "wof:placetype":"venue"
},
  "geometry": {"coordinates":[-96.78548600000001,33.124189],"type":"Point"}
}