{
  "type": "Feature",
  "properties": {
    "iso:country":"US",
    "sg:address":"3515 Ave M",
    "sg:city":"Galveston",
    "sg:classifiers":[
        {
            "category":"Building & Trades",
            "subcategory":"Cleaning & Sanitation",
            "type":"Services"
        }
    ],
    "sg:phone":"+1 409 256 6900",
    "sg:postcode":"77550",
    "sg:province":"TX",
    "sg:tags":[
        "janitor"
    ],
    "wof:name":"Give Me A Break Cleaning Svc",
    "wof:placetype":"venue"
},
  "geometry": {"coordinates":[-94.805851,29.293429],"type":"Point"}
}