{
  "type": "Feature",
  "properties": {
    "iso:country":"US",
    "sg:address":"5134 Williams Dr",
    "sg:city":"Corpus Christi",
    "sg:classifiers":[
        {
            "category":"Real Estate",
            "subcategory":"Real Estate Agent",
            "type":"Services"
        }
    ],
    "sg:phone":"+1 361 814 7129",
    "sg:postcode":"78411",
    "sg:province":"TX",
    "wof:name":"Valencia Real Estate",
    "wof:placetype":"venue"
},
  "geometry": {"coordinates":[-97.38126099999999,27.709356],"type":"Point"}
}