{
  "type": "Feature",
  "properties": {
    "iso:country":"US",
    "sg:address":"26533 Deerwood Dr",
    "sg:city":"Hempstead",
    "sg:classifiers":[
        {
            "category":"Manufacturing",
            "subcategory":"Rubber & Plastics",
            "type":"Manufacturing & Wholesale Goods"
        },
        {
            "category":"Wholesale",
            "subcategory":"Home Furnishings",
            "type":"Manufacturing & Wholesale Goods"
        }
    ],
    "sg:phone":"+1 979 826 4787",
    "sg:postcode":"77445",
    "sg:province":"TX",
    "sg:tags":[
        "plastics-vacuum",
        "plastics-fabricating",
        "plastics-molders",
        "pressure",
        "forming-manufacturers",
        "finishing",
        "thermoforming",
        "decorating"
    ],
    "wof:name":"Cynjoe Polyurethane",
    "wof:placetype":"venue"
},
  "geometry": {"coordinates":[-96.02488200000001,30.202512],"type":"Point"}
}