{
  "type": "Feature",
  "properties": {
    "iso:country":"US",
    "sg:address":"205 N 4th St",
    "sg:city":"Sanger",
    "sg:classifiers":[
        {
            "category":"Professional",
            "type":"Services"
        }
    ],
    "sg:phone":"+1 940 458 6789",
    "sg:postcode":"76266",
    "sg:province":"TX",
    "wof:name":"Nackatish Natives",
    "wof:placetype":"venue"
},
  "geometry": {"coordinates":[-97.17297600000001,33.361423],"type":"Point"}
}