{
  "type": "Feature",
  "properties": {
    "iso:country":"US",
    "sg:address":"2465 Royal Ln",
    "sg:city":"Dallas",
    "sg:classifiers":[
        {
            "category":"Autos & Motor Vehicles",
            "subcategory":"Auto Supplies",
            "type":"Retail Goods"
        }
    ],
    "sg:phone":"+1 972 488 9662",
    "sg:postcode":"75229",
    "sg:province":"TX",
    "sg:tags":[
        "tire"
    ],
    "wof:name":"C & M Discount Tires",
    "wof:placetype":"venue"
},
  "geometry": {"coordinates":[-96.897598,32.896198],"type":"Point"}
}