{
  "type": "Feature",
  "properties": {
    "iso:country":"US",
    "sg:address":"2266 Neely Trl",
    "sg:city":"Valley View",
    "sg:classifiers":[
        {
            "category":"Building & Trades",
            "subcategory":"Construction",
            "type":"Services"
        }
    ],
    "sg:phone":"+1 940 668 8626",
    "sg:postcode":"76272",
    "sg:province":"TX",
    "sg:tags":[
        "house"
    ],
    "wof:name":"Dan Alexander Builder",
    "wof:placetype":"venue"
},
  "geometry": {"coordinates":[-97.059045,33.503587],"type":"Point"}
}