{
  "type": "Feature",
  "properties": {
    "iso:country":"US",
    "sg:address":"21764 Red Oak Rd",
    "sg:city":"Chandler",
    "sg:classifiers":[
        {
            "category":"Recreation",
            "type":"Entertainment"
        }
    ],
    "sg:phone":"+1 903 849 3275",
    "sg:postcode":"75758",
    "sg:province":"TX",
    "wof:name":"Psychic Corner",
    "wof:placetype":"venue"
},
  "geometry": {"coordinates":[-95.493962,32.234836],"type":"Point"}
}