{
  "type": "Feature",
  "properties": {
    "iso:country":"US",
    "sg:address":"124 Fannett Rd",
    "sg:city":"Beaumont",
    "sg:classifiers":[
        {
            "category":"Community Center",
            "type":"Public Place"
        }
    ],
    "sg:phone":"+1 409 794 2314",
    "sg:postcode":"77705",
    "sg:province":"TX",
    "sg:tags":[
        "medical"
    ],
    "wof:name":"Fannett Medical Center",
    "wof:placetype":"venue"
},
  "geometry": {"coordinates":[-94.119579,30.05189],"type":"Point"}
}