{
  "type": "Feature",
  "properties": {
    "iso:country":"US",
    "sg:address":"23106 Harrowby Dr",
    "sg:city":"Spring",
    "sg:classifiers":[
        {
            "category":"Health Services",
            "subcategory":"Clinic",
            "type":"Services"
        }
    ],
    "sg:phone":"+1 281 689 7846",
    "sg:postcode":"77373",
    "sg:province":"TX",
    "sg:tags":[
        "home",
        "care"
    ],
    "wof:name":"Support Services For Hlth Care",
    "wof:placetype":"venue"
},
  "geometry": {"coordinates":[-95.399607,30.042931],"type":"Point"}
}