{
  "type": "Feature",
  "properties": {
    "iso:country":"US",
    "sg:address":"1732 Milford St",
    "sg:city":"Houston",
    "sg:classifiers":[
        {
            "category":"Professional",
            "subcategory":"Management & Consulting",
            "type":"Services"
        }
    ],
    "sg:phone":"+1 713 582 2000",
    "sg:postcode":"77098",
    "sg:province":"TX",
    "sg:tags":[
        "business"
    ],
    "wof:name":"Lack Holdings Inc",
    "wof:placetype":"venue"
},
  "geometry": {"coordinates":[-95.40375899999999,29.728823],"type":"Point"}
}