{
  "type": "Feature",
  "properties": {
    "iso:country":"US",
    "sg:address":"7400 Sandy Woods Ct",
    "sg:city":"Fort Worth",
    "sg:classifiers":[
        {
            "category":"Shopping",
            "subcategory":"Hobbies, Toys, & Games",
            "type":"Retail Goods"
        }
    ],
    "sg:phone":"+1 817 457 3602",
    "sg:postcode":"76112",
    "sg:province":"TX",
    "wof:name":"Crafts By Priscilla",
    "wof:placetype":"venue"
},
  "geometry": {"coordinates":[-97.19449299999999,32.737628],"type":"Point"}
}