{
  "type": "Feature",
  "properties": {
    "iso:country":"US",
    "sg:address":"509 N Lewis St",
    "sg:city":"Round Rock",
    "sg:classifiers":[
        {
            "category":"Building & Trades",
            "subcategory":"Construction",
            "type":"Services"
        }
    ],
    "sg:phone":"+1 512 244 1520",
    "sg:postcode":"78664",
    "sg:province":"TX",
    "sg:tags":[
        "concrete",
        "contractor"
    ],
    "wof:name":"Fred Solis Underpinning",
    "wof:placetype":"venue"
},
  "geometry": {"coordinates":[-97.676062,30.513621],"type":"Point"}
}