{
  "type": "Feature",
  "properties": {
    "iso:country":"US",
    "sg:address":"1411 J R Hawkins Rd",
    "sg:city":"Kennedale",
    "sg:classifiers":[
        {
            "category":"Manufacturing",
            "subcategory":"Chemicals & Compounds",
            "type":"Manufacturing & Wholesale Goods"
        }
    ],
    "sg:phone":"+1 817 453 0704",
    "sg:postcode":"76060",
    "sg:province":"TX",
    "sg:tags":[
        "finishing",
        "metal",
        "for",
        "mfg"
    ],
    "wof:name":"Custom Chemicals Of Texas",
    "wof:placetype":"venue"
},
  "geometry": {"coordinates":[-97.188976,32.634798],"type":"Point"}
}