{
  "type": "Feature",
  "properties": {
    "iso:country":"US",
    "sg:address":"1808 Washington Ave",
    "sg:city":"Waco",
    "sg:classifiers":[
        {
            "category":"Banks & Credit Unions",
            "subcategory":"Financial Services",
            "type":"Services"
        }
    ],
    "sg:phone":"+1 254 753 1521",
    "sg:postcode":"76701",
    "sg:province":"TX",
    "sg:tags":[
        "company",
        "holding"
    ],
    "wof:name":"Community Co",
    "wof:placetype":"venue"
},
  "geometry": {"coordinates":[-97.14928500000001,31.543002],"type":"Point"}
}