{
  "type": "Feature",
  "properties": {
    "iso:country":"US",
    "sg:address":"56 Wellington St",
    "sg:city":"Houston",
    "sg:classifiers":[
        {
            "category":"Building & Trades",
            "subcategory":"Construction",
            "type":"Services"
        }
    ],
    "sg:phone":"+1 713 695 1529",
    "sg:postcode":"77076",
    "sg:province":"TX",
    "sg:tags":[
        "contractor"
    ],
    "wof:name":"O GP Contractor",
    "wof:placetype":"venue"
},
  "geometry": {"coordinates":[-95.38178600000001,29.858057],"type":"Point"}
}