{
  "type": "Feature",
  "properties": {
    "iso:country":"US",
    "sg:address":"7616 Culebra Rd",
    "sg:city":"San Antonio",
    "sg:classifiers":[
        {
            "category":"Recreation",
            "type":"Entertainment"
        }
    ],
    "sg:phone":"+1 210 520 3325",
    "sg:postcode":"78251",
    "sg:province":"TX",
    "sg:tags":[
        "parlor",
        "billiard"
    ],
    "wof:name":"Fast Eddie's Billiards",
    "wof:placetype":"venue"
},
  "geometry": {"coordinates":[-98.63888900000001,29.459345],"type":"Point"}
}