{
  "type": "Feature",
  "properties": {
    "iso:country":"US",
    "sg:address":"8885 Heath Circle Dr",
    "sg:city":"San Antonio",
    "sg:classifiers":[
        {
            "category":"Education",
            "subcategory":"School",
            "type":"Public Place"
        }
    ],
    "sg:phone":"+1 210 706 7485",
    "sg:postcode":"78250",
    "sg:province":"TX",
    "sg:website":"www.nisd.net",
    "wof:name":"Jimmy Elrod Elementary School",
    "wof:placetype":"venue"
},
  "geometry": {"coordinates":[-98.645618,29.501763],"type":"Point"}
}