{
  "type": "Feature",
  "properties": {
    "iso:country":"US",
    "sg:address":"3931 Granbury Dr",
    "sg:city":"Dallas",
    "sg:classifiers":[
        {
            "category":"Building & Trades",
            "subcategory":"Landscaping Services",
            "type":"Services"
        }
    ],
    "sg:phone":"+1 972 307 7375",
    "sg:postcode":"75287",
    "sg:province":"TX",
    "sg:tags":[
        "designer",
        "landscape"
    ],
    "wof:name":"Legacy Landscape & Lighting",
    "wof:placetype":"venue"
},
  "geometry": {"coordinates":[-96.84819899999999,33.001125],"type":"Point"}
}