{
  "type": "Feature",
  "properties": {
    "iso:country":"US",
    "sg:address":"3443 W Campbell Rd Ste 550",
    "sg:city":"Garland",
    "sg:classifiers":[
        {
            "category":"Restaurant",
            "type":"Food & Drink"
        }
    ],
    "sg:phone":"+1 972 530 8886",
    "sg:postcode":"75044",
    "sg:province":"TX",
    "sg:tags":[
        "mexican"
    ],
    "wof:name":"Desperados",
    "wof:placetype":"venue"
},
  "geometry": {"coordinates":[-96.665497,32.9515],"type":"Point"}
}