{
  "type": "Feature",
  "properties": {
    "iso:country":"US",
    "sg:address":"24609 Willow Ln",
    "sg:city":"Hockley",
    "sg:classifiers":[
        {
            "category":"Building & Trades",
            "subcategory":"Construction",
            "type":"Services"
        }
    ],
    "sg:phone":"+1 936 931 3900",
    "sg:postcode":"77447",
    "sg:province":"TX",
    "sg:tags":[
        "repair",
        "fence",
        "contractor"
    ],
    "wof:name":"Road Runner Fencing & Home Rep",
    "wof:placetype":"venue"
},
  "geometry": {"coordinates":[-95.814635,30.130144],"type":"Point"}
}