{
  "type": "Feature",
  "properties": {
    "iso:country":"US",
    "sg:address":"786 County Road 1140",
    "sg:city":"Ravenna",
    "sg:classifiers":[
        {
            "category":"Professional",
            "subcategory":"Lawyer & Legal Services",
            "type":"Services"
        }
    ],
    "sg:phone":"+1 903 583 6080",
    "sg:postcode":"75476",
    "sg:province":"TX",
    "sg:tags":[
        "attorney"
    ],
    "wof:name":"Kristofer O Taylor",
    "wof:placetype":"venue"
},
  "geometry": {"coordinates":[-96.19106600000001,33.709558],"type":"Point"}
}