{
  "type": "Feature",
  "properties": {
    "iso:country":"US",
    "sg:address":"2722 W Kingsley Rd",
    "sg:city":"Garland",
    "sg:classifiers":[
        {
            "category":"Shopping",
            "subcategory":"Clothing, Apparel, & Fashions",
            "type":"Retail Goods"
        }
    ],
    "sg:phone":"+1 214 703 0312",
    "sg:postcode":"75041",
    "sg:province":"TX",
    "sg:tags":[
        "shop",
        "bridal"
    ],
    "wof:name":"Margarita's Bridal",
    "wof:placetype":"venue"
},
  "geometry": {"coordinates":[-96.67192900000001,32.878705],"type":"Point"}
}