{
  "type": "Feature",
  "properties": {
    "iso:country":"US",
    "sg:address":"15 Circle Park Ct",
    "sg:city":"Mansfield",
    "sg:classifiers":[
        {
            "category":"Building & Trades",
            "subcategory":"Plumbing",
            "type":"Services"
        }
    ],
    "sg:phone":"+1 817 473 0048",
    "sg:postcode":"76063",
    "sg:province":"TX",
    "sg:tags":[
        "contractor"
    ],
    "wof:name":"Bob Block Air Conditioning",
    "wof:placetype":"venue"
},
  "geometry": {"coordinates":[-97.13588799999999,32.571494],"type":"Point"}
}