{
  "type": "Feature",
  "properties": {
    "iso:country":"US",
    "sg:address":"12309 Hodges St",
    "sg:city":"Houston",
    "sg:classifiers":[
        {
            "category":"Manufacturing",
            "subcategory":"Tools & Machinery",
            "type":"Manufacturing & Wholesale Goods"
        }
    ],
    "sg:phone":"+1 713 729 9660",
    "sg:postcode":"77085",
    "sg:province":"TX",
    "sg:tags":[
        "equipment",
        "cooking",
        "commercial",
        "mfg"
    ],
    "wof:name":"Super Chef Manufacturing Co",
    "wof:placetype":"venue"
},
  "geometry": {"coordinates":[-95.50336900000001,29.627762],"type":"Point"}
}