{
  "type": "Feature",
  "properties": {
    "iso:country":"US",
    "sg:address":"1446 Halsey Way",
    "sg:city":"Carrollton",
    "sg:classifiers":[
        {
            "category":"Wholesale",
            "subcategory":"Sporting Goods",
            "type":"Manufacturing & Wholesale Goods"
        },
        {
            "category":"Manufacturing",
            "subcategory":"Toys & Sporting Goods",
            "type":"Manufacturing & Wholesale Goods"
        }
    ],
    "sg:phone":"+1 972 446 8011",
    "sg:postcode":"75007",
    "sg:province":"TX",
    "sg:tags":[
        "sales"
    ],
    "wof:name":"Winning Edge Sales Group Inc",
    "wof:placetype":"venue"
},
  "geometry": {"coordinates":[-96.922256,32.987836],"type":"Point"}
}