{
  "type": "Feature",
  "properties": {
    "iso:country":"US",
    "sg:address":"7721 W Bellfort St",
    "sg:city":"Houston",
    "sg:classifiers":[
        {
            "category":"Shopping",
            "subcategory":"Stationery & Office Supplies",
            "type":"Retail Goods"
        }
    ],
    "sg:phone":"+1 713 995 6355",
    "sg:postcode":"77071",
    "sg:province":"TX",
    "wof:name":"Christine's Corner",
    "wof:placetype":"venue"
},
  "geometry": {"coordinates":[-95.510964,29.655919],"type":"Point"}
}