{
  "type": "Feature",
  "properties": {
    "iso:country":"US",
    "sg:address":"6300 Bridge Point Pkwy",
    "sg:city":"Austin",
    "sg:classifiers":[
        {
            "category":"Professional",
            "subcategory":"Lawyer & Legal Services",
            "type":"Services"
        }
    ],
    "sg:phone":"+1 877 948 4842",
    "sg:postcode":"78730",
    "sg:province":"TX",
    "sg:tags":[
        "personal",
        "injury"
    ],
    "sg:website":"www.withvic.com",
    "wof:name":"FEAZELL VIC LAW OFFICE",
    "wof:placetype":"venue"
},
  "geometry": {"coordinates":[-97.80084600000001,30.354204],"type":"Point"}
}