{
  "type": "Feature",
  "properties": {
    "iso:country":"US",
    "sg:address":"5005 Colleyville Blvd",
    "sg:city":"Colleyville",
    "sg:classifiers":[
        {
            "category":"Personal",
            "subcategory":"Beauty Salon",
            "type":"Services"
        },
        {
            "category":"Personal",
            "subcategory":"Skin Care",
            "type":"Services"
        }
    ],
    "sg:phone":"+1 817 656 8482",
    "sg:postcode":"76034",
    "sg:province":"TX",
    "wof:name":"Viva Derm",
    "wof:placetype":"venue"
},
  "geometry": {"coordinates":[-97.154579,32.88232],"type":"Point"}
}