{
  "type": "Feature",
  "properties": {
    "iso:country":"US",
    "sg:address":"7237 Rochester Dr",
    "sg:city":"El Paso",
    "sg:classifiers":[
        {
            "category":"Retail",
            "subcategory":"Auto Repair",
            "type":"Services"
        }
    ],
    "sg:phone":"+1 915 587 9255",
    "sg:postcode":"79912",
    "sg:province":"TX",
    "sg:tags":[
        "automotive"
    ],
    "wof:name":"Dakota Country",
    "wof:placetype":"venue"
},
  "geometry": {"coordinates":[-106.55501099999999,31.854662],"type":"Point"}
}