{
  "type": "Feature",
  "properties": {
    "iso:country":"US",
    "sg:address":"2215 State Hwy 6",
    "sg:city":"Houston",
    "sg:classifiers":[
        {
            "category":"Insurance",
            "subcategory":"Insurance Agent",
            "type":"Services"
        }
    ],
    "sg:phone":"+1 281 752 9200",
    "sg:postcode":"77077",
    "sg:province":"TX",
    "wof:name":"Roland R Cardner",
    "wof:placetype":"venue"
},
  "geometry": {"coordinates":[-95.644147,29.741491],"type":"Point"}
}