{
  "type": "Feature",
  "properties": {
    "iso:country":"US",
    "sg:address":"1216 Church St",
    "sg:city":"Sulphur Springs",
    "sg:classifiers":[
        {
            "category":"Health Services",
            "subcategory":"Health Practitioner",
            "type":"Services"
        }
    ],
    "sg:phone":"+1 903 439 1990",
    "sg:postcode":"75482",
    "sg:province":"TX",
    "sg:tags":[
        "psychologist"
    ],
    "wof:name":"Darrell Horton PHD",
    "wof:placetype":"venue"
},
  "geometry": {"coordinates":[-95.59909399999999,33.155647],"type":"Point"}
}