{
  "type": "Feature",
  "properties": {
    "iso:country":"US",
    "sg:address":"101 Deer Lake Est",
    "sg:city":"Wimberley",
    "sg:classifiers":[
        {
            "category":"Wholesale",
            "subcategory":"Electrical",
            "type":"Manufacturing & Wholesale Goods"
        },
        {
            "category":"Shopping",
            "subcategory":"Computers & Home Electronics",
            "type":"Retail Goods"
        }
    ],
    "sg:phone":"+1 512 858 1938",
    "sg:postcode":"78676",
    "sg:province":"TX",
    "sg:tags":[
        "equipment",
        "consumer",
        "electric",
        "supply"
    ],
    "wof:name":"Kp Electronics",
    "wof:placetype":"venue"
},
  "geometry": {"coordinates":[-98.03958900000001,30.032141],"type":"Point"}
}