{
  "type": "Feature",
  "properties": {
    "iso:country":"US",
    "sg:address":"612 W Gibson St",
    "sg:city":"Jasper",
    "sg:classifiers":[
        {
            "category":"Travel",
            "subcategory":"Hotels & Motels",
            "type":"Entertainment"
        }
    ],
    "sg:phone":"+1 409 384 2511",
    "sg:postcode":"75951",
    "sg:province":"TX",
    "sg:tags":[
        "lodging"
    ],
    "sg:website":"http://www.econolodge.com/hotel-jasper-texas-TX811",
    "wof:name":"Econo Lodge Jasper",
    "wof:placetype":"venue"
},
  "geometry": {"coordinates":[-93.992833,30.91232],"type":"Point"}
}