{
  "type": "Feature",
  "properties": {
    "iso:country":"US",
    "sg:address":"16135 Preston Rd",
    "sg:city":"Dallas",
    "sg:classifiers":[
        {
            "category":"Professional",
            "type":"Services"
        }
    ],
    "sg:phone":"+1 972 763 0048",
    "sg:postcode":"75248",
    "sg:province":"TX",
    "sg:tags":[
        "establishment"
    ],
    "wof:name":"Ale Moble Housing",
    "wof:placetype":"venue"
},
  "geometry": {"coordinates":[-96.80436,32.968812],"type":"Point"}
}