{
  "type": "Feature",
  "properties": {
    "iso:country":"US",
    "sg:address":"1422 West Dr",
    "sg:city":"Kingsland",
    "sg:classifiers":[
        {
            "category":"Utilities",
            "subcategory":"Water",
            "type":"Services"
        }
    ],
    "sg:phone":"+1 325 388 6611",
    "sg:postcode":"78639",
    "sg:province":"TX",
    "sg:tags":[
        "company",
        "sewage"
    ],
    "wof:name":"Kingsland Water Supply Corp",
    "wof:placetype":"venue"
},
  "geometry": {"coordinates":[-98.44062099999999,30.655127],"type":"Point"}
}