{
  "type": "Feature",
  "properties": {
    "iso:country":"US",
    "sg:address":"5000 S 31st St",
    "sg:city":"Temple",
    "sg:classifiers":[
        {
            "category":"Organizations",
            "subcategory":"Religious Organization",
            "type":"Services"
        }
    ],
    "sg:phone":"+1 254 773 3744",
    "sg:postcode":"76502",
    "sg:province":"TX",
    "sg:tags":[
        "center",
        "daycare",
        "church"
    ],
    "wof:name":"Temple First Nazarene Church",
    "wof:placetype":"venue"
},
  "geometry": {"coordinates":[-97.375513,31.053659],"type":"Point"}
}