{
  "type": "Feature",
  "properties": {
    "iso:country":"US",
    "sg:address":"120 Barkley St",
    "sg:city":"Spearman",
    "sg:classifiers":[
        {
            "category":"Organizations",
            "subcategory":"Religious Organization",
            "type":"Services"
        }
    ],
    "sg:phone":"+1 806 659 2870",
    "sg:postcode":"79081",
    "sg:province":"TX",
    "wof:name":"Apostolic Faith Parsonage",
    "wof:placetype":"venue"
},
  "geometry": {"coordinates":[-101.194733,36.19694],"type":"Point"}
}