{
  "type": "Feature",
  "properties": {
    "iso:country":"US",
    "sg:address":"3332 Fillmore Ave",
    "sg:city":"El Paso",
    "sg:classifiers":[
        {
            "category":"Professional",
            "subcategory":"Computer Services",
            "type":"Services"
        }
    ],
    "sg:phone":"+1 915 566 3762",
    "sg:postcode":"79930",
    "sg:province":"TX",
    "sg:tags":[
        "datum"
    ],
    "wof:name":"Terrazas Alberto",
    "wof:placetype":"venue"
},
  "geometry": {"coordinates":[-106.454317,31.817338],"type":"Point"}
}