{
  "type": "Feature",
  "properties": {
    "iso:country":"US",
    "sg:address":"1900 Preston Rd",
    "sg:city":"Plano",
    "sg:classifiers":[
        {
            "category":"Restaurant",
            "type":"Food & Drink"
        },
        {
            "category":"Food & Beverages",
            "subcategory":"Bakery",
            "type":"Retail Goods"
        }
    ],
    "sg:phone":"+1 469 467 7042",
    "sg:postcode":"75093",
    "sg:province":"TX",
    "sg:tags":[
        "breakfast",
        "sandwich",
        "brunch"
    ],
    "sg:website":"www.panerabread.com",
    "wof:name":"Panera Bread",
    "wof:placetype":"venue"
},
  "geometry": {"coordinates":[-96.794923,33.025704],"type":"Point"}
}