{
  "type": "Feature",
  "properties": {
    "iso:country":"US",
    "sg:address":"108 Rainbow Dr",
    "sg:city":"Atlanta",
    "sg:classifiers":[
        {
            "category":"Manufacturing",
            "subcategory":"Wood Products",
            "type":"Manufacturing & Wholesale Goods"
        }
    ],
    "sg:phone":"+1 903 796 8646",
    "sg:postcode":"75551",
    "sg:province":"TX",
    "sg:tags":[
        "mfg"
    ],
    "wof:name":"Rainbow Custom Wood Designs",
    "wof:placetype":"venue"
},
  "geometry": {"coordinates":[-94.182141,33.08656],"type":"Point"}
}