{
  "type": "Feature",
  "properties": {
    "iso:country":"US",
    "sg:address":"1815 E Lawndale Dr",
    "sg:city":"San Antonio",
    "sg:classifiers":[
        {
            "category":"Real Estate",
            "subcategory":"Architect",
            "type":"Services"
        }
    ],
    "sg:phone":"+1 210 824 1449",
    "sg:postcode":"78209",
    "sg:province":"TX",
    "wof:name":"Alamo Adobe Designs",
    "wof:placetype":"venue"
},
  "geometry": {"coordinates":[-98.465231,29.509803],"type":"Point"}
}