{
  "type": "Feature",
  "properties": {
    "iso:country":"US",
    "sg:address":"4362 Spring Valley Rd.",
    "sg:city":"Dallas",
    "sg:classifiers":[
        {
            "category":"Building & Trades",
            "subcategory":"Plumbing",
            "type":"Services"
        },
        {
            "category":"Building & Trades",
            "subcategory":"Cleaning & Sanitation",
            "type":"Services"
        },
        {
            "category":"Building & Trades",
            "subcategory":"Construction",
            "type":"Services"
        }
    ],
    "sg:phone":"+1 972 953 6261",
    "sg:postcode":"75244",
    "sg:province":"TX",
    "sg:tags":[
        "cleaner",
        "pool",
        "contractor"
    ],
    "sg:website":"www.gabespoolservice.com",
    "wof:name":"Gabe's Pool Service",
    "wof:placetype":"venue"
},
  "geometry": {"coordinates":[-96.835486,32.93964],"type":"Point"}
}