{
  "type": "Feature",
  "properties": {
    "iso:country":"US",
    "sg:address":"12871 N Highway 183",
    "sg:city":"Austin",
    "sg:classifiers":[
        {
            "category":"Organizations",
            "subcategory":"Religious Organization",
            "type":"Services"
        }
    ],
    "sg:phone":"+1 512 336 7370",
    "sg:postcode":"78750",
    "sg:province":"TX",
    "wof:name":"St Barnabas Church",
    "wof:placetype":"venue"
},
  "geometry": {"coordinates":[-97.78029600000001,30.4401],"type":"Point"}
}