{
  "type": "Feature",
  "properties": {
    "iso:country":"US",
    "sg:address":"203 Main St",
    "sg:city":"Moulton",
    "sg:classifiers":[
        {
            "category":"Retail",
            "subcategory":"Repair Shop",
            "type":"Services"
        }
    ],
    "sg:phone":"+1 361 596 7438",
    "sg:postcode":"77975",
    "sg:province":"TX",
    "sg:tags":[
        "upholsterer"
    ],
    "wof:name":"Filipp Upholstery",
    "wof:placetype":"venue"
},
  "geometry": {"coordinates":[-97.14584499999999,29.575543],"type":"Point"}
}