{
  "type": "Feature",
  "properties": {
    "iso:country":"US",
    "sg:address":"1221 Blalock Rd",
    "sg:city":"Houston",
    "sg:classifiers":[
        {
            "category":"Autos & Motor Vehicles",
            "subcategory":"Recreational Vehicle Sales",
            "type":"Retail Goods"
        }
    ],
    "sg:phone":"+1 713 932 1717",
    "sg:postcode":"77055",
    "sg:province":"TX",
    "wof:name":"Family Rv's",
    "wof:placetype":"venue"
},
  "geometry": {"coordinates":[-95.52186,29.790346],"type":"Point"}
}