{
  "type": "Feature",
  "properties": {
    "iso:country":"US",
    "sg:address":"1 Applehead Island Dr",
    "sg:city":"Horseshoe Bay",
    "sg:classifiers":[
        {
            "category":"Professional",
            "subcategory":"Detective & Security Services",
            "type":"Services"
        }
    ],
    "sg:phone":"+1 830 598 8320",
    "sg:postcode":"78654",
    "sg:province":"TX",
    "sg:tags":[
        "guard",
        "patrol"
    ],
    "wof:name":"Applehead Island Security",
    "wof:placetype":"venue"
},
  "geometry": {"coordinates":[-98.39448899999999,30.560076],"type":"Point"}
}