{
  "type": "Feature",
  "properties": {
    "iso:country":"US",
    "sg:address":"118 Summer Rd",
    "sg:city":"Georgetown",
    "sg:classifiers":[
        {
            "category":"Shopping",
            "subcategory":"Department Store",
            "type":"Retail Goods"
        }
    ],
    "sg:phone":"+1 512 240 4288",
    "sg:postcode":"78633",
    "sg:province":"TX",
    "wof:name":"Virginia Eyerly",
    "wof:placetype":"venue"
},
  "geometry": {"coordinates":[-97.716223,30.727646],"type":"Point"}
}