{
  "type": "Feature",
  "properties": {
    "iso:country":"US",
    "sg:address":"4412 Graves Dr",
    "sg:city":"Odessa",
    "sg:classifiers":[
        {
            "category":"Home & Garden",
            "subcategory":"Hardware",
            "type":"Retail Goods"
        }
    ],
    "sg:phone":"+1 432 550 3921",
    "sg:postcode":"79762",
    "sg:province":"TX",
    "wof:name":"Doug Scott Tools",
    "wof:placetype":"venue"
},
  "geometry": {"coordinates":[-102.34551,31.8988],"type":"Point"}
}