{
  "type": "Feature",
  "properties": {
    "iso:country":"US",
    "sg:address":"5100 Edgecliff Dr",
    "sg:city":"Wichita Falls",
    "sg:classifiers":[
        {
            "category":"Building & Trades",
            "subcategory":"Electrical",
            "type":"Services"
        }
    ],
    "sg:phone":"+1 940 723 6500",
    "sg:postcode":"76302",
    "sg:province":"TX",
    "sg:tags":[
        "electrical",
        "contractor"
    ],
    "wof:name":"Sg Electronics",
    "wof:placetype":"venue"
},
  "geometry": {"coordinates":[-98.510745,33.852571],"type":"Point"}
}