{
  "type": "Feature",
  "properties": {
    "iso:country":"US",
    "sg:address":"911 S Clay St",
    "sg:city":"Ennis",
    "sg:classifiers":[
        {
            "category":"Health Services",
            "subcategory":"Doctor",
            "type":"Services"
        }
    ],
    "sg:phone":"+1 972 875 4200",
    "sg:postcode":"75119",
    "sg:province":"TX",
    "sg:tags":[
        "physician",
        "surgeon"
    ],
    "wof:name":"North Texas Childrens Clinic",
    "wof:placetype":"venue"
},
  "geometry": {"coordinates":[-96.62855500000001,32.318047],"type":"Point"}
}