{
  "type": "Feature",
  "properties": {
    "iso:country":"US",
    "sg:address":"211 W Levert St",
    "sg:city":"Kirbyville",
    "sg:classifiers":[
        {
            "category":"Retail",
            "subcategory":"Auto Repair",
            "type":"Services"
        }
    ],
    "sg:phone":"+1 409 420 0602",
    "sg:postcode":"75956",
    "sg:province":"TX",
    "wof:name":"Levert Auto Center",
    "wof:placetype":"venue"
},
  "geometry": {"coordinates":[-93.894873,30.657695],"type":"Point"}
}