{
  "type": "Feature",
  "properties": {
    "iso:country":"US",
    "sg:address":"431 Spanish Moss Ct",
    "sg:city":"Coppell",
    "sg:classifiers":[
        {
            "category":"Professional",
            "type":"Services"
        }
    ],
    "sg:phone":"+1 972 393 4776",
    "sg:postcode":"75019",
    "sg:province":"TX",
    "wof:name":"Blue Coyote",
    "wof:placetype":"venue"
},
  "geometry": {"coordinates":[-97.00442200000001,32.961186],"type":"Point"}
}