{
  "type": "Feature",
  "properties": {
    "iso:country":"US",
    "sg:address":"2807 Mc Kinley Ave",
    "sg:city":"Fort Worth",
    "sg:classifiers":[
        {
            "category":"Building & Trades",
            "subcategory":"Landscaping Services",
            "type":"Services"
        }
    ],
    "sg:phone":"+1 817 624 2714",
    "sg:postcode":"76106",
    "sg:province":"TX",
    "wof:name":"Anas Lawn Service",
    "wof:placetype":"venue"
},
  "geometry": {"coordinates":[-97.36957,32.796523],"type":"Point"}
}