{
  "type": "Feature",
  "properties": {
    "iso:country":"US",
    "sg:address":"610 Rainforest Ln",
    "sg:city":"Allen",
    "sg:classifiers":[
        {
            "category":"Professional",
            "subcategory":"Art Services",
            "type":"Services"
        }
    ],
    "sg:phone":"+1 972 359 9000",
    "sg:postcode":"75013",
    "sg:province":"TX",
    "sg:tags":[
        "photographer"
    ],
    "wof:name":"Jim Wilson Photography",
    "wof:placetype":"venue"
},
  "geometry": {"coordinates":[-96.69121699999999,33.107403],"type":"Point"}
}