{
  "type": "Feature",
  "properties": {
    "iso:country":"US",
    "sg:address":"1800 Dabney Dr",
    "sg:city":"Pasadena",
    "sg:classifiers":[
        {
            "category":"Freight",
            "type":"Transportation"
        }
    ],
    "sg:phone":"+1 713 910 4688",
    "sg:postcode":"77502",
    "sg:province":"TX",
    "sg:tags":[
        "fixed",
        "motor",
        "facility"
    ],
    "wof:name":"Camin Cargo Control Inc",
    "wof:placetype":"venue"
},
  "geometry": {"coordinates":[-95.18634900000001,29.666597],"type":"Point"}
}