{
  "type": "Feature",
  "properties": {
    "iso:country":"US",
    "sg:address":"1109 S Airport Cir",
    "sg:city":"Euless",
    "sg:classifiers":[
        {
            "category":"Wholesale",
            "subcategory":"Construction Materials",
            "type":"Manufacturing & Wholesale Goods"
        }
    ],
    "sg:phone":"+1 817 868 0079",
    "sg:postcode":"76040",
    "sg:province":"TX",
    "sg:tags":[
        "gates"
    ],
    "wof:name":"American National Fence",
    "wof:placetype":"venue"
},
  "geometry": {"coordinates":[-97.11441499999999,32.819981],"type":"Point"}
}