{
  "type": "Feature",
  "properties": {
    "iso:country":"US",
    "sg:address":"999 E Fm 628",
    "sg:city":"Riviera",
    "sg:classifiers":[
        {
            "category":"Coffee & Tea",
            "type":"Food & Drink"
        },
        {
            "category":"Restaurant",
            "type":"Food & Drink"
        }
    ],
    "sg:phone":"+1 361 297 5706",
    "sg:postcode":"78379",
    "sg:province":"TX",
    "sg:tags":[
        "espresso"
    ],
    "wof:name":"Front Porch Cafe",
    "wof:placetype":"venue"
},
  "geometry": {"coordinates":[-97.691249,27.330282],"type":"Point"}
}