{
  "type": "Feature",
  "properties": {
    "iso:country":"US",
    "sg:address":"2915 Guadalupe",
    "sg:city":"Austin",
    "sg:classifiers":[
        {
            "category":"Coffee & Tea",
            "type":"Food & Drink"
        }
    ],
    "sg:phone":"+1 512 699 7434",
    "sg:postcode":"78705",
    "sg:province":"TX",
    "sg:website":"www.fatcockcoffee.com/",
    "wof:name":"Fatcock Coffee's Sno Cones",
    "wof:placetype":"venue"
},
  "geometry": {"coordinates":[-97.742131,30.295858],"type":"Point"}
}