{
  "type": "Feature",
  "properties": {
    "iso:country":"US",
    "sg:address":"2416 S 13th St",
    "sg:city":"Temple",
    "sg:classifiers":[
        {
            "category":"Real Estate",
            "subcategory":"Real Estate Operator",
            "type":"Services"
        }
    ],
    "sg:phone":"+1 254 773 7731",
    "sg:postcode":"76504",
    "sg:province":"TX",
    "sg:tags":[
        "apartment"
    ],
    "wof:name":"Arbors Of Temple",
    "wof:placetype":"venue"
},
  "geometry": {"coordinates":[-97.35893,31.071561],"type":"Point"}
}