{
  "type": "Feature",
  "properties": {
    "iso:country":"US",
    "sg:address":"114 W 3rd St",
    "sg:city":"San Juan",
    "sg:classifiers":[
        {
            "category":"Food & Beverages",
            "subcategory":"Bakery",
            "type":"Retail Goods"
        }
    ],
    "sg:phone":"+1 956 783 0296",
    "sg:postcode":"78589",
    "sg:province":"TX",
    "wof:name":"Especial Bakery",
    "wof:placetype":"venue"
},
  "geometry": {"coordinates":[-98.15639299999999,26.19247],"type":"Point"}
}