{
  "type": "Feature",
  "properties": {
    "iso:country":"US",
    "sg:address":"4501 Park Meadow Ct",
    "sg:city":"Garland",
    "sg:classifiers":[
        {
            "category":"Manufacturing",
            "subcategory":"Glass & Minerals",
            "type":"Manufacturing & Wholesale Goods"
        }
    ],
    "sg:phone":"+1 972 303 6605",
    "sg:postcode":"75043",
    "sg:province":"TX",
    "sg:tags":[
        "fiberglass",
        "insulation",
        "mfg"
    ],
    "wof:name":"Owens Corning",
    "wof:placetype":"venue"
},
  "geometry": {"coordinates":[-96.585269,32.865232],"type":"Point"}
}