{
  "type": "Feature",
  "properties": {
    "iso:country":"US",
    "sg:address":"1725 Dismuke St",
    "sg:city":"Houston",
    "sg:classifiers":[
        {
            "category":"Food & Beverages",
            "subcategory":"Groceries & Convenience Stores",
            "type":"Retail Goods"
        }
    ],
    "sg:phone":"+1 713 926 1977",
    "sg:postcode":"77023",
    "sg:province":"TX",
    "wof:name":"Sam's Drive-Inn Grocery",
    "wof:placetype":"venue"
},
  "geometry": {"coordinates":[-95.31909899999999,29.723301],"type":"Point"}
}