{
  "type": "Feature",
  "properties": {
    "iso:country":"US",
    "sg:address":"2214 Canyon Creek Plz",
    "sg:city":"Richardson",
    "sg:classifiers":[
        {
            "category":"Freight",
            "type":"Transportation"
        }
    ],
    "sg:phone":"+1 972 690 4828",
    "sg:postcode":"75080",
    "sg:province":"TX",
    "wof:name":"Scooter Town",
    "wof:placetype":"venue"
},
  "geometry": {"coordinates":[-96.729345,32.980654],"type":"Point"}
}