{
  "type": "Feature",
  "properties": {
    "iso:country":"US",
    "sg:address":"5246 Highway 71 E",
    "sg:city":"Austin",
    "sg:classifiers":[
        {
            "category":"Cinema",
            "subcategory":"Movie Rental",
            "type":"Entertainment"
        }
    ],
    "sg:phone":"+1 512 385 6057",
    "sg:postcode":"78617",
    "sg:province":"TX",
    "sg:tags":[
        "game",
        "video"
    ],
    "wof:name":"Ave",
    "wof:placetype":"venue"
},
  "geometry": {"coordinates":[-97.551351,30.18539],"type":"Point"}
}