{
  "type": "Feature",
  "properties": {
    "iso:country":"US",
    "sg:address":"14648 Walters St",
    "sg:city":"Houston",
    "sg:classifiers":[
        {
            "category":"Retail",
            "subcategory":"Laundry & Dry Cleaning",
            "type":"Services"
        }
    ],
    "sg:phone":"+1 281 537 8131",
    "sg:postcode":"77068",
    "sg:province":"TX",
    "wof:name":"Joyful Alterations & Cleaning",
    "wof:placetype":"venue"
},
  "geometry": {"coordinates":[-95.485896,29.995778],"type":"Point"}
}