{
  "type": "Feature",
  "properties": {
    "iso:country":"US",
    "sg:address":"6301 18th St",
    "sg:city":"Lubbock",
    "sg:classifiers":[
        {
            "category":"Professional",
            "type":"Services"
        }
    ],
    "sg:phone":"+1 806 722 6021",
    "sg:postcode":"79416",
    "sg:province":"TX",
    "wof:name":"Light House Fundraising I",
    "wof:placetype":"venue"
},
  "geometry": {"coordinates":[-101.952625,33.579887],"type":"Point"}
}