{
  "type": "Feature",
  "properties": {
    "iso:country":"US",
    "sg:address":"104 I- 35 Svc Rd",
    "sg:city":"Hillsboro",
    "sg:classifiers":[
        {
            "category":"Shopping",
            "subcategory":"Clothing, Apparel, & Fashions",
            "type":"Retail Goods"
        }
    ],
    "sg:phone":"+1 254 582 8212",
    "sg:postcode":"76640",
    "sg:province":"TX",
    "sg:tags":[
        "retailer",
        "hosiery",
        "lady",
        "knit",
        "sportswear"
    ],
    "wof:name":"Jockey 78",
    "wof:placetype":"venue"
},
  "geometry": {"coordinates":[-97.099763,31.67272],"type":"Point"}
}