{
  "type": "Feature",
  "properties": {
    "iso:country":"US",
    "sg:address":"12002 Beechnut St",
    "sg:city":"Houston",
    "sg:classifiers":[
        {
            "category":"Utilities",
            "subcategory":"Cable",
            "type":"Services"
        }
    ],
    "sg:phone":"+1 281 530 4500",
    "sg:postcode":"77072",
    "sg:province":"TX",
    "sg:tags":[
        "satellite",
        "carrier"
    ],
    "wof:name":"Global Link Satellites",
    "wof:placetype":"venue"
},
  "geometry": {"coordinates":[-95.591454,29.688941],"type":"Point"}
}