{
  "type": "Feature",
  "properties": {
    "iso:country":"US",
    "sg:address":"8227 Heights Vly",
    "sg:city":"Converse",
    "sg:classifiers":[
        {
            "category":"Building & Trades",
            "subcategory":"Cleaning & Sanitation",
            "type":"Services"
        }
    ],
    "sg:phone":"+1 210 662 2806",
    "sg:postcode":"78109",
    "sg:province":"TX",
    "sg:tags":[
        "cleaning-industrial",
        "contractor"
    ],
    "wof:name":"Z & Z Cleaning Services",
    "wof:placetype":"venue"
},
  "geometry": {"coordinates":[-98.326746,29.493944],"type":"Point"}
}