{
  "type": "Feature",
  "properties": {
    "iso:country":"US",
    "sg:address":"601 Balboa St",
    "sg:city":"Irving",
    "sg:classifiers":[
        {
            "category":"Organizations",
            "subcategory":"Community Association",
            "type":"Services"
        }
    ],
    "sg:phone":"+1 972 791 0281",
    "sg:postcode":"75062",
    "sg:province":"TX",
    "sg:tags":[
        "educational"
    ],
    "wof:name":"Choices Plus Action",
    "wof:placetype":"venue"
},
  "geometry": {"coordinates":[-96.93535,32.853505],"type":"Point"}
}