{
  "type": "Feature",
  "properties": {
    "iso:country":"US",
    "sg:address":"10003 Weldon Rd",
    "sg:city":"Freeport",
    "sg:classifiers":[
        {
            "category":"Building & Trades",
            "subcategory":"Construction",
            "type":"Services"
        }
    ],
    "sg:phone":"+1 979 233 4985",
    "sg:postcode":"77541",
    "sg:province":"TX",
    "sg:tags":[
        "welder"
    ],
    "wof:name":"Whitton's Welding Shop",
    "wof:placetype":"venue"
},
  "geometry": {"coordinates":[-95.500013,28.98454],"type":"Point"}
}