{
  "type": "Feature",
  "properties": {
    "iso:country":"US",
    "sg:address":"9337 Katy Fwy",
    "sg:city":"Houston",
    "sg:classifiers":[
        {
            "category":"Building & Trades",
            "subcategory":"Landscaping Services",
            "type":"Services"
        }
    ],
    "sg:phone":"+1 281 556 8089",
    "sg:postcode":"77024",
    "sg:province":"TX",
    "wof:name":"Houston Lawn Management",
    "wof:placetype":"venue"
},
  "geometry": {"coordinates":[-95.52126,29.783734],"type":"Point"}
}