{
  "type": "Feature",
  "properties": {
    "iso:country":"US",
    "sg:address":"2705 Hampstead Ln",
    "sg:city":"Wichita Falls",
    "sg:classifiers":[
        {
            "category":"Shopping",
            "subcategory":"Clothing, Apparel, & Fashions",
            "type":"Retail Goods"
        }
    ],
    "sg:phone":"+1 940 696 9333",
    "sg:postcode":"76308",
    "sg:province":"TX",
    "sg:tags":[
        "tailor"
    ],
    "wof:name":"Dolores' Sewing Room Boutique",
    "wof:placetype":"venue"
},
  "geometry": {"coordinates":[-98.53063,33.877915],"type":"Point"}
}