{
  "type": "Feature",
  "properties": {
    "iso:country":"US",
    "sg:address":"1433 Lone Star Ct",
    "sg:city":"Allen",
    "sg:classifiers":[
        {
            "category":"Professional",
            "subcategory":"Business Services",
            "type":"Services"
        }
    ],
    "sg:phone":"+1 972 359 0753",
    "sg:postcode":"75013",
    "sg:province":"TX",
    "wof:name":"Zenga Solutions LLC",
    "wof:placetype":"venue"
},
  "geometry": {"coordinates":[-96.70589200000001,33.108553],"type":"Point"}
}