{
  "type": "Feature",
  "properties": {
    "iso:country":"US",
    "sg:address":"501 Indian Springs Dr",
    "sg:city":"Marshall",
    "sg:classifiers":[
        {
            "category":"Organizations",
            "subcategory":"Religious Organization",
            "type":"Services"
        }
    ],
    "sg:phone":"+1 903 935 3787",
    "sg:postcode":"75672",
    "sg:province":"TX",
    "sg:tags":[
        "church"
    ],
    "wof:name":"Cumberland Presbyterian Church",
    "wof:placetype":"venue"
},
  "geometry": {"coordinates":[-94.33417300000001,32.538404],"type":"Point"}
}