{
  "type": "Feature",
  "properties": {
    "iso:country":"US",
    "sg:address":"810 Tucker Hill Rd",
    "sg:city":"Silsbee",
    "sg:classifiers":[
        {
            "category":"Retail",
            "subcategory":"Auto Repair",
            "type":"Services"
        }
    ],
    "sg:phone":"+1 409 386 1395",
    "sg:postcode":"77656",
    "sg:province":"TX",
    "sg:tags":[
        "engine"
    ],
    "wof:name":"P2x Diesel Performance",
    "wof:placetype":"venue"
},
  "geometry": {"coordinates":[-94.161393,30.370047],"type":"Point"}
}