{
  "type": "Feature",
  "properties": {
    "iso:country":"US",
    "sg:address":"22103 Fm 2100 Rd",
    "sg:city":"Crosby",
    "sg:classifiers":[
        {
            "category":"Building & Trades",
            "subcategory":"Construction",
            "type":"Services"
        }
    ],
    "sg:phone":"+1 281 806 0775",
    "sg:postcode":"77532",
    "sg:province":"TX",
    "sg:tags":[
        "consultant",
        "industrial",
        "contractors-commercial"
    ],
    "wof:name":"Pilecap, Incorporated",
    "wof:placetype":"venue"
},
  "geometry": {"coordinates":[-95.092528,29.994287],"type":"Point"}
}