{
  "type": "Feature",
  "properties": {
    "iso:country":"US",
    "sg:address":"13905 R L Ostos Rd",
    "sg:city":"Brownsville",
    "sg:classifiers":[
        {
            "category":"Mining & Drilling",
            "type":"Manufacturing & Wholesale Goods"
        }
    ],
    "sg:phone":"+1 956 831 8140",
    "sg:postcode":"78521",
    "sg:province":"TX",
    "sg:tags":[
        "company",
        "ore",
        "processing"
    ],
    "wof:name":"U S Clay LP",
    "wof:placetype":"venue"
},
  "geometry": {"coordinates":[-97.38868600000001,25.952451],"type":"Point"}
}