{
  "type": "Feature",
  "properties": {
    "iso:country":"US",
    "sg:address":"118 E 5th St",
    "sg:city":"Austin",
    "sg:classifiers":[
        {
            "category":"Professional",
            "subcategory":"Accounting & Tax Preparation",
            "type":"Services"
        }
    ],
    "sg:phone":"+1 512 323 5501",
    "sg:postcode":"78701",
    "sg:province":"TX",
    "sg:tags":[
        "accountant"
    ],
    "sg:website":"www.samedaypassport-visa.com",
    "wof:name":"Austin Passport Service",
    "wof:placetype":"venue"
},
  "geometry": {"coordinates":[-97.74290999999999,30.267069],"type":"Point"}
}