{
  "type": "Feature",
  "properties": {
    "iso:country":"US",
    "sg:address":"9803 Harwin Dr",
    "sg:city":"Houston",
    "sg:classifiers":[
        {
            "category":"Shopping",
            "subcategory":"Florist",
            "type":"Retail Goods"
        }
    ],
    "sg:phone":"+1 713 784 4848",
    "sg:postcode":"77036",
    "sg:province":"TX",
    "wof:name":"Lexis Florist",
    "wof:placetype":"venue"
},
  "geometry": {"coordinates":[-95.536697,29.717657],"type":"Point"}
}