{
  "type": "Feature",
  "properties": {
    "iso:country":"US",
    "sg:address":"4327 Vespero St",
    "sg:city":"San Antonio",
    "sg:classifiers":[
        {
            "category":"Personal",
            "type":"Services"
        }
    ],
    "sg:phone":"+1 210 599 3728",
    "sg:postcode":"78233",
    "sg:province":"TX",
    "wof:name":"Kimco Services",
    "wof:placetype":"venue"
},
  "geometry": {"coordinates":[-98.407127,29.543307],"type":"Point"}
}