{
  "type": "Feature",
  "properties": {
    "iso:country":"US",
    "sg:address":"1033 Jarvis Rd",
    "sg:city":"Fort Worth",
    "sg:classifiers":[
        {
            "category":"Wholesale",
            "subcategory":"Machinery & Supplies",
            "type":"Manufacturing & Wholesale Goods"
        }
    ],
    "sg:phone":"+1 817 232 5593",
    "sg:postcode":"76179",
    "sg:province":"TX",
    "sg:tags":[
        "industrial"
    ],
    "wof:name":"Air Nail Systems",
    "wof:placetype":"venue"
},
  "geometry": {"coordinates":[-97.369818,32.871907],"type":"Point"}
}