{
  "type": "Feature",
  "properties": {
    "iso:country":"US",
    "sg:address":"26275 FM 2090",
    "sg:city":"Splendora",
    "sg:classifiers":[
        {
            "category":"Education",
            "subcategory":"School",
            "type":"Public Place"
        }
    ],
    "sg:phone":"+1 281 689 8020",
    "sg:postcode":"77372",
    "sg:province":"TX",
    "sg:tags":[
        "intermediate"
    ],
    "wof:name":"Splendora Intermediate School",
    "wof:placetype":"venue"
},
  "geometry": {"coordinates":[-95.156425,30.233227],"type":"Point"}
}