{
  "type": "Feature",
  "properties": {
    "iso:country":"US",
    "sg:address":"808 Clover Hill Ln",
    "sg:city":"Cedar Hill",
    "sg:classifiers":[
        {
            "category":"Shopping",
            "subcategory":"Clothing, Apparel, & Fashions",
            "type":"Retail Goods"
        }
    ],
    "sg:phone":"+1 972 291 6584",
    "sg:postcode":"75104",
    "sg:province":"TX",
    "wof:name":"CCS Fashions",
    "wof:placetype":"venue"
},
  "geometry": {"coordinates":[-96.928809,32.612839],"type":"Point"}
}