{
  "type": "Feature",
  "properties": {
    "iso:country":"US",
    "sg:address":"1908 Hanover Dr",
    "sg:city":"Richardson",
    "sg:classifiers":[
        {
            "category":"Banks & Credit Unions",
            "subcategory":"Financial Services",
            "type":"Services"
        }
    ],
    "sg:phone":"+1 972 690 4543",
    "sg:postcode":"75081",
    "sg:province":"TX",
    "sg:tags":[
        "trust",
        "management"
    ],
    "wof:name":"Cahoone Revocable Trust",
    "wof:placetype":"venue"
},
  "geometry": {"coordinates":[-96.689184,32.959932],"type":"Point"}
}