{
  "type": "Feature",
  "properties": {
    "iso:country":"US",
    "sg:address":"1911 Pitts Rd",
    "sg:city":"Richmond",
    "sg:classifiers":[
        {
            "category":"Communications",
            "type":"Services"
        }
    ],
    "sg:phone":"+1 281 232 6800",
    "sg:postcode":"77469",
    "sg:province":"TX",
    "sg:tags":[
        "internet"
    ],
    "wof:name":"Andrews Website Svc",
    "wof:placetype":"venue"
},
  "geometry": {"coordinates":[-95.733429,29.62414],"type":"Point"}
}