{
  "type": "Feature",
  "properties": {
    "iso:country":"US",
    "sg:address":"502 E Tyler Ave",
    "sg:city":"Harlingen",
    "sg:classifiers":[
        {
            "category":"Government",
            "subcategory":"Office",
            "type":"Public Place"
        }
    ],
    "sg:phone":"+1 956 430 8103",
    "sg:postcode":"78550",
    "sg:province":"TX",
    "sg:tags":[
        "city",
        "inspection"
    ],
    "wof:name":"Harlingen Building Inspections",
    "wof:placetype":"venue"
},
  "geometry": {"coordinates":[-97.690136,26.18956],"type":"Point"}
}