{
  "type": "Feature",
  "properties": {
    "iso:country":"US",
    "sg:address":"213 W Shaw Ave",
    "sg:city":"Pasadena",
    "sg:classifiers":[
        {
            "category":"Organizations",
            "subcategory":"Labor Organization",
            "type":"Services"
        }
    ],
    "sg:phone":"+1 713 473 9436",
    "sg:postcode":"77506",
    "sg:province":"TX",
    "wof:name":"ILA",
    "wof:placetype":"venue"
},
  "geometry": {"coordinates":[-95.212918,29.712494],"type":"Point"}
}