{
  "type": "Feature",
  "properties": {
    "iso:country":"US",
    "sg:address":"3526 Rushwater Ln",
    "sg:city":"Friendswood",
    "sg:classifiers":[
        {
            "category":"Shopping",
            "subcategory":"Bicycles & Sporting Goods",
            "type":"Retail Goods"
        }
    ],
    "sg:phone":"+1 281 993 2274",
    "sg:postcode":"77546",
    "sg:province":"TX",
    "wof:name":"Trinity Firearms",
    "wof:placetype":"venue"
},
  "geometry": {"coordinates":[-95.17081399999999,29.534267],"type":"Point"}
}