{
  "type": "Feature",
  "properties": {
    "iso:country":"US",
    "sg:address":"2227 Newbury Dr",
    "sg:city":"Arlington",
    "sg:classifiers":[
        {
            "category":"Retail",
            "subcategory":"Laundry & Dry Cleaning",
            "type":"Services"
        }
    ],
    "sg:phone":"+1 817 797 5538",
    "sg:postcode":"76014",
    "sg:province":"TX",
    "sg:tags":[
        "cleaners",
        "rug",
        "carpet"
    ],
    "wof:name":"Fredd's Super Carpet Cleaning",
    "wof:placetype":"venue"
},
  "geometry": {"coordinates":[-97.06780500000001,32.686608],"type":"Point"}
}