{
  "type": "Feature",
  "properties": {
    "iso:country":"US",
    "sg:address":"6200 Harborside Dr",
    "sg:city":"Galveston",
    "sg:classifiers":[
        {
            "category":"Home & Garden",
            "subcategory":"Building Materials",
            "type":"Retail Goods"
        }
    ],
    "sg:phone":"+1 409 744 9993",
    "sg:postcode":"77554",
    "sg:province":"TX",
    "sg:tags":[
        "mixed",
        "concrete"
    ],
    "wof:name":"Kelso Concrete Co",
    "wof:placetype":"venue"
},
  "geometry": {"coordinates":[-94.839068,29.297166],"type":"Point"}
}