{
  "type": "Feature",
  "properties": {
    "iso:country":"US",
    "sg:address":"808 8th St",
    "sg:city":"Lubbock",
    "sg:classifiers":[
        {
            "category":"Professional",
            "subcategory":"Advertising",
            "type":"Services"
        }
    ],
    "sg:phone":"+1 806 744 4736",
    "sg:postcode":"79401",
    "sg:province":"TX",
    "sg:tags":[
        "agency",
        "business"
    ],
    "wof:name":"Universal Graphix",
    "wof:placetype":"venue"
},
  "geometry": {"coordinates":[-101.843839,33.588382],"type":"Point"}
}