{
  "type": "Feature",
  "properties": {
    "iso:country":"US",
    "sg:address":"1601 Western Cir",
    "sg:city":"Dimmitt",
    "sg:classifiers":[
        {
            "category":"Farming",
            "subcategory":"Livestock Farm",
            "type":"Manufacturing & Wholesale Goods"
        }
    ],
    "sg:phone":"+1 806 647 5111",
    "sg:postcode":"79027",
    "sg:province":"TX",
    "sg:tags":[
        "feeding"
    ],
    "wof:name":"Bud Hill Feedlots",
    "wof:placetype":"venue"
},
  "geometry": {"coordinates":[-102.334689,34.545089],"type":"Point"}
}