{
  "type": "Feature",
  "properties": {
    "iso:country":"US",
    "sg:address":"12813 Webercrest Rd",
    "sg:city":"Houston",
    "sg:classifiers":[
        {
            "category":"Building & Trades",
            "subcategory":"Construction",
            "type":"Services"
        }
    ],
    "sg:phone":"+1 713 991 6767",
    "sg:postcode":"77048",
    "sg:province":"TX",
    "sg:tags":[
        "concrete",
        "contractor"
    ],
    "sg:website":"www.mbconcrete.com",
    "wof:name":"Miller Builders",
    "wof:placetype":"venue"
},
  "geometry": {"coordinates":[-95.33147599999999,29.623227],"type":"Point"}
}