{
  "type": "Feature",
  "properties": {
    "iso:country":"US",
    "sg:address":"802 Bogart Rd",
    "sg:city":"Cedar Park",
    "sg:classifiers":[
        {
            "category":"Home & Garden",
            "subcategory":"Carpets & Floor Coverings",
            "type":"Retail Goods"
        }
    ],
    "sg:phone":"+1 512 260 6250",
    "sg:postcode":"78613",
    "sg:province":"TX",
    "sg:tags":[
        "flooring"
    ],
    "wof:name":"Nah Inc",
    "wof:placetype":"venue"
},
  "geometry": {"coordinates":[-97.813166,30.517385],"type":"Point"}
}