{
  "type": "Feature",
  "properties": {
    "iso:country":"US",
    "sg:address":"3402 N Navarro St",
    "sg:city":"Victoria",
    "sg:classifiers":[
        {
            "category":"Autos & Motor Vehicles",
            "subcategory":"Auto Supplies",
            "type":"Retail Goods"
        },
        {
            "category":"Wholesale",
            "subcategory":"Auto Parts",
            "type":"Manufacturing & Wholesale Goods"
        }
    ],
    "sg:phone":"+1 361 578 2888",
    "sg:postcode":"77901",
    "sg:province":"TX",
    "wof:name":"Hi-Lo Auto Supply Inc 41",
    "wof:placetype":"venue"
},
  "geometry": {"coordinates":[-97.000863,28.826902],"type":"Point"}
}