{
  "type": "Feature",
  "properties": {
    "iso:country":"US",
    "sg:address":"1821 Norman St",
    "sg:city":"La Marque",
    "sg:classifiers":[
        {
            "category":"Professional",
            "subcategory":"Management & Consulting",
            "type":"Services"
        }
    ],
    "sg:phone":"+1 409 949 4248",
    "sg:postcode":"77568",
    "sg:province":"TX",
    "sg:tags":[
        "business"
    ],
    "wof:name":"C & C Consulting",
    "wof:placetype":"venue"
},
  "geometry": {"coordinates":[-94.968598,29.361714],"type":"Point"}
}