{
  "type": "Feature",
  "properties": {
    "iso:country":"US",
    "sg:address":"4717 Kress St",
    "sg:city":"Houston",
    "sg:classifiers":[
        {
            "category":"Education",
            "subcategory":"Special Training",
            "type":"Public Place"
        }
    ],
    "sg:phone":"+1 713 672 7830",
    "sg:postcode":"77026",
    "sg:province":"TX",
    "wof:name":"Air Xpressions",
    "wof:placetype":"venue"
},
  "geometry": {"coordinates":[-95.30928400000001,29.801231],"type":"Point"}
}