{
  "type": "Feature",
  "properties": {
    "iso:country":"US",
    "sg:address":"5959 Westheimer Rd Ste 110",
    "sg:city":"Houston",
    "sg:classifiers":[
        {
            "category":"Building & Trades",
            "subcategory":"Pest Control",
            "type":"Services"
        }
    ],
    "sg:phone":"+1 713 974 6706",
    "sg:postcode":"77057",
    "sg:province":"TX",
    "wof:name":"Pest Control One",
    "wof:placetype":"venue"
},
  "geometry": {"coordinates":[-95.48780499999999,29.737067],"type":"Point"}
}