{
  "type": "Feature",
  "properties": {
    "iso:country":"US",
    "sg:address":"1637 Pasadena Blvd",
    "sg:city":"Pasadena",
    "sg:classifiers":[
        {
            "category":"Building & Trades",
            "subcategory":"Locksmith",
            "type":"Services"
        }
    ],
    "sg:phone":"+1 281 602 6837",
    "sg:postcode":"77502",
    "sg:province":"TX",
    "sg:tags":[
        "key"
    ],
    "sg:website":"www.availablelocksmithinc.com/Pa...",
    "wof:name":"Available Locksmith",
    "wof:placetype":"venue"
},
  "geometry": {"coordinates":[-95.19995400000001,29.687495],"type":"Point"}
}