{
  "type": "Feature",
  "properties": {
    "iso:country":"US",
    "sg:address":"1904 Hines Blvd",
    "sg:city":"Wichita Falls",
    "sg:classifiers":[
        {
            "category":"Retail",
            "subcategory":"Auto Repair",
            "type":"Services"
        }
    ],
    "sg:phone":"+1 940 763 0049",
    "sg:postcode":"76301",
    "sg:province":"TX",
    "sg:tags":[
        "repairing",
        "tire"
    ],
    "wof:name":"Clifford's Rioservice For Tire",
    "wof:placetype":"venue"
},
  "geometry": {"coordinates":[-98.465535,33.897146],"type":"Point"}
}