{
  "type": "Feature",
  "properties": {
    "iso:country":"US",
    "sg:address":"11910 Swan Dr",
    "sg:city":"Austin",
    "sg:classifiers":[
        {
            "category":"Professional",
            "subcategory":"Computer Services",
            "type":"Services"
        }
    ],
    "sg:phone":"+1 512 331 6929",
    "sg:postcode":"78750",
    "sg:province":"TX",
    "wof:name":"Eagle Computers Inc",
    "wof:placetype":"venue"
},
  "geometry": {"coordinates":[-97.800006,30.449383],"type":"Point"}
}