{
  "type": "Feature",
  "properties": {
    "iso:country":"US",
    "sg:address":"108 Arbor Ave",
    "sg:city":"Del Rio",
    "sg:classifiers":[
        {
            "category":"Retail",
            "subcategory":"Laundry & Dry Cleaning",
            "type":"Services"
        }
    ],
    "sg:phone":"+1 830 775 2680",
    "sg:postcode":"78840",
    "sg:province":"TX",
    "wof:name":"Magic Carpet Cleaning",
    "wof:placetype":"venue"
},
  "geometry": {"coordinates":[-100.89358900000001,29.347129],"type":"Point"}
}