{
  "type": "Feature",
  "properties": {
    "iso:country":"US",
    "sg:address":"4646 Sinclair Rd",
    "sg:city":"San Antonio",
    "sg:classifiers":[
        {
            "category":"Manufacturing",
            "subcategory":"Glass & Minerals",
            "type":"Manufacturing & Wholesale Goods"
        }
    ],
    "sg:phone":"+1 210 648 6100",
    "sg:postcode":"78222",
    "sg:province":"TX",
    "sg:tags":[
        "concrete",
        "brick",
        "prod",
        "block"
    ],
    "sg:website":"www.symons.com",
    "wof:name":"Symons Corp",
    "wof:placetype":"venue"
},
  "geometry": {"coordinates":[-98.403046,29.386308],"type":"Point"}
}