{
  "type": "Feature",
  "properties": {
    "iso:country":"US",
    "sg:address":"1001 S Main St",
    "sg:city":"Euless",
    "sg:classifiers":[
        {
            "category":"Shopping",
            "subcategory":"Gifts & Souvenirs",
            "type":"Retail Goods"
        },
        {
            "category":"Manufacturing",
            "subcategory":"Jewelry",
            "type":"Manufacturing & Wholesale Goods"
        }
    ],
    "sg:phone":"+1 817 545 2745",
    "sg:postcode":"76040",
    "sg:province":"TX",
    "sg:tags":[
        "shop",
        "novelty"
    ],
    "sg:website":"http://www.westernskate.com",
    "wof:name":"Rebecca's",
    "wof:placetype":"venue"
},
  "geometry": {"coordinates":[-97.082306,32.823357],"type":"Point"}
}