{
  "type": "Feature",
  "properties": {
    "iso:country":"US",
    "sg:address":"1311 Ave T",
    "sg:city":"Snyder",
    "sg:classifiers":[
        {
            "category":"Mining & Drilling",
            "type":"Manufacturing & Wholesale Goods"
        }
    ],
    "sg:phone":"+1 325 573 3888",
    "sg:postcode":"79549",
    "sg:province":"TX",
    "sg:tags":[
        "field",
        "oil"
    ],
    "wof:name":"Reneau Casing & Rathole Svc",
    "wof:placetype":"venue"
},
  "geometry": {"coordinates":[-100.92009400000001,32.728741],"type":"Point"}
}