{
  "type": "Feature",
  "properties": {
    "iso:country":"US",
    "sg:address":"7129 Villa Hermosa Dr",
    "sg:city":"El Paso",
    "sg:classifiers":[
        {
            "category":"Building & Trades",
            "subcategory":"Construction",
            "type":"Services"
        }
    ],
    "sg:phone":"+1 915 845 8133",
    "sg:postcode":"79912",
    "sg:province":"TX",
    "sg:tags":[
        "home",
        "builder"
    ],
    "wof:name":"Benavides Construction",
    "wof:placetype":"venue"
},
  "geometry": {"coordinates":[-106.550157,31.852603],"type":"Point"}
}