{
  "type": "Feature",
  "properties": {
    "iso:country":"US",
    "sg:address":"3703 Pine Lawn Dr",
    "sg:city":"Pearland",
    "sg:classifiers":[
        {
            "category":"Wholesale",
            "subcategory":"Machinery & Supplies",
            "type":"Manufacturing & Wholesale Goods"
        }
    ],
    "sg:phone":"+1 281 997 0657",
    "sg:postcode":"77581",
    "sg:province":"TX",
    "sg:tags":[
        "equipment",
        "industrial"
    ],
    "wof:name":"Rotating Equipment Components",
    "wof:placetype":"venue"
},
  "geometry": {"coordinates":[-95.230037,29.540211],"type":"Point"}
}