{
  "type": "Feature",
  "properties": {
    "iso:country":"US",
    "sg:address":"437 Cather St",
    "sg:city":"Houston",
    "sg:classifiers":[
        {
            "category":"Retail",
            "subcategory":"Repair Shop",
            "type":"Services"
        }
    ],
    "sg:phone":"+1 713 697 7070",
    "sg:postcode":"77076",
    "sg:province":"TX",
    "sg:tags":[
        "reupholstery",
        "furniture"
    ],
    "wof:name":"Jones William I",
    "wof:placetype":"venue"
},
  "geometry": {"coordinates":[-95.393204,29.851299],"type":"Point"}
}