{
  "type": "Feature",
  "properties": {
    "iso:country":"US",
    "sg:address":"100 Craig St",
    "sg:city":"Sulphur Springs",
    "sg:classifiers":[
        {
            "category":"Education",
            "subcategory":"School",
            "type":"Public Place"
        }
    ],
    "sg:phone":"+1 903 885 7277",
    "sg:postcode":"75482",
    "sg:province":"TX",
    "wof:name":"Hopkins County Special Ed",
    "wof:placetype":"venue"
},
  "geometry": {"coordinates":[-95.61452300000001,33.133773],"type":"Point"}
}