{
  "type": "Feature",
  "properties": {
    "iso:country":"US",
    "sg:address":"122 Blue Oaks Dr",
    "sg:city":"Cedar Creek",
    "sg:classifiers":[
        {
            "category":"Building & Trades",
            "subcategory":"Construction",
            "type":"Services"
        }
    ],
    "sg:phone":"+1 512 581 3110",
    "sg:postcode":"78612",
    "sg:province":"TX",
    "sg:tags":[
        "contractor"
    ],
    "wof:name":"Margaritos Masonry",
    "wof:placetype":"venue"
},
  "geometry": {"coordinates":[-97.436757,30.112278],"type":"Point"}
}