{
  "type": "Feature",
  "properties": {
    "iso:country":"US",
    "sg:address":"2011 Morgan St",
    "sg:city":"Houston",
    "sg:classifiers":[
        {
            "category":"Restaurant",
            "type":"Food & Drink"
        }
    ],
    "sg:phone":"+1 713 520 1093",
    "sg:postcode":"77006",
    "sg:province":"TX",
    "sg:tags":[
        "eating"
    ],
    "wof:name":"Get Wired Internet Cafe",
    "wof:placetype":"venue"
},
  "geometry": {"coordinates":[-95.38646,29.750299],"type":"Point"}
}