{
  "type": "Feature",
  "properties": {
    "iso:country":"US",
    "sg:address":"19710 Hwy 6",
    "sg:city":"Manvel",
    "sg:classifiers":[
        {
            "category":"Retail",
            "subcategory":"Auto Repair",
            "type":"Services"
        }
    ],
    "sg:phone":"+1 281 489 0154",
    "sg:postcode":"77578",
    "sg:province":"TX",
    "sg:tags":[
        "body",
        "automobile",
        "painting"
    ],
    "wof:name":"Manuel Paint & Body Shop",
    "wof:placetype":"venue"
},
  "geometry": {"coordinates":[-95.35974,29.468341],"type":"Point"}
}