{
  "type": "Feature",
  "properties": {
    "iso:country":"US",
    "sg:address":"3156 E Ledbetter Dr",
    "sg:city":"Dallas",
    "sg:classifiers":[
        {
            "category":"Personal",
            "subcategory":"Beauty Salon",
            "type":"Services"
        }
    ],
    "sg:phone":"+1 214 374 3994",
    "sg:postcode":"75216",
    "sg:province":"TX",
    "wof:name":"R C's Hair Fix",
    "wof:placetype":"venue"
},
  "geometry": {"coordinates":[-96.765353,32.696368],"type":"Point"}
}