{
  "type": "Feature",
  "properties": {
    "iso:country":"US",
    "sg:address":"117 W 11th St",
    "sg:city":"San Juan",
    "sg:classifiers":[
        {
            "category":"Wholesale",
            "subcategory":"Fruits & Vegetables",
            "type":"Manufacturing & Wholesale Goods"
        }
    ],
    "sg:phone":"+1 956 781 7707",
    "sg:postcode":"78589",
    "sg:province":"TX",
    "sg:tags":[
        "produce"
    ],
    "wof:name":"Kay-Dee Produce",
    "wof:placetype":"venue"
},
  "geometry": {"coordinates":[-98.157866,26.183722],"type":"Point"}
}