{
  "type": "Feature",
  "properties": {
    "iso:country":"US",
    "sg:address":"9390 Research Blvd",
    "sg:city":"Austin",
    "sg:classifiers":[
        {
            "category":"Insurance",
            "subcategory":"Insurance Agent",
            "type":"Services"
        }
    ],
    "sg:phone":"+1 512 343 7444",
    "sg:postcode":"78759",
    "sg:province":"TX",
    "sg:tags":[
        "claim"
    ],
    "wof:name":"Matrix Companies",
    "wof:placetype":"venue"
},
  "geometry": {"coordinates":[-97.743165,30.384273],"type":"Point"}
}