{
  "type": "Feature",
  "properties": {
    "iso:country":"US",
    "sg:address":"8817 Stewart Rd",
    "sg:city":"Galveston",
    "sg:classifiers":[
        {
            "category":"Professional",
            "subcategory":"Business Services",
            "type":"Services"
        }
    ],
    "sg:phone":"+1 409 744 3166",
    "sg:postcode":"77554",
    "sg:province":"TX",
    "sg:tags":[
        "personal"
    ],
    "wof:name":"I Can Fix It",
    "wof:placetype":"venue"
},
  "geometry": {"coordinates":[-94.852889,29.254723],"type":"Point"}
}