{
  "type": "Feature",
  "properties": {
    "iso:country":"US",
    "sg:address":"810 E Juanita St",
    "sg:city":"San Diego",
    "sg:classifiers":[
        {
            "category":"Personal",
            "subcategory":"Beauty Salon",
            "type":"Services"
        }
    ],
    "sg:phone":"+1 361 279 7195",
    "sg:postcode":"78384",
    "sg:province":"TX",
    "sg:tags":[
        "shop"
    ],
    "wof:name":"Noemis Hair Salon",
    "wof:placetype":"venue"
},
  "geometry": {"coordinates":[-98.232945,27.756378],"type":"Point"}
}