{
  "type": "Feature",
  "properties": {
    "iso:country":"US",
    "sg:address":"514 Davis St",
    "sg:city":"Grand Prairie",
    "sg:classifiers":[
        {
            "category":"Building & Trades",
            "subcategory":"Cleaning & Sanitation",
            "type":"Services"
        }
    ],
    "sg:phone":"+1 972 263 0600",
    "sg:postcode":"75050",
    "sg:province":"TX",
    "sg:tags":[
        "janitor"
    ],
    "wof:name":"Ideal Cleaning Svc",
    "wof:placetype":"venue"
},
  "geometry": {"coordinates":[-96.99690200000001,32.746173],"type":"Point"}
}