{
  "type": "Feature",
  "properties": {
    "iso:country":"US",
    "sg:address":"2204 Hill St",
    "sg:city":"Huntsville",
    "sg:classifiers":[
        {
            "category":"Building & Trades",
            "subcategory":"Construction",
            "type":"Services"
        }
    ],
    "sg:phone":"+1 936 581 1717",
    "sg:postcode":"77320",
    "sg:province":"TX",
    "sg:tags":[
        "house"
    ],
    "wof:name":"Grigsby & Grigsby Construction",
    "wof:placetype":"venue"
},
  "geometry": {"coordinates":[-95.565963,30.73558],"type":"Point"}
}