{
  "type": "Feature",
  "properties": {
    "iso:country":"US",
    "sg:address":"11123 Mccracken Ln",
    "sg:city":"Cypress",
    "sg:classifiers":[
        {
            "category":"Professional",
            "subcategory":"Lawyer & Legal Services",
            "type":"Services"
        }
    ],
    "sg:phone":"+1 281 664 7777",
    "sg:postcode":"77429",
    "sg:province":"TX",
    "sg:tags":[
        "attorney",
        "practice",
        "plan"
    ],
    "wof:name":"The Warner Law Firm",
    "wof:placetype":"venue"
},
  "geometry": {"coordinates":[-95.58815800000001,29.954457],"type":"Point"}
}