{
  "type": "Feature",
  "properties": {
    "iso:country":"US",
    "sg:address":"231 Wild Senna Dr",
    "sg:city":"Pflugerville",
    "sg:classifiers":[
        {
            "category":"Food & Beverages",
            "subcategory":"Groceries & Convenience Stores",
            "type":"Retail Goods"
        }
    ],
    "sg:phone":"+1 512 252 8051",
    "sg:postcode":"78660",
    "sg:province":"TX",
    "wof:name":"Marias International Food",
    "wof:placetype":"venue"
},
  "geometry": {"coordinates":[-97.655597,30.41971],"type":"Point"}
}