{
  "type": "Feature",
  "properties": {
    "iso:country":"US",
    "sg:address":"404 Woodlawn St",
    "sg:city":"Krum",
    "sg:classifiers":[
        {
            "category":"Shopping",
            "subcategory":"Party Supplies",
            "type":"Retail Goods"
        }
    ],
    "sg:phone":"+1 940 482 7072",
    "sg:postcode":"76249",
    "sg:province":"TX",
    "sg:tags":[
        "delivery",
        "balloons-retail"
    ],
    "wof:name":"Creations By Carolyn",
    "wof:placetype":"venue"
},
  "geometry": {"coordinates":[-97.24046300000001,33.267071],"type":"Point"}
}