{
  "type": "Feature",
  "properties": {
    "iso:country":"US",
    "sg:address":"548 Williams Ranch Rd",
    "sg:city":"Seguin",
    "sg:classifiers":[
        {
            "category":"Shopping",
            "subcategory":"Bicycles & Sporting Goods",
            "type":"Retail Goods"
        }
    ],
    "sg:phone":"+1 830 626 1132",
    "sg:postcode":"78155",
    "sg:province":"TX",
    "sg:tags":[
        "clothing"
    ],
    "wof:name":"Accuracy",
    "wof:placetype":"venue"
},
  "geometry": {"coordinates":[-97.864964,29.620848],"type":"Point"}
}