{
  "type": "Feature",
  "properties": {
    "iso:country":"US",
    "sg:address":"501 E Main St",
    "sg:city":"Little River",
    "sg:classifiers":[
        {
            "category":"Education",
            "subcategory":"School",
            "type":"Public Place"
        }
    ],
    "sg:phone":"+1 254 982 4620",
    "sg:postcode":"76554",
    "sg:province":"TX",
    "wof:name":"Academy Middle School",
    "wof:placetype":"venue"
},
  "geometry": {"coordinates":[-97.347971,30.982696],"type":"Point"}
}