{
  "type": "Feature",
  "properties": {
    "iso:country":"US",
    "sg:address":"1322 Space Park Dr",
    "sg:city":"Houston",
    "sg:classifiers":[
        {
            "category":"Manufacturing",
            "subcategory":"Electronics",
            "type":"Manufacturing & Wholesale Goods"
        }
    ],
    "sg:phone":"+1 281 335 9600",
    "sg:postcode":"77058",
    "sg:province":"TX",
    "sg:tags":[
        "customer",
        "automation"
    ],
    "wof:name":"Alert Technologies Inc",
    "wof:placetype":"venue"
},
  "geometry": {"coordinates":[-95.095012,29.548041],"type":"Point"}
}