{
  "type": "Feature",
  "properties": {
    "iso:country":"US",
    "sg:address":"248 Dodge Pl",
    "sg:city":"Port Arthur",
    "sg:classifiers":[
        {
            "category":"Building & Trades",
            "subcategory":"Landscaping Services",
            "type":"Services"
        }
    ],
    "sg:phone":"+1 409 982 9897",
    "sg:postcode":"77642",
    "sg:province":"TX",
    "wof:name":"Hebert Lawn Maintenance S",
    "wof:placetype":"venue"
},
  "geometry": {"coordinates":[-93.910939,29.896588],"type":"Point"}
}