{
  "type": "Feature",
  "properties": {
    "iso:country":"US",
    "sg:address":"304 State Hwy 101",
    "sg:city":"Chico",
    "sg:classifiers":[
        {
            "category":"Recreation",
            "type":"Entertainment"
        }
    ],
    "sg:phone":"+1 940 644 2136",
    "sg:postcode":"76431",
    "sg:province":"TX",
    "sg:tags":[
        "stable"
    ],
    "wof:name":"Paul Liebel Custom Quality",
    "wof:placetype":"venue"
},
  "geometry": {"coordinates":[-97.79407999999999,33.292989],"type":"Point"}
}