{
  "type": "Feature",
  "properties": {
    "iso:country":"US",
    "sg:address":"2921 Brown Trl",
    "sg:city":"Bedford",
    "sg:classifiers":[
        {
            "category":"Banks & Credit Unions",
            "subcategory":"Investment Brokerage",
            "type":"Services"
        },
        {
            "category":"Professional",
            "subcategory":"Management & Consulting",
            "type":"Services"
        }
    ],
    "sg:phone":"+1 817 577 8686",
    "sg:postcode":"76021",
    "sg:province":"TX",
    "sg:tags":[
        "consultant",
        "planning",
        "financial"
    ],
    "wof:name":"Lee & Mason Financial Services",
    "wof:placetype":"venue"
},
  "geometry": {"coordinates":[-97.16020899999999,32.851682],"type":"Point"}
}