{
  "type": "Feature",
  "properties": {
    "iso:country":"US",
    "sg:address":"5001 Fairway Dr",
    "sg:city":"Alvin",
    "sg:classifiers":[
        {
            "category":"Food & Beverages",
            "subcategory":"Groceries & Convenience Stores",
            "type":"Retail Goods"
        }
    ],
    "sg:phone":"+1 281 331 5010",
    "sg:postcode":"77511",
    "sg:province":"TX",
    "sg:tags":[
        "gas"
    ],
    "wof:name":"Lucky Stop",
    "wof:placetype":"venue"
},
  "geometry": {"coordinates":[-95.23123200000001,29.400926],"type":"Point"}
}