{
  "type": "Feature",
  "properties": {
    "iso:country":"US",
    "sg:address":"9335 Howard Dr",
    "sg:city":"Houston",
    "sg:classifiers":[
        {
            "category":"Professional",
            "subcategory":"Accounting & Tax Preparation",
            "type":"Services"
        }
    ],
    "sg:phone":"+1 713 740 9684",
    "sg:postcode":"77017",
    "sg:province":"TX",
    "sg:tags":[
        "return",
        "filing"
    ],
    "wof:name":"Lozano Income Tax Svc",
    "wof:placetype":"venue"
},
  "geometry": {"coordinates":[-95.24061,29.683673],"type":"Point"}
}