{
  "type": "Feature",
  "properties": {
    "iso:country":"US",
    "sg:address":"2301 6th Ave",
    "sg:city":"Amarillo",
    "sg:classifiers":[
        {
            "category":"Autos & Motor Vehicles",
            "subcategory":"Automobile Sales",
            "type":"Retail Goods"
        }
    ],
    "sg:phone":"+1 806 373 0022",
    "sg:postcode":"79106",
    "sg:province":"TX",
    "sg:tags":[
        "car",
        "used",
        "dealer",
        "dealership"
    ],
    "wof:name":"Walt's Used Cars",
    "wof:placetype":"venue"
},
  "geometry": {"coordinates":[-101.863381,35.211093],"type":"Point"}
}