{
  "type": "Feature",
  "properties": {
    "iso:country":"US",
    "sg:address":"1827 Ash Meadow Dr",
    "sg:city":"Houston",
    "sg:classifiers":[
        {
            "category":"Retail",
            "subcategory":"Animal Services",
            "type":"Services"
        }
    ],
    "sg:phone":"+1 281 580 6692",
    "sg:postcode":"77090",
    "sg:province":"TX",
    "wof:name":"Miniature Schnzer Rscue Huston",
    "wof:placetype":"venue"
},
  "geometry": {"coordinates":[-95.45858800000001,30.013696],"type":"Point"}
}