{
  "type": "Feature",
  "properties": {
    "iso:country":"US",
    "sg:address":"15800 Foothill Farms Loop",
    "sg:city":"Pflugerville",
    "sg:classifiers":[
        {
            "category":"Retail",
            "subcategory":"Emissions Testing",
            "type":"Services"
        },
        {
            "category":"Autos & Motor Vehicles",
            "subcategory":"Auto Supplies",
            "type":"Retail Goods"
        },
        {
            "category":"Retail",
            "subcategory":"Auto Repair",
            "type":"Services"
        }
    ],
    "sg:phone":"+1 512 670 2244",
    "sg:postcode":"78660",
    "sg:province":"TX",
    "sg:tags":[
        "wheel",
        "oil",
        "tire",
        "transmission",
        "automotive",
        "lube",
        "brake",
        "inspection",
        "tune"
    ],
    "sg:website":"http://www.lambstire.com",
    "wof:name":"Lambs Tire & Automotive Repair Centers - Pflugerville",
    "wof:placetype":"venue"
},
  "geometry": {"coordinates":[-97.652519,30.447144],"type":"Point"}
}