{
  "type": "Feature",
  "properties": {
    "iso:country":"US",
    "sg:address":"407 N Spring Ave",
    "sg:city":"Tyler",
    "sg:classifiers":[
        {
            "category":"Building & Trades",
            "subcategory":"Construction",
            "type":"Services"
        }
    ],
    "sg:phone":"+1 903 526 1500",
    "sg:postcode":"75702",
    "sg:province":"TX",
    "sg:tags":[
        "carpenter"
    ],
    "wof:name":"Carpenter Ward Hefner Homes",
    "wof:placetype":"venue"
},
  "geometry": {"coordinates":[-95.299464,32.354481],"type":"Point"}
}