{
  "type": "Feature",
  "properties": {
    "iso:country":"US",
    "sg:address":"3758 S Carrier Pkwy",
    "sg:city":"Grand Prairie",
    "sg:classifiers":[
        {
            "category":"Retail",
            "subcategory":"Repair Shop",
            "type":"Services"
        }
    ],
    "sg:phone":"+1 972 504 6554",
    "sg:postcode":"75052",
    "sg:province":"TX",
    "sg:tags":[
        "equipment",
        "electronic",
        "supply"
    ],
    "wof:name":"Electronic Express",
    "wof:placetype":"venue"
},
  "geometry": {"coordinates":[-97.00727000000001,32.681943],"type":"Point"}
}