{
  "type": "Feature",
  "properties": {
    "iso:country":"US",
    "sg:address":"2924 Story Rd W",
    "sg:city":"Irving",
    "sg:classifiers":[
        {
            "category":"Professional",
            "type":"Services"
        }
    ],
    "sg:phone":"+1 214 441 2429",
    "sg:postcode":"75038",
    "sg:province":"TX",
    "sg:tags":[
        "establishment"
    ],
    "wof:name":"Oh2go",
    "wof:placetype":"venue"
},
  "geometry": {"coordinates":[-96.983242,32.871333],"type":"Point"}
}