{
  "type": "Feature",
  "properties": {
    "iso:country":"US",
    "sg:address":"807 N Main St",
    "sg:city":"Dayton",
    "sg:classifiers":[
        {
            "category":"Social Services",
            "subcategory":"Child Care",
            "type":"Services"
        }
    ],
    "sg:phone":"+1 936 258 3138",
    "sg:postcode":"77535",
    "sg:province":"TX",
    "sg:tags":[
        "kindergarten",
        "academic",
        "school"
    ],
    "wof:name":"A Bright Beginning Pre-K",
    "wof:placetype":"venue"
},
  "geometry": {"coordinates":[-94.89165300000001,30.050573],"type":"Point"}
}