{
  "type": "Feature",
  "properties": {
    "iso:country":"US",
    "sg:address":"710 N Colorado St",
    "sg:city":"Midland",
    "sg:classifiers":[
        {
            "category":"Banks & Credit Unions",
            "subcategory":"Investment Brokerage",
            "type":"Services"
        }
    ],
    "sg:phone":"+1 432 683 3544",
    "sg:postcode":"79701",
    "sg:province":"TX",
    "sg:tags":[
        "security"
    ],
    "wof:name":"Mark G Burns",
    "wof:placetype":"venue"
},
  "geometry": {"coordinates":[-102.076959,32.004685],"type":"Point"}
}