{
  "type": "Feature",
  "properties": {
    "iso:country":"US",
    "sg:address":"1012 Ridgeview St",
    "sg:city":"Mesquite",
    "sg:classifiers":[
        {
            "category":"Building & Trades",
            "subcategory":"Plumbing",
            "type":"Services"
        }
    ],
    "sg:phone":"+1 972 681 8460",
    "sg:postcode":"75149",
    "sg:province":"TX",
    "sg:tags":[
        "conditioning",
        "air",
        "system",
        "contractor"
    ],
    "wof:name":"Airflow Tech Svc",
    "wof:placetype":"venue"
},
  "geometry": {"coordinates":[-96.62173199999999,32.781535],"type":"Point"}
}