{
  "type": "Feature",
  "properties": {
    "iso:country":"US",
    "sg:address":"1740 Texas Ave",
    "sg:city":"Bridge City",
    "sg:classifiers":[
        {
            "category":"Restaurant",
            "type":"Food & Drink"
        }
    ],
    "sg:phone":"+1 409 735 2499",
    "sg:postcode":"77611",
    "sg:province":"TX",
    "sg:tags":[
        "eating"
    ],
    "wof:name":"Mac Daddys Cajun Fried Chicke",
    "wof:placetype":"venue"
},
  "geometry": {"coordinates":[-93.827736,30.03866],"type":"Point"}
}