{
  "type": "Feature",
  "properties": {
    "iso:country":"US",
    "sg:address":"3457 Curry Ln",
    "sg:city":"Abilene",
    "sg:phone":"+1 325 692 8200",
    "sg:postcode":"79606",
    "sg:province":"TX",
    "sg:tags":[
        "gasoline"
    ],
    "wof:name":"Skinnys Wholesale Fuels Inc",
    "wof:placetype":"venue"
},
  "geometry": {"coordinates":[-99.770836,32.406481],"type":"Point"}
}