{
  "type": "Feature",
  "properties": {
    "iso:country":"US",
    "sg:address":"14011 Fm 529 Rd",
    "sg:city":"Houston",
    "sg:classifiers":[
        {
            "category":"Manufacturing",
            "subcategory":"Motor Vehicles & Parts",
            "type":"Manufacturing & Wholesale Goods"
        },
        {
            "category":"Wholesale",
            "subcategory":"Auto Parts",
            "type":"Manufacturing & Wholesale Goods"
        },
        {
            "category":"Retail",
            "subcategory":"Auto Repair",
            "type":"Services"
        }
    ],
    "sg:phone":"+1 713 460 2088",
    "sg:postcode":"77041",
    "sg:province":"TX",
    "sg:tags":[
        "body",
        "shop",
        "supply",
        "automobile",
        "supply-wholesale",
        "equipment",
        "service-equipment",
        "repairing",
        "manufacturer"
    ],
    "wof:name":"Auto Equipment Specialists Inc",
    "wof:placetype":"venue"
},
  "geometry": {"coordinates":[-95.620968,29.879446],"type":"Point"}
}