{
  "type": "Feature",
  "properties": {
    "iso:country":"US",
    "sg:address":"3422 Olton Rd",
    "sg:city":"Plainview",
    "sg:classifiers":[
        {
            "category":"Professional",
            "subcategory":"Management & Consulting",
            "type":"Services"
        }
    ],
    "sg:phone":"+1 806 293 3203",
    "sg:postcode":"79072",
    "sg:province":"TX",
    "sg:tags":[
        "consultant",
        "business"
    ],
    "wof:name":"DCS Sanitation Management",
    "wof:placetype":"venue"
},
  "geometry": {"coordinates":[-101.74905099999999,34.187457],"type":"Point"}
}