{
  "type": "Feature",
  "properties": {
    "iso:country":"US",
    "sg:address":"207 N 3rd St",
    "sg:city":"Mabank",
    "sg:classifiers":[
        {
            "category":"Shopping",
            "subcategory":"Pharmacy",
            "type":"Retail Goods"
        }
    ],
    "sg:phone":"+1 903 887 3711",
    "sg:postcode":"75147",
    "sg:province":"TX",
    "sg:website":"www.gifts-scripts.com",
    "wof:name":"Family Pharmacy & Drug",
    "wof:placetype":"venue"
},
  "geometry": {"coordinates":[-96.100515,32.368103],"type":"Point"}
}