{
  "type": "Feature",
  "properties": {
    "iso:country":"US",
    "sg:address":"5329 Corinthian Bay Dr",
    "sg:city":"Plano",
    "sg:classifiers":[
        {
            "category":"Banks & Credit Unions",
            "subcategory":"Financial Services",
            "type":"Services"
        }
    ],
    "sg:phone":"+1 972 612 0880",
    "sg:postcode":"75093",
    "sg:province":"TX",
    "sg:tags":[
        "investor"
    ],
    "wof:name":"Noaman Investment Company Ltd",
    "wof:placetype":"venue"
},
  "geometry": {"coordinates":[-96.80601799999999,33.037118],"type":"Point"}
}