{
  "type": "Feature",
  "properties": {
    "iso:country":"US",
    "sg:address":"222 S 66th St",
    "sg:city":"Houston",
    "sg:classifiers":[
        {
            "category":"Real Estate",
            "subcategory":"Real Estate Operator",
            "type":"Services"
        }
    ],
    "sg:phone":"+1 713 923 6433",
    "sg:postcode":"77011",
    "sg:province":"TX",
    "sg:tags":[
        "housing",
        "facility"
    ],
    "wof:name":"Eastend Apartments",
    "wof:placetype":"venue"
},
  "geometry": {"coordinates":[-95.31066800000001,29.737205],"type":"Point"}
}