{
  "type": "Feature",
  "properties": {
    "iso:country":"US",
    "sg:address":"7147 Carvel Ln",
    "sg:city":"Houston",
    "sg:classifiers":[
        {
            "category":"Building & Trades",
            "subcategory":"Landscaping Services",
            "type":"Services"
        }
    ],
    "sg:phone":"+1 713 773 3968",
    "sg:postcode":"77074",
    "sg:province":"TX",
    "sg:tags":[
        "landscape"
    ],
    "wof:name":"Aarons Landscape",
    "wof:placetype":"venue"
},
  "geometry": {"coordinates":[-95.51048400000001,29.69693],"type":"Point"}
}