{
  "type": "Feature",
  "properties": {
    "iso:country":"US",
    "sg:address":"1600 Sledge St",
    "sg:city":"Marshall",
    "sg:classifiers":[
        {
            "category":"Building & Trades",
            "subcategory":"Plumbing",
            "type":"Services"
        }
    ],
    "sg:phone":"+1 903 935 9465",
    "sg:postcode":"75670",
    "sg:province":"TX",
    "sg:tags":[
        "contractor"
    ],
    "wof:name":"Marshall Plumbing",
    "wof:placetype":"venue"
},
  "geometry": {"coordinates":[-94.358695,32.559146],"type":"Point"}
}