{
  "type": "Feature",
  "properties": {
    "iso:country":"US",
    "sg:address":"4625 Old Jacksboro Hwy",
    "sg:city":"Wichita Falls",
    "sg:classifiers":[
        {
            "category":"Home & Garden",
            "subcategory":"Building Materials",
            "type":"Retail Goods"
        }
    ],
    "sg:phone":"+1 940 767 7788",
    "sg:postcode":"76302",
    "sg:province":"TX",
    "sg:tags":[
        "type",
        "door"
    ],
    "sg:website":"www.overheaddoor.com",
    "wof:name":"Overhead Door Corp",
    "wof:placetype":"venue"
},
  "geometry": {"coordinates":[-98.494437,33.862812],"type":"Point"}
}