{
  "type": "Feature",
  "properties": {
    "iso:country":"US",
    "sg:address":"204 Brooks Rd",
    "sg:city":"Victoria",
    "sg:classifiers":[
        {
            "category":"Real Estate",
            "subcategory":"Real Estate Agent",
            "type":"Services"
        }
    ],
    "sg:phone":"+1 361 655 0710",
    "sg:postcode":"77904",
    "sg:province":"TX",
    "wof:name":"Robin Luster Real Estate",
    "wof:placetype":"venue"
},
  "geometry": {"coordinates":[-97.005433,28.872693],"type":"Point"}
}