{
  "type": "Feature",
  "properties": {
    "iso:country":"US",
    "sg:address":"701 13th St",
    "sg:city":"Lubbock",
    "sg:classifiers":[
        {
            "category":"Restaurant",
            "type":"Food & Drink"
        }
    ],
    "sg:phone":"+1 806 799 5374",
    "sg:postcode":"79401",
    "sg:province":"TX",
    "sg:tags":[
        "banquet",
        "rooms"
    ],
    "wof:name":"F3 Party House",
    "wof:placetype":"venue"
},
  "geometry": {"coordinates":[-101.843205,33.583538],"type":"Point"}
}