{
  "type": "Feature",
  "properties": {
    "iso:country":"US",
    "sg:address":"8507 Phoenix Ave",
    "sg:city":"Schertz",
    "sg:classifiers":[
        {
            "category":"Recreation",
            "type":"Entertainment"
        }
    ],
    "sg:phone":"+1 210 658 8585",
    "sg:postcode":"78154",
    "sg:province":"TX",
    "sg:tags":[
        "association",
        "softball"
    ],
    "wof:name":"San Antonio Royals",
    "wof:placetype":"venue"
},
  "geometry": {"coordinates":[-98.31775399999999,29.573076],"type":"Point"}
}