{
  "type": "Feature",
  "properties": {
    "iso:country":"US",
    "sg:address":"7005 Priscilla Dr",
    "sg:city":"Austin",
    "sg:classifiers":[
        {
            "category":"Education",
            "subcategory":"Special Training",
            "type":"Public Place"
        }
    ],
    "sg:phone":"+1 512 467 2060",
    "sg:postcode":"78752",
    "sg:province":"TX",
    "sg:tags":[
        "instruction",
        "music"
    ],
    "wof:name":"Traveling Minstrel Music Lessn",
    "wof:placetype":"venue"
},
  "geometry": {"coordinates":[-97.710469,30.333182],"type":"Point"}
}