{
  "type": "Feature",
  "properties": {
    "iso:country":"US",
    "sg:address":"4521 W Lovers Ln",
    "sg:city":"Dallas",
    "sg:classifiers":[
        {
            "category":"Social Services",
            "subcategory":"Child Care",
            "type":"Services"
        }
    ],
    "sg:phone":"+1 214 357 1444",
    "sg:postcode":"75209",
    "sg:province":"TX",
    "sg:tags":[
        "day"
    ],
    "wof:name":"Lovers Lane Daycare",
    "wof:placetype":"venue"
},
  "geometry": {"coordinates":[-96.831715,32.851365],"type":"Point"}
}