{
  "type": "Feature",
  "properties": {
    "iso:country":"US",
    "sg:address":"5435 Worth St",
    "sg:city":"Dallas",
    "sg:classifiers":[
        {
            "category":"Personal",
            "subcategory":"Beauty Salon",
            "type":"Services"
        }
    ],
    "sg:phone":"+1 214 826 8705",
    "sg:postcode":"75214",
    "sg:province":"TX",
    "sg:tags":[
        "shop"
    ],
    "wof:name":"Cut Above Carpentry & Remodeli",
    "wof:placetype":"venue"
},
  "geometry": {"coordinates":[-96.76323600000001,32.80164],"type":"Point"}
}