{
  "type": "Feature",
  "properties": {
    "iso:country":"US",
    "sg:address":"300 Callaghan Rd",
    "sg:city":"San Antonio",
    "sg:classifiers":[
        {
            "category":"Building & Trades",
            "subcategory":"Construction",
            "type":"Services"
        }
    ],
    "sg:phone":"+1 210 438 5820",
    "sg:postcode":"78228",
    "sg:province":"TX",
    "sg:tags":[
        "general",
        "contractor"
    ],
    "wof:name":"W G Yates & Sons",
    "wof:placetype":"venue"
},
  "geometry": {"coordinates":[-98.600291,29.44028],"type":"Point"}
}