{
  "type": "Feature",
  "properties": {
    "iso:country":"US",
    "sg:address":"10002 Kirkaspen Dr",
    "sg:city":"Houston",
    "sg:classifiers":[
        {
            "category":"Professional",
            "subcategory":"Business Services",
            "type":"Services"
        }
    ],
    "sg:phone":"+1 281 481 1297",
    "sg:postcode":"77089",
    "sg:province":"TX",
    "wof:name":"Lucky Old Sun Corp",
    "wof:placetype":"venue"
},
  "geometry": {"coordinates":[-95.24028,29.591902],"type":"Point"}
}