{
  "type": "Feature",
  "properties": {
    "iso:country":"US",
    "sg:address":"3918 Fairmont Pkwy",
    "sg:city":"Pasadena",
    "sg:classifiers":[
        {
            "category":"Bars & Pubs",
            "subcategory":"Nightclub",
            "type":"Food & Drink"
        }
    ],
    "sg:phone":"+1 281 487 0905",
    "sg:postcode":"77504",
    "sg:province":"TX",
    "sg:tags":[
        "nightlife"
    ],
    "wof:name":"Pub the",
    "wof:placetype":"venue"
},
  "geometry": {"coordinates":[-95.185097,29.6507],"type":"Point"}
}