{
  "type": "Feature",
  "properties": {
    "iso:country":"US",
    "sg:address":"3900 Essex Ln Ste 215",
    "sg:city":"Houston",
    "sg:classifiers":[
        {
            "category":"Community Center",
            "type":"Public Place"
        }
    ],
    "sg:phone":"+1 713 622 2345",
    "sg:postcode":"77027",
    "sg:province":"TX",
    "sg:tags":[
        "medical"
    ],
    "sg:website":"www.snoringcenter.com/",
    "wof:name":"The Snoring Center",
    "wof:placetype":"venue"
},
  "geometry": {"coordinates":[-95.44219099999999,29.739931],"type":"Point"}
}