{
  "type": "Feature",
  "properties": {
    "iso:country":"US",
    "sg:address":"3566 Lamar Ave",
    "sg:city":"Paris",
    "sg:classifiers":[
        {
            "category":"Shopping",
            "subcategory":"Clothing, Apparel, & Fashions",
            "type":"Retail Goods"
        }
    ],
    "sg:phone":"+1 903 784 2234",
    "sg:postcode":"75460",
    "sg:province":"TX",
    "wof:name":"Cato",
    "wof:placetype":"venue"
},
  "geometry": {"coordinates":[-95.509874,33.661446],"type":"Point"}
}