{
  "type": "Feature",
  "properties": {
    "iso:country":"US",
    "sg:address":"2120 Myrtle Ave",
    "sg:city":"El Paso",
    "sg:classifiers":[
        {
            "category":"Real Estate",
            "subcategory":"Real Estate Operator",
            "type":"Services"
        }
    ],
    "sg:phone":"+1 915 532 8383",
    "sg:postcode":"79901",
    "sg:province":"TX",
    "sg:tags":[
        "building",
        "electrical",
        "apt"
    ],
    "wof:name":"City Vending Co",
    "wof:placetype":"venue"
},
  "geometry": {"coordinates":[-106.465407,31.771586],"type":"Point"}
}