{
  "type": "Feature",
  "properties": {
    "iso:country":"US",
    "sg:address":"2914 Aftonshire Way",
    "sg:city":"Austin",
    "sg:classifiers":[
        {
            "category":"Manufacturing",
            "subcategory":"Chemicals & Compounds",
            "type":"Manufacturing & Wholesale Goods"
        }
    ],
    "sg:phone":"+1 512 291 0440",
    "sg:postcode":"78748",
    "sg:province":"TX",
    "sg:tags":[
        "mfg"
    ],
    "wof:name":"Ebert Enterprises",
    "wof:placetype":"venue"
},
  "geometry": {"coordinates":[-97.839737,30.181727],"type":"Point"}
}