{
  "type": "Feature",
  "properties": {
    "iso:country":"US",
    "sg:address":"808 N 17th St",
    "sg:city":"Lamesa",
    "sg:classifiers":[
        {
            "category":"Professional",
            "type":"Services"
        }
    ],
    "sg:phone":"+1 806 872 2709",
    "sg:postcode":"79331",
    "sg:province":"TX",
    "wof:name":"Finebuysonline Co",
    "wof:placetype":"venue"
},
  "geometry": {"coordinates":[-101.96177400000001,32.747415],"type":"Point"}
}