{
  "type": "Feature",
  "properties": {
    "iso:country":"US",
    "sg:address":"5315 Mangum Rd",
    "sg:city":"Houston",
    "sg:classifiers":[
        {
            "category":"Retail",
            "subcategory":"Auto Repair",
            "type":"Services"
        }
    ],
    "sg:phone":"+1 713 812 7800",
    "sg:postcode":"77091",
    "sg:province":"TX",
    "wof:name":"C C Automotive Service",
    "wof:placetype":"venue"
},
  "geometry": {"coordinates":[-95.46320299999999,29.8424],"type":"Point"}
}