{
  "type": "Feature",
  "properties": {
    "iso:country":"US",
    "sg:address":"615 S Grandview Ave",
    "sg:city":"Odessa",
    "sg:classifiers":[
        {
            "category":"Wholesale",
            "subcategory":"Machinery & Supplies",
            "type":"Manufacturing & Wholesale Goods"
        }
    ],
    "sg:phone":"+1 432 333 3636",
    "sg:postcode":"79761",
    "sg:province":"TX",
    "sg:tags":[
        "industrial",
        "electronic"
    ],
    "wof:name":"CAM Bar",
    "wof:placetype":"venue"
},
  "geometry": {"coordinates":[-102.34098400000001,31.845409],"type":"Point"}
}