{
  "type": "Feature",
  "properties": {
    "iso:country":"US",
    "sg:address":"200 S Westgate Way",
    "sg:city":"Wylie",
    "sg:classifiers":[
        {
            "category":"Fast Food",
            "type":"Food & Drink"
        },
        {
            "category":"Restaurant",
            "type":"Food & Drink"
        }
    ],
    "sg:phone":"+1 972 442 7916",
    "sg:postcode":"75098",
    "sg:province":"TX",
    "sg:tags":[
        "hamburger",
        "hot",
        "dog",
        "american",
        "take",
        "chicken"
    ],
    "wof:name":"Mcdonald's",
    "wof:placetype":"venue"
},
  "geometry": {"coordinates":[-96.551582,33.01442],"type":"Point"}
}