{
  "type": "Feature",
  "properties": {
    "iso:country":"US",
    "sg:address":"9240 Bryant St",
    "sg:city":"Houston",
    "sg:classifiers":[
        {
            "category":"Shopping",
            "subcategory":"Bicycles & Sporting Goods",
            "type":"Retail Goods"
        }
    ],
    "sg:phone":"+1 713 980 9834",
    "sg:postcode":"77075",
    "sg:province":"TX",
    "sg:tags":[
        "bike"
    ],
    "wof:name":"Galveston County Cycles",
    "wof:placetype":"venue"
},
  "geometry": {"coordinates":[-95.252394,29.647757],"type":"Point"}
}