{
  "type": "Feature",
  "properties": {
    "iso:country":"US",
    "sg:address":"6125 Sky Rd",
    "sg:city":"Joshua",
    "sg:classifiers":[
        {
            "category":"Manufacturing",
            "subcategory":"Tools & Machinery",
            "type":"Manufacturing & Wholesale Goods"
        }
    ],
    "sg:phone":"+1 817 309 3302",
    "sg:postcode":"76058",
    "sg:province":"TX",
    "sg:tags":[
        "machine",
        "parts",
        "mfg"
    ],
    "wof:name":"Brady Machine Inc",
    "wof:placetype":"venue"
},
  "geometry": {"coordinates":[-97.48462000000001,32.526838],"type":"Point"}
}