{
  "type": "Feature",
  "properties": {
    "iso:country":"US",
    "sg:address":"225 Gibson Ln",
    "sg:city":"Valley View",
    "sg:classifiers":[
        {
            "category":"Wholesale",
            "subcategory":"Construction Materials",
            "type":"Manufacturing & Wholesale Goods"
        },
        {
            "category":"Manufacturing",
            "subcategory":"Building Materials",
            "type":"Manufacturing & Wholesale Goods"
        }
    ],
    "sg:phone":"+1 940 726 5016",
    "sg:postcode":"76272",
    "sg:province":"TX",
    "sg:tags":[
        "lumber",
        "plywood"
    ],
    "wof:name":"Westwood Millwork Inc",
    "wof:placetype":"venue"
},
  "geometry": {"coordinates":[-97.16045800000001,33.488182],"type":"Point"}
}