{
  "type": "Feature",
  "properties": {
    "iso:country":"US",
    "sg:address":"211 S Main St",
    "sg:city":"Mcallen",
    "sg:classifiers":[
        {
            "category":"Shopping",
            "subcategory":"Jewelry",
            "type":"Retail Goods"
        },
        {
            "category":"Manufacturing",
            "subcategory":"Jewelry",
            "type":"Manufacturing & Wholesale Goods"
        }
    ],
    "sg:phone":"+1 956 682 0000",
    "sg:postcode":"78501",
    "sg:province":"TX",
    "sg:tags":[
        "designer",
        "jeweler"
    ],
    "wof:name":"Meena Bazaar Jewelry & Fragances",
    "wof:placetype":"venue"
},
  "geometry": {"coordinates":[-98.23475000000001,26.202303],"type":"Point"}
}