{
  "type": "Feature",
  "properties": {
    "iso:country":"US",
    "sg:address":"6350 Skyline Dr",
    "sg:city":"Houston",
    "sg:classifiers":[
        {
            "category":"Building & Trades",
            "subcategory":"Landscaping Services",
            "type":"Services"
        }
    ],
    "sg:phone":"+1 713 266 8585",
    "sg:postcode":"77057",
    "sg:province":"TX",
    "sg:tags":[
        "landscape",
        "contractor"
    ],
    "wof:name":"Dawson-Estes Inc",
    "wof:placetype":"venue"
},
  "geometry": {"coordinates":[-95.494872,29.728262],"type":"Point"}
}