{
  "type": "Feature",
  "properties": {
    "iso:country":"US",
    "sg:address":"3917 Up River Rd",
    "sg:city":"Corpus Christi",
    "sg:classifiers":[
        {
            "category":"Retail",
            "subcategory":"Laundry & Dry Cleaning",
            "type":"Services"
        }
    ],
    "sg:phone":"+1 361 884 8431",
    "sg:postcode":"78408",
    "sg:province":"TX",
    "sg:tags":[
        "cleaners"
    ],
    "wof:name":"Peerless Cleaners",
    "wof:placetype":"venue"
},
  "geometry": {"coordinates":[-97.437466,27.799064],"type":"Point"}
}