{
  "type": "Feature",
  "properties": {
    "iso:country":"US",
    "sg:address":"2100 Hamilton St",
    "sg:city":"Houston",
    "sg:classifiers":[
        {
            "category":"Autos & Motor Vehicles",
            "subcategory":"Fuel & Gas Station",
            "type":"Retail Goods"
        }
    ],
    "sg:phone":"+1 713 571 0480",
    "sg:postcode":"77003",
    "sg:province":"TX",
    "sg:tags":[
        "gasoline"
    ],
    "sg:website":"www.citgo.com",
    "wof:name":"Downtown Citgo",
    "wof:placetype":"venue"
},
  "geometry": {"coordinates":[-95.364098,29.743799],"type":"Point"}
}