{
  "type": "Feature",
  "properties": {
    "iso:country":"US",
    "sg:address":"1236 Eidson Rd",
    "sg:city":"Eagle Pass",
    "sg:classifiers":[
        {
            "category":"Food & Beverages",
            "subcategory":"Meat & Fish",
            "type":"Retail Goods"
        }
    ],
    "sg:phone":"+1 830 773 6691",
    "sg:postcode":"78852",
    "sg:province":"TX",
    "wof:name":"Rogelio's Meat Market",
    "wof:placetype":"venue"
},
  "geometry": {"coordinates":[-100.487835,28.690694],"type":"Point"}
}