{
  "type": "Feature",
  "properties": {
    "iso:country":"US",
    "sg:address":"3011 Harlan Dr",
    "sg:city":"Mesquite",
    "sg:classifiers":[
        {
            "category":"Retail",
            "subcategory":"Repair Shop",
            "type":"Services"
        }
    ],
    "sg:phone":"+1 972 270 7008",
    "sg:postcode":"75150",
    "sg:province":"TX",
    "wof:name":"Bret Davis Inc",
    "wof:placetype":"venue"
},
  "geometry": {"coordinates":[-96.656312,32.803657],"type":"Point"}
}