{
  "type": "Feature",
  "properties": {
    "iso:country":"US",
    "sg:address":"2642 Main St",
    "sg:city":"Dallas",
    "sg:classifiers":[
        {
            "category":"Professional",
            "type":"Services"
        }
    ],
    "sg:phone":"+1 214 744 2642",
    "sg:postcode":"75226",
    "sg:province":"TX",
    "sg:tags":[
        "establishment"
    ],
    "wof:name":"Ground Zero",
    "wof:placetype":"venue"
},
  "geometry": {"coordinates":[-96.784972,32.783706],"type":"Point"}
}