{
  "type": "Feature",
  "properties": {
    "iso:country":"US",
    "sg:address":"13050 Northwest Fwy",
    "sg:city":"Houston",
    "sg:classifiers":[
        {
            "category":"Restaurant",
            "type":"Food & Drink"
        }
    ],
    "sg:menulink":"http://www.allmenus.com/tx/houston/49379-chilis/menu/",
    "sg:phone":"+1 713 690 3800",
    "sg:postcode":"77040",
    "sg:province":"TX",
    "sg:tags":[
        "burger",
        "american",
        "sandwich",
        "tex-mex",
        "soup"
    ],
    "wof:name":"Chili's",
    "wof:placetype":"venue"
},
  "geometry": {"coordinates":[-95.49948500000001,29.845927],"type":"Point"}
}