{
  "type": "Feature",
  "properties": {
    "iso:country":"US",
    "sg:address":"1431 E Houston St",
    "sg:city":"San Antonio",
    "sg:classifiers":[
        {
            "category":"Restaurant",
            "type":"Food & Drink"
        }
    ],
    "sg:phone":"+1 210 271 0557",
    "sg:postcode":"78202",
    "sg:province":"TX",
    "wof:name":"J & I Cafe",
    "wof:placetype":"venue"
},
  "geometry": {"coordinates":[-98.47512500000001,29.425132],"type":"Point"}
}