{
  "type": "Feature",
  "properties": {
    "iso:country":"US",
    "sg:address":"4111 Fannin St",
    "sg:city":"Houston",
    "sg:classifiers":[
        {
            "category":"Autos & Motor Vehicles",
            "subcategory":"Auto Supplies",
            "type":"Retail Goods"
        },
        {
            "category":"Retail",
            "subcategory":"Auto Repair",
            "type":"Services"
        }
    ],
    "sg:phone":"+1 713 527 2295",
    "sg:postcode":"77004",
    "sg:province":"TX",
    "sg:tags":[
        "tire"
    ],
    "wof:name":"Sears Roebuck and Co",
    "wof:placetype":"venue"
},
  "geometry": {"coordinates":[-95.38069900000001,29.735201],"type":"Point"}
}