{
  "type": "Feature",
  "properties": {
    "iso:country":"US",
    "sg:address":"1607 McCormick St",
    "sg:city":"Denton",
    "sg:classifiers":[
        {
            "category":"Real Estate",
            "subcategory":"Real Estate Agent",
            "type":"Services"
        }
    ],
    "sg:phone":"+1 940 566 8730",
    "sg:postcode":"76205",
    "sg:province":"TX",
    "wof:name":"Yarbrough Realty",
    "wof:placetype":"venue"
},
  "geometry": {"coordinates":[-97.147333,33.197696],"type":"Point"}
}