{
  "type": "Feature",
  "properties": {
    "iso:country":"US",
    "sg:address":"202 N Milam St",
    "sg:city":"Fredericksburg",
    "sg:classifiers":[
        {
            "category":"Shopping",
            "subcategory":"Clothing, Apparel, & Fashions",
            "type":"Retail Goods"
        }
    ],
    "sg:phone":"+1 830 997 3113",
    "sg:postcode":"78624",
    "sg:province":"TX",
    "wof:name":"Madlyn's Inc",
    "wof:placetype":"venue"
},
  "geometry": {"coordinates":[-98.875421,30.280919],"type":"Point"}
}