{
  "type": "Feature",
  "properties": {
    "iso:country":"US",
    "sg:address":"2821 Cullen St",
    "sg:city":"Fort Worth",
    "sg:classifiers":[
        {
            "category":"Manufacturing",
            "subcategory":"Printing",
            "type":"Manufacturing & Wholesale Goods"
        }
    ],
    "sg:phone":"+1 817 332 1918",
    "sg:postcode":"76107",
    "sg:province":"TX",
    "sg:tags":[
        "printer"
    ],
    "wof:name":"Hart Intercivic",
    "wof:placetype":"venue"
},
  "geometry": {"coordinates":[-97.358473,32.761896],"type":"Point"}
}