{
  "type": "Feature",
  "properties": {
    "iso:country":"US",
    "sg:address":"1820 N Brazosport Blvd",
    "sg:city":"Freeport",
    "sg:classifiers":[
        {
            "category":"Autos & Motor Vehicles",
            "subcategory":"Automobile Sales",
            "type":"Retail Goods"
        }
    ],
    "sg:phone":"+1 979 233 6344",
    "sg:postcode":"77541",
    "sg:province":"TX",
    "sg:tags":[
        "used"
    ],
    "wof:name":"Gulf Motors",
    "wof:placetype":"venue"
},
  "geometry": {"coordinates":[-95.37482799999999,28.978783],"type":"Point"}
}