{
  "type": "Feature",
  "properties": {
    "iso:country":"US",
    "sg:address":"440 W 2nd St",
    "sg:city":"Austin",
    "sg:classifiers":[
        {
            "category":"Bars & Pubs",
            "type":"Food & Drink"
        },
        {
            "category":"Bars & Pubs",
            "subcategory":"Wine Bar",
            "type":"Food & Drink"
        }
    ],
    "sg:phone":"+1 512 236 8020",
    "sg:postcode":"78701",
    "sg:province":"TX",
    "sg:tags":[
        "tapa"
    ],
    "sg:website":"www.malagaaustin.com",
    "wof:name":"M?laga Tapas & Bar",
    "wof:placetype":"venue"
},
  "geometry": {"coordinates":[-97.74829200000001,30.265604],"type":"Point"}
}