{
  "type": "Feature",
  "properties": {
    "iso:country":"US",
    "sg:address":"1225 W Trinity Mills Rd",
    "sg:city":"Carrollton",
    "sg:classifiers":[
        {
            "category":"Retail",
            "subcategory":"Storage",
            "type":"Services"
        }
    ],
    "sg:phone":"+1 972 242 9403",
    "sg:postcode":"75006",
    "sg:province":"TX",
    "sg:tags":[
        "self"
    ],
    "wof:name":"Public Storage",
    "wof:placetype":"venue"
},
  "geometry": {"coordinates":[-96.91619900000001,32.9827],"type":"Point"}
}