{
  "type": "Feature",
  "properties": {
    "iso:country":"US",
    "sg:address":"2769 N Frankford Ave",
    "sg:city":"Lubbock",
    "sg:classifiers":[
        {
            "category":"Recreation",
            "subcategory":"Amusement Park",
            "type":"Entertainment"
        }
    ],
    "sg:phone":"+1 806 797 7223",
    "sg:postcode":"79416",
    "sg:province":"TX",
    "wof:name":"Dave's Need For Speed",
    "wof:placetype":"venue"
},
  "geometry": {"coordinates":[-101.939927,33.626201],"type":"Point"}
}