{
  "type": "Feature",
  "properties": {
    "iso:country":"US",
    "sg:address":"1143 S Cedar Ridge Dr",
    "sg:city":"Duncanville",
    "sg:classifiers":[
        {
            "category":"Autos & Motor Vehicles",
            "subcategory":"Auto Supplies",
            "type":"Retail Goods"
        },
        {
            "category":"Retail",
            "subcategory":"Auto Repair",
            "type":"Services"
        }
    ],
    "sg:phone":"+1 972 298 9942",
    "sg:postcode":"75137",
    "sg:province":"TX",
    "sg:tags":[
        "body",
        "shop",
        "tire",
        "automobile",
        "painting",
        "repairing"
    ],
    "sg:website":"www.calibercollision.com",
    "wof:name":"Caliber Collision Center",
    "wof:placetype":"venue"
},
  "geometry": {"coordinates":[-96.924944,32.638601],"type":"Point"}
}