{
  "type": "Feature",
  "properties": {
    "iso:country":"US",
    "sg:address":"4040 Crow Rd",
    "sg:city":"Beaumont",
    "sg:classifiers":[
        {
            "category":"Professional",
            "subcategory":"Research",
            "type":"Services"
        }
    ],
    "sg:phone":"+1 409 899 5856",
    "sg:postcode":"77706",
    "sg:province":"TX",
    "sg:tags":[
        "organization",
        "noncommercial"
    ],
    "wof:name":"Concern Foundation",
    "wof:placetype":"venue"
},
  "geometry": {"coordinates":[-94.155871,30.119303],"type":"Point"}
}