{
  "type": "Feature",
  "properties": {
    "iso:country":"US",
    "sg:address":"605 E Dewey Pl",
    "sg:city":"San Antonio",
    "sg:classifiers":[
        {
            "category":"Professional",
            "subcategory":"Business Services",
            "type":"Services"
        }
    ],
    "sg:phone":"+1 210 737 2400",
    "sg:postcode":"78212",
    "sg:province":"TX",
    "sg:tags":[
        "interior",
        "consultant",
        "design",
        "architectural"
    ],
    "wof:name":"G2",
    "wof:placetype":"venue"
},
  "geometry": {"coordinates":[-98.486665,29.447109],"type":"Point"}
}