{
  "type": "Feature",
  "properties": {
    "iso:country":"US",
    "sg:address":"4144 N Central Expy",
    "sg:city":"Dallas",
    "sg:classifiers":[
        {
            "category":"Food & Beverages",
            "subcategory":"Groceries & Convenience Stores",
            "type":"Retail Goods"
        }
    ],
    "sg:phone":"+1 214 826 9180",
    "sg:postcode":"75204",
    "sg:province":"TX",
    "sg:tags":[
        "market"
    ],
    "wof:name":"One Market",
    "wof:placetype":"venue"
},
  "geometry": {"coordinates":[-96.789068,32.815438],"type":"Point"}
}