{
  "type": "Feature",
  "properties": {
    "iso:country":"US",
    "sg:address":"2625 Miller Ranch Rd",
    "sg:city":"Pearland",
    "sg:classifiers":[
        {
            "category":"Manufacturing",
            "subcategory":"Rubber & Plastics",
            "type":"Manufacturing & Wholesale Goods"
        }
    ],
    "sg:phone":"+1 713 436 1600",
    "sg:postcode":"77584",
    "sg:province":"TX",
    "sg:tags":[
        "injection",
        "mold",
        "mfg"
    ],
    "wof:name":"Matrix Manufacturing Inc",
    "wof:placetype":"venue"
},
  "geometry": {"coordinates":[-95.373245,29.561288],"type":"Point"}
}