{
  "type": "Feature",
  "properties": {
    "iso:country":"US",
    "sg:address":"348 Parkview Dr",
    "sg:city":"Hurst",
    "sg:classifiers":[
        {
            "category":"Shopping",
            "subcategory":"Used Merchandise",
            "type":"Retail Goods"
        },
        {
            "category":"Retail",
            "subcategory":"Repair Shop",
            "type":"Services"
        }
    ],
    "sg:phone":"+1 817 282 6629",
    "sg:postcode":"76053",
    "sg:province":"TX",
    "sg:tags":[
        "antique",
        "restoring"
    ],
    "wof:name":"Kenny's Antiques & Clock Rpr",
    "wof:placetype":"venue"
},
  "geometry": {"coordinates":[-97.15433299999999,32.813092],"type":"Point"}
}