{
  "type": "Feature",
  "properties": {
    "iso:country":"US",
    "sg:address":"107 Ranch Rd 620 S",
    "sg:city":"Lakeway",
    "sg:classifiers":[
        {
            "category":"Restaurant",
            "type":"Food & Drink"
        }
    ],
    "sg:phone":"+1 512 266 9328",
    "sg:postcode":"78734",
    "sg:province":"TX",
    "wof:name":"China Pacific Restaurant",
    "wof:placetype":"venue"
},
  "geometry": {"coordinates":[-97.952327,30.363498],"type":"Point"}
}