{
  "type": "Feature",
  "properties": {
    "iso:country":"US",
    "sg:address":"1004 W Whitestone Blvd",
    "sg:city":"Cedar Park",
    "sg:classifiers":[
        {
            "category":"Organizations",
            "subcategory":"Religious Organization",
            "type":"Services"
        }
    ],
    "sg:phone":"+1 512 258 1362",
    "sg:postcode":"78613",
    "sg:province":"TX",
    "sg:tags":[
        "church"
    ],
    "wof:name":"Whitestone Assembly Of God",
    "wof:placetype":"venue"
},
  "geometry": {"coordinates":[-97.84135000000001,30.517197],"type":"Point"}
}