{
  "type": "Feature",
  "properties": {
    "iso:country":"US",
    "sg:address":"10523 Harry Hines Blvd",
    "sg:city":"Dallas",
    "sg:classifiers":[
        {
            "category":"Bars & Pubs",
            "type":"Food & Drink"
        }
    ],
    "sg:phone":"+1 214 350 4046",
    "sg:postcode":"75220",
    "sg:province":"TX",
    "sg:tags":[
        "club",
        "bar",
        "night"
    ],
    "wof:name":"El Cristal",
    "wof:placetype":"venue"
},
  "geometry": {"coordinates":[-96.882255,32.868104],"type":"Point"}
}