{
  "type": "Feature",
  "properties": {
    "iso:country":"US",
    "sg:address":"400 Laurel St",
    "sg:city":"Texarkana",
    "sg:classifiers":[
        {
            "category":"Government",
            "subcategory":"Office",
            "type":"Public Place"
        }
    ],
    "sg:phone":"+1 870 774 1502",
    "sg:postcode":"71854",
    "sg:province":"TX",
    "sg:tags":[
        "county",
        "taxation"
    ],
    "wof:name":"Miller County Tax Assessor",
    "wof:placetype":"venue"
},
  "geometry": {"coordinates":[-94.039322,33.42664],"type":"Point"}
}