{
  "type": "Feature",
  "properties": {
    "iso:country":"US",
    "sg:address":"3616 Regent Dr",
    "sg:city":"Dallas",
    "sg:classifiers":[
        {
            "category":"Professional",
            "subcategory":"Art Services",
            "type":"Services"
        }
    ],
    "sg:phone":"+1 214 357 1272",
    "sg:postcode":"75229",
    "sg:province":"TX",
    "sg:tags":[
        "commercial",
        "design"
    ],
    "wof:name":"Overton Design",
    "wof:placetype":"venue"
},
  "geometry": {"coordinates":[-96.859837,32.894065],"type":"Point"}
}