{
  "type": "Feature",
  "properties": {
    "iso:country":"US",
    "sg:address":"2506 Meadows Ln",
    "sg:city":"Sherman",
    "sg:classifiers":[
        {
            "category":"Building & Trades",
            "subcategory":"Landscaping Services",
            "type":"Services"
        },
        {
            "category":"Wholesale",
            "subcategory":"Machinery & Supplies",
            "type":"Manufacturing & Wholesale Goods"
        }
    ],
    "sg:phone":"+1 903 868 0939",
    "sg:postcode":"75092",
    "sg:province":"TX",
    "sg:tags":[
        "equipment",
        "lawn",
        "irrigation",
        "system"
    ],
    "wof:name":"Cutting Edge Landscape & Irrigation",
    "wof:placetype":"venue"
},
  "geometry": {"coordinates":[-96.632677,33.659542],"type":"Point"}
}