{
  "type": "Feature",
  "properties": {
    "iso:country":"US",
    "sg:address":"1625 FM 1948 N",
    "sg:city":"Burton",
    "sg:classifiers":[
        {
            "category":"Professional",
            "type":"Services"
        }
    ],
    "sg:phone":"+1 979 289 3481",
    "sg:postcode":"77835",
    "sg:province":"TX",
    "sg:tags":[
        "establishment"
    ],
    "wof:name":"Meadowland Management Inc",
    "wof:placetype":"venue"
},
  "geometry": {"coordinates":[-96.56854199999999,30.205503],"type":"Point"}
}