{
  "type": "Feature",
  "properties": {
    "iso:country":"US",
    "sg:address":"235 Cedarhurst Dr",
    "sg:city":"San Antonio",
    "sg:classifiers":[
        {
            "category":"Organizations",
            "subcategory":"Membership Organization",
            "type":"Services"
        },
        {
            "category":"Organizations",
            "subcategory":"Community Association",
            "type":"Services"
        }
    ],
    "sg:phone":"+1 210 673 3731",
    "sg:postcode":"78227",
    "sg:province":"TX",
    "sg:tags":[
        "fraternal"
    ],
    "wof:name":"Valley HI Lodge 1407",
    "wof:placetype":"venue"
},
  "geometry": {"coordinates":[-98.645988,29.392775],"type":"Point"}
}