{
  "type": "Feature",
  "properties": {
    "iso:country":"US",
    "sg:address":"601 FM 156",
    "sg:city":"Ponder",
    "sg:classifiers":[
        {
            "category":"Personal",
            "subcategory":"Beauty Salon",
            "type":"Services"
        }
    ],
    "sg:phone":"+1 940 479 0500",
    "sg:postcode":"76259",
    "sg:province":"TX",
    "wof:name":"Kelly Futch Hair Stylists",
    "wof:placetype":"venue"
},
  "geometry": {"coordinates":[-97.227385,33.279666],"type":"Point"}
}