{
  "type": "Feature",
  "properties": {
    "iso:country":"US",
    "sg:address":"738 Barchester Dr",
    "sg:city":"San Antonio",
    "sg:classifiers":[
        {
            "category":"Real Estate",
            "subcategory":"Surveying",
            "type":"Services"
        }
    ],
    "sg:phone":"+1 210 308 5540",
    "sg:postcode":"78216",
    "sg:province":"TX",
    "sg:tags":[
        "engineering"
    ],
    "wof:name":"Urban Design Group",
    "wof:placetype":"venue"
},
  "geometry": {"coordinates":[-98.506389,29.510577],"type":"Point"}
}