{
  "type": "Feature",
  "properties": {
    "iso:country":"US",
    "sg:address":"2022 N Broadway St",
    "sg:city":"Ballinger",
    "sg:classifiers":[
        {
            "category":"Shopping",
            "type":"Retail Goods"
        }
    ],
    "sg:phone":"+1 325 365 9096",
    "sg:postcode":"76821",
    "sg:province":"TX",
    "sg:tags":[
        "mart",
        "machinery"
    ],
    "wof:name":"Ballinger Lonestar Parts Corp",
    "wof:placetype":"venue"
},
  "geometry": {"coordinates":[-99.96625400000001,31.74996],"type":"Point"}
}