{
  "type": "Feature",
  "properties": {
    "iso:country":"US",
    "sg:address":"3701 W Alabama St Ste 210",
    "sg:city":"Houston",
    "sg:phone":"+1 832 460 1724",
    "sg:postcode":"77027",
    "sg:province":"TX",
    "sg:website":"http://houston.citysearch.com/profile/external/604214832/houston_tx/soma_solutions.html?publisher=yellowpages&reference_id=1&placement=ypwebsitemip",
    "wof:name":"Soma Solutions",
    "wof:placetype":"venue"
},
  "geometry": {"coordinates":[-95.436607,29.738279],"type":"Point"}
}