{
  "type": "Feature",
  "properties": {
    "iso:country":"US",
    "sg:address":"115 E Bagdad Ave",
    "sg:city":"Round Rock",
    "sg:classifiers":[
        {
            "category":"Wholesale",
            "subcategory":"Construction Materials",
            "type":"Manufacturing & Wholesale Goods"
        }
    ],
    "sg:phone":"+1 512 310 1240",
    "sg:postcode":"78664",
    "sg:province":"TX",
    "wof:name":"Builders Gypsum",
    "wof:placetype":"venue"
},
  "geometry": {"coordinates":[-97.676332,30.508224],"type":"Point"}
}