{
  "type": "Feature",
  "properties": {
    "iso:country":"US",
    "sg:address":"301 W 2nd St",
    "sg:city":"Odessa",
    "sg:classifiers":[
        {
            "category":"Manufacturing",
            "subcategory":"Chemicals & Compounds",
            "type":"Manufacturing & Wholesale Goods"
        },
        {
            "category":"Wholesale",
            "subcategory":"Machinery & Supplies",
            "type":"Manufacturing & Wholesale Goods"
        },
        {
            "category":"Retail",
            "subcategory":"Repair Shop",
            "type":"Services"
        }
    ],
    "sg:phone":"+1 432 332 9753",
    "sg:postcode":"79761",
    "sg:province":"TX",
    "sg:tags":[
        "equipment",
        "pump",
        "valve",
        "pumps-service",
        "lubricating"
    ],
    "sg:website":"http://www.up-s.com",
    "wof:name":"U P & S Inc",
    "wof:placetype":"venue"
},
  "geometry": {"coordinates":[-102.369804,31.844604],"type":"Point"}
}