{
  "type": "Feature",
  "properties": {
    "iso:country":"US",
    "sg:address":"5101 Norwood Rd",
    "sg:city":"Dallas",
    "sg:classifiers":[
        {
            "category":"Manufacturing",
            "subcategory":"Printing",
            "type":"Manufacturing & Wholesale Goods"
        }
    ],
    "sg:phone":"+1 972 263 0845",
    "sg:postcode":"75247",
    "sg:province":"TX",
    "sg:tags":[
        "commercial"
    ],
    "wof:name":"Econowebb Inc",
    "wof:placetype":"venue"
},
  "geometry": {"coordinates":[-96.88965399999999,32.81254],"type":"Point"}
}