{
  "type": "Feature",
  "properties": {
    "iso:country":"US",
    "sg:address":"201 N Main St",
    "sg:city":"Highlands",
    "sg:classifiers":[
        {
            "category":"Freight",
            "type":"Transportation"
        }
    ],
    "sg:phone":"+1 281 426 5050",
    "sg:postcode":"77562",
    "sg:province":"TX",
    "sg:tags":[
        "delivery"
    ],
    "wof:name":"Jimco Delivery Inc",
    "wof:placetype":"venue"
},
  "geometry": {"coordinates":[-95.05713299999999,29.817266],"type":"Point"}
}