{
  "type": "Feature",
  "properties": {
    "iso:country":"US",
    "sg:address":"224 Hwy 332 W",
    "sg:city":"Lake Jackson",
    "sg:classifiers":[
        {
            "category":"Shopping",
            "subcategory":"Shoes",
            "type":"Retail Goods"
        }
    ],
    "sg:phone":"+1 979 297 3881",
    "sg:postcode":"77566",
    "sg:province":"TX",
    "wof:name":"Payless Shoe Source",
    "wof:placetype":"venue"
},
  "geometry": {"coordinates":[-95.46884900000001,29.047671],"type":"Point"}
}