{
  "type": "Feature",
  "properties": {
    "iso:country":"US",
    "sg:address":"5515 Robert Alva Ave",
    "sg:city":"El Paso",
    "sg:classifiers":[
        {
            "category":"Education",
            "subcategory":"Library",
            "type":"Public Place"
        }
    ],
    "sg:phone":"+1 915 772 0501",
    "sg:postcode":"79905",
    "sg:province":"TX",
    "wof:name":"El Paso City Public Library",
    "wof:placetype":"venue"
},
  "geometry": {"coordinates":[-106.42660100000001,31.763661],"type":"Point"}
}