{
  "type": "Feature",
  "properties": {
    "iso:country":"US",
    "sg:address":"1515 Verde Ave",
    "sg:city":"Odessa",
    "sg:classifiers":[
        {
            "category":"Building & Trades",
            "subcategory":"Pest Control",
            "type":"Services"
        }
    ],
    "sg:phone":"+1 432 272 2847",
    "sg:postcode":"79761",
    "sg:province":"TX",
    "sg:tags":[
        "industrial",
        "services-commercial"
    ],
    "wof:name":"Advanced Pest Management",
    "wof:placetype":"venue"
},
  "geometry": {"coordinates":[-102.339231,31.870392],"type":"Point"}
}