{
  "type": "Feature",
  "properties": {
    "iso:country":"US",
    "sg:address":"10447 Nacogdoches Rd",
    "sg:city":"San Antonio",
    "sg:classifiers":[
        {
            "category":"Restaurant",
            "type":"Food & Drink"
        }
    ],
    "sg:phone":"+1 210 590 9583",
    "sg:postcode":"78217",
    "sg:province":"TX",
    "sg:tags":[
        "eating"
    ],
    "wof:name":"Augies By The Park",
    "wof:placetype":"venue"
},
  "geometry": {"coordinates":[-98.42823799999999,29.53455],"type":"Point"}
}