{
  "type": "Feature",
  "properties": {
    "iso:country":"US",
    "sg:address":"6406 Stuebner Airline Rd",
    "sg:city":"Houston",
    "sg:classifiers":[
        {
            "category":"Personal",
            "type":"Services"
        }
    ],
    "sg:phone":"+1 713 692 3433",
    "sg:postcode":"77091",
    "sg:province":"TX",
    "sg:tags":[
        "mover"
    ],
    "sg:website":"www.autodriveaway.com",
    "wof:name":"Auto Driveaway Co",
    "wof:placetype":"venue"
},
  "geometry": {"coordinates":[-95.409302,29.857599],"type":"Point"}
}