{
  "type": "Feature",
  "properties": {
    "iso:country":"US",
    "sg:address":"1516 W Ave H",
    "sg:city":"Temple",
    "sg:classifiers":[
        {
            "category":"Restaurant",
            "type":"Food & Drink"
        }
    ],
    "sg:phone":"+1 254 298 5690",
    "sg:postcode":"76504",
    "sg:province":"TX",
    "sg:tags":[
        "banquet",
        "rooms"
    ],
    "wof:name":"Gober Party House",
    "wof:placetype":"venue"
},
  "geometry": {"coordinates":[-97.360491,31.092972],"type":"Point"}
}