{
  "type": "Feature",
  "properties": {
    "iso:country":"US",
    "sg:address":"5315 Laurel Creek Way",
    "sg:city":"Houston",
    "sg:classifiers":[
        {
            "category":"Building & Trades",
            "subcategory":"Construction",
            "type":"Services"
        }
    ],
    "sg:phone":"+1 713 944 9687",
    "sg:postcode":"77017",
    "sg:province":"TX",
    "sg:tags":[
        "house"
    ],
    "wof:name":"Neely & Sons Construction",
    "wof:placetype":"venue"
},
  "geometry": {"coordinates":[-95.243064,29.678318],"type":"Point"}
}