{
  "type": "Feature",
  "properties": {
    "iso:country":"US",
    "sg:address":"1220 N Main St",
    "sg:city":"Fort Worth",
    "sg:classifiers":[
        {
            "category":"Professional",
            "subcategory":"Lawyer & Legal Services",
            "type":"Services"
        }
    ],
    "sg:phone":"+1 817 625 4674",
    "sg:postcode":"76164",
    "sg:province":"TX",
    "sg:tags":[
        "attorney"
    ],
    "wof:name":"Montemayor Myrna",
    "wof:placetype":"venue"
},
  "geometry": {"coordinates":[-97.344922,32.775265],"type":"Point"}
}