{
  "type": "Feature",
  "properties": {
    "iso:country":"US",
    "sg:address":"1302 E 6th Street",
    "sg:city":"Austin",
    "sg:classifiers":[
        {
            "category":"Personal",
            "subcategory":"Barber",
            "type":"Services"
        }
    ],
    "sg:phone":"+1 512 477 7194",
    "sg:postcode":"78702",
    "sg:province":"TX",
    "wof:name":"Valentinos Barber Shop",
    "wof:placetype":"venue"
},
  "geometry": {"coordinates":[-97.72932,30.263861],"type":"Point"}
}