{
  "type": "Feature",
  "properties": {
    "iso:country":"US",
    "sg:address":"304 Pearl St",
    "sg:city":"Beaumont",
    "sg:classifiers":[
        {
            "category":"Professional",
            "subcategory":"Employment Agencies",
            "type":"Services"
        }
    ],
    "sg:phone":"+1 409 839 8045",
    "sg:postcode":"77701",
    "sg:province":"TX",
    "sg:tags":[
        "opportunity"
    ],
    "wof:name":"Texas Workforce Ctr",
    "wof:placetype":"venue"
},
  "geometry": {"coordinates":[-94.099127,30.083987],"type":"Point"}
}