{
  "type": "Feature",
  "properties": {
    "iso:country":"US",
    "sg:address":"18653 FM 1431",
    "sg:city":"Leander",
    "sg:classifiers":[
        {
            "category":"Restaurant",
            "type":"Food & Drink"
        }
    ],
    "sg:phone":"+1 512 267 2112",
    "sg:postcode":"78645",
    "sg:province":"TX",
    "sg:tags":[
        "eating"
    ],
    "wof:name":"Fairway The",
    "wof:placetype":"venue"
},
  "geometry": {"coordinates":[-97.923833,30.491252],"type":"Point"}
}