{
  "type": "Feature",
  "properties": {
    "iso:country":"US",
    "sg:address":"8424 Hansen Rd",
    "sg:city":"Houston",
    "sg:classifiers":[
        {
            "category":"Building & Trades",
            "subcategory":"Equipment Rental",
            "type":"Services"
        }
    ],
    "sg:phone":"+1 713 378 2800",
    "sg:postcode":"77075",
    "sg:province":"TX",
    "sg:tags":[
        "contractor"
    ],
    "wof:name":"Atlas Copco Rental Svc Corp",
    "wof:placetype":"venue"
},
  "geometry": {"coordinates":[-95.258253,29.646036],"type":"Point"}
}