{
  "type": "Feature",
  "properties": {
    "iso:country":"US",
    "sg:address":"2421 College Ave",
    "sg:city":"Snyder",
    "sg:classifiers":[
        {
            "category":"Personal",
            "subcategory":"Barber",
            "type":"Services"
        }
    ],
    "sg:phone":"+1 325 574 6844",
    "sg:postcode":"79549",
    "sg:province":"TX",
    "sg:tags":[
        "shop"
    ],
    "wof:name":"City Barber Shop",
    "wof:placetype":"venue"
},
  "geometry": {"coordinates":[-100.91842800000001,32.71798],"type":"Point"}
}