{
  "type": "Feature",
  "properties": {
    "iso:country":"US",
    "sg:address":"12701 Veterans Memorial Dr",
    "sg:city":"Houston",
    "sg:classifiers":[
        {
            "category":"Wholesale",
            "subcategory":"Machinery & Supplies",
            "type":"Manufacturing & Wholesale Goods"
        }
    ],
    "sg:phone":"+1 281 895 0867",
    "sg:postcode":"77014",
    "sg:province":"TX",
    "sg:tags":[
        "equipment",
        "industrial"
    ],
    "wof:name":"Ram & Crown International",
    "wof:placetype":"venue"
},
  "geometry": {"coordinates":[-95.486994,29.972657],"type":"Point"}
}