{
  "type": "Feature",
  "properties": {
    "iso:country":"US",
    "sg:address":"506 Cameron Ave",
    "sg:city":"Dallas",
    "sg:classifiers":[
        {
            "category":"Professional",
            "type":"Services"
        }
    ],
    "sg:phone":"+1 214 827 4996",
    "sg:postcode":"75223",
    "sg:province":"TX",
    "wof:name":"Patrick R Faulhaber",
    "wof:placetype":"venue"
},
  "geometry": {"coordinates":[-96.746887,32.804264],"type":"Point"}
}