{
  "type": "Feature",
  "properties": {
    "iso:country":"US",
    "sg:address":"7433 Chelmsford Pl",
    "sg:city":"N Richland Hills",
    "sg:classifiers":[
        {
            "category":"Freight",
            "type":"Transportation"
        }
    ],
    "sg:phone":"+1 817 485 9355",
    "sg:postcode":"76180",
    "sg:province":"TX",
    "sg:tags":[
        "hauling",
        "trucking"
    ],
    "wof:name":"G G & R Trucking",
    "wof:placetype":"venue"
},
  "geometry": {"coordinates":[-97.221909,32.862542],"type":"Point"}
}