{
  "type": "Feature",
  "properties": {
    "iso:country":"US",
    "sg:address":"3222 Cedar Knolls Dr",
    "sg:city":"Kingwood",
    "sg:classifiers":[
        {
            "category":"Professional",
            "subcategory":"Research",
            "type":"Services"
        },
        {
            "category":"Science Facility",
            "type":"Public Place"
        }
    ],
    "sg:phone":"+1 281 813 2664",
    "sg:postcode":"77339",
    "sg:province":"TX",
    "sg:tags":[
        "development",
        "laboratories-research"
    ],
    "wof:name":"Tobias Safety Services",
    "wof:placetype":"venue"
},
  "geometry": {"coordinates":[-95.206255,30.054746],"type":"Point"}
}