{
  "type": "Feature",
  "properties": {
    "iso:country":"US",
    "sg:address":"6711 Bingle Rd",
    "sg:city":"Houston",
    "sg:classifiers":[
        {
            "category":"Shopping",
            "subcategory":"Clothing, Apparel, & Fashions",
            "type":"Retail Goods"
        },
        {
            "category":"Professional",
            "subcategory":"Advertising",
            "type":"Services"
        },
        {
            "category":"Shopping",
            "subcategory":"Crafts & Fabrics",
            "type":"Retail Goods"
        }
    ],
    "sg:phone":"+1 713 939 9730",
    "sg:postcode":"77092",
    "sg:province":"TX",
    "sg:tags":[
        "t-shirt",
        "advertising-promotional",
        "product",
        "embroidery"
    ],
    "sg:website":"http://www.prolinesupplyco.com",
    "wof:name":"Proline Supply Company",
    "wof:placetype":"venue"
},
  "geometry": {"coordinates":[-95.488049,29.86232],"type":"Point"}
}