{
  "type": "Feature",
  "properties": {
    "iso:country":"US",
    "sg:address":"107 Guinevere St",
    "sg:city":"Victoria",
    "sg:classifiers":[
        {
            "category":"Place Of Worship",
            "type":"Public Place"
        }
    ],
    "sg:phone":"+1 361 485 2808",
    "sg:postcode":"77904",
    "sg:province":"TX",
    "sg:tags":[
        "church"
    ],
    "wof:name":"Lighthouse Fwb Church",
    "wof:placetype":"venue"
},
  "geometry": {"coordinates":[-96.99178999999999,28.85204],"type":"Point"}
}