{
  "type": "Feature",
  "properties": {
    "iso:country":"US",
    "sg:address":"14080 Nacogdoches Rd",
    "sg:city":"San Antonio",
    "sg:classifiers":[
        {
            "category":"Professional",
            "subcategory":"Management & Consulting",
            "type":"Services"
        }
    ],
    "sg:phone":"+1 210 656 9080",
    "sg:postcode":"78247",
    "sg:province":"TX",
    "sg:tags":[
        "marketing",
        "program"
    ],
    "wof:name":"GBA Marketing",
    "wof:placetype":"venue"
},
  "geometry": {"coordinates":[-98.384359,29.568518],"type":"Point"}
}