{
  "type": "Feature",
  "properties": {
    "iso:country":"US",
    "sg:address":"6432 Amposta Dr",
    "sg:city":"El Paso",
    "sg:classifiers":[
        {
            "category":"Manufacturing",
            "subcategory":"Printing",
            "type":"Manufacturing & Wholesale Goods"
        }
    ],
    "sg:phone":"+1 915 845 8474",
    "sg:postcode":"79912",
    "sg:province":"TX",
    "sg:tags":[
        "periodical"
    ],
    "wof:name":"Schnell Publishing Co Inc",
    "wof:placetype":"venue"
},
  "geometry": {"coordinates":[-106.534025,31.852136],"type":"Point"}
}