{
  "type": "Feature",
  "properties": {
    "iso:country":"US",
    "sg:address":"2218 S Tyler St",
    "sg:city":"Amarillo",
    "sg:classifiers":[
        {
            "category":"Retail",
            "subcategory":"Car Wash",
            "type":"Services"
        }
    ],
    "sg:phone":"+1 806 374 9879",
    "sg:postcode":"79109",
    "sg:province":"TX",
    "sg:tags":[
        "carwash"
    ],
    "wof:name":"Dj Car Wash Service",
    "wof:placetype":"venue"
},
  "geometry": {"coordinates":[-101.842269,35.187585],"type":"Point"}
}