{
  "type": "Feature",
  "properties": {
    "iso:country":"US",
    "sg:address":"11583 Wilcrest Dr",
    "sg:city":"Houston",
    "sg:classifiers":[
        {
            "category":"Professional",
            "subcategory":"Business Services",
            "type":"Services"
        }
    ],
    "sg:phone":"+1 281 933 2405",
    "sg:postcode":"77099",
    "sg:province":"TX",
    "wof:name":"Vision Line Enterprises",
    "wof:placetype":"venue"
},
  "geometry": {"coordinates":[-95.570367,29.653741],"type":"Point"}
}