{
  "type": "Feature",
  "properties": {
    "iso:country":"US",
    "sg:address":"1 Courthouse Circle Dr, Suite 206",
    "sg:city":"Jourdanton",
    "sg:classifiers":[
        {
            "category":"Government",
            "subcategory":"Court House",
            "type":"Public Place"
        }
    ],
    "sg:phone":"+1 830 769 3750",
    "sg:postcode":"78026",
    "sg:province":"TX",
    "sg:tags":[
        "justice"
    ],
    "sg:website":"http://www.81st-218thdistrictcourt.org",
    "wof:name":"81st & 218th District Court",
    "wof:placetype":"venue"
},
  "geometry": {"coordinates":[-98.546234,28.920031],"type":"Point"}
}