{
  "type": "Feature",
  "properties": {
    "iso:country":"US",
    "sg:address":"2139 Lotus Blossom St",
    "sg:city":"San Antonio",
    "sg:classifiers":[
        {
            "category":"Shopping",
            "subcategory":"Musical Instruments",
            "type":"Retail Goods"
        }
    ],
    "sg:phone":"+1 210 496 7880",
    "sg:postcode":"78247",
    "sg:province":"TX",
    "wof:name":"Mitch Guitars",
    "wof:placetype":"venue"
},
  "geometry": {"coordinates":[-98.460792,29.549514],"type":"Point"}
}