{
  "type": "Feature",
  "properties": {
    "iso:country":"US",
    "sg:address":"107 W Buck St",
    "sg:city":"Caldwell",
    "sg:classifiers":[
        {
            "category":"Health Services",
            "subcategory":"Clinic",
            "type":"Services"
        }
    ],
    "sg:phone":"+1 979 567 4441",
    "sg:postcode":"77836",
    "sg:province":"TX",
    "sg:tags":[
        "home",
        "care"
    ],
    "wof:name":"Healthwise Home Health",
    "wof:placetype":"venue"
},
  "geometry": {"coordinates":[-96.69244,30.531984],"type":"Point"}
}