{
  "type": "Feature",
  "properties": {
    "iso:country":"US",
    "sg:address":"111 Kessler Dr",
    "sg:city":"Granbury",
    "sg:classifiers":[
        {
            "category":"Building & Trades",
            "subcategory":"Electrical",
            "type":"Services"
        }
    ],
    "sg:phone":"+1 817 573 8445",
    "sg:postcode":"76048",
    "sg:province":"TX",
    "sg:tags":[
        "electrical",
        "contractor"
    ],
    "wof:name":"Phones Buy Action & Son Inc",
    "wof:placetype":"venue"
},
  "geometry": {"coordinates":[-97.795416,32.438682],"type":"Point"}
}