{
  "type": "Feature",
  "properties": {
    "iso:country":"US",
    "sg:address":"2201 Plaza Pkwy",
    "sg:city":"Bedford",
    "sg:classifiers":[
        {
            "category":"Travel",
            "subcategory":"Hotels & Motels",
            "type":"Entertainment"
        }
    ],
    "sg:phone":"+1 817 283 3725",
    "sg:postcode":"76021",
    "sg:province":"TX",
    "wof:name":"Townplace Suites",
    "wof:placetype":"venue"
},
  "geometry": {"coordinates":[-97.132592,32.838175],"type":"Point"}
}