{
  "type": "Feature",
  "properties": {
    "iso:country":"US",
    "sg:address":"625 S Briery Rd",
    "sg:city":"Irving",
    "sg:classifiers":[
        {
            "category":"Communications",
            "subcategory":"Film & Video Production",
            "type":"Services"
        }
    ],
    "sg:phone":"+1 972 953 0446",
    "sg:postcode":"75060",
    "sg:province":"TX",
    "sg:tags":[
        "motion",
        "picture"
    ],
    "wof:name":"Uplink Communications",
    "wof:placetype":"venue"
},
  "geometry": {"coordinates":[-96.990326,32.807488],"type":"Point"}
}