{
  "type": "Feature",
  "properties": {
    "iso:country":"US",
    "sg:address":"211 S Gaston St",
    "sg:city":"Crane",
    "sg:classifiers":[
        {
            "category":"Banks & Credit Unions",
            "subcategory":"Bank",
            "type":"Services"
        }
    ],
    "sg:phone":"+1 432 558 7101",
    "sg:postcode":"79731",
    "sg:province":"TX",
    "wof:name":"Security State Bank",
    "wof:placetype":"venue"
},
  "geometry": {"coordinates":[-102.35138000000001,31.401177],"type":"Point"}
}