{
  "type": "Feature",
  "properties": {
    "iso:country":"US",
    "sg:address":"391 Sawdust Rd",
    "sg:city":"Spring",
    "sg:classifiers":[
        {
            "category":"Social Services",
            "type":"Services"
        }
    ],
    "sg:phone":"+1 281 296 9105",
    "sg:postcode":"77380",
    "sg:province":"TX",
    "sg:tags":[
        "organization",
        "welfare"
    ],
    "wof:name":"American Red Cross-Central Tx",
    "wof:placetype":"venue"
},
  "geometry": {"coordinates":[-95.446648,30.126638],"type":"Point"}
}