{
  "type": "Feature",
  "properties": {
    "iso:country":"US",
    "sg:address":"10909 Indian Trl Ste 101",
    "sg:city":"Dallas",
    "sg:classifiers":[
        {
            "category":"Retail",
            "subcategory":"Auto Repair",
            "type":"Services"
        }
    ],
    "sg:phone":"+1 972 406 9957",
    "sg:postcode":"75229",
    "sg:province":"TX",
    "sg:tags":[
        "body",
        "shop"
    ],
    "sg:website":"www.wjautobody.com",
    "wof:name":"WJ Auto Body",
    "wof:placetype":"venue"
},
  "geometry": {"coordinates":[-96.884224,32.896573],"type":"Point"}
}