{
  "type": "Feature",
  "properties": {
    "iso:country":"US",
    "sg:address":"1275 N Main St",
    "sg:city":"Mansfield",
    "sg:classifiers":[
        {
            "category":"Professional",
            "type":"Services"
        }
    ],
    "sg:phone":"+1 972 366 9400",
    "sg:postcode":"76063",
    "sg:province":"TX",
    "wof:name":"Fiber Technology Svc",
    "wof:placetype":"venue"
},
  "geometry": {"coordinates":[-97.151173,32.580365],"type":"Point"}
}