{
  "type": "Feature",
  "properties": {
    "iso:country":"US",
    "sg:address":"1113 Ragsdale St",
    "sg:city":"Terrell",
    "sg:classifiers":[
        {
            "category":"Shopping",
            "subcategory":"Used Merchandise",
            "type":"Retail Goods"
        }
    ],
    "sg:phone":"+1 972 564 4315",
    "sg:postcode":"75160",
    "sg:province":"TX",
    "wof:name":"M & M Designs & Sales",
    "wof:placetype":"venue"
},
  "geometry": {"coordinates":[-96.39088700000001,32.675117],"type":"Point"}
}