{
  "type": "Feature",
  "properties": {
    "iso:country":"US",
    "sg:address":"235 E Loop 820",
    "sg:city":"Fort Worth",
    "sg:classifiers":[
        {
            "category":"Professional",
            "subcategory":"Employment Agencies",
            "type":"Services"
        }
    ],
    "sg:phone":"+1 817 589 7100",
    "sg:postcode":"76120",
    "sg:province":"TX",
    "sg:tags":[
        "help",
        "supply"
    ],
    "wof:name":"Continous Care Solutions",
    "wof:placetype":"venue"
},
  "geometry": {"coordinates":[-97.212165,32.775315],"type":"Point"}
}