{
  "type": "Feature",
  "properties": {
    "iso:country":"US",
    "sg:address":"9666 Westheimer Rd",
    "sg:city":"Houston",
    "sg:classifiers":[
        {
            "category":"Retail",
            "subcategory":"Auto Repair",
            "type":"Services"
        }
    ],
    "sg:phone":"+1 713 789 8434",
    "sg:postcode":"77063",
    "sg:province":"TX",
    "sg:tags":[
        "automotive"
    ],
    "wof:name":"Jiffy Lube",
    "wof:placetype":"venue"
},
  "geometry": {"coordinates":[-95.537614,29.737216],"type":"Point"}
}