{
  "type": "Feature",
  "properties": {
    "iso:country":"US",
    "sg:address":"957 Rio Verde",
    "sg:city":"New Braunfels",
    "sg:classifiers":[
        {
            "category":"Professional",
            "subcategory":"Business Services",
            "type":"Services"
        }
    ],
    "sg:phone":"+1 210 867 3939",
    "sg:postcode":"78130",
    "sg:province":"TX",
    "wof:name":"Events Etc",
    "wof:placetype":"venue"
},
  "geometry": {"coordinates":[-98.089944,29.690221],"type":"Point"}
}