{
  "type": "Feature",
  "properties": {
    "iso:country":"US",
    "sg:address":"1920 Abrams Pkwy",
    "sg:city":"Dallas",
    "sg:classifiers":[
        {
            "category":"Professional",
            "type":"Services"
        }
    ],
    "sg:phone":"+1 214 887 0054",
    "sg:postcode":"75214",
    "sg:province":"TX",
    "wof:name":"Optick Networks",
    "wof:placetype":"venue"
},
  "geometry": {"coordinates":[-96.75278400000001,32.812014],"type":"Point"}
}