{
  "type": "Feature",
  "properties": {
    "iso:country":"US",
    "sg:address":"622 W Malone",
    "sg:city":"San Antonio",
    "sg:classifiers":[
        {
            "category":"Retail",
            "subcategory":"Repair Shop",
            "type":"Services"
        }
    ],
    "sg:phone":"+1 210 534 1263",
    "sg:postcode":"78225",
    "sg:province":"TX",
    "sg:tags":[
        "refrigeration"
    ],
    "wof:name":"Cantu Refrigeration",
    "wof:placetype":"venue"
},
  "geometry": {"coordinates":[-98.513347,29.387246],"type":"Point"}
}