{
  "type": "Feature",
  "properties": {
    "iso:country":"US",
    "sg:address":"600 E Taylor St",
    "sg:city":"Sherman",
    "sg:classifiers":[
        {
            "category":"Government",
            "subcategory":"Office",
            "type":"Public Place"
        }
    ],
    "sg:phone":"+1 903 893 7142",
    "sg:postcode":"75090",
    "sg:province":"TX",
    "sg:tags":[
        "federal"
    ],
    "wof:name":"US Labor Dept",
    "wof:placetype":"venue"
},
  "geometry": {"coordinates":[-96.60672599999999,33.656875],"type":"Point"}
}