{
  "type": "Feature",
  "properties": {
    "iso:country":"US",
    "sg:address":"108 W 22nd St",
    "sg:city":"San Angelo",
    "sg:classifiers":[
        {
            "category":"Shopping",
            "subcategory":"Discount & Variety Stores",
            "type":"Retail Goods"
        }
    ],
    "sg:phone":"+1 325 653 0273",
    "sg:postcode":"76903",
    "sg:province":"TX",
    "sg:tags":[
        "merchandise",
        "general"
    ],
    "wof:name":"Ramiro Hernandez Diaz",
    "wof:placetype":"venue"
},
  "geometry": {"coordinates":[-100.45245,31.481152],"type":"Point"}
}