{
  "type": "Feature",
  "properties": {
    "iso:country":"US",
    "sg:address":"542 Haggard St",
    "sg:city":"Plano",
    "sg:classifiers":[
        {
            "category":"Building & Trades",
            "subcategory":"Cleaning & Sanitation",
            "type":"Services"
        }
    ],
    "sg:phone":"+1 972 578 8985",
    "sg:postcode":"75074",
    "sg:province":"TX",
    "sg:tags":[
        "maintenance"
    ],
    "wof:name":"Fribourg Services Inc",
    "wof:placetype":"venue"
},
  "geometry": {"coordinates":[-96.707066,33.026275],"type":"Point"}
}