{
  "type": "Feature",
  "properties": {
    "iso:country":"US",
    "sg:address":"1500 S Saint Marys St",
    "sg:city":"San Antonio",
    "sg:classifiers":[
        {
            "category":"Manufacturing",
            "subcategory":"Printing",
            "type":"Manufacturing & Wholesale Goods"
        }
    ],
    "sg:phone":"+1 210 227 0044",
    "sg:postcode":"78210",
    "sg:province":"TX",
    "sg:tags":[
        "newspaper"
    ],
    "sg:website":"www.sacurrent.com",
    "wof:name":"San Antonio Current Co",
    "wof:placetype":"venue"
},
  "geometry": {"coordinates":[-98.486541,29.406916],"type":"Point"}
}