{
  "type": "Feature",
  "properties": {
    "iso:country":"US",
    "sg:address":"9702 W Ferris Branch Blvd",
    "sg:city":"Dallas",
    "sg:classifiers":[
        {
            "category":"Shopping",
            "subcategory":"Clothing, Apparel, & Fashions",
            "type":"Retail Goods"
        }
    ],
    "sg:phone":"+1 214 349 2827",
    "sg:postcode":"75243",
    "sg:province":"TX",
    "sg:tags":[
        "baby",
        "accessory"
    ],
    "wof:name":"Hats For Babies & Children",
    "wof:placetype":"venue"
},
  "geometry": {"coordinates":[-96.72616600000001,32.903744],"type":"Point"}
}