{
  "type": "Feature",
  "properties": {
    "iso:country":"US",
    "sg:address":"1420 Century Dr Ste 600",
    "sg:city":"Carrollton",
    "sg:classifiers":[
        {
            "category":"Building & Trades",
            "subcategory":"Cleaning & Sanitation",
            "type":"Services"
        }
    ],
    "sg:phone":"+1 972 386 3808",
    "sg:postcode":"75006",
    "sg:province":"TX",
    "sg:tags":[
        "carpet"
    ],
    "wof:name":"SERVPRO",
    "wof:placetype":"venue"
},
  "geometry": {"coordinates":[-96.916218,32.956025],"type":"Point"}
}