{
  "type": "Feature",
  "properties": {
    "iso:country":"US",
    "sg:address":"3237 Ayers St",
    "sg:city":"Corpus Christi",
    "sg:classifiers":[
        {
            "category":"Retail",
            "subcategory":"Laundry & Dry Cleaning",
            "type":"Services"
        }
    ],
    "sg:phone":"+1 361 883 3362",
    "sg:postcode":"78415",
    "sg:province":"TX",
    "sg:tags":[
        "cleaners"
    ],
    "sg:website":"www.jrviolacleaners.com",
    "wof:name":"J R Viola Cleaners",
    "wof:placetype":"venue"
},
  "geometry": {"coordinates":[-97.412207,27.760299],"type":"Point"}
}