{
  "type": "Feature",
  "properties": {
    "iso:country":"US",
    "sg:address":"1624 Northcrest Dr",
    "sg:city":"Plano",
    "sg:classifiers":[
        {
            "category":"Home & Garden",
            "subcategory":"Garden Supply",
            "type":"Retail Goods"
        }
    ],
    "sg:phone":"+1 972 633 0068",
    "sg:postcode":"75075",
    "sg:province":"TX",
    "sg:tags":[
        "fertilizer"
    ],
    "wof:name":"PCS Sales",
    "wof:placetype":"venue"
},
  "geometry": {"coordinates":[-96.723292,33.009705],"type":"Point"}
}