{
  "type": "Feature",
  "properties": {
    "iso:country":"US",
    "sg:address":"801 E Ave C",
    "sg:city":"Lampasas",
    "sg:classifiers":[
        {
            "category":"Health Services",
            "subcategory":"Nursing And Care Facility",
            "type":"Services"
        }
    ],
    "sg:phone":"+1 512 556 3570",
    "sg:postcode":"76550",
    "sg:province":"TX",
    "sg:tags":[
        "home",
        "retirement",
        "community"
    ],
    "wof:name":"Antique Oaks Veterans Home",
    "wof:placetype":"venue"
},
  "geometry": {"coordinates":[-98.176638,31.072661],"type":"Point"}
}