{
  "type": "Feature",
  "properties": {
    "iso:country":"US",
    "sg:address":"2285 Salt Branch Loop",
    "sg:city":"Doss",
    "sg:classifiers":[
        {
            "category":"Farming",
            "subcategory":"Livestock Farm",
            "type":"Manufacturing & Wholesale Goods"
        }
    ],
    "sg:phone":"+1 830 669 2320",
    "sg:postcode":"78618",
    "sg:province":"TX",
    "sg:tags":[
        "beef",
        "feedlot",
        "cattle"
    ],
    "wof:name":"Jim Faught",
    "wof:placetype":"venue"
},
  "geometry": {"coordinates":[-99.169388,30.481628],"type":"Point"}
}