{
  "type": "Feature",
  "properties": {
    "iso:country":"US",
    "sg:address":"7241 S Hulen St",
    "sg:city":"Fort Worth",
    "sg:classifiers":[
        {
            "category":"Retail",
            "subcategory":"Laundry & Dry Cleaning",
            "type":"Services"
        }
    ],
    "sg:phone":"+1 817 263 4722",
    "sg:postcode":"76133",
    "sg:province":"TX",
    "sg:tags":[
        "drycleaning"
    ],
    "wof:name":"Dryclean Super Center",
    "wof:placetype":"venue"
},
  "geometry": {"coordinates":[-97.395903,32.641092],"type":"Point"}
}