{
  "type": "Feature",
  "properties": {
    "iso:country":"US",
    "sg:address":"14235 Blanco Rd",
    "sg:city":"San Antonio",
    "sg:classifiers":[
        {
            "category":"Professional",
            "subcategory":"Management & Consulting",
            "type":"Services"
        }
    ],
    "sg:phone":"+1 210 764 1660",
    "sg:postcode":"78216",
    "sg:province":"TX",
    "sg:tags":[
        "marketing",
        "consultant"
    ],
    "wof:name":"Marketing Effects",
    "wof:placetype":"venue"
},
  "geometry": {"coordinates":[-98.51812200000001,29.570363],"type":"Point"}
}