{
  "type": "Feature",
  "properties": {
    "iso:country":"US",
    "sg:address":"501 NE 4th St",
    "sg:city":"Tulia",
    "sg:classifiers":[
        {
            "category":"Education",
            "subcategory":"School",
            "type":"Public Place"
        }
    ],
    "sg:phone":"+1 806 995 3500",
    "sg:postcode":"79088",
    "sg:province":"TX",
    "wof:name":"Tulia ISD School",
    "wof:placetype":"venue"
},
  "geometry": {"coordinates":[-101.75689800000001,34.541559],"type":"Point"}
}