{
  "type": "Feature",
  "properties": {
    "iso:country":"US",
    "sg:address":"1521 Azteca Dr",
    "sg:city":"Fort Worth",
    "sg:classifiers":[
        {
            "category":"Banks & Credit Unions",
            "subcategory":"Financial Services",
            "type":"Services"
        }
    ],
    "sg:phone":"+1 817 451 0819",
    "sg:postcode":"76112",
    "sg:province":"TX",
    "sg:tags":[
        "investor"
    ],
    "wof:name":"Wf Fuller Investments",
    "wof:placetype":"venue"
},
  "geometry": {"coordinates":[-97.227335,32.755653],"type":"Point"}
}