{
  "type": "Feature",
  "properties": {
    "iso:country":"US",
    "sg:address":"2003 Woodland Haven Rd",
    "sg:city":"Houston",
    "sg:classifiers":[
        {
            "category":"Organizations",
            "subcategory":"Religious Organization",
            "type":"Services"
        }
    ],
    "sg:phone":"+1 281 480 5400",
    "sg:postcode":"77062",
    "sg:province":"TX",
    "wof:name":"Galveston Islamic Society",
    "wof:placetype":"venue"
},
  "geometry": {"coordinates":[-95.116479,29.577964],"type":"Point"}
}