{
  "type": "Feature",
  "properties": {
    "iso:country":"US",
    "sg:address":"1211 Miramar St",
    "sg:city":"Houston",
    "sg:classifiers":[
        {
            "category":"Real Estate",
            "subcategory":"Real Estate Agent",
            "type":"Services"
        }
    ],
    "sg:phone":"+1 713 533 9510",
    "sg:postcode":"77006",
    "sg:province":"TX",
    "wof:name":"Larry West Photography",
    "wof:placetype":"venue"
},
  "geometry": {"coordinates":[-95.39455700000001,29.732603],"type":"Point"}
}