{
  "type": "Feature",
  "properties": {
    "iso:country":"US",
    "sg:address":"19091 I- 45 S",
    "sg:city":"Conroe",
    "sg:classifiers":[
        {
            "category":"Autos & Motor Vehicles",
            "subcategory":"Fuel & Gas Station",
            "type":"Retail Goods"
        }
    ],
    "sg:phone":"+1 936 271 1273",
    "sg:postcode":"77385",
    "sg:province":"TX",
    "sg:tags":[
        "oil"
    ],
    "wof:name":"Sam's Club Gas",
    "wof:placetype":"venue"
},
  "geometry": {"coordinates":[-95.45161899999999,30.179771],"type":"Point"}
}