{
  "type": "Feature",
  "properties": {
    "iso:country":"US",
    "sg:address":"1010 Red Bud St",
    "sg:city":"Channelview",
    "sg:classifiers":[
        {
            "category":"Shopping",
            "subcategory":"Computers & Home Electronics",
            "type":"Retail Goods"
        }
    ],
    "sg:phone":"+1 281 860 0412",
    "sg:postcode":"77530",
    "sg:province":"TX",
    "wof:name":"D & P Services",
    "wof:placetype":"venue"
},
  "geometry": {"coordinates":[-95.110682,29.796683],"type":"Point"}
}