{
  "type": "Feature",
  "properties": {
    "iso:country":"US",
    "sg:address":"806 W Centerville Rd",
    "sg:city":"Garland",
    "sg:classifiers":[
        {
            "category":"Autos & Motor Vehicles",
            "subcategory":"Fuel & Gas Station",
            "type":"Retail Goods"
        }
    ],
    "sg:phone":"+1 972 279 0496",
    "sg:postcode":"75041",
    "sg:province":"TX",
    "sg:website":"http://www.phillips66.com",
    "wof:name":"Conocophillips Company",
    "wof:placetype":"venue"
},
  "geometry": {"coordinates":[-96.64259,32.86106],"type":"Point"}
}