{
  "type": "Feature",
  "properties": {
    "iso:country":"US",
    "sg:address":"6405 Antoine Dr",
    "sg:city":"Houston",
    "sg:classifiers":[
        {
            "category":"Shopping",
            "type":"Retail Goods"
        }
    ],
    "sg:phone":"+1 713 680 2786",
    "sg:postcode":"77091",
    "sg:province":"TX",
    "sg:tags":[
        "telephone",
        "cellular"
    ],
    "wof:name":"Nations Pager",
    "wof:placetype":"venue"
},
  "geometry": {"coordinates":[-95.473411,29.851472],"type":"Point"}
}