{
  "type": "Feature",
  "properties": {
    "iso:country":"US",
    "sg:address":"11888 Marsh Ln Ste 600",
    "sg:city":"Dallas",
    "sg:classifiers":[
        {
            "category":"Arts & Performance",
            "subcategory":"Arts Center",
            "type":"Entertainment"
        },
        {
            "category":"Education",
            "subcategory":"Special Training",
            "type":"Public Place"
        }
    ],
    "sg:phone":"+1 972 484 7900",
    "sg:postcode":"75234",
    "sg:province":"TX",
    "sg:tags":[
        "school",
        "performing"
    ],
    "wof:name":"Jtm Studio of the Performing Arts",
    "wof:placetype":"venue"
},
  "geometry": {"coordinates":[-96.855904,32.9109],"type":"Point"}
}