{
  "type": "Feature",
  "properties": {
    "iso:country":"US",
    "sg:address":"4000 Essex Ln",
    "sg:city":"Houston",
    "sg:classifiers":[
        {
            "category":"Real Estate",
            "subcategory":"Real Estate Operator",
            "type":"Services"
        }
    ],
    "sg:phone":"+1 713 355 2828",
    "sg:postcode":"77027",
    "sg:province":"TX",
    "sg:tags":[
        "building",
        "apartment"
    ],
    "wof:name":"Gael/Essex House",
    "wof:placetype":"venue"
},
  "geometry": {"coordinates":[-95.447509,29.739677],"type":"Point"}
}