{
  "type": "Feature",
  "properties": {
    "iso:country":"US",
    "sg:address":"205 Hollow Tree Ln",
    "sg:city":"Houston",
    "sg:classifiers":[
        {
            "category":"Professional",
            "subcategory":"Management & Consulting",
            "type":"Services"
        }
    ],
    "sg:phone":"+1 832 249 2700",
    "sg:postcode":"77090",
    "sg:province":"TX",
    "sg:tags":[
        "hospital",
        "general"
    ],
    "wof:name":"Triumph Hospital Northwest",
    "wof:placetype":"venue"
},
  "geometry": {"coordinates":[-95.433131,30.028254],"type":"Point"}
}