{
  "type": "Feature",
  "properties": {
    "iso:country":"US",
    "sg:address":"1221 W Airport Fwy",
    "sg:city":"Irving",
    "sg:classifiers":[
        {
            "category":"Banks & Credit Unions",
            "subcategory":"Bank",
            "type":"Services"
        }
    ],
    "sg:phone":"+1 214 492 2552",
    "sg:postcode":"75062",
    "sg:province":"TX",
    "sg:tags":[
        "loan"
    ],
    "wof:name":"Americash Services Inc",
    "wof:placetype":"venue"
},
  "geometry": {"coordinates":[-96.96055800000001,32.837386],"type":"Point"}
}