{
  "type": "Feature",
  "properties": {
    "iso:country":"US",
    "sg:address":"10078 W Shore Dr",
    "sg:city":"Willis",
    "sg:classifiers":[
        {
            "category":"Building & Trades",
            "subcategory":"Equipment Rental",
            "type":"Services"
        }
    ],
    "sg:phone":"+1 936 856 1758",
    "sg:postcode":"77318",
    "sg:province":"TX",
    "wof:name":"Sounds Good",
    "wof:placetype":"venue"
},
  "geometry": {"coordinates":[-95.554052,30.387787],"type":"Point"}
}