{
  "type": "Feature",
  "properties": {
    "iso:country":"US",
    "sg:address":"3565 W Walnut St Ste G",
    "sg:city":"Garland",
    "sg:classifiers":[
        {
            "category":"Personal",
            "subcategory":"Beauty Salon",
            "type":"Services"
        }
    ],
    "sg:phone":"+1 972 272 9923",
    "sg:postcode":"75042",
    "sg:province":"TX",
    "sg:tags":[
        "hair",
        "stylist"
    ],
    "wof:name":"Annies Hair Salon",
    "wof:placetype":"venue"
},
  "geometry": {"coordinates":[-96.684557,32.917131],"type":"Point"}
}