{
  "type": "Feature",
  "properties": {
    "iso:country":"US",
    "sg:address":"18202 Spruce Creek Dr",
    "sg:city":"Houston",
    "sg:classifiers":[
        {
            "category":"Professional",
            "subcategory":"Business Services",
            "type":"Services"
        }
    ],
    "sg:phone":"+1 281 463 3117",
    "sg:postcode":"77084",
    "sg:province":"TX",
    "wof:name":"Flexible Solutions Inc",
    "wof:placetype":"venue"
},
  "geometry": {"coordinates":[-95.679726,29.844274],"type":"Point"}
}