{
  "type": "Feature",
  "properties": {
    "iso:country":"US",
    "sg:address":"1605 Briarpath Ln",
    "sg:city":"Arlington",
    "sg:classifiers":[
        {
            "category":"Retail",
            "subcategory":"Repair Shop",
            "type":"Services"
        }
    ],
    "sg:phone":"+1 817 557 4089",
    "sg:postcode":"76018",
    "sg:province":"TX",
    "wof:name":"Hmd Unlimited Cleaning",
    "wof:placetype":"venue"
},
  "geometry": {"coordinates":[-97.080005,32.667915],"type":"Point"}
}