{
  "type": "Feature",
  "properties": {
    "iso:country":"US",
    "sg:address":"1400 Five Notch Rd",
    "sg:city":"Marshall",
    "sg:classifiers":[
        {
            "category":"Building & Trades",
            "subcategory":"Construction",
            "type":"Services"
        }
    ],
    "sg:phone":"+1 903 935 2562",
    "sg:postcode":"75670",
    "sg:province":"TX",
    "sg:tags":[
        "contractor"
    ],
    "wof:name":"J E Hortman Construction Co",
    "wof:placetype":"venue"
},
  "geometry": {"coordinates":[-94.35178999999999,32.532492],"type":"Point"}
}