{
  "type": "Feature",
  "properties": {
    "iso:country":"US",
    "sg:address":"8717 Governors Row",
    "sg:city":"Dallas",
    "sg:classifiers":[
        {
            "category":"Manufacturing",
            "subcategory":"Printing",
            "type":"Manufacturing & Wholesale Goods"
        }
    ],
    "sg:phone":"+1 214 631 8881",
    "sg:postcode":"75247",
    "sg:province":"TX",
    "sg:tags":[
        "commercial"
    ],
    "wof:name":"Empire Print & Laser Imaging",
    "wof:placetype":"venue"
},
  "geometry": {"coordinates":[-96.87725399999999,32.824372],"type":"Point"}
}