{
  "type": "Feature",
  "properties": {
    "iso:country":"US",
    "sg:address":"404 N 40th St",
    "sg:city":"Corsicana",
    "sg:classifiers":[
        {
            "category":"Building & Trades",
            "subcategory":"Landscaping Services",
            "type":"Services"
        }
    ],
    "sg:phone":"+1 903 872 9754",
    "sg:postcode":"75110",
    "sg:province":"TX",
    "wof:name":"Lawn Techniques",
    "wof:placetype":"venue"
},
  "geometry": {"coordinates":[-96.499544,32.0815],"type":"Point"}
}