{
  "type": "Feature",
  "properties": {
    "iso:country":"US",
    "sg:address":"421 S Main St",
    "sg:city":"Del Rio",
    "sg:classifiers":[
        {
            "category":"Professional",
            "subcategory":"Lawyer & Legal Services",
            "type":"Services"
        }
    ],
    "sg:phone":"+1 830 775 7774",
    "sg:postcode":"78840",
    "sg:province":"TX",
    "sg:tags":[
        "attorney"
    ],
    "wof:name":"Ruben Nino Law Offices",
    "wof:placetype":"venue"
},
  "geometry": {"coordinates":[-100.89962,29.360971],"type":"Point"}
}