{
  "type": "Feature",
  "properties": {
    "iso:country":"US",
    "sg:address":"9603 Diamond Gap",
    "sg:city":"San Antonio",
    "sg:classifiers":[
        {
            "category":"Insurance",
            "subcategory":"Insurance Agent",
            "type":"Services"
        }
    ],
    "sg:phone":"+1 210 647 0588",
    "sg:postcode":"78254",
    "sg:province":"TX",
    "wof:name":"First Choice Claims Adjuster",
    "wof:placetype":"venue"
},
  "geometry": {"coordinates":[-98.668936,29.544858],"type":"Point"}
}