{
  "type": "Feature",
  "properties": {
    "iso:country":"US",
    "sg:address":"4601 S Loop 289",
    "sg:city":"Lubbock",
    "sg:classifiers":[
        {
            "category":"Education",
            "subcategory":"Special Training",
            "type":"Public Place"
        }
    ],
    "sg:phone":"+1 806 785 4400",
    "sg:postcode":"79424",
    "sg:province":"TX",
    "wof:name":"Sylvan Learning Centers",
    "wof:placetype":"venue"
},
  "geometry": {"coordinates":[-101.913332,33.532339],"type":"Point"}
}