{
  "type": "Feature",
  "properties": {
    "iso:country":"US",
    "sg:address":"2104 Dornoch Dr",
    "sg:city":"League City",
    "sg:classifiers":[
        {
            "category":"Professional",
            "type":"Services"
        }
    ],
    "sg:phone":"+1 281 538 1920",
    "sg:postcode":"77573",
    "sg:province":"TX",
    "wof:name":"Alta Tierra Co",
    "wof:placetype":"venue"
},
  "geometry": {"coordinates":[-95.06674599999999,29.53037],"type":"Point"}
}