{
  "type": "Feature",
  "properties": {
    "iso:country":"US",
    "sg:address":"3107 Yost Blvd",
    "sg:city":"Pearland",
    "sg:classifiers":[
        {
            "category":"Building & Trades",
            "subcategory":"Construction",
            "type":"Services"
        }
    ],
    "sg:phone":"+1 281 412 7750",
    "sg:postcode":"77581",
    "sg:province":"TX",
    "sg:tags":[
        "plastering",
        "contractor"
    ],
    "wof:name":"Elliott's Plastering",
    "wof:placetype":"venue"
},
  "geometry": {"coordinates":[-95.244972,29.55175],"type":"Point"}
}