{
  "type": "Feature",
  "properties": {
    "iso:country":"US",
    "sg:address":"6006 Morning Glory Cir",
    "sg:city":"El Paso",
    "sg:classifiers":[
        {
            "category":"Shopping",
            "subcategory":"Gifts & Souvenirs",
            "type":"Retail Goods"
        }
    ],
    "sg:phone":"+1 915 755 5535",
    "sg:postcode":"79924",
    "sg:province":"TX",
    "wof:name":"Gifts For You",
    "wof:placetype":"venue"
},
  "geometry": {"coordinates":[-106.39650399999999,31.894478],"type":"Point"}
}