{
  "type": "Feature",
  "properties": {
    "iso:country":"US",
    "sg:address":"217 Sweetgum St",
    "sg:city":"Nacogdoches",
    "sg:classifiers":[
        {
            "category":"Place Of Worship",
            "type":"Public Place"
        }
    ],
    "sg:phone":"+1 936 559 1502",
    "sg:postcode":"75961",
    "sg:province":"TX",
    "sg:tags":[
        "church"
    ],
    "wof:name":"Church Faithtemple",
    "wof:placetype":"venue"
},
  "geometry": {"coordinates":[-94.634587,31.594672],"type":"Point"}
}