{
  "type": "Feature",
  "properties": {
    "iso:country":"US",
    "sg:address":"5205 Cloverdale Ln",
    "sg:city":"Austin",
    "sg:classifiers":[
        {
            "category":"Manufacturing",
            "subcategory":"Printing",
            "type":"Manufacturing & Wholesale Goods"
        }
    ],
    "sg:phone":"+1 512 343 4546",
    "sg:postcode":"78723",
    "sg:province":"TX",
    "sg:tags":[
        "publisher"
    ],
    "wof:name":"Max Wells Maxims Inc",
    "wof:placetype":"venue"
},
  "geometry": {"coordinates":[-97.687488,30.300676],"type":"Point"}
}