{
  "type": "Feature",
  "properties": {
    "iso:country":"US",
    "sg:address":"102 Wilbarger St",
    "sg:city":"Vernon",
    "sg:classifiers":[
        {
            "category":"Home & Garden",
            "subcategory":"Furniture",
            "type":"Retail Goods"
        }
    ],
    "sg:phone":"+1 940 552 9277",
    "sg:postcode":"76384",
    "sg:province":"TX",
    "wof:name":"Canton Furniture & Flea Market",
    "wof:placetype":"venue"
},
  "geometry": {"coordinates":[-99.262806,34.151805],"type":"Point"}
}