{
  "type": "Feature",
  "properties": {
    "iso:country":"US",
    "sg:address":"9950 Cypresswood Dr",
    "sg:city":"Houston",
    "sg:classifiers":[
        {
            "category":"Banks & Credit Unions",
            "subcategory":"Investment Brokerage",
            "type":"Services"
        }
    ],
    "sg:phone":"+1 281 897 9141",
    "sg:postcode":"77070",
    "sg:province":"TX",
    "sg:tags":[
        "advisory",
        "financial"
    ],
    "wof:name":"Cypresswood Financial",
    "wof:placetype":"venue"
},
  "geometry": {"coordinates":[-95.56628499999999,29.981552],"type":"Point"}
}