{
  "type": "Feature",
  "properties": {
    "iso:country":"US",
    "sg:address":"1269 E Kleberg Ave",
    "sg:city":"Kingsville",
    "sg:classifiers":[
        {
            "category":"Organizations",
            "subcategory":"Religious Organization",
            "type":"Services"
        }
    ],
    "sg:phone":"+1 361 592 3642",
    "sg:postcode":"78363",
    "sg:province":"TX",
    "wof:name":"New Life Church of God",
    "wof:placetype":"venue"
},
  "geometry": {"coordinates":[-97.85228600000001,27.516726],"type":"Point"}
}