{
  "type": "Feature",
  "properties": {
    "iso:country":"US",
    "sg:address":"164 E College St",
    "sg:city":"Stephenville",
    "sg:classifiers":[
        {
            "category":"Real Estate",
            "subcategory":"Real Estate Operator",
            "type":"Services"
        }
    ],
    "sg:phone":"+1 254 965 3443",
    "sg:postcode":"76401",
    "sg:province":"TX",
    "sg:tags":[
        "apartment"
    ],
    "wof:name":"Stethnvlle Senior Citizens Ctr",
    "wof:placetype":"venue"
},
  "geometry": {"coordinates":[-98.20124300000001,32.22025],"type":"Point"}
}