{
  "type": "Feature",
  "properties": {
    "iso:country":"US",
    "sg:address":"14114 Dallas Pkwy",
    "sg:city":"Dallas",
    "sg:classifiers":[
        {
            "category":"Shopping",
            "subcategory":"Pharmacy",
            "type":"Retail Goods"
        }
    ],
    "sg:phone":"+1 972 788 0153",
    "sg:postcode":"75254",
    "sg:province":"TX",
    "sg:tags":[
        "drugstore"
    ],
    "wof:name":"Rite Aid Pharmacy",
    "wof:placetype":"venue"
},
  "geometry": {"coordinates":[-96.82157599999999,32.939901],"type":"Point"}
}