{
  "type": "Feature",
  "properties": {
    "iso:country":"US",
    "sg:address":"221 W Colorado Blvd",
    "sg:city":"Dallas",
    "sg:classifiers":[
        {
            "category":"Health Services",
            "subcategory":"Doctor",
            "type":"Services"
        }
    ],
    "sg:phone":"+1 214 942 5222",
    "sg:postcode":"75208",
    "sg:province":"TX",
    "sg:tags":[
        "medical"
    ],
    "wof:name":"Lonnie Whiddon",
    "wof:placetype":"venue"
},
  "geometry": {"coordinates":[-96.825603,32.759271],"type":"Point"}
}