{
  "type": "Feature",
  "properties": {
    "iso:country":"US",
    "sg:address":"8839 Knight Rd",
    "sg:city":"Houston",
    "sg:classifiers":[
        {
            "category":"Professional",
            "subcategory":"Management & Consulting",
            "type":"Services"
        },
        {
            "category":"Professional",
            "subcategory":"Engineering",
            "type":"Services"
        }
    ],
    "sg:phone":"+1 713 729 2533",
    "sg:postcode":"77054",
    "sg:province":"TX",
    "sg:tags":[
        "environmental",
        "ecological",
        "engineer",
        "consultant"
    ],
    "sg:website":"http://www.bayenv.com",
    "wof:name":"Bay Env",
    "wof:placetype":"venue"
},
  "geometry": {"coordinates":[-95.39983700000001,29.677008],"type":"Point"}
}