{
  "type": "Feature",
  "properties": {
    "iso:country":"US",
    "sg:address":"1709 Ambler Ave",
    "sg:city":"Abilene",
    "sg:classifiers":[
        {
            "category":"Autos & Motor Vehicles",
            "subcategory":"Auto Supplies",
            "type":"Retail Goods"
        }
    ],
    "sg:phone":"+1 325 676 1626",
    "sg:postcode":"79603",
    "sg:province":"TX",
    "wof:name":"Reeders Automotive Supply",
    "wof:placetype":"venue"
},
  "geometry": {"coordinates":[-99.740239,32.474398],"type":"Point"}
}