{
  "type": "Feature",
  "properties": {
    "iso:country":"US",
    "sg:address":"2500 N I- 35E",
    "sg:city":"Carrollton",
    "sg:classifiers":[
        {
            "category":"Building & Trades",
            "subcategory":"Construction",
            "type":"Services"
        }
    ],
    "sg:phone":"+1 972 242 4771",
    "sg:postcode":"75006",
    "sg:province":"TX",
    "sg:tags":[
        "steel",
        "reinforcing"
    ],
    "wof:name":"Wasco Reinforcing Steel Supply",
    "wof:placetype":"venue"
},
  "geometry": {"coordinates":[-96.93389000000001,32.986112],"type":"Point"}
}