{
  "type": "Feature",
  "properties": {
    "iso:country":"US",
    "sg:address":"1809 S Midkiff Rd",
    "sg:city":"Midland",
    "sg:classifiers":[
        {
            "category":"Manufacturing",
            "subcategory":"Chemicals & Compounds",
            "type":"Manufacturing & Wholesale Goods"
        }
    ],
    "sg:phone":"+1 432 570 1906",
    "sg:postcode":"79701",
    "sg:province":"TX",
    "sg:tags":[
        "product",
        "gas",
        "related",
        "mfg"
    ],
    "wof:name":"Boc Gases",
    "wof:placetype":"venue"
},
  "geometry": {"coordinates":[-102.10928,31.971286],"type":"Point"}
}