{
  "type": "Feature",
  "properties": {
    "iso:country":"US",
    "sg:address":"7512 Kingswood Ct",
    "sg:city":"Fort Worth",
    "sg:classifiers":[
        {
            "category":"Professional",
            "subcategory":"Secretarial Services",
            "type":"Services"
        }
    ],
    "sg:phone":"+1 817 656 8440",
    "sg:postcode":"76180",
    "sg:province":"TX",
    "sg:tags":[
        "typing"
    ],
    "wof:name":"Atypical Typing",
    "wof:placetype":"venue"
},
  "geometry": {"coordinates":[-97.21865,32.882946],"type":"Point"}
}