{
  "type": "Feature",
  "properties": {
    "iso:country":"US",
    "sg:address":"8560 Katy Fwy",
    "sg:city":"Houston",
    "sg:classifiers":[
        {
            "category":"Professional",
            "type":"Services"
        }
    ],
    "sg:phone":"+1 713 827 6100",
    "sg:postcode":"77024",
    "sg:province":"TX",
    "wof:name":"International Support Center",
    "wof:placetype":"venue"
},
  "geometry": {"coordinates":[-95.493469,29.784277],"type":"Point"}
}