{
  "type": "Feature",
  "properties": {
    "iso:country":"US",
    "sg:address":"1201 Lake Woodlands Dr",
    "sg:city":"Spring",
    "sg:classifiers":[
        {
            "category":"Bars & Pubs",
            "subcategory":"Wine Bar",
            "type":"Food & Drink"
        }
    ],
    "sg:menulink":"http://www.allmenus.com/tx/southeast-montgomery/11921-flemings/menu/",
    "sg:phone":"+1 281 362 0103",
    "sg:postcode":"77380",
    "sg:province":"TX",
    "sg:tags":[
        "american",
        "steakhouse"
    ],
    "wof:name":"Fleming's Prime Steakhouse & Wine Bar",
    "wof:placetype":"venue"
},
  "geometry": {"coordinates":[-95.45437200000001,30.166081],"type":"Point"}
}