{
  "type": "Feature",
  "properties": {
    "iso:country":"US",
    "sg:address":"301 S Porch St",
    "sg:city":"Tioga",
    "sg:classifiers":[
        {
            "category":"Organizations",
            "subcategory":"Religious Organization",
            "type":"Services"
        }
    ],
    "sg:phone":"+1 940 437 2500",
    "sg:postcode":"76271",
    "sg:province":"TX",
    "sg:tags":[
        "church"
    ],
    "wof:name":"Tioga United Methodist Church",
    "wof:placetype":"venue"
},
  "geometry": {"coordinates":[-96.91752,33.462936],"type":"Point"}
}