{
  "type": "Feature",
  "properties": {
    "iso:country":"US",
    "sg:address":"3515 Ave L",
    "sg:city":"Nederland",
    "sg:classifiers":[
        {
            "category":"Retail",
            "subcategory":"Animal Services",
            "type":"Services"
        }
    ],
    "sg:phone":"+1 409 729 7387",
    "sg:postcode":"77627",
    "sg:province":"TX",
    "sg:tags":[
        "pet",
        "boarding",
        "sitting"
    ],
    "wof:name":"Triangle Pet Sitters",
    "wof:placetype":"venue"
},
  "geometry": {"coordinates":[-93.995132,29.949704],"type":"Point"}
}