{
  "type": "Feature",
  "properties": {
    "iso:country":"US",
    "sg:address":"824 S Jackson St",
    "sg:city":"Jacksonville",
    "sg:classifiers":[
        {
            "category":"Travel",
            "subcategory":"Hotels & Motels",
            "type":"Entertainment"
        }
    ],
    "sg:phone":"+1 903 586 2255",
    "sg:postcode":"75766",
    "sg:province":"TX",
    "wof:name":"Pine Lodge Motel",
    "wof:placetype":"venue"
},
  "geometry": {"coordinates":[-95.26730499999999,31.957629],"type":"Point"}
}