{
  "type": "Feature",
  "properties": {
    "iso:country":"US",
    "sg:address":"1410 Waco Rd",
    "sg:city":"Belton",
    "sg:classifiers":[
        {
            "category":"Recreation",
            "subcategory":"Amusement Park",
            "type":"Entertainment"
        }
    ],
    "sg:phone":"+1 254 939 0366",
    "sg:postcode":"76513",
    "sg:province":"TX",
    "wof:name":"Summer Fun USA",
    "wof:placetype":"venue"
},
  "geometry": {"coordinates":[-97.443023,31.066206],"type":"Point"}
}