{
  "type": "Feature",
  "properties": {
    "iso:country":"US",
    "sg:address":"2845 Ridge Rd",
    "sg:city":"Rockwall",
    "sg:classifiers":[
        {
            "category":"Shopping",
            "type":"Retail Goods"
        }
    ],
    "sg:phone":"+1 972 771 4559",
    "sg:postcode":"75032",
    "sg:province":"TX",
    "sg:tags":[
        "picture",
        "frame",
        "merchandise",
        "repair"
    ],
    "wof:name":"Art Frame Craft",
    "wof:placetype":"venue"
},
  "geometry": {"coordinates":[-96.473894,32.88631],"type":"Point"}
}