{
  "type": "Feature",
  "properties": {
    "iso:country":"US",
    "sg:address":"511 Cozby St N",
    "sg:city":"Benbrook",
    "sg:classifiers":[
        {
            "category":"Restaurant",
            "type":"Food & Drink"
        }
    ],
    "sg:phone":"+1 817 738 6996",
    "sg:postcode":"76126",
    "sg:province":"TX",
    "wof:name":"Tin Star",
    "wof:placetype":"venue"
},
  "geometry": {"coordinates":[-97.460938,32.677658],"type":"Point"}
}