{
  "type": "Feature",
  "properties": {
    "iso:country":"US",
    "sg:address":"1131-08 Uptown Park Blvd",
    "sg:city":"Houston",
    "sg:classifiers":[
        {
            "category":"Shopping",
            "subcategory":"Clothing, Apparel, & Fashions",
            "type":"Retail Goods"
        }
    ],
    "sg:phone":"+1 713 850 7107",
    "sg:postcode":"77056",
    "sg:province":"TX",
    "sg:tags":[
        "men's",
        "clothing",
        "women's"
    ],
    "sg:website":"www.universitycoop.com",
    "wof:name":"University Co-op",
    "wof:placetype":"venue"
},
  "geometry": {"coordinates":[-95.457649,29.755909],"type":"Point"}
}