{
  "type": "Feature",
  "properties": {
    "iso:country":"US",
    "sg:address":"7400 Blanco Rd",
    "sg:city":"San Antonio",
    "sg:classifiers":[
        {
            "category":"Wholesale",
            "subcategory":"Metals & Minerals",
            "type":"Manufacturing & Wholesale Goods"
        }
    ],
    "sg:phone":"+1 210 979 8484",
    "sg:postcode":"78216",
    "sg:province":"TX",
    "sg:tags":[
        "center"
    ],
    "wof:name":"Leal Steel and Wire",
    "wof:placetype":"venue"
},
  "geometry": {"coordinates":[-98.505348,29.527708],"type":"Point"}
}