{
  "type": "Feature",
  "properties": {
    "iso:country":"US",
    "sg:address":"6011 Callaghan Rd",
    "sg:city":"San Antonio",
    "sg:classifiers":[
        {
            "category":"Shopping",
            "subcategory":"Florist",
            "type":"Retail Goods"
        }
    ],
    "sg:phone":"+1 210 684 1000",
    "sg:postcode":"78228",
    "sg:province":"TX",
    "wof:name":"Rolling Ridge Florist",
    "wof:placetype":"venue"
},
  "geometry": {"coordinates":[-98.576194,29.487594],"type":"Point"}
}