{
  "type": "Feature",
  "properties": {
    "iso:country":"US",
    "sg:address":"1018 E 4th St",
    "sg:city":"Fort Worth",
    "sg:classifiers":[
        {
            "category":"Restaurant",
            "type":"Food & Drink"
        }
    ],
    "sg:phone":"+1 817 338 4032",
    "sg:postcode":"76102",
    "sg:province":"TX",
    "sg:tags":[
        "drinking",
        "eating"
    ],
    "wof:name":"Jeans Place",
    "wof:placetype":"venue"
},
  "geometry": {"coordinates":[-97.32310200000001,32.758316],"type":"Point"}
}