{
  "type": "Feature",
  "properties": {
    "iso:country":"US",
    "sg:address":"15040 de Ville Pl",
    "sg:city":"San Antonio",
    "sg:classifiers":[
        {
            "category":"Real Estate",
            "subcategory":"Real Estate Agent",
            "type":"Services"
        }
    ],
    "sg:phone":"+1 210 698 0584",
    "sg:postcode":"78248",
    "sg:province":"TX",
    "wof:name":"Wayne S Curtis Real Estate",
    "wof:placetype":"venue"
},
  "geometry": {"coordinates":[-98.525102,29.579532],"type":"Point"}
}