{
  "type": "Feature",
  "properties": {
    "iso:country":"US",
    "sg:address":"706 Everest St",
    "sg:city":"San Antonio",
    "sg:classifiers":[
        {
            "category":"Shopping",
            "subcategory":"Books",
            "type":"Retail Goods"
        }
    ],
    "sg:phone":"+1 210 828 6114",
    "sg:postcode":"78209",
    "sg:province":"TX",
    "wof:name":"American Opinion Book Store",
    "wof:placetype":"venue"
},
  "geometry": {"coordinates":[-98.470799,29.509888],"type":"Point"}
}