{
  "type": "Feature",
  "properties": {
    "iso:country":"US",
    "sg:address":"17950 Preston Rd",
    "sg:city":"Dallas",
    "sg:classifiers":[
        {
            "category":"Banks & Credit Unions",
            "subcategory":"Bank",
            "type":"Services"
        }
    ],
    "sg:phone":"+1 972 239 4100",
    "sg:postcode":"75252",
    "sg:province":"TX",
    "sg:tags":[
        "loan",
        "broker",
        "real estate"
    ],
    "sg:website":"www.prestonwoodmortgage.com",
    "wof:name":"Prestonwood Mortgage LP",
    "wof:placetype":"venue"
},
  "geometry": {"coordinates":[-96.799648,32.994585],"type":"Point"}
}