{
  "type": "Feature",
  "properties": {
    "iso:country":"US",
    "sg:address":"1610 N K St",
    "sg:city":"Midland",
    "sg:classifiers":[
        {
            "category":"Utilities",
            "subcategory":"Telephone",
            "type":"Services"
        }
    ],
    "sg:phone":"+1 432 699 6369",
    "sg:postcode":"79701",
    "sg:province":"TX",
    "sg:tags":[
        "telecommunication"
    ],
    "wof:name":"MCI",
    "wof:placetype":"venue"
},
  "geometry": {"coordinates":[-102.098311,32.010664],"type":"Point"}
}