{
  "type": "Feature",
  "properties": {
    "iso:country":"US",
    "sg:address":"24485 W Country Ln",
    "sg:city":"Hockley",
    "sg:classifiers":[
        {
            "category":"Shopping",
            "subcategory":"Clothing, Apparel, & Fashions",
            "type":"Retail Goods"
        }
    ],
    "sg:phone":"+1 936 372 5163",
    "sg:postcode":"77447",
    "sg:province":"TX",
    "wof:name":"Patricia M Cortez",
    "wof:placetype":"venue"
},
  "geometry": {"coordinates":[-95.81289700000001,30.168046],"type":"Point"}
}