{
  "type": "Feature",
  "properties": {
    "iso:country":"US",
    "sg:address":"1400 W Panola St",
    "sg:city":"Carthage",
    "sg:classifiers":[
        {
            "category":"Home & Garden",
            "subcategory":"Hardware",
            "type":"Retail Goods"
        }
    ],
    "sg:phone":"+1 903 693 3222",
    "sg:postcode":"75633",
    "sg:province":"TX",
    "sg:tags":[
        "mach",
        "nonresidential"
    ],
    "wof:name":"E T P S East Eastex Plty Sup",
    "wof:placetype":"venue"
},
  "geometry": {"coordinates":[-94.36220400000001,32.159453],"type":"Point"}
}