{
  "type": "Feature",
  "properties": {
    "iso:country":"US",
    "sg:address":"17540 Stuebner Airline Rd",
    "sg:city":"Spring",
    "sg:classifiers":[
        {
            "category":"Organizations",
            "subcategory":"Religious Organization",
            "type":"Services"
        }
    ],
    "sg:phone":"+1 281 370 7691",
    "sg:postcode":"77379",
    "sg:province":"TX",
    "wof:name":"Philippine-American Baptist Ch",
    "wof:placetype":"venue"
},
  "geometry": {"coordinates":[-95.530677,30.027571],"type":"Point"}
}