{
  "type": "Feature",
  "properties": {
    "iso:country":"US",
    "sg:address":"421 Church St",
    "sg:city":"Grapevine",
    "sg:classifiers":[
        {
            "category":"Recreation",
            "type":"Entertainment"
        }
    ],
    "sg:phone":"+1 817 251 9351",
    "sg:postcode":"76051",
    "sg:province":"TX",
    "sg:tags":[
        "club",
        "membership"
    ],
    "wof:name":"Friends of The Grapevine",
    "wof:placetype":"venue"
},
  "geometry": {"coordinates":[-97.079888,32.936833],"type":"Point"}
}