{
  "type": "Feature",
  "properties": {
    "iso:country":"US",
    "sg:address":"55 2nd St",
    "sg:city":"Maxwell",
    "sg:classifiers":[
        {
            "category":"Manufacturing",
            "subcategory":"Tools & Machinery",
            "type":"Manufacturing & Wholesale Goods"
        }
    ],
    "sg:phone":"+1 512 339 6765",
    "sg:postcode":"78656",
    "sg:province":"TX",
    "sg:tags":[
        "equipment",
        "lighting"
    ],
    "sg:website":"www.limelite.com",
    "wof:name":"E I Products",
    "wof:placetype":"venue"
},
  "geometry": {"coordinates":[-97.797546,29.881473],"type":"Point"}
}