{
  "type": "Feature",
  "properties": {
    "iso:country":"US",
    "sg:address":"7130 Cook Rd",
    "sg:city":"Houston",
    "sg:classifiers":[
        {
            "category":"Education",
            "subcategory":"Special Training",
            "type":"Public Place"
        }
    ],
    "sg:phone":"+1 281 498 0465",
    "sg:postcode":"77072",
    "sg:province":"TX",
    "sg:tags":[
        "educational"
    ],
    "wof:name":"Bible Correspondence Course",
    "wof:placetype":"venue"
},
  "geometry": {"coordinates":[-95.596096,29.699704],"type":"Point"}
}