{
  "type": "Feature",
  "properties": {
    "iso:country":"US",
    "sg:address":"5322 Elm St",
    "sg:city":"Houston",
    "sg:classifiers":[
        {
            "category":"Taxi",
            "type":"Transportation"
        },
        {
            "category":"Professional",
            "subcategory":"Business Services",
            "type":"Services"
        },
        {
            "category":"Government",
            "subcategory":"Post Office",
            "type":"Public Place"
        }
    ],
    "sg:phone":"+1 713 664 9999",
    "sg:postcode":"77081",
    "sg:province":"TX",
    "sg:tags":[
        "delivery",
        "courier"
    ],
    "sg:website":"http://www.a1delivery.com",
    "wof:name":"A-1 Delivery Services",
    "wof:placetype":"venue"
},
  "geometry": {"coordinates":[-95.4729,29.712999],"type":"Point"}
}