{
  "type": "Feature",
  "properties": {
    "iso:country":"US",
    "sg:address":"1601 Rice Dr",
    "sg:city":"Lufkin",
    "sg:classifiers":[
        {
            "category":"Education",
            "subcategory":"School",
            "type":"Public Place"
        }
    ],
    "sg:phone":"+1 936 632 1905",
    "sg:postcode":"75901",
    "sg:province":"TX",
    "wof:name":"Harmony Christian School",
    "wof:placetype":"venue"
},
  "geometry": {"coordinates":[-94.71025400000001,31.306535],"type":"Point"}
}