{
  "type": "Feature",
  "properties": {
    "iso:country":"US",
    "sg:address":"150 Interloop Rd",
    "sg:city":"San Antonio",
    "sg:classifiers":[
        {
            "category":"Autos & Motor Vehicles",
            "subcategory":"Auto Supplies",
            "type":"Retail Goods"
        }
    ],
    "sg:phone":"+1 210 342 9330",
    "sg:postcode":"78216",
    "sg:province":"TX",
    "sg:tags":[
        "automobile",
        "parts"
    ],
    "wof:name":"Northside Auto Parts",
    "wof:placetype":"venue"
},
  "geometry": {"coordinates":[-98.503214,29.494335],"type":"Point"}
}