{
  "type": "Feature",
  "properties": {
    "iso:country":"US",
    "sg:address":"323 Oblate Dr",
    "sg:city":"San Antonio",
    "sg:classifiers":[
        {
            "category":"Organizations",
            "subcategory":"Religious Organization",
            "type":"Services"
        }
    ],
    "sg:phone":"+1 210 736 1685",
    "sg:postcode":"78216",
    "sg:province":"TX",
    "sg:website":"www.oblatemissions.com",
    "wof:name":"Oblate Missions",
    "wof:placetype":"venue"
},
  "geometry": {"coordinates":[-98.50075099999999,29.504418],"type":"Point"}
}