{
  "type": "Feature",
  "properties": {
    "iso:country":"US",
    "sg:address":"8627 Castlecreek Ct",
    "sg:city":"Fort Worth",
    "sg:classifiers":[
        {
            "category":"Professional",
            "type":"Services"
        },
        {
            "category":"Travel",
            "subcategory":"Travel Agent",
            "type":"Entertainment"
        }
    ],
    "sg:phone":"+1 817 788 8299",
    "sg:postcode":"76180",
    "sg:province":"TX",
    "sg:tags":[
        "agency",
        "bureau"
    ],
    "wof:name":"Senior Sojourns",
    "wof:placetype":"venue"
},
  "geometry": {"coordinates":[-97.19846699999999,32.907155],"type":"Point"}
}