{
  "type": "Feature",
  "properties": {
    "iso:country":"US",
    "sg:address":"9137 Turrentine Dr",
    "sg:city":"El Paso",
    "sg:classifiers":[
        {
            "category":"Organizations",
            "subcategory":"Membership Organization",
            "type":"Services"
        }
    ],
    "sg:phone":"+1 915 598 8903",
    "sg:postcode":"79925",
    "sg:province":"TX",
    "wof:name":"Eta PI Omega Education &",
    "wof:placetype":"venue"
},
  "geometry": {"coordinates":[-106.3657,31.778731],"type":"Point"}
}