{
  "type": "Feature",
  "properties": {
    "iso:country":"US",
    "sg:address":"16402 Co Rd 3302",
    "sg:city":"Brownsboro",
    "sg:classifiers":[
        {
            "category":"Farming",
            "subcategory":"Livestock Farm",
            "type":"Manufacturing & Wholesale Goods"
        }
    ],
    "sg:phone":"+1 903 852 5355",
    "sg:postcode":"75756",
    "sg:province":"TX",
    "sg:tags":[
        "beef",
        "feedlot",
        "cattle"
    ],
    "wof:name":"River Hill Farms Inc",
    "wof:placetype":"venue"
},
  "geometry": {"coordinates":[-95.584446,32.33561],"type":"Point"}
}