{
  "type": "Feature",
  "properties": {
    "iso:country":"US",
    "sg:address":"3224 Burke Rd",
    "sg:city":"Pasadena",
    "sg:classifiers":[
        {
            "category":"Real Estate",
            "subcategory":"Real Estate Operator",
            "type":"Services"
        }
    ],
    "sg:phone":"+1 713 944 3371",
    "sg:postcode":"77504",
    "sg:province":"TX",
    "sg:tags":[
        "apartment"
    ],
    "wof:name":"Bayshore Park Apartments",
    "wof:placetype":"venue"
},
  "geometry": {"coordinates":[-95.186699,29.663099],"type":"Point"}
}