{
  "type": "Feature",
  "properties": {
    "iso:country":"US",
    "sg:address":"117 E Lufkin Ave",
    "sg:city":"Lufkin",
    "sg:classifiers":[
        {
            "category":"Professional",
            "subcategory":"Lawyer & Legal Services",
            "type":"Services"
        }
    ],
    "sg:phone":"+1 936 639 0007",
    "sg:postcode":"75901",
    "sg:province":"TX",
    "sg:tags":[
        "attorney"
    ],
    "wof:name":"Wayne D Haglund",
    "wof:placetype":"venue"
},
  "geometry": {"coordinates":[-94.72865,31.339115],"type":"Point"}
}