{
  "type": "Feature",
  "properties": {
    "iso:country":"US",
    "sg:address":"3807 Graustark St",
    "sg:city":"Houston",
    "sg:classifiers":[
        {
            "category":"Shopping",
            "subcategory":"Books",
            "type":"Retail Goods"
        }
    ],
    "sg:phone":"+1 713 525 3806",
    "sg:postcode":"77006",
    "sg:province":"TX",
    "sg:tags":[
        "textbook"
    ],
    "wof:name":"St Thomas University Bookstore",
    "wof:placetype":"venue"
},
  "geometry": {"coordinates":[-95.394649,29.737888],"type":"Point"}
}