{
  "type": "Feature",
  "properties": {
    "iso:country":"US",
    "sg:address":"3434 W Plantation Dr",
    "sg:city":"La Porte",
    "sg:classifiers":[
        {
            "category":"Professional",
            "subcategory":"Management & Consulting",
            "type":"Services"
        }
    ],
    "sg:phone":"+1 281 479 4192",
    "sg:postcode":"77571",
    "sg:province":"TX",
    "sg:tags":[
        "retail",
        "direct",
        "sales"
    ],
    "wof:name":"Yulizas",
    "wof:placetype":"venue"
},
  "geometry": {"coordinates":[-95.10076599999999,29.658521],"type":"Point"}
}