{
  "type": "Feature",
  "properties": {
    "iso:country":"US",
    "sg:address":"4403 Bilboa Dr",
    "sg:city":"Austin",
    "sg:classifiers":[
        {
            "category":"Shopping",
            "subcategory":"Jewelry",
            "type":"Retail Goods"
        }
    ],
    "sg:phone":"+1 512 345 5424",
    "sg:postcode":"78759",
    "sg:province":"TX",
    "wof:name":"Rudy M Moreno Jeweler Gemologi",
    "wof:placetype":"venue"
},
  "geometry": {"coordinates":[-97.74004100000001,30.405076],"type":"Point"}
}