{
  "type": "Feature",
  "properties": {
    "iso:country":"US",
    "sg:address":"7111 Greenbrook Ln",
    "sg:city":"Dallas",
    "sg:classifiers":[
        {
            "category":"Professional",
            "subcategory":"Management & Consulting",
            "type":"Services"
        }
    ],
    "sg:phone":"+1 214 824 8393",
    "sg:postcode":"75214",
    "sg:province":"TX",
    "wof:name":"Benedetto Distributors Inc",
    "wof:placetype":"venue"
},
  "geometry": {"coordinates":[-96.735192,32.846088],"type":"Point"}
}