{
  "type": "Feature",
  "properties": {
    "iso:country":"US",
    "sg:address":"2401 Green Oak Dr",
    "sg:city":"Humble",
    "sg:classifiers":[
        {
            "category":"Social Services",
            "subcategory":"Adult Care",
            "type":"Services"
        }
    ],
    "sg:phone":"+1 281 359 8959",
    "sg:postcode":"77339",
    "sg:province":"TX",
    "sg:tags":[
        "home",
        "residential"
    ],
    "wof:name":"Atria of Kingwood",
    "wof:placetype":"venue"
},
  "geometry": {"coordinates":[-95.23663500000001,30.04966],"type":"Point"}
}