{
  "type": "Feature",
  "properties": {
    "iso:country":"US",
    "sg:address":"616 Deckhouse Dr",
    "sg:city":"Leander",
    "sg:classifiers":[
        {
            "category":"Professional",
            "subcategory":"Accounting & Tax Preparation",
            "type":"Services"
        }
    ],
    "sg:phone":"+1 512 267 2881",
    "sg:postcode":"78645",
    "sg:province":"TX",
    "wof:name":"Jeanne Calvi Inc",
    "wof:placetype":"venue"
},
  "geometry": {"coordinates":[-98.00582799999999,30.382166],"type":"Point"}
}