{
  "type": "Feature",
  "properties": {
    "iso:country":"US",
    "sg:address":"3614 N Main St",
    "sg:city":"Victoria",
    "sg:phone":"+1 361 578 5287",
    "sg:postcode":"77901",
    "sg:province":"TX",
    "wof:name":"Kats Nail Salon",
    "wof:placetype":"venue"
},
  "geometry": {"coordinates":[-97.008011,28.827677],"type":"Point"}
}