{
  "type": "Feature",
  "properties": {
    "iso:country":"US",
    "sg:address":"209 N Esplanade St",
    "sg:city":"Cuero",
    "sg:classifiers":[
        {
            "category":"Banks & Credit Unions",
            "subcategory":"Investment Brokerage",
            "type":"Services"
        }
    ],
    "sg:phone":"+1 361 275 9702",
    "sg:postcode":"77954",
    "sg:province":"TX",
    "sg:tags":[
        "stock",
        "bond"
    ],
    "sg:website":"www.edwardsjones.com",
    "wof:name":"Edward Jones Co",
    "wof:placetype":"venue"
},
  "geometry": {"coordinates":[-97.29082099999999,29.092024],"type":"Point"}
}