{
  "type": "Feature",
  "properties": {
    "iso:country":"US",
    "sg:address":"10326 Sagevale Ln",
    "sg:city":"Houston",
    "sg:classifiers":[
        {
            "category":"Professional",
            "subcategory":"Research",
            "type":"Services"
        }
    ],
    "sg:phone":"+1 281 484 0727",
    "sg:postcode":"77089",
    "sg:province":"TX",
    "sg:tags":[
        "nonphysical",
        "commercial"
    ],
    "wof:name":"Betsee F Valladolid",
    "wof:placetype":"venue"
},
  "geometry": {"coordinates":[-95.23748399999999,29.598135],"type":"Point"}
}