{
  "type": "Feature",
  "properties": {
    "iso:country":"US",
    "sg:address":"706 West Ave",
    "sg:city":"Austin",
    "sg:classifiers":[
        {
            "category":"Health Services",
            "subcategory":"Doctor",
            "type":"Services"
        }
    ],
    "sg:phone":"+1 512 478 4653",
    "sg:postcode":"78701",
    "sg:province":"TX",
    "wof:name":"James T Cordera DDS",
    "wof:placetype":"venue"
},
  "geometry": {"coordinates":[-97.750001,30.272067],"type":"Point"}
}