{
  "type": "Feature",
  "properties": {
    "iso:country":"US",
    "sg:address":"3117 Kingsbury Ave",
    "sg:city":"Fort Worth",
    "sg:classifiers":[
        {
            "category":"Manufacturing",
            "subcategory":"Retail Goods",
            "type":"Manufacturing & Wholesale Goods"
        }
    ],
    "sg:phone":"+1 817 595 7498",
    "sg:postcode":"76118",
    "sg:province":"TX",
    "sg:tags":[
        "product",
        "mfg"
    ],
    "wof:name":"All In One Trade Show",
    "wof:placetype":"venue"
},
  "geometry": {"coordinates":[-97.23367,32.808885],"type":"Point"}
}