{
  "type": "Feature",
  "properties": {
    "iso:country":"US",
    "sg:address":"700 N Pearl St",
    "sg:city":"Dallas",
    "sg:classifiers":[
        {
            "category":"Banks & Credit Unions",
            "subcategory":"Investment Brokerage",
            "type":"Services"
        }
    ],
    "sg:phone":"+1 214 953 0066",
    "sg:postcode":"75201",
    "sg:province":"TX",
    "sg:tags":[
        "funds",
        "mutual"
    ],
    "sg:website":"www.mutuals.com",
    "wof:name":"MUTUALS.COM",
    "wof:placetype":"venue"
},
  "geometry": {"coordinates":[-96.796841,32.787296],"type":"Point"}
}