{
  "type": "Feature",
  "properties": {
    "iso:country":"US",
    "sg:address":"1430 Valwood Pkwy",
    "sg:city":"Carrollton",
    "sg:classifiers":[
        {
            "category":"Government",
            "subcategory":"Office",
            "type":"Public Place"
        }
    ],
    "sg:phone":"+1 972 484 9863",
    "sg:postcode":"75006",
    "sg:province":"TX",
    "sg:tags":[
        "control",
        "flood",
        "district",
        "village"
    ],
    "wof:name":"Valwood Improvement Authority",
    "wof:placetype":"venue"
},
  "geometry": {"coordinates":[-96.917185,32.938625],"type":"Point"}
}