{
  "type": "Feature",
  "properties": {
    "iso:country":"US",
    "sg:address":"8104 US Hwy 80",
    "sg:city":"Fort Worth",
    "sg:classifiers":[
        {
            "category":"Bars & Pubs",
            "type":"Food & Drink"
        }
    ],
    "sg:phone":"+1 817 244 4690",
    "sg:postcode":"76116",
    "sg:province":"TX",
    "sg:tags":[
        "drinking"
    ],
    "wof:name":"Anthonys",
    "wof:placetype":"venue"
},
  "geometry": {"coordinates":[-97.457066,32.723783],"type":"Point"}
}