{
  "type": "Feature",
  "properties": {
    "iso:country":"US",
    "sg:address":"5212 Joe Sayers Ave",
    "sg:city":"Austin",
    "sg:classifiers":[
        {
            "category":"Building & Trades",
            "subcategory":"Equipment Rental",
            "type":"Services"
        }
    ],
    "sg:phone":"+1 512 377 2665",
    "sg:postcode":"78756",
    "sg:province":"TX",
    "sg:tags":[
        "party",
        "supply"
    ],
    "wof:name":"Righteous 'Ritas",
    "wof:placetype":"venue"
},
  "geometry": {"coordinates":[-97.737193,30.324641],"type":"Point"}
}