{
  "type": "Feature",
  "properties": {
    "iso:country":"US",
    "sg:address":"626 W Alabama St",
    "sg:city":"Houston",
    "sg:classifiers":[
        {
            "category":"Manufacturing",
            "subcategory":"Tools & Machinery",
            "type":"Manufacturing & Wholesale Goods"
        }
    ],
    "sg:phone":"+1 713 942 7077",
    "sg:postcode":"77006",
    "sg:province":"TX",
    "sg:tags":[
        "aid",
        "precision",
        "grinding",
        "mfg"
    ],
    "wof:name":"Quality Grinding Aids",
    "wof:placetype":"venue"
},
  "geometry": {"coordinates":[-95.387276,29.738851],"type":"Point"}
}