{
  "type": "Feature",
  "properties": {
    "iso:country":"US",
    "sg:address":"2714 Park Meadows Ave",
    "sg:city":"Deer Park",
    "sg:classifiers":[
        {
            "category":"Professional",
            "subcategory":"Management & Consulting",
            "type":"Services"
        }
    ],
    "sg:phone":"+1 281 479 8158",
    "sg:postcode":"77536",
    "sg:province":"TX",
    "sg:tags":[
        "support"
    ],
    "wof:name":"Adrienne Windsor",
    "wof:placetype":"venue"
},
  "geometry": {"coordinates":[-95.108023,29.684838],"type":"Point"}
}