{
  "type": "Feature",
  "properties": {
    "iso:country":"US",
    "sg:address":"1235 N Business 45",
    "sg:city":"Corsicana",
    "sg:classifiers":[
        {
            "category":"Professional",
            "type":"Services"
        }
    ],
    "sg:phone":"+1 903 874 7546",
    "sg:postcode":"75110",
    "sg:province":"TX",
    "sg:tags":[
        "establishment"
    ],
    "wof:name":"Reed J C Welding",
    "wof:placetype":"venue"
},
  "geometry": {"coordinates":[-96.464105,32.111805],"type":"Point"}
}