{
  "type": "Feature",
  "properties": {
    "iso:country":"US",
    "sg:address":"4619 Fort Crockett Blvd",
    "sg:city":"Galveston",
    "sg:classifiers":[
        {
            "category":"Professional",
            "type":"Services"
        }
    ],
    "sg:phone":"+1 409 762 8558",
    "sg:postcode":"77551",
    "sg:province":"TX",
    "wof:name":"Triple 777",
    "wof:placetype":"venue"
},
  "geometry": {"coordinates":[-94.815228,29.275015],"type":"Point"}
}