{
  "type": "Feature",
  "properties": {
    "iso:country":"US",
    "sg:address":"5721 E Yandell Dr",
    "sg:city":"El Paso",
    "sg:classifiers":[
        {
            "category":"Social Services",
            "subcategory":"Job Training",
            "type":"Services"
        }
    ],
    "sg:phone":"+1 915 778 1796",
    "sg:postcode":"79925",
    "sg:province":"TX",
    "sg:tags":[
        "rehabilitation"
    ],
    "wof:name":"Diamond Rehab Ctr",
    "wof:placetype":"venue"
},
  "geometry": {"coordinates":[-106.42080300000001,31.780155],"type":"Point"}
}