{
  "type": "Feature",
  "properties": {
    "iso:country":"US",
    "sg:address":"4928 Miller Ave",
    "sg:city":"Fort Worth",
    "sg:classifiers":[
        {
            "category":"Organizations",
            "subcategory":"Religious Organization",
            "type":"Services"
        }
    ],
    "sg:phone":"+1 817 534 8700",
    "sg:postcode":"76119",
    "sg:province":"TX",
    "sg:tags":[
        "church"
    ],
    "wof:name":"First Missionary Baptist Chr",
    "wof:placetype":"venue"
},
  "geometry": {"coordinates":[-97.263254,32.689186],"type":"Point"}
}