{
  "type": "Feature",
  "properties": {
    "iso:country":"US",
    "sg:address":"3100 Ammunition Dr",
    "sg:city":"Austin",
    "sg:classifiers":[
        {
            "category":"Wholesale",
            "subcategory":"Jewelry",
            "type":"Manufacturing & Wholesale Goods"
        },
        {
            "category":"Shopping",
            "subcategory":"Crafts & Fabrics",
            "type":"Retail Goods"
        }
    ],
    "sg:phone":"+1 512 282 1763",
    "sg:postcode":"78748",
    "sg:province":"TX",
    "sg:tags":[
        "bead",
        "beads-wholesale",
        "manufacturer"
    ],
    "wof:name":"Elizabeth Adkins",
    "wof:placetype":"venue"
},
  "geometry": {"coordinates":[-97.850983,30.166109],"type":"Point"}
}