{
  "type": "Feature",
  "properties": {
    "iso:country":"US",
    "sg:address":"1332 Virgie Joe Dr",
    "sg:city":"Mesquite",
    "sg:classifiers":[
        {
            "category":"Building & Trades",
            "subcategory":"Cleaning & Sanitation",
            "type":"Services"
        }
    ],
    "sg:phone":"+1 972 552 3444",
    "sg:postcode":"75149",
    "sg:province":"TX",
    "sg:tags":[
        "window"
    ],
    "wof:name":"Cactus Window Cleaning",
    "wof:placetype":"venue"
},
  "geometry": {"coordinates":[-96.57641599999999,32.750321],"type":"Point"}
}