{
  "type": "Feature",
  "properties": {
    "iso:country":"US",
    "sg:address":"300 E Broadway St",
    "sg:city":"Clarksville",
    "sg:classifiers":[
        {
            "category":"Insurance",
            "subcategory":"Insurance Agent",
            "type":"Services"
        }
    ],
    "sg:phone":"+1 903 427 2221",
    "sg:postcode":"75426",
    "sg:province":"TX",
    "wof:name":"Goodman Insurance Inc",
    "wof:placetype":"venue"
},
  "geometry": {"coordinates":[-95.04754699999999,33.612108],"type":"Point"}
}