{
  "type": "Feature",
  "properties": {
    "iso:country":"US",
    "sg:address":"6655 Co Rd 118",
    "sg:city":"Kaufman",
    "sg:classifiers":[
        {
            "category":"Farming",
            "subcategory":"Livestock Farm",
            "type":"Manufacturing & Wholesale Goods"
        }
    ],
    "sg:phone":"+1 972 932 3452",
    "sg:postcode":"75142",
    "sg:province":"TX",
    "sg:tags":[
        "beef",
        "feedlot",
        "cattle"
    ],
    "wof:name":"W K Welding",
    "wof:placetype":"venue"
},
  "geometry": {"coordinates":[-96.12194,32.584009],"type":"Point"}
}