{
  "type": "Feature",
  "properties": {
    "iso:country":"US",
    "sg:address":"2710 Raintree St",
    "sg:city":"Sugar Land",
    "sg:classifiers":[
        {
            "category":"Insurance",
            "subcategory":"Insurance Agent",
            "type":"Services"
        }
    ],
    "sg:phone":"+1 281 313 2296",
    "sg:postcode":"77478",
    "sg:province":"TX",
    "wof:name":"INB Engineering",
    "wof:placetype":"venue"
},
  "geometry": {"coordinates":[-95.60707499999999,29.602051],"type":"Point"}
}