{
  "type": "Feature",
  "properties": {
    "iso:country":"US",
    "sg:address":"4001 Fannin St",
    "sg:city":"Houston",
    "sg:classifiers":[
        {
            "category":"Professional",
            "type":"Services"
        },
        {
            "category":"Recreation",
            "type":"Entertainment"
        }
    ],
    "sg:phone":"+1 713 385 7781",
    "sg:postcode":"77004",
    "sg:province":"TX",
    "sg:tags":[
        "astrologer"
    ],
    "wof:name":"Affordable Numerology",
    "wof:placetype":"venue"
},
  "geometry": {"coordinates":[-95.380629,29.735497],"type":"Point"}
}