{
  "type": "Feature",
  "properties": {
    "iso:country":"US",
    "sg:address":"215 E Fairview Dr",
    "sg:city":"Kingsville",
    "sg:classifiers":[
        {
            "category":"Building & Trades",
            "subcategory":"Construction",
            "type":"Services"
        }
    ],
    "sg:phone":"+1 361 221 9948",
    "sg:postcode":"78363",
    "sg:province":"TX",
    "sg:tags":[
        "hanging",
        "contractor"
    ],
    "wof:name":"Precision Painting",
    "wof:placetype":"venue"
},
  "geometry": {"coordinates":[-97.84609399999999,27.524188],"type":"Point"}
}