{
  "type": "Feature",
  "properties": {
    "iso:country":"US",
    "sg:address":"200 S Wayside Dr",
    "sg:city":"Houston",
    "sg:classifiers":[
        {
            "category":"Health Services",
            "subcategory":"Doctor",
            "type":"Services"
        }
    ],
    "sg:phone":"+1 713 926 0200",
    "sg:postcode":"77011",
    "sg:province":"TX",
    "sg:tags":[
        "dentist"
    ],
    "wof:name":"Empire Dental Center",
    "wof:placetype":"venue"
},
  "geometry": {"coordinates":[-95.306999,29.7355],"type":"Point"}
}