{
  "type": "Feature",
  "properties": {
    "iso:country":"US",
    "sg:address":"2007 S Goliad St",
    "sg:city":"Rockwall",
    "sg:classifiers":[
        {
            "category":"Home & Garden",
            "subcategory":"Building Materials",
            "type":"Retail Goods"
        }
    ],
    "sg:phone":"+1 972 771 9626",
    "sg:postcode":"75032",
    "sg:province":"TX",
    "sg:tags":[
        "paint"
    ],
    "wof:name":"Sherwin-Williams Paints",
    "wof:placetype":"venue"
},
  "geometry": {"coordinates":[-96.450255,32.909596],"type":"Point"}
}