{
  "type": "Feature",
  "properties": {
    "iso:country":"US",
    "sg:address":"102 Meadowview Rd",
    "sg:city":"Weatherford",
    "sg:classifiers":[
        {
            "category":"Education",
            "subcategory":"School",
            "type":"Public Place"
        }
    ],
    "sg:phone":"+1 817 598 2960",
    "sg:postcode":"76087",
    "sg:province":"TX",
    "wof:name":"Joe Tyson Jr High School",
    "wof:placetype":"venue"
},
  "geometry": {"coordinates":[-97.738356,32.766126],"type":"Point"}
}