{
  "type": "Feature",
  "properties": {
    "iso:country":"US",
    "sg:address":"2126 Co Rd 1143",
    "sg:city":"Tyler",
    "sg:classifiers":[
        {
            "category":"Retail",
            "subcategory":"Repair Shop",
            "type":"Services"
        },
        {
            "category":"Building & Trades",
            "subcategory":"Equipment Rental",
            "type":"Services"
        }
    ],
    "sg:phone":"+1 903 592 3651",
    "sg:postcode":"75704",
    "sg:province":"TX",
    "sg:tags":[
        "nonscheduled",
        "leasing",
        "charter",
        "air",
        "aircraft",
        "transportation"
    ],
    "sg:website":"www.was.com",
    "wof:name":"Wilkinson Aircraft Services",
    "wof:placetype":"venue"
},
  "geometry": {"coordinates":[-95.390879,32.355507],"type":"Point"}
}