{
  "type": "Feature",
  "properties": {
    "iso:country":"US",
    "sg:address":"10631 Stone Canyon Rd",
    "sg:city":"Dallas",
    "sg:classifiers":[
        {
            "category":"Freight",
            "type":"Transportation"
        }
    ],
    "sg:phone":"+1 214 696 5855",
    "sg:postcode":"75230",
    "sg:province":"TX",
    "sg:tags":[
        "mover"
    ],
    "wof:name":"Alexanders Moving & Storage",
    "wof:placetype":"venue"
},
  "geometry": {"coordinates":[-96.775126,32.891536],"type":"Point"}
}