{
  "type": "Feature",
  "properties": {
    "iso:country":"US",
    "sg:address":"1801 Shiloh Rd",
    "sg:city":"Tyler",
    "sg:classifiers":[
        {
            "category":"Organizations",
            "subcategory":"Religious Organization",
            "type":"Services"
        }
    ],
    "sg:phone":"+1 903 561 7992",
    "sg:postcode":"75703",
    "sg:province":"TX",
    "sg:tags":[
        "testament",
        "churches-church",
        "christ-new"
    ],
    "sg:website":"http://www.shilohroad.com",
    "wof:name":"Shiloh Road Church Of Christ",
    "wof:placetype":"venue"
},
  "geometry": {"coordinates":[-95.280428,32.295298],"type":"Point"}
}