{
  "type": "Feature",
  "properties": {
    "iso:country":"US",
    "sg:address":"20319 Sequoia Trce",
    "sg:city":"Spring",
    "sg:classifiers":[
        {
            "category":"Shopping",
            "subcategory":"Clothing, Apparel, & Fashions",
            "type":"Retail Goods"
        }
    ],
    "sg:phone":"+1 281 351 2346",
    "sg:postcode":"77379",
    "sg:province":"TX",
    "wof:name":"G B Western Wear",
    "wof:placetype":"venue"
},
  "geometry": {"coordinates":[-95.508066,30.062742],"type":"Point"}
}