{
  "type": "Feature",
  "properties": {
    "iso:country":"US",
    "sg:address":"15402 Hickory Dale St",
    "sg:city":"Cypress",
    "sg:classifiers":[
        {
            "category":"Structure",
            "subcategory":"Office Building",
            "type":"Public Place"
        }
    ],
    "sg:phone":"+1 281 898 0880",
    "sg:postcode":"77429",
    "sg:province":"TX",
    "sg:tags":[
        "park"
    ],
    "wof:name":"Rosherm Properties",
    "wof:placetype":"venue"
},
  "geometry": {"coordinates":[-95.700248,29.993872],"type":"Point"}
}