{
  "type": "Feature",
  "properties": {
    "iso:country":"US",
    "sg:address":"5600 E Loop 820 S",
    "sg:city":"Fort Worth",
    "sg:classifiers":[
        {
            "category":"Organizations",
            "subcategory":"Religious Organization",
            "type":"Services"
        }
    ],
    "sg:phone":"+1 817 561 0879",
    "sg:postcode":"76119",
    "sg:province":"TX",
    "sg:tags":[
        "church"
    ],
    "wof:name":"Southwestern District-Chrstn",
    "wof:placetype":"venue"
},
  "geometry": {"coordinates":[-97.241056,32.675364],"type":"Point"}
}