{
  "type": "Feature",
  "properties": {
    "iso:country":"US",
    "sg:address":"501 Tahoka Rd",
    "sg:city":"Brownfield",
    "sg:classifiers":[
        {
            "category":"Shopping",
            "subcategory":"Discount & Variety Stores",
            "type":"Retail Goods"
        },
        {
            "category":"Shopping",
            "subcategory":"Department Store",
            "type":"Retail Goods"
        }
    ],
    "sg:phone":"+1 806 637 0373",
    "sg:postcode":"79316",
    "sg:province":"TX",
    "sg:tags":[
        "shop"
    ],
    "wof:name":"Family Dollar Stores",
    "wof:placetype":"venue"
},
  "geometry": {"coordinates":[-102.270668,33.181084],"type":"Point"}
}