{
  "type": "Feature",
  "properties": {
    "iso:country":"US",
    "sg:address":"1903 N I- 35",
    "sg:city":"San Marcos",
    "sg:classifiers":[
        {
            "category":"Food & Beverages",
            "subcategory":"Groceries & Convenience Stores",
            "type":"Retail Goods"
        }
    ],
    "sg:phone":"+1 512 754 6611",
    "sg:postcode":"78666",
    "sg:province":"TX",
    "wof:name":"Texaco Food Mart 1",
    "wof:placetype":"venue"
},
  "geometry": {"coordinates":[-97.891407,29.92656],"type":"Point"}
}