{
  "type": "Feature",
  "properties": {
    "iso:country":"US",
    "sg:address":"13346 Bee St",
    "sg:city":"Farmers Branch",
    "sg:classifiers":[
        {
            "category":"Building & Trades",
            "subcategory":"Cleaning & Sanitation",
            "type":"Services"
        }
    ],
    "sg:phone":"+1 214 351 3039",
    "sg:postcode":"75234",
    "sg:province":"TX",
    "sg:tags":[
        "window"
    ],
    "wof:name":"Restoration Inc",
    "wof:placetype":"venue"
},
  "geometry": {"coordinates":[-96.89594099999999,32.925892],"type":"Point"}
}