{
  "type": "Feature",
  "properties": {
    "iso:country":"US",
    "sg:address":"7979 Skillman St",
    "sg:city":"Dallas",
    "sg:classifiers":[
        {
            "category":"Professional",
            "type":"Services"
        }
    ],
    "sg:phone":"+1 214 340 6570",
    "sg:postcode":"75231",
    "sg:province":"TX",
    "wof:name":"Ray Swannie",
    "wof:placetype":"venue"
},
  "geometry": {"coordinates":[-96.73191799999999,32.888785],"type":"Point"}
}