{
  "type": "Feature",
  "properties": {
    "iso:country":"US",
    "sg:address":"9142 Autumnsong Dr",
    "sg:city":"Houston",
    "sg:classifiers":[
        {
            "category":"Wholesale",
            "subcategory":"Durable Goods & Equipment",
            "type":"Manufacturing & Wholesale Goods"
        }
    ],
    "sg:phone":"+1 281 890 7989",
    "sg:postcode":"77064",
    "sg:province":"TX",
    "wof:name":"Trishas Pretties",
    "wof:placetype":"venue"
},
  "geometry": {"coordinates":[-95.559523,29.929527],"type":"Point"}
}