{
  "type": "Feature",
  "properties": {
    "iso:country":"US",
    "sg:address":"4246 Alta Vista Ln",
    "sg:city":"Dallas",
    "sg:classifiers":[
        {
            "category":"Sports & Exercise",
            "subcategory":"Sports Center",
            "type":"Entertainment"
        }
    ],
    "sg:phone":"+1 214 350 5606",
    "sg:postcode":"75229",
    "sg:province":"TX",
    "sg:tags":[
        "manager",
        "promoter"
    ],
    "sg:website":"http://www.quickfoot.com",
    "wof:name":"Quickfoot Inc",
    "wof:placetype":"venue"
},
  "geometry": {"coordinates":[-96.837326,32.904348],"type":"Point"}
}