{
  "type": "Feature",
  "properties": {
    "iso:country":"US",
    "sg:address":"108 W Oak St",
    "sg:city":"Denton",
    "sg:classifiers":[
        {
            "category":"Shopping",
            "subcategory":"Jewelry",
            "type":"Retail Goods"
        }
    ],
    "sg:phone":"+1 940 382 0708",
    "sg:postcode":"76201",
    "sg:province":"TX",
    "sg:tags":[
        "repair",
        "made",
        "custom"
    ],
    "wof:name":"Jewelry Expressions",
    "wof:placetype":"venue"
},
  "geometry": {"coordinates":[-97.132497,33.215661],"type":"Point"}
}