{
  "type": "Feature",
  "properties": {
    "iso:country":"US",
    "sg:address":"4895 Fm 850",
    "sg:city":"Tyler",
    "sg:classifiers":[
        {
            "category":"Real Estate",
            "subcategory":"Real Estate Services",
            "type":"Services"
        },
        {
            "category":"Real Estate",
            "subcategory":"Real Estate Agent",
            "type":"Services"
        }
    ],
    "sg:phone":"+1 903 592 5805",
    "sg:postcode":"75705",
    "sg:province":"TX",
    "sg:tags":[
        "management"
    ],
    "wof:name":"Smith Lone Star Event Center Inc",
    "wof:placetype":"venue"
},
  "geometry": {"coordinates":[-95.259196,32.35265],"type":"Point"}
}