{
  "type": "Feature",
  "properties": {
    "iso:country":"US",
    "sg:address":"1600 Plymouth Dr N",
    "sg:city":"Irving",
    "sg:classifiers":[
        {
            "category":"Retail",
            "subcategory":"Auto Rental",
            "type":"Services"
        }
    ],
    "sg:phone":"+1 972 254 3400",
    "sg:postcode":"75061",
    "sg:province":"TX",
    "sg:tags":[
        "renting",
        "truck",
        "leasing"
    ],
    "sg:website":"www.interstatetruckrental.com",
    "wof:name":"INTERSTATE Truck Rental",
    "wof:placetype":"venue"
},
  "geometry": {"coordinates":[-96.97475900000001,32.833047],"type":"Point"}
}