{
  "type": "Feature",
  "properties": {
    "iso:country":"US",
    "sg:address":"221 Katie Ln",
    "sg:city":"Seguin",
    "sg:classifiers":[
        {
            "category":"Building & Trades",
            "subcategory":"Plumbing",
            "type":"Services"
        }
    ],
    "sg:phone":"+1 830 303 2707",
    "sg:postcode":"78155",
    "sg:province":"TX",
    "sg:tags":[
        "plumbing",
        "contractor"
    ],
    "wof:name":"A & B Rooter Sewer & Drain",
    "wof:placetype":"venue"
},
  "geometry": {"coordinates":[-98.048179,29.553889],"type":"Point"}
}