{
  "type": "Feature",
  "properties": {
    "iso:country":"US",
    "sg:address":"2004 Cantura Dr",
    "sg:city":"Mesquite",
    "sg:classifiers":[
        {
            "category":"Professional",
            "subcategory":"Computer Services",
            "type":"Services"
        }
    ],
    "sg:phone":"+1 469 726 0059",
    "sg:postcode":"75181",
    "sg:province":"TX",
    "sg:tags":[
        "repair",
        "programming"
    ],
    "wof:name":"Up-N-Running Technical Svcs",
    "wof:placetype":"venue"
},
  "geometry": {"coordinates":[-96.57165500000001,32.744846],"type":"Point"}
}