{
  "type": "Feature",
  "properties": {
    "iso:country":"US",
    "sg:address":"229 E Shelton St",
    "sg:city":"Kingsville",
    "sg:classifiers":[
        {
            "category":"Manufacturing",
            "subcategory":"Printing",
            "type":"Manufacturing & Wholesale Goods"
        }
    ],
    "sg:phone":"+1 361 595 4221",
    "sg:postcode":"78363",
    "sg:province":"TX",
    "sg:tags":[
        "printer"
    ],
    "wof:name":"Economy Printing",
    "wof:placetype":"venue"
},
  "geometry": {"coordinates":[-97.867064,27.504652],"type":"Point"}
}