{
  "type": "Feature",
  "properties": {
    "iso:country":"US",
    "sg:address":"1101 Melbourne Rd",
    "sg:city":"Hurst",
    "sg:classifiers":[
        {
            "category":"Restaurant",
            "type":"Food & Drink"
        }
    ],
    "sg:menulink":"http://www.allmenus.com/tx/northeast-tarrant/98509-carrabbas/menu/",
    "sg:phone":"+1 817 595 3345",
    "sg:postcode":"76053",
    "sg:province":"TX",
    "sg:tags":[
        "italian"
    ],
    "wof:name":"Carrabba's",
    "wof:placetype":"venue"
},
  "geometry": {"coordinates":[-97.199433,32.830764],"type":"Point"}
}