{
  "type": "Feature",
  "properties": {
    "iso:country":"US",
    "sg:address":"2920 Tidwell Rd",
    "sg:city":"Houston",
    "sg:classifiers":[
        {
            "category":"Banks & Credit Unions",
            "subcategory":"Bank",
            "type":"Services"
        }
    ],
    "sg:phone":"+1 713 699 4167",
    "sg:postcode":"77093",
    "sg:province":"TX",
    "sg:tags":[
        "cashing",
        "check"
    ],
    "wof:name":"EZ Money Inc",
    "wof:placetype":"venue"
},
  "geometry": {"coordinates":[-95.33983600000001,29.848144],"type":"Point"}
}