{
  "type": "Feature",
  "properties": {
    "iso:country":"US",
    "sg:address":"6909 Hartline Ct",
    "sg:city":"Plano",
    "sg:classifiers":[
        {
            "category":"Professional",
            "subcategory":"Management & Consulting",
            "type":"Services"
        }
    ],
    "sg:phone":"+1 972 491 3852",
    "sg:postcode":"75023",
    "sg:province":"TX",
    "wof:name":"Harwell Marketing Services",
    "wof:placetype":"venue"
},
  "geometry": {"coordinates":[-96.759539,33.06942],"type":"Point"}
}