{
  "type": "Feature",
  "properties": {
    "iso:country":"US",
    "sg:address":"105 N River St",
    "sg:city":"Seguin",
    "sg:classifiers":[
        {
            "category":"Manufacturing",
            "subcategory":"Printing",
            "type":"Manufacturing & Wholesale Goods"
        }
    ],
    "sg:phone":"+1 830 401 0050",
    "sg:postcode":"78155",
    "sg:province":"TX",
    "sg:tags":[
        "photocopying",
        "commercial"
    ],
    "wof:name":"Viva Seguin Advertising & Prin",
    "wof:placetype":"venue"
},
  "geometry": {"coordinates":[-97.963718,29.568962],"type":"Point"}
}