{
  "type": "Feature",
  "properties": {
    "iso:country":"US",
    "sg:address":"8880 Bellaire Blvd",
    "sg:city":"Houston",
    "sg:classifiers":[
        {
            "category":"Shopping",
            "subcategory":"Mobile Phones",
            "type":"Retail Goods"
        }
    ],
    "sg:phone":"+1 713 541 1400",
    "sg:postcode":"77036",
    "sg:province":"TX",
    "wof:name":"Wireless Zone",
    "wof:placetype":"venue"
},
  "geometry": {"coordinates":[-95.54065799999999,29.7052],"type":"Point"}
}