{
  "type": "Feature",
  "properties": {
    "iso:country":"US",
    "sg:address":"1603 Harrison Rd",
    "sg:city":"Brenham",
    "sg:classifiers":[
        {
            "category":"Personal",
            "type":"Services"
        }
    ],
    "sg:phone":"+1 979 830 1133",
    "sg:postcode":"77833",
    "sg:province":"TX",
    "wof:name":"Events By Room Service",
    "wof:placetype":"venue"
},
  "geometry": {"coordinates":[-96.388362,30.156411],"type":"Point"}
}