{
  "type": "Feature",
  "properties": {
    "iso:country":"US",
    "sg:address":"4341 Canyon Dr",
    "sg:city":"Amarillo",
    "sg:classifiers":[
        {
            "category":"Insurance",
            "subcategory":"Hazard Insurance",
            "type":"Services"
        }
    ],
    "sg:phone":"+1 806 358 4891",
    "sg:postcode":"79110",
    "sg:province":"TX",
    "sg:tags":[
        "warranty"
    ],
    "wof:name":"Golden Eagle Rv Warranty Svc",
    "wof:placetype":"venue"
},
  "geometry": {"coordinates":[-101.86669999999999,35.168964],"type":"Point"}
}