{
  "type": "Feature",
  "properties": {
    "iso:country":"US",
    "sg:address":"24902 Crescent Run",
    "sg:city":"San Antonio",
    "sg:classifiers":[
        {
            "category":"Retail",
            "subcategory":"Animal Services",
            "type":"Services"
        }
    ],
    "sg:phone":"+1 210 534 7218",
    "sg:postcode":"78258",
    "sg:province":"TX",
    "sg:tags":[
        "pet",
        "grooming",
        "washing"
    ],
    "wof:name":"Cathy-Ann Pet Ctr",
    "wof:placetype":"venue"
},
  "geometry": {"coordinates":[-98.502332,29.641048],"type":"Point"}
}