{
  "type": "Feature",
  "properties": {
    "iso:country":"US",
    "sg:address":"2100 N Stemmons Fwy",
    "sg:city":"Dallas",
    "sg:classifiers":[
        {
            "category":"Home & Garden",
            "subcategory":"Home Furnishings",
            "type":"Retail Goods"
        }
    ],
    "sg:phone":"+1 214 747 5339",
    "sg:postcode":"75207",
    "sg:province":"TX",
    "sg:tags":[
        "pottery"
    ],
    "wof:name":"Frankoma Pottery",
    "wof:placetype":"venue"
},
  "geometry": {"coordinates":[-96.82739599999999,32.802121],"type":"Point"}
}