{
  "type": "Feature",
  "properties": {
    "iso:country":"US",
    "sg:address":"1201 N Watson Rd",
    "sg:city":"Arlington",
    "sg:classifiers":[
        {
            "category":"Wholesale",
            "subcategory":"Stationery",
            "type":"Manufacturing & Wholesale Goods"
        }
    ],
    "sg:phone":"+1 817 649 5278",
    "sg:postcode":"76006",
    "sg:province":"TX",
    "sg:tags":[
        "paper"
    ],
    "wof:name":"International Paper",
    "wof:placetype":"venue"
},
  "geometry": {"coordinates":[-97.06304799999999,32.770711],"type":"Point"}
}