{
  "type": "Feature",
  "properties": {
    "iso:country":"US",
    "sg:address":"7603 Valburn Dr",
    "sg:city":"Austin",
    "sg:classifiers":[
        {
            "category":"Real Estate",
            "subcategory":"Real Estate Agent",
            "type":"Services"
        }
    ],
    "sg:phone":"+1 512 345 5555",
    "sg:postcode":"78731",
    "sg:province":"TX",
    "wof:name":"P Shanks Realtor",
    "wof:placetype":"venue"
},
  "geometry": {"coordinates":[-97.77427900000001,30.37275],"type":"Point"}
}