{
  "type": "Feature",
  "properties": {
    "iso:country":"US",
    "sg:address":"2820 Commerce St",
    "sg:city":"Dallas",
    "sg:classifiers":[
        {
            "category":"Restaurant",
            "type":"Food & Drink"
        }
    ],
    "sg:phone":"+1 214 749 1911",
    "sg:postcode":"75226",
    "sg:province":"TX",
    "sg:tags":[
        "cajun/creole"
    ],
    "wof:name":"Sankofa Arts Kafe",
    "wof:placetype":"venue"
},
  "geometry": {"coordinates":[-96.782113,32.783104],"type":"Point"}
}