{
  "type": "Feature",
  "properties": {
    "iso:country":"US",
    "sg:address":"2732 Springhill Dr",
    "sg:city":"Grapevine",
    "sg:classifiers":[
        {
            "category":"Restaurant",
            "type":"Food & Drink"
        }
    ],
    "sg:phone":"+1 817 488 4850",
    "sg:postcode":"76051",
    "sg:province":"TX",
    "sg:tags":[
        "eating"
    ],
    "wof:name":"T A M T E X",
    "wof:placetype":"venue"
},
  "geometry": {"coordinates":[-97.108147,32.908423],"type":"Point"}
}