{
  "type": "Feature",
  "properties": {
    "iso:country":"US",
    "sg:address":"8800 Camelia Ln",
    "sg:city":"Austin",
    "sg:classifiers":[
        {
            "category":"Building & Trades",
            "subcategory":"Plumbing",
            "type":"Services"
        }
    ],
    "sg:phone":"+1 512 338 8113",
    "sg:postcode":"78759",
    "sg:province":"TX",
    "sg:tags":[
        "conditioning",
        "air",
        "system",
        "contractor"
    ],
    "wof:name":"Russell's Heating & Air Cond",
    "wof:placetype":"venue"
},
  "geometry": {"coordinates":[-97.74126,30.376224],"type":"Point"}
}