{
  "type": "Feature",
  "properties": {
    "iso:country":"US",
    "sg:address":"4411 Yale St",
    "sg:city":"Houston",
    "sg:classifiers":[
        {
            "category":"Retail",
            "subcategory":"Auto Repair",
            "type":"Services"
        }
    ],
    "sg:phone":"+1 713 699 2793",
    "sg:postcode":"77018",
    "sg:province":"TX",
    "sg:tags":[
        "transmission"
    ],
    "wof:name":"General Auto Repair",
    "wof:placetype":"venue"
},
  "geometry": {"coordinates":[-95.400173,29.828763],"type":"Point"}
}