{
  "type": "Feature",
  "properties": {
    "iso:country":"US",
    "sg:address":"4023 Betsy Ln",
    "sg:city":"Houston",
    "sg:classifiers":[
        {
            "category":"Shopping",
            "subcategory":"Used Merchandise",
            "type":"Retail Goods"
        }
    ],
    "sg:phone":"+1 713 871 8662",
    "sg:postcode":"77027",
    "sg:province":"TX",
    "sg:tags":[
        "antique"
    ],
    "wof:name":"Alphabet Alley",
    "wof:placetype":"venue"
},
  "geometry": {"coordinates":[-95.447081,29.738837],"type":"Point"}
}