{
  "type": "Feature",
  "properties": {
    "iso:country":"US",
    "sg:address":"1603 McGowen St",
    "sg:city":"Houston",
    "sg:classifiers":[
        {
            "category":"Organizations",
            "subcategory":"Religious Organization",
            "type":"Services"
        }
    ],
    "sg:phone":"+1 713 650 6530",
    "sg:postcode":"77004",
    "sg:province":"TX",
    "sg:tags":[
        "membership"
    ],
    "wof:name":"Southern Territorial Salvation",
    "wof:placetype":"venue"
},
  "geometry": {"coordinates":[-95.368038,29.741833],"type":"Point"}
}