{
  "type": "Feature",
  "properties": {
    "iso:country":"US",
    "sg:address":"6115 Ave L",
    "sg:city":"Galveston",
    "sg:classifiers":[
        {
            "category":"Health Services",
            "subcategory":"Doctor",
            "type":"Services"
        }
    ],
    "sg:phone":"+1 409 741 0256",
    "sg:postcode":"77551",
    "sg:province":"TX",
    "sg:tags":[
        "clinic"
    ],
    "wof:name":"Galveston Va Outpatient Clinic",
    "wof:placetype":"venue"
},
  "geometry": {"coordinates":[-94.83811300000001,29.286391],"type":"Point"}
}