{
  "type": "Feature",
  "properties": {
    "iso:country":"US",
    "sg:address":"10511 Fm 1585",
    "sg:city":"Wolfforth",
    "sg:classifiers":[
        {
            "category":"Arts & Performance",
            "subcategory":"Music",
            "type":"Entertainment"
        }
    ],
    "sg:phone":"+1 806 866 4964",
    "sg:postcode":"79382",
    "sg:province":"TX",
    "sg:tags":[
        "instrument",
        "musical"
    ],
    "sg:website":"http://www.repeatperformanceband.com",
    "wof:name":"Repeat Performance",
    "wof:placetype":"venue"
},
  "geometry": {"coordinates":[-102.049876,33.476117],"type":"Point"}
}