{
  "type": "Feature",
  "properties": {
    "iso:country":"US",
    "sg:address":"35 Richardson Hts Village",
    "sg:city":"Richardson",
    "sg:classifiers":[
        {
            "category":"Restaurant",
            "type":"Food & Drink"
        }
    ],
    "sg:phone":"+1 469 330 1600",
    "sg:postcode":"75080",
    "sg:province":"TX",
    "sg:website":"www.udipicafeusa.com",
    "wof:name":"Udipi Cafe",
    "wof:placetype":"venue"
},
  "geometry": {"coordinates":[-96.73615700000001,32.950714],"type":"Point"}
}