{
  "type": "Feature",
  "properties": {
    "iso:country":"US",
    "sg:address":"6627 Mimms Dr",
    "sg:city":"Dallas",
    "sg:classifiers":[
        {
            "category":"Professional",
            "subcategory":"Management & Consulting",
            "type":"Services"
        }
    ],
    "sg:phone":"+1 469 467 4545",
    "sg:postcode":"75252",
    "sg:province":"TX",
    "sg:tags":[
        "fuel"
    ],
    "wof:name":"Management Plus Inc",
    "wof:placetype":"venue"
},
  "geometry": {"coordinates":[-96.79004999999999,33.000847],"type":"Point"}
}