{
  "type": "Feature",
  "properties": {
    "iso:country":"US",
    "sg:address":"132 Holly Loop",
    "sg:city":"Ennis",
    "sg:classifiers":[
        {
            "category":"Building & Trades",
            "subcategory":"Construction",
            "type":"Services"
        }
    ],
    "sg:phone":"+1 972 878 0086",
    "sg:postcode":"75119",
    "sg:province":"TX",
    "sg:tags":[
        "contractor"
    ],
    "wof:name":"Dorety Masonry",
    "wof:placetype":"venue"
},
  "geometry": {"coordinates":[-96.65227400000001,32.356768],"type":"Point"}
}