{
  "type": "Feature",
  "properties": {
    "iso:country":"US",
    "sg:address":"304 S Main St",
    "sg:city":"Quitman",
    "sg:classifiers":[
        {
            "category":"Professional",
            "subcategory":"Lawyer & Legal Services",
            "type":"Services"
        }
    ],
    "sg:phone":"+1 903 763 5425",
    "sg:postcode":"75783",
    "sg:province":"TX",
    "sg:tags":[
        "attorney"
    ],
    "wof:name":"Brown KERR & King Law Offices",
    "wof:placetype":"venue"
},
  "geometry": {"coordinates":[-95.451615,32.794503],"type":"Point"}
}