{
  "type": "Feature",
  "properties": {
    "iso:country":"US",
    "sg:address":"2604 Geraghty Ave",
    "sg:city":"Austin",
    "sg:classifiers":[
        {
            "category":"Professional",
            "subcategory":"Management & Consulting",
            "type":"Services"
        }
    ],
    "sg:phone":"+1 512 459 1828",
    "sg:postcode":"78757",
    "sg:province":"TX",
    "sg:tags":[
        "business"
    ],
    "wof:name":"Brigit Shea & Associates",
    "wof:placetype":"venue"
},
  "geometry": {"coordinates":[-97.743003,30.347034],"type":"Point"}
}