{
  "type": "Feature",
  "properties": {
    "iso:country":"US",
    "sg:address":"5925 US Hwy 62",
    "sg:city":"Lubbock",
    "sg:classifiers":[
        {
            "category":"Autos & Motor Vehicles",
            "subcategory":"Automobile Sales",
            "type":"Retail Goods"
        }
    ],
    "sg:phone":"+1 806 763 8789",
    "sg:postcode":"79403",
    "sg:province":"TX",
    "sg:tags":[
        "car",
        "dealer"
    ],
    "wof:name":"Lone Star Sales",
    "wof:placetype":"venue"
},
  "geometry": {"coordinates":[-101.734666,33.646714],"type":"Point"}
}