{
  "type": "Feature",
  "properties": {
    "iso:country":"US",
    "sg:address":"7533 Vineyard Trl",
    "sg:city":"Garland",
    "sg:classifiers":[
        {
            "category":"Manufacturing",
            "subcategory":"Metals",
            "type":"Manufacturing & Wholesale Goods"
        }
    ],
    "sg:phone":"+1 972 530 6106",
    "sg:postcode":"75044",
    "sg:province":"TX",
    "sg:tags":[
        "scraps",
        "mix",
        "export"
    ],
    "wof:name":"Microconcept Enterprises",
    "wof:placetype":"venue"
},
  "geometry": {"coordinates":[-96.67102300000001,32.981972],"type":"Point"}
}