{
  "type": "Feature",
  "properties": {
    "iso:country":"US",
    "sg:address":"1806 N Velasco St",
    "sg:city":"Angleton",
    "sg:classifiers":[
        {
            "category":"Sports & Exercise",
            "subcategory":"Gym",
            "type":"Entertainment"
        }
    ],
    "sg:phone":"+1 979 849 2555",
    "sg:postcode":"77515",
    "sg:province":"TX",
    "sg:tags":[
        "fitness",
        "physical",
        "facility"
    ],
    "wof:name":"Curves For Women Angleton",
    "wof:placetype":"venue"
},
  "geometry": {"coordinates":[-95.433965,29.197377],"type":"Point"}
}