{
  "type": "Feature",
  "properties": {
    "iso:country":"US",
    "sg:address":"835 W Price Rd",
    "sg:city":"Brownsville",
    "sg:classifiers":[
        {
            "category":"Cinema",
            "subcategory":"Movie Rental",
            "type":"Entertainment"
        }
    ],
    "sg:phone":"+1 956 548 9062",
    "sg:postcode":"78520",
    "sg:province":"TX",
    "sg:tags":[
        "motion",
        "video",
        "tape",
        "picture"
    ],
    "wof:name":"Reasonable Price Video Taping",
    "wof:placetype":"venue"
},
  "geometry": {"coordinates":[-97.509213,25.937441],"type":"Point"}
}