{
  "type": "Feature",
  "properties": {
    "iso:country":"US",
    "sg:address":"4302 Heathfield Dr",
    "sg:city":"Pasadena",
    "sg:classifiers":[
        {
            "category":"Building & Trades",
            "subcategory":"Plumbing",
            "type":"Services"
        }
    ],
    "sg:phone":"+1 281 998 0804",
    "sg:postcode":"77505",
    "sg:province":"TX",
    "sg:tags":[
        "contractor"
    ],
    "wof:name":"Phillip A/C & Heating",
    "wof:placetype":"venue"
},
  "geometry": {"coordinates":[-95.13825300000001,29.645512],"type":"Point"}
}