{
  "type": "Feature",
  "properties": {
    "iso:country":"US",
    "sg:address":"7500 Eckhert Rd",
    "sg:city":"San Antonio",
    "sg:classifiers":[
        {
            "category":"Professional",
            "subcategory":"Business Services",
            "type":"Services"
        },
        {
            "category":"Manufacturing",
            "subcategory":"Tools & Machinery",
            "type":"Manufacturing & Wholesale Goods"
        }
    ],
    "sg:phone":"+1 210 509 2444",
    "sg:postcode":"78240",
    "sg:province":"TX",
    "sg:tags":[
        "water",
        "product",
        "filtration",
        "treatment"
    ],
    "wof:name":"Alpha Filtronics",
    "wof:placetype":"venue"
},
  "geometry": {"coordinates":[-98.626639,29.508497],"type":"Point"}
}