{
  "type": "Feature",
  "properties": {
    "iso:country":"US",
    "sg:address":"929 Raynolds St",
    "sg:city":"El Paso",
    "sg:classifiers":[
        {
            "category":"Professional",
            "subcategory":"Business Services",
            "type":"Services"
        }
    ],
    "sg:phone":"+1 915 598 3513",
    "sg:postcode":"79903",
    "sg:province":"TX",
    "wof:name":"Sun City Fund Raising",
    "wof:placetype":"venue"
},
  "geometry": {"coordinates":[-106.43294400000001,31.781777],"type":"Point"}
}