{
  "type": "Feature",
  "properties": {
    "iso:country":"US",
    "sg:address":"501 Pelham St",
    "sg:city":"Bowie",
    "sg:classifiers":[
        {
            "category":"Social Services",
            "type":"Services"
        }
    ],
    "sg:phone":"+1 940 872 4500",
    "sg:postcode":"76230",
    "sg:province":"TX",
    "sg:tags":[
        "organization",
        "welfare"
    ],
    "wof:name":"Senior Citizens Project",
    "wof:placetype":"venue"
},
  "geometry": {"coordinates":[-97.83160100000001,33.553338],"type":"Point"}
}