{
  "type": "Feature",
  "properties": {
    "iso:country":"US",
    "sg:address":"5333 Westheimer Rd",
    "sg:city":"Houston",
    "sg:classifiers":[
        {
            "category":"Home & Garden",
            "subcategory":"Building Materials",
            "type":"Retail Goods"
        },
        {
            "category":"Professional",
            "subcategory":"Management & Consulting",
            "type":"Services"
        }
    ],
    "sg:phone":"+1 713 850 6790",
    "sg:postcode":"77056",
    "sg:province":"TX",
    "sg:tags":[
        "energy",
        "conservation",
        "prod",
        "sales"
    ],
    "sg:website":"www.justenergy.com",
    "wof:name":"Just Energy LLC",
    "wof:placetype":"venue"
},
  "geometry": {"coordinates":[-95.468397,29.739903],"type":"Point"}
}