{
  "type": "Feature",
  "properties": {
    "iso:country":"US",
    "sg:address":"34691 Co Rd 1577",
    "sg:city":"San Benito",
    "sg:classifiers":[
        {
            "category":"Shopping",
            "subcategory":"Hobbies, Toys, & Games",
            "type":"Retail Goods"
        }
    ],
    "sg:phone":"+1 956 361 0442",
    "sg:postcode":"78586",
    "sg:province":"TX",
    "wof:name":"Hobby Shop",
    "wof:placetype":"venue"
},
  "geometry": {"coordinates":[-97.627039,26.036868],"type":"Point"}
}