{
  "type": "Feature",
  "properties": {
    "iso:country":"US",
    "sg:address":"5807 66th St",
    "sg:city":"Lubbock",
    "sg:classifiers":[
        {
            "category":"Professional",
            "type":"Services"
        }
    ],
    "sg:phone":"+1 806 722 6876",
    "sg:postcode":"79424",
    "sg:province":"TX",
    "wof:name":"Robin Burch",
    "wof:placetype":"venue"
},
  "geometry": {"coordinates":[-101.942015,33.534242],"type":"Point"}
}