{
  "type": "Feature",
  "properties": {
    "iso:country":"US",
    "sg:address":"5525 Pine St",
    "sg:city":"Houston",
    "sg:phone":"+1 713 665 8692",
    "sg:postcode":"77081",
    "sg:province":"TX",
    "wof:name":"S & B Plumbing",
    "wof:placetype":"venue"
},
  "geometry": {"coordinates":[-95.48557700000001,29.694605],"type":"Point"}
}