{
  "type": "Feature",
  "properties": {
    "iso:country":"US",
    "sg:address":"1340 Backus St",
    "sg:city":"El Paso",
    "sg:classifiers":[
        {
            "category":"Restaurant",
            "type":"Food & Drink"
        }
    ],
    "sg:phone":"+1 915 592 8138",
    "sg:postcode":"79925",
    "sg:province":"TX",
    "sg:tags":[
        "eating"
    ],
    "wof:name":"Home Cooking Gourmet Serv",
    "wof:placetype":"venue"
},
  "geometry": {"coordinates":[-106.36170799999999,31.774212],"type":"Point"}
}