{
  "type": "Feature",
  "properties": {
    "iso:country":"US",
    "sg:address":"5548 Fairmont Pkwy",
    "sg:city":"Pasadena",
    "sg:classifiers":[
        {
            "category":"Building & Trades",
            "subcategory":"Construction",
            "type":"Services"
        }
    ],
    "sg:phone":"+1 832 251 1577",
    "sg:postcode":"77505",
    "sg:province":"TX",
    "sg:tags":[
        "general",
        "contractor"
    ],
    "wof:name":"Canyon Contractors",
    "wof:placetype":"venue"
},
  "geometry": {"coordinates":[-95.155598,29.649793],"type":"Point"}
}