{
  "type": "Feature",
  "properties": {
    "iso:country":"US",
    "sg:address":"308 Suncreek Dr",
    "sg:city":"Allen",
    "sg:classifiers":[
        {
            "category":"Professional",
            "subcategory":"Management & Consulting",
            "type":"Services"
        }
    ],
    "sg:phone":"+1 214 495 0086",
    "sg:postcode":"75013",
    "sg:province":"TX",
    "wof:name":"Barry & Associates",
    "wof:placetype":"venue"
},
  "geometry": {"coordinates":[-96.707807,33.09849],"type":"Point"}
}