{
  "type": "Feature",
  "properties": {
    "iso:country":"US",
    "sg:address":"16307 Lone Wolf Dr",
    "sg:city":"Leander",
    "sg:classifiers":[
        {
            "category":"Arts & Performance",
            "subcategory":"Arts Center",
            "type":"Entertainment"
        }
    ],
    "sg:phone":"+1 512 528 0662",
    "sg:postcode":"78641",
    "sg:province":"TX",
    "sg:tags":[
        "performing"
    ],
    "wof:name":"Irish Dance Center",
    "wof:placetype":"venue"
},
  "geometry": {"coordinates":[-97.826939,30.543579],"type":"Point"}
}