{
  "type": "Feature",
  "properties": {
    "iso:country":"US",
    "sg:address":"4700 Nolan St",
    "sg:city":"Fort Worth",
    "sg:classifiers":[
        {
            "category":"Freight",
            "type":"Transportation"
        }
    ],
    "sg:phone":"+1 817 531 2930",
    "sg:postcode":"76119",
    "sg:province":"TX",
    "sg:tags":[
        "operator",
        "local",
        "trucking"
    ],
    "wof:name":"Vazquez Trucking",
    "wof:placetype":"venue"
},
  "geometry": {"coordinates":[-97.275746,32.692242],"type":"Point"}
}