{
  "type": "Feature",
  "properties": {
    "iso:country":"US",
    "sg:address":"13810 Champion Forest Dr",
    "sg:city":"Houston",
    "sg:classifiers":[
        {
            "category":"Professional",
            "subcategory":"Research",
            "type":"Services"
        }
    ],
    "sg:phone":"+1 281 895 0700",
    "sg:postcode":"77069",
    "sg:province":"TX",
    "sg:tags":[
        "merger",
        "firm",
        "acquisition"
    ],
    "wof:name":"Joseph Hale Co",
    "wof:placetype":"venue"
},
  "geometry": {"coordinates":[-95.52050199999999,29.988184],"type":"Point"}
}