{
  "type": "Feature",
  "properties": {
    "iso:country":"US",
    "sg:address":"6702 Congress Ave S",
    "sg:city":"Austin",
    "sg:classifiers":[
        {
            "category":"Food & Beverages",
            "subcategory":"Groceries & Convenience Stores",
            "type":"Retail Goods"
        }
    ],
    "sg:phone":"+1 512 441 7598",
    "sg:postcode":"78745",
    "sg:province":"TX",
    "wof:name":"7-Eleven",
    "wof:placetype":"venue"
},
  "geometry": {"coordinates":[-97.779612,30.19123],"type":"Point"}
}