{
  "type": "Feature",
  "properties": {
    "iso:country":"US",
    "sg:address":"8008 Rio Vista Dr",
    "sg:city":"Woodway",
    "sg:classifiers":[
        {
            "category":"Home & Garden",
            "subcategory":"Furniture",
            "type":"Retail Goods"
        }
    ],
    "sg:phone":"+1 254 235 8196",
    "sg:postcode":"76712",
    "sg:province":"TX",
    "sg:tags":[
        "store"
    ],
    "wof:name":"Capron Collection",
    "wof:placetype":"venue"
},
  "geometry": {"coordinates":[-97.220268,31.517283],"type":"Point"}
}