{
  "type": "Feature",
  "properties": {
    "iso:country":"US",
    "sg:address":"4001 N 10th St",
    "sg:city":"Mcallen",
    "sg:classifiers":[
        {
            "category":"Cinema",
            "subcategory":"Movie Rental",
            "type":"Entertainment"
        }
    ],
    "sg:phone":"+1 956 682 3183",
    "sg:postcode":"78504",
    "sg:province":"TX",
    "sg:tags":[
        "leasing",
        "video",
        "disc",
        "tape"
    ],
    "wof:name":"Blockbuster Video",
    "wof:placetype":"venue"
},
  "geometry": {"coordinates":[-98.223845,26.239428],"type":"Point"}
}