{
  "type": "Feature",
  "properties": {
    "iso:country":"US",
    "sg:address":"718 W 6th St",
    "sg:city":"Weslaco",
    "sg:classifiers":[
        {
            "category":"Food & Beverages",
            "subcategory":"Groceries & Convenience Stores",
            "type":"Retail Goods"
        }
    ],
    "sg:phone":"+1 956 969 1020",
    "sg:postcode":"78596",
    "sg:province":"TX",
    "wof:name":"Sixth Street Market",
    "wof:placetype":"venue"
},
  "geometry": {"coordinates":[-97.996707,26.15538],"type":"Point"}
}