{
  "type": "Feature",
  "properties": {
    "iso:country":"US",
    "sg:address":"2481 Juanita Dr",
    "sg:city":"Denison",
    "sg:classifiers":[
        {
            "category":"Building & Trades",
            "subcategory":"Pest Control",
            "type":"Services"
        }
    ],
    "sg:phone":"+1 903 463 1723",
    "sg:postcode":"75020",
    "sg:province":"TX",
    "wof:name":"Kenny's Spraying Svc",
    "wof:placetype":"venue"
},
  "geometry": {"coordinates":[-96.563383,33.768054],"type":"Point"}
}