{
  "type": "Feature",
  "properties": {
    "iso:country":"US",
    "sg:address":"8725 Cornell Ave",
    "sg:city":"Odessa",
    "sg:classifiers":[
        {
            "category":"Professional",
            "subcategory":"Management & Consulting",
            "type":"Services"
        }
    ],
    "sg:phone":"+1 432 618 0705",
    "sg:postcode":"79765",
    "sg:province":"TX",
    "sg:tags":[
        "consultant",
        "business"
    ],
    "wof:name":"Entrepreneur's Source",
    "wof:placetype":"venue"
},
  "geometry": {"coordinates":[-102.394509,31.937616],"type":"Point"}
}