{
  "type": "Feature",
  "properties": {
    "iso:country":"US",
    "sg:address":"206 Mary St",
    "sg:city":"Rowena",
    "sg:classifiers":[
        {
            "category":"Building & Trades",
            "subcategory":"Construction",
            "type":"Services"
        }
    ],
    "sg:phone":"+1 325 895 1557",
    "sg:postcode":"76875",
    "sg:province":"TX",
    "sg:tags":[
        "system",
        "contractor",
        "air conditioning"
    ],
    "wof:name":"J Ds Heating & Air Conditioning",
    "wof:placetype":"venue"
},
  "geometry": {"coordinates":[-100.047569,31.646925],"type":"Point"}
}