{
  "type": "Feature",
  "properties": {
    "iso:country":"US",
    "sg:address":"2000 Royal Ln",
    "sg:city":"Dallas",
    "sg:classifiers":[
        {
            "category":"Professional",
            "subcategory":"Art Services",
            "type":"Services"
        }
    ],
    "sg:phone":"+1 469 522 5288",
    "sg:postcode":"75229",
    "sg:province":"TX",
    "sg:tags":[
        "graphic",
        "designer"
    ],
    "wof:name":"Pine Media",
    "wof:placetype":"venue"
},
  "geometry": {"coordinates":[-96.90898300000001,32.895669],"type":"Point"}
}