{
  "type": "Feature",
  "properties": {
    "iso:country":"US",
    "sg:address":"1953 Denton St",
    "sg:city":"Abilene",
    "sg:classifiers":[
        {
            "category":"Health Services",
            "subcategory":"Medical Lab",
            "type":"Services"
        }
    ],
    "sg:phone":"+1 325 691 5605",
    "sg:postcode":"79605",
    "sg:province":"TX",
    "sg:tags":[
        "laboratory"
    ],
    "wof:name":"Beechwood Laboratory Services",
    "wof:placetype":"venue"
},
  "geometry": {"coordinates":[-99.791371,32.425398],"type":"Point"}
}