{
  "type": "Feature",
  "properties": {
    "iso:country":"US",
    "sg:address":"8713 S Normandale St",
    "sg:city":"Fort Worth",
    "sg:classifiers":[
        {
            "category":"Real Estate",
            "subcategory":"Real Estate Operator",
            "type":"Services"
        }
    ],
    "sg:phone":"+1 817 244 2665",
    "sg:postcode":"76116",
    "sg:province":"TX",
    "sg:tags":[
        "retirement",
        "apartment"
    ],
    "wof:name":"Normandale Place Apartments",
    "wof:placetype":"venue"
},
  "geometry": {"coordinates":[-97.466825,32.728867],"type":"Point"}
}