{
  "type": "Feature",
  "properties": {
    "iso:country":"US",
    "sg:address":"4021 Spencer St",
    "sg:city":"Houston",
    "sg:classifiers":[
        {
            "category":"Restaurant",
            "type":"Food & Drink"
        }
    ],
    "sg:phone":"+1 713 946 1092",
    "sg:postcode":"77007",
    "sg:province":"TX",
    "wof:name":"Golden Corral Restaurant",
    "wof:placetype":"venue"
},
  "geometry": {"coordinates":[-95.401815,29.775207],"type":"Point"}
}