{
  "type": "Feature",
  "properties": {
    "iso:country":"US",
    "sg:address":"1610 Milam St",
    "sg:city":"Uvalde",
    "sg:classifiers":[
        {
            "category":"Wholesale",
            "subcategory":"Machinery & Supplies",
            "type":"Manufacturing & Wholesale Goods"
        }
    ],
    "sg:phone":"+1 830 278 1197",
    "sg:postcode":"78801",
    "sg:province":"TX",
    "sg:tags":[
        "refrigeration",
        "esta"
    ],
    "wof:name":"Universal Wholesale Supply",
    "wof:placetype":"venue"
},
  "geometry": {"coordinates":[-99.793564,29.229927],"type":"Point"}
}