{
  "type": "Feature",
  "properties": {
    "iso:country":"US",
    "sg:address":"1132 Valwood Pkwy",
    "sg:city":"Carrollton",
    "sg:classifiers":[
        {
            "category":"Wholesale",
            "subcategory":"Machinery & Supplies",
            "type":"Manufacturing & Wholesale Goods"
        }
    ],
    "sg:phone":"+1 972 446 3467",
    "sg:postcode":"75006",
    "sg:province":"TX",
    "sg:tags":[
        "equipment",
        "industrial"
    ],
    "wof:name":"Kennametal Inc",
    "wof:placetype":"venue"
},
  "geometry": {"coordinates":[-96.90789700000001,32.938887],"type":"Point"}
}