{
  "type": "Feature",
  "properties": {
    "iso:country":"US",
    "sg:address":"5917 67th St",
    "sg:city":"Lubbock",
    "sg:classifiers":[
        {
            "category":"Professional",
            "subcategory":"Business Services",
            "type":"Services"
        }
    ],
    "sg:phone":"+1 806 799 8572",
    "sg:postcode":"79424",
    "sg:province":"TX",
    "wof:name":"Dax Enterprises",
    "wof:placetype":"venue"
},
  "geometry": {"coordinates":[-101.94226500000001,33.532859],"type":"Point"}
}