{
  "type": "Feature",
  "properties": {
    "iso:country":"US",
    "sg:address":"1300 S Wheeler St",
    "sg:city":"Jasper",
    "sg:classifiers":[
        {
            "category":"Personal",
            "subcategory":"Barber",
            "type":"Services"
        }
    ],
    "sg:phone":"+1 409 384 2429",
    "sg:postcode":"75951",
    "sg:province":"TX",
    "sg:tags":[
        "shop"
    ],
    "wof:name":"Dub-N-Flos Barber & Styling",
    "wof:placetype":"venue"
},
  "geometry": {"coordinates":[-93.994754,30.908987],"type":"Point"}
}