{
  "type": "Feature",
  "properties": {
    "iso:country":"US",
    "sg:address":"903 N Greer Blvd",
    "sg:city":"Pittsburg",
    "sg:classifiers":[
        {
            "category":"Shopping",
            "subcategory":"Department Store",
            "type":"Retail Goods"
        }
    ],
    "sg:phone":"+1 903 856 3353",
    "sg:postcode":"75686",
    "sg:province":"TX",
    "sg:tags":[
        "shop"
    ],
    "wof:name":"Dollar General",
    "wof:placetype":"venue"
},
  "geometry": {"coordinates":[-94.96572500000001,33.014583],"type":"Point"}
}