{
  "type": "Feature",
  "properties": {
    "iso:country":"US",
    "sg:address":"9931 Railroad Dr",
    "sg:city":"El Paso",
    "sg:classifiers":[
        {
            "category":"Manufacturing",
            "subcategory":"Building Materials",
            "type":"Manufacturing & Wholesale Goods"
        }
    ],
    "sg:phone":"+1 915 751 0025",
    "sg:postcode":"79924",
    "sg:province":"TX",
    "sg:tags":[
        "wood",
        "truss",
        "roof",
        "mfg"
    ],
    "wof:name":"El Paso Truss Inc",
    "wof:placetype":"venue"
},
  "geometry": {"coordinates":[-106.39467999999999,31.896212],"type":"Point"}
}