{
  "type": "Feature",
  "properties": {
    "iso:country":"US",
    "sg:address":"1222 Oriole Ln",
    "sg:city":"Garland",
    "sg:classifiers":[
        {
            "category":"Building & Trades",
            "subcategory":"Construction",
            "type":"Services"
        }
    ],
    "sg:phone":"+1 972 276 1180",
    "sg:postcode":"75042",
    "sg:province":"TX",
    "sg:tags":[
        "roofing",
        "contractor"
    ],
    "wof:name":"Janis Molsbee",
    "wof:placetype":"venue"
},
  "geometry": {"coordinates":[-96.657785,32.903289],"type":"Point"}
}