{
  "type": "Feature",
  "properties": {
    "iso:country":"US",
    "sg:address":"219 S Main St",
    "sg:city":"La Feria",
    "sg:classifiers":[
        {
            "category":"Retail",
            "subcategory":"Funeral Services",
            "type":"Services"
        }
    ],
    "sg:phone":"+1 956 797 3122",
    "sg:postcode":"78559",
    "sg:province":"TX",
    "sg:tags":[
        "home"
    ],
    "wof:name":"Garza Rudys Funeral Home",
    "wof:placetype":"venue"
},
  "geometry": {"coordinates":[-97.823958,26.156703],"type":"Point"}
}