{
  "type": "Feature",
  "properties": {
    "iso:country":"US",
    "sg:address":"2525 Wallingwood Dr",
    "sg:city":"Austin",
    "sg:classifiers":[
        {
            "category":"Health Services",
            "subcategory":"Doctor",
            "type":"Services"
        }
    ],
    "sg:phone":"+1 512 535 7075",
    "sg:postcode":"78746",
    "sg:province":"TX",
    "wof:name":"Cole Letha",
    "wof:placetype":"venue"
},
  "geometry": {"coordinates":[-97.784863,30.264111],"type":"Point"}
}