{
  "type": "Feature",
  "properties": {
    "iso:country":"US",
    "sg:address":"9560 Long Point Rd",
    "sg:city":"Houston",
    "sg:classifiers":[
        {
            "category":"Place Of Worship",
            "subcategory":"Church",
            "type":"Public Place"
        },
        {
            "category":"Place Of Worship",
            "type":"Public Place"
        }
    ],
    "sg:phone":"+1 713 465 3473",
    "sg:postcode":"77055",
    "sg:province":"TX",
    "sg:tags":[
        "churches-non-denominational",
        "christ",
        "churches-community"
    ],
    "wof:name":"Branch Spring Community Church",
    "wof:placetype":"venue"
},
  "geometry": {"coordinates":[-95.52803400000001,29.796671],"type":"Point"}
}