{
  "type": "Feature",
  "properties": {
    "iso:country":"US",
    "sg:address":"17965 State Hwy 95",
    "sg:city":"Holland",
    "sg:classifiers":[
        {
            "category":"Personal",
            "subcategory":"Beauty Salon",
            "type":"Services"
        }
    ],
    "sg:phone":"+1 254 982 4358",
    "sg:postcode":"76534",
    "sg:province":"TX",
    "wof:name":"Lueck's Beauty Salon",
    "wof:placetype":"venue"
},
  "geometry": {"coordinates":[-97.36260900000001,30.921464],"type":"Point"}
}