{
  "type": "Feature",
  "properties": {
    "iso:country":"US",
    "sg:address":"300 S Johnson St",
    "sg:city":"Alice",
    "sg:classifiers":[
        {
            "category":"Government",
            "subcategory":"Police Station",
            "type":"Public Place"
        }
    ],
    "sg:phone":"+1 361 668 8296",
    "sg:postcode":"78332",
    "sg:province":"TX",
    "sg:tags":[
        "state"
    ],
    "wof:name":"Texas Highway Patrol",
    "wof:placetype":"venue"
},
  "geometry": {"coordinates":[-98.082537,27.746411],"type":"Point"}
}