{
  "type": "Feature",
  "properties": {
    "iso:country":"US",
    "sg:address":"1902 Cooper Dr",
    "sg:city":"Irving",
    "sg:classifiers":[
        {
            "category":"Building & Trades",
            "subcategory":"Landscaping Services",
            "type":"Services"
        }
    ],
    "sg:phone":"+1 972 554 6174",
    "sg:postcode":"75061",
    "sg:province":"TX",
    "wof:name":"Cutting Edge Lawn and Ldscp",
    "wof:placetype":"venue"
},
  "geometry": {"coordinates":[-96.92407799999999,32.836581],"type":"Point"}
}