{
  "type": "Feature",
  "properties": {
    "iso:country":"US",
    "sg:address":"3337 State Hwy 6",
    "sg:city":"Sugar Land",
    "sg:classifiers":[
        {
            "category":"Home & Garden",
            "subcategory":"Building Materials",
            "type":"Retail Goods"
        }
    ],
    "sg:phone":"+1 281 980 1250",
    "sg:postcode":"77478",
    "sg:province":"TX",
    "sg:tags":[
        "wallpaper"
    ],
    "wof:name":"Total Wallcovering Inc",
    "wof:placetype":"venue"
},
  "geometry": {"coordinates":[-95.60408099999999,29.591801],"type":"Point"}
}