{
  "type": "Feature",
  "properties": {
    "iso:country":"US",
    "sg:address":"8079 N Lamar Blvd",
    "sg:city":"Austin",
    "sg:classifiers":[
        {
            "category":"Real Estate",
            "subcategory":"Real Estate Agent",
            "type":"Services"
        }
    ],
    "sg:phone":"+1 512 834 9004",
    "sg:postcode":"78753",
    "sg:province":"TX",
    "wof:name":"Cocomax Realty",
    "wof:placetype":"venue"
},
  "geometry": {"coordinates":[-97.709349,30.350404],"type":"Point"}
}