{
  "type": "Feature",
  "properties": {
    "iso:country":"US",
    "sg:address":"3710 Cedar Street Suite 12",
    "sg:city":"Austin",
    "sg:classifiers":[
        {
            "category":"Organizations",
            "subcategory":"Non-profit Organization",
            "type":"Services"
        }
    ],
    "sg:phone":"+1 512 458 8600",
    "sg:postcode":"78705",
    "sg:province":"TX",
    "sg:tags":[
        "service/non-profit",
        "community"
    ],
    "wof:name":"Texas Parent To Parent",
    "wof:placetype":"venue"
},
  "geometry": {"coordinates":[-97.734938,30.300719],"type":"Point"}
}