{
  "type": "Feature",
  "properties": {
    "iso:country":"US",
    "sg:address":"3010 Frankford Rd",
    "sg:city":"Dallas",
    "sg:classifiers":[
        {
            "category":"Banks & Credit Unions",
            "subcategory":"Financial Services",
            "type":"Services"
        }
    ],
    "sg:phone":"+1 972 733 3637",
    "sg:postcode":"75287",
    "sg:province":"TX",
    "sg:tags":[
        "broker",
        "mortgage"
    ],
    "wof:name":"American Mortgage Funds",
    "wof:placetype":"venue"
},
  "geometry": {"coordinates":[-96.861993,32.996803],"type":"Point"}
}