{
  "type": "Feature",
  "properties": {
    "iso:country":"US",
    "sg:address":"3601 Kite Landing Ln",
    "sg:city":"Plano",
    "sg:classifiers":[
        {
            "category":"Retail",
            "subcategory":"Repair Shop",
            "type":"Services"
        }
    ],
    "sg:phone":"+1 972 633 0412",
    "sg:postcode":"75074",
    "sg:province":"TX",
    "sg:tags":[
        "electrical"
    ],
    "wof:name":"San Su Service Co",
    "wof:placetype":"venue"
},
  "geometry": {"coordinates":[-96.64991499999999,33.045045],"type":"Point"}
}