{
  "type": "Feature",
  "properties": {
    "iso:country":"US",
    "sg:address":"4415 Moulton St",
    "sg:city":"Greenville",
    "sg:classifiers":[
        {
            "category":"Food & Beverages",
            "subcategory":"Groceries & Convenience Stores",
            "type":"Retail Goods"
        }
    ],
    "sg:phone":"+1 903 450 8958",
    "sg:postcode":"75401",
    "sg:province":"TX",
    "wof:name":"Oviedos Tienda",
    "wof:placetype":"venue"
},
  "geometry": {"coordinates":[-96.098415,33.124697],"type":"Point"}
}