{
  "type": "Feature",
  "properties": {
    "iso:country":"US",
    "sg:address":"6407 Sandshof Dr",
    "sg:city":"Austin",
    "sg:classifiers":[
        {
            "category":"Professional",
            "subcategory":"Accounting & Tax Preparation",
            "type":"Services"
        }
    ],
    "sg:phone":"+1 512 933 9736",
    "sg:postcode":"78724",
    "sg:province":"TX",
    "sg:tags":[
        "billing"
    ],
    "wof:name":"Sums Medical Claims",
    "wof:placetype":"venue"
},
  "geometry": {"coordinates":[-97.64625100000001,30.297701],"type":"Point"}
}