{
  "type": "Feature",
  "properties": {
    "iso:country":"US",
    "sg:address":"502 Kayton Ave",
    "sg:city":"San Antonio",
    "sg:classifiers":[
        {
            "category":"Organizations",
            "subcategory":"Religious Organization",
            "type":"Services"
        }
    ],
    "sg:phone":"+1 210 532 6671",
    "sg:postcode":"78210",
    "sg:province":"TX",
    "wof:name":"Aldersgate Untd Methdst Church",
    "wof:placetype":"venue"
},
  "geometry": {"coordinates":[-98.463358,29.397338],"type":"Point"}
}