{
  "type": "Feature",
  "properties": {
    "iso:country":"US",
    "sg:address":"5958 FM 1753",
    "sg:city":"Denison",
    "sg:classifiers":[
        {
            "category":"Building & Trades",
            "subcategory":"Construction",
            "type":"Services"
        }
    ],
    "sg:phone":"+1 903 465 1311",
    "sg:postcode":"75021",
    "sg:province":"TX",
    "sg:tags":[
        "house"
    ],
    "wof:name":"John Robinson Construction",
    "wof:placetype":"venue"
},
  "geometry": {"coordinates":[-96.435621,33.703269],"type":"Point"}
}