{
  "type": "Feature",
  "properties": {
    "iso:country":"US",
    "sg:address":"2510 Daisy Ln",
    "sg:city":"Rowlett",
    "sg:classifiers":[
        {
            "category":"Food & Beverages",
            "subcategory":"Specialty",
            "type":"Retail Goods"
        }
    ],
    "sg:phone":"+1 972 463 4918",
    "sg:postcode":"75089",
    "sg:province":"TX",
    "wof:name":"Affordable Health",
    "wof:placetype":"venue"
},
  "geometry": {"coordinates":[-96.57428299999999,32.919278],"type":"Point"}
}