{
  "type": "Feature",
  "properties": {
    "iso:country":"US",
    "sg:address":"2909 Keller Rd",
    "sg:city":"Temple",
    "sg:classifiers":[
        {
            "category":"Building & Trades",
            "subcategory":"Construction",
            "type":"Services"
        }
    ],
    "sg:phone":"+1 254 778 1443",
    "sg:postcode":"76504",
    "sg:province":"TX",
    "sg:tags":[
        "repairing",
        "remodeling",
        "contractor"
    ],
    "wof:name":"Cedar Ridge Trim",
    "wof:placetype":"venue"
},
  "geometry": {"coordinates":[-97.37440700000001,31.101006],"type":"Point"}
}