{
  "type": "Feature",
  "properties": {
    "iso:country":"US",
    "sg:address":"1020 Montana Ave",
    "sg:city":"El Paso",
    "sg:classifiers":[
        {
            "category":"Professional",
            "subcategory":"Business Services",
            "type":"Services"
        }
    ],
    "sg:phone":"+1 915 534 7000",
    "sg:postcode":"79902",
    "sg:province":"TX",
    "wof:name":"Hammond Terry W & Associates",
    "wof:placetype":"venue"
},
  "geometry": {"coordinates":[-106.483801,31.768832],"type":"Point"}
}