{
  "type": "Feature",
  "properties": {
    "iso:country":"US",
    "sg:address":"9709 Swansons Ranch Rd",
    "sg:city":"Austin",
    "sg:classifiers":[
        {
            "category":"Retail",
            "subcategory":"Auto Repair",
            "type":"Services"
        }
    ],
    "sg:phone":"+1 512 292 3277",
    "sg:postcode":"78748",
    "sg:province":"TX",
    "wof:name":"T-N-D Automotive",
    "wof:placetype":"venue"
},
  "geometry": {"coordinates":[-97.816112,30.17309],"type":"Point"}
}