{
  "type": "Feature",
  "properties": {
    "iso:country":"US",
    "sg:address":"8550 Katy Fwy",
    "sg:city":"Houston",
    "sg:classifiers":[
        {
            "category":"Professional",
            "type":"Services"
        }
    ],
    "sg:phone":"+1 713 468 7951",
    "sg:postcode":"77024",
    "sg:province":"TX",
    "sg:tags":[
        "establishment"
    ],
    "wof:name":"Logtark International",
    "wof:placetype":"venue"
},
  "geometry": {"coordinates":[-95.49332800000001,29.784277],"type":"Point"}
}