{
  "type": "Feature",
  "properties": {
    "iso:country":"US",
    "sg:address":"531 S 3rd St",
    "sg:city":"Bellaire",
    "sg:classifiers":[
        {
            "category":"Manufacturing",
            "subcategory":"Metals",
            "type":"Manufacturing & Wholesale Goods"
        }
    ],
    "sg:phone":"+1 713 782 1727",
    "sg:postcode":"77401",
    "sg:province":"TX",
    "sg:tags":[
        "fabricated",
        "structural"
    ],
    "sg:website":"www.edreed.com",
    "wof:name":"Ed Reed Co",
    "wof:placetype":"venue"
},
  "geometry": {"coordinates":[-95.46662499999999,29.699558],"type":"Point"}
}