{
  "type": "Feature",
  "properties": {
    "iso:country":"US",
    "sg:address":"12104 Westheimer Rd",
    "sg:city":"Houston",
    "sg:classifiers":[
        {
            "category":"Retail",
            "subcategory":"Laundry & Dry Cleaning",
            "type":"Services"
        }
    ],
    "sg:phone":"+1 281 584 0566",
    "sg:postcode":"77077",
    "sg:province":"TX",
    "sg:tags":[
        "cleaners"
    ],
    "wof:name":"Beh's Cleaning Alterations",
    "wof:placetype":"venue"
},
  "geometry": {"coordinates":[-95.592713,29.73637],"type":"Point"}
}