{
  "type": "Feature",
  "properties": {
    "iso:country":"US",
    "sg:address":"3902 N Chadbourne St",
    "sg:city":"San Angelo",
    "sg:classifiers":[
        {
            "category":"Food & Beverages",
            "subcategory":"Groceries & Convenience Stores",
            "type":"Retail Goods"
        }
    ],
    "sg:phone":"+1 325 653 7707",
    "sg:postcode":"76903",
    "sg:province":"TX",
    "sg:tags":[
        "station",
        "gasoline"
    ],
    "wof:name":"Town & Country Food Store 5",
    "wof:placetype":"venue"
},
  "geometry": {"coordinates":[-100.46031499999999,31.498745],"type":"Point"}
}