{
  "type": "Feature",
  "properties": {
    "iso:country":"US",
    "sg:address":"9898 Bissonnet St",
    "sg:city":"Houston",
    "sg:classifiers":[
        {
            "category":"Organizations",
            "subcategory":"Religious Organization",
            "type":"Services"
        }
    ],
    "sg:phone":"+1 713 270 8554",
    "sg:postcode":"77036",
    "sg:province":"TX",
    "sg:tags":[
        "church"
    ],
    "wof:name":"Living Water Ministries",
    "wof:placetype":"venue"
},
  "geometry": {"coordinates":[-95.55271500000001,29.675152],"type":"Point"}
}