{
  "type": "Feature",
  "properties": {
    "iso:country":"US",
    "sg:address":"7920 Belt Line Rd",
    "sg:city":"Dallas",
    "sg:classifiers":[
        {
            "category":"Professional",
            "subcategory":"Credit Reporting & Collection",
            "type":"Services"
        }
    ],
    "sg:phone":"+1 972 991 1339",
    "sg:postcode":"75254",
    "sg:province":"TX",
    "sg:tags":[
        "mortgage"
    ],
    "wof:name":"Northrop Grumman Space",
    "wof:placetype":"venue"
},
  "geometry": {"coordinates":[-96.769818,32.95064],"type":"Point"}
}