{
  "type": "Feature",
  "properties": {
    "iso:country":"US",
    "sg:address":"913 Hewitt Dr",
    "sg:city":"Woodway",
    "sg:classifiers":[
        {
            "category":"Restaurant",
            "type":"Food & Drink"
        }
    ],
    "sg:menulink":"http://www.allmenus.com/tx/waco/201898-mcdonalds/menu/",
    "sg:postcode":"76712",
    "sg:province":"TX",
    "sg:tags":[
        "burger",
        "american"
    ],
    "wof:name":"McDonald's",
    "wof:placetype":"venue"
},
  "geometry": {"coordinates":[-97.21307400000001,31.489479],"type":"Point"}
}