{
  "type": "Feature",
  "properties": {
    "iso:country":"US",
    "sg:address":"4003 Old Spanish Trl",
    "sg:city":"Houston",
    "sg:classifiers":[
        {
            "category":"Organizations",
            "subcategory":"Religious Organization",
            "type":"Services"
        }
    ],
    "sg:phone":"+1 713 842 5863",
    "sg:postcode":"77021",
    "sg:province":"TX",
    "wof:name":"Miracle of Hope Church",
    "wof:placetype":"venue"
},
  "geometry": {"coordinates":[-95.355564,29.70265],"type":"Point"}
}