{
  "type": "Feature",
  "properties": {
    "iso:country":"US",
    "sg:address":"907 Chelsea St",
    "sg:city":"El Paso",
    "sg:classifiers":[
        {
            "category":"Shopping",
            "type":"Retail Goods"
        }
    ],
    "sg:phone":"+1 915 772 6010",
    "sg:postcode":"79903",
    "sg:province":"TX",
    "sg:tags":[
        "cellular",
        "merchandise",
        "telephone"
    ],
    "wof:name":"Universal Communications",
    "wof:placetype":"venue"
},
  "geometry": {"coordinates":[-106.42558099999999,31.783521],"type":"Point"}
}