{
  "type": "Feature",
  "properties": {
    "iso:country":"US",
    "sg:address":"5106 Peppertree Pkwy",
    "sg:city":"Austin",
    "sg:classifiers":[
        {
            "category":"Building & Trades",
            "subcategory":"Landscaping Services",
            "type":"Services"
        }
    ],
    "sg:phone":"+1 512 731 2443",
    "sg:postcode":"78744",
    "sg:province":"TX",
    "sg:tags":[
        "tree"
    ],
    "wof:name":"Textafari",
    "wof:placetype":"venue"
},
  "geometry": {"coordinates":[-97.75162400000001,30.201532],"type":"Point"}
}