{
  "type": "Feature",
  "properties": {
    "iso:country":"US",
    "sg:address":"211 S Brazos St",
    "sg:city":"Whitney",
    "sg:classifiers":[
        {
            "category":"Professional",
            "subcategory":"Computer Services",
            "type":"Services"
        }
    ],
    "sg:phone":"+1 254 694 5092",
    "sg:postcode":"76692",
    "sg:province":"TX",
    "sg:tags":[
        "prepackaged",
        "software"
    ],
    "wof:name":"Data Results Inc",
    "wof:placetype":"venue"
},
  "geometry": {"coordinates":[-97.320626,31.946197],"type":"Point"}
}