{
  "type": "Feature",
  "properties": {
    "iso:country":"US",
    "sg:address":"5431 Firestar Trl",
    "sg:city":"San Antonio",
    "sg:classifiers":[
        {
            "category":"Professional",
            "subcategory":"Business Services",
            "type":"Services"
        }
    ],
    "sg:phone":"+1 210 648 0944",
    "sg:postcode":"78222",
    "sg:province":"TX",
    "wof:name":"Jn Enterprises",
    "wof:placetype":"venue"
},
  "geometry": {"coordinates":[-98.385339,29.373944],"type":"Point"}
}