{
  "type": "Feature",
  "properties": {
    "iso:country":"US",
    "sg:address":"2840 Keller Springs Rd Ste 901",
    "sg:city":"Carrollton",
    "sg:classifiers":[
        {
            "category":"Health Services",
            "subcategory":"Chiropractor",
            "type":"Services"
        }
    ],
    "sg:phone":"+1 972 416 3439",
    "sg:postcode":"75006",
    "sg:province":"TX",
    "sg:website":"www.holisticharmonycenter.com",
    "wof:name":"Holistic Harmony Center",
    "wof:placetype":"venue"
},
  "geometry": {"coordinates":[-96.85858500000001,32.970233],"type":"Point"}
}