{
  "type": "Feature",
  "properties": {
    "iso:country":"US",
    "sg:address":"6548 Windrock Dr",
    "sg:city":"Fort Worth",
    "sg:classifiers":[
        {
            "category":"Organizations",
            "subcategory":"Religious Organization",
            "type":"Services"
        }
    ],
    "sg:phone":"+1 817 485 8850",
    "sg:postcode":"76148",
    "sg:province":"TX",
    "wof:name":"Hodesh Ministries",
    "wof:placetype":"venue"
},
  "geometry": {"coordinates":[-97.24183499999999,32.880711],"type":"Point"}
}