{
  "type": "Feature",
  "properties": {
    "iso:country":"US",
    "sg:address":"1912 K Ave",
    "sg:city":"Plano",
    "sg:classifiers":[
        {
            "category":"Banks & Credit Unions",
            "subcategory":"Bank",
            "type":"Services"
        }
    ],
    "sg:phone":"+1 972 578 7777",
    "sg:postcode":"75074",
    "sg:province":"TX",
    "sg:website":"www.fibtx.com",
    "wof:name":"First International Bank",
    "wof:placetype":"venue"
},
  "geometry": {"coordinates":[-96.699027,33.02659],"type":"Point"}
}