{
  "type": "Feature",
  "properties": {
    "iso:country":"US",
    "sg:address":"263 E 40th St",
    "sg:city":"San Angelo",
    "sg:classifiers":[
        {
            "category":"Organizations",
            "subcategory":"Religious Organization",
            "type":"Services"
        }
    ],
    "sg:phone":"+1 325 653 2845",
    "sg:postcode":"76903",
    "sg:province":"TX",
    "sg:tags":[
        "church"
    ],
    "wof:name":"Lake View United Methodist",
    "wof:placetype":"venue"
},
  "geometry": {"coordinates":[-100.453215,31.500756],"type":"Point"}
}