{
  "type": "Feature",
  "properties": {
    "iso:country":"US",
    "sg:address":"500 Broad St",
    "sg:city":"Wichita Falls",
    "sg:classifiers":[
        {
            "category":"Health Services",
            "subcategory":"Hospital",
            "type":"Services"
        }
    ],
    "sg:phone":"+1 940 397 3300",
    "sg:postcode":"76301",
    "sg:province":"TX",
    "sg:tags":[
        "mental"
    ],
    "wof:name":"Helen Farabee Regional Ctr",
    "wof:placetype":"venue"
},
  "geometry": {"coordinates":[-98.500862,33.909749],"type":"Point"}
}