{
  "type": "Feature",
  "properties": {
    "iso:country":"US",
    "sg:address":"1300 W Nolana Loop",
    "sg:city":"Pharr",
    "sg:classifiers":[
        {
            "category":"Bars & Pubs",
            "type":"Food & Drink"
        }
    ],
    "sg:phone":"+1 956 702 1984",
    "sg:postcode":"78577",
    "sg:province":"TX",
    "sg:tags":[
        "drinking"
    ],
    "wof:name":"Tejano Saloon",
    "wof:placetype":"venue"
},
  "geometry": {"coordinates":[-98.18945100000001,26.234802],"type":"Point"}
}