{
  "type": "Feature",
  "properties": {
    "iso:country":"US",
    "sg:address":"1914 Augusta Dr",
    "sg:city":"Houston",
    "sg:phone":"+1 713 780 7633",
    "sg:postcode":"77057",
    "sg:province":"TX",
    "sg:tags":[
        "product",
        "petroleum"
    ],
    "wof:name":"Austin Chalk Oil & Gas Ltd",
    "wof:placetype":"venue"
},
  "geometry": {"coordinates":[-95.48271099999999,29.749953],"type":"Point"}
}