{
  "type": "Feature",
  "properties": {
    "iso:country":"US",
    "sg:address":"2715 Loop 256",
    "sg:city":"Palestine",
    "sg:classifiers":[
        {
            "category":"Home & Garden",
            "subcategory":"Building Materials",
            "type":"Retail Goods"
        }
    ],
    "sg:phone":"+1 903 723 6400",
    "sg:postcode":"75801",
    "sg:province":"TX",
    "sg:tags":[
        "center",
        "improvement"
    ],
    "wof:name":"Lowes",
    "wof:placetype":"venue"
},
  "geometry": {"coordinates":[-95.621807,31.733112],"type":"Point"}
}