{
  "type": "Feature",
  "properties": {
    "iso:country":"US",
    "sg:address":"8500 Viscount Blvd",
    "sg:city":"El Paso",
    "sg:classifiers":[
        {
            "category":"Retail",
            "subcategory":"Laundry & Dry Cleaning",
            "type":"Services"
        }
    ],
    "sg:phone":"+1 915 274 5173",
    "sg:postcode":"79925",
    "sg:province":"TX",
    "wof:name":"Miriam Garcia",
    "wof:placetype":"venue"
},
  "geometry": {"coordinates":[-106.37463700000001,31.775658],"type":"Point"}
}