{
  "type": "Feature",
  "properties": {
    "iso:country":"US",
    "sg:address":"701 E Main St",
    "sg:city":"Lewisville",
    "sg:classifiers":[
        {
            "category":"Building & Trades",
            "subcategory":"Construction",
            "type":"Services"
        }
    ],
    "sg:phone":"+1 972 874 8724",
    "sg:postcode":"75057",
    "sg:province":"TX",
    "sg:tags":[
        "general",
        "contractor"
    ],
    "sg:website":"www.graniteconstruction.com",
    "wof:name":"Granite Construction Co",
    "wof:placetype":"venue"
},
  "geometry": {"coordinates":[-96.98118100000001,33.043127],"type":"Point"}
}