{
  "type": "Feature",
  "properties": {
    "iso:country":"US",
    "sg:address":"1200 Oak St",
    "sg:city":"Corsicana",
    "sg:classifiers":[
        {
            "category":"Building & Trades",
            "subcategory":"Construction",
            "type":"Services"
        }
    ],
    "sg:phone":"+1 903 872 4897",
    "sg:postcode":"75110",
    "sg:province":"TX",
    "sg:website":"www.watkinsdevelopment.com",
    "wof:name":"Watkins Development Corp",
    "wof:placetype":"venue"
},
  "geometry": {"coordinates":[-96.461865,32.108902],"type":"Point"}
}