{
  "type": "Feature",
  "properties": {
    "iso:country":"US",
    "sg:address":"911 Federal Rd",
    "sg:city":"Houston",
    "sg:classifiers":[
        {
            "category":"Building & Trades",
            "subcategory":"Construction",
            "type":"Services"
        }
    ],
    "sg:phone":"+1 713 450 1150",
    "sg:postcode":"77015",
    "sg:province":"TX",
    "sg:tags":[
        "carpenter"
    ],
    "wof:name":"Jamac Services",
    "wof:placetype":"venue"
},
  "geometry": {"coordinates":[-95.21717700000001,29.774465],"type":"Point"}
}