{
  "type": "Feature",
  "properties": {
    "iso:country":"US",
    "sg:address":"2905 Denison Ave",
    "sg:city":"Snyder",
    "sg:classifiers":[
        {
            "category":"Banks & Credit Unions",
            "subcategory":"Investment Brokerage",
            "type":"Services"
        }
    ],
    "sg:phone":"+1 325 574 2552",
    "sg:postcode":"79549",
    "sg:province":"TX",
    "wof:name":"SBB Inc",
    "wof:placetype":"venue"
},
  "geometry": {"coordinates":[-100.93143000000001,32.712967],"type":"Point"}
}