{
  "type": "Feature",
  "properties": {
    "iso:country":"US",
    "sg:address":"404 N Witter St",
    "sg:city":"Pasadena",
    "sg:classifiers":[
        {
            "category":"Freight",
            "type":"Transportation"
        }
    ],
    "sg:phone":"+1 281 932 4499",
    "sg:postcode":"77506",
    "sg:province":"TX",
    "sg:tags":[
        "warehouse",
        "distribution",
        "public"
    ],
    "wof:name":"Gulf Winds International Inc",
    "wof:placetype":"venue"
},
  "geometry": {"coordinates":[-95.203344,29.717263],"type":"Point"}
}