{
  "type": "Feature",
  "properties": {
    "iso:country":"US",
    "sg:address":"2150 Linda Ln",
    "sg:city":"Pearland",
    "sg:classifiers":[
        {
            "category":"Professional",
            "subcategory":"Art Services",
            "type":"Services"
        }
    ],
    "sg:phone":"+1 281 485 7963",
    "sg:postcode":"77584",
    "sg:province":"TX",
    "sg:tags":[
        "commercial",
        "design"
    ],
    "wof:name":"Yorke Design Studio",
    "wof:placetype":"venue"
},
  "geometry": {"coordinates":[-95.35851700000001,29.57049],"type":"Point"}
}