{
  "type": "Feature",
  "properties": {
    "iso:country":"US",
    "sg:address":"11535 Harry Hines Blvd",
    "sg:city":"Dallas",
    "sg:classifiers":[
        {
            "category":"Retail",
            "subcategory":"Auto Rental",
            "type":"Services"
        }
    ],
    "sg:phone":"+1 972 241 1930",
    "sg:postcode":"75229",
    "sg:province":"TX",
    "sg:tags":[
        "car"
    ],
    "wof:name":"Car Search Auto Sales",
    "wof:placetype":"venue"
},
  "geometry": {"coordinates":[-96.89360000000001,32.902],"type":"Point"}
}