{
  "type": "Feature",
  "properties": {
    "iso:country":"US",
    "sg:address":"5017 W Expy 83",
    "sg:city":"Mcallen",
    "sg:classifiers":[
        {
            "category":"Local Transit",
            "type":"Transportation"
        }
    ],
    "sg:phone":"+1 956 519 0346",
    "sg:postcode":"78503",
    "sg:province":"TX",
    "sg:tags":[
        "passenger"
    ],
    "wof:name":"Lifeline EMS",
    "wof:placetype":"venue"
},
  "geometry": {"coordinates":[-98.27167799999999,26.195508],"type":"Point"}
}