{
  "type": "Feature",
  "properties": {
    "iso:country":"US",
    "sg:address":"318 Bluebonnet Cir",
    "sg:city":"Mc Gregor",
    "sg:classifiers":[
        {
            "category":"Professional",
            "subcategory":"Management & Consulting",
            "type":"Services"
        }
    ],
    "sg:phone":"+1 254 848 5960",
    "sg:postcode":"76657",
    "sg:province":"TX",
    "sg:tags":[
        "business"
    ],
    "wof:name":"Kathy Watha",
    "wof:placetype":"venue"
},
  "geometry": {"coordinates":[-97.312122,31.475797],"type":"Point"}
}