{
  "type": "Feature",
  "properties": {
    "iso:country":"US",
    "sg:address":"3341 FM 439",
    "sg:city":"Belton",
    "sg:classifiers":[
        {
            "category":"Arts & Performance",
            "subcategory":"Theater",
            "type":"Entertainment"
        }
    ],
    "sg:phone":"+1 254 939 0226",
    "sg:postcode":"76513",
    "sg:province":"TX",
    "sg:tags":[
        "live",
        "music"
    ],
    "wof:name":"Cliff Rock Productions",
    "wof:placetype":"venue"
},
  "geometry": {"coordinates":[-97.48839599999999,31.101523],"type":"Point"}
}