{
  "type": "Feature",
  "properties": {
    "iso:country":"US",
    "sg:address":"2600 W 81st St",
    "sg:city":"Odessa",
    "sg:classifiers":[
        {
            "category":"Wholesale",
            "subcategory":"Machinery & Supplies",
            "type":"Manufacturing & Wholesale Goods"
        }
    ],
    "sg:phone":"+1 432 366 2514",
    "sg:postcode":"79764",
    "sg:province":"TX",
    "sg:tags":[
        "boring",
        "drilling"
    ],
    "sg:website":"www.wfjdrillingtools.com",
    "wof:name":"WFJ Drilling Tools Inc",
    "wof:placetype":"venue"
},
  "geometry": {"coordinates":[-102.42719,31.919243],"type":"Point"}
}