{
  "type": "Feature",
  "properties": {
    "iso:country":"US",
    "sg:address":"225 W Mulberry St",
    "sg:city":"Denton",
    "sg:classifiers":[
        {
            "category":"Banks & Credit Unions",
            "subcategory":"Bank",
            "type":"Services"
        },
        {
            "category":"Professional",
            "subcategory":"Employment Agencies",
            "type":"Services"
        }
    ],
    "sg:phone":"+1 940 387 8585",
    "sg:postcode":"76201",
    "sg:province":"TX",
    "wof:name":"Denton Area Teachers CU",
    "wof:placetype":"venue"
},
  "geometry": {"coordinates":[-97.134635,33.213461],"type":"Point"}
}