{
  "type": "Feature",
  "properties": {
    "iso:country":"US",
    "sg:address":"1730 Boston Ave",
    "sg:city":"Bridgeport",
    "sg:classifiers":[
        {
            "category":"Freight",
            "type":"Transportation"
        }
    ],
    "sg:phone":"+1 940 683 6311",
    "sg:postcode":"76426",
    "sg:province":"TX",
    "sg:tags":[
        "operator",
        "local",
        "trucking"
    ],
    "wof:name":"Special Deliveries",
    "wof:placetype":"venue"
},
  "geometry": {"coordinates":[-97.744906,33.206482],"type":"Point"}
}