{
  "type": "Feature",
  "properties": {
    "iso:country":"US",
    "sg:address":"1652 McKnight Rd",
    "sg:city":"Seguin",
    "sg:classifiers":[
        {
            "category":"Manufacturing",
            "subcategory":"Chemicals & Compounds",
            "type":"Manufacturing & Wholesale Goods"
        }
    ],
    "sg:phone":"+1 830 379 2499",
    "sg:postcode":"78155",
    "sg:province":"TX",
    "sg:tags":[
        "fertilizer",
        "only",
        "mfg"
    ],
    "wof:name":"Dooner Organics Inc",
    "wof:placetype":"venue"
},
  "geometry": {"coordinates":[-97.89425199999999,29.498129],"type":"Point"}
}