{
  "type": "Feature",
  "properties": {
    "iso:country":"US",
    "sg:address":"220 N Mesa St",
    "sg:city":"El Paso",
    "sg:classifiers":[
        {
            "category":"Restaurant",
            "type":"Food & Drink"
        }
    ],
    "sg:phone":"+1 915 543 6006",
    "sg:postcode":"79901",
    "sg:province":"TX",
    "wof:name":"Royal Chinese Express",
    "wof:placetype":"venue"
},
  "geometry": {"coordinates":[-106.487632,31.759467],"type":"Point"}
}