{
  "type": "Feature",
  "properties": {
    "iso:country":"US",
    "sg:address":"321 W 19th St",
    "sg:city":"Houston",
    "sg:classifiers":[
        {
            "category":"Home & Garden",
            "subcategory":"Home Furnishings",
            "type":"Retail Goods"
        }
    ],
    "sg:phone":"+1 713 880 5100",
    "sg:postcode":"77008",
    "sg:province":"TX",
    "wof:name":"Tansu",
    "wof:placetype":"venue"
},
  "geometry": {"coordinates":[-95.40322500000001,29.802963],"type":"Point"}
}