{
  "type": "Feature",
  "properties": {
    "iso:country":"US",
    "sg:address":"6138 Luther Ln",
    "sg:city":"Dallas",
    "sg:classifiers":[
        {
            "category":"Shopping",
            "subcategory":"Clothing, Apparel, & Fashions",
            "type":"Retail Goods"
        }
    ],
    "sg:phone":"+1 214 369 2243",
    "sg:postcode":"75225",
    "sg:province":"TX",
    "wof:name":"Kids Kloset",
    "wof:placetype":"venue"
},
  "geometry": {"coordinates":[-96.80427299999999,32.863574],"type":"Point"}
}