{
  "type": "Feature",
  "properties": {
    "iso:country":"US",
    "sg:address":"1901 Texas Ave S",
    "sg:city":"Bryan",
    "sg:classifiers":[
        {
            "category":"Food & Beverages",
            "subcategory":"Groceries & Convenience Stores",
            "type":"Retail Goods"
        }
    ],
    "sg:phone":"+1 979 822 8002",
    "sg:postcode":"77802",
    "sg:province":"TX",
    "sg:tags":[
        "supermarket"
    ],
    "wof:name":"Albertsons 2796",
    "wof:placetype":"venue"
},
  "geometry": {"coordinates":[-96.361368,30.65074],"type":"Point"}
}