{
  "type": "Feature",
  "properties": {
    "iso:country":"US",
    "sg:address":"3012 Canal St",
    "sg:city":"Houston",
    "sg:classifiers":[
        {
            "category":"Professional",
            "subcategory":"Business Services",
            "type":"Services"
        }
    ],
    "sg:phone":"+1 713 228 8900",
    "sg:postcode":"77003",
    "sg:province":"TX",
    "wof:name":"In Fleet Safety Equipment",
    "wof:placetype":"venue"
},
  "geometry": {"coordinates":[-95.340509,29.75416],"type":"Point"}
}