{
  "type": "Feature",
  "properties": {
    "iso:country":"US",
    "sg:address":"4121 S Padre Island Dr",
    "sg:city":"Corpus Christi",
    "sg:classifiers":[
        {
            "category":"Building & Trades",
            "subcategory":"Construction",
            "type":"Services"
        }
    ],
    "sg:phone":"+1 361 654 2241",
    "sg:postcode":"78411",
    "sg:province":"TX",
    "sg:tags":[
        "contractor"
    ],
    "wof:name":"Oceanview Builders",
    "wof:placetype":"venue"
},
  "geometry": {"coordinates":[-97.39445499999999,27.719241],"type":"Point"}
}