{
  "type": "Feature",
  "properties": {
    "iso:country":"US",
    "sg:address":"303 W 19th St",
    "sg:city":"Houston",
    "sg:classifiers":[
        {
            "category":"Personal",
            "subcategory":"Shoe Repair & Shine",
            "type":"Services"
        }
    ],
    "sg:phone":"+1 713 802 1323",
    "sg:postcode":"77008",
    "sg:province":"TX",
    "wof:name":"Almogabar's Shoe Shop & Western Goods",
    "wof:placetype":"venue"
},
  "geometry": {"coordinates":[-95.40149700000001,29.802799],"type":"Point"}
}