{
  "type": "Feature",
  "properties": {
    "iso:country":"US",
    "sg:address":"309 N Main St",
    "sg:city":"Higgins",
    "sg:classifiers":[
        {
            "category":"Organizations",
            "subcategory":"Religious Organization",
            "type":"Services"
        }
    ],
    "sg:phone":"+1 806 852 2811",
    "sg:postcode":"79014",
    "sg:province":"TX",
    "sg:tags":[
        "church"
    ],
    "wof:name":"First Baptist Church",
    "wof:placetype":"venue"
},
  "geometry": {"coordinates":[-100.02663699999999,36.122374],"type":"Point"}
}