{
  "type": "Feature",
  "properties": {
    "iso:country":"US",
    "sg:address":"1400 Main St",
    "sg:city":"Dallas",
    "sg:classifiers":[
        {
            "category":"Professional",
            "type":"Services"
        }
    ],
    "sg:phone":"+1 214 651 9113",
    "sg:postcode":"75202",
    "sg:province":"TX",
    "sg:tags":[
        "establishment"
    ],
    "wof:name":"Pegasus Room",
    "wof:placetype":"venue"
},
  "geometry": {"coordinates":[-96.799503,32.780572],"type":"Point"}
}