{
  "type": "Feature",
  "properties": {
    "iso:country":"US",
    "sg:address":"339 W US Hwy 79",
    "sg:city":"Rockdale",
    "sg:classifiers":[
        {
            "category":"Autos & Motor Vehicles",
            "subcategory":"Boat Sales",
            "type":"Retail Goods"
        }
    ],
    "sg:phone":"+1 512 446 3482",
    "sg:postcode":"76567",
    "sg:province":"TX",
    "sg:tags":[
        "equipment",
        "marine",
        "supply"
    ],
    "wof:name":"Marine Outlet Inc",
    "wof:placetype":"venue"
},
  "geometry": {"coordinates":[-97.00385799999999,30.654373],"type":"Point"}
}