{
  "type": "Feature",
  "properties": {
    "iso:country":"US",
    "sg:address":"2120 52nd St",
    "sg:city":"Dallas",
    "sg:classifiers":[
        {
            "category":"Real Estate",
            "subcategory":"Real Estate Operator",
            "type":"Services"
        }
    ],
    "sg:phone":"+1 214 371 1516",
    "sg:postcode":"75216",
    "sg:province":"TX",
    "sg:tags":[
        "apartment"
    ],
    "wof:name":"Oak Glen Apartments",
    "wof:placetype":"venue"
},
  "geometry": {"coordinates":[-96.789596,32.690096],"type":"Point"}
}