{
  "type": "Feature",
  "properties": {
    "iso:country":"US",
    "sg:address":"8220 Walnut Hill Ln",
    "sg:city":"Dallas",
    "sg:classifiers":[
        {
            "category":"Health Services",
            "subcategory":"Doctor",
            "type":"Services"
        }
    ],
    "sg:phone":"+1 214 739 0016",
    "sg:postcode":"75231",
    "sg:province":"TX",
    "sg:tags":[
        "physician",
        "surgeon"
    ],
    "wof:name":"E Clark Odom MD",
    "wof:placetype":"venue"
},
  "geometry": {"coordinates":[-96.759793,32.88317],"type":"Point"}
}