{
  "type": "Feature",
  "properties": {
    "iso:country":"US",
    "sg:address":"1909 Duroux Rd",
    "sg:city":"La Marque",
    "sg:classifiers":[
        {
            "category":"Social Services",
            "subcategory":"Child Care",
            "type":"Services"
        }
    ],
    "sg:phone":"+1 409 935 9359",
    "sg:postcode":"77568",
    "sg:province":"TX",
    "wof:name":"Nettie Close Ola",
    "wof:placetype":"venue"
},
  "geometry": {"coordinates":[-94.995502,29.367325],"type":"Point"}
}