{
  "type": "Feature",
  "properties": {
    "iso:country":"US",
    "sg:address":"34 Lanell Dr",
    "sg:city":"Belton",
    "sg:classifiers":[
        {
            "category":"Freight",
            "type":"Transportation"
        }
    ],
    "sg:phone":"+1 254 939 8603",
    "sg:postcode":"76513",
    "sg:province":"TX",
    "sg:tags":[
        "truck",
        "excavating",
        "tree",
        "hauling",
        "dump"
    ],
    "wof:name":"Duck Works",
    "wof:placetype":"venue"
},
  "geometry": {"coordinates":[-97.524361,31.042109],"type":"Point"}
}