{
  "type": "Feature",
  "properties": {
    "iso:country":"US",
    "sg:address":"14519 Triple Crown Ln",
    "sg:city":"San Antonio",
    "sg:classifiers":[
        {
            "category":"Professional",
            "subcategory":"Business Services",
            "type":"Services"
        }
    ],
    "sg:phone":"+1 210 493 8664",
    "sg:postcode":"78248",
    "sg:province":"TX",
    "wof:name":"Magna Vibe",
    "wof:placetype":"venue"
},
  "geometry": {"coordinates":[-98.532838,29.580448],"type":"Point"}
}