{
  "type": "Feature",
  "properties": {
    "iso:country":"US",
    "sg:address":"701 S 1st St",
    "sg:city":"Lamesa",
    "sg:classifiers":[
        {
            "category":"Banks & Credit Unions",
            "subcategory":"Investment Brokerage",
            "type":"Services"
        }
    ],
    "sg:phone":"+1 806 872 4545",
    "sg:postcode":"79331",
    "sg:province":"TX",
    "sg:tags":[
        "stock",
        "bond"
    ],
    "wof:name":"Edward Jones Co",
    "wof:placetype":"venue"
},
  "geometry": {"coordinates":[-101.955178,32.731378],"type":"Point"}
}