{
  "type": "Feature",
  "properties": {
    "iso:country":"US",
    "sg:address":"3307 Terry St",
    "sg:city":"Houston",
    "sg:classifiers":[
        {
            "category":"Personal",
            "type":"Services"
        }
    ],
    "sg:phone":"+1 832 889 7415",
    "sg:postcode":"77009",
    "sg:province":"TX",
    "sg:tags":[
        "mover"
    ],
    "sg:website":"www.launionmovers.net",
    "wof:name":"La Union Movers",
    "wof:placetype":"venue"
},
  "geometry": {"coordinates":[-95.353217,29.790713],"type":"Point"}
}