{
  "type": "Feature",
  "properties": {
    "iso:country":"US",
    "sg:address":"3610 Green Spring",
    "sg:city":"San Antonio",
    "sg:classifiers":[
        {
            "category":"Professional",
            "type":"Services"
        }
    ],
    "sg:phone":"+1 210 494 4613",
    "sg:postcode":"78247",
    "sg:province":"TX",
    "wof:name":"Just For You Custom Puppe",
    "wof:placetype":"venue"
},
  "geometry": {"coordinates":[-98.424978,29.582859],"type":"Point"}
}