{
  "type": "Feature",
  "properties": {
    "iso:country":"US",
    "sg:address":"3804 Greystone Dr",
    "sg:city":"Austin",
    "sg:classifiers":[
        {
            "category":"Social Services",
            "type":"Services"
        }
    ],
    "sg:phone":"+1 512 418 9632",
    "sg:postcode":"78731",
    "sg:province":"TX",
    "wof:name":"Leslie Massad",
    "wof:placetype":"venue"
},
  "geometry": {"coordinates":[-97.754229,30.359044],"type":"Point"}
}