{
  "type": "Feature",
  "properties": {
    "iso:country":"US",
    "sg:address":"724 N Lamar Blvd",
    "sg:city":"Austin",
    "sg:classifiers":[
        {
            "category":"Autos & Motor Vehicles",
            "subcategory":"Automobile Sales",
            "type":"Retail Goods"
        }
    ],
    "sg:phone":"+1 512 473 2300",
    "sg:postcode":"78703",
    "sg:province":"TX",
    "sg:tags":[
        "car",
        "used",
        "dealer"
    ],
    "sg:website":"www.austinsportscars.com",
    "wof:name":"Austin Sports Cars Inc",
    "wof:placetype":"venue"
},
  "geometry": {"coordinates":[-97.753269,30.272975],"type":"Point"}
}