{
  "type": "Feature",
  "properties": {
    "iso:country":"US",
    "sg:address":"1720 N Galloway Ave",
    "sg:city":"Mesquite",
    "sg:classifiers":[
        {
            "category":"Building & Trades",
            "subcategory":"Cleaning & Sanitation",
            "type":"Services"
        }
    ],
    "sg:phone":"+1 972 216 7078",
    "sg:postcode":"75149",
    "sg:province":"TX",
    "sg:tags":[
        "maintenance"
    ],
    "wof:name":"Daystar Cleaning Service",
    "wof:placetype":"venue"
},
  "geometry": {"coordinates":[-96.605024,32.785979],"type":"Point"}
}