{
  "type": "Feature",
  "properties": {
    "iso:country":"US",
    "sg:address":"130 W Hundley Dr",
    "sg:city":"Lake Dallas",
    "sg:classifiers":[
        {
            "category":"Health Services",
            "subcategory":"Doctor",
            "type":"Services"
        }
    ],
    "sg:phone":"+1 940 497 2204",
    "sg:postcode":"75065",
    "sg:province":"TX",
    "sg:tags":[
        "physician",
        "surgeon",
        "medical"
    ],
    "wof:name":"Lake Cities Medical Center",
    "wof:placetype":"venue"
},
  "geometry": {"coordinates":[-97.03103900000001,33.122514],"type":"Point"}
}