{
  "type": "Feature",
  "properties": {
    "iso:country":"US",
    "sg:address":"5801 Harrington Cove",
    "sg:city":"Austin",
    "sg:classifiers":[
        {
            "category":"Real Estate",
            "subcategory":"Real Estate Agent",
            "type":"Services"
        }
    ],
    "sg:phone":"+1 512 418 9012",
    "sg:postcode":"78731",
    "sg:province":"TX",
    "sg:tags":[
        "management"
    ],
    "wof:name":"East 54",
    "wof:placetype":"venue"
},
  "geometry": {"coordinates":[-97.788499,30.355255],"type":"Point"}
}