{
  "type": "Feature",
  "properties": {
    "iso:country":"US",
    "sg:address":"1609 Pearlie Dr",
    "sg:city":"Wichita Falls",
    "sg:classifiers":[
        {
            "category":"Retail",
            "subcategory":"Auto Repair",
            "type":"Services"
        }
    ],
    "sg:phone":"+1 940 851 5060",
    "sg:postcode":"76306",
    "sg:province":"TX",
    "sg:tags":[
        "automobile",
        "lubrication"
    ],
    "wof:name":"Quality Lube",
    "wof:placetype":"venue"
},
  "geometry": {"coordinates":[-98.51708600000001,33.964044],"type":"Point"}
}