{
  "type": "Feature",
  "properties": {
    "iso:country":"US",
    "sg:address":"2201 Long Prairie Rd",
    "sg:city":"Flower Mound",
    "sg:classifiers":[
        {
            "category":"Shopping",
            "subcategory":"Stationery & Office Supplies",
            "type":"Retail Goods"
        },
        {
            "category":"Professional",
            "subcategory":"Computer Services",
            "type":"Services"
        }
    ],
    "sg:phone":"+1 972 243 2222",
    "sg:postcode":"75022",
    "sg:province":"TX",
    "sg:tags":[
        "imaging",
        "software",
        "sales",
        "programing",
        "custom"
    ],
    "sg:website":"www.compuscan.com",
    "wof:name":"Compuscan Office Solutions Inc",
    "wof:placetype":"venue"
},
  "geometry": {"coordinates":[-97.070942,33.015521],"type":"Point"}
}