{
  "type": "Feature",
  "properties": {
    "iso:country":"US",
    "sg:address":"5524 W Ledbetter Dr",
    "sg:city":"Dallas",
    "sg:classifiers":[
        {
            "category":"Professional",
            "type":"Services"
        }
    ],
    "sg:phone":"+1 972 298 7434",
    "sg:postcode":"75236",
    "sg:province":"TX",
    "sg:tags":[
        "establishment"
    ],
    "wof:name":"Express Sales",
    "wof:placetype":"venue"
},
  "geometry": {"coordinates":[-96.917806,32.691062],"type":"Point"}
}