{
  "type": "Feature",
  "properties": {
    "iso:country":"US",
    "sg:address":"311 Meadow Dr",
    "sg:city":"Mesquite",
    "sg:classifiers":[
        {
            "category":"Professional",
            "subcategory":"Business Services",
            "type":"Services"
        }
    ],
    "sg:phone":"+1 972 226 0991",
    "sg:postcode":"75182",
    "sg:province":"TX",
    "wof:name":"L Davidson Group Inc",
    "wof:placetype":"venue"
},
  "geometry": {"coordinates":[-96.577974,32.793082],"type":"Point"}
}