{
  "type": "Feature",
  "properties": {
    "iso:country":"US",
    "sg:address":"220 E Elm St",
    "sg:city":"Breckenridge",
    "sg:classifiers":[
        {
            "category":"Retail",
            "subcategory":"Auto Repair",
            "type":"Services"
        }
    ],
    "sg:phone":"+1 254 559 1456",
    "sg:postcode":"76424",
    "sg:province":"TX",
    "sg:tags":[
        "body",
        "automobile",
        "painting"
    ],
    "wof:name":"Breckenridge Collision",
    "wof:placetype":"venue"
},
  "geometry": {"coordinates":[-98.900313,32.756339],"type":"Point"}
}