{
  "type": "Feature",
  "properties": {
    "iso:country":"US",
    "sg:address":"292 Pershing Blvd",
    "sg:city":"Bastrop",
    "sg:classifiers":[
        {
            "category":"Professional",
            "subcategory":"Detective & Security Services",
            "type":"Services"
        }
    ],
    "sg:phone":"+1 512 581 7938",
    "sg:postcode":"78602",
    "sg:province":"TX",
    "sg:tags":[
        "enforcement",
        "law"
    ],
    "wof:name":"Daniel Rivera",
    "wof:placetype":"venue"
},
  "geometry": {"coordinates":[-97.297383,30.198491],"type":"Point"}
}