{
  "type": "Feature",
  "properties": {
    "iso:country":"US",
    "sg:address":"4800 W 34th St",
    "sg:city":"Houston",
    "sg:classifiers":[
        {
            "category":"Professional",
            "subcategory":"Management & Consulting",
            "type":"Services"
        }
    ],
    "sg:phone":"+1 713 812 1496",
    "sg:postcode":"77092",
    "sg:province":"TX",
    "sg:tags":[
        "fuel"
    ],
    "wof:name":"Gallagher Management",
    "wof:placetype":"venue"
},
  "geometry": {"coordinates":[-95.461247,29.819669],"type":"Point"}
}