{
  "type": "Feature",
  "properties": {
    "iso:country":"US",
    "sg:address":"204 Montrose St",
    "sg:city":"Belton",
    "sg:classifiers":[
        {
            "category":"Building & Trades",
            "subcategory":"Landscaping Services",
            "type":"Services"
        }
    ],
    "sg:phone":"+1 254 939 3508",
    "sg:postcode":"76513",
    "sg:province":"TX",
    "wof:name":"Triple H Lawncare & Service",
    "wof:placetype":"venue"
},
  "geometry": {"coordinates":[-97.45968000000001,31.078317],"type":"Point"}
}