{
  "type": "Feature",
  "properties": {
    "iso:country":"US",
    "sg:address":"421 E Hickory St",
    "sg:city":"Denton",
    "sg:classifiers":[
        {
            "category":"Professional",
            "subcategory":"Detective & Security Services",
            "type":"Services"
        },
        {
            "category":"Professional",
            "subcategory":"Business Services",
            "type":"Services"
        }
    ],
    "sg:phone":"+1 940 566 7025",
    "sg:postcode":"76201",
    "sg:province":"TX",
    "sg:tags":[
        "process",
        "investigator",
        "server"
    ],
    "sg:website":"www.zenithinvestigations.com",
    "wof:name":"Zenith Investigations",
    "wof:placetype":"venue"
},
  "geometry": {"coordinates":[-97.127944,33.214544],"type":"Point"}
}