{
  "type": "Feature",
  "properties": {
    "iso:country":"US",
    "sg:address":"209 Kalura Way",
    "sg:city":"Tool",
    "sg:classifiers":[
        {
            "category":"Real Estate",
            "subcategory":"Real Estate Services",
            "type":"Services"
        },
        {
            "category":"Building & Trades",
            "subcategory":"Cleaning & Sanitation",
            "type":"Services"
        }
    ],
    "sg:phone":"+1 903 432 3450",
    "sg:postcode":"75143",
    "sg:province":"TX",
    "sg:tags":[
        "maintenance",
        "cleaners-interior"
    ],
    "wof:name":"Melody's Cleaning Service",
    "wof:placetype":"venue"
},
  "geometry": {"coordinates":[-96.16960899999999,32.276503],"type":"Point"}
}