{
  "type": "Feature",
  "properties": {
    "iso:country":"US",
    "sg:address":"830 Gilham Cir",
    "sg:city":"Port Arthur",
    "sg:classifiers":[
        {
            "category":"Food & Beverages",
            "subcategory":"Meat & Fish",
            "type":"Retail Goods"
        }
    ],
    "sg:phone":"+1 409 985 7904",
    "sg:postcode":"77640",
    "sg:province":"TX",
    "sg:tags":[
        "seafood"
    ],
    "wof:name":"Hung's Seafood Market",
    "wof:placetype":"venue"
},
  "geometry": {"coordinates":[-93.936097,29.88509],"type":"Point"}
}