{
  "type": "Feature",
  "properties": {
    "iso:country":"US",
    "sg:address":"4118 Pompano Pl",
    "sg:city":"Corpus Christi",
    "sg:classifiers":[
        {
            "category":"Health Services",
            "subcategory":"Doctor",
            "type":"Services"
        }
    ],
    "sg:phone":"+1 361 852 7315",
    "sg:postcode":"78411",
    "sg:province":"TX",
    "sg:tags":[
        "medical"
    ],
    "wof:name":"W C Ghermley",
    "wof:placetype":"venue"
},
  "geometry": {"coordinates":[-97.375818,27.729011],"type":"Point"}
}