{
  "type": "Feature",
  "properties": {
    "iso:country":"US",
    "sg:address":"3767 Co Rd 313 Lp",
    "sg:city":"Glen Rose",
    "sg:classifiers":[
        {
            "category":"Building & Trades",
            "subcategory":"Construction",
            "type":"Services"
        }
    ],
    "sg:phone":"+1 254 897 7286",
    "sg:postcode":"76043",
    "sg:province":"TX",
    "sg:tags":[
        "excavation",
        "trucking"
    ],
    "wof:name":"Kirby & Sons",
    "wof:placetype":"venue"
},
  "geometry": {"coordinates":[-97.778052,32.270576],"type":"Point"}
}