{
  "type": "Feature",
  "properties": {
    "iso:country":"US",
    "sg:address":"6710 Virginia Pkwy",
    "sg:city":"Mckinney",
    "sg:classifiers":[
        {
            "category":"Restaurant",
            "type":"Food & Drink"
        }
    ],
    "sg:menulink":"http://www.allmenus.com/tx/mckinney/77593-papa-murphys/menu/",
    "sg:phone":"+1 469 952 3100",
    "sg:postcode":"75071",
    "sg:province":"TX",
    "sg:tags":[
        "american",
        "pizza"
    ],
    "wof:name":"Papa Murphy's",
    "wof:placetype":"venue"
},
  "geometry": {"coordinates":[-96.705872,33.199076],"type":"Point"}
}