{
  "type": "Feature",
  "properties": {
    "iso:country":"US",
    "sg:address":"17109 Whitetail Run",
    "sg:city":"Austin",
    "sg:phone":"+1 512 894 0655",
    "sg:postcode":"78737",
    "sg:province":"TX",
    "wof:name":"Kathi Kaz Permanent Make-Up",
    "wof:placetype":"venue"
},
  "geometry": {"coordinates":[-97.970778,30.130942],"type":"Point"}
}