{
  "type": "Feature",
  "properties": {
    "iso:country":"US",
    "sg:address":"1702 S State Highway 121",
    "sg:city":"Lewisville",
    "sg:classifiers":[
        {
            "category":"Wholesale",
            "subcategory":"Medical Equipment & Supplies",
            "type":"Manufacturing & Wholesale Goods"
        },
        {
            "category":"Recreation",
            "subcategory":"Water Park",
            "type":"Entertainment"
        },
        {
            "category":"Building & Trades",
            "subcategory":"Equipment Rental",
            "type":"Services"
        }
    ],
    "sg:phone":"+1 972 434 0923",
    "sg:postcode":"75067",
    "sg:province":"TX",
    "sg:tags":[
        "oxygen",
        "wheelchair",
        "appliance",
        "orthopedic",
        "therapy",
        "wheelchairs-rental"
    ],
    "wof:name":"Speciality Medical Sales",
    "wof:placetype":"venue"
},
  "geometry": {"coordinates":[-96.992867,33.019131],"type":"Point"}
}