{
  "type": "Feature",
  "properties": {
    "iso:country":"US",
    "sg:address":"5202 Oriole Dr",
    "sg:city":"San Angelo",
    "sg:classifiers":[
        {
            "category":"Real Estate",
            "subcategory":"Real Estate Agent",
            "type":"Services"
        }
    ],
    "sg:phone":"+1 325 655 4845",
    "sg:postcode":"76903",
    "sg:province":"TX",
    "wof:name":"Mc Clain Realty",
    "wof:placetype":"venue"
},
  "geometry": {"coordinates":[-100.454166,31.5161],"type":"Point"}
}