{
  "type": "Feature",
  "properties": {
    "iso:country":"US",
    "sg:address":"6625 Overlook Ct",
    "sg:city":"Plano",
    "sg:classifiers":[
        {
            "category":"Banks & Credit Unions",
            "subcategory":"Investment Brokerage",
            "type":"Services"
        }
    ],
    "sg:phone":"+1 972 624 1619",
    "sg:postcode":"75024",
    "sg:province":"TX",
    "sg:tags":[
        "security"
    ],
    "wof:name":"Netherland Security Inc",
    "wof:placetype":"venue"
},
  "geometry": {"coordinates":[-96.84526099999999,33.063289],"type":"Point"}
}