{
  "type": "Feature",
  "properties": {
    "iso:country":"US",
    "sg:address":"3632 Frankford Rd",
    "sg:city":"Dallas",
    "sg:classifiers":[
        {
            "category":"Home & Garden",
            "subcategory":"Furniture",
            "type":"Retail Goods"
        },
        {
            "category":"Shopping",
            "subcategory":"Computers & Home Electronics",
            "type":"Retail Goods"
        },
        {
            "category":"Wholesale",
            "subcategory":"Computers",
            "type":"Manufacturing & Wholesale Goods"
        }
    ],
    "sg:phone":"+1 972 862 2222",
    "sg:postcode":"75287",
    "sg:province":"TX",
    "sg:tags":[
        "store"
    ],
    "sg:website":"www.colortyme.com/stores/Texas/D...",
    "wof:name":"Colortyme",
    "wof:placetype":"venue"
},
  "geometry": {"coordinates":[-96.854062,32.995903],"type":"Point"}
}