{
  "type": "Feature",
  "properties": {
    "iso:country":"US",
    "sg:address":"336 Trammel Rd",
    "sg:city":"Eddy",
    "sg:classifiers":[
        {
            "category":"Professional",
            "type":"Services"
        }
    ],
    "sg:phone":"+1 254 859 5887",
    "sg:postcode":"76524",
    "sg:province":"TX",
    "wof:name":"Maximono Gonzalez",
    "wof:placetype":"venue"
},
  "geometry": {"coordinates":[-97.298483,31.284359],"type":"Point"}
}