{
  "type": "Feature",
  "properties": {
    "iso:country":"US",
    "sg:address":"237 Lafayette St",
    "sg:city":"Pittsburg",
    "sg:classifiers":[
        {
            "category":"Food & Beverages",
            "subcategory":"Meat & Fish",
            "type":"Retail Goods"
        }
    ],
    "sg:phone":"+1 903 855 0066",
    "sg:postcode":"75686",
    "sg:province":"TX",
    "wof:name":"Los Mismos",
    "wof:placetype":"venue"
},
  "geometry": {"coordinates":[-94.963939,32.993222],"type":"Point"}
}