{
  "type": "Feature",
  "properties": {
    "iso:country":"US",
    "sg:address":"204 E Henderson St",
    "sg:city":"Overton",
    "sg:classifiers":[
        {
            "category":"Shopping",
            "subcategory":"Bicycles & Sporting Goods",
            "type":"Retail Goods"
        }
    ],
    "sg:phone":"+1 903 834 3453",
    "sg:postcode":"75684",
    "sg:province":"TX",
    "sg:tags":[
        "equipment",
        "golf",
        "supply"
    ],
    "wof:name":"Phil's Golf Club Svc",
    "wof:placetype":"venue"
},
  "geometry": {"coordinates":[-94.97698800000001,32.274178],"type":"Point"}
}