{
  "type": "Feature",
  "properties": {
    "iso:country":"US",
    "sg:address":"651 E Tudor St",
    "sg:city":"Paris",
    "sg:classifiers":[
        {
            "category":"Organizations",
            "subcategory":"Religious Organization",
            "type":"Services"
        }
    ],
    "sg:phone":"+1 903 739 8673",
    "sg:postcode":"75460",
    "sg:province":"TX",
    "sg:tags":[
        "church"
    ],
    "wof:name":"Galilee Full Gospel Baptist",
    "wof:placetype":"venue"
},
  "geometry": {"coordinates":[-95.549868,33.667809],"type":"Point"}
}