{
  "type": "Feature",
  "properties": {
    "iso:country":"US",
    "sg:address":"2907 Catalpa St",
    "sg:city":"Victoria",
    "sg:classifiers":[
        {
            "category":"Wholesale",
            "subcategory":"Machinery & Supplies",
            "type":"Manufacturing & Wholesale Goods"
        }
    ],
    "sg:phone":"+1 361 578 7956",
    "sg:postcode":"77901",
    "sg:province":"TX",
    "sg:tags":[
        "field",
        "oil"
    ],
    "wof:name":"Bob Herbert & Assoc Inc",
    "wof:placetype":"venue"
},
  "geometry": {"coordinates":[-96.972081,28.816048],"type":"Point"}
}