{
  "type": "Feature",
  "properties": {
    "iso:country":"US",
    "sg:address":"8523 Perrin Beitel Rd",
    "sg:city":"San Antonio",
    "sg:classifiers":[
        {
            "category":"Shopping",
            "subcategory":"Bicycles & Sporting Goods",
            "type":"Retail Goods"
        }
    ],
    "sg:phone":"+1 210 340 7811",
    "sg:postcode":"78217",
    "sg:province":"TX",
    "sg:tags":[
        "equipment",
        "arts",
        "supply",
        "martial"
    ],
    "wof:name":"Shaolin Do Kung Fu",
    "wof:placetype":"venue"
},
  "geometry": {"coordinates":[-98.411002,29.518077],"type":"Point"}
}