{
  "type": "Feature",
  "properties": {
    "iso:country":"US",
    "sg:address":"16038 Waverly Dr",
    "sg:city":"Houston",
    "sg:classifiers":[
        {
            "category":"Manufacturing",
            "subcategory":"Tools & Machinery",
            "type":"Manufacturing & Wholesale Goods"
        }
    ],
    "sg:phone":"+1 281 443 4646",
    "sg:postcode":"77032",
    "sg:province":"TX",
    "sg:tags":[
        "machine",
        "shop"
    ],
    "wof:name":"Pauls Machine",
    "wof:placetype":"venue"
},
  "geometry": {"coordinates":[-95.363433,29.950685],"type":"Point"}
}