{
  "type": "Feature",
  "properties": {
    "iso:country":"US",
    "sg:address":"3245 S Alameda St",
    "sg:city":"Corpus Christi",
    "sg:classifiers":[
        {
            "category":"Professional",
            "subcategory":"Management & Consulting",
            "type":"Services"
        }
    ],
    "sg:phone":"+1 361 851 0265",
    "sg:postcode":"78404",
    "sg:province":"TX",
    "sg:tags":[
        "retail",
        "direct",
        "sales"
    ],
    "wof:name":"Alameda Foods",
    "wof:placetype":"venue"
},
  "geometry": {"coordinates":[-97.38988000000001,27.756542],"type":"Point"}
}