{
  "type": "Feature",
  "properties": {
    "iso:country":"US",
    "sg:address":"7638 Forney Rd",
    "sg:city":"Dallas",
    "sg:classifiers":[
        {
            "category":"Manufacturing",
            "subcategory":"Tools & Machinery",
            "type":"Manufacturing & Wholesale Goods"
        }
    ],
    "sg:phone":"+1 214 388 4274",
    "sg:postcode":"75227",
    "sg:province":"TX",
    "sg:tags":[
        "industrial",
        "mfg"
    ],
    "wof:name":"Miniprecision Machine Inc",
    "wof:placetype":"venue"
},
  "geometry": {"coordinates":[-96.693309,32.778004],"type":"Point"}
}