{
  "type": "Feature",
  "properties": {
    "iso:country":"US",
    "sg:address":"105 2nd St",
    "sg:city":"Richmond",
    "sg:classifiers":[
        {
            "category":"Retail",
            "subcategory":"Auto Repair",
            "type":"Services"
        }
    ],
    "sg:phone":"+1 281 232 3333",
    "sg:postcode":"77469",
    "sg:province":"TX",
    "sg:tags":[
        "automobile",
        "restoration",
        "classic"
    ],
    "wof:name":"Dunright By Chris",
    "wof:placetype":"venue"
},
  "geometry": {"coordinates":[-95.75414499999999,29.584615],"type":"Point"}
}