{
  "type": "Feature",
  "properties": {
    "iso:country":"US",
    "sg:address":"118 E Main St",
    "sg:city":"Royse City",
    "sg:classifiers":[
        {
            "category":"Insurance",
            "subcategory":"Insurance Agent",
            "type":"Services"
        }
    ],
    "sg:phone":"+1 972 636 7799",
    "sg:postcode":"75189",
    "sg:province":"TX",
    "wof:name":"Verhagen Insurance Services",
    "wof:placetype":"venue"
},
  "geometry": {"coordinates":[-96.33148300000001,32.975476],"type":"Point"}
}