{
  "type": "Feature",
  "properties": {
    "iso:country":"US",
    "sg:address":"120 Easy Ln",
    "sg:city":"Whitney",
    "sg:classifiers":[
        {
            "category":"Retail",
            "subcategory":"Portrait Studio",
            "type":"Services"
        },
        {
            "category":"Professional",
            "subcategory":"Art Services",
            "type":"Services"
        }
    ],
    "sg:phone":"+1 254 694 7433",
    "sg:postcode":"76692",
    "sg:province":"TX",
    "sg:tags":[
        "rental",
        "photographers-portrait",
        "photographic",
        "darkroom"
    ],
    "wof:name":"Laurie K Robb Photography",
    "wof:placetype":"venue"
},
  "geometry": {"coordinates":[-97.381316,31.95537],"type":"Point"}
}