{
  "type": "Feature",
  "properties": {
    "iso:country":"US",
    "sg:address":"8610 Cedarspur Dr",
    "sg:city":"Houston",
    "sg:classifiers":[
        {
            "category":"Banks & Credit Unions",
            "subcategory":"Financial Services",
            "type":"Services"
        }
    ],
    "sg:phone":"+1 713 935 9900",
    "sg:postcode":"77055",
    "sg:province":"TX",
    "sg:tags":[
        "investment",
        "closed"
    ],
    "wof:name":"Caltex Development Corp",
    "wof:placetype":"venue"
},
  "geometry": {"coordinates":[-95.501186,29.790354],"type":"Point"}
}