{
  "type": "Feature",
  "properties": {
    "iso:country":"US",
    "sg:address":"4545 Fuller Dr",
    "sg:city":"Irving",
    "sg:classifiers":[
        {
            "category":"Personal",
            "type":"Services"
        },
        {
            "category":"Professional",
            "subcategory":"Accounting & Tax Preparation",
            "type":"Services"
        }
    ],
    "sg:phone":"+1 972 659 0259",
    "sg:postcode":"75038",
    "sg:province":"TX",
    "sg:tags":[
        "welcoming",
        "hotel",
        "newcomer",
        "for"
    ],
    "sg:website":"www.huntingtonhospitality.com",
    "wof:name":"Huntington Hospitality Group",
    "wof:placetype":"venue"
},
  "geometry": {"coordinates":[-96.948323,32.867886],"type":"Point"}
}