{
  "type": "Feature",
  "properties": {
    "iso:country":"US",
    "sg:address":"4101 Wiseman Blvd",
    "sg:city":"San Antonio",
    "sg:classifiers":[
        {
            "category":"Banks & Credit Unions",
            "subcategory":"Bank",
            "type":"Services"
        }
    ],
    "sg:phone":"+1 210 543 4300",
    "sg:postcode":"78251",
    "sg:province":"TX",
    "wof:name":"World Savings Bank FSB",
    "wof:placetype":"venue"
},
  "geometry": {"coordinates":[-98.697576,29.475313],"type":"Point"}
}