{
  "type": "Feature",
  "properties": {
    "iso:country":"US",
    "sg:address":"453 Rainier St",
    "sg:city":"Cedar Hill",
    "sg:classifiers":[
        {
            "category":"Professional",
            "subcategory":"Management & Consulting",
            "type":"Services"
        }
    ],
    "sg:phone":"+1 972 291 1397",
    "sg:postcode":"75104",
    "sg:province":"TX",
    "wof:name":"Carolyn B Strong",
    "wof:placetype":"venue"
},
  "geometry": {"coordinates":[-96.93951,32.585219],"type":"Point"}
}