{
  "type": "Feature",
  "properties": {
    "iso:country":"US",
    "sg:address":"1605 W Travis St",
    "sg:city":"La Grange",
    "sg:classifiers":[
        {
            "category":"Autos & Motor Vehicles",
            "subcategory":"Automobile Sales",
            "type":"Retail Goods"
        }
    ],
    "sg:phone":"+1 979 968 6461",
    "sg:postcode":"78945",
    "sg:province":"TX",
    "sg:tags":[
        "car",
        "dealer"
    ],
    "sg:website":"www.lagrangeford.com",
    "wof:name":"LA Grange Ford-Lincoln Mercury",
    "wof:placetype":"venue"
},
  "geometry": {"coordinates":[-96.90136800000001,29.902128],"type":"Point"}
}