{
  "type": "Feature",
  "properties": {
    "iso:country":"US",
    "sg:address":"721 N Great Southwest Pkwy",
    "sg:city":"Arlington",
    "sg:classifiers":[
        {
            "category":"Manufacturing",
            "subcategory":"Tools & Machinery",
            "type":"Manufacturing & Wholesale Goods"
        },
        {
            "category":"Wholesale",
            "subcategory":"Machinery & Supplies",
            "type":"Manufacturing & Wholesale Goods"
        }
    ],
    "sg:phone":"+1 817 530 1917",
    "sg:postcode":"76011",
    "sg:province":"TX",
    "sg:tags":[
        "control",
        "flood",
        "pump",
        "equipment"
    ],
    "sg:website":"http://www.upump.com",
    "wof:name":"United Pump",
    "wof:placetype":"venue"
},
  "geometry": {"coordinates":[-97.04589,32.752427],"type":"Point"}
}