{
  "type": "Feature",
  "properties": {
    "iso:country":"US",
    "sg:address":"4518 Brinkley St",
    "sg:city":"Houston",
    "sg:classifiers":[
        {
            "category":"Building & Trades",
            "subcategory":"Construction",
            "type":"Services"
        }
    ],
    "sg:phone":"+1 713 731 8946",
    "sg:postcode":"77051",
    "sg:province":"TX",
    "sg:tags":[
        "house"
    ],
    "wof:name":"Ocampo Remodeling",
    "wof:placetype":"venue"
},
  "geometry": {"coordinates":[-95.360376,29.663163],"type":"Point"}
}