{
  "type": "Feature",
  "properties": {
    "iso:country":"US",
    "sg:address":"8621 Westheimer Rd",
    "sg:city":"Houston",
    "sg:classifiers":[
        {
            "category":"Food & Beverages",
            "subcategory":"Groceries & Convenience Stores",
            "type":"Retail Goods"
        }
    ],
    "sg:phone":"+1 713 780 2213",
    "sg:postcode":"77063",
    "sg:province":"TX",
    "sg:tags":[
        "beer",
        "gasoline"
    ],
    "wof:name":"Westheimer Supermart",
    "wof:placetype":"venue"
},
  "geometry": {"coordinates":[-95.518107,29.737287],"type":"Point"}
}