{
  "type": "Feature",
  "properties": {
    "iso:country":"US",
    "sg:address":"10005 Bermuda Ave",
    "sg:city":"El Paso",
    "sg:classifiers":[
        {
            "category":"Manufacturing",
            "subcategory":"Tools & Machinery",
            "type":"Manufacturing & Wholesale Goods"
        }
    ],
    "sg:phone":"+1 915 595 2945",
    "sg:postcode":"79925",
    "sg:province":"TX",
    "sg:tags":[
        "manufacture",
        "industrial",
        "general"
    ],
    "wof:name":"Ppm Manufacturing Services",
    "wof:placetype":"venue"
},
  "geometry": {"coordinates":[-106.35077,31.776738],"type":"Point"}
}