{
  "type": "Feature",
  "properties": {
    "iso:country":"US",
    "sg:address":"23207 Lazy Hollow Ln",
    "sg:city":"Hockley",
    "sg:classifiers":[
        {
            "category":"Professional",
            "type":"Services"
        }
    ],
    "sg:phone":"+1 281 356 2315",
    "sg:postcode":"77447",
    "sg:province":"TX",
    "wof:name":"Diamond S Stables",
    "wof:placetype":"venue"
},
  "geometry": {"coordinates":[-95.77956399999999,30.106932],"type":"Point"}
}