{
  "type": "Feature",
  "properties": {
    "iso:country":"US",
    "sg:address":"4101 San Jacinto St",
    "sg:city":"Houston",
    "sg:classifiers":[
        {
            "category":"Shopping",
            "subcategory":"Beauty & Cosmetics",
            "type":"Retail Goods"
        }
    ],
    "sg:phone":"+1 713 522 6050",
    "sg:postcode":"77004",
    "sg:province":"TX",
    "sg:tags":[
        "merchandise"
    ],
    "wof:name":"U Th Skin Cosmetics",
    "wof:placetype":"venue"
},
  "geometry": {"coordinates":[-95.38036099999999,29.734261],"type":"Point"}
}