{
  "type": "Feature",
  "properties": {
    "iso:country":"US",
    "sg:address":"14624 Monrad Dr",
    "sg:city":"Houston",
    "sg:classifiers":[
        {
            "category":"Shopping",
            "subcategory":"Used Merchandise",
            "type":"Retail Goods"
        }
    ],
    "sg:phone":"+1 713 433 0730",
    "sg:postcode":"77045",
    "sg:province":"TX",
    "wof:name":"Novas Resale Shop",
    "wof:placetype":"venue"
},
  "geometry": {"coordinates":[-95.44289499999999,29.613683],"type":"Point"}
}