{
  "type": "Feature",
  "properties": {
    "iso:country":"US",
    "sg:address":"4911 Harmon Ave",
    "sg:city":"Austin",
    "sg:classifiers":[
        {
            "category":"Organizations",
            "subcategory":"Non-profit Organization",
            "type":"Services"
        }
    ],
    "sg:phone":"+1 512 220 4590",
    "sg:postcode":"78751",
    "sg:province":"TX",
    "sg:tags":[
        "service/non-profit",
        "community"
    ],
    "wof:name":"Manos De Cristo",
    "wof:placetype":"venue"
},
  "geometry": {"coordinates":[-97.712836,30.308755],"type":"Point"}
}