{
  "type": "Feature",
  "properties": {
    "iso:country":"US",
    "sg:address":"1203 Bayou Woods Dr",
    "sg:city":"College Station",
    "sg:classifiers":[
        {
            "category":"Professional",
            "subcategory":"Business Services",
            "type":"Services"
        }
    ],
    "sg:phone":"+1 979 764 8308",
    "sg:postcode":"77840",
    "sg:province":"TX",
    "wof:name":"Loscolinas Group For Inve",
    "wof:placetype":"venue"
},
  "geometry": {"coordinates":[-96.308876,30.628421],"type":"Point"}
}