{
  "type": "Feature",
  "properties": {
    "iso:country":"US",
    "sg:address":"11 Cavelier Pass",
    "sg:city":"San Antonio",
    "sg:classifiers":[
        {
            "category":"Professional",
            "subcategory":"Detective & Security Services",
            "type":"Services"
        }
    ],
    "sg:phone":"+1 210 699 6983",
    "sg:postcode":"78240",
    "sg:province":"TX",
    "sg:tags":[
        "guard"
    ],
    "wof:name":"Gilbert Barrientos",
    "wof:placetype":"venue"
},
  "geometry": {"coordinates":[-98.59610000000001,29.519481],"type":"Point"}
}