{
  "type": "Feature",
  "properties": {
    "iso:country":"US",
    "sg:address":"478 Alpine Ln",
    "sg:city":"Crowley",
    "sg:classifiers":[
        {
            "category":"Building & Trades",
            "subcategory":"Construction",
            "type":"Services"
        }
    ],
    "sg:phone":"+1 817 297 3932",
    "sg:postcode":"76036",
    "sg:province":"TX",
    "sg:tags":[
        "contractor"
    ],
    "wof:name":"John Glass Man",
    "wof:placetype":"venue"
},
  "geometry": {"coordinates":[-97.345589,32.589947],"type":"Point"}
}