{
  "type": "Feature",
  "properties": {
    "iso:country":"US",
    "sg:address":"100 S Belt Line Rd",
    "sg:city":"Dallas",
    "sg:classifiers":[
        {
            "category":"Building & Trades",
            "subcategory":"Construction",
            "type":"Services"
        },
        {
            "category":"Home & Garden",
            "subcategory":"Mobile Homes",
            "type":"Retail Goods"
        }
    ],
    "sg:phone":"+1 972 286 0769",
    "sg:postcode":"75253",
    "sg:province":"TX",
    "sg:tags":[
        "manufactured",
        "housing-communities",
        "park"
    ],
    "wof:name":"Mesquite Greens Mhc",
    "wof:placetype":"venue"
},
  "geometry": {"coordinates":[-96.586281,32.70306],"type":"Point"}
}