{
  "type": "Feature",
  "properties": {
    "iso:country":"US",
    "sg:address":"9705 Burnet Rd Ste 310",
    "sg:city":"Austin",
    "sg:classifiers":[
        {
            "category":"Building & Trades",
            "subcategory":"Plumbing",
            "type":"Services"
        }
    ],
    "sg:phone":"+1 512 833 0888",
    "sg:postcode":"78758",
    "sg:province":"TX",
    "wof:name":"Greater Austin Plumbing",
    "wof:placetype":"venue"
},
  "geometry": {"coordinates":[-97.724563,30.380617],"type":"Point"}
}