{
  "type": "Feature",
  "properties": {
    "iso:country":"US",
    "sg:address":"1405 N Main Ave",
    "sg:city":"San Antonio",
    "sg:classifiers":[
        {
            "category":"Real Estate",
            "subcategory":"Real Estate Agent",
            "type":"Services"
        }
    ],
    "sg:phone":"+1 210 225 0071",
    "sg:postcode":"78212",
    "sg:province":"TX",
    "sg:tags":[
        "authorities",
        "housing"
    ],
    "wof:name":"Bexar County Housing Authority",
    "wof:placetype":"venue"
},
  "geometry": {"coordinates":[-98.494263,29.442755],"type":"Point"}
}