{
  "type": "Feature",
  "properties": {
    "iso:country":"US",
    "sg:address":"5002 Tavenor Ln",
    "sg:city":"Houston",
    "sg:classifiers":[
        {
            "category":"Building & Trades",
            "subcategory":"Construction",
            "type":"Services"
        }
    ],
    "sg:phone":"+1 713 738 8839",
    "sg:postcode":"77048",
    "sg:province":"TX",
    "sg:tags":[
        "concrete",
        "contractor"
    ],
    "wof:name":"Mitchell & Son Concrete",
    "wof:placetype":"venue"
},
  "geometry": {"coordinates":[-95.349507,29.634784],"type":"Point"}
}