{
  "type": "Feature",
  "properties": {
    "iso:country":"US",
    "sg:address":"4231 Lakewood Dr",
    "sg:city":"Pasadena",
    "sg:classifiers":[
        {
            "category":"Wholesale",
            "subcategory":"Durable Goods & Equipment",
            "type":"Manufacturing & Wholesale Goods"
        }
    ],
    "sg:phone":"+1 866 789 7026",
    "sg:postcode":"77504",
    "sg:province":"TX",
    "wof:name":"Paramount Supplies",
    "wof:placetype":"venue"
},
  "geometry": {"coordinates":[-95.17863800000001,29.637444],"type":"Point"}
}