{
  "type": "Feature",
  "properties": {
    "iso:country":"US",
    "sg:address":"1400 Avenue F NW",
    "sg:city":"Childress",
    "sg:classifiers":[
        {
            "category":"Restaurant",
            "type":"Food & Drink"
        }
    ],
    "sg:phone":"+1 940 937 8475",
    "sg:postcode":"79201",
    "sg:province":"TX",
    "wof:name":"G10's Ranch House Restaurant & Bar",
    "wof:placetype":"venue"
},
  "geometry": {"coordinates":[-100.219093,34.431889],"type":"Point"}
}