{
  "type": "Feature",
  "properties": {
    "iso:country":"US",
    "sg:address":"9103 Hazelhurst Dr",
    "sg:city":"Austin",
    "sg:classifiers":[
        {
            "category":"Retail",
            "subcategory":"Repair Shop",
            "type":"Services"
        }
    ],
    "sg:phone":"+1 512 206 4062",
    "sg:postcode":"78729",
    "sg:province":"TX",
    "sg:tags":[
        "upholsterer"
    ],
    "wof:name":"Added Touch Upholstery",
    "wof:placetype":"venue"
},
  "geometry": {"coordinates":[-97.773264,30.460752],"type":"Point"}
}