{
  "type": "Feature",
  "properties": {
    "iso:country":"US",
    "sg:address":"182 Gayle Ave",
    "sg:city":"San Antonio",
    "sg:classifiers":[
        {
            "category":"Arts & Performance",
            "subcategory":"Theater",
            "type":"Entertainment"
        },
        {
            "category":"Retail",
            "subcategory":"Repair Shop",
            "type":"Services"
        }
    ],
    "sg:phone":"+1 210 359 8585",
    "sg:postcode":"78223",
    "sg:province":"TX",
    "sg:tags":[
        "musician"
    ],
    "wof:name":"Los Romanticos Mariachi Trio",
    "wof:placetype":"venue"
},
  "geometry": {"coordinates":[-98.434707,29.365403],"type":"Point"}
}