{
  "type": "Feature",
  "properties": {
    "iso:country":"US",
    "sg:address":"430 S Trade Days Blvd",
    "sg:city":"Canton",
    "sg:classifiers":[
        {
            "category":"Real Estate",
            "subcategory":"Real Estate Agent",
            "type":"Services"
        }
    ],
    "sg:phone":"+1 903 567 5267",
    "sg:postcode":"75103",
    "sg:province":"TX",
    "wof:name":"Remax Rose Realty",
    "wof:placetype":"venue"
},
  "geometry": {"coordinates":[-95.86161199999999,32.55418],"type":"Point"}
}