{
  "type": "Feature",
  "properties": {
    "iso:country":"US",
    "sg:address":"2110 Lone Pecan Dr",
    "sg:city":"Garland",
    "sg:classifiers":[
        {
            "category":"Health Services",
            "subcategory":"Optometrist",
            "type":"Services"
        }
    ],
    "sg:phone":"+1 469 544 0612",
    "sg:postcode":"75040",
    "sg:province":"TX",
    "wof:name":"Le Khanh",
    "wof:placetype":"venue"
},
  "geometry": {"coordinates":[-96.598815,32.941952],"type":"Point"}
}