{
  "type": "Feature",
  "properties": {
    "iso:country":"US",
    "sg:address":"4263 Dacoma St",
    "sg:city":"Houston",
    "sg:classifiers":[
        {
            "category":"Manufacturing",
            "subcategory":"Buildings",
            "type":"Manufacturing & Wholesale Goods"
        },
        {
            "category":"Building & Trades",
            "subcategory":"Construction",
            "type":"Services"
        }
    ],
    "sg:phone":"+1 713 840 8441",
    "sg:postcode":"77092",
    "sg:province":"TX",
    "sg:tags":[
        "industrial",
        "altering",
        "consultant",
        "builder",
        "contractor",
        "contractors-commercial",
        "home",
        "remodeling"
    ],
    "sg:website":"http://www.tcco.com",
    "wof:name":"Turner Construction Co",
    "wof:placetype":"venue"
},
  "geometry": {"coordinates":[-95.451797,29.809],"type":"Point"}
}