{
  "type": "Feature",
  "properties": {
    "iso:country":"US",
    "sg:address":"3603 Ash Glen Dr",
    "sg:city":"Spring",
    "sg:classifiers":[
        {
            "category":"Shopping",
            "subcategory":"Clothing, Apparel, & Fashions",
            "type":"Retail Goods"
        }
    ],
    "sg:phone":"+1 281 355 5494",
    "sg:postcode":"77388",
    "sg:province":"TX",
    "wof:name":"Ruth Hemming",
    "wof:placetype":"venue"
},
  "geometry": {"coordinates":[-95.47234,30.054627],"type":"Point"}
}