{
  "type": "Feature",
  "properties": {
    "iso:country":"US",
    "sg:address":"2213 Lakeshore Dr",
    "sg:city":"Cleburne",
    "sg:classifiers":[
        {
            "category":"Banks & Credit Unions",
            "subcategory":"Investment Brokerage",
            "type":"Services"
        }
    ],
    "sg:phone":"+1 817 558 8765",
    "sg:postcode":"76033",
    "sg:province":"TX",
    "sg:tags":[
        "advisory"
    ],
    "wof:name":"Al Flynn Investments",
    "wof:placetype":"venue"
},
  "geometry": {"coordinates":[-97.416299,32.297182],"type":"Point"}
}