{
  "type": "Feature",
  "properties": {
    "iso:country":"US",
    "sg:address":"625 Williams Rd",
    "sg:city":"Fort Worth",
    "sg:classifiers":[
        {
            "category":"Organizations",
            "subcategory":"Religious Organization",
            "type":"Services"
        }
    ],
    "sg:phone":"+1 817 457 1665",
    "sg:postcode":"76120",
    "sg:province":"TX",
    "sg:tags":[
        "church"
    ],
    "wof:name":"Calvary Baptist Church",
    "wof:placetype":"venue"
},
  "geometry": {"coordinates":[-97.200881,32.769514],"type":"Point"}
}