{
  "type": "Feature",
  "properties": {
    "iso:country":"US",
    "sg:address":"3822 S Padre Island Dr",
    "sg:city":"Corpus Christi",
    "sg:classifiers":[
        {
            "category":"Professional",
            "subcategory":"Business Services",
            "type":"Services"
        },
        {
            "category":"Autos & Motor Vehicles",
            "subcategory":"Auto Supplies",
            "type":"Retail Goods"
        },
        {
            "category":"Retail",
            "subcategory":"Auto Repair",
            "type":"Services"
        }
    ],
    "sg:phone":"+1 361 853 9903",
    "sg:postcode":"78415",
    "sg:province":"TX",
    "sg:tags":[
        "center",
        "tire",
        "general"
    ],
    "wof:name":"South Park Tire & Auto Center",
    "wof:placetype":"venue"
},
  "geometry": {"coordinates":[-97.399756,27.722592],"type":"Point"}
}