{
  "type": "Feature",
  "properties": {
    "iso:country":"US",
    "sg:address":"6055 Bissonnet St",
    "sg:city":"Houston",
    "sg:classifiers":[
        {
            "category":"Shopping",
            "subcategory":"Clothing, Apparel, & Fashions",
            "type":"Retail Goods"
        }
    ],
    "sg:phone":"+1 713 661 9122",
    "sg:postcode":"77081",
    "sg:province":"TX",
    "sg:tags":[
        "shop",
        "bridal"
    ],
    "wof:name":"Beautiful Bride",
    "wof:placetype":"venue"
},
  "geometry": {"coordinates":[-95.487184,29.697786],"type":"Point"}
}