{
  "type": "Feature",
  "properties": {
    "iso:country":"US",
    "sg:address":"6025 I- 20 W",
    "sg:city":"Arlington",
    "sg:classifiers":[
        {
            "category":"Professional",
            "subcategory":"Lawyer & Legal Services",
            "type":"Services"
        }
    ],
    "sg:phone":"+1 817 478 4940",
    "sg:postcode":"76017",
    "sg:province":"TX",
    "sg:tags":[
        "attorney"
    ],
    "wof:name":"Jensen & Jensen",
    "wof:placetype":"venue"
},
  "geometry": {"coordinates":[-97.202533,32.673279],"type":"Point"}
}