{
  "type": "Feature",
  "properties": {
    "iso:country":"US",
    "sg:address":"2816 Thousand Oaks Dr",
    "sg:city":"San Antonio",
    "sg:classifiers":[
        {
            "category":"Retail",
            "subcategory":"Repair Shop",
            "type":"Services"
        }
    ],
    "sg:phone":"+1 210 499 1016",
    "sg:postcode":"78232",
    "sg:province":"TX",
    "sg:tags":[
        "bicycle"
    ],
    "wof:name":"Bike City",
    "wof:placetype":"venue"
},
  "geometry": {"coordinates":[-98.442166,29.578435],"type":"Point"}
}