{
  "type": "Feature",
  "properties": {
    "iso:country":"US",
    "sg:address":"907 E Broadway St",
    "sg:city":"Sweetwater",
    "sg:classifiers":[
        {
            "category":"Professional",
            "subcategory":"Engineering",
            "type":"Services"
        }
    ],
    "sg:phone":"+1 325 235 8616",
    "sg:postcode":"79556",
    "sg:province":"TX",
    "sg:tags":[
        "cattle",
        "beef",
        "feedlot",
        "engineer"
    ],
    "wof:name":"Stanley Morris Engineering Co",
    "wof:placetype":"venue"
},
  "geometry": {"coordinates":[-100.39881200000001,32.474747],"type":"Point"}
}