{
  "type": "Feature",
  "properties": {
    "iso:country":"US",
    "sg:address":"1201 Minters Chapel Rd",
    "sg:city":"Grapevine",
    "sg:classifiers":[
        {
            "category":"Autos & Motor Vehicles",
            "subcategory":"Boat Sales",
            "type":"Retail Goods"
        }
    ],
    "sg:phone":"+1 817 481 3556",
    "sg:postcode":"76051",
    "sg:province":"TX",
    "wof:name":"Marine-Division D Southwest",
    "wof:placetype":"venue"
},
  "geometry": {"coordinates":[-97.064733,32.923993],"type":"Point"}
}