{
  "type": "Feature",
  "properties": {
    "iso:country":"US",
    "sg:address":"4805 Village Fair Dr",
    "sg:city":"Dallas",
    "sg:classifiers":[
        {
            "category":"Home & Garden",
            "subcategory":"Furniture",
            "type":"Retail Goods"
        }
    ],
    "sg:phone":"+1 214 375 0939",
    "sg:postcode":"75224",
    "sg:province":"TX",
    "sg:tags":[
        "custom"
    ],
    "wof:name":"Furniture Shop",
    "wof:placetype":"venue"
},
  "geometry": {"coordinates":[-96.82505500000001,32.691215],"type":"Point"}
}