{
  "type": "Feature",
  "properties": {
    "iso:country":"US",
    "sg:address":"1442 E Austin St",
    "sg:city":"Giddings",
    "sg:classifiers":[
        {
            "category":"Banks & Credit Unions",
            "subcategory":"Bank",
            "type":"Services"
        }
    ],
    "sg:phone":"+1 979 542 7872",
    "sg:postcode":"78942",
    "sg:province":"TX",
    "sg:tags":[
        "state",
        "commercial"
    ],
    "wof:name":"Round Top State Bank",
    "wof:placetype":"venue"
},
  "geometry": {"coordinates":[-96.92386399999999,30.180376],"type":"Point"}
}