{
  "type": "Feature",
  "properties": {
    "iso:country":"US",
    "sg:address":"13301 East Fwy",
    "sg:city":"Houston",
    "sg:classifiers":[
        {
            "category":"Freight",
            "type":"Transportation"
        }
    ],
    "sg:phone":"+1 713 450 4777",
    "sg:postcode":"77015",
    "sg:province":"TX",
    "sg:tags":[
        "over",
        "road",
        "trucking"
    ],
    "wof:name":"Garrett Trucking",
    "wof:placetype":"venue"
},
  "geometry": {"coordinates":[-95.18814399999999,29.771123],"type":"Point"}
}