{
  "type": "Feature",
  "properties": {
    "iso:country":"US",
    "sg:address":"600 S Main Ave",
    "sg:city":"Monahans",
    "sg:classifiers":[
        {
            "category":"Restaurant",
            "type":"Food & Drink"
        }
    ],
    "sg:phone":"+1 432 943 5351",
    "sg:postcode":"79756",
    "sg:province":"TX",
    "sg:tags":[
        "eating"
    ],
    "wof:name":"Howard's Drive Inn",
    "wof:placetype":"venue"
},
  "geometry": {"coordinates":[-102.89147199999999,31.589911],"type":"Point"}
}