{
  "type": "Feature",
  "properties": {
    "iso:country":"US",
    "sg:address":"1401 E Rabbit Cove Rd",
    "sg:city":"Quinlan",
    "sg:classifiers":[
        {
            "category":"Government",
            "subcategory":"Office",
            "type":"Public Place"
        }
    ],
    "sg:phone":"+1 903 447 3324",
    "sg:postcode":"75474",
    "sg:province":"TX",
    "sg:tags":[
        "village"
    ],
    "wof:name":"West Tawakoni City Sewer",
    "wof:placetype":"venue"
},
  "geometry": {"coordinates":[-96.02824099999999,32.889032],"type":"Point"}
}