{
  "type": "Feature",
  "properties": {
    "iso:country":"US",
    "sg:address":"5419 Cobble Ln",
    "sg:city":"Spring",
    "sg:classifiers":[
        {
            "category":"Banks & Credit Unions",
            "subcategory":"Financial Services",
            "type":"Services"
        }
    ],
    "sg:phone":"+1 281 320 2715",
    "sg:postcode":"77379",
    "sg:province":"TX",
    "sg:tags":[
        "investor"
    ],
    "wof:name":"Prism Investments Inc",
    "wof:placetype":"venue"
},
  "geometry": {"coordinates":[-95.496956,30.031677],"type":"Point"}
}