{
  "type": "Feature",
  "properties": {
    "iso:country":"US",
    "sg:address":"404 E Burress St",
    "sg:city":"Houston",
    "sg:classifiers":[
        {
            "category":"Building & Trades",
            "subcategory":"Construction",
            "type":"Services"
        }
    ],
    "sg:phone":"+1 713 884 1800",
    "sg:postcode":"77022",
    "sg:province":"TX",
    "sg:tags":[
        "tile",
        "dealer"
    ],
    "wof:name":"Liberty Tile & Marble Depot",
    "wof:placetype":"venue"
},
  "geometry": {"coordinates":[-95.390619,29.841466],"type":"Point"}
}