{
  "type": "Feature",
  "properties": {
    "iso:country":"US",
    "sg:address":"1860 Crown Dr",
    "sg:city":"Dallas",
    "sg:classifiers":[
        {
            "category":"Retail",
            "subcategory":"Repair Shop",
            "type":"Services"
        }
    ],
    "sg:phone":"+1 214 574 5200",
    "sg:postcode":"75234",
    "sg:province":"TX",
    "sg:tags":[
        "equipment"
    ],
    "wof:name":"Hagar Restaurant Svc LLC",
    "wof:placetype":"venue"
},
  "geometry": {"coordinates":[-96.912201,32.899649],"type":"Point"}
}