{
  "type": "Feature",
  "properties": {
    "iso:country":"US",
    "sg:address":"426 7th St",
    "sg:city":"Comfort",
    "sg:classifiers":[
        {
            "category":"Restaurant",
            "type":"Food & Drink"
        }
    ],
    "sg:phone":"+1 830 995 3330",
    "sg:postcode":"78013",
    "sg:province":"TX",
    "sg:tags":[
        "eating"
    ],
    "wof:name":"Arlene's Cafe & Gift Shop",
    "wof:placetype":"venue"
},
  "geometry": {"coordinates":[-98.90824000000001,29.966756],"type":"Point"}
}