{
  "type": "Feature",
  "properties": {
    "iso:country":"US",
    "sg:address":"2514 Tryon Rd",
    "sg:city":"Longview",
    "sg:classifiers":[
        {
            "category":"Retail",
            "subcategory":"Veterinary Services",
            "type":"Services"
        }
    ],
    "sg:phone":"+1 903 753 7625",
    "sg:postcode":"75605",
    "sg:province":"TX",
    "sg:tags":[
        "veterinarian"
    ],
    "wof:name":"Glaze Veterinary Clinic",
    "wof:placetype":"venue"
},
  "geometry": {"coordinates":[-94.7179,32.522936],"type":"Point"}
}