{
  "type": "Feature",
  "properties": {
    "iso:country":"US",
    "sg:address":"1027 Merlene Dr",
    "sg:city":"Austin",
    "sg:classifiers":[
        {
            "category":"Professional",
            "subcategory":"Accounting & Tax Preparation",
            "type":"Services"
        }
    ],
    "sg:phone":"+1 512 266 9801",
    "sg:postcode":"78732",
    "sg:province":"TX",
    "wof:name":"Independent Enterprises",
    "wof:placetype":"venue"
},
  "geometry": {"coordinates":[-97.92313300000001,30.332554],"type":"Point"}
}