{
  "type": "Feature",
  "properties": {
    "iso:country":"US",
    "sg:address":"2964 Park Hill Dr",
    "sg:city":"Fort Worth",
    "sg:classifiers":[
        {
            "category":"Shopping",
            "type":"Retail Goods"
        }
    ],
    "sg:phone":"+1 817 923 2500",
    "sg:postcode":"76109",
    "sg:province":"TX",
    "sg:tags":[
        "merchandise"
    ],
    "wof:name":"Spicy Shop",
    "wof:placetype":"venue"
},
  "geometry": {"coordinates":[-97.359184,32.716111],"type":"Point"}
}