{
  "type": "Feature",
  "properties": {
    "iso:country":"US",
    "sg:address":"907 Sagebrush Dr",
    "sg:city":"Austin",
    "sg:classifiers":[
        {
            "category":"Autos & Motor Vehicles",
            "subcategory":"Motorcycle Sales",
            "type":"Retail Goods"
        }
    ],
    "sg:phone":"+1 512 339 3161",
    "sg:postcode":"78758",
    "sg:province":"TX",
    "sg:tags":[
        "scooters-parts",
        "supply"
    ],
    "wof:name":"Alpha Motorsports",
    "wof:placetype":"venue"
},
  "geometry": {"coordinates":[-97.69227600000001,30.374034],"type":"Point"}
}