{
  "type": "Feature",
  "properties": {
    "iso:country":"US",
    "sg:address":"903 S Water St",
    "sg:city":"Burnet",
    "sg:classifiers":[
        {
            "category":"Personal",
            "subcategory":"Tanning Parlor",
            "type":"Services"
        }
    ],
    "sg:phone":"+1 512 756 9606",
    "sg:postcode":"78611",
    "sg:province":"TX",
    "sg:tags":[
        "salon"
    ],
    "wof:name":"The Finishing Touch",
    "wof:placetype":"venue"
},
  "geometry": {"coordinates":[-98.228127,30.750648],"type":"Point"}
}