{
  "type": "Feature",
  "properties": {
    "iso:country":"US",
    "sg:address":"15900 Lyndon B Johnson Fwy",
    "sg:city":"Mesquite",
    "sg:classifiers":[
        {
            "category":"Autos & Motor Vehicles",
            "subcategory":"Automobile Sales",
            "type":"Retail Goods"
        }
    ],
    "sg:phone":"+1 972 686 6200",
    "sg:postcode":"75150",
    "sg:province":"TX",
    "sg:tags":[
        "car"
    ],
    "wof:name":"Saturn of Mesquite",
    "wof:placetype":"venue"
},
  "geometry": {"coordinates":[-96.631401,32.834099],"type":"Point"}
}