{
  "type": "Feature",
  "properties": {
    "iso:country":"US",
    "sg:address":"1419 Kingstree Ln",
    "sg:city":"Houston",
    "sg:classifiers":[
        {
            "category":"Professional",
            "subcategory":"Business Services",
            "type":"Services"
        }
    ],
    "sg:phone":"+1 713 419 4549",
    "sg:postcode":"77058",
    "sg:province":"TX",
    "sg:tags":[
        "holding"
    ],
    "wof:name":"Walker Gang Holdings",
    "wof:placetype":"venue"
},
  "geometry": {"coordinates":[-95.09218199999999,29.538665],"type":"Point"}
}