{
  "type": "Feature",
  "properties": {
    "iso:country":"US",
    "sg:address":"5110 Duval St",
    "sg:city":"Austin",
    "sg:classifiers":[
        {
            "category":"Professional",
            "type":"Services"
        }
    ],
    "sg:phone":"+1 512 833 7694",
    "sg:postcode":"78751",
    "sg:province":"TX",
    "wof:name":"Wrapperz N Things",
    "wof:placetype":"venue"
},
  "geometry": {"coordinates":[-97.719352,30.315227],"type":"Point"}
}