{
  "type": "Feature",
  "properties": {
    "iso:country":"US",
    "sg:address":"1101 E Wintergreen Rd",
    "sg:city":"Cedar Hill",
    "sg:classifiers":[
        {
            "category":"Organizations",
            "subcategory":"Religious Organization",
            "type":"Services"
        }
    ],
    "sg:phone":"+1 972 296 0685",
    "sg:postcode":"75104",
    "sg:province":"TX",
    "wof:name":"First African Bible Church",
    "wof:placetype":"venue"
},
  "geometry": {"coordinates":[-96.91811800000001,32.619024],"type":"Point"}
}