{
  "type": "Feature",
  "properties": {
    "iso:country":"US",
    "sg:address":"1609 Brentwood Trl",
    "sg:city":"Keller",
    "sg:classifiers":[
        {
            "category":"Professional",
            "subcategory":"Art Services",
            "type":"Services"
        }
    ],
    "sg:phone":"+1 817 788 2301",
    "sg:postcode":"76248",
    "sg:province":"TX",
    "sg:tags":[
        "designer",
        "display",
        "producer"
    ],
    "wof:name":"Fdg",
    "wof:placetype":"venue"
},
  "geometry": {"coordinates":[-97.21247099999999,32.916969],"type":"Point"}
}