{
  "type": "Feature",
  "properties": {
    "iso:country":"US",
    "sg:address":"3741 Wedgworth Rd S",
    "sg:city":"Fort Worth",
    "sg:classifiers":[
        {
            "category":"Retail",
            "subcategory":"Repair Shop",
            "type":"Services"
        }
    ],
    "sg:phone":"+1 817 346 3115",
    "sg:postcode":"76133",
    "sg:province":"TX",
    "sg:tags":[
        "related"
    ],
    "wof:name":"GNJ Testing & Repair",
    "wof:placetype":"venue"
},
  "geometry": {"coordinates":[-97.372773,32.654871],"type":"Point"}
}