{
  "type": "Feature",
  "properties": {
    "iso:country":"US",
    "sg:address":"1512 Broadmoor Dr",
    "sg:city":"Richardson",
    "sg:classifiers":[
        {
            "category":"Home & Garden",
            "subcategory":"Building Materials",
            "type":"Retail Goods"
        }
    ],
    "sg:phone":"+1 972 231 0777",
    "sg:postcode":"75082",
    "sg:province":"TX",
    "sg:tags":[
        "windows"
    ],
    "wof:name":"Spring Creek Remodeling Inc",
    "wof:placetype":"venue"
},
  "geometry": {"coordinates":[-96.69314900000001,32.994693],"type":"Point"}
}