{
  "type": "Feature",
  "properties": {
    "iso:country":"US",
    "sg:address":"5658 Westcreek Dr",
    "sg:city":"Fort Worth",
    "sg:classifiers":[
        {
            "category":"Shopping",
            "type":"Retail Goods"
        }
    ],
    "sg:phone":"+1 817 294 2070",
    "sg:postcode":"76133",
    "sg:province":"TX",
    "sg:tags":[
        "trophy",
        "medal",
        "award"
    ],
    "wof:name":"Trophies Etc",
    "wof:placetype":"venue"
},
  "geometry": {"coordinates":[-97.361965,32.663073],"type":"Point"}
}