{
  "type": "Feature",
  "properties": {
    "iso:country":"US",
    "sg:address":"1100 Hendricks Ave",
    "sg:city":"Laredo",
    "sg:classifiers":[
        {
            "category":"Place Of Worship",
            "subcategory":"Church",
            "type":"Public Place"
        },
        {
            "category":"Place Of Worship",
            "type":"Public Place"
        },
        {
            "category":"Organizations",
            "subcategory":"Religious Organization",
            "type":"Services"
        }
    ],
    "sg:phone":"+1 956 722 7821",
    "sg:postcode":"78040",
    "sg:province":"TX",
    "sg:tags":[
        "churches-catholic-traditional",
        "churches-catholic"
    ],
    "wof:name":"Catechetical Center Ccd",
    "wof:placetype":"venue"
},
  "geometry": {"coordinates":[-99.486572,27.505659],"type":"Point"}
}