{
  "type": "Feature",
  "properties": {
    "iso:country":"US",
    "sg:address":"7707 Battlecreek Dr",
    "sg:city":"Houston",
    "sg:classifiers":[
        {
            "category":"Building & Trades",
            "subcategory":"Landscaping Services",
            "type":"Services"
        }
    ],
    "sg:phone":"+1 832 203 6504",
    "sg:postcode":"77040",
    "sg:province":"TX",
    "wof:name":"Gomez Lawn Service",
    "wof:placetype":"venue"
},
  "geometry": {"coordinates":[-95.50559199999999,29.882427],"type":"Point"}
}