{
  "type": "Feature",
  "properties": {
    "iso:country":"US",
    "sg:address":"2607 Manana Dr",
    "sg:city":"Dallas",
    "sg:classifiers":[
        {
            "category":"Manufacturing",
            "subcategory":"Metals",
            "type":"Manufacturing & Wholesale Goods"
        }
    ],
    "sg:phone":"+1 214 366 0045",
    "sg:postcode":"75220",
    "sg:province":"TX",
    "sg:tags":[
        "mfg"
    ],
    "wof:name":"Raco Interior Products Inc",
    "wof:placetype":"venue"
},
  "geometry": {"coordinates":[-96.889503,32.873949],"type":"Point"}
}