{
  "type": "Feature",
  "properties": {
    "iso:country":"US",
    "sg:address":"100 Allentown Pkwy",
    "sg:city":"Allen",
    "sg:classifiers":[
        {
            "category":"Shopping",
            "subcategory":"Computers & Home Electronics",
            "type":"Retail Goods"
        }
    ],
    "sg:phone":"+1 972 727 8511",
    "sg:postcode":"75002",
    "sg:province":"TX",
    "sg:tags":[
        "software"
    ],
    "wof:name":"Diamond Control Systems Inc",
    "wof:placetype":"venue"
},
  "geometry": {"coordinates":[-96.67863,33.08302],"type":"Point"}
}