{
  "type": "Feature",
  "properties": {
    "iso:country":"US",
    "sg:address":"2902 Montgomery Rd",
    "sg:city":"Huntsville",
    "sg:classifiers":[
        {
            "category":"Retail",
            "subcategory":"Veterinary Services",
            "type":"Services"
        }
    ],
    "sg:phone":"+1 936 295 8106",
    "sg:postcode":"77340",
    "sg:province":"TX",
    "wof:name":"Etheredge Gerry",
    "wof:placetype":"venue"
},
  "geometry": {"coordinates":[-95.548068,30.69916],"type":"Point"}
}