{
  "type": "Feature",
  "properties": {
    "iso:country":"US",
    "sg:address":"1613 Old Course Dr",
    "sg:city":"Plano",
    "sg:classifiers":[
        {
            "category":"Building & Trades",
            "subcategory":"Construction",
            "type":"Services"
        }
    ],
    "sg:phone":"+1 972 735 8149",
    "sg:postcode":"75093",
    "sg:province":"TX",
    "sg:tags":[
        "specializing",
        "home",
        "family",
        "contractor"
    ],
    "wof:name":"Johannsen Brothers Inc",
    "wof:placetype":"venue"
},
  "geometry": {"coordinates":[-96.802725,33.021832],"type":"Point"}
}