{
  "type": "Feature",
  "properties": {
    "iso:country":"US",
    "sg:address":"212 Dover Ln",
    "sg:city":"Friendswood",
    "sg:classifiers":[
        {
            "category":"Professional",
            "subcategory":"Management & Consulting",
            "type":"Services"
        }
    ],
    "sg:phone":"+1 281 482 3025",
    "sg:postcode":"77546",
    "sg:province":"TX",
    "wof:name":"Propylene Management Inc",
    "wof:placetype":"venue"
},
  "geometry": {"coordinates":[-95.216846,29.53596],"type":"Point"}
}