{
  "type": "Feature",
  "properties": {
    "iso:country":"US",
    "sg:address":"300 Family Cir",
    "sg:city":"Fischer",
    "sg:classifiers":[
        {
            "category":"Manufacturing",
            "subcategory":"Buildings",
            "type":"Manufacturing & Wholesale Goods"
        },
        {
            "category":"Building & Trades",
            "subcategory":"Construction",
            "type":"Services"
        }
    ],
    "sg:phone":"+1 830 935 4589",
    "sg:postcode":"78623",
    "sg:province":"TX",
    "sg:tags":[
        "home",
        "builder",
        "contractor"
    ],
    "wof:name":"Oak Hill Homes & Garden",
    "wof:placetype":"venue"
},
  "geometry": {"coordinates":[-98.206609,29.956909],"type":"Point"}
}