{
  "type": "Feature",
  "properties": {
    "iso:country":"US",
    "sg:address":"2231 Michigan Ave",
    "sg:city":"Arlington",
    "sg:classifiers":[
        {
            "category":"Utilities",
            "subcategory":"Telephone",
            "type":"Services"
        }
    ],
    "sg:phone":"+1 817 548 9000",
    "sg:postcode":"76013",
    "sg:province":"TX",
    "sg:tags":[
        "communications"
    ],
    "wof:name":"Geiers Business Solutions",
    "wof:placetype":"venue"
},
  "geometry": {"coordinates":[-97.15716,32.707887],"type":"Point"}
}