{
  "type": "Feature",
  "properties": {
    "iso:country":"US",
    "sg:address":"7312 E Ben White Blvd",
    "sg:city":"Austin",
    "sg:classifiers":[
        {
            "category":"Transit Center",
            "subcategory":"Freight",
            "type":"Transportation"
        },
        {
            "category":"Freight",
            "type":"Transportation"
        }
    ],
    "sg:phone":"+1 512 848 1337",
    "sg:postcode":"78741",
    "sg:province":"TX",
    "sg:tags":[
        "local",
        "trucking-motor",
        "trucking"
    ],
    "wof:name":"Zapata Trucking",
    "wof:placetype":"venue"
},
  "geometry": {"coordinates":[-97.698604,30.215767],"type":"Point"}
}