{
  "type": "Feature",
  "properties": {
    "iso:country":"US",
    "sg:address":"7906 Glenvista St",
    "sg:city":"Houston",
    "sg:classifiers":[
        {
            "category":"Bars & Pubs",
            "type":"Food & Drink"
        }
    ],
    "sg:phone":"+1 713 748 3755",
    "sg:postcode":"77061",
    "sg:province":"TX",
    "sg:tags":[
        "drinking"
    ],
    "wof:name":"Lil James Reminisce Inc",
    "wof:placetype":"venue"
},
  "geometry": {"coordinates":[-95.27443599999999,29.66884],"type":"Point"}
}