{
  "type": "Feature",
  "properties": {
    "iso:country":"US",
    "sg:address":"14980 Omicron Dr",
    "sg:city":"San Antonio",
    "sg:classifiers":[
        {
            "category":"Organizations",
            "subcategory":"Professional Association",
            "type":"Services"
        }
    ],
    "sg:phone":"+1 210 677 8808",
    "sg:postcode":"78245",
    "sg:province":"TX",
    "sg:tags":[
        "membership"
    ],
    "wof:name":"Southwest Oncology Group",
    "wof:placetype":"venue"
},
  "geometry": {"coordinates":[-98.79595399999999,29.418263],"type":"Point"}
}