{
  "type": "Feature",
  "properties": {
    "iso:country":"US",
    "sg:address":"2220 Hwy 365",
    "sg:city":"Port Arthur",
    "sg:classifiers":[
        {
            "category":"Manufacturing",
            "subcategory":"Rubber & Plastics",
            "type":"Manufacturing & Wholesale Goods"
        }
    ],
    "sg:phone":"+1 409 727 1476",
    "sg:postcode":"77640",
    "sg:province":"TX",
    "sg:tags":[
        "seal"
    ],
    "sg:website":"www.flowserve.com",
    "wof:name":"Flowserve Corp",
    "wof:placetype":"venue"
},
  "geometry": {"coordinates":[-94.00437599999999,29.934446],"type":"Point"}
}