{
  "type": "Feature",
  "properties": {
    "iso:country":"US",
    "sg:address":"2514 Pecan Blvd",
    "sg:city":"Mcallen",
    "sg:classifiers":[
        {
            "category":"Food & Beverages",
            "subcategory":"Specialty",
            "type":"Retail Goods"
        }
    ],
    "sg:phone":"+1 956 687 6220",
    "sg:postcode":"78501",
    "sg:province":"TX",
    "sg:tags":[
        "herb"
    ],
    "wof:name":"Yerberia El Indio",
    "wof:placetype":"venue"
},
  "geometry": {"coordinates":[-98.247406,26.218972],"type":"Point"}
}