{
  "type": "Feature",
  "properties": {
    "iso:country":"US",
    "sg:address":"217 Pear Tree Pl",
    "sg:city":"Denton",
    "sg:classifiers":[
        {
            "category":"Professional",
            "type":"Services"
        }
    ],
    "sg:phone":"+1 940 320 0809",
    "sg:postcode":"76207",
    "sg:province":"TX",
    "wof:name":"Jennie Sainah",
    "wof:placetype":"venue"
},
  "geometry": {"coordinates":[-97.129993,33.250583],"type":"Point"}
}