{
  "type": "Feature",
  "properties": {
    "iso:country":"US",
    "sg:address":"900 Louisiana St",
    "sg:city":"Houston",
    "sg:classifiers":[
        {
            "category":"Health Services",
            "subcategory":"Optometrist",
            "type":"Services"
        }
    ],
    "sg:phone":"+1 713 225 2600",
    "sg:postcode":"77002",
    "sg:province":"TX",
    "wof:name":"Stolzberg Todd M Optmtrst",
    "wof:placetype":"venue"
},
  "geometry": {"coordinates":[-95.36689800000001,29.759199],"type":"Point"}
}