{
  "type": "Feature",
  "properties": {
    "iso:country":"US",
    "sg:address":"25770 Fm 159 Rd",
    "sg:city":"Navasota",
    "sg:classifiers":[
        {
            "category":"Transit Center",
            "subcategory":"Freight",
            "type":"Transportation"
        },
        {
            "category":"Freight",
            "type":"Transportation"
        }
    ],
    "sg:phone":"+1 936 825 0393",
    "sg:postcode":"77868",
    "sg:province":"TX",
    "sg:tags":[
        "local",
        "trucking-motor",
        "trucking"
    ],
    "wof:name":"Gpj Trucking",
    "wof:placetype":"venue"
},
  "geometry": {"coordinates":[-96.24010699999999,30.423911],"type":"Point"}
}