{
  "type": "Feature",
  "properties": {
    "iso:country":"US",
    "sg:address":"139 S L B J Dr",
    "sg:city":"San Marcos",
    "sg:classifiers":[
        {
            "category":"Professional",
            "type":"Services"
        }
    ],
    "sg:phone":"+1 512 392 7660",
    "sg:postcode":"78666",
    "sg:province":"TX",
    "wof:name":"Stpopa",
    "wof:placetype":"venue"
},
  "geometry": {"coordinates":[-97.93979,29.88137],"type":"Point"}
}