{
  "type": "Feature",
  "properties": {
    "iso:country":"US",
    "sg:address":"1305 State Hwy 121H Bus",
    "sg:city":"Lewisville",
    "sg:classifiers":[
        {
            "category":"Shopping",
            "subcategory":"Pharmacy",
            "type":"Retail Goods"
        }
    ],
    "sg:phone":"+1 972 436 7707",
    "sg:postcode":"75067",
    "sg:province":"TX",
    "sg:tags":[
        "drug",
        "store"
    ],
    "wof:name":"Eckerd",
    "wof:placetype":"venue"
},
  "geometry": {"coordinates":[-96.99306300000001,33.026756],"type":"Point"}
}