{
  "type": "Feature",
  "properties": {
    "iso:country":"US",
    "sg:address":"11551 West Ave",
    "sg:city":"San Antonio",
    "sg:classifiers":[
        {
            "category":"Shopping",
            "subcategory":"Gifts & Souvenirs",
            "type":"Retail Goods"
        }
    ],
    "sg:phone":"+1 210 349 1641",
    "sg:postcode":"78213",
    "sg:province":"TX",
    "sg:tags":[
        "shop"
    ],
    "wof:name":"Quickgifts Inc",
    "wof:placetype":"venue"
},
  "geometry": {"coordinates":[-98.50946,29.545911],"type":"Point"}
}