{
  "type": "Feature",
  "properties": {
    "iso:country":"US",
    "sg:address":"5411 E Sam Houston Pkwy S",
    "sg:city":"Houston",
    "sg:classifiers":[
        {
            "category":"Food & Beverages",
            "subcategory":"Groceries & Convenience Stores",
            "type":"Retail Goods"
        }
    ],
    "sg:phone":"+1 281 487 1136",
    "sg:postcode":"77034",
    "sg:province":"TX",
    "wof:name":"Ruby Foodmart",
    "wof:placetype":"venue"
},
  "geometry": {"coordinates":[-95.169674,29.630339],"type":"Point"}
}