{
  "type": "Feature",
  "properties": {
    "iso:country":"US",
    "sg:address":"737 Meadowcreek Ct",
    "sg:city":"Garland",
    "sg:classifiers":[
        {
            "category":"Building & Trades",
            "subcategory":"Cleaning & Sanitation",
            "type":"Services"
        }
    ],
    "sg:phone":"+1 972 619 3444",
    "sg:postcode":"75043",
    "sg:province":"TX",
    "sg:tags":[
        "maintenance"
    ],
    "wof:name":"Beautyscape Maintenance &",
    "wof:placetype":"venue"
},
  "geometry": {"coordinates":[-96.632659,32.854374],"type":"Point"}
}