{
  "type": "Feature",
  "properties": {
    "iso:country":"US",
    "sg:address":"807 Center Ave",
    "sg:city":"Brownwood",
    "sg:classifiers":[
        {
            "category":"Insurance",
            "subcategory":"Hazard Insurance",
            "type":"Services"
        },
        {
            "category":"Insurance",
            "subcategory":"Insurance Agent",
            "type":"Services"
        },
        {
            "category":"Insurance",
            "subcategory":"Life Insurance",
            "type":"Services"
        },
        {
            "category":"Banks & Credit Unions",
            "subcategory":"Financial Services",
            "type":"Services"
        }
    ],
    "sg:phone":"+1 325 203 5605",
    "sg:postcode":"76801",
    "sg:province":"TX",
    "sg:tags":[
        "auto",
        "financing"
    ],
    "sg:website":"http://statefarm.mqgroup.com/url.asp?usr=431097",
    "wof:name":"Hall, Mike - State Farm Insurance Agent",
    "wof:placetype":"venue"
},
  "geometry": {"coordinates":[-98.984818,31.718246],"type":"Point"}
}