{
  "type": "Feature",
  "properties": {
    "iso:country":"US",
    "sg:address":"27832 I-45 N",
    "sg:city":"Conroe",
    "sg:classifiers":[
        {
            "category":"Restaurant",
            "type":"Food & Drink"
        }
    ],
    "sg:menulink":"http://www.allmenus.com/tx/southeast-montgomery/60472-panchos-mexican-buffet/menu/",
    "sg:phone":"+1 281 363 0683",
    "sg:postcode":"77385",
    "sg:province":"TX",
    "sg:tags":[
        "mexican"
    ],
    "wof:name":"Pancho's Mexican Buffet",
    "wof:placetype":"venue"
},
  "geometry": {"coordinates":[-95.45132599999999,30.169205],"type":"Point"}
}