{
  "type": "Feature",
  "properties": {
    "iso:country":"US",
    "sg:address":"6915 Fremont Ave",
    "sg:city":"Lubbock",
    "sg:classifiers":[
        {
            "category":"Recreation",
            "type":"Entertainment"
        }
    ],
    "sg:phone":"+1 806 784 0204",
    "sg:postcode":"79413",
    "sg:province":"TX",
    "wof:name":"Premier Image Paintball",
    "wof:placetype":"venue"
},
  "geometry": {"coordinates":[-101.882259,33.530917],"type":"Point"}
}