{
  "type": "Feature",
  "properties": {
    "iso:country":"US",
    "sg:address":"7220 McCallum Blvd",
    "sg:city":"Dallas",
    "sg:classifiers":[
        {
            "category":"Professional",
            "type":"Services"
        }
    ],
    "sg:phone":"+1 469 879 6111",
    "sg:postcode":"75252",
    "sg:province":"TX",
    "wof:name":"Becsar Groups",
    "wof:placetype":"venue"
},
  "geometry": {"coordinates":[-96.777379,32.987839],"type":"Point"}
}