{
  "type": "Feature",
  "properties": {
    "iso:country":"US",
    "sg:address":"9814 Madison Dr",
    "sg:city":"Frisco",
    "sg:classifiers":[
        {
            "category":"Retail",
            "subcategory":"Portrait Studio",
            "type":"Services"
        }
    ],
    "sg:phone":"+1 972 335 0770",
    "sg:postcode":"75035",
    "sg:province":"TX",
    "sg:tags":[
        "photo"
    ],
    "wof:name":"Patterson P Frances Rooks",
    "wof:placetype":"venue"
},
  "geometry": {"coordinates":[-96.79397,33.121973],"type":"Point"}
}