{
  "type": "Feature",
  "properties": {
    "iso:country":"US",
    "sg:address":"1505 James St",
    "sg:city":"Sweetwater",
    "sg:classifiers":[
        {
            "category":"Shopping",
            "subcategory":"Jewelry",
            "type":"Retail Goods"
        }
    ],
    "sg:phone":"+1 325 235 3130",
    "sg:postcode":"79556",
    "sg:province":"TX",
    "wof:name":"James Jewelry",
    "wof:placetype":"venue"
},
  "geometry": {"coordinates":[-100.391353,32.478293],"type":"Point"}
}