{
  "type": "Feature",
  "properties": {
    "iso:country":"US",
    "sg:address":"15327 E Barbara Cir",
    "sg:city":"Houston",
    "sg:classifiers":[
        {
            "category":"Manufacturing",
            "subcategory":"Apparel",
            "type":"Manufacturing & Wholesale Goods"
        }
    ],
    "sg:phone":"+1 713 726 1726",
    "sg:postcode":"77071",
    "sg:province":"TX",
    "sg:tags":[
        "product",
        "mfg"
    ],
    "wof:name":"White Canvas Productions",
    "wof:placetype":"venue"
},
  "geometry": {"coordinates":[-95.518125,29.639375],"type":"Point"}
}