{
  "type": "Feature",
  "properties": {
    "iso:country":"US",
    "sg:address":"4101 US Hwy 281",
    "sg:city":"Alice",
    "sg:classifiers":[
        {
            "category":"Mining & Drilling",
            "type":"Manufacturing & Wholesale Goods"
        }
    ],
    "sg:phone":"+1 361 661 1202",
    "sg:postcode":"78332",
    "sg:province":"TX",
    "sg:tags":[
        "field",
        "oil"
    ],
    "wof:name":"Performance Fluids Co Inc",
    "wof:placetype":"venue"
},
  "geometry": {"coordinates":[-98.084405,27.837916],"type":"Point"}
}