{
  "type": "Feature",
  "properties": {
    "iso:country":"US",
    "sg:address":"315 Patrick Pike Rd",
    "sg:city":"Ferris",
    "sg:classifiers":[
        {
            "category":"Personal",
            "type":"Services"
        }
    ],
    "sg:phone":"+1 972 225 5414",
    "sg:postcode":"75125",
    "sg:province":"TX",
    "sg:tags":[
        "wedding",
        "chapel"
    ],
    "wof:name":"Shadow Creek Ranch",
    "wof:placetype":"venue"
},
  "geometry": {"coordinates":[-96.667008,32.566885],"type":"Point"}
}