{
  "type": "Feature",
  "properties": {
    "iso:country":"US",
    "sg:address":"19200 Space Center Blvd",
    "sg:city":"Houston",
    "sg:classifiers":[
        {
            "category":"Home & Garden",
            "subcategory":"Garden Supply",
            "type":"Retail Goods"
        }
    ],
    "sg:phone":"+1 281 480 2787",
    "sg:postcode":"77058",
    "sg:province":"TX",
    "sg:tags":[
        "fertilizer"
    ],
    "wof:name":"Agrifos Fertilizer",
    "wof:placetype":"venue"
},
  "geometry": {"coordinates":[-95.07588199999999,29.558671],"type":"Point"}
}