{
  "type": "Feature",
  "properties": {
    "iso:country":"US",
    "sg:address":"209 S Pioneer Dr",
    "sg:city":"Abilene",
    "sg:classifiers":[
        {
            "category":"Insurance",
            "subcategory":"Insurance Agent",
            "type":"Services"
        }
    ],
    "sg:phone":"+1 325 690 9494",
    "sg:postcode":"79605",
    "sg:province":"TX",
    "wof:name":"Miller Insurance",
    "wof:placetype":"venue"
},
  "geometry": {"coordinates":[-99.779099,32.449458],"type":"Point"}
}