{
  "type": "Feature",
  "properties": {
    "iso:country":"US",
    "sg:address":"440 Benmar Dr",
    "sg:city":"Houston",
    "sg:classifiers":[
        {
            "category":"Health Services",
            "subcategory":"Clinic",
            "type":"Services"
        }
    ],
    "sg:phone":"+1 281 591 0206",
    "sg:postcode":"77060",
    "sg:province":"TX",
    "sg:tags":[
        "home"
    ],
    "wof:name":"Nature",
    "wof:placetype":"venue"
},
  "geometry": {"coordinates":[-95.398763,29.943907],"type":"Point"}
}