{
  "type": "Feature",
  "properties": {
    "iso:country":"US",
    "sg:address":"7900 Fannin St",
    "sg:city":"Houston",
    "sg:classifiers":[
        {
            "category":"Health Services",
            "subcategory":"Doctor",
            "type":"Services"
        }
    ],
    "sg:phone":"+1 713 512 7500",
    "sg:postcode":"77054",
    "sg:province":"TX",
    "sg:tags":[
        "obstetrician",
        "gynecologist"
    ],
    "sg:website":"www.obgynassociates.com",
    "wof:name":"John F. Irwin, MD",
    "wof:placetype":"venue"
},
  "geometry": {"coordinates":[-95.403407,29.691669],"type":"Point"}
}