{
  "type": "Feature",
  "properties": {
    "iso:country":"US",
    "sg:address":"437 Inland Cir",
    "sg:city":"Azle",
    "sg:classifiers":[
        {
            "category":"Restaurant",
            "type":"Food & Drink"
        }
    ],
    "sg:phone":"+1 817 444 5271",
    "sg:postcode":"76020",
    "sg:province":"TX",
    "sg:tags":[
        "eating"
    ],
    "wof:name":"Sarahs Dog House",
    "wof:placetype":"venue"
},
  "geometry": {"coordinates":[-97.522756,32.90126],"type":"Point"}
}