{
  "type": "Feature",
  "properties": {
    "iso:country":"US",
    "sg:address":"207 N Main St",
    "sg:city":"Hutchins",
    "sg:classifiers":[
        {
            "category":"Professional",
            "subcategory":"Management & Consulting",
            "type":"Services"
        }
    ],
    "sg:phone":"+1 972 225 4332",
    "sg:postcode":"75141",
    "sg:province":"TX",
    "sg:tags":[
        "consultant",
        "business"
    ],
    "wof:name":"21st Century Safety Consultant",
    "wof:placetype":"venue"
},
  "geometry": {"coordinates":[-96.71302900000001,32.649153],"type":"Point"}
}