{
  "type": "Feature",
  "properties": {
    "iso:country":"US",
    "sg:address":"510 N Zang Blvd",
    "sg:city":"Dallas",
    "sg:classifiers":[
        {
            "category":"Retail",
            "subcategory":"Auto Repair",
            "type":"Services"
        }
    ],
    "sg:phone":"+1 214 942 1522",
    "sg:postcode":"75208",
    "sg:province":"TX",
    "wof:name":"Auto Titulos Capi",
    "wof:placetype":"venue"
},
  "geometry": {"coordinates":[-96.823999,32.748922],"type":"Point"}
}