{
  "type": "Feature",
  "properties": {
    "iso:country":"US",
    "sg:address":"7129 Broadway St",
    "sg:city":"Pearland",
    "sg:classifiers":[
        {
            "category":"Restaurant",
            "type":"Food & Drink"
        }
    ],
    "sg:phone":"+1 281 997 0890",
    "sg:postcode":"77581",
    "sg:province":"TX",
    "wof:name":"Zest's Bbq & Grill",
    "wof:placetype":"venue"
},
  "geometry": {"coordinates":[-95.33058,29.559358],"type":"Point"}
}