{
  "type": "Feature",
  "properties": {
    "iso:country":"US",
    "sg:address":"900 Sids Rd",
    "sg:city":"Rockwall",
    "sg:classifiers":[
        {
            "category":"Home & Garden",
            "subcategory":"Building Materials",
            "type":"Retail Goods"
        },
        {
            "category":"Manufacturing",
            "subcategory":"Glass & Minerals",
            "type":"Manufacturing & Wholesale Goods"
        }
    ],
    "sg:phone":"+1 972 772 9490",
    "sg:postcode":"75032",
    "sg:province":"TX",
    "sg:tags":[
        "cast",
        "stone",
        "mfg"
    ],
    "sg:website":"www.pristinecaststone.com",
    "wof:name":"Pristine Cast Stone Inc",
    "wof:placetype":"venue"
},
  "geometry": {"coordinates":[-96.4435,32.899606],"type":"Point"}
}