{
  "type": "Feature",
  "properties": {
    "iso:country":"US",
    "sg:address":"3321 Bell St",
    "sg:city":"Amarillo",
    "sg:classifiers":[
        {
            "category":"Insurance",
            "subcategory":"Insurance Agent",
            "type":"Services"
        }
    ],
    "sg:phone":"+1 806 352 2777",
    "sg:postcode":"79106",
    "sg:province":"TX",
    "wof:name":"Ronnie Mankin Insurance",
    "wof:placetype":"venue"
},
  "geometry": {"coordinates":[-101.90221699999999,35.176786],"type":"Point"}
}