{
  "type": "Feature",
  "properties": {
    "iso:country":"US",
    "sg:address":"1706 Creekpoint Dr",
    "sg:city":"Lewisville",
    "sg:classifiers":[
        {
            "category":"Home & Garden",
            "subcategory":"Building Materials",
            "type":"Retail Goods"
        }
    ],
    "sg:phone":"+1 972 219 0997",
    "sg:postcode":"75067",
    "sg:province":"TX",
    "wof:name":"Sk Plumbing Inc",
    "wof:placetype":"venue"
},
  "geometry": {"coordinates":[-97.032454,33.026835],"type":"Point"}
}