{
  "type": "Feature",
  "properties": {
    "iso:country":"US",
    "sg:address":"6862 Koppe Bridge Rd",
    "sg:city":"College Station",
    "sg:classifiers":[
        {
            "category":"Retail",
            "subcategory":"Veterinary Services",
            "type":"Services"
        }
    ],
    "sg:phone":"+1 979 690 0887",
    "sg:postcode":"77845",
    "sg:province":"TX",
    "wof:name":"Barbara Hannes Dvm",
    "wof:placetype":"venue"
},
  "geometry": {"coordinates":[-96.33618199999999,30.510148],"type":"Point"}
}