{
  "type": "Feature",
  "properties": {
    "iso:country":"US",
    "sg:address":"3301 S Broadway Ave",
    "sg:city":"Tyler",
    "sg:classifiers":[
        {
            "category":"Real Estate",
            "subcategory":"Real Estate Operator",
            "type":"Services"
        }
    ],
    "sg:phone":"+1 903 592 1060",
    "sg:postcode":"75701",
    "sg:province":"TX",
    "sg:tags":[
        "building",
        "apartment"
    ],
    "wof:name":"Barclay Apartments Inc",
    "wof:placetype":"venue"
},
  "geometry": {"coordinates":[-95.30063199999999,32.316258],"type":"Point"}
}