{
  "type": "Feature",
  "properties": {
    "iso:country":"US",
    "sg:address":"1205 Texas Star Pkwy",
    "sg:city":"Euless",
    "sg:classifiers":[
        {
            "category":"Education",
            "subcategory":"Special Training",
            "type":"Public Place"
        }
    ],
    "sg:phone":"+1 817 545 4500",
    "sg:postcode":"76040",
    "sg:province":"TX",
    "sg:tags":[
        "center"
    ],
    "wof:name":"Learn Education Ctr",
    "wof:placetype":"venue"
},
  "geometry": {"coordinates":[-97.114367,32.820059],"type":"Point"}
}