{
  "type": "Feature",
  "properties": {
    "iso:country":"US",
    "sg:address":"3113 Edgewood Dr",
    "sg:city":"Dickinson",
    "sg:classifiers":[
        {
            "category":"Building & Trades",
            "subcategory":"Construction",
            "type":"Services"
        }
    ],
    "sg:phone":"+1 281 337 4595",
    "sg:postcode":"77539",
    "sg:province":"TX",
    "sg:tags":[
        "house"
    ],
    "wof:name":"Brown Builders",
    "wof:placetype":"venue"
},
  "geometry": {"coordinates":[-95.04925799999999,29.472474],"type":"Point"}
}