{
  "type": "Feature",
  "properties": {
    "iso:country":"US",
    "sg:address":"1113 Vine St",
    "sg:city":"Houston",
    "sg:classifiers":[
        {
            "category":"Professional",
            "subcategory":"Advertising",
            "type":"Services"
        }
    ],
    "sg:phone":"+1 713 236 0274",
    "sg:postcode":"77002",
    "sg:province":"TX",
    "sg:tags":[
        "counselor"
    ],
    "wof:name":"Morrison Design & Advertising",
    "wof:placetype":"venue"
},
  "geometry": {"coordinates":[-95.35706500000001,29.767917],"type":"Point"}
}