{
  "type": "Feature",
  "properties": {
    "iso:country":"US",
    "sg:address":"6039 Settlers Village Dr",
    "sg:city":"Katy",
    "sg:classifiers":[
        {
            "category":"Professional",
            "type":"Services"
        }
    ],
    "sg:phone":"+1 281 856 2059",
    "sg:postcode":"77449",
    "sg:province":"TX",
    "wof:name":"Candle Craze",
    "wof:placetype":"venue"
},
  "geometry": {"coordinates":[-95.73080299999999,29.864815],"type":"Point"}
}