{
  "type": "Feature",
  "properties": {
    "iso:country":"US",
    "sg:address":"4211 Albans Rd",
    "sg:city":"Houston",
    "sg:classifiers":[
        {
            "category":"Professional",
            "subcategory":"Advertising",
            "type":"Services"
        }
    ],
    "sg:phone":"+1 713 660 0154",
    "sg:postcode":"77005",
    "sg:province":"TX",
    "sg:tags":[
        "agency"
    ],
    "wof:name":"Egads",
    "wof:placetype":"venue"
},
  "geometry": {"coordinates":[-95.446933,29.723741],"type":"Point"}
}