{
  "type": "Feature",
  "properties": {
    "iso:country":"US",
    "sg:address":"818 Hurley St",
    "sg:city":"Houston",
    "sg:classifiers":[
        {
            "category":"Professional",
            "subcategory":"Business Services",
            "type":"Services"
        }
    ],
    "sg:phone":"+1 713 699 3239",
    "sg:postcode":"77022",
    "sg:province":"TX",
    "wof:name":"Tupperware",
    "wof:placetype":"venue"
},
  "geometry": {"coordinates":[-95.365196,29.845041],"type":"Point"}
}