{
  "type": "Feature",
  "properties": {
    "iso:country":"US",
    "sg:address":"1726 E Hufsmith Rd",
    "sg:city":"Tomball",
    "sg:classifiers":[
        {
            "category":"Building & Trades",
            "subcategory":"Plumbing",
            "type":"Services"
        }
    ],
    "sg:phone":"+1 281 255 6464",
    "sg:postcode":"77375",
    "sg:province":"TX",
    "sg:tags":[
        "mechanical",
        "welding"
    ],
    "wof:name":"Efficient Mech & Wldg Svc",
    "wof:placetype":"venue"
},
  "geometry": {"coordinates":[-95.59851999999999,30.11669],"type":"Point"}
}