{
  "type": "Feature",
  "properties": {
    "iso:country":"US",
    "sg:address":"729 N Bailey Ave",
    "sg:city":"Fort Worth",
    "sg:classifiers":[
        {
            "category":"Restaurant",
            "type":"Food & Drink"
        }
    ],
    "sg:phone":"+1 817 625 1725",
    "sg:postcode":"76107",
    "sg:province":"TX",
    "sg:tags":[
        "drinking",
        "eating"
    ],
    "wof:name":"Patio King Entertainment",
    "wof:placetype":"venue"
},
  "geometry": {"coordinates":[-97.375525,32.770742],"type":"Point"}
}