{
  "type": "Feature",
  "properties": {
    "iso:country":"US",
    "sg:address":"1105 Pine Hollow Dr",
    "sg:city":"Friendswood",
    "sg:classifiers":[
        {
            "category":"Wholesale",
            "subcategory":"Chemicals & Plastics",
            "type":"Manufacturing & Wholesale Goods"
        }
    ],
    "sg:phone":"+1 281 996 8211",
    "sg:postcode":"77546",
    "sg:province":"TX",
    "wof:name":"Gulf Coast Chemical",
    "wof:placetype":"venue"
},
  "geometry": {"coordinates":[-95.21843699999999,29.519909],"type":"Point"}
}