{
  "type": "Feature",
  "properties": {
    "iso:country":"US",
    "sg:address":"2718 Sherwood Way",
    "sg:city":"San Angelo",
    "sg:classifiers":[
        {
            "category":"Food & Beverages",
            "subcategory":"Groceries & Convenience Stores",
            "type":"Retail Goods"
        }
    ],
    "sg:phone":"+1 325 944 1621",
    "sg:postcode":"76901",
    "sg:province":"TX",
    "wof:name":"Town & Country Food Store 76",
    "wof:placetype":"venue"
},
  "geometry": {"coordinates":[-100.473173,31.449032],"type":"Point"}
}