{
  "type": "Feature",
  "properties": {
    "iso:country":"US",
    "sg:address":"1204 Cedar Ave",
    "sg:city":"Austin",
    "sg:classifiers":[
        {
            "category":"Organizations",
            "subcategory":"Religious Organization",
            "type":"Services"
        }
    ],
    "sg:phone":"+1 512 478 3693",
    "sg:postcode":"78702",
    "sg:province":"TX",
    "sg:tags":[
        "church"
    ],
    "wof:name":"Rosewood Congregation",
    "wof:placetype":"venue"
},
  "geometry": {"coordinates":[-97.713314,30.275797],"type":"Point"}
}