{
  "type": "Feature",
  "properties": {
    "iso:country":"US",
    "sg:address":"12102 14th St",
    "sg:city":"Santa Fe",
    "sg:classifiers":[
        {
            "category":"Retail",
            "subcategory":"Repair Shop",
            "type":"Services"
        }
    ],
    "sg:phone":"+1 409 927 1465",
    "sg:postcode":"77510",
    "sg:province":"TX",
    "sg:tags":[
        "refrigeration"
    ],
    "wof:name":"A/C Doctor",
    "wof:placetype":"venue"
},
  "geometry": {"coordinates":[-95.085786,29.372583],"type":"Point"}
}