{
  "type": "Feature",
  "properties": {
    "iso:country":"US",
    "sg:address":"3720 Old Spanish Trl",
    "sg:city":"Houston",
    "sg:classifiers":[
        {
            "category":"Restaurant",
            "type":"Food & Drink"
        }
    ],
    "sg:phone":"+1 713 842 2137",
    "sg:postcode":"77021",
    "sg:province":"TX",
    "wof:name":"Family Eats",
    "wof:placetype":"venue"
},
  "geometry": {"coordinates":[-95.359416,29.702375],"type":"Point"}
}