{
  "type": "Feature",
  "properties": {
    "iso:country":"US",
    "sg:address":"61 S Shamrock Ct",
    "sg:city":"Lake Jackson",
    "sg:classifiers":[
        {
            "category":"Real Estate",
            "subcategory":"Real Estate Operator",
            "type":"Services"
        }
    ],
    "sg:phone":"+1 979 297 1808",
    "sg:postcode":"77566",
    "sg:province":"TX",
    "sg:tags":[
        "building",
        "apartment"
    ],
    "wof:name":"Riverside Apts",
    "wof:placetype":"venue"
},
  "geometry": {"coordinates":[-95.42567699999999,29.034137],"type":"Point"}
}