{
  "type": "Feature",
  "properties": {
    "iso:country":"US",
    "sg:address":"108 S 16th St",
    "sg:city":"Mcallen",
    "sg:classifiers":[
        {
            "category":"Shopping",
            "subcategory":"Department Store",
            "type":"Retail Goods"
        }
    ],
    "sg:phone":"+1 956 682 1394",
    "sg:postcode":"78501",
    "sg:province":"TX",
    "wof:name":"Detodo Inc",
    "wof:placetype":"venue"
},
  "geometry": {"coordinates":[-98.237002,26.20279],"type":"Point"}
}