{
  "type": "Feature",
  "properties": {
    "iso:country":"US",
    "sg:address":"3220 Custer Rd",
    "sg:city":"Plano",
    "sg:classifiers":[
        {
            "category":"Retail",
            "subcategory":"Auto Repair",
            "type":"Services"
        }
    ],
    "sg:phone":"+1 972 964 3200",
    "sg:postcode":"75075",
    "sg:province":"TX",
    "sg:tags":[
        "wrecker"
    ],
    "wof:name":"Broken Toe Inc",
    "wof:placetype":"venue"
},
  "geometry": {"coordinates":[-96.73324700000001,33.040658],"type":"Point"}
}