{
  "type": "Feature",
  "properties": {
    "iso:country":"US",
    "sg:address":"327 University Dr",
    "sg:city":"College Station",
    "sg:classifiers":[
        {
            "category":"Shopping",
            "subcategory":"Books",
            "type":"Retail Goods"
        }
    ],
    "sg:phone":"+1 979 846 4518",
    "sg:postcode":"77840",
    "sg:province":"TX",
    "sg:tags":[
        "dealer"
    ],
    "sg:website":"www.txag.com",
    "wof:name":"Texas Aggie Bookstores",
    "wof:placetype":"venue"
},
  "geometry": {"coordinates":[-96.34681999999999,30.617096],"type":"Point"}
}