{
  "type": "Feature",
  "properties": {
    "iso:country":"US",
    "sg:address":"514 N Main St",
    "sg:city":"Duncanville",
    "sg:classifiers":[
        {
            "category":"Retail",
            "subcategory":"Repair Shop",
            "type":"Services"
        }
    ],
    "sg:phone":"+1 972 298 4435",
    "sg:postcode":"75116",
    "sg:province":"TX",
    "sg:tags":[
        "key",
        "locksmith"
    ],
    "wof:name":"Lincoln Lock",
    "wof:placetype":"venue"
},
  "geometry": {"coordinates":[-96.9076,32.656399],"type":"Point"}
}