{
  "type": "Feature",
  "properties": {
    "iso:country":"US",
    "sg:address":"2054 N Kimball Ave",
    "sg:city":"Southlake",
    "sg:classifiers":[
        {
            "category":"Professional",
            "subcategory":"Business Services",
            "type":"Services"
        }
    ],
    "sg:phone":"+1 817 488 4570",
    "sg:postcode":"76092",
    "sg:province":"TX",
    "sg:tags":[
        "interior",
        "consultant",
        "design",
        "decorator"
    ],
    "wof:name":"Mitzi's Interior Designs",
    "wof:placetype":"venue"
},
  "geometry": {"coordinates":[-97.116753,32.962774],"type":"Point"}
}