{
  "type": "Feature",
  "properties": {
    "iso:country":"US",
    "sg:address":"4815 Vicksburg St",
    "sg:city":"Dallas",
    "sg:classifiers":[
        {
            "category":"Building & Trades",
            "subcategory":"Construction",
            "type":"Services"
        }
    ],
    "sg:phone":"+1 214 689 3882",
    "sg:postcode":"75207",
    "sg:province":"TX",
    "sg:tags":[
        "general",
        "contractor"
    ],
    "wof:name":"R M Rebar",
    "wof:placetype":"venue"
},
  "geometry": {"coordinates":[-96.850257,32.807124],"type":"Point"}
}