{
  "type": "Feature",
  "properties": {
    "iso:country":"US",
    "sg:address":"434 S Main Ave",
    "sg:city":"San Antonio",
    "sg:classifiers":[
        {
            "category":"Professional",
            "subcategory":"Lawyer & Legal Services",
            "type":"Services"
        }
    ],
    "sg:phone":"+1 210 226 1145",
    "sg:postcode":"78204",
    "sg:province":"TX",
    "sg:tags":[
        "attorney"
    ],
    "wof:name":"Ricardo A Byngtn Law Office",
    "wof:placetype":"venue"
},
  "geometry": {"coordinates":[-98.49473999999999,29.420435],"type":"Point"}
}