{
  "type": "Feature",
  "properties": {
    "iso:country":"US",
    "sg:address":"609 Lindenwood Dr",
    "sg:city":"Lancaster",
    "sg:classifiers":[
        {
            "category":"Professional",
            "type":"Services"
        }
    ],
    "sg:phone":"+1 972 227 2018",
    "sg:postcode":"75134",
    "sg:province":"TX",
    "wof:name":"Sealy Studio",
    "wof:placetype":"venue"
},
  "geometry": {"coordinates":[-96.766124,32.610031],"type":"Point"}
}