{
  "type": "Feature",
  "properties": {
    "iso:country":"US",
    "sg:address":"2600 W Hwy 377",
    "sg:city":"Granbury",
    "sg:classifiers":[
        {
            "category":"Real Estate",
            "subcategory":"Real Estate Operator",
            "type":"Services"
        }
    ],
    "sg:phone":"+1 817 573 7539",
    "sg:postcode":"76048",
    "sg:province":"TX",
    "sg:tags":[
        "mobile",
        "home",
        "site"
    ],
    "wof:name":"Country Side Rv Park",
    "wof:placetype":"venue"
},
  "geometry": {"coordinates":[-97.822681,32.434065],"type":"Point"}
}