{
  "type": "Feature",
  "properties": {
    "iso:country":"US",
    "sg:address":"8300 Douglas Ave",
    "sg:city":"Dallas",
    "sg:classifiers":[
        {
            "category":"Professional",
            "type":"Services"
        }
    ],
    "sg:phone":"+1 214 450 6500",
    "sg:postcode":"75225",
    "sg:province":"TX",
    "wof:name":"Preston 8300 Douglas",
    "wof:placetype":"venue"
},
  "geometry": {"coordinates":[-96.80864099999999,32.864843],"type":"Point"}
}