{
  "type": "Feature",
  "properties": {
    "iso:country":"US",
    "sg:address":"303 Westwood Dr",
    "sg:city":"Friendswood",
    "sg:classifiers":[
        {
            "category":"Professional",
            "subcategory":"Management & Consulting",
            "type":"Services"
        }
    ],
    "sg:phone":"+1 281 482 8186",
    "sg:postcode":"77546",
    "sg:province":"TX",
    "wof:name":"Gies Management Services",
    "wof:placetype":"venue"
},
  "geometry": {"coordinates":[-95.214034,29.543211],"type":"Point"}
}