{
  "type": "Feature",
  "properties": {
    "iso:country":"US",
    "sg:address":"11914 State Hwy 30",
    "sg:city":"College Station",
    "sg:classifiers":[
        {
            "category":"Organizations",
            "subcategory":"Religious Organization",
            "type":"Services"
        }
    ],
    "sg:phone":"+1 979 774 7470",
    "sg:postcode":"77845",
    "sg:province":"TX",
    "sg:tags":[
        "church"
    ],
    "wof:name":"Bryan College Sta Chr-Christ",
    "wof:placetype":"venue"
},
  "geometry": {"coordinates":[-96.247164,30.637386],"type":"Point"}
}