{
  "type": "Feature",
  "properties": {
    "iso:country":"US",
    "sg:address":"1501 W 5th Suite C",
    "sg:city":"Austin",
    "sg:classifiers":[
        {
            "category":"Personal",
            "subcategory":"Beauty Salon",
            "type":"Services"
        }
    ],
    "sg:phone":"+1 512 474 6333",
    "sg:postcode":"78703",
    "sg:province":"TX",
    "sg:tags":[
        "spa"
    ],
    "wof:name":"Salon On 5th",
    "wof:placetype":"venue"
},
  "geometry": {"coordinates":[-97.761859,30.273107],"type":"Point"}
}