{
  "type": "Feature",
  "properties": {
    "iso:country":"US",
    "sg:address":"2901 S Capital of Texas Hwy",
    "sg:city":"Austin",
    "sg:classifiers":[
        {
            "category":"Shopping",
            "subcategory":"Optician",
            "type":"Retail Goods"
        }
    ],
    "sg:phone":"+1 512 328 0203",
    "sg:postcode":"78746",
    "sg:province":"TX",
    "sg:tags":[
        "eyewear"
    ],
    "wof:name":"Barton Creek O-Store",
    "wof:placetype":"venue"
},
  "geometry": {"coordinates":[-97.81076400000001,30.256312],"type":"Point"}
}