{
  "type": "Feature",
  "properties": {
    "iso:country":"US",
    "sg:address":"106 Summerwood Dr",
    "sg:city":"Liberty Hill",
    "sg:classifiers":[
        {
            "category":"Shopping",
            "subcategory":"Gifts & Souvenirs",
            "type":"Retail Goods"
        }
    ],
    "sg:phone":"+1 512 515 0914",
    "sg:postcode":"78642",
    "sg:province":"TX",
    "wof:name":"Hummingbird Greetings",
    "wof:placetype":"venue"
},
  "geometry": {"coordinates":[-97.87960200000001,30.735739],"type":"Point"}
}