{
  "type": "Feature",
  "properties": {
    "iso:country":"US",
    "sg:address":"4001 Preston Ave",
    "sg:city":"Pasadena",
    "sg:classifiers":[
        {
            "category":"Health Services",
            "subcategory":"Doctor",
            "type":"Services"
        }
    ],
    "sg:phone":"+1 281 998 8497",
    "sg:postcode":"77505",
    "sg:province":"TX",
    "sg:tags":[
        "physician",
        "surgeon"
    ],
    "wof:name":"Greater Houston Anesthesiology",
    "wof:placetype":"venue"
},
  "geometry": {"coordinates":[-95.17133200000001,29.648647],"type":"Point"}
}