{
  "type": "Feature",
  "properties": {
    "iso:country":"US",
    "sg:address":"906 Mimosa Dr",
    "sg:city":"Mineola",
    "sg:classifiers":[
        {
            "category":"Shopping",
            "subcategory":"Gifts & Souvenirs",
            "type":"Retail Goods"
        }
    ],
    "sg:phone":"+1 903 569 2033",
    "sg:postcode":"75773",
    "sg:province":"TX",
    "wof:name":"Enchanted Cottage",
    "wof:placetype":"venue"
},
  "geometry": {"coordinates":[-95.479259,32.662059],"type":"Point"}
}