{
  "type": "Feature",
  "properties": {
    "iso:country":"US",
    "sg:address":"2064 Boulder Ridge Dr",
    "sg:city":"Eagle Pass",
    "sg:classifiers":[
        {
            "category":"Organizations",
            "subcategory":"Community Association",
            "type":"Services"
        }
    ],
    "sg:phone":"+1 830 752 1288",
    "sg:postcode":"78852",
    "sg:province":"TX",
    "wof:name":"Community Clonias Organization",
    "wof:placetype":"venue"
},
  "geometry": {"coordinates":[-100.49640599999999,28.681119],"type":"Point"}
}