{
  "type": "Feature",
  "properties": {
    "iso:country":"US",
    "sg:address":"16854 Tortoise St",
    "sg:city":"Round Rock",
    "sg:classifiers":[
        {
            "category":"Retail",
            "subcategory":"Repair Shop",
            "type":"Services"
        }
    ],
    "sg:phone":"+1 512 252 8775",
    "sg:postcode":"78664",
    "sg:province":"TX",
    "wof:name":"R&M Cleaning",
    "wof:placetype":"venue"
},
  "geometry": {"coordinates":[-97.650249,30.46404],"type":"Point"}
}