{
  "type": "Feature",
  "properties": {
    "iso:country":"US",
    "sg:address":"3600 Huffines Blvd",
    "sg:city":"Carrollton",
    "sg:classifiers":[
        {
            "category":"Restaurant",
            "type":"Food & Drink"
        }
    ],
    "sg:phone":"+1 972 394 8270",
    "sg:postcode":"75010",
    "sg:province":"TX",
    "sg:tags":[
        "indian"
    ],
    "sg:website":"www.keralakitchenonline.com",
    "wof:name":"Kerala Kitchen",
    "wof:placetype":"venue"
},
  "geometry": {"coordinates":[-96.942581,33.010903],"type":"Point"}
}