{
  "type": "Feature",
  "properties": {
    "iso:country":"US",
    "sg:address":"2100 E 6th Street",
    "sg:city":"Austin",
    "sg:classifiers":[
        {
            "category":"Health Services",
            "subcategory":"Doctor",
            "type":"Services"
        }
    ],
    "sg:phone":"+1 512 482 0248",
    "sg:postcode":"78702",
    "sg:province":"TX",
    "sg:tags":[
        "physician",
        "family",
        "practice",
        "surgeons",
        "medicine",
        "surgeon"
    ],
    "wof:name":"Zamora Guadalupe MD",
    "wof:placetype":"venue"
},
  "geometry": {"coordinates":[-97.719894,30.260758],"type":"Point"}
}