{
  "type": "Feature",
  "properties": {
    "iso:country":"US",
    "sg:address":"7231 Richwood Rd",
    "sg:city":"Houston",
    "sg:classifiers":[
        {
            "category":"Building & Trades",
            "subcategory":"Plumbing",
            "type":"Services"
        }
    ],
    "sg:phone":"+1 713 641 1336",
    "sg:postcode":"77087",
    "sg:province":"TX",
    "sg:tags":[
        "contractor"
    ],
    "wof:name":"Mays AC & Htg Svcs Co",
    "wof:placetype":"venue"
},
  "geometry": {"coordinates":[-95.297597,29.677631],"type":"Point"}
}