{
  "type": "Feature",
  "properties": {
    "iso:country":"US",
    "sg:address":"409 W Wheat St",
    "sg:city":"Woodville",
    "sg:classifiers":[
        {
            "category":"Professional",
            "subcategory":"Computer Services",
            "type":"Services"
        }
    ],
    "sg:phone":"+1 409 331 0988",
    "sg:postcode":"75979",
    "sg:province":"TX",
    "sg:tags":[
        "related"
    ],
    "wof:name":"Webstrom",
    "wof:placetype":"venue"
},
  "geometry": {"coordinates":[-94.41852299999999,30.774312],"type":"Point"}
}