{
  "type": "Feature",
  "properties": {
    "iso:country":"US",
    "sg:address":"110 W Airport Fwy",
    "sg:city":"Irving",
    "sg:classifiers":[
        {
            "category":"Travel",
            "subcategory":"Hotels & Motels",
            "type":"Entertainment"
        }
    ],
    "sg:phone":"+1 972 438 2000",
    "sg:postcode":"75062",
    "sg:province":"TX",
    "wof:name":"Skyway Inn",
    "wof:placetype":"venue"
},
  "geometry": {"coordinates":[-96.945373,32.836542],"type":"Point"}
}