{
  "type": "Feature",
  "properties": {
    "iso:country":"US",
    "sg:address":"809 E Pecan St",
    "sg:city":"Celina",
    "sg:classifiers":[
        {
            "category":"Health Services",
            "subcategory":"Doctor",
            "type":"Services"
        }
    ],
    "sg:phone":"+1 972 382 2660",
    "sg:postcode":"75009",
    "sg:province":"TX",
    "sg:tags":[
        "dentist"
    ],
    "wof:name":"Celina Dentristry",
    "wof:placetype":"venue"
},
  "geometry": {"coordinates":[-96.77700900000001,33.323703],"type":"Point"}
}