{
  "type": "Feature",
  "properties": {
    "iso:country":"US",
    "sg:address":"2340 Barker Oaks Dr",
    "sg:city":"Houston",
    "sg:classifiers":[
        {
            "category":"Building & Trades",
            "subcategory":"Construction",
            "type":"Services"
        }
    ],
    "sg:phone":"+1 713 896 0266",
    "sg:postcode":"77077",
    "sg:province":"TX",
    "sg:tags":[
        "hanging",
        "contractor"
    ],
    "wof:name":"Texas Paints Specialist",
    "wof:placetype":"venue"
},
  "geometry": {"coordinates":[-95.64702800000001,29.738069],"type":"Point"}
}