{
  "type": "Feature",
  "properties": {
    "iso:country":"US",
    "sg:address":"2606 E 14th St",
    "sg:city":"Austin",
    "sg:classifiers":[
        {
            "category":"Health Services",
            "subcategory":"Nursing And Care Facility",
            "type":"Services"
        }
    ],
    "sg:phone":"+1 512 474 9514",
    "sg:postcode":"78702",
    "sg:province":"TX",
    "wof:name":"E&C Boarding Home",
    "wof:placetype":"venue"
},
  "geometry": {"coordinates":[-97.71257300000001,30.277053],"type":"Point"}
}