{
  "type": "Feature",
  "properties": {
    "iso:country":"US",
    "sg:address":"1295 Pearl St",
    "sg:city":"Beaumont",
    "sg:classifiers":[
        {
            "category":"Health Services",
            "subcategory":"Doctor",
            "type":"Services"
        }
    ],
    "sg:phone":"+1 409 833 0452",
    "sg:postcode":"77701",
    "sg:province":"TX",
    "sg:tags":[
        "clinic"
    ],
    "wof:name":"Pre Natal Clinic",
    "wof:placetype":"venue"
},
  "geometry": {"coordinates":[-94.092812,30.078112],"type":"Point"}
}