{
  "type": "Feature",
  "properties": {
    "iso:country":"US",
    "sg:address":"17304 Preston Rd",
    "sg:city":"Dallas",
    "sg:classifiers":[
        {
            "category":"Banks & Credit Unions",
            "subcategory":"Financial Services",
            "type":"Services"
        }
    ],
    "sg:phone":"+1 972 733 6590",
    "sg:postcode":"75252",
    "sg:province":"TX",
    "sg:tags":[
        "broker",
        "mortgage"
    ],
    "wof:name":"Oates Gordon",
    "wof:placetype":"venue"
},
  "geometry": {"coordinates":[-96.789101,33.002701],"type":"Point"}
}