{
  "type": "Feature",
  "properties": {
    "iso:country":"US",
    "sg:address":"2022 Bandera Rd",
    "sg:city":"San Antonio",
    "sg:classifiers":[
        {
            "category":"Personal",
            "subcategory":"Shoe Repair & Shine",
            "type":"Services"
        }
    ],
    "sg:phone":"+1 210 434 3037",
    "sg:postcode":"78228",
    "sg:province":"TX",
    "sg:tags":[
        "shop"
    ],
    "wof:name":"Hoa Shoes",
    "wof:placetype":"venue"
},
  "geometry": {"coordinates":[-98.57962499999999,29.473872],"type":"Point"}
}