{
  "type": "Feature",
  "properties": {
    "iso:country":"US",
    "sg:address":"205 N Marable St",
    "sg:city":"West",
    "sg:classifiers":[
        {
            "category":"Travel",
            "subcategory":"Travel Agent",
            "type":"Entertainment"
        }
    ],
    "sg:phone":"+1 254 826 3811",
    "sg:postcode":"76691",
    "sg:province":"TX",
    "sg:tags":[
        "agency",
        "bureau"
    ],
    "wof:name":"Going Places Travel",
    "wof:placetype":"venue"
},
  "geometry": {"coordinates":[-97.096158,31.8044],"type":"Point"}
}