{
  "type": "Feature",
  "properties": {
    "iso:country":"US",
    "sg:address":"1222 Cherrywood Dr",
    "sg:city":"Richardson",
    "sg:classifiers":[
        {
            "category":"Shopping",
            "subcategory":"Clothing, Apparel, & Fashions",
            "type":"Retail Goods"
        }
    ],
    "sg:phone":"+1 972 235 8761",
    "sg:postcode":"75080",
    "sg:province":"TX",
    "wof:name":"Fantasy & Friends",
    "wof:placetype":"venue"
},
  "geometry": {"coordinates":[-96.75990899999999,32.953976],"type":"Point"}
}