{
  "type": "Feature",
  "properties": {
    "iso:country":"US",
    "sg:address":"1615 Stoneway Dr",
    "sg:city":"Grapevine",
    "sg:classifiers":[
        {
            "category":"Banks & Credit Unions",
            "subcategory":"Bank",
            "type":"Services"
        }
    ],
    "sg:phone":"+1 817 421 9058",
    "sg:postcode":"76051",
    "sg:province":"TX",
    "sg:tags":[
        "mortgage"
    ],
    "wof:name":"Kissell Terry & Dunton J",
    "wof:placetype":"venue"
},
  "geometry": {"coordinates":[-97.09141099999999,32.96026],"type":"Point"}
}