{
  "type": "Feature",
  "properties": {
    "iso:country":"US",
    "sg:address":"404 Co Rd 211",
    "sg:city":"Gainesville",
    "sg:classifiers":[
        {
            "category":"Wholesale",
            "subcategory":"Groceries",
            "type":"Manufacturing & Wholesale Goods"
        }
    ],
    "sg:phone":"+1 940 665 3426",
    "sg:postcode":"76240",
    "sg:province":"TX",
    "sg:tags":[
        "bean"
    ],
    "wof:name":"Lewis Grain Sales",
    "wof:placetype":"venue"
},
  "geometry": {"coordinates":[-97.015586,33.608959],"type":"Point"}
}