{
  "type": "Feature",
  "properties": {
    "iso:country":"US",
    "sg:address":"911 Timber Ln",
    "sg:city":"Caldwell",
    "sg:classifiers":[
        {
            "category":"Professional",
            "type":"Services"
        }
    ],
    "sg:phone":"+1 979 567 0496",
    "sg:postcode":"77836",
    "sg:province":"TX",
    "sg:tags":[
        "establishment"
    ],
    "wof:name":"Nickel Thrifty",
    "wof:placetype":"venue"
},
  "geometry": {"coordinates":[-96.712276,30.540327],"type":"Point"}
}