{
  "type": "Feature",
  "properties": {
    "iso:country":"US",
    "sg:address":"1514 Absher Ln",
    "sg:city":"Mansfield",
    "sg:classifiers":[
        {
            "category":"Professional",
            "type":"Services"
        }
    ],
    "sg:phone":"+1 817 477 2761",
    "sg:postcode":"76063",
    "sg:province":"TX",
    "wof:name":"William C Kothmann",
    "wof:placetype":"venue"
},
  "geometry": {"coordinates":[-97.132177,32.594562],"type":"Point"}
}