{
  "type": "Feature",
  "properties": {
    "iso:country":"US",
    "sg:address":"9800 N Lamar Boulevard Suite 280",
    "sg:city":"Austin",
    "sg:classifiers":[
        {
            "category":"Professional",
            "subcategory":"Employment Agencies",
            "type":"Services"
        }
    ],
    "sg:phone":"+1 512 873 9400",
    "sg:postcode":"78753",
    "sg:province":"TX",
    "wof:name":"V I P Employment Services",
    "wof:placetype":"venue"
},
  "geometry": {"coordinates":[-97.694535,30.367479],"type":"Point"}
}