{
  "type": "Feature",
  "properties": {
    "iso:country":"US",
    "sg:address":"2107 Mayfield Dr",
    "sg:city":"Round Rock",
    "sg:classifiers":[
        {
            "category":"Retail",
            "subcategory":"Animal Services",
            "type":"Services"
        }
    ],
    "sg:phone":"+1 512 246 9487",
    "sg:postcode":"78681",
    "sg:province":"TX",
    "wof:name":"Canine Rehabilitation & Condit",
    "wof:placetype":"venue"
},
  "geometry": {"coordinates":[-97.751339,30.532681],"type":"Point"}
}