{
  "type": "Feature",
  "properties": {
    "iso:country":"US",
    "sg:address":"5100 Tennyson Pkwy",
    "sg:city":"Plano",
    "sg:classifiers":[
        {
            "category":"Insurance",
            "subcategory":"Insurance Agent",
            "type":"Services"
        }
    ],
    "sg:phone":"+1 972 378 5466",
    "sg:postcode":"75024",
    "sg:province":"TX",
    "wof:name":"Northwestern Mutual Financial",
    "wof:placetype":"venue"
},
  "geometry": {"coordinates":[-96.80419000000001,33.065531],"type":"Point"}
}