{
  "type": "Feature",
  "properties": {
    "iso:country":"US",
    "sg:address":"4300 Holland Ave",
    "sg:city":"Dallas",
    "sg:classifiers":[
        {
            "category":"Professional",
            "subcategory":"Computer Services",
            "type":"Services"
        }
    ],
    "sg:phone":"+1 214 520 8783",
    "sg:postcode":"75219",
    "sg:province":"TX",
    "sg:tags":[
        "datum"
    ],
    "wof:name":"Koolhostwebcom",
    "wof:placetype":"venue"
},
  "geometry": {"coordinates":[-96.81066800000001,32.819463],"type":"Point"}
}