{
  "type": "Feature",
  "properties": {
    "iso:country":"US",
    "sg:address":"13 Chris Thompson Rd",
    "sg:city":"Victoria",
    "sg:classifiers":[
        {
            "category":"Professional",
            "type":"Services"
        }
    ],
    "sg:phone":"+1 361 578 6070",
    "sg:postcode":"77905",
    "sg:province":"TX",
    "wof:name":"Larry Duval's Welding Svc",
    "wof:placetype":"venue"
},
  "geometry": {"coordinates":[-97.205012,28.819802],"type":"Point"}
}