{
  "type": "Feature",
  "properties": {
    "iso:country":"US",
    "sg:address":"2508 Durwood St",
    "sg:city":"Austin",
    "sg:classifiers":[
        {
            "category":"Government",
            "subcategory":"Office",
            "type":"Public Place"
        }
    ],
    "sg:phone":"+1 512 707 7418",
    "sg:postcode":"78704",
    "sg:province":"TX",
    "sg:tags":[
        "government-united",
        "state"
    ],
    "wof:name":"City of Austin Health-Fax",
    "wof:placetype":"venue"
},
  "geometry": {"coordinates":[-97.758741,30.239811],"type":"Point"}
}