{
  "type": "Feature",
  "properties": {
    "iso:country":"US",
    "sg:address":"6414 Jersey Ln",
    "sg:city":"Arlington",
    "sg:classifiers":[
        {
            "category":"Professional",
            "subcategory":"Business Services",
            "type":"Services"
        }
    ],
    "sg:phone":"+1 817 417 6075",
    "sg:postcode":"76018",
    "sg:province":"TX",
    "wof:name":"Lineage Group",
    "wof:placetype":"venue"
},
  "geometry": {"coordinates":[-97.07812699999999,32.641601],"type":"Point"}
}