{
  "type": "Feature",
  "properties": {
    "iso:country":"US",
    "sg:address":"1418 Lakecrest St",
    "sg:city":"Grand Prairie",
    "sg:classifiers":[
        {
            "category":"Building & Trades",
            "subcategory":"Plumbing",
            "type":"Services"
        }
    ],
    "sg:phone":"+1 972 262 0624",
    "sg:postcode":"75051",
    "sg:province":"TX",
    "sg:tags":[
        "contractor"
    ],
    "wof:name":"Cornerstone A/C",
    "wof:placetype":"venue"
},
  "geometry": {"coordinates":[-96.98267,32.728938],"type":"Point"}
}