{
  "type": "Feature",
  "properties": {
    "iso:country":"US",
    "sg:address":"505 Sunset Ln",
    "sg:city":"Copperas Cove",
    "sg:classifiers":[
        {
            "category":"Restaurant",
            "type":"Food & Drink"
        }
    ],
    "sg:phone":"+1 254 518 5900",
    "sg:postcode":"76522",
    "sg:province":"TX",
    "sg:tags":[
        "eating",
        "caterer"
    ],
    "wof:name":"Annointed Hands Catering Svc",
    "wof:placetype":"venue"
},
  "geometry": {"coordinates":[-97.91182499999999,31.113147],"type":"Point"}
}