{
  "type": "Feature",
  "properties": {
    "iso:country":"US",
    "sg:address":"12208 Co Rd 3100",
    "sg:city":"Slaton",
    "sg:classifiers":[
        {
            "category":"Wholesale",
            "subcategory":"Farm Supplies",
            "type":"Manufacturing & Wholesale Goods"
        },
        {
            "category":"Farming",
            "subcategory":"Livestock Farm",
            "type":"Manufacturing & Wholesale Goods"
        }
    ],
    "sg:phone":"+1 806 828 5544",
    "sg:postcode":"79364",
    "sg:province":"TX",
    "sg:tags":[
        "beekeeper"
    ],
    "wof:name":"Bill's Bees",
    "wof:placetype":"venue"
},
  "geometry": {"coordinates":[-101.710303,33.484546],"type":"Point"}
}