{
  "type": "Feature",
  "properties": {
    "iso:country":"US",
    "sg:address":"1101 Commerce Dr",
    "sg:city":"Richardson",
    "sg:classifiers":[
        {
            "category":"Manufacturing",
            "subcategory":"Tools & Machinery",
            "type":"Manufacturing & Wholesale Goods"
        }
    ],
    "sg:phone":"+1 972 994 0000",
    "sg:postcode":"75081",
    "sg:province":"TX",
    "sg:tags":[
        "machine",
        "shop"
    ],
    "wof:name":"Camtron Inc",
    "wof:placetype":"venue"
},
  "geometry": {"coordinates":[-96.705353,32.965939],"type":"Point"}
}