{
  "type": "Feature",
  "properties": {
    "iso:country":"US",
    "sg:address":"1716 Irwin Ln",
    "sg:city":"Sulphur Springs",
    "sg:classifiers":[
        {
            "category":"Freight",
            "type":"Transportation"
        }
    ],
    "sg:phone":"+1 903 439 1393",
    "sg:postcode":"75482",
    "sg:province":"TX",
    "sg:tags":[
        "trucking"
    ],
    "wof:name":"Gamblin Trucking Inc",
    "wof:placetype":"venue"
},
  "geometry": {"coordinates":[-95.593593,33.108292],"type":"Point"}
}