{
  "type": "Feature",
  "properties": {
    "iso:country":"US",
    "sg:address":"203 S Walcott St",
    "sg:city":"Jefferson",
    "sg:classifiers":[
        {
            "category":"Restaurant",
            "type":"Food & Drink"
        }
    ],
    "sg:menulink":"http://www.allmenus.com/tx/marion-east/204138-sonic/menu/",
    "sg:phone":"+1 903 665 2800",
    "sg:postcode":"75657",
    "sg:province":"TX",
    "sg:tags":[
        "burger",
        "american"
    ],
    "wof:name":"Sonic",
    "wof:placetype":"venue"
},
  "geometry": {"coordinates":[-94.35498200000001,32.760333],"type":"Point"}
}