{
  "type": "Feature",
  "properties": {
    "iso:country":"US",
    "sg:address":"5118 S Staples St",
    "sg:city":"Corpus Christi",
    "sg:classifiers":[
        {
            "category":"Shopping",
            "subcategory":"Clothing, Apparel, & Fashions",
            "type":"Retail Goods"
        }
    ],
    "sg:phone":"+1 361 985 1820",
    "sg:postcode":"78411",
    "sg:province":"TX",
    "sg:tags":[
        "furnishing"
    ],
    "wof:name":"Casual Male Big & Tall 9417",
    "wof:placetype":"venue"
},
  "geometry": {"coordinates":[-97.369991,27.707558],"type":"Point"}
}