{
  "type": "Feature",
  "properties": {
    "iso:country":"US",
    "sg:address":"4312 Green Meadow St W",
    "sg:city":"Colleyville",
    "sg:classifiers":[
        {
            "category":"Education",
            "subcategory":"Special Training",
            "type":"Public Place"
        }
    ],
    "sg:phone":"+1 817 581 1438",
    "sg:postcode":"76034",
    "sg:province":"TX",
    "sg:tags":[
        "school",
        "computer",
        "technology"
    ],
    "wof:name":"H And H Entreprises Limited",
    "wof:placetype":"venue"
},
  "geometry": {"coordinates":[-97.160004,32.87339],"type":"Point"}
}