{
  "type": "Feature",
  "properties": {
    "iso:country":"US",
    "sg:address":"10929 Nacogdoches Rd",
    "sg:city":"San Antonio",
    "sg:classifiers":[
        {
            "category":"Retail",
            "subcategory":"Auto Repair",
            "type":"Services"
        }
    ],
    "sg:phone":"+1 210 655 1170",
    "sg:postcode":"78217",
    "sg:province":"TX",
    "sg:tags":[
        "repairing",
        "automobile"
    ],
    "wof:name":"Han's Auto",
    "wof:placetype":"venue"
},
  "geometry": {"coordinates":[-98.42368399999999,29.538224],"type":"Point"}
}