{
  "type": "Feature",
  "properties": {
    "iso:country":"US",
    "sg:address":"1106 N Windomere Ave",
    "sg:city":"Dallas",
    "sg:classifiers":[
        {
            "category":"Professional",
            "type":"Services"
        }
    ],
    "sg:phone":"+1 214 946 1067",
    "sg:postcode":"75208",
    "sg:province":"TX",
    "wof:name":"Garden Quest",
    "wof:placetype":"venue"
},
  "geometry": {"coordinates":[-96.843836,32.759341],"type":"Point"}
}