{
  "type": "Feature",
  "properties": {
    "iso:country":"US",
    "sg:address":"9610 Long Point Rd",
    "sg:city":"Houston",
    "sg:classifiers":[
        {
            "category":"Professional",
            "subcategory":"Business Services",
            "type":"Services"
        }
    ],
    "sg:phone":"+1 713 973 8865",
    "sg:postcode":"77055",
    "sg:province":"TX",
    "sg:tags":[
        "international",
        "air",
        "freight",
        "ocean"
    ],
    "wof:name":"Impex Transport Inc",
    "wof:placetype":"venue"
},
  "geometry": {"coordinates":[-95.529054,29.796395],"type":"Point"}
}