{
  "type": "Feature",
  "properties": {
    "iso:country":"US",
    "sg:address":"13140 Coit Rd",
    "sg:city":"Dallas",
    "sg:classifiers":[
        {
            "category":"Wholesale",
            "subcategory":"Computers",
            "type":"Manufacturing & Wholesale Goods"
        },
        {
            "category":"Professional",
            "subcategory":"Computer Services",
            "type":"Services"
        }
    ],
    "sg:phone":"+1 972 889 8090",
    "sg:postcode":"75240",
    "sg:province":"TX",
    "sg:tags":[
        "information",
        "system",
        "software"
    ],
    "wof:name":"Ascendix Technologies Inc",
    "wof:placetype":"venue"
},
  "geometry": {"coordinates":[-96.76909999999999,32.928337],"type":"Point"}
}