{
  "type": "Feature",
  "properties": {
    "iso:country":"US",
    "sg:address":"300 Bower Rd",
    "sg:city":"Bridge City",
    "sg:classifiers":[
        {
            "category":"Education",
            "subcategory":"School",
            "type":"Public Place"
        }
    ],
    "sg:phone":"+1 409 735 1501",
    "sg:postcode":"77611",
    "sg:province":"TX",
    "wof:name":"Bridge City H S",
    "wof:placetype":"venue"
},
  "geometry": {"coordinates":[-93.82089000000001,30.039262],"type":"Point"}
}