{
  "type": "Feature",
  "properties": {
    "iso:country":"US",
    "sg:address":"600 Highway 377 N",
    "sg:city":"Argyle",
    "sg:classifiers":[
        {
            "category":"Shopping",
            "type":"Retail Goods"
        }
    ],
    "sg:phone":"+1 940 464 3700",
    "sg:postcode":"76226",
    "sg:province":"TX",
    "sg:tags":[
        "merchandise"
    ],
    "wof:name":"General Store",
    "wof:placetype":"venue"
},
  "geometry": {"coordinates":[-97.185226,33.121929],"type":"Point"}
}