{
  "type": "Feature",
  "properties": {
    "iso:country":"US",
    "sg:address":"5486 S Staples St",
    "sg:city":"Corpus Christi",
    "sg:classifiers":[
        {
            "category":"Shopping",
            "subcategory":"Clothing, Apparel, & Fashions",
            "type":"Retail Goods"
        }
    ],
    "sg:phone":"+1 361 985 0248",
    "sg:postcode":"78411",
    "sg:province":"TX",
    "wof:name":"Wet Seal",
    "wof:placetype":"venue"
},
  "geometry": {"coordinates":[-97.37298199999999,27.702748],"type":"Point"}
}