{
  "type": "Feature",
  "properties": {
    "iso:country":"US",
    "sg:address":"107 Eagle Ct",
    "sg:city":"Bastrop",
    "sg:classifiers":[
        {
            "category":"Home & Garden",
            "subcategory":"Home Furnishings",
            "type":"Retail Goods"
        },
        {
            "category":"Parking",
            "subcategory":"Garage",
            "type":"Transportation"
        },
        {
            "category":"Building & Trades",
            "subcategory":"Construction",
            "type":"Services"
        },
        {
            "category":"Building & Trades",
            "subcategory":"Locksmith",
            "type":"Services"
        },
        {
            "category":"Structure",
            "subcategory":"Building",
            "type":"Public Place"
        },
        {
            "category":"Building & Trades",
            "subcategory":"Cleaning & Sanitation",
            "type":"Services"
        }
    ],
    "sg:phone":"+1 866 786 5549",
    "sg:postcode":"78602",
    "sg:province":"TX",
    "sg:tags":[
        "sunroom",
        "repair",
        "industrial",
        "carport",
        "deck",
        "demolition",
        "bathroom",
        "management",
        "windows-repair",
        "solarium",
        "damage",
        "contractor",
        "treatment",
        "maintenance",
        "remodeling",
        "contractors-commercial",
        "door",
        "storm",
        "shelter",
        "handyman",
        "specialty",
        "carpenter",
        "water",
        "restoration",
        "installation",
        "altering",
        "builder",
        "fence-sales",
        "replacement"
    ],
    "wof:name":"The Handy Husband",
    "wof:placetype":"venue"
},
  "geometry": {"coordinates":[-97.26507700000001,30.046602],"type":"Point"}
}