{
  "type": "Feature",
  "properties": {
    "iso:country":"US",
    "sg:address":"14526 Brook Hollow Blvd",
    "sg:city":"San Antonio",
    "sg:classifiers":[
        {
            "category":"Education",
            "subcategory":"Special Training",
            "type":"Public Place"
        }
    ],
    "sg:phone":"+1 210 490 9686",
    "sg:postcode":"78232",
    "sg:province":"TX",
    "sg:tags":[
        "instruction",
        "driving"
    ],
    "wof:name":"Rhodes Driving Schools Inc",
    "wof:placetype":"venue"
},
  "geometry": {"coordinates":[-98.47579500000001,29.579898],"type":"Point"}
}