{
  "type": "Feature",
  "properties": {
    "iso:country":"US",
    "sg:address":"203 Pin Oak Dr",
    "sg:city":"Harker Heights",
    "sg:classifiers":[
        {
            "category":"Real Estate",
            "subcategory":"Real Estate Operator",
            "type":"Services"
        }
    ],
    "sg:phone":"+1 254 699 4290",
    "sg:postcode":"76548",
    "sg:province":"TX",
    "sg:tags":[
        "building",
        "nonresidential"
    ],
    "wof:name":"K B Investments",
    "wof:placetype":"venue"
},
  "geometry": {"coordinates":[-97.67978599999999,31.076407],"type":"Point"}
}