{
  "type": "Feature",
  "properties": {
    "iso:country":"US",
    "sg:address":"2413 Loon Lake Rd",
    "sg:city":"Denton",
    "sg:classifiers":[
        {
            "category":"Shopping",
            "subcategory":"Gifts & Souvenirs",
            "type":"Retail Goods"
        }
    ],
    "sg:phone":"+1 940 387 5278",
    "sg:postcode":"76210",
    "sg:province":"TX",
    "wof:name":"Big State Gifts",
    "wof:placetype":"venue"
},
  "geometry": {"coordinates":[-97.105191,33.174497],"type":"Point"}
}