{
  "type": "Feature",
  "properties": {
    "iso:country":"US",
    "sg:address":"1610 George St",
    "sg:city":"Georgetown",
    "sg:classifiers":[
        {
            "category":"Shopping",
            "subcategory":"Hobbies, Toys, & Games",
            "type":"Retail Goods"
        }
    ],
    "sg:phone":"+1 512 869 7014",
    "sg:postcode":"78626",
    "sg:province":"TX",
    "wof:name":"Goulash",
    "wof:placetype":"venue"
},
  "geometry": {"coordinates":[-97.67599800000001,30.630107],"type":"Point"}
}