{
  "type": "Feature",
  "properties": {
    "iso:country":"US",
    "sg:address":"1301 W Marshall Ave",
    "sg:city":"Longview",
    "sg:classifiers":[
        {
            "category":"Retail",
            "subcategory":"Auto Repair",
            "type":"Services"
        }
    ],
    "sg:phone":"+1 903 234 9966",
    "sg:postcode":"75604",
    "sg:province":"TX",
    "sg:tags":[
        "body",
        "automobile",
        "painting",
        "repairing"
    ],
    "wof:name":"Collision Paint & Repair",
    "wof:placetype":"venue"
},
  "geometry": {"coordinates":[-94.766998,32.504257],"type":"Point"}
}