{
  "type": "Feature",
  "properties": {
    "iso:country":"US",
    "sg:address":"623 Canterbury St",
    "sg:city":"Euless",
    "sg:classifiers":[
        {
            "category":"Professional",
            "subcategory":"Business Services",
            "type":"Services"
        }
    ],
    "sg:phone":"+1 817 283 4786",
    "sg:postcode":"76039",
    "sg:province":"TX",
    "wof:name":"Almira Group LLC",
    "wof:placetype":"venue"
},
  "geometry": {"coordinates":[-97.092433,32.876827],"type":"Point"}
}