{
  "type": "Feature",
  "properties": {
    "iso:country":"US",
    "sg:address":"424 Dreamland Dr",
    "sg:city":"New Braunfels",
    "sg:classifiers":[
        {
            "category":"Professional",
            "type":"Services"
        }
    ],
    "sg:phone":"+1 830 899 7532",
    "sg:postcode":"78133",
    "sg:province":"TX",
    "wof:name":"Granting 3 Wishes",
    "wof:placetype":"venue"
},
  "geometry": {"coordinates":[-98.30000200000001,29.875344],"type":"Point"}
}