{
  "type": "Feature",
  "properties": {
    "iso:country":"US",
    "sg:address":"6307 Steeple Chasse Dr",
    "sg:city":"Orange",
    "sg:classifiers":[
        {
            "category":"Professional",
            "subcategory":"Lawyer & Legal Services",
            "type":"Services"
        }
    ],
    "sg:phone":"+1 409 882 9670",
    "sg:postcode":"77632",
    "sg:province":"TX",
    "sg:tags":[
        "attorney",
        "practice"
    ],
    "wof:name":"Orange Law Firm",
    "wof:placetype":"venue"
},
  "geometry": {"coordinates":[-93.76367399999999,30.157971],"type":"Point"}
}