{
  "type": "Feature",
  "properties": {
    "iso:country":"US",
    "sg:address":"2209 Hancock Dr",
    "sg:city":"Austin",
    "sg:classifiers":[
        {
            "category":"Real Estate",
            "subcategory":"Real Estate Operator",
            "type":"Services"
        }
    ],
    "sg:phone":"+1 512 454 2787",
    "sg:postcode":"78756",
    "sg:province":"TX",
    "sg:tags":[
        "apartment"
    ],
    "wof:name":"Ventana",
    "wof:placetype":"venue"
},
  "geometry": {"coordinates":[-97.740835,30.322834],"type":"Point"}
}