{
  "type": "Feature",
  "properties": {
    "iso:country":"US",
    "sg:address":"1616 Logan Ave",
    "sg:city":"Laredo",
    "sg:classifiers":[
        {
            "category":"Health Services",
            "subcategory":"Doctor",
            "type":"Services"
        }
    ],
    "sg:phone":"+1 956 722 5162",
    "sg:postcode":"78040",
    "sg:province":"TX",
    "sg:tags":[
        "physician",
        "surgeon",
        "medical"
    ],
    "wof:name":"Pediatrics Associates",
    "wof:placetype":"venue"
},
  "geometry": {"coordinates":[-99.488713,27.510989],"type":"Point"}
}