{
  "type": "Feature",
  "properties": {
    "iso:country":"US",
    "sg:address":"13807 Cedar St",
    "sg:city":"Santa Fe",
    "sg:classifiers":[
        {
            "category":"Shopping",
            "subcategory":"Hobbies, Toys, & Games",
            "type":"Retail Goods"
        }
    ],
    "sg:phone":"+1 409 927 8635",
    "sg:postcode":"77517",
    "sg:province":"TX",
    "wof:name":"Playtime Ceramics",
    "wof:placetype":"venue"
},
  "geometry": {"coordinates":[-95.11741000000001,29.369943],"type":"Point"}
}