{
  "type": "Feature",
  "properties": {
    "iso:country":"US",
    "sg:address":"309 W 7th St",
    "sg:city":"Fort Worth",
    "sg:classifiers":[
        {
            "category":"Professional",
            "subcategory":"Engineering",
            "type":"Services"
        }
    ],
    "sg:phone":"+1 817 877 3718",
    "sg:postcode":"76102",
    "sg:province":"TX",
    "sg:tags":[
        "field"
    ],
    "wof:name":"B J Services",
    "wof:placetype":"venue"
},
  "geometry": {"coordinates":[-97.332177,32.751492],"type":"Point"}
}