{
  "type": "Feature",
  "properties": {
    "iso:country":"US",
    "sg:address":"406 Texas St",
    "sg:city":"Calvert",
    "sg:classifiers":[
        {
            "category":"Travel",
            "subcategory":"Hotels & Motels",
            "type":"Entertainment"
        }
    ],
    "sg:phone":"+1 979 364 2868",
    "sg:postcode":"77837",
    "sg:province":"TX",
    "sg:tags":[
        "breakfast",
        "accommodation",
        "bed"
    ],
    "sg:website":"www.calvertinn.com",
    "wof:name":"Calvert Inn Gourmet B & B",
    "wof:placetype":"venue"
},
  "geometry": {"coordinates":[-96.67518699999999,30.974833],"type":"Point"}
}