{
  "type": "Feature",
  "properties": {
    "iso:country":"US",
    "sg:address":"4505 Ramsgate Ct",
    "sg:city":"Arlington",
    "sg:classifiers":[
        {
            "category":"Building & Trades",
            "subcategory":"Construction",
            "type":"Services"
        }
    ],
    "sg:phone":"+1 817 429 6655",
    "sg:postcode":"76013",
    "sg:province":"TX",
    "sg:tags":[
        "contractor"
    ],
    "wof:name":"Gonzales Alexander",
    "wof:placetype":"venue"
},
  "geometry": {"coordinates":[-97.179367,32.708313],"type":"Point"}
}