{
  "type": "Feature",
  "properties": {
    "iso:country":"US",
    "sg:address":"203 Garrett St",
    "sg:city":"Borger",
    "sg:classifiers":[
        {
            "category":"Shopping",
            "subcategory":"Clothing, Apparel, & Fashions",
            "type":"Retail Goods"
        }
    ],
    "sg:phone":"+1 806 273 7432",
    "sg:postcode":"79007",
    "sg:province":"TX",
    "sg:tags":[
        "t"
    ],
    "wof:name":"J H Collectibles",
    "wof:placetype":"venue"
},
  "geometry": {"coordinates":[-101.377267,35.652492],"type":"Point"}
}