{
  "type": "Feature",
  "properties": {
    "iso:country":"US",
    "sg:address":"3741 Shelby Rd",
    "sg:city":"Fort Worth",
    "sg:classifiers":[
        {
            "category":"Building & Trades",
            "subcategory":"Construction",
            "type":"Services"
        }
    ],
    "sg:phone":"+1 817 300 8430",
    "sg:postcode":"76140",
    "sg:province":"TX",
    "sg:tags":[
        "carpentry",
        "contractor"
    ],
    "wof:name":"Door Tech",
    "wof:placetype":"venue"
},
  "geometry": {"coordinates":[-97.26173199999999,32.623817],"type":"Point"}
}