{
  "type": "Feature",
  "properties": {
    "iso:country":"US",
    "sg:address":"147 Meadow Glade Dr",
    "sg:city":"San Antonio",
    "sg:classifiers":[
        {
            "category":"Professional",
            "subcategory":"Management & Consulting",
            "type":"Services"
        }
    ],
    "sg:phone":"+1 210 673 1606",
    "sg:postcode":"78227",
    "sg:province":"TX",
    "sg:tags":[
        "business"
    ],
    "wof:name":"Carr Company",
    "wof:placetype":"venue"
},
  "geometry": {"coordinates":[-98.641959,29.425764],"type":"Point"}
}