{
  "type": "Feature",
  "properties": {
    "iso:country":"US",
    "sg:address":"7620 Ferguson Rd",
    "sg:city":"Dallas",
    "sg:classifiers":[
        {
            "category":"Education",
            "subcategory":"School",
            "type":"Public Place"
        }
    ],
    "sg:phone":"+1 214 328 2114",
    "sg:postcode":"75228",
    "sg:province":"TX",
    "wof:name":"Christian Stronghold Academy",
    "wof:placetype":"venue"
},
  "geometry": {"coordinates":[-96.716318,32.799835],"type":"Point"}
}