{
  "type": "Feature",
  "properties": {
    "iso:country":"US",
    "sg:address":"1917 Broadway St Suite 3",
    "sg:city":"Galveston",
    "sg:classifiers":[
        {
            "category":"Health Services",
            "subcategory":"Doctor",
            "type":"Services"
        }
    ],
    "sg:phone":"+1 409 762 0177",
    "sg:postcode":"77550",
    "sg:province":"TX",
    "sg:tags":[
        "physician",
        "family",
        "practice",
        "surgeons",
        "medicine",
        "surgeon"
    ],
    "wof:name":"Diana Villarreal Md Pa",
    "wof:placetype":"venue"
},
  "geometry": {"coordinates":[-94.787525,29.301141],"type":"Point"}
}