{
  "type": "Feature",
  "properties": {
    "iso:country":"US",
    "sg:address":"2802 Lavon Dr",
    "sg:city":"Garland",
    "sg:classifiers":[
        {
            "category":"Ice Cream",
            "type":"Food & Drink"
        }
    ],
    "sg:phone":"+1 972 495 2221",
    "sg:postcode":"75040",
    "sg:province":"TX",
    "sg:tags":[
        "frozen",
        "yogurt"
    ],
    "wof:name":"Braum's Ice Cream & Dairy Stores",
    "wof:placetype":"venue"
},
  "geometry": {"coordinates":[-96.622299,32.940899],"type":"Point"}
}