{
  "type": "Feature",
  "properties": {
    "iso:country":"US",
    "sg:address":"5816 Hwy 78",
    "sg:city":"Sachse",
    "sg:classifiers":[
        {
            "category":"Retail",
            "subcategory":"Auto Repair",
            "type":"Services"
        }
    ],
    "sg:phone":"+1 972 414 9009",
    "sg:postcode":"75048",
    "sg:province":"TX",
    "wof:name":"Xpress Auto Care",
    "wof:placetype":"venue"
},
  "geometry": {"coordinates":[-96.595939,32.975402],"type":"Point"}
}