{
  "type": "Feature",
  "properties": {
    "iso:country":"US",
    "sg:address":"2809 Austin Ave",
    "sg:city":"Orange",
    "sg:classifiers":[
        {
            "category":"Professional",
            "subcategory":"Business Services",
            "type":"Services"
        }
    ],
    "sg:phone":"+1 409 882 9081",
    "sg:postcode":"77630",
    "sg:province":"TX",
    "wof:name":"Cagle Enterprises",
    "wof:placetype":"venue"
},
  "geometry": {"coordinates":[-93.76257200000001,30.08453],"type":"Point"}
}