{
  "type": "Feature",
  "properties": {
    "iso:country":"US",
    "sg:address":"301 Central Dr",
    "sg:city":"Cedar Park",
    "sg:classifiers":[
        {
            "category":"Freight",
            "type":"Transportation"
        }
    ],
    "sg:phone":"+1 512 259 0588",
    "sg:postcode":"78613",
    "sg:province":"TX",
    "sg:tags":[
        "operator",
        "local",
        "trucking"
    ],
    "wof:name":"Getting R Dun Delivery Service",
    "wof:placetype":"venue"
},
  "geometry": {"coordinates":[-97.834703,30.524207],"type":"Point"}
}