{
  "type": "Feature",
  "properties": {
    "iso:country":"US",
    "sg:address":"10 Wishbonebush Rd",
    "sg:city":"Spring",
    "sg:classifiers":[
        {
            "category":"Food & Beverages",
            "subcategory":"Groceries & Convenience Stores",
            "type":"Retail Goods"
        }
    ],
    "sg:phone":"+1 281 292 0458",
    "sg:postcode":"77380",
    "sg:province":"TX",
    "wof:name":"Market Place",
    "wof:placetype":"venue"
},
  "geometry": {"coordinates":[-95.4562,30.143829],"type":"Point"}
}