{
  "type": "Feature",
  "properties": {
    "iso:country":"US",
    "sg:address":"1102 Howard Dr",
    "sg:city":"Deer Park",
    "sg:classifiers":[
        {
            "category":"Manufacturing",
            "subcategory":"Metals",
            "type":"Manufacturing & Wholesale Goods"
        }
    ],
    "sg:phone":"+1 281 930 0303",
    "sg:postcode":"77536",
    "sg:province":"TX",
    "sg:tags":[
        "engineering",
        "valve",
        "product",
        "mfg"
    ],
    "wof:name":"Yarway-Keystone",
    "wof:placetype":"venue"
},
  "geometry": {"coordinates":[-95.132772,29.707884],"type":"Point"}
}