{
  "type": "Feature",
  "properties": {
    "iso:country":"US",
    "sg:address":"405 S Fry Rd",
    "sg:city":"Katy",
    "sg:classifiers":[
        {
            "category":"Restaurant",
            "type":"Food & Drink"
        }
    ],
    "sg:menulink":"http://www.allmenus.com/tx/houston/48662-boston-market/menu/",
    "sg:phone":"+1 281 398 8421",
    "sg:postcode":"77450",
    "sg:province":"TX",
    "sg:tags":[
        "barbecue",
        "american",
        "soup"
    ],
    "wof:name":"Boston Market",
    "wof:placetype":"venue"
},
  "geometry": {"coordinates":[-95.718906,29.780985],"type":"Point"}
}