{
  "type": "Feature",
  "properties": {
    "iso:country":"US",
    "sg:address":"11712 N Lamar Blvd",
    "sg:city":"Austin",
    "sg:classifiers":[
        {
            "category":"Professional",
            "subcategory":"Computer Services",
            "type":"Services"
        }
    ],
    "sg:phone":"+1 512 833 0776",
    "sg:postcode":"78753",
    "sg:province":"TX",
    "sg:tags":[
        "website",
        "design"
    ],
    "wof:name":"CSS Media",
    "wof:placetype":"venue"
},
  "geometry": {"coordinates":[-97.683402,30.388298],"type":"Point"}
}