{
  "type": "Feature",
  "properties": {
    "iso:country":"US",
    "sg:address":"607 S Friendswood Dr",
    "sg:city":"Friendswood",
    "sg:classifiers":[
        {
            "category":"Social Services",
            "subcategory":"Child Care",
            "type":"Services"
        }
    ],
    "sg:phone":"+1 281 482 7117",
    "sg:postcode":"77546",
    "sg:province":"TX",
    "sg:tags":[
        "day"
    ],
    "wof:name":"Country Meadows Montessori",
    "wof:placetype":"venue"
},
  "geometry": {"coordinates":[-95.19919299999999,29.528],"type":"Point"}
}