{
  "type": "Feature",
  "properties": {
    "iso:country":"US",
    "sg:address":"4715 Nashwood Ln",
    "sg:city":"Dallas",
    "sg:classifiers":[
        {
            "category":"Professional",
            "subcategory":"Business Services",
            "type":"Services"
        }
    ],
    "sg:phone":"+1 972 980 0063",
    "sg:postcode":"75244",
    "sg:province":"TX",
    "wof:name":"Allardyce Interiors",
    "wof:placetype":"venue"
},
  "geometry": {"coordinates":[-96.82890399999999,32.91213],"type":"Point"}
}