{
  "type": "Feature",
  "properties": {
    "iso:country":"US",
    "sg:address":"6301 E US Hwy 80",
    "sg:city":"Abilene",
    "sg:classifiers":[
        {
            "category":"Building & Trades",
            "subcategory":"Construction",
            "type":"Services"
        }
    ],
    "sg:phone":"+1 325 676 0001",
    "sg:postcode":"79601",
    "sg:province":"TX",
    "sg:tags":[
        "product",
        "asphalt"
    ],
    "wof:name":"Vulcan Construction Material",
    "wof:placetype":"venue"
},
  "geometry": {"coordinates":[-99.617929,32.434073],"type":"Point"}
}