{
  "type": "Feature",
  "properties": {
    "iso:country":"US",
    "sg:address":"44 Creekmont Ln",
    "sg:city":"Longview",
    "sg:classifiers":[
        {
            "category":"Manufacturing",
            "subcategory":"Tools & Machinery",
            "type":"Manufacturing & Wholesale Goods"
        }
    ],
    "sg:phone":"+1 903 234 2847",
    "sg:postcode":"75605",
    "sg:province":"TX",
    "sg:tags":[
        "computer",
        "electronic",
        "mfg"
    ],
    "wof:name":"Audio World",
    "wof:placetype":"venue"
},
  "geometry": {"coordinates":[-94.745853,32.529528],"type":"Point"}
}