{
  "type": "Feature",
  "properties": {
    "iso:country":"US",
    "sg:address":"3725 Ira E Woods Ave",
    "sg:city":"Grapevine",
    "sg:classifiers":[
        {
            "category":"Home & Garden",
            "subcategory":"Garden Supply",
            "type":"Retail Goods"
        }
    ],
    "sg:phone":"+1 817 481 3654",
    "sg:postcode":"76051",
    "sg:province":"TX",
    "sg:tags":[
        "tie",
        "railroad"
    ],
    "wof:name":"D Wayne Bailey",
    "wof:placetype":"venue"
},
  "geometry": {"coordinates":[-97.12698399999999,32.914447],"type":"Point"}
}