{
  "type": "Feature",
  "properties": {
    "iso:country":"US",
    "sg:address":"3505 Bratton Ridge Xing",
    "sg:city":"Austin",
    "sg:classifiers":[
        {
            "category":"Professional",
            "subcategory":"Research",
            "type":"Services"
        }
    ],
    "sg:phone":"+1 512 388 3113",
    "sg:postcode":"78728",
    "sg:province":"TX",
    "sg:tags":[
        "environmental",
        "ecological"
    ],
    "wof:name":"Lonestar State Environ Svc LP",
    "wof:placetype":"venue"
},
  "geometry": {"coordinates":[-97.682317,30.461857],"type":"Point"}
}