{
  "type": "Feature",
  "properties": {
    "iso:country":"US",
    "sg:address":"115 E 2nd St",
    "sg:city":"Dumas",
    "sg:classifiers":[
        {
            "category":"Restaurant",
            "type":"Food & Drink"
        }
    ],
    "sg:phone":"+1 806 934 4620",
    "sg:postcode":"79029",
    "sg:province":"TX",
    "wof:name":"La Casita 2",
    "wof:placetype":"venue"
},
  "geometry": {"coordinates":[-101.973022,35.864268],"type":"Point"}
}