{
  "type": "Feature",
  "properties": {
    "iso:country":"US",
    "sg:address":"2916 Alton Rd",
    "sg:city":"Fort Worth",
    "sg:classifiers":[
        {
            "category":"Professional",
            "subcategory":"Lawyer & Legal Services",
            "type":"Services"
        }
    ],
    "sg:phone":"+1 817 923 1600",
    "sg:postcode":"76109",
    "sg:province":"TX",
    "sg:tags":[
        "attorney"
    ],
    "wof:name":"Winfred Hooper",
    "wof:placetype":"venue"
},
  "geometry": {"coordinates":[-97.371405,32.709597],"type":"Point"}
}