{
  "type": "Feature",
  "properties": {
    "iso:country":"US",
    "sg:address":"1610 Main St",
    "sg:city":"Junction",
    "sg:classifiers":[
        {
            "category":"Shopping",
            "subcategory":"Pharmacy",
            "type":"Retail Goods"
        }
    ],
    "sg:phone":"+1 325 446 2511",
    "sg:postcode":"76849",
    "sg:province":"TX",
    "wof:name":"City Pharmacy",
    "wof:placetype":"venue"
},
  "geometry": {"coordinates":[-99.777941,30.491976],"type":"Point"}
}