{
  "type": "Feature",
  "properties": {
    "iso:country":"US",
    "sg:address":"11285 Southwest Fwy Ste 120",
    "sg:city":"Houston",
    "sg:classifiers":[
        {
            "category":"Donuts",
            "subcategory":"None",
            "type":"Food & Drink"
        }
    ],
    "sg:phone":"+1 281 575 1766",
    "sg:postcode":"77031",
    "sg:province":"TX",
    "wof:name":"Shipley Donut Shop",
    "wof:placetype":"venue"
},
  "geometry": {"coordinates":[-95.563202,29.6556],"type":"Point"}
}