{
  "type": "Feature",
  "properties": {
    "iso:country":"US",
    "sg:address":"1910 E Riverside Dr",
    "sg:city":"Austin",
    "sg:classifiers":[
        {
            "category":"Personal",
            "subcategory":"Beauty Salon",
            "type":"Services"
        }
    ],
    "sg:phone":"+1 512 447 4545",
    "sg:postcode":"78741",
    "sg:province":"TX",
    "sg:tags":[
        "shop"
    ],
    "wof:name":"Hair Station",
    "wof:placetype":"venue"
},
  "geometry": {"coordinates":[-97.72887,30.243038],"type":"Point"}
}