{
  "type": "Feature",
  "properties": {
    "iso:country":"US",
    "sg:address":"3301 E Stan Schlueter Loop",
    "sg:city":"Killeen",
    "sg:classifiers":[
        {
            "category":"Real Estate",
            "subcategory":"Real Estate Services",
            "type":"Services"
        }
    ],
    "sg:phone":"+1 254 634 2227",
    "sg:postcode":"76542",
    "sg:province":"TX",
    "sg:tags":[
        "company",
        "search",
        "abstract",
        "title"
    ],
    "wof:name":"Land Exchange Abstract & Title",
    "wof:placetype":"venue"
},
  "geometry": {"coordinates":[-97.71793700000001,31.067607],"type":"Point"}
}