{
  "type": "Feature",
  "properties": {
    "iso:country":"US",
    "sg:address":"3801 Immel Dr",
    "sg:city":"Flower Mound",
    "sg:classifiers":[
        {
            "category":"Professional",
            "subcategory":"Business Services",
            "type":"Services"
        }
    ],
    "sg:phone":"+1 817 464 1500",
    "sg:postcode":"75022",
    "sg:province":"TX",
    "wof:name":"Insite Enterprises LLC",
    "wof:placetype":"venue"
},
  "geometry": {"coordinates":[-97.148398,33.040566],"type":"Point"}
}