{
  "type": "Feature",
  "properties": {
    "iso:country":"US",
    "sg:address":"4255 Carbon Rd",
    "sg:city":"Irving",
    "sg:classifiers":[
        {
            "category":"Retail",
            "subcategory":"Auto Rental",
            "type":"Services"
        },
        {
            "category":"Professional",
            "subcategory":"Business Services",
            "type":"Services"
        },
        {
            "category":"Retail",
            "subcategory":"Storage",
            "type":"Services"
        }
    ],
    "sg:postcode":"75038",
    "sg:province":"TX",
    "sg:tags":[
        "renting",
        "leasing",
        "portable",
        "mobile",
        "commercial",
        "unit",
        "trailer"
    ],
    "sg:website":"http://N",
    "wof:name":"Modspace",
    "wof:placetype":"venue"
},
  "geometry": {"coordinates":[-97.001931,32.877904],"type":"Point"}
}