{
  "type": "Feature",
  "properties": {
    "iso:country":"US",
    "sg:address":"6354 Hart St",
    "sg:city":"Fort Worth",
    "sg:classifiers":[
        {
            "category":"Building & Trades",
            "subcategory":"Plumbing",
            "type":"Services"
        }
    ],
    "sg:phone":"+1 817 429 6734",
    "sg:postcode":"76112",
    "sg:province":"TX",
    "sg:tags":[
        "refrigeration",
        "contractor"
    ],
    "wof:name":"Lone Star Mechanical",
    "wof:placetype":"venue"
},
  "geometry": {"coordinates":[-97.22145399999999,32.731983],"type":"Point"}
}