{
  "type": "Feature",
  "properties": {
    "iso:country":"US",
    "sg:address":"315 Lindale St",
    "sg:city":"Houston",
    "sg:classifiers":[
        {
            "category":"Freight",
            "type":"Transportation"
        }
    ],
    "sg:phone":"+1 713 697 3399",
    "sg:postcode":"77022",
    "sg:province":"TX",
    "sg:tags":[
        "haulage",
        "truck",
        "dump"
    ],
    "wof:name":"Adrian L Lizalde Trucking",
    "wof:placetype":"venue"
},
  "geometry": {"coordinates":[-95.36818100000001,29.818031],"type":"Point"}
}