{
  "type": "Feature",
  "properties": {
    "iso:country":"US",
    "sg:address":"300 St Andrews Pl",
    "sg:city":"Belton",
    "sg:classifiers":[
        {
            "category":"Cinema",
            "subcategory":"Movie Rental",
            "type":"Entertainment"
        }
    ],
    "sg:phone":"+1 254 780 2314",
    "sg:postcode":"76513",
    "sg:province":"TX",
    "sg:tags":[
        "motion",
        "video",
        "production",
        "tape"
    ],
    "wof:name":"Lakwood Video Services",
    "wof:placetype":"venue"
},
  "geometry": {"coordinates":[-97.45696700000001,31.127886],"type":"Point"}
}