{
  "type": "Feature",
  "properties": {
    "iso:country":"US",
    "sg:address":"521 Sims Ave",
    "sg:city":"San Antonio",
    "sg:classifiers":[
        {
            "category":"Professional",
            "subcategory":"Business Services",
            "type":"Services"
        },
        {
            "category":"Manufacturing",
            "subcategory":"Apparel",
            "type":"Manufacturing & Wholesale Goods"
        }
    ],
    "sg:phone":"+1 210 534 5135",
    "sg:postcode":"78225",
    "sg:province":"TX",
    "sg:tags":[
        "embroidery"
    ],
    "wof:name":"Busy Dee's Embroidery",
    "wof:placetype":"venue"
},
  "geometry": {"coordinates":[-98.517613,29.383757],"type":"Point"}
}