{
  "type": "Feature",
  "properties": {
    "iso:country":"US",
    "sg:address":"7108 Bandera Rd",
    "sg:city":"San Antonio",
    "sg:classifiers":[
        {
            "category":"Banks & Credit Unions",
            "subcategory":"Bank",
            "type":"Services"
        }
    ],
    "sg:phone":"+1 210 637 8800",
    "sg:postcode":"78238",
    "sg:province":"TX",
    "sg:tags":[
        "national"
    ],
    "wof:name":"Bank Of America",
    "wof:placetype":"venue"
},
  "geometry": {"coordinates":[-98.626554,29.503466],"type":"Point"}
}