{
  "type": "Feature",
  "properties": {
    "iso:country":"US",
    "sg:address":"13450 Mill Grove Ln",
    "sg:city":"Dallas",
    "sg:phone":"+1 972 386 2951",
    "sg:postcode":"75240",
    "sg:province":"TX",
    "sg:tags":[
        "farm",
        "soybean"
    ],
    "wof:name":"H A McLean Farms Inc",
    "wof:placetype":"venue"
},
  "geometry": {"coordinates":[-96.777553,32.931719],"type":"Point"}
}