{
  "type": "Feature",
  "properties": {
    "iso:country":"US",
    "sg:address":"1103 Frances Dr",
    "sg:city":"Rosenberg",
    "sg:classifiers":[
        {
            "category":"Manufacturing",
            "subcategory":"Wood Products",
            "type":"Manufacturing & Wholesale Goods"
        }
    ],
    "sg:phone":"+1 281 342 6107",
    "sg:postcode":"77471",
    "sg:province":"TX",
    "sg:tags":[
        "mfg"
    ],
    "wof:name":"Tex DJS Mow",
    "wof:placetype":"venue"
},
  "geometry": {"coordinates":[-95.77167300000001,29.568194],"type":"Point"}
}