{
  "type": "Feature",
  "properties": {
    "iso:country":"US",
    "sg:address":"5703 Addicks Satsuma Rd",
    "sg:city":"Houston",
    "sg:classifiers":[
        {
            "category":"Real Estate",
            "subcategory":"Surveying",
            "type":"Services"
        }
    ],
    "sg:phone":"+1 281 463 2710",
    "sg:postcode":"77084",
    "sg:province":"TX",
    "sg:tags":[
        "surveyor"
    ],
    "wof:name":"KATY Geophysical Svc",
    "wof:placetype":"venue"
},
  "geometry": {"coordinates":[-95.64519,29.860246],"type":"Point"}
}