{
  "type": "Feature",
  "properties": {
    "iso:country":"US",
    "sg:address":"4715 Creighton Dr",
    "sg:city":"Dallas",
    "sg:classifiers":[
        {
            "category":"Restaurant",
            "type":"Food & Drink"
        }
    ],
    "sg:phone":"+1 214 739 3854",
    "sg:postcode":"75214",
    "sg:province":"TX",
    "sg:tags":[
        "eating"
    ],
    "wof:name":"Prego Pizza Express",
    "wof:placetype":"venue"
},
  "geometry": {"coordinates":[-96.760724,32.84462],"type":"Point"}
}