{
  "type": "Feature",
  "properties": {
    "iso:country":"US",
    "sg:address":"110 Jolly Cir",
    "sg:city":"Mabank",
    "sg:classifiers":[
        {
            "category":"Building & Trades",
            "subcategory":"Plumbing",
            "type":"Services"
        }
    ],
    "sg:phone":"+1 903 887 0909",
    "sg:postcode":"75156",
    "sg:province":"TX",
    "sg:tags":[
        "contractor"
    ],
    "wof:name":"Zoco Inc",
    "wof:placetype":"venue"
},
  "geometry": {"coordinates":[-96.13585399999999,32.323675],"type":"Point"}
}