{
  "type": "Feature",
  "properties": {
    "iso:country":"US",
    "sg:address":"320 N Polk St",
    "sg:city":"Jefferson",
    "sg:classifiers":[
        {
            "category":"Shopping",
            "subcategory":"Gifts & Souvenirs",
            "type":"Retail Goods"
        }
    ],
    "sg:phone":"+1 903 665 8989",
    "sg:postcode":"75657",
    "sg:province":"TX",
    "sg:tags":[
        "shop"
    ],
    "wof:name":"Donnie's Giftworld",
    "wof:placetype":"venue"
},
  "geometry": {"coordinates":[-94.34644299999999,32.759023],"type":"Point"}
}