{
  "type": "Feature",
  "properties": {
    "iso:country":"US",
    "sg:address":"1003 US Hwy 77",
    "sg:city":"Waxahachie",
    "sg:classifiers":[
        {
            "category":"Restaurant",
            "type":"Food & Drink"
        }
    ],
    "sg:phone":"+1 972 937 3030",
    "sg:postcode":"75165",
    "sg:province":"TX",
    "sg:tags":[
        "barbecue",
        "eating"
    ],
    "wof:name":"Dickey's Barbeque",
    "wof:placetype":"venue"
},
  "geometry": {"coordinates":[-96.84460900000001,32.397757],"type":"Point"}
}