{
  "type": "Feature",
  "properties": {
    "iso:country":"US",
    "sg:address":"3319 N Twin City Hwy",
    "sg:city":"Nederland",
    "sg:phone":"+1 409 729 0314",
    "sg:postcode":"77627",
    "sg:province":"TX",
    "wof:name":"Bayou Customs Collision",
    "wof:placetype":"venue"
},
  "geometry": {"coordinates":[-94.013628,29.994992],"type":"Point"}
}