{
  "type": "Feature",
  "properties": {
    "iso:country":"US",
    "sg:address":"10811 Richmond Ave",
    "sg:city":"Houston",
    "sg:classifiers":[
        {
            "category":"Education",
            "subcategory":"Dance Studio",
            "type":"Public Place"
        }
    ],
    "sg:phone":"+1 281 513 3175",
    "sg:postcode":"77042",
    "sg:province":"TX",
    "sg:website":"www.stripteasehouston.com",
    "wof:name":"Striptease Houston",
    "wof:placetype":"venue"
},
  "geometry": {"coordinates":[-95.567482,29.727441],"type":"Point"}
}