{
  "type": "Feature",
  "properties": {
    "iso:country":"US",
    "sg:address":"16775 Addison Rd Ste 325",
    "sg:city":"Addison",
    "sg:classifiers":[
        {
            "category":"Shopping",
            "subcategory":"Stationery & Office Supplies",
            "type":"Retail Goods"
        }
    ],
    "sg:phone":"+1 214 271 4871",
    "sg:postcode":"75001",
    "sg:province":"TX",
    "sg:tags":[
        "equipment"
    ],
    "wof:name":"Pinnacle Office Products",
    "wof:placetype":"venue"
},
  "geometry": {"coordinates":[-96.830456,32.980651],"type":"Point"}
}