{
  "type": "Feature",
  "properties": {
    "iso:country":"US",
    "sg:address":"5078 Brush Creek Rd",
    "sg:city":"Fort Worth",
    "sg:classifiers":[
        {
            "category":"Real Estate",
            "subcategory":"Real Estate Agent",
            "type":"Services"
        }
    ],
    "sg:phone":"+1 817 457 8836",
    "sg:postcode":"76119",
    "sg:province":"TX",
    "wof:name":"Village Creek Business Park",
    "wof:placetype":"venue"
},
  "geometry": {"coordinates":[-97.246624,32.696282],"type":"Point"}
}