{
  "type": "Feature",
  "properties": {
    "iso:country":"US",
    "sg:address":"1701 E Euless Blvd",
    "sg:city":"Euless",
    "sg:classifiers":[
        {
            "category":"Organizations",
            "subcategory":"Religious Organization",
            "type":"Services"
        }
    ],
    "sg:phone":"+1 817 571 4980",
    "sg:postcode":"76040",
    "sg:province":"TX",
    "sg:tags":[
        "church"
    ],
    "wof:name":"Redeem Christian Chr-God",
    "wof:placetype":"venue"
},
  "geometry": {"coordinates":[-97.11108900000001,32.824613],"type":"Point"}
}