{
  "type": "Feature",
  "properties": {
    "iso:country":"US",
    "sg:address":"660 W Main St",
    "sg:city":"Lancaster",
    "sg:classifiers":[
        {
            "category":"Professional",
            "subcategory":"Accounting & Tax Preparation",
            "type":"Services"
        }
    ],
    "sg:phone":"+1 972 227 7450",
    "sg:postcode":"75146",
    "sg:province":"TX",
    "wof:name":"Ted F Cutchall",
    "wof:placetype":"venue"
},
  "geometry": {"coordinates":[-96.76809799999999,32.591199],"type":"Point"}
}