{
  "type": "Feature",
  "properties": {
    "iso:country":"US",
    "sg:address":"900 E Wells Ave",
    "sg:city":"Sherman",
    "sg:classifiers":[
        {
            "category":"Real Estate",
            "subcategory":"Real Estate Operator",
            "type":"Services"
        }
    ],
    "sg:phone":"+1 903 868 1108",
    "sg:postcode":"75090",
    "sg:province":"TX",
    "sg:tags":[
        "building",
        "apartment"
    ],
    "wof:name":"Eastside Gardens",
    "wof:placetype":"venue"
},
  "geometry": {"coordinates":[-96.596328,33.63312],"type":"Point"}
}