{
  "type": "Feature",
  "properties": {
    "iso:country":"US",
    "sg:address":"5343 E Riverview St",
    "sg:city":"Robstown",
    "sg:classifiers":[
        {
            "category":"Building & Trades",
            "subcategory":"Construction",
            "type":"Services"
        }
    ],
    "sg:phone":"+1 361 813 8432",
    "sg:postcode":"78380",
    "sg:province":"TX",
    "sg:tags":[
        "paving",
        "contractor"
    ],
    "wof:name":"Texas Asphalt Co",
    "wof:placetype":"venue"
},
  "geometry": {"coordinates":[-97.662576,27.858757],"type":"Point"}
}