{
  "type": "Feature",
  "properties": {
    "iso:country":"US",
    "sg:address":"10284 Briar Forest Dr",
    "sg:city":"Houston",
    "sg:classifiers":[
        {
            "category":"Real Estate",
            "subcategory":"Real Estate Agent",
            "type":"Services"
        },
        {
            "category":"Professional",
            "subcategory":"Business Services",
            "type":"Services"
        }
    ],
    "sg:phone":"+1 713 339 2851",
    "sg:postcode":"77042",
    "sg:province":"TX",
    "sg:tags":[
        "relocation"
    ],
    "wof:name":"Adaptations Inc",
    "wof:placetype":"venue"
},
  "geometry": {"coordinates":[-95.5543,29.747476],"type":"Point"}
}