{
  "type": "Feature",
  "properties": {
    "iso:country":"US",
    "sg:address":"1009 Glenda St",
    "sg:city":"Terrell",
    "sg:classifiers":[
        {
            "category":"Shopping",
            "type":"Retail Goods"
        },
        {
            "category":"Organizations",
            "subcategory":"Non-profit Organization",
            "type":"Services"
        }
    ],
    "sg:phone":"+1 972 524 6116",
    "sg:postcode":"75160",
    "sg:province":"TX",
    "sg:tags":[
        "fund",
        "games",
        "raising",
        "merchandise",
        "supply"
    ],
    "wof:name":"Wiley Club",
    "wof:placetype":"venue"
},
  "geometry": {"coordinates":[-96.286873,32.758421],"type":"Point"}
}