{
  "type": "Feature",
  "properties": {
    "iso:country":"US",
    "sg:address":"25 Highland Park Vlg Ste 100",
    "sg:city":"Dallas",
    "sg:classifiers":[
        {
            "category":"Building & Trades",
            "subcategory":"Construction",
            "type":"Services"
        }
    ],
    "sg:phone":"+1 214 522 6162",
    "sg:postcode":"75205",
    "sg:province":"TX",
    "sg:tags":[
        "interior",
        "design"
    ],
    "wof:name":"Field Beverly Interiors Asid",
    "wof:placetype":"venue"
},
  "geometry": {"coordinates":[-96.80650300000001,32.835999],"type":"Point"}
}