{
  "type": "Feature",
  "properties": {
    "iso:country":"US",
    "sg:address":"1801 W Indiana Ave",
    "sg:city":"Midland",
    "sg:classifiers":[
        {
            "category":"Farming",
            "subcategory":"Livestock Farm",
            "type":"Manufacturing & Wholesale Goods"
        }
    ],
    "sg:phone":"+1 432 687 0223",
    "sg:postcode":"79701",
    "sg:province":"TX",
    "sg:tags":[
        "ranch"
    ],
    "wof:name":"Haley Ranches",
    "wof:placetype":"venue"
},
  "geometry": {"coordinates":[-102.09394,31.992383],"type":"Point"}
}