{
  "type": "Feature",
  "properties": {
    "iso:country":"US",
    "sg:address":"1310 N Temple Dr",
    "sg:city":"Diboll",
    "sg:classifiers":[
        {
            "category":"Restaurant",
            "type":"Food & Drink"
        }
    ],
    "sg:phone":"+1 936 829 3040",
    "sg:postcode":"75941",
    "sg:province":"TX",
    "sg:tags":[
        "caterer"
    ],
    "wof:name":"Moye's Catering Svc",
    "wof:placetype":"venue"
},
  "geometry": {"coordinates":[-94.77622599999999,31.206373],"type":"Point"}
}