{
  "type": "Feature",
  "properties": {
    "iso:country":"US",
    "sg:address":"1512 E Langdon Rd",
    "sg:city":"Dallas",
    "sg:classifiers":[
        {
            "category":"Government",
            "subcategory":"Police Station",
            "type":"Public Place"
        }
    ],
    "sg:phone":"+1 972 225 6118",
    "sg:postcode":"75241",
    "sg:province":"TX",
    "sg:tags":[
        "sheriff"
    ],
    "sg:website":"www.dallascounty.org",
    "wof:name":"County Sheriff-Patrol Section",
    "wof:placetype":"venue"
},
  "geometry": {"coordinates":[-96.705259,32.669625],"type":"Point"}
}