{
  "type": "Feature",
  "properties": {
    "iso:country":"US",
    "sg:address":"230 Co Rd 447",
    "sg:city":"Thorndale",
    "sg:classifiers":[
        {
            "category":"Real Estate",
            "subcategory":"Real Estate Agent",
            "type":"Services"
        }
    ],
    "sg:phone":"+1 512 446 6114",
    "sg:postcode":"76574",
    "sg:province":"TX",
    "wof:name":"McWilliams Appraisal Service",
    "wof:placetype":"venue"
},
  "geometry": {"coordinates":[-97.373234,30.539366],"type":"Point"}
}