{
  "type": "Feature",
  "properties": {
    "iso:country":"US",
    "sg:address":"1630 Valwood Pkwy",
    "sg:city":"Carrollton",
    "sg:classifiers":[
        {
            "category":"Food & Beverages",
            "subcategory":"Bakery",
            "type":"Retail Goods"
        }
    ],
    "sg:phone":"+1 972 241 8881",
    "sg:postcode":"75006",
    "sg:province":"TX",
    "sg:tags":[
        "sandwich"
    ],
    "wof:name":"Subway Sandwiches",
    "wof:placetype":"venue"
},
  "geometry": {"coordinates":[-96.922887,32.937717],"type":"Point"}
}