{
  "type": "Feature",
  "properties": {
    "iso:country":"US",
    "sg:address":"605 S Austin St",
    "sg:city":"Brenham",
    "sg:classifiers":[
        {
            "category":"Real Estate",
            "subcategory":"Real Estate Agent",
            "type":"Services"
        }
    ],
    "sg:phone":"+1 979 836 3633",
    "sg:postcode":"77833",
    "sg:province":"TX",
    "wof:name":"Heritage Texas Country Propert",
    "wof:placetype":"venue"
},
  "geometry": {"coordinates":[-96.39909,30.163249],"type":"Point"}
}