{
  "type": "Feature",
  "properties": {
    "iso:country":"US",
    "sg:address":"4418 Franklin St",
    "sg:city":"Lancaster",
    "sg:classifiers":[
        {
            "category":"Building & Trades",
            "subcategory":"Construction",
            "type":"Services"
        }
    ],
    "sg:phone":"+1 972 228 1412",
    "sg:postcode":"75134",
    "sg:province":"TX",
    "sg:tags":[
        "house"
    ],
    "wof:name":"Umana Form Setting Foundation",
    "wof:placetype":"venue"
},
  "geometry": {"coordinates":[-96.791933,32.637334],"type":"Point"}
}