{
  "type": "Feature",
  "properties": {
    "iso:country":"US",
    "sg:address":"3220 Ipswich Dr",
    "sg:city":"Plano",
    "sg:classifiers":[
        {
            "category":"Real Estate",
            "subcategory":"Real Estate Agent",
            "type":"Services"
        }
    ],
    "sg:phone":"+1 972 208 2432",
    "sg:postcode":"75025",
    "sg:province":"TX",
    "wof:name":"Ker Property Management Inc",
    "wof:placetype":"venue"
},
  "geometry": {"coordinates":[-96.753539,33.073779],"type":"Point"}
}