{
  "type": "Feature",
  "properties": {
    "iso:country":"US",
    "sg:address":"490 Marceline Blvd",
    "sg:city":"Beaumont",
    "sg:classifiers":[
        {
            "category":"Retail",
            "subcategory":"Animal Services",
            "type":"Services"
        }
    ],
    "sg:phone":"+1 409 866 9229",
    "sg:postcode":"77707",
    "sg:province":"TX",
    "sg:tags":[
        "pet",
        "boarding",
        "sitting"
    ],
    "wof:name":"Pampered Pet Sitters",
    "wof:placetype":"venue"
},
  "geometry": {"coordinates":[-94.171351,30.074708],"type":"Point"}
}