{
  "type": "Feature",
  "properties": {
    "iso:country":"US",
    "sg:address":"9007 Christina Dr",
    "sg:city":"Elgin",
    "sg:classifiers":[
        {
            "category":"Shopping",
            "type":"Retail Goods"
        }
    ],
    "sg:phone":"+1 512 272 4252",
    "sg:postcode":"78621",
    "sg:province":"TX",
    "sg:tags":[
        "merchandise"
    ],
    "wof:name":"B&J Pool Service Inc",
    "wof:placetype":"venue"
},
  "geometry": {"coordinates":[-97.44861299999999,30.281864],"type":"Point"}
}