{
  "type": "Feature",
  "properties": {
    "iso:country":"US",
    "sg:address":"120 Bremond St",
    "sg:city":"Nacogdoches",
    "sg:classifiers":[
        {
            "category":"Wholesale",
            "subcategory":"Hardware",
            "type":"Manufacturing & Wholesale Goods"
        }
    ],
    "sg:phone":"+1 936 564 8331",
    "sg:postcode":"75964",
    "sg:province":"TX",
    "sg:tags":[
        "plumbing",
        "fixture",
        "supply"
    ],
    "wof:name":"Moore Supply Co",
    "wof:placetype":"venue"
},
  "geometry": {"coordinates":[-94.66023800000001,31.604128],"type":"Point"}
}