{
  "type": "Feature",
  "properties": {
    "iso:country":"US",
    "sg:address":"1902 State Hwy 121H Bus",
    "sg:city":"Lewisville",
    "sg:classifiers":[
        {
            "category":"Professional",
            "type":"Services"
        }
    ],
    "sg:phone":"+1 972 315 7557",
    "sg:postcode":"75067",
    "sg:province":"TX",
    "wof:name":"Bill Wilkins",
    "wof:placetype":"venue"
},
  "geometry": {"coordinates":[-96.992893,33.017705],"type":"Point"}
}