{
  "type": "Feature",
  "properties": {
    "iso:country":"US",
    "sg:address":"2620 W Pioneer Pkwy",
    "sg:city":"Arlington",
    "sg:classifiers":[
        {
            "category":"Professional",
            "subcategory":"Testing Lab",
            "type":"Services"
        }
    ],
    "sg:phone":"+1 817 265 4840",
    "sg:postcode":"76013",
    "sg:province":"TX",
    "sg:tags":[
        "laboratory"
    ],
    "wof:name":"K & H Assoc",
    "wof:placetype":"venue"
},
  "geometry": {"coordinates":[-97.15000999999999,32.709555],"type":"Point"}
}