{
  "type": "Feature",
  "properties": {
    "iso:country":"US",
    "sg:address":"1221 S Mo-Pac Expy",
    "sg:city":"Austin",
    "sg:classifiers":[
        {
            "category":"Real Estate",
            "subcategory":"Real Estate Agent",
            "type":"Services"
        }
    ],
    "sg:phone":"+1 512 327 3162",
    "sg:postcode":"78746",
    "sg:province":"TX",
    "wof:name":"Matt Ikard Team",
    "wof:placetype":"venue"
},
  "geometry": {"coordinates":[-97.787637,30.26463],"type":"Point"}
}