{
  "type": "Feature",
  "properties": {
    "iso:country":"US",
    "sg:address":"1425 N 23rd St",
    "sg:city":"Mcallen",
    "sg:classifiers":[
        {
            "category":"Building & Trades",
            "subcategory":"Equipment Rental",
            "type":"Services"
        }
    ],
    "sg:phone":"+1 956 631 7356",
    "sg:postcode":"78501",
    "sg:province":"TX",
    "wof:name":"Amigo Rent To Own",
    "wof:placetype":"venue"
},
  "geometry": {"coordinates":[-98.243341,26.21826],"type":"Point"}
}