{
  "type": "Feature",
  "properties": {
    "iso:country":"US",
    "sg:address":"602 E Myrtle St",
    "sg:city":"Angleton",
    "sg:classifiers":[
        {
            "category":"Personal",
            "subcategory":"Beauty Salon",
            "type":"Services"
        }
    ],
    "sg:phone":"+1 979 848 0049",
    "sg:postcode":"77515",
    "sg:province":"TX",
    "wof:name":"Panache",
    "wof:placetype":"venue"
},
  "geometry": {"coordinates":[-95.424286,29.165454],"type":"Point"}
}