{
  "type": "Feature",
  "properties": {
    "iso:country":"US",
    "sg:address":"2324 Skymaster Rd",
    "sg:city":"Galveston",
    "sg:classifiers":[
        {
            "category":"Recreation",
            "type":"Entertainment"
        }
    ],
    "sg:phone":"+1 409 740 6547",
    "sg:postcode":"77554",
    "sg:province":"TX",
    "sg:tags":[
        "instruction",
        "gymnastic"
    ],
    "wof:name":"Geo's Texas Tumblers",
    "wof:placetype":"venue"
},
  "geometry": {"coordinates":[-94.852796,29.265878],"type":"Point"}
}