{
  "type": "Feature",
  "properties": {
    "iso:country":"US",
    "sg:address":"1715 Cedar Hill Rd",
    "sg:city":"Duncanville",
    "sg:classifiers":[
        {
            "category":"Banks & Credit Unions",
            "subcategory":"Bank",
            "type":"Services"
        }
    ],
    "sg:phone":"+1 972 775 2583",
    "sg:postcode":"75137",
    "sg:province":"TX",
    "sg:tags":[
        "loan",
        "real estate"
    ],
    "wof:name":"Allied Home Mtg Capital Corp",
    "wof:placetype":"venue"
},
  "geometry": {"coordinates":[-96.920548,32.629734],"type":"Point"}
}