{
  "type": "Feature",
  "properties": {
    "iso:country":"US",
    "sg:address":"300 N Breckenridge Ave",
    "sg:city":"Breckenridge",
    "sg:classifiers":[
        {
            "category":"Mining & Drilling",
            "type":"Manufacturing & Wholesale Goods"
        }
    ],
    "sg:phone":"+1 254 559 3355",
    "sg:postcode":"76424",
    "sg:province":"TX",
    "sg:tags":[
        "oil",
        "gas",
        "producer"
    ],
    "wof:name":"BBL LTD",
    "wof:placetype":"venue"
},
  "geometry": {"coordinates":[-98.902581,32.758345],"type":"Point"}
}