{
  "type": "Feature",
  "properties": {
    "iso:country":"US",
    "sg:address":"4601 Fountain Ln",
    "sg:city":"Odessa",
    "sg:classifiers":[
        {
            "category":"Real Estate",
            "subcategory":"Real Estate Agent",
            "type":"Services"
        }
    ],
    "sg:phone":"+1 432 552 0277",
    "sg:postcode":"79761",
    "sg:province":"TX",
    "wof:name":"Apex Real Estate Co",
    "wof:placetype":"venue"
},
  "geometry": {"coordinates":[-102.322704,31.874955],"type":"Point"}
}