{
  "type": "Feature",
  "properties": {
    "iso:country":"US",
    "sg:address":"105 Saddletree Rd",
    "sg:city":"Shavano Park",
    "sg:classifiers":[
        {
            "category":"Building & Trades",
            "subcategory":"Construction",
            "type":"Services"
        }
    ],
    "sg:phone":"+1 210 479 2672",
    "sg:postcode":"78231",
    "sg:province":"TX",
    "sg:tags":[
        "home",
        "builder"
    ],
    "wof:name":"N L Austin & Assoc",
    "wof:placetype":"venue"
},
  "geometry": {"coordinates":[-98.55253999999999,29.588996],"type":"Point"}
}