{
  "type": "Feature",
  "properties": {
    "iso:country":"US",
    "sg:address":"4010 William D Tate Ave",
    "sg:city":"Grapevine",
    "sg:classifiers":[
        {
            "category":"Professional",
            "subcategory":"Management & Consulting",
            "type":"Services"
        }
    ],
    "sg:phone":"+1 817 251 1291",
    "sg:postcode":"76051",
    "sg:province":"TX",
    "sg:tags":[
        "consultant",
        "business"
    ],
    "wof:name":"Advantage Resources Inc",
    "wof:placetype":"venue"
},
  "geometry": {"coordinates":[-97.099853,32.893421],"type":"Point"}
}