{
  "type": "Feature",
  "properties": {
    "iso:country":"US",
    "sg:address":"300 N Conway Ave",
    "sg:city":"Mission",
    "sg:classifiers":[
        {
            "category":"Personal",
            "subcategory":"Shoe Repair & Shine",
            "type":"Services"
        }
    ],
    "sg:phone":"+1 956 583 0784",
    "sg:postcode":"78572",
    "sg:province":"TX",
    "sg:tags":[
        "parlor"
    ],
    "wof:name":"Mission Boot & Shoe Repair",
    "wof:placetype":"venue"
},
  "geometry": {"coordinates":[-98.32671999999999,26.209559],"type":"Point"}
}