{
  "type": "Feature",
  "properties": {
    "iso:country":"US",
    "sg:address":"348 Stotts Ave",
    "sg:city":"El Paso",
    "sg:classifiers":[
        {
            "category":"Professional",
            "subcategory":"Management & Consulting",
            "type":"Services"
        }
    ],
    "sg:phone":"+1 915 581 9066",
    "sg:postcode":"79932",
    "sg:province":"TX",
    "sg:tags":[
        "business"
    ],
    "wof:name":"Rheol Quality LLC",
    "wof:placetype":"venue"
},
  "geometry": {"coordinates":[-106.590276,31.847172],"type":"Point"}
}