{
  "type": "Feature",
  "properties": {
    "iso:country":"US",
    "sg:address":"404 Rose Ln",
    "sg:city":"El Paso",
    "sg:classifiers":[
        {
            "category":"Real Estate",
            "subcategory":"Architect",
            "type":"Services"
        }
    ],
    "sg:phone":"+1 915 781 2763",
    "sg:postcode":"79915",
    "sg:province":"TX",
    "sg:tags":[
        "estimate",
        "construction"
    ],
    "wof:name":"CPME",
    "wof:placetype":"venue"
},
  "geometry": {"coordinates":[-106.370276,31.748324],"type":"Point"}
}