{
  "type": "Feature",
  "properties": {
    "iso:country":"US",
    "sg:address":"21314 Highland Knolls Dr",
    "sg:city":"Katy",
    "sg:classifiers":[
        {
            "category":"Professional",
            "type":"Services"
        }
    ],
    "sg:phone":"+1 281 578 6556",
    "sg:postcode":"77450",
    "sg:province":"TX",
    "wof:name":"Heaven Sent Home Services",
    "wof:placetype":"venue"
},
  "geometry": {"coordinates":[-95.737897,29.759341],"type":"Point"}
}