{
  "type": "Feature",
  "properties": {
    "iso:country":"US",
    "sg:address":"2732 Glenhaven Dr",
    "sg:city":"Plano",
    "sg:classifiers":[
        {
            "category":"Shopping",
            "subcategory":"Bicycles & Sporting Goods",
            "type":"Retail Goods"
        }
    ],
    "sg:phone":"+1 972 612 3769",
    "sg:postcode":"75023",
    "sg:province":"TX",
    "wof:name":"Sport Attivo Inc",
    "wof:placetype":"venue"
},
  "geometry": {"coordinates":[-96.746807,33.048172],"type":"Point"}
}