{
  "type": "Feature",
  "properties": {
    "iso:country":"US",
    "sg:address":"412 E Anderson St",
    "sg:city":"Weimar",
    "sg:classifiers":[
        {
            "category":"Organizations",
            "subcategory":"Religious Organization",
            "type":"Services"
        }
    ],
    "sg:phone":"+1 979 725 8453",
    "sg:postcode":"78956",
    "sg:province":"TX",
    "sg:tags":[
        "church"
    ],
    "wof:name":"St James AME Church",
    "wof:placetype":"venue"
},
  "geometry": {"coordinates":[-96.89267599999999,29.681174],"type":"Point"}
}