{
  "type": "Feature",
  "properties": {
    "iso:country":"US",
    "sg:address":"5005 W Royal Ln",
    "sg:city":"Irving",
    "sg:classifiers":[
        {
            "category":"Professional",
            "type":"Services"
        }
    ],
    "sg:phone":"+1 972 929 7374",
    "sg:postcode":"75063",
    "sg:province":"TX",
    "wof:name":"Draka USA",
    "wof:placetype":"venue"
},
  "geometry": {"coordinates":[-97.017144,32.921853],"type":"Point"}
}