{
  "type": "Feature",
  "properties": {
    "iso:country":"US",
    "sg:address":"5531 Silver Maple Dr",
    "sg:city":"Arlington",
    "sg:classifiers":[
        {
            "category":"Professional",
            "subcategory":"Business Services",
            "type":"Services"
        }
    ],
    "sg:phone":"+1 817 784 9159",
    "sg:postcode":"76018",
    "sg:province":"TX",
    "wof:name":"Houdini Custom Interiors",
    "wof:placetype":"venue"
},
  "geometry": {"coordinates":[-97.110998,32.653423],"type":"Point"}
}