{
  "type": "Feature",
  "properties": {
    "iso:country":"US",
    "sg:address":"2516 Birch Ln",
    "sg:city":"Burleson",
    "sg:classifiers":[
        {
            "category":"Building & Trades",
            "subcategory":"Plumbing",
            "type":"Services"
        }
    ],
    "sg:phone":"+1 817 426 5219",
    "sg:postcode":"76028",
    "sg:province":"TX",
    "sg:tags":[
        "contractor"
    ],
    "wof:name":"Elite Plumbing",
    "wof:placetype":"venue"
},
  "geometry": {"coordinates":[-97.231499,32.535301],"type":"Point"}
}