{
  "type": "Feature",
  "properties": {
    "iso:country":"US",
    "sg:address":"3754 W Buckingham Rd",
    "sg:city":"Garland",
    "sg:classifiers":[
        {
            "category":"Real Estate",
            "subcategory":"Real Estate Operator",
            "type":"Services"
        }
    ],
    "sg:phone":"+1 972 272 5438",
    "sg:postcode":"75042",
    "sg:province":"TX",
    "sg:tags":[
        "apartment",
        "management"
    ],
    "wof:name":"Cedars Apartments",
    "wof:placetype":"venue"
},
  "geometry": {"coordinates":[-96.686813,32.931054],"type":"Point"}
}