{
  "type": "Feature",
  "properties": {
    "iso:country":"US",
    "sg:address":"2405 Nueces St Ste A",
    "sg:city":"Austin",
    "sg:classifiers":[
        {
            "category":"Insurance",
            "subcategory":"Health Insurance",
            "type":"Services"
        },
        {
            "category":"Sports & Exercise",
            "subcategory":"Playing Field",
            "type":"Entertainment"
        }
    ],
    "sg:phone":"+1 512 473 8300",
    "sg:postcode":"78705",
    "sg:province":"TX",
    "sg:tags":[
        "instruction",
        "market",
        "fitness"
    ],
    "sg:website":"www.simplyfitmeals.com",
    "wof:name":"Simply Fit Meals",
    "wof:placetype":"venue"
},
  "geometry": {"coordinates":[-97.742851,30.288094],"type":"Point"}
}