{
  "type": "Feature",
  "properties": {
    "iso:country":"US",
    "sg:address":"5300 Memorial Dr",
    "sg:city":"Houston",
    "sg:classifiers":[
        {
            "category":"Building & Trades",
            "subcategory":"Construction",
            "type":"Services"
        }
    ],
    "sg:phone":"+1 713 802 2060",
    "sg:postcode":"77007",
    "sg:province":"TX",
    "sg:tags":[
        "designer",
        "installation",
        "abandonment",
        "contractor",
        "marine",
        "offshore"
    ],
    "wof:name":"Bluewater Industries Inc",
    "wof:placetype":"venue"
},
  "geometry": {"coordinates":[-95.41620899999999,29.761481],"type":"Point"}
}