{
  "type": "Feature",
  "properties": {
    "iso:country":"US",
    "sg:address":"326 W Josephine",
    "sg:city":"San Antonio",
    "sg:classifiers":[
        {
            "category":"Building & Trades",
            "subcategory":"Construction",
            "type":"Services"
        }
    ],
    "sg:phone":"+1 210 734 7474",
    "sg:postcode":"78212",
    "sg:province":"TX",
    "sg:tags":[
        "house"
    ],
    "wof:name":"Paraguas Design & Renovation",
    "wof:placetype":"venue"
},
  "geometry": {"coordinates":[-98.485749,29.446858],"type":"Point"}
}