{
  "type": "Feature",
  "properties": {
    "iso:country":"US",
    "sg:address":"4111 Callahan Rd",
    "sg:city":"Big Spring",
    "sg:classifiers":[
        {
            "category":"Retail",
            "subcategory":"Veterinary Services",
            "type":"Services"
        }
    ],
    "sg:phone":"+1 432 264 6253",
    "sg:postcode":"79720",
    "sg:province":"TX",
    "wof:name":"Veterinary Consult",
    "wof:placetype":"venue"
},
  "geometry": {"coordinates":[-101.459856,32.191775],"type":"Point"}
}