{
  "type": "Feature",
  "properties": {
    "iso:country":"US",
    "sg:address":"1407 FM 1462",
    "sg:city":"Alvin",
    "sg:classifiers":[
        {
            "category":"Retail",
            "subcategory":"Auto Repair",
            "type":"Services"
        }
    ],
    "sg:phone":"+1 281 585 2893",
    "sg:postcode":"77511",
    "sg:province":"TX",
    "sg:tags":[
        "repairing",
        "automobile"
    ],
    "wof:name":"William's Auto Svc",
    "wof:placetype":"venue"
},
  "geometry": {"coordinates":[-95.251473,29.399556],"type":"Point"}
}