{
  "type": "Feature",
  "properties": {
    "iso:country":"US",
    "sg:address":"462 McMakin Rd",
    "sg:city":"Argyle",
    "sg:classifiers":[
        {
            "category":"Professional",
            "subcategory":"Management & Consulting",
            "type":"Services"
        }
    ],
    "sg:phone":"+1 817 430 3883",
    "sg:postcode":"76226",
    "sg:province":"TX",
    "wof:name":"Kennemer Management LLC",
    "wof:placetype":"venue"
},
  "geometry": {"coordinates":[-97.13148,33.06667],"type":"Point"}
}