{
  "type": "Feature",
  "properties": {
    "iso:country":"US",
    "sg:address":"4407 Foster Ave",
    "sg:city":"Laredo",
    "sg:classifiers":[
        {
            "category":"Social Services",
            "subcategory":"Child Care",
            "type":"Services"
        }
    ],
    "sg:phone":"+1 956 724 9288",
    "sg:postcode":"78041",
    "sg:province":"TX",
    "sg:tags":[
        "school",
        "day"
    ],
    "wof:name":"Education Center",
    "wof:placetype":"venue"
},
  "geometry": {"coordinates":[-99.475634,27.535804],"type":"Point"}
}