{
  "type": "Feature",
  "properties": {
    "iso:country":"US",
    "sg:address":"308 Magnolia Dr",
    "sg:city":"San Marcos",
    "sg:classifiers":[
        {
            "category":"Building & Trades",
            "subcategory":"Cleaning & Sanitation",
            "type":"Services"
        }
    ],
    "sg:phone":"+1 512 353 3330",
    "sg:postcode":"78666",
    "sg:province":"TX",
    "sg:tags":[
        "maintenance"
    ],
    "wof:name":"American Maids",
    "wof:placetype":"venue"
},
  "geometry": {"coordinates":[-97.942088,29.861939],"type":"Point"}
}