{
  "type": "Feature",
  "properties": {
    "iso:country":"US",
    "sg:address":"4000 N Macarthur Blvd",
    "sg:city":"Irving",
    "sg:classifiers":[
        {
            "category":"Shopping",
            "subcategory":"Gifts & Souvenirs",
            "type":"Retail Goods"
        }
    ],
    "sg:phone":"+1 972 717 1266",
    "sg:postcode":"75038",
    "sg:province":"TX",
    "wof:name":"Personally Yours Gifts & ACC",
    "wof:placetype":"venue"
},
  "geometry": {"coordinates":[-96.95932000000001,32.860545],"type":"Point"}
}