{
  "type": "Feature",
  "properties": {
    "iso:country":"US",
    "sg:address":"62 E Sundance Cir",
    "sg:city":"Spring",
    "sg:classifiers":[
        {
            "category":"Wholesale",
            "subcategory":"Apparel",
            "type":"Manufacturing & Wholesale Goods"
        }
    ],
    "sg:phone":"+1 314 452 6376",
    "sg:postcode":"77382",
    "sg:province":"TX",
    "sg:tags":[
        "shoes"
    ],
    "wof:name":"Red Shoes LLC",
    "wof:placetype":"venue"
},
  "geometry": {"coordinates":[-95.55379000000001,30.212516],"type":"Point"}
}