{
  "type": "Feature",
  "properties": {
    "iso:country":"US",
    "sg:address":"2601 N Pecan St",
    "sg:city":"Nacogdoches",
    "sg:classifiers":[
        {
            "category":"Professional",
            "subcategory":"Employment Agencies",
            "type":"Services"
        }
    ],
    "sg:phone":"+1 936 560 9504",
    "sg:postcode":"75965",
    "sg:province":"TX",
    "wof:name":"Ashcraft Associates",
    "wof:placetype":"venue"
},
  "geometry": {"coordinates":[-94.65055099999999,31.627398],"type":"Point"}
}