{
  "type": "Feature",
  "properties": {
    "iso:country":"US",
    "sg:address":"6703 Levelland Rd",
    "sg:city":"Dallas",
    "sg:classifiers":[
        {
            "category":"Building & Trades",
            "subcategory":"Construction",
            "type":"Services"
        }
    ],
    "sg:phone":"+1 972 447 9480",
    "sg:postcode":"75252",
    "sg:province":"TX",
    "sg:tags":[
        "concrete",
        "contractor"
    ],
    "wof:name":"Pro Concrete Services Inc",
    "wof:placetype":"venue"
},
  "geometry": {"coordinates":[-96.792665,32.988961],"type":"Point"}
}