{
  "type": "Feature",
  "properties": {
    "iso:country":"US",
    "sg:address":"3611 14th St",
    "sg:city":"Plano",
    "sg:classifiers":[
        {
            "category":"Personal",
            "subcategory":"Beauty Salon",
            "type":"Services"
        }
    ],
    "sg:phone":"+1 972 424 2812",
    "sg:postcode":"75074",
    "sg:province":"TX",
    "sg:tags":[
        "shop"
    ],
    "wof:name":"Nails Pro",
    "wof:placetype":"venue"
},
  "geometry": {"coordinates":[-96.66297900000001,33.014398],"type":"Point"}
}