{
  "type": "Feature",
  "properties": {
    "iso:country":"US",
    "sg:address":"1901 S Goliad St",
    "sg:city":"Amarillo",
    "sg:classifiers":[
        {
            "category":"Insurance",
            "subcategory":"Insurance Agent",
            "type":"Services"
        }
    ],
    "sg:phone":"+1 806 358 6408",
    "sg:postcode":"79106",
    "sg:province":"TX",
    "wof:name":"Jameson & Associates",
    "wof:placetype":"venue"
},
  "geometry": {"coordinates":[-101.886944,35.194296],"type":"Point"}
}