{
  "type": "Feature",
  "properties": {
    "iso:country":"US",
    "sg:address":"18952 Co Rd 234",
    "sg:city":"Tyler",
    "sg:classifiers":[
        {
            "category":"Professional",
            "type":"Services"
        }
    ],
    "sg:phone":"+1 903 566 4519",
    "sg:postcode":"75707",
    "sg:province":"TX",
    "wof:name":"Amrc Inc",
    "wof:placetype":"venue"
},
  "geometry": {"coordinates":[-95.096142,32.327605],"type":"Point"}
}