{
  "type": "Feature",
  "properties": {
    "iso:country":"US",
    "sg:address":"14679 Midway Rd",
    "sg:city":"Addison",
    "sg:classifiers":[
        {
            "category":"Shopping",
            "subcategory":"Computers & Home Electronics",
            "type":"Retail Goods"
        }
    ],
    "sg:phone":"+1 972 503 0500",
    "sg:postcode":"75001",
    "sg:province":"TX",
    "sg:tags":[
        "software"
    ],
    "sg:website":"www.cmdcorp.com",
    "wof:name":"CMD Corp",
    "wof:placetype":"venue"
},
  "geometry": {"coordinates":[-96.83899599999999,32.94592],"type":"Point"}
}