{
  "type": "Feature",
  "properties": {
    "iso:country":"US",
    "sg:address":"906 W Mcdermott Dr",
    "sg:city":"Allen",
    "sg:classifiers":[
        {
            "category":"Restaurant",
            "type":"Food & Drink"
        }
    ],
    "sg:menulink":"http://www.allmenus.com/tx/plano/40781-samui/menu/",
    "sg:phone":"+1 972 747 7452",
    "sg:postcode":"75013",
    "sg:province":"TX",
    "sg:tags":[
        "thai",
        "asian"
    ],
    "wof:name":"Samui",
    "wof:placetype":"venue"
},
  "geometry": {"coordinates":[-96.682304,33.101645],"type":"Point"}
}