{
  "type": "Feature",
  "properties": {
    "iso:country":"US",
    "sg:address":"1109 Tyler Ave",
    "sg:city":"Corpus Christi",
    "sg:classifiers":[
        {
            "category":"Professional",
            "type":"Services"
        }
    ],
    "sg:phone":"+1 361 884 4249",
    "sg:postcode":"78404",
    "sg:province":"TX",
    "wof:name":"Advantage Backflow Service",
    "wof:placetype":"venue"
},
  "geometry": {"coordinates":[-97.404882,27.759844],"type":"Point"}
}