{
  "type": "Feature",
  "properties": {
    "iso:country":"US",
    "sg:address":"9316 Coriander Pl",
    "sg:city":"Dallas",
    "sg:classifiers":[
        {
            "category":"Real Estate",
            "subcategory":"Real Estate Services",
            "type":"Services"
        },
        {
            "category":"Real Estate",
            "subcategory":"Real Estate Agent",
            "type":"Services"
        }
    ],
    "sg:phone":"+1 469 547 4836",
    "sg:postcode":"75217",
    "sg:province":"TX",
    "sg:tags":[
        "management"
    ],
    "wof:name":"Candace Properties",
    "wof:placetype":"venue"
},
  "geometry": {"coordinates":[-96.664725,32.672659],"type":"Point"}
}