{
  "type": "Feature",
  "properties": {
    "iso:country":"US",
    "sg:address":"8416 Gary Ave",
    "sg:city":"Lubbock",
    "sg:classifiers":[
        {
            "category":"Professional",
            "subcategory":"Business Services",
            "type":"Services"
        }
    ],
    "sg:phone":"+1 806 797 0064",
    "sg:postcode":"79423",
    "sg:province":"TX",
    "sg:tags":[
        "interior",
        "consultant",
        "design",
        "decorator"
    ],
    "wof:name":"Morning Glories",
    "wof:placetype":"venue"
},
  "geometry": {"coordinates":[-101.882668,33.514692],"type":"Point"}
}