{
  "type": "Feature",
  "properties": {
    "iso:country":"US",
    "sg:address":"1625 Crescent Cir Ste 225",
    "sg:city":"Carrollton",
    "sg:classifiers":[
        {
            "category":"Manufacturing",
            "subcategory":"Apparel",
            "type":"Manufacturing & Wholesale Goods"
        }
    ],
    "sg:phone":"+1 972 242 5600",
    "sg:postcode":"75006",
    "sg:province":"TX",
    "sg:tags":[
        "clothing-men's-wholesale",
        "manufacturer"
    ],
    "wof:name":"Aladdin Imports Limited Partnership",
    "wof:placetype":"venue"
},
  "geometry": {"coordinates":[-96.91783599999999,32.960016],"type":"Point"}
}