{
  "type": "Feature",
  "properties": {
    "iso:country":"US",
    "sg:address":"106 S Van Buren Ave",
    "sg:city":"Mount Pleasant",
    "sg:classifiers":[
        {
            "category":"Shopping",
            "subcategory":"Gifts & Souvenirs",
            "type":"Retail Goods"
        }
    ],
    "sg:phone":"+1 903 575 9912",
    "sg:postcode":"75455",
    "sg:province":"TX",
    "wof:name":"Tied With A Bow",
    "wof:placetype":"venue"
},
  "geometry": {"coordinates":[-94.970567,33.156651],"type":"Point"}
}