{
  "type": "Feature",
  "properties": {
    "iso:country":"US",
    "sg:address":"4510 Broadway St",
    "sg:city":"Galveston",
    "sg:classifiers":[
        {
            "category":"Wholesale",
            "subcategory":"Poultry",
            "type":"Manufacturing & Wholesale Goods"
        }
    ],
    "sg:phone":"+1 409 763 8811",
    "sg:postcode":"77551",
    "sg:province":"TX",
    "sg:tags":[
        "seafood",
        "eggs"
    ],
    "wof:name":"D&M Poultry Egg & Seafood",
    "wof:placetype":"venue"
},
  "geometry": {"coordinates":[-94.81831699999999,29.293264],"type":"Point"}
}