{
  "type": "Feature",
  "properties": {
    "iso:country":"US",
    "sg:address":"1317 W Broadway Ave",
    "sg:city":"Fort Worth",
    "sg:classifiers":[
        {
            "category":"Mining & Drilling",
            "type":"Manufacturing & Wholesale Goods"
        }
    ],
    "sg:phone":"+1 325 869 5242",
    "sg:postcode":"76104",
    "sg:province":"TX",
    "sg:tags":[
        "field",
        "oil"
    ],
    "wof:name":"Concho Services LLC",
    "wof:placetype":"venue"
},
  "geometry": {"coordinates":[-97.34040899999999,32.741137],"type":"Point"}
}