{
  "type": "Feature",
  "properties": {
    "iso:country":"US",
    "sg:address":"120 S Mesa St",
    "sg:city":"El Paso",
    "sg:classifiers":[
        {
            "category":"Shopping",
            "subcategory":"Jewelry",
            "type":"Retail Goods"
        }
    ],
    "sg:phone":"+1 915 838 9436",
    "sg:postcode":"79901",
    "sg:province":"TX",
    "sg:tags":[
        "jeweler"
    ],
    "wof:name":"Esmeralda Joyeria",
    "wof:placetype":"venue"
},
  "geometry": {"coordinates":[-106.486616,31.75758],"type":"Point"}
}