{
  "type": "Feature",
  "properties": {
    "iso:country":"US",
    "sg:address":"2637 Royal Ln",
    "sg:city":"Dallas",
    "sg:classifiers":[
        {
            "category":"Shopping",
            "subcategory":"Bicycles & Sporting Goods",
            "type":"Retail Goods"
        }
    ],
    "sg:phone":"+1 972 241 5570",
    "sg:postcode":"75229",
    "sg:province":"TX",
    "wof:name":"Paladin Arms Co",
    "wof:placetype":"venue"
},
  "geometry": {"coordinates":[-96.88890600000001,32.895406],"type":"Point"}
}