{
  "type": "Feature",
  "properties": {
    "iso:country":"US",
    "sg:address":"712 Spencer Hwy",
    "sg:city":"South Houston",
    "sg:classifiers":[
        {
            "category":"Professional",
            "subcategory":"Lawyer & Legal Services",
            "type":"Services"
        }
    ],
    "sg:phone":"+1 713 943 9537",
    "sg:postcode":"77587",
    "sg:province":"TX",
    "wof:name":"Garcia Israel B",
    "wof:placetype":"venue"
},
  "geometry": {"coordinates":[-95.223176,29.664427],"type":"Point"}
}