{
  "type": "Feature",
  "properties": {
    "iso:country":"US",
    "sg:address":"4000 Loop 256",
    "sg:city":"Palestine",
    "sg:classifiers":[
        {
            "category":"Social Services",
            "type":"Services"
        }
    ],
    "sg:phone":"+1 903 731 5194",
    "sg:postcode":"75801",
    "sg:province":"TX",
    "wof:name":"Red Cross",
    "wof:placetype":"venue"
},
  "geometry": {"coordinates":[-95.646688,31.741668],"type":"Point"}
}