{
  "type": "Feature",
  "properties": {
    "iso:country":"US",
    "sg:address":"5000 Lucas Ln",
    "sg:city":"Austin",
    "sg:classifiers":[
        {
            "category":"Real Estate",
            "subcategory":"Real Estate Agent",
            "type":"Services"
        }
    ],
    "sg:phone":"+1 512 453 8071",
    "sg:postcode":"78731",
    "sg:province":"TX",
    "wof:name":"Garner Dewayne Srpa Sra",
    "wof:placetype":"venue"
},
  "geometry": {"coordinates":[-97.763491,30.337155],"type":"Point"}
}