{
  "type": "Feature",
  "properties": {
    "iso:country":"US",
    "sg:address":"607 Saldana St",
    "sg:city":"San Antonio",
    "sg:classifiers":[
        {
            "category":"Organizations",
            "subcategory":"Religious Organization",
            "type":"Services"
        }
    ],
    "sg:phone":"+1 210 532 4044",
    "sg:postcode":"78225",
    "sg:province":"TX",
    "sg:tags":[
        "church"
    ],
    "wof:name":"Templo Elim Assemblies Of God",
    "wof:placetype":"venue"
},
  "geometry": {"coordinates":[-98.512401,29.392167],"type":"Point"}
}