{
  "type": "Feature",
  "properties": {
    "iso:country":"US",
    "sg:address":"3104 Foxboro Dr",
    "sg:city":"Richardson",
    "sg:classifiers":[
        {
            "category":"Retail",
            "subcategory":"Auto Repair",
            "type":"Services"
        }
    ],
    "sg:phone":"+1 972 783 6448",
    "sg:postcode":"75082",
    "sg:province":"TX",
    "sg:tags":[
        "body"
    ],
    "wof:name":"Steven B Gladu",
    "wof:placetype":"venue"
},
  "geometry": {"coordinates":[-96.695875,32.995272],"type":"Point"}
}