{
  "type": "Feature",
  "properties": {
    "iso:country":"US",
    "sg:address":"1301 S I H 35",
    "sg:city":"Austin",
    "sg:classifiers":[
        {
            "category":"Real Estate",
            "subcategory":"Real Estate Services",
            "type":"Services"
        }
    ],
    "sg:phone":"+1 512 448 3333",
    "sg:postcode":"78741",
    "sg:province":"TX",
    "wof:name":"Lewis Douglass D Rltr",
    "wof:placetype":"venue"
},
  "geometry": {"coordinates":[-97.734596,30.245001],"type":"Point"}
}