{
  "type": "Feature",
  "properties": {
    "iso:country":"US",
    "sg:address":"96 Red River St",
    "sg:city":"Austin",
    "sg:phone":"+1 512 243 0044",
    "sg:postcode":"78701",
    "sg:province":"TX",
    "sg:website":"http://www.austincarriage.com",
    "wof:name":"Austin Carriage",
    "wof:placetype":"venue"
},
  "geometry": {"coordinates":[-97.73896000000001,30.26119],"type":"Point"}
}