{
  "type": "Feature",
  "properties": {
    "iso:country":"US",
    "sg:address":"100 S Wall St",
    "sg:city":"Iowa Park",
    "sg:classifiers":[
        {
            "category":"Retail",
            "subcategory":"Auto Repair",
            "type":"Services"
        }
    ],
    "sg:phone":"+1 940 592 2231",
    "sg:postcode":"76367",
    "sg:province":"TX",
    "sg:tags":[
        "body"
    ],
    "wof:name":"James Billy Paint & Body",
    "wof:placetype":"venue"
},
  "geometry": {"coordinates":[-98.667919,33.950423],"type":"Point"}
}