{
  "type": "Feature",
  "properties": {
    "iso:country":"US",
    "sg:address":"4440 S Padre Island Dr",
    "sg:city":"Corpus Christi",
    "sg:classifiers":[
        {
            "category":"Retail",
            "subcategory":"Auto Repair",
            "type":"Services"
        }
    ],
    "sg:phone":"+1 361 853 6257",
    "sg:postcode":"78411",
    "sg:province":"TX",
    "sg:tags":[
        "transmission"
    ],
    "wof:name":"AAMCO Transmissions",
    "wof:placetype":"venue"
},
  "geometry": {"coordinates":[-97.38985,27.717024],"type":"Point"}
}