{
  "type": "Feature",
  "properties": {
    "iso:country":"US",
    "sg:address":"2817 Bonnie View Rd",
    "sg:city":"Dallas",
    "sg:classifiers":[
        {
            "category":"Shopping",
            "subcategory":"Clothing, Apparel, & Fashions",
            "type":"Retail Goods"
        }
    ],
    "sg:phone":"+1 214 375 9888",
    "sg:postcode":"75216",
    "sg:province":"TX",
    "wof:name":"Clothes By Freanwil",
    "wof:placetype":"venue"
},
  "geometry": {"coordinates":[-96.78398900000001,32.720095],"type":"Point"}
}