{
  "type": "Feature",
  "properties": {
    "iso:country":"US",
    "sg:address":"1102 Tulane St",
    "sg:city":"Houston",
    "sg:classifiers":[
        {
            "category":"Shopping",
            "subcategory":"Books",
            "type":"Retail Goods"
        }
    ],
    "sg:phone":"+1 713 864 9717",
    "sg:postcode":"77008",
    "sg:province":"TX",
    "wof:name":"Another Place In Time",
    "wof:placetype":"venue"
},
  "geometry": {"coordinates":[-95.40223400000001,29.792431],"type":"Point"}
}