{
  "type": "Feature",
  "properties": {
    "iso:country":"US",
    "sg:address":"1436 Cross Bend Rd",
    "sg:city":"Plano",
    "sg:classifiers":[
        {
            "category":"Professional",
            "subcategory":"Computer Services",
            "type":"Services"
        }
    ],
    "sg:phone":"+1 972 881 2175",
    "sg:postcode":"75023",
    "sg:province":"TX",
    "wof:name":"Protec Engineering Service",
    "wof:placetype":"venue"
},
  "geometry": {"coordinates":[-96.720471,33.049183],"type":"Point"}
}