{
  "type": "Feature",
  "properties": {
    "iso:country":"US",
    "sg:address":"7559 Arcadia Trl",
    "sg:city":"Fort Worth",
    "sg:classifiers":[
        {
            "category":"Building & Trades",
            "subcategory":"Construction",
            "type":"Services"
        }
    ],
    "sg:phone":"+1 817 371 6235",
    "sg:postcode":"76137",
    "sg:province":"TX",
    "sg:tags":[
        "contractor"
    ],
    "wof:name":"Landmark Fence & Patio",
    "wof:placetype":"venue"
},
  "geometry": {"coordinates":[-97.27478600000001,32.875327],"type":"Point"}
}