{
  "type": "Feature",
  "properties": {
    "iso:country":"US",
    "sg:address":"7057 Greenville Ave",
    "sg:city":"Dallas",
    "sg:classifiers":[
        {
            "category":"Autos & Motor Vehicles",
            "subcategory":"Fuel & Gas Station",
            "type":"Retail Goods"
        }
    ],
    "sg:phone":"+1 214 987 4040",
    "sg:postcode":"75231",
    "sg:province":"TX",
    "wof:name":"Racetrac Petroleum",
    "wof:placetype":"venue"
},
  "geometry": {"coordinates":[-96.761398,32.877201],"type":"Point"}
}