{
  "type": "Feature",
  "properties": {
    "iso:country":"US",
    "sg:address":"4211 Luckenbach Rd",
    "sg:city":"San Antonio",
    "sg:classifiers":[
        {
            "category":"Farming",
            "subcategory":"Farm & Veterinary Services",
            "type":"Manufacturing & Wholesale Goods"
        }
    ],
    "sg:phone":"+1 210 680 1610",
    "sg:postcode":"78251",
    "sg:province":"TX",
    "sg:tags":[
        "crop",
        "harvesting"
    ],
    "wof:name":"Texas Rainwater Harvesting",
    "wof:placetype":"venue"
},
  "geometry": {"coordinates":[-98.68373200000001,29.476589],"type":"Point"}
}