{
  "type": "Feature",
  "properties": {
    "iso:country":"US",
    "sg:address":"902 Kck Way",
    "sg:city":"Cedar Hill",
    "sg:classifiers":[
        {
            "category":"Retail",
            "subcategory":"Auto Repair",
            "type":"Services"
        }
    ],
    "sg:phone":"+1 972 293 0400",
    "sg:postcode":"75104",
    "sg:province":"TX",
    "sg:tags":[
        "automotive",
        "general",
        "automobile",
        "motor",
        "rebuilding"
    ],
    "wof:name":"Southwest Engines",
    "wof:placetype":"venue"
},
  "geometry": {"coordinates":[-96.961635,32.569003],"type":"Point"}
}