{
  "type": "Feature",
  "properties": {
    "iso:country":"US",
    "sg:address":"1330 Centerville Rd",
    "sg:city":"Dallas",
    "sg:classifiers":[
        {
            "category":"Building & Trades",
            "subcategory":"Construction",
            "type":"Services"
        }
    ],
    "sg:phone":"+1 214 320 2700",
    "sg:postcode":"75218",
    "sg:province":"TX",
    "sg:tags":[
        "contractor"
    ],
    "wof:name":"Gcs Roofing",
    "wof:placetype":"venue"
},
  "geometry": {"coordinates":[-96.688283,32.843485],"type":"Point"}
}