{
  "type": "Feature",
  "properties": {
    "iso:country":"US",
    "sg:address":"451 SW 1st St",
    "sg:city":"Cooper",
    "sg:classifiers":[
        {
            "category":"Retail",
            "subcategory":"Funeral Services",
            "type":"Services"
        }
    ],
    "sg:phone":"+1 903 395 2165",
    "sg:postcode":"75432",
    "sg:province":"TX",
    "sg:tags":[
        "director"
    ],
    "wof:name":"Delta Funeral Home",
    "wof:placetype":"venue"
},
  "geometry": {"coordinates":[-95.688703,33.371458],"type":"Point"}
}