{
  "type": "Feature",
  "properties": {
    "iso:country":"US",
    "sg:address":"14775 Midway Rd",
    "sg:city":"Addison",
    "sg:classifiers":[
        {
            "category":"Professional",
            "subcategory":"Business Services",
            "type":"Services"
        }
    ],
    "sg:phone":"+1 972 934 9911",
    "sg:postcode":"75001",
    "sg:province":"TX",
    "sg:tags":[
        "event"
    ],
    "wof:name":"Addison Event Ctr",
    "wof:placetype":"venue"
},
  "geometry": {"coordinates":[-96.83898499999999,32.95048],"type":"Point"}
}