{
  "type": "Feature",
  "properties": {
    "iso:country":"US",
    "sg:address":"350 Eva St",
    "sg:city":"Montgomery",
    "sg:classifiers":[
        {
            "category":"Restaurant",
            "type":"Food & Drink"
        }
    ],
    "sg:menulink":"http://www.allmenus.com/tx/montgomery/57425-kirbys-bbq--more/menu/",
    "sg:phone":"+1 936 597 5044",
    "sg:postcode":"77356",
    "sg:province":"TX",
    "sg:tags":[
        "barbecue",
        "american"
    ],
    "wof:name":"Kirby's Bbq & More",
    "wof:placetype":"venue"
},
  "geometry": {"coordinates":[-95.68427699999999,30.388668],"type":"Point"}
}