{
  "type": "Feature",
  "properties": {
    "iso:country":"US",
    "sg:address":"2511 College Ave",
    "sg:city":"Snyder",
    "sg:classifiers":[
        {
            "category":"Government",
            "subcategory":"Office",
            "type":"Public Place"
        }
    ],
    "sg:phone":"+1 325 573 8524",
    "sg:postcode":"79549",
    "sg:province":"TX",
    "sg:tags":[
        "parish",
        "government-county"
    ],
    "wof:name":"Scurry-County of",
    "wof:placetype":"venue"
},
  "geometry": {"coordinates":[-100.918381,32.717061],"type":"Point"}
}