{
  "type": "Feature",
  "properties": {
    "iso:country":"US",
    "sg:address":"3450 Lee Blvd",
    "sg:city":"El Paso",
    "sg:classifiers":[
        {
            "category":"Autos & Motor Vehicles",
            "subcategory":"Boat Sales",
            "type":"Retail Goods"
        }
    ],
    "sg:phone":"+1 915 849 6190",
    "sg:postcode":"79936",
    "sg:province":"TX",
    "sg:tags":[
        "dealer",
        "sales"
    ],
    "wof:name":"Boat Shop",
    "wof:placetype":"venue"
},
  "geometry": {"coordinates":[-106.29379299999999,31.795662],"type":"Point"}
}