{
  "type": "Feature",
  "properties": {
    "iso:country":"US",
    "sg:address":"11633 Harry Hines Blvd Ste 105",
    "sg:city":"Dallas",
    "sg:classifiers":[
        {
            "category":"Shopping",
            "subcategory":"Jewelry",
            "type":"Retail Goods"
        }
    ],
    "sg:phone":"+1 214 634 7110",
    "sg:postcode":"75229",
    "sg:province":"TX",
    "wof:name":"Star Designs",
    "wof:placetype":"venue"
},
  "geometry": {"coordinates":[-96.894465,32.905485],"type":"Point"}
}