{
  "type": "Feature",
  "properties": {
    "iso:country":"US",
    "sg:address":"1802 Old Nacogdoches Rd",
    "sg:city":"Henderson",
    "sg:classifiers":[
        {
            "category":"Farming",
            "subcategory":"Farm",
            "type":"Manufacturing & Wholesale Goods"
        }
    ],
    "sg:phone":"+1 903 657 8690",
    "sg:postcode":"75654",
    "sg:province":"TX",
    "sg:tags":[
        "crop",
        "animal",
        "general"
    ],
    "wof:name":"Greg Green",
    "wof:placetype":"venue"
},
  "geometry": {"coordinates":[-94.797382,32.134852],"type":"Point"}
}