{
  "type": "Feature",
  "properties": {
    "iso:country":"US",
    "sg:address":"3465 Courtyard Cir",
    "sg:city":"Dallas",
    "sg:classifiers":[
        {
            "category":"Professional",
            "subcategory":"Business Services",
            "type":"Services"
        }
    ],
    "sg:phone":"+1 972 620 2819",
    "sg:postcode":"75234",
    "sg:province":"TX",
    "wof:name":"B&B Kids Ventures Ltd",
    "wof:placetype":"venue"
},
  "geometry": {"coordinates":[-96.864808,32.933199],"type":"Point"}
}