{
  "type": "Feature",
  "properties": {
    "iso:country":"US",
    "sg:address":"4612 Williams Rd",
    "sg:city":"Benbrook",
    "sg:classifiers":[
        {
            "category":"Wholesale",
            "subcategory":"Vending Machines",
            "type":"Manufacturing & Wholesale Goods"
        }
    ],
    "sg:phone":"+1 817 292 2041",
    "sg:postcode":"76116",
    "sg:province":"TX",
    "wof:name":"Fort Worth Value Vending",
    "wof:placetype":"venue"
},
  "geometry": {"coordinates":[-97.452861,32.706373],"type":"Point"}
}