{
  "type": "Feature",
  "properties": {
    "iso:country":"US",
    "sg:address":"6103 Bark Valley Dr",
    "sg:city":"San Antonio",
    "sg:classifiers":[
        {
            "category":"Wholesale",
            "subcategory":"Non-durable Goods",
            "type":"Manufacturing & Wholesale Goods"
        }
    ],
    "sg:phone":"+1 210 623 3661",
    "sg:postcode":"78242",
    "sg:province":"TX",
    "wof:name":"Manas",
    "wof:placetype":"venue"
},
  "geometry": {"coordinates":[-98.624107,29.353381],"type":"Point"}
}