{
  "type": "Feature",
  "properties": {
    "iso:country":"US",
    "sg:address":"10811 Nacogdoches Rd",
    "sg:city":"San Antonio",
    "sg:classifiers":[
        {
            "category":"Retail",
            "subcategory":"Auto Repair",
            "type":"Services"
        }
    ],
    "sg:phone":"+1 210 655 6546",
    "sg:postcode":"78217",
    "sg:province":"TX",
    "sg:tags":[
        "general"
    ],
    "wof:name":"Team Extreme Racing",
    "wof:placetype":"venue"
},
  "geometry": {"coordinates":[-98.422595,29.539474],"type":"Point"}
}