{
  "type": "Feature",
  "properties": {
    "iso:country":"US",
    "sg:address":"2839 Galleria Dr",
    "sg:city":"Arlington",
    "sg:classifiers":[
        {
            "category":"Personal",
            "subcategory":"Beauty Salon",
            "type":"Services"
        }
    ],
    "sg:phone":"+1 817 417 4442",
    "sg:postcode":"76011",
    "sg:province":"TX",
    "sg:tags":[
        "shop"
    ],
    "wof:name":"Double Take Salon",
    "wof:placetype":"venue"
},
  "geometry": {"coordinates":[-97.05910299999999,32.746465],"type":"Point"}
}