{
  "type": "Feature",
  "properties": {
    "iso:country":"US",
    "sg:address":"6001 Airport Blvd",
    "sg:city":"Austin",
    "sg:classifiers":[
        {
            "category":"Personal",
            "type":"Services"
        }
    ],
    "sg:phone":"+1 512 452 8500",
    "sg:postcode":"78752",
    "sg:province":"TX",
    "sg:tags":[
        "party",
        "planning",
        "event"
    ],
    "wof:name":"El Palacio De La Quinceanera",
    "wof:placetype":"venue"
},
  "geometry": {"coordinates":[-97.71555600000001,30.324163],"type":"Point"}
}