{
  "type": "Feature",
  "properties": {
    "iso:country":"US",
    "sg:address":"330 S R L Thornton Fwy",
    "sg:city":"Dallas",
    "sg:classifiers":[
        {
            "category":"Professional",
            "subcategory":"Accounting & Tax Preparation",
            "type":"Services"
        }
    ],
    "sg:phone":"+1 214 943 8774",
    "sg:postcode":"75203",
    "sg:province":"TX",
    "sg:tags":[
        "return",
        "filing"
    ],
    "wof:name":"Williams & Assoc Tax Office",
    "wof:placetype":"venue"
},
  "geometry": {"coordinates":[-96.810294,32.756981],"type":"Point"}
}