{
  "type": "Feature",
  "properties": {
    "iso:country":"US",
    "sg:address":"210 Avenue D NW",
    "sg:city":"Childress",
    "sg:classifiers":[
        {
            "category":"Manufacturing",
            "subcategory":"Glass & Minerals",
            "type":"Manufacturing & Wholesale Goods"
        }
    ],
    "sg:phone":"+1 940 937 3471",
    "sg:postcode":"79201",
    "sg:province":"TX",
    "sg:tags":[
        "plate",
        "shape",
        "glass-wholesale",
        "window",
        "special",
        "circle",
        "glass-auto",
        "manufacturer"
    ],
    "wof:name":"Childress Glass",
    "wof:placetype":"venue"
},
  "geometry": {"coordinates":[-100.206563,34.424938],"type":"Point"}
}