{
  "type": "Feature",
  "properties": {
    "iso:country":"US",
    "sg:address":"1500 N Hobart St",
    "sg:city":"Pampa",
    "sg:classifiers":[
        {
            "category":"Shopping",
            "subcategory":"Shoes",
            "type":"Retail Goods"
        }
    ],
    "sg:phone":"+1 806 665 5691",
    "sg:postcode":"79065",
    "sg:province":"TX",
    "wof:name":"Brown's Shoe Fit Co",
    "wof:placetype":"venue"
},
  "geometry": {"coordinates":[-100.971897,35.553335],"type":"Point"}
}