{
  "type": "Feature",
  "properties": {
    "iso:country":"US",
    "sg:address":"16951 Addison Rd",
    "sg:city":"Addison",
    "sg:classifiers":[
        {
            "category":"Shopping",
            "subcategory":"Gifts & Souvenirs",
            "type":"Retail Goods"
        }
    ],
    "sg:phone":"+1 972 248 2975",
    "sg:postcode":"75001",
    "sg:province":"TX",
    "wof:name":"Elisa C Taylor",
    "wof:placetype":"venue"
},
  "geometry": {"coordinates":[-96.830404,32.979512],"type":"Point"}
}