{
  "type": "Feature",
  "properties": {
    "iso:country":"US",
    "sg:address":"439 E Austin St",
    "sg:city":"Giddings",
    "sg:classifiers":[
        {
            "category":"Cinema",
            "subcategory":"Movie Rental",
            "type":"Entertainment"
        }
    ],
    "sg:phone":"+1 979 542 0007",
    "sg:postcode":"78942",
    "sg:province":"TX",
    "sg:tags":[
        "video",
        "tape"
    ],
    "wof:name":"Movie Gallery",
    "wof:placetype":"venue"
},
  "geometry": {"coordinates":[-96.933685,30.182295],"type":"Point"}
}