{
  "type": "Feature",
  "properties": {
    "iso:country":"US",
    "sg:address":"9186 S Hampton Rd",
    "sg:city":"Dallas",
    "sg:classifiers":[
        {
            "category":"Freight",
            "type":"Transportation"
        }
    ],
    "sg:phone":"+1 972 224 8780",
    "sg:postcode":"75232",
    "sg:province":"TX",
    "sg:tags":[
        "distance",
        "carrier",
        "long",
        "trucking"
    ],
    "sg:website":"www.gaineycorp.com",
    "wof:name":"Gainey Transportation Services",
    "wof:placetype":"venue"
},
  "geometry": {"coordinates":[-96.856944,32.636491],"type":"Point"}
}