{
  "type": "Feature",
  "properties": {
    "iso:country":"US",
    "sg:address":"929 Gessner Rd",
    "sg:city":"Houston",
    "sg:classifiers":[
        {
            "category":"Health Services",
            "subcategory":"Doctor",
            "type":"Services"
        }
    ],
    "sg:phone":"+1 713 465 1211",
    "sg:postcode":"77024",
    "sg:province":"TX",
    "sg:website":"www.houston-ivf.com",
    "wof:name":"Houston Ivf",
    "wof:placetype":"venue"
},
  "geometry": {"coordinates":[-95.544578,29.780328],"type":"Point"}
}