{
  "type": "Feature",
  "properties": {
    "iso:country":"US",
    "sg:address":"306 E Ennis Ave",
    "sg:city":"Ennis",
    "sg:classifiers":[
        {
            "category":"Retail",
            "subcategory":"Self-service Laundry",
            "type":"Services"
        }
    ],
    "sg:phone":"+1 972 875 0354",
    "sg:postcode":"75119",
    "sg:province":"TX",
    "sg:tags":[
        "coin"
    ],
    "wof:name":"Avenue Laundry",
    "wof:placetype":"venue"
},
  "geometry": {"coordinates":[-96.62360200000001,32.329649],"type":"Point"}
}