{
  "type": "Feature",
  "properties": {
    "iso:country":"US",
    "sg:address":"2609 24th St",
    "sg:city":"Lubbock",
    "sg:classifiers":[
        {
            "category":"Manufacturing",
            "subcategory":"Printing",
            "type":"Manufacturing & Wholesale Goods"
        }
    ],
    "sg:phone":"+1 806 747 3872",
    "sg:postcode":"79410",
    "sg:province":"TX",
    "sg:tags":[
        "book"
    ],
    "wof:name":"Ferret Publishing",
    "wof:placetype":"venue"
},
  "geometry": {"coordinates":[-101.874993,33.57247],"type":"Point"}
}