{
  "type": "Feature",
  "properties": {
    "iso:country":"US",
    "sg:address":"601 S China St",
    "sg:city":"Brady",
    "sg:classifiers":[
        {
            "category":"Organizations",
            "subcategory":"Religious Organization",
            "type":"Services"
        }
    ],
    "sg:phone":"+1 325 597 1063",
    "sg:postcode":"76825",
    "sg:province":"TX",
    "sg:tags":[
        "church"
    ],
    "wof:name":"Central Baptist Church",
    "wof:placetype":"venue"
},
  "geometry": {"coordinates":[-99.340981,31.130923],"type":"Point"}
}