{
  "type": "Feature",
  "properties": {
    "iso:country":"US",
    "sg:address":"4705 Easley Pl",
    "sg:city":"Amarillo",
    "sg:classifiers":[
        {
            "category":"Real Estate",
            "subcategory":"Real Estate Operator",
            "type":"Services"
        }
    ],
    "sg:phone":"+1 806 353 0964",
    "sg:postcode":"79119",
    "sg:province":"TX",
    "sg:tags":[
        "building",
        "nonresidential"
    ],
    "wof:name":"Stradley Properties LLC",
    "wof:placetype":"venue"
},
  "geometry": {"coordinates":[-101.93321,35.159126],"type":"Point"}
}