{
  "type": "Feature",
  "properties": {
    "iso:country":"US",
    "sg:address":"6724 Meadowcrest Dr",
    "sg:city":"Arlington",
    "sg:classifiers":[
        {
            "category":"Real Estate",
            "subcategory":"Real Estate Services",
            "type":"Services"
        },
        {
            "category":"Real Estate",
            "subcategory":"Real Estate Agent",
            "type":"Services"
        }
    ],
    "sg:phone":"+1 817 419 6051",
    "sg:postcode":"76002",
    "sg:province":"TX",
    "sg:tags":[
        "management"
    ],
    "wof:name":"Dj3 Enterprises",
    "wof:placetype":"venue"
},
  "geometry": {"coordinates":[-97.088943,32.630291],"type":"Point"}
}