{
  "type": "Feature",
  "properties": {
    "iso:country":"US",
    "sg:address":"11802 Vancouver Ln",
    "sg:city":"Houston",
    "sg:classifiers":[
        {
            "category":"Building & Trades",
            "subcategory":"Construction",
            "type":"Services"
        }
    ],
    "sg:phone":"+1 281 890 1354",
    "sg:postcode":"77064",
    "sg:province":"TX",
    "sg:tags":[
        "steel",
        "erection",
        "structural"
    ],
    "wof:name":"Steel Road Plate Rentals",
    "wof:placetype":"venue"
},
  "geometry": {"coordinates":[-95.555138,29.94659],"type":"Point"}
}