{
  "type": "Feature",
  "properties": {
    "iso:country":"US",
    "sg:address":"265 Turner Pass",
    "sg:city":"Marble Falls",
    "sg:classifiers":[
        {
            "category":"Autos & Motor Vehicles",
            "subcategory":"Auto Supplies",
            "type":"Retail Goods"
        }
    ],
    "sg:phone":"+1 830 798 9147",
    "sg:postcode":"78654",
    "sg:province":"TX",
    "wof:name":"Rolling J Tire Service",
    "wof:placetype":"venue"
},
  "geometry": {"coordinates":[-98.22754399999999,30.623398],"type":"Point"}
}