{
  "type": "Feature",
  "properties": {
    "iso:country":"US",
    "sg:address":"7542 Dawn Mist Ct",
    "sg:city":"Sugar Land",
    "sg:classifiers":[
        {
            "category":"Building & Trades",
            "subcategory":"Construction",
            "type":"Services"
        }
    ],
    "sg:phone":"+1 281 343 1665",
    "sg:postcode":"77479",
    "sg:province":"TX",
    "sg:tags":[
        "masonry",
        "contractor"
    ],
    "wof:name":"TJC Masonry",
    "wof:placetype":"venue"
},
  "geometry": {"coordinates":[-95.67429300000001,29.556974],"type":"Point"}
}