{
  "type": "Feature",
  "properties": {
    "iso:country":"US",
    "sg:address":"6602 Castle Lane Dr",
    "sg:city":"Houston",
    "sg:classifiers":[
        {
            "category":"Health Services",
            "subcategory":"Medical Lab",
            "type":"Services"
        }
    ],
    "sg:phone":"+1 281 895 7898",
    "sg:postcode":"77066",
    "sg:province":"TX",
    "sg:tags":[
        "laboratory"
    ],
    "wof:name":"M R Diagnostic",
    "wof:placetype":"venue"
},
  "geometry": {"coordinates":[-95.51188500000001,29.949023],"type":"Point"}
}