{
  "type": "Feature",
  "properties": {
    "iso:country":"US",
    "sg:address":"7137 Bell St",
    "sg:city":"Amarillo",
    "sg:classifiers":[
        {
            "category":"Building & Trades",
            "subcategory":"Construction",
            "type":"Services"
        }
    ],
    "sg:phone":"+1 806 352 9900",
    "sg:postcode":"79109",
    "sg:province":"TX",
    "sg:tags":[
        "house",
        "general",
        "contractor"
    ],
    "wof:name":"Lone Star General Contractors",
    "wof:placetype":"venue"
},
  "geometry": {"coordinates":[-101.901813,35.133203],"type":"Point"}
}