{
  "type": "Feature",
  "properties": {
    "iso:country":"US",
    "sg:address":"2006 S Washington St",
    "sg:city":"Kaufman",
    "sg:classifiers":[
        {
            "category":"Food & Beverages",
            "subcategory":"Groceries & Convenience Stores",
            "type":"Retail Goods"
        }
    ],
    "sg:phone":"+1 972 932 6146",
    "sg:postcode":"75142",
    "sg:province":"TX",
    "sg:tags":[
        "grocer"
    ],
    "wof:name":"Kountry Korner",
    "wof:placetype":"venue"
},
  "geometry": {"coordinates":[-96.309252,32.576259],"type":"Point"}
}