{
  "type": "Feature",
  "properties": {
    "iso:country":"US",
    "sg:address":"120 9th St",
    "sg:city":"San Antonio",
    "sg:classifiers":[
        {
            "category":"Organizations",
            "subcategory":"Community Association",
            "type":"Services"
        }
    ],
    "sg:phone":"+1 210 227 4412",
    "sg:postcode":"78215",
    "sg:province":"TX",
    "sg:tags":[
        "eating",
        "center",
        "bowling"
    ],
    "wof:name":"Turner Club",
    "wof:placetype":"venue"
},
  "geometry": {"coordinates":[-98.482511,29.43431],"type":"Point"}
}