{
  "type": "Feature",
  "properties": {
    "iso:country":"US",
    "sg:address":"802 Convent Ave",
    "sg:city":"Laredo",
    "sg:classifiers":[
        {
            "category":"Taxi",
            "type":"Transportation"
        }
    ],
    "sg:phone":"+1 956 722 8811",
    "sg:postcode":"78040",
    "sg:province":"TX",
    "sg:tags":[
        "taxicab"
    ],
    "wof:name":"Crown Cab",
    "wof:placetype":"venue"
},
  "geometry": {"coordinates":[-99.507575,27.507112],"type":"Point"}
}