{
  "type": "Feature",
  "properties": {
    "iso:country":"US",
    "sg:address":"1110 Timberview Ln",
    "sg:city":"Richardson",
    "sg:classifiers":[
        {
            "category":"Retail",
            "subcategory":"Repair Shop",
            "type":"Services"
        }
    ],
    "sg:phone":"+1 972 238 9309",
    "sg:postcode":"75080",
    "sg:province":"TX",
    "wof:name":"Bulldozier Window Service",
    "wof:placetype":"venue"
},
  "geometry": {"coordinates":[-96.742141,32.996297],"type":"Point"}
}