{
  "type": "Feature",
  "properties": {
    "iso:country":"US",
    "sg:address":"21093 US Hwy 271",
    "sg:city":"Gladewater",
    "sg:classifiers":[
        {
            "category":"Farming",
            "subcategory":"Livestock Farm",
            "type":"Manufacturing & Wholesale Goods"
        }
    ],
    "sg:phone":"+1 903 845 4534",
    "sg:postcode":"75647",
    "sg:province":"TX",
    "sg:tags":[
        "animal",
        "general"
    ],
    "wof:name":"Saber & Roses Ranch",
    "wof:placetype":"venue"
},
  "geometry": {"coordinates":[-95.04728900000001,32.481877],"type":"Point"}
}