{
  "type": "Feature",
  "properties": {
    "iso:country":"US",
    "sg:address":"1026 Halsell Ave",
    "sg:city":"Bridgeport",
    "sg:classifiers":[
        {
            "category":"Shopping",
            "subcategory":"Pharmacy",
            "type":"Retail Goods"
        }
    ],
    "sg:phone":"+1 940 683 2950",
    "sg:postcode":"76426",
    "sg:province":"TX",
    "wof:name":"Valu-Rite Pharmacy",
    "wof:placetype":"venue"
},
  "geometry": {"coordinates":[-97.757677,33.21034],"type":"Point"}
}