{
  "type": "Feature",
  "properties": {
    "iso:country":"US",
    "sg:address":"303 Eden Dr",
    "sg:city":"Longview",
    "sg:classifiers":[
        {
            "category":"Real Estate",
            "subcategory":"Real Estate Services",
            "type":"Services"
        },
        {
            "category":"Real Estate",
            "subcategory":"Real Estate Operator",
            "type":"Services"
        }
    ],
    "sg:phone":"+1 903 753 5117",
    "sg:postcode":"75605",
    "sg:province":"TX",
    "sg:tags":[
        "vacancy",
        "apartment",
        "rental",
        "listing"
    ],
    "wof:name":"Eden Apartments",
    "wof:placetype":"venue"
},
  "geometry": {"coordinates":[-94.73765400000001,32.523063],"type":"Point"}
}