{
  "type": "Feature",
  "properties": {
    "iso:country":"US",
    "sg:address":"100 Commercial Cir",
    "sg:city":"Conroe",
    "sg:classifiers":[
        {
            "category":"Wholesale",
            "subcategory":"Farm Supplies",
            "type":"Manufacturing & Wholesale Goods"
        }
    ],
    "sg:phone":"+1 936 539 4100",
    "sg:postcode":"77304",
    "sg:province":"TX",
    "sg:tags":[
        "fertilizer"
    ],
    "wof:name":"Vick Martin Office",
    "wof:placetype":"venue"
},
  "geometry": {"coordinates":[-95.48043199999999,30.308811],"type":"Point"}
}