{
  "type": "Feature",
  "properties": {
    "iso:country":"US",
    "sg:address":"15704 Kuykendahl Rd",
    "sg:city":"Houston",
    "sg:classifiers":[
        {
            "category":"Restaurant",
            "type":"Food & Drink"
        }
    ],
    "sg:phone":"+1 281 440 4133",
    "sg:postcode":"77090",
    "sg:province":"TX",
    "sg:tags":[
        "eating"
    ],
    "wof:name":"Hartz Chicken Buffet",
    "wof:placetype":"venue"
},
  "geometry": {"coordinates":[-95.46047799999999,30.003307],"type":"Point"}
}