{
  "type": "Feature",
  "properties": {
    "iso:country":"US",
    "sg:address":"1152 N Great Southwest Pkwy",
    "sg:city":"Grand Prairie",
    "sg:classifiers":[
        {
            "category":"Manufacturing",
            "subcategory":"Tools & Machinery",
            "type":"Manufacturing & Wholesale Goods"
        }
    ],
    "sg:phone":"+1 972 647 9011",
    "sg:postcode":"75050",
    "sg:province":"TX",
    "sg:tags":[
        "machine",
        "shop"
    ],
    "wof:name":"Mid-Cities Mfg Inc",
    "wof:placetype":"venue"
},
  "geometry": {"coordinates":[-97.045599,32.764302],"type":"Point"}
}