{
  "type": "Feature",
  "properties": {
    "iso:country":"US",
    "sg:address":"2125 SW 3rd St",
    "sg:city":"Grand Prairie",
    "sg:classifiers":[
        {
            "category":"Real Estate",
            "subcategory":"Real Estate Agent",
            "type":"Services"
        }
    ],
    "sg:phone":"+1 214 707 2174",
    "sg:postcode":"75051",
    "sg:province":"TX",
    "sg:tags":[
        "development",
        "sales"
    ],
    "wof:name":"Home Sweet Home Realty Inc",
    "wof:placetype":"venue"
},
  "geometry": {"coordinates":[-97.007429,32.71355],"type":"Point"}
}