{
  "type": "Feature",
  "properties": {
    "iso:country":"US",
    "sg:address":"2114 Goodrich Ave",
    "sg:city":"Austin",
    "sg:classifiers":[
        {
            "category":"Professional",
            "subcategory":"Management & Consulting",
            "type":"Services"
        }
    ],
    "sg:phone":"+1 512 414 4921",
    "sg:postcode":"78704",
    "sg:province":"TX",
    "sg:tags":[
        "consultant",
        "educational"
    ],
    "wof:name":"It Boot Camp",
    "wof:placetype":"venue"
},
  "geometry": {"coordinates":[-97.77278099999999,30.249595],"type":"Point"}
}