{
  "type": "Feature",
  "properties": {
    "iso:country":"US",
    "sg:address":"5524 FM 236",
    "sg:city":"Victoria",
    "sg:classifiers":[
        {
            "category":"Freight",
            "type":"Transportation"
        }
    ],
    "sg:phone":"+1 361 573 2120",
    "sg:postcode":"77905",
    "sg:province":"TX",
    "sg:tags":[
        "commercial",
        "storage"
    ],
    "wof:name":"Mission Valley Storage",
    "wof:placetype":"venue"
},
  "geometry": {"coordinates":[-97.111903,28.830296],"type":"Point"}
}