{
  "type": "Feature",
  "properties": {
    "iso:country":"US",
    "sg:address":"502 W Main St",
    "sg:city":"Grand Prairie",
    "sg:classifiers":[
        {
            "category":"Retail",
            "subcategory":"Repair Shop",
            "type":"Services"
        }
    ],
    "sg:phone":"+1 972 262 6434",
    "sg:postcode":"75050",
    "sg:province":"TX",
    "sg:tags":[
        "lock",
        "locksmith"
    ],
    "wof:name":"Accent Lock & Key & Safe",
    "wof:placetype":"venue"
},
  "geometry": {"coordinates":[-97.010442,32.744593],"type":"Point"}
}