{
  "type": "Feature",
  "properties": {
    "iso:country":"US",
    "sg:address":"4221 Ghio Fish Rd",
    "sg:city":"Texarkana",
    "sg:classifiers":[
        {
            "category":"Freight",
            "type":"Transportation"
        }
    ],
    "sg:phone":"+1 903 793 6022",
    "sg:postcode":"75503",
    "sg:province":"TX",
    "wof:name":"Pegasus Transport LLC",
    "wof:placetype":"venue"
},
  "geometry": {"coordinates":[-94.053021,33.460032],"type":"Point"}
}