{
  "type": "Feature",
  "properties": {
    "iso:country":"US",
    "sg:address":"33 Well Rd",
    "sg:city":"Denison",
    "sg:classifiers":[
        {
            "category":"Freight",
            "type":"Transportation"
        }
    ],
    "sg:phone":"+1 903 465 4004",
    "sg:postcode":"75020",
    "sg:province":"TX",
    "sg:tags":[
        "commercial",
        "storage"
    ],
    "wof:name":"Four Oaks Storage Ctr",
    "wof:placetype":"venue"
},
  "geometry": {"coordinates":[-96.643824,33.751929],"type":"Point"}
}