{
  "type": "Feature",
  "properties": {
    "iso:country":"US",
    "sg:address":"151 Co Rd 307",
    "sg:city":"Jarrell",
    "sg:classifiers":[
        {
            "category":"Manufacturing",
            "subcategory":"Glass & Minerals",
            "type":"Manufacturing & Wholesale Goods"
        }
    ],
    "sg:phone":"+1 512 746 4450",
    "sg:postcode":"76537",
    "sg:province":"TX",
    "sg:tags":[
        "concrete",
        "brick",
        "prod",
        "block"
    ],
    "wof:name":"Concrete Products Inc",
    "wof:placetype":"venue"
},
  "geometry": {"coordinates":[-97.616844,30.838725],"type":"Point"}
}