{
  "type": "Feature",
  "properties": {
    "iso:country":"US",
    "sg:address":"4310 S Georgia St",
    "sg:city":"Amarillo",
    "sg:classifiers":[
        {
            "category":"Retail",
            "subcategory":"Auto Repair",
            "type":"Services"
        }
    ],
    "sg:phone":"+1 806 353 4151",
    "sg:postcode":"79110",
    "sg:province":"TX",
    "sg:tags":[
        "repairing",
        "automobile",
        "general"
    ],
    "wof:name":"Dwayne Husemans Quick Auto Svc",
    "wof:placetype":"venue"
},
  "geometry": {"coordinates":[-101.866247,35.166931],"type":"Point"}
}