{
  "type": "Feature",
  "properties": {
    "iso:country":"US",
    "sg:address":"12212 Cypress North Houston Rd",
    "sg:city":"Cypress",
    "sg:classifiers":[
        {
            "category":"Recreation",
            "type":"Entertainment"
        }
    ],
    "sg:phone":"+1 281 890 6700",
    "sg:postcode":"77429",
    "sg:province":"TX",
    "sg:tags":[
        "skating",
        "rink"
    ],
    "wof:name":"Lone Star Skate Inc",
    "wof:placetype":"venue"
},
  "geometry": {"coordinates":[-95.605563,29.952402],"type":"Point"}
}