{
  "type": "Feature",
  "properties": {
    "iso:country":"US",
    "sg:address":"10719 Seneca St",
    "sg:city":"Houston",
    "sg:classifiers":[
        {
            "category":"Education",
            "subcategory":"School",
            "type":"Public Place"
        }
    ],
    "sg:phone":"+1 713 633 0781",
    "sg:postcode":"77016",
    "sg:province":"TX",
    "wof:name":"Schools",
    "wof:placetype":"venue"
},
  "geometry": {"coordinates":[-95.302004,29.869445],"type":"Point"}
}