{
  "type": "Feature",
  "properties": {
    "iso:country":"US",
    "sg:address":"15305 Flying Cir",
    "sg:city":"Helotes",
    "sg:classifiers":[
        {
            "category":"Building & Trades",
            "subcategory":"Plumbing",
            "type":"Services"
        }
    ],
    "sg:phone":"+1 210 695 9648",
    "sg:postcode":"78023",
    "sg:province":"TX",
    "sg:tags":[
        "conditioning",
        "air",
        "system",
        "contractor"
    ],
    "wof:name":"Eric Gandara Heating & Air",
    "wof:placetype":"venue"
},
  "geometry": {"coordinates":[-98.699631,29.586257],"type":"Point"}
}