{
  "type": "Feature",
  "properties": {
    "iso:country":"US",
    "sg:address":"8117 Preston Rd",
    "sg:city":"Dallas",
    "sg:classifiers":[
        {
            "category":"Professional",
            "subcategory":"Lawyer & Legal Services",
            "type":"Services"
        }
    ],
    "sg:phone":"+1 214 987 3800",
    "sg:postcode":"75225",
    "sg:province":"TX",
    "sg:tags":[
        "attorney",
        "law",
        "employment",
        "labor"
    ],
    "wof:name":"Snyder , Kristin Michelle - Ogletree, De",
    "wof:placetype":"venue"
},
  "geometry": {"coordinates":[-96.80415000000001,32.861398],"type":"Point"}
}