{
  "type": "Feature",
  "properties": {
    "iso:country":"US",
    "sg:address":"1301 W Expressway 83",
    "sg:city":"Pharr",
    "sg:classifiers":[
        {
            "category":"Travel",
            "subcategory":"Hotels & Motels",
            "type":"Entertainment"
        }
    ],
    "sg:phone":"+1 956 702 4880",
    "sg:postcode":"78577",
    "sg:province":"TX",
    "sg:tags":[
        "lodging"
    ],
    "sg:website":"http://www.qualityinn.com/hotel-pharr-texas-TX033",
    "wof:name":"Quality Inn Pharr",
    "wof:placetype":"venue"
},
  "geometry": {"coordinates":[-98.200013,26.200826],"type":"Point"}
}