{
  "type": "Feature",
  "properties": {
    "iso:country":"US",
    "sg:address":"2231 Anthony-Hay Ln",
    "sg:city":"Katy",
    "sg:classifiers":[
        {
            "category":"Utilities",
            "subcategory":"Cable",
            "type":"Services"
        }
    ],
    "sg:phone":"+1 281 541 4218",
    "sg:postcode":"77449",
    "sg:province":"TX",
    "sg:tags":[
        "television"
    ],
    "wof:name":"Blue Star Satellite",
    "wof:placetype":"venue"
},
  "geometry": {"coordinates":[-95.768322,29.805601],"type":"Point"}
}