{
  "type": "Feature",
  "properties": {
    "iso:country":"US",
    "sg:address":"4650 Regent Blvd",
    "sg:city":"Irving",
    "sg:classifiers":[
        {
            "category":"Banks & Credit Unions",
            "subcategory":"Bank",
            "type":"Services"
        }
    ],
    "sg:phone":"+1 972 657 2511",
    "sg:postcode":"75063",
    "sg:province":"TX",
    "sg:tags":[
        "bus",
        "term"
    ],
    "wof:name":"Citicorp",
    "wof:placetype":"venue"
},
  "geometry": {"coordinates":[-97.011467,32.933846],"type":"Point"}
}