{
  "type": "Feature",
  "properties": {
    "iso:country":"US",
    "sg:address":"7703 North Lamar",
    "sg:city":"Austin",
    "sg:classifiers":[
        {
            "category":"Professional",
            "subcategory":"Art Services",
            "type":"Services"
        },
        {
            "category":"Communications",
            "type":"Services"
        }
    ],
    "sg:phone":"+1 512 206 4220",
    "sg:postcode":"78752",
    "sg:province":"TX",
    "sg:tags":[
        "web",
        "graphic",
        "design"
    ],
    "sg:website":"www.FahrenheitMarketing.com",
    "wof:name":"Fahrenheit Marketing, LLC",
    "wof:placetype":"venue"
},
  "geometry": {"coordinates":[-97.713307,30.344925],"type":"Point"}
}