{
  "type": "Feature",
  "properties": {
    "iso:country":"US",
    "sg:address":"7819 Sands Point Dr",
    "sg:city":"Houston",
    "sg:classifiers":[
        {
            "category":"Professional",
            "subcategory":"Lawyer & Legal Services",
            "type":"Services"
        }
    ],
    "sg:phone":"+1 713 772 4800",
    "sg:postcode":"77036",
    "sg:province":"TX",
    "sg:tags":[
        "attorney"
    ],
    "wof:name":"Thomas E Edmonson",
    "wof:placetype":"venue"
},
  "geometry": {"coordinates":[-95.52413199999999,29.714568],"type":"Point"}
}