{
  "type": "Feature",
  "properties": {
    "iso:country":"US",
    "sg:address":"1500 Keaton Rd",
    "sg:city":"Sanger",
    "sg:classifiers":[
        {
            "category":"Real Estate",
            "subcategory":"Real Estate Operator",
            "type":"Services"
        }
    ],
    "sg:phone":"+1 940 536 1274",
    "sg:postcode":"76266",
    "sg:province":"TX",
    "sg:tags":[
        "mobile",
        "home",
        "community"
    ],
    "wof:name":"Mariam's Family Mobile Home Pk",
    "wof:placetype":"venue"
},
  "geometry": {"coordinates":[-97.185254,33.348765],"type":"Point"}
}