{
  "type": "Feature",
  "properties": {
    "iso:country":"US",
    "sg:address":"2524 FM 1960 E",
    "sg:city":"Houston",
    "sg:classifiers":[
        {
            "category":"Home & Garden",
            "subcategory":"Furniture",
            "type":"Retail Goods"
        }
    ],
    "sg:phone":"+1 281 821 3808",
    "sg:postcode":"77073",
    "sg:province":"TX",
    "wof:name":"Furniture Depot Inc",
    "wof:placetype":"venue"
},
  "geometry": {"coordinates":[-95.392619,30.024231],"type":"Point"}
}