{
  "type": "Feature",
  "properties": {
    "iso:country":"US",
    "sg:address":"11619 Cherry Knoll Dr",
    "sg:city":"Houston",
    "sg:classifiers":[
        {
            "category":"Professional",
            "subcategory":"Computer Services",
            "type":"Services"
        }
    ],
    "sg:phone":"+1 281 589 6708",
    "sg:postcode":"77077",
    "sg:province":"TX",
    "wof:name":"Cache Systems",
    "wof:placetype":"venue"
},
  "geometry": {"coordinates":[-95.584273,29.751082],"type":"Point"}
}