{
  "type": "Feature",
  "properties": {
    "iso:country":"US",
    "sg:address":"50 N Kessler Ave",
    "sg:city":"Schulenburg",
    "sg:classifiers":[
        {
            "category":"Restaurant",
            "type":"Food & Drink"
        }
    ],
    "sg:phone":"+1 979 743 4888",
    "sg:postcode":"78956",
    "sg:province":"TX",
    "wof:name":"El Mar Cafe'",
    "wof:placetype":"venue"
},
  "geometry": {"coordinates":[-96.902657,29.690781],"type":"Point"}
}