{
  "type": "Feature",
  "properties": {
    "iso:country":"US",
    "sg:address":"7646 Dashwood Dr",
    "sg:city":"Houston",
    "sg:classifiers":[
        {
            "category":"Insurance",
            "subcategory":"Insurance Agent",
            "type":"Services"
        }
    ],
    "sg:phone":"+1 713 995 4164",
    "sg:postcode":"77036",
    "sg:province":"TX",
    "wof:name":"Lady G Insurance",
    "wof:placetype":"venue"
},
  "geometry": {"coordinates":[-95.519284,29.707504],"type":"Point"}
}