{
  "type": "Feature",
  "properties": {
    "iso:country":"US",
    "sg:address":"3621 Aspen Creek Pkwy",
    "sg:city":"Austin",
    "sg:classifiers":[
        {
            "category":"Manufacturing",
            "subcategory":"Tools & Machinery",
            "type":"Manufacturing & Wholesale Goods"
        }
    ],
    "sg:phone":"+1 512 292 6119",
    "sg:postcode":"78749",
    "sg:province":"TX",
    "sg:tags":[
        "mfg"
    ],
    "wof:name":"Motor City Tool & Die Corp",
    "wof:placetype":"venue"
},
  "geometry": {"coordinates":[-97.85714,30.182538],"type":"Point"}
}