{
  "type": "Feature",
  "properties": {
    "iso:country":"US",
    "sg:address":"501 N Spur 63",
    "sg:city":"Longview",
    "sg:classifiers":[
        {
            "category":"Professional",
            "type":"Services"
        }
    ],
    "sg:phone":"+1 903 236 4900",
    "sg:postcode":"75601",
    "sg:province":"TX",
    "sg:tags":[
        "establishment"
    ],
    "wof:name":"OFC",
    "wof:placetype":"venue"
},
  "geometry": {"coordinates":[-94.749438,32.504376],"type":"Point"}
}