{
  "type": "Feature",
  "properties": {
    "iso:country":"US",
    "sg:address":"11825 Oak Highland Dr",
    "sg:city":"Dallas",
    "sg:classifiers":[
        {
            "category":"Professional",
            "subcategory":"Business Services",
            "type":"Services"
        }
    ],
    "sg:phone":"+1 972 792 0868",
    "sg:postcode":"75243",
    "sg:province":"TX",
    "wof:name":"Tnn Business LLC",
    "wof:placetype":"venue"
},
  "geometry": {"coordinates":[-96.709834,32.911581],"type":"Point"}
}