{
  "type": "Feature",
  "properties": {
    "iso:country":"US",
    "sg:address":"1313 Shady Ln",
    "sg:city":"Lufkin",
    "sg:classifiers":[
        {
            "category":"Building & Trades",
            "subcategory":"Landscaping Services",
            "type":"Services"
        }
    ],
    "sg:phone":"+1 936 632 4235",
    "sg:postcode":"75904",
    "sg:province":"TX",
    "wof:name":"Chapmans Yards Beautiful",
    "wof:placetype":"venue"
},
  "geometry": {"coordinates":[-94.766338,31.313705],"type":"Point"}
}