{
  "type": "Feature",
  "properties": {
    "iso:country":"US",
    "sg:address":"3823 Shaver St",
    "sg:city":"Pasadena",
    "sg:classifiers":[
        {
            "category":"Health Services",
            "subcategory":"Dentist",
            "type":"Services"
        }
    ],
    "sg:phone":"+1 713 947 7837",
    "sg:postcode":"77504",
    "sg:province":"TX",
    "wof:name":"Excite Dental",
    "wof:placetype":"venue"
},
  "geometry": {"coordinates":[-95.207857,29.652069],"type":"Point"}
}