{
  "type": "Feature",
  "properties": {
    "iso:country":"US",
    "sg:address":"4584 Skyline Dr",
    "sg:city":"Chandler",
    "sg:classifiers":[
        {
            "category":"Building & Trades",
            "subcategory":"Landscaping Services",
            "type":"Services"
        }
    ],
    "sg:phone":"+1 903 849 3994",
    "sg:postcode":"75758",
    "sg:province":"TX",
    "sg:tags":[
        "lawn",
        "maintenance"
    ],
    "wof:name":"Kyles Lawn Service",
    "wof:placetype":"venue"
},
  "geometry": {"coordinates":[-95.510617,32.185373],"type":"Point"}
}