{
  "type": "Feature",
  "properties": {
    "iso:country":"US",
    "sg:address":"11713 Tanglebriar Trl",
    "sg:city":"Austin",
    "sg:classifiers":[
        {
            "category":"Manufacturing",
            "subcategory":"Buildings",
            "type":"Manufacturing & Wholesale Goods"
        },
        {
            "category":"Building & Trades",
            "subcategory":"Construction",
            "type":"Services"
        }
    ],
    "sg:phone":"+1 512 789 6398",
    "sg:postcode":"78750",
    "sg:province":"TX",
    "sg:tags":[
        "altering",
        "builder",
        "contractor",
        "home",
        "remodeling"
    ],
    "wof:name":"Robertson Homes, Inc.",
    "wof:placetype":"venue"
},
  "geometry": {"coordinates":[-97.82237000000001,30.455811],"type":"Point"}
}