{
  "type": "Feature",
  "properties": {
    "iso:country":"US",
    "sg:address":"402 Pacific St",
    "sg:city":"Houston",
    "sg:classifiers":[
        {
            "category":"Social Services",
            "type":"Services"
        }
    ],
    "sg:phone":"+1 713 528 5667",
    "sg:postcode":"77006",
    "sg:province":"TX",
    "sg:tags":[
        "organization",
        "welfare"
    ],
    "sg:website":"www.hacstxs.org",
    "wof:name":"Houston Area Community Svc Inc",
    "wof:placetype":"venue"
},
  "geometry": {"coordinates":[-95.387255,29.74684],"type":"Point"}
}