{
  "type": "Feature",
  "properties": {
    "iso:country":"US",
    "sg:address":"620 Pecan Grove Rd",
    "sg:city":"Ennis",
    "sg:classifiers":[
        {
            "category":"Retail",
            "subcategory":"Car Wash",
            "type":"Services"
        }
    ],
    "sg:phone":"+1 972 878 2179",
    "sg:postcode":"75119",
    "sg:province":"TX",
    "sg:tags":[
        "carwash"
    ],
    "wof:name":"Power Clean Power Wash",
    "wof:placetype":"venue"
},
  "geometry": {"coordinates":[-96.49441299999999,32.356063],"type":"Point"}
}