{
  "type": "Feature",
  "properties": {
    "iso:country":"US",
    "sg:address":"907 Elmdale Rd N",
    "sg:city":"Abilene",
    "sg:classifiers":[
        {
            "category":"Health Services",
            "subcategory":"Clinic",
            "type":"Services"
        }
    ],
    "sg:phone":"+1 325 548 2916",
    "sg:postcode":"79601",
    "sg:province":"TX",
    "wof:name":"Owen Healthcare Inc",
    "wof:placetype":"venue"
},
  "geometry": {"coordinates":[-99.63076100000001,32.496255],"type":"Point"}
}