{
  "type": "Feature",
  "properties": {
    "iso:country":"US",
    "sg:address":"2111 Sand Mist Cir",
    "sg:city":"League City",
    "sg:classifiers":[
        {
            "category":"Real Estate",
            "subcategory":"Real Estate Agent",
            "type":"Services"
        }
    ],
    "sg:phone":"+1 281 538 0029",
    "sg:postcode":"77573",
    "sg:province":"TX",
    "wof:name":"LLP Property Management Inc",
    "wof:placetype":"venue"
},
  "geometry": {"coordinates":[-95.04893,29.540724],"type":"Point"}
}