{
  "type": "Feature",
  "properties": {
    "iso:country":"US",
    "sg:address":"2120 W Braker Ln",
    "sg:city":"Austin",
    "sg:classifiers":[
        {
            "category":"Manufacturing",
            "subcategory":"Electronics",
            "type":"Manufacturing & Wholesale Goods"
        }
    ],
    "sg:phone":"+1 512 835 6772",
    "sg:postcode":"78758",
    "sg:province":"TX",
    "sg:tags":[
        "engineering",
        "mfg",
        "boards",
        "circuit",
        "printed"
    ],
    "wof:name":"Virtex Assembly Services Inc",
    "wof:placetype":"venue"
},
  "geometry": {"coordinates":[-97.71217900000001,30.392759],"type":"Point"}
}