{
  "type": "Feature",
  "properties": {
    "iso:country":"US",
    "sg:address":"535 Harrison St",
    "sg:city":"Corpus Christi",
    "sg:classifiers":[
        {
            "category":"Building & Trades",
            "subcategory":"Construction",
            "type":"Services"
        }
    ],
    "sg:phone":"+1 361 851 2770",
    "sg:postcode":"78404",
    "sg:province":"TX",
    "sg:tags":[
        "hanging",
        "painter",
        "contractor"
    ],
    "wof:name":"Kainer Bill Painting",
    "wof:placetype":"venue"
},
  "geometry": {"coordinates":[-97.395591,27.762381],"type":"Point"}
}