{
  "type": "Feature",
  "properties": {
    "iso:country":"US",
    "sg:address":"2525 W. Anderson Ln., #610 Suite A-1",
    "sg:city":"Austin",
    "sg:classifiers":[
        {
            "category":"Personal",
            "subcategory":"Beauty Salon",
            "type":"Services"
        }
    ],
    "sg:phone":"+1 512 851 7183",
    "sg:postcode":"78757",
    "sg:province":"TX",
    "sg:tags":[
        "hair"
    ],
    "sg:website":"kristinmichaelstylist.com/",
    "wof:name":"Kristin Michael Salon",
    "wof:placetype":"venue"
},
  "geometry": {"coordinates":[-97.73512599999999,30.354435],"type":"Point"}
}