{
  "type": "Feature",
  "properties": {
    "iso:country":"US",
    "sg:address":"1349 Empire Central Dr",
    "sg:city":"Dallas",
    "sg:classifiers":[
        {
            "category":"Organizations",
            "subcategory":"Non-profit Organization",
            "type":"Services"
        }
    ],
    "sg:phone":"+1 214 987 4662",
    "sg:postcode":"75247",
    "sg:province":"TX",
    "sg:tags":[
        "fund",
        "raising"
    ],
    "wof:name":"Wipe Out Kids Cancer",
    "wof:placetype":"venue"
},
  "geometry": {"coordinates":[-96.870808,32.826908],"type":"Point"}
}