{
  "type": "Feature",
  "properties": {
    "iso:country":"US",
    "sg:address":"802 W Elm St",
    "sg:city":"Edna",
    "sg:classifiers":[
        {
            "category":"Autos & Motor Vehicles",
            "subcategory":"Auto Supplies",
            "type":"Retail Goods"
        },
        {
            "category":"Retail",
            "subcategory":"Auto Repair",
            "type":"Services"
        }
    ],
    "sg:phone":"+1 361 782 2272",
    "sg:postcode":"77957",
    "sg:province":"TX",
    "sg:tags":[
        "lettering",
        "automobile",
        "body",
        "truck",
        "painting",
        "repairing"
    ],
    "wof:name":"Tones Body Shop",
    "wof:placetype":"venue"
},
  "geometry": {"coordinates":[-96.65492999999999,28.975344],"type":"Point"}
}