{
  "type": "Feature",
  "properties": {
    "iso:country":"US",
    "sg:address":"12126 Arrowhead Glen Dr",
    "sg:city":"Houston",
    "sg:classifiers":[
        {
            "category":"Professional",
            "subcategory":"Computer Services",
            "type":"Services"
        }
    ],
    "sg:phone":"+1 713 981 8944",
    "sg:postcode":"77071",
    "sg:province":"TX",
    "sg:tags":[
        "credit",
        "card"
    ],
    "wof:name":"Calsco Inc",
    "wof:placetype":"venue"
},
  "geometry": {"coordinates":[-95.52853399999999,29.646105],"type":"Point"}
}