{
  "type": "Feature",
  "properties": {
    "iso:country":"US",
    "sg:address":"2279 Grubbs Rd",
    "sg:city":"Sealy",
    "sg:classifiers":[
        {
            "category":"Building & Trades",
            "subcategory":"Construction",
            "type":"Services"
        }
    ],
    "sg:phone":"+1 979 885 2881",
    "sg:postcode":"77474",
    "sg:province":"TX",
    "sg:tags":[
        "contractor"
    ],
    "wof:name":"Leonard Villarreal Roofing",
    "wof:placetype":"venue"
},
  "geometry": {"coordinates":[-96.147215,29.853035],"type":"Point"}
}