{
  "type": "Feature",
  "properties": {
    "iso:country":"US",
    "sg:address":"5840 I- 20 W",
    "sg:city":"Arlington",
    "sg:classifiers":[
        {
            "category":"Banks & Credit Unions",
            "subcategory":"Investment Brokerage",
            "type":"Services"
        },
        {
            "category":"Banks & Credit Unions",
            "subcategory":"Financial Services",
            "type":"Services"
        }
    ],
    "sg:phone":"+1 817 705 7762",
    "sg:postcode":"76017",
    "sg:province":"TX",
    "wof:name":"Philan Investments Corp",
    "wof:placetype":"venue"
},
  "geometry": {"coordinates":[-97.19924,32.672819],"type":"Point"}
}