{
  "type": "Feature",
  "properties": {
    "iso:country":"US",
    "sg:address":"2508 Clay St",
    "sg:city":"Houston",
    "sg:classifiers":[
        {
            "category":"Organizations",
            "subcategory":"Religious Organization",
            "type":"Services"
        }
    ],
    "sg:phone":"+1 713 223 5210",
    "sg:postcode":"77003",
    "sg:province":"TX",
    "wof:name":"Saint Nicholas Church",
    "wof:placetype":"venue"
},
  "geometry": {"coordinates":[-95.35368699999999,29.745668],"type":"Point"}
}