{
  "type": "Feature",
  "properties": {
    "iso:country":"US",
    "sg:address":"4011 Seymour Hwy",
    "sg:city":"Wichita Falls",
    "sg:classifiers":[
        {
            "category":"Social Services",
            "type":"Services"
        }
    ],
    "sg:phone":"+1 940 691 9935",
    "sg:postcode":"76309",
    "sg:province":"TX",
    "sg:tags":[
        "organization",
        "welfare"
    ],
    "wof:name":"Loving Christian Maternity",
    "wof:placetype":"venue"
},
  "geometry": {"coordinates":[-98.540553,33.902618],"type":"Point"}
}