{
  "type": "Feature",
  "properties": {
    "iso:country":"US",
    "sg:address":"1111 Louisiana St",
    "sg:city":"Houston",
    "sg:classifiers":[
        {
            "category":"Restaurant",
            "type":"Food & Drink"
        }
    ],
    "sg:menulink":"http://www.allmenus.com/tx/houston/191886-wendys/menu/",
    "sg:phone":"+1 713 650 6136",
    "sg:postcode":"77002",
    "sg:province":"TX",
    "sg:tags":[
        "burger",
        "american",
        "soup"
    ],
    "wof:name":"Wendy's",
    "wof:placetype":"venue"
},
  "geometry": {"coordinates":[-95.368083,29.757565],"type":"Point"}
}