{
  "type": "Feature",
  "properties": {
    "iso:country":"US",
    "sg:address":"2800 Gulfway Dr",
    "sg:city":"Port Arthur",
    "sg:classifiers":[
        {
            "category":"Building & Trades",
            "subcategory":"Construction",
            "type":"Services"
        }
    ],
    "sg:phone":"+1 409 985 4478",
    "sg:postcode":"77640",
    "sg:province":"TX",
    "sg:tags":[
        "roofing",
        "contractor"
    ],
    "wof:name":"Hatch Construction",
    "wof:placetype":"venue"
},
  "geometry": {"coordinates":[-93.928755,29.89888],"type":"Point"}
}