{
  "type": "Feature",
  "properties": {
    "iso:country":"US",
    "sg:address":"6060 Gulfton St",
    "sg:city":"Houston",
    "sg:classifiers":[
        {
            "category":"Professional",
            "subcategory":"Business Services",
            "type":"Services"
        }
    ],
    "sg:phone":"+1 832 567 3812",
    "sg:postcode":"77081",
    "sg:province":"TX",
    "wof:name":"Atlantic Solution",
    "wof:placetype":"venue"
},
  "geometry": {"coordinates":[-95.488415,29.716461],"type":"Point"}
}