{
  "type": "Feature",
  "properties": {
    "iso:country":"US",
    "sg:address":"7317 Lakewood Dr",
    "sg:city":"Austin",
    "sg:classifiers":[
        {
            "category":"Organizations",
            "subcategory":"Professional Association",
            "type":"Services"
        }
    ],
    "sg:phone":"+1 512 345 8367",
    "sg:postcode":"78750",
    "sg:province":"TX",
    "sg:tags":[
        "business",
        "trade"
    ],
    "wof:name":"Lakewood Homeowners Assn",
    "wof:placetype":"venue"
},
  "geometry": {"coordinates":[-97.789238,30.375191],"type":"Point"}
}