{
  "type": "Feature",
  "properties": {
    "iso:country":"US",
    "sg:address":"4804 Wesley St",
    "sg:city":"Greenville",
    "sg:classifiers":[
        {
            "category":"Health Services",
            "subcategory":"Nursing And Care Facility",
            "type":"Services"
        }
    ],
    "sg:phone":"+1 903 455 5770",
    "sg:postcode":"75401",
    "sg:province":"TX",
    "sg:tags":[
        "residential"
    ],
    "wof:name":"Lakes Regional Mhmr Center",
    "wof:placetype":"venue"
},
  "geometry": {"coordinates":[-96.109281,33.122194],"type":"Point"}
}