{
  "type": "Feature",
  "properties": {
    "iso:country":"US",
    "sg:address":"1706 Wyndale Ct",
    "sg:city":"Richmond",
    "sg:classifiers":[
        {
            "category":"Personal",
            "type":"Services"
        }
    ],
    "sg:phone":"+1 281 344 9560",
    "sg:postcode":"77469",
    "sg:province":"TX",
    "wof:name":"Greetings & Gifts",
    "wof:placetype":"venue"
},
  "geometry": {"coordinates":[-95.733211,29.624231],"type":"Point"}
}