{
  "type": "Feature",
  "properties": {
    "iso:country":"US",
    "sg:address":"613 Santa Fe St",
    "sg:city":"Keene",
    "sg:classifiers":[
        {
            "category":"Banks & Credit Unions",
            "subcategory":"Bank",
            "type":"Services"
        }
    ],
    "sg:phone":"+1 817 367 2323",
    "sg:postcode":"76059",
    "sg:province":"TX",
    "sg:tags":[
        "broker",
        "mortgage"
    ],
    "wof:name":"Green Acres Mortgage",
    "wof:placetype":"venue"
},
  "geometry": {"coordinates":[-97.32722699999999,32.379343],"type":"Point"}
}