{
  "type": "Feature",
  "properties": {
    "iso:country":"US",
    "sg:address":"2817 Frostwood Cir",
    "sg:city":"Dickinson",
    "sg:classifiers":[
        {
            "category":"Shopping",
            "subcategory":"Jewelry",
            "type":"Retail Goods"
        }
    ],
    "sg:phone":"+1 281 337 4461",
    "sg:postcode":"77539",
    "sg:province":"TX",
    "sg:tags":[
        "precious",
        "semi-precious",
        "stone"
    ],
    "wof:name":"Dnd Gifts & Jewelry",
    "wof:placetype":"venue"
},
  "geometry": {"coordinates":[-95.080473,29.456405],"type":"Point"}
}