{
  "type": "Feature",
  "properties": {
    "iso:country":"US",
    "sg:address":"4025 E Belknap St",
    "sg:city":"Fort Worth",
    "sg:classifiers":[
        {
            "category":"Shopping",
            "subcategory":"Clothing, Apparel, & Fashions",
            "type":"Retail Goods"
        }
    ],
    "sg:phone":"+1 817 834 9650",
    "sg:postcode":"76111",
    "sg:province":"TX",
    "sg:tags":[
        "family"
    ],
    "wof:name":"Fancy Fashions",
    "wof:placetype":"venue"
},
  "geometry": {"coordinates":[-97.28773,32.783124],"type":"Point"}
}