{
  "type": "Feature",
  "properties": {
    "iso:country":"US",
    "sg:address":"1510 N 1st St",
    "sg:city":"Merkel",
    "sg:classifiers":[
        {
            "category":"Utilities",
            "subcategory":"Cable",
            "type":"Services"
        }
    ],
    "sg:phone":"+1 325 928 4750",
    "sg:postcode":"79536",
    "sg:province":"TX",
    "sg:tags":[
        "television"
    ],
    "wof:name":"CMA Cablevision Of West Texas",
    "wof:placetype":"venue"
},
  "geometry": {"coordinates":[-100.01746799999999,32.471358],"type":"Point"}
}