{
  "type": "Feature",
  "properties": {
    "iso:country":"US",
    "sg:address":"11209 N Lamar Blvd",
    "sg:city":"Austin",
    "sg:classifiers":[
        {
            "category":"Personal",
            "subcategory":"Beauty Salon",
            "type":"Services"
        }
    ],
    "sg:phone":"+1 512 837 3247",
    "sg:postcode":"78753",
    "sg:province":"TX",
    "wof:name":"Mimosa's Hair & Nail Design",
    "wof:placetype":"venue"
},
  "geometry": {"coordinates":[-97.6871,30.380443],"type":"Point"}
}