{
  "type": "Feature",
  "properties": {
    "iso:country":"US",
    "sg:address":"2900 Fredericksburg Rd",
    "sg:city":"San Antonio",
    "sg:classifiers":[
        {
            "category":"Banks & Credit Unions",
            "subcategory":"Financial Services",
            "type":"Services"
        }
    ],
    "sg:phone":"+1 210 734 4311",
    "sg:postcode":"78201",
    "sg:province":"TX",
    "sg:tags":[
        "company",
        "holding"
    ],
    "wof:name":"Jefferson Bancshares Inc",
    "wof:placetype":"venue"
},
  "geometry": {"coordinates":[-98.53230000000001,29.470717],"type":"Point"}
}