{
  "type": "Feature",
  "properties": {
    "iso:country":"US",
    "sg:address":"218 Williams Ave",
    "sg:city":"Odessa",
    "sg:classifiers":[
        {
            "category":"Building & Trades",
            "subcategory":"Electrical",
            "type":"Services"
        }
    ],
    "sg:phone":"+1 432 580 9000",
    "sg:postcode":"79763",
    "sg:province":"TX",
    "sg:tags":[
        "electric",
        "contractor"
    ],
    "sg:website":"www.dixielectric.com",
    "wof:name":"Dixie Electric Inc",
    "wof:placetype":"venue"
},
  "geometry": {"coordinates":[-102.388672,31.830819],"type":"Point"}
}