{
  "type": "Feature",
  "properties": {
    "iso:country":"US",
    "sg:address":"408 W Davis St",
    "sg:city":"Dallas",
    "sg:classifiers":[
        {
            "category":"Building & Trades",
            "subcategory":"Plumbing",
            "type":"Services"
        }
    ],
    "sg:phone":"+1 214 942 8922",
    "sg:postcode":"75208",
    "sg:province":"TX",
    "sg:tags":[
        "contractor"
    ],
    "wof:name":"A Abel Plumbing Co",
    "wof:placetype":"venue"
},
  "geometry": {"coordinates":[-96.829043,32.749374],"type":"Point"}
}