{
  "type": "Feature",
  "properties": {
    "iso:country":"US",
    "sg:address":"5411 Feagan St",
    "sg:city":"Houston",
    "sg:classifiers":[
        {
            "category":"Manufacturing",
            "subcategory":"Wood Products",
            "type":"Manufacturing & Wholesale Goods"
        },
        {
            "category":"Professional",
            "subcategory":"Art Services",
            "type":"Services"
        }
    ],
    "sg:phone":"+1 713 869 5861",
    "sg:postcode":"77007",
    "sg:province":"TX",
    "sg:tags":[
        "picture",
        "frame",
        "frames-wholesale",
        "manufacturer"
    ],
    "wof:name":"National Art Svc Co Inc",
    "wof:placetype":"venue"
},
  "geometry": {"coordinates":[-95.41644599999999,29.765927],"type":"Point"}
}