{
  "type": "Feature",
  "properties": {
    "iso:country":"US",
    "sg:address":"9453 Katy Fwy",
    "sg:city":"Houston",
    "sg:classifiers":[
        {
            "category":"Shopping",
            "subcategory":"Optical Goods",
            "type":"Retail Goods"
        }
    ],
    "sg:phone":"+1 713 468 6648",
    "sg:postcode":"77024",
    "sg:province":"TX",
    "wof:name":"Eye Masters",
    "wof:placetype":"venue"
},
  "geometry": {"coordinates":[-95.525235,29.783716],"type":"Point"}
}