{
  "type": "Feature",
  "properties": {
    "iso:country":"US",
    "sg:address":"124 S Carroll Ave",
    "sg:city":"Dallas",
    "sg:classifiers":[
        {
            "category":"Banks & Credit Unions",
            "subcategory":"Investment Brokerage",
            "type":"Services"
        }
    ],
    "sg:phone":"+1 214 821 5459",
    "sg:postcode":"75226",
    "sg:province":"TX",
    "sg:tags":[
        "advisory",
        "financial"
    ],
    "wof:name":"Rubarza Financial Svc",
    "wof:placetype":"venue"
},
  "geometry": {"coordinates":[-96.766553,32.790794],"type":"Point"}
}