{
  "type": "Feature",
  "properties": {
    "iso:country":"US",
    "sg:address":"3505 Falcon Way",
    "sg:city":"Conroe",
    "sg:classifiers":[
        {
            "category":"Retail",
            "subcategory":"Veterinary Services",
            "type":"Services"
        }
    ],
    "sg:phone":"+1 936 756 3318",
    "sg:postcode":"77304",
    "sg:province":"TX",
    "sg:tags":[
        "veterinarian"
    ],
    "wof:name":"Triangle Animal Clinic",
    "wof:placetype":"venue"
},
  "geometry": {"coordinates":[-95.52129100000001,30.351169],"type":"Point"}
}