{
  "type": "Feature",
  "properties": {
    "iso:country":"US",
    "sg:address":"3615 Tidwell Rd",
    "sg:city":"Houston",
    "sg:classifiers":[
        {
            "category":"Autos & Motor Vehicles",
            "subcategory":"Fuel & Gas Station",
            "type":"Retail Goods"
        }
    ],
    "sg:phone":"+1 713 695 2509",
    "sg:postcode":"77093",
    "sg:province":"TX",
    "wof:name":"Texas Petroleum Grp",
    "wof:placetype":"venue"
},
  "geometry": {"coordinates":[-95.332891,29.848919],"type":"Point"}
}