{
  "type": "Feature",
  "properties": {
    "iso:country":"US",
    "sg:address":"2804 Ryan Place Dr",
    "sg:city":"Fort Worth",
    "sg:classifiers":[
        {
            "category":"Shopping",
            "subcategory":"Gifts & Souvenirs",
            "type":"Retail Goods"
        }
    ],
    "sg:phone":"+1 817 921 6005",
    "sg:postcode":"76110",
    "sg:province":"TX",
    "wof:name":"Nancraft",
    "wof:placetype":"venue"
},
  "geometry": {"coordinates":[-97.338036,32.709636],"type":"Point"}
}