{
  "type": "Feature",
  "properties": {
    "iso:country":"US",
    "sg:address":"1233 Covina Ct",
    "sg:city":"Allen",
    "sg:classifiers":[
        {
            "category":"Manufacturing",
            "subcategory":"Printing",
            "type":"Manufacturing & Wholesale Goods"
        }
    ],
    "sg:phone":"+1 214 509 9340",
    "sg:postcode":"75013",
    "sg:province":"TX",
    "sg:tags":[
        "art",
        "mfg",
        "needle",
        "greeting",
        "design",
        "cards"
    ],
    "wof:name":"Bizzi Creations",
    "wof:placetype":"venue"
},
  "geometry": {"coordinates":[-96.698971,33.094103],"type":"Point"}
}