{
  "type": "Feature",
  "properties": {
    "iso:country":"US",
    "sg:address":"1404 Meriden Ln",
    "sg:city":"Austin",
    "sg:classifiers":[
        {
            "category":"Professional",
            "type":"Services"
        }
    ],
    "sg:phone":"+1 512 476 4117",
    "sg:postcode":"78703",
    "sg:province":"TX",
    "wof:name":"Ned D Ewart",
    "wof:placetype":"venue"
},
  "geometry": {"coordinates":[-97.76688300000001,30.286167],"type":"Point"}
}