{
  "type": "Feature",
  "properties": {
    "iso:country":"US",
    "sg:address":"8055 Eastex Fwy",
    "sg:city":"Beaumont",
    "sg:classifiers":[
        {
            "category":"Wholesale",
            "subcategory":"Farm Supplies",
            "type":"Manufacturing & Wholesale Goods"
        }
    ],
    "sg:phone":"+1 409 892 1949",
    "sg:postcode":"77708",
    "sg:province":"TX",
    "wof:name":"Tractor Supply Co",
    "wof:placetype":"venue"
},
  "geometry": {"coordinates":[-94.17995500000001,30.149002],"type":"Point"}
}