{
  "type": "Feature",
  "properties": {
    "iso:country":"US",
    "sg:address":"1745 N Belt Line Rd",
    "sg:city":"Mesquite",
    "sg:classifiers":[
        {
            "category":"Food & Beverages",
            "subcategory":"Groceries & Convenience Stores",
            "type":"Retail Goods"
        }
    ],
    "sg:phone":"+1 972 290 9709",
    "sg:postcode":"75149",
    "sg:province":"TX",
    "wof:name":"Kwikway Food Store",
    "wof:placetype":"venue"
},
  "geometry": {"coordinates":[-96.595888,32.783693],"type":"Point"}
}