{
  "type": "Feature",
  "properties": {
    "iso:country":"US",
    "sg:address":"415 Owen Ln",
    "sg:city":"Waco",
    "sg:classifiers":[
        {
            "category":"Building & Trades",
            "subcategory":"Landscaping Services",
            "type":"Services"
        }
    ],
    "sg:phone":"+1 254 776 4326",
    "sg:postcode":"76710",
    "sg:province":"TX",
    "wof:name":"Fitzhugh Lawn Care",
    "wof:placetype":"venue"
},
  "geometry": {"coordinates":[-97.193354,31.516357],"type":"Point"}
}