{
  "type": "Feature",
  "properties": {
    "iso:country":"US",
    "sg:address":"501 S Lynn Ave",
    "sg:city":"Lamesa",
    "sg:phone":"+1 806 872 5200",
    "sg:postcode":"79331",
    "sg:province":"TX",
    "sg:tags":[
        "oil",
        "gasoline"
    ],
    "wof:name":"Lamesa Butane",
    "wof:placetype":"venue"
},
  "geometry": {"coordinates":[-101.948093,32.729586],"type":"Point"}
}