{
  "type": "Feature",
  "properties": {
    "iso:country":"US",
    "sg:address":"6101 Dyer St",
    "sg:city":"El Paso",
    "sg:classifiers":[
        {
            "category":"Bars & Pubs",
            "type":"Food & Drink"
        }
    ],
    "sg:phone":"+1 915 566 8226",
    "sg:postcode":"79904",
    "sg:province":"TX",
    "sg:tags":[
        "club",
        "night"
    ],
    "wof:name":"Big Sister's Lounge",
    "wof:placetype":"venue"
},
  "geometry": {"coordinates":[-106.44521400000001,31.83398],"type":"Point"}
}