{
  "type": "Feature",
  "properties": {
    "iso:country":"US",
    "sg:address":"124 W Pioneer Pkwy",
    "sg:city":"Arlington",
    "sg:classifiers":[
        {
            "category":"Banks & Credit Unions",
            "subcategory":"Bank",
            "type":"Services"
        }
    ],
    "sg:phone":"+1 817 469 1771",
    "sg:postcode":"76010",
    "sg:province":"TX",
    "sg:tags":[
        "loan",
        "real estate"
    ],
    "wof:name":"Asia Financial Group",
    "wof:placetype":"venue"
},
  "geometry": {"coordinates":[-97.108947,32.707946],"type":"Point"}
}