{
  "type": "Feature",
  "properties": {
    "iso:country":"US",
    "sg:address":"4312 W Crawford St",
    "sg:city":"Denison",
    "sg:classifiers":[
        {
            "category":"Retail",
            "subcategory":"Funeral Services",
            "type":"Services"
        }
    ],
    "sg:phone":"+1 903 463 6300",
    "sg:postcode":"75020",
    "sg:province":"TX",
    "sg:tags":[
        "director"
    ],
    "wof:name":"American Funeral Svc",
    "wof:placetype":"venue"
},
  "geometry": {"coordinates":[-96.60260700000001,33.744983],"type":"Point"}
}