{
  "type": "Feature",
  "properties": {
    "iso:country":"US",
    "sg:address":"12335 Antoine Dr",
    "sg:city":"Houston",
    "sg:classifiers":[
        {
            "category":"Building & Trades",
            "subcategory":"Landscaping Services",
            "type":"Services"
        }
    ],
    "sg:phone":"+1 281 444 7385",
    "sg:postcode":"77067",
    "sg:province":"TX",
    "wof:name":"Mendez Lawn Care",
    "wof:placetype":"venue"
},
  "geometry": {"coordinates":[-95.474558,29.963064],"type":"Point"}
}