{
  "type": "Feature",
  "properties": {
    "iso:country":"US",
    "sg:address":"16221 Jersey Dr",
    "sg:city":"Houston",
    "sg:classifiers":[
        {
            "category":"Building & Trades",
            "subcategory":"Construction",
            "type":"Services"
        }
    ],
    "sg:phone":"+1 713 466 4882",
    "sg:postcode":"77040",
    "sg:province":"TX",
    "sg:tags":[
        "addition",
        "residential",
        "remodeling"
    ],
    "wof:name":"Smith-Barry Unlimited",
    "wof:placetype":"venue"
},
  "geometry": {"coordinates":[-95.571032,29.884877],"type":"Point"}
}