{
  "type": "Feature",
  "properties": {
    "iso:country":"US",
    "sg:address":"1472 N Hampton Rd",
    "sg:city":"De Soto",
    "sg:classifiers":[
        {
            "category":"Building & Trades",
            "subcategory":"Construction",
            "type":"Services"
        }
    ],
    "sg:phone":"+1 972 230 2372",
    "sg:postcode":"75115",
    "sg:province":"TX",
    "sg:tags":[
        "house"
    ],
    "wof:name":"Concepts Construction",
    "wof:placetype":"venue"
},
  "geometry": {"coordinates":[-96.856863,32.617981],"type":"Point"}
}