{
  "type": "Feature",
  "properties": {
    "iso:country":"US",
    "sg:address":"406 43rd St",
    "sg:city":"Orange",
    "sg:classifiers":[
        {
            "category":"Shopping",
            "subcategory":"Computers & Home Electronics",
            "type":"Retail Goods"
        }
    ],
    "sg:phone":"+1 409 886 7343",
    "sg:postcode":"77630",
    "sg:province":"TX",
    "sg:tags":[
        "equipment",
        "metal",
        "locating"
    ],
    "wof:name":"Berry's Metal Detector Sales",
    "wof:placetype":"venue"
},
  "geometry": {"coordinates":[-93.78957,30.084536],"type":"Point"}
}