{
  "type": "Feature",
  "properties": {
    "iso:country":"US",
    "sg:address":"2154 Chenault Dr",
    "sg:city":"Carrollton",
    "sg:classifiers":[
        {
            "category":"Shopping",
            "subcategory":"Department Store",
            "type":"Retail Goods"
        }
    ],
    "sg:phone":"+1 972 488 2626",
    "sg:postcode":"75006",
    "sg:province":"TX",
    "sg:website":"www.sears.com",
    "wof:name":"Sears",
    "wof:placetype":"venue"
},
  "geometry": {"coordinates":[-96.844724,32.966113],"type":"Point"}
}