{
  "type": "Feature",
  "properties": {
    "iso:country":"US",
    "sg:address":"9261 Mc Cabe Dr",
    "sg:city":"El Paso",
    "sg:classifiers":[
        {
            "category":"Building & Trades",
            "subcategory":"Construction",
            "type":"Services"
        }
    ],
    "sg:phone":"+1 915 594 8425",
    "sg:postcode":"79925",
    "sg:province":"TX",
    "sg:tags":[
        "builder",
        "operative"
    ],
    "wof:name":"Harrison Homes Software",
    "wof:placetype":"venue"
},
  "geometry": {"coordinates":[-106.362647,31.776118],"type":"Point"}
}