{
  "type": "Feature",
  "properties": {
    "iso:country":"US",
    "sg:address":"5537 Shirley Dr",
    "sg:city":"Tyler",
    "sg:classifiers":[
        {
            "category":"Wholesale",
            "subcategory":"Machinery & Supplies",
            "type":"Manufacturing & Wholesale Goods"
        }
    ],
    "sg:phone":"+1 903 593 2899",
    "sg:postcode":"75708",
    "sg:province":"TX",
    "sg:tags":[
        "janitor"
    ],
    "wof:name":"Baxter Sales Co",
    "wof:placetype":"venue"
},
  "geometry": {"coordinates":[-95.26469299999999,32.384238],"type":"Point"}
}