{
  "type": "Feature",
  "properties": {
    "iso:country":"US",
    "sg:address":"11311 Reeder Rd.",
    "sg:city":"Dallas",
    "sg:classifiers":[
        {
            "category":"Shopping",
            "subcategory":"Jewelry",
            "type":"Retail Goods"
        },
        {
            "category":"Manufacturing",
            "subcategory":"Jewelry",
            "type":"Manufacturing & Wholesale Goods"
        }
    ],
    "sg:phone":"+1 972 481 3800",
    "sg:postcode":"75229",
    "sg:province":"TX",
    "sg:tags":[
        "platinum",
        "diamond",
        "gold",
        "buyer",
        "silver",
        "appraiser"
    ],
    "sg:website":"http://www.dgse.com",
    "wof:name":"Dallas Gold & SIlver Exchange",
    "wof:placetype":"venue"
},
  "geometry": {"coordinates":[-96.89601999999999,32.893215],"type":"Point"}
}