{
  "type": "Feature",
  "properties": {
    "iso:country":"US",
    "sg:address":"2850 Ruidosa Ave",
    "sg:city":"Dallas",
    "sg:classifiers":[
        {
            "category":"Government",
            "subcategory":"Fire Station",
            "type":"Public Place"
        }
    ],
    "sg:phone":"+1 214 670 5085",
    "sg:postcode":"75228",
    "sg:province":"TX",
    "sg:tags":[
        "protection"
    ],
    "wof:name":"Fire Station 39",
    "wof:placetype":"venue"
},
  "geometry": {"coordinates":[-96.666861,32.84554],"type":"Point"}
}