{
  "type": "Feature",
  "properties": {
    "iso:country":"US",
    "sg:address":"1125 Co Rd 705",
    "sg:city":"Joshua",
    "sg:classifiers":[
        {
            "category":"Retail",
            "subcategory":"Repair Shop",
            "type":"Services"
        }
    ],
    "sg:phone":"+1 817 558 7425",
    "sg:postcode":"76058",
    "sg:province":"TX",
    "sg:tags":[
        "welding"
    ],
    "wof:name":"T's Specialties",
    "wof:placetype":"venue"
},
  "geometry": {"coordinates":[-97.363204,32.43345],"type":"Point"}
}