{
  "type": "Feature",
  "properties": {
    "iso:country":"US",
    "sg:address":"6450 Phelan Blvd",
    "sg:city":"Beaumont",
    "sg:classifiers":[
        {
            "category":"Home & Garden",
            "subcategory":"Furniture",
            "type":"Retail Goods"
        }
    ],
    "sg:phone":"+1 409 866 2646",
    "sg:postcode":"77706",
    "sg:province":"TX",
    "wof:name":"Ashley Furniture Home Store",
    "wof:placetype":"venue"
},
  "geometry": {"coordinates":[-94.169302,30.078233],"type":"Point"}
}