{
  "type": "Feature",
  "properties": {
    "iso:country":"US",
    "sg:address":"4701 Altamesa Blvd",
    "sg:city":"Fort Worth",
    "sg:classifiers":[
        {
            "category":"Insurance",
            "subcategory":"Insurance Agent",
            "type":"Services"
        }
    ],
    "sg:phone":"+1 817 370 7150",
    "sg:postcode":"76133",
    "sg:province":"TX",
    "wof:name":"Aflac",
    "wof:placetype":"venue"
},
  "geometry": {"coordinates":[-97.39700499999999,32.647841],"type":"Point"}
}