{
  "type": "Feature",
  "properties": {
    "iso:country":"US",
    "sg:address":"2215 N Zarzamora",
    "sg:city":"San Antonio",
    "sg:classifiers":[
        {
            "category":"Retail",
            "subcategory":"Auto Repair",
            "type":"Services"
        }
    ],
    "sg:phone":"+1 210 734 6622",
    "sg:postcode":"78201",
    "sg:province":"TX",
    "sg:tags":[
        "general"
    ],
    "wof:name":"Tony & Sons Garage Auto Repair",
    "wof:placetype":"venue"
},
  "geometry": {"coordinates":[-98.524235,29.451457],"type":"Point"}
}