{
  "type": "Feature",
  "properties": {
    "iso:country":"US",
    "sg:address":"111 S Union Ave",
    "sg:city":"New Braunfels",
    "sg:classifiers":[
        {
            "category":"Shopping",
            "subcategory":"Florist",
            "type":"Retail Goods"
        }
    ],
    "sg:phone":"+1 830 629 1604",
    "sg:postcode":"78130",
    "sg:province":"TX",
    "wof:name":"Blumen Meisters",
    "wof:placetype":"venue"
},
  "geometry": {"coordinates":[-98.119113,29.709122],"type":"Point"}
}