{
  "type": "Feature",
  "properties": {
    "iso:country":"US",
    "sg:address":"110 Co Rd 1200",
    "sg:city":"Fairfield",
    "sg:classifiers":[
        {
            "category":"Mining & Drilling",
            "type":"Manufacturing & Wholesale Goods"
        }
    ],
    "sg:phone":"+1 903 389 9183",
    "sg:postcode":"75840",
    "sg:province":"TX",
    "sg:tags":[
        "field"
    ],
    "wof:name":"Advanced Completion Systems",
    "wof:placetype":"venue"
},
  "geometry": {"coordinates":[-96.20807499999999,31.751714],"type":"Point"}
}