{
  "type": "Feature",
  "properties": {
    "iso:country":"US",
    "sg:address":"517 S Texas Blvd",
    "sg:city":"Weslaco",
    "sg:classifiers":[
        {
            "category":"Professional",
            "subcategory":"Business Services",
            "type":"Services"
        }
    ],
    "sg:phone":"+1 956 973 1665",
    "sg:postcode":"78596",
    "sg:province":"TX",
    "sg:tags":[
        "paper"
    ],
    "wof:name":"Lone Star Shredding",
    "wof:placetype":"venue"
},
  "geometry": {"coordinates":[-97.99055799999999,26.15681],"type":"Point"}
}