{
  "type": "Feature",
  "properties": {
    "iso:country":"US",
    "sg:address":"10660 Co Rd 577",
    "sg:city":"Blue Ridge",
    "sg:classifiers":[
        {
            "category":"Home & Garden",
            "subcategory":"Building Materials",
            "type":"Retail Goods"
        }
    ],
    "sg:phone":"+1 972 752 5443",
    "sg:postcode":"75424",
    "sg:province":"TX",
    "sg:tags":[
        "door"
    ],
    "wof:name":"All American Garage Doors",
    "wof:placetype":"venue"
},
  "geometry": {"coordinates":[-96.42754499999999,33.312897],"type":"Point"}
}