{
  "type": "Feature",
  "properties": {
    "iso:country":"US",
    "sg:address":"8080 Park Lane Ste 770",
    "sg:city":"Dallas",
    "sg:classifiers":[
        {
            "category":"Professional",
            "type":"Services"
        },
        {
            "category":"Personal",
            "type":"Services"
        }
    ],
    "sg:phone":"+1 214 777 5100",
    "sg:postcode":"75231",
    "sg:province":"TX",
    "sg:tags":[
        "local"
    ],
    "sg:website":"www.brg.com",
    "wof:name":"BRG - Business Resource Group",
    "wof:placetype":"venue"
},
  "geometry": {"coordinates":[-96.767967,32.870892],"type":"Point"}
}