{
  "type": "Feature",
  "properties": {
    "iso:country":"US",
    "sg:address":"11555 Louetta Rd",
    "sg:city":"Houston",
    "sg:classifiers":[
        {
            "category":"Retail",
            "subcategory":"Storage",
            "type":"Services"
        }
    ],
    "sg:phone":"+1 832 717 1708",
    "sg:postcode":"77070",
    "sg:province":"TX",
    "sg:tags":[
        "self",
        "commercial",
        "household",
        "boat"
    ],
    "sg:website":"http://www.morningstarstorage.com/louettaroad/houston/tx/77070/mini-storage-location.php",
    "wof:name":"Morningstar Mini-Storage of Louetta Road",
    "wof:placetype":"venue"
},
  "geometry": {"coordinates":[-95.592838,29.99661],"type":"Point"}
}