{
  "type": "Feature",
  "properties": {
    "iso:country":"US",
    "sg:address":"2914 Windy Gorge Ct",
    "sg:city":"Humble",
    "sg:classifiers":[
        {
            "category":"Building & Trades",
            "subcategory":"Construction",
            "type":"Services"
        }
    ],
    "sg:phone":"+1 281 361 7854",
    "sg:postcode":"77345",
    "sg:province":"TX",
    "sg:tags":[
        "contractor"
    ],
    "wof:name":"Houston Cool Pools",
    "wof:placetype":"venue"
},
  "geometry": {"coordinates":[-95.174083,30.07817],"type":"Point"}
}