{
  "type": "Feature",
  "properties": {
    "iso:country":"US",
    "sg:address":"14230 Cross Canyon",
    "sg:city":"San Antonio",
    "sg:classifiers":[
        {
            "category":"Social Services",
            "subcategory":"Child Care",
            "type":"Services"
        }
    ],
    "sg:phone":"+1 210 490 0187",
    "sg:postcode":"78232",
    "sg:province":"TX",
    "sg:tags":[
        "day"
    ],
    "sg:website":"www.childrensworld.com",
    "wof:name":"Children's World Learning Ctr",
    "wof:placetype":"venue"
},
  "geometry": {"coordinates":[-98.47137499999999,29.568767],"type":"Point"}
}