{
  "type": "Feature",
  "properties": {
    "iso:country":"US",
    "sg:address":"1389 Sweetgum Cir",
    "sg:city":"Keller",
    "sg:classifiers":[
        {
            "category":"Shopping",
            "subcategory":"Stationery & Office Supplies",
            "type":"Retail Goods"
        }
    ],
    "sg:phone":"+1 817 498 0665",
    "sg:postcode":"76248",
    "sg:province":"TX",
    "wof:name":"Hurricane Tarver Office Ctr",
    "wof:placetype":"venue"
},
  "geometry": {"coordinates":[-97.227313,32.906749],"type":"Point"}
}