{
  "type": "Feature",
  "properties": {
    "iso:country":"US",
    "sg:address":"1100 Airport Rd",
    "sg:city":"Terrell",
    "sg:classifiers":[
        {
            "category":"Building & Trades",
            "subcategory":"Construction",
            "type":"Services"
        }
    ],
    "sg:phone":"+1 972 551 6643",
    "sg:postcode":"75160",
    "sg:province":"TX",
    "sg:tags":[
        "marking",
        "maintenance",
        "parking"
    ],
    "wof:name":"Terrell City Street Dept",
    "wof:placetype":"venue"
},
  "geometry": {"coordinates":[-96.26093,32.712328],"type":"Point"}
}