{
  "type": "Feature",
  "properties": {
    "iso:country":"US",
    "sg:address":"2616 Windswept Ln",
    "sg:city":"Mesquite",
    "sg:classifiers":[
        {
            "category":"Building & Trades",
            "subcategory":"Construction",
            "type":"Services"
        }
    ],
    "sg:phone":"+1 972 222 6554",
    "sg:postcode":"75181",
    "sg:province":"TX",
    "sg:tags":[
        "contractor"
    ],
    "wof:name":"R&M Contractor Services",
    "wof:placetype":"venue"
},
  "geometry": {"coordinates":[-96.590405,32.731185],"type":"Point"}
}