{
  "type": "Feature",
  "properties": {
    "iso:country":"US",
    "sg:address":"808 Travis St",
    "sg:city":"Houston",
    "sg:classifiers":[
        {
            "category":"Professional",
            "subcategory":"Lawyer & Legal Services",
            "type":"Services"
        }
    ],
    "sg:phone":"+1 713 757 0679",
    "sg:postcode":"77002",
    "sg:province":"TX",
    "wof:name":"Secrest George McCall Atty",
    "wof:placetype":"venue"
},
  "geometry": {"coordinates":[-95.3647,29.7589],"type":"Point"}
}