{
  "type": "Feature",
  "properties": {
    "iso:country":"US",
    "sg:address":"120 S Main St",
    "sg:city":"La Feria",
    "sg:classifiers":[
        {
            "category":"Building & Trades",
            "subcategory":"Electrical",
            "type":"Services"
        },
        {
            "category":"Professional",
            "subcategory":"Management & Consulting",
            "type":"Services"
        }
    ],
    "sg:phone":"+1 956 797 9766",
    "sg:postcode":"78559",
    "sg:province":"TX",
    "sg:tags":[
        "consultant",
        "installation",
        "telecommunication",
        "telephone"
    ],
    "wof:name":"All Valley Communications",
    "wof:placetype":"venue"
},
  "geometry": {"coordinates":[-97.82411999999999,26.157563],"type":"Point"}
}