{
  "type": "Feature",
  "properties": {
    "iso:country":"US",
    "sg:address":"424 Windjammer Ln",
    "sg:city":"Azle",
    "sg:classifiers":[
        {
            "category":"Professional",
            "subcategory":"Business Services",
            "type":"Services"
        }
    ],
    "sg:phone":"+1 817 444 3974",
    "sg:postcode":"76020",
    "sg:province":"TX",
    "wof:name":"Technical Design Exchange LLC",
    "wof:placetype":"venue"
},
  "geometry": {"coordinates":[-97.51706799999999,32.899737],"type":"Point"}
}