{
  "type": "Feature",
  "properties": {
    "iso:country":"US",
    "sg:address":"8922 FM 765",
    "sg:city":"San Angelo",
    "sg:classifiers":[
        {
            "category":"Professional",
            "subcategory":"Management & Consulting",
            "type":"Services"
        }
    ],
    "sg:phone":"+1 325 947 9508",
    "sg:postcode":"76905",
    "sg:province":"TX",
    "sg:tags":[
        "test"
    ],
    "wof:name":"Nancy A Cooper",
    "wof:placetype":"venue"
},
  "geometry": {"coordinates":[-100.28956700000001,31.419654],"type":"Point"}
}