{
  "type": "Feature",
  "properties": {
    "iso:country":"US",
    "sg:address":"2120 Strand St",
    "sg:city":"Galveston",
    "sg:classifiers":[
        {
            "category":"Restaurant",
            "type":"Food & Drink"
        }
    ],
    "sg:phone":"+1 409 772 1533",
    "sg:postcode":"77550",
    "sg:province":"TX",
    "sg:tags":[
        "eating"
    ],
    "wof:name":"Saeed Food Services Inc",
    "wof:placetype":"venue"
},
  "geometry": {"coordinates":[-94.79304399999999,29.307594],"type":"Point"}
}