{
  "type": "Feature",
  "properties": {
    "iso:country":"US",
    "sg:address":"1722 Ascension Point Dr",
    "sg:city":"Arlington",
    "sg:classifiers":[
        {
            "category":"Professional",
            "subcategory":"Accounting & Tax Preparation",
            "type":"Services"
        }
    ],
    "sg:phone":"+1 817 303 5861",
    "sg:postcode":"76006",
    "sg:province":"TX",
    "sg:tags":[
        "statistics"
    ],
    "wof:name":"Zhou Jie",
    "wof:placetype":"venue"
},
  "geometry": {"coordinates":[-97.084357,32.776113],"type":"Point"}
}