{
  "type": "Feature",
  "properties": {
    "iso:country":"US",
    "sg:address":"1003 Patsy St",
    "sg:city":"Baytown",
    "sg:classifiers":[
        {
            "category":"Retail",
            "subcategory":"Portrait Studio",
            "type":"Services"
        }
    ],
    "sg:phone":"+1 281 428 1186",
    "sg:postcode":"77520",
    "sg:province":"TX",
    "sg:tags":[
        "photo"
    ],
    "wof:name":"Sam Compton Photography",
    "wof:placetype":"venue"
},
  "geometry": {"coordinates":[-94.953141,29.742679],"type":"Point"}
}