{
  "type": "Feature",
  "properties": {
    "iso:country":"US",
    "sg:address":"75 Lake Forest Cir",
    "sg:city":"Conroe",
    "sg:classifiers":[
        {
            "category":"Home & Garden",
            "subcategory":"Furniture",
            "type":"Retail Goods"
        }
    ],
    "sg:phone":"+1 936 321 2534",
    "sg:postcode":"77384",
    "sg:province":"TX",
    "wof:name":"Display & Play",
    "wof:placetype":"venue"
},
  "geometry": {"coordinates":[-95.54078699999999,30.25847],"type":"Point"}
}