{
  "type": "Feature",
  "properties": {
    "iso:country":"US",
    "sg:address":"2420 Rice Blvd # B",
    "sg:city":"Houston",
    "sg:classifiers":[
        {
            "category":"Restaurant",
            "type":"Food & Drink"
        }
    ],
    "sg:phone":"+1 713 528 6998",
    "sg:postcode":"77005",
    "sg:province":"TX",
    "sg:tags":[
        "thai"
    ],
    "wof:name":"Patu's Thai Cuisine",
    "wof:placetype":"venue"
},
  "geometry": {"coordinates":[-95.415802,29.7176],"type":"Point"}
}