{
  "type": "Feature",
  "properties": {
    "iso:country":"US",
    "sg:address":"330 W Texas Ave",
    "sg:city":"Waskom",
    "sg:classifiers":[
        {
            "category":"Food & Beverages",
            "subcategory":"Groceries & Convenience Stores",
            "type":"Retail Goods"
        }
    ],
    "sg:phone":"+1 903 687 3693",
    "sg:postcode":"75692",
    "sg:province":"TX",
    "sg:tags":[
        "grocer"
    ],
    "wof:name":"Hall's Super Store Inc",
    "wof:placetype":"venue"
},
  "geometry": {"coordinates":[-94.074073,32.479284],"type":"Point"}
}