{
  "type": "Feature",
  "properties": {
    "iso:country":"US",
    "sg:address":"1500 W Park Ave",
    "sg:city":"Hereford",
    "sg:classifiers":[
        {
            "category":"Health Services",
            "subcategory":"Doctor",
            "type":"Services"
        },
        {
            "category":"Health Services",
            "subcategory":"Health Practitioner",
            "type":"Services"
        },
        {
            "category":"Professional",
            "subcategory":"Business Services",
            "type":"Services"
        }
    ],
    "sg:phone":"+1 806 364 5422",
    "sg:postcode":"79045",
    "sg:province":"TX",
    "sg:tags":[
        "nutritionist",
        "physician",
        "surgeon",
        "coach",
        "consultant"
    ],
    "wof:name":"Hoelscher Marcus A DR Consulting Nutritionist & Feed Consultants",
    "wof:placetype":"venue"
},
  "geometry": {"coordinates":[-102.42214300000001,34.822298],"type":"Point"}
}