{
  "type": "Feature",
  "properties": {
    "iso:country":"US",
    "sg:address":"1000 Sagemont Dr",
    "sg:city":"Wimberley",
    "sg:classifiers":[
        {
            "category":"Building & Trades",
            "subcategory":"Construction",
            "type":"Services"
        }
    ],
    "sg:phone":"+1 512 847 7975",
    "sg:postcode":"78676",
    "sg:province":"TX",
    "sg:tags":[
        "house",
        "land",
        "leveling",
        "clearing"
    ],
    "wof:name":"Greater Wimberley Construction",
    "wof:placetype":"venue"
},
  "geometry": {"coordinates":[-98.08462900000001,30.044425],"type":"Point"}
}