{
  "type": "Feature",
  "properties": {
    "iso:country":"US",
    "sg:address":"5636 Costa Blanca Pl",
    "sg:city":"El Paso",
    "sg:classifiers":[
        {
            "category":"Retail",
            "subcategory":"Laundry & Dry Cleaning",
            "type":"Services"
        }
    ],
    "sg:phone":"+1 915 584 0142",
    "sg:postcode":"79932",
    "sg:province":"TX",
    "wof:name":"Advance Chem Dry",
    "wof:placetype":"venue"
},
  "geometry": {"coordinates":[-106.593626,31.864221],"type":"Point"}
}