{
  "type": "Feature",
  "properties": {
    "iso:country":"US",
    "sg:address":"5121 Fredericksburg Rd",
    "sg:city":"San Antonio",
    "sg:classifiers":[
        {
            "category":"Restaurant",
            "type":"Food & Drink"
        }
    ],
    "sg:phone":"+1 210 340 7857",
    "sg:postcode":"78229",
    "sg:province":"TX",
    "sg:tags":[
        "caterer"
    ],
    "wof:name":"Baron Catering",
    "wof:placetype":"venue"
},
  "geometry": {"coordinates":[-98.560399,29.502787],"type":"Point"}
}