{
  "type": "Feature",
  "properties": {
    "iso:country":"US",
    "sg:address":"4661 Concord Rd",
    "sg:city":"Beaumont",
    "sg:classifiers":[
        {
            "category":"Personal",
            "subcategory":"Beauty Salon",
            "type":"Services"
        }
    ],
    "sg:phone":"+1 409 832 1686",
    "sg:postcode":"77703",
    "sg:province":"TX",
    "sg:tags":[
        "school",
        "cosmetology"
    ],
    "wof:name":"Lonnies School of Hair Design",
    "wof:placetype":"venue"
},
  "geometry": {"coordinates":[-94.13934399999999,30.118737],"type":"Point"}
}