{
  "type": "Feature",
  "properties": {
    "iso:country":"US",
    "sg:address":"11522 Wind Tree",
    "sg:city":"San Antonio",
    "sg:classifiers":[
        {
            "category":"Wholesale",
            "subcategory":"Computers",
            "type":"Manufacturing & Wholesale Goods"
        }
    ],
    "sg:phone":"+1 210 679 8501",
    "sg:postcode":"78253",
    "sg:province":"TX",
    "sg:tags":[
        "information",
        "product",
        "technology"
    ],
    "wof:name":"Pante Technology Corporation",
    "wof:placetype":"venue"
},
  "geometry": {"coordinates":[-98.714034,29.441124],"type":"Point"}
}