{
  "type": "Feature",
  "properties": {
    "iso:country":"US",
    "sg:address":"11260 N Central Expy",
    "sg:city":"Dallas",
    "sg:classifiers":[
        {
            "category":"Cinema",
            "subcategory":"Movie Rental",
            "type":"Entertainment"
        }
    ],
    "sg:phone":"+1 214 369 3457",
    "sg:postcode":"75243",
    "sg:province":"TX",
    "sg:tags":[
        "video",
        "tape"
    ],
    "wof:name":"Blockbuster",
    "wof:placetype":"venue"
},
  "geometry": {"coordinates":[-96.769519,32.900867],"type":"Point"}
}