{
  "type": "Feature",
  "properties": {
    "iso:country":"US",
    "sg:address":"9323 Eagle Creek Ln",
    "sg:city":"Houston",
    "sg:classifiers":[
        {
            "category":"Social Services",
            "subcategory":"Child Care",
            "type":"Services"
        }
    ],
    "sg:phone":"+1 713 779 3232",
    "sg:postcode":"77036",
    "sg:province":"TX",
    "wof:name":"Nguyen Ngocdung Thi",
    "wof:placetype":"venue"
},
  "geometry": {"coordinates":[-95.554508,29.682571],"type":"Point"}
}