{
  "type": "Feature",
  "properties": {
    "iso:country":"US",
    "sg:address":"14241 Dallas Pkwy",
    "sg:city":"Dallas",
    "sg:classifiers":[
        {
            "category":"Professional",
            "subcategory":"Employment Agencies",
            "type":"Services"
        }
    ],
    "sg:phone":"+1 972 720 1020",
    "sg:postcode":"75254",
    "sg:province":"TX",
    "sg:tags":[
        "opportunity",
        "contractor"
    ],
    "sg:website":"http://www.qarecruiting.com",
    "wof:name":"Q & A Recruiting",
    "wof:placetype":"venue"
},
  "geometry": {"coordinates":[-96.82225800000001,32.940813],"type":"Point"}
}