{
  "type": "Feature",
  "properties": {
    "iso:country":"US",
    "sg:address":"700 S Zarzamora",
    "sg:city":"San Antonio",
    "sg:classifiers":[
        {
            "category":"Health Services",
            "subcategory":"Doctor",
            "type":"Services"
        }
    ],
    "sg:phone":"+1 210 433 3334",
    "sg:postcode":"78207",
    "sg:province":"TX",
    "sg:tags":[
        "physician",
        "surgeon"
    ],
    "wof:name":"Lucina B Trevino MD",
    "wof:placetype":"venue"
},
  "geometry": {"coordinates":[-98.52788099999999,29.420789],"type":"Point"}
}