{
  "type": "Feature",
  "properties": {
    "iso:country":"US",
    "sg:address":"541 Rolling Block Dr",
    "sg:city":"Liberty Hill",
    "sg:classifiers":[
        {
            "category":"Building & Trades",
            "subcategory":"Plumbing",
            "type":"Services"
        }
    ],
    "sg:phone":"+1 512 355 2494",
    "sg:postcode":"78642",
    "sg:province":"TX",
    "sg:tags":[
        "contractor"
    ],
    "wof:name":"Altek Plumbing",
    "wof:placetype":"venue"
},
  "geometry": {"coordinates":[-98.009067,30.688387],"type":"Point"}
}