{
  "type": "Feature",
  "properties": {
    "iso:country":"US",
    "sg:address":"1402 Vassar St",
    "sg:city":"Houston",
    "sg:classifiers":[
        {
            "category":"Building & Trades",
            "subcategory":"Construction",
            "type":"Services"
        }
    ],
    "sg:phone":"+1 713 529 7663",
    "sg:postcode":"77006",
    "sg:province":"TX",
    "sg:tags":[
        "contractor"
    ],
    "wof:name":"Solid Construction & Roofing",
    "wof:placetype":"venue"
},
  "geometry": {"coordinates":[-95.39827,29.730567],"type":"Point"}
}