{
  "type": "Feature",
  "properties": {
    "iso:country":"US",
    "sg:address":"2301 W Plano Pkwy",
    "sg:city":"Plano",
    "sg:classifiers":[
        {
            "category":"Real Estate",
            "subcategory":"Real Estate Services",
            "type":"Services"
        },
        {
            "category":"Real Estate",
            "subcategory":"Real Estate Agent",
            "type":"Services"
        }
    ],
    "sg:phone":"+1 972 312 0903",
    "sg:postcode":"75075",
    "sg:province":"TX",
    "sg:tags":[
        "buyer",
        "broker"
    ],
    "wof:name":"PM. Reality Group",
    "wof:placetype":"venue"
},
  "geometry": {"coordinates":[-96.74311899999999,33.008073],"type":"Point"}
}