{
  "type": "Feature",
  "properties": {
    "iso:country":"US",
    "sg:address":"2160 N Collins St",
    "sg:city":"Arlington",
    "sg:classifiers":[
        {
            "category":"Home & Garden",
            "subcategory":"Furniture",
            "type":"Retail Goods"
        }
    ],
    "sg:phone":"+1 817 261 2800",
    "sg:postcode":"76011",
    "sg:province":"TX",
    "sg:tags":[
        "store"
    ],
    "wof:name":"By Design Contemporary Furniture",
    "wof:placetype":"venue"
},
  "geometry": {"coordinates":[-97.09711299999999,32.768465],"type":"Point"}
}