{
  "type": "Feature",
  "properties": {
    "iso:country":"US",
    "sg:address":"1505 Pecan Ct",
    "sg:city":"Allen",
    "sg:classifiers":[
        {
            "category":"Manufacturing",
            "subcategory":"Tools & Machinery",
            "type":"Manufacturing & Wholesale Goods"
        }
    ],
    "sg:phone":"+1 214 495 9696",
    "sg:postcode":"75002",
    "sg:province":"TX",
    "sg:tags":[
        "optical",
        "mfg"
    ],
    "wof:name":"International Opitical Broker",
    "wof:placetype":"venue"
},
  "geometry": {"coordinates":[-96.662036,33.073474],"type":"Point"}
}