{
  "type": "Feature",
  "properties": {
    "iso:country":"US",
    "sg:address":"11204 West Ave",
    "sg:city":"San Antonio",
    "sg:classifiers":[
        {
            "category":"Personal",
            "type":"Services"
        }
    ],
    "sg:phone":"+1 210 355 2710",
    "sg:postcode":"78213",
    "sg:province":"TX",
    "sg:tags":[
        "therapist",
        "massage"
    ],
    "wof:name":"Ron Lammert Neuromuscular",
    "wof:placetype":"venue"
},
  "geometry": {"coordinates":[-98.512426,29.542792],"type":"Point"}
}