{
  "type": "Feature",
  "properties": {
    "iso:country":"US",
    "sg:address":"22040 State Hwy 16",
    "sg:city":"Von Ormy",
    "sg:classifiers":[
        {
            "category":"Utilities",
            "subcategory":"Refuse",
            "type":"Services"
        }
    ],
    "sg:phone":"+1 210 624 3000",
    "sg:postcode":"78073",
    "sg:province":"TX",
    "sg:tags":[
        "garbage",
        "collection"
    ],
    "wof:name":"Apache Disposal",
    "wof:placetype":"venue"
},
  "geometry": {"coordinates":[-98.585098,29.191979],"type":"Point"}
}