{
  "type": "Feature",
  "properties": {
    "iso:country":"US",
    "sg:address":"10407 North Fwy",
    "sg:city":"Houston",
    "sg:classifiers":[
        {
            "category":"Shopping",
            "subcategory":"Mobile Phones",
            "type":"Retail Goods"
        }
    ],
    "sg:phone":"+1 281 448 4908",
    "sg:postcode":"77037",
    "sg:province":"TX",
    "sg:website":"www.radioshack.com",
    "wof:name":"Radioshack",
    "wof:placetype":"venue"
},
  "geometry": {"coordinates":[-95.413101,29.917601],"type":"Point"}
}