{
  "type": "Feature",
  "properties": {
    "iso:country":"US",
    "sg:address":"13802 Laurel Hollow",
    "sg:city":"San Antonio",
    "sg:classifiers":[
        {
            "category":"Building & Trades",
            "subcategory":"Electrical",
            "type":"Services"
        }
    ],
    "sg:phone":"+1 210 402 6099",
    "sg:postcode":"78232",
    "sg:province":"TX",
    "sg:tags":[
        "electrical",
        "contractor"
    ],
    "wof:name":"Steve Swaney",
    "wof:placetype":"venue"
},
  "geometry": {"coordinates":[-98.462475,29.572453],"type":"Point"}
}