{
  "type": "Feature",
  "properties": {
    "iso:country":"US",
    "sg:address":"325 Yacht Club Dr",
    "sg:city":"Rockwall",
    "sg:classifiers":[
        {
            "category":"Professional",
            "subcategory":"Lawyer & Legal Services",
            "type":"Services"
        }
    ],
    "sg:phone":"+1 972 771 7228",
    "sg:postcode":"75032",
    "sg:province":"TX",
    "wof:name":"Stucker Michael W Law Office",
    "wof:placetype":"venue"
},
  "geometry": {"coordinates":[-96.48181700000001,32.878932],"type":"Point"}
}