{
  "type": "Feature",
  "properties": {
    "iso:country":"US",
    "sg:address":"1815 Meadow Creek Dr",
    "sg:city":"Pearland",
    "sg:classifiers":[
        {
            "category":"Professional",
            "subcategory":"Art Services",
            "type":"Services"
        }
    ],
    "sg:phone":"+1 281 648 1212",
    "sg:postcode":"77581",
    "sg:province":"TX",
    "sg:tags":[
        "photography",
        "commercial"
    ],
    "wof:name":"Captured Moments",
    "wof:placetype":"venue"
},
  "geometry": {"coordinates":[-95.233946,29.550933],"type":"Point"}
}