{
  "type": "Feature",
  "properties": {
    "iso:country":"US",
    "sg:address":"2908 Morton St",
    "sg:city":"Fort Worth",
    "sg:classifiers":[
        {
            "category":"Home & Garden",
            "subcategory":"Carpets & Floor Coverings",
            "type":"Retail Goods"
        }
    ],
    "sg:phone":"+1 817 920 9904",
    "sg:postcode":"76107",
    "sg:province":"TX",
    "wof:name":"Carpetsplus of America",
    "wof:placetype":"venue"
},
  "geometry": {"coordinates":[-97.360077,32.749325],"type":"Point"}
}