{
  "type": "Feature",
  "properties": {
    "iso:country":"US",
    "sg:address":"1725 Belgrade Dr",
    "sg:city":"Plano",
    "sg:classifiers":[
        {
            "category":"Building & Trades",
            "subcategory":"Construction",
            "type":"Services"
        }
    ],
    "sg:phone":"+1 972 599 9133",
    "sg:postcode":"75023",
    "sg:province":"TX",
    "sg:tags":[
        "contractor"
    ],
    "wof:name":"Plano Quality Roofing",
    "wof:placetype":"venue"
},
  "geometry": {"coordinates":[-96.72717,33.043166],"type":"Point"}
}