{
  "type": "Feature",
  "properties": {
    "iso:country":"US",
    "sg:address":"5300 N Braeswood Blvd",
    "sg:city":"Houston",
    "sg:classifiers":[
        {
            "category":"Professional",
            "subcategory":"Management & Consulting",
            "type":"Services"
        }
    ],
    "sg:phone":"+1 713 660 7553",
    "sg:postcode":"77096",
    "sg:province":"TX",
    "sg:tags":[
        "consultant",
        "real estate"
    ],
    "wof:name":"I E Properties",
    "wof:placetype":"venue"
},
  "geometry": {"coordinates":[-95.47757900000001,29.677812],"type":"Point"}
}