{
  "type": "Feature",
  "properties": {
    "iso:country":"US",
    "sg:address":"201 E 4th St",
    "sg:city":"Austin",
    "sg:classifiers":[
        {
            "category":"Professional",
            "type":"Services"
        }
    ],
    "sg:phone":"+1 512 857 0466",
    "sg:postcode":"78701",
    "sg:province":"TX",
    "wof:name":"Diva Imaging",
    "wof:placetype":"venue"
},
  "geometry": {"coordinates":[-97.741062,30.265527],"type":"Point"}
}