{
  "type": "Feature",
  "properties": {
    "iso:country":"US",
    "sg:address":"9700 Richmond Ave Ste 121",
    "sg:city":"Houston",
    "sg:classifiers":[
        {
            "category":"Professional",
            "subcategory":"Accounting & Tax Preparation",
            "type":"Services"
        }
    ],
    "sg:phone":"+1 713 977 8845",
    "sg:postcode":"77042",
    "sg:province":"TX",
    "sg:tags":[
        "accountant"
    ],
    "wof:name":"Femi Jenmy & Co CPA",
    "wof:placetype":"venue"
},
  "geometry": {"coordinates":[-95.539299,29.7278],"type":"Point"}
}