{
  "type": "Feature",
  "properties": {
    "iso:country":"US",
    "sg:address":"1350 E Euless Blvd",
    "sg:city":"Euless",
    "sg:classifiers":[
        {
            "category":"Professional",
            "subcategory":"Accounting & Tax Preparation",
            "type":"Services"
        }
    ],
    "sg:phone":"+1 817 868 1321",
    "sg:postcode":"76040",
    "sg:province":"TX",
    "sg:tags":[
        "return"
    ],
    "wof:name":"Domah Tax Express",
    "wof:placetype":"venue"
},
  "geometry": {"coordinates":[-97.102493,32.827738],"type":"Point"}
}