{
  "type": "Feature",
  "properties": {
    "iso:country":"US",
    "sg:address":"1204 N Main St",
    "sg:city":"Fort Worth",
    "sg:classifiers":[
        {
            "category":"Professional",
            "type":"Services"
        }
    ],
    "sg:phone":"+1 817 624 1767",
    "sg:postcode":"76164",
    "sg:province":"TX",
    "sg:tags":[
        "establishment"
    ],
    "wof:name":"Servicio LA Carreda",
    "wof:placetype":"venue"
},
  "geometry": {"coordinates":[-97.345046,32.775479],"type":"Point"}
}