{
  "type": "Feature",
  "properties": {
    "iso:country":"US",
    "sg:address":"5950 Sherry Ln",
    "sg:city":"Dallas",
    "sg:classifiers":[
        {
            "category":"Insurance",
            "subcategory":"Insurance Agent",
            "type":"Services"
        }
    ],
    "sg:phone":"+1 214 346 6800",
    "sg:postcode":"75225",
    "sg:province":"TX",
    "sg:website":"www.guycarp.com",
    "wof:name":"Guy Carpenter & Co",
    "wof:placetype":"venue"
},
  "geometry": {"coordinates":[-96.81008,32.862213],"type":"Point"}
}