{
  "type": "Feature",
  "properties": {
    "iso:country":"US",
    "sg:address":"330 Crestover Dr",
    "sg:city":"Richardson",
    "sg:classifiers":[
        {
            "category":"Professional",
            "subcategory":"Business Services",
            "type":"Services"
        }
    ],
    "sg:phone":"+1 972 644 1711",
    "sg:postcode":"75080",
    "sg:province":"TX",
    "wof:name":"Contour Realty Group Inc",
    "wof:placetype":"venue"
},
  "geometry": {"coordinates":[-96.72636799999999,32.977005],"type":"Point"}
}