{
  "type": "Feature",
  "properties": {
    "iso:country":"US",
    "sg:address":"1231 Alma St",
    "sg:city":"Tomball",
    "sg:classifiers":[
        {
            "category":"Shopping",
            "subcategory":"Clothing, Apparel, & Fashions",
            "type":"Retail Goods"
        }
    ],
    "sg:phone":"+1 281 351 6040",
    "sg:postcode":"77375",
    "sg:province":"TX",
    "sg:tags":[
        "western"
    ],
    "wof:name":"El Rancho Western Wear",
    "wof:placetype":"venue"
},
  "geometry": {"coordinates":[-95.62808800000001,30.090291],"type":"Point"}
}