{
  "type": "Feature",
  "properties": {
    "iso:country":"US",
    "sg:address":"2104 Lyons Ave",
    "sg:city":"Houston",
    "sg:classifiers":[
        {
            "category":"Personal",
            "type":"Services"
        }
    ],
    "sg:phone":"+1 713 228 2909",
    "sg:postcode":"77020",
    "sg:province":"TX",
    "sg:tags":[
        "towing"
    ],
    "sg:website":"www.fasttow.net/",
    "wof:name":"Fast Tow",
    "wof:placetype":"venue"
},
  "geometry": {"coordinates":[-95.3479,29.7715],"type":"Point"}
}