{
  "type": "Feature",
  "properties": {
    "iso:country":"US",
    "sg:address":"4321 General Aviation Ave.",
    "sg:city":"Austin",
    "sg:classifiers":[
        {
            "category":"Manufacturing",
            "subcategory":"Motor Vehicles & Parts",
            "type":"Manufacturing & Wholesale Goods"
        },
        {
            "category":"Airline",
            "type":"Transportation"
        },
        {
            "category":"Manufacturing",
            "subcategory":"Aerospace",
            "type":"Manufacturing & Wholesale Goods"
        },
        {
            "category":"Airport",
            "type":"Transportation"
        },
        {
            "category":"Autos & Motor Vehicles",
            "subcategory":"Recreational Vehicle Sales",
            "type":"Retail Goods"
        }
    ],
    "sg:phone":"+1 512 638 3333",
    "sg:postcode":"78719",
    "sg:province":"TX",
    "sg:tags":[
        "leasing",
        "supply",
        "aircraft-charter",
        "equipment",
        "aircraft",
        "ferry",
        "rental",
        "transport"
    ],
    "sg:website":"http://www.paradigmjet.com",
    "wof:name":"Paradigm Jet Management",
    "wof:placetype":"venue"
},
  "geometry": {"coordinates":[-97.66357000000001,30.18841],"type":"Point"}
}