{
  "type": "Feature",
  "properties": {
    "iso:country":"US",
    "sg:address":"203 Gardenia Cir",
    "sg:city":"Duncanville",
    "sg:classifiers":[
        {
            "category":"Professional",
            "subcategory":"Business Services",
            "type":"Services"
        }
    ],
    "sg:phone":"+1 972 780 7843",
    "sg:postcode":"75137",
    "sg:province":"TX",
    "wof:name":"Texas Interiors",
    "wof:placetype":"venue"
},
  "geometry": {"coordinates":[-96.906268,32.642146],"type":"Point"}
}