{
  "type": "Feature",
  "properties": {
    "iso:country":"US",
    "sg:address":"302 N Windomere Ave",
    "sg:city":"Dallas",
    "sg:classifiers":[
        {
            "category":"Deli",
            "type":"Food & Drink"
        },
        {
            "category":"Restaurant",
            "type":"Food & Drink"
        }
    ],
    "sg:phone":"+1 214 942 9749",
    "sg:postcode":"75208",
    "sg:province":"TX",
    "sg:tags":[
        "delicatessen"
    ],
    "wof:name":"Pete Stein Deli",
    "wof:placetype":"venue"
},
  "geometry": {"coordinates":[-96.84531699999999,32.747319],"type":"Point"}
}