{
  "type": "Feature",
  "properties": {
    "iso:country":"US",
    "sg:address":"2701 Broadway St",
    "sg:city":"Galveston",
    "sg:classifiers":[
        {
            "category":"Shopping",
            "subcategory":"Used Merchandise",
            "type":"Retail Goods"
        }
    ],
    "sg:phone":"+1 409 763 0827",
    "sg:postcode":"77550",
    "sg:province":"TX",
    "sg:tags":[
        "antique"
    ],
    "wof:name":"Larry's Place",
    "wof:placetype":"venue"
},
  "geometry": {"coordinates":[-94.797797,29.298567],"type":"Point"}
}