{
  "type": "Feature",
  "properties": {
    "iso:country":"US",
    "sg:address":"14911 Quorum Dr",
    "sg:city":"Dallas",
    "sg:classifiers":[
        {
            "category":"Banks & Credit Unions",
            "subcategory":"Investment Brokerage",
            "type":"Services"
        },
        {
            "category":"Professional",
            "subcategory":"Management & Consulting",
            "type":"Services"
        }
    ],
    "sg:phone":"+1 972 361 3815",
    "sg:postcode":"75254",
    "sg:province":"TX",
    "sg:tags":[
        "advisory",
        "financial"
    ],
    "wof:name":"Botsford Financial Group",
    "wof:placetype":"venue"
},
  "geometry": {"coordinates":[-96.82565099999999,32.948717],"type":"Point"}
}