{
  "type": "Feature",
  "properties": {
    "iso:country":"US",
    "sg:address":"14655 Champion Forest Dr",
    "sg:city":"Houston",
    "sg:classifiers":[
        {
            "category":"Real Estate",
            "subcategory":"Real Estate Services",
            "type":"Services"
        },
        {
            "category":"Building & Trades",
            "subcategory":"Construction",
            "type":"Services"
        },
        {
            "category":"Organizations",
            "subcategory":"Community Association",
            "type":"Services"
        }
    ],
    "sg:phone":"+1 281 583 0080",
    "sg:postcode":"77069",
    "sg:province":"TX",
    "sg:tags":[
        "management",
        "condominium"
    ],
    "wof:name":"Timber Top Condominiums",
    "wof:placetype":"venue"
},
  "geometry": {"coordinates":[-95.53067,29.99786],"type":"Point"}
}