{
  "type": "Feature",
  "properties": {
    "iso:country":"US",
    "sg:address":"845 Augusta Dr",
    "sg:city":"Houston",
    "sg:classifiers":[
        {
            "category":"Manufacturing",
            "subcategory":"Printing",
            "type":"Manufacturing & Wholesale Goods"
        }
    ],
    "sg:phone":"+1 713 977 6625",
    "sg:postcode":"77057",
    "sg:province":"TX",
    "sg:tags":[
        "periodical"
    ],
    "wof:name":"J D T V",
    "wof:placetype":"venue"
},
  "geometry": {"coordinates":[-95.482676,29.757923],"type":"Point"}
}