{
  "type": "Feature",
  "properties": {
    "iso:country":"US",
    "sg:address":"1524 Oak Forest Dr",
    "sg:city":"Graham",
    "sg:classifiers":[
        {
            "category":"Shopping",
            "subcategory":"Used Merchandise",
            "type":"Retail Goods"
        }
    ],
    "sg:phone":"+1 940 549 8185",
    "sg:postcode":"76450",
    "sg:province":"TX",
    "sg:tags":[
        "pawnbroker"
    ],
    "wof:name":"Loan Star Pawn & Trading Co",
    "wof:placetype":"venue"
},
  "geometry": {"coordinates":[-98.569537,33.088044],"type":"Point"}
}