{
  "type": "Feature",
  "properties": {
    "iso:country":"US",
    "sg:address":"2532 32nd Ave N",
    "sg:city":"Texas City",
    "sg:classifiers":[
        {
            "category":"Shopping",
            "subcategory":"Clothing, Apparel, & Fashions",
            "type":"Retail Goods"
        }
    ],
    "sg:phone":"+1 409 948 4843",
    "sg:postcode":"77590",
    "sg:province":"TX",
    "wof:name":"Joanie Place of Fashion",
    "wof:placetype":"venue"
},
  "geometry": {"coordinates":[-94.93185099999999,29.413223],"type":"Point"}
}