{
  "type": "Feature",
  "properties": {
    "iso:country":"US",
    "sg:address":"7416 Harrisburg Blvd",
    "sg:city":"Houston",
    "sg:classifiers":[
        {
            "category":"Food & Beverages",
            "subcategory":"Specialty",
            "type":"Retail Goods"
        }
    ],
    "sg:phone":"+1 713 928 3969",
    "sg:postcode":"77011",
    "sg:province":"TX",
    "sg:tags":[
        "herb"
    ],
    "wof:name":"Botanica Indio Del Amazona",
    "wof:placetype":"venue"
},
  "geometry": {"coordinates":[-95.292446,29.732575],"type":"Point"}
}