{
  "type": "Feature",
  "properties": {
    "iso:country":"US",
    "sg:address":"555 Bolton Pl",
    "sg:city":"Houston",
    "sg:classifiers":[
        {
            "category":"Utilities",
            "subcategory":"Telephone",
            "type":"Services"
        }
    ],
    "sg:phone":"+1 713 681 0170",
    "sg:postcode":"77024",
    "sg:province":"TX",
    "sg:tags":[
        "telecommunication"
    ],
    "wof:name":"MBA Telecommunication Svc",
    "wof:placetype":"venue"
},
  "geometry": {"coordinates":[-95.457319,29.776899],"type":"Point"}
}