{
  "type": "Feature",
  "properties": {
    "iso:country":"US",
    "sg:address":"8734 Stella Link Rd",
    "sg:city":"Houston",
    "sg:classifiers":[
        {
            "category":"Health Services",
            "subcategory":"Chiropractor",
            "type":"Services"
        }
    ],
    "sg:phone":"+1 713 592 5650",
    "sg:postcode":"77025",
    "sg:province":"TX",
    "wof:name":"A-Access Chiropractic",
    "wof:placetype":"venue"
},
  "geometry": {"coordinates":[-95.440028,29.687673],"type":"Point"}
}