{
  "type": "Feature",
  "properties": {
    "iso:country":"US",
    "sg:address":"3800 Seawall Blvd",
    "sg:city":"Galveston",
    "sg:classifiers":[
        {
            "category":"Recreation",
            "type":"Entertainment"
        }
    ],
    "sg:phone":"+1 409 762 7200",
    "sg:postcode":"77550",
    "sg:province":"TX",
    "sg:tags":[
        "club",
        "membership"
    ],
    "wof:name":"Gaidos of Galveston Inc",
    "wof:placetype":"venue"
},
  "geometry": {"coordinates":[-94.803804,29.279702],"type":"Point"}
}