{
  "type": "Feature",
  "properties": {
    "iso:country":"US",
    "sg:address":"2424 Swiss Ave",
    "sg:city":"Dallas",
    "sg:classifiers":[
        {
            "category":"Recreation",
            "subcategory":"Dance Hall",
            "type":"Entertainment"
        }
    ],
    "sg:phone":"+1 214 826 4769",
    "sg:postcode":"75204",
    "sg:province":"TX",
    "sg:tags":[
        "club"
    ],
    "sg:website":"www.thechurchdallas.com/",
    "wof:name":"The Church",
    "wof:placetype":"venue"
},
  "geometry": {"coordinates":[-96.7901,32.785198],"type":"Point"}
}