{
  "type": "Feature",
  "properties": {
    "iso:country":"US",
    "sg:address":"4720 84th St",
    "sg:city":"Lubbock",
    "sg:classifiers":[
        {
            "category":"Real Estate",
            "subcategory":"Real Estate Operator",
            "type":"Services"
        }
    ],
    "sg:phone":"+1 806 798 1479",
    "sg:postcode":"79424",
    "sg:province":"TX",
    "sg:tags":[
        "building",
        "nonresidential"
    ],
    "wof:name":"Young Properties",
    "wof:placetype":"venue"
},
  "geometry": {"coordinates":[-101.912627,33.517555],"type":"Point"}
}