{
  "type": "Feature",
  "properties": {
    "iso:country":"US",
    "sg:address":"1735 Highway 12",
    "sg:city":"Vidor",
    "sg:classifiers":[
        {
            "category":"Place Of Worship",
            "subcategory":"Church",
            "type":"Public Place"
        },
        {
            "category":"Place Of Worship",
            "type":"Public Place"
        }
    ],
    "sg:phone":"+1 409 769 9717",
    "sg:postcode":"77662",
    "sg:province":"TX",
    "sg:tags":[
        "churches-pentecostal-independent",
        "churches-pentecostal"
    ],
    "wof:name":"Faith Tabernacle Pentecostal",
    "wof:placetype":"venue"
},
  "geometry": {"coordinates":[-93.990257,30.143071],"type":"Point"}
}