{
  "type": "Feature",
  "properties": {
    "iso:country":"US",
    "sg:address":"206 N Gilmer St",
    "sg:city":"Killeen",
    "sg:classifiers":[
        {
            "category":"Retail",
            "subcategory":"Auto Repair",
            "type":"Services"
        }
    ],
    "sg:phone":"+1 254 634 2793",
    "sg:postcode":"76541",
    "sg:province":"TX",
    "sg:tags":[
        "transmission"
    ],
    "wof:name":"American Transmission Svc",
    "wof:placetype":"venue"
},
  "geometry": {"coordinates":[-97.737854,31.121986],"type":"Point"}
}