{
  "type": "Feature",
  "properties": {
    "iso:country":"US",
    "sg:address":"13630 Beamer Rd",
    "sg:city":"Houston",
    "sg:classifiers":[
        {
            "category":"Restaurant",
            "type":"Food & Drink"
        }
    ],
    "sg:phone":"+1 713 453 4162",
    "sg:postcode":"77089",
    "sg:province":"TX",
    "sg:tags":[
        "eating"
    ],
    "wof:name":"Java Express Coffee House",
    "wof:placetype":"venue"
},
  "geometry": {"coordinates":[-95.204773,29.577565],"type":"Point"}
}