{
  "type": "Feature",
  "properties": {
    "iso:country":"US",
    "sg:address":"404 S McCarty Ave",
    "sg:city":"Eagle Lake",
    "sg:classifiers":[
        {
            "category":"Professional",
            "type":"Services"
        }
    ],
    "sg:phone":"+1 979 234 5728",
    "sg:postcode":"77434",
    "sg:province":"TX",
    "wof:name":"Eagle Lake City Swimming",
    "wof:placetype":"venue"
},
  "geometry": {"coordinates":[-96.33697600000001,29.586673],"type":"Point"}
}