{
  "type": "Feature",
  "properties": {
    "iso:country":"US",
    "sg:address":"106 Forest Trl",
    "sg:city":"Leander",
    "sg:classifiers":[
        {
            "category":"Building & Trades",
            "subcategory":"Construction",
            "type":"Services"
        }
    ],
    "sg:phone":"+1 512 259 8228",
    "sg:postcode":"78641",
    "sg:province":"TX",
    "sg:tags":[
        "nonresidential"
    ],
    "wof:name":"United Building Inc",
    "wof:placetype":"venue"
},
  "geometry": {"coordinates":[-97.808722,30.551569],"type":"Point"}
}