{
  "type": "Feature",
  "properties": {
    "iso:country":"US",
    "sg:address":"207 N 8th St",
    "sg:city":"Midlothian",
    "sg:classifiers":[
        {
            "category":"Banks & Credit Unions",
            "subcategory":"Investment Brokerage",
            "type":"Services"
        }
    ],
    "sg:phone":"+1 972 723 5354",
    "sg:postcode":"76065",
    "sg:province":"TX",
    "sg:tags":[
        "consultant",
        "planning",
        "financial"
    ],
    "wof:name":"Norman Financial Svc",
    "wof:placetype":"venue"
},
  "geometry": {"coordinates":[-96.994584,32.483334],"type":"Point"}
}