{
  "type": "Feature",
  "properties": {
    "iso:country":"US",
    "sg:address":"13743 Castle Grove Dr",
    "sg:city":"San Antonio",
    "sg:classifiers":[
        {
            "category":"Food & Beverages",
            "subcategory":"Specialty",
            "type":"Retail Goods"
        }
    ],
    "sg:phone":"+1 210 492 0009",
    "sg:postcode":"78231",
    "sg:province":"TX",
    "wof:name":"Toni Hernandez Pardo",
    "wof:placetype":"venue"
},
  "geometry": {"coordinates":[-98.53496199999999,29.568885],"type":"Point"}
}