{
  "type": "Feature",
  "properties": {
    "iso:country":"US",
    "sg:address":"12804 Beltex Rd",
    "sg:city":"Manor",
    "sg:classifiers":[
        {
            "category":"Manufacturing",
            "subcategory":"Metals",
            "type":"Manufacturing & Wholesale Goods"
        }
    ],
    "sg:phone":"+1 512 272 9723",
    "sg:postcode":"78653",
    "sg:province":"TX",
    "sg:tags":[
        "manufacture",
        "shutter"
    ],
    "wof:name":"Panel Fabrication Systems Inc",
    "wof:placetype":"venue"
},
  "geometry": {"coordinates":[-97.51224499999999,30.349795],"type":"Point"}
}