{
  "type": "Feature",
  "properties": {
    "iso:country":"US",
    "sg:address":"3321 Cimarron Blvd",
    "sg:city":"Corpus Christi",
    "sg:classifiers":[
        {
            "category":"Organizations",
            "subcategory":"Religious Organization",
            "type":"Services"
        }
    ],
    "sg:phone":"+1 361 991 4593",
    "sg:postcode":"78414",
    "sg:province":"TX",
    "wof:name":"Galilean Lutheran Church",
    "wof:placetype":"venue"
},
  "geometry": {"coordinates":[-97.371938,27.674824],"type":"Point"}
}