{
  "type": "Feature",
  "properties": {
    "iso:country":"US",
    "sg:address":"1221 Buckner Blvd",
    "sg:city":"Dallas",
    "sg:classifiers":[
        {
            "category":"Retail",
            "subcategory":"Auto Repair",
            "type":"Services"
        }
    ],
    "sg:phone":"+1 214 398 8430",
    "sg:postcode":"75217",
    "sg:province":"TX",
    "sg:tags":[
        "repairing",
        "automobile"
    ],
    "wof:name":"Flores Automotive Svc",
    "wof:placetype":"venue"
},
  "geometry": {"coordinates":[-96.68285,32.73278],"type":"Point"}
}