{
  "type": "Feature",
  "properties": {
    "iso:country":"US",
    "sg:address":"2711 Yellowstone Park Ln",
    "sg:city":"Denton",
    "sg:classifiers":[
        {
            "category":"Building & Trades",
            "subcategory":"Plumbing",
            "type":"Services"
        }
    ],
    "sg:phone":"+1 940 321 3493",
    "sg:postcode":"76210",
    "sg:province":"TX",
    "sg:tags":[
        "contractor"
    ],
    "wof:name":"Rmk Plumbing & Heating",
    "wof:placetype":"venue"
},
  "geometry": {"coordinates":[-97.075726,33.136893],"type":"Point"}
}