{
  "type": "Feature",
  "properties": {
    "iso:country":"US",
    "sg:address":"5601 W 34th St",
    "sg:city":"Houston",
    "sg:classifiers":[
        {
            "category":"Restaurant",
            "type":"Food & Drink"
        }
    ],
    "sg:phone":"+1 713 680 0901",
    "sg:postcode":"77092",
    "sg:province":"TX",
    "sg:tags":[
        "a",
        "as",
        "steak",
        "operates"
    ],
    "wof:name":"Ryans",
    "wof:placetype":"venue"
},
  "geometry": {"coordinates":[-95.471943,29.819324],"type":"Point"}
}