{
  "type": "Feature",
  "properties": {
    "iso:country":"US",
    "sg:address":"715 E Border St",
    "sg:city":"Arlington",
    "sg:classifiers":[
        {
            "category":"Education",
            "subcategory":"Library",
            "type":"Public Place"
        }
    ],
    "sg:phone":"+1 817 462 5252",
    "sg:postcode":"76010",
    "sg:province":"TX",
    "wof:name":"Agent Production Library",
    "wof:placetype":"venue"
},
  "geometry": {"coordinates":[-97.10129000000001,32.733453],"type":"Point"}
}