{
  "type": "Feature",
  "properties": {
    "iso:country":"US",
    "sg:address":"713 E Juan Linn St",
    "sg:city":"Victoria",
    "sg:classifiers":[
        {
            "category":"Home & Garden",
            "subcategory":"Carpets & Floor Coverings",
            "type":"Retail Goods"
        }
    ],
    "sg:phone":"+1 361 578 5099",
    "sg:postcode":"77901",
    "sg:province":"TX",
    "sg:tags":[
        "laying",
        "contractor"
    ],
    "wof:name":"Crossroads Flooring & Supplies",
    "wof:placetype":"venue"
},
  "geometry": {"coordinates":[-96.99999099999999,28.795109],"type":"Point"}
}