{
  "type": "Feature",
  "properties": {
    "iso:country":"US",
    "sg:address":"3203 Delaford Dr",
    "sg:city":"Carrollton",
    "sg:classifiers":[
        {
            "category":"Building & Trades",
            "subcategory":"Cleaning & Sanitation",
            "type":"Services"
        }
    ],
    "sg:phone":"+1 214 653 1043",
    "sg:postcode":"75007",
    "sg:province":"TX",
    "sg:tags":[
        "janitor"
    ],
    "sg:website":"www.bcijanitorial.com",
    "wof:name":"Building Contractors Inc",
    "wof:placetype":"venue"
},
  "geometry": {"coordinates":[-96.89436499999999,33.004414],"type":"Point"}
}