{
  "type": "Feature",
  "properties": {
    "iso:country":"US",
    "sg:address":"18352 Dallas Pkwy",
    "sg:city":"Dallas",
    "sg:classifiers":[
        {
            "category":"Professional",
            "subcategory":"Computer Services",
            "type":"Services"
        }
    ],
    "sg:phone":"+1 214 336 8017",
    "sg:postcode":"75287",
    "sg:province":"TX",
    "sg:tags":[
        "website",
        "design"
    ],
    "wof:name":"Dallas Web Builders",
    "wof:placetype":"venue"
},
  "geometry": {"coordinates":[-96.82887599999999,32.999377],"type":"Point"}
}