{
  "type": "Feature",
  "properties": {
    "iso:country":"US",
    "sg:address":"1200 E 12th St",
    "sg:city":"Austin",
    "sg:classifiers":[
        {
            "category":"Home & Garden",
            "subcategory":"Home Furnishings",
            "type":"Retail Goods"
        },
        {
            "category":"Real Estate",
            "subcategory":"Architect",
            "type":"Services"
        }
    ],
    "sg:phone":"+1 512 499 1591",
    "sg:postcode":"78702",
    "sg:province":"TX",
    "sg:tags":[
        "architects'",
        "designer",
        "residential",
        "specification",
        "builders'",
        "planning",
        "design",
        "architectural",
        "construction"
    ],
    "sg:website":"www.urbanjobe.com",
    "wof:name":"Urban Jobe Architecture",
    "wof:placetype":"venue"
},
  "geometry": {"coordinates":[-97.72777499999999,30.272655],"type":"Point"}
}