{
  "type": "Feature",
  "properties": {
    "iso:country":"US",
    "sg:address":"6050 S Padre Island Dr",
    "sg:city":"Corpus Christi",
    "sg:classifiers":[
        {
            "category":"Autos & Motor Vehicles",
            "subcategory":"Auto Supplies",
            "type":"Retail Goods"
        }
    ],
    "sg:phone":"+1 361 654 2160",
    "sg:postcode":"78412",
    "sg:province":"TX",
    "sg:tags":[
        "automobile",
        "parts"
    ],
    "wof:name":"Vista Cadillac Oldsmobile Part",
    "wof:placetype":"venue"
},
  "geometry": {"coordinates":[-97.361132,27.703605],"type":"Point"}
}