{
  "type": "Feature",
  "properties": {
    "iso:country":"US",
    "sg:address":"29201 State Loop 494",
    "sg:city":"Humble",
    "sg:classifiers":[
        {
            "category":"Home & Garden",
            "subcategory":"Garden Supply",
            "type":"Retail Goods"
        }
    ],
    "sg:phone":"+1 281 359 5660",
    "sg:postcode":"77339",
    "sg:province":"TX",
    "wof:name":"Custom Landscaping & Design",
    "wof:placetype":"venue"
},
  "geometry": {"coordinates":[-95.242204,30.066384],"type":"Point"}
}