{
  "type": "Feature",
  "properties": {
    "iso:country":"US",
    "sg:address":"2800 Sage Rd Ste 900",
    "sg:city":"Houston",
    "sg:classifiers":[
        {
            "category":"Recreation",
            "subcategory":"Dance Hall",
            "type":"Entertainment"
        }
    ],
    "sg:postcode":"77056",
    "sg:province":"TX",
    "sg:tags":[
        "club"
    ],
    "sg:website":"www.myspace.com/crobarhouston",
    "wof:name":"Crobar",
    "wof:placetype":"venue"
},
  "geometry": {"coordinates":[-95.46763199999999,29.737501],"type":"Point"}
}