{
  "type": "Feature",
  "properties": {
    "iso:country":"US",
    "sg:address":"703 N Wall St",
    "sg:city":"Belton",
    "sg:classifiers":[
        {
            "category":"Professional",
            "type":"Services"
        }
    ],
    "sg:phone":"+1 254 939 1497",
    "sg:postcode":"76513",
    "sg:province":"TX",
    "wof:name":"Cottage Gardens",
    "wof:placetype":"venue"
},
  "geometry": {"coordinates":[-97.457703,31.063334],"type":"Point"}
}