{
  "type": "Feature",
  "properties": {
    "iso:country":"US",
    "sg:address":"3433 Brady Ave",
    "sg:city":"Fort Worth",
    "sg:classifiers":[
        {
            "category":"Manufacturing",
            "subcategory":"Textiles",
            "type":"Manufacturing & Wholesale Goods"
        }
    ],
    "sg:phone":"+1 817 921 2113",
    "sg:postcode":"76109",
    "sg:province":"TX",
    "sg:tags":[
        "plant",
        "silk",
        "finishing",
        "fiber"
    ],
    "wof:name":"Cjp Products",
    "wof:placetype":"venue"
},
  "geometry": {"coordinates":[-97.365779,32.691667],"type":"Point"}
}