{
  "type": "Feature",
  "properties": {
    "iso:country":"US",
    "sg:address":"105 E Harwood Rd",
    "sg:city":"Euless",
    "sg:classifiers":[
        {
            "category":"Real Estate",
            "subcategory":"Real Estate Operator",
            "type":"Services"
        }
    ],
    "sg:phone":"+1 817 267 9900",
    "sg:postcode":"76039",
    "sg:province":"TX",
    "sg:tags":[
        "apartment",
        "complex"
    ],
    "wof:name":"Charter Oak Apartments",
    "wof:placetype":"venue"
},
  "geometry": {"coordinates":[-97.081552,32.851777],"type":"Point"}
}