{
  "type": "Feature",
  "properties": {
    "iso:country":"US",
    "sg:address":"4422 Weber Rd",
    "sg:city":"Corpus Christi",
    "sg:classifiers":[
        {
            "category":"Food & Beverages",
            "subcategory":"Groceries & Convenience Stores",
            "type":"Retail Goods"
        }
    ],
    "sg:phone":"+1 361 225 3812",
    "sg:postcode":"78411",
    "sg:province":"TX",
    "wof:name":"Country Store",
    "wof:placetype":"venue"
},
  "geometry": {"coordinates":[-97.392016,27.732218],"type":"Point"}
}