{
  "type": "Feature",
  "properties": {
    "iso:country":"US",
    "sg:address":"620 N Conway Ave",
    "sg:city":"Mission",
    "sg:classifiers":[
        {
            "category":"Food & Beverages",
            "subcategory":"Groceries & Convenience Stores",
            "type":"Retail Goods"
        }
    ],
    "sg:phone":"+1 956 581 2154",
    "sg:postcode":"78572",
    "sg:province":"TX",
    "wof:name":"H-E-B Food Store",
    "wof:placetype":"venue"
},
  "geometry": {"coordinates":[-98.326179,26.21228],"type":"Point"}
}