{
  "type": "Feature",
  "properties": {
    "iso:country":"US",
    "sg:address":"4835 W Ost Dr",
    "sg:city":"Houston",
    "sg:classifiers":[
        {
            "category":"Building & Trades",
            "subcategory":"Construction",
            "type":"Services"
        }
    ],
    "sg:phone":"+1 713 673 4035",
    "sg:postcode":"77013",
    "sg:province":"TX",
    "sg:tags":[
        "contractor"
    ],
    "wof:name":"G & Q Roofing",
    "wof:placetype":"venue"
},
  "geometry": {"coordinates":[-95.263344,29.80149],"type":"Point"}
}