{
  "type": "Feature",
  "properties": {
    "iso:country":"US",
    "sg:address":"15006 Old Frio City Rd",
    "sg:city":"Lytle",
    "sg:classifiers":[
        {
            "category":"Organizations",
            "subcategory":"Religious Organization",
            "type":"Services"
        }
    ],
    "sg:phone":"+1 830 709 2222",
    "sg:postcode":"78052",
    "sg:province":"TX",
    "sg:tags":[
        "church"
    ],
    "wof:name":"Gathering Church",
    "wof:placetype":"venue"
},
  "geometry": {"coordinates":[-98.79535799999999,29.25111],"type":"Point"}
}