{
  "type": "Feature",
  "properties": {
    "iso:country":"US",
    "sg:address":"1419 Sereno Dr",
    "sg:city":"Dallas",
    "sg:classifiers":[
        {
            "category":"Shopping",
            "subcategory":"Used Merchandise",
            "type":"Retail Goods"
        }
    ],
    "sg:phone":"+1 214 328 8001",
    "sg:postcode":"75218",
    "sg:province":"TX",
    "wof:name":"Judith L Wolfe",
    "wof:placetype":"venue"
},
  "geometry": {"coordinates":[-96.695842,32.830583],"type":"Point"}
}