{
  "type": "Feature",
  "properties": {
    "iso:country":"US",
    "sg:address":"1120 Ridgewood Ln",
    "sg:city":"Hutchins",
    "sg:classifiers":[
        {
            "category":"Education",
            "subcategory":"School",
            "type":"Public Place"
        }
    ],
    "sg:phone":"+1 972 225 4426",
    "sg:postcode":"75141",
    "sg:province":"TX",
    "wof:name":"Shelton Hubbard Plumbing Schl",
    "wof:placetype":"venue"
},
  "geometry": {"coordinates":[-96.696029,32.642812],"type":"Point"}
}