{
  "type": "Feature",
  "properties": {
    "iso:country":"US",
    "sg:address":"19626 Enchanted Oaks Dr",
    "sg:city":"Spring",
    "sg:classifiers":[
        {
            "category":"Insurance",
            "subcategory":"Insurance Agent",
            "type":"Services"
        }
    ],
    "sg:phone":"+1 281 353 2507",
    "sg:postcode":"77388",
    "sg:province":"TX",
    "wof:name":"Bob Hamilton Insurance",
    "wof:placetype":"venue"
},
  "geometry": {"coordinates":[-95.44212,30.050251],"type":"Point"}
}