{
  "type": "Feature",
  "properties": {
    "iso:country":"US",
    "sg:address":"2601 Colby St",
    "sg:city":"Dallas",
    "sg:classifiers":[
        {
            "category":"Professional",
            "subcategory":"Management & Consulting",
            "type":"Services"
        }
    ],
    "sg:phone":"+1 214 871 2332",
    "sg:postcode":"75204",
    "sg:province":"TX",
    "wof:name":"Carter Cook Cement LLC",
    "wof:placetype":"venue"
},
  "geometry": {"coordinates":[-96.798237,32.794424],"type":"Point"}
}