{
  "type": "Feature",
  "properties": {
    "iso:country":"US",
    "sg:address":"6223 Rincon Way",
    "sg:city":"Dallas",
    "sg:classifiers":[
        {
            "category":"Communications",
            "subcategory":"Film & Video Production",
            "type":"Services"
        }
    ],
    "sg:phone":"+1 214 696 0726",
    "sg:postcode":"75214",
    "sg:province":"TX",
    "sg:tags":[
        "motion"
    ],
    "wof:name":"Tilt Productions",
    "wof:placetype":"venue"
},
  "geometry": {"coordinates":[-96.75469200000001,32.854576],"type":"Point"}
}