{
  "type": "Feature",
  "properties": {
    "iso:country":"US",
    "sg:address":"6326 Oakleaf Rd",
    "sg:city":"Dallas",
    "sg:classifiers":[
        {
            "category":"Organizations",
            "subcategory":"Religious Organization",
            "type":"Services"
        }
    ],
    "sg:phone":"+1 972 458 7700",
    "sg:postcode":"75248",
    "sg:province":"TX",
    "sg:tags":[
        "science",
        "christian",
        "practitioner"
    ],
    "wof:name":"Mary Ridgway",
    "wof:placetype":"venue"
},
  "geometry": {"coordinates":[-96.796198,32.964533],"type":"Point"}
}