{
  "type": "Feature",
  "properties": {
    "iso:country":"US",
    "sg:address":"406 S Nebraska Ave Ste B",
    "sg:city":"Weslaco",
    "sg:classifiers":[
        {
            "category":"Professional",
            "subcategory":"Engineering",
            "type":"Services"
        },
        {
            "category":"Wholesale",
            "subcategory":"Electrical",
            "type":"Manufacturing & Wholesale Goods"
        }
    ],
    "sg:phone":"+1 956 447 2500",
    "sg:postcode":"78596",
    "sg:province":"TX",
    "sg:tags":[
        "system",
        "systems-wholesale",
        "equipment",
        "air conditioning",
        "manufacturer"
    ],
    "sg:website":"http://www.txap.com",
    "wof:name":"Texas Air Products, Ltd.",
    "wof:placetype":"venue"
},
  "geometry": {"coordinates":[-97.99263500000001,26.156938],"type":"Point"}
}