{
  "type": "Feature",
  "properties": {
    "iso:country":"US",
    "sg:address":"2106 Quail Run",
    "sg:city":"San Marcos",
    "sg:classifiers":[
        {
            "category":"Health Services",
            "subcategory":"Health Practitioner",
            "type":"Services"
        }
    ],
    "sg:phone":"+1 512 392 8105",
    "sg:postcode":"78666",
    "sg:province":"TX",
    "sg:tags":[
        "psychologist"
    ],
    "wof:name":"E H Kotin PHD",
    "wof:placetype":"venue"
},
  "geometry": {"coordinates":[-98.018112,29.834937],"type":"Point"}
}