{
  "type": "Feature",
  "properties": {
    "iso:country":"US",
    "sg:address":"3221 Summer Canyon Dr",
    "sg:city":"Austin",
    "sg:classifiers":[
        {
            "category":"Professional",
            "type":"Services"
        }
    ],
    "sg:phone":"+1 512 266 8299",
    "sg:postcode":"78732",
    "sg:province":"TX",
    "wof:name":"Texas Ppm Inc",
    "wof:placetype":"venue"
},
  "geometry": {"coordinates":[-97.90495199999999,30.379395],"type":"Point"}
}