{
  "type": "Feature",
  "properties": {
    "iso:country":"US",
    "sg:address":"208 W Main St",
    "sg:city":"Crowley",
    "sg:classifiers":[
        {
            "category":"Shopping",
            "subcategory":"Tobacco",
            "type":"Retail Goods"
        }
    ],
    "sg:phone":"+1 817 991 3140",
    "sg:postcode":"76036",
    "sg:province":"TX",
    "sg:tags":[
        "product"
    ],
    "wof:name":"Smoke Delight",
    "wof:placetype":"venue"
},
  "geometry": {"coordinates":[-97.361294,32.578994],"type":"Point"}
}