{
  "type": "Feature",
  "properties": {
    "iso:country":"US",
    "sg:address":"1718 Eastside Dr",
    "sg:city":"Wichita Falls",
    "sg:classifiers":[
        {
            "category":"Building & Trades",
            "subcategory":"Construction",
            "type":"Services"
        }
    ],
    "sg:phone":"+1 940 767 1191",
    "sg:postcode":"76301",
    "sg:province":"TX",
    "sg:tags":[
        "general",
        "contractor"
    ],
    "wof:name":"R & W Painting & Repair",
    "wof:placetype":"venue"
},
  "geometry": {"coordinates":[-98.45863300000001,33.904121],"type":"Point"}
}