{
  "type": "Feature",
  "properties": {
    "iso:country":"US",
    "sg:address":"3904 Pembrooke Pkwy W",
    "sg:city":"Colleyville",
    "sg:classifiers":[
        {
            "category":"Professional",
            "subcategory":"Computer Services",
            "type":"Services"
        }
    ],
    "sg:phone":"+1 817 545 2238",
    "sg:postcode":"76034",
    "sg:province":"TX",
    "sg:tags":[
        "consulting",
        "datum",
        "business"
    ],
    "wof:name":"Webweavers",
    "wof:placetype":"venue"
},
  "geometry": {"coordinates":[-97.11526600000001,32.867038],"type":"Point"}
}