{
  "type": "Feature",
  "properties": {
    "iso:country":"US",
    "sg:address":"1302 N State Hwy 91",
    "sg:city":"Denison",
    "sg:classifiers":[
        {
            "category":"Professional",
            "subcategory":"Accounting & Tax Preparation",
            "type":"Services"
        }
    ],
    "sg:phone":"+1 903 465 1857",
    "sg:postcode":"75020",
    "sg:province":"TX",
    "wof:name":"Digital Billing Services",
    "wof:placetype":"venue"
},
  "geometry": {"coordinates":[-96.55410000000001,33.766466],"type":"Point"}
}