{
  "type": "Feature",
  "properties": {
    "iso:country":"US",
    "sg:address":"14312 Burrell St",
    "sg:city":"Amarillo",
    "sg:classifiers":[
        {
            "category":"Retail",
            "subcategory":"Laundry & Dry Cleaning",
            "type":"Services"
        }
    ],
    "sg:phone":"+1 806 622 5055",
    "sg:postcode":"79119",
    "sg:province":"TX",
    "sg:tags":[
        "cleaners",
        "rug",
        "carpet"
    ],
    "wof:name":"All American Cleaning & Rstrtn",
    "wof:placetype":"venue"
},
  "geometry": {"coordinates":[-101.927499,35.071962],"type":"Point"}
}