{
  "type": "Feature",
  "properties": {
    "iso:country":"US",
    "sg:address":"3707 W William Cannon Dr",
    "sg:city":"Austin",
    "sg:classifiers":[
        {
            "category":"Shopping",
            "subcategory":"Hobbies, Toys, & Games",
            "type":"Retail Goods"
        }
    ],
    "sg:phone":"+1 512 358 0430",
    "sg:postcode":"78749",
    "sg:province":"TX",
    "sg:tags":[
        "video",
        "supply"
    ],
    "sg:website":"http://www.gamecrazy.com",
    "wof:name":"Game Crazy",
    "wof:placetype":"venue"
},
  "geometry": {"coordinates":[-97.83303100000001,30.215352],"type":"Point"}
}