{
  "type": "Feature",
  "properties": {
    "iso:country":"US",
    "sg:address":"4306 Baccarat Dr",
    "sg:city":"Garland",
    "sg:classifiers":[
        {
            "category":"Professional",
            "type":"Services"
        }
    ],
    "sg:phone":"+1 972 226 7633",
    "sg:postcode":"75043",
    "sg:province":"TX",
    "wof:name":"Jmc Services",
    "wof:placetype":"venue"
},
  "geometry": {"coordinates":[-96.569034,32.840925],"type":"Point"}
}