{
  "type": "Feature",
  "properties": {
    "iso:country":"US",
    "sg:address":"230 Omaha Dr",
    "sg:city":"Corpus Christi",
    "sg:classifiers":[
        {
            "category":"Wholesale",
            "subcategory":"Auto Parts",
            "type":"Manufacturing & Wholesale Goods"
        }
    ],
    "sg:phone":"+1 361 883 2581",
    "sg:postcode":"78408",
    "sg:province":"TX",
    "sg:tags":[
        "used",
        "yard",
        "automotive",
        "operates",
        "an",
        "retailing",
        "amer",
        "salvage"
    ],
    "wof:name":"Deluxe Auto Parts",
    "wof:placetype":"venue"
},
  "geometry": {"coordinates":[-97.448035,27.790944],"type":"Point"}
}