{
  "type": "Feature",
  "properties": {
    "iso:country":"US",
    "sg:address":"6611 General Store St",
    "sg:city":"San Antonio",
    "sg:classifiers":[
        {
            "category":"Manufacturing",
            "subcategory":"Tobacco Products",
            "type":"Manufacturing & Wholesale Goods"
        }
    ],
    "sg:phone":"+1 210 647 8898",
    "sg:postcode":"78238",
    "sg:province":"TX",
    "sg:tags":[
        "mfg"
    ],
    "wof:name":"Brown & Williamson",
    "wof:placetype":"venue"
},
  "geometry": {"coordinates":[-98.628495,29.494269],"type":"Point"}
}