{
  "type": "Feature",
  "properties": {
    "iso:country":"US",
    "sg:address":"2203 S 23rd St",
    "sg:city":"Mcallen",
    "sg:classifiers":[
        {
            "category":"Bars & Pubs",
            "type":"Food & Drink"
        }
    ],
    "sg:phone":"+1 956 994 9410",
    "sg:postcode":"78503",
    "sg:province":"TX",
    "sg:tags":[
        "drinking"
    ],
    "wof:name":"Toro El",
    "wof:placetype":"venue"
},
  "geometry": {"coordinates":[-98.247793,26.189673],"type":"Point"}
}