{
  "type": "Feature",
  "properties": {
    "iso:country":"US",
    "sg:address":"3110 Manor Rd",
    "sg:city":"Austin",
    "sg:classifiers":[
        {
            "category":"Organizations",
            "subcategory":"Professional Association",
            "type":"Services"
        }
    ],
    "sg:phone":"+1 512 220 1520",
    "sg:postcode":"78723",
    "sg:province":"TX",
    "sg:tags":[
        "executive",
        "business"
    ],
    "wof:name":"Austin Sickle Cell Anemia Assn",
    "wof:placetype":"venue"
},
  "geometry": {"coordinates":[-97.706041,30.286313],"type":"Point"}
}