{
  "type": "Feature",
  "properties": {
    "iso:country":"US",
    "sg:address":"7100 Midway Rd",
    "sg:city":"Fort Worth",
    "sg:classifiers":[
        {
            "category":"Manufacturing",
            "subcategory":"Metals",
            "type":"Manufacturing & Wholesale Goods"
        }
    ],
    "sg:phone":"+1 817 284 2286",
    "sg:postcode":"76118",
    "sg:province":"TX",
    "sg:tags":[
        "plating",
        "electroplating"
    ],
    "wof:name":"Amalgam Plating  Inc",
    "wof:placetype":"venue"
},
  "geometry": {"coordinates":[-97.22778099999999,32.794456],"type":"Point"}
}