{
  "type": "Feature",
  "properties": {
    "iso:country":"US",
    "sg:address":"227 Burwell Rd",
    "sg:city":"Highlands",
    "sg:classifiers":[
        {
            "category":"Professional",
            "subcategory":"Engineering",
            "type":"Services"
        }
    ],
    "sg:phone":"+1 281 426 7726",
    "sg:postcode":"77562",
    "sg:province":"TX",
    "wof:name":"Nxt Resources Inc",
    "wof:placetype":"venue"
},
  "geometry": {"coordinates":[-95.052254,29.834343],"type":"Point"}
}