{
  "type": "Feature",
  "properties": {
    "iso:country":"US",
    "sg:address":"15050 Old Humble Rd",
    "sg:city":"Humble",
    "sg:classifiers":[
        {
            "category":"Autos & Motor Vehicles",
            "subcategory":"Fuel & Gas Station",
            "type":"Retail Goods"
        }
    ],
    "sg:phone":"+1 281 441 8363",
    "sg:postcode":"77396",
    "sg:province":"TX",
    "wof:name":"Chevron Station",
    "wof:placetype":"venue"
},
  "geometry": {"coordinates":[-95.284401,29.939199],"type":"Point"}
}