{
  "type": "Feature",
  "properties": {
    "iso:country":"US",
    "sg:address":"10819 Kirkmead Dr",
    "sg:city":"Houston",
    "sg:classifiers":[
        {
            "category":"Professional",
            "subcategory":"Business Services",
            "type":"Services"
        }
    ],
    "sg:phone":"+1 281 481 4604",
    "sg:postcode":"77089",
    "sg:province":"TX",
    "wof:name":"Ascendant Resources Group",
    "wof:placetype":"venue"
},
  "geometry": {"coordinates":[-95.229506,29.596149],"type":"Point"}
}