{
  "type": "Feature",
  "properties": {
    "iso:country":"US",
    "sg:address":"2517 Highland Park Dr",
    "sg:city":"Vernon",
    "sg:classifiers":[
        {
            "category":"Retail",
            "subcategory":"Auto Repair",
            "type":"Services"
        }
    ],
    "sg:phone":"+1 940 553 1793",
    "sg:postcode":"76384",
    "sg:province":"TX",
    "sg:tags":[
        "general"
    ],
    "wof:name":"Your Turn To Fix It",
    "wof:placetype":"venue"
},
  "geometry": {"coordinates":[-99.292284,34.141852],"type":"Point"}
}