{
  "type": "Feature",
  "properties": {
    "iso:country":"US",
    "sg:address":"1406 Hays St",
    "sg:city":"Houston",
    "sg:classifiers":[
        {
            "category":"Taxi",
            "type":"Transportation"
        }
    ],
    "sg:phone":"+1 713 699 8040",
    "sg:postcode":"77009",
    "sg:province":"TX",
    "sg:tags":[
        "taxicab"
    ],
    "wof:name":"Taxi Cabs U S A Inc",
    "wof:placetype":"venue"
},
  "geometry": {"coordinates":[-95.353103,29.789724],"type":"Point"}
}