{
  "type": "Feature",
  "properties": {
    "iso:country":"US",
    "sg:address":"1620 W University Dr",
    "sg:city":"Edinburg",
    "sg:classifiers":[
        {
            "category":"Restaurant",
            "type":"Food & Drink"
        }
    ],
    "sg:phone":"+1 956 292 0133",
    "sg:postcode":"78539",
    "sg:province":"TX",
    "sg:tags":[
        "eating"
    ],
    "wof:name":"Panini Cafe & Deli",
    "wof:placetype":"venue"
},
  "geometry": {"coordinates":[-98.17851,26.303781],"type":"Point"}
}