{
  "type": "Feature",
  "properties": {
    "iso:country":"US",
    "sg:address":"2755 S Hulen St",
    "sg:city":"Fort Worth",
    "sg:classifiers":[
        {
            "category":"Bars & Pubs",
            "type":"Food & Drink"
        },
        {
            "category":"Restaurant",
            "type":"Food & Drink"
        }
    ],
    "sg:phone":"+1 817 207 0788",
    "sg:postcode":"76109",
    "sg:province":"TX",
    "sg:tags":[
        "grill",
        "bar"
    ],
    "sg:website":"www.snookies.com",
    "wof:name":"Snookie's Bar & Grill",
    "wof:placetype":"venue"
},
  "geometry": {"coordinates":[-97.386837,32.709945],"type":"Point"}
}