{
  "type": "Feature",
  "properties": {
    "iso:country":"US",
    "sg:address":"1130 E Marshall Ave",
    "sg:city":"Longview",
    "sg:classifiers":[
        {
            "category":"Shopping",
            "subcategory":"Department Store",
            "type":"Retail Goods"
        }
    ],
    "sg:phone":"+1 903 753 9936",
    "sg:postcode":"75601",
    "sg:province":"TX",
    "sg:tags":[
        "shop"
    ],
    "wof:name":"Just A Dollar",
    "wof:placetype":"venue"
},
  "geometry": {"coordinates":[-94.72454,32.503104],"type":"Point"}
}