{
  "type": "Feature",
  "properties": {
    "iso:country":"US",
    "sg:address":"7536 Ave K",
    "sg:city":"Houston",
    "sg:classifiers":[
        {
            "category":"Restaurant",
            "type":"Food & Drink"
        }
    ],
    "sg:phone":"+1 713 926 3830",
    "sg:postcode":"77012",
    "sg:province":"TX",
    "sg:tags":[
        "eating"
    ],
    "wof:name":"Tacos Diaz",
    "wof:placetype":"venue"
},
  "geometry": {"coordinates":[-95.28804100000001,29.738885],"type":"Point"}
}