{
  "type": "Feature",
  "properties": {
    "iso:country":"US",
    "sg:address":"608 Morrow St",
    "sg:city":"Austin",
    "sg:classifiers":[
        {
            "category":"Professional",
            "subcategory":"Employment Agencies",
            "type":"Services"
        },
        {
            "category":"Organizations",
            "subcategory":"Non-profit Organization",
            "type":"Services"
        }
    ],
    "sg:phone":"+1 512 419 0524",
    "sg:postcode":"78752",
    "sg:province":"TX",
    "sg:tags":[
        "opportunity",
        "community",
        "service/non-profit"
    ],
    "wof:name":"Centerpoint Career Institute Inc",
    "wof:placetype":"venue"
},
  "geometry": {"coordinates":[-97.712581,30.343235],"type":"Point"}
}