{
  "type": "Feature",
  "properties": {
    "iso:country":"US",
    "sg:address":"11744 Wilcrest Dr",
    "sg:city":"Houston",
    "sg:classifiers":[
        {
            "category":"Building & Trades",
            "subcategory":"Construction",
            "type":"Services"
        }
    ],
    "sg:phone":"+1 281 850 6389",
    "sg:postcode":"77099",
    "sg:province":"TX",
    "wof:name":"J D Averens Construction",
    "wof:placetype":"venue"
},
  "geometry": {"coordinates":[-95.569142,29.651964],"type":"Point"}
}