{
  "type": "Feature",
  "properties": {
    "iso:country":"US",
    "sg:address":"8420 Co Rd 272",
    "sg:city":"Terrell",
    "sg:classifiers":[
        {
            "category":"Shopping",
            "type":"Retail Goods"
        }
    ],
    "sg:phone":"+1 972 563 3992",
    "sg:postcode":"75160",
    "sg:province":"TX",
    "sg:tags":[
        "merchandise"
    ],
    "wof:name":"Weddings By Vaughn",
    "wof:placetype":"venue"
},
  "geometry": {"coordinates":[-96.348472,32.681572],"type":"Point"}
}