{
  "type": "Feature",
  "properties": {
    "iso:country":"US",
    "sg:address":"340 E 40th St",
    "sg:city":"Lubbock",
    "sg:classifiers":[
        {
            "category":"Shopping",
            "subcategory":"Clothing, Apparel, & Fashions",
            "type":"Retail Goods"
        }
    ],
    "sg:phone":"+1 806 744 1059",
    "sg:postcode":"79404",
    "sg:province":"TX",
    "wof:name":"Jo-Dees TS & Caps",
    "wof:placetype":"venue"
},
  "geometry": {"coordinates":[-101.833777,33.557743],"type":"Point"}
}