{
  "type": "Feature",
  "properties": {
    "iso:country":"US",
    "sg:address":"793 Co Rd 313 W",
    "sg:city":"Tyler",
    "sg:classifiers":[
        {
            "category":"Organizations",
            "subcategory":"Religious Organization",
            "type":"Services"
        }
    ],
    "sg:phone":"+1 903 597 6131",
    "sg:postcode":"75706",
    "sg:province":"TX",
    "wof:name":"Antioch Baptist",
    "wof:placetype":"venue"
},
  "geometry": {"coordinates":[-95.28306600000001,32.488538],"type":"Point"}
}