{
  "type": "Feature",
  "properties": {
    "iso:country":"US",
    "sg:address":"524 Phinney Ave",
    "sg:city":"Dallas",
    "sg:classifiers":[
        {
            "category":"Building & Trades",
            "subcategory":"Construction",
            "type":"Services"
        }
    ],
    "sg:phone":"+1 214 330 4770",
    "sg:postcode":"75211",
    "sg:province":"TX",
    "sg:tags":[
        "contractor"
    ],
    "wof:name":"Angel General Contractor",
    "wof:placetype":"venue"
},
  "geometry": {"coordinates":[-96.887108,32.740448],"type":"Point"}
}