{
  "type": "Feature",
  "properties": {
    "iso:country":"US",
    "sg:address":"201 S Kaysie St",
    "sg:city":"Angleton",
    "sg:classifiers":[
        {
            "category":"Real Estate",
            "subcategory":"Real Estate Operator",
            "type":"Services"
        }
    ],
    "sg:phone":"+1 979 849 6150",
    "sg:postcode":"77515",
    "sg:province":"TX",
    "sg:tags":[
        "building",
        "apartment"
    ],
    "wof:name":"Fairywynd Apartments",
    "wof:placetype":"venue"
},
  "geometry": {"coordinates":[-95.436668,29.175659],"type":"Point"}
}