{
  "type": "Feature",
  "properties": {
    "iso:country":"US",
    "sg:address":"1103 S Broadway St",
    "sg:city":"Plainview",
    "sg:classifiers":[
        {
            "category":"Organizations",
            "subcategory":"Professional Association",
            "type":"Services"
        }
    ],
    "sg:phone":"+1 806 293 1502",
    "sg:postcode":"79072",
    "sg:province":"TX",
    "wof:name":"American Assoc of Univers",
    "wof:placetype":"venue"
},
  "geometry": {"coordinates":[-101.702647,34.169489],"type":"Point"}
}