{
  "type": "Feature",
  "properties": {
    "iso:country":"US",
    "sg:address":"5802 Cannonade Ct",
    "sg:city":"Austin",
    "sg:classifiers":[
        {
            "category":"Professional",
            "subcategory":"Computer Services",
            "type":"Services"
        }
    ],
    "sg:phone":"+1 512 659 8100",
    "sg:postcode":"78746",
    "sg:province":"TX",
    "sg:tags":[
        "info",
        "technology"
    ],
    "wof:name":"Eutecus Inc",
    "wof:placetype":"venue"
},
  "geometry": {"coordinates":[-97.803522,30.330485],"type":"Point"}
}