{
  "type": "Feature",
  "properties": {
    "iso:country":"US",
    "sg:address":"601 E 15th St",
    "sg:city":"Austin",
    "sg:classifiers":[
        {
            "category":"Shopping",
            "subcategory":"Gifts & Souvenirs",
            "type":"Retail Goods"
        }
    ],
    "sg:phone":"+1 512 480 1679",
    "sg:postcode":"78701",
    "sg:province":"TX",
    "wof:name":"Choa Aux",
    "wof:placetype":"venue"
},
  "geometry": {"coordinates":[-97.733971,30.275336],"type":"Point"}
}