{
  "type": "Feature",
  "properties": {
    "iso:country":"US",
    "sg:address":"10550 Pleasanton Dr",
    "sg:city":"Houston",
    "sg:classifiers":[
        {
            "category":"Professional",
            "subcategory":"Business Services",
            "type":"Services"
        }
    ],
    "sg:phone":"+1 281 931 1878",
    "sg:postcode":"77038",
    "sg:province":"TX",
    "wof:name":"Jasen Hagger",
    "wof:placetype":"venue"
},
  "geometry": {"coordinates":[-95.440321,29.925246],"type":"Point"}
}