{
  "type": "Feature",
  "properties": {
    "iso:country":"US",
    "sg:address":"2004 Indian Trl",
    "sg:city":"Austin",
    "sg:classifiers":[
        {
            "category":"Professional",
            "subcategory":"Art Services",
            "type":"Services"
        }
    ],
    "sg:phone":"+1 512 477 3832",
    "sg:postcode":"78703",
    "sg:province":"TX",
    "sg:tags":[
        "graphic",
        "designer"
    ],
    "wof:name":"Gryphon Enterprises",
    "wof:placetype":"venue"
},
  "geometry": {"coordinates":[-97.76102899999999,30.293986],"type":"Point"}
}