{
  "type": "Feature",
  "properties": {
    "iso:country":"US",
    "sg:address":"6610 State Hwy 78",
    "sg:city":"Garland",
    "sg:classifiers":[
        {
            "category":"Building & Trades",
            "subcategory":"Construction",
            "type":"Services"
        }
    ],
    "sg:phone":"+1 972 495 7657",
    "sg:postcode":"75048",
    "sg:province":"TX",
    "sg:tags":[
        "house"
    ],
    "wof:name":"Gs Baker Construction",
    "wof:placetype":"venue"
},
  "geometry": {"coordinates":[-96.587716,32.981196],"type":"Point"}
}