{
  "type": "Feature",
  "properties": {
    "iso:country":"US",
    "sg:address":"502 S de Leon St",
    "sg:city":"Victoria",
    "sg:classifiers":[
        {
            "category":"Building & Trades",
            "subcategory":"Plumbing",
            "type":"Services"
        }
    ],
    "sg:phone":"+1 361 575 3301",
    "sg:postcode":"77901",
    "sg:province":"TX",
    "sg:tags":[
        "plumbing",
        "contractor"
    ],
    "wof:name":"Caraway Plumbing Inc",
    "wof:placetype":"venue"
},
  "geometry": {"coordinates":[-97.00488900000001,28.793825],"type":"Point"}
}