{
  "type": "Feature",
  "properties": {
    "iso:country":"US",
    "sg:address":"18751 Lyndon B Johnson Fwy",
    "sg:city":"Mesquite",
    "sg:classifiers":[
        {
            "category":"Restaurant",
            "type":"Food & Drink"
        }
    ],
    "sg:menulink":"http://www.allmenus.com/tx/northeast/202250-mcdonalds/menu/",
    "sg:postcode":"75150",
    "sg:province":"TX",
    "sg:tags":[
        "burger",
        "american"
    ],
    "wof:name":"McDonald's",
    "wof:placetype":"venue"
},
  "geometry": {"coordinates":[-96.627222,32.80065],"type":"Point"}
}