{
  "type": "Feature",
  "properties": {
    "iso:country":"US",
    "sg:address":"6811 Washita Way",
    "sg:city":"San Antonio",
    "sg:classifiers":[
        {
            "category":"Shopping",
            "subcategory":"Gifts & Souvenirs",
            "type":"Retail Goods"
        }
    ],
    "sg:phone":"+1 210 212 5233",
    "sg:postcode":"78256",
    "sg:province":"TX",
    "wof:name":"Fiesta Gourmet of Tejas",
    "wof:placetype":"venue"
},
  "geometry": {"coordinates":[-98.614768,29.611864],"type":"Point"}
}