{
  "type": "Feature",
  "properties": {
    "iso:country":"US",
    "sg:address":"620 Yorktown St",
    "sg:city":"Dallas",
    "sg:classifiers":[
        {
            "category":"Retail",
            "subcategory":"Laundry & Dry Cleaning",
            "type":"Services"
        }
    ],
    "sg:phone":"+1 214 741 1751",
    "sg:postcode":"75208",
    "sg:province":"TX",
    "sg:tags":[
        "linen",
        "supply"
    ],
    "sg:website":"www.national-linen.com",
    "wof:name":"National Linen Svc",
    "wof:placetype":"venue"
},
  "geometry": {"coordinates":[-96.83314799999999,32.770895],"type":"Point"}
}