{
  "type": "Feature",
  "properties": {
    "iso:country":"US",
    "sg:address":"1318 Crockett St",
    "sg:city":"Garland",
    "sg:classifiers":[
        {
            "category":"Building & Trades",
            "subcategory":"Electrical",
            "type":"Services"
        }
    ],
    "sg:phone":"+1 972 276 2672",
    "sg:postcode":"75040",
    "sg:province":"TX",
    "sg:tags":[
        "repair",
        "electrical",
        "contractor"
    ],
    "wof:name":"Jims TV Service",
    "wof:placetype":"venue"
},
  "geometry": {"coordinates":[-96.64535100000001,32.925995],"type":"Point"}
}