{
  "type": "Feature",
  "properties": {
    "iso:country":"US",
    "sg:address":"164 Byrd Ln",
    "sg:city":"Pottsboro",
    "sg:classifiers":[
        {
            "category":"Communications",
            "subcategory":"Radio Station",
            "type":"Services"
        }
    ],
    "sg:phone":"+1 903 786 7253",
    "sg:postcode":"75076",
    "sg:province":"TX",
    "sg:tags":[
        "broadcast"
    ],
    "wof:name":"Monroe Stephens Broadcasting",
    "wof:placetype":"venue"
},
  "geometry": {"coordinates":[-96.721462,33.821312],"type":"Point"}
}