{
  "type": "Feature",
  "properties": {
    "iso:country":"US",
    "sg:address":"1947 Gessner Dr",
    "sg:city":"Houston",
    "sg:classifiers":[
        {
            "category":"Building & Trades",
            "subcategory":"Construction",
            "type":"Services"
        }
    ],
    "sg:phone":"+1 281 808 9454",
    "sg:postcode":"77080",
    "sg:province":"TX",
    "sg:tags":[
        "planning",
        "remodeling",
        "kitchen"
    ],
    "wof:name":"Davis Kitchen Designers",
    "wof:placetype":"venue"
},
  "geometry": {"coordinates":[-95.545239,29.807753],"type":"Point"}
}