{
  "type": "Feature",
  "properties": {
    "iso:country":"US",
    "sg:address":"1553 Gravel Cir N",
    "sg:city":"Southlake",
    "sg:classifiers":[
        {
            "category":"Home & Garden",
            "subcategory":"Building Materials",
            "type":"Retail Goods"
        }
    ],
    "sg:phone":"+1 817 481 7633",
    "sg:postcode":"76092",
    "sg:province":"TX",
    "sg:tags":[
        "glass",
        "window",
        "plate"
    ],
    "wof:name":"Southlake Glass & Mirror",
    "wof:placetype":"venue"
},
  "geometry": {"coordinates":[-97.12576300000001,32.977164],"type":"Point"}
}