{
  "type": "Feature",
  "properties": {
    "iso:country":"US",
    "sg:address":"10245 Kempwood Dr",
    "sg:city":"Houston",
    "sg:classifiers":[
        {
            "category":"Restaurant",
            "type":"Food & Drink"
        }
    ],
    "sg:menulink":"http://www.allmenus.com/tx/houston/85909-little-caesars-pizza/menu/",
    "sg:phone":"+1 713 462 7422",
    "sg:postcode":"77043",
    "sg:province":"TX",
    "sg:tags":[
        "american",
        "pizza"
    ],
    "wof:name":"Little Caesar's Pizza",
    "wof:placetype":"venue"
},
  "geometry": {"coordinates":[-95.546789,29.822615],"type":"Point"}
}