{
  "type": "Feature",
  "properties": {
    "iso:country":"US",
    "sg:address":"1505 Williams Dr",
    "sg:city":"Garland",
    "sg:classifiers":[
        {
            "category":"Farming",
            "subcategory":"Farm",
            "type":"Manufacturing & Wholesale Goods"
        }
    ],
    "sg:phone":"+1 972 271 1021",
    "sg:postcode":"75042",
    "sg:province":"TX",
    "sg:tags":[
        "food",
        "grown",
        "cover",
        "crop",
        "under"
    ],
    "wof:name":"Jerry Mabes Tree Care",
    "wof:placetype":"venue"
},
  "geometry": {"coordinates":[-96.650215,32.897515],"type":"Point"}
}