{
  "type": "Feature",
  "properties": {
    "iso:country":"US",
    "sg:address":"18474 US Hwy 59",
    "sg:city":"New Caney",
    "sg:classifiers":[
        {
            "category":"Home & Garden",
            "subcategory":"Household Appliances",
            "type":"Retail Goods"
        }
    ],
    "sg:phone":"+1 281 399 0100",
    "sg:postcode":"77357",
    "sg:province":"TX",
    "wof:name":"J & R Appliances",
    "wof:placetype":"venue"
},
  "geometry": {"coordinates":[-95.20011,30.178967],"type":"Point"}
}