{
  "type": "Feature",
  "properties": {
    "iso:country":"US",
    "sg:address":"1300 Johnny Dr",
    "sg:city":"Port Lavaca",
    "sg:classifiers":[
        {
            "category":"Retail",
            "subcategory":"Auto Repair",
            "type":"Services"
        }
    ],
    "sg:phone":"+1 361 552 1723",
    "sg:postcode":"77979",
    "sg:province":"TX",
    "sg:tags":[
        "repairing",
        "automobile",
        "general"
    ],
    "wof:name":"Dwayne's Auto Repair",
    "wof:placetype":"venue"
},
  "geometry": {"coordinates":[-96.63489800000001,28.609582],"type":"Point"}
}