{
  "type": "Feature",
  "properties": {
    "iso:country":"US",
    "sg:address":"1716 County Road 212 E",
    "sg:city":"Henderson",
    "sg:classifiers":[
        {
            "category":"Personal",
            "type":"Services"
        }
    ],
    "sg:phone":"+1 903 836 4073",
    "sg:postcode":"75652",
    "sg:province":"TX",
    "sg:tags":[
        "party",
        "planning",
        "event"
    ],
    "wof:name":"Party Plans Etc",
    "wof:placetype":"venue"
},
  "geometry": {"coordinates":[-94.814645,32.210091],"type":"Point"}
}