{
  "type": "Feature",
  "properties": {
    "iso:country":"US",
    "sg:address":"10001 Westheimer Rd",
    "sg:city":"Houston",
    "sg:classifiers":[
        {
            "category":"Restaurant",
            "type":"Food & Drink"
        }
    ],
    "sg:menulink":"http://www.allmenus.com/tx/houston/222808-chicken-kitchen/menu/",
    "sg:phone":"+1 713 952 5300",
    "sg:postcode":"77042",
    "sg:province":"TX",
    "sg:tags":[
        "american",
        "wing"
    ],
    "wof:name":"Chicken Kitchen",
    "wof:placetype":"venue"
},
  "geometry": {"coordinates":[-95.54943,29.736109],"type":"Point"}
}