{
  "type": "Feature",
  "properties": {
    "iso:country":"US",
    "sg:address":"2801 Hillcroft St",
    "sg:city":"Houston",
    "sg:classifiers":[
        {
            "category":"Restaurant",
            "type":"Food & Drink"
        }
    ],
    "sg:menulink":"http://www.allmenus.com/tx/houston/177501-jack-in-the-box/menu/",
    "sg:phone":"+1 713 783 4977",
    "sg:postcode":"77057",
    "sg:province":"TX",
    "sg:tags":[
        "burger",
        "american"
    ],
    "wof:name":"Jack in the Box",
    "wof:placetype":"venue"
},
  "geometry": {"coordinates":[-95.50037,29.735796],"type":"Point"}
}