{
  "type": "Feature",
  "properties": {
    "iso:country":"US",
    "sg:address":"2610 Raven Falls Ln",
    "sg:city":"Friendswood",
    "sg:classifiers":[
        {
            "category":"Shopping",
            "subcategory":"Clothing, Apparel, & Fashions",
            "type":"Retail Goods"
        }
    ],
    "sg:phone":"+1 281 482 4723",
    "sg:postcode":"77546",
    "sg:province":"TX",
    "sg:tags":[
        "electrical",
        "contract"
    ],
    "wof:name":"Rema L L C",
    "wof:placetype":"venue"
},
  "geometry": {"coordinates":[-95.17068399999999,29.535535],"type":"Point"}
}