{
  "type": "Feature",
  "properties": {
    "iso:country":"US",
    "sg:address":"1404 Heath St",
    "sg:city":"Merkel",
    "sg:classifiers":[
        {
            "category":"Retail",
            "subcategory":"Repair Shop",
            "type":"Services"
        }
    ],
    "sg:phone":"+1 325 928 4797",
    "sg:postcode":"79536",
    "sg:province":"TX",
    "sg:tags":[
        "welding"
    ],
    "wof:name":"Big Country Welding",
    "wof:placetype":"venue"
},
  "geometry": {"coordinates":[-100.01940500000001,32.461021],"type":"Point"}
}