{
  "type": "Feature",
  "properties": {
    "iso:country":"US",
    "sg:address":"8533 Ferndale Rd Ste 201",
    "sg:city":"Dallas",
    "sg:classifiers":[
        {
            "category":"Building & Trades",
            "subcategory":"Construction",
            "type":"Services"
        }
    ],
    "sg:phone":"+1 214 348 8700",
    "sg:postcode":"75238",
    "sg:province":"TX",
    "sg:tags":[
        "contractor"
    ],
    "wof:name":"Jacobie Hollis Co the",
    "wof:placetype":"venue"
},
  "geometry": {"coordinates":[-96.71080000000001,32.864899],"type":"Point"}
}