{
  "type": "Feature",
  "properties": {
    "iso:country":"US",
    "sg:address":"112 W Knox St",
    "sg:city":"Ennis",
    "sg:classifiers":[
        {
            "category":"Shopping",
            "subcategory":"Florist",
            "type":"Retail Goods"
        },
        {
            "category":"Shopping",
            "subcategory":"Gifts & Souvenirs",
            "type":"Retail Goods"
        }
    ],
    "sg:phone":"+1 972 878 6616",
    "sg:postcode":"75119",
    "sg:province":"TX",
    "wof:name":"Garden Gate Floral & Gifts",
    "wof:placetype":"venue"
},
  "geometry": {"coordinates":[-96.627773,32.328655],"type":"Point"}
}