{
  "type": "Feature",
  "properties": {
    "iso:country":"US",
    "sg:address":"8100 Seawall Blvd Apt 280",
    "sg:city":"Galveston",
    "sg:classifiers":[
        {
            "category":"Professional",
            "subcategory":"Detective & Security Services",
            "type":"Services"
        }
    ],
    "sg:phone":"+1 409 457 7136",
    "sg:postcode":"77551",
    "sg:province":"TX",
    "sg:tags":[
        "information",
        "bureau"
    ],
    "wof:name":"Pat's Mobile Notary Services",
    "wof:placetype":"venue"
},
  "geometry": {"coordinates":[-94.84520000000001,29.25598],"type":"Point"}
}