{
  "type": "Feature",
  "properties": {
    "iso:country":"US",
    "sg:address":"2620 Fountain View Dr Ste 108",
    "sg:city":"Houston",
    "sg:classifiers":[
        {
            "category":"Professional",
            "subcategory":"Employment Agencies",
            "type":"Services"
        }
    ],
    "sg:phone":"+1 713 270 4734",
    "sg:postcode":"77057",
    "sg:province":"TX",
    "wof:name":"Favorite Healthcare Staffing Inc",
    "wof:placetype":"venue"
},
  "geometry": {"coordinates":[-95.484829,29.7402],"type":"Point"}
}