{
  "type": "Feature",
  "properties": {
    "iso:country":"US",
    "sg:address":"8901 Whispering Mdws",
    "sg:city":"Celina",
    "sg:classifiers":[
        {
            "category":"Farming",
            "subcategory":"Farm",
            "type":"Manufacturing & Wholesale Goods"
        }
    ],
    "sg:phone":"+1 214 727 2789",
    "sg:postcode":"75009",
    "sg:province":"TX",
    "wof:name":"Halter Cross Farm",
    "wof:placetype":"venue"
},
  "geometry": {"coordinates":[-96.740448,33.38052],"type":"Point"}
}