{
  "type": "Feature",
  "properties": {
    "iso:country":"US",
    "sg:address":"30419 Glenboro Dr",
    "sg:city":"Spring",
    "sg:classifiers":[
        {
            "category":"Professional",
            "subcategory":"Research",
            "type":"Services"
        }
    ],
    "sg:phone":"+1 281 419 4980",
    "sg:postcode":"77386",
    "sg:province":"TX",
    "wof:name":"Aspen Research Group",
    "wof:placetype":"venue"
},
  "geometry": {"coordinates":[-95.406481,30.13212],"type":"Point"}
}