{
  "type": "Feature",
  "properties": {
    "iso:country":"US",
    "sg:address":"5806 Mesa Dr Ste 375",
    "sg:city":"Austin",
    "sg:classifiers":[
        {
            "category":"Professional",
            "subcategory":"Accounting & Tax Preparation",
            "type":"Services"
        }
    ],
    "sg:phone":"+1 512 649 2212",
    "sg:postcode":"78731",
    "sg:province":"TX",
    "sg:tags":[
        "bookkeeping",
        "return",
        "preparation-business"
    ],
    "sg:website":"http://www.premiertaxservice.org",
    "wof:name":"Premier Tax Service",
    "wof:placetype":"venue"
},
  "geometry": {"coordinates":[-97.77076,30.34288],"type":"Point"}
}