{
  "type": "Feature",
  "properties": {
    "iso:country":"US",
    "sg:address":"14420 US Hwy 290",
    "sg:city":"Stonewall",
    "sg:classifiers":[
        {
            "category":"Shopping",
            "subcategory":"Gifts & Souvenirs",
            "type":"Retail Goods"
        }
    ],
    "sg:phone":"+1 830 644 2828",
    "sg:postcode":"78671",
    "sg:province":"TX",
    "sg:tags":[
        "shop"
    ],
    "wof:name":"Davis Emporium",
    "wof:placetype":"venue"
},
  "geometry": {"coordinates":[-98.678732,30.230209],"type":"Point"}
}