{
  "type": "Feature",
  "properties": {
    "iso:country":"US",
    "sg:address":"1341 W Mockingbird Ln Ste 710E",
    "sg:city":"Dallas",
    "sg:classifiers":[
        {
            "category":"Professional",
            "subcategory":"Lawyer & Legal Services",
            "type":"Services"
        }
    ],
    "sg:phone":"+1 214 819 2400",
    "sg:postcode":"75247",
    "sg:province":"TX",
    "wof:name":"Krause Earwood & Ward PC",
    "wof:placetype":"venue"
},
  "geometry": {"coordinates":[-96.865799,32.821301],"type":"Point"}
}