{
  "type": "Feature",
  "properties": {
    "iso:country":"US",
    "sg:address":"8501 Grassbur Rd",
    "sg:city":"Bryan",
    "sg:classifiers":[
        {
            "category":"Banks & Credit Unions",
            "subcategory":"Financial Services",
            "type":"Services"
        }
    ],
    "sg:phone":"+1 979 589 3203",
    "sg:postcode":"77808",
    "sg:province":"TX",
    "sg:tags":[
        "investor"
    ],
    "wof:name":"Best Properties & Investments",
    "wof:placetype":"venue"
},
  "geometry": {"coordinates":[-96.239682,30.724123],"type":"Point"}
}