{
  "type": "Feature",
  "properties": {
    "iso:country":"US",
    "sg:address":"911 N 14th St",
    "sg:city":"Kingsville",
    "sg:classifiers":[
        {
            "category":"Shopping",
            "subcategory":"Luggage & Leather Goods",
            "type":"Retail Goods"
        },
        {
            "category":"Wholesale",
            "subcategory":"Non-durable Goods",
            "type":"Manufacturing & Wholesale Goods"
        }
    ],
    "sg:phone":"+1 361 592 5995",
    "sg:postcode":"78363",
    "sg:province":"TX",
    "wof:name":"Jerry's Leather Crafts",
    "wof:placetype":"venue"
},
  "geometry": {"coordinates":[-97.85621,27.525236],"type":"Point"}
}