{
  "type": "Feature",
  "properties": {
    "iso:country":"US",
    "sg:address":"2814 Canyon Creek Dr",
    "sg:city":"San Angelo",
    "sg:classifiers":[
        {
            "category":"Utilities",
            "subcategory":"Natural Gas",
            "type":"Services"
        }
    ],
    "sg:phone":"+1 325 944 3017",
    "sg:postcode":"76904",
    "sg:province":"TX",
    "sg:tags":[
        "company"
    ],
    "wof:name":"Ventura Gas Corp",
    "wof:placetype":"venue"
},
  "geometry": {"coordinates":[-100.48289,31.416851],"type":"Point"}
}