{
  "type": "Feature",
  "properties": {
    "iso:country":"US",
    "sg:address":"908 Pennsylvania Ave",
    "sg:city":"Fort Worth",
    "sg:classifiers":[
        {
            "category":"Organizations",
            "subcategory":"Religious Organization",
            "type":"Services"
        }
    ],
    "sg:phone":"+1 817 335 3222",
    "sg:postcode":"76104",
    "sg:province":"TX",
    "wof:name":"Celebration Community Church",
    "wof:placetype":"venue"
},
  "geometry": {"coordinates":[-97.335194,32.738548],"type":"Point"}
}