{
  "type": "Feature",
  "properties": {
    "iso:country":"US",
    "sg:address":"2615 Gwendolyn Ln",
    "sg:city":"Austin",
    "sg:classifiers":[
        {
            "category":"Building & Trades",
            "subcategory":"Construction",
            "type":"Services"
        }
    ],
    "sg:phone":"+1 512 280 0805",
    "sg:postcode":"78748",
    "sg:province":"TX",
    "sg:tags":[
        "house"
    ],
    "wof:name":"Tara Steel Structures",
    "wof:placetype":"venue"
},
  "geometry": {"coordinates":[-97.837819,30.174472],"type":"Point"}
}