{
  "type": "Feature",
  "properties": {
    "iso:country":"US",
    "sg:address":"8600 Park Place Blvd",
    "sg:city":"Houston",
    "sg:classifiers":[
        {
            "category":"Wholesale",
            "subcategory":"Chemicals & Plastics",
            "type":"Manufacturing & Wholesale Goods"
        }
    ],
    "sg:phone":"+1 713 477 9211",
    "sg:postcode":"77017",
    "sg:province":"TX",
    "sg:tags":[
        "preparation",
        "mfg"
    ],
    "wof:name":"Texas Petrochemicals Corp",
    "wof:placetype":"venue"
},
  "geometry": {"coordinates":[-95.262675,29.696377],"type":"Point"}
}