{
  "type": "Feature",
  "properties": {
    "iso:country":"US",
    "sg:address":"1703 West Ave",
    "sg:city":"Austin",
    "sg:classifiers":[
        {
            "category":"Professional",
            "subcategory":"Lawyer & Legal Services",
            "type":"Services"
        }
    ],
    "sg:phone":"+1 512 236 1300",
    "sg:postcode":"78701",
    "sg:province":"TX",
    "wof:name":"Lee Steven C Attorney At Law",
    "wof:placetype":"venue"
},
  "geometry": {"coordinates":[-97.74620899999999,30.281789],"type":"Point"}
}