{
  "type": "Feature",
  "properties": {
    "iso:country":"US",
    "sg:address":"415 W Marshall Ave",
    "sg:city":"Longview",
    "sg:classifiers":[
        {
            "category":"Wholesale",
            "subcategory":"Auto Parts",
            "type":"Manufacturing & Wholesale Goods"
        }
    ],
    "sg:phone":"+1 903 758 5824",
    "sg:postcode":"75601",
    "sg:province":"TX",
    "sg:tags":[
        "tire"
    ],
    "wof:name":"Southwest Tire & Supply",
    "wof:placetype":"venue"
},
  "geometry": {"coordinates":[-94.745374,32.500101],"type":"Point"}
}