{
  "type": "Feature",
  "properties": {
    "iso:country":"US",
    "sg:address":"404 E Reuss Blvd",
    "sg:city":"Cuero",
    "sg:classifiers":[
        {
            "category":"Transit Center",
            "subcategory":"Freight",
            "type":"Transportation"
        },
        {
            "category":"Professional",
            "subcategory":"Advertising",
            "type":"Services"
        }
    ],
    "sg:phone":"+1 361 275 6395",
    "sg:postcode":"77954",
    "sg:province":"TX",
    "sg:tags":[
        "outdoor"
    ],
    "wof:name":"Fny Outdoor Advertising",
    "wof:placetype":"venue"
},
  "geometry": {"coordinates":[-97.284195,29.097177],"type":"Point"}
}