{
  "type": "Feature",
  "properties": {
    "iso:country":"US",
    "sg:address":"516 2nd St",
    "sg:city":"Graham",
    "sg:classifiers":[
        {
            "category":"Banks & Credit Unions",
            "subcategory":"Investment Brokerage",
            "type":"Services"
        }
    ],
    "sg:phone":"+1 940 549 9898",
    "sg:postcode":"76450",
    "sg:province":"TX",
    "sg:tags":[
        "security"
    ],
    "wof:name":"American Express",
    "wof:placetype":"venue"
},
  "geometry": {"coordinates":[-98.591014,33.104698],"type":"Point"}
}