{
  "type": "Feature",
  "properties": {
    "iso:country":"US",
    "sg:address":"3838 Shiloh Rd",
    "sg:city":"Richardson",
    "sg:classifiers":[
        {
            "category":"Wholesale",
            "subcategory":"Petroleum",
            "type":"Manufacturing & Wholesale Goods"
        }
    ],
    "sg:phone":"+1 972 235 3214",
    "sg:postcode":"75022",
    "sg:province":"TX",
    "sg:tags":[
        "pipeline"
    ],
    "wof:name":"Explorer Pipeline Richardson",
    "wof:placetype":"venue"
},
  "geometry": {"coordinates":[-97.129035,33.039004],"type":"Point"}
}