{
  "type": "Feature",
  "properties": {
    "iso:country":"US",
    "sg:address":"2975 Penoak Ave",
    "sg:city":"Ingleside",
    "sg:classifiers":[
        {
            "category":"Freight",
            "type":"Transportation"
        }
    ],
    "sg:phone":"+1 361 776 2174",
    "sg:postcode":"78362",
    "sg:province":"TX",
    "sg:tags":[
        "local",
        "trucking"
    ],
    "wof:name":"Z and C Trucking",
    "wof:placetype":"venue"
},
  "geometry": {"coordinates":[-97.189786,27.87565],"type":"Point"}
}