{
  "type": "Feature",
  "properties": {
    "iso:country":"US",
    "sg:address":"424 Llano Ct",
    "sg:city":"Weatherford",
    "sg:classifiers":[
        {
            "category":"Shopping",
            "subcategory":"Gifts & Souvenirs",
            "type":"Retail Goods"
        }
    ],
    "sg:phone":"+1 817 448 9755",
    "sg:postcode":"76087",
    "sg:province":"TX",
    "wof:name":"Editions Et Cetera",
    "wof:placetype":"venue"
},
  "geometry": {"coordinates":[-97.589027,32.796645],"type":"Point"}
}