{
  "type": "Feature",
  "properties": {
    "iso:country":"US",
    "sg:address":"2212 S Cooper St",
    "sg:city":"Arlington",
    "sg:classifiers":[
        {
            "category":"Retail",
            "subcategory":"Veterinary Services",
            "type":"Services"
        }
    ],
    "sg:phone":"+1 817 277 1127",
    "sg:postcode":"76013",
    "sg:province":"TX",
    "sg:tags":[
        "hospital",
        "animal"
    ],
    "wof:name":"Cooper Street Animal Hospital",
    "wof:placetype":"venue"
},
  "geometry": {"coordinates":[-97.116905,32.707293],"type":"Point"}
}