{
  "type": "Feature",
  "properties": {
    "iso:country":"US",
    "sg:address":"22311 Sierra Blanca",
    "sg:city":"San Antonio",
    "sg:classifiers":[
        {
            "category":"Wholesale",
            "subcategory":"Medical Equipment & Supplies",
            "type":"Manufacturing & Wholesale Goods"
        }
    ],
    "sg:phone":"+1 210 602 6600",
    "sg:postcode":"78259",
    "sg:province":"TX",
    "sg:tags":[
        "distribution"
    ],
    "wof:name":"Imagine Medical",
    "wof:placetype":"venue"
},
  "geometry": {"coordinates":[-98.431049,29.652927],"type":"Point"}
}