{
  "type": "Feature",
  "properties": {
    "iso:country":"US",
    "sg:address":"2720 Stain Glass Ct",
    "sg:city":"Carrollton",
    "sg:classifiers":[
        {
            "category":"Organizations",
            "subcategory":"Religious Organization",
            "type":"Services"
        }
    ],
    "sg:phone":"+1 972 236 5700",
    "sg:postcode":"75007",
    "sg:province":"TX",
    "wof:name":"Trinity Health & Home Care",
    "wof:placetype":"venue"
},
  "geometry": {"coordinates":[-96.89707300000001,32.989501],"type":"Point"}
}