{
  "type": "Feature",
  "properties": {
    "iso:country":"US",
    "sg:address":"2303 Ave C",
    "sg:city":"Grand Prairie",
    "sg:classifiers":[
        {
            "category":"Shopping",
            "type":"Retail Goods"
        }
    ],
    "sg:phone":"+1 972 263 6863",
    "sg:postcode":"75051",
    "sg:province":"TX",
    "sg:tags":[
        "merchandise"
    ],
    "wof:name":"Prairie Angel Candles",
    "wof:placetype":"venue"
},
  "geometry": {"coordinates":[-96.982378,32.712119],"type":"Point"}
}