{
  "type": "Feature",
  "properties": {
    "iso:country":"US",
    "sg:address":"7815 Fulton St",
    "sg:city":"Houston",
    "sg:classifiers":[
        {
            "category":"Restaurant",
            "type":"Food & Drink"
        }
    ],
    "sg:menulink":"http://www.allmenus.com/tx/houston/70518-pizza-hut/menu/",
    "sg:phone":"+1 713 695 0384",
    "sg:postcode":"77022",
    "sg:province":"TX",
    "sg:tags":[
        "american",
        "pizza"
    ],
    "wof:name":"Pizza Hut",
    "wof:placetype":"venue"
},
  "geometry": {"coordinates":[-95.376847,29.831951],"type":"Point"}
}