{
  "type": "Feature",
  "properties": {
    "iso:country":"US",
    "sg:address":"1450 Preston Rd",
    "sg:city":"Dallas",
    "sg:classifiers":[
        {
            "category":"Personal",
            "subcategory":"Nail Salon",
            "type":"Services"
        }
    ],
    "sg:phone":"+1 972 661 5750",
    "sg:postcode":"75230",
    "sg:province":"TX",
    "wof:name":"Joys Nails",
    "wof:placetype":"venue"
},
  "geometry": {"coordinates":[-96.804016,32.896946],"type":"Point"}
}