{
  "type": "Feature",
  "properties": {
    "iso:country":"US",
    "sg:address":"16730 Jacintoport Blvd",
    "sg:city":"Houston",
    "sg:classifiers":[
        {
            "category":"Manufacturing",
            "subcategory":"Tools & Machinery",
            "type":"Manufacturing & Wholesale Goods"
        }
    ],
    "sg:phone":"+1 281 452 7900",
    "sg:postcode":"77015",
    "sg:province":"TX",
    "sg:tags":[
        "manufacture",
        "field",
        "oil",
        "equipment"
    ],
    "wof:name":"Dreco Channelview",
    "wof:placetype":"venue"
},
  "geometry": {"coordinates":[-95.11609199999999,29.747441],"type":"Point"}
}