{
  "type": "Feature",
  "properties": {
    "iso:country":"US",
    "sg:address":"1100 Morrow St",
    "sg:city":"Austin",
    "sg:classifiers":[
        {
            "category":"Health Services",
            "subcategory":"Optometrist",
            "type":"Services"
        }
    ],
    "sg:phone":"+1 512 451 8355",
    "sg:postcode":"78757",
    "sg:province":"TX",
    "wof:name":"North Austin Optimist Club",
    "wof:placetype":"venue"
},
  "geometry": {"coordinates":[-97.71860700000001,30.345987],"type":"Point"}
}