{
  "type": "Feature",
  "properties": {
    "iso:country":"US",
    "sg:address":"1300 Preston Rd",
    "sg:city":"Plano",
    "sg:classifiers":[
        {
            "category":"Banks & Credit Unions",
            "subcategory":"Bank",
            "type":"Services"
        }
    ],
    "sg:phone":"+1 972 985 7311",
    "sg:postcode":"75093",
    "sg:province":"TX",
    "sg:tags":[
        "mortgage"
    ],
    "wof:name":"Cornerstone Mortgage Company",
    "wof:placetype":"venue"
},
  "geometry": {"coordinates":[-96.79515600000001,33.017922],"type":"Point"}
}