{
  "type": "Feature",
  "properties": {
    "iso:country":"US",
    "sg:address":"6818 Austin Center Blvd Ste 202",
    "sg:city":"Austin",
    "sg:classifiers":[
        {
            "category":"Health Services",
            "subcategory":"Doctor",
            "type":"Services"
        }
    ],
    "sg:phone":"+1 512 346 7600",
    "sg:postcode":"78731",
    "sg:province":"TX",
    "wof:name":"Fyfe Steven Trey",
    "wof:placetype":"venue"
},
  "geometry": {"coordinates":[-97.751278,30.350617],"type":"Point"}
}