{
  "type": "Feature",
  "properties": {
    "iso:country":"US",
    "sg:address":"9100 Forest Ln",
    "sg:city":"Dallas",
    "sg:classifiers":[
        {
            "category":"Autos & Motor Vehicles",
            "subcategory":"Fuel & Gas Station",
            "type":"Retail Goods"
        }
    ],
    "sg:phone":"+1 214 343 8443",
    "sg:postcode":"75243",
    "sg:province":"TX",
    "sg:tags":[
        "convenience",
        "oil",
        "store"
    ],
    "sg:website":"www.mobil.com",
    "wof:name":"Green Forest Mobil",
    "wof:placetype":"venue"
},
  "geometry": {"coordinates":[-96.746837,32.908922],"type":"Point"}
}