{
  "type": "Feature",
  "properties": {
    "iso:country":"US",
    "sg:address":"901 Clark Blvd",
    "sg:city":"Laredo",
    "sg:classifiers":[
        {
            "category":"Shopping",
            "type":"Retail Goods"
        }
    ],
    "sg:phone":"+1 956 791 0399",
    "sg:postcode":"78040",
    "sg:province":"TX",
    "sg:tags":[
        "craft",
        "gallery",
        "dealer"
    ],
    "wof:name":"Fabiola",
    "wof:placetype":"venue"
},
  "geometry": {"coordinates":[-99.48653299999999,27.516675],"type":"Point"}
}