{
  "type": "Feature",
  "properties": {
    "iso:country":"US",
    "sg:address":"1716 Banks St",
    "sg:city":"Houston",
    "sg:classifiers":[
        {
            "category":"Professional",
            "subcategory":"Advertising",
            "type":"Services"
        }
    ],
    "sg:phone":"+1 713 522 9205",
    "sg:postcode":"77098",
    "sg:province":"TX",
    "sg:tags":[
        "promotion",
        "sale"
    ],
    "wof:name":"Cavnar Co",
    "wof:placetype":"venue"
},
  "geometry": {"coordinates":[-95.402478,29.729599],"type":"Point"}
}