{
  "type": "Feature",
  "properties": {
    "iso:country":"US",
    "sg:address":"5 Spring Valley Ct",
    "sg:city":"Richardson",
    "sg:classifiers":[
        {
            "category":"Recreation",
            "type":"Entertainment"
        }
    ],
    "sg:phone":"+1 972 690 6764",
    "sg:postcode":"75081",
    "sg:province":"TX",
    "wof:name":"Kims College of Tae Kwon Do",
    "wof:placetype":"venue"
},
  "geometry": {"coordinates":[-96.71107499999999,32.939069],"type":"Point"}
}