{
  "type": "Feature",
  "properties": {
    "iso:country":"US",
    "sg:address":"709 W Abram St",
    "sg:city":"Arlington",
    "sg:classifiers":[
        {
            "category":"Education",
            "subcategory":"Special Training",
            "type":"Public Place"
        }
    ],
    "sg:phone":"+1 817 795 8141",
    "sg:postcode":"76013",
    "sg:province":"TX",
    "sg:tags":[
        "tutoring"
    ],
    "sg:website":"www.professionaltutoring.com",
    "wof:name":"Knowledge Guides",
    "wof:placetype":"venue"
},
  "geometry": {"coordinates":[-97.11605,32.735839],"type":"Point"}
}