{
  "type": "Feature",
  "properties": {
    "iso:country":"US",
    "sg:address":"6211 Edloe St",
    "sg:city":"Houston",
    "sg:classifiers":[
        {
            "category":"Sports & Exercise",
            "subcategory":"Gym",
            "type":"Entertainment"
        }
    ],
    "sg:phone":"+1 713 661 5800",
    "sg:postcode":"77005",
    "sg:province":"TX",
    "sg:tags":[
        "trainer",
        "pilate"
    ],
    "sg:website":"www.westufit.com",
    "wof:name":"West U Fitness",
    "wof:placetype":"venue"
},
  "geometry": {"coordinates":[-95.433817,29.715562],"type":"Point"}
}