{
  "type": "Feature",
  "properties": {
    "iso:country":"US",
    "sg:address":"1601 Chasewood Dr",
    "sg:city":"Austin",
    "sg:classifiers":[
        {
            "category":"Professional",
            "subcategory":"Business Services",
            "type":"Services"
        }
    ],
    "sg:phone":"+1 512 990 2349",
    "sg:postcode":"78727",
    "sg:province":"TX",
    "wof:name":"Mandavia Enterprises Inc",
    "wof:placetype":"venue"
},
  "geometry": {"coordinates":[-97.68092,30.421324],"type":"Point"}
}