{
  "type": "Feature",
  "properties": {
    "iso:country":"US",
    "sg:address":"1211 Zeola St",
    "sg:city":"Longview",
    "sg:classifiers":[
        {
            "category":"Professional",
            "subcategory":"Business Services",
            "type":"Services"
        }
    ],
    "sg:phone":"+1 903 234 2407",
    "sg:postcode":"75604",
    "sg:province":"TX",
    "wof:name":"Ford Real Estate Inspection",
    "wof:placetype":"venue"
},
  "geometry": {"coordinates":[-94.76691099999999,32.507765],"type":"Point"}
}