{
  "type": "Feature",
  "properties": {
    "iso:country":"US",
    "sg:address":"1115 Broadway St",
    "sg:city":"Lubbock",
    "sg:classifiers":[
        {
            "category":"Professional",
            "subcategory":"Lawyer & Legal Services",
            "type":"Services"
        }
    ],
    "sg:phone":"+1 806 763 2146",
    "sg:postcode":"79401",
    "sg:province":"TX",
    "sg:tags":[
        "attorney"
    ],
    "wof:name":"Sam L Fadduol Law Offices",
    "wof:placetype":"venue"
},
  "geometry": {"coordinates":[-101.84780000000001,33.584407],"type":"Point"}
}