{
  "type": "Feature",
  "properties": {
    "iso:country":"US",
    "sg:address":"600 N Cotton St",
    "sg:city":"El Paso",
    "sg:classifiers":[
        {
            "category":"Wholesale",
            "subcategory":"Medical Equipment & Supplies",
            "type":"Manufacturing & Wholesale Goods"
        }
    ],
    "sg:phone":"+1 915 565 2604",
    "sg:postcode":"79902",
    "sg:province":"TX",
    "wof:name":"Global Medical Alliance",
    "wof:placetype":"venue"
},
  "geometry": {"coordinates":[-106.47348,31.772567],"type":"Point"}
}