{
  "type": "Feature",
  "properties": {
    "iso:country":"US",
    "sg:address":"1505 Elm St",
    "sg:city":"Dallas",
    "sg:classifiers":[
        {
            "category":"Real Estate",
            "subcategory":"Real Estate Services",
            "type":"Services"
        }
    ],
    "sg:phone":"+1 214 871 1505",
    "sg:postcode":"75201",
    "sg:province":"TX",
    "sg:website":"www.1505elmstreet.com",
    "wof:name":"1505 Elm Street Owners Association",
    "wof:placetype":"venue"
},
  "geometry": {"coordinates":[-96.79969800000001,32.781399],"type":"Point"}
}