{
  "type": "Feature",
  "properties": {
    "iso:country":"US",
    "sg:address":"943 N Grandview Ave",
    "sg:city":"Odessa",
    "sg:classifiers":[
        {
            "category":"Shopping",
            "subcategory":"Discount & Variety Stores",
            "type":"Retail Goods"
        }
    ],
    "sg:phone":"+1 432 333 8953",
    "sg:postcode":"79761",
    "sg:province":"TX",
    "wof:name":"Dollar Station",
    "wof:placetype":"venue"
},
  "geometry": {"coordinates":[-102.34657900000001,31.863323],"type":"Point"}
}