{
  "type": "Feature",
  "properties": {
    "iso:country":"US",
    "sg:address":"1618 W 6th St",
    "sg:city":"Texarkana",
    "sg:classifiers":[
        {
            "category":"Building & Trades",
            "subcategory":"Cleaning & Sanitation",
            "type":"Services"
        }
    ],
    "sg:phone":"+1 903 793 5687",
    "sg:postcode":"75501",
    "sg:province":"TX",
    "sg:tags":[
        "maintenance"
    ],
    "wof:name":"Kings Cleaning Services",
    "wof:placetype":"venue"
},
  "geometry": {"coordinates":[-94.06068399999999,33.422349],"type":"Point"}
}