{
  "type": "Feature",
  "properties": {
    "iso:country":"US",
    "sg:address":"9105 Hoffman Cove",
    "sg:city":"Austin",
    "sg:classifiers":[
        {
            "category":"Building & Trades",
            "subcategory":"Landscaping Services",
            "type":"Services"
        }
    ],
    "sg:phone":"+1 512 282 2933",
    "sg:postcode":"78749",
    "sg:province":"TX",
    "sg:tags":[
        "designer",
        "landscape"
    ],
    "wof:name":"Waterloo Design Co",
    "wof:placetype":"venue"
},
  "geometry": {"coordinates":[-97.855908,30.198235],"type":"Point"}
}