{
  "type": "Feature",
  "properties": {
    "iso:country":"US",
    "sg:address":"5858 Greenville Ave",
    "sg:city":"Dallas",
    "sg:classifiers":[
        {
            "category":"Shopping",
            "subcategory":"Mobile Phones",
            "type":"Retail Goods"
        }
    ],
    "sg:phone":"+1 214 360 4249",
    "sg:postcode":"75206",
    "sg:province":"TX",
    "wof:name":"Cellular Sales",
    "wof:placetype":"venue"
},
  "geometry": {"coordinates":[-96.76844699999999,32.856768],"type":"Point"}
}