{
  "type": "Feature",
  "properties": {
    "iso:country":"US",
    "sg:address":"10252 Brenden Dr",
    "sg:city":"Mckinney",
    "sg:classifiers":[
        {
            "category":"Real Estate",
            "subcategory":"Developer",
            "type":"Services"
        }
    ],
    "sg:phone":"+1 972 562 0527",
    "sg:postcode":"75070",
    "sg:province":"TX",
    "sg:tags":[
        "investing"
    ],
    "wof:name":"M.C. Investment Group",
    "wof:placetype":"venue"
},
  "geometry": {"coordinates":[-96.75432600000001,33.183581],"type":"Point"}
}