{
  "type": "Feature",
  "properties": {
    "iso:country":"US",
    "sg:address":"406 Sunset Dr",
    "sg:city":"Round Rock",
    "sg:classifiers":[
        {
            "category":"Retail",
            "subcategory":"Auto Repair",
            "type":"Services"
        }
    ],
    "sg:phone":"+1 512 255 3411",
    "sg:postcode":"78664",
    "sg:province":"TX",
    "sg:tags":[
        "body",
        "automobile",
        "painting"
    ],
    "wof:name":"Hester Automotive & Body Shop",
    "wof:placetype":"venue"
},
  "geometry": {"coordinates":[-97.685081,30.514749],"type":"Point"}
}