{
  "type": "Feature",
  "properties": {
    "iso:country":"US",
    "sg:address":"4201 52nd St",
    "sg:city":"Lubbock",
    "sg:classifiers":[
        {
            "category":"Building & Trades",
            "subcategory":"Plumbing",
            "type":"Services"
        }
    ],
    "sg:phone":"+1 806 792 7556",
    "sg:postcode":"79413",
    "sg:province":"TX",
    "sg:tags":[
        "contractor"
    ],
    "wof:name":"Welch Brothers Plumbing",
    "wof:placetype":"venue"
},
  "geometry": {"coordinates":[-101.90387,33.54685],"type":"Point"}
}