{
  "type": "Feature",
  "properties": {
    "iso:country":"US",
    "sg:address":"12520 Westheimer Rd",
    "sg:city":"Houston",
    "sg:classifiers":[
        {
            "category":"Professional",
            "subcategory":"Advertising",
            "type":"Services"
        }
    ],
    "sg:phone":"+1 281 496 6400",
    "sg:postcode":"77077",
    "sg:province":"TX",
    "sg:tags":[
        "mail",
        "direct"
    ],
    "wof:name":"Harsal Inc",
    "wof:placetype":"venue"
},
  "geometry": {"coordinates":[-95.603804,29.73622],"type":"Point"}
}