{
  "type": "Feature",
  "properties": {
    "iso:country":"US",
    "sg:address":"706 S Sandpiper St",
    "sg:city":"Ingleside",
    "sg:classifiers":[
        {
            "category":"Building & Trades",
            "subcategory":"Construction",
            "type":"Services"
        }
    ],
    "sg:phone":"+1 361 776 3026",
    "sg:postcode":"78336",
    "sg:province":"TX",
    "sg:tags":[
        "house"
    ],
    "wof:name":"Bill Windsor Construction",
    "wof:placetype":"venue"
},
  "geometry": {"coordinates":[-97.220832,27.825751],"type":"Point"}
}