{
  "type": "Feature",
  "properties": {
    "iso:country":"US",
    "sg:address":"807 Palm Grove Cir",
    "sg:city":"Sugar Land",
    "sg:classifiers":[
        {
            "category":"Banks & Credit Unions",
            "subcategory":"Financial Services",
            "type":"Services"
        }
    ],
    "sg:phone":"+1 281 242 4566",
    "sg:postcode":"77478",
    "sg:province":"TX",
    "sg:tags":[
        "trust",
        "management"
    ],
    "wof:name":"Four C Trust",
    "wof:placetype":"venue"
},
  "geometry": {"coordinates":[-95.624645,29.631781],"type":"Point"}
}