{
  "type": "Feature",
  "properties": {
    "iso:country":"US",
    "sg:address":"5605 Atlantis Ter",
    "sg:city":"Arlington",
    "sg:classifiers":[
        {
            "category":"Shopping",
            "subcategory":"Gifts & Souvenirs",
            "type":"Retail Goods"
        }
    ],
    "sg:phone":"+1 817 451 7861",
    "sg:postcode":"76016",
    "sg:province":"TX",
    "wof:name":"High Plains Petroglyphics",
    "wof:placetype":"venue"
},
  "geometry": {"coordinates":[-97.19029999999999,32.693591],"type":"Point"}
}