{
  "type": "Feature",
  "properties": {
    "iso:country":"US",
    "sg:address":"130 Grand Ave",
    "sg:city":"Bacliff",
    "sg:classifiers":[
        {
            "category":"Home & Garden",
            "subcategory":"Furniture",
            "type":"Retail Goods"
        }
    ],
    "sg:phone":"+1 713 462 5300",
    "sg:postcode":"77518",
    "sg:province":"TX",
    "sg:tags":[
        "mattress"
    ],
    "wof:name":"Adjustable Bed Repair",
    "wof:placetype":"venue"
},
  "geometry": {"coordinates":[-94.977896,29.510686],"type":"Point"}
}