{
  "type": "Feature",
  "properties": {
    "iso:country":"US",
    "sg:address":"282 E Seley",
    "sg:city":"Axtell",
    "sg:classifiers":[
        {
            "category":"Freight",
            "type":"Transportation"
        }
    ],
    "sg:phone":"+1 254 822 1501",
    "sg:postcode":"76624",
    "sg:province":"TX",
    "sg:tags":[
        "commercial",
        "storage"
    ],
    "wof:name":"Axtell Self-Storage",
    "wof:placetype":"venue"
},
  "geometry": {"coordinates":[-96.968999,31.65775],"type":"Point"}
}