{
  "type": "Feature",
  "properties": {
    "iso:country":"US",
    "sg:address":"7501 Chesterfield Dr",
    "sg:city":"Dallas",
    "sg:classifiers":[
        {
            "category":"Professional",
            "type":"Services"
        }
    ],
    "sg:phone":"+1 972 709 7354",
    "sg:postcode":"75237",
    "sg:province":"TX",
    "wof:name":"Lues",
    "wof:placetype":"venue"
},
  "geometry": {"coordinates":[-96.869889,32.658377],"type":"Point"}
}