{
  "type": "Feature",
  "properties": {
    "iso:country":"US",
    "sg:address":"17118 W Little York Rd",
    "sg:city":"Houston",
    "sg:phone":"+1 281 345 9168",
    "sg:postcode":"77084",
    "sg:province":"TX",
    "wof:name":"Paris Spa",
    "wof:placetype":"venue"
},
  "geometry": {"coordinates":[-95.669231,29.865326],"type":"Point"}
}