{
  "type": "Feature",
  "properties": {
    "iso:country":"US",
    "sg:address":"4523 S Hackberry St",
    "sg:city":"San Antonio",
    "sg:classifiers":[
        {
            "category":"Building & Trades",
            "subcategory":"Construction",
            "type":"Services"
        }
    ],
    "sg:phone":"+1 210 532 6247",
    "sg:postcode":"78223",
    "sg:province":"TX",
    "sg:tags":[
        "contractor"
    ],
    "wof:name":"Franco Tile",
    "wof:placetype":"venue"
},
  "geometry": {"coordinates":[-98.47348100000001,29.377161],"type":"Point"}
}