{
  "type": "Feature",
  "properties": {
    "iso:country":"US",
    "sg:address":"1501 SE Parkway St",
    "sg:city":"Azle",
    "sg:classifiers":[
        {
            "category":"Professional",
            "subcategory":"Lawyer & Legal Services",
            "type":"Services"
        }
    ],
    "sg:phone":"+1 817 237 5991",
    "sg:postcode":"76020",
    "sg:province":"TX",
    "sg:tags":[
        "attorney"
    ],
    "wof:name":"J Scott Spitzer",
    "wof:placetype":"venue"
},
  "geometry": {"coordinates":[-97.52408699999999,32.869295],"type":"Point"}
}