{
  "type": "Feature",
  "properties": {
    "iso:country":"US",
    "sg:address":"ARKeX Inc 11490 Westheimer, Suite 850",
    "sg:city":"Houston ",
    "sg:classifiers":[
        {
            "category":"Professional",
            "subcategory":"Computer Services",
            "type":"Services"
        }
    ],
    "sg:phone":"+44 1223 427400",
    "sg:postcode":"TX 77077",
    "sg:province":"TX",
    "sg:website":"http://www.arkex.com",
    "wof:name":"ARKeX",
    "wof:placetype":"venue"
},
  "geometry": {"coordinates":[-95.58467400000001,29.736458],"type":"Point"}
}