{
  "type": "Feature",
  "properties": {
    "iso:country":"US",
    "sg:address":"804 E Jackson Ave",
    "sg:city":"Temple",
    "sg:classifiers":[
        {
            "category":"Professional",
            "subcategory":"Business Services",
            "type":"Services"
        }
    ],
    "sg:phone":"+1 254 808 1360",
    "sg:postcode":"76501",
    "sg:province":"TX",
    "wof:name":"R&H Enterprises",
    "wof:placetype":"venue"
},
  "geometry": {"coordinates":[-97.32929799999999,31.102876],"type":"Point"}
}