{
  "type": "Feature",
  "properties": {
    "iso:country":"US",
    "sg:address":"10768 Co Rd 2335",
    "sg:city":"Tyler",
    "sg:classifiers":[
        {
            "category":"Manufacturing",
            "subcategory":"Tools & Machinery",
            "type":"Manufacturing & Wholesale Goods"
        }
    ],
    "sg:phone":"+1 903 566 3342",
    "sg:postcode":"75707",
    "sg:province":"TX",
    "sg:tags":[
        "mfg",
        "industrial",
        "general"
    ],
    "wof:name":"Arrick Robotics",
    "wof:placetype":"venue"
},
  "geometry": {"coordinates":[-95.22859800000001,32.324232],"type":"Point"}
}