{
  "type": "Feature",
  "properties": {
    "iso:country":"US",
    "sg:address":"1023 N 23rd St",
    "sg:city":"Mcallen",
    "sg:classifiers":[
        {
            "category":"Retail",
            "subcategory":"Funeral Services",
            "type":"Services"
        }
    ],
    "sg:phone":"+1 956 682 3431",
    "sg:postcode":"78501",
    "sg:province":"TX",
    "sg:tags":[
        "home",
        "crematory"
    ],
    "wof:name":"Ceballos Funeral Home",
    "wof:placetype":"venue"
},
  "geometry": {"coordinates":[-98.24375999999999,26.215033],"type":"Point"}
}