{
  "type": "Feature",
  "properties": {
    "iso:country":"US",
    "sg:address":"6 Evans Ave",
    "sg:city":"Midland",
    "sg:classifiers":[
        {
            "category":"Professional",
            "subcategory":"Business Services",
            "type":"Services"
        }
    ],
    "sg:phone":"+1 432 686 8949",
    "sg:postcode":"79701",
    "sg:province":"TX",
    "wof:name":"Josef Rusnak Warehouse",
    "wof:placetype":"venue"
},
  "geometry": {"coordinates":[-102.10314,31.975362],"type":"Point"}
}