{
  "type": "Feature",
  "properties": {
    "iso:country":"US",
    "sg:address":"437 N Sunset Blvd",
    "sg:city":"Angleton",
    "sg:classifiers":[
        {
            "category":"Building & Trades",
            "subcategory":"Landscaping Services",
            "type":"Services"
        }
    ],
    "sg:phone":"+1 979 848 8434",
    "sg:postcode":"77515",
    "sg:province":"TX",
    "sg:tags":[
        "lawn",
        "maintenance",
        "grounds"
    ],
    "wof:name":"First Choice Lawn Care",
    "wof:placetype":"venue"
},
  "geometry": {"coordinates":[-95.520509,29.209919],"type":"Point"}
}