{
  "type": "Feature",
  "properties": {
    "iso:country":"US",
    "sg:address":"101 Westcott St",
    "sg:city":"Houston",
    "sg:classifiers":[
        {
            "category":"Organizations",
            "subcategory":"Membership Organization",
            "type":"Services"
        }
    ],
    "sg:phone":"+1 713 862 6888",
    "sg:postcode":"77007",
    "sg:province":"TX",
    "wof:name":"Cluthe & William B Oliver Foun",
    "wof:placetype":"venue"
},
  "geometry": {"coordinates":[-95.421583,29.762835],"type":"Point"}
}