{
  "type": "Feature",
  "properties": {
    "iso:country":"US",
    "sg:address":"3774 N Central Expy",
    "sg:city":"Mckinney",
    "sg:classifiers":[
        {
            "category":"Wholesale",
            "subcategory":"Hardware",
            "type":"Manufacturing & Wholesale Goods"
        },
        {
            "category":"Home & Garden",
            "subcategory":"Garden Supply",
            "type":"Retail Goods"
        },
        {
            "category":"Retail",
            "subcategory":"Repair Shop",
            "type":"Services"
        }
    ],
    "sg:phone":"+1 972 548 9590",
    "sg:postcode":"75071",
    "sg:province":"TX",
    "sg:tags":[
        "renting",
        "lawn",
        "outdoor",
        "power",
        "landscaping",
        "equipment-sales",
        "equipment",
        "saw"
    ],
    "sg:website":"http://www.stihldealer.net/default-dealer-020011.aspx",
    "wof:name":"Landmark Equipment Company",
    "wof:placetype":"venue"
},
  "geometry": {"coordinates":[-96.630188,33.238239],"type":"Point"}
}