{
  "type": "Feature",
  "properties": {
    "iso:country":"US",
    "sg:address":"11248 Veterans Memorial Dr",
    "sg:city":"Houston",
    "sg:classifiers":[
        {
            "category":"Restaurant",
            "type":"Food & Drink"
        }
    ],
    "sg:phone":"+1 281 847 2300",
    "sg:postcode":"77067",
    "sg:province":"TX",
    "sg:tags":[
        "eating"
    ],
    "wof:name":"Saigon Oriental Restaurant",
    "wof:placetype":"venue"
},
  "geometry": {"coordinates":[-95.465959,29.94533],"type":"Point"}
}