{
  "type": "Feature",
  "properties": {
    "iso:country":"US",
    "sg:address":"1928 Main St",
    "sg:city":"Junction",
    "sg:classifiers":[
        {
            "category":"Autos & Motor Vehicles",
            "subcategory":"Fuel & Gas Station",
            "type":"Retail Goods"
        }
    ],
    "sg:phone":"+1 325 446 2539",
    "sg:postcode":"76849",
    "sg:province":"TX",
    "sg:tags":[
        "station",
        "gasoline",
        "dealer",
        "oil"
    ],
    "wof:name":"Kimble Oil Co",
    "wof:placetype":"venue"
},
  "geometry": {"coordinates":[-99.77826399999999,30.495901],"type":"Point"}
}