{
  "type": "Feature",
  "properties": {
    "iso:country":"US",
    "sg:address":"301 Garitty St",
    "sg:city":"Frost",
    "sg:classifiers":[
        {
            "category":"Government",
            "subcategory":"Post Office",
            "type":"Public Place"
        }
    ],
    "sg:phone":"+1 903 682 3661",
    "sg:postcode":"76641",
    "sg:province":"TX",
    "wof:name":"US Post Office",
    "wof:placetype":"venue"
},
  "geometry": {"coordinates":[-96.807895,32.082085],"type":"Point"}
}