{
  "type": "Feature",
  "properties": {
    "iso:country":"US",
    "sg:address":"409 Starlight Ln",
    "sg:city":"Royse City",
    "sg:classifiers":[
        {
            "category":"Building & Trades",
            "subcategory":"Pest Control",
            "type":"Services"
        }
    ],
    "sg:phone":"+1 972 636 7878",
    "sg:postcode":"75189",
    "sg:province":"TX",
    "wof:name":"Bug Stompers",
    "wof:placetype":"venue"
},
  "geometry": {"coordinates":[-96.33185400000001,32.95104],"type":"Point"}
}