{
  "type": "Feature",
  "properties": {
    "iso:country":"US",
    "sg:address":"837 Junction Hwy",
    "sg:city":"Kerrville",
    "sg:classifiers":[
        {
            "category":"Sports & Exercise",
            "subcategory":"Gym",
            "type":"Entertainment"
        }
    ],
    "sg:phone":"+1 830 896 9292",
    "sg:postcode":"78028",
    "sg:province":"TX",
    "sg:tags":[
        "facility",
        "club",
        "gymnasium",
        "health",
        "fitness",
        "studio",
        "physical"
    ],
    "wof:name":"Curves For Women",
    "wof:placetype":"venue"
},
  "geometry": {"coordinates":[-99.16158,30.057461],"type":"Point"}
}