{
  "type": "Feature",
  "properties": {
    "iso:country":"US",
    "sg:address":"14803 FM 2920",
    "sg:city":"Tomball",
    "sg:classifiers":[
        {
            "category":"Wholesale",
            "subcategory":"Auto Parts",
            "type":"Manufacturing & Wholesale Goods"
        }
    ],
    "sg:phone":"+1 281 351 0355",
    "sg:postcode":"77377",
    "sg:province":"TX",
    "sg:tags":[
        "automobile",
        "rebuilt"
    ],
    "wof:name":"Johnson Motors & Salvage Co",
    "wof:placetype":"venue"
},
  "geometry": {"coordinates":[-95.645219,30.089316],"type":"Point"}
}