{
  "type": "Feature",
  "properties": {
    "iso:country":"US",
    "sg:address":"5920 Lago Vista Way",
    "sg:city":"Leander",
    "sg:classifiers":[
        {
            "category":"Professional",
            "subcategory":"Management & Consulting",
            "type":"Services"
        }
    ],
    "sg:phone":"+1 512 267 1312",
    "sg:postcode":"78645",
    "sg:province":"TX",
    "wof:name":"Specialty One Marketing",
    "wof:placetype":"venue"
},
  "geometry": {"coordinates":[-97.993028,30.454465],"type":"Point"}
}