{
  "type": "Feature",
  "properties": {
    "iso:country":"US",
    "sg:address":"7897 Seymour Hwy",
    "sg:city":"Wichita Falls",
    "sg:classifiers":[
        {
            "category":"Building & Trades",
            "subcategory":"Equipment Rental",
            "type":"Services"
        }
    ],
    "sg:phone":"+1 940 692 7851",
    "sg:postcode":"76310",
    "sg:province":"TX",
    "sg:tags":[
        "heavy",
        "construction"
    ],
    "wof:name":"G & L Tool Company",
    "wof:placetype":"venue"
},
  "geometry": {"coordinates":[-98.631231,33.860252],"type":"Point"}
}