{
  "type": "Feature",
  "properties": {
    "iso:country":"US",
    "sg:address":"411 N 4th St",
    "sg:city":"Stratford",
    "sg:classifiers":[
        {
            "category":"Insurance",
            "subcategory":"Insurance Agent",
            "type":"Services"
        }
    ],
    "sg:phone":"+1 806 396 2456",
    "sg:postcode":"79084",
    "sg:province":"TX",
    "wof:name":"Vincent Insurance",
    "wof:placetype":"venue"
},
  "geometry": {"coordinates":[-102.073313,36.337138],"type":"Point"}
}