{
  "type": "Feature",
  "properties": {
    "iso:country":"US",
    "sg:address":"2701 Fannin St",
    "sg:city":"Houston",
    "sg:classifiers":[
        {
            "category":"Education",
            "subcategory":"Vocational School",
            "type":"Public Place"
        }
    ],
    "sg:phone":"+1 713 654 7777",
    "sg:postcode":"77002",
    "sg:province":"TX",
    "sg:tags":[
        "training",
        "computer"
    ],
    "wof:name":"Computer School Training",
    "wof:placetype":"venue"
},
  "geometry": {"coordinates":[-95.37420899999999,29.743582],"type":"Point"}
}