{
  "type": "Feature",
  "properties": {
    "iso:country":"US",
    "sg:address":"1800 E US Hwy 80",
    "sg:city":"White Oak",
    "sg:classifiers":[
        {
            "category":"Retail",
            "subcategory":"Auto Repair",
            "type":"Services"
        }
    ],
    "sg:phone":"+1 903 295 0385",
    "sg:postcode":"75693",
    "sg:province":"TX",
    "sg:tags":[
        "body",
        "automobile",
        "painting"
    ],
    "wof:name":"Gavy's Body Shop",
    "wof:placetype":"venue"
},
  "geometry": {"coordinates":[-94.836376,32.5133],"type":"Point"}
}