{
  "type": "Feature",
  "properties": {
    "iso:country":"US",
    "sg:address":"4212 Rosehill Rd",
    "sg:city":"Garland",
    "sg:classifiers":[
        {
            "category":"Education",
            "subcategory":"Special Training",
            "type":"Public Place"
        }
    ],
    "sg:phone":"+1 972 303 0101",
    "sg:postcode":"75043",
    "sg:province":"TX",
    "sg:tags":[
        "school",
        "instruction",
        "driving"
    ],
    "sg:website":"www.allamericandrivingschool.com",
    "wof:name":"All American Driving School",
    "wof:placetype":"venue"
},
  "geometry": {"coordinates":[-96.602441,32.862627],"type":"Point"}
}