{
  "type": "Feature",
  "properties": {
    "iso:country":"US",
    "sg:address":"13335 Western Oak Dr",
    "sg:city":"Helotes",
    "sg:classifiers":[
        {
            "category":"Wholesale",
            "subcategory":"Metals & Minerals",
            "type":"Manufacturing & Wholesale Goods"
        }
    ],
    "sg:phone":"+1 210 695 8716",
    "sg:postcode":"78023",
    "sg:province":"TX",
    "sg:tags":[
        "pipe"
    ],
    "sg:website":"www.hughessupply.com",
    "wof:name":"Hughes Supply Inc",
    "wof:placetype":"venue"
},
  "geometry": {"coordinates":[-98.661851,29.564554],"type":"Point"}
}