{
  "type": "Feature",
  "properties": {
    "iso:country":"US",
    "sg:address":"443 State Hwy 71 W",
    "sg:city":"Bastrop",
    "sg:classifiers":[
        {
            "category":"Social Services",
            "type":"Services"
        }
    ],
    "sg:phone":"+1 512 321 6144",
    "sg:postcode":"78602",
    "sg:province":"TX",
    "wof:name":"Wic",
    "wof:placetype":"venue"
},
  "geometry": {"coordinates":[-97.348282,30.111336],"type":"Point"}
}