{
  "type": "Feature",
  "properties": {
    "iso:country":"US",
    "sg:address":"838 Mesquite Rd",
    "sg:city":"Belton",
    "sg:classifiers":[
        {
            "category":"Professional",
            "subcategory":"Business Services",
            "type":"Services"
        }
    ],
    "sg:phone":"+1 254 939 6667",
    "sg:postcode":"76513",
    "sg:province":"TX",
    "wof:name":"N Wood Brush",
    "wof:placetype":"venue"
},
  "geometry": {"coordinates":[-97.48307,31.020425],"type":"Point"}
}