{
  "type": "Feature",
  "properties": {
    "iso:country":"US",
    "sg:address":"3537 Co Rd 312",
    "sg:city":"Cleburne",
    "sg:classifiers":[
        {
            "category":"Professional",
            "type":"Services"
        }
    ],
    "sg:phone":"+1 817 558 7122",
    "sg:postcode":"76031",
    "sg:province":"TX",
    "wof:name":"Sculpting By Dana",
    "wof:placetype":"venue"
},
  "geometry": {"coordinates":[-97.324575,32.326341],"type":"Point"}
}