{
  "type": "Feature",
  "properties": {
    "iso:country":"US",
    "sg:address":"4124 Hockaday Dr",
    "sg:city":"Dallas",
    "sg:classifiers":[
        {
            "category":"Shopping",
            "subcategory":"Used Merchandise",
            "type":"Retail Goods"
        }
    ],
    "sg:phone":"+1 214 352 1291",
    "sg:postcode":"75229",
    "sg:province":"TX",
    "wof:name":"Julies Cottage Antiques",
    "wof:placetype":"venue"
},
  "geometry": {"coordinates":[-96.84127700000001,32.906804],"type":"Point"}
}