{
  "type": "Feature",
  "properties": {
    "iso:country":"US",
    "sg:address":"8210 Mosley Rd",
    "sg:city":"Houston",
    "sg:classifiers":[
        {
            "category":"Professional",
            "subcategory":"Testing Lab",
            "type":"Services"
        }
    ],
    "sg:phone":"+1 713 943 9776",
    "sg:postcode":"77075",
    "sg:province":"TX",
    "sg:tags":[
        "laboratory"
    ],
    "sg:website":"www.corelab.com",
    "wof:name":"Core Laboratories Inc",
    "wof:placetype":"venue"
},
  "geometry": {"coordinates":[-95.25379,29.650482],"type":"Point"}
}