{
  "type": "Feature",
  "properties": {
    "iso:country":"US",
    "sg:address":"102 I- 20 E",
    "sg:city":"Arlington",
    "sg:classifiers":[
        {
            "category":"Shopping",
            "subcategory":"Computers & Home Electronics",
            "type":"Retail Goods"
        }
    ],
    "sg:phone":"+1 817 557 6500",
    "sg:postcode":"76018",
    "sg:province":"TX",
    "sg:tags":[
        "c",
        "supply",
        "household",
        "appliance",
        "equipment",
        "electronic"
    ],
    "sg:website":"www.outpost.com",
    "wof:name":"Fry's Electronics",
    "wof:placetype":"venue"
},
  "geometry": {"coordinates":[-97.11441499999999,32.677579],"type":"Point"}
}