{
  "type": "Feature",
  "properties": {
    "iso:country":"US",
    "sg:address":"6202 Skyline Dr #14",
    "sg:city":"Houston",
    "sg:classifiers":[
        {
            "category":"Education",
            "subcategory":"Music School",
            "type":"Public Place"
        }
    ],
    "sg:phone":"+1 800 332 7460",
    "sg:postcode":"77057",
    "sg:province":"TX",
    "sg:tags":[
        "instrument",
        "teacher",
        "musical"
    ],
    "wof:name":"Cymbalism Music",
    "wof:placetype":"venue"
},
  "geometry": {"coordinates":[-95.490008,29.729045],"type":"Point"}
}