{
  "type": "Feature",
  "properties": {
    "iso:country":"US",
    "sg:address":"7408 Maybrook Ct",
    "sg:city":"Plano",
    "sg:classifiers":[
        {
            "category":"Wholesale",
            "subcategory":"Non-durable Goods",
            "type":"Manufacturing & Wholesale Goods"
        }
    ],
    "sg:phone":"+1 972 491 1992",
    "sg:postcode":"75024",
    "sg:province":"TX",
    "wof:name":"Gail W Stevens",
    "wof:placetype":"venue"
},
  "geometry": {"coordinates":[-96.778513,33.079483],"type":"Point"}
}