{
  "type": "Feature",
  "properties": {
    "iso:country":"US",
    "sg:address":"7975 Bellfort St",
    "sg:city":"Houston",
    "sg:classifiers":[
        {
            "category":"Professional",
            "subcategory":"Engineering",
            "type":"Services"
        }
    ],
    "sg:phone":"+1 713 641 3333",
    "sg:postcode":"77061",
    "sg:province":"TX",
    "sg:tags":[
        "engineer",
        "contractor"
    ],
    "wof:name":"Pablo's Mechanic",
    "wof:placetype":"venue"
},
  "geometry": {"coordinates":[-95.26992799999999,29.674192],"type":"Point"}
}