{
  "type": "Feature",
  "properties": {
    "iso:country":"US",
    "sg:address":"1501 E Mockingbird Ln",
    "sg:city":"Victoria",
    "sg:classifiers":[
        {
            "category":"Health Services",
            "subcategory":"Doctor",
            "type":"Services"
        }
    ],
    "sg:phone":"+1 361 570 2900",
    "sg:postcode":"77904",
    "sg:province":"TX",
    "sg:tags":[
        "medical"
    ],
    "wof:name":"Gregory B Creager MD",
    "wof:placetype":"venue"
},
  "geometry": {"coordinates":[-96.99129499999999,28.835884],"type":"Point"}
}