{
  "type": "Feature",
  "properties": {
    "iso:country":"US",
    "sg:address":"4822 Palmetto St",
    "sg:city":"Bellaire",
    "sg:classifiers":[
        {
            "category":"Manufacturing",
            "subcategory":"Petroleum Products",
            "type":"Manufacturing & Wholesale Goods"
        },
        {
            "category":"Wholesale",
            "subcategory":"Petroleum",
            "type":"Manufacturing & Wholesale Goods"
        }
    ],
    "sg:phone":"+1 713 666 3281",
    "sg:postcode":"77401",
    "sg:province":"TX",
    "sg:tags":[
        "manufacturer",
        "products-wholesale",
        "oils-petroleum"
    ],
    "wof:name":"Kubelka Petroleum Enginee",
    "wof:placetype":"venue"
},
  "geometry": {"coordinates":[-95.4628,29.711666],"type":"Point"}
}