{
  "type": "Feature",
  "properties": {
    "iso:country":"US",
    "sg:address":"1506 Chapman Dr",
    "sg:city":"Lancaster",
    "sg:classifiers":[
        {
            "category":"Wholesale",
            "subcategory":"Non-durable Goods",
            "type":"Manufacturing & Wholesale Goods"
        }
    ],
    "sg:phone":"+1 972 218 8033",
    "sg:postcode":"75134",
    "sg:province":"TX",
    "wof:name":"Sand Tees Bodyworks & Baskets",
    "wof:placetype":"venue"
},
  "geometry": {"coordinates":[-96.796903,32.610351],"type":"Point"}
}