{
  "type": "Feature",
  "properties": {
    "iso:country":"US",
    "sg:address":"8181 Douglas Ave",
    "sg:city":"Dallas",
    "sg:classifiers":[
        {
            "category":"Professional",
            "subcategory":"Business Services",
            "type":"Services"
        }
    ],
    "sg:phone":"+1 214 987 4588",
    "sg:postcode":"75225",
    "sg:province":"TX",
    "wof:name":"Mabrey & Partners Develop",
    "wof:placetype":"venue"
},
  "geometry": {"coordinates":[-96.808657,32.861513],"type":"Point"}
}