{
  "type": "Feature",
  "properties": {
    "iso:country":"US",
    "sg:address":"1600 Watauga Rd",
    "sg:city":"Blue Mound",
    "sg:classifiers":[
        {
            "category":"Food & Beverages",
            "subcategory":"Groceries & Convenience Stores",
            "type":"Retail Goods"
        }
    ],
    "sg:phone":"+1 817 232 1700",
    "sg:postcode":"76131",
    "sg:province":"TX",
    "sg:tags":[
        "grocer"
    ],
    "wof:name":"Harold's & Foods",
    "wof:placetype":"venue"
},
  "geometry": {"coordinates":[-97.33917099999999,32.861412],"type":"Point"}
}