{
  "type": "Feature",
  "properties": {
    "iso:country":"US",
    "sg:address":"1527 Big Horn Dr",
    "sg:city":"Houston",
    "sg:classifiers":[
        {
            "category":"Professional",
            "type":"Services"
        }
    ],
    "sg:phone":"+1 281 866 8807",
    "sg:postcode":"77090",
    "sg:province":"TX",
    "wof:name":"Roger Glynn",
    "wof:placetype":"venue"
},
  "geometry": {"coordinates":[-95.45948,30.023276],"type":"Point"}
}