{
  "type": "Feature",
  "properties": {
    "iso:country":"US",
    "sg:address":"2202 Club Creek Cir",
    "sg:city":"Garland",
    "sg:classifiers":[
        {
            "category":"Retail",
            "subcategory":"Repair Shop",
            "type":"Services"
        }
    ],
    "sg:phone":"+1 972 240 0011",
    "sg:postcode":"75043",
    "sg:province":"TX",
    "wof:name":"Onsite PC Repair",
    "wof:placetype":"venue"
},
  "geometry": {"coordinates":[-96.596912,32.873047],"type":"Point"}
}