{
  "type": "Feature",
  "properties": {
    "iso:country":"US",
    "sg:address":"4409 Echo Bluff Dr",
    "sg:city":"Plano",
    "sg:classifiers":[
        {
            "category":"Professional",
            "subcategory":"Art Services",
            "type":"Services"
        }
    ],
    "sg:phone":"+1 972 943 3102",
    "sg:postcode":"75024",
    "sg:province":"TX",
    "sg:tags":[
        "graphic",
        "design"
    ],
    "wof:name":"Infinite Designs",
    "wof:placetype":"venue"
},
  "geometry": {"coordinates":[-96.77887200000001,33.059562],"type":"Point"}
}