{
  "type": "Feature",
  "properties": {
    "iso:country":"US",
    "sg:address":"5704 Westheimer Rd",
    "sg:city":"Houston",
    "sg:classifiers":[
        {
            "category":"Retail",
            "subcategory":"Auto Repair",
            "type":"Services"
        }
    ],
    "sg:phone":"+1 713 781 6644",
    "sg:postcode":"77057",
    "sg:province":"TX",
    "wof:name":"Sal's Westheimer Auto Service",
    "wof:placetype":"venue"
},
  "geometry": {"coordinates":[-95.477203,29.7381],"type":"Point"}
}