{
  "type": "Feature",
  "properties": {
    "iso:country":"US",
    "sg:address":"810 Jackson St",
    "sg:city":"Richmond",
    "sg:classifiers":[
        {
            "category":"Professional",
            "subcategory":"Management & Consulting",
            "type":"Services"
        }
    ],
    "sg:phone":"+1 281 344 9556",
    "sg:postcode":"77469",
    "sg:province":"TX",
    "sg:tags":[
        "consultant",
        "business"
    ],
    "wof:name":"Industry Consulting Group",
    "wof:placetype":"venue"
},
  "geometry": {"coordinates":[-95.764748,29.580906],"type":"Point"}
}