{
  "type": "Feature",
  "properties": {
    "iso:country":"US",
    "sg:address":"2017 W Hebron Pkwy",
    "sg:city":"Carrollton",
    "sg:classifiers":[
        {
            "category":"Food & Beverages",
            "subcategory":"Groceries & Convenience Stores",
            "type":"Retail Goods"
        }
    ],
    "sg:phone":"+1 972 939 2522",
    "sg:postcode":"75010",
    "sg:province":"TX",
    "wof:name":"Chevron Foodmart",
    "wof:placetype":"venue"
},
  "geometry": {"coordinates":[-96.945503,33.015099],"type":"Point"}
}