{
  "type": "Feature",
  "properties": {
    "iso:country":"US",
    "sg:address":"1717 Morning Glory",
    "sg:city":"Carrollton",
    "sg:classifiers":[
        {
            "category":"Building & Trades",
            "subcategory":"Construction",
            "type":"Services"
        }
    ],
    "sg:phone":"+1 972 418 0949",
    "sg:postcode":"75007",
    "sg:province":"TX",
    "wof:name":"Sasoon Sewing Co",
    "wof:placetype":"venue"
},
  "geometry": {"coordinates":[-96.894779,33.018819],"type":"Point"}
}