{
  "type": "Feature",
  "properties": {
    "iso:country":"US",
    "sg:address":"9640 Wilcrest Dr",
    "sg:city":"Houston",
    "sg:classifiers":[
        {
            "category":"Government",
            "subcategory":"Fire Station",
            "type":"Public Place"
        }
    ],
    "sg:phone":"+1 713 222 7643",
    "sg:postcode":"77099",
    "sg:province":"TX",
    "sg:tags":[
        "protection"
    ],
    "wof:name":"Fire Dept-Station 73",
    "wof:placetype":"venue"
},
  "geometry": {"coordinates":[-95.57043400000001,29.672641],"type":"Point"}
}