{
  "type": "Feature",
  "properties": {
    "iso:country":"US",
    "sg:address":"319 W 1st St",
    "sg:city":"Weatherford",
    "sg:classifiers":[
        {
            "category":"Personal",
            "subcategory":"Beauty Salon",
            "type":"Services"
        }
    ],
    "sg:phone":"+1 817 594 3541",
    "sg:postcode":"76086",
    "sg:province":"TX",
    "wof:name":"Floy B Beauty Shop",
    "wof:placetype":"venue"
},
  "geometry": {"coordinates":[-97.801773,32.76971],"type":"Point"}
}