{
  "type": "Feature",
  "properties": {
    "iso:country":"US",
    "sg:address":"771 Eiffel Dr",
    "sg:city":"Plano",
    "sg:classifiers":[
        {
            "category":"Shopping",
            "subcategory":"Gifts & Souvenirs",
            "type":"Retail Goods"
        }
    ],
    "sg:phone":"+1 972 509 5425",
    "sg:postcode":"75023",
    "sg:province":"TX",
    "wof:name":"Yong & Si Gift Shop",
    "wof:placetype":"venue"
},
  "geometry": {"coordinates":[-96.707815,33.044839],"type":"Point"}
}