{
  "type": "Feature",
  "properties": {
    "iso:country":"US",
    "sg:address":"124 W Pioneer Pkwy # 120",
    "sg:city":"Arlington",
    "sg:classifiers":[
        {
            "category":"Health Services",
            "subcategory":"Health Practitioner",
            "type":"Services"
        }
    ],
    "sg:phone":"+1 817 795 8278",
    "sg:postcode":"76010",
    "sg:province":"TX",
    "sg:tags":[
        "addiction",
        "abuse",
        "drug"
    ],
    "wof:name":"Ntac",
    "wof:placetype":"venue"
},
  "geometry": {"coordinates":[-97.107896,32.70804],"type":"Point"}
}