{
  "type": "Feature",
  "properties": {
    "iso:country":"US",
    "sg:address":"200 S Crockett St",
    "sg:city":"Sherman",
    "sg:classifiers":[
        {
            "category":"Government",
            "subcategory":"Office",
            "type":"Public Place"
        }
    ],
    "sg:phone":"+1 903 813 4336",
    "sg:postcode":"75090",
    "sg:province":"TX",
    "sg:tags":[
        "county"
    ],
    "wof:name":"County Clerk",
    "wof:placetype":"venue"
},
  "geometry": {"coordinates":[-96.609877,33.634367],"type":"Point"}
}