{
  "type": "Feature",
  "properties": {
    "iso:country":"US",
    "sg:address":"11211 Old Mint House Ln",
    "sg:city":"Tomball",
    "sg:classifiers":[
        {
            "category":"Professional",
            "subcategory":"Research",
            "type":"Services"
        }
    ],
    "sg:phone":"+1 281 255 0149",
    "sg:postcode":"77375",
    "sg:province":"TX",
    "sg:tags":[
        "laboratory"
    ],
    "wof:name":"Howell Laboratories Inc",
    "wof:placetype":"venue"
},
  "geometry": {"coordinates":[-95.586303,30.0671],"type":"Point"}
}