{
  "type": "Feature",
  "properties": {
    "iso:country":"US",
    "sg:address":"146 E Houston St",
    "sg:city":"San Antonio",
    "sg:classifiers":[
        {
            "category":"Restaurant",
            "type":"Food & Drink"
        }
    ],
    "sg:menulink":"http://www.allmenus.com/tx/san-antonio/268560-acenar/menu/",
    "sg:phone":"+1 210 222 2362",
    "sg:postcode":"78205",
    "sg:province":"TX",
    "sg:tags":[
        "mexican"
    ],
    "wof:name":"Acenar",
    "wof:placetype":"venue"
},
  "geometry": {"coordinates":[-98.49233599999999,29.426482],"type":"Point"}
}