{
  "type": "Feature",
  "properties": {
    "iso:country":"US",
    "sg:address":"316 Spring St",
    "sg:city":"Columbus",
    "sg:classifiers":[
        {
            "category":"Government",
            "subcategory":"Police Station",
            "type":"Public Place"
        }
    ],
    "sg:phone":"+1 979 732 3651",
    "sg:postcode":"78934",
    "sg:province":"TX",
    "sg:tags":[
        "state"
    ],
    "wof:name":"Highway Patrol-Lic-Wgt",
    "wof:placetype":"venue"
},
  "geometry": {"coordinates":[-96.53815899999999,29.705516],"type":"Point"}
}