{
  "type": "Feature",
  "properties": {
    "iso:country":"US",
    "sg:address":"1001 5th St",
    "sg:city":"Palacios",
    "sg:classifiers":[
        {
            "category":"Education",
            "subcategory":"School",
            "type":"Public Place"
        }
    ],
    "sg:phone":"+1 361 972 2915",
    "sg:postcode":"77465",
    "sg:province":"TX",
    "wof:name":"Palacios Head Start",
    "wof:placetype":"venue"
},
  "geometry": {"coordinates":[-96.216672,28.710242],"type":"Point"}
}