{
  "type": "Feature",
  "properties": {
    "iso:country":"US",
    "sg:address":"1301 W Parker Rd",
    "sg:city":"Plano",
    "sg:classifiers":[
        {
            "category":"Home & Garden",
            "subcategory":"Home Furnishings",
            "type":"Retail Goods"
        }
    ],
    "sg:phone":"+1 972 422 0003",
    "sg:postcode":"75023",
    "sg:province":"TX",
    "sg:tags":[
        "curtain",
        "made",
        "drapery"
    ],
    "wof:name":"Southwest Interiors Design Inc",
    "wof:placetype":"venue"
},
  "geometry": {"coordinates":[-96.718119,33.041165],"type":"Point"}
}