{
  "type": "Feature",
  "properties": {
    "iso:country":"US",
    "sg:address":"16300 State Hwy 123",
    "sg:city":"San Marcos",
    "sg:classifiers":[
        {
            "category":"Bars & Pubs",
            "type":"Food & Drink"
        }
    ],
    "sg:phone":"+1 512 353 5129",
    "sg:postcode":"78666",
    "sg:province":"TX",
    "sg:tags":[
        "club",
        "night"
    ],
    "wof:name":"Tejano Country Ballroom",
    "wof:placetype":"venue"
},
  "geometry": {"coordinates":[-97.94465,29.805815],"type":"Point"}
}