{
  "type": "Feature",
  "properties": {
    "iso:country":"US",
    "sg:address":"711 Sabel Ridge",
    "sg:city":"Grapevine",
    "sg:classifiers":[
        {
            "category":"Wholesale",
            "subcategory":"Vending Machines",
            "type":"Manufacturing & Wholesale Goods"
        }
    ],
    "sg:phone":"+1 817 481 3078",
    "sg:postcode":"76051",
    "sg:province":"TX",
    "sg:tags":[
        "operator"
    ],
    "wof:name":"Victory Vending Inc",
    "wof:placetype":"venue"
},
  "geometry": {"coordinates":[-97.089055,32.89262],"type":"Point"}
}