{
  "type": "Feature",
  "properties": {
    "iso:country":"US",
    "sg:address":"11383 Ferrill Creek Rd",
    "sg:city":"Bryan",
    "sg:classifiers":[
        {
            "category":"Wholesale",
            "subcategory":"Farm Supplies",
            "type":"Manufacturing & Wholesale Goods"
        }
    ],
    "sg:phone":"+1 979 589 2614",
    "sg:postcode":"77808",
    "sg:province":"TX",
    "wof:name":"Glen Pate",
    "wof:placetype":"venue"
},
  "geometry": {"coordinates":[-96.30043499999999,30.83163],"type":"Point"}
}