{
  "type": "Feature",
  "properties": {
    "iso:country":"US",
    "sg:address":"251 N Harbin Dr",
    "sg:city":"Stephenville",
    "sg:classifiers":[
        {
            "category":"Personal",
            "type":"Services"
        }
    ],
    "sg:phone":"+1 254 968 0311",
    "sg:postcode":"76401",
    "sg:province":"TX",
    "sg:tags":[
        "therapist",
        "massage"
    ],
    "wof:name":"Healing Hands Therapy Ctr",
    "wof:placetype":"venue"
},
  "geometry": {"coordinates":[-98.223355,32.212129],"type":"Point"}
}