{
  "type": "Feature",
  "properties": {
    "iso:country":"US",
    "sg:address":"610 Thistlewood Dr",
    "sg:city":"Houston",
    "sg:classifiers":[
        {
            "category":"Professional",
            "subcategory":"Management & Consulting",
            "type":"Services"
        }
    ],
    "sg:phone":"+1 281 558 4955",
    "sg:postcode":"77079",
    "sg:province":"TX",
    "sg:tags":[
        "business"
    ],
    "wof:name":"Terremark Consulting & Mktg",
    "wof:placetype":"venue"
},
  "geometry": {"coordinates":[-95.62125399999999,29.774506],"type":"Point"}
}