{
  "type": "Feature",
  "properties": {
    "iso:country":"US",
    "sg:address":"800 E General Cavazos Blvd",
    "sg:city":"Kingsville",
    "sg:classifiers":[
        {
            "category":"Real Estate",
            "subcategory":"Real Estate Operator",
            "type":"Services"
        }
    ],
    "sg:phone":"+1 361 595 1271",
    "sg:postcode":"78363",
    "sg:province":"TX",
    "sg:tags":[
        "building",
        "apartment"
    ],
    "wof:name":"Casa Del Ray Apartement",
    "wof:placetype":"venue"
},
  "geometry": {"coordinates":[-97.858627,27.491419],"type":"Point"}
}