{
  "type": "Feature",
  "properties": {
    "iso:country":"US",
    "sg:address":"201 Flat Creek Rd",
    "sg:city":"Athens",
    "sg:classifiers":[
        {
            "category":"Real Estate",
            "subcategory":"Real Estate Operator",
            "type":"Services"
        }
    ],
    "sg:phone":"+1 903 675 5422",
    "sg:postcode":"75751",
    "sg:province":"TX",
    "sg:tags":[
        "building",
        "apartment"
    ],
    "wof:name":"Village Apartments",
    "wof:placetype":"venue"
},
  "geometry": {"coordinates":[-95.82996199999999,32.209172],"type":"Point"}
}