{
  "type": "Feature",
  "properties": {
    "iso:country":"US",
    "sg:address":"1722 W Southcross Blvd",
    "sg:city":"San Antonio",
    "sg:classifiers":[
        {
            "category":"Professional",
            "subcategory":"Accounting & Tax Preparation",
            "type":"Services"
        }
    ],
    "sg:phone":"+1 210 923 4462",
    "sg:postcode":"78211",
    "sg:province":"TX",
    "sg:tags":[
        "auditing",
        "bookkeeping"
    ],
    "wof:name":"Childress Tax Service",
    "wof:placetype":"venue"
},
  "geometry": {"coordinates":[-98.53601500000001,29.368027],"type":"Point"}
}