{
  "type": "Feature",
  "properties": {
    "iso:country":"US",
    "sg:address":"8612 Preston Rd",
    "sg:city":"Plano",
    "sg:classifiers":[
        {
            "category":"Banks & Credit Unions",
            "subcategory":"Bank",
            "type":"Services"
        }
    ],
    "sg:phone":"+1 214 630 3030",
    "sg:postcode":"75024",
    "sg:province":"TX",
    "wof:name":"Commercial Bank",
    "wof:placetype":"venue"
},
  "geometry": {"coordinates":[-96.80538199999999,33.096041],"type":"Point"}
}