{
  "type": "Feature",
  "properties": {
    "iso:country":"US",
    "sg:address":"803 Schweikhardt St",
    "sg:city":"Houston",
    "sg:classifiers":[
        {
            "category":"Restaurant",
            "type":"Food & Drink"
        }
    ],
    "sg:phone":"+1 713 673 9428",
    "sg:postcode":"77020",
    "sg:province":"TX",
    "sg:tags":[
        "barbecue"
    ],
    "wof:name":"Green Oak Barbecue",
    "wof:placetype":"venue"
},
  "geometry": {"coordinates":[-95.32335399999999,29.770088],"type":"Point"}
}