{
  "type": "Feature",
  "properties": {
    "iso:country":"US",
    "sg:address":"11326 FM 326 N",
    "sg:city":"Lufkin",
    "sg:classifiers":[
        {
            "category":"Farming",
            "subcategory":"Farm & Veterinary Services",
            "type":"Manufacturing & Wholesale Goods"
        }
    ],
    "sg:phone":"+1 936 824 2026",
    "sg:postcode":"75901",
    "sg:province":"TX",
    "sg:tags":[
        "ranch",
        "cattle"
    ],
    "wof:name":"Moore Cattle Co",
    "wof:placetype":"venue"
},
  "geometry": {"coordinates":[-94.627009,31.205553],"type":"Point"}
}