{
  "type": "Feature",
  "properties": {
    "iso:country":"US",
    "sg:address":"218 N Preston Ave",
    "sg:city":"Pasadena",
    "sg:classifiers":[
        {
            "category":"Building & Trades",
            "subcategory":"Construction",
            "type":"Services"
        }
    ],
    "sg:phone":"+1 713 477 4406",
    "sg:postcode":"77503",
    "sg:province":"TX",
    "sg:tags":[
        "painter"
    ],
    "wof:name":"Protherm Services Group Llc",
    "wof:placetype":"venue"
},
  "geometry": {"coordinates":[-95.1716,29.715599],"type":"Point"}
}