{
  "type": "Feature",
  "properties": {
    "iso:country":"US",
    "sg:address":"1309 Grape St",
    "sg:city":"Abilene",
    "sg:classifiers":[
        {
            "category":"Restaurant",
            "type":"Food & Drink"
        }
    ],
    "sg:phone":"+1 325 672 4672",
    "sg:postcode":"79601",
    "sg:province":"TX",
    "sg:tags":[
        "eating"
    ],
    "wof:name":"Church's Chicken",
    "wof:placetype":"venue"
},
  "geometry": {"coordinates":[-99.74008000000001,32.465183],"type":"Point"}
}