{
  "type": "Feature",
  "properties": {
    "iso:country":"US",
    "sg:address":"32 Chaparral Dr 9",
    "sg:city":"Kerrville",
    "sg:classifiers":[
        {
            "category":"Professional",
            "subcategory":"Computer Services",
            "type":"Services"
        }
    ],
    "sg:phone":"+1 830 688 7056",
    "sg:postcode":"78028",
    "sg:province":"TX",
    "sg:tags":[
        "systems-consultants",
        "designer",
        "data"
    ],
    "wof:name":"Sidrl",
    "wof:placetype":"venue"
},
  "geometry": {"coordinates":[-99.1409,30.036659],"type":"Point"}
}