{
  "type": "Feature",
  "properties": {
    "iso:country":"US",
    "sg:address":"3713 Cranston Ct E",
    "sg:city":"Irving",
    "sg:classifiers":[
        {
            "category":"Communications",
            "type":"Services"
        }
    ],
    "sg:phone":"+1 972 255 8120",
    "sg:postcode":"75062",
    "sg:province":"TX",
    "sg:tags":[
        "equipment",
        "data",
        "telephone",
        "systems-repair",
        "system"
    ],
    "wof:name":"Alphatronics Company",
    "wof:placetype":"venue"
},
  "geometry": {"coordinates":[-96.965896,32.854167],"type":"Point"}
}