{
  "type": "Feature",
  "properties": {
    "iso:country":"US",
    "sg:address":"1202 W Centerville Rd",
    "sg:city":"Garland",
    "sg:classifiers":[
        {
            "category":"Wholesale",
            "subcategory":"Construction Materials",
            "type":"Manufacturing & Wholesale Goods"
        }
    ],
    "sg:phone":"+1 972 681 5960",
    "sg:postcode":"75041",
    "sg:province":"TX",
    "sg:tags":[
        "floor",
        "covering"
    ],
    "wof:name":"Tile Warehouse",
    "wof:placetype":"venue"
},
  "geometry": {"coordinates":[-96.646153,32.858196],"type":"Point"}
}