{
  "type": "Feature",
  "properties": {
    "iso:country":"US",
    "sg:address":"2515 Broadway St",
    "sg:city":"Beaumont",
    "sg:classifiers":[
        {
            "category":"Personal",
            "type":"Services"
        }
    ],
    "sg:phone":"+1 409 832 7787",
    "sg:postcode":"77702",
    "sg:province":"TX",
    "wof:name":"D Stress Systems",
    "wof:placetype":"venue"
},
  "geometry": {"coordinates":[-94.126874,30.084595],"type":"Point"}
}