{
  "type": "Feature",
  "properties": {
    "iso:country":"US",
    "sg:address":"319 W Park Ave",
    "sg:city":"Orange",
    "sg:classifiers":[
        {
            "category":"Professional",
            "type":"Services"
        }
    ],
    "sg:phone":"+1 409 883 0106",
    "sg:postcode":"77630",
    "sg:province":"TX",
    "sg:tags":[
        "establishment"
    ],
    "wof:name":"Ware Plaza",
    "wof:placetype":"venue"
},
  "geometry": {"coordinates":[-93.732034,30.09911],"type":"Point"}
}