{
  "type": "Feature",
  "properties": {
    "iso:country":"US",
    "sg:address":"301 N Hwy 78",
    "sg:city":"Blue Ridge",
    "sg:classifiers":[
        {
            "category":"Government",
            "subcategory":"Post Office",
            "type":"Public Place"
        }
    ],
    "sg:phone":"+1 972 752 5326",
    "sg:postcode":"75424",
    "sg:province":"TX",
    "sg:tags":[
        "postal",
        "executive",
        "us"
    ],
    "wof:name":"US Post Office",
    "wof:placetype":"venue"
},
  "geometry": {"coordinates":[-96.39646399999999,33.303064],"type":"Point"}
}