{
  "type": "Feature",
  "properties": {
    "iso:country":"US",
    "sg:address":"5500 FM 1788 S",
    "sg:city":"Midland",
    "sg:classifiers":[
        {
            "category":"Wholesale",
            "subcategory":"Office Equipment",
            "type":"Manufacturing & Wholesale Goods"
        }
    ],
    "sg:phone":"+1 432 563 1418",
    "sg:postcode":"79706",
    "sg:province":"TX",
    "sg:tags":[
        "machine",
        "duplicating",
        "copying"
    ],
    "wof:name":"Copy Service & Supply Inc",
    "wof:placetype":"venue"
},
  "geometry": {"coordinates":[-102.205772,31.880032],"type":"Point"}
}