{
  "type": "Feature",
  "properties": {
    "iso:country":"US",
    "sg:address":"2101 E Ben White Blvd Ste 3",
    "sg:city":"Austin",
    "sg:classifiers":[
        {
            "category":"Professional",
            "subcategory":"Employment Agencies",
            "type":"Services"
        }
    ],
    "sg:phone":"+1 512 447 5627",
    "sg:postcode":"78741",
    "sg:province":"TX",
    "sg:tags":[
        "opportunity",
        "contractor"
    ],
    "wof:name":"Quality Staff",
    "wof:placetype":"venue"
},
  "geometry": {"coordinates":[-97.740891,30.215611],"type":"Point"}
}