{
  "type": "Feature",
  "properties": {
    "iso:country":"US",
    "sg:address":"2509 Nogales St",
    "sg:city":"Corpus Christi",
    "sg:classifiers":[
        {
            "category":"Organizations",
            "subcategory":"Religious Organization",
            "type":"Services"
        }
    ],
    "sg:phone":"+1 361 882 3245",
    "sg:postcode":"78416",
    "sg:province":"TX",
    "wof:name":"Holy Family Church",
    "wof:placetype":"venue"
},
  "geometry": {"coordinates":[-97.425901,27.766491],"type":"Point"}
}