{
  "type": "Feature",
  "properties": {
    "iso:country":"US",
    "sg:address":"211 W Belt Line Rd",
    "sg:city":"Cedar Hill",
    "sg:classifiers":[
        {
            "category":"Health Services",
            "subcategory":"Doctor",
            "type":"Services"
        }
    ],
    "sg:phone":"+1 972 291 4282",
    "sg:postcode":"75104",
    "sg:province":"TX",
    "sg:tags":[
        "surgeon",
        "oral"
    ],
    "wof:name":"Clark Brian G DDS",
    "wof:placetype":"venue"
},
  "geometry": {"coordinates":[-96.948196,32.589901],"type":"Point"}
}