{
  "type": "Feature",
  "properties": {
    "iso:country":"US",
    "sg:address":"5615 Richmond Ave",
    "sg:city":"Houston",
    "sg:classifiers":[
        {
            "category":"Building & Trades",
            "subcategory":"Construction",
            "type":"Services"
        }
    ],
    "sg:phone":"+1 713 781 1699",
    "sg:postcode":"77057",
    "sg:province":"TX",
    "sg:tags":[
        "site",
        "clean"
    ],
    "wof:name":"C Ya Asset Management",
    "wof:placetype":"venue"
},
  "geometry": {"coordinates":[-95.47712799999999,29.73151],"type":"Point"}
}