{
  "type": "Feature",
  "properties": {
    "iso:country":"US",
    "sg:address":"422 N Main St",
    "sg:city":"Borger",
    "sg:classifiers":[
        {
            "category":"Bars & Pubs",
            "type":"Food & Drink"
        }
    ],
    "sg:phone":"+1 806 274 2253",
    "sg:postcode":"79007",
    "sg:province":"TX",
    "wof:name":"Good Times",
    "wof:placetype":"venue"
},
  "geometry": {"coordinates":[-101.38977,35.67014],"type":"Point"}
}