{
  "type": "Feature",
  "properties": {
    "iso:country":"US",
    "sg:address":"1301 W Waco Dr",
    "sg:city":"Waco",
    "sg:classifiers":[
        {
            "category":"Personal",
            "subcategory":"Barber",
            "type":"Services"
        }
    ],
    "sg:phone":"+1 254 753 7818",
    "sg:postcode":"76707",
    "sg:province":"TX",
    "sg:tags":[
        "shop"
    ],
    "wof:name":"Mr C's Barber Shop",
    "wof:placetype":"venue"
},
  "geometry": {"coordinates":[-97.14341899999999,31.553126],"type":"Point"}
}