{
  "type": "Feature",
  "properties": {
    "iso:country":"US",
    "sg:address":"3017 Co Rd 7700",
    "sg:city":"Lubbock",
    "sg:classifiers":[
        {
            "category":"Building & Trades",
            "subcategory":"Construction",
            "type":"Services"
        }
    ],
    "sg:phone":"+1 806 863 3385",
    "sg:postcode":"79423",
    "sg:province":"TX",
    "sg:tags":[
        "contractor"
    ],
    "wof:name":"Sotelo Asphalt Service",
    "wof:placetype":"venue"
},
  "geometry": {"coordinates":[-101.88096299999999,33.432662],"type":"Point"}
}