{
  "type": "Feature",
  "properties": {
    "iso:country":"US",
    "sg:address":"121 N Greenville Ave",
    "sg:city":"Allen",
    "sg:classifiers":[
        {
            "category":"Retail",
            "subcategory":"Laundry & Dry Cleaning",
            "type":"Services"
        },
        {
            "category":"Shopping",
            "subcategory":"Clothing, Apparel, & Fashions",
            "type":"Retail Goods"
        }
    ],
    "sg:phone":"+1 972 390 9931",
    "sg:postcode":"75002",
    "sg:province":"TX",
    "sg:tags":[
        "repair",
        "alteration",
        "shoe"
    ],
    "wof:name":"C 3 Alteration",
    "wof:placetype":"venue"
},
  "geometry": {"coordinates":[-96.661963,33.100291],"type":"Point"}
}