{
  "type": "Feature",
  "properties": {
    "iso:country":"US",
    "sg:address":"7339 Lazy Trl",
    "sg:city":"San Antonio",
    "sg:classifiers":[
        {
            "category":"Professional",
            "type":"Services"
        }
    ],
    "sg:phone":"+1 210 681 6469",
    "sg:postcode":"78250",
    "sg:province":"TX",
    "wof:name":"Miles Misoon",
    "wof:placetype":"venue"
},
  "geometry": {"coordinates":[-98.67653,29.511409],"type":"Point"}
}