{
  "type": "Feature",
  "properties": {
    "iso:country":"US",
    "sg:address":"5201 Covington Ln",
    "sg:city":"Temple",
    "sg:classifiers":[
        {
            "category":"Shopping",
            "subcategory":"Used Merchandise",
            "type":"Retail Goods"
        }
    ],
    "sg:phone":"+1 254 778 1016",
    "sg:postcode":"76502",
    "sg:province":"TX",
    "wof:name":"Bunny Dust",
    "wof:placetype":"venue"
},
  "geometry": {"coordinates":[-97.391262,31.054976],"type":"Point"}
}