{
  "type": "Feature",
  "properties": {
    "iso:country":"US",
    "sg:address":"12850 Memorial Dr",
    "sg:city":"Houston",
    "sg:classifiers":[
        {
            "category":"Shopping",
            "subcategory":"Pharmacy",
            "type":"Retail Goods"
        }
    ],
    "sg:phone":"+1 713 722 7247",
    "sg:postcode":"77024",
    "sg:province":"TX",
    "sg:tags":[
        "drugstore",
        "store",
        "drug"
    ],
    "sg:website":"www.walgreens.com",
    "wof:name":"Walgreens",
    "wof:placetype":"venue"
},
  "geometry": {"coordinates":[-95.56082000000001,29.772852],"type":"Point"}
}