{
  "type": "Feature",
  "properties": {
    "iso:country":"US",
    "sg:address":"110 Cuernavaca Dr N",
    "sg:city":"Austin",
    "sg:classifiers":[
        {
            "category":"Education",
            "subcategory":"Special Training",
            "type":"Public Place"
        }
    ],
    "sg:phone":"+1 512 263 9944",
    "sg:postcode":"78733",
    "sg:province":"TX",
    "sg:tags":[
        "school",
        "language"
    ],
    "wof:name":"Rapid Spanish",
    "wof:placetype":"venue"
},
  "geometry": {"coordinates":[-97.8715,30.328547],"type":"Point"}
}