{
  "type": "Feature",
  "properties": {
    "iso:country":"US",
    "sg:address":"13505 Westheimer Rd",
    "sg:city":"Houston",
    "sg:classifiers":[
        {
            "category":"Personal",
            "subcategory":"Beauty Salon",
            "type":"Services"
        }
    ],
    "sg:phone":"+1 281 531 6241",
    "sg:postcode":"77077",
    "sg:province":"TX",
    "sg:tags":[
        "shop"
    ],
    "wof:name":"Layers",
    "wof:placetype":"venue"
},
  "geometry": {"coordinates":[-95.62879100000001,29.735787],"type":"Point"}
}