{
  "type": "Feature",
  "properties": {
    "iso:country":"US",
    "sg:address":"10826 Green Hollow St",
    "sg:city":"San Antonio",
    "sg:classifiers":[
        {
            "category":"Manufacturing",
            "subcategory":"Glass & Minerals",
            "type":"Manufacturing & Wholesale Goods"
        }
    ],
    "sg:phone":"+1 210 633 1131",
    "sg:postcode":"78223",
    "sg:province":"TX",
    "sg:tags":[
        "mfg"
    ],
    "wof:name":"Als Datacom",
    "wof:placetype":"venue"
},
  "geometry": {"coordinates":[-98.38148200000001,29.310744],"type":"Point"}
}