{
  "type": "Feature",
  "properties": {
    "iso:country":"US",
    "sg:address":"1276 W Arkansas Ln",
    "sg:city":"Arlington",
    "sg:classifiers":[
        {
            "category":"Manufacturing",
            "subcategory":"Tools & Machinery",
            "type":"Manufacturing & Wholesale Goods"
        }
    ],
    "sg:phone":"+1 817 459 4277",
    "sg:postcode":"76013",
    "sg:province":"TX",
    "sg:tags":[
        "machine",
        "shop"
    ],
    "wof:name":"L G Machine & Mfg Inc",
    "wof:placetype":"venue"
},
  "geometry": {"coordinates":[-97.1237,32.706419],"type":"Point"}
}