{
  "type": "Feature",
  "properties": {
    "iso:country":"US",
    "sg:address":"7806 Lavender St",
    "sg:city":"Houston",
    "sg:classifiers":[
        {
            "category":"Organizations",
            "subcategory":"Religious Organization",
            "type":"Services"
        }
    ],
    "sg:phone":"+1 713 631 0005",
    "sg:postcode":"77016",
    "sg:province":"TX",
    "wof:name":"Abundance of Blessings Ch",
    "wof:placetype":"venue"
},
  "geometry": {"coordinates":[-95.321196,29.827578],"type":"Point"}
}