{
  "type": "Feature",
  "properties": {
    "iso:country":"US",
    "sg:address":"2944 Motley Dr",
    "sg:city":"Mesquite",
    "sg:classifiers":[
        {
            "category":"Health Services",
            "subcategory":"Doctor",
            "type":"Services"
        }
    ],
    "sg:phone":"+1 972 681 2375",
    "sg:postcode":"75150",
    "sg:province":"TX",
    "sg:tags":[
        "medical"
    ],
    "wof:name":"James D Houston MD Inc",
    "wof:placetype":"venue"
},
  "geometry": {"coordinates":[-96.648938,32.804827],"type":"Point"}
}