{
  "type": "Feature",
  "properties": {
    "iso:country":"US",
    "sg:address":"6200 Forest Highlands Dr",
    "sg:city":"Fort Worth",
    "sg:classifiers":[
        {
            "category":"Professional",
            "subcategory":"Management & Consulting",
            "type":"Services"
        }
    ],
    "sg:phone":"+1 817 346 3012",
    "sg:postcode":"76132",
    "sg:province":"TX",
    "wof:name":"R McClure Management LLC",
    "wof:placetype":"venue"
},
  "geometry": {"coordinates":[-97.435232,32.660403],"type":"Point"}
}