{
  "type": "Feature",
  "properties": {
    "iso:country":"US",
    "sg:address":"11053 Richard Cir",
    "sg:city":"Forney",
    "sg:classifiers":[
        {
            "category":"Building & Trades",
            "subcategory":"Plumbing",
            "type":"Services"
        }
    ],
    "sg:phone":"+1 972 564 5166",
    "sg:postcode":"75126",
    "sg:province":"TX",
    "sg:tags":[
        "plumber",
        "industrial",
        "contractors-commercial"
    ],
    "wof:name":"Bubba's Plumbing",
    "wof:placetype":"venue"
},
  "geometry": {"coordinates":[-96.438422,32.722062],"type":"Point"}
}