{
  "type": "Feature",
  "properties": {
    "iso:country":"US",
    "sg:address":"738 Walnut St",
    "sg:city":"Columbus",
    "sg:classifiers":[
        {
            "category":"Personal",
            "type":"Services"
        }
    ],
    "sg:phone":"+1 979 732 8888",
    "sg:postcode":"78934",
    "sg:province":"TX",
    "sg:tags":[
        "therapist",
        "massage"
    ],
    "wof:name":"Therapeutic Massage",
    "wof:placetype":"venue"
},
  "geometry": {"coordinates":[-96.543892,29.706581],"type":"Point"}
}