{
  "type": "Feature",
  "properties": {
    "iso:country":"US",
    "sg:address":"525 N University Dr",
    "sg:city":"Nacogdoches",
    "sg:classifiers":[
        {
            "category":"Shopping",
            "subcategory":"Discount & Variety Stores",
            "type":"Retail Goods"
        },
        {
            "category":"Shopping",
            "subcategory":"Department Store",
            "type":"Retail Goods"
        }
    ],
    "sg:phone":"+1 936 462 9767",
    "sg:postcode":"75962",
    "sg:province":"TX",
    "sg:tags":[
        "shop"
    ],
    "wof:name":"Family Dollar Stores",
    "wof:placetype":"venue"
},
  "geometry": {"coordinates":[-94.643258,31.60437],"type":"Point"}
}