{
  "type": "Feature",
  "properties": {
    "iso:country":"US",
    "sg:address":"12901 N I H 35 Ste 3-300",
    "sg:city":"Austin",
    "sg:classifiers":[
        {
            "category":"Shopping",
            "subcategory":"Department Store",
            "type":"Retail Goods"
        }
    ],
    "sg:phone":"+1 512 651 0608",
    "sg:postcode":"78753",
    "sg:province":"TX",
    "sg:website":"www.target.com",
    "wof:name":"SuperTarget",
    "wof:placetype":"venue"
},
  "geometry": {"coordinates":[-97.6728,30.415675],"type":"Point"}
}