{
  "type": "Feature",
  "properties": {
    "iso:country":"US",
    "sg:address":"205 N Green St",
    "sg:city":"Grand Saline",
    "sg:classifiers":[
        {
            "category":"Health Services",
            "subcategory":"Clinic",
            "type":"Services"
        }
    ],
    "sg:phone":"+1 903 962 3026",
    "sg:postcode":"75140",
    "sg:province":"TX",
    "sg:tags":[
        "home",
        "care"
    ],
    "wof:name":"Secure Home Health Inc",
    "wof:placetype":"venue"
},
  "geometry": {"coordinates":[-95.70857700000001,32.674502],"type":"Point"}
}