{
  "type": "Feature",
  "properties": {
    "iso:country":"US",
    "sg:address":"301 E Broadway St",
    "sg:city":"Cuero",
    "sg:classifiers":[
        {
            "category":"Food & Beverages",
            "subcategory":"Groceries & Convenience Stores",
            "type":"Retail Goods"
        }
    ],
    "sg:phone":"+1 361 275 9888",
    "sg:postcode":"77954",
    "sg:province":"TX",
    "wof:name":"Get & Go Food Mart",
    "wof:placetype":"venue"
},
  "geometry": {"coordinates":[-97.287719,29.092924],"type":"Point"}
}