{
  "type": "Feature",
  "properties": {
    "iso:country":"US",
    "sg:address":"8726 Antelope Dr",
    "sg:city":"Houston",
    "sg:classifiers":[
        {
            "category":"Travel",
            "subcategory":"Hotels & Motels",
            "type":"Entertainment"
        }
    ],
    "sg:phone":"+1 713 224 6300",
    "sg:postcode":"77063",
    "sg:province":"TX",
    "wof:name":"Ambulance Pro",
    "wof:placetype":"venue"
},
  "geometry": {"coordinates":[-95.51746799999999,29.724866],"type":"Point"}
}