{
  "type": "Feature",
  "properties": {
    "iso:country":"US",
    "sg:address":"20306 FM 1094",
    "sg:city":"New Ulm",
    "sg:classifiers":[
        {
            "category":"Shopping",
            "subcategory":"Florist",
            "type":"Retail Goods"
        }
    ],
    "sg:phone":"+1 979 992 3011",
    "sg:postcode":"78950",
    "sg:province":"TX",
    "wof:name":"Sweet Petals Florist Inc",
    "wof:placetype":"venue"
},
  "geometry": {"coordinates":[-96.433617,29.884548],"type":"Point"}
}