{
  "type": "Feature",
  "properties": {
    "iso:country":"US",
    "sg:address":"804 W American Blvd Ste B",
    "sg:city":"Muleshoe",
    "sg:classifiers":[
        {
            "category":"Health Services",
            "subcategory":"Chiropractor",
            "type":"Services"
        }
    ],
    "sg:phone":"+1 806 272 4000",
    "sg:postcode":"79347",
    "sg:province":"TX",
    "sg:tags":[
        "chiropractic"
    ],
    "wof:name":"Partain Chiropractic Wellness Center Pa",
    "wof:placetype":"venue"
},
  "geometry": {"coordinates":[-102.731042,34.230595],"type":"Point"}
}