{
  "type": "Feature",
  "properties": {
    "iso:country":"US",
    "sg:address":"224 E Cano St",
    "sg:city":"Edinburg",
    "sg:classifiers":[
        {
            "category":"Retail",
            "subcategory":"Laundry & Dry Cleaning",
            "type":"Services"
        }
    ],
    "sg:phone":"+1 956 316 2424",
    "sg:postcode":"78539",
    "sg:province":"TX",
    "sg:tags":[
        "drycleaning",
        "plant"
    ],
    "wof:name":"Mr Press Cleaners & Laundry",
    "wof:placetype":"venue"
},
  "geometry": {"coordinates":[-98.16060299999999,26.300013],"type":"Point"}
}