{
  "type": "Feature",
  "properties": {
    "iso:country":"US",
    "sg:address":"2616 Daytona Ave",
    "sg:city":"Mcallen",
    "sg:classifiers":[
        {
            "category":"Shopping",
            "subcategory":"Used Merchandise",
            "type":"Retail Goods"
        }
    ],
    "sg:phone":"+1 956 687 2967",
    "sg:postcode":"78503",
    "sg:province":"TX",
    "wof:name":"Dela Garza Carla",
    "wof:placetype":"venue"
},
  "geometry": {"coordinates":[-98.256017,26.169681],"type":"Point"}
}