{
  "type": "Feature",
  "properties": {
    "iso:country":"US",
    "sg:address":"3630 Harry Hines Blvd",
    "sg:city":"Dallas",
    "sg:classifiers":[
        {
            "category":"Museum",
            "type":"Entertainment"
        }
    ],
    "sg:phone":"+1 214 520 2219",
    "sg:postcode":"75219",
    "sg:province":"TX",
    "sg:tags":[
        "organization",
        "arts",
        "information"
    ],
    "wof:name":"Fine Arts Chamber Players",
    "wof:placetype":"venue"
},
  "geometry": {"coordinates":[-96.816946,32.800253],"type":"Point"}
}