{
  "type": "Feature",
  "properties": {
    "iso:country":"US",
    "sg:address":"3300 Nacogdoches Rd",
    "sg:city":"San Antonio",
    "sg:classifiers":[
        {
            "category":"Government",
            "subcategory":"Office",
            "type":"Public Place"
        }
    ],
    "sg:phone":"+1 210 646 0399",
    "sg:postcode":"78217",
    "sg:province":"TX",
    "wof:name":"Texas Enforcement Div",
    "wof:placetype":"venue"
},
  "geometry": {"coordinates":[-98.432073,29.529228],"type":"Point"}
}