{
  "type": "Feature",
  "properties": {
    "iso:country":"US",
    "sg:address":"6263 Mcneil Dr Apt 2514",
    "sg:city":"Austin",
    "sg:classifiers":[
        {
            "category":"Shopping",
            "subcategory":"Department Store",
            "type":"Retail Goods"
        },
        {
            "category":"Shopping",
            "subcategory":"Clothing, Apparel, & Fashions",
            "type":"Retail Goods"
        },
        {
            "category":"Shopping",
            "type":"Retail Goods"
        },
        {
            "category":"Shopping",
            "subcategory":"Discount & Variety Stores",
            "type":"Retail Goods"
        }
    ],
    "sg:phone":"+1 512 249 9185",
    "sg:postcode":"78729",
    "sg:province":"TX",
    "sg:tags":[
        "clothing",
        "merchandise"
    ],
    "sg:website":"http://www.walmart.com",
    "wof:name":"Wal-Mart",
    "wof:placetype":"venue"
},
  "geometry": {"coordinates":[-97.74767300000001,30.441851],"type":"Point"}
}