{
  "type": "Feature",
  "properties": {
    "iso:country":"US",
    "sg:address":"4945 E 42nd St",
    "sg:city":"Odessa",
    "sg:classifiers":[
        {
            "category":"Restaurant",
            "type":"Food & Drink"
        }
    ],
    "sg:phone":"+1 432 362 5512",
    "sg:postcode":"79762",
    "sg:province":"TX",
    "wof:name":"Rosa's Cafe & Tortilla Factory",
    "wof:placetype":"venue"
},
  "geometry": {"coordinates":[-102.33601899999999,31.893069],"type":"Point"}
}