{
  "type": "Feature",
  "properties": {
    "iso:country":"US",
    "sg:address":"11615 Landsdowne Dr",
    "sg:city":"Houston",
    "sg:classifiers":[
        {
            "category":"Arts & Performance",
            "subcategory":"Theater",
            "type":"Entertainment"
        }
    ],
    "sg:phone":"+1 713 729 5689",
    "sg:postcode":"77035",
    "sg:province":"TX",
    "sg:tags":[
        "group"
    ],
    "wof:name":"Midstream",
    "wof:placetype":"venue"
},
  "geometry": {"coordinates":[-95.486732,29.651565],"type":"Point"}
}