{
  "type": "Feature",
  "properties": {
    "iso:country":"US",
    "sg:address":"120 S Carroll Blvd",
    "sg:city":"Denton",
    "sg:classifiers":[
        {
            "category":"Cemetery",
            "type":"Public Place"
        },
        {
            "category":"Retail",
            "subcategory":"Funeral Services",
            "type":"Services"
        }
    ],
    "sg:phone":"+1 940 382 2214",
    "sg:postcode":"76201",
    "sg:province":"TX",
    "sg:tags":[
        "director",
        "embalmer",
        "crematory",
        "plans-pre-arranged",
        "supply"
    ],
    "wof:name":"Denton Funeral Home",
    "wof:placetype":"venue"
},
  "geometry": {"coordinates":[-97.13725599999999,33.214362],"type":"Point"}
}