{
  "type": "Feature",
  "properties": {
    "iso:country":"US",
    "sg:address":"9400 Grogans Mill Rd",
    "sg:city":"Spring",
    "sg:classifiers":[
        {
            "category":"Transit Center",
            "subcategory":"Freight",
            "type":"Transportation"
        }
    ],
    "sg:phone":"+1 832 585 8611",
    "sg:postcode":"77380",
    "sg:province":"TX",
    "sg:tags":[
        "air",
        "cargo",
        "express",
        "package"
    ],
    "wof:name":"Volga Dnepr Unique Air Cargo",
    "wof:placetype":"venue"
},
  "geometry": {"coordinates":[-95.46534699999999,30.167509],"type":"Point"}
}