{
  "type": "Feature",
  "properties": {
    "iso:country":"US",
    "sg:address":"1055 W Sam Houston Pkwy N Ste 110",
    "sg:city":"Houston",
    "sg:classifiers":[
        {
            "category":"Shopping",
            "subcategory":"Luggage & Leather Goods",
            "type":"Retail Goods"
        }
    ],
    "sg:phone":"+1 713 461 1191",
    "sg:postcode":"77043",
    "sg:province":"TX",
    "sg:website":"www.luggageandleather.com",
    "wof:name":"Luggage and Leather",
    "wof:placetype":"venue"
},
  "geometry": {"coordinates":[-95.56496799999999,29.787991],"type":"Point"}
}