{
  "type": "Feature",
  "properties": {
    "iso:country":"US",
    "sg:address":"1514 Franklin Ave",
    "sg:city":"Bonham",
    "sg:classifiers":[
        {
            "category":"Restaurant",
            "type":"Food & Drink"
        }
    ],
    "sg:phone":"+1 903 583 3844",
    "sg:postcode":"75418",
    "sg:province":"TX",
    "sg:tags":[
        "eating"
    ],
    "wof:name":"Fannin Enterprises Inc",
    "wof:placetype":"venue"
},
  "geometry": {"coordinates":[-96.180618,33.590947],"type":"Point"}
}