{
  "type": "Feature",
  "properties": {
    "iso:country":"US",
    "sg:address":"1202 S FM 116",
    "sg:city":"Copperas Cove",
    "sg:classifiers":[
        {
            "category":"Real Estate",
            "subcategory":"Real Estate Operator",
            "type":"Services"
        }
    ],
    "sg:phone":"+1 254 547 0533",
    "sg:postcode":"76522",
    "sg:province":"TX",
    "sg:tags":[
        "apartment"
    ],
    "wof:name":"Clear Creek Meadows",
    "wof:placetype":"venue"
},
  "geometry": {"coordinates":[-97.90955099999999,31.109977],"type":"Point"}
}