{
  "type": "Feature",
  "properties": {
    "iso:country":"US",
    "sg:address":"5955 S M L King Jr Pkwy",
    "sg:city":"Beaumont",
    "sg:classifiers":[
        {
            "category":"Recreation",
            "subcategory":"Marina",
            "type":"Entertainment"
        }
    ],
    "sg:phone":"+1 409 838 6908",
    "sg:postcode":"77705",
    "sg:province":"TX",
    "sg:tags":[
        "repairing",
        "boat"
    ],
    "wof:name":"Boat Marine Salvage Parts",
    "wof:placetype":"venue"
},
  "geometry": {"coordinates":[-94.05780300000001,30.028433],"type":"Point"}
}