{
  "type": "Feature",
  "properties": {
    "iso:country":"US",
    "sg:address":"15422 Eastex Fwy",
    "sg:city":"Humble",
    "sg:classifiers":[
        {
            "category":"Autos & Motor Vehicles",
            "subcategory":"Recreational Vehicle Sales",
            "type":"Retail Goods"
        }
    ],
    "sg:phone":"+1 281 441 2138",
    "sg:postcode":"77396",
    "sg:province":"TX",
    "wof:name":"Eastex Camper Sales",
    "wof:placetype":"venue"
},
  "geometry": {"coordinates":[-95.293075,29.946458],"type":"Point"}
}