{
  "type": "Feature",
  "properties": {
    "iso:country":"US",
    "sg:address":"7104 Masters Rd",
    "sg:city":"Manvel",
    "sg:classifiers":[
        {
            "category":"Education",
            "subcategory":"Library",
            "type":"Public Place"
        }
    ],
    "sg:phone":"+1 281 489 7596",
    "sg:postcode":"77578",
    "sg:province":"TX",
    "wof:name":"Manvel Branch Library",
    "wof:placetype":"venue"
},
  "geometry": {"coordinates":[-95.355053,29.470197],"type":"Point"}
}