{
  "type": "Feature",
  "properties": {
    "iso:country":"US",
    "sg:address":"2002 45th St",
    "sg:city":"Galveston",
    "sg:classifiers":[
        {
            "category":"Health Services",
            "subcategory":"Doctor",
            "type":"Services"
        }
    ],
    "sg:phone":"+1 409 750 8000",
    "sg:postcode":"77550",
    "sg:province":"TX",
    "sg:tags":[
        "dentist"
    ],
    "wof:name":"George M Moore DDS",
    "wof:placetype":"venue"
},
  "geometry": {"coordinates":[-94.81401200000001,29.284275],"type":"Point"}
}