{
  "type": "Feature",
  "properties": {
    "iso:country":"US",
    "sg:address":"808 Foxglove Dr",
    "sg:city":"Edna",
    "sg:classifiers":[
        {
            "category":"Building & Trades",
            "subcategory":"Construction",
            "type":"Services"
        }
    ],
    "sg:phone":"+1 361 782 5668",
    "sg:postcode":"77957",
    "sg:province":"TX",
    "sg:tags":[
        "contractor"
    ],
    "wof:name":"Grona Roofing",
    "wof:placetype":"venue"
},
  "geometry": {"coordinates":[-96.64708899999999,28.964939],"type":"Point"}
}