{
  "type": "Feature",
  "properties": {
    "iso:country":"US",
    "sg:address":"2810 Baskin Dr",
    "sg:city":"Lancaster",
    "sg:classifiers":[
        {
            "category":"Shopping",
            "type":"Retail Goods"
        }
    ],
    "sg:phone":"+1 972 224 0397",
    "sg:postcode":"75134",
    "sg:province":"TX",
    "sg:tags":[
        "item",
        "boutique"
    ],
    "wof:name":"Adkison Boutique",
    "wof:placetype":"venue"
},
  "geometry": {"coordinates":[-96.793503,32.617599],"type":"Point"}
}