{
  "type": "Feature",
  "properties": {
    "iso:country":"US",
    "sg:address":"333 Brough Rd",
    "sg:city":"Huntington",
    "sg:classifiers":[
        {
            "category":"Freight",
            "type":"Transportation"
        }
    ],
    "sg:phone":"+1 936 854 2226",
    "sg:postcode":"75949",
    "sg:province":"TX",
    "sg:tags":[
        "tex",
        "throughout",
        "trucking"
    ],
    "wof:name":"J & J Trucking",
    "wof:placetype":"venue"
},
  "geometry": {"coordinates":[-94.52408699999999,31.369218],"type":"Point"}
}