{
  "type": "Feature",
  "properties": {
    "iso:country":"US",
    "sg:address":"624 San Carlos Dr",
    "sg:city":"Garland",
    "sg:classifiers":[
        {
            "category":"Wholesale",
            "subcategory":"Machinery & Supplies",
            "type":"Manufacturing & Wholesale Goods"
        }
    ],
    "sg:phone":"+1 972 613 6676",
    "sg:postcode":"75043",
    "sg:province":"TX",
    "sg:tags":[
        "equipment",
        "industrial"
    ],
    "wof:name":"Interco Products Inc",
    "wof:placetype":"venue"
},
  "geometry": {"coordinates":[-96.629272,32.853476],"type":"Point"}
}