{
  "type": "Feature",
  "properties": {
    "iso:country":"US",
    "sg:address":"2995 Lamar Ave",
    "sg:city":"Paris",
    "sg:classifiers":[
        {
            "category":"Government",
            "subcategory":"Office",
            "type":"Public Place"
        }
    ],
    "sg:phone":"+1 903 785 0761",
    "sg:postcode":"75460",
    "sg:province":"TX",
    "sg:tags":[
        "federal",
        "program"
    ],
    "wof:name":"US Health Dept",
    "wof:placetype":"venue"
},
  "geometry": {"coordinates":[-95.52364300000001,33.660949],"type":"Point"}
}