{
  "type": "Feature",
  "properties": {
    "iso:country":"US",
    "sg:address":"1949 Pine Ridge Dr",
    "sg:city":"Bedford",
    "sg:classifiers":[
        {
            "category":"Building & Trades",
            "subcategory":"Landscaping Services",
            "type":"Services"
        }
    ],
    "sg:phone":"+1 817 283 3163",
    "sg:postcode":"76021",
    "sg:province":"TX",
    "sg:tags":[
        "lawn",
        "maintenance",
        "grounds"
    ],
    "wof:name":"Dane's Lawn Svc",
    "wof:placetype":"venue"
},
  "geometry": {"coordinates":[-97.137624,32.846226],"type":"Point"}
}