{
  "type": "Feature",
  "properties": {
    "iso:country":"US",
    "sg:address":"3428 N Littlejohn Ave",
    "sg:city":"Fort Worth",
    "sg:classifiers":[
        {
            "category":"Organizations",
            "subcategory":"Religious Organization",
            "type":"Services"
        }
    ],
    "sg:phone":"+1 817 534 4771",
    "sg:postcode":"76105",
    "sg:province":"TX",
    "sg:tags":[
        "church"
    ],
    "wof:name":"Miracle Revival Ctr",
    "wof:placetype":"venue"
},
  "geometry": {"coordinates":[-97.273326,32.720326],"type":"Point"}
}