{
  "type": "Feature",
  "properties": {
    "iso:country":"US",
    "sg:address":"876 Norwood Rd",
    "sg:city":"Sherman",
    "sg:classifiers":[
        {
            "category":"Shopping",
            "subcategory":"Clothing, Apparel, & Fashions",
            "type":"Retail Goods"
        }
    ],
    "sg:phone":"+1 903 868 3105",
    "sg:postcode":"75092",
    "sg:province":"TX",
    "sg:tags":[
        "merchandise"
    ],
    "wof:name":"Color ME Patterns",
    "wof:placetype":"venue"
},
  "geometry": {"coordinates":[-96.651259,33.654285],"type":"Point"}
}