{
  "type": "Feature",
  "properties": {
    "iso:country":"US",
    "sg:address":"1450 Main St",
    "sg:city":"Southlake",
    "sg:classifiers":[
        {
            "category":"Shopping",
            "subcategory":"Clothing, Apparel, & Fashions",
            "type":"Retail Goods"
        }
    ],
    "sg:phone":"+1 817 416 6767",
    "sg:postcode":"76092",
    "sg:province":"TX",
    "sg:tags":[
        "infant",
        "wear"
    ],
    "sg:website":"www.oshkoshbgosh.com",
    "wof:name":"Osh Kosh B'Gosh",
    "wof:placetype":"venue"
},
  "geometry": {"coordinates":[-97.123423,32.941834],"type":"Point"}
}