{
  "type": "Feature",
  "properties": {
    "iso:country":"US",
    "sg:address":"925 S Main St",
    "sg:city":"Anthony",
    "sg:classifiers":[
        {
            "category":"Restaurant",
            "type":"Food & Drink"
        }
    ],
    "sg:phone":"+1 915 886 6080",
    "sg:postcode":"79821",
    "sg:province":"NM",
    "sg:tags":[
        "parlor",
        "ice",
        "cream"
    ],
    "wof:name":"Paletas Agua Viva",
    "wof:placetype":"venue"
},
  "geometry": {"coordinates":[-106.605518,31.991753],"type":"Point"}
}