{
  "type": "Feature",
  "properties": {
    "iso:country":"US",
    "sg:address":"21555 Katy Fwy",
    "sg:city":"Katy",
    "sg:classifiers":[
        {
            "category":"Autos & Motor Vehicles",
            "subcategory":"Automobile Sales",
            "type":"Retail Goods"
        }
    ],
    "sg:phone":"+1 866 994 2598",
    "sg:postcode":"77450",
    "sg:province":"TX",
    "sg:tags":[
        "new",
        "car"
    ],
    "sg:website":"http://www.DonMcgillToyotaKaty.com",
    "wof:name":"Don McGill Toyota of Katy",
    "wof:placetype":"venue"
},
  "geometry": {"coordinates":[-95.73983,29.784807],"type":"Point"}
}