{
  "type": "Feature",
  "properties": {
    "iso:country":"US",
    "sg:address":"100 Schertz Pkwy",
    "sg:city":"Schertz",
    "sg:classifiers":[
        {
            "category":"Professional",
            "subcategory":"Lawyer & Legal Services",
            "type":"Services"
        }
    ],
    "sg:phone":"+1 210 658 7799",
    "sg:postcode":"78154",
    "sg:province":"TX",
    "sg:tags":[
        "attorney"
    ],
    "wof:name":"Jodi Head Lopez Law Office",
    "wof:placetype":"venue"
},
  "geometry": {"coordinates":[-98.263538,29.555042],"type":"Point"}
}