{
  "type": "Feature",
  "properties": {
    "iso:country":"US",
    "sg:address":"524 N Salinas Blvd",
    "sg:city":"Donna",
    "sg:classifiers":[
        {
            "category":"Restaurant",
            "type":"Food & Drink"
        }
    ],
    "sg:phone":"+1 956 464 3121",
    "sg:postcode":"78537",
    "sg:province":"TX",
    "sg:tags":[
        "parlor",
        "eating",
        "ice",
        "cream"
    ],
    "wof:name":"Dairy Queen",
    "wof:placetype":"venue"
},
  "geometry": {"coordinates":[-98.041454,26.178404],"type":"Point"}
}