{
  "type": "Feature",
  "properties": {
    "iso:country":"US",
    "sg:address":"3625 W Royal Ln",
    "sg:city":"Irving",
    "sg:classifiers":[
        {
            "category":"Banks & Credit Unions",
            "subcategory":"Bank",
            "type":"Services"
        }
    ],
    "sg:phone":"+1 972 871 7566",
    "sg:postcode":"75063",
    "sg:province":"TX",
    "sg:tags":[
        "loan",
        "real estate"
    ],
    "wof:name":"Home Funds Direct",
    "wof:placetype":"venue"
},
  "geometry": {"coordinates":[-97.000426,32.920608],"type":"Point"}
}