{
  "type": "Feature",
  "properties": {
    "iso:country":"US",
    "sg:address":"3920 Lost Creek Dr",
    "sg:city":"Dallas",
    "sg:classifiers":[
        {
            "category":"Wholesale",
            "subcategory":"Machinery & Supplies",
            "type":"Manufacturing & Wholesale Goods"
        }
    ],
    "sg:phone":"+1 214 337 1283",
    "sg:postcode":"75224",
    "sg:province":"TX",
    "sg:tags":[
        "equipment",
        "industrial"
    ],
    "wof:name":"Mel Handling Equipment Co",
    "wof:placetype":"venue"
},
  "geometry": {"coordinates":[-96.84565000000001,32.696743],"type":"Point"}
}