{
  "type": "Feature",
  "properties": {
    "iso:country":"US",
    "sg:address":"110 W Mockingbird Ln",
    "sg:city":"Austin",
    "sg:classifiers":[
        {
            "category":"Manufacturing",
            "subcategory":"Soap",
            "type":"Manufacturing & Wholesale Goods"
        }
    ],
    "sg:phone":"+1 512 326 1213",
    "sg:postcode":"78745",
    "sg:province":"TX",
    "sg:tags":[
        "perfume-wholesale",
        "manufacturer"
    ],
    "wof:name":"Bunny And Cloud Perfumes",
    "wof:placetype":"venue"
},
  "geometry": {"coordinates":[-97.773776,30.207523],"type":"Point"}
}