{
  "type": "Feature",
  "properties": {
    "iso:country":"US",
    "sg:address":"1131 Rockingham Ln",
    "sg:city":"Richardson",
    "sg:classifiers":[
        {
            "category":"Organizations",
            "subcategory":"Community Association",
            "type":"Services"
        }
    ],
    "sg:phone":"+1 972 644 5979",
    "sg:postcode":"75080",
    "sg:province":"TX",
    "wof:name":"Jr League of Richardson",
    "wof:placetype":"venue"
},
  "geometry": {"coordinates":[-96.739802,32.965041],"type":"Point"}
}