{
  "type": "Feature",
  "properties": {
    "iso:country":"US",
    "sg:address":"119 Dividend Ct",
    "sg:city":"Arlington",
    "sg:classifiers":[
        {
            "category":"Banks & Credit Unions",
            "subcategory":"Bank",
            "type":"Services"
        }
    ],
    "sg:phone":"+1 817 459 4084",
    "sg:postcode":"76012",
    "sg:province":"TX",
    "sg:tags":[
        "personal",
        "institution"
    ],
    "wof:name":"Citifinancial",
    "wof:placetype":"venue"
},
  "geometry": {"coordinates":[-97.15760400000001,32.734513],"type":"Point"}
}