{
  "type": "Feature",
  "properties": {
    "iso:country":"US",
    "sg:address":"3100 Forest Ln",
    "sg:city":"Dallas",
    "sg:classifiers":[
        {
            "category":"Coffee & Tea",
            "type":"Food & Drink"
        }
    ],
    "sg:menulink":"http://www.allmenus.com/tx/northeast/112778-starbucks-coffee/menu/",
    "sg:phone":"+1 972 243 9968",
    "sg:postcode":"75234",
    "sg:province":"TX",
    "sg:tags":[
        "american"
    ],
    "wof:name":"Starbucks Coffee",
    "wof:placetype":"venue"
},
  "geometry": {"coordinates":[-96.871943,32.909416],"type":"Point"}
}