{
  "type": "Feature",
  "properties": {
    "iso:country":"US",
    "sg:address":"311 W Gramercy Pl",
    "sg:city":"San Antonio",
    "sg:classifiers":[
        {
            "category":"Retail",
            "subcategory":"Photofinishing",
            "type":"Services"
        }
    ],
    "sg:phone":"+1 210 736 3130",
    "sg:postcode":"78212",
    "sg:province":"TX",
    "sg:tags":[
        "photo",
        "retouching"
    ],
    "wof:name":"Claudette Victoria",
    "wof:placetype":"venue"
},
  "geometry": {"coordinates":[-98.499144,29.461143],"type":"Point"}
}