{
  "type": "Feature",
  "properties": {
    "iso:country":"US",
    "sg:address":"308 W Yucca Ave",
    "sg:city":"Mcallen",
    "sg:classifiers":[
        {
            "category":"Building & Trades",
            "subcategory":"Construction",
            "type":"Services"
        }
    ],
    "sg:phone":"+1 956 668 0312",
    "sg:postcode":"78504",
    "sg:province":"TX",
    "sg:tags":[
        "contractor"
    ],
    "wof:name":"JRS Masonry Service",
    "wof:placetype":"venue"
},
  "geometry": {"coordinates":[-98.214888,26.248776],"type":"Point"}
}