{
  "type": "Feature",
  "properties": {
    "iso:country":"US",
    "sg:address":"1845 Lake Shore Dr",
    "sg:city":"Waco",
    "sg:classifiers":[
        {
            "category":"Shopping",
            "subcategory":"Florist",
            "type":"Retail Goods"
        }
    ],
    "sg:phone":"+1 254 754 5000",
    "sg:postcode":"76708",
    "sg:province":"TX",
    "wof:name":"Bubbles & Balloons Flowers",
    "wof:placetype":"venue"
},
  "geometry": {"coordinates":[-97.15397400000001,31.601369],"type":"Point"}
}