{
  "type": "Feature",
  "properties": {
    "iso:country":"US",
    "sg:address":"1600 Meadows Ave",
    "sg:city":"Lantana",
    "sg:classifiers":[
        {
            "category":"Professional",
            "subcategory":"Business Services",
            "type":"Services"
        }
    ],
    "sg:phone":"+1 940 725 0361",
    "sg:postcode":"76226",
    "sg:province":"TX",
    "sg:tags":[
        "holding"
    ],
    "wof:name":"Pkw Holdings",
    "wof:placetype":"venue"
},
  "geometry": {"coordinates":[-97.11646500000001,33.099421],"type":"Point"}
}