{
  "type": "Feature",
  "properties": {
    "iso:country":"US",
    "sg:address":"8140 Walnut Hill Ln",
    "sg:city":"Dallas",
    "sg:classifiers":[
        {
            "category":"Real Estate",
            "subcategory":"Real Estate Agent",
            "type":"Services"
        }
    ],
    "sg:phone":"+1 214 696 9500",
    "sg:postcode":"75231",
    "sg:province":"TX",
    "sg:tags":[
        "property",
        "management"
    ],
    "sg:website":"www.regencycenters.com",
    "wof:name":"Regency Centers Corporation",
    "wof:placetype":"venue"
},
  "geometry": {"coordinates":[-96.768214,32.880136],"type":"Point"}
}