{
  "type": "Feature",
  "properties": {
    "iso:country":"US",
    "sg:address":"1240 Shiloh Rd",
    "sg:city":"Plano",
    "sg:classifiers":[
        {
            "category":"Building & Trades",
            "subcategory":"Construction",
            "type":"Services"
        }
    ],
    "sg:phone":"+1 972 422 0470",
    "sg:postcode":"75074",
    "sg:province":"TX",
    "sg:tags":[
        "residential"
    ],
    "wof:name":"R D C Enterprises",
    "wof:placetype":"venue"
},
  "geometry": {"coordinates":[-96.664637,33.012944],"type":"Point"}
}