{
  "type": "Feature",
  "properties": {
    "iso:country":"US",
    "sg:address":"121 Meadow Way",
    "sg:city":"Converse",
    "sg:classifiers":[
        {
            "category":"Shopping",
            "subcategory":"Books",
            "type":"Retail Goods"
        }
    ],
    "sg:phone":"+1 210 659 4845",
    "sg:postcode":"78109",
    "sg:province":"TX",
    "wof:name":"Voodoo Comics",
    "wof:placetype":"venue"
},
  "geometry": {"coordinates":[-98.317683,29.524772],"type":"Point"}
}