{
  "type": "Feature",
  "properties": {
    "iso:country":"US",
    "sg:address":"7512 Big Leaf Ln",
    "sg:city":"Fort Worth",
    "sg:classifiers":[
        {
            "category":"Professional",
            "type":"Services"
        }
    ],
    "sg:phone":"+1 817 847 5432",
    "sg:postcode":"76137",
    "sg:province":"TX",
    "wof:name":"Kpy",
    "wof:placetype":"venue"
},
  "geometry": {"coordinates":[-97.29426100000001,32.875211],"type":"Point"}
}