{
  "type": "Feature",
  "properties": {
    "iso:country":"US",
    "sg:address":"5934 River Oaks Blvd",
    "sg:city":"Fort Worth",
    "sg:classifiers":[
        {
            "category":"Education",
            "subcategory":"Dance Studio",
            "type":"Public Place"
        }
    ],
    "sg:phone":"+1 817 738 4463",
    "sg:postcode":"76114",
    "sg:province":"TX",
    "sg:tags":[
        "instruction",
        "dancing"
    ],
    "wof:name":"Dance Expressions",
    "wof:placetype":"venue"
},
  "geometry": {"coordinates":[-97.408215,32.765969],"type":"Point"}
}