{
  "type": "Feature",
  "properties": {
    "iso:country":"US",
    "sg:address":"29801 I- 45 N",
    "sg:city":"Spring",
    "sg:classifiers":[
        {
            "category":"Professional",
            "subcategory":"Accounting & Tax Preparation",
            "type":"Services"
        }
    ],
    "sg:phone":"+1 281 296 2122",
    "sg:postcode":"77381",
    "sg:province":"TX",
    "sg:tags":[
        "billing"
    ],
    "wof:name":"Bottom Line Billing & Cllctns",
    "wof:placetype":"venue"
},
  "geometry": {"coordinates":[-95.45272199999999,30.181395],"type":"Point"}
}