{
  "type": "Feature",
  "properties": {
    "iso:country":"US",
    "sg:address":"423 Mustang Mesa",
    "sg:city":"Liberty Hill",
    "sg:classifiers":[
        {
            "category":"Building & Trades",
            "subcategory":"Equipment Rental",
            "type":"Services"
        }
    ],
    "sg:phone":"+1 512 778 6601",
    "sg:postcode":"78642",
    "sg:province":"TX",
    "sg:tags":[
        "medical"
    ],
    "wof:name":"GE Medical Systems",
    "wof:placetype":"venue"
},
  "geometry": {"coordinates":[-97.92911599999999,30.699299],"type":"Point"}
}