{
  "type": "Feature",
  "properties": {
    "iso:country":"US",
    "sg:address":"302 Wickes St",
    "sg:city":"San Antonio",
    "sg:classifiers":[
        {
            "category":"Professional",
            "subcategory":"Lawyer & Legal Services",
            "type":"Services"
        }
    ],
    "sg:phone":"+1 210 472 1500",
    "sg:postcode":"78210",
    "sg:province":"TX",
    "wof:name":"Emmett Marita",
    "wof:placetype":"venue"
},
  "geometry": {"coordinates":[-98.490466,29.406876],"type":"Point"}
}