{
  "type": "Feature",
  "properties": {
    "iso:country":"US",
    "sg:address":"1207 Lake St",
    "sg:city":"Fort Worth",
    "sg:classifiers":[
        {
            "category":"Organizations",
            "subcategory":"Non-profit Organization",
            "type":"Services"
        }
    ],
    "sg:phone":"+1 817 336 2492",
    "sg:postcode":"76102",
    "sg:province":"TX",
    "sg:tags":[
        "information",
        "alcoholism",
        "treatment"
    ],
    "wof:name":"Al-Anon & Al-Ateen Information",
    "wof:placetype":"venue"
},
  "geometry": {"coordinates":[-97.338955,32.746087],"type":"Point"}
}