{
  "type": "Feature",
  "properties": {
    "iso:country":"US",
    "sg:address":"742 Archstone",
    "sg:city":"San Antonio",
    "sg:classifiers":[
        {
            "category":"Banks & Credit Unions",
            "subcategory":"Financial Services",
            "type":"Services"
        }
    ],
    "sg:phone":"+1 210 497 3354",
    "sg:postcode":"78258",
    "sg:province":"TX",
    "sg:tags":[
        "company",
        "holding"
    ],
    "wof:name":"P&J Davidson Holdings LLC",
    "wof:placetype":"venue"
},
  "geometry": {"coordinates":[-98.49792600000001,29.646176],"type":"Point"}
}