{
  "type": "Feature",
  "properties": {
    "iso:country":"US",
    "sg:address":"4798 Doniphan Dr",
    "sg:city":"El Paso",
    "sg:classifiers":[
        {
            "category":"Home & Garden",
            "subcategory":"Home Furnishings",
            "type":"Retail Goods"
        }
    ],
    "sg:phone":"+1 915 587 5077",
    "sg:postcode":"79922",
    "sg:province":"TX",
    "sg:tags":[
        "reupholstery",
        "wallpaper",
        "drapery",
        "carpet"
    ],
    "wof:name":"England Drapes Boutique",
    "wof:placetype":"venue"
},
  "geometry": {"coordinates":[-106.574507,31.83305],"type":"Point"}
}