{
  "type": "Feature",
  "properties": {
    "iso:country":"US",
    "sg:address":"5414 Fisher Cir",
    "sg:city":"Corpus Christi",
    "sg:classifiers":[
        {
            "category":"Shopping",
            "subcategory":"Jewelry",
            "type":"Retail Goods"
        }
    ],
    "sg:phone":"+1 361 992 0816",
    "sg:postcode":"78413",
    "sg:province":"TX",
    "sg:tags":[
        "jeweler"
    ],
    "wof:name":"Jewels & Trinkets",
    "wof:placetype":"venue"
},
  "geometry": {"coordinates":[-97.40244199999999,27.664613],"type":"Point"}
}