{
  "type": "Feature",
  "properties": {
    "iso:country":"US",
    "sg:address":"2825 Belt Line Rd",
    "sg:city":"Garland",
    "sg:classifiers":[
        {
            "category":"Restaurant",
            "type":"Food & Drink"
        }
    ],
    "sg:phone":"+1 972 414 8886",
    "sg:postcode":"75044",
    "sg:province":"TX",
    "wof:name":"Mr Jims Pizza",
    "wof:placetype":"venue"
},
  "geometry": {"coordinates":[-96.673136,32.944744],"type":"Point"}
}