{
  "type": "Feature",
  "properties": {
    "iso:country":"US",
    "sg:address":"5916 Curzon Ave",
    "sg:city":"Fort Worth",
    "sg:classifiers":[
        {
            "category":"Wholesale",
            "subcategory":"Medical Equipment & Supplies",
            "type":"Manufacturing & Wholesale Goods"
        }
    ],
    "sg:phone":"+1 817 732 6797",
    "sg:postcode":"76107",
    "sg:province":"TX",
    "sg:tags":[
        "re",
        "merchandise"
    ],
    "wof:name":"Relax The Back Store",
    "wof:placetype":"venue"
},
  "geometry": {"coordinates":[-97.413416,32.730303],"type":"Point"}
}