{
  "type": "Feature",
  "properties": {
    "iso:country":"US",
    "sg:address":"2525 Voss Rd",
    "sg:city":"Houston",
    "sg:classifiers":[
        {
            "category":"Real Estate",
            "subcategory":"Real Estate Operator",
            "type":"Services"
        }
    ],
    "sg:phone":"+1 713 974 0566",
    "sg:postcode":"77057",
    "sg:province":"TX",
    "sg:tags":[
        "apartment"
    ],
    "sg:website":"www.liveatalliance.com/Broadston...",
    "wof:name":"Broadstone 2525",
    "wof:placetype":"venue"
},
  "geometry": {"coordinates":[-95.500077,29.739779],"type":"Point"}
}