{
  "type": "Feature",
  "properties": {
    "iso:country":"US",
    "sg:address":"5005 Plantation Ln",
    "sg:city":"Frisco",
    "sg:classifiers":[
        {
            "category":"Social Services",
            "subcategory":"Child Care",
            "type":"Services"
        }
    ],
    "sg:phone":"+1 469 633 0621",
    "sg:postcode":"75035",
    "sg:province":"TX",
    "sg:tags":[
        "day"
    ],
    "wof:name":"Prosper Learn & Play",
    "wof:placetype":"venue"
},
  "geometry": {"coordinates":[-96.780564,33.119286],"type":"Point"}
}