{
  "type": "Feature",
  "properties": {
    "iso:country":"US",
    "sg:address":"1303 Loop 306 S",
    "sg:city":"San Angelo",
    "sg:classifiers":[
        {
            "category":"Freight",
            "type":"Transportation"
        }
    ],
    "sg:phone":"+1 325 651 3000",
    "sg:postcode":"76905",
    "sg:province":"TX",
    "sg:tags":[
        "storage"
    ],
    "wof:name":"Silver Dollar Self Storage",
    "wof:placetype":"venue"
},
  "geometry": {"coordinates":[-100.37806,31.44739],"type":"Point"}
}