{
  "type": "Feature",
  "properties": {
    "iso:country":"US",
    "sg:address":"3525 Andrews Hwy",
    "sg:city":"Midland",
    "sg:classifiers":[
        {
            "category":"Insurance",
            "subcategory":"Insurance Agent",
            "type":"Services"
        }
    ],
    "sg:phone":"+1 432 697 1240",
    "sg:postcode":"79703",
    "sg:province":"TX",
    "sg:tags":[
        "adjuster"
    ],
    "wof:name":"Littleton Group Insurance Clms",
    "wof:placetype":"venue"
},
  "geometry": {"coordinates":[-102.127044,32.004077],"type":"Point"}
}