{
  "type": "Feature",
  "properties": {
    "iso:country":"US",
    "sg:address":"513 E Alamo St",
    "sg:city":"Elgin",
    "sg:classifiers":[
        {
            "category":"Building & Trades",
            "subcategory":"Electrical",
            "type":"Services"
        }
    ],
    "sg:phone":"+1 512 468 2660",
    "sg:postcode":"78621",
    "sg:province":"TX",
    "sg:tags":[
        "electrician"
    ],
    "wof:name":"Alamo Electrical Services",
    "wof:placetype":"venue"
},
  "geometry": {"coordinates":[-97.36430900000001,30.344686],"type":"Point"}
}