{
  "type": "Feature",
  "properties": {
    "iso:country":"US",
    "sg:address":"4414 North Fwy",
    "sg:city":"Houston",
    "sg:classifiers":[
        {
            "category":"Personal",
            "subcategory":"Nail Salon",
            "type":"Services"
        }
    ],
    "sg:phone":"+1 713 695 9000",
    "sg:postcode":"77022",
    "sg:province":"TX",
    "wof:name":"Nails Club",
    "wof:placetype":"venue"
},
  "geometry": {"coordinates":[-95.381578,29.830554],"type":"Point"}
}