{
  "type": "Feature",
  "properties": {
    "iso:country":"US",
    "sg:address":"4005 McCullough Ave",
    "sg:city":"San Antonio",
    "sg:classifiers":[
        {
            "category":"Utilities",
            "subcategory":"Telephone",
            "type":"Services"
        }
    ],
    "sg:phone":"+1 210 824 5300",
    "sg:postcode":"78212",
    "sg:province":"TX",
    "sg:tags":[
        "telecommunication"
    ],
    "wof:name":"Telecom Enterprises",
    "wof:placetype":"venue"
},
  "geometry": {"coordinates":[-98.491866,29.467328],"type":"Point"}
}