{
  "type": "Feature",
  "properties": {
    "iso:country":"US",
    "sg:address":"4808 N County Road 1700",
    "sg:city":"Shallowater",
    "sg:classifiers":[
        {
            "category":"Home & Garden",
            "subcategory":"Household Appliances",
            "type":"Retail Goods"
        },
        {
            "category":"Building & Trades",
            "subcategory":"Plumbing",
            "type":"Services"
        },
        {
            "category":"Building & Trades",
            "subcategory":"Construction",
            "type":"Services"
        },
        {
            "category":"Building & Trades",
            "subcategory":"Electrical",
            "type":"Services"
        },
        {
            "category":"Building & Trades",
            "subcategory":"Cleaning & Sanitation",
            "type":"Services"
        }
    ],
    "sg:phone":"+1 806 316 5872",
    "sg:postcode":"79363",
    "sg:province":"TX",
    "sg:tags":[
        "repair",
        "plumber",
        "specialty",
        "systems-repairing",
        "duct",
        "system",
        "equipment",
        "furnaces-heating",
        "furnaces-repairing",
        "clean",
        "pump",
        "ventilating",
        "heating",
        "contractor",
        "heat",
        "air conditioning",
        "boilers-repair"
    ],
    "sg:website":"http://www.yext.com/p/superpages/reese-heating-air-cond-shallowater-texas.html",
    "wof:name":"Reese Heating & Air Cond",
    "wof:placetype":"venue"
},
  "geometry": {"coordinates":[-101.957195,33.644942],"type":"Point"}
}