{
  "type": "Feature",
  "properties": {
    "iso:country":"US",
    "sg:address":"588 W Harris Ave",
    "sg:city":"Raymondville",
    "sg:classifiers":[
        {
            "category":"Social Services",
            "type":"Services"
        }
    ],
    "sg:phone":"+1 956 689 6445",
    "sg:postcode":"78580",
    "sg:province":"TX",
    "sg:tags":[
        "care",
        "center",
        "day"
    ],
    "wof:name":"TLC Adult Day Care Center",
    "wof:placetype":"venue"
},
  "geometry": {"coordinates":[-97.78713399999999,26.478944],"type":"Point"}
}