{
  "type": "Feature",
  "properties": {
    "iso:country":"US",
    "sg:address":"2500 Bluebonnet Ave",
    "sg:city":"Port Arthur",
    "sg:classifiers":[
        {
            "category":"Shopping",
            "type":"Retail Goods"
        }
    ],
    "sg:phone":"+1 409 982 9211",
    "sg:postcode":"77640",
    "sg:province":"TX",
    "sg:tags":[
        "repair",
        "merchandise"
    ],
    "wof:name":"Noack Locksmith and Supply",
    "wof:placetype":"venue"
},
  "geometry": {"coordinates":[-93.932315,29.897388],"type":"Point"}
}