{
  "type": "Feature",
  "properties": {
    "iso:country":"US",
    "sg:address":"2002 Academy Ln",
    "sg:city":"Dallas",
    "sg:classifiers":[
        {
            "category":"Manufacturing",
            "subcategory":"Printing",
            "type":"Manufacturing & Wholesale Goods"
        }
    ],
    "sg:phone":"+1 972 484 0733",
    "sg:postcode":"75234",
    "sg:province":"TX",
    "sg:tags":[
        "print",
        "newspaper",
        "medium"
    ],
    "wof:name":"USA Today Advertising",
    "wof:placetype":"venue"
},
  "geometry": {"coordinates":[-96.912003,32.919498],"type":"Point"}
}