{
  "type": "Feature",
  "properties": {
    "iso:country":"US",
    "sg:address":"203 I- 35 Svc Rd",
    "sg:city":"Hillsboro",
    "sg:classifiers":[
        {
            "category":"Travel",
            "subcategory":"Hotels & Motels",
            "type":"Entertainment"
        }
    ],
    "sg:phone":"+1 254 582 8452",
    "sg:postcode":"76640",
    "sg:province":"TX",
    "sg:tags":[
        "operation"
    ],
    "wof:name":"Thunderbird Motel",
    "wof:placetype":"venue"
},
  "geometry": {"coordinates":[-97.099616,31.66947],"type":"Point"}
}