{
  "type": "Feature",
  "properties": {
    "iso:country":"US",
    "sg:address":"632 S Friendswood Dr",
    "sg:city":"Friendswood",
    "sg:classifiers":[
        {
            "category":"Insurance",
            "subcategory":"Insurance Agent",
            "type":"Services"
        }
    ],
    "sg:phone":"+1 281 648 3870",
    "sg:postcode":"77546",
    "sg:province":"TX",
    "sg:tags":[
        "adjuster"
    ],
    "wof:name":"Crawley Adjusting Svc",
    "wof:placetype":"venue"
},
  "geometry": {"coordinates":[-95.199108,29.527712],"type":"Point"}
}