{
  "type": "Feature",
  "properties": {
    "iso:country":"US",
    "sg:address":"106 E Yandell Dr",
    "sg:city":"El Paso",
    "sg:classifiers":[
        {
            "category":"Organizations",
            "subcategory":"Non-profit Organization",
            "type":"Services"
        }
    ],
    "sg:phone":"+1 915 544 4041",
    "sg:postcode":"79902",
    "sg:province":"TX",
    "wof:name":"Las Americas Immigrant Ctr",
    "wof:placetype":"venue"
},
  "geometry": {"coordinates":[-106.490993,31.763098],"type":"Point"}
}