{
  "type": "Feature",
  "properties": {
    "iso:country":"US",
    "sg:address":"8817 Dyer St",
    "sg:city":"El Paso",
    "sg:classifiers":[
        {
            "category":"Retail",
            "subcategory":"Funeral Services",
            "type":"Services"
        }
    ],
    "sg:phone":"+1 915 532 3431",
    "sg:postcode":"79904",
    "sg:province":"TX",
    "sg:tags":[
        "home"
    ],
    "wof:name":"SCI",
    "wof:placetype":"venue"
},
  "geometry": {"coordinates":[-106.43315699999999,31.862515],"type":"Point"}
}