{
  "type": "Feature",
  "properties": {
    "iso:country":"US",
    "sg:address":"123 Grapeland Ave",
    "sg:city":"San Antonio",
    "sg:classifiers":[
        {
            "category":"Manufacturing",
            "subcategory":"Building Materials",
            "type":"Manufacturing & Wholesale Goods"
        }
    ],
    "sg:phone":"+1 210 924 5690",
    "sg:postcode":"78214",
    "sg:province":"TX",
    "sg:tags":[
        "mfg",
        "wood",
        "kitchen",
        "cabinet"
    ],
    "wof:name":"Crl Cabinet Work",
    "wof:placetype":"venue"
},
  "geometry": {"coordinates":[-98.502343,29.367833],"type":"Point"}
}