{
  "type": "Feature",
  "properties": {
    "iso:country":"US",
    "sg:address":"949 US Hwy 90",
    "sg:city":"Columbus",
    "sg:classifiers":[
        {
            "category":"Organizations",
            "subcategory":"Non-profit Organization",
            "type":"Services"
        }
    ],
    "sg:phone":"+1 979 732 6991",
    "sg:postcode":"78934",
    "sg:province":"TX",
    "sg:tags":[
        "program",
        "prevention",
        "crime"
    ],
    "wof:name":"Columbus Crime Stoppers",
    "wof:placetype":"venue"
},
  "geometry": {"coordinates":[-96.573476,29.704027],"type":"Point"}
}