{
  "type": "Feature",
  "properties": {
    "iso:country":"US",
    "sg:address":"221 Bonham St",
    "sg:city":"Paris",
    "sg:classifiers":[
        {
            "category":"Shopping",
            "subcategory":"Used Merchandise",
            "type":"Retail Goods"
        }
    ],
    "sg:phone":"+1 903 783 1656",
    "sg:postcode":"75460",
    "sg:province":"TX",
    "sg:tags":[
        "junk"
    ],
    "wof:name":"Junktique",
    "wof:placetype":"venue"
},
  "geometry": {"coordinates":[-95.558673,33.661383],"type":"Point"}
}