{
  "type": "Feature",
  "properties": {
    "iso:country":"US",
    "sg:address":"13710 Judson Rd",
    "sg:city":"San Antonio",
    "sg:classifiers":[
        {
            "category":"Retail",
            "subcategory":"Auto Repair",
            "type":"Services"
        }
    ],
    "sg:phone":"+1 210 655 5086",
    "sg:postcode":"78233",
    "sg:province":"TX",
    "sg:tags":[
        "repairing",
        "automobile"
    ],
    "wof:name":"Vokstoy Blanco Rd",
    "wof:placetype":"venue"
},
  "geometry": {"coordinates":[-98.363646,29.564998],"type":"Point"}
}