{
  "type": "Feature",
  "properties": {
    "iso:country":"US",
    "sg:address":"1181 S Stemmons Fwy",
    "sg:city":"Lewisville",
    "sg:classifiers":[
        {
            "category":"Restaurant",
            "type":"Food & Drink"
        }
    ],
    "sg:phone":"+1 972 436 0566",
    "sg:postcode":"75067",
    "sg:province":"TX",
    "sg:tags":[
        "eating"
    ],
    "wof:name":"Waffle House",
    "wof:placetype":"venue"
},
  "geometry": {"coordinates":[-96.993253,33.029371],"type":"Point"}
}