{
  "type": "Feature",
  "properties": {
    "iso:country":"US",
    "sg:address":"8900 Manchaca Road",
    "sg:city":"Austin",
    "sg:classifiers":[
        {
            "category":"Organizations",
            "subcategory":"Religious Organization",
            "type":"Services"
        }
    ],
    "sg:phone":"+1 512 282 2438",
    "sg:postcode":"78748",
    "sg:province":"TX",
    "wof:name":"Church of Christ Southwest",
    "wof:placetype":"venue"
},
  "geometry": {"coordinates":[-97.817859,30.183329],"type":"Point"}
}