{
  "type": "Feature",
  "properties": {
    "iso:country":"US",
    "sg:address":"1712 Wyoming Ave",
    "sg:city":"El Paso",
    "sg:classifiers":[
        {
            "category":"Building & Trades",
            "subcategory":"Construction",
            "type":"Services"
        }
    ],
    "sg:phone":"+1 915 351 8771",
    "sg:postcode":"79902",
    "sg:province":"TX",
    "sg:tags":[
        "contractor"
    ],
    "wof:name":"Technical Building Svc",
    "wof:placetype":"venue"
},
  "geometry": {"coordinates":[-106.47398800000001,31.772887],"type":"Point"}
}