{
  "type": "Feature",
  "properties": {
    "iso:country":"US",
    "sg:address":"7120 Tram Rd",
    "sg:city":"Beaumont",
    "sg:classifiers":[
        {
            "category":"Shopping Center",
            "type":"Public Place"
        }
    ],
    "sg:phone":"+1 409 899 9346",
    "sg:postcode":"77713",
    "sg:province":"TX",
    "sg:tags":[
        "flea",
        "market"
    ],
    "wof:name":"Tram Road Flea Market",
    "wof:placetype":"venue"
},
  "geometry": {"coordinates":[-94.186876,30.170821],"type":"Point"}
}