{
  "type": "Feature",
  "properties": {
    "iso:country":"US",
    "sg:address":"750 N Riverfront Blvd",
    "sg:city":"Dallas",
    "sg:classifiers":[
        {
            "category":"Food & Beverages",
            "subcategory":"Groceries & Convenience Stores",
            "type":"Retail Goods"
        }
    ],
    "sg:phone":"+1 214 752 4942",
    "sg:postcode":"75207",
    "sg:province":"TX",
    "wof:name":"Exxon Tigermarket 63291",
    "wof:placetype":"venue"
},
  "geometry": {"coordinates":[-96.81529,32.783475],"type":"Point"}
}