{
  "type": "Feature",
  "properties": {
    "iso:country":"US",
    "sg:address":"3159 Denton Hwy",
    "sg:city":"Haltom City",
    "sg:classifiers":[
        {
            "category":"Shopping",
            "subcategory":"Tobacco",
            "type":"Retail Goods"
        }
    ],
    "sg:phone":"+1 817 759 0800",
    "sg:postcode":"76117",
    "sg:province":"TX",
    "sg:tags":[
        "shop",
        "smoke",
        "supply"
    ],
    "wof:name":"Smoke City",
    "wof:placetype":"venue"
},
  "geometry": {"coordinates":[-97.264584,32.805163],"type":"Point"}
}