{
  "type": "Feature",
  "properties": {
    "iso:country":"US",
    "sg:address":"1517 Coronado Ave",
    "sg:city":"Odessa",
    "sg:classifiers":[
        {
            "category":"Building & Trades",
            "subcategory":"Construction",
            "type":"Services"
        }
    ],
    "sg:phone":"+1 432 580 0300",
    "sg:postcode":"79763",
    "sg:province":"TX",
    "sg:tags":[
        "home",
        "improvement"
    ],
    "wof:name":"CCH Home Svc",
    "wof:placetype":"venue"
},
  "geometry": {"coordinates":[-102.40601599999999,31.847233],"type":"Point"}
}