{
  "type": "Feature",
  "properties": {
    "iso:country":"US",
    "sg:address":"6280 Mc Neil Dr",
    "sg:city":"Austin",
    "sg:classifiers":[
        {
            "category":"Professional",
            "subcategory":"Business Services",
            "type":"Services"
        }
    ],
    "sg:phone":"+1 512 258 3212",
    "sg:postcode":"78729",
    "sg:province":"TX",
    "wof:name":"Mahaffey Design Co",
    "wof:placetype":"venue"
},
  "geometry": {"coordinates":[-97.74961,30.441274],"type":"Point"}
}