{
  "type": "Feature",
  "properties": {
    "iso:country":"US",
    "sg:address":"5 Tanager Trl",
    "sg:city":"Spring",
    "sg:classifiers":[
        {
            "category":"Personal",
            "subcategory":"Beauty Salon",
            "type":"Services"
        }
    ],
    "sg:phone":"+1 281 364 1859",
    "sg:postcode":"77381",
    "sg:province":"TX",
    "wof:name":"Defining Moment Aviation",
    "wof:placetype":"venue"
},
  "geometry": {"coordinates":[-95.495138,30.184362],"type":"Point"}
}