{
  "type": "Feature",
  "properties": {
    "iso:country":"US",
    "sg:address":"340 Garden Oaks Blvd",
    "sg:city":"Houston",
    "sg:classifiers":[
        {
            "category":"Wholesale",
            "subcategory":"Electrical",
            "type":"Manufacturing & Wholesale Goods"
        }
    ],
    "sg:phone":"+1 713 699 2000",
    "sg:postcode":"77018",
    "sg:province":"TX",
    "sg:tags":[
        "cable"
    ],
    "wof:name":"Atlantic Cable International",
    "wof:placetype":"venue"
},
  "geometry": {"coordinates":[-95.40524499999999,29.827799],"type":"Point"}
}