{
  "type": "Feature",
  "properties": {
    "iso:country":"US",
    "sg:address":"3225 Jane Ln",
    "sg:city":"Fort Worth",
    "sg:classifiers":[
        {
            "category":"Retail",
            "subcategory":"Repair Shop",
            "type":"Services"
        },
        {
            "category":"Building & Trades",
            "subcategory":"Construction",
            "type":"Services"
        }
    ],
    "sg:phone":"+1 817 834 6911",
    "sg:postcode":"76117",
    "sg:province":"TX",
    "sg:tags":[
        "woodworker"
    ],
    "wof:name":"Little Red Barn",
    "wof:placetype":"venue"
},
  "geometry": {"coordinates":[-97.268959,32.809414],"type":"Point"}
}