{
  "type": "Feature",
  "properties": {
    "iso:country":"US",
    "sg:address":"6806 Long Point Rd",
    "sg:city":"Houston",
    "sg:classifiers":[
        {
            "category":"Travel",
            "subcategory":"Travel Agent",
            "type":"Entertainment"
        }
    ],
    "sg:phone":"+1 713 681 0304",
    "sg:postcode":"77055",
    "sg:province":"TX",
    "sg:tags":[
        "agency",
        "bureau"
    ],
    "wof:name":"Marina Tours & Travel",
    "wof:placetype":"venue"
},
  "geometry": {"coordinates":[-95.46961400000001,29.802973],"type":"Point"}
}