{
  "type": "Feature",
  "properties": {
    "iso:country":"US",
    "sg:address":"107 N Hughes St",
    "sg:city":"Amarillo",
    "sg:classifiers":[
        {
            "category":"Organizations",
            "subcategory":"Non-profit Organization",
            "type":"Services"
        }
    ],
    "sg:phone":"+1 806 373 2740",
    "sg:postcode":"79107",
    "sg:province":"TX",
    "sg:tags":[
        "information",
        "alcoholism",
        "treatment"
    ],
    "wof:name":"Alcoholics Anonymous",
    "wof:placetype":"venue"
},
  "geometry": {"coordinates":[-101.84847499999999,35.21566],"type":"Point"}
}