{
  "type": "Feature",
  "properties": {
    "iso:country":"US",
    "sg:address":"1108 E Broadway St",
    "sg:city":"Sweetwater",
    "sg:classifiers":[
        {
            "category":"Wholesale",
            "subcategory":"Medical Equipment & Supplies",
            "type":"Manufacturing & Wholesale Goods"
        }
    ],
    "sg:phone":"+1 325 235 9001",
    "sg:postcode":"79556",
    "sg:province":"TX",
    "sg:tags":[
        "physician",
        "surgeon"
    ],
    "wof:name":"McGlothlin Medical Supply & Un",
    "wof:placetype":"venue"
},
  "geometry": {"coordinates":[-100.39465800000001,32.476328],"type":"Point"}
}