{
  "type": "Feature",
  "properties": {
    "iso:country":"US",
    "sg:address":"2125 Brandon Dr",
    "sg:city":"Tyler",
    "sg:classifiers":[
        {
            "category":"Freight",
            "type":"Transportation"
        }
    ],
    "sg:phone":"+1 903 561 7313",
    "sg:postcode":"75703",
    "sg:province":"TX",
    "sg:tags":[
        "commercial",
        "storage"
    ],
    "wof:name":"AAA Self Storage",
    "wof:placetype":"venue"
},
  "geometry": {"coordinates":[-95.275243,32.266546],"type":"Point"}
}