{
  "type": "Feature",
  "properties": {
    "iso:country":"US",
    "sg:address":"3045 Nora St",
    "sg:city":"Beaumont",
    "sg:classifiers":[
        {
            "category":"Retail",
            "subcategory":"Animal Services",
            "type":"Services"
        }
    ],
    "sg:phone":"+1 409 840 9820",
    "sg:postcode":"77705",
    "sg:province":"TX",
    "sg:tags":[
        "pet",
        "boarding",
        "sitting"
    ],
    "wof:name":"Shug's Kennel & Pet Svc",
    "wof:placetype":"venue"
},
  "geometry": {"coordinates":[-94.116321,30.047137],"type":"Point"}
}