{
  "type": "Feature",
  "properties": {
    "iso:country":"US",
    "sg:address":"1303 Castroville Rd",
    "sg:city":"San Antonio",
    "sg:classifiers":[
        {
            "category":"Wholesale",
            "subcategory":"Medical Equipment & Supplies",
            "type":"Manufacturing & Wholesale Goods"
        }
    ],
    "sg:phone":"+1 210 433 3100",
    "sg:postcode":"78237",
    "sg:province":"TX",
    "wof:name":"Ruby Medical Equipment and Sup",
    "wof:placetype":"venue"
},
  "geometry": {"coordinates":[-98.559208,29.415489],"type":"Point"}
}