{
  "type": "Feature",
  "properties": {
    "iso:country":"US",
    "sg:address":"3010 E Red River St",
    "sg:city":"Victoria",
    "sg:classifiers":[
        {
            "category":"Personal",
            "subcategory":"Beauty Salon",
            "type":"Services"
        }
    ],
    "sg:phone":"+1 361 575 4911",
    "sg:postcode":"77901",
    "sg:province":"TX",
    "sg:tags":[
        "shop",
        "barber"
    ],
    "wof:name":"Charm Beauty Salon",
    "wof:placetype":"venue"
},
  "geometry": {"coordinates":[-96.97281,28.815199],"type":"Point"}
}