{
  "type": "Feature",
  "properties": {
    "iso:country":"US",
    "sg:address":"2033 W Beauregard Ave",
    "sg:city":"San Angelo",
    "sg:classifiers":[
        {
            "category":"Professional",
            "type":"Services"
        }
    ],
    "sg:phone":"+1 325 949 7974",
    "sg:postcode":"76901",
    "sg:province":"TX",
    "sg:tags":[
        "establishment"
    ],
    "wof:name":"Success By 6",
    "wof:placetype":"venue"
},
  "geometry": {"coordinates":[-100.463362,31.45165],"type":"Point"}
}