{
  "type": "Feature",
  "properties": {
    "iso:country":"US",
    "sg:address":"7905 Aqua Vista Dr",
    "sg:city":"Plano",
    "sg:classifiers":[
        {
            "category":"Home & Garden",
            "subcategory":"Home Furnishings",
            "type":"Retail Goods"
        }
    ],
    "sg:phone":"+1 972 618 2291",
    "sg:postcode":"75025",
    "sg:province":"TX",
    "sg:tags":[
        "blanket"
    ],
    "wof:name":"Victoria's Quilts",
    "wof:placetype":"venue"
},
  "geometry": {"coordinates":[-96.756576,33.083791],"type":"Point"}
}