{
  "type": "Feature",
  "properties": {
    "iso:country":"US",
    "sg:address":"13760 Noel Rd Ste 236",
    "sg:city":"Dallas",
    "sg:classifiers":[
        {
            "category":"Utilities",
            "type":"Services"
        },
        {
            "category":"Professional",
            "subcategory":"Computer Services",
            "type":"Services"
        }
    ],
    "sg:phone":"+1 972 866 9580",
    "sg:postcode":"75240",
    "sg:province":"TX",
    "sg:tags":[
        "repair",
        "provider",
        "internet"
    ],
    "wof:name":"Aspware Communications",
    "wof:placetype":"venue"
},
  "geometry": {"coordinates":[-96.817902,32.9342],"type":"Point"}
}