{
  "type": "Feature",
  "properties": {
    "iso:country":"US",
    "sg:address":"2443 FM 1092",
    "sg:city":"Missouri City",
    "sg:classifiers":[
        {
            "category":"Social Services",
            "type":"Services"
        }
    ],
    "sg:phone":"+1 281 403 9048",
    "sg:postcode":"77459",
    "sg:province":"TX",
    "sg:tags":[
        "youth",
        "organization",
        "center"
    ],
    "wof:name":"Quail Valley Youth Ctr",
    "wof:placetype":"venue"
},
  "geometry": {"coordinates":[-95.564004,29.58366],"type":"Point"}
}