{
  "type": "Feature",
  "properties": {
    "iso:country":"US",
    "sg:address":"8001 Broadway",
    "sg:city":"San Antonio",
    "sg:classifiers":[
        {
            "category":"Professional",
            "type":"Services"
        }
    ],
    "sg:phone":"+1 210 829 5440",
    "sg:postcode":"78209",
    "sg:province":"TX",
    "wof:name":"Oh Susannah",
    "wof:placetype":"venue"
},
  "geometry": {"coordinates":[-98.466213,29.509726],"type":"Point"}
}