{
  "type": "Feature",
  "properties": {
    "iso:country":"US",
    "sg:address":"320 W Airport Fwy",
    "sg:city":"Irving",
    "sg:classifiers":[
        {
            "category":"Insurance",
            "subcategory":"Insurance Agent",
            "type":"Services"
        }
    ],
    "sg:phone":"+1 972 579 0987",
    "sg:postcode":"75062",
    "sg:province":"TX",
    "wof:name":"State Farm Insurance",
    "wof:placetype":"venue"
},
  "geometry": {"coordinates":[-96.949513,32.836567],"type":"Point"}
}