{
  "type": "Feature",
  "properties": {
    "iso:country":"US",
    "sg:address":"1411 US Hwy 90 Alt",
    "sg:city":"Sealy",
    "sg:classifiers":[
        {
            "category":"Health Services",
            "subcategory":"Doctor",
            "type":"Services"
        }
    ],
    "sg:phone":"+1 979 885 7466",
    "sg:postcode":"77434",
    "sg:province":"TX",
    "sg:tags":[
        "clinic"
    ],
    "wof:name":"Brazos Valley Medical Clinic",
    "wof:placetype":"venue"
},
  "geometry": {"coordinates":[-96.32370299999999,29.579615],"type":"Point"}
}