{
  "type": "Feature",
  "properties": {
    "iso:country":"US",
    "sg:address":"212 W Spring Valley Rd",
    "sg:city":"Richardson",
    "sg:classifiers":[
        {
            "category":"Wholesale",
            "subcategory":"Computers",
            "type":"Manufacturing & Wholesale Goods"
        }
    ],
    "sg:phone":"+1 972 644 1992",
    "sg:postcode":"75081",
    "sg:province":"TX",
    "wof:name":"Preferred Computer Systems",
    "wof:placetype":"venue"
},
  "geometry": {"coordinates":[-96.7407,32.940201],"type":"Point"}
}