{
  "type": "Feature",
  "properties": {
    "iso:country":"US",
    "sg:address":"301 S Polk St",
    "sg:city":"Amarillo",
    "sg:classifiers":[
        {
            "category":"Professional",
            "subcategory":"Management & Consulting",
            "type":"Services"
        }
    ],
    "sg:phone":"+1 806 371 9595",
    "sg:postcode":"79101",
    "sg:province":"AR",
    "sg:tags":[
        "consultant",
        "energy",
        "conservation"
    ],
    "wof:name":"RIO Technical Svc Inc",
    "wof:placetype":"venue"
},
  "geometry": {"coordinates":[-101.83654300000001,35.209661],"type":"Point"}
}