{
  "type": "Feature",
  "properties": {
    "iso:country":"US",
    "sg:address":"1521 Ammons St",
    "sg:city":"South Houston",
    "sg:classifiers":[
        {
            "category":"Organizations",
            "subcategory":"Religious Organization",
            "type":"Services"
        }
    ],
    "sg:phone":"+1 281 487 3293",
    "sg:postcode":"77587",
    "sg:province":"TX",
    "sg:tags":[
        "church"
    ],
    "wof:name":"Faith Memorial Baptist Church",
    "wof:placetype":"venue"
},
  "geometry": {"coordinates":[-95.210106,29.668045],"type":"Point"}
}