{
  "type": "Feature",
  "properties": {
    "iso:country":"US",
    "sg:address":"115 Oak Haven Dr",
    "sg:city":"Round Rock",
    "sg:classifiers":[
        {
            "category":"Organizations",
            "subcategory":"Religious Organization",
            "type":"Services"
        }
    ],
    "sg:phone":"+1 512 671 9466",
    "sg:postcode":"78681",
    "sg:province":"TX",
    "wof:name":"Life Church",
    "wof:placetype":"venue"
},
  "geometry": {"coordinates":[-97.719465,30.508082],"type":"Point"}
}