{
  "type": "Feature",
  "properties": {
    "iso:country":"US",
    "sg:address":"400 S Record St",
    "sg:city":"Dallas",
    "sg:classifiers":[
        {
            "category":"Manufacturing",
            "subcategory":"Printing",
            "type":"Manufacturing & Wholesale Goods"
        }
    ],
    "sg:phone":"+1 214 747 5995",
    "sg:postcode":"75202",
    "sg:province":"TX",
    "sg:tags":[
        "newspaper"
    ],
    "wof:name":"Houston Chronicle",
    "wof:placetype":"venue"
},
  "geometry": {"coordinates":[-96.80608599999999,32.776013],"type":"Point"}
}