{
  "type": "Feature",
  "properties": {
    "iso:country":"US",
    "sg:address":"3604 Asset St",
    "sg:city":"Garland",
    "sg:classifiers":[
        {
            "category":"Professional",
            "subcategory":"Business Services",
            "type":"Services"
        }
    ],
    "sg:phone":"+1 214 221 4492",
    "sg:postcode":"75042",
    "sg:province":"TX",
    "sg:tags":[
        "engraver"
    ],
    "wof:name":"Aragon Graphics & Screen Ptg",
    "wof:placetype":"venue"
},
  "geometry": {"coordinates":[-96.684488,32.895881],"type":"Point"}
}