{
  "type": "Feature",
  "properties": {
    "iso:country":"US",
    "sg:address":"856 W Price Rd",
    "sg:city":"Brownsville",
    "sg:classifiers":[
        {
            "category":"Social Services",
            "subcategory":"Child Care",
            "type":"Services"
        },
        {
            "category":"Health Services",
            "subcategory":"Health Practitioner",
            "type":"Services"
        }
    ],
    "sg:phone":"+1 956 504 2200",
    "sg:postcode":"78520",
    "sg:province":"TX",
    "sg:tags":[
        "pathologist",
        "speech",
        "day"
    ],
    "wof:name":"Valley Spech Language Lrng Ctr",
    "wof:placetype":"venue"
},
  "geometry": {"coordinates":[-97.50868,25.937246],"type":"Point"}
}