{
  "type": "Feature",
  "properties": {
    "iso:country":"US",
    "sg:address":"213 Sharpstown Center",
    "sg:city":"Houston",
    "sg:classifiers":[
        {
            "category":"Shopping",
            "subcategory":"Clothing, Apparel, & Fashions",
            "type":"Retail Goods"
        }
    ],
    "sg:phone":"+1 713 772 9076",
    "sg:postcode":"77036",
    "sg:province":"TX",
    "sg:tags":[
        "furnishing"
    ],
    "wof:name":"Georgio's Of Houston",
    "wof:placetype":"venue"
},
  "geometry": {"coordinates":[-95.516796,29.705401],"type":"Point"}
}