{
  "type": "Feature",
  "properties": {
    "iso:country":"US",
    "sg:address":"3104 Indiana Ave",
    "sg:city":"Lubbock",
    "sg:classifiers":[
        {
            "category":"Health Services",
            "subcategory":"Chiropractor",
            "type":"Services"
        },
        {
            "category":"Health Services",
            "subcategory":"Doctor",
            "type":"Services"
        }
    ],
    "sg:phone":"+1 806 785 6550",
    "sg:postcode":"79410",
    "sg:province":"TX",
    "sg:tags":[
        "clinic"
    ],
    "wof:name":"Absolute Body Chiropractic",
    "wof:placetype":"venue"
},
  "geometry": {"coordinates":[-101.88804,33.565131],"type":"Point"}
}