{
  "type": "Feature",
  "properties": {
    "iso:country":"US",
    "sg:address":"212 S Friendswood Dr",
    "sg:city":"Friendswood",
    "sg:classifiers":[
        {
            "category":"Personal",
            "subcategory":"Beauty Salon",
            "type":"Services"
        }
    ],
    "sg:phone":"+1 281 992 8830",
    "sg:postcode":"77546",
    "sg:province":"TX",
    "sg:tags":[
        "shop",
        "manicuring"
    ],
    "wof:name":"C Nails",
    "wof:placetype":"venue"
},
  "geometry": {"coordinates":[-95.204382,29.532101],"type":"Point"}
}