{
  "type": "Feature",
  "properties": {
    "iso:country":"US",
    "sg:address":"800 Wilcrest Dr",
    "sg:city":"Houston",
    "sg:classifiers":[
        {
            "category":"Professional",
            "subcategory":"Employment Agencies",
            "type":"Services"
        }
    ],
    "sg:phone":"+1 281 759 1982",
    "sg:postcode":"77042",
    "sg:province":"TX",
    "sg:tags":[
        "consultant",
        "search",
        "executive"
    ],
    "wof:name":"Executives At The Top",
    "wof:placetype":"venue"
},
  "geometry": {"coordinates":[-95.576364,29.757645],"type":"Point"}
}