{
  "type": "Feature",
  "properties": {
    "iso:country":"US",
    "sg:address":"9364 Co Rd 628",
    "sg:city":"Brazoria",
    "sg:classifiers":[
        {
            "category":"Building & Trades",
            "subcategory":"Construction",
            "type":"Services"
        }
    ],
    "sg:phone":"+1 979 798 8794",
    "sg:postcode":"77422",
    "sg:province":"TX",
    "sg:tags":[
        "general",
        "contractor"
    ],
    "wof:name":"SFR Welboan Construction",
    "wof:placetype":"venue"
},
  "geometry": {"coordinates":[-95.644999,28.968819],"type":"Point"}
}