{
  "type": "Feature",
  "properties": {
    "iso:country":"US",
    "sg:address":"12640 E Northwest Hwy",
    "sg:city":"Dallas",
    "sg:classifiers":[
        {
            "category":"Building & Trades",
            "subcategory":"Construction",
            "type":"Services"
        }
    ],
    "sg:phone":"+1 903 682 7592",
    "sg:postcode":"75228",
    "sg:province":"TX",
    "sg:tags":[
        "house"
    ],
    "wof:name":"Gillispie Custom Homes",
    "wof:placetype":"venue"
},
  "geometry": {"coordinates":[-96.662499,32.863955],"type":"Point"}
}