{
  "type": "Feature",
  "properties": {
    "iso:country":"US",
    "sg:address":"518 N Main St",
    "sg:city":"Donna",
    "sg:classifiers":[
        {
            "category":"Shopping",
            "subcategory":"Gifts & Souvenirs",
            "type":"Retail Goods"
        }
    ],
    "sg:phone":"+1 956 464 0992",
    "sg:postcode":"78537",
    "sg:province":"TX",
    "wof:name":"Smashmouth Sports",
    "wof:placetype":"venue"
},
  "geometry": {"coordinates":[-98.05298999999999,26.177617],"type":"Point"}
}