{
  "type": "Feature",
  "properties": {
    "iso:country":"US",
    "sg:address":"7903 Pettitt St",
    "sg:city":"Amarillo",
    "sg:classifiers":[
        {
            "category":"Shopping",
            "subcategory":"Bicycles & Sporting Goods",
            "type":"Retail Goods"
        }
    ],
    "sg:phone":"+1 806 381 8884",
    "sg:postcode":"79108",
    "sg:province":"TX",
    "wof:name":"Harris Firearms & Supplies",
    "wof:placetype":"venue"
},
  "geometry": {"coordinates":[-101.77177,35.282845],"type":"Point"}
}