{
  "type": "Feature",
  "properties": {
    "iso:country":"US",
    "sg:address":"9017 Westfield Dr",
    "sg:city":"Rowlett",
    "sg:classifiers":[
        {
            "category":"Shopping",
            "subcategory":"Gifts & Souvenirs",
            "type":"Retail Goods"
        }
    ],
    "sg:phone":"+1 972 475 4310",
    "sg:postcode":"75088",
    "sg:province":"TX",
    "wof:name":"Rockwall Gifts",
    "wof:placetype":"venue"
},
  "geometry": {"coordinates":[-96.51340500000001,32.911661],"type":"Point"}
}