{
  "type": "Feature",
  "properties": {
    "iso:country":"US",
    "sg:address":"303 Arthur Dr",
    "sg:city":"Kennedale",
    "sg:classifiers":[
        {
            "category":"Autos & Motor Vehicles",
            "subcategory":"Auto Supplies",
            "type":"Retail Goods"
        }
    ],
    "sg:phone":"+1 817 478 3738",
    "sg:postcode":"76060",
    "sg:province":"TX",
    "wof:name":"Watson Automotive",
    "wof:placetype":"venue"
},
  "geometry": {"coordinates":[-97.223204,32.654141],"type":"Point"}
}