{
  "type": "Feature",
  "properties": {
    "iso:country":"US",
    "sg:address":"7418 Village Lake Dr",
    "sg:city":"Cypress",
    "sg:classifiers":[
        {
            "category":"Food & Beverages",
            "subcategory":"Bakery",
            "type":"Retail Goods"
        }
    ],
    "sg:phone":"+1 281 687 0581",
    "sg:postcode":"77433",
    "sg:province":"TX",
    "sg:tags":[
        "baker"
    ],
    "sg:website":"www.cakesbymelanie.com",
    "wof:name":"Cakes By Melanie",
    "wof:placetype":"venue"
},
  "geometry": {"coordinates":[-95.712834,29.88634],"type":"Point"}
}