{
  "type": "Feature",
  "properties": {
    "iso:country":"US",
    "sg:address":"8371 Co Rd 219",
    "sg:city":"Tyler",
    "sg:classifiers":[
        {
            "category":"Shopping",
            "type":"Retail Goods"
        },
        {
            "category":"Retail",
            "subcategory":"Animal Services",
            "type":"Services"
        }
    ],
    "sg:phone":"+1 903 566 1260",
    "sg:postcode":"75707",
    "sg:province":"TX",
    "sg:tags":[
        "pet",
        "shop"
    ],
    "wof:name":"R & R Farm Kennel",
    "wof:placetype":"venue"
},
  "geometry": {"coordinates":[-95.235766,32.324446],"type":"Point"}
}