{
  "type": "Feature",
  "properties": {
    "iso:country":"US",
    "sg:address":"7 Arapaho Village Center",
    "sg:city":"Richardson",
    "sg:classifiers":[
        {
            "category":"Personal",
            "type":"Services"
        }
    ],
    "sg:phone":"+1 972 479 0690",
    "sg:postcode":"75080",
    "sg:province":"TX",
    "wof:name":"Therapeutic Massage",
    "wof:placetype":"venue"
},
  "geometry": {"coordinates":[-96.749205,32.961786],"type":"Point"}
}