{
  "type": "Feature",
  "properties": {
    "iso:country":"US",
    "sg:address":"1012 E Main St",
    "sg:city":"Brenham",
    "sg:classifiers":[
        {
            "category":"Organizations",
            "subcategory":"Religious Organization",
            "type":"Services"
        }
    ],
    "sg:phone":"+1 979 836 4156",
    "sg:postcode":"77833",
    "sg:province":"TX",
    "sg:tags":[
        "place",
        "worship",
        "church"
    ],
    "wof:name":"St. John Ame Church",
    "wof:placetype":"venue"
},
  "geometry": {"coordinates":[-96.389505,30.169141],"type":"Point"}
}