{
  "type": "Feature",
  "properties": {
    "iso:country":"US",
    "sg:address":"1111 E 12th St",
    "sg:city":"Big Lake",
    "sg:classifiers":[
        {
            "category":"Restaurant",
            "type":"Food & Drink"
        }
    ],
    "sg:phone":"+1 325 884 2757",
    "sg:postcode":"76932",
    "sg:province":"TX",
    "sg:tags":[
        "eating"
    ],
    "wof:name":"Elementary Cafeteria",
    "wof:placetype":"venue"
},
  "geometry": {"coordinates":[-101.453284,31.201249],"type":"Point"}
}