{
  "type": "Feature",
  "properties": {
    "iso:country":"US",
    "sg:address":"3033 Arlington Ave",
    "sg:city":"Abilene",
    "sg:classifiers":[
        {
            "category":"Retail",
            "subcategory":"Laundry & Dry Cleaning",
            "type":"Services"
        }
    ],
    "sg:phone":"+1 325 698 1752",
    "sg:postcode":"79606",
    "sg:province":"TX",
    "wof:name":"Xtreme Carpet Cleaning",
    "wof:placetype":"venue"
},
  "geometry": {"coordinates":[-99.760991,32.390928],"type":"Point"}
}