{
  "type": "Feature",
  "properties": {
    "iso:country":"US",
    "sg:address":"3003 Lyndon B Johnson Fwy",
    "sg:city":"Dallas",
    "sg:classifiers":[
        {
            "category":"Real Estate",
            "subcategory":"Real Estate Services",
            "type":"Services"
        }
    ],
    "sg:phone":"+1 972 481 1246",
    "sg:postcode":"75234",
    "sg:province":"TX",
    "wof:name":"Texas Home Equities",
    "wof:placetype":"venue"
},
  "geometry": {"coordinates":[-96.876999,32.912601],"type":"Point"}
}