{
  "type": "Feature",
  "properties": {
    "iso:country":"US",
    "sg:address":"100 Parkwood Ave",
    "sg:city":"Arlington",
    "sg:classifiers":[
        {
            "category":"Restaurant",
            "type":"Food & Drink"
        }
    ],
    "sg:phone":"+1 817 366 7786",
    "sg:postcode":"76013",
    "sg:province":"TX",
    "sg:tags":[
        "cake",
        "catering"
    ],
    "wof:name":"Jans Goodies",
    "wof:placetype":"venue"
},
  "geometry": {"coordinates":[-97.12911,32.728932],"type":"Point"}
}