{
  "type": "Feature",
  "properties": {
    "iso:country":"US",
    "sg:address":"10902 Scarsdale Blvd",
    "sg:city":"Houston",
    "sg:classifiers":[
        {
            "category":"Shopping",
            "subcategory":"Mobile Phones",
            "type":"Retail Goods"
        }
    ],
    "sg:phone":"+1 281 922 4100",
    "sg:postcode":"77089",
    "sg:province":"TX",
    "wof:name":"EZ Wireless",
    "wof:placetype":"venue"
},
  "geometry": {"coordinates":[-95.21211099999999,29.58571],"type":"Point"}
}