{
  "type": "Feature",
  "properties": {
    "iso:country":"US",
    "sg:address":"3903 Eisenhauer Rd",
    "sg:city":"San Antonio",
    "sg:classifiers":[
        {
            "category":"Professional",
            "type":"Services"
        }
    ],
    "sg:phone":"+1 210 576 0757",
    "sg:postcode":"78218",
    "sg:province":"TX",
    "sg:tags":[
        "establishment"
    ],
    "wof:name":"Smith & Haynes Mgmt",
    "wof:placetype":"venue"
},
  "geometry": {"coordinates":[-98.418446,29.496653],"type":"Point"}
}