{
  "type": "Feature",
  "properties": {
    "iso:country":"US",
    "sg:address":"503 Mckeever Rd Ste 1502",
    "sg:city":"Rosharon",
    "sg:classifiers":[
        {
            "category":"Building & Trades",
            "subcategory":"Equipment Rental",
            "type":"Services"
        }
    ],
    "sg:phone":"+1 281 431 1756",
    "sg:postcode":"77583",
    "sg:province":"TX",
    "sg:tags":[
        "yard",
        "leasing",
        "store"
    ],
    "wof:name":"B D Leasing",
    "wof:placetype":"venue"
},
  "geometry": {"coordinates":[-95.46803300000001,29.507681],"type":"Point"}
}