{
  "type": "Feature",
  "properties": {
    "iso:country":"US",
    "sg:address":"1211 Ave H NW",
    "sg:city":"Childress",
    "sg:classifiers":[
        {
            "category":"Organizations",
            "subcategory":"Religious Organization",
            "type":"Services"
        }
    ],
    "sg:phone":"+1 940 937 2818",
    "sg:postcode":"79201",
    "sg:province":"TX",
    "wof:name":"Harvest Time Church",
    "wof:placetype":"venue"
},
  "geometry": {"coordinates":[-100.216841,34.433252],"type":"Point"}
}