{
  "type": "Feature",
  "properties": {
    "iso:country":"US",
    "sg:address":"7802 Indiana Ave",
    "sg:city":"Lubbock",
    "sg:classifiers":[
        {
            "category":"Real Estate",
            "subcategory":"Real Estate Services",
            "type":"Services"
        }
    ],
    "sg:phone":"+1 806 793 1389",
    "sg:postcode":"79423",
    "sg:province":"TX",
    "sg:tags":[
        "abstract",
        "management",
        "consulting",
        "title"
    ],
    "wof:name":"Stewart Title Co of Lubbock",
    "wof:placetype":"venue"
},
  "geometry": {"coordinates":[-101.88780800000001,33.522839],"type":"Point"}
}