{
  "type": "Feature",
  "properties": {
    "iso:country":"US",
    "sg:address":"4320 E Belknap St",
    "sg:city":"Fort Worth",
    "sg:classifiers":[
        {
            "category":"Manufacturing",
            "subcategory":"Furniture",
            "type":"Manufacturing & Wholesale Goods"
        }
    ],
    "sg:phone":"+1 817 834 6131",
    "sg:postcode":"76117",
    "sg:province":"TX",
    "sg:tags":[
        "venetian",
        "repair",
        "blind",
        "mfg"
    ],
    "wof:name":"C & W Blind & Screen Co Llc",
    "wof:placetype":"venue"
},
  "geometry": {"coordinates":[-97.2826,32.78673],"type":"Point"}
}