{
  "type": "Feature",
  "properties": {
    "iso:country":"US",
    "sg:address":"7670 Gessner Dr",
    "sg:city":"Houston",
    "sg:classifiers":[
        {
            "category":"Food & Beverages",
            "subcategory":"Bakery",
            "type":"Retail Goods"
        }
    ],
    "sg:phone":"+1 713 983 0513",
    "sg:postcode":"77040",
    "sg:province":"TX",
    "sg:tags":[
        "doughnut"
    ],
    "wof:name":"Simply Donuts",
    "wof:placetype":"venue"
},
  "geometry": {"coordinates":[-95.540809,29.884123],"type":"Point"}
}