{
  "type": "Feature",
  "properties": {
    "iso:country":"US",
    "sg:address":"620 Murphy Rd",
    "sg:city":"Stafford",
    "sg:classifiers":[
        {
            "category":"Personal",
            "subcategory":"Barber",
            "type":"Services"
        }
    ],
    "sg:phone":"+1 281 499 4310",
    "sg:postcode":"77477",
    "sg:province":"TX",
    "sg:tags":[
        "shop"
    ],
    "wof:name":"Mr TS Barber Shop",
    "wof:placetype":"venue"
},
  "geometry": {"coordinates":[-95.564542,29.610145],"type":"Point"}
}