{
  "type": "Feature",
  "properties": {
    "iso:country":"US",
    "sg:address":"9540 Casa Linda Plz Ste 381",
    "sg:city":"Dallas",
    "sg:classifiers":[
        {
            "category":"Personal",
            "type":"Services"
        }
    ],
    "sg:phone":"+1 972 203 8003",
    "sg:postcode":"75218",
    "sg:province":"TX",
    "sg:tags":[
        "party",
        "planning",
        "event"
    ],
    "wof:name":"VIP Events",
    "wof:placetype":"venue"
},
  "geometry": {"coordinates":[-96.703883,32.835192],"type":"Point"}
}