{
  "type": "Feature",
  "properties": {
    "iso:country":"US",
    "sg:address":"18759 Candlepark Dr",
    "sg:city":"Spring",
    "sg:classifiers":[
        {
            "category":"Shopping",
            "subcategory":"Bicycles & Sporting Goods",
            "type":"Retail Goods"
        }
    ],
    "sg:phone":"+1 281 350 0794",
    "sg:postcode":"77388",
    "sg:province":"TX",
    "wof:name":"Texas Custom Golf Inc",
    "wof:placetype":"venue"
},
  "geometry": {"coordinates":[-95.449775,30.040471],"type":"Point"}
}