{
  "type": "Feature",
  "properties": {
    "iso:country":"US",
    "sg:address":"11802 Onion Hollow Run",
    "sg:city":"Austin",
    "sg:classifiers":[
        {
            "category":"Shopping",
            "subcategory":"Hobbies, Toys, & Games",
            "type":"Retail Goods"
        }
    ],
    "sg:phone":"+1 512 280 4064",
    "sg:postcode":"78739",
    "sg:province":"TX",
    "wof:name":"Scot Sassy",
    "wof:placetype":"venue"
},
  "geometry": {"coordinates":[-97.863084,30.159822],"type":"Point"}
}