{
  "type": "Feature",
  "properties": {
    "iso:country":"US",
    "sg:address":"616 NE Front St",
    "sg:city":"De Kalb",
    "sg:classifiers":[
        {
            "category":"Utilities",
            "subcategory":"Fuel Oil & Lpg",
            "type":"Services"
        }
    ],
    "sg:phone":"+1 903 684 3333",
    "sg:postcode":"75559",
    "sg:province":"TX",
    "sg:tags":[
        "liquefied",
        "gas",
        "petroleum"
    ],
    "wof:name":"Cooper Propane Co",
    "wof:placetype":"venue"
},
  "geometry": {"coordinates":[-94.611268,33.506275],"type":"Point"}
}