{
  "type": "Feature",
  "properties": {
    "iso:country":"US",
    "sg:address":"302 S Jackson St",
    "sg:city":"Jacksonville",
    "sg:classifiers":[
        {
            "category":"Restaurant",
            "type":"Food & Drink"
        }
    ],
    "sg:menulink":"http://www.allmenus.com/tx/jacksonville/193485-taco-bell/menu/",
    "sg:postcode":"75766",
    "sg:province":"TX",
    "sg:tags":[
        "mexican"
    ],
    "wof:name":"Taco Bell",
    "wof:placetype":"venue"
},
  "geometry": {"coordinates":[-95.270442,31.963422],"type":"Point"}
}