{
  "type": "Feature",
  "properties": {
    "iso:country":"US",
    "sg:address":"3501 Chisholm Trl",
    "sg:city":"Salado",
    "sg:classifiers":[
        {
            "category":"Organizations",
            "subcategory":"Non-profit Organization",
            "type":"Services"
        }
    ],
    "sg:phone":"+1 254 947 9237",
    "sg:postcode":"76571",
    "sg:province":"TX",
    "sg:tags":[
        "fund",
        "raising"
    ],
    "wof:name":"Broadway Consulting Service Inc",
    "wof:placetype":"venue"
},
  "geometry": {"coordinates":[-97.513908,30.95262],"type":"Point"}
}