{
  "type": "Feature",
  "properties": {
    "iso:country":"US",
    "sg:address":"17207 Carllswood St",
    "sg:city":"Baytown",
    "sg:classifiers":[
        {
            "category":"Wholesale",
            "subcategory":"Machinery & Supplies",
            "type":"Manufacturing & Wholesale Goods"
        }
    ],
    "sg:phone":"+1 281 573 3317",
    "sg:postcode":"77520",
    "sg:province":"TX",
    "sg:tags":[
        "equipment",
        "industrial"
    ],
    "wof:name":"Tecon Water Co",
    "wof:placetype":"venue"
},
  "geometry": {"coordinates":[-94.89087499999999,29.778416],"type":"Point"}
}