{
  "type": "Feature",
  "properties": {
    "iso:country":"US",
    "sg:address":"1101 Scott Ave",
    "sg:city":"Wichita Falls",
    "sg:classifiers":[
        {
            "category":"Insurance",
            "subcategory":"Insurance Agent",
            "type":"Services"
        }
    ],
    "sg:phone":"+1 940 766 1312",
    "sg:postcode":"76301",
    "sg:province":"TX",
    "wof:name":"M&L Insurance Services",
    "wof:placetype":"venue"
},
  "geometry": {"coordinates":[-98.48888599999999,33.908006],"type":"Point"}
}