{
  "type": "Feature",
  "properties": {
    "iso:country":"US",
    "sg:address":"611 E Main St",
    "sg:city":"Fredericksburg",
    "sg:classifiers":[
        {
            "category":"Restaurant",
            "type":"Food & Drink"
        }
    ],
    "sg:phone":"+1 830 997 7337",
    "sg:postcode":"78624",
    "sg:province":"TX",
    "sg:tags":[
        "eating"
    ],
    "wof:name":"McDonalds",
    "wof:placetype":"venue"
},
  "geometry": {"coordinates":[-98.863688,30.268875],"type":"Point"}
}