{
  "type": "Feature",
  "properties": {
    "iso:country":"US",
    "sg:address":"18941 Aldine Westfield Rd",
    "sg:city":"Houston",
    "sg:classifiers":[
        {
            "category":"Freight",
            "type":"Transportation"
        },
        {
            "category":"Professional",
            "subcategory":"Business Services",
            "type":"Services"
        }
    ],
    "sg:phone":"+1 281 443 3222",
    "sg:postcode":"77073",
    "sg:province":"TX",
    "sg:tags":[
        "packing",
        "crating"
    ],
    "wof:name":"Houston Crafting Inc",
    "wof:placetype":"venue"
},
  "geometry": {"coordinates":[-95.36461799999999,29.977617],"type":"Point"}
}