{
  "type": "Feature",
  "properties": {
    "iso:country":"US",
    "sg:address":"3701 5th Ave N",
    "sg:city":"Texas City",
    "sg:classifiers":[
        {
            "category":"Wholesale",
            "subcategory":"Machinery & Supplies",
            "type":"Manufacturing & Wholesale Goods"
        },
        {
            "category":"Professional",
            "type":"Services"
        }
    ],
    "sg:phone":"+1 409 945 7565",
    "sg:postcode":"77590",
    "sg:province":"TX",
    "sg:tags":[
        "pressure",
        "tube",
        "establishment",
        "fitting"
    ],
    "wof:name":"Prp International Inc",
    "wof:placetype":"venue"
},
  "geometry": {"coordinates":[-94.95107899999999,29.388083],"type":"Point"}
}