{
  "type": "Feature",
  "properties": {
    "iso:country":"US",
    "sg:address":"15203 Knoll Trail Dr Ste 115",
    "sg:city":"Dallas",
    "sg:classifiers":[
        {
            "category":"Restaurant",
            "type":"Food & Drink"
        }
    ],
    "sg:phone":"+1 972 387 3030",
    "sg:postcode":"75248",
    "sg:province":"TX",
    "sg:tags":[
        "pizza"
    ],
    "sg:website":"www.dominos.com",
    "wof:name":"Domino's Pizza",
    "wof:placetype":"venue"
},
  "geometry": {"coordinates":[-96.796898,32.966999],"type":"Point"}
}