{
  "type": "Feature",
  "properties": {
    "iso:country":"US",
    "sg:address":"2161 Co Rd 163",
    "sg:city":"Kenedy",
    "sg:classifiers":[
        {
            "category":"Farming",
            "subcategory":"Livestock Farm",
            "type":"Manufacturing & Wholesale Goods"
        }
    ],
    "sg:phone":"+1 830 583 9930",
    "sg:postcode":"78119",
    "sg:province":"TX",
    "sg:tags":[
        "beef",
        "feedlot",
        "cattle"
    ],
    "wof:name":"Ot Cattle Co Inc",
    "wof:placetype":"venue"
},
  "geometry": {"coordinates":[-97.881004,28.802237],"type":"Point"}
}