{
  "type": "Feature",
  "properties": {
    "iso:country":"US",
    "sg:address":"507 SE 2nd St",
    "sg:city":"Seminole",
    "sg:classifiers":[
        {
            "category":"Home & Garden",
            "subcategory":"Carpets & Floor Coverings",
            "type":"Retail Goods"
        }
    ],
    "sg:phone":"+1 432 758 3791",
    "sg:postcode":"79360",
    "sg:province":"TX",
    "sg:tags":[
        "dealer",
        "rug"
    ],
    "wof:name":"Jimmy's Carpet",
    "wof:placetype":"venue"
},
  "geometry": {"coordinates":[-102.643698,32.713907],"type":"Point"}
}