{
  "type": "Feature",
  "properties": {
    "iso:country":"US",
    "sg:address":"1604 9th Ave N",
    "sg:city":"Texas City",
    "sg:classifiers":[
        {
            "category":"Organizations",
            "subcategory":"Religious Organization",
            "type":"Services"
        }
    ],
    "sg:phone":"+1 409 948 8448",
    "sg:postcode":"77590",
    "sg:province":"TX",
    "sg:tags":[
        "catholic",
        "church"
    ],
    "sg:website":"www.stmarycctc.org",
    "wof:name":"Saint Marys Catholic Church",
    "wof:placetype":"venue"
},
  "geometry": {"coordinates":[-94.91675499999999,29.393374],"type":"Point"}
}