{
  "type": "Feature",
  "properties": {
    "iso:country":"US",
    "sg:address":"2005 Short Summer Dr",
    "sg:city":"Austin",
    "sg:classifiers":[
        {
            "category":"Social Services",
            "type":"Services"
        },
        {
            "category":"Health Services",
            "subcategory":"Nursing And Care Facility",
            "type":"Services"
        }
    ],
    "sg:phone":"+1 512 836 2900",
    "sg:postcode":"78754",
    "sg:province":"TX",
    "sg:tags":[
        "blind",
        "product",
        "developmentally",
        "disabled",
        "vision",
        "need",
        "impaired",
        "special"
    ],
    "sg:website":"http://www.kewing.com",
    "wof:name":"Kenneth Ewing",
    "wof:placetype":"venue"
},
  "geometry": {"coordinates":[-97.651596,30.372655],"type":"Point"}
}