{
  "type": "Feature",
  "properties": {
    "iso:country":"US",
    "sg:address":"2044 Valley View Dr",
    "sg:city":"Burleson",
    "sg:classifiers":[
        {
            "category":"Structure",
            "subcategory":"Office Building",
            "type":"Public Place"
        }
    ],
    "sg:phone":"+1 817 295 4332",
    "sg:postcode":"76028",
    "sg:province":"TX",
    "sg:tags":[
        "park"
    ],
    "wof:name":"Precision Properties",
    "wof:placetype":"venue"
},
  "geometry": {"coordinates":[-97.304067,32.496052],"type":"Point"}
}