{
  "type": "Feature",
  "properties": {
    "iso:country":"US",
    "sg:address":"4004 S Belt Line Rd",
    "sg:city":"Grand Prairie",
    "sg:classifiers":[
        {
            "category":"Restaurant",
            "type":"Food & Drink"
        }
    ],
    "sg:menulink":"http://www.allmenus.com/tx/southwest/177473-jack-in-the-box/menu/",
    "sg:phone":"+1 972 642 3330",
    "sg:postcode":"75052",
    "sg:province":"TX",
    "sg:tags":[
        "burger",
        "american"
    ],
    "wof:name":"Jack in the Box",
    "wof:placetype":"venue"
},
  "geometry": {"coordinates":[-96.98521599999999,32.673536],"type":"Point"}
}