{
  "type": "Feature",
  "properties": {
    "iso:country":"US",
    "sg:address":"4207 Meadow Ridge Dr",
    "sg:city":"Carrollton",
    "sg:classifiers":[
        {
            "category":"Organizations",
            "subcategory":"Religious Organization",
            "type":"Services"
        }
    ],
    "sg:phone":"+1 972 939 4337",
    "sg:postcode":"75010",
    "sg:province":"TX",
    "wof:name":"Mission Alive",
    "wof:placetype":"venue"
},
  "geometry": {"coordinates":[-96.87857200000001,33.025042],"type":"Point"}
}