{
  "type": "Feature",
  "properties": {
    "iso:country":"US",
    "sg:address":"14426 Bellaire Blvd",
    "sg:city":"Houston",
    "sg:classifiers":[
        {
            "category":"Health Services",
            "subcategory":"Doctor",
            "type":"Services"
        }
    ],
    "sg:phone":"+1 281 530 6868",
    "sg:postcode":"77083",
    "sg:province":"TX",
    "sg:tags":[
        "dentist"
    ],
    "wof:name":"Wayne C Hsu DDS",
    "wof:placetype":"venue"
},
  "geometry": {"coordinates":[-95.640569,29.704071],"type":"Point"}
}