{
  "type": "Feature",
  "properties": {
    "iso:country":"US",
    "sg:address":"711 Oak Park Ave",
    "sg:city":"Corpus Christi",
    "sg:classifiers":[
        {
            "category":"Autos & Motor Vehicles",
            "subcategory":"Auto Supplies",
            "type":"Retail Goods"
        }
    ],
    "sg:phone":"+1 361 888 6338",
    "sg:postcode":"78408",
    "sg:province":"TX",
    "sg:tags":[
        "automobile",
        "parts"
    ],
    "wof:name":"O'Reilly Auto Parts",
    "wof:placetype":"venue"
},
  "geometry": {"coordinates":[-97.435722,27.797992],"type":"Point"}
}