{
  "type": "Feature",
  "properties": {
    "iso:country":"US",
    "sg:address":"15821 East Fwy",
    "sg:city":"Channelview",
    "sg:classifiers":[
        {
            "category":"Shopping",
            "subcategory":"Books",
            "type":"Retail Goods"
        }
    ],
    "sg:phone":"+1 281 452 1509",
    "sg:postcode":"77530",
    "sg:province":"TX",
    "sg:tags":[
        "dealer"
    ],
    "wof:name":"Family Christian Book Store",
    "wof:placetype":"venue"
},
  "geometry": {"coordinates":[-95.12199200000001,29.779187],"type":"Point"}
}