{
  "type": "Feature",
  "properties": {
    "iso:country":"US",
    "sg:address":"2000 Smith St",
    "sg:city":"Houston",
    "sg:classifiers":[
        {
            "category":"Professional",
            "subcategory":"Lawyer & Legal Services",
            "type":"Services"
        }
    ],
    "sg:phone":"+1 713 871 8888",
    "sg:postcode":"77002",
    "sg:province":"TX",
    "sg:tags":[
        "attorney"
    ],
    "wof:name":"Immigration Specialists",
    "wof:placetype":"venue"
},
  "geometry": {"coordinates":[-95.374397,29.7516],"type":"Point"}
}