{
  "type": "Feature",
  "properties": {
    "iso:country":"US",
    "sg:address":"5504 Westgate Dr",
    "sg:city":"Amarillo",
    "sg:classifiers":[
        {
            "category":"Building & Trades",
            "subcategory":"Construction",
            "type":"Services"
        }
    ],
    "sg:phone":"+1 806 359 4155",
    "sg:postcode":"79106",
    "sg:province":"TX",
    "sg:tags":[
        "repairing",
        "remodeling",
        "contractor"
    ],
    "wof:name":"Carnes & Co",
    "wof:placetype":"venue"
},
  "geometry": {"coordinates":[-101.901381,35.197297],"type":"Point"}
}