{
  "type": "Feature",
  "properties": {
    "iso:country":"US",
    "sg:address":"4611 Magnolia Bend",
    "sg:city":"Missouri City",
    "sg:classifiers":[
        {
            "category":"Professional",
            "subcategory":"Engineering",
            "type":"Services"
        }
    ],
    "sg:phone":"+1 281 208 9042",
    "sg:postcode":"77459",
    "sg:province":"TX",
    "wof:name":"Float Offshore Inc",
    "wof:placetype":"venue"
},
  "geometry": {"coordinates":[-95.569258,29.563099],"type":"Point"}
}