{
  "type": "Feature",
  "properties": {
    "iso:country":"US",
    "sg:address":"3207 S 1st St",
    "sg:city":"Lufkin",
    "sg:classifiers":[
        {
            "category":"Cafe",
            "type":"Food & Drink"
        }
    ],
    "sg:menulink":"http://www.allmenus.com/tx/lufkin/222136-cotton-patch-cafe/menu/",
    "sg:phone":"+1 936 639 4949",
    "sg:postcode":"75901",
    "sg:province":"TX",
    "sg:tags":[
        "burger",
        "american",
        "salad",
        "soup"
    ],
    "wof:name":"Cotton Patch Cafe",
    "wof:placetype":"venue"
},
  "geometry": {"coordinates":[-94.729218,31.2911],"type":"Point"}
}