{
  "type": "Feature",
  "properties": {
    "iso:country":"US",
    "sg:address":"609 Lake Side Cove",
    "sg:city":"Georgetown",
    "sg:classifiers":[
        {
            "category":"Building & Trades",
            "subcategory":"Construction",
            "type":"Services"
        }
    ],
    "sg:phone":"+1 512 864 7979",
    "sg:postcode":"78628",
    "sg:province":"TX",
    "sg:tags":[
        "home",
        "builder"
    ],
    "wof:name":"Zenterra Custom Homes & Design",
    "wof:placetype":"venue"
},
  "geometry": {"coordinates":[-97.799632,30.615929],"type":"Point"}
}