{
  "type": "Feature",
  "properties": {
    "iso:country":"US",
    "sg:address":"617 High Starr Dr",
    "sg:city":"Corpus Christi",
    "sg:classifiers":[
        {
            "category":"Wholesale",
            "subcategory":"Electrical",
            "type":"Manufacturing & Wholesale Goods"
        }
    ],
    "sg:phone":"+1 361 888 4133",
    "sg:postcode":"78408",
    "sg:province":"TX",
    "sg:tags":[
        "repair",
        "electric",
        "motor"
    ],
    "wof:name":"C-D Electric Motor Sales & Svc",
    "wof:placetype":"venue"
},
  "geometry": {"coordinates":[-97.45479,27.797833],"type":"Point"}
}