{
  "type": "Feature",
  "properties": {
    "iso:country":"US",
    "sg:address":"233 Lake Wichita Dr",
    "sg:city":"Wylie",
    "sg:classifiers":[
        {
            "category":"Personal",
            "type":"Services"
        }
    ],
    "sg:phone":"+1 972 442 7813",
    "sg:postcode":"75098",
    "sg:province":"TX",
    "wof:name":"Unique Tan Plus",
    "wof:placetype":"venue"
},
  "geometry": {"coordinates":[-96.53602600000001,32.998813],"type":"Point"}
}