{
  "type": "Feature",
  "properties": {
    "iso:country":"US",
    "sg:address":"1820 Texoma Pkwy",
    "sg:city":"Sherman",
    "sg:classifiers":[
        {
            "category":"Restaurant",
            "type":"Food & Drink"
        }
    ],
    "sg:menulink":"http://www.allmenus.com/tx/east-grayson/204447-sonic/menu/",
    "sg:phone":"+1 903 891 0646",
    "sg:postcode":"75090",
    "sg:province":"TX",
    "sg:tags":[
        "burger",
        "american"
    ],
    "wof:name":"Sonic",
    "wof:placetype":"venue"
},
  "geometry": {"coordinates":[-96.605582,33.655223],"type":"Point"}
}