{
  "type": "Feature",
  "properties": {
    "iso:country":"US",
    "sg:address":"423 S 4th St",
    "sg:city":"Donna",
    "sg:classifiers":[
        {
            "category":"Freight",
            "type":"Transportation"
        }
    ],
    "sg:phone":"+1 956 262 1338",
    "sg:postcode":"78537",
    "sg:province":"TX",
    "sg:tags":[
        "grain",
        "elevator"
    ],
    "wof:name":"Bee Agricultural Co",
    "wof:placetype":"venue"
},
  "geometry": {"coordinates":[-98.06148899999999,26.165913],"type":"Point"}
}