{
  "type": "Feature",
  "properties": {
    "iso:country":"US",
    "sg:address":"5933 Bellaire Blvd",
    "sg:city":"Houston",
    "sg:classifiers":[
        {
            "category":"Manufacturing",
            "subcategory":"Metals",
            "type":"Manufacturing & Wholesale Goods"
        }
    ],
    "sg:phone":"+1 713 218 9121",
    "sg:postcode":"77081",
    "sg:province":"TX",
    "sg:tags":[
        "residential",
        "mfg",
        "door",
        "entry"
    ],
    "wof:name":"Door Stop Cutom Shop",
    "wof:placetype":"venue"
},
  "geometry": {"coordinates":[-95.485277,29.705455],"type":"Point"}
}