{
  "type": "Feature",
  "properties": {
    "iso:country":"US",
    "sg:address":"7205 S Ww White Rd",
    "sg:city":"San Antonio",
    "sg:classifiers":[
        {
            "category":"Manufacturing",
            "subcategory":"Tools & Machinery",
            "type":"Manufacturing & Wholesale Goods"
        }
    ],
    "sg:phone":"+1 210 648 6000",
    "sg:postcode":"78222",
    "sg:province":"TX",
    "sg:tags":[
        "contractor"
    ],
    "wof:name":"Pathfinder Equipment Locators",
    "wof:placetype":"venue"
},
  "geometry": {"coordinates":[-98.39720699999999,29.349177],"type":"Point"}
}