{
  "type": "Feature",
  "properties": {
    "iso:country":"US",
    "sg:address":"13927 Montaigne Dr",
    "sg:city":"Cypress",
    "sg:classifiers":[
        {
            "category":"Building & Trades",
            "subcategory":"Construction",
            "type":"Services"
        }
    ],
    "sg:phone":"+1 281 894 2008",
    "sg:postcode":"77429",
    "sg:province":"TX",
    "sg:tags":[
        "contractor",
        "mechanical"
    ],
    "wof:name":"County Mechanical",
    "wof:placetype":"venue"
},
  "geometry": {"coordinates":[-95.631103,29.936514],"type":"Point"}
}