{
  "type": "Feature",
  "properties": {
    "iso:country":"US",
    "sg:address":"810 Tradesmens Park Loop",
    "sg:city":"Hutto",
    "sg:classifiers":[
        {
            "category":"Manufacturing",
            "subcategory":"Tools & Machinery",
            "type":"Manufacturing & Wholesale Goods"
        }
    ],
    "sg:phone":"+1 512 759 5137",
    "sg:postcode":"78634",
    "sg:province":"TX",
    "sg:tags":[
        "crane",
        "system",
        "weight",
        "mfg"
    ],
    "wof:name":"3ps Services",
    "wof:placetype":"venue"
},
  "geometry": {"coordinates":[-97.591668,30.540759],"type":"Point"}
}