{
  "type": "Feature",
  "properties": {
    "iso:country":"US",
    "sg:address":"201 Stadium Dr",
    "sg:city":"Seymour",
    "sg:classifiers":[
        {
            "category":"Health Services",
            "subcategory":"Clinic",
            "type":"Services"
        },
        {
            "category":"Health Services",
            "subcategory":"Doctor",
            "type":"Services"
        }
    ],
    "sg:phone":"+1 940 889 5583",
    "sg:postcode":"76380",
    "sg:province":"TX",
    "sg:tags":[
        "home"
    ],
    "wof:name":"Seymour Hospital Rural Health",
    "wof:placetype":"venue"
},
  "geometry": {"coordinates":[-99.24705400000001,33.59299],"type":"Point"}
}