{
  "type": "Feature",
  "properties": {
    "iso:country":"US",
    "sg:address":"5618 Wyoming Ave",
    "sg:city":"Odessa",
    "sg:classifiers":[
        {
            "category":"Communications",
            "subcategory":"Film & Video Production",
            "type":"Services"
        }
    ],
    "sg:phone":"+1 432 363 8937",
    "sg:postcode":"79762",
    "sg:province":"TX",
    "sg:tags":[
        "motion",
        "distribution"
    ],
    "wof:name":"It Takes Two LLP",
    "wof:placetype":"venue"
},
  "geometry": {"coordinates":[-102.308904,31.918366],"type":"Point"}
}