{
  "type": "Feature",
  "properties": {
    "iso:country":"US",
    "sg:address":"9922 Fernstone Ln",
    "sg:city":"Houston",
    "sg:classifiers":[
        {
            "category":"Personal",
            "type":"Services"
        }
    ],
    "sg:phone":"+1 281 894 4118",
    "sg:postcode":"77070",
    "sg:province":"TX",
    "wof:name":"Apartment Made Easy",
    "wof:placetype":"venue"
},
  "geometry": {"coordinates":[-95.567482,29.952454],"type":"Point"}
}