{
  "type": "Feature",
  "properties": {
    "iso:country":"US",
    "sg:address":"11942 Garden Grove Dr",
    "sg:city":"Dallas",
    "sg:classifiers":[
        {
            "category":"Shopping",
            "subcategory":"Computers & Home Electronics",
            "type":"Retail Goods"
        }
    ],
    "sg:phone":"+1 972 557 0963",
    "sg:postcode":"75253",
    "sg:province":"TX",
    "sg:tags":[
        "software"
    ],
    "wof:name":"Compact Data Solutions",
    "wof:placetype":"venue"
},
  "geometry": {"coordinates":[-96.604952,32.690749],"type":"Point"}
}