{
  "type": "Feature",
  "properties": {
    "iso:country":"US",
    "sg:address":"807 N Central Expy",
    "sg:city":"Richardson",
    "sg:classifiers":[
        {
            "category":"Cafe",
            "type":"Food & Drink"
        }
    ],
    "sg:menulink":"http://www.allmenus.com/tx/northeast/46133-cafe-mexico/menu/",
    "sg:phone":"+1 972 238 9741",
    "sg:postcode":"75080",
    "sg:province":"TX",
    "sg:tags":[
        "mexican"
    ],
    "wof:name":"Cafe Mexico",
    "wof:placetype":"venue"
},
  "geometry": {"coordinates":[-96.729901,32.958799],"type":"Point"}
}