{
  "type": "Feature",
  "properties": {
    "iso:country":"US",
    "sg:address":"1808 Ulit Ave",
    "sg:city":"Austin",
    "sg:classifiers":[
        {
            "category":"Shopping",
            "subcategory":"Books",
            "type":"Retail Goods"
        },
        {
            "category":"Wholesale",
            "subcategory":"Books, Periodicals, & Newspapers",
            "type":"Manufacturing & Wholesale Goods"
        }
    ],
    "sg:phone":"+1 512 472 4238",
    "sg:postcode":"78702",
    "sg:province":"TX",
    "sg:tags":[
        "books-wholesale",
        "store",
        "manufacturer"
    ],
    "wof:name":"White Publishers",
    "wof:placetype":"venue"
},
  "geometry": {"coordinates":[-97.712209,30.280071],"type":"Point"}
}