{
  "type": "Feature",
  "properties": {
    "iso:country":"US",
    "sg:address":"1027 Main St Ste C",
    "sg:city":"Pasadena",
    "sg:classifiers":[
        {
            "category":"Professional",
            "subcategory":"Testing Lab",
            "type":"Services"
        },
        {
            "category":"Health Services",
            "subcategory":"Medical Lab",
            "type":"Services"
        }
    ],
    "sg:phone":"+1 713 477 6979",
    "sg:postcode":"77506",
    "sg:province":"TX",
    "sg:tags":[
        "laboratory",
        "dental"
    ],
    "wof:name":"E W Morris Laboratory Inc",
    "wof:placetype":"venue"
},
  "geometry": {"coordinates":[-95.209344,29.695741],"type":"Point"}
}