{
  "type": "Feature",
  "properties": {
    "iso:country":"US",
    "sg:address":"2425 E Side Dr",
    "sg:city":"Austin",
    "sg:classifiers":[
        {
            "category":"Shopping",
            "subcategory":"Pharmacy",
            "type":"Retail Goods"
        }
    ],
    "sg:phone":"+1 512 478 6419",
    "sg:postcode":"78704",
    "sg:province":"TX",
    "wof:name":"Tarrytown Pharmacy Inc",
    "wof:placetype":"venue"
},
  "geometry": {"coordinates":[-97.749312,30.235512],"type":"Point"}
}