{
  "type": "Feature",
  "properties": {
    "iso:country":"US",
    "sg:address":"1620 Mayflower Dr",
    "sg:city":"Carrollton",
    "sg:classifiers":[
        {
            "category":"Freight",
            "type":"Transportation"
        }
    ],
    "sg:phone":"+1 972 939 0946",
    "sg:postcode":"75007",
    "sg:province":"TX",
    "sg:tags":[
        "fixed",
        "motor",
        "facility"
    ],
    "wof:name":"Armentrout Building Contractor",
    "wof:placetype":"venue"
},
  "geometry": {"coordinates":[-96.90098399999999,33.006538],"type":"Point"}
}