{
  "type": "Feature",
  "properties": {
    "iso:country":"US",
    "sg:address":"3921 Ayers St",
    "sg:city":"Corpus Christi",
    "sg:classifiers":[
        {
            "category":"Personal",
            "subcategory":"Beauty Salon",
            "type":"Services"
        }
    ],
    "sg:phone":"+1 361 855 2566",
    "sg:postcode":"78415",
    "sg:province":"TX",
    "sg:tags":[
        "shop"
    ],
    "wof:name":"Beauty Box Hair Fashions",
    "wof:placetype":"venue"
},
  "geometry": {"coordinates":[-97.415288,27.754965],"type":"Point"}
}