{
  "type": "Feature",
  "properties": {
    "iso:country":"US",
    "sg:address":"14885 US Hwy 181",
    "sg:city":"San Antonio",
    "sg:classifiers":[
        {
            "category":"Retail",
            "subcategory":"Auto Repair",
            "type":"Services"
        }
    ],
    "sg:phone":"+1 210 635 7582",
    "sg:postcode":"78223",
    "sg:province":"TX",
    "sg:tags":[
        "repairing",
        "automobile",
        "general"
    ],
    "wof:name":"Southeast Unlimited Auto RPR",
    "wof:placetype":"venue"
},
  "geometry": {"coordinates":[-98.31806899999999,29.27369],"type":"Point"}
}