{
  "type": "Feature",
  "properties": {
    "iso:country":"US",
    "sg:address":"7171 State Hwy 6",
    "sg:city":"Houston",
    "sg:classifiers":[
        {
            "category":"Wholesale",
            "subcategory":"Electrical",
            "type":"Manufacturing & Wholesale Goods"
        }
    ],
    "sg:phone":"+1 281 859 4396",
    "sg:postcode":"77095",
    "sg:province":"TX",
    "sg:tags":[
        "electronic",
        "furniture"
    ],
    "wof:name":"Hamamatsu Corporation",
    "wof:placetype":"venue"
},
  "geometry": {"coordinates":[-95.645391,29.881252],"type":"Point"}
}