{
  "type": "Feature",
  "properties": {
    "iso:country":"US",
    "sg:address":"2779 Ridge Rd",
    "sg:city":"Rockwall",
    "sg:classifiers":[
        {
            "category":"Coffee & Tea",
            "type":"Food & Drink"
        }
    ],
    "sg:menulink":"http://www.allmenus.com/tx/south-rockwall/113107-starbucks-coffee/menu/",
    "sg:phone":"+1 972 772 4461",
    "sg:postcode":"75032",
    "sg:province":"TX",
    "sg:tags":[
        "american"
    ],
    "wof:name":"Starbucks Coffee",
    "wof:placetype":"venue"
},
  "geometry": {"coordinates":[-96.47178599999999,32.890957],"type":"Point"}
}