{
  "type": "Feature",
  "properties": {
    "iso:country":"US",
    "sg:address":"4396 Main St",
    "sg:city":"The Colony",
    "sg:classifiers":[
        {
            "category":"Organizations",
            "subcategory":"Religious Organization",
            "type":"Services"
        }
    ],
    "sg:phone":"+1 972 625 8186",
    "sg:postcode":"75056",
    "sg:province":"TX",
    "sg:tags":[
        "church"
    ],
    "sg:website":"www.fbc-online.net",
    "wof:name":"Friendship Baptist Church",
    "wof:placetype":"venue"
},
  "geometry": {"coordinates":[-96.892709,33.075989],"type":"Point"}
}