{
  "type": "Feature",
  "properties": {
    "iso:country":"US",
    "sg:address":"11510 Roseview",
    "sg:city":"San Antonio",
    "sg:classifiers":[
        {
            "category":"Freight",
            "type":"Transportation"
        }
    ],
    "sg:phone":"+1 210 679 5059",
    "sg:postcode":"78253",
    "sg:province":"TX",
    "sg:tags":[
        "general"
    ],
    "wof:name":"Carls Boat & Rv Storage LLC",
    "wof:placetype":"venue"
},
  "geometry": {"coordinates":[-98.712953,29.439541],"type":"Point"}
}