{
  "type": "Feature",
  "properties": {
    "iso:country":"US",
    "sg:address":"4115 Woodbriar Ct",
    "sg:city":"Sugar Land",
    "sg:classifiers":[
        {
            "category":"Farming",
            "subcategory":"Livestock Farm",
            "type":"Manufacturing & Wholesale Goods"
        }
    ],
    "sg:phone":"+1 281 980 0710",
    "sg:postcode":"77479",
    "sg:province":"TX",
    "sg:tags":[
        "animal",
        "general"
    ],
    "wof:name":"BV Ranch Inc",
    "wof:placetype":"venue"
},
  "geometry": {"coordinates":[-95.602096,29.565161],"type":"Point"}
}