{
  "type": "Feature",
  "properties": {
    "iso:country":"US",
    "sg:address":"16055 Space Center Blvd",
    "sg:city":"Houston",
    "sg:classifiers":[
        {
            "category":"Utilities",
            "subcategory":"Telephone",
            "type":"Services"
        }
    ],
    "sg:phone":"+1 281 283 8010",
    "sg:postcode":"77058",
    "sg:province":"TX",
    "sg:tags":[
        "communications",
        "company"
    ],
    "sg:website":"www.birch.com",
    "wof:name":"Birch Telecom",
    "wof:placetype":"venue"
},
  "geometry": {"coordinates":[-95.11378999999999,29.574164],"type":"Point"}
}