{
  "type": "Feature",
  "properties": {
    "iso:country":"US",
    "sg:address":"1551 N Walnut Ave",
    "sg:city":"New Braunfels",
    "sg:classifiers":[
        {
            "category":"Banks & Credit Unions",
            "subcategory":"Bank",
            "type":"Services"
        }
    ],
    "sg:phone":"+1 830 625 2943",
    "sg:postcode":"78130",
    "sg:province":"TX",
    "sg:tags":[
        "loan",
        "real estate"
    ],
    "wof:name":"First Choice Lending",
    "wof:placetype":"venue"
},
  "geometry": {"coordinates":[-98.155377,29.713508],"type":"Point"}
}