{
  "type": "Feature",
  "properties": {
    "iso:country":"US",
    "sg:address":"1800 Shady Brook Ln",
    "sg:city":"Cedar Park",
    "sg:classifiers":[
        {
            "category":"Manufacturing",
            "subcategory":"Toys & Sporting Goods",
            "type":"Manufacturing & Wholesale Goods"
        }
    ],
    "sg:phone":"+1 512 423 7740",
    "sg:postcode":"78613",
    "sg:province":"TX",
    "sg:tags":[
        "mfg"
    ],
    "wof:name":"Lake Champ Lures LLC",
    "wof:placetype":"venue"
},
  "geometry": {"coordinates":[-97.85098000000001,30.524687],"type":"Point"}
}