{
  "type": "Feature",
  "properties": {
    "iso:country":"US",
    "sg:address":"13717 Neutron Rd",
    "sg:city":"Dallas",
    "sg:classifiers":[
        {
            "category":"Wholesale",
            "subcategory":"Non-durable Goods",
            "type":"Manufacturing & Wholesale Goods"
        }
    ],
    "sg:phone":"+1 972 448 2632",
    "sg:postcode":"75244",
    "sg:province":"TX",
    "wof:name":"National Wholesale Compressor",
    "wof:placetype":"venue"
},
  "geometry": {"coordinates":[-96.835027,32.934763],"type":"Point"}
}