{
  "type": "Feature",
  "properties": {
    "iso:country":"US",
    "sg:address":"2 London Ln",
    "sg:city":"Breckenridge",
    "sg:classifiers":[
        {
            "category":"Organizations",
            "subcategory":"Membership Organization",
            "type":"Services"
        }
    ],
    "sg:phone":"+1 254 559 8630",
    "sg:postcode":"76424",
    "sg:province":"TX",
    "wof:name":"Quail Unlimited Inc",
    "wof:placetype":"venue"
},
  "geometry": {"coordinates":[-98.927876,32.747611],"type":"Point"}
}