{
  "type": "Feature",
  "properties": {
    "iso:country":"US",
    "sg:address":"810 Nantucket Dr",
    "sg:city":"Beaumont",
    "sg:classifiers":[
        {
            "category":"Professional",
            "subcategory":"Engineering",
            "type":"Services"
        }
    ],
    "sg:phone":"+1 409 866 7096",
    "sg:postcode":"77706",
    "sg:province":"TX",
    "sg:tags":[
        "engineer"
    ],
    "wof:name":"Brymcon Inc",
    "wof:placetype":"venue"
},
  "geometry": {"coordinates":[-94.18221200000001,30.08234],"type":"Point"}
}