{
  "type": "Feature",
  "properties": {
    "iso:country":"US",
    "sg:address":"3918 Colquitt St",
    "sg:city":"Houston",
    "sg:classifiers":[
        {
            "category":"Organizations",
            "subcategory":"Membership Organization",
            "type":"Services"
        }
    ],
    "sg:phone":"+1 713 961 5993",
    "sg:postcode":"77027",
    "sg:province":"TX",
    "wof:name":"Paperweight Collectors Associa",
    "wof:placetype":"venue"
},
  "geometry": {"coordinates":[-95.442824,29.735348],"type":"Point"}
}