{
  "type": "Feature",
  "properties": {
    "iso:country":"US",
    "sg:address":"2500 Old Oaks Dr",
    "sg:city":"Waco",
    "sg:phone":"+1 254 772 2455",
    "sg:postcode":"76710",
    "sg:province":"TX",
    "sg:tags":[
        "fuel",
        "gasoline",
        "diesel"
    ],
    "wof:name":"Breckenridge Petroleum Inc",
    "wof:placetype":"venue"
},
  "geometry": {"coordinates":[-97.193814,31.552976],"type":"Point"}
}