{
  "type": "Feature",
  "properties": {
    "iso:country":"US",
    "sg:address":"707 Hwy 59 N",
    "sg:city":"Bowie",
    "sg:classifiers":[
        {
            "category":"Professional",
            "subcategory":"Accounting & Tax Preparation",
            "type":"Services"
        }
    ],
    "sg:phone":"+1 940 872 5157",
    "sg:postcode":"76230",
    "sg:province":"TX",
    "sg:tags":[
        "accountant"
    ],
    "wof:name":"Stephen G Gilland CPA",
    "wof:placetype":"venue"
},
  "geometry": {"coordinates":[-97.843136,33.56328],"type":"Point"}
}