{
  "type": "Feature",
  "properties": {
    "iso:country":"US",
    "sg:address":"234 Michigan Ave",
    "sg:city":"Mercedes",
    "sg:classifiers":[
        {
            "category":"Restaurant",
            "type":"Food & Drink"
        }
    ],
    "sg:phone":"+1 956 565 2309",
    "sg:postcode":"78570",
    "sg:province":"TX",
    "sg:tags":[
        "eating"
    ],
    "wof:name":"Cortinos Italian Restaurant",
    "wof:placetype":"venue"
},
  "geometry": {"coordinates":[-97.92287899999999,26.153194],"type":"Point"}
}