{
  "type": "Feature",
  "properties": {
    "iso:country":"US",
    "sg:address":"206 Wild Basin Rd S",
    "sg:city":"Austin",
    "sg:classifiers":[
        {
            "category":"Insurance",
            "subcategory":"Health Insurance",
            "type":"Services"
        }
    ],
    "sg:phone":"+1 512 327 7800",
    "sg:postcode":"78746",
    "sg:province":"TX",
    "sg:tags":[
        "life",
        "agency",
        "accident"
    ],
    "wof:name":"Provident",
    "wof:placetype":"venue"
},
  "geometry": {"coordinates":[-97.827167,30.30512],"type":"Point"}
}