{
  "type": "Feature",
  "properties": {
    "iso:country":"US",
    "sg:address":"2301 Ave H",
    "sg:city":"Nederland",
    "sg:classifiers":[
        {
            "category":"Recreation",
            "type":"Entertainment"
        }
    ],
    "sg:phone":"+1 409 724 0773",
    "sg:postcode":"77627",
    "sg:province":"TX",
    "sg:tags":[
        "parks"
    ],
    "wof:name":"Parks Dept",
    "wof:placetype":"venue"
},
  "geometry": {"coordinates":[-93.990285,29.96204],"type":"Point"}
}