{
  "type": "Feature",
  "properties": {
    "iso:country":"US",
    "sg:address":"200 Village Ct",
    "sg:city":"El Paso",
    "sg:classifiers":[
        {
            "category":"Freight",
            "type":"Transportation"
        }
    ],
    "sg:phone":"+1 915 581 7700",
    "sg:postcode":"79922",
    "sg:province":"TX",
    "sg:tags":[
        "commercial",
        "storage"
    ],
    "wof:name":"Crossroads Village Self Strg",
    "wof:placetype":"venue"
},
  "geometry": {"coordinates":[-106.573741,31.838673],"type":"Point"}
}