{
  "type": "Feature",
  "properties": {
    "iso:country":"US",
    "sg:address":"945 W Parker Rd",
    "sg:city":"Plano",
    "sg:classifiers":[
        {
            "category":"Autos & Motor Vehicles",
            "subcategory":"Fuel & Gas Station",
            "type":"Retail Goods"
        }
    ],
    "sg:phone":"+1 972 881 9977",
    "sg:postcode":"75023",
    "sg:province":"TX",
    "sg:tags":[
        "station",
        "gasoline"
    ],
    "wof:name":"Playno Food Mart",
    "wof:placetype":"venue"
},
  "geometry": {"coordinates":[-96.71381700000001,33.041114],"type":"Point"}
}