{
  "type": "Feature",
  "properties": {
    "iso:country":"US",
    "sg:address":"608 S Willow St",
    "sg:city":"Mansfield",
    "sg:classifiers":[
        {
            "category":"Building & Trades",
            "subcategory":"Construction",
            "type":"Services"
        }
    ],
    "sg:phone":"+1 817 657 7544",
    "sg:postcode":"76063",
    "sg:province":"TX",
    "sg:tags":[
        "roofing",
        "contractor"
    ],
    "wof:name":"Carl Lamb Roofing",
    "wof:placetype":"venue"
},
  "geometry": {"coordinates":[-97.127044,32.558966],"type":"Point"}
}