{
  "type": "Feature",
  "properties": {
    "iso:country":"US",
    "sg:address":"515 FM 1015",
    "sg:city":"Progreso",
    "sg:classifiers":[
        {
            "category":"Social Services",
            "type":"Services"
        }
    ],
    "sg:phone":"+1 956 565 9117",
    "sg:postcode":"78596",
    "sg:province":"TX",
    "sg:tags":[
        "care",
        "center",
        "day"
    ],
    "wof:name":"Amigos De Progresso Adult Dycr",
    "wof:placetype":"venue"
},
  "geometry": {"coordinates":[-97.958258,26.153426],"type":"Point"}
}