{
  "type": "Feature",
  "properties": {
    "iso:country":"US",
    "sg:address":"510 Bering Dr Ste 100",
    "sg:city":"Houston",
    "sg:classifiers":[
        {
            "category":"Banks & Credit Unions",
            "subcategory":"Investment Brokerage",
            "type":"Services"
        }
    ],
    "sg:phone":"+1 713 871 8300",
    "sg:postcode":"77057",
    "sg:province":"TX",
    "sg:tags":[
        "investing"
    ],
    "wof:name":"Pin Oak Investments Advisors",
    "wof:placetype":"venue"
},
  "geometry": {"coordinates":[-95.48106199999999,29.76393],"type":"Point"}
}