{
  "type": "Feature",
  "properties": {
    "iso:country":"US",
    "sg:address":"2809 Jasmine Ct",
    "sg:city":"Plano",
    "sg:classifiers":[
        {
            "category":"Retail",
            "subcategory":"Portrait Studio",
            "type":"Services"
        }
    ],
    "sg:phone":"+1 972 423 0300",
    "sg:postcode":"75074",
    "sg:province":"TX",
    "sg:tags":[
        "photo"
    ],
    "wof:name":"Bill Lindley Photography",
    "wof:placetype":"venue"
},
  "geometry": {"coordinates":[-96.688365,33.035904],"type":"Point"}
}