{
  "type": "Feature",
  "properties": {
    "iso:country":"US",
    "sg:address":"3524 Knickerbocker Rd",
    "sg:city":"San Angelo",
    "sg:classifiers":[
        {
            "category":"Banks & Credit Unions",
            "subcategory":"Investment Brokerage",
            "type":"Services"
        }
    ],
    "sg:phone":"+1 325 224 0470",
    "sg:postcode":"76904",
    "sg:province":"TX",
    "sg:tags":[
        "advisory",
        "financial"
    ],
    "wof:name":"Freedom Financial Solutions",
    "wof:placetype":"venue"
},
  "geometry": {"coordinates":[-100.470129,31.419977],"type":"Point"}
}