{
  "type": "Feature",
  "properties": {
    "iso:country":"US",
    "sg:address":"1201 S Park St",
    "sg:city":"Pecos",
    "sg:classifiers":[
        {
            "category":"Education",
            "subcategory":"School",
            "type":"Public Place"
        }
    ],
    "sg:phone":"+1 432 447 7222",
    "sg:postcode":"79772",
    "sg:province":"TX",
    "wof:name":"Pecos High School",
    "wof:placetype":"venue"
},
  "geometry": {"coordinates":[-103.502509,31.414834],"type":"Point"}
}