{
  "type": "Feature",
  "properties": {
    "iso:country":"US",
    "sg:address":"1579 E Main St",
    "sg:city":"Fredericksburg",
    "sg:classifiers":[
        {
            "category":"Manufacturing",
            "subcategory":"Signs",
            "type":"Manufacturing & Wholesale Goods"
        }
    ],
    "sg:phone":"+1 830 990 8062",
    "sg:postcode":"78624",
    "sg:province":"TX",
    "sg:tags":[
        "specialty",
        "mfg"
    ],
    "wof:name":"Engravers Inc",
    "wof:placetype":"venue"
},
  "geometry": {"coordinates":[-98.847977,30.25078],"type":"Point"}
}