{
  "type": "Feature",
  "properties": {
    "iso:country":"US",
    "sg:address":"2811 Depla St",
    "sg:city":"San Antonio",
    "sg:classifiers":[
        {
            "category":"Restaurant",
            "type":"Food & Drink"
        }
    ],
    "sg:phone":"+1 210 433 8903",
    "sg:postcode":"78207",
    "sg:province":"TX",
    "sg:tags":[
        "eating"
    ],
    "wof:name":"Creekside Concessions",
    "wof:placetype":"venue"
},
  "geometry": {"coordinates":[-98.548585,29.40103],"type":"Point"}
}