{
  "type": "Feature",
  "properties": {
    "iso:country":"US",
    "sg:address":"22 Chapparal Ct",
    "sg:city":"Missouri City",
    "sg:classifiers":[
        {
            "category":"Manufacturing",
            "subcategory":"Jewelry",
            "type":"Manufacturing & Wholesale Goods"
        }
    ],
    "sg:phone":"+1 281 261 4550",
    "sg:postcode":"77459",
    "sg:province":"TX",
    "sg:tags":[
        "precious",
        "metal",
        "mfg"
    ],
    "wof:name":"Lisas Little Treasures",
    "wof:placetype":"venue"
},
  "geometry": {"coordinates":[-95.558975,29.584979],"type":"Point"}
}