{
  "type": "Feature",
  "properties": {
    "iso:country":"US",
    "sg:address":"4900 Alameda Ave",
    "sg:city":"El Paso",
    "sg:classifiers":[
        {
            "category":"Utilities",
            "subcategory":"Mobile Phone",
            "type":"Services"
        }
    ],
    "sg:phone":"+1 915 772 3236",
    "sg:postcode":"79905",
    "sg:province":"TX",
    "sg:tags":[
        "telephone",
        "cellular"
    ],
    "wof:name":"Classic Cellular Plus",
    "wof:placetype":"venue"
},
  "geometry": {"coordinates":[-106.43161000000001,31.76981],"type":"Point"}
}