{
  "type": "Feature",
  "properties": {
    "iso:country":"US",
    "sg:address":"124 E Main St",
    "sg:city":"Fredericksburg",
    "sg:classifiers":[
        {
            "category":"Home & Garden",
            "subcategory":"Furniture",
            "type":"Retail Goods"
        }
    ],
    "sg:phone":"+1 830 997 5614",
    "sg:postcode":"78624",
    "sg:province":"TX",
    "sg:tags":[
        "import"
    ],
    "wof:name":"Elephant House",
    "wof:placetype":"venue"
},
  "geometry": {"coordinates":[-98.871875,30.274851],"type":"Point"}
}