{
  "type": "Feature",
  "properties": {
    "iso:country":"US",
    "sg:address":"2814 Bee Caves Rd Ste A",
    "sg:city":"Austin",
    "sg:classifiers":[
        {
            "category":"Professional",
            "subcategory":"Printing & Photocopies",
            "type":"Services"
        }
    ],
    "sg:phone":"+1 512 328 7266",
    "sg:postcode":"78746",
    "sg:province":"TX",
    "sg:website":"www.stokessigncompany.com",
    "wof:name":"Stokes Sign Company",
    "wof:placetype":"venue"
},
  "geometry": {"coordinates":[-97.789869,30.271322],"type":"Point"}
}