{
  "type": "Feature",
  "properties": {
    "iso:country":"US",
    "sg:address":"1804 Brothers Blvd",
    "sg:city":"College Station",
    "sg:classifiers":[
        {
            "category":"Real Estate",
            "subcategory":"Real Estate Agent",
            "type":"Services"
        }
    ],
    "sg:phone":"+1 979 696 7653",
    "sg:postcode":"77845",
    "sg:province":"TX",
    "wof:name":"Celtic Realtors",
    "wof:placetype":"venue"
},
  "geometry": {"coordinates":[-96.30004099999999,30.595714],"type":"Point"}
}