{
  "type": "Feature",
  "properties": {
    "iso:country":"US",
    "sg:address":"10356 Estacado Dr",
    "sg:city":"Dallas",
    "sg:classifiers":[
        {
            "category":"Professional",
            "type":"Services"
        }
    ],
    "sg:phone":"+1 214 324 4353",
    "sg:postcode":"75228",
    "sg:province":"TX",
    "wof:name":"Queenie Foundation Inc",
    "wof:placetype":"venue"
},
  "geometry": {"coordinates":[-96.68159300000001,32.83524],"type":"Point"}
}