{
  "type": "Feature",
  "properties": {
    "iso:country":"US",
    "sg:address":"112 Cypress Ln",
    "sg:city":"Boerne",
    "sg:classifiers":[
        {
            "category":"Professional",
            "subcategory":"Management & Consulting",
            "type":"Services"
        }
    ],
    "sg:phone":"+1 830 537 4250",
    "sg:postcode":"78006",
    "sg:province":"TX",
    "sg:tags":[
        "retail",
        "direct",
        "sales"
    ],
    "wof:name":"Violet Floral",
    "wof:placetype":"venue"
},
  "geometry": {"coordinates":[-98.722902,29.87109],"type":"Point"}
}