{
  "type": "Feature",
  "properties": {
    "iso:country":"US",
    "sg:address":"938 Wakefield Dr",
    "sg:city":"Houston",
    "sg:classifiers":[
        {
            "category":"Freight",
            "type":"Transportation"
        }
    ],
    "sg:phone":"+1 713 686 4858",
    "sg:postcode":"77018",
    "sg:province":"TX",
    "sg:tags":[
        "delivery"
    ],
    "wof:name":"Easterwood Delivery Svc",
    "wof:placetype":"venue"
},
  "geometry": {"coordinates":[-95.423208,29.821558],"type":"Point"}
}