{
  "type": "Feature",
  "properties": {
    "iso:country":"US",
    "sg:address":"6302 Deerwood Rd",
    "sg:city":"Houston",
    "sg:classifiers":[
        {
            "category":"Social Services",
            "subcategory":"Child Care",
            "type":"Services"
        }
    ],
    "sg:phone":"+1 713 826 8842",
    "sg:postcode":"77057",
    "sg:province":"TX",
    "sg:tags":[
        "day"
    ],
    "wof:name":"Bloom and Associates",
    "wof:placetype":"venue"
},
  "geometry": {"coordinates":[-95.49703599999999,29.759475],"type":"Point"}
}