{
  "type": "Feature",
  "properties": {
    "iso:country":"US",
    "sg:address":"1102 Riley St",
    "sg:city":"Freer",
    "sg:classifiers":[
        {
            "category":"Food & Beverages",
            "subcategory":"Groceries & Convenience Stores",
            "type":"Retail Goods"
        }
    ],
    "sg:phone":"+1 361 394 6055",
    "sg:postcode":"78384",
    "sg:province":"TX",
    "sg:tags":[
        "grocer"
    ],
    "wof:name":"Super S Foods",
    "wof:placetype":"venue"
},
  "geometry": {"coordinates":[-98.605825,27.882896],"type":"Point"}
}