{
  "type": "Feature",
  "properties": {
    "iso:country":"US",
    "sg:address":"111 W Park Ave",
    "sg:city":"Iowa Park",
    "sg:classifiers":[
        {
            "category":"Food & Beverages",
            "subcategory":"Bakery",
            "type":"Retail Goods"
        }
    ],
    "sg:phone":"+1 940 592 3354",
    "sg:postcode":"76367",
    "sg:province":"TX",
    "wof:name":"Kathys Bakery & Delivery Inc",
    "wof:placetype":"venue"
},
  "geometry": {"coordinates":[-98.669006,33.952216],"type":"Point"}
}