{
  "type": "Feature",
  "properties": {
    "iso:country":"US",
    "sg:address":"900 W Milam St",
    "sg:city":"Ennis",
    "sg:classifiers":[
        {
            "category":"Shopping",
            "type":"Retail Goods"
        }
    ],
    "sg:phone":"+1 972 878 6391",
    "sg:postcode":"75119",
    "sg:province":"TX",
    "sg:tags":[
        "ice"
    ],
    "wof:name":"Kold Ice Co",
    "wof:placetype":"venue"
},
  "geometry": {"coordinates":[-96.632606,32.321871],"type":"Point"}
}