{
  "type": "Feature",
  "properties": {
    "iso:country":"US",
    "sg:address":"1519 Co Rd 129",
    "sg:city":"Pearland",
    "sg:classifiers":[
        {
            "category":"Retail",
            "subcategory":"Auto Repair",
            "type":"Services"
        }
    ],
    "sg:phone":"+1 281 996 7000",
    "sg:postcode":"77581",
    "sg:province":"TX",
    "sg:tags":[
        "body",
        "automobile",
        "painting"
    ],
    "wof:name":"Kings Carriage Repair Shoppe",
    "wof:placetype":"venue"
},
  "geometry": {"coordinates":[-95.232798,29.508953],"type":"Point"}
}