{
  "type": "Feature",
  "properties": {
    "iso:country":"US",
    "sg:address":"220 E Hidden Creek Pkwy",
    "sg:city":"Burleson",
    "sg:classifiers":[
        {
            "category":"Freight",
            "type":"Transportation"
        }
    ],
    "sg:phone":"+1 817 426 5800",
    "sg:postcode":"76028",
    "sg:province":"TX",
    "sg:tags":[
        "commercial",
        "storage"
    ],
    "wof:name":"Storage Depot",
    "wof:placetype":"venue"
},
  "geometry": {"coordinates":[-97.31501799999999,32.525537],"type":"Point"}
}