{
  "type": "Feature",
  "properties": {
    "iso:country":"US",
    "sg:address":"6550 Browning Dr",
    "sg:city":"Fort Worth",
    "sg:classifiers":[
        {
            "category":"Retail",
            "subcategory":"Auto Rental",
            "type":"Services"
        }
    ],
    "sg:phone":"+1 817 577 1732",
    "sg:postcode":"76180",
    "sg:province":"TX",
    "sg:tags":[
        "renting",
        "truck",
        "leasing"
    ],
    "wof:name":"U-Haul Co",
    "wof:placetype":"venue"
},
  "geometry": {"coordinates":[-97.24445,32.847675],"type":"Point"}
}