{
  "type": "Feature",
  "properties": {
    "iso:country":"US",
    "sg:address":"7920 College St Rear",
    "sg:city":"Beaumont",
    "sg:classifiers":[
        {
            "category":"Home & Garden",
            "subcategory":"Household Appliances",
            "type":"Retail Goods"
        },
        {
            "category":"Home & Garden",
            "subcategory":"Furniture",
            "type":"Retail Goods"
        }
    ],
    "sg:phone":"+1 409 860 9650",
    "sg:postcode":"77707",
    "sg:province":"TX",
    "sg:tags":[
        "machine",
        "major",
        "dishwashing",
        "store"
    ],
    "wof:name":"Diggers Paradise",
    "wof:placetype":"venue"
},
  "geometry": {"coordinates":[-94.183494,30.067512],"type":"Point"}
}