{
  "type": "Feature",
  "properties": {
    "iso:country":"US",
    "sg:address":"1144 N Stemmons Fwy",
    "sg:city":"Lewisville",
    "sg:classifiers":[
        {
            "category":"Autos & Motor Vehicles",
            "subcategory":"Automobile Sales",
            "type":"Retail Goods"
        }
    ],
    "sg:phone":"+1 972 221 2900",
    "sg:postcode":"75067",
    "sg:province":"TX",
    "sg:tags":[
        "car",
        "dealer"
    ],
    "sg:website":"www.fordcountry.net",
    "wof:name":"Ford Country-Lewisville",
    "wof:placetype":"venue"
},
  "geometry": {"coordinates":[-97.012344,33.059378],"type":"Point"}
}