{
  "type": "Feature",
  "properties": {
    "iso:country":"US",
    "sg:address":"3504 Robin Rd",
    "sg:city":"Plano",
    "sg:classifiers":[
        {
            "category":"Restaurant",
            "type":"Food & Drink"
        }
    ],
    "sg:phone":"+1 972 491 1841",
    "sg:postcode":"75075",
    "sg:province":"TX",
    "sg:tags":[
        "eating"
    ],
    "wof:name":"Mandarin Group USA Inc",
    "wof:placetype":"venue"
},
  "geometry": {"coordinates":[-96.758348,33.013507],"type":"Point"}
}