{
  "type": "Feature",
  "properties": {
    "iso:country":"US",
    "sg:address":"306 Rattlesnake Rd",
    "sg:city":"Riesel",
    "sg:classifiers":[
        {
            "category":"Professional",
            "type":"Services"
        }
    ],
    "sg:phone":"+1 254 896 2229",
    "sg:postcode":"76682",
    "sg:province":"TX",
    "wof:name":"Ellis Yancy Sr",
    "wof:placetype":"venue"
},
  "geometry": {"coordinates":[-96.940489,31.486266],"type":"Point"}
}