{
  "type": "Feature",
  "properties": {
    "iso:country":"US",
    "sg:address":"635 Co Rd 161",
    "sg:city":"Granger",
    "sg:classifiers":[
        {
            "category":"Food & Beverages",
            "subcategory":"Specialty",
            "type":"Retail Goods"
        }
    ],
    "sg:phone":"+1 512 415 9113",
    "sg:postcode":"76530",
    "sg:province":"TX",
    "sg:tags":[
        "business"
    ],
    "wof:name":"Rls Enterprises",
    "wof:placetype":"venue"
},
  "geometry": {"coordinates":[-97.528994,30.699744],"type":"Point"}
}