{
  "type": "Feature",
  "properties": {
    "iso:country":"US",
    "sg:address":"987 Co Rd 165",
    "sg:city":"Whitesboro",
    "sg:classifiers":[
        {
            "category":"Farming",
            "subcategory":"Nursery",
            "type":"Manufacturing & Wholesale Goods"
        }
    ],
    "sg:phone":"+1 903 564 7412",
    "sg:postcode":"76273",
    "sg:province":"TX",
    "sg:tags":[
        "ornamental"
    ],
    "wof:name":"Diversified Land Service",
    "wof:placetype":"venue"
},
  "geometry": {"coordinates":[-96.952753,33.689149],"type":"Point"}
}