{
  "type": "Feature",
  "properties": {
    "iso:country":"US",
    "sg:address":"603 Main",
    "sg:city":"Schertz",
    "sg:classifiers":[
        {
            "category":"Personal",
            "type":"Services"
        },
        {
            "category":"Building & Trades",
            "subcategory":"Cleaning & Sanitation",
            "type":"Services"
        }
    ],
    "sg:phone":"+1 210 945 8775",
    "sg:postcode":"78154",
    "sg:province":"TX",
    "sg:tags":[
        "house",
        "butlers'",
        "maids'"
    ],
    "sg:website":"http://www.maggiemaid.org",
    "wof:name":"Maggie Maid Inc",
    "wof:placetype":"venue"
},
  "geometry": {"coordinates":[-98.26885799999999,29.553613],"type":"Point"}
}