{
  "type": "Feature",
  "properties": {
    "iso:country":"US",
    "sg:address":"916 W Hwy 190",
    "sg:city":"Copperas Cove",
    "sg:classifiers":[
        {
            "category":"Social Services",
            "subcategory":"Child Care",
            "type":"Services"
        }
    ],
    "sg:phone":"+1 254 547 1144",
    "sg:postcode":"76522",
    "sg:province":"TX",
    "wof:name":"Perfect Praise Day Care Ctr",
    "wof:placetype":"venue"
},
  "geometry": {"coordinates":[-97.914447,31.108583],"type":"Point"}
}