{
  "type": "Feature",
  "properties": {
    "iso:country":"US",
    "sg:address":"12922 Hempstead Rd",
    "sg:city":"Houston",
    "sg:classifiers":[
        {
            "category":"Food & Beverages",
            "subcategory":"Groceries & Convenience Stores",
            "type":"Retail Goods"
        }
    ],
    "sg:phone":"+1 713 460 8000",
    "sg:postcode":"77040",
    "sg:province":"TX",
    "sg:website":"www.metcompany.net",
    "wof:name":"Met Company Inc",
    "wof:placetype":"venue"
},
  "geometry": {"coordinates":[-95.506699,29.8349],"type":"Point"}
}