{
  "type": "Feature",
  "properties": {
    "iso:country":"US",
    "sg:address":"1625 Wildcat Dr",
    "sg:city":"Portland",
    "sg:classifiers":[
        {
            "category":"Autos & Motor Vehicles",
            "subcategory":"Automobile Sales",
            "type":"Retail Goods"
        }
    ],
    "sg:phone":"+1 361 777 3304",
    "sg:postcode":"78374",
    "sg:province":"TX",
    "sg:tags":[
        "dealers-used",
        "car",
        "used",
        "cars-wholesale"
    ],
    "wof:name":"Kodel Enterprises",
    "wof:placetype":"venue"
},
  "geometry": {"coordinates":[-97.31908799999999,27.885953],"type":"Point"}
}