{
  "type": "Feature",
  "properties": {
    "iso:country":"US",
    "sg:address":"7650 Co Rd 48",
    "sg:city":"Rosharon",
    "sg:classifiers":[
        {
            "category":"Retail",
            "subcategory":"Repair Shop",
            "type":"Services"
        },
        {
            "category":"Manufacturing",
            "subcategory":"Tools & Machinery",
            "type":"Manufacturing & Wholesale Goods"
        }
    ],
    "sg:phone":"+1 281 431 6691",
    "sg:postcode":"77583",
    "sg:province":"TX",
    "sg:tags":[
        "equipment",
        "turbine",
        "industrial"
    ],
    "wof:name":"Trinity Turbine Technology LP",
    "wof:placetype":"venue"
},
  "geometry": {"coordinates":[-95.415249,29.479031],"type":"Point"}
}