{
  "type": "Feature",
  "properties": {
    "iso:country":"US",
    "sg:address":"4500 Huntwick Dr",
    "sg:city":"Plano",
    "sg:classifiers":[
        {
            "category":"Organizations",
            "subcategory":"Religious Organization",
            "type":"Services"
        }
    ],
    "sg:phone":"+1 972 596 6670",
    "sg:postcode":"75024",
    "sg:province":"TX",
    "wof:name":"Thirtythreeadcom Inc",
    "wof:placetype":"venue"
},
  "geometry": {"coordinates":[-96.781049,33.057021],"type":"Point"}
}