{
  "type": "Feature",
  "properties": {
    "iso:country":"US",
    "sg:address":"6300 Regional Plz",
    "sg:city":"Abilene",
    "sg:classifiers":[
        {
            "category":"Health Services",
            "subcategory":"Doctor",
            "type":"Services"
        }
    ],
    "sg:phone":"+1 325 691 1899",
    "sg:postcode":"79606",
    "sg:province":"TX",
    "sg:tags":[
        "physician",
        "family",
        "practice",
        "surgeons",
        "medicine",
        "surgeon"
    ],
    "wof:name":"Dixon, Joseph",
    "wof:placetype":"venue"
},
  "geometry": {"coordinates":[-99.74464999999999,32.374007],"type":"Point"}
}