{
  "type": "Feature",
  "properties": {
    "iso:country":"US",
    "sg:address":"2601 Preston Rd",
    "sg:city":"Frisco",
    "sg:classifiers":[
        {
            "category":"Food & Beverages",
            "subcategory":"Candy",
            "type":"Retail Goods"
        }
    ],
    "sg:phone":"+1 469 633 1309",
    "sg:postcode":"75034",
    "sg:province":"TX",
    "sg:tags":[
        "confectionery"
    ],
    "wof:name":"Godiva Chocolatier Inc",
    "wof:placetype":"venue"
},
  "geometry": {"coordinates":[-96.805673,33.099351],"type":"Point"}
}