{
  "type": "Feature",
  "properties": {
    "iso:country":"US",
    "sg:address":"3700 Santa Maria Ave",
    "sg:city":"Laredo",
    "sg:classifiers":[
        {
            "category":"Personal",
            "subcategory":"Beauty Salon",
            "type":"Services"
        }
    ],
    "sg:phone":"+1 956 729 0248",
    "sg:postcode":"78041",
    "sg:province":"TX",
    "wof:name":"Kid's & Teens Beauty Salon",
    "wof:placetype":"venue"
},
  "geometry": {"coordinates":[-99.509992,27.533724],"type":"Point"}
}