{
  "type": "Feature",
  "properties": {
    "iso:country":"US",
    "sg:address":"1405 W Davis St",
    "sg:city":"Dallas",
    "sg:classifiers":[
        {
            "category":"Shopping",
            "type":"Retail Goods"
        }
    ],
    "sg:phone":"+1 214 941 4119",
    "sg:postcode":"75208",
    "sg:province":"TX",
    "sg:tags":[
        "religious"
    ],
    "wof:name":"Chango Botanica",
    "wof:placetype":"venue"
},
  "geometry": {"coordinates":[-96.84470399999999,32.749401],"type":"Point"}
}