{
  "type": "Feature",
  "properties": {
    "iso:country":"US",
    "sg:address":"640 S Central Expy",
    "sg:city":"Dallas",
    "sg:classifiers":[
        {
            "category":"Building & Trades",
            "subcategory":"Equipment Rental",
            "type":"Services"
        }
    ],
    "sg:phone":"+1 972 664 1099",
    "sg:postcode":"75201",
    "sg:province":"TX",
    "wof:name":"Dfw Remarketing Service Inc",
    "wof:placetype":"venue"
},
  "geometry": {"coordinates":[-96.789022,32.779285],"type":"Point"}
}