{
  "type": "Feature",
  "properties": {
    "iso:country":"US",
    "sg:address":"11730 Imperial Woods Ln",
    "sg:city":"Cypress",
    "sg:classifiers":[
        {
            "category":"Professional",
            "subcategory":"Business Services",
            "type":"Services"
        }
    ],
    "sg:phone":"+1 281 376 2809",
    "sg:postcode":"77429",
    "sg:province":"TX",
    "wof:name":"Inside Edge Solutions Inc",
    "wof:placetype":"venue"
},
  "geometry": {"coordinates":[-95.628782,29.991378],"type":"Point"}
}