{
  "type": "Feature",
  "properties": {
    "iso:country":"US",
    "sg:address":"10343 Sahara St",
    "sg:city":"San Antonio",
    "sg:classifiers":[
        {
            "category":"Wholesale",
            "subcategory":"Non-durable Goods",
            "type":"Manufacturing & Wholesale Goods"
        }
    ],
    "sg:phone":"+1 210 377 0255",
    "sg:postcode":"78216",
    "sg:province":"TX",
    "wof:name":"Kona Traders Inc",
    "wof:placetype":"venue"
},
  "geometry": {"coordinates":[-98.49220099999999,29.531322],"type":"Point"}
}