{
  "type": "Feature",
  "properties": {
    "iso:country":"US",
    "sg:address":"6134 Siesta Valley Dr",
    "sg:city":"San Antonio",
    "sg:classifiers":[
        {
            "category":"Building & Trades",
            "subcategory":"Cleaning & Sanitation",
            "type":"Services"
        }
    ],
    "sg:phone":"+1 210 623 2541",
    "sg:postcode":"78242",
    "sg:province":"TX",
    "wof:name":"Janistar",
    "wof:placetype":"venue"
},
  "geometry": {"coordinates":[-98.622983,29.34962],"type":"Point"}
}