{
  "type": "Feature",
  "properties": {
    "iso:country":"US",
    "sg:address":"2100 Bering Dr",
    "sg:city":"Houston",
    "sg:classifiers":[
        {
            "category":"Professional",
            "type":"Services"
        }
    ],
    "sg:phone":"+1 713 355 3775",
    "sg:postcode":"77057",
    "sg:province":"TX",
    "wof:name":"Franco Davati",
    "wof:placetype":"venue"
},
  "geometry": {"coordinates":[-95.479552,29.744319],"type":"Point"}
}