{
  "type": "Feature",
  "properties": {
    "iso:country":"US",
    "sg:address":"2730 Fyke Rd Ofc",
    "sg:city":"Farmers Branch",
    "sg:classifiers":[
        {
            "category":"Real Estate",
            "subcategory":"Real Estate Operator",
            "type":"Services"
        }
    ],
    "sg:phone":"+1 972 241 7327",
    "sg:postcode":"75234",
    "sg:province":"TX",
    "sg:tags":[
        "apartment"
    ],
    "wof:name":"Villa Marquis Apts",
    "wof:placetype":"venue"
},
  "geometry": {"coordinates":[-96.887703,32.9464],"type":"Point"}
}