{
  "type": "Feature",
  "properties": {
    "iso:country":"US",
    "sg:address":"124 Highlander",
    "sg:city":"Austin",
    "sg:classifiers":[
        {
            "category":"Professional",
            "subcategory":"Business Services",
            "type":"Services"
        }
    ],
    "sg:phone":"+1 512 261 5395",
    "sg:postcode":"78734",
    "sg:province":"TX",
    "wof:name":"Communication Connection",
    "wof:placetype":"venue"
},
  "geometry": {"coordinates":[-97.993844,30.368192],"type":"Point"}
}