{
  "type": "Feature",
  "properties": {
    "iso:country":"US",
    "sg:address":"2950 FM 2181",
    "sg:city":"Corinth",
    "sg:classifiers":[
        {
            "category":"Professional",
            "subcategory":"Business Services",
            "type":"Services"
        }
    ],
    "sg:phone":"+1 940 321 2840",
    "sg:postcode":"76210",
    "sg:province":"TX",
    "sg:tags":[
        "convention",
        "meeting",
        "facility"
    ],
    "wof:name":"Canyon Lake Ranch",
    "wof:placetype":"venue"
},
  "geometry": {"coordinates":[-97.08461200000001,33.132036],"type":"Point"}
}