{
  "type": "Feature",
  "properties": {
    "iso:country":"US",
    "sg:address":"6001 Yale St",
    "sg:city":"Houston",
    "sg:classifiers":[
        {
            "category":"Food & Beverages",
            "subcategory":"Groceries & Convenience Stores",
            "type":"Retail Goods"
        }
    ],
    "sg:phone":"+1 713 692 7385",
    "sg:postcode":"77076",
    "sg:province":"TX",
    "wof:name":"Jimmy's Food Market",
    "wof:placetype":"venue"
},
  "geometry": {"coordinates":[-95.403198,29.8522],"type":"Point"}
}