{
  "type": "Feature",
  "properties": {
    "iso:country":"US",
    "sg:address":"3208 Preston Rd",
    "sg:city":"Frisco",
    "sg:classifiers":[
        {
            "category":"Restaurant",
            "type":"Food & Drink"
        }
    ],
    "sg:menulink":"http://www.allmenus.com/tx/mckinney/192120-wendys/menu/",
    "sg:phone":"+1 469 633 0641",
    "sg:postcode":"75034",
    "sg:province":"TX",
    "sg:tags":[
        "burger",
        "american",
        "soup"
    ],
    "wof:name":"Wendy's",
    "wof:placetype":"venue"
},
  "geometry": {"coordinates":[-96.805055,33.105237],"type":"Point"}
}