{
  "type": "Feature",
  "properties": {
    "iso:country":"US",
    "sg:address":"522 Oakhill Rd",
    "sg:city":"Texarkana",
    "sg:classifiers":[
        {
            "category":"Organizations",
            "subcategory":"Religious Organization",
            "type":"Services"
        }
    ],
    "sg:phone":"+1 903 838 2484",
    "sg:postcode":"75501",
    "sg:province":"TX",
    "sg:tags":[
        "church"
    ],
    "wof:name":"Church Of God Of Prophecy",
    "wof:placetype":"venue"
},
  "geometry": {"coordinates":[-94.089195,33.450114],"type":"Point"}
}