{
  "type": "Feature",
  "properties": {
    "iso:country":"US",
    "sg:address":"4403 W Walnut St",
    "sg:city":"Garland",
    "sg:classifiers":[
        {
            "category":"Manufacturing",
            "subcategory":"Food",
            "type":"Manufacturing & Wholesale Goods"
        }
    ],
    "sg:phone":"+1 972 485 8888",
    "sg:postcode":"75042",
    "sg:province":"TX",
    "sg:tags":[
        "mfg"
    ],
    "wof:name":"Hu Tien Nam Vang Asian Noodle",
    "wof:placetype":"venue"
},
  "geometry": {"coordinates":[-96.696986,32.916669],"type":"Point"}
}