{
  "type": "Feature",
  "properties": {
    "iso:country":"US",
    "sg:address":"13806 Ramblewood Trl",
    "sg:city":"Dallas",
    "sg:classifiers":[
        {
            "category":"Manufacturing",
            "subcategory":"Apparel",
            "type":"Manufacturing & Wholesale Goods"
        }
    ],
    "sg:phone":"+1 972 231 2930",
    "sg:postcode":"75240",
    "sg:province":"TX",
    "sg:tags":[
        "blouse",
        "mfg"
    ],
    "wof:name":"M Larson Ursula",
    "wof:placetype":"venue"
},
  "geometry": {"coordinates":[-96.762027,32.937559],"type":"Point"}
}