{
  "type": "Feature",
  "properties": {
    "iso:country":"US",
    "sg:address":"5905 Waltrip St",
    "sg:city":"Houston",
    "sg:classifiers":[
        {
            "category":"Education",
            "subcategory":"School",
            "type":"Public Place"
        }
    ],
    "sg:phone":"+1 713 845 5600",
    "sg:postcode":"77087",
    "sg:province":"TX",
    "sg:tags":[
        "high",
        "middle",
        "elementary"
    ],
    "sg:website":"www.houstonisd.org",
    "wof:name":"Houston Independent School District",
    "wof:placetype":"venue"
},
  "geometry": {"coordinates":[-95.306691,29.679234],"type":"Point"}
}