{
  "type": "Feature",
  "properties": {
    "iso:country":"US",
    "sg:address":"107 US Hwy 79",
    "sg:city":"Franklin",
    "sg:classifiers":[
        {
            "category":"Real Estate",
            "subcategory":"Real Estate Agent",
            "type":"Services"
        }
    ],
    "sg:phone":"+1 979 828 4000",
    "sg:postcode":"77859",
    "sg:province":"TX",
    "wof:name":"Texas Land Co Of Franklin",
    "wof:placetype":"venue"
},
  "geometry": {"coordinates":[-96.59662,30.883235],"type":"Point"}
}