{
  "type": "Feature",
  "properties": {
    "iso:country":"US",
    "sg:address":"5909 Centralcrest St",
    "sg:city":"Houston",
    "sg:classifiers":[
        {
            "category":"Organizations",
            "subcategory":"Religious Organization",
            "type":"Services"
        }
    ],
    "sg:phone":"+1 713 681 6374",
    "sg:postcode":"77092",
    "sg:province":"TX",
    "sg:tags":[
        "church"
    ],
    "wof:name":"Central Garden Missionary",
    "wof:placetype":"venue"
},
  "geometry": {"coordinates":[-95.47766900000001,29.815613],"type":"Point"}
}