{
  "type": "Feature",
  "properties": {
    "iso:country":"US",
    "sg:address":"6418 Sevenleaf Ln",
    "sg:city":"Humble",
    "sg:classifiers":[
        {
            "category":"Professional",
            "type":"Services"
        }
    ],
    "sg:phone":"+1 281 361 5868",
    "sg:postcode":"77345",
    "sg:province":"TX",
    "wof:name":"CD Polytech Inc",
    "wof:placetype":"venue"
},
  "geometry": {"coordinates":[-95.156933,30.06753],"type":"Point"}
}