{
  "type": "Feature",
  "properties": {
    "iso:country":"US",
    "sg:address":"510 S Congress Ave Ste 100",
    "sg:city":"Austin",
    "sg:classifiers":[
        {
            "category":"Insurance",
            "subcategory":"Insurance Agent",
            "type":"Services"
        },
        {
            "category":"Insurance",
            "subcategory":"Hazard Insurance",
            "type":"Services"
        }
    ],
    "sg:phone":"+1 512 477 5663",
    "sg:postcode":"78704",
    "sg:province":"TX",
    "sg:tags":[
        "consultant",
        "analyst"
    ],
    "sg:website":"http://www.alonsocamarainsurance.com",
    "wof:name":"Alonso Camara Insurance Agency",
    "wof:placetype":"venue"
},
  "geometry": {"coordinates":[-97.74704199999999,30.256744],"type":"Point"}
}