{
  "type": "Feature",
  "properties": {
    "iso:country":"US",
    "sg:address":"640 Paint Pony Trl N",
    "sg:city":"Fort Worth",
    "sg:classifiers":[
        {
            "category":"Banks & Credit Unions",
            "subcategory":"Financial Services",
            "type":"Services"
        }
    ],
    "sg:phone":"+1 817 246 2526",
    "sg:postcode":"76108",
    "sg:province":"TX",
    "sg:tags":[
        "investor"
    ],
    "wof:name":"Dolphin Investments Corp",
    "wof:placetype":"venue"
},
  "geometry": {"coordinates":[-97.498486,32.777759],"type":"Point"}
}