{
  "type": "Feature",
  "properties": {
    "iso:country":"US",
    "sg:address":"27234 Lana Ln",
    "sg:city":"Conroe",
    "sg:classifiers":[
        {
            "category":"Building & Trades",
            "subcategory":"Construction",
            "type":"Services"
        }
    ],
    "sg:phone":"+1 281 367 0517",
    "sg:postcode":"77385",
    "sg:province":"TX",
    "sg:tags":[
        "home",
        "builder"
    ],
    "wof:name":"Frank Waggoner",
    "wof:placetype":"venue"
},
  "geometry": {"coordinates":[-95.445075,30.158623],"type":"Point"}
}