{
  "type": "Feature",
  "properties": {
    "iso:country":"US",
    "sg:address":"4800 US Hwy 377",
    "sg:city":"Aubrey",
    "sg:classifiers":[
        {
            "category":"Building & Trades",
            "subcategory":"Construction",
            "type":"Services"
        }
    ],
    "sg:phone":"+1 940 440 0530",
    "sg:postcode":"76227",
    "sg:province":"TX",
    "sg:tags":[
        "contractor"
    ],
    "wof:name":"Wileys General Contracting",
    "wof:placetype":"venue"
},
  "geometry": {"coordinates":[-96.98723699999999,33.261193],"type":"Point"}
}