{
  "type": "Feature",
  "properties": {
    "iso:country":"US",
    "sg:address":"1315 Mockingbird Ln",
    "sg:city":"Seguin",
    "sg:classifiers":[
        {
            "category":"Retail",
            "subcategory":"Funeral Services",
            "type":"Services"
        }
    ],
    "sg:phone":"+1 830 379 4516",
    "sg:postcode":"78155",
    "sg:province":"TX",
    "sg:tags":[
        "cemetery"
    ],
    "wof:name":"Boecker Cemetery Association",
    "wof:placetype":"venue"
},
  "geometry": {"coordinates":[-97.94602999999999,29.581617],"type":"Point"}
}