{
  "type": "Feature",
  "properties": {
    "iso:country":"US",
    "sg:address":"108 Magnolia St",
    "sg:city":"Mansfield",
    "sg:classifiers":[
        {
            "category":"Shopping",
            "subcategory":"Used Merchandise",
            "type":"Retail Goods"
        }
    ],
    "sg:phone":"+1 817 453 0133",
    "sg:postcode":"76063",
    "sg:province":"TX",
    "wof:name":"Antique Marketplace",
    "wof:placetype":"venue"
},
  "geometry": {"coordinates":[-97.123334,32.569005],"type":"Point"}
}