{
  "type": "Feature",
  "properties": {
    "iso:country":"US",
    "sg:address":"514 Preston St",
    "sg:city":"Waco",
    "sg:classifiers":[
        {
            "category":"Personal",
            "subcategory":"Beauty Salon",
            "type":"Services"
        }
    ],
    "sg:phone":"+1 254 756 0309",
    "sg:postcode":"76704",
    "sg:province":"TX",
    "wof:name":"Mary Beal's Beauty Shop",
    "wof:placetype":"venue"
},
  "geometry": {"coordinates":[-97.12756899999999,31.569726],"type":"Point"}
}