{
  "type": "Feature",
  "properties": {
    "iso:country":"US",
    "sg:address":"1103 Houston St",
    "sg:city":"Levelland",
    "sg:classifiers":[
        {
            "category":"Real Estate",
            "subcategory":"Real Estate Services",
            "type":"Services"
        },
        {
            "category":"Professional",
            "subcategory":"Business Services",
            "type":"Services"
        }
    ],
    "sg:phone":"+1 806 894 9654",
    "sg:postcode":"79336",
    "sg:province":"TX",
    "sg:tags":[
        "appraisers-business",
        "industrial",
        "commercial",
        "broker",
        "buyer",
        "appraiser"
    ],
    "sg:website":"http://www.hockleycad.org",
    "wof:name":"County Of Hockley",
    "wof:placetype":"venue"
},
  "geometry": {"coordinates":[-102.40273999999999,33.587099],"type":"Point"}
}