{
  "type": "Feature",
  "properties": {
    "iso:country":"US",
    "sg:address":"5502 Cowhorn Creek Rd",
    "sg:city":"Texarkana",
    "sg:classifiers":[
        {
            "category":"Mining & Drilling",
            "type":"Manufacturing & Wholesale Goods"
        }
    ],
    "sg:phone":"+1 903 838 4493",
    "sg:postcode":"75503",
    "sg:province":"TX",
    "sg:tags":[
        "company",
        "mineral",
        "nonmetallic"
    ],
    "wof:name":"Sidco Mining Co",
    "wof:placetype":"venue"
},
  "geometry": {"coordinates":[-94.077961,33.471184],"type":"Point"}
}