{
  "type": "Feature",
  "properties": {
    "iso:country":"US",
    "sg:address":"13504 Wyoming Valley Dr",
    "sg:city":"Austin",
    "sg:classifiers":[
        {
            "category":"Restaurant",
            "type":"Food & Drink"
        }
    ],
    "sg:phone":"+1 512 989 1885",
    "sg:postcode":"78727",
    "sg:province":"TX",
    "sg:tags":[
        "eating"
    ],
    "wof:name":"Taqueria Restaurant Guadalajar",
    "wof:placetype":"venue"
},
  "geometry": {"coordinates":[-97.680736,30.424392],"type":"Point"}
}