{
  "type": "Feature",
  "properties": {
    "iso:country":"US",
    "sg:address":"10440 Ember Glen Dr",
    "sg:city":"Austin",
    "sg:classifiers":[
        {
            "category":"Manufacturing",
            "subcategory":"Metals",
            "type":"Manufacturing & Wholesale Goods"
        }
    ],
    "sg:phone":"+1 512 335 1121",
    "sg:postcode":"78726",
    "sg:province":"TX",
    "sg:tags":[
        "fabrication",
        "structural"
    ],
    "wof:name":"A 6 Labs Inc",
    "wof:placetype":"venue"
},
  "geometry": {"coordinates":[-97.830038,30.436612],"type":"Point"}
}