{
  "type": "Feature",
  "properties": {
    "iso:country":"US",
    "sg:address":"211 S Hwy 67",
    "sg:city":"Cedar Hill",
    "sg:classifiers":[
        {
            "category":"Retail",
            "subcategory":"Auto Repair",
            "type":"Services"
        }
    ],
    "sg:phone":"+1 972 291 7637",
    "sg:postcode":"75104",
    "sg:province":"TX",
    "sg:tags":[
        "repairing",
        "automobile"
    ],
    "wof:name":"Mike's Brake & Alignment",
    "wof:placetype":"venue"
},
  "geometry": {"coordinates":[-96.949383,32.587631],"type":"Point"}
}