{
  "type": "Feature",
  "properties": {
    "iso:country":"US",
    "sg:address":"2203 E University Dr",
    "sg:city":"Edinburg",
    "sg:classifiers":[
        {
            "category":"Social Services",
            "subcategory":"Child Care",
            "type":"Services"
        }
    ],
    "sg:phone":"+1 956 380 1641",
    "sg:postcode":"78539",
    "sg:province":"TX",
    "sg:tags":[
        "day"
    ],
    "wof:name":"Almost Home Childcare & Develo",
    "wof:placetype":"venue"
},
  "geometry": {"coordinates":[-98.139161,26.298152],"type":"Point"}
}