{
  "type": "Feature",
  "properties": {
    "iso:country":"US",
    "sg:address":"2025 Redwood Trl",
    "sg:city":"Grapevine",
    "sg:classifiers":[
        {
            "category":"Building & Trades",
            "subcategory":"Landscaping Services",
            "type":"Services"
        }
    ],
    "sg:phone":"+1 817 798 1742",
    "sg:postcode":"76051",
    "sg:province":"TX",
    "sg:tags":[
        "landscape"
    ],
    "wof:name":"Southern Dreamscapes",
    "wof:placetype":"venue"
},
  "geometry": {"coordinates":[-97.098044,32.947712],"type":"Point"}
}