{
  "type": "Feature",
  "properties": {
    "iso:country":"US",
    "sg:address":"303 Tower Dr",
    "sg:city":"San Antonio",
    "sg:classifiers":[
        {
            "category":"Building & Trades",
            "subcategory":"Construction",
            "type":"Services"
        }
    ],
    "sg:phone":"+1 210 494 1802",
    "sg:postcode":"78232",
    "sg:province":"TX",
    "wof:name":"Cook Construction Co",
    "wof:placetype":"venue"
},
  "geometry": {"coordinates":[-98.488035,29.588939],"type":"Point"}
}