{
  "type": "Feature",
  "properties": {
    "iso:country":"US",
    "sg:address":"118 Tigertail Rd",
    "sg:city":"San Antonio",
    "sg:classifiers":[
        {
            "category":"Organizations",
            "subcategory":"Political Organization",
            "type":"Services"
        }
    ],
    "sg:phone":"+1 210 490 8393",
    "sg:postcode":"78232",
    "sg:province":"TX",
    "wof:name":"Warepac",
    "wof:placetype":"venue"
},
  "geometry": {"coordinates":[-98.477566,29.600404],"type":"Point"}
}