{
  "type": "Feature",
  "properties": {
    "iso:country":"US",
    "sg:address":"4108 Catawba Ave",
    "sg:city":"Carrollton",
    "sg:classifiers":[
        {
            "category":"Professional",
            "subcategory":"Accounting & Tax Preparation",
            "type":"Services"
        }
    ],
    "sg:phone":"+1 972 394 8100",
    "sg:postcode":"75010",
    "sg:province":"TX",
    "sg:tags":[
        "accountant"
    ],
    "wof:name":"Briggs Toni L CPA",
    "wof:placetype":"venue"
},
  "geometry": {"coordinates":[-96.928363,33.023549],"type":"Point"}
}