{
  "type": "Feature",
  "properties": {
    "iso:country":"US",
    "sg:address":"3311 Cedar Village Dr",
    "sg:city":"Humble",
    "sg:classifiers":[
        {
            "category":"Professional",
            "subcategory":"Management & Consulting",
            "type":"Services"
        }
    ],
    "sg:phone":"+1 281 352 1149",
    "sg:postcode":"77345",
    "sg:province":"TX",
    "sg:tags":[
        "energy"
    ],
    "wof:name":"American Energy Consultants",
    "wof:placetype":"venue"
},
  "geometry": {"coordinates":[-95.176035,30.06368],"type":"Point"}
}