{
  "type": "Feature",
  "properties": {
    "iso:country":"US",
    "sg:address":"1144 Doy Dr",
    "sg:city":"El Paso",
    "sg:classifiers":[
        {
            "category":"Shopping",
            "subcategory":"Clothing, Apparel, & Fashions",
            "type":"Retail Goods"
        }
    ],
    "sg:phone":"+1 915 590 7747",
    "sg:postcode":"79927",
    "sg:province":"TX",
    "sg:tags":[
        "commercial",
        "uniform"
    ],
    "wof:name":"Uniform Technology Group LP",
    "wof:placetype":"venue"
},
  "geometry": {"coordinates":[-106.23451,31.661645],"type":"Point"}
}