{
  "type": "Feature",
  "properties": {
    "iso:country":"US",
    "sg:address":"30903 Coco St",
    "sg:city":"Cypress",
    "sg:classifiers":[
        {
            "category":"Freight",
            "type":"Transportation"
        }
    ],
    "sg:phone":"+1 281 373 4738",
    "sg:postcode":"77433",
    "sg:province":"TX",
    "sg:tags":[
        "operator",
        "local",
        "trucking"
    ],
    "wof:name":"M Saucedo Hauling",
    "wof:placetype":"venue"
},
  "geometry": {"coordinates":[-95.77817400000001,30.01097],"type":"Point"}
}