{
  "type": "Feature",
  "properties": {
    "iso:country":"US",
    "sg:address":"6630 Roxburgh Dr",
    "sg:city":"Houston",
    "sg:classifiers":[
        {
            "category":"Home & Garden",
            "subcategory":"Furniture",
            "type":"Retail Goods"
        }
    ],
    "sg:phone":"+1 713 983 7079",
    "sg:postcode":"77041",
    "sg:province":"TX",
    "sg:tags":[
        "custom",
        "accessory"
    ],
    "wof:name":"Norwalk The Furniture Idea",
    "wof:placetype":"venue"
},
  "geometry": {"coordinates":[-95.556091,29.864673],"type":"Point"}
}