{
  "type": "Feature",
  "properties": {
    "iso:country":"US",
    "sg:address":"913 N Carrier Pkwy",
    "sg:city":"Grand Prairie",
    "sg:classifiers":[
        {
            "category":"Wholesale",
            "subcategory":"Construction Materials",
            "type":"Manufacturing & Wholesale Goods"
        }
    ],
    "sg:phone":"+1 972 641 1817",
    "sg:postcode":"75050",
    "sg:province":"TX",
    "sg:tags":[
        "tile",
        "ceramic",
        "italian"
    ],
    "wof:name":"Casa Reale Ceramic Inc",
    "wof:placetype":"venue"
},
  "geometry": {"coordinates":[-97.017101,32.751908],"type":"Point"}
}