{
  "type": "Feature",
  "properties": {
    "iso:country":"US",
    "sg:address":"5818 Winding Ridge Dr",
    "sg:city":"San Antonio",
    "sg:classifiers":[
        {
            "category":"Home & Garden",
            "subcategory":"Home Furnishings",
            "type":"Retail Goods"
        }
    ],
    "sg:phone":"+1 210 657 4485",
    "sg:postcode":"78239",
    "sg:province":"TX",
    "sg:tags":[
        "installation",
        "drapery"
    ],
    "wof:name":"Drapery Handyman",
    "wof:placetype":"venue"
},
  "geometry": {"coordinates":[-98.375011,29.523348],"type":"Point"}
}