{
  "type": "Feature",
  "properties": {
    "iso:country":"US",
    "sg:address":"2304 Cypress Pt W",
    "sg:city":"Austin",
    "sg:classifiers":[
        {
            "category":"Professional",
            "subcategory":"Management & Consulting",
            "type":"Services"
        }
    ],
    "sg:phone":"+1 512 329 8930",
    "sg:postcode":"78746",
    "sg:province":"TX",
    "sg:tags":[
        "business"
    ],
    "wof:name":"Trusted Business Information",
    "wof:placetype":"venue"
},
  "geometry": {"coordinates":[-97.845563,30.278439],"type":"Point"}
}