{
  "type": "Feature",
  "properties": {
    "iso:country":"US",
    "sg:address":"1923 Alta Vista St",
    "sg:city":"Houston",
    "sg:classifiers":[
        {
            "category":"Shopping",
            "subcategory":"Jewelry",
            "type":"Retail Goods"
        }
    ],
    "sg:phone":"+1 713 921 4672",
    "sg:postcode":"77023",
    "sg:province":"TX",
    "wof:name":"Milian's Jewelry",
    "wof:placetype":"venue"
},
  "geometry": {"coordinates":[-95.299297,29.722142],"type":"Point"}
}