{
  "type": "Feature",
  "properties": {
    "iso:country":"US",
    "sg:address":"2500 Crenshaw Dr",
    "sg:city":"Round Rock",
    "sg:classifiers":[
        {
            "category":"Building & Trades",
            "subcategory":"Construction",
            "type":"Services"
        }
    ],
    "sg:phone":"+1 512 671 9809",
    "sg:postcode":"78664",
    "sg:province":"TX",
    "sg:tags":[
        "house"
    ],
    "wof:name":"Doyle Wilson Homebuilders",
    "wof:placetype":"venue"
},
  "geometry": {"coordinates":[-97.603959,30.514419],"type":"Point"}
}