{
  "type": "Feature",
  "properties": {
    "iso:country":"US",
    "sg:address":"3405 Amherst St",
    "sg:city":"Houston",
    "sg:classifiers":[
        {
            "category":"Professional",
            "type":"Services"
        }
    ],
    "sg:phone":"+1 713 660 6640",
    "sg:postcode":"77005",
    "sg:province":"TX",
    "wof:name":"Vida Y Casa Latina",
    "wof:placetype":"venue"
},
  "geometry": {"coordinates":[-95.431033,29.715901],"type":"Point"}
}