{
  "type": "Feature",
  "properties": {
    "iso:country":"US",
    "sg:address":"701 Hawthorne St",
    "sg:city":"Houston",
    "sg:classifiers":[
        {
            "category":"Professional",
            "subcategory":"Engineering",
            "type":"Services"
        }
    ],
    "sg:phone":"+1 713 528 1552",
    "sg:postcode":"77006",
    "sg:province":"TX",
    "sg:tags":[
        "engineer"
    ],
    "wof:name":"Daram Engineers Inc",
    "wof:placetype":"venue"
},
  "geometry": {"coordinates":[-95.38893899999999,29.742395],"type":"Point"}
}