{
  "type": "Feature",
  "properties": {
    "iso:country":"US",
    "sg:address":"921 English Rd",
    "sg:city":"Rockwall",
    "sg:classifiers":[
        {
            "category":"Building & Trades",
            "subcategory":"Construction",
            "type":"Services"
        }
    ],
    "sg:phone":"+1 972 524 8306",
    "sg:postcode":"75032",
    "sg:province":"TX",
    "sg:tags":[
        "house"
    ],
    "wof:name":"Lowell English Builders Inc",
    "wof:placetype":"venue"
},
  "geometry": {"coordinates":[-96.35190799999999,32.841826],"type":"Point"}
}