{
  "type": "Feature",
  "properties": {
    "iso:country":"US",
    "sg:address":"515 Fm 2821 Rd E",
    "sg:city":"Huntsville",
    "sg:classifiers":[
        {
            "category":"Education",
            "subcategory":"Music School",
            "type":"Public Place"
        },
        {
            "category":"Education",
            "subcategory":"School",
            "type":"Public Place"
        }
    ],
    "sg:phone":"+1 936 293 2624",
    "sg:postcode":"77320",
    "sg:province":"TX",
    "sg:tags":[
        "information"
    ],
    "wof:name":"Huntsville High School - Music Dept.",
    "wof:placetype":"venue"
},
  "geometry": {"coordinates":[-95.539225,30.742135],"type":"Point"}
}