{
  "type": "Feature",
  "properties": {
    "iso:country":"US",
    "sg:address":"2705 Hawes Ave",
    "sg:city":"Dallas",
    "sg:classifiers":[
        {
            "category":"Professional",
            "subcategory":"Management & Consulting",
            "type":"Services"
        }
    ],
    "sg:phone":"+1 214 353 2661",
    "sg:postcode":"75235",
    "sg:province":"TX",
    "sg:tags":[
        "food"
    ],
    "sg:website":"www.signatureservices.com",
    "wof:name":"Signature Services Corp",
    "wof:placetype":"venue"
},
  "geometry": {"coordinates":[-96.844976,32.829884],"type":"Point"}
}