{
  "type": "Feature",
  "properties": {
    "iso:country":"US",
    "sg:address":"4640 N Loop 289",
    "sg:city":"Lubbock",
    "sg:classifiers":[
        {
            "category":"Health Services",
            "subcategory":"Clinic",
            "type":"Services"
        }
    ],
    "sg:phone":"+1 806 749 5208",
    "sg:postcode":"79416",
    "sg:province":"TX",
    "sg:tags":[
        "surgical",
        "center"
    ],
    "sg:website":"www.northstarsurgicalcenter.net",
    "wof:name":"North Star Surgical Ctr",
    "wof:placetype":"venue"
},
  "geometry": {"coordinates":[-101.90875,33.605993],"type":"Point"}
}