{
  "type": "Feature",
  "properties": {
    "iso:country":"US",
    "sg:address":"3816 Fossil Creek Rd",
    "sg:city":"San Antonio",
    "sg:classifiers":[
        {
            "category":"Retail",
            "subcategory":"Auto Repair",
            "type":"Services"
        }
    ],
    "sg:phone":"+1 210 404 9019",
    "sg:postcode":"78261",
    "sg:province":"TX",
    "sg:tags":[
        "automotive"
    ],
    "wof:name":"Knot Weddingpages",
    "wof:placetype":"venue"
},
  "geometry": {"coordinates":[-98.422836,29.654426],"type":"Point"}
}