{
  "type": "Feature",
  "properties": {
    "iso:country":"US",
    "sg:address":"4609 South St",
    "sg:city":"Nacogdoches",
    "sg:classifiers":[
        {
            "category":"Home & Garden",
            "subcategory":"Mobile Homes",
            "type":"Retail Goods"
        }
    ],
    "sg:phone":"+1 936 564 6964",
    "sg:postcode":"75964",
    "sg:province":"TX",
    "wof:name":"CMH",
    "wof:placetype":"venue"
},
  "geometry": {"coordinates":[-94.678726,31.564048],"type":"Point"}
}