{
  "type": "Feature",
  "properties": {
    "iso:country":"US",
    "sg:address":"3100 Robin Rd",
    "sg:city":"Waco",
    "sg:classifiers":[
        {
            "category":"Government",
            "subcategory":"Court House",
            "type":"Public Place"
        }
    ],
    "sg:phone":"+1 254 753 3402",
    "sg:postcode":"76708",
    "sg:province":"TX",
    "sg:tags":[
        "justice"
    ],
    "wof:name":"United Grand Imperial Court",
    "wof:placetype":"venue"
},
  "geometry": {"coordinates":[-97.158569,31.580241],"type":"Point"}
}