{
  "type": "Feature",
  "properties": {
    "iso:country":"US",
    "sg:address":"900 N Grand Ave",
    "sg:city":"Gainesville",
    "sg:classifiers":[
        {
            "category":"Professional",
            "subcategory":"Management & Consulting",
            "type":"Services"
        },
        {
            "category":"Education",
            "subcategory":"Special Training",
            "type":"Public Place"
        }
    ],
    "sg:phone":"+1 940 665 5085",
    "sg:postcode":"76240",
    "sg:province":"TX",
    "sg:tags":[
        "consultant",
        "educational"
    ],
    "wof:name":"Education Plus",
    "wof:placetype":"venue"
},
  "geometry": {"coordinates":[-97.13337199999999,33.634574],"type":"Point"}
}