{
  "type": "Feature",
  "properties": {
    "iso:country":"US",
    "sg:address":"2205 Patricia Ln",
    "sg:city":"Port Neches",
    "sg:classifiers":[
        {
            "category":"Real Estate",
            "subcategory":"Real Estate Agent",
            "type":"Services"
        }
    ],
    "sg:phone":"+1 409 981 6066",
    "sg:postcode":"77651",
    "sg:province":"TX",
    "wof:name":"Hatfield Real Estate",
    "wof:placetype":"venue"
},
  "geometry": {"coordinates":[-93.955804,29.97044],"type":"Point"}
}