{
  "type": "Feature",
  "properties": {
    "iso:country":"US",
    "sg:address":"635 W 19th St",
    "sg:city":"Houston",
    "sg:classifiers":[
        {
            "category":"Personal",
            "type":"Services"
        },
        {
            "category":"Health Services",
            "subcategory":"Medical Lab",
            "type":"Services"
        }
    ],
    "sg:phone":"+1 713 869 8378",
    "sg:postcode":"77008",
    "sg:province":"TX",
    "sg:tags":[
        "testing",
        "paternity",
        "drug"
    ],
    "sg:website":"http://www.nationwidetestingsys.com/",
    "wof:name":"Nationwide Testing Systems",
    "wof:placetype":"venue"
},
  "geometry": {"coordinates":[-95.408756,29.802806],"type":"Point"}
}