{
  "type": "Feature",
  "properties": {
    "iso:country":"US",
    "sg:address":"10810 Eastex Fwy",
    "sg:city":"Houston",
    "sg:classifiers":[
        {
            "category":"Insurance",
            "subcategory":"Insurance Agent",
            "type":"Services"
        }
    ],
    "sg:phone":"+1 281 449 4111",
    "sg:postcode":"77093",
    "sg:province":"TX",
    "wof:name":"Farmers Insurance Group",
    "wof:placetype":"venue"
},
  "geometry": {"coordinates":[-95.32977200000001,29.871878],"type":"Point"}
}