{
  "type": "Feature",
  "properties": {
    "iso:country":"US",
    "sg:address":"525 Shoreview Dr",
    "sg:city":"Rockwall",
    "sg:classifiers":[
        {
            "category":"Home & Garden",
            "subcategory":"Building Materials",
            "type":"Retail Goods"
        }
    ],
    "sg:phone":"+1 972 771 3134",
    "sg:postcode":"75087",
    "sg:province":"TX",
    "wof:name":"Rockwall Garage Door",
    "wof:placetype":"venue"
},
  "geometry": {"coordinates":[-96.467432,32.924715],"type":"Point"}
}