{
  "type": "Feature",
  "properties": {
    "iso:country":"US",
    "sg:address":"1335 N Lydia Ave",
    "sg:city":"Stephenville",
    "sg:classifiers":[
        {
            "category":"Shopping",
            "subcategory":"Hobbies, Toys, & Games",
            "type":"Retail Goods"
        }
    ],
    "sg:phone":"+1 254 965 7801",
    "sg:postcode":"76401",
    "sg:province":"TX",
    "sg:tags":[
        "sporting"
    ],
    "wof:name":"D&R Ltd",
    "wof:placetype":"venue"
},
  "geometry": {"coordinates":[-98.23267,32.223375],"type":"Point"}
}