{
  "type": "Feature",
  "properties": {
    "iso:country":"US",
    "sg:address":"1129 Timberview Dr",
    "sg:city":"Bedford",
    "sg:classifiers":[
        {
            "category":"Building & Trades",
            "subcategory":"Construction",
            "type":"Services"
        }
    ],
    "sg:phone":"+1 817 428 8896",
    "sg:postcode":"76021",
    "sg:province":"TX",
    "sg:tags":[
        "residential"
    ],
    "wof:name":"Fred D Williams Inc",
    "wof:placetype":"venue"
},
  "geometry": {"coordinates":[-97.15029699999999,32.857632],"type":"Point"}
}