{
  "type": "Feature",
  "properties": {
    "iso:country":"US",
    "sg:address":"16961 FM 1314",
    "sg:city":"Conroe",
    "sg:classifiers":[
        {
            "category":"Wholesale",
            "subcategory":"Construction Materials",
            "type":"Manufacturing & Wholesale Goods"
        }
    ],
    "sg:phone":"+1 281 429 9150",
    "sg:postcode":"77302",
    "sg:province":"TX",
    "sg:tags":[
        "fence"
    ],
    "wof:name":"Avantage Ornamental Fence",
    "wof:placetype":"venue"
},
  "geometry": {"coordinates":[-95.353514,30.205688],"type":"Point"}
}