{
  "type": "Feature",
  "properties": {
    "iso:country":"US",
    "sg:address":"2911 Turtle Creek Blvd",
    "sg:city":"Dallas",
    "sg:classifiers":[
        {
            "category":"Professional",
            "subcategory":"Lawyer & Legal Services",
            "type":"Services"
        }
    ],
    "sg:phone":"+1 214 528 7977",
    "sg:postcode":"75219",
    "sg:province":"TX",
    "wof:name":"Cohen Janice E Atty/Consultnt",
    "wof:placetype":"venue"
},
  "geometry": {"coordinates":[-96.805598,32.803778],"type":"Point"}
}