{
  "type": "Feature",
  "properties": {
    "iso:country":"US",
    "sg:address":"4101 Old Brownsville Rd",
    "sg:city":"Corpus Christi",
    "sg:classifiers":[
        {
            "category":"Professional",
            "subcategory":"Employment Agencies",
            "type":"Services"
        }
    ],
    "sg:phone":"+1 361 888 6027",
    "sg:postcode":"78405",
    "sg:province":"TX",
    "sg:tags":[
        "opportunity"
    ],
    "wof:name":"Workforce Network Inc",
    "wof:placetype":"venue"
},
  "geometry": {"coordinates":[-97.438768,27.773743],"type":"Point"}
}