{
  "type": "Feature",
  "properties": {
    "iso:country":"US",
    "sg:address":"203 Glentower Dr",
    "sg:city":"San Antonio",
    "sg:classifiers":[
        {
            "category":"Professional",
            "type":"Services"
        }
    ],
    "sg:phone":"+1 210 530 0884",
    "sg:postcode":"78213",
    "sg:province":"TX",
    "wof:name":"Christine E Dextraze Cpcu CIC",
    "wof:placetype":"venue"
},
  "geometry": {"coordinates":[-98.509916,29.526803],"type":"Point"}
}