{
  "type": "Feature",
  "properties": {
    "iso:country":"US",
    "sg:address":"1600 Richmond Ave",
    "sg:city":"Mcallen",
    "sg:classifiers":[
        {
            "category":"Professional",
            "subcategory":"Engineering",
            "type":"Services"
        }
    ],
    "sg:phone":"+1 956 618 2202",
    "sg:postcode":"78503",
    "sg:province":"TX",
    "sg:tags":[
        "engineer"
    ],
    "wof:name":"Universal Engineering Corp",
    "wof:placetype":"venue"
},
  "geometry": {"coordinates":[-98.24140199999999,26.189518],"type":"Point"}
}