{
  "type": "Feature",
  "properties": {
    "iso:country":"US",
    "sg:address":"430 E Huisache Ave",
    "sg:city":"San Antonio",
    "sg:classifiers":[
        {
            "category":"Wholesale",
            "subcategory":"Durable Goods & Equipment",
            "type":"Manufacturing & Wholesale Goods"
        }
    ],
    "sg:phone":"+1 210 732 3033",
    "sg:postcode":"78212",
    "sg:province":"TX",
    "sg:tags":[
        "representative",
        "manufacturer"
    ],
    "wof:name":"Marketing Concepts",
    "wof:placetype":"venue"
},
  "geometry": {"coordinates":[-98.48499,29.455577],"type":"Point"}
}