{
  "type": "Feature",
  "properties": {
    "iso:country":"US",
    "sg:address":"14651 Dallas Pkwy Ste 130",
    "sg:city":"Dallas",
    "sg:classifiers":[
        {
            "category":"Professional",
            "subcategory":"Lawyer & Legal Services",
            "type":"Services"
        }
    ],
    "sg:phone":"+1 972 726 7400",
    "sg:postcode":"75254",
    "sg:province":"TX",
    "wof:name":"The Devadoss Law Firm PLLC",
    "wof:placetype":"venue"
},
  "geometry": {"coordinates":[-96.823746,32.947328],"type":"Point"}
}