{
  "type": "Feature",
  "properties": {
    "iso:country":"US",
    "sg:address":"7464 Dogwood Park",
    "sg:city":"Richland Hills",
    "sg:classifiers":[
        {
            "category":"Retail",
            "subcategory":"Repair Shop",
            "type":"Services"
        }
    ],
    "sg:phone":"+1 817 589 0011",
    "sg:postcode":"76118",
    "sg:province":"TX",
    "sg:tags":[
        "tool",
        "parts"
    ],
    "wof:name":"Metrology Resource Inc",
    "wof:placetype":"venue"
},
  "geometry": {"coordinates":[-97.22021700000001,32.80378],"type":"Point"}
}