{
  "type": "Feature",
  "properties": {
    "iso:country":"US",
    "sg:address":"3704 Yachtclub Dr",
    "sg:city":"Arlington",
    "sg:classifiers":[
        {
            "category":"Professional",
            "subcategory":"Lawyer & Legal Services",
            "type":"Services"
        }
    ],
    "sg:phone":"+1 817 561 1008",
    "sg:postcode":"76016",
    "sg:province":"TX",
    "sg:tags":[
        "attorney",
        "practice"
    ],
    "wof:name":"Jones, Jerry L Attorney At Law",
    "wof:placetype":"venue"
},
  "geometry": {"coordinates":[-97.210463,32.688682],"type":"Point"}
}