{
  "type": "Feature",
  "properties": {
    "iso:country":"US",
    "sg:address":"6007 Old Jacksboro Hwy",
    "sg:city":"Wichita Falls",
    "sg:classifiers":[
        {
            "category":"Wholesale",
            "subcategory":"Farm Supplies",
            "type":"Manufacturing & Wholesale Goods"
        },
        {
            "category":"Shopping",
            "type":"Retail Goods"
        }
    ],
    "sg:phone":"+1 940 761 1227",
    "sg:postcode":"76302",
    "sg:province":"TX",
    "sg:tags":[
        "pet",
        "food"
    ],
    "wof:name":"Feed & Garden Store The",
    "wof:placetype":"venue"
},
  "geometry": {"coordinates":[-98.49405400000001,33.852014],"type":"Point"}
}