{
  "type": "Feature",
  "properties": {
    "iso:country":"US",
    "sg:address":"4023 Singleton Blvd",
    "sg:city":"Dallas",
    "sg:classifiers":[
        {
            "category":"Manufacturing",
            "subcategory":"Metals",
            "type":"Manufacturing & Wholesale Goods"
        }
    ],
    "sg:phone":"+1 214 634 0211",
    "sg:postcode":"75212",
    "sg:province":"TX",
    "sg:tags":[
        "plate",
        "sheet",
        "mfg",
        "work",
        "fabricated",
        "metalwork"
    ],
    "wof:name":"Industrial Metal Specialties",
    "wof:placetype":"venue"
},
  "geometry": {"coordinates":[-96.888645,32.778973],"type":"Point"}
}