{
  "type": "Feature",
  "properties": {
    "iso:country":"US",
    "sg:address":"19134 Stone Oak Pkwy",
    "sg:city":"San Antonio",
    "sg:classifiers":[
        {
            "category":"Insurance",
            "subcategory":"Insurance Agent",
            "type":"Services"
        }
    ],
    "sg:phone":"+1 210 497 4488",
    "sg:postcode":"78258",
    "sg:province":"TX",
    "wof:name":"Optima Group",
    "wof:placetype":"venue"
},
  "geometry": {"coordinates":[-98.494873,29.62495],"type":"Point"}
}