{
  "type": "Feature",
  "properties": {
    "iso:country":"US",
    "sg:address":"9776 Harry Hines Blvd",
    "sg:city":"Dallas",
    "sg:classifiers":[
        {
            "category":"Restaurant",
            "type":"Food & Drink"
        }
    ],
    "sg:phone":"+1 214 350 8070",
    "sg:postcode":"75220",
    "sg:province":"TX",
    "sg:tags":[
        "eating"
    ],
    "wof:name":"B-J Coffee Shop",
    "wof:placetype":"venue"
},
  "geometry": {"coordinates":[-96.878969,32.854225],"type":"Point"}
}