{
  "type": "Feature",
  "properties": {
    "iso:country":"US",
    "sg:address":"909 W Cuthbert Ave",
    "sg:city":"Midland",
    "sg:classifiers":[
        {
            "category":"Banks & Credit Unions",
            "subcategory":"Bank",
            "type":"Services"
        }
    ],
    "sg:phone":"+1 432 682 8443",
    "sg:postcode":"79701",
    "sg:province":"TX",
    "sg:tags":[
        "personal",
        "institution"
    ],
    "wof:name":"Ridge Lane Capital Corp",
    "wof:placetype":"venue"
},
  "geometry": {"coordinates":[-102.087327,32.005553],"type":"Point"}
}