{
  "type": "Feature",
  "properties": {
    "iso:country":"US",
    "sg:address":"7509 South Fwy",
    "sg:city":"Houston",
    "sg:classifiers":[
        {
            "category":"Health Services",
            "subcategory":"Hospital",
            "type":"Services"
        },
        {
            "category":"Local Transit",
            "type":"Transportation"
        }
    ],
    "sg:phone":"+1 713 741 9540",
    "sg:postcode":"77021",
    "sg:province":"TX",
    "sg:tags":[
        "public",
        "ambulance"
    ],
    "sg:website":"http://www.amr.net",
    "wof:name":"American Medical Response Of Texas, Inc.",
    "wof:placetype":"venue"
},
  "geometry": {"coordinates":[-95.37849900000001,29.686393],"type":"Point"}
}