{
  "type": "Feature",
  "properties": {
    "iso:country":"US",
    "sg:address":"1910 S Broadway St",
    "sg:city":"Sulphur Springs",
    "sg:classifiers":[
        {
            "category":"Wholesale",
            "subcategory":"Farm Supplies",
            "type":"Manufacturing & Wholesale Goods"
        }
    ],
    "sg:phone":"+1 903 885 3311",
    "sg:postcode":"75482",
    "sg:province":"TX",
    "sg:tags":[
        "commission",
        "livestock"
    ],
    "wof:name":"Sulphur Springs Dairy Auction",
    "wof:placetype":"venue"
},
  "geometry": {"coordinates":[-95.597088,33.103309],"type":"Point"}
}