{
  "type": "Feature",
  "properties": {
    "iso:country":"US",
    "sg:address":"11431 Lockport Ln",
    "sg:city":"Mesquite",
    "sg:classifiers":[
        {
            "category":"Home & Garden",
            "subcategory":"Carpets & Floor Coverings",
            "type":"Retail Goods"
        }
    ],
    "sg:phone":"+1 214 681 5357",
    "sg:postcode":"75180",
    "sg:province":"TX",
    "sg:tags":[
        "flooring",
        "contractor"
    ],
    "wof:name":"Up Town Flooring",
    "wof:placetype":"venue"
},
  "geometry": {"coordinates":[-96.630852,32.70204],"type":"Point"}
}