{
  "type": "Feature",
  "properties": {
    "iso:country":"US",
    "sg:address":"3100 Avon Dr",
    "sg:city":"Arlington",
    "sg:classifiers":[
        {
            "category":"Professional",
            "subcategory":"Accounting & Tax Preparation",
            "type":"Services"
        }
    ],
    "sg:phone":"+1 817 860 1866",
    "sg:postcode":"76015",
    "sg:province":"TX",
    "wof:name":"American Soc Women Accountants",
    "wof:placetype":"venue"
},
  "geometry": {"coordinates":[-97.148628,32.692886],"type":"Point"}
}