{
  "type": "Feature",
  "properties": {
    "iso:country":"US",
    "sg:address":"11325 I- 37",
    "sg:city":"Corpus Christi",
    "sg:classifiers":[
        {
            "category":"Building & Trades",
            "subcategory":"Plumbing",
            "type":"Services"
        }
    ],
    "sg:phone":"+1 361 242 8833",
    "sg:postcode":"78410",
    "sg:province":"TX",
    "sg:tags":[
        "contractor"
    ],
    "wof:name":"Con Tech Contracting",
    "wof:placetype":"venue"
},
  "geometry": {"coordinates":[-97.586224,27.851365],"type":"Point"}
}