{
  "type": "Feature",
  "properties": {
    "iso:country":"US",
    "sg:address":"3043 Gessner Dr",
    "sg:city":"Houston",
    "sg:classifiers":[
        {
            "category":"Health Services",
            "subcategory":"Clinic",
            "type":"Services"
        },
        {
            "category":"Health Services",
            "subcategory":"Hospital",
            "type":"Services"
        }
    ],
    "sg:phone":"+1 713 939 7272",
    "sg:postcode":"77080",
    "sg:province":"TX",
    "sg:tags":[
        "medical",
        "rehabilitation"
    ],
    "sg:website":"http://www.mhparc.org",
    "wof:name":"Memorial Hermann PaRC Prevention & Recovery Center",
    "wof:placetype":"venue"
},
  "geometry": {"coordinates":[-95.54541,29.827916],"type":"Point"}
}