{
  "type": "Feature",
  "properties": {
    "iso:country":"US",
    "sg:address":"2001 Coit Rd",
    "sg:city":"Plano",
    "sg:classifiers":[
        {
            "category":"Retail",
            "subcategory":"Repair Shop",
            "type":"Services"
        }
    ],
    "sg:phone":"+1 972 612 9748",
    "sg:postcode":"75075",
    "sg:province":"TX",
    "sg:tags":[
        "miscellaneous"
    ],
    "wof:name":"A J Electronics-T V V C R Repr",
    "wof:placetype":"venue"
},
  "geometry": {"coordinates":[-96.77015,33.026854],"type":"Point"}
}