{
  "type": "Feature",
  "properties": {
    "iso:country":"US",
    "sg:address":"3415 Ledgestone Dr",
    "sg:city":"Houston",
    "sg:classifiers":[
        {
            "category":"Building & Trades",
            "subcategory":"Construction",
            "type":"Services"
        }
    ],
    "sg:phone":"+1 281 488 1890",
    "sg:postcode":"77059",
    "sg:province":"TX",
    "sg:tags":[
        "home",
        "general",
        "contractor"
    ],
    "wof:name":"Kingston Construction",
    "wof:placetype":"venue"
},
  "geometry": {"coordinates":[-95.10369799999999,29.588118],"type":"Point"}
}