{
  "type": "Feature",
  "properties": {
    "iso:country":"US",
    "sg:address":"6810 FM 2403",
    "sg:city":"Alvin",
    "sg:classifiers":[
        {
            "category":"Retail",
            "subcategory":"Animal Services",
            "type":"Services"
        }
    ],
    "sg:phone":"+1 281 585 5090",
    "sg:postcode":"77511",
    "sg:province":"TX",
    "wof:name":"Doggie Doos MBL Pet Grooming",
    "wof:placetype":"venue"
},
  "geometry": {"coordinates":[-95.25905899999999,29.329173],"type":"Point"}
}