{
  "type": "Feature",
  "properties": {
    "iso:country":"US",
    "sg:address":"2323 N Henderson Ave Ste 105",
    "sg:city":"Dallas",
    "sg:classifiers":[
        {
            "category":"Ice Cream",
            "type":"Food & Drink"
        }
    ],
    "sg:phone":"+1 214 823 1707",
    "sg:postcode":"75206",
    "sg:province":"TX",
    "sg:tags":[
        "frozen",
        "yogurt"
    ],
    "sg:website":"www.natsumiusa.com",
    "wof:name":"Natsumi",
    "wof:placetype":"venue"
},
  "geometry": {"coordinates":[-96.778018,32.814438],"type":"Point"}
}