{
  "type": "Feature",
  "properties": {
    "iso:country":"US",
    "sg:address":"10214 Sagerock Dr",
    "sg:city":"Houston",
    "sg:classifiers":[
        {
            "category":"Home & Garden",
            "subcategory":"Building Materials",
            "type":"Retail Goods"
        }
    ],
    "sg:phone":"+1 281 922 4673",
    "sg:postcode":"77089",
    "sg:province":"TX",
    "wof:name":"Enchanted Stained Glass",
    "wof:placetype":"venue"
},
  "geometry": {"coordinates":[-95.22855300000001,29.581479],"type":"Point"}
}