{
  "type": "Feature",
  "properties": {
    "iso:country":"US",
    "sg:address":"4624 Prewett Rd",
    "sg:city":"Fort Worth",
    "sg:classifiers":[
        {
            "category":"Manufacturing",
            "subcategory":"Signs",
            "type":"Manufacturing & Wholesale Goods"
        }
    ],
    "sg:phone":"+1 817 514 0505",
    "sg:postcode":"76137",
    "sg:province":"TX",
    "wof:name":"Signmasters Electric & Lghtng",
    "wof:placetype":"venue"
},
  "geometry": {"coordinates":[-97.28418600000001,32.877738],"type":"Point"}
}