{
  "type": "Feature",
  "properties": {
    "iso:country":"US",
    "sg:address":"1829 S Good Latimer Expy",
    "sg:city":"Dallas",
    "sg:classifiers":[
        {
            "category":"Restaurant",
            "type":"Food & Drink"
        }
    ],
    "sg:phone":"+1 214 428 3584",
    "sg:postcode":"75226",
    "sg:province":"TX",
    "sg:tags":[
        "eating"
    ],
    "wof:name":"Mr Charlie's Hamburgers",
    "wof:placetype":"venue"
},
  "geometry": {"coordinates":[-96.7808,32.774899],"type":"Point"}
}