{
  "type": "Feature",
  "properties": {
    "iso:country":"US",
    "sg:address":"3100 June St",
    "sg:city":"Killeen",
    "sg:classifiers":[
        {
            "category":"Social Services",
            "subcategory":"Child Care",
            "type":"Services"
        }
    ],
    "sg:phone":"+1 254 690 6551",
    "sg:postcode":"76543",
    "sg:province":"TX",
    "sg:tags":[
        "day"
    ],
    "wof:name":"McPherson Learning House",
    "wof:placetype":"venue"
},
  "geometry": {"coordinates":[-97.70586299999999,31.099677],"type":"Point"}
}