{
  "type": "Feature",
  "properties": {
    "iso:country":"US",
    "sg:address":"2318 Munger St",
    "sg:city":"Houston",
    "sg:classifiers":[
        {
            "category":"Professional",
            "type":"Services"
        }
    ],
    "sg:phone":"+1 713 921 7374",
    "sg:postcode":"77023",
    "sg:province":"TX",
    "wof:name":"Magdaleno Llanas",
    "wof:placetype":"venue"
},
  "geometry": {"coordinates":[-95.324319,29.718248],"type":"Point"}
}