{
  "type": "Feature",
  "properties": {
    "iso:country":"US",
    "sg:address":"106 Portaleza Ave",
    "sg:city":"Roma",
    "sg:classifiers":[
        {
            "category":"Health Services",
            "subcategory":"Hospital",
            "type":"Services"
        }
    ],
    "sg:phone":"+1 956 849 9620",
    "sg:postcode":"78584",
    "sg:province":"TX",
    "sg:tags":[
        "mental"
    ],
    "wof:name":"M & M Behavioral Health Cnslnt",
    "wof:placetype":"venue"
},
  "geometry": {"coordinates":[-98.992402,26.402044],"type":"Point"}
}