{
  "type": "Feature",
  "properties": {
    "iso:country":"US",
    "sg:address":"236 S Hwy 67",
    "sg:city":"Cedar Hill",
    "sg:classifiers":[
        {
            "category":"Shopping",
            "subcategory":"Clothing, Apparel, & Fashions",
            "type":"Retail Goods"
        }
    ],
    "sg:phone":"+1 972 293 7572",
    "sg:postcode":"75104",
    "sg:province":"TX",
    "sg:tags":[
        "uniform"
    ],
    "wof:name":"C C's Uniforms",
    "wof:placetype":"venue"
},
  "geometry": {"coordinates":[-96.946355,32.589091],"type":"Point"}
}