{
  "type": "Feature",
  "properties": {
    "iso:country":"US",
    "sg:address":"3001 Alton Rd",
    "sg:city":"Fort Worth",
    "sg:classifiers":[
        {
            "category":"Banks & Credit Unions",
            "subcategory":"Financial Services",
            "type":"Services"
        }
    ],
    "sg:phone":"+1 817 927 7469",
    "sg:postcode":"76109",
    "sg:province":"TX",
    "sg:tags":[
        "company",
        "holding"
    ],
    "wof:name":"Whm Holdings Ltd",
    "wof:placetype":"venue"
},
  "geometry": {"coordinates":[-97.370143,32.706091],"type":"Point"}
}