{
  "type": "Feature",
  "properties": {
    "iso:country":"US",
    "sg:address":"6360 Lyndon B Johnson Fwy",
    "sg:city":"Dallas",
    "sg:classifiers":[
        {
            "category":"Professional",
            "subcategory":"Lawyer & Legal Services",
            "type":"Services"
        }
    ],
    "sg:phone":"+1 972 233 4100",
    "sg:postcode":"75240",
    "sg:province":"TX",
    "wof:name":"Cohen Rick L",
    "wof:placetype":"venue"
},
  "geometry": {"coordinates":[-96.79650100000001,32.9244],"type":"Point"}
}