{
  "type": "Feature",
  "properties": {
    "iso:country":"US",
    "sg:address":"18838 S Memorial Dr",
    "sg:city":"Humble",
    "sg:classifiers":[
        {
            "category":"Professional",
            "subcategory":"Accounting & Tax Preparation",
            "type":"Services"
        }
    ],
    "sg:phone":"+1 281 446 1506",
    "sg:postcode":"77338",
    "sg:province":"TX",
    "wof:name":"Doctors Admin Services Inc",
    "wof:placetype":"venue"
},
  "geometry": {"coordinates":[-95.275915,29.993251],"type":"Point"}
}