{
  "type": "Feature",
  "properties": {
    "iso:country":"US",
    "sg:address":"201 E San Antonio St",
    "sg:city":"Lockhart",
    "sg:classifiers":[
        {
            "category":"Government",
            "subcategory":"Court House",
            "type":"Public Place"
        }
    ],
    "sg:phone":"+1 512 398 1811",
    "sg:postcode":"78644",
    "sg:province":"TX",
    "sg:tags":[
        "county",
        "counsel"
    ],
    "wof:name":"Caldwell County Dist Attorney",
    "wof:placetype":"venue"
},
  "geometry": {"coordinates":[-97.672274,29.884789],"type":"Point"}
}