{
  "type": "Feature",
  "properties": {
    "iso:country":"US",
    "sg:address":"608 E Blanco Rd",
    "sg:city":"Boerne",
    "sg:classifiers":[
        {
            "category":"Professional",
            "subcategory":"Advertising",
            "type":"Services"
        }
    ],
    "sg:phone":"+1 830 249 1892",
    "sg:postcode":"78006",
    "sg:province":"TX",
    "sg:tags":[
        "mailing",
        "shipping"
    ],
    "wof:name":"UPS/Boerne Business Ctr",
    "wof:placetype":"venue"
},
  "geometry": {"coordinates":[-98.72824199999999,29.796137],"type":"Point"}
}