{
  "type": "Feature",
  "properties": {
    "iso:country":"US",
    "sg:address":"1815 N Washington Ave",
    "sg:city":"Odessa",
    "sg:classifiers":[
        {
            "category":"Real Estate",
            "subcategory":"Architect",
            "type":"Services"
        }
    ],
    "sg:phone":"+1 432 582 0333",
    "sg:postcode":"79761",
    "sg:province":"TX",
    "wof:name":"A Dc Arch Developers Contr",
    "wof:placetype":"venue"
},
  "geometry": {"coordinates":[-102.382716,31.858601],"type":"Point"}
}