{
  "type": "Feature",
  "properties": {
    "iso:country":"US",
    "sg:address":"851 Cincinnati Ave",
    "sg:city":"San Antonio",
    "sg:classifiers":[
        {
            "category":"Bars & Pubs",
            "type":"Food & Drink"
        }
    ],
    "sg:phone":"+1 210 731 9370",
    "sg:postcode":"78201",
    "sg:province":"TX",
    "sg:tags":[
        "club",
        "night"
    ],
    "wof:name":"Sombras Night Club",
    "wof:placetype":"venue"
},
  "geometry": {"coordinates":[-98.52338899999999,29.449487],"type":"Point"}
}