{
  "type": "Feature",
  "properties": {
    "iso:country":"US",
    "sg:address":"2126 Sam Houston Ave",
    "sg:city":"Huntsville",
    "sg:classifiers":[
        {
            "category":"Retail",
            "subcategory":"Auto Repair",
            "type":"Services"
        }
    ],
    "sg:phone":"+1 936 295 3021",
    "sg:postcode":"77320",
    "sg:province":"TX",
    "sg:tags":[
        "repairing",
        "automobile",
        "automotive",
        "general"
    ],
    "wof:name":"Martinez Garage & Wrecker Inc",
    "wof:placetype":"venue"
},
  "geometry": {"coordinates":[-95.551317,30.712395],"type":"Point"}
}