{
  "type": "Feature",
  "properties": {
    "iso:country":"US",
    "sg:address":"23977 N FM 95",
    "sg:city":"Garrison",
    "sg:classifiers":[
        {
            "category":"Mining & Drilling",
            "type":"Manufacturing & Wholesale Goods"
        }
    ],
    "sg:phone":"+1 936 347 2904",
    "sg:postcode":"75946",
    "sg:province":"TX",
    "sg:tags":[
        "well"
    ],
    "wof:name":"T5 Directional Boring",
    "wof:placetype":"venue"
},
  "geometry": {"coordinates":[-94.497052,31.807245],"type":"Point"}
}