{
  "type": "Feature",
  "properties": {
    "iso:country":"US",
    "sg:address":"7171 Buffalo Gap Rd",
    "sg:city":"Abilene",
    "sg:classifiers":[
        {
            "category":"Health Services",
            "subcategory":"Nursing And Care Facility",
            "type":"Services"
        }
    ],
    "sg:phone":"+1 432 292 8080",
    "sg:postcode":"79606",
    "sg:province":"TX",
    "sg:tags":[
        "center"
    ],
    "wof:name":"Mesa Springs Healthcare Center",
    "wof:placetype":"venue"
},
  "geometry": {"coordinates":[-99.781136,32.363547],"type":"Point"}
}