{
  "type": "Feature",
  "properties": {
    "iso:country":"US",
    "sg:address":"12033 Crockett Martin Rd",
    "sg:city":"Conroe",
    "sg:classifiers":[
        {
            "category":"Farming",
            "subcategory":"Livestock Farm",
            "type":"Manufacturing & Wholesale Goods"
        }
    ],
    "sg:phone":"+1 936 446 2127",
    "sg:postcode":"77306",
    "sg:province":"TX",
    "sg:tags":[
        "hog",
        "or",
        "feedlot"
    ],
    "wof:name":"Lazy J Farms",
    "wof:placetype":"venue"
},
  "geometry": {"coordinates":[-95.306521,30.276887],"type":"Point"}
}