{
  "type": "Feature",
  "properties": {
    "iso:country":"US",
    "sg:address":"220 N Story Rd",
    "sg:city":"Irving",
    "sg:classifiers":[
        {
            "category":"Building & Trades",
            "subcategory":"Construction",
            "type":"Services"
        },
        {
            "category":"Professional",
            "subcategory":"Accounting & Tax Preparation",
            "type":"Services"
        }
    ],
    "sg:phone":"+1 972 399 2070",
    "sg:postcode":"75061",
    "sg:province":"TX",
    "sg:tags":[
        "restoration",
        "cleaning",
        "patio",
        "deck"
    ],
    "wof:name":"Red River Management",
    "wof:placetype":"venue"
},
  "geometry": {"coordinates":[-96.976322,32.816433],"type":"Point"}
}