{
  "type": "Feature",
  "properties": {
    "iso:country":"US",
    "sg:address":"2419 S Austin Ave",
    "sg:city":"Pearland",
    "sg:classifiers":[
        {
            "category":"Professional",
            "subcategory":"Business Services",
            "type":"Services"
        }
    ],
    "sg:phone":"+1 281 485 5513",
    "sg:postcode":"77581",
    "sg:province":"TX",
    "sg:tags":[
        "inspection"
    ],
    "wof:name":"Cobb Fendley Inspector",
    "wof:placetype":"venue"
},
  "geometry": {"coordinates":[-95.292513,29.563204],"type":"Point"}
}