{
  "type": "Feature",
  "properties": {
    "iso:country":"US",
    "sg:address":"10203 E Northwest Hwy",
    "sg:city":"Dallas",
    "sg:classifiers":[
        {
            "category":"Utilities",
            "subcategory":"Mobile Phone",
            "type":"Services"
        }
    ],
    "sg:phone":"+1 214 221 8868",
    "sg:postcode":"75238",
    "sg:province":"TX",
    "sg:tags":[
        "telephone",
        "cellular"
    ],
    "wof:name":"Wireless Point",
    "wof:placetype":"venue"
},
  "geometry": {"coordinates":[-96.7107,32.864407],"type":"Point"}
}