{
  "type": "Feature",
  "properties": {
    "iso:country":"US",
    "sg:address":"1106 W 38th St Ste 200",
    "sg:city":"Austin",
    "sg:classifiers":[
        {
            "category":"Fast Food",
            "type":"Food & Drink"
        },
        {
            "category":"Restaurant",
            "type":"Food & Drink"
        },
        {
            "category":"Food & Beverages",
            "subcategory":"Bakery",
            "type":"Retail Goods"
        }
    ],
    "sg:phone":"+1 512 451 5245",
    "sg:postcode":"78705",
    "sg:province":"TX",
    "sg:tags":[
        "traditional",
        "burger",
        "american",
        "sandwich"
    ],
    "sg:website":"www.waterlooicehouse.com/",
    "wof:name":"Waterloo Ice House",
    "wof:placetype":"venue"
},
  "geometry": {"coordinates":[-97.744283,30.305876],"type":"Point"}
}