{
  "type": "Feature",
  "properties": {
    "iso:country":"US",
    "sg:address":"914 Walger Ave",
    "sg:city":"Rosenberg",
    "sg:classifiers":[
        {
            "category":"Retail",
            "subcategory":"Animal Services",
            "type":"Services"
        }
    ],
    "sg:phone":"+1 281 232 2341",
    "sg:postcode":"77471",
    "sg:province":"TX",
    "wof:name":"Preferred Pet Sitters",
    "wof:placetype":"venue"
},
  "geometry": {"coordinates":[-95.817922,29.548961],"type":"Point"}
}