{
  "type": "Feature",
  "properties": {
    "iso:country":"US",
    "sg:address":"739 Highway 71 W",
    "sg:city":"Bastrop",
    "sg:classifiers":[
        {
            "category":"Shopping",
            "subcategory":"Tobacco",
            "type":"Retail Goods"
        },
        {
            "category":"Bars & Pubs",
            "subcategory":"Lounge",
            "type":"Food & Drink"
        },
        {
            "category":"Food & Beverages",
            "subcategory":"Liquor & Beverages",
            "type":"Retail Goods"
        },
        {
            "category":"Wholesale",
            "subcategory":"Wine & Distilled Alcoholic Beverages",
            "type":"Manufacturing & Wholesale Goods"
        }
    ],
    "sg:phone":"+1 512 308 0250",
    "sg:postcode":"78602",
    "sg:province":"TX",
    "sg:tags":[
        "cigar",
        "cocktail",
        "ale",
        "broker",
        "cigarette",
        "beer",
        "store"
    ],
    "sg:website":"http://www.specsonline.com",
    "wof:name":"Specs Liquors",
    "wof:placetype":"venue"
},
  "geometry": {"coordinates":[-97.2663,30.093622],"type":"Point"}
}