{
  "type": "Feature",
  "properties": {
    "iso:country":"US",
    "sg:address":"1117 S Tripp Ave",
    "sg:city":"Odessa",
    "sg:classifiers":[
        {
            "category":"Manufacturing",
            "subcategory":"Tools & Machinery",
            "type":"Manufacturing & Wholesale Goods"
        }
    ],
    "sg:phone":"+1 432 381 5542",
    "sg:postcode":"79763",
    "sg:province":"TX",
    "sg:tags":[
        "field",
        "plate",
        "work",
        "fabricated",
        "mfg"
    ],
    "wof:name":"Pbp Fabrication Inc",
    "wof:placetype":"venue"
},
  "geometry": {"coordinates":[-102.464876,31.798528],"type":"Point"}
}