{
  "type": "Feature",
  "properties": {
    "iso:country":"US",
    "sg:address":"702 Arpege Cir",
    "sg:city":"Dallas",
    "sg:classifiers":[
        {
            "category":"Building & Trades",
            "subcategory":"Construction",
            "type":"Services"
        }
    ],
    "sg:phone":"+1 214 766 1236",
    "sg:postcode":"75224",
    "sg:province":"TX",
    "sg:tags":[
        "roofing",
        "consultant",
        "contractor"
    ],
    "wof:name":"Spanish Roofing & Remodeling",
    "wof:placetype":"venue"
},
  "geometry": {"coordinates":[-96.836219,32.705592],"type":"Point"}
}