{
  "type": "Feature",
  "properties": {
    "iso:country":"US",
    "sg:address":"1553 Bennett Ave",
    "sg:city":"Tyler",
    "sg:classifiers":[
        {
            "category":"Freight",
            "type":"Transportation"
        }
    ],
    "sg:phone":"+1 903 531 0023",
    "sg:postcode":"75701",
    "sg:province":"TX",
    "sg:tags":[
        "operator",
        "trucking"
    ],
    "wof:name":"Overnite Transportation Co",
    "wof:placetype":"venue"
},
  "geometry": {"coordinates":[-95.336799,32.333335],"type":"Point"}
}