{
  "type": "Feature",
  "properties": {
    "iso:country":"US",
    "sg:address":"13052 Trail Hollow Dr",
    "sg:city":"Houston",
    "sg:classifiers":[
        {
            "category":"Real Estate",
            "subcategory":"Real Estate Services",
            "type":"Services"
        }
    ],
    "sg:phone":"+1 713 465 9877",
    "sg:postcode":"77079",
    "sg:province":"TX",
    "sg:tags":[
        "management",
        "property"
    ],
    "wof:name":"Garza-McNamee Insurance Agency",
    "wof:placetype":"venue"
},
  "geometry": {"coordinates":[-95.5672,29.7791],"type":"Point"}
}