{
  "type": "Feature",
  "properties": {
    "iso:country":"US",
    "sg:address":"15984 FM 3083",
    "sg:city":"Grangerland",
    "sg:classifiers":[
        {
            "category":"Home & Garden",
            "subcategory":"Hardware",
            "type":"Retail Goods"
        }
    ],
    "sg:phone":"+1 936 231 2721",
    "sg:postcode":"77302",
    "sg:province":"TX",
    "wof:name":"Granger Hardware",
    "wof:placetype":"venue"
},
  "geometry": {"coordinates":[-95.32855600000001,30.251079],"type":"Point"}
}