{
  "type": "Feature",
  "properties": {
    "iso:country":"US",
    "sg:address":"7970 N Mesa St",
    "sg:city":"El Paso",
    "sg:classifiers":[
        {
            "category":"Shopping",
            "subcategory":"Department Store",
            "type":"Retail Goods"
        },
        {
            "category":"Shopping",
            "subcategory":"Optician",
            "type":"Retail Goods"
        }
    ],
    "sg:phone":"+1 915 833 1229",
    "sg:postcode":"79932",
    "sg:province":"TX",
    "sg:tags":[
        "eyewear"
    ],
    "wof:name":"Sam's Optical",
    "wof:placetype":"venue"
},
  "geometry": {"coordinates":[-106.577003,31.8407],"type":"Point"}
}