{
  "type": "Feature",
  "properties": {
    "iso:country":"US",
    "sg:address":"1837 N Main St",
    "sg:city":"Pearland",
    "sg:classifiers":[
        {
            "category":"Restaurant",
            "type":"Food & Drink"
        }
    ],
    "sg:phone":"+1 281 412 4165",
    "sg:postcode":"77581",
    "sg:province":"TX",
    "wof:name":"Taqueria Arandas",
    "wof:placetype":"venue"
},
  "geometry": {"coordinates":[-95.286098,29.571606],"type":"Point"}
}