{
  "type": "Feature",
  "properties": {
    "iso:country":"US",
    "sg:address":"641 Navy Dr",
    "sg:city":"Corpus Christi",
    "sg:classifiers":[
        {
            "category":"Real Estate",
            "subcategory":"Real Estate Agent",
            "type":"Services"
        }
    ],
    "sg:phone":"+1 361 937 3147",
    "sg:postcode":"78418",
    "sg:province":"TX",
    "wof:name":"Happy Homes Realty",
    "wof:placetype":"venue"
},
  "geometry": {"coordinates":[-97.27715600000001,27.67834],"type":"Point"}
}