{
  "type": "Feature",
  "properties": {
    "iso:country":"US",
    "sg:address":"6559 N Mesa St",
    "sg:city":"El Paso",
    "sg:classifiers":[
        {
            "category":"Professional",
            "subcategory":"Management & Consulting",
            "type":"Services"
        }
    ],
    "sg:phone":"+1 915 581 9797",
    "sg:postcode":"79912",
    "sg:province":"TX",
    "sg:tags":[
        "accident",
        "reconstruction"
    ],
    "wof:name":"West Mesa Management Inc",
    "wof:placetype":"venue"
},
  "geometry": {"coordinates":[-106.53819900000001,31.833108],"type":"Point"}
}