{
  "type": "Feature",
  "properties": {
    "iso:country":"US",
    "sg:address":"210 W Live Oak",
    "sg:city":"Joaquin",
    "sg:classifiers":[
        {
            "category":"Government",
            "subcategory":"Office",
            "type":"Public Place"
        }
    ],
    "sg:phone":"+1 830 379 0931",
    "sg:postcode":"75979",
    "sg:province":"TX",
    "sg:tags":[
        "bus",
        "dir"
    ],
    "wof:name":"Farm Service Agency",
    "wof:placetype":"venue"
},
  "geometry": {"coordinates":[-94.41664,30.772556],"type":"Point"}
}