{
  "type": "Feature",
  "properties": {
    "iso:country":"US",
    "sg:address":"1209 Energy Dr",
    "sg:city":"Abilene",
    "sg:classifiers":[
        {
            "category":"Wholesale",
            "subcategory":"Machinery & Supplies",
            "type":"Manufacturing & Wholesale Goods"
        },
        {
            "category":"Mining & Drilling",
            "type":"Manufacturing & Wholesale Goods"
        }
    ],
    "sg:phone":"+1 325 695 5420",
    "sg:postcode":"79602",
    "sg:province":"TX",
    "sg:tags":[
        "equipment",
        "oil",
        "specialty",
        "field"
    ],
    "wof:name":"Lancaster Specialties Inc",
    "wof:placetype":"venue"
},
  "geometry": {"coordinates":[-99.73798499999999,32.398834],"type":"Point"}
}