{
  "type": "Feature",
  "properties": {
    "iso:country":"US",
    "sg:address":"1219 E 8th St",
    "sg:city":"Odessa",
    "sg:classifiers":[
        {
            "category":"Food & Beverages",
            "subcategory":"Bakery",
            "type":"Retail Goods"
        }
    ],
    "sg:phone":"+1 432 332 9916",
    "sg:postcode":"79761",
    "sg:province":"TX",
    "sg:tags":[
        "baker"
    ],
    "wof:name":"D J's Cakes",
    "wof:placetype":"venue"
},
  "geometry": {"coordinates":[-102.359538,31.857272],"type":"Point"}
}