{
  "type": "Feature",
  "properties": {
    "iso:country":"US",
    "sg:address":"13239 Bellaire Blvd",
    "sg:city":"Houston",
    "sg:classifiers":[
        {
            "category":"Social Services",
            "subcategory":"Child Care",
            "type":"Services"
        }
    ],
    "sg:phone":"+1 281 498 4498",
    "sg:postcode":"77083",
    "sg:province":"TX",
    "wof:name":"Allbright Academy",
    "wof:placetype":"venue"
},
  "geometry": {"coordinates":[-95.615601,29.70345],"type":"Point"}
}