{
  "type": "Feature",
  "properties": {
    "iso:country":"US",
    "sg:address":"1649 Bonnie View Rd",
    "sg:city":"Dallas",
    "sg:classifiers":[
        {
            "category":"Organizations",
            "subcategory":"Professional Association",
            "type":"Services"
        }
    ],
    "sg:phone":"+1 214 942 4546",
    "sg:postcode":"75203",
    "sg:province":"TX",
    "wof:name":"Pop Warner Football Assn",
    "wof:placetype":"venue"
},
  "geometry": {"coordinates":[-96.79089399999999,32.727442],"type":"Point"}
}