{
  "type": "Feature",
  "properties": {
    "iso:country":"US",
    "sg:address":"9022 Co Rd 2193",
    "sg:city":"Whitehouse",
    "sg:classifiers":[
        {
            "category":"Retail",
            "subcategory":"Animal Services",
            "type":"Services"
        }
    ],
    "sg:phone":"+1 903 839 2267",
    "sg:postcode":"75791",
    "sg:province":"TX",
    "wof:name":"Country Clippers",
    "wof:placetype":"venue"
},
  "geometry": {"coordinates":[-95.25523099999999,32.232873],"type":"Point"}
}