{
  "type": "Feature",
  "properties": {
    "iso:country":"US",
    "sg:address":"806 Delia Ct",
    "sg:city":"Arlington",
    "sg:classifiers":[
        {
            "category":"Manufacturing",
            "subcategory":"Buildings",
            "type":"Manufacturing & Wholesale Goods"
        },
        {
            "category":"Building & Trades",
            "subcategory":"Construction",
            "type":"Services"
        }
    ],
    "sg:phone":"+1 817 801 9289",
    "sg:postcode":"76012",
    "sg:province":"TX",
    "sg:tags":[
        "home",
        "builder",
        "contractor"
    ],
    "wof:name":"Southern Home Company",
    "wof:placetype":"venue"
},
  "geometry": {"coordinates":[-97.11606399999999,32.767745],"type":"Point"}
}