{
  "type": "Feature",
  "properties": {
    "iso:country":"US",
    "sg:address":"9809 Stella Link Rd",
    "sg:city":"Houston",
    "sg:classifiers":[
        {
            "category":"Retail",
            "subcategory":"Veterinary Services",
            "type":"Services"
        }
    ],
    "sg:phone":"+1 713 666 1771",
    "sg:postcode":"77025",
    "sg:province":"TX",
    "sg:tags":[
        "veterinarian"
    ],
    "sg:website":"www.stellalinkanimalclinic.com",
    "wof:name":"Stella Link Animal Clinic",
    "wof:placetype":"venue"
},
  "geometry": {"coordinates":[-95.439697,29.6766],"type":"Point"}
}