{
  "type": "Feature",
  "properties": {
    "iso:country":"US",
    "sg:address":"106 College Park Dr",
    "sg:city":"Weatherford",
    "sg:classifiers":[
        {
            "category":"Restaurant",
            "type":"Food & Drink"
        }
    ],
    "sg:phone":"+1 817 599 5568",
    "sg:postcode":"76086",
    "sg:province":"TX",
    "sg:tags":[
        "buffet"
    ],
    "wof:name":"Buffet City",
    "wof:placetype":"venue"
},
  "geometry": {"coordinates":[-97.797264,32.739049],"type":"Point"}
}