{
  "type": "Feature",
  "properties": {
    "iso:country":"US",
    "sg:address":"11230 Slaughter Creek Dr",
    "sg:city":"Austin",
    "sg:classifiers":[
        {
            "category":"Retail",
            "subcategory":"Auto Repair",
            "type":"Services"
        }
    ],
    "sg:phone":"+1 512 292 9466",
    "sg:postcode":"78748",
    "sg:province":"TX",
    "sg:tags":[
        "general"
    ],
    "wof:name":"Allies Automotive",
    "wof:placetype":"venue"
},
  "geometry": {"coordinates":[-97.819729,30.171931],"type":"Point"}
}