{
  "type": "Feature",
  "properties": {
    "iso:country":"US",
    "sg:address":"1201 Hawkins Blvd",
    "sg:city":"El Paso",
    "sg:classifiers":[
        {
            "category":"Shopping",
            "subcategory":"Books",
            "type":"Retail Goods"
        }
    ],
    "sg:phone":"+1 915 772 8305",
    "sg:postcode":"79925",
    "sg:province":"TX",
    "wof:name":"Hosanna Christian Bkstr",
    "wof:placetype":"venue"
},
  "geometry": {"coordinates":[-106.373474,31.777262],"type":"Point"}
}