{
  "type": "Feature",
  "properties": {
    "iso:country":"US",
    "sg:address":"1780 Co Rd C",
    "sg:city":"Springlake",
    "sg:phone":"+1 806 986 4209",
    "sg:postcode":"79035",
    "sg:province":"TX",
    "sg:tags":[
        "farm",
        "cotton"
    ],
    "wof:name":"Bob Cleavinger",
    "wof:placetype":"venue"
},
  "geometry": {"coordinates":[-102.74636099999999,34.713467],"type":"Point"}
}