{
  "type": "Feature",
  "properties": {
    "iso:country":"US",
    "sg:address":"9050 Cook Rd",
    "sg:city":"Houston",
    "sg:classifiers":[
        {
            "category":"Building & Trades",
            "subcategory":"Construction",
            "type":"Services"
        }
    ],
    "sg:phone":"+1 281 561 9418",
    "sg:postcode":"77099",
    "sg:province":"TX",
    "sg:tags":[
        "house",
        "c",
        "hanging",
        "contractor"
    ],
    "wof:name":"Ram Maintenance Services",
    "wof:placetype":"venue"
},
  "geometry": {"coordinates":[-95.595806,29.680484],"type":"Point"}
}