{
  "type": "Feature",
  "properties": {
    "iso:country":"US",
    "sg:address":"817 Hall Ave",
    "sg:city":"Littlefield",
    "sg:classifiers":[
        {
            "category":"Home & Garden",
            "subcategory":"Carpets & Floor Coverings",
            "type":"Retail Goods"
        }
    ],
    "sg:phone":"+1 806 385 1663",
    "sg:postcode":"79339",
    "sg:province":"TX",
    "sg:tags":[
        "dealer",
        "rug"
    ],
    "wof:name":"Duncan Carpets",
    "wof:placetype":"venue"
},
  "geometry": {"coordinates":[-102.32536,33.91819],"type":"Point"}
}