{
  "type": "Feature",
  "properties": {
    "iso:country":"US",
    "sg:address":"409 Bob White St",
    "sg:city":"De Soto",
    "sg:classifiers":[
        {
            "category":"Freight",
            "type":"Transportation"
        }
    ],
    "sg:phone":"+1 972 274 9284",
    "sg:postcode":"75115",
    "sg:province":"TX",
    "sg:tags":[
        "operator",
        "local",
        "trucking"
    ],
    "wof:name":"Ellis Trucking",
    "wof:placetype":"venue"
},
  "geometry": {"coordinates":[-96.85234699999999,32.595661],"type":"Point"}
}