{
  "type": "Feature",
  "properties": {
    "iso:country":"US",
    "sg:address":"2212 Amhearst Ln",
    "sg:city":"Flower Mound",
    "sg:classifiers":[
        {
            "category":"Professional",
            "subcategory":"Computer Services",
            "type":"Services"
        }
    ],
    "sg:phone":"+1 972 355 1518",
    "sg:postcode":"75028",
    "sg:province":"TX",
    "sg:tags":[
        "design",
        "system"
    ],
    "wof:name":"Barcellona Labs Inc",
    "wof:placetype":"venue"
},
  "geometry": {"coordinates":[-97.06256,33.015703],"type":"Point"}
}