{
  "type": "Feature",
  "properties": {
    "iso:country":"US",
    "sg:address":"9783 FM 949",
    "sg:city":"Cat Spring",
    "sg:classifiers":[
        {
            "category":"Retail",
            "subcategory":"Repair Shop",
            "type":"Services"
        }
    ],
    "sg:phone":"+1 979 865 0373",
    "sg:postcode":"78933",
    "sg:province":"TX",
    "wof:name":"Hills Repair Service",
    "wof:placetype":"venue"
},
  "geometry": {"coordinates":[-96.321068,29.855765],"type":"Point"}
}