{
  "type": "Feature",
  "properties": {
    "iso:country":"US",
    "sg:address":"9707 S Gessner Dr",
    "sg:city":"Houston",
    "sg:classifiers":[
        {
            "category":"Retail",
            "subcategory":"Repair Shop",
            "type":"Services"
        }
    ],
    "sg:phone":"+1 713 212 4062",
    "sg:postcode":"77071",
    "sg:province":"TX",
    "wof:name":"Hogans Heroes Cleaning Svcs",
    "wof:placetype":"venue"
},
  "geometry": {"coordinates":[-95.528127,29.674477],"type":"Point"}
}