{
  "type": "Feature",
  "properties": {
    "iso:country":"US",
    "sg:address":"9500 E Highway 290",
    "sg:city":"Austin",
    "sg:classifiers":[
        {
            "category":"Shopping",
            "subcategory":"Jewelry",
            "type":"Retail Goods"
        }
    ],
    "sg:phone":"+1 512 272 8369",
    "sg:postcode":"78724",
    "sg:province":"TX",
    "wof:name":"Crystal Jewelry",
    "wof:placetype":"venue"
},
  "geometry": {"coordinates":[-97.60459899999999,30.335501],"type":"Point"}
}