{
  "type": "Feature",
  "properties": {
    "iso:country":"US",
    "sg:address":"26707 Sunset Ln",
    "sg:city":"Magnolia",
    "sg:classifiers":[
        {
            "category":"Real Estate",
            "subcategory":"Real Estate Services",
            "type":"Services"
        },
        {
            "category":"Real Estate",
            "subcategory":"Real Estate Agent",
            "type":"Services"
        }
    ],
    "sg:phone":"+1 281 772 5906",
    "sg:postcode":"77355",
    "sg:province":"TX",
    "sg:tags":[
        "buyer",
        "broker"
    ],
    "wof:name":"National Association Of Realtors",
    "wof:placetype":"venue"
},
  "geometry": {"coordinates":[-95.746478,30.134666],"type":"Point"}
}