{
  "type": "Feature",
  "properties": {
    "iso:country":"US",
    "sg:address":"6731 State Hwy 1604",
    "sg:city":"Adkins",
    "sg:classifiers":[
        {
            "category":"Retail",
            "subcategory":"Auto Repair",
            "type":"Services"
        }
    ],
    "sg:phone":"+1 210 649 1008",
    "sg:postcode":"78101",
    "sg:province":"TX",
    "sg:tags":[
        "truck",
        "general"
    ],
    "wof:name":"B R N Diesel Repair",
    "wof:placetype":"venue"
},
  "geometry": {"coordinates":[-98.24669299999999,29.358817],"type":"Point"}
}