{
  "type": "Feature",
  "properties": {
    "iso:country":"US",
    "sg:address":"3750 Randle Hill Rd",
    "sg:city":"Brenham",
    "sg:classifiers":[
        {
            "category":"Farming",
            "subcategory":"Livestock Farm",
            "type":"Manufacturing & Wholesale Goods"
        }
    ],
    "sg:phone":"+1 979 836 0156",
    "sg:postcode":"77833",
    "sg:province":"TX",
    "sg:tags":[
        "beef",
        "feedlot",
        "cattle"
    ],
    "wof:name":"Ralph & Elizabeth Latimer",
    "wof:placetype":"venue"
},
  "geometry": {"coordinates":[-96.42031299999999,30.086064],"type":"Point"}
}