{
  "type": "Feature",
  "properties": {
    "iso:country":"US",
    "sg:address":"1409 Enchanted Ln",
    "sg:city":"Lancaster",
    "sg:classifiers":[
        {
            "category":"Wholesale",
            "subcategory":"Non-durable Goods",
            "type":"Manufacturing & Wholesale Goods"
        }
    ],
    "sg:phone":"+1 972 227 9623",
    "sg:postcode":"75146",
    "sg:province":"TX",
    "wof:name":"Hinojosas Imports",
    "wof:placetype":"venue"
},
  "geometry": {"coordinates":[-96.790085,32.579215],"type":"Point"}
}