{
  "type": "Feature",
  "properties": {
    "iso:country":"US",
    "sg:address":"6222 Richmond Ave",
    "sg:city":"Houston",
    "sg:classifiers":[
        {
            "category":"Shopping",
            "subcategory":"Jewelry",
            "type":"Retail Goods"
        }
    ],
    "sg:phone":"+1 713 774 7528",
    "sg:postcode":"77057",
    "sg:province":"TX",
    "wof:name":"Gemonds",
    "wof:placetype":"venue"
},
  "geometry": {"coordinates":[-95.491367,29.731903],"type":"Point"}
}