{
  "type": "Feature",
  "properties": {
    "iso:country":"US",
    "sg:address":"1710 N Vermillion Ave",
    "sg:city":"Brownsville",
    "sg:classifiers":[
        {
            "category":"Real Estate",
            "subcategory":"Real Estate Operator",
            "type":"Services"
        }
    ],
    "sg:phone":"+1 956 831 4427",
    "sg:postcode":"78521",
    "sg:province":"TX",
    "sg:tags":[
        "mobile",
        "home",
        "site",
        "trailer"
    ],
    "wof:name":"Breeze Lake Campground",
    "wof:placetype":"venue"
},
  "geometry": {"coordinates":[-97.41775,25.936524],"type":"Point"}
}