{
  "type": "Feature",
  "properties": {
    "iso:country":"US",
    "sg:address":"5251 Gasmer Dr Ofc",
    "sg:city":"Houston",
    "sg:classifiers":[
        {
            "category":"Real Estate",
            "subcategory":"Real Estate Operator",
            "type":"Services"
        }
    ],
    "sg:phone":"+1 713 721 3631",
    "sg:postcode":"77035",
    "sg:province":"TX",
    "sg:tags":[
        "apartment"
    ],
    "wof:name":"Indochinese Culture Center",
    "wof:placetype":"venue"
},
  "geometry": {"coordinates":[-95.470398,29.651199],"type":"Point"}
}