{
  "type": "Feature",
  "properties": {
    "iso:country":"US",
    "sg:address":"1742 Oak Forest Dr",
    "sg:city":"New Braunfels",
    "sg:classifiers":[
        {
            "category":"Shopping",
            "subcategory":"Gifts & Souvenirs",
            "type":"Retail Goods"
        }
    ],
    "sg:phone":"+1 830 620 1743",
    "sg:postcode":"78132",
    "sg:province":"TX",
    "wof:name":"Marcias",
    "wof:placetype":"venue"
},
  "geometry": {"coordinates":[-98.162986,29.723762],"type":"Point"}
}