{
  "type": "Feature",
  "properties": {
    "iso:country":"US",
    "sg:address":"207 Parliament Dr",
    "sg:city":"Houston",
    "sg:classifiers":[
        {
            "category":"Real Estate",
            "subcategory":"Real Estate Agent",
            "type":"Services"
        }
    ],
    "sg:phone":"+1 713 910 1333",
    "sg:postcode":"77034",
    "sg:province":"TX",
    "wof:name":"NASA Area Appraisal Company",
    "wof:placetype":"venue"
},
  "geometry": {"coordinates":[-95.20921800000001,29.645526],"type":"Point"}
}