{
  "type": "Feature",
  "properties": {
    "iso:country":"US",
    "sg:address":"3803 W 28th St",
    "sg:city":"Bryan",
    "sg:classifiers":[
        {
            "category":"Organizations",
            "subcategory":"Religious Organization",
            "type":"Services"
        }
    ],
    "sg:phone":"+1 979 575 1658",
    "sg:postcode":"77803",
    "sg:province":"TX",
    "wof:name":"Freedom From Bondage Ministries, Inc",
    "wof:placetype":"venue"
},
  "geometry": {"coordinates":[-96.408913,30.66483],"type":"Point"}
}