{
  "type": "Feature",
  "properties": {
    "iso:country":"US",
    "sg:address":"2404 Jacquelyn Dr",
    "sg:city":"Pearland",
    "sg:classifiers":[
        {
            "category":"Retail",
            "subcategory":"Portrait Studio",
            "type":"Services"
        }
    ],
    "sg:phone":"+1 281 997 9852",
    "sg:postcode":"77581",
    "sg:province":"TX",
    "sg:tags":[
        "photo"
    ],
    "wof:name":"Keepsake Equine Portraits",
    "wof:placetype":"venue"
},
  "geometry": {"coordinates":[-95.273787,29.563384],"type":"Point"}
}