{
  "type": "Feature",
  "properties": {
    "iso:country":"US",
    "sg:address":"8910 Mines Rd",
    "sg:city":"Laredo",
    "sg:classifiers":[
        {
            "category":"Autos & Motor Vehicles",
            "subcategory":"Automobile Sales",
            "type":"Retail Goods"
        }
    ],
    "sg:phone":"+1 956 725 4847",
    "sg:postcode":"78045",
    "sg:province":"TX",
    "sg:tags":[
        "car",
        "used",
        "dealer"
    ],
    "wof:name":"Cavazos Auto Sales",
    "wof:placetype":"venue"
},
  "geometry": {"coordinates":[-99.509354,27.583221],"type":"Point"}
}