{
  "type": "Feature",
  "properties": {
    "iso:country":"US",
    "sg:address":"2719 Southwest Pkwy",
    "sg:city":"Wichita Falls",
    "sg:classifiers":[
        {
            "category":"Restaurant",
            "type":"Food & Drink"
        }
    ],
    "sg:phone":"+1 940 691 7640",
    "sg:postcode":"76308",
    "sg:province":"TX",
    "sg:tags":[
        "eating"
    ],
    "sg:website":"www.parkwaygrill.com",
    "wof:name":"Parkway Grill & Club",
    "wof:placetype":"venue"
},
  "geometry": {"coordinates":[-98.53525500000001,33.85771],"type":"Point"}
}