{
  "type": "Feature",
  "properties": {
    "iso:country":"US",
    "sg:address":"2550 W Davis St",
    "sg:city":"Dallas",
    "sg:classifiers":[
        {
            "category":"Autos & Motor Vehicles",
            "subcategory":"Auto Supplies",
            "type":"Retail Goods"
        }
    ],
    "sg:phone":"+1 214 948 6006",
    "sg:postcode":"75211",
    "sg:province":"TX",
    "sg:tags":[
        "tire"
    ],
    "wof:name":"Oakcliff Tire & Wheel",
    "wof:placetype":"venue"
},
  "geometry": {"coordinates":[-96.85975000000001,32.749382],"type":"Point"}
}