{
  "type": "Feature",
  "properties": {
    "iso:country":"US",
    "sg:address":"10400 Enchanted Meadow Dr",
    "sg:city":"Frisco",
    "sg:classifiers":[
        {
            "category":"Building & Trades",
            "subcategory":"Construction",
            "type":"Services"
        }
    ],
    "sg:phone":"+1 972 335 4877",
    "sg:postcode":"75034",
    "sg:province":"TX",
    "sg:tags":[
        "house"
    ],
    "wof:name":"Drees Homes of Plano",
    "wof:placetype":"venue"
},
  "geometry": {"coordinates":[-96.816149,33.165315],"type":"Point"}
}