{
  "type": "Feature",
  "properties": {
    "iso:country":"US",
    "sg:address":"306 22nd St",
    "sg:city":"Galveston",
    "sg:classifiers":[
        {
            "category":"Professional",
            "subcategory":"Lawyer & Legal Services",
            "type":"Services"
        }
    ],
    "sg:phone":"+1 409 763 0381",
    "sg:postcode":"77550",
    "sg:province":"TX",
    "wof:name":"Gulf Coast Legal Foundation",
    "wof:placetype":"venue"
},
  "geometry": {"coordinates":[-94.79272,29.306224],"type":"Point"}
}