{
  "type": "Feature",
  "properties": {
    "iso:country":"US",
    "sg:address":"11915 Starcrest Dr",
    "sg:city":"San Antonio",
    "sg:classifiers":[
        {
            "category":"Building & Trades",
            "subcategory":"Plumbing",
            "type":"Services"
        }
    ],
    "sg:phone":"+1 210 308 5951",
    "sg:postcode":"78247",
    "sg:province":"TX",
    "sg:tags":[
        "conditioning",
        "air",
        "system",
        "contractor"
    ],
    "wof:name":"H D Grant Co",
    "wof:placetype":"venue"
},
  "geometry": {"coordinates":[-98.464828,29.550218],"type":"Point"}
}