{
  "type": "Feature",
  "properties": {
    "iso:country":"US",
    "sg:address":"120 Texas Dr",
    "sg:city":"Kerrville",
    "sg:classifiers":[
        {
            "category":"Banks & Credit Unions",
            "subcategory":"Bank",
            "type":"Services"
        }
    ],
    "sg:phone":"+1 830 257 8238",
    "sg:postcode":"78028",
    "sg:province":"TX",
    "wof:name":"Hilco Federal Credit Union",
    "wof:placetype":"venue"
},
  "geometry": {"coordinates":[-99.154101,30.04598],"type":"Point"}
}