{
  "type": "Feature",
  "properties": {
    "iso:country":"US",
    "sg:address":"10201 Gateway Blvd W",
    "sg:city":"El Paso",
    "sg:classifiers":[
        {
            "category":"Health Services",
            "subcategory":"Clinic",
            "type":"Services"
        }
    ],
    "sg:phone":"+1 915 591 2193",
    "sg:postcode":"79935",
    "sg:province":"TX",
    "wof:name":"Columbia Healthcare Syst-El",
    "wof:placetype":"venue"
},
  "geometry": {"coordinates":[-106.354128,31.758627],"type":"Point"}
}