{
  "type": "Feature",
  "properties": {
    "iso:country":"US",
    "sg:address":"11949 FM 3005",
    "sg:city":"Galveston",
    "sg:classifiers":[
        {
            "category":"Real Estate",
            "subcategory":"Developer",
            "type":"Services"
        }
    ],
    "sg:phone":"+1 409 737 5888",
    "sg:postcode":"77554",
    "sg:province":"TX",
    "wof:name":"Appaloosa Land Company",
    "wof:placetype":"venue"
},
  "geometry": {"coordinates":[-94.88101399999999,29.239155],"type":"Point"}
}