{
  "type": "Feature",
  "properties": {
    "iso:country":"US",
    "sg:address":"2605 Co Rd 531",
    "sg:city":"Burleson",
    "sg:classifiers":[
        {
            "category":"Building & Trades",
            "subcategory":"Landscaping Services",
            "type":"Services"
        }
    ],
    "sg:phone":"+1 817 295 5182",
    "sg:postcode":"76028",
    "sg:province":"TX",
    "sg:tags":[
        "landscape"
    ],
    "wof:name":"Native Nursery & Landscape",
    "wof:placetype":"venue"
},
  "geometry": {"coordinates":[-97.254672,32.540903],"type":"Point"}
}