{
  "type": "Feature",
  "properties": {
    "iso:country":"US",
    "sg:address":"8008 Slide Rd",
    "sg:city":"Lubbock",
    "sg:classifiers":[
        {
            "category":"Health Services",
            "subcategory":"Clinic",
            "type":"Services"
        }
    ],
    "sg:phone":"+1 806 794 4283",
    "sg:postcode":"79424",
    "sg:province":"TX",
    "sg:tags":[
        "home",
        "agency",
        "employment",
        "care"
    ],
    "wof:name":"Nurscare IV Med Inc",
    "wof:placetype":"venue"
},
  "geometry": {"coordinates":[-101.922466,33.520866],"type":"Point"}
}