{
  "type": "Feature",
  "properties": {
    "iso:country":"US",
    "sg:address":"5414 N 10th St",
    "sg:city":"Mcallen",
    "sg:classifiers":[
        {
            "category":"Professional",
            "subcategory":"Accounting & Tax Preparation",
            "type":"Services"
        }
    ],
    "sg:phone":"+1 956 631 9100",
    "sg:postcode":"78504",
    "sg:province":"TX",
    "wof:name":"Villeda & Aliseda Attys At Law",
    "wof:placetype":"venue"
},
  "geometry": {"coordinates":[-98.221362,26.253481],"type":"Point"}
}