{
  "type": "Feature",
  "properties": {
    "iso:country":"US",
    "sg:address":"848 Dominion Dr Ste 200",
    "sg:city":"Katy",
    "sg:classifiers":[
        {
            "category":"Health Services",
            "subcategory":"Doctor",
            "type":"Services"
        }
    ],
    "sg:phone":"+1 281 578 5479",
    "sg:postcode":"77450",
    "sg:province":"TX",
    "sg:tags":[
        "medicine",
        "physician",
        "practice",
        "surgeons",
        "family"
    ],
    "wof:name":"Nottingham Family Medical Ctr",
    "wof:placetype":"venue"
},
  "geometry": {"coordinates":[-95.729467,29.77497],"type":"Point"}
}