{
  "type": "Feature",
  "properties": {
    "iso:country":"US",
    "sg:address":"1316 Mojave Bend",
    "sg:city":"Leander",
    "sg:classifiers":[
        {
            "category":"Professional",
            "subcategory":"Business Services",
            "type":"Services"
        }
    ],
    "sg:phone":"+1 512 331 1976",
    "sg:postcode":"78641",
    "sg:province":"TX",
    "wof:name":"Romance By Design",
    "wof:placetype":"venue"
},
  "geometry": {"coordinates":[-97.82084999999999,30.545344],"type":"Point"}
}