{
  "type": "Feature",
  "properties": {
    "iso:country":"US",
    "sg:address":"2736 Virginia St",
    "sg:city":"Houston",
    "sg:classifiers":[
        {
            "category":"Bars & Pubs",
            "subcategory":"Lounge",
            "type":"Food & Drink"
        },
        {
            "category":"Arts & Performance",
            "subcategory":"Music",
            "type":"Entertainment"
        }
    ],
    "sg:phone":"+1 713 520 7001",
    "sg:postcode":"77098",
    "sg:province":"TX",
    "sg:tags":[
        "venue"
    ],
    "sg:website":"www.88keyshouston.com",
    "wof:name":"88 Keys",
    "wof:placetype":"venue"
},
  "geometry": {"coordinates":[-95.42141599999999,29.741513],"type":"Point"}
}