{
  "type": "Feature",
  "properties": {
    "iso:country":"US",
    "sg:address":"7989 Belt Line Rd",
    "sg:city":"Dallas",
    "sg:classifiers":[
        {
            "category":"Professional",
            "subcategory":"Business Services",
            "type":"Services"
        }
    ],
    "sg:phone":"+1 972 239 8686",
    "sg:postcode":"75254",
    "sg:province":"TX",
    "sg:tags":[
        "box",
        "mail"
    ],
    "wof:name":"Mail Stop",
    "wof:placetype":"venue"
},
  "geometry": {"coordinates":[-96.769047,32.95091],"type":"Point"}
}