{
  "type": "Feature",
  "properties": {
    "iso:country":"US",
    "sg:address":"104 Church St",
    "sg:city":"Liberty Hill",
    "sg:classifiers":[
        {
            "category":"Organizations",
            "subcategory":"Religious Organization",
            "type":"Services"
        }
    ],
    "sg:phone":"+1 512 515 0070",
    "sg:postcode":"78642",
    "sg:province":"TX",
    "sg:tags":[
        "church"
    ],
    "wof:name":"Liberty Hill United Meth Chr",
    "wof:placetype":"venue"
},
  "geometry": {"coordinates":[-97.919484,30.665169],"type":"Point"}
}