{
  "type": "Feature",
  "properties": {
    "iso:country":"US",
    "sg:address":"3008 W Slaughter Ln",
    "sg:city":"Austin",
    "sg:classifiers":[
        {
            "category":"Insurance",
            "subcategory":"Insurance Agent",
            "type":"Services"
        }
    ],
    "sg:phone":"+1 512 441 3704",
    "sg:postcode":"78748",
    "sg:province":"TX",
    "wof:name":"State Farm Insurance",
    "wof:placetype":"venue"
},
  "geometry": {"coordinates":[-97.83882199999999,30.17835],"type":"Point"}
}