{
  "type": "Feature",
  "properties": {
    "iso:country":"US",
    "sg:address":"2158 Sandy Ln",
    "sg:city":"Dallas",
    "sg:classifiers":[
        {
            "category":"Manufacturing",
            "subcategory":"Tools & Machinery",
            "type":"Manufacturing & Wholesale Goods"
        }
    ],
    "sg:phone":"+1 972 659 1396",
    "sg:postcode":"75220",
    "sg:province":"TX",
    "sg:tags":[
        "water",
        "equipment",
        "treatment",
        "mfg"
    ],
    "wof:name":"Purotek Corporation",
    "wof:placetype":"venue"
},
  "geometry": {"coordinates":[-96.904211,32.860448],"type":"Point"}
}