{
  "type": "Feature",
  "properties": {
    "iso:country":"US",
    "sg:address":"1442 N Fairgrounds Rd",
    "sg:city":"Rio Grande City",
    "sg:classifiers":[
        {
            "category":"Organizations",
            "subcategory":"Religious Organization",
            "type":"Services"
        }
    ],
    "sg:phone":"+1 956 487 0020",
    "sg:postcode":"78582",
    "sg:province":"TX",
    "wof:name":"Juan Romero",
    "wof:placetype":"venue"
},
  "geometry": {"coordinates":[-98.82968700000001,26.392675],"type":"Point"}
}