{
  "type": "Feature",
  "properties": {
    "iso:country":"US",
    "sg:address":"4109 Ambrosia Ln",
    "sg:city":"Plano",
    "sg:classifiers":[
        {
            "category":"Professional",
            "subcategory":"Computer Services",
            "type":"Services"
        }
    ],
    "sg:phone":"+1 972 867 0061",
    "sg:postcode":"75093",
    "sg:province":"TX",
    "sg:tags":[
        "design",
        "system"
    ],
    "wof:name":"Compu Solutions",
    "wof:placetype":"venue"
},
  "geometry": {"coordinates":[-96.77220699999999,33.021285],"type":"Point"}
}