{
  "type": "Feature",
  "properties": {
    "iso:country":"US",
    "sg:address":"2430 Summit Ridge Dr",
    "sg:city":"San Marcos",
    "sg:classifiers":[
        {
            "category":"Banks & Credit Unions",
            "subcategory":"Financial Services",
            "type":"Services"
        }
    ],
    "sg:phone":"+1 512 396 4287",
    "sg:postcode":"78666",
    "sg:province":"TX",
    "sg:tags":[
        "investor"
    ],
    "wof:name":"Thornton Family Investments LP",
    "wof:placetype":"venue"
},
  "geometry": {"coordinates":[-97.98074200000001,29.872126],"type":"Point"}
}