{
  "type": "Feature",
  "properties": {
    "iso:country":"US",
    "sg:address":"2100 Jacocks Ln",
    "sg:city":"Fort Worth",
    "sg:classifiers":[
        {
            "category":"Building & Trades",
            "subcategory":"Construction",
            "type":"Services"
        }
    ],
    "sg:phone":"+1 817 924 8500",
    "sg:postcode":"76115",
    "sg:province":"TX",
    "sg:tags":[
        "house"
    ],
    "wof:name":"Parkcrest Builders Inc",
    "wof:placetype":"venue"
},
  "geometry": {"coordinates":[-97.35009100000001,32.67143],"type":"Point"}
}