{
  "type": "Feature",
  "properties": {
    "iso:country":"US",
    "sg:address":"330 S Blue Mound Rd",
    "sg:city":"Fort Worth",
    "sg:classifiers":[
        {
            "category":"Professional",
            "subcategory":"Lawyer & Legal Services",
            "type":"Services"
        }
    ],
    "sg:phone":"+1 817 338 0009",
    "sg:postcode":"76131",
    "sg:province":"TX",
    "sg:tags":[
        "attorney"
    ],
    "wof:name":"Karen Baylor",
    "wof:placetype":"venue"
},
  "geometry": {"coordinates":[-97.34312799999999,32.858545],"type":"Point"}
}