{
  "type": "Feature",
  "properties": {
    "iso:country":"US",
    "sg:address":"2611 FM 1960 W",
    "sg:city":"Houston",
    "sg:classifiers":[
        {
            "category":"Recreation",
            "type":"Entertainment"
        }
    ],
    "sg:phone":"+1 281 397 8124",
    "sg:postcode":"77068",
    "sg:province":"TX",
    "sg:tags":[
        "ticket"
    ],
    "sg:website":"www.eventsunlimitedtix.com",
    "wof:name":"Events Unlimited",
    "wof:placetype":"venue"
},
  "geometry": {"coordinates":[-95.46396900000001,30.007014],"type":"Point"}
}