{
  "type": "Feature",
  "properties": {
    "iso:country":"US",
    "sg:address":"11586 Gatesville Dr",
    "sg:city":"Frisco",
    "sg:classifiers":[
        {
            "category":"Professional",
            "subcategory":"Art Services",
            "type":"Services"
        }
    ],
    "sg:phone":"+1 214 422 9964",
    "sg:postcode":"75035",
    "sg:province":"TX",
    "sg:tags":[
        "picture",
        "frame"
    ],
    "wof:name":"Beyond The Walls Internat",
    "wof:placetype":"venue"
},
  "geometry": {"coordinates":[-96.77893899999999,33.185384],"type":"Point"}
}