{
  "type": "Feature",
  "properties": {
    "iso:country":"US",
    "sg:address":"4202 Stallion Brook Ln",
    "sg:city":"Spring",
    "sg:classifiers":[
        {
            "category":"Taxi",
            "type":"Transportation"
        }
    ],
    "sg:phone":"+1 281 288 6585",
    "sg:postcode":"77388",
    "sg:province":"TX",
    "wof:name":"Cab Investments",
    "wof:placetype":"venue"
},
  "geometry": {"coordinates":[-95.48453600000001,30.06707],"type":"Point"}
}