{
  "type": "Feature",
  "properties": {
    "iso:country":"US",
    "sg:address":"2009 108th St",
    "sg:city":"Grand Prairie",
    "sg:classifiers":[
        {
            "category":"Wholesale",
            "subcategory":"Machinery & Supplies",
            "type":"Manufacturing & Wholesale Goods"
        }
    ],
    "sg:phone":"+1 972 641 9590",
    "sg:postcode":"75050",
    "sg:province":"TX",
    "sg:tags":[
        "equipment",
        "laundry"
    ],
    "wof:name":"Pellerin Laundry Machinery",
    "wof:placetype":"venue"
},
  "geometry": {"coordinates":[-97.055965,32.782698],"type":"Point"}
}