{
  "type": "Feature",
  "properties": {
    "iso:country":"US",
    "sg:address":"317 Andre Dr",
    "sg:city":"Irving",
    "sg:classifiers":[
        {
            "category":"Professional",
            "type":"Services"
        }
    ],
    "sg:phone":"+1 972 444 0442",
    "sg:postcode":"75063",
    "sg:province":"TX",
    "wof:name":"Tracy Holland Designs",
    "wof:placetype":"venue"
},
  "geometry": {"coordinates":[-96.94668299999999,32.945537],"type":"Point"}
}