{
  "type": "Feature",
  "properties": {
    "iso:country":"US",
    "sg:address":"2908 W Ohio Ave",
    "sg:city":"Midland",
    "sg:classifiers":[
        {
            "category":"Organizations",
            "subcategory":"Community Association",
            "type":"Services"
        }
    ],
    "sg:phone":"+1 432 694 2648",
    "sg:postcode":"79701",
    "sg:province":"TX",
    "sg:tags":[
        "blind"
    ],
    "wof:name":"VAN Serving Visually Impaired",
    "wof:placetype":"venue"
},
  "geometry": {"coordinates":[-102.110801,31.994292],"type":"Point"}
}