{
  "type": "Feature",
  "properties": {
    "iso:country":"US",
    "sg:address":"7080 Calder Ave",
    "sg:city":"Beaumont",
    "sg:classifiers":[
        {
            "category":"Social Services",
            "type":"Services"
        }
    ],
    "sg:phone":"+1 409 860 0371",
    "sg:postcode":"77706",
    "sg:province":"TX",
    "sg:tags":[
        "personal"
    ],
    "wof:name":"Buckner Eldercare Services",
    "wof:placetype":"venue"
},
  "geometry": {"coordinates":[-94.17378100000001,30.073394],"type":"Point"}
}