{
  "type": "Feature",
  "properties": {
    "iso:country":"US",
    "sg:address":"814 Bay Star Blvd",
    "sg:city":"Webster",
    "sg:classifiers":[
        {
            "category":"Building & Trades",
            "subcategory":"Pest Control",
            "type":"Services"
        }
    ],
    "sg:phone":"+1 281 482 9294",
    "sg:postcode":"77598",
    "sg:province":"TX",
    "wof:name":"Gulf Exterminators",
    "wof:placetype":"venue"
},
  "geometry": {"coordinates":[-95.169256,29.591269],"type":"Point"}
}