{
  "type": "Feature",
  "properties": {
    "iso:country":"US",
    "sg:address":"6829 Smithfield Rd",
    "sg:city":"Fort Worth",
    "sg:classifiers":[
        {
            "category":"Retail",
            "subcategory":"Auto Repair",
            "type":"Services"
        }
    ],
    "sg:phone":"+1 817 485 8870",
    "sg:postcode":"76180",
    "sg:province":"TX",
    "sg:tags":[
        "body",
        "automobile",
        "painting"
    ],
    "wof:name":"Car Craft Paint & Body Repair",
    "wof:placetype":"venue"
},
  "geometry": {"coordinates":[-97.212086,32.871071],"type":"Point"}
}