{
  "type": "Feature",
  "properties": {
    "iso:country":"US",
    "sg:address":"2000 Central Expy",
    "sg:city":"Plano",
    "sg:classifiers":[
        {
            "category":"Organizations",
            "subcategory":"Non-profit Organization",
            "type":"Services"
        }
    ],
    "sg:phone":"+1 972 424 1070",
    "sg:postcode":"75074",
    "sg:province":"TX",
    "sg:tags":[
        "agency",
        "health",
        "staffing",
        "care"
    ],
    "wof:name":"Shc Services Inc",
    "wof:placetype":"venue"
},
  "geometry": {"coordinates":[-96.70898800000001,33.027311],"type":"Point"}
}