{
  "type": "Feature",
  "properties": {
    "iso:country":"US",
    "sg:address":"4814 Beechnut St",
    "sg:city":"Houston",
    "sg:classifiers":[
        {
            "category":"Personal",
            "type":"Services"
        }
    ],
    "sg:phone":"+1 713 668 2826",
    "sg:postcode":"77096",
    "sg:province":"TX",
    "wof:name":"Keep A Tan",
    "wof:placetype":"venue"
},
  "geometry": {"coordinates":[-95.462959,29.689245],"type":"Point"}
}