{
  "type": "Feature",
  "properties": {
    "iso:country":"US",
    "sg:address":"20615 State Hwy 46",
    "sg:city":"Spring Branch",
    "sg:classifiers":[
        {
            "category":"Autos & Motor Vehicles",
            "subcategory":"Auto Supplies",
            "type":"Retail Goods"
        }
    ],
    "sg:phone":"+1 830 980 6337",
    "sg:postcode":"78070",
    "sg:province":"TX",
    "sg:tags":[
        "automobile",
        "parts"
    ],
    "wof:name":"NAPA Auto Parts",
    "wof:placetype":"venue"
},
  "geometry": {"coordinates":[-98.42891,29.798632],"type":"Point"}
}