{
  "type": "Feature",
  "properties": {
    "iso:country":"US",
    "sg:address":"3310 Deer Valley Dr",
    "sg:city":"Spring",
    "sg:classifiers":[
        {
            "category":"Recreation",
            "type":"Entertainment"
        }
    ],
    "sg:phone":"+1 281 288 8058",
    "sg:postcode":"77373",
    "sg:province":"TX",
    "sg:tags":[
        "center"
    ],
    "wof:name":"Lexington Wood Recreational",
    "wof:placetype":"venue"
},
  "geometry": {"coordinates":[-95.388094,30.080063],"type":"Point"}
}