{
  "type": "Feature",
  "properties": {
    "iso:country":"US",
    "sg:address":"2611 N Grandview Ave",
    "sg:city":"Odessa",
    "sg:classifiers":[
        {
            "category":"Shopping",
            "subcategory":"Hobbies, Toys, & Games",
            "type":"Retail Goods"
        },
        {
            "category":"Shopping",
            "subcategory":"Bicycles & Sporting Goods",
            "type":"Retail Goods"
        },
        {
            "category":"Recreation",
            "subcategory":"Fishing",
            "type":"Entertainment"
        }
    ],
    "sg:phone":"+1 432 552 6730",
    "sg:postcode":"79761",
    "sg:province":"TX",
    "sg:tags":[
        "archery",
        "supply",
        "gun",
        "gunsmith",
        "equipment",
        "tackle"
    ],
    "wof:name":"Brush Mountain Outfitters",
    "wof:placetype":"venue"
},
  "geometry": {"coordinates":[-102.346968,31.874491],"type":"Point"}
}