{
  "type": "Feature",
  "properties": {
    "iso:country":"US",
    "sg:address":"702 Mercedes St",
    "sg:city":"Benbrook",
    "sg:classifiers":[
        {
            "category":"Building & Trades",
            "subcategory":"Construction",
            "type":"Services"
        },
        {
            "category":"Building & Trades",
            "subcategory":"Plumbing",
            "type":"Services"
        }
    ],
    "sg:phone":"+1 817 249 3733",
    "sg:postcode":"76126",
    "sg:province":"TX",
    "sg:tags":[
        "sheet",
        "work",
        "metal",
        "contractor"
    ],
    "wof:name":"Casey Sheetmetal",
    "wof:placetype":"venue"
},
  "geometry": {"coordinates":[-97.45892600000001,32.678875],"type":"Point"}
}