{
  "type": "Feature",
  "properties": {
    "iso:country":"US",
    "sg:address":"1406 New Haven St",
    "sg:city":"Grand Prairie",
    "sg:classifiers":[
        {
            "category":"Freight",
            "type":"Transportation"
        }
    ],
    "sg:phone":"+1 972 264 2433",
    "sg:postcode":"75051",
    "sg:province":"TX",
    "sg:tags":[
        "courier"
    ],
    "wof:name":"Wilson Express Courier Service",
    "wof:placetype":"venue"
},
  "geometry": {"coordinates":[-96.992908,32.726492],"type":"Point"}
}