{
  "type": "Feature",
  "properties": {
    "iso:country":"US",
    "sg:address":"4506 Natural Bridge Dr",
    "sg:city":"Humble",
    "sg:classifiers":[
        {
            "category":"Home & Garden",
            "subcategory":"Building Materials",
            "type":"Retail Goods"
        }
    ],
    "sg:phone":"+1 281 360 0535",
    "sg:postcode":"77345",
    "sg:province":"TX",
    "wof:name":"Alluring Wall Designs",
    "wof:placetype":"venue"
},
  "geometry": {"coordinates":[-95.184516,30.072237],"type":"Point"}
}