{
  "type": "Feature",
  "properties": {
    "iso:country":"US",
    "sg:address":"2800 Irving Blvd",
    "sg:city":"Dallas",
    "sg:classifiers":[
        {
            "category":"Shopping",
            "subcategory":"Gifts & Souvenirs",
            "type":"Retail Goods"
        }
    ],
    "sg:phone":"+1 972 373 0337",
    "sg:postcode":"75207",
    "sg:province":"TX",
    "sg:tags":[
        "shop"
    ],
    "wof:name":"Rocibelle Gifts",
    "wof:placetype":"venue"
},
  "geometry": {"coordinates":[-96.848653,32.808394],"type":"Point"}
}