{
  "type": "Feature",
  "properties": {
    "iso:country":"US",
    "sg:address":"8014 Harry Hines Blvd",
    "sg:city":"Dallas",
    "sg:classifiers":[
        {
            "category":"Personal",
            "subcategory":"Beauty Salon",
            "type":"Services"
        }
    ],
    "sg:phone":"+1 214 637 4307",
    "sg:postcode":"75235",
    "sg:province":"TX",
    "sg:tags":[
        "shop"
    ],
    "wof:name":"Adalind's Beauty Salon",
    "wof:placetype":"venue"
},
  "geometry": {"coordinates":[-96.861035,32.833853],"type":"Point"}
}