{
  "type": "Feature",
  "properties": {
    "iso:country":"US",
    "sg:address":"8600 SW 34th Ave",
    "sg:city":"Amarillo",
    "sg:classifiers":[
        {
            "category":"Home & Garden",
            "subcategory":"Furniture",
            "type":"Retail Goods"
        },
        {
            "category":"Home & Garden",
            "subcategory":"Home Furnishings",
            "type":"Retail Goods"
        },
        {
            "category":"Home & Garden",
            "subcategory":"Carpets & Floor Coverings",
            "type":"Retail Goods"
        }
    ],
    "sg:phone":"+1 806 358 7544",
    "sg:postcode":"79121",
    "sg:province":"TX",
    "sg:tags":[
        "set",
        "house",
        "bed",
        "mattress",
        "bedroom",
        "store"
    ],
    "sg:website":"http://clickserve.us2.dartsearch.net/link/click?lid=43000000124318585",
    "wof:name":"Havertys Furniture",
    "wof:placetype":"venue"
},
  "geometry": {"coordinates":[-101.939301,35.176582],"type":"Point"}
}