{
  "type": "Feature",
  "properties": {
    "iso:country":"US",
    "sg:address":"2305 Donley Dr",
    "sg:city":"Austin",
    "sg:classifiers":[
        {
            "category":"Health Services",
            "subcategory":"Clinic",
            "type":"Services"
        }
    ],
    "sg:phone":"+1 512 832 1066",
    "sg:postcode":"78758",
    "sg:province":"TX",
    "sg:tags":[
        "home"
    ],
    "wof:name":"Apria Healthcare",
    "wof:placetype":"venue"
},
  "geometry": {"coordinates":[-97.71279199999999,30.388067],"type":"Point"}
}