{
  "type": "Feature",
  "properties": {
    "iso:country":"US",
    "sg:address":"655 Langham Rd Ste 12",
    "sg:city":"Beaumont",
    "sg:classifiers":[
        {
            "category":"Real Estate",
            "subcategory":"Real Estate Operator",
            "type":"Services"
        }
    ],
    "sg:phone":"+1 409 861 1800",
    "sg:postcode":"77707",
    "sg:province":"TX",
    "sg:tags":[
        "apartment"
    ],
    "wof:name":"Cypress Bend Apartments",
    "wof:placetype":"venue"
},
  "geometry": {"coordinates":[-94.164648,30.070138],"type":"Point"}
}