{
  "type": "Feature",
  "properties": {
    "iso:country":"US",
    "sg:address":"201 S Cleburne Whitney Rd",
    "sg:city":"Rio Vista",
    "sg:classifiers":[
        {
            "category":"Organizations",
            "subcategory":"Religious Organization",
            "type":"Services"
        }
    ],
    "sg:phone":"+1 817 373 2352",
    "sg:postcode":"76093",
    "sg:province":"TX",
    "sg:tags":[
        "church"
    ],
    "wof:name":"First Baptist Church",
    "wof:placetype":"venue"
},
  "geometry": {"coordinates":[-97.37376,32.231703],"type":"Point"}
}