{
  "type": "Feature",
  "properties": {
    "iso:country":"US",
    "sg:address":"45 Meandering Way",
    "sg:city":"Round Rock",
    "sg:classifiers":[
        {
            "category":"Professional",
            "subcategory":"Management & Consulting",
            "type":"Services"
        }
    ],
    "sg:phone":"+1 512 310 2266",
    "sg:postcode":"78664",
    "sg:province":"TX",
    "sg:tags":[
        "business"
    ],
    "wof:name":"Petsche Consulting",
    "wof:placetype":"venue"
},
  "geometry": {"coordinates":[-97.60669300000001,30.522404],"type":"Point"}
}