{
  "type": "Feature",
  "properties": {
    "iso:country":"US",
    "sg:address":"4006 Misty Glade",
    "sg:city":"San Antonio",
    "sg:classifiers":[
        {
            "category":"Retail",
            "subcategory":"Portrait Studio",
            "type":"Services"
        }
    ],
    "sg:phone":"+1 210 495 1996",
    "sg:postcode":"78247",
    "sg:province":"TX",
    "sg:tags":[
        "laboratory",
        "photofinishing",
        "photo"
    ],
    "wof:name":"Bob Wickley Photographer",
    "wof:placetype":"venue"
},
  "geometry": {"coordinates":[-98.41291099999999,29.588786],"type":"Point"}
}