{
  "type": "Feature",
  "properties": {
    "iso:country":"US",
    "sg:address":"922 W Travis St",
    "sg:city":"La Grange",
    "sg:classifiers":[
        {
            "category":"Restaurant",
            "type":"Food & Drink"
        }
    ],
    "sg:phone":"+1 979 968 3033",
    "sg:postcode":"78945",
    "sg:province":"TX",
    "wof:name":"Gold'n Crisp Fried Chicken",
    "wof:placetype":"venue"
},
  "geometry": {"coordinates":[-96.889443,29.900395],"type":"Point"}
}