{
  "type": "Feature",
  "properties": {
    "iso:country":"US",
    "sg:address":"502 N Tenery St",
    "sg:city":"Gladewater",
    "sg:classifiers":[
        {
            "category":"Health Services",
            "subcategory":"Clinic",
            "type":"Services"
        }
    ],
    "sg:phone":"+1 903 845 4275",
    "sg:postcode":"75647",
    "sg:province":"TX",
    "wof:name":"Harmony Living Ctr",
    "wof:placetype":"venue"
},
  "geometry": {"coordinates":[-94.943888,32.540696],"type":"Point"}
}