{
  "type": "Feature",
  "properties": {
    "iso:country":"US",
    "sg:address":"7302 Arbor Oaks Dr",
    "sg:city":"Dallas",
    "sg:classifiers":[
        {
            "category":"Professional",
            "subcategory":"Management & Consulting",
            "type":"Services"
        }
    ],
    "sg:phone":"+1 214 774 3150",
    "sg:postcode":"75248",
    "sg:province":"TX",
    "sg:tags":[
        "business"
    ],
    "wof:name":"Objective Marketing",
    "wof:placetype":"venue"
},
  "geometry": {"coordinates":[-96.77992999999999,32.975645],"type":"Point"}
}