{
  "type": "Feature",
  "properties": {
    "iso:country":"US",
    "sg:address":"1400 Caudill St",
    "sg:city":"College Station",
    "sg:classifiers":[
        {
            "category":"Real Estate",
            "subcategory":"Real Estate Agent",
            "type":"Services"
        }
    ],
    "sg:phone":"+1 979 764 6400",
    "sg:postcode":"77840",
    "sg:province":"TX",
    "wof:name":"Texas Real Estate Services",
    "wof:placetype":"venue"
},
  "geometry": {"coordinates":[-96.32058600000001,30.599707],"type":"Point"}
}