{
  "type": "Feature",
  "properties": {
    "iso:country":"US",
    "sg:address":"2415 Pinn Rd",
    "sg:city":"San Antonio",
    "sg:classifiers":[
        {
            "category":"Retail",
            "subcategory":"Auto Repair",
            "type":"Services"
        }
    ],
    "sg:phone":"+1 210 675 2411",
    "sg:postcode":"78227",
    "sg:province":"TX",
    "sg:tags":[
        "repairing",
        "automobile",
        "general"
    ],
    "wof:name":"Affordable Motors Inc",
    "wof:placetype":"venue"
},
  "geometry": {"coordinates":[-98.62419300000001,29.403722],"type":"Point"}
}