{
  "type": "Feature",
  "properties": {
    "iso:country":"US",
    "sg:address":"22738 Cypresswood Dr",
    "sg:city":"Spring",
    "sg:classifiers":[
        {
            "category":"Health Services",
            "subcategory":"Doctor",
            "type":"Services"
        }
    ],
    "sg:phone":"+1 281 443 1515",
    "sg:postcode":"77373",
    "sg:province":"TX",
    "sg:tags":[
        "dentist"
    ],
    "wof:name":"Cypresswood Family Dental Cent",
    "wof:placetype":"venue"
},
  "geometry": {"coordinates":[-95.345934,30.044368],"type":"Point"}
}