{
  "type": "Feature",
  "properties": {
    "iso:country":"US",
    "sg:address":"12804 Gulf Fwy Ste 400",
    "sg:city":"Houston",
    "sg:classifiers":[
        {
            "category":"Health Services",
            "subcategory":"Dentist",
            "type":"Services"
        }
    ],
    "sg:phone":"+1 281 481 2048",
    "sg:postcode":"77034",
    "sg:province":"TX",
    "sg:website":"www.sunnydental.com",
    "wof:name":"Sunny Dental",
    "wof:placetype":"venue"
},
  "geometry": {"coordinates":[-95.21361400000001,29.613225],"type":"Point"}
}