{
  "type": "Feature",
  "properties": {
    "iso:country":"US",
    "sg:address":"5718 Pindula Rd",
    "sg:city":"Sealy",
    "sg:classifiers":[
        {
            "category":"Professional",
            "subcategory":"Accounting & Tax Preparation",
            "type":"Services"
        }
    ],
    "sg:phone":"+1 979 885 2119",
    "sg:postcode":"77474",
    "sg:province":"TX",
    "wof:name":"Donna A Wilson CPA",
    "wof:placetype":"venue"
},
  "geometry": {"coordinates":[-96.117053,29.738448],"type":"Point"}
}