{
  "type": "Feature",
  "properties": {
    "iso:country":"US",
    "sg:address":"110 W Martin Luther King Dr",
    "sg:city":"San Marcos",
    "sg:classifiers":[
        {
            "category":"Government",
            "subcategory":"Office",
            "type":"Public Place"
        }
    ],
    "sg:phone":"+1 512 393 7636",
    "sg:postcode":"78666",
    "sg:province":"TX",
    "wof:name":"Honorable Margie Hernandez",
    "wof:placetype":"venue"
},
  "geometry": {"coordinates":[-97.94106499999999,29.880184],"type":"Point"}
}