{
  "type": "Feature",
  "properties": {
    "iso:country":"US",
    "sg:address":"13900 Maham Rd",
    "sg:city":"Dallas",
    "sg:classifiers":[
        {
            "category":"Education",
            "subcategory":"School",
            "type":"Public Place"
        }
    ],
    "sg:phone":"+1 469 593 4900",
    "sg:postcode":"75240",
    "sg:province":"TX",
    "sg:tags":[
        "high",
        "middle",
        "elementary"
    ],
    "sg:website":"www.risd.org",
    "wof:name":"Richardson Independent School District",
    "wof:placetype":"venue"
},
  "geometry": {"coordinates":[-96.76099600000001,32.937281],"type":"Point"}
}