{
  "type": "Feature",
  "properties": {
    "iso:country":"US",
    "sg:address":"710 Avant Ave",
    "sg:city":"San Antonio",
    "sg:classifiers":[
        {
            "category":"Retail",
            "subcategory":"Laundry & Dry Cleaning",
            "type":"Services"
        }
    ],
    "sg:phone":"+1 210 532 3222",
    "sg:postcode":"78210",
    "sg:province":"TX",
    "wof:name":"Carpet Pros",
    "wof:placetype":"venue"
},
  "geometry": {"coordinates":[-98.459182,29.39526],"type":"Point"}
}