{
  "type": "Feature",
  "properties": {
    "iso:country":"US",
    "sg:address":"20315 Louetta Crossing Dr",
    "sg:city":"Spring",
    "sg:classifiers":[
        {
            "category":"Retail",
            "subcategory":"Laundry & Dry Cleaning",
            "type":"Services"
        },
        {
            "category":"Building & Trades",
            "subcategory":"Cleaning & Sanitation",
            "type":"Services"
        }
    ],
    "sg:phone":"+1 713 480 9867",
    "sg:postcode":"77388",
    "sg:province":"TX",
    "sg:tags":[
        "cleaner",
        "house"
    ],
    "wof:name":"Sur Kleen Environmental",
    "wof:placetype":"venue"
},
  "geometry": {"coordinates":[-95.444594,30.058166],"type":"Point"}
}