{
  "type": "Feature",
  "properties": {
    "iso:country":"US",
    "sg:address":"9990 Perrin Beitel Rd",
    "sg:city":"San Antonio",
    "sg:classifiers":[
        {
            "category":"Retail",
            "subcategory":"Auto Rental",
            "type":"Services"
        }
    ],
    "sg:phone":"+1 210 646 6664",
    "sg:postcode":"78217",
    "sg:province":"TX",
    "sg:tags":[
        "marina",
        "operation"
    ],
    "wof:name":"Budget Rent-A-Car",
    "wof:placetype":"venue"
},
  "geometry": {"coordinates":[-98.410984,29.530388],"type":"Point"}
}