{
  "type": "Feature",
  "properties": {
    "iso:country":"US",
    "sg:address":"403 E Brenham St",
    "sg:city":"Elgin",
    "sg:classifiers":[
        {
            "category":"Professional",
            "type":"Services"
        },
        {
            "category":"Building & Trades",
            "subcategory":"Construction",
            "type":"Services"
        }
    ],
    "sg:phone":"+1 512 285 5400",
    "sg:postcode":"78621",
    "sg:province":"TX",
    "sg:tags":[
        "home",
        "builder"
    ],
    "wof:name":"Build Your Own Amercn Dream HM",
    "wof:placetype":"venue"
},
  "geometry": {"coordinates":[-97.36506799999999,30.346374],"type":"Point"}
}