{
  "type": "Feature",
  "properties": {
    "iso:country":"US",
    "sg:address":"9305 Harwin Dr",
    "sg:city":"Houston",
    "sg:classifiers":[
        {
            "category":"Manufacturing",
            "subcategory":"Electronics",
            "type":"Manufacturing & Wholesale Goods"
        }
    ],
    "sg:phone":"+1 713 782 7797",
    "sg:postcode":"77036",
    "sg:province":"TX",
    "sg:tags":[
        "equipment",
        "mfg",
        "communication"
    ],
    "wof:name":"Wireless Phone Cmmunicationcom",
    "wof:placetype":"venue"
},
  "geometry": {"coordinates":[-95.527976,29.717825],"type":"Point"}
}