{
  "type": "Feature",
  "properties": {
    "iso:country":"US",
    "sg:address":"4800 Clarkson Ave",
    "sg:city":"Austin",
    "sg:classifiers":[
        {
            "category":"Professional",
            "type":"Services"
        }
    ],
    "sg:phone":"+1 512 420 0179",
    "sg:postcode":"78751",
    "sg:province":"TX",
    "wof:name":"Spring Break Trips",
    "wof:placetype":"venue"
},
  "geometry": {"coordinates":[-97.71592099999999,30.31056],"type":"Point"}
}