{
  "type": "Feature",
  "properties": {
    "iso:country":"US",
    "sg:address":"1528 Bennett St",
    "sg:city":"Bryan",
    "sg:classifiers":[
        {
            "category":"Professional",
            "subcategory":"Business Services",
            "type":"Services"
        }
    ],
    "sg:phone":"+1 979 822 7897",
    "sg:postcode":"77802",
    "sg:province":"TX",
    "sg:tags":[
        "arbitration",
        "mediation"
    ],
    "wof:name":"Milden J Fox Jr",
    "wof:placetype":"venue"
},
  "geometry": {"coordinates":[-96.35791999999999,30.65846],"type":"Point"}
}