{
  "type": "Feature",
  "properties": {
    "iso:country":"US",
    "sg:address":"2636 Tibbets Dr",
    "sg:city":"Bedford",
    "sg:classifiers":[
        {
            "category":"Health Services",
            "subcategory":"Doctor",
            "type":"Services"
        }
    ],
    "sg:phone":"+1 817 283 0881",
    "sg:postcode":"76022",
    "sg:province":"TX",
    "sg:tags":[
        "clinic"
    ],
    "wof:name":"Capello Juan J",
    "wof:placetype":"venue"
},
  "geometry": {"coordinates":[-97.124039,32.832797],"type":"Point"}
}