{
  "type": "Feature",
  "properties": {
    "iso:country":"US",
    "sg:address":"1532 Commercial Ave",
    "sg:city":"Anson",
    "sg:classifiers":[
        {
            "category":"Travel",
            "subcategory":"Hotels & Motels",
            "type":"Entertainment"
        }
    ],
    "sg:phone":"+1 325 823 4117",
    "sg:postcode":"79501",
    "sg:province":"TX",
    "wof:name":"Anson Inn",
    "wof:placetype":"venue"
},
  "geometry": {"coordinates":[-99.896874,32.75278],"type":"Point"}
}