{
  "type": "Feature",
  "properties": {
    "iso:country":"US",
    "sg:address":"113 Circle Vis",
    "sg:city":"Gatesville",
    "sg:classifiers":[
        {
            "category":"Building & Trades",
            "subcategory":"Plumbing",
            "type":"Services"
        }
    ],
    "sg:phone":"+1 254 865 6625",
    "sg:postcode":"76528",
    "sg:province":"TX",
    "sg:tags":[
        "plumber",
        "industrial",
        "contractors-commercial"
    ],
    "wof:name":"Double S Plumbing",
    "wof:placetype":"venue"
},
  "geometry": {"coordinates":[-97.842697,31.338704],"type":"Point"}
}