{
  "type": "Feature",
  "properties": {
    "iso:country":"US",
    "sg:address":"815 Lindbergh Dr",
    "sg:city":"Beaumont",
    "sg:classifiers":[
        {
            "category":"Health Services",
            "subcategory":"Chiropractor",
            "type":"Services"
        }
    ],
    "sg:phone":"+1 409 840 9300",
    "sg:postcode":"77707",
    "sg:province":"TX",
    "wof:name":"Rising Chiropractic Clinic",
    "wof:placetype":"venue"
},
  "geometry": {"coordinates":[-94.155413,30.068758],"type":"Point"}
}