{
  "type": "Feature",
  "properties": {
    "iso:country":"US",
    "sg:address":"1010 Cecelia St",
    "sg:city":"Taylor",
    "sg:classifiers":[
        {
            "category":"Building & Trades",
            "subcategory":"Construction",
            "type":"Services"
        }
    ],
    "sg:phone":"+1 512 365 5400",
    "sg:postcode":"76574",
    "sg:province":"TX",
    "sg:tags":[
        "hanging",
        "contractor"
    ],
    "wof:name":"Improve Properties",
    "wof:placetype":"venue"
},
  "geometry": {"coordinates":[-97.421047,30.576037],"type":"Point"}
}