{
  "type": "Feature",
  "properties": {
    "iso:country":"US",
    "sg:address":"8810 Spicebrush Dr",
    "sg:city":"Austin",
    "sg:classifiers":[
        {
            "category":"Professional",
            "subcategory":"Computer Services",
            "type":"Services"
        }
    ],
    "sg:phone":"+1 512 342 0203",
    "sg:postcode":"78759",
    "sg:province":"TX",
    "sg:tags":[
        "programing",
        "custom"
    ],
    "wof:name":"El Rey Software Services",
    "wof:placetype":"venue"
},
  "geometry": {"coordinates":[-97.773612,30.395046],"type":"Point"}
}