{
  "type": "Feature",
  "properties": {
    "iso:country":"US",
    "sg:address":"2969 Southmost Rd",
    "sg:city":"Brownsville",
    "sg:classifiers":[
        {
            "category":"Insurance",
            "subcategory":"Insurance Agent",
            "type":"Services"
        }
    ],
    "sg:phone":"+1 956 544 6445",
    "sg:postcode":"78521",
    "sg:province":"TX",
    "sg:website":"www.brownsvilleinsurance.com",
    "wof:name":"Allstate Insurance",
    "wof:placetype":"venue"
},
  "geometry": {"coordinates":[-97.463026,25.906231],"type":"Point"}
}