{
  "type": "Feature",
  "properties": {
    "iso:country":"US",
    "sg:address":"1624 N 16th St",
    "sg:city":"Waco",
    "sg:classifiers":[
        {
            "category":"Personal",
            "type":"Services"
        }
    ],
    "sg:phone":"+1 254 235 6568",
    "sg:postcode":"76707",
    "sg:province":"TX",
    "wof:name":"Wacos Greatest Sitters",
    "wof:placetype":"venue"
},
  "geometry": {"coordinates":[-97.154276,31.559928],"type":"Point"}
}