{
  "type": "Feature",
  "properties": {
    "iso:country":"US",
    "sg:address":"4844 Samuell Blvd",
    "sg:city":"Mesquite",
    "sg:classifiers":[
        {
            "category":"Wholesale",
            "subcategory":"Auto Parts",
            "type":"Manufacturing & Wholesale Goods"
        }
    ],
    "sg:phone":"+1 214 327 2780",
    "sg:postcode":"75149",
    "sg:province":"TX",
    "sg:tags":[
        "accessory"
    ],
    "wof:name":"Age Classic Design Inc",
    "wof:placetype":"venue"
},
  "geometry": {"coordinates":[-96.67045,32.792159],"type":"Point"}
}