{
  "type": "Feature",
  "properties": {
    "iso:country":"US",
    "sg:address":"10102 Synott Rd",
    "sg:city":"Sugar Land",
    "sg:classifiers":[
        {
            "category":"Building & Trades",
            "subcategory":"Construction",
            "type":"Services"
        }
    ],
    "sg:phone":"+1 281 495 8965",
    "sg:postcode":"77478",
    "sg:province":"TX",
    "sg:tags":[
        "steel",
        "erectors"
    ],
    "wof:name":"Vulcan Steel Erectors Inc",
    "wof:placetype":"venue"
},
  "geometry": {"coordinates":[-95.61738200000001,29.66719],"type":"Point"}
}