{
  "type": "Feature",
  "properties": {
    "iso:country":"US",
    "sg:address":"7715 Baughman Dr",
    "sg:city":"Amarillo",
    "sg:classifiers":[
        {
            "category":"Autos & Motor Vehicles",
            "subcategory":"Auto Supplies",
            "type":"Retail Goods"
        }
    ],
    "sg:phone":"+1 806 355 0383",
    "sg:postcode":"79121",
    "sg:province":"TX",
    "sg:tags":[
        "tire"
    ],
    "wof:name":"Jones Tire",
    "wof:placetype":"venue"
},
  "geometry": {"coordinates":[-101.931911,35.169197],"type":"Point"}
}