{
  "type": "Feature",
  "properties": {
    "iso:country":"US",
    "sg:address":"185 Talford St",
    "sg:city":"Fairfield",
    "sg:classifiers":[
        {
            "category":"Retail",
            "subcategory":"Auto Repair",
            "type":"Services"
        }
    ],
    "sg:phone":"+1 903 389 3956",
    "sg:postcode":"75840",
    "sg:province":"TX",
    "sg:tags":[
        "general"
    ],
    "wof:name":"Millers Small Engine Repair",
    "wof:placetype":"venue"
},
  "geometry": {"coordinates":[-96.143182,31.725634],"type":"Point"}
}