{
  "type": "Feature",
  "properties": {
    "iso:country":"US",
    "sg:address":"909 Oak Dr",
    "sg:city":"Flower Mound",
    "sg:classifiers":[
        {
            "category":"Professional",
            "subcategory":"Management & Consulting",
            "type":"Services"
        }
    ],
    "sg:phone":"+1 972 539 6227",
    "sg:postcode":"75028",
    "sg:province":"TX",
    "wof:name":"C & Bs Compu Shot",
    "wof:placetype":"venue"
},
  "geometry": {"coordinates":[-97.04006200000001,33.024848],"type":"Point"}
}