{
  "type": "Feature",
  "properties": {
    "iso:country":"US",
    "sg:address":"2000 E Cesar Chavez St",
    "sg:city":"Austin",
    "sg:classifiers":[
        {
            "category":"Recreation",
            "type":"Entertainment"
        },
        {
            "category":"Organizations",
            "subcategory":"Community Association",
            "type":"Services"
        }
    ],
    "sg:phone":"+1 512 474 9364",
    "sg:postcode":"78702",
    "sg:province":"TX",
    "sg:tags":[
        "club",
        "membership"
    ],
    "wof:name":"Capuchino's Gameroom & Bar",
    "wof:placetype":"venue"
},
  "geometry": {"coordinates":[-97.723326,30.256663],"type":"Point"}
}