{
  "type": "Feature",
  "properties": {
    "iso:country":"US",
    "sg:address":"625 N Beaton St",
    "sg:city":"Corsicana",
    "sg:classifiers":[
        {
            "category":"Real Estate",
            "subcategory":"Real Estate Agent",
            "type":"Services"
        }
    ],
    "sg:phone":"+1 903 872 9400",
    "sg:postcode":"75110",
    "sg:province":"TX",
    "wof:name":"One Way Home & Land Co Inc",
    "wof:placetype":"venue"
},
  "geometry": {"coordinates":[-96.467901,32.10013],"type":"Point"}
}