{
  "type": "Feature",
  "properties": {
    "iso:country":"US",
    "sg:address":"147 Conley Pl",
    "sg:city":"Odessa",
    "sg:classifiers":[
        {
            "category":"Wholesale",
            "subcategory":"Machinery & Supplies",
            "type":"Manufacturing & Wholesale Goods"
        }
    ],
    "sg:phone":"+1 432 363 3797",
    "sg:postcode":"79762",
    "sg:province":"TX",
    "sg:tags":[
        "equipment",
        "safety",
        "clothing"
    ],
    "wof:name":"Southwest Specialty",
    "wof:placetype":"venue"
},
  "geometry": {"coordinates":[-102.361908,31.89971],"type":"Point"}
}