{
  "type": "Feature",
  "properties": {
    "iso:country":"US",
    "sg:address":"7801 Southeast Dr",
    "sg:city":"Lubbock",
    "sg:classifiers":[
        {
            "category":"Wholesale",
            "subcategory":"Construction Materials",
            "type":"Manufacturing & Wholesale Goods"
        }
    ],
    "sg:phone":"+1 806 762 6076",
    "sg:postcode":"79404",
    "sg:province":"TX",
    "sg:tags":[
        "pallet",
        "skid"
    ],
    "sg:website":"www.ifco-us.com",
    "wof:name":"Ifco Systems",
    "wof:placetype":"venue"
},
  "geometry": {"coordinates":[-101.777576,33.522569],"type":"Point"}
}