{
  "type": "Feature",
  "properties": {
    "iso:country":"US",
    "sg:address":"1307 Fort Branch Boulevard",
    "sg:city":"Austin",
    "sg:classifiers":[
        {
            "category":"Social Services",
            "subcategory":"Child Care",
            "type":"Services"
        }
    ],
    "sg:phone":"+1 512 220 1527",
    "sg:postcode":"78721",
    "sg:province":"TX",
    "sg:tags":[
        "day"
    ],
    "wof:name":"True Light Daycare",
    "wof:placetype":"venue"
},
  "geometry": {"coordinates":[-97.680178,30.277491],"type":"Point"}
}