{
  "type": "Feature",
  "properties": {
    "iso:country":"US",
    "sg:address":"1817 Concord St",
    "sg:city":"Deer Park",
    "sg:classifiers":[
        {
            "category":"Retail",
            "subcategory":"Repair Shop",
            "type":"Services"
        }
    ],
    "sg:phone":"+1 281 479 3939",
    "sg:postcode":"77536",
    "sg:province":"TX",
    "sg:tags":[
        "repairing",
        "organs"
    ],
    "wof:name":"Benton's Electronics",
    "wof:placetype":"venue"
},
  "geometry": {"coordinates":[-95.14117299999999,29.685059],"type":"Point"}
}