{
  "type": "Feature",
  "properties": {
    "iso:country":"US",
    "sg:address":"1720 W Northwest Hwy",
    "sg:city":"Dallas",
    "sg:classifiers":[
        {
            "category":"Professional",
            "subcategory":"Management & Consulting",
            "type":"Services"
        }
    ],
    "sg:phone":"+1 214 352 0490",
    "sg:postcode":"75220",
    "sg:province":"TX",
    "sg:tags":[
        "consultant",
        "business"
    ],
    "wof:name":"American Management Inc",
    "wof:placetype":"venue"
},
  "geometry": {"coordinates":[-96.917502,32.870086],"type":"Point"}
}