{
  "type": "Feature",
  "properties": {
    "iso:country":"US",
    "sg:address":"505 Huntland Dr E",
    "sg:city":"Austin",
    "sg:classifiers":[
        {
            "category":"Professional",
            "subcategory":"Management & Consulting",
            "type":"Services"
        }
    ],
    "sg:phone":"+1 512 832 5300",
    "sg:postcode":"78752",
    "sg:province":"TX",
    "sg:tags":[
        "personnel",
        "consultant"
    ],
    "wof:name":"Sedona Group",
    "wof:placetype":"venue"
},
  "geometry": {"coordinates":[-97.707796,30.330848],"type":"Point"}
}