{
  "type": "Feature",
  "properties": {
    "iso:country":"US",
    "sg:address":"1450 E Hwy 90",
    "sg:city":"Liberty",
    "sg:classifiers":[
        {
            "category":"Autos & Motor Vehicles",
            "subcategory":"Auto Supplies",
            "type":"Retail Goods"
        }
    ],
    "sg:phone":"+1 936 336 8676",
    "sg:postcode":"77575",
    "sg:province":"TX",
    "wof:name":"Autozone",
    "wof:placetype":"venue"
},
  "geometry": {"coordinates":[-94.727541,30.051013],"type":"Point"}
}