{
  "type": "Feature",
  "properties": {
    "iso:country":"US",
    "sg:address":"2400 Dallas Pkwy",
    "sg:city":"Plano",
    "sg:classifiers":[
        {
            "category":"Manufacturing",
            "subcategory":"Rubber & Plastics",
            "type":"Manufacturing & Wholesale Goods"
        }
    ],
    "sg:phone":"+1 972 443 1776",
    "sg:postcode":"75093",
    "sg:province":"TX",
    "sg:tags":[
        "product",
        "mfg",
        "injection",
        "molded"
    ],
    "wof:name":"Cornerstone Products Inc",
    "wof:placetype":"venue"
},
  "geometry": {"coordinates":[-96.82869599999999,33.031384],"type":"Point"}
}