{
  "type": "Feature",
  "properties": {
    "iso:country":"US",
    "sg:address":"8612 Preston Rd",
    "sg:city":"Plano",
    "sg:classifiers":[
        {
            "category":"Professional",
            "type":"Services"
        }
    ],
    "sg:phone":"+1 972 668 8200",
    "sg:postcode":"75024",
    "sg:province":"TX",
    "sg:tags":[
        "establishment"
    ],
    "wof:name":"Coldwell Banker Residential",
    "wof:placetype":"venue"
},
  "geometry": {"coordinates":[-96.80538199999999,33.096041],"type":"Point"}
}