{
  "type": "Feature",
  "properties": {
    "iso:country":"US",
    "sg:address":"13027 Brittmoore Park Dr",
    "sg:city":"Houston",
    "sg:classifiers":[
        {
            "category":"Wholesale",
            "subcategory":"Durable Goods & Equipment",
            "type":"Manufacturing & Wholesale Goods"
        }
    ],
    "sg:phone":"+1 713 466 6414",
    "sg:postcode":"77041",
    "sg:province":"TX",
    "sg:tags":[
        "guitar",
        "parts"
    ],
    "wof:name":"Allparts",
    "wof:placetype":"venue"
},
  "geometry": {"coordinates":[-95.585584,29.850971],"type":"Point"}
}