{
  "type": "Feature",
  "properties": {
    "iso:country":"US",
    "sg:address":"329 W State St",
    "sg:city":"Pharr",
    "sg:classifiers":[
        {
            "category":"Government",
            "subcategory":"Office",
            "type":"Public Place"
        }
    ],
    "sg:phone":"+1 956 787 4941",
    "sg:postcode":"78577",
    "sg:province":"TX",
    "wof:name":"Hidalgo County Shop",
    "wof:placetype":"venue"
},
  "geometry": {"coordinates":[-98.187702,26.196215],"type":"Point"}
}