{
  "type": "Feature",
  "properties": {
    "iso:country":"US",
    "sg:address":"2924 Ave K",
    "sg:city":"Bay City",
    "sg:classifiers":[
        {
            "category":"Professional",
            "subcategory":"Accounting & Tax Preparation",
            "type":"Services"
        }
    ],
    "sg:phone":"+1 979 245 0373",
    "sg:postcode":"77414",
    "sg:province":"TX",
    "sg:tags":[
        "return",
        "filing"
    ],
    "wof:name":"Trisha's Tax & Bookkeeping",
    "wof:placetype":"venue"
},
  "geometry": {"coordinates":[-95.963763,28.974461],"type":"Point"}
}