{
  "type": "Feature",
  "properties": {
    "iso:country":"US",
    "sg:address":"1201 E 15th St",
    "sg:city":"Plano",
    "sg:classifiers":[
        {
            "category":"Health Services",
            "subcategory":"Health Practitioner",
            "type":"Services"
        }
    ],
    "sg:phone":"+1 972 516 1777",
    "sg:postcode":"75074",
    "sg:province":"TX",
    "wof:name":"Day Spring Center",
    "wof:placetype":"venue"
},
  "geometry": {"coordinates":[-96.696365,33.019691],"type":"Point"}
}