{
  "type": "Feature",
  "properties": {
    "iso:country":"US",
    "sg:address":"112 US Hwy 281",
    "sg:city":"Falfurrias",
    "sg:classifiers":[
        {
            "category":"Autos & Motor Vehicles",
            "subcategory":"Fuel & Gas Station",
            "type":"Retail Goods"
        }
    ],
    "sg:phone":"+1 361 325 5613",
    "sg:postcode":"78355",
    "sg:province":"TX",
    "sg:tags":[
        "plaza",
        "truck",
        "stops"
    ],
    "wof:name":"El Heart's Delight Travel Ctr",
    "wof:placetype":"venue"
},
  "geometry": {"coordinates":[-98.144318,27.22666],"type":"Point"}
}