{
  "type": "Feature",
  "properties": {
    "iso:country":"US",
    "sg:address":"9339 Clearway Dr",
    "sg:city":"Houston",
    "sg:classifiers":[
        {
            "category":"Real Estate",
            "subcategory":"Real Estate Agent",
            "type":"Services"
        }
    ],
    "sg:phone":"+1 713 733 3211",
    "sg:postcode":"77033",
    "sg:province":"TX",
    "wof:name":"Inregard Properties",
    "wof:placetype":"venue"
},
  "geometry": {"coordinates":[-95.33381300000001,29.647154],"type":"Point"}
}