{
  "type": "Feature",
  "properties": {
    "iso:country":"US",
    "sg:address":"806 E Calton Rd",
    "sg:city":"Laredo",
    "sg:classifiers":[
        {
            "category":"Education",
            "subcategory":"School",
            "type":"Public Place"
        }
    ],
    "sg:phone":"+1 956 753 8777",
    "sg:postcode":"78041",
    "sg:province":"TX",
    "sg:tags":[
        "academic",
        "special"
    ],
    "wof:name":"Lollipop Learning Ctr",
    "wof:placetype":"venue"
},
  "geometry": {"coordinates":[-99.486357,27.541463],"type":"Point"}
}