{
  "type": "Feature",
  "properties": {
    "iso:country":"US",
    "sg:address":"14038 Sunset Ct",
    "sg:city":"Forney",
    "sg:classifiers":[
        {
            "category":"Home & Garden",
            "subcategory":"Furniture",
            "type":"Retail Goods"
        }
    ],
    "sg:phone":"+1 972 552 1012",
    "sg:postcode":"75126",
    "sg:province":"TX",
    "wof:name":"Home Center",
    "wof:placetype":"venue"
},
  "geometry": {"coordinates":[-96.4841,32.735269],"type":"Point"}
}