{
  "type": "Feature",
  "properties": {
    "iso:country":"US",
    "sg:address":"2306 Port Lavaca Dr",
    "sg:city":"Victoria",
    "sg:classifiers":[
        {
            "category":"Building & Trades",
            "subcategory":"Construction",
            "type":"Services"
        }
    ],
    "sg:phone":"+1 361 576 0926",
    "sg:postcode":"77901",
    "sg:province":"TX",
    "sg:tags":[
        "roofing",
        "industrial",
        "contractors-commercial",
        "waterproofing",
        "contractor"
    ],
    "wof:name":"Rain Seal Master Roofing And Sheet Metal, Inc.",
    "wof:placetype":"venue"
},
  "geometry": {"coordinates":[-96.98540199999999,28.790711],"type":"Point"}
}