{
  "type": "Feature",
  "properties": {
    "iso:country":"US",
    "sg:address":"814 Myrtle Ave",
    "sg:city":"El Paso",
    "sg:classifiers":[
        {
            "category":"Health Services",
            "subcategory":"Health Practitioner",
            "type":"Services"
        }
    ],
    "sg:phone":"+1 915 588 1168",
    "sg:postcode":"79901",
    "sg:province":"TX",
    "sg:tags":[
        "psychotherapist"
    ],
    "wof:name":"Interventions International",
    "wof:placetype":"venue"
},
  "geometry": {"coordinates":[-106.480645,31.761797],"type":"Point"}
}