{
  "type": "Feature",
  "properties": {
    "iso:country":"US",
    "sg:address":"309 N Garza Rd",
    "sg:city":"Denton",
    "sg:classifiers":[
        {
            "category":"Manufacturing",
            "subcategory":"Textiles",
            "type":"Manufacturing & Wholesale Goods"
        }
    ],
    "sg:phone":"+1 940 321 2603",
    "sg:postcode":"76208",
    "sg:province":"TX",
    "sg:tags":[
        "finishing",
        "plant",
        "cotton"
    ],
    "wof:name":"Chris Tees",
    "wof:placetype":"venue"
},
  "geometry": {"coordinates":[-97.039731,33.17074],"type":"Point"}
}