{
  "type": "Feature",
  "properties": {
    "iso:country":"US",
    "sg:address":"2661 Dowdy Ferry Rd",
    "sg:city":"Dallas",
    "sg:classifiers":[
        {
            "category":"Autos & Motor Vehicles",
            "subcategory":"Automobile Sales",
            "type":"Retail Goods"
        },
        {
            "category":"Autos & Motor Vehicles",
            "subcategory":"Auto Supplies",
            "type":"Retail Goods"
        }
    ],
    "sg:phone":"+1 972 286 0833",
    "sg:postcode":"75217",
    "sg:province":"TX",
    "sg:tags":[
        "used",
        "car",
        "dealers-used",
        "part",
        "supplies-used",
        "rebuilt",
        "cars-wholesale"
    ],
    "wof:name":"Dowdy Ferry Auto",
    "wof:placetype":"venue"
},
  "geometry": {"coordinates":[-96.675405,32.659624],"type":"Point"}
}