{
  "type": "Feature",
  "properties": {
    "iso:country":"US",
    "sg:address":"8505 Lavender St",
    "sg:city":"Houston",
    "sg:classifiers":[
        {
            "category":"Professional",
            "subcategory":"Business Services",
            "type":"Services"
        }
    ],
    "sg:phone":"+1 713 631 8396",
    "sg:postcode":"77016",
    "sg:province":"TX",
    "wof:name":"Krm Enterprises",
    "wof:placetype":"venue"
},
  "geometry": {"coordinates":[-95.32156000000001,29.840429],"type":"Point"}
}