{
  "type": "Feature",
  "properties": {
    "iso:country":"US",
    "sg:address":"704 Park St",
    "sg:city":"Azle",
    "sg:classifiers":[
        {
            "category":"Building & Trades",
            "subcategory":"Construction",
            "type":"Services"
        }
    ],
    "sg:phone":"+1 817 444 3299",
    "sg:postcode":"76020",
    "sg:province":"TX",
    "sg:tags":[
        "general",
        "contractor"
    ],
    "wof:name":"M & M Builders",
    "wof:placetype":"venue"
},
  "geometry": {"coordinates":[-97.53492799999999,32.890428],"type":"Point"}
}