{
  "type": "Feature",
  "properties": {
    "iso:country":"US",
    "sg:address":"9332 Summerbell Ln",
    "sg:city":"Houston",
    "sg:classifiers":[
        {
            "category":"Autos & Motor Vehicles",
            "subcategory":"Automobile Sales",
            "type":"Retail Goods"
        }
    ],
    "sg:phone":"+1 713 541 3030",
    "sg:postcode":"77074",
    "sg:province":"TX",
    "sg:tags":[
        "used"
    ],
    "wof:name":"Pameer Autos",
    "wof:placetype":"venue"
},
  "geometry": {"coordinates":[-95.53900400000001,29.671584],"type":"Point"}
}