{
  "type": "Feature",
  "properties": {
    "iso:country":"US",
    "sg:address":"900 Forest Vista Dr",
    "sg:city":"Flower Mound",
    "sg:classifiers":[
        {
            "category":"Education",
            "subcategory":"School",
            "type":"Public Place"
        }
    ],
    "sg:phone":"+1 972 355 3332",
    "sg:postcode":"75028",
    "sg:province":"TX",
    "sg:website":"www.lisd.net",
    "wof:name":"Forest Vista Elementary School",
    "wof:placetype":"venue"
},
  "geometry": {"coordinates":[-97.045346,33.019456],"type":"Point"}
}