{
  "type": "Feature",
  "properties": {
    "iso:country":"US",
    "sg:address":"32344 State Hwy 249",
    "sg:city":"Pinehurst",
    "sg:classifiers":[
        {
            "category":"Professional",
            "type":"Services"
        }
    ],
    "sg:phone":"+1 281 259 7486",
    "sg:postcode":"77362",
    "sg:province":"TX",
    "sg:tags":[
        "establishment"
    ],
    "wof:name":"NNM Inc",
    "wof:placetype":"venue"
},
  "geometry": {"coordinates":[-95.65532,30.136634],"type":"Point"}
}