{
  "type": "Feature",
  "properties": {
    "iso:country":"US",
    "sg:address":"585 River Bend Ln",
    "sg:city":"Martindale",
    "sg:classifiers":[
        {
            "category":"Professional",
            "subcategory":"Business Services",
            "type":"Services"
        }
    ],
    "sg:phone":"+1 512 357 6960",
    "sg:postcode":"78655",
    "sg:province":"TX",
    "wof:name":"Pro Spec Trec 4613",
    "wof:placetype":"venue"
},
  "geometry": {"coordinates":[-97.870177,29.853334],"type":"Point"}
}