{
  "type": "Feature",
  "properties": {
    "iso:country":"US",
    "sg:address":"531 N Main St",
    "sg:city":"Schulenburg",
    "sg:classifiers":[
        {
            "category":"Shopping",
            "subcategory":"Discount & Variety Stores",
            "type":"Retail Goods"
        }
    ],
    "sg:phone":"+1 979 743 3557",
    "sg:postcode":"78956",
    "sg:province":"TX",
    "sg:tags":[
        "merchandise",
        "general"
    ],
    "wof:name":"Western Auto Assoc Store",
    "wof:placetype":"venue"
},
  "geometry": {"coordinates":[-96.905242,29.679926],"type":"Point"}
}