{
  "type": "Feature",
  "properties": {
    "iso:country":"US",
    "sg:address":"7573 Alameda Ave",
    "sg:city":"El Paso",
    "sg:classifiers":[
        {
            "category":"Bars & Pubs",
            "type":"Food & Drink"
        }
    ],
    "sg:phone":"+1 915 779 7244",
    "sg:postcode":"79915",
    "sg:province":"TX",
    "sg:tags":[
        "drinking"
    ],
    "wof:name":"El Escandalo",
    "wof:placetype":"venue"
},
  "geometry": {"coordinates":[-106.371408,31.736986],"type":"Point"}
}