{
  "type": "Feature",
  "properties": {
    "iso:country":"US",
    "sg:address":"1311 Emily Morgan Cir",
    "sg:city":"Richmond",
    "sg:classifiers":[
        {
            "category":"Professional",
            "subcategory":"Business Services",
            "type":"Services"
        }
    ],
    "sg:phone":"+1 832 595 2500",
    "sg:postcode":"77469",
    "sg:province":"TX",
    "wof:name":"Express Business Solutions",
    "wof:placetype":"venue"
},
  "geometry": {"coordinates":[-95.739813,29.613974],"type":"Point"}
}