{
  "type": "Feature",
  "properties": {
    "iso:country":"US",
    "sg:address":"10405 Co Rd 2258",
    "sg:city":"Tyler",
    "sg:classifiers":[
        {
            "category":"Retail",
            "subcategory":"Repair Shop",
            "type":"Services"
        }
    ],
    "sg:phone":"+1 903 597 6179",
    "sg:postcode":"75707",
    "sg:province":"TX",
    "wof:name":"A&A Antenna Satellite Systems",
    "wof:placetype":"venue"
},
  "geometry": {"coordinates":[-95.14105499999999,32.327884],"type":"Point"}
}