{
  "type": "Feature",
  "properties": {
    "iso:country":"US",
    "sg:address":"3624 Kim Dr",
    "sg:city":"Irving",
    "sg:classifiers":[
        {
            "category":"Building & Trades",
            "subcategory":"Construction",
            "type":"Services"
        }
    ],
    "sg:phone":"+1 972 687 0115",
    "sg:postcode":"75061",
    "sg:province":"TX",
    "sg:tags":[
        "painter"
    ],
    "wof:name":"Skinny-Tex Painting/Decorating",
    "wof:placetype":"venue"
},
  "geometry": {"coordinates":[-96.994721,32.820218],"type":"Point"}
}