{
  "type": "Feature",
  "properties": {
    "iso:country":"US",
    "sg:address":"7621 Fm 1960 Rd W",
    "sg:city":"Houston",
    "sg:classifiers":[
        {
            "category":"Restaurant",
            "type":"Food & Drink"
        }
    ],
    "sg:menulink":"http://www.allmenus.com/tx/northwest-harris/46976-chilis/menu/",
    "sg:phone":"+1 281 469 2200",
    "sg:postcode":"77070",
    "sg:province":"TX",
    "sg:tags":[
        "burger",
        "american",
        "sandwich",
        "tex-mex",
        "soup"
    ],
    "wof:name":"Chili's",
    "wof:placetype":"venue"
},
  "geometry": {"coordinates":[-95.543915,29.96275],"type":"Point"}
}