{
  "type": "Feature",
  "properties": {
    "iso:country":"US",
    "sg:address":"3111 Yost Blvd",
    "sg:city":"Pearland",
    "sg:classifiers":[
        {
            "category":"Building & Trades",
            "subcategory":"Construction",
            "type":"Services"
        }
    ],
    "sg:phone":"+1 281 485 1974",
    "sg:postcode":"77581",
    "sg:province":"TX",
    "sg:tags":[
        "house"
    ],
    "wof:name":"D JS Home Repair",
    "wof:placetype":"venue"
},
  "geometry": {"coordinates":[-95.24501600000001,29.551705],"type":"Point"}
}