{
  "type": "Feature",
  "properties": {
    "iso:country":"US",
    "sg:address":"4516 Teal Glen St",
    "sg:city":"Pearland",
    "sg:classifiers":[
        {
            "category":"Professional",
            "subcategory":"Computer Services",
            "type":"Services"
        }
    ],
    "sg:phone":"+1 281 489 4701",
    "sg:postcode":"77584",
    "sg:province":"TX",
    "sg:tags":[
        "related"
    ],
    "wof:name":"Diakonos",
    "wof:placetype":"venue"
},
  "geometry": {"coordinates":[-95.28981,29.542603],"type":"Point"}
}