{
  "type": "Feature",
  "properties": {
    "iso:country":"US",
    "sg:address":"13910 Champion Forest Dr",
    "sg:city":"Houston",
    "sg:classifiers":[
        {
            "category":"Professional",
            "subcategory":"Advertising",
            "type":"Services"
        }
    ],
    "sg:phone":"+1 281 444 5104",
    "sg:postcode":"77069",
    "sg:province":"TX",
    "sg:tags":[
        "mail"
    ],
    "wof:name":"Money Mailer Inc",
    "wof:placetype":"venue"
},
  "geometry": {"coordinates":[-95.52050199999999,29.988184],"type":"Point"}
}