{
  "type": "Feature",
  "properties": {
    "iso:country":"US",
    "sg:address":"17950 Preston Rd",
    "sg:city":"Dallas",
    "sg:classifiers":[
        {
            "category":"Banks & Credit Unions",
            "subcategory":"Investment Brokerage",
            "type":"Services"
        }
    ],
    "sg:phone":"+1 972 447 9200",
    "sg:postcode":"75252",
    "sg:province":"TX",
    "sg:tags":[
        "planning"
    ],
    "wof:name":"Bank of America",
    "wof:placetype":"venue"
},
  "geometry": {"coordinates":[-96.799648,32.994585],"type":"Point"}
}