{
  "type": "Feature",
  "properties": {
    "iso:country":"US",
    "sg:address":"121 Oak Ave",
    "sg:city":"Sulphur Springs",
    "sg:classifiers":[
        {
            "category":"Professional",
            "subcategory":"Lawyer & Legal Services",
            "type":"Services"
        }
    ],
    "sg:phone":"+1 903 885 8691",
    "sg:postcode":"75482",
    "sg:province":"TX",
    "sg:tags":[
        "attorney"
    ],
    "wof:name":"Raymond R Johnson",
    "wof:placetype":"venue"
},
  "geometry": {"coordinates":[-95.600328,33.13714],"type":"Point"}
}