{
  "type": "Feature",
  "properties": {
    "iso:country":"US",
    "sg:address":"404 Hawkins St",
    "sg:city":"Hillsboro",
    "sg:classifiers":[
        {
            "category":"Home & Garden",
            "subcategory":"Furniture",
            "type":"Retail Goods"
        },
        {
            "category":"Wholesale",
            "subcategory":"Home Furnishings",
            "type":"Manufacturing & Wholesale Goods"
        }
    ],
    "sg:phone":"+1 254 580 1200",
    "sg:postcode":"76645",
    "sg:province":"TX",
    "sg:tags":[
        "equipment-wholesale",
        "kitchen",
        "equipment-household",
        "manufacturer",
        "cabinet"
    ],
    "sg:website":"http://www.brandom.com",
    "wof:name":"Brandom Cabinets",
    "wof:placetype":"venue"
},
  "geometry": {"coordinates":[-97.134708,32.005592],"type":"Point"}
}