{
  "type": "Feature",
  "properties": {
    "iso:country":"US",
    "sg:address":"12818 Reedwood Ridge Rd",
    "sg:city":"Houston",
    "sg:classifiers":[
        {
            "category":"Professional",
            "type":"Services"
        }
    ],
    "sg:phone":"+1 281 477 8676",
    "sg:postcode":"77065",
    "sg:province":"TX",
    "sg:tags":[
        "establishment"
    ],
    "wof:name":"Inventure Technologies Inc",
    "wof:placetype":"venue"
},
  "geometry": {"coordinates":[-95.611265,29.932307],"type":"Point"}
}