{
  "type": "Feature",
  "properties": {
    "iso:country":"US",
    "sg:address":"250 W Highway 67",
    "sg:city":"Duncanville",
    "sg:classifiers":[
        {
            "category":"Health Services",
            "subcategory":"Optometrist",
            "type":"Services"
        }
    ],
    "sg:phone":"+1 972 572 9555",
    "sg:postcode":"75137",
    "sg:province":"TX",
    "wof:name":"Lee Mija J OD",
    "wof:placetype":"venue"
},
  "geometry": {"coordinates":[-96.91105899999999,32.621629],"type":"Point"}
}