{
  "type": "Feature",
  "properties": {
    "iso:country":"US",
    "sg:address":"3025 Forest Ave",
    "sg:city":"Fort Worth",
    "sg:classifiers":[
        {
            "category":"Real Estate",
            "subcategory":"Surveying",
            "type":"Services"
        }
    ],
    "sg:phone":"+1 817 429 0194",
    "sg:postcode":"76112",
    "sg:province":"TX",
    "sg:tags":[
        "surveyor"
    ],
    "wof:name":"Herbert S Beasley Land",
    "wof:placetype":"venue"
},
  "geometry": {"coordinates":[-97.21889400000001,32.734772],"type":"Point"}
}