{
  "type": "Feature",
  "properties": {
    "iso:country":"US",
    "sg:address":"305 S Commercial St",
    "sg:city":"Aransas Pass",
    "sg:classifiers":[
        {
            "category":"Shopping",
            "subcategory":"Used Merchandise",
            "type":"Retail Goods"
        }
    ],
    "sg:phone":"+1 361 758 9707",
    "sg:postcode":"78336",
    "sg:province":"TX",
    "sg:tags":[
        "shop",
        "consignment"
    ],
    "wof:name":"A J's & Gloria's Treasures",
    "wof:placetype":"venue"
},
  "geometry": {"coordinates":[-97.145314,27.903501],"type":"Point"}
}