{
  "type": "Feature",
  "properties": {
    "iso:country":"US",
    "sg:address":"4701 Nett St",
    "sg:city":"Houston",
    "sg:classifiers":[
        {
            "category":"Manufacturing",
            "subcategory":"Jewelry",
            "type":"Manufacturing & Wholesale Goods"
        }
    ],
    "sg:phone":"+1 713 861 6336",
    "sg:postcode":"77007",
    "sg:province":"TX",
    "sg:tags":[
        "mfg"
    ],
    "wof:name":"Stony Jewelry",
    "wof:placetype":"venue"
},
  "geometry": {"coordinates":[-95.409493,29.771939],"type":"Point"}
}