{
  "type": "Feature",
  "properties": {
    "iso:country":"US",
    "sg:address":"4702 Westheimer Rd",
    "sg:city":"Houston",
    "sg:classifiers":[
        {
            "category":"Restaurant",
            "type":"Food & Drink"
        }
    ],
    "sg:phone":"+1 713 629 7337",
    "sg:postcode":"77027",
    "sg:province":"TX",
    "sg:tags":[
        "traditional",
        "american",
        "brunch",
        "breakfast"
    ],
    "wof:name":"Le Peep",
    "wof:placetype":"venue"
},
  "geometry": {"coordinates":[-95.455704,29.741199],"type":"Point"}
}