{
  "type": "Feature",
  "properties": {
    "iso:country":"US",
    "sg:address":"1700 E 6th St",
    "sg:city":"Brownsville",
    "sg:classifiers":[
        {
            "category":"Building & Trades",
            "subcategory":"Construction",
            "type":"Services"
        }
    ],
    "sg:phone":"+1 956 541 1203",
    "sg:postcode":"78520",
    "sg:province":"TX",
    "sg:tags":[
        "home",
        "builder"
    ],
    "wof:name":"International Investments",
    "wof:placetype":"venue"
},
  "geometry": {"coordinates":[-97.492672,25.913741],"type":"Point"}
}