{
  "type": "Feature",
  "properties": {
    "iso:country":"US",
    "sg:address":"2722 Wuthering Heights Dr",
    "sg:city":"Houston",
    "sg:classifiers":[
        {
            "category":"Shopping",
            "subcategory":"Bicycles & Sporting Goods",
            "type":"Retail Goods"
        }
    ],
    "sg:phone":"+1 713 433 7810",
    "sg:postcode":"77045",
    "sg:province":"TX",
    "wof:name":"Blazing Saddles Transport",
    "wof:placetype":"venue"
},
  "geometry": {"coordinates":[-95.414733,29.633263],"type":"Point"}
}