{
  "type": "Feature",
  "properties": {
    "iso:country":"US",
    "sg:address":"3305 W Slaughter Ln",
    "sg:city":"Austin",
    "sg:classifiers":[
        {
            "category":"Insurance",
            "subcategory":"Insurance Agent",
            "type":"Services"
        }
    ],
    "sg:phone":"+1 512 441 8597",
    "sg:postcode":"78748",
    "sg:province":"TX",
    "wof:name":"Allstate",
    "wof:placetype":"venue"
},
  "geometry": {"coordinates":[-97.84983200000001,30.18341],"type":"Point"}
}