{
  "type": "Feature",
  "properties": {
    "iso:country":"US",
    "sg:address":"5300 Jimmy Clay Dr",
    "sg:city":"Austin",
    "sg:classifiers":[
        {
            "category":"Professional",
            "subcategory":"Business Services",
            "type":"Services"
        }
    ],
    "sg:phone":"+1 512 693 4636",
    "sg:postcode":"78744",
    "sg:province":"TX",
    "sg:tags":[
        "information",
        "referral"
    ],
    "wof:name":"Info Ology",
    "wof:placetype":"venue"
},
  "geometry": {"coordinates":[-97.732755,30.189435],"type":"Point"}
}