{
  "type": "Feature",
  "properties": {
    "iso:country":"US",
    "sg:address":"13705 Topper Cir",
    "sg:city":"San Antonio",
    "sg:classifiers":[
        {
            "category":"Restaurant",
            "type":"Food & Drink"
        }
    ],
    "sg:phone":"+1 210 590 6301",
    "sg:postcode":"78233",
    "sg:province":"TX",
    "wof:name":"Whataburger Maintenance San",
    "wof:placetype":"venue"
},
  "geometry": {"coordinates":[-98.358328,29.56544],"type":"Point"}
}