{
  "type": "Feature",
  "properties": {
    "iso:country":"US",
    "sg:address":"100 Main Plz",
    "sg:city":"New Braunfels",
    "sg:classifiers":[
        {
            "category":"Government",
            "subcategory":"Court House",
            "type":"Public Place"
        }
    ],
    "sg:phone":"+1 830 620 5582",
    "sg:postcode":"78130",
    "sg:province":"TX",
    "sg:tags":[
        "county"
    ],
    "wof:name":"Comal County Court-At-Law",
    "wof:placetype":"venue"
},
  "geometry": {"coordinates":[-98.124228,29.703387],"type":"Point"}
}