{
  "type": "Feature",
  "properties": {
    "iso:country":"US",
    "sg:address":"7120 Cole Creek Dr",
    "sg:city":"Houston",
    "sg:classifiers":[
        {
            "category":"Professional",
            "type":"Services"
        }
    ],
    "sg:phone":"+1 713 460 2310",
    "sg:postcode":"77092",
    "sg:province":"TX",
    "wof:name":"Eyvonne Malnado",
    "wof:placetype":"venue"
},
  "geometry": {"coordinates":[-95.49768299999999,29.853534],"type":"Point"}
}