{
  "type": "Feature",
  "properties": {
    "iso:country":"US",
    "sg:address":"149 Grape St",
    "sg:city":"Abilene",
    "sg:classifiers":[
        {
            "category":"Health Services",
            "subcategory":"Doctor",
            "type":"Services"
        },
        {
            "category":"Health Services",
            "subcategory":"Clinic",
            "type":"Services"
        }
    ],
    "sg:phone":"+1 325 676 7000",
    "sg:postcode":"79601",
    "sg:province":"TX",
    "sg:tags":[
        "physician",
        "family",
        "practice",
        "surgeons",
        "medicine",
        "surgeon"
    ],
    "wof:name":"Lien Jung C MD Family Practice",
    "wof:placetype":"venue"
},
  "geometry": {"coordinates":[-99.741654,32.450268],"type":"Point"}
}