{
  "type": "Feature",
  "properties": {
    "iso:country":"US",
    "sg:address":"304 E Milam St",
    "sg:city":"Mexia",
    "sg:classifiers":[
        {
            "category":"Food & Beverages",
            "subcategory":"Groceries & Convenience Stores",
            "type":"Retail Goods"
        }
    ],
    "sg:phone":"+1 254 562 3388",
    "sg:postcode":"76667",
    "sg:province":"TX",
    "wof:name":"Cefco Food Stores",
    "wof:placetype":"venue"
},
  "geometry": {"coordinates":[-96.482927,31.683847],"type":"Point"}
}