{
  "type": "Feature",
  "properties": {
    "iso:country":"US",
    "sg:address":"310 W Foster Ave",
    "sg:city":"Pampa",
    "sg:classifiers":[
        {
            "category":"Building & Trades",
            "subcategory":"Construction",
            "type":"Services"
        }
    ],
    "sg:phone":"+1 806 665 2133",
    "sg:postcode":"79065",
    "sg:province":"TX",
    "sg:tags":[
        "home",
        "improvement"
    ],
    "wof:name":"Home Projects",
    "wof:placetype":"venue"
},
  "geometry": {"coordinates":[-100.963155,35.535085],"type":"Point"}
}