{
  "type": "Feature",
  "properties": {
    "iso:country":"US",
    "sg:address":"103 Saddlebrook Ln",
    "sg:city":"Harper",
    "sg:classifiers":[
        {
            "category":"Retail",
            "subcategory":"Repair Shop",
            "type":"Services"
        }
    ],
    "sg:phone":"+1 830 864 4041",
    "sg:postcode":"78655",
    "sg:province":"TX",
    "sg:tags":[
        "upholsterer"
    ],
    "wof:name":"First Choice",
    "wof:placetype":"venue"
},
  "geometry": {"coordinates":[-97.87655700000001,29.810887],"type":"Point"}
}