{
  "type": "Feature",
  "properties": {
    "iso:country":"US",
    "sg:address":"1201 Willow Springs Rd",
    "sg:city":"Killeen",
    "sg:classifiers":[
        {
            "category":"Retail",
            "subcategory":"Auto Repair",
            "type":"Services"
        }
    ],
    "sg:phone":"+1 254 554 5000",
    "sg:postcode":"76549",
    "sg:province":"TX",
    "sg:tags":[
        "automobile",
        "lubrication"
    ],
    "wof:name":"Mc Dos Lube Ctr",
    "wof:placetype":"venue"
},
  "geometry": {"coordinates":[-97.76310599999999,31.10918],"type":"Point"}
}