{
  "type": "Feature",
  "properties": {
    "iso:country":"US",
    "sg:address":"5403 Everhart Rd",
    "sg:city":"Corpus Christi",
    "sg:classifiers":[
        {
            "category":"Professional",
            "subcategory":"Computer Services",
            "type":"Services"
        }
    ],
    "sg:phone":"+1 361 854 2253",
    "sg:postcode":"78411",
    "sg:province":"TX",
    "sg:tags":[
        "repair"
    ],
    "sg:website":"www.buy-okidata.com",
    "wof:name":"Texpro Computer Inc",
    "wof:placetype":"venue"
},
  "geometry": {"coordinates":[-97.38812299999999,27.708446],"type":"Point"}
}