{
  "type": "Feature",
  "properties": {
    "iso:country":"US",
    "sg:address":"301 N 8th St",
    "sg:city":"Midlothian",
    "sg:classifiers":[
        {
            "category":"Shopping",
            "subcategory":"Department Store",
            "type":"Retail Goods"
        }
    ],
    "sg:phone":"+1 972 775 5499",
    "sg:postcode":"76065",
    "sg:province":"TX",
    "sg:tags":[
        "shop"
    ],
    "wof:name":"Family Dollar Store",
    "wof:placetype":"venue"
},
  "geometry": {"coordinates":[-96.994518,32.484287],"type":"Point"}
}