{
  "type": "Feature",
  "properties": {
    "iso:country":"US",
    "sg:address":"6240 Utsa Blvd",
    "sg:city":"San Antonio",
    "sg:classifiers":[
        {
            "category":"Organizations",
            "subcategory":"Religious Organization",
            "type":"Services"
        }
    ],
    "sg:phone":"+1 210 691 0686",
    "sg:postcode":"78249",
    "sg:province":"TX",
    "sg:tags":[
        "church"
    ],
    "wof:name":"Church Of Jesus Christ Of Lds",
    "wof:placetype":"venue"
},
  "geometry": {"coordinates":[-98.611311,29.579465],"type":"Point"}
}