{
  "type": "Feature",
  "properties": {
    "iso:country":"US",
    "sg:address":"2115 Red Bluff Rd",
    "sg:city":"Pasadena",
    "sg:classifiers":[
        {
            "category":"Autos & Motor Vehicles",
            "subcategory":"Motorcycle Sales",
            "type":"Retail Goods"
        }
    ],
    "sg:phone":"+1 713 472 3694",
    "sg:postcode":"77506",
    "sg:province":"TX",
    "wof:name":"Kawasaki of Pasadena",
    "wof:placetype":"venue"
},
  "geometry": {"coordinates":[-95.183601,29.701099],"type":"Point"}
}