{
  "type": "Feature",
  "properties": {
    "iso:country":"US",
    "sg:address":"10333 Garland Rd",
    "sg:city":"Dallas",
    "sg:classifiers":[
        {
            "category":"Building & Trades",
            "subcategory":"Electrical",
            "type":"Services"
        }
    ],
    "sg:phone":"+1 214 321 3972",
    "sg:postcode":"75218",
    "sg:province":"TX",
    "sg:tags":[
        "electric",
        "contractor"
    ],
    "wof:name":"Glow Electric Co Inc",
    "wof:placetype":"venue"
},
  "geometry": {"coordinates":[-96.690989,32.842981],"type":"Point"}
}