{
  "type": "Feature",
  "properties": {
    "iso:country":"US",
    "sg:address":"635 Billy Mitchell Blvd",
    "sg:city":"Brownsville",
    "sg:classifiers":[
        {
            "category":"Wholesale",
            "subcategory":"Machinery & Supplies",
            "type":"Manufacturing & Wholesale Goods"
        }
    ],
    "sg:phone":"+1 956 541 2281",
    "sg:postcode":"78521",
    "sg:province":"TX",
    "sg:tags":[
        "janitor"
    ],
    "sg:website":"www.gulfcoastpaper.com",
    "wof:name":"Gulf Coast Paper Co",
    "wof:placetype":"venue"
},
  "geometry": {"coordinates":[-97.447934,25.909491],"type":"Point"}
}