{
  "type": "Feature",
  "properties": {
    "iso:country":"US",
    "sg:address":"475 Highway 71 W",
    "sg:city":"Bastrop",
    "sg:classifiers":[
        {
            "category":"Health Services",
            "subcategory":"Doctor",
            "type":"Services"
        },
        {
            "category":"Health Services",
            "subcategory":"Clinic",
            "type":"Services"
        }
    ],
    "sg:phone":"+1 512 321 9091",
    "sg:postcode":"78602",
    "sg:province":"TX",
    "sg:tags":[
        "physician",
        "surgeons",
        "internal",
        "osteopathic",
        "medicine",
        "surgeon"
    ],
    "sg:website":"http://www.srhnet.com",
    "wof:name":"Bastrop Family Medical Center",
    "wof:placetype":"venue"
},
  "geometry": {"coordinates":[-97.333344,30.106892],"type":"Point"}
}