{
  "type": "Feature",
  "properties": {
    "iso:country":"US",
    "sg:address":"11601 Anderson Mill Rd",
    "sg:city":"Austin",
    "sg:classifiers":[
        {
            "category":"Wholesale",
            "subcategory":"Medical Equipment & Supplies",
            "type":"Manufacturing & Wholesale Goods"
        },
        {
            "category":"Personal",
            "type":"Services"
        },
        {
            "category":"Professional",
            "subcategory":"Detective & Security Services",
            "type":"Services"
        },
        {
            "category":"Shopping",
            "subcategory":"Pharmacy",
            "type":"Retail Goods"
        }
    ],
    "sg:phone":"+1 512 266 6931",
    "sg:postcode":"78750",
    "sg:province":"TX",
    "sg:tags":[
        "control",
        "monitoring",
        "alarm",
        "system",
        "health",
        "home",
        "care"
    ],
    "wof:name":"Associated Home Services",
    "wof:placetype":"venue"
},
  "geometry": {"coordinates":[-97.82334899999999,30.453529],"type":"Point"}
}