{
  "type": "Feature",
  "properties": {
    "iso:country":"US",
    "sg:address":"5419 Bandera Rd",
    "sg:city":"San Antonio",
    "sg:classifiers":[
        {
            "category":"Shopping",
            "subcategory":"Bicycles & Sporting Goods",
            "type":"Retail Goods"
        }
    ],
    "sg:phone":"+1 210 682 9881",
    "sg:postcode":"78238",
    "sg:province":"TX",
    "sg:tags":[
        "equipment",
        "sales",
        "camping"
    ],
    "wof:name":"Bce",
    "wof:placetype":"venue"
},
  "geometry": {"coordinates":[-98.59199700000001,29.479743],"type":"Point"}
}