{
  "type": "Feature",
  "properties": {
    "iso:country":"US",
    "sg:address":"5300 Cueva Dr",
    "sg:city":"Austin",
    "sg:classifiers":[
        {
            "category":"Wholesale",
            "subcategory":"Office Equipment",
            "type":"Manufacturing & Wholesale Goods"
        }
    ],
    "sg:phone":"+1 512 263 7733",
    "sg:postcode":"78738",
    "sg:province":"TX",
    "sg:tags":[
        "equipment-wholesale",
        "manufacturer",
        "furniture"
    ],
    "wof:name":"Hmh/Roger's Group",
    "wof:placetype":"venue"
},
  "geometry": {"coordinates":[-97.98255,30.309838],"type":"Point"}
}