{
  "type": "Feature",
  "properties": {
    "iso:country":"US",
    "sg:address":"402 Westwood Ct",
    "sg:city":"Lamesa",
    "sg:classifiers":[
        {
            "category":"Building & Trades",
            "subcategory":"Construction",
            "type":"Services"
        }
    ],
    "sg:phone":"+1 806 872 6304",
    "sg:postcode":"79331",
    "sg:province":"TX",
    "sg:tags":[
        "roofing",
        "industrial",
        "contractors-commercial",
        "contractor"
    ],
    "wof:name":"S&S Roofing",
    "wof:placetype":"venue"
},
  "geometry": {"coordinates":[-101.97931199999999,32.7303],"type":"Point"}
}