{
  "type": "Feature",
  "properties": {
    "iso:country":"US",
    "sg:address":"1905 E Lamar St",
    "sg:city":"Sherman",
    "sg:classifiers":[
        {
            "category":"Retail",
            "subcategory":"Auto Repair",
            "type":"Services"
        }
    ],
    "sg:phone":"+1 903 892 0488",
    "sg:postcode":"75090",
    "sg:province":"TX",
    "sg:tags":[
        "repairing",
        "automobile",
        "transmission"
    ],
    "wof:name":"Turner's Automotive",
    "wof:placetype":"venue"
},
  "geometry": {"coordinates":[-96.58663900000001,33.640517],"type":"Point"}
}