{
  "type": "Feature",
  "properties": {
    "iso:country":"US",
    "sg:address":"6214 Turtle Cove Ct",
    "sg:city":"Arlington",
    "sg:classifiers":[
        {
            "category":"Professional",
            "type":"Services"
        }
    ],
    "sg:phone":"+1 817 649 1343",
    "sg:postcode":"76018",
    "sg:province":"TX",
    "sg:tags":[
        "establishment"
    ],
    "wof:name":"Salesmakers Inc",
    "wof:placetype":"venue"
},
  "geometry": {"coordinates":[-97.067273,32.645926],"type":"Point"}
}