{
  "type": "Feature",
  "properties": {
    "iso:country":"US",
    "sg:address":"2000 N I- 35",
    "sg:city":"Gainesville",
    "sg:classifiers":[
        {
            "category":"Travel",
            "subcategory":"Hotels & Motels",
            "type":"Entertainment"
        }
    ],
    "sg:phone":"+1 940 612 2995",
    "sg:postcode":"76240",
    "sg:province":"TX",
    "wof:name":"Bed & Bath Inn",
    "wof:placetype":"venue"
},
  "geometry": {"coordinates":[-97.15563899999999,33.637152],"type":"Point"}
}