{
  "type": "Feature",
  "properties": {
    "iso:country":"US",
    "sg:address":"2206 Lake Austin Blvd",
    "sg:city":"Austin",
    "sg:classifiers":[
        {
            "category":"Communications",
            "type":"Services"
        }
    ],
    "sg:phone":"+1 512 447 2337",
    "sg:postcode":"78703",
    "sg:province":"TX",
    "sg:tags":[
        "recording",
        "rehearsal",
        "studio"
    ],
    "wof:name":"Pedernales Recording Studio",
    "wof:placetype":"venue"
},
  "geometry": {"coordinates":[-97.770982,30.277747],"type":"Point"}
}