{
  "type": "Feature",
  "properties": {
    "iso:country":"US",
    "sg:address":"417 N 2nd St",
    "sg:city":"Killeen",
    "sg:classifiers":[
        {
            "category":"Professional",
            "subcategory":"Business Services",
            "type":"Services"
        }
    ],
    "sg:phone":"+1 254 501 9675",
    "sg:postcode":"76541",
    "sg:province":"TX",
    "wof:name":"Jae Smith & Associates",
    "wof:placetype":"venue"
},
  "geometry": {"coordinates":[-97.72975700000001,31.122302],"type":"Point"}
}