{
  "type": "Feature",
  "properties": {
    "iso:country":"US",
    "sg:address":"1653 Autumn Breeze Ln",
    "sg:city":"Lewisville",
    "sg:classifiers":[
        {
            "category":"Building & Trades",
            "subcategory":"Construction",
            "type":"Services"
        }
    ],
    "sg:phone":"+1 972 317 4605",
    "sg:postcode":"75077",
    "sg:province":"TX",
    "sg:tags":[
        "floor",
        "laying",
        "contractor"
    ],
    "wof:name":"Choice Flooring",
    "wof:placetype":"venue"
},
  "geometry": {"coordinates":[-97.04401,33.061003],"type":"Point"}
}