{
  "type": "Feature",
  "properties": {
    "iso:country":"US",
    "sg:address":"980 N Marshall St",
    "sg:city":"Henderson",
    "sg:classifiers":[
        {
            "category":"Wholesale",
            "subcategory":"Hardware",
            "type":"Manufacturing & Wholesale Goods"
        },
        {
            "category":"Home & Garden",
            "subcategory":"Household Appliances",
            "type":"Retail Goods"
        }
    ],
    "sg:phone":"+1 903 657 5349",
    "sg:postcode":"75652",
    "sg:province":"TX",
    "sg:tags":[
        "conditioner",
        "air",
        "refrigerating",
        "heater"
    ],
    "wof:name":"R E S Air Conditioning",
    "wof:placetype":"venue"
},
  "geometry": {"coordinates":[-94.79427,32.167008],"type":"Point"}
}