{
  "type": "Feature",
  "properties": {
    "iso:country":"US",
    "sg:address":"5250 W Alabama St",
    "sg:city":"Houston",
    "sg:classifiers":[
        {
            "category":"Personal",
            "subcategory":"Beauty Salon",
            "type":"Services"
        },
        {
            "category":"Personal",
            "subcategory":"Day Spa",
            "type":"Services"
        }
    ],
    "sg:phone":"+1 713 963 9121",
    "sg:postcode":"77056",
    "sg:province":"TX",
    "sg:tags":[
        "hair"
    ],
    "sg:website":"www.michaelyndon.com",
    "wof:name":"Michaelyndon",
    "wof:placetype":"venue"
},
  "geometry": {"coordinates":[-95.46815599999999,29.739037],"type":"Point"}
}