{
  "type": "Feature",
  "properties": {
    "iso:country":"US",
    "sg:address":"106 Mill St",
    "sg:city":"Valley View",
    "sg:classifiers":[
        {
            "category":"Personal",
            "subcategory":"Beauty Salon",
            "type":"Services"
        }
    ],
    "sg:phone":"+1 940 726 3417",
    "sg:postcode":"76272",
    "sg:province":"TX",
    "wof:name":"Maurine's Beauty Shop",
    "wof:placetype":"venue"
},
  "geometry": {"coordinates":[-97.163814,33.487327],"type":"Point"}
}