{
  "type": "Feature",
  "properties": {
    "iso:country":"US",
    "sg:address":"7902 Hillmont St",
    "sg:city":"Houston",
    "sg:classifiers":[
        {
            "category":"Home & Garden",
            "subcategory":"Building Materials",
            "type":"Retail Goods"
        }
    ],
    "sg:phone":"+1 713 934 7887",
    "sg:postcode":"77040",
    "sg:province":"TX",
    "sg:tags":[
        "stone"
    ],
    "wof:name":"Golden Stones Corp",
    "wof:placetype":"venue"
},
  "geometry": {"coordinates":[-95.511683,29.844515],"type":"Point"}
}