{
  "type": "Feature",
  "properties": {
    "iso:country":"US",
    "sg:address":"10505 Church Rd",
    "sg:city":"Dallas",
    "sg:classifiers":[
        {
            "category":"Health Services",
            "subcategory":"Doctor",
            "type":"Services"
        }
    ],
    "sg:phone":"+1 214 341 3114",
    "sg:postcode":"75238",
    "sg:province":"TX",
    "sg:tags":[
        "dentist",
        "dental"
    ],
    "wof:name":"Monarch Dental Associates",
    "wof:placetype":"venue"
},
  "geometry": {"coordinates":[-96.704364,32.886326],"type":"Point"}
}