{
  "type": "Feature",
  "properties": {
    "iso:country":"US",
    "sg:address":"19130 Co Rd 478",
    "sg:city":"Lindale",
    "sg:classifiers":[
        {
            "category":"Manufacturing",
            "subcategory":"Printing",
            "type":"Manufacturing & Wholesale Goods"
        }
    ],
    "sg:phone":"+1 903 882 8917",
    "sg:postcode":"75771",
    "sg:province":"TX",
    "sg:tags":[
        "mfg"
    ],
    "wof:name":"Memories Are 4 Ever",
    "wof:placetype":"venue"
},
  "geometry": {"coordinates":[-95.478849,32.548367],"type":"Point"}
}