{
  "type": "Feature",
  "properties": {
    "iso:country":"US",
    "sg:address":"1608 N Commerce St",
    "sg:city":"Gainesville",
    "sg:classifiers":[
        {
            "category":"Social Services",
            "subcategory":"Adult Care",
            "type":"Services"
        }
    ],
    "sg:phone":"+1 940 665 9154",
    "sg:postcode":"76240",
    "sg:province":"TX",
    "sg:tags":[
        "residential",
        "sp"
    ],
    "wof:name":"Anchor Club",
    "wof:placetype":"venue"
},
  "geometry": {"coordinates":[-97.14645899999999,33.640387],"type":"Point"}
}