{
  "type": "Feature",
  "properties": {
    "iso:country":"US",
    "sg:address":"4445 Flo Ave",
    "sg:city":"Dallas",
    "sg:classifiers":[
        {
            "category":"Professional",
            "type":"Services"
        }
    ],
    "sg:phone":"+1 214 337 8776",
    "sg:postcode":"75211",
    "sg:province":"TX",
    "wof:name":"Audio Works & Accessories",
    "wof:placetype":"venue"
},
  "geometry": {"coordinates":[-96.893738,32.734219],"type":"Point"}
}