{
  "type": "Feature",
  "properties": {
    "iso:country":"US",
    "sg:address":"923 Mayo Ave",
    "sg:city":"Houston",
    "sg:classifiers":[
        {
            "category":"Recreation",
            "type":"Entertainment"
        }
    ],
    "sg:phone":"+1 713 649 0757",
    "sg:postcode":"77017",
    "sg:province":"TX",
    "sg:tags":[
        "camps-recreational"
    ],
    "wof:name":"Workingman Charters",
    "wof:placetype":"venue"
},
  "geometry": {"coordinates":[-95.238028,29.691523],"type":"Point"}
}