{
  "type": "Feature",
  "properties": {
    "iso:country":"US",
    "sg:address":"8905 Chester Forest St",
    "sg:city":"Austin",
    "sg:classifiers":[
        {
            "category":"Professional",
            "subcategory":"Research",
            "type":"Services"
        }
    ],
    "sg:phone":"+1 512 401 0710",
    "sg:postcode":"78729",
    "sg:province":"TX",
    "sg:tags":[
        "organization",
        "noncommercial"
    ],
    "wof:name":"Themis Institute",
    "wof:placetype":"venue"
},
  "geometry": {"coordinates":[-97.775893,30.456394],"type":"Point"}
}