{
  "type": "Feature",
  "properties": {
    "iso:country":"US",
    "sg:address":"3411 Cascade Springs Dr",
    "sg:city":"Manvel",
    "sg:classifiers":[
        {
            "category":"Insurance",
            "subcategory":"Insurance Agent",
            "type":"Services"
        }
    ],
    "sg:phone":"+1 281 489 2839",
    "sg:postcode":"77578",
    "sg:province":"TX",
    "wof:name":"Chubb Insurance",
    "wof:placetype":"venue"
},
  "geometry": {"coordinates":[-95.37872400000001,29.536624],"type":"Point"}
}