{
  "type": "Feature",
  "properties": {
    "iso:country":"US",
    "sg:address":"515 S Fry Rd Ste A",
    "sg:city":"Katy",
    "sg:classifiers":[
        {
            "category":"Coffee & Tea",
            "type":"Food & Drink"
        },
        {
            "category":"Restaurant",
            "type":"Food & Drink"
        }
    ],
    "sg:phone":"+1 281 550 2008",
    "sg:postcode":"77450",
    "sg:province":"TX",
    "sg:tags":[
        "espresso"
    ],
    "wof:name":"Jocka Meaus Creole Cafe",
    "wof:placetype":"venue"
},
  "geometry": {"coordinates":[-95.74608000000001,29.726032],"type":"Point"}
}