{
  "type": "Feature",
  "properties": {
    "iso:country":"US",
    "sg:address":"5811 Rose St",
    "sg:city":"Houston",
    "sg:classifiers":[
        {
            "category":"Real Estate",
            "subcategory":"Architect",
            "type":"Services"
        }
    ],
    "sg:phone":"+1 713 802 1676",
    "sg:postcode":"77007",
    "sg:province":"TX",
    "sg:tags":[
        "architectural"
    ],
    "sg:website":"www.architectworks.com",
    "wof:name":"Architect Works Inc",
    "wof:placetype":"venue"
},
  "geometry": {"coordinates":[-95.420601,29.768801],"type":"Point"}
}