{
  "type": "Feature",
  "properties": {
    "iso:country":"US",
    "sg:address":"1011 Meridith Dr",
    "sg:city":"Austin",
    "sg:classifiers":[
        {
            "category":"Insurance",
            "subcategory":"Insurance Agent",
            "type":"Services"
        }
    ],
    "sg:phone":"+1 512 312 2711",
    "sg:postcode":"78748",
    "sg:province":"TX",
    "wof:name":"M A Wenzel & Assoc",
    "wof:placetype":"venue"
},
  "geometry": {"coordinates":[-97.83160599999999,30.141848],"type":"Point"}
}