{
  "type": "Feature",
  "properties": {
    "iso:country":"US",
    "sg:address":"8425 Phelan Blvd",
    "sg:city":"Beaumont",
    "sg:classifiers":[
        {
            "category":"Banks & Credit Unions",
            "subcategory":"Bank",
            "type":"Services"
        }
    ],
    "sg:phone":"+1 409 866 9781",
    "sg:postcode":"77706",
    "sg:province":"TX",
    "sg:tags":[
        "state",
        "commercial"
    ],
    "wof:name":"Community Bank Mortgage",
    "wof:placetype":"venue"
},
  "geometry": {"coordinates":[-94.19508999999999,30.076517],"type":"Point"}
}