{
  "type": "Feature",
  "properties": {
    "iso:country":"US",
    "sg:address":"9675 Rochelle St",
    "sg:city":"San Antonio",
    "sg:classifiers":[
        {
            "category":"Professional",
            "subcategory":"Business Services",
            "type":"Services"
        }
    ],
    "sg:phone":"+1 210 641 6166",
    "sg:postcode":"78240",
    "sg:province":"TX",
    "wof:name":"Jdb Group Inc",
    "wof:placetype":"venue"
},
  "geometry": {"coordinates":[-98.62670199999999,29.531005],"type":"Point"}
}