{
  "type": "Feature",
  "properties": {
    "iso:country":"US",
    "sg:address":"7309 San Dario Ave",
    "sg:city":"Laredo",
    "sg:classifiers":[
        {
            "category":"Wholesale",
            "subcategory":"Computers",
            "type":"Manufacturing & Wholesale Goods"
        }
    ],
    "sg:phone":"+1 956 727 3458",
    "sg:postcode":"78045",
    "sg:province":"TX",
    "sg:tags":[
        "equipment",
        "processing",
        "datum"
    ],
    "wof:name":"Radio Shack",
    "wof:placetype":"venue"
},
  "geometry": {"coordinates":[-99.50214,27.571959],"type":"Point"}
}