{
  "type": "Feature",
  "properties": {
    "iso:country":"US",
    "sg:address":"6547 Gentle River Dr",
    "sg:city":"Dallas",
    "sg:classifiers":[
        {
            "category":"Building & Trades",
            "subcategory":"Plumbing",
            "type":"Services"
        }
    ],
    "sg:phone":"+1 972 225 1582",
    "sg:postcode":"75241",
    "sg:province":"TX",
    "sg:tags":[
        "plumbing",
        "contractor"
    ],
    "wof:name":"Around The Clock Plbg & Hvac",
    "wof:placetype":"venue"
},
  "geometry": {"coordinates":[-96.765939,32.660293],"type":"Point"}
}