{
  "type": "Feature",
  "properties": {
    "iso:country":"US",
    "sg:address":"913 W Loop 281",
    "sg:city":"Longview",
    "sg:classifiers":[
        {
            "category":"Professional",
            "type":"Services"
        }
    ],
    "sg:phone":"+1 903 759 3235",
    "sg:postcode":"75604",
    "sg:province":"TX",
    "sg:tags":[
        "establishment"
    ],
    "wof:name":"Morton Ruel",
    "wof:placetype":"venue"
},
  "geometry": {"coordinates":[-94.764938,32.537826],"type":"Point"}
}