{
  "type": "Feature",
  "properties": {
    "iso:country":"US",
    "sg:address":"3131 Southwest Fwy",
    "sg:city":"Houston",
    "sg:classifiers":[
        {
            "category":"Shopping",
            "subcategory":"Gifts & Souvenirs",
            "type":"Retail Goods"
        }
    ],
    "sg:phone":"+1 713 526 5854",
    "sg:postcode":"77098",
    "sg:province":"TX",
    "sg:tags":[
        "announcement",
        "invitation"
    ],
    "wof:name":"Event Essentials",
    "wof:placetype":"venue"
},
  "geometry": {"coordinates":[-95.427055,29.729596],"type":"Point"}
}