{
  "type": "Feature",
  "properties": {
    "iso:country":"US",
    "sg:address":"9010 Viking Dr",
    "sg:city":"Austin",
    "sg:classifiers":[
        {
            "category":"Organizations",
            "subcategory":"Religious Organization",
            "type":"Services"
        }
    ],
    "sg:phone":"+1 512 797 6699",
    "sg:postcode":"78758",
    "sg:province":"TX",
    "wof:name":"His Encouraging Word Ministries Inc",
    "wof:placetype":"venue"
},
  "geometry": {"coordinates":[-97.70581799999999,30.363825],"type":"Point"}
}