{
  "type": "Feature",
  "properties": {
    "iso:country":"US",
    "sg:address":"516 S Dumas Ave",
    "sg:city":"Dumas",
    "sg:classifiers":[
        {
            "category":"Fast Food",
            "type":"Food & Drink"
        },
        {
            "category":"Restaurant",
            "type":"Food & Drink"
        }
    ],
    "sg:phone":"+1 806 935 2505",
    "sg:postcode":"79029",
    "sg:province":"TX",
    "sg:tags":[
        "mexican",
        "take"
    ],
    "wof:name":"Valdez, Taqueria",
    "wof:placetype":"venue"
},
  "geometry": {"coordinates":[-101.97325600000001,35.860651],"type":"Point"}
}