{
  "type": "Feature",
  "properties": {
    "iso:country":"US",
    "sg:address":"9067 Fringewood Dr",
    "sg:city":"Dallas",
    "sg:classifiers":[
        {
            "category":"Building & Trades",
            "subcategory":"Landscaping Services",
            "type":"Services"
        }
    ],
    "sg:phone":"+1 214 321 7106",
    "sg:postcode":"75228",
    "sg:province":"TX",
    "wof:name":"Kennedys Quality Lawncar",
    "wof:placetype":"venue"
},
  "geometry": {"coordinates":[-96.69419499999999,32.812366],"type":"Point"}
}