{
  "type": "Feature",
  "properties": {
    "iso:country":"US",
    "sg:address":"724 Rowan St",
    "sg:city":"Rockport",
    "sg:classifiers":[
        {
            "category":"Organizations",
            "subcategory":"Religious Organization",
            "type":"Services"
        }
    ],
    "sg:phone":"+1 361 727 0970",
    "sg:postcode":"78382",
    "sg:province":"TX",
    "sg:tags":[
        "church"
    ],
    "wof:name":"Church St Antq Mall At Rowan",
    "wof:placetype":"venue"
},
  "geometry": {"coordinates":[-97.059742,28.013154],"type":"Point"}
}