{
  "type": "Feature",
  "properties": {
    "iso:country":"US",
    "sg:address":"10515-J N Mopac Expwy Austin #2 - Arbor Walk",
    "sg:city":"Austin",
    "sg:classifiers":[
        {
            "category":"Building & Trades",
            "subcategory":"Construction",
            "type":"Services"
        }
    ],
    "sg:phone":"+1 512 346 2900",
    "sg:postcode":"78759",
    "sg:province":"TX",
    "sg:tags":[
        "interior",
        "design"
    ],
    "sg:website":"www.thehomeconsignmentcenter.com",
    "wof:name":"Home Consignment Center",
    "wof:placetype":"venue"
},
  "geometry": {"coordinates":[-97.73298699999999,30.392245],"type":"Point"}
}