{
  "type": "Feature",
  "properties": {
    "iso:country":"US",
    "sg:address":"15010 San Pedro Ave",
    "sg:city":"San Antonio",
    "sg:classifiers":[
        {
            "category":"Shopping",
            "subcategory":"Florist",
            "type":"Retail Goods"
        }
    ],
    "sg:phone":"+1 210 494 1010",
    "sg:postcode":"78232",
    "sg:province":"TX",
    "wof:name":"Last Straw Plants & Florists",
    "wof:placetype":"venue"
},
  "geometry": {"coordinates":[-98.47707800000001,29.579778],"type":"Point"}
}