{
  "type": "Feature",
  "properties": {
    "iso:country":"US",
    "sg:address":"5901 Bandolero Dr",
    "sg:city":"El Paso",
    "sg:classifiers":[
        {
            "category":"Health Services",
            "subcategory":"Clinic",
            "type":"Services"
        },
        {
            "category":"Social Services",
            "type":"Services"
        }
    ],
    "sg:phone":"+1 915 842 0900",
    "sg:postcode":"79912",
    "sg:province":"TX",
    "sg:tags":[
        "senior",
        "citizen"
    ],
    "wof:name":"Desert Springs Alzheimer Speci",
    "wof:placetype":"venue"
},
  "geometry": {"coordinates":[-106.518539,31.855915],"type":"Point"}
}