{
  "type": "Feature",
  "properties": {
    "iso:country":"US",
    "sg:address":"5409 Blackhawk Dr",
    "sg:city":"Plano",
    "sg:classifiers":[
        {
            "category":"Recreation",
            "type":"Entertainment"
        }
    ],
    "sg:phone":"+1 972 380 2583",
    "sg:postcode":"75093",
    "sg:province":"TX",
    "wof:name":"Shamrock Golf Enterprises",
    "wof:placetype":"venue"
},
  "geometry": {"coordinates":[-96.807069,33.022929],"type":"Point"}
}