{
  "type": "Feature",
  "properties": {
    "iso:country":"US",
    "sg:address":"2617 3rd Ave",
    "sg:city":"Canyon",
    "sg:classifiers":[
        {
            "category":"Building & Trades",
            "subcategory":"Construction",
            "type":"Services"
        }
    ],
    "sg:phone":"+1 806 655 1420",
    "sg:postcode":"79015",
    "sg:province":"TX",
    "sg:tags":[
        "builder",
        "general"
    ],
    "wof:name":"Chris Gerald Builder Inc",
    "wof:placetype":"venue"
},
  "geometry": {"coordinates":[-101.913332,34.980796],"type":"Point"}
}