{
  "type": "Feature",
  "properties": {
    "iso:country":"US",
    "sg:address":"1205 Park Center St",
    "sg:city":"Fort Worth",
    "sg:classifiers":[
        {
            "category":"Shopping",
            "subcategory":"Shoes",
            "type":"Retail Goods"
        }
    ],
    "sg:phone":"+1 817 249 0038",
    "sg:postcode":"76126",
    "sg:province":"TX",
    "sg:tags":[
        "wear"
    ],
    "wof:name":"Gifford Boots",
    "wof:placetype":"venue"
},
  "geometry": {"coordinates":[-97.457949,32.665979],"type":"Point"}
}