{
  "type": "Feature",
  "properties": {
    "iso:country":"US",
    "sg:address":"11436 Rojas Dr",
    "sg:city":"El Paso",
    "sg:classifiers":[
        {
            "category":"Professional",
            "type":"Services"
        }
    ],
    "sg:phone":"+1 915 598 2600",
    "sg:postcode":"79936",
    "sg:province":"TX",
    "sg:tags":[
        "establishment"
    ],
    "wof:name":"Mustang Express",
    "wof:placetype":"venue"
},
  "geometry": {"coordinates":[-106.320283,31.740828],"type":"Point"}
}