{
  "type": "Feature",
  "properties": {
    "iso:country":"US",
    "sg:address":"8229 Katy Fwy",
    "sg:city":"Houston",
    "sg:classifiers":[
        {
            "category":"Restaurant",
            "type":"Food & Drink"
        }
    ],
    "sg:menulink":"http://www.allmenus.com/tx/houston/5066-jillians/menu/",
    "sg:phone":"+1 713 263 0303",
    "sg:postcode":"77024",
    "sg:province":"TX",
    "sg:tags":[
        "american"
    ],
    "wof:name":"Jillian's",
    "wof:placetype":"venue"
},
  "geometry": {"coordinates":[-95.48584700000001,29.783447],"type":"Point"}
}