{
  "type": "Feature",
  "properties": {
    "iso:country":"US",
    "sg:address":"927 Silverstone Dr",
    "sg:city":"Lewisville",
    "sg:classifiers":[
        {
            "category":"Shopping",
            "subcategory":"Discount & Variety Stores",
            "type":"Retail Goods"
        }
    ],
    "sg:phone":"+1 972 315 3810",
    "sg:postcode":"75067",
    "sg:province":"TX",
    "wof:name":"Daniel Manning Co",
    "wof:placetype":"venue"
},
  "geometry": {"coordinates":[-97.009995,33.010753],"type":"Point"}
}