{
  "type": "Feature",
  "properties": {
    "iso:country":"US",
    "sg:address":"300 W Cotter Ave",
    "sg:city":"Port Aransas",
    "sg:classifiers":[
        {
            "category":"Recreation",
            "type":"Entertainment"
        }
    ],
    "sg:phone":"+1 361 749 4188",
    "sg:postcode":"78373",
    "sg:province":"TX",
    "sg:tags":[
        "equipment",
        "charter",
        "fishing",
        "boat",
        "party"
    ],
    "sg:website":"www.dolphindocks.com",
    "wof:name":"Dolphin Docks",
    "wof:placetype":"venue"
},
  "geometry": {"coordinates":[-97.064336,27.83788],"type":"Point"}
}