{
  "type": "Feature",
  "properties": {
    "iso:country":"US",
    "sg:address":"2108 Dallas Park Way Suite #236",
    "sg:city":"Plano",
    "sg:classifiers":[
        {
            "category":"Personal",
            "subcategory":"Nail Salon",
            "type":"Services"
        }
    ],
    "sg:phone":"+1 972 378 0807",
    "sg:postcode":"75093",
    "sg:province":"TX",
    "sg:website":"www.polonails.com",
    "wof:name":"Polo Nails",
    "wof:placetype":"venue"
},
  "geometry": {"coordinates":[-96.801205,33.027561],"type":"Point"}
}