{
  "type": "Feature",
  "properties": {
    "iso:country":"US",
    "sg:address":"14110 Red Maple Wood",
    "sg:city":"San Antonio",
    "sg:classifiers":[
        {
            "category":"Shopping",
            "type":"Retail Goods"
        }
    ],
    "sg:phone":"+1 210 408 2090",
    "sg:postcode":"78249",
    "sg:province":"TX",
    "sg:tags":[
        "art",
        "dealer"
    ],
    "wof:name":"Singulartistscom",
    "wof:placetype":"venue"
},
  "geometry": {"coordinates":[-98.580241,29.573943],"type":"Point"}
}