{
  "type": "Feature",
  "properties": {
    "iso:country":"US",
    "sg:address":"402 S Pioneer Dr",
    "sg:city":"Abilene",
    "sg:classifiers":[
        {
            "category":"Place Of Worship",
            "subcategory":"Church",
            "type":"Public Place"
        },
        {
            "category":"Place Of Worship",
            "type":"Public Place"
        }
    ],
    "sg:phone":"+1 325 692 2300",
    "sg:postcode":"79605",
    "sg:province":"TX",
    "sg:tags":[
        "testament",
        "christ-new",
        "churches-church",
        "christ"
    ],
    "wof:name":"Westgate Church of Christ",
    "wof:placetype":"venue"
},
  "geometry": {"coordinates":[-99.779521,32.44669],"type":"Point"}
}