{
  "type": "Feature",
  "properties": {
    "iso:country":"US",
    "sg:address":"116 S Cuyler St",
    "sg:city":"Pampa",
    "sg:classifiers":[
        {
            "category":"Government",
            "subcategory":"Office",
            "type":"Public Place"
        }
    ],
    "sg:phone":"+1 806 669 8041",
    "sg:postcode":"79065",
    "sg:province":"TX",
    "wof:name":"White Deer Land Museum",
    "wof:placetype":"venue"
},
  "geometry": {"coordinates":[-100.961422,35.535635],"type":"Point"}
}