{
  "type": "Feature",
  "properties": {
    "iso:country":"US",
    "sg:address":"1015 Ellis Ave",
    "sg:city":"Lufkin",
    "sg:classifiers":[
        {
            "category":"Health Services",
            "subcategory":"Doctor",
            "type":"Services"
        }
    ],
    "sg:phone":"+1 936 634 3329",
    "sg:postcode":"75904",
    "sg:province":"TX",
    "sg:tags":[
        "physician",
        "surgeon"
    ],
    "wof:name":"Terry Wells MD",
    "wof:placetype":"venue"
},
  "geometry": {"coordinates":[-94.73905000000001,31.336335],"type":"Point"}
}