{
  "type": "Feature",
  "properties": {
    "iso:country":"US",
    "sg:address":"15825 Hope Village Rd",
    "sg:city":"Friendswood",
    "sg:classifiers":[
        {
            "category":"Personal",
            "subcategory":"Beauty Salon",
            "type":"Services"
        }
    ],
    "sg:phone":"+1 281 992 8193",
    "sg:postcode":"77546",
    "sg:province":"TX",
    "wof:name":"Fantastic Beauty",
    "wof:placetype":"venue"
},
  "geometry": {"coordinates":[-95.180668,29.545138],"type":"Point"}
}