{
  "type": "Feature",
  "properties": {
    "iso:country":"US",
    "sg:address":"414 E Loop 281",
    "sg:city":"Longview",
    "sg:classifiers":[
        {
            "category":"Real Estate",
            "subcategory":"Real Estate Operator",
            "type":"Services"
        }
    ],
    "sg:phone":"+1 903 297 4903",
    "sg:postcode":"75605",
    "sg:province":"TX",
    "sg:tags":[
        "building",
        "parks"
    ],
    "wof:name":"Office Ctr",
    "wof:placetype":"venue"
},
  "geometry": {"coordinates":[-94.736946,32.541939],"type":"Point"}
}