{
  "type": "Feature",
  "properties": {
    "iso:country":"US",
    "sg:address":"2343 University Blvd",
    "sg:city":"Houston",
    "sg:classifiers":[
        {
            "category":"Home & Garden",
            "subcategory":"Building Materials",
            "type":"Retail Goods"
        }
    ],
    "sg:phone":"+1 832 767 3353",
    "sg:postcode":"77005",
    "sg:province":"TX",
    "sg:tags":[
        "energy",
        "conservation",
        "product"
    ],
    "wof:name":"Manitou Energy",
    "wof:placetype":"venue"
},
  "geometry": {"coordinates":[-95.41382299999999,29.715118],"type":"Point"}
}