{
  "type": "Feature",
  "properties": {
    "iso:country":"US",
    "sg:address":"2329 Mistletoe Dr",
    "sg:city":"Fort Worth",
    "sg:classifiers":[
        {
            "category":"Professional",
            "subcategory":"Management & Consulting",
            "type":"Services"
        }
    ],
    "sg:phone":"+1 817 927 2277",
    "sg:postcode":"76110",
    "sg:province":"TX",
    "wof:name":"Wm Carr Inc",
    "wof:placetype":"venue"
},
  "geometry": {"coordinates":[-97.354066,32.727734],"type":"Point"}
}