{
  "type": "Feature",
  "properties": {
    "iso:country":"US",
    "sg:address":"507 Chestnut St",
    "sg:city":"Forney",
    "sg:classifiers":[
        {
            "category":"Building & Trades",
            "subcategory":"Construction",
            "type":"Services"
        }
    ],
    "sg:phone":"+1 972 564 5355",
    "sg:postcode":"75126",
    "sg:province":"TX",
    "sg:tags":[
        "home",
        "builder"
    ],
    "wof:name":"Horizon Homes",
    "wof:placetype":"venue"
},
  "geometry": {"coordinates":[-96.46346800000001,32.745486],"type":"Point"}
}