{
  "type": "Feature",
  "properties": {
    "iso:country":"US",
    "sg:address":"2106 W Yorkshire",
    "sg:city":"Prosper",
    "sg:classifiers":[
        {
            "category":"Communications",
            "subcategory":"Film & Video Production",
            "type":"Services"
        }
    ],
    "sg:phone":"+1 214 924 7207",
    "sg:postcode":"75078",
    "sg:province":"TX",
    "sg:tags":[
        "motion"
    ],
    "wof:name":"Noble Video Productions LLC",
    "wof:placetype":"venue"
},
  "geometry": {"coordinates":[-96.78242400000001,33.241104],"type":"Point"}
}