{
  "type": "Feature",
  "properties": {
    "iso:country":"US",
    "sg:address":"3114 Clymer St",
    "sg:city":"Dallas",
    "sg:classifiers":[
        {
            "category":"Recreation",
            "type":"Entertainment"
        },
        {
            "category":"Government",
            "subcategory":"Office",
            "type":"Public Place"
        }
    ],
    "sg:phone":"+1 214 670 6188",
    "sg:postcode":"75212",
    "sg:province":"TX",
    "sg:tags":[
        "center"
    ],
    "wof:name":"Jaycee/ Zragoza Recreation Ctr",
    "wof:placetype":"venue"
},
  "geometry": {"coordinates":[-96.909361,32.779436],"type":"Point"}
}