{
  "type": "Feature",
  "properties": {
    "iso:country":"US",
    "sg:address":"1308 S 8th St",
    "sg:city":"Mcallen",
    "sg:classifiers":[
        {
            "category":"Social Services",
            "subcategory":"Child Care",
            "type":"Services"
        }
    ],
    "sg:phone":"+1 956 686 2555",
    "sg:postcode":"78501",
    "sg:province":"TX",
    "sg:tags":[
        "day"
    ],
    "wof:name":"Sunshine Academy",
    "wof:placetype":"venue"
},
  "geometry": {"coordinates":[-98.23012199999999,26.190307],"type":"Point"}
}