{
  "type": "Feature",
  "properties": {
    "iso:country":"US",
    "sg:address":"186 Reid Dr",
    "sg:city":"Victoria",
    "sg:classifiers":[
        {
            "category":"Organizations",
            "subcategory":"Professional Association",
            "type":"Services"
        },
        {
            "category":"Organizations",
            "subcategory":"Community Association",
            "type":"Services"
        }
    ],
    "sg:phone":"+1 361 572 4686",
    "sg:postcode":"77904",
    "sg:province":"TX",
    "wof:name":"Victoria Apartment Association",
    "wof:placetype":"venue"
},
  "geometry": {"coordinates":[-97.002713,28.916391],"type":"Point"}
}