{
  "type": "Feature",
  "properties": {
    "iso:country":"US",
    "sg:address":"14202 Golf View Trl",
    "sg:city":"Houston",
    "sg:classifiers":[
        {
            "category":"Professional",
            "type":"Services"
        }
    ],
    "sg:phone":"+1 281 286 4060",
    "sg:postcode":"77059",
    "sg:province":"TX",
    "wof:name":"Property Divestiture Services",
    "wof:placetype":"venue"
},
  "geometry": {"coordinates":[-95.13082900000001,29.598131],"type":"Point"}
}