{
  "type": "Feature",
  "properties": {
    "iso:country":"US",
    "sg:address":"16680 Briaridge Dr",
    "sg:city":"Tyler",
    "sg:classifiers":[
        {
            "category":"Professional",
            "type":"Services"
        }
    ],
    "sg:phone":"+1 903 561 1010",
    "sg:postcode":"75703",
    "sg:province":"TX",
    "wof:name":"Almonte Corp",
    "wof:placetype":"venue"
},
  "geometry": {"coordinates":[-95.35945700000001,32.23833],"type":"Point"}
}