{
  "type": "Feature",
  "properties": {
    "iso:country":"US",
    "sg:address":"122 Retama Dr",
    "sg:city":"Georgetown",
    "sg:classifiers":[
        {
            "category":"Professional",
            "type":"Services"
        }
    ],
    "sg:phone":"+1 512 868 2417",
    "sg:postcode":"78626",
    "sg:province":"TX",
    "wof:name":"J Clint Anderson Co",
    "wof:placetype":"venue"
},
  "geometry": {"coordinates":[-97.64099299999999,30.638626],"type":"Point"}
}