{
  "type": "Feature",
  "properties": {
    "iso:country":"US",
    "sg:address":"9920 Windmill Lakes Blvd",
    "sg:city":"Houston",
    "sg:classifiers":[
        {
            "category":"Personal",
            "type":"Services"
        }
    ],
    "sg:phone":"+1 713 910 0340",
    "sg:postcode":"77075",
    "sg:province":"TX",
    "wof:name":"Jordans Courtyard Banquet Hall",
    "wof:placetype":"venue"
},
  "geometry": {"coordinates":[-95.240506,29.625846],"type":"Point"}
}