{
  "type": "Feature",
  "properties": {
    "iso:country":"US",
    "sg:address":"5901 Bedrock Dr",
    "sg:city":"Killeen",
    "sg:classifiers":[
        {
            "category":"Real Estate",
            "subcategory":"Real Estate Services",
            "type":"Services"
        },
        {
            "category":"Real Estate",
            "subcategory":"Real Estate Agent",
            "type":"Services"
        }
    ],
    "sg:phone":"+1 254 768 2007",
    "sg:postcode":"76542",
    "sg:province":"TX",
    "sg:tags":[
        "buyer",
        "broker"
    ],
    "wof:name":"Stevenella",
    "wof:placetype":"venue"
},
  "geometry": {"coordinates":[-97.686836,31.04892],"type":"Point"}
}