{
  "type": "Feature",
  "properties": {
    "iso:country":"US",
    "sg:address":"1205 S FM 51",
    "sg:city":"Decatur",
    "sg:classifiers":[
        {
            "category":"Restaurant",
            "type":"Food & Drink"
        }
    ],
    "sg:phone":"+1 940 627 7010",
    "sg:postcode":"76234",
    "sg:province":"TX",
    "sg:tags":[
        "eating"
    ],
    "wof:name":"Sonic Drive-In",
    "wof:placetype":"venue"
},
  "geometry": {"coordinates":[-97.593604,33.227472],"type":"Point"}
}