{
  "type": "Feature",
  "properties": {
    "iso:country":"US",
    "sg:address":"1828 Willard Ave",
    "sg:city":"Canadian",
    "sg:classifiers":[
        {
            "category":"Retail",
            "subcategory":"Repair Shop",
            "type":"Services"
        }
    ],
    "sg:phone":"+1 806 323 9901",
    "sg:postcode":"79014",
    "sg:province":"TX",
    "sg:tags":[
        "compressor"
    ],
    "wof:name":"T C Industrial",
    "wof:placetype":"venue"
},
  "geometry": {"coordinates":[-100.378839,35.900312],"type":"Point"}
}