{
  "type": "Feature",
  "properties": {
    "iso:country":"US",
    "sg:address":"332 Towne Vue Dr",
    "sg:city":"San Antonio",
    "sg:classifiers":[
        {
            "category":"Real Estate",
            "subcategory":"Real Estate Operator",
            "type":"Services"
        }
    ],
    "sg:phone":"+1 210 224 2000",
    "sg:postcode":"78213",
    "sg:province":"TX",
    "sg:tags":[
        "property",
        "lessor"
    ],
    "wof:name":"Oppen Heimer",
    "wof:placetype":"venue"
},
  "geometry": {"coordinates":[-98.519599,29.517878],"type":"Point"}
}