{
  "type": "Feature",
  "properties": {
    "iso:country":"US",
    "sg:address":"126 Brahman Rd",
    "sg:city":"Big Sandy",
    "sg:classifiers":[
        {
            "category":"Shopping",
            "type":"Retail Goods"
        }
    ],
    "sg:phone":"+1 903 725 3249",
    "sg:postcode":"75755",
    "sg:province":"TX",
    "sg:tags":[
        "merchandise"
    ],
    "wof:name":"Kreations By Kathy",
    "wof:placetype":"venue"
},
  "geometry": {"coordinates":[-95.121292,32.765944],"type":"Point"}
}