{
  "type": "Feature",
  "properties": {
    "iso:country":"US",
    "sg:address":"5449 Marina Dr",
    "sg:city":"Garland",
    "sg:classifiers":[
        {
            "category":"Building & Trades",
            "subcategory":"Construction",
            "type":"Services"
        }
    ],
    "sg:phone":"+1 972 226 4342",
    "sg:postcode":"75043",
    "sg:province":"TX",
    "sg:tags":[
        "home",
        "builder"
    ],
    "wof:name":"Choice Homes",
    "wof:placetype":"venue"
},
  "geometry": {"coordinates":[-96.551304,32.8582],"type":"Point"}
}