{
  "type": "Feature",
  "properties": {
    "iso:country":"US",
    "sg:address":"608 S Andrews Dr",
    "sg:city":"Waco",
    "sg:classifiers":[
        {
            "category":"Freight",
            "type":"Transportation"
        }
    ],
    "sg:phone":"+1 254 662 3595",
    "sg:postcode":"76706",
    "sg:province":"TX",
    "wof:name":"Gideons Transpoport",
    "wof:placetype":"venue"
},
  "geometry": {"coordinates":[-97.110512,31.466414],"type":"Point"}
}