{
  "type": "Feature",
  "properties": {
    "iso:country":"US",
    "sg:address":"17 Hogan Dr",
    "sg:city":"Amarillo",
    "sg:classifiers":[
        {
            "category":"Building & Trades",
            "subcategory":"Construction",
            "type":"Services"
        }
    ],
    "sg:phone":"+1 806 342 5851",
    "sg:postcode":"79124",
    "sg:province":"TX",
    "sg:tags":[
        "contractor"
    ],
    "wof:name":"Alco Builders",
    "wof:placetype":"venue"
},
  "geometry": {"coordinates":[-101.894491,35.232063],"type":"Point"}
}