{
  "type": "Feature",
  "properties": {
    "iso:country":"US",
    "sg:address":"3808 W 35th St",
    "sg:city":"Austin",
    "sg:classifiers":[
        {
            "category":"Organizations",
            "subcategory":"Community Association",
            "type":"Services"
        }
    ],
    "sg:phone":"+1 512 453 7249",
    "sg:postcode":"78703",
    "sg:province":"TX",
    "sg:tags":[
        "club",
        "golf"
    ],
    "sg:website":"www.westwoodcountryclub.com/",
    "wof:name":"Westwood Country Club",
    "wof:placetype":"venue"
},
  "geometry": {"coordinates":[-97.774345,30.313464],"type":"Point"}
}