{
  "type": "Feature",
  "properties": {
    "iso:country":"US",
    "sg:address":"318 Congress Ave",
    "sg:city":"Austin",
    "sg:classifiers":[
        {
            "category":"Professional",
            "subcategory":"Art Services",
            "type":"Services"
        }
    ],
    "sg:phone":"+1 512 426 8556",
    "sg:postcode":"78701",
    "sg:province":"TX",
    "sg:tags":[
        "commercial",
        "design"
    ],
    "wof:name":"Mkr Creative",
    "wof:placetype":"venue"
},
  "geometry": {"coordinates":[-97.74361399999999,30.266092],"type":"Point"}
}