{
  "type": "Feature",
  "properties": {
    "iso:country":"US",
    "sg:address":"2695 I- 10 Svc Rd",
    "sg:city":"Beaumont",
    "sg:classifiers":[
        {
            "category":"Restaurant",
            "type":"Food & Drink"
        }
    ],
    "sg:phone":"+1 409 838 5566",
    "sg:postcode":"77702",
    "sg:province":"TX",
    "sg:tags":[
        "cafeteria"
    ],
    "wof:name":"Lubys",
    "wof:placetype":"venue"
},
  "geometry": {"coordinates":[-94.129778,30.095575],"type":"Point"}
}