{
  "type": "Feature",
  "properties": {
    "iso:country":"US",
    "sg:address":"2105 S Congress Ave",
    "sg:city":"Austin",
    "sg:classifiers":[
        {
            "category":"Autos & Motor Vehicles",
            "subcategory":"Fuel & Gas Station",
            "type":"Retail Goods"
        },
        {
            "category":"Food & Beverages",
            "subcategory":"Groceries & Convenience Stores",
            "type":"Retail Goods"
        }
    ],
    "sg:phone":"+1 512 462 4717",
    "sg:postcode":"78704",
    "sg:province":"TX",
    "wof:name":"Shell",
    "wof:placetype":"venue"
},
  "geometry": {"coordinates":[-97.75177600000001,30.242785],"type":"Point"}
}