{
  "type": "Feature",
  "properties": {
    "iso:country":"US",
    "sg:address":"10836 Stone Canyon Rd",
    "sg:city":"Dallas",
    "sg:classifiers":[
        {
            "category":"Professional",
            "subcategory":"Management & Consulting",
            "type":"Services"
        }
    ],
    "sg:phone":"+1 214 691 2232",
    "sg:postcode":"75230",
    "sg:province":"TX",
    "sg:tags":[
        "counselor",
        "public",
        "relations"
    ],
    "sg:website":"www.fairchildtraining.com",
    "wof:name":"Fairchild Consulting",
    "wof:placetype":"venue"
},
  "geometry": {"coordinates":[-96.773742,32.895299],"type":"Point"}
}