{
  "type": "Feature",
  "properties": {
    "iso:country":"US",
    "sg:address":"6400 Creekbend Ct",
    "sg:city":"Arlington",
    "sg:classifiers":[
        {
            "category":"Building & Trades",
            "subcategory":"Construction",
            "type":"Services"
        }
    ],
    "sg:phone":"+1 817 925 9396",
    "sg:postcode":"76001",
    "sg:province":"TX",
    "wof:name":"L G Coffman Construction Inc",
    "wof:placetype":"venue"
},
  "geometry": {"coordinates":[-97.15208800000001,32.641413],"type":"Point"}
}