{
  "type": "Feature",
  "properties": {
    "iso:country":"US",
    "sg:address":"1314 Foley Rd",
    "sg:city":"Crosby",
    "sg:classifiers":[
        {
            "category":"Building & Trades",
            "subcategory":"Landscaping Services",
            "type":"Services"
        }
    ],
    "sg:phone":"+1 281 328 7187",
    "sg:postcode":"77532",
    "sg:province":"TX",
    "sg:tags":[
        "landscape"
    ],
    "wof:name":"Brocken Enterprises Inc",
    "wof:placetype":"venue"
},
  "geometry": {"coordinates":[-95.115103,29.948471],"type":"Point"}
}