{
  "type": "Feature",
  "properties": {
    "iso:country":"US",
    "sg:address":"11824 Radium St",
    "sg:city":"San Antonio",
    "sg:classifiers":[
        {
            "category":"Building & Trades",
            "subcategory":"Landscaping Services",
            "type":"Services"
        }
    ],
    "sg:phone":"+1 210 366 1911",
    "sg:postcode":"78216",
    "sg:province":"TX",
    "sg:tags":[
        "designer",
        "architecture",
        "landscape"
    ],
    "wof:name":"C F Zavala Group",
    "wof:placetype":"venue"
},
  "geometry": {"coordinates":[-98.494934,29.552457],"type":"Point"}
}