{
  "type": "Feature",
  "properties": {
    "iso:country":"US",
    "sg:address":"813 E Esperanza Ave",
    "sg:city":"Mcallen",
    "sg:classifiers":[
        {
            "category":"Wholesale",
            "subcategory":"Non-durable Goods",
            "type":"Manufacturing & Wholesale Goods"
        }
    ],
    "sg:phone":"+1 956 686 6232",
    "sg:postcode":"78501",
    "sg:province":"TX",
    "wof:name":"C&C Distributing",
    "wof:placetype":"venue"
},
  "geometry": {"coordinates":[-98.205533,26.229038],"type":"Point"}
}