{
  "type": "Feature",
  "properties": {
    "iso:country":"US",
    "sg:address":"7140 Doniphan Dr",
    "sg:city":"Canutillo",
    "sg:classifiers":[
        {
            "category":"Retail",
            "subcategory":"Auto Repair",
            "type":"Services"
        }
    ],
    "sg:phone":"+1 915 877 4409",
    "sg:postcode":"79835",
    "sg:province":"TX",
    "sg:tags":[
        "automobile",
        "inspection"
    ],
    "wof:name":"Lugo's Automotive",
    "wof:placetype":"venue"
},
  "geometry": {"coordinates":[-106.60046800000001,31.915789],"type":"Point"}
}