{
  "type": "Feature",
  "properties": {
    "iso:country":"US",
    "sg:address":"608 Grand Ave",
    "sg:city":"Arlington",
    "sg:classifiers":[
        {
            "category":"Home & Garden",
            "subcategory":"Building Materials",
            "type":"Retail Goods"
        },
        {
            "category":"Building & Trades",
            "subcategory":"Construction",
            "type":"Services"
        },
        {
            "category":"Manufacturing",
            "subcategory":"Building Materials",
            "type":"Manufacturing & Wholesale Goods"
        }
    ],
    "sg:phone":"+1 972 660 3106",
    "sg:postcode":"76010",
    "sg:province":"TX",
    "sg:tags":[
        "installation",
        "windows-repair",
        "cover",
        "siding",
        "contractor",
        "window",
        "doors",
        "frames",
        "accessory",
        "enclosure",
        "patio",
        "replacement"
    ],
    "sg:website":"http://www.brennancorp.com",
    "wof:name":"Brennan Enterprise",
    "wof:placetype":"venue"
},
  "geometry": {"coordinates":[-97.113575,32.722502],"type":"Point"}
}