{
  "type": "Feature",
  "properties": {
    "iso:country":"US",
    "sg:address":"317 SW 2nd St",
    "sg:city":"Tulia",
    "sg:classifiers":[
        {
            "category":"Health Services",
            "subcategory":"Optometrist",
            "type":"Services"
        }
    ],
    "sg:phone":"+1 806 995 4102",
    "sg:postcode":"79088",
    "sg:province":"TX",
    "wof:name":"Brown Vision Ctr",
    "wof:placetype":"venue"
},
  "geometry": {"coordinates":[-101.76826699999999,34.535943],"type":"Point"}
}