{
  "type": "Feature",
  "properties": {
    "iso:country":"US",
    "sg:address":"20631 Aldine Westfield Rd",
    "sg:city":"Humble",
    "sg:classifiers":[
        {
            "category":"Professional",
            "type":"Services"
        }
    ],
    "sg:phone":"+1 281 895 7789",
    "sg:postcode":"77338",
    "sg:province":"TX",
    "wof:name":"Diana Super Inc",
    "wof:placetype":"venue"
},
  "geometry": {"coordinates":[-95.377047,30.01439],"type":"Point"}
}