{
  "type": "Feature",
  "properties": {
    "iso:country":"US",
    "sg:address":"8230 Thetford Ln",
    "sg:city":"Houston",
    "sg:classifiers":[
        {
            "category":"Building & Trades",
            "subcategory":"Plumbing",
            "type":"Services"
        }
    ],
    "sg:phone":"+1 281 469 2728",
    "sg:postcode":"77070",
    "sg:province":"TX",
    "sg:tags":[
        "conditioning",
        "contractor",
        "system",
        "air"
    ],
    "wof:name":"Gilbert's Air Conditioning Svc",
    "wof:placetype":"venue"
},
  "geometry": {"coordinates":[-95.559938,29.978672],"type":"Point"}
}