{
  "type": "Feature",
  "properties": {
    "iso:country":"US",
    "sg:address":"12219 Ecksminster St",
    "sg:city":"San Antonio",
    "sg:classifiers":[
        {
            "category":"Building & Trades",
            "subcategory":"Construction",
            "type":"Services"
        }
    ],
    "sg:phone":"+1 210 410 4350",
    "sg:postcode":"78216",
    "sg:province":"TX",
    "sg:tags":[
        "residential",
        "painting",
        "contractor"
    ],
    "wof:name":"Certa Propainters San Antonio",
    "wof:placetype":"venue"
},
  "geometry": {"coordinates":[-98.47187,29.551273],"type":"Point"}
}