{
  "type": "Feature",
  "properties": {
    "iso:country":"US",
    "sg:address":"1023 N Mound St",
    "sg:city":"Nacogdoches",
    "sg:classifiers":[
        {
            "category":"Health Services",
            "subcategory":"Doctor",
            "type":"Services"
        }
    ],
    "sg:phone":"+1 936 569 9433",
    "sg:postcode":"75961",
    "sg:province":"TX",
    "sg:tags":[
        "obstetrician",
        "gynecologist"
    ],
    "wof:name":"Lowe II William Matt M D",
    "wof:placetype":"venue"
},
  "geometry": {"coordinates":[-94.649523,31.614134],"type":"Point"}
}