{
  "type": "Feature",
  "properties": {
    "iso:country":"US",
    "sg:address":"3154 Fairway Dr",
    "sg:city":"Katy",
    "sg:classifiers":[
        {
            "category":"Personal",
            "subcategory":"Beauty Salon",
            "type":"Services"
        }
    ],
    "sg:phone":"+1 281 829 2444",
    "sg:postcode":"77478",
    "sg:province":"TX",
    "sg:tags":[
        "shop"
    ],
    "wof:name":"D Q Salon",
    "wof:placetype":"venue"
},
  "geometry": {"coordinates":[-95.585058,29.610289],"type":"Point"}
}