{
  "type": "Feature",
  "properties": {
    "iso:country":"US",
    "sg:address":"5150 Belmont St",
    "sg:city":"Beaumont",
    "sg:classifiers":[
        {
            "category":"Retail",
            "subcategory":"Auto Repair",
            "type":"Services"
        }
    ],
    "sg:phone":"+1 409 842 1892",
    "sg:postcode":"77707",
    "sg:province":"TX",
    "sg:tags":[
        "glass",
        "replacement"
    ],
    "wof:name":"Wholesale Glass",
    "wof:placetype":"venue"
},
  "geometry": {"coordinates":[-94.14726899999999,30.066419],"type":"Point"}
}