{
  "type": "Feature",
  "properties": {
    "iso:country":"US",
    "sg:address":"7318 Dew Mist Ln",
    "sg:city":"Houston",
    "sg:classifiers":[
        {
            "category":"Shopping",
            "subcategory":"Hobbies, Toys, & Games",
            "type":"Retail Goods"
        }
    ],
    "sg:phone":"+1 281 859 6620",
    "sg:postcode":"77095",
    "sg:province":"TX",
    "wof:name":"Krafty",
    "wof:placetype":"venue"
},
  "geometry": {"coordinates":[-95.656943,29.884231],"type":"Point"}
}