{
  "type": "Feature",
  "properties": {
    "iso:country":"US",
    "sg:address":"203 Chattington Ct",
    "sg:city":"San Antonio",
    "sg:classifiers":[
        {
            "category":"Wholesale",
            "subcategory":"Apparel",
            "type":"Manufacturing & Wholesale Goods"
        }
    ],
    "sg:phone":"+1 210 367 8329",
    "sg:postcode":"78213",
    "sg:province":"TX",
    "sg:tags":[
        "athletic",
        "shoes"
    ],
    "wof:name":"Outfitters Inc",
    "wof:placetype":"venue"
},
  "geometry": {"coordinates":[-98.510867,29.518829],"type":"Point"}
}