{
  "type": "Feature",
  "properties": {
    "iso:country":"US",
    "sg:address":"322 Laurel St",
    "sg:city":"La Marque",
    "sg:classifiers":[
        {
            "category":"Personal",
            "type":"Services"
        }
    ],
    "sg:phone":"+1 409 908 0923",
    "sg:postcode":"77568",
    "sg:province":"TX",
    "wof:name":"New Beginnings",
    "wof:placetype":"venue"
},
  "geometry": {"coordinates":[-94.97028899999999,29.374882],"type":"Point"}
}