{
  "type": "Feature",
  "properties": {
    "iso:country":"US",
    "sg:address":"5454 Peterson Ln",
    "sg:city":"Dallas",
    "sg:classifiers":[
        {
            "category":"Building & Trades",
            "subcategory":"Cleaning & Sanitation",
            "type":"Services"
        }
    ],
    "sg:phone":"+1 972 386 7832",
    "sg:postcode":"75240",
    "sg:province":"TX",
    "sg:tags":[
        "janitor"
    ],
    "wof:name":"Gio Cleaning Svc",
    "wof:placetype":"venue"
},
  "geometry": {"coordinates":[-96.814787,32.930529],"type":"Point"}
}