{
  "type": "Feature",
  "properties": {
    "iso:country":"US",
    "sg:address":"206 Prairie Wind Blvd",
    "sg:city":"Stephenville",
    "sg:classifiers":[
        {
            "category":"Shopping",
            "subcategory":"Computers & Home Electronics",
            "type":"Retail Goods"
        }
    ],
    "sg:phone":"+1 254 968 3713",
    "sg:postcode":"76401",
    "sg:province":"TX",
    "wof:name":"SBS Group Satellite",
    "wof:placetype":"venue"
},
  "geometry": {"coordinates":[-98.22165099999999,32.229377],"type":"Point"}
}