{
  "type": "Feature",
  "properties": {
    "iso:country":"US",
    "sg:address":"4003 Rustic Woods Dr",
    "sg:city":"Kingwood",
    "sg:classifiers":[
        {
            "category":"Fast Food",
            "type":"Food & Drink"
        },
        {
            "category":"Restaurant",
            "type":"Food & Drink"
        },
        {
            "category":"Professional",
            "type":"Services"
        }
    ],
    "sg:phone":"+1 281 913 0664",
    "sg:postcode":"77339",
    "sg:province":"TX",
    "sg:tags":[
        "american",
        "hot",
        "hamburger",
        "dog",
        "caterer"
    ],
    "sg:website":"http://www.cityeatstexas.com",
    "wof:name":"City Eats",
    "wof:placetype":"venue"
},
  "geometry": {"coordinates":[-95.18758800000001,30.05439],"type":"Point"}
}