{
  "type": "Feature",
  "properties": {
    "iso:country":"US",
    "sg:address":"45 Richardson Heights Center",
    "sg:city":"Richardson",
    "sg:classifiers":[
        {
            "category":"Health Services",
            "subcategory":"Doctor",
            "type":"Services"
        }
    ],
    "sg:phone":"+1 972 644 1100",
    "sg:postcode":"75080",
    "sg:province":"TX",
    "sg:tags":[
        "physician",
        "surgeon"
    ],
    "wof:name":"Boppana Primary Care Clinic",
    "wof:placetype":"venue"
},
  "geometry": {"coordinates":[-96.735799,32.950541],"type":"Point"}
}