{
  "type": "Feature",
  "properties": {
    "iso:country":"US",
    "sg:address":"944 S Fry Rd",
    "sg:city":"Katy",
    "sg:classifiers":[
        {
            "category":"Retail",
            "subcategory":"Laundry & Dry Cleaning",
            "type":"Services"
        }
    ],
    "sg:phone":"+1 281 578 6855",
    "sg:postcode":"77450",
    "sg:province":"TX",
    "sg:tags":[
        "drycleaning",
        "plant"
    ],
    "wof:name":"Classic Cleaners",
    "wof:placetype":"venue"
},
  "geometry": {"coordinates":[-95.718886,29.770677],"type":"Point"}
}