{
  "type": "Feature",
  "properties": {
    "iso:country":"US",
    "sg:address":"6214 Paddle Wheel Dr",
    "sg:city":"Katy",
    "sg:classifiers":[
        {
            "category":"Travel",
            "subcategory":"Travel Agent",
            "type":"Entertainment"
        }
    ],
    "sg:phone":"+1 281 855 8690",
    "sg:postcode":"77449",
    "sg:province":"TX",
    "sg:tags":[
        "agency"
    ],
    "wof:name":"Business Travel & Tours",
    "wof:placetype":"venue"
},
  "geometry": {"coordinates":[-95.705518,29.86357],"type":"Point"}
}