{
  "type": "Feature",
  "properties": {
    "iso:country":"US",
    "sg:address":"3133 Autumn Leaf Dr",
    "sg:city":"Friendswood",
    "sg:classifiers":[
        {
            "category":"Professional",
            "subcategory":"Employment Agencies",
            "type":"Services"
        },
        {
            "category":"Organizations",
            "subcategory":"Community Association",
            "type":"Services"
        }
    ],
    "sg:phone":"+1 281 993 8147",
    "sg:postcode":"77546",
    "sg:province":"TX",
    "sg:tags":[
        "employer"
    ],
    "wof:name":"Alba Games",
    "wof:placetype":"venue"
},
  "geometry": {"coordinates":[-95.16231999999999,29.514219],"type":"Point"}
}