{
  "type": "Feature",
  "properties": {
    "iso:country":"US",
    "sg:address":"3504 Pembroke Pl",
    "sg:city":"Bedford",
    "sg:classifiers":[
        {
            "category":"Real Estate",
            "subcategory":"Real Estate Operator",
            "type":"Services"
        }
    ],
    "sg:phone":"+1 817 684 8946",
    "sg:postcode":"76021",
    "sg:province":"TX",
    "sg:tags":[
        "building",
        "nonresidential"
    ],
    "wof:name":"Sovereign Properties",
    "wof:placetype":"venue"
},
  "geometry": {"coordinates":[-97.112347,32.860328],"type":"Point"}
}