{
  "type": "Feature",
  "properties": {
    "iso:country":"US",
    "sg:address":"311 E 5th Ave",
    "sg:city":"Amarillo",
    "sg:classifiers":[
        {
            "category":"Building & Trades",
            "subcategory":"Construction",
            "type":"Services"
        }
    ],
    "sg:phone":"+1 806 379 5512",
    "sg:postcode":"79101",
    "sg:province":"AR",
    "sg:tags":[
        "company"
    ],
    "wof:name":"Royall Construction",
    "wof:placetype":"venue"
},
  "geometry": {"coordinates":[-101.833145,35.208212],"type":"Point"}
}