{
  "type": "Feature",
  "properties": {
    "iso:country":"US",
    "sg:address":"302 NE Wilshire Blvd",
    "sg:city":"Burleson",
    "sg:classifiers":[
        {
            "category":"Personal",
            "subcategory":"Nail Salon",
            "type":"Services"
        }
    ],
    "sg:phone":"+1 817 447 0808",
    "sg:postcode":"76028",
    "sg:province":"TX",
    "wof:name":"Elan Full Service Family Salon",
    "wof:placetype":"venue"
},
  "geometry": {"coordinates":[-97.32399700000001,32.5476],"type":"Point"}
}