{
  "type": "Feature",
  "properties": {
    "iso:country":"US",
    "sg:address":"4115 Keller Springs Rd",
    "sg:city":"Addison",
    "sg:classifiers":[
        {
            "category":"Manufacturing",
            "subcategory":"Metals",
            "type":"Manufacturing & Wholesale Goods"
        }
    ],
    "sg:phone":"+1 972 732 8045",
    "sg:postcode":"75006",
    "sg:province":"TX",
    "sg:tags":[
        "grating"
    ],
    "wof:name":"Chemgrate Corp",
    "wof:placetype":"venue"
},
  "geometry": {"coordinates":[-96.840586,32.969052],"type":"Point"}
}