{
  "type": "Feature",
  "properties": {
    "iso:country":"US",
    "sg:address":"1004 W Tate St",
    "sg:city":"Waco",
    "sg:classifiers":[
        {
            "category":"Education",
            "subcategory":"School",
            "type":"Public Place"
        }
    ],
    "sg:phone":"+1 254 752 1119",
    "sg:postcode":"76706",
    "sg:province":"TX",
    "wof:name":"Waco Isd Police Assoc",
    "wof:placetype":"venue"
},
  "geometry": {"coordinates":[-97.12851999999999,31.459619],"type":"Point"}
}