{
  "type": "Feature",
  "properties": {
    "iso:country":"US",
    "sg:address":"514 Over Ridge Dr",
    "sg:city":"San Antonio",
    "sg:classifiers":[
        {
            "category":"Restaurant",
            "type":"Food & Drink"
        }
    ],
    "sg:phone":"+1 210 923 2637",
    "sg:postcode":"78221",
    "sg:province":"TX",
    "sg:tags":[
        "eating"
    ],
    "wof:name":"Perfect Service Catering",
    "wof:placetype":"venue"
},
  "geometry": {"coordinates":[-98.512524,29.338849],"type":"Point"}
}