{
  "type": "Feature",
  "properties": {
    "iso:country":"US",
    "sg:address":"900 Strey Ln",
    "sg:city":"Houston",
    "sg:classifiers":[
        {
            "category":"Retail",
            "subcategory":"Auto Rental",
            "type":"Services"
        }
    ],
    "sg:phone":"+1 713 984 9082",
    "sg:postcode":"77024",
    "sg:province":"TX",
    "sg:tags":[
        "renting",
        "car",
        "automobile"
    ],
    "sg:website":"www.budget.com",
    "wof:name":"Budget Rent A Car Iahsg",
    "wof:placetype":"venue"
},
  "geometry": {"coordinates":[-95.538887,29.781968],"type":"Point"}
}