{
  "type": "Feature",
  "properties": {
    "iso:country":"US",
    "sg:address":"3502 Shadow Trl",
    "sg:city":"Houston",
    "sg:classifiers":[
        {
            "category":"Shopping",
            "subcategory":"Jewelry",
            "type":"Retail Goods"
        }
    ],
    "sg:phone":"+1 281 599 7808",
    "sg:postcode":"77084",
    "sg:province":"TX",
    "wof:name":"Rj & G Goods",
    "wof:placetype":"venue"
},
  "geometry": {"coordinates":[-95.693806,29.822574],"type":"Point"}
}