{
  "type": "Feature",
  "properties": {
    "iso:country":"US",
    "sg:address":"4600 Elwood Rd",
    "sg:city":"Austin",
    "sg:classifiers":[
        {
            "category":"Organizations",
            "subcategory":"Membership Organization",
            "type":"Services"
        }
    ],
    "sg:phone":"+1 512 467 6616",
    "sg:postcode":"78722",
    "sg:province":"TX",
    "wof:name":"United Sttes Hspnic Cntrs Assn",
    "wof:placetype":"venue"
},
  "geometry": {"coordinates":[-97.712001,30.3045],"type":"Point"}
}