{
  "type": "Feature",
  "properties": {
    "iso:country":"US",
    "sg:address":"12213 Waters Park Rd",
    "sg:city":"Austin",
    "sg:classifiers":[
        {
            "category":"Retail",
            "subcategory":"Laundry & Dry Cleaning",
            "type":"Services"
        }
    ],
    "sg:phone":"+1 512 490 1112",
    "sg:postcode":"78759",
    "sg:province":"TX",
    "sg:tags":[
        "cleaners",
        "rug",
        "carpet"
    ],
    "wof:name":"Rainbow International Carpet",
    "wof:placetype":"venue"
},
  "geometry": {"coordinates":[-97.710205,30.411853],"type":"Point"}
}