{
  "type": "Feature",
  "properties": {
    "iso:country":"US",
    "sg:address":"201 Elizabeth Rd",
    "sg:city":"San Antonio",
    "sg:classifiers":[
        {
            "category":"Professional",
            "subcategory":"Lawyer & Legal Services",
            "type":"Services"
        }
    ],
    "sg:phone":"+1 210 930 4470",
    "sg:postcode":"78209",
    "sg:province":"TX",
    "wof:name":"David A Whipple Attorney Law",
    "wof:placetype":"venue"
},
  "geometry": {"coordinates":[-98.457211,29.472731],"type":"Point"}
}