{
  "type": "Feature",
  "properties": {
    "iso:country":"US",
    "sg:address":"3024 Sheraton Dr",
    "sg:city":"Plano",
    "sg:classifiers":[
        {
            "category":"Real Estate",
            "subcategory":"Real Estate Agent",
            "type":"Services"
        }
    ],
    "sg:phone":"+1 972 612 2007",
    "sg:postcode":"75075",
    "sg:province":"TX",
    "wof:name":"Clayton E Bennett Realtors",
    "wof:placetype":"venue"
},
  "geometry": {"coordinates":[-96.75393800000001,33.038929],"type":"Point"}
}