{
  "type": "Feature",
  "properties": {
    "iso:country":"US",
    "sg:address":"2310 4th St",
    "sg:city":"Orange",
    "sg:classifiers":[
        {
            "category":"Building & Trades",
            "subcategory":"Construction",
            "type":"Services"
        }
    ],
    "sg:phone":"+1 409 886 1193",
    "sg:postcode":"77630",
    "sg:province":"TX",
    "sg:tags":[
        "general",
        "contractor"
    ],
    "wof:name":"Big Al's Construction",
    "wof:placetype":"venue"
},
  "geometry": {"coordinates":[-93.733115,30.113115],"type":"Point"}
}