{
  "type": "Feature",
  "properties": {
    "iso:country":"US",
    "sg:address":"7810 Callaghan Rd",
    "sg:city":"San Antonio",
    "sg:classifiers":[
        {
            "category":"Personal",
            "subcategory":"Beauty Salon",
            "type":"Services"
        }
    ],
    "sg:phone":"+1 210 348 9559",
    "sg:postcode":"78229",
    "sg:province":"TX",
    "sg:tags":[
        "shop"
    ],
    "wof:name":"Beauty For Ashes",
    "wof:placetype":"venue"
},
  "geometry": {"coordinates":[-98.553926,29.509513],"type":"Point"}
}