{
  "type": "Feature",
  "properties": {
    "iso:country":"US",
    "sg:address":"2711 Highway 35 N",
    "sg:city":"Rockport",
    "sg:classifiers":[
        {
            "category":"Restaurant",
            "type":"Food & Drink"
        }
    ],
    "sg:menulink":"http://www.allmenus.com/tx/rockport/70529-pizza-hut/menu/",
    "sg:phone":"+1 361 729 7270",
    "sg:postcode":"78382",
    "sg:province":"TX",
    "sg:tags":[
        "american",
        "pizza"
    ],
    "wof:name":"PIZZA HUT",
    "wof:placetype":"venue"
},
  "geometry": {"coordinates":[-97.04161999999999,28.054024],"type":"Point"}
}