{
  "type": "Feature",
  "properties": {
    "iso:country":"US",
    "sg:address":"424 Countryside Ln",
    "sg:city":"Richardson",
    "sg:classifiers":[
        {
            "category":"Organizations",
            "subcategory":"Community Association",
            "type":"Services"
        }
    ],
    "sg:phone":"+1 972 889 8037",
    "sg:postcode":"75081",
    "sg:province":"TX",
    "wof:name":"Sett Stiles Electronically Tau",
    "wof:placetype":"venue"
},
  "geometry": {"coordinates":[-96.73171600000001,32.928787],"type":"Point"}
}