{
  "type": "Feature",
  "properties": {
    "iso:country":"US",
    "sg:address":"201 Ferris Ave",
    "sg:city":"Waxahachie",
    "sg:classifiers":[
        {
            "category":"Personal",
            "subcategory":"Massage",
            "type":"Services"
        },
        {
            "category":"Health Services",
            "subcategory":"Clinic",
            "type":"Services"
        },
        {
            "category":"Health Services",
            "subcategory":"Doctor",
            "type":"Services"
        },
        {
            "category":"Health Services",
            "subcategory":"Health Practitioner",
            "type":"Services"
        },
        {
            "category":"Health Services",
            "subcategory":"Chiropractor",
            "type":"Services"
        }
    ],
    "sg:phone":"+1 888 802 0231",
    "sg:postcode":"75165",
    "sg:province":"TX",
    "sg:tags":[
        "physician",
        "chiropractic",
        "medical",
        "therapist",
        "medicine",
        "alternative",
        "surgeon"
    ],
    "wof:name":"Quest Healthcare",
    "wof:placetype":"venue"
},
  "geometry": {"coordinates":[-96.85006,32.387642],"type":"Point"}
}