{
  "type": "Feature",
  "properties": {
    "iso:country":"US",
    "sg:address":"408 Willow Way",
    "sg:city":"Wylie",
    "sg:classifiers":[
        {
            "category":"Building & Trades",
            "subcategory":"Cleaning & Sanitation",
            "type":"Services"
        }
    ],
    "sg:phone":"+1 972 429 9656",
    "sg:postcode":"75098",
    "sg:province":"TX",
    "sg:tags":[
        "maintenance"
    ],
    "wof:name":"Sunflower Services & Referrals",
    "wof:placetype":"venue"
},
  "geometry": {"coordinates":[-96.545323,33.00272],"type":"Point"}
}