{
  "type": "Feature",
  "properties": {
    "iso:country":"US",
    "sg:address":"323 N Main St",
    "sg:city":"Belton",
    "sg:classifiers":[
        {
            "category":"Restaurant",
            "type":"Food & Drink"
        }
    ],
    "sg:menulink":"http://www.allmenus.com/tx/belton/94517-dominos-pizza/menu/",
    "sg:phone":"+1 254 939 2888",
    "sg:postcode":"76513",
    "sg:province":"TX",
    "sg:tags":[
        "american",
        "wing",
        "pizza"
    ],
    "wof:name":"Domino's Pizza",
    "wof:placetype":"venue"
},
  "geometry": {"coordinates":[-97.462785,31.058975],"type":"Point"}
}