{
  "type": "Feature",
  "properties": {
    "iso:country":"US",
    "sg:address":"1605 Francis St",
    "sg:city":"Carrollton",
    "sg:classifiers":[
        {
            "category":"Freight",
            "type":"Transportation"
        }
    ],
    "sg:phone":"+1 972 245 7552",
    "sg:postcode":"75006",
    "sg:province":"TX",
    "sg:tags":[
        "operator",
        "trucking"
    ],
    "wof:name":"Mc Transport Inc",
    "wof:placetype":"venue"
},
  "geometry": {"coordinates":[-96.897497,32.952449],"type":"Point"}
}