{
  "type": "Feature",
  "properties": {
    "iso:country":"US",
    "sg:address":"2115 Judiway St",
    "sg:city":"Houston",
    "sg:classifiers":[
        {
            "category":"Building & Trades",
            "subcategory":"Construction",
            "type":"Services"
        }
    ],
    "sg:phone":"+1 713 680 8025",
    "sg:postcode":"77018",
    "sg:province":"TX",
    "sg:tags":[
        "contractor"
    ],
    "wof:name":"Marek Brothers Systems Inc",
    "wof:placetype":"venue"
},
  "geometry": {"coordinates":[-95.436718,29.8205],"type":"Point"}
}