{
  "type": "Feature",
  "properties": {
    "iso:country":"US",
    "sg:address":"12631 Ivyforest Dr",
    "sg:city":"Cypress",
    "sg:classifiers":[
        {
            "category":"Professional",
            "subcategory":"Business Services",
            "type":"Services"
        }
    ],
    "sg:phone":"+1 281 379 6118",
    "sg:postcode":"77429",
    "sg:province":"TX",
    "wof:name":"Mae Enterprises",
    "wof:placetype":"venue"
},
  "geometry": {"coordinates":[-95.61177499999999,29.997722],"type":"Point"}
}