{
  "type": "Feature",
  "properties": {
    "iso:country":"US",
    "sg:address":"7906 Fields St",
    "sg:city":"Houston",
    "sg:classifiers":[
        {
            "category":"Freight",
            "type":"Transportation"
        }
    ],
    "sg:phone":"+1 713 675 8029",
    "sg:postcode":"77028",
    "sg:province":"TX",
    "sg:tags":[
        "operator",
        "local",
        "trucking"
    ],
    "wof:name":"Phoenix Enterprise Trucking",
    "wof:placetype":"venue"
},
  "geometry": {"coordinates":[-95.282888,29.80867],"type":"Point"}
}