{
  "type": "Feature",
  "properties": {
    "iso:country":"US",
    "sg:address":"1001 Andrews Hwy",
    "sg:city":"Midland",
    "sg:classifiers":[
        {
            "category":"Organizations",
            "subcategory":"Religious Organization",
            "type":"Services"
        }
    ],
    "sg:phone":"+1 432 694 5321",
    "sg:postcode":"79701",
    "sg:province":"TX",
    "wof:name":"Memorial Christian Church",
    "wof:placetype":"venue"
},
  "geometry": {"coordinates":[-102.11438699999999,32.000994],"type":"Point"}
}