{
  "type": "Feature",
  "properties": {
    "iso:country":"US",
    "sg:address":"9001 Blue Hill Ct",
    "sg:city":"Austin",
    "sg:classifiers":[
        {
            "category":"Professional",
            "subcategory":"Secretarial Services",
            "type":"Services"
        }
    ],
    "sg:phone":"+1 512 288 9715",
    "sg:postcode":"78736",
    "sg:province":"TX",
    "sg:tags":[
        "reporting"
    ],
    "wof:name":"Glenda Green",
    "wof:placetype":"venue"
},
  "geometry": {"coordinates":[-97.93607,30.238785],"type":"Point"}
}