{
  "type": "Feature",
  "properties": {
    "iso:country":"US",
    "sg:address":"705 S Lee St",
    "sg:city":"Santa Anna",
    "sg:classifiers":[
        {
            "category":"Communications",
            "subcategory":"Radio Station",
            "type":"Services"
        }
    ],
    "sg:phone":"+1 325 348 3000",
    "sg:postcode":"76878",
    "sg:province":"TX",
    "sg:tags":[
        "company",
        "broadcasting"
    ],
    "wof:name":"Nexstar Broadcasting-Abilene",
    "wof:placetype":"venue"
},
  "geometry": {"coordinates":[-99.321117,31.734092],"type":"Point"}
}