{
  "type": "Feature",
  "properties": {
    "iso:country":"US",
    "sg:address":"7025 Hill Forest Dr",
    "sg:city":"Dallas",
    "sg:classifiers":[
        {
            "category":"Professional",
            "subcategory":"Computer Services",
            "type":"Services"
        }
    ],
    "sg:phone":"+1 972 980 0500",
    "sg:postcode":"75230",
    "sg:province":"TX",
    "sg:tags":[
        "information",
        "recovery",
        "processing",
        "system",
        "equipment",
        "data",
        "retrieval"
    ],
    "wof:name":"Lake Forest Information Line",
    "wof:placetype":"venue"
},
  "geometry": {"coordinates":[-96.78429,32.911764],"type":"Point"}
}