{
  "type": "Feature",
  "properties": {
    "iso:country":"US",
    "sg:address":"2144 Rand Morgan Rd",
    "sg:city":"Corpus Christi",
    "sg:classifiers":[
        {
            "category":"Building & Trades",
            "subcategory":"Construction",
            "type":"Services"
        }
    ],
    "sg:phone":"+1 361 241 7977",
    "sg:postcode":"78410",
    "sg:province":"TX",
    "sg:tags":[
        "residential"
    ],
    "wof:name":"Siding Co Inc",
    "wof:placetype":"venue"
},
  "geometry": {"coordinates":[-97.547658,27.823783],"type":"Point"}
}