{
  "type": "Feature",
  "properties": {
    "iso:country":"US",
    "sg:address":"7317 Springdale St",
    "sg:city":"Houston",
    "sg:classifiers":[
        {
            "category":"Freight",
            "type":"Transportation"
        }
    ],
    "sg:phone":"+1 713 635 5882",
    "sg:postcode":"77028",
    "sg:province":"TX",
    "sg:tags":[
        "local",
        "trucking"
    ],
    "wof:name":"Williams & Sons Inc",
    "wof:placetype":"venue"
},
  "geometry": {"coordinates":[-95.294082,29.839513],"type":"Point"}
}