{
  "type": "Feature",
  "properties": {
    "iso:country":"US",
    "sg:address":"11116 Ebb Tide Dr",
    "sg:city":"El Paso",
    "sg:classifiers":[
        {
            "category":"Retail",
            "subcategory":"Car Wash",
            "type":"Services"
        }
    ],
    "sg:phone":"+1 915 592 1222",
    "sg:postcode":"79936",
    "sg:province":"TX",
    "sg:tags":[
        "automobile",
        "detail",
        "clean"
    ],
    "wof:name":"G & G Auto Details",
    "wof:placetype":"venue"
},
  "geometry": {"coordinates":[-106.310373,31.782385],"type":"Point"}
}