{
  "type": "Feature",
  "properties": {
    "iso:country":"US",
    "sg:address":"415 US Hwy 180",
    "sg:city":"Lamesa",
    "sg:classifiers":[
        {
            "category":"Farming",
            "subcategory":"Farm & Veterinary Services",
            "type":"Manufacturing & Wholesale Goods"
        }
    ],
    "sg:phone":"+1 806 462 7351",
    "sg:postcode":"79331",
    "sg:province":"TX",
    "sg:tags":[
        "gin",
        "cotton"
    ],
    "wof:name":"King Mesa Gin",
    "wof:placetype":"venue"
},
  "geometry": {"coordinates":[-101.949521,32.730231],"type":"Point"}
}