{
  "type": "Feature",
  "properties": {
    "iso:country":"US",
    "sg:address":"1823 Locksford St",
    "sg:city":"Houston",
    "sg:classifiers":[
        {
            "category":"Manufacturing",
            "subcategory":"Paper Products",
            "type":"Manufacturing & Wholesale Goods"
        }
    ],
    "sg:phone":"+1 713 864 2854",
    "sg:postcode":"77008",
    "sg:province":"TX",
    "sg:tags":[
        "sanitary",
        "mfg"
    ],
    "wof:name":"Anns Kids",
    "wof:placetype":"venue"
},
  "geometry": {"coordinates":[-95.446135,29.803347],"type":"Point"}
}