{
  "type": "Feature",
  "properties": {
    "iso:country":"US",
    "sg:address":"3907 Senour Ct",
    "sg:city":"Kingwood",
    "sg:classifiers":[
        {
            "category":"Home & Garden",
            "subcategory":"Furniture",
            "type":"Retail Goods"
        }
    ],
    "sg:phone":"+1 281 359 7673",
    "sg:postcode":"77339",
    "sg:province":"TX",
    "sg:tags":[
        "equipment-household",
        "kitchen",
        "cabinet"
    ],
    "wof:name":"Djt Enterprises",
    "wof:placetype":"venue"
},
  "geometry": {"coordinates":[-95.20608799999999,30.070052],"type":"Point"}
}