{
  "type": "Feature",
  "properties": {
    "iso:country":"US",
    "sg:address":"8181 Tezel Rd",
    "sg:city":"San Antonio",
    "sg:classifiers":[
        {
            "category":"Building & Trades",
            "subcategory":"Construction",
            "type":"Services"
        }
    ],
    "sg:phone":"+1 210 647 8023",
    "sg:postcode":"78250",
    "sg:province":"TX",
    "sg:tags":[
        "painter",
        "contractor"
    ],
    "wof:name":"Action Painting",
    "wof:placetype":"venue"
},
  "geometry": {"coordinates":[-98.66242,29.517095],"type":"Point"}
}