{
  "type": "Feature",
  "properties": {
    "iso:country":"US",
    "sg:address":"700 Hidalgo St",
    "sg:city":"Mercedes",
    "sg:classifiers":[
        {
            "category":"Personal",
            "subcategory":"Beauty Salon",
            "type":"Services"
        }
    ],
    "sg:phone":"+1 956 565 6433",
    "sg:postcode":"78570",
    "sg:province":"TX",
    "sg:tags":[
        "shop"
    ],
    "wof:name":"Lillys Beauty Salon",
    "wof:placetype":"venue"
},
  "geometry": {"coordinates":[-97.91714899999999,26.152825],"type":"Point"}
}