{
  "type": "Feature",
  "properties": {
    "iso:country":"US",
    "sg:address":"13450 Maham Rd Apt 324",
    "sg:city":"Dallas",
    "sg:classifiers":[
        {
            "category":"Retail",
            "subcategory":"Laundry & Dry Cleaning",
            "type":"Services"
        },
        {
            "category":"Building & Trades",
            "subcategory":"Cleaning & Sanitation",
            "type":"Services"
        }
    ],
    "sg:phone":"+1 214 929 7024",
    "sg:postcode":"75240",
    "sg:province":"TX",
    "sg:tags":[
        "cleaner",
        "house"
    ],
    "wof:name":"Mavy, S House Cleaning Service",
    "wof:placetype":"venue"
},
  "geometry": {"coordinates":[-96.761185,32.931696],"type":"Point"}
}