{
  "type": "Feature",
  "properties": {
    "iso:country":"US",
    "sg:address":"5303 Lilac Ln",
    "sg:city":"Victoria",
    "sg:classifiers":[
        {
            "category":"Professional",
            "subcategory":"Computer Services",
            "type":"Services"
        }
    ],
    "sg:phone":"+1 361 579 9884",
    "sg:postcode":"77904",
    "sg:province":"TX",
    "wof:name":"Accelerated Computer Tech Svcs",
    "wof:placetype":"venue"
},
  "geometry": {"coordinates":[-96.9979,28.8431],"type":"Point"}
}