{
  "type": "Feature",
  "properties": {
    "iso:country":"US",
    "sg:address":"313 Osage St",
    "sg:city":"Refugio",
    "sg:classifiers":[
        {
            "category":"Professional",
            "subcategory":"Business Services",
            "type":"Services"
        }
    ],
    "sg:phone":"+1 361 526 1597",
    "sg:postcode":"78377",
    "sg:province":"TX",
    "wof:name":"A and A Bail Bonding",
    "wof:placetype":"venue"
},
  "geometry": {"coordinates":[-97.272982,28.302415],"type":"Point"}
}