{
  "type": "Feature",
  "properties": {
    "iso:country":"US",
    "sg:address":"621 N Hampton Rd Suite 104",
    "sg:city":"Desoto",
    "sg:classifiers":[
        {
            "category":"Banks & Credit Unions",
            "subcategory":"Investment Brokerage",
            "type":"Services"
        },
        {
            "category":"Banks & Credit Unions",
            "subcategory":"Bank",
            "type":"Services"
        },
        {
            "category":"Banks & Credit Unions",
            "subcategory":"Financial Services",
            "type":"Services"
        }
    ],
    "sg:phone":"+1 972 230 7098",
    "sg:postcode":"75115",
    "sg:province":"TX",
    "sg:tags":[
        "advisory",
        "mutual",
        "retirement",
        "annuity",
        "broker",
        "fund",
        "planning",
        "plan",
        "consultant",
        "security",
        "bond",
        "insurance",
        "stock"
    ],
    "sg:website":"http://edwardjones.com",
    "wof:name":"Edward Jones - JEFF BUTTGEN",
    "wof:placetype":"venue"
},
  "geometry": {"coordinates":[-96.85719400000001,32.599642],"type":"Point"}
}