{
  "type": "Feature",
  "properties": {
    "iso:country":"US",
    "sg:address":"323 N Sam Houston Pkwy E",
    "sg:city":"Houston",
    "sg:classifiers":[
        {
            "category":"Banks & Credit Unions",
            "subcategory":"Bank",
            "type":"Services"
        }
    ],
    "sg:phone":"+1 281 931 4208",
    "sg:postcode":"77060",
    "sg:province":"TX",
    "wof:name":"Amegy Bank",
    "wof:placetype":"venue"
},
  "geometry": {"coordinates":[-95.400127,29.940517],"type":"Point"}
}