{
  "type": "Feature",
  "properties": {
    "iso:country":"US",
    "sg:address":"1324 SW Military Dr",
    "sg:city":"San Antonio",
    "sg:classifiers":[
        {
            "category":"Professional",
            "subcategory":"Accounting & Tax Preparation",
            "type":"Services"
        }
    ],
    "sg:phone":"+1 210 922 3171",
    "sg:postcode":"78221",
    "sg:province":"TX",
    "sg:tags":[
        "return",
        "filing"
    ],
    "wof:name":"Fast Cash Refund Express",
    "wof:placetype":"venue"
},
  "geometry": {"coordinates":[-98.513931,29.356595],"type":"Point"}
}