{
  "type": "Feature",
  "properties": {
    "iso:country":"US",
    "sg:address":"9807 Mula Rd",
    "sg:city":"Stafford",
    "sg:classifiers":[
        {
            "category":"Wholesale",
            "subcategory":"Machinery & Supplies",
            "type":"Manufacturing & Wholesale Goods"
        },
        {
            "category":"Home & Garden",
            "subcategory":"Building Materials",
            "type":"Retail Goods"
        }
    ],
    "sg:phone":"+1 281 564 3726",
    "sg:postcode":"77477",
    "sg:province":"TX",
    "sg:tags":[
        "plumbing",
        "industrial",
        "fixture",
        "merchandise"
    ],
    "sg:website":"www.ferguson.com",
    "wof:name":"Esco Supply Co",
    "wof:placetype":"venue"
},
  "geometry": {"coordinates":[-95.54934900000001,29.632786],"type":"Point"}
}