{
  "type": "Feature",
  "properties": {
    "iso:country":"US",
    "sg:address":"5401 N 10th St",
    "sg:city":"Mcallen",
    "sg:classifiers":[
        {
            "category":"Personal",
            "type":"Services"
        },
        {
            "category":"Sports & Exercise",
            "subcategory":"Gym",
            "type":"Entertainment"
        },
        {
            "category":"Health Services",
            "subcategory":"Health Practitioner",
            "type":"Services"
        },
        {
            "category":"Arena",
            "subcategory":"Sports Club",
            "type":"Entertainment"
        }
    ],
    "sg:phone":"+1 956 972 1000",
    "sg:postcode":"78504",
    "sg:province":"TX",
    "sg:tags":[
        "control",
        "weight",
        "consultant",
        "program",
        "fitness",
        "physical"
    ],
    "sg:website":"http://www.curves.com",
    "wof:name":"Curves",
    "wof:placetype":"venue"
},
  "geometry": {"coordinates":[-98.221808,26.251657],"type":"Point"}
}