{
  "type": "Feature",
  "properties": {
    "iso:country":"US",
    "sg:address":"11991 Main St",
    "sg:city":"Houston",
    "sg:classifiers":[
        {
            "category":"Travel",
            "subcategory":"Campground",
            "type":"Entertainment"
        }
    ],
    "sg:phone":"+1 713 723 0973",
    "sg:postcode":"77035",
    "sg:province":"TX",
    "wof:name":"All Star Rv Resort",
    "wof:placetype":"venue"
},
  "geometry": {"coordinates":[-95.445436,29.653398],"type":"Point"}
}