{
  "type": "Feature",
  "properties": {
    "iso:country":"US",
    "sg:address":"1510 NW 28th St",
    "sg:city":"Fort Worth",
    "sg:classifiers":[
        {
            "category":"Food & Beverages",
            "subcategory":"Bakery",
            "type":"Retail Goods"
        }
    ],
    "sg:phone":"+1 817 624 2077",
    "sg:postcode":"76164",
    "sg:province":"TX",
    "sg:tags":[
        "baker"
    ],
    "wof:name":"Panaderia San Marcus",
    "wof:placetype":"venue"
},
  "geometry": {"coordinates":[-97.367068,32.795581],"type":"Point"}
}