{
  "type": "Feature",
  "properties": {
    "iso:country":"US",
    "sg:address":"1020 S 14th St",
    "sg:city":"Kingsville",
    "sg:classifiers":[
        {
            "category":"Social Services",
            "subcategory":"Child Care",
            "type":"Services"
        }
    ],
    "sg:phone":"+1 361 592 0125",
    "sg:postcode":"78363",
    "sg:province":"TX",
    "sg:tags":[
        "kindergarten",
        "academic",
        "school"
    ],
    "wof:name":"Community Action Headstart",
    "wof:placetype":"venue"
},
  "geometry": {"coordinates":[-97.855925,27.507567],"type":"Point"}
}