{
  "type": "Feature",
  "properties": {
    "iso:country":"US",
    "sg:address":"2118 Marsalis Dr",
    "sg:city":"Abilene",
    "sg:classifiers":[
        {
            "category":"Building & Trades",
            "subcategory":"Landscaping Services",
            "type":"Services"
        }
    ],
    "sg:phone":"+1 325 672 7647",
    "sg:postcode":"79603",
    "sg:province":"TX",
    "wof:name":"Rks Sr Enterprises Inc",
    "wof:placetype":"venue"
},
  "geometry": {"coordinates":[-99.770655,32.471435],"type":"Point"}
}