{
  "type": "Feature",
  "properties": {
    "iso:country":"US",
    "sg:address":"4835 N O Connor Rd",
    "sg:city":"Irving",
    "sg:classifiers":[
        {
            "category":"Manufacturing",
            "subcategory":"Printing",
            "type":"Manufacturing & Wholesale Goods"
        }
    ],
    "sg:phone":"+1 972 717 1888",
    "sg:postcode":"75062",
    "sg:province":"TX",
    "sg:tags":[
        "printer"
    ],
    "wof:name":"Signal Graphics Printing",
    "wof:placetype":"venue"
},
  "geometry": {"coordinates":[-96.950822,32.863238],"type":"Point"}
}