{
  "type": "Feature",
  "properties": {
    "iso:country":"US",
    "sg:address":"2401 Fountain View Dr",
    "sg:city":"Houston",
    "sg:classifiers":[
        {
            "category":"Professional",
            "subcategory":"Lawyer & Legal Services",
            "type":"Services"
        }
    ],
    "sg:phone":"+1 713 623 6881",
    "sg:postcode":"77057",
    "sg:province":"TX",
    "wof:name":"Durrett J Brantley III Atty",
    "wof:placetype":"venue"
},
  "geometry": {"coordinates":[-95.48462000000001,29.741604],"type":"Point"}
}