{
  "type": "Feature",
  "properties": {
    "iso:country":"US",
    "sg:address":"2744 Horseback Ct",
    "sg:city":"College Station",
    "sg:classifiers":[
        {
            "category":"Recreation",
            "type":"Entertainment"
        }
    ],
    "sg:phone":"+1 979 696 1388",
    "sg:postcode":"77845",
    "sg:province":"TX",
    "sg:tags":[
        "stable"
    ],
    "wof:name":"Hunter's Creek Stable",
    "wof:placetype":"venue"
},
  "geometry": {"coordinates":[-96.29103000000001,30.626031],"type":"Point"}
}