{
  "type": "Feature",
  "properties": {
    "iso:country":"US",
    "sg:address":"1611 Ave M",
    "sg:city":"Lubbock",
    "sg:classifiers":[
        {
            "category":"Social Services",
            "subcategory":"Child Care",
            "type":"Services"
        }
    ],
    "sg:phone":"+1 806 749 0093",
    "sg:postcode":"79401",
    "sg:province":"TX",
    "sg:tags":[
        "kindergarten",
        "academic",
        "school"
    ],
    "wof:name":"Shapes Academy",
    "wof:placetype":"venue"
},
  "geometry": {"coordinates":[-101.85011299999999,33.579934],"type":"Point"}
}