{
  "type": "Feature",
  "properties": {
    "iso:country":"US",
    "sg:address":"3920 Phelan Blvd",
    "sg:city":"Beaumont",
    "sg:classifiers":[
        {
            "category":"Manufacturing",
            "subcategory":"Signs",
            "type":"Manufacturing & Wholesale Goods"
        }
    ],
    "sg:phone":"+1 409 892 5456",
    "sg:postcode":"77707",
    "sg:province":"TX",
    "sg:tags":[
        "advertising",
        "specialty"
    ],
    "wof:name":"High Tech Signs",
    "wof:placetype":"venue"
},
  "geometry": {"coordinates":[-94.143878,30.084535],"type":"Point"}
}