{
  "type": "Feature",
  "properties": {
    "iso:country":"US",
    "sg:address":"4527 E Grand Ave",
    "sg:city":"Dallas",
    "sg:classifiers":[
        {
            "category":"Retail",
            "subcategory":"Auto Repair",
            "type":"Services"
        }
    ],
    "sg:phone":"+1 214 821 3188",
    "sg:postcode":"75223",
    "sg:province":"TX",
    "sg:tags":[
        "repairing",
        "automobile",
        "general"
    ],
    "wof:name":"Agustin's Auto Repair",
    "wof:placetype":"venue"
},
  "geometry": {"coordinates":[-96.757628,32.784463],"type":"Point"}
}