{
  "type": "Feature",
  "properties": {
    "iso:country":"US",
    "sg:address":"11991 Main St",
    "sg:city":"Houston",
    "sg:classifiers":[
        {
            "category":"Freight",
            "type":"Transportation"
        }
    ],
    "sg:phone":"+1 713 283 1846",
    "sg:postcode":"77035",
    "sg:province":"TX",
    "sg:tags":[
        "commercial",
        "storage"
    ],
    "wof:name":"Champs Construction Co",
    "wof:placetype":"venue"
},
  "geometry": {"coordinates":[-95.445436,29.653398],"type":"Point"}
}