{
  "type": "Feature",
  "properties": {
    "iso:country":"US",
    "sg:address":"502 Windsor Glen Dr",
    "sg:city":"Katy",
    "sg:classifiers":[
        {
            "category":"Real Estate",
            "subcategory":"Real Estate Agent",
            "type":"Services"
        }
    ],
    "sg:phone":"+1 281 646 0373",
    "sg:postcode":"77450",
    "sg:province":"TX",
    "wof:name":"Silver Key Properties",
    "wof:placetype":"venue"
},
  "geometry": {"coordinates":[-95.73224,29.782101],"type":"Point"}
}