{
  "type": "Feature",
  "properties": {
    "iso:country":"US",
    "sg:address":"101 W Borden Dr",
    "sg:city":"Diboll",
    "sg:classifiers":[
        {
            "category":"Manufacturing",
            "subcategory":"Petroleum Products",
            "type":"Manufacturing & Wholesale Goods"
        }
    ],
    "sg:phone":"+1 936 829 5279",
    "sg:postcode":"75941",
    "sg:province":"TX",
    "sg:tags":[
        "roofing",
        "material"
    ],
    "wof:name":"Atlas Roofing",
    "wof:placetype":"venue"
},
  "geometry": {"coordinates":[-94.781661,31.195311],"type":"Point"}
}