{
  "type": "Feature",
  "properties": {
    "iso:country":"US",
    "sg:address":"505 S Texas Blvd",
    "sg:city":"Weslaco",
    "sg:classifiers":[
        {
            "category":"Retail",
            "subcategory":"Animal Services",
            "type":"Services"
        }
    ],
    "sg:phone":"+1 956 447 8133",
    "sg:postcode":"78596",
    "sg:province":"TX",
    "sg:tags":[
        "pet",
        "grooming",
        "washing"
    ],
    "wof:name":"Paw Prints Pet Salon",
    "wof:placetype":"venue"
},
  "geometry": {"coordinates":[-97.990561,26.157016],"type":"Point"}
}