{
  "type": "Feature",
  "properties": {
    "iso:country":"US",
    "sg:address":"27 Cherokee Trl",
    "sg:city":"Henderson",
    "sg:classifiers":[
        {
            "category":"Retail",
            "subcategory":"Animal Services",
            "type":"Services"
        }
    ],
    "sg:phone":"+1 903 643 2898",
    "sg:postcode":"75652",
    "sg:province":"TX",
    "wof:name":"Rancho Poco Loco L L C",
    "wof:placetype":"venue"
},
  "geometry": {"coordinates":[-94.66931599999999,32.362591],"type":"Point"}
}