{
  "type": "Feature",
  "properties": {
    "iso:country":"US",
    "sg:address":"600 Six Flags Dr",
    "sg:city":"Arlington",
    "sg:classifiers":[
        {
            "category":"Utilities",
            "subcategory":"Cable",
            "type":"Services"
        }
    ],
    "sg:phone":"+1 817 417 0466",
    "sg:postcode":"76011",
    "sg:province":"TX",
    "sg:tags":[
        "television"
    ],
    "wof:name":"CA Bill Services Inc",
    "wof:placetype":"venue"
},
  "geometry": {"coordinates":[-97.06877299999999,32.749432],"type":"Point"}
}