{
  "type": "Feature",
  "properties": {
    "iso:country":"US",
    "sg:address":"2427 N Fry Rd",
    "sg:city":"Katy",
    "sg:classifiers":[
        {
            "category":"Health Services",
            "subcategory":"Doctor",
            "type":"Services"
        }
    ],
    "sg:phone":"+1 281 599 1755",
    "sg:postcode":"77449",
    "sg:province":"TX",
    "wof:name":"KATY Dental",
    "wof:placetype":"venue"
},
  "geometry": {"coordinates":[-95.71935000000001,29.802367],"type":"Point"}
}