{
  "type": "Feature",
  "properties": {
    "iso:country":"US",
    "sg:address":"1101 S Capital of Texas Hwy",
    "sg:city":"Austin",
    "sg:classifiers":[
        {
            "category":"Real Estate",
            "subcategory":"Real Estate Agent",
            "type":"Services"
        }
    ],
    "sg:phone":"+1 512 328 5740",
    "sg:postcode":"78746",
    "sg:province":"TX",
    "wof:name":"Boardwalk Properties",
    "wof:placetype":"venue"
},
  "geometry": {"coordinates":[-97.819907,30.278209],"type":"Point"}
}