{
  "type": "Feature",
  "properties": {
    "iso:country":"US",
    "sg:address":"1903 Central Dr",
    "sg:city":"Bedford",
    "sg:classifiers":[
        {
            "category":"Banks & Credit Unions",
            "subcategory":"Bank",
            "type":"Services"
        }
    ],
    "sg:phone":"+1 817 540 4800",
    "sg:postcode":"76021",
    "sg:province":"TX",
    "sg:tags":[
        "banking",
        "mortgage"
    ],
    "wof:name":"Universal American Mrtg Co LLC",
    "wof:placetype":"venue"
},
  "geometry": {"coordinates":[-97.13345200000001,32.840035],"type":"Point"}
}