{
  "type": "Feature",
  "properties": {
    "iso:country":"US",
    "sg:address":"13017 Perico Dr",
    "sg:city":"San Elizario",
    "sg:classifiers":[
        {
            "category":"Health Services",
            "subcategory":"Doctor",
            "type":"Services"
        }
    ],
    "sg:phone":"+1 915 851 0999",
    "sg:postcode":"79849",
    "sg:province":"TX",
    "sg:tags":[
        "clinic"
    ],
    "wof:name":"Centro San Vicente",
    "wof:placetype":"venue"
},
  "geometry": {"coordinates":[-106.283804,31.5807],"type":"Point"}
}