{
  "type": "Feature",
  "properties": {
    "iso:country":"US",
    "sg:address":"3500 Oak Ridge Dr",
    "sg:city":"Bryan",
    "sg:classifiers":[
        {
            "category":"Professional",
            "subcategory":"Computer Services",
            "type":"Services"
        }
    ],
    "sg:phone":"+1 979 260 1089",
    "sg:postcode":"77802",
    "sg:province":"TX",
    "sg:tags":[
        "datum"
    ],
    "wof:name":"Stella S Nolen",
    "wof:placetype":"venue"
},
  "geometry": {"coordinates":[-96.33131299999999,30.650682],"type":"Point"}
}