{
  "type": "Feature",
  "properties": {
    "iso:country":"US",
    "sg:address":"1852 Norwood Plaza Ct",
    "sg:city":"Hurst",
    "sg:classifiers":[
        {
            "category":"Professional",
            "subcategory":"Lawyer & Legal Services",
            "type":"Services"
        }
    ],
    "sg:phone":"+1 817 336 5436",
    "sg:postcode":"76054",
    "sg:province":"TX",
    "sg:tags":[
        "attorney"
    ],
    "wof:name":"Alice Holland",
    "wof:placetype":"venue"
},
  "geometry": {"coordinates":[-97.167992,32.849053],"type":"Point"}
}