{
  "type": "Feature",
  "properties": {
    "iso:country":"US",
    "sg:address":"200 W Yoakum Ave",
    "sg:city":"Kingsville",
    "sg:classifiers":[
        {
            "category":"Real Estate",
            "subcategory":"Real Estate Agent",
            "type":"Services"
        }
    ],
    "sg:phone":"+1 361 592 3575",
    "sg:postcode":"78363",
    "sg:province":"TX",
    "sg:tags":[
        "authorities",
        "housing"
    ],
    "wof:name":"Kingsville Housing Authority",
    "wof:placetype":"venue"
},
  "geometry": {"coordinates":[-97.87065200000001,27.517636],"type":"Point"}
}