{
  "type": "Feature",
  "properties": {
    "iso:country":"US",
    "sg:address":"815 Brazos St Ste A",
    "sg:city":"Austin",
    "sg:classifiers":[
        {
            "category":"Autos & Motor Vehicles",
            "subcategory":"Automobile Sales",
            "type":"Retail Goods"
        }
    ],
    "sg:phone":"+1 512 255 2454",
    "sg:postcode":"78701",
    "sg:province":"TX",
    "sg:tags":[
        "limo"
    ],
    "wof:name":"Executive Limo Service",
    "wof:placetype":"venue"
},
  "geometry": {"coordinates":[-97.74057000000001,30.269631],"type":"Point"}
}