{
  "type": "Feature",
  "properties": {
    "iso:country":"US",
    "sg:address":"12256 Amstater Cir",
    "sg:city":"El Paso",
    "sg:classifiers":[
        {
            "category":"Retail",
            "subcategory":"Auto Repair",
            "type":"Services"
        }
    ],
    "sg:phone":"+1 915 591 4479",
    "sg:postcode":"79936",
    "sg:province":"TX",
    "sg:tags":[
        "automotive"
    ],
    "wof:name":"Ginos Radiator Service",
    "wof:placetype":"venue"
},
  "geometry": {"coordinates":[-106.26971899999999,31.728456],"type":"Point"}
}