{
  "type": "Feature",
  "properties": {
    "iso:country":"US",
    "sg:address":"918 W 14th St",
    "sg:city":"San Angelo",
    "sg:classifiers":[
        {
            "category":"Retail",
            "subcategory":"Repair Shop",
            "type":"Services"
        }
    ],
    "sg:phone":"+1 325 655 2959",
    "sg:postcode":"76903",
    "sg:province":"TX",
    "sg:tags":[
        "vehicle"
    ],
    "wof:name":"Caddy Shack Golf Cars",
    "wof:placetype":"venue"
},
  "geometry": {"coordinates":[-100.45712399999999,31.46688],"type":"Point"}
}