{
  "type": "Feature",
  "properties": {
    "iso:country":"US",
    "sg:address":"1903 Big Horn Dr",
    "sg:city":"Houston",
    "sg:classifiers":[
        {
            "category":"Professional",
            "subcategory":"Business Services",
            "type":"Services"
        }
    ],
    "sg:phone":"+1 281 880 6815",
    "sg:postcode":"77090",
    "sg:province":"TX",
    "wof:name":"Party Solutions",
    "wof:placetype":"venue"
},
  "geometry": {"coordinates":[-95.465475,30.019982],"type":"Point"}
}