{
  "type": "Feature",
  "properties": {
    "iso:country":"US",
    "sg:address":"1211 Palo Blanco Dr",
    "sg:city":"Port Isabel",
    "sg:classifiers":[
        {
            "category":"Utilities",
            "subcategory":"Telephone",
            "type":"Services"
        }
    ],
    "sg:phone":"+1 956 433 1219",
    "sg:postcode":"78578",
    "sg:province":"TX",
    "sg:tags":[
        "communications"
    ],
    "wof:name":"Thunder Road",
    "wof:placetype":"venue"
},
  "geometry": {"coordinates":[-97.299335,26.1051],"type":"Point"}
}