{
  "type": "Feature",
  "properties": {
    "iso:country":"US",
    "sg:address":"9901 State Hwy 95",
    "sg:city":"Bartlett",
    "sg:classifiers":[
        {
            "category":"Manufacturing",
            "subcategory":"Chemicals & Compounds",
            "type":"Manufacturing & Wholesale Goods"
        }
    ],
    "sg:phone":"+1 254 527 3354",
    "sg:postcode":"76511",
    "sg:province":"TX",
    "sg:tags":[
        "fertilizer",
        "mixing",
        "only"
    ],
    "wof:name":"American Plant Food Corp",
    "wof:placetype":"venue"
},
  "geometry": {"coordinates":[-97.432616,30.78325],"type":"Point"}
}