{
  "type": "Feature",
  "properties": {
    "iso:country":"US",
    "sg:address":"800 Jordan St",
    "sg:city":"White Deer",
    "sg:classifiers":[
        {
            "category":"Organizations",
            "subcategory":"Religious Organization",
            "type":"Services"
        }
    ],
    "sg:phone":"+1 806 883 5391",
    "sg:postcode":"79065",
    "sg:province":"TX",
    "sg:tags":[
        "clergy"
    ],
    "wof:name":"United Methodist Chr Parsonage",
    "wof:placetype":"venue"
},
  "geometry": {"coordinates":[-100.95572300000001,35.545432],"type":"Point"}
}