{
  "type": "Feature",
  "properties": {
    "iso:country":"US",
    "sg:address":"1005 W Lucas Rd",
    "sg:city":"Allen",
    "sg:classifiers":[
        {
            "category":"Building & Trades",
            "subcategory":"Landscaping Services",
            "type":"Services"
        }
    ],
    "sg:phone":"+1 972 442 1997",
    "sg:postcode":"75002",
    "sg:province":"TX",
    "sg:tags":[
        "landscape"
    ],
    "wof:name":"Central North Construction",
    "wof:placetype":"venue"
},
  "geometry": {"coordinates":[-96.59179399999999,33.085272],"type":"Point"}
}