{
  "type": "Feature",
  "properties": {
    "iso:country":"US",
    "sg:address":"120 Basse Rd E",
    "sg:city":"San Antonio",
    "sg:classifiers":[
        {
            "category":"Professional",
            "subcategory":"Computer Services",
            "type":"Services"
        }
    ],
    "sg:phone":"+1 210 545 2128",
    "sg:postcode":"78209",
    "sg:province":"TX",
    "sg:tags":[
        "programing",
        "custom"
    ],
    "wof:name":"Cognitive Systems Technologies",
    "wof:placetype":"venue"
},
  "geometry": {"coordinates":[-98.480491,29.492058],"type":"Point"}
}