{
  "type": "Feature",
  "properties": {
    "iso:country":"US",
    "sg:address":"107 W Mossy Cup Ln",
    "sg:city":"San Antonio",
    "sg:classifiers":[
        {
            "category":"Retail",
            "subcategory":"Portrait Studio",
            "type":"Services"
        }
    ],
    "sg:phone":"+1 210 479 3078",
    "sg:postcode":"78231",
    "sg:province":"TX",
    "sg:tags":[
        "photo"
    ],
    "wof:name":"Southern Exposure Photography",
    "wof:placetype":"venue"
},
  "geometry": {"coordinates":[-98.565304,29.590937],"type":"Point"}
}