{
  "type": "Feature",
  "properties": {
    "iso:country":"US",
    "sg:address":"204 Dellwood St",
    "sg:city":"Bryan",
    "sg:classifiers":[
        {
            "category":"Manufacturing",
            "subcategory":"Jewelry",
            "type":"Manufacturing & Wholesale Goods"
        }
    ],
    "sg:phone":"+1 979 822 9724",
    "sg:postcode":"77801",
    "sg:province":"TX",
    "sg:tags":[
        "material",
        "mfg"
    ],
    "wof:name":"Gioro Designs",
    "wof:placetype":"venue"
},
  "geometry": {"coordinates":[-96.35770100000001,30.642117],"type":"Point"}
}