{
  "type": "Feature",
  "properties": {
    "iso:country":"US",
    "sg:address":"5350 Jarman St",
    "sg:city":"Abilene",
    "sg:classifiers":[
        {
            "category":"Organizations",
            "subcategory":"Community Association",
            "type":"Services"
        }
    ],
    "sg:phone":"+1 325 673 0587",
    "sg:postcode":"79601",
    "sg:province":"TX",
    "wof:name":"Kiwanis International",
    "wof:placetype":"venue"
},
  "geometry": {"coordinates":[-99.73775000000001,32.515949],"type":"Point"}
}