{
  "type": "Feature",
  "properties": {
    "iso:country":"US",
    "sg:address":"10 Hilltop Ln",
    "sg:city":"Texarkana",
    "sg:classifiers":[
        {
            "category":"Professional",
            "subcategory":"Management & Consulting",
            "type":"Services"
        }
    ],
    "sg:phone":"+1 903 223 7224",
    "sg:postcode":"75501",
    "sg:province":"TX",
    "sg:tags":[
        "public",
        "relations"
    ],
    "wof:name":"Unlimited Promotions",
    "wof:placetype":"venue"
},
  "geometry": {"coordinates":[-94.115199,33.368544],"type":"Point"}
}