{
  "type": "Feature",
  "properties": {
    "iso:country":"US",
    "sg:address":"5722 Cedar Cove",
    "sg:city":"San Antonio",
    "sg:phone":"+1 210 690 4172",
    "sg:postcode":"78249",
    "sg:province":"TX",
    "sg:tags":[
        "shutter",
        "conditioner",
        "fluid"
    ],
    "wof:name":"Mag-Well Associated Inc",
    "wof:placetype":"venue"
},
  "geometry": {"coordinates":[-98.59597100000001,29.549821],"type":"Point"}
}