{
  "type": "Feature",
  "properties": {
    "iso:country":"US",
    "sg:address":"5500 E Grand Ave",
    "sg:city":"Dallas",
    "sg:classifiers":[
        {
            "category":"Food & Beverages",
            "subcategory":"Groceries & Convenience Stores",
            "type":"Retail Goods"
        }
    ],
    "sg:phone":"+1 214 827 9081",
    "sg:postcode":"75223",
    "sg:province":"TX",
    "wof:name":"7-Eleven Stores",
    "wof:placetype":"venue"
},
  "geometry": {"coordinates":[-96.747803,32.793201],"type":"Point"}
}