{
  "type": "Feature",
  "properties": {
    "iso:country":"US",
    "sg:address":"1013 Tamara Ln",
    "sg:city":"Grand Prairie",
    "sg:classifiers":[
        {
            "category":"Building & Trades",
            "subcategory":"Construction",
            "type":"Services"
        }
    ],
    "sg:phone":"+1 972 262 5681",
    "sg:postcode":"75051",
    "sg:province":"TX",
    "sg:tags":[
        "home",
        "improvement"
    ],
    "wof:name":"K W & Co",
    "wof:placetype":"venue"
},
  "geometry": {"coordinates":[-97.00797300000001,32.731186],"type":"Point"}
}