{
  "type": "Feature",
  "properties": {
    "iso:country":"US",
    "sg:address":"1011 Pecan St",
    "sg:city":"Sanger",
    "sg:classifiers":[
        {
            "category":"Retail",
            "subcategory":"Auto Repair",
            "type":"Services"
        }
    ],
    "sg:phone":"+1 940 458 4091",
    "sg:postcode":"76266",
    "sg:province":"TX",
    "sg:tags":[
        "repairing",
        "automobile"
    ],
    "wof:name":"409 Auto Repair",
    "wof:placetype":"venue"
},
  "geometry": {"coordinates":[-97.180002,33.363931],"type":"Point"}
}