{
  "type": "Feature",
  "properties": {
    "iso:country":"US",
    "sg:address":"5311 Crestway Dr",
    "sg:city":"San Antonio",
    "sg:classifiers":[
        {
            "category":"Organizations",
            "subcategory":"Religious Organization",
            "type":"Services"
        }
    ],
    "sg:phone":"+1 210 653 2225",
    "sg:postcode":"78239",
    "sg:province":"TX",
    "wof:name":"Calvary Baptist Church",
    "wof:placetype":"venue"
},
  "geometry": {"coordinates":[-98.381649,29.523083],"type":"Point"}
}