{
  "type": "Feature",
  "properties": {
    "iso:country":"US",
    "sg:address":"9724 Skillman St",
    "sg:city":"Dallas",
    "sg:classifiers":[
        {
            "category":"Shopping",
            "subcategory":"Computers & Home Electronics",
            "type":"Retail Goods"
        },
        {
            "category":"Wholesale",
            "subcategory":"Computers",
            "type":"Manufacturing & Wholesale Goods"
        }
    ],
    "sg:phone":"+1 214 348 9880",
    "sg:postcode":"75243",
    "sg:province":"TX",
    "sg:tags":[
        "equipment",
        "repair",
        "electronic",
        "supply"
    ],
    "sg:website":"www.usaelectronics.com",
    "wof:name":"USA Electronics",
    "wof:placetype":"venue"
},
  "geometry": {"coordinates":[-96.70700100000001,32.908199],"type":"Point"}
}