{
  "type": "Feature",
  "properties": {
    "iso:country":"US",
    "sg:address":"709 Pecan St",
    "sg:city":"Bandera",
    "sg:classifiers":[
        {
            "category":"Organizations",
            "subcategory":"Religious Organization",
            "type":"Services"
        }
    ],
    "sg:phone":"+1 830 796 8260",
    "sg:postcode":"78003",
    "sg:province":"TX",
    "sg:tags":[
        "church"
    ],
    "wof:name":"Jehovah's Witnesses",
    "wof:placetype":"venue"
},
  "geometry": {"coordinates":[-99.076992,29.723564],"type":"Point"}
}