{
  "type": "Feature",
  "properties": {
    "iso:country":"US",
    "sg:address":"3231 Maroneal St",
    "sg:city":"Houston",
    "sg:classifiers":[
        {
            "category":"Real Estate",
            "subcategory":"Architect",
            "type":"Services"
        }
    ],
    "sg:phone":"+1 713 661 8881",
    "sg:postcode":"77025",
    "sg:province":"TX",
    "wof:name":"BPM Group",
    "wof:placetype":"venue"
},
  "geometry": {"coordinates":[-95.427666,29.702084],"type":"Point"}
}