{
  "type": "Feature",
  "properties": {
    "iso:country":"US",
    "sg:address":"12360 Richmond Ave",
    "sg:city":"Houston",
    "sg:classifiers":[
        {
            "category":"Professional",
            "subcategory":"Computer Services",
            "type":"Services"
        }
    ],
    "sg:phone":"+1 281 752 8902",
    "sg:postcode":"77082",
    "sg:province":"TX",
    "sg:tags":[
        "consulting"
    ],
    "wof:name":"Intellisft",
    "wof:placetype":"venue"
},
  "geometry": {"coordinates":[-95.59902700000001,29.729925],"type":"Point"}
}