{
  "type": "Feature",
  "properties": {
    "iso:country":"US",
    "sg:address":"309 Mill St",
    "sg:city":"Del Rio",
    "sg:classifiers":[
        {
            "category":"Government",
            "subcategory":"Office",
            "type":"Public Place"
        }
    ],
    "sg:phone":"+1 830 774 7581",
    "sg:postcode":"78840",
    "sg:province":"TX",
    "wof:name":"Honorable Luna Virgilio",
    "wof:placetype":"venue"
},
  "geometry": {"coordinates":[-100.893441,29.355556],"type":"Point"}
}