{
  "type": "Feature",
  "properties": {
    "iso:country":"US",
    "sg:address":"1820 S 10th St",
    "sg:city":"Mcallen",
    "sg:classifiers":[
        {
            "category":"Banks & Credit Unions",
            "subcategory":"Bank",
            "type":"Services"
        }
    ],
    "sg:phone":"+1 956 631 2016",
    "sg:postcode":"78503",
    "sg:province":"TX",
    "sg:tags":[
        "currency",
        "foreign",
        "exchange"
    ],
    "wof:name":"Casa De Cambio Lone Star",
    "wof:placetype":"venue"
},
  "geometry": {"coordinates":[-98.232646,26.188431],"type":"Point"}
}