{
  "type": "Feature",
  "properties": {
    "iso:country":"US",
    "sg:address":"8511 San Lorenzo Dr",
    "sg:city":"Laredo",
    "sg:classifiers":[
        {
            "category":"Freight",
            "type":"Transportation"
        }
    ],
    "sg:phone":"+1 956 712 1935",
    "sg:postcode":"78045",
    "sg:province":"TX",
    "sg:tags":[
        "trucking"
    ],
    "wof:name":"Cavazos Car Transport",
    "wof:placetype":"venue"
},
  "geometry": {"coordinates":[-99.510592,27.586097],"type":"Point"}
}