{
  "type": "Feature",
  "properties": {
    "iso:country":"US",
    "sg:address":"707 E 3rd St",
    "sg:city":"Big Spring",
    "sg:classifiers":[
        {
            "category":"Health Services",
            "subcategory":"Health Practitioner",
            "type":"Services"
        }
    ],
    "sg:phone":"+1 432 263 3868",
    "sg:postcode":"79720",
    "sg:province":"TX",
    "wof:name":"Downing Michael PHD",
    "wof:placetype":"venue"
},
  "geometry": {"coordinates":[-101.46912399999999,32.255654],"type":"Point"}
}