{
  "type": "Feature",
  "properties": {
    "iso:country":"US",
    "sg:address":"2436 Sherwood Way",
    "sg:city":"San Angelo",
    "sg:classifiers":[
        {
            "category":"Insurance",
            "subcategory":"Insurance Agent",
            "type":"Services"
        }
    ],
    "sg:phone":"+1 325 224 2800",
    "sg:postcode":"76901",
    "sg:province":"TX",
    "wof:name":"Maverick Insurance",
    "wof:placetype":"venue"
},
  "geometry": {"coordinates":[-100.47074600000001,31.450299],"type":"Point"}
}