{
  "type": "Feature",
  "properties": {
    "iso:country":"US",
    "sg:address":"305 W Schreiner St",
    "sg:city":"Kerrville",
    "sg:classifiers":[
        {
            "category":"Food & Beverages",
            "subcategory":"Specialty",
            "type":"Retail Goods"
        }
    ],
    "sg:phone":"+1 830 896 2085",
    "sg:postcode":"78028",
    "sg:province":"TX",
    "sg:tags":[
        "health",
        "diet"
    ],
    "wof:name":"Watkins Quality Products",
    "wof:placetype":"venue"
},
  "geometry": {"coordinates":[-99.14736000000001,30.057244],"type":"Point"}
}