{
  "type": "Feature",
  "properties": {
    "iso:country":"US",
    "sg:address":"1101 Split Oak Cove",
    "sg:city":"Pflugerville",
    "sg:classifiers":[
        {
            "category":"Professional",
            "subcategory":"Business Services",
            "type":"Services"
        }
    ],
    "sg:phone":"+1 512 251 2031",
    "sg:postcode":"78660",
    "sg:province":"TX",
    "wof:name":"Bounce About Moonwalks",
    "wof:placetype":"venue"
},
  "geometry": {"coordinates":[-97.61003599999999,30.44664],"type":"Point"}
}