{
  "type": "Feature",
  "properties": {
    "iso:country":"US",
    "sg:address":"17300 Dallas Pkwy",
    "sg:city":"Dallas",
    "sg:classifiers":[
        {
            "category":"Arts & Performance",
            "subcategory":"Theater",
            "type":"Entertainment"
        }
    ],
    "sg:phone":"+1 972 778 7700",
    "sg:postcode":"75248",
    "sg:province":"TX",
    "sg:tags":[
        "sport"
    ],
    "wof:name":"Hoop It Up",
    "wof:placetype":"venue"
},
  "geometry": {"coordinates":[-96.82830199999999,32.985793],"type":"Point"}
}