{
  "type": "Feature",
  "properties": {
    "iso:country":"US",
    "sg:address":"2125 Co Rd 2840",
    "sg:city":"Mineola",
    "sg:classifiers":[
        {
            "category":"Professional",
            "subcategory":"Art Services",
            "type":"Services"
        }
    ],
    "sg:phone":"+1 903 569 2966",
    "sg:postcode":"75773",
    "sg:province":"TX",
    "sg:tags":[
        "graphic",
        "designer"
    ],
    "wof:name":"Greazmonkey Grafix",
    "wof:placetype":"venue"
},
  "geometry": {"coordinates":[-95.518058,32.671631],"type":"Point"}
}