{
  "type": "Feature",
  "properties": {
    "iso:country":"US",
    "sg:address":"3008 Commerce St",
    "sg:city":"Dallas",
    "sg:classifiers":[
        {
            "category":"Professional",
            "subcategory":"Business Services",
            "type":"Services"
        }
    ],
    "sg:phone":"+1 214 745 5585",
    "sg:postcode":"75226",
    "sg:province":"TX",
    "wof:name":"Kul Design Studios",
    "wof:placetype":"venue"
},
  "geometry": {"coordinates":[-96.778744,32.783982],"type":"Point"}
}