{
  "type": "Feature",
  "properties": {
    "iso:country":"US",
    "sg:address":"1177 Rockingham Ln",
    "sg:city":"Richardson",
    "sg:classifiers":[
        {
            "category":"Shopping",
            "subcategory":"Florist",
            "type":"Retail Goods"
        }
    ],
    "sg:phone":"+1 972 248 2666",
    "sg:postcode":"75080",
    "sg:province":"TX",
    "sg:tags":[
        "event",
        "special"
    ],
    "wof:name":"Floral Secrets",
    "wof:placetype":"venue"
},
  "geometry": {"coordinates":[-96.74092400000001,32.963857],"type":"Point"}
}