{
  "type": "Feature",
  "properties": {
    "iso:country":"US",
    "sg:address":"3841 Ranch Rd 620 S",
    "sg:city":"Austin",
    "sg:classifiers":[
        {
            "category":"Shopping",
            "subcategory":"Used Merchandise",
            "type":"Retail Goods"
        },
        {
            "category":"Home & Garden",
            "subcategory":"Carpets & Floor Coverings",
            "type":"Retail Goods"
        }
    ],
    "sg:phone":"+1 512 263 3333",
    "sg:postcode":"78738",
    "sg:province":"TX",
    "sg:tags":[
        "dealer",
        "laying",
        "rug",
        "contractor"
    ],
    "sg:website":"www.designerfloorsoftexas.com",
    "wof:name":"Designer Floors Of Texas Inc",
    "wof:placetype":"venue"
},
  "geometry": {"coordinates":[-97.94883799999999,30.31451],"type":"Point"}
}