{
  "type": "Feature",
  "properties": {
    "iso:country":"US",
    "sg:address":"834 Moonshine Hill Rd",
    "sg:city":"Humble",
    "sg:classifiers":[
        {
            "category":"Banks & Credit Unions",
            "subcategory":"Financial Services",
            "type":"Services"
        }
    ],
    "sg:phone":"+1 281 540 1897",
    "sg:postcode":"77338",
    "sg:province":"TX",
    "sg:tags":[
        "company",
        "holding"
    ],
    "wof:name":"Hilltop Properties Inc",
    "wof:placetype":"venue"
},
  "geometry": {"coordinates":[-95.236806,30.010772],"type":"Point"}
}