{
  "type": "Feature",
  "properties": {
    "iso:country":"US",
    "sg:address":"100 Baker Ct",
    "sg:city":"Hurst",
    "sg:classifiers":[
        {
            "category":"Shopping",
            "subcategory":"Bicycles & Sporting Goods",
            "type":"Retail Goods"
        }
    ],
    "sg:phone":"+1 817 285 7484",
    "sg:postcode":"76054",
    "sg:province":"TX",
    "wof:name":"Donald L Smith",
    "wof:placetype":"venue"
},
  "geometry": {"coordinates":[-97.167321,32.845014],"type":"Point"}
}