{
  "type": "Feature",
  "properties": {
    "iso:country":"US",
    "sg:address":"921 Sirocco Dr",
    "sg:city":"Austin",
    "sg:classifiers":[
        {
            "category":"Retail",
            "subcategory":"Repair Shop",
            "type":"Services"
        }
    ],
    "sg:phone":"+1 512 444 8766",
    "sg:postcode":"78745",
    "sg:province":"TX",
    "wof:name":"S & S Satellite-Austin",
    "wof:placetype":"venue"
},
  "geometry": {"coordinates":[-97.789342,30.202771],"type":"Point"}
}