{
  "type": "Feature",
  "properties": {
    "iso:country":"US",
    "sg:address":"221 N Glenwood Blvd",
    "sg:city":"Tyler",
    "sg:classifiers":[
        {
            "category":"Retail",
            "subcategory":"Veterinary Services",
            "type":"Services"
        }
    ],
    "sg:phone":"+1 903 592 3877",
    "sg:postcode":"75702",
    "sg:province":"TX",
    "sg:tags":[
        "specialty"
    ],
    "wof:name":"Buchanan Ann",
    "wof:placetype":"venue"
},
  "geometry": {"coordinates":[-95.31928600000001,32.352235],"type":"Point"}
}