{
  "type": "Feature",
  "properties": {
    "iso:country":"US",
    "sg:address":"302 N Main St",
    "sg:city":"Mart",
    "sg:classifiers":[
        {
            "category":"Professional",
            "type":"Services"
        }
    ],
    "sg:phone":"+1 254 876 3117",
    "sg:postcode":"76664",
    "sg:province":"TX",
    "wof:name":"Elmo J Milling",
    "wof:placetype":"venue"
},
  "geometry": {"coordinates":[-96.83755499999999,31.544867],"type":"Point"}
}