{
  "type": "Feature",
  "properties": {
    "iso:country":"US",
    "sg:address":"18201 Travis Dr",
    "sg:city":"Leander",
    "sg:classifiers":[
        {
            "category":"Real Estate",
            "subcategory":"Real Estate Agent",
            "type":"Services"
        }
    ],
    "sg:phone":"+1 512 892 6400",
    "sg:postcode":"78645",
    "sg:province":"TX",
    "wof:name":"Mined Games Inc",
    "wof:placetype":"venue"
},
  "geometry": {"coordinates":[-97.96259999999999,30.424187],"type":"Point"}
}