{
  "type": "Feature",
  "properties": {
    "iso:country":"US",
    "sg:address":"762 W Southcross Blvd",
    "sg:city":"San Antonio",
    "sg:classifiers":[
        {
            "category":"Shopping",
            "type":"Retail Goods"
        }
    ],
    "sg:phone":"+1 210 923 7436",
    "sg:postcode":"78211",
    "sg:province":"TX",
    "sg:tags":[
        "merchandise"
    ],
    "wof:name":"John C Freeman",
    "wof:placetype":"venue"
},
  "geometry": {"coordinates":[-98.52171,29.368118],"type":"Point"}
}