{
  "type": "Feature",
  "properties": {
    "iso:country":"US",
    "sg:address":"209 Old Hewitt Rd Ste 3",
    "sg:city":"Waco",
    "sg:classifiers":[
        {
            "category":"Professional",
            "subcategory":"Detective & Security Services",
            "type":"Services"
        }
    ],
    "sg:phone":"+1 254 772 9558",
    "sg:postcode":"76712",
    "sg:province":"TX",
    "sg:tags":[
        "information",
        "bureau"
    ],
    "wof:name":"Kyser & Associates",
    "wof:placetype":"venue"
},
  "geometry": {"coordinates":[-97.211327,31.497761],"type":"Point"}
}