{
  "type": "Feature",
  "properties": {
    "iso:country":"US",
    "sg:address":"621 Post Oak Dr",
    "sg:city":"Hurst",
    "sg:classifiers":[
        {
            "category":"Real Estate",
            "subcategory":"Real Estate Agent",
            "type":"Services"
        }
    ],
    "sg:phone":"+1 817 280 9909",
    "sg:postcode":"76053",
    "sg:province":"TX",
    "sg:tags":[
        "appraiser"
    ],
    "wof:name":"A & M Appraisal Assoc",
    "wof:placetype":"venue"
},
  "geometry": {"coordinates":[-97.17968399999999,32.811312],"type":"Point"}
}