{
  "type": "Feature",
  "properties": {
    "iso:country":"US",
    "sg:address":"455 State Hwy 27",
    "sg:city":"Kerrville",
    "sg:classifiers":[
        {
            "category":"Building & Trades",
            "subcategory":"Construction",
            "type":"Services"
        }
    ],
    "sg:phone":"+1 830 377 8663",
    "sg:postcode":"78028",
    "sg:province":"TX",
    "sg:tags":[
        "heavy"
    ],
    "wof:name":"Karrville Wetscapes",
    "wof:placetype":"venue"
},
  "geometry": {"coordinates":[-99.15241899999999,30.054605],"type":"Point"}
}