{
  "type": "Feature",
  "properties": {
    "iso:country":"US",
    "sg:address":"5806 Bankside Dr",
    "sg:city":"Houston",
    "sg:classifiers":[
        {
            "category":"Professional",
            "subcategory":"Art Services",
            "type":"Services"
        }
    ],
    "sg:phone":"+1 713 283 5951",
    "sg:postcode":"77096",
    "sg:province":"TX",
    "sg:tags":[
        "picture",
        "frame"
    ],
    "wof:name":"All About Frames",
    "wof:placetype":"venue"
},
  "geometry": {"coordinates":[-95.490044,29.663022],"type":"Point"}
}