{
  "type": "Feature",
  "properties": {
    "iso:country":"US",
    "sg:address":"208 Parkview Dr",
    "sg:city":"Arlington",
    "sg:classifiers":[
        {
            "category":"Building & Trades",
            "subcategory":"Landscaping Services",
            "type":"Services"
        }
    ],
    "sg:phone":"+1 817 460 3579",
    "sg:postcode":"76010",
    "sg:province":"TX",
    "sg:tags":[
        "landscape",
        "contractor"
    ],
    "wof:name":"Green Dreams Landscpg & Lawn",
    "wof:placetype":"venue"
},
  "geometry": {"coordinates":[-97.080978,32.738157],"type":"Point"}
}