{
  "type": "Feature",
  "properties": {
    "iso:country":"US",
    "sg:address":"304 S Lowell Ave",
    "sg:city":"Breckenridge",
    "sg:classifiers":[
        {
            "category":"Social Services",
            "subcategory":"Adult Care",
            "type":"Services"
        }
    ],
    "sg:phone":"+1 254 559 2024",
    "sg:postcode":"76424",
    "sg:province":"TX",
    "sg:tags":[
        "home",
        "residential"
    ],
    "wof:name":"Margie's Place",
    "wof:placetype":"venue"
},
  "geometry": {"coordinates":[-98.88024900000001,32.752085],"type":"Point"}
}