{
  "type": "Feature",
  "properties": {
    "iso:country":"US",
    "sg:address":"2300 W Lavender Ln",
    "sg:city":"Arlington",
    "sg:classifiers":[
        {
            "category":"Manufacturing",
            "subcategory":"Tools & Machinery",
            "type":"Manufacturing & Wholesale Goods"
        }
    ],
    "sg:phone":"+1 817 460 5435",
    "sg:postcode":"76013",
    "sg:province":"TX",
    "sg:tags":[
        "electrical",
        "mfg"
    ],
    "wof:name":"Thomas & Betts Corporation",
    "wof:placetype":"venue"
},
  "geometry": {"coordinates":[-97.139257,32.711367],"type":"Point"}
}