{
  "type": "Feature",
  "properties": {
    "iso:country":"US",
    "sg:address":"1915 Laredo St",
    "sg:city":"Corpus Christi",
    "sg:classifiers":[
        {
            "category":"Autos & Motor Vehicles",
            "subcategory":"Automobile Sales",
            "type":"Retail Goods"
        }
    ],
    "sg:phone":"+1 361 881 9416",
    "sg:postcode":"78405",
    "sg:province":"TX",
    "sg:tags":[
        "car",
        "dealer"
    ],
    "wof:name":"Henry's Auto Sales",
    "wof:placetype":"venue"
},
  "geometry": {"coordinates":[-97.41103699999999,27.787746],"type":"Point"}
}