{
  "type": "Feature",
  "properties": {
    "iso:country":"US",
    "sg:address":"2723 S Marsalis Ave",
    "sg:city":"Dallas",
    "sg:classifiers":[
        {
            "category":"Organizations",
            "subcategory":"Religious Organization",
            "type":"Services"
        }
    ],
    "sg:phone":"+1 214 943 6007",
    "sg:postcode":"75216",
    "sg:province":"TX",
    "wof:name":"Marsalis Mssnary Baptst Church",
    "wof:placetype":"venue"
},
  "geometry": {"coordinates":[-96.814644,32.713573],"type":"Point"}
}