{
  "type": "Feature",
  "properties": {
    "iso:country":"US",
    "sg:address":"2423 Harbinger Ln",
    "sg:city":"Dallas",
    "sg:classifiers":[
        {
            "category":"Personal",
            "type":"Services"
        }
    ],
    "sg:phone":"+1 972 679 3786",
    "sg:postcode":"75287",
    "sg:province":"TX",
    "wof:name":"Powered By Pilates & Yoga",
    "wof:placetype":"venue"
},
  "geometry": {"coordinates":[-96.871393,32.992277],"type":"Point"}
}