{
  "type": "Feature",
  "properties": {
    "iso:country":"US",
    "sg:address":"5724 Bryant Irvin Rd",
    "sg:city":"Fort Worth",
    "sg:classifiers":[
        {
            "category":"Restaurant",
            "type":"Food & Drink"
        }
    ],
    "sg:phone":"+1 817 416 9834",
    "sg:postcode":"76132",
    "sg:province":"TX",
    "sg:tags":[
        "eating"
    ],
    "wof:name":"Dickeys Barbecue Pit",
    "wof:placetype":"venue"
},
  "geometry": {"coordinates":[-97.42027400000001,32.666121],"type":"Point"}
}