{
  "type": "Feature",
  "properties": {
    "iso:country":"US",
    "sg:address":"128 Country Craft Rd",
    "sg:city":"Brookeland",
    "sg:classifiers":[
        {
            "category":"Organizations",
            "subcategory":"Community Association",
            "type":"Services"
        }
    ],
    "sg:phone":"+1 409 698 2323",
    "sg:postcode":"75904",
    "sg:province":"TX",
    "sg:tags":[
        "club"
    ],
    "wof:name":"Rayburn Country Club",
    "wof:placetype":"venue"
},
  "geometry": {"coordinates":[-94.75599699999999,31.373076],"type":"Point"}
}