{
  "type": "Feature",
  "properties": {
    "iso:country":"US",
    "sg:address":"3443 Briargrove Ln",
    "sg:city":"Dallas",
    "sg:classifiers":[
        {
            "category":"Social Services",
            "subcategory":"Child Care",
            "type":"Services"
        }
    ],
    "sg:phone":"+1 972 307 5021",
    "sg:postcode":"75287",
    "sg:province":"TX",
    "sg:tags":[
        "day"
    ],
    "wof:name":"After The Bell Academy",
    "wof:placetype":"venue"
},
  "geometry": {"coordinates":[-96.860641,32.991379],"type":"Point"}
}