{
  "type": "Feature",
  "properties": {
    "iso:country":"US",
    "sg:address":"1820 E Kearney St",
    "sg:city":"Laredo",
    "sg:classifiers":[
        {
            "category":"Shopping",
            "subcategory":"Clothing, Apparel, & Fashions",
            "type":"Retail Goods"
        }
    ],
    "sg:phone":"+1 956 206 3347",
    "sg:postcode":"78043",
    "sg:province":"TX",
    "wof:name":"Maria C Lule",
    "wof:placetype":"venue"
},
  "geometry": {"coordinates":[-99.477464,27.52143],"type":"Point"}
}