{
  "type": "Feature",
  "properties": {
    "iso:country":"US",
    "sg:address":"100 Champions Pl",
    "sg:city":"El Paso",
    "sg:classifiers":[
        {
            "category":"Education",
            "subcategory":"School",
            "type":"Public Place"
        }
    ],
    "sg:phone":"+1 915 834 2460",
    "sg:postcode":"79912",
    "sg:province":"TX",
    "wof:name":"Schools",
    "wof:placetype":"venue"
},
  "geometry": {"coordinates":[-106.54631500000001,31.835057],"type":"Point"}
}