{
  "type": "Feature",
  "properties": {
    "iso:country":"US",
    "sg:address":"2315 Rutland Dr",
    "sg:city":"Austin",
    "sg:classifiers":[
        {
            "category":"Wholesale",
            "subcategory":"Machinery & Supplies",
            "type":"Manufacturing & Wholesale Goods"
        }
    ],
    "sg:phone":"+1 512 610 4737",
    "sg:postcode":"78758",
    "sg:province":"TX",
    "sg:tags":[
        "equipment",
        "layer",
        "carpet"
    ],
    "wof:name":"Professional Flooring",
    "wof:placetype":"venue"
},
  "geometry": {"coordinates":[-97.720788,30.38224],"type":"Point"}
}