{
  "type": "Feature",
  "properties": {
    "iso:country":"US",
    "sg:address":"210 S Main St",
    "sg:city":"Donna",
    "sg:classifiers":[
        {
            "category":"Shopping",
            "subcategory":"Gifts & Souvenirs",
            "type":"Retail Goods"
        }
    ],
    "sg:phone":"+1 956 464 8321",
    "sg:postcode":"78537",
    "sg:province":"TX",
    "sg:tags":[
        "basket",
        "parcel"
    ],
    "sg:website":"www.rogersfarms.com",
    "wof:name":"Rogers Farms",
    "wof:placetype":"venue"
},
  "geometry": {"coordinates":[-98.054464,26.169152],"type":"Point"}
}