{
  "type": "Feature",
  "properties": {
    "iso:country":"US",
    "sg:address":"1116 Halsell Ave",
    "sg:city":"Bridgeport",
    "sg:classifiers":[
        {
            "category":"Real Estate",
            "subcategory":"Real Estate Agent",
            "type":"Services"
        }
    ],
    "sg:phone":"+1 940 683 1776",
    "sg:postcode":"76426",
    "sg:province":"TX",
    "wof:name":"Executive Suites",
    "wof:placetype":"venue"
},
  "geometry": {"coordinates":[-97.756669,33.210334],"type":"Point"}
}