{
  "type": "Feature",
  "properties": {
    "iso:country":"US",
    "sg:address":"1881 Grove Blvd Apt 627",
    "sg:city":"Austin",
    "sg:classifiers":[
        {
            "category":"Social Services",
            "type":"Services"
        },
        {
            "category":"Community Center",
            "type":"Public Place"
        }
    ],
    "sg:phone":"+1 512 701 0504",
    "sg:postcode":"78741",
    "sg:province":"TX",
    "sg:tags":[
        "recreation"
    ],
    "wof:name":"Flowing Water Community Center",
    "wof:placetype":"venue"
},
  "geometry": {"coordinates":[-97.706366,30.229505],"type":"Point"}
}