{
  "type": "Feature",
  "properties": {
    "iso:country":"US",
    "sg:address":"651 Hueco Springs Loop Rd",
    "sg:city":"New Braunfels",
    "sg:classifiers":[
        {
            "category":"Shopping",
            "subcategory":"Music",
            "type":"Retail Goods"
        }
    ],
    "sg:phone":"+1 830 643 0685",
    "sg:postcode":"78132",
    "sg:province":"TX",
    "wof:name":"Hastings Entertainment Inc",
    "wof:placetype":"venue"
},
  "geometry": {"coordinates":[-98.178714,29.742738],"type":"Point"}
}