{
  "type": "Feature",
  "properties": {
    "iso:country":"US",
    "sg:address":"1421 N Lee Trevino Dr",
    "sg:city":"El Paso",
    "sg:classifiers":[
        {
            "category":"Communications",
            "type":"Services"
        }
    ],
    "sg:phone":"+1 915 598 4300",
    "sg:postcode":"79936",
    "sg:province":"TX",
    "wof:name":"Fox Communications",
    "wof:placetype":"venue"
},
  "geometry": {"coordinates":[-106.320122,31.745436],"type":"Point"}
}