{
  "type": "Feature",
  "properties": {
    "iso:country":"US",
    "sg:address":"2523 E Park Row Dr",
    "sg:city":"Arlington",
    "sg:classifiers":[
        {
            "category":"Manufacturing",
            "subcategory":"Electronics",
            "type":"Manufacturing & Wholesale Goods"
        },
        {
            "category":"Shopping",
            "subcategory":"Music",
            "type":"Retail Goods"
        }
    ],
    "sg:phone":"+1 817 860 7444",
    "sg:postcode":"76010",
    "sg:province":"TX",
    "sg:tags":[
        "record"
    ],
    "wof:name":"Discote A Durango",
    "wof:placetype":"venue"
},
  "geometry": {"coordinates":[-97.063416,32.720828],"type":"Point"}
}