{
  "type": "Feature",
  "properties": {
    "iso:country":"US",
    "sg:address":"1350 S Hwy 67",
    "sg:city":"Cedar Hill",
    "sg:classifiers":[
        {
            "category":"Recreation",
            "type":"Entertainment"
        }
    ],
    "sg:phone":"+1 972 291 4242",
    "sg:postcode":"75104",
    "sg:province":"TX",
    "sg:tags":[
        "course",
        "golf"
    ],
    "sg:website":"www.ellensac.com",
    "wof:name":"Ellen's Amusement Ctr",
    "wof:placetype":"venue"
},
  "geometry": {"coordinates":[-96.97183,32.557197],"type":"Point"}
}