{
  "type": "Feature",
  "properties": {
    "iso:country":"US",
    "sg:address":"5018 Antoine Dr Ste A",
    "sg:city":"Houston",
    "sg:classifiers":[
        {
            "category":"Health Services",
            "subcategory":"Dentist",
            "type":"Services"
        }
    ],
    "sg:phone":"+1 713 263 8900",
    "sg:postcode":"77092",
    "sg:province":"TX",
    "wof:name":"Antione Dental Center",
    "wof:placetype":"venue"
},
  "geometry": {"coordinates":[-95.473,29.8374],"type":"Point"}
}