{
  "type": "Feature",
  "properties": {
    "iso:country":"US",
    "sg:address":"610 E Sealy Ave",
    "sg:city":"Monahans",
    "sg:classifiers":[
        {
            "category":"Retail",
            "subcategory":"Auto Rental",
            "type":"Services"
        }
    ],
    "sg:phone":"+1 432 943 6624",
    "sg:postcode":"79756",
    "sg:province":"TX",
    "sg:tags":[
        "renting",
        "truck",
        "leasing"
    ],
    "wof:name":"U-Haul Co",
    "wof:placetype":"venue"
},
  "geometry": {"coordinates":[-102.886672,31.596133],"type":"Point"}
}