{
  "type": "Feature",
  "properties": {
    "iso:country":"US",
    "sg:address":"542 Fm 473",
    "sg:city":"Comfort",
    "sg:classifiers":[
        {
            "category":"Insurance",
            "subcategory":"Hazard Insurance",
            "type":"Services"
        }
    ],
    "sg:phone":"+1 830 995 5504",
    "sg:postcode":"78013",
    "sg:province":"TX",
    "wof:name":"New Christianna & Kaid",
    "wof:placetype":"venue"
},
  "geometry": {"coordinates":[-98.819473,29.995834],"type":"Point"}
}