{
  "type": "Feature",
  "properties": {
    "iso:country":"US",
    "sg:address":"2213 23rd St",
    "sg:city":"Lubbock",
    "sg:classifiers":[
        {
            "category":"Retail",
            "subcategory":"Repair Shop",
            "type":"Services"
        }
    ],
    "sg:phone":"+1 806 763 3513",
    "sg:postcode":"79411",
    "sg:province":"TX",
    "wof:name":"Irenes Upholstery",
    "wof:placetype":"venue"
},
  "geometry": {"coordinates":[-101.864904,33.57382],"type":"Point"}
}