{
  "type": "Feature",
  "properties": {
    "iso:country":"US",
    "sg:address":"800 Nelda St",
    "sg:city":"Seguin",
    "sg:classifiers":[
        {
            "category":"Real Estate",
            "subcategory":"Real Estate Operator",
            "type":"Services"
        }
    ],
    "sg:phone":"+1 830 372 4313",
    "sg:postcode":"78155",
    "sg:province":"TX",
    "sg:tags":[
        "mobile",
        "home",
        "site",
        "community"
    ],
    "wof:name":"N C's Mobile Home Park",
    "wof:placetype":"venue"
},
  "geometry": {"coordinates":[-97.97510699999999,29.56089],"type":"Point"}
}