{
  "type": "Feature",
  "properties": {
    "iso:country":"US",
    "sg:address":"109 Shelbyville St",
    "sg:city":"Center",
    "sg:classifiers":[
        {
            "category":"Shopping",
            "subcategory":"Clothing, Apparel, & Fashions",
            "type":"Retail Goods"
        }
    ],
    "sg:phone":"+1 936 598 4535",
    "sg:postcode":"75935",
    "sg:province":"TX",
    "wof:name":"Factory Connection 74",
    "wof:placetype":"venue"
},
  "geometry": {"coordinates":[-94.181383,31.795866],"type":"Point"}
}