{
  "type": "Feature",
  "properties": {
    "iso:country":"US",
    "sg:address":"2343 McFaddin Ave",
    "sg:city":"Beaumont",
    "sg:classifiers":[
        {
            "category":"Health Services",
            "subcategory":"Doctor",
            "type":"Services"
        }
    ],
    "sg:phone":"+1 409 839 8900",
    "sg:postcode":"77702",
    "sg:province":"TX",
    "sg:tags":[
        "physician",
        "surgeon"
    ],
    "wof:name":"Michael S Findley MD",
    "wof:placetype":"venue"
},
  "geometry": {"coordinates":[-94.12177800000001,30.086698],"type":"Point"}
}