{
  "type": "Feature",
  "properties": {
    "iso:country":"US",
    "sg:address":"13237 Bellaire Blvd",
    "sg:city":"Houston",
    "sg:classifiers":[
        {
            "category":"Shopping",
            "subcategory":"Pharmacy",
            "type":"Retail Goods"
        }
    ],
    "sg:phone":"+1 281 530 7172",
    "sg:postcode":"77083",
    "sg:province":"TX",
    "wof:name":"Eckerd",
    "wof:placetype":"venue"
},
  "geometry": {"coordinates":[-95.615551,29.703449],"type":"Point"}
}