{
  "type": "Feature",
  "properties": {
    "iso:country":"US",
    "sg:address":"1001 E Southeast Loop 323 # 310",
    "sg:city":"Tyler",
    "sg:classifiers":[
        {
            "category":"Autos & Motor Vehicles",
            "subcategory":"Fuel & Gas Station",
            "type":"Retail Goods"
        },
        {
            "category":"Manufacturing",
            "subcategory":"Petroleum Products",
            "type":"Manufacturing & Wholesale Goods"
        }
    ],
    "sg:phone":"+1 903 581 5993",
    "sg:postcode":"75701",
    "sg:province":"TX",
    "sg:tags":[
        "oils-petroleum"
    ],
    "wof:name":"Brasfield Oil And Gas",
    "wof:placetype":"venue"
},
  "geometry": {"coordinates":[-95.267016,32.337358],"type":"Point"}
}