{
  "type": "Feature",
  "properties": {
    "iso:country":"US",
    "sg:address":"120 N Wheeler St",
    "sg:city":"Jasper",
    "sg:classifiers":[
        {
            "category":"Shopping",
            "subcategory":"Gifts & Souvenirs",
            "type":"Retail Goods"
        }
    ],
    "sg:phone":"+1 409 384 5175",
    "sg:postcode":"75951",
    "sg:province":"TX",
    "wof:name":"Craft Basket",
    "wof:placetype":"venue"
},
  "geometry": {"coordinates":[-93.996763,30.92162],"type":"Point"}
}