{
  "type": "Feature",
  "properties": {
    "iso:country":"US",
    "sg:address":"550 Genoa Red Bluff Rd",
    "sg:city":"Houston",
    "sg:classifiers":[
        {
            "category":"Sports & Exercise",
            "subcategory":"Playing Field",
            "type":"Entertainment"
        }
    ],
    "sg:phone":"+1 281 991 1417",
    "sg:postcode":"77034",
    "sg:province":"TX",
    "sg:tags":[
        "instruction",
        "fitness"
    ],
    "sg:website":"www.universitycheer.com",
    "wof:name":"University Cheer Air Force, Inc",
    "wof:placetype":"venue"
},
  "geometry": {"coordinates":[-95.190804,29.626801],"type":"Point"}
}