{
  "type": "Feature",
  "properties": {
    "iso:country":"US",
    "sg:address":"327 Rayford Rd",
    "sg:city":"Spring",
    "sg:classifiers":[
        {
            "category":"Insurance",
            "subcategory":"Insurance Agent",
            "type":"Services"
        }
    ],
    "sg:phone":"+1 281 681 3684",
    "sg:postcode":"77386",
    "sg:province":"TX",
    "wof:name":"Flanagan Insurance",
    "wof:placetype":"venue"
},
  "geometry": {"coordinates":[-95.439206,30.127076],"type":"Point"}
}