{
  "type": "Feature",
  "properties": {
    "iso:country":"US",
    "sg:address":"1330 W Main St",
    "sg:city":"Mabank",
    "sg:classifiers":[
        {
            "category":"Retail",
            "subcategory":"Laundry & Dry Cleaning",
            "type":"Services"
        }
    ],
    "sg:phone":"+1 903 887 1928",
    "sg:postcode":"75156",
    "sg:province":"TX",
    "wof:name":"Holiday Cleaners",
    "wof:placetype":"venue"
},
  "geometry": {"coordinates":[-96.136927,32.33084],"type":"Point"}
}