{
  "type": "Feature",
  "properties": {
    "iso:country":"US",
    "sg:address":"5381 Wagon Wheel Ave",
    "sg:city":"Abilene",
    "sg:classifiers":[
        {
            "category":"Wholesale",
            "subcategory":"Vending Machines",
            "type":"Manufacturing & Wholesale Goods"
        }
    ],
    "sg:phone":"+1 325 691 0183",
    "sg:postcode":"79606",
    "sg:province":"TX",
    "sg:tags":[
        "operator"
    ],
    "wof:name":"Sweet Tooth Vending",
    "wof:placetype":"venue"
},
  "geometry": {"coordinates":[-99.794387,32.358199],"type":"Point"}
}