{
  "type": "Feature",
  "properties": {
    "iso:country":"US",
    "sg:address":"1604 Bluebank Rd",
    "sg:city":"Dallas",
    "sg:classifiers":[
        {
            "category":"Professional",
            "subcategory":"Lawyer & Legal Services",
            "type":"Services"
        }
    ],
    "sg:phone":"+1 214 747 5200",
    "sg:postcode":"75229",
    "sg:province":"TX",
    "wof:name":"Spencer Herndon PC",
    "wof:placetype":"venue"
},
  "geometry": {"coordinates":[-96.918404,32.8923],"type":"Point"}
}