{
  "type": "Feature",
  "properties": {
    "iso:country":"US",
    "sg:address":"1502 Summertree Ct",
    "sg:city":"Richardson",
    "sg:classifiers":[
        {
            "category":"Professional",
            "subcategory":"Management & Consulting",
            "type":"Services"
        }
    ],
    "sg:phone":"+1 972 231 6721",
    "sg:postcode":"75082",
    "sg:province":"TX",
    "sg:tags":[
        "business"
    ],
    "wof:name":"Farrar Lighting Associates",
    "wof:placetype":"venue"
},
  "geometry": {"coordinates":[-96.694942,32.975324],"type":"Point"}
}