{
  "type": "Feature",
  "properties": {
    "iso:country":"US",
    "sg:address":"710 E Monroe Ave",
    "sg:city":"Harlingen",
    "sg:classifiers":[
        {
            "category":"Professional",
            "type":"Services"
        }
    ],
    "sg:phone":"+1 956 428 2593",
    "sg:postcode":"78550",
    "sg:province":"TX",
    "wof:name":"Vasquez Mechanic Service",
    "wof:placetype":"venue"
},
  "geometry": {"coordinates":[-97.68817,26.193745],"type":"Point"}
}