{
  "type": "Feature",
  "properties": {
    "iso:country":"US",
    "sg:address":"830 Pruitt Rd",
    "sg:city":"Spring",
    "sg:classifiers":[
        {
            "category":"Arena",
            "subcategory":"Sports Club",
            "type":"Entertainment"
        }
    ],
    "sg:phone":"+1 281 292 3765",
    "sg:postcode":"77380",
    "sg:province":"TX",
    "wof:name":"Oakridge Little League",
    "wof:placetype":"venue"
},
  "geometry": {"coordinates":[-95.44950300000001,30.116474],"type":"Point"}
}