{
  "type": "Feature",
  "properties": {
    "iso:country":"US",
    "sg:address":"2728 Palmer Hwy",
    "sg:city":"Texas City",
    "sg:classifiers":[
        {
            "category":"Shopping",
            "subcategory":"Used Merchandise",
            "type":"Retail Goods"
        }
    ],
    "sg:phone":"+1 409 943 4600",
    "sg:postcode":"77590",
    "sg:province":"TX",
    "wof:name":"Quik Pawn",
    "wof:placetype":"venue"
},
  "geometry": {"coordinates":[-94.936716,29.395356],"type":"Point"}
}