{
  "type": "Feature",
  "properties": {
    "iso:country":"US",
    "sg:address":"12626 W Bellfort Ave",
    "sg:city":"Houston",
    "sg:classifiers":[
        {
            "category":"Manufacturing",
            "subcategory":"Signs",
            "type":"Manufacturing & Wholesale Goods"
        }
    ],
    "sg:phone":"+1 281 568 4000",
    "sg:postcode":"77099",
    "sg:province":"TX",
    "sg:tags":[
        "building",
        "graphic",
        "mfg"
    ],
    "wof:name":"Intex United Inc",
    "wof:placetype":"venue"
},
  "geometry": {"coordinates":[-95.603993,29.661046],"type":"Point"}
}