{
  "type": "Feature",
  "properties": {
    "iso:country":"US",
    "sg:address":"300 S Phelps St",
    "sg:city":"Alpine",
    "sg:classifiers":[
        {
            "category":"Bars & Pubs",
            "type":"Food & Drink"
        }
    ],
    "sg:phone":"+1 432 837 5074",
    "sg:postcode":"79830",
    "sg:province":"TX",
    "sg:tags":[
        "drinking",
        "restaurant"
    ],
    "wof:name":"The Outback Bar & Grill",
    "wof:placetype":"venue"
},
  "geometry": {"coordinates":[-103.655022,30.35729],"type":"Point"}
}