{
  "type": "Feature",
  "properties": {
    "iso:country":"US",
    "sg:address":"5906 Cliff Ridge",
    "sg:city":"San Antonio",
    "sg:classifiers":[
        {
            "category":"Professional",
            "type":"Services"
        }
    ],
    "sg:phone":"+1 210 543 0776",
    "sg:postcode":"78250",
    "sg:province":"TX",
    "wof:name":"Cannco Construction",
    "wof:placetype":"venue"
},
  "geometry": {"coordinates":[-98.683976,29.49579],"type":"Point"}
}