{
  "type": "Feature",
  "properties": {
    "iso:country":"US",
    "sg:address":"13473 Wetmore Rd",
    "sg:city":"San Antonio",
    "sg:classifiers":[
        {
            "category":"Home & Garden",
            "subcategory":"Home Furnishings",
            "type":"Retail Goods"
        }
    ],
    "sg:phone":"+1 210 860 0688",
    "sg:postcode":"78247",
    "sg:province":"TX",
    "sg:tags":[
        "curtain",
        "made",
        "drapery"
    ],
    "wof:name":"Imaginations",
    "wof:placetype":"venue"
},
  "geometry": {"coordinates":[-98.42178199999999,29.561445],"type":"Point"}
}