{
  "type": "Feature",
  "properties": {
    "iso:country":"US",
    "sg:address":"4051 Beltway Dr",
    "sg:city":"Addison",
    "sg:classifiers":[
        {
            "category":"Real Estate",
            "subcategory":"Real Estate Agent",
            "type":"Services"
        }
    ],
    "sg:phone":"+1 972 960 6867",
    "sg:postcode":"75001",
    "sg:province":"TX",
    "sg:tags":[
        "management",
        "property"
    ],
    "sg:website":"www.walnutsquare.com",
    "wof:name":"Walnut Square",
    "wof:placetype":"venue"
},
  "geometry": {"coordinates":[-96.845259,32.951357],"type":"Point"}
}