{
  "type": "Feature",
  "properties": {
    "iso:country":"US",
    "sg:address":"1901 Lakeview Cir",
    "sg:city":"Lewisville",
    "sg:classifiers":[
        {
            "category":"Professional",
            "type":"Services"
        }
    ],
    "sg:phone":"+1 972 221 6422",
    "sg:postcode":"75057",
    "sg:province":"TX",
    "wof:name":"Bryans Conservation Services",
    "wof:placetype":"venue"
},
  "geometry": {"coordinates":[-97.00957,33.073808],"type":"Point"}
}