{
  "type": "Feature",
  "properties": {
    "iso:country":"US",
    "sg:address":"1250 Co Rd 456",
    "sg:city":"De Leon",
    "sg:classifiers":[
        {
            "category":"Retail",
            "subcategory":"Repair Shop",
            "type":"Services"
        }
    ],
    "sg:phone":"+1 254 893 6164",
    "sg:postcode":"76444",
    "sg:province":"TX",
    "sg:tags":[
        "welding"
    ],
    "wof:name":"Mh Welding LLC",
    "wof:placetype":"venue"
},
  "geometry": {"coordinates":[-98.51432200000001,32.160063],"type":"Point"}
}