{
  "type": "Feature",
  "properties": {
    "iso:country":"US",
    "sg:address":"844 US Hwy 281",
    "sg:city":"Brownsville",
    "sg:classifiers":[
        {
            "category":"Retail",
            "subcategory":"Car Wash",
            "type":"Services"
        }
    ],
    "sg:phone":"+1 956 541 1010",
    "sg:postcode":"78520",
    "sg:province":"TX",
    "sg:tags":[
        "polishing",
        "washing"
    ],
    "wof:name":"J J's Car Wash",
    "wof:placetype":"venue"
},
  "geometry": {"coordinates":[-97.510474,25.925707],"type":"Point"}
}