{
  "type": "Feature",
  "properties": {
    "iso:country":"US",
    "sg:address":"529 S Ivy Ave",
    "sg:city":"Crosbyton",
    "sg:classifiers":[
        {
            "category":"Manufacturing",
            "subcategory":"Apparel",
            "type":"Manufacturing & Wholesale Goods"
        }
    ],
    "sg:phone":"+1 806 675 1125",
    "sg:postcode":"79322",
    "sg:province":"TX",
    "wof:name":"Tee Pee Investments",
    "wof:placetype":"venue"
},
  "geometry": {"coordinates":[-101.247758,33.654072],"type":"Point"}
}