{
  "type": "Feature",
  "properties": {
    "iso:country":"US",
    "sg:address":"220 Molina St",
    "sg:city":"Mesquite",
    "sg:classifiers":[
        {
            "category":"Professional",
            "type":"Services"
        }
    ],
    "sg:phone":"+1 972 226 0251",
    "sg:postcode":"75182",
    "sg:province":"TX",
    "wof:name":"Touch of Country",
    "wof:placetype":"venue"
},
  "geometry": {"coordinates":[-96.580894,32.797228],"type":"Point"}
}