{
  "type": "Feature",
  "properties": {
    "iso:country":"US",
    "sg:address":"3308 Shorecrest Dr",
    "sg:city":"Dallas",
    "sg:classifiers":[
        {
            "category":"Building & Trades",
            "subcategory":"Construction",
            "type":"Services"
        }
    ],
    "sg:phone":"+1 214 350 8959",
    "sg:postcode":"75235",
    "sg:province":"TX",
    "sg:tags":[
        "contractor"
    ],
    "wof:name":"Concept Contractors Group",
    "wof:placetype":"venue"
},
  "geometry": {"coordinates":[-96.85973,32.855368],"type":"Point"}
}