{
  "type": "Feature",
  "properties": {
    "iso:country":"US",
    "sg:address":"2121 Marsh Ln",
    "sg:city":"Carrollton",
    "sg:classifiers":[
        {
            "category":"Wholesale",
            "subcategory":"Construction Materials",
            "type":"Manufacturing & Wholesale Goods"
        }
    ],
    "sg:phone":"+1 469 892 0274",
    "sg:postcode":"75006",
    "sg:province":"TX",
    "sg:tags":[
        "tile"
    ],
    "wof:name":"ADS Imports",
    "wof:placetype":"venue"
},
  "geometry": {"coordinates":[-96.853711,32.967436],"type":"Point"}
}