{
  "type": "Feature",
  "properties": {
    "iso:country":"US",
    "sg:address":"994 Sunshine Rd",
    "sg:city":"Brownsville",
    "sg:classifiers":[
        {
            "category":"Real Estate",
            "subcategory":"Architect",
            "type":"Services"
        }
    ],
    "sg:phone":"+1 956 542 4586",
    "sg:postcode":"78521",
    "sg:province":"TX",
    "sg:tags":[
        "architectural"
    ],
    "wof:name":"Growth Concepts Inc",
    "wof:placetype":"venue"
},
  "geometry": {"coordinates":[-97.49587200000001,25.948509],"type":"Point"}
}