{
  "type": "Feature",
  "properties": {
    "iso:country":"US",
    "sg:address":"1807 W 29th St",
    "sg:city":"Austin",
    "sg:classifiers":[
        {
            "category":"Professional",
            "type":"Services"
        }
    ],
    "sg:phone":"+1 512 495 6559",
    "sg:postcode":"78703",
    "sg:province":"TX",
    "sg:tags":[
        "establishment"
    ],
    "wof:name":"K P Partners",
    "wof:placetype":"venue"
},
  "geometry": {"coordinates":[-97.756428,30.30227],"type":"Point"}
}