{
  "type": "Feature",
  "properties": {
    "iso:country":"US",
    "sg:address":"205 E Fairlane Dr",
    "sg:city":"Longview",
    "sg:classifiers":[
        {
            "category":"Building & Trades",
            "subcategory":"Construction",
            "type":"Services"
        }
    ],
    "sg:phone":"+1 903 291 8262",
    "sg:postcode":"75604",
    "sg:province":"TX",
    "sg:tags":[
        "restoration",
        "cleaning",
        "patio",
        "deck"
    ],
    "wof:name":"Whitsett Pressure Washing Svc",
    "wof:placetype":"venue"
},
  "geometry": {"coordinates":[-94.80380100000001,32.534223],"type":"Point"}
}