{
  "type": "Feature",
  "properties": {
    "iso:country":"US",
    "sg:address":"12926 Taylor Ln",
    "sg:city":"Stafford",
    "sg:classifiers":[
        {
            "category":"Shopping",
            "type":"Retail Goods"
        }
    ],
    "sg:phone":"+1 281 208 0979",
    "sg:postcode":"77477",
    "sg:province":"TX",
    "sg:tags":[
        "merchandise"
    ],
    "wof:name":"Ftn Global Artist",
    "wof:placetype":"venue"
},
  "geometry": {"coordinates":[-95.542303,29.631583],"type":"Point"}
}