{
  "type": "Feature",
  "properties": {
    "iso:country":"US",
    "sg:address":"309 College Ave",
    "sg:city":"College Station",
    "sg:classifiers":[
        {
            "category":"Shopping",
            "subcategory":"Crafts & Fabrics",
            "type":"Retail Goods"
        }
    ],
    "sg:phone":"+1 979 846 1241",
    "sg:postcode":"77840",
    "sg:province":"TX",
    "sg:tags":[
        "shop",
        "store"
    ],
    "wof:name":"Hancock Fabrics 188",
    "wof:placetype":"venue"
},
  "geometry": {"coordinates":[-96.34195099999999,30.623731],"type":"Point"}
}