{
  "type": "Feature",
  "properties": {
    "iso:country":"US",
    "sg:address":"13809 N US Hwy 183",
    "sg:city":"Austin",
    "sg:classifiers":[
        {
            "category":"Banks & Credit Unions",
            "subcategory":"Investment Brokerage",
            "type":"Services"
        }
    ],
    "sg:phone":"+1 512 336 1754",
    "sg:postcode":"78750",
    "sg:province":"TX",
    "sg:tags":[
        "commodity"
    ],
    "wof:name":"RWA Financial Svc",
    "wof:placetype":"venue"
},
  "geometry": {"coordinates":[-97.794848,30.462612],"type":"Point"}
}