{
  "type": "Feature",
  "properties": {
    "iso:country":"US",
    "sg:address":"1713 City View Dr",
    "sg:city":"Wichita Falls",
    "sg:classifiers":[
        {
            "category":"Professional",
            "subcategory":"Business Services",
            "type":"Services"
        }
    ],
    "sg:phone":"+1 940 855 3491",
    "sg:postcode":"76306",
    "sg:province":"TX",
    "wof:name":"Supreme Enterprizes",
    "wof:placetype":"venue"
},
  "geometry": {"coordinates":[-98.553105,33.948432],"type":"Point"}
}