{
  "type": "Feature",
  "properties": {
    "iso:country":"US",
    "sg:address":"405 Zion Hill Rd",
    "sg:city":"Weatherford",
    "sg:classifiers":[
        {
            "category":"Insurance",
            "subcategory":"Insurance Agent",
            "type":"Services"
        }
    ],
    "sg:phone":"+1 817 596 4629",
    "sg:postcode":"76088",
    "sg:province":"TX",
    "wof:name":"Sam E Hindman",
    "wof:placetype":"venue"
},
  "geometry": {"coordinates":[-97.809185,32.787609],"type":"Point"}
}