{
  "type": "Feature",
  "properties": {
    "iso:country":"US",
    "sg:address":"414 S West St",
    "sg:city":"Arlington",
    "sg:classifiers":[
        {
            "category":"Place Of Worship",
            "subcategory":"Church",
            "type":"Public Place"
        },
        {
            "category":"Place Of Worship",
            "type":"Public Place"
        },
        {
            "category":"Organizations",
            "subcategory":"Religious Organization",
            "type":"Services"
        }
    ],
    "sg:phone":"+1 817 277 4195",
    "sg:postcode":"76010",
    "sg:province":"TX",
    "sg:tags":[
        "churches-baptist-general",
        "churches-baptist"
    ],
    "sg:website":"http://www.bifork.org",
    "wof:name":"Baptist Student Ministry",
    "wof:placetype":"venue"
},
  "geometry": {"coordinates":[-97.110992,32.732445],"type":"Point"}
}