{
  "type": "Feature",
  "properties": {
    "iso:country":"US",
    "sg:address":"7242 W Main St",
    "sg:city":"Frisco",
    "sg:classifiers":[
        {
            "category":"Structure",
            "subcategory":"Office Building",
            "type":"Public Place"
        }
    ],
    "sg:phone":"+1 972 335 9000",
    "sg:postcode":"75034",
    "sg:province":"TX",
    "sg:tags":[
        "park"
    ],
    "wof:name":"Kraft Properties",
    "wof:placetype":"venue"
},
  "geometry": {"coordinates":[-96.821499,33.150034],"type":"Point"}
}