{
  "type": "Feature",
  "properties": {
    "iso:country":"US",
    "sg:address":"4941 Lamonte Ln",
    "sg:city":"Houston",
    "sg:classifiers":[
        {
            "category":"Professional",
            "subcategory":"Art Services",
            "type":"Services"
        }
    ],
    "sg:phone":"+1 713 957 2211",
    "sg:postcode":"77092",
    "sg:province":"TX",
    "sg:tags":[
        "commercial",
        "design"
    ],
    "wof:name":"Sharon M Gillen",
    "wof:placetype":"venue"
},
  "geometry": {"coordinates":[-95.463652,29.823922],"type":"Point"}
}