{
  "type": "Feature",
  "properties": {
    "iso:country":"US",
    "sg:address":"203 N Bolton St",
    "sg:city":"Jacksonville",
    "sg:classifiers":[
        {
            "category":"Retail",
            "subcategory":"Auto Repair",
            "type":"Services"
        }
    ],
    "sg:phone":"+1 903 586 6442",
    "sg:postcode":"75766",
    "sg:province":"TX",
    "sg:tags":[
        "repairing",
        "automobile",
        "general"
    ],
    "wof:name":"Damon's Automotive",
    "wof:placetype":"venue"
},
  "geometry": {"coordinates":[-95.27551,31.965968],"type":"Point"}
}