{
  "type": "Feature",
  "properties": {
    "iso:country":"US",
    "sg:address":"2601 Augusta Dr",
    "sg:city":"Houston",
    "sg:classifiers":[
        {
            "category":"Professional",
            "subcategory":"Management & Consulting",
            "type":"Services"
        }
    ],
    "sg:phone":"+1 713 952 6800",
    "sg:postcode":"77057",
    "sg:province":"TX",
    "sg:tags":[
        "break",
        "coffee",
        "supply"
    ],
    "wof:name":"Classic Coffee Svc",
    "wof:placetype":"venue"
},
  "geometry": {"coordinates":[-95.48242399999999,29.73993],"type":"Point"}
}