{
  "type": "Feature",
  "properties": {
    "iso:country":"US",
    "sg:address":"17518 Baronshire Dr",
    "sg:city":"Houston",
    "sg:classifiers":[
        {
            "category":"Professional",
            "subcategory":"Business Services",
            "type":"Services"
        }
    ],
    "sg:phone":"+1 281 251 1621",
    "sg:postcode":"77070",
    "sg:province":"TX",
    "wof:name":"Sommer Group Inc",
    "wof:placetype":"venue"
},
  "geometry": {"coordinates":[-95.569292,30.019009],"type":"Point"}
}