{
  "type": "Feature",
  "properties": {
    "iso:country":"US",
    "sg:address":"1211 Antoine",
    "sg:city":"Houston",
    "sg:classifiers":[
        {
            "category":"Building & Trades",
            "subcategory":"Construction",
            "type":"Services"
        }
    ],
    "sg:phone":"+1 713 622 0990",
    "sg:postcode":"77055",
    "sg:province":"TX",
    "sg:tags":[
        "contractor"
    ],
    "sg:website":"www.mwdesigngroup.com",
    "wof:name":"MW Design Group, LLC",
    "wof:placetype":"venue"
},
  "geometry": {"coordinates":[-95.475999,29.791145],"type":"Point"}
}