{
  "type": "Feature",
  "properties": {
    "iso:country":"US",
    "sg:address":"8176 Kirby Dr",
    "sg:city":"Houston",
    "sg:classifiers":[
        {
            "category":"Shopping",
            "subcategory":"Discount & Variety Stores",
            "type":"Retail Goods"
        }
    ],
    "sg:phone":"+1 713 668 4167",
    "sg:postcode":"77054",
    "sg:province":"TX",
    "wof:name":"Dollar Mart",
    "wof:placetype":"venue"
},
  "geometry": {"coordinates":[-95.412778,29.691882],"type":"Point"}
}