{
  "type": "Feature",
  "properties": {
    "iso:country":"US",
    "sg:address":"4001 Guadalupe St",
    "sg:city":"Austin",
    "sg:classifiers":[
        {
            "category":"Retail",
            "subcategory":"Auto Repair",
            "type":"Services"
        }
    ],
    "sg:phone":"+1 512 454 0388",
    "sg:postcode":"78751",
    "sg:province":"TX",
    "sg:tags":[
        "muffler",
        "exhaust",
        "system"
    ],
    "wof:name":"Midas Auto Svc Experts",
    "wof:placetype":"venue"
},
  "geometry": {"coordinates":[-97.73579599999999,30.30639],"type":"Point"}
}