{
  "type": "Feature",
  "properties": {
    "iso:country":"US",
    "sg:address":"120 FM 64",
    "sg:city":"Cooper",
    "sg:classifiers":[
        {
            "category":"Organizations",
            "subcategory":"Religious Organization",
            "type":"Services"
        }
    ],
    "sg:phone":"+1 903 395 4278",
    "sg:postcode":"75432",
    "sg:province":"TX",
    "sg:tags":[
        "church"
    ],
    "wof:name":"Church Of Christ",
    "wof:placetype":"venue"
},
  "geometry": {"coordinates":[-95.699716,33.374317],"type":"Point"}
}