{
  "type": "Feature",
  "properties": {
    "iso:country":"US",
    "sg:address":"11835 Wilcrest Dr",
    "sg:city":"Houston",
    "sg:classifiers":[
        {
            "category":"Wholesale",
            "subcategory":"Durable Goods & Equipment",
            "type":"Manufacturing & Wholesale Goods"
        }
    ],
    "sg:phone":"+1 713 355 6800",
    "sg:postcode":"77031",
    "sg:province":"TX",
    "wof:name":"Sunshine Wholesale Inc",
    "wof:placetype":"venue"
},
  "geometry": {"coordinates":[-95.567887,29.651079],"type":"Point"}
}