{
  "type": "Feature",
  "properties": {
    "iso:country":"US",
    "sg:address":"1121 Tahoe Dr",
    "sg:city":"Garland",
    "sg:classifiers":[
        {
            "category":"Wholesale",
            "subcategory":"Plants",
            "type":"Manufacturing & Wholesale Goods"
        }
    ],
    "sg:phone":"+1 972 270 4482",
    "sg:postcode":"75043",
    "sg:province":"TX",
    "sg:tags":[
        "supply"
    ],
    "wof:name":"Puzzles & More",
    "wof:placetype":"venue"
},
  "geometry": {"coordinates":[-96.640717,32.854084],"type":"Point"}
}