{
  "type": "Feature",
  "properties": {
    "iso:country":"US",
    "sg:address":"3806 Maywood Dr",
    "sg:city":"Carrollton",
    "sg:classifiers":[
        {
            "category":"Professional",
            "type":"Services"
        }
    ],
    "sg:phone":"+1 972 306 4641",
    "sg:postcode":"75007",
    "sg:province":"TX",
    "wof:name":"Susan Pollard Gillespie",
    "wof:placetype":"venue"
},
  "geometry": {"coordinates":[-96.855304,33.015079],"type":"Point"}
}