{
  "type": "Feature",
  "properties": {
    "iso:country":"US",
    "sg:address":"618 E 6th St",
    "sg:city":"Austin",
    "sg:classifiers":[
        {
            "category":"Food & Beverages",
            "subcategory":"Specialty",
            "type":"Retail Goods"
        }
    ],
    "sg:phone":"+1 512 499 0766",
    "sg:postcode":"78701",
    "sg:province":"TX",
    "sg:website":"www.tearsofjoysauces.com",
    "wof:name":"Tears Of Joy Hot Sauce Shop",
    "wof:placetype":"venue"
},
  "geometry": {"coordinates":[-97.73629800000001,30.266557],"type":"Point"}
}