{
  "type": "Feature",
  "properties": {
    "iso:country":"US",
    "sg:address":"908 S Lamar St",
    "sg:city":"De Leon",
    "sg:classifiers":[
        {
            "category":"Real Estate",
            "subcategory":"Real Estate Operator",
            "type":"Services"
        }
    ],
    "sg:phone":"+1 254 893 6553",
    "sg:postcode":"76444",
    "sg:province":"TX",
    "sg:tags":[
        "property",
        "lessor"
    ],
    "wof:name":"R George Farm",
    "wof:placetype":"venue"
},
  "geometry": {"coordinates":[-98.53756199999999,32.100189],"type":"Point"}
}