{
  "type": "Feature",
  "properties": {
    "iso:country":"US",
    "sg:address":"2901 Peppertree Pl",
    "sg:city":"Plano",
    "sg:classifiers":[
        {
            "category":"Retail",
            "subcategory":"Auto Repair",
            "type":"Services"
        }
    ],
    "sg:phone":"+1 972 423 3739",
    "sg:postcode":"75074",
    "sg:province":"TX",
    "sg:tags":[
        "automobile",
        "used",
        "general"
    ],
    "wof:name":"Heller Auto Service",
    "wof:placetype":"venue"
},
  "geometry": {"coordinates":[-96.670845,33.033653],"type":"Point"}
}