{
  "type": "Feature",
  "properties": {
    "iso:country":"US",
    "sg:address":"1113 Eton Dr",
    "sg:city":"Richardson",
    "sg:classifiers":[
        {
            "category":"Organizations",
            "subcategory":"Non-profit Organization",
            "type":"Services"
        }
    ],
    "sg:phone":"+1 972 437 5999",
    "sg:postcode":"75080",
    "sg:province":"TX",
    "sg:tags":[
        "service/non-profit",
        "community"
    ],
    "sg:website":"www.juniorachievement.com",
    "wof:name":"Junior Achievement",
    "wof:placetype":"venue"
},
  "geometry": {"coordinates":[-96.757254,32.974216],"type":"Point"}
}