{
  "type": "Feature",
  "properties": {
    "iso:country":"US",
    "sg:address":"1407 Campbell St",
    "sg:city":"Sweetwater",
    "sg:classifiers":[
        {
            "category":"Professional",
            "type":"Services"
        }
    ],
    "sg:phone":"+1 325 235 2405",
    "sg:postcode":"79556",
    "sg:province":"TX",
    "sg:tags":[
        "churches-baptist"
    ],
    "wof:name":"Highland Baptist Church Parsonage",
    "wof:placetype":"venue"
},
  "geometry": {"coordinates":[-100.396635,32.456632],"type":"Point"}
}