{
  "type": "Feature",
  "properties": {
    "iso:country":"US",
    "sg:address":"1849 Lamar Ave",
    "sg:city":"Paris",
    "sg:classifiers":[
        {
            "category":"Fast Food",
            "type":"Food & Drink"
        },
        {
            "category":"Restaurant",
            "type":"Food & Drink"
        }
    ],
    "sg:phone":"+1 903 784 4071",
    "sg:postcode":"75460",
    "sg:province":"TX",
    "sg:tags":[
        "take"
    ],
    "wof:name":"Frank Homer",
    "wof:placetype":"venue"
},
  "geometry": {"coordinates":[-95.53685400000001,33.661251],"type":"Point"}
}