{
  "type": "Feature",
  "properties": {
    "iso:country":"US",
    "sg:address":"2601 Fort Worth Dr",
    "sg:city":"Denton",
    "sg:classifiers":[
        {
            "category":"Building & Trades",
            "subcategory":"Landscaping Services",
            "type":"Services"
        }
    ],
    "sg:phone":"+1 940 566 2458",
    "sg:postcode":"76205",
    "sg:province":"TX",
    "sg:tags":[
        "landscape",
        "contractor"
    ],
    "wof:name":"TLC Landscapes Co",
    "wof:placetype":"venue"
},
  "geometry": {"coordinates":[-97.139988,33.179246],"type":"Point"}
}