{
  "type": "Feature",
  "properties": {
    "iso:country":"US",
    "sg:address":"100 E 15th St",
    "sg:city":"Fort Worth",
    "sg:classifiers":[
        {
            "category":"Professional",
            "subcategory":"Engineering",
            "type":"Services"
        }
    ],
    "sg:phone":"+1 817 446 1800",
    "sg:postcode":"76102",
    "sg:province":"TX",
    "sg:tags":[
        "engineer"
    ],
    "sg:website":"www.lopezgarciagroup.com",
    "wof:name":"Lopez Garcia Group",
    "wof:placetype":"venue"
},
  "geometry": {"coordinates":[-97.32492499999999,32.748418],"type":"Point"}
}