{
  "type": "Feature",
  "properties": {
    "iso:country":"US",
    "sg:address":"2295 N Austin Ave",
    "sg:city":"Georgetown",
    "sg:classifiers":[
        {
            "category":"Education",
            "subcategory":"School",
            "type":"Public Place"
        }
    ],
    "sg:phone":"+1 512 943 5130",
    "sg:postcode":"78626",
    "sg:province":"TX",
    "wof:name":"GISD 9th Grade Campus",
    "wof:placetype":"venue"
},
  "geometry": {"coordinates":[-97.665177,30.669096],"type":"Point"}
}