{
  "type": "Feature",
  "properties": {
    "iso:country":"US",
    "sg:address":"8800 Miller Road 2",
    "sg:city":"Houston",
    "sg:classifiers":[
        {
            "category":"Personal",
            "type":"Services"
        }
    ],
    "sg:phone":"+1 281 456 0665",
    "sg:postcode":"77049",
    "sg:province":"TX",
    "sg:tags":[
        "assistant"
    ],
    "wof:name":"Tubular Solutions",
    "wof:placetype":"venue"
},
  "geometry": {"coordinates":[-95.143608,29.85211],"type":"Point"}
}