{
  "type": "Feature",
  "properties": {
    "iso:country":"US",
    "sg:address":"1031 E Ashley Rd",
    "sg:city":"San Antonio",
    "sg:classifiers":[
        {
            "category":"Autos & Motor Vehicles",
            "subcategory":"Automobile Sales",
            "type":"Retail Goods"
        }
    ],
    "sg:phone":"+1 210 670 3600",
    "sg:postcode":"78221",
    "sg:province":"TX",
    "sg:tags":[
        "car",
        "dealer"
    ],
    "wof:name":"South Texas Motor Sales",
    "wof:placetype":"venue"
},
  "geometry": {"coordinates":[-98.482006,29.334121],"type":"Point"}
}