{
  "type": "Feature",
  "properties": {
    "iso:country":"US",
    "sg:address":"204 E Bethany Dr",
    "sg:city":"Allen",
    "sg:classifiers":[
        {
            "category":"Communications",
            "subcategory":"Film & Video Production",
            "type":"Services"
        },
        {
            "category":"Building & Trades",
            "subcategory":"Locksmith",
            "type":"Services"
        },
        {
            "category":"Manufacturing",
            "subcategory":"Paper Products",
            "type":"Manufacturing & Wholesale Goods"
        }
    ],
    "sg:phone":"+1 214 383 7700",
    "sg:postcode":"75002",
    "sg:province":"TX",
    "sg:tags":[
        "equipment",
        "die",
        "cutting",
        "supply"
    ],
    "wof:name":"Graphic Converting Inc.",
    "wof:placetype":"venue"
},
  "geometry": {"coordinates":[-96.673328,33.090285],"type":"Point"}
}