{
  "type": "Feature",
  "properties": {
    "iso:country":"US",
    "sg:address":"510 State Hwy 304",
    "sg:city":"Bastrop",
    "sg:classifiers":[
        {
            "category":"Professional",
            "subcategory":"Research",
            "type":"Services"
        }
    ],
    "sg:phone":"+1 512 321 2725",
    "sg:postcode":"78602",
    "sg:province":"TX",
    "sg:tags":[
        "nonphysical",
        "commercial"
    ],
    "wof:name":"Market Strategies Intl",
    "wof:placetype":"venue"
},
  "geometry": {"coordinates":[-97.360657,30.08486],"type":"Point"}
}