{
  "type": "Feature",
  "properties": {
    "iso:country":"US",
    "sg:address":"622 W Theo Ave",
    "sg:city":"San Antonio",
    "sg:classifiers":[
        {
            "category":"Professional",
            "subcategory":"Business Services",
            "type":"Services"
        }
    ],
    "sg:phone":"+1 210 533 0036",
    "sg:postcode":"78225",
    "sg:province":"TX",
    "sg:tags":[
        "recording",
        "studio"
    ],
    "wof:name":"Lay Down Studio",
    "wof:placetype":"venue"
},
  "geometry": {"coordinates":[-98.51240199999999,29.387914],"type":"Point"}
}