{
  "type": "Feature",
  "properties": {
    "iso:country":"US",
    "sg:address":"3123 S Braeswood Blvd",
    "sg:city":"Houston",
    "sg:classifiers":[
        {
            "category":"Professional",
            "subcategory":"Business Services",
            "type":"Services"
        }
    ],
    "sg:phone":"+1 281 660 2203",
    "sg:postcode":"77025",
    "sg:province":"TX",
    "sg:tags":[
        "cards",
        "providing",
        "payroll",
        "debit"
    ],
    "wof:name":"Global Card Systems",
    "wof:placetype":"venue"
},
  "geometry": {"coordinates":[-95.422816,29.695965],"type":"Point"}
}