{
  "type": "Feature",
  "properties": {
    "iso:country":"US",
    "sg:address":"3903 Majestic Trl",
    "sg:city":"Houston",
    "sg:classifiers":[
        {
            "category":"Professional",
            "subcategory":"Business Services",
            "type":"Services"
        }
    ],
    "sg:phone":"+1 281 286 7870",
    "sg:postcode":"77059",
    "sg:province":"TX",
    "wof:name":"Jjacdmb Partners Ltd",
    "wof:placetype":"venue"
},
  "geometry": {"coordinates":[-95.12670199999999,29.602815],"type":"Point"}
}