{
  "type": "Feature",
  "properties": {
    "iso:country":"US",
    "sg:address":"2735 Spring Colony Dr",
    "sg:city":"Spring",
    "sg:classifiers":[
        {
            "category":"Communications",
            "subcategory":"Film & Video Production",
            "type":"Services"
        }
    ],
    "sg:phone":"+1 281 528 0960",
    "sg:postcode":"77386",
    "sg:province":"TX",
    "sg:tags":[
        "motion"
    ],
    "wof:name":"Harrington Productions",
    "wof:placetype":"venue"
},
  "geometry": {"coordinates":[-95.39359899999999,30.11347],"type":"Point"}
}