{
  "type": "Feature",
  "properties": {
    "iso:country":"US",
    "sg:address":"115 W 2nd St",
    "sg:city":"Fort Worth",
    "sg:classifiers":[
        {
            "category":"Professional",
            "subcategory":"Lawyer & Legal Services",
            "type":"Services"
        }
    ],
    "sg:phone":"+1 817 332 3822",
    "sg:postcode":"76102",
    "sg:province":"TX",
    "sg:tags":[
        "attorney"
    ],
    "wof:name":"Evans Gandy Daniel & Moore",
    "wof:placetype":"venue"
},
  "geometry": {"coordinates":[-97.332652,32.755379],"type":"Point"}
}