{
  "type": "Feature",
  "properties": {
    "iso:country":"US",
    "sg:address":"2800 Hulen St",
    "sg:city":"Fort Worth",
    "sg:classifiers":[
        {
            "category":"Banks & Credit Unions",
            "subcategory":"Bank",
            "type":"Services"
        }
    ],
    "sg:phone":"+1 817 738 8358",
    "sg:postcode":"76107",
    "sg:province":"TX",
    "sg:tags":[
        "federal",
        "savings",
        "institution"
    ],
    "wof:name":"Washington Mutual Bank",
    "wof:placetype":"venue"
},
  "geometry": {"coordinates":[-97.38784800000001,32.72909],"type":"Point"}
}