{
  "type": "Feature",
  "properties": {
    "iso:country":"US",
    "sg:address":"700 International Pkwy",
    "sg:city":"Richardson",
    "sg:classifiers":[
        {
            "category":"Building & Trades",
            "subcategory":"Pest Control",
            "type":"Services"
        }
    ],
    "sg:phone":"+1 972 831 9999",
    "sg:postcode":"75081",
    "sg:province":"TX",
    "wof:name":"Home Team Pest Defense",
    "wof:placetype":"venue"
},
  "geometry": {"coordinates":[-96.70828,32.95845],"type":"Point"}
}