{
  "type": "Feature",
  "properties": {
    "iso:country":"US",
    "sg:address":"1305 S Key Ave",
    "sg:city":"Lampasas",
    "sg:classifiers":[
        {
            "category":"Professional",
            "type":"Services"
        }
    ],
    "sg:phone":"+1 512 556 9733",
    "sg:postcode":"76550",
    "sg:province":"TX",
    "sg:tags":[
        "establishment"
    ],
    "wof:name":"T J Interest",
    "wof:placetype":"venue"
},
  "geometry": {"coordinates":[-98.17917,31.057114],"type":"Point"}
}