{
  "type": "Feature",
  "properties": {
    "iso:country":"US",
    "sg:address":"16144 Market St",
    "sg:city":"Channelview",
    "sg:classifiers":[
        {
            "category":"Wholesale",
            "subcategory":"Machinery & Supplies",
            "type":"Manufacturing & Wholesale Goods"
        },
        {
            "category":"Retail",
            "subcategory":"Repair Shop",
            "type":"Services"
        },
        {
            "category":"Retail",
            "subcategory":"Auto Repair",
            "type":"Services"
        }
    ],
    "sg:phone":"+1 281 457 1262",
    "sg:postcode":"77530",
    "sg:province":"TX",
    "sg:tags":[
        "used",
        "machinery-new",
        "specially",
        "automobile",
        "machine",
        "designed"
    ],
    "wof:name":"Independent Equipment & Supply Co",
    "wof:placetype":"venue"
},
  "geometry": {"coordinates":[-95.115161,29.776247],"type":"Point"}
}