{
  "type": "Feature",
  "properties": {
    "iso:country":"US",
    "sg:address":"806 Shadycreek Ln",
    "sg:city":"Bedford",
    "sg:classifiers":[
        {
            "category":"Professional",
            "subcategory":"Computer Services",
            "type":"Services"
        }
    ],
    "sg:phone":"+1 817 685 2999",
    "sg:postcode":"76021",
    "sg:province":"TX",
    "wof:name":"J6 Enterprises",
    "wof:placetype":"venue"
},
  "geometry": {"coordinates":[-97.153256,32.853051],"type":"Point"}
}