{
  "type": "Feature",
  "properties": {
    "iso:country":"US",
    "sg:address":"201 N Crescent Dr",
    "sg:city":"Victoria",
    "sg:classifiers":[
        {
            "category":"Organizations",
            "subcategory":"Non-profit Organization",
            "type":"Services"
        }
    ],
    "sg:phone":"+1 361 572 3007",
    "sg:postcode":"77901",
    "sg:province":"TX",
    "sg:tags":[
        "information",
        "alcoholism",
        "treatment"
    ],
    "wof:name":"Alcohol & Drug Treatment Assoc",
    "wof:placetype":"venue"
},
  "geometry": {"coordinates":[-96.98633,28.834678],"type":"Point"}
}