{
  "type": "Feature",
  "properties": {
    "iso:country":"US",
    "sg:address":"1850 NE Loop 820",
    "sg:city":"Fort Worth",
    "sg:classifiers":[
        {
            "category":"Home & Garden",
            "subcategory":"Mobile Homes",
            "type":"Retail Goods"
        }
    ],
    "sg:phone":"+1 817 624 6423",
    "sg:postcode":"76106",
    "sg:province":"TX",
    "wof:name":"Great American Homes",
    "wof:placetype":"venue"
},
  "geometry": {"coordinates":[-97.32620799999999,32.83869],"type":"Point"}
}