{
  "type": "Feature",
  "properties": {
    "iso:country":"US",
    "sg:address":"7821 Fm 1960 Rd E",
    "sg:city":"Humble",
    "sg:classifiers":[
        {
            "category":"Insurance",
            "subcategory":"Title Insurance",
            "type":"Services"
        }
    ],
    "sg:phone":"+1 281 852 1650",
    "sg:postcode":"77346",
    "sg:province":"TX",
    "sg:website":"http://www.commonwealthca.com",
    "wof:name":"Landamerica Commonwealth Land Title Of Houston",
    "wof:placetype":"venue"
},
  "geometry": {"coordinates":[-95.15752500000001,30.000692],"type":"Point"}
}