{
  "type": "Feature",
  "properties": {
    "iso:country":"US",
    "sg:address":"3206 Winthrop Ave",
    "sg:city":"Fort Worth",
    "sg:classifiers":[
        {
            "category":"Restaurant",
            "type":"Food & Drink"
        }
    ],
    "sg:phone":"+1 817 731 0711",
    "sg:postcode":"76116",
    "sg:province":"TX",
    "sg:tags":[
        "drinking",
        "eating"
    ],
    "wof:name":"Aventino's Ristorante",
    "wof:placetype":"venue"
},
  "geometry": {"coordinates":[-97.41521400000001,32.728976],"type":"Point"}
}