{
  "type": "Feature",
  "properties": {
    "iso:country":"US",
    "sg:address":"6033 Berkshire Ln",
    "sg:city":"Dallas",
    "sg:classifiers":[
        {
            "category":"Banks & Credit Unions",
            "subcategory":"Bank",
            "type":"Services"
        }
    ],
    "sg:phone":"+1 214 696 4646",
    "sg:postcode":"75225",
    "sg:province":"TX",
    "sg:tags":[
        "loan",
        "real estate"
    ],
    "wof:name":"Southwestern Commercial Mtg",
    "wof:placetype":"venue"
},
  "geometry": {"coordinates":[-96.80666100000001,32.864944],"type":"Point"}
}