{
  "type": "Feature",
  "properties": {
    "iso:country":"US",
    "sg:address":"2425 Salmon St",
    "sg:city":"Irving",
    "sg:classifiers":[
        {
            "category":"Professional",
            "subcategory":"Business Services",
            "type":"Services"
        },
        {
            "category":"Insurance",
            "subcategory":"Insurance Agent",
            "type":"Services"
        }
    ],
    "sg:phone":"+1 972 255 6538",
    "sg:postcode":"75062",
    "sg:province":"TX",
    "wof:name":"N C Agency",
    "wof:placetype":"venue"
},
  "geometry": {"coordinates":[-97.00890099999999,32.841382],"type":"Point"}
}