{
  "type": "Feature",
  "properties": {
    "iso:country":"US",
    "sg:address":"4500 N Chadbourne St",
    "sg:city":"San Angelo",
    "sg:classifiers":[
        {
            "category":"Mining & Drilling",
            "type":"Manufacturing & Wholesale Goods"
        }
    ],
    "sg:phone":"+1 325 651 4785",
    "sg:postcode":"76903",
    "sg:province":"TX",
    "sg:tags":[
        "well"
    ],
    "wof:name":"Paterson Energy Shop",
    "wof:placetype":"venue"
},
  "geometry": {"coordinates":[-100.46639399999999,31.507111],"type":"Point"}
}