{
  "type": "Feature",
  "properties": {
    "iso:country":"US",
    "sg:address":"106 Conveyor Dr",
    "sg:city":"Joshua",
    "sg:classifiers":[
        {
            "category":"Food & Beverages",
            "subcategory":"Supermarket",
            "type":"Retail Goods"
        },
        {
            "category":"Food & Beverages",
            "subcategory":"Groceries & Convenience Stores",
            "type":"Retail Goods"
        }
    ],
    "sg:phone":"+1 817 558 4422",
    "sg:postcode":"76058",
    "sg:province":"TX",
    "sg:tags":[
        "super"
    ],
    "sg:website":"http://www.brookshires.com",
    "wof:name":"Brookshire's",
    "wof:placetype":"venue"
},
  "geometry": {"coordinates":[-97.38838800000001,32.461517],"type":"Point"}
}