{
  "type": "Feature",
  "properties": {
    "iso:country":"US",
    "sg:address":"10027 Hufsmith Rd",
    "sg:city":"Tomball",
    "sg:classifiers":[
        {
            "category":"Real Estate",
            "subcategory":"Real Estate Agent",
            "type":"Services"
        }
    ],
    "sg:phone":"+1 281 516 3357",
    "sg:postcode":"77375",
    "sg:province":"TX",
    "wof:name":"Stonebridge Ranch Estate Sales",
    "wof:placetype":"venue"
},
  "geometry": {"coordinates":[-95.57444099999999,30.126519],"type":"Point"}
}