{
  "type": "Feature",
  "properties": {
    "iso:country":"US",
    "sg:address":"6615 Stewart Rd",
    "sg:city":"Galveston",
    "sg:classifiers":[
        {
            "category":"Professional",
            "subcategory":"Advertising",
            "type":"Services"
        }
    ],
    "sg:phone":"+1 409 741 5107",
    "sg:postcode":"77551",
    "sg:province":"TX",
    "wof:name":"Marketing Specialties",
    "wof:placetype":"venue"
},
  "geometry": {"coordinates":[-94.836765,29.273105],"type":"Point"}
}