{
  "type": "Feature",
  "properties": {
    "iso:country":"US",
    "sg:address":"10217 Harry Hines Blvd",
    "sg:city":"Dallas",
    "sg:classifiers":[
        {
            "category":"Manufacturing",
            "subcategory":"Chemicals & Compounds",
            "type":"Manufacturing & Wholesale Goods"
        }
    ],
    "sg:phone":"+1 469 335 9975",
    "sg:postcode":"75220",
    "sg:province":"TX",
    "sg:tags":[
        "preparation",
        "toilet",
        "mfg"
    ],
    "wof:name":"Dawn Enterprises",
    "wof:placetype":"venue"
},
  "geometry": {"coordinates":[-96.880982,32.862996],"type":"Point"}
}