{
  "type": "Feature",
  "properties": {
    "iso:country":"US",
    "sg:address":"310 Robin St",
    "sg:city":"Throckmorton",
    "sg:classifiers":[
        {
            "category":"Building & Trades",
            "subcategory":"Construction",
            "type":"Services"
        }
    ],
    "sg:phone":"+1 940 849 2401",
    "sg:postcode":"76483",
    "sg:province":"TX",
    "sg:tags":[
        "contractor"
    ],
    "wof:name":"Mosaics Etc",
    "wof:placetype":"venue"
},
  "geometry": {"coordinates":[-99.182712,33.184868],"type":"Point"}
}