{
  "type": "Feature",
  "properties": {
    "iso:country":"US",
    "sg:address":"6 Timberline Dr",
    "sg:city":"Round Rock",
    "sg:classifiers":[
        {
            "category":"Professional",
            "subcategory":"Business Services",
            "type":"Services"
        }
    ],
    "sg:phone":"+1 512 388 2467",
    "sg:postcode":"78665",
    "sg:province":"TX",
    "wof:name":"Austin Drafting USA",
    "wof:placetype":"venue"
},
  "geometry": {"coordinates":[-97.65228999999999,30.527043],"type":"Point"}
}