{
  "type": "Feature",
  "properties": {
    "iso:country":"US",
    "sg:address":"5190 Hidalgo St",
    "sg:city":"Houston",
    "sg:classifiers":[
        {
            "category":"Travel",
            "subcategory":"Hotels & Motels",
            "type":"Entertainment"
        },
        {
            "category":"Retail",
            "subcategory":"Event Space",
            "type":"Services"
        }
    ],
    "sg:phone":"+1 713 355 8888",
    "sg:postcode":"77056",
    "sg:province":"TX",
    "sg:tags":[
        "facility",
        "venue",
        "hall",
        "reception",
        "lodging",
        "corporate",
        "banquet"
    ],
    "sg:website":"www.staybridge.com",
    "wof:name":"Staybridge Suites Extended Stay Hotel Houston Galleria Area",
    "wof:placetype":"venue"
},
  "geometry": {"coordinates":[-95.466121,29.735431],"type":"Point"}
}