{
  "type": "Feature",
  "properties": {
    "iso:country":"US",
    "sg:address":"2108 Rose Bluff Ter",
    "sg:city":"Flower Mound",
    "sg:classifiers":[
        {
            "category":"Manufacturing",
            "subcategory":"Printing",
            "type":"Manufacturing & Wholesale Goods"
        }
    ],
    "sg:phone":"+1 972 355 5801",
    "sg:postcode":"75028",
    "sg:province":"TX",
    "sg:tags":[
        "publishing"
    ],
    "wof:name":"Creative News Inc",
    "wof:placetype":"venue"
},
  "geometry": {"coordinates":[-97.060304,33.026462],"type":"Point"}
}