{
  "type": "Feature",
  "properties": {
    "iso:country":"US",
    "sg:address":"813 W Moore Ave",
    "sg:city":"Terrell",
    "sg:classifiers":[
        {
            "category":"Restaurant",
            "type":"Food & Drink"
        }
    ],
    "sg:phone":"+1 972 551 0313",
    "sg:postcode":"75160",
    "sg:province":"TX",
    "sg:tags":[
        "eating"
    ],
    "wof:name":"Greek Sub Corner Inc",
    "wof:placetype":"venue"
},
  "geometry": {"coordinates":[-96.2884,32.737672],"type":"Point"}
}