{
  "type": "Feature",
  "properties": {
    "iso:country":"US",
    "sg:address":"2808 Fairmount St Ste 250",
    "sg:city":"Dallas",
    "sg:classifiers":[
        {
            "category":"Real Estate",
            "subcategory":"Real Estate Services",
            "type":"Services"
        }
    ],
    "sg:phone":"+1 214 303 1653",
    "sg:postcode":"75201",
    "sg:province":"TX",
    "sg:tags":[
        "consultant"
    ],
    "sg:website":"http://www.afglimited.com",
    "wof:name":"Atlantic Financial Group, Ltd.",
    "wof:placetype":"venue"
},
  "geometry": {"coordinates":[-96.804773,32.797294],"type":"Point"}
}