{
  "type": "Feature",
  "properties": {
    "iso:country":"US",
    "sg:address":"18714 Brookwood Forest",
    "sg:city":"San Antonio",
    "sg:classifiers":[
        {
            "category":"Building & Trades",
            "subcategory":"Construction",
            "type":"Services"
        }
    ],
    "sg:phone":"+1 210 492 1321",
    "sg:postcode":"78258",
    "sg:province":"TX",
    "sg:tags":[
        "house"
    ],
    "wof:name":"Austin Gutterman",
    "wof:placetype":"venue"
},
  "geometry": {"coordinates":[-98.516834,29.612796],"type":"Point"}
}