{
  "type": "Feature",
  "properties": {
    "iso:country":"US",
    "sg:address":"2828 Franklin Ave",
    "sg:city":"Waco",
    "sg:classifiers":[
        {
            "category":"Autos & Motor Vehicles",
            "subcategory":"Automobile Sales",
            "type":"Retail Goods"
        }
    ],
    "sg:phone":"+1 254 759 2828",
    "sg:postcode":"76710",
    "sg:province":"TX",
    "sg:tags":[
        "car",
        "dealer"
    ],
    "wof:name":"Williams Brothers Autos",
    "wof:placetype":"venue"
},
  "geometry": {"coordinates":[-97.152693,31.536641],"type":"Point"}
}