{
  "type": "Feature",
  "properties": {
    "iso:country":"US",
    "sg:address":"506 Woodhill Ct",
    "sg:city":"Grapevine",
    "sg:classifiers":[
        {
            "category":"Professional",
            "subcategory":"Management & Consulting",
            "type":"Services"
        }
    ],
    "sg:phone":"+1 817 329 5261",
    "sg:postcode":"76051",
    "sg:province":"TX",
    "sg:tags":[
        "business"
    ],
    "wof:name":"Paul McNeill",
    "wof:placetype":"venue"
},
  "geometry": {"coordinates":[-97.082607,32.88647],"type":"Point"}
}