{
  "type": "Feature",
  "properties": {
    "iso:country":"US",
    "sg:address":"10920 Elam Rd",
    "sg:city":"Mesquite",
    "sg:classifiers":[
        {
            "category":"Organizations",
            "subcategory":"Religious Organization",
            "type":"Services"
        }
    ],
    "sg:phone":"+1 972 286 6902",
    "sg:postcode":"75180",
    "sg:province":"TX",
    "sg:tags":[
        "church"
    ],
    "wof:name":"Frontier Revival Center",
    "wof:placetype":"venue"
},
  "geometry": {"coordinates":[-96.63921000000001,32.719512],"type":"Point"}
}