{
  "type": "Feature",
  "properties": {
    "iso:country":"US",
    "sg:address":"726 Stoneway Dr",
    "sg:city":"San Antonio",
    "sg:classifiers":[
        {
            "category":"Building & Trades",
            "subcategory":"Landscaping Services",
            "type":"Services"
        }
    ],
    "sg:phone":"+1 210 365 5022",
    "sg:postcode":"78258",
    "sg:province":"TX",
    "sg:tags":[
        "landscape",
        "contractor"
    ],
    "wof:name":"Amistad Landscaping",
    "wof:placetype":"venue"
},
  "geometry": {"coordinates":[-98.498627,29.644441],"type":"Point"}
}