{
  "type": "Feature",
  "properties": {
    "iso:country":"US",
    "sg:address":"920 Harper Rd",
    "sg:city":"Kerrville",
    "sg:classifiers":[
        {
            "category":"Food & Beverages",
            "subcategory":"Groceries & Convenience Stores",
            "type":"Retail Goods"
        }
    ],
    "sg:phone":"+1 830 895 2141",
    "sg:postcode":"78028",
    "sg:province":"TX",
    "wof:name":"Kerr Villa Kountry Store",
    "wof:placetype":"venue"
},
  "geometry": {"coordinates":[-99.15276299999999,30.087167],"type":"Point"}
}