{
  "type": "Feature",
  "properties": {
    "iso:country":"US",
    "sg:address":"12414 Cobblestone Dr",
    "sg:city":"Houston",
    "sg:classifiers":[
        {
            "category":"Professional",
            "subcategory":"Management & Consulting",
            "type":"Services"
        }
    ],
    "sg:phone":"+1 713 647 9600",
    "sg:postcode":"77024",
    "sg:province":"TX",
    "wof:name":"CAM Interests Inc",
    "wof:placetype":"venue"
},
  "geometry": {"coordinates":[-95.548502,29.771999],"type":"Point"}
}