{
  "type": "Feature",
  "properties": {
    "iso:country":"US",
    "sg:address":"1020 S 3rd St",
    "sg:city":"Mabank",
    "sg:classifiers":[
        {
            "category":"Personal",
            "subcategory":"Beauty Salon",
            "type":"Services"
        }
    ],
    "sg:phone":"+1 903 887 8202",
    "sg:postcode":"75147",
    "sg:province":"TX",
    "sg:tags":[
        "shop"
    ],
    "wof:name":"Universal Cuts/Hair Dsgn",
    "wof:placetype":"venue"
},
  "geometry": {"coordinates":[-96.10424500000001,32.356246],"type":"Point"}
}