{
  "type": "Feature",
  "properties": {
    "iso:country":"US",
    "sg:address":"5601 Fishtrap Rd",
    "sg:city":"Crossroads",
    "sg:classifiers":[
        {
            "category":"Farming",
            "subcategory":"Livestock Farm",
            "type":"Manufacturing & Wholesale Goods"
        },
        {
            "category":"Farming",
            "subcategory":"Farm",
            "type":"Manufacturing & Wholesale Goods"
        }
    ],
    "sg:phone":"+1 940 365 2081",
    "sg:postcode":"76227",
    "sg:province":"TX",
    "sg:tags":[
        "horse"
    ],
    "wof:name":"Top Step Farms",
    "wof:placetype":"venue"
},
  "geometry": {"coordinates":[-96.99759299999999,33.235051],"type":"Point"}
}