{
  "type": "Feature",
  "properties": {
    "iso:country":"US",
    "sg:address":"2137B W Anderson Ln",
    "sg:city":"Austin",
    "sg:classifiers":[
        {
            "category":"Banks & Credit Unions",
            "subcategory":"Investment Brokerage",
            "type":"Services"
        }
    ],
    "sg:phone":"+1 512 467 0007",
    "sg:postcode":"78757",
    "sg:province":"TX",
    "sg:tags":[
        "security"
    ],
    "sg:website":"http://www.edwardjones.com",
    "wof:name":"Edward Jones 01393",
    "wof:placetype":"venue"
},
  "geometry": {"coordinates":[-97.72874899999999,30.355105],"type":"Point"}
}