{
  "type": "Feature",
  "properties": {
    "iso:country":"US",
    "sg:address":"770 Sudduth Dr",
    "sg:city":"Bridge City",
    "sg:classifiers":[
        {
            "category":"Organizations",
            "subcategory":"Labor Organization",
            "type":"Services"
        }
    ],
    "sg:phone":"+1 409 735 3097",
    "sg:postcode":"77611",
    "sg:province":"TX",
    "wof:name":"Groves Municipal Employees Un",
    "wof:placetype":"venue"
},
  "geometry": {"coordinates":[-93.853505,30.025212],"type":"Point"}
}