{
  "type": "Feature",
  "properties": {
    "iso:country":"US",
    "sg:address":"19021 Midway Rd",
    "sg:city":"Dallas",
    "sg:classifiers":[
        {
            "category":"Retail",
            "subcategory":"Laundry & Dry Cleaning",
            "type":"Services"
        }
    ],
    "sg:phone":"+1 972 307 0139",
    "sg:postcode":"75287",
    "sg:province":"TX",
    "sg:tags":[
        "cleaners"
    ],
    "wof:name":"Polo Press",
    "wof:placetype":"venue"
},
  "geometry": {"coordinates":[-96.843744,32.990288],"type":"Point"}
}