{
  "type": "Feature",
  "properties": {
    "iso:country":"US",
    "sg:address":"305 Hickory Dr",
    "sg:city":"Elgin",
    "sg:classifiers":[
        {
            "category":"Building & Trades",
            "subcategory":"Landscaping Services",
            "type":"Services"
        }
    ],
    "sg:phone":"+1 512 281 2161",
    "sg:postcode":"78621",
    "sg:province":"TX",
    "sg:tags":[
        "landscape",
        "contractor"
    ],
    "wof:name":"Nalle Landscape Company",
    "wof:placetype":"venue"
},
  "geometry": {"coordinates":[-97.34625200000001,30.278155],"type":"Point"}
}