{
  "type": "Feature",
  "properties": {
    "iso:country":"US",
    "sg:address":"436 Murdock Rd",
    "sg:city":"Dallas",
    "sg:classifiers":[
        {
            "category":"Food & Beverages",
            "subcategory":"Groceries & Convenience Stores",
            "type":"Retail Goods"
        },
        {
            "category":"Professional",
            "type":"Services"
        }
    ],
    "sg:phone":"+1 214 398 6652",
    "sg:postcode":"75217",
    "sg:province":"TX",
    "wof:name":"Wally's Food & Deli",
    "wof:placetype":"venue"
},
  "geometry": {"coordinates":[-96.68301599999999,32.707491],"type":"Point"}
}