{
  "type": "Feature",
  "properties": {
    "iso:country":"US",
    "sg:address":"1845 Summit Ave",
    "sg:city":"Plano",
    "sg:classifiers":[
        {
            "category":"Professional",
            "type":"Services"
        }
    ],
    "sg:phone":"+1 972 398 1562",
    "sg:postcode":"75074",
    "sg:province":"TX",
    "sg:tags":[
        "establishment"
    ],
    "wof:name":"2turniton Inc",
    "wof:placetype":"venue"
},
  "geometry": {"coordinates":[-96.682829,33.009948],"type":"Point"}
}