{
  "type": "Feature",
  "properties": {
    "iso:country":"US",
    "sg:address":"1373 E Walnut St",
    "sg:city":"Seguin",
    "sg:classifiers":[
        {
            "category":"Cinema",
            "subcategory":"Movie Theater",
            "type":"Entertainment"
        }
    ],
    "sg:phone":"+1 830 379 8425",
    "sg:postcode":"78155",
    "sg:province":"TX",
    "sg:tags":[
        "motion",
        "picture"
    ],
    "wof:name":"King Ranger Theatres",
    "wof:placetype":"venue"
},
  "geometry": {"coordinates":[-97.944908,29.572121],"type":"Point"}
}