{
  "type": "Feature",
  "properties": {
    "iso:country":"US",
    "sg:address":"12801 Midway Rd",
    "sg:city":"Dallas",
    "sg:classifiers":[
        {
            "category":"Professional",
            "subcategory":"Accounting & Tax Preparation",
            "type":"Services"
        }
    ],
    "sg:phone":"+1 469 522 1488",
    "sg:postcode":"75229",
    "sg:province":"TX",
    "sg:tags":[
        "return",
        "filing"
    ],
    "wof:name":"H & R Block Tax Svc",
    "wof:placetype":"venue"
},
  "geometry": {"coordinates":[-96.838453,32.924585],"type":"Point"}
}