{
  "type": "Feature",
  "properties": {
    "iso:country":"US",
    "sg:address":"1822 S Ww White Rd",
    "sg:city":"San Antonio",
    "sg:classifiers":[
        {
            "category":"Banks & Credit Unions",
            "subcategory":"Bank",
            "type":"Services"
        }
    ],
    "sg:phone":"+1 210 333 4633",
    "sg:postcode":"78220",
    "sg:province":"TX",
    "sg:tags":[
        "small",
        "lender",
        "loan"
    ],
    "wof:name":"World Acceptance",
    "wof:placetype":"venue"
},
  "geometry": {"coordinates":[-98.404589,29.398919],"type":"Point"}
}