{
  "type": "Feature",
  "properties": {
    "iso:country":"US",
    "sg:address":"908 Essex Dr",
    "sg:city":"Friendswood",
    "sg:classifiers":[
        {
            "category":"Building & Trades",
            "subcategory":"Construction",
            "type":"Services"
        }
    ],
    "sg:phone":"+1 281 992 5896",
    "sg:postcode":"77546",
    "sg:province":"TX",
    "sg:tags":[
        "house"
    ],
    "wof:name":"Resources Fabricators",
    "wof:placetype":"venue"
},
  "geometry": {"coordinates":[-95.198875,29.51014],"type":"Point"}
}