{
  "type": "Feature",
  "properties": {
    "iso:country":"US",
    "sg:address":"1326 Fenfield Ave",
    "sg:city":"San Antonio",
    "sg:classifiers":[
        {
            "category":"Professional",
            "type":"Services"
        }
    ],
    "sg:phone":"+1 210 924 3088",
    "sg:postcode":"78211",
    "sg:province":"TX",
    "wof:name":"Jesses Cool Stuff",
    "wof:placetype":"venue"
},
  "geometry": {"coordinates":[-98.567064,29.363207],"type":"Point"}
}