{
  "type": "Feature",
  "properties": {
    "iso:country":"US",
    "sg:address":"503 SW 14th St",
    "sg:city":"Seminole",
    "sg:classifiers":[
        {
            "category":"Social Services",
            "subcategory":"Child Care",
            "type":"Services"
        }
    ],
    "sg:phone":"+1 432 758 6430",
    "sg:postcode":"79360",
    "sg:province":"TX",
    "sg:tags":[
        "day"
    ],
    "wof:name":"Ruth's Day Care",
    "wof:placetype":"venue"
},
  "geometry": {"coordinates":[-102.660843,32.714165],"type":"Point"}
}