{
  "type": "Feature",
  "properties": {
    "iso:country":"US",
    "sg:address":"1200 S 1st St",
    "sg:city":"Mcallen",
    "sg:classifiers":[
        {
            "category":"Farming",
            "subcategory":"Farm & Veterinary Services",
            "type":"Manufacturing & Wholesale Goods"
        }
    ],
    "sg:phone":"+1 956 687 2142",
    "sg:postcode":"78501",
    "sg:province":"TX",
    "sg:tags":[
        "management"
    ],
    "wof:name":"Tacubaya Ranch Management LLC",
    "wof:placetype":"venue"
},
  "geometry": {"coordinates":[-98.221236,26.191816],"type":"Point"}
}