{
  "type": "Feature",
  "properties": {
    "iso:country":"US",
    "sg:address":"1103 E 5th St",
    "sg:city":"Tyler",
    "sg:classifiers":[
        {
            "category":"Professional",
            "subcategory":"Management & Consulting",
            "type":"Services"
        }
    ],
    "sg:phone":"+1 903 592 7494",
    "sg:postcode":"75701",
    "sg:province":"TX",
    "wof:name":"Bee Natural",
    "wof:placetype":"venue"
},
  "geometry": {"coordinates":[-95.286553,32.332304],"type":"Point"}
}