{
  "type": "Feature",
  "properties": {
    "iso:country":"US",
    "sg:address":"1015 Erin St",
    "sg:city":"Houston",
    "sg:classifiers":[
        {
            "category":"Building & Trades",
            "subcategory":"Pest Control",
            "type":"Services"
        }
    ],
    "sg:phone":"+1 713 465 4157",
    "sg:postcode":"77009",
    "sg:province":"TX",
    "sg:website":"www.springbranchexterminators.com",
    "wof:name":"Spring Branch Exterminators",
    "wof:placetype":"venue"
},
  "geometry": {"coordinates":[-95.358487,29.796767],"type":"Point"}
}