{
  "type": "Feature",
  "properties": {
    "iso:country":"US",
    "sg:address":"23910 US Hwy 59",
    "sg:city":"Humble",
    "sg:classifiers":[
        {
            "category":"Professional",
            "subcategory":"Employment Agencies",
            "type":"Services"
        }
    ],
    "sg:phone":"+1 281 358 6172",
    "sg:postcode":"77339",
    "sg:province":"TX",
    "sg:tags":[
        "supportive"
    ],
    "wof:name":"Village Learning Center Inc",
    "wof:placetype":"venue"
},
  "geometry": {"coordinates":[-95.246709,30.067812],"type":"Point"}
}