{
  "type": "Feature",
  "properties": {
    "iso:country":"US",
    "sg:address":"808 E Rio Grande St",
    "sg:city":"Victoria",
    "sg:classifiers":[
        {
            "category":"Professional",
            "type":"Services"
        }
    ],
    "sg:phone":"+1 361 573 7511",
    "sg:postcode":"77901",
    "sg:province":"TX",
    "sg:tags":[
        "establishment"
    ],
    "wof:name":"Burns Jr",
    "wof:placetype":"venue"
},
  "geometry": {"coordinates":[-96.995215,28.806019],"type":"Point"}
}