{
  "type": "Feature",
  "properties": {
    "iso:country":"US",
    "sg:address":"604 Hickory Ridge Rd",
    "sg:city":"Manchaca",
    "sg:classifiers":[
        {
            "category":"Retail",
            "subcategory":"Auto Repair",
            "type":"Services"
        }
    ],
    "sg:phone":"+1 512 291 1052",
    "sg:postcode":"78652",
    "sg:province":"TX",
    "wof:name":"Capitol Fleet Service",
    "wof:placetype":"venue"
},
  "geometry": {"coordinates":[-97.82563,30.13496],"type":"Point"}
}