{
  "type": "Feature",
  "properties": {
    "iso:country":"US",
    "sg:address":"29018 Quail St",
    "sg:city":"Katy",
    "sg:classifiers":[
        {
            "category":"Building & Trades",
            "subcategory":"Landscaping Services",
            "type":"Services"
        }
    ],
    "sg:phone":"+1 281 391 4854",
    "sg:postcode":"77493",
    "sg:province":"TX",
    "wof:name":"Junction Ldscp Mint Irrigation",
    "wof:placetype":"venue"
},
  "geometry": {"coordinates":[-95.878145,29.829844],"type":"Point"}
}