{
  "type": "Feature",
  "properties": {
    "iso:country":"US",
    "sg:address":"7406 Wood Bluff Blvd",
    "sg:city":"Houston",
    "sg:classifiers":[
        {
            "category":"Food & Beverages",
            "subcategory":"Specialty",
            "type":"Retail Goods"
        }
    ],
    "sg:phone":"+1 713 983 6811",
    "sg:postcode":"77040",
    "sg:province":"TX",
    "wof:name":"Indian Lady Tea Co",
    "wof:placetype":"venue"
},
  "geometry": {"coordinates":[-95.518156,29.882175],"type":"Point"}
}