{
  "type": "Feature",
  "properties": {
    "iso:country":"US",
    "sg:address":"3812 Belt Line Rd",
    "sg:city":"Addison",
    "sg:classifiers":[
        {
            "category":"Personal",
            "subcategory":"Beauty Salon",
            "type":"Services"
        }
    ],
    "sg:phone":"+1 972 248 5088",
    "sg:postcode":"75001",
    "sg:province":"TX",
    "sg:tags":[
        "shop"
    ],
    "wof:name":"Hair By Hollywood",
    "wof:placetype":"venue"
},
  "geometry": {"coordinates":[-96.85030500000001,32.953007],"type":"Point"}
}