{
  "type": "Feature",
  "properties": {
    "iso:country":"US",
    "sg:address":"6614 Yosemite Ln",
    "sg:city":"Dallas",
    "sg:classifiers":[
        {
            "category":"Shopping Center",
            "type":"Public Place"
        }
    ],
    "sg:phone":"+1 214 373 4557",
    "sg:postcode":"75214",
    "sg:province":"TX",
    "wof:name":"Spigel Properties",
    "wof:placetype":"venue"
},
  "geometry": {"coordinates":[-96.747488,32.836437],"type":"Point"}
}