{
  "type": "Feature",
  "properties": {
    "iso:country":"US",
    "sg:address":"2030 E Paisano Dr",
    "sg:city":"El Paso",
    "sg:classifiers":[
        {
            "category":"Building & Trades",
            "subcategory":"Equipment Rental",
            "type":"Services"
        }
    ],
    "sg:phone":"+1 915 544 4481",
    "sg:postcode":"79905",
    "sg:province":"TX",
    "sg:tags":[
        "scale",
        "electronic",
        "sales"
    ],
    "wof:name":"Sbm Scale Int L",
    "wof:placetype":"venue"
},
  "geometry": {"coordinates":[-106.46148100000001,31.766294],"type":"Point"}
}