{
  "type": "Feature",
  "properties": {
    "iso:country":"US",
    "sg:address":"9766 Overmead Dr",
    "sg:city":"Houston",
    "sg:classifiers":[
        {
            "category":"Home & Garden",
            "subcategory":"Building Materials",
            "type":"Retail Goods"
        },
        {
            "category":"Building & Trades",
            "subcategory":"Construction",
            "type":"Services"
        }
    ],
    "sg:phone":"+1 713 331 9671",
    "sg:postcode":"77065",
    "sg:province":"TX",
    "sg:tags":[
        "concrete-stamped",
        "decorative",
        "asphalt",
        "specialty",
        "contractor",
        "concrete",
        "sealcoating",
        "staining",
        "fence-sales",
        "paving"
    ],
    "wof:name":"Turner Concrete Specialists",
    "wof:placetype":"venue"
},
  "geometry": {"coordinates":[-95.59509300000001,29.915039],"type":"Point"}
}