{
  "type": "Feature",
  "properties": {
    "iso:country":"US",
    "sg:address":"3863 Summer Manor Dr",
    "sg:city":"League City",
    "sg:classifiers":[
        {
            "category":"Food & Beverages",
            "subcategory":"Groceries & Convenience Stores",
            "type":"Retail Goods"
        }
    ],
    "sg:phone":"+1 281 334 0928",
    "sg:postcode":"77573",
    "sg:province":"TX",
    "sg:tags":[
        "product"
    ],
    "wof:name":"Intracoastal Food Corp",
    "wof:placetype":"venue"
},
  "geometry": {"coordinates":[-95.020549,29.505291],"type":"Point"}
}