{
  "type": "Feature",
  "properties": {
    "iso:country":"US",
    "sg:address":"102 Rob Ln",
    "sg:city":"De Soto",
    "sg:classifiers":[
        {
            "category":"Building & Trades",
            "subcategory":"Plumbing",
            "type":"Services"
        }
    ],
    "sg:phone":"+1 972 223 0528",
    "sg:postcode":"75115",
    "sg:province":"TX",
    "sg:tags":[
        "contractor"
    ],
    "wof:name":"Pauls Plumbing Co",
    "wof:placetype":"venue"
},
  "geometry": {"coordinates":[-96.860687,32.56602],"type":"Point"}
}