{
  "type": "Feature",
  "properties": {
    "iso:country":"US",
    "sg:address":"321 Oak Ridge Rd",
    "sg:city":"Georgetown",
    "sg:classifiers":[
        {
            "category":"Building & Trades",
            "subcategory":"Construction",
            "type":"Services"
        }
    ],
    "sg:phone":"+1 512 863 9153",
    "sg:postcode":"78628",
    "sg:province":"TX",
    "sg:tags":[
        "residential",
        "nonresidential"
    ],
    "wof:name":"San Gabriel Building & Remodel",
    "wof:placetype":"venue"
},
  "geometry": {"coordinates":[-97.714305,30.65308],"type":"Point"}
}