{
  "type": "Feature",
  "properties": {
    "iso:country":"US",
    "sg:address":"5110 I- 37",
    "sg:city":"Corpus Christi",
    "sg:classifiers":[
        {
            "category":"Real Estate",
            "subcategory":"Architect",
            "type":"Services"
        }
    ],
    "sg:phone":"+1 361 882 2999",
    "sg:postcode":"78407",
    "sg:province":"TX",
    "wof:name":"MURRAY Architects",
    "wof:placetype":"venue"
},
  "geometry": {"coordinates":[-97.451364,27.804128],"type":"Point"}
}