{
  "type": "Feature",
  "properties": {
    "iso:country":"US",
    "sg:address":"700 University Dr E",
    "sg:city":"College Station",
    "sg:classifiers":[
        {
            "category":"Personal",
            "subcategory":"Beauty Salon",
            "type":"Services"
        }
    ],
    "sg:phone":"+1 979 260 8900",
    "sg:postcode":"77840",
    "sg:province":"TX",
    "wof:name":"A Wild Hair",
    "wof:placetype":"venue"
},
  "geometry": {"coordinates":[-96.32693500000001,30.63449],"type":"Point"}
}