{
  "type": "Feature",
  "properties": {
    "iso:country":"US",
    "sg:address":"3001 Graystone Rd",
    "sg:city":"Longview",
    "sg:classifiers":[
        {
            "category":"Real Estate",
            "subcategory":"Real Estate Operator",
            "type":"Services"
        }
    ],
    "sg:phone":"+1 903 753 9595",
    "sg:postcode":"75605",
    "sg:province":"TX",
    "sg:tags":[
        "mobile",
        "home",
        "site",
        "community"
    ],
    "wof:name":"Stone Oaks Mobile Home Cmnty",
    "wof:placetype":"venue"
},
  "geometry": {"coordinates":[-94.788212,32.573053],"type":"Point"}
}