{
  "type": "Feature",
  "properties": {
    "iso:country":"US",
    "sg:address":"11511 W Airport Blvd",
    "sg:city":"Stafford",
    "sg:classifiers":[
        {
            "category":"Restaurant",
            "type":"Food & Drink"
        }
    ],
    "sg:menulink":"http://www.allmenus.com/tx/sugar-land/11196-dennys/menu/",
    "sg:phone":"+1 281 494 2577",
    "sg:postcode":"77477",
    "sg:province":"TX",
    "sg:tags":[
        "american",
        "diner"
    ],
    "wof:name":"Denny's",
    "wof:placetype":"venue"
},
  "geometry": {"coordinates":[-95.579519,29.646278],"type":"Point"}
}