{
  "type": "Feature",
  "properties": {
    "iso:country":"US",
    "sg:address":"7735 Querida Ln",
    "sg:city":"Dallas",
    "sg:classifiers":[
        {
            "category":"Professional",
            "subcategory":"Business Services",
            "type":"Services"
        }
    ],
    "sg:phone":"+1 972 720 9936",
    "sg:postcode":"75248",
    "sg:province":"TX",
    "wof:name":"Kec Express Inc",
    "wof:placetype":"venue"
},
  "geometry": {"coordinates":[-96.776405,32.9696],"type":"Point"}
}