{
  "type": "Feature",
  "properties": {
    "iso:country":"US",
    "sg:address":"10007 Broadway",
    "sg:city":"San Antonio",
    "sg:classifiers":[
        {
            "category":"Home & Garden",
            "subcategory":"Building Materials",
            "type":"Retail Goods"
        }
    ],
    "sg:phone":"+1 210 805 8823",
    "sg:postcode":"78217",
    "sg:province":"TX",
    "sg:tags":[
        "glass",
        "window",
        "plate"
    ],
    "wof:name":"Phenix Glass",
    "wof:placetype":"venue"
},
  "geometry": {"coordinates":[-98.449613,29.531631],"type":"Point"}
}