{
  "type": "Feature",
  "properties": {
    "iso:country":"US",
    "sg:address":"508 S Broadway St",
    "sg:city":"Plainview",
    "sg:classifiers":[
        {
            "category":"Retail",
            "subcategory":"Portrait Studio",
            "type":"Services"
        }
    ],
    "sg:phone":"+1 806 296 0828",
    "sg:postcode":"79072",
    "sg:province":"TX",
    "sg:tags":[
        "photographer"
    ],
    "wof:name":"Bill Weaks",
    "wof:placetype":"venue"
},
  "geometry": {"coordinates":[-101.702889,34.174864],"type":"Point"}
}