{
  "type": "Feature",
  "properties": {
    "iso:country":"US",
    "sg:address":"625 Mowery St",
    "sg:city":"Blossom",
    "sg:classifiers":[
        {
            "category":"Professional",
            "type":"Services"
        }
    ],
    "sg:phone":"+1 903 982 5920",
    "sg:postcode":"75416",
    "sg:province":"TX",
    "wof:name":"Wilkerson Motor Sports",
    "wof:placetype":"venue"
},
  "geometry": {"coordinates":[-95.37887000000001,33.656223],"type":"Point"}
}