{
  "type": "Feature",
  "properties": {
    "iso:country":"US",
    "sg:address":"3648 FM 1960 W",
    "sg:city":"Houston",
    "sg:classifiers":[
        {
            "category":"Professional",
            "subcategory":"Lawyer & Legal Services",
            "type":"Services"
        }
    ],
    "sg:phone":"+1 713 521 2137",
    "sg:postcode":"77068",
    "sg:province":"TX",
    "sg:tags":[
        "attorney"
    ],
    "wof:name":"Erma J Carey",
    "wof:placetype":"venue"
},
  "geometry": {"coordinates":[-95.480146,29.998054],"type":"Point"}
}