{
  "type": "Feature",
  "properties": {
    "iso:country":"US",
    "sg:address":"1075 Griffin St W",
    "sg:city":"Dallas",
    "sg:classifiers":[
        {
            "category":"Real Estate",
            "subcategory":"Real Estate Agent",
            "type":"Services"
        }
    ],
    "sg:phone":"+1 214 565 0021",
    "sg:postcode":"75215",
    "sg:province":"TX",
    "sg:tags":[
        "appraiser"
    ],
    "wof:name":"Bill Lewis & Assoc",
    "wof:placetype":"venue"
},
  "geometry": {"coordinates":[-96.796544,32.771454],"type":"Point"}
}