{
  "type": "Feature",
  "properties": {
    "iso:country":"US",
    "sg:address":"8400 Douglas Ave",
    "sg:city":"Dallas",
    "sg:classifiers":[
        {
            "category":"Health Services",
            "subcategory":"Doctor",
            "type":"Services"
        }
    ],
    "sg:phone":"+1 214 692 1700",
    "sg:postcode":"75225",
    "sg:province":"TX",
    "sg:tags":[
        "dentist"
    ],
    "wof:name":"Dallas Center For Cosmetic Den",
    "wof:placetype":"venue"
},
  "geometry": {"coordinates":[-96.808612,32.865488],"type":"Point"}
}