{
  "type": "Feature",
  "properties": {
    "iso:country":"US",
    "sg:address":"2829 Lawrence St",
    "sg:city":"Irving",
    "sg:classifiers":[
        {
            "category":"Banks & Credit Unions",
            "subcategory":"Investment Brokerage",
            "type":"Services"
        }
    ],
    "sg:phone":"+1 972 790 3400",
    "sg:postcode":"75061",
    "sg:province":"TX",
    "wof:name":"Prestige Investment",
    "wof:placetype":"venue"
},
  "geometry": {"coordinates":[-96.984223,32.825005],"type":"Point"}
}