{
  "type": "Feature",
  "properties": {
    "iso:country":"US",
    "sg:address":"2731 W 6th St",
    "sg:city":"Fort Worth",
    "sg:classifiers":[
        {
            "category":"Shopping",
            "subcategory":"Used Merchandise",
            "type":"Retail Goods"
        }
    ],
    "sg:phone":"+1 817 810 0100",
    "sg:postcode":"76107",
    "sg:province":"TX",
    "sg:tags":[
        "antique"
    ],
    "wof:name":"Museum District Antiques",
    "wof:placetype":"venue"
},
  "geometry": {"coordinates":[-97.35601699999999,32.752015],"type":"Point"}
}