{
  "type": "Feature",
  "properties": {
    "iso:country":"US",
    "sg:address":"400 W Commerce St",
    "sg:city":"Brady",
    "sg:classifiers":[
        {
            "category":"Autos & Motor Vehicles",
            "subcategory":"Auto Supplies",
            "type":"Retail Goods"
        }
    ],
    "sg:phone":"+1 325 597 2177",
    "sg:postcode":"76825",
    "sg:province":"TX",
    "sg:tags":[
        "tire"
    ],
    "wof:name":"Evridge Tire & Auto Ctr",
    "wof:placetype":"venue"
},
  "geometry": {"coordinates":[-99.33834899999999,31.134812],"type":"Point"}
}