{
  "type": "Feature",
  "properties": {
    "iso:country":"US",
    "sg:address":"15919 Crooked Lake Way S",
    "sg:city":"Cypress",
    "sg:classifiers":[
        {
            "category":"Manufacturing",
            "subcategory":"Printing",
            "type":"Manufacturing & Wholesale Goods"
        }
    ],
    "sg:phone":"+1 281 256 0678",
    "sg:postcode":"77433",
    "sg:province":"TX",
    "sg:tags":[
        "commercial"
    ],
    "wof:name":"MMS Specialties",
    "wof:placetype":"venue"
},
  "geometry": {"coordinates":[-95.753454,30.005763],"type":"Point"}
}