{
  "type": "Feature",
  "properties": {
    "iso:country":"US",
    "sg:address":"1095 Windy Hill Rd",
    "sg:city":"Kyle",
    "sg:classifiers":[
        {
            "category":"Food & Beverages",
            "subcategory":"Meat & Fish",
            "type":"Retail Goods"
        }
    ],
    "sg:phone":"+1 512 295 4466",
    "sg:postcode":"78640",
    "sg:province":"TX",
    "sg:tags":[
        "shop"
    ],
    "wof:name":"Mirancho Meat Market",
    "wof:placetype":"venue"
},
  "geometry": {"coordinates":[-97.829337,30.184286],"type":"Point"}
}