{
  "type": "Feature",
  "properties": {
    "iso:country":"US",
    "sg:address":"2625 N Josey Ln Ste 100",
    "sg:city":"Carrollton",
    "sg:classifiers":[
        {
            "category":"Recreation",
            "subcategory":"Amusement Park",
            "type":"Entertainment"
        }
    ],
    "sg:phone":"+1 972 242 7474",
    "sg:postcode":"75007",
    "sg:province":"TX",
    "wof:name":"Main Event Entertainment Lp",
    "wof:placetype":"venue"
},
  "geometry": {"coordinates":[-96.89129200000001,32.987123],"type":"Point"}
}