{
  "type": "Feature",
  "properties": {
    "iso:country":"US",
    "sg:address":"825 W 11th St 153",
    "sg:city":"Austin",
    "sg:classifiers":[
        {
            "category":"Wholesale",
            "subcategory":"Non-durable Goods",
            "type":"Manufacturing & Wholesale Goods"
        }
    ],
    "sg:phone":"+1 512 473 6409",
    "sg:postcode":"78701",
    "sg:province":"TX",
    "sg:tags":[
        "biological",
        "product"
    ],
    "wof:name":"Proactive Medical Technologies, Inc",
    "wof:placetype":"venue"
},
  "geometry": {"coordinates":[-97.750401,30.275353],"type":"Point"}
}