{
  "type": "Feature",
  "properties": {
    "iso:country":"US",
    "sg:address":"301 Bronze St",
    "sg:city":"Garland",
    "sg:classifiers":[
        {
            "category":"Building & Trades",
            "subcategory":"Construction",
            "type":"Services"
        }
    ],
    "sg:phone":"+1 972 276 0400",
    "sg:postcode":"75042",
    "sg:province":"TX",
    "sg:tags":[
        "contractor"
    ],
    "wof:name":"King Building Svc",
    "wof:placetype":"venue"
},
  "geometry": {"coordinates":[-96.657287,32.910207],"type":"Point"}
}