{
  "type": "Feature",
  "properties": {
    "iso:country":"US",
    "sg:address":"2830 S Ervay St",
    "sg:city":"Dallas",
    "sg:classifiers":[
        {
            "category":"Retail",
            "subcategory":"Funeral Services",
            "type":"Services"
        }
    ],
    "sg:phone":"+1 214 421 4700",
    "sg:postcode":"75215",
    "sg:province":"TX",
    "sg:tags":[
        "cemetery"
    ],
    "wof:name":"Benevolence Funeral Home",
    "wof:placetype":"venue"
},
  "geometry": {"coordinates":[-96.779404,32.763199],"type":"Point"}
}