{
  "type": "Feature",
  "properties": {
    "iso:country":"US",
    "sg:address":"1230 N 14th St",
    "sg:city":"Kingsville",
    "sg:classifiers":[
        {
            "category":"Retail",
            "subcategory":"Auto Repair",
            "type":"Services"
        }
    ],
    "sg:phone":"+1 361 592 0425",
    "sg:postcode":"78363",
    "sg:province":"TX",
    "sg:tags":[
        "glass",
        "replacement"
    ],
    "wof:name":"Victors Auto Glass",
    "wof:placetype":"venue"
},
  "geometry": {"coordinates":[-97.85610800000001,27.528479],"type":"Point"}
}