{
  "type": "Feature",
  "properties": {
    "iso:country":"US",
    "sg:address":"11547 Arbor Downs Rd",
    "sg:city":"Austin",
    "sg:classifiers":[
        {
            "category":"Real Estate",
            "subcategory":"Real Estate Agent",
            "type":"Services"
        }
    ],
    "sg:phone":"+1 512 280 4449",
    "sg:postcode":"78748",
    "sg:province":"TX",
    "wof:name":"Alltex Residential Pllc",
    "wof:placetype":"venue"
},
  "geometry": {"coordinates":[-97.851282,30.158385],"type":"Point"}
}