{
  "type": "Feature",
  "properties": {
    "iso:country":"US",
    "sg:address":"4945 Gulfway Dr",
    "sg:city":"Port Arthur",
    "sg:classifiers":[
        {
            "category":"Professional",
            "subcategory":"Accounting & Tax Preparation",
            "type":"Services"
        }
    ],
    "sg:phone":"+1 409 985 8598",
    "sg:postcode":"77642",
    "sg:province":"TX",
    "sg:tags":[
        "return",
        "filing"
    ],
    "wof:name":"Compro Tax",
    "wof:placetype":"venue"
},
  "geometry": {"coordinates":[-93.911867,29.916851],"type":"Point"}
}