{
  "type": "Feature",
  "properties": {
    "iso:country":"US",
    "sg:address":"11723 Curry Ridge Ln",
    "sg:city":"Tomball",
    "sg:classifiers":[
        {
            "category":"Education",
            "subcategory":"Vocational School",
            "type":"Public Place"
        }
    ],
    "sg:phone":"+1 281 255 9980",
    "sg:postcode":"77377",
    "sg:province":"TX",
    "sg:tags":[
        "training",
        "computer"
    ],
    "wof:name":"Mindleaders",
    "wof:placetype":"venue"
},
  "geometry": {"coordinates":[-95.61456200000001,30.043716],"type":"Point"}
}