{
  "type": "Feature",
  "properties": {
    "iso:country":"US",
    "sg:address":"407 Enterprise St",
    "sg:city":"Laredo",
    "sg:classifiers":[
        {
            "category":"Wholesale",
            "subcategory":"Non-durable Goods",
            "type":"Manufacturing & Wholesale Goods"
        }
    ],
    "sg:phone":"+1 956 728 9611",
    "sg:postcode":"78045",
    "sg:province":"TX",
    "wof:name":"A B International",
    "wof:placetype":"venue"
},
  "geometry": {"coordinates":[-99.535073,27.619253],"type":"Point"}
}