{
  "type": "Feature",
  "properties": {
    "iso:country":"US",
    "sg:address":"920 Murphy Rd",
    "sg:city":"Stafford",
    "sg:classifiers":[
        {
            "category":"Freight",
            "type":"Transportation"
        }
    ],
    "sg:phone":"+1 281 261 6294",
    "sg:postcode":"77477",
    "sg:province":"TX",
    "wof:name":"Gordons Moving & Mobil",
    "wof:placetype":"venue"
},
  "geometry": {"coordinates":[-95.564508,29.606913],"type":"Point"}
}