{
  "type": "Feature",
  "properties": {
    "iso:country":"US",
    "sg:address":"7300 Spanish Oak Dr",
    "sg:city":"Leander",
    "sg:classifiers":[
        {
            "category":"Building & Trades",
            "subcategory":"Construction",
            "type":"Services"
        }
    ],
    "sg:phone":"+1 512 267 0333",
    "sg:postcode":"78645",
    "sg:province":"TX",
    "sg:tags":[
        "home",
        "builder"
    ],
    "wof:name":"Reytex Homes Inc",
    "wof:placetype":"venue"
},
  "geometry": {"coordinates":[-97.97824900000001,30.468065],"type":"Point"}
}