{
  "type": "Feature",
  "properties": {
    "iso:country":"US",
    "sg:address":"3501 Towne Crossing Blvd Ste 180",
    "sg:city":"Mesquite",
    "sg:classifiers":[
        {
            "category":"Health Services",
            "subcategory":"Dentist",
            "type":"Services"
        }
    ],
    "sg:phone":"+1 972 270 7940",
    "sg:postcode":"75150",
    "sg:province":"TX",
    "wof:name":"Monarch Dental Associates",
    "wof:placetype":"venue"
},
  "geometry": {"coordinates":[-96.628899,32.812599],"type":"Point"}
}