{
  "type": "Feature",
  "properties": {
    "iso:country":"US",
    "sg:address":"1200 N Main St",
    "sg:city":"Fort Worth",
    "sg:classifiers":[
        {
            "category":"Autos & Motor Vehicles",
            "subcategory":"Automobile Sales",
            "type":"Retail Goods"
        }
    ],
    "sg:phone":"+1 817 626 1499",
    "sg:postcode":"76164",
    "sg:province":"TX",
    "sg:tags":[
        "car",
        "dealer"
    ],
    "wof:name":"Garzas Auto Sales",
    "wof:placetype":"venue"
},
  "geometry": {"coordinates":[-97.345142,32.775495],"type":"Point"}
}