{
  "type": "Feature",
  "properties": {
    "iso:country":"US",
    "sg:address":"205 N Johnson St",
    "sg:city":"Mineola",
    "sg:classifiers":[
        {
            "category":"Shopping",
            "type":"Retail Goods"
        }
    ],
    "sg:phone":"+1 903 569 2090",
    "sg:postcode":"75773",
    "sg:province":"TX",
    "sg:tags":[
        "merchandise"
    ],
    "wof:name":"Hart Magnolia House",
    "wof:placetype":"venue"
},
  "geometry": {"coordinates":[-95.48871800000001,32.665442],"type":"Point"}
}