{
  "type": "Feature",
  "properties": {
    "iso:country":"US",
    "sg:address":"11810 Lockwood Rd",
    "sg:city":"Houston",
    "sg:classifiers":[
        {
            "category":"Education",
            "subcategory":"School",
            "type":"Public Place"
        }
    ],
    "sg:phone":"+1 281 459 4323",
    "sg:postcode":"77044",
    "sg:province":"TX",
    "wof:name":"Holy Trinity Episcopal School",
    "wof:placetype":"venue"
},
  "geometry": {"coordinates":[-95.211197,29.911699],"type":"Point"}
}