{
  "type": "Feature",
  "properties": {
    "iso:country":"US",
    "sg:address":"2508 Hurstview Dr",
    "sg:city":"Hurst",
    "sg:classifiers":[
        {
            "category":"Professional",
            "subcategory":"Management & Consulting",
            "type":"Services"
        }
    ],
    "sg:phone":"+1 817 281 6764",
    "sg:postcode":"76054",
    "sg:province":"TX",
    "wof:name":"Triple C Management LLC",
    "wof:placetype":"venue"
},
  "geometry": {"coordinates":[-97.17744,32.860686],"type":"Point"}
}