{
  "type": "Feature",
  "properties": {
    "iso:country":"US",
    "sg:address":"1535 West Loop S Ste 200",
    "sg:city":"Houston",
    "sg:classifiers":[
        {
            "category":"Professional",
            "subcategory":"Employment Agencies",
            "type":"Services"
        }
    ],
    "sg:phone":"+1 713 522 4357",
    "sg:postcode":"77027",
    "sg:province":"TX",
    "sg:tags":[
        "opportunity"
    ],
    "wof:name":"Quatum Solutions For Business",
    "wof:placetype":"venue"
},
  "geometry": {"coordinates":[-95.45509300000001,29.752484],"type":"Point"}
}