{
  "type": "Feature",
  "properties": {
    "iso:country":"US",
    "sg:address":"2501 Oak Hill Dr",
    "sg:city":"Arlington",
    "sg:classifiers":[
        {
            "category":"Professional",
            "subcategory":"Engineering",
            "type":"Services"
        }
    ],
    "sg:phone":"+1 817 874 7113",
    "sg:postcode":"76006",
    "sg:province":"TX",
    "sg:tags":[
        "engineer"
    ],
    "wof:name":"KWS Structural Consultant",
    "wof:placetype":"venue"
},
  "geometry": {"coordinates":[-97.070269,32.777799],"type":"Point"}
}