{
  "type": "Feature",
  "properties": {
    "iso:country":"US",
    "sg:address":"1413 NE 15th Ave",
    "sg:city":"Amarillo",
    "sg:classifiers":[
        {
            "category":"Shopping",
            "subcategory":"Music",
            "type":"Retail Goods"
        }
    ],
    "sg:phone":"+1 806 383 4970",
    "sg:postcode":"79107",
    "sg:province":"TX",
    "wof:name":"Ramirez Records",
    "wof:placetype":"venue"
},
  "geometry": {"coordinates":[-101.810681,35.229342],"type":"Point"}
}