{
  "type": "Feature",
  "properties": {
    "iso:country":"US",
    "sg:address":"4717 Harley Ave",
    "sg:city":"Fort Worth",
    "sg:classifiers":[
        {
            "category":"Professional",
            "type":"Services"
        }
    ],
    "sg:phone":"+1 817 732 2213",
    "sg:postcode":"76107",
    "sg:province":"TX",
    "wof:name":"Beasley Foundation",
    "wof:placetype":"venue"
},
  "geometry": {"coordinates":[-97.390995,32.742363],"type":"Point"}
}