{
  "type": "Feature",
  "properties": {
    "iso:country":"US",
    "sg:address":"2403 S Shepherd Dr",
    "sg:city":"Houston",
    "sg:classifiers":[
        {
            "category":"Personal",
            "subcategory":"Beauty Salon",
            "type":"Services"
        }
    ],
    "sg:phone":"+1 713 523 4727",
    "sg:postcode":"77019",
    "sg:province":"TX",
    "sg:tags":[
        "shop"
    ],
    "sg:website":"www.billiejeans.com",
    "wof:name":"Billie Jean's",
    "wof:placetype":"venue"
},
  "geometry": {"coordinates":[-95.41065999999999,29.743429],"type":"Point"}
}