{
  "type": "Feature",
  "properties": {
    "iso:country":"US",
    "sg:address":"1618 Bill Ogden Dr",
    "sg:city":"El Paso",
    "sg:classifiers":[
        {
            "category":"Freight",
            "type":"Transportation"
        }
    ],
    "sg:phone":"+1 915 855 2021",
    "sg:postcode":"79936",
    "sg:province":"TX",
    "sg:tags":[
        "trucking"
    ],
    "wof:name":"Triple O Trucking",
    "wof:placetype":"venue"
},
  "geometry": {"coordinates":[-106.292222,31.750776],"type":"Point"}
}