{
  "type": "Feature",
  "properties": {
    "iso:country":"US",
    "sg:address":"9798 Bellaire Blvd",
    "sg:city":"Houston",
    "sg:classifiers":[
        {
            "category":"Health Services",
            "subcategory":"Health Practitioner",
            "type":"Services"
        }
    ],
    "sg:phone":"+1 713 771 7246",
    "sg:postcode":"77036",
    "sg:province":"TX",
    "sg:tags":[
        "gambling",
        "addiction-information",
        "treatment"
    ],
    "wof:name":"Espiritus Spine & Pain Rehab",
    "wof:placetype":"venue"
},
  "geometry": {"coordinates":[-95.55368,29.704795],"type":"Point"}
}