{
  "type": "Feature",
  "properties": {
    "iso:country":"US",
    "sg:address":"220 S Lockwood Dr",
    "sg:city":"Houston",
    "sg:classifiers":[
        {
            "category":"Building & Trades",
            "subcategory":"Construction",
            "type":"Services"
        }
    ],
    "sg:phone":"+1 713 926 3018",
    "sg:postcode":"77011",
    "sg:province":"TX",
    "sg:tags":[
        "a",
        "as",
        "operates",
        "demolition",
        "contractor"
    ],
    "wof:name":"AAA Demolishing",
    "wof:placetype":"venue"
},
  "geometry": {"coordinates":[-95.32808799999999,29.745008],"type":"Point"}
}