{
  "type": "Feature",
  "properties": {
    "iso:country":"US",
    "sg:address":"9894 Bissonnet St",
    "sg:city":"Houston",
    "sg:classifiers":[
        {
            "category":"Wholesale",
            "subcategory":"Drugs",
            "type":"Manufacturing & Wholesale Goods"
        }
    ],
    "sg:phone":"+1 713 995 1364",
    "sg:postcode":"77036",
    "sg:province":"TX",
    "sg:tags":[
        "perfumer",
        "material"
    ],
    "wof:name":"International Aromatic Chem",
    "wof:placetype":"venue"
},
  "geometry": {"coordinates":[-95.55294600000001,29.675218],"type":"Point"}
}