{
  "type": "Feature",
  "properties": {
    "iso:country":"US",
    "sg:address":"4244 Twilight Trl",
    "sg:city":"Fort Worth",
    "sg:classifiers":[
        {
            "category":"Food & Beverages",
            "subcategory":"Specialty",
            "type":"Retail Goods"
        }
    ],
    "sg:phone":"+1 817 249 4234",
    "sg:postcode":"76126",
    "sg:province":"TX",
    "wof:name":"Rycon LLC",
    "wof:placetype":"venue"
},
  "geometry": {"coordinates":[-97.50720099999999,32.629195],"type":"Point"}
}