{
  "type": "Feature",
  "properties": {
    "iso:country":"US",
    "sg:address":"3814 Marquis Dr Ste 109",
    "sg:city":"Garland",
    "sg:classifiers":[
        {
            "category":"Building & Trades",
            "subcategory":"Construction",
            "type":"Services"
        }
    ],
    "sg:phone":"+1 972 276 7663",
    "sg:postcode":"75042",
    "sg:province":"TX",
    "sg:tags":[
        "contractor"
    ],
    "sg:website":"www.preferredhomerehab.com/",
    "wof:name":"Preferred Home Rehab",
    "wof:placetype":"venue"
},
  "geometry": {"coordinates":[-96.68920799999999,32.901414],"type":"Point"}
}