{
  "type": "Feature",
  "properties": {
    "iso:country":"US",
    "sg:address":"902 N Highway 67",
    "sg:city":"Cedar Hill",
    "sg:classifiers":[
        {
            "category":"Professional",
            "subcategory":"Lawyer & Legal Services",
            "type":"Services"
        }
    ],
    "sg:phone":"+1 972 293 7774",
    "sg:postcode":"75104",
    "sg:province":"TX",
    "wof:name":"Morris Juliana atty",
    "wof:placetype":"venue"
},
  "geometry": {"coordinates":[-96.93034900000001,32.60441],"type":"Point"}
}