{
  "type": "Feature",
  "properties": {
    "iso:country":"US",
    "sg:address":"2107 Vance Jackson Rd",
    "sg:city":"San Antonio",
    "sg:classifiers":[
        {
            "category":"Home & Garden",
            "subcategory":"Household Appliances",
            "type":"Retail Goods"
        }
    ],
    "sg:phone":"+1 210 732 6309",
    "sg:postcode":"78213",
    "sg:province":"TX",
    "sg:tags":[
        "repair"
    ],
    "wof:name":"Ledenham Sewing Machine Co",
    "wof:placetype":"venue"
},
  "geometry": {"coordinates":[-98.535077,29.492271],"type":"Point"}
}