{
  "type": "Feature",
  "properties": {
    "iso:country":"US",
    "sg:address":"4470 Mockingbird Ln",
    "sg:city":"Midlothian",
    "sg:classifiers":[
        {
            "category":"Building & Trades",
            "subcategory":"Construction",
            "type":"Services"
        }
    ],
    "sg:phone":"+1 972 723 5300",
    "sg:postcode":"75154",
    "sg:province":"TX",
    "sg:tags":[
        "carpentry",
        "contractor"
    ],
    "wof:name":"Bruce Sanders",
    "wof:placetype":"venue"
},
  "geometry": {"coordinates":[-96.937046,32.495348],"type":"Point"}
}