{
  "type": "Feature",
  "properties": {
    "iso:country":"US",
    "sg:address":"301 Old Brandon Rd",
    "sg:city":"Hillsboro",
    "sg:classifiers":[
        {
            "category":"Organizations",
            "subcategory":"Religious Organization",
            "type":"Services"
        }
    ],
    "sg:phone":"+1 254 582 3473",
    "sg:postcode":"76645",
    "sg:province":"TX",
    "sg:tags":[
        "church"
    ],
    "wof:name":"First Presbyterian Church",
    "wof:placetype":"venue"
},
  "geometry": {"coordinates":[-97.111295,32.014204],"type":"Point"}
}