{
  "type": "Feature",
  "properties": {
    "iso:country":"US",
    "sg:address":"4051 FM 1960 W",
    "sg:city":"Houston",
    "sg:classifiers":[
        {
            "category":"Restaurant",
            "type":"Food & Drink"
        }
    ],
    "sg:phone":"+1 281 583 1535",
    "sg:postcode":"77068",
    "sg:province":"TX",
    "sg:tags":[
        "delicatessen"
    ],
    "wof:name":"Murphy's Deli",
    "wof:placetype":"venue"
},
  "geometry": {"coordinates":[-95.489006,29.992884],"type":"Point"}
}