{
  "type": "Feature",
  "properties": {
    "iso:country":"US",
    "sg:address":"3207 Carmel Valley Dr",
    "sg:city":"Missouri City",
    "sg:classifiers":[
        {
            "category":"Shopping",
            "subcategory":"Computers & Home Electronics",
            "type":"Retail Goods"
        }
    ],
    "sg:phone":"+1 281 261 0307",
    "sg:postcode":"77459",
    "sg:province":"TX",
    "wof:name":"Electrasoft",
    "wof:placetype":"venue"
},
  "geometry": {"coordinates":[-95.55925000000001,29.57317],"type":"Point"}
}