{
  "type": "Feature",
  "properties": {
    "iso:country":"US",
    "sg:address":"6221 Loma de Cristo Dr",
    "sg:city":"El Paso",
    "sg:classifiers":[
        {
            "category":"Building & Trades",
            "subcategory":"Landscaping Services",
            "type":"Services"
        }
    ],
    "sg:phone":"+1 915 588 3164",
    "sg:postcode":"79912",
    "sg:province":"TX",
    "sg:tags":[
        "landscaper"
    ],
    "wof:name":"Robert Martin",
    "wof:placetype":"venue"
},
  "geometry": {"coordinates":[-106.528852,31.860592],"type":"Point"}
}