{
  "type": "Feature",
  "properties": {
    "iso:country":"US",
    "sg:address":"1345 Philomena St",
    "sg:city":"Austin",
    "sg:classifiers":[
        {
            "category":"Manufacturing",
            "subcategory":"Pet Food",
            "type":"Manufacturing & Wholesale Goods"
        }
    ],
    "sg:phone":"+1 512 324 5813",
    "sg:postcode":"78723",
    "sg:province":"TX",
    "sg:tags":[
        "hay"
    ],
    "wof:name":"Seton Mso, Inc.",
    "wof:placetype":"venue"
},
  "geometry": {"coordinates":[-97.706543,30.301555],"type":"Point"}
}