{
  "type": "Feature",
  "properties": {
    "iso:country":"US",
    "sg:address":"823 SE Military Dr",
    "sg:city":"San Antonio",
    "sg:classifiers":[
        {
            "category":"Shopping",
            "type":"Retail Goods"
        }
    ],
    "sg:phone":"+1 210 924 0027",
    "sg:postcode":"78214",
    "sg:province":"TX",
    "sg:tags":[
        "merchandise"
    ],
    "wof:name":"Sgt Clutchs Discount Transm",
    "wof:placetype":"venue"
},
  "geometry": {"coordinates":[-98.48732,29.356792],"type":"Point"}
}