{
  "type": "Feature",
  "properties": {
    "iso:country":"US",
    "sg:address":"1619 Pecos St",
    "sg:city":"Amarillo",
    "sg:classifiers":[
        {
            "category":"Banks & Credit Unions",
            "subcategory":"Bank",
            "type":"Services"
        }
    ],
    "sg:phone":"+1 806 358 7109",
    "sg:postcode":"79102",
    "sg:province":"TX",
    "sg:tags":[
        "federal"
    ],
    "wof:name":"Bnsf Credit Union",
    "wof:placetype":"venue"
},
  "geometry": {"coordinates":[-101.87608,35.199379],"type":"Point"}
}