{
  "type": "Feature",
  "properties": {
    "iso:country":"US",
    "sg:address":"304 Atkinson Ave",
    "sg:city":"Copperas Cove",
    "sg:classifiers":[
        {
            "category":"Professional",
            "subcategory":"Advertising",
            "type":"Services"
        }
    ],
    "sg:phone":"+1 254 547 4877",
    "sg:postcode":"76522",
    "sg:province":"TX",
    "sg:tags":[
        "representative"
    ],
    "wof:name":"Excel Ind Reps",
    "wof:placetype":"venue"
},
  "geometry": {"coordinates":[-97.906057,31.09295],"type":"Point"}
}