{
  "type": "Feature",
  "properties": {
    "iso:country":"US",
    "sg:address":"2140 Ridgmar Blvd",
    "sg:city":"Fort Worth",
    "sg:classifiers":[
        {
            "category":"Restaurant",
            "type":"Food & Drink"
        }
    ],
    "sg:phone":"+1 817 732 5999",
    "sg:postcode":"76116",
    "sg:province":"TX",
    "sg:tags":[
        "eating"
    ],
    "wof:name":"Giovanni's Italian Restaurant",
    "wof:placetype":"venue"
},
  "geometry": {"coordinates":[-97.424879,32.739503],"type":"Point"}
}