{
  "type": "Feature",
  "properties": {
    "iso:country":"US",
    "sg:address":"2717 E Belt Line Rd",
    "sg:city":"Carrollton",
    "sg:classifiers":[
        {
            "category":"Restaurant",
            "type":"Food & Drink"
        }
    ],
    "sg:menulink":"http://www.allmenus.com/tx/northeast/101259-cousins-subs/menu/",
    "sg:phone":"+1 972 418 9393",
    "sg:postcode":"75006",
    "sg:province":"TX",
    "sg:tags":[
        "wrap",
        "american",
        "sandwich"
    ],
    "wof:name":"Cousin's Subs",
    "wof:placetype":"venue"
},
  "geometry": {"coordinates":[-96.859503,32.953763],"type":"Point"}
}