{
  "type": "Feature",
  "properties": {
    "iso:country":"US",
    "sg:address":"9226 Sequoia Dr",
    "sg:city":"Houston",
    "sg:classifiers":[
        {
            "category":"Shopping",
            "subcategory":"Music",
            "type":"Retail Goods"
        }
    ],
    "sg:phone":"+1 713 462 5166",
    "sg:postcode":"77041",
    "sg:province":"TX",
    "wof:name":"Touchonce Record Management",
    "wof:placetype":"venue"
},
  "geometry": {"coordinates":[-95.521655,29.840607],"type":"Point"}
}