{
  "type": "Feature",
  "properties": {
    "iso:country":"US",
    "sg:address":"10426 Leopard St",
    "sg:city":"Corpus Christi",
    "sg:classifiers":[
        {
            "category":"Autos & Motor Vehicles",
            "subcategory":"Automobile Sales",
            "type":"Retail Goods"
        }
    ],
    "sg:phone":"+1 361 242 9977",
    "sg:postcode":"78410",
    "sg:province":"TX",
    "sg:tags":[
        "car",
        "dealer"
    ],
    "wof:name":"Happy Trails",
    "wof:placetype":"venue"
},
  "geometry": {"coordinates":[-97.573702,27.838659],"type":"Point"}
}