{
  "type": "Feature",
  "properties": {
    "iso:country":"US",
    "sg:address":"5250 Whittier Oaks Dr",
    "sg:city":"Friendswood",
    "sg:classifiers":[
        {
            "category":"Organizations",
            "subcategory":"Non-profit Organization",
            "type":"Services"
        }
    ],
    "sg:phone":"+1 281 996 0445",
    "sg:postcode":"77546",
    "sg:province":"TX",
    "sg:tags":[
        "social"
    ],
    "wof:name":"CBI Home Inspections",
    "wof:placetype":"venue"
},
  "geometry": {"coordinates":[-95.18696799999999,29.533589],"type":"Point"}
}