{
  "type": "Feature",
  "properties": {
    "iso:country":"US",
    "sg:address":"1901 Taylor St",
    "sg:city":"Houston",
    "sg:classifiers":[
        {
            "category":"Shopping",
            "subcategory":"Mobile Phones",
            "type":"Retail Goods"
        }
    ],
    "sg:phone":"+1 713 868 3422",
    "sg:postcode":"77007",
    "sg:province":"TX",
    "wof:name":"RadioShack",
    "wof:placetype":"venue"
},
  "geometry": {"coordinates":[-95.381607,29.774386],"type":"Point"}
}