{
  "type": "Feature",
  "properties": {
    "iso:country":"US",
    "sg:address":"1407 Braewood Pl",
    "sg:city":"Duncanville",
    "sg:classifiers":[
        {
            "category":"Social Services",
            "type":"Services"
        }
    ],
    "sg:phone":"+1 972 296 1510",
    "sg:postcode":"75137",
    "sg:province":"TX",
    "wof:name":"Caremore Personal Care Home",
    "wof:placetype":"venue"
},
  "geometry": {"coordinates":[-96.942587,32.640177],"type":"Point"}
}