{
  "type": "Feature",
  "properties": {
    "iso:country":"US",
    "sg:address":"11710 Trickey Rd",
    "sg:city":"Houston",
    "sg:classifiers":[
        {
            "category":"Banks & Credit Unions",
            "subcategory":"Bank",
            "type":"Services"
        }
    ],
    "sg:phone":"+1 281 875 0553",
    "sg:postcode":"77067",
    "sg:province":"TX",
    "sg:tags":[
        "loan",
        "real estate"
    ],
    "wof:name":"Countrywide Home Loans",
    "wof:placetype":"venue"
},
  "geometry": {"coordinates":[-95.444818,29.953703],"type":"Point"}
}