{
  "type": "Feature",
  "properties": {
    "iso:country":"US",
    "sg:address":"3300 N A St",
    "sg:city":"Midland",
    "sg:classifiers":[
        {
            "category":"Professional",
            "type":"Services"
        }
    ],
    "sg:phone":"+1 432 683 7200",
    "sg:postcode":"79705",
    "sg:province":"TX",
    "sg:tags":[
        "geophysicist"
    ],
    "sg:website":"www.trnco.net",
    "wof:name":"TRNCO Petroleum Corp",
    "wof:placetype":"venue"
},
  "geometry": {"coordinates":[-102.09317,32.031909],"type":"Point"}
}