{
  "type": "Feature",
  "properties": {
    "iso:country":"US",
    "sg:address":"5701 Airport Rd",
    "sg:city":"Temple",
    "sg:classifiers":[
        {
            "category":"Building & Trades",
            "subcategory":"Cleaning & Sanitation",
            "type":"Services"
        }
    ],
    "sg:phone":"+1 254 770 3333",
    "sg:postcode":"76502",
    "sg:province":"TX",
    "sg:tags":[
        "property",
        "maintenance"
    ],
    "wof:name":"CFMS",
    "wof:placetype":"venue"
},
  "geometry": {"coordinates":[-97.390002,31.12207],"type":"Point"}
}