{
  "type": "Feature",
  "properties": {
    "iso:country":"US",
    "sg:address":"10407 Alpine Village",
    "sg:city":"San Antonio",
    "sg:classifiers":[
        {
            "category":"Building & Trades",
            "subcategory":"Construction",
            "type":"Services"
        }
    ],
    "sg:phone":"+1 210 675 6049",
    "sg:postcode":"78245",
    "sg:province":"TX",
    "sg:tags":[
        "nonresidential"
    ],
    "wof:name":"C Kc Construction",
    "wof:placetype":"venue"
},
  "geometry": {"coordinates":[-98.693234,29.430557],"type":"Point"}
}