{
  "type": "Feature",
  "properties": {
    "iso:country":"US",
    "sg:address":"2300 W Morton St",
    "sg:city":"Denison",
    "sg:classifiers":[
        {
            "category":"Restaurant",
            "type":"Food & Drink"
        }
    ],
    "sg:phone":"+1 903 463 3204",
    "sg:postcode":"75020",
    "sg:province":"TX",
    "sg:tags":[
        "shop",
        "coffee"
    ],
    "wof:name":"My Coffee Corner",
    "wof:placetype":"venue"
},
  "geometry": {"coordinates":[-96.57013999999999,33.760632],"type":"Point"}
}