{
  "type": "Feature",
  "properties": {
    "iso:country":"US",
    "sg:address":"4402 Spearhead Dr",
    "sg:city":"San Antonio",
    "sg:classifiers":[
        {
            "category":"Organizations",
            "subcategory":"Religious Organization",
            "type":"Services"
        }
    ],
    "sg:phone":"+1 210 431 8809",
    "sg:postcode":"78238",
    "sg:province":"TX",
    "wof:name":"Ingrams Chrch God Christn Schl",
    "wof:placetype":"venue"
},
  "geometry": {"coordinates":[-98.603072,29.475817],"type":"Point"}
}