{
  "type": "Feature",
  "properties": {
    "iso:country":"US",
    "sg:address":"210 N Mallard St",
    "sg:city":"Palestine",
    "sg:classifiers":[
        {
            "category":"Real Estate",
            "subcategory":"Surveying",
            "type":"Services"
        }
    ],
    "sg:phone":"+1 903 723 2208",
    "sg:postcode":"75801",
    "sg:province":"TX",
    "sg:tags":[
        "surveyor"
    ],
    "wof:name":"Richard J Reed Pro Land Survyr",
    "wof:placetype":"venue"
},
  "geometry": {"coordinates":[-95.627235,31.762145],"type":"Point"}
}