{
  "type": "Feature",
  "properties": {
    "iso:country":"US",
    "sg:address":"810 Chaparral Ln",
    "sg:city":"Arlington",
    "sg:classifiers":[
        {
            "category":"Building & Trades",
            "subcategory":"Construction",
            "type":"Services"
        }
    ],
    "sg:phone":"+1 817 275 6984",
    "sg:postcode":"76012",
    "sg:province":"TX",
    "sg:tags":[
        "repairing",
        "remodeling",
        "contractor"
    ],
    "wof:name":"Bob's Home Remodeling & Repair",
    "wof:placetype":"venue"
},
  "geometry": {"coordinates":[-97.134826,32.746169],"type":"Point"}
}