{
  "type": "Feature",
  "properties": {
    "iso:country":"US",
    "sg:address":"3434 5th St",
    "sg:city":"Port Arthur",
    "sg:classifiers":[
        {
            "category":"Retail",
            "subcategory":"Repair Shop",
            "type":"Services"
        }
    ],
    "sg:phone":"+1 409 982 0502",
    "sg:postcode":"77642",
    "sg:province":"TX",
    "sg:tags":[
        "lock",
        "business",
        "locksmith"
    ],
    "wof:name":"Jesuss Locksmith Shop Inc",
    "wof:placetype":"venue"
},
  "geometry": {"coordinates":[-93.911975,29.897591],"type":"Point"}
}