{
  "type": "Feature",
  "properties": {
    "iso:country":"US",
    "sg:address":"1302 Main St",
    "sg:city":"Lubbock",
    "sg:classifiers":[
        {
            "category":"Real Estate",
            "subcategory":"Real Estate Agent",
            "type":"Services"
        }
    ],
    "sg:phone":"+1 806 687 5263",
    "sg:postcode":"79401",
    "sg:province":"TX",
    "wof:name":"Talent Realtors",
    "wof:placetype":"venue"
},
  "geometry": {"coordinates":[-101.850185,33.585566],"type":"Point"}
}