{
  "type": "Feature",
  "properties": {
    "iso:country":"US",
    "sg:address":"3310 N Midkiff Rd",
    "sg:city":"Midland",
    "sg:classifiers":[
        {
            "category":"Personal",
            "subcategory":"Nail Salon",
            "type":"Services"
        }
    ],
    "sg:phone":"+1 432 697 4300",
    "sg:postcode":"79705",
    "sg:province":"TX",
    "wof:name":"A & A Nails",
    "wof:placetype":"venue"
},
  "geometry": {"coordinates":[-102.12498100000001,32.020029],"type":"Point"}
}