{
  "type": "Feature",
  "properties": {
    "iso:country":"US",
    "sg:address":"14710 Ranch Rd 12",
    "sg:city":"Wimberley",
    "sg:classifiers":[
        {
            "category":"Banks & Credit Unions",
            "subcategory":"Bank",
            "type":"Services"
        }
    ],
    "sg:phone":"+1 512 847 5504",
    "sg:postcode":"78676",
    "sg:province":"TX",
    "sg:tags":[
        "loan"
    ],
    "wof:name":"Balcones Bank SSB",
    "wof:placetype":"venue"
},
  "geometry": {"coordinates":[-98.10254399999999,30.00612],"type":"Point"}
}