{
  "type": "Feature",
  "properties": {
    "iso:country":"US",
    "sg:address":"1705 Lakeshore Dr",
    "sg:city":"Austin",
    "sg:classifiers":[
        {
            "category":"Restaurant",
            "type":"Food & Drink"
        }
    ],
    "sg:phone":"+1 512 447 1339",
    "sg:postcode":"78746",
    "sg:province":"TX",
    "sg:website":"www.babyacapulco.com",
    "wof:name":"Baby Acapulco",
    "wof:placetype":"venue"
},
  "geometry": {"coordinates":[-97.788751,30.298544],"type":"Point"}
}