{
  "type": "Feature",
  "properties": {
    "iso:country":"US",
    "sg:address":"16707 Holly Trail Dr",
    "sg:city":"Houston",
    "sg:classifiers":[
        {
            "category":"Wholesale",
            "subcategory":"Durable Goods & Equipment",
            "type":"Manufacturing & Wholesale Goods"
        }
    ],
    "sg:phone":"+1 281 480 7090",
    "sg:postcode":"77058",
    "sg:province":"TX",
    "wof:name":"DM Cherry",
    "wof:placetype":"venue"
},
  "geometry": {"coordinates":[-95.110285,29.562096],"type":"Point"}
}