{
  "type": "Feature",
  "properties": {
    "iso:country":"US",
    "sg:address":"2616 Ashley Dr",
    "sg:city":"Garland",
    "sg:classifiers":[
        {
            "category":"Professional",
            "subcategory":"Printing & Photocopies",
            "type":"Services"
        }
    ],
    "sg:phone":"+1 972 278 7860",
    "sg:postcode":"75041",
    "sg:province":"TX",
    "sg:tags":[
        "lithographer"
    ],
    "wof:name":"Astro Printing",
    "wof:placetype":"venue"
},
  "geometry": {"coordinates":[-96.647008,32.886453],"type":"Point"}
}