{
  "type": "Feature",
  "properties": {
    "iso:country":"US",
    "sg:address":"217 E Silver Sands Dr",
    "sg:city":"San Antonio",
    "sg:classifiers":[
        {
            "category":"Home & Garden",
            "subcategory":"Home Furnishings",
            "type":"Retail Goods"
        }
    ],
    "sg:phone":"+1 210 393 4797",
    "sg:postcode":"78216",
    "sg:province":"TX",
    "sg:tags":[
        "pottery"
    ],
    "wof:name":"Mexican Pottery Imports",
    "wof:placetype":"venue"
},
  "geometry": {"coordinates":[-98.493347,29.542012],"type":"Point"}
}