{
  "type": "Feature",
  "properties": {
    "iso:country":"US",
    "sg:address":"430 Forestgate Dr",
    "sg:city":"Garland",
    "sg:classifiers":[
        {
            "category":"Manufacturing",
            "subcategory":"Metals",
            "type":"Manufacturing & Wholesale Goods"
        }
    ],
    "sg:phone":"+1 972 272 9014",
    "sg:postcode":"75042",
    "sg:province":"TX",
    "sg:tags":[
        "fabrication",
        "structural"
    ],
    "wof:name":"Dm Acquisition LP",
    "wof:placetype":"venue"
},
  "geometry": {"coordinates":[-96.668093,32.909834],"type":"Point"}
}