{
  "type": "Feature",
  "properties": {
    "iso:country":"US",
    "sg:address":"177 Broadmoor St",
    "sg:city":"Meadowlakes",
    "sg:classifiers":[
        {
            "category":"Government",
            "subcategory":"Office",
            "type":"Public Place"
        }
    ],
    "sg:phone":"+1 830 693 2951",
    "sg:postcode":"78654",
    "sg:province":"TX",
    "sg:tags":[
        "govt",
        "city"
    ],
    "wof:name":"Meadowlakes Municipal Utility",
    "wof:placetype":"venue"
},
  "geometry": {"coordinates":[-98.291501,30.560288],"type":"Point"}
}