{
  "type": "Feature",
  "properties": {
    "iso:country":"US",
    "sg:address":"11840 Windville Ln",
    "sg:city":"Aledo",
    "sg:classifiers":[
        {
            "category":"Professional",
            "subcategory":"Management & Consulting",
            "type":"Services"
        }
    ],
    "sg:phone":"+1 817 244 4167",
    "sg:postcode":"76008",
    "sg:province":"TX",
    "wof:name":"Cygnus Consulting Service",
    "wof:placetype":"venue"
},
  "geometry": {"coordinates":[-97.52457200000001,32.709385],"type":"Point"}
}