{
  "type": "Feature",
  "properties": {
    "iso:country":"US",
    "sg:address":"9201 Metric Blvd Ste A",
    "sg:city":"Austin",
    "sg:classifiers":[
        {
            "category":"Professional",
            "type":"Services"
        }
    ],
    "sg:phone":"+1 512 832 1921",
    "sg:postcode":"78758",
    "sg:province":"TX",
    "sg:tags":[
        "planning",
        "event"
    ],
    "sg:website":"www.xtremexhibits.com",
    "wof:name":"Xtreme Xhibits by Skyline",
    "wof:placetype":"venue"
},
  "geometry": {"coordinates":[-97.721243,30.374164],"type":"Point"}
}