{
  "type": "Feature",
  "properties": {
    "iso:country":"US",
    "sg:address":"1300 E Pinecrest Dr Ste C",
    "sg:city":"Marshall",
    "sg:classifiers":[
        {
            "category":"Shopping",
            "subcategory":"Clothing, Apparel, & Fashions",
            "type":"Retail Goods"
        },
        {
            "category":"Shopping",
            "subcategory":"Department Store",
            "type":"Retail Goods"
        },
        {
            "category":"Shopping",
            "subcategory":"Jewelry",
            "type":"Retail Goods"
        },
        {
            "category":"Home & Garden",
            "subcategory":"Home Furnishings",
            "type":"Retail Goods"
        },
        {
            "category":"Shopping",
            "subcategory":"Shoes",
            "type":"Retail Goods"
        }
    ],
    "sg:phone":"+1 903 935 7981",
    "sg:postcode":"75670",
    "sg:province":"TX",
    "sg:tags":[
        "men's",
        "jeweler",
        "housewares",
        "apparel",
        "women's",
        "clothing"
    ],
    "sg:website":"http://jcpenney.com",
    "wof:name":"J C Penney Co",
    "wof:placetype":"venue"
},
  "geometry": {"coordinates":[-94.353889,32.526981],"type":"Point"}
}