{
  "type": "Feature",
  "properties": {
    "iso:country":"US",
    "sg:address":"521 Stonebluff Rd",
    "sg:city":"El Paso",
    "sg:classifiers":[
        {
            "category":"Shopping",
            "type":"Retail Goods"
        }
    ],
    "sg:phone":"+1 915 581 6287",
    "sg:postcode":"79912",
    "sg:province":"TX",
    "sg:tags":[
        "cosmetic",
        "perfume"
    ],
    "wof:name":"Mary Kay Cosmetics",
    "wof:placetype":"venue"
},
  "geometry": {"coordinates":[-106.52548899999999,31.841756],"type":"Point"}
}