{
  "type": "Feature",
  "properties": {
    "iso:country":"US",
    "sg:address":"923 S Alamo St",
    "sg:city":"San Antonio",
    "sg:classifiers":[
        {
            "category":"Real Estate",
            "subcategory":"Real Estate Agent",
            "type":"Services"
        }
    ],
    "sg:phone":"+1 210 225 0009",
    "sg:postcode":"78205",
    "sg:province":"TX",
    "wof:name":"William King Realty",
    "wof:placetype":"venue"
},
  "geometry": {"coordinates":[-98.49036599999999,29.41478],"type":"Point"}
}