{
  "type": "Feature",
  "properties": {
    "iso:country":"US",
    "sg:address":"628 Wilbarger St Unit A",
    "sg:city":"Vernon",
    "sg:classifiers":[
        {
            "category":"Building & Trades",
            "subcategory":"Equipment Rental",
            "type":"Services"
        }
    ],
    "sg:phone":"+1 940 552 5985",
    "sg:postcode":"76384",
    "sg:province":"TX",
    "sg:tags":[
        "yard",
        "leasing",
        "store"
    ],
    "wof:name":"Jerry Goodrum Rentals",
    "wof:placetype":"venue"
},
  "geometry": {"coordinates":[-99.31071900000001,34.152325],"type":"Point"}
}