{
  "type": "Feature",
  "properties": {
    "iso:country":"US",
    "sg:address":"4303 State Hwy 1604",
    "sg:city":"San Antonio",
    "sg:classifiers":[
        {
            "category":"Manufacturing",
            "subcategory":"Tools & Machinery",
            "type":"Manufacturing & Wholesale Goods"
        }
    ],
    "sg:phone":"+1 210 495 6224",
    "sg:postcode":"78251",
    "sg:province":"TX",
    "sg:tags":[
        "concrete",
        "mfg"
    ],
    "wof:name":"Meader Construction Co Inc",
    "wof:placetype":"venue"
},
  "geometry": {"coordinates":[-98.711039,29.476324],"type":"Point"}
}