{
  "type": "Feature",
  "properties": {
    "iso:country":"US",
    "sg:address":"3602 Slide Rd",
    "sg:city":"Lubbock",
    "sg:classifiers":[
        {
            "category":"Personal",
            "subcategory":"Beauty Salon",
            "type":"Services"
        }
    ],
    "sg:phone":"+1 806 797 3899",
    "sg:postcode":"79414",
    "sg:province":"TX",
    "sg:tags":[
        "shop"
    ],
    "wof:name":"MI Place",
    "wof:placetype":"venue"
},
  "geometry": {"coordinates":[-101.92256500000001,33.560555],"type":"Point"}
}