{
  "type": "Feature",
  "properties": {
    "iso:country":"US",
    "sg:address":"1416 N Mesa St",
    "sg:city":"El Paso",
    "sg:classifiers":[
        {
            "category":"Health Services",
            "subcategory":"Doctor",
            "type":"Services"
        }
    ],
    "sg:phone":"+1 915 533 0162",
    "sg:postcode":"79902",
    "sg:province":"TX",
    "sg:tags":[
        "clinic"
    ],
    "wof:name":"Jaunell's Electrolysis Clinic",
    "wof:placetype":"venue"
},
  "geometry": {"coordinates":[-106.495285,31.768163],"type":"Point"}
}