{
  "type": "Feature",
  "properties": {
    "iso:country":"US",
    "sg:address":"15730 Samoa Way",
    "sg:city":"Houston",
    "sg:classifiers":[
        {
            "category":"Building & Trades",
            "subcategory":"Landscaping Services",
            "type":"Services"
        }
    ],
    "sg:phone":"+1 281 437 1557",
    "sg:postcode":"77053",
    "sg:province":"TX",
    "wof:name":"Resendiz Lawn Service",
    "wof:placetype":"venue"
},
  "geometry": {"coordinates":[-95.472616,29.598213],"type":"Point"}
}