{
  "type": "Feature",
  "properties": {
    "iso:country":"US",
    "sg:address":"5900 Inks Lake Dr",
    "sg:city":"Arlington",
    "sg:classifiers":[
        {
            "category":"Education",
            "subcategory":"School",
            "type":"Public Place"
        }
    ],
    "sg:phone":"+1 817 419 5100",
    "sg:postcode":"76018",
    "sg:province":"TX",
    "wof:name":"Bebensee Elementary School",
    "wof:placetype":"venue"
},
  "geometry": {"coordinates":[-97.10497100000001,32.64743],"type":"Point"}
}