{
  "type": "Feature",
  "properties": {
    "iso:country":"US",
    "sg:address":"202 Loch Lomond Dr",
    "sg:city":"League City",
    "sg:classifiers":[
        {
            "category":"Building & Trades",
            "subcategory":"Equipment Rental",
            "type":"Services"
        }
    ],
    "sg:phone":"+1 281 554 2895",
    "sg:postcode":"77573",
    "sg:province":"TX",
    "wof:name":"Kosher Development",
    "wof:placetype":"venue"
},
  "geometry": {"coordinates":[-95.110032,29.501809],"type":"Point"}
}