{
  "type": "Feature",
  "properties": {
    "iso:country":"US",
    "sg:address":"495 Coryell St",
    "sg:city":"League City",
    "sg:classifiers":[
        {
            "category":"Wholesale",
            "subcategory":"Auto Parts",
            "type":"Manufacturing & Wholesale Goods"
        }
    ],
    "sg:phone":"+1 281 338 8777",
    "sg:postcode":"77573",
    "sg:province":"TX",
    "wof:name":"Clear Lake Body Shop",
    "wof:placetype":"venue"
},
  "geometry": {"coordinates":[-95.097689,29.510963],"type":"Point"}
}