{
  "type": "Feature",
  "properties": {
    "iso:country":"US",
    "sg:address":"15303 Huebner Rd",
    "sg:city":"San Antonio",
    "sg:classifiers":[
        {
            "category":"Professional",
            "subcategory":"Lawyer & Legal Services",
            "type":"Services"
        }
    ],
    "sg:phone":"+1 210 828 5499",
    "sg:postcode":"78248",
    "sg:province":"TX",
    "sg:tags":[
        "attorney"
    ],
    "wof:name":"Mc Donough & Smith",
    "wof:placetype":"venue"
},
  "geometry": {"coordinates":[-98.53796699999999,29.582499],"type":"Point"}
}