{
  "type": "Feature",
  "properties": {
    "iso:country":"US",
    "sg:address":"2320 Mesquite Ct W",
    "sg:city":"Bedford",
    "sg:classifiers":[
        {
            "category":"Real Estate",
            "subcategory":"Real Estate Operator",
            "type":"Services"
        }
    ],
    "sg:phone":"+1 817 868 0798",
    "sg:postcode":"76021",
    "sg:province":"TX",
    "sg:tags":[
        "building",
        "nonresidential"
    ],
    "wof:name":"Heb Properties LLC",
    "wof:placetype":"venue"
},
  "geometry": {"coordinates":[-97.127933,32.856412],"type":"Point"}
}