{
  "type": "Feature",
  "properties": {
    "iso:country":"US",
    "sg:address":"113 Aviation Dr",
    "sg:city":"Corpus Christi",
    "sg:classifiers":[
        {
            "category":"Professional",
            "subcategory":"Management & Consulting",
            "type":"Services"
        }
    ],
    "sg:phone":"+1 817 439 5588",
    "sg:postcode":"78418",
    "sg:province":"TX",
    "sg:tags":[
        "marketing",
        "program"
    ],
    "wof:name":"Performance Direct Marketing",
    "wof:placetype":"venue"
},
  "geometry": {"coordinates":[-97.277265,27.681254],"type":"Point"}
}