{
  "type": "Feature",
  "properties": {
    "iso:country":"US",
    "sg:address":"1811 W Park Row Dr",
    "sg:city":"Arlington",
    "sg:classifiers":[
        {
            "category":"Building & Trades",
            "subcategory":"Construction",
            "type":"Services"
        }
    ],
    "sg:phone":"+1 817 261 6577",
    "sg:postcode":"76013",
    "sg:province":"TX",
    "sg:tags":[
        "bathroom",
        "remodeling",
        "kitchen"
    ],
    "wof:name":"A1 Professional Remodeling",
    "wof:placetype":"venue"
},
  "geometry": {"coordinates":[-97.137094,32.721369],"type":"Point"}
}