{
  "type": "Feature",
  "properties": {
    "iso:country":"US",
    "sg:address":"402 Stephenson St",
    "sg:city":"Victoria",
    "sg:classifiers":[
        {
            "category":"Professional",
            "subcategory":"Testing Lab",
            "type":"Services"
        }
    ],
    "sg:phone":"+1 361 575 0281",
    "sg:postcode":"77904",
    "sg:province":"TX",
    "sg:tags":[
        "laboratory"
    ],
    "wof:name":"Professional Service Inds",
    "wof:placetype":"venue"
},
  "geometry": {"coordinates":[-97.002619,28.84142],"type":"Point"}
}