{
  "type": "Feature",
  "properties": {
    "iso:country":"US",
    "sg:address":"4535 Rittiman Rd",
    "sg:city":"San Antonio",
    "sg:classifiers":[
        {
            "category":"Restaurant",
            "type":"Food & Drink"
        }
    ],
    "sg:phone":"+1 210 656 9119",
    "sg:postcode":"78218",
    "sg:province":"TX",
    "wof:name":"Popeyes Chicken & Biscuits",
    "wof:placetype":"venue"
},
  "geometry": {"coordinates":[-98.40581400000001,29.484076],"type":"Point"}
}