{
  "type": "Feature",
  "properties": {
    "iso:country":"US",
    "sg:address":"100 S Texas St",
    "sg:city":"Crowley",
    "sg:classifiers":[
        {
            "category":"Real Estate",
            "subcategory":"Real Estate Agent",
            "type":"Services"
        }
    ],
    "sg:phone":"+1 817 426 2100",
    "sg:postcode":"76036",
    "sg:province":"TX",
    "wof:name":"Larry Leach Real Estate",
    "wof:placetype":"venue"
},
  "geometry": {"coordinates":[-97.360328,32.578773],"type":"Point"}
}