{
  "type": "Feature",
  "properties": {
    "iso:country":"US",
    "sg:address":"300 San Marcos St",
    "sg:city":"Buda",
    "sg:classifiers":[
        {
            "category":"Education",
            "subcategory":"School",
            "type":"Public Place"
        }
    ],
    "sg:phone":"+1 512 295 4431",
    "sg:postcode":"78610",
    "sg:province":"TX",
    "wof:name":"Buda Elementary School",
    "wof:placetype":"venue"
},
  "geometry": {"coordinates":[-97.844306,30.083315],"type":"Point"}
}