{
  "type": "Feature",
  "properties": {
    "iso:country":"US",
    "sg:address":"1910 Greenhill Dr",
    "sg:city":"Round Rock",
    "sg:classifiers":[
        {
            "category":"Building & Trades",
            "subcategory":"Equipment Rental",
            "type":"Services"
        }
    ],
    "sg:phone":"+1 512 733 1856",
    "sg:postcode":"78664",
    "sg:province":"TX",
    "wof:name":"Ashleys Party Rentals",
    "wof:placetype":"venue"
},
  "geometry": {"coordinates":[-97.679739,30.529511],"type":"Point"}
}