{
  "type": "Feature",
  "properties": {
    "iso:country":"US",
    "sg:address":"1811 Breezy Bend Dr",
    "sg:city":"Katy",
    "sg:classifiers":[
        {
            "category":"Manufacturing",
            "subcategory":"Printing",
            "type":"Manufacturing & Wholesale Goods"
        }
    ],
    "sg:phone":"+1 281 395 4783",
    "sg:postcode":"77494",
    "sg:province":"TX",
    "sg:tags":[
        "publishing"
    ],
    "wof:name":"Round Oak Publishing Inc",
    "wof:placetype":"venue"
},
  "geometry": {"coordinates":[-95.808716,29.765898],"type":"Point"}
}