{
  "type": "Feature",
  "properties": {
    "iso:country":"US",
    "sg:address":"5711 Clarewood Dr",
    "sg:city":"Houston",
    "sg:classifiers":[
        {
            "category":"Building & Trades",
            "subcategory":"Electrical",
            "type":"Services"
        }
    ],
    "sg:phone":"+1 713 218 0410",
    "sg:postcode":"77081",
    "sg:province":"TX",
    "sg:tags":[
        "electrical",
        "contractor"
    ],
    "wof:name":"Total Electrical Services",
    "wof:placetype":"venue"
},
  "geometry": {"coordinates":[-95.48103,29.70911],"type":"Point"}
}