{
  "type": "Feature",
  "properties": {
    "iso:country":"US",
    "sg:address":"6108 McPherson Ave",
    "sg:city":"Laredo",
    "sg:classifiers":[
        {
            "category":"Professional",
            "subcategory":"Engineering",
            "type":"Services"
        }
    ],
    "sg:phone":"+1 956 728 8585",
    "sg:postcode":"78041",
    "sg:province":"TX",
    "sg:tags":[
        "engineer"
    ],
    "wof:name":"Rosin-Johnson",
    "wof:placetype":"venue"
},
  "geometry": {"coordinates":[-99.475674,27.558597],"type":"Point"}
}