{
  "type": "Feature",
  "properties": {
    "iso:country":"US",
    "sg:address":"7 Clarion Ridge Ct",
    "sg:city":"The Woodlands",
    "sg:classifiers":[
        {
            "category":"Professional",
            "subcategory":"Business Services",
            "type":"Services"
        }
    ],
    "sg:phone":"+1 281 298 6444",
    "sg:postcode":"77382",
    "sg:province":"TX",
    "sg:tags":[
        "interior",
        "consultant",
        "design",
        "decorator"
    ],
    "wof:name":"House Sweet It Is",
    "wof:placetype":"venue"
},
  "geometry": {"coordinates":[-95.51283599999999,30.216974],"type":"Point"}
}