{
  "type": "Feature",
  "properties": {
    "iso:country":"US",
    "sg:address":"4225 Bellaire Blvd",
    "sg:city":"Houston",
    "sg:classifiers":[
        {
            "category":"Retail",
            "subcategory":"Laundry & Dry Cleaning",
            "type":"Services"
        }
    ],
    "sg:phone":"+1 713 218 6262",
    "sg:postcode":"77025",
    "sg:province":"TX",
    "sg:tags":[
        "drycleaning",
        "plant"
    ],
    "wof:name":"A Carlyns",
    "wof:placetype":"venue"
},
  "geometry": {"coordinates":[-95.445809,29.705858],"type":"Point"}
}