{
  "type": "Feature",
  "properties": {
    "iso:country":"US",
    "sg:address":"15302 Hillside Park Way",
    "sg:city":"Cypress",
    "sg:classifiers":[
        {
            "category":"Professional",
            "subcategory":"Lawyer & Legal Services",
            "type":"Services"
        }
    ],
    "sg:phone":"+1 281 373 9332",
    "sg:postcode":"77433",
    "sg:province":"TX",
    "wof:name":"Kent A Rowald PC",
    "wof:placetype":"venue"
},
  "geometry": {"coordinates":[-95.73690000000001,29.997191],"type":"Point"}
}