{
  "type": "Feature",
  "properties": {
    "iso:country":"US",
    "sg:address":"6700 S 33rd St",
    "sg:city":"Mcallen",
    "sg:classifiers":[
        {
            "category":"Professional",
            "subcategory":"Management & Consulting",
            "type":"Services"
        }
    ],
    "sg:phone":"+1 956 687 1383",
    "sg:postcode":"78503",
    "sg:province":"TX",
    "sg:tags":[
        "logistics"
    ],
    "wof:name":"R S Logistics",
    "wof:placetype":"venue"
},
  "geometry": {"coordinates":[-98.267808,26.148697],"type":"Point"}
}