{
  "type": "Feature",
  "properties": {
    "iso:country":"US",
    "sg:address":"4655 Wild Indigo",
    "sg:city":"Houston",
    "sg:classifiers":[
        {
            "category":"Manufacturing",
            "subcategory":"Printing",
            "type":"Manufacturing & Wholesale Goods"
        }
    ],
    "sg:phone":"+1 713 840 0124",
    "sg:postcode":"77027",
    "sg:province":"TX",
    "sg:tags":[
        "newspaper"
    ],
    "wof:name":"Katrina Daily",
    "wof:placetype":"venue"
},
  "geometry": {"coordinates":[-95.452438,29.728215],"type":"Point"}
}