{
  "type": "Feature",
  "properties": {
    "iso:country":"US",
    "sg:address":"1114 Colby Ln",
    "sg:city":"Cedar Park",
    "sg:classifiers":[
        {
            "category":"Professional",
            "subcategory":"Business Services",
            "type":"Services"
        }
    ],
    "sg:phone":"+1 512 918 2195",
    "sg:postcode":"78613",
    "sg:province":"TX",
    "wof:name":"Mfn Ventures Inc",
    "wof:placetype":"venue"
},
  "geometry": {"coordinates":[-97.839022,30.502888],"type":"Point"}
}