{
  "type": "Feature",
  "properties": {
    "iso:country":"US",
    "sg:address":"302 Brookside Dr",
    "sg:city":"Grapevine",
    "sg:classifiers":[
        {
            "category":"Professional",
            "subcategory":"Business Services",
            "type":"Services"
        }
    ],
    "sg:phone":"+1 817 329 1682",
    "sg:postcode":"76051",
    "sg:province":"TX",
    "wof:name":"Ironwood Design Group I Inc",
    "wof:placetype":"venue"
},
  "geometry": {"coordinates":[-97.097482,32.94311],"type":"Point"}
}