{
  "type": "Feature",
  "properties": {
    "iso:country":"US",
    "sg:address":"2903 Grand Ave",
    "sg:city":"Dallas",
    "sg:classifiers":[
        {
            "category":"Organizations",
            "subcategory":"Religious Organization",
            "type":"Services"
        }
    ],
    "sg:phone":"+1 214 421 1951",
    "sg:postcode":"75215",
    "sg:province":"TX",
    "sg:tags":[
        "church"
    ],
    "wof:name":"Faith Cumberland Presbyterian",
    "wof:placetype":"venue"
},
  "geometry": {"coordinates":[-96.769535,32.773645],"type":"Point"}
}