{
  "type": "Feature",
  "properties": {
    "iso:country":"US",
    "sg:address":"1764 Lonesome",
    "sg:city":"Canyon Lake",
    "sg:classifiers":[
        {
            "category":"Building & Trades",
            "subcategory":"Plumbing",
            "type":"Services"
        }
    ],
    "sg:phone":"+1 830 964 4477",
    "sg:postcode":"78133",
    "sg:province":"TX",
    "sg:tags":[
        "plumbing",
        "contractor"
    ],
    "wof:name":"Don's Plumbing",
    "wof:placetype":"venue"
},
  "geometry": {"coordinates":[-98.226731,29.934746],"type":"Point"}
}