{
  "type": "Feature",
  "properties": {
    "iso:country":"US",
    "sg:address":"208 E Main St",
    "sg:city":"Crowley",
    "sg:classifiers":[
        {
            "category":"Retail",
            "subcategory":"Repair Shop",
            "type":"Services"
        }
    ],
    "sg:phone":"+1 817 297 2111",
    "sg:postcode":"76036",
    "sg:province":"TX",
    "wof:name":"Lewis TV Service",
    "wof:placetype":"venue"
},
  "geometry": {"coordinates":[-97.358159,32.578391],"type":"Point"}
}