{
  "type": "Feature",
  "properties": {
    "iso:country":"US",
    "sg:address":"1513 E Lawrence St",
    "sg:city":"Tyler",
    "sg:classifiers":[
        {
            "category":"Building & Trades",
            "subcategory":"Construction",
            "type":"Services"
        }
    ],
    "sg:phone":"+1 903 597 1740",
    "sg:postcode":"75702",
    "sg:province":"TX",
    "sg:tags":[
        "house"
    ],
    "wof:name":"JV Remodeling",
    "wof:placetype":"venue"
},
  "geometry": {"coordinates":[-95.28359399999999,32.345066],"type":"Point"}
}