{
  "type": "Feature",
  "properties": {
    "iso:country":"US",
    "sg:address":"3211 Old Hwy 105 W",
    "sg:city":"Conroe",
    "sg:classifiers":[
        {
            "category":"Professional",
            "subcategory":"Business Services",
            "type":"Services"
        }
    ],
    "sg:phone":"+1 936 588 1306",
    "sg:postcode":"77304",
    "sg:province":"TX",
    "wof:name":"All Things Imaginable",
    "wof:placetype":"venue"
},
  "geometry": {"coordinates":[-95.563191,30.338508],"type":"Point"}
}