{
  "type": "Feature",
  "properties": {
    "iso:country":"US",
    "sg:address":"826 Kramer Lane",
    "sg:city":"Austin",
    "sg:classifiers":[
        {
            "category":"Retail",
            "subcategory":"Auto Repair",
            "type":"Services"
        }
    ],
    "sg:phone":"+1 512 836 1990",
    "sg:postcode":"78758",
    "sg:province":"TX",
    "sg:tags":[
        "brake",
        "truck"
    ],
    "wof:name":"Donco Truck & Automotive",
    "wof:placetype":"venue"
},
  "geometry": {"coordinates":[-97.688806,30.380217],"type":"Point"}
}