{
  "type": "Feature",
  "properties": {
    "iso:country":"US",
    "sg:address":"4022 Grapevine St",
    "sg:city":"Houston",
    "sg:classifiers":[
        {
            "category":"Insurance",
            "subcategory":"Insurance Agent",
            "type":"Services"
        }
    ],
    "sg:phone":"+1 713 413 8691",
    "sg:postcode":"77045",
    "sg:province":"TX",
    "wof:name":"Lady G Insurance",
    "wof:placetype":"venue"
},
  "geometry": {"coordinates":[-95.438249,29.61667],"type":"Point"}
}