{
  "type": "Feature",
  "properties": {
    "iso:country":"US",
    "sg:address":"18011 Glenledi Dr",
    "sg:city":"Houston",
    "sg:classifiers":[
        {
            "category":"Professional",
            "type":"Services"
        }
    ],
    "sg:phone":"+1 281 858 6600",
    "sg:postcode":"77084",
    "sg:province":"TX",
    "wof:name":"Ceiling Savers",
    "wof:placetype":"venue"
},
  "geometry": {"coordinates":[-95.675369,29.853136],"type":"Point"}
}