{
  "type": "Feature",
  "properties": {
    "iso:country":"US",
    "sg:address":"6502 Mesa Dr",
    "sg:city":"Austin",
    "sg:classifiers":[
        {
            "category":"Professional",
            "subcategory":"Accounting & Tax Preparation",
            "type":"Services"
        }
    ],
    "sg:phone":"+1 512 231 0252",
    "sg:postcode":"78731",
    "sg:province":"TX",
    "sg:tags":[
        "accountant"
    ],
    "sg:website":"www.taxhelp.net",
    "wof:name":"Taxhelp LLC",
    "wof:placetype":"venue"
},
  "geometry": {"coordinates":[-97.77112,30.353796],"type":"Point"}
}