{
  "type": "Feature",
  "properties": {
    "iso:country":"US",
    "sg:address":"1021 Lakeridge Ct",
    "sg:city":"Colleyville",
    "sg:classifiers":[
        {
            "category":"Professional",
            "subcategory":"Business Services",
            "type":"Services"
        }
    ],
    "sg:phone":"+1 817 283 8110",
    "sg:postcode":"76034",
    "sg:province":"TX",
    "sg:tags":[
        "interior",
        "consultant",
        "design",
        "decorator"
    ],
    "sg:website":"www.designgroup.net",
    "wof:name":"Design Group",
    "wof:placetype":"venue"
},
  "geometry": {"coordinates":[-97.15251600000001,32.875988],"type":"Point"}
}