{
  "type": "Feature",
  "properties": {
    "iso:country":"US",
    "sg:address":"2101 San Sebastian Ct",
    "sg:city":"Houston",
    "sg:classifiers":[
        {
            "category":"Freight",
            "type":"Transportation"
        }
    ],
    "sg:phone":"+1 281 333 4224",
    "sg:postcode":"77058",
    "sg:province":"TX",
    "sg:tags":[
        "operator",
        "local",
        "trucking"
    ],
    "wof:name":"Always Moving",
    "wof:placetype":"venue"
},
  "geometry": {"coordinates":[-95.086736,29.546913],"type":"Point"}
}