{
  "type": "Feature",
  "properties": {
    "iso:country":"US",
    "sg:address":"1005 Georgia Ave",
    "sg:city":"Deer Park",
    "sg:classifiers":[
        {
            "category":"Manufacturing",
            "subcategory":"Tools & Machinery",
            "type":"Manufacturing & Wholesale Goods"
        }
    ],
    "sg:phone":"+1 281 478 4040",
    "sg:postcode":"77536",
    "sg:province":"TX",
    "sg:tags":[
        "turbine"
    ],
    "sg:website":"www.turbomachinery.com",
    "wof:name":"H B Turbo",
    "wof:placetype":"venue"
},
  "geometry": {"coordinates":[-95.134981,29.702501],"type":"Point"}
}