{
  "type": "Feature",
  "properties": {
    "iso:country":"US",
    "sg:address":"7323 Dale Rd",
    "sg:city":"El Paso",
    "sg:classifiers":[
        {
            "category":"Wholesale",
            "subcategory":"Groceries",
            "type":"Manufacturing & Wholesale Goods"
        }
    ],
    "sg:phone":"+1 915 779 3656",
    "sg:postcode":"79915",
    "sg:province":"TX",
    "wof:name":"Chile Chipotle",
    "wof:placetype":"venue"
},
  "geometry": {"coordinates":[-106.377673,31.750967],"type":"Point"}
}