{
  "type": "Feature",
  "properties": {
    "iso:country":"US",
    "sg:address":"205 S Timberland Dr",
    "sg:city":"Lufkin",
    "sg:classifiers":[
        {
            "category":"Restaurant",
            "type":"Food & Drink"
        }
    ],
    "sg:menulink":"http://www.allmenus.com/tx/lufkin/177153-kfc---kentucky-fried-chicken/menu/",
    "sg:phone":"+1 409 634 9414",
    "sg:postcode":"75901",
    "sg:province":"TX",
    "sg:tags":[
        "american",
        "chicken"
    ],
    "wof:name":"KFC - Kentucky Fried Chicken",
    "wof:placetype":"venue"
},
  "geometry": {"coordinates":[-94.71926999999999,31.334439],"type":"Point"}
}