{
  "type": "Feature",
  "properties": {
    "iso:country":"US",
    "sg:address":"705 Ellen Trout Dr",
    "sg:city":"Lufkin",
    "sg:classifiers":[
        {
            "category":"Social Services",
            "type":"Services"
        }
    ],
    "sg:phone":"+1 936 634 8367",
    "sg:postcode":"75904",
    "sg:province":"TX",
    "sg:tags":[
        "probation"
    ],
    "wof:name":"Probation Officer-Juvenile",
    "wof:placetype":"venue"
},
  "geometry": {"coordinates":[-94.718052,31.372638],"type":"Point"}
}