{
  "type": "Feature",
  "properties": {
    "iso:country":"US",
    "sg:address":"1004 N 10th St",
    "sg:city":"Mcallen",
    "sg:classifiers":[
        {
            "category":"Personal",
            "subcategory":"Beauty Salon",
            "type":"Services"
        }
    ],
    "sg:phone":"+1 956 631 3700",
    "sg:postcode":"78501",
    "sg:province":"TX",
    "sg:tags":[
        "shop"
    ],
    "wof:name":"Hair Sentral",
    "wof:placetype":"venue"
},
  "geometry": {"coordinates":[-98.228261,26.213295],"type":"Point"}
}