{
  "type": "Feature",
  "properties": {
    "iso:country":"US",
    "sg:address":"4501 N McColl Rd",
    "sg:city":"Mcallen",
    "sg:classifiers":[
        {
            "category":"Organizations",
            "subcategory":"Religious Organization",
            "type":"Services"
        }
    ],
    "sg:phone":"+1 956 686 6382",
    "sg:postcode":"78504",
    "sg:province":"TX",
    "wof:name":"Christian Radio",
    "wof:placetype":"venue"
},
  "geometry": {"coordinates":[-98.20553200000001,26.244168],"type":"Point"}
}