{
  "type": "Feature",
  "properties": {
    "iso:country":"US",
    "sg:address":"2609 Johnson Ave",
    "sg:city":"San Angelo",
    "sg:classifiers":[
        {
            "category":"Shopping",
            "subcategory":"Books",
            "type":"Retail Goods"
        }
    ],
    "sg:phone":"+1 325 949 3350",
    "sg:postcode":"76904",
    "sg:province":"TX",
    "sg:tags":[
        "dealer"
    ],
    "wof:name":"Mary-Martha Christian Book Str",
    "wof:placetype":"venue"
},
  "geometry": {"coordinates":[-100.46311900000001,31.433341],"type":"Point"}
}