{
  "type": "Feature",
  "properties": {
    "iso:country":"US",
    "sg:address":"413 E Homan Ave",
    "sg:city":"Baytown",
    "sg:classifiers":[
        {
            "category":"Wholesale",
            "subcategory":"Poultry",
            "type":"Manufacturing & Wholesale Goods"
        }
    ],
    "sg:phone":"+1 281 422 8871",
    "sg:postcode":"77520",
    "sg:province":"TX",
    "wof:name":"Baytown Poultry Co",
    "wof:placetype":"venue"
},
  "geometry": {"coordinates":[-94.959135,29.746315],"type":"Point"}
}