{
  "type": "Feature",
  "properties": {
    "iso:country":"US",
    "sg:address":"3034 Beacon Field Dr",
    "sg:city":"San Antonio",
    "sg:classifiers":[
        {
            "category":"Manufacturing",
            "subcategory":"Watercraft",
            "type":"Manufacturing & Wholesale Goods"
        }
    ],
    "sg:phone":"+1 210 675 6914",
    "sg:postcode":"78245",
    "sg:province":"TX",
    "wof:name":"Paulas Arts & Crafts",
    "wof:placetype":"venue"
},
  "geometry": {"coordinates":[-98.694333,29.397605],"type":"Point"}
}