{
  "type": "Feature",
  "properties": {
    "iso:country":"US",
    "sg:address":"7408 Bay Chase Dr",
    "sg:city":"Arlington",
    "sg:classifiers":[
        {
            "category":"Professional",
            "type":"Services"
        }
    ],
    "sg:phone":"+1 817 561 0346",
    "sg:postcode":"76016",
    "sg:province":"TX",
    "wof:name":"Aims Worldwide Inc",
    "wof:placetype":"venue"
},
  "geometry": {"coordinates":[-97.225678,32.677162],"type":"Point"}
}