{
  "type": "Feature",
  "properties": {
    "iso:country":"US",
    "sg:address":"3223 Spencer Hwy",
    "sg:city":"Pasadena",
    "sg:classifiers":[
        {
            "category":"Restaurant",
            "type":"Food & Drink"
        }
    ],
    "sg:menulink":"http://www.allmenus.com/tx/pasadena/202451-mcdonalds/menu/",
    "sg:postcode":"77504",
    "sg:province":"TX",
    "sg:tags":[
        "burger",
        "american"
    ],
    "wof:name":"McDonald's",
    "wof:placetype":"venue"
},
  "geometry": {"coordinates":[-95.194118,29.665526],"type":"Point"}
}