{
  "type": "Feature",
  "properties": {
    "iso:country":"US",
    "sg:address":"14131 Midway Rd",
    "sg:city":"Addison",
    "sg:classifiers":[
        {
            "category":"Personal",
            "subcategory":"Beauty Salon",
            "type":"Services"
        }
    ],
    "sg:phone":"+1 972 490 3435",
    "sg:postcode":"75001",
    "sg:province":"TX",
    "wof:name":"Randy Richards Salon & Spa",
    "wof:placetype":"venue"
},
  "geometry": {"coordinates":[-96.839052,32.942057],"type":"Point"}
}