{
  "type": "Feature",
  "properties": {
    "iso:country":"US",
    "sg:address":"134 Spring Branch Dr",
    "sg:city":"Kyle",
    "sg:classifiers":[
        {
            "category":"Building & Trades",
            "subcategory":"Construction",
            "type":"Services"
        }
    ],
    "sg:phone":"+1 512 262 6400",
    "sg:postcode":"78640",
    "sg:province":"TX",
    "sg:tags":[
        "house"
    ],
    "wof:name":"Centex Homes Spring Branch",
    "wof:placetype":"venue"
},
  "geometry": {"coordinates":[-97.87735000000001,30.001655],"type":"Point"}
}