{
  "type": "Feature",
  "properties": {
    "iso:country":"US",
    "sg:address":"6800 N Lamar Boulevard",
    "sg:city":"Austin",
    "sg:classifiers":[
        {
            "category":"Real Estate",
            "subcategory":"Real Estate Services",
            "type":"Services"
        }
    ],
    "sg:phone":"+1 512 533 9777",
    "sg:postcode":"78752",
    "sg:province":"TX",
    "sg:tags":[
        "management",
        "property"
    ],
    "wof:name":"Yom Kerry S",
    "wof:placetype":"venue"
},
  "geometry": {"coordinates":[-97.701404,30.325687],"type":"Point"}
}