{
  "type": "Feature",
  "properties": {
    "iso:country":"US",
    "sg:address":"3121 NE 28th St",
    "sg:city":"Fort Worth",
    "sg:classifiers":[
        {
            "category":"Retail",
            "subcategory":"Auto Repair",
            "type":"Services"
        }
    ],
    "sg:phone":"+1 817 834 4877",
    "sg:postcode":"76111",
    "sg:province":"TX",
    "sg:tags":[
        "automotive"
    ],
    "wof:name":"Alliance Towing & Recovery",
    "wof:placetype":"venue"
},
  "geometry": {"coordinates":[-97.30131299999999,32.795059],"type":"Point"}
}