{
  "type": "Feature",
  "properties": {
    "iso:country":"US",
    "sg:address":"12209 Twin Creeks Rd",
    "sg:city":"Manchaca",
    "sg:classifiers":[
        {
            "category":"Manufacturing",
            "subcategory":"Signs",
            "type":"Manufacturing & Wholesale Goods"
        }
    ],
    "sg:phone":"+1 512 292 7446",
    "sg:postcode":"78652",
    "sg:province":"TX",
    "sg:tags":[
        "specialty",
        "mfg"
    ],
    "wof:name":"Shelton Signs",
    "wof:placetype":"venue"
},
  "geometry": {"coordinates":[-97.82843699999999,30.139496],"type":"Point"}
}