{
  "type": "Feature",
  "properties": {
    "iso:country":"US",
    "sg:address":"125 W Lubbock St",
    "sg:city":"Slaton",
    "sg:classifiers":[
        {
            "category":"Shopping",
            "subcategory":"Pharmacy",
            "type":"Retail Goods"
        }
    ],
    "sg:phone":"+1 806 828 1100",
    "sg:postcode":"79364",
    "sg:province":"TX",
    "wof:name":"Family Pharmacy",
    "wof:placetype":"venue"
},
  "geometry": {"coordinates":[-101.64283500000001,33.436822],"type":"Point"}
}