{
  "type": "Feature",
  "properties": {
    "iso:country":"US",
    "sg:address":"248 Memorial City Way",
    "sg:city":"Houston",
    "sg:classifiers":[
        {
            "category":"Shopping",
            "subcategory":"Optical Goods",
            "type":"Retail Goods"
        }
    ],
    "sg:phone":"+1 713 468 6648",
    "sg:postcode":"77024",
    "sg:province":"TX",
    "wof:name":"Eyemasters",
    "wof:placetype":"venue"
},
  "geometry": {"coordinates":[-95.53583500000001,29.778874],"type":"Point"}
}