{
  "type": "Feature",
  "properties": {
    "iso:country":"US",
    "sg:address":"1212 4th St",
    "sg:city":"Ingleside",
    "sg:classifiers":[
        {
            "category":"Organizations",
            "subcategory":"Religious Organization",
            "type":"Services"
        }
    ],
    "sg:phone":"+1 361 776 3076",
    "sg:postcode":"78362",
    "sg:province":"TX",
    "wof:name":"Ingelside Christian Fellowship",
    "wof:placetype":"venue"
},
  "geometry": {"coordinates":[-97.183528,27.859045],"type":"Point"}
}