{
  "type": "Feature",
  "properties": {
    "iso:country":"US",
    "sg:address":"2229 Hanley St",
    "sg:city":"Odessa",
    "sg:classifiers":[
        {
            "category":"Manufacturing",
            "subcategory":"Lumber",
            "type":"Manufacturing & Wholesale Goods"
        }
    ],
    "sg:phone":"+1 432 550 4835",
    "sg:postcode":"79762",
    "sg:province":"TX",
    "sg:tags":[
        "hardwood",
        "mill",
        "wood",
        "mfg",
        "structural"
    ],
    "wof:name":"J & S Grips Inc",
    "wof:placetype":"venue"
},
  "geometry": {"coordinates":[-102.354587,31.897271],"type":"Point"}
}