{
  "type": "Feature",
  "properties": {
    "iso:country":"US",
    "sg:address":"7028 Seth Barwise St",
    "sg:city":"Fort Worth",
    "sg:classifiers":[
        {
            "category":"Shopping",
            "subcategory":"Discount & Variety Stores",
            "type":"Retail Goods"
        }
    ],
    "sg:phone":"+1 817 237 1419",
    "sg:postcode":"76179",
    "sg:province":"TX",
    "sg:tags":[
        "merchandise",
        "general"
    ],
    "wof:name":"K Stacy Creative Photography",
    "wof:placetype":"venue"
},
  "geometry": {"coordinates":[-97.415779,32.862806],"type":"Point"}
}