{
  "type": "Feature",
  "properties": {
    "iso:country":"US",
    "sg:address":"500 Chicon St",
    "sg:city":"Austin",
    "sg:classifiers":[
        {
            "category":"Professional",
            "subcategory":"Art Services",
            "type":"Services"
        }
    ],
    "sg:phone":"+1 512 476 7733",
    "sg:postcode":"78702",
    "sg:province":"TX",
    "sg:tags":[
        "environmental",
        "graphic",
        "design",
        "advertising"
    ],
    "wof:name":"F D 2 S",
    "wof:placetype":"venue"
},
  "geometry": {"coordinates":[-97.72251199999999,30.261694],"type":"Point"}
}