{
  "type": "Feature",
  "properties": {
    "iso:country":"US",
    "sg:address":"221 Baker Rd",
    "sg:city":"Houston",
    "sg:classifiers":[
        {
            "category":"Autos & Motor Vehicles",
            "subcategory":"Auto Supplies",
            "type":"Retail Goods"
        }
    ],
    "sg:phone":"+1 281 599 9966",
    "sg:postcode":"77094",
    "sg:province":"TX",
    "sg:tags":[
        "automobile",
        "stereo",
        "radio"
    ],
    "wof:name":"Cold Forged Customs",
    "wof:placetype":"venue"
},
  "geometry": {"coordinates":[-95.701852,29.783019],"type":"Point"}
}