{
  "type": "Feature",
  "properties": {
    "iso:country":"US",
    "sg:address":"1705 Elizabeth Dr",
    "sg:city":"Carrollton",
    "sg:classifiers":[
        {
            "category":"Building & Trades",
            "subcategory":"Cleaning & Sanitation",
            "type":"Services"
        }
    ],
    "sg:phone":"+1 972 492 5779",
    "sg:postcode":"75007",
    "sg:province":"TX",
    "sg:tags":[
        "janitor"
    ],
    "wof:name":"JPH Building Maintenance",
    "wof:placetype":"venue"
},
  "geometry": {"coordinates":[-96.897571,33.010645],"type":"Point"}
}