{
  "type": "Feature",
  "properties": {
    "iso:country":"US",
    "sg:address":"770 S Post Oak Ln",
    "sg:city":"Houston",
    "sg:classifiers":[
        {
            "category":"Professional",
            "subcategory":"Accounting & Tax Preparation",
            "type":"Services"
        }
    ],
    "sg:phone":"+1 713 621 9833",
    "sg:postcode":"77056",
    "sg:province":"TX",
    "wof:name":"Margaret E McConn",
    "wof:placetype":"venue"
},
  "geometry": {"coordinates":[-95.46339399999999,29.760956],"type":"Point"}
}