{
  "type": "Feature",
  "properties": {
    "iso:country":"US",
    "sg:address":"2502 Justina Ct",
    "sg:city":"Sugar Land",
    "sg:classifiers":[
        {
            "category":"Professional",
            "subcategory":"Management & Consulting",
            "type":"Services"
        }
    ],
    "sg:phone":"+1 281 325 1093",
    "sg:postcode":"77478",
    "sg:province":"TX",
    "sg:tags":[
        "public",
        "relations"
    ],
    "wof:name":"PM Promotions",
    "wof:placetype":"venue"
},
  "geometry": {"coordinates":[-95.582489,29.58572],"type":"Point"}
}