{
  "type": "Feature",
  "properties": {
    "iso:country":"US",
    "sg:address":"9101 Chancellor Row",
    "sg:city":"Dallas",
    "sg:classifiers":[
        {
            "category":"Wholesale",
            "subcategory":"Construction Materials",
            "type":"Manufacturing & Wholesale Goods"
        }
    ],
    "sg:phone":"+1 214 688 9000",
    "sg:postcode":"75247",
    "sg:province":"TX",
    "wof:name":"United Building Products Inc",
    "wof:placetype":"venue"
},
  "geometry": {"coordinates":[-96.889032,32.819592],"type":"Point"}
}