{
  "type": "Feature",
  "properties": {
    "iso:country":"US",
    "sg:address":"3215 Celeste Dr",
    "sg:city":"Edinburg",
    "sg:classifiers":[
        {
            "category":"Retail",
            "subcategory":"Car Wash",
            "type":"Services"
        }
    ],
    "sg:phone":"+1 956 787 0603",
    "sg:postcode":"78539",
    "sg:province":"TX",
    "sg:tags":[
        "automobile",
        "detail",
        "clean"
    ],
    "wof:name":"Absolute Detailing",
    "wof:placetype":"venue"
},
  "geometry": {"coordinates":[-98.16671700000001,26.269387],"type":"Point"}
}