{
  "type": "Feature",
  "properties": {
    "iso:country":"US",
    "sg:address":"2116 Thompson Rd",
    "sg:city":"Richmond",
    "sg:classifiers":[
        {
            "category":"Professional",
            "subcategory":"Lawyer & Legal Services",
            "type":"Services"
        }
    ],
    "sg:phone":"+1 281 342 5655",
    "sg:postcode":"77469",
    "sg:province":"TX",
    "sg:tags":[
        "attorney"
    ],
    "wof:name":"Richard F Knipling",
    "wof:placetype":"venue"
},
  "geometry": {"coordinates":[-95.760867,29.565329],"type":"Point"}
}