{
  "type": "Feature",
  "properties": {
    "iso:country":"US",
    "sg:address":"520 S Shoreline Blvd",
    "sg:city":"Corpus Christi",
    "sg:classifiers":[
        {
            "category":"Restaurant",
            "type":"Food & Drink"
        }
    ],
    "sg:menulink":"http://www.allmenus.com/tx/corpus-christi/164179-wienerschnitzel/menu/",
    "sg:phone":"+1 361 881 9122",
    "sg:postcode":"78401",
    "sg:province":"TX",
    "sg:tags":[
        "sandwich",
        "dog",
        "burger",
        "hot",
        "wrap",
        "american"
    ],
    "wof:name":"Wienerschnitzel",
    "wof:placetype":"venue"
},
  "geometry": {"coordinates":[-97.393191,27.78751],"type":"Point"}
}