{
  "type": "Feature",
  "properties": {
    "iso:country":"US",
    "sg:address":"15910 FM 529",
    "sg:city":"Houston",
    "sg:classifiers":[
        {
            "category":"Real Estate",
            "subcategory":"Real Estate Operator",
            "type":"Services"
        }
    ],
    "sg:phone":"+1 281 859 0870",
    "sg:postcode":"77095",
    "sg:province":"TX",
    "sg:tags":[
        "building",
        "apartment"
    ],
    "wof:name":"Copper Mill Apartments",
    "wof:placetype":"venue"
},
  "geometry": {"coordinates":[-95.65019100000001,29.879223],"type":"Point"}
}