{
  "type": "Feature",
  "properties": {
    "iso:country":"US",
    "sg:address":"1058 E Austin St",
    "sg:city":"Giddings",
    "sg:classifiers":[
        {
            "category":"Restaurant",
            "type":"Food & Drink"
        }
    ],
    "sg:phone":"+1 979 542 0845",
    "sg:postcode":"78942",
    "sg:province":"TX",
    "wof:name":"Jambalaya's Restaurant",
    "wof:placetype":"venue"
},
  "geometry": {"coordinates":[-96.927612,30.181044],"type":"Point"}
}