{
  "type": "Feature",
  "properties": {
    "iso:country":"US",
    "sg:address":"407 W Baker Rd",
    "sg:city":"Baytown",
    "sg:classifiers":[
        {
            "category":"Banks & Credit Unions",
            "subcategory":"Bank",
            "type":"Services"
        }
    ],
    "sg:phone":"+1 281 425 6967",
    "sg:postcode":"77521",
    "sg:province":"TX",
    "sg:tags":[
        "broker",
        "mortgage"
    ],
    "wof:name":"American Fdral Rsidential Mrtg",
    "wof:placetype":"venue"
},
  "geometry": {"coordinates":[-94.967331,29.769859],"type":"Point"}
}