{
  "type": "Feature",
  "properties": {
    "iso:country":"US",
    "sg:address":"402 N Houston St",
    "sg:city":"Bullard",
    "sg:classifiers":[
        {
            "category":"Building & Trades",
            "subcategory":"Construction",
            "type":"Services"
        }
    ],
    "sg:phone":"+1 903 894 3274",
    "sg:postcode":"75757",
    "sg:province":"TX",
    "sg:tags":[
        "home",
        "builder"
    ],
    "wof:name":"C & L Custom Homes",
    "wof:placetype":"venue"
},
  "geometry": {"coordinates":[-95.32364200000001,32.142517],"type":"Point"}
}