{
  "type": "Feature",
  "properties": {
    "iso:country":"US",
    "sg:address":"6024 Denton Hwy",
    "sg:city":"Fort Worth",
    "sg:classifiers":[
        {
            "category":"Restaurant",
            "type":"Food & Drink"
        }
    ],
    "sg:phone":"+1 817 281 8780",
    "sg:postcode":"76148",
    "sg:province":"TX",
    "sg:tags":[
        "eating"
    ],
    "wof:name":"Joe's Pizza & Pasta",
    "wof:placetype":"venue"
},
  "geometry": {"coordinates":[-97.264028,32.855981],"type":"Point"}
}