{
  "type": "Feature",
  "properties": {
    "iso:country":"US",
    "sg:address":"309 N Water St",
    "sg:city":"Corpus Christi",
    "sg:classifiers":[
        {
            "category":"Professional",
            "type":"Services"
        },
        {
            "category":"Shopping",
            "type":"Retail Goods"
        }
    ],
    "sg:phone":"+1 361 882 4822",
    "sg:postcode":"78401",
    "sg:province":"TX",
    "sg:tags":[
        "art",
        "gallery",
        "dealer"
    ],
    "wof:name":"Cherokee Accents",
    "wof:placetype":"venue"
},
  "geometry": {"coordinates":[-97.39319999999999,27.794798],"type":"Point"}
}