{
  "type": "Feature",
  "properties": {
    "iso:country":"US",
    "sg:address":"7220 Duffield Dr",
    "sg:city":"Dallas",
    "sg:classifiers":[
        {
            "category":"Freight",
            "type":"Transportation"
        }
    ],
    "sg:phone":"+1 972 407 8314",
    "sg:postcode":"75248",
    "sg:province":"TX",
    "wof:name":"My Ride Transportation Service",
    "wof:placetype":"venue"
},
  "geometry": {"coordinates":[-96.790453,32.987043],"type":"Point"}
}