{
  "type": "Feature",
  "properties": {
    "iso:country":"US",
    "sg:address":"23527 Verngate Dr",
    "sg:city":"Spring",
    "sg:classifiers":[
        {
            "category":"Building & Trades",
            "subcategory":"Construction",
            "type":"Services"
        }
    ],
    "sg:phone":"+1 713 869 4113",
    "sg:postcode":"77373",
    "sg:province":"TX",
    "sg:tags":[
        "woodworker"
    ],
    "wof:name":"Barry's Woodshop",
    "wof:placetype":"venue"
},
  "geometry": {"coordinates":[-95.372106,30.047327],"type":"Point"}
}