{
  "type": "Feature",
  "properties": {
    "iso:country":"US",
    "sg:address":"305 N Magnolia Ave",
    "sg:city":"Hubbard",
    "sg:classifiers":[
        {
            "category":"Retail",
            "subcategory":"Repair Shop",
            "type":"Services"
        }
    ],
    "sg:phone":"+1 254 576 1279",
    "sg:postcode":"76648",
    "sg:province":"TX",
    "wof:name":"Scotts Antiques & Refinishing",
    "wof:placetype":"venue"
},
  "geometry": {"coordinates":[-96.797352,31.848148],"type":"Point"}
}