{
  "type": "Feature",
  "properties": {
    "iso:country":"US",
    "sg:address":"316 S Main St",
    "sg:city":"Mcallen",
    "sg:classifiers":[
        {
            "category":"Professional",
            "subcategory":"Business Services",
            "type":"Services"
        }
    ],
    "sg:phone":"+1 956 972 1955",
    "sg:postcode":"78501",
    "sg:province":"TX",
    "wof:name":"Sign Express",
    "wof:placetype":"venue"
},
  "geometry": {"coordinates":[-98.235103,26.200651],"type":"Point"}
}