{
  "type": "Feature",
  "properties": {
    "iso:country":"US",
    "sg:address":"809 Pinnacle Cir",
    "sg:city":"Lewisville",
    "sg:classifiers":[
        {
            "category":"Real Estate",
            "subcategory":"Real Estate Agent",
            "type":"Services"
        }
    ],
    "sg:phone":"+1 972 221 1459",
    "sg:postcode":"75077",
    "sg:province":"TX",
    "wof:name":"Remax Allegiance",
    "wof:placetype":"venue"
},
  "geometry": {"coordinates":[-97.01606200000001,33.052176],"type":"Point"}
}