{
  "type": "Feature",
  "properties": {
    "iso:country":"US",
    "sg:address":"7510 Oak Village Dr",
    "sg:city":"Humble",
    "sg:classifiers":[
        {
            "category":"Building & Trades",
            "subcategory":"Construction",
            "type":"Services"
        }
    ],
    "sg:phone":"+1 281 441 1495",
    "sg:postcode":"77396",
    "sg:province":"TX",
    "sg:tags":[
        "contractor"
    ],
    "wof:name":"Pierce Pressure Washing",
    "wof:placetype":"venue"
},
  "geometry": {"coordinates":[-95.273708,29.935634],"type":"Point"}
}