{
  "type": "Feature",
  "properties": {
    "iso:country":"US",
    "sg:address":"24814 Kuykendahl Rd",
    "sg:city":"Tomball",
    "sg:classifiers":[
        {
            "category":"Retail",
            "subcategory":"Laundry & Dry Cleaning",
            "type":"Services"
        }
    ],
    "sg:phone":"+1 281 357 0331",
    "sg:postcode":"77375",
    "sg:province":"TX",
    "sg:tags":[
        "drycleaning",
        "plant"
    ],
    "wof:name":"Vo Mastercleaners",
    "wof:placetype":"venue"
},
  "geometry": {"coordinates":[-95.55431,30.120402],"type":"Point"}
}