{
  "type": "Feature",
  "properties": {
    "iso:country":"US",
    "sg:address":"19723 Powerscourt Dr",
    "sg:city":"Humble",
    "sg:classifiers":[
        {
            "category":"Professional",
            "subcategory":"Computer Services",
            "type":"Services"
        }
    ],
    "sg:phone":"+1 281 852 7487",
    "sg:postcode":"77346",
    "sg:province":"TX",
    "sg:tags":[
        "information",
        "consul",
        "technology",
        "related"
    ],
    "wof:name":"Castillo & Associates",
    "wof:placetype":"venue"
},
  "geometry": {"coordinates":[-95.165879,30.003519],"type":"Point"}
}