{
  "type": "Feature",
  "properties": {
    "iso:country":"US",
    "sg:address":"7133 Reed Rd",
    "sg:city":"Houston",
    "sg:classifiers":[
        {
            "category":"Restaurant",
            "type":"Food & Drink"
        }
    ],
    "sg:phone":"+1 713 641 2379",
    "sg:postcode":"77087",
    "sg:province":"TX",
    "sg:tags":[
        "eating"
    ],
    "wof:name":"B Mac Enterprises",
    "wof:placetype":"venue"
},
  "geometry": {"coordinates":[-95.300094,29.667081],"type":"Point"}
}