{
  "type": "Feature",
  "properties": {
    "iso:country":"US",
    "sg:address":"7501 E Hwy 290",
    "sg:city":"Austin",
    "sg:classifiers":[
        {
            "category":"Professional",
            "type":"Services"
        }
    ],
    "sg:phone":"+1 512 382 4747",
    "sg:postcode":"78723",
    "sg:province":"TX",
    "sg:tags":[
        "establishment"
    ],
    "wof:name":"Warenty Gold",
    "wof:placetype":"venue"
},
  "geometry": {"coordinates":[-97.67509099999999,30.324348],"type":"Point"}
}