{
  "type": "Feature",
  "properties": {
    "iso:country":"US",
    "sg:address":"13552 N US Hwy 183",
    "sg:city":"Austin",
    "sg:classifiers":[
        {
            "category":"Insurance",
            "subcategory":"Insurance Agent",
            "type":"Services"
        }
    ],
    "sg:phone":"+1 512 257 2602",
    "sg:postcode":"78750",
    "sg:province":"TX",
    "wof:name":"Jason Moyer Insurance",
    "wof:placetype":"venue"
},
  "geometry": {"coordinates":[-97.79126100000001,30.450488],"type":"Point"}
}