{
  "type": "Feature",
  "properties": {
    "iso:country":"US",
    "sg:address":"1819 Creole Dr",
    "sg:city":"Austin",
    "sg:classifiers":[
        {
            "category":"Manufacturing",
            "subcategory":"Signs",
            "type":"Manufacturing & Wholesale Goods"
        }
    ],
    "sg:phone":"+1 512 238 6774",
    "sg:postcode":"78727",
    "sg:province":"TX",
    "sg:tags":[
        "school",
        "specialty",
        "language",
        "mfg"
    ],
    "wof:name":"Tot Signs",
    "wof:placetype":"venue"
},
  "geometry": {"coordinates":[-97.68511700000001,30.424948],"type":"Point"}
}