{
  "type": "Feature",
  "properties": {
    "iso:country":"US",
    "sg:address":"5426 Meadow Creek Dr",
    "sg:city":"Dallas",
    "sg:classifiers":[
        {
            "category":"Professional",
            "type":"Services"
        }
    ],
    "sg:phone":"+1 972 503 3919",
    "sg:postcode":"75248",
    "sg:province":"TX",
    "sg:tags":[
        "arts",
        "artist"
    ],
    "wof:name":"Atelier D'Art",
    "wof:placetype":"venue"
},
  "geometry": {"coordinates":[-96.791916,32.95962],"type":"Point"}
}