{
  "type": "Feature",
  "properties": {
    "iso:country":"US",
    "sg:address":"12230 Southwest Fwy",
    "sg:city":"Stafford",
    "sg:classifiers":[
        {
            "category":"Autos & Motor Vehicles",
            "subcategory":"Automobile Sales",
            "type":"Retail Goods"
        }
    ],
    "sg:phone":"+1 281 243 1915",
    "sg:postcode":"77477",
    "sg:province":"TX",
    "sg:tags":[
        "new",
        "car"
    ],
    "sg:website":"http://www.advantagebmw.com",
    "wof:name":"Advantage B M W",
    "wof:placetype":"venue"
},
  "geometry": {"coordinates":[-95.57511100000001,29.64563],"type":"Point"}
}