{
  "type": "Feature",
  "properties": {
    "iso:country":"US",
    "sg:address":"400 Chisholm Pl",
    "sg:city":"Plano",
    "sg:classifiers":[
        {
            "category":"Professional",
            "subcategory":"Lawyer & Legal Services",
            "type":"Services"
        }
    ],
    "sg:phone":"+1 972 423 4518",
    "sg:postcode":"75075",
    "sg:province":"TX",
    "sg:tags":[
        "attorney"
    ],
    "wof:name":"Grubbs & Goeller",
    "wof:placetype":"venue"
},
  "geometry": {"coordinates":[-96.712583,33.027896],"type":"Point"}
}