{
  "type": "Feature",
  "properties": {
    "iso:country":"US",
    "sg:address":"4701 N Galloway Ave Ste 108",
    "sg:city":"Mesquite",
    "sg:classifiers":[
        {
            "category":"Personal",
            "subcategory":"Nail Salon",
            "type":"Services"
        }
    ],
    "sg:phone":"+1 972 270 7466",
    "sg:postcode":"75150",
    "sg:province":"TX",
    "wof:name":"Van Nails",
    "wof:placetype":"venue"
},
  "geometry": {"coordinates":[-96.626209,32.826988],"type":"Point"}
}