{
  "type": "Feature",
  "properties": {
    "iso:country":"US",
    "sg:address":"11220 Grader St",
    "sg:city":"Dallas",
    "sg:classifiers":[
        {
            "category":"Building & Trades",
            "subcategory":"Construction",
            "type":"Services"
        }
    ],
    "sg:phone":"+1 214 221 2016",
    "sg:postcode":"75238",
    "sg:province":"TX",
    "sg:tags":[
        "general",
        "contractor"
    ],
    "wof:name":"Image Teknique",
    "wof:placetype":"venue"
},
  "geometry": {"coordinates":[-96.683312,32.885861],"type":"Point"}
}