{
  "type": "Feature",
  "properties": {
    "iso:country":"US",
    "sg:address":"245 Pine Cone Ln",
    "sg:city":"Lufkin",
    "sg:classifiers":[
        {
            "category":"Building & Trades",
            "subcategory":"Construction",
            "type":"Services"
        }
    ],
    "sg:phone":"+1 936 634 2267",
    "sg:postcode":"75901",
    "sg:province":"TX",
    "sg:tags":[
        "contractor"
    ],
    "wof:name":"Texas Premier Roofing",
    "wof:placetype":"venue"
},
  "geometry": {"coordinates":[-94.644178,31.339625],"type":"Point"}
}