{
  "type": "Feature",
  "properties": {
    "iso:country":"US",
    "sg:address":"1111 Montana Ave",
    "sg:city":"El Paso",
    "sg:classifiers":[
        {
            "category":"Professional",
            "subcategory":"Accounting & Tax Preparation",
            "type":"Services"
        }
    ],
    "sg:phone":"+1 915 542 1693",
    "sg:postcode":"79902",
    "sg:province":"TX",
    "sg:tags":[
        "accountant"
    ],
    "wof:name":"Oscar Ornelas CPA",
    "wof:placetype":"venue"
},
  "geometry": {"coordinates":[-106.482794,31.769645],"type":"Point"}
}