{
  "type": "Feature",
  "properties": {
    "iso:country":"US",
    "sg:address":"2 Tamarind Pl",
    "sg:city":"Spring",
    "sg:classifiers":[
        {
            "category":"Professional",
            "subcategory":"Management & Consulting",
            "type":"Services"
        }
    ],
    "sg:phone":"+1 281 363 2822",
    "sg:postcode":"77381",
    "sg:province":"TX",
    "sg:tags":[
        "marketing",
        "consultant"
    ],
    "wof:name":"Interact Marketing",
    "wof:placetype":"venue"
},
  "geometry": {"coordinates":[-95.520746,30.166719],"type":"Point"}
}