{
  "type": "Feature",
  "properties": {
    "iso:country":"US",
    "sg:address":"15901 S Post Oak Rd",
    "sg:city":"Houston",
    "sg:classifiers":[
        {
            "category":"Restaurant",
            "type":"Food & Drink"
        }
    ],
    "sg:phone":"+1 281 835 5209",
    "sg:postcode":"77053",
    "sg:province":"TX",
    "wof:name":"Subway Sandwiches & Salads",
    "wof:placetype":"venue"
},
  "geometry": {"coordinates":[-95.467102,29.594999],"type":"Point"}
}