{
  "type": "Feature",
  "properties": {
    "iso:country":"US",
    "sg:address":"2332 Beaumont St",
    "sg:city":"Fort Worth",
    "sg:classifiers":[
        {
            "category":"Shopping",
            "subcategory":"Discount & Variety Stores",
            "type":"Retail Goods"
        }
    ],
    "sg:phone":"+1 817 740 0365",
    "sg:postcode":"76106",
    "sg:province":"TX",
    "sg:tags":[
        "merchandise",
        "general"
    ],
    "wof:name":"Dollar Store Y Mas",
    "wof:placetype":"venue"
},
  "geometry": {"coordinates":[-97.325687,32.814315],"type":"Point"}
}