{
  "type": "Feature",
  "properties": {
    "iso:country":"US",
    "sg:address":"2042 Lexington Woods Dr",
    "sg:city":"Spring",
    "sg:classifiers":[
        {
            "category":"Wholesale",
            "subcategory":"Vending Machines",
            "type":"Manufacturing & Wholesale Goods"
        }
    ],
    "sg:phone":"+1 281 350 3875",
    "sg:postcode":"77373",
    "sg:province":"TX",
    "sg:tags":[
        "operator"
    ],
    "wof:name":"Creations By Cathy",
    "wof:placetype":"venue"
},
  "geometry": {"coordinates":[-95.40928599999999,30.076983],"type":"Point"}
}