{
  "type": "Feature",
  "properties": {
    "iso:country":"US",
    "sg:address":"508 S Washington Ave",
    "sg:city":"Marshall",
    "sg:classifiers":[
        {
            "category":"Restaurant",
            "type":"Food & Drink"
        }
    ],
    "sg:phone":"+1 903 935 9434",
    "sg:postcode":"75670",
    "sg:province":"TX",
    "sg:tags":[
        "caterer"
    ],
    "wof:name":"Reese Reed's At Your Svc",
    "wof:placetype":"venue"
},
  "geometry": {"coordinates":[-94.367503,32.541415],"type":"Point"}
}