{
  "type": "Feature",
  "properties": {
    "iso:country":"US",
    "sg:address":"7003 Oak Ln",
    "sg:city":"Richmond",
    "sg:classifiers":[
        {
            "category":"Building & Trades",
            "subcategory":"Construction",
            "type":"Services"
        }
    ],
    "sg:phone":"+1 281 346 0095",
    "sg:postcode":"77469",
    "sg:province":"TX",
    "sg:tags":[
        "contractor"
    ],
    "wof:name":"Wages Construction Co",
    "wof:placetype":"venue"
},
  "geometry": {"coordinates":[-95.87381499999999,29.663143],"type":"Point"}
}