{
  "type": "Feature",
  "properties": {
    "iso:country":"US",
    "sg:address":"518 River Walk St",
    "sg:city":"San Antonio",
    "sg:classifiers":[
        {
            "category":"Food & Beverages",
            "subcategory":"Groceries & Convenience Stores",
            "type":"Retail Goods"
        }
    ],
    "sg:phone":"+1 210 224 2128",
    "sg:postcode":"78205",
    "sg:province":"TX",
    "sg:tags":[
        "product"
    ],
    "wof:name":"Texan Accent General Store",
    "wof:placetype":"venue"
},
  "geometry": {"coordinates":[-98.491536,29.423529],"type":"Point"}
}