{
  "type": "Feature",
  "properties": {
    "iso:country":"US",
    "sg:address":"3019 Orchard Hill",
    "sg:city":"San Antonio",
    "sg:classifiers":[
        {
            "category":"Restaurant",
            "type":"Food & Drink"
        }
    ],
    "sg:phone":"+1 210 492 0071",
    "sg:postcode":"78230",
    "sg:province":"TX",
    "sg:tags":[
        "eating"
    ],
    "wof:name":"Joy Luck Inc",
    "wof:placetype":"venue"
},
  "geometry": {"coordinates":[-98.543503,29.55962],"type":"Point"}
}