{
  "type": "Feature",
  "properties": {
    "iso:country":"US",
    "sg:address":"4500 Amon Carter Blvd",
    "sg:city":"Fort Worth",
    "sg:classifiers":[
        {
            "category":"Professional",
            "subcategory":"Business Services",
            "type":"Services"
        }
    ],
    "sg:phone":"+1 817 258 8212",
    "sg:postcode":"76155",
    "sg:province":"TX",
    "sg:tags":[
        "credit",
        "card"
    ],
    "wof:name":"Capital One Services Inc",
    "wof:placetype":"venue"
},
  "geometry": {"coordinates":[-97.049359,32.830461],"type":"Point"}
}