{
  "type": "Feature",
  "properties": {
    "iso:country":"US",
    "sg:address":"1104 N 16th St",
    "sg:city":"Orange",
    "sg:classifiers":[
        {
            "category":"Banks & Credit Unions",
            "subcategory":"Bank",
            "type":"Services"
        }
    ],
    "sg:phone":"+1 409 886 1077",
    "sg:postcode":"77630",
    "sg:province":"TX",
    "sg:tags":[
        "loan"
    ],
    "wof:name":"Sun Loan Co",
    "wof:placetype":"venue"
},
  "geometry": {"coordinates":[-93.747102,30.100373],"type":"Point"}
}