{
  "type": "Feature",
  "properties": {
    "iso:country":"US",
    "sg:address":"3000 S Country Club Rd",
    "sg:city":"Garland",
    "sg:classifiers":[
        {
            "category":"Sports & Exercise",
            "subcategory":"Golf",
            "type":"Entertainment"
        }
    ],
    "sg:phone":"+1 972 271 4876",
    "sg:postcode":"75043",
    "sg:province":"TX",
    "sg:website":"www.easternhillscc.com",
    "wof:name":"Eastern Hills Country Club",
    "wof:placetype":"venue"
},
  "geometry": {"coordinates":[-96.604797,32.879902],"type":"Point"}
}