{
  "type": "Feature",
  "properties": {
    "iso:country":"US",
    "sg:address":"1705 S 11th St",
    "sg:city":"Abilene",
    "sg:classifiers":[
        {
            "category":"Organizations",
            "subcategory":"Religious Organization",
            "type":"Services"
        }
    ],
    "sg:phone":"+1 325 672 7265",
    "sg:postcode":"79602",
    "sg:province":"TX",
    "wof:name":"Shining Star Fellowship Church",
    "wof:placetype":"venue"
},
  "geometry": {"coordinates":[-99.744355,32.437266],"type":"Point"}
}