{
  "type": "Feature",
  "properties": {
    "iso:country":"US",
    "sg:address":"1800 Lawrence St",
    "sg:city":"Gainesville",
    "sg:classifiers":[
        {
            "category":"Restaurant",
            "type":"Food & Drink"
        }
    ],
    "sg:menulink":"http://www.allmenus.com/tx/gainesville/130493-subway/menu/",
    "sg:phone":"+1 940 668 6400",
    "sg:postcode":"76240",
    "sg:province":"TX",
    "sg:tags":[
        "american",
        "sandwich"
    ],
    "wof:name":"Subway",
    "wof:placetype":"venue"
},
  "geometry": {"coordinates":[-97.137215,33.641355],"type":"Point"}
}