{
  "type": "Feature",
  "properties": {
    "iso:country":"US",
    "sg:address":"2 Royal Dalton Cir",
    "sg:city":"Conroe",
    "sg:classifiers":[
        {
            "category":"Professional",
            "subcategory":"Business Services",
            "type":"Services"
        }
    ],
    "sg:phone":"+1 936 756 4705",
    "sg:postcode":"77304",
    "sg:province":"TX",
    "wof:name":"Kim Caywood Interior Design",
    "wof:placetype":"venue"
},
  "geometry": {"coordinates":[-95.51632499999999,30.347908],"type":"Point"}
}