{
  "type": "Feature",
  "properties": {
    "iso:country":"US",
    "sg:address":"3129 Hwy 67",
    "sg:city":"Mesquite",
    "sg:classifiers":[
        {
            "category":"Building & Trades",
            "subcategory":"Cleaning & Sanitation",
            "type":"Services"
        }
    ],
    "sg:phone":"+1 972 682 0691",
    "sg:postcode":"75150",
    "sg:province":"TX",
    "sg:tags":[
        "house"
    ],
    "wof:name":"Merry Maids Inc",
    "wof:placetype":"venue"
},
  "geometry": {"coordinates":[-96.647391,32.814108],"type":"Point"}
}