{
  "type": "Feature",
  "properties": {
    "iso:country":"US",
    "sg:address":"4701 Maple Shade Ave",
    "sg:city":"Garland",
    "sg:classifiers":[
        {
            "category":"Building & Trades",
            "subcategory":"Construction",
            "type":"Services"
        }
    ],
    "sg:phone":"+1 972 414 5558",
    "sg:postcode":"75048",
    "sg:province":"TX",
    "sg:tags":[
        "home",
        "builder"
    ],
    "wof:name":"Santi Homes",
    "wof:placetype":"venue"
},
  "geometry": {"coordinates":[-96.58165700000001,32.963197],"type":"Point"}
}