{
  "type": "Feature",
  "properties": {
    "iso:country":"US",
    "sg:address":"107 E Colorado St",
    "sg:city":"Palestine",
    "sg:classifiers":[
        {
            "category":"Health Services",
            "subcategory":"Doctor",
            "type":"Services"
        }
    ],
    "sg:phone":"+1 903 729 1442",
    "sg:postcode":"75801",
    "sg:province":"TX",
    "sg:tags":[
        "dentist"
    ],
    "wof:name":"C L Kolstad III Inc",
    "wof:placetype":"venue"
},
  "geometry": {"coordinates":[-95.62801399999999,31.752482],"type":"Point"}
}