{
  "type": "Feature",
  "properties": {
    "iso:country":"US",
    "sg:address":"3304 Houston Hwy",
    "sg:city":"Victoria",
    "sg:classifiers":[
        {
            "category":"Mining & Drilling",
            "type":"Manufacturing & Wholesale Goods"
        }
    ],
    "sg:phone":"+1 361 575 0249",
    "sg:postcode":"77901",
    "sg:province":"TX",
    "sg:tags":[
        "field",
        "oil"
    ],
    "wof:name":"Stuart Petroleum Testers Inc",
    "wof:placetype":"venue"
},
  "geometry": {"coordinates":[-96.96978300000001,28.814054],"type":"Point"}
}