{
  "type": "Feature",
  "properties": {
    "iso:country":"US",
    "sg:address":"434 Edward Dr",
    "sg:city":"Dublin",
    "sg:classifiers":[
        {
            "category":"Freight",
            "type":"Transportation"
        }
    ],
    "sg:phone":"+1 254 445 2584",
    "sg:postcode":"76446",
    "sg:province":"TX",
    "sg:tags":[
        "operator",
        "local",
        "trucking"
    ],
    "wof:name":"B&B Trucking",
    "wof:placetype":"venue"
},
  "geometry": {"coordinates":[-98.332984,32.097904],"type":"Point"}
}