{
  "type": "Feature",
  "properties": {
    "iso:country":"US",
    "sg:address":"3246 Co Rd 205",
    "sg:city":"Mc Kinney",
    "sg:classifiers":[
        {
            "category":"Retail",
            "subcategory":"Auto Repair",
            "type":"Services"
        }
    ],
    "sg:phone":"+1 972 838 9035",
    "sg:postcode":"75071",
    "sg:province":"TX",
    "sg:tags":[
        "repairing",
        "automobile"
    ],
    "wof:name":"Auto Barn",
    "wof:placetype":"venue"
},
  "geometry": {"coordinates":[-96.64713999999999,33.305071],"type":"Point"}
}