{
  "type": "Feature",
  "properties": {
    "iso:country":"US",
    "sg:address":"12790 S Dairy Ashford St",
    "sg:city":"Houston",
    "sg:classifiers":[
        {
            "category":"Food & Beverages",
            "subcategory":"Groceries & Convenience Stores",
            "type":"Retail Goods"
        }
    ],
    "sg:phone":"+1 281 879 9310",
    "sg:postcode":"77099",
    "sg:province":"TX",
    "wof:name":"Encore Petroleum",
    "wof:placetype":"venue"
},
  "geometry": {"coordinates":[-95.597915,29.661134],"type":"Point"}
}