{
  "type": "Feature",
  "properties": {
    "iso:country":"US",
    "sg:address":"2551 I- 35 Svc Rd",
    "sg:city":"Round Rock",
    "sg:classifiers":[
        {
            "category":"Home & Garden",
            "subcategory":"Building Materials",
            "type":"Retail Goods"
        }
    ],
    "sg:phone":"+1 512 238 0820",
    "sg:postcode":"78664",
    "sg:province":"TX",
    "sg:tags":[
        "center"
    ],
    "sg:website":"www.homedepot.com",
    "wof:name":"Home Depot",
    "wof:placetype":"venue"
},
  "geometry": {"coordinates":[-97.69163399999999,30.537788],"type":"Point"}
}