{
  "type": "Feature",
  "properties": {
    "iso:country":"US",
    "sg:address":"989 W Sandy Lake Rd Ste 500",
    "sg:city":"Coppell",
    "sg:classifiers":[
        {
            "category":"Shopping",
            "subcategory":"Clothing, Apparel, & Fashions",
            "type":"Retail Goods"
        }
    ],
    "sg:phone":"+1 972 956 8161",
    "sg:postcode":"75019",
    "sg:province":"TX",
    "sg:tags":[
        "accessory",
        "clothing",
        "women's"
    ],
    "sg:website":"www.campuscouture.com",
    "wof:name":"Campus Couture",
    "wof:placetype":"venue"
},
  "geometry": {"coordinates":[-96.960595,32.969268],"type":"Point"}
}