{
  "type": "Feature",
  "properties": {
    "iso:country":"US",
    "sg:address":"600 Main St",
    "sg:city":"Richmond",
    "sg:classifiers":[
        {
            "category":"Government",
            "subcategory":"Office",
            "type":"Public Place"
        }
    ],
    "sg:phone":"+1 281 342 8582",
    "sg:postcode":"77469",
    "sg:province":"TX",
    "sg:tags":[
        "federal"
    ],
    "wof:name":"Natural Resources Conservation",
    "wof:placetype":"venue"
},
  "geometry": {"coordinates":[-95.76195300000001,29.579303],"type":"Point"}
}