{
  "type": "Feature",
  "properties": {
    "iso:country":"US",
    "sg:address":"2415 N Krenek Rd",
    "sg:city":"Crosby",
    "sg:classifiers":[
        {
            "category":"Shopping",
            "subcategory":"Jewelry",
            "type":"Retail Goods"
        }
    ],
    "sg:phone":"+1 281 328 6277",
    "sg:postcode":"77532",
    "sg:province":"TX",
    "wof:name":"Jens Jewels",
    "wof:placetype":"venue"
},
  "geometry": {"coordinates":[-95.028662,29.901795],"type":"Point"}
}