{
  "type": "Feature",
  "properties": {
    "iso:country":"US",
    "sg:address":"6201 Bonhomme Rd",
    "sg:city":"Houston",
    "sg:classifiers":[
        {
            "category":"Banks & Credit Unions",
            "subcategory":"Financial Services",
            "type":"Services"
        }
    ],
    "sg:phone":"+1 713 785 5550",
    "sg:postcode":"77036",
    "sg:province":"TX",
    "sg:tags":[
        "broker",
        "mortgage"
    ],
    "wof:name":"Fortunate Mortgage",
    "wof:placetype":"venue"
},
  "geometry": {"coordinates":[-95.513603,29.712],"type":"Point"}
}