{
  "type": "Feature",
  "properties": {
    "iso:country":"US",
    "sg:address":"8335 W Little York Rd",
    "sg:city":"Houston",
    "sg:classifiers":[
        {
            "category":"Organizations",
            "subcategory":"Religious Organization",
            "type":"Services"
        }
    ],
    "sg:phone":"+1 713 462 4813",
    "sg:postcode":"77040",
    "sg:province":"TX",
    "wof:name":"Little York Church of Christ",
    "wof:placetype":"venue"
},
  "geometry": {"coordinates":[-95.522301,29.8654],"type":"Point"}
}