{
  "type": "Feature",
  "properties": {
    "iso:country":"US",
    "sg:address":"7407 Christie Ln",
    "sg:city":"Dallas",
    "sg:classifiers":[
        {
            "category":"Building & Trades",
            "subcategory":"Construction",
            "type":"Services"
        }
    ],
    "sg:phone":"+1 972 296 8971",
    "sg:postcode":"75249",
    "sg:province":"TX",
    "sg:tags":[
        "house"
    ],
    "wof:name":"Homecrafters Construction",
    "wof:placetype":"venue"
},
  "geometry": {"coordinates":[-96.95231,32.64451],"type":"Point"}
}