{
  "type": "Feature",
  "properties": {
    "iso:country":"US",
    "sg:address":"505 N Velasco Blvd",
    "sg:city":"Freeport",
    "sg:classifiers":[
        {
            "category":"Shopping",
            "subcategory":"Florist",
            "type":"Retail Goods"
        }
    ],
    "sg:phone":"+1 979 265 7376",
    "sg:postcode":"77541",
    "sg:province":"TX",
    "wof:name":"Angelton Flower & Gift",
    "wof:placetype":"venue"
},
  "geometry": {"coordinates":[-95.355558,28.960531],"type":"Point"}
}