{
  "type": "Feature",
  "properties": {
    "iso:country":"US",
    "sg:address":"2304 Wysteria St",
    "sg:city":"Mission",
    "sg:classifiers":[
        {
            "category":"Shopping",
            "type":"Retail Goods"
        }
    ],
    "sg:phone":"+1 956 580 4153",
    "sg:postcode":"78574",
    "sg:province":"TX",
    "sg:tags":[
        "merchandise"
    ],
    "wof:name":"Edwina Doffing",
    "wof:placetype":"venue"
},
  "geometry": {"coordinates":[-98.293464,26.226905],"type":"Point"}
}