{
  "type": "Feature",
  "properties": {
    "iso:country":"US",
    "sg:address":"1118 W Bow St",
    "sg:city":"Tyler",
    "sg:classifiers":[
        {
            "category":"Personal",
            "subcategory":"Barber",
            "type":"Services"
        }
    ],
    "sg:phone":"+1 903 596 7080",
    "sg:postcode":"75702",
    "sg:province":"TX",
    "sg:tags":[
        "shop"
    ],
    "wof:name":"Freestyle Barber Shop",
    "wof:placetype":"venue"
},
  "geometry": {"coordinates":[-95.313405,32.358476],"type":"Point"}
}