{
  "type": "Feature",
  "properties": {
    "iso:country":"US",
    "sg:address":"3605 NE Loop 286",
    "sg:city":"Paris",
    "sg:classifiers":[
        {
            "category":"Communications",
            "subcategory":"Radio Station",
            "type":"Services"
        }
    ],
    "sg:phone":"+1 903 784 6952",
    "sg:postcode":"75460",
    "sg:province":"TX",
    "sg:tags":[
        "company",
        "broadcasting"
    ],
    "wof:name":"KITX",
    "wof:placetype":"venue"
},
  "geometry": {"coordinates":[-95.510463,33.664913],"type":"Point"}
}