{
  "type": "Feature",
  "properties": {
    "iso:country":"US",
    "sg:address":"4800 Broadway St",
    "sg:city":"Addison",
    "sg:classifiers":[
        {
            "category":"Real Estate",
            "subcategory":"Real Estate Agent",
            "type":"Services"
        }
    ],
    "sg:phone":"+1 972 380 9989",
    "sg:postcode":"75001",
    "sg:province":"TX",
    "wof:name":"Home Value Plus",
    "wof:placetype":"venue"
},
  "geometry": {"coordinates":[-96.828442,32.959047],"type":"Point"}
}