{
  "type": "Feature",
  "properties": {
    "iso:country":"US",
    "sg:address":"8102 Beverlyhill St",
    "sg:city":"Houston",
    "sg:classifiers":[
        {
            "category":"Shopping",
            "subcategory":"Jewelry",
            "type":"Retail Goods"
        }
    ],
    "sg:phone":"+1 713 952 3451",
    "sg:postcode":"77063",
    "sg:province":"TX",
    "wof:name":"Jewelry & Fine Accents",
    "wof:placetype":"venue"
},
  "geometry": {"coordinates":[-95.510424,29.730347],"type":"Point"}
}