{
  "type": "Feature",
  "properties": {
    "iso:country":"US",
    "sg:address":"1420 E Fremont St",
    "sg:city":"Laredo",
    "sg:classifiers":[
        {
            "category":"Professional",
            "type":"Services"
        }
    ],
    "sg:phone":"+1 956 791 3581",
    "sg:postcode":"78040",
    "sg:province":"TX",
    "sg:tags":[
        "establishment"
    ],
    "wof:name":"Santa Rita Inc",
    "wof:placetype":"venue"
},
  "geometry": {"coordinates":[-99.481589,27.513981],"type":"Point"}
}