{
  "type": "Feature",
  "properties": {
    "iso:country":"US",
    "sg:address":"210 Co Rd 107",
    "sg:city":"Gatesville",
    "sg:classifiers":[
        {
            "category":"Building & Trades",
            "subcategory":"Plumbing",
            "type":"Services"
        }
    ],
    "sg:phone":"+1 254 223 0604",
    "sg:postcode":"76528",
    "sg:province":"TX",
    "sg:tags":[
        "ac",
        "installation"
    ],
    "wof:name":"Muegge Air Conditioning",
    "wof:placetype":"venue"
},
  "geometry": {"coordinates":[-97.88363099999999,31.542745],"type":"Point"}
}