{
  "type": "Feature",
  "properties": {
    "iso:country":"US",
    "sg:address":"115 W West St",
    "sg:city":"Livingston",
    "sg:classifiers":[
        {
            "category":"Organizations",
            "subcategory":"Religious Organization",
            "type":"Services"
        }
    ],
    "sg:phone":"+1 936 327 5385",
    "sg:postcode":"77351",
    "sg:province":"TX",
    "sg:tags":[
        "church"
    ],
    "wof:name":"St Luke's United Methodist Chr",
    "wof:placetype":"venue"
},
  "geometry": {"coordinates":[-94.93377099999999,30.720887],"type":"Point"}
}