{
  "type": "Feature",
  "properties": {
    "iso:country":"US",
    "sg:address":"3 Village Way",
    "sg:city":"Roanoke",
    "sg:classifiers":[
        {
            "category":"Professional",
            "subcategory":"Business Services",
            "type":"Services"
        }
    ],
    "sg:phone":"+1 817 430 0212",
    "sg:postcode":"76262",
    "sg:province":"TX",
    "sg:tags":[
        "bus"
    ],
    "wof:name":"Solana Education Center",
    "wof:placetype":"venue"
},
  "geometry": {"coordinates":[-97.18030299999999,32.993888],"type":"Point"}
}