{
  "type": "Feature",
  "properties": {
    "iso:country":"US",
    "sg:address":"309 W Oak St",
    "sg:city":"Denton",
    "sg:classifiers":[
        {
            "category":"Building & Trades",
            "subcategory":"Plumbing",
            "type":"Services"
        }
    ],
    "sg:phone":"+1 940 387 1780",
    "sg:postcode":"76201",
    "sg:province":"TX",
    "sg:tags":[
        "contractor",
        "system",
        "air conditioning"
    ],
    "wof:name":"Daniels Air Incorp",
    "wof:placetype":"venue"
},
  "geometry": {"coordinates":[-97.135288,33.215619],"type":"Point"}
}