{
  "type": "Feature",
  "properties": {
    "iso:country":"US",
    "sg:address":"20206 White Poplar Dr",
    "sg:city":"Katy",
    "sg:classifiers":[
        {
            "category":"Building & Trades",
            "subcategory":"Pest Control",
            "type":"Services"
        }
    ],
    "sg:phone":"+1 281 829 5756",
    "sg:postcode":"77449",
    "sg:province":"TX",
    "wof:name":"Legend Pest Co Inc",
    "wof:placetype":"venue"
},
  "geometry": {"coordinates":[-95.73295299999999,29.803051],"type":"Point"}
}