{
  "type": "Feature",
  "properties": {
    "iso:country":"US",
    "sg:address":"2020 Altamesa Blvd",
    "sg:city":"Fort Worth",
    "sg:classifiers":[
        {
            "category":"Professional",
            "subcategory":"Business Services",
            "type":"Services"
        }
    ],
    "sg:phone":"+1 817 921 2065",
    "sg:postcode":"76134",
    "sg:province":"TX",
    "wof:name":"Lopez & Lopez Enterprises Inc",
    "wof:placetype":"venue"
},
  "geometry": {"coordinates":[-97.348771,32.648861],"type":"Point"}
}