{
  "type": "Feature",
  "properties": {
    "iso:country":"US",
    "sg:address":"5909 Clovis Ct",
    "sg:city":"Fort Worth",
    "sg:classifiers":[
        {
            "category":"Professional",
            "type":"Services"
        }
    ],
    "sg:phone":"+1 817 514 6228",
    "sg:postcode":"76148",
    "sg:province":"TX",
    "wof:name":"DTR Electronics",
    "wof:placetype":"venue"
},
  "geometry": {"coordinates":[-97.262439,32.854594],"type":"Point"}
}