{
  "type": "Feature",
  "properties": {
    "iso:country":"US",
    "sg:address":"2271 French Settlement Rd",
    "sg:city":"Dallas",
    "sg:classifiers":[
        {
            "category":"Autos & Motor Vehicles",
            "subcategory":"Auto Supplies",
            "type":"Retail Goods"
        }
    ],
    "sg:phone":"+1 214 638 2187",
    "sg:postcode":"75212",
    "sg:province":"TX",
    "wof:name":"Ampack Tire Distribution",
    "wof:placetype":"venue"
},
  "geometry": {"coordinates":[-96.884415,32.772866],"type":"Point"}
}