{
  "type": "Feature",
  "properties": {
    "iso:country":"US",
    "sg:address":"1630 Mistletoe Blvd",
    "sg:city":"Fort Worth",
    "sg:classifiers":[
        {
            "category":"Professional",
            "type":"Services"
        }
    ],
    "sg:phone":"+1 817 927 8561",
    "sg:postcode":"76104",
    "sg:province":"TX",
    "wof:name":"Archival Images",
    "wof:placetype":"venue"
},
  "geometry": {"coordinates":[-97.34551399999999,32.731543],"type":"Point"}
}