{
  "type": "Feature",
  "properties": {
    "iso:country":"US",
    "sg:address":"7624 Smith Dr",
    "sg:city":"Mansfield",
    "sg:classifiers":[
        {
            "category":"Building & Trades",
            "subcategory":"Construction",
            "type":"Services"
        }
    ],
    "sg:phone":"+1 817 477 2806",
    "sg:postcode":"76063",
    "sg:province":"TX",
    "sg:tags":[
        "house"
    ],
    "wof:name":"Jenkins Construction",
    "wof:placetype":"venue"
},
  "geometry": {"coordinates":[-97.19530399999999,32.560561],"type":"Point"}
}