{
  "type": "Feature",
  "properties": {
    "iso:country":"US",
    "sg:address":"12201 Jekel Cir",
    "sg:city":"Austin",
    "sg:classifiers":[
        {
            "category":"Building & Trades",
            "subcategory":"Cleaning & Sanitation",
            "type":"Services"
        }
    ],
    "sg:phone":"+1 512 203 7051",
    "sg:postcode":"78729",
    "sg:province":"TX",
    "sg:tags":[
        "carpet"
    ],
    "sg:website":"www.organiccarpetcare.com",
    "wof:name":"Organic Carpet Care",
    "wof:placetype":"venue"
},
  "geometry": {"coordinates":[-97.762209,30.434781],"type":"Point"}
}