{
  "type": "Feature",
  "properties": {
    "iso:country":"US",
    "sg:address":"810 N 4th St",
    "sg:city":"Silsbee",
    "sg:classifiers":[
        {
            "category":"Professional",
            "subcategory":"Business Services",
            "type":"Services"
        }
    ],
    "sg:phone":"+1 409 385 4783",
    "sg:postcode":"77656",
    "sg:province":"TX",
    "wof:name":"We So & Etc",
    "wof:placetype":"venue"
},
  "geometry": {"coordinates":[-94.17447199999999,30.354895],"type":"Point"}
}