{
  "type": "Feature",
  "properties": {
    "iso:country":"US",
    "sg:address":"2914 SW H K Dodgen Loop",
    "sg:city":"Temple",
    "sg:classifiers":[
        {
            "category":"Home & Garden",
            "subcategory":"Furniture",
            "type":"Retail Goods"
        }
    ],
    "sg:phone":"+1 254 773 7300",
    "sg:postcode":"76504",
    "sg:province":"TX",
    "wof:name":"Unfinished Furniture Outlet",
    "wof:placetype":"venue"
},
  "geometry": {"coordinates":[-97.383168,31.082135],"type":"Point"}
}