{
  "type": "Feature",
  "properties": {
    "iso:country":"US",
    "sg:address":"2235 Richmond Ave",
    "sg:city":"Houston",
    "sg:classifiers":[
        {
            "category":"Shopping",
            "type":"Retail Goods"
        }
    ],
    "sg:phone":"+1 713 521 7235",
    "sg:postcode":"77098",
    "sg:province":"TX",
    "sg:tags":[
        "merchandise"
    ],
    "wof:name":"Emerald Spa",
    "wof:placetype":"venue"
},
  "geometry": {"coordinates":[-95.414427,29.734119],"type":"Point"}
}