{
  "type": "Feature",
  "properties": {
    "iso:country":"US",
    "sg:address":"401 Riverside Dr",
    "sg:city":"Fort Worth",
    "sg:classifiers":[
        {
            "category":"Social Services",
            "type":"Services"
        }
    ],
    "sg:phone":"+1 817 877 1314",
    "sg:postcode":"76111",
    "sg:province":"TX",
    "sg:tags":[
        "health"
    ],
    "wof:name":"Michael Strain Associates",
    "wof:placetype":"venue"
},
  "geometry": {"coordinates":[-97.301723,32.761246],"type":"Point"}
}