{
  "type": "Feature",
  "properties": {
    "iso:country":"US",
    "sg:address":"3706 Palomino Dr",
    "sg:city":"Arlington",
    "sg:classifiers":[
        {
            "category":"Shopping",
            "subcategory":"Florist",
            "type":"Retail Goods"
        }
    ],
    "sg:phone":"+1 817 467 6684",
    "sg:postcode":"76017",
    "sg:province":"TX",
    "wof:name":"Flowers By Dorothy",
    "wof:placetype":"venue"
},
  "geometry": {"coordinates":[-97.166242,32.671763],"type":"Point"}
}