{
  "type": "Feature",
  "properties": {
    "iso:country":"US",
    "sg:address":"503 W 18th Street",
    "sg:city":"Austin",
    "sg:classifiers":[
        {
            "category":"Shopping",
            "subcategory":"Pets & Pet Supplies",
            "type":"Retail Goods"
        },
        {
            "category":"Retail",
            "subcategory":"Veterinary Services",
            "type":"Services"
        },
        {
            "category":"Retail",
            "subcategory":"Animal Services",
            "type":"Services"
        }
    ],
    "sg:phone":"+1 512 472 5879",
    "sg:postcode":"78701",
    "sg:province":"TX",
    "sg:tags":[
        "product",
        "hospital",
        "specialty",
        "clinic",
        "health",
        "veterinarian",
        "store"
    ],
    "sg:website":"www.austinpetdoctor.com/",
    "wof:name":"Abraham Veterinary Clinic",
    "wof:placetype":"venue"
},
  "geometry": {"coordinates":[-97.743217,30.280835],"type":"Point"}
}