{
  "type": "Feature",
  "properties": {
    "iso:country":"US",
    "sg:address":"741 Eagle Lake Ct",
    "sg:city":"Allen",
    "sg:classifiers":[
        {
            "category":"Professional",
            "subcategory":"Computer Services",
            "type":"Services"
        }
    ],
    "sg:phone":"+1 214 923 5848",
    "sg:postcode":"75002",
    "sg:province":"TX",
    "sg:tags":[
        "related"
    ],
    "wof:name":"Mercury Enterprises",
    "wof:placetype":"venue"
},
  "geometry": {"coordinates":[-96.62458100000001,33.087023],"type":"Point"}
}