{
  "type": "Feature",
  "properties": {
    "iso:country":"US",
    "sg:address":"3926 Sacramento Ave",
    "sg:city":"El Paso",
    "sg:classifiers":[
        {
            "category":"Social Services",
            "subcategory":"Child Care",
            "type":"Services"
        }
    ],
    "sg:phone":"+1 915 566 5590",
    "sg:postcode":"79930",
    "sg:province":"TX",
    "sg:tags":[
        "day"
    ],
    "wof:name":"Three AS",
    "wof:placetype":"venue"
},
  "geometry": {"coordinates":[-106.445072,31.802108],"type":"Point"}
}