{
  "type": "Feature",
  "properties": {
    "iso:country":"US",
    "sg:address":"7307 Hundley Blvd",
    "sg:city":"Dallas",
    "sg:classifiers":[
        {
            "category":"Professional",
            "type":"Services"
        }
    ],
    "sg:phone":"+1 214 343 1845",
    "sg:postcode":"75231",
    "sg:province":"TX",
    "wof:name":"Kimberly Stroope Designs",
    "wof:placetype":"venue"
},
  "geometry": {"coordinates":[-96.742664,32.882048],"type":"Point"}
}