{
  "type": "Feature",
  "properties": {
    "iso:country":"US",
    "sg:address":"701 N San Jacinto St",
    "sg:city":"Houston",
    "sg:classifiers":[
        {
            "category":"Government",
            "subcategory":"Jail",
            "type":"Public Place"
        }
    ],
    "sg:phone":"+1 713 755 8430",
    "sg:postcode":"77002",
    "sg:province":"TX",
    "sg:tags":[
        "county",
        "govt",
        "institution"
    ],
    "wof:name":"Harris County Jail Facility",
    "wof:placetype":"venue"
},
  "geometry": {"coordinates":[-95.35700799999999,29.764996],"type":"Point"}
}