{
  "type": "Feature",
  "properties": {
    "iso:country":"US",
    "sg:address":"612 E 16th St",
    "sg:city":"Plano",
    "sg:classifiers":[
        {
            "category":"Real Estate",
            "subcategory":"Architect",
            "type":"Services"
        }
    ],
    "sg:phone":"+1 972 422 5601",
    "sg:postcode":"75074",
    "sg:province":"TX",
    "wof:name":"J L Brantley Inc",
    "wof:placetype":"venue"
},
  "geometry": {"coordinates":[-96.707812,33.021313],"type":"Point"}
}