{
  "type": "Feature",
  "properties": {
    "iso:country":"US",
    "sg:address":"1627 7th St",
    "sg:city":"Bay City",
    "sg:classifiers":[
        {
            "category":"Insurance",
            "subcategory":"Insurance Agent",
            "type":"Services"
        }
    ],
    "sg:phone":"+1 979 245 1194",
    "sg:postcode":"77414",
    "sg:province":"TX",
    "wof:name":"Nalleys Insurance Agency",
    "wof:placetype":"venue"
},
  "geometry": {"coordinates":[-95.970955,28.98305],"type":"Point"}
}