{
  "type": "Feature",
  "properties": {
    "iso:country":"US",
    "sg:address":"5305 Wilmington St",
    "sg:city":"Houston",
    "sg:classifiers":[
        {
            "category":"Government",
            "subcategory":"Office",
            "type":"Public Place"
        }
    ],
    "sg:phone":"+1 713 734 5877",
    "sg:postcode":"77033",
    "sg:province":"TX",
    "sg:tags":[
        "housing",
        "program"
    ],
    "wof:name":"Garden of Gethsemana Hous",
    "wof:placetype":"venue"
},
  "geometry": {"coordinates":[-95.341714,29.655513],"type":"Point"}
}