{
  "type": "Feature",
  "properties": {
    "iso:country":"US",
    "sg:address":"2708 Holmes Rd",
    "sg:city":"Houston",
    "sg:classifiers":[
        {
            "category":"Freight",
            "type":"Transportation"
        }
    ],
    "sg:phone":"+1 713 799 9429",
    "sg:postcode":"77051",
    "sg:province":"TX",
    "sg:tags":[
        "operator",
        "general",
        "local",
        "trucking"
    ],
    "wof:name":"Distribution Specialists Inc",
    "wof:placetype":"venue"
},
  "geometry": {"coordinates":[-95.38709900000001,29.67331],"type":"Point"}
}