{
  "type": "Feature",
  "properties": {
    "iso:country":"US",
    "sg:address":"4422 Lareina Dr",
    "sg:city":"Austin",
    "sg:classifiers":[
        {
            "category":"Restaurant",
            "type":"Food & Drink"
        }
    ],
    "sg:phone":"+1 512 299 7413",
    "sg:postcode":"78798",
    "sg:province":"TX",
    "sg:tags":[
        "flavor",
        "local"
    ],
    "sg:website":"www.roadsideamerica.com/attract/...",
    "wof:name":"Cathedral of Junk",
    "wof:placetype":"venue"
},
  "geometry": {"coordinates":[-97.770865,30.219649],"type":"Point"}
}