{
  "type": "Feature",
  "properties": {
    "iso:country":"US",
    "sg:address":"1717 Yellowstone St",
    "sg:city":"Freeport",
    "sg:classifiers":[
        {
            "category":"Place Of Worship",
            "subcategory":"Church",
            "type":"Public Place"
        },
        {
            "category":"Place Of Worship",
            "type":"Public Place"
        },
        {
            "category":"Organizations",
            "subcategory":"Religious Organization",
            "type":"Services"
        }
    ],
    "sg:phone":"+1 979 233 5123",
    "sg:postcode":"77541",
    "sg:province":"TX",
    "sg:tags":[
        "churches-interdenominational",
        "churches-various",
        "denomination"
    ],
    "wof:name":"Freeport Christian Center",
    "wof:placetype":"venue"
},
  "geometry": {"coordinates":[-95.37394999999999,28.979219],"type":"Point"}
}