{
  "type": "Feature",
  "properties": {
    "iso:country":"US",
    "sg:address":"1501 Merrimac Cir",
    "sg:city":"Fort Worth",
    "sg:classifiers":[
        {
            "category":"Health Services",
            "subcategory":"Health Practitioner",
            "type":"Services"
        }
    ],
    "sg:phone":"+1 817 877 0033",
    "sg:postcode":"76107",
    "sg:province":"TX",
    "sg:tags":[
        "laboratory",
        "psychologist",
        "testing"
    ],
    "wof:name":"Raymond F Finn PHD",
    "wof:placetype":"venue"
},
  "geometry": {"coordinates":[-97.36006399999999,32.728691],"type":"Point"}
}