{
  "type": "Feature",
  "properties": {
    "iso:country":"US",
    "sg:address":"12440 Oxford Park Dr",
    "sg:city":"Houston",
    "sg:classifiers":[
        {
            "category":"Professional",
            "type":"Services"
        }
    ],
    "sg:phone":"+1 281 752 6725",
    "sg:postcode":"77082",
    "sg:province":"TX",
    "sg:tags":[
        "establishment"
    ],
    "wof:name":"CIG LLC",
    "wof:placetype":"venue"
},
  "geometry": {"coordinates":[-95.60062000000001,29.734351],"type":"Point"}
}