{
  "type": "Feature",
  "properties": {
    "iso:country":"US",
    "sg:address":"7015 Echo Lake Ct",
    "sg:city":"Arlington",
    "sg:classifiers":[
        {
            "category":"Shopping",
            "type":"Retail Goods"
        }
    ],
    "sg:phone":"+1 817 466 1717",
    "sg:postcode":"76001",
    "sg:province":"TX",
    "sg:tags":[
        "merchandise"
    ],
    "wof:name":"Ginas Gifts & Awards",
    "wof:placetype":"venue"
},
  "geometry": {"coordinates":[-97.15114,32.630691],"type":"Point"}
}