{
  "type": "Feature",
  "properties": {
    "iso:country":"US",
    "sg:address":"807 Sanders St",
    "sg:city":"Grand Prairie",
    "sg:classifiers":[
        {
            "category":"Professional",
            "subcategory":"Business Services",
            "type":"Services"
        }
    ],
    "sg:phone":"+1 972 571 3034",
    "sg:postcode":"75051",
    "sg:province":"TX",
    "wof:name":"DJM Service Co",
    "wof:placetype":"venue"
},
  "geometry": {"coordinates":[-96.99807300000001,32.735416],"type":"Point"}
}