{
  "type": "Feature",
  "properties": {
    "iso:country":"US",
    "sg:address":"521 N Conway Ave",
    "sg:city":"Mission",
    "sg:classifiers":[
        {
            "category":"Recreation",
            "type":"Entertainment"
        }
    ],
    "sg:phone":"+1 956 585 9006",
    "sg:postcode":"78572",
    "sg:province":"TX",
    "sg:tags":[
        "center"
    ],
    "wof:name":"Mission Recreation Club",
    "wof:placetype":"venue"
},
  "geometry": {"coordinates":[-98.326492,26.211319],"type":"Point"}
}