{
  "type": "Feature",
  "properties": {
    "iso:country":"US",
    "sg:address":"8000 Research Forest Dr",
    "sg:city":"The Woodlands",
    "sg:classifiers":[
        {
            "category":"Professional",
            "subcategory":"Art Services",
            "type":"Services"
        }
    ],
    "sg:phone":"+1 281 300 6261",
    "sg:postcode":"77382",
    "sg:province":"TX",
    "sg:tags":[
        "graphic",
        "designer"
    ],
    "wof:name":"Faithspan",
    "wof:placetype":"venue"
},
  "geometry": {"coordinates":[-95.531043,30.210269],"type":"Point"}
}