{
  "type": "Feature",
  "properties": {
    "iso:country":"US",
    "sg:address":"11002 Bandera Rd",
    "sg:city":"San Antonio",
    "sg:classifiers":[
        {
            "category":"Shopping",
            "type":"Retail Goods"
        },
        {
            "category":"Home & Garden",
            "subcategory":"Garden Supply",
            "type":"Retail Goods"
        }
    ],
    "sg:phone":"+1 210 684 5296",
    "sg:postcode":"78250",
    "sg:province":"TX",
    "sg:tags":[
        "farm",
        "repair",
        "lawn",
        "industrial",
        "mower"
    ],
    "wof:name":"De Winne Equipment Co",
    "wof:placetype":"venue"
},
  "geometry": {"coordinates":[-98.65961299999999,29.545869],"type":"Point"}
}