{
  "type": "Feature",
  "properties": {
    "iso:country":"US",
    "sg:address":"319 Dixie Dr",
    "sg:city":"Bridge City",
    "sg:classifiers":[
        {
            "category":"Freight",
            "type":"Transportation"
        }
    ],
    "sg:phone":"+1 409 735 7088",
    "sg:postcode":"77611",
    "sg:province":"TX",
    "sg:tags":[
        "operator",
        "local",
        "trucking"
    ],
    "wof:name":"C&J Trucking",
    "wof:placetype":"venue"
},
  "geometry": {"coordinates":[-93.840293,30.022959],"type":"Point"}
}