{
  "type": "Feature",
  "properties": {
    "iso:country":"US",
    "sg:address":"11711 Knobcrest Dr",
    "sg:city":"Houston",
    "sg:classifiers":[
        {
            "category":"Professional",
            "subcategory":"Management & Consulting",
            "type":"Services"
        }
    ],
    "sg:phone":"+1 281 370 4461",
    "sg:postcode":"77070",
    "sg:province":"TX",
    "sg:tags":[
        "marketing",
        "advertising"
    ],
    "wof:name":"JW Collins Marketing & Advg",
    "wof:placetype":"venue"
},
  "geometry": {"coordinates":[-95.59630799999999,29.982684],"type":"Point"}
}