{
  "type": "Feature",
  "properties": {
    "iso:country":"US",
    "sg:address":"6700 Shirley Ave",
    "sg:city":"Austin",
    "sg:classifiers":[
        {
            "category":"Autos & Motor Vehicles",
            "subcategory":"Automobile Sales",
            "type":"Retail Goods"
        }
    ],
    "sg:phone":"+1 512 374 0262",
    "sg:postcode":"78752",
    "sg:province":"TX",
    "sg:tags":[
        "used"
    ],
    "wof:name":"Eldridge Auto Sales",
    "wof:placetype":"venue"
},
  "geometry": {"coordinates":[-97.71946,30.334802],"type":"Point"}
}