{
  "type": "Feature",
  "properties": {
    "iso:country":"US",
    "sg:address":"8199 Robertson Dr",
    "sg:city":"Frisco",
    "sg:classifiers":[
        {
            "category":"Real Estate",
            "subcategory":"Real Estate Agent",
            "type":"Services"
        }
    ],
    "sg:phone":"+1 972 668 5722",
    "sg:postcode":"75034",
    "sg:province":"TX",
    "wof:name":"Silvero Group Ultima Real Est",
    "wof:placetype":"venue"
},
  "geometry": {"coordinates":[-96.866759,33.146221],"type":"Point"}
}