{
  "type": "Feature",
  "properties": {
    "iso:country":"US",
    "sg:address":"806 S Dumas Ave",
    "sg:city":"Dumas",
    "sg:classifiers":[
        {
            "category":"Personal",
            "type":"Services"
        },
        {
            "category":"Freight",
            "type":"Transportation"
        },
        {
            "category":"Retail",
            "subcategory":"Storage",
            "type":"Services"
        }
    ],
    "sg:phone":"+1 806 935 2295",
    "sg:postcode":"79029",
    "sg:province":"TX",
    "sg:tags":[
        "household",
        "full",
        "commercial",
        "mover",
        "trucking"
    ],
    "wof:name":"Gene's Transfer & Storage",
    "wof:placetype":"venue"
},
  "geometry": {"coordinates":[-101.97327900000001,35.857241],"type":"Point"}
}