{
  "type": "Feature",
  "properties": {
    "iso:country":"US",
    "sg:address":"2933 S 7th St",
    "sg:city":"Abilene",
    "sg:classifiers":[
        {
            "category":"Education",
            "subcategory":"School",
            "type":"Public Place"
        }
    ],
    "sg:phone":"+1 325 676 8232",
    "sg:postcode":"79605",
    "sg:province":"TX",
    "wof:name":"Cornerstone Christian School",
    "wof:placetype":"venue"
},
  "geometry": {"coordinates":[-99.75887299999999,32.443622],"type":"Point"}
}