{
  "type": "Feature",
  "properties": {
    "iso:country":"US",
    "sg:address":"1406 N Trail Dr",
    "sg:city":"Carrollton",
    "sg:classifiers":[
        {
            "category":"Utilities",
            "subcategory":"Water",
            "type":"Services"
        },
        {
            "category":"Food & Beverages",
            "subcategory":"Liquor & Beverages",
            "type":"Retail Goods"
        }
    ],
    "sg:phone":"+1 972 718 0189",
    "sg:postcode":"75006",
    "sg:province":"TX",
    "sg:tags":[
        "bulk",
        "companies-bottled"
    ],
    "wof:name":"Living Water Irrigation",
    "wof:placetype":"venue"
},
  "geometry": {"coordinates":[-96.903676,32.980392],"type":"Point"}
}