{
  "type": "Feature",
  "properties": {
    "iso:country":"US",
    "sg:address":"2540 K Ave",
    "sg:city":"Plano",
    "sg:classifiers":[
        {
            "category":"Organizations",
            "subcategory":"Religious Organization",
            "type":"Services"
        }
    ],
    "sg:phone":"+1 972 578 1382",
    "sg:postcode":"75074",
    "sg:province":"TX",
    "wof:name":"Fellowship In Christ Church",
    "wof:placetype":"venue"
},
  "geometry": {"coordinates":[-96.69897899999999,33.032002],"type":"Point"}
}