{
  "type": "Feature",
  "properties": {
    "iso:country":"US",
    "sg:address":"10675 South Fwy",
    "sg:city":"Fort Worth",
    "sg:classifiers":[
        {
            "category":"Travel",
            "subcategory":"Hotels & Motels",
            "type":"Entertainment"
        }
    ],
    "sg:phone":"+1 817 551 7000",
    "sg:postcode":"76140",
    "sg:province":"TX",
    "wof:name":"Microtel Inn & Suites",
    "wof:placetype":"venue"
},
  "geometry": {"coordinates":[-97.318703,32.600601],"type":"Point"}
}