{
  "type": "Feature",
  "properties": {
    "iso:country":"US",
    "sg:address":"1033 Choke Cherry Ln",
    "sg:city":"Crowley",
    "sg:classifiers":[
        {
            "category":"Wholesale",
            "subcategory":"Durable Goods & Equipment",
            "type":"Manufacturing & Wholesale Goods"
        }
    ],
    "sg:phone":"+1 817 297 3116",
    "sg:postcode":"76036",
    "sg:province":"TX",
    "sg:tags":[
        "representative",
        "manufacturer"
    ],
    "wof:name":"Service Associates Wire-Cable",
    "wof:placetype":"venue"
},
  "geometry": {"coordinates":[-97.351249,32.56053],"type":"Point"}
}