{
  "type": "Feature",
  "properties": {
    "iso:country":"US",
    "sg:address":"4603 Linden Pl",
    "sg:city":"Pearland",
    "sg:classifiers":[
        {
            "category":"Professional",
            "subcategory":"Secretarial Services",
            "type":"Services"
        }
    ],
    "sg:phone":"+1 713 516 7228",
    "sg:postcode":"77584",
    "sg:province":"TX",
    "sg:tags":[
        "reporting"
    ],
    "wof:name":"Bioscience Writers",
    "wof:placetype":"venue"
},
  "geometry": {"coordinates":[-95.344869,29.549027],"type":"Point"}
}