{
  "type": "Feature",
  "properties": {
    "iso:country":"US",
    "sg:address":"2661 Midway Rd",
    "sg:city":"Carrollton",
    "sg:classifiers":[
        {
            "category":"Personal",
            "subcategory":"Beauty Salon",
            "type":"Services"
        }
    ],
    "sg:phone":"+1 972 931 2696",
    "sg:postcode":"75006",
    "sg:province":"TX",
    "sg:tags":[
        "shop"
    ],
    "wof:name":"Today's Cut",
    "wof:placetype":"venue"
},
  "geometry": {"coordinates":[-96.84227199999999,32.986274],"type":"Point"}
}