{
  "type": "Feature",
  "properties": {
    "iso:country":"US",
    "sg:address":"520 E Central Pkwy",
    "sg:city":"Plano",
    "sg:classifiers":[
        {
            "category":"Banks & Credit Unions",
            "subcategory":"Investment Brokerage",
            "type":"Services"
        }
    ],
    "sg:phone":"+1 972 881 7755",
    "sg:postcode":"75074",
    "sg:province":"TX",
    "sg:tags":[
        "advisory",
        "financial"
    ],
    "wof:name":"Precept Financial Solutions",
    "wof:placetype":"venue"
},
  "geometry": {"coordinates":[-96.708989,33.026161],"type":"Point"}
}