{
  "type": "Feature",
  "properties": {
    "iso:country":"US",
    "sg:address":"1510 Ray St",
    "sg:city":"San Angelo",
    "sg:classifiers":[
        {
            "category":"Recreation",
            "type":"Entertainment"
        }
    ],
    "sg:phone":"+1 325 655 0877",
    "sg:postcode":"76904",
    "sg:province":"TX",
    "sg:tags":[
        "guide"
    ],
    "sg:website":"www.wildlifesystems.com",
    "wof:name":"Wildlife Systems Inc",
    "wof:placetype":"venue"
},
  "geometry": {"coordinates":[-100.456215,31.397281],"type":"Point"}
}