{
  "type": "Feature",
  "properties": {
    "iso:country":"US",
    "sg:address":"6117 Sutherland Dr",
    "sg:city":"Tyler",
    "sg:classifiers":[
        {
            "category":"Organizations",
            "subcategory":"Community Association",
            "type":"Services"
        }
    ],
    "sg:phone":"+1 903 581 6398",
    "sg:postcode":"75703",
    "sg:province":"TX",
    "wof:name":"Landing Place",
    "wof:placetype":"venue"
},
  "geometry": {"coordinates":[-95.30096500000001,32.282629],"type":"Point"}
}