{
  "type": "Feature",
  "properties": {
    "iso:country":"US",
    "sg:address":"2400 Canyon Dr",
    "sg:city":"Amarillo",
    "sg:classifiers":[
        {
            "category":"Autos & Motor Vehicles",
            "subcategory":"Auto Supplies",
            "type":"Retail Goods"
        },
        {
            "category":"Manufacturing",
            "subcategory":"Motor Vehicles & Parts",
            "type":"Manufacturing & Wholesale Goods"
        },
        {
            "category":"Wholesale",
            "subcategory":"Auto Parts",
            "type":"Manufacturing & Wholesale Goods"
        },
        {
            "category":"Retail",
            "subcategory":"Auto Repair",
            "type":"Services"
        }
    ],
    "sg:phone":"+1 806 372 8228",
    "sg:postcode":"79109",
    "sg:province":"TX",
    "sg:tags":[
        "body",
        "shop",
        "automobile",
        "supply-wholesale",
        "equipment",
        "service-equipment",
        "painting",
        "repairing",
        "manufacturer"
    ],
    "wof:name":"Sharps Auto Paint",
    "wof:placetype":"venue"
},
  "geometry": {"coordinates":[-101.838448,35.18745],"type":"Point"}
}