{
  "type": "Feature",
  "properties": {
    "iso:country":"US",
    "sg:address":"1102 N Marshall St",
    "sg:city":"Henderson",
    "sg:classifiers":[
        {
            "category":"Farming",
            "subcategory":"Livestock Farm",
            "type":"Manufacturing & Wholesale Goods"
        }
    ],
    "sg:phone":"+1 903 657 7700",
    "sg:postcode":"75652",
    "sg:province":"TX",
    "sg:tags":[
        "beef",
        "feedlot",
        "cattle"
    ],
    "wof:name":"Three M Farms",
    "wof:placetype":"venue"
},
  "geometry": {"coordinates":[-94.789331,32.168864],"type":"Point"}
}