{
  "type": "Feature",
  "properties": {
    "iso:country":"US",
    "sg:address":"5001 34th St",
    "sg:city":"Lubbock",
    "sg:classifiers":[
        {
            "category":"Restaurant",
            "type":"Food & Drink"
        }
    ],
    "sg:phone":"+1 806 795 9552",
    "sg:postcode":"79410",
    "sg:province":"TX",
    "wof:name":"Amigos Mexican Restaurant",
    "wof:placetype":"venue"
},
  "geometry": {"coordinates":[-101.92025099999999,33.563255],"type":"Point"}
}