{
  "type": "Feature",
  "properties": {
    "iso:country":"US",
    "sg:address":"1314 Hines",
    "sg:city":"San Antonio",
    "sg:classifiers":[
        {
            "category":"Organizations",
            "subcategory":"Community Association",
            "type":"Services"
        }
    ],
    "sg:phone":"+1 210 370 5200",
    "sg:postcode":"78208",
    "sg:province":"TX",
    "sg:tags":[
        "educational"
    ],
    "sg:website":"www.esc20.net",
    "wof:name":"Education Svc Ctr Region 20",
    "wof:placetype":"venue"
},
  "geometry": {"coordinates":[-98.44651399999999,29.441297],"type":"Point"}
}