{
  "type": "Feature",
  "properties": {
    "iso:country":"US",
    "sg:address":"2205 Longmire Dr",
    "sg:city":"College Station",
    "sg:classifiers":[
        {
            "category":"Personal",
            "type":"Services"
        }
    ],
    "sg:phone":"+1 979 695 6565",
    "sg:postcode":"77845",
    "sg:province":"TX",
    "sg:tags":[
        "salon",
        "tanning"
    ],
    "wof:name":"Sun City Tanning",
    "wof:placetype":"venue"
},
  "geometry": {"coordinates":[-96.30171,30.596285],"type":"Point"}
}