{
  "type": "Feature",
  "properties": {
    "iso:country":"US",
    "sg:address":"410 N Oak St",
    "sg:city":"Archer City",
    "sg:classifiers":[
        {
            "category":"Shopping",
            "subcategory":"Hobbies, Toys, & Games",
            "type":"Retail Goods"
        }
    ],
    "sg:phone":"+1 940 574 4931",
    "sg:postcode":"76351",
    "sg:province":"TX",
    "sg:tags":[
        "craft"
    ],
    "wof:name":"Jimmie Dee Crafts",
    "wof:placetype":"venue"
},
  "geometry": {"coordinates":[-98.62594,33.599491],"type":"Point"}
}