{
  "type": "Feature",
  "properties": {
    "iso:country":"US",
    "sg:address":"2501 Lakeview Pkwy",
    "sg:city":"Rowlett",
    "sg:classifiers":[
        {
            "category":"Restaurant",
            "type":"Food & Drink"
        }
    ],
    "sg:phone":"+1 972 412 2195",
    "sg:postcode":"75088",
    "sg:province":"TX",
    "wof:name":"Blimpie Subs & Salads",
    "wof:placetype":"venue"
},
  "geometry": {"coordinates":[-96.578676,32.907849],"type":"Point"}
}