{
  "type": "Feature",
  "properties": {
    "iso:country":"US",
    "sg:address":"400 N Olive St",
    "sg:city":"Dallas",
    "sg:classifiers":[
        {
            "category":"Travel",
            "subcategory":"Hotels & Motels",
            "type":"Entertainment"
        },
        {
            "category":"Retail",
            "subcategory":"Event Space",
            "type":"Services"
        }
    ],
    "sg:phone":"+1 866 716 8134",
    "sg:postcode":"75201",
    "sg:province":"TX",
    "sg:tags":[
        "venue"
    ],
    "sg:website":"www.sheratondallashotel.com",
    "wof:name":"Sheraton Dallas Hotel",
    "wof:placetype":"venue"
},
  "geometry": {"coordinates":[-96.794679,32.784677],"type":"Point"}
}