{
  "type": "Feature",
  "properties": {
    "iso:country":"US",
    "sg:address":"4610 Argonne Dr",
    "sg:city":"San Antonio",
    "sg:classifiers":[
        {
            "category":"Building & Trades",
            "subcategory":"Plumbing",
            "type":"Services"
        }
    ],
    "sg:phone":"+1 210 337 1725",
    "sg:postcode":"78220",
    "sg:province":"TX",
    "sg:tags":[
        "contractor"
    ],
    "wof:name":"ABC Plumbing Service",
    "wof:placetype":"venue"
},
  "geometry": {"coordinates":[-98.401984,29.420937],"type":"Point"}
}