{
  "type": "Feature",
  "properties": {
    "iso:country":"US",
    "sg:address":"794 Featherstone Dr",
    "sg:city":"Rockwall",
    "sg:classifiers":[
        {
            "category":"Manufacturing",
            "subcategory":"Buildings",
            "type":"Manufacturing & Wholesale Goods"
        },
        {
            "category":"Building & Trades",
            "subcategory":"Construction",
            "type":"Services"
        }
    ],
    "sg:phone":"+1 972 961 0249",
    "sg:postcode":"75087",
    "sg:province":"TX",
    "sg:tags":[
        "home",
        "builder",
        "contractor"
    ],
    "wof:name":"Windsor Homes",
    "wof:placetype":"venue"
},
  "geometry": {"coordinates":[-96.462548,32.954832],"type":"Point"}
}