{
  "type": "Feature",
  "properties": {
    "iso:country":"US",
    "sg:address":"7413 Mesa Dr",
    "sg:city":"Houston",
    "sg:classifiers":[
        {
            "category":"Wholesale",
            "subcategory":"Apparel",
            "type":"Manufacturing & Wholesale Goods"
        },
        {
            "category":"Wholesale",
            "subcategory":"Scrap",
            "type":"Manufacturing & Wholesale Goods"
        }
    ],
    "sg:phone":"+1 713 491 0414",
    "sg:postcode":"77028",
    "sg:province":"TX",
    "sg:tags":[
        "rag",
        "export",
        "used",
        "clothing"
    ],
    "wof:name":"American Trading Company",
    "wof:placetype":"venue"
},
  "geometry": {"coordinates":[-95.261999,29.825904],"type":"Point"}
}