{
  "type": "Feature",
  "properties": {
    "iso:country":"US",
    "sg:address":"433 Motley St",
    "sg:city":"Grand Prairie",
    "sg:classifiers":[
        {
            "category":"Building & Trades",
            "subcategory":"Construction",
            "type":"Services"
        }
    ],
    "sg:phone":"+1 972 263 5073",
    "sg:postcode":"75051",
    "sg:province":"TX",
    "sg:tags":[
        "concrete",
        "contractor"
    ],
    "wof:name":"Titos Quality Concrete Work",
    "wof:placetype":"venue"
},
  "geometry": {"coordinates":[-97.008177,32.740704],"type":"Point"}
}