{
  "type": "Feature",
  "properties": {
    "iso:country":"US",
    "sg:address":"3395 del Monte Dr",
    "sg:city":"Houston",
    "sg:classifiers":[
        {
            "category":"Travel",
            "subcategory":"Campground",
            "type":"Entertainment"
        }
    ],
    "sg:phone":"+1 713 522 1639",
    "sg:postcode":"77019",
    "sg:province":"TX",
    "sg:tags":[
        "camp"
    ],
    "wof:name":"American Creek Ranch Ltd",
    "wof:placetype":"venue"
},
  "geometry": {"coordinates":[-95.426723,29.749547],"type":"Point"}
}