{
  "type": "Feature",
  "properties": {
    "iso:country":"US",
    "sg:address":"11402 Chelsea Walk Dr",
    "sg:city":"Houston",
    "sg:classifiers":[
        {
            "category":"Shopping",
            "subcategory":"Discount & Variety Stores",
            "type":"Retail Goods"
        }
    ],
    "sg:phone":"+1 281 586 2097",
    "sg:postcode":"77066",
    "sg:province":"TX",
    "sg:tags":[
        "merchandise",
        "general"
    ],
    "wof:name":"Moon Mart Products",
    "wof:placetype":"venue"
},
  "geometry": {"coordinates":[-95.47739300000001,29.948795],"type":"Point"}
}