{
  "type": "Feature",
  "properties": {
    "iso:country":"US",
    "sg:address":"418 W Chestnut St",
    "sg:city":"Denison",
    "sg:classifiers":[
        {
            "category":"Organizations",
            "subcategory":"Non-profit Organization",
            "type":"Services"
        }
    ],
    "sg:phone":"+1 903 465 5101",
    "sg:postcode":"75020",
    "sg:province":"TX",
    "sg:tags":[
        "human"
    ],
    "sg:website":"www.helping-hands.net",
    "wof:name":"Denison Helping Hands",
    "wof:placetype":"venue"
},
  "geometry": {"coordinates":[-96.541342,33.754465],"type":"Point"}
}