{
  "type": "Feature",
  "properties": {
    "iso:country":"US",
    "sg:address":"2025 Irving Blvd",
    "sg:city":"Dallas",
    "sg:classifiers":[
        {
            "category":"Wholesale",
            "subcategory":"Apparel",
            "type":"Manufacturing & Wholesale Goods"
        }
    ],
    "sg:phone":"+1 214 741 8100",
    "sg:postcode":"75247",
    "sg:province":"TX",
    "sg:tags":[
        "piece",
        "fabric"
    ],
    "wof:name":"Joseph Noble Inc",
    "wof:placetype":"venue"
},
  "geometry": {"coordinates":[-96.829797,32.795315],"type":"Point"}
}