{
  "type": "Feature",
  "properties": {
    "iso:country":"US",
    "sg:address":"7402 Euclid Dr",
    "sg:city":"Rowlett",
    "sg:classifiers":[
        {
            "category":"Professional",
            "subcategory":"Business Services",
            "type":"Services"
        }
    ],
    "sg:phone":"+1 210 670 9200",
    "sg:postcode":"75089",
    "sg:province":"TX",
    "wof:name":"Atlantis Enterprise",
    "wof:placetype":"venue"
},
  "geometry": {"coordinates":[-96.525498,32.926002],"type":"Point"}
}