{
  "type": "Feature",
  "properties": {
    "iso:country":"US",
    "sg:address":"443 Sussex Ave",
    "sg:city":"San Antonio",
    "sg:classifiers":[
        {
            "category":"Personal",
            "subcategory":"Beauty Salon",
            "type":"Services"
        }
    ],
    "sg:phone":"+1 210 921 0372",
    "sg:postcode":"78221",
    "sg:province":"TX",
    "wof:name":"Style Cuts & Perms By Dd",
    "wof:placetype":"venue"
},
  "geometry": {"coordinates":[-98.491811,29.35324],"type":"Point"}
}