{
  "type": "Feature",
  "properties": {
    "iso:country":"US",
    "sg:address":"707 Tilden St",
    "sg:city":"Cotulla",
    "sg:classifiers":[
        {
            "category":"Professional",
            "type":"Services"
        }
    ],
    "sg:phone":"+1 830 879 2215",
    "sg:postcode":"78014",
    "sg:province":"TX",
    "sg:tags":[
        "establishment"
    ],
    "wof:name":"Galactic Inc",
    "wof:placetype":"venue"
},
  "geometry": {"coordinates":[-99.241022,28.435901],"type":"Point"}
}