{
  "type": "Feature",
  "properties": {
    "iso:country":"US",
    "sg:address":"1414 W Randol Mill Rd",
    "sg:city":"Arlington",
    "sg:classifiers":[
        {
            "category":"Professional",
            "subcategory":"Detective & Security Services",
            "type":"Services"
        }
    ],
    "sg:phone":"+1 817 860 4116",
    "sg:postcode":"76012",
    "sg:province":"TX",
    "sg:tags":[
        "guard",
        "patrol"
    ],
    "wof:name":"Pinkerton Security Automotive",
    "wof:placetype":"venue"
},
  "geometry": {"coordinates":[-97.128248,32.750107],"type":"Point"}
}