{
  "type": "Feature",
  "properties": {
    "iso:country":"US",
    "sg:address":"2016 Main St",
    "sg:city":"Houston",
    "sg:classifiers":[
        {
            "category":"Professional",
            "subcategory":"Computer Services",
            "type":"Services"
        }
    ],
    "sg:phone":"+1 713 880 3367",
    "sg:postcode":"77002",
    "sg:province":"TX",
    "sg:tags":[
        "repair",
        "maintenance"
    ],
    "wof:name":"Nutcracker Electronics",
    "wof:placetype":"venue"
},
  "geometry": {"coordinates":[-95.37109,29.749261],"type":"Point"}
}