{
  "type": "Feature",
  "properties": {
    "iso:country":"US",
    "sg:address":"1941 Pine Ridge Dr",
    "sg:city":"Bedford",
    "sg:classifiers":[
        {
            "category":"Local Transit",
            "type":"Transportation"
        }
    ],
    "sg:phone":"+1 817 540 2094",
    "sg:postcode":"76021",
    "sg:province":"TX",
    "sg:tags":[
        "limousine"
    ],
    "wof:name":"Arta Transportation",
    "wof:placetype":"venue"
},
  "geometry": {"coordinates":[-97.137427,32.846224],"type":"Point"}
}