{
  "type": "Feature",
  "properties": {
    "iso:country":"US",
    "sg:address":"14102 Cypress Falls Dr",
    "sg:city":"Cypress",
    "sg:classifiers":[
        {
            "category":"Freight",
            "type":"Transportation"
        }
    ],
    "sg:phone":"+1 281 655 4369",
    "sg:postcode":"77429",
    "sg:province":"TX",
    "sg:tags":[
        "operator",
        "local",
        "trucking"
    ],
    "wof:name":"Leonards Trucking Co",
    "wof:placetype":"venue"
},
  "geometry": {"coordinates":[-95.633229,30.001271],"type":"Point"}
}