{
  "type": "Feature",
  "properties": {
    "iso:country":"US",
    "sg:address":"16286 Loch Katrine Ln",
    "sg:city":"Houston",
    "sg:classifiers":[
        {
            "category":"Social Services",
            "type":"Services"
        },
        {
            "category":"Professional",
            "subcategory":"Employment Agencies",
            "type":"Services"
        },
        {
            "category":"Organizations",
            "subcategory":"Community Association",
            "type":"Services"
        }
    ],
    "sg:phone":"+1 281 859 3039",
    "sg:postcode":"77084",
    "sg:province":"TX",
    "sg:tags":[
        "club",
        "workers'",
        "placement",
        "volunteer"
    ],
    "wof:name":"El Centernario Club",
    "wof:placetype":"venue"
},
  "geometry": {"coordinates":[-95.648532,29.845943],"type":"Point"}
}