{
  "type": "Feature",
  "properties": {
    "iso:country":"US",
    "sg:address":"1959 Oak Hill Cir",
    "sg:city":"Dallas",
    "sg:classifiers":[
        {
            "category":"Food & Beverages",
            "subcategory":"Groceries & Convenience Stores",
            "type":"Retail Goods"
        }
    ],
    "sg:phone":"+1 214 398 5759",
    "sg:postcode":"75217",
    "sg:province":"TX",
    "wof:name":"Greenwood Flea Market Booth",
    "wof:placetype":"venue"
},
  "geometry": {"coordinates":[-96.673205,32.746583],"type":"Point"}
}