{
  "type": "Feature",
  "properties": {
    "iso:country":"US",
    "sg:address":"2925 Briarpark Dr",
    "sg:city":"Houston",
    "sg:classifiers":[
        {
            "category":"Building & Trades",
            "subcategory":"Construction",
            "type":"Services"
        }
    ],
    "sg:phone":"+1 713 435 6300",
    "sg:postcode":"77042",
    "sg:province":"TX",
    "sg:tags":[
        "contractor"
    ],
    "wof:name":"Belmont Constructors",
    "wof:placetype":"venue"
},
  "geometry": {"coordinates":[-95.548698,29.735001],"type":"Point"}
}