{
  "type": "Feature",
  "properties": {
    "iso:country":"US",
    "sg:address":"5222 Stamper Way",
    "sg:city":"Houston",
    "sg:classifiers":[
        {
            "category":"Professional",
            "type":"Services"
        }
    ],
    "sg:phone":"+1 713 622 8828",
    "sg:postcode":"77056",
    "sg:province":"TX",
    "wof:name":"Ktell Services",
    "wof:placetype":"venue"
},
  "geometry": {"coordinates":[-95.467857,29.744732],"type":"Point"}
}