{
  "type": "Feature",
  "properties": {
    "iso:country":"US",
    "sg:address":"3617 White Oak Dr",
    "sg:city":"Houston",
    "sg:classifiers":[
        {
            "category":"Professional",
            "subcategory":"Advertising",
            "type":"Services"
        }
    ],
    "sg:phone":"+1 713 868 4056",
    "sg:postcode":"77007",
    "sg:province":"TX",
    "sg:tags":[
        "agency"
    ],
    "wof:name":"Ivox Media",
    "wof:placetype":"venue"
},
  "geometry": {"coordinates":[-95.397328,29.781396],"type":"Point"}
}