{
  "type": "Feature",
  "properties": {
    "iso:country":"US",
    "sg:address":"2525 Bay Area Blvd",
    "sg:city":"Houston",
    "sg:classifiers":[
        {
            "category":"Real Estate",
            "subcategory":"Real Estate Agent",
            "type":"Services"
        }
    ],
    "sg:phone":"+1 281 480 5151",
    "sg:postcode":"77058",
    "sg:province":"TX",
    "wof:name":"Chen & Assoc",
    "wof:placetype":"venue"
},
  "geometry": {"coordinates":[-95.108889,29.573588],"type":"Point"}
}