{
  "type": "Feature",
  "properties": {
    "iso:country":"US",
    "sg:address":"2022 Hickory Tree Rd",
    "sg:city":"Mesquite",
    "sg:classifiers":[
        {
            "category":"Building & Trades",
            "subcategory":"Construction",
            "type":"Services"
        }
    ],
    "sg:phone":"+1 972 839 4096",
    "sg:postcode":"75180",
    "sg:province":"TX",
    "sg:tags":[
        "house"
    ],
    "wof:name":"Wilks Construction Services",
    "wof:placetype":"venue"
},
  "geometry": {"coordinates":[-96.622502,32.741529],"type":"Point"}
}