{
  "type": "Feature",
  "properties": {
    "iso:country":"US",
    "sg:address":"1645 Dick Ritter Dr",
    "sg:city":"El Paso",
    "sg:classifiers":[
        {
            "category":"Building & Trades",
            "subcategory":"Construction",
            "type":"Services"
        }
    ],
    "sg:phone":"+1 915 629 9390",
    "sg:postcode":"79936",
    "sg:province":"TX",
    "sg:tags":[
        "concrete",
        "contractor"
    ],
    "wof:name":"Texas Custom Concrete LLC",
    "wof:placetype":"venue"
},
  "geometry": {"coordinates":[-106.31068399999999,31.754918],"type":"Point"}
}