{
  "type": "Feature",
  "properties": {
    "iso:country":"US",
    "sg:address":"16250 County Road 440",
    "sg:city":"Lindale",
    "sg:classifiers":[
        {
            "category":"Health Services",
            "subcategory":"Doctor",
            "type":"Services"
        }
    ],
    "sg:phone":"+1 903 520 7282",
    "sg:postcode":"75771",
    "sg:province":"TX",
    "sg:tags":[
        "physician",
        "surgeon"
    ],
    "wof:name":"Lascelles",
    "wof:placetype":"venue"
},
  "geometry": {"coordinates":[-95.51148000000001,32.502481],"type":"Point"}
}