{
  "type": "Feature",
  "properties": {
    "iso:country":"US",
    "sg:address":"4930 Gulfway Dr",
    "sg:city":"Port Arthur",
    "sg:classifiers":[
        {
            "category":"Shopping",
            "subcategory":"Pharmacy",
            "type":"Retail Goods"
        }
    ],
    "sg:phone":"+1 409 982 1927",
    "sg:postcode":"77642",
    "sg:province":"TX",
    "sg:tags":[
        "drug",
        "store"
    ],
    "wof:name":"Walgreens",
    "wof:placetype":"venue"
},
  "geometry": {"coordinates":[-93.91152700000001,29.917033],"type":"Point"}
}