{
  "type": "Feature",
  "properties": {
    "iso:country":"US",
    "sg:address":"3624 Oak Lawn Ave",
    "sg:city":"Dallas",
    "sg:classifiers":[
        {
            "category":"Professional",
            "subcategory":"Lawyer & Legal Services",
            "type":"Services"
        }
    ],
    "sg:phone":"+1 214 599 9792",
    "sg:postcode":"75219",
    "sg:province":"TX",
    "wof:name":"Southwest Law Assoc",
    "wof:placetype":"venue"
},
  "geometry": {"coordinates":[-96.803828,32.813198],"type":"Point"}
}