{
  "type": "Feature",
  "properties": {
    "iso:country":"US",
    "sg:address":"2470 N 11th St",
    "sg:city":"Beaumont",
    "sg:classifiers":[
        {
            "category":"Insurance",
            "subcategory":"Insurance Agent",
            "type":"Services"
        }
    ],
    "sg:phone":"+1 409 347 0553",
    "sg:postcode":"77703",
    "sg:province":"TX",
    "wof:name":"Brooke Agency",
    "wof:placetype":"venue"
},
  "geometry": {"coordinates":[-94.13027200000001,30.100729],"type":"Point"}
}