{
  "type": "Feature",
  "properties": {
    "iso:country":"US",
    "sg:address":"10958 North Fwy",
    "sg:city":"Houston",
    "sg:classifiers":[
        {
            "category":"Manufacturing",
            "subcategory":"Tools & Machinery",
            "type":"Manufacturing & Wholesale Goods"
        }
    ],
    "sg:phone":"+1 281 448 3168",
    "sg:postcode":"77037",
    "sg:province":"TX",
    "sg:tags":[
        "printing",
        "trade"
    ],
    "wof:name":"Thrifty Nickel Want ADS",
    "wof:placetype":"venue"
},
  "geometry": {"coordinates":[-95.412381,29.922751],"type":"Point"}
}