{
  "type": "Feature",
  "properties": {
    "iso:country":"US",
    "sg:address":"3635 Leon Rd",
    "sg:city":"Garland",
    "sg:classifiers":[
        {
            "category":"Travel",
            "subcategory":"Hotels & Motels",
            "type":"Entertainment"
        }
    ],
    "sg:phone":"+1 972 864 1802",
    "sg:postcode":"75041",
    "sg:province":"TX",
    "sg:tags":[
        "operations"
    ],
    "wof:name":"Deluxe Inn",
    "wof:placetype":"venue"
},
  "geometry": {"coordinates":[-96.662094,32.873935],"type":"Point"}
}