{
  "type": "Feature",
  "properties": {
    "iso:country":"US",
    "sg:address":"200 Padre Blvd",
    "sg:city":"S Padre Island",
    "sg:classifiers":[
        {
            "category":"Building & Trades",
            "subcategory":"Plumbing",
            "type":"Services"
        }
    ],
    "sg:phone":"+1 956 761 8400",
    "sg:postcode":"78597",
    "sg:province":"TX",
    "sg:tags":[
        "plumbing",
        "contractor"
    ],
    "wof:name":"SPI Plumbing Co",
    "wof:placetype":"venue"
},
  "geometry": {"coordinates":[-97.16076099999999,26.074374],"type":"Point"}
}