{
  "type": "Feature",
  "properties": {
    "iso:country":"US",
    "sg:address":"13237 Montfort Dr",
    "sg:city":"Dallas",
    "sg:classifiers":[
        {
            "category":"Manufacturing",
            "subcategory":"Tools & Machinery",
            "type":"Manufacturing & Wholesale Goods"
        }
    ],
    "sg:phone":"+1 417 598 0682",
    "sg:postcode":"75240",
    "sg:province":"TX",
    "sg:tags":[
        "surgical",
        "mfg"
    ],
    "wof:name":"Total Balance Orthotics",
    "wof:placetype":"venue"
},
  "geometry": {"coordinates":[-96.811446,32.927846],"type":"Point"}
}