{
  "type": "Feature",
  "properties": {
    "iso:country":"US",
    "sg:address":"253 Sarah Ln",
    "sg:city":"Trinity",
    "sg:classifiers":[
        {
            "category":"Shopping",
            "type":"Retail Goods"
        },
        {
            "category":"Organizations",
            "subcategory":"Non-profit Organization",
            "type":"Services"
        }
    ],
    "sg:phone":"+1 936 594 4567",
    "sg:postcode":"75862",
    "sg:province":"TX",
    "sg:tags":[
        "fund",
        "games",
        "raising",
        "merchandise",
        "supply"
    ],
    "wof:name":"Rx For Ms Now Inc",
    "wof:placetype":"venue"
},
  "geometry": {"coordinates":[-95.29998500000001,31.005613],"type":"Point"}
}