{
  "type": "Feature",
  "properties": {
    "iso:country":"US",
    "sg:address":"6628 Dawn Dr",
    "sg:city":"El Paso",
    "sg:classifiers":[
        {
            "category":"Building & Trades",
            "subcategory":"Construction",
            "type":"Services"
        }
    ],
    "sg:phone":"+1 915 584 2674",
    "sg:postcode":"79912",
    "sg:province":"TX",
    "sg:tags":[
        "contractor"
    ],
    "wof:name":"Goetting Construction Co",
    "wof:placetype":"venue"
},
  "geometry": {"coordinates":[-106.53800200000001,31.8438],"type":"Point"}
}