{
  "type": "Feature",
  "properties": {
    "iso:country":"US",
    "sg:address":"12300 Hunters Creek Rd",
    "sg:city":"College Station",
    "sg:classifiers":[
        {
            "category":"Mining & Drilling",
            "type":"Manufacturing & Wholesale Goods"
        }
    ],
    "sg:phone":"+1 979 690 2220",
    "sg:postcode":"77845",
    "sg:province":"TX",
    "sg:tags":[
        "crude",
        "production",
        "gas"
    ],
    "wof:name":"Cago Inc",
    "wof:placetype":"venue"
},
  "geometry": {"coordinates":[-96.342512,30.553205],"type":"Point"}
}