{
  "type": "Feature",
  "properties": {
    "iso:country":"US",
    "sg:address":"690 W Campbell Rd",
    "sg:city":"Richardson",
    "sg:classifiers":[
        {
            "category":"Insurance",
            "subcategory":"Insurance Agent",
            "type":"Services"
        }
    ],
    "sg:phone":"+1 972 238 1802",
    "sg:postcode":"75080",
    "sg:province":"TX",
    "wof:name":"Randy L Shockey",
    "wof:placetype":"venue"
},
  "geometry": {"coordinates":[-96.744648,32.978094],"type":"Point"}
}