{
  "type": "Feature",
  "properties": {
    "iso:country":"US",
    "sg:address":"119 W Southmore Ave",
    "sg:city":"Pasadena",
    "sg:classifiers":[
        {
            "category":"Insurance",
            "subcategory":"Insurance Agent",
            "type":"Services"
        }
    ],
    "sg:phone":"+1 713 477 4770",
    "sg:postcode":"77502",
    "sg:province":"TX",
    "wof:name":"Amco Auto Insurance",
    "wof:placetype":"venue"
},
  "geometry": {"coordinates":[-95.211704,29.690708],"type":"Point"}
}