{
  "type": "Feature",
  "properties": {
    "iso:country":"US",
    "sg:address":"921 W New Braunfels St",
    "sg:city":"Seguin",
    "sg:classifiers":[
        {
            "category":"Museum",
            "type":"Entertainment"
        }
    ],
    "sg:phone":"+1 830 401 0232",
    "sg:postcode":"78155",
    "sg:province":"TX",
    "sg:tags":[
        "organization",
        "arts",
        "information"
    ],
    "wof:name":"Teatro De Artes De Juan Seguin",
    "wof:placetype":"venue"
},
  "geometry": {"coordinates":[-97.976963,29.584495],"type":"Point"}
}