{
  "type": "Feature",
  "properties": {
    "iso:country":"US",
    "sg:address":"1250 Delmont Dr",
    "sg:city":"Richardson",
    "sg:classifiers":[
        {
            "category":"Manufacturing",
            "subcategory":"Tobacco Products",
            "type":"Manufacturing & Wholesale Goods"
        }
    ],
    "sg:phone":"+1 972 661 9136",
    "sg:postcode":"75080",
    "sg:province":"TX",
    "sg:tags":[
        "cigar",
        "mfg"
    ],
    "wof:name":"Cigars & More Inc",
    "wof:placetype":"venue"
},
  "geometry": {"coordinates":[-96.760959,32.948856],"type":"Point"}
}