{
  "type": "Feature",
  "properties": {
    "iso:country":"US",
    "sg:address":"5869 Holloway St",
    "sg:city":"Fort Worth",
    "sg:classifiers":[
        {
            "category":"Shopping",
            "subcategory":"Used Merchandise",
            "type":"Retail Goods"
        }
    ],
    "sg:phone":"+1 817 377 8521",
    "sg:postcode":"76114",
    "sg:province":"TX",
    "wof:name":"Joel N Elizondo",
    "wof:placetype":"venue"
},
  "geometry": {"coordinates":[-97.41236600000001,32.759798],"type":"Point"}
}