{
  "type": "Feature",
  "properties": {
    "iso:country":"US",
    "sg:address":"13310 White Settlement Rd",
    "sg:city":"Fort Worth",
    "sg:classifiers":[
        {
            "category":"Building & Trades",
            "subcategory":"Construction",
            "type":"Services"
        }
    ],
    "sg:phone":"+1 817 448 0054",
    "sg:postcode":"76108",
    "sg:province":"TX",
    "sg:tags":[
        "hanging",
        "contractor"
    ],
    "wof:name":"Billy G Farquhar",
    "wof:placetype":"venue"
},
  "geometry": {"coordinates":[-97.545856,32.774375],"type":"Point"}
}