{
  "type": "Feature",
  "properties": {
    "iso:country":"US",
    "sg:address":"4005 Garden Springs Dr",
    "sg:city":"Fort Worth",
    "sg:classifiers":[
        {
            "category":"Personal",
            "type":"Services"
        }
    ],
    "sg:phone":"+1 817 370 1209",
    "sg:postcode":"76123",
    "sg:province":"TX",
    "wof:name":"Season For Celebration",
    "wof:placetype":"venue"
},
  "geometry": {"coordinates":[-97.380281,32.62103],"type":"Point"}
}