{
  "type": "Feature",
  "properties": {
    "iso:country":"US",
    "sg:address":"1615 Raleigh Dr",
    "sg:city":"Carrollton",
    "sg:classifiers":[
        {
            "category":"Professional",
            "subcategory":"Management & Consulting",
            "type":"Services"
        }
    ],
    "sg:phone":"+1 972 939 9798",
    "sg:postcode":"75007",
    "sg:province":"TX",
    "sg:tags":[
        "personnel",
        "consultant"
    ],
    "wof:name":"Sancora",
    "wof:placetype":"venue"
},
  "geometry": {"coordinates":[-96.899861,33.010093],"type":"Point"}
}