{
  "type": "Feature",
  "properties": {
    "iso:country":"US",
    "sg:address":"107 NE 4th St",
    "sg:city":"Hubbard",
    "sg:classifiers":[
        {
            "category":"Restaurant",
            "type":"Food & Drink"
        }
    ],
    "sg:phone":"+1 254 576 2778",
    "sg:postcode":"76648",
    "sg:province":"TX",
    "wof:name":"El Zarape Mex. Restaurant",
    "wof:placetype":"venue"
},
  "geometry": {"coordinates":[-96.79727699999999,31.848316],"type":"Point"}
}