{
  "type": "Feature",
  "properties": {
    "iso:country":"US",
    "sg:address":"3704 Navigation Blvd",
    "sg:city":"Houston",
    "sg:classifiers":[
        {
            "category":"Professional",
            "type":"Services"
        }
    ],
    "sg:phone":"+1 713 224 5774",
    "sg:postcode":"77003",
    "sg:province":"TX",
    "sg:tags":[
        "establishment"
    ],
    "wof:name":"Donafaria USA",
    "wof:placetype":"venue"
},
  "geometry": {"coordinates":[-95.332482,29.754061],"type":"Point"}
}