{
  "type": "Feature",
  "properties": {
    "iso:country":"US",
    "sg:address":"511 S Stanton St",
    "sg:city":"El Paso",
    "sg:classifiers":[
        {
            "category":"Shopping",
            "subcategory":"Clothing, Apparel, & Fashions",
            "type":"Retail Goods"
        }
    ],
    "sg:phone":"+1 915 532 7777",
    "sg:postcode":"79901",
    "sg:province":"TX",
    "wof:name":"Fashion Outlet",
    "wof:placetype":"venue"
},
  "geometry": {"coordinates":[-106.484619,31.754185],"type":"Point"}
}