{
  "type": "Feature",
  "properties": {
    "iso:country":"US",
    "sg:address":"6814 Jensen Dr",
    "sg:city":"Houston",
    "sg:classifiers":[
        {
            "category":"Restaurant",
            "type":"Food & Drink"
        }
    ],
    "sg:phone":"+1 713 697 4445",
    "sg:postcode":"77093",
    "sg:province":"TX",
    "sg:tags":[
        "barbeque"
    ],
    "wof:name":"Chom's Bbq",
    "wof:placetype":"venue"
},
  "geometry": {"coordinates":[-95.342263,29.821364],"type":"Point"}
}