{
  "type": "Feature",
  "properties": {
    "iso:country":"US",
    "sg:address":"219 E Main St",
    "sg:city":"Port Lavaca",
    "sg:classifiers":[
        {
            "category":"Retail",
            "subcategory":"Repair Shop",
            "type":"Services"
        }
    ],
    "sg:phone":"+1 361 552 4888",
    "sg:postcode":"77979",
    "sg:province":"TX",
    "sg:tags":[
        "upholsterer"
    ],
    "wof:name":"Carroll Brown Shop",
    "wof:placetype":"venue"
},
  "geometry": {"coordinates":[-96.62491199999999,28.615859],"type":"Point"}
}