{
  "type": "Feature",
  "properties": {
    "iso:country":"US",
    "sg:address":"7010 Preston Rd",
    "sg:city":"Frisco",
    "sg:classifiers":[
        {
            "category":"Cinema",
            "subcategory":"Movie Rental",
            "type":"Entertainment"
        }
    ],
    "sg:phone":"+1 972 335 7300",
    "sg:postcode":"75034",
    "sg:province":"TX",
    "sg:tags":[
        "leasing",
        "video",
        "disc",
        "tape"
    ],
    "wof:name":"Flicks Home Video",
    "wof:placetype":"venue"
},
  "geometry": {"coordinates":[-96.804503,33.136846],"type":"Point"}
}