{
  "type": "Feature",
  "properties": {
    "iso:country":"US",
    "sg:address":"1024 S. Greenville Avenue Suite 130",
    "sg:city":"Allen",
    "sg:classifiers":[
        {
            "category":"Professional",
            "subcategory":"Computer Services",
            "type":"Services"
        }
    ],
    "sg:phone":"+1 214 547 0460",
    "sg:postcode":"75002",
    "sg:province":"TX",
    "sg:website":"http://www.quickfiltertech.com/",
    "wof:name":"Quickfilter Technologies",
    "wof:placetype":"venue"
},
  "geometry": {"coordinates":[-96.67549099999999,33.081828],"type":"Point"}
}