{
  "type": "Feature",
  "properties": {
    "iso:country":"US",
    "sg:address":"10939 Shady Trl",
    "sg:city":"Dallas",
    "sg:classifiers":[
        {
            "category":"Government",
            "subcategory":"Office",
            "type":"Public Place"
        }
    ],
    "sg:phone":"+1 214 351 6231",
    "sg:postcode":"75220",
    "sg:province":"TX",
    "sg:tags":[
        "government-state",
        "government-united",
        "state"
    ],
    "sg:website":"http://www.hhsc.com",
    "wof:name":"Health & Human Services Commission, Texas",
    "wof:placetype":"venue"
},
  "geometry": {"coordinates":[-96.890291,32.88075],"type":"Point"}
}