{
  "type": "Feature",
  "properties": {
    "iso:country":"US",
    "sg:address":"1101 Melbourne Rd",
    "sg:city":"Hurst",
    "sg:classifiers":[
        {
            "category":"Real Estate",
            "subcategory":"Real Estate Operator",
            "type":"Services"
        }
    ],
    "sg:phone":"+1 817 590 4595",
    "sg:postcode":"76053",
    "sg:province":"TX",
    "sg:tags":[
        "building",
        "nonresidential"
    ],
    "wof:name":"Embroidery Plus",
    "wof:placetype":"venue"
},
  "geometry": {"coordinates":[-97.197171,32.829429],"type":"Point"}
}