{
  "type": "Feature",
  "properties": {
    "iso:country":"US",
    "sg:address":"2205 Country Club Dr",
    "sg:city":"Carrollton",
    "sg:classifiers":[
        {
            "category":"Freight",
            "type":"Transportation"
        }
    ],
    "sg:phone":"+1 972 245 8004",
    "sg:postcode":"75006",
    "sg:province":"TX",
    "sg:tags":[
        "trucking"
    ],
    "wof:name":"Roadway Express Inc",
    "wof:placetype":"venue"
},
  "geometry": {"coordinates":[-96.877279,32.960972],"type":"Point"}
}