{
  "type": "Feature",
  "properties": {
    "iso:country":"US",
    "sg:address":"114 Golden Oaks Dr",
    "sg:city":"Georgetown",
    "sg:classifiers":[
        {
            "category":"Personal",
            "subcategory":"Beauty Salon",
            "type":"Services"
        },
        {
            "category":"Personal",
            "subcategory":"Barber",
            "type":"Services"
        }
    ],
    "sg:phone":"+1 512 863 4827",
    "sg:postcode":"78628",
    "sg:province":"TX",
    "sg:tags":[
        "shop"
    ],
    "wof:name":"Tortoise & The Hair",
    "wof:placetype":"venue"
},
  "geometry": {"coordinates":[-97.686685,30.659669],"type":"Point"}
}