{
  "type": "Feature",
  "properties": {
    "iso:country":"US",
    "sg:address":"2240 S Washington St",
    "sg:city":"Kaufman",
    "sg:classifiers":[
        {
            "category":"Autos & Motor Vehicles",
            "subcategory":"Automobile Sales",
            "type":"Retail Goods"
        }
    ],
    "sg:phone":"+1 972 962 3316",
    "sg:postcode":"75142",
    "sg:province":"TX",
    "sg:tags":[
        "car",
        "dealer"
    ],
    "wof:name":"Kaufman PBR Auto Sales",
    "wof:placetype":"venue"
},
  "geometry": {"coordinates":[-96.311243,32.572235],"type":"Point"}
}