{
  "type": "Feature",
  "properties": {
    "iso:country":"US",
    "sg:address":"8122 Forest Ln",
    "sg:city":"Dallas",
    "sg:classifiers":[
        {
            "category":"Food & Beverages",
            "subcategory":"Groceries & Convenience Stores",
            "type":"Retail Goods"
        }
    ],
    "sg:phone":"+1 214 343 4232",
    "sg:postcode":"75243",
    "sg:province":"TX",
    "wof:name":"1st Choice Grocery",
    "wof:placetype":"venue"
},
  "geometry": {"coordinates":[-96.76469,32.909022],"type":"Point"}
}