{
  "type": "Feature",
  "properties": {
    "iso:country":"US",
    "sg:address":"8429 Scott St",
    "sg:city":"Houston",
    "sg:classifiers":[
        {
            "category":"Restaurant",
            "type":"Food & Drink"
        }
    ],
    "sg:phone":"+1 713 738 3700",
    "sg:postcode":"77051",
    "sg:province":"TX",
    "sg:tags":[
        "eating"
    ],
    "wof:name":"Allisons Soul Food & Bar-B-Qu",
    "wof:placetype":"venue"
},
  "geometry": {"coordinates":[-95.367684,29.670417],"type":"Point"}
}