{
  "type": "Feature",
  "properties": {
    "iso:country":"US",
    "sg:address":"1301 49th St",
    "sg:city":"Lubbock",
    "sg:classifiers":[
        {
            "category":"Organizations",
            "subcategory":"Religious Organization",
            "type":"Services"
        }
    ],
    "sg:phone":"+1 806 765 7531",
    "sg:postcode":"79412",
    "sg:province":"TX",
    "wof:name":"Providence Baptist Church",
    "wof:placetype":"venue"
},
  "geometry": {"coordinates":[-101.85309700000001,33.550039],"type":"Point"}
}