{
  "type": "Feature",
  "properties": {
    "iso:country":"US",
    "sg:address":"10045 Custer Rd",
    "sg:city":"Plano",
    "sg:classifiers":[
        {
            "category":"Retail",
            "subcategory":"Laundry & Dry Cleaning",
            "type":"Services"
        }
    ],
    "sg:phone":"+1 214 509 0888",
    "sg:postcode":"75025",
    "sg:province":"TX",
    "sg:tags":[
        "drycleaning",
        "plant"
    ],
    "wof:name":"Kwik Dry Clean Supercenter",
    "wof:placetype":"venue"
},
  "geometry": {"coordinates":[-96.733486,33.117238],"type":"Point"}
}