{
  "type": "Feature",
  "properties": {
    "iso:country":"US",
    "sg:address":"9219 Katy Fwy",
    "sg:city":"Houston",
    "sg:classifiers":[
        {
            "category":"Professional",
            "subcategory":"Accounting & Tax Preparation",
            "type":"Services"
        }
    ],
    "sg:phone":"+1 713 468 7909",
    "sg:postcode":"77024",
    "sg:province":"TX",
    "sg:tags":[
        "accountant"
    ],
    "wof:name":"Price Long & Company",
    "wof:placetype":"venue"
},
  "geometry": {"coordinates":[-95.518501,29.783701],"type":"Point"}
}