{
  "type": "Feature",
  "properties": {
    "iso:country":"US",
    "sg:address":"2301 Coit Rd",
    "sg:city":"Plano",
    "sg:classifiers":[
        {
            "category":"Personal",
            "type":"Services"
        }
    ],
    "sg:phone":"+1 972 964 5057",
    "sg:postcode":"75075",
    "sg:province":"TX",
    "sg:tags":[
        "therapist",
        "massage"
    ],
    "wof:name":"Body Concepts Inc",
    "wof:placetype":"venue"
},
  "geometry": {"coordinates":[-96.770248,33.029919],"type":"Point"}
}