{
  "type": "Feature",
  "properties": {
    "iso:country":"US",
    "sg:address":"2514 Cedar Dr",
    "sg:city":"La Marque",
    "sg:classifiers":[
        {
            "category":"Real Estate",
            "subcategory":"Real Estate Agent",
            "type":"Services"
        }
    ],
    "sg:phone":"+1 409 935 1531",
    "sg:postcode":"77568",
    "sg:province":"TX",
    "sg:tags":[
        "appraiser"
    ],
    "wof:name":"Action Real Estate",
    "wof:placetype":"venue"
},
  "geometry": {"coordinates":[-94.981403,29.368488],"type":"Point"}
}