{
  "type": "Feature",
  "properties": {
    "iso:country":"US",
    "sg:address":"650 W Fm 78",
    "sg:city":"Cibolo",
    "sg:classifiers":[
        {
            "category":"Restaurant",
            "type":"Food & Drink"
        }
    ],
    "sg:phone":"+1 210 658 5933",
    "sg:postcode":"78108",
    "sg:province":"TX",
    "sg:tags":[
        "mexican"
    ],
    "wof:name":"La Tortillita Mexican Restaurant",
    "wof:placetype":"venue"
},
  "geometry": {"coordinates":[-98.239963,29.560311],"type":"Point"}
}