{
  "type": "Feature",
  "properties": {
    "iso:country":"US",
    "sg:address":"15551 Wright Brothers Dr",
    "sg:city":"Addison",
    "sg:classifiers":[
        {
            "category":"Social Services",
            "subcategory":"Job Training",
            "type":"Services"
        },
        {
            "category":"Retail",
            "subcategory":"Laundry & Dry Cleaning",
            "type":"Services"
        },
        {
            "category":"Wholesale",
            "subcategory":"Machinery & Supplies",
            "type":"Manufacturing & Wholesale Goods"
        }
    ],
    "sg:phone":"+1 972 991 9274",
    "sg:postcode":"75001",
    "sg:province":"TX",
    "sg:tags":[
        "coin",
        "commercial",
        "equipment",
        "dryer",
        "operated",
        "washer",
        "laundromat",
        "equipment-repairing"
    ],
    "sg:website":"http://washerdryer1.com",
    "wof:name":"Commercial Equipment Co.",
    "wof:placetype":"venue"
},
  "geometry": {"coordinates":[-96.83622,32.960671],"type":"Point"}
}