{
  "type": "Feature",
  "properties": {
    "iso:country":"US",
    "sg:address":"1140 Cedar Dr",
    "sg:city":"Midlothian",
    "sg:classifiers":[
        {
            "category":"Building & Trades",
            "subcategory":"Construction",
            "type":"Services"
        }
    ],
    "sg:phone":"+1 972 723 2056",
    "sg:postcode":"76065",
    "sg:province":"TX",
    "sg:tags":[
        "contractor",
        "fence-sales"
    ],
    "wof:name":"Triple R Fence Co",
    "wof:placetype":"venue"
},
  "geometry": {"coordinates":[-97.00755700000001,32.461226],"type":"Point"}
}