{
  "type": "Feature",
  "properties": {
    "iso:country":"US",
    "sg:address":"1010 S Barnes St",
    "sg:city":"Pampa",
    "sg:classifiers":[
        {
            "category":"Local Transit",
            "type":"Transportation"
        }
    ],
    "sg:phone":"+1 806 669 9999",
    "sg:postcode":"79065",
    "sg:province":"TX",
    "sg:tags":[
        "ambulance"
    ],
    "wof:name":"Guardian EMS",
    "wof:placetype":"venue"
},
  "geometry": {"coordinates":[-100.954132,35.52366],"type":"Point"}
}