{
  "type": "Feature",
  "properties": {
    "iso:country":"US",
    "sg:address":"1220 Barranca Dr",
    "sg:city":"El Paso",
    "sg:classifiers":[
        {
            "category":"Professional",
            "subcategory":"Business Services",
            "type":"Services"
        }
    ],
    "sg:phone":"+1 915 590 4611",
    "sg:postcode":"79935",
    "sg:province":"TX",
    "sg:tags":[
        "inspection"
    ],
    "wof:name":"Inspector For El Paso Cold",
    "wof:placetype":"venue"
},
  "geometry": {"coordinates":[-106.331411,31.752792],"type":"Point"}
}