{
  "type": "Feature",
  "properties": {
    "iso:country":"US",
    "sg:address":"4400 Marsalis St",
    "sg:city":"Fort Worth",
    "sg:classifiers":[
        {
            "category":"Utilities",
            "subcategory":"Refuse",
            "type":"Services"
        }
    ],
    "sg:phone":"+1 817 831 0871",
    "sg:postcode":"76117",
    "sg:province":"TX",
    "sg:tags":[
        "system"
    ],
    "wof:name":"Allied Waste Systems (de)",
    "wof:placetype":"venue"
},
  "geometry": {"coordinates":[-97.286512,32.774163],"type":"Point"}
}