{
  "type": "Feature",
  "properties": {
    "iso:country":"US",
    "sg:address":"7120 Whifflewind Way",
    "sg:city":"Austin",
    "sg:classifiers":[
        {
            "category":"Professional",
            "subcategory":"Computer Services",
            "type":"Services"
        }
    ],
    "sg:phone":"+1 512 278 0133",
    "sg:postcode":"78754",
    "sg:province":"TX",
    "sg:tags":[
        "prepackaged",
        "related",
        "software"
    ],
    "wof:name":"Peterson Compusulting",
    "wof:placetype":"venue"
},
  "geometry": {"coordinates":[-97.611335,30.344177],"type":"Point"}
}