{
  "type": "Feature",
  "properties": {
    "iso:country":"US",
    "sg:address":"207 Comanche Dr",
    "sg:city":"Gainesville",
    "sg:classifiers":[
        {
            "category":"Building & Trades",
            "subcategory":"Electrical",
            "type":"Services"
        }
    ],
    "sg:phone":"+1 940 668 8980",
    "sg:postcode":"76240",
    "sg:province":"TX",
    "sg:tags":[
        "electrician"
    ],
    "wof:name":"Reed Electrical Contracting",
    "wof:placetype":"venue"
},
  "geometry": {"coordinates":[-97.00376,33.570862],"type":"Point"}
}