{
  "type": "Feature",
  "properties": {
    "iso:country":"US",
    "sg:address":"4835 Medical Dr",
    "sg:city":"San Antonio",
    "sg:classifiers":[
        {
            "category":"Real Estate",
            "subcategory":"Real Estate Agent",
            "type":"Services"
        }
    ],
    "sg:phone":"+1 210 692 0990",
    "sg:postcode":"78229",
    "sg:province":"TX",
    "wof:name":"Casco Inc",
    "wof:placetype":"venue"
},
  "geometry": {"coordinates":[-98.58058800000001,29.510506],"type":"Point"}
}