{
  "type": "Feature",
  "properties": {
    "iso:country":"US",
    "sg:address":"2653 Mariposa Cir",
    "sg:city":"Plano",
    "sg:classifiers":[
        {
            "category":"Building & Trades",
            "subcategory":"Landscaping Services",
            "type":"Services"
        }
    ],
    "sg:phone":"+1 972 424 2626",
    "sg:postcode":"75075",
    "sg:province":"TX",
    "sg:tags":[
        "landscape"
    ],
    "wof:name":"Paul A REA Assoc Ldscp & Irr",
    "wof:placetype":"venue"
},
  "geometry": {"coordinates":[-96.714303,33.035139],"type":"Point"}
}