{
  "type": "Feature",
  "properties": {
    "iso:country":"US",
    "sg:address":"601 S Ash St",
    "sg:city":"Perryton",
    "sg:classifiers":[
        {
            "category":"Place Of Worship",
            "subcategory":"Church",
            "type":"Public Place"
        },
        {
            "category":"Place Of Worship",
            "type":"Public Place"
        },
        {
            "category":"Organizations",
            "subcategory":"Religious Organization",
            "type":"Services"
        }
    ],
    "sg:phone":"+1 806 435 5110",
    "sg:postcode":"79070",
    "sg:province":"TX",
    "sg:tags":[
        "god",
        "churches-church",
        "churches-pentecostal"
    ],
    "wof:name":"Cornerstone Church",
    "wof:placetype":"venue"
},
  "geometry": {"coordinates":[-100.801331,36.394341],"type":"Point"}
}