{
  "type": "Feature",
  "properties": {
    "iso:country":"US",
    "sg:address":"147 N Dreamweaver Cir",
    "sg:city":"Spring",
    "sg:classifiers":[
        {
            "category":"Professional",
            "subcategory":"Business Services",
            "type":"Services"
        }
    ],
    "sg:phone":"+1 281 367 6140",
    "sg:postcode":"77380",
    "sg:province":"TX",
    "wof:name":"Dv8 Technologies LLC",
    "wof:placetype":"venue"
},
  "geometry": {"coordinates":[-95.459898,30.124277],"type":"Point"}
}