{
  "type": "Feature",
  "properties": {
    "iso:country":"US",
    "sg:address":"2619 Texas St",
    "sg:city":"Houston",
    "sg:classifiers":[
        {
            "category":"Food & Beverages",
            "subcategory":"Groceries & Convenience Stores",
            "type":"Retail Goods"
        }
    ],
    "sg:phone":"+1 713 222 9262",
    "sg:postcode":"77003",
    "sg:province":"TX",
    "wof:name":"Golden Duck Inc",
    "wof:placetype":"venue"
},
  "geometry": {"coordinates":[-95.348045,29.751355],"type":"Point"}
}