{
  "type": "Feature",
  "properties": {
    "iso:country":"US",
    "sg:address":"8102 Pine Green Ln",
    "sg:city":"Humble",
    "sg:classifiers":[
        {
            "category":"Professional",
            "subcategory":"Engineering",
            "type":"Services"
        }
    ],
    "sg:phone":"+1 281 852 1366",
    "sg:postcode":"77346",
    "sg:province":"TX",
    "wof:name":"Damon A Briggs",
    "wof:placetype":"venue"
},
  "geometry": {"coordinates":[-95.154976,30.007407],"type":"Point"}
}