{
  "type": "Feature",
  "properties": {
    "iso:country":"US",
    "sg:address":"8801 Wall St",
    "sg:city":"Austin",
    "sg:classifiers":[
        {
            "category":"Professional",
            "subcategory":"Engineering",
            "type":"Services"
        },
        {
            "category":"Health Services",
            "subcategory":"Nursing And Care Facility",
            "type":"Services"
        },
        {
            "category":"Professional",
            "subcategory":"Testing Lab",
            "type":"Services"
        }
    ],
    "sg:phone":"+1 512 834 8911",
    "sg:postcode":"78754",
    "sg:province":"TX",
    "sg:tags":[
        "laboratory",
        "x-ray",
        "laboratories-industrial",
        "engineer"
    ],
    "sg:website":"http://www.reinhartassoc.com",
    "wof:name":"Reinhart & Associates Inc",
    "wof:placetype":"venue"
},
  "geometry": {"coordinates":[-97.67192,30.339987],"type":"Point"}
}