{
  "type": "Feature",
  "properties": {
    "iso:country":"US",
    "sg:address":"6363 Beacon Vista Cir",
    "sg:city":"Granbury",
    "sg:classifiers":[
        {
            "category":"Organizations",
            "subcategory":"Community Association",
            "type":"Services"
        }
    ],
    "sg:phone":"+1 817 326 4732",
    "sg:postcode":"76049",
    "sg:province":"TX",
    "wof:name":"Beacon Vlley Estates Properly",
    "wof:placetype":"venue"
},
  "geometry": {"coordinates":[-97.684073,32.400638],"type":"Point"}
}