{
  "type": "Feature",
  "properties": {
    "iso:country":"US",
    "sg:address":"1433 Waverly St",
    "sg:city":"Houston",
    "sg:classifiers":[
        {
            "category":"Professional",
            "type":"Services"
        }
    ],
    "sg:phone":"+1 713 864 5450",
    "sg:postcode":"77008",
    "sg:province":"TX",
    "wof:name":"Heights Community League",
    "wof:placetype":"venue"
},
  "geometry": {"coordinates":[-95.404675,29.797362],"type":"Point"}
}