{
  "type": "Feature",
  "properties": {
    "iso:country":"US",
    "sg:address":"3319 Roberts Cut Off Rd",
    "sg:city":"Fort Worth",
    "sg:classifiers":[
        {
            "category":"Wholesale",
            "subcategory":"Office Equipment",
            "type":"Manufacturing & Wholesale Goods"
        }
    ],
    "sg:phone":"+1 817 237 0668",
    "sg:postcode":"76114",
    "sg:province":"TX",
    "wof:name":"Adcox Office Equipment",
    "wof:placetype":"venue"
},
  "geometry": {"coordinates":[-97.412024,32.808591],"type":"Point"}
}