{
  "type": "Feature",
  "properties": {
    "iso:country":"US",
    "sg:address":"301 Short St",
    "sg:city":"Smithville",
    "sg:classifiers":[
        {
            "category":"Food & Beverages",
            "subcategory":"Groceries & Convenience Stores",
            "type":"Retail Goods"
        }
    ],
    "sg:phone":"+1 512 360 3339",
    "sg:postcode":"78957",
    "sg:province":"TX",
    "wof:name":"7-Eleven",
    "wof:placetype":"venue"
},
  "geometry": {"coordinates":[-97.154234,30.007237],"type":"Point"}
}