{
  "type": "Feature",
  "properties": {
    "iso:country":"US",
    "sg:address":"9420 McCombs St",
    "sg:city":"El Paso",
    "sg:classifiers":[
        {
            "category":"Social Services",
            "type":"Services"
        }
    ],
    "sg:phone":"+1 915 757 0199",
    "sg:postcode":"79924",
    "sg:province":"TX",
    "sg:tags":[
        "community"
    ],
    "wof:name":"Project Bravo Inc",
    "wof:placetype":"venue"
},
  "geometry": {"coordinates":[-106.40620800000001,31.877574],"type":"Point"}
}