{
  "type": "Feature",
  "properties": {
    "iso:country":"US",
    "sg:address":"4015 Holland Ave",
    "sg:city":"Dallas",
    "sg:classifiers":[
        {
            "category":"Professional",
            "subcategory":"Lawyer & Legal Services",
            "type":"Services"
        }
    ],
    "sg:phone":"+1 214 526 2030",
    "sg:postcode":"75219",
    "sg:province":"TX",
    "wof:name":"James F Gilbert PC",
    "wof:placetype":"venue"
},
  "geometry": {"coordinates":[-96.807028,32.816192],"type":"Point"}
}