{
  "type": "Feature",
  "properties": {
    "iso:country":"US",
    "sg:address":"1409 Bandera Rd",
    "sg:city":"San Antonio",
    "sg:classifiers":[
        {
            "category":"Bars & Pubs",
            "type":"Food & Drink"
        }
    ],
    "sg:phone":"+1 210 433 6646",
    "sg:postcode":"78228",
    "sg:province":"TX",
    "sg:tags":[
        "drinking"
    ],
    "wof:name":"Good Times Lounge",
    "wof:placetype":"venue"
},
  "geometry": {"coordinates":[-98.56651100000001,29.46582],"type":"Point"}
}