{
  "type": "Feature",
  "properties": {
    "iso:country":"US",
    "sg:address":"1511 Mistletoe Ln",
    "sg:city":"Humble",
    "sg:classifiers":[
        {
            "category":"Professional",
            "subcategory":"Engineering",
            "type":"Services"
        }
    ],
    "sg:phone":"+1 281 358 6409",
    "sg:postcode":"77339",
    "sg:province":"TX",
    "wof:name":"Skillern Rogers Energy Cons",
    "wof:placetype":"venue"
},
  "geometry": {"coordinates":[-95.228351,30.037798],"type":"Point"}
}