{
  "type": "Feature",
  "properties": {
    "iso:country":"US",
    "sg:address":"1414 E Main St",
    "sg:city":"Eastland",
    "sg:classifiers":[
        {
            "category":"Professional",
            "subcategory":"Accounting & Tax Preparation",
            "type":"Services"
        }
    ],
    "sg:phone":"+1 254 629 8688",
    "sg:postcode":"76448",
    "sg:province":"TX",
    "wof:name":"Pitts Leslie Greer CPA",
    "wof:placetype":"venue"
},
  "geometry": {"coordinates":[-98.791562,32.401707],"type":"Point"}
}