{
  "type": "Feature",
  "properties": {
    "iso:country":"US",
    "sg:address":"201 Short St",
    "sg:city":"San Marcos",
    "sg:classifiers":[
        {
            "category":"Retail",
            "subcategory":"Auto Repair",
            "type":"Services"
        }
    ],
    "sg:phone":"+1 512 353 3321",
    "sg:postcode":"78666",
    "sg:province":"TX",
    "sg:tags":[
        "automotive"
    ],
    "wof:name":"Peveto Companies Ltd",
    "wof:placetype":"venue"
},
  "geometry": {"coordinates":[-97.92341500000001,29.883899],"type":"Point"}
}