{
  "type": "Feature",
  "properties": {
    "iso:country":"US",
    "sg:address":"12410 River Trail Dr",
    "sg:city":"Houston",
    "sg:classifiers":[
        {
            "category":"Shopping",
            "subcategory":"Hobbies, Toys, & Games",
            "type":"Retail Goods"
        }
    ],
    "sg:phone":"+1 281 449 0315",
    "sg:postcode":"77050",
    "sg:province":"TX",
    "sg:tags":[
        "toy",
        "store"
    ],
    "sg:website":"www.jmsmodeltrains.com",
    "wof:name":"J M S Model Trains",
    "wof:placetype":"venue"
},
  "geometry": {"coordinates":[-95.291612,29.903121],"type":"Point"}
}