{
  "type": "Feature",
  "properties": {
    "iso:country":"US",
    "sg:address":"203 W Main Ave",
    "sg:city":"Alton",
    "sg:classifiers":[
        {
            "category":"Government",
            "subcategory":"Office",
            "type":"Public Place"
        }
    ],
    "sg:phone":"+1 956 581 2733",
    "sg:postcode":"78580",
    "sg:province":"TX",
    "sg:tags":[
        "city"
    ],
    "wof:name":"Alton City Hall",
    "wof:placetype":"venue"
},
  "geometry": {"coordinates":[-97.78378499999999,26.482849],"type":"Point"}
}