{
  "type": "Feature",
  "properties": {
    "iso:country":"US",
    "sg:address":"505 W 17th St",
    "sg:city":"Plainview",
    "sg:classifiers":[
        {
            "category":"Organizations",
            "subcategory":"Religious Organization",
            "type":"Services"
        }
    ],
    "sg:phone":"+1 806 296 9583",
    "sg:postcode":"79072",
    "sg:province":"TX",
    "wof:name":"Spanish Nazarene Church",
    "wof:placetype":"venue"
},
  "geometry": {"coordinates":[-101.70837299999999,34.198847],"type":"Point"}
}