{
  "type": "Feature",
  "properties": {
    "iso:country":"US",
    "sg:address":"2220 Hwy 35 N",
    "sg:city":"Rockport",
    "sg:classifiers":[
        {
            "category":"Building & Trades",
            "subcategory":"Construction",
            "type":"Services"
        }
    ],
    "sg:phone":"+1 361 790 7171",
    "sg:postcode":"78382",
    "sg:province":"TX",
    "sg:tags":[
        "general",
        "contractor"
    ],
    "wof:name":"Loy Raggy Builder Inc",
    "wof:placetype":"venue"
},
  "geometry": {"coordinates":[-97.042361,28.042592],"type":"Point"}
}