{
  "type": "Feature",
  "properties": {
    "iso:country":"US",
    "sg:address":"3227 Bob Billa St",
    "sg:city":"San Antonio",
    "sg:classifiers":[
        {
            "category":"Shopping",
            "subcategory":"Jewelry",
            "type":"Retail Goods"
        }
    ],
    "sg:phone":"+1 210 333 6461",
    "sg:postcode":"78223",
    "sg:province":"TX",
    "sg:tags":[
        "jeweler"
    ],
    "wof:name":"Dolores Aguilar Jeweler",
    "wof:placetype":"venue"
},
  "geometry": {"coordinates":[-98.434365,29.368705],"type":"Point"}
}