{
  "type": "Feature",
  "properties": {
    "iso:country":"US",
    "sg:address":"605 W Harrison Rd",
    "sg:city":"Longview",
    "sg:classifiers":[
        {
            "category":"Professional",
            "subcategory":"Management & Consulting",
            "type":"Services"
        }
    ],
    "sg:phone":"+1 903 759 1766",
    "sg:postcode":"75604",
    "sg:province":"TX",
    "wof:name":"Brumble Management LLC",
    "wof:placetype":"venue"
},
  "geometry": {"coordinates":[-94.803206,32.495889],"type":"Point"}
}