{
  "type": "Feature",
  "properties": {
    "iso:country":"US",
    "sg:address":"500 4th St Aly",
    "sg:city":"Orange",
    "sg:classifiers":[
        {
            "category":"Professional",
            "subcategory":"Accounting & Tax Preparation",
            "type":"Services"
        }
    ],
    "sg:phone":"+1 409 883 5200",
    "sg:postcode":"77630",
    "sg:province":"TX",
    "sg:tags":[
        "return",
        "filing"
    ],
    "wof:name":"Vernon L Davis PC",
    "wof:placetype":"venue"
},
  "geometry": {"coordinates":[-93.73407400000001,30.099407],"type":"Point"}
}