{
  "type": "Feature",
  "properties": {
    "iso:country":"US",
    "sg:address":"100 Wolfe Nursery Rd Ste 154",
    "sg:city":"Stephenville",
    "sg:classifiers":[
        {
            "category":"Personal",
            "subcategory":"Beauty Salon",
            "type":"Services"
        },
        {
            "category":"Shopping",
            "subcategory":"Beauty & Cosmetics",
            "type":"Retail Goods"
        },
        {
            "category":"Personal",
            "subcategory":"Nail Salon",
            "type":"Services"
        }
    ],
    "sg:phone":"+1 254 965 8050",
    "sg:postcode":"76401",
    "sg:province":"TX",
    "sg:tags":[
        "perfume",
        "salons-equipment",
        "supply"
    ],
    "wof:name":"Luxury Nails",
    "wof:placetype":"venue"
},
  "geometry": {"coordinates":[-98.238609,32.204811],"type":"Point"}
}