{
  "type": "Feature",
  "properties": {
    "iso:country":"US",
    "sg:address":"10027 State Hwy 31",
    "sg:city":"Tyler",
    "sg:classifiers":[
        {
            "category":"Organizations",
            "subcategory":"Community Association",
            "type":"Services"
        }
    ],
    "sg:phone":"+1 903 566 2151",
    "sg:postcode":"75705",
    "sg:province":"TX",
    "sg:tags":[
        "fraternal"
    ],
    "wof:name":"Sharon Shrine Temple",
    "wof:placetype":"venue"
},
  "geometry": {"coordinates":[-95.24649700000001,32.349641],"type":"Point"}
}