{
  "type": "Feature",
  "properties": {
    "iso:country":"US",
    "sg:address":"405 S 15th St",
    "sg:city":"Silsbee",
    "sg:classifiers":[
        {
            "category":"Organizations",
            "subcategory":"Religious Organization",
            "type":"Services"
        }
    ],
    "sg:phone":"+1 409 385 4217",
    "sg:postcode":"77656",
    "sg:province":"TX",
    "wof:name":"Saint Chapel Church of Go",
    "wof:placetype":"venue"
},
  "geometry": {"coordinates":[-94.188835,30.350077],"type":"Point"}
}