{
  "type": "Feature",
  "properties": {
    "iso:country":"US",
    "sg:address":"9209 Levering Ln",
    "sg:city":"Houston",
    "sg:classifiers":[
        {
            "category":"Shopping",
            "subcategory":"Clothing, Apparel, & Fashions",
            "type":"Retail Goods"
        }
    ],
    "sg:phone":"+1 713 633 2970",
    "sg:postcode":"77028",
    "sg:province":"TX",
    "wof:name":"Chachee Fashion & Fragrance",
    "wof:placetype":"venue"
},
  "geometry": {"coordinates":[-95.291504,29.845903],"type":"Point"}
}