{
  "type": "Feature",
  "properties": {
    "iso:country":"US",
    "sg:address":"7600 Burnet Rd",
    "sg:city":"Austin",
    "sg:classifiers":[
        {
            "category":"Travel",
            "subcategory":"Travel Agent",
            "type":"Entertainment"
        }
    ],
    "sg:phone":"+1 512 458 5089",
    "sg:postcode":"78757",
    "sg:province":"TX",
    "sg:tags":[
        "agency",
        "bureau"
    ],
    "wof:name":"American Express Travel Rltd",
    "wof:placetype":"venue"
},
  "geometry": {"coordinates":[-97.730864,30.356212],"type":"Point"}
}