{
  "type": "Feature",
  "properties": {
    "iso:country":"US",
    "sg:address":"1029 Austin Ave",
    "sg:city":"Waco",
    "sg:classifiers":[
        {
            "category":"Shopping",
            "subcategory":"Florist",
            "type":"Retail Goods"
        }
    ],
    "sg:phone":"+1 254 753 3617",
    "sg:postcode":"76701",
    "sg:province":"TX",
    "sg:website":"www.reedsflowers.com",
    "wof:name":"Reed's Flowers",
    "wof:placetype":"venue"
},
  "geometry": {"coordinates":[-97.13631100000001,31.553075],"type":"Point"}
}