{
  "type": "Feature",
  "properties": {
    "iso:country":"US",
    "sg:address":"528 Lockwood Dr",
    "sg:city":"Richardson",
    "sg:classifiers":[
        {
            "category":"Organizations",
            "subcategory":"Community Association",
            "type":"Services"
        }
    ],
    "sg:phone":"+1 972 235 5667",
    "sg:postcode":"75080",
    "sg:province":"TX",
    "sg:tags":[
        "fraternal"
    ],
    "wof:name":"Richardson Masonic Lodge",
    "wof:placetype":"venue"
},
  "geometry": {"coordinates":[-96.736,32.951992],"type":"Point"}
}