{
  "type": "Feature",
  "properties": {
    "iso:country":"US",
    "sg:address":"200 N Almond St",
    "sg:city":"Alice",
    "sg:classifiers":[
        {
            "category":"Government",
            "subcategory":"Court House",
            "type":"Public Place"
        }
    ],
    "sg:phone":"+1 361 664 5997",
    "sg:postcode":"78332",
    "sg:province":"TX",
    "sg:tags":[
        "state",
        "counsel"
    ],
    "wof:name":"Attorney General",
    "wof:placetype":"venue"
},
  "geometry": {"coordinates":[-98.071117,27.75312],"type":"Point"}
}