{
  "type": "Feature",
  "properties": {
    "iso:country":"US",
    "sg:address":"1383 S Danville Dr",
    "sg:city":"Abilene",
    "sg:classifiers":[
        {
            "category":"Home & Garden",
            "subcategory":"Furniture",
            "type":"Retail Goods"
        },
        {
            "category":"Home & Garden",
            "subcategory":"Home Furnishings",
            "type":"Retail Goods"
        },
        {
            "category":"Home & Garden",
            "subcategory":"Carpets & Floor Coverings",
            "type":"Retail Goods"
        }
    ],
    "sg:phone":"+1 325 692 0300",
    "sg:postcode":"79605",
    "sg:province":"TX",
    "sg:tags":[
        "set",
        "house",
        "bed",
        "mattress",
        "bedroom",
        "store"
    ],
    "sg:website":"http://clickserve.us2.dartsearch.net/link/click?lid=43000000124318580",
    "wof:name":"Havertys Furniture",
    "wof:placetype":"venue"
},
  "geometry": {"coordinates":[-99.78537,32.449705],"type":"Point"}
}