{
  "type": "Feature",
  "properties": {
    "iso:country":"US",
    "sg:address":"4329 Heath Ct",
    "sg:city":"Plano",
    "sg:classifiers":[
        {
            "category":"Shopping",
            "subcategory":"Gifts & Souvenirs",
            "type":"Retail Goods"
        }
    ],
    "sg:phone":"+1 972 618 7320",
    "sg:postcode":"75024",
    "sg:province":"TX",
    "wof:name":"Renaissance Riches",
    "wof:placetype":"venue"
},
  "geometry": {"coordinates":[-96.776652,33.080351],"type":"Point"}
}