{
  "type": "Feature",
  "properties": {
    "iso:country":"US",
    "sg:address":"3312 Dooling St",
    "sg:city":"Fort Worth",
    "sg:classifiers":[
        {
            "category":"Retail",
            "subcategory":"Auto Rental",
            "type":"Services"
        }
    ],
    "sg:phone":"+1 817 335 7493",
    "sg:postcode":"76111",
    "sg:province":"TX",
    "sg:tags":[
        "renting",
        "truck",
        "leasing"
    ],
    "sg:website":"www.paccar.com",
    "wof:name":"Pac Lease",
    "wof:placetype":"venue"
},
  "geometry": {"coordinates":[-97.315687,32.805403],"type":"Point"}
}