{
  "type": "Feature",
  "properties": {
    "iso:country":"US",
    "sg:address":"2220 Hopkins St",
    "sg:city":"Houston",
    "sg:classifiers":[
        {
            "category":"Wholesale",
            "subcategory":"Drugs",
            "type":"Manufacturing & Wholesale Goods"
        }
    ],
    "sg:phone":"+1 713 807 0605",
    "sg:postcode":"77006",
    "sg:province":"TX",
    "wof:name":"Zohar Inc",
    "wof:placetype":"venue"
},
  "geometry": {"coordinates":[-95.388165,29.748974],"type":"Point"}
}