{
  "type": "Feature",
  "properties": {
    "iso:country":"US",
    "sg:address":"8350 Forest Ln",
    "sg:city":"Dallas",
    "sg:classifiers":[
        {
            "category":"Organizations",
            "subcategory":"Religious Organization",
            "type":"Services"
        }
    ],
    "sg:phone":"+1 214 349 7701",
    "sg:postcode":"75243",
    "sg:province":"TX",
    "sg:website":"www.greatercornerstone.org",
    "wof:name":"Greater Cornerstone Baptist Church",
    "wof:placetype":"venue"
},
  "geometry": {"coordinates":[-96.7603,32.909],"type":"Point"}
}