{
  "type": "Feature",
  "properties": {
    "iso:country":"US",
    "sg:address":"7232 Overhill Rd",
    "sg:city":"Fort Worth",
    "sg:classifiers":[
        {
            "category":"Wholesale",
            "subcategory":"Medical Equipment & Supplies",
            "type":"Manufacturing & Wholesale Goods"
        }
    ],
    "sg:phone":"+1 817 732 3383",
    "sg:postcode":"76116",
    "sg:province":"TX",
    "sg:tags":[
        "x",
        "apparatus"
    ],
    "wof:name":"Southwest Imaging Consultants",
    "wof:placetype":"venue"
},
  "geometry": {"coordinates":[-97.43797499999999,32.703157],"type":"Point"}
}