{
  "type": "Feature",
  "properties": {
    "iso:country":"US",
    "sg:address":"990 N Walnut Creek Dr #1005",
    "sg:city":"Mansfield",
    "sg:classifiers":[
        {
            "category":"Insurance",
            "subcategory":"Insurance Agent",
            "type":"Services"
        }
    ],
    "sg:phone":"+1 817 453 7500",
    "sg:postcode":"76063",
    "sg:province":"TX",
    "sg:tags":[
        "auto"
    ],
    "sg:website":"http://clickserve.dartsearch.net/link/click?lid=43000000277022837",
    "wof:name":"Allstate Insurance Company - Julia Serebro",
    "wof:placetype":"venue"
},
  "geometry": {"coordinates":[-97.132248,32.580513],"type":"Point"}
}