{
  "type": "Feature",
  "properties": {
    "iso:country":"US",
    "sg:address":"551 Cass Holland Rd",
    "sg:city":"Mineral Wells",
    "sg:classifiers":[
        {
            "category":"Building & Trades",
            "subcategory":"Construction",
            "type":"Services"
        }
    ],
    "sg:phone":"+1 940 325 0935",
    "sg:postcode":"76067",
    "sg:province":"TX",
    "sg:tags":[
        "excavation",
        "clearing",
        "land",
        "leveling",
        "contractor"
    ],
    "wof:name":"Under Construction Excavation",
    "wof:placetype":"venue"
},
  "geometry": {"coordinates":[-98.05691,32.77162],"type":"Point"}
}