{
  "type": "Feature",
  "properties": {
    "iso:country":"US",
    "sg:address":"1540 Dian St",
    "sg:city":"Houston",
    "sg:classifiers":[
        {
            "category":"Arts & Performance",
            "subcategory":"Theater",
            "type":"Entertainment"
        }
    ],
    "sg:phone":"+1 713 862 3770",
    "sg:postcode":"77008",
    "sg:province":"TX",
    "sg:tags":[
        "equipment",
        "supply",
        "theatrical"
    ],
    "wof:name":"R 'n'r Staging Inc.",
    "wof:placetype":"venue"
},
  "geometry": {"coordinates":[-95.41404199999999,29.798743],"type":"Point"}
}