{
  "type": "Feature",
  "properties": {
    "iso:country":"US",
    "sg:address":"1400 NE Mustang Dr",
    "sg:city":"Andrews",
    "sg:classifiers":[
        {
            "category":"Retail",
            "subcategory":"Auto Repair",
            "type":"Services"
        }
    ],
    "sg:phone":"+1 432 448 0752",
    "sg:postcode":"79714",
    "sg:province":"TX",
    "sg:tags":[
        "body",
        "automobile",
        "painting",
        "repairing"
    ],
    "wof:name":"Metal Works Unlimited",
    "wof:placetype":"venue"
},
  "geometry": {"coordinates":[-102.54338799999999,32.335079],"type":"Point"}
}