{
  "type": "Feature",
  "properties": {
    "iso:country":"US",
    "sg:address":"709 E Calton Rd",
    "sg:city":"Laredo",
    "sg:classifiers":[
        {
            "category":"Professional",
            "subcategory":"Employment Agencies",
            "type":"Services"
        }
    ],
    "sg:phone":"+1 956 723 8261",
    "sg:postcode":"78041",
    "sg:province":"TX",
    "sg:tags":[
        "consultant",
        "outplacement"
    ],
    "wof:name":"Employment Commission Texas",
    "wof:placetype":"venue"
},
  "geometry": {"coordinates":[-99.48735499999999,27.541584],"type":"Point"}
}