{
  "type": "Feature",
  "properties": {
    "iso:country":"US",
    "sg:address":"16006 Castletown Ct",
    "sg:city":"Spring",
    "sg:classifiers":[
        {
            "category":"Wholesale",
            "subcategory":"Chemicals & Plastics",
            "type":"Manufacturing & Wholesale Goods"
        }
    ],
    "sg:phone":"+1 281 376 1474",
    "sg:postcode":"77379",
    "sg:province":"TX",
    "sg:tags":[
        "trading"
    ],
    "wof:name":"Greenwoods International Inc",
    "wof:placetype":"venue"
},
  "geometry": {"coordinates":[-95.512157,30.014782],"type":"Point"}
}