{
  "type": "Feature",
  "properties": {
    "iso:country":"US",
    "sg:address":"609 Greensprings St",
    "sg:city":"Lewisville",
    "sg:classifiers":[
        {
            "category":"Building & Trades",
            "subcategory":"Construction",
            "type":"Services"
        }
    ],
    "sg:phone":"+1 972 436 2707",
    "sg:postcode":"75077",
    "sg:province":"TX",
    "sg:tags":[
        "carpenter"
    ],
    "wof:name":"J John Custom Trim",
    "wof:placetype":"venue"
},
  "geometry": {"coordinates":[-97.037824,33.083188],"type":"Point"}
}