{
  "type": "Feature",
  "properties": {
    "iso:country":"US",
    "sg:address":"605 Church St",
    "sg:city":"Brenham",
    "sg:classifiers":[
        {
            "category":"Organizations",
            "subcategory":"Religious Organization",
            "type":"Services"
        }
    ],
    "sg:phone":"+1 979 836 9481",
    "sg:postcode":"77833",
    "sg:province":"TX",
    "sg:tags":[
        "monastery",
        "convent"
    ],
    "wof:name":"Sister's Of St Francis",
    "wof:placetype":"venue"
},
  "geometry": {"coordinates":[-96.39801199999999,30.163482],"type":"Point"}
}