{
  "type": "Feature",
  "properties": {
    "iso:country":"US",
    "sg:address":"17480 Dallas Pkwy, Suite 120",
    "sg:city":"Dallas",
    "sg:classifiers":[
        {
            "category":"Health Services",
            "subcategory":"Dentist",
            "type":"Services"
        }
    ],
    "sg:phone":"+1 972 930 0100",
    "sg:postcode":"75287",
    "sg:province":"TX",
    "sg:tags":[
        "cosmetic"
    ],
    "wof:name":"Smile America",
    "wof:placetype":"venue"
},
  "geometry": {"coordinates":[-96.827714,32.989125],"type":"Point"}
}