{
  "type": "Feature",
  "properties": {
    "iso:country":"US",
    "sg:address":"3920 Alma Dr",
    "sg:city":"Plano",
    "sg:classifiers":[
        {
            "category":"Health Services",
            "subcategory":"Clinic",
            "type":"Services"
        }
    ],
    "sg:phone":"+1 469 467 8629",
    "sg:postcode":"75023",
    "sg:province":"TX",
    "sg:tags":[
        "welfare"
    ],
    "wof:name":"Metrocare Services Outpatient Clinics And Pharma",
    "wof:placetype":"venue"
},
  "geometry": {"coordinates":[-96.71019699999999,33.048389],"type":"Point"}
}