{
  "type": "Feature",
  "properties": {
    "iso:country":"US",
    "sg:address":"703 State Hwy 198",
    "sg:city":"Canton",
    "sg:classifiers":[
        {
            "category":"Shopping",
            "subcategory":"Used Merchandise",
            "type":"Retail Goods"
        }
    ],
    "sg:phone":"+1 903 567 6868",
    "sg:postcode":"75103",
    "sg:province":"TX",
    "sg:tags":[
        "store"
    ],
    "wof:name":"Red Barn Antiques",
    "wof:placetype":"venue"
},
  "geometry": {"coordinates":[-95.864555,32.55139],"type":"Point"}
}