{
  "type": "Feature",
  "properties": {
    "iso:country":"US",
    "sg:address":"1620 S Friendswood Dr",
    "sg:city":"Friendswood",
    "sg:classifiers":[
        {
            "category":"Utilities",
            "subcategory":"Cable",
            "type":"Services"
        },
        {
            "category":"Shopping",
            "subcategory":"Computers & Home Electronics",
            "type":"Retail Goods"
        }
    ],
    "sg:phone":"+1 281 482 5237",
    "sg:postcode":"77546",
    "sg:province":"TX",
    "sg:tags":[
        "satellite",
        "television",
        "antenna"
    ],
    "wof:name":"Accurate Cable & Electronics",
    "wof:placetype":"venue"
},
  "geometry": {"coordinates":[-95.188344,29.508947],"type":"Point"}
}