{
  "type": "Feature",
  "properties": {
    "iso:country":"US",
    "sg:address":"4102 S 31st Street Suite 350",
    "sg:city":"Temple",
    "sg:classifiers":[
        {
            "category":"Professional",
            "subcategory":"Accounting & Tax Preparation",
            "type":"Services"
        },
        {
            "category":"Professional",
            "subcategory":"Business Services",
            "type":"Services"
        }
    ],
    "sg:phone":"+1 254 771 9925",
    "sg:postcode":"76502",
    "sg:province":"TX",
    "sg:tags":[
        "return",
        "preparation-business",
        "taxes-consultants",
        "payroll",
        "representative",
        "notary",
        "public"
    ],
    "sg:website":"http://www.aceittaxservices.com",
    "wof:name":"ACE IT Tax Services LLC",
    "wof:placetype":"venue"
},
  "geometry": {"coordinates":[-97.372643,31.061172],"type":"Point"}
}