{
  "type": "Feature",
  "properties": {
    "iso:country":"US",
    "sg:address":"1316 Moller Rd",
    "sg:city":"Alvin",
    "sg:classifiers":[
        {
            "category":"Retail",
            "subcategory":"Portrait Studio",
            "type":"Services"
        },
        {
            "category":"Professional",
            "subcategory":"Art Services",
            "type":"Services"
        }
    ],
    "sg:phone":"+1 281 585 8565",
    "sg:postcode":"77511",
    "sg:province":"TX",
    "sg:tags":[
        "photographer",
        "photo"
    ],
    "wof:name":"Bell's Photography",
    "wof:placetype":"venue"
},
  "geometry": {"coordinates":[-95.256199,29.412744],"type":"Point"}
}