{
  "type": "Feature",
  "properties": {
    "iso:country":"US",
    "sg:address":"5316 Dazzle Dr",
    "sg:city":"Dallas",
    "sg:classifiers":[
        {
            "category":"Professional",
            "subcategory":"Computer Services",
            "type":"Services"
        }
    ],
    "sg:phone":"+1 214 330 6992",
    "sg:postcode":"75232",
    "sg:province":"TX",
    "wof:name":"All In One Computer Cente",
    "wof:placetype":"venue"
},
  "geometry": {"coordinates":[-96.84841400000001,32.679051],"type":"Point"}
}