{
  "type": "Feature",
  "properties": {
    "iso:country":"US",
    "sg:address":"2605 Dupree Cir",
    "sg:city":"Austin",
    "sg:classifiers":[
        {
            "category":"Professional",
            "subcategory":"Computer Services",
            "type":"Services"
        }
    ],
    "sg:phone":"+1 512 292 7445",
    "sg:postcode":"78748",
    "sg:province":"TX",
    "sg:tags":[
        "development",
        "consulting",
        "software"
    ],
    "wof:name":"Riverton & Associates Inc",
    "wof:placetype":"venue"
},
  "geometry": {"coordinates":[-97.849299,30.155846],"type":"Point"}
}