{
  "type": "Feature",
  "properties": {
    "iso:country":"US",
    "sg:address":"10601 Grant Rd",
    "sg:city":"Houston",
    "sg:classifiers":[
        {
            "category":"Organizations",
            "subcategory":"Religious Organization",
            "type":"Services"
        }
    ],
    "sg:phone":"+1 281 807 6301",
    "sg:postcode":"77429",
    "sg:province":"TX",
    "wof:name":"Global Vision",
    "wof:placetype":"venue"
},
  "geometry": {"coordinates":[-95.577389,29.967144],"type":"Point"}
}