{
  "type": "Feature",
  "properties": {
    "iso:country":"US",
    "sg:address":"125 Vista Way",
    "sg:city":"Benbrook",
    "sg:classifiers":[
        {
            "category":"Real Estate",
            "subcategory":"Real Estate Services",
            "type":"Services"
        },
        {
            "category":"Real Estate",
            "subcategory":"Real Estate Operator",
            "type":"Services"
        }
    ],
    "sg:phone":"+1 817 249 2143",
    "sg:postcode":"76126",
    "sg:province":"TX",
    "sg:tags":[
        "vacancy",
        "apartment",
        "rental",
        "listing"
    ],
    "wof:name":"Lakeview Apartments",
    "wof:placetype":"venue"
},
  "geometry": {"coordinates":[-97.473123,32.670252],"type":"Point"}
}