{
  "type": "Feature",
  "properties": {
    "iso:country":"US",
    "sg:address":"11943 Duran Canyon Ct",
    "sg:city":"Houston",
    "sg:classifiers":[
        {
            "category":"Freight",
            "type":"Transportation"
        }
    ],
    "sg:phone":"+1 281 537 2087",
    "sg:postcode":"77067",
    "sg:province":"TX",
    "wof:name":"Back & Forth Transport",
    "wof:placetype":"venue"
},
  "geometry": {"coordinates":[-95.473296,29.958351],"type":"Point"}
}