{
  "type": "Feature",
  "properties": {
    "iso:country":"US",
    "sg:address":"1204 Welch St",
    "sg:city":"Houston",
    "sg:classifiers":[
        {
            "category":"Arts & Performance",
            "subcategory":"Theater",
            "type":"Entertainment"
        }
    ],
    "sg:phone":"+1 713 522 9134",
    "sg:postcode":"77006",
    "sg:province":"TX",
    "sg:tags":[
        "theatrical"
    ],
    "wof:name":"180 Entertainment",
    "wof:placetype":"venue"
},
  "geometry": {"coordinates":[-95.396574,29.750435],"type":"Point"}
}