{
  "type": "Feature",
  "properties": {
    "iso:country":"US",
    "sg:address":"1515 Hendricks Ave",
    "sg:city":"Laredo",
    "sg:classifiers":[
        {
            "category":"Professional",
            "type":"Services"
        }
    ],
    "sg:phone":"+1 956 794 1500",
    "sg:postcode":"78040",
    "sg:province":"TX",
    "wof:name":"Ccms Child Care Management Svc",
    "wof:placetype":"venue"
},
  "geometry": {"coordinates":[-99.48647099999999,27.510104],"type":"Point"}
}