{
  "type": "Feature",
  "properties": {
    "iso:country":"US",
    "sg:address":"2274 N Collins St",
    "sg:city":"Arlington",
    "sg:classifiers":[
        {
            "category":"Shopping",
            "subcategory":"Department Store",
            "type":"Retail Goods"
        }
    ],
    "sg:phone":"+1 817 299 8224",
    "sg:postcode":"76011",
    "sg:province":"TX",
    "sg:tags":[
        "shop"
    ],
    "wof:name":"Dollar Fiesta",
    "wof:placetype":"venue"
},
  "geometry": {"coordinates":[-97.09693900000001,32.770755],"type":"Point"}
}