{
  "type": "Feature",
  "properties": {
    "iso:country":"US",
    "sg:address":"1605 Montana Ave",
    "sg:city":"El Paso",
    "sg:classifiers":[
        {
            "category":"Banks & Credit Unions",
            "subcategory":"Bank",
            "type":"Services"
        }
    ],
    "sg:phone":"+1 915 542 4700",
    "sg:postcode":"79902",
    "sg:province":"TX",
    "sg:tags":[
        "mortgage"
    ],
    "wof:name":"American Home Buyers Assn",
    "wof:placetype":"venue"
},
  "geometry": {"coordinates":[-106.47647600000001,31.773747],"type":"Point"}
}