{
  "type": "Feature",
  "properties": {
    "iso:country":"US",
    "sg:address":"1017 McClintic Dr",
    "sg:city":"Groesbeck",
    "sg:classifiers":[
        {
            "category":"Retail",
            "subcategory":"Auto Repair",
            "type":"Services"
        }
    ],
    "sg:phone":"+1 254 729 8404",
    "sg:postcode":"76642",
    "sg:province":"TX",
    "sg:tags":[
        "body"
    ],
    "wof:name":"Groesbeck Paint & Body",
    "wof:placetype":"venue"
},
  "geometry": {"coordinates":[-96.526962,31.543464],"type":"Point"}
}