{
  "type": "Feature",
  "properties": {
    "iso:country":"US",
    "sg:address":"502 State Hwy 71 W",
    "sg:city":"Bastrop",
    "sg:classifiers":[
        {
            "category":"Restaurant",
            "type":"Food & Drink"
        }
    ],
    "sg:phone":"+1 512 303 6003",
    "sg:postcode":"78602",
    "sg:province":"TX",
    "sg:tags":[
        "eating"
    ],
    "wof:name":"Taco Bell",
    "wof:placetype":"venue"
},
  "geometry": {"coordinates":[-97.35351799999999,30.111323],"type":"Point"}
}