{
  "type": "Feature",
  "properties": {
    "iso:country":"US",
    "sg:address":"3003 Memorial Ct",
    "sg:city":"Houston",
    "sg:classifiers":[
        {
            "category":"Professional",
            "subcategory":"Accounting & Tax Preparation",
            "type":"Services"
        }
    ],
    "sg:phone":"+1 713 862 9400",
    "sg:postcode":"77007",
    "sg:province":"TX",
    "sg:tags":[
        "accountant"
    ],
    "wof:name":"Quarters the At Memorial",
    "wof:placetype":"venue"
},
  "geometry": {"coordinates":[-95.391098,29.7656],"type":"Point"}
}