{
  "type": "Feature",
  "properties": {
    "iso:country":"US",
    "sg:address":"105 W Illinois Ave",
    "sg:city":"Midland",
    "sg:classifiers":[
        {
            "category":"Education",
            "subcategory":"College",
            "type":"Public Place"
        }
    ],
    "sg:phone":"+1 432 683 2832",
    "sg:postcode":"79701",
    "sg:province":"TX",
    "sg:tags":[
        "academic",
        "school"
    ],
    "wof:name":"Midland College Petroleum Pro",
    "wof:placetype":"venue"
},
  "geometry": {"coordinates":[-102.075616,31.999501],"type":"Point"}
}