{
  "type": "Feature",
  "properties": {
    "iso:country":"US",
    "sg:address":"14726 Celestial Pl",
    "sg:city":"Dallas",
    "sg:classifiers":[
        {
            "category":"Professional",
            "subcategory":"Lawyer & Legal Services",
            "type":"Services"
        }
    ],
    "sg:phone":"+1 972 726 1812",
    "sg:postcode":"75254",
    "sg:province":"TX",
    "sg:tags":[
        "attorney"
    ],
    "wof:name":"Dennis O Kraft",
    "wof:placetype":"venue"
},
  "geometry": {"coordinates":[-96.815198,32.945952],"type":"Point"}
}