{
  "type": "Feature",
  "properties": {
    "iso:country":"US",
    "sg:address":"535 S Frazier St",
    "sg:city":"Conroe",
    "sg:classifiers":[
        {
            "category":"Recreation",
            "subcategory":"Arcade",
            "type":"Entertainment"
        }
    ],
    "sg:phone":"+1 281 756 8769",
    "sg:postcode":"77301",
    "sg:province":"TX",
    "sg:tags":[
        "device",
        "operator",
        "amusement"
    ],
    "wof:name":"Centurion Amusements Inc",
    "wof:placetype":"venue"
},
  "geometry": {"coordinates":[-95.45891399999999,30.302993],"type":"Point"}
}