{
  "type": "Feature",
  "properties": {
    "iso:country":"US",
    "sg:address":"19333 US Hwy 59",
    "sg:city":"Humble",
    "sg:classifiers":[
        {
            "category":"Home & Garden",
            "subcategory":"Carpets & Floor Coverings",
            "type":"Retail Goods"
        }
    ],
    "sg:phone":"+1 281 548 3600",
    "sg:postcode":"77338",
    "sg:province":"TX",
    "sg:tags":[
        "material"
    ],
    "wof:name":"Houston Custom Carpets",
    "wof:placetype":"venue"
},
  "geometry": {"coordinates":[-95.272063,29.995973],"type":"Point"}
}