{
  "type": "Feature",
  "properties": {
    "iso:country":"US",
    "sg:address":"503 S Bridge St",
    "sg:city":"Hidalgo",
    "sg:classifiers":[
        {
            "category":"Retail",
            "subcategory":"Laundry & Dry Cleaning",
            "type":"Services"
        }
    ],
    "sg:phone":"+1 956 583 5837",
    "sg:postcode":"78557",
    "sg:province":"TX",
    "sg:tags":[
        "cleaners"
    ],
    "wof:name":"American Cleaners",
    "wof:placetype":"venue"
},
  "geometry": {"coordinates":[-98.262839,26.101406],"type":"Point"}
}