{
  "type": "Feature",
  "properties": {
    "iso:country":"US",
    "sg:address":"676 S Walnut Ave",
    "sg:city":"New Braunfels",
    "sg:classifiers":[
        {
            "category":"Shopping",
            "subcategory":"Computers & Home Electronics",
            "type":"Retail Goods"
        }
    ],
    "sg:phone":"+1 830 626 0939",
    "sg:postcode":"78130",
    "sg:province":"TX",
    "sg:tags":[
        "game",
        "video"
    ],
    "wof:name":"EB Games",
    "wof:placetype":"venue"
},
  "geometry": {"coordinates":[-98.12737799999999,29.688964],"type":"Point"}
}