{
  "type": "Feature",
  "properties": {
    "iso:country":"US",
    "sg:address":"1220 Telephone Rd",
    "sg:city":"Houston",
    "sg:classifiers":[
        {
            "category":"Professional",
            "type":"Services"
        }
    ],
    "sg:phone":"+1 713 926 6910",
    "sg:postcode":"77023",
    "sg:province":"TX",
    "wof:name":"A More On Parts",
    "wof:placetype":"venue"
},
  "geometry": {"coordinates":[-95.32757700000001,29.731446],"type":"Point"}
}