{
  "type": "Feature",
  "properties": {
    "iso:country":"US",
    "sg:address":"1201 Holik Dr",
    "sg:city":"College Station",
    "sg:classifiers":[
        {
            "category":"Real Estate",
            "subcategory":"Real Estate Operator",
            "type":"Services"
        }
    ],
    "sg:phone":"+1 979 696 2998",
    "sg:postcode":"77840",
    "sg:province":"TX",
    "sg:tags":[
        "apartment"
    ],
    "wof:name":"Ridgewood Village Apartments",
    "wof:placetype":"venue"
},
  "geometry": {"coordinates":[-96.31856399999999,30.606064],"type":"Point"}
}