{
  "type": "Feature",
  "properties": {
    "iso:country":"US",
    "sg:address":"4302 Sexton Ln",
    "sg:city":"Dallas",
    "sg:classifiers":[
        {
            "category":"Building & Trades",
            "subcategory":"Construction",
            "type":"Services"
        }
    ],
    "sg:phone":"+1 214 358 1858",
    "sg:postcode":"75229",
    "sg:province":"TX",
    "sg:tags":[
        "contractor"
    ],
    "wof:name":"Balen Roofing",
    "wof:placetype":"venue"
},
  "geometry": {"coordinates":[-96.836455,32.886723],"type":"Point"}
}