{
  "type": "Feature",
  "properties": {
    "iso:country":"US",
    "sg:address":"11379 Harry Hines Blvd",
    "sg:city":"Dallas",
    "sg:classifiers":[
        {
            "category":"Wholesale",
            "subcategory":"Electrical",
            "type":"Manufacturing & Wholesale Goods"
        }
    ],
    "sg:phone":"+1 972 484 9787",
    "sg:postcode":"75229",
    "sg:province":"TX",
    "sg:tags":[
        "electronic"
    ],
    "wof:name":"Car Audio Distributors",
    "wof:placetype":"venue"
},
  "geometry": {"coordinates":[-96.890728,32.893825],"type":"Point"}
}