{
  "type": "Feature",
  "properties": {
    "iso:country":"US",
    "sg:address":"3829 US Hwy 77",
    "sg:city":"Corpus Christi",
    "sg:classifiers":[
        {
            "category":"Banks & Credit Unions",
            "subcategory":"Bank",
            "type":"Services"
        }
    ],
    "sg:phone":"+1 361 767 3577",
    "sg:postcode":"78410",
    "sg:province":"TX",
    "wof:name":"First Convenience Bank",
    "wof:placetype":"venue"
},
  "geometry": {"coordinates":[-97.630567,27.855468],"type":"Point"}
}