{
  "type": "Feature",
  "properties": {
    "iso:country":"US",
    "sg:address":"123 E Peden Aly",
    "sg:city":"San Antonio",
    "sg:classifiers":[
        {
            "category":"Wholesale",
            "subcategory":"Scrap",
            "type":"Manufacturing & Wholesale Goods"
        }
    ],
    "sg:phone":"+1 210 225 5556",
    "sg:postcode":"78204",
    "sg:province":"TX",
    "sg:tags":[
        "plastic"
    ],
    "wof:name":"Nation Plastics",
    "wof:placetype":"venue"
},
  "geometry": {"coordinates":[-98.49738600000001,29.408607],"type":"Point"}
}