{
  "type": "Feature",
  "properties": {
    "iso:country":"US",
    "sg:address":"8911 State Hwy 6",
    "sg:city":"Cisco",
    "sg:classifiers":[
        {
            "category":"Food & Beverages",
            "subcategory":"Meat & Fish",
            "type":"Retail Goods"
        }
    ],
    "sg:phone":"+1 254 442 3495",
    "sg:postcode":"76437",
    "sg:province":"TX",
    "wof:name":"Rust Processing",
    "wof:placetype":"venue"
},
  "geometry": {"coordinates":[-98.917924,32.390127],"type":"Point"}
}