{
  "type": "Feature",
  "properties": {
    "iso:country":"US",
    "sg:address":"1529 Dorothy St",
    "sg:city":"Houston",
    "sg:classifiers":[
        {
            "category":"Sports & Exercise",
            "subcategory":"Gym",
            "type":"Entertainment"
        }
    ],
    "sg:phone":"+1 832 483 5787",
    "sg:postcode":"77008",
    "sg:province":"TX",
    "sg:tags":[
        "yoga"
    ],
    "sg:website":"www.hotyogahere.com",
    "wof:name":"Darla's Yoga Garden",
    "wof:placetype":"venue"
},
  "geometry": {"coordinates":[-95.40946599999999,29.798618],"type":"Point"}
}