{
  "type": "Feature",
  "properties": {
    "iso:country":"US",
    "sg:address":"5940 Lynette Cir",
    "sg:city":"Bryan",
    "sg:classifiers":[
        {
            "category":"Manufacturing",
            "subcategory":"Signs",
            "type":"Manufacturing & Wholesale Goods"
        }
    ],
    "sg:phone":"+1 979 779 8601",
    "sg:postcode":"77807",
    "sg:province":"TX",
    "sg:tags":[
        "specialty",
        "mfg"
    ],
    "wof:name":"SBS Signs",
    "wof:placetype":"venue"
},
  "geometry": {"coordinates":[-96.431556,30.617522],"type":"Point"}
}