{
  "type": "Feature",
  "properties": {
    "iso:country":"US",
    "sg:address":"1601 US Hwy 77",
    "sg:city":"Harlingen",
    "sg:classifiers":[
        {
            "category":"Retail",
            "subcategory":"Auto Repair",
            "type":"Services"
        }
    ],
    "sg:phone":"+1 956 423 5623",
    "sg:postcode":"78550",
    "sg:province":"TX",
    "sg:tags":[
        "automotive",
        "rental",
        "trailer",
        "utility"
    ],
    "wof:name":"Isidros Trailer Rentals",
    "wof:placetype":"venue"
},
  "geometry": {"coordinates":[-97.70313299999999,26.176524],"type":"Point"}
}