{
  "type": "Feature",
  "properties": {
    "iso:country":"US",
    "sg:address":"2006 N W S Young Dr",
    "sg:city":"Killeen",
    "sg:classifiers":[
        {
            "category":"Professional",
            "subcategory":"Computer Services",
            "type":"Services"
        }
    ],
    "sg:phone":"+1 254 628 1794",
    "sg:postcode":"76543",
    "sg:province":"TX",
    "sg:tags":[
        "repair"
    ],
    "wof:name":"Cyber-Mart Computers & More",
    "wof:placetype":"venue"
},
  "geometry": {"coordinates":[-97.706164,31.130238],"type":"Point"}
}