{
  "type": "Feature",
  "properties": {
    "iso:country":"US",
    "sg:address":"4980 Belt Line Rd",
    "sg:city":"Addison",
    "sg:classifiers":[
        {
            "category":"Fast Food",
            "type":"Food & Drink"
        },
        {
            "category":"Restaurant",
            "type":"Food & Drink"
        }
    ],
    "sg:postcode":"75254",
    "sg:province":"TX",
    "sg:tags":[
        "burger"
    ],
    "sg:website":"www.smashburger.com/",
    "wof:name":"Smashburger",
    "wof:placetype":"venue"
},
  "geometry": {"coordinates":[-96.822777,32.953992],"type":"Point"}
}