{
  "type": "Feature",
  "properties": {
    "iso:country":"US",
    "sg:address":"802 Emerald Wood Dr",
    "sg:city":"Austin",
    "sg:classifiers":[
        {
            "category":"Professional",
            "subcategory":"Employment Agencies",
            "type":"Services"
        }
    ],
    "sg:phone":"+1 512 445 2059",
    "sg:postcode":"78745",
    "sg:province":"TX",
    "sg:tags":[
        "help",
        "supply"
    ],
    "wof:name":"Never Outta Ink",
    "wof:placetype":"venue"
},
  "geometry": {"coordinates":[-97.782764,30.214847],"type":"Point"}
}