{
  "type": "Feature",
  "properties": {
    "iso:country":"US",
    "sg:address":"235 Barracuda St",
    "sg:city":"Hitchcock",
    "sg:classifiers":[
        {
            "category":"Shopping",
            "subcategory":"Hobbies, Toys, & Games",
            "type":"Retail Goods"
        }
    ],
    "sg:phone":"+1 409 935 3547",
    "sg:postcode":"77563",
    "sg:province":"TX",
    "wof:name":"Mari Berend",
    "wof:placetype":"venue"
},
  "geometry": {"coordinates":[-94.94132500000001,29.32775],"type":"Point"}
}