{
  "type": "Feature",
  "properties": {
    "iso:country":"US",
    "sg:address":"1326 Forest Home Dr",
    "sg:city":"Houston",
    "sg:classifiers":[
        {
            "category":"Local Transit",
            "type":"Transportation"
        }
    ],
    "sg:phone":"+1 713 227 2582",
    "sg:postcode":"77077",
    "sg:province":"TX",
    "sg:tags":[
        "passenger"
    ],
    "wof:name":"Car Club of Houston",
    "wof:placetype":"venue"
},
  "geometry": {"coordinates":[-95.637349,29.764174],"type":"Point"}
}