{
  "type": "Feature",
  "properties": {
    "iso:country":"US",
    "sg:address":"1550 Tarberry Rd",
    "sg:city":"Houston",
    "sg:classifiers":[
        {
            "category":"Professional",
            "subcategory":"Accounting & Tax Preparation",
            "type":"Services"
        }
    ],
    "sg:phone":"+1 281 931 6513",
    "sg:postcode":"77088",
    "sg:province":"TX",
    "sg:tags":[
        "return"
    ],
    "wof:name":"Savoy Tax Service Mary",
    "wof:placetype":"venue"
},
  "geometry": {"coordinates":[-95.42626799999999,29.883428],"type":"Point"}
}