{
  "type": "Feature",
  "properties": {
    "iso:country":"US",
    "sg:address":"811 NE Alsbury Blvd Ste 200",
    "sg:city":"Burleson",
    "sg:classifiers":[
        {
            "category":"Retail",
            "subcategory":"Laundry & Dry Cleaning",
            "type":"Services"
        }
    ],
    "sg:phone":"+1 817 295 2010",
    "sg:postcode":"76028",
    "sg:province":"TX",
    "wof:name":"Ken's Cleaners",
    "wof:placetype":"venue"
},
  "geometry": {"coordinates":[-97.3218,32.563099],"type":"Point"}
}