{
  "type": "Feature",
  "properties": {
    "iso:country":"US",
    "sg:address":"202 Sawdust Rd",
    "sg:city":"Spring",
    "sg:classifiers":[
        {
            "category":"Restaurant",
            "type":"Food & Drink"
        }
    ],
    "sg:menulink":"http://www.allmenus.com/tx/southeast-montgomery/156607-sweet-bella-italian-kitchen/menu/",
    "sg:phone":"+1 832 585 0066",
    "sg:postcode":"77380",
    "sg:province":"TX",
    "sg:tags":[
        "italian"
    ],
    "wof:name":"Sweet Bella Italian Kitchen",
    "wof:placetype":"venue"
},
  "geometry": {"coordinates":[-95.44658699999999,30.127495],"type":"Point"}
}