{
  "type": "Feature",
  "properties": {
    "iso:country":"US",
    "sg:address":"12330 Ledger Ln",
    "sg:city":"Houston",
    "sg:classifiers":[
        {
            "category":"Organizations",
            "subcategory":"Religious Organization",
            "type":"Services"
        }
    ],
    "sg:phone":"+1 713 453 4235",
    "sg:postcode":"77015",
    "sg:province":"TX",
    "wof:name":"Jacinto City Church of Christ",
    "wof:placetype":"venue"
},
  "geometry": {"coordinates":[-95.217221,29.752159],"type":"Point"}
}