{
  "type": "Feature",
  "properties": {
    "iso:country":"US",
    "sg:address":"4112 Briarbend Rd",
    "sg:city":"Dallas",
    "sg:classifiers":[
        {
            "category":"Real Estate",
            "subcategory":"Real Estate Agent",
            "type":"Services"
        }
    ],
    "sg:phone":"+1 972 713 7723",
    "sg:postcode":"75287",
    "sg:province":"TX",
    "wof:name":"Scandia Realty Inc",
    "wof:placetype":"venue"
},
  "geometry": {"coordinates":[-96.84213800000001,33.006403],"type":"Point"}
}