{
  "type": "Feature",
  "properties": {
    "iso:country":"US",
    "sg:address":"101 N Sylvania Ave",
    "sg:city":"Fort Worth",
    "sg:classifiers":[
        {
            "category":"Building & Trades",
            "subcategory":"Pest Control",
            "type":"Services"
        }
    ],
    "sg:phone":"+1 817 831 2078",
    "sg:postcode":"76111",
    "sg:province":"TX",
    "wof:name":"Cunningham Pest Control",
    "wof:placetype":"venue"
},
  "geometry": {"coordinates":[-97.30894499999999,32.766126],"type":"Point"}
}