{
  "type": "Feature",
  "properties": {
    "iso:country":"US",
    "sg:address":"10947 Mayfield Rd",
    "sg:city":"Houston",
    "sg:classifiers":[
        {
            "category":"Freight",
            "type":"Transportation"
        }
    ],
    "sg:phone":"+1 713 467 2635",
    "sg:postcode":"77043",
    "sg:province":"TX",
    "sg:tags":[
        "operator",
        "local",
        "trucking"
    ],
    "wof:name":"Mireles Rogelio Aguilar",
    "wof:placetype":"venue"
},
  "geometry": {"coordinates":[-95.57026500000001,29.795529],"type":"Point"}
}