{
  "type": "Feature",
  "properties": {
    "iso:country":"US",
    "sg:address":"526 N Interurban St",
    "sg:city":"Richardson",
    "sg:classifiers":[
        {
            "category":"Home & Garden",
            "subcategory":"Carpets & Floor Coverings",
            "type":"Retail Goods"
        }
    ],
    "sg:phone":"+1 972 234 1143",
    "sg:postcode":"75081",
    "sg:province":"TX",
    "wof:name":"Carpet One",
    "wof:placetype":"venue"
},
  "geometry": {"coordinates":[-96.72749,32.95705],"type":"Point"}
}