{
  "type": "Feature",
  "properties": {
    "iso:country":"US",
    "sg:address":"5002 Columbia Ave",
    "sg:city":"Dallas",
    "sg:classifiers":[
        {
            "category":"Shopping",
            "subcategory":"Shoes",
            "type":"Retail Goods"
        }
    ],
    "sg:phone":"+1 214 821 7178",
    "sg:postcode":"75214",
    "sg:province":"TX",
    "sg:tags":[
        "store"
    ],
    "wof:name":"Perfect Shoes",
    "wof:placetype":"venue"
},
  "geometry": {"coordinates":[-96.76175499999999,32.796382],"type":"Point"}
}