{
  "type": "Feature",
  "properties": {
    "iso:country":"US",
    "sg:address":"5921 San Pedro Ave",
    "sg:city":"San Antonio",
    "sg:classifiers":[
        {
            "category":"Retail",
            "subcategory":"Auto Repair",
            "type":"Services"
        }
    ],
    "sg:phone":"+1 210 342 5507",
    "sg:postcode":"78212",
    "sg:province":"TX",
    "sg:tags":[
        "specializing",
        "automotive",
        "lubrication"
    ],
    "wof:name":"Jiffy Lube",
    "wof:placetype":"venue"
},
  "geometry": {"coordinates":[-98.499336,29.488791],"type":"Point"}
}