{
  "type": "Feature",
  "properties": {
    "iso:country":"US",
    "sg:address":"207 Bellevue Dr",
    "sg:city":"Cleburne",
    "sg:classifiers":[
        {
            "category":"Professional",
            "type":"Services"
        }
    ],
    "sg:phone":"+1 817 558 8239",
    "sg:postcode":"76033",
    "sg:province":"TX",
    "wof:name":"Lindas Studio",
    "wof:placetype":"venue"
},
  "geometry": {"coordinates":[-97.394469,32.339322],"type":"Point"}
}