{
  "type": "Feature",
  "properties": {
    "iso:country":"US",
    "sg:address":"11942 Massey Ave",
    "sg:city":"Tyler",
    "sg:classifiers":[
        {
            "category":"Manufacturing",
            "subcategory":"Building Materials",
            "type":"Manufacturing & Wholesale Goods"
        }
    ],
    "sg:phone":"+1 903 877 0300",
    "sg:postcode":"75708",
    "sg:province":"TX",
    "sg:tags":[
        "member",
        "mfg",
        "wood",
        "structural"
    ],
    "wof:name":"Tyler Truss Systems Inc",
    "wof:placetype":"venue"
},
  "geometry": {"coordinates":[-95.195719,32.437484],"type":"Point"}
}