{
  "type": "Feature",
  "properties": {
    "iso:country":"US",
    "sg:address":"301 Cherry St",
    "sg:city":"Waco",
    "sg:classifiers":[
        {
            "category":"Social Services",
            "subcategory":"Child Care",
            "type":"Services"
        }
    ],
    "sg:phone":"+1 254 753 1147",
    "sg:postcode":"76704",
    "sg:province":"TX",
    "wof:name":"F C Green Child Dev Ctr",
    "wof:placetype":"venue"
},
  "geometry": {"coordinates":[-97.11755599999999,31.567935],"type":"Point"}
}