{
  "type": "Feature",
  "properties": {
    "iso:country":"US",
    "sg:address":"12108 Robin Ridge Ln",
    "sg:city":"Austin",
    "sg:classifiers":[
        {
            "category":"Manufacturing",
            "subcategory":"Textiles",
            "type":"Manufacturing & Wholesale Goods"
        }
    ],
    "sg:phone":"+1 512 249 9043",
    "sg:postcode":"78750",
    "sg:province":"TX",
    "sg:tags":[
        "finishing",
        "plant",
        "cotton"
    ],
    "wof:name":"Turkel Corporation",
    "wof:placetype":"venue"
},
  "geometry": {"coordinates":[-97.798316,30.451837],"type":"Point"}
}