{
  "type": "Feature",
  "properties": {
    "iso:country":"US",
    "sg:address":"1509 Willow St",
    "sg:city":"Austin",
    "sg:classifiers":[
        {
            "category":"Professional",
            "type":"Services"
        }
    ],
    "sg:phone":"+1 512 482 9949",
    "sg:postcode":"78702",
    "sg:province":"TX",
    "wof:name":"Wendy McKibben",
    "wof:placetype":"venue"
},
  "geometry": {"coordinates":[-97.729936,30.258035],"type":"Point"}
}