{
  "type": "Feature",
  "properties": {
    "iso:country":"US",
    "sg:address":"8730 Avator Cir",
    "sg:city":"Boerne",
    "sg:classifiers":[
        {
            "category":"Recreation",
            "type":"Entertainment"
        }
    ],
    "sg:phone":"+1 830 981 8297",
    "sg:postcode":"78015",
    "sg:province":"TX",
    "sg:tags":[
        "camps-recreational"
    ],
    "wof:name":"Camp Independence Of San Antonio",
    "wof:placetype":"venue"
},
  "geometry": {"coordinates":[-98.657089,29.73584],"type":"Point"}
}