{
  "type": "Feature",
  "properties": {
    "iso:country":"US",
    "sg:address":"1057 Granite Ln",
    "sg:city":"De Soto",
    "sg:classifiers":[
        {
            "category":"Professional",
            "type":"Services"
        }
    ],
    "sg:phone":"+1 972 223 5146",
    "sg:postcode":"75115",
    "sg:province":"TX",
    "wof:name":"Kendrick Information Technolog",
    "wof:placetype":"venue"
},
  "geometry": {"coordinates":[-96.880809,32.589211],"type":"Point"}
}