{
  "type": "Feature",
  "properties": {
    "iso:country":"US",
    "sg:address":"806 W Dagmar St",
    "sg:city":"Beeville",
    "sg:classifiers":[
        {
            "category":"Wholesale",
            "subcategory":"Vending Machines",
            "type":"Manufacturing & Wholesale Goods"
        }
    ],
    "sg:phone":"+1 361 358 2191",
    "sg:postcode":"78102",
    "sg:province":"TX",
    "wof:name":"Rhonda G Smith Vending",
    "wof:placetype":"venue"
},
  "geometry": {"coordinates":[-97.764346,28.417099],"type":"Point"}
}