{
  "type": "Feature",
  "properties": {
    "iso:country":"US",
    "sg:address":"10341 East Fwy",
    "sg:city":"Houston",
    "sg:classifiers":[
        {
            "category":"Travel",
            "subcategory":"Hotels & Motels",
            "type":"Entertainment"
        }
    ],
    "sg:phone":"+1 713 678 7575",
    "sg:postcode":"77029",
    "sg:province":"TX",
    "wof:name":"Premier Inn",
    "wof:placetype":"venue"
},
  "geometry": {"coordinates":[-95.237602,29.7735],"type":"Point"}
}