{
  "type": "Feature",
  "properties": {
    "iso:country":"US",
    "sg:address":"6102 Chicago Ave",
    "sg:city":"Lubbock",
    "sg:classifiers":[
        {
            "category":"Shopping",
            "subcategory":"Catalog Store",
            "type":"Retail Goods"
        }
    ],
    "sg:phone":"+1 806 798 1116",
    "sg:postcode":"79424",
    "sg:province":"TX",
    "sg:tags":[
        "mail",
        "television",
        "order",
        "sales"
    ],
    "wof:name":"Shape and Dry Enterprises",
    "wof:placetype":"venue"
},
  "geometry": {"coordinates":[-101.932073,33.537897],"type":"Point"}
}