{
  "type": "Feature",
  "properties": {
    "iso:country":"US",
    "sg:address":"1801 Salina St",
    "sg:city":"Austin",
    "sg:classifiers":[
        {
            "category":"Cinema",
            "subcategory":"Movie Rental",
            "type":"Entertainment"
        }
    ],
    "sg:phone":"+1 512 732 1228",
    "sg:postcode":"78702",
    "sg:province":"TX",
    "sg:tags":[
        "motion",
        "picture",
        "distributor",
        "film",
        "exchange"
    ],
    "wof:name":"24/36 Productions",
    "wof:placetype":"venue"
},
  "geometry": {"coordinates":[-97.72197,30.27861],"type":"Point"}
}