{
  "type": "Feature",
  "properties": {
    "iso:country":"US",
    "sg:address":"1216 Heights St",
    "sg:city":"Pasadena",
    "sg:classifiers":[
        {
            "category":"Retail",
            "subcategory":"Auto Repair",
            "type":"Services"
        }
    ],
    "sg:phone":"+1 713 534 9038",
    "sg:postcode":"77503",
    "sg:province":"TX",
    "sg:tags":[
        "repairing",
        "automobile"
    ],
    "wof:name":"Gordo's Auto Ctr",
    "wof:placetype":"venue"
},
  "geometry": {"coordinates":[-95.172045,29.693267],"type":"Point"}
}