{
  "type": "Feature",
  "properties": {
    "iso:country":"US",
    "sg:address":"5311 N Mccoll Rd Ste 108",
    "sg:city":"Mcallen",
    "sg:classifiers":[
        {
            "category":"Professional",
            "subcategory":"Lawyer & Legal Services",
            "type":"Services"
        }
    ],
    "sg:phone":"+1 956 618 3220",
    "sg:postcode":"78504",
    "sg:province":"TX",
    "sg:tags":[
        "information",
        "attorney",
        "referral"
    ],
    "wof:name":"Information On Call",
    "wof:placetype":"venue"
},
  "geometry": {"coordinates":[-98.20482199999999,26.248535],"type":"Point"}
}