{
  "type": "Feature",
  "properties": {
    "iso:country":"US",
    "sg:address":"6722 Wood Duck Dr",
    "sg:city":"Corpus Christi",
    "sg:classifiers":[
        {
            "category":"Retail",
            "subcategory":"Laundry & Dry Cleaning",
            "type":"Services"
        }
    ],
    "sg:phone":"+1 361 728 9540",
    "sg:postcode":"78413",
    "sg:province":"TX",
    "sg:tags":[
        "cleaners",
        "rug",
        "carpet"
    ],
    "wof:name":"C C Top Notch Carpet Cleaning",
    "wof:placetype":"venue"
},
  "geometry": {"coordinates":[-97.395279,27.682924],"type":"Point"}
}