{
  "type": "Feature",
  "properties": {
    "iso:country":"US",
    "sg:address":"10899 Royal Pines Dr",
    "sg:city":"Conroe",
    "sg:classifiers":[
        {
            "category":"Building & Trades",
            "subcategory":"Construction",
            "type":"Services"
        }
    ],
    "sg:phone":"+1 936 520 8551",
    "sg:postcode":"77303",
    "sg:province":"TX",
    "sg:tags":[
        "hanging",
        "contractor"
    ],
    "wof:name":"Garcia Painting",
    "wof:placetype":"venue"
},
  "geometry": {"coordinates":[-95.40568500000001,30.41493],"type":"Point"}
}