{
  "type": "Feature",
  "properties": {
    "iso:country":"US",
    "sg:address":"3333 Telephone Rd",
    "sg:city":"Houston",
    "sg:classifiers":[
        {
            "category":"Home & Garden",
            "subcategory":"Furniture",
            "type":"Retail Goods"
        }
    ],
    "sg:phone":"+1 713 514 1200",
    "sg:postcode":"77023",
    "sg:province":"TX",
    "sg:tags":[
        "store"
    ],
    "wof:name":"Famsa",
    "wof:placetype":"venue"
},
  "geometry": {"coordinates":[-95.315335,29.711664],"type":"Point"}
}