{
  "type": "Feature",
  "properties": {
    "iso:country":"US",
    "sg:address":"2604 S Zapata Hwy",
    "sg:city":"Laredo",
    "sg:classifiers":[
        {
            "category":"Restaurant",
            "type":"Food & Drink"
        }
    ],
    "sg:phone":"+1 956 791 1379",
    "sg:postcode":"78046",
    "sg:province":"TX",
    "wof:name":"Mariachi Express",
    "wof:placetype":"venue"
},
  "geometry": {"coordinates":[-99.47690299999999,27.470899],"type":"Point"}
}