{
  "type": "Feature",
  "properties": {
    "iso:country":"US",
    "sg:address":"104 E 3rd St",
    "sg:city":"Hallettsville",
    "sg:classifiers":[
        {
            "category":"Home & Garden",
            "subcategory":"Hardware",
            "type":"Retail Goods"
        }
    ],
    "sg:phone":"+1 361 798 5371",
    "sg:postcode":"77964",
    "sg:province":"TX",
    "wof:name":"Hallettsville Hardware & Auto",
    "wof:placetype":"venue"
},
  "geometry": {"coordinates":[-96.943208,29.444492],"type":"Point"}
}