{
  "type": "Feature",
  "properties": {
    "iso:country":"US",
    "sg:address":"404 Walton Dr",
    "sg:city":"Texarkana",
    "sg:classifiers":[
        {
            "category":"Personal",
            "subcategory":"Beauty Salon",
            "type":"Services"
        },
        {
            "category":"Personal",
            "subcategory":"Nail Salon",
            "type":"Services"
        }
    ],
    "sg:phone":"+1 903 838 0617",
    "sg:postcode":"75501",
    "sg:province":"TX",
    "wof:name":"Ck Nail & Spa",
    "wof:placetype":"venue"
},
  "geometry": {"coordinates":[-94.09934800000001,33.44354],"type":"Point"}
}