{
  "type": "Feature",
  "properties": {
    "iso:country":"US",
    "sg:address":"5331 Summer Snow Dr",
    "sg:city":"Houston",
    "sg:classifiers":[
        {
            "category":"Real Estate",
            "subcategory":"Real Estate Agent",
            "type":"Services"
        }
    ],
    "sg:phone":"+1 713 466 0501",
    "sg:postcode":"77041",
    "sg:province":"TX",
    "wof:name":"Singer Vntr A Texas Ltd Partnr",
    "wof:placetype":"venue"
},
  "geometry": {"coordinates":[-95.608566,29.84488],"type":"Point"}
}