{
  "type": "Feature",
  "properties": {
    "iso:country":"US",
    "sg:address":"2406 Suzette Ave",
    "sg:city":"San Antonio",
    "sg:classifiers":[
        {
            "category":"Retail",
            "subcategory":"Repair Shop",
            "type":"Services"
        }
    ],
    "sg:phone":"+1 210 673 6219",
    "sg:postcode":"78227",
    "sg:province":"TX",
    "sg:tags":[
        "machine",
        "sewing"
    ],
    "wof:name":"AAA Sewing",
    "wof:placetype":"venue"
},
  "geometry": {"coordinates":[-98.62287600000001,29.405111],"type":"Point"}
}