{
  "type": "Feature",
  "properties": {
    "iso:country":"US",
    "sg:address":"3419 Westminster Ave # 202",
    "sg:city":"Dallas",
    "sg:classifiers":[
        {
            "category":"Communications",
            "subcategory":"Film & Video Production",
            "type":"Services"
        }
    ],
    "sg:phone":"+1 214 369 3002",
    "sg:postcode":"75205",
    "sg:province":"TX",
    "sg:tags":[
        "tv",
        "picture",
        "radio",
        "motion",
        "companies-film"
    ],
    "sg:website":"http://www.roberttullierproductions.com",
    "wof:name":"Robert Tullier Productions Inc",
    "wof:placetype":"venue"
},
  "geometry": {"coordinates":[-96.787537,32.850231],"type":"Point"}
}