{
  "type": "Feature",
  "properties": {
    "iso:country":"US",
    "sg:address":"5220 Spring Valley Rd # 190",
    "sg:city":"Dallas",
    "sg:classifiers":[
        {
            "category":"Place Of Worship",
            "type":"Public Place"
        }
    ],
    "sg:phone":"+1 469 374 0446",
    "sg:postcode":"75254",
    "sg:province":"TX",
    "sg:tags":[
        "church"
    ],
    "wof:name":"Ses Church Financial",
    "wof:placetype":"venue"
},
  "geometry": {"coordinates":[-96.820165,32.939461],"type":"Point"}
}