{
  "type": "Feature",
  "properties": {
    "iso:country":"US",
    "sg:address":"4210 Spicewood Springs Rd Ste 210",
    "sg:city":"Austin",
    "sg:classifiers":[
        {
            "category":"Professional",
            "subcategory":"Lawyer & Legal Services",
            "type":"Services"
        }
    ],
    "sg:phone":"+1 512 420 0555",
    "sg:postcode":"78759",
    "sg:province":"TX",
    "sg:tags":[
        "divorce",
        "law",
        "family"
    ],
    "sg:website":"www.milnerlawfirm.com",
    "wof:name":"Milner Law Firm",
    "wof:placetype":"venue"
},
  "geometry": {"coordinates":[-97.756079,30.371479],"type":"Point"}
}