{
  "type": "Feature",
  "properties": {
    "iso:country":"US",
    "sg:address":"4625 Crockett St",
    "sg:city":"Amarillo",
    "sg:classifiers":[
        {
            "category":"Shopping",
            "subcategory":"Hobbies, Toys, & Games",
            "type":"Retail Goods"
        }
    ],
    "sg:phone":"+1 806 353 6908",
    "sg:postcode":"79110",
    "sg:province":"TX",
    "sg:tags":[
        "craft"
    ],
    "wof:name":"L & J Crafts Etc",
    "wof:placetype":"venue"
},
  "geometry": {"coordinates":[-101.858267,35.159282],"type":"Point"}
}