{
  "type": "Feature",
  "properties": {
    "iso:country":"US",
    "sg:address":"2037 Allen-Genoa Rd",
    "sg:city":"Pasadena",
    "sg:classifiers":[
        {
            "category":"Retail",
            "subcategory":"Auto Repair",
            "type":"Services"
        }
    ],
    "sg:phone":"+1 713 472 3124",
    "sg:postcode":"77502",
    "sg:province":"TX",
    "sg:tags":[
        "transmission"
    ],
    "wof:name":"A-OK Transmission Service",
    "wof:placetype":"venue"
},
  "geometry": {"coordinates":[-95.229339,29.683278],"type":"Point"}
}