{
  "type": "Feature",
  "properties": {
    "iso:country":"US",
    "sg:address":"205 N Velasco St",
    "sg:city":"Angleton",
    "sg:classifiers":[
        {
            "category":"Professional",
            "subcategory":"Employment Agencies",
            "type":"Services"
        }
    ],
    "sg:phone":"+1 979 549 0826",
    "sg:postcode":"77515",
    "sg:province":"TX",
    "sg:tags":[
        "opportunity"
    ],
    "wof:name":"Labor Ready",
    "wof:placetype":"venue"
},
  "geometry": {"coordinates":[-95.43189599999999,29.165746],"type":"Point"}
}