{
  "type": "Feature",
  "properties": {
    "iso:country":"US",
    "sg:address":"207 N Binkley St",
    "sg:city":"Sherman",
    "sg:classifiers":[
        {
            "category":"Organizations",
            "subcategory":"Religious Organization",
            "type":"Services"
        }
    ],
    "sg:phone":"+1 903 892 1995",
    "sg:postcode":"75092",
    "sg:province":"TX",
    "sg:tags":[
        "church"
    ],
    "wof:name":"Pecan Grove Baptist Church",
    "wof:placetype":"venue"
},
  "geometry": {"coordinates":[-96.621582,33.635897],"type":"Point"}
}