{
  "type": "Feature",
  "properties": {
    "iso:country":"US",
    "sg:address":"1005 W Jefferson",
    "sg:city":"Dallas",
    "sg:classifiers":[
        {
            "category":"Professional",
            "subcategory":"Lawyer & Legal Services",
            "type":"Services"
        }
    ],
    "sg:phone":"+1 469 522 3225",
    "sg:postcode":"75208",
    "sg:province":"TX",
    "sg:website":"immigrationlawyerdallastx.com",
    "wof:name":"The Dickson Firm, PLLC",
    "wof:placetype":"venue"
},
  "geometry": {"coordinates":[-96.83992000000001,32.743516],"type":"Point"}
}