{
  "type": "Feature",
  "properties": {
    "iso:country":"US",
    "sg:address":"1312 N Jim Miller Rd",
    "sg:city":"Dallas",
    "sg:classifiers":[
        {
            "category":"Retail",
            "subcategory":"Laundry & Dry Cleaning",
            "type":"Services"
        }
    ],
    "sg:phone":"+1 214 398 9856",
    "sg:postcode":"75217",
    "sg:province":"TX",
    "sg:tags":[
        "drycleaning",
        "plant"
    ],
    "wof:name":"Prescott One Hour Cleaners",
    "wof:placetype":"venue"
},
  "geometry": {"coordinates":[-96.699898,32.734798],"type":"Point"}
}