{
  "type": "Feature",
  "properties": {
    "iso:country":"US",
    "sg:address":"1430 FM 1960 W",
    "sg:city":"Houston",
    "sg:classifiers":[
        {
            "category":"Personal",
            "type":"Services"
        }
    ],
    "sg:phone":"+1 281 880 8826",
    "sg:postcode":"77090",
    "sg:province":"TX",
    "sg:tags":[
        "salon",
        "tanning"
    ],
    "wof:name":"Banana Tan",
    "wof:placetype":"venue"
},
  "geometry": {"coordinates":[-95.45074200000001,30.014039],"type":"Point"}
}