{
  "type": "Feature",
  "properties": {
    "iso:country":"US",
    "sg:address":"2944 Motley Dr",
    "sg:city":"Mesquite",
    "sg:classifiers":[
        {
            "category":"Manufacturing",
            "subcategory":"Furniture",
            "type":"Manufacturing & Wholesale Goods"
        }
    ],
    "sg:phone":"+1 972 681 4541",
    "sg:postcode":"75150",
    "sg:province":"TX",
    "sg:tags":[
        "equipment",
        "supply"
    ],
    "wof:name":"Cuff-Muse Marketing",
    "wof:placetype":"venue"
},
  "geometry": {"coordinates":[-96.648938,32.804827],"type":"Point"}
}