{
  "type": "Feature",
  "properties": {
    "iso:country":"US",
    "sg:address":"107 Ranch Rd 620 S",
    "sg:city":"Lakeway",
    "sg:classifiers":[
        {
            "category":"Building & Trades",
            "subcategory":"Construction",
            "type":"Services"
        }
    ],
    "sg:phone":"+1 512 266 3908",
    "sg:postcode":"78734",
    "sg:province":"TX",
    "sg:tags":[
        "home",
        "builder"
    ],
    "wof:name":"JWJ Homes",
    "wof:placetype":"venue"
},
  "geometry": {"coordinates":[-97.952327,30.363498],"type":"Point"}
}