{
  "type": "Feature",
  "properties": {
    "iso:country":"US",
    "sg:address":"1163 Horizon Blvd",
    "sg:city":"El Paso",
    "sg:classifiers":[
        {
            "category":"Wholesale",
            "subcategory":"Construction Materials",
            "type":"Manufacturing & Wholesale Goods"
        }
    ],
    "sg:phone":"+1 915 858 3780",
    "sg:postcode":"79927",
    "sg:province":"TX",
    "sg:tags":[
        "pallet",
        "skid"
    ],
    "wof:name":"Mc Carthy Pallets Inc",
    "wof:placetype":"venue"
},
  "geometry": {"coordinates":[-106.243208,31.658202],"type":"Point"}
}