{
  "type": "Feature",
  "properties": {
    "iso:country":"US",
    "sg:address":"2075 Laurel Oaks Dr",
    "sg:city":"Irving",
    "sg:classifiers":[
        {
            "category":"Recreation",
            "type":"Entertainment"
        }
    ],
    "sg:phone":"+1 281 440 1959",
    "sg:postcode":"75060",
    "sg:province":"TX",
    "sg:tags":[
        "center"
    ],
    "wof:name":"Laurel Oaks Recreational Ctr",
    "wof:placetype":"venue"
},
  "geometry": {"coordinates":[-96.938131,32.791637],"type":"Point"}
}