{
  "type": "Feature",
  "properties": {
    "iso:country":"US",
    "sg:address":"13101 Northwest Fwy Ste 110",
    "sg:city":"Houston",
    "sg:classifiers":[
        {
            "category":"Professional",
            "subcategory":"Employment Agencies",
            "type":"Services"
        }
    ],
    "sg:phone":"+1 713 329 9990",
    "sg:postcode":"77040",
    "sg:province":"TX",
    "sg:website":"www.carltonstaffing.com",
    "wof:name":"Carlton Staffing",
    "wof:placetype":"venue"
},
  "geometry": {"coordinates":[-95.501198,29.846001],"type":"Point"}
}