{
  "type": "Feature",
  "properties": {
    "iso:country":"US",
    "sg:address":"2410 Sieber Dr",
    "sg:city":"Houston",
    "sg:classifiers":[
        {
            "category":"Real Estate",
            "subcategory":"Real Estate Agent",
            "type":"Services"
        }
    ],
    "sg:phone":"+1 713 941 0596",
    "sg:postcode":"77017",
    "sg:province":"TX",
    "wof:name":"Whites Appraisal Svc",
    "wof:placetype":"venue"
},
  "geometry": {"coordinates":[-95.238617,29.674114],"type":"Point"}
}