{
  "type": "Feature",
  "properties": {
    "iso:country":"US",
    "sg:address":"5414 Port Townsend Dr",
    "sg:city":"San Antonio",
    "sg:classifiers":[
        {
            "category":"Building & Trades",
            "subcategory":"Construction",
            "type":"Services"
        }
    ],
    "sg:phone":"+1 210 932 3560",
    "sg:postcode":"78242",
    "sg:province":"TX",
    "sg:tags":[
        "concrete",
        "contractor"
    ],
    "wof:name":"Bondoc & Bondoc Cncrt Constr",
    "wof:placetype":"venue"
},
  "geometry": {"coordinates":[-98.60736900000001,29.330546],"type":"Point"}
}