{
  "type": "Feature",
  "properties": {
    "iso:country":"US",
    "sg:address":"2427 Finley Rd",
    "sg:city":"Irving",
    "sg:classifiers":[
        {
            "category":"Organizations",
            "subcategory":"Religious Organization",
            "type":"Services"
        }
    ],
    "sg:phone":"+1 972 659 1034",
    "sg:postcode":"75062",
    "sg:province":"TX",
    "wof:name":"Irving Fith Church of Nazarene",
    "wof:placetype":"venue"
},
  "geometry": {"coordinates":[-96.979795,32.850914],"type":"Point"}
}