{
  "type": "Feature",
  "properties": {
    "iso:country":"US",
    "sg:address":"3201 Bee Caves Rd Ste 100",
    "sg:city":"Austin",
    "sg:classifiers":[
        {
            "category":"Restaurant",
            "type":"Food & Drink"
        }
    ],
    "sg:phone":"+1 512 732 0010",
    "sg:postcode":"78746",
    "sg:province":"TX",
    "wof:name":"Holiday House Restaurant",
    "wof:placetype":"venue"
},
  "geometry": {"coordinates":[-97.798698,30.273199],"type":"Point"}
}