{
  "type": "Feature",
  "properties": {
    "iso:country":"US",
    "sg:address":"966 Leadenhall Cir",
    "sg:city":"Channelview",
    "sg:classifiers":[
        {
            "category":"Retail",
            "subcategory":"Laundry & Dry Cleaning",
            "type":"Services"
        }
    ],
    "sg:phone":"+1 281 862 0571",
    "sg:postcode":"77530",
    "sg:province":"TX",
    "wof:name":"Ellen Tanner",
    "wof:placetype":"venue"
},
  "geometry": {"coordinates":[-95.14684099999999,29.793168],"type":"Point"}
}