{
  "type": "Feature",
  "properties": {
    "iso:country":"US",
    "sg:address":"5440 E Lakeshore Dr",
    "sg:city":"Belton",
    "sg:classifiers":[
        {
            "category":"Building & Trades",
            "subcategory":"Landscaping Services",
            "type":"Services"
        }
    ],
    "sg:phone":"+1 254 933 9182",
    "sg:postcode":"76513",
    "sg:province":"TX",
    "wof:name":"Freedom Rain",
    "wof:placetype":"venue"
},
  "geometry": {"coordinates":[-97.508026,31.106477],"type":"Point"}
}