{
  "type": "Feature",
  "properties": {
    "iso:country":"US",
    "sg:address":"6600 Lebanon Rd",
    "sg:city":"Frisco",
    "sg:classifiers":[
        {
            "category":"Social Services",
            "subcategory":"Child Care",
            "type":"Services"
        }
    ],
    "sg:phone":"+1 972 712 8080",
    "sg:postcode":"75034",
    "sg:province":"TX",
    "sg:tags":[
        "day"
    ],
    "wof:name":"Starwood Montessori School",
    "wof:placetype":"venue"
},
  "geometry": {"coordinates":[-96.814775,33.123669],"type":"Point"}
}