{
  "type": "Feature",
  "properties": {
    "iso:country":"US",
    "sg:address":"3536 Milton Ave",
    "sg:city":"Dallas",
    "sg:classifiers":[
        {
            "category":"Retail",
            "subcategory":"Veterinary Services",
            "type":"Services"
        }
    ],
    "sg:phone":"+1 214 363 2129",
    "sg:postcode":"75205",
    "sg:province":"TX",
    "sg:tags":[
        "veterinarian"
    ],
    "wof:name":"Cameron Malcom D DVM",
    "wof:placetype":"venue"
},
  "geometry": {"coordinates":[-96.791,32.8484],"type":"Point"}
}