{
  "type": "Feature",
  "properties": {
    "iso:country":"US",
    "sg:address":"11027 Southwest Fwy",
    "sg:city":"Houston",
    "sg:classifiers":[
        {
            "category":"Autos & Motor Vehicles",
            "subcategory":"Automobile Sales",
            "type":"Retail Goods"
        }
    ],
    "sg:phone":"+1 832 328 4900",
    "sg:postcode":"77074",
    "sg:province":"TX",
    "sg:tags":[
        "truck",
        "broker"
    ],
    "wof:name":"Your Auto Broker",
    "wof:placetype":"venue"
},
  "geometry": {"coordinates":[-95.560018,29.658399],"type":"Point"}
}