{
  "type": "Feature",
  "properties": {
    "iso:country":"US",
    "sg:address":"9626 Forestridge Dr",
    "sg:city":"Dallas",
    "sg:classifiers":[
        {
            "category":"Professional",
            "type":"Services"
        }
    ],
    "sg:phone":"+1 214 824 1188",
    "sg:postcode":"75238",
    "sg:province":"TX",
    "wof:name":"What I Just Wanted",
    "wof:placetype":"venue"
},
  "geometry": {"coordinates":[-96.71895000000001,32.870362],"type":"Point"}
}