{
  "type": "Feature",
  "properties": {
    "iso:country":"US",
    "sg:address":"3 Raintree Crossing Dr",
    "sg:city":"Spring",
    "sg:classifiers":[
        {
            "category":"Retail",
            "subcategory":"Laundry & Dry Cleaning",
            "type":"Services"
        }
    ],
    "sg:phone":"+1 281 296 8743",
    "sg:postcode":"77381",
    "sg:province":"TX",
    "sg:tags":[
        "drycleaning",
        "plant"
    ],
    "wof:name":"Mason Rd Ventures Inc",
    "wof:placetype":"venue"
},
  "geometry": {"coordinates":[-95.506803,30.190271],"type":"Point"}
}