{
  "type": "Feature",
  "properties": {
    "iso:country":"US",
    "sg:address":"9003 Winnsboro Dr",
    "sg:city":"Houston",
    "sg:classifiers":[
        {
            "category":"Freight",
            "type":"Transportation"
        }
    ],
    "sg:phone":"+1 281 260 9121",
    "sg:postcode":"77088",
    "sg:province":"TX",
    "sg:tags":[
        "operator",
        "local",
        "trucking"
    ],
    "wof:name":"A Guerra Trucking",
    "wof:placetype":"venue"
},
  "geometry": {"coordinates":[-95.489974,29.896121],"type":"Point"}
}