{
  "type": "Feature",
  "properties": {
    "iso:country":"US",
    "sg:address":"265 N Main St",
    "sg:city":"Boerne",
    "sg:classifiers":[
        {
            "category":"Professional",
            "subcategory":"Business Services",
            "type":"Services"
        }
    ],
    "sg:phone":"+1 830 248 1145",
    "sg:postcode":"78006",
    "sg:province":"TX",
    "wof:name":"Cook Winston LLP",
    "wof:placetype":"venue"
},
  "geometry": {"coordinates":[-98.732304,29.79497],"type":"Point"}
}