{
  "type": "Feature",
  "properties": {
    "iso:country":"US",
    "sg:address":"910 Pinafore Ln",
    "sg:city":"Houston",
    "sg:classifiers":[
        {
            "category":"Professional",
            "subcategory":"Business Services",
            "type":"Services"
        }
    ],
    "sg:phone":"+1 281 987 0039",
    "sg:postcode":"77039",
    "sg:province":"TX",
    "wof:name":"Package Plus",
    "wof:placetype":"venue"
},
  "geometry": {"coordinates":[-95.373242,29.922059],"type":"Point"}
}