{
  "type": "Feature",
  "properties": {
    "iso:country":"US",
    "sg:address":"1709 S I- 35",
    "sg:city":"San Marcos",
    "sg:classifiers":[
        {
            "category":"Professional",
            "subcategory":"Business Services",
            "type":"Services"
        }
    ],
    "sg:phone":"+1 512 754 8039",
    "sg:postcode":"78666",
    "sg:province":"TX",
    "sg:tags":[
        "embroidery"
    ],
    "sg:website":"www.designsongarments.com",
    "wof:name":"Designs On Garments",
    "wof:placetype":"venue"
},
  "geometry": {"coordinates":[-97.94773000000001,29.862178],"type":"Point"}
}