{
  "type": "Feature",
  "properties": {
    "iso:country":"US",
    "sg:address":"401 W Dallas St",
    "sg:city":"Llano",
    "sg:classifiers":[
        {
            "category":"Organizations",
            "subcategory":"Religious Organization",
            "type":"Services"
        }
    ],
    "sg:phone":"+1 325 247 4720",
    "sg:postcode":"78643",
    "sg:province":"TX",
    "sg:tags":[
        "church"
    ],
    "wof:name":"Faith Tabernacle Church",
    "wof:placetype":"venue"
},
  "geometry": {"coordinates":[-98.68047300000001,30.758536],"type":"Point"}
}