{
  "type": "Feature",
  "properties": {
    "iso:country":"US",
    "sg:address":"119 Regal Row",
    "sg:city":"Dallas",
    "sg:classifiers":[
        {
            "category":"Wholesale",
            "subcategory":"Auto Parts",
            "type":"Manufacturing & Wholesale Goods"
        }
    ],
    "sg:phone":"+1 214 688 0018",
    "sg:postcode":"75247",
    "sg:province":"TX",
    "sg:tags":[
        "body",
        "automobile",
        "supply"
    ],
    "sg:website":"www.partschannel.com",
    "wof:name":"Partschannel Inc",
    "wof:placetype":"venue"
},
  "geometry": {"coordinates":[-96.90038699999999,32.808961],"type":"Point"}
}