{
  "type": "Feature",
  "properties": {
    "iso:country":"US",
    "sg:address":"3302 Georgetown St",
    "sg:city":"Houston",
    "sg:classifiers":[
        {
            "category":"Professional",
            "subcategory":"Lawyer & Legal Services",
            "type":"Services"
        }
    ],
    "sg:phone":"+1 713 661 5590",
    "sg:postcode":"77005",
    "sg:province":"TX",
    "wof:name":"G Wesley Urquhart",
    "wof:placetype":"venue"
},
  "geometry": {"coordinates":[-95.429964,29.718041],"type":"Point"}
}