{
  "type": "Feature",
  "properties": {
    "iso:country":"US",
    "sg:address":"3806 40th St",
    "sg:city":"Lubbock",
    "sg:classifiers":[
        {
            "category":"Building & Trades",
            "subcategory":"Construction",
            "type":"Services"
        }
    ],
    "sg:phone":"+1 806 799 6109",
    "sg:postcode":"79413",
    "sg:province":"TX",
    "sg:tags":[
        "roofing",
        "contractor"
    ],
    "wof:name":"Jim Woodell Roofing",
    "wof:placetype":"venue"
},
  "geometry": {"coordinates":[-101.89854200000001,33.55799],"type":"Point"}
}