{
  "type": "Feature",
  "properties": {
    "iso:country":"US",
    "sg:address":"5 Cynthia Dr",
    "sg:city":"Denison",
    "sg:classifiers":[
        {
            "category":"Shopping",
            "type":"Retail Goods"
        }
    ],
    "sg:phone":"+1 903 465 5868",
    "sg:postcode":"75020",
    "sg:province":"TX",
    "sg:tags":[
        "merchandise"
    ],
    "wof:name":"L & M Candles",
    "wof:placetype":"venue"
},
  "geometry": {"coordinates":[-96.538888,33.768203],"type":"Point"}
}