{
  "type": "Feature",
  "properties": {
    "iso:country":"US",
    "sg:address":"207 Dallas St",
    "sg:city":"Gunter",
    "sg:classifiers":[
        {
            "category":"Real Estate",
            "subcategory":"Real Estate Agent",
            "type":"Services"
        }
    ],
    "sg:phone":"+1 903 433 0999",
    "sg:postcode":"75076",
    "sg:province":"TX",
    "wof:name":"Century 21 David Norman & Assc",
    "wof:placetype":"venue"
},
  "geometry": {"coordinates":[-96.67865999999999,33.843425],"type":"Point"}
}