{
  "type": "Feature",
  "properties": {
    "iso:country":"US",
    "sg:address":"6404 Industrial Dr",
    "sg:city":"Garland",
    "sg:classifiers":[
        {
            "category":"Manufacturing",
            "subcategory":"Furniture",
            "type":"Manufacturing & Wholesale Goods"
        }
    ],
    "sg:phone":"+1 972 495 9142",
    "sg:postcode":"75048",
    "sg:province":"TX",
    "sg:tags":[
        "wood",
        "mfg"
    ],
    "wof:name":"Campbells Cabinets Inc",
    "wof:placetype":"venue"
},
  "geometry": {"coordinates":[-96.590194,32.981003],"type":"Point"}
}