{
  "type": "Feature",
  "properties": {
    "iso:country":"US",
    "sg:address":"6816 Barbican Dr",
    "sg:city":"Plano",
    "sg:classifiers":[
        {
            "category":"Professional",
            "subcategory":"Business Services",
            "type":"Services"
        }
    ],
    "sg:phone":"+1 972 491 7616",
    "sg:postcode":"75023",
    "sg:province":"TX",
    "wof:name":"Dreamline Design",
    "wof:placetype":"venue"
},
  "geometry": {"coordinates":[-96.754017,33.068962],"type":"Point"}
}