{
  "type": "Feature",
  "properties": {
    "iso:country":"US",
    "sg:address":"3910 Kirby Dr",
    "sg:city":"Houston",
    "sg:classifiers":[
        {
            "category":"Personal",
            "subcategory":"Beauty Salon",
            "type":"Services"
        }
    ],
    "sg:phone":"+1 713 522 2111",
    "sg:postcode":"77019",
    "sg:province":"TX",
    "sg:tags":[
        "treatment",
        "skin"
    ],
    "wof:name":"Chrysalis Skin Care Systems",
    "wof:placetype":"venue"
},
  "geometry": {"coordinates":[-95.418666,29.732758],"type":"Point"}
}