{
  "type": "Feature",
  "properties": {
    "iso:country":"US",
    "sg:address":"7911 Birchbark Dr",
    "sg:city":"Humble",
    "sg:classifiers":[
        {
            "category":"Professional",
            "type":"Services"
        }
    ],
    "sg:phone":"+1 281 540 0666",
    "sg:postcode":"77338",
    "sg:province":"TX",
    "wof:name":"Farrah K Stone",
    "wof:placetype":"venue"
},
  "geometry": {"coordinates":[-95.305587,30.00852],"type":"Point"}
}