{
  "type": "Feature",
  "properties": {
    "iso:country":"US",
    "sg:address":"10885 Dyer St",
    "sg:city":"El Paso",
    "sg:classifiers":[
        {
            "category":"Professional",
            "type":"Services"
        },
        {
            "category":"Manufacturing",
            "subcategory":"Motor Vehicles & Parts",
            "type":"Manufacturing & Wholesale Goods"
        }
    ],
    "sg:phone":"+1 915 822 2288",
    "sg:postcode":"79934",
    "sg:province":"TX",
    "sg:tags":[
        "car",
        "race",
        "establishment",
        "mfg"
    ],
    "wof:name":"Don Davis Race Cars",
    "wof:placetype":"venue"
},
  "geometry": {"coordinates":[-106.388828,31.929116],"type":"Point"}
}