{
  "type": "Feature",
  "properties": {
    "iso:country":"US",
    "sg:address":"988 State Hwy 46",
    "sg:city":"New Braunfels",
    "sg:classifiers":[
        {
            "category":"Shopping",
            "subcategory":"Department Store",
            "type":"Retail Goods"
        }
    ],
    "sg:phone":"+1 830 626 5464",
    "sg:postcode":"78130",
    "sg:province":"TX",
    "wof:name":"Dollar General",
    "wof:placetype":"venue"
},
  "geometry": {"coordinates":[-98.102926,29.714031],"type":"Point"}
}