{
  "type": "Feature",
  "properties": {
    "iso:country":"US",
    "sg:address":"1428 Sierra Springs Dr",
    "sg:city":"Bedford",
    "sg:classifiers":[
        {
            "category":"Building & Trades",
            "subcategory":"Construction",
            "type":"Services"
        }
    ],
    "sg:phone":"+1 817 540 3199",
    "sg:postcode":"76021",
    "sg:province":"TX",
    "sg:tags":[
        "concrete",
        "contractor"
    ],
    "wof:name":"Blackwell Concrete",
    "wof:placetype":"venue"
},
  "geometry": {"coordinates":[-97.14826499999999,32.840548],"type":"Point"}
}