{
  "type": "Feature",
  "properties": {
    "iso:country":"US",
    "sg:address":"14101 Sunshine Rd",
    "sg:city":"Holland",
    "sg:classifiers":[
        {
            "category":"Insurance",
            "subcategory":"Insurance Agent",
            "type":"Services"
        }
    ],
    "sg:phone":"+1 254 778 1609",
    "sg:postcode":"76534",
    "sg:province":"TX",
    "wof:name":"Glenn Richards",
    "wof:placetype":"venue"
},
  "geometry": {"coordinates":[-97.35994599999999,30.895267],"type":"Point"}
}