{
  "type": "Feature",
  "properties": {
    "iso:country":"US",
    "sg:address":"3535 Cedar Knolls Dr",
    "sg:city":"Humble",
    "sg:classifiers":[
        {
            "category":"Education",
            "subcategory":"School",
            "type":"Public Place"
        }
    ],
    "sg:phone":"+1 281 358 8933",
    "sg:postcode":"77339",
    "sg:province":"TX",
    "sg:tags":[
        "child",
        "day",
        "care"
    ],
    "wof:name":"Scils Spcl Chldrn Indv Lrng CT",
    "wof:placetype":"venue"
},
  "geometry": {"coordinates":[-95.201559,30.054433],"type":"Point"}
}