{
  "type": "Feature",
  "properties": {
    "iso:country":"US",
    "sg:address":"3525 Sage Rd",
    "sg:city":"Houston",
    "sg:classifiers":[
        {
            "category":"Shopping",
            "type":"Retail Goods"
        }
    ],
    "sg:phone":"+1 713 675 0770",
    "sg:postcode":"77056",
    "sg:province":"TX",
    "sg:tags":[
        "art",
        "gallery",
        "merchandise",
        "dealer"
    ],
    "wof:name":"Decarlo Gallery",
    "wof:placetype":"venue"
},
  "geometry": {"coordinates":[-95.466511,29.729652],"type":"Point"}
}