{
  "type": "Feature",
  "properties": {
    "iso:country":"US",
    "sg:address":"6255 Lamar Rd",
    "sg:city":"Reno",
    "sg:classifiers":[
        {
            "category":"Autos & Motor Vehicles",
            "subcategory":"Automobile Sales",
            "type":"Retail Goods"
        }
    ],
    "sg:phone":"+1 903 782 9441",
    "sg:postcode":"75462",
    "sg:province":"TX",
    "sg:tags":[
        "car",
        "dealer"
    ],
    "wof:name":"Car Lot",
    "wof:placetype":"venue"
},
  "geometry": {"coordinates":[-95.467077,33.663404],"type":"Point"}
}