{
  "type": "Feature",
  "properties": {
    "iso:country":"US",
    "sg:address":"620 Marx Ln",
    "sg:city":"La Vernia",
    "sg:classifiers":[
        {
            "category":"Manufacturing",
            "subcategory":"Apparel",
            "type":"Manufacturing & Wholesale Goods"
        }
    ],
    "sg:phone":"+1 830 947 3074",
    "sg:postcode":"78121",
    "sg:province":"TX",
    "wof:name":"Miown Embroidery",
    "wof:placetype":"venue"
},
  "geometry": {"coordinates":[-98.17558099999999,29.281513],"type":"Point"}
}