{
  "type": "Feature",
  "properties": {
    "iso:country":"US",
    "sg:address":"1501 US Hwy 83",
    "sg:city":"Zapata",
    "sg:classifiers":[
        {
            "category":"Autos & Motor Vehicles",
            "subcategory":"Auto Supplies",
            "type":"Retail Goods"
        }
    ],
    "sg:phone":"+1 956 765 5876",
    "sg:postcode":"78076",
    "sg:province":"TX",
    "sg:tags":[
        "automobile",
        "parts"
    ],
    "wof:name":"Gonzalez Auto Parts",
    "wof:placetype":"venue"
},
  "geometry": {"coordinates":[-99.27395199999999,26.910194],"type":"Point"}
}