{
  "type": "Feature",
  "properties": {
    "iso:country":"US",
    "sg:address":"1406 E Laurel Ave",
    "sg:city":"Mcallen",
    "sg:classifiers":[
        {
            "category":"Mining & Drilling",
            "type":"Manufacturing & Wholesale Goods"
        }
    ],
    "sg:phone":"+1 956 992 9777",
    "sg:postcode":"78501",
    "sg:province":"TX",
    "sg:tags":[
        "stone"
    ],
    "wof:name":"Natural Stone",
    "wof:placetype":"venue"
},
  "geometry": {"coordinates":[-98.20481100000001,26.211152],"type":"Point"}
}