{
  "type": "Feature",
  "properties": {
    "iso:country":"US",
    "sg:address":"1052 Canyon Creek Dr",
    "sg:city":"Temple",
    "sg:classifiers":[
        {
            "category":"Home & Garden",
            "subcategory":"Furniture",
            "type":"Retail Goods"
        }
    ],
    "sg:phone":"+1 254 774 9776",
    "sg:postcode":"76502",
    "sg:province":"TX",
    "wof:name":"Dubois Furniture Inc",
    "wof:placetype":"venue"
},
  "geometry": {"coordinates":[-97.359396,31.05768],"type":"Point"}
}