{
  "type": "Feature",
  "properties": {
    "iso:country":"US",
    "sg:address":"945 Lariat St",
    "sg:city":"El Paso",
    "sg:classifiers":[
        {
            "category":"Professional",
            "subcategory":"Accounting & Tax Preparation",
            "type":"Services"
        }
    ],
    "sg:phone":"+1 915 593 8504",
    "sg:postcode":"79915",
    "sg:province":"TX",
    "sg:tags":[
        "accountant"
    ],
    "wof:name":"BBS Accounting & Data Proc",
    "wof:placetype":"venue"
},
  "geometry": {"coordinates":[-106.351737,31.751526],"type":"Point"}
}