{
  "type": "Feature",
  "properties": {
    "iso:country":"US",
    "sg:address":"1620 Aurora Dr",
    "sg:city":"Richardson",
    "sg:classifiers":[
        {
            "category":"Professional",
            "subcategory":"Business Services",
            "type":"Services"
        }
    ],
    "sg:phone":"+1 972 437 1081",
    "sg:postcode":"75081",
    "sg:province":"TX",
    "sg:tags":[
        "appraiser"
    ],
    "wof:name":"Prize Appraisals",
    "wof:placetype":"venue"
},
  "geometry": {"coordinates":[-96.692547,32.970057],"type":"Point"}
}