{
  "type": "Feature",
  "properties": {
    "iso:country":"US",
    "sg:address":"2410 Garwood Dr",
    "sg:city":"Houston",
    "sg:classifiers":[
        {
            "category":"Building & Trades",
            "subcategory":"Landscaping Services",
            "type":"Services"
        }
    ],
    "sg:phone":"+1 713 290 0485",
    "sg:postcode":"77091",
    "sg:province":"TX",
    "sg:tags":[
        "lawn",
        "garden"
    ],
    "wof:name":"Espinoza Brothers",
    "wof:placetype":"venue"
},
  "geometry": {"coordinates":[-95.448823,29.862448],"type":"Point"}
}