{
  "type": "Feature",
  "properties": {
    "iso:country":"US",
    "sg:address":"7514 N Mo Pac Expy",
    "sg:city":"Austin",
    "sg:classifiers":[
        {
            "category":"Professional",
            "subcategory":"Employment Agencies",
            "type":"Services"
        }
    ],
    "sg:phone":"+1 512 454 5555",
    "sg:postcode":"78731",
    "sg:province":"TX",
    "sg:tags":[
        "temporary",
        "help"
    ],
    "wof:name":"Austin Personnel Services",
    "wof:placetype":"venue"
},
  "geometry": {"coordinates":[-97.74639999999999,30.358325],"type":"Point"}
}