{
  "type": "Feature",
  "properties": {
    "iso:country":"US",
    "sg:address":"3143 N Lee Trevino Dr",
    "sg:city":"El Paso",
    "sg:classifiers":[
        {
            "category":"Restaurant",
            "type":"Food & Drink"
        }
    ],
    "sg:phone":"+1 915 592 5243",
    "sg:postcode":"79936",
    "sg:province":"TX",
    "sg:tags":[
        "eating"
    ],
    "wof:name":"Los Tres Gallegos",
    "wof:placetype":"venue"
},
  "geometry": {"coordinates":[-106.32334400000001,31.785958],"type":"Point"}
}