{
  "type": "Feature",
  "properties": {
    "iso:country":"US",
    "sg:address":"3109 S Cockrell Hill Rd",
    "sg:city":"Dallas",
    "sg:classifiers":[
        {
            "category":"Personal",
            "subcategory":"Barber",
            "type":"Services"
        }
    ],
    "sg:phone":"+1 214 941 7071",
    "sg:postcode":"75236",
    "sg:province":"TX",
    "wof:name":"Rayz Barber Shop",
    "wof:placetype":"venue"
},
  "geometry": {"coordinates":[-96.891553,32.708352],"type":"Point"}
}