{
  "type": "Feature",
  "properties": {
    "iso:country":"US",
    "sg:address":"500 Bayou Dr",
    "sg:city":"Richmond",
    "sg:classifiers":[
        {
            "category":"Farming",
            "subcategory":"Farm & Veterinary Services",
            "type":"Manufacturing & Wholesale Goods"
        }
    ],
    "sg:phone":"+1 281 232 5465",
    "sg:postcode":"77469",
    "sg:province":"TX",
    "sg:tags":[
        "livestock"
    ],
    "wof:name":"Culpepper Ranch",
    "wof:placetype":"venue"
},
  "geometry": {"coordinates":[-95.75593499999999,29.572046],"type":"Point"}
}