{
  "type": "Feature",
  "properties": {
    "iso:country":"US",
    "sg:address":"22759 Co Rd 508",
    "sg:city":"Harlingen",
    "sg:classifiers":[
        {
            "category":"Freight",
            "type":"Transportation"
        }
    ],
    "sg:phone":"+1 956 440 1141",
    "sg:postcode":"78583",
    "sg:province":"TX",
    "sg:tags":[
        "trucking"
    ],
    "wof:name":"Longhorn Trucking",
    "wof:placetype":"venue"
},
  "geometry": {"coordinates":[-97.661129,26.247544],"type":"Point"}
}