{
  "type": "Feature",
  "properties": {
    "iso:country":"US",
    "sg:address":"2014 Southern Pl",
    "sg:city":"Richmond",
    "sg:classifiers":[
        {
            "category":"Mining & Drilling",
            "type":"Manufacturing & Wholesale Goods"
        }
    ],
    "sg:phone":"+1 281 341 1870",
    "sg:postcode":"77469",
    "sg:province":"TX",
    "sg:tags":[
        "exploration"
    ],
    "wof:name":"Seismic Resources Inc",
    "wof:placetype":"venue"
},
  "geometry": {"coordinates":[-95.738761,29.614716],"type":"Point"}
}