{
  "type": "Feature",
  "properties": {
    "iso:country":"US",
    "sg:address":"4006 Doniphan Dr",
    "sg:city":"El Paso",
    "sg:classifiers":[
        {
            "category":"Restaurant",
            "type":"Food & Drink"
        }
    ],
    "sg:phone":"+1 915 585 1010",
    "sg:postcode":"79922",
    "sg:province":"TX",
    "sg:tags":[
        "eating"
    ],
    "wof:name":"Los Mundo's Mexican Food",
    "wof:placetype":"venue"
},
  "geometry": {"coordinates":[-106.561773,31.817052],"type":"Point"}
}