{
  "type": "Feature",
  "properties": {
    "iso:country":"US",
    "sg:address":"503 E Sterling St",
    "sg:city":"Baytown",
    "sg:classifiers":[
        {
            "category":"Personal",
            "subcategory":"Beauty Salon",
            "type":"Services"
        }
    ],
    "sg:phone":"+1 281 422 0557",
    "sg:postcode":"77520",
    "sg:province":"TX",
    "sg:tags":[
        "shop"
    ],
    "wof:name":"Wonders Family Hair Center",
    "wof:placetype":"venue"
},
  "geometry": {"coordinates":[-94.96108599999999,29.731292],"type":"Point"}
}