{
  "type": "Feature",
  "properties": {
    "iso:country":"US",
    "sg:address":"6703 Canal St",
    "sg:city":"Austin",
    "sg:classifiers":[
        {
            "category":"Wholesale",
            "subcategory":"Machinery & Supplies",
            "type":"Manufacturing & Wholesale Goods"
        },
        {
            "category":"Professional",
            "subcategory":"Business Services",
            "type":"Services"
        }
    ],
    "sg:phone":"+1 512 385 7339",
    "sg:postcode":"78741",
    "sg:province":"TX",
    "sg:tags":[
        "equipment",
        "irrigation",
        "system",
        "consultant"
    ],
    "wof:name":"Av Irrigation",
    "wof:placetype":"venue"
},
  "geometry": {"coordinates":[-97.69766,30.227071],"type":"Point"}
}