{
  "type": "Feature",
  "properties": {
    "iso:country":"US",
    "sg:address":"3303 Nottingham St",
    "sg:city":"Pearland",
    "sg:classifiers":[
        {
            "category":"Wholesale",
            "subcategory":"Durable Goods & Equipment",
            "type":"Manufacturing & Wholesale Goods"
        }
    ],
    "sg:phone":"+1 281 412 9634",
    "sg:postcode":"77581",
    "sg:province":"TX",
    "wof:name":"Net Supply Inc",
    "wof:placetype":"venue"
},
  "geometry": {"coordinates":[-95.273934,29.55383],"type":"Point"}
}