{
  "type": "Feature",
  "properties": {
    "iso:country":"US",
    "sg:address":"7410 Colorado St",
    "sg:city":"Hungerford",
    "sg:classifiers":[
        {
            "category":"Organizations",
            "subcategory":"Religious Organization",
            "type":"Services"
        }
    ],
    "sg:phone":"+1 979 532 8028",
    "sg:postcode":"77488",
    "sg:province":"TX",
    "sg:tags":[
        "church"
    ],
    "wof:name":"Faith Temple COGIC",
    "wof:placetype":"venue"
},
  "geometry": {"coordinates":[-96.077975,29.396365],"type":"Point"}
}