{
  "type": "Feature",
  "properties": {
    "iso:country":"US",
    "sg:address":"3317 McKinney Ave",
    "sg:city":"Dallas",
    "sg:classifiers":[
        {
            "category":"Health Services",
            "subcategory":"Doctor",
            "type":"Services"
        }
    ],
    "sg:phone":"+1 214 208 0015",
    "sg:postcode":"75204",
    "sg:province":"TX",
    "sg:tags":[
        "medical"
    ],
    "wof:name":"Martin L Kram MD",
    "wof:placetype":"venue"
},
  "geometry": {"coordinates":[-96.79849,32.805755],"type":"Point"}
}