{
  "type": "Feature",
  "properties": {
    "iso:country":"US",
    "sg:address":"4511 Highway 6 N",
    "sg:city":"Houston",
    "sg:classifiers":[
        {
            "category":"Manufacturing",
            "subcategory":"Rubber & Plastics",
            "type":"Manufacturing & Wholesale Goods"
        },
        {
            "category":"Autos & Motor Vehicles",
            "subcategory":"Auto Supplies",
            "type":"Retail Goods"
        }
    ],
    "sg:phone":"+1 281 859 6151",
    "sg:postcode":"77084",
    "sg:province":"TX",
    "sg:tags":[
        "wheel",
        "tires-wholesale",
        "tire",
        "manufacturer"
    ],
    "sg:website":"http://www.discounttire.com/dtcs/home.do?utm_source=YellowPages&utm_medium=iyp&utm_campaign=YellowPagesIYPOrg",
    "wof:name":"Discount Tire",
    "wof:placetype":"venue"
},
  "geometry": {"coordinates":[-95.64568300000001,29.839685],"type":"Point"}
}