{
  "type": "Feature",
  "properties": {
    "iso:country":"US",
    "sg:address":"415 N High St",
    "sg:city":"Longview",
    "sg:classifiers":[
        {
            "category":"Restaurant",
            "type":"Food & Drink"
        }
    ],
    "sg:phone":"+1 903 234 2211",
    "sg:postcode":"75601",
    "sg:province":"TX",
    "sg:tags":[
        "eating"
    ],
    "wof:name":"Don Giovanni's Pizza Express",
    "wof:placetype":"venue"
},
  "geometry": {"coordinates":[-94.740357,32.500243],"type":"Point"}
}