{
  "type": "Feature",
  "properties": {
    "iso:country":"US",
    "sg:address":"5445 Wayside Ave",
    "sg:city":"Fort Worth",
    "sg:classifiers":[
        {
            "category":"Manufacturing",
            "subcategory":"Wood Products",
            "type":"Manufacturing & Wholesale Goods"
        }
    ],
    "sg:phone":"+1 817 568 0416",
    "sg:postcode":"76134",
    "sg:province":"TX",
    "sg:tags":[
        "mfg"
    ],
    "wof:name":"C S I Woodwork",
    "wof:placetype":"venue"
},
  "geometry": {"coordinates":[-97.348455,32.66377],"type":"Point"}
}