{
  "type": "Feature",
  "properties": {
    "iso:country":"US",
    "sg:address":"8255 Sunbury Ln",
    "sg:city":"Houston",
    "sg:classifiers":[
        {
            "category":"Building & Trades",
            "subcategory":"Construction",
            "type":"Services"
        }
    ],
    "sg:phone":"+1 281 859 9545",
    "sg:postcode":"77095",
    "sg:province":"TX",
    "sg:tags":[
        "house"
    ],
    "wof:name":"Precision Painting",
    "wof:placetype":"venue"
},
  "geometry": {"coordinates":[-95.62925199999999,29.896541],"type":"Point"}
}