{
  "type": "Feature",
  "properties": {
    "iso:country":"US",
    "sg:address":"7700 Forest Hill Dr",
    "sg:city":"Fort Worth",
    "sg:classifiers":[
        {
            "category":"Professional",
            "type":"Services"
        }
    ],
    "sg:phone":"+1 817 551 7919",
    "sg:postcode":"76140",
    "sg:province":"TX",
    "wof:name":"A C Svc",
    "wof:placetype":"venue"
},
  "geometry": {"coordinates":[-97.269943,32.640402],"type":"Point"}
}