{
  "type": "Feature",
  "properties": {
    "iso:country":"US",
    "sg:address":"1811 Frankford Rd E",
    "sg:city":"Carrollton",
    "sg:classifiers":[
        {
            "category":"Personal",
            "type":"Services"
        }
    ],
    "sg:phone":"+1 972 492 8527",
    "sg:postcode":"75007",
    "sg:province":"TX",
    "wof:name":"A Carroll Seril",
    "wof:placetype":"venue"
},
  "geometry": {"coordinates":[-96.88942900000001,32.99967],"type":"Point"}
}