{
  "type": "Feature",
  "properties": {
    "iso:country":"US",
    "sg:address":"5420 Hickory Dr",
    "sg:city":"Austin",
    "sg:classifiers":[
        {
            "category":"Building & Trades",
            "subcategory":"Cleaning & Sanitation",
            "type":"Services"
        }
    ],
    "sg:phone":"+1 512 441 3448",
    "sg:postcode":"78744",
    "sg:province":"TX",
    "sg:tags":[
        "maintenance"
    ],
    "wof:name":"Zavalas Janitorial Services",
    "wof:placetype":"venue"
},
  "geometry": {"coordinates":[-97.736577,30.190633],"type":"Point"}
}