{
  "type": "Feature",
  "properties": {
    "iso:country":"US",
    "sg:address":"3350 Western Center Blvd",
    "sg:city":"Fort Worth",
    "sg:classifiers":[
        {
            "category":"Building & Trades",
            "subcategory":"Construction",
            "type":"Services"
        }
    ],
    "sg:phone":"+1 817 613 8175",
    "sg:postcode":"76137",
    "sg:province":"TX",
    "sg:tags":[
        "hanging",
        "contractor"
    ],
    "wof:name":"S&S Custom Paperhanging",
    "wof:placetype":"venue"
},
  "geometry": {"coordinates":[-97.31119200000001,32.860667],"type":"Point"}
}