{
  "type": "Feature",
  "properties": {
    "iso:country":"US",
    "sg:address":"4400 Co Rd 278",
    "sg:city":"Zephyr",
    "sg:classifiers":[
        {
            "category":"Wholesale",
            "subcategory":"Farm Supplies",
            "type":"Manufacturing & Wholesale Goods"
        }
    ],
    "sg:phone":"+1 325 739 3501",
    "sg:postcode":"76890",
    "sg:province":"TX",
    "sg:tags":[
        "livestock"
    ],
    "wof:name":"Alldredge Livestock",
    "wof:placetype":"venue"
},
  "geometry": {"coordinates":[-98.80179200000001,31.67533],"type":"Point"}
}