{
  "type": "Feature",
  "properties": {
    "iso:country":"US",
    "sg:address":"5321 Industrial Oaks Blvd",
    "sg:city":"Austin",
    "sg:classifiers":[
        {
            "category":"Manufacturing",
            "subcategory":"Printing",
            "type":"Manufacturing & Wholesale Goods"
        }
    ],
    "sg:phone":"+1 512 892 7105",
    "sg:postcode":"78735",
    "sg:province":"TX",
    "sg:tags":[
        "printer"
    ],
    "wof:name":"Proto Printing",
    "wof:placetype":"venue"
},
  "geometry": {"coordinates":[-97.839855,30.238112],"type":"Point"}
}