{
  "type": "Feature",
  "properties": {
    "iso:country":"US",
    "sg:address":"5503 Forest Bend Dr",
    "sg:city":"Arlington",
    "sg:classifiers":[
        {
            "category":"Personal",
            "type":"Services"
        }
    ],
    "sg:phone":"+1 817 483 5630",
    "sg:postcode":"76017",
    "sg:province":"TX",
    "wof:name":"Roses Gardens",
    "wof:placetype":"venue"
},
  "geometry": {"coordinates":[-97.19206,32.672684],"type":"Point"}
}