{
  "type": "Feature",
  "properties": {
    "iso:country":"US",
    "sg:address":"117 Holleman Dr W",
    "sg:city":"College Station",
    "sg:classifiers":[
        {
            "category":"Real Estate",
            "subcategory":"Real Estate Operator",
            "type":"Services"
        }
    ],
    "sg:phone":"+1 979 696 5711",
    "sg:postcode":"77840",
    "sg:province":"TX",
    "sg:tags":[
        "building",
        "apartment"
    ],
    "wof:name":"Sterling University Village",
    "wof:placetype":"venue"
},
  "geometry": {"coordinates":[-96.33400399999999,30.595541],"type":"Point"}
}