{
  "type": "Feature",
  "properties": {
    "iso:country":"US",
    "sg:address":"10530 FM 1484",
    "sg:city":"Conroe",
    "sg:classifiers":[
        {
            "category":"Shopping",
            "subcategory":"Jewelry",
            "type":"Retail Goods"
        }
    ],
    "sg:phone":"+1 936 756 6196",
    "sg:postcode":"77303",
    "sg:province":"TX",
    "wof:name":"Everything That Glitters",
    "wof:placetype":"venue"
},
  "geometry": {"coordinates":[-95.413481,30.372071],"type":"Point"}
}