{
  "type": "Feature",
  "properties": {
    "iso:country":"US",
    "sg:address":"1210 N Teal Ct",
    "sg:city":"Pearland",
    "sg:classifiers":[
        {
            "category":"Professional",
            "subcategory":"Management & Consulting",
            "type":"Services"
        }
    ],
    "sg:phone":"+1 281 997 6668",
    "sg:postcode":"77584",
    "sg:province":"TX",
    "sg:tags":[
        "business"
    ],
    "wof:name":"McLain Consulting Inc",
    "wof:placetype":"venue"
},
  "geometry": {"coordinates":[-95.352193,29.570088],"type":"Point"}
}