{
  "type": "Feature",
  "properties": {
    "iso:country":"US",
    "sg:address":"7607 Ravenswood Rd",
    "sg:city":"Granbury",
    "sg:classifiers":[
        {
            "category":"Retail",
            "subcategory":"Auto Repair",
            "type":"Services"
        }
    ],
    "sg:phone":"+1 817 573 4429",
    "sg:postcode":"76049",
    "sg:province":"TX",
    "wof:name":"Import Motorsports",
    "wof:placetype":"venue"
},
  "geometry": {"coordinates":[-97.64411,32.375445],"type":"Point"}
}