{
  "type": "Feature",
  "properties": {
    "iso:country":"US",
    "sg:address":"589 Sheffield Rd",
    "sg:city":"Seguin",
    "sg:classifiers":[
        {
            "category":"Building & Trades",
            "subcategory":"Construction",
            "type":"Services"
        }
    ],
    "sg:phone":"+1 830 372 9852",
    "sg:postcode":"78155",
    "sg:province":"TX",
    "sg:tags":[
        "concrete",
        "contractor"
    ],
    "wof:name":"Dominguez Construction Inc",
    "wof:placetype":"venue"
},
  "geometry": {"coordinates":[-97.929717,29.468079],"type":"Point"}
}