{
  "type": "Feature",
  "properties": {
    "iso:country":"US",
    "sg:address":"12844 Bandera Rd",
    "sg:city":"Helotes",
    "sg:classifiers":[
        {
            "category":"Freight",
            "type":"Transportation"
        }
    ],
    "sg:phone":"+1 210 695 8484",
    "sg:postcode":"78023",
    "sg:province":"TX",
    "sg:tags":[
        "mover"
    ],
    "wof:name":"Best Discount Moving",
    "wof:placetype":"venue"
},
  "geometry": {"coordinates":[-98.683504,29.562496],"type":"Point"}
}