{
  "type": "Feature",
  "properties": {
    "iso:country":"US",
    "sg:address":"1801 Hart Rd",
    "sg:city":"Conroe",
    "sg:classifiers":[
        {
            "category":"Shopping",
            "subcategory":"Discount & Variety Stores",
            "type":"Retail Goods"
        }
    ],
    "sg:phone":"+1 936 539 9351",
    "sg:postcode":"77304",
    "sg:province":"TX",
    "sg:tags":[
        "merchandise",
        "general"
    ],
    "wof:name":"Universal Sales & Marketing",
    "wof:placetype":"venue"
},
  "geometry": {"coordinates":[-95.516453,30.336651],"type":"Point"}
}