{
  "type": "Feature",
  "properties": {
    "iso:country":"US",
    "sg:address":"3804 Edwards Mountain Dr",
    "sg:city":"Austin",
    "sg:classifiers":[
        {
            "category":"Professional",
            "subcategory":"Business Services",
            "type":"Services"
        }
    ],
    "sg:phone":"+1 512 374 1460",
    "sg:postcode":"78731",
    "sg:province":"TX",
    "wof:name":"Twenty Four Seven Solutions LL",
    "wof:placetype":"venue"
},
  "geometry": {"coordinates":[-97.768411,30.349696],"type":"Point"}
}