{
  "type": "Feature",
  "properties": {
    "iso:country":"US",
    "sg:address":"4015 Callaghan Rd",
    "sg:city":"San Antonio",
    "sg:classifiers":[
        {
            "category":"Building & Trades",
            "subcategory":"Landscaping Services",
            "type":"Services"
        }
    ],
    "sg:phone":"+1 210 288 5909",
    "sg:postcode":"78228",
    "sg:province":"TX",
    "sg:tags":[
        "lawn",
        "maintenance",
        "grounds"
    ],
    "wof:name":"Alvarez Lawn Care",
    "wof:placetype":"venue"
},
  "geometry": {"coordinates":[-98.60260700000001,29.461859],"type":"Point"}
}