{
  "type": "Feature",
  "properties": {
    "iso:country":"US",
    "sg:address":"1708 Ginebra St",
    "sg:city":"Eagle Pass",
    "sg:classifiers":[
        {
            "category":"Professional",
            "type":"Services"
        }
    ],
    "sg:phone":"+1 830 773 4613",
    "sg:postcode":"78852",
    "sg:province":"TX",
    "wof:name":"Alicia Garcia",
    "wof:placetype":"venue"
},
  "geometry": {"coordinates":[-100.49382799999999,28.688233],"type":"Point"}
}