{
  "type": "Feature",
  "properties": {
    "iso:country":"US",
    "sg:address":"407 16th St",
    "sg:city":"Canyon",
    "sg:classifiers":[
        {
            "category":"Shopping",
            "subcategory":"Used Merchandise",
            "type":"Retail Goods"
        }
    ],
    "sg:phone":"+1 806 655 0111",
    "sg:postcode":"79015",
    "sg:province":"TX",
    "sg:tags":[
        "antique"
    ],
    "wof:name":"It's The Berry's",
    "wof:placetype":"venue"
},
  "geometry": {"coordinates":[-101.92748400000001,34.979805],"type":"Point"}
}