{
  "type": "Feature",
  "properties": {
    "iso:country":"US",
    "sg:address":"3219 N Macarthur Blvd Ste 100",
    "sg:city":"Irving",
    "sg:phone":"+1 972 252 7569",
    "sg:postcode":"75062",
    "sg:province":"TX",
    "wof:name":"Wilson, Carolyn, Dds - Pediatric Dentistry-North Tx",
    "wof:placetype":"venue"
},
  "geometry": {"coordinates":[-96.959129,32.849072],"type":"Point"}
}