{
  "type": "Feature",
  "properties": {
    "iso:country":"US",
    "sg:address":"10601 N Lamar Blvd",
    "sg:city":"Austin",
    "sg:classifiers":[
        {
            "category":"Shopping",
            "subcategory":"Books",
            "type":"Retail Goods"
        }
    ],
    "sg:phone":"+1 512 873 8400",
    "sg:postcode":"78753",
    "sg:province":"TX",
    "sg:tags":[
        "dealer"
    ],
    "wof:name":"Spiritual Gifts Christian",
    "wof:placetype":"venue"
},
  "geometry": {"coordinates":[-97.68975399999999,30.375892],"type":"Point"}
}