{
  "type": "Feature",
  "properties": {
    "iso:country":"US",
    "sg:address":"4502 Harbinger Dr",
    "sg:city":"Mesquite",
    "sg:classifiers":[
        {
            "category":"Professional",
            "subcategory":"Detective & Security Services",
            "type":"Services"
        }
    ],
    "sg:phone":"+1 972 686 1854",
    "sg:postcode":"75150",
    "sg:province":"TX",
    "sg:tags":[
        "car"
    ],
    "wof:name":"Pinkerton Mary Kathryn",
    "wof:placetype":"venue"
},
  "geometry": {"coordinates":[-96.617372,32.824641],"type":"Point"}
}