{
  "type": "Feature",
  "properties": {
    "iso:country":"US",
    "sg:address":"1227 World Store Ct",
    "sg:city":"Dallas",
    "sg:classifiers":[
        {
            "category":"Organizations",
            "subcategory":"Non-profit Organization",
            "type":"Services"
        }
    ],
    "sg:phone":"+1 214 381 9535",
    "sg:postcode":"75217",
    "sg:province":"TX",
    "sg:tags":[
        "info",
        "addiction",
        "abuse",
        "treatment",
        "drug"
    ],
    "sg:website":"www.sos-tx.com",
    "wof:name":"Solutions Over Substances",
    "wof:placetype":"venue"
},
  "geometry": {"coordinates":[-96.684078,32.732877],"type":"Point"}
}