{
  "type": "Feature",
  "properties": {
    "iso:country":"US",
    "sg:address":"1204 Dundale Cir",
    "sg:city":"Sherman",
    "sg:classifiers":[
        {
            "category":"Professional",
            "type":"Services"
        }
    ],
    "sg:phone":"+1 903 868 4884",
    "sg:postcode":"75092",
    "sg:province":"TX",
    "wof:name":"JMB Services",
    "wof:placetype":"venue"
},
  "geometry": {"coordinates":[-96.631874,33.647245],"type":"Point"}
}