{
  "type": "Feature",
  "properties": {
    "iso:country":"US",
    "sg:address":"6009 Tautoga Dr",
    "sg:city":"El Paso",
    "sg:classifiers":[
        {
            "category":"Personal",
            "subcategory":"Barber",
            "type":"Services"
        }
    ],
    "sg:phone":"+1 915 757 2227",
    "sg:postcode":"79924",
    "sg:province":"TX",
    "wof:name":"A & K Hair Care Ctr",
    "wof:placetype":"venue"
},
  "geometry": {"coordinates":[-106.400228,31.891336],"type":"Point"}
}