{
  "type": "Feature",
  "properties": {
    "iso:country":"US",
    "sg:address":"425 Coneflower Dr",
    "sg:city":"Garland",
    "sg:classifiers":[
        {
            "category":"Tea Room",
            "subcategory":"None",
            "type":"Food & Drink"
        }
    ],
    "sg:phone":"+1 972 530 2288",
    "sg:postcode":"75040",
    "sg:province":"TX",
    "sg:website":"chandtea.com/",
    "wof:name":"Cha & Tea",
    "wof:placetype":"venue"
},
  "geometry": {"coordinates":[-96.61243,32.952616],"type":"Point"}
}