{
  "type": "Feature",
  "properties": {
    "iso:country":"US",
    "sg:address":"101 W Glade Rd",
    "sg:city":"Euless",
    "sg:classifiers":[
        {
            "category":"Personal",
            "subcategory":"Beauty Salon",
            "type":"Services"
        },
        {
            "category":"Personal",
            "subcategory":"Barber",
            "type":"Services"
        },
        {
            "category":"Personal",
            "subcategory":"Skin Care",
            "type":"Services"
        }
    ],
    "sg:phone":"+1 817 540 3366",
    "sg:postcode":"76039",
    "sg:province":"TX",
    "sg:tags":[
        "hair",
        "stylist"
    ],
    "sg:website":"http://www.tonishairworks.com",
    "wof:name":"Toni's Hairworks",
    "wof:placetype":"venue"
},
  "geometry": {"coordinates":[-97.082359,32.881119],"type":"Point"}
}