{
  "type": "Feature",
  "properties": {
    "iso:country":"US",
    "sg:address":"105 E San Antonio Ave",
    "sg:city":"El Paso",
    "sg:classifiers":[
        {
            "category":"Professional",
            "subcategory":"Advertising",
            "type":"Services"
        }
    ],
    "sg:phone":"+1 915 542 4533",
    "sg:postcode":"79901",
    "sg:province":"TX",
    "sg:tags":[
        "mailing",
        "shipping"
    ],
    "wof:name":"UPS Store",
    "wof:placetype":"venue"
},
  "geometry": {"coordinates":[-106.487988,31.758084],"type":"Point"}
}