{
  "type": "Feature",
  "properties": {
    "iso:country":"US",
    "sg:address":"2528 Warden Rd",
    "sg:city":"Kountze",
    "sg:classifiers":[
        {
            "category":"Farming",
            "subcategory":"Livestock Farm",
            "type":"Manufacturing & Wholesale Goods"
        }
    ],
    "sg:phone":"+1 409 246 4622",
    "sg:postcode":"77625",
    "sg:province":"TX",
    "sg:tags":[
        "animal",
        "general"
    ],
    "wof:name":"Randy Jauer Ranch",
    "wof:placetype":"venue"
},
  "geometry": {"coordinates":[-94.27336200000001,30.35145],"type":"Point"}
}