{
  "type": "Feature",
  "properties": {
    "iso:country":"US",
    "sg:address":"10730 Estelle Cir",
    "sg:city":"Montgomery",
    "sg:classifiers":[
        {
            "category":"Shopping",
            "type":"Retail Goods"
        }
    ],
    "sg:phone":"+1 936 448 2282",
    "sg:postcode":"77356",
    "sg:province":"TX",
    "sg:tags":[
        "merchandise"
    ],
    "wof:name":"J M P Datacom",
    "wof:placetype":"venue"
},
  "geometry": {"coordinates":[-95.641475,30.383283],"type":"Point"}
}