{
  "type": "Feature",
  "properties": {
    "iso:country":"US",
    "sg:address":"701 Tumbleweed Trl N",
    "sg:city":"Austin",
    "sg:classifiers":[
        {
            "category":"Insurance",
            "subcategory":"Insurance Agent",
            "type":"Services"
        }
    ],
    "sg:phone":"+1 512 347 9197",
    "sg:postcode":"78733",
    "sg:province":"TX",
    "wof:name":"Bright Health Insurance Soluti",
    "wof:placetype":"venue"
},
  "geometry": {"coordinates":[-97.864824,30.32662],"type":"Point"}
}