{
  "type": "Feature",
  "properties": {
    "iso:country":"US",
    "sg:address":"17312 Highway 3",
    "sg:city":"Webster",
    "sg:classifiers":[
        {
            "category":"Wholesale",
            "subcategory":"Medical Equipment & Supplies",
            "type":"Manufacturing & Wholesale Goods"
        }
    ],
    "sg:phone":"+1 281 338 0701",
    "sg:postcode":"77598",
    "sg:province":"TX",
    "sg:tags":[
        "wheelchair"
    ],
    "sg:website":"http://www.aamobility.com",
    "wof:name":"Active American",
    "wof:placetype":"venue"
},
  "geometry": {"coordinates":[-95.12217699999999,29.542059],"type":"Point"}
}