{
  "type": "Feature",
  "properties": {
    "iso:country":"US",
    "sg:address":"3202 E Grimes St",
    "sg:city":"Harlingen",
    "sg:classifiers":[
        {
            "category":"Building & Trades",
            "subcategory":"Cleaning & Sanitation",
            "type":"Services"
        }
    ],
    "sg:phone":"+1 956 421 4383",
    "sg:postcode":"78550",
    "sg:province":"TX",
    "sg:tags":[
        "maintenance"
    ],
    "wof:name":"Fiesta Car Wash",
    "wof:placetype":"venue"
},
  "geometry": {"coordinates":[-97.65374799999999,26.205388],"type":"Point"}
}