{
  "type": "Feature",
  "properties": {
    "iso:country":"US",
    "sg:address":"3902 Commonwealth Dr",
    "sg:city":"Garland",
    "sg:classifiers":[
        {
            "category":"Recreation",
            "type":"Entertainment"
        }
    ],
    "sg:phone":"+1 972 271 7769",
    "sg:postcode":"75043",
    "sg:province":"TX",
    "sg:tags":[
        "club",
        "membership"
    ],
    "wof:name":"Treminios Private Club Inc",
    "wof:placetype":"venue"
},
  "geometry": {"coordinates":[-96.61547400000001,32.868336],"type":"Point"}
}