{
  "type": "Feature",
  "properties": {
    "iso:country":"US",
    "sg:address":"3310 1st St",
    "sg:city":"Rosenberg",
    "sg:classifiers":[
        {
            "category":"Banks & Credit Unions",
            "subcategory":"Investment Brokerage",
            "type":"Services"
        }
    ],
    "sg:phone":"+1 281 238 9599",
    "sg:postcode":"77471",
    "sg:province":"TX",
    "sg:tags":[
        "stock",
        "bond"
    ],
    "wof:name":"Edward Jones Investments",
    "wof:placetype":"venue"
},
  "geometry": {"coordinates":[-95.80826500000001,29.534027],"type":"Point"}
}