{
  "type": "Feature",
  "properties": {
    "iso:country":"US",
    "sg:address":"5786 High Point Rd",
    "sg:city":"Fort Worth",
    "sg:classifiers":[
        {
            "category":"Professional",
            "subcategory":"Business Services",
            "type":"Services"
        }
    ],
    "sg:phone":"+1 817 249 6813",
    "sg:postcode":"76126",
    "sg:province":"TX",
    "wof:name":"LGS Design",
    "wof:placetype":"venue"
},
  "geometry": {"coordinates":[-97.49415399999999,32.624112],"type":"Point"}
}