{
  "type": "Feature",
  "properties": {
    "iso:country":"US",
    "sg:address":"1095 del Rio Blvd",
    "sg:city":"Eagle Pass",
    "sg:classifiers":[
        {
            "category":"Government",
            "subcategory":"Office",
            "type":"Public Place"
        }
    ],
    "sg:phone":"+1 830 757 3263",
    "sg:postcode":"78852",
    "sg:province":"TX",
    "sg:tags":[
        "state",
        "taxation"
    ],
    "wof:name":"Unemployment Tax Assistance",
    "wof:placetype":"venue"
},
  "geometry": {"coordinates":[-100.49923,28.719425],"type":"Point"}
}