{
  "type": "Feature",
  "properties": {
    "iso:country":"US",
    "sg:address":"3801 Feagan St",
    "sg:city":"Houston",
    "sg:classifiers":[
        {
            "category":"Shopping",
            "type":"Retail Goods"
        }
    ],
    "sg:phone":"+1 713 256 0839",
    "sg:postcode":"77007",
    "sg:province":"TX",
    "sg:tags":[
        "merchandise"
    ],
    "wof:name":"Dragon Aquarium",
    "wof:placetype":"venue"
},
  "geometry": {"coordinates":[-95.400803,29.766349],"type":"Point"}
}