{
  "type": "Feature",
  "properties": {
    "iso:country":"US",
    "sg:address":"7419 W 34th Ave",
    "sg:city":"Amarillo",
    "sg:classifiers":[
        {
            "category":"Retail",
            "subcategory":"Auto Repair",
            "type":"Services"
        }
    ],
    "sg:phone":"+1 806 354 8877",
    "sg:postcode":"79121",
    "sg:province":"TX",
    "sg:tags":[
        "automotive"
    ],
    "wof:name":"Jiffy Lube",
    "wof:placetype":"venue"
},
  "geometry": {"coordinates":[-101.922585,35.176461],"type":"Point"}
}