{
  "type": "Feature",
  "properties": {
    "iso:country":"US",
    "sg:address":"5020 Mill Creek Rd",
    "sg:city":"Dallas",
    "sg:classifiers":[
        {
            "category":"Wholesale",
            "subcategory":"Groceries",
            "type":"Manufacturing & Wholesale Goods"
        }
    ],
    "sg:phone":"+1 972 818 2246",
    "sg:postcode":"75244",
    "sg:province":"TX",
    "wof:name":"Ryan Burkhart",
    "wof:placetype":"venue"
},
  "geometry": {"coordinates":[-96.82375399999999,32.920589],"type":"Point"}
}