{
  "type": "Feature",
  "properties": {
    "iso:country":"US",
    "sg:address":"2500 Chestnut Dr",
    "sg:city":"Pampa",
    "sg:classifiers":[
        {
            "category":"Farming",
            "subcategory":"Livestock Farm",
            "type":"Manufacturing & Wholesale Goods"
        }
    ],
    "sg:phone":"+1 806 669 9269",
    "sg:postcode":"79065",
    "sg:province":"TX",
    "sg:tags":[
        "feeding"
    ],
    "wof:name":"Five L Cattle Corporation",
    "wof:placetype":"venue"
},
  "geometry": {"coordinates":[-100.95929,35.565571],"type":"Point"}
}