{
  "type": "Feature",
  "properties": {
    "iso:country":"US",
    "sg:address":"1525 W Cameron Ave",
    "sg:city":"Rockdale",
    "sg:classifiers":[
        {
            "category":"Banks & Credit Unions",
            "subcategory":"Bank",
            "type":"Services"
        }
    ],
    "sg:phone":"+1 512 446 2583",
    "sg:postcode":"76567",
    "sg:province":"TX",
    "sg:tags":[
        "federal"
    ],
    "wof:name":"Rockdale Federal Credit Union",
    "wof:placetype":"venue"
},
  "geometry": {"coordinates":[-97.02053100000001,30.646693],"type":"Point"}
}