{
  "type": "Feature",
  "properties": {
    "iso:country":"US",
    "sg:address":"7860 Culebra Rd",
    "sg:city":"San Antonio",
    "sg:classifiers":[
        {
            "category":"Health Services",
            "subcategory":"Doctor",
            "type":"Services"
        }
    ],
    "sg:phone":"+1 210 647 3151",
    "sg:postcode":"78251",
    "sg:province":"TX",
    "sg:tags":[
        "dentist",
        "practice",
        "general",
        "orthodontics",
        "dentistry"
    ],
    "sg:website":"www.brightnow.com",
    "wof:name":"Monarch Dental Associates Inc",
    "wof:placetype":"venue"
},
  "geometry": {"coordinates":[-98.64273799999999,29.4629],"type":"Point"}
}