{
  "type": "Feature",
  "properties": {
    "iso:country":"US",
    "sg:address":"810 Hospital Dr",
    "sg:city":"Beaumont",
    "sg:classifiers":[
        {
            "category":"Social Services",
            "type":"Services"
        }
    ],
    "sg:phone":"+1 409 832 0421",
    "sg:postcode":"77701",
    "sg:province":"TX",
    "wof:name":"Child Abuse & Forensic Svcs",
    "wof:placetype":"venue"
},
  "geometry": {"coordinates":[-94.120724,30.069028],"type":"Point"}
}