{
  "type": "Feature",
  "properties": {
    "iso:country":"US",
    "sg:address":"5340 Mockingbird Ln",
    "sg:city":"Dallas",
    "sg:classifiers":[
        {
            "category":"Freight",
            "type":"Transportation"
        }
    ],
    "sg:phone":"+1 214 824 9994",
    "sg:postcode":"75206",
    "sg:province":"TX",
    "sg:tags":[
        "paper",
        "general"
    ],
    "wof:name":"Shurgard Storage Centers Inc",
    "wof:placetype":"venue"
},
  "geometry": {"coordinates":[-96.77533,32.836503],"type":"Point"}
}