{
  "type": "Feature",
  "properties": {
    "iso:country":"US",
    "sg:address":"4401 Tiptop St",
    "sg:city":"Fort Worth",
    "sg:classifiers":[
        {
            "category":"Retail",
            "subcategory":"Repair Shop",
            "type":"Services"
        }
    ],
    "sg:phone":"+1 817 281 4400",
    "sg:postcode":"76117",
    "sg:province":"TX",
    "sg:tags":[
        "equipment",
        "conditioning",
        "air"
    ],
    "wof:name":"Ringener Air Conditioning",
    "wof:placetype":"venue"
},
  "geometry": {"coordinates":[-97.276647,32.836267],"type":"Point"}
}