{
  "type": "Feature",
  "properties": {
    "iso:country":"US",
    "sg:address":"112 N Poplar St",
    "sg:city":"Kermit",
    "sg:classifiers":[
        {
            "category":"Organizations",
            "subcategory":"Professional Association",
            "type":"Services"
        }
    ],
    "sg:phone":"+1 432 586 2507",
    "sg:postcode":"79745",
    "sg:province":"TX",
    "sg:tags":[
        "business"
    ],
    "wof:name":"Kermit Chamber of Commerce",
    "wof:placetype":"venue"
},
  "geometry": {"coordinates":[-103.09369100000001,31.858652],"type":"Point"}
}