{
  "type": "Feature",
  "properties": {
    "iso:country":"US",
    "sg:address":"9817 Walnut St",
    "sg:city":"Dallas",
    "sg:classifiers":[
        {
            "category":"Food & Beverages",
            "subcategory":"Meat & Fish",
            "type":"Retail Goods"
        }
    ],
    "sg:phone":"+1 469 330 8627",
    "sg:postcode":"75243",
    "sg:province":"TX",
    "wof:name":"Dallas Quality Meat Savers",
    "wof:placetype":"venue"
},
  "geometry": {"coordinates":[-96.71604600000001,32.922027],"type":"Point"}
}