{
  "type": "Feature",
  "properties": {
    "iso:country":"US",
    "sg:address":"11020 Northwest Fwy",
    "sg:city":"Houston",
    "sg:classifiers":[
        {
            "category":"Restaurant",
            "type":"Food & Drink"
        }
    ],
    "sg:phone":"+1 713 957 4580",
    "sg:postcode":"77092",
    "sg:province":"TX",
    "wof:name":"Baytown Sea Food",
    "wof:placetype":"venue"
},
  "geometry": {"coordinates":[-95.46670899999999,29.818116],"type":"Point"}
}