{
  "type": "Feature",
  "properties": {
    "iso:country":"US",
    "sg:address":"426 E Main St",
    "sg:city":"Grand Prairie",
    "sg:classifiers":[
        {
            "category":"Building & Trades",
            "subcategory":"Equipment Rental",
            "type":"Services"
        }
    ],
    "sg:phone":"+1 972 262 9905",
    "sg:postcode":"75050",
    "sg:province":"TX",
    "sg:tags":[
        "yard"
    ],
    "wof:name":"Rent Way",
    "wof:placetype":"venue"
},
  "geometry": {"coordinates":[-96.99854499999999,32.745786],"type":"Point"}
}