{
  "type": "Feature",
  "properties": {
    "iso:country":"US",
    "sg:address":"9707 Anderson Mill Rd Ste 230",
    "sg:city":"Austin",
    "sg:classifiers":[
        {
            "category":"Health Services",
            "subcategory":"Doctor",
            "type":"Services"
        },
        {
            "category":"Community Center",
            "type":"Public Place"
        }
    ],
    "sg:phone":"+1 512 219 8787",
    "sg:postcode":"78750",
    "sg:province":"TX",
    "sg:tags":[
        "medical"
    ],
    "wof:name":"Republic Spine and Pain",
    "wof:placetype":"venue"
},
  "geometry": {"coordinates":[-97.79352,30.446544],"type":"Point"}
}