{
  "type": "Feature",
  "properties": {
    "iso:country":"US",
    "sg:address":"1612 Roy St",
    "sg:city":"Houston",
    "sg:classifiers":[
        {
            "category":"Building & Trades",
            "subcategory":"Construction",
            "type":"Services"
        }
    ],
    "sg:phone":"+1 713 864 1171",
    "sg:postcode":"77007",
    "sg:province":"TX",
    "sg:tags":[
        "contractor"
    ],
    "wof:name":"Bas Roofing Inc",
    "wof:placetype":"venue"
},
  "geometry": {"coordinates":[-95.412519,29.775443],"type":"Point"}
}