{
  "type": "Feature",
  "properties": {
    "iso:country":"US",
    "sg:address":"1901 S Colorado St",
    "sg:city":"Lockhart",
    "sg:classifiers":[
        {
            "category":"Freight",
            "type":"Transportation"
        }
    ],
    "sg:phone":"+1 512 376 2490",
    "sg:postcode":"78644",
    "sg:province":"TX",
    "sg:tags":[
        "storage",
        "household",
        "commercial",
        "special"
    ],
    "sg:website":"http://www.alliance-selfstorage.com",
    "wof:name":"Alliance Self Storage",
    "wof:placetype":"venue"
},
  "geometry": {"coordinates":[-97.668435,29.860817],"type":"Point"}
}