{
  "type": "Feature",
  "properties": {
    "iso:country":"US",
    "sg:address":"2000 E 7th St",
    "sg:city":"Austin",
    "sg:classifiers":[
        {
            "category":"Personal",
            "subcategory":"Beauty Salon",
            "type":"Services"
        }
    ],
    "sg:phone":"+1 512 482 8890",
    "sg:postcode":"78702",
    "sg:province":"TX",
    "sg:tags":[
        "shop"
    ],
    "wof:name":"B & J Cuts and Fades",
    "wof:placetype":"venue"
},
  "geometry": {"coordinates":[-97.72127500000001,30.262575],"type":"Point"}
}