{
  "type": "Feature",
  "properties": {
    "iso:country":"US",
    "sg:address":"2018 W Rundberg Ln",
    "sg:city":"Austin",
    "sg:classifiers":[
        {
            "category":"Wholesale",
            "subcategory":"Computers",
            "type":"Manufacturing & Wholesale Goods"
        }
    ],
    "sg:phone":"+1 512 835 5725",
    "sg:postcode":"78758",
    "sg:province":"TX",
    "wof:name":"Annor Import Export Agency",
    "wof:placetype":"venue"
},
  "geometry": {"coordinates":[-97.719562,30.375702],"type":"Point"}
}