{
  "type": "Feature",
  "properties": {
    "iso:country":"US",
    "sg:address":"1312 Studemont St",
    "sg:city":"Houston",
    "sg:classifiers":[
        {
            "category":"Wholesale",
            "subcategory":"Construction Materials",
            "type":"Manufacturing & Wholesale Goods"
        }
    ],
    "sg:phone":"+1 713 864 2113",
    "sg:postcode":"77007",
    "sg:province":"TX",
    "sg:tags":[
        "glass",
        "flat"
    ],
    "wof:name":"Complete Line Glass Wholesaler",
    "wof:placetype":"venue"
},
  "geometry": {"coordinates":[-95.389049,29.776155],"type":"Point"}
}