{
  "type": "Feature",
  "properties": {
    "iso:country":"US",
    "sg:address":"713 N Cypress St",
    "sg:city":"Gilmer",
    "sg:classifiers":[
        {
            "category":"Retail",
            "subcategory":"Auto Repair",
            "type":"Services"
        }
    ],
    "sg:phone":"+1 903 843 5848",
    "sg:postcode":"75644",
    "sg:province":"TX",
    "sg:tags":[
        "supply",
        "general"
    ],
    "wof:name":"Gilmer Discount Tire & Wheel",
    "wof:placetype":"venue"
},
  "geometry": {"coordinates":[-94.940185,32.735419],"type":"Point"}
}