{
  "type": "Feature",
  "properties": {
    "iso:country":"US",
    "sg:address":"410 el Paso St",
    "sg:city":"Mason",
    "sg:classifiers":[
        {
            "category":"Shopping",
            "subcategory":"Bicycles & Sporting Goods",
            "type":"Retail Goods"
        }
    ],
    "sg:phone":"+1 325 347 1700",
    "sg:postcode":"76856",
    "sg:province":"TX",
    "wof:name":"Commanche Creek Products",
    "wof:placetype":"venue"
},
  "geometry": {"coordinates":[-99.235956,30.748966],"type":"Point"}
}