{
  "type": "Feature",
  "properties": {
    "iso:country":"US",
    "sg:address":"11800 Bellaire Blvd",
    "sg:city":"Houston",
    "sg:classifiers":[
        {
            "category":"Insurance",
            "subcategory":"Insurance Agent",
            "type":"Services"
        }
    ],
    "sg:phone":"+1 281 564 4900",
    "sg:postcode":"77072",
    "sg:province":"TX",
    "wof:name":"A Affordable Insurance",
    "wof:placetype":"venue"
},
  "geometry": {"coordinates":[-95.586055,29.703827],"type":"Point"}
}