{
  "type": "Feature",
  "properties": {
    "iso:country":"US",
    "sg:address":"14100 Horseshoe Bnd",
    "sg:city":"Conroe",
    "sg:classifiers":[
        {
            "category":"Professional",
            "subcategory":"Art Services",
            "type":"Services"
        }
    ],
    "sg:phone":"+1 936 271 0839",
    "sg:postcode":"77384",
    "sg:province":"TX",
    "sg:tags":[
        "designer",
        "display",
        "producer"
    ],
    "wof:name":"Designs By Elizabeth",
    "wof:placetype":"venue"
},
  "geometry": {"coordinates":[-95.530073,30.23715],"type":"Point"}
}