{
  "type": "Feature",
  "properties": {
    "iso:country":"US",
    "sg:address":"5440 Old Brownsville Rd",
    "sg:city":"Corpus Christi",
    "sg:classifiers":[
        {
            "category":"Government",
            "subcategory":"Office",
            "type":"Public Place"
        }
    ],
    "sg:phone":"+1 361 289 2416",
    "sg:postcode":"78417",
    "sg:province":"TX",
    "sg:tags":[
        "federal",
        "international",
        "affairs"
    ],
    "wof:name":"German Federal Republic Hon",
    "wof:placetype":"venue"
},
  "geometry": {"coordinates":[-97.46913499999999,27.749613],"type":"Point"}
}