{
  "type": "Feature",
  "properties": {
    "iso:country":"US",
    "sg:address":"218 Ironbridge Pl",
    "sg:city":"Euless",
    "sg:classifiers":[
        {
            "category":"Organizations",
            "subcategory":"Religious Organization",
            "type":"Services"
        }
    ],
    "sg:phone":"+1 817 571 3268",
    "sg:postcode":"76040",
    "sg:province":"TX",
    "wof:name":"Outdoor Youth Ministries",
    "wof:placetype":"venue"
},
  "geometry": {"coordinates":[-97.078497,32.830164],"type":"Point"}
}