{
  "type": "Feature",
  "properties": {
    "iso:country":"US",
    "sg:address":"10053 Kenworthy St",
    "sg:city":"El Paso",
    "sg:classifiers":[
        {
            "category":"Manufacturing",
            "subcategory":"Metals",
            "type":"Manufacturing & Wholesale Goods"
        }
    ],
    "sg:phone":"+1 915 751 8187",
    "sg:postcode":"79924",
    "sg:province":"TX",
    "wof:name":"Gators Gold Inc",
    "wof:placetype":"venue"
},
  "geometry": {"coordinates":[-106.433572,31.900881],"type":"Point"}
}