{
  "type": "Feature",
  "properties": {
    "iso:country":"US",
    "sg:address":"514 Enchanted Ln",
    "sg:city":"Spring",
    "sg:classifiers":[
        {
            "category":"Shopping",
            "subcategory":"Computers & Home Electronics",
            "type":"Retail Goods"
        }
    ],
    "sg:phone":"+1 281 353 9858",
    "sg:postcode":"77388",
    "sg:province":"TX",
    "wof:name":"Texas Stereo LLC",
    "wof:placetype":"venue"
},
  "geometry": {"coordinates":[-95.44513600000001,30.047516],"type":"Point"}
}