{
  "type": "Feature",
  "properties": {
    "iso:country":"US",
    "sg:address":"3403 Plains Blvd",
    "sg:city":"Amarillo",
    "sg:classifiers":[
        {
            "category":"Shopping",
            "type":"Retail Goods"
        }
    ],
    "sg:phone":"+1 806 353 2548",
    "sg:postcode":"79102",
    "sg:province":"TX",
    "sg:tags":[
        "merchandise",
        "animal"
    ],
    "wof:name":"Dog PATCH USA",
    "wof:placetype":"venue"
},
  "geometry": {"coordinates":[-101.874961,35.202687],"type":"Point"}
}