{
  "type": "Feature",
  "properties": {
    "iso:country":"US",
    "sg:address":"4225 Johns Light Dr",
    "sg:city":"Austin",
    "sg:classifiers":[
        {
            "category":"Wholesale",
            "subcategory":"Furniture",
            "type":"Manufacturing & Wholesale Goods"
        }
    ],
    "sg:phone":"+1 512 246 6755",
    "sg:postcode":"78727",
    "sg:province":"TX",
    "sg:tags":[
        "furniture-wholesale",
        "manufacturer"
    ],
    "wof:name":"Lifestyle Enterprises Group",
    "wof:placetype":"venue"
},
  "geometry": {"coordinates":[-97.70602100000001,30.441608],"type":"Point"}
}