{
  "type": "Feature",
  "properties": {
    "iso:country":"US",
    "sg:address":"3952 N Story Rd",
    "sg:city":"Irving",
    "sg:classifiers":[
        {
            "category":"Retail",
            "subcategory":"Repair Shop",
            "type":"Services"
        }
    ],
    "sg:phone":"+1 972 871 2838",
    "sg:postcode":"75038",
    "sg:province":"TX",
    "wof:name":"Chapin Clean",
    "wof:placetype":"venue"
},
  "geometry": {"coordinates":[-96.975548,32.859649],"type":"Point"}
}