{
  "type": "Feature",
  "properties": {
    "iso:country":"US",
    "sg:address":"18518 Andalusian Dr",
    "sg:city":"Cypress",
    "sg:classifiers":[
        {
            "category":"Personal",
            "type":"Services"
        }
    ],
    "sg:phone":"+1 281 859 2437",
    "sg:postcode":"77433",
    "sg:province":"TX",
    "wof:name":"My Massage Therapist",
    "wof:placetype":"venue"
},
  "geometry": {"coordinates":[-95.69180799999999,29.88277],"type":"Point"}
}