{
  "type": "Feature",
  "properties": {
    "iso:country":"US",
    "sg:address":"615 Elca Ln",
    "sg:city":"Brownsville",
    "sg:classifiers":[
        {
            "category":"Manufacturing",
            "subcategory":"Tools & Machinery",
            "type":"Manufacturing & Wholesale Goods"
        }
    ],
    "sg:phone":"+1 956 548 9700",
    "sg:postcode":"78521",
    "sg:province":"TX",
    "sg:tags":[
        "automotive",
        "switch",
        "mfg"
    ],
    "wof:name":"Delphi Mechatronic Systems",
    "wof:placetype":"venue"
},
  "geometry": {"coordinates":[-97.44381300000001,25.906478],"type":"Point"}
}