{
  "type": "Feature",
  "properties": {
    "iso:country":"US",
    "sg:address":"1011 County Road 212",
    "sg:city":"Giddings",
    "sg:classifiers":[
        {
            "category":"Museum",
            "type":"Entertainment"
        }
    ],
    "sg:phone":"+1 979 366 2441",
    "sg:postcode":"78942",
    "sg:province":"TX",
    "wof:name":"Texas Wendish Heritage Museum",
    "wof:placetype":"venue"
},
  "geometry": {"coordinates":[-96.986925,30.116386],"type":"Point"}
}