{
  "type": "Feature",
  "properties": {
    "iso:country":"US",
    "sg:address":"500 E Ave N",
    "sg:city":"Silsbee",
    "sg:classifiers":[
        {
            "category":"Wholesale",
            "subcategory":"Machinery & Supplies",
            "type":"Manufacturing & Wholesale Goods"
        }
    ],
    "sg:phone":"+1 409 385 6422",
    "sg:postcode":"77656",
    "sg:province":"TX",
    "sg:tags":[
        "equipment",
        "drying"
    ],
    "sg:website":"www.moisturecontrols.com",
    "wof:name":"Drying Technology Inc",
    "wof:placetype":"venue"
},
  "geometry": {"coordinates":[-94.177313,30.342706],"type":"Point"}
}