{
  "type": "Feature",
  "properties": {
    "iso:country":"US",
    "sg:address":"735 S Colorado St",
    "sg:city":"Lockhart",
    "sg:classifiers":[
        {
            "category":"Home & Garden",
            "subcategory":"Garden Supply",
            "type":"Retail Goods"
        }
    ],
    "sg:phone":"+1 512 376 9959",
    "sg:postcode":"78644",
    "sg:province":"TX",
    "sg:tags":[
        "nurseryman"
    ],
    "wof:name":"Backyard Nursery Bertram's",
    "wof:placetype":"venue"
},
  "geometry": {"coordinates":[-97.669038,29.878289],"type":"Point"}
}