{
  "type": "Feature",
  "properties": {
    "iso:country":"US",
    "sg:address":"4211 Airport Dr",
    "sg:city":"Denison",
    "sg:classifiers":[
        {
            "category":"Insurance",
            "subcategory":"Hazard Insurance",
            "type":"Services"
        }
    ],
    "sg:phone":"+1 903 786 7711",
    "sg:postcode":"75020",
    "sg:province":"TX",
    "sg:tags":[
        "commercial",
        "business"
    ],
    "wof:name":"Maximum Performance",
    "wof:placetype":"venue"
},
  "geometry": {"coordinates":[-96.665916,33.715279],"type":"Point"}
}