{
  "type": "Feature",
  "properties": {
    "iso:country":"US",
    "sg:address":"3840 Fredericksburg Rd",
    "sg:city":"San Antonio",
    "sg:classifiers":[
        {
            "category":"Retail",
            "subcategory":"Auto Repair",
            "type":"Services"
        }
    ],
    "sg:phone":"+1 210 736 2300",
    "sg:postcode":"78201",
    "sg:province":"TX",
    "sg:tags":[
        "repairing",
        "automobile"
    ],
    "wof:name":"Outlaw Performance Automotive",
    "wof:placetype":"venue"
},
  "geometry": {"coordinates":[-98.545163,29.483697],"type":"Point"}
}