{
  "type": "Feature",
  "properties": {
    "iso:country":"US",
    "sg:address":"5801 Buffalo Pass",
    "sg:city":"Austin",
    "sg:classifiers":[
        {
            "category":"Professional",
            "subcategory":"Art Services",
            "type":"Services"
        }
    ],
    "sg:phone":"+1 512 447 7502",
    "sg:postcode":"78745",
    "sg:province":"TX",
    "sg:tags":[
        "photography",
        "commercial"
    ],
    "wof:name":"Arturo Zaldivar",
    "wof:placetype":"venue"
},
  "geometry": {"coordinates":[-97.804886,30.216656],"type":"Point"}
}