{
  "type": "Feature",
  "properties": {
    "iso:country":"US",
    "sg:address":"2009 Emory Ave",
    "sg:city":"Mcallen",
    "sg:classifiers":[
        {
            "category":"Home & Garden",
            "subcategory":"Home Furnishings",
            "type":"Retail Goods"
        }
    ],
    "sg:phone":"+1 956 686 2260",
    "sg:postcode":"78504",
    "sg:province":"TX",
    "wof:name":"Health Vision",
    "wof:placetype":"venue"
},
  "geometry": {"coordinates":[-98.228105,26.277824],"type":"Point"}
}