{
  "type": "Feature",
  "properties": {
    "iso:country":"US",
    "sg:address":"2011 Fostoria Tram Rd",
    "sg:city":"Cleveland",
    "sg:classifiers":[
        {
            "category":"Wholesale",
            "subcategory":"Electrical",
            "type":"Manufacturing & Wholesale Goods"
        }
    ],
    "sg:phone":"+1 281 592 2059",
    "sg:postcode":"77328",
    "sg:province":"TX",
    "sg:tags":[
        "alarm",
        "burglar",
        "system"
    ],
    "wof:name":"Burkett Security Systems",
    "wof:placetype":"venue"
},
  "geometry": {"coordinates":[-95.168436,30.385134],"type":"Point"}
}