{
  "type": "Feature",
  "properties": {
    "iso:country":"US",
    "sg:address":"1355 Stevenage Ln",
    "sg:city":"Channelview",
    "sg:classifiers":[
        {
            "category":"Manufacturing",
            "subcategory":"Food",
            "type":"Manufacturing & Wholesale Goods"
        }
    ],
    "sg:phone":"+1 281 452 2801",
    "sg:postcode":"77530",
    "sg:province":"TX",
    "sg:tags":[
        "corn",
        "product"
    ],
    "wof:name":"Roasted Corn Fabi",
    "wof:placetype":"venue"
},
  "geometry": {"coordinates":[-95.14627299999999,29.800053],"type":"Point"}
}