{
  "type": "Feature",
  "properties": {
    "iso:country":"US",
    "sg:address":"5110 Westerham Pl",
    "sg:city":"Houston",
    "sg:classifiers":[
        {
            "category":"Banks & Credit Unions",
            "subcategory":"Investment Brokerage",
            "type":"Services"
        }
    ],
    "sg:phone":"+1 281 537 6431",
    "sg:postcode":"77069",
    "sg:province":"TX",
    "sg:tags":[
        "advisory"
    ],
    "wof:name":"Jameson Financial Services",
    "wof:placetype":"venue"
},
  "geometry": {"coordinates":[-95.515157,29.995694],"type":"Point"}
}