{
  "type": "Feature",
  "properties": {
    "iso:country":"US",
    "sg:address":"2300 Red Fox Rd",
    "sg:city":"Austin",
    "sg:classifiers":[
        {
            "category":"Wholesale",
            "subcategory":"Construction Materials",
            "type":"Manufacturing & Wholesale Goods"
        }
    ],
    "sg:phone":"+1 512 266 2293",
    "sg:postcode":"78734",
    "sg:province":"TX",
    "wof:name":"Northwest Dirt Materials",
    "wof:placetype":"venue"
},
  "geometry": {"coordinates":[-97.926102,30.376855],"type":"Point"}
}