{
  "type": "Feature",
  "properties": {
    "iso:country":"US",
    "sg:address":"409 E Rundberg Ln",
    "sg:city":"Austin",
    "sg:classifiers":[
        {
            "category":"Professional",
            "type":"Services"
        }
    ],
    "sg:phone":"+1 512 837 9209",
    "sg:postcode":"78753",
    "sg:province":"TX",
    "wof:name":"O Martinez Svc Inc",
    "wof:placetype":"venue"
},
  "geometry": {"coordinates":[-97.690532,30.359329],"type":"Point"}
}