{
  "type": "Feature",
  "properties": {
    "iso:country":"US",
    "sg:address":"11035 Almond Park",
    "sg:city":"San Antonio",
    "sg:classifiers":[
        {
            "category":"Building & Trades",
            "subcategory":"Construction",
            "type":"Services"
        }
    ],
    "sg:phone":"+1 210 558 7852",
    "sg:postcode":"78249",
    "sg:province":"TX",
    "sg:tags":[
        "house"
    ],
    "wof:name":"Honey Dew Home Repair",
    "wof:placetype":"venue"
},
  "geometry": {"coordinates":[-98.635082,29.551686],"type":"Point"}
}