{
  "type": "Feature",
  "properties": {
    "iso:country":"US",
    "sg:address":"5727 82nd St",
    "sg:city":"Lubbock",
    "sg:classifiers":[
        {
            "category":"Building & Trades",
            "subcategory":"Construction",
            "type":"Services"
        }
    ],
    "sg:phone":"+1 806 783 8586",
    "sg:postcode":"79424",
    "sg:province":"TX",
    "sg:tags":[
        "general",
        "contractor"
    ],
    "wof:name":"Parkway Construction Co",
    "wof:placetype":"venue"
},
  "geometry": {"coordinates":[-101.93959099999999,33.519625],"type":"Point"}
}