{
  "type": "Feature",
  "properties": {
    "iso:country":"US",
    "sg:address":"1219 N Verne St",
    "sg:city":"Rockport",
    "sg:classifiers":[
        {
            "category":"Recreation",
            "subcategory":"Marina",
            "type":"Entertainment"
        }
    ],
    "sg:phone":"+1 361 729 0483",
    "sg:postcode":"78382",
    "sg:province":"TX",
    "sg:tags":[
        "repairing",
        "boat"
    ],
    "wof:name":"Waller's Boat Repair",
    "wof:placetype":"venue"
},
  "geometry": {"coordinates":[-97.06195200000001,28.03746],"type":"Point"}
}