{
  "type": "Feature",
  "properties": {
    "iso:country":"US",
    "sg:address":"14602 Garden Rd",
    "sg:city":"Pearland",
    "sg:classifiers":[
        {
            "category":"Shopping",
            "subcategory":"Used Merchandise",
            "type":"Retail Goods"
        }
    ],
    "sg:phone":"+1 281 997 8807",
    "sg:postcode":"77581",
    "sg:province":"TX",
    "sg:tags":[
        "antique"
    ],
    "wof:name":"Garden Road Antiques",
    "wof:placetype":"venue"
},
  "geometry": {"coordinates":[-95.320723,29.561957],"type":"Point"}
}