{
  "type": "Feature",
  "properties": {
    "iso:country":"US",
    "sg:address":"4101 Greenbriar St Ste 305",
    "sg:city":"Houston",
    "sg:classifiers":[
        {
            "category":"Health Services",
            "subcategory":"Doctor",
            "type":"Services"
        }
    ],
    "sg:phone":"+1 713 523 7844",
    "sg:postcode":"77098",
    "sg:province":"TX",
    "wof:name":"Velazquez Medical Practice",
    "wof:placetype":"venue"
},
  "geometry": {"coordinates":[-95.412662,29.729811],"type":"Point"}
}