{
  "type": "Feature",
  "properties": {
    "iso:country":"US",
    "sg:address":"13301 Midway Rd",
    "sg:city":"Dallas",
    "sg:classifiers":[
        {
            "category":"Banks & Credit Unions",
            "subcategory":"Bank",
            "type":"Services"
        }
    ],
    "sg:phone":"+1 972 588 6688",
    "sg:postcode":"75244",
    "sg:province":"TX",
    "wof:name":"Wells Fargo",
    "wof:placetype":"venue"
},
  "geometry": {"coordinates":[-96.839247,32.926647],"type":"Point"}
}