{
  "type": "Feature",
  "properties": {
    "iso:country":"US",
    "sg:address":"5701 Johnny Morris Rd # 97",
    "sg:city":"Austin",
    "sg:classifiers":[
        {
            "category":"Real Estate",
            "subcategory":"Real Estate Services",
            "type":"Services"
        },
        {
            "category":"Building & Trades",
            "subcategory":"Cleaning & Sanitation",
            "type":"Services"
        }
    ],
    "sg:phone":"+1 512 926 8059",
    "sg:postcode":"78724",
    "sg:province":"TX",
    "sg:tags":[
        "maintenance",
        "cleaners-interior"
    ],
    "wof:name":"Clean Out Of Sight",
    "wof:placetype":"venue"
},
  "geometry": {"coordinates":[-97.652681,30.293258],"type":"Point"}
}