{
  "type": "Feature",
  "properties": {
    "iso:country":"US",
    "sg:address":"2018 Sussex Ave",
    "sg:city":"Dallas",
    "sg:classifiers":[
        {
            "category":"Real Estate",
            "subcategory":"Real Estate Agent",
            "type":"Services"
        }
    ],
    "sg:phone":"+1 214 946 7806",
    "sg:postcode":"75203",
    "sg:province":"TX",
    "wof:name":"Ko Property Management",
    "wof:placetype":"venue"
},
  "geometry": {"coordinates":[-96.796352,32.725443],"type":"Point"}
}