{
  "type": "Feature",
  "properties": {
    "iso:country":"US",
    "sg:address":"9848 Monroe Dr",
    "sg:city":"Dallas",
    "sg:classifiers":[
        {
            "category":"Insurance",
            "subcategory":"Insurance Agent",
            "type":"Services"
        }
    ],
    "sg:phone":"+1 214 350 7719",
    "sg:postcode":"75220",
    "sg:province":"TX",
    "wof:name":"Joe Baver Insurance",
    "wof:placetype":"venue"
},
  "geometry": {"coordinates":[-96.877983,32.875776],"type":"Point"}
}