{
  "type": "Feature",
  "properties": {
    "iso:country":"US",
    "sg:address":"516 Burton Ave",
    "sg:city":"Orange",
    "sg:classifiers":[
        {
            "category":"Real Estate",
            "subcategory":"Real Estate Operator",
            "type":"Services"
        }
    ],
    "sg:phone":"+1 409 988 1851",
    "sg:postcode":"77630",
    "sg:province":"TX",
    "sg:tags":[
        "apartment"
    ],
    "wof:name":"Orange Housing Development Corporation",
    "wof:placetype":"venue"
},
  "geometry": {"coordinates":[-93.73380899999999,30.104958],"type":"Point"}
}