{
  "type": "Feature",
  "properties": {
    "iso:country":"US",
    "sg:address":"1912 US Hwy 90 Alt",
    "sg:city":"Richmond",
    "sg:classifiers":[
        {
            "category":"Education",
            "subcategory":"Dance Studio",
            "type":"Public Place"
        }
    ],
    "sg:phone":"+1 281 232 7365",
    "sg:postcode":"77469",
    "sg:province":"TX",
    "wof:name":"Mission Dance Academy",
    "wof:placetype":"venue"
},
  "geometry": {"coordinates":[-95.772049,29.576748],"type":"Point"}
}