{
  "type": "Feature",
  "properties": {
    "iso:country":"US",
    "sg:address":"713 Doral Ct",
    "sg:city":"Midland",
    "sg:classifiers":[
        {
            "category":"Building & Trades",
            "subcategory":"Construction",
            "type":"Services"
        }
    ],
    "sg:phone":"+1 432 687 2960",
    "sg:postcode":"79705",
    "sg:province":"TX",
    "sg:tags":[
        "contractor"
    ],
    "wof:name":"Custom Living Spaces",
    "wof:placetype":"venue"
},
  "geometry": {"coordinates":[-102.098811,32.051093],"type":"Point"}
}