{
  "type": "Feature",
  "properties": {
    "iso:country":"US",
    "sg:address":"112 E Camp Wisdom Rd",
    "sg:city":"Duncanville",
    "sg:classifiers":[
        {
            "category":"Personal",
            "subcategory":"Beauty Salon",
            "type":"Services"
        }
    ],
    "sg:phone":"+1 972 296 8650",
    "sg:postcode":"75116",
    "sg:province":"TX",
    "sg:tags":[
        "shop"
    ],
    "wof:name":"Hair Nettes Salon",
    "wof:placetype":"venue"
},
  "geometry": {"coordinates":[-96.90618499999999,32.661766],"type":"Point"}
}