{
  "type": "Feature",
  "properties": {
    "iso:country":"US",
    "sg:address":"2504 Isabella St",
    "sg:city":"Houston",
    "sg:classifiers":[
        {
            "category":"Building & Trades",
            "subcategory":"Electrical",
            "type":"Services"
        }
    ],
    "sg:phone":"+1 713 523 6937",
    "sg:postcode":"77004",
    "sg:province":"TX",
    "sg:tags":[
        "electrical",
        "contractor"
    ],
    "wof:name":"Big Dog Electric",
    "wof:placetype":"venue"
},
  "geometry": {"coordinates":[-95.368093,29.728897],"type":"Point"}
}