{
  "type": "Feature",
  "properties": {
    "iso:country":"US",
    "sg:address":"7808 Barryknoll Ln",
    "sg:city":"Port Arthur",
    "sg:classifiers":[
        {
            "category":"Professional",
            "subcategory":"Management & Consulting",
            "type":"Services"
        }
    ],
    "sg:phone":"+1 409 729 4277",
    "sg:postcode":"77642",
    "sg:province":"TX",
    "sg:tags":[
        "business"
    ],
    "wof:name":"Camberton",
    "wof:placetype":"venue"
},
  "geometry": {"coordinates":[-93.96756499999999,29.954245],"type":"Point"}
}