{
  "type": "Feature",
  "properties": {
    "iso:country":"US",
    "sg:address":"5709 Whitecliff Cir",
    "sg:city":"Plano",
    "sg:classifiers":[
        {
            "category":"Professional",
            "subcategory":"Business Services",
            "type":"Services"
        }
    ],
    "sg:phone":"+1 972 732 1514",
    "sg:postcode":"75093",
    "sg:province":"TX",
    "wof:name":"Kharrat Group Inc",
    "wof:placetype":"venue"
},
  "geometry": {"coordinates":[-96.818026,33.022553],"type":"Point"}
}