{
  "type": "Feature",
  "properties": {
    "iso:country":"US",
    "sg:address":"210 S Main St",
    "sg:city":"Salado",
    "sg:classifiers":[
        {
            "category":"Organizations",
            "subcategory":"Religious Organization",
            "type":"Services"
        }
    ],
    "sg:phone":"+1 254 947 5465",
    "sg:postcode":"76571",
    "sg:province":"TX",
    "wof:name":"First Baptist Church",
    "wof:placetype":"venue"
},
  "geometry": {"coordinates":[-97.537206,30.944163],"type":"Point"}
}