{
  "type": "Feature",
  "properties": {
    "iso:country":"US",
    "sg:address":"814 Hueco Springs Loop Rd",
    "sg:city":"New Braunfels",
    "sg:classifiers":[
        {
            "category":"Professional",
            "subcategory":"Management & Consulting",
            "type":"Services"
        }
    ],
    "sg:phone":"+1 830 625 4087",
    "sg:postcode":"78132",
    "sg:province":"TX",
    "wof:name":"Marketing Consulting",
    "wof:placetype":"venue"
},
  "geometry": {"coordinates":[-98.177723,29.743307],"type":"Point"}
}