{
  "type": "Feature",
  "properties": {
    "iso:country":"US",
    "sg:address":"3324 State Hwy 6",
    "sg:city":"Sugar Land",
    "sg:classifiers":[
        {
            "category":"Professional",
            "subcategory":"Computer Services",
            "type":"Services"
        }
    ],
    "sg:phone":"+1 281 980 5888",
    "sg:postcode":"77478",
    "sg:province":"TX",
    "sg:tags":[
        "repair"
    ],
    "wof:name":"Concept Computer Svc",
    "wof:placetype":"venue"
},
  "geometry": {"coordinates":[-95.60437,29.591767],"type":"Point"}
}