{
  "type": "Feature",
  "properties": {
    "iso:country":"US",
    "sg:address":"345 Oakforest Dr",
    "sg:city":"Lewisville",
    "sg:classifiers":[
        {
            "category":"Professional",
            "subcategory":"Art Services",
            "type":"Services"
        }
    ],
    "sg:phone":"+1 214 773 2655",
    "sg:postcode":"75077",
    "sg:province":"TX",
    "sg:tags":[
        "commercial",
        "design"
    ],
    "wof:name":"Custom Wakeboard Graphics",
    "wof:placetype":"venue"
},
  "geometry": {"coordinates":[-97.060277,33.077312],"type":"Point"}
}