{
  "type": "Feature",
  "properties": {
    "iso:country":"US",
    "sg:address":"6604 Snider Plz",
    "sg:city":"Dallas",
    "sg:classifiers":[
        {
            "category":"Home & Garden",
            "subcategory":"Carpets & Floor Coverings",
            "type":"Retail Goods"
        }
    ],
    "sg:phone":"+1 214 373 8533",
    "sg:postcode":"75205",
    "sg:province":"TX",
    "sg:tags":[
        "repair"
    ],
    "wof:name":"Sarkis Oriental Rugs",
    "wof:placetype":"venue"
},
  "geometry": {"coordinates":[-96.787688,32.84755],"type":"Point"}
}