{
  "type": "Feature",
  "properties": {
    "iso:country":"US",
    "sg:address":"9658 Plano Rd",
    "sg:city":"Dallas",
    "sg:classifiers":[
        {
            "category":"Shopping",
            "subcategory":"Crafts & Fabrics",
            "type":"Retail Goods"
        }
    ],
    "sg:phone":"+1 214 343 1440",
    "sg:postcode":"75238",
    "sg:province":"TX",
    "sg:tags":[
        "quilting",
        "book",
        "class",
        "supply"
    ],
    "wof:name":"Quiltmakers",
    "wof:placetype":"venue"
},
  "geometry": {"coordinates":[-96.700458,32.878659],"type":"Point"}
}