{
  "type": "Feature",
  "properties": {
    "iso:country":"US",
    "sg:address":"3000 Kellway Dr",
    "sg:city":"Carrollton",
    "sg:classifiers":[
        {
            "category":"Professional",
            "subcategory":"Credit Reporting & Collection",
            "type":"Services"
        }
    ],
    "sg:phone":"+1 972 394 3981",
    "sg:postcode":"75006",
    "sg:province":"TX",
    "sg:tags":[
        "agency"
    ],
    "wof:name":"Information Services",
    "wof:placetype":"venue"
},
  "geometry": {"coordinates":[-96.851404,32.973884],"type":"Point"}
}