{
  "type": "Feature",
  "properties": {
    "iso:country":"US",
    "sg:address":"6210 E Riverside Drive",
    "sg:city":"Austin",
    "sg:classifiers":[
        {
            "category":"Organizations",
            "subcategory":"Religious Organization",
            "type":"Services"
        }
    ],
    "sg:phone":"+1 512 385 7265",
    "sg:postcode":"78741",
    "sg:province":"TX",
    "wof:name":"Templo Sinai Church",
    "wof:placetype":"venue"
},
  "geometry": {"coordinates":[-97.704643,30.225478],"type":"Point"}
}