{
  "type": "Feature",
  "properties": {
    "iso:country":"US",
    "sg:address":"624 Trails Pkwy",
    "sg:city":"Garland",
    "sg:classifiers":[
        {
            "category":"Professional",
            "type":"Services"
        }
    ],
    "sg:phone":"+1 972 682 5647",
    "sg:postcode":"75043",
    "sg:province":"TX",
    "wof:name":"Ajalli Progressives",
    "wof:placetype":"venue"
},
  "geometry": {"coordinates":[-96.611574,32.841535],"type":"Point"}
}