{
  "type": "Feature",
  "properties": {
    "iso:country":"US",
    "sg:address":"4208 Judith Way",
    "sg:city":"Fort Worth",
    "sg:classifiers":[
        {
            "category":"Freight",
            "type":"Transportation"
        }
    ],
    "sg:phone":"+1 817 485 8258",
    "sg:postcode":"76137",
    "sg:province":"TX",
    "sg:tags":[
        "operator",
        "local",
        "trucking"
    ],
    "wof:name":"Magic Deliveries Inc",
    "wof:placetype":"venue"
},
  "geometry": {"coordinates":[-97.283883,32.860245],"type":"Point"}
}