{
  "type": "Feature",
  "properties": {
    "iso:country":"US",
    "sg:address":"320 W Rice St",
    "sg:city":"Falfurrias",
    "sg:classifiers":[
        {
            "category":"Retail",
            "subcategory":"Auto Repair",
            "type":"Services"
        }
    ],
    "sg:phone":"+1 361 325 5780",
    "sg:postcode":"78355",
    "sg:province":"TX",
    "sg:tags":[
        "general"
    ],
    "wof:name":"Johnnys Motor Service",
    "wof:placetype":"venue"
},
  "geometry": {"coordinates":[-98.147569,27.227133],"type":"Point"}
}