{
  "type": "Feature",
  "properties": {
    "iso:country":"US",
    "sg:address":"212 SW 1st St",
    "sg:city":"Andrews",
    "sg:classifiers":[
        {
            "category":"Social Services",
            "subcategory":"Child Care",
            "type":"Services"
        }
    ],
    "sg:phone":"+1 432 524 7772",
    "sg:postcode":"79714",
    "sg:province":"TX",
    "wof:name":"Kiddie Kollege Learning Ctr",
    "wof:placetype":"venue"
},
  "geometry": {"coordinates":[-102.54746900000001,32.317329],"type":"Point"}
}