{
  "type": "Feature",
  "properties": {
    "iso:country":"US",
    "sg:address":"1521 N Loop W",
    "sg:city":"Houston",
    "sg:classifiers":[
        {
            "category":"Autos & Motor Vehicles",
            "subcategory":"Fuel & Gas Station",
            "type":"Retail Goods"
        }
    ],
    "sg:postcode":"77018",
    "sg:province":"TX",
    "wof:name":"Murphy USA",
    "wof:placetype":"venue"
},
  "geometry": {"coordinates":[-95.428832,29.812302],"type":"Point"}
}