{
  "type": "Feature",
  "properties": {
    "iso:country":"US",
    "sg:address":"3105 E Harrison Ave",
    "sg:city":"Harlingen",
    "sg:classifiers":[
        {
            "category":"Retail",
            "subcategory":"Auto Repair",
            "type":"Services"
        }
    ],
    "sg:phone":"+1 956 412 9877",
    "sg:postcode":"78550",
    "sg:province":"TX",
    "sg:tags":[
        "automobile",
        "used",
        "general"
    ],
    "wof:name":"Rodriguez Homer Auto Center I",
    "wof:placetype":"venue"
},
  "geometry": {"coordinates":[-97.66327,26.190784],"type":"Point"}
}