{
  "type": "Feature",
  "properties": {
    "iso:country":"US",
    "sg:address":"920 W Houston Ave",
    "sg:city":"Mcallen",
    "sg:classifiers":[
        {
            "category":"Professional",
            "subcategory":"Computer Services",
            "type":"Services"
        }
    ],
    "sg:phone":"+1 956 688 6262",
    "sg:postcode":"78501",
    "sg:province":"TX",
    "sg:tags":[
        "repair"
    ],
    "wof:name":"Epsilon Computers",
    "wof:placetype":"venue"
},
  "geometry": {"coordinates":[-98.22999299999999,26.195952],"type":"Point"}
}