{
  "type": "Feature",
  "properties": {
    "iso:country":"US",
    "sg:address":"4350 Kolloch Dr",
    "sg:city":"Dallas",
    "sg:classifiers":[
        {
            "category":"Organizations",
            "subcategory":"Religious Organization",
            "type":"Services"
        }
    ],
    "sg:phone":"+1 214 376 2977",
    "sg:postcode":"75216",
    "sg:province":"TX",
    "wof:name":"Church of Revelation",
    "wof:placetype":"venue"
},
  "geometry": {"coordinates":[-96.75990299999999,32.709999],"type":"Point"}
}