{
  "type": "Feature",
  "properties": {
    "iso:country":"US",
    "sg:address":"14173 NW Fwy Ste 207",
    "sg:city":"Houston",
    "sg:classifiers":[
        {
            "category":"Building & Trades",
            "subcategory":"Construction",
            "type":"Services"
        }
    ],
    "sg:phone":"+1 281 257 9797",
    "sg:postcode":"77040",
    "sg:province":"TX",
    "sg:tags":[
        "air",
        "heating",
        "conditioning/hvac"
    ],
    "sg:website":"www.proairduct.net",
    "wof:name":"Pro-DC",
    "wof:placetype":"venue"
},
  "geometry": {"coordinates":[-95.29220599999999,29.804656],"type":"Point"}
}