{
  "type": "Feature",
  "properties": {
    "iso:country":"US",
    "sg:address":"340 W Main St Ste A",
    "sg:city":"Azle",
    "sg:classifiers":[
        {
            "category":"Wholesale",
            "subcategory":"Office Equipment",
            "type":"Manufacturing & Wholesale Goods"
        },
        {
            "category":"Manufacturing",
            "subcategory":"Electronics",
            "type":"Manufacturing & Wholesale Goods"
        },
        {
            "category":"Professional",
            "subcategory":"Printing & Photocopies",
            "type":"Services"
        },
        {
            "category":"Shopping",
            "subcategory":"Computers & Home Electronics",
            "type":"Retail Goods"
        }
    ],
    "sg:phone":"+1 817 444 2222",
    "sg:postcode":"76020",
    "sg:province":"TX",
    "sg:tags":[
        "scanning",
        "printer",
        "supply",
        "services-commercial",
        "printers-equipment",
        "plotting"
    ],
    "wof:name":"Sutton Printing Co",
    "wof:placetype":"venue"
},
  "geometry": {"coordinates":[-97.54652299999999,32.895405],"type":"Point"}
}