{
  "type": "Feature",
  "properties": {
    "iso:country":"US",
    "sg:address":"2147 Frey Rd",
    "sg:city":"Houston",
    "sg:classifiers":[
        {
            "category":"Building & Trades",
            "subcategory":"Construction",
            "type":"Services"
        }
    ],
    "sg:phone":"+1 713 941 8022",
    "sg:postcode":"77034",
    "sg:province":"TX",
    "sg:tags":[
        "contractor"
    ],
    "wof:name":"Gomez Cleaning Services",
    "wof:placetype":"venue"
},
  "geometry": {"coordinates":[-95.22649,29.650294],"type":"Point"}
}