{
  "type": "Feature",
  "properties": {
    "iso:country":"US",
    "sg:address":"221 E Ave B",
    "sg:city":"Muleshoe",
    "sg:classifiers":[
        {
            "category":"Manufacturing",
            "subcategory":"Printing",
            "type":"Manufacturing & Wholesale Goods"
        }
    ],
    "sg:phone":"+1 806 272 3373",
    "sg:postcode":"79347",
    "sg:province":"TX",
    "sg:tags":[
        "lithographic",
        "commercial"
    ],
    "wof:name":"Stovall Printing",
    "wof:placetype":"venue"
},
  "geometry": {"coordinates":[-102.723315,34.224744],"type":"Point"}
}