{
  "type": "Feature",
  "properties": {
    "iso:country":"US",
    "sg:address":"14604 Garner Rd",
    "sg:city":"Beaumont",
    "sg:classifiers":[
        {
            "category":"Farming",
            "subcategory":"Livestock Farm",
            "type":"Manufacturing & Wholesale Goods"
        }
    ],
    "sg:phone":"+1 409 796 1473",
    "sg:postcode":"77705",
    "sg:province":"TX",
    "sg:tags":[
        "beef",
        "feedlot",
        "cattle"
    ],
    "wof:name":"Melton Farms Inc",
    "wof:placetype":"venue"
},
  "geometry": {"coordinates":[-94.140129,29.912355],"type":"Point"}
}