{
  "type": "Feature",
  "properties": {
    "iso:country":"US",
    "sg:address":"PO Box 11555",
    "sg:city":"Houston",
    "sg:classifiers":[
        {
            "category":"Communications",
            "subcategory":"Newspaper",
            "type":"Services"
        }
    ],
    "sg:phone":"+1 281 449 9945",
    "sg:postcode":"77293",
    "sg:province":"TX",
    "sg:tags":[
        "print",
        "medium"
    ],
    "wof:name":"Northeast News",
    "wof:placetype":"venue"
},
  "geometry": {"coordinates":[-95.466904,29.8633],"type":"Point"}
}