{
  "type": "Feature",
  "properties": {
    "iso:country":"US",
    "sg:address":"2126 Irving Blvd",
    "sg:city":"Dallas",
    "sg:phone":"+1 214 760 8310",
    "sg:postcode":"75207",
    "sg:province":"TX",
    "sg:tags":[
        "case",
        "mfg",
        "fixture",
        "metal",
        "equipment",
        "display",
        "store"
    ],
    "wof:name":"M B Store Fixture Co",
    "wof:placetype":"venue"
},
  "geometry": {"coordinates":[-96.83311500000001,32.795665],"type":"Point"}
}