{
  "type": "Feature",
  "properties": {
    "iso:country":"US",
    "sg:address":"302 Almeda Rd",
    "sg:city":"Houston",
    "sg:classifiers":[
        {
            "category":"Shopping Center",
            "type":"Public Place"
        }
    ],
    "sg:phone":"+1 713 941 1214",
    "sg:postcode":"77004",
    "sg:province":"TX",
    "sg:tags":[
        "mall"
    ],
    "sg:website":"http://www.243eyemasters.listandfound.com",
    "wof:name":"Almeda Mall",
    "wof:placetype":"venue"
},
  "geometry": {"coordinates":[-95.378613,29.7232],"type":"Point"}
}