{
  "type": "Feature",
  "properties": {
    "iso:country":"US",
    "sg:address":"11391 Beach Front Dr",
    "sg:city":"El Paso",
    "sg:classifiers":[
        {
            "category":"Personal",
            "subcategory":"Beauty Salon",
            "type":"Services"
        }
    ],
    "sg:phone":"+1 915 855 6765",
    "sg:postcode":"79936",
    "sg:province":"TX",
    "sg:tags":[
        "shop"
    ],
    "wof:name":"Mercedes Beauty Salon",
    "wof:placetype":"venue"
},
  "geometry": {"coordinates":[-106.29965,31.774451],"type":"Point"}
}