{
  "type": "Feature",
  "properties": {
    "iso:country":"US",
    "sg:address":"4762 Apricot St",
    "sg:city":"Dallas",
    "sg:classifiers":[
        {
            "category":"Manufacturing",
            "subcategory":"Printing",
            "type":"Manufacturing & Wholesale Goods"
        }
    ],
    "sg:phone":"+1 214 634 2103",
    "sg:postcode":"75247",
    "sg:province":"TX",
    "sg:tags":[
        "lithographic",
        "commercial"
    ],
    "wof:name":"A Printing Co",
    "wof:placetype":"venue"
},
  "geometry": {"coordinates":[-96.880044,32.805082],"type":"Point"}
}