{
  "type": "Feature",
  "properties": {
    "iso:country":"US",
    "sg:address":"14615 Hazy Ridge Ln",
    "sg:city":"Cypress",
    "sg:classifiers":[
        {
            "category":"Professional",
            "type":"Services"
        }
    ],
    "sg:phone":"+1 281 304 4810",
    "sg:postcode":"77429",
    "sg:province":"TX",
    "wof:name":"Jody Honeycutt",
    "wof:placetype":"venue"
},
  "geometry": {"coordinates":[-95.69108799999999,29.983696],"type":"Point"}
}