{
  "type": "Feature",
  "properties": {
    "iso:country":"US",
    "sg:address":"2948 Berry Ave",
    "sg:city":"Groves",
    "sg:classifiers":[
        {
            "category":"Professional",
            "type":"Services"
        }
    ],
    "sg:phone":"+1 409 963 3534",
    "sg:postcode":"77619",
    "sg:province":"TX",
    "wof:name":"Charles J Newman",
    "wof:placetype":"venue"
},
  "geometry": {"coordinates":[-93.910237,29.933823],"type":"Point"}
}