{
  "type": "Feature",
  "properties": {
    "iso:country":"US",
    "sg:address":"824 Patti Dr",
    "sg:city":"Bedford",
    "sg:classifiers":[
        {
            "category":"Professional",
            "subcategory":"Accounting & Tax Preparation",
            "type":"Services"
        }
    ],
    "sg:phone":"+1 817 268 5149",
    "sg:postcode":"76022",
    "sg:province":"TX",
    "wof:name":"Rk Research Unlimited",
    "wof:placetype":"venue"
},
  "geometry": {"coordinates":[-97.155473,32.82672],"type":"Point"}
}