{
  "type": "Feature",
  "properties": {
    "iso:country":"US",
    "sg:address":"945 E Nasa Pkwy",
    "sg:city":"Houston",
    "sg:classifiers":[
        {
            "category":"Cinema",
            "subcategory":"Movie Rental",
            "type":"Entertainment"
        }
    ],
    "sg:phone":"+1 281 486 1195",
    "sg:postcode":"77058",
    "sg:province":"TX",
    "sg:tags":[
        "video",
        "tape"
    ],
    "wof:name":"A & B Video",
    "wof:placetype":"venue"
},
  "geometry": {"coordinates":[-95.107707,29.545366],"type":"Point"}
}