{
  "type": "Feature",
  "properties": {
    "iso:country":"US",
    "sg:address":"700 Rockledge Dr",
    "sg:city":"Fort Worth",
    "sg:classifiers":[
        {
            "category":"Building & Trades",
            "subcategory":"Construction",
            "type":"Services"
        }
    ],
    "sg:phone":"+1 817 991 8040",
    "sg:postcode":"76179",
    "sg:province":"TX",
    "sg:tags":[
        "house",
        "general",
        "contractor"
    ],
    "wof:name":"T U Contractors",
    "wof:placetype":"venue"
},
  "geometry": {"coordinates":[-97.37408499999999,32.848639],"type":"Point"}
}