{
  "type": "Feature",
  "properties": {
    "iso:country":"US",
    "sg:address":"5301 W Lovers Ln",
    "sg:city":"Dallas",
    "sg:classifiers":[
        {
            "category":"Retail",
            "subcategory":"Laundry & Dry Cleaning",
            "type":"Services"
        }
    ],
    "sg:phone":"+1 214 357 3313",
    "sg:postcode":"75209",
    "sg:province":"TX",
    "sg:tags":[
        "garment",
        "agent"
    ],
    "wof:name":"Dd Cleaners & Tailor",
    "wof:placetype":"venue"
},
  "geometry": {"coordinates":[-96.82117599999999,32.851177],"type":"Point"}
}