{
  "type": "Feature",
  "properties": {
    "iso:country":"US",
    "sg:address":"4731 McKinney Ave",
    "sg:city":"Dallas",
    "sg:classifiers":[
        {
            "category":"Professional",
            "type":"Services"
        }
    ],
    "sg:phone":"+1 214 662 0554",
    "sg:postcode":"75205",
    "sg:province":"TX",
    "wof:name":"All About You",
    "wof:placetype":"venue"
},
  "geometry": {"coordinates":[-96.785535,32.826565],"type":"Point"}
}