{
  "type": "Feature",
  "properties": {
    "iso:country":"US",
    "sg:address":"840 Yucca St",
    "sg:city":"Canutillo",
    "sg:classifiers":[
        {
            "category":"Shopping",
            "subcategory":"Pets & Pet Supplies",
            "type":"Retail Goods"
        }
    ],
    "sg:phone":"+1 915 877 3647",
    "sg:postcode":"79835",
    "sg:province":"TX",
    "sg:tags":[
        "training"
    ],
    "wof:name":"Reidsan Dog Training Center",
    "wof:placetype":"venue"
},
  "geometry": {"coordinates":[-106.58899700000001,31.922701],"type":"Point"}
}