{
  "type": "Feature",
  "properties": {
    "iso:country":"US",
    "sg:address":"5403 S Broadway Ave",
    "sg:city":"Tyler",
    "sg:classifiers":[
        {
            "category":"Building & Trades",
            "subcategory":"Construction",
            "type":"Services"
        }
    ],
    "sg:phone":"+1 903 561 0380",
    "sg:postcode":"75703",
    "sg:province":"TX",
    "sg:tags":[
        "general",
        "contractor"
    ],
    "wof:name":"Langford Construction",
    "wof:placetype":"venue"
},
  "geometry": {"coordinates":[-95.30304099999999,32.290594],"type":"Point"}
}