{
  "type": "Feature",
  "properties": {
    "iso:country":"US",
    "sg:address":"606 Midland Dr",
    "sg:city":"Houston",
    "sg:classifiers":[
        {
            "category":"Retail",
            "subcategory":"Laundry & Dry Cleaning",
            "type":"Services"
        }
    ],
    "sg:phone":"+1 281 272 8833",
    "sg:postcode":"77037",
    "sg:province":"TX",
    "sg:tags":[
        "house",
        "plant",
        "commercial",
        "drycleaning"
    ],
    "wof:name":"Restorative Cleaning Services",
    "wof:placetype":"venue"
},
  "geometry": {"coordinates":[-95.41054699999999,29.910353],"type":"Point"}
}