{
  "type": "Feature",
  "properties": {
    "iso:country":"US",
    "sg:address":"7519 April Ln",
    "sg:city":"Fort Worth",
    "sg:classifiers":[
        {
            "category":"Retail",
            "subcategory":"Repair Shop",
            "type":"Services"
        }
    ],
    "sg:phone":"+1 817 656 7456",
    "sg:postcode":"76180",
    "sg:province":"TX",
    "wof:name":"Harrys Golf Club",
    "wof:placetype":"venue"
},
  "geometry": {"coordinates":[-97.219922,32.863334],"type":"Point"}
}