{
  "type": "Feature",
  "properties": {
    "iso:country":"US",
    "sg:address":"3500 Pershing Dr",
    "sg:city":"El Paso",
    "sg:classifiers":[
        {
            "category":"Organizations",
            "subcategory":"Religious Organization",
            "type":"Services"
        }
    ],
    "sg:phone":"+1 915 566 1654",
    "sg:postcode":"79903",
    "sg:province":"TX",
    "sg:tags":[
        "church"
    ],
    "wof:name":"Faith United Methodist Church",
    "wof:placetype":"venue"
},
  "geometry": {"coordinates":[-106.451471,31.787051],"type":"Point"}
}