{
  "type": "Feature",
  "properties": {
    "iso:country":"US",
    "sg:address":"2574 W Pioneer Pkwy",
    "sg:city":"Arlington",
    "sg:classifiers":[
        {
            "category":"Personal",
            "subcategory":"Beauty Salon",
            "type":"Services"
        }
    ],
    "sg:phone":"+1 817 277 6161",
    "sg:postcode":"76013",
    "sg:province":"TX",
    "sg:tags":[
        "shop"
    ],
    "wof:name":"Hair Designers",
    "wof:placetype":"venue"
},
  "geometry": {"coordinates":[-97.150457,32.709564],"type":"Point"}
}