{
  "type": "Feature",
  "properties": {
    "iso:country":"US",
    "sg:address":"1009 Wade Hampton St",
    "sg:city":"Fort Worth",
    "sg:classifiers":[
        {
            "category":"Retail",
            "subcategory":"Repair Shop",
            "type":"Services"
        }
    ],
    "sg:phone":"+1 817 249 2584",
    "sg:postcode":"76126",
    "sg:province":"TX",
    "sg:tags":[
        "equipment",
        "electrical"
    ],
    "wof:name":"Westside Cash Register",
    "wof:placetype":"venue"
},
  "geometry": {"coordinates":[-97.460711,32.6738],"type":"Point"}
}