{
  "type": "Feature",
  "properties": {
    "iso:country":"US",
    "sg:address":"316 N Staples St",
    "sg:city":"Corpus Christi",
    "sg:classifiers":[
        {
            "category":"Shopping",
            "type":"Retail Goods"
        }
    ],
    "sg:phone":"+1 361 888 6758",
    "sg:postcode":"78401",
    "sg:province":"TX",
    "sg:tags":[
        "candle",
        "merchandise",
        "news"
    ],
    "sg:website":"www.texmexcurios.com",
    "wof:name":"Tex-Mex Curios Inc",
    "wof:placetype":"venue"
},
  "geometry": {"coordinates":[-97.402976,27.79312],"type":"Point"}
}