{
  "type": "Feature",
  "properties": {
    "iso:country":"US",
    "sg:address":"253 Co Rd 364",
    "sg:city":"Kenedy",
    "sg:classifiers":[
        {
            "category":"Government",
            "subcategory":"Office",
            "type":"Public Place"
        }
    ],
    "sg:phone":"+1 830 583 2035",
    "sg:postcode":"78130",
    "sg:province":"TX",
    "sg:tags":[
        "conservation"
    ],
    "wof:name":"H Rudolph & Son Inc",
    "wof:placetype":"venue"
},
  "geometry": {"coordinates":[-98.07592099999999,29.668433],"type":"Point"}
}