{
  "type": "Feature",
  "properties": {
    "iso:country":"US",
    "sg:address":"5705 Verbena St",
    "sg:city":"San Antonio",
    "sg:classifiers":[
        {
            "category":"Shopping",
            "subcategory":"Books",
            "type":"Retail Goods"
        }
    ],
    "sg:phone":"+1 210 696 8508",
    "sg:postcode":"78240",
    "sg:province":"TX",
    "wof:name":"Catherine Meaney Books On SW",
    "wof:placetype":"venue"
},
  "geometry": {"coordinates":[-98.597447,29.53396],"type":"Point"}
}