{
  "type": "Feature",
  "properties": {
    "iso:country":"US",
    "sg:address":"100 S Bryan Rd",
    "sg:city":"Mission",
    "sg:classifiers":[
        {
            "category":"Restaurant",
            "type":"Food & Drink"
        }
    ],
    "sg:phone":"+1 956 585 1922",
    "sg:postcode":"78572",
    "sg:province":"TX",
    "wof:name":"Danny's Mexican Restaurant",
    "wof:placetype":"venue"
},
  "geometry": {"coordinates":[-98.311493,26.203758],"type":"Point"}
}