{
  "type": "Feature",
  "properties": {
    "iso:country":"US",
    "sg:address":"3618 Green Spring",
    "sg:city":"San Antonio",
    "sg:classifiers":[
        {
            "category":"Professional",
            "subcategory":"Computer Services",
            "type":"Services"
        }
    ],
    "sg:phone":"+1 210 494 9933",
    "sg:postcode":"78247",
    "sg:province":"TX",
    "wof:name":"Techs After 5",
    "wof:placetype":"venue"
},
  "geometry": {"coordinates":[-98.425116,29.582811],"type":"Point"}
}