{
  "type": "Feature",
  "properties": {
    "iso:country":"US",
    "sg:address":"1912 Hebron Pkwy E",
    "sg:city":"Carrollton",
    "sg:classifiers":[
        {
            "category":"Shopping",
            "subcategory":"Florist",
            "type":"Retail Goods"
        }
    ],
    "sg:phone":"+1 972 394 5090",
    "sg:postcode":"75007",
    "sg:province":"TX",
    "wof:name":"Texas In Bloom Inc",
    "wof:placetype":"venue"
},
  "geometry": {"coordinates":[-96.884407,33.024594],"type":"Point"}
}