{
  "type": "Feature",
  "properties": {
    "iso:country":"US",
    "sg:address":"580 Westlake Park Blvd",
    "sg:city":"Houston",
    "sg:classifiers":[
        {
            "category":"Wholesale",
            "subcategory":"Petroleum",
            "type":"Manufacturing & Wholesale Goods"
        },
        {
            "category":"Mining & Drilling",
            "type":"Manufacturing & Wholesale Goods"
        }
    ],
    "sg:phone":"+1 281 368 7050",
    "sg:postcode":"77079",
    "sg:province":"TX",
    "sg:tags":[
        "equipment",
        "pipeline",
        "oil",
        "mfg",
        "company",
        "gas",
        "pipe",
        "field",
        "line"
    ],
    "wof:name":"Jetair International Inc",
    "wof:placetype":"venue"
},
  "geometry": {"coordinates":[-95.630071,29.780586],"type":"Point"}
}