{
  "type": "Feature",
  "properties": {
    "iso:country":"US",
    "sg:address":"2305 Hayes Rd",
    "sg:city":"Houston",
    "sg:classifiers":[
        {
            "category":"Real Estate",
            "subcategory":"Real Estate Operator",
            "type":"Services"
        }
    ],
    "sg:phone":"+1 713 974 3185",
    "sg:postcode":"77077",
    "sg:province":"TX",
    "sg:tags":[
        "apartment"
    ],
    "wof:name":"Hayes Place",
    "wof:placetype":"venue"
},
  "geometry": {"coordinates":[-95.576131,29.739639],"type":"Point"}
}