{
  "type": "Feature",
  "properties": {
    "iso:country":"US",
    "sg:address":"6061 Scott St",
    "sg:city":"Houston",
    "sg:classifiers":[
        {
            "category":"Food & Beverages",
            "subcategory":"Liquor & Beverages",
            "type":"Retail Goods"
        }
    ],
    "sg:phone":"+1 713 741 6100",
    "sg:postcode":"77021",
    "sg:province":"TX",
    "wof:name":"Export Liquor",
    "wof:placetype":"venue"
},
  "geometry": {"coordinates":[-95.359262,29.702596],"type":"Point"}
}