{
  "type": "Feature",
  "properties": {
    "iso:country":"US",
    "sg:address":"262 Willow Dr",
    "sg:city":"Mc Queeney",
    "sg:classifiers":[
        {
            "category":"Professional",
            "type":"Services"
        }
    ],
    "sg:phone":"+1 830 557 6999",
    "sg:postcode":"78123",
    "sg:province":"TX",
    "wof:name":"Toms Tractor Service",
    "wof:placetype":"venue"
},
  "geometry": {"coordinates":[-98.032292,29.606958],"type":"Point"}
}