{
  "type": "Feature",
  "properties": {
    "iso:country":"US",
    "sg:address":"4240 Preston Smith Rd",
    "sg:city":"Odessa",
    "sg:classifiers":[
        {
            "category":"Bars & Pubs",
            "type":"Food & Drink"
        }
    ],
    "sg:phone":"+1 432 367 7064",
    "sg:postcode":"79762",
    "sg:province":"TX",
    "sg:tags":[
        "club",
        "drinking",
        "night"
    ],
    "wof:name":"Graham Central Station Inc",
    "wof:placetype":"venue"
},
  "geometry": {"coordinates":[-102.326154,31.895886],"type":"Point"}
}