{
  "type": "Feature",
  "properties": {
    "iso:country":"US",
    "sg:address":"425 S El Paso St",
    "sg:city":"El Paso",
    "sg:classifiers":[
        {
            "category":"Restaurant",
            "type":"Food & Drink"
        }
    ],
    "sg:menulink":"http://www.allmenus.com/tx/el-paso/217883-burger-king/menu/",
    "sg:phone":"+1 915 545 1994",
    "sg:postcode":"79901",
    "sg:province":"TX",
    "sg:tags":[
        "american"
    ],
    "wof:name":"Burger King",
    "wof:placetype":"venue"
},
  "geometry": {"coordinates":[-106.4883,31.755696],"type":"Point"}
}