{
  "type": "Feature",
  "properties": {
    "iso:country":"US",
    "sg:address":"4433 Motley Dr",
    "sg:city":"Mesquite",
    "sg:classifiers":[
        {
            "category":"Professional",
            "subcategory":"Engineering",
            "type":"Services"
        }
    ],
    "sg:phone":"+1 972 270 4325",
    "sg:postcode":"75150",
    "sg:province":"TX",
    "sg:tags":[
        "repair"
    ],
    "wof:name":"J & M Service Center",
    "wof:placetype":"venue"
},
  "geometry": {"coordinates":[-96.65776099999999,32.827236],"type":"Point"}
}