{
  "type": "Feature",
  "properties": {
    "iso:country":"US",
    "sg:address":"2415 E 5th St",
    "sg:city":"Austin",
    "sg:classifiers":[
        {
            "category":"Retail",
            "subcategory":"Auto Repair",
            "type":"Services"
        }
    ],
    "sg:phone":"+1 512 538 7276",
    "sg:postcode":"78702",
    "sg:province":"TX",
    "sg:tags":[
        "motorcycle"
    ],
    "sg:website":"gogogoscooters.com",
    "wof:name":"Go Go Go Scooter Shop",
    "wof:placetype":"venue"
},
  "geometry": {"coordinates":[-97.715771,30.257851],"type":"Point"}
}