{
  "type": "Feature",
  "properties": {
    "iso:country":"US",
    "sg:address":"6355 Stinson St",
    "sg:city":"Plano",
    "sg:classifiers":[
        {
            "category":"Professional",
            "type":"Services"
        }
    ],
    "sg:phone":"+1 972 380 5976",
    "sg:postcode":"75093",
    "sg:province":"TX",
    "wof:name":"Commreps",
    "wof:placetype":"venue"
},
  "geometry": {"coordinates":[-96.838239,33.021212],"type":"Point"}
}