{
  "type": "Feature",
  "properties": {
    "iso:country":"US",
    "sg:address":"208 N Spring St",
    "sg:city":"Grand Saline",
    "sg:classifiers":[
        {
            "category":"Retail",
            "subcategory":"Self-service Laundry",
            "type":"Services"
        }
    ],
    "sg:phone":"+1 903 962 4464",
    "sg:postcode":"75140",
    "sg:province":"TX",
    "wof:name":"Granny & Pops Laundrymat",
    "wof:placetype":"venue"
},
  "geometry": {"coordinates":[-95.710604,32.674487],"type":"Point"}
}