{
  "type": "Feature",
  "properties": {
    "iso:country":"US",
    "sg:address":"1908 N Frazier St",
    "sg:city":"Conroe",
    "sg:classifiers":[
        {
            "category":"Shopping",
            "subcategory":"Shoes",
            "type":"Retail Goods"
        }
    ],
    "sg:phone":"+1 936 788 1193",
    "sg:postcode":"77301",
    "sg:province":"TX",
    "wof:name":"Baskins Group Ltd",
    "wof:placetype":"venue"
},
  "geometry": {"coordinates":[-95.466414,30.331715],"type":"Point"}
}