{
  "type": "Feature",
  "properties": {
    "iso:country":"US",
    "sg:address":"2717 Lawrence Rd",
    "sg:city":"Arlington",
    "sg:classifiers":[
        {
            "category":"Real Estate",
            "subcategory":"Real Estate Operator",
            "type":"Services"
        }
    ],
    "sg:phone":"+1 817 261 4341",
    "sg:postcode":"76006",
    "sg:province":"TX",
    "sg:tags":[
        "apartment"
    ],
    "wof:name":"Woodcreek Apartments",
    "wof:placetype":"venue"
},
  "geometry": {"coordinates":[-97.096954,32.783619],"type":"Point"}
}