{
  "type": "Feature",
  "properties": {
    "iso:country":"US",
    "sg:address":"6821 McCallum Blvd",
    "sg:city":"Dallas",
    "sg:classifiers":[
        {
            "category":"Education",
            "subcategory":"School",
            "type":"Public Place"
        }
    ],
    "sg:phone":"+1 972 250 4888",
    "sg:postcode":"75252",
    "sg:province":"TX",
    "wof:name":"Texas Torah Institute",
    "wof:placetype":"venue"
},
  "geometry": {"coordinates":[-96.786433,32.988093],"type":"Point"}
}