{
  "type": "Feature",
  "properties": {
    "iso:country":"US",
    "sg:address":"7105 Bus Park Dr",
    "sg:city":"Houston",
    "sg:classifiers":[
        {
            "category":"Wholesale",
            "subcategory":"Petroleum",
            "type":"Manufacturing & Wholesale Goods"
        }
    ],
    "sg:phone":"+1 713 849 6300",
    "sg:postcode":"77041",
    "sg:province":"TX",
    "sg:tags":[
        "pipeline",
        "integrity"
    ],
    "wof:name":"PII North America Inc",
    "wof:placetype":"venue"
},
  "geometry": {"coordinates":[-95.56667299999999,29.873081],"type":"Point"}
}