{
  "type": "Feature",
  "properties": {
    "iso:country":"US",
    "sg:address":"310 US Hwy 287",
    "sg:city":"Elkhart",
    "sg:classifiers":[
        {
            "category":"Shopping",
            "subcategory":"Department Store",
            "type":"Retail Goods"
        }
    ],
    "sg:phone":"+1 903 764 5686",
    "sg:postcode":"75839",
    "sg:province":"TX",
    "sg:tags":[
        "shop"
    ],
    "wof:name":"Dollar General",
    "wof:placetype":"venue"
},
  "geometry": {"coordinates":[-95.57875799999999,31.639764],"type":"Point"}
}