{
  "type": "Feature",
  "properties": {
    "iso:country":"US",
    "sg:address":"400 S C M Allen Pkwy",
    "sg:city":"San Marcos",
    "sg:classifiers":[
        {
            "category":"Shopping",
            "type":"Retail Goods"
        }
    ],
    "sg:phone":"+1 512 396 5315",
    "sg:postcode":"78666",
    "sg:province":"TX",
    "sg:tags":[
        "ice"
    ],
    "wof:name":"Fire & Ice Pit Stop",
    "wof:placetype":"venue"
},
  "geometry": {"coordinates":[-97.93513799999999,29.876718],"type":"Point"}
}