{
  "type": "Feature",
  "properties": {
    "iso:country":"US",
    "sg:address":"1208 Northpark Dr",
    "sg:city":"Richardson",
    "sg:classifiers":[
        {
            "category":"Shopping",
            "subcategory":"Clothing, Apparel, & Fashions",
            "type":"Retail Goods"
        }
    ],
    "sg:phone":"+1 214 346 0356",
    "sg:postcode":"75081",
    "sg:province":"TX",
    "sg:tags":[
        "accessory",
        "clothing",
        "women's"
    ],
    "wof:name":"Talbots",
    "wof:placetype":"venue"
},
  "geometry": {"coordinates":[-96.705254,32.93401],"type":"Point"}
}