{
  "type": "Feature",
  "properties": {
    "iso:country":"US",
    "sg:address":"25403 I- 45",
    "sg:city":"Spring",
    "sg:classifiers":[
        {
            "category":"Food & Beverages",
            "subcategory":"Bakery",
            "type":"Retail Goods"
        }
    ],
    "sg:phone":"+1 281 363 9890",
    "sg:postcode":"77380",
    "sg:province":"TX",
    "sg:tags":[
        "baker"
    ],
    "wof:name":"Paris Cafe & Bakery",
    "wof:placetype":"venue"
},
  "geometry": {"coordinates":[-95.44541599999999,30.1349],"type":"Point"}
}