{
  "type": "Feature",
  "properties": {
    "iso:country":"US",
    "sg:address":"1701 Hanover Dr",
    "sg:city":"Richardson",
    "sg:classifiers":[
        {
            "category":"Arts & Performance",
            "subcategory":"Theater",
            "type":"Entertainment"
        }
    ],
    "sg:phone":"+1 972 231 7200",
    "sg:postcode":"75081",
    "sg:province":"TX",
    "sg:tags":[
        "live",
        "music"
    ],
    "sg:website":"www.prodjtx.com",
    "wof:name":"Professional DJ Svc",
    "wof:placetype":"venue"
},
  "geometry": {"coordinates":[-96.691226,32.960029],"type":"Point"}
}