{
  "type": "Feature",
  "properties": {
    "iso:country":"US",
    "sg:address":"10420 Hillcroft St",
    "sg:city":"Houston",
    "sg:classifiers":[
        {
            "category":"Education",
            "subcategory":"School",
            "type":"Public Place"
        }
    ],
    "sg:phone":"+1 713 551 8100",
    "sg:postcode":"77096",
    "sg:province":"TX",
    "sg:website":"http://www.westburycoc.com",
    "wof:name":"Westbury Christian School",
    "wof:placetype":"venue"
},
  "geometry": {"coordinates":[-95.49250000000001,29.6684],"type":"Point"}
}