{
  "type": "Feature",
  "properties": {
    "iso:country":"US",
    "sg:address":"1414 Caywood Ln",
    "sg:city":"Houston",
    "sg:classifiers":[
        {
            "category":"Freight",
            "type":"Transportation"
        }
    ],
    "sg:phone":"+1 713 688 5443",
    "sg:postcode":"77055",
    "sg:province":"TX",
    "sg:tags":[
        "operator",
        "local",
        "trucking"
    ],
    "wof:name":"Dillmons Dump Trucking",
    "wof:placetype":"venue"
},
  "geometry": {"coordinates":[-95.47430900000001,29.796025],"type":"Point"}
}