{
  "type": "Feature",
  "properties": {
    "iso:country":"US",
    "sg:address":"2301 N Bryant Blvd",
    "sg:city":"San Angelo",
    "sg:classifiers":[
        {
            "category":"Restaurant",
            "type":"Food & Drink"
        },
        {
            "category":"Food & Beverages",
            "subcategory":"Groceries & Convenience Stores",
            "type":"Retail Goods"
        }
    ],
    "sg:menulink":"http://www.allmenus.com/tx/san-angelo/13327-churchs-chicken/menu/",
    "sg:phone":"+1 325 658 3142",
    "sg:postcode":"76903",
    "sg:province":"TX",
    "sg:tags":[
        "chicken",
        "wing"
    ],
    "wof:name":"Church's Chicken",
    "wof:placetype":"venue"
},
  "geometry": {"coordinates":[-100.456551,31.480169],"type":"Point"}
}