{
  "type": "Feature",
  "properties": {
    "iso:country":"US",
    "sg:address":"4200 S Hulen St",
    "sg:city":"Fort Worth",
    "sg:classifiers":[
        {
            "category":"Banks & Credit Unions",
            "subcategory":"Investment Brokerage",
            "type":"Services"
        }
    ],
    "sg:phone":"+1 817 731 1101",
    "sg:postcode":"76109",
    "sg:province":"TX",
    "sg:tags":[
        "consultant",
        "planning",
        "financial",
        "advisory"
    ],
    "wof:name":"Financial Investment Service",
    "wof:placetype":"venue"
},
  "geometry": {"coordinates":[-97.39295,32.687701],"type":"Point"}
}