{
  "type": "Feature",
  "properties": {
    "iso:country":"US",
    "sg:address":"5606 Marina Dr",
    "sg:city":"Garland",
    "sg:classifiers":[
        {
            "category":"Professional",
            "subcategory":"Business Services",
            "type":"Services"
        }
    ],
    "sg:phone":"+1 972 226 3321",
    "sg:postcode":"75043",
    "sg:province":"TX",
    "sg:tags":[
        "translator",
        "interpreter"
    ],
    "wof:name":"Polbiz",
    "wof:placetype":"venue"
},
  "geometry": {"coordinates":[-96.551384,32.858065],"type":"Point"}
}