{
  "type": "Feature",
  "properties": {
    "iso:country":"US",
    "sg:address":"1103 Wood Creek Dr",
    "sg:city":"Cedar Park",
    "sg:classifiers":[
        {
            "category":"Wholesale",
            "subcategory":"Machinery & Supplies",
            "type":"Manufacturing & Wholesale Goods"
        }
    ],
    "sg:phone":"+1 512 259 5592",
    "sg:postcode":"78613",
    "sg:province":"TX",
    "sg:tags":[
        "industrial"
    ],
    "wof:name":"Velcro USA Inc",
    "wof:placetype":"venue"
},
  "geometry": {"coordinates":[-97.847972,30.523991],"type":"Point"}
}