{
  "type": "Feature",
  "properties": {
    "iso:country":"US",
    "sg:address":"1781 Spyglass Dr Ofc",
    "sg:city":"Austin",
    "sg:classifiers":[
        {
            "category":"Arts & Performance",
            "subcategory":"Art Gallery",
            "type":"Entertainment"
        }
    ],
    "sg:phone":"+1 512 732 7378",
    "sg:postcode":"78746",
    "sg:province":"TX",
    "sg:tags":[
        "fine",
        "artist"
    ],
    "wof:name":"Darim Studios",
    "wof:placetype":"venue"
},
  "geometry": {"coordinates":[-97.79107,30.25903],"type":"Point"}
}