{
  "type": "Feature",
  "properties": {
    "iso:country":"US",
    "sg:address":"4931 Willowbend Blvd",
    "sg:city":"Houston",
    "sg:classifiers":[
        {
            "category":"Home & Garden",
            "subcategory":"Building Materials",
            "type":"Retail Goods"
        },
        {
            "category":"Building & Trades",
            "subcategory":"Construction",
            "type":"Services"
        },
        {
            "category":"Home & Garden",
            "subcategory":"Carpets & Floor Coverings",
            "type":"Retail Goods"
        }
    ],
    "sg:phone":"+1 281 660 9862",
    "sg:postcode":"77035",
    "sg:province":"TX",
    "sg:tags":[
        "roofing",
        "deck",
        "roof",
        "improvement",
        "maintenance",
        "contractor",
        "repair",
        "structure"
    ],
    "sg:website":"http://www.jackrabbitgutters.com",
    "wof:name":"Jackrabbit Gutters",
    "wof:placetype":"venue"
},
  "geometry": {"coordinates":[-95.46456000000001,29.664209],"type":"Point"}
}