{
  "type": "Feature",
  "properties": {
    "iso:country":"US",
    "sg:address":"10777 Westheimer Rd",
    "sg:city":"Houston",
    "sg:classifiers":[
        {
            "category":"Professional",
            "subcategory":"Computer Services",
            "type":"Services"
        },
        {
            "category":"Shopping",
            "subcategory":"Computers & Home Electronics",
            "type":"Retail Goods"
        }
    ],
    "sg:phone":"+1 713 974 9000",
    "sg:postcode":"77042",
    "sg:province":"TX",
    "sg:tags":[
        "software",
        "design",
        "system",
        "programing",
        "custom"
    ],
    "wof:name":"Caminus",
    "wof:placetype":"venue"
},
  "geometry": {"coordinates":[-95.566406,29.736671],"type":"Point"}
}