{
  "type": "Feature",
  "properties": {
    "iso:country":"US",
    "sg:address":"6210 Walden Rd",
    "sg:city":"Beaumont",
    "sg:classifiers":[
        {
            "category":"Wholesale",
            "subcategory":"Machinery & Supplies",
            "type":"Manufacturing & Wholesale Goods"
        }
    ],
    "sg:phone":"+1 409 840 4463",
    "sg:postcode":"77707",
    "sg:province":"TX",
    "sg:tags":[
        "contractor"
    ],
    "sg:website":"www.briggsequipment.com",
    "wof:name":"Briggs Equipment",
    "wof:placetype":"venue"
},
  "geometry": {"coordinates":[-94.164891,30.038656],"type":"Point"}
}