{
  "type": "Feature",
  "properties": {
    "iso:country":"US",
    "sg:address":"908 E 5th St",
    "sg:city":"Austin",
    "sg:classifiers":[
        {
            "category":"Banks & Credit Unions",
            "subcategory":"Bank",
            "type":"Services"
        }
    ],
    "sg:phone":"+1 512 493 0913",
    "sg:postcode":"78702",
    "sg:province":"TX",
    "wof:name":"Banco Immobiliare",
    "wof:placetype":"venue"
},
  "geometry": {"coordinates":[-97.73300399999999,30.264275],"type":"Point"}
}