{
  "type": "Feature",
  "properties": {
    "iso:country":"US",
    "sg:address":"8805 Saint Thomas Cir",
    "sg:city":"Dallas",
    "sg:classifiers":[
        {
            "category":"Real Estate",
            "subcategory":"Real Estate Operator",
            "type":"Services"
        }
    ],
    "sg:phone":"+1 214 320 3611",
    "sg:postcode":"75228",
    "sg:province":"TX",
    "sg:tags":[
        "apartment"
    ],
    "wof:name":"Shadow Glen Apartments",
    "wof:placetype":"venue"
},
  "geometry": {"coordinates":[-96.692545,32.798872],"type":"Point"}
}