{
  "type": "Feature",
  "properties": {
    "iso:country":"US",
    "sg:address":"600 Shelby Rd",
    "sg:city":"Fort Worth",
    "sg:classifiers":[
        {
            "category":"Building & Trades",
            "subcategory":"Cleaning & Sanitation",
            "type":"Services"
        }
    ],
    "sg:phone":"+1 817 293 5553",
    "sg:postcode":"76140",
    "sg:province":"TX",
    "sg:tags":[
        "carpet"
    ],
    "sg:website":"www.servpro.com",
    "wof:name":"SERVPRO",
    "wof:placetype":"venue"
},
  "geometry": {"coordinates":[-97.274708,32.623877],"type":"Point"}
}