{
  "type": "Feature",
  "properties": {
    "iso:country":"US",
    "sg:address":"802 W 7th St",
    "sg:city":"Dalhart",
    "sg:classifiers":[
        {
            "category":"Farming",
            "subcategory":"Farm",
            "type":"Manufacturing & Wholesale Goods"
        }
    ],
    "sg:phone":"+1 806 249 8359",
    "sg:postcode":"79022",
    "sg:province":"TX",
    "wof:name":"Sublette Farms",
    "wof:placetype":"venue"
},
  "geometry": {"coordinates":[-102.533249,36.059022],"type":"Point"}
}