{
  "type": "Feature",
  "properties": {
    "iso:country":"US",
    "sg:address":"401 N Main St",
    "sg:city":"Springtown",
    "sg:classifiers":[
        {
            "category":"Retail",
            "subcategory":"Funeral Services",
            "type":"Services"
        }
    ],
    "sg:phone":"+1 817 523 7211",
    "sg:postcode":"76082",
    "sg:province":"TX",
    "sg:tags":[
        "director"
    ],
    "wof:name":"White Funeral Homes Inc",
    "wof:placetype":"venue"
},
  "geometry": {"coordinates":[-97.684747,32.970673],"type":"Point"}
}