{
  "type": "Feature",
  "properties": {
    "iso:country":"US",
    "sg:address":"419 Cottletown Rd",
    "sg:city":"Smithville",
    "sg:classifiers":[
        {
            "category":"Professional",
            "subcategory":"Detective & Security Services",
            "type":"Services"
        }
    ],
    "sg:phone":"+1 512 517 6472",
    "sg:postcode":"78957",
    "sg:province":"TX",
    "sg:tags":[
        "information",
        "bureau"
    ],
    "wof:name":"Diamond It Services Inc",
    "wof:placetype":"venue"
},
  "geometry": {"coordinates":[-97.19847900000001,30.078529],"type":"Point"}
}