{
  "type": "Feature",
  "properties": {
    "iso:country":"US",
    "sg:address":"1626 Federal Rd",
    "sg:city":"Houston",
    "sg:classifiers":[
        {
            "category":"Retail",
            "subcategory":"Event Space",
            "type":"Services"
        }
    ],
    "sg:phone":"+1 713 455 4003",
    "sg:postcode":"77015",
    "sg:province":"TX",
    "sg:tags":[
        "venue"
    ],
    "wof:name":"Party & Reception Center Inc",
    "wof:placetype":"venue"
},
  "geometry": {"coordinates":[-95.213303,29.760799],"type":"Point"}
}