{
  "type": "Feature",
  "properties": {
    "iso:country":"US",
    "sg:address":"316 N Bonnie Brae St",
    "sg:city":"Denton",
    "sg:classifiers":[
        {
            "category":"Retail",
            "subcategory":"Repair Shop",
            "type":"Services"
        }
    ],
    "sg:phone":"+1 940 382 7049",
    "sg:postcode":"76201",
    "sg:province":"TX",
    "wof:name":"Willies Service Inc",
    "wof:placetype":"venue"
},
  "geometry": {"coordinates":[-97.161654,33.217775],"type":"Point"}
}