{
  "type": "Feature",
  "properties": {
    "iso:country":"US",
    "sg:address":"508 E Garland St",
    "sg:city":"Grand Saline",
    "sg:classifiers":[
        {
            "category":"Professional",
            "type":"Services"
        }
    ],
    "sg:phone":"+1 903 962 0000",
    "sg:postcode":"75140",
    "sg:province":"TX",
    "wof:name":"Whisky Hill Custom Cycle",
    "wof:placetype":"venue"
},
  "geometry": {"coordinates":[-95.70403399999999,32.67435],"type":"Point"}
}