{
  "type": "Feature",
  "properties": {
    "iso:country":"US",
    "sg:address":"10527 FM 1764",
    "sg:city":"Santa Fe",
    "sg:classifiers":[
        {
            "category":"Restaurant",
            "type":"Food & Drink"
        }
    ],
    "sg:phone":"+1 409 316 1611",
    "sg:postcode":"77510",
    "sg:province":"TX",
    "wof:name":"Ranchland Cafe",
    "wof:placetype":"venue"
},
  "geometry": {"coordinates":[-95.05306,29.392419],"type":"Point"}
}