{
  "type": "Feature",
  "properties": {
    "iso:country":"US",
    "sg:address":"3602 Fern River Dr",
    "sg:city":"Humble",
    "sg:classifiers":[
        {
            "category":"Retail",
            "subcategory":"Auto Repair",
            "type":"Services"
        }
    ],
    "sg:phone":"+1 281 689 2353",
    "sg:postcode":"77345",
    "sg:province":"TX",
    "sg:tags":[
        "general"
    ],
    "wof:name":"First Auto Source Inc",
    "wof:placetype":"venue"
},
  "geometry": {"coordinates":[-95.184595,30.070302],"type":"Point"}
}