{
  "type": "Feature",
  "properties": {
    "iso:country":"US",
    "sg:address":"198 Civic Cir",
    "sg:city":"Lewisville",
    "sg:classifiers":[
        {
            "category":"Social Services",
            "subcategory":"Child Care",
            "type":"Services"
        }
    ],
    "sg:phone":"+1 972 221 3910",
    "sg:postcode":"75067",
    "sg:province":"TX",
    "sg:tags":[
        "day"
    ],
    "wof:name":"Family Prtctive Svcs Txas Dept",
    "wof:placetype":"venue"
},
  "geometry": {"coordinates":[-97.02363800000001,33.044151],"type":"Point"}
}