{
  "type": "Feature",
  "properties": {
    "iso:country":"US",
    "sg:address":"14140 Cypress North Houston Rd",
    "sg:city":"Cypress",
    "sg:classifiers":[
        {
            "category":"Building & Trades",
            "subcategory":"Construction",
            "type":"Services"
        }
    ],
    "sg:phone":"+1 281 477 6662",
    "sg:postcode":"77429",
    "sg:province":"TX",
    "sg:tags":[
        "specializing",
        "contractor",
        "utility"
    ],
    "wof:name":"George M Construction Co Inc",
    "wof:placetype":"venue"
},
  "geometry": {"coordinates":[-95.634557,29.947431],"type":"Point"}
}