{
  "type": "Feature",
  "properties": {
    "iso:country":"US",
    "sg:address":"2411 Coggin Ave",
    "sg:city":"Brownwood",
    "sg:classifiers":[
        {
            "category":"Organizations",
            "subcategory":"Religious Organization",
            "type":"Services"
        }
    ],
    "sg:phone":"+1 325 646 8901",
    "sg:postcode":"76801",
    "sg:province":"TX",
    "sg:tags":[
        "church"
    ],
    "wof:name":"First Christian Church Inc",
    "wof:placetype":"venue"
},
  "geometry": {"coordinates":[-98.988614,31.699922],"type":"Point"}
}