{
  "type": "Feature",
  "properties": {
    "iso:country":"US",
    "sg:address":"9500 Co Rd 603",
    "sg:city":"Burleson",
    "sg:classifiers":[
        {
            "category":"Insurance",
            "subcategory":"Health Insurance",
            "type":"Services"
        }
    ],
    "sg:phone":"+1 817 447 6858",
    "sg:postcode":"76028",
    "sg:province":"TX",
    "sg:tags":[
        "accident"
    ],
    "wof:name":"National Health Insurance Co",
    "wof:placetype":"venue"
},
  "geometry": {"coordinates":[-97.255118,32.523713],"type":"Point"}
}