{
  "type": "Feature",
  "properties": {
    "iso:country":"US",
    "sg:address":"4760 Beechnut St",
    "sg:city":"Houston",
    "sg:classifiers":[
        {
            "category":"Health Services",
            "subcategory":"Optometrist",
            "type":"Services"
        }
    ],
    "sg:phone":"+1 713 664 4760",
    "sg:postcode":"77096",
    "sg:province":"TX",
    "sg:website":"www.houstondryeyeclinic.com",
    "wof:name":"Allan J. Panzer",
    "wof:placetype":"venue"
},
  "geometry": {"coordinates":[-95.461118,29.689242],"type":"Point"}
}