{
  "type": "Feature",
  "properties": {
    "iso:country":"US",
    "sg:address":"2201 Long Prairie Rd",
    "sg:city":"Flower Mound",
    "sg:classifiers":[
        {
            "category":"Building & Trades",
            "subcategory":"Electrical",
            "type":"Services"
        },
        {
            "category":"Wholesale",
            "subcategory":"Electrical",
            "type":"Manufacturing & Wholesale Goods"
        }
    ],
    "sg:phone":"+1 972 484 7722",
    "sg:postcode":"75022",
    "sg:province":"TX",
    "sg:tags":[
        "fire",
        "alarm",
        "system",
        "contractor"
    ],
    "wof:name":"Protection Systems L L C",
    "wof:placetype":"venue"
},
  "geometry": {"coordinates":[-97.070942,33.015521],"type":"Point"}
}