{
  "type": "Feature",
  "properties": {
    "iso:country":"US",
    "sg:address":"6601 S Fort Hood St",
    "sg:city":"Killeen",
    "sg:classifiers":[
        {
            "category":"Organizations",
            "subcategory":"Religious Organization",
            "type":"Services"
        }
    ],
    "sg:phone":"+1 254 554 2920",
    "sg:postcode":"76542",
    "sg:province":"TX",
    "sg:tags":[
        "church"
    ],
    "wof:name":"Tabernacle Baptist Church",
    "wof:placetype":"venue"
},
  "geometry": {"coordinates":[-97.76401199999999,31.063858],"type":"Point"}
}