{
  "type": "Feature",
  "properties": {
    "iso:country":"US",
    "sg:address":"829 Industrial Ave",
    "sg:city":"Robstown",
    "sg:classifiers":[
        {
            "category":"Restaurant",
            "type":"Food & Drink"
        }
    ],
    "sg:phone":"+1 361 767 2085",
    "sg:postcode":"78380",
    "sg:province":"TX",
    "sg:tags":[
        "mexican"
    ],
    "wof:name":"Taqueria Jalisco",
    "wof:placetype":"venue"
},
  "geometry": {"coordinates":[-97.657509,27.786311],"type":"Point"}
}