{
  "type": "Feature",
  "properties": {
    "iso:country":"US",
    "sg:address":"2201 Jefferson Trl",
    "sg:city":"Denton",
    "sg:classifiers":[
        {
            "category":"Shopping",
            "subcategory":"Shoes",
            "type":"Retail Goods"
        }
    ],
    "sg:phone":"+1 940 206 6657",
    "sg:postcode":"76205",
    "sg:province":"TX",
    "sg:tags":[
        "boots-retail"
    ],
    "wof:name":"Gordy's Boots",
    "wof:placetype":"venue"
},
  "geometry": {"coordinates":[-97.122849,33.182701],"type":"Point"}
}