{
  "type": "Feature",
  "properties": {
    "iso:country":"US",
    "sg:address":"1009 15th St",
    "sg:city":"Wellington",
    "sg:classifiers":[
        {
            "category":"Health Services",
            "subcategory":"Doctor",
            "type":"Services"
        }
    ],
    "sg:phone":"+1 806 447 5311",
    "sg:postcode":"79095",
    "sg:province":"TX",
    "sg:tags":[
        "clinic"
    ],
    "wof:name":"Collingsworth Family Clinic",
    "wof:placetype":"venue"
},
  "geometry": {"coordinates":[-100.212063,34.849014],"type":"Point"}
}