{
  "type": "Feature",
  "properties": {
    "iso:country":"US",
    "sg:address":"8820 US Hwy 67",
    "sg:city":"Alvarado",
    "sg:classifiers":[
        {
            "category":"Home & Garden",
            "subcategory":"Building Materials",
            "type":"Retail Goods"
        }
    ],
    "sg:phone":"+1 817 790 8612",
    "sg:postcode":"76009",
    "sg:province":"TX",
    "sg:tags":[
        "mixed",
        "concrete"
    ],
    "wof:name":"Colorado River Components",
    "wof:placetype":"venue"
},
  "geometry": {"coordinates":[-97.173742,32.415784],"type":"Point"}
}