{
  "type": "Feature",
  "properties": {
    "iso:country":"US",
    "sg:address":"100 Wagner Ave",
    "sg:city":"San Antonio",
    "sg:classifiers":[
        {
            "category":"Government",
            "subcategory":"Office",
            "type":"Public Place"
        }
    ],
    "sg:phone":"+1 210 925 7501",
    "sg:postcode":"78211",
    "sg:province":"TX",
    "sg:tags":[
        "medical",
        "group"
    ],
    "wof:name":"76th Medical Group/Sgsl",
    "wof:placetype":"venue"
},
  "geometry": {"coordinates":[-98.526341,29.36481],"type":"Point"}
}