{
  "type": "Feature",
  "properties": {
    "iso:country":"US",
    "sg:address":"655 Lavaca St",
    "sg:city":"Beaumont",
    "sg:classifiers":[
        {
            "category":"Food & Beverages",
            "subcategory":"Groceries & Convenience Stores",
            "type":"Retail Goods"
        }
    ],
    "sg:phone":"+1 409 835 0626",
    "sg:postcode":"77705",
    "sg:province":"TX",
    "wof:name":"Market Basket 06",
    "wof:placetype":"venue"
},
  "geometry": {"coordinates":[-94.087867,30.047237],"type":"Point"}
}