{
  "type": "Feature",
  "properties": {
    "iso:country":"US",
    "sg:address":"3302 S Alameda St",
    "sg:city":"Corpus Christi",
    "sg:classifiers":[
        {
            "category":"Health Services",
            "subcategory":"Medical Lab",
            "type":"Services"
        }
    ],
    "sg:phone":"+1 361 851 0333",
    "sg:postcode":"78411",
    "sg:province":"TX",
    "sg:tags":[
        "laboratory"
    ],
    "wof:name":"Childrens Hlth Assoc of Crps C",
    "wof:placetype":"venue"
},
  "geometry": {"coordinates":[-97.386915,27.752374],"type":"Point"}
}