{
  "type": "Feature",
  "properties": {
    "iso:country":"US",
    "sg:address":"3013 W Grand Ave",
    "sg:city":"Marshall",
    "sg:classifiers":[
        {
            "category":"Autos & Motor Vehicles",
            "subcategory":"Automobile Sales",
            "type":"Retail Goods"
        }
    ],
    "sg:phone":"+1 903 938 8913",
    "sg:postcode":"75670",
    "sg:province":"TX",
    "sg:tags":[
        "used"
    ],
    "wof:name":"Ea Auto Sales",
    "wof:placetype":"venue"
},
  "geometry": {"coordinates":[-94.39743900000001,32.548735],"type":"Point"}
}