{
  "type": "Feature",
  "properties": {
    "iso:country":"US",
    "sg:address":"8008 Laurel Bend",
    "sg:city":"San Antonio",
    "sg:classifiers":[
        {
            "category":"Building & Trades",
            "subcategory":"Plumbing",
            "type":"Services"
        }
    ],
    "sg:phone":"+1 210 521 6844",
    "sg:postcode":"78250",
    "sg:province":"TX",
    "sg:tags":[
        "contractor"
    ],
    "wof:name":"900 Plumber",
    "wof:placetype":"venue"
},
  "geometry": {"coordinates":[-98.684884,29.517143],"type":"Point"}
}