{
  "type": "Feature",
  "properties": {
    "iso:country":"US",
    "sg:address":"4355 Goliad St",
    "sg:city":"Beaumont",
    "sg:classifiers":[
        {
            "category":"Organizations",
            "subcategory":"Community Association",
            "type":"Services"
        }
    ],
    "sg:phone":"+1 409 842 1499",
    "sg:postcode":"77705",
    "sg:province":"TX",
    "wof:name":"National Sorority of PHI",
    "wof:placetype":"venue"
},
  "geometry": {"coordinates":[-94.112472,30.045395],"type":"Point"}
}