{
  "type": "Feature",
  "properties": {
    "iso:country":"US",
    "sg:address":"400 Santa Fe Dr",
    "sg:city":"Weatherford",
    "sg:classifiers":[
        {
            "category":"Food & Beverages",
            "subcategory":"Groceries & Convenience Stores",
            "type":"Retail Goods"
        }
    ],
    "sg:phone":"+1 817 599 8888",
    "sg:postcode":"76086",
    "sg:province":"TX",
    "wof:name":"Mr CS",
    "wof:placetype":"venue"
},
  "geometry": {"coordinates":[-97.79069800000001,32.75572],"type":"Point"}
}