{
  "type": "Feature",
  "properties": {
    "iso:country":"US",
    "sg:address":"601 7th St",
    "sg:city":"Port Arthur",
    "sg:classifiers":[
        {
            "category":"Retail",
            "subcategory":"Repair Shop",
            "type":"Services"
        }
    ],
    "sg:phone":"+1 409 983 6357",
    "sg:postcode":"77640",
    "sg:province":"TX",
    "sg:tags":[
        "marine",
        "electric"
    ],
    "wof:name":"G C Electric Inc",
    "wof:placetype":"venue"
},
  "geometry": {"coordinates":[-93.936166,29.874995],"type":"Point"}
}