{
  "type": "Feature",
  "properties": {
    "iso:country":"US",
    "sg:address":"916 Wynnewood Dr",
    "sg:city":"Dallas",
    "sg:classifiers":[
        {
            "category":"Health Services",
            "subcategory":"Doctor",
            "type":"Services"
        }
    ],
    "sg:phone":"+1 214 941 7611",
    "sg:postcode":"75224",
    "sg:province":"TX",
    "sg:tags":[
        "physician",
        "surgeon"
    ],
    "wof:name":"Top Care",
    "wof:placetype":"venue"
},
  "geometry": {"coordinates":[-96.831942,32.723438],"type":"Point"}
}