{
  "type": "Feature",
  "properties": {
    "iso:country":"US",
    "sg:address":"9000 Gulf Fwy",
    "sg:city":"Houston",
    "sg:classifiers":[
        {
            "category":"Shopping",
            "subcategory":"Computers & Home Electronics",
            "type":"Retail Goods"
        }
    ],
    "sg:phone":"+1 713 944 4357",
    "sg:postcode":"77017",
    "sg:province":"TX",
    "sg:tags":[
        "software"
    ],
    "sg:website":"www.computeriq.com",
    "wof:name":"Computer IQ",
    "wof:placetype":"venue"
},
  "geometry": {"coordinates":[-95.270387,29.678048],"type":"Point"}
}