{
  "type": "Feature",
  "properties": {
    "iso:country":"US",
    "sg:address":"1033 Wyoming Ave",
    "sg:city":"El Paso",
    "sg:classifiers":[
        {
            "category":"Bars & Pubs",
            "type":"Food & Drink"
        }
    ],
    "sg:phone":"+1 915 564 9838",
    "sg:postcode":"79902",
    "sg:province":"TX",
    "wof:name":"Murcia's Tavern",
    "wof:placetype":"venue"
},
  "geometry": {"coordinates":[-106.482742,31.767409],"type":"Point"}
}