{
  "type": "Feature",
  "properties": {
    "iso:country":"US",
    "sg:address":"1490 Shady Ln",
    "sg:city":"Vidor",
    "sg:classifiers":[
        {
            "category":"Building & Trades",
            "subcategory":"Landscaping Services",
            "type":"Services"
        }
    ],
    "sg:phone":"+1 409 769 2691",
    "sg:postcode":"77662",
    "sg:province":"TX",
    "sg:tags":[
        "lawn",
        "maintenance",
        "grounds"
    ],
    "wof:name":"Ray Lawn Svc",
    "wof:placetype":"venue"
},
  "geometry": {"coordinates":[-94.004835,30.142807],"type":"Point"}
}