{
  "type": "Feature",
  "properties": {
    "iso:country":"US",
    "sg:address":"5886 de Zavala Rd",
    "sg:city":"San Antonio",
    "sg:classifiers":[
        {
            "category":"Banks & Credit Unions",
            "subcategory":"Bank",
            "type":"Services"
        }
    ],
    "sg:phone":"+1 210 877 0254",
    "sg:postcode":"78231",
    "sg:province":"TX",
    "sg:tags":[
        "loan"
    ],
    "wof:name":"Payday Advance",
    "wof:placetype":"venue"
},
  "geometry": {"coordinates":[-98.59916800000001,29.56302],"type":"Point"}
}