{
  "type": "Feature",
  "properties": {
    "iso:country":"US",
    "sg:address":"1516 N Hoard Ave",
    "sg:city":"Sherman",
    "sg:classifiers":[
        {
            "category":"Shopping",
            "subcategory":"Computers & Home Electronics",
            "type":"Retail Goods"
        }
    ],
    "sg:phone":"+1 903 891 8867",
    "sg:postcode":"75090",
    "sg:province":"TX",
    "wof:name":"Dctowers",
    "wof:placetype":"venue"
},
  "geometry": {"coordinates":[-96.590554,33.655679],"type":"Point"}
}