{
  "type": "Feature",
  "properties": {
    "iso:country":"US",
    "sg:address":"216 Macarthur St",
    "sg:city":"Tyler",
    "sg:classifiers":[
        {
            "category":"Building & Trades",
            "subcategory":"Cleaning & Sanitation",
            "type":"Services"
        }
    ],
    "sg:phone":"+1 903 593 2842",
    "sg:postcode":"75704",
    "sg:province":"TX",
    "sg:tags":[
        "janitorial"
    ],
    "wof:name":"D & V Janitorial & Cleaning",
    "wof:placetype":"venue"
},
  "geometry": {"coordinates":[-95.366477,32.352257],"type":"Point"}
}