{
  "type": "Feature",
  "properties": {
    "iso:country":"US",
    "sg:address":"3400 Club Gate Dr",
    "sg:city":"Fort Worth",
    "sg:classifiers":[
        {
            "category":"Organizations",
            "subcategory":"Professional Association",
            "type":"Services"
        }
    ],
    "sg:phone":"+1 817 847 1752",
    "sg:postcode":"76137",
    "sg:province":"TX",
    "wof:name":"Chateaus Of Fossil Creek Home",
    "wof:placetype":"venue"
},
  "geometry": {"coordinates":[-97.306325,32.854259],"type":"Point"}
}