{
  "type": "Feature",
  "properties": {
    "iso:country":"US",
    "sg:address":"1111 Amarillo St",
    "sg:city":"Plainview",
    "sg:classifiers":[
        {
            "category":"Manufacturing",
            "subcategory":"Printing",
            "type":"Manufacturing & Wholesale Goods"
        }
    ],
    "sg:phone":"+1 806 293 1490",
    "sg:postcode":"79072",
    "sg:province":"TX",
    "sg:tags":[
        "typesetting"
    ],
    "wof:name":"R & H Custom Harvesters Inc",
    "wof:placetype":"venue"
},
  "geometry": {"coordinates":[-101.73703999999999,34.193692],"type":"Point"}
}