{
  "type": "Feature",
  "properties": {
    "iso:country":"US",
    "sg:address":"3218 Holly Green Dr",
    "sg:city":"Humble",
    "sg:classifiers":[
        {
            "category":"Professional",
            "subcategory":"Management & Consulting",
            "type":"Services"
        }
    ],
    "sg:phone":"+1 281 360 6117",
    "sg:postcode":"77339",
    "sg:province":"TX",
    "sg:tags":[
        "house",
        "construction"
    ],
    "wof:name":"Ashworth Associates Inc",
    "wof:placetype":"venue"
},
  "geometry": {"coordinates":[-95.192025,30.068406],"type":"Point"}
}