{
  "type": "Feature",
  "properties": {
    "iso:country":"US",
    "sg:address":"1608 Spring Creek Ct",
    "sg:city":"Keller",
    "sg:classifiers":[
        {
            "category":"Banks & Credit Unions",
            "subcategory":"Financial Services",
            "type":"Services"
        }
    ],
    "sg:phone":"+1 817 581 0980",
    "sg:postcode":"76248",
    "sg:province":"TX",
    "sg:tags":[
        "trust",
        "management"
    ],
    "wof:name":"Galemore Richard & Kat Etux",
    "wof:placetype":"venue"
},
  "geometry": {"coordinates":[-97.229558,32.899233],"type":"Point"}
}