{
  "type": "Feature",
  "properties": {
    "iso:country":"US",
    "sg:address":"2205 Ridgewood Dr",
    "sg:city":"Sherman",
    "sg:classifiers":[
        {
            "category":"Shopping",
            "subcategory":"Used Merchandise",
            "type":"Retail Goods"
        }
    ],
    "sg:phone":"+1 903 893 2517",
    "sg:postcode":"75092",
    "sg:province":"TX",
    "wof:name":"Pieces of Past",
    "wof:placetype":"venue"
},
  "geometry": {"coordinates":[-96.63008000000001,33.659222],"type":"Point"}
}