{
  "type": "Feature",
  "properties": {
    "iso:country":"US",
    "sg:address":"8502 Rio Grande St",
    "sg:city":"Houston",
    "sg:classifiers":[
        {
            "category":"Sports & Exercise",
            "subcategory":"Golf",
            "type":"Entertainment"
        }
    ],
    "sg:phone":"+1 713 896 0900",
    "sg:postcode":"77040",
    "sg:province":"TX",
    "sg:tags":[
        "course"
    ],
    "sg:website":"www.jerseymeadow.com",
    "wof:name":"Jersey Meadow Golf Course",
    "wof:placetype":"venue"
},
  "geometry": {"coordinates":[-95.572565,29.894855],"type":"Point"}
}