{
  "type": "Feature",
  "properties": {
    "iso:country":"US",
    "sg:address":"1528 Brazosport Blvd N",
    "sg:city":"Clute",
    "sg:classifiers":[
        {
            "category":"Professional",
            "subcategory":"Business Services",
            "type":"Services"
        }
    ],
    "sg:phone":"+1 979 265 7281",
    "sg:postcode":"77531",
    "sg:province":"TX",
    "wof:name":"Impex Sales Co Inc",
    "wof:placetype":"venue"
},
  "geometry": {"coordinates":[-95.403463,29.0508],"type":"Point"}
}