{
  "type": "Feature",
  "properties": {
    "iso:country":"US",
    "sg:address":"2109 Cesear Chavez",
    "sg:city":"Austin",
    "sg:classifiers":[
        {
            "category":"Shopping",
            "subcategory":"Used Merchandise",
            "type":"Retail Goods"
        }
    ],
    "sg:phone":"+1 719 640 6484",
    "sg:postcode":"78702",
    "sg:province":"TX",
    "sg:tags":[
        "vintage",
        "consignment"
    ],
    "wof:name":"Charm School Vintage",
    "wof:placetype":"venue"
},
  "geometry": {"coordinates":[-97.721509,30.255854],"type":"Point"}
}