{
  "type": "Feature",
  "properties": {
    "iso:country":"US",
    "sg:address":"129 W Water St",
    "sg:city":"Kerrville",
    "sg:classifiers":[
        {
            "category":"Shopping",
            "type":"Retail Goods"
        }
    ],
    "sg:phone":"+1 830 895 9700",
    "sg:postcode":"78028",
    "sg:province":"TX",
    "sg:tags":[
        "merchandise"
    ],
    "wof:name":"A C S Adams Copier Solutions",
    "wof:placetype":"venue"
},
  "geometry": {"coordinates":[-99.148405,30.052846],"type":"Point"}
}