{
  "type": "Feature",
  "properties": {
    "iso:country":"US",
    "sg:address":"9322 Edgebrook St",
    "sg:city":"Houston",
    "sg:classifiers":[
        {
            "category":"Organizations",
            "subcategory":"Religious Organization",
            "type":"Services"
        }
    ],
    "sg:phone":"+1 713 644 5161",
    "sg:postcode":"77075",
    "sg:province":"TX",
    "wof:name":"Trinity Fellowship Church",
    "wof:placetype":"venue"
},
  "geometry": {"coordinates":[-95.24991199999999,29.639695],"type":"Point"}
}