{
  "type": "Feature",
  "properties": {
    "iso:country":"US",
    "sg:address":"113 S 13th Ave",
    "sg:city":"Edinburg",
    "sg:classifiers":[
        {
            "category":"Personal",
            "subcategory":"Beauty Salon",
            "type":"Services"
        }
    ],
    "sg:phone":"+1 956 287 2687",
    "sg:postcode":"78539",
    "sg:province":"TX",
    "sg:tags":[
        "shop"
    ],
    "wof:name":"Doris Beauty Salon",
    "wof:placetype":"venue"
},
  "geometry": {"coordinates":[-98.16038,26.300183],"type":"Point"}
}