{
  "type": "Feature",
  "properties": {
    "iso:country":"US",
    "sg:address":"1000 Walter St",
    "sg:city":"Austin",
    "sg:classifiers":[
        {
            "category":"Building & Trades",
            "subcategory":"Construction",
            "type":"Services"
        }
    ],
    "sg:phone":"+1 512 477 2743",
    "sg:postcode":"78702",
    "sg:province":"TX",
    "sg:tags":[
        "floor",
        "laying",
        "contractor"
    ],
    "wof:name":"Trackless Floors",
    "wof:placetype":"venue"
},
  "geometry": {"coordinates":[-97.71220099999999,30.267735],"type":"Point"}
}