{
  "type": "Feature",
  "properties": {
    "iso:country":"US",
    "sg:address":"1616 Abrams Rd",
    "sg:city":"Dallas",
    "sg:classifiers":[
        {
            "category":"Professional",
            "subcategory":"Lawyer & Legal Services",
            "type":"Services"
        }
    ],
    "sg:phone":"+1 214 252 5766",
    "sg:postcode":"75214",
    "sg:province":"TX",
    "sg:tags":[
        "attorney"
    ],
    "wof:name":"E Bruce Donaghe",
    "wof:placetype":"venue"
},
  "geometry": {"coordinates":[-96.75323899999999,32.808153],"type":"Point"}
}