{
  "type": "Feature",
  "properties": {
    "iso:country":"US",
    "sg:address":"6042 Cartagena St",
    "sg:city":"Houston",
    "sg:classifiers":[
        {
            "category":"Communications",
            "subcategory":"Film & Video Production",
            "type":"Services"
        },
        {
            "category":"Communications",
            "type":"Services"
        }
    ],
    "sg:phone":"+1 713 826 4942",
    "sg:postcode":"77035",
    "sg:province":"TX",
    "sg:tags":[
        "web",
        "design",
        "video/film"
    ],
    "sg:website":"www.paintedpathdesigns.com",
    "wof:name":"Painted Path Designs",
    "wof:placetype":"venue"
},
  "geometry": {"coordinates":[-95.497184,29.651333],"type":"Point"}
}