{
  "type": "Feature",
  "properties": {
    "iso:country":"US",
    "sg:address":"5 N Bolton St",
    "sg:city":"Jacksonville",
    "sg:classifiers":[
        {
            "category":"Wholesale",
            "subcategory":"Auto Parts",
            "type":"Manufacturing & Wholesale Goods"
        }
    ],
    "sg:phone":"+1 903 586 8346",
    "sg:postcode":"75766",
    "sg:province":"TX",
    "sg:tags":[
        "automobile",
        "rebuilt"
    ],
    "wof:name":"Smith Auto Salvage",
    "wof:placetype":"venue"
},
  "geometry": {"coordinates":[-95.275019,31.965114],"type":"Point"}
}