{
  "type": "Feature",
  "properties": {
    "iso:country":"US",
    "sg:address":"3113 E Denman Ave",
    "sg:city":"Lufkin",
    "sg:classifiers":[
        {
            "category":"Building & Trades",
            "subcategory":"Construction",
            "type":"Services"
        }
    ],
    "sg:phone":"+1 936 637 3981",
    "sg:postcode":"75901",
    "sg:province":"TX",
    "sg:tags":[
        "general",
        "contractor"
    ],
    "wof:name":"Guy's Construction",
    "wof:placetype":"venue"
},
  "geometry": {"coordinates":[-94.686813,31.312692],"type":"Point"}
}