{
  "type": "Feature",
  "properties": {
    "iso:country":"US",
    "sg:address":"5703 Irvington Blvd",
    "sg:city":"Houston",
    "sg:classifiers":[
        {
            "category":"Shopping",
            "subcategory":"Clothing, Apparel, & Fashions",
            "type":"Retail Goods"
        }
    ],
    "sg:phone":"+1 713 695 0400",
    "sg:postcode":"77009",
    "sg:province":"TX",
    "wof:name":"Friends Fashion Boutique",
    "wof:placetype":"venue"
},
  "geometry": {"coordinates":[-95.361296,29.811653],"type":"Point"}
}