{
  "type": "Feature",
  "properties": {
    "iso:country":"US",
    "sg:address":"6402 Jupiter",
    "sg:city":"Temple",
    "sg:classifiers":[
        {
            "category":"Home & Garden",
            "subcategory":"Furniture",
            "type":"Retail Goods"
        }
    ],
    "sg:phone":"+1 254 939 5764",
    "sg:postcode":"76502",
    "sg:province":"TX",
    "wof:name":"Mihatsch Cabinet Shop",
    "wof:placetype":"venue"
},
  "geometry": {"coordinates":[-97.41263499999999,31.105087],"type":"Point"}
}