{
  "type": "Feature",
  "properties": {
    "iso:country":"US",
    "sg:address":"811 S Stockton Ave",
    "sg:city":"Monahans",
    "sg:classifiers":[
        {
            "category":"Restaurant",
            "type":"Food & Drink"
        }
    ],
    "sg:menulink":"http://www.allmenus.com/tx/monahans/204270-sonic/menu/",
    "sg:phone":"+1 432 943 3232",
    "sg:postcode":"79756",
    "sg:province":"TX",
    "sg:tags":[
        "burger",
        "american"
    ],
    "wof:name":"Sonic",
    "wof:placetype":"venue"
},
  "geometry": {"coordinates":[-102.890923,31.587719],"type":"Point"}
}