{
  "type": "Feature",
  "properties": {
    "iso:country":"US",
    "sg:address":"2213 Richmond Ave",
    "sg:city":"Houston",
    "sg:classifiers":[
        {
            "category":"Bars & Pubs",
            "subcategory":"Sports Bar",
            "type":"Food & Drink"
        }
    ],
    "sg:phone":"+1 713 527 9432",
    "sg:postcode":"77098",
    "sg:province":"TX",
    "wof:name":"Jime's Sports Bar",
    "wof:placetype":"venue"
},
  "geometry": {"coordinates":[-95.413498,29.733999],"type":"Point"}
}