{
  "type": "Feature",
  "properties": {
    "iso:country":"US",
    "sg:address":"2218 Patterson Industrial Dr",
    "sg:city":"Pflugerville",
    "sg:classifiers":[
        {
            "category":"Shopping",
            "subcategory":"Computers & Home Electronics",
            "type":"Retail Goods"
        }
    ],
    "sg:phone":"+1 512 873 8706",
    "sg:postcode":"78660",
    "sg:province":"TX",
    "sg:website":"www.dishnetwork.com",
    "wof:name":"DISH Network",
    "wof:placetype":"venue"
},
  "geometry": {"coordinates":[-97.628438,30.404643],"type":"Point"}
}