{
  "type": "Feature",
  "properties": {
    "iso:country":"US",
    "sg:address":"11782 Jollyville Road",
    "sg:city":"Austin",
    "sg:classifiers":[
        {
            "category":"Professional",
            "subcategory":"Lawyer & Legal Services",
            "type":"Services"
        }
    ],
    "sg:phone":"+1 512 266 6344",
    "sg:postcode":"78759",
    "sg:province":"TX",
    "wof:name":"Law Offices of Rebecca S Whitehouse",
    "wof:placetype":"venue"
},
  "geometry": {"coordinates":[-97.75411699999999,30.42133],"type":"Point"}
}