{
  "type": "Feature",
  "properties": {
    "iso:country":"US",
    "sg:address":"4316 Sunbelt Dr",
    "sg:city":"Addison",
    "sg:classifiers":[
        {
            "category":"Banks & Credit Unions",
            "subcategory":"Bank",
            "type":"Services"
        }
    ],
    "sg:phone":"+1 972 741 3948",
    "sg:postcode":"75001",
    "sg:province":"TX",
    "sg:tags":[
        "broker",
        "mortgage"
    ],
    "wof:name":"24 Hour Offer LLC",
    "wof:placetype":"venue"
},
  "geometry": {"coordinates":[-96.83689800000001,32.976911],"type":"Point"}
}