{
  "type": "Feature",
  "properties": {
    "iso:country":"US",
    "sg:address":"1810 9th St",
    "sg:city":"Wichita Falls",
    "sg:classifiers":[
        {
            "category":"Home & Garden",
            "subcategory":"Building Materials",
            "type":"Retail Goods"
        }
    ],
    "sg:phone":"+1 940 322 5201",
    "sg:postcode":"76301",
    "sg:province":"TX",
    "sg:tags":[
        "paint"
    ],
    "wof:name":"AWC Paint & Decorating Ctr",
    "wof:placetype":"venue"
},
  "geometry": {"coordinates":[-98.507947,33.903892],"type":"Point"}
}