{
  "type": "Feature",
  "properties": {
    "iso:country":"US",
    "sg:address":"1609 N 7th St",
    "sg:city":"Mcallen",
    "sg:classifiers":[
        {
            "category":"Real Estate",
            "subcategory":"Architect",
            "type":"Services"
        },
        {
            "category":"Building & Trades",
            "subcategory":"Construction",
            "type":"Services"
        }
    ],
    "sg:phone":"+1 956 664 0428",
    "sg:postcode":"78501",
    "sg:province":"TX",
    "sg:tags":[
        "estimate",
        "general",
        "contractor"
    ],
    "wof:name":"Ricardo Lopez Construction",
    "wof:placetype":"venue"
},
  "geometry": {"coordinates":[-98.224097,26.219164],"type":"Point"}
}