{
  "type": "Feature",
  "properties": {
    "iso:country":"US",
    "sg:address":"102 Avenue E",
    "sg:city":"Hereford",
    "sg:classifiers":[
        {
            "category":"Social Services",
            "type":"Services"
        }
    ],
    "sg:phone":"+1 806 364 7692",
    "sg:postcode":"79045",
    "sg:province":"TX",
    "sg:tags":[
        "organization",
        "welfare"
    ],
    "wof:name":"WIC Hereford",
    "wof:placetype":"venue"
},
  "geometry": {"coordinates":[-102.398026,34.82328],"type":"Point"}
}