{
  "type": "Feature",
  "properties": {
    "iso:country":"US",
    "sg:address":"1428 N Post Oak Rd",
    "sg:city":"Houston",
    "sg:classifiers":[
        {
            "category":"Wholesale",
            "subcategory":"Machinery & Supplies",
            "type":"Manufacturing & Wholesale Goods"
        }
    ],
    "sg:phone":"+1 713 680 9649",
    "sg:postcode":"77055",
    "sg:province":"TX",
    "sg:tags":[
        "equipment",
        "layer",
        "carpet"
    ],
    "wof:name":"C & C Distributors",
    "wof:placetype":"venue"
},
  "geometry": {"coordinates":[-95.457009,29.795425],"type":"Point"}
}