{
  "type": "Feature",
  "properties": {
    "iso:country":"US",
    "sg:address":"114 S Fairview St",
    "sg:city":"Keene",
    "sg:classifiers":[
        {
            "category":"Organizations",
            "subcategory":"Religious Organization",
            "type":"Services"
        }
    ],
    "sg:phone":"+1 817 641 9804",
    "sg:postcode":"76059",
    "sg:province":"TX",
    "sg:tags":[
        "church"
    ],
    "wof:name":"Keene Seventh Day Adventist",
    "wof:placetype":"venue"
},
  "geometry": {"coordinates":[-97.324432,32.394252],"type":"Point"}
}