{
  "type": "Feature",
  "properties": {
    "iso:country":"US",
    "sg:address":"6196 Co Rd 440",
    "sg:city":"Alice",
    "sg:classifiers":[
        {
            "category":"Professional",
            "subcategory":"Business Services",
            "type":"Services"
        }
    ],
    "sg:phone":"+1 361 668 1175",
    "sg:postcode":"78332",
    "sg:province":"TX",
    "wof:name":"Barrientos Enterprises",
    "wof:placetype":"venue"
},
  "geometry": {"coordinates":[-98.189153,27.577068],"type":"Point"}
}