{
  "type": "Feature",
  "properties": {
    "iso:country":"US",
    "sg:address":"3109 E Seminary Dr",
    "sg:city":"Fort Worth",
    "sg:classifiers":[
        {
            "category":"Home & Garden",
            "subcategory":"Furniture",
            "type":"Retail Goods"
        },
        {
            "category":"Home & Garden",
            "subcategory":"Home Furnishings",
            "type":"Retail Goods"
        }
    ],
    "sg:phone":"+1 817 536 5643",
    "sg:postcode":"76119",
    "sg:province":"TX",
    "sg:tags":[
        "bedspread",
        "household"
    ],
    "wof:name":"Super Star Furniture",
    "wof:placetype":"venue"
},
  "geometry": {"coordinates":[-97.282934,32.684902],"type":"Point"}
}