{
  "type": "Feature",
  "properties": {
    "iso:country":"US",
    "sg:address":"4336 N McColl Rd",
    "sg:city":"Mcallen",
    "sg:classifiers":[
        {
            "category":"Health Services",
            "subcategory":"Doctor",
            "type":"Services"
        }
    ],
    "sg:phone":"+1 956 686 5577",
    "sg:postcode":"78504",
    "sg:province":"TX",
    "sg:tags":[
        "dentist"
    ],
    "wof:name":"Jason A Burkett DDS",
    "wof:placetype":"venue"
},
  "geometry": {"coordinates":[-98.20632000000001,26.238535],"type":"Point"}
}