{
  "type": "Feature",
  "properties": {
    "iso:country":"US",
    "sg:address":"337 W Broadview Dr",
    "sg:city":"San Antonio",
    "sg:classifiers":[
        {
            "category":"Freight",
            "type":"Transportation"
        }
    ],
    "sg:phone":"+1 210 413 2034",
    "sg:postcode":"78228",
    "sg:province":"TX",
    "sg:tags":[
        "operator",
        "trucking"
    ],
    "wof:name":"Sureway Transport Svc",
    "wof:placetype":"venue"
},
  "geometry": {"coordinates":[-98.57925899999999,29.4641],"type":"Point"}
}