{
  "type": "Feature",
  "properties": {
    "iso:country":"US",
    "sg:address":"29919 Abilene St",
    "sg:city":"Magnolia",
    "sg:classifiers":[
        {
            "category":"Professional",
            "type":"Services"
        }
    ],
    "sg:phone":"+1 281 252 8343",
    "sg:postcode":"77354",
    "sg:province":"TX",
    "wof:name":"Sunshine Yard Service",
    "wof:placetype":"venue"
},
  "geometry": {"coordinates":[-95.630152,30.183234],"type":"Point"}
}