{
  "type": "Feature",
  "properties": {
    "iso:country":"US",
    "sg:address":"2613 Hilcroft Ave",
    "sg:city":"Denton",
    "sg:classifiers":[
        {
            "category":"Education",
            "subcategory":"Music School",
            "type":"Public Place"
        }
    ],
    "sg:phone":"+1 940 566 0040",
    "sg:postcode":"76210",
    "sg:province":"TX",
    "sg:tags":[
        "instruction-instrumental"
    ],
    "wof:name":"Nancy Clark Assoc",
    "wof:placetype":"venue"
},
  "geometry": {"coordinates":[-97.104961,33.166914],"type":"Point"}
}