{
  "type": "Feature",
  "properties": {
    "iso:country":"US",
    "sg:address":"3900 American Dr",
    "sg:city":"Plano",
    "sg:classifiers":[
        {
            "category":"Professional",
            "subcategory":"Lawyer & Legal Services",
            "type":"Services"
        }
    ],
    "sg:phone":"+1 469 467 0700",
    "sg:postcode":"75075",
    "sg:province":"TX",
    "sg:tags":[
        "attorney"
    ],
    "wof:name":"Nikki Carmondy",
    "wof:placetype":"venue"
},
  "geometry": {"coordinates":[-96.76763699999999,33.02427],"type":"Point"}
}