{
  "type": "Feature",
  "properties": {
    "iso:country":"US",
    "sg:address":"11631 Rolling Stream Dr",
    "sg:city":"Tomball",
    "sg:classifiers":[
        {
            "category":"Restaurant",
            "type":"Food & Drink"
        }
    ],
    "sg:phone":"+1 281 357 5562",
    "sg:postcode":"77375",
    "sg:province":"TX",
    "sg:tags":[
        "eating"
    ],
    "wof:name":"S and J Kettle Korn",
    "wof:placetype":"venue"
},
  "geometry": {"coordinates":[-95.592733,30.044563],"type":"Point"}
}