{
  "type": "Feature",
  "properties": {
    "iso:country":"US",
    "sg:address":"609 Elm St",
    "sg:city":"Graham",
    "sg:classifiers":[
        {
            "category":"Museum",
            "type":"Entertainment"
        }
    ],
    "sg:phone":"+1 940 549 0401",
    "sg:postcode":"76450",
    "sg:province":"TX",
    "sg:tags":[
        "gallery"
    ],
    "wof:name":"Main Street Graham Inc",
    "wof:placetype":"venue"
},
  "geometry": {"coordinates":[-98.589488,33.105797],"type":"Point"}
}