{
  "type": "Feature",
  "properties": {
    "iso:country":"US",
    "sg:address":"1003 Wirt Rd",
    "sg:city":"Houston",
    "sg:classifiers":[
        {
            "category":"Personal",
            "type":"Services"
        }
    ],
    "sg:phone":"+1 713 465 3304",
    "sg:postcode":"77055",
    "sg:province":"TX",
    "sg:tags":[
        "organization",
        "consumer"
    ],
    "wof:name":"Consumer Counseling",
    "wof:placetype":"venue"
},
  "geometry": {"coordinates":[-95.484897,29.785263],"type":"Point"}
}