{
  "type": "Feature",
  "properties": {
    "iso:country":"US",
    "sg:address":"1411 E Campbell Rd",
    "sg:city":"Richardson",
    "sg:classifiers":[
        {
            "category":"Wholesale",
            "subcategory":"Durable Goods & Equipment",
            "type":"Manufacturing & Wholesale Goods"
        }
    ],
    "sg:phone":"+1 972 235 3834",
    "sg:postcode":"75081",
    "sg:province":"TX",
    "sg:tags":[
        "importer"
    ],
    "wof:name":"Misa Imports Inc",
    "wof:placetype":"venue"
},
  "geometry": {"coordinates":[-96.69805700000001,32.97471],"type":"Point"}
}