{
  "type": "Feature",
  "properties": {
    "iso:country":"US",
    "sg:address":"1135 State Hwy 173",
    "sg:city":"Bandera",
    "sg:classifiers":[
        {
            "category":"Manufacturing",
            "subcategory":"Furniture",
            "type":"Manufacturing & Wholesale Goods"
        }
    ],
    "sg:phone":"+1 830 796 4696",
    "sg:postcode":"78003",
    "sg:province":"TX",
    "sg:tags":[
        "fixture",
        "store"
    ],
    "wof:name":"Hearn Products Inc",
    "wof:placetype":"venue"
},
  "geometry": {"coordinates":[-99.059343,29.697878],"type":"Point"}
}