{
  "type": "Feature",
  "properties": {
    "iso:country":"US",
    "sg:address":"2276 Des Jardines St",
    "sg:city":"Houston",
    "sg:classifiers":[
        {
            "category":"Building & Trades",
            "subcategory":"Landscaping Services",
            "type":"Services"
        }
    ],
    "sg:phone":"+1 713 923 1432",
    "sg:postcode":"77023",
    "sg:province":"TX",
    "wof:name":"Charles Welch Lawn Ser",
    "wof:placetype":"venue"
},
  "geometry": {"coordinates":[-95.32640499999999,29.715432],"type":"Point"}
}