{
  "type": "Feature",
  "properties": {
    "iso:country":"US",
    "sg:address":"6110 Bullard Dr",
    "sg:city":"Austin",
    "sg:classifiers":[
        {
            "category":"Social Services",
            "subcategory":"Adult Care",
            "type":"Services"
        }
    ],
    "sg:phone":"+1 512 451 5801",
    "sg:postcode":"78757",
    "sg:province":"TX",
    "sg:tags":[
        "retardation",
        "home",
        "dev",
        "disabled"
    ],
    "wof:name":"Allendale House",
    "wof:placetype":"venue"
},
  "geometry": {"coordinates":[-97.751606,30.343093],"type":"Point"}
}