{
  "type": "Feature",
  "properties": {
    "iso:country":"US",
    "sg:address":"1420 US Hwy 271",
    "sg:city":"Gilmer",
    "sg:classifiers":[
        {
            "category":"Personal",
            "subcategory":"Beauty Salon",
            "type":"Services"
        }
    ],
    "sg:phone":"+1 903 797 2888",
    "sg:postcode":"75644",
    "sg:province":"TX",
    "sg:tags":[
        "shop"
    ],
    "wof:name":"Merle Norman Cosmetics",
    "wof:placetype":"venue"
},
  "geometry": {"coordinates":[-94.941591,32.742401],"type":"Point"}
}