{
  "type": "Feature",
  "properties": {
    "iso:country":"US",
    "sg:address":"325 S Cowan Ave",
    "sg:city":"Lewisville",
    "sg:classifiers":[
        {
            "category":"Organizations",
            "subcategory":"Religious Organization",
            "type":"Services"
        }
    ],
    "sg:phone":"+1 972 436 1358",
    "sg:postcode":"75057",
    "sg:province":"TX",
    "sg:tags":[
        "church"
    ],
    "sg:website":"www.centralbaptistchurchlewisville.org",
    "wof:name":"Central Baptist Church",
    "wof:placetype":"venue"
},
  "geometry": {"coordinates":[-97.001465,33.044011],"type":"Point"}
}