{
  "type": "Feature",
  "properties": {
    "iso:country":"US",
    "sg:address":"305 E Park Ln",
    "sg:city":"Brownfield",
    "sg:classifiers":[
        {
            "category":"Shopping",
            "subcategory":"Clothing, Apparel, & Fashions",
            "type":"Retail Goods"
        }
    ],
    "sg:phone":"+1 806 637 3908",
    "sg:postcode":"79316",
    "sg:province":"TX",
    "wof:name":"Romelia Contreras",
    "wof:placetype":"venue"
},
  "geometry": {"coordinates":[-102.27384499999999,33.194337],"type":"Point"}
}