{
  "type": "Feature",
  "properties": {
    "iso:country":"US",
    "sg:address":"105 N Alexander Dr",
    "sg:city":"Baytown",
    "sg:classifiers":[
        {
            "category":"Shopping",
            "type":"Retail Goods"
        }
    ],
    "sg:phone":"+1 281 428 3335",
    "sg:postcode":"77520",
    "sg:province":"TX",
    "sg:tags":[
        "eating",
        "merchandise"
    ],
    "wof:name":"Nios Trinidad Roti Shop & Wes",
    "wof:placetype":"venue"
},
  "geometry": {"coordinates":[-94.95848599999999,29.729617],"type":"Point"}
}