{
  "type": "Feature",
  "properties": {
    "iso:country":"US",
    "sg:address":"3128 Touraine Dr",
    "sg:city":"Dallas",
    "sg:classifiers":[
        {
            "category":"Shopping",
            "subcategory":"Hobbies, Toys, & Games",
            "type":"Retail Goods"
        }
    ],
    "sg:phone":"+1 214 339 4531",
    "sg:postcode":"75211",
    "sg:province":"TX",
    "wof:name":"Crafts & Gifts",
    "wof:placetype":"venue"
},
  "geometry": {"coordinates":[-96.869141,32.760595],"type":"Point"}
}