{
  "type": "Feature",
  "properties": {
    "iso:country":"US",
    "sg:address":"1502 Hunter Green Ln",
    "sg:city":"Fresno",
    "sg:classifiers":[
        {
            "category":"Shopping",
            "subcategory":"Jewelry",
            "type":"Retail Goods"
        }
    ],
    "sg:phone":"+1 281 431 0540",
    "sg:postcode":"77545",
    "sg:province":"TX",
    "sg:tags":[
        "jeweler"
    ],
    "wof:name":"A Silver Lining",
    "wof:placetype":"venue"
},
  "geometry": {"coordinates":[-95.474175,29.520438],"type":"Point"}
}