{
  "type": "Feature",
  "properties": {
    "iso:country":"US",
    "sg:address":"306 Westpark Dr N",
    "sg:city":"Mc Kinney",
    "sg:classifiers":[
        {
            "category":"Professional",
            "subcategory":"Management & Consulting",
            "type":"Services"
        }
    ],
    "sg:phone":"+1 972 548 0509",
    "sg:postcode":"75071",
    "sg:province":"TX",
    "wof:name":"Rpmccoy & Assoc",
    "wof:placetype":"venue"
},
  "geometry": {"coordinates":[-96.640692,33.201296],"type":"Point"}
}