{
  "type": "Feature",
  "properties": {
    "iso:country":"US",
    "sg:address":"14045 Fm 2100 Rd Ste 300",
    "sg:city":"Crosby",
    "sg:classifiers":[
        {
            "category":"Banks & Credit Unions",
            "subcategory":"Bank",
            "type":"Services"
        }
    ],
    "sg:phone":"+1 713 495 8115",
    "sg:postcode":"77532",
    "sg:province":"TX",
    "sg:tags":[
        "saving",
        "commercial"
    ],
    "wof:name":"Woodforest National Bank Missing Level",
    "wof:placetype":"venue"
},
  "geometry": {"coordinates":[-95.063316,29.890908],"type":"Point"}
}