{
  "type": "Feature",
  "properties": {
    "iso:country":"US",
    "sg:address":"1714 Deerfield Dr",
    "sg:city":"Austin",
    "sg:classifiers":[
        {
            "category":"Professional",
            "subcategory":"Business Services",
            "type":"Services"
        }
    ],
    "sg:phone":"+1 512 447 7520",
    "sg:postcode":"78741",
    "sg:province":"TX",
    "wof:name":"Perez & Cervantes",
    "wof:placetype":"venue"
},
  "geometry": {"coordinates":[-97.735422,30.23846],"type":"Point"}
}