{
  "type": "Feature",
  "properties": {
    "iso:country":"US",
    "sg:address":"98 Co Rd 131",
    "sg:city":"Edna",
    "sg:classifiers":[
        {
            "category":"Professional",
            "type":"Services"
        }
    ],
    "sg:phone":"+1 361 781 0333",
    "sg:postcode":"77957",
    "sg:province":"TX",
    "wof:name":"D C M Technical Services",
    "wof:placetype":"venue"
},
  "geometry": {"coordinates":[-96.668099,29.032601],"type":"Point"}
}