{
  "type": "Feature",
  "properties": {
    "iso:country":"US",
    "sg:address":"301 N Pearson St",
    "sg:city":"Godley",
    "sg:classifiers":[
        {
            "category":"Organizations",
            "subcategory":"Religious Organization",
            "type":"Services"
        }
    ],
    "sg:phone":"+1 830 665 2721",
    "sg:postcode":"76044",
    "sg:province":"TX",
    "sg:tags":[
        "church"
    ],
    "sg:website":"www.devtex.net",
    "wof:name":"First Baptist Church NATALIA",
    "wof:placetype":"venue"
},
  "geometry": {"coordinates":[-97.52942899999999,32.453333],"type":"Point"}
}