{
  "type": "Feature",
  "properties": {
    "iso:country":"US",
    "sg:address":"218 W Little York Rd",
    "sg:city":"Houston",
    "sg:classifiers":[
        {
            "category":"Building & Trades",
            "subcategory":"Construction",
            "type":"Services"
        }
    ],
    "sg:phone":"+1 713 692 5756",
    "sg:postcode":"77076",
    "sg:province":"TX",
    "sg:tags":[
        "window",
        "tinting"
    ],
    "wof:name":"Solar Pro Tint",
    "wof:placetype":"venue"
},
  "geometry": {"coordinates":[-95.401689,29.869942],"type":"Point"}
}