{
  "type": "Feature",
  "properties": {
    "iso:country":"US",
    "sg:address":"100 W 8th St",
    "sg:city":"Tyler",
    "sg:classifiers":[
        {
            "category":"Shopping",
            "subcategory":"Used Merchandise",
            "type":"Retail Goods"
        }
    ],
    "sg:phone":"+1 903 592 4541",
    "sg:postcode":"75701",
    "sg:province":"TX",
    "sg:tags":[
        "sewing"
    ],
    "wof:name":"London Shop The",
    "wof:placetype":"venue"
},
  "geometry": {"coordinates":[-95.302717,32.328043],"type":"Point"}
}