{
  "type": "Feature",
  "properties": {
    "iso:country":"US",
    "sg:address":"601 Chestnut St",
    "sg:city":"Bastrop",
    "sg:classifiers":[
        {
            "category":"Restaurant",
            "type":"Food & Drink"
        }
    ],
    "sg:phone":"+1 512 321 2545",
    "sg:postcode":"78602",
    "sg:province":"TX",
    "sg:tags":[
        "eating"
    ],
    "wof:name":"Yacht Club",
    "wof:placetype":"venue"
},
  "geometry": {"coordinates":[-97.320002,30.110552],"type":"Point"}
}