{
  "type": "Feature",
  "properties": {
    "iso:country":"US",
    "sg:address":"965 N Resler Ste 105",
    "sg:city":"El Paso",
    "sg:classifiers":[
        {
            "category":"Health Services",
            "subcategory":"Dentist",
            "type":"Services"
        }
    ],
    "sg:phone":"+1 915 585 2020",
    "sg:postcode":"79912",
    "sg:province":"TX",
    "sg:tags":[
        "pediatric"
    ],
    "wof:name":"Mollere Rod, DDS",
    "wof:placetype":"venue"
},
  "geometry": {"coordinates":[-106.55801099999999,31.862134],"type":"Point"}
}