{
  "type": "Feature",
  "properties": {
    "iso:country":"US",
    "sg:address":"2412 Sunset St",
    "sg:city":"Denison",
    "sg:classifiers":[
        {
            "category":"Retail",
            "subcategory":"Auto Repair",
            "type":"Services"
        }
    ],
    "sg:phone":"+1 903 465 1101",
    "sg:postcode":"75020",
    "sg:province":"TX",
    "sg:tags":[
        "truck"
    ],
    "wof:name":"3G Precision Truck Repair",
    "wof:placetype":"venue"
},
  "geometry": {"coordinates":[-96.572667,33.73964],"type":"Point"}
}