{
  "type": "Feature",
  "properties": {
    "iso:country":"US",
    "sg:address":"688 Canyon Springs Dr",
    "sg:city":"Canyon Lake",
    "sg:classifiers":[
        {
            "category":"Building & Trades",
            "subcategory":"Construction",
            "type":"Services"
        }
    ],
    "sg:phone":"+1 830 899 4594",
    "sg:postcode":"78133",
    "sg:province":"TX",
    "sg:tags":[
        "house",
        "general",
        "contractor"
    ],
    "wof:name":"Peter Varhol Construction",
    "wof:placetype":"venue"
},
  "geometry": {"coordinates":[-98.287549,29.8731],"type":"Point"}
}