{
  "type": "Feature",
  "properties": {
    "iso:country":"US",
    "sg:address":"104 Padre Blvd",
    "sg:city":"South Padre Island",
    "sg:classifiers":[
        {
            "category":"Shopping",
            "subcategory":"Clothing, Apparel, & Fashions",
            "type":"Retail Goods"
        }
    ],
    "sg:phone":"+1 956 761 7222",
    "sg:postcode":"78597",
    "sg:province":"TX",
    "sg:tags":[
        "custom",
        "t",
        "printed"
    ],
    "wof:name":"Jamaica On The Bay",
    "wof:placetype":"venue"
},
  "geometry": {"coordinates":[-97.16055299999999,26.074295],"type":"Point"}
}