{
  "type": "Feature",
  "properties": {
    "iso:country":"US",
    "sg:address":"1315 N Elmendorf St",
    "sg:city":"San Antonio",
    "sg:classifiers":[
        {
            "category":"Government",
            "subcategory":"Court House",
            "type":"Public Place"
        }
    ],
    "sg:phone":"+1 210 736 4327",
    "sg:postcode":"78207",
    "sg:province":"TX",
    "sg:tags":[
        "city"
    ],
    "wof:name":"Lincoln Heights Courts",
    "wof:placetype":"venue"
},
  "geometry": {"coordinates":[-98.52767,29.441937],"type":"Point"}
}