{
  "type": "Feature",
  "properties": {
    "iso:country":"US",
    "sg:address":"1714 Spann St",
    "sg:city":"Dallas",
    "sg:classifiers":[
        {
            "category":"Retail",
            "subcategory":"Laundry & Dry Cleaning",
            "type":"Services"
        }
    ],
    "sg:phone":"+1 214 948 7330",
    "sg:postcode":"75203",
    "sg:province":"TX",
    "wof:name":"Dry Cleaning Shops of America",
    "wof:placetype":"venue"
},
  "geometry": {"coordinates":[-96.821404,32.765099],"type":"Point"}
}