{
  "type": "Feature",
  "properties": {
    "iso:country":"US",
    "sg:address":"122 Chachalaca Dr",
    "sg:city":"Los Fresnos",
    "sg:classifiers":[
        {
            "category":"Building & Trades",
            "subcategory":"Construction",
            "type":"Services"
        }
    ],
    "sg:phone":"+1 956 233 5455",
    "sg:postcode":"78566",
    "sg:province":"TX",
    "wof:name":"Coastal Contractors",
    "wof:placetype":"venue"
},
  "geometry": {"coordinates":[-97.395556,26.132844],"type":"Point"}
}