{
  "type": "Feature",
  "properties": {
    "iso:country":"US",
    "sg:address":"7975 Bellfort St",
    "sg:city":"Houston",
    "sg:classifiers":[
        {
            "category":"Food & Beverages",
            "subcategory":"Groceries & Convenience Stores",
            "type":"Retail Goods"
        }
    ],
    "sg:phone":"+1 713 643 0403",
    "sg:postcode":"77061",
    "sg:province":"TX",
    "wof:name":"Pyramid Treasures",
    "wof:placetype":"venue"
},
  "geometry": {"coordinates":[-95.269659,29.674364],"type":"Point"}
}