{
  "type": "Feature",
  "properties": {
    "iso:country":"US",
    "sg:address":"902 Clearview Dr",
    "sg:city":"San Antonio",
    "sg:classifiers":[
        {
            "category":"Insurance",
            "subcategory":"Insurance Agent",
            "type":"Services"
        }
    ],
    "sg:phone":"+1 210 680 9864",
    "sg:postcode":"78228",
    "sg:province":"TX",
    "wof:name":"Moreno G B & Assoc",
    "wof:placetype":"venue"
},
  "geometry": {"coordinates":[-98.584706,29.482292],"type":"Point"}
}