{
  "type": "Feature",
  "properties": {
    "iso:country":"US",
    "sg:address":"15035 Four Winds Dr",
    "sg:city":"Missouri City",
    "sg:classifiers":[
        {
            "category":"Freight",
            "type":"Transportation"
        }
    ],
    "sg:phone":"+1 281 416 8043",
    "sg:postcode":"77489",
    "sg:province":"TX",
    "sg:tags":[
        "operator",
        "trucking"
    ],
    "wof:name":"Ballistic Express LLC",
    "wof:placetype":"venue"
},
  "geometry": {"coordinates":[-95.492366,29.609122],"type":"Point"}
}