{
  "type": "Feature",
  "properties": {
    "iso:country":"US",
    "sg:address":"6355 Lamar Rd",
    "sg:city":"Reno",
    "sg:classifiers":[
        {
            "category":"Professional",
            "subcategory":"Engineering",
            "type":"Services"
        }
    ],
    "sg:phone":"+1 903 783 9995",
    "sg:postcode":"75462",
    "sg:province":"TX",
    "sg:tags":[
        "engineer"
    ],
    "wof:name":"Five G Consulting",
    "wof:placetype":"venue"
},
  "geometry": {"coordinates":[-95.46314700000001,33.663397],"type":"Point"}
}