{
  "type": "Feature",
  "properties": {
    "iso:country":"US",
    "sg:address":"1010 Lamar St",
    "sg:city":"Houston",
    "sg:classifiers":[
        {
            "category":"Shopping",
            "subcategory":"Computers & Home Electronics",
            "type":"Retail Goods"
        }
    ],
    "sg:phone":"+1 713 652 4066",
    "sg:postcode":"77002",
    "sg:province":"TX",
    "sg:tags":[
        "software"
    ],
    "wof:name":"Logical Information Machines",
    "wof:placetype":"venue"
},
  "geometry": {"coordinates":[-95.36475799999999,29.755681],"type":"Point"}
}