{
  "type": "Feature",
  "properties": {
    "iso:country":"US",
    "sg:address":"4242 Woodcock Dr",
    "sg:city":"San Antonio",
    "sg:classifiers":[
        {
            "category":"Professional",
            "subcategory":"Accounting & Tax Preparation",
            "type":"Services"
        }
    ],
    "sg:phone":"+1 210 525 8747",
    "sg:postcode":"78228",
    "sg:province":"TX",
    "sg:tags":[
        "return",
        "filing"
    ],
    "wof:name":"Transamerica Real Estate Tax",
    "wof:placetype":"venue"
},
  "geometry": {"coordinates":[-98.570778,29.48723],"type":"Point"}
}