{
  "type": "Feature",
  "properties": {
    "iso:country":"US",
    "sg:address":"1803 Beechaven Dr",
    "sg:city":"San Antonio",
    "sg:classifiers":[
        {
            "category":"Retail",
            "subcategory":"Repair Shop",
            "type":"Services"
        }
    ],
    "sg:phone":"+1 210 227 7106",
    "sg:postcode":"78207",
    "sg:province":"TX",
    "sg:tags":[
        "equipment",
        "refrigeration",
        "conditioning",
        "air"
    ],
    "wof:name":"Henrys Air Conditioning Sup Co",
    "wof:placetype":"venue"
},
  "geometry": {"coordinates":[-98.53185000000001,29.406223],"type":"Point"}
}