{
  "type": "Feature",
  "properties": {
    "iso:country":"US",
    "sg:address":"419 W Ave C",
    "sg:city":"San Angelo",
    "sg:classifiers":[
        {
            "category":"Professional",
            "type":"Services"
        }
    ],
    "sg:phone":"+1 325 658 7095",
    "sg:postcode":"76903",
    "sg:province":"TX",
    "sg:tags":[
        "establishment"
    ],
    "wof:name":"Spectrtech",
    "wof:placetype":"venue"
},
  "geometry": {"coordinates":[-100.44189,31.454301],"type":"Point"}
}