{
  "type": "Feature",
  "properties": {
    "iso:country":"US",
    "sg:address":"1921 Austin Ave",
    "sg:city":"Waco",
    "sg:classifiers":[
        {
            "category":"Professional",
            "subcategory":"Lawyer & Legal Services",
            "type":"Services"
        }
    ],
    "sg:phone":"+1 254 754 5458",
    "sg:postcode":"76701",
    "sg:province":"TX",
    "sg:tags":[
        "attorney"
    ],
    "wof:name":"Lanelle Mc Namara PC",
    "wof:placetype":"venue"
},
  "geometry": {"coordinates":[-97.144071,31.546148],"type":"Point"}
}