{
  "type": "Feature",
  "properties": {
    "iso:country":"US",
    "sg:address":"9015 Winkler Dr",
    "sg:city":"Houston",
    "sg:classifiers":[
        {
            "category":"Animal Shelter",
            "type":"Public Place"
        }
    ],
    "sg:phone":"+1 713 799 1300",
    "sg:postcode":"77017",
    "sg:province":"TX",
    "sg:tags":[
        "adult"
    ],
    "wof:name":"Carmen's Boutique",
    "wof:placetype":"venue"
},
  "geometry": {"coordinates":[-95.255199,29.670485],"type":"Point"}
}