{
  "type": "Feature",
  "properties": {
    "iso:country":"US",
    "sg:address":"18215 Center St",
    "sg:city":"Jonestown",
    "sg:classifiers":[
        {
            "category":"Restaurant",
            "type":"Food & Drink"
        }
    ],
    "sg:phone":"+1 512 267 5859",
    "sg:postcode":"78645",
    "sg:province":"TX",
    "wof:name":"Pizza Guy",
    "wof:placetype":"venue"
},
  "geometry": {"coordinates":[-97.91666499999999,30.498208],"type":"Point"}
}