{
  "type": "Feature",
  "properties": {
    "iso:country":"US",
    "sg:address":"207 S Denton St",
    "sg:city":"Mexia",
    "sg:classifiers":[
        {
            "category":"Organizations",
            "subcategory":"Religious Organization",
            "type":"Services"
        }
    ],
    "sg:phone":"+1 254 562 2612",
    "sg:postcode":"76667",
    "sg:province":"TX",
    "sg:tags":[
        "churches-baptist",
        "church"
    ],
    "wof:name":"Union Baptist Church",
    "wof:placetype":"venue"
},
  "geometry": {"coordinates":[-96.489773,31.679246],"type":"Point"}
}