{
  "type": "Feature",
  "properties": {
    "iso:country":"US",
    "sg:address":"3605 Co Rd 152 W",
    "sg:city":"Bullard",
    "sg:classifiers":[
        {
            "category":"Wholesale",
            "subcategory":"Machinery & Supplies",
            "type":"Manufacturing & Wholesale Goods"
        }
    ],
    "sg:phone":"+1 903 894 7273",
    "sg:postcode":"75703",
    "sg:province":"TX",
    "wof:name":"Unique Sales & Products",
    "wof:placetype":"venue"
},
  "geometry": {"coordinates":[-95.322332,32.169826],"type":"Point"}
}