{
  "type": "Feature",
  "properties": {
    "iso:country":"US",
    "sg:address":"6188 Galloway Ln",
    "sg:city":"League City",
    "sg:classifiers":[
        {
            "category":"Personal",
            "type":"Services"
        }
    ],
    "sg:phone":"+1 281 316 5962",
    "sg:postcode":"77573",
    "sg:province":"TX",
    "sg:tags":[
        "planning",
        "management",
        "event"
    ],
    "wof:name":"Christopher & Co",
    "wof:placetype":"venue"
},
  "geometry": {"coordinates":[-95.161536,29.478661],"type":"Point"}
}