{
  "type": "Feature",
  "properties": {
    "iso:country":"US",
    "sg:address":"1437 Pine Bluff Dr",
    "sg:city":"Allen",
    "sg:classifiers":[
        {
            "category":"Shopping",
            "subcategory":"Computers & Home Electronics",
            "type":"Retail Goods"
        }
    ],
    "sg:phone":"+1 214 547 8865",
    "sg:postcode":"75002",
    "sg:province":"TX",
    "sg:tags":[
        "equipment",
        "dealer"
    ],
    "wof:name":"GHA Technologies",
    "wof:placetype":"venue"
},
  "geometry": {"coordinates":[-96.634265,33.091009],"type":"Point"}
}