{
  "type": "Feature",
  "properties": {
    "iso:country":"US",
    "sg:address":"2001 North Ave",
    "sg:city":"Donna",
    "sg:classifiers":[
        {
            "category":"Shopping",
            "subcategory":"Gifts & Souvenirs",
            "type":"Retail Goods"
        }
    ],
    "sg:phone":"+1 956 464 3635",
    "sg:postcode":"78537",
    "sg:province":"TX",
    "sg:tags":[
        "novelty"
    ],
    "wof:name":"Camilles",
    "wof:placetype":"venue"
},
  "geometry": {"coordinates":[-98.041293,26.178597],"type":"Point"}
}