{
  "type": "Feature",
  "properties": {
    "iso:country":"US",
    "sg:address":"701 J A Brooks",
    "sg:city":"Teague",
    "sg:classifiers":[
        {
            "category":"Professional",
            "type":"Services"
        }
    ],
    "sg:phone":"+1 254 739 5548",
    "sg:postcode":"75860",
    "sg:province":"TX",
    "wof:name":"Willie J Keener Jr",
    "wof:placetype":"venue"
},
  "geometry": {"coordinates":[-96.28702699999999,31.621235],"type":"Point"}
}