{
  "type": "Feature",
  "properties": {
    "iso:country":"US",
    "sg:address":"3103 Lantern Bay Ln",
    "sg:city":"Katy",
    "sg:classifiers":[
        {
            "category":"Retail",
            "subcategory":"Laundry & Dry Cleaning",
            "type":"Services"
        },
        {
            "category":"Building & Trades",
            "subcategory":"Cleaning & Sanitation",
            "type":"Services"
        }
    ],
    "sg:phone":"+1 281 398 7111",
    "sg:postcode":"77449",
    "sg:province":"TX",
    "sg:tags":[
        "cleaner",
        "upholstery",
        "fabric",
        "floor",
        "duct",
        "rug",
        "air",
        "waxing",
        "protection",
        "polishing",
        "furniture",
        "carpet"
    ],
    "sg:website":"http://www.affordablecarpetclean.net",
    "wof:name":"Affordable Carpet & Upholstery",
    "wof:placetype":"venue"
},
  "geometry": {"coordinates":[-95.746983,29.821734],"type":"Point"}
}