{
  "type": "Feature",
  "properties": {
    "iso:country":"US",
    "sg:address":"400 Jefferson St",
    "sg:city":"Kerrville",
    "sg:classifiers":[
        {
            "category":"Retail",
            "subcategory":"Auto Repair",
            "type":"Services"
        }
    ],
    "sg:phone":"+1 830 792 4300",
    "sg:postcode":"78028",
    "sg:province":"TX",
    "sg:tags":[
        "muffler",
        "exhaust",
        "system"
    ],
    "wof:name":"American Muffler & Brake",
    "wof:placetype":"venue"
},
  "geometry": {"coordinates":[-99.14267599999999,30.051212],"type":"Point"}
}