{
  "type": "Feature",
  "properties": {
    "iso:country":"US",
    "sg:address":"2201 Westlake Dr",
    "sg:city":"Austin",
    "sg:classifiers":[
        {
            "category":"Real Estate",
            "subcategory":"Real Estate Services",
            "type":"Services"
        }
    ],
    "sg:phone":"+1 512 327 1888",
    "sg:postcode":"78746",
    "sg:province":"TX",
    "sg:tags":[
        "vacancy",
        "rental",
        "listing"
    ],
    "wof:name":"Texas Beach Rentals Co",
    "wof:placetype":"venue"
},
  "geometry": {"coordinates":[-97.78724699999999,30.30372],"type":"Point"}
}