{
  "type": "Feature",
  "properties": {
    "iso:country":"US",
    "sg:address":"2207 N MacGregor Way",
    "sg:city":"Houston",
    "sg:classifiers":[
        {
            "category":"Real Estate",
            "subcategory":"Architect",
            "type":"Services"
        }
    ],
    "sg:phone":"+1 713 524 9524",
    "sg:postcode":"77004",
    "sg:province":"TX",
    "wof:name":"Rpm Design Group",
    "wof:placetype":"venue"
},
  "geometry": {"coordinates":[-95.379997,29.716299],"type":"Point"}
}