{
  "type": "Feature",
  "properties": {
    "iso:country":"US",
    "sg:address":"1209 Crescent Dr",
    "sg:city":"Andrews",
    "sg:classifiers":[
        {
            "category":"Professional",
            "type":"Services"
        }
    ],
    "sg:phone":"+1 432 523 7254",
    "sg:postcode":"79714",
    "sg:province":"TX",
    "sg:tags":[
        "establishment"
    ],
    "wof:name":"Nazarene Parsonage",
    "wof:placetype":"venue"
},
  "geometry": {"coordinates":[-102.536404,32.335341],"type":"Point"}
}