{
  "type": "Feature",
  "properties": {
    "iso:country":"US",
    "sg:address":"8500 Bluffstone Cove",
    "sg:city":"Austin",
    "sg:classifiers":[
        {
            "category":"Professional",
            "subcategory":"Engineering",
            "type":"Services"
        }
    ],
    "sg:phone":"+1 512 338 1101",
    "sg:postcode":"78759",
    "sg:province":"TX",
    "sg:tags":[
        "engineer"
    ],
    "sg:website":"www.encotechengineering.com",
    "wof:name":"Encotech Engineering Cnsltnts",
    "wof:placetype":"venue"
},
  "geometry": {"coordinates":[-97.76676500000001,30.387953],"type":"Point"}
}