{
  "type": "Feature",
  "properties": {
    "iso:country":"US",
    "sg:address":"6706 Pebble Beach Dr",
    "sg:city":"Houston",
    "sg:classifiers":[
        {
            "category":"Retail",
            "subcategory":"Repair Shop",
            "type":"Services"
        }
    ],
    "sg:phone":"+1 281 444 5055",
    "sg:postcode":"77069",
    "sg:province":"TX",
    "sg:tags":[
        "refrigeration"
    ],
    "wof:name":"John Hemmat Technical Services",
    "wof:placetype":"venue"
},
  "geometry": {"coordinates":[-95.532293,29.974139],"type":"Point"}
}