{
  "type": "Feature",
  "properties": {
    "iso:country":"US",
    "sg:address":"10524 Harry Hines Blvd",
    "sg:city":"Dallas",
    "sg:classifiers":[
        {
            "category":"Shopping",
            "subcategory":"Clothing, Apparel, & Fashions",
            "type":"Retail Goods"
        }
    ],
    "sg:phone":"+1 214 351 6160",
    "sg:postcode":"75220",
    "sg:province":"TX",
    "sg:tags":[
        "clothing",
        "women's"
    ],
    "sg:website":"www.hugosimports.net",
    "wof:name":"Hugo's Imports",
    "wof:placetype":"venue"
},
  "geometry": {"coordinates":[-96.882401,32.8689],"type":"Point"}
}