{
  "type": "Feature",
  "properties": {
    "iso:country":"US",
    "sg:address":"1720 Northwest Hwy",
    "sg:city":"Garland",
    "sg:classifiers":[
        {
            "category":"Real Estate",
            "subcategory":"Real Estate Services",
            "type":"Services"
        }
    ],
    "sg:phone":"+1 214 352 0490",
    "sg:postcode":"75041",
    "sg:province":"TX",
    "sg:tags":[
        "management",
        "property"
    ],
    "wof:name":"American Management",
    "wof:placetype":"venue"
},
  "geometry": {"coordinates":[-96.65389999999999,32.863998],"type":"Point"}
}