{
  "type": "Feature",
  "properties": {
    "iso:country":"US",
    "sg:address":"6205 Brookhill Dr",
    "sg:city":"Houston",
    "sg:classifiers":[
        {
            "category":"Wholesale",
            "subcategory":"Non-durable Goods",
            "type":"Manufacturing & Wholesale Goods"
        },
        {
            "category":"Manufacturing",
            "subcategory":"Printing",
            "type":"Manufacturing & Wholesale Goods"
        }
    ],
    "sg:phone":"+1 713 645 7693",
    "sg:postcode":"77087",
    "sg:province":"TX",
    "sg:tags":[
        "screen",
        "design",
        "advertising",
        "graphics"
    ],
    "wof:name":"Ad Power",
    "wof:placetype":"venue"
},
  "geometry": {"coordinates":[-95.31903699999999,29.699006],"type":"Point"}
}