{
  "type": "Feature",
  "properties": {
    "iso:country":"US",
    "sg:address":"3653 Briargrove Ln",
    "sg:city":"Dallas",
    "sg:classifiers":[
        {
            "category":"Banks & Credit Unions",
            "subcategory":"Financial Services",
            "type":"Services"
        }
    ],
    "sg:phone":"+1 214 325 0630",
    "sg:postcode":"75287",
    "sg:province":"TX",
    "sg:tags":[
        "investment",
        "real estate"
    ],
    "wof:name":"Ebaty Investments",
    "wof:placetype":"venue"
},
  "geometry": {"coordinates":[-96.850205,32.993323],"type":"Point"}
}