{
  "type": "Feature",
  "properties": {
    "iso:country":"US",
    "sg:address":"2322 Franklin Dr",
    "sg:city":"Fort Worth",
    "sg:classifiers":[
        {
            "category":"Real Estate",
            "subcategory":"Real Estate Agent",
            "type":"Services"
        }
    ],
    "sg:phone":"+1 817 625 9698",
    "sg:postcode":"76106",
    "sg:province":"TX",
    "wof:name":"Jagee Real Properties",
    "wof:placetype":"venue"
},
  "geometry": {"coordinates":[-97.328113,32.8259],"type":"Point"}
}