{
  "type": "Feature",
  "properties": {
    "iso:country":"US",
    "sg:address":"305 E Saint Elmo Rd Ste 1",
    "sg:city":"Austin",
    "sg:classifiers":[
        {
            "category":"Retail",
            "subcategory":"Auto Repair",
            "type":"Services"
        }
    ],
    "sg:phone":"+1 512 636 3176",
    "sg:postcode":"78745",
    "sg:province":"TX",
    "wof:name":"Gary Grizzle Auto Parts",
    "wof:placetype":"venue"
},
  "geometry": {"coordinates":[-97.764296,30.216134],"type":"Point"}
}