{
  "type": "Feature",
  "properties": {
    "iso:country":"US",
    "sg:address":"2609 S Co Rd 1257",
    "sg:city":"Midland",
    "sg:classifiers":[
        {
            "category":"Wholesale",
            "subcategory":"Hardware",
            "type":"Manufacturing & Wholesale Goods"
        }
    ],
    "sg:phone":"+1 432 561 8705",
    "sg:postcode":"79706",
    "sg:province":"TX",
    "sg:tags":[
        "builder"
    ],
    "wof:name":"Hallgren Co",
    "wof:placetype":"venue"
},
  "geometry": {"coordinates":[-102.180178,31.944933],"type":"Point"}
}