{
  "type": "Feature",
  "properties": {
    "iso:country":"US",
    "sg:address":"1500 Norwood Dr",
    "sg:city":"Hurst",
    "sg:classifiers":[
        {
            "category":"Banks & Credit Unions",
            "subcategory":"Bank",
            "type":"Services"
        }
    ],
    "sg:phone":"+1 817 280 0062",
    "sg:postcode":"76054",
    "sg:province":"TX",
    "sg:tags":[
        "loan",
        "real estate"
    ],
    "wof:name":"CSI Residential Lending",
    "wof:placetype":"venue"
},
  "geometry": {"coordinates":[-97.16769499999999,32.841999],"type":"Point"}
}