{
  "type": "Feature",
  "properties": {
    "iso:country":"US",
    "sg:address":"5022 Bay St",
    "sg:city":"Groves",
    "sg:classifiers":[
        {
            "category":"Organizations",
            "subcategory":"Community Association",
            "type":"Services"
        }
    ],
    "sg:phone":"+1 409 962 7997",
    "sg:postcode":"77619",
    "sg:province":"TX",
    "wof:name":"International Assoc of LI",
    "wof:placetype":"venue"
},
  "geometry": {"coordinates":[-93.920902,29.929179],"type":"Point"}
}