{
  "type": "Feature",
  "properties": {
    "iso:country":"US",
    "sg:address":"5720 Tracyne Dr",
    "sg:city":"Fort Worth",
    "sg:classifiers":[
        {
            "category":"Home & Garden",
            "subcategory":"Carpets & Floor Coverings",
            "type":"Retail Goods"
        }
    ],
    "sg:phone":"+1 817 731 6889",
    "sg:postcode":"76114",
    "sg:province":"TX",
    "wof:name":"Wilsons Laminate Floor Spc",
    "wof:placetype":"venue"
},
  "geometry": {"coordinates":[-97.41096899999999,32.755096],"type":"Point"}
}