{
  "type": "Feature",
  "properties": {
    "iso:country":"US",
    "sg:address":"418 Peoples St",
    "sg:city":"Corpus Christi",
    "sg:classifiers":[
        {
            "category":"Professional",
            "type":"Services"
        }
    ],
    "sg:phone":"+1 361 884 1943",
    "sg:postcode":"78401",
    "sg:province":"TX",
    "sg:tags":[
        "establishment"
    ],
    "wof:name":"Independence Gathering & Mrktg",
    "wof:placetype":"venue"
},
  "geometry": {"coordinates":[-97.394774,27.796884],"type":"Point"}
}