{
  "type": "Feature",
  "properties": {
    "iso:country":"US",
    "sg:address":"2702 Old Iowa Park Rd",
    "sg:city":"Wichita Falls",
    "sg:classifiers":[
        {
            "category":"Shopping",
            "subcategory":"Clothing, Apparel, & Fashions",
            "type":"Retail Goods"
        }
    ],
    "sg:phone":"+1 940 723 8989",
    "sg:postcode":"76306",
    "sg:province":"TX",
    "wof:name":"Chun S Lockett",
    "wof:placetype":"venue"
},
  "geometry": {"coordinates":[-98.523527,33.928671],"type":"Point"}
}