{
  "type": "Feature",
  "properties": {
    "iso:country":"US",
    "sg:address":"2120 W 18th St",
    "sg:city":"Houston",
    "sg:classifiers":[
        {
            "category":"Restaurant",
            "type":"Food & Drink"
        }
    ],
    "sg:phone":"+1 713 861 2389",
    "sg:postcode":"77008",
    "sg:province":"TX",
    "sg:tags":[
        "pizza"
    ],
    "sg:website":"www.pizzainn.com",
    "wof:name":"Pizza Inn",
    "wof:placetype":"venue"
},
  "geometry": {"coordinates":[-95.436699,29.8018],"type":"Point"}
}