{
  "type": "Feature",
  "properties": {
    "iso:country":"US",
    "sg:address":"2805 Milroy Ln",
    "sg:city":"Houston",
    "sg:classifiers":[
        {
            "category":"Freight",
            "type":"Transportation"
        }
    ],
    "sg:phone":"+1 281 444 3353",
    "sg:postcode":"77066",
    "sg:province":"TX",
    "sg:tags":[
        "operator",
        "trucking"
    ],
    "wof:name":"B&F Hauling",
    "wof:placetype":"venue"
},
  "geometry": {"coordinates":[-95.476253,29.952065],"type":"Point"}
}