{
  "type": "Feature",
  "properties": {
    "iso:country":"US",
    "sg:address":"705 Maydelle Ln",
    "sg:city":"Garland",
    "sg:classifiers":[
        {
            "category":"Recreation",
            "type":"Entertainment"
        }
    ],
    "sg:phone":"+1 972 276 2612",
    "sg:postcode":"75042",
    "sg:province":"TX",
    "wof:name":"J&J Designs",
    "wof:placetype":"venue"
},
  "geometry": {"coordinates":[-96.673413,32.919349],"type":"Point"}
}