{
  "type": "Feature",
  "properties": {
    "iso:country":"US",
    "sg:address":"4600 W Bayshore Dr",
    "sg:city":"Bacliff",
    "sg:classifiers":[
        {
            "category":"Structure",
            "subcategory":"Warehouse",
            "type":"Public Place"
        },
        {
            "category":"Retail",
            "subcategory":"Storage",
            "type":"Services"
        }
    ],
    "sg:phone":"+1 281 339 5200",
    "sg:postcode":"77518",
    "sg:province":"TX",
    "sg:tags":[
        "self",
        "commercial",
        "warehouses-public-commercial",
        "household"
    ],
    "wof:name":"Americas Storage",
    "wof:placetype":"venue"
},
  "geometry": {"coordinates":[-94.977638,29.5107],"type":"Point"}
}