{
  "type": "Feature",
  "properties": {
    "iso:country":"US",
    "sg:address":"3505 Boca Chica Blvd",
    "sg:city":"Brownsville",
    "sg:classifiers":[
        {
            "category":"Health Services",
            "subcategory":"Doctor",
            "type":"Services"
        },
        {
            "category":"Social Services",
            "type":"Services"
        },
        {
            "category":"Personal",
            "type":"Services"
        }
    ],
    "sg:phone":"+1 956 504 1215",
    "sg:postcode":"78521",
    "sg:province":"TX",
    "sg:tags":[
        "family",
        "professional",
        "counselors-licensed",
        "psychologist",
        "individual",
        "marriage",
        "child",
        "counseling",
        "counselor"
    ],
    "wof:name":"South Texas Counseling & Psychological Testing",
    "wof:placetype":"venue"
},
  "geometry": {"coordinates":[-97.463883,25.919798],"type":"Point"}
}