{
  "type": "Feature",
  "properties": {
    "iso:country":"US",
    "sg:address":"15715 Wagon Rd",
    "sg:city":"Houston",
    "sg:classifiers":[
        {
            "category":"Manufacturing",
            "subcategory":"Glass & Minerals",
            "type":"Manufacturing & Wholesale Goods"
        }
    ],
    "sg:phone":"+1 281 820 2298",
    "sg:postcode":"77060",
    "sg:province":"TX",
    "sg:tags":[
        "ready",
        "concrete",
        "mfg"
    ],
    "wof:name":"Miguels Make Ready",
    "wof:placetype":"venue"
},
  "geometry": {"coordinates":[-95.40615200000001,29.928557],"type":"Point"}
}