{
  "type": "Feature",
  "properties": {
    "iso:country":"US",
    "sg:address":"5290 Belt Line Rd",
    "sg:city":"Dallas",
    "sg:classifiers":[
        {
            "category":"Restaurant",
            "type":"Food & Drink"
        }
    ],
    "sg:phone":"+1 972 386 7373",
    "sg:postcode":"75254",
    "sg:province":"TX",
    "sg:tags":[
        "italian"
    ],
    "wof:name":"Momos Pasta of Addison",
    "wof:placetype":"venue"
},
  "geometry": {"coordinates":[-96.814336,32.953875],"type":"Point"}
}