{
  "type": "Feature",
  "properties": {
    "iso:country":"US",
    "sg:address":"1315 SW Military Dr",
    "sg:city":"San Antonio",
    "sg:classifiers":[
        {
            "category":"Shopping",
            "subcategory":"Used Merchandise",
            "type":"Retail Goods"
        }
    ],
    "sg:phone":"+1 210 921 2274",
    "sg:postcode":"78221",
    "sg:province":"TX",
    "sg:tags":[
        "pawnbroker"
    ],
    "wof:name":"Cash America Pawn",
    "wof:placetype":"venue"
},
  "geometry": {"coordinates":[-98.514087,29.356744],"type":"Point"}
}