{
  "type": "Feature",
  "properties": {
    "iso:country":"US",
    "sg:address":"7838 Barlite Blvd",
    "sg:city":"San Antonio",
    "sg:classifiers":[
        {
            "category":"Health Services",
            "subcategory":"Doctor",
            "type":"Services"
        }
    ],
    "sg:phone":"+1 210 924 4400",
    "sg:postcode":"78224",
    "sg:province":"TX",
    "sg:tags":[
        "physician",
        "surgeon"
    ],
    "wof:name":"Arthritis & Osteoporosis Ctr",
    "wof:placetype":"venue"
},
  "geometry": {"coordinates":[-98.54648299999999,29.350959],"type":"Point"}
}