{
  "type": "Feature",
  "properties": {
    "iso:country":"US",
    "sg:address":"3240 Happy Meadows Dr",
    "sg:city":"Alvarado",
    "sg:classifiers":[
        {
            "category":"Wholesale",
            "subcategory":"Hardware",
            "type":"Manufacturing & Wholesale Goods"
        }
    ],
    "sg:phone":"+1 817 790 8964",
    "sg:postcode":"76009",
    "sg:province":"TX",
    "sg:tags":[
        "tool"
    ],
    "wof:name":"Wayne's Tools",
    "wof:placetype":"venue"
},
  "geometry": {"coordinates":[-97.20480999999999,32.460924],"type":"Point"}
}