{
  "type": "Feature",
  "properties": {
    "iso:country":"US",
    "sg:address":"530 Vega Dr",
    "sg:city":"Corpus Christi",
    "sg:classifiers":[
        {
            "category":"Professional",
            "subcategory":"Accounting & Tax Preparation",
            "type":"Services"
        },
        {
            "category":"Health Services",
            "subcategory":"Doctor",
            "type":"Services"
        }
    ],
    "sg:phone":"+1 361 937 1954",
    "sg:postcode":"78418",
    "sg:province":"TX",
    "sg:tags":[
        "clinic"
    ],
    "wof:name":"Allied Medical Auditors",
    "wof:placetype":"venue"
},
  "geometry": {"coordinates":[-97.30109899999999,27.63163],"type":"Point"}
}