{
  "type": "Feature",
  "properties": {
    "iso:country":"US",
    "sg:address":"12600 Lowden Ln",
    "sg:city":"Manchaca",
    "sg:classifiers":[
        {
            "category":"Professional",
            "type":"Services"
        }
    ],
    "sg:phone":"+1 512 282 9516",
    "sg:postcode":"78652",
    "sg:province":"TX",
    "wof:name":"Rogue River Rentavation",
    "wof:placetype":"venue"
},
  "geometry": {"coordinates":[-97.835804,30.137485],"type":"Point"}
}