{
  "type": "Feature",
  "properties": {
    "iso:country":"US",
    "sg:address":"3041 Milton Ave",
    "sg:city":"Dallas",
    "sg:classifiers":[
        {
            "category":"Professional",
            "subcategory":"Lawyer & Legal Services",
            "type":"Services"
        }
    ],
    "sg:phone":"+1 214 351 9941",
    "sg:postcode":"75205",
    "sg:province":"TX",
    "wof:name":"Estep Lynn Jr Atty",
    "wof:placetype":"venue"
},
  "geometry": {"coordinates":[-96.780761,32.8486],"type":"Point"}
}