{
  "type": "Feature",
  "properties": {
    "iso:country":"US",
    "sg:address":"2921 Windsor Dr",
    "sg:city":"Flower Mound",
    "sg:classifiers":[
        {
            "category":"Building & Trades",
            "subcategory":"Plumbing",
            "type":"Services"
        }
    ],
    "sg:phone":"+1 972 691 8880",
    "sg:postcode":"75028",
    "sg:province":"TX",
    "sg:tags":[
        "contractor"
    ],
    "wof:name":"L&S Heating & Air",
    "wof:placetype":"venue"
},
  "geometry": {"coordinates":[-97.07375,33.044083],"type":"Point"}
}