{
  "type": "Feature",
  "properties": {
    "iso:country":"US",
    "sg:address":"12020 Autumn Gate Dr",
    "sg:city":"El Paso",
    "sg:classifiers":[
        {
            "category":"Freight",
            "type":"Transportation"
        }
    ],
    "sg:phone":"+1 325 856 1156",
    "sg:postcode":"79936",
    "sg:province":"TX",
    "wof:name":"SE Xpress",
    "wof:placetype":"venue"
},
  "geometry": {"coordinates":[-106.28166400000001,31.759311],"type":"Point"}
}