{
  "type": "Feature",
  "properties": {
    "iso:country":"US",
    "sg:address":"9206 Kempwood Dr",
    "sg:city":"Houston",
    "sg:classifiers":[
        {
            "category":"Building & Trades",
            "subcategory":"Landscaping Services",
            "type":"Services"
        }
    ],
    "sg:phone":"+1 713 460 2005",
    "sg:postcode":"77080",
    "sg:province":"TX",
    "sg:tags":[
        "landscape"
    ],
    "wof:name":"Plant It Earth Landscape",
    "wof:placetype":"venue"
},
  "geometry": {"coordinates":[-95.52135699999999,29.822044],"type":"Point"}
}