{
  "type": "Feature",
  "properties": {
    "iso:country":"US",
    "sg:address":"400 W Cesar Chavez St",
    "sg:city":"Austin",
    "sg:classifiers":[
        {
            "category":"Real Estate",
            "subcategory":"Architect",
            "type":"Services"
        }
    ],
    "sg:phone":"+1 512 472 6721",
    "sg:postcode":"78701",
    "sg:province":"TX",
    "sg:website":"www.psp.com",
    "wof:name":"Page Southerland Page",
    "wof:placetype":"venue"
},
  "geometry": {"coordinates":[-97.749118,30.264656],"type":"Point"}
}