{
  "type": "Feature",
  "properties": {
    "iso:country":"US",
    "sg:address":"24307 Aldine Westfield Rd",
    "sg:city":"Spring",
    "sg:classifiers":[
        {
            "category":"Personal",
            "subcategory":"Beauty Salon",
            "type":"Services"
        }
    ],
    "sg:phone":"+1 281 353 7799",
    "sg:postcode":"77373",
    "sg:province":"TX",
    "wof:name":"Golden Shears Headquarters",
    "wof:placetype":"venue"
},
  "geometry": {"coordinates":[-95.39802,30.058316],"type":"Point"}
}