{
  "type": "Feature",
  "properties": {
    "iso:country":"US",
    "sg:address":"310 E Josephine St",
    "sg:city":"Mc Kinney",
    "sg:classifiers":[
        {
            "category":"Manufacturing",
            "subcategory":"Rubber & Plastics",
            "type":"Manufacturing & Wholesale Goods"
        }
    ],
    "sg:phone":"+1 972 548 0781",
    "sg:postcode":"75069",
    "sg:province":"TX",
    "sg:website":"www.ventureplastics.net",
    "wof:name":"Venture Plastics",
    "wof:placetype":"venue"
},
  "geometry": {"coordinates":[-96.61432499999999,33.206663],"type":"Point"}
}