{
  "type": "Feature",
  "properties": {
    "iso:country":"US",
    "sg:address":"722 Harrison St",
    "sg:city":"Corpus Christi",
    "sg:classifiers":[
        {
            "category":"Arts & Performance",
            "subcategory":"Theater",
            "type":"Entertainment"
        }
    ],
    "sg:phone":"+1 361 443 0079",
    "sg:postcode":"78404",
    "sg:province":"TX",
    "sg:tags":[
        "theatrical"
    ],
    "wof:name":"7bstage Thter Rsources MGT LLC",
    "wof:placetype":"venue"
},
  "geometry": {"coordinates":[-97.398312,27.760113],"type":"Point"}
}