{
  "type": "Feature",
  "properties": {
    "iso:country":"US",
    "sg:address":"2219 Blaine St",
    "sg:city":"Laredo",
    "sg:classifiers":[
        {
            "category":"Professional",
            "type":"Services"
        }
    ],
    "sg:phone":"+1 956 727 5559",
    "sg:postcode":"78043",
    "sg:province":"TX",
    "wof:name":"Ramirez International",
    "wof:placetype":"venue"
},
  "geometry": {"coordinates":[-99.472762,27.490435],"type":"Point"}
}