{
  "type": "Feature",
  "properties": {
    "iso:country":"US",
    "sg:address":"200 E Sam Rayburn Dr",
    "sg:city":"Bonham",
    "sg:classifiers":[
        {
            "category":"Autos & Motor Vehicles",
            "subcategory":"Auto Supplies",
            "type":"Retail Goods"
        }
    ],
    "sg:phone":"+1 903 583 5553",
    "sg:postcode":"75418",
    "sg:province":"TX",
    "sg:tags":[
        "operator",
        "dwelling",
        "beef",
        "cattle"
    ],
    "wof:name":"Coast To Coast",
    "wof:placetype":"venue"
},
  "geometry": {"coordinates":[-96.178029,33.577027],"type":"Point"}
}