{
  "type": "Feature",
  "properties": {
    "iso:country":"US",
    "sg:address":"6100 Whispering Ln",
    "sg:city":"Fort Worth",
    "sg:classifiers":[
        {
            "category":"Education",
            "subcategory":"School",
            "type":"Public Place"
        }
    ],
    "sg:phone":"+1 817 547 5820",
    "sg:postcode":"76148",
    "sg:province":"TX",
    "wof:name":"Hardeman Elementary School",
    "wof:placetype":"venue"
},
  "geometry": {"coordinates":[-97.24811200000001,32.863782],"type":"Point"}
}