{
  "type": "Feature",
  "properties": {
    "iso:country":"US",
    "sg:address":"316 E Navarro St",
    "sg:city":"De Leon",
    "sg:classifiers":[
        {
            "category":"Organizations",
            "subcategory":"Religious Organization",
            "type":"Services"
        }
    ],
    "sg:phone":"+1 254 893 5842",
    "sg:postcode":"76444",
    "sg:province":"TX",
    "sg:tags":[
        "church"
    ],
    "wof:name":"Church Of Christ",
    "wof:placetype":"venue"
},
  "geometry": {"coordinates":[-98.532718,32.116957],"type":"Point"}
}