{
  "type": "Feature",
  "properties": {
    "iso:country":"US",
    "sg:address":"111 Rosewood Ave",
    "sg:city":"Boerne",
    "sg:classifiers":[
        {
            "category":"Retail",
            "subcategory":"Funeral Services",
            "type":"Services"
        }
    ],
    "sg:phone":"+1 830 249 2321",
    "sg:postcode":"78006",
    "sg:province":"TX",
    "sg:tags":[
        "director"
    ],
    "wof:name":"Ebensberger Funeral Home",
    "wof:placetype":"venue"
},
  "geometry": {"coordinates":[-98.729617,29.79309],"type":"Point"}
}