{
  "type": "Feature",
  "properties": {
    "iso:country":"US",
    "sg:address":"4310 Buffalo Gap Rd",
    "sg:city":"Abilene",
    "sg:classifiers":[
        {
            "category":"Shopping",
            "subcategory":"Clothing, Apparel, & Fashions",
            "type":"Retail Goods"
        }
    ],
    "sg:phone":"+1 325 690 1007",
    "sg:postcode":"79606",
    "sg:province":"TX",
    "sg:tags":[
        "woman",
        "store"
    ],
    "sg:website":"www.lanebryant.com",
    "wof:name":"Lane Bryant",
    "wof:placetype":"venue"
},
  "geometry": {"coordinates":[-99.759399,32.399097],"type":"Point"}
}