{
  "type": "Feature",
  "properties": {
    "iso:country":"US",
    "sg:address":"608 N High St",
    "sg:city":"San Saba",
    "sg:classifiers":[
        {
            "category":"Shopping",
            "subcategory":"Pharmacy",
            "type":"Retail Goods"
        }
    ],
    "sg:phone":"+1 325 372 5445",
    "sg:postcode":"76877",
    "sg:province":"TX",
    "sg:tags":[
        "veterinary"
    ],
    "wof:name":"San Saba Animal Hospital",
    "wof:placetype":"venue"
},
  "geometry": {"coordinates":[-98.718408,31.199896],"type":"Point"}
}