{
  "type": "Feature",
  "properties": {
    "iso:country":"US",
    "sg:address":"1203 E Marshall Ave",
    "sg:city":"Longview",
    "sg:classifiers":[
        {
            "category":"Personal",
            "subcategory":"Nail Salon",
            "type":"Services"
        }
    ],
    "sg:phone":"+1 903 553 0499",
    "sg:postcode":"75601",
    "sg:province":"TX",
    "wof:name":"Nail Spa",
    "wof:placetype":"venue"
},
  "geometry": {"coordinates":[-94.724272,32.503215],"type":"Point"}
}