{
  "type": "Feature",
  "properties": {
    "iso:country":"US",
    "sg:address":"2807 Oak Park Dr",
    "sg:city":"Austin",
    "sg:classifiers":[
        {
            "category":"Freight",
            "type":"Transportation"
        }
    ],
    "sg:phone":"+1 512 448 3200",
    "sg:postcode":"78704",
    "sg:province":"TX",
    "sg:tags":[
        "special"
    ],
    "wof:name":"Boathandlers Inc",
    "wof:placetype":"venue"
},
  "geometry": {"coordinates":[-97.78494600000001,30.249395],"type":"Point"}
}