{
  "type": "Feature",
  "properties": {
    "iso:country":"US",
    "sg:address":"211 W San Antonio St",
    "sg:city":"San Marcos",
    "sg:classifiers":[
        {
            "category":"Banks & Credit Unions",
            "subcategory":"Bank",
            "type":"Services"
        }
    ],
    "sg:phone":"+1 512 396 4444",
    "sg:postcode":"78666",
    "sg:province":"TX",
    "sg:tags":[
        "loan"
    ],
    "wof:name":"Banner Finance Co",
    "wof:placetype":"venue"
},
  "geometry": {"coordinates":[-97.942716,29.881884],"type":"Point"}
}