{
  "type": "Feature",
  "properties": {
    "iso:country":"US",
    "sg:address":"2119 W Walker St",
    "sg:city":"Breckenridge",
    "sg:classifiers":[
        {
            "category":"Building & Trades",
            "subcategory":"Equipment Rental",
            "type":"Services"
        }
    ],
    "sg:phone":"+1 254 559 8762",
    "sg:postcode":"76424",
    "sg:province":"TX",
    "sg:tags":[
        "yard",
        "feedlot",
        "beef",
        "cattle"
    ],
    "wof:name":"Latham's Rent-All",
    "wof:placetype":"venue"
},
  "geometry": {"coordinates":[-98.930678,32.756006],"type":"Point"}
}