{
  "type": "Feature",
  "properties": {
    "iso:country":"US",
    "sg:address":"12346 Gulf Fwy Ste B",
    "sg:city":"Houston",
    "sg:classifiers":[
        {
            "category":"Banks & Credit Unions",
            "subcategory":"Bank",
            "type":"Services"
        }
    ],
    "sg:phone":"+1 713 850 1254",
    "sg:postcode":"77034",
    "sg:province":"TX",
    "wof:name":"First Educators Credit Union",
    "wof:placetype":"venue"
},
  "geometry": {"coordinates":[-95.220901,29.6199],"type":"Point"}
}