{
  "type": "Feature",
  "properties": {
    "iso:country":"US",
    "sg:address":"1106 12th Man Cir",
    "sg:city":"College Station",
    "sg:classifiers":[
        {
            "category":"Shopping",
            "subcategory":"Jewelry",
            "type":"Retail Goods"
        }
    ],
    "sg:phone":"+1 979 690 2912",
    "sg:postcode":"77845",
    "sg:province":"TX",
    "wof:name":"David Gardeners Jeweler",
    "wof:placetype":"venue"
},
  "geometry": {"coordinates":[-96.24311299999999,30.569723],"type":"Point"}
}