{
  "type": "Feature",
  "properties": {
    "iso:country":"US",
    "sg:address":"7 Lake Shore Dr",
    "sg:city":"Corpus Christi",
    "sg:classifiers":[
        {
            "category":"Shopping",
            "subcategory":"Used Merchandise",
            "type":"Retail Goods"
        }
    ],
    "sg:phone":"+1 361 853 5483",
    "sg:postcode":"78413",
    "sg:province":"TX",
    "wof:name":"Sarahs",
    "wof:placetype":"venue"
},
  "geometry": {"coordinates":[-97.39825,27.694266],"type":"Point"}
}