{
  "type": "Feature",
  "properties": {
    "iso:country":"US",
    "sg:address":"709 W Green Ave",
    "sg:city":"Killeen",
    "sg:classifiers":[
        {
            "category":"Building & Trades",
            "subcategory":"Construction",
            "type":"Services"
        }
    ],
    "sg:phone":"+1 254 290 2419",
    "sg:postcode":"76541",
    "sg:province":"TX",
    "sg:tags":[
        "concrete",
        "contractor"
    ],
    "wof:name":"Jmg Construction",
    "wof:placetype":"venue"
},
  "geometry": {"coordinates":[-97.73492,31.126797],"type":"Point"}
}