{
  "type": "Feature",
  "properties": {
    "iso:country":"US",
    "sg:address":"3511 W Alberta Rd",
    "sg:city":"Edinburg",
    "sg:classifiers":[
        {
            "category":"Professional",
            "subcategory":"Advertising",
            "type":"Services"
        },
        {
            "category":"Professional",
            "subcategory":"Printing & Photocopies",
            "type":"Services"
        }
    ],
    "sg:phone":"+1 956 994 3422",
    "sg:postcode":"78539",
    "sg:province":"TX",
    "sg:tags":[
        "directory",
        "consultant",
        "guide"
    ],
    "wof:name":"User Friendly Phone Book",
    "wof:placetype":"venue"
},
  "geometry": {"coordinates":[-98.20559299999999,26.25916],"type":"Point"}
}