{
  "type": "Feature",
  "properties": {
    "iso:country":"US",
    "sg:address":"10609 Macmora Rd",
    "sg:city":"Austin",
    "sg:classifiers":[
        {
            "category":"Building & Trades",
            "subcategory":"Landscaping Services",
            "type":"Services"
        }
    ],
    "sg:phone":"+1 512 836 1620",
    "sg:postcode":"78758",
    "sg:province":"TX",
    "wof:name":"Shawn A Walker Lawn Svc",
    "wof:placetype":"venue"
},
  "geometry": {"coordinates":[-97.702186,30.381621],"type":"Point"}
}