{
  "type": "Feature",
  "properties": {
    "iso:country":"US",
    "sg:address":"14811 Canonero",
    "sg:city":"San Antonio",
    "sg:classifiers":[
        {
            "category":"Utilities",
            "subcategory":"Refuse",
            "type":"Services"
        }
    ],
    "sg:phone":"+1 210 492 8938",
    "sg:postcode":"78248",
    "sg:province":"TX",
    "sg:tags":[
        "system"
    ],
    "wof:name":"King Recycling Co Inc",
    "wof:placetype":"venue"
},
  "geometry": {"coordinates":[-98.52857,29.579958],"type":"Point"}
}