{
  "type": "Feature",
  "properties": {
    "iso:country":"US",
    "sg:address":"436 Sawdust Rd",
    "sg:city":"Spring",
    "sg:classifiers":[
        {
            "category":"Personal",
            "type":"Services"
        }
    ],
    "sg:phone":"+1 281 465 4461",
    "sg:postcode":"77380",
    "sg:province":"TX",
    "sg:tags":[
        "control",
        "weight"
    ],
    "wof:name":"Center MM Quick Weight Loss",
    "wof:placetype":"venue"
},
  "geometry": {"coordinates":[-95.452825,30.126808],"type":"Point"}
}