{
  "type": "Feature",
  "properties": {
    "iso:country":"US",
    "sg:address":"900 E Amarillo Blvd",
    "sg:city":"Amarillo",
    "sg:classifiers":[
        {
            "category":"Bars & Pubs",
            "type":"Food & Drink"
        }
    ],
    "sg:phone":"+1 806 353 2467",
    "sg:postcode":"79107",
    "sg:province":"TX",
    "sg:tags":[
        "drinking"
    ],
    "wof:name":"Los Tres Amigos",
    "wof:placetype":"venue"
},
  "geometry": {"coordinates":[-101.823802,35.221976],"type":"Point"}
}