{
  "type": "Feature",
  "properties": {
    "iso:country":"US",
    "sg:address":"502 Cedar Ridge Dr",
    "sg:city":"Pflugerville",
    "sg:classifiers":[
        {
            "category":"Shopping",
            "subcategory":"Clothing, Apparel, & Fashions",
            "type":"Retail Goods"
        }
    ],
    "sg:phone":"+1 512 990 0264",
    "sg:postcode":"78660",
    "sg:province":"TX",
    "sg:tags":[
        "item",
        "boutique"
    ],
    "wof:name":"Lizs Fashions",
    "wof:placetype":"venue"
},
  "geometry": {"coordinates":[-97.615297,30.442083],"type":"Point"}
}