{
  "type": "Feature",
  "properties": {
    "iso:country":"US",
    "sg:address":"100 Diane Rd",
    "sg:city":"Ferris",
    "sg:classifiers":[
        {
            "category":"Government",
            "subcategory":"Office",
            "type":"Public Place"
        }
    ],
    "sg:phone":"+1 972 544 2110",
    "sg:postcode":"75125",
    "sg:province":"TX",
    "sg:tags":[
        "town"
    ],
    "wof:name":"City of Ferris",
    "wof:placetype":"venue"
},
  "geometry": {"coordinates":[-96.631096,32.525287],"type":"Point"}
}