{
  "type": "Feature",
  "properties": {
    "iso:country":"US",
    "sg:address":"716 Chelsea Blvd",
    "sg:city":"Houston",
    "sg:classifiers":[
        {
            "category":"Health Services",
            "subcategory":"Health Practitioner",
            "type":"Services"
        }
    ],
    "sg:phone":"+1 713 942 9688",
    "sg:postcode":"77006",
    "sg:province":"TX",
    "sg:tags":[
        "acupuncture"
    ],
    "wof:name":"Acupuncture Medical Services",
    "wof:placetype":"venue"
},
  "geometry": {"coordinates":[-95.388603,29.730301],"type":"Point"}
}