{
  "type": "Feature",
  "properties": {
    "iso:country":"US",
    "sg:address":"15734 Edenvale St",
    "sg:city":"Friendswood",
    "sg:classifiers":[
        {
            "category":"Professional",
            "type":"Services"
        }
    ],
    "sg:phone":"+1 281 996 1080",
    "sg:postcode":"77546",
    "sg:province":"TX",
    "wof:name":"John & Lisa Pfeifer",
    "wof:placetype":"venue"
},
  "geometry": {"coordinates":[-95.188249,29.538083],"type":"Point"}
}