{
  "type": "Feature",
  "properties": {
    "iso:country":"US",
    "sg:address":"4900 Allendale Rd",
    "sg:city":"Houston",
    "sg:classifiers":[
        {
            "category":"Food & Beverages",
            "subcategory":"Groceries & Convenience Stores",
            "type":"Retail Goods"
        }
    ],
    "sg:phone":"+1 713 946 4198",
    "sg:postcode":"77017",
    "sg:province":"TX",
    "wof:name":"Step & Go Food Store",
    "wof:placetype":"venue"
},
  "geometry": {"coordinates":[-95.247704,29.6821],"type":"Point"}
}