{
  "type": "Feature",
  "properties": {
    "iso:country":"US",
    "sg:address":"10109 W Co Rd 150",
    "sg:city":"Midland",
    "sg:classifiers":[
        {
            "category":"Retail",
            "subcategory":"Repair Shop",
            "type":"Services"
        }
    ],
    "sg:phone":"+1 432 563 8098",
    "sg:postcode":"79706",
    "sg:province":"TX",
    "sg:tags":[
        "blacksmith"
    ],
    "wof:name":"Flatland Forge",
    "wof:placetype":"venue"
},
  "geometry": {"coordinates":[-102.195977,31.881608],"type":"Point"}
}