{
  "type": "Feature",
  "properties": {
    "iso:country":"US",
    "sg:address":"1815 Junction Hwy",
    "sg:city":"Kerrville",
    "sg:classifiers":[
        {
            "category":"Autos & Motor Vehicles",
            "subcategory":"Recreational Vehicle Sales",
            "type":"Retail Goods"
        }
    ],
    "sg:phone":"+1 830 257 2640",
    "sg:postcode":"78028",
    "sg:province":"TX",
    "sg:tags":[
        "home",
        "camper"
    ],
    "wof:name":"Home Town Rv's",
    "wof:placetype":"venue"
},
  "geometry": {"coordinates":[-99.183639,30.068538],"type":"Point"}
}