{
  "type": "Feature",
  "properties": {
    "iso:country":"US",
    "sg:address":"15794 Chapel Rd",
    "sg:city":"Lorena",
    "sg:classifiers":[
        {
            "category":"Shopping",
            "type":"Retail Goods"
        }
    ],
    "sg:phone":"+1 254 857 8844",
    "sg:postcode":"76655",
    "sg:province":"TX",
    "sg:tags":[
        "merchandise"
    ],
    "wof:name":"Amy K Kunze",
    "wof:placetype":"venue"
},
  "geometry": {"coordinates":[-97.28315000000001,31.431195],"type":"Point"}
}