{
  "type": "Feature",
  "properties": {
    "iso:country":"US",
    "sg:address":"7700 San Felipe St",
    "sg:city":"Houston",
    "sg:classifiers":[
        {
            "category":"Health Services",
            "subcategory":"Doctor",
            "type":"Services"
        },
        {
            "category":"Health Services",
            "subcategory":"Dentist",
            "type":"Services"
        }
    ],
    "sg:phone":"+1 713 784 4200",
    "sg:postcode":"77063",
    "sg:province":"TX",
    "sg:tags":[
        "dentists-oral",
        "physician",
        "maxillofacial",
        "surgeons",
        "surgery",
        "oral"
    ],
    "wof:name":"O'shell, Michael V, Dds - Oral Maxillofacial Surgery",
    "wof:placetype":"venue"
},
  "geometry": {"coordinates":[-95.503415,29.750636],"type":"Point"}
}