{
  "type": "Feature",
  "properties": {
    "iso:country":"US",
    "sg:address":"1252 Harwood Rd",
    "sg:city":"Bedford",
    "sg:classifiers":[
        {
            "category":"Banks & Credit Unions",
            "subcategory":"Investment Brokerage",
            "type":"Services"
        }
    ],
    "sg:phone":"+1 817 358 9870",
    "sg:postcode":"76021",
    "sg:province":"TX",
    "sg:tags":[
        "security"
    ],
    "wof:name":"Securities America",
    "wof:placetype":"venue"
},
  "geometry": {"coordinates":[-97.150683,32.853317],"type":"Point"}
}