{
  "type": "Feature",
  "properties": {
    "iso:country":"US",
    "sg:address":"4103 Balcones Dr",
    "sg:city":"Austin",
    "sg:classifiers":[
        {
            "category":"Manufacturing",
            "subcategory":"Glass & Minerals",
            "type":"Manufacturing & Wholesale Goods"
        }
    ],
    "sg:phone":"+1 512 458 9330",
    "sg:postcode":"78731",
    "sg:province":"TX",
    "sg:tags":[
        "glassware",
        "glassware-wholesale",
        "manufacturer"
    ],
    "sg:website":"http://www.homefrontartisans.com",
    "wof:name":"Home Front Artisans",
    "wof:placetype":"venue"
},
  "geometry": {"coordinates":[-97.77017499999999,30.322549],"type":"Point"}
}