{
  "type": "Feature",
  "properties": {
    "iso:country":"US",
    "sg:address":"745 Oak Dale Ave",
    "sg:city":"Lake Dallas",
    "sg:classifiers":[
        {
            "category":"Professional",
            "subcategory":"Computer Services",
            "type":"Services"
        }
    ],
    "sg:phone":"+1 940 321 0151",
    "sg:postcode":"75065",
    "sg:province":"TX",
    "sg:tags":[
        "design",
        "system"
    ],
    "wof:name":"Millennium Broadband",
    "wof:placetype":"venue"
},
  "geometry": {"coordinates":[-97.031475,33.140154],"type":"Point"}
}