{
  "type": "Feature",
  "properties": {
    "iso:country":"US",
    "sg:address":"5714 Wyrick Ln",
    "sg:city":"Garland",
    "sg:classifiers":[
        {
            "category":"Shopping",
            "subcategory":"Discount & Variety Stores",
            "type":"Retail Goods"
        }
    ],
    "sg:phone":"+1 972 530 9787",
    "sg:postcode":"75044",
    "sg:province":"TX",
    "sg:tags":[
        "merchandise",
        "general"
    ],
    "wof:name":"Yati & Niki Inc",
    "wof:placetype":"venue"
},
  "geometry": {"coordinates":[-96.667338,32.966706],"type":"Point"}
}