{
  "type": "Feature",
  "properties": {
    "iso:country":"US",
    "sg:address":"7306 Louetta Rd",
    "sg:city":"Spring",
    "sg:classifiers":[
        {
            "category":"Shopping",
            "type":"Retail Goods"
        }
    ],
    "sg:phone":"+1 281 257 3663",
    "sg:postcode":"77379",
    "sg:province":"TX",
    "sg:tags":[
        "picture",
        "frame"
    ],
    "wof:name":"Great Frame Up",
    "wof:placetype":"venue"
},
  "geometry": {"coordinates":[-95.52384499999999,30.021058],"type":"Point"}
}