{
  "type": "Feature",
  "properties": {
    "iso:country":"US",
    "sg:address":"108 Pebbles Dr",
    "sg:city":"Liberty Hill",
    "sg:classifiers":[
        {
            "category":"Shopping",
            "subcategory":"Clothing, Apparel, & Fashions",
            "type":"Retail Goods"
        }
    ],
    "sg:phone":"+1 512 515 0704",
    "sg:postcode":"78642",
    "sg:province":"TX",
    "sg:tags":[
        "wear"
    ],
    "wof:name":"Spoiled Rotten",
    "wof:placetype":"venue"
},
  "geometry": {"coordinates":[-98.006399,30.656122],"type":"Point"}
}