{
  "type": "Feature",
  "properties": {
    "iso:country":"US",
    "sg:address":"6500 Depot Dr",
    "sg:city":"Waco",
    "sg:classifiers":[
        {
            "category":"Wholesale",
            "subcategory":"Machinery & Supplies",
            "type":"Manufacturing & Wholesale Goods"
        }
    ],
    "sg:phone":"+1 817 722 1119",
    "sg:postcode":"76712",
    "sg:province":"TX",
    "sg:tags":[
        "industrial"
    ],
    "wof:name":"Motion Industries Inc",
    "wof:placetype":"venue"
},
  "geometry": {"coordinates":[-97.18903899999999,31.507417],"type":"Point"}
}