{
  "type": "Feature",
  "properties": {
    "iso:country":"US",
    "sg:address":"965 W Lamar Blvd",
    "sg:city":"Arlington",
    "sg:classifiers":[
        {
            "category":"Restaurant",
            "type":"Food & Drink"
        }
    ],
    "sg:menulink":"http://www.allmenus.com/tx/arlington/235131-roly-poly-sandwiches/menu/",
    "sg:phone":"+1 817 274 7659",
    "sg:postcode":"76012",
    "sg:province":"TX",
    "sg:tags":[
        "wrap",
        "american",
        "sandwich"
    ],
    "wof:name":"Roly Poly Sandwiches",
    "wof:placetype":"venue"
},
  "geometry": {"coordinates":[-97.11887,32.762616],"type":"Point"}
}