{
  "type": "Feature",
  "properties": {
    "iso:country":"US",
    "sg:address":"3591 Luedecke Ln",
    "sg:city":"Bryan",
    "sg:classifiers":[
        {
            "category":"Retail",
            "subcategory":"Auto Repair",
            "type":"Services"
        }
    ],
    "sg:phone":"+1 979 822 8441",
    "sg:postcode":"77807",
    "sg:province":"TX",
    "sg:tags":[
        "body"
    ],
    "wof:name":"L&G Collision Inc",
    "wof:placetype":"venue"
},
  "geometry": {"coordinates":[-96.39466400000001,30.625415],"type":"Point"}
}