{
  "type": "Feature",
  "properties": {
    "iso:country":"US",
    "sg:address":"502 E Ave B",
    "sg:city":"Alpine",
    "sg:classifiers":[
        {
            "category":"Building & Trades",
            "subcategory":"Construction",
            "type":"Services"
        }
    ],
    "sg:phone":"+1 432 837 7050",
    "sg:postcode":"79830",
    "sg:province":"TX",
    "sg:tags":[
        "repairing",
        "remodeling",
        "contractor"
    ],
    "wof:name":"Home Front",
    "wof:placetype":"venue"
},
  "geometry": {"coordinates":[-103.658779,30.362183],"type":"Point"}
}