{
  "type": "Feature",
  "properties": {
    "iso:country":"US",
    "sg:address":"3831 Westminster Dr",
    "sg:city":"Carrollton",
    "sg:classifiers":[
        {
            "category":"Professional",
            "subcategory":"Computer Services",
            "type":"Services"
        }
    ],
    "sg:phone":"+1 972 492 2733",
    "sg:postcode":"75007",
    "sg:province":"TX",
    "sg:tags":[
        "web",
        "design",
        "site",
        "software"
    ],
    "wof:name":"Mtb Enterprises Inc",
    "wof:placetype":"venue"
},
  "geometry": {"coordinates":[-96.89127000000001,33.015585],"type":"Point"}
}