{
  "type": "Feature",
  "properties": {
    "iso:country":"US",
    "sg:address":"2350 Lakeside Blvd",
    "sg:city":"Richardson",
    "sg:classifiers":[
        {
            "category":"Coffee & Tea",
            "type":"Food & Drink"
        },
        {
            "category":"Restaurant",
            "type":"Food & Drink"
        }
    ],
    "sg:phone":"+1 972 231 1611",
    "sg:postcode":"75082",
    "sg:province":"TX",
    "sg:tags":[
        "lunch",
        "brunch",
        "cafeteria",
        "espresso",
        "breakfast"
    ],
    "wof:name":"Lakeside Cafe",
    "wof:placetype":"venue"
},
  "geometry": {"coordinates":[-96.710938,32.981411],"type":"Point"}
}