{
  "type": "Feature",
  "properties": {
    "iso:country":"US",
    "sg:address":"1029 Co Rd 101",
    "sg:city":"Falfurrias",
    "sg:classifiers":[
        {
            "category":"Professional",
            "subcategory":"Business Services",
            "type":"Services"
        }
    ],
    "sg:phone":"+1 361 325 3483",
    "sg:postcode":"78384",
    "sg:province":"TX",
    "sg:tags":[
        "interior",
        "consultant",
        "design",
        "decorator"
    ],
    "wof:name":"Decorating Den",
    "wof:placetype":"venue"
},
  "geometry": {"coordinates":[-98.452761,27.999139],"type":"Point"}
}