{
  "type": "Feature",
  "properties": {
    "iso:country":"US",
    "sg:address":"1110 Phyllis St",
    "sg:city":"Deer Park",
    "sg:classifiers":[
        {
            "category":"Shopping",
            "subcategory":"Hobbies, Toys, & Games",
            "type":"Retail Goods"
        }
    ],
    "sg:phone":"+1 281 479 1967",
    "sg:postcode":"77536",
    "sg:province":"TX",
    "wof:name":"Old Waverly Woodcrafters",
    "wof:placetype":"venue"
},
  "geometry": {"coordinates":[-95.111738,29.696287],"type":"Point"}
}