{
  "type": "Feature",
  "properties": {
    "iso:country":"US",
    "sg:address":"601 E Whitestone Blvd Ste 206",
    "sg:city":"Cedar Park",
    "sg:classifiers":[
        {
            "category":"Health Services",
            "subcategory":"Dentist",
            "type":"Services"
        }
    ],
    "sg:phone":"+1 512 260 8556",
    "sg:postcode":"78613",
    "sg:province":"TX",
    "wof:name":"Cedar Park Dental Care",
    "wof:placetype":"venue"
},
  "geometry": {"coordinates":[-97.82398999999999,30.523927],"type":"Point"}
}