{
  "type": "Feature",
  "properties": {
    "iso:country":"US",
    "sg:address":"402 N Glendale St",
    "sg:city":"Hallettsville",
    "sg:classifiers":[
        {
            "category":"Professional",
            "subcategory":"Business Services",
            "type":"Services"
        }
    ],
    "sg:phone":"+1 361 798 9102",
    "sg:postcode":"77964",
    "sg:province":"TX",
    "wof:name":"Titus Technologies LLC",
    "wof:placetype":"venue"
},
  "geometry": {"coordinates":[-96.94000800000001,29.448392],"type":"Point"}
}