{
  "type": "Feature",
  "properties": {
    "iso:country":"US",
    "sg:address":"16903 Red Oak Dr",
    "sg:city":"Houston",
    "sg:classifiers":[
        {
            "category":"Shopping",
            "subcategory":"Gifts & Souvenirs",
            "type":"Retail Goods"
        }
    ],
    "sg:phone":"+1 281 528 7329",
    "sg:postcode":"77090",
    "sg:province":"TX",
    "sg:tags":[
        "shop"
    ],
    "wof:name":"Laster & Mc Kenzie",
    "wof:placetype":"venue"
},
  "geometry": {"coordinates":[-95.44608599999999,30.020341],"type":"Point"}
}