{
  "type": "Feature",
  "properties": {
    "iso:country":"US",
    "sg:address":"7051 C F Hawn Fwy",
    "sg:city":"Dallas",
    "sg:classifiers":[
        {
            "category":"Autos & Motor Vehicles",
            "subcategory":"Automobile Sales",
            "type":"Retail Goods"
        }
    ],
    "sg:phone":"+1 972 674 2770",
    "sg:postcode":"75217",
    "sg:province":"TX",
    "sg:tags":[
        "new",
        "used",
        "car"
    ],
    "wof:name":"Easy Credit Auto Sales",
    "wof:placetype":"venue"
},
  "geometry": {"coordinates":[-96.701599,32.724873],"type":"Point"}
}