{
  "type": "Feature",
  "properties": {
    "iso:country":"US",
    "sg:address":"2309 Sha Ln",
    "sg:city":"Breckenridge",
    "sg:classifiers":[
        {
            "category":"Mining & Drilling",
            "type":"Manufacturing & Wholesale Goods"
        }
    ],
    "sg:phone":"+1 254 559 6584",
    "sg:postcode":"76424",
    "sg:province":"TX",
    "sg:tags":[
        "field"
    ],
    "wof:name":"Bandy Geophysical",
    "wof:placetype":"venue"
},
  "geometry": {"coordinates":[-98.935767,32.759563],"type":"Point"}
}