{
  "type": "Feature",
  "properties": {
    "iso:country":"US",
    "sg:address":"11507 Harry Hines Blvd",
    "sg:city":"Dallas",
    "sg:classifiers":[
        {
            "category":"Retail",
            "subcategory":"Auto Repair",
            "type":"Services"
        }
    ],
    "sg:phone":"+1 972 620 5100",
    "sg:postcode":"75229",
    "sg:province":"TX",
    "wof:name":"D & L Vehicle Sales Inc",
    "wof:placetype":"venue"
},
  "geometry": {"coordinates":[-96.89290099999999,32.899832],"type":"Point"}
}