{
  "type": "Feature",
  "properties": {
    "iso:country":"US",
    "sg:address":"919 Isom Rd",
    "sg:city":"San Antonio",
    "sg:classifiers":[
        {
            "category":"Manufacturing",
            "subcategory":"Tools & Machinery",
            "type":"Manufacturing & Wholesale Goods"
        }
    ],
    "sg:phone":"+1 210 349 3771",
    "sg:postcode":"78216",
    "sg:province":"TX",
    "sg:tags":[
        "field",
        "oil",
        "equipment"
    ],
    "wof:name":"Petroleum Analyzer Co LP",
    "wof:placetype":"venue"
},
  "geometry": {"coordinates":[-98.484336,29.536526],"type":"Point"}
}