{
  "type": "Feature",
  "properties": {
    "iso:country":"US",
    "sg:address":"4620 Yellow Rose Trl",
    "sg:city":"Austin",
    "sg:classifiers":[
        {
            "category":"Professional",
            "type":"Services"
        }
    ],
    "sg:phone":"+1 512 892 4492",
    "sg:postcode":"78749",
    "sg:province":"TX",
    "wof:name":"Briscoe Studio",
    "wof:placetype":"venue"
},
  "geometry": {"coordinates":[-97.838998,30.227563],"type":"Point"}
}