{
  "type": "Feature",
  "properties": {
    "iso:country":"US",
    "sg:address":"8218 Broken Branch Dr",
    "sg:city":"Round Rock",
    "sg:classifiers":[
        {
            "category":"Recreation",
            "type":"Entertainment"
        }
    ],
    "sg:phone":"+1 512 828 4096",
    "sg:postcode":"78681",
    "sg:province":"TX",
    "sg:tags":[
        "club",
        "membership"
    ],
    "wof:name":"Pro Fitness Solutions",
    "wof:placetype":"venue"
},
  "geometry": {"coordinates":[-97.723001,30.513208],"type":"Point"}
}