{
  "type": "Feature",
  "properties": {
    "iso:country":"US",
    "sg:address":"1724 Airline Dr",
    "sg:city":"Katy",
    "sg:classifiers":[
        {
            "category":"Professional",
            "type":"Services"
        }
    ],
    "sg:phone":"+1 281 391 8068",
    "sg:postcode":"77493",
    "sg:province":"TX",
    "wof:name":"Personal Touch Embroidery",
    "wof:placetype":"venue"
},
  "geometry": {"coordinates":[-95.81830100000001,29.797176],"type":"Point"}
}