{
  "type": "Feature",
  "properties": {
    "iso:country":"US",
    "sg:address":"7250 Gulf Fwy",
    "sg:city":"Houston",
    "sg:classifiers":[
        {
            "category":"Autos & Motor Vehicles",
            "subcategory":"Automobile Sales",
            "type":"Retail Goods"
        }
    ],
    "sg:phone":"+1 713 641 8100",
    "sg:postcode":"77017",
    "sg:province":"TX",
    "sg:tags":[
        "truck"
    ],
    "wof:name":"Allen Samuels Auto Group",
    "wof:placetype":"venue"
},
  "geometry": {"coordinates":[-95.250998,29.651766],"type":"Point"}
}