{
  "type": "Feature",
  "properties": {
    "iso:country":"US",
    "sg:address":"7305 Brookfield Dr",
    "sg:city":"Amarillo",
    "sg:classifiers":[
        {
            "category":"Building & Trades",
            "subcategory":"Equipment Rental",
            "type":"Services"
        }
    ],
    "sg:phone":"+1 806 355 3555",
    "sg:postcode":"79124",
    "sg:province":"TX",
    "wof:name":"Leisure Leasing Motor HM Rentl",
    "wof:placetype":"venue"
},
  "geometry": {"coordinates":[-101.92085,35.233987],"type":"Point"}
}