{
  "type": "Feature",
  "properties": {
    "iso:country":"US",
    "sg:address":"2121 Hepburn St",
    "sg:city":"Houston",
    "sg:classifiers":[
        {
            "category":"Food & Beverages",
            "subcategory":"Groceries & Convenience Stores",
            "type":"Retail Goods"
        }
    ],
    "sg:phone":"+1 713 795 0380",
    "sg:postcode":"77054",
    "sg:province":"TX",
    "sg:tags":[
        "coin",
        "laundry"
    ],
    "wof:name":"Wah Lee Food Market",
    "wof:placetype":"venue"
},
  "geometry": {"coordinates":[-95.390224,29.692019],"type":"Point"}
}