{
  "type": "Feature",
  "properties": {
    "iso:country":"US",
    "sg:address":"49 Li Linoe Ln",
    "sg:city":"Sadler",
    "sg:classifiers":[
        {
            "category":"Retail",
            "subcategory":"Repair Shop",
            "type":"Services"
        }
    ],
    "sg:phone":"+1 903 523 4286",
    "sg:postcode":"76264",
    "sg:province":"TX",
    "sg:tags":[
        "upholsterer"
    ],
    "wof:name":"Sonny's Upholstery",
    "wof:placetype":"venue"
},
  "geometry": {"coordinates":[-96.82004999999999,33.781504],"type":"Point"}
}