{
  "type": "Feature",
  "properties": {
    "iso:country":"US",
    "sg:address":"8694 Skillman St",
    "sg:city":"Dallas",
    "sg:classifiers":[
        {
            "category":"Personal",
            "subcategory":"Beauty Salon",
            "type":"Services"
        }
    ],
    "sg:phone":"+1 214 349 3600",
    "sg:postcode":"75243",
    "sg:province":"TX",
    "sg:tags":[
        "shop"
    ],
    "wof:name":"Tiffany's Hair Design",
    "wof:placetype":"venue"
},
  "geometry": {"coordinates":[-96.724177,32.894575],"type":"Point"}
}