{
  "type": "Feature",
  "properties": {
    "iso:country":"US",
    "sg:address":"1661 Gessner Dr",
    "sg:city":"Houston",
    "sg:classifiers":[
        {
            "category":"Personal",
            "subcategory":"Psychics & Astrologers",
            "type":"Services"
        }
    ],
    "sg:phone":"+1 713 932 7754",
    "sg:postcode":"77080",
    "sg:province":"TX",
    "sg:tags":[
        "medium"
    ],
    "wof:name":"Mrs Temple Psychic Reader",
    "wof:placetype":"venue"
},
  "geometry": {"coordinates":[-95.544937,29.802677],"type":"Point"}
}