{
  "type": "Feature",
  "properties": {
    "iso:country":"US",
    "sg:address":"2701 Padre Blvd",
    "sg:city":"S Padre Island",
    "sg:classifiers":[
        {
            "category":"Banks & Credit Unions",
            "subcategory":"Bank",
            "type":"Services"
        }
    ],
    "sg:phone":"+1 956 761 8589",
    "sg:postcode":"78597",
    "sg:province":"TX",
    "wof:name":"South Padre Bank",
    "wof:placetype":"venue"
},
  "geometry": {"coordinates":[-97.168426,26.10464],"type":"Point"}
}