{
  "type": "Feature",
  "properties": {
    "iso:country":"US",
    "sg:address":"12765 Indian Hill Rd",
    "sg:city":"Amarillo",
    "sg:classifiers":[
        {
            "category":"Building & Trades",
            "subcategory":"Equipment Rental",
            "type":"Services"
        }
    ],
    "sg:phone":"+1 806 352 8001",
    "sg:postcode":"79124",
    "sg:province":"TX",
    "sg:tags":[
        "compressor"
    ],
    "wof:name":"Rankins Co",
    "wof:placetype":"venue"
},
  "geometry": {"coordinates":[-101.992341,35.191559],"type":"Point"}
}