{
  "type": "Feature",
  "properties": {
    "iso:country":"US",
    "sg:address":"2279 Collins Rd",
    "sg:city":"Denton",
    "sg:classifiers":[
        {
            "category":"Manufacturing",
            "subcategory":"Wood Products",
            "type":"Manufacturing & Wholesale Goods"
        }
    ],
    "sg:phone":"+1 972 436 8815",
    "sg:postcode":"76208",
    "sg:province":"TX",
    "sg:tags":[
        "manufacture",
        "marble"
    ],
    "wof:name":"Nor-Tex Kitchen & Bath",
    "wof:placetype":"venue"
},
  "geometry": {"coordinates":[-97.061545,33.246764],"type":"Point"}
}