{
  "type": "Feature",
  "properties": {
    "iso:country":"US",
    "sg:address":"2619 Stapleford Dr",
    "sg:city":"Cedar Park",
    "sg:classifiers":[
        {
            "category":"Building & Trades",
            "subcategory":"Landscaping Services",
            "type":"Services"
        }
    ],
    "sg:phone":"+1 512 260 5300",
    "sg:postcode":"78613",
    "sg:province":"TX",
    "sg:tags":[
        "designer",
        "landscape"
    ],
    "wof:name":"True Blue Land Design",
    "wof:placetype":"venue"
},
  "geometry": {"coordinates":[-97.84355100000001,30.540124],"type":"Point"}
}