{
  "type": "Feature",
  "properties": {
    "iso:country":"US",
    "sg:address":"30 Cherry Hills St",
    "sg:city":"Abilene",
    "sg:classifiers":[
        {
            "category":"Shopping",
            "subcategory":"Florist",
            "type":"Retail Goods"
        }
    ],
    "sg:phone":"+1 325 677 8506",
    "sg:postcode":"79606",
    "sg:province":"TX",
    "wof:name":"University Florist",
    "wof:placetype":"venue"
},
  "geometry": {"coordinates":[-99.75324000000001,32.373962],"type":"Point"}
}