{
  "type": "Feature",
  "properties": {
    "iso:country":"US",
    "sg:address":"11052 Briar Forest Dr",
    "sg:city":"Houston",
    "sg:classifiers":[
        {
            "category":"Retail",
            "subcategory":"Photofinishing",
            "type":"Services"
        }
    ],
    "sg:phone":"+1 713 266 5906",
    "sg:postcode":"77042",
    "sg:province":"TX",
    "sg:tags":[
        "laboratory"
    ],
    "wof:name":"Bonanza Photo",
    "wof:placetype":"venue"
},
  "geometry": {"coordinates":[-95.571479,29.74802],"type":"Point"}
}