{
  "type": "Feature",
  "properties": {
    "iso:country":"US",
    "sg:address":"1303 Clark St",
    "sg:city":"Round Rock",
    "sg:classifiers":[
        {
            "category":"Wholesale",
            "subcategory":"Machinery & Supplies",
            "type":"Manufacturing & Wholesale Goods"
        }
    ],
    "sg:phone":"+1 512 244 7535",
    "sg:postcode":"78681",
    "sg:province":"TX",
    "sg:tags":[
        "hardware",
        "industrial"
    ],
    "wof:name":"Sunbelt Fasteners",
    "wof:placetype":"venue"
},
  "geometry": {"coordinates":[-97.697461,30.516785],"type":"Point"}
}