{
  "type": "Feature",
  "properties": {
    "iso:country":"US",
    "sg:address":"772 Magnolia Ave",
    "sg:city":"Port Neches",
    "sg:classifiers":[
        {
            "category":"Restaurant",
            "type":"Food & Drink"
        }
    ],
    "sg:menulink":"http://www.allmenus.com/tx/east-jefferson/204342-sonic/menu/",
    "sg:phone":"+1 409 727 7011",
    "sg:postcode":"77651",
    "sg:province":"TX",
    "sg:tags":[
        "burger",
        "american"
    ],
    "wof:name":"Sonic",
    "wof:placetype":"venue"
},
  "geometry": {"coordinates":[-93.955664,29.975729],"type":"Point"}
}