{
  "type": "Feature",
  "properties": {
    "iso:country":"US",
    "sg:address":"3921 Kelsey Ct",
    "sg:city":"Grapevine",
    "sg:classifiers":[
        {
            "category":"Organizations",
            "subcategory":"Membership Organization",
            "type":"Services"
        }
    ],
    "sg:phone":"+1 817 424 0228",
    "sg:postcode":"76051",
    "sg:province":"TX",
    "wof:name":"Childrens Intl Toy Chest",
    "wof:placetype":"venue"
},
  "geometry": {"coordinates":[-97.112104,32.895941],"type":"Point"}
}