{
  "type": "Feature",
  "properties": {
    "iso:country":"US",
    "sg:address":"4401 E Stagecoach Rd",
    "sg:city":"Killeen",
    "sg:classifiers":[
        {
            "category":"Building & Trades",
            "subcategory":"Construction",
            "type":"Services"
        }
    ],
    "sg:phone":"+1 254 519 1735",
    "sg:postcode":"76542",
    "sg:province":"TX",
    "sg:tags":[
        "manufactured",
        "housing-communities"
    ],
    "wof:name":"Morning Sun Mobile Home Park",
    "wof:placetype":"venue"
},
  "geometry": {"coordinates":[-97.709152,31.05477],"type":"Point"}
}