{
  "type": "Feature",
  "properties": {
    "iso:country":"US",
    "sg:address":"808 Spence St",
    "sg:city":"Austin",
    "sg:classifiers":[
        {
            "category":"Building & Trades",
            "subcategory":"Landscaping Services",
            "type":"Services"
        }
    ],
    "sg:phone":"+1 512 474 5265",
    "sg:postcode":"78702",
    "sg:province":"TX",
    "sg:tags":[
        "landscape"
    ],
    "wof:name":"Holy Water Landscaping",
    "wof:placetype":"venue"
},
  "geometry": {"coordinates":[-97.735457,30.258906],"type":"Point"}
}