{
  "type": "Feature",
  "properties": {
    "iso:country":"US",
    "sg:address":"9819 Marek Dr",
    "sg:city":"Houston",
    "sg:classifiers":[
        {
            "category":"Organizations",
            "subcategory":"Religious Organization",
            "type":"Services"
        }
    ],
    "sg:phone":"+1 281 820 3732",
    "sg:postcode":"77038",
    "sg:province":"TX",
    "sg:tags":[
        "monastery",
        "convent"
    ],
    "wof:name":"Missionary Carmelite Sisters",
    "wof:placetype":"venue"
},
  "geometry": {"coordinates":[-95.416571,29.906477],"type":"Point"}
}