{
  "type": "Feature",
  "properties": {
    "iso:country":"US",
    "sg:address":"8701 W Parmer Ln Apt 8320",
    "sg:city":"Austin",
    "sg:classifiers":[
        {
            "category":"Professional",
            "subcategory":"Printing & Photocopies",
            "type":"Services"
        }
    ],
    "sg:phone":"+1 512 249 6634",
    "sg:postcode":"78729",
    "sg:province":"TX",
    "sg:tags":[
        "photographers-commercial"
    ],
    "wof:name":"Saulmanphotos.Com",
    "wof:placetype":"venue"
},
  "geometry": {"coordinates":[-97.761303,30.467929],"type":"Point"}
}