{
  "type": "Feature",
  "properties": {
    "iso:country":"US",
    "sg:address":"10055 Grogans Mill Rd",
    "sg:city":"Spring",
    "sg:classifiers":[
        {
            "category":"Banks & Credit Unions",
            "subcategory":"Investment Brokerage",
            "type":"Services"
        }
    ],
    "sg:phone":"+1 281 292 0229",
    "sg:postcode":"77380",
    "sg:province":"TX",
    "wof:name":"Gamma Capital Svc Inc",
    "wof:placetype":"venue"
},
  "geometry": {"coordinates":[-95.47050400000001,30.159316],"type":"Point"}
}