{
  "type": "Feature",
  "properties": {
    "iso:country":"US",
    "sg:address":"5996 Whitby Rd",
    "sg:city":"San Antonio",
    "sg:classifiers":[
        {
            "category":"Health Services",
            "subcategory":"Nursing And Care Facility",
            "type":"Services"
        }
    ],
    "sg:phone":"+1 210 561 9500",
    "sg:postcode":"78240",
    "sg:province":"TX",
    "wof:name":"Sterling House of Whitby",
    "wof:placetype":"venue"
},
  "geometry": {"coordinates":[-98.60906,29.52223],"type":"Point"}
}