{
  "type": "Feature",
  "properties": {
    "iso:country":"US",
    "sg:address":"505 Chestnut St",
    "sg:city":"Colorado City",
    "sg:classifiers":[
        {
            "category":"Government",
            "subcategory":"Office",
            "type":"Public Place"
        }
    ],
    "sg:phone":"+1 325 728 5701",
    "sg:postcode":"79512",
    "sg:province":"TX",
    "wof:name":"Veterans County Svc Office",
    "wof:placetype":"venue"
},
  "geometry": {"coordinates":[-100.86429200000001,32.392573],"type":"Point"}
}