{
  "type": "Feature",
  "properties": {
    "iso:country":"US",
    "sg:address":"2304 English Oak Dr",
    "sg:city":"Arlington",
    "sg:classifiers":[
        {
            "category":"Banks & Credit Unions",
            "subcategory":"Bank",
            "type":"Services"
        }
    ],
    "sg:phone":"+1 817 469 9596",
    "sg:postcode":"76016",
    "sg:province":"TX",
    "sg:tags":[
        "loan",
        "real estate"
    ],
    "wof:name":"American Promise Mortgage Inc",
    "wof:placetype":"venue"
},
  "geometry": {"coordinates":[-97.20232900000001,32.710365],"type":"Point"}
}