{
  "type": "Feature",
  "properties": {
    "iso:country":"US",
    "sg:address":"11217 Wilding Ln",
    "sg:city":"Houston",
    "sg:classifiers":[
        {
            "category":"Professional",
            "subcategory":"Accounting & Tax Preparation",
            "type":"Services"
        }
    ],
    "sg:phone":"+1 713 463 7434",
    "sg:postcode":"77024",
    "sg:province":"TX",
    "wof:name":"Kenneth Miller",
    "wof:placetype":"venue"
},
  "geometry": {"coordinates":[-95.510476,29.774695],"type":"Point"}
}