{
  "type": "Feature",
  "properties": {
    "iso:country":"US",
    "sg:address":"3709 Irvin Dr",
    "sg:city":"Midland",
    "sg:classifiers":[
        {
            "category":"Mining & Drilling",
            "type":"Manufacturing & Wholesale Goods"
        }
    ],
    "sg:phone":"+1 432 683 8525",
    "sg:postcode":"79705",
    "sg:province":"TX",
    "sg:tags":[
        "field"
    ],
    "wof:name":"Golson Enterprises",
    "wof:placetype":"venue"
},
  "geometry": {"coordinates":[-102.04628099999999,32.042697],"type":"Point"}
}