{
  "type": "Feature",
  "properties": {
    "iso:country":"US",
    "sg:address":"1020 Northville St",
    "sg:city":"Houston",
    "sg:classifiers":[
        {
            "category":"Wholesale",
            "subcategory":"Auto Parts",
            "type":"Manufacturing & Wholesale Goods"
        }
    ],
    "sg:phone":"+1 281 447 8634",
    "sg:postcode":"77038",
    "sg:province":"TX",
    "sg:tags":[
        "used"
    ],
    "wof:name":"Off The Shelf",
    "wof:placetype":"venue"
},
  "geometry": {"coordinates":[-95.419122,29.908798],"type":"Point"}
}