{
  "type": "Feature",
  "properties": {
    "iso:country":"US",
    "sg:address":"9220 Spicebrush Dr",
    "sg:city":"Austin",
    "sg:classifiers":[
        {
            "category":"Real Estate",
            "subcategory":"Real Estate Agent",
            "type":"Services"
        }
    ],
    "sg:phone":"+1 512 343 7730",
    "sg:postcode":"78759",
    "sg:province":"TX",
    "sg:website":"www.brokerbrad.com",
    "wof:name":"BROKERBRAD.COM",
    "wof:placetype":"venue"
},
  "geometry": {"coordinates":[-97.773072,30.398861],"type":"Point"}
}