{
  "type": "Feature",
  "properties": {
    "iso:country":"US",
    "sg:address":"337 Miles St",
    "sg:city":"Hereford",
    "sg:classifiers":[
        {
            "category":"Wholesale",
            "subcategory":"Machinery & Supplies",
            "type":"Manufacturing & Wholesale Goods"
        }
    ],
    "sg:phone":"+1 806 363 2700",
    "sg:postcode":"79045",
    "sg:province":"TX",
    "sg:tags":[
        "casket"
    ],
    "wof:name":"Caskets & Monuments Outlet",
    "wof:placetype":"venue"
},
  "geometry": {"coordinates":[-102.400927,34.816734],"type":"Point"}
}