{
  "type": "Feature",
  "properties": {
    "iso:country":"US",
    "sg:address":"13645 Murphy Rd",
    "sg:city":"Stafford",
    "sg:classifiers":[
        {
            "category":"Shopping",
            "subcategory":"Used Merchandise",
            "type":"Retail Goods"
        }
    ],
    "sg:phone":"+1 281 403 9894",
    "sg:postcode":"77477",
    "sg:province":"TX",
    "sg:tags":[
        "book",
        "rare",
        "dealer"
    ],
    "wof:name":"College Book Store",
    "wof:placetype":"venue"
},
  "geometry": {"coordinates":[-95.564716,29.625369],"type":"Point"}
}