{
  "type": "Feature",
  "properties": {
    "iso:country":"US",
    "sg:address":"236 E Nopal St",
    "sg:city":"Uvalde",
    "sg:classifiers":[
        {
            "category":"Shopping",
            "type":"Retail Goods"
        }
    ],
    "sg:phone":"+1 830 278 3747",
    "sg:postcode":"78801",
    "sg:province":"TX",
    "sg:tags":[
        "farm",
        "supply"
    ],
    "wof:name":"Texas Farm Store",
    "wof:placetype":"venue"
},
  "geometry": {"coordinates":[-99.783388,29.212185],"type":"Point"}
}