{
  "type": "Feature",
  "properties": {
    "iso:country":"US",
    "sg:address":"1614 Finfeather Rd",
    "sg:city":"Bryan",
    "sg:classifiers":[
        {
            "category":"Farming",
            "subcategory":"Poultry Farm",
            "type":"Manufacturing & Wholesale Goods"
        }
    ],
    "sg:phone":"+1 979 822 3781",
    "sg:postcode":"77801",
    "sg:province":"TX",
    "sg:website":"www.hyline.com",
    "wof:name":"Hy-Line International",
    "wof:placetype":"venue"
},
  "geometry": {"coordinates":[-96.37559,30.653753],"type":"Point"}
}