{
  "type": "Feature",
  "properties": {
    "iso:country":"US",
    "sg:address":"115 N Leggett Dr",
    "sg:city":"Abilene",
    "sg:classifiers":[
        {
            "category":"Insurance",
            "subcategory":"Insurance Agent",
            "type":"Services"
        },
        {
            "category":"Insurance",
            "subcategory":"Hazard Insurance",
            "type":"Services"
        },
        {
            "category":"Insurance",
            "subcategory":"Title Insurance",
            "type":"Services"
        },
        {
            "category":"Insurance",
            "subcategory":"Life Insurance",
            "type":"Services"
        }
    ],
    "sg:phone":"+1 325 676 3131",
    "sg:postcode":"79603",
    "sg:province":"TX",
    "sg:tags":[
        "business",
        "auto",
        "commercial",
        "homeowner",
        "motorcycle",
        "renter"
    ],
    "wof:name":"Allstate Insurance Company - Ricki Stanley",
    "wof:placetype":"venue"
},
  "geometry": {"coordinates":[-99.77030499999999,32.452045],"type":"Point"}
}