{
  "type": "Feature",
  "properties": {
    "iso:country":"US",
    "sg:address":"811 S Main St",
    "sg:city":"Hereford",
    "sg:classifiers":[
        {
            "category":"Restaurant",
            "type":"Food & Drink"
        }
    ],
    "sg:phone":"+1 806 364 7772",
    "sg:postcode":"79045",
    "sg:province":"TX",
    "sg:tags":[
        "eating"
    ],
    "wof:name":"Pizza Mill & Sub Factory",
    "wof:placetype":"venue"
},
  "geometry": {"coordinates":[-102.39278299999999,34.806593],"type":"Point"}
}