{
  "type": "Feature",
  "properties": {
    "iso:country":"US",
    "sg:address":"13224 Saratoga Ln",
    "sg:city":"Mesquite",
    "sg:classifiers":[
        {
            "category":"Manufacturing",
            "subcategory":"Tools & Machinery",
            "type":"Manufacturing & Wholesale Goods"
        }
    ],
    "sg:phone":"+1 972 286 8534",
    "sg:postcode":"75180",
    "sg:province":"TX",
    "sg:tags":[
        "mfg",
        "apparatus",
        "welding"
    ],
    "wof:name":"Jose J Munoz",
    "wof:placetype":"venue"
},
  "geometry": {"coordinates":[-96.599025,32.720352],"type":"Point"}
}