{
  "type": "Feature",
  "properties": {
    "iso:country":"US",
    "sg:address":"4407 Bouvet Ct",
    "sg:city":"Austin",
    "sg:classifiers":[
        {
            "category":"Shopping",
            "subcategory":"Hobbies, Toys, & Games",
            "type":"Retail Goods"
        }
    ],
    "sg:phone":"+1 512 837 6627",
    "sg:postcode":"78727",
    "sg:province":"TX",
    "sg:tags":[
        "supply"
    ],
    "wof:name":"Perfect Timing Ltd",
    "wof:placetype":"venue"
},
  "geometry": {"coordinates":[-97.72303599999999,30.422634],"type":"Point"}
}