{
  "type": "Feature",
  "properties": {
    "iso:country":"US",
    "sg:address":"155 Cypresswood Dr",
    "sg:city":"Spring",
    "sg:classifiers":[
        {
            "category":"Retail",
            "subcategory":"Portrait Studio",
            "type":"Services"
        }
    ],
    "sg:phone":"+1 281 350 5400",
    "sg:postcode":"77388",
    "sg:province":"TX",
    "sg:tags":[
        "photographer",
        "photo"
    ],
    "sg:website":"www.gmichaelphoto.com",
    "wof:name":"G Michael Photography & Assoc",
    "wof:placetype":"venue"
},
  "geometry": {"coordinates":[-95.43378,30.052754],"type":"Point"}
}