{
  "type": "Feature",
  "properties": {
    "iso:country":"US",
    "sg:address":"405 5th St",
    "sg:city":"Valley Mills",
    "sg:classifiers":[
        {
            "category":"Education",
            "subcategory":"Library",
            "type":"Public Place"
        }
    ],
    "sg:phone":"+1 254 932 6370",
    "sg:postcode":"76689",
    "sg:province":"TX",
    "wof:name":"Valley Mills Public Library",
    "wof:placetype":"venue"
},
  "geometry": {"coordinates":[-97.471639,31.658003],"type":"Point"}
}