{
  "type": "Feature",
  "properties": {
    "iso:country":"US",
    "sg:address":"142 44th St",
    "sg:city":"Corpus Christi",
    "sg:classifiers":[
        {
            "category":"Mining & Drilling",
            "type":"Manufacturing & Wholesale Goods"
        }
    ],
    "sg:phone":"+1 361 883 8100",
    "sg:postcode":"78405",
    "sg:province":"TX",
    "sg:tags":[
        "oil",
        "well"
    ],
    "wof:name":"Target Well Svc Inc",
    "wof:placetype":"venue"
},
  "geometry": {"coordinates":[-97.442044,27.782958],"type":"Point"}
}