{
  "type": "Feature",
  "properties": {
    "iso:country":"US",
    "sg:address":"1 State Hwy 146",
    "sg:city":"Hardin",
    "sg:classifiers":[
        {
            "category":"Organizations",
            "subcategory":"Community Association",
            "type":"Services"
        }
    ],
    "sg:phone":"+1 936 298 3628",
    "sg:postcode":"77590",
    "sg:province":"TX",
    "wof:name":"Hardin Lions Club",
    "wof:placetype":"venue"
},
  "geometry": {"coordinates":[-94.95107899999999,29.384469],"type":"Point"}
}