{
  "type": "Feature",
  "properties": {
    "iso:country":"US",
    "sg:address":"524 Pasadena Blvd",
    "sg:city":"Pasadena",
    "sg:classifiers":[
        {
            "category":"Health Services",
            "subcategory":"Doctor",
            "type":"Services"
        }
    ],
    "sg:phone":"+1 713 473 4455",
    "sg:postcode":"77506",
    "sg:province":"TX",
    "sg:tags":[
        "medical"
    ],
    "wof:name":"Leach Neville Gary",
    "wof:placetype":"venue"
},
  "geometry": {"coordinates":[-95.20106699999999,29.703235],"type":"Point"}
}