{
  "type": "Feature",
  "properties": {
    "iso:country":"US",
    "sg:address":"555 Butterfield Rd",
    "sg:city":"Houston",
    "sg:classifiers":[
        {
            "category":"Shopping",
            "subcategory":"Department Store",
            "type":"Retail Goods"
        }
    ],
    "sg:phone":"+1 281 876 2923",
    "sg:postcode":"77090",
    "sg:province":"TX",
    "wof:name":"Texas 99 Cents Inc",
    "wof:placetype":"venue"
},
  "geometry": {"coordinates":[-95.436538,30.016218],"type":"Point"}
}