{
  "type": "Feature",
  "properties": {
    "iso:country":"US",
    "sg:address":"3200 E Randol Mill Rd",
    "sg:city":"Arlington",
    "sg:classifiers":[
        {
            "category":"Autos & Motor Vehicles",
            "subcategory":"Automobile Sales",
            "type":"Retail Goods"
        }
    ],
    "sg:phone":"+1 817 522 0237",
    "sg:postcode":"76011",
    "sg:province":"TX",
    "sg:tags":[
        "car",
        "dealer"
    ],
    "wof:name":"Sunday Side Motors",
    "wof:placetype":"venue"
},
  "geometry": {"coordinates":[-97.05018699999999,32.748913],"type":"Point"}
}