{
  "type": "Feature",
  "properties": {
    "iso:country":"US",
    "sg:address":"1714 Matamoros St",
    "sg:city":"Laredo",
    "sg:classifiers":[
        {
            "category":"Freight",
            "type":"Transportation"
        }
    ],
    "sg:phone":"+1 956 728 0984",
    "sg:postcode":"78040",
    "sg:province":"TX",
    "sg:tags":[
        "broker",
        "customs"
    ],
    "wof:name":"Mario O Tello",
    "wof:placetype":"venue"
},
  "geometry": {"coordinates":[-99.51317299999999,27.506506],"type":"Point"}
}