{
  "type": "Feature",
  "properties": {
    "iso:country":"US",
    "sg:address":"1900 Preston Road Suite 343",
    "sg:city":"Plano",
    "sg:classifiers":[
        {
            "category":"Restaurant",
            "type":"Food & Drink"
        }
    ],
    "sg:phone":"+1 972 964 2200",
    "sg:postcode":"75093",
    "sg:province":"TX",
    "sg:tags":[
        "italian"
    ],
    "sg:website":"www.patrizios.net/",
    "wof:name":"Patrizio's",
    "wof:placetype":"venue"
},
  "geometry": {"coordinates":[-96.788619,33.025415],"type":"Point"}
}