{
  "type": "Feature",
  "properties": {
    "iso:country":"US",
    "sg:address":"2458 Freeman St",
    "sg:city":"Houston",
    "sg:classifiers":[
        {
            "category":"Personal",
            "subcategory":"Barber",
            "type":"Services"
        }
    ],
    "sg:phone":"+1 281 440 6557",
    "sg:postcode":"77009",
    "sg:province":"TX",
    "sg:tags":[
        "shop"
    ],
    "wof:name":"Looks Barber & Styling Center",
    "wof:placetype":"venue"
},
  "geometry": {"coordinates":[-95.363882,29.782829],"type":"Point"}
}