{
  "type": "Feature",
  "properties": {
    "iso:country":"US",
    "sg:address":"408 W Main St",
    "sg:city":"Weimar",
    "sg:classifiers":[
        {
            "category":"Restaurant",
            "type":"Food & Drink"
        }
    ],
    "sg:phone":"+1 979 725 6510",
    "sg:postcode":"78962",
    "sg:province":"TX",
    "wof:name":"Corner Bakery",
    "wof:placetype":"venue"
},
  "geometry": {"coordinates":[-96.786722,29.703342],"type":"Point"}
}