{
  "type": "Feature",
  "properties": {
    "iso:country":"US",
    "sg:address":"566 S State Hwy 208",
    "sg:city":"Colorado City",
    "sg:classifiers":[
        {
            "category":"Farming",
            "subcategory":"Livestock Farm",
            "type":"Manufacturing & Wholesale Goods"
        }
    ],
    "sg:phone":"+1 325 728 4028",
    "sg:postcode":"79512",
    "sg:province":"TX",
    "sg:tags":[
        "beef",
        "feedlot",
        "cattle"
    ],
    "wof:name":"Wood Land & Cattle Co",
    "wof:placetype":"venue"
},
  "geometry": {"coordinates":[-100.836116,32.37969],"type":"Point"}
}