{
  "type": "Feature",
  "properties": {
    "iso:country":"US",
    "sg:address":"8744 Westpark Dr",
    "sg:city":"Houston",
    "sg:classifiers":[
        {
            "category":"Shopping",
            "subcategory":"Stationery & Office Supplies",
            "type":"Retail Goods"
        }
    ],
    "sg:phone":"+1 800 460 8900",
    "sg:postcode":"77063",
    "sg:province":"TX",
    "sg:tags":[
        "equipment"
    ],
    "sg:website":"www.libertyoffice.com",
    "wof:name":"Liberty Office Products",
    "wof:placetype":"venue"
},
  "geometry": {"coordinates":[-95.518204,29.721701],"type":"Point"}
}