{
  "type": "Feature",
  "properties": {
    "iso:country":"US",
    "sg:address":"11108 Plains Trl",
    "sg:city":"Austin",
    "sg:classifiers":[
        {
            "category":"Shopping",
            "subcategory":"Hobbies, Toys, & Games",
            "type":"Retail Goods"
        }
    ],
    "sg:phone":"+1 512 837 7056",
    "sg:postcode":"78758",
    "sg:province":"TX",
    "sg:tags":[
        "tile",
        "ceramic",
        "mfg"
    ],
    "wof:name":"Goertzs Creations",
    "wof:placetype":"venue"
},
  "geometry": {"coordinates":[-97.693426,30.383855],"type":"Point"}
}