{
  "type": "Feature",
  "properties": {
    "iso:country":"US",
    "sg:address":"1525 Merrimac Cir",
    "sg:city":"Fort Worth",
    "sg:classifiers":[
        {
            "category":"Real Estate",
            "subcategory":"Real Estate Agent",
            "type":"Services"
        }
    ],
    "sg:phone":"+1 817 921 2212",
    "sg:postcode":"76107",
    "sg:province":"TX",
    "wof:name":"Mitchell Properties",
    "wof:placetype":"venue"
},
  "geometry": {"coordinates":[-97.359103,32.72845],"type":"Point"}
}