{
  "type": "Feature",
  "properties": {
    "iso:country":"US",
    "sg:address":"2921 Brown Trl",
    "sg:city":"Bedford",
    "sg:classifiers":[
        {
            "category":"Health Services",
            "subcategory":"Doctor",
            "type":"Services"
        }
    ],
    "sg:phone":"+1 817 498 3022",
    "sg:postcode":"76021",
    "sg:province":"TX",
    "sg:tags":[
        "osteopathic"
    ],
    "wof:name":"James E Laughlin",
    "wof:placetype":"venue"
},
  "geometry": {"coordinates":[-97.16020899999999,32.851682],"type":"Point"}
}