{
  "type": "Feature",
  "properties": {
    "iso:country":"US",
    "sg:address":"6500 N Mesa St",
    "sg:city":"El Paso",
    "sg:classifiers":[
        {
            "category":"Government",
            "subcategory":"Fire Station",
            "type":"Public Place"
        }
    ],
    "sg:phone":"+1 915 771 1000",
    "sg:postcode":"79912",
    "sg:province":"TX",
    "sg:tags":[
        "protection"
    ],
    "wof:name":"El Paso Fire Station 22",
    "wof:placetype":"venue"
},
  "geometry": {"coordinates":[-106.540648,31.833923],"type":"Point"}
}