{
  "type": "Feature",
  "properties": {
    "iso:country":"US",
    "sg:address":"2626 Main St",
    "sg:city":"Dallas",
    "sg:classifiers":[
        {
            "category":"Manufacturing",
            "subcategory":"Tools & Machinery",
            "type":"Manufacturing & Wholesale Goods"
        }
    ],
    "sg:phone":"+1 214 939 0812",
    "sg:postcode":"75226",
    "sg:province":"TX",
    "sg:tags":[
        "machine",
        "shop",
        "engine",
        "repair"
    ],
    "wof:name":"Bruce Mc Beth Parts & Service",
    "wof:placetype":"venue"
},
  "geometry": {"coordinates":[-96.78467000000001,32.783779],"type":"Point"}
}