{
  "type": "Feature",
  "properties": {
    "iso:country":"US",
    "sg:address":"201 NW 2nd St",
    "sg:city":"Morton",
    "sg:classifiers":[
        {
            "category":"Home & Garden",
            "subcategory":"Building Materials",
            "type":"Retail Goods"
        }
    ],
    "sg:phone":"+1 806 266 5255",
    "sg:postcode":"79346",
    "sg:province":"TX",
    "sg:tags":[
        "lumber"
    ],
    "wof:name":"Higginbotham Bartlett Co",
    "wof:placetype":"venue"
},
  "geometry": {"coordinates":[-102.761539,33.727267],"type":"Point"}
}