{
  "type": "Feature",
  "properties": {
    "iso:country":"US",
    "sg:address":"8004 Main St",
    "sg:city":"N Richland Hills",
    "sg:classifiers":[
        {
            "category":"Building & Trades",
            "subcategory":"Construction",
            "type":"Services"
        }
    ],
    "sg:phone":"+1 817 498 9810",
    "sg:postcode":"76180",
    "sg:province":"TX",
    "sg:tags":[
        "home",
        "builder"
    ],
    "sg:website":"www.cdhomes.net",
    "wof:name":"Custom Design Homes",
    "wof:placetype":"venue"
},
  "geometry": {"coordinates":[-97.208573,32.86709],"type":"Point"}
}