{
  "type": "Feature",
  "properties": {
    "iso:country":"US",
    "sg:address":"8335 Bonner Dr",
    "sg:city":"Houston",
    "sg:classifiers":[
        {
            "category":"Insurance",
            "subcategory":"Insurance Agent",
            "type":"Services"
        }
    ],
    "sg:phone":"+1 713 643 8579",
    "sg:postcode":"77017",
    "sg:province":"TX",
    "wof:name":"American General Life Insur",
    "wof:placetype":"venue"
},
  "geometry": {"coordinates":[-95.260057,29.684124],"type":"Point"}
}