{
  "type": "Feature",
  "properties": {
    "iso:country":"US",
    "sg:address":"8004 Quaker Ave",
    "sg:city":"Lubbock",
    "sg:classifiers":[
        {
            "category":"Building & Trades",
            "subcategory":"Landscaping Services",
            "type":"Services"
        }
    ],
    "sg:phone":"+1 806 791 7670",
    "sg:postcode":"79424",
    "sg:province":"TX",
    "sg:tags":[
        "landscape",
        "contractor"
    ],
    "wof:name":"Garden Works Inc",
    "wof:placetype":"venue"
},
  "geometry": {"coordinates":[-101.905053,33.521746],"type":"Point"}
}