{
  "type": "Feature",
  "properties": {
    "iso:country":"US",
    "sg:address":"323 Inverness Dr",
    "sg:city":"Roanoke",
    "sg:classifiers":[
        {
            "category":"Professional",
            "subcategory":"Art Services",
            "type":"Services"
        }
    ],
    "sg:phone":"+1 682 831 1518",
    "sg:postcode":"76262",
    "sg:province":"TX",
    "sg:tags":[
        "commercial",
        "design"
    ],
    "wof:name":"Sidecar Creative",
    "wof:placetype":"venue"
},
  "geometry": {"coordinates":[-97.171066,32.989843],"type":"Point"}
}