{
  "type": "Feature",
  "properties": {
    "iso:country":"US",
    "sg:address":"4703 Cole Ave",
    "sg:city":"Dallas",
    "sg:classifiers":[
        {
            "category":"Professional",
            "subcategory":"Advertising",
            "type":"Services"
        }
    ],
    "sg:phone":"+1 214 522 3288",
    "sg:postcode":"75205",
    "sg:province":"TX",
    "sg:tags":[
        "agency"
    ],
    "wof:name":"Radio-Active Net-Works Inc",
    "wof:placetype":"venue"
},
  "geometry": {"coordinates":[-96.787628,32.825468],"type":"Point"}
}