{
  "type": "Feature",
  "properties": {
    "iso:country":"US",
    "sg:address":"6202 Pecan Valley Dr",
    "sg:city":"San Antonio",
    "sg:classifiers":[
        {
            "category":"Food & Beverages",
            "subcategory":"Groceries & Convenience Stores",
            "type":"Retail Goods"
        }
    ],
    "sg:phone":"+1 210 333 1032",
    "sg:postcode":"78223",
    "sg:province":"TX",
    "wof:name":"For Your Convenience Inc",
    "wof:placetype":"venue"
},
  "geometry": {"coordinates":[-98.439009,29.366488],"type":"Point"}
}