{
  "type": "Feature",
  "properties": {
    "iso:country":"US",
    "sg:address":"805 Eaglecreek Dr",
    "sg:city":"Leander",
    "sg:classifiers":[
        {
            "category":"Real Estate",
            "subcategory":"Real Estate Operator",
            "type":"Services"
        }
    ],
    "sg:phone":"+1 512 259 7737",
    "sg:postcode":"78641",
    "sg:province":"TX",
    "sg:tags":[
        "building",
        "nonresidential"
    ],
    "wof:name":"White House Properties",
    "wof:placetype":"venue"
},
  "geometry": {"coordinates":[-97.87782,30.579459],"type":"Point"}
}