{
  "type": "Feature",
  "properties": {
    "iso:country":"US",
    "sg:address":"1618 N Colorado St",
    "sg:city":"San Antonio",
    "sg:classifiers":[
        {
            "category":"Retail",
            "subcategory":"Repair Shop",
            "type":"Services"
        }
    ],
    "sg:phone":"+1 210 736 0604",
    "sg:postcode":"78201",
    "sg:province":"TX",
    "wof:name":"Classic Iron Works",
    "wof:placetype":"venue"
},
  "geometry": {"coordinates":[-98.508962,29.443357],"type":"Point"}
}