{
  "type": "Feature",
  "properties": {
    "iso:country":"US",
    "sg:address":"312 E Ward St",
    "sg:city":"Refugio",
    "sg:classifiers":[
        {
            "category":"Restaurant",
            "type":"Food & Drink"
        }
    ],
    "sg:phone":"+1 361 526 2201",
    "sg:postcode":"78377",
    "sg:province":"TX",
    "sg:tags":[
        "eating"
    ],
    "wof:name":"Henrys Mexican Food",
    "wof:placetype":"venue"
},
  "geometry": {"coordinates":[-97.272693,28.303607],"type":"Point"}
}