{
  "type": "Feature",
  "properties": {
    "iso:country":"US",
    "sg:address":"2501 N Business 45",
    "sg:city":"Corsicana",
    "sg:classifiers":[
        {
            "category":"Utilities",
            "subcategory":"Refuse",
            "type":"Services"
        }
    ],
    "sg:phone":"+1 903 874 2351",
    "sg:postcode":"75110",
    "sg:province":"TX",
    "sg:tags":[
        "garbage",
        "collection"
    ],
    "wof:name":"Olympic Waste Svc",
    "wof:placetype":"venue"
},
  "geometry": {"coordinates":[-96.46459299999999,32.115184],"type":"Point"}
}