{
  "type": "Feature",
  "properties": {
    "iso:country":"US",
    "sg:address":"2801 E Randol Mill Rd",
    "sg:city":"Arlington",
    "sg:classifiers":[
        {
            "category":"Manufacturing",
            "subcategory":"Tools & Machinery",
            "type":"Manufacturing & Wholesale Goods"
        }
    ],
    "sg:phone":"+1 817 640 3037",
    "sg:postcode":"76011",
    "sg:province":"TX",
    "sg:tags":[
        "equipment",
        "printing"
    ],
    "sg:website":"www.epicproducts.com",
    "wof:name":"Epic Products",
    "wof:placetype":"venue"
},
  "geometry": {"coordinates":[-97.058296,32.748897],"type":"Point"}
}