{
  "type": "Feature",
  "properties": {
    "iso:country":"US",
    "sg:address":"800 Vis Valet",
    "sg:city":"San Antonio",
    "sg:classifiers":[
        {
            "category":"Building & Trades",
            "subcategory":"Plumbing",
            "type":"Services"
        }
    ],
    "sg:phone":"+1 210 416 4125",
    "sg:postcode":"78216",
    "sg:province":"TX",
    "sg:tags":[
        "plumbing",
        "contractor"
    ],
    "wof:name":"Salazar Custom Control Panels",
    "wof:placetype":"venue"
},
  "geometry": {"coordinates":[-98.510581,29.55968],"type":"Point"}
}