{
  "type": "Feature",
  "properties": {
    "iso:country":"US",
    "sg:address":"1506 Broughton Ave",
    "sg:city":"Odessa",
    "sg:classifiers":[
        {
            "category":"Professional",
            "type":"Services"
        }
    ],
    "sg:phone":"+1 432 332 0735",
    "sg:postcode":"79761",
    "sg:province":"TX",
    "wof:name":"Evangelina",
    "wof:placetype":"venue"
},
  "geometry": {"coordinates":[-102.36452300000001,31.827217],"type":"Point"}
}