{
  "type": "Feature",
  "properties": {
    "iso:country":"US",
    "sg:address":"910 N Central Expy Ste 150",
    "sg:city":"Dallas",
    "sg:classifiers":[
        {
            "category":"Professional",
            "subcategory":"Lawyer & Legal Services",
            "type":"Services"
        }
    ],
    "sg:phone":"+1 214 571 7199",
    "sg:postcode":"75204",
    "sg:province":"TX",
    "sg:tags":[
        "divorce",
        "law",
        "family"
    ],
    "sg:website":"www.reimerlegalservices.com",
    "wof:name":"REIMER TROY A ATTORNEY AT LAW",
    "wof:placetype":"venue"
},
  "geometry": {"coordinates":[-96.79148600000001,32.790019],"type":"Point"}
}