{
  "type": "Feature",
  "properties": {
    "iso:country":"US",
    "sg:address":"5407 Challenger Dr",
    "sg:city":"Dallas",
    "sg:classifiers":[
        {
            "category":"Education",
            "subcategory":"Vocational School",
            "type":"Public Place"
        }
    ],
    "sg:phone":"+1 214 337 6622",
    "sg:postcode":"75237",
    "sg:province":"TX",
    "sg:tags":[
        "aircraft",
        "flight",
        "sales",
        "maintenance"
    ],
    "wof:name":"Texas Aviation",
    "wof:placetype":"venue"
},
  "geometry": {"coordinates":[-96.859616,32.680256],"type":"Point"}
}