{
  "type": "Feature",
  "properties": {
    "iso:country":"US",
    "sg:address":"3105 Brookhollow Dr",
    "sg:city":"Farmers Branch",
    "sg:classifiers":[
        {
            "category":"Professional",
            "type":"Services"
        }
    ],
    "sg:phone":"+1 972 620 8775",
    "sg:postcode":"75234",
    "sg:province":"TX",
    "sg:tags":[
        "establishment"
    ],
    "wof:name":"Perfumery",
    "wof:placetype":"venue"
},
  "geometry": {"coordinates":[-96.870327,32.921626],"type":"Point"}
}