{
  "type": "Feature",
  "properties": {
    "iso:country":"US",
    "sg:address":"2421 Tangley St",
    "sg:city":"Houston",
    "sg:classifiers":[
        {
            "category":"Shopping",
            "subcategory":"Books",
            "type":"Retail Goods"
        }
    ],
    "sg:phone":"+1 713 965 2922",
    "sg:postcode":"77005",
    "sg:province":"TX",
    "sg:tags":[
        "bookstore"
    ],
    "wof:name":"The Social Book",
    "wof:placetype":"venue"
},
  "geometry": {"coordinates":[-95.415312,29.71972],"type":"Point"}
}