{
  "type": "Feature",
  "properties": {
    "iso:country":"US",
    "sg:address":"21321 Babcock Rd",
    "sg:city":"San Antonio",
    "sg:classifiers":[
        {
            "category":"Professional",
            "subcategory":"Management & Consulting",
            "type":"Services"
        }
    ],
    "sg:phone":"+1 210 695 6899",
    "sg:postcode":"78255",
    "sg:province":"TX",
    "sg:tags":[
        "marketing",
        "program"
    ],
    "wof:name":"SBC Event Marketing",
    "wof:placetype":"venue"
},
  "geometry": {"coordinates":[-98.67591400000001,29.644906],"type":"Point"}
}