{
  "type": "Feature",
  "properties": {
    "iso:country":"US",
    "sg:address":"2124 E State Hwy 31",
    "sg:city":"Corsicana",
    "sg:classifiers":[
        {
            "category":"Professional",
            "subcategory":"Research",
            "type":"Services"
        }
    ],
    "sg:phone":"+1 903 874 1188",
    "sg:postcode":"75109",
    "sg:province":"TX",
    "sg:tags":[
        "environmental",
        "ecological"
    ],
    "wof:name":"US Filter",
    "wof:placetype":"venue"
},
  "geometry": {"coordinates":[-96.442685,32.098552],"type":"Point"}
}