{
  "type": "Feature",
  "properties": {
    "iso:country":"US",
    "sg:address":"3904 Daniels Pl",
    "sg:city":"Joshua",
    "sg:classifiers":[
        {
            "category":"Building & Trades",
            "subcategory":"Construction",
            "type":"Services"
        }
    ],
    "sg:phone":"+1 817 297 6526",
    "sg:postcode":"76058",
    "sg:province":"TX",
    "sg:tags":[
        "house"
    ],
    "wof:name":"Cox Homes",
    "wof:placetype":"venue"
},
  "geometry": {"coordinates":[-97.454965,32.52838],"type":"Point"}
}