{
  "type": "Feature",
  "properties": {
    "iso:country":"US",
    "sg:address":"6201 W 34th St Ste D",
    "sg:city":"Houston",
    "sg:classifiers":[
        {
            "category":"Home & Garden",
            "subcategory":"Home Furnishings",
            "type":"Retail Goods"
        }
    ],
    "sg:phone":"+1 713 681 9200",
    "sg:postcode":"77092",
    "sg:province":"TX",
    "sg:tags":[
        "decor"
    ],
    "wof:name":"Imagine That",
    "wof:placetype":"venue"
},
  "geometry": {"coordinates":[-95.48005000000001,29.819002],"type":"Point"}
}