{
  "type": "Feature",
  "properties": {
    "iso:country":"US",
    "sg:address":"600 Regina Dr",
    "sg:city":"New Braunfels",
    "sg:classifiers":[
        {
            "category":"Manufacturing",
            "subcategory":"Motor Vehicles & Parts",
            "type":"Manufacturing & Wholesale Goods"
        }
    ],
    "sg:phone":"+1 830 822 5385",
    "sg:postcode":"78133",
    "sg:province":"TX",
    "sg:tags":[
        "mfg"
    ],
    "wof:name":"Tex Std",
    "wof:placetype":"venue"
},
  "geometry": {"coordinates":[-98.17048200000001,29.873806],"type":"Point"}
}