{
  "type": "Feature",
  "properties": {
    "iso:country":"US",
    "sg:address":"3678 Culebra Rd",
    "sg:city":"San Antonio",
    "sg:classifiers":[
        {
            "category":"Banks & Credit Unions",
            "subcategory":"Bank",
            "type":"Services"
        }
    ],
    "sg:phone":"+1 210 436 1288",
    "sg:postcode":"78228",
    "sg:province":"TX",
    "sg:tags":[
        "cashing",
        "depository",
        "check",
        "banking"
    ],
    "wof:name":"Ace Cash Express",
    "wof:placetype":"venue"
},
  "geometry": {"coordinates":[-98.574866,29.449848],"type":"Point"}
}