{
  "type": "Feature",
  "properties": {
    "iso:country":"US",
    "sg:address":"600 N Leona St",
    "sg:city":"San Antonio",
    "sg:classifiers":[
        {
            "category":"Government",
            "subcategory":"Office",
            "type":"Public Place"
        }
    ],
    "sg:phone":"+1 210 335 8964",
    "sg:postcode":"78207",
    "sg:province":"TX",
    "wof:name":"Pre-Trial Services",
    "wof:placetype":"venue"
},
  "geometry": {"coordinates":[-98.50195600000001,29.430938],"type":"Point"}
}