{
  "type": "Feature",
  "properties": {
    "iso:country":"US",
    "sg:address":"1235 N Mockingbird Ln",
    "sg:city":"Abilene",
    "sg:classifiers":[
        {
            "category":"Personal",
            "subcategory":"Tattoo Parlor",
            "type":"Services"
        }
    ],
    "sg:phone":"+1 325 672 9909",
    "sg:postcode":"79603",
    "sg:province":"TX",
    "sg:tags":[
        "tattooing"
    ],
    "wof:name":"Scott's Tattoo & Body Piercing",
    "wof:placetype":"venue"
},
  "geometry": {"coordinates":[-99.75771899999999,32.464961],"type":"Point"}
}