{
  "type": "Feature",
  "properties": {
    "iso:country":"US",
    "sg:address":"1521 Centerville Rd",
    "sg:city":"Dallas",
    "sg:classifiers":[
        {
            "category":"Retail",
            "subcategory":"Laundry & Dry Cleaning",
            "type":"Services"
        }
    ],
    "sg:phone":"+1 214 321 3140",
    "sg:postcode":"75228",
    "sg:province":"TX",
    "sg:tags":[
        "cleaner",
        "upholstery",
        "fabric",
        "protection",
        "furniture"
    ],
    "wof:name":"Quality Maintenance",
    "wof:placetype":"venue"
},
  "geometry": {"coordinates":[-96.684625,32.842999],"type":"Point"}
}