{
  "type": "Feature",
  "properties": {
    "iso:country":"US",
    "sg:address":"1201 Rio Grande St",
    "sg:city":"Austin",
    "sg:classifiers":[
        {
            "category":"Professional",
            "subcategory":"Lawyer & Legal Services",
            "type":"Services"
        }
    ],
    "sg:phone":"+1 512 499 8838",
    "sg:postcode":"78701",
    "sg:province":"TX",
    "wof:name":"Clarence A West",
    "wof:placetype":"venue"
},
  "geometry": {"coordinates":[-97.746939,30.276916],"type":"Point"}
}