{
  "type": "Feature",
  "properties": {
    "iso:country":"US",
    "sg:address":"350 Pine St",
    "sg:city":"Beaumont",
    "sg:classifiers":[
        {
            "category":"Professional",
            "subcategory":"Engineering",
            "type":"Services"
        }
    ],
    "sg:phone":"+1 409 722 7941",
    "sg:postcode":"77703",
    "sg:province":"TX",
    "sg:tags":[
        "engineer"
    ],
    "wof:name":"Cdi Engineering",
    "wof:placetype":"venue"
},
  "geometry": {"coordinates":[-94.097785,30.085637],"type":"Point"}
}