{
  "type": "Feature",
  "properties": {
    "iso:country":"US",
    "sg:address":"410 N Main Ave",
    "sg:city":"Monahans",
    "sg:classifiers":[
        {
            "category":"Personal",
            "subcategory":"Beauty Salon",
            "type":"Services"
        }
    ],
    "sg:phone":"+1 432 943 3362",
    "sg:postcode":"79756",
    "sg:province":"TX",
    "sg:tags":[
        "shop"
    ],
    "wof:name":"Northside Beauty Palace",
    "wof:placetype":"venue"
},
  "geometry": {"coordinates":[-102.89424,31.597978],"type":"Point"}
}