{
  "type": "Feature",
  "properties": {
    "iso:country":"US",
    "sg:address":"7807 Caruth Ct",
    "sg:city":"Dallas",
    "sg:classifiers":[
        {
            "category":"Building & Trades",
            "subcategory":"Construction",
            "type":"Services"
        }
    ],
    "sg:phone":"+1 214 361 2283",
    "sg:postcode":"75225",
    "sg:province":"TX",
    "sg:tags":[
        "contractor"
    ],
    "wof:name":"Bramcon Construction",
    "wof:placetype":"venue"
},
  "geometry": {"coordinates":[-96.77318099999999,32.85725],"type":"Point"}
}