{
  "type": "Feature",
  "properties": {
    "iso:country":"US",
    "sg:address":"5636 Kansas St",
    "sg:city":"Houston",
    "sg:classifiers":[
        {
            "category":"Building & Trades",
            "subcategory":"Equipment Rental",
            "type":"Services"
        }
    ],
    "sg:phone":"+1 713 868 3255",
    "sg:postcode":"77007",
    "sg:province":"TX",
    "sg:tags":[
        "pump",
        "electrician"
    ],
    "sg:website":"www.hahnequipment.com",
    "wof:name":"Hahn Equipment Co",
    "wof:placetype":"venue"
},
  "geometry": {"coordinates":[-95.423897,29.782101],"type":"Point"}
}