{
  "type": "Feature",
  "properties": {
    "iso:country":"US",
    "sg:address":"2121 Congress St",
    "sg:city":"Houston",
    "sg:classifiers":[
        {
            "category":"Shopping",
            "subcategory":"Gifts & Souvenirs",
            "type":"Retail Goods"
        },
        {
            "category":"Home & Garden",
            "subcategory":"Home Furnishings",
            "type":"Retail Goods"
        }
    ],
    "sg:phone":"+1 713 222 6121",
    "sg:postcode":"77002",
    "sg:province":"TX",
    "sg:tags":[
        "shop",
        "candle"
    ],
    "sg:website":"http://www.houstoncandleco.com",
    "wof:name":"Houston Candle Co",
    "wof:placetype":"venue"
},
  "geometry": {"coordinates":[-95.364262,29.76481],"type":"Point"}
}