{
  "type": "Feature",
  "properties": {
    "iso:country":"US",
    "sg:address":"3135 W Commerce St",
    "sg:city":"San Antonio",
    "sg:classifiers":[
        {
            "category":"Retail",
            "subcategory":"Auto Repair",
            "type":"Services"
        }
    ],
    "sg:phone":"+1 210 432 5404",
    "sg:postcode":"78207",
    "sg:province":"TX",
    "sg:tags":[
        "shop",
        "automotive",
        "general"
    ],
    "wof:name":"Dan Repair Service",
    "wof:placetype":"venue"
},
  "geometry": {"coordinates":[-98.53119599999999,29.428601],"type":"Point"}
}