{
  "type": "Feature",
  "properties": {
    "iso:country":"US",
    "sg:address":"1521 Sherwood Forest St",
    "sg:city":"Houston",
    "sg:classifiers":[
        {
            "category":"Shopping",
            "subcategory":"Clothing, Apparel, & Fashions",
            "type":"Retail Goods"
        }
    ],
    "sg:phone":"+1 713 501 8411",
    "sg:postcode":"77043",
    "sg:province":"TX",
    "wof:name":"Jjt Interests",
    "wof:placetype":"venue"
},
  "geometry": {"coordinates":[-95.579654,29.794652],"type":"Point"}
}