{
  "type": "Feature",
  "properties": {
    "iso:country":"US",
    "sg:address":"1511 University Dr E",
    "sg:city":"College Station",
    "sg:classifiers":[
        {
            "category":"Restaurant",
            "type":"Food & Drink"
        }
    ],
    "sg:phone":"+1 979 691 2100",
    "sg:postcode":"77840",
    "sg:province":"TX",
    "wof:name":"Wings N'More",
    "wof:placetype":"venue"
},
  "geometry": {"coordinates":[-96.31827199999999,30.63711],"type":"Point"}
}