{
  "type": "Feature",
  "properties": {
    "iso:country":"US",
    "sg:address":"2304 S 1st St Ste A",
    "sg:city":"Austin",
    "sg:classifiers":[
        {
            "category":"Restaurant",
            "type":"Food & Drink"
        },
        {
            "category":"Food & Beverages",
            "subcategory":"Groceries & Convenience Stores",
            "type":"Retail Goods"
        }
    ],
    "sg:phone":"+1 512 462 2188",
    "sg:postcode":"78704",
    "sg:province":"TX",
    "sg:tags":[
        "style",
        "latin",
        "mexican",
        "family",
        "lunch",
        "american",
        "brunch",
        "breakfast"
    ],
    "wof:name":"Little Mexico Restaurant",
    "wof:placetype":"venue"
},
  "geometry": {"coordinates":[-97.75897000000001,30.243037],"type":"Point"}
}