{
  "type": "Feature",
  "properties": {
    "iso:country":"US",
    "sg:address":"900 S Woodrow Ln",
    "sg:city":"Denton",
    "sg:classifiers":[
        {
            "category":"Building & Trades",
            "subcategory":"Plumbing",
            "type":"Services"
        }
    ],
    "sg:phone":"+1 940 243 9199",
    "sg:postcode":"76205",
    "sg:province":"TX",
    "sg:tags":[
        "conditioning",
        "contractor",
        "system",
        "air"
    ],
    "sg:website":"www.achotline.com",
    "wof:name":"Cogburn's Service General",
    "wof:placetype":"venue"
},
  "geometry": {"coordinates":[-97.11229,33.20145],"type":"Point"}
}