{
  "type": "Feature",
  "properties": {
    "iso:country":"US",
    "sg:address":"11901 Hill Country Cir",
    "sg:city":"Ponder",
    "sg:classifiers":[
        {
            "category":"Communications",
            "subcategory":"Film & Video Production",
            "type":"Services"
        }
    ],
    "sg:phone":"+1 940 479 0668",
    "sg:postcode":"76259",
    "sg:province":"TX",
    "sg:tags":[
        "motion"
    ],
    "wof:name":"Tyler Productions",
    "wof:placetype":"venue"
},
  "geometry": {"coordinates":[-97.33327300000001,33.183795],"type":"Point"}
}