{
  "type": "Feature",
  "properties": {
    "iso:country":"US",
    "sg:address":"947 Webster St",
    "sg:city":"Eagle Pass",
    "sg:classifiers":[
        {
            "category":"Organizations",
            "subcategory":"Religious Organization",
            "type":"Services"
        }
    ],
    "sg:phone":"+1 830 773 8964",
    "sg:postcode":"78852",
    "sg:province":"TX",
    "sg:tags":[
        "church"
    ],
    "wof:name":"Church Of Christ",
    "wof:placetype":"venue"
},
  "geometry": {"coordinates":[-100.501234,28.718044],"type":"Point"}
}