{
  "type": "Feature",
  "properties": {
    "iso:country":"US",
    "sg:address":"11785 Apacheria",
    "sg:city":"Helotes",
    "sg:classifiers":[
        {
            "category":"Building & Trades",
            "subcategory":"Construction",
            "type":"Services"
        }
    ],
    "sg:phone":"+1 210 695 6043",
    "sg:postcode":"78023",
    "sg:province":"TX",
    "wof:name":"C & L Stein Construction Inc",
    "wof:placetype":"venue"
},
  "geometry": {"coordinates":[-98.726564,29.608887],"type":"Point"}
}