{
  "type": "Feature",
  "properties": {
    "iso:country":"US",
    "sg:address":"1752 Oakland Blvd",
    "sg:city":"Fort Worth",
    "sg:classifiers":[
        {
            "category":"Building & Trades",
            "subcategory":"Electrical",
            "type":"Services"
        }
    ],
    "sg:phone":"+1 817 535 0112",
    "sg:postcode":"76103",
    "sg:province":"TX",
    "sg:tags":[
        "electric",
        "contractor"
    ],
    "wof:name":"Phoenix Electrical Svc",
    "wof:placetype":"venue"
},
  "geometry": {"coordinates":[-97.261736,32.752912],"type":"Point"}
}