{
  "type": "Feature",
  "properties": {
    "iso:country":"US",
    "sg:address":"210 W Austin St",
    "sg:city":"Jefferson",
    "sg:classifiers":[
        {
            "category":"Shopping",
            "subcategory":"Books",
            "type":"Retail Goods"
        }
    ],
    "sg:phone":"+1 903 665 7520",
    "sg:postcode":"75657",
    "sg:province":"TX",
    "sg:tags":[
        "shop",
        "beauty"
    ],
    "wof:name":"Beauty and Book",
    "wof:placetype":"venue"
},
  "geometry": {"coordinates":[-94.345282,32.756076],"type":"Point"}
}