{
  "type": "Feature",
  "properties": {
    "iso:country":"US",
    "sg:address":"11615 Forest Central Dr",
    "sg:city":"Dallas",
    "sg:classifiers":[
        {
            "category":"Travel",
            "subcategory":"Travel Agent",
            "type":"Entertainment"
        }
    ],
    "sg:phone":"+1 214 349 4188",
    "sg:postcode":"75243",
    "sg:province":"TX",
    "sg:tags":[
        "agency"
    ],
    "wof:name":"USA Toura Travel",
    "wof:placetype":"venue"
},
  "geometry": {"coordinates":[-96.767116,32.909109],"type":"Point"}
}