{
  "type": "Feature",
  "properties": {
    "iso:country":"US",
    "sg:address":"382 Sprucewood Ln",
    "sg:city":"San Antonio",
    "sg:classifiers":[
        {
            "category":"Building & Trades",
            "subcategory":"Cleaning & Sanitation",
            "type":"Services"
        }
    ],
    "sg:phone":"+1 210 349 2045",
    "sg:postcode":"78216",
    "sg:province":"TX",
    "sg:tags":[
        "maintenance"
    ],
    "wof:name":"Imperial Maintenance Co",
    "wof:placetype":"venue"
},
  "geometry": {"coordinates":[-98.490516,29.512379],"type":"Point"}
}