{
  "type": "Feature",
  "properties": {
    "iso:country":"US",
    "sg:address":"820 S MacArthur Blvd Ste 151",
    "sg:city":"Coppell",
    "sg:classifiers":[
        {
            "category":"Personal",
            "subcategory":"Nail Salon",
            "type":"Services"
        }
    ],
    "sg:phone":"+1 972 745 1402",
    "sg:postcode":"75019",
    "sg:province":"TX",
    "wof:name":"Phi Kim Nguyen",
    "wof:placetype":"venue"
},
  "geometry": {"coordinates":[-96.95767600000001,32.951342],"type":"Point"}
}