{
  "type": "Feature",
  "properties": {
    "iso:country":"US",
    "sg:address":"6720 Corpus Christi Drive",
    "sg:city":"Austin",
    "sg:classifiers":[
        {
            "category":"Education",
            "subcategory":"School",
            "type":"Public Place"
        }
    ],
    "sg:phone":"+1 512 428 2200",
    "sg:postcode":"78729",
    "sg:province":"TX",
    "sg:website":"schools.roundrockisd.org/jollyville",
    "wof:name":"Round Rock Independent School District",
    "wof:placetype":"venue"
},
  "geometry": {"coordinates":[-97.750472,30.44261],"type":"Point"}
}