{
  "type": "Feature",
  "properties": {
    "iso:country":"US",
    "sg:address":"501 Northern Dancer Dr",
    "sg:city":"Copperas Cove",
    "sg:classifiers":[
        {
            "category":"Education",
            "subcategory":"Special Training",
            "type":"Public Place"
        }
    ],
    "sg:phone":"+1 254 547 5857",
    "sg:postcode":"76522",
    "sg:province":"TX",
    "wof:name":"Modeling Studio",
    "wof:placetype":"venue"
},
  "geometry": {"coordinates":[-97.89439299999999,31.104523],"type":"Point"}
}