{
  "type": "Feature",
  "properties": {
    "iso:country":"US",
    "sg:address":"1702 Pensacola Ln",
    "sg:city":"Friendswood",
    "sg:classifiers":[
        {
            "category":"Professional",
            "type":"Services"
        }
    ],
    "sg:phone":"+1 281 993 5359",
    "sg:postcode":"77546",
    "sg:province":"TX",
    "wof:name":"Beam Lok LLC",
    "wof:placetype":"venue"
},
  "geometry": {"coordinates":[-95.217123,29.481617],"type":"Point"}
}