{
  "type": "Feature",
  "properties": {
    "iso:country":"US",
    "sg:address":"11B Kern Ramble St # 107",
    "sg:city":"Austin",
    "sg:classifiers":[
        {
            "category":"Government",
            "subcategory":"Fire Station",
            "type":"Public Place"
        }
    ],
    "sg:phone":"+1 512 445 4425",
    "sg:postcode":"78722",
    "sg:province":"TX",
    "sg:tags":[
        "protection"
    ],
    "sg:website":"http://www.sibt.com",
    "wof:name":"Siemens Industry, Inc.",
    "wof:placetype":"venue"
},
  "geometry": {"coordinates":[-97.716627,30.289229],"type":"Point"}
}