{
  "type": "Feature",
  "properties": {
    "iso:country":"US",
    "sg:address":"1305 Davis Bend Rd",
    "sg:city":"Alvin",
    "sg:classifiers":[
        {
            "category":"Social Services",
            "subcategory":"Child Care",
            "type":"Services"
        }
    ],
    "sg:phone":"+1 281 388 1700",
    "sg:postcode":"77511",
    "sg:province":"TX",
    "wof:name":"Granny B's Child Development",
    "wof:placetype":"venue"
},
  "geometry": {"coordinates":[-95.27278699999999,29.415006],"type":"Point"}
}