{
  "type": "Feature",
  "properties": {
    "iso:country":"US",
    "sg:address":"109 W Villa Maria Rd",
    "sg:city":"Bryan",
    "sg:classifiers":[
        {
            "category":"Professional",
            "subcategory":"Lawyer & Legal Services",
            "type":"Services"
        }
    ],
    "sg:phone":"+1 979 776 6363",
    "sg:postcode":"77801",
    "sg:province":"TX",
    "wof:name":"Steven A Milburn",
    "wof:placetype":"venue"
},
  "geometry": {"coordinates":[-96.359804,30.638894],"type":"Point"}
}