{
  "type": "Feature",
  "properties": {
    "iso:country":"US",
    "sg:address":"2037 Wirt Rd",
    "sg:city":"Houston",
    "sg:classifiers":[
        {
            "category":"Personal",
            "subcategory":"Beauty Salon",
            "type":"Services"
        }
    ],
    "sg:phone":"+1 713 465 5818",
    "sg:postcode":"77055",
    "sg:province":"TX",
    "sg:tags":[
        "shop"
    ],
    "wof:name":"Cristina's Beauty Salon",
    "wof:placetype":"venue"
},
  "geometry": {"coordinates":[-95.48493999999999,29.807685],"type":"Point"}
}