{
  "type": "Feature",
  "properties": {
    "iso:country":"US",
    "sg:address":"6322 Water Point Ct",
    "sg:city":"Humble",
    "sg:classifiers":[
        {
            "category":"Professional",
            "subcategory":"Management & Consulting",
            "type":"Services"
        }
    ],
    "sg:phone":"+1 281 812 6667",
    "sg:postcode":"77346",
    "sg:province":"TX",
    "sg:tags":[
        "consultant",
        "safety",
        "business"
    ],
    "wof:name":"Applied Hygiene Services Inc",
    "wof:placetype":"venue"
},
  "geometry": {"coordinates":[-95.177488,30.0182],"type":"Point"}
}