{
  "type": "Feature",
  "properties": {
    "iso:country":"US",
    "sg:address":"405 Colebrook Ln",
    "sg:city":"Dickinson",
    "sg:classifiers":[
        {
            "category":"Insurance",
            "subcategory":"Insurance Agent",
            "type":"Services"
        }
    ],
    "sg:phone":"+1 281 309 9866",
    "sg:postcode":"77539",
    "sg:province":"TX",
    "wof:name":"Daniel Thomason Insurance Agen",
    "wof:placetype":"venue"
},
  "geometry": {"coordinates":[-95.09298800000001,29.444754],"type":"Point"}
}