{
  "type": "Feature",
  "properties": {
    "iso:country":"US",
    "sg:address":"22459 Katy Fwy",
    "sg:city":"Katy",
    "sg:classifiers":[
        {
            "category":"Autos & Motor Vehicles",
            "subcategory":"Auto Supplies",
            "type":"Retail Goods"
        }
    ],
    "sg:phone":"+1 281 693 2886",
    "sg:postcode":"77450",
    "sg:province":"TX",
    "sg:tags":[
        "tire"
    ],
    "sg:website":"http://www.katyautocare.com",
    "wof:name":"Professional Tire & Auto",
    "wof:placetype":"venue"
},
  "geometry": {"coordinates":[-95.762229,29.784946],"type":"Point"}
}