{
  "type": "Feature",
  "properties": {
    "iso:country":"US",
    "sg:address":"1337 Naples Dr",
    "sg:city":"Dallas",
    "sg:classifiers":[
        {
            "category":"Building & Trades",
            "subcategory":"Construction",
            "type":"Services"
        }
    ],
    "sg:phone":"+1 972 296 8777",
    "sg:postcode":"75232",
    "sg:province":"TX",
    "sg:tags":[
        "system",
        "specialty",
        "heating",
        "mechanical",
        "contractor",
        "air conditioning"
    ],
    "wof:name":"Tipco Mechanical",
    "wof:placetype":"venue"
},
  "geometry": {"coordinates":[-96.842398,32.683218],"type":"Point"}
}