{
  "type": "Feature",
  "properties": {
    "iso:country":"US",
    "sg:address":"104 Kailyn Ln",
    "sg:city":"Weatherford",
    "sg:classifiers":[
        {
            "category":"Wholesale",
            "subcategory":"Hardware",
            "type":"Manufacturing & Wholesale Goods"
        }
    ],
    "sg:phone":"+1 817 594 8426",
    "sg:postcode":"76085",
    "sg:province":"TX",
    "sg:tags":[
        "refrigerating"
    ],
    "wof:name":"FES Southwest Inc",
    "wof:placetype":"venue"
},
  "geometry": {"coordinates":[-97.639036,32.918133],"type":"Point"}
}