{
  "type": "Feature",
  "properties": {
    "iso:country":"US",
    "sg:address":"6210 Roseridge Ln",
    "sg:city":"Houston",
    "sg:classifiers":[
        {
            "category":"Organizations",
            "subcategory":"Religious Organization",
            "type":"Services"
        }
    ],
    "sg:phone":"+1 281 438 3056",
    "sg:postcode":"77053",
    "sg:province":"TX",
    "wof:name":"Jesus Carillo",
    "wof:placetype":"venue"
},
  "geometry": {"coordinates":[-95.478926,29.596449],"type":"Point"}
}