{
  "type": "Feature",
  "properties": {
    "iso:country":"US",
    "sg:address":"9623 Airline Rd",
    "sg:city":"Dallas",
    "sg:classifiers":[
        {
            "category":"Manufacturing",
            "subcategory":"Jewelry",
            "type":"Manufacturing & Wholesale Goods"
        }
    ],
    "sg:phone":"+1 214 340 1707",
    "sg:postcode":"75225",
    "sg:province":"TX",
    "wof:name":"Ann Cichon & Co",
    "wof:placetype":"venue"
},
  "geometry": {"coordinates":[-96.782758,32.879118],"type":"Point"}
}