{
  "type": "Feature",
  "properties": {
    "iso:country":"US",
    "sg:address":"4822 Wilmington St",
    "sg:city":"Houston",
    "sg:classifiers":[
        {
            "category":"Freight",
            "type":"Transportation"
        }
    ],
    "sg:phone":"+1 713 738 2733",
    "sg:postcode":"77033",
    "sg:province":"TX",
    "wof:name":"Big Dog Freight Express",
    "wof:placetype":"venue"
},
  "geometry": {"coordinates":[-95.348826,29.655936],"type":"Point"}
}