{
  "type": "Feature",
  "properties": {
    "iso:country":"US",
    "sg:address":"11100 Parkfield Drive",
    "sg:city":"Austin",
    "sg:classifiers":[
        {
            "category":"Health Services",
            "subcategory":"Dentist",
            "type":"Services"
        }
    ],
    "sg:phone":"+1 512 339 7848",
    "sg:postcode":"78758",
    "sg:province":"TX",
    "wof:name":"Economy Dental",
    "wof:placetype":"venue"
},
  "geometry": {"coordinates":[-97.697107,30.383801],"type":"Point"}
}