{
  "type": "Feature",
  "properties": {
    "iso:country":"US",
    "sg:address":"4800 Texoma Pkwy",
    "sg:city":"Sherman",
    "sg:classifiers":[
        {
            "category":"Shopping",
            "subcategory":"Jewelry",
            "type":"Retail Goods"
        }
    ],
    "sg:phone":"+1 903 982 8586",
    "sg:postcode":"75090",
    "sg:province":"TX",
    "sg:tags":[
        "store"
    ],
    "wof:name":"Gordons Jewelers 4554",
    "wof:placetype":"venue"
},
  "geometry": {"coordinates":[-96.58098,33.687988],"type":"Point"}
}