{
  "type": "Feature",
  "properties": {
    "iso:country":"US",
    "sg:address":"1360 Co Rd 414",
    "sg:city":"Stockdale",
    "sg:classifiers":[
        {
            "category":"Farming",
            "subcategory":"Farm",
            "type":"Manufacturing & Wholesale Goods"
        }
    ],
    "sg:phone":"+1 830 996 3384",
    "sg:postcode":"78160",
    "sg:province":"TX",
    "sg:tags":[
        "crop",
        "general"
    ],
    "wof:name":"Ronald Hastings",
    "wof:placetype":"venue"
},
  "geometry": {"coordinates":[-97.97162,29.223274],"type":"Point"}
}