{
  "type": "Feature",
  "properties": {
    "iso:country":"US",
    "sg:address":"801 Travis St",
    "sg:city":"Houston",
    "sg:classifiers":[
        {
            "category":"Professional",
            "subcategory":"Employment Agencies",
            "type":"Services"
        }
    ],
    "sg:phone":"+1 713 339 1213",
    "sg:postcode":"77002",
    "sg:province":"TX",
    "sg:tags":[
        "body",
        "equipment",
        "handicap",
        "armor",
        "wholesaler",
        "installer"
    ],
    "wof:name":"Randale Group  LLC",
    "wof:placetype":"venue"
},
  "geometry": {"coordinates":[-95.36521500000001,29.758226],"type":"Point"}
}