{
  "type": "Feature",
  "properties": {
    "iso:country":"US",
    "sg:address":"15140 John Miller Rd",
    "sg:city":"Guy",
    "sg:phone":"+1 979 793 6223",
    "sg:postcode":"77444",
    "sg:province":"TX",
    "sg:tags":[
        "farm",
        "corn",
        "grain",
        "cash",
        "cotton"
    ],
    "wof:name":"Bosak Crayden",
    "wof:placetype":"venue"
},
  "geometry": {"coordinates":[-95.759907,29.341787],"type":"Point"}
}