{
  "type": "Feature",
  "properties": {
    "iso:country":"US",
    "sg:address":"209 Hidden Ln",
    "sg:city":"Laredo",
    "sg:classifiers":[
        {
            "category":"Social Services",
            "subcategory":"Child Care",
            "type":"Services"
        }
    ],
    "sg:phone":"+1 956 722 0718",
    "sg:postcode":"78041",
    "sg:province":"TX",
    "wof:name":"Cabbage Patch Day Care",
    "wof:placetype":"venue"
},
  "geometry": {"coordinates":[-99.485428,27.552809],"type":"Point"}
}