{
  "type": "Feature",
  "properties": {
    "iso:country":"US",
    "sg:address":"2797 S Main St",
    "sg:city":"Ingleside",
    "sg:classifiers":[
        {
            "category":"Health Services",
            "subcategory":"Doctor",
            "type":"Services"
        }
    ],
    "sg:phone":"+1 361 776 5166",
    "sg:postcode":"78362",
    "sg:province":"TX",
    "wof:name":"Ben Costal Dental",
    "wof:placetype":"venue"
},
  "geometry": {"coordinates":[-97.211369,27.878819],"type":"Point"}
}