{
  "type": "Feature",
  "properties": {
    "iso:country":"US",
    "sg:address":"1906 N 8th St",
    "sg:city":"Killeen",
    "sg:classifiers":[
        {
            "category":"Food & Beverages",
            "subcategory":"Groceries & Convenience Stores",
            "type":"Retail Goods"
        }
    ],
    "sg:phone":"+1 254 526 0707",
    "sg:postcode":"76541",
    "sg:province":"TX",
    "wof:name":"Ms Kwick Shop",
    "wof:placetype":"venue"
},
  "geometry": {"coordinates":[-97.722753,31.131924],"type":"Point"}
}