{
  "type": "Feature",
  "properties": {
    "iso:country":"US",
    "sg:address":"2556 Madison Ave",
    "sg:city":"Abilene",
    "sg:classifiers":[
        {
            "category":"Autos & Motor Vehicles",
            "subcategory":"Auto Supplies",
            "type":"Retail Goods"
        }
    ],
    "sg:phone":"+1 325 672 3394",
    "sg:postcode":"79601",
    "sg:province":"TX",
    "wof:name":"Abilene Mustang Parts",
    "wof:placetype":"venue"
},
  "geometry": {"coordinates":[-99.716121,32.477067],"type":"Point"}
}