{
  "type": "Feature",
  "properties": {
    "iso:country":"US",
    "sg:address":"2512 River Oaks Ln",
    "sg:city":"Mesquite",
    "sg:classifiers":[
        {
            "category":"Manufacturing",
            "subcategory":"Printing",
            "type":"Manufacturing & Wholesale Goods"
        }
    ],
    "sg:phone":"+1 972 613 6709",
    "sg:postcode":"75150",
    "sg:province":"TX",
    "sg:tags":[
        "commercial"
    ],
    "wof:name":"Hand Engraving",
    "wof:placetype":"venue"
},
  "geometry": {"coordinates":[-96.637744,32.834631],"type":"Point"}
}