{
  "type": "Feature",
  "properties": {
    "iso:country":"US",
    "sg:address":"1776 Yorktown St",
    "sg:city":"Houston",
    "sg:classifiers":[
        {
            "category":"Real Estate",
            "subcategory":"Real Estate Agent",
            "type":"Services"
        }
    ],
    "sg:phone":"+1 713 871 0001",
    "sg:postcode":"77056",
    "sg:province":"TX",
    "wof:name":"Essex Realty Svc",
    "wof:placetype":"venue"
},
  "geometry": {"coordinates":[-95.470949,29.74876],"type":"Point"}
}