{
  "type": "Feature",
  "properties": {
    "iso:country":"US",
    "sg:address":"304 Magnolia Blvd",
    "sg:city":"Magnolia",
    "sg:classifiers":[
        {
            "category":"Shopping",
            "subcategory":"Gifts & Souvenirs",
            "type":"Retail Goods"
        }
    ],
    "sg:phone":"+1 281 252 6122",
    "sg:postcode":"77355",
    "sg:province":"TX",
    "sg:tags":[
        "shop"
    ],
    "wof:name":"Shelf Decor",
    "wof:placetype":"venue"
},
  "geometry": {"coordinates":[-95.75443199999999,30.211476],"type":"Point"}
}