{
  "type": "Feature",
  "properties": {
    "iso:country":"US",
    "sg:address":"6401 Hartman Rd",
    "sg:city":"Fort Worth",
    "sg:classifiers":[
        {
            "category":"Organizations",
            "subcategory":"Religious Organization",
            "type":"Services"
        }
    ],
    "sg:phone":"+1 817 534 6451",
    "sg:postcode":"76119",
    "sg:province":"TX",
    "wof:name":"Forest Hl Untd Methdst Church",
    "wof:placetype":"venue"
},
  "geometry": {"coordinates":[-97.26007799999999,32.661837],"type":"Point"}
}