{
  "type": "Feature",
  "properties": {
    "iso:country":"US",
    "sg:address":"12751 S Dairy Ashford St",
    "sg:city":"Houston",
    "sg:classifiers":[
        {
            "category":"Food & Beverages",
            "subcategory":"Groceries & Convenience Stores",
            "type":"Retail Goods"
        }
    ],
    "sg:phone":"+1 281 530 9736",
    "sg:postcode":"77099",
    "sg:province":"TX",
    "wof:name":"Smart Stop",
    "wof:placetype":"venue"
},
  "geometry": {"coordinates":[-95.597769,29.661621],"type":"Point"}
}