{
  "type": "Feature",
  "properties": {
    "iso:country":"US",
    "sg:address":"4510 Ridgecove Dr",
    "sg:city":"Rowlett",
    "sg:classifiers":[
        {
            "category":"Professional",
            "type":"Services"
        }
    ],
    "sg:phone":"+1 972 463 1275",
    "sg:postcode":"75088",
    "sg:province":"TX",
    "wof:name":"Liev Dynasty Inc",
    "wof:placetype":"venue"
},
  "geometry": {"coordinates":[-96.55731,32.883551],"type":"Point"}
}