{
  "type": "Feature",
  "properties": {
    "iso:country":"US",
    "sg:address":"14854 Cobo de Bara Cir",
    "sg:city":"Corpus Christi",
    "sg:classifiers":[
        {
            "category":"Building & Trades",
            "subcategory":"Landscaping Services",
            "type":"Services"
        }
    ],
    "sg:phone":"+1 361 949 7165",
    "sg:postcode":"78418",
    "sg:province":"TX",
    "sg:tags":[
        "landscape",
        "contractor"
    ],
    "wof:name":"Testa Landscaping & Maint",
    "wof:placetype":"venue"
},
  "geometry": {"coordinates":[-97.239493,27.610612],"type":"Point"}
}