{
  "type": "Feature",
  "properties": {
    "iso:country":"US",
    "sg:address":"780 W Mansfield Hwy",
    "sg:city":"Kennedale",
    "sg:classifiers":[
        {
            "category":"Building & Trades",
            "subcategory":"Construction",
            "type":"Services"
        }
    ],
    "sg:phone":"+1 817 478 1119",
    "sg:postcode":"76060",
    "sg:province":"TX",
    "sg:tags":[
        "underground",
        "utility"
    ],
    "wof:name":"Gin-Spen Inc",
    "wof:placetype":"venue"
},
  "geometry": {"coordinates":[-97.23351099999999,32.658248],"type":"Point"}
}