{
  "type": "Feature",
  "properties": {
    "iso:country":"US",
    "sg:address":"16300 Kuykendahl Rd",
    "sg:city":"Houston",
    "sg:classifiers":[
        {
            "category":"Shopping",
            "subcategory":"Clothing, Apparel, & Fashions",
            "type":"Retail Goods"
        }
    ],
    "sg:phone":"+1 281 440 4747",
    "sg:postcode":"77068",
    "sg:province":"TX",
    "wof:name":"Stork Stop",
    "wof:placetype":"venue"
},
  "geometry": {"coordinates":[-95.46847699999999,30.013399],"type":"Point"}
}