{
  "type": "Feature",
  "properties": {
    "iso:country":"US",
    "sg:address":"10404 Co Rd 1016",
    "sg:city":"Burleson",
    "sg:classifiers":[
        {
            "category":"Autos & Motor Vehicles",
            "subcategory":"Automobile Sales",
            "type":"Retail Goods"
        }
    ],
    "sg:phone":"+1 817 295 2556",
    "sg:postcode":"76028",
    "sg:province":"TX",
    "sg:tags":[
        "used"
    ],
    "wof:name":"Caseys Used Cars",
    "wof:placetype":"venue"
},
  "geometry": {"coordinates":[-97.39526600000001,32.527968],"type":"Point"}
}