{
  "type": "Feature",
  "properties": {
    "iso:country":"US",
    "sg:address":"9542 Ravensworth Dr",
    "sg:city":"Houston",
    "sg:classifiers":[
        {
            "category":"Professional",
            "subcategory":"Business Services",
            "type":"Services"
        }
    ],
    "sg:phone":"+1 281 530 3451",
    "sg:postcode":"77031",
    "sg:province":"TX",
    "wof:name":"Anjali Enterprises Inc",
    "wof:placetype":"venue"
},
  "geometry": {"coordinates":[-95.544911,29.642749],"type":"Point"}
}