{
  "type": "Feature",
  "properties": {
    "iso:country":"US",
    "sg:address":"10414 Clear Cove Ln",
    "sg:city":"Houston",
    "sg:classifiers":[
        {
            "category":"Building & Trades",
            "subcategory":"Plumbing",
            "type":"Services"
        }
    ],
    "sg:phone":"+1 713 466 3737",
    "sg:postcode":"77041",
    "sg:province":"TX",
    "sg:tags":[
        "contractor"
    ],
    "wof:name":"America Divison",
    "wof:placetype":"venue"
},
  "geometry": {"coordinates":[-95.551016,29.834589],"type":"Point"}
}