{
  "type": "Feature",
  "properties": {
    "iso:country":"US",
    "sg:address":"7710 FM 1960 W",
    "sg:city":"Houston",
    "sg:classifiers":[
        {
            "category":"Shopping",
            "subcategory":"Shoes",
            "type":"Retail Goods"
        }
    ],
    "sg:phone":"+1 281 890 5633",
    "sg:postcode":"77070",
    "sg:province":"TX",
    "sg:tags":[
        "shoe",
        "store"
    ],
    "wof:name":"Famous Footwear",
    "wof:placetype":"venue"
},
  "geometry": {"coordinates":[-95.544411,29.963561],"type":"Point"}
}