{
  "type": "Feature",
  "properties": {
    "iso:country":"US",
    "sg:address":"7104 Berkman Drive",
    "sg:city":"Austin",
    "sg:classifiers":[
        {
            "category":"Education",
            "subcategory":"School",
            "type":"Public Place"
        }
    ],
    "sg:phone":"+1 512 414 2523",
    "sg:postcode":"78752",
    "sg:province":"TX",
    "sg:website":"www.austin.isd.tenet.edu",
    "wof:name":"Austin Independent School District",
    "wof:placetype":"venue"
},
  "geometry": {"coordinates":[-97.689255,30.322287],"type":"Point"}
}