{
  "type": "Feature",
  "properties": {
    "iso:country":"US",
    "sg:address":"1407 West Ave",
    "sg:city":"San Antonio",
    "sg:classifiers":[
        {
            "category":"Education",
            "subcategory":"School",
            "type":"Public Place"
        }
    ],
    "sg:phone":"+1 210 733 9125",
    "sg:postcode":"78201",
    "sg:province":"TX",
    "wof:name":"Northside Baptist Church",
    "wof:placetype":"venue"
},
  "geometry": {"coordinates":[-98.52608600000001,29.475194],"type":"Point"}
}