{
  "type": "Feature",
  "properties": {
    "iso:country":"US",
    "sg:address":"214 Mid Tex Rd",
    "sg:city":"Lorena",
    "sg:classifiers":[
        {
            "category":"Building & Trades",
            "subcategory":"Construction",
            "type":"Services"
        }
    ],
    "sg:phone":"+1 254 857 4632",
    "sg:postcode":"76655",
    "sg:province":"TX",
    "sg:tags":[
        "general",
        "contractor"
    ],
    "wof:name":"Mitchell Construction Co Inc",
    "wof:placetype":"venue"
},
  "geometry": {"coordinates":[-97.196322,31.413432],"type":"Point"}
}