{
  "type": "Feature",
  "properties": {
    "iso:country":"US",
    "sg:address":"327 Hampton Ct",
    "sg:city":"Longview",
    "sg:classifiers":[
        {
            "category":"Manufacturing",
            "subcategory":"Metals",
            "type":"Manufacturing & Wholesale Goods"
        }
    ],
    "sg:phone":"+1 903 663 4772",
    "sg:postcode":"75605",
    "sg:province":"TX",
    "sg:tags":[
        "steel"
    ],
    "wof:name":"Cobblestone Industries Inc",
    "wof:placetype":"venue"
},
  "geometry": {"coordinates":[-94.74705299999999,32.527557],"type":"Point"}
}