{
  "type": "Feature",
  "properties": {
    "iso:country":"US",
    "sg:address":"1133 E Birdsong St",
    "sg:city":"Longview",
    "sg:classifiers":[
        {
            "category":"Government",
            "subcategory":"Police Station",
            "type":"Public Place"
        }
    ],
    "sg:phone":"+1 903 758 6512",
    "sg:postcode":"75602",
    "sg:province":"TX",
    "sg:tags":[
        "department"
    ],
    "wof:name":"Longview Police Dept",
    "wof:placetype":"venue"
},
  "geometry": {"coordinates":[-94.716948,32.472196],"type":"Point"}
}