{
  "type": "Feature",
  "properties": {
    "iso:country":"US",
    "sg:address":"4317 Convent Ave",
    "sg:city":"Laredo",
    "sg:classifiers":[
        {
            "category":"Retail",
            "subcategory":"Auto Repair",
            "type":"Services"
        }
    ],
    "sg:phone":"+1 956 726 8852",
    "sg:postcode":"78041",
    "sg:province":"TX",
    "sg:tags":[
        "general"
    ],
    "wof:name":"Martinez Auto Repair",
    "wof:placetype":"venue"
},
  "geometry": {"coordinates":[-99.507063,27.539057],"type":"Point"}
}