{
  "type": "Feature",
  "properties": {
    "iso:country":"US",
    "sg:address":"2805 Hickory Bend Dr",
    "sg:city":"Garland",
    "sg:phone":"+1 972 496 2583",
    "sg:postcode":"75044",
    "sg:province":"TX",
    "sg:tags":[
        "production",
        "gas",
        "oil"
    ],
    "wof:name":"Champ Operating Co",
    "wof:placetype":"venue"
},
  "geometry": {"coordinates":[-96.67045400000001,32.941278],"type":"Point"}
}