{
  "type": "Feature",
  "properties": {
    "iso:country":"US",
    "sg:address":"1580 Hwy 157 N",
    "sg:city":"Mansfield",
    "sg:classifiers":[
        {
            "category":"Retail",
            "subcategory":"Auto Rental",
            "type":"Services"
        }
    ],
    "sg:phone":"+1 817 453 9889",
    "sg:postcode":"76063",
    "sg:province":"TX",
    "sg:tags":[
        "renting",
        "truck",
        "leasing"
    ],
    "wof:name":"U-Haul Co",
    "wof:placetype":"venue"
},
  "geometry": {"coordinates":[-97.151887,32.586321],"type":"Point"}
}