{
  "type": "Feature",
  "properties": {
    "iso:country":"US",
    "sg:address":"11407 Dugat Rd",
    "sg:city":"Beaumont",
    "sg:classifiers":[
        {
            "category":"Education",
            "subcategory":"School",
            "type":"Public Place"
        }
    ],
    "sg:phone":"+1 409 794 1558",
    "sg:postcode":"77705",
    "sg:province":"TX",
    "wof:name":"Hamshire-Fannett Intermediate",
    "wof:placetype":"venue"
},
  "geometry": {"coordinates":[-94.253491,29.917242],"type":"Point"}
}