{
  "type": "Feature",
  "properties": {
    "iso:country":"US",
    "sg:address":"814 Hall Ave",
    "sg:city":"Littlefield",
    "sg:classifiers":[
        {
            "category":"Retail",
            "subcategory":"Auto Repair",
            "type":"Services"
        }
    ],
    "sg:phone":"+1 806 385 6100",
    "sg:postcode":"79339",
    "sg:province":"TX",
    "sg:tags":[
        "body"
    ],
    "wof:name":"Lemer Hot Rods",
    "wof:placetype":"venue"
},
  "geometry": {"coordinates":[-102.325209,33.918205],"type":"Point"}
}