{
  "type": "Feature",
  "properties": {
    "iso:country":"US",
    "sg:address":"400 W Texas Ave",
    "sg:city":"Baytown",
    "sg:classifiers":[
        {
            "category":"Building & Trades",
            "subcategory":"Pest Control",
            "type":"Services"
        }
    ],
    "sg:phone":"+1 281 427 5512",
    "sg:postcode":"77520",
    "sg:province":"TX",
    "wof:name":"Glen's Pest Control",
    "wof:placetype":"venue"
},
  "geometry": {"coordinates":[-94.97170699999999,29.733386],"type":"Point"}
}