{
  "type": "Feature",
  "properties": {
    "iso:country":"US",
    "sg:address":"2302 Oberlin St",
    "sg:city":"Lubbock",
    "sg:classifiers":[
        {
            "category":"Home & Garden",
            "subcategory":"Furniture",
            "type":"Retail Goods"
        }
    ],
    "sg:phone":"+1 806 744 6806",
    "sg:postcode":"79415",
    "sg:province":"TX",
    "sg:tags":[
        "maker",
        "cabinet"
    ],
    "wof:name":"Third Day Cabinetry",
    "wof:placetype":"venue"
},
  "geometry": {"coordinates":[-101.868228,33.615998],"type":"Point"}
}