{
  "type": "Feature",
  "properties": {
    "iso:country":"US",
    "sg:address":"508 N Main St",
    "sg:city":"Sweeny",
    "sg:classifiers":[
        {
            "category":"Manufacturing",
            "subcategory":"Food",
            "type":"Manufacturing & Wholesale Goods"
        }
    ],
    "sg:phone":"+1 979 548 3603",
    "sg:postcode":"77480",
    "sg:province":"TX",
    "sg:tags":[
        "bakery"
    ],
    "wof:name":"Sprinkle Donut",
    "wof:placetype":"venue"
},
  "geometry": {"coordinates":[-95.701753,29.041459],"type":"Point"}
}