{
  "type": "Feature",
  "properties": {
    "iso:country":"US",
    "sg:address":"601 S Terrell St",
    "sg:city":"Midland",
    "sg:classifiers":[
        {
            "category":"Home & Garden",
            "subcategory":"Home Furnishings",
            "type":"Retail Goods"
        }
    ],
    "sg:phone":"+1 432 570 0132",
    "sg:postcode":"79701",
    "sg:province":"TX",
    "sg:tags":[
        "mirror"
    ],
    "wof:name":"Basin Glass & Mirror",
    "wof:placetype":"venue"
},
  "geometry": {"coordinates":[-102.068061,31.99136],"type":"Point"}
}