{
  "type": "Feature",
  "properties": {
    "iso:country":"US",
    "sg:address":"800 Co Rd 405",
    "sg:city":"Coleman",
    "sg:classifiers":[
        {
            "category":"Farming",
            "subcategory":"Livestock Farm",
            "type":"Manufacturing & Wholesale Goods"
        }
    ],
    "sg:phone":"+1 325 636 4370",
    "sg:postcode":"76834",
    "sg:province":"TX",
    "sg:tags":[
        "beef",
        "feedlot",
        "cattle"
    ],
    "wof:name":"Lloyd Hopper",
    "wof:placetype":"venue"
},
  "geometry": {"coordinates":[-99.495779,31.802521],"type":"Point"}
}