{
  "type": "Feature",
  "properties": {
    "iso:country":"US",
    "sg:address":"3400 Nacogdoches Rd",
    "sg:city":"San Antonio",
    "sg:classifiers":[
        {
            "category":"Retail",
            "subcategory":"Repair Shop",
            "type":"Services"
        }
    ],
    "sg:phone":"+1 210 657 6173",
    "sg:postcode":"78217",
    "sg:province":"TX",
    "wof:name":"A1 Furniture Refinishing",
    "wof:placetype":"venue"
},
  "geometry": {"coordinates":[-98.43078800000001,29.530458],"type":"Point"}
}