{
  "type": "Feature",
  "properties": {
    "iso:country":"US",
    "sg:address":"1108 Grace St",
    "sg:city":"Deer Park",
    "sg:classifiers":[
        {
            "category":"Professional",
            "type":"Services"
        }
    ],
    "sg:phone":"+1 281 479 1753",
    "sg:postcode":"77536",
    "sg:province":"TX",
    "wof:name":"B&L Yard Service",
    "wof:placetype":"venue"
},
  "geometry": {"coordinates":[-95.112342,29.701643],"type":"Point"}
}