{
  "type": "Feature",
  "properties": {
    "iso:country":"US",
    "sg:address":"3965 Phelan Blvd",
    "sg:city":"Beaumont",
    "sg:classifiers":[
        {
            "category":"Home & Garden",
            "subcategory":"Building Materials",
            "type":"Retail Goods"
        },
        {
            "category":"Building & Trades",
            "subcategory":"Construction",
            "type":"Services"
        },
        {
            "category":"Home & Garden",
            "subcategory":"Carpets & Floor Coverings",
            "type":"Retail Goods"
        }
    ],
    "sg:phone":"+1 409 838 5229",
    "sg:postcode":"77707",
    "sg:province":"TX",
    "sg:tags":[
        "granite",
        "top",
        "counter",
        "rug",
        "tile-contractors"
    ],
    "sg:website":"http://www.ramirezfloors.com",
    "wof:name":"Ramirez Carpet & Tile",
    "wof:placetype":"venue"
},
  "geometry": {"coordinates":[-94.14507399999999,30.084254],"type":"Point"}
}