{
  "type": "Feature",
  "properties": {
    "iso:country":"US",
    "sg:address":"2812 6th Ave",
    "sg:city":"Amarillo",
    "sg:classifiers":[
        {
            "category":"Manufacturing",
            "subcategory":"Leather Goods",
            "type":"Manufacturing & Wholesale Goods"
        }
    ],
    "sg:phone":"+1 806 342 0930",
    "sg:postcode":"79106",
    "sg:province":"TX",
    "sg:tags":[
        "mfg"
    ],
    "wof:name":"Tees A Division of Leathers",
    "wof:placetype":"venue"
},
  "geometry": {"coordinates":[-101.868533,35.211373],"type":"Point"}
}