{
  "type": "Feature",
  "properties": {
    "iso:country":"US",
    "sg:address":"1204 C C Woodson Rd",
    "sg:city":"Brownwood",
    "sg:classifiers":[
        {
            "category":"Travel",
            "subcategory":"Hotels & Motels",
            "type":"Entertainment"
        }
    ],
    "sg:phone":"+1 325 643 5611",
    "sg:postcode":"76802",
    "sg:province":"TX",
    "wof:name":"Executive Inn Motel",
    "wof:placetype":"venue"
},
  "geometry": {"coordinates":[-98.96632700000001,31.733076],"type":"Point"}
}