{
  "type": "Feature",
  "properties": {
    "iso:country":"US",
    "sg:address":"1851 Prairie View Dr Ste E",
    "sg:city":"Dallas",
    "sg:classifiers":[
        {
            "category":"Health Services",
            "subcategory":"Doctor",
            "type":"Services"
        }
    ],
    "sg:phone":"+1 214 630 9331",
    "sg:postcode":"75235",
    "sg:province":"TX",
    "sg:tags":[
        "dermatologist"
    ],
    "wof:name":"Eichhorn Phillip J MD",
    "wof:placetype":"venue"
},
  "geometry": {"coordinates":[-96.850098,32.815701],"type":"Point"}
}