{
  "type": "Feature",
  "properties": {
    "iso:country":"US",
    "sg:address":"1521 S Loop Dr",
    "sg:city":"Waco",
    "sg:classifiers":[
        {
            "category":"Restaurant",
            "type":"Food & Drink"
        }
    ],
    "sg:phone":"+1 254 867 6621",
    "sg:postcode":"76705",
    "sg:province":"TX",
    "sg:tags":[
        "eating"
    ],
    "wof:name":"McDonalds",
    "wof:placetype":"venue"
},
  "geometry": {"coordinates":[-97.102796,31.560919],"type":"Point"}
}