{
  "type": "Feature",
  "properties": {
    "iso:country":"US",
    "sg:address":"13214 Benford Dr",
    "sg:city":"Houston",
    "sg:classifiers":[
        {
            "category":"Shopping",
            "subcategory":"Hobbies, Toys, & Games",
            "type":"Retail Goods"
        }
    ],
    "sg:phone":"+1 281 561 5446",
    "sg:postcode":"77083",
    "sg:province":"TX",
    "wof:name":"Getout Toys",
    "wof:placetype":"venue"
},
  "geometry": {"coordinates":[-95.616045,29.677517],"type":"Point"}
}