{
  "type": "Feature",
  "properties": {
    "iso:country":"US",
    "sg:address":"205 E 8th St",
    "sg:city":"Deer Park",
    "sg:classifiers":[
        {
            "category":"Health Services",
            "subcategory":"Chiropractor",
            "type":"Services"
        }
    ],
    "sg:phone":"+1 281 479 9757",
    "sg:postcode":"77536",
    "sg:province":"TX",
    "wof:name":"McPearson Chiropractic Clinic Inc",
    "wof:placetype":"venue"
},
  "geometry": {"coordinates":[-95.12190200000001,29.7052],"type":"Point"}
}