{
  "type": "Feature",
  "properties": {
    "iso:country":"US",
    "sg:address":"606 Weizmann St",
    "sg:city":"San Antonio",
    "sg:classifiers":[
        {
            "category":"Professional",
            "subcategory":"Advertising",
            "type":"Services"
        }
    ],
    "sg:phone":"+1 210 342 5794",
    "sg:postcode":"78213",
    "sg:province":"TX",
    "sg:tags":[
        "distribution"
    ],
    "wof:name":"R C Enterprises",
    "wof:placetype":"venue"
},
  "geometry": {"coordinates":[-98.516194,29.492314],"type":"Point"}
}