{
  "type": "Feature",
  "properties": {
    "iso:country":"US",
    "sg:address":"6706 Barbarella Ct",
    "sg:city":"Houston",
    "sg:classifiers":[
        {
            "category":"Professional",
            "subcategory":"Management & Consulting",
            "type":"Services"
        }
    ],
    "sg:phone":"+1 281 448 6005",
    "sg:postcode":"77088",
    "sg:province":"TX",
    "sg:tags":[
        "retail",
        "direct",
        "sales"
    ],
    "wof:name":"Your Natural Health & Ntrtn",
    "wof:placetype":"venue"
},
  "geometry": {"coordinates":[-95.490346,29.885972],"type":"Point"}
}