{
  "type": "Feature",
  "properties": {
    "iso:country":"US",
    "sg:address":"5762 Fitzhugh Ave",
    "sg:city":"Fort Worth",
    "sg:classifiers":[
        {
            "category":"Organizations",
            "subcategory":"Religious Organization",
            "type":"Services"
        }
    ],
    "sg:phone":"+1 817 451 4279",
    "sg:postcode":"76119",
    "sg:province":"TX",
    "wof:name":"Christland Baptist Church",
    "wof:placetype":"venue"
},
  "geometry": {"coordinates":[-97.231037,32.717866],"type":"Point"}
}