{
  "type": "Feature",
  "properties": {
    "iso:country":"US",
    "sg:address":"3026 Mockingbird Ln",
    "sg:city":"Dallas",
    "sg:classifiers":[
        {
            "category":"Real Estate",
            "subcategory":"Real Estate Operator",
            "type":"Services"
        }
    ],
    "sg:phone":"+1 214 818 0900",
    "sg:postcode":"75205",
    "sg:province":"TX",
    "sg:tags":[
        "building",
        "apartment"
    ],
    "wof:name":"Morningside Property Company",
    "wof:placetype":"venue"
},
  "geometry": {"coordinates":[-96.78054899999999,32.836659],"type":"Point"}
}