{
  "type": "Feature",
  "properties": {
    "iso:country":"US",
    "sg:address":"5650 Guhn Rd",
    "sg:city":"Houston",
    "sg:classifiers":[
        {
            "category":"Freight",
            "type":"Transportation"
        }
    ],
    "sg:phone":"+1 713 939 7813",
    "sg:postcode":"77040",
    "sg:province":"TX",
    "sg:tags":[
        "warehouse",
        "self",
        "storage"
    ],
    "wof:name":"Statewide Logistics LP",
    "wof:placetype":"venue"
},
  "geometry": {"coordinates":[-95.51465899999999,29.847773],"type":"Point"}
}