{
  "type": "Feature",
  "properties": {
    "iso:country":"US",
    "sg:address":"5407 Hunter Park Ct",
    "sg:city":"Arlington",
    "sg:classifiers":[
        {
            "category":"Building & Trades",
            "subcategory":"Construction",
            "type":"Services"
        }
    ],
    "sg:phone":"+1 817 557 0567",
    "sg:postcode":"76017",
    "sg:province":"TX",
    "sg:tags":[
        "house"
    ],
    "wof:name":"Hendley Construction",
    "wof:placetype":"venue"
},
  "geometry": {"coordinates":[-97.15923600000001,32.659457],"type":"Point"}
}