{
  "type": "Feature",
  "properties": {
    "iso:country":"US",
    "sg:address":"4417 Allencrest Ln",
    "sg:city":"Dallas",
    "sg:classifiers":[
        {
            "category":"Professional",
            "subcategory":"Accounting & Tax Preparation",
            "type":"Services"
        }
    ],
    "sg:phone":"+1 972 661 5523",
    "sg:postcode":"75244",
    "sg:province":"TX",
    "wof:name":"Ulrich Financial Services Inc",
    "wof:placetype":"venue"
},
  "geometry": {"coordinates":[-96.82986200000001,32.91105],"type":"Point"}
}