{
  "type": "Feature",
  "properties": {
    "iso:country":"US",
    "sg:address":"2705 Arbor Dr",
    "sg:city":"Bryan",
    "sg:classifiers":[
        {
            "category":"Professional",
            "subcategory":"Business Services",
            "type":"Services"
        }
    ],
    "sg:phone":"+1 979 776 0221",
    "sg:postcode":"77802",
    "sg:province":"TX",
    "wof:name":"Beth Goyen Enterprises",
    "wof:placetype":"venue"
},
  "geometry": {"coordinates":[-96.334127,30.667146],"type":"Point"}
}