{
  "type": "Feature",
  "properties": {
    "iso:country":"US",
    "sg:address":"2123 Fm 1960 Rd W",
    "sg:city":"Houston",
    "sg:classifiers":[
        {
            "category":"Autos & Motor Vehicles",
            "subcategory":"Automobile Sales",
            "type":"Retail Goods"
        }
    ],
    "sg:phone":"+1 713 517 1322",
    "sg:postcode":"77090",
    "sg:province":"TX",
    "sg:tags":[
        "car",
        "used"
    ],
    "wof:name":"A A One Auto Dealer",
    "wof:placetype":"venue"
},
  "geometry": {"coordinates":[-95.460966,30.008511],"type":"Point"}
}