{
  "type": "Feature",
  "properties": {
    "iso:country":"US",
    "sg:address":"4426 Grove Park Dr",
    "sg:city":"League City",
    "sg:classifiers":[
        {
            "category":"Professional",
            "subcategory":"Employment Agencies",
            "type":"Services"
        }
    ],
    "sg:phone":"+1 281 770 1104",
    "sg:postcode":"77573",
    "sg:province":"TX",
    "wof:name":"S A International",
    "wof:placetype":"venue"
},
  "geometry": {"coordinates":[-95.139111,29.492326],"type":"Point"}
}