{
  "type": "Feature",
  "properties": {
    "iso:country":"US",
    "sg:address":"2928 Briarwick Ln",
    "sg:city":"Houston",
    "sg:classifiers":[
        {
            "category":"Freight",
            "type":"Transportation"
        }
    ],
    "sg:phone":"+1 713 699 0013",
    "sg:postcode":"77093",
    "sg:province":"TX",
    "sg:tags":[
        "operator",
        "local",
        "trucking"
    ],
    "wof:name":"Buckeyes Trucking",
    "wof:placetype":"venue"
},
  "geometry": {"coordinates":[-95.33874299999999,29.867632],"type":"Point"}
}