{
  "type": "Feature",
  "properties": {
    "iso:country":"US",
    "sg:address":"1504 E Mckinney St # 500",
    "sg:city":"Denton",
    "sg:classifiers":[
        {
            "category":"Professional",
            "subcategory":"Lawyer & Legal Services",
            "type":"Services"
        }
    ],
    "sg:phone":"+1 940 484 8578",
    "sg:postcode":"76209",
    "sg:province":"TX",
    "sg:tags":[
        "attorney",
        "practice",
        "plan"
    ],
    "wof:name":"Steve Burgess",
    "wof:placetype":"venue"
},
  "geometry": {"coordinates":[-97.11354,33.215848],"type":"Point"}
}