{
  "type": "Feature",
  "properties": {
    "iso:country":"US",
    "sg:address":"4132 S Cooper St",
    "sg:city":"Arlington",
    "sg:classifiers":[
        {
            "category":"Shopping",
            "subcategory":"Bicycles & Sporting Goods",
            "type":"Retail Goods"
        }
    ],
    "sg:phone":"+1 817 784 8006",
    "sg:postcode":"76015",
    "sg:province":"TX",
    "wof:name":"Soccer Stot",
    "wof:placetype":"venue"
},
  "geometry": {"coordinates":[-97.13481,32.680021],"type":"Point"}
}