{
  "type": "Feature",
  "properties": {
    "iso:country":"US",
    "sg:address":"4222 Fieldview Ct",
    "sg:city":"Fresno",
    "sg:classifiers":[
        {
            "category":"Freight",
            "type":"Transportation"
        }
    ],
    "sg:phone":"+1 713 806 8463",
    "sg:postcode":"77545",
    "sg:province":"TX",
    "sg:tags":[
        "operator",
        "local",
        "trucking"
    ],
    "wof:name":"Navys Freight Services",
    "wof:placetype":"venue"
},
  "geometry": {"coordinates":[-95.47837199999999,29.525571],"type":"Point"}
}