{
  "type": "Feature",
  "properties": {
    "iso:country":"US",
    "sg:address":"500 Southpark Dr",
    "sg:city":"Lufkin",
    "sg:classifiers":[
        {
            "category":"Building & Trades",
            "subcategory":"Construction",
            "type":"Services"
        }
    ],
    "sg:phone":"+1 936 633 0340",
    "sg:postcode":"75904",
    "sg:province":"TX",
    "sg:tags":[
        "marking",
        "maintenance",
        "parking"
    ],
    "sg:website":"www.cityoflufkin.com",
    "wof:name":"Lufkin Public Works Recycling",
    "wof:placetype":"venue"
},
  "geometry": {"coordinates":[-94.740961,31.2955],"type":"Point"}
}