{
  "type": "Feature",
  "properties": {
    "iso:country":"US",
    "sg:address":"554 Hampton Rd",
    "sg:city":"Conroe",
    "sg:classifiers":[
        {
            "category":"Freight",
            "type":"Transportation"
        }
    ],
    "sg:phone":"+1 713 932 7765",
    "sg:postcode":"77302",
    "sg:province":"TX",
    "wof:name":"Texas Bobtail Freight",
    "wof:placetype":"venue"
},
  "geometry": {"coordinates":[-95.443648,30.252517],"type":"Point"}
}