{
  "type": "Feature",
  "properties": {
    "iso:country":"US",
    "sg:address":"113 N Hill Ave",
    "sg:city":"Tyler",
    "sg:classifiers":[
        {
            "category":"Retail",
            "subcategory":"Auto Repair",
            "type":"Services"
        }
    ],
    "sg:phone":"+1 903 533 1085",
    "sg:postcode":"75702",
    "sg:province":"TX",
    "sg:tags":[
        "body",
        "automobile",
        "painting"
    ],
    "wof:name":"S & B Paint & Body Shop",
    "wof:placetype":"venue"
},
  "geometry": {"coordinates":[-95.317909,32.351584],"type":"Point"}
}