{
  "type": "Feature",
  "properties": {
    "iso:country":"US",
    "sg:address":"4304 John Reagan St",
    "sg:city":"Marshall",
    "sg:classifiers":[
        {
            "category":"Professional",
            "type":"Services"
        }
    ],
    "sg:phone":"+1 903 938 7448",
    "sg:postcode":"75672",
    "sg:province":"TX",
    "wof:name":"Brian Bradbury",
    "wof:placetype":"venue"
},
  "geometry": {"coordinates":[-94.318687,32.548986],"type":"Point"}
}