{
  "type": "Feature",
  "properties": {
    "iso:country":"US",
    "sg:address":"2081 E Division St",
    "sg:city":"Arlington",
    "sg:classifiers":[
        {
            "category":"Home & Garden",
            "subcategory":"Home Furnishings",
            "type":"Retail Goods"
        },
        {
            "category":"Shopping",
            "subcategory":"Crafts & Fabrics",
            "type":"Retail Goods"
        }
    ],
    "sg:phone":"+1 817 795 0900",
    "sg:postcode":"76011",
    "sg:province":"TX",
    "sg:tags":[
        "bedding",
        "material",
        "quilting",
        "quilt",
        "supply"
    ],
    "wof:name":"Quilts Among Friends",
    "wof:placetype":"venue"
},
  "geometry": {"coordinates":[-97.076655,32.742714],"type":"Point"}
}