{
  "type": "Feature",
  "properties": {
    "iso:country":"US",
    "sg:address":"1012 1st St",
    "sg:city":"Rosenberg",
    "sg:classifiers":[
        {
            "category":"Retail",
            "subcategory":"Auto Repair",
            "type":"Services"
        }
    ],
    "sg:phone":"+1 281 232 6222",
    "sg:postcode":"77471",
    "sg:province":"TX",
    "sg:tags":[
        "repairing",
        "automobile",
        "sale",
        "radiator",
        "automotive"
    ],
    "wof:name":"Bob's Radiator Works",
    "wof:placetype":"venue"
},
  "geometry": {"coordinates":[-95.808824,29.558118],"type":"Point"}
}