{
  "type": "Feature",
  "properties": {
    "iso:country":"US",
    "sg:address":"195 Triangle Dr",
    "sg:city":"Vidor",
    "sg:classifiers":[
        {
            "category":"Personal",
            "subcategory":"Beauty Salon",
            "type":"Services"
        },
        {
            "category":"Personal",
            "subcategory":"Nail Salon",
            "type":"Services"
        }
    ],
    "sg:phone":"+1 409 769 5551",
    "sg:postcode":"77662",
    "sg:province":"TX",
    "wof:name":"Della's Corner Hair & Nail Salon",
    "wof:placetype":"venue"
},
  "geometry": {"coordinates":[-94.023781,30.117292],"type":"Point"}
}