{
  "type": "Feature",
  "properties": {
    "iso:country":"US",
    "sg:address":"10126 Bayou Manor Ln",
    "sg:city":"Houston",
    "sg:classifiers":[
        {
            "category":"Wholesale",
            "subcategory":"Non-durable Goods",
            "type":"Manufacturing & Wholesale Goods"
        }
    ],
    "sg:phone":"+1 281 469 7216",
    "sg:postcode":"77064",
    "sg:province":"TX",
    "wof:name":"Sandhu Trading Co",
    "wof:placetype":"venue"
},
  "geometry": {"coordinates":[-95.57906199999999,29.918597],"type":"Point"}
}