{
  "type": "Feature",
  "properties": {
    "iso:country":"US",
    "sg:address":"10100 Reunion Pl",
    "sg:city":"San Antonio",
    "sg:classifiers":[
        {
            "category":"Shopping",
            "subcategory":"Stationery & Office Supplies",
            "type":"Retail Goods"
        }
    ],
    "sg:phone":"+1 210 349 7218",
    "sg:postcode":"78216",
    "sg:province":"TX",
    "sg:tags":[
        "business",
        "form"
    ],
    "wof:name":"Standard Register Company",
    "wof:placetype":"venue"
},
  "geometry": {"coordinates":[-98.483631,29.532838],"type":"Point"}
}