{
  "type": "Feature",
  "properties": {
    "iso:country":"US",
    "sg:address":"11521 Seagoville Rd",
    "sg:city":"Mesquite",
    "sg:classifiers":[
        {
            "category":"Farming",
            "subcategory":"Livestock Farm",
            "type":"Manufacturing & Wholesale Goods"
        }
    ],
    "sg:phone":"+1 972 286 4067",
    "sg:postcode":"75180",
    "sg:province":"TX",
    "sg:tags":[
        "beef",
        "feedlot",
        "cattle"
    ],
    "wof:name":"Chumely Engineering",
    "wof:placetype":"venue"
},
  "geometry": {"coordinates":[-96.62471600000001,32.704987],"type":"Point"}
}