{
  "type": "Feature",
  "properties": {
    "iso:country":"US",
    "sg:address":"1743 Mc Kinley St",
    "sg:city":"Brownsville",
    "sg:classifiers":[
        {
            "category":"Retail",
            "subcategory":"Repair Shop",
            "type":"Services"
        }
    ],
    "sg:phone":"+1 956 541 6373",
    "sg:postcode":"78521",
    "sg:province":"TX",
    "sg:tags":[
        "related"
    ],
    "wof:name":"Scratch N Fix",
    "wof:placetype":"venue"
},
  "geometry": {"coordinates":[-97.479749,25.909118],"type":"Point"}
}