{
  "type": "Feature",
  "properties": {
    "iso:country":"US",
    "sg:address":"103 Adobe Dr",
    "sg:city":"San Antonio",
    "sg:classifiers":[
        {
            "category":"Wholesale",
            "subcategory":"Electrical",
            "type":"Manufacturing & Wholesale Goods"
        }
    ],
    "sg:phone":"+1 210 366 4872",
    "sg:postcode":"78213",
    "sg:province":"TX",
    "sg:tags":[
        "alarm",
        "burglar",
        "system"
    ],
    "wof:name":"Alert Security Inc",
    "wof:placetype":"venue"
},
  "geometry": {"coordinates":[-98.5234,29.520354],"type":"Point"}
}