{
  "type": "Feature",
  "properties": {
    "iso:country":"US",
    "sg:address":"523 N 1st St",
    "sg:city":"Harlingen",
    "sg:classifiers":[
        {
            "category":"Shopping",
            "subcategory":"Used Merchandise",
            "type":"Retail Goods"
        }
    ],
    "sg:phone":"+1 956 425 5222",
    "sg:postcode":"78550",
    "sg:province":"TX",
    "wof:name":"Books N Things",
    "wof:placetype":"venue"
},
  "geometry": {"coordinates":[-97.695622,26.196953],"type":"Point"}
}