{
  "type": "Feature",
  "properties": {
    "iso:country":"US",
    "sg:address":"2801 Hemphill St",
    "sg:city":"Fort Worth",
    "sg:classifiers":[
        {
            "category":"Restaurant",
            "type":"Food & Drink"
        }
    ],
    "sg:phone":"+1 817 921 2346",
    "sg:postcode":"76110",
    "sg:province":"TX",
    "wof:name":"Taqueria San Luis",
    "wof:placetype":"venue"
},
  "geometry": {"coordinates":[-97.33163500000001,32.709536],"type":"Point"}
}