{
  "type": "Feature",
  "properties": {
    "iso:country":"US",
    "sg:address":"6310 Libyan Dr",
    "sg:city":"Austin",
    "sg:classifiers":[
        {
            "category":"Professional",
            "subcategory":"Computer Services",
            "type":"Services"
        }
    ],
    "sg:phone":"+1 512 443 0100",
    "sg:postcode":"78745",
    "sg:province":"TX",
    "sg:tags":[
        "consultant",
        "planning",
        "business"
    ],
    "wof:name":"Ross Business Systems",
    "wof:placetype":"venue"
},
  "geometry": {"coordinates":[-97.79501,30.204892],"type":"Point"}
}