{
  "type": "Feature",
  "properties": {
    "iso:country":"US",
    "sg:address":"3816 Hardin Rd",
    "sg:city":"Baytown",
    "sg:classifiers":[
        {
            "category":"Social Services",
            "subcategory":"Child Care",
            "type":"Services"
        }
    ],
    "sg:phone":"+1 281 427 1800",
    "sg:postcode":"77521",
    "sg:province":"TX",
    "wof:name":"Broussards Day Care",
    "wof:placetype":"venue"
},
  "geometry": {"coordinates":[-94.93782899999999,29.77114],"type":"Point"}
}