{
  "type": "Feature",
  "properties": {
    "iso:country":"US",
    "sg:address":"2502 N Main St Ste C",
    "sg:city":"Baytown",
    "sg:classifiers":[
        {
            "category":"Building & Trades",
            "subcategory":"Construction",
            "type":"Services"
        }
    ],
    "sg:phone":"+1 281 427 4493",
    "sg:postcode":"77520",
    "sg:province":"TX",
    "sg:tags":[
        "handyman"
    ],
    "wof:name":"S & S Lawnmower Repair",
    "wof:placetype":"venue"
},
  "geometry": {"coordinates":[-94.963703,29.74935],"type":"Point"}
}