{
  "type": "Feature",
  "properties": {
    "iso:country":"US",
    "sg:address":"1507 S Bolton St",
    "sg:city":"Jacksonville",
    "sg:classifiers":[
        {
            "category":"Building & Trades",
            "subcategory":"Construction",
            "type":"Services"
        }
    ],
    "sg:phone":"+1 903 586 0772",
    "sg:postcode":"75766",
    "sg:province":"TX",
    "sg:tags":[
        "shed",
        "utility"
    ],
    "wof:name":"Bass Storage Co",
    "wof:placetype":"venue"
},
  "geometry": {"coordinates":[-95.272245,31.947571],"type":"Point"}
}