{
  "type": "Feature",
  "properties": {
    "iso:country":"US",
    "sg:address":"13123 Winding Wood Dr",
    "sg:city":"Houston",
    "sg:classifiers":[
        {
            "category":"Professional",
            "type":"Services"
        }
    ],
    "sg:phone":"+1 281 445 4619",
    "sg:postcode":"77038",
    "sg:province":"TX",
    "wof:name":"Stained Glass Reflections",
    "wof:placetype":"venue"
},
  "geometry": {"coordinates":[-95.452465,29.924394],"type":"Point"}
}