{
  "type": "Feature",
  "properties": {
    "iso:country":"US",
    "sg:address":"308 W 7th St",
    "sg:city":"Sundown",
    "sg:classifiers":[
        {
            "category":"Social Services",
            "subcategory":"Job Training",
            "type":"Services"
        }
    ],
    "sg:phone":"+1 806 229 2153",
    "sg:postcode":"79372",
    "sg:province":"TX",
    "sg:tags":[
        "retardation",
        "disabled",
        "mental",
        "dev"
    ],
    "wof:name":"American Habilitation Svc",
    "wof:placetype":"venue"
},
  "geometry": {"coordinates":[-102.492974,33.459314],"type":"Point"}
}