{
  "type": "Feature",
  "properties": {
    "iso:country":"US",
    "sg:address":"5100 Twin City Hwy",
    "sg:city":"Groves",
    "sg:classifiers":[
        {
            "category":"Personal",
            "subcategory":"Beauty Salon",
            "type":"Services"
        }
    ],
    "sg:phone":"+1 409 962 3088",
    "sg:postcode":"77619",
    "sg:province":"TX",
    "sg:tags":[
        "shop"
    ],
    "wof:name":"Designer Nails",
    "wof:placetype":"venue"
},
  "geometry": {"coordinates":[-93.94342,29.943037],"type":"Point"}
}