{
  "type": "Feature",
  "properties": {
    "iso:country":"US",
    "sg:address":"6245 Renwick Dr",
    "sg:city":"Houston",
    "sg:classifiers":[
        {
            "category":"Shopping",
            "subcategory":"Discount & Variety Stores",
            "type":"Retail Goods"
        }
    ],
    "sg:phone":"+1 713 592 8363",
    "sg:postcode":"77081",
    "sg:province":"TX",
    "sg:tags":[
        "merchandise",
        "general"
    ],
    "wof:name":"AAA Things",
    "wof:placetype":"venue"
},
  "geometry": {"coordinates":[-95.484691,29.71307],"type":"Point"}
}