{
  "type": "Feature",
  "properties": {
    "iso:country":"US",
    "sg:address":"301 W White St",
    "sg:city":"Pilot Point",
    "sg:classifiers":[
        {
            "category":"Building & Trades",
            "subcategory":"Construction",
            "type":"Services"
        }
    ],
    "sg:phone":"+1 940 686 2143",
    "sg:postcode":"76258",
    "sg:province":"TX",
    "sg:tags":[
        "floor",
        "laying",
        "contractor"
    ],
    "wof:name":"Del Bosque Flooring",
    "wof:placetype":"venue"
},
  "geometry": {"coordinates":[-96.96432900000001,33.39213],"type":"Point"}
}