{
  "type": "Feature",
  "properties": {
    "iso:country":"US",
    "sg:address":"5127 Timber Shade Dr",
    "sg:city":"Humble",
    "sg:classifiers":[
        {
            "category":"Banks & Credit Unions",
            "subcategory":"Bank",
            "type":"Services"
        }
    ],
    "sg:phone":"+1 281 361 9700",
    "sg:postcode":"77345",
    "sg:province":"TX",
    "sg:tags":[
        "mortgage"
    ],
    "wof:name":"Morrison Financial Services LL",
    "wof:placetype":"venue"
},
  "geometry": {"coordinates":[-95.168108,30.052413],"type":"Point"}
}