{
  "type": "Feature",
  "properties": {
    "iso:country":"US",
    "sg:address":"1800 W Loop 281",
    "sg:city":"Longview",
    "sg:classifiers":[
        {
            "category":"Government",
            "subcategory":"Office",
            "type":"Public Place"
        }
    ],
    "sg:phone":"+1 903 297 3142",
    "sg:postcode":"75604",
    "sg:province":"TX",
    "sg:tags":[
        "policy"
    ],
    "wof:name":"Internal Revenue Service",
    "wof:placetype":"venue"
},
  "geometry": {"coordinates":[-94.78352099999999,32.523843],"type":"Point"}
}