{
  "type": "Feature",
  "properties": {
    "iso:country":"US",
    "sg:address":"1501 W 5th St Ste 108",
    "sg:city":"Austin",
    "sg:classifiers":[
        {
            "category":"Sports & Exercise",
            "subcategory":"Gym",
            "type":"Entertainment"
        }
    ],
    "sg:phone":"+1 512 461 1022",
    "sg:postcode":"78703",
    "sg:province":"TX",
    "sg:tags":[
        "trainer",
        "personal",
        "instruction",
        "equipment",
        "fitness",
        "pilate"
    ],
    "wof:name":"Animo Pilates",
    "wof:placetype":"venue"
},
  "geometry": {"coordinates":[-97.761848,30.273121],"type":"Point"}
}