{
  "type": "Feature",
  "properties": {
    "iso:country":"US",
    "sg:address":"3330 Lake Ridge Bend",
    "sg:city":"Spring",
    "sg:classifiers":[
        {
            "category":"Manufacturing",
            "subcategory":"Apparel",
            "type":"Manufacturing & Wholesale Goods"
        }
    ],
    "sg:phone":"+1 281 419 1159",
    "sg:postcode":"77380",
    "sg:province":"TX",
    "wof:name":"Embroidery Creations Housto",
    "wof:placetype":"venue"
},
  "geometry": {"coordinates":[-95.493689,30.133751],"type":"Point"}
}