{
  "type": "Feature",
  "properties": {
    "iso:country":"US",
    "sg:address":"789 Anson Ave",
    "sg:city":"Abilene",
    "sg:classifiers":[
        {
            "category":"Mining & Drilling",
            "type":"Manufacturing & Wholesale Goods"
        }
    ],
    "sg:phone":"+1 325 676 9349",
    "sg:postcode":"79601",
    "sg:province":"TX",
    "sg:tags":[
        "operator",
        "oil"
    ],
    "wof:name":"Humphrey-Bashford Oil Inc",
    "wof:placetype":"venue"
},
  "geometry": {"coordinates":[-99.72768600000001,32.486701],"type":"Point"}
}