{
  "type": "Feature",
  "properties": {
    "iso:country":"US",
    "sg:address":"10802 Rampart St",
    "sg:city":"Houston",
    "sg:classifiers":[
        {
            "category":"Professional",
            "subcategory":"Engineering",
            "type":"Services"
        }
    ],
    "sg:phone":"+1 713 721 3142",
    "sg:postcode":"77096",
    "sg:province":"TX",
    "wof:name":"Applied Gfx Inc",
    "wof:placetype":"venue"
},
  "geometry": {"coordinates":[-95.490137,29.661445],"type":"Point"}
}