{
  "type": "Feature",
  "properties": {
    "iso:country":"US",
    "sg:address":"103 E Belt Line Rd Ste E",
    "sg:city":"Cedar Hill",
    "sg:classifiers":[
        {
            "category":"Professional",
            "subcategory":"Accounting & Tax Preparation",
            "type":"Services"
        }
    ],
    "sg:phone":"+1 972 293 8224",
    "sg:postcode":"75104",
    "sg:province":"TX",
    "sg:tags":[
        "accountant"
    ],
    "wof:name":"Logan Thaland D CPA",
    "wof:placetype":"venue"
},
  "geometry": {"coordinates":[-96.94229900000001,32.59],"type":"Point"}
}