{
  "type": "Feature",
  "properties": {
    "iso:country":"US",
    "sg:address":"4801 Allendale Rd Ofc",
    "sg:city":"Houston",
    "sg:classifiers":[
        {
            "category":"Social Services",
            "subcategory":"Retirement Home",
            "type":"Services"
        }
    ],
    "sg:phone":"+1 713 941 7700",
    "sg:postcode":"77017",
    "sg:province":"TX",
    "wof:name":"Oak Shadows Allendale Retirement Community",
    "wof:placetype":"venue"
},
  "geometry": {"coordinates":[-95.25839999999999,29.680201],"type":"Point"}
}