{
  "type": "Feature",
  "properties": {
    "iso:country":"US",
    "sg:address":"427 S Durham Ave",
    "sg:city":"Crosbyton",
    "sg:classifiers":[
        {
            "category":"Manufacturing",
            "subcategory":"Tools & Machinery",
            "type":"Manufacturing & Wholesale Goods"
        }
    ],
    "sg:phone":"+1 806 675 2059",
    "sg:postcode":"79322",
    "sg:province":"TX",
    "sg:tags":[
        "equipment",
        "mfg"
    ],
    "wof:name":"Palacios Repair Shop",
    "wof:placetype":"venue"
},
  "geometry": {"coordinates":[-101.241776,33.65558],"type":"Point"}
}