{
  "type": "Feature",
  "properties": {
    "iso:country":"US",
    "sg:address":"3333 Coulter St",
    "sg:city":"Amarillo",
    "sg:classifiers":[
        {
            "category":"Utilities",
            "subcategory":"Mobile Phone",
            "type":"Services"
        },
        {
            "category":"Shopping",
            "type":"Retail Goods"
        }
    ],
    "sg:phone":"+1 806 331 1699",
    "sg:postcode":"79106",
    "sg:province":"TX",
    "sg:tags":[
        "merchandise",
        "cellular",
        "telephone"
    ],
    "wof:name":"B Wireless",
    "wof:placetype":"venue"
},
  "geometry": {"coordinates":[-101.920208,35.17735],"type":"Point"}
}