{
  "type": "Feature",
  "properties": {
    "iso:country":"US",
    "sg:address":"1900 Strawberry Rd Ste F",
    "sg:city":"Pasadena",
    "sg:classifiers":[
        {
            "category":"Personal",
            "subcategory":"Nail Salon",
            "type":"Services"
        }
    ],
    "sg:phone":"+1 713 477 1429",
    "sg:postcode":"77502",
    "sg:province":"TX",
    "wof:name":"New Look Nails",
    "wof:placetype":"venue"
},
  "geometry": {"coordinates":[-95.19319900000001,29.684799],"type":"Point"}
}