{
  "type": "Feature",
  "properties": {
    "iso:country":"US",
    "sg:address":"6520 Stewart Rd",
    "sg:city":"Galveston",
    "sg:classifiers":[
        {
            "category":"Home & Garden",
            "subcategory":"Building Materials",
            "type":"Retail Goods"
        }
    ],
    "sg:phone":"+1 409 744 7181",
    "sg:postcode":"77551",
    "sg:province":"TX",
    "sg:tags":[
        "hardware",
        "lumber",
        "store"
    ],
    "sg:website":"http://www.ideal.doitbest.com",
    "wof:name":"Ideal Lumber Co.",
    "wof:placetype":"venue"
},
  "geometry": {"coordinates":[-94.835233,29.273788],"type":"Point"}
}