{
  "type": "Feature",
  "properties": {
    "iso:country":"US",
    "sg:address":"213 Black Oak Cir",
    "sg:city":"Coppell",
    "sg:classifiers":[
        {
            "category":"Building & Trades",
            "subcategory":"Construction",
            "type":"Services"
        }
    ],
    "sg:phone":"+1 972 745 0022",
    "sg:postcode":"75019",
    "sg:province":"TX",
    "wof:name":"Nalbantova Danka",
    "wof:placetype":"venue"
},
  "geometry": {"coordinates":[-96.994426,32.975834],"type":"Point"}
}