{
  "type": "Feature",
  "properties": {
    "iso:country":"US",
    "sg:address":"4201 S Medford Dr",
    "sg:city":"Lufkin",
    "sg:classifiers":[
        {
            "category":"Restaurant",
            "type":"Food & Drink"
        }
    ],
    "sg:menulink":"http://www.allmenus.com/tx/lufkin/99575-logans-roadhouse/menu/",
    "sg:phone":"+1 936 632 0929",
    "sg:postcode":"75901",
    "sg:province":"TX",
    "sg:tags":[
        "american"
    ],
    "wof:name":"Logan's Roadhouse",
    "wof:placetype":"venue"
},
  "geometry": {"coordinates":[-94.719775,31.312673],"type":"Point"}
}