{
  "type": "Feature",
  "properties": {
    "iso:country":"US",
    "sg:address":"3406 McNiel Ave",
    "sg:city":"Wichita Falls",
    "sg:phone":"+1 940 689 9276",
    "sg:postcode":"76308",
    "sg:province":"TX",
    "sg:tags":[
        "oil"
    ],
    "wof:name":"BMH Oil Co Inc",
    "wof:placetype":"venue"
},
  "geometry": {"coordinates":[-98.547749,33.878239],"type":"Point"}
}