{
  "type": "Feature",
  "properties": {
    "iso:country":"US",
    "sg:address":"1900 Greenville Ave",
    "sg:city":"Dallas",
    "sg:classifiers":[
        {
            "category":"Autos & Motor Vehicles",
            "subcategory":"Motorcycle Sales",
            "type":"Retail Goods"
        }
    ],
    "sg:phone":"+1 214 821 3616",
    "sg:postcode":"75206",
    "sg:province":"TX",
    "sg:tags":[
        "scooters-parts",
        "supply"
    ],
    "wof:name":"Southwest Choppers",
    "wof:placetype":"venue"
},
  "geometry": {"coordinates":[-96.770026,32.81268],"type":"Point"}
}