{
  "type": "Feature",
  "properties": {
    "iso:country":"US",
    "sg:address":"1 Oak Hill Pl",
    "sg:city":"Texarkana",
    "sg:classifiers":[
        {
            "category":"Shopping",
            "subcategory":"Clothing, Apparel, & Fashions",
            "type":"Retail Goods"
        }
    ],
    "sg:phone":"+1 903 793 1464",
    "sg:postcode":"75503",
    "sg:province":"TX",
    "sg:tags":[
        "family"
    ],
    "wof:name":"Cire",
    "wof:placetype":"venue"
},
  "geometry": {"coordinates":[-94.05307999999999,33.443779],"type":"Point"}
}