{
  "type": "Feature",
  "properties": {
    "iso:country":"US",
    "sg:address":"14623 Oak Bend Dr",
    "sg:city":"Houston",
    "sg:classifiers":[
        {
            "category":"Mining & Drilling",
            "type":"Manufacturing & Wholesale Goods"
        }
    ],
    "sg:phone":"+1 281 493 2702",
    "sg:postcode":"77079",
    "sg:province":"TX",
    "sg:tags":[
        "crude",
        "production",
        "management",
        "gas"
    ],
    "wof:name":"Illinois Coal Gas Inc",
    "wof:placetype":"venue"
},
  "geometry": {"coordinates":[-95.60809999999999,29.763787],"type":"Point"}
}