{
  "type": "Feature",
  "properties": {
    "iso:country":"US",
    "sg:address":"1810 Mariposa Dr",
    "sg:city":"Dallas",
    "sg:classifiers":[
        {
            "category":"Professional",
            "subcategory":"Business Services",
            "type":"Services"
        }
    ],
    "sg:phone":"+1 214 319 7655",
    "sg:postcode":"75228",
    "sg:province":"TX",
    "wof:name":"Errands 2do",
    "wof:placetype":"venue"
},
  "geometry": {"coordinates":[-96.69023900000001,32.823874],"type":"Point"}
}