{
  "type": "Feature",
  "properties": {
    "iso:country":"US",
    "sg:address":"505 Beverly Dr",
    "sg:city":"Wichita Falls",
    "sg:classifiers":[
        {
            "category":"Professional",
            "subcategory":"Detective & Security Services",
            "type":"Services"
        }
    ],
    "sg:phone":"+1 940 692 7331",
    "sg:postcode":"76309",
    "sg:province":"TX",
    "sg:tags":[
        "system"
    ],
    "wof:name":"24 7 Home Security Inc",
    "wof:placetype":"venue"
},
  "geometry": {"coordinates":[-98.53180500000001,33.904069],"type":"Point"}
}