{
  "type": "Feature",
  "properties": {
    "iso:country":"US",
    "sg:address":"4381 US Hwy 377",
    "sg:city":"Aubrey",
    "sg:classifiers":[
        {
            "category":"Autos & Motor Vehicles",
            "subcategory":"Automobile Sales",
            "type":"Retail Goods"
        }
    ],
    "sg:phone":"+1 940 440 9321",
    "sg:postcode":"76227",
    "sg:province":"TX",
    "sg:tags":[
        "car",
        "dealer"
    ],
    "wof:name":"Paaco Automotive Group",
    "wof:placetype":"venue"
},
  "geometry": {"coordinates":[-96.98821,33.248439],"type":"Point"}
}