{
  "type": "Feature",
  "properties": {
    "iso:country":"US",
    "sg:address":"6656 Whitemarsh Valley Walk",
    "sg:city":"Austin",
    "sg:classifiers":[
        {
            "category":"Autos & Motor Vehicles",
            "subcategory":"Fuel & Gas Station",
            "type":"Retail Goods"
        }
    ],
    "sg:phone":"+1 512 327 1127",
    "sg:postcode":"78746",
    "sg:province":"TX",
    "sg:tags":[
        "stop",
        "truck"
    ],
    "wof:name":"Truckers Heaven",
    "wof:placetype":"venue"
},
  "geometry": {"coordinates":[-97.83529299999999,30.28863],"type":"Point"}
}