{
  "type": "Feature",
  "properties": {
    "iso:country":"US",
    "sg:address":"223 Cavalcade St",
    "sg:city":"Houston",
    "sg:classifiers":[
        {
            "category":"Personal",
            "subcategory":"Barber",
            "type":"Services"
        }
    ],
    "sg:phone":"+1 713 742 0900",
    "sg:postcode":"77009",
    "sg:province":"TX",
    "sg:tags":[
        "shop"
    ],
    "wof:name":"Clipper Joint",
    "wof:placetype":"venue"
},
  "geometry": {"coordinates":[-95.368628,29.803253],"type":"Point"}
}