{
  "type": "Feature",
  "properties": {
    "iso:country":"US",
    "sg:address":"812 W 2nd Ave",
    "sg:city":"Corsicana",
    "sg:classifiers":[
        {
            "category":"Real Estate",
            "subcategory":"Real Estate Agent",
            "type":"Services"
        }
    ],
    "sg:phone":"+1 903 874 7015",
    "sg:postcode":"75110",
    "sg:province":"TX",
    "wof:name":"Bennie R Sammons",
    "wof:placetype":"venue"
},
  "geometry": {"coordinates":[-96.473527,32.093588],"type":"Point"}
}