{
  "type": "Feature",
  "properties": {
    "iso:country":"US",
    "sg:address":"721 Sue Ann Ln",
    "sg:city":"Burleson",
    "sg:classifiers":[
        {
            "category":"Autos & Motor Vehicles",
            "subcategory":"Auto Supplies",
            "type":"Retail Goods"
        }
    ],
    "sg:phone":"+1 817 447 7000",
    "sg:postcode":"76028",
    "sg:province":"TX",
    "sg:tags":[
        "automobile",
        "part"
    ],
    "wof:name":"Scotts American Truck Parts",
    "wof:placetype":"venue"
},
  "geometry": {"coordinates":[-97.330585,32.526118],"type":"Point"}
}