{
  "type": "Feature",
  "properties": {
    "iso:country":"US",
    "sg:address":"470 S Main St",
    "sg:city":"Boerne",
    "sg:classifiers":[
        {
            "category":"Shopping",
            "subcategory":"Used Merchandise",
            "type":"Retail Goods"
        }
    ],
    "sg:phone":"+1 830 249 9386",
    "sg:postcode":"78006",
    "sg:province":"TX",
    "sg:tags":[
        "antique"
    ],
    "wof:name":"Tri K Antiques",
    "wof:placetype":"venue"
},
  "geometry": {"coordinates":[-98.72985199999999,29.789905],"type":"Point"}
}