{
  "type": "Feature",
  "properties": {
    "iso:country":"US",
    "sg:address":"800 W 34th St",
    "sg:city":"Austin",
    "sg:classifiers":[
        {
            "category":"Social Services",
            "subcategory":"Job Training",
            "type":"Services"
        }
    ],
    "sg:phone":"+1 512 454 4599",
    "sg:postcode":"78705",
    "sg:province":"TX",
    "sg:tags":[
        "rehabilitation"
    ],
    "wof:name":"Sante Rehabilitation",
    "wof:placetype":"venue"
},
  "geometry": {"coordinates":[-97.743718,30.302218],"type":"Point"}
}