{
  "type": "Feature",
  "properties": {
    "iso:country":"US",
    "sg:address":"1106 S Blackburn St",
    "sg:city":"Brady",
    "sg:classifiers":[
        {
            "category":"Education",
            "subcategory":"Library",
            "type":"Public Place"
        }
    ],
    "sg:phone":"+1 325 597 2617",
    "sg:postcode":"76825",
    "sg:province":"TX",
    "wof:name":"F M Richards Library",
    "wof:placetype":"venue"
},
  "geometry": {"coordinates":[-99.334271,31.127241],"type":"Point"}
}