{
  "type": "Feature",
  "properties": {
    "iso:country":"US",
    "sg:address":"929 Rosedale Dr",
    "sg:city":"Hewitt",
    "sg:phone":"+1 254 857 3500",
    "sg:postcode":"76643",
    "sg:province":"TX",
    "sg:tags":[
        "scale"
    ],
    "wof:name":"Heart O'Texas Callibration",
    "wof:placetype":"venue"
},
  "geometry": {"coordinates":[-97.193376,31.426395],"type":"Point"}
}