{
  "type": "Feature",
  "properties": {
    "iso:country":"US",
    "sg:address":"5700 Granite Pkwy",
    "sg:city":"Plano",
    "sg:classifiers":[
        {
            "category":"Building & Trades",
            "subcategory":"Construction",
            "type":"Services"
        }
    ],
    "sg:phone":"+1 972 731 2580",
    "sg:postcode":"75024",
    "sg:province":"TX",
    "sg:tags":[
        "new",
        "commercial"
    ],
    "wof:name":"Meridian Landscapes Ltd Co",
    "wof:placetype":"venue"
},
  "geometry": {"coordinates":[-96.81727600000001,33.086931],"type":"Point"}
}