{
  "type": "Feature",
  "properties": {
    "iso:country":"US",
    "sg:address":"118 Mill Valley Dr",
    "sg:city":"Colleyville",
    "sg:classifiers":[
        {
            "category":"Food & Beverages",
            "subcategory":"Bakery",
            "type":"Retail Goods"
        },
        {
            "category":"Wholesale",
            "subcategory":"Groceries",
            "type":"Manufacturing & Wholesale Goods"
        }
    ],
    "sg:phone":"+1 817 281 0220",
    "sg:postcode":"76034",
    "sg:province":"TX",
    "sg:tags":[
        "cooky",
        "crackers-wholesale",
        "bakers-wholesale",
        "manufacturer"
    ],
    "wof:name":"Polka Dots Cookies & Cupcakes",
    "wof:placetype":"venue"
},
  "geometry": {"coordinates":[-97.167458,32.875274],"type":"Point"}
}