{
  "type": "Feature",
  "properties": {
    "iso:country":"US",
    "sg:address":"104 W 1st St",
    "sg:city":"Elgin",
    "sg:classifiers":[
        {
            "category":"Professional",
            "type":"Services"
        }
    ],
    "sg:phone":"+1 512 281 4310",
    "sg:postcode":"78621",
    "sg:province":"TX",
    "sg:tags":[
        "establishment"
    ],
    "wof:name":"Geneti Source Inc",
    "wof:placetype":"venue"
},
  "geometry": {"coordinates":[-97.370858,30.348646],"type":"Point"}
}