{
  "type": "Feature",
  "properties": {
    "iso:country":"US",
    "sg:address":"1035 W Abram St",
    "sg:city":"Arlington",
    "sg:classifiers":[
        {
            "category":"Professional",
            "subcategory":"Printing & Photocopies",
            "type":"Services"
        }
    ],
    "sg:phone":"+1 817 277 6226",
    "sg:postcode":"76013",
    "sg:province":"TX",
    "sg:tags":[
        "laboratory",
        "blueprinting",
        "photofinishing",
        "photocopying"
    ],
    "wof:name":"L A Blueline Inc",
    "wof:placetype":"venue"
},
  "geometry": {"coordinates":[-97.11961599999999,32.735863],"type":"Point"}
}