{
  "type": "Feature",
  "properties": {
    "iso:country":"US",
    "sg:address":"1845 Garrett Ln",
    "sg:city":"China Spring",
    "sg:classifiers":[
        {
            "category":"Personal",
            "type":"Services"
        }
    ],
    "sg:phone":"+1 254 836 9188",
    "sg:postcode":"76633",
    "sg:province":"TX",
    "wof:name":"Vonco Co of Waco",
    "wof:placetype":"venue"
},
  "geometry": {"coordinates":[-97.32557300000001,31.672126],"type":"Point"}
}