{
  "type": "Feature",
  "properties": {
    "iso:country":"US",
    "sg:address":"11309 January Dr",
    "sg:city":"Austin",
    "sg:classifiers":[
        {
            "category":"Home & Garden",
            "subcategory":"Furniture",
            "type":"Retail Goods"
        }
    ],
    "sg:phone":"+1 512 567 8852",
    "sg:postcode":"78753",
    "sg:province":"TX",
    "sg:tags":[
        "renting",
        "leasing"
    ],
    "wof:name":"Austin Chair & Table Rental",
    "wof:placetype":"venue"
},
  "geometry": {"coordinates":[-97.667581,30.373348],"type":"Point"}
}