{
  "type": "Feature",
  "properties": {
    "iso:country":"US",
    "sg:address":"8242 US Hwy 67",
    "sg:city":"Glen Rose",
    "sg:classifiers":[
        {
            "category":"Restaurant",
            "type":"Food & Drink"
        }
    ],
    "sg:phone":"+1 254 898 1571",
    "sg:postcode":"76043",
    "sg:province":"TX",
    "wof:name":"V Bar Brand Restaurant & Steak",
    "wof:placetype":"venue"
},
  "geometry": {"coordinates":[-97.89124099999999,32.170105],"type":"Point"}
}