{
  "type": "Feature",
  "properties": {
    "iso:country":"US",
    "sg:address":"3324 Southmost Rd",
    "sg:city":"Brownsville",
    "sg:classifiers":[
        {
            "category":"Food & Beverages",
            "subcategory":"Bakery",
            "type":"Retail Goods"
        }
    ],
    "sg:phone":"+1 956 504 1379",
    "sg:postcode":"78521",
    "sg:province":"TX",
    "sg:tags":[
        "baker"
    ],
    "wof:name":"Panaderia El Az",
    "wof:placetype":"venue"
},
  "geometry": {"coordinates":[-97.456418,25.902343],"type":"Point"}
}