{
  "type": "Feature",
  "properties": {
    "iso:country":"US",
    "sg:address":"2834 Quincannon Ln",
    "sg:city":"Houston",
    "sg:classifiers":[
        {
            "category":"Health Services",
            "subcategory":"Medical Lab",
            "type":"Services"
        }
    ],
    "sg:phone":"+1 713 462 6781",
    "sg:postcode":"77043",
    "sg:province":"TX",
    "sg:tags":[
        "laboratory",
        "dental"
    ],
    "wof:name":"Michel Ceramic Laboratories",
    "wof:placetype":"venue"
},
  "geometry": {"coordinates":[-95.55641199999999,29.82291],"type":"Point"}
}