{
  "type": "Feature",
  "properties": {
    "iso:country":"US",
    "sg:address":"4512 Sidereal Dr",
    "sg:city":"Austin",
    "sg:classifiers":[
        {
            "category":"Professional",
            "subcategory":"Research",
            "type":"Services"
        }
    ],
    "sg:phone":"+1 512 821 2879",
    "sg:postcode":"78727",
    "sg:province":"TX",
    "sg:tags":[
        "market",
        "analysis"
    ],
    "wof:name":"Research Spectrum",
    "wof:placetype":"venue"
},
  "geometry": {"coordinates":[-97.72161199999999,30.427982],"type":"Point"}
}