{
  "type": "Feature",
  "properties": {
    "iso:country":"US",
    "sg:address":"2304 Dunlavy St",
    "sg:city":"Houston",
    "sg:classifiers":[
        {
            "category":"Mining & Drilling",
            "type":"Manufacturing & Wholesale Goods"
        }
    ],
    "sg:phone":"+1 713 623 6116",
    "sg:postcode":"77006",
    "sg:province":"TX",
    "sg:tags":[
        "development",
        "gas",
        "oil",
        "exploration"
    ],
    "wof:name":"Buffalo Petroleum",
    "wof:placetype":"venue"
},
  "geometry": {"coordinates":[-95.40216100000001,29.744793],"type":"Point"}
}