{
  "type": "Feature",
  "properties": {
    "iso:country":"US",
    "sg:address":"2810 E Trinity Mills Rd Ste 173",
    "sg:city":"Carrollton",
    "sg:classifiers":[
        {
            "category":"Health Services",
            "subcategory":"Optometrist",
            "type":"Services"
        }
    ],
    "sg:phone":"+1 972 416 1270",
    "sg:postcode":"75006",
    "sg:province":"TX",
    "sg:website":"www.1steyecare.com",
    "wof:name":"1st Eye Care",
    "wof:placetype":"venue"
},
  "geometry": {"coordinates":[-96.854401,32.9869],"type":"Point"}
}