{
  "type": "Feature",
  "properties": {
    "iso:country":"US",
    "sg:address":"8201 Manderville Ln",
    "sg:city":"Dallas",
    "sg:classifiers":[
        {
            "category":"Professional",
            "type":"Services"
        }
    ],
    "sg:phone":"+1 214 750 1521",
    "sg:postcode":"75231",
    "sg:province":"TX",
    "sg:tags":[
        "establishment"
    ],
    "wof:name":"Heart House Dakota",
    "wof:placetype":"venue"
},
  "geometry": {"coordinates":[-96.76526800000001,32.892178],"type":"Point"}
}