{
  "type": "Feature",
  "properties": {
    "iso:country":"US",
    "sg:address":"2610 Walnut Hill Ln",
    "sg:city":"Dallas",
    "sg:classifiers":[
        {
            "category":"Restaurant",
            "type":"Food & Drink"
        }
    ],
    "sg:phone":"+1 214 956 7200",
    "sg:postcode":"75229",
    "sg:province":"TX",
    "sg:tags":[
        "style",
        "family"
    ],
    "wof:name":"El Forastero Restaurant",
    "wof:placetype":"venue"
},
  "geometry": {"coordinates":[-96.88996299999999,32.881031],"type":"Point"}
}