{
  "type": "Feature",
  "properties": {
    "iso:country":"US",
    "sg:address":"11330 E Coker Loop",
    "sg:city":"San Antonio",
    "sg:classifiers":[
        {
            "category":"Building & Trades",
            "subcategory":"Construction",
            "type":"Services"
        }
    ],
    "sg:phone":"+1 210 490 0598",
    "sg:postcode":"78216",
    "sg:province":"TX",
    "sg:tags":[
        "concrete",
        "work"
    ],
    "wof:name":"Concrete Concepts",
    "wof:placetype":"venue"
},
  "geometry": {"coordinates":[-98.48093900000001,29.548375],"type":"Point"}
}