{
  "type": "Feature",
  "properties": {
    "iso:country":"US",
    "sg:address":"1027 Allen St",
    "sg:city":"Irving",
    "sg:classifiers":[
        {
            "category":"Building & Trades",
            "subcategory":"Construction",
            "type":"Services"
        }
    ],
    "sg:phone":"+1 972 438 1717",
    "sg:postcode":"75060",
    "sg:province":"TX",
    "sg:tags":[
        "maker",
        "cabinet"
    ],
    "wof:name":"Woodcrafters",
    "wof:placetype":"venue"
},
  "geometry": {"coordinates":[-96.92071799999999,32.803806],"type":"Point"}
}