{
  "type": "Feature",
  "properties": {
    "iso:country":"US",
    "sg:address":"8801 Woodway Dr",
    "sg:city":"Waco",
    "sg:classifiers":[
        {
            "category":"Real Estate",
            "subcategory":"Real Estate Agent",
            "type":"Services"
        }
    ],
    "sg:phone":"+1 254 776 3734",
    "sg:postcode":"76712",
    "sg:province":"TX",
    "sg:tags":[
        "appraiser"
    ],
    "wof:name":"Millard Real Estate Advisors",
    "wof:placetype":"venue"
},
  "geometry": {"coordinates":[-97.217073,31.49834],"type":"Point"}
}