{
  "type": "Feature",
  "properties": {
    "iso:country":"US",
    "sg:address":"550 Grapevine Hwy",
    "sg:city":"Hurst",
    "sg:classifiers":[
        {
            "category":"Professional",
            "subcategory":"Business Services",
            "type":"Services"
        }
    ],
    "sg:phone":"+1 817 656 0609",
    "sg:postcode":"76054",
    "sg:province":"TX",
    "wof:name":"Sales Acceloraters",
    "wof:placetype":"venue"
},
  "geometry": {"coordinates":[-97.17694299999999,32.863383],"type":"Point"}
}