{
  "type": "Feature",
  "properties": {
    "iso:country":"US",
    "sg:address":"526 Towne House Ln",
    "sg:city":"Richardson",
    "sg:classifiers":[
        {
            "category":"Professional",
            "type":"Services"
        }
    ],
    "sg:phone":"+1 972 766 6754",
    "sg:postcode":"75081",
    "sg:province":"TX",
    "wof:name":"Sylvia Sanchez",
    "wof:placetype":"venue"
},
  "geometry": {"coordinates":[-96.71518399999999,32.942531],"type":"Point"}
}