{
  "type": "Feature",
  "properties": {
    "iso:country":"US",
    "sg:address":"3601 Camp Bowie Blvd",
    "sg:city":"Fort Worth",
    "sg:classifiers":[
        {
            "category":"Restaurant",
            "type":"Food & Drink"
        }
    ],
    "sg:menulink":"http://www.allmenus.com/tx/fort-worth/202480-mcdonalds/menu/",
    "sg:postcode":"76107",
    "sg:province":"TX",
    "sg:tags":[
        "burger",
        "american"
    ],
    "wof:name":"McDonald's",
    "wof:placetype":"venue"
},
  "geometry": {"coordinates":[-97.370574,32.747154],"type":"Point"}
}