{
  "type": "Feature",
  "properties": {
    "iso:country":"US",
    "sg:address":"2314 W 44th St",
    "sg:city":"Odessa",
    "sg:classifiers":[
        {
            "category":"Wholesale",
            "subcategory":"Machinery & Supplies",
            "type":"Manufacturing & Wholesale Goods"
        }
    ],
    "sg:phone":"+1 432 368 9318",
    "sg:postcode":"79764",
    "sg:province":"TX",
    "sg:tags":[
        "field",
        "oil",
        "equipment"
    ],
    "wof:name":"C & C Packer Svc",
    "wof:placetype":"venue"
},
  "geometry": {"coordinates":[-102.411782,31.880006],"type":"Point"}
}