{
  "type": "Feature",
  "properties": {
    "iso:country":"US",
    "sg:address":"5937 Plum St",
    "sg:city":"Fort Worth",
    "sg:classifiers":[
        {
            "category":"Wholesale",
            "subcategory":"Construction Materials",
            "type":"Manufacturing & Wholesale Goods"
        }
    ],
    "sg:phone":"+1 817 281 6861",
    "sg:postcode":"76148",
    "sg:province":"TX",
    "sg:tags":[
        "repair"
    ],
    "wof:name":"K E Services",
    "wof:placetype":"venue"
},
  "geometry": {"coordinates":[-97.26266,32.855504],"type":"Point"}
}