{
  "type": "Feature",
  "properties": {
    "iso:country":"US",
    "sg:address":"12271 Plano Rd",
    "sg:city":"Dallas",
    "sg:classifiers":[
        {
            "category":"Shopping",
            "subcategory":"Computers & Home Electronics",
            "type":"Retail Goods"
        }
    ],
    "sg:phone":"+1 972 690 7033",
    "sg:postcode":"75243",
    "sg:province":"TX",
    "sg:tags":[
        "software"
    ],
    "wof:name":"Techville Computer Ctr",
    "wof:placetype":"venue"
},
  "geometry": {"coordinates":[-96.70052200000001,32.913303],"type":"Point"}
}