{
  "type": "Feature",
  "properties": {
    "iso:country":"US",
    "sg:address":"200 Hall Rd",
    "sg:city":"Seagoville",
    "sg:classifiers":[
        {
            "category":"Restaurant",
            "type":"Food & Drink"
        }
    ],
    "sg:phone":"+1 972 287 4126",
    "sg:postcode":"75159",
    "sg:province":"TX",
    "wof:name":"Granny's Fried Chicken",
    "wof:placetype":"venue"
},
  "geometry": {"coordinates":[-96.54763199999999,32.648902],"type":"Point"}
}