{
  "type": "Feature",
  "properties": {
    "iso:country":"US",
    "sg:address":"2347 Bisontine St",
    "sg:city":"Friendswood",
    "sg:classifiers":[
        {
            "category":"Shopping",
            "subcategory":"Stationery & Office Supplies",
            "type":"Retail Goods"
        }
    ],
    "sg:phone":"+1 281 648 1834",
    "sg:postcode":"77546",
    "sg:province":"TX",
    "wof:name":"Progressive Trading",
    "wof:placetype":"venue"
},
  "geometry": {"coordinates":[-95.168617,29.541907],"type":"Point"}
}