{
  "type": "Feature",
  "properties": {
    "iso:country":"US",
    "sg:address":"2800 8th Ave",
    "sg:city":"Fort Worth",
    "sg:classifiers":[
        {
            "category":"Restaurant",
            "type":"Food & Drink"
        }
    ],
    "sg:phone":"+1 817 920 9939",
    "sg:postcode":"76110",
    "sg:province":"TX",
    "sg:tags":[
        "eating"
    ],
    "wof:name":"Lubys",
    "wof:placetype":"venue"
},
  "geometry": {"coordinates":[-97.3439,32.71089],"type":"Point"}
}