{
  "type": "Feature",
  "properties": {
    "iso:country":"US",
    "sg:address":"1704 Chalk Cove",
    "sg:city":"Cedar Park",
    "sg:classifiers":[
        {
            "category":"Retail",
            "subcategory":"Repair Shop",
            "type":"Services"
        }
    ],
    "sg:phone":"+1 512 633 0862",
    "sg:postcode":"78613",
    "sg:province":"TX",
    "wof:name":"Bauers Paintless Dent Repair",
    "wof:placetype":"venue"
},
  "geometry": {"coordinates":[-97.844627,30.484672],"type":"Point"}
}