{
  "type": "Feature",
  "properties": {
    "iso:country":"US",
    "sg:address":"3730 Taylor Ave",
    "sg:city":"El Paso",
    "sg:classifiers":[
        {
            "category":"Freight",
            "type":"Transportation"
        }
    ],
    "sg:phone":"+1 915 562 3347",
    "sg:postcode":"79930",
    "sg:province":"TX",
    "sg:tags":[
        "motor"
    ],
    "wof:name":"Falc Enterprises LLC",
    "wof:placetype":"venue"
},
  "geometry": {"coordinates":[-106.448089,31.816445],"type":"Point"}
}