{
  "type": "Feature",
  "properties": {
    "iso:country":"US",
    "sg:address":"95 Rainey St",
    "sg:city":"Austin",
    "sg:classifiers":[
        {
            "category":"Juice Bar",
            "subcategory":"None",
            "type":"Food & Drink"
        }
    ],
    "sg:postcode":"78701",
    "sg:province":"TX",
    "sg:tags":[
        "smoothy"
    ],
    "wof:name":"Baltimore Ballers",
    "wof:placetype":"venue"
},
  "geometry": {"coordinates":[-97.73781099999999,30.260522],"type":"Point"}
}