{
  "type": "Feature",
  "properties": {
    "iso:country":"US",
    "sg:address":"102 Walnut Way",
    "sg:city":"Euless",
    "sg:classifiers":[
        {
            "category":"Shopping",
            "subcategory":"Discount & Variety Stores",
            "type":"Retail Goods"
        }
    ],
    "sg:phone":"+1 817 283 0906",
    "sg:postcode":"76039",
    "sg:province":"TX",
    "sg:tags":[
        "merchandise",
        "general"
    ],
    "wof:name":"Sevan Merchandising Co",
    "wof:placetype":"venue"
},
  "geometry": {"coordinates":[-97.086253,32.858432],"type":"Point"}
}