{
  "type": "Feature",
  "properties": {
    "iso:country":"US",
    "sg:address":"413 E Northwest Hwy",
    "sg:city":"Grapevine",
    "sg:classifiers":[
        {
            "category":"Food & Beverages",
            "subcategory":"Bakery",
            "type":"Retail Goods"
        },
        {
            "category":"Bakery",
            "type":"Food & Drink"
        }
    ],
    "sg:phone":"+1 817 481 7799",
    "sg:postcode":"76051",
    "sg:province":"TX",
    "sg:tags":[
        "bakers-wholesale"
    ],
    "wof:name":"Hometown Bakery",
    "wof:placetype":"venue"
},
  "geometry": {"coordinates":[-97.07475100000001,32.94104],"type":"Point"}
}