{
  "type": "Feature",
  "properties": {
    "iso:country":"US",
    "sg:address":"4725 Wellington St",
    "sg:city":"Greenville",
    "sg:classifiers":[
        {
            "category":"Health Services",
            "subcategory":"Doctor",
            "type":"Services"
        }
    ],
    "sg:phone":"+1 903 450 9120",
    "sg:postcode":"75401",
    "sg:province":"TX",
    "sg:tags":[
        "medical"
    ],
    "wof:name":"Maxine J Thomas",
    "wof:placetype":"venue"
},
  "geometry": {"coordinates":[-96.123784,33.124612],"type":"Point"}
}