{
  "type": "Feature",
  "properties": {
    "iso:country":"US",
    "sg:address":"12911 Lake Forest Dr",
    "sg:city":"Cypress",
    "sg:classifiers":[
        {
            "category":"Building & Trades",
            "subcategory":"Construction",
            "type":"Services"
        }
    ],
    "sg:phone":"+1 281 890 3004",
    "sg:postcode":"77429",
    "sg:province":"TX",
    "sg:tags":[
        "industrial",
        "coating"
    ],
    "wof:name":"Premier Coatings Inc",
    "wof:placetype":"venue"
},
  "geometry": {"coordinates":[-95.617465,29.955055],"type":"Point"}
}