{
  "type": "Feature",
  "properties": {
    "iso:country":"US",
    "sg:address":"14729 Old Hwy 105 W",
    "sg:city":"Montgomery",
    "sg:classifiers":[
        {
            "category":"Professional",
            "subcategory":"Lawyer & Legal Services",
            "type":"Services"
        }
    ],
    "sg:phone":"+1 936 447 2006",
    "sg:postcode":"77356",
    "sg:province":"TX",
    "sg:tags":[
        "attorney"
    ],
    "wof:name":"William J Hawkins",
    "wof:placetype":"venue"
},
  "geometry": {"coordinates":[-95.79275800000001,30.346444],"type":"Point"}
}