{
  "type": "Feature",
  "properties": {
    "iso:country":"US",
    "sg:address":"530 W Market St",
    "sg:city":"San Antonio",
    "sg:classifiers":[
        {
            "category":"Shopping",
            "subcategory":"Clothing, Apparel, & Fashions",
            "type":"Retail Goods"
        }
    ],
    "sg:phone":"+1 210 212 7277",
    "sg:postcode":"78205",
    "sg:province":"TX",
    "wof:name":"Joannas",
    "wof:placetype":"venue"
},
  "geometry": {"coordinates":[-98.491128,29.42369],"type":"Point"}
}