{
  "type": "Feature",
  "properties": {
    "iso:country":"US",
    "sg:address":"2208 Heather Hill Ln",
    "sg:city":"Plano",
    "sg:classifiers":[
        {
            "category":"Food & Beverages",
            "subcategory":"Specialty",
            "type":"Retail Goods"
        }
    ],
    "sg:phone":"+1 972 964 9529",
    "sg:postcode":"75075",
    "sg:province":"TX",
    "wof:name":"Elite Nutrition Online",
    "wof:placetype":"venue"
},
  "geometry": {"coordinates":[-96.739197,33.034911],"type":"Point"}
}