{
  "type": "Feature",
  "properties": {
    "iso:country":"US",
    "sg:address":"4931 Falvey St",
    "sg:city":"Houston",
    "sg:classifiers":[
        {
            "category":"Education",
            "subcategory":"Special Training",
            "type":"Public Place"
        }
    ],
    "sg:phone":"+1 713 649 2761",
    "sg:postcode":"77017",
    "sg:province":"TX",
    "wof:name":"Als K9 School",
    "wof:placetype":"venue"
},
  "geometry": {"coordinates":[-95.239093,29.696259],"type":"Point"}
}