{
  "type": "Feature",
  "properties": {
    "iso:country":"US",
    "sg:address":"1910 Tulane Ave",
    "sg:city":"Gainesville",
    "sg:classifiers":[
        {
            "category":"Farming",
            "subcategory":"Livestock Farm",
            "type":"Manufacturing & Wholesale Goods"
        }
    ],
    "sg:phone":"+1 940 665 6145",
    "sg:postcode":"76240",
    "sg:province":"TX",
    "sg:tags":[
        "beef",
        "feedlot",
        "cattle"
    ],
    "wof:name":"Robert Voth",
    "wof:placetype":"venue"
},
  "geometry": {"coordinates":[-97.167896,33.615548],"type":"Point"}
}