{
  "type": "Feature",
  "properties": {
    "iso:country":"US",
    "sg:address":"4235 Roaring Rapids Dr",
    "sg:city":"Houston",
    "sg:classifiers":[
        {
            "category":"Organizations",
            "subcategory":"Professional Association",
            "type":"Services"
        }
    ],
    "sg:phone":"+1 281 286 7131",
    "sg:postcode":"77059",
    "sg:province":"TX",
    "wof:name":"Pasadena Area Music Teach",
    "wof:placetype":"venue"
},
  "geometry": {"coordinates":[-95.09606700000001,29.598049],"type":"Point"}
}