{
  "type": "Feature",
  "properties": {
    "iso:country":"US",
    "sg:address":"6101 Glenmont Dr",
    "sg:city":"Houston",
    "sg:classifiers":[
        {
            "category":"Banks & Credit Unions",
            "subcategory":"Bank",
            "type":"Services"
        }
    ],
    "sg:phone":"+1 713 270 4777",
    "sg:postcode":"77081",
    "sg:province":"TX",
    "sg:tags":[
        "cashing",
        "check"
    ],
    "wof:name":"A 1 Check Cashing II",
    "wof:placetype":"venue"
},
  "geometry": {"coordinates":[-95.48963000000001,29.72],"type":"Point"}
}