{
  "type": "Feature",
  "properties": {
    "iso:country":"US",
    "sg:address":"102 SW Railroad St",
    "sg:city":"Seadrift",
    "sg:classifiers":[
        {
            "category":"Autos & Motor Vehicles",
            "subcategory":"Motorcycle Sales",
            "type":"Retail Goods"
        }
    ],
    "sg:phone":"+1 361 785 5150",
    "sg:postcode":"77954",
    "sg:province":"TX",
    "sg:tags":[
        "scooter"
    ],
    "wof:name":"Seadrift Custom Choppers",
    "wof:placetype":"venue"
},
  "geometry": {"coordinates":[-97.293165,29.089893],"type":"Point"}
}