{
  "type": "Feature",
  "properties": {
    "iso:country":"US",
    "sg:address":"1049 Stadium Rd",
    "sg:city":"Port Arthur",
    "sg:classifiers":[
        {
            "category":"Shopping",
            "subcategory":"Discount & Variety Stores",
            "type":"Retail Goods"
        }
    ],
    "sg:phone":"+1 409 982 6380",
    "sg:postcode":"77642",
    "sg:province":"TX",
    "wof:name":"Dolex Dollar Express Inc",
    "wof:placetype":"venue"
},
  "geometry": {"coordinates":[-93.903513,29.914478],"type":"Point"}
}