{
  "type": "Feature",
  "properties": {
    "iso:country":"US",
    "sg:address":"1314 Allen Genoa Rd",
    "sg:city":"Houston",
    "sg:classifiers":[
        {
            "category":"Food & Beverages",
            "subcategory":"Groceries & Convenience Stores",
            "type":"Retail Goods"
        }
    ],
    "sg:phone":"+1 713 649 1571",
    "sg:postcode":"77017",
    "sg:province":"TX",
    "wof:name":"Jack's Super Drive-In-Grocery",
    "wof:placetype":"venue"
},
  "geometry": {"coordinates":[-95.2341,29.689501],"type":"Point"}
}