{
  "type": "Feature",
  "properties": {
    "iso:country":"US",
    "sg:address":"1531 Co Rd 1248",
    "sg:city":"Muleshoe",
    "sg:classifiers":[
        {
            "category":"Recreation",
            "type":"Entertainment"
        }
    ],
    "sg:phone":"+1 806 946 3317",
    "sg:postcode":"79347",
    "sg:province":"TX",
    "sg:tags":[
        "parks"
    ],
    "wof:name":"Muleshoe National Wildlife Rfg",
    "wof:placetype":"venue"
},
  "geometry": {"coordinates":[-102.778893,33.957333],"type":"Point"}
}