{
  "type": "Feature",
  "properties": {
    "iso:country":"US",
    "sg:address":"1601 State Hwy 100",
    "sg:city":"Port Isabel",
    "sg:classifiers":[
        {
            "category":"Banks & Credit Unions",
            "subcategory":"Bank",
            "type":"Services"
        }
    ],
    "sg:phone":"+1 956 943 2108",
    "sg:postcode":"78578",
    "sg:province":"TX",
    "wof:name":"International Bank Of Commerce",
    "wof:placetype":"venue"
},
  "geometry": {"coordinates":[-97.223353,26.071729],"type":"Point"}
}