{
  "type": "Feature",
  "properties": {
    "iso:country":"US",
    "sg:address":"103 S General Bruce Dr",
    "sg:city":"Temple",
    "sg:classifiers":[
        {
            "category":"Retail",
            "subcategory":"Repair Shop",
            "type":"Services"
        },
        {
            "category":"Wholesale",
            "subcategory":"Machinery & Supplies",
            "type":"Manufacturing & Wholesale Goods"
        },
        {
            "category":"Building & Trades",
            "subcategory":"Construction",
            "type":"Services"
        }
    ],
    "sg:phone":"+1 254 771 1394",
    "sg:postcode":"76504",
    "sg:province":"TX",
    "sg:tags":[
        "heating",
        "major",
        "refinishing",
        "appliance",
        "system",
        "specialty",
        "part",
        "small",
        "contractor",
        "air conditioning"
    ],
    "sg:website":"http://winklersserviceandpartsin.liveonatt.com",
    "wof:name":"Winkler's Service & Parts Inc.",
    "wof:placetype":"venue"
},
  "geometry": {"coordinates":[-97.359898,31.100668],"type":"Point"}
}