{
  "type": "Feature",
  "properties": {
    "iso:country":"US",
    "sg:address":"10908 Estacado Dr",
    "sg:city":"Dallas",
    "sg:classifiers":[
        {
            "category":"Building & Trades",
            "subcategory":"Landscaping Services",
            "type":"Services"
        }
    ],
    "sg:phone":"+1 214 324 0387",
    "sg:postcode":"75228",
    "sg:province":"TX",
    "sg:tags":[
        "landscape",
        "contractor"
    ],
    "wof:name":"Tovar Lawn Grooming Svc",
    "wof:placetype":"venue"
},
  "geometry": {"coordinates":[-96.67596500000001,32.848373],"type":"Point"}
}