{
  "type": "Feature",
  "properties": {
    "iso:country":"US",
    "sg:address":"11070 Kinney Rd",
    "sg:city":"Atascosa",
    "sg:classifiers":[
        {
            "category":"Social Services",
            "subcategory":"Child Care",
            "type":"Services"
        }
    ],
    "sg:phone":"+1 210 622 3585",
    "sg:postcode":"78002",
    "sg:province":"TX",
    "sg:tags":[
        "day"
    ],
    "wof:name":"Cils Day Care",
    "wof:placetype":"venue"
},
  "geometry": {"coordinates":[-98.68042800000001,29.313039],"type":"Point"}
}