{
  "type": "Feature",
  "properties": {
    "iso:country":"US",
    "sg:address":"2518 Thompson St",
    "sg:city":"Victoria",
    "sg:classifiers":[
        {
            "category":"Retail",
            "subcategory":"Laundry & Dry Cleaning",
            "type":"Services"
        }
    ],
    "sg:phone":"+1 361 579 0018",
    "sg:postcode":"77901",
    "sg:province":"TX",
    "wof:name":"Job Master",
    "wof:placetype":"venue"
},
  "geometry": {"coordinates":[-96.97805,28.773667],"type":"Point"}
}