{
  "type": "Feature",
  "properties": {
    "iso:country":"US",
    "sg:address":"14121 Gulf Fwy",
    "sg:city":"Houston",
    "sg:classifiers":[
        {
            "category":"Recreation",
            "subcategory":"Arcade",
            "type":"Entertainment"
        }
    ],
    "sg:phone":"+1 281 484 2523",
    "sg:postcode":"77034",
    "sg:province":"TX",
    "sg:tags":[
        "device",
        "operator",
        "amusement"
    ],
    "wof:name":"Gulf CST Telecm MSC Hold Syst",
    "wof:placetype":"venue"
},
  "geometry": {"coordinates":[-95.199938,29.60181],"type":"Point"}
}