{
  "type": "Feature",
  "properties": {
    "iso:country":"US",
    "sg:address":"1403 W Pine Ave",
    "sg:city":"Midland",
    "sg:classifiers":[
        {
            "category":"Real Estate",
            "subcategory":"Real Estate Operator",
            "type":"Services"
        }
    ],
    "sg:phone":"+1 432 684 4311",
    "sg:postcode":"79705",
    "sg:province":"TX",
    "sg:tags":[
        "building",
        "nonresidential"
    ],
    "wof:name":"Triangle S Properties",
    "wof:placetype":"venue"
},
  "geometry": {"coordinates":[-102.09715199999999,32.02079],"type":"Point"}
}