{
  "type": "Feature",
  "properties": {
    "iso:country":"US",
    "sg:address":"5421 Flynn Pkwy",
    "sg:city":"Corpus Christi",
    "sg:classifiers":[
        {
            "category":"Professional",
            "subcategory":"Business Services",
            "type":"Services"
        }
    ],
    "sg:phone":"+1 361 852 4603",
    "sg:postcode":"78411",
    "sg:province":"TX",
    "wof:name":"Cynthia Maiden",
    "wof:placetype":"venue"
},
  "geometry": {"coordinates":[-97.393728,27.713368],"type":"Point"}
}