{
  "type": "Feature",
  "properties": {
    "iso:country":"US",
    "sg:address":"18614 Walden Forest Dr",
    "sg:city":"Humble",
    "sg:classifiers":[
        {
            "category":"Restaurant",
            "type":"Food & Drink"
        }
    ],
    "sg:phone":"+1 832 445 0183",
    "sg:postcode":"77346",
    "sg:province":"TX",
    "sg:tags":[
        "mexican"
    ],
    "wof:name":"Taconis Taco",
    "wof:placetype":"venue"
},
  "geometry": {"coordinates":[-95.15560000000001,29.995341],"type":"Point"}
}