{
  "type": "Feature",
  "properties": {
    "iso:country":"US",
    "sg:address":"8320 Bee Caves Rd",
    "sg:city":"Austin",
    "sg:classifiers":[
        {
            "category":"Real Estate",
            "subcategory":"Real Estate Agent",
            "type":"Services"
        }
    ],
    "sg:phone":"+1 512 328 6686",
    "sg:postcode":"78746",
    "sg:province":"TX",
    "sg:tags":[
        "broker"
    ],
    "sg:website":"www.capitolarearealty.com",
    "wof:name":"Capital Area Realty",
    "wof:placetype":"venue"
},
  "geometry": {"coordinates":[-97.85273100000001,30.313343],"type":"Point"}
}