{
  "type": "Feature",
  "properties": {
    "iso:country":"US",
    "sg:address":"6601 Snider Plz",
    "sg:city":"Dallas",
    "sg:classifiers":[
        {
            "category":"Deli",
            "type":"Food & Drink"
        },
        {
            "category":"Restaurant",
            "type":"Food & Drink"
        },
        {
            "category":"Food & Beverages",
            "subcategory":"Meat & Fish",
            "type":"Retail Goods"
        }
    ],
    "sg:phone":"+1 214 363 2231",
    "sg:postcode":"75205",
    "sg:province":"TX",
    "sg:tags":[
        "german",
        "shop"
    ],
    "sg:website":"www.kubys.com/",
    "wof:name":"Kuby's Sausage House",
    "wof:placetype":"venue"
},
  "geometry": {"coordinates":[-96.788101,32.846699],"type":"Point"}
}