{
  "type": "Feature",
  "properties": {
    "iso:country":"US",
    "sg:address":"5060 Addison Cir",
    "sg:city":"Addison",
    "sg:classifiers":[
        {
            "category":"Communications",
            "subcategory":"Film & Video Production",
            "type":"Services"
        }
    ],
    "sg:phone":"+1 972 869 7607",
    "sg:postcode":"75001",
    "sg:province":"TX",
    "sg:tags":[
        "motion",
        "picture",
        "studio",
        "producer"
    ],
    "sg:website":"www.filmxero.com",
    "wof:name":"Film Xero",
    "wof:placetype":"venue"
},
  "geometry": {"coordinates":[-96.823432,32.962123],"type":"Point"}
}