{
  "type": "Feature",
  "properties": {
    "iso:country":"US",
    "sg:address":"3804 Holiday Dr",
    "sg:city":"Amarillo",
    "sg:classifiers":[
        {
            "category":"Retail",
            "subcategory":"Portrait Studio",
            "type":"Services"
        }
    ],
    "sg:phone":"+1 806 356 7973",
    "sg:postcode":"79109",
    "sg:province":"TX",
    "sg:tags":[
        "photographer"
    ],
    "wof:name":"Steven Line Photography",
    "wof:placetype":"venue"
},
  "geometry": {"coordinates":[-101.900925,35.168161],"type":"Point"}
}