{
  "type": "Feature",
  "properties": {
    "iso:country":"US",
    "sg:address":"4210 Huckleberry Dr",
    "sg:city":"Fort Worth",
    "sg:classifiers":[
        {
            "category":"Government",
            "subcategory":"Office",
            "type":"Public Place"
        }
    ],
    "sg:phone":"+1 817 732 5736",
    "sg:postcode":"76137",
    "sg:province":"TX",
    "sg:tags":[
        "national",
        "security"
    ],
    "wof:name":"United States Marine Corps",
    "wof:placetype":"venue"
},
  "geometry": {"coordinates":[-97.29615200000001,32.880652],"type":"Point"}
}