{
  "type": "Feature",
  "properties": {
    "iso:country":"US",
    "sg:address":"17727 Addison Rd",
    "sg:city":"Dallas",
    "sg:classifiers":[
        {
            "category":"Bars & Pubs",
            "type":"Food & Drink"
        },
        {
            "category":"Restaurant",
            "type":"Food & Drink"
        }
    ],
    "sg:phone":"+1 972 381 9796",
    "sg:postcode":"75287",
    "sg:province":"TX",
    "wof:name":"Cape Buffalo Grille",
    "wof:placetype":"venue"
},
  "geometry": {"coordinates":[-96.830704,32.9893],"type":"Point"}
}