{
  "type": "Feature",
  "properties": {
    "iso:country":"US",
    "sg:address":"1959 State Hwy 78",
    "sg:city":"Wylie",
    "sg:classifiers":[
        {
            "category":"Wholesale",
            "subcategory":"Hardware",
            "type":"Manufacturing & Wholesale Goods"
        }
    ],
    "sg:phone":"+1 972 429 4006",
    "sg:postcode":"75098",
    "sg:province":"TX",
    "sg:tags":[
        "tool"
    ],
    "wof:name":"Centurion Tools",
    "wof:placetype":"venue"
},
  "geometry": {"coordinates":[-96.514916,33.022824],"type":"Point"}
}