{
  "type": "Feature",
  "properties": {
    "iso:country":"US",
    "sg:address":"140 Kirkham Cir",
    "sg:city":"Kyle",
    "sg:classifiers":[
        {
            "category":"Insurance",
            "subcategory":"Hazard Insurance",
            "type":"Services"
        }
    ],
    "sg:phone":"+1 512 449 6040",
    "sg:postcode":"78640",
    "sg:province":"TX",
    "sg:website":"http://www.agentwayne.com",
    "wof:name":"Weigelt, Wayne - State Farm Insurance Agent",
    "wof:placetype":"venue"
},
  "geometry": {"coordinates":[-97.890221,30.01305],"type":"Point"}
}