{
  "type": "Feature",
  "properties": {
    "iso:country":"US",
    "sg:address":"873 Eva St",
    "sg:city":"Montgomery",
    "sg:classifiers":[
        {
            "category":"Restaurant",
            "type":"Food & Drink"
        }
    ],
    "sg:menulink":"http://www.allmenus.com/tx/montgomery/57460-pizza-shack/menu/",
    "sg:phone":"+1 936 597 9488",
    "sg:postcode":"77356",
    "sg:province":"TX",
    "sg:tags":[
        "american",
        "pizza"
    ],
    "wof:name":"Pizza Shack",
    "wof:placetype":"venue"
},
  "geometry": {"coordinates":[-95.704641,30.388227],"type":"Point"}
}