{
  "type": "Feature",
  "properties": {
    "iso:country":"US",
    "sg:address":"206 Santa Fe Dr",
    "sg:city":"Weatherford",
    "sg:classifiers":[
        {
            "category":"Banks & Credit Unions",
            "subcategory":"Bank",
            "type":"Services"
        }
    ],
    "sg:phone":"+1 817 599 0777",
    "sg:postcode":"76086",
    "sg:province":"TX",
    "sg:tags":[
        "institution",
        "business"
    ],
    "wof:name":"Delta Loans",
    "wof:placetype":"venue"
},
  "geometry": {"coordinates":[-97.79202600000001,32.757266],"type":"Point"}
}