{
  "type": "Feature",
  "properties": {
    "iso:country":"US",
    "sg:address":"2929 Westheimer Rd",
    "sg:city":"Houston",
    "sg:classifiers":[
        {
            "category":"Real Estate",
            "subcategory":"Real Estate Operator",
            "type":"Services"
        }
    ],
    "sg:phone":"+1 713 522 1122",
    "sg:postcode":"77098",
    "sg:province":"TX",
    "sg:tags":[
        "apartment"
    ],
    "sg:website":"www.thebellemeade.com/index.php",
    "wof:name":"The Belle Meade at River Oaks",
    "wof:placetype":"venue"
},
  "geometry": {"coordinates":[-95.422589,29.742128],"type":"Point"}
}