{
  "type": "Feature",
  "properties": {
    "iso:country":"US",
    "sg:address":"612 Sherwood Dr",
    "sg:city":"Richardson",
    "sg:classifiers":[
        {
            "category":"Building & Trades",
            "subcategory":"Cleaning & Sanitation",
            "type":"Services"
        }
    ],
    "sg:phone":"+1 972 907 9610",
    "sg:postcode":"75080",
    "sg:province":"TX",
    "sg:tags":[
        "maintenance"
    ],
    "wof:name":"M&M Maintenance",
    "wof:placetype":"venue"
},
  "geometry": {"coordinates":[-96.743441,32.949083],"type":"Point"}
}