{
  "type": "Feature",
  "properties": {
    "iso:country":"US",
    "sg:address":"1115 Chihuahua St",
    "sg:city":"Laredo",
    "sg:classifiers":[
        {
            "category":"Social Services",
            "type":"Services"
        }
    ],
    "sg:phone":"+1 956 726 4949",
    "sg:postcode":"78040",
    "sg:province":"TX",
    "wof:name":"Case Laredo Management Service",
    "wof:placetype":"venue"
},
  "geometry": {"coordinates":[-99.484617,27.505584],"type":"Point"}
}