{
  "type": "Feature",
  "properties": {
    "iso:country":"US",
    "sg:address":"3196 Executive Dr",
    "sg:city":"San Angelo",
    "sg:classifiers":[
        {
            "category":"Health Services",
            "subcategory":"Doctor",
            "type":"Services"
        }
    ],
    "sg:phone":"+1 325 944 4677",
    "sg:postcode":"76904",
    "sg:province":"TX",
    "sg:tags":[
        "medical"
    ],
    "wof:name":"Carolyn B Reed PHD",
    "wof:placetype":"venue"
},
  "geometry": {"coordinates":[-100.46468299999999,31.422474],"type":"Point"}
}