{
  "type": "Feature",
  "properties": {
    "iso:country":"US",
    "sg:address":"1614 Ave K",
    "sg:city":"Lubbock",
    "sg:classifiers":[
        {
            "category":"Organizations",
            "subcategory":"Non-profit Organization",
            "type":"Services"
        }
    ],
    "sg:phone":"+1 806 763 7633",
    "sg:postcode":"79401",
    "sg:province":"TX",
    "sg:tags":[
        "information",
        "alcoholism",
        "treatment"
    ],
    "wof:name":"Managed Care Ctr",
    "wof:placetype":"venue"
},
  "geometry": {"coordinates":[-101.847998,33.579978],"type":"Point"}
}