{
  "type": "Feature",
  "properties": {
    "iso:country":"US",
    "sg:address":"4026 Woodhaven St",
    "sg:city":"Houston",
    "sg:classifiers":[
        {
            "category":"Building & Trades",
            "subcategory":"Landscaping Services",
            "type":"Services"
        }
    ],
    "sg:phone":"+1 713 667 4476",
    "sg:postcode":"77025",
    "sg:province":"TX",
    "sg:tags":[
        "landscape",
        "contractor"
    ],
    "wof:name":"Nancy Baldwin",
    "wof:placetype":"venue"
},
  "geometry": {"coordinates":[-95.443658,29.6657],"type":"Point"}
}