{
  "type": "Feature",
  "properties": {
    "iso:country":"US",
    "sg:address":"27711 Katy Fwy",
    "sg:city":"Katy",
    "sg:classifiers":[
        {
            "category":"Building & Trades",
            "subcategory":"Construction",
            "type":"Services"
        }
    ],
    "sg:phone":"+1 281 371 8180",
    "sg:postcode":"77494",
    "sg:province":"TX",
    "sg:tags":[
        "designer",
        "dealer",
        "pool",
        "swimming"
    ],
    "wof:name":"Best Pools For Less",
    "wof:placetype":"venue"
},
  "geometry": {"coordinates":[-95.842584,29.77686],"type":"Point"}
}