{
  "type": "Feature",
  "properties": {
    "iso:country":"US",
    "sg:address":"2110 Ave F",
    "sg:city":"Del Rio",
    "sg:classifiers":[
        {
            "category":"Restaurant",
            "type":"Food & Drink"
        }
    ],
    "sg:phone":"+1 830 774 4536",
    "sg:postcode":"78840",
    "sg:province":"TX",
    "sg:tags":[
        "eating"
    ],
    "wof:name":"Subway",
    "wof:placetype":"venue"
},
  "geometry": {"coordinates":[-100.905365,29.388058],"type":"Point"}
}