{
  "type": "Feature",
  "properties": {
    "iso:country":"US",
    "sg:address":"3415 Greystone Dr #301",
    "sg:city":"Austin",
    "sg:classifiers":[
        {
            "category":"Banks & Credit Unions",
            "subcategory":"Financial Services",
            "type":"Services"
        }
    ],
    "sg:phone":"+1 512 795 1800",
    "sg:postcode":"78731",
    "sg:province":"TX",
    "sg:tags":[
        "broker",
        "mortgage"
    ],
    "sg:website":"www.ihsloans.com",
    "wof:name":"IHS Mortgage",
    "wof:placetype":"venue"
},
  "geometry": {"coordinates":[-97.747979,30.356995],"type":"Point"}
}