{
  "type": "Feature",
  "properties": {
    "iso:country":"US",
    "sg:address":"2507 25th St",
    "sg:city":"Snyder",
    "sg:classifiers":[
        {
            "category":"Mining & Drilling",
            "type":"Manufacturing & Wholesale Goods"
        }
    ],
    "sg:phone":"+1 325 573 9325",
    "sg:postcode":"79549",
    "sg:province":"TX",
    "sg:tags":[
        "field",
        "oil"
    ],
    "wof:name":"ESP",
    "wof:placetype":"venue"
},
  "geometry": {"coordinates":[-100.927083,32.717369],"type":"Point"}
}