{
  "type": "Feature",
  "properties": {
    "iso:country":"US",
    "sg:address":"8503 Socrates Ln",
    "sg:city":"Universal City",
    "sg:classifiers":[
        {
            "category":"Banks & Credit Unions",
            "subcategory":"Financial Services",
            "type":"Services"
        }
    ],
    "sg:phone":"+1 210 659 7202",
    "sg:postcode":"78148",
    "sg:province":"TX",
    "sg:tags":[
        "investor"
    ],
    "wof:name":"Le Hotchkiss Invest Ltd",
    "wof:placetype":"venue"
},
  "geometry": {"coordinates":[-98.31400600000001,29.569729],"type":"Point"}
}