{
  "type": "Feature",
  "properties": {
    "iso:country":"US",
    "sg:address":"12401 Hewitt Ln",
    "sg:city":"Austin",
    "sg:classifiers":[
        {
            "category":"Building & Trades",
            "subcategory":"Construction",
            "type":"Services"
        }
    ],
    "sg:phone":"+1 512 292 1601",
    "sg:postcode":"78748",
    "sg:province":"TX",
    "sg:tags":[
        "clearing",
        "land",
        "leveling"
    ],
    "wof:name":"Guajardo Landscaping Inc",
    "wof:placetype":"venue"
},
  "geometry": {"coordinates":[-97.846992,30.148491],"type":"Point"}
}