{
  "type": "Feature",
  "properties": {
    "iso:country":"US",
    "sg:address":"4110 Woodland Ct",
    "sg:city":"Grapevine",
    "sg:classifiers":[
        {
            "category":"Wholesale",
            "subcategory":"Electrical",
            "type":"Manufacturing & Wholesale Goods"
        }
    ],
    "sg:phone":"+1 817 267 8825",
    "sg:postcode":"76051",
    "sg:province":"TX",
    "sg:tags":[
        "parts"
    ],
    "wof:name":"Cynthia J Moulder",
    "wof:placetype":"venue"
},
  "geometry": {"coordinates":[-97.12365699999999,32.892353],"type":"Point"}
}