{
  "type": "Feature",
  "properties": {
    "iso:country":"US",
    "sg:address":"8550 Hansen Rd",
    "sg:city":"Houston",
    "sg:classifiers":[
        {
            "category":"Manufacturing",
            "subcategory":"Metals",
            "type":"Manufacturing & Wholesale Goods"
        }
    ],
    "sg:phone":"+1 713 943 0688",
    "sg:postcode":"77075",
    "sg:province":"TX",
    "sg:tags":[
        "control",
        "industrial",
        "valve",
        "mfg"
    ],
    "wof:name":"Watts Acv Finished Goods Whse",
    "wof:placetype":"venue"
},
  "geometry": {"coordinates":[-95.258205,29.643833],"type":"Point"}
}