{
  "type": "Feature",
  "properties": {
    "iso:country":"US",
    "sg:address":"3803 Brazos Ave",
    "sg:city":"Odessa",
    "sg:classifiers":[
        {
            "category":"Wholesale",
            "subcategory":"Machinery & Supplies",
            "type":"Manufacturing & Wholesale Goods"
        }
    ],
    "sg:phone":"+1 432 362 7778",
    "sg:postcode":"79764",
    "sg:province":"TX",
    "sg:tags":[
        "field",
        "oil",
        "equipment"
    ],
    "wof:name":"Four J's Sales & Svc",
    "wof:placetype":"venue"
},
  "geometry": {"coordinates":[-102.402505,31.87641],"type":"Point"}
}