{
  "type": "Feature",
  "properties": {
    "iso:country":"US",
    "sg:address":"1570 W Crosby St",
    "sg:city":"Slaton",
    "sg:phone":"+1 806 828 3286",
    "sg:postcode":"79364",
    "sg:province":"TX",
    "sg:tags":[
        "farm",
        "cotton"
    ],
    "wof:name":"David Anton Bednarz",
    "wof:placetype":"venue"
},
  "geometry": {"coordinates":[-101.66378899999999,33.437649],"type":"Point"}
}