{
  "type": "Feature",
  "properties": {
    "iso:country":"US",
    "sg:address":"2918 Pecanwood Dr",
    "sg:city":"Missouri City",
    "sg:classifiers":[
        {
            "category":"Manufacturing",
            "subcategory":"Printing",
            "type":"Manufacturing & Wholesale Goods"
        }
    ],
    "sg:phone":"+1 281 499 6794",
    "sg:postcode":"77459",
    "sg:province":"TX",
    "sg:tags":[
        "newspaper"
    ],
    "wof:name":"Nationalautoemployment Co",
    "wof:placetype":"venue"
},
  "geometry": {"coordinates":[-95.575523,29.579859],"type":"Point"}
}