{
  "type": "Feature",
  "properties": {
    "iso:country":"US",
    "sg:address":"5909 Westmont Dr",
    "sg:city":"Plano",
    "sg:classifiers":[
        {
            "category":"Manufacturing",
            "subcategory":"Chemicals & Compounds",
            "type":"Manufacturing & Wholesale Goods"
        }
    ],
    "sg:phone":"+1 972 403 1429",
    "sg:postcode":"75093",
    "sg:province":"TX",
    "sg:tags":[
        "preparation",
        "mfg"
    ],
    "wof:name":"Bio Tech Research & Dev",
    "wof:placetype":"venue"
},
  "geometry": {"coordinates":[-96.837925,33.053975],"type":"Point"}
}