{
  "type": "Feature",
  "properties": {
    "iso:country":"US",
    "sg:address":"4017 Ross Ave",
    "sg:city":"Dallas",
    "sg:classifiers":[
        {
            "category":"Retail",
            "subcategory":"Auto Repair",
            "type":"Services"
        }
    ],
    "sg:phone":"+1 214 827 7748",
    "sg:postcode":"75204",
    "sg:province":"TX",
    "sg:tags":[
        "repairing",
        "automobile"
    ],
    "wof:name":"Automotive Enterprise",
    "wof:placetype":"venue"
},
  "geometry": {"coordinates":[-96.784452,32.799346],"type":"Point"}
}