{
  "type": "Feature",
  "properties": {
    "iso:country":"US",
    "sg:address":"225 US Hwy 69 N",
    "sg:city":"Woodville",
    "sg:classifiers":[
        {
            "category":"Autos & Motor Vehicles",
            "subcategory":"Recreational Vehicle Sales",
            "type":"Retail Goods"
        }
    ],
    "sg:phone":"+1 409 283 3888",
    "sg:postcode":"75979",
    "sg:province":"TX",
    "wof:name":"R V & Trailer Sales",
    "wof:placetype":"venue"
},
  "geometry": {"coordinates":[-94.428985,30.817223],"type":"Point"}
}