{
  "type": "Feature",
  "properties": {
    "iso:country":"US",
    "sg:address":"502 Depot St",
    "sg:city":"El Campo",
    "sg:classifiers":[
        {
            "category":"Social Services",
            "type":"Services"
        }
    ],
    "sg:phone":"+1 979 543 8154",
    "sg:postcode":"77437",
    "sg:province":"TX",
    "wof:name":"Living Well Resource Center",
    "wof:placetype":"venue"
},
  "geometry": {"coordinates":[-96.27467900000001,29.199039],"type":"Point"}
}