{
  "type": "Feature",
  "properties": {
    "iso:country":"US",
    "sg:address":"2103 Gray St",
    "sg:city":"Houston",
    "sg:classifiers":[
        {
            "category":"Retail",
            "subcategory":"Auto Repair",
            "type":"Services"
        }
    ],
    "sg:phone":"+1 713 659 8289",
    "sg:postcode":"77003",
    "sg:province":"TX",
    "wof:name":"Quick Foreign Car Service",
    "wof:placetype":"venue"
},
  "geometry": {"coordinates":[-95.36196099999999,29.743038],"type":"Point"}
}