{
  "type": "Feature",
  "properties": {
    "iso:country":"US",
    "sg:address":"438 Vine St",
    "sg:city":"San Antonio",
    "sg:classifiers":[
        {
            "category":"Manufacturing",
            "subcategory":"Aerospace",
            "type":"Manufacturing & Wholesale Goods"
        }
    ],
    "sg:phone":"+1 210 534 9492",
    "sg:postcode":"78210",
    "sg:province":"TX",
    "sg:tags":[
        "aircraft",
        "component"
    ],
    "sg:website":"www.aaammminc.com",
    "wof:name":"AAA Machine Metal Stamping",
    "wof:placetype":"venue"
},
  "geometry": {"coordinates":[-98.45066300000001,29.407843],"type":"Point"}
}