{
  "type": "Feature",
  "properties": {
    "iso:country":"US",
    "sg:address":"11906 Plum Meadow Ln",
    "sg:city":"Houston",
    "sg:classifiers":[
        {
            "category":"Building & Trades",
            "subcategory":"Construction",
            "type":"Services"
        }
    ],
    "sg:phone":"+1 281 442 2956",
    "sg:postcode":"77039",
    "sg:province":"TX",
    "sg:tags":[
        "hanging",
        "contractor"
    ],
    "wof:name":"Viramontes Painting",
    "wof:placetype":"venue"
},
  "geometry": {"coordinates":[-95.333601,29.898199],"type":"Point"}
}