{
  "type": "Feature",
  "properties": {
    "iso:country":"US",
    "sg:address":"12515 Beauline Abbey St",
    "sg:city":"Tomball",
    "sg:classifiers":[
        {
            "category":"Professional",
            "type":"Services"
        }
    ],
    "sg:phone":"+1 281 370 7685",
    "sg:postcode":"77377",
    "sg:province":"TX",
    "wof:name":"J Pritts",
    "wof:placetype":"venue"
},
  "geometry": {"coordinates":[-95.616135,30.006944],"type":"Point"}
}