{
  "type": "Feature",
  "properties": {
    "iso:country":"US",
    "sg:address":"10109 Mc Kalla Pl",
    "sg:city":"Austin",
    "sg:classifiers":[
        {
            "category":"Shopping",
            "subcategory":"Computers & Home Electronics",
            "type":"Retail Goods"
        }
    ],
    "sg:phone":"+1 512 928 8926",
    "sg:postcode":"78758",
    "sg:province":"TX",
    "wof:name":"Computerware On Line",
    "wof:placetype":"venue"
},
  "geometry": {"coordinates":[-97.720005,30.383932],"type":"Point"}
}