{
  "type": "Feature",
  "properties": {
    "iso:country":"US",
    "sg:address":"1009 E 40th St",
    "sg:city":"Austin",
    "sg:classifiers":[
        {
            "category":"Health Services",
            "subcategory":"Doctor",
            "type":"Services"
        }
    ],
    "sg:phone":"+1 512 482 0248",
    "sg:postcode":"78751",
    "sg:province":"TX",
    "sg:tags":[
        "medical"
    ],
    "wof:name":"Guadalupe Zamora MD",
    "wof:placetype":"venue"
},
  "geometry": {"coordinates":[-97.71884799999999,30.296721],"type":"Point"}
}