{
  "type": "Feature",
  "properties": {
    "iso:country":"US",
    "sg:address":"116 S Main St",
    "sg:city":"Cleburne",
    "sg:classifiers":[
        {
            "category":"Shopping",
            "subcategory":"Books",
            "type":"Retail Goods"
        }
    ],
    "sg:phone":"+1 817 645 7591",
    "sg:postcode":"76033",
    "sg:province":"TX",
    "wof:name":"Bills",
    "wof:placetype":"venue"
},
  "geometry": {"coordinates":[-97.386476,32.346158],"type":"Point"}
}