{
  "type": "Feature",
  "properties": {
    "iso:country":"US",
    "sg:address":"7000 Mansfield Hwy",
    "sg:city":"Kennedale",
    "sg:classifiers":[
        {
            "category":"Retail",
            "subcategory":"Auto Repair",
            "type":"Services"
        }
    ],
    "sg:phone":"+1 817 478 3788",
    "sg:postcode":"76060",
    "sg:province":"TX",
    "sg:tags":[
        "repairing",
        "automobile"
    ],
    "wof:name":"Jazz Auto Repair",
    "wof:placetype":"venue"
},
  "geometry": {"coordinates":[-97.204239,32.630326],"type":"Point"}
}