{
  "type": "Feature",
  "properties": {
    "iso:country":"US",
    "sg:address":"2230 Industrial Blvd",
    "sg:city":"Abilene",
    "sg:classifiers":[
        {
            "category":"Professional",
            "type":"Services"
        }
    ],
    "sg:phone":"+1 325 698 1200",
    "sg:postcode":"79602",
    "sg:province":"TX",
    "sg:tags":[
        "establishment"
    ],
    "wof:name":"Greenfix Texas",
    "wof:placetype":"venue"
},
  "geometry": {"coordinates":[-99.74981,32.401449],"type":"Point"}
}