{
  "type": "Feature",
  "properties": {
    "iso:country":"US",
    "sg:address":"5401 N McColl Rd",
    "sg:city":"Mcallen",
    "sg:classifiers":[
        {
            "category":"Professional",
            "subcategory":"Accounting & Tax Preparation",
            "type":"Services"
        }
    ],
    "sg:phone":"+1 956 683 7000",
    "sg:postcode":"78504",
    "sg:province":"TX",
    "sg:tags":[
        "accountant"
    ],
    "wof:name":"Joseph Hicks CPA",
    "wof:placetype":"venue"
},
  "geometry": {"coordinates":[-98.204719,26.248888],"type":"Point"}
}