{
  "type": "Feature",
  "properties": {
    "iso:country":"US",
    "sg:address":"405 E Houston St",
    "sg:city":"Luling",
    "sg:classifiers":[
        {
            "category":"Autos & Motor Vehicles",
            "subcategory":"Automobile Sales",
            "type":"Retail Goods"
        }
    ],
    "sg:phone":"+1 830 875 5435",
    "sg:postcode":"78648",
    "sg:province":"TX",
    "sg:tags":[
        "car",
        "dealer"
    ],
    "wof:name":"Lundgren Chevrolet Buick GMC",
    "wof:placetype":"venue"
},
  "geometry": {"coordinates":[-97.652129,29.677062],"type":"Point"}
}