{
  "type": "Feature",
  "properties": {
    "iso:country":"US",
    "sg:address":"1225 E Pioneer Dr",
    "sg:city":"Irving",
    "sg:classifiers":[
        {
            "category":"Building & Trades",
            "subcategory":"Cleaning & Sanitation",
            "type":"Services"
        }
    ],
    "sg:phone":"+1 972 579 8020",
    "sg:postcode":"75061",
    "sg:province":"TX",
    "sg:tags":[
        "carpet"
    ],
    "wof:name":"Abby's Chem-Dry",
    "wof:placetype":"venue"
},
  "geometry": {"coordinates":[-96.93119799999999,32.817699],"type":"Point"}
}