{
  "type": "Feature",
  "properties": {
    "iso:country":"US",
    "sg:address":"301 W Main St",
    "sg:city":"Ore City",
    "sg:classifiers":[
        {
            "category":"Insurance",
            "subcategory":"Insurance Agent",
            "type":"Services"
        }
    ],
    "sg:phone":"+1 903 968 2223",
    "sg:postcode":"75683",
    "sg:province":"TX",
    "wof:name":"Jeannette Orms Insurance",
    "wof:placetype":"venue"
},
  "geometry": {"coordinates":[-94.72453,32.801024],"type":"Point"}
}