{
  "type": "Feature",
  "properties": {
    "iso:country":"US",
    "sg:address":"3325 Wurzbach Rd",
    "sg:city":"San Antonio",
    "sg:classifiers":[
        {
            "category":"Shopping",
            "subcategory":"Clothing, Apparel, & Fashions",
            "type":"Retail Goods"
        }
    ],
    "sg:phone":"+1 210 684 2889",
    "sg:postcode":"78238",
    "sg:province":"TX",
    "wof:name":"Rex Formal Wear",
    "wof:placetype":"venue"
},
  "geometry": {"coordinates":[-98.623976,29.468185],"type":"Point"}
}