{
  "type": "Feature",
  "properties": {
    "iso:country":"US",
    "sg:address":"200 S Getty St",
    "sg:city":"Uvalde",
    "sg:classifiers":[
        {
            "category":"Place Of Worship",
            "subcategory":"Church",
            "type":"Public Place"
        },
        {
            "category":"Place Of Worship",
            "type":"Public Place"
        }
    ],
    "sg:phone":"+1 830 278 5659",
    "sg:postcode":"78801",
    "sg:province":"TX",
    "sg:tags":[
        "testament",
        "christ-new",
        "churches-church",
        "christ"
    ],
    "wof:name":"Church of Christ",
    "wof:placetype":"venue"
},
  "geometry": {"coordinates":[-99.78585099999999,29.20887],"type":"Point"}
}