{
  "type": "Feature",
  "properties": {
    "iso:country":"US",
    "sg:address":"3833 Franklin Ave",
    "sg:city":"Waco",
    "sg:classifiers":[
        {
            "category":"Professional",
            "subcategory":"Management & Consulting",
            "type":"Services"
        }
    ],
    "sg:phone":"+1 254 755 7700",
    "sg:postcode":"76710",
    "sg:province":"TX",
    "wof:name":"Hvac Facilities Maint Cons",
    "wof:placetype":"venue"
},
  "geometry": {"coordinates":[-97.162717,31.527729],"type":"Point"}
}