{
  "type": "Feature",
  "properties": {
    "iso:country":"US",
    "sg:address":"1166 W Pioneer Pkwy",
    "sg:city":"Arlington",
    "sg:classifiers":[
        {
            "category":"Professional",
            "subcategory":"Management & Consulting",
            "type":"Services"
        }
    ],
    "sg:phone":"+1 817 459 3837",
    "sg:postcode":"76013",
    "sg:province":"TX",
    "sg:tags":[
        "consultant",
        "planning",
        "space",
        "facility"
    ],
    "wof:name":"4 Ever & Always",
    "wof:placetype":"venue"
},
  "geometry": {"coordinates":[-97.122569,32.708918],"type":"Point"}
}