{
  "type": "Feature",
  "properties": {
    "iso:country":"US",
    "sg:address":"14525 FM 529",
    "sg:city":"Houston",
    "sg:classifiers":[
        {
            "category":"Real Estate",
            "subcategory":"Developer",
            "type":"Services"
        }
    ],
    "sg:phone":"+1 713 690 1000",
    "sg:postcode":"77095",
    "sg:province":"TX",
    "wof:name":"Country Communites",
    "wof:placetype":"venue"
},
  "geometry": {"coordinates":[-95.63302299999999,29.879316],"type":"Point"}
}