{
  "type": "Feature",
  "properties": {
    "iso:country":"US",
    "sg:address":"398 Industrial Park Dr",
    "sg:city":"Victoria",
    "sg:classifiers":[
        {
            "category":"Wholesale",
            "subcategory":"Scrap",
            "type":"Manufacturing & Wholesale Goods"
        }
    ],
    "sg:phone":"+1 361 573 4661",
    "sg:postcode":"77905",
    "sg:province":"TX",
    "sg:tags":[
        "recycling",
        "center"
    ],
    "wof:name":"Commercial Metals Co",
    "wof:placetype":"venue"
},
  "geometry": {"coordinates":[-97.090844,28.766916],"type":"Point"}
}