{
  "type": "Feature",
  "properties": {
    "iso:country":"US",
    "sg:address":"7709 Rd H",
    "sg:city":"Corpus Christi",
    "sg:classifiers":[
        {
            "category":"Wholesale",
            "subcategory":"Construction Materials",
            "type":"Manufacturing & Wholesale Goods"
        },
        {
            "category":"Shopping",
            "type":"Retail Goods"
        }
    ],
    "sg:phone":"+1 361 991 8404",
    "sg:postcode":"78414",
    "sg:province":"TX",
    "sg:tags":[
        "marble",
        "merchandise"
    ],
    "wof:name":"Dominque Marble & Granite",
    "wof:placetype":"venue"
},
  "geometry": {"coordinates":[-97.37423800000001,27.649575],"type":"Point"}
}