{
  "type": "Feature",
  "properties": {
    "iso:country":"US",
    "sg:address":"17023 Barcelona Dr",
    "sg:city":"Friendswood",
    "sg:classifiers":[
        {
            "category":"Professional",
            "subcategory":"Business Services",
            "type":"Services"
        }
    ],
    "sg:phone":"+1 281 992 2025",
    "sg:postcode":"77546",
    "sg:province":"TX",
    "wof:name":"Colmer & Associates",
    "wof:placetype":"venue"
},
  "geometry": {"coordinates":[-95.174063,29.526956],"type":"Point"}
}