{
  "type": "Feature",
  "properties": {
    "iso:country":"US",
    "sg:address":"104 Brothers Blvd",
    "sg:city":"Red Oak",
    "sg:classifiers":[
        {
            "category":"Organizations",
            "subcategory":"Professional Association",
            "type":"Services"
        }
    ],
    "sg:phone":"+1 972 617 8410",
    "sg:postcode":"75154",
    "sg:province":"TX",
    "sg:tags":[
        "automobile",
        "business"
    ],
    "wof:name":"Fidelity Shipping",
    "wof:placetype":"venue"
},
  "geometry": {"coordinates":[-96.82167099999999,32.514724],"type":"Point"}
}