{
  "type": "Feature",
  "properties": {
    "iso:country":"US",
    "sg:address":"13907 Montfort Dr",
    "sg:city":"Dallas",
    "sg:classifiers":[
        {
            "category":"Shopping",
            "subcategory":"Clothing, Apparel, & Fashions",
            "type":"Retail Goods"
        }
    ],
    "sg:phone":"+1 214 729 0132",
    "sg:postcode":"75240",
    "sg:province":"TX",
    "sg:tags":[
        "baby",
        "accessory"
    ],
    "wof:name":"Simple Storks Of Dallas",
    "wof:placetype":"venue"
},
  "geometry": {"coordinates":[-96.814015,32.938245],"type":"Point"}
}