{
  "type": "Feature",
  "properties": {
    "iso:country":"US",
    "sg:address":"13690 Montana Ave",
    "sg:city":"El Paso",
    "sg:classifiers":[
        {
            "category":"Mining & Drilling",
            "type":"Manufacturing & Wholesale Goods"
        }
    ],
    "sg:phone":"+1 915 598 2482",
    "sg:postcode":"79938",
    "sg:province":"TX",
    "sg:tags":[
        "field"
    ],
    "wof:name":"Oasis Transportation",
    "wof:placetype":"venue"
},
  "geometry": {"coordinates":[-106.20578399999999,31.814692],"type":"Point"}
}