{
  "type": "Feature",
  "properties": {
    "iso:country":"US",
    "sg:address":"4544 Post Oak Place Dr Ste 330",
    "sg:city":"Houston",
    "sg:classifiers":[
        {
            "category":"Professional",
            "subcategory":"Accounting & Tax Preparation",
            "type":"Services"
        }
    ],
    "sg:phone":"+1 713 622 9825",
    "sg:postcode":"77027",
    "sg:province":"TX",
    "sg:tags":[
        "accountant"
    ],
    "wof:name":"Young Jess H & Co",
    "wof:placetype":"venue"
},
  "geometry": {"coordinates":[-95.450699,29.750299],"type":"Point"}
}