{
  "type": "Feature",
  "properties": {
    "iso:country":"US",
    "sg:address":"4146 State Hwy 21",
    "sg:city":"Paige",
    "sg:classifiers":[
        {
            "category":"Organizations",
            "subcategory":"Religious Organization",
            "type":"Services"
        }
    ],
    "sg:phone":"+1 512 253 6636",
    "sg:postcode":"78659",
    "sg:province":"TX",
    "wof:name":"Ebenezer Lutheran Church",
    "wof:placetype":"venue"
},
  "geometry": {"coordinates":[-97.030907,30.230518],"type":"Point"}
}