{
  "type": "Feature",
  "properties": {
    "iso:country":"US",
    "sg:address":"700 Johansen Rd",
    "sg:city":"Big Spring",
    "sg:classifiers":[
        {
            "category":"Building & Trades",
            "subcategory":"Landscaping Services",
            "type":"Services"
        }
    ],
    "sg:phone":"+1 432 267 5275",
    "sg:postcode":"79720",
    "sg:province":"TX",
    "sg:tags":[
        "supply"
    ],
    "wof:name":"Johansen Landscape & Nursery",
    "wof:placetype":"venue"
},
  "geometry": {"coordinates":[-101.473153,32.214889],"type":"Point"}
}