{
  "type": "Feature",
  "properties": {
    "iso:country":"US",
    "sg:address":"6943 Narcissus St",
    "sg:city":"Houston",
    "sg:classifiers":[
        {
            "category":"Personal",
            "type":"Services"
        }
    ],
    "sg:phone":"+1 713 643 7700",
    "sg:postcode":"77087",
    "sg:province":"TX",
    "sg:tags":[
        "therapist",
        "massage"
    ],
    "wof:name":"Benny Villarreal Massage",
    "wof:placetype":"venue"
},
  "geometry": {"coordinates":[-95.295311,29.707035],"type":"Point"}
}