{
  "type": "Feature",
  "properties": {
    "iso:country":"US",
    "sg:address":"5731 Threadgill Ave",
    "sg:city":"El Paso",
    "sg:classifiers":[
        {
            "category":"Wholesale",
            "subcategory":"Durable Goods & Equipment",
            "type":"Manufacturing & Wholesale Goods"
        }
    ],
    "sg:phone":"+1 915 759 7838",
    "sg:postcode":"79924",
    "sg:province":"TX",
    "sg:tags":[
        "enforcement",
        "law"
    ],
    "wof:name":"David Rains",
    "wof:placetype":"venue"
},
  "geometry": {"coordinates":[-106.41001799999999,31.884739],"type":"Point"}
}