{
  "type": "Feature",
  "properties": {
    "iso:country":"US",
    "sg:address":"14615 Benfer Rd Ste 200",
    "sg:city":"Houston",
    "sg:classifiers":[
        {
            "category":"Banks & Credit Unions",
            "subcategory":"Investment Brokerage",
            "type":"Services"
        },
        {
            "category":"Banks & Credit Unions",
            "subcategory":"Bank",
            "type":"Services"
        }
    ],
    "sg:phone":"+1 281 444 5600",
    "sg:postcode":"77069",
    "sg:province":"TX",
    "sg:tags":[
        "security",
        "bond",
        "broker",
        "stock"
    ],
    "sg:website":"http://www.churchtrust.com",
    "wof:name":"American Church Trust Company",
    "wof:placetype":"venue"
},
  "geometry": {"coordinates":[-95.51437300000001,29.991797],"type":"Point"}
}