{
  "type": "Feature",
  "properties": {
    "iso:country":"US",
    "sg:address":"705 Murrell Ave",
    "sg:city":"Ballinger",
    "sg:classifiers":[
        {
            "category":"Professional",
            "type":"Services"
        }
    ],
    "sg:phone":"+1 325 365 3817",
    "sg:postcode":"76821",
    "sg:province":"TX",
    "wof:name":"Artcetera Ltd",
    "wof:placetype":"venue"
},
  "geometry": {"coordinates":[-99.95054500000001,31.741569],"type":"Point"}
}