{
  "type": "Feature",
  "properties": {
    "iso:country":"US",
    "sg:address":"711 Main St",
    "sg:city":"Houston",
    "sg:classifiers":[
        {
            "category":"Professional",
            "subcategory":"Management & Consulting",
            "type":"Services"
        }
    ],
    "sg:phone":"+1 713 223 0316",
    "sg:postcode":"77002",
    "sg:province":"TX",
    "sg:tags":[
        "business"
    ],
    "wof:name":"Christopher David",
    "wof:placetype":"venue"
},
  "geometry": {"coordinates":[-95.36362699999999,29.75848],"type":"Point"}
}