{
  "type": "Feature",
  "properties": {
    "iso:country":"US",
    "sg:address":"1430 Macclesby Ln",
    "sg:city":"Channelview",
    "sg:classifiers":[
        {
            "category":"Manufacturing",
            "subcategory":"Printing",
            "type":"Manufacturing & Wholesale Goods"
        }
    ],
    "sg:phone":"+1 281 452 6774",
    "sg:postcode":"77530",
    "sg:province":"TX",
    "wof:name":"M & C Nameplating",
    "wof:placetype":"venue"
},
  "geometry": {"coordinates":[-95.14961,29.80269],"type":"Point"}
}