{
  "type": "Feature",
  "properties": {
    "iso:country":"US",
    "sg:address":"1100 Winchell Dr",
    "sg:city":"Waco",
    "sg:classifiers":[
        {
            "category":"Manufacturing",
            "subcategory":"Metals",
            "type":"Manufacturing & Wholesale Goods"
        }
    ],
    "sg:phone":"+1 254 776 8000",
    "sg:postcode":"76712",
    "sg:province":"TX",
    "sg:tags":[
        "fabricated",
        "structural"
    ],
    "sg:website":"www.ctiw.com",
    "wof:name":"Central Texas Iron Works",
    "wof:placetype":"venue"
},
  "geometry": {"coordinates":[-97.18234200000001,31.503357],"type":"Point"}
}