{
  "type": "Feature",
  "properties": {
    "iso:country":"US",
    "sg:address":"750 E Irving Blvd",
    "sg:city":"Irving",
    "sg:classifiers":[
        {
            "category":"Local Transit",
            "type":"Transportation"
        }
    ],
    "sg:phone":"+1 972 484 4848",
    "sg:postcode":"75060",
    "sg:province":"TX",
    "sg:tags":[
        "airport"
    ],
    "wof:name":"Golden Cab Svc",
    "wof:placetype":"venue"
},
  "geometry": {"coordinates":[-96.939469,32.813728],"type":"Point"}
}