{
  "type": "Feature",
  "properties": {
    "iso:country":"US",
    "sg:address":"5000 Montrose Blvd",
    "sg:city":"Houston",
    "sg:classifiers":[
        {
            "category":"Real Estate",
            "subcategory":"Real Estate Agent",
            "type":"Services"
        }
    ],
    "sg:phone":"+1 713 529 8992",
    "sg:postcode":"77006",
    "sg:province":"TX",
    "wof:name":"Carroll & Carroll Properties",
    "wof:placetype":"venue"
},
  "geometry": {"coordinates":[-95.391025,29.727752],"type":"Point"}
}