{
  "type": "Feature",
  "properties": {
    "iso:country":"US",
    "sg:address":"128 E 6th St",
    "sg:city":"Irving",
    "sg:classifiers":[
        {
            "category":"Health Services",
            "subcategory":"Chiropractor",
            "type":"Services"
        }
    ],
    "sg:phone":"+1 817 326 1256",
    "sg:postcode":"75060",
    "sg:province":"TX",
    "wof:name":"Classic Chiropractic",
    "wof:placetype":"venue"
},
  "geometry": {"coordinates":[-96.943684,32.808527],"type":"Point"}
}