{
  "type": "Feature",
  "properties": {
    "iso:country":"US",
    "sg:address":"2455 Commerce St",
    "sg:city":"Beaumont",
    "sg:classifiers":[
        {
            "category":"Organizations",
            "subcategory":"Religious Organization",
            "type":"Services"
        }
    ],
    "sg:phone":"+1 409 892 7063",
    "sg:postcode":"77703",
    "sg:province":"TX",
    "wof:name":"Ridgewood Church Of Christ",
    "wof:placetype":"venue"
},
  "geometry": {"coordinates":[-94.12476700000001,30.09735],"type":"Point"}
}