{
  "type": "Feature",
  "properties": {
    "iso:country":"US",
    "sg:address":"1034 Profit Dr",
    "sg:city":"Garland",
    "sg:classifiers":[
        {
            "category":"Manufacturing",
            "subcategory":"Furniture",
            "type":"Manufacturing & Wholesale Goods"
        }
    ],
    "sg:phone":"+1 972 272 4222",
    "sg:postcode":"75040",
    "sg:province":"TX",
    "sg:tags":[
        "mfg",
        "stereo",
        "wood",
        "cabinet"
    ],
    "wof:name":"Morale Woodcraft Inc",
    "wof:placetype":"venue"
},
  "geometry": {"coordinates":[-96.630174,32.919553],"type":"Point"}
}