{
  "type": "Feature",
  "properties": {
    "iso:country":"US",
    "sg:address":"1208 Laurie Ave",
    "sg:city":"De Soto",
    "sg:classifiers":[
        {
            "category":"Professional",
            "subcategory":"Secretarial Services",
            "type":"Services"
        }
    ],
    "sg:phone":"+1 972 224 8771",
    "sg:postcode":"75115",
    "sg:province":"TX",
    "sg:tags":[
        "reporting"
    ],
    "wof:name":"Expect Professinal Service",
    "wof:placetype":"venue"
},
  "geometry": {"coordinates":[-96.852608,32.611362],"type":"Point"}
}