{
  "type": "Feature",
  "properties": {
    "iso:country":"US",
    "sg:address":"1212 Montana Ave",
    "sg:city":"El Paso",
    "sg:classifiers":[
        {
            "category":"Professional",
            "subcategory":"Lawyer & Legal Services",
            "type":"Services"
        }
    ],
    "sg:phone":"+1 915 543 9342",
    "sg:postcode":"79902",
    "sg:province":"TX",
    "sg:tags":[
        "attorney"
    ],
    "wof:name":"Darren Ligon Attorney Law",
    "wof:placetype":"venue"
},
  "geometry": {"coordinates":[-106.48121500000001,31.770516],"type":"Point"}
}