{
  "type": "Feature",
  "properties": {
    "iso:country":"US",
    "sg:address":"12526 Blackstone Ct",
    "sg:city":"Houston",
    "sg:classifiers":[
        {
            "category":"Professional",
            "subcategory":"Business Services",
            "type":"Services"
        }
    ],
    "sg:phone":"+1 281 558 5289",
    "sg:postcode":"77077",
    "sg:province":"TX",
    "wof:name":"Avl Solutions",
    "wof:placetype":"venue"
},
  "geometry": {"coordinates":[-95.60381,29.759531],"type":"Point"}
}