{
  "type": "Feature",
  "properties": {
    "iso:country":"US",
    "sg:address":"713 N Riedel St",
    "sg:city":"Yorktown",
    "sg:classifiers":[
        {
            "category":"Restaurant",
            "type":"Food & Drink"
        }
    ],
    "sg:phone":"+1 361 564 3669",
    "sg:postcode":"78164",
    "sg:province":"TX",
    "sg:tags":[
        "mexican"
    ],
    "wof:name":"El Sombrero Cafe",
    "wof:placetype":"venue"
},
  "geometry": {"coordinates":[-97.504769,28.98999],"type":"Point"}
}