{
  "type": "Feature",
  "properties": {
    "iso:country":"US",
    "sg:address":"929 W Pioneer Pkwy",
    "sg:city":"Grand Prairie",
    "sg:classifiers":[
        {
            "category":"Health Services",
            "subcategory":"Doctor",
            "type":"Services"
        }
    ],
    "sg:phone":"+1 972 206 2339",
    "sg:postcode":"75051",
    "sg:province":"TX",
    "sg:tags":[
        "physician",
        "surgeon"
    ],
    "wof:name":"Texas Hematology-Oncology Ctr",
    "wof:placetype":"venue"
},
  "geometry": {"coordinates":[-97.018441,32.709607],"type":"Point"}
}