{
  "type": "Feature",
  "properties": {
    "iso:country":"US",
    "sg:address":"2643 Yandall Dr",
    "sg:city":"Austin",
    "sg:classifiers":[
        {
            "category":"Professional",
            "subcategory":"Management & Consulting",
            "type":"Services"
        }
    ],
    "sg:phone":"+1 512 282 5175",
    "sg:postcode":"78748",
    "sg:province":"TX",
    "wof:name":"C4geovations",
    "wof:placetype":"venue"
},
  "geometry": {"coordinates":[-97.84916800000001,30.15498],"type":"Point"}
}