{
  "type": "Feature",
  "properties": {
    "iso:country":"US",
    "sg:address":"108 E University Blvd",
    "sg:city":"Odessa",
    "sg:classifiers":[
        {
            "category":"Retail",
            "subcategory":"Auto Repair",
            "type":"Services"
        }
    ],
    "sg:phone":"+1 432 332 1901",
    "sg:postcode":"79762",
    "sg:province":"TX",
    "sg:tags":[
        "repairing",
        "automobile"
    ],
    "wof:name":"Finishmaster Automotive Paint",
    "wof:placetype":"venue"
},
  "geometry": {"coordinates":[-102.37844699999999,31.868668],"type":"Point"}
}