{
  "type": "Feature",
  "properties": {
    "iso:country":"US",
    "sg:address":"1315 Carroll Ave",
    "sg:city":"Duncanville",
    "sg:classifiers":[
        {
            "category":"Building & Trades",
            "subcategory":"Construction",
            "type":"Services"
        }
    ],
    "sg:phone":"+1 972 298 8177",
    "sg:postcode":"75137",
    "sg:province":"TX",
    "sg:tags":[
        "covering",
        "floor",
        "contractor"
    ],
    "wof:name":"Barnes Commercial Interiors",
    "wof:placetype":"venue"
},
  "geometry": {"coordinates":[-96.904166,32.63676],"type":"Point"}
}