{
  "type": "Feature",
  "properties": {
    "iso:country":"US",
    "sg:address":"8200 N Mo Pac Expy",
    "sg:city":"Austin",
    "sg:phone":"+1 512 349 2233",
    "sg:postcode":"78759",
    "sg:province":"TX",
    "wof:name":"Industrial Systems Inc",
    "wof:placetype":"venue"
},
  "geometry": {"coordinates":[-97.743134,30.368481],"type":"Point"}
}