{
  "type": "Feature",
  "properties": {
    "iso:country":"US",
    "sg:address":"708 Magnolia Dr",
    "sg:city":"Refugio",
    "sg:classifiers":[
        {
            "category":"Restaurant",
            "type":"Food & Drink"
        }
    ],
    "sg:phone":"+1 361 526 4946",
    "sg:postcode":"78377",
    "sg:province":"TX",
    "sg:tags":[
        "eating"
    ],
    "wof:name":"T J Grumbles Catering",
    "wof:placetype":"venue"
},
  "geometry": {"coordinates":[-97.281311,28.32132],"type":"Point"}
}