{
  "type": "Feature",
  "properties": {
    "iso:country":"US",
    "sg:address":"601 S Marshall St",
    "sg:city":"Henderson",
    "sg:classifiers":[
        {
            "category":"Professional",
            "subcategory":"Accounting & Tax Preparation",
            "type":"Services"
        }
    ],
    "sg:phone":"+1 903 657 3529",
    "sg:postcode":"75654",
    "sg:province":"TX",
    "sg:tags":[
        "accountant"
    ],
    "wof:name":"Richard W Ferguson CPA",
    "wof:placetype":"venue"
},
  "geometry": {"coordinates":[-94.798075,32.148485],"type":"Point"}
}