{
  "type": "Feature",
  "properties": {
    "iso:country":"US",
    "sg:address":"306 Seacrest Blvd",
    "sg:city":"League City",
    "sg:classifiers":[
        {
            "category":"Building & Trades",
            "subcategory":"Construction",
            "type":"Services"
        }
    ],
    "sg:phone":"+1 281 334 5678",
    "sg:postcode":"77573",
    "sg:province":"TX",
    "sg:tags":[
        "residential"
    ],
    "wof:name":"VPS Trade",
    "wof:placetype":"venue"
},
  "geometry": {"coordinates":[-95.03440500000001,29.505626],"type":"Point"}
}