{
  "type": "Feature",
  "properties": {
    "iso:country":"US",
    "sg:address":"2221 Post Oak Dr",
    "sg:city":"Sherman",
    "sg:classifiers":[
        {
            "category":"Health Services",
            "subcategory":"Doctor",
            "type":"Services"
        }
    ],
    "sg:phone":"+1 903 868 3690",
    "sg:postcode":"75092",
    "sg:province":"TX",
    "sg:tags":[
        "medical"
    ],
    "wof:name":"North Texas Medical Cons",
    "wof:placetype":"venue"
},
  "geometry": {"coordinates":[-96.635617,33.656356],"type":"Point"}
}