{
  "type": "Feature",
  "properties": {
    "iso:country":"US",
    "sg:address":"801 E Mid Cities Blvd",
    "sg:city":"Euless",
    "sg:classifiers":[
        {
            "category":"Retail",
            "subcategory":"Laundry & Dry Cleaning",
            "type":"Services"
        }
    ],
    "sg:phone":"+1 817 684 8529",
    "sg:postcode":"76039",
    "sg:province":"TX",
    "sg:tags":[
        "cleaners",
        "plant",
        "drycleaning"
    ],
    "wof:name":"High Point Dry Cleaning",
    "wof:placetype":"venue"
},
  "geometry": {"coordinates":[-97.069012,32.867389],"type":"Point"}
}