{
  "type": "Feature",
  "properties": {
    "iso:country":"US",
    "sg:address":"300 S Front St",
    "sg:city":"Kyle",
    "sg:classifiers":[
        {
            "category":"Retail",
            "subcategory":"Auto Repair",
            "type":"Services"
        }
    ],
    "sg:phone":"+1 512 268 1137",
    "sg:postcode":"78640",
    "sg:province":"TX",
    "sg:tags":[
        "wrecker"
    ],
    "wof:name":"Pete's Wrecker Svc",
    "wof:placetype":"venue"
},
  "geometry": {"coordinates":[-97.875602,29.986738],"type":"Point"}
}