{
  "type": "Feature",
  "properties": {
    "iso:country":"US",
    "sg:address":"3780 Co Rd 3322",
    "sg:city":"Greenville",
    "sg:classifiers":[
        {
            "category":"Shopping",
            "subcategory":"Jewelry",
            "type":"Retail Goods"
        }
    ],
    "sg:phone":"+1 903 883 4766",
    "sg:postcode":"75402",
    "sg:province":"TX",
    "wof:name":"Hartsong Handworks",
    "wof:placetype":"venue"
},
  "geometry": {"coordinates":[-96.101468,33.040753],"type":"Point"}
}