{
  "type": "Feature",
  "properties": {
    "iso:country":"US",
    "sg:address":"112 Stanford St",
    "sg:city":"Forney",
    "sg:classifiers":[
        {
            "category":"Building & Trades",
            "subcategory":"Construction",
            "type":"Services"
        }
    ],
    "sg:phone":"+1 972 285 6381",
    "sg:postcode":"75126",
    "sg:province":"TX",
    "sg:tags":[
        "woodworker"
    ],
    "wof:name":"K Layne Co",
    "wof:placetype":"venue"
},
  "geometry": {"coordinates":[-96.468084,32.743538],"type":"Point"}
}