{
  "type": "Feature",
  "properties": {
    "iso:country":"US",
    "sg:address":"2750 Ted Trout Dr",
    "sg:city":"Lufkin",
    "sg:classifiers":[
        {
            "category":"Wholesale",
            "subcategory":"Farm Supplies",
            "type":"Manufacturing & Wholesale Goods"
        }
    ],
    "sg:phone":"+1 936 875 1922",
    "sg:postcode":"75904",
    "sg:province":"TX",
    "sg:tags":[
        "feed"
    ],
    "wof:name":"Clark's Feed & Fertilizer",
    "wof:placetype":"venue"
},
  "geometry": {"coordinates":[-94.768136,31.331994],"type":"Point"}
}