{
  "type": "Feature",
  "properties": {
    "iso:country":"US",
    "sg:address":"8218 Squires Place Dr",
    "sg:city":"Houston",
    "sg:classifiers":[
        {
            "category":"Retail",
            "subcategory":"Repair Shop",
            "type":"Services"
        }
    ],
    "sg:phone":"+1 281 277 7570",
    "sg:postcode":"77083",
    "sg:province":"TX",
    "sg:tags":[
        "refrigeration"
    ],
    "wof:name":"Jays Refrig A/C H",
    "wof:placetype":"venue"
},
  "geometry": {"coordinates":[-95.67717,29.685327],"type":"Point"}
}