{
  "type": "Feature",
  "properties": {
    "iso:country":"US",
    "sg:address":"9211 Rockmore Dr",
    "sg:city":"Houston",
    "sg:classifiers":[
        {
            "category":"Home & Garden",
            "subcategory":"Building Materials",
            "type":"Retail Goods"
        }
    ],
    "sg:phone":"+1 281 970 3555",
    "sg:postcode":"77064",
    "sg:province":"TX",
    "sg:tags":[
        "shutter"
    ],
    "wof:name":"Custom Bilt Shutter Shop",
    "wof:placetype":"venue"
},
  "geometry": {"coordinates":[-95.55731,29.94503],"type":"Point"}
}