{
  "type": "Feature",
  "properties": {
    "iso:country":"US",
    "sg:address":"806 W McDermott Dr",
    "sg:city":"Allen",
    "sg:classifiers":[
        {
            "category":"Shopping",
            "subcategory":"Hobbies, Toys, & Games",
            "type":"Retail Goods"
        },
        {
            "category":"Shopping",
            "subcategory":"Computers & Home Electronics",
            "type":"Retail Goods"
        }
    ],
    "sg:phone":"+1 214 509 0544",
    "sg:postcode":"75013",
    "sg:province":"TX",
    "sg:tags":[
        "software"
    ],
    "sg:website":"www.gamestop.com",
    "wof:name":"Gamestop",
    "wof:placetype":"venue"
},
  "geometry": {"coordinates":[-96.678988,33.101729],"type":"Point"}
}