{
  "type": "Feature",
  "properties": {
    "iso:country":"US",
    "sg:address":"2433 W Shady Grove Rd",
    "sg:city":"Irving",
    "sg:classifiers":[
        {
            "category":"Fast Food",
            "type":"Food & Drink"
        },
        {
            "category":"Restaurant",
            "type":"Food & Drink"
        }
    ],
    "sg:phone":"+1 972 790 2511",
    "sg:postcode":"75060",
    "sg:province":"TX",
    "sg:tags":[
        "hot",
        "hamburger",
        "dog"
    ],
    "wof:name":"Burger Station",
    "wof:placetype":"venue"
},
  "geometry": {"coordinates":[-96.977717,32.800496],"type":"Point"}
}