{
  "type": "Feature",
  "properties": {
    "iso:country":"US",
    "sg:address":"2011 Stratford Dr",
    "sg:city":"Round Rock",
    "sg:classifiers":[
        {
            "category":"Social Services",
            "subcategory":"Child Care",
            "type":"Services"
        }
    ],
    "sg:phone":"+1 512 388 4567",
    "sg:postcode":"78664",
    "sg:province":"TX",
    "wof:name":"Cradles To Kids",
    "wof:placetype":"venue"
},
  "geometry": {"coordinates":[-97.66692500000001,30.489559],"type":"Point"}
}