{
  "type": "Feature",
  "properties": {
    "iso:country":"US",
    "sg:address":"10500 US Hwy 80",
    "sg:city":"Forney",
    "sg:classifiers":[
        {
            "category":"Shopping",
            "type":"Retail Goods"
        }
    ],
    "sg:phone":"+1 972 864 0278",
    "sg:postcode":"75126",
    "sg:province":"TX",
    "sg:tags":[
        "picture",
        "frame"
    ],
    "wof:name":"Wholesale Art & Frames",
    "wof:placetype":"venue"
},
  "geometry": {"coordinates":[-96.436341,32.74137],"type":"Point"}
}