{
  "type": "Feature",
  "properties": {
    "iso:country":"US",
    "sg:address":"7110 Gateway Blvd E",
    "sg:city":"El Paso",
    "sg:classifiers":[
        {
            "category":"Restaurant",
            "type":"Food & Drink"
        }
    ],
    "sg:menulink":"http://www.allmenus.com/tx/el-paso/202184-mcdonalds/menu/",
    "sg:postcode":"79915",
    "sg:province":"TX",
    "sg:tags":[
        "burger",
        "american"
    ],
    "wof:name":"McDonald's",
    "wof:placetype":"venue"
},
  "geometry": {"coordinates":[-106.376842,31.770434],"type":"Point"}
}