{
  "type": "Feature",
  "properties": {
    "iso:country":"US",
    "sg:address":"304 Houston St",
    "sg:city":"Fort Worth",
    "sg:classifiers":[
        {
            "category":"Cinema",
            "subcategory":"Movie Theater",
            "type":"Entertainment"
        }
    ],
    "sg:phone":"+1 817 870 1111",
    "sg:postcode":"76102",
    "sg:province":"TX",
    "wof:name":"AMC",
    "wof:placetype":"venue"
},
  "geometry": {"coordinates":[-97.33242,32.754742],"type":"Point"}
}