{
  "type": "Feature",
  "properties": {
    "iso:country":"US",
    "sg:address":"7615 Campbell Rd",
    "sg:city":"Dallas",
    "sg:classifiers":[
        {
            "category":"Shopping",
            "subcategory":"Clothing, Apparel, & Fashions",
            "type":"Retail Goods"
        }
    ],
    "sg:phone":"+1 972 380 4433",
    "sg:postcode":"75248",
    "sg:province":"TX",
    "wof:name":"Xclusive Gifts & Jewelry",
    "wof:placetype":"venue"
},
  "geometry": {"coordinates":[-96.77015900000001,32.978277],"type":"Point"}
}