{
  "type": "Feature",
  "properties": {
    "iso:country":"US",
    "sg:address":"8719 Trumpet Cir",
    "sg:city":"Converse",
    "sg:classifiers":[
        {
            "category":"Autos & Motor Vehicles",
            "subcategory":"Recreational Vehicle Sales",
            "type":"Retail Goods"
        }
    ],
    "sg:phone":"+1 210 967 4045",
    "sg:postcode":"78109",
    "sg:province":"TX",
    "sg:tags":[
        "camper"
    ],
    "wof:name":"South Texas Happy Trails",
    "wof:placetype":"venue"
},
  "geometry": {"coordinates":[-98.31931299999999,29.46306],"type":"Point"}
}