{
  "type": "Feature",
  "properties": {
    "iso:country":"US",
    "sg:address":"210 E 57th St",
    "sg:city":"Odessa",
    "sg:classifiers":[
        {
            "category":"Manufacturing",
            "subcategory":"Tools & Machinery",
            "type":"Manufacturing & Wholesale Goods"
        }
    ],
    "sg:phone":"+1 432 362 7998",
    "sg:postcode":"79762",
    "sg:province":"TX",
    "sg:tags":[
        "equipment",
        "system",
        "automation"
    ],
    "sg:website":"www.kelleyscontrols.com",
    "wof:name":"Kelley's Controls Inc",
    "wof:placetype":"venue"
},
  "geometry": {"coordinates":[-102.38635499999999,31.898391],"type":"Point"}
}