{
  "type": "Feature",
  "properties": {
    "iso:country":"US",
    "sg:address":"118 Main St",
    "sg:city":"Lometa",
    "sg:classifiers":[
        {
            "category":"Shopping",
            "subcategory":"Discount & Variety Stores",
            "type":"Retail Goods"
        }
    ],
    "sg:phone":"+1 512 752 8463",
    "sg:postcode":"76853",
    "sg:province":"TX",
    "wof:name":"Lometa Mercantile",
    "wof:placetype":"venue"
},
  "geometry": {"coordinates":[-98.391336,31.21746],"type":"Point"}
}