{
  "type": "Feature",
  "properties": {
    "iso:country":"US",
    "sg:address":"502 Stone City Dr",
    "sg:city":"Bryan",
    "sg:classifiers":[
        {
            "category":"Professional",
            "subcategory":"Detective & Security Services",
            "type":"Services"
        }
    ],
    "sg:phone":"+1 979 779 8114",
    "sg:postcode":"77803",
    "sg:province":"TX",
    "sg:tags":[
        "car"
    ],
    "wof:name":"First Star Transport",
    "wof:placetype":"venue"
},
  "geometry": {"coordinates":[-96.40449599999999,30.651986],"type":"Point"}
}