{
  "type": "Feature",
  "properties": {
    "iso:country":"US",
    "sg:address":"5016 Justin St",
    "sg:city":"Nacogdoches",
    "sg:classifiers":[
        {
            "category":"Personal",
            "subcategory":"Beauty Salon",
            "type":"Services"
        }
    ],
    "sg:phone":"+1 936 564 5041",
    "sg:postcode":"75965",
    "sg:province":"TX",
    "sg:tags":[
        "shop"
    ],
    "wof:name":"Special F X Salon",
    "wof:placetype":"venue"
},
  "geometry": {"coordinates":[-94.66249999999999,31.65357],"type":"Point"}
}