{
  "type": "Feature",
  "properties": {
    "iso:country":"US",
    "sg:address":"128 S Magdalen St",
    "sg:city":"San Angelo",
    "sg:classifiers":[
        {
            "category":"Social Services",
            "subcategory":"Adult Care",
            "type":"Services"
        }
    ],
    "sg:phone":"+1 325 658 6664",
    "sg:postcode":"76903",
    "sg:province":"TX",
    "sg:tags":[
        "residential"
    ],
    "wof:name":"Bluebonnet Homes Inc",
    "wof:placetype":"venue"
},
  "geometry": {"coordinates":[-100.432655,31.462772],"type":"Point"}
}