{
  "type": "Feature",
  "properties": {
    "iso:country":"US",
    "sg:address":"1113 Main St",
    "sg:city":"Bastrop",
    "sg:classifiers":[
        {
            "category":"Health Services",
            "subcategory":"Podiatrist",
            "type":"Services"
        }
    ],
    "sg:phone":"+1 512 321 0000",
    "sg:postcode":"78602",
    "sg:province":"TX",
    "wof:name":"Bastrop Regional Foot & Ankle",
    "wof:placetype":"venue"
},
  "geometry": {"coordinates":[-97.319971,30.112566],"type":"Point"}
}