{
  "type": "Feature",
  "properties": {
    "iso:country":"US",
    "sg:address":"502 50th St",
    "sg:city":"Lubbock",
    "sg:classifiers":[
        {
            "category":"Banks & Credit Unions",
            "subcategory":"Bank",
            "type":"Services"
        }
    ],
    "sg:phone":"+1 806 763 0244",
    "sg:postcode":"79404",
    "sg:province":"TX",
    "sg:tags":[
        "depository",
        "banking"
    ],
    "wof:name":"Western Union Agnt Prnto Chk",
    "wof:placetype":"venue"
},
  "geometry": {"coordinates":[-101.841815,33.548862],"type":"Point"}
}