{
  "type": "Feature",
  "properties": {
    "iso:country":"US",
    "sg:address":"4701 Monterey Oaks Blvd",
    "sg:city":"Austin",
    "sg:classifiers":[
        {
            "category":"Retail",
            "subcategory":"Portrait Studio",
            "type":"Services"
        }
    ],
    "sg:phone":"+1 512 892 9313",
    "sg:postcode":"78749",
    "sg:province":"TX",
    "sg:tags":[
        "photo"
    ],
    "wof:name":"Jorgenson Photography",
    "wof:placetype":"venue"
},
  "geometry": {"coordinates":[-97.840352,30.232325],"type":"Point"}
}