{
  "type": "Feature",
  "properties": {
    "iso:country":"US",
    "sg:address":"4706 Hilwin Cir",
    "sg:city":"Austin",
    "sg:classifiers":[
        {
            "category":"Health Services",
            "subcategory":"Health Practitioner",
            "type":"Services"
        }
    ],
    "sg:phone":"+1 512 451 6023",
    "sg:postcode":"78756",
    "sg:province":"TX",
    "wof:name":"Fitzsimmons Charles PHD",
    "wof:placetype":"venue"
},
  "geometry": {"coordinates":[-97.744452,30.321163],"type":"Point"}
}