{
  "type": "Feature",
  "properties": {
    "iso:country":"US",
    "sg:address":"10101 Reunion Pl",
    "sg:city":"San Antonio",
    "sg:classifiers":[
        {
            "category":"Professional",
            "subcategory":"Accounting & Tax Preparation",
            "type":"Services"
        }
    ],
    "sg:phone":"+1 210 341 9400",
    "sg:postcode":"78216",
    "sg:province":"TX",
    "sg:tags":[
        "consulting",
        "business"
    ],
    "wof:name":"Hanke Group PC",
    "wof:placetype":"venue"
},
  "geometry": {"coordinates":[-98.483631,29.532838],"type":"Point"}
}