{
  "type": "Feature",
  "properties": {
    "iso:country":"US",
    "sg:address":"200 E Starr Ave",
    "sg:city":"Hemphill",
    "sg:classifiers":[
        {
            "category":"Shopping",
            "subcategory":"Florist",
            "type":"Retail Goods"
        }
    ],
    "sg:phone":"+1 409 787 2396",
    "sg:postcode":"75961",
    "sg:province":"TX",
    "wof:name":"Hemphill Flower Shop & Gifts",
    "wof:placetype":"venue"
},
  "geometry": {"coordinates":[-94.652159,31.615931],"type":"Point"}
}