{
  "type": "Feature",
  "properties": {
    "iso:country":"US",
    "sg:address":"126 E Parade Dr",
    "sg:city":"S Padre Island",
    "sg:classifiers":[
        {
            "category":"Food & Beverages",
            "subcategory":"Groceries & Convenience Stores",
            "type":"Retail Goods"
        }
    ],
    "sg:phone":"+1 956 761 1498",
    "sg:postcode":"78597",
    "sg:province":"TX",
    "wof:name":"Hop N Shop Stores Inc",
    "wof:placetype":"venue"
},
  "geometry": {"coordinates":[-97.16972699999999,26.128695],"type":"Point"}
}