{
  "type": "Feature",
  "properties": {
    "iso:country":"US",
    "sg:address":"2550 Elm St",
    "sg:city":"Dallas",
    "sg:classifiers":[
        {
            "category":"Personal",
            "subcategory":"Beauty Salon",
            "type":"Services"
        }
    ],
    "sg:phone":"+1 214 742 2500",
    "sg:postcode":"75226",
    "sg:province":"TX",
    "sg:tags":[
        "shop"
    ],
    "wof:name":"Sweet 200",
    "wof:placetype":"venue"
},
  "geometry": {"coordinates":[-96.787862,32.783724],"type":"Point"}
}