{
  "type": "Feature",
  "properties": {
    "iso:country":"US",
    "sg:address":"343 Brompton Ct",
    "sg:city":"Highlands",
    "sg:classifiers":[
        {
            "category":"Building & Trades",
            "subcategory":"Construction",
            "type":"Services"
        }
    ],
    "sg:phone":"+1 281 843 3147",
    "sg:postcode":"77562",
    "sg:province":"TX",
    "sg:tags":[
        "house"
    ],
    "wof:name":"Mas Painting & Remodeling",
    "wof:placetype":"venue"
},
  "geometry": {"coordinates":[-95.068293,29.820093],"type":"Point"}
}