{
  "type": "Feature",
  "properties": {
    "iso:country":"US",
    "sg:address":"318 E Nakoma Dr",
    "sg:city":"San Antonio",
    "sg:classifiers":[
        {
            "category":"Professional",
            "type":"Services"
        }
    ],
    "sg:phone":"+1 210 545 5975",
    "sg:postcode":"78216",
    "sg:province":"TX",
    "sg:tags":[
        "arts",
        "artist"
    ],
    "wof:name":"Jim Bower",
    "wof:placetype":"venue"
},
  "geometry": {"coordinates":[-98.48889800000001,29.549392],"type":"Point"}
}