{
  "type": "Feature",
  "properties": {
    "iso:country":"US",
    "sg:address":"Memorial City Shopping Ctr",
    "sg:city":"Houston",
    "sg:classifiers":[
        {
            "category":"Shopping",
            "subcategory":"Optician",
            "type":"Retail Goods"
        }
    ],
    "sg:phone":"+1 713 973 9694",
    "sg:postcode":"77024",
    "sg:province":"TX",
    "sg:tags":[
        "eyewear"
    ],
    "wof:name":"Sunglass Hut",
    "wof:placetype":"venue"
},
  "geometry": {"coordinates":[-95.542042,29.781564],"type":"Point"}
}