{
  "type": "Feature",
  "properties": {
    "iso:country":"US",
    "sg:address":"2409 Whitmore St",
    "sg:city":"Fort Worth",
    "sg:classifiers":[
        {
            "category":"Manufacturing",
            "subcategory":"Metals",
            "type":"Manufacturing & Wholesale Goods"
        }
    ],
    "sg:phone":"+1 817 336 8025",
    "sg:postcode":"76107",
    "sg:province":"TX",
    "sg:tags":[
        "plating"
    ],
    "wof:name":"AAA Industrial Chromium Co",
    "wof:placetype":"venue"
},
  "geometry": {"coordinates":[-97.350826,32.757986],"type":"Point"}
}