{
  "type": "Feature",
  "properties": {
    "iso:country":"US",
    "sg:address":"10901 Harry Hines Blvd",
    "sg:city":"Dallas",
    "sg:classifiers":[
        {
            "category":"Retail",
            "subcategory":"Repair Shop",
            "type":"Services"
        },
        {
            "category":"Home & Garden",
            "subcategory":"Home Furnishings",
            "type":"Retail Goods"
        },
        {
            "category":"Shopping",
            "subcategory":"Crafts & Fabrics",
            "type":"Retail Goods"
        }
    ],
    "sg:phone":"+1 214 350 2583",
    "sg:postcode":"75220",
    "sg:province":"TX",
    "sg:tags":[
        "decor",
        "reupholstery",
        "store",
        "furniture"
    ],
    "wof:name":"Best Fabrics Llc",
    "wof:placetype":"venue"
},
  "geometry": {"coordinates":[-96.884804,32.877499],"type":"Point"}
}