{
  "type": "Feature",
  "properties": {
    "iso:country":"US",
    "sg:address":"3627 Ave H",
    "sg:city":"Rosenberg",
    "sg:classifiers":[
        {
            "category":"Restaurant",
            "type":"Food & Drink"
        }
    ],
    "sg:phone":"+1 281 342 8373",
    "sg:postcode":"77471",
    "sg:province":"TX",
    "wof:name":"Mc Donald's",
    "wof:placetype":"venue"
},
  "geometry": {"coordinates":[-95.79016900000001,29.559417],"type":"Point"}
}