{
  "type": "Feature",
  "properties": {
    "iso:country":"US",
    "sg:address":"3215 W Ranch Rd 1431",
    "sg:city":"Kingsland",
    "sg:classifiers":[
        {
            "category":"Shopping",
            "subcategory":"Discount & Variety Stores",
            "type":"Retail Goods"
        }
    ],
    "sg:phone":"+1 325 388 8205",
    "sg:postcode":"78639",
    "sg:province":"TX",
    "wof:name":"Dollar General",
    "wof:placetype":"venue"
},
  "geometry": {"coordinates":[-98.454649,30.671318],"type":"Point"}
}