{
  "type": "Feature",
  "properties": {
    "iso:country":"US",
    "sg:address":"16555 Fir Rd",
    "sg:city":"Santa Fe",
    "sg:classifiers":[
        {
            "category":"Building & Trades",
            "subcategory":"Construction",
            "type":"Services"
        }
    ],
    "sg:phone":"+1 409 925 2560",
    "sg:postcode":"77517",
    "sg:province":"TX",
    "sg:tags":[
        "maintenance",
        "contractor"
    ],
    "wof:name":"Quality Mowing & Mntnc Inc",
    "wof:placetype":"venue"
},
  "geometry": {"coordinates":[-95.166094,29.391227],"type":"Point"}
}