{
  "type": "Feature",
  "properties": {
    "iso:country":"US",
    "sg:address":"721 Park St",
    "sg:city":"Baytown",
    "sg:classifiers":[
        {
            "category":"Food & Beverages",
            "subcategory":"Groceries & Convenience Stores",
            "type":"Retail Goods"
        }
    ],
    "sg:phone":"+1 281 422 1010",
    "sg:postcode":"77520",
    "sg:province":"TX",
    "wof:name":"Garth Powerfuel",
    "wof:placetype":"venue"
},
  "geometry": {"coordinates":[-94.97518700000001,29.746493],"type":"Point"}
}