{
  "type": "Feature",
  "properties": {
    "iso:country":"US",
    "sg:address":"16013 Scenic Oaks Trl",
    "sg:city":"Buda",
    "sg:classifiers":[
        {
            "category":"Professional",
            "subcategory":"Business Services",
            "type":"Services"
        }
    ],
    "sg:phone":"+1 512 295 2323",
    "sg:postcode":"78610",
    "sg:province":"TX",
    "wof:name":"Dy Enterprisessafety Ser",
    "wof:placetype":"venue"
},
  "geometry": {"coordinates":[-97.890001,30.114587],"type":"Point"}
}