{
  "type": "Feature",
  "properties": {
    "iso:country":"US",
    "sg:address":"520 S Austin St",
    "sg:city":"Webster",
    "sg:classifiers":[
        {
            "category":"Organizations",
            "subcategory":"Religious Organization",
            "type":"Services"
        }
    ],
    "sg:phone":"+1 281 338 1842",
    "sg:postcode":"77598",
    "sg:province":"TX",
    "sg:tags":[
        "church"
    ],
    "wof:name":"Community Of Christ",
    "wof:placetype":"venue"
},
  "geometry": {"coordinates":[-95.117271,29.53333],"type":"Point"}
}