{
  "type": "Feature",
  "properties": {
    "iso:country":"US",
    "sg:address":"1623 Parkdale Dr",
    "sg:city":"Wichita Falls",
    "sg:classifiers":[
        {
            "category":"Professional",
            "type":"Services"
        }
    ],
    "sg:phone":"+1 940 766 3826",
    "sg:postcode":"76306",
    "sg:province":"TX",
    "wof:name":"Bettys Sewing Corner",
    "wof:placetype":"venue"
},
  "geometry": {"coordinates":[-98.517644,33.945255],"type":"Point"}
}