{
  "type": "Feature",
  "properties": {
    "iso:country":"US",
    "sg:address":"834 S Bolton St",
    "sg:city":"Jacksonville",
    "sg:classifiers":[
        {
            "category":"Personal",
            "subcategory":"Beauty Salon",
            "type":"Services"
        }
    ],
    "sg:phone":"+1 903 586 5018",
    "sg:postcode":"75766",
    "sg:province":"TX",
    "sg:tags":[
        "shop"
    ],
    "wof:name":"Stacies",
    "wof:placetype":"venue"
},
  "geometry": {"coordinates":[-95.272255,31.956675],"type":"Point"}
}