{
  "type": "Feature",
  "properties": {
    "iso:country":"US",
    "sg:address":"8002 Hartford St",
    "sg:city":"Houston",
    "sg:classifiers":[
        {
            "category":"Banks & Credit Unions",
            "subcategory":"Financial Services",
            "type":"Services"
        }
    ],
    "sg:phone":"+1 713 649 3777",
    "sg:postcode":"77017",
    "sg:province":"TX",
    "sg:tags":[
        "trust",
        "management"
    ],
    "wof:name":"Entrust One",
    "wof:placetype":"venue"
},
  "geometry": {"coordinates":[-95.277681,29.691291],"type":"Point"}
}