{
  "type": "Feature",
  "properties": {
    "iso:country":"US",
    "sg:address":"901 S Mo Pac Expy",
    "sg:city":"Austin",
    "sg:classifiers":[
        {
            "category":"Health Services",
            "subcategory":"Clinic",
            "type":"Services"
        }
    ],
    "sg:phone":"+1 512 413 9219",
    "sg:postcode":"78746",
    "sg:province":"TX",
    "sg:tags":[
        "counseling",
        "mental"
    ],
    "wof:name":"Palmer John C Lcsw Acp",
    "wof:placetype":"venue"
},
  "geometry": {"coordinates":[-97.777496,30.268],"type":"Point"}
}