{
  "type": "Feature",
  "properties": {
    "iso:country":"US",
    "sg:address":"32 Highland Park Vlg",
    "sg:city":"Dallas",
    "sg:classifiers":[
        {
            "category":"Ice Cream",
            "type":"Food & Drink"
        }
    ],
    "sg:phone":"+1 214 219 6161",
    "sg:postcode":"75205",
    "sg:province":"TX",
    "sg:tags":[
        "frozen",
        "yogurt"
    ],
    "wof:name":"Paciugo",
    "wof:placetype":"venue"
},
  "geometry": {"coordinates":[-96.806297,32.8363],"type":"Point"}
}