{
  "type": "Feature",
  "properties": {
    "iso:country":"US",
    "sg:address":"47 Highland Park Village",
    "sg:city":"Dallas",
    "sg:classifiers":[
        {
            "category":"Sports & Exercise",
            "subcategory":"Gym",
            "type":"Entertainment"
        }
    ],
    "sg:phone":"+1 214 526 6784",
    "sg:postcode":"75205",
    "sg:province":"TX",
    "sg:tags":[
        "center",
        "fitness"
    ],
    "wof:name":"Larry North Total Fitness",
    "wof:placetype":"venue"
},
  "geometry": {"coordinates":[-96.806456,32.83632],"type":"Point"}
}