{
  "type": "Feature",
  "properties": {
    "iso:country":"US",
    "sg:address":"13843 Highway 105 W # 423",
    "sg:city":"Conroe",
    "sg:classifiers":[
        {
            "category":"Shopping",
            "subcategory":"Bicycles & Sporting Goods",
            "type":"Retail Goods"
        }
    ],
    "sg:phone":"+1 936 588 2510",
    "sg:postcode":"77304",
    "sg:province":"TX",
    "sg:tags":[
        "equipment",
        "supply",
        "archery"
    ],
    "wof:name":"Evolution Archery Technologies",
    "wof:placetype":"venue"
},
  "geometry": {"coordinates":[-95.56986999999999,30.349098],"type":"Point"}
}