{
  "type": "Feature",
  "properties": {
    "iso:country":"US",
    "sg:address":"2062 FM 368 S",
    "sg:city":"Iowa Park",
    "sg:classifiers":[
        {
            "category":"Manufacturing",
            "subcategory":"Chemicals & Compounds",
            "type":"Manufacturing & Wholesale Goods"
        }
    ],
    "sg:phone":"+1 940 592 4161",
    "sg:postcode":"76367",
    "sg:province":"TX",
    "sg:tags":[
        "fertilizer"
    ],
    "wof:name":"Texoma Fertilizers",
    "wof:placetype":"venue"
},
  "geometry": {"coordinates":[-98.671953,33.926828],"type":"Point"}
}