{
  "type": "Feature",
  "properties": {
    "iso:country":"US",
    "sg:address":"301 Nature Center Dr",
    "sg:city":"Austin",
    "sg:classifiers":[
        {
            "category":"Professional",
            "type":"Services"
        }
    ],
    "sg:phone":"+1 512 327 8180",
    "sg:postcode":"78746",
    "sg:province":"TX",
    "wof:name":"Austin Nature & Science Center",
    "wof:placetype":"venue"
},
  "geometry": {"coordinates":[-97.775311,30.270377],"type":"Point"}
}