{
  "type": "Feature",
  "properties": {
    "iso:country":"US",
    "sg:address":"220 Elizabeth Dr",
    "sg:city":"Del Rio",
    "sg:classifiers":[
        {
            "category":"Professional",
            "type":"Services"
        }
    ],
    "sg:phone":"+1 830 778 1020",
    "sg:postcode":"78840",
    "sg:province":"TX",
    "wof:name":"Score",
    "wof:placetype":"venue"
},
  "geometry": {"coordinates":[-100.912086,29.395005],"type":"Point"}
}