{
  "type": "Feature",
  "properties": {
    "iso:country":"US",
    "sg:address":"1087 W Main St",
    "sg:city":"Coppell",
    "sg:classifiers":[
        {
            "category":"Shopping",
            "subcategory":"Pharmacy",
            "type":"Retail Goods"
        }
    ],
    "sg:phone":"+1 972 420 8590",
    "sg:postcode":"75019",
    "sg:province":"TX",
    "sg:tags":[
        "drugstore"
    ],
    "wof:name":"Sav -On Pharmacies",
    "wof:placetype":"venue"
},
  "geometry": {"coordinates":[-96.907847,32.952508],"type":"Point"}
}