{
  "type": "Feature",
  "properties": {
    "iso:country":"US",
    "sg:address":"2717 Jewell Dr",
    "sg:city":"Arlington",
    "sg:classifiers":[
        {
            "category":"Shopping",
            "subcategory":"Crafts & Fabrics",
            "type":"Retail Goods"
        }
    ],
    "sg:phone":"+1 817 496 3602",
    "sg:postcode":"76016",
    "sg:province":"TX",
    "sg:tags":[
        "material",
        "needlework"
    ],
    "wof:name":"Suzan's Sewing",
    "wof:placetype":"venue"
},
  "geometry": {"coordinates":[-97.184301,32.700316],"type":"Point"}
}