{
  "type": "Feature",
  "properties": {
    "iso:country":"US",
    "sg:address":"2533 Belmeade Dr",
    "sg:city":"Carrollton",
    "sg:classifiers":[
        {
            "category":"Communications",
            "subcategory":"Film & Video Production",
            "type":"Services"
        }
    ],
    "sg:phone":"+1 972 478 2077",
    "sg:postcode":"75006",
    "sg:province":"TX",
    "sg:tags":[
        "motion"
    ],
    "wof:name":"Don Chesshir Productions",
    "wof:placetype":"venue"
},
  "geometry": {"coordinates":[-96.865815,32.980308],"type":"Point"}
}