{
  "type": "Feature",
  "properties": {
    "iso:country":"US",
    "sg:address":"321 W Cleveland Blvd",
    "sg:city":"Aransas Pass",
    "sg:classifiers":[
        {
            "category":"Real Estate",
            "subcategory":"Real Estate Operator",
            "type":"Services"
        }
    ],
    "sg:phone":"+1 361 758 3812",
    "sg:postcode":"78336",
    "sg:province":"TX",
    "sg:tags":[
        "apartment"
    ],
    "wof:name":"Jackson Square Apartments",
    "wof:placetype":"venue"
},
  "geometry": {"coordinates":[-97.143728,27.910909],"type":"Point"}
}