{
  "type": "Feature",
  "properties": {
    "iso:country":"US",
    "sg:address":"5811 Mesa Dr",
    "sg:city":"Austin",
    "sg:classifiers":[
        {
            "category":"Real Estate",
            "subcategory":"Real Estate Operator",
            "type":"Services"
        }
    ],
    "sg:phone":"+1 512 451 9933",
    "sg:postcode":"78731",
    "sg:province":"TX",
    "sg:tags":[
        "building",
        "apartment"
    ],
    "sg:website":"www.gables.com",
    "wof:name":"Gables At Park Mesa",
    "wof:placetype":"venue"
},
  "geometry": {"coordinates":[-97.770792,30.342914],"type":"Point"}
}