{
  "type": "Feature",
  "properties": {
    "iso:country":"US",
    "sg:address":"3340 Greens Rd",
    "sg:city":"Houston",
    "sg:classifiers":[
        {
            "category":"Freight",
            "type":"Transportation"
        }
    ],
    "sg:phone":"+1 281 219 2828",
    "sg:postcode":"77032",
    "sg:province":"TX",
    "wof:name":"Dart Express",
    "wof:placetype":"venue"
},
  "geometry": {"coordinates":[-95.334037,29.951369],"type":"Point"}
}