{
  "type": "Feature",
  "properties": {
    "iso:country":"US",
    "sg:address":"2305 Truxillo St",
    "sg:city":"Houston",
    "sg:classifiers":[
        {
            "category":"Building & Trades",
            "subcategory":"Construction",
            "type":"Services"
        }
    ],
    "sg:phone":"+1 713 478 8551",
    "sg:postcode":"77004",
    "sg:province":"TX",
    "sg:tags":[
        "repair",
        "new"
    ],
    "wof:name":"Advanced Cnstr Tech - Act",
    "wof:placetype":"venue"
},
  "geometry": {"coordinates":[-95.369231,29.730667],"type":"Point"}
}