{
  "type": "Feature",
  "properties": {
    "iso:country":"US",
    "sg:address":"2813 W T C Jester Blvd",
    "sg:city":"Houston",
    "sg:classifiers":[
        {
            "category":"Professional",
            "subcategory":"Lawyer & Legal Services",
            "type":"Services"
        }
    ],
    "sg:phone":"+1 713 680 3296",
    "sg:postcode":"77018",
    "sg:province":"TX",
    "sg:tags":[
        "attorney"
    ],
    "wof:name":"Brian Middleton",
    "wof:placetype":"venue"
},
  "geometry": {"coordinates":[-95.44544999999999,29.812818],"type":"Point"}
}