{
  "type": "Feature",
  "properties": {
    "iso:country":"US",
    "sg:address":"222 E Laurel Ave",
    "sg:city":"Lufkin",
    "sg:classifiers":[
        {
            "category":"Wholesale",
            "subcategory":"Non-durable Goods",
            "type":"Manufacturing & Wholesale Goods"
        }
    ],
    "sg:phone":"+1 936 699 2562",
    "sg:postcode":"75901",
    "sg:province":"TX",
    "wof:name":"Tienda Mexicana El Veracrusano",
    "wof:placetype":"venue"
},
  "geometry": {"coordinates":[-94.724451,31.346177],"type":"Point"}
}