{
  "type": "Feature",
  "properties": {
    "iso:country":"US",
    "sg:address":"5501 Valerie St",
    "sg:city":"Houston",
    "sg:classifiers":[
        {
            "category":"Building & Trades",
            "subcategory":"Equipment Rental",
            "type":"Services"
        }
    ],
    "sg:phone":"+1 713 592 9687",
    "sg:postcode":"77081",
    "sg:province":"TX",
    "sg:tags":[
        "heavy",
        "construction"
    ],
    "wof:name":"Lindsey Builders Cnstr Rentals",
    "wof:placetype":"venue"
},
  "geometry": {"coordinates":[-95.488647,29.693419],"type":"Point"}
}