{
  "type": "Feature",
  "properties": {
    "iso:country":"US",
    "sg:address":"5900 Balcones Rd Ste 242",
    "sg:city":"Austin",
    "sg:classifiers":[
        {
            "category":"Personal",
            "subcategory":"Beauty Salon",
            "type":"Services"
        },
        {
            "category":"Shopping",
            "type":"Retail Goods"
        }
    ],
    "sg:phone":"+1 512 217 9869",
    "sg:postcode":"78731",
    "sg:province":"TX",
    "sg:tags":[
        "spa"
    ],
    "sg:website":"www.austinpersonalstylist.com",
    "wof:name":"Thea Wood - Austin's Personal Stylist",
    "wof:placetype":"venue"
},
  "geometry": {"coordinates":[-97.754993,30.34147],"type":"Point"}
}