{
  "type": "Feature",
  "properties": {
    "iso:country":"US",
    "sg:address":"116 E Post Office St",
    "sg:city":"Weimar",
    "sg:classifiers":[
        {
            "category":"Banks & Credit Unions",
            "subcategory":"Bank",
            "type":"Services"
        }
    ],
    "sg:phone":"+1 979 725 8507",
    "sg:postcode":"78962",
    "sg:province":"TX",
    "wof:name":"Hibernia National Bank",
    "wof:placetype":"venue"
},
  "geometry": {"coordinates":[-96.779371,29.703521],"type":"Point"}
}