{
  "type": "Feature",
  "properties": {
    "iso:country":"US",
    "sg:address":"3613 Frankford Rd Ofc",
    "sg:city":"Dallas",
    "sg:classifiers":[
        {
            "category":"Real Estate",
            "subcategory":"Real Estate Operator",
            "type":"Services"
        }
    ],
    "sg:phone":"+1 972 820 0200",
    "sg:postcode":"75287",
    "sg:province":"TX",
    "sg:tags":[
        "apartment"
    ],
    "wof:name":"Gates De Provence",
    "wof:placetype":"venue"
},
  "geometry": {"coordinates":[-96.853302,32.9972],"type":"Point"}
}