{
  "type": "Feature",
  "properties": {
    "iso:country":"US",
    "sg:address":"4014 Fairmount St",
    "sg:city":"Dallas",
    "sg:classifiers":[
        {
            "category":"Arts & Performance",
            "subcategory":"Theater",
            "type":"Entertainment"
        }
    ],
    "sg:phone":"+1 214 641 3887",
    "sg:postcode":"75219",
    "sg:province":"TX",
    "sg:tags":[
        "theatrical"
    ],
    "wof:name":"Tsu Lighting",
    "wof:placetype":"venue"
},
  "geometry": {"coordinates":[-96.815692,32.807253],"type":"Point"}
}