{
  "type": "Feature",
  "properties": {
    "iso:country":"US",
    "sg:address":"3840 Steeple Chase Ct",
    "sg:city":"Midlothian",
    "sg:classifiers":[
        {
            "category":"Organizations",
            "subcategory":"Religious Organization",
            "type":"Services"
        }
    ],
    "sg:phone":"+1 972 723 6769",
    "sg:postcode":"76065",
    "sg:province":"TX",
    "wof:name":"Riding 4 Christ Inc",
    "wof:placetype":"venue"
},
  "geometry": {"coordinates":[-96.94326599999999,32.51021],"type":"Point"}
}