{
  "type": "Feature",
  "properties": {
    "iso:country":"US",
    "sg:address":"11920 Westheimer Rd",
    "sg:city":"Houston",
    "sg:classifiers":[
        {
            "category":"Retail",
            "subcategory":"Auto Rental",
            "type":"Services"
        }
    ],
    "sg:phone":"+1 281 679 1166",
    "sg:postcode":"77077",
    "sg:province":"TX",
    "sg:tags":[
        "renting",
        "automobile",
        "passenger",
        "car"
    ],
    "sg:website":"www.enterprise.com",
    "wof:name":"Enterprise Rent-A-Car",
    "wof:placetype":"venue"
},
  "geometry": {"coordinates":[-95.59236900000001,29.736382],"type":"Point"}
}