{
  "type": "Feature",
  "properties": {
    "iso:country":"US",
    "sg:address":"5219 Santa Maria Ave",
    "sg:city":"Laredo",
    "sg:classifiers":[
        {
            "category":"Shopping",
            "subcategory":"Department Store",
            "type":"Retail Goods"
        }
    ],
    "sg:phone":"+1 956 727 0501",
    "sg:postcode":"78041",
    "sg:province":"TX",
    "sg:website":"http://www.kohls.com",
    "wof:name":"Kohl's",
    "wof:placetype":"venue"
},
  "geometry": {"coordinates":[-99.509694,27.547259],"type":"Point"}
}