{
  "type": "Feature",
  "properties": {
    "iso:country":"US",
    "sg:address":"3233 N Mesa St",
    "sg:city":"El Paso",
    "sg:classifiers":[
        {
            "category":"Restaurant",
            "type":"Food & Drink"
        }
    ],
    "sg:phone":"+1 915 838 1226",
    "sg:postcode":"79902",
    "sg:province":"TX",
    "sg:website":"www.cafe.net",
    "wof:name":"CAFE.NET",
    "wof:placetype":"venue"
},
  "geometry": {"coordinates":[-106.50548000000001,31.782245],"type":"Point"}
}