{
  "type": "Feature",
  "properties": {
    "iso:country":"US",
    "sg:address":"6822 Canal St",
    "sg:city":"Houston",
    "sg:classifiers":[
        {
            "category":"Professional",
            "subcategory":"Lawyer & Legal Services",
            "type":"Services"
        }
    ],
    "sg:phone":"+1 713 923 2464",
    "sg:postcode":"77011",
    "sg:province":"TX",
    "sg:tags":[
        "attorney"
    ],
    "wof:name":"Noel Bailey Atty At Law",
    "wof:placetype":"venue"
},
  "geometry": {"coordinates":[-95.303,29.740476],"type":"Point"}
}