{
  "type": "Feature",
  "properties": {
    "iso:country":"US",
    "sg:address":"214 Teakwood Ln",
    "sg:city":"Lewisville",
    "sg:classifiers":[
        {
            "category":"Retail",
            "subcategory":"Repair Shop",
            "type":"Services"
        }
    ],
    "sg:phone":"+1 972 459 7425",
    "sg:postcode":"75067",
    "sg:province":"TX",
    "sg:tags":[
        "satellite",
        "system"
    ],
    "wof:name":"ACF Communications & Tech",
    "wof:placetype":"venue"
},
  "geometry": {"coordinates":[-96.997658,33.012341],"type":"Point"}
}