{
  "type": "Feature",
  "properties": {
    "iso:country":"US",
    "sg:address":"11760 Ferguson Rd",
    "sg:city":"Dallas",
    "sg:classifiers":[
        {
            "category":"Real Estate",
            "subcategory":"Real Estate Operator",
            "type":"Services"
        }
    ],
    "sg:phone":"+1 972 681 2415",
    "sg:postcode":"75228",
    "sg:province":"TX",
    "sg:tags":[
        "apartment"
    ],
    "wof:name":"Nat L Cntr For Hsng",
    "wof:placetype":"venue"
},
  "geometry": {"coordinates":[-96.649714,32.855005],"type":"Point"}
}