{
  "type": "Feature",
  "properties": {
    "iso:country":"US",
    "sg:address":"20202 Cypresswood Glen Dr",
    "sg:city":"Spring",
    "sg:classifiers":[
        {
            "category":"Health Services",
            "subcategory":"Clinic",
            "type":"Services"
        }
    ],
    "sg:phone":"+1 281 350 0365",
    "sg:postcode":"77388",
    "sg:province":"TX",
    "wof:name":"Heart & Soul Reflexology",
    "wof:placetype":"venue"
},
  "geometry": {"coordinates":[-95.47111099999999,30.054221],"type":"Point"}
}