{
  "type": "Feature",
  "properties": {
    "iso:country":"US",
    "sg:address":"4904 Lodgepole Ln",
    "sg:city":"Fort Worth",
    "sg:classifiers":[
        {
            "category":"Professional",
            "type":"Services"
        }
    ],
    "sg:phone":"+1 817 788 9311",
    "sg:postcode":"76137",
    "sg:province":"TX",
    "wof:name":"Richard Justice",
    "wof:placetype":"venue"
},
  "geometry": {"coordinates":[-97.27529699999999,32.864695],"type":"Point"}
}