{
  "type": "Feature",
  "properties": {
    "iso:country":"US",
    "sg:address":"4500 Westway Ave",
    "sg:city":"Dallas",
    "sg:classifiers":[
        {
            "category":"Banks & Credit Unions",
            "subcategory":"Investment Brokerage",
            "type":"Services"
        }
    ],
    "sg:phone":"+1 214 522 0194",
    "sg:postcode":"75205",
    "sg:province":"TX",
    "sg:tags":[
        "commodity"
    ],
    "wof:name":"Watauga Strategies LLC",
    "wof:placetype":"venue"
},
  "geometry": {"coordinates":[-96.81629,32.824135],"type":"Point"}
}