{
  "type": "Feature",
  "properties": {
    "iso:country":"US",
    "sg:address":"4933 Ambassador Row",
    "sg:city":"Corpus Christi",
    "sg:classifiers":[
        {
            "category":"Building & Trades",
            "subcategory":"Construction",
            "type":"Services"
        }
    ],
    "sg:phone":"+1 361 852 8647",
    "sg:postcode":"78416",
    "sg:province":"TX",
    "sg:tags":[
        "dry wall",
        "contractor"
    ],
    "wof:name":"Able Drywall Corp",
    "wof:placetype":"venue"
},
  "geometry": {"coordinates":[-97.444714,27.746889],"type":"Point"}
}