{
  "type": "Feature",
  "properties": {
    "iso:country":"US",
    "sg:address":"3508 Ave J",
    "sg:city":"Lubbock",
    "sg:classifiers":[
        {
            "category":"Building & Trades",
            "subcategory":"Electrical",
            "type":"Services"
        }
    ],
    "sg:phone":"+1 806 747 2443",
    "sg:postcode":"79412",
    "sg:province":"TX",
    "sg:tags":[
        "electric",
        "contractor"
    ],
    "wof:name":"Artex Electric Inc",
    "wof:placetype":"venue"
},
  "geometry": {"coordinates":[-101.846678,33.561541],"type":"Point"}
}