{
  "type": "Feature",
  "properties": {
    "iso:country":"US",
    "sg:address":"512 Acacia Ct",
    "sg:city":"League City",
    "sg:classifiers":[
        {
            "category":"Banks & Credit Unions",
            "subcategory":"Financial Services",
            "type":"Services"
        }
    ],
    "sg:phone":"+1 281 332 3731",
    "sg:postcode":"77573",
    "sg:province":"TX",
    "sg:tags":[
        "investment",
        "closed"
    ],
    "wof:name":"Bem Inc",
    "wof:placetype":"venue"
},
  "geometry": {"coordinates":[-95.124781,29.505252],"type":"Point"}
}