{
  "type": "Feature",
  "properties": {
    "iso:country":"US",
    "sg:address":"9828 Montana Ave",
    "sg:city":"El Paso",
    "sg:classifiers":[
        {
            "category":"Recreation",
            "type":"Entertainment"
        }
    ],
    "sg:phone":"+1 915 595 0655",
    "sg:postcode":"79925",
    "sg:province":"TX",
    "sg:tags":[
        "martial",
        "arts",
        "instruction"
    ],
    "wof:name":"Shinjimasu International",
    "wof:placetype":"venue"
},
  "geometry": {"coordinates":[-106.354488,31.794889],"type":"Point"}
}