{
  "type": "Feature",
  "properties": {
    "iso:country":"US",
    "sg:address":"901 S Elm St",
    "sg:city":"Denton",
    "sg:classifiers":[
        {
            "category":"Personal",
            "subcategory":"Beauty Salon",
            "type":"Services"
        }
    ],
    "sg:phone":"+1 940 387 9372",
    "sg:postcode":"76201",
    "sg:province":"TX",
    "wof:name":"Tapanga's Beauty Salon",
    "wof:placetype":"venue"
},
  "geometry": {"coordinates":[-97.134069,33.205433],"type":"Point"}
}