{
  "type": "Feature",
  "properties": {
    "iso:country":"US",
    "sg:address":"1428 W Gray St",
    "sg:city":"Houston",
    "sg:classifiers":[
        {
            "category":"Shopping",
            "subcategory":"Discount & Variety Stores",
            "type":"Retail Goods"
        }
    ],
    "sg:phone":"+1 713 522 3255",
    "sg:postcode":"77019",
    "sg:province":"TX",
    "sg:tags":[
        "merchandise",
        "general"
    ],
    "wof:name":"Dollar Tree",
    "wof:placetype":"venue"
},
  "geometry": {"coordinates":[-95.398921,29.75329],"type":"Point"}
}