{
  "type": "Feature",
  "properties": {
    "iso:country":"US",
    "sg:address":"220 N I- 35 E",
    "sg:city":"Denton",
    "sg:classifiers":[
        {
            "category":"Shopping",
            "subcategory":"Department Store",
            "type":"Retail Goods"
        }
    ],
    "sg:phone":"+1 940 566 2400",
    "sg:postcode":"76205",
    "sg:province":"TX",
    "wof:name":"Ross Dress For Less",
    "wof:placetype":"venue"
},
  "geometry": {"coordinates":[-97.13592199999999,33.196454],"type":"Point"}
}