{
  "type": "Feature",
  "properties": {
    "iso:country":"US",
    "sg:address":"415 Oak Leaf Dr",
    "sg:city":"Duncanville",
    "sg:classifiers":[
        {
            "category":"Banks & Credit Unions",
            "subcategory":"Investment Brokerage",
            "type":"Services"
        }
    ],
    "sg:phone":"+1 972 572 5756",
    "sg:postcode":"75137",
    "sg:province":"TX",
    "sg:tags":[
        "security"
    ],
    "wof:name":"Raymond James Financial Svcs",
    "wof:placetype":"venue"
},
  "geometry": {"coordinates":[-96.916968,32.63323],"type":"Point"}
}