{
  "type": "Feature",
  "properties": {
    "iso:country":"US",
    "sg:address":"1231 W Pierce St",
    "sg:city":"Houston",
    "sg:classifiers":[
        {
            "category":"Banks & Credit Unions",
            "subcategory":"Bank",
            "type":"Services"
        }
    ],
    "sg:phone":"+1 713 522 0336",
    "sg:postcode":"77019",
    "sg:province":"TX",
    "sg:tags":[
        "loan",
        "real estate"
    ],
    "wof:name":"Amerifirst Home Loan",
    "wof:placetype":"venue"
},
  "geometry": {"coordinates":[-95.395777,29.753919],"type":"Point"}
}