{
  "type": "Feature",
  "properties": {
    "iso:country":"US",
    "sg:address":"3705 Ryan Ave",
    "sg:city":"Fort Worth",
    "sg:classifiers":[
        {
            "category":"Banks & Credit Unions",
            "subcategory":"Bank",
            "type":"Services"
        }
    ],
    "sg:phone":"+1 817 531 2300",
    "sg:postcode":"76110",
    "sg:province":"TX",
    "sg:tags":[
        "cashing",
        "check"
    ],
    "wof:name":"Quick Pick Check Cashing",
    "wof:placetype":"venue"
},
  "geometry": {"coordinates":[-97.342529,32.693461],"type":"Point"}
}