{
  "type": "Feature",
  "properties": {
    "iso:country":"US",
    "sg:address":"6135 Queensloch Dr",
    "sg:city":"Houston",
    "sg:classifiers":[
        {
            "category":"Real Estate",
            "subcategory":"Real Estate Operator",
            "type":"Services"
        }
    ],
    "sg:phone":"+1 713 774 9124",
    "sg:postcode":"77096",
    "sg:province":"TX",
    "sg:tags":[
        "building",
        "apartment"
    ],
    "wof:name":"2001 Brun LLC",
    "wof:placetype":"venue"
},
  "geometry": {"coordinates":[-95.49901,29.673379],"type":"Point"}
}