{
  "type": "Feature",
  "properties": {
    "iso:country":"US",
    "sg:address":"10031 Cayuga Dr",
    "sg:city":"Dallas",
    "sg:classifiers":[
        {
            "category":"Manufacturing",
            "subcategory":"Food",
            "type":"Manufacturing & Wholesale Goods"
        }
    ],
    "sg:phone":"+1 214 327 0856",
    "sg:postcode":"75228",
    "sg:province":"TX",
    "sg:tags":[
        "drink",
        "soft",
        "mfg"
    ],
    "wof:name":"Zemi Sports Drink",
    "wof:placetype":"venue"
},
  "geometry": {"coordinates":[-96.689018,32.833165],"type":"Point"}
}