{
  "type": "Feature",
  "properties": {
    "iso:country":"US",
    "sg:address":"1614 Rambling Stone Dr",
    "sg:city":"Richmond",
    "sg:classifiers":[
        {
            "category":"Social Services",
            "type":"Services"
        }
    ],
    "sg:phone":"+1 281 341 7389",
    "sg:postcode":"77469",
    "sg:province":"TX",
    "sg:tags":[
        "instruction",
        "health",
        "care"
    ],
    "wof:name":"Life Line Consulting",
    "wof:placetype":"venue"
},
  "geometry": {"coordinates":[-95.732274,29.627455],"type":"Point"}
}