{
  "type": "Feature",
  "properties": {
    "iso:country":"US",
    "sg:address":"2801 Seagoville Rd",
    "sg:city":"Seagoville",
    "sg:classifiers":[
        {
            "category":"Sports & Exercise",
            "subcategory":"Race Track",
            "type":"Entertainment"
        }
    ],
    "sg:phone":"+1 972 287 2153",
    "sg:postcode":"75159",
    "sg:province":"TX",
    "sg:tags":[
        "repair",
        "auto",
        "general",
        "operation",
        "racing",
        "or"
    ],
    "wof:name":"Chase ME Racing Products",
    "wof:placetype":"venue"
},
  "geometry": {"coordinates":[-96.57731200000001,32.67635],"type":"Point"}
}