{
  "type": "Feature",
  "properties": {
    "iso:country":"US",
    "sg:address":"9508 Jollyville Rd",
    "sg:city":"Austin",
    "sg:classifiers":[
        {
            "category":"Manufacturing",
            "subcategory":"Tools & Machinery",
            "type":"Manufacturing & Wholesale Goods"
        }
    ],
    "sg:phone":"+1 512 637 4800",
    "sg:postcode":"78759",
    "sg:province":"TX",
    "sg:tags":[
        "electronic",
        "component",
        "mfg"
    ],
    "wof:name":"Uplink Corporation",
    "wof:placetype":"venue"
},
  "geometry": {"coordinates":[-97.745379,30.384599],"type":"Point"}
}