{
  "type": "Feature",
  "properties": {
    "iso:country":"US",
    "sg:address":"578 Ranch Rd 2831",
    "sg:city":"Horseshoe Bay",
    "sg:classifiers":[
        {
            "category":"Professional",
            "type":"Services"
        },
        {
            "category":"Professional",
            "subcategory":"Business Services",
            "type":"Services"
        }
    ],
    "sg:phone":"+1 830 598 1409",
    "sg:postcode":"78657",
    "sg:province":"TX",
    "sg:tags":[
        "transcribing",
        "disc"
    ],
    "wof:name":"Meditask",
    "wof:placetype":"venue"
},
  "geometry": {"coordinates":[-98.422448,30.533193],"type":"Point"}
}