{
  "type": "Feature",
  "properties": {
    "iso:country":"US",
    "sg:address":"2207 Toulon Ln",
    "sg:city":"Dallas",
    "sg:classifiers":[
        {
            "category":"Manufacturing",
            "subcategory":"Printing",
            "type":"Manufacturing & Wholesale Goods"
        }
    ],
    "sg:phone":"+1 214 388 1933",
    "sg:postcode":"75227",
    "sg:province":"TX",
    "sg:tags":[
        "publishing"
    ],
    "wof:name":"Hnq Music",
    "wof:placetype":"venue"
},
  "geometry": {"coordinates":[-96.675214,32.753671],"type":"Point"}
}