{
  "type": "Feature",
  "properties": {
    "iso:country":"US",
    "sg:address":"9606 Mopac Expressway North, Suite 870",
    "sg:city":"Austin",
    "sg:classifiers":[
        {
            "category":"Professional",
            "subcategory":"Computer Services",
            "type":"Services"
        }
    ],
    "sg:phone":"+1 512 219 9891",
    "sg:postcode":"78759",
    "sg:province":"TX",
    "sg:website":"http://www.aztecsystems.com",
    "wof:name":"Aztec Systems",
    "wof:placetype":"venue"
},
  "geometry": {"coordinates":[-97.74260099999999,30.368247],"type":"Point"}
}