{
  "type": "Feature",
  "properties": {
    "iso:country":"US",
    "sg:address":"4209 W Waco Dr",
    "sg:city":"Waco",
    "sg:classifiers":[
        {
            "category":"Insurance",
            "subcategory":"Insurance Agent",
            "type":"Services"
        }
    ],
    "sg:phone":"+1 254 757 1511",
    "sg:postcode":"76710",
    "sg:province":"TX",
    "wof:name":"Mary Graham Insurance",
    "wof:placetype":"venue"
},
  "geometry": {"coordinates":[-97.169721,31.52926],"type":"Point"}
}