{
  "type": "Feature",
  "properties": {
    "iso:country":"US",
    "sg:address":"2543 E 8th St",
    "sg:city":"Odessa",
    "sg:phone":"+1 432 332 5344",
    "sg:postcode":"79761",
    "sg:province":"TX",
    "wof:name":"Texas Certified Motors",
    "wof:placetype":"venue"
},
  "geometry": {"coordinates":[-102.333794,31.863703],"type":"Point"}
}