{
  "type": "Feature",
  "properties": {
    "iso:country":"US",
    "sg:address":"1517 Burmeister Rd",
    "sg:city":"Fort Worth",
    "sg:classifiers":[
        {
            "category":"Shopping",
            "subcategory":"Hobbies, Toys, & Games",
            "type":"Retail Goods"
        }
    ],
    "sg:phone":"+1 817 551 7378",
    "sg:postcode":"76134",
    "sg:province":"TX",
    "wof:name":"Hearts & Crafts",
    "wof:placetype":"venue"
},
  "geometry": {"coordinates":[-97.341774,32.643901],"type":"Point"}
}