{
  "type": "Feature",
  "properties": {
    "iso:country":"US",
    "sg:address":"762 Enterprise St",
    "sg:city":"Houston",
    "sg:classifiers":[
        {
            "category":"Organizations",
            "subcategory":"Religious Organization",
            "type":"Services"
        }
    ],
    "sg:phone":"+1 281 445 7186",
    "sg:postcode":"77088",
    "sg:province":"TX",
    "wof:name":"God's Holy Place",
    "wof:placetype":"venue"
},
  "geometry": {"coordinates":[-95.415925,29.874464],"type":"Point"}
}