{
  "type": "Feature",
  "properties": {
    "iso:country":"US",
    "sg:address":"354 Point Trl",
    "sg:city":"Arlington",
    "sg:classifiers":[
        {
            "category":"Banks & Credit Unions",
            "subcategory":"Financial Services",
            "type":"Services"
        }
    ],
    "sg:phone":"+1 817 417 5918",
    "sg:postcode":"76015",
    "sg:province":"TX",
    "sg:tags":[
        "investor"
    ],
    "wof:name":"Homes Your Way Inc",
    "wof:placetype":"venue"
},
  "geometry": {"coordinates":[-97.13924799999999,32.687086],"type":"Point"}
}