{
  "type": "Feature",
  "properties": {
    "iso:country":"US",
    "sg:address":"2303 Old Chappell Hill Rd",
    "sg:city":"Brenham",
    "sg:classifiers":[
        {
            "category":"Organizations",
            "subcategory":"Community Association",
            "type":"Services"
        }
    ],
    "sg:phone":"+1 979 836 8350",
    "sg:postcode":"77833",
    "sg:province":"TX",
    "wof:name":"American Legion Post No 814",
    "wof:placetype":"venue"
},
  "geometry": {"coordinates":[-96.376564,30.170267],"type":"Point"}
}