{
  "type": "Feature",
  "properties": {
    "iso:country":"US",
    "sg:address":"206 S High St",
    "sg:city":"Longview",
    "sg:classifiers":[
        {
            "category":"Retail",
            "subcategory":"Repair Shop",
            "type":"Services"
        },
        {
            "category":"Shopping",
            "type":"Retail Goods"
        }
    ],
    "sg:phone":"+1 903 758 8864",
    "sg:postcode":"75601",
    "sg:province":"TX",
    "sg:tags":[
        "equipment",
        "locksmith",
        "merchandise",
        "lock"
    ],
    "wof:name":"Sartain Lock & Safe Co",
    "wof:placetype":"venue"
},
  "geometry": {"coordinates":[-94.742705,32.493514],"type":"Point"}
}