{
  "type": "Feature",
  "properties": {
    "iso:country":"US",
    "sg:address":"3701 Lariat Ln",
    "sg:city":"Garland",
    "sg:classifiers":[
        {
            "category":"Professional",
            "subcategory":"Management & Consulting",
            "type":"Services"
        }
    ],
    "sg:phone":"+1 972 276 9642",
    "sg:postcode":"75042",
    "sg:province":"TX",
    "sg:tags":[
        "c",
        "business"
    ],
    "wof:name":"Veejer Enterprises",
    "wof:placetype":"venue"
},
  "geometry": {"coordinates":[-96.685727,32.919355],"type":"Point"}
}