{
  "type": "Feature",
  "properties": {
    "iso:country":"US",
    "sg:address":"12823 Butterfly Ln",
    "sg:city":"Houston",
    "sg:classifiers":[
        {
            "category":"Autos & Motor Vehicles",
            "subcategory":"Auto Supplies",
            "type":"Retail Goods"
        }
    ],
    "sg:phone":"+1 832 460 1587",
    "sg:postcode":"77024",
    "sg:province":"TX",
    "sg:tags":[
        "glass"
    ],
    "wof:name":"Soldier Auto Glass",
    "wof:placetype":"venue"
},
  "geometry": {"coordinates":[-95.56083099999999,29.771522],"type":"Point"}
}