{
  "type": "Feature",
  "properties": {
    "iso:country":"US",
    "sg:address":"500 E Pierce St",
    "sg:city":"Luling",
    "sg:classifiers":[
        {
            "category":"Manufacturing",
            "subcategory":"Metals",
            "type":"Manufacturing & Wholesale Goods"
        }
    ],
    "sg:phone":"+1 830 875 2401",
    "sg:postcode":"78648",
    "sg:province":"TX",
    "sg:tags":[
        "tool",
        "mfg"
    ],
    "wof:name":"Durol Western Manufacturing Co",
    "wof:placetype":"venue"
},
  "geometry": {"coordinates":[-97.640484,29.679775],"type":"Point"}
}