{
  "type": "Feature",
  "properties": {
    "iso:country":"US",
    "sg:address":"9713 Kerr St",
    "sg:city":"Houston",
    "sg:classifiers":[
        {
            "category":"Manufacturing",
            "subcategory":"Metals",
            "type":"Manufacturing & Wholesale Goods"
        },
        {
            "category":"Retail",
            "subcategory":"Repair Shop",
            "type":"Services"
        }
    ],
    "sg:phone":"+1 713 671 2331",
    "sg:postcode":"77029",
    "sg:province":"TX",
    "sg:tags":[
        "ornamental",
        "work",
        "welding"
    ],
    "wof:name":"G & F Welding Inc",
    "wof:placetype":"venue"
},
  "geometry": {"coordinates":[-95.256815,29.756147],"type":"Point"}
}