{
  "type": "Feature",
  "properties": {
    "iso:country":"US",
    "sg:address":"118 S James St",
    "sg:city":"Spearman",
    "sg:classifiers":[
        {
            "category":"Recreation",
            "type":"Entertainment"
        }
    ],
    "sg:phone":"+1 806 659 3051",
    "sg:postcode":"79081",
    "sg:province":"TX",
    "wof:name":"Black Sky Outfitters Inc",
    "wof:placetype":"venue"
},
  "geometry": {"coordinates":[-101.186243,36.196094],"type":"Point"}
}