{
  "type": "Feature",
  "properties": {
    "iso:country":"US",
    "sg:address":"20060 Sunny Shores Dr",
    "sg:city":"Humble",
    "sg:classifiers":[
        {
            "category":"Real Estate",
            "subcategory":"Real Estate Agent",
            "type":"Services"
        }
    ],
    "sg:phone":"+1 281 812 2258",
    "sg:postcode":"77346",
    "sg:province":"TX",
    "wof:name":"Five Star Realty",
    "wof:placetype":"venue"
},
  "geometry": {"coordinates":[-95.15660099999999,30.010526],"type":"Point"}
}