{
  "type": "Feature",
  "properties": {
    "iso:country":"US",
    "sg:address":"6260 Westpark Dr",
    "sg:city":"Houston",
    "sg:classifiers":[
        {
            "category":"Health Services",
            "subcategory":"Hospital",
            "type":"Services"
        }
    ],
    "sg:phone":"+1 713 995 8889",
    "sg:postcode":"77057",
    "sg:province":"TX",
    "sg:tags":[
        "substance",
        "psychiatric",
        "abuse",
        "center"
    ],
    "wof:name":"Blues Management Inc",
    "wof:placetype":"venue"
},
  "geometry": {"coordinates":[-95.492238,29.723774],"type":"Point"}
}