{
  "type": "Feature",
  "properties": {
    "iso:country":"US",
    "sg:address":"4011 Inwood Rd",
    "sg:city":"Dallas",
    "sg:classifiers":[
        {
            "category":"Education",
            "subcategory":"School",
            "type":"Public Place"
        }
    ],
    "sg:phone":"+1 214 350 2503",
    "sg:postcode":"75209",
    "sg:province":"TX",
    "wof:name":"Schools",
    "wof:placetype":"venue"
},
  "geometry": {"coordinates":[-96.8228,32.835098],"type":"Point"}
}