{
  "type": "Feature",
  "properties": {
    "iso:country":"US",
    "sg:address":"600 S Bell Blvd",
    "sg:city":"Cedar Park",
    "sg:classifiers":[
        {
            "category":"Recreation",
            "subcategory":"Arcade",
            "type":"Entertainment"
        },
        {
            "category":"Arts & Performance",
            "subcategory":"Theater",
            "type":"Entertainment"
        }
    ],
    "sg:phone":"+1 512 259 1305",
    "sg:postcode":"78613",
    "sg:province":"TX",
    "sg:tags":[
        "entertainer",
        "equipment",
        "amusement",
        "business"
    ],
    "sg:website":"www.sock-hop.com",
    "wof:name":"Sock Hop Inflatable Bouncers",
    "wof:placetype":"venue"
},
  "geometry": {"coordinates":[-97.81801299999999,30.502664],"type":"Point"}
}