{
  "type": "Feature",
  "properties": {
    "iso:country":"US",
    "sg:address":"2117 Dicey Rd",
    "sg:city":"Weatherford",
    "sg:classifiers":[
        {
            "category":"Farming",
            "subcategory":"Fish & Marine Products",
            "type":"Manufacturing & Wholesale Goods"
        }
    ],
    "sg:phone":"+1 817 329 1055",
    "sg:postcode":"76085",
    "sg:province":"TX",
    "sg:tags":[
        "management"
    ],
    "wof:name":"Horseshoe Gameroom Inc",
    "wof:placetype":"venue"
},
  "geometry": {"coordinates":[-97.749363,32.765504],"type":"Point"}
}