{
  "type": "Feature",
  "properties": {
    "iso:country":"US",
    "sg:address":"4545 Mossford Dr",
    "sg:city":"Houston",
    "sg:classifiers":[
        {
            "category":"Retail",
            "subcategory":"Auto Repair",
            "type":"Services"
        }
    ],
    "sg:phone":"+1 713 649 5596",
    "sg:postcode":"77087",
    "sg:province":"TX",
    "sg:tags":[
        "recap",
        "truck",
        "tire"
    ],
    "wof:name":"Snider Tire Inc",
    "wof:placetype":"venue"
},
  "geometry": {"coordinates":[-95.318254,29.69812],"type":"Point"}
}