{
  "type": "Feature",
  "properties": {
    "iso:country":"US",
    "sg:address":"520 S Bonner Ave",
    "sg:city":"Tyler",
    "sg:classifiers":[
        {
            "category":"Professional",
            "type":"Services"
        }
    ],
    "sg:phone":"+1 903 597 2703",
    "sg:postcode":"75702",
    "sg:province":"TX",
    "wof:name":"Summerland",
    "wof:placetype":"venue"
},
  "geometry": {"coordinates":[-95.305904,32.34514],"type":"Point"}
}