{
  "type": "Feature",
  "properties": {
    "iso:country":"US",
    "sg:address":"2910 Fort Worth Ave",
    "sg:city":"Dallas",
    "sg:classifiers":[
        {
            "category":"Restaurant",
            "type":"Food & Drink"
        }
    ],
    "sg:phone":"+1 214 333 2150",
    "sg:postcode":"75211",
    "sg:province":"TX",
    "wof:name":"Food Mart & Grill",
    "wof:placetype":"venue"
},
  "geometry": {"coordinates":[-96.86930099999999,32.755901],"type":"Point"}
}