{
  "type": "Feature",
  "properties": {
    "iso:country":"US",
    "sg:address":"423 N Zarzamora",
    "sg:city":"San Antonio",
    "sg:classifiers":[
        {
            "category":"Professional",
            "subcategory":"Lawyer & Legal Services",
            "type":"Services"
        }
    ],
    "sg:phone":"+1 210 432 4303",
    "sg:postcode":"78207",
    "sg:province":"TX",
    "wof:name":"Alvin Braunstein",
    "wof:placetype":"venue"
},
  "geometry": {"coordinates":[-98.526535,29.432042],"type":"Point"}
}