{
  "type": "Feature",
  "properties": {
    "iso:country":"US",
    "sg:address":"3389 Laurel St",
    "sg:city":"Beaumont",
    "sg:classifiers":[
        {
            "category":"Health Services",
            "subcategory":"Doctor",
            "type":"Services"
        }
    ],
    "sg:phone":"+1 409 835 9846",
    "sg:postcode":"77707",
    "sg:province":"TX",
    "wof:name":"Ronald Citrano DDS",
    "wof:placetype":"venue"
},
  "geometry": {"coordinates":[-94.136403,30.082666],"type":"Point"}
}