{
  "type": "Feature",
  "properties": {
    "iso:country":"US",
    "sg:address":"701 W Uvalde St",
    "sg:city":"Crystal City",
    "sg:classifiers":[
        {
            "category":"Building & Trades",
            "subcategory":"Plumbing",
            "type":"Services"
        }
    ],
    "sg:phone":"+1 830 374 5554",
    "sg:postcode":"78839",
    "sg:province":"TX",
    "sg:tags":[
        "conditioning",
        "air",
        "system",
        "contractor"
    ],
    "wof:name":"Cool Comfort",
    "wof:placetype":"venue"
},
  "geometry": {"coordinates":[-99.83560900000001,28.677235],"type":"Point"}
}