{
  "type": "Feature",
  "properties": {
    "iso:country":"US",
    "sg:address":"615 N 5th St",
    "sg:city":"Canadian",
    "sg:classifiers":[
        {
            "category":"Retail",
            "subcategory":"Repair Shop",
            "type":"Services"
        }
    ],
    "sg:phone":"+1 806 323 5598",
    "sg:postcode":"79014",
    "sg:province":"TX",
    "sg:tags":[
        "welding"
    ],
    "wof:name":"Bobs Welding",
    "wof:placetype":"venue"
},
  "geometry": {"coordinates":[-100.377622,35.916907],"type":"Point"}
}