{
  "type": "Feature",
  "properties": {
    "iso:country":"US",
    "sg:address":"3207 58th St",
    "sg:city":"Lubbock",
    "sg:classifiers":[
        {
            "category":"Building & Trades",
            "subcategory":"Landscaping Services",
            "type":"Services"
        }
    ],
    "sg:phone":"+1 806 438 7837",
    "sg:postcode":"79413",
    "sg:province":"TX",
    "sg:tags":[
        "washing",
        "power"
    ],
    "wof:name":"M2 Services",
    "wof:placetype":"venue"
},
  "geometry": {"coordinates":[-101.885569,33.541508],"type":"Point"}
}