{
  "type": "Feature",
  "properties": {
    "iso:country":"US",
    "sg:address":"1309 W Washington St",
    "sg:city":"Stephenville",
    "sg:classifiers":[
        {
            "category":"Communications",
            "subcategory":"Radio Station",
            "type":"Services"
        }
    ],
    "sg:phone":"+1 254 968 5788",
    "sg:postcode":"76401",
    "sg:province":"TX",
    "sg:tags":[
        "broadcast"
    ],
    "wof:name":"377 Broadcasting Inc",
    "wof:placetype":"venue"
},
  "geometry": {"coordinates":[-98.213966,32.214771],"type":"Point"}
}