{
  "type": "Feature",
  "properties": {
    "iso:country":"US",
    "sg:address":"5645 Shallow Creek Dr",
    "sg:city":"Midlothian",
    "sg:classifiers":[
        {
            "category":"Building & Trades",
            "subcategory":"Construction",
            "type":"Services"
        }
    ],
    "sg:phone":"+1 214 212 6252",
    "sg:postcode":"76065",
    "sg:province":"TX",
    "sg:tags":[
        "contractor"
    ],
    "wof:name":"Ark Roofing",
    "wof:placetype":"venue"
},
  "geometry": {"coordinates":[-96.97751,32.422923],"type":"Point"}
}