{
  "type": "Feature",
  "properties": {
    "iso:country":"US",
    "sg:address":"305 NE Loop 820",
    "sg:city":"Hurst",
    "sg:classifiers":[
        {
            "category":"Wholesale",
            "subcategory":"Computers",
            "type":"Manufacturing & Wholesale Goods"
        }
    ],
    "sg:phone":"+1 817 284 0383",
    "sg:postcode":"76053",
    "sg:province":"TX",
    "sg:tags":[
        "equipment",
        "processing",
        "datum"
    ],
    "wof:name":"Storage Tek",
    "wof:placetype":"venue"
},
  "geometry": {"coordinates":[-97.20737800000001,32.815348],"type":"Point"}
}