{
  "type": "Feature",
  "properties": {
    "iso:country":"US",
    "sg:address":"1450 Westheimer Rd",
    "sg:city":"Houston",
    "sg:classifiers":[
        {
            "category":"Retail",
            "subcategory":"Auto Rental",
            "type":"Services"
        }
    ],
    "sg:phone":"+1 281 497 6530",
    "sg:postcode":"77006",
    "sg:province":"TX",
    "sg:tags":[
        "renting",
        "truck",
        "leasing"
    ],
    "wof:name":"Budget Truck Rental",
    "wof:placetype":"venue"
},
  "geometry": {"coordinates":[-95.39649199999999,29.743191],"type":"Point"}
}