{
  "type": "Feature",
  "properties": {
    "iso:country":"US",
    "sg:address":"12010 C F Hawn Fwy",
    "sg:city":"Dallas",
    "sg:classifiers":[
        {
            "category":"Home & Garden",
            "subcategory":"Mobile Homes",
            "type":"Retail Goods"
        }
    ],
    "sg:phone":"+1 972 557 1537",
    "sg:postcode":"75253",
    "sg:province":"TX",
    "wof:name":"Lender's Clearinghouse Inc",
    "wof:placetype":"venue"
},
  "geometry": {"coordinates":[-96.617681,32.683639],"type":"Point"}
}