{
  "type": "Feature",
  "properties": {
    "iso:country":"US",
    "sg:address":"3702 95th St",
    "sg:city":"Lubbock",
    "sg:classifiers":[
        {
            "category":"Professional",
            "subcategory":"Business Services",
            "type":"Services"
        }
    ],
    "sg:phone":"+1 806 799 6577",
    "sg:postcode":"79423",
    "sg:province":"TX",
    "wof:name":"Organic Odor Solutions Inc",
    "wof:placetype":"venue"
},
  "geometry": {"coordinates":[-101.89274500000001,33.508599],"type":"Point"}
}