{
  "type": "Feature",
  "properties": {
    "iso:country":"US",
    "sg:address":"2261 Reagan Blvd",
    "sg:city":"Carrollton",
    "sg:classifiers":[
        {
            "category":"Retail",
            "subcategory":"Repair Shop",
            "type":"Services"
        }
    ],
    "sg:phone":"+1 972 418 5384",
    "sg:postcode":"75006",
    "sg:province":"TX",
    "wof:name":"Framers Touch",
    "wof:placetype":"venue"
},
  "geometry": {"coordinates":[-96.877532,32.950475],"type":"Point"}
}