{
  "type": "Feature",
  "properties": {
    "iso:country":"US",
    "sg:address":"5110 San Felipe St",
    "sg:city":"Houston",
    "sg:classifiers":[
        {
            "category":"Manufacturing",
            "subcategory":"Retail Goods",
            "type":"Manufacturing & Wholesale Goods"
        }
    ],
    "sg:phone":"+1 713 355 7172",
    "sg:postcode":"77056",
    "sg:province":"TX",
    "sg:tags":[
        "product",
        "mfg"
    ],
    "wof:name":"Magnetic Wonders",
    "wof:placetype":"venue"
},
  "geometry": {"coordinates":[-95.464911,29.750228],"type":"Point"}
}