{
  "type": "Feature",
  "properties": {
    "iso:country":"US",
    "sg:address":"14950 Heathrow Forrest Pkwy Ste 140",
    "sg:city":"Houston",
    "sg:classifiers":[
        {
            "category":"Deli",
            "type":"Food & Drink"
        }
    ],
    "sg:phone":"+1 281 590 4230",
    "sg:postcode":"77032",
    "sg:province":"TX",
    "wof:name":"Jung's Deli",
    "wof:placetype":"venue"
},
  "geometry": {"coordinates":[-95.323525,29.93557],"type":"Point"}
}