{
  "type": "Feature",
  "properties": {
    "iso:country":"US",
    "sg:address":"1801 Kokomo St",
    "sg:city":"Plainview",
    "sg:classifiers":[
        {
            "category":"Personal",
            "type":"Services"
        },
        {
            "category":"Professional",
            "subcategory":"Art Services",
            "type":"Services"
        }
    ],
    "sg:phone":"+1 806 296 5047",
    "sg:postcode":"79072",
    "sg:province":"TX",
    "sg:tags":[
        "photography",
        "videography",
        "wedding"
    ],
    "wof:name":"G C Photography",
    "wof:placetype":"venue"
},
  "geometry": {"coordinates":[-101.717178,34.199558],"type":"Point"}
}