{
  "type": "Feature",
  "properties": {
    "iso:country":"US",
    "sg:address":"1700 W Parmer Ln",
    "sg:city":"Austin",
    "sg:classifiers":[
        {
            "category":"Shopping",
            "type":"Retail Goods"
        }
    ],
    "sg:phone":"+1 512 832 0001",
    "sg:postcode":"78727",
    "sg:province":"TX",
    "sg:tags":[
        "telephone",
        "cellular"
    ],
    "wof:name":"One Source Wireless",
    "wof:placetype":"venue"
},
  "geometry": {"coordinates":[-97.687698,30.411865],"type":"Point"}
}