{
  "type": "Feature",
  "properties": {
    "iso:country":"US",
    "sg:address":"3829 US Hwy 77",
    "sg:city":"Corpus Christi",
    "sg:classifiers":[
        {
            "category":"Professional",
            "subcategory":"Accounting & Tax Preparation",
            "type":"Services"
        }
    ],
    "sg:phone":"+1 361 767 4231",
    "sg:postcode":"78410",
    "sg:province":"TX",
    "sg:tags":[
        "return",
        "filing"
    ],
    "wof:name":"Jackson Hewitt Tax Svc",
    "wof:placetype":"venue"
},
  "geometry": {"coordinates":[-97.630567,27.855468],"type":"Point"}
}