{
  "type": "Feature",
  "properties": {
    "iso:country":"US",
    "sg:address":"116 Oak Knoll Cir",
    "sg:city":"Boerne",
    "sg:classifiers":[
        {
            "category":"Home & Garden",
            "subcategory":"Building Materials",
            "type":"Retail Goods"
        }
    ],
    "sg:phone":"+1 830 249 5410",
    "sg:postcode":"78006",
    "sg:province":"TX",
    "wof:name":"Apache 2 Metal Buildings",
    "wof:placetype":"venue"
},
  "geometry": {"coordinates":[-98.714933,29.802783],"type":"Point"}
}