{
  "type": "Feature",
  "properties": {
    "iso:country":"US",
    "sg:address":"920 Frostwood Dr",
    "sg:city":"Houston",
    "sg:classifiers":[
        {
            "category":"Health Services",
            "subcategory":"Doctor",
            "type":"Services"
        },
        {
            "category":"Health Services",
            "subcategory":"Hospital",
            "type":"Services"
        }
    ],
    "sg:phone":"+1 713 932 3000",
    "sg:postcode":"77024",
    "sg:province":"TX",
    "wof:name":"Sherman Neil E MD",
    "wof:placetype":"venue"
},
  "geometry": {"coordinates":[-95.545306,29.78101],"type":"Point"}
}