{
  "type": "Feature",
  "properties": {
    "iso:country":"US",
    "sg:address":"1230 Division Ave",
    "sg:city":"San Antonio",
    "sg:classifiers":[
        {
            "category":"Organizations",
            "subcategory":"Religious Organization",
            "type":"Services"
        }
    ],
    "sg:phone":"+1 210 922 7549",
    "sg:postcode":"78225",
    "sg:province":"TX",
    "sg:tags":[
        "church"
    ],
    "wof:name":"Genesis Church",
    "wof:placetype":"venue"
},
  "geometry": {"coordinates":[-98.52588299999999,29.379377],"type":"Point"}
}