{
  "type": "Feature",
  "properties": {
    "iso:country":"US",
    "sg:address":"421 Rustic Ridge Dr",
    "sg:city":"Garland",
    "sg:classifiers":[
        {
            "category":"Real Estate",
            "subcategory":"Real Estate Agent",
            "type":"Services"
        }
    ],
    "sg:phone":"+1 972 495 1393",
    "sg:postcode":"75040",
    "sg:province":"TX",
    "wof:name":"Tobe Enterprises Inc",
    "wof:placetype":"venue"
},
  "geometry": {"coordinates":[-96.634961,32.946585],"type":"Point"}
}