{
  "type": "Feature",
  "properties": {
    "iso:country":"US",
    "sg:address":"2405 W Waco Dr",
    "sg:city":"Waco",
    "sg:classifiers":[
        {
            "category":"Insurance",
            "subcategory":"Hazard Insurance",
            "type":"Services"
        }
    ],
    "sg:phone":"+1 254 752 4040",
    "sg:postcode":"76707",
    "sg:province":"TX",
    "sg:website":"http://www.texasinsconnection.com",
    "wof:name":"1 Stop Financial Service Centers",
    "wof:placetype":"venue"
},
  "geometry": {"coordinates":[-97.152247,31.543903],"type":"Point"}
}