{
  "type": "Feature",
  "properties": {
    "iso:country":"US",
    "sg:address":"1924 Ave Durango",
    "sg:city":"Laredo",
    "sg:classifiers":[
        {
            "category":"Health Services",
            "subcategory":"Clinic",
            "type":"Services"
        }
    ],
    "sg:phone":"+1 956 286 9311",
    "sg:postcode":"78046",
    "sg:province":"TX",
    "sg:tags":[
        "agency",
        "welfare"
    ],
    "wof:name":"Precious Garden Primary Care",
    "wof:placetype":"venue"
},
  "geometry": {"coordinates":[-99.45281900000001,27.479278],"type":"Point"}
}