{
  "type": "Feature",
  "properties": {
    "iso:country":"US",
    "sg:address":"12275 FM 1097 W",
    "sg:city":"Willis",
    "sg:classifiers":[
        {
            "category":"Mining & Drilling",
            "type":"Manufacturing & Wholesale Goods"
        }
    ],
    "sg:phone":"+1 936 582 1308",
    "sg:postcode":"77318",
    "sg:province":"TX",
    "sg:tags":[
        "development",
        "gas",
        "oil",
        "exploration"
    ],
    "wof:name":"Fortune Exploration-Kentucky",
    "wof:placetype":"venue"
},
  "geometry": {"coordinates":[-95.541212,30.426486],"type":"Point"}
}