{
  "type": "Feature",
  "properties": {
    "iso:country":"US",
    "sg:address":"11869 Rosser Rd",
    "sg:city":"Dallas",
    "sg:classifiers":[
        {
            "category":"Wholesale",
            "subcategory":"Furniture",
            "type":"Manufacturing & Wholesale Goods"
        }
    ],
    "sg:phone":"+1 972 620 2259",
    "sg:postcode":"75244",
    "sg:province":"TX",
    "sg:tags":[
        "construction"
    ],
    "wof:name":"Rabbit Wood",
    "wof:placetype":"venue"
},
  "geometry": {"coordinates":[-96.84595299999999,32.91209],"type":"Point"}
}