{
  "type": "Feature",
  "properties": {
    "iso:country":"US",
    "sg:address":"2813 Erie Dr",
    "sg:city":"Corpus Christi",
    "sg:classifiers":[
        {
            "category":"Building & Trades",
            "subcategory":"Landscaping Services",
            "type":"Services"
        }
    ],
    "sg:phone":"+1 361 992 0510",
    "sg:postcode":"78414",
    "sg:province":"TX",
    "wof:name":"Jims Lawn Works",
    "wof:placetype":"venue"
},
  "geometry": {"coordinates":[-97.35008999999999,27.670186],"type":"Point"}
}