{
  "type": "Feature",
  "properties": {
    "iso:country":"US",
    "sg:address":"7310 Santa Fe Dr",
    "sg:city":"Houston",
    "sg:classifiers":[
        {
            "category":"Professional",
            "type":"Services"
        }
    ],
    "sg:phone":"+1 713 645 8506",
    "sg:postcode":"77061",
    "sg:province":"TX",
    "wof:name":"Ramos Yard Service",
    "wof:placetype":"venue"
},
  "geometry": {"coordinates":[-95.298682,29.663437],"type":"Point"}
}