{
  "type": "Feature",
  "properties": {
    "iso:country":"US",
    "sg:address":"501 N Main St",
    "sg:city":"Taylor",
    "sg:classifiers":[
        {
            "category":"Autos & Motor Vehicles",
            "subcategory":"Fuel & Gas Station",
            "type":"Retail Goods"
        }
    ],
    "sg:phone":"+1 512 352 5350",
    "sg:postcode":"76574",
    "sg:province":"TX",
    "sg:tags":[
        "oil"
    ],
    "wof:name":"Shell Main Street Car Wash",
    "wof:placetype":"venue"
},
  "geometry": {"coordinates":[-97.40988900000001,30.572557],"type":"Point"}
}