{
  "type": "Feature",
  "properties": {
    "iso:country":"US",
    "sg:address":"12963 Pine Cone Dr",
    "sg:city":"Tyler",
    "sg:classifiers":[
        {
            "category":"Professional",
            "type":"Services"
        }
    ],
    "sg:phone":"+1 903 592 5592",
    "sg:postcode":"75704",
    "sg:province":"TX",
    "wof:name":"Kelly Bell",
    "wof:placetype":"venue"
},
  "geometry": {"coordinates":[-95.38341,32.352327],"type":"Point"}
}