{
  "type": "Feature",
  "properties": {
    "iso:country":"US",
    "sg:address":"820 S Macarthur Blvd",
    "sg:city":"Coppell",
    "sg:phone":"+1 972 393 3933",
    "sg:postcode":"75019",
    "sg:province":"TX",
    "sg:website":"http://www.pizzahut.com",
    "wof:name":"Pizza Hut",
    "wof:placetype":"venue"
},
  "geometry": {"coordinates":[-96.95784,32.951291],"type":"Point"}
}