{
  "type": "Feature",
  "properties": {
    "iso:country":"US",
    "sg:address":"1414 E Blanco Rd",
    "sg:city":"Boerne",
    "sg:classifiers":[
        {
            "category":"Professional",
            "subcategory":"Advertising",
            "type":"Services"
        }
    ],
    "sg:phone":"+1 830 336 2553",
    "sg:postcode":"78006",
    "sg:province":"TX",
    "sg:tags":[
        "counselor",
        "agency"
    ],
    "sg:website":"www.rudkinproductions.com",
    "wof:name":"Rudkin Productions LLC",
    "wof:placetype":"venue"
},
  "geometry": {"coordinates":[-98.715198,29.797561],"type":"Point"}
}