{
  "type": "Feature",
  "properties": {
    "iso:country":"US",
    "sg:address":"2124 Texoma Pkwy",
    "sg:city":"Sherman",
    "sg:classifiers":[
        {
            "category":"Restaurant",
            "type":"Food & Drink"
        }
    ],
    "sg:phone":"+1 903 892 1644",
    "sg:postcode":"75090",
    "sg:province":"TX",
    "sg:tags":[
        "mexican"
    ],
    "sg:website":"http://www.shermanlamesa.com",
    "wof:name":"La Mesa Mexican Restaurant",
    "wof:placetype":"venue"
},
  "geometry": {"coordinates":[-96.600218,33.660289],"type":"Point"}
}