{
  "type": "Feature",
  "properties": {
    "iso:country":"US",
    "sg:address":"6500 Northwest Dr Ste 350",
    "sg:city":"Mesquite",
    "sg:classifiers":[
        {
            "category":"Health Services",
            "subcategory":"Optometrist",
            "type":"Services"
        }
    ],
    "sg:phone":"+1 972 686 2500",
    "sg:postcode":"75150",
    "sg:province":"TX",
    "sg:website":"www.primeeyecare.com",
    "wof:name":"PRIME EYE CARE",
    "wof:placetype":"venue"
},
  "geometry": {"coordinates":[-96.62922500000001,32.846678],"type":"Point"}
}