{
  "type": "Feature",
  "properties": {
    "iso:country":"US",
    "sg:address":"8407 Vaquero Cove",
    "sg:city":"Austin",
    "sg:classifiers":[
        {
            "category":"Professional",
            "subcategory":"Business Services",
            "type":"Services"
        }
    ],
    "sg:phone":"+1 512 335 5659",
    "sg:postcode":"78759",
    "sg:province":"TX",
    "wof:name":"Marie James & Company",
    "wof:placetype":"venue"
},
  "geometry": {"coordinates":[-97.789728,30.418468],"type":"Point"}
}