{
  "type": "Feature",
  "properties": {
    "iso:country":"US",
    "sg:address":"1701 E Pioneer Dr",
    "sg:city":"Irving",
    "sg:classifiers":[
        {
            "category":"Wholesale",
            "subcategory":"Construction Materials",
            "type":"Manufacturing & Wholesale Goods"
        }
    ],
    "sg:phone":"+1 972 438 7447",
    "sg:postcode":"75061",
    "sg:province":"TX",
    "sg:tags":[
        "drywall"
    ],
    "wof:name":"Twa",
    "wof:placetype":"venue"
},
  "geometry": {"coordinates":[-96.92306000000001,32.817624],"type":"Point"}
}