{
  "type": "Feature",
  "properties": {
    "iso:country":"US",
    "sg:address":"2815 Gaston Ave",
    "sg:city":"Dallas",
    "sg:classifiers":[
        {
            "category":"Organizations",
            "subcategory":"Non-profit Organization",
            "type":"Services"
        }
    ],
    "sg:phone":"+1 214 827 8961",
    "sg:postcode":"75226",
    "sg:province":"TX",
    "sg:tags":[
        "information",
        "abuse",
        "treatment",
        "child"
    ],
    "wof:name":"Dallas Casa",
    "wof:placetype":"venue"
},
  "geometry": {"coordinates":[-96.785104,32.787359],"type":"Point"}
}