{
  "type": "Feature",
  "properties": {
    "iso:country":"US",
    "sg:address":"7004 Oakfield Corner Ct",
    "sg:city":"Fort Worth",
    "sg:classifiers":[
        {
            "category":"Building & Trades",
            "subcategory":"Cleaning & Sanitation",
            "type":"Services"
        }
    ],
    "sg:phone":"+1 817 656 4396",
    "sg:postcode":"76180",
    "sg:province":"TX",
    "sg:tags":[
        "maintenance"
    ],
    "wof:name":"Maid To Clean",
    "wof:placetype":"venue"
},
  "geometry": {"coordinates":[-97.228701,32.883192],"type":"Point"}
}