{
  "type": "Feature",
  "properties": {
    "iso:country":"US",
    "sg:address":"2527 Royal Ln",
    "sg:city":"Dallas",
    "sg:classifiers":[
        {
            "category":"Wholesale",
            "subcategory":"Apparel",
            "type":"Manufacturing & Wholesale Goods"
        }
    ],
    "sg:phone":"+1 972 488 9694",
    "sg:postcode":"75229",
    "sg:province":"TX",
    "wof:name":"Encore Bayahada Inc",
    "wof:placetype":"venue"
},
  "geometry": {"coordinates":[-96.893091,32.896187],"type":"Point"}
}