{
  "type": "Feature",
  "properties": {
    "iso:country":"US",
    "sg:address":"214 Hillcrest Dr",
    "sg:city":"Hico",
    "sg:classifiers":[
        {
            "category":"Personal",
            "subcategory":"Barber",
            "type":"Services"
        }
    ],
    "sg:phone":"+1 254 796 4649",
    "sg:postcode":"76457",
    "sg:province":"TX",
    "sg:tags":[
        "shop"
    ],
    "wof:name":"Barber Pole",
    "wof:placetype":"venue"
},
  "geometry": {"coordinates":[-98.022786,31.982524],"type":"Point"}
}