{
  "type": "Feature",
  "properties": {
    "iso:country":"US",
    "sg:address":"5501 S I H 35",
    "sg:city":"Austin",
    "sg:classifiers":[
        {
            "category":"Cinema",
            "subcategory":"Movie Theater",
            "type":"Entertainment"
        }
    ],
    "sg:phone":"+1 512 326 3800",
    "sg:postcode":"78744",
    "sg:province":"TX",
    "wof:name":"Tinseltown USA",
    "wof:placetype":"venue"
},
  "geometry": {"coordinates":[-97.76159699999999,30.200701],"type":"Point"}
}