{
  "type": "Feature",
  "properties": {
    "iso:country":"US",
    "sg:address":"3620 E Whitestone Blvd",
    "sg:city":"Cedar Park",
    "sg:classifiers":[
        {
            "category":"Autos & Motor Vehicles",
            "subcategory":"Automobile Sales",
            "type":"Retail Goods"
        },
        {
            "category":"Retail",
            "subcategory":"Auto Repair",
            "type":"Services"
        }
    ],
    "sg:phone":"+1 512 259 6600",
    "sg:postcode":"78613",
    "sg:province":"TX",
    "sg:tags":[
        "car"
    ],
    "sg:website":"www.cleobaysuzuki.com",
    "wof:name":"Cleo Bay Suzuki",
    "wof:placetype":"venue"
},
  "geometry": {"coordinates":[-97.775091,30.537609],"type":"Point"}
}