{
  "type": "Feature",
  "properties": {
    "iso:country":"US",
    "sg:address":"6904 Summerhill Rd",
    "sg:city":"Texarkana",
    "sg:classifiers":[
        {
            "category":"Farming",
            "subcategory":"Livestock Farm",
            "type":"Manufacturing & Wholesale Goods"
        }
    ],
    "sg:phone":"+1 903 794 1304",
    "sg:postcode":"75503",
    "sg:province":"TX",
    "sg:tags":[
        "equine"
    ],
    "wof:name":"Sundance Ridge Farm Inc",
    "wof:placetype":"venue"
},
  "geometry": {"coordinates":[-94.07430600000001,33.498191],"type":"Point"}
}