{
  "type": "Feature",
  "properties": {
    "iso:country":"US",
    "sg:address":"1374 Highland Ave",
    "sg:city":"Abilene",
    "sg:classifiers":[
        {
            "category":"Building & Trades",
            "subcategory":"Cleaning & Sanitation",
            "type":"Services"
        }
    ],
    "sg:phone":"+1 325 677 1256",
    "sg:postcode":"79605",
    "sg:province":"TX",
    "sg:tags":[
        "maintenance"
    ],
    "wof:name":"Abilene House Cleaning",
    "wof:placetype":"venue"
},
  "geometry": {"coordinates":[-99.749292,32.432539],"type":"Point"}
}