{
  "type": "Feature",
  "properties": {
    "iso:country":"US",
    "sg:address":"4316 E Washington",
    "sg:city":"Dickinson",
    "sg:classifiers":[
        {
            "category":"Health Services",
            "subcategory":"Clinic",
            "type":"Services"
        },
        {
            "category":"Social Services",
            "subcategory":"Job Training",
            "type":"Services"
        }
    ],
    "sg:phone":"+1 281 337 1343",
    "sg:postcode":"77539",
    "sg:province":"TX",
    "sg:tags":[
        "hospital",
        "rehabilitation",
        "specialty",
        "outpatient"
    ],
    "wof:name":"Bay Area Recovery Center",
    "wof:placetype":"venue"
},
  "geometry": {"coordinates":[-95.05224,29.460007],"type":"Point"}
}