{
  "type": "Feature",
  "properties": {
    "iso:country":"US",
    "sg:address":"17404 Priest River Cove",
    "sg:city":"Round Rock",
    "sg:classifiers":[
        {
            "category":"Social Services",
            "subcategory":"Child Care",
            "type":"Services"
        }
    ],
    "sg:phone":"+1 512 388 1831",
    "sg:postcode":"78681",
    "sg:province":"TX",
    "sg:tags":[
        "day"
    ],
    "wof:name":"Kidz Kastle",
    "wof:placetype":"venue"
},
  "geometry": {"coordinates":[-97.727194,30.512132],"type":"Point"}
}