{
  "type": "Feature",
  "properties": {
    "iso:country":"US",
    "sg:address":"2836 Bill Owens Pkwy",
    "sg:city":"Longview",
    "sg:classifiers":[
        {
            "category":"Professional",
            "subcategory":"Accounting & Tax Preparation",
            "type":"Services"
        }
    ],
    "sg:phone":"+1 903 297 9933",
    "sg:postcode":"75605",
    "sg:province":"TX",
    "wof:name":"Geneos Wealth Management",
    "wof:placetype":"venue"
},
  "geometry": {"coordinates":[-94.768041,32.538273],"type":"Point"}
}