{
  "type": "Feature",
  "properties": {
    "iso:country":"US",
    "sg:address":"7812 Tierwester St",
    "sg:city":"Houston",
    "sg:classifiers":[
        {
            "category":"Real Estate",
            "subcategory":"Real Estate Operator",
            "type":"Services"
        }
    ],
    "sg:phone":"+1 713 741 8069",
    "sg:postcode":"77021",
    "sg:province":"TX",
    "sg:tags":[
        "building",
        "apartment"
    ],
    "wof:name":"Tierwester Village",
    "wof:placetype":"venue"
},
  "geometry": {"coordinates":[-95.372636,29.68144],"type":"Point"}
}