{
  "type": "Feature",
  "properties": {
    "iso:country":"US",
    "sg:address":"1405 Courtney Pl",
    "sg:city":"Cleburne",
    "sg:classifiers":[
        {
            "category":"Shopping",
            "type":"Retail Goods"
        }
    ],
    "sg:phone":"+1 817 558 8425",
    "sg:postcode":"76033",
    "sg:province":"TX",
    "sg:tags":[
        "merchandise"
    ],
    "wof:name":"Tina Lynnette Dawson",
    "wof:placetype":"venue"
},
  "geometry": {"coordinates":[-97.42019999999999,32.362185],"type":"Point"}
}