{
  "type": "Feature",
  "properties": {
    "iso:country":"US",
    "sg:address":"216 Williams Ln",
    "sg:city":"Cedar Creek",
    "sg:classifiers":[
        {
            "category":"Organizations",
            "subcategory":"Labor Organization",
            "type":"Services"
        }
    ],
    "sg:phone":"+1 512 587 4160",
    "sg:postcode":"78612",
    "sg:province":"TX",
    "wof:name":"Local Group",
    "wof:placetype":"venue"
},
  "geometry": {"coordinates":[-97.482713,30.144192],"type":"Point"}
}