{
  "type": "Feature",
  "properties": {
    "iso:country":"US",
    "sg:address":"8259 State Hwy 16",
    "sg:city":"De Leon",
    "sg:classifiers":[
        {
            "category":"Farming",
            "subcategory":"Livestock Farm",
            "type":"Manufacturing & Wholesale Goods"
        }
    ],
    "sg:phone":"+1 254 893 6739",
    "sg:postcode":"76444",
    "sg:province":"TX",
    "sg:tags":[
        "beef",
        "feedlot",
        "cattle"
    ],
    "wof:name":"Keith Moon",
    "wof:placetype":"venue"
},
  "geometry": {"coordinates":[-98.54602,32.035833],"type":"Point"}
}