{
  "type": "Feature",
  "properties": {
    "iso:country":"US",
    "sg:address":"924 S 14th St",
    "sg:city":"Kingsville",
    "sg:classifiers":[
        {
            "category":"Retail",
            "subcategory":"Repair Shop",
            "type":"Services"
        }
    ],
    "sg:phone":"+1 361 592 0226",
    "sg:postcode":"78363",
    "sg:province":"TX",
    "sg:tags":[
        "jewelry"
    ],
    "wof:name":"Kingsville Jewelry & Watch Rpr",
    "wof:placetype":"venue"
},
  "geometry": {"coordinates":[-97.855937,27.50851],"type":"Point"}
}