{
  "type": "Feature",
  "properties": {
    "iso:country":"US",
    "sg:address":"9112 Lanham St",
    "sg:city":"Fort Worth",
    "sg:classifiers":[
        {
            "category":"Retail",
            "subcategory":"Repair Shop",
            "type":"Services"
        }
    ],
    "sg:phone":"+1 817 246 2987",
    "sg:postcode":"76108",
    "sg:province":"TX",
    "wof:name":"Galaxy Orbital Cleaning",
    "wof:placetype":"venue"
},
  "geometry": {"coordinates":[-97.473038,32.761464],"type":"Point"}
}