{
  "type": "Feature",
  "properties": {
    "iso:country":"US",
    "sg:address":"3950 Carter Rd",
    "sg:city":"Vidor",
    "sg:classifiers":[
        {
            "category":"Recreation",
            "subcategory":"Fishing",
            "type":"Entertainment"
        }
    ],
    "sg:phone":"+1 409 786 2045",
    "sg:postcode":"77662",
    "sg:province":"TX",
    "sg:tags":[
        "tackle-wholesale",
        "manufacturer"
    ],
    "wof:name":"Pirate Lure Co",
    "wof:placetype":"venue"
},
  "geometry": {"coordinates":[-94.043142,30.186741],"type":"Point"}
}