{
  "type": "Feature",
  "properties": {
    "iso:country":"US",
    "sg:address":"7030 Winchester St",
    "sg:city":"Dallas",
    "sg:classifiers":[
        {
            "category":"Retail",
            "subcategory":"Laundry & Dry Cleaning",
            "type":"Services"
        }
    ],
    "sg:phone":"+1 214 340 5911",
    "sg:postcode":"75231",
    "sg:province":"TX",
    "sg:tags":[
        "carpet"
    ],
    "wof:name":"Genie Carpet Services",
    "wof:placetype":"venue"
},
  "geometry": {"coordinates":[-96.74099699999999,32.862099],"type":"Point"}
}