{
  "type": "Feature",
  "properties": {
    "iso:country":"US",
    "sg:address":"3980 Bluebonnet Dr",
    "sg:city":"Stafford",
    "sg:classifiers":[
        {
            "category":"Professional",
            "type":"Services"
        }
    ],
    "sg:phone":"+1 281 242 2941",
    "sg:postcode":"77477",
    "sg:province":"TX",
    "wof:name":"Enyong Godwin",
    "wof:placetype":"venue"
},
  "geometry": {"coordinates":[-95.569416,29.635966],"type":"Point"}
}