{
  "type": "Feature",
  "properties": {
    "iso:country":"US",
    "sg:address":"7311 Galveston Rd",
    "sg:city":"Houston",
    "sg:classifiers":[
        {
            "category":"Wholesale",
            "subcategory":"Machinery & Supplies",
            "type":"Manufacturing & Wholesale Goods"
        }
    ],
    "sg:phone":"+1 713 378 4111",
    "sg:postcode":"77034",
    "sg:province":"TX",
    "sg:tags":[
        "valve"
    ],
    "wof:name":"Global Distribution",
    "wof:placetype":"venue"
},
  "geometry": {"coordinates":[-95.223753,29.650707],"type":"Point"}
}