{
  "type": "Feature",
  "properties": {
    "iso:country":"US",
    "sg:address":"117 N Industrial Hwy",
    "sg:city":"Perryton",
    "sg:classifiers":[
        {
            "category":"Farming",
            "subcategory":"Farm",
            "type":"Manufacturing & Wholesale Goods"
        }
    ],
    "sg:phone":"+1 806 435 2356",
    "sg:postcode":"79070",
    "sg:province":"TX",
    "sg:tags":[
        "crop",
        "general"
    ],
    "wof:name":"Texas Farm Inc",
    "wof:placetype":"venue"
},
  "geometry": {"coordinates":[-100.79168,36.40143],"type":"Point"}
}