{
  "type": "Feature",
  "properties": {
    "iso:country":"US",
    "sg:address":"323 Montfort Dr",
    "sg:city":"San Antonio",
    "sg:classifiers":[
        {
            "category":"Professional",
            "subcategory":"Management & Consulting",
            "type":"Services"
        }
    ],
    "sg:phone":"+1 210 344 6167",
    "sg:postcode":"78216",
    "sg:province":"TX",
    "sg:tags":[
        "support",
        "facility"
    ],
    "wof:name":"Stroke Support Group",
    "wof:placetype":"venue"
},
  "geometry": {"coordinates":[-98.50617699999999,29.513458],"type":"Point"}
}