{
  "type": "Feature",
  "properties": {
    "iso:country":"US",
    "sg:address":"332 Texas St",
    "sg:city":"Cedar Hill",
    "sg:classifiers":[
        {
            "category":"Organizations",
            "subcategory":"Religious Organization",
            "type":"Services"
        }
    ],
    "sg:phone":"+1 972 291 7858",
    "sg:postcode":"75104",
    "sg:province":"TX",
    "wof:name":"New Life Apostolic UPC",
    "wof:placetype":"venue"
},
  "geometry": {"coordinates":[-96.953779,32.587846],"type":"Point"}
}