{
  "type": "Feature",
  "properties": {
    "iso:country":"US",
    "sg:address":"1510 Rainbow Bend",
    "sg:city":"Austin",
    "sg:classifiers":[
        {
            "category":"Professional",
            "type":"Services"
        }
    ],
    "sg:phone":"+1 512 476 1855",
    "sg:postcode":"78703",
    "sg:province":"TX",
    "wof:name":"Its About Water",
    "wof:placetype":"venue"
},
  "geometry": {"coordinates":[-97.756339,30.286002],"type":"Point"}
}