{
  "type": "Feature",
  "properties": {
    "iso:country":"US",
    "sg:address":"4515 San Bernardo Ave",
    "sg:city":"Laredo",
    "sg:classifiers":[
        {
            "category":"Professional",
            "type":"Services"
        }
    ],
    "sg:phone":"+1 956 725 4701",
    "sg:postcode":"78041",
    "sg:province":"TX",
    "sg:tags":[
        "establishment"
    ],
    "wof:name":"Epl Azteca Sacv",
    "wof:placetype":"venue"
},
  "geometry": {"coordinates":[-99.504248,27.540356],"type":"Point"}
}