{
  "type": "Feature",
  "properties": {
    "iso:country":"US",
    "sg:address":"224 W Holmes Ave",
    "sg:city":"Bronte",
    "sg:classifiers":[
        {
            "category":"Organizations",
            "subcategory":"Religious Organization",
            "type":"Services"
        }
    ],
    "sg:phone":"+1 325 473 3281",
    "sg:postcode":"76933",
    "sg:province":"TX",
    "sg:tags":[
        "church"
    ],
    "wof:name":"First United Methodist Church",
    "wof:placetype":"venue"
},
  "geometry": {"coordinates":[-100.293837,31.884556],"type":"Point"}
}