{
  "type": "Feature",
  "properties": {
    "iso:country":"US",
    "sg:address":"15823 Brookford Dr",
    "sg:city":"Houston",
    "sg:classifiers":[
        {
            "category":"Professional",
            "type":"Services"
        }
    ],
    "sg:phone":"+1 281 486 9286",
    "sg:postcode":"77059",
    "sg:province":"TX",
    "wof:name":"Dual Resources Inc",
    "wof:placetype":"venue"
},
  "geometry": {"coordinates":[-95.11878900000001,29.596186],"type":"Point"}
}