{
  "type": "Feature",
  "properties": {
    "iso:country":"US",
    "sg:address":"7607 Fernbrook Ln",
    "sg:city":"Houston",
    "sg:classifiers":[
        {
            "category":"Manufacturing",
            "subcategory":"Printing",
            "type":"Manufacturing & Wholesale Goods"
        }
    ],
    "sg:phone":"+1 281 970 5377",
    "sg:postcode":"77070",
    "sg:province":"TX",
    "sg:tags":[
        "publishing"
    ],
    "wof:name":"New Image Consultants",
    "wof:placetype":"venue"
},
  "geometry": {"coordinates":[-95.550102,29.981879],"type":"Point"}
}