{
  "type": "Feature",
  "properties": {
    "iso:country":"US",
    "sg:address":"3207 Wurzbach Rd",
    "sg:city":"San Antonio",
    "sg:classifiers":[
        {
            "category":"Personal",
            "subcategory":"Beauty Salon",
            "type":"Services"
        }
    ],
    "sg:phone":"+1 210 521 7309",
    "sg:postcode":"78238",
    "sg:province":"TX",
    "sg:tags":[
        "shop",
        "manicuring"
    ],
    "wof:name":"Beauty Nails",
    "wof:placetype":"venue"
},
  "geometry": {"coordinates":[-98.623216,29.466707],"type":"Point"}
}