{
  "type": "Feature",
  "properties": {
    "iso:country":"US",
    "sg:address":"1010 W 8th Ave",
    "sg:city":"Amarillo",
    "sg:classifiers":[
        {
            "category":"Home & Garden",
            "subcategory":"Household Appliances",
            "type":"Retail Goods"
        }
    ],
    "sg:phone":"+1 806 374 4441",
    "sg:postcode":"79101",
    "sg:province":"AR",
    "sg:tags":[
        "electronics",
        "consumer"
    ],
    "wof:name":"Bgt Productions",
    "wof:placetype":"venue"
},
  "geometry": {"coordinates":[-101.850556,35.207364],"type":"Point"}
}