{
  "type": "Feature",
  "properties": {
    "iso:country":"US",
    "sg:address":"1200 Ave C",
    "sg:city":"Del Rio",
    "sg:classifiers":[
        {
            "category":"Health Services",
            "subcategory":"Health Practitioner",
            "type":"Services"
        }
    ],
    "sg:phone":"+1 830 774 2121",
    "sg:postcode":"78840",
    "sg:province":"TX",
    "sg:tags":[
        "nurse",
        "registry"
    ],
    "wof:name":"Chartwell Community Services",
    "wof:placetype":"venue"
},
  "geometry": {"coordinates":[-100.90567900000001,29.374831],"type":"Point"}
}