{
  "type": "Feature",
  "properties": {
    "iso:country":"US",
    "sg:address":"4306 N General Bruce Dr",
    "sg:city":"Temple",
    "sg:classifiers":[
        {
            "category":"Food & Beverages",
            "subcategory":"Groceries & Convenience Stores",
            "type":"Retail Goods"
        }
    ],
    "sg:phone":"+1 254 771 0706",
    "sg:postcode":"76501",
    "sg:province":"TX",
    "wof:name":"Diamond Shamrock",
    "wof:placetype":"venue"
},
  "geometry": {"coordinates":[-97.32941099999999,31.141342],"type":"Point"}
}