{
  "type": "Feature",
  "properties": {
    "iso:country":"US",
    "sg:address":"6142 Montana Ave",
    "sg:city":"El Paso",
    "sg:classifiers":[
        {
            "category":"Shopping",
            "subcategory":"Used Merchandise",
            "type":"Retail Goods"
        }
    ],
    "sg:phone":"+1 915 778 7296",
    "sg:postcode":"79925",
    "sg:province":"TX",
    "sg:tags":[
        "pawnbroker"
    ],
    "wof:name":"Benny's Pawn Shop",
    "wof:placetype":"venue"
},
  "geometry": {"coordinates":[-106.412392,31.785781],"type":"Point"}
}