{
  "type": "Feature",
  "properties": {
    "iso:country":"US",
    "sg:address":"13511 Decker Dr",
    "sg:city":"Magnolia",
    "sg:classifiers":[
        {
            "category":"Building & Trades",
            "subcategory":"Pest Control",
            "type":"Services"
        }
    ],
    "sg:phone":"+1 281 356 3325",
    "sg:postcode":"77355",
    "sg:province":"TX",
    "wof:name":"Nichols Pest Control",
    "wof:placetype":"venue"
},
  "geometry": {"coordinates":[-95.676214,30.136368],"type":"Point"}
}