{
  "type": "Feature",
  "properties": {
    "iso:country":"US",
    "sg:address":"808 W 16th Ave",
    "sg:city":"Amarillo",
    "sg:classifiers":[
        {
            "category":"Food & Beverages",
            "subcategory":"Liquor & Beverages",
            "type":"Retail Goods"
        }
    ],
    "sg:phone":"+1 806 372 7213",
    "sg:postcode":"79101",
    "sg:province":"AR",
    "sg:tags":[
        "alcoholic"
    ],
    "wof:name":"Party Stop Warehouse 1",
    "wof:placetype":"venue"
},
  "geometry": {"coordinates":[-101.848446,35.198566],"type":"Point"}
}