{
  "type": "Feature",
  "properties": {
    "iso:country":"US",
    "sg:address":"1025 Edmondson Dr",
    "sg:city":"Irving",
    "sg:classifiers":[
        {
            "category":"Professional",
            "subcategory":"Lawyer & Legal Services",
            "type":"Services"
        }
    ],
    "sg:phone":"+1 972 438 3303",
    "sg:postcode":"75060",
    "sg:province":"TX",
    "wof:name":"Power Robert Atty",
    "wof:placetype":"venue"
},
  "geometry": {"coordinates":[-96.934898,32.804901],"type":"Point"}
}