{
  "type": "Feature",
  "properties": {
    "iso:country":"US",
    "sg:address":"101 Whitewood St",
    "sg:city":"San Antonio",
    "sg:classifiers":[
        {
            "category":"Shopping",
            "subcategory":"Bicycles & Sporting Goods",
            "type":"Retail Goods"
        }
    ],
    "sg:phone":"+1 210 673 9466",
    "sg:postcode":"78242",
    "sg:province":"TX",
    "wof:name":"Hamby's Darts & Stuff",
    "wof:placetype":"venue"
},
  "geometry": {"coordinates":[-98.60054100000001,29.367649],"type":"Point"}
}