{
  "type": "Feature",
  "properties": {
    "iso:country":"US",
    "sg:address":"727 N Madison Ave",
    "sg:city":"Dallas",
    "sg:classifiers":[
        {
            "category":"Professional",
            "subcategory":"Business Services",
            "type":"Services"
        }
    ],
    "sg:phone":"+1 214 943 1444",
    "sg:postcode":"75208",
    "sg:province":"TX",
    "wof:name":"Global Exim Traders",
    "wof:placetype":"venue"
},
  "geometry": {"coordinates":[-96.826668,32.751827],"type":"Point"}
}