{
  "type": "Feature",
  "properties": {
    "iso:country":"US",
    "sg:address":"304 N Main St",
    "sg:city":"Taylor",
    "sg:classifiers":[
        {
            "category":"Health Services",
            "subcategory":"Doctor",
            "type":"Services"
        }
    ],
    "sg:phone":"+1 512 352 8677",
    "sg:postcode":"76574",
    "sg:province":"TX",
    "wof:name":"Thomas E Foyt Jr DDS PC",
    "wof:placetype":"venue"
},
  "geometry": {"coordinates":[-97.40961900000001,30.570606],"type":"Point"}
}