{
  "type": "Feature",
  "properties": {
    "iso:country":"US",
    "sg:address":"115 Airport Rd",
    "sg:city":"Sulphur Springs",
    "sg:classifiers":[
        {
            "category":"Professional",
            "subcategory":"Management & Consulting",
            "type":"Services"
        }
    ],
    "sg:phone":"+1 903 439 4917",
    "sg:postcode":"75482",
    "sg:province":"TX",
    "sg:tags":[
        "hospital"
    ],
    "wof:name":"Darryl Doughtie Dr Darryl",
    "wof:placetype":"venue"
},
  "geometry": {"coordinates":[-95.600714,33.156419],"type":"Point"}
}