{
  "type": "Feature",
  "properties": {
    "iso:country":"US",
    "sg:address":"1142 W Woodlawn Ave",
    "sg:city":"San Antonio",
    "sg:classifiers":[
        {
            "category":"Professional",
            "subcategory":"Management & Consulting",
            "type":"Services"
        }
    ],
    "sg:phone":"+1 210 734 7849",
    "sg:postcode":"78201",
    "sg:province":"TX",
    "sg:tags":[
        "development",
        "training"
    ],
    "wof:name":"Yolanda Rodriguez-Escobar",
    "wof:placetype":"venue"
},
  "geometry": {"coordinates":[-98.5147,29.452834],"type":"Point"}
}