{
  "type": "Feature",
  "properties": {
    "iso:country":"US",
    "sg:address":"930 E 15th St",
    "sg:city":"Plano",
    "sg:classifiers":[
        {
            "category":"Home & Garden",
            "subcategory":"Hardware",
            "type":"Retail Goods"
        }
    ],
    "sg:phone":"+1 972 423 2512",
    "sg:postcode":"75074",
    "sg:province":"TX",
    "wof:name":"Plano Lumber & Hardware Co",
    "wof:placetype":"venue"
},
  "geometry": {"coordinates":[-96.700913,33.019656],"type":"Point"}
}