{
  "type": "Feature",
  "properties": {
    "iso:country":"US",
    "sg:address":"808 W Rice St",
    "sg:city":"Falfurrias",
    "sg:classifiers":[
        {
            "category":"Wholesale",
            "subcategory":"Machinery & Supplies",
            "type":"Manufacturing & Wholesale Goods"
        }
    ],
    "sg:phone":"+1 361 325 5656",
    "sg:postcode":"78355",
    "sg:province":"TX",
    "sg:tags":[
        "tractor"
    ],
    "wof:name":"Farm & Ranch Ctr",
    "wof:placetype":"venue"
},
  "geometry": {"coordinates":[-98.156999,27.228005],"type":"Point"}
}