{
  "type": "Feature",
  "properties": {
    "iso:country":"US",
    "sg:address":"412 Kentucky St",
    "sg:city":"Liberty",
    "sg:classifiers":[
        {
            "category":"Professional",
            "subcategory":"Detective & Security Services",
            "type":"Services"
        }
    ],
    "sg:phone":"+1 936 334 8300",
    "sg:postcode":"77575",
    "sg:province":"TX",
    "sg:tags":[
        "guard",
        "patrol",
        "private",
        "investigator"
    ],
    "wof:name":"Best Spi Security & Investigations",
    "wof:placetype":"venue"
},
  "geometry": {"coordinates":[-94.78970099999999,30.059997],"type":"Point"}
}