{
  "type": "Feature",
  "properties": {
    "iso:country":"US",
    "sg:address":"2860 W Washington St",
    "sg:city":"Stephenville",
    "sg:classifiers":[
        {
            "category":"Cafe",
            "type":"Food & Drink"
        }
    ],
    "sg:menulink":"http://www.allmenus.com/tx/stephenville/222144-cotton-patch-cafe/menu/",
    "sg:phone":"+1 254 965 5255",
    "sg:postcode":"76401",
    "sg:province":"TX",
    "sg:tags":[
        "burger",
        "american",
        "salad",
        "soup"
    ],
    "wof:name":"Cotton Patch Cafe",
    "wof:placetype":"venue"
},
  "geometry": {"coordinates":[-98.229285,32.207923],"type":"Point"}
}