{
  "type": "Feature",
  "properties": {
    "iso:country":"US",
    "sg:address":"712 19th St SE",
    "sg:city":"Paris",
    "sg:classifiers":[
        {
            "category":"Real Estate",
            "subcategory":"Real Estate Agent",
            "type":"Services"
        },
        {
            "category":"Professional",
            "subcategory":"Business Services",
            "type":"Services"
        }
    ],
    "sg:phone":"+1 903 785 0441",
    "sg:postcode":"75460",
    "sg:province":"TX",
    "sg:tags":[
        "appraiser"
    ],
    "wof:name":"Pat Murphy & Associates",
    "wof:placetype":"venue"
},
  "geometry": {"coordinates":[-95.53649900000001,33.65513],"type":"Point"}
}