{
  "type": "Feature",
  "properties": {
    "iso:country":"US",
    "sg:address":"18601 Lyndon B Johnson Fwy",
    "sg:city":"Mesquite",
    "sg:classifiers":[
        {
            "category":"Banks & Credit Unions",
            "subcategory":"Financial Services",
            "type":"Services"
        }
    ],
    "sg:phone":"+1 972 329 6458",
    "sg:postcode":"75150",
    "sg:province":"TX",
    "sg:tags":[
        "broker",
        "mortgage"
    ],
    "wof:name":"Alphabet Mortgage",
    "wof:placetype":"venue"
},
  "geometry": {"coordinates":[-96.628012,32.802534],"type":"Point"}
}