{
  "type": "Feature",
  "properties": {
    "iso:country":"US",
    "sg:address":"2627 Friarwood Trl",
    "sg:city":"Humble",
    "sg:classifiers":[
        {
            "category":"Building & Trades",
            "subcategory":"Construction",
            "type":"Services"
        }
    ],
    "sg:phone":"+1 281 358 0091",
    "sg:postcode":"77339",
    "sg:province":"TX",
    "sg:tags":[
        "carpentry",
        "contractor"
    ],
    "wof:name":"Brian Bates",
    "wof:placetype":"venue"
},
  "geometry": {"coordinates":[-95.20345399999999,30.075285],"type":"Point"}
}