{
  "type": "Feature",
  "properties": {
    "iso:country":"US",
    "sg:address":"812 S Goliad St",
    "sg:city":"Rockwall",
    "sg:classifiers":[
        {
            "category":"Personal",
            "subcategory":"Beauty Salon",
            "type":"Services"
        }
    ],
    "sg:phone":"+1 972 771 0566",
    "sg:postcode":"75087",
    "sg:province":"TX",
    "wof:name":"Imagination Salon & Gifts",
    "wof:placetype":"venue"
},
  "geometry": {"coordinates":[-96.460398,32.922966],"type":"Point"}
}