{
  "type": "Feature",
  "properties": {
    "iso:country":"US",
    "sg:address":"2502 E Travis St",
    "sg:city":"Laredo",
    "sg:classifiers":[
        {
            "category":"Social Services",
            "type":"Services"
        }
    ],
    "sg:phone":"+1 956 712 2442",
    "sg:postcode":"78043",
    "sg:province":"TX",
    "wof:name":"Willow Creek Inc",
    "wof:placetype":"venue"
},
  "geometry": {"coordinates":[-99.47158399999999,27.530015],"type":"Point"}
}