{
  "type": "Feature",
  "properties": {
    "iso:country":"US",
    "sg:address":"1600 E Pioneer Pkwy",
    "sg:city":"Arlington",
    "sg:classifiers":[
        {
            "category":"Organizations",
            "subcategory":"Political Organization",
            "type":"Services"
        }
    ],
    "sg:phone":"+1 817 276 0443",
    "sg:postcode":"76010",
    "sg:province":"TX",
    "wof:name":"Campaign Bill Burch",
    "wof:placetype":"venue"
},
  "geometry": {"coordinates":[-97.088043,32.708098],"type":"Point"}
}