{
  "type": "Feature",
  "properties": {
    "iso:country":"US",
    "sg:address":"6102 Bissonnet St",
    "sg:city":"Houston",
    "sg:classifiers":[
        {
            "category":"Food & Beverages",
            "subcategory":"Meat & Fish",
            "type":"Retail Goods"
        }
    ],
    "sg:phone":"+1 713 777 6393",
    "sg:postcode":"77081",
    "sg:province":"TX",
    "wof:name":"LA Princesa Meat Market",
    "wof:placetype":"venue"
},
  "geometry": {"coordinates":[-95.48965200000001,29.69665],"type":"Point"}
}