{
  "type": "Feature",
  "properties": {
    "iso:country":"US",
    "sg:address":"301 W 3rd St",
    "sg:city":"Lampasas",
    "sg:classifiers":[
        {
            "category":"Museum",
            "type":"Entertainment"
        }
    ],
    "sg:phone":"+1 512 556 2701",
    "sg:postcode":"76550",
    "sg:province":"TX",
    "sg:tags":[
        "place",
        "gallery",
        "historical"
    ],
    "wof:name":"Preservation Lampasas Inc",
    "wof:placetype":"venue"
},
  "geometry": {"coordinates":[-98.184479,31.063999],"type":"Point"}
}