{
  "type": "Feature",
  "properties": {
    "iso:country":"US",
    "sg:address":"7503 Airline Dr",
    "sg:city":"Houston",
    "sg:classifiers":[
        {
            "category":"Shopping",
            "subcategory":"Pawn Shop",
            "type":"Retail Goods"
        }
    ],
    "sg:phone":"+1 713 697 4439",
    "sg:postcode":"77037",
    "sg:province":"TX",
    "sg:website":"www.ezpawn.com",
    "wof:name":"EZ Pawn",
    "wof:placetype":"venue"
},
  "geometry": {"coordinates":[-95.384991,29.870503],"type":"Point"}
}