{
  "type": "Feature",
  "properties": {
    "iso:country":"US",
    "sg:address":"318 S Cage Blvd",
    "sg:city":"Pharr",
    "sg:classifiers":[
        {
            "category":"Shopping",
            "subcategory":"Music",
            "type":"Retail Goods"
        }
    ],
    "sg:phone":"+1 956 787 1387",
    "sg:postcode":"78577",
    "sg:province":"TX",
    "sg:tags":[
        "video",
        "disc",
        "tape",
        "cassette"
    ],
    "wof:name":"All Hit Video",
    "wof:placetype":"venue"
},
  "geometry": {"coordinates":[-98.184659,26.191601],"type":"Point"}
}