{
  "type": "Feature",
  "properties": {
    "iso:country":"US",
    "sg:address":"1510 Kilgore Dr",
    "sg:city":"Henderson",
    "sg:classifiers":[
        {
            "category":"Building & Trades",
            "subcategory":"Construction",
            "type":"Services"
        }
    ],
    "sg:phone":"+1 903 657 7646",
    "sg:postcode":"75652",
    "sg:province":"TX",
    "sg:tags":[
        "painter"
    ],
    "wof:name":"Chuck's Paint & Paper",
    "wof:placetype":"venue"
},
  "geometry": {"coordinates":[-94.80123,32.187375],"type":"Point"}
}