{
  "type": "Feature",
  "properties": {
    "iso:country":"US",
    "sg:address":"7104 N Mesa St",
    "sg:city":"El Paso",
    "sg:classifiers":[
        {
            "category":"Retail",
            "subcategory":"Repair Shop",
            "type":"Services"
        }
    ],
    "sg:phone":"+1 915 584 9223",
    "sg:postcode":"79912",
    "sg:province":"TX",
    "sg:tags":[
        "lock",
        "locksmith"
    ],
    "wof:name":"Saucedo Brothers Inc",
    "wof:placetype":"venue"
},
  "geometry": {"coordinates":[-106.55465,31.836623],"type":"Point"}
}