{
  "type": "Feature",
  "properties": {
    "iso:country":"US",
    "sg:address":"412 W 5th St",
    "sg:city":"Denver City",
    "sg:classifiers":[
        {
            "category":"Government",
            "subcategory":"Office",
            "type":"Public Place"
        }
    ],
    "sg:phone":"+1 806 592 9111",
    "sg:postcode":"79323",
    "sg:province":"TX",
    "sg:tags":[
        "state",
        "resource"
    ],
    "wof:name":"Human Services-Food Stamps",
    "wof:placetype":"venue"
},
  "geometry": {"coordinates":[-102.83394699999999,32.969302],"type":"Point"}
}