{
  "type": "Feature",
  "properties": {
    "iso:country":"US",
    "sg:address":"510 W Wm J Bryan Pkwy",
    "sg:city":"Bryan",
    "sg:classifiers":[
        {
            "category":"Food & Beverages",
            "subcategory":"Meat & Fish",
            "type":"Retail Goods"
        }
    ],
    "sg:phone":"+1 979 823 8624",
    "sg:postcode":"77803",
    "sg:province":"TX",
    "wof:name":"La Perla Tapatia Carniceria",
    "wof:placetype":"venue"
},
  "geometry": {"coordinates":[-96.37805299999999,30.675273],"type":"Point"}
}