{
  "type": "Feature",
  "properties": {
    "iso:country":"US",
    "sg:address":"12044 Duncan Rd",
    "sg:city":"Houston",
    "sg:classifiers":[
        {
            "category":"Utilities",
            "subcategory":"Refuse",
            "type":"Services"
        },
        {
            "category":"Utilities",
            "subcategory":"Recycling",
            "type":"Services"
        }
    ],
    "sg:phone":"+1 281 537 8442",
    "sg:postcode":"77066",
    "sg:province":"TX",
    "sg:tags":[
        "container",
        "dumpster",
        "garbage",
        "hauling",
        "removal",
        "rubbish",
        "trash"
    ],
    "sg:website":"http://www.controlwasteservices.com",
    "wof:name":"Control Waste Services",
    "wof:placetype":"venue"
},
  "geometry": {"coordinates":[-95.51427200000001,29.962804],"type":"Point"}
}