{
  "type": "Feature",
  "properties": {
    "iso:country":"US",
    "sg:address":"1401 Pullman Dr",
    "sg:city":"El Paso",
    "sg:classifiers":[
        {
            "category":"Freight",
            "type":"Transportation"
        }
    ],
    "sg:phone":"+1 915 592 8216",
    "sg:postcode":"79936",
    "sg:province":"TX",
    "sg:tags":[
        "warehouse"
    ],
    "wof:name":"Avon Automotive Distribution",
    "wof:placetype":"venue"
},
  "geometry": {"coordinates":[-106.288262,31.735978],"type":"Point"}
}