{
  "type": "Feature",
  "properties": {
    "iso:country":"US",
    "sg:address":"6607 Autumn Woods Trl",
    "sg:city":"Dallas",
    "sg:classifiers":[
        {
            "category":"Shopping",
            "subcategory":"Used Merchandise",
            "type":"Retail Goods"
        }
    ],
    "sg:phone":"+1 214 374 5884",
    "sg:postcode":"75232",
    "sg:province":"TX",
    "wof:name":"Collectible Designs of Dallas",
    "wof:placetype":"venue"
},
  "geometry": {"coordinates":[-96.83604800000001,32.667084],"type":"Point"}
}