{
  "type": "Feature",
  "properties": {
    "iso:country":"US",
    "sg:address":"633 Santa Fe Dr",
    "sg:city":"Woodway",
    "sg:classifiers":[
        {
            "category":"Home & Garden",
            "subcategory":"Building Materials",
            "type":"Retail Goods"
        },
        {
            "category":"Building & Trades",
            "subcategory":"Construction",
            "type":"Services"
        }
    ],
    "sg:phone":"+1 254 756 0703",
    "sg:postcode":"76712",
    "sg:province":"TX",
    "sg:tags":[
        "altering",
        "concrete",
        "remodeling",
        "staining",
        "contractor"
    ],
    "wof:name":"American Concrete",
    "wof:placetype":"venue"
},
  "geometry": {"coordinates":[-97.210077,31.512825],"type":"Point"}
}