{
  "type": "Feature",
  "properties": {
    "iso:country":"US",
    "sg:address":"2651 Twin Hills Rd",
    "sg:city":"Kempner",
    "sg:classifiers":[
        {
            "category":"Personal",
            "subcategory":"Beauty Salon",
            "type":"Services"
        }
    ],
    "sg:phone":"+1 254 466 3517",
    "sg:postcode":"76539",
    "sg:province":"TX",
    "wof:name":"Ajs Hair",
    "wof:placetype":"venue"
},
  "geometry": {"coordinates":[-97.89625100000001,31.094301],"type":"Point"}
}