{
  "type": "Feature",
  "properties": {
    "iso:country":"US",
    "sg:address":"1605 NW 19th Ave",
    "sg:city":"Amarillo",
    "sg:classifiers":[
        {
            "category":"Freight",
            "type":"Transportation"
        }
    ],
    "sg:phone":"+1 806 374 9524",
    "sg:postcode":"79107",
    "sg:province":"TX",
    "sg:tags":[
        "operator",
        "local",
        "trucking"
    ],
    "wof:name":"Joe King Lawn & Hauling S",
    "wof:placetype":"venue"
},
  "geometry": {"coordinates":[-101.855401,35.233357],"type":"Point"}
}