{
  "type": "Feature",
  "properties": {
    "iso:country":"US",
    "sg:address":"5323 McCullough Ave",
    "sg:city":"San Antonio",
    "sg:classifiers":[
        {
            "category":"Professional",
            "type":"Services"
        },
        {
            "category":"Shopping",
            "subcategory":"Clothing, Apparel, & Fashions",
            "type":"Retail Goods"
        }
    ],
    "sg:phone":"+1 210 829 8776",
    "sg:postcode":"78212",
    "sg:province":"TX",
    "sg:tags":[
        "establishment"
    ],
    "wof:name":"Gracielas Creations",
    "wof:placetype":"venue"
},
  "geometry": {"coordinates":[-98.491783,29.480003],"type":"Point"}
}