{
  "type": "Feature",
  "properties": {
    "iso:country":"US",
    "sg:address":"1209 Missouri St",
    "sg:city":"South Houston",
    "sg:classifiers":[
        {
            "category":"Personal",
            "type":"Services"
        }
    ],
    "sg:phone":"+1 713 944 8200",
    "sg:postcode":"77587",
    "sg:province":"TX",
    "sg:tags":[
        "home"
    ],
    "sg:website":"americanroof.net",
    "wof:name":"American Roofing & Construction",
    "wof:placetype":"venue"
},
  "geometry": {"coordinates":[-95.242143,29.654712],"type":"Point"}
}