{
  "type": "Feature",
  "properties": {
    "iso:country":"US",
    "sg:address":"6927 Amber St",
    "sg:city":"Houston",
    "sg:classifiers":[
        {
            "category":"Retail",
            "subcategory":"Repair Shop",
            "type":"Services"
        }
    ],
    "sg:phone":"+1 713 695 2900",
    "sg:postcode":"77022",
    "sg:province":"TX",
    "sg:tags":[
        "trade",
        "refrigeration",
        "contractor"
    ],
    "wof:name":"4 Seasons AC Htg & Rfrgn",
    "wof:placetype":"venue"
},
  "geometry": {"coordinates":[-95.373716,29.823266],"type":"Point"}
}