{
  "type": "Feature",
  "properties": {
    "iso:country":"US",
    "sg:address":"3329 Singletree Trl",
    "sg:city":"Plano",
    "sg:classifiers":[
        {
            "category":"Banks & Credit Unions",
            "subcategory":"Investment Brokerage",
            "type":"Services"
        }
    ],
    "sg:phone":"+1 972 519 1957",
    "sg:postcode":"75023",
    "sg:province":"TX",
    "sg:tags":[
        "advisory"
    ],
    "wof:name":"Sharkkiss Financial LLC",
    "wof:placetype":"venue"
},
  "geometry": {"coordinates":[-96.758309,33.047539],"type":"Point"}
}