{
  "type": "Feature",
  "properties": {
    "iso:country":"US",
    "sg:address":"1916 SE 1st St",
    "sg:city":"Mineral Wells",
    "sg:classifiers":[
        {
            "category":"Building & Trades",
            "subcategory":"Plumbing",
            "type":"Services"
        }
    ],
    "sg:phone":"+1 940 325 7244",
    "sg:postcode":"76067",
    "sg:province":"TX",
    "sg:tags":[
        "conditioning",
        "air",
        "system",
        "contractor"
    ],
    "wof:name":"Arrow Air Conditioning",
    "wof:placetype":"venue"
},
  "geometry": {"coordinates":[-98.093254,32.808315],"type":"Point"}
}