{
  "type": "Feature",
  "properties": {
    "iso:country":"US",
    "sg:address":"804 S Katherine St",
    "sg:city":"Crane",
    "sg:classifiers":[
        {
            "category":"Building & Trades",
            "subcategory":"Construction",
            "type":"Services"
        }
    ],
    "sg:phone":"+1 432 558 7487",
    "sg:postcode":"79731",
    "sg:province":"TX",
    "sg:tags":[
        "house"
    ],
    "wof:name":"Monty King Construction",
    "wof:placetype":"venue"
},
  "geometry": {"coordinates":[-102.35647899999999,31.39406],"type":"Point"}
}