{
  "type": "Feature",
  "properties": {
    "iso:country":"US",
    "sg:address":"753 Scott St",
    "sg:city":"Tye",
    "sg:classifiers":[
        {
            "category":"Building & Trades",
            "subcategory":"Construction",
            "type":"Services"
        }
    ],
    "sg:phone":"+1 325 692 9514",
    "sg:postcode":"79563",
    "sg:province":"TX",
    "sg:tags":[
        "road",
        "contractor"
    ],
    "wof:name":"Contract Paving Co",
    "wof:placetype":"venue"
},
  "geometry": {"coordinates":[-99.869867,32.448748],"type":"Point"}
}