{
  "type": "Feature",
  "properties": {
    "iso:country":"US",
    "sg:address":"7410 N MacArthur Blvd Ste 105",
    "sg:city":"Irving",
    "sg:classifiers":[
        {
            "category":"Professional",
            "subcategory":"Employment Agencies",
            "type":"Services"
        }
    ],
    "sg:phone":"+1 972 373 8826",
    "sg:postcode":"75063",
    "sg:province":"TX",
    "wof:name":"Trc Staffing",
    "wof:placetype":"venue"
},
  "geometry": {"coordinates":[-96.958603,32.9072],"type":"Point"}
}