{
  "type": "Feature",
  "properties": {
    "iso:country":"US",
    "sg:address":"17 Verde Hills Dr",
    "sg:city":"Center Point",
    "sg:classifiers":[
        {
            "category":"Professional",
            "subcategory":"Computer Services",
            "type":"Services"
        }
    ],
    "sg:phone":"+1 830 634 7414",
    "sg:postcode":"78010",
    "sg:province":"TX",
    "sg:tags":[
        "datum"
    ],
    "wof:name":"Cardinal Office Management",
    "wof:placetype":"venue"
},
  "geometry": {"coordinates":[-99.04977100000001,29.932018],"type":"Point"}
}