{
  "type": "Feature",
  "properties": {
    "iso:country":"US",
    "sg:address":"5800 Wellington Dr",
    "sg:city":"Austin",
    "sg:classifiers":[
        {
            "category":"Real Estate",
            "subcategory":"Real Estate Operator",
            "type":"Services"
        }
    ],
    "sg:phone":"+1 512 926 6886",
    "sg:postcode":"78723",
    "sg:province":"TX",
    "sg:tags":[
        "building",
        "apartment"
    ],
    "wof:name":"Westheimer House Apts",
    "wof:placetype":"venue"
},
  "geometry": {"coordinates":[-97.688062,30.311125],"type":"Point"}
}