{
  "type": "Feature",
  "properties": {
    "iso:country":"US",
    "sg:address":"2725 Valley View Ln",
    "sg:city":"Dallas",
    "sg:classifiers":[
        {
            "category":"Social Services",
            "subcategory":"Child Care",
            "type":"Services"
        },
        {
            "category":"Education",
            "subcategory":"Preschool",
            "type":"Public Place"
        },
        {
            "category":"Education",
            "subcategory":"School",
            "type":"Public Place"
        }
    ],
    "sg:phone":"+1 972 247 3246",
    "sg:postcode":"75234",
    "sg:province":"TX",
    "sg:tags":[
        "elementary",
        "day"
    ],
    "sg:website":"www.hamiltonacademy.com",
    "wof:name":"Hamilton Academy",
    "wof:placetype":"venue"
},
  "geometry": {"coordinates":[-96.887199,32.9245],"type":"Point"}
}