{
  "type": "Feature",
  "properties": {
    "iso:country":"US",
    "sg:address":"11107 Greenwillow St",
    "sg:city":"Houston",
    "sg:classifiers":[
        {
            "category":"Freight",
            "type":"Transportation"
        }
    ],
    "sg:phone":"+1 713 728 2462",
    "sg:postcode":"77035",
    "sg:province":"TX",
    "sg:tags":[
        "operator",
        "local",
        "trucking"
    ],
    "wof:name":"Snead Rd & Son",
    "wof:placetype":"venue"
},
  "geometry": {"coordinates":[-95.448758,29.659274],"type":"Point"}
}