{
  "type": "Feature",
  "properties": {
    "iso:country":"US",
    "sg:address":"436 W Louella Dr",
    "sg:city":"Hurst",
    "sg:classifiers":[
        {
            "category":"Professional",
            "subcategory":"Business Services",
            "type":"Services"
        }
    ],
    "sg:phone":"+1 817 282 4300",
    "sg:postcode":"76054",
    "sg:province":"TX",
    "sg:tags":[
        "tax"
    ],
    "wof:name":"C B Tax Service",
    "wof:placetype":"venue"
},
  "geometry": {"coordinates":[-97.176804,32.846153],"type":"Point"}
}