{
  "type": "Feature",
  "properties": {
    "iso:country":"US",
    "sg:address":"105 W Bourn St",
    "sg:city":"Rockwall",
    "sg:classifiers":[
        {
            "category":"Personal",
            "subcategory":"Beauty Salon",
            "type":"Services"
        }
    ],
    "sg:phone":"+1 469 698 8989",
    "sg:postcode":"75087",
    "sg:province":"TX",
    "sg:website":"http://www.preciouspetsdayspa.com/",
    "wof:name":"Precious Pets Day Spa",
    "wof:placetype":"venue"
},
  "geometry": {"coordinates":[-96.460463,32.921876],"type":"Point"}
}