{
  "type": "Feature",
  "properties": {
    "iso:country":"US",
    "sg:address":"400 S Record St",
    "sg:city":"Dallas",
    "sg:classifiers":[
        {
            "category":"Communications",
            "subcategory":"Television Station",
            "type":"Services"
        }
    ],
    "sg:phone":"+1 214 977 6606",
    "sg:postcode":"75202",
    "sg:province":"TX",
    "sg:tags":[
        "broadcasting",
        "co"
    ],
    "sg:website":"www.belo.com",
    "wof:name":"Belo Corp",
    "wof:placetype":"venue"
},
  "geometry": {"coordinates":[-96.80608599999999,32.776013],"type":"Point"}
}