{
  "type": "Feature",
  "properties": {
    "iso:country":"US",
    "sg:address":"1010 W 23rd St",
    "sg:city":"Austin",
    "sg:classifiers":[
        {
            "category":"Professional",
            "subcategory":"Lawyer & Legal Services",
            "type":"Services"
        }
    ],
    "sg:phone":"+1 512 474 5195",
    "sg:postcode":"78705",
    "sg:province":"TX",
    "sg:tags":[
        "attorney"
    ],
    "wof:name":"David Shaw Law Office",
    "wof:placetype":"venue"
},
  "geometry": {"coordinates":[-97.749295,30.287386],"type":"Point"}
}