{
  "type": "Feature",
  "properties": {
    "iso:country":"US",
    "sg:address":"2411 6th Ave",
    "sg:city":"Amarillo",
    "sg:classifiers":[
        {
            "category":"Home & Garden",
            "subcategory":"Hardware",
            "type":"Retail Goods"
        }
    ],
    "sg:phone":"+1 806 373 8301",
    "sg:postcode":"79106",
    "sg:province":"TX",
    "wof:name":"Beebe's Ace Home Ctr",
    "wof:placetype":"venue"
},
  "geometry": {"coordinates":[-101.86452,35.211164],"type":"Point"}
}