{
  "type": "Feature",
  "properties": {
    "iso:country":"US",
    "sg:address":"4601 Shiloh Rd",
    "sg:city":"Flower Mound",
    "sg:classifiers":[
        {
            "category":"Real Estate",
            "subcategory":"Real Estate Operator",
            "type":"Services"
        }
    ],
    "sg:phone":"+1 817 430 4622",
    "sg:postcode":"75022",
    "sg:province":"TX",
    "sg:tags":[
        "mobile",
        "home",
        "park"
    ],
    "wof:name":"CMH",
    "wof:placetype":"venue"
},
  "geometry": {"coordinates":[-97.12909399999999,33.046765],"type":"Point"}
}