{
  "type": "Feature",
  "properties": {
    "iso:country":"US",
    "sg:address":"9901 Valley Ranch Pkwy E",
    "sg:city":"Irving",
    "sg:classifiers":[
        {
            "category":"Building & Trades",
            "subcategory":"Construction",
            "type":"Services"
        }
    ],
    "sg:phone":"+1 972 869 1808",
    "sg:postcode":"75063",
    "sg:province":"TX",
    "sg:tags":[
        "contractor"
    ],
    "wof:name":"Texas Bbl Lp",
    "wof:placetype":"venue"
},
  "geometry": {"coordinates":[-96.950699,32.940399],"type":"Point"}
}