{
  "type": "Feature",
  "properties": {
    "iso:country":"US",
    "sg:address":"9898 Hollow Way Rd",
    "sg:city":"Dallas",
    "sg:classifiers":[
        {
            "category":"Professional",
            "subcategory":"Business Services",
            "type":"Services"
        }
    ],
    "sg:phone":"+1 214 369 6925",
    "sg:postcode":"75220",
    "sg:province":"TX",
    "wof:name":"S P J Joint Venture",
    "wof:placetype":"venue"
},
  "geometry": {"coordinates":[-96.813864,32.877074],"type":"Point"}
}