{
  "type": "Feature",
  "properties": {
    "iso:country":"US",
    "sg:address":"1300 College Dr",
    "sg:city":"Waco",
    "sg:classifiers":[
        {
            "category":"Museum",
            "type":"Entertainment"
        }
    ],
    "sg:phone":"+1 254 752 4371",
    "sg:postcode":"76708",
    "sg:province":"TX",
    "sg:tags":[
        "gallery"
    ],
    "wof:name":"Art Center Shop The",
    "wof:placetype":"venue"
},
  "geometry": {"coordinates":[-97.174317,31.593007],"type":"Point"}
}