{
  "type": "Feature",
  "properties": {
    "iso:country":"US",
    "sg:address":"901 E Marshall Ave",
    "sg:city":"Longview",
    "sg:classifiers":[
        {
            "category":"Shopping",
            "subcategory":"Party Supplies",
            "type":"Retail Goods"
        },
        {
            "category":"Shopping",
            "subcategory":"Florist",
            "type":"Retail Goods"
        }
    ],
    "sg:phone":"+1 903 753 6802",
    "sg:postcode":"75601",
    "sg:province":"TX",
    "sg:tags":[
        "wedding"
    ],
    "sg:website":"http://www.carmensflowershop.com",
    "wof:name":"Flower Shoppe & Gifts",
    "wof:placetype":"venue"
},
  "geometry": {"coordinates":[-94.72925600000001,32.502258],"type":"Point"}
}