{
  "type": "Feature",
  "properties": {
    "iso:country":"US",
    "sg:address":"2171 FM 2931",
    "sg:city":"Aubrey",
    "sg:classifiers":[
        {
            "category":"Retail",
            "subcategory":"Animal Services",
            "type":"Services"
        }
    ],
    "sg:phone":"+1 940 365 9097",
    "sg:postcode":"76227",
    "sg:province":"TX",
    "sg:tags":[
        "breeder",
        "horse"
    ],
    "wof:name":"Eagle Branch Quarter Horses",
    "wof:placetype":"venue"
},
  "geometry": {"coordinates":[-96.961765,33.241024],"type":"Point"}
}