{
  "type": "Feature",
  "properties": {
    "iso:country":"US",
    "sg:address":"7013 Avenue E",
    "sg:city":"Santa Fe",
    "sg:classifiers":[
        {
            "category":"Retail",
            "subcategory":"Repair Shop",
            "type":"Services"
        }
    ],
    "sg:phone":"+1 409 925 8282",
    "sg:postcode":"77510",
    "sg:province":"TX",
    "wof:name":"Geese Key & Lock Shop",
    "wof:placetype":"venue"
},
  "geometry": {"coordinates":[-95.07234099999999,29.348961],"type":"Point"}
}