{
  "type": "Feature",
  "properties": {
    "iso:country":"US",
    "sg:address":"6015 Meadowbrook Dr",
    "sg:city":"Fort Worth",
    "sg:classifiers":[
        {
            "category":"Professional",
            "subcategory":"Lawyer & Legal Services",
            "type":"Services"
        }
    ],
    "sg:phone":"+1 940 591 1359",
    "sg:postcode":"76112",
    "sg:province":"TX",
    "sg:tags":[
        "attorney"
    ],
    "wof:name":"Gwinda L Burns Attorney At Law",
    "wof:placetype":"venue"
},
  "geometry": {"coordinates":[-97.22713899999999,32.746015],"type":"Point"}
}