{
  "type": "Feature",
  "properties": {
    "iso:country":"US",
    "sg:address":"720 E Stewart St",
    "sg:city":"Laredo",
    "sg:classifiers":[
        {
            "category":"Personal",
            "subcategory":"Beauty Salon",
            "type":"Services"
        }
    ],
    "sg:phone":"+1 956 724 4731",
    "sg:postcode":"78040",
    "sg:province":"TX",
    "wof:name":"Josie's Beauty Salon",
    "wof:placetype":"venue"
},
  "geometry": {"coordinates":[-99.48942099999999,27.519529],"type":"Point"}
}