{
  "type": "Feature",
  "properties": {
    "iso:country":"US",
    "sg:address":"4020 Preston Rd",
    "sg:city":"Plano",
    "sg:classifiers":[
        {
            "category":"Banks & Credit Unions",
            "subcategory":"Bank",
            "type":"Services"
        }
    ],
    "sg:phone":"+1 972 964 6961",
    "sg:postcode":"75093",
    "sg:province":"TX",
    "wof:name":"Regions",
    "wof:placetype":"venue"
},
  "geometry": {"coordinates":[-96.79428299999999,33.051656],"type":"Point"}
}