{
  "type": "Feature",
  "properties": {
    "iso:country":"US",
    "sg:address":"3220 W Park Row Dr",
    "sg:city":"Arlington",
    "sg:classifiers":[
        {
            "category":"Insurance",
            "subcategory":"Insurance Agent",
            "type":"Services"
        }
    ],
    "sg:phone":"+1 817 860 0000",
    "sg:postcode":"76013",
    "sg:province":"TX",
    "wof:name":"Reyes Orlando Insurance Agency",
    "wof:placetype":"venue"
},
  "geometry": {"coordinates":[-97.15990600000001,32.721416],"type":"Point"}
}