{
  "type": "Feature",
  "properties": {
    "iso:country":"US",
    "sg:address":"15093 Las Colonias Rd",
    "sg:city":"El Paso",
    "sg:classifiers":[
        {
            "category":"Freight",
            "type":"Transportation"
        }
    ],
    "sg:phone":"+1 915 851 8579",
    "sg:postcode":"79928",
    "sg:province":"TX",
    "sg:tags":[
        "trucking"
    ],
    "wof:name":"Arma & Son Trucking",
    "wof:placetype":"venue"
},
  "geometry": {"coordinates":[-106.147408,31.609269],"type":"Point"}
}