{
  "type": "Feature",
  "properties": {
    "iso:country":"US",
    "sg:address":"4003 Kelley St",
    "sg:city":"Houston",
    "sg:classifiers":[
        {
            "category":"Food & Beverages",
            "subcategory":"Groceries & Convenience Stores",
            "type":"Retail Goods"
        }
    ],
    "sg:phone":"+1 713 491 8204",
    "sg:postcode":"77026",
    "sg:province":"TX",
    "wof:name":"Friendly Tom",
    "wof:placetype":"venue"
},
  "geometry": {"coordinates":[-95.330597,29.813601],"type":"Point"}
}