{
  "type": "Feature",
  "properties": {
    "iso:country":"US",
    "sg:address":"213 Alpine Rd E",
    "sg:city":"Austin",
    "sg:classifiers":[
        {
            "category":"Organizations",
            "subcategory":"Labor Organization",
            "type":"Services"
        }
    ],
    "sg:phone":"+1 512 444 5633",
    "sg:postcode":"78704",
    "sg:province":"TX",
    "wof:name":"SEIU",
    "wof:placetype":"venue"
},
  "geometry": {"coordinates":[-97.759469,30.225771],"type":"Point"}
}