{
  "type": "Feature",
  "properties": {
    "iso:country":"US",
    "sg:address":"8714 Mc Avoy Dr",
    "sg:city":"Houston",
    "sg:classifiers":[
        {
            "category":"Education",
            "subcategory":"School",
            "type":"Public Place"
        }
    ],
    "sg:phone":"+1 713 774 1201",
    "sg:postcode":"77074",
    "sg:province":"TX",
    "sg:tags":[
        "elementary"
    ],
    "wof:name":"Mc Namara Elementary School",
    "wof:placetype":"venue"
},
  "geometry": {"coordinates":[-95.503758,29.683816],"type":"Point"}
}