{
  "type": "Feature",
  "properties": {
    "iso:country":"US",
    "sg:address":"424 Water St",
    "sg:city":"Brownsville",
    "sg:classifiers":[
        {
            "category":"Building & Trades",
            "subcategory":"Cleaning & Sanitation",
            "type":"Services"
        }
    ],
    "sg:phone":"+1 956 547 8346",
    "sg:postcode":"78520",
    "sg:province":"TX",
    "sg:tags":[
        "janitor"
    ],
    "wof:name":"Torres Janitorial Svc",
    "wof:placetype":"venue"
},
  "geometry": {"coordinates":[-97.527439,25.933997],"type":"Point"}
}