{
  "type": "Feature",
  "properties": {
    "iso:country":"US",
    "sg:address":"1105 Somerset Blvd",
    "sg:city":"Colleyville",
    "sg:classifiers":[
        {
            "category":"Professional",
            "subcategory":"Management & Consulting",
            "type":"Services"
        }
    ],
    "sg:phone":"+1 817 581 9546",
    "sg:postcode":"76034",
    "sg:province":"TX",
    "sg:tags":[
        "business",
        "public",
        "relations"
    ],
    "wof:name":"Paul Driskell & Assoc Inc",
    "wof:placetype":"venue"
},
  "geometry": {"coordinates":[-97.14988099999999,32.874443],"type":"Point"}
}