{
  "type": "Feature",
  "properties": {
    "iso:country":"US",
    "sg:address":"14540 Tamerisk Ln",
    "sg:city":"Dallas",
    "sg:classifiers":[
        {
            "category":"Health Services",
            "subcategory":"Health Practitioner",
            "type":"Services"
        }
    ],
    "sg:phone":"+1 972 620 7478",
    "sg:postcode":"75234",
    "sg:province":"TX",
    "wof:name":"Occupational Therapy Rehab",
    "wof:placetype":"venue"
},
  "geometry": {"coordinates":[-96.869286,32.946054],"type":"Point"}
}