{
  "type": "Feature",
  "properties": {
    "iso:country":"US",
    "sg:address":"2708 Dutton Dr",
    "sg:city":"Dallas",
    "sg:classifiers":[
        {
            "category":"Building & Trades",
            "subcategory":"Cleaning & Sanitation",
            "type":"Services"
        }
    ],
    "sg:phone":"+1 214 684 1855",
    "sg:postcode":"75211",
    "sg:province":"TX",
    "sg:tags":[
        "janitor"
    ],
    "wof:name":"Best Price Cleaning Svc",
    "wof:placetype":"venue"
},
  "geometry": {"coordinates":[-96.86591199999999,32.72543],"type":"Point"}
}