{
  "type": "Feature",
  "properties": {
    "iso:country":"US",
    "sg:address":"1621 SW Military Dr",
    "sg:city":"San Antonio",
    "sg:classifiers":[
        {
            "category":"Wholesale",
            "subcategory":"Auto Parts",
            "type":"Manufacturing & Wholesale Goods"
        }
    ],
    "sg:phone":"+1 210 927 9018",
    "sg:postcode":"78221",
    "sg:province":"TX",
    "wof:name":"Macias Tire Shop",
    "wof:placetype":"venue"
},
  "geometry": {"coordinates":[-98.519367,29.356728],"type":"Point"}
}