{
  "type": "Feature",
  "properties": {
    "iso:country":"US",
    "sg:address":"706 Curtin St",
    "sg:city":"Houston",
    "sg:classifiers":[
        {
            "category":"Organizations",
            "subcategory":"Religious Organization",
            "type":"Services"
        }
    ],
    "sg:phone":"+1 281 501 0477",
    "sg:postcode":"77018",
    "sg:province":"TX",
    "wof:name":"The Whale Church",
    "wof:placetype":"venue"
},
  "geometry": {"coordinates":[-95.410748,29.831526],"type":"Point"}
}