{
  "type": "Feature",
  "properties": {
    "iso:country":"US",
    "sg:address":"1048 Gardenia Dr",
    "sg:city":"New Braunfels",
    "sg:classifiers":[
        {
            "category":"Professional",
            "type":"Services"
        }
    ],
    "sg:phone":"+1 830 626 6260",
    "sg:postcode":"78130",
    "sg:province":"TX",
    "sg:tags":[
        "establishment"
    ],
    "wof:name":"Hanna's Be Goods",
    "wof:placetype":"venue"
},
  "geometry": {"coordinates":[-98.12246500000001,29.681745],"type":"Point"}
}