{
  "type": "Feature",
  "properties": {
    "iso:country":"US",
    "sg:address":"1010 S Pearl Expy",
    "sg:city":"Dallas",
    "sg:classifiers":[
        {
            "category":"Food & Beverages",
            "subcategory":"Fruits & Vegetables",
            "type":"Retail Goods"
        }
    ],
    "sg:phone":"+1 214 742 1477",
    "sg:postcode":"75201",
    "sg:province":"TX",
    "sg:tags":[
        "veggie"
    ],
    "wof:name":"Stubblefield D L Produce",
    "wof:placetype":"venue"
},
  "geometry": {"coordinates":[-96.78939800000001,32.7775],"type":"Point"}
}