{
  "type": "Feature",
  "properties": {
    "iso:country":"US",
    "sg:address":"5821 Northgate Ln",
    "sg:city":"Laredo",
    "sg:classifiers":[
        {
            "category":"Wholesale",
            "subcategory":"Furniture",
            "type":"Manufacturing & Wholesale Goods"
        }
    ],
    "sg:phone":"+1 956 728 0068",
    "sg:postcode":"78041",
    "sg:province":"TX",
    "wof:name":"Wittings Office",
    "wof:placetype":"venue"
},
  "geometry": {"coordinates":[-99.50198,27.555918],"type":"Point"}
}