{
  "type": "Feature",
  "properties": {
    "iso:country":"US",
    "sg:address":"1209 Thrasher Rd",
    "sg:city":"Callisburg",
    "sg:classifiers":[
        {
            "category":"Farming",
            "subcategory":"Livestock Farm",
            "type":"Manufacturing & Wholesale Goods"
        }
    ],
    "sg:phone":"+1 940 668 8403",
    "sg:postcode":"76240",
    "sg:province":"TX",
    "sg:tags":[
        "ranch"
    ],
    "wof:name":"Charles Dean",
    "wof:placetype":"venue"
},
  "geometry": {"coordinates":[-96.99960900000001,33.694989],"type":"Point"}
}