{
  "type": "Feature",
  "properties": {
    "iso:country":"US",
    "sg:address":"2746 W Brooklyn Ave",
    "sg:city":"Dallas",
    "sg:classifiers":[
        {
            "category":"Restaurant",
            "type":"Food & Drink"
        }
    ],
    "sg:phone":"+1 214 942 7930",
    "sg:postcode":"75211",
    "sg:province":"TX",
    "sg:tags":[
        "eating"
    ],
    "wof:name":"El Rico Elote",
    "wof:placetype":"venue"
},
  "geometry": {"coordinates":[-96.865084,32.739096],"type":"Point"}
}