{
  "type": "Feature",
  "properties": {
    "iso:country":"US",
    "sg:address":"2925 Dowlen Rd",
    "sg:city":"Beaumont",
    "sg:classifiers":[
        {
            "category":"Banks & Credit Unions",
            "subcategory":"Bank",
            "type":"Services"
        },
        {
            "category":"Banks & Credit Unions",
            "subcategory":"Financial Services",
            "type":"Services"
        }
    ],
    "sg:phone":"+1 409 866 3624",
    "sg:postcode":"77706",
    "sg:province":"TX",
    "sg:tags":[
        "commercial",
        "loan",
        "saving"
    ],
    "sg:website":"http://www.compassbank.com",
    "wof:name":"Compass Bank",
    "wof:placetype":"venue"
},
  "geometry": {"coordinates":[-94.16851,30.10513],"type":"Point"}
}