{
  "type": "Feature",
  "properties": {
    "iso:country":"US",
    "sg:address":"2106 Hillridge Ct",
    "sg:city":"Arlington",
    "sg:classifiers":[
        {
            "category":"Real Estate",
            "subcategory":"Real Estate Agent",
            "type":"Services"
        }
    ],
    "sg:phone":"+1 817 274 7660",
    "sg:postcode":"76012",
    "sg:province":"TX",
    "wof:name":"Richlen Co",
    "wof:placetype":"venue"
},
  "geometry": {"coordinates":[-97.143539,32.76523],"type":"Point"}
}