{
  "type": "Feature",
  "properties": {
    "iso:country":"US",
    "sg:address":"5313 Mariners Dr",
    "sg:city":"Plano",
    "sg:classifiers":[
        {
            "category":"Banks & Credit Unions",
            "subcategory":"Financial Services",
            "type":"Services"
        }
    ],
    "sg:phone":"+1 972 612 3023",
    "sg:postcode":"75093",
    "sg:province":"TX",
    "sg:tags":[
        "investor"
    ],
    "wof:name":"Sharshiv Capital Ltd",
    "wof:placetype":"venue"
},
  "geometry": {"coordinates":[-96.80543900000001,33.033212],"type":"Point"}
}