{
  "type": "Feature",
  "properties": {
    "iso:country":"US",
    "sg:address":"9011 Bill Hickcock Pass",
    "sg:city":"Austin",
    "sg:classifiers":[
        {
            "category":"Building & Trades",
            "subcategory":"Cleaning & Sanitation",
            "type":"Services"
        }
    ],
    "sg:phone":"+1 512 686 4638",
    "sg:postcode":"78748",
    "sg:province":"TX",
    "sg:tags":[
        "house"
    ],
    "sg:website":"http://austin.citysearch.com/profile/external/47486678/austin_tx/welcome_home_cleaning_services.html?publisher=yellowpages&reference_id=1&placement=ypwebsitemip",
    "wof:name":"Welcome Home Cleaning Services",
    "wof:placetype":"venue"
},
  "geometry": {"coordinates":[-97.742333,30.26896],"type":"Point"}
}