{
  "type": "Feature",
  "properties": {
    "iso:country":"US",
    "sg:address":"3500 Thomas Ave",
    "sg:city":"Midland",
    "sg:classifiers":[
        {
            "category":"Recreation",
            "subcategory":"Amusement Park",
            "type":"Entertainment"
        }
    ],
    "sg:phone":"+1 432 570 1187",
    "sg:postcode":"79703",
    "sg:province":"TX",
    "wof:name":"Lucky Lady Arcade",
    "wof:placetype":"venue"
},
  "geometry": {"coordinates":[-102.11972,31.990744],"type":"Point"}
}