{
  "type": "Feature",
  "properties": {
    "iso:country":"US",
    "sg:address":"808 Hunter Ridge",
    "sg:city":"Nederland",
    "sg:classifiers":[
        {
            "category":"Manufacturing",
            "subcategory":"Metals",
            "type":"Manufacturing & Wholesale Goods"
        }
    ],
    "sg:phone":"+1 409 727 7384",
    "sg:postcode":"77627",
    "sg:province":"TX",
    "sg:tags":[
        "screw",
        "nut",
        "bolt"
    ],
    "wof:name":"Texas 24 Hour Nut & Bolt",
    "wof:placetype":"venue"
},
  "geometry": {"coordinates":[-93.983259,29.976482],"type":"Point"}
}