{
  "type": "Feature",
  "properties": {
    "iso:country":"US",
    "sg:address":"3925 W Baker Ln",
    "sg:city":"Austin",
    "sg:classifiers":[
        {
            "category":"Professional",
            "subcategory":"Research",
            "type":"Services"
        }
    ],
    "sg:phone":"+1 512 961 3680",
    "sg:postcode":"78759",
    "sg:province":"TX",
    "sg:tags":[
        "smoothstone",
        "smooth-stone"
    ],
    "sg:website":"http://www.smooth-stone.com/",
    "wof:name":"Smooth-Stone",
    "wof:placetype":"venue"
},
  "geometry": {"coordinates":[-97.679002,30.282888],"type":"Point"}
}