{
  "type": "Feature",
  "properties": {
    "iso:country":"US",
    "sg:address":"630 Columbine Ave",
    "sg:city":"Cedar Park",
    "sg:classifiers":[
        {
            "category":"Organizations",
            "subcategory":"Religious Organization",
            "type":"Services"
        }
    ],
    "sg:phone":"+1 512 528 8474",
    "sg:postcode":"78613",
    "sg:province":"TX",
    "wof:name":"New Birth Community Baptist Ch",
    "wof:placetype":"venue"
},
  "geometry": {"coordinates":[-97.84278500000001,30.535727],"type":"Point"}
}