{
  "type": "Feature",
  "properties": {
    "iso:country":"US",
    "sg:address":"11112 Oak Branch Dr",
    "sg:city":"Austin",
    "sg:classifiers":[
        {
            "category":"Professional",
            "subcategory":"Research",
            "type":"Services"
        }
    ],
    "sg:phone":"+1 512 301 1102",
    "sg:postcode":"78737",
    "sg:province":"TX",
    "sg:tags":[
        "environmental",
        "ecological"
    ],
    "wof:name":"Reliance Industries",
    "wof:placetype":"venue"
},
  "geometry": {"coordinates":[-97.973551,30.209911],"type":"Point"}
}