{
  "type": "Feature",
  "properties": {
    "iso:country":"US",
    "sg:address":"269 E Golden Arrow Cir",
    "sg:city":"Spring",
    "sg:classifiers":[
        {
            "category":"Shopping",
            "subcategory":"Computers & Home Electronics",
            "type":"Retail Goods"
        }
    ],
    "sg:phone":"+1 281 363 9805",
    "sg:postcode":"77381",
    "sg:province":"TX",
    "wof:name":"Lukos Electronic Environments",
    "wof:placetype":"venue"
},
  "geometry": {"coordinates":[-95.526802,30.182982],"type":"Point"}
}