{
  "type": "Feature",
  "properties": {
    "iso:country":"US",
    "sg:address":"3116 Telge St Ste E",
    "sg:city":"Houston",
    "sg:classifiers":[
        {
            "category":"Personal",
            "subcategory":"Barber",
            "type":"Services"
        }
    ],
    "sg:phone":"+1 713 748 8999",
    "sg:postcode":"77054",
    "sg:province":"TX",
    "wof:name":"Trimmers Barber Salon",
    "wof:placetype":"venue"
},
  "geometry": {"coordinates":[-95.379501,29.6999],"type":"Point"}
}