{
  "type": "Feature",
  "properties": {
    "iso:country":"US",
    "sg:address":"3602 Summerhill Rd",
    "sg:city":"Texarkana",
    "sg:classifiers":[
        {
            "category":"Wholesale",
            "subcategory":"Machinery & Supplies",
            "type":"Manufacturing & Wholesale Goods"
        }
    ],
    "sg:phone":"+1 903 793 8426",
    "sg:postcode":"75503",
    "sg:province":"TX",
    "sg:tags":[
        "janitor"
    ],
    "sg:website":"www.parwin.com",
    "wof:name":"Parwin Co",
    "wof:placetype":"venue"
},
  "geometry": {"coordinates":[-94.065004,33.45186],"type":"Point"}
}