{
  "type": "Feature",
  "properties": {
    "iso:country":"US",
    "sg:address":"7055 Hollister St",
    "sg:city":"Houston",
    "sg:classifiers":[
        {
            "category":"Banks & Credit Unions",
            "subcategory":"Financial Services",
            "type":"Services"
        }
    ],
    "sg:phone":"+1 713 462 4122",
    "sg:postcode":"77040",
    "sg:province":"TX",
    "sg:tags":[
        "international",
        "trade"
    ],
    "wof:name":"Gulf Coast Petro Trading Co",
    "wof:placetype":"venue"
},
  "geometry": {"coordinates":[-95.50633500000001,29.862981],"type":"Point"}
}