{
  "type": "Feature",
  "properties": {
    "iso:country":"US",
    "sg:address":"907 N Bowser Rd",
    "sg:city":"Richardson",
    "sg:classifiers":[
        {
            "category":"Building & Trades",
            "subcategory":"Electrical",
            "type":"Services"
        }
    ],
    "sg:phone":"+1 972 644 5407",
    "sg:postcode":"75081",
    "sg:province":"TX",
    "sg:tags":[
        "electrical",
        "electric",
        "contractor"
    ],
    "sg:website":"www.petri-electric.com",
    "wof:name":"Petri Electric Inc",
    "wof:placetype":"venue"
},
  "geometry": {"coordinates":[-96.71376600000001,32.960633],"type":"Point"}
}