{
  "type": "Feature",
  "properties": {
    "iso:country":"US",
    "sg:address":"3775 Stagg Dr",
    "sg:city":"Beaumont",
    "sg:classifiers":[
        {
            "category":"Banks & Credit Unions",
            "subcategory":"Bank",
            "type":"Services"
        }
    ],
    "sg:phone":"+1 409 654 7523",
    "sg:postcode":"77701",
    "sg:province":"TX",
    "sg:tags":[
        "saving",
        "commercial"
    ],
    "sg:website":"http://www.hibernia.com",
    "wof:name":"Capital One Bank",
    "wof:placetype":"venue"
},
  "geometry": {"coordinates":[-94.132817,30.070022],"type":"Point"}
}