{
  "type": "Feature",
  "properties": {
    "iso:country":"US",
    "sg:address":"5004 Norfolk Dr",
    "sg:city":"Plano",
    "sg:classifiers":[
        {
            "category":"Professional",
            "subcategory":"Business Services",
            "type":"Services"
        }
    ],
    "sg:phone":"+1 972 881 9143",
    "sg:postcode":"75023",
    "sg:province":"TX",
    "wof:name":"Carroll Tamie Interiors",
    "wof:placetype":"venue"
},
  "geometry": {"coordinates":[-96.726105,33.055118],"type":"Point"}
}