{
  "type": "Feature",
  "properties": {
    "iso:country":"US",
    "sg:address":"1224 E 14th St",
    "sg:city":"Brownsville",
    "sg:classifiers":[
        {
            "category":"Restaurant",
            "type":"Food & Drink"
        }
    ],
    "sg:phone":"+1 956 546 8812",
    "sg:postcode":"78520",
    "sg:province":"TX",
    "sg:tags":[
        "eating"
    ],
    "wof:name":"Garcia's Restaurant",
    "wof:placetype":"venue"
},
  "geometry": {"coordinates":[-97.49095800000001,25.904453],"type":"Point"}
}