{
  "type": "Feature",
  "properties": {
    "iso:country":"US",
    "sg:address":"1102 W Pioneer Pkwy",
    "sg:city":"Grand Prairie",
    "sg:classifiers":[
        {
            "category":"Recreation",
            "subcategory":"Arcade",
            "type":"Entertainment"
        }
    ],
    "sg:phone":"+1 972 623 2662",
    "sg:postcode":"75051",
    "sg:province":"TX",
    "sg:tags":[
        "device",
        "operator",
        "amusement"
    ],
    "wof:name":"Magical Odds",
    "wof:placetype":"venue"
},
  "geometry": {"coordinates":[-97.021664,32.709703],"type":"Point"}
}