{
  "type": "Feature",
  "properties": {
    "iso:country":"US",
    "sg:address":"2555 I- 35 Svc Rd",
    "sg:city":"Round Rock",
    "sg:classifiers":[
        {
            "category":"Manufacturing",
            "subcategory":"Tools & Machinery",
            "type":"Manufacturing & Wholesale Goods"
        }
    ],
    "sg:phone":"+1 512 388 9100",
    "sg:postcode":"78664",
    "sg:province":"TX",
    "sg:tags":[
        "process",
        "mfg",
        "ra",
        "instr"
    ],
    "wof:name":"Thermo Measuretech",
    "wof:placetype":"venue"
},
  "geometry": {"coordinates":[-97.69162,30.537661],"type":"Point"}
}