{
  "type": "Feature",
  "properties": {
    "iso:country":"US",
    "sg:address":"3206 E Richardson Rd",
    "sg:city":"Edinburg",
    "sg:classifiers":[
        {
            "category":"Organizations",
            "subcategory":"Non-profit Organization",
            "type":"Services"
        }
    ],
    "sg:phone":"+1 956 386 0212",
    "sg:postcode":"78539",
    "sg:province":"TX",
    "sg:tags":[
        "human"
    ],
    "wof:name":"Grocery Services South Ednbrg",
    "wof:placetype":"venue"
},
  "geometry": {"coordinates":[-98.13450899999999,26.304686],"type":"Point"}
}