{
  "type": "Feature",
  "properties": {
    "iso:country":"US",
    "sg:address":"231 E Main Ave",
    "sg:city":"Round Rock",
    "sg:classifiers":[
        {
            "category":"Social Services",
            "type":"Services"
        }
    ],
    "sg:phone":"+1 512 388 2400",
    "sg:postcode":"78664",
    "sg:province":"TX",
    "sg:tags":[
        "organization",
        "welfare"
    ],
    "sg:website":"www.arrow.org",
    "wof:name":"Arrow Project",
    "wof:placetype":"venue"
},
  "geometry": {"coordinates":[-97.676957,30.509007],"type":"Point"}
}