{
  "type": "Feature",
  "properties": {
    "iso:country":"US",
    "sg:address":"11949 Bissonnet St",
    "sg:city":"Houston",
    "sg:classifiers":[
        {
            "category":"Health Services",
            "subcategory":"Medical Lab",
            "type":"Services"
        }
    ],
    "sg:phone":"+1 281 988 6111",
    "sg:postcode":"77099",
    "sg:province":"TX",
    "sg:tags":[
        "info",
        "laboratory",
        "pathology",
        "speech",
        "language"
    ],
    "wof:name":"Cytology & Associates",
    "wof:placetype":"venue"
},
  "geometry": {"coordinates":[-95.58788,29.675173],"type":"Point"}
}