{
  "type": "Feature",
  "properties": {
    "iso:country":"US",
    "sg:address":"4907 Stonewall St",
    "sg:city":"Greenville",
    "sg:classifiers":[
        {
            "category":"Shopping",
            "subcategory":"Used Merchandise",
            "type":"Retail Goods"
        }
    ],
    "sg:phone":"+1 903 455 1536",
    "sg:postcode":"75401",
    "sg:province":"TX",
    "sg:tags":[
        "shop",
        "consignment"
    ],
    "wof:name":"ABC Market",
    "wof:placetype":"venue"
},
  "geometry": {"coordinates":[-96.107309,33.120441],"type":"Point"}
}