{
  "type": "Feature",
  "properties": {
    "iso:country":"US",
    "sg:address":"301 S 17th St",
    "sg:city":"Donna",
    "sg:classifiers":[
        {
            "category":"Health Services",
            "subcategory":"Clinic",
            "type":"Services"
        },
        {
            "category":"Health Services",
            "subcategory":"Doctor",
            "type":"Services"
        }
    ],
    "sg:phone":"+1 956 464 5809",
    "sg:postcode":"78537",
    "sg:province":"TX",
    "wof:name":"Nuestra Clinic Del Valle",
    "wof:placetype":"venue"
},
  "geometry": {"coordinates":[-98.04582600000001,26.165351],"type":"Point"}
}