{
  "type": "Feature",
  "properties": {
    "iso:country":"US",
    "sg:address":"11065 Nathan Bay Dr",
    "sg:city":"El Paso",
    "sg:classifiers":[
        {
            "category":"Shopping",
            "type":"Retail Goods"
        }
    ],
    "sg:phone":"+1 915 821 7470",
    "sg:postcode":"79934",
    "sg:province":"TX",
    "sg:tags":[
        "merchandise"
    ],
    "wof:name":"Charles R Bondurant",
    "wof:placetype":"venue"
},
  "geometry": {"coordinates":[-106.403395,31.932206],"type":"Point"}
}