{
  "type": "Feature",
  "properties": {
    "iso:country":"US",
    "sg:address":"1710 Briar St",
    "sg:city":"Austin",
    "sg:classifiers":[
        {
            "category":"Health Services",
            "subcategory":"Health Practitioner",
            "type":"Services"
        }
    ],
    "sg:phone":"+1 512 431 2445",
    "sg:postcode":"78704",
    "sg:province":"TX",
    "sg:tags":[
        "therapist",
        "physical"
    ],
    "wof:name":"P T Bodyworks",
    "wof:placetype":"venue"
},
  "geometry": {"coordinates":[-97.760598,30.249138],"type":"Point"}
}