{
  "type": "Feature",
  "properties": {
    "iso:country":"US",
    "sg:address":"1725 Babcock Rd",
    "sg:city":"San Antonio",
    "sg:classifiers":[
        {
            "category":"Retail",
            "subcategory":"Laundry & Dry Cleaning",
            "type":"Services"
        }
    ],
    "sg:phone":"+1 210 341 8440",
    "sg:postcode":"78229",
    "sg:province":"TX",
    "sg:tags":[
        "power"
    ],
    "wof:name":"Pilgrim Cleaners 316",
    "wof:placetype":"venue"
},
  "geometry": {"coordinates":[-98.571487,29.494955],"type":"Point"}
}