{
  "type": "Feature",
  "properties": {
    "iso:country":"US",
    "sg:address":"2315 E Front St",
    "sg:city":"Midland",
    "sg:classifiers":[
        {
            "category":"Food & Beverages",
            "subcategory":"Groceries & Convenience Stores",
            "type":"Retail Goods"
        }
    ],
    "sg:phone":"+1 432 682 4558",
    "sg:postcode":"79701",
    "sg:province":"TX",
    "wof:name":"Kent KWIK Convenience Stores",
    "wof:placetype":"venue"
},
  "geometry": {"coordinates":[-102.051401,32.007588],"type":"Point"}
}