{
  "type": "Feature",
  "properties": {
    "iso:country":"US",
    "sg:address":"211 E Hackberry St",
    "sg:city":"Fredericksburg",
    "sg:classifiers":[
        {
            "category":"Shopping",
            "subcategory":"Catalog Store",
            "type":"Retail Goods"
        }
    ],
    "sg:phone":"+1 830 997 9780",
    "sg:postcode":"78624",
    "sg:province":"TX",
    "sg:tags":[
        "mail",
        "sewing",
        "house"
    ],
    "wof:name":"Lace Tales",
    "wof:placetype":"venue"
},
  "geometry": {"coordinates":[-98.863528,30.281045],"type":"Point"}
}