{
  "type": "Feature",
  "properties": {
    "iso:country":"US",
    "sg:address":"12612 Rip Van Winkle Dr",
    "sg:city":"Houston",
    "sg:classifiers":[
        {
            "category":"Professional",
            "subcategory":"Business Services",
            "type":"Services"
        }
    ],
    "sg:phone":"+1 713 464 1580",
    "sg:postcode":"77024",
    "sg:province":"TX",
    "wof:name":"Midwest Restoration Svc",
    "wof:placetype":"venue"
},
  "geometry": {"coordinates":[-95.55682299999999,29.767149],"type":"Point"}
}