{
  "type": "Feature",
  "properties": {
    "iso:country":"US",
    "sg:address":"4544 Post Oak Place Dr Ste 350",
    "sg:city":"Houston",
    "sg:classifiers":[
        {
            "category":"Professional",
            "subcategory":"Lawyer & Legal Services",
            "type":"Services"
        }
    ],
    "sg:phone":"+1 713 784 9855",
    "sg:postcode":"77027",
    "sg:province":"TX",
    "wof:name":"Williams Mark J Atty",
    "wof:placetype":"venue"
},
  "geometry": {"coordinates":[-95.449335,29.750665],"type":"Point"}
}