{
  "type": "Feature",
  "properties": {
    "iso:country":"US",
    "sg:address":"5723 Grande Blvd",
    "sg:city":"Brownsville",
    "sg:classifiers":[
        {
            "category":"Autos & Motor Vehicles",
            "subcategory":"Auto Supplies",
            "type":"Retail Goods"
        }
    ],
    "sg:phone":"+1 956 838 0003",
    "sg:postcode":"78521",
    "sg:province":"TX",
    "sg:tags":[
        "tire"
    ],
    "wof:name":"Max Tire",
    "wof:placetype":"venue"
},
  "geometry": {"coordinates":[-97.42733,25.951229],"type":"Point"}
}