{
  "type": "Feature",
  "properties": {
    "iso:country":"US",
    "sg:address":"1216 Hunter St",
    "sg:city":"Mission",
    "sg:classifiers":[
        {
            "category":"Place Of Worship",
            "type":"Public Place"
        }
    ],
    "sg:phone":"+1 956 584 0637",
    "sg:postcode":"78572",
    "sg:province":"TX",
    "sg:tags":[
        "church"
    ],
    "wof:name":"Jesus Rene Cuellar",
    "wof:placetype":"venue"
},
  "geometry": {"coordinates":[-98.339017,26.222519],"type":"Point"}
}