{
  "type": "Feature",
  "properties": {
    "iso:country":"US",
    "sg:address":"200 W Houston St",
    "sg:city":"Marshall",
    "sg:classifiers":[
        {
            "category":"Government",
            "subcategory":"Office",
            "type":"Public Place"
        }
    ],
    "sg:phone":"+1 903 935 8412",
    "sg:postcode":"75670",
    "sg:province":"TX",
    "wof:name":"Harrison County Purchasing",
    "wof:placetype":"venue"
},
  "geometry": {"coordinates":[-94.36832099999999,32.545035],"type":"Point"}
}