{
  "type": "Feature",
  "properties": {
    "iso:country":"US",
    "sg:address":"7526 Grackle Dr",
    "sg:city":"Cypress",
    "sg:classifiers":[
        {
            "category":"Personal",
            "subcategory":"Beauty Salon",
            "type":"Services"
        }
    ],
    "sg:phone":"+1 281 933 3533",
    "sg:postcode":"77433",
    "sg:province":"TX",
    "sg:tags":[
        "shop"
    ],
    "wof:name":"Essential Btq & Hair Salon",
    "wof:placetype":"venue"
},
  "geometry": {"coordinates":[-95.695441,29.885991],"type":"Point"}
}