{
  "type": "Feature",
  "properties": {
    "iso:country":"US",
    "sg:address":"2713 N Larkspur Ln",
    "sg:city":"Pharr",
    "sg:classifiers":[
        {
            "category":"Manufacturing",
            "subcategory":"Building Materials",
            "type":"Manufacturing & Wholesale Goods"
        }
    ],
    "sg:phone":"+1 956 702 7549",
    "sg:postcode":"78577",
    "sg:province":"TX",
    "sg:tags":[
        "mfg",
        "wood",
        "kitchen",
        "cabinet"
    ],
    "wof:name":"Garzas Cabinets Plus Trim Spc",
    "wof:placetype":"venue"
},
  "geometry": {"coordinates":[-98.194383,26.218948],"type":"Point"}
}