{
  "type": "Feature",
  "properties": {
    "iso:country":"US",
    "sg:address":"5050 Golden Ln",
    "sg:city":"Fort Worth",
    "sg:classifiers":[
        {
            "category":"Travel",
            "subcategory":"Travel Agent",
            "type":"Entertainment"
        }
    ],
    "sg:phone":"+1 817 292 3131",
    "sg:postcode":"76123",
    "sg:province":"TX",
    "sg:tags":[
        "agency"
    ],
    "wof:name":"Leesure Travel",
    "wof:placetype":"venue"
},
  "geometry": {"coordinates":[-97.401737,32.626213],"type":"Point"}
}