{
  "type": "Feature",
  "properties": {
    "iso:country":"US",
    "sg:address":"3206 Main St",
    "sg:city":"Rowlett",
    "sg:classifiers":[
        {
            "category":"Retail",
            "subcategory":"Auto Repair",
            "type":"Services"
        }
    ],
    "sg:phone":"+1 972 463 4979",
    "sg:postcode":"75088",
    "sg:province":"TX",
    "sg:tags":[
        "body"
    ],
    "wof:name":"Sarco Motor Sports",
    "wof:placetype":"venue"
},
  "geometry": {"coordinates":[-96.570069,32.902506],"type":"Point"}
}