{
  "type": "Feature",
  "properties": {
    "iso:country":"US",
    "sg:address":"2822 E Illinois Ave",
    "sg:city":"Dallas",
    "sg:classifiers":[
        {
            "category":"Health Services",
            "subcategory":"Clinic",
            "type":"Services"
        },
        {
            "category":"Health Services",
            "subcategory":"Health Practitioner",
            "type":"Services"
        }
    ],
    "sg:phone":"+1 214 376 0999",
    "sg:postcode":"75216",
    "sg:province":"TX",
    "sg:tags":[
        "substance",
        "group",
        "mental",
        "ca",
        "psychologist",
        "abuse",
        "treatment",
        "home"
    ],
    "wof:name":"Hillvale Medical Group Associa",
    "wof:placetype":"venue"
},
  "geometry": {"coordinates":[-96.77720600000001,32.716362],"type":"Point"}
}