{
  "type": "Feature",
  "properties": {
    "iso:country":"US",
    "sg:address":"1031 N Broadway St",
    "sg:city":"La Porte",
    "sg:classifiers":[
        {
            "category":"Shopping",
            "subcategory":"Florist",
            "type":"Retail Goods"
        }
    ],
    "sg:phone":"+1 281 471 2124",
    "sg:postcode":"77571",
    "sg:province":"TX",
    "wof:name":"Compton's Florist",
    "wof:placetype":"venue"
},
  "geometry": {"coordinates":[-95.019606,29.677102],"type":"Point"}
}