{
  "type": "Feature",
  "properties": {
    "iso:country":"US",
    "sg:address":"115 N Venita Ave",
    "sg:city":"Lubbock",
    "sg:classifiers":[
        {
            "category":"Building & Trades",
            "subcategory":"Construction",
            "type":"Services"
        }
    ],
    "sg:phone":"+1 806 792 7058",
    "sg:postcode":"79416",
    "sg:province":"TX",
    "sg:tags":[
        "contractor",
        "laying",
        "floor",
        "covering"
    ],
    "wof:name":"McClurg Floor Covering",
    "wof:placetype":"venue"
},
  "geometry": {"coordinates":[-101.97728600000001,33.597433],"type":"Point"}
}