{
  "type": "Feature",
  "properties": {
    "iso:country":"US",
    "sg:address":"4613 N Fm 1417",
    "sg:city":"Sherman",
    "sg:classifiers":[
        {
            "category":"Utilities",
            "subcategory":"Electric",
            "type":"Services"
        },
        {
            "category":"Manufacturing",
            "subcategory":"Electronics",
            "type":"Manufacturing & Wholesale Goods"
        },
        {
            "category":"Building & Trades",
            "subcategory":"Electrical",
            "type":"Services"
        }
    ],
    "sg:phone":"+1 903 893 0949",
    "sg:postcode":"75092",
    "sg:province":"TX",
    "sg:tags":[
        "industrial",
        "electrician",
        "contractors-commercial",
        "equipment-testing"
    ],
    "sg:website":"http://www.napaautocare.com/",
    "wof:name":"Texas Electric",
    "wof:placetype":"venue"
},
  "geometry": {"coordinates":[-96.64398199999999,33.678437],"type":"Point"}
}