{
  "type": "Feature",
  "properties": {
    "iso:country":"US",
    "sg:address":"1016 16th St",
    "sg:city":"Wellington",
    "sg:classifiers":[
        {
            "category":"Health Services",
            "subcategory":"Nursing And Care Facility",
            "type":"Services"
        }
    ],
    "sg:phone":"+1 806 447 1187",
    "sg:postcode":"79095",
    "sg:province":"TX",
    "sg:tags":[
        "intermediate"
    ],
    "wof:name":"Parkview Manor",
    "wof:placetype":"venue"
},
  "geometry": {"coordinates":[-100.212914,34.848212],"type":"Point"}
}