{
  "type": "Feature",
  "properties": {
    "iso:country":"US",
    "sg:address":"4805 Frankford Rd",
    "sg:city":"Irving",
    "sg:classifiers":[
        {
            "category":"Shopping",
            "subcategory":"Florist",
            "type":"Retail Goods"
        }
    ],
    "sg:phone":"+1 972 256 6637",
    "sg:postcode":"75038",
    "sg:province":"TX",
    "wof:name":"In Bloom Florist",
    "wof:placetype":"venue"
},
  "geometry": {"coordinates":[-96.984497,32.869598],"type":"Point"}
}