{
  "type": "Feature",
  "properties": {
    "iso:country":"US",
    "sg:address":"3002 Thornton Ln",
    "sg:city":"Temple",
    "sg:classifiers":[
        {
            "category":"Retail",
            "subcategory":"Auto Repair",
            "type":"Services"
        }
    ],
    "sg:phone":"+1 254 773 7235",
    "sg:postcode":"76502",
    "sg:province":"TX",
    "sg:tags":[
        "repairing",
        "automobile"
    ],
    "wof:name":"Teal's Exxon Svc",
    "wof:placetype":"venue"
},
  "geometry": {"coordinates":[-97.384146,31.077396],"type":"Point"}
}