{
  "type": "Feature",
  "properties": {
    "iso:country":"US",
    "sg:address":"1917 Lake Omega St",
    "sg:city":"El Paso",
    "sg:classifiers":[
        {
            "category":"Manufacturing",
            "subcategory":"Wood Products",
            "type":"Manufacturing & Wholesale Goods"
        }
    ],
    "sg:phone":"+1 915 855 7773",
    "sg:postcode":"79936",
    "sg:province":"TX",
    "sg:tags":[
        "mfg"
    ],
    "wof:name":"Southwest Distribution Center",
    "wof:placetype":"venue"
},
  "geometry": {"coordinates":[-106.301687,31.770795],"type":"Point"}
}