{
  "type": "Feature",
  "properties": {
    "iso:country":"US",
    "sg:address":"804 Santa Fe Dr",
    "sg:city":"Weatherford",
    "sg:classifiers":[
        {
            "category":"Professional",
            "subcategory":"Business Services",
            "type":"Services"
        }
    ],
    "sg:phone":"+1 817 596 3288",
    "sg:postcode":"76086",
    "sg:province":"TX",
    "wof:name":"Alterntive Solutions Mediation",
    "wof:placetype":"venue"
},
  "geometry": {"coordinates":[-97.78589700000001,32.750606],"type":"Point"}
}