{
  "type": "Feature",
  "properties": {
    "iso:country":"US",
    "sg:address":"6734 Leyland Dr",
    "sg:city":"San Antonio",
    "sg:classifiers":[
        {
            "category":"Professional",
            "subcategory":"Business Services",
            "type":"Services"
        }
    ],
    "sg:phone":"+1 210 653 5446",
    "sg:postcode":"78239",
    "sg:province":"TX",
    "wof:name":"Aggie Inspection Services",
    "wof:placetype":"venue"
},
  "geometry": {"coordinates":[-98.35243699999999,29.516301],"type":"Point"}
}