{
  "type": "Feature",
  "properties": {
    "iso:country":"US",
    "sg:address":"4801 Congress Ave S",
    "sg:city":"Austin",
    "sg:classifiers":[
        {
            "category":"Real Estate",
            "subcategory":"Real Estate Operator",
            "type":"Services"
        }
    ],
    "sg:phone":"+1 512 637 6949",
    "sg:postcode":"78745",
    "sg:province":"TX",
    "sg:tags":[
        "building",
        "parks"
    ],
    "wof:name":"Bel Air Lofts",
    "wof:placetype":"venue"
},
  "geometry": {"coordinates":[-97.770132,30.213204],"type":"Point"}
}