{
  "type": "Feature",
  "properties": {
    "iso:country":"US",
    "sg:address":"1020 N Houston Ave",
    "sg:city":"New Braunfels",
    "sg:classifiers":[
        {
            "category":"Professional",
            "subcategory":"Business Services",
            "type":"Services"
        }
    ],
    "sg:phone":"+1 830 629 7123",
    "sg:postcode":"78130",
    "sg:province":"TX",
    "wof:name":"Svoboda Family Ltd Partnership",
    "wof:placetype":"venue"
},
  "geometry": {"coordinates":[-98.12657799999999,29.719375],"type":"Point"}
}