{
  "type": "Feature",
  "properties": {
    "iso:country":"US",
    "sg:address":"1406 Vermont St",
    "sg:city":"Houston",
    "sg:classifiers":[
        {
            "category":"Health Services",
            "subcategory":"Health Practitioner",
            "type":"Services"
        }
    ],
    "sg:phone":"+1 713 572 1888",
    "sg:postcode":"77006",
    "sg:province":"TX",
    "sg:tags":[
        "nutritionist"
    ],
    "wof:name":"Clinical Nutrition & Lifestyle",
    "wof:placetype":"venue"
},
  "geometry": {"coordinates":[-95.398241,29.750505],"type":"Point"}
}