{
  "type": "Feature",
  "properties": {
    "iso:country":"US",
    "sg:address":"2712 Parkview Ln",
    "sg:city":"Bedford",
    "sg:classifiers":[
        {
            "category":"Retail",
            "subcategory":"Auto Repair",
            "type":"Services"
        }
    ],
    "sg:phone":"+1 817 267 6564",
    "sg:postcode":"76022",
    "sg:province":"TX",
    "sg:tags":[
        "body"
    ],
    "wof:name":"Paul Clocks",
    "wof:placetype":"venue"
},
  "geometry": {"coordinates":[-97.122901,32.830531],"type":"Point"}
}