{
  "type": "Feature",
  "properties": {
    "iso:country":"US",
    "sg:address":"202 W Tarrant Rd",
    "sg:city":"Grand Prairie",
    "sg:classifiers":[
        {
            "category":"Social Services",
            "subcategory":"Child Care",
            "type":"Services"
        },
        {
            "category":"Organizations",
            "subcategory":"Religious Organization",
            "type":"Services"
        }
    ],
    "sg:phone":"+1 972 262 7434",
    "sg:postcode":"75050",
    "sg:province":"TX",
    "sg:tags":[
        "day"
    ],
    "wof:name":"First Christian Church Child D",
    "wof:placetype":"venue"
},
  "geometry": {"coordinates":[-97.00691,32.755819],"type":"Point"}
}