{
  "type": "Feature",
  "properties": {
    "iso:country":"US",
    "sg:address":"2904 Hillview Rd",
    "sg:city":"Austin",
    "sg:classifiers":[
        {
            "category":"Manufacturing",
            "subcategory":"Chemicals & Compounds",
            "type":"Manufacturing & Wholesale Goods"
        }
    ],
    "sg:phone":"+1 512 832 1945",
    "sg:postcode":"78703",
    "sg:province":"TX",
    "sg:tags":[
        "preparation",
        "mfg"
    ],
    "wof:name":"Mascoat",
    "wof:placetype":"venue"
},
  "geometry": {"coordinates":[-97.766542,30.308201],"type":"Point"}
}