{
  "type": "Feature",
  "properties": {
    "iso:country":"US",
    "sg:address":"610 W Clay St",
    "sg:city":"Houston",
    "sg:classifiers":[
        {
            "category":"Professional",
            "type":"Services"
        }
    ],
    "sg:phone":"+1 713 524 0971",
    "sg:postcode":"77019",
    "sg:province":"TX",
    "wof:name":"30th Parallel Inc",
    "wof:placetype":"venue"
},
  "geometry": {"coordinates":[-95.386742,29.755624],"type":"Point"}
}