{
  "type": "Feature",
  "properties": {
    "iso:country":"US",
    "sg:address":"259 W Gulf Bank Rd",
    "sg:city":"Houston",
    "sg:classifiers":[
        {
            "category":"Building & Trades",
            "subcategory":"Cleaning & Sanitation",
            "type":"Services"
        }
    ],
    "sg:phone":"+1 281 445 1558",
    "sg:postcode":"77037",
    "sg:province":"TX",
    "sg:tags":[
        "carpet"
    ],
    "wof:name":"Billy's Realsteam",
    "wof:placetype":"venue"
},
  "geometry": {"coordinates":[-95.39980300000001,29.889],"type":"Point"}
}