{
  "type": "Feature",
  "properties": {
    "iso:country":"US",
    "sg:address":"12201 Technology Blvd",
    "sg:city":"Austin",
    "sg:classifiers":[
        {
            "category":"Shopping",
            "subcategory":"Computers & Home Electronics",
            "type":"Retail Goods"
        }
    ],
    "sg:phone":"+1 512 231 8800",
    "sg:postcode":"78727",
    "sg:province":"TX",
    "sg:tags":[
        "equipment",
        "dealer"
    ],
    "wof:name":"Amherst Computer Product",
    "wof:placetype":"venue"
},
  "geometry": {"coordinates":[-97.760052,30.434206],"type":"Point"}
}