{
  "type": "Feature",
  "properties": {
    "iso:country":"US",
    "sg:address":"11101 Leopard St",
    "sg:city":"Corpus Christi",
    "sg:classifiers":[
        {
            "category":"Sports & Exercise",
            "subcategory":"Gym",
            "type":"Entertainment"
        }
    ],
    "sg:phone":"+1 361 242 8860",
    "sg:postcode":"78410",
    "sg:province":"TX",
    "sg:tags":[
        "club",
        "health",
        "studio",
        "gymnasium"
    ],
    "wof:name":"Ladies Workout Exp Corpus",
    "wof:placetype":"venue"
},
  "geometry": {"coordinates":[-97.586456,27.8459],"type":"Point"}
}