{
  "type": "Feature",
  "properties": {
    "iso:country":"US",
    "sg:address":"2625 Matlock Rd",
    "sg:city":"Arlington",
    "sg:classifiers":[
        {
            "category":"Health Services",
            "subcategory":"Doctor",
            "type":"Services"
        }
    ],
    "sg:phone":"+1 817 274 4888",
    "sg:postcode":"76015",
    "sg:province":"TX",
    "sg:tags":[
        "physician",
        "surgeon"
    ],
    "wof:name":"Ragendra S Chouhan MD",
    "wof:placetype":"venue"
},
  "geometry": {"coordinates":[-97.11494399999999,32.700862],"type":"Point"}
}