{
  "type": "Feature",
  "properties": {
    "iso:country":"US",
    "sg:address":"8859 State Hwy 123",
    "sg:city":"Stockdale",
    "sg:phone":"+1 830 745 2056",
    "sg:postcode":"78160",
    "sg:province":"TX",
    "sg:tags":[
        "farm",
        "corn"
    ],
    "wof:name":"Kotara Farm",
    "wof:placetype":"venue"
},
  "geometry": {"coordinates":[-97.938957,29.09327],"type":"Point"}
}