{
  "type": "Feature",
  "properties": {
    "iso:country":"US",
    "sg:address":"1 Riverway",
    "sg:city":"Houston",
    "sg:classifiers":[
        {
            "category":"Professional",
            "subcategory":"Lawyer & Legal Services",
            "type":"Services"
        }
    ],
    "sg:phone":"+1 713 782 4646",
    "sg:postcode":"77056",
    "sg:province":"TX",
    "sg:tags":[
        "attorney"
    ],
    "sg:website":"www.dhbllp.com",
    "wof:name":"Dunbar Harder & Benson",
    "wof:placetype":"venue"
},
  "geometry": {"coordinates":[-95.462144,29.761415],"type":"Point"}
}