{
  "type": "Feature",
  "properties": {
    "iso:country":"US",
    "sg:address":"1420 N Durham Dr",
    "sg:city":"Houston",
    "sg:classifiers":[
        {
            "category":"Building & Trades",
            "subcategory":"Plumbing",
            "type":"Services"
        }
    ],
    "sg:phone":"+1 713 868 9907",
    "sg:postcode":"77008",
    "sg:province":"TX",
    "sg:website":"www.nicksplumbing.com",
    "wof:name":"Nick's Plumbing & Sewer Service",
    "wof:placetype":"venue"
},
  "geometry": {"coordinates":[-95.411389,29.796792],"type":"Point"}
}