{
  "type": "Feature",
  "properties": {
    "iso:country":"US",
    "sg:address":"103 Burleson St",
    "sg:city":"Smithville",
    "sg:classifiers":[
        {
            "category":"Manufacturing",
            "subcategory":"Textiles",
            "type":"Manufacturing & Wholesale Goods"
        }
    ],
    "sg:phone":"+1 512 237 5500",
    "sg:postcode":"78957",
    "sg:province":"TX",
    "sg:tags":[
        "mfg"
    ],
    "wof:name":"Leonine Enterprises",
    "wof:placetype":"venue"
},
  "geometry": {"coordinates":[-97.15719799999999,30.0064],"type":"Point"}
}