{
  "type": "Feature",
  "properties": {
    "iso:country":"US",
    "sg:address":"333 Guadalupe St",
    "sg:city":"Austin",
    "sg:classifiers":[
        {
            "category":"Government",
            "subcategory":"Office",
            "type":"Public Place"
        }
    ],
    "sg:phone":"+1 512 305 7555",
    "sg:postcode":"78701",
    "sg:province":"TX",
    "sg:tags":[
        "state",
        "program"
    ],
    "sg:website":"www.tbvme.state.tx.us",
    "wof:name":"Veterinary Medical Examiners",
    "wof:placetype":"venue"
},
  "geometry": {"coordinates":[-97.74698100000001,30.266868],"type":"Point"}
}