{
  "type": "Feature",
  "properties": {
    "iso:country":"US",
    "sg:address":"104 E Broadway St",
    "sg:city":"Prosper",
    "sg:classifiers":[
        {
            "category":"Building & Trades",
            "subcategory":"Construction",
            "type":"Services"
        }
    ],
    "sg:phone":"+1 972 347 2149",
    "sg:postcode":"75078",
    "sg:province":"TX",
    "sg:tags":[
        "masonry",
        "contractor"
    ],
    "wof:name":"Martinez Masonry",
    "wof:placetype":"venue"
},
  "geometry": {"coordinates":[-96.80186399999999,33.23608],"type":"Point"}
}