{
  "type": "Feature",
  "properties": {
    "iso:country":"US",
    "sg:address":"4316 Dollar St",
    "sg:city":"Midlothian",
    "sg:classifiers":[
        {
            "category":"Building & Trades",
            "subcategory":"Landscaping Services",
            "type":"Services"
        }
    ],
    "sg:phone":"+1 972 333 2997",
    "sg:postcode":"76065",
    "sg:province":"TX",
    "sg:tags":[
        "lawn",
        "maintenance",
        "grounds"
    ],
    "wof:name":"J C Lawn & Landscape",
    "wof:placetype":"venue"
},
  "geometry": {"coordinates":[-97.068152,32.546248],"type":"Point"}
}