{
  "type": "Feature",
  "properties": {
    "iso:country":"US",
    "sg:address":"109 N College Ave",
    "sg:city":"Cleveland",
    "sg:classifiers":[
        {
            "category":"Shopping",
            "subcategory":"Florist",
            "type":"Retail Goods"
        }
    ],
    "sg:phone":"+1 281 592 2372",
    "sg:postcode":"77327",
    "sg:province":"TX",
    "wof:name":"Pace Stancil Florist",
    "wof:placetype":"venue"
},
  "geometry": {"coordinates":[-95.08692499999999,30.342938],"type":"Point"}
}