{
  "type": "Feature",
  "properties": {
    "iso:country":"US",
    "sg:address":"7000 N Mesa St",
    "sg:city":"El Paso",
    "sg:classifiers":[
        {
            "category":"Restaurant",
            "type":"Food & Drink"
        }
    ],
    "sg:phone":"+1 915 581 6396",
    "sg:postcode":"79912",
    "sg:province":"TX",
    "wof:name":"Wienerschnitzel",
    "wof:placetype":"venue"
},
  "geometry": {"coordinates":[-106.55100299999999,31.8358],"type":"Point"}
}