{
  "type": "Feature",
  "properties": {
    "iso:country":"US",
    "sg:address":"1215 Webhollow Cir",
    "sg:city":"Bryan",
    "sg:classifiers":[
        {
            "category":"Professional",
            "subcategory":"Business Services",
            "type":"Services"
        }
    ],
    "sg:phone":"+1 979 775 1993",
    "sg:postcode":"77801",
    "sg:province":"TX",
    "wof:name":"Obviuos Business Solutions",
    "wof:placetype":"venue"
},
  "geometry": {"coordinates":[-96.375621,30.636223],"type":"Point"}
}