{
  "type": "Feature",
  "properties": {
    "iso:country":"US",
    "sg:address":"6119 US Hwy 380",
    "sg:city":"Bridgeport",
    "sg:classifiers":[
        {
            "category":"Real Estate",
            "subcategory":"Real Estate Agent",
            "type":"Services"
        }
    ],
    "sg:phone":"+1 940 683 5191",
    "sg:postcode":"76426",
    "sg:province":"TX",
    "sg:website":"www.midwayproperties.com",
    "wof:name":"Midway Properties",
    "wof:placetype":"venue"
},
  "geometry": {"coordinates":[-97.71102999999999,33.229689],"type":"Point"}
}