{
  "type": "Feature",
  "properties": {
    "iso:country":"US",
    "sg:address":"13425 Rolling Hills Dr",
    "sg:city":"Beaumont",
    "sg:classifiers":[
        {
            "category":"Insurance",
            "subcategory":"Insurance Agent",
            "type":"Services"
        }
    ],
    "sg:phone":"+1 409 753 2444",
    "sg:postcode":"77713",
    "sg:province":"TX",
    "wof:name":"Reed John Insurance",
    "wof:placetype":"venue"
},
  "geometry": {"coordinates":[-94.268058,30.157401],"type":"Point"}
}