{
  "type": "Feature",
  "properties": {
    "iso:country":"US",
    "sg:address":"101 Hide A Way Lane Central",
    "sg:city":"Hideaway",
    "sg:classifiers":[
        {
            "category":"Real Estate",
            "subcategory":"Real Estate Services",
            "type":"Services"
        },
        {
            "category":"Home & Garden",
            "subcategory":"Home Furnishings",
            "type":"Retail Goods"
        }
    ],
    "sg:phone":"+1 903 882 7531",
    "sg:postcode":"75771",
    "sg:province":"TX",
    "sg:tags":[
        "tourists'",
        "rental",
        "sale",
        "vacation"
    ],
    "wof:name":"Lodge Restaurant",
    "wof:placetype":"venue"
},
  "geometry": {"coordinates":[-95.455669,32.470417],"type":"Point"}
}