{
  "type": "Feature",
  "properties": {
    "iso:country":"US",
    "sg:address":"3500 McCann Rd",
    "sg:city":"Longview",
    "sg:classifiers":[
        {
            "category":"Shopping",
            "subcategory":"Department Store",
            "type":"Retail Goods"
        }
    ],
    "sg:phone":"+1 903 758 0753",
    "sg:postcode":"75605",
    "sg:province":"TX",
    "sg:website":"www.stagestoresinc.com",
    "wof:name":"Beall's Department Store",
    "wof:placetype":"venue"
},
  "geometry": {"coordinates":[-94.75432499999999,32.538447],"type":"Point"}
}