{
  "type": "Feature",
  "properties": {
    "iso:country":"US",
    "sg:address":"5921 Sunny Crest Ln",
    "sg:city":"Dallas",
    "sg:classifiers":[
        {
            "category":"Organizations",
            "subcategory":"Religious Organization",
            "type":"Services"
        }
    ],
    "sg:phone":"+1 214 375 9664",
    "sg:postcode":"75241",
    "sg:province":"TX",
    "sg:tags":[
        "church"
    ],
    "wof:name":"King Of Glory Baptist Church",
    "wof:placetype":"venue"
},
  "geometry": {"coordinates":[-96.803693,32.675151],"type":"Point"}
}