{
  "type": "Feature",
  "properties": {
    "iso:country":"US",
    "sg:address":"6605 Overlook Ct",
    "sg:city":"Plano",
    "sg:classifiers":[
        {
            "category":"Banks & Credit Unions",
            "subcategory":"Financial Services",
            "type":"Services"
        }
    ],
    "sg:phone":"+1 972 370 1424",
    "sg:postcode":"75024",
    "sg:province":"TX",
    "sg:tags":[
        "investor"
    ],
    "wof:name":"Jnj Family Investments Inc",
    "wof:placetype":"venue"
},
  "geometry": {"coordinates":[-96.843638,33.063018],"type":"Point"}
}