{
  "type": "Feature",
  "properties": {
    "iso:country":"US",
    "sg:address":"9869 Tanner Rd",
    "sg:city":"Houston",
    "sg:classifiers":[
        {
            "category":"Wholesale",
            "subcategory":"Metals & Minerals",
            "type":"Manufacturing & Wholesale Goods"
        }
    ],
    "sg:phone":"+1 713 895 8806",
    "sg:postcode":"77041",
    "sg:province":"TX",
    "sg:tags":[
        "extruded",
        "product",
        "aluminum"
    ],
    "wof:name":"OC Aluminum Inc",
    "wof:placetype":"venue"
},
  "geometry": {"coordinates":[-95.53675,29.84997],"type":"Point"}
}