{
  "type": "Feature",
  "properties": {
    "iso:country":"US",
    "sg:address":"16033 Pool Canyon Rd",
    "sg:city":"Austin",
    "sg:classifiers":[
        {
            "category":"Insurance",
            "subcategory":"Insurance Agent",
            "type":"Services"
        }
    ],
    "sg:phone":"+1 512 266 2155",
    "sg:postcode":"78734",
    "sg:province":"TX",
    "wof:name":"McMahon Insurance Group",
    "wof:placetype":"venue"
},
  "geometry": {"coordinates":[-97.929782,30.420721],"type":"Point"}
}