{
  "type": "Feature",
  "properties": {
    "iso:country":"US",
    "sg:address":"2802 Winding Shore Ln",
    "sg:city":"Katy",
    "sg:classifiers":[
        {
            "category":"Professional",
            "subcategory":"Business Services",
            "type":"Services"
        }
    ],
    "sg:phone":"+1 281 395 3045",
    "sg:postcode":"77450",
    "sg:province":"TX",
    "wof:name":"Barefoot Design",
    "wof:placetype":"venue"
},
  "geometry": {"coordinates":[-95.765244,29.742649],"type":"Point"}
}