{
  "type": "Feature",
  "properties": {
    "iso:country":"US",
    "sg:address":"2100 E Riverside Dr",
    "sg:city":"Austin",
    "sg:classifiers":[
        {
            "category":"Shopping",
            "subcategory":"Clothing, Apparel, & Fashions",
            "type":"Retail Goods"
        }
    ],
    "sg:phone":"+1 512 441 6800",
    "sg:postcode":"78741",
    "sg:province":"TX",
    "sg:tags":[
        "western"
    ],
    "wof:name":"New West Western Wear",
    "wof:placetype":"venue"
},
  "geometry": {"coordinates":[-97.72560799999999,30.237534],"type":"Point"}
}