{
  "type": "Feature",
  "properties": {
    "iso:country":"US",
    "sg:address":"1100 E Pleasant Run Rd",
    "sg:city":"De Soto",
    "sg:classifiers":[
        {
            "category":"Banks & Credit Unions",
            "subcategory":"Bank",
            "type":"Services"
        }
    ],
    "sg:phone":"+1 972 230 3900",
    "sg:postcode":"75115",
    "sg:province":"TX",
    "sg:tags":[
        "mortgage"
    ],
    "wof:name":"Commander Mortgage",
    "wof:placetype":"venue"
},
  "geometry": {"coordinates":[-96.82944000000001,32.604324],"type":"Point"}
}