{
  "type": "Feature",
  "properties": {
    "iso:country":"US",
    "sg:address":"6751 E Lancaster Ave",
    "sg:city":"Fort Worth",
    "sg:classifiers":[
        {
            "category":"Food & Beverages",
            "subcategory":"Liquor & Beverages",
            "type":"Retail Goods"
        }
    ],
    "sg:phone":"+1 817 457 8889",
    "sg:postcode":"76112",
    "sg:province":"TX",
    "wof:name":"U-Sav Liquor",
    "wof:placetype":"venue"
},
  "geometry": {"coordinates":[-97.21536399999999,32.731798],"type":"Point"}
}