{
  "type": "Feature",
  "properties": {
    "iso:country":"US",
    "sg:address":"12561 State Hwy 53",
    "sg:city":"Temple",
    "sg:classifiers":[
        {
            "category":"Organizations",
            "subcategory":"Religious Organization",
            "type":"Services"
        }
    ],
    "sg:phone":"+1 254 985 2694",
    "sg:postcode":"76501",
    "sg:province":"TX",
    "sg:tags":[
        "church"
    ],
    "wof:name":"Seaton Brethren Church",
    "wof:placetype":"venue"
},
  "geometry": {"coordinates":[-97.209267,31.055607],"type":"Point"}
}