{
  "type": "Feature",
  "properties": {
    "iso:country":"US",
    "sg:address":"3818 Spicewood Springs Road",
    "sg:city":"Austin",
    "sg:classifiers":[
        {
            "category":"Professional",
            "subcategory":"Accounting & Tax Preparation",
            "type":"Services"
        }
    ],
    "sg:phone":"+1 512 346 3782",
    "sg:postcode":"78759",
    "sg:province":"TX",
    "sg:tags":[
        "accountant"
    ],
    "wof:name":"Hagy & Associates PC",
    "wof:placetype":"venue"
},
  "geometry": {"coordinates":[-97.749809,30.365511],"type":"Point"}
}