{
  "type": "Feature",
  "properties": {
    "iso:country":"US",
    "sg:address":"4400 Blanco Ave",
    "sg:city":"El Paso",
    "sg:classifiers":[
        {
            "category":"Education",
            "subcategory":"School",
            "type":"Public Place"
        }
    ],
    "sg:phone":"+1 915 351 3260",
    "sg:postcode":"79905",
    "sg:province":"TX",
    "wof:name":"Burleson School",
    "wof:placetype":"venue"
},
  "geometry": {"coordinates":[-106.43724400000001,31.766129],"type":"Point"}
}