{
  "type": "Feature",
  "properties": {
    "iso:country":"US",
    "sg:address":"62 W Elm St",
    "sg:city":"Hillsboro",
    "sg:classifiers":[
        {
            "category":"Professional",
            "subcategory":"Lawyer & Legal Services",
            "type":"Services"
        }
    ],
    "sg:phone":"+1 254 582 2536",
    "sg:postcode":"76645",
    "sg:province":"TX",
    "sg:tags":[
        "attorney"
    ],
    "sg:website":"www.mssm-law.com",
    "wof:name":"Martin Showers Smith Mc Donald",
    "wof:placetype":"venue"
},
  "geometry": {"coordinates":[-97.131055,32.010681],"type":"Point"}
}