{
  "type": "Feature",
  "properties": {
    "iso:country":"US",
    "sg:address":"2137 Branard St",
    "sg:city":"Houston",
    "sg:classifiers":[
        {
            "category":"Health Services",
            "subcategory":"Doctor",
            "type":"Services"
        }
    ],
    "sg:phone":"+1 713 521 9686",
    "sg:postcode":"77098",
    "sg:province":"TX",
    "wof:name":"Cory Logan DDS PA",
    "wof:placetype":"venue"
},
  "geometry": {"coordinates":[-95.41218000000001,29.736718],"type":"Point"}
}