{
  "type": "Feature",
  "properties": {
    "iso:country":"US",
    "sg:address":"12308 Twin Creeks Rd",
    "sg:city":"Manchaca",
    "sg:classifiers":[
        {
            "category":"Wholesale",
            "subcategory":"Stationery",
            "type":"Manufacturing & Wholesale Goods"
        }
    ],
    "sg:phone":"+1 512 928 9099",
    "sg:postcode":"78652",
    "sg:province":"TX",
    "sg:tags":[
        "business",
        "form",
        "system"
    ],
    "wof:name":"Extreme Business Svc",
    "wof:placetype":"venue"
},
  "geometry": {"coordinates":[-97.82850999999999,30.139295],"type":"Point"}
}