{
  "type": "Feature",
  "properties": {
    "iso:country":"US",
    "sg:address":"5302 Slide Rd",
    "sg:city":"Lubbock",
    "sg:classifiers":[
        {
            "category":"Utilities",
            "subcategory":"Mobile Phone",
            "type":"Services"
        }
    ],
    "sg:phone":"+1 806 785 2311",
    "sg:postcode":"79414",
    "sg:province":"TX",
    "sg:tags":[
        "telephone",
        "cellular"
    ],
    "wof:name":"Trio Wireless",
    "wof:placetype":"venue"
},
  "geometry": {"coordinates":[-101.922493,33.545095],"type":"Point"}
}