{
  "type": "Feature",
  "properties": {
    "iso:country":"US",
    "sg:address":"5935 Culebra Rd",
    "sg:city":"San Antonio",
    "sg:classifiers":[
        {
            "category":"Professional",
            "subcategory":"Art Services",
            "type":"Services"
        }
    ],
    "sg:phone":"+1 210 521 7506",
    "sg:postcode":"78238",
    "sg:province":"TX",
    "sg:tags":[
        "commercial",
        "design"
    ],
    "wof:name":"Alamo Silk Screen & Designs",
    "wof:placetype":"venue"
},
  "geometry": {"coordinates":[-98.604685,29.449384],"type":"Point"}
}