{
  "type": "Feature",
  "properties": {
    "iso:country":"US",
    "sg:address":"1300 S Frazier St",
    "sg:city":"Conroe",
    "sg:classifiers":[
        {
            "category":"Professional",
            "type":"Services"
        },
        {
            "category":"Retail",
            "subcategory":"Repair Shop",
            "type":"Services"
        }
    ],
    "sg:phone":"+1 936 441 7710",
    "sg:postcode":"77301",
    "sg:province":"TX",
    "sg:tags":[
        "establishment"
    ],
    "wof:name":"Dyne Tek Inc",
    "wof:placetype":"venue"
},
  "geometry": {"coordinates":[-95.45626300000001,30.289717],"type":"Point"}
}