{
  "type": "Feature",
  "properties": {
    "iso:country":"US",
    "sg:address":"932 W 34th St",
    "sg:city":"Houston",
    "sg:classifiers":[
        {
            "category":"Manufacturing",
            "subcategory":"Electronics",
            "type":"Manufacturing & Wholesale Goods"
        }
    ],
    "sg:phone":"+1 713 868 9144",
    "sg:postcode":"77018",
    "sg:province":"TX",
    "sg:tags":[
        "compact",
        "disc",
        "laser",
        "mfg"
    ],
    "wof:name":"Media Access Inc",
    "wof:placetype":"venue"
},
  "geometry": {"coordinates":[-95.41728000000001,29.817447],"type":"Point"}
}