{
  "type": "Feature",
  "properties": {
    "iso:country":"US",
    "sg:address":"4933 Sabre Ln",
    "sg:city":"Denton",
    "sg:classifiers":[
        {
            "category":"Transit Center",
            "subcategory":"Freight",
            "type":"Transportation"
        }
    ],
    "sg:phone":"+1 940 566 3025",
    "sg:postcode":"76207",
    "sg:province":"TX",
    "sg:tags":[
        "air",
        "cargo",
        "express",
        "package"
    ],
    "wof:name":"Texstar Airfreight",
    "wof:placetype":"venue"
},
  "geometry": {"coordinates":[-97.19416099999999,33.20624],"type":"Point"}
}