{
  "type": "Feature",
  "properties": {
    "iso:country":"US",
    "sg:address":"3142 US Hwy 287",
    "sg:city":"Waxahachie",
    "sg:classifiers":[
        {
            "category":"Building & Trades",
            "subcategory":"Construction",
            "type":"Services"
        }
    ],
    "sg:phone":"+1 972 351 9369",
    "sg:postcode":"75165",
    "sg:province":"TX",
    "sg:tags":[
        "contractor"
    ],
    "wof:name":"Steel Life Designs",
    "wof:placetype":"venue"
},
  "geometry": {"coordinates":[-96.801337,32.359009],"type":"Point"}
}