{
  "type": "Feature",
  "properties": {
    "iso:country":"US",
    "sg:address":"105 FM 517 W",
    "sg:city":"Dickinson",
    "sg:classifiers":[
        {
            "category":"Autos & Motor Vehicles",
            "subcategory":"Fuel & Gas Station",
            "type":"Retail Goods"
        }
    ],
    "sg:phone":"+1 281 337 4512",
    "sg:postcode":"77539",
    "sg:province":"TX",
    "sg:tags":[
        "grocery",
        "station",
        "gasoline"
    ],
    "wof:name":"Texaco",
    "wof:placetype":"venue"
},
  "geometry": {"coordinates":[-95.07818399999999,29.448465],"type":"Point"}
}