{
  "type": "Feature",
  "properties": {
    "iso:country":"US",
    "sg:address":"4920 FM 1102",
    "sg:city":"New Braunfels",
    "sg:classifiers":[
        {
            "category":"Wholesale",
            "subcategory":"Vending Machines",
            "type":"Manufacturing & Wholesale Goods"
        }
    ],
    "sg:phone":"+1 830 625 1879",
    "sg:postcode":"78132",
    "sg:province":"TX",
    "sg:tags":[
        "operator"
    ],
    "wof:name":"Armadillo Vending",
    "wof:placetype":"venue"
},
  "geometry": {"coordinates":[-98.06460199999999,29.776145],"type":"Point"}
}