{
  "type": "Feature",
  "properties": {
    "iso:country":"US",
    "sg:address":"2653 Brenner Dr",
    "sg:city":"Dallas",
    "sg:classifiers":[
        {
            "category":"Home & Garden",
            "subcategory":"Home Furnishings",
            "type":"Retail Goods"
        }
    ],
    "sg:phone":"+1 214 357 2846",
    "sg:postcode":"75220",
    "sg:province":"TX",
    "sg:tags":[
        "shelving"
    ],
    "sg:website":"http://www.wwcannon.com",
    "wof:name":"W W Cannon Inc",
    "wof:placetype":"venue"
},
  "geometry": {"coordinates":[-96.88551699999999,32.872044],"type":"Point"}
}