{
  "type": "Feature",
  "properties": {
    "iso:country":"US",
    "sg:address":"132 Donna Dr",
    "sg:city":"Kerrville",
    "sg:classifiers":[
        {
            "category":"Shopping",
            "subcategory":"Hobbies, Toys, & Games",
            "type":"Retail Goods"
        }
    ],
    "sg:phone":"+1 830 257 6660",
    "sg:postcode":"78028",
    "sg:province":"TX",
    "wof:name":"A Jenny Thing",
    "wof:placetype":"venue"
},
  "geometry": {"coordinates":[-99.16292,30.014599],"type":"Point"}
}