{
  "type": "Feature",
  "properties": {
    "iso:country":"US",
    "sg:address":"5828 Balcones Dr",
    "sg:city":"Austin",
    "sg:classifiers":[
        {
            "category":"Real Estate",
            "subcategory":"Real Estate Services",
            "type":"Services"
        },
        {
            "category":"Building & Trades",
            "subcategory":"Cleaning & Sanitation",
            "type":"Services"
        }
    ],
    "sg:phone":"+1 512 302 5522",
    "sg:postcode":"78731",
    "sg:province":"TX",
    "sg:tags":[
        "maintenance",
        "cleaners-interior"
    ],
    "wof:name":"Fish Window Cleaning",
    "wof:placetype":"venue"
},
  "geometry": {"coordinates":[-97.755442,30.33995],"type":"Point"}
}