{
  "type": "Feature",
  "properties": {
    "iso:country":"US",
    "sg:address":"7873 Pecan Villas Dr",
    "sg:city":"Houston",
    "sg:classifiers":[
        {
            "category":"Manufacturing",
            "subcategory":"Metals",
            "type":"Manufacturing & Wholesale Goods"
        },
        {
            "category":"Manufacturing",
            "subcategory":"Building Materials",
            "type":"Manufacturing & Wholesale Goods"
        }
    ],
    "sg:phone":"+1 713 643 2989",
    "sg:postcode":"77061",
    "sg:province":"TX",
    "sg:tags":[
        "fabricator",
        "work",
        "sheet"
    ],
    "wof:name":"Gonzalez Sheet Metal Roofing",
    "wof:placetype":"venue"
},
  "geometry": {"coordinates":[-95.27960899999999,29.671093],"type":"Point"}
}