{
  "type": "Feature",
  "properties": {
    "iso:country":"US",
    "sg:address":"7100 Gateway Blvd E",
    "sg:city":"El Paso",
    "sg:classifiers":[
        {
            "category":"Manufacturing",
            "subcategory":"Leather Goods",
            "type":"Manufacturing & Wholesale Goods"
        }
    ],
    "sg:phone":"+1 915 779 5465",
    "sg:postcode":"79915",
    "sg:province":"TX",
    "sg:tags":[
        "boot"
    ],
    "wof:name":"Justin Boot Co",
    "wof:placetype":"venue"
},
  "geometry": {"coordinates":[-106.37710800000001,31.771051],"type":"Point"}
}