{
  "type": "Feature",
  "properties": {
    "iso:country":"US",
    "sg:address":"1906 E Park Ave",
    "sg:city":"Palestine",
    "sg:classifiers":[
        {
            "category":"Professional",
            "type":"Services"
        }
    ],
    "sg:phone":"+1 903 723 0522",
    "sg:postcode":"75801",
    "sg:province":"TX",
    "wof:name":"East Texas Intermediaries",
    "wof:placetype":"venue"
},
  "geometry": {"coordinates":[-95.607936,31.758464],"type":"Point"}
}