{
  "type": "Feature",
  "properties": {
    "iso:country":"US",
    "sg:address":"1735 Texoma Pkwy",
    "sg:city":"Sherman",
    "sg:classifiers":[
        {
            "category":"Personal",
            "subcategory":"Beauty Salon",
            "type":"Services"
        }
    ],
    "sg:phone":"+1 903 813 1121",
    "sg:postcode":"75090",
    "sg:province":"TX",
    "wof:name":"Exceptions",
    "wof:placetype":"venue"
},
  "geometry": {"coordinates":[-96.606829,33.653827],"type":"Point"}
}