{
  "type": "Feature",
  "properties": {
    "iso:country":"US",
    "sg:address":"1500 E 6th St",
    "sg:city":"Weslaco",
    "sg:classifiers":[
        {
            "category":"Shopping",
            "subcategory":"Pharmacy",
            "type":"Retail Goods"
        }
    ],
    "sg:phone":"+1 956 968 8995",
    "sg:postcode":"78596",
    "sg:province":"TX",
    "wof:name":"De LA Rosa Pharmacy Inc",
    "wof:placetype":"venue"
},
  "geometry": {"coordinates":[-97.976547,26.155607],"type":"Point"}
}