{
  "type": "Feature",
  "properties": {
    "iso:country":"US",
    "sg:address":"2509 Memphis Ave",
    "sg:city":"Nederland",
    "sg:classifiers":[
        {
            "category":"Insurance",
            "subcategory":"Insurance Agent",
            "type":"Services"
        }
    ],
    "sg:phone":"+1 409 727 8549",
    "sg:postcode":"77627",
    "sg:province":"TX",
    "wof:name":"Texas Roughriders Baseball CLB",
    "wof:placetype":"venue"
},
  "geometry": {"coordinates":[-94.007846,29.97289],"type":"Point"}
}