{
  "type": "Feature",
  "properties": {
    "iso:country":"US",
    "sg:address":"116 Sligo St",
    "sg:city":"San Antonio",
    "sg:classifiers":[
        {
            "category":"Retail",
            "subcategory":"Repair Shop",
            "type":"Services"
        }
    ],
    "sg:phone":"+1 210 633 3511",
    "sg:postcode":"78223",
    "sg:province":"TX",
    "sg:tags":[
        "bathtub",
        "sink",
        "refinishing"
    ],
    "wof:name":"Reliable Refinishing",
    "wof:placetype":"venue"
},
  "geometry": {"coordinates":[-98.430121,29.328777],"type":"Point"}
}