{
  "type": "Feature",
  "properties": {
    "iso:country":"US",
    "sg:address":"210 N Van Buren St",
    "sg:city":"Amarillo",
    "sg:classifiers":[
        {
            "category":"Building & Trades",
            "subcategory":"Construction",
            "type":"Services"
        }
    ],
    "sg:phone":"+1 806 379 8600",
    "sg:postcode":"79107",
    "sg:province":"TX",
    "wof:name":"House Cabinets",
    "wof:placetype":"venue"
},
  "geometry": {"coordinates":[-101.839039,35.216314],"type":"Point"}
}