{
  "type": "Feature",
  "properties": {
    "iso:country":"US",
    "sg:address":"24571 Fm 1314 Rd",
    "sg:city":"Porter",
    "sg:classifiers":[
        {
            "category":"Restaurant",
            "type":"Food & Drink"
        }
    ],
    "sg:menulink":"http://www.allmenus.com/tx/southeast-montgomery/218063-burger-king/menu/",
    "sg:phone":"+1 281 354 4841",
    "sg:postcode":"77365",
    "sg:province":"TX",
    "sg:tags":[
        "american"
    ],
    "wof:name":"Burger King",
    "wof:placetype":"venue"
},
  "geometry": {"coordinates":[-95.238353,30.104658],"type":"Point"}
}