{
  "type": "Feature",
  "properties": {
    "iso:country":"US",
    "sg:address":"4801 S State Hwy 91",
    "sg:city":"Denison",
    "sg:classifiers":[
        {
            "category":"Organizations",
            "subcategory":"Community Association",
            "type":"Services"
        }
    ],
    "sg:phone":"+1 903 463 3561",
    "sg:postcode":"75020",
    "sg:province":"TX",
    "sg:tags":[
        "club"
    ],
    "wof:name":"Calhoons Club",
    "wof:placetype":"venue"
},
  "geometry": {"coordinates":[-96.57004999999999,33.704172],"type":"Point"}
}