{
  "type": "Feature",
  "properties": {
    "iso:country":"US",
    "sg:address":"6323 Bay Meadows St",
    "sg:city":"San Antonio",
    "sg:classifiers":[
        {
            "category":"Personal",
            "subcategory":"Beauty Salon",
            "type":"Services"
        }
    ],
    "sg:phone":"+1 210 661 4619",
    "sg:postcode":"78244",
    "sg:province":"TX",
    "sg:tags":[
        "shop"
    ],
    "wof:name":"Two Gals Nail Skin Care Salon",
    "wof:placetype":"venue"
},
  "geometry": {"coordinates":[-98.340762,29.486816],"type":"Point"}
}