{
  "type": "Feature",
  "properties": {
    "iso:country":"US",
    "sg:address":"401 N Ave D",
    "sg:city":"Cross Plains",
    "sg:classifiers":[
        {
            "category":"Retail",
            "subcategory":"Auto Repair",
            "type":"Services"
        }
    ],
    "sg:phone":"+1 254 725 7606",
    "sg:postcode":"76443",
    "sg:province":"TX",
    "sg:tags":[
        "automotive"
    ],
    "wof:name":"Mikes Wrecking Auto",
    "wof:placetype":"venue"
},
  "geometry": {"coordinates":[-99.164131,32.129089],"type":"Point"}
}