{
  "type": "Feature",
  "properties": {
    "iso:country":"US",
    "sg:address":"111 S Victoria St",
    "sg:city":"San Diego",
    "sg:classifiers":[
        {
            "category":"Restaurant",
            "type":"Food & Drink"
        }
    ],
    "sg:phone":"+1 361 279 8877",
    "sg:postcode":"78384",
    "sg:province":"TX",
    "sg:tags":[
        "eating"
    ],
    "wof:name":"Jerry's Diner",
    "wof:placetype":"venue"
},
  "geometry": {"coordinates":[-98.236789,27.763498],"type":"Point"}
}