{
  "type": "Feature",
  "properties": {
    "iso:country":"US",
    "sg:address":"1612 W Shane St",
    "sg:city":"Alvin",
    "sg:classifiers":[
        {
            "category":"Place Of Worship",
            "type":"Public Place"
        }
    ],
    "sg:phone":"+1 281 585 5431",
    "sg:postcode":"77511",
    "sg:province":"TX",
    "sg:tags":[
        "church"
    ],
    "wof:name":"Rose Of Sharon Gospel I",
    "wof:placetype":"venue"
},
  "geometry": {"coordinates":[-95.260164,29.4129],"type":"Point"}
}