{
  "type": "Feature",
  "properties": {
    "iso:country":"US",
    "sg:address":"6 Sherborne Ln",
    "sg:city":"San Antonio",
    "sg:classifiers":[
        {
            "category":"Professional",
            "type":"Services"
        }
    ],
    "sg:phone":"+1 210 698 6649",
    "sg:postcode":"78257",
    "sg:province":"TX",
    "wof:name":"Fountains & Mountains Bui",
    "wof:placetype":"venue"
},
  "geometry": {"coordinates":[-98.616646,29.657422],"type":"Point"}
}