{
  "type": "Feature",
  "properties": {
    "iso:country":"US",
    "sg:address":"6155 Little Brandywine Creek",
    "sg:city":"San Antonio",
    "sg:classifiers":[
        {
            "category":"Professional",
            "subcategory":"Business Services",
            "type":"Services"
        }
    ],
    "sg:phone":"+1 210 646 8583",
    "sg:postcode":"78233",
    "sg:province":"TX",
    "wof:name":"Guion Enterprises",
    "wof:placetype":"venue"
},
  "geometry": {"coordinates":[-98.365205,29.553915],"type":"Point"}
}