{
  "type": "Feature",
  "properties": {
    "iso:country":"US",
    "sg:address":"338 S Main St",
    "sg:city":"Lumberton",
    "sg:classifiers":[
        {
            "category":"Building & Trades",
            "subcategory":"Construction",
            "type":"Services"
        }
    ],
    "sg:phone":"+1 409 755 1114",
    "sg:postcode":"77657",
    "sg:province":"TX",
    "sg:tags":[
        "altering",
        "remodeling",
        "contractor"
    ],
    "wof:name":"Robbins Remodeling",
    "wof:placetype":"venue"
},
  "geometry": {"coordinates":[-94.197284,30.250472],"type":"Point"}
}