{
  "type": "Feature",
  "properties": {
    "iso:country":"US",
    "sg:address":"2100 6th St",
    "sg:city":"Bay City",
    "sg:classifiers":[
        {
            "category":"Manufacturing",
            "subcategory":"Printing",
            "type":"Manufacturing & Wholesale Goods"
        }
    ],
    "sg:phone":"+1 979 245 2680",
    "sg:postcode":"77414",
    "sg:province":"TX",
    "sg:tags":[
        "commercial",
        "lithographic"
    ],
    "wof:name":"Lyle Printing",
    "wof:placetype":"venue"
},
  "geometry": {"coordinates":[-95.96389000000001,28.98203],"type":"Point"}
}