{
  "type": "Feature",
  "properties": {
    "iso:country":"US",
    "sg:address":"18619 Highway 290 E",
    "sg:city":"Elgin",
    "sg:classifiers":[
        {
            "category":"Restaurant",
            "type":"Food & Drink"
        }
    ],
    "sg:menulink":"http://www.allmenus.com/tx/austin/199962-long-john-silvers/menu/",
    "sg:phone":"+1 512 285 4165",
    "sg:postcode":"78621",
    "sg:province":"TX",
    "sg:tags":[
        "seafood",
        "american"
    ],
    "wof:name":"Long John Silver's",
    "wof:placetype":"venue"
},
  "geometry": {"coordinates":[-97.416113,30.350481],"type":"Point"}
}