{
  "type": "Feature",
  "properties": {
    "iso:country":"US",
    "sg:address":"4402 Broadway Blvd",
    "sg:city":"Garland",
    "sg:classifiers":[
        {
            "category":"Health Services",
            "subcategory":"Doctor",
            "type":"Services"
        }
    ],
    "sg:phone":"+1 972 488 8441",
    "sg:postcode":"75043",
    "sg:province":"TX",
    "sg:tags":[
        "physician",
        "surgeon",
        "medical"
    ],
    "wof:name":"Kathy A Toler MD",
    "wof:placetype":"venue"
},
  "geometry": {"coordinates":[-96.603343,32.861298],"type":"Point"}
}