{
  "type": "Feature",
  "properties": {
    "iso:country":"US",
    "sg:address":"303 E Young St",
    "sg:city":"Llano",
    "sg:classifiers":[
        {
            "category":"Restaurant",
            "type":"Food & Drink"
        }
    ],
    "sg:phone":"+1 325 247 1642",
    "sg:postcode":"78643",
    "sg:province":"TX",
    "wof:name":"Nanny's & Pa Pa's Tejas Tacos",
    "wof:placetype":"venue"
},
  "geometry": {"coordinates":[-98.672116,30.759557],"type":"Point"}
}