{
  "type": "Feature",
  "properties": {
    "iso:country":"US",
    "sg:address":"1938 W Dallas St",
    "sg:city":"Houston",
    "sg:classifiers":[
        {
            "category":"Banks & Credit Unions",
            "subcategory":"Bank",
            "type":"Services"
        }
    ],
    "sg:phone":"+1 713 926 7500",
    "sg:postcode":"77019",
    "sg:province":"TX",
    "wof:name":"Aquila Bancorp Inc",
    "wof:placetype":"venue"
},
  "geometry": {"coordinates":[-95.38786,29.757649],"type":"Point"}
}