{
  "type": "Feature",
  "properties": {
    "iso:country":"US",
    "sg:address":"1600 Commerce St",
    "sg:city":"Dallas",
    "sg:classifiers":[
        {
            "category":"Parking",
            "type":"Transportation"
        }
    ],
    "sg:phone":"+1 214 744 6168",
    "sg:postcode":"75201",
    "sg:province":"TX",
    "sg:tags":[
        "automobile"
    ],
    "wof:name":"Allright Parking",
    "wof:placetype":"venue"
},
  "geometry": {"coordinates":[-96.797501,32.780102],"type":"Point"}
}