{
  "type": "Feature",
  "properties": {
    "iso:country":"US",
    "sg:address":"2127 Broadway St",
    "sg:city":"Galveston",
    "sg:classifiers":[
        {
            "category":"Professional",
            "subcategory":"Lawyer & Legal Services",
            "type":"Services"
        }
    ],
    "sg:phone":"+1 409 762 4405",
    "sg:postcode":"77550",
    "sg:province":"TX",
    "wof:name":"Paul G Ash Jr Attonery At Law",
    "wof:placetype":"venue"
},
  "geometry": {"coordinates":[-94.790549,29.300413],"type":"Point"}
}