{
  "type": "Feature",
  "properties": {
    "iso:country":"US",
    "sg:address":"3231 Bee Caves Rd",
    "sg:city":"Austin",
    "sg:classifiers":[
        {
            "category":"Retail",
            "subcategory":"Laundry & Dry Cleaning",
            "type":"Services"
        }
    ],
    "sg:phone":"+1 512 327 4752",
    "sg:postcode":"78746",
    "sg:province":"TX",
    "sg:tags":[
        "drycleaning",
        "plant",
        "shoe",
        "parlor"
    ],
    "sg:website":"http://www.jackbrowncleaners.com",
    "wof:name":"Jack Brown Cleaners",
    "wof:placetype":"venue"
},
  "geometry": {"coordinates":[-97.799407,30.273693],"type":"Point"}
}