{
  "type": "Feature",
  "properties": {
    "iso:country":"US",
    "sg:address":"6310 Lemmon Ave",
    "sg:city":"Dallas",
    "sg:classifiers":[
        {
            "category":"Mining & Drilling",
            "type":"Manufacturing & Wholesale Goods"
        }
    ],
    "sg:phone":"+1 214 358 2622",
    "sg:postcode":"75209",
    "sg:province":"TX",
    "sg:tags":[
        "oil",
        "gas",
        "producer"
    ],
    "wof:name":"Triangle Productions",
    "wof:placetype":"venue"
},
  "geometry": {"coordinates":[-96.830018,32.834504],"type":"Point"}
}