{
  "type": "Feature",
  "properties": {
    "iso:country":"US",
    "sg:address":"743 FM 1058",
    "sg:city":"Friona",
    "sg:classifiers":[
        {
            "category":"Personal",
            "subcategory":"Beauty Salon",
            "type":"Services"
        }
    ],
    "sg:phone":"+1 806 289 5968",
    "sg:postcode":"79035",
    "sg:province":"TX",
    "sg:tags":[
        "shop",
        "photo",
        "studio",
        "portrait"
    ],
    "wof:name":"P and N Photography",
    "wof:placetype":"venue"
},
  "geometry": {"coordinates":[-102.926112,34.828216],"type":"Point"}
}