{
  "type": "Feature",
  "properties": {
    "iso:country":"US",
    "sg:address":"9039 Katy Fwy Ste 342",
    "sg:city":"Houston",
    "sg:classifiers":[
        {
            "category":"Building & Trades",
            "subcategory":"Construction",
            "type":"Services"
        }
    ],
    "sg:phone":"+1 713 461 5088",
    "sg:postcode":"77024",
    "sg:province":"TX",
    "sg:tags":[
        "contractor"
    ],
    "wof:name":"Blalock Builders",
    "wof:placetype":"venue"
},
  "geometry": {"coordinates":[-95.511438,29.783812],"type":"Point"}
}