{
  "type": "Feature",
  "properties": {
    "iso:country":"US",
    "sg:address":"202 Winkler Dr",
    "sg:city":"Houston",
    "sg:classifiers":[
        {
            "category":"Personal",
            "subcategory":"Nail Salon",
            "type":"Services"
        }
    ],
    "sg:phone":"+1 713 941 0265",
    "sg:postcode":"77087",
    "sg:province":"TX",
    "wof:name":"C & E Nail & Skincare",
    "wof:placetype":"venue"
},
  "geometry": {"coordinates":[-95.300336,29.701821],"type":"Point"}
}