{
  "type": "Feature",
  "properties": {
    "iso:country":"US",
    "sg:address":"2602 Kimbleton Ct",
    "sg:city":"Houston",
    "sg:classifiers":[
        {
            "category":"Professional",
            "subcategory":"Computer Services",
            "type":"Services"
        }
    ],
    "sg:phone":"+1 713 245 7823",
    "sg:postcode":"77082",
    "sg:province":"TX",
    "sg:tags":[
        "development",
        "software"
    ],
    "wof:name":"Instruments 2000 Inc",
    "wof:placetype":"venue"
},
  "geometry": {"coordinates":[-95.621808,29.733526],"type":"Point"}
}