{
  "type": "Feature",
  "properties": {
    "iso:country":"US",
    "sg:address":"891 Abrams Rd",
    "sg:city":"Richardson",
    "sg:classifiers":[
        {
            "category":"Organizations",
            "subcategory":"Religious Organization",
            "type":"Services"
        }
    ],
    "sg:phone":"+1 972 235 0951",
    "sg:postcode":"75081",
    "sg:province":"TX",
    "wof:name":"Christian World",
    "wof:placetype":"venue"
},
  "geometry": {"coordinates":[-96.731499,32.935902],"type":"Point"}
}