{
  "type": "Feature",
  "properties": {
    "iso:country":"US",
    "sg:address":"8954 Green Ray Dr",
    "sg:city":"Houston",
    "sg:classifiers":[
        {
            "category":"Building & Trades",
            "subcategory":"Construction",
            "type":"Services"
        }
    ],
    "sg:phone":"+1 281 859 7101",
    "sg:postcode":"77095",
    "sg:province":"TX",
    "sg:tags":[
        "industrial"
    ],
    "wof:name":"True Construction Inc",
    "wof:placetype":"venue"
},
  "geometry": {"coordinates":[-95.652574,29.912975],"type":"Point"}
}