{
  "type": "Feature",
  "properties": {
    "iso:country":"US",
    "sg:address":"725 E Belt Line Rd",
    "sg:city":"Cedar Hill",
    "sg:classifiers":[
        {
            "category":"Banks & Credit Unions",
            "subcategory":"Bank",
            "type":"Services"
        }
    ],
    "sg:phone":"+1 469 272 5858",
    "sg:postcode":"75104",
    "sg:province":"TX",
    "sg:website":"www.wachovia.com",
    "wof:name":"Wachovia",
    "wof:placetype":"venue"
},
  "geometry": {"coordinates":[-96.927075,32.590107],"type":"Point"}
}