{
  "type": "Feature",
  "properties": {
    "iso:country":"US",
    "sg:address":"6116 Luther Ln",
    "sg:city":"Dallas",
    "sg:classifiers":[
        {
            "category":"Personal",
            "subcategory":"Beauty Salon",
            "type":"Services"
        }
    ],
    "sg:phone":"+1 214 750 0040",
    "sg:postcode":"75225",
    "sg:province":"TX",
    "wof:name":"Beauty First",
    "wof:placetype":"venue"
},
  "geometry": {"coordinates":[-96.805854,32.863542],"type":"Point"}
}