{
  "type": "Feature",
  "properties": {
    "iso:country":"US",
    "sg:address":"8027 Gulf Fwy",
    "sg:city":"Houston",
    "sg:classifiers":[
        {
            "category":"Insurance",
            "subcategory":"Insurance Agent",
            "type":"Services"
        }
    ],
    "sg:phone":"+1 713 782 2138",
    "sg:postcode":"77017",
    "sg:province":"TX",
    "wof:name":"AABC Insurance",
    "wof:placetype":"venue"
},
  "geometry": {"coordinates":[-95.256023,29.65942],"type":"Point"}
}