{
  "type": "Feature",
  "properties": {
    "iso:country":"US",
    "sg:address":"5250 FM 920",
    "sg:city":"Weatherford",
    "sg:classifiers":[
        {
            "category":"Freight",
            "type":"Transportation"
        }
    ],
    "sg:phone":"+1 817 596 9297",
    "sg:postcode":"76088",
    "sg:province":"TX",
    "sg:tags":[
        "operator",
        "local",
        "trucking"
    ],
    "wof:name":"G&V Trucking",
    "wof:placetype":"venue"
},
  "geometry": {"coordinates":[-97.854598,32.825483],"type":"Point"}
}