{
  "type": "Feature",
  "properties": {
    "iso:country":"US",
    "sg:address":"307 N Meerscheidt St",
    "sg:city":"Dilley",
    "sg:classifiers":[
        {
            "category":"Place Of Worship",
            "subcategory":"Church",
            "type":"Public Place"
        },
        {
            "category":"Place Of Worship",
            "type":"Public Place"
        }
    ],
    "sg:phone":"+1 830 965 2091",
    "sg:postcode":"78017",
    "sg:province":"TX",
    "sg:tags":[
        "churches-methodist"
    ],
    "wof:name":"Bethenia United Methodist Church",
    "wof:placetype":"venue"
},
  "geometry": {"coordinates":[-99.166349,28.670548],"type":"Point"}
}