{
  "type": "Feature",
  "properties": {
    "iso:country":"US",
    "sg:address":"3307 Hancock Dr",
    "sg:city":"Austin",
    "sg:classifiers":[
        {
            "category":"Banks & Credit Unions",
            "subcategory":"Investment Brokerage",
            "type":"Services"
        }
    ],
    "sg:phone":"+1 512 476 2475",
    "sg:postcode":"78731",
    "sg:province":"TX",
    "sg:tags":[
        "security"
    ],
    "wof:name":"Cowden J Coley",
    "wof:placetype":"venue"
},
  "geometry": {"coordinates":[-97.760345,30.33292],"type":"Point"}
}