{
  "type": "Feature",
  "properties": {
    "iso:country":"US",
    "sg:address":"601 Scruggs",
    "sg:city":"Corsicana",
    "sg:classifiers":[
        {
            "category":"Building & Trades",
            "subcategory":"Plumbing",
            "type":"Services"
        }
    ],
    "sg:phone":"+1 903 654 1669",
    "sg:postcode":"75110",
    "sg:province":"TX",
    "sg:tags":[
        "conditioning",
        "air",
        "system",
        "contractor"
    ],
    "wof:name":"Scruggs Heating & Air Cond",
    "wof:placetype":"venue"
},
  "geometry": {"coordinates":[-96.381096,31.994359],"type":"Point"}
}