{
  "type": "Feature",
  "properties": {
    "iso:country":"US",
    "sg:address":"14817 Co Rd 210",
    "sg:city":"Danbury",
    "sg:classifiers":[
        {
            "category":"Real Estate",
            "subcategory":"Real Estate Operator",
            "type":"Services"
        }
    ],
    "sg:phone":"+1 979 922 1209",
    "sg:postcode":"77534",
    "sg:province":"TX",
    "sg:tags":[
        "dwelling"
    ],
    "wof:name":"Jds Realty Inc",
    "wof:placetype":"venue"
},
  "geometry": {"coordinates":[-95.30301,29.228461],"type":"Point"}
}