{
  "type": "Feature",
  "properties": {
    "iso:country":"US",
    "sg:address":"207 Palo Grande St",
    "sg:city":"San Antonio",
    "sg:classifiers":[
        {
            "category":"Professional",
            "subcategory":"Business Services",
            "type":"Services"
        }
    ],
    "sg:phone":"+1 210 494 5317",
    "sg:postcode":"78232",
    "sg:province":"TX",
    "sg:tags":[
        "interior",
        "consultant",
        "design",
        "decorator"
    ],
    "wof:name":"Shelley A Stewart Interiors",
    "wof:placetype":"venue"
},
  "geometry": {"coordinates":[-98.46580400000001,29.589469],"type":"Point"}
}