{
  "type": "Feature",
  "properties": {
    "iso:country":"US",
    "sg:address":"1235 Arizona Ave",
    "sg:city":"Dallas",
    "sg:classifiers":[
        {
            "category":"Banks & Credit Unions",
            "subcategory":"Financial Services",
            "type":"Services"
        }
    ],
    "sg:phone":"+1 214 943 6670",
    "sg:postcode":"75216",
    "sg:province":"TX",
    "sg:tags":[
        "broker",
        "mortgage"
    ],
    "wof:name":"Gateway Mortgage",
    "wof:placetype":"venue"
},
  "geometry": {"coordinates":[-96.817493,32.734184],"type":"Point"}
}