{
  "type": "Feature",
  "properties": {
    "iso:country":"US",
    "sg:address":"7223 Grapevine Hwy",
    "sg:city":"Richland Hills",
    "sg:classifiers":[
        {
            "category":"Personal",
            "subcategory":"Barber",
            "type":"Services"
        }
    ],
    "sg:phone":"+1 817 281 9913",
    "sg:postcode":"76180",
    "sg:province":"TX",
    "wof:name":"PRO Barber Shop",
    "wof:placetype":"venue"
},
  "geometry": {"coordinates":[-97.227453,32.824183],"type":"Point"}
}