{
  "type": "Feature",
  "properties": {
    "iso:country":"US",
    "sg:address":"12801 Mosielee St",
    "sg:city":"Houston",
    "sg:classifiers":[
        {
            "category":"Building & Trades",
            "subcategory":"Construction",
            "type":"Services"
        }
    ],
    "sg:phone":"+1 281 847 0885",
    "sg:postcode":"77086",
    "sg:province":"TX",
    "sg:tags":[
        "concrete",
        "staining",
        "contractor"
    ],
    "wof:name":"Guerreros Concrete",
    "wof:placetype":"venue"
},
  "geometry": {"coordinates":[-95.47337,29.918605],"type":"Point"}
}