{
  "type": "Feature",
  "properties": {
    "iso:country":"US",
    "sg:address":"608 Turner Dr",
    "sg:city":"Houston",
    "sg:classifiers":[
        {
            "category":"Organizations",
            "subcategory":"Religious Organization",
            "type":"Services"
        }
    ],
    "sg:phone":"+1 713 692 7388",
    "sg:postcode":"77076",
    "sg:province":"TX",
    "wof:name":"Mission Iluminedos Paz Y Gozo",
    "wof:placetype":"venue"
},
  "geometry": {"coordinates":[-95.366901,29.851739],"type":"Point"}
}