{
  "type": "Feature",
  "properties": {
    "iso:country":"US",
    "sg:address":"3401 SW Military Dr",
    "sg:city":"San Antonio",
    "sg:classifiers":[
        {
            "category":"Banks & Credit Unions",
            "subcategory":"Bank",
            "type":"Services"
        }
    ],
    "sg:phone":"+1 210 932 1010",
    "sg:postcode":"78211",
    "sg:province":"TX",
    "wof:name":"Southside Credit Union",
    "wof:placetype":"venue"
},
  "geometry": {"coordinates":[-98.558464,29.358165],"type":"Point"}
}