{
  "type": "Feature",
  "properties": {
    "iso:country":"US",
    "sg:address":"7166 Alameda Ave",
    "sg:city":"El Paso",
    "sg:classifiers":[
        {
            "category":"Autos & Motor Vehicles",
            "subcategory":"Automobile Sales",
            "type":"Retail Goods"
        }
    ],
    "sg:phone":"+1 915 771 0027",
    "sg:postcode":"79915",
    "sg:province":"TX",
    "sg:tags":[
        "used"
    ],
    "wof:name":"Quintero Auto Sales",
    "wof:placetype":"venue"
},
  "geometry": {"coordinates":[-106.38942299999999,31.751298],"type":"Point"}
}