{
  "type": "Feature",
  "properties": {
    "iso:country":"US",
    "sg:address":"1402 Covington St",
    "sg:city":"Wichita Falls",
    "sg:classifiers":[
        {
            "category":"Professional",
            "type":"Services"
        },
        {
            "category":"Shopping",
            "type":"Retail Goods"
        }
    ],
    "sg:phone":"+1 940 855 1756",
    "sg:postcode":"76306",
    "sg:province":"TX",
    "sg:tags":[
        "miscellaneous",
        "store"
    ],
    "wof:name":"Gildo's Bolas & Stars",
    "wof:placetype":"venue"
},
  "geometry": {"coordinates":[-98.542658,33.941152],"type":"Point"}
}