{
  "type": "Feature",
  "properties": {
    "iso:country":"US",
    "sg:address":"5420 W Loop S Ste 2500",
    "sg:city":"Bellaire",
    "sg:classifiers":[
        {
            "category":"Health Services",
            "subcategory":"Doctor",
            "type":"Services"
        }
    ],
    "sg:phone":"+1 713 383 7100",
    "sg:postcode":"77401",
    "sg:province":"TX",
    "sg:tags":[
        "orthopedist",
        "pediatrician"
    ],
    "wof:name":"Richard Francis, MD",
    "wof:placetype":"venue"
},
  "geometry": {"coordinates":[-95.460297,29.707599],"type":"Point"}
}