{
  "type": "Feature",
  "properties": {
    "iso:country":"US",
    "sg:address":"505 N Ave C",
    "sg:city":"Denver City",
    "sg:classifiers":[
        {
            "category":"Museum",
            "type":"Entertainment"
        }
    ],
    "sg:phone":"+1 806 592 2897",
    "sg:postcode":"79323",
    "sg:province":"TX",
    "sg:tags":[
        "gallery"
    ],
    "wof:name":"Denver City Museum",
    "wof:placetype":"venue"
},
  "geometry": {"coordinates":[-102.831853,32.970148],"type":"Point"}
}