{
  "type": "Feature",
  "properties": {
    "iso:country":"US",
    "sg:address":"15206 Highsprings Dr",
    "sg:city":"Houston",
    "sg:classifiers":[
        {
            "category":"Restaurant",
            "type":"Food & Drink"
        }
    ],
    "sg:phone":"+1 281 444 6700",
    "sg:postcode":"77068",
    "sg:province":"TX",
    "sg:tags":[
        "eating"
    ],
    "wof:name":"K&S Concessions",
    "wof:placetype":"venue"
},
  "geometry": {"coordinates":[-95.494748,30.002508],"type":"Point"}
}