{
  "type": "Feature",
  "properties": {
    "iso:country":"US",
    "sg:address":"702 Southland Ave",
    "sg:city":"Electra",
    "sg:classifiers":[
        {
            "category":"Mining & Drilling",
            "type":"Manufacturing & Wholesale Goods"
        }
    ],
    "sg:phone":"+1 940 495 2802",
    "sg:postcode":"76360",
    "sg:province":"TX",
    "sg:tags":[
        "field"
    ],
    "wof:name":"Tri-Mc Oil Compnay",
    "wof:placetype":"venue"
},
  "geometry": {"coordinates":[-98.92175,34.024776],"type":"Point"}
}