{
  "type": "Feature",
  "properties": {
    "iso:country":"US",
    "sg:address":"2315 Club Oaks Ct",
    "sg:city":"Mc Kinney",
    "sg:classifiers":[
        {
            "category":"Professional",
            "type":"Services"
        }
    ],
    "sg:phone":"+1 972 562 9175",
    "sg:postcode":"75070",
    "sg:province":"TX",
    "wof:name":"Four Cs Co",
    "wof:placetype":"venue"
},
  "geometry": {"coordinates":[-96.64870999999999,33.175182],"type":"Point"}
}