{
  "type": "Feature",
  "properties": {
    "iso:country":"US",
    "sg:address":"3207 Preston Ave",
    "sg:city":"Pasadena",
    "sg:classifiers":[
        {
            "category":"Shopping",
            "subcategory":"Used Merchandise",
            "type":"Retail Goods"
        }
    ],
    "sg:phone":"+1 281 998 2775",
    "sg:postcode":"77505",
    "sg:province":"TX",
    "sg:tags":[
        "antique"
    ],
    "wof:name":"Heritage Collectables & Antqs",
    "wof:placetype":"venue"
},
  "geometry": {"coordinates":[-95.171987,29.662549],"type":"Point"}
}