{
  "type": "Feature",
  "properties": {
    "iso:country":"US",
    "sg:address":"8035 Glenforest Ct",
    "sg:city":"Houston",
    "sg:classifiers":[
        {
            "category":"Retail",
            "subcategory":"Repair Shop",
            "type":"Services"
        }
    ],
    "sg:phone":"+1 713 644 9387",
    "sg:postcode":"77061",
    "sg:province":"TX",
    "wof:name":"Richard E Sharpe Repair Shop",
    "wof:placetype":"venue"
},
  "geometry": {"coordinates":[-95.27934,29.677172],"type":"Point"}
}