{
  "type": "Feature",
  "properties": {
    "iso:country":"US",
    "sg:address":"11490 FM 2868",
    "sg:city":"Flint",
    "sg:classifiers":[
        {
            "category":"Building & Trades",
            "subcategory":"Electrical",
            "type":"Services"
        }
    ],
    "sg:phone":"+1 903 894 9609",
    "sg:postcode":"75762",
    "sg:province":"TX",
    "sg:tags":[
        "electric",
        "contractor"
    ],
    "wof:name":"Steve Parnell Electric",
    "wof:placetype":"venue"
},
  "geometry": {"coordinates":[-95.359566,32.202474],"type":"Point"}
}