{
  "type": "Feature",
  "properties": {
    "iso:country":"US",
    "sg:address":"132 E Main St",
    "sg:city":"Whitesboro",
    "sg:classifiers":[
        {
            "category":"Insurance",
            "subcategory":"Hazard Insurance",
            "type":"Services"
        }
    ],
    "sg:phone":"+1 903 564 9131",
    "sg:postcode":"76273",
    "sg:province":"TX",
    "sg:tags":[
        "commercial",
        "business"
    ],
    "wof:name":"Smith Joy Insurance Agency",
    "wof:placetype":"venue"
},
  "geometry": {"coordinates":[-96.905672,33.655774],"type":"Point"}
}