{
  "type": "Feature",
  "properties": {
    "iso:country":"US",
    "sg:address":"203 S Oleander St",
    "sg:city":"Pecos",
    "sg:classifiers":[
        {
            "category":"Autos & Motor Vehicles",
            "subcategory":"Auto Supplies",
            "type":"Retail Goods"
        }
    ],
    "sg:phone":"+1 432 445 3427",
    "sg:postcode":"79772",
    "sg:province":"TX",
    "sg:tags":[
        "bo"
    ],
    "wof:name":"NAPA Auto Parts",
    "wof:placetype":"venue"
},
  "geometry": {"coordinates":[-103.502813,31.424099],"type":"Point"}
}