{
  "type": "Feature",
  "properties": {
    "iso:country":"US",
    "sg:address":"14605 Main St",
    "sg:city":"Houston",
    "sg:classifiers":[
        {
            "category":"Organizations",
            "subcategory":"Religious Organization",
            "type":"Services"
        }
    ],
    "sg:phone":"+1 713 283 0057",
    "sg:postcode":"77035",
    "sg:province":"TX",
    "wof:name":"Christ Annoited Word Christian",
    "wof:placetype":"venue"
},
  "geometry": {"coordinates":[-95.507485,29.630718],"type":"Point"}
}