{
  "type": "Feature",
  "properties": {
    "iso:country":"US",
    "sg:address":"349 Brown Creek Rd",
    "sg:city":"Weatherford",
    "sg:classifiers":[
        {
            "category":"Building & Trades",
            "subcategory":"Construction",
            "type":"Services"
        }
    ],
    "sg:phone":"+1 817 335 5711",
    "sg:postcode":"76085",
    "sg:province":"TX",
    "sg:tags":[
        "water",
        "well",
        "drilling"
    ],
    "wof:name":"Ft Worth Well Svc",
    "wof:placetype":"venue"
},
  "geometry": {"coordinates":[-97.715008,32.856827],"type":"Point"}
}