{
  "type": "Feature",
  "properties": {
    "iso:country":"US",
    "sg:address":"12722 Hunting Briar Dr",
    "sg:city":"Houston",
    "sg:classifiers":[
        {
            "category":"Building & Trades",
            "subcategory":"Landscaping Services",
            "type":"Services"
        }
    ],
    "sg:phone":"+1 281 495 6287",
    "sg:postcode":"77099",
    "sg:province":"TX",
    "wof:name":"Sunny Lawn Service",
    "wof:placetype":"venue"
},
  "geometry": {"coordinates":[-95.61001899999999,29.672459],"type":"Point"}
}