{
  "type": "Feature",
  "properties": {
    "iso:country":"US",
    "sg:address":"2306 State Hwy 36",
    "sg:city":"Sealy",
    "sg:classifiers":[
        {
            "category":"Banks & Credit Unions",
            "subcategory":"Bank",
            "type":"Services"
        }
    ],
    "sg:phone":"+1 979 627 7583",
    "sg:postcode":"77474",
    "sg:province":"TX",
    "sg:tags":[
        "cashing",
        "check"
    ],
    "wof:name":"Advance America",
    "wof:placetype":"venue"
},
  "geometry": {"coordinates":[-96.16176900000001,29.803828],"type":"Point"}
}