{
  "type": "Feature",
  "properties": {
    "iso:country":"US",
    "sg:address":"2411 Dowling St",
    "sg:city":"Houston",
    "sg:classifiers":[
        {
            "category":"Education",
            "subcategory":"College",
            "type":"Public Place"
        },
        {
            "category":"Organizations",
            "subcategory":"Community Association",
            "type":"Services"
        },
        {
            "category":"Organizations",
            "subcategory":"Membership Organization",
            "type":"Services"
        }
    ],
    "sg:phone":"+1 713 659 7736",
    "sg:postcode":"77004",
    "sg:province":"TX",
    "sg:tags":[
        "fraternal",
        "sorority",
        "housing",
        "fraternity",
        "student"
    ],
    "wof:name":"Grand Court Order Of Calanthe",
    "wof:placetype":"venue"
},
  "geometry": {"coordinates":[-95.361367,29.739073],"type":"Point"}
}