{
  "type": "Feature",
  "properties": {
    "iso:country":"US",
    "sg:address":"650 Bastrop Hwy",
    "sg:city":"Austin",
    "sg:classifiers":[
        {
            "category":"Building & Trades",
            "subcategory":"Construction",
            "type":"Services"
        }
    ],
    "sg:phone":"+1 512 386 9144",
    "sg:postcode":"78741",
    "sg:province":"TX",
    "sg:tags":[
        "foundation"
    ],
    "wof:name":"Straight Arrow Foundation Rpr",
    "wof:placetype":"venue"
},
  "geometry": {"coordinates":[-97.68633699999999,30.236402],"type":"Point"}
}