{
  "type": "Feature",
  "properties": {
    "iso:country":"US",
    "sg:address":"441 E FM 1462",
    "sg:city":"Rosharon",
    "sg:classifiers":[
        {
            "category":"Organizations",
            "subcategory":"Religious Organization",
            "type":"Services"
        }
    ],
    "sg:phone":"+1 281 595 3737",
    "sg:postcode":"77583",
    "sg:province":"TX",
    "sg:tags":[
        "church"
    ],
    "wof:name":"Elion Zion Church",
    "wof:placetype":"venue"
},
  "geometry": {"coordinates":[-95.457037,29.354214],"type":"Point"}
}