{
  "type": "Feature",
  "properties": {
    "iso:country":"US",
    "sg:address":"412 Westchase",
    "sg:city":"Grand Prairie",
    "sg:classifiers":[
        {
            "category":"Fast Food",
            "type":"Food & Drink"
        },
        {
            "category":"Restaurant",
            "type":"Food & Drink"
        }
    ],
    "sg:phone":"+1 972 642 0006",
    "sg:postcode":"75052",
    "sg:province":"TX",
    "sg:tags":[
        "traditional",
        "burger",
        "american"
    ],
    "wof:name":"Chili's",
    "wof:placetype":"venue"
},
  "geometry": {"coordinates":[-97.003642,32.673781],"type":"Point"}
}