{
  "type": "Feature",
  "properties": {
    "iso:country":"US",
    "sg:address":"4309 N 22nd St",
    "sg:city":"Mcallen",
    "sg:classifiers":[
        {
            "category":"Wholesale",
            "subcategory":"Machinery & Supplies",
            "type":"Manufacturing & Wholesale Goods"
        }
    ],
    "sg:phone":"+1 956 631 0545",
    "sg:postcode":"78504",
    "sg:province":"TX",
    "sg:tags":[
        "field",
        "oil"
    ],
    "wof:name":"South Texas Valve & Supply",
    "wof:placetype":"venue"
},
  "geometry": {"coordinates":[-98.23708999999999,26.243956],"type":"Point"}
}