{
  "type": "Feature",
  "properties": {
    "iso:country":"US",
    "sg:address":"902 S Main St",
    "sg:city":"Del Rio",
    "sg:classifiers":[
        {
            "category":"Organizations",
            "subcategory":"Membership Organization",
            "type":"Services"
        }
    ],
    "sg:phone":"+1 830 774 1156",
    "sg:postcode":"78840",
    "sg:province":"TX",
    "wof:name":"Early Childhood Intrvntn Eci P",
    "wof:placetype":"venue"
},
  "geometry": {"coordinates":[-100.898528,29.356262],"type":"Point"}
}