{
  "type": "Feature",
  "properties": {
    "iso:country":"US",
    "sg:address":"555 Rebel Rd",
    "sg:city":"Kyle",
    "sg:classifiers":[
        {
            "category":"Government",
            "subcategory":"Post Office",
            "type":"Public Place"
        }
    ],
    "sg:phone":"+1 512 268 5541",
    "sg:postcode":"78640",
    "sg:province":"TX",
    "sg:tags":[
        "postal",
        "us"
    ],
    "wof:name":"US Post Office",
    "wof:placetype":"venue"
},
  "geometry": {"coordinates":[-97.883315,29.991364],"type":"Point"}
}