{
  "type": "Feature",
  "properties": {
    "iso:country":"US",
    "sg:address":"1016 E Village Ct",
    "sg:city":"Pasadena",
    "sg:classifiers":[
        {
            "category":"Home & Garden",
            "subcategory":"Carpets & Floor Coverings",
            "type":"Retail Goods"
        }
    ],
    "sg:phone":"+1 713 750 9515",
    "sg:postcode":"77506",
    "sg:province":"TX",
    "sg:tags":[
        "hardwood"
    ],
    "wof:name":"Rio Bravo Hardwoods Inc",
    "wof:placetype":"venue"
},
  "geometry": {"coordinates":[-95.189835,29.694366],"type":"Point"}
}