{
  "type": "Feature",
  "properties": {
    "iso:country":"US",
    "sg:address":"1710 Country Club Dr",
    "sg:city":"Mansfield",
    "sg:classifiers":[
        {
            "category":"Insurance",
            "subcategory":"Insurance Agent",
            "type":"Services"
        }
    ],
    "sg:phone":"+1 817 473 9384",
    "sg:postcode":"76063",
    "sg:province":"TX",
    "wof:name":"John Kennedy Insurance Agency",
    "wof:placetype":"venue"
},
  "geometry": {"coordinates":[-97.109219,32.593467],"type":"Point"}
}