{
  "type": "Feature",
  "properties": {
    "iso:country":"US",
    "sg:address":"5100 W Eldorado Pkwy # 102",
    "sg:city":"Mckinney",
    "sg:classifiers":[
        {
            "category":"Real Estate",
            "subcategory":"Real Estate Services",
            "type":"Services"
        },
        {
            "category":"Real Estate",
            "subcategory":"Surveying",
            "type":"Services"
        }
    ],
    "sg:phone":"+1 214 213 2374",
    "sg:postcode":"75070",
    "sg:province":"TX",
    "sg:tags":[
        "industrial",
        "appraisers-commercial",
        "appraiser"
    ],
    "wof:name":"Legacy Appraisals",
    "wof:placetype":"venue"
},
  "geometry": {"coordinates":[-96.685391,33.173975],"type":"Point"}
}