{
  "type": "Feature",
  "properties": {
    "iso:country":"US",
    "sg:address":"524 Pasadena Blvd",
    "sg:city":"Pasadena",
    "sg:classifiers":[
        {
            "category":"Professional",
            "subcategory":"Engineering",
            "type":"Services"
        }
    ],
    "sg:phone":"+1 713 477 7640",
    "sg:postcode":"77506",
    "sg:province":"TX",
    "sg:tags":[
        "construction"
    ],
    "wof:name":"Triple Beam Engnring Prcrement",
    "wof:placetype":"venue"
},
  "geometry": {"coordinates":[-95.20106699999999,29.703235],"type":"Point"}
}