{
  "type": "Feature",
  "properties": {
    "iso:country":"US",
    "sg:address":"300 S Hickory Hill Rd",
    "sg:city":"Royse City",
    "sg:classifiers":[
        {
            "category":"Organizations",
            "subcategory":"Religious Organization",
            "type":"Services"
        }
    ],
    "sg:phone":"+1 972 635 2532",
    "sg:postcode":"75189",
    "sg:province":"TX",
    "sg:tags":[
        "church"
    ],
    "wof:name":"Trinity Baptist Church",
    "wof:placetype":"venue"
},
  "geometry": {"coordinates":[-96.34061199999999,32.971828],"type":"Point"}
}