{
  "type": "Feature",
  "properties": {
    "iso:country":"US",
    "sg:address":"4307 Overlook Ct",
    "sg:city":"Granbury",
    "sg:classifiers":[
        {
            "category":"Wholesale",
            "subcategory":"Non-durable Goods",
            "type":"Manufacturing & Wholesale Goods"
        }
    ],
    "sg:phone":"+1 817 326 3250",
    "sg:postcode":"76049",
    "sg:province":"TX",
    "wof:name":"TAS Trading Co",
    "wof:placetype":"venue"
},
  "geometry": {"coordinates":[-97.69484300000001,32.428823],"type":"Point"}
}