{
  "type": "Feature",
  "properties": {
    "iso:country":"US",
    "sg:address":"2815 Barge Ln",
    "sg:city":"Dallas",
    "sg:classifiers":[
        {
            "category":"Wholesale",
            "subcategory":"Machinery & Supplies",
            "type":"Manufacturing & Wholesale Goods"
        }
    ],
    "sg:phone":"+1 214 630 4517",
    "sg:postcode":"75212",
    "sg:province":"TX",
    "sg:tags":[
        "equipment",
        "establishment",
        "repair"
    ],
    "wof:name":"Brim Laundry Machinery Co",
    "wof:placetype":"venue"
},
  "geometry": {"coordinates":[-96.920765,32.776077],"type":"Point"}
}