{
  "type": "Feature",
  "properties": {
    "iso:country":"US",
    "sg:address":"11515 Burdine St",
    "sg:city":"Houston",
    "sg:classifiers":[
        {
            "category":"Wholesale",
            "subcategory":"Machinery & Supplies",
            "type":"Manufacturing & Wholesale Goods"
        },
        {
            "category":"Home & Garden",
            "subcategory":"Household Appliances",
            "type":"Retail Goods"
        }
    ],
    "sg:phone":"+1 713 266 0200",
    "sg:postcode":"77035",
    "sg:province":"TX",
    "sg:tags":[
        "equipment",
        "pump",
        "industrial"
    ],
    "wof:name":"Bornemann Pumps",
    "wof:placetype":"venue"
},
  "geometry": {"coordinates":[-95.481166,29.654612],"type":"Point"}
}