{
  "type": "Feature",
  "properties": {
    "iso:country":"US",
    "sg:address":"523 Benrus Blvd",
    "sg:city":"San Antonio",
    "sg:classifiers":[
        {
            "category":"Local Transit",
            "type":"Transportation"
        }
    ],
    "sg:phone":"+1 210 436 2065",
    "sg:postcode":"78228",
    "sg:province":"TX",
    "sg:tags":[
        "passenger"
    ],
    "wof:name":"Emerald Transportation",
    "wof:placetype":"venue"
},
  "geometry": {"coordinates":[-98.58528800000001,29.443847],"type":"Point"}
}