{
  "type": "Feature",
  "properties": {
    "iso:country":"US",
    "sg:address":"149 Hwy 3351 N",
    "sg:city":"Bergheim",
    "sg:classifiers":[
        {
            "category":"Building & Trades",
            "subcategory":"Construction",
            "type":"Services"
        }
    ],
    "sg:phone":"+1 830 336 2274",
    "sg:postcode":"78004",
    "sg:province":"TX",
    "sg:tags":[
        "residential",
        "nonresidential"
    ],
    "wof:name":"James Riebe Construction",
    "wof:placetype":"venue"
},
  "geometry": {"coordinates":[-98.57161000000001,29.835947],"type":"Point"}
}