{
  "type": "Feature",
  "properties": {
    "iso:country":"US",
    "sg:address":"812 S Crockett St",
    "sg:city":"Sherman",
    "sg:classifiers":[
        {
            "category":"Shopping",
            "subcategory":"Catalog Store",
            "type":"Retail Goods"
        }
    ],
    "sg:phone":"+1 903 893 1561",
    "sg:postcode":"75090",
    "sg:province":"TX",
    "sg:tags":[
        "house",
        "mail"
    ],
    "wof:name":"Early Payday Catalog Sales",
    "wof:placetype":"venue"
},
  "geometry": {"coordinates":[-96.60848,33.628115],"type":"Point"}
}