{
  "type": "Feature",
  "properties": {
    "iso:country":"US",
    "sg:address":"8090 Pat Booker Rd",
    "sg:city":"Live Oak",
    "sg:classifiers":[
        {
            "category":"Organizations",
            "subcategory":"Community Association",
            "type":"Services"
        }
    ],
    "sg:phone":"+1 210 599 9622",
    "sg:postcode":"78233",
    "sg:province":"TX",
    "sg:tags":[
        "club"
    ],
    "wof:name":"Coffe Club Cafe",
    "wof:placetype":"venue"
},
  "geometry": {"coordinates":[-98.33249000000001,29.562656],"type":"Point"}
}