{
  "type": "Feature",
  "properties": {
    "iso:country":"US",
    "sg:address":"206 W Wallace St",
    "sg:city":"San Saba",
    "sg:classifiers":[
        {
            "category":"Restaurant",
            "type":"Food & Drink"
        }
    ],
    "sg:phone":"+1 325 372 3369",
    "sg:postcode":"76877",
    "sg:province":"TX",
    "sg:tags":[
        "eating"
    ],
    "wof:name":"Aramark",
    "wof:placetype":"venue"
},
  "geometry": {"coordinates":[-98.722009,31.195846],"type":"Point"}
}