{
  "type": "Feature",
  "properties": {
    "iso:country":"US",
    "sg:address":"1415 3rd St",
    "sg:city":"Corpus Christi",
    "sg:classifiers":[
        {
            "category":"Health Services",
            "subcategory":"Clinic",
            "type":"Services"
        }
    ],
    "sg:phone":"+1 361 881 3280",
    "sg:postcode":"78404",
    "sg:province":"TX",
    "sg:tags":[
        "home",
        "care"
    ],
    "wof:name":"Christuf Spohn Health Network",
    "wof:placetype":"venue"
},
  "geometry": {"coordinates":[-97.39555,27.775869],"type":"Point"}
}