{
  "type": "Feature",
  "properties": {
    "iso:country":"US",
    "sg:address":"12 Scarborough Sq",
    "sg:city":"San Antonio",
    "sg:classifiers":[
        {
            "category":"Professional",
            "subcategory":"Management & Consulting",
            "type":"Services"
        }
    ],
    "sg:phone":"+1 210 828 3549",
    "sg:postcode":"78218",
    "sg:province":"TX",
    "wof:name":"West Finance Group Management",
    "wof:placetype":"venue"
},
  "geometry": {"coordinates":[-98.426343,29.506481],"type":"Point"}
}