{
  "type": "Feature",
  "properties": {
    "iso:country":"US",
    "sg:address":"3802 Highway 35 N",
    "sg:city":"Rockport",
    "sg:classifiers":[
        {
            "category":"Building & Trades",
            "subcategory":"Construction",
            "type":"Services"
        },
        {
            "category":"Recreation",
            "subcategory":"Campground",
            "type":"Entertainment"
        }
    ],
    "sg:phone":"+1 361 729 2760",
    "sg:postcode":"78382",
    "sg:province":"TX",
    "sg:tags":[
        "manufactured",
        "housing-communities",
        "recreational",
        "park",
        "vehicle"
    ],
    "wof:name":"Seahorse RV Park",
    "wof:placetype":"venue"
},
  "geometry": {"coordinates":[-97.041359,28.070049],"type":"Point"}
}