{
  "type": "Feature",
  "properties": {
    "iso:country":"US",
    "sg:address":"911 S Lasalle St",
    "sg:city":"Navasota",
    "sg:classifiers":[
        {
            "category":"Retail",
            "subcategory":"Laundry & Dry Cleaning",
            "type":"Services"
        }
    ],
    "sg:phone":"+1 936 825 8767",
    "sg:postcode":"77868",
    "sg:province":"TX",
    "sg:tags":[
        "drycleaning",
        "plant"
    ],
    "wof:name":"Kirks Cleaners",
    "wof:placetype":"venue"
},
  "geometry": {"coordinates":[-96.08438,30.382029],"type":"Point"}
}