{
  "type": "Feature",
  "properties": {
    "iso:country":"US",
    "sg:address":"2214 Paddock Way Dr",
    "sg:city":"Grand Prairie",
    "sg:classifiers":[
        {
            "category":"Professional",
            "type":"Services"
        }
    ],
    "sg:phone":"+1 972 660 3447",
    "sg:postcode":"75050",
    "sg:province":"TX",
    "sg:tags":[
        "establishment"
    ],
    "wof:name":"LET'STALK.COM",
    "wof:placetype":"venue"
},
  "geometry": {"coordinates":[-97.05486000000001,32.793039],"type":"Point"}
}