{
  "type": "Feature",
  "properties": {
    "iso:country":"US",
    "sg:address":"506 E Louisiana Ave",
    "sg:city":"Sweetwater",
    "sg:classifiers":[
        {
            "category":"Farming",
            "subcategory":"Farm & Veterinary Services",
            "type":"Manufacturing & Wholesale Goods"
        }
    ],
    "sg:phone":"+1 325 236 9752",
    "sg:postcode":"79556",
    "sg:province":"TX",
    "sg:tags":[
        "custom"
    ],
    "wof:name":"Martinez Alfredo Pena",
    "wof:placetype":"venue"
},
  "geometry": {"coordinates":[-100.39546900000001,32.460903],"type":"Point"}
}