{
  "type": "Feature",
  "properties": {
    "iso:country":"US",
    "sg:address":"3407 Navigation Blvd",
    "sg:city":"Houston",
    "sg:classifiers":[
        {
            "category":"Shopping",
            "type":"Retail Goods"
        }
    ],
    "sg:phone":"+1 713 223 8900",
    "sg:postcode":"77003",
    "sg:province":"TX",
    "sg:tags":[
        "art",
        "gallery",
        "dealer"
    ],
    "wof:name":"LNZ Distributors",
    "wof:placetype":"venue"
},
  "geometry": {"coordinates":[-95.336062,29.755384],"type":"Point"}
}