{
  "type": "Feature",
  "properties": {
    "iso:country":"US",
    "sg:address":"6420 Bandera Rd",
    "sg:city":"San Antonio",
    "sg:classifiers":[
        {
            "category":"Food & Beverages",
            "subcategory":"Specialty",
            "type":"Retail Goods"
        }
    ],
    "sg:phone":"+1 210 679 7137",
    "sg:postcode":"78238",
    "sg:province":"TX",
    "sg:tags":[
        "gourmet",
        "shop"
    ],
    "wof:name":"Gourmet Everyday",
    "wof:placetype":"venue"
},
  "geometry": {"coordinates":[-98.61074499999999,29.489714],"type":"Point"}
}