{
  "type": "Feature",
  "properties": {
    "iso:country":"US",
    "sg:address":"100 Hennessee Ln",
    "sg:city":"Angleton",
    "sg:classifiers":[
        {
            "category":"Shopping",
            "type":"Retail Goods"
        }
    ],
    "sg:phone":"+1 979 849 5156",
    "sg:postcode":"77515",
    "sg:province":"TX",
    "sg:tags":[
        "mexican"
    ],
    "wof:name":"Taste Of Mexico",
    "wof:placetype":"venue"
},
  "geometry": {"coordinates":[-95.51485599999999,29.215313],"type":"Point"}
}