{
  "type": "Feature",
  "properties": {
    "iso:country":"US",
    "sg:address":"12101 Fondren Rd",
    "sg:city":"Houston",
    "sg:classifiers":[
        {
            "category":"Professional",
            "type":"Services"
        }
    ],
    "sg:phone":"+1 713 200 4052",
    "sg:postcode":"77035",
    "sg:province":"TX",
    "wof:name":"Flashy Watches",
    "wof:placetype":"venue"
},
  "geometry": {"coordinates":[-95.50832699999999,29.647304],"type":"Point"}
}