{
  "type": "Feature",
  "properties": {
    "iso:country":"US",
    "sg:address":"3141 Hood St",
    "sg:city":"Dallas",
    "sg:classifiers":[
        {
            "category":"Insurance",
            "subcategory":"Insurance Agent",
            "type":"Services"
        }
    ],
    "sg:phone":"+1 214 520 2345",
    "sg:postcode":"75219",
    "sg:province":"TX",
    "wof:name":"Rekerdres & Sons Insurance",
    "wof:placetype":"venue"
},
  "geometry": {"coordinates":[-96.80549000000001,32.808153],"type":"Point"}
}