{
  "type": "Feature",
  "properties": {
    "iso:country":"US",
    "sg:address":"3401 Custer Rd",
    "sg:city":"Plano",
    "sg:classifiers":[
        {
            "category":"Insurance",
            "subcategory":"Hazard Insurance",
            "type":"Services"
        }
    ],
    "sg:phone":"+1 972 540 1117",
    "sg:postcode":"75023",
    "sg:province":"TX",
    "sg:tags":[
        "bond"
    ],
    "wof:name":"Bail Bonds Unlimited",
    "wof:placetype":"venue"
},
  "geometry": {"coordinates":[-96.73347,33.043016],"type":"Point"}
}