{
  "type": "Feature",
  "properties": {
    "iso:country":"US",
    "sg:address":"3901 Tuscany Ct",
    "sg:city":"Arlington",
    "sg:classifiers":[
        {
            "category":"Organizations",
            "subcategory":"Professional Association",
            "type":"Services"
        }
    ],
    "sg:phone":"+1 817 572 0700",
    "sg:postcode":"76016",
    "sg:province":"TX",
    "sg:tags":[
        "educational",
        "seminar"
    ],
    "wof:name":"Lone Star Pets Inc",
    "wof:placetype":"venue"
},
  "geometry": {"coordinates":[-97.169365,32.683836],"type":"Point"}
}