{
  "type": "Feature",
  "properties": {
    "iso:country":"US",
    "sg:address":"7922 State Hwy 6",
    "sg:city":"Houston",
    "sg:classifiers":[
        {
            "category":"Government",
            "subcategory":"Fire Station",
            "type":"Public Place"
        }
    ],
    "sg:phone":"+1 713 466 6161",
    "sg:postcode":"77095",
    "sg:province":"TX",
    "sg:tags":[
        "protection"
    ],
    "wof:name":"Communications Department",
    "wof:placetype":"venue"
},
  "geometry": {"coordinates":[-95.639222,29.894161],"type":"Point"}
}