{
  "type": "Feature",
  "properties": {
    "iso:country":"US",
    "sg:address":"107 S Elizabeth Ave",
    "sg:city":"Kirbyville",
    "sg:classifiers":[
        {
            "category":"Government",
            "subcategory":"Office",
            "type":"Public Place"
        }
    ],
    "sg:phone":"+1 409 423 6191",
    "sg:postcode":"75956",
    "sg:province":"TX",
    "sg:tags":[
        "city"
    ],
    "wof:name":"Kirbyville City Hall",
    "wof:placetype":"venue"
},
  "geometry": {"coordinates":[-93.892819,30.660595],"type":"Point"}
}