{
  "type": "Feature",
  "properties": {
    "iso:country":"US",
    "sg:address":"2400 N Macarthur Blvd",
    "sg:city":"Irving",
    "sg:classifiers":[
        {
            "category":"Manufacturing",
            "subcategory":"Printing",
            "type":"Manufacturing & Wholesale Goods"
        }
    ],
    "sg:phone":"+1 972 867 3642",
    "sg:postcode":"75062",
    "sg:province":"TX",
    "sg:tags":[
        "newsletter",
        "publishing"
    ],
    "wof:name":"Well Dunn Creations",
    "wof:placetype":"venue"
},
  "geometry": {"coordinates":[-96.959097,32.84158],"type":"Point"}
}