{
  "type": "Feature",
  "properties": {
    "iso:country":"US",
    "sg:address":"9901 Valley Ranch Pkwy W",
    "sg:city":"Irving",
    "sg:classifiers":[
        {
            "category":"Shopping",
            "type":"Retail Goods"
        }
    ],
    "sg:phone":"+1 972 401 0005",
    "sg:postcode":"75063",
    "sg:province":"TX",
    "sg:tags":[
        "product",
        "wood"
    ],
    "wof:name":"Mjb Wood Grp Inc",
    "wof:placetype":"venue"
},
  "geometry": {"coordinates":[-96.95513099999999,32.940281],"type":"Point"}
}