{
  "type": "Feature",
  "properties": {
    "iso:country":"US",
    "sg:address":"840 Bennett Rd",
    "sg:city":"Howe",
    "sg:classifiers":[
        {
            "category":"Building & Trades",
            "subcategory":"Landscaping Services",
            "type":"Services"
        }
    ],
    "sg:phone":"+1 903 870 7991",
    "sg:postcode":"75459",
    "sg:province":"TX",
    "wof:name":"Adans Landscaping",
    "wof:placetype":"venue"
},
  "geometry": {"coordinates":[-96.57952,33.562386],"type":"Point"}
}