{
  "type": "Feature",
  "properties": {
    "iso:country":"US",
    "sg:address":"113 Laughlin Rd",
    "sg:city":"Eagle Lake",
    "sg:classifiers":[
        {
            "category":"Professional",
            "type":"Services"
        }
    ],
    "sg:phone":"+1 979 234 5930",
    "sg:postcode":"77434",
    "sg:province":"TX",
    "wof:name":"Charles V Corman",
    "wof:placetype":"venue"
},
  "geometry": {"coordinates":[-96.33884500000001,29.581297],"type":"Point"}
}