{
  "type": "Feature",
  "properties": {
    "iso:country":"US",
    "sg:address":"4211 Joe Ramsey Blvd E",
    "sg:city":"Greenville",
    "sg:classifiers":[
        {
            "category":"Health Services",
            "subcategory":"Clinic",
            "type":"Services"
        }
    ],
    "sg:phone":"+1 903 408 7970",
    "sg:postcode":"75401",
    "sg:province":"TX",
    "sg:tags":[
        "osteopathic"
    ],
    "wof:name":"Brookshire, Ralph",
    "wof:placetype":"venue"
},
  "geometry": {"coordinates":[-96.12296600000001,33.123304],"type":"Point"}
}