{
  "type": "Feature",
  "properties": {
    "iso:country":"US",
    "sg:address":"405 E Marshall St",
    "sg:city":"Gilmer",
    "sg:classifiers":[
        {
            "category":"Autos & Motor Vehicles",
            "subcategory":"Automobile Sales",
            "type":"Retail Goods"
        }
    ],
    "sg:phone":"+1 903 843 6071",
    "sg:postcode":"75644",
    "sg:province":"TX",
    "sg:tags":[
        "used"
    ],
    "wof:name":"Walkers Auto Sales",
    "wof:placetype":"venue"
},
  "geometry": {"coordinates":[-94.941525,32.728722],"type":"Point"}
}