{
  "type": "Feature",
  "properties": {
    "iso:country":"US",
    "sg:address":"14220 FM 1314",
    "sg:city":"Conroe",
    "sg:classifiers":[
        {
            "category":"Recreation",
            "type":"Entertainment"
        }
    ],
    "sg:phone":"+1 936 446 3600",
    "sg:postcode":"77302",
    "sg:province":"TX",
    "sg:tags":[
        "riding",
        "academy"
    ],
    "wof:name":"Foxcroft Carriage Co",
    "wof:placetype":"venue"
},
  "geometry": {"coordinates":[-95.39158999999999,30.249322],"type":"Point"}
}