{
  "type": "Feature",
  "properties": {
    "iso:country":"US",
    "sg:address":"2900 Municipal St",
    "sg:city":"Dallas",
    "sg:classifiers":[
        {
            "category":"Government",
            "subcategory":"Office",
            "type":"Public Place"
        }
    ],
    "sg:phone":"+1 214 670 8681",
    "sg:postcode":"75215",
    "sg:province":"TX",
    "sg:tags":[
        "management"
    ],
    "wof:name":"Water Utilities",
    "wof:placetype":"venue"
},
  "geometry": {"coordinates":[-96.747547,32.738358],"type":"Point"}
}