{
  "type": "Feature",
  "properties": {
    "iso:country":"US",
    "sg:address":"1403 N Tenneha Ave",
    "sg:city":"Tyler",
    "sg:classifiers":[
        {
            "category":"Organizations",
            "subcategory":"Religious Organization",
            "type":"Services"
        }
    ],
    "sg:phone":"+1 903 595 2612",
    "sg:postcode":"75702",
    "sg:province":"TX",
    "sg:tags":[
        "church"
    ],
    "wof:name":"St Peter Claver Catholic Chr",
    "wof:placetype":"venue"
},
  "geometry": {"coordinates":[-95.307992,32.363605],"type":"Point"}
}