{
  "type": "Feature",
  "properties": {
    "iso:country":"US",
    "sg:address":"6102 FM 3009",
    "sg:city":"Schertz",
    "sg:classifiers":[
        {
            "category":"Health Services",
            "subcategory":"Optometrist",
            "type":"Services"
        }
    ],
    "sg:phone":"+1 210 651 3926",
    "sg:postcode":"78154",
    "sg:province":"TX",
    "wof:name":"Diamond K Eyecare",
    "wof:placetype":"venue"
},
  "geometry": {"coordinates":[-98.28031799999999,29.605953],"type":"Point"}
}