{
  "type": "Feature",
  "properties": {
    "iso:country":"US",
    "sg:address":"119 Pittsburg St",
    "sg:city":"Dallas",
    "sg:classifiers":[
        {
            "category":"Casinos & Gambling",
            "type":"Entertainment"
        }
    ],
    "sg:phone":"+1 214 741 3585",
    "sg:postcode":"75207",
    "sg:province":"TX",
    "wof:name":"Arrangers The",
    "wof:placetype":"venue"
},
  "geometry": {"coordinates":[-96.82068200000001,32.785959],"type":"Point"}
}