{
  "type": "Feature",
  "properties": {
    "iso:country":"US",
    "sg:address":"5740 Co Rd 898",
    "sg:city":"West Columbia",
    "sg:classifiers":[
        {
            "category":"Shopping",
            "subcategory":"Gifts & Souvenirs",
            "type":"Retail Goods"
        }
    ],
    "sg:phone":"+1 979 345 3703",
    "sg:postcode":"77486",
    "sg:province":"TX",
    "sg:tags":[
        "home",
        "decor",
        "collector",
        "sales"
    ],
    "wof:name":"Sultans Treasure",
    "wof:placetype":"venue"
},
  "geometry": {"coordinates":[-95.74712700000001,29.151381],"type":"Point"}
}