{
  "type": "Feature",
  "properties": {
    "iso:country":"US",
    "sg:address":"2435 College Hills Blvd",
    "sg:city":"San Angelo",
    "sg:classifiers":[
        {
            "category":"Retail",
            "subcategory":"Repair Shop",
            "type":"Services"
        }
    ],
    "sg:phone":"+1 325 944 7088",
    "sg:postcode":"76904",
    "sg:province":"TX",
    "sg:tags":[
        "television",
        "radio"
    ],
    "wof:name":"A A TV Repair",
    "wof:placetype":"venue"
},
  "geometry": {"coordinates":[-100.479163,31.437435],"type":"Point"}
}