{
  "type": "Feature",
  "properties": {
    "iso:country":"US",
    "sg:address":"706 Main St",
    "sg:city":"Canadian",
    "sg:classifiers":[
        {
            "category":"Place Of Worship",
            "subcategory":"Church",
            "type":"Public Place"
        },
        {
            "category":"Place Of Worship",
            "type":"Public Place"
        }
    ],
    "sg:phone":"+1 806 323 8388",
    "sg:postcode":"79014",
    "sg:province":"TX",
    "sg:tags":[
        "churches-baptist-general",
        "churches-baptist"
    ],
    "sg:website":"http://www.abc-usa.org",
    "wof:name":"First Baptist Church",
    "wof:placetype":"venue"
},
  "geometry": {"coordinates":[-100.38029,35.911563],"type":"Point"}
}