{
  "type": "Feature",
  "properties": {
    "iso:country":"US",
    "sg:address":"950 Market Pl",
    "sg:city":"Irving",
    "sg:classifiers":[
        {
            "category":"Fast Food",
            "type":"Food & Drink"
        }
    ],
    "sg:phone":"+1 214 574 5300",
    "sg:postcode":"75038",
    "sg:province":"TX",
    "sg:website":"www.steaknshake.com",
    "wof:name":"Steak N Shake",
    "wof:placetype":"venue"
},
  "geometry": {"coordinates":[-96.961219,32.917965],"type":"Point"}
}