{
  "type": "Feature",
  "properties": {
    "iso:country":"US",
    "sg:address":"3411 W Wall St",
    "sg:city":"Midland",
    "sg:classifiers":[
        {
            "category":"Travel",
            "subcategory":"Hotels & Motels",
            "type":"Entertainment"
        }
    ],
    "sg:phone":"+1 432 694 0360",
    "sg:postcode":"79701",
    "sg:province":"TX",
    "sg:tags":[
        "operation"
    ],
    "wof:name":"Texas Motel & Apartments",
    "wof:placetype":"venue"
},
  "geometry": {"coordinates":[-102.10993999999999,31.982001],"type":"Point"}
}