{
  "type": "Feature",
  "properties": {
    "iso:country":"US",
    "sg:address":"237 Dean St",
    "sg:city":"San Antonio",
    "sg:classifiers":[
        {
            "category":"Retail",
            "subcategory":"Auto Repair",
            "type":"Services"
        }
    ],
    "sg:phone":"+1 210 656 0686",
    "sg:postcode":"78212",
    "sg:province":"TX",
    "sg:tags":[
        "automotive"
    ],
    "wof:name":"Falcon Radiator",
    "wof:placetype":"venue"
},
  "geometry": {"coordinates":[-98.495244,29.476599],"type":"Point"}
}