{
  "type": "Feature",
  "properties": {
    "iso:country":"US",
    "sg:address":"5342 Miller Ave",
    "sg:city":"Dallas",
    "sg:classifiers":[
        {
            "category":"Freight",
            "type":"Transportation"
        }
    ],
    "sg:phone":"+1 214 828 1175",
    "sg:postcode":"75206",
    "sg:province":"TX",
    "sg:tags":[
        "storage",
        "mover",
        "local",
        "trucking"
    ],
    "wof:name":"Kimber Relocation",
    "wof:placetype":"venue"
},
  "geometry": {"coordinates":[-96.778198,32.821201],"type":"Point"}
}