{
  "type": "Feature",
  "properties": {
    "iso:country":"US",
    "sg:address":"3703 Big Piney Dr",
    "sg:city":"Humble",
    "sg:classifiers":[
        {
            "category":"Professional",
            "type":"Services"
        }
    ],
    "sg:phone":"+1 281 360 8572",
    "sg:postcode":"77345",
    "sg:province":"TX",
    "wof:name":"Accessories By Claire",
    "wof:placetype":"venue"
},
  "geometry": {"coordinates":[-95.16600099999999,30.065713],"type":"Point"}
}