{
  "type": "Feature",
  "properties": {
    "iso:country":"US",
    "sg:address":"1315 N Milam St",
    "sg:city":"Seguin",
    "sg:classifiers":[
        {
            "category":"Retail",
            "subcategory":"Laundry & Dry Cleaning",
            "type":"Services"
        }
    ],
    "sg:phone":"+1 830 372 0844",
    "sg:postcode":"78155",
    "sg:province":"TX",
    "sg:tags":[
        "power"
    ],
    "wof:name":"Seguin General Store",
    "wof:placetype":"venue"
},
  "geometry": {"coordinates":[-97.962262,29.580982],"type":"Point"}
}