{
  "type": "Feature",
  "properties": {
    "iso:country":"US",
    "sg:address":"9516 Hopeland Dr",
    "sg:city":"Austin",
    "sg:classifiers":[
        {
            "category":"Professional",
            "type":"Services"
        }
    ],
    "sg:phone":"+1 512 394 9050",
    "sg:postcode":"78749",
    "sg:province":"TX",
    "wof:name":"Austin Cdwg",
    "wof:placetype":"venue"
},
  "geometry": {"coordinates":[-97.881297,30.204866],"type":"Point"}
}