{
  "type": "Feature",
  "properties": {
    "iso:country":"US",
    "sg:address":"1836 Hillcrest St",
    "sg:city":"Fort Worth",
    "sg:classifiers":[
        {
            "category":"Professional",
            "subcategory":"Business Services",
            "type":"Services"
        }
    ],
    "sg:phone":"+1 817 731 2965",
    "sg:postcode":"76107",
    "sg:province":"TX",
    "wof:name":"Momentum Group",
    "wof:placetype":"venue"
},
  "geometry": {"coordinates":[-97.381201,32.741975],"type":"Point"}
}