{
  "type": "Feature",
  "properties": {
    "iso:country":"US",
    "sg:address":"15393 State Hwy 322 N",
    "sg:city":"Longview",
    "sg:classifiers":[
        {
            "category":"Building & Trades",
            "subcategory":"Plumbing",
            "type":"Services"
        }
    ],
    "sg:phone":"+1 903 643 9690",
    "sg:postcode":"75603",
    "sg:province":"TX",
    "sg:tags":[
        "conditioning",
        "contractor",
        "system",
        "air"
    ],
    "wof:name":"S & H A/C Contractors",
    "wof:placetype":"venue"
},
  "geometry": {"coordinates":[-94.722888,32.359059],"type":"Point"}
}