{
  "type": "Feature",
  "properties": {
    "iso:country":"US",
    "sg:address":"1707 Centennial Blvd",
    "sg:city":"San Antonio",
    "sg:classifiers":[
        {
            "category":"Social Services",
            "subcategory":"Child Care",
            "type":"Services"
        }
    ],
    "sg:phone":"+1 210 924 4443",
    "sg:postcode":"78211",
    "sg:province":"TX",
    "wof:name":"St Anthony Day Care/Learning",
    "wof:placetype":"venue"
},
  "geometry": {"coordinates":[-98.53897499999999,29.37687],"type":"Point"}
}