{
  "type": "Feature",
  "properties": {
    "iso:country":"US",
    "sg:address":"2222 Rivas St",
    "sg:city":"San Antonio",
    "sg:classifiers":[
        {
            "category":"Organizations",
            "subcategory":"Religious Organization",
            "type":"Services"
        }
    ],
    "sg:phone":"+1 210 432 0826",
    "sg:postcode":"78228",
    "sg:province":"TX",
    "wof:name":"Victory Chapel Inc",
    "wof:placetype":"venue"
},
  "geometry": {"coordinates":[-98.545485,29.441352],"type":"Point"}
}