{
  "type": "Feature",
  "properties": {
    "iso:country":"US",
    "sg:address":"2110 W Northwest Hwy",
    "sg:city":"Dallas",
    "sg:classifiers":[
        {
            "category":"Education",
            "subcategory":"Dance Studio",
            "type":"Public Place"
        },
        {
            "category":"Bars & Pubs",
            "type":"Food & Drink"
        }
    ],
    "sg:phone":"+1 972 556 9099",
    "sg:postcode":"75220",
    "sg:province":"TX",
    "sg:tags":[
        "club",
        "night"
    ],
    "sg:website":"www.toprailballroom.com",
    "wof:name":"Ole Top Rail Ballroom",
    "wof:placetype":"venue"
},
  "geometry": {"coordinates":[-96.90269499999999,32.865314],"type":"Point"}
}