{
  "type": "Feature",
  "properties": {
    "iso:country":"US",
    "sg:address":"799 N Wills St",
    "sg:city":"Wills Point",
    "sg:classifiers":[
        {
            "category":"Retail",
            "subcategory":"Repair Shop",
            "type":"Services"
        }
    ],
    "sg:phone":"+1 903 873 3677",
    "sg:postcode":"75169",
    "sg:province":"TX",
    "sg:tags":[
        "electrical"
    ],
    "wof:name":"East Texas Appliance Service",
    "wof:placetype":"venue"
},
  "geometry": {"coordinates":[-96.01074300000001,32.715299],"type":"Point"}
}