{
  "type": "Feature",
  "properties": {
    "iso:country":"US",
    "sg:address":"13944 Schiller Rd",
    "sg:city":"Houston",
    "sg:classifiers":[
        {
            "category":"Organizations",
            "subcategory":"Membership Organization",
            "type":"Services"
        }
    ],
    "sg:phone":"+1 281 589 7700",
    "sg:postcode":"77082",
    "sg:province":"TX",
    "wof:name":"Houston Burga Bari Society",
    "wof:placetype":"venue"
},
  "geometry": {"coordinates":[-95.63772899999999,29.718626],"type":"Point"}
}