{
  "type": "Feature",
  "properties": {
    "iso:country":"US",
    "sg:address":"1121 Capitol St",
    "sg:city":"Houston",
    "sg:classifiers":[
        {
            "category":"Professional",
            "subcategory":"Lawyer & Legal Services",
            "type":"Services"
        }
    ],
    "sg:phone":"+1 713 226 8888",
    "sg:postcode":"77002",
    "sg:province":"TX",
    "wof:name":"Don Elliott Autoworld",
    "wof:placetype":"venue"
},
  "geometry": {"coordinates":[-95.362021,29.758675],"type":"Point"}
}