{
  "type": "Feature",
  "properties": {
    "iso:country":"US",
    "sg:address":"107 S Texas Ave",
    "sg:city":"Mercedes",
    "sg:classifiers":[
        {
            "category":"Retail",
            "subcategory":"Auto Rental",
            "type":"Services"
        }
    ],
    "sg:phone":"+1 956 825 9358",
    "sg:postcode":"78570",
    "sg:province":"TX",
    "sg:tags":[
        "passenger",
        "car"
    ],
    "wof:name":"Amigo Rent To Own",
    "wof:placetype":"venue"
},
  "geometry": {"coordinates":[-97.913545,26.150642],"type":"Point"}
}