{
  "type": "Feature",
  "properties": {
    "iso:country":"US",
    "sg:address":"2603 W Berry St",
    "sg:city":"Fort Worth",
    "sg:classifiers":[
        {
            "category":"Shopping",
            "subcategory":"Pharmacy",
            "type":"Retail Goods"
        }
    ],
    "sg:phone":"+1 817 923 8259",
    "sg:postcode":"76109",
    "sg:province":"TX",
    "sg:tags":[
        "drug",
        "store"
    ],
    "wof:name":"Eckerd",
    "wof:placetype":"venue"
},
  "geometry": {"coordinates":[-97.35548,32.706021],"type":"Point"}
}