{
  "type": "Feature",
  "properties": {
    "iso:country":"US",
    "sg:address":"1707 Roosevelt Ave",
    "sg:city":"San Antonio",
    "sg:classifiers":[
        {
            "category":"Travel",
            "subcategory":"Hotels & Motels",
            "type":"Entertainment"
        }
    ],
    "sg:phone":"+1 210 532 4246",
    "sg:postcode":"78210",
    "sg:province":"TX",
    "sg:tags":[
        "operation"
    ],
    "wof:name":"Prado Motel",
    "wof:placetype":"venue"
},
  "geometry": {"coordinates":[-98.48559,29.386726],"type":"Point"}
}