{
  "type": "Feature",
  "properties": {
    "iso:country":"US",
    "sg:address":"7801 Briarstone Ct",
    "sg:city":"Fort Worth",
    "sg:classifiers":[
        {
            "category":"Restaurant",
            "type":"Food & Drink"
        }
    ],
    "sg:phone":"+1 817 429 6093",
    "sg:postcode":"76112",
    "sg:province":"TX",
    "sg:tags":[
        "eating"
    ],
    "wof:name":"Ketan Corp",
    "wof:placetype":"venue"
},
  "geometry": {"coordinates":[-97.186204,32.755872],"type":"Point"}
}