{
  "type": "Feature",
  "properties": {
    "iso:country":"US",
    "sg:address":"1101 S Koenigheim St",
    "sg:city":"San Angelo",
    "sg:classifiers":[
        {
            "category":"Wholesale",
            "subcategory":"Stationery",
            "type":"Manufacturing & Wholesale Goods"
        }
    ],
    "sg:phone":"+1 325 655 6608",
    "sg:postcode":"76903",
    "sg:province":"TX",
    "sg:tags":[
        "supply",
        "p",
        "blueprinting",
        "commercial",
        "offset"
    ],
    "wof:name":"Reproduction Center",
    "wof:placetype":"venue"
},
  "geometry": {"coordinates":[-100.44058200000001,31.449709],"type":"Point"}
}