{
  "type": "Feature",
  "properties": {
    "iso:country":"US",
    "sg:address":"1211 Windsong Trl",
    "sg:city":"Richardson",
    "sg:classifiers":[
        {
            "category":"Manufacturing",
            "subcategory":"Printing",
            "type":"Manufacturing & Wholesale Goods"
        }
    ],
    "sg:phone":"+1 972 907 8056",
    "sg:postcode":"75081",
    "sg:province":"TX",
    "sg:tags":[
        "newspaper"
    ],
    "wof:name":"Mark A Daily",
    "wof:placetype":"venue"
},
  "geometry": {"coordinates":[-96.705985,32.942249],"type":"Point"}
}