{
  "type": "Feature",
  "properties": {
    "iso:country":"US",
    "sg:address":"1367 Jasmin Ln",
    "sg:city":"San Elizario",
    "sg:classifiers":[
        {
            "category":"Wholesale",
            "subcategory":"Toys & Hobbies",
            "type":"Manufacturing & Wholesale Goods"
        }
    ],
    "sg:phone":"+1 915 851 3311",
    "sg:postcode":"79849",
    "sg:province":"TX",
    "wof:name":"Angelina Rangel",
    "wof:placetype":"venue"
},
  "geometry": {"coordinates":[-106.28302600000001,31.579508],"type":"Point"}
}