{
  "type": "Feature",
  "properties": {
    "iso:country":"US",
    "sg:address":"2911 N 19th St",
    "sg:city":"Waco",
    "sg:classifiers":[
        {
            "category":"Organizations",
            "subcategory":"Community Association",
            "type":"Services"
        }
    ],
    "sg:phone":"+1 254 752 4793",
    "sg:postcode":"76708",
    "sg:province":"TX",
    "sg:tags":[
        "club"
    ],
    "wof:name":"LA Onda Club",
    "wof:placetype":"venue"
},
  "geometry": {"coordinates":[-97.16682299999999,31.571974],"type":"Point"}
}