{
  "type": "Feature",
  "properties": {
    "iso:country":"US",
    "sg:address":"4804 Richmond Ave",
    "sg:city":"Austin",
    "sg:classifiers":[
        {
            "category":"Building & Trades",
            "subcategory":"Landscaping Services",
            "type":"Services"
        }
    ],
    "sg:phone":"+1 512 448 4013",
    "sg:postcode":"78745",
    "sg:province":"TX",
    "sg:tags":[
        "landscape"
    ],
    "wof:name":"Js Landscaping",
    "wof:placetype":"venue"
},
  "geometry": {"coordinates":[-97.78415200000001,30.218606],"type":"Point"}
}