{
  "type": "Feature",
  "properties": {
    "iso:country":"US",
    "sg:address":"5405 Stanley Keller Rd",
    "sg:city":"Fort Worth",
    "sg:classifiers":[
        {
            "category":"Manufacturing",
            "subcategory":"Apparel",
            "type":"Manufacturing & Wholesale Goods"
        }
    ],
    "sg:phone":"+1 817 485 9132",
    "sg:postcode":"76117",
    "sg:province":"TX",
    "wof:name":"SCULLY By Marsha Wright",
    "wof:placetype":"venue"
},
  "geometry": {"coordinates":[-97.264489,32.824142],"type":"Point"}
}