{
  "type": "Feature",
  "properties": {
    "iso:country":"US",
    "sg:address":"2828 W Parker Rd",
    "sg:city":"Plano",
    "sg:classifiers":[
        {
            "category":"Professional",
            "subcategory":"Business Services",
            "type":"Services"
        }
    ],
    "sg:phone":"+1 972 867 7612",
    "sg:postcode":"75075",
    "sg:province":"TX",
    "sg:tags":[
        "foreground",
        "music"
    ],
    "wof:name":"Muzak",
    "wof:placetype":"venue"
},
  "geometry": {"coordinates":[-96.749925,33.040895],"type":"Point"}
}