{
  "type": "Feature",
  "properties": {
    "iso:country":"US",
    "sg:address":"222 S Amherst St",
    "sg:city":"Perryton",
    "sg:classifiers":[
        {
            "category":"Utilities",
            "subcategory":"Telephone",
            "type":"Services"
        }
    ],
    "sg:phone":"+1 806 648 1111",
    "sg:postcode":"79070",
    "sg:province":"TX",
    "sg:tags":[
        "communications"
    ],
    "wof:name":"P T S I Panhandle Telecom",
    "wof:placetype":"venue"
},
  "geometry": {"coordinates":[-100.804149,36.398283],"type":"Point"}
}