{
  "type": "Feature",
  "properties": {
    "iso:country":"US",
    "sg:address":"111 Grove Ave",
    "sg:city":"Laredo",
    "sg:classifiers":[
        {
            "category":"Freight",
            "type":"Transportation"
        }
    ],
    "sg:phone":"+1 956 753 6328",
    "sg:postcode":"78045",
    "sg:province":"TX",
    "sg:tags":[
        "arrangement"
    ],
    "wof:name":"Freight Network Co",
    "wof:placetype":"venue"
},
  "geometry": {"coordinates":[-99.485055,27.576293],"type":"Point"}
}