{
  "type": "Feature",
  "properties": {
    "iso:country":"US",
    "sg:address":"100 Main St",
    "sg:city":"Colleyville",
    "sg:classifiers":[
        {
            "category":"Government",
            "subcategory":"Office",
            "type":"Public Place"
        }
    ],
    "sg:phone":"+1 817 503 1070",
    "sg:postcode":"76060",
    "sg:province":"TX",
    "sg:tags":[
        "village"
    ],
    "wof:name":"Colleyville Human Resources",
    "wof:placetype":"venue"
},
  "geometry": {"coordinates":[-97.226602,32.644774],"type":"Point"}
}