{
  "type": "Feature",
  "properties": {
    "iso:country":"US",
    "sg:address":"4460 Fm 930",
    "sg:city":"Gatesville",
    "sg:classifiers":[
        {
            "category":"Place Of Worship",
            "subcategory":"Church",
            "type":"Public Place"
        },
        {
            "category":"Place Of Worship",
            "type":"Public Place"
        }
    ],
    "sg:phone":"+1 254 865 7198",
    "sg:postcode":"76528",
    "sg:province":"TX",
    "sg:tags":[
        "churches-baptist-general",
        "churches-baptist"
    ],
    "wof:name":"Levita Baptist Church",
    "wof:placetype":"venue"
},
  "geometry": {"coordinates":[-97.892944,31.474868],"type":"Point"}
}