{
  "type": "Feature",
  "properties": {
    "iso:country":"US",
    "sg:address":"2410 Bugtussle Ln",
    "sg:city":"West",
    "sg:classifiers":[
        {
            "category":"Building & Trades",
            "subcategory":"Landscaping Services",
            "type":"Services"
        }
    ],
    "sg:phone":"+1 254 829 1818",
    "sg:postcode":"76691",
    "sg:province":"TX",
    "wof:name":"Brazos Landscapers",
    "wof:placetype":"venue"
},
  "geometry": {"coordinates":[-97.14355999999999,31.751321],"type":"Point"}
}