{
  "type": "Feature",
  "properties": {
    "iso:country":"US",
    "sg:address":"1401 N Plano Rd",
    "sg:city":"Richardson",
    "sg:classifiers":[
        {
            "category":"Wholesale",
            "subcategory":"Hardware",
            "type":"Manufacturing & Wholesale Goods"
        }
    ],
    "sg:phone":"+1 972 699 1030",
    "sg:postcode":"75081",
    "sg:province":"TX",
    "sg:tags":[
        "distribution",
        "handling",
        "air"
    ],
    "wof:name":"Titus",
    "wof:placetype":"venue"
},
  "geometry": {"coordinates":[-96.699997,32.967219],"type":"Point"}
}