{
  "type": "Feature",
  "properties": {
    "iso:country":"US",
    "sg:address":"202 W 15th St 84",
    "sg:city":"Post",
    "sg:classifiers":[
        {
            "category":"Restaurant",
            "type":"Food & Drink"
        }
    ],
    "sg:phone":"+1 806 495 3848",
    "sg:postcode":"79356",
    "sg:province":"TX",
    "sg:tags":[
        "mexican"
    ],
    "wof:name":"Chapa's Family Restaurant",
    "wof:placetype":"venue"
},
  "geometry": {"coordinates":[-101.37963499999999,33.19807],"type":"Point"}
}