{
  "type": "Feature",
  "properties": {
    "iso:country":"US",
    "sg:address":"138 Creekview Dr",
    "sg:city":"Canyon Lake",
    "sg:classifiers":[
        {
            "category":"Building & Trades",
            "subcategory":"Construction",
            "type":"Services"
        }
    ],
    "sg:phone":"+1 830 899 2843",
    "sg:postcode":"78133",
    "sg:province":"TX",
    "sg:tags":[
        "painter"
    ],
    "wof:name":"Charlie Schubert Painting",
    "wof:placetype":"venue"
},
  "geometry": {"coordinates":[-98.27980700000001,29.871215],"type":"Point"}
}