{
  "type": "Feature",
  "properties": {
    "iso:country":"US",
    "sg:address":"6715 N Lone Star Pkwy",
    "sg:city":"Crawford",
    "sg:classifiers":[
        {
            "category":"Shopping",
            "subcategory":"Gifts & Souvenirs",
            "type":"Retail Goods"
        }
    ],
    "sg:phone":"+1 254 486 9559",
    "sg:postcode":"76638",
    "sg:province":"TX",
    "sg:tags":[
        "shop"
    ],
    "wof:name":"Red Bull",
    "wof:placetype":"venue"
},
  "geometry": {"coordinates":[-97.456931,31.587342],"type":"Point"}
}