{
  "type": "Feature",
  "properties": {
    "iso:country":"US",
    "sg:address":"926 Lexington Dr",
    "sg:city":"Rockwall",
    "sg:classifiers":[
        {
            "category":"Shopping",
            "subcategory":"Computers & Home Electronics",
            "type":"Retail Goods"
        }
    ],
    "sg:phone":"+1 972 772 2870",
    "sg:postcode":"75087",
    "sg:province":"TX",
    "sg:tags":[
        "equipment",
        "dealer"
    ],
    "wof:name":"My Computer Guy",
    "wof:placetype":"venue"
},
  "geometry": {"coordinates":[-96.46977699999999,32.905274],"type":"Point"}
}