{
  "type": "Feature",
  "properties": {
    "iso:country":"US",
    "sg:address":"627 Strong Ave",
    "sg:city":"Ballinger",
    "sg:classifiers":[
        {
            "category":"Community Center",
            "subcategory":"Senior",
            "type":"Public Place"
        },
        {
            "category":"Social Services",
            "subcategory":"Adult Care",
            "type":"Services"
        },
        {
            "category":"Government",
            "subcategory":"Office",
            "type":"Public Place"
        }
    ],
    "sg:phone":"+1 325 365 5027",
    "sg:postcode":"76821",
    "sg:province":"TX",
    "sg:tags":[
        "counseling",
        "parish",
        "government-county",
        "citizen"
    ],
    "wof:name":"Senior Citizens Center",
    "wof:placetype":"venue"
},
  "geometry": {"coordinates":[-99.945065,31.738322],"type":"Point"}
}