{
  "type": "Feature",
  "properties": {
    "iso:country":"US",
    "sg:address":"4706 Coventry Ln",
    "sg:city":"Corpus Christi",
    "sg:classifiers":[
        {
            "category":"Shopping",
            "subcategory":"Catalog Store",
            "type":"Retail Goods"
        }
    ],
    "sg:phone":"+1 361 852 3536",
    "sg:postcode":"78411",
    "sg:province":"TX",
    "sg:tags":[
        "mail",
        "order"
    ],
    "sg:website":"www.skranch.com",
    "wof:name":"Sauerkraut Ranch",
    "wof:placetype":"venue"
},
  "geometry": {"coordinates":[-97.390756,27.708976],"type":"Point"}
}