{
  "type": "Feature",
  "properties": {
    "iso:country":"US",
    "sg:address":"10505 Little Thicket Rd",
    "sg:city":"Austin",
    "sg:classifiers":[
        {
            "category":"Professional",
            "type":"Services"
        }
    ],
    "sg:phone":"+1 512 288 3297",
    "sg:postcode":"78736",
    "sg:province":"TX",
    "wof:name":"Performance Solutions",
    "wof:placetype":"venue"
},
  "geometry": {"coordinates":[-97.99781400000001,30.249472],"type":"Point"}
}