{
  "type": "Feature",
  "properties": {
    "iso:country":"US",
    "sg:address":"305 W Gillis Ave",
    "sg:city":"Cameron",
    "sg:classifiers":[
        {
            "category":"Manufacturing",
            "subcategory":"Buildings",
            "type":"Manufacturing & Wholesale Goods"
        },
        {
            "category":"Building & Trades",
            "subcategory":"Construction",
            "type":"Services"
        }
    ],
    "sg:phone":"+1 254 697 8516",
    "sg:postcode":"76520",
    "sg:province":"TX",
    "sg:tags":[
        "home",
        "builder",
        "contractor"
    ],
    "sg:website":"http://ebcogc.com",
    "wof:name":"Ebco Commercial",
    "wof:placetype":"venue"
},
  "geometry": {"coordinates":[-96.978739,30.849593],"type":"Point"}
}