{
  "type": "Feature",
  "properties": {
    "iso:country":"US",
    "sg:address":"4200 Smith School Rd",
    "sg:city":"Austin",
    "sg:classifiers":[
        {
            "category":"Government",
            "subcategory":"Office",
            "type":"Public Place"
        }
    ],
    "sg:phone":"+1 512 912 7124",
    "sg:postcode":"78744",
    "sg:province":"TX",
    "sg:tags":[
        "conservation",
        "mineral"
    ],
    "wof:name":"Tim C Hogsett",
    "wof:placetype":"venue"
},
  "geometry": {"coordinates":[-97.71328200000001,30.19759],"type":"Point"}
}