{
  "type": "Feature",
  "properties": {
    "iso:country":"US",
    "sg:address":"2000 Ridgmar Blvd",
    "sg:city":"Fort Worth",
    "sg:classifiers":[
        {
            "category":"Shopping",
            "subcategory":"Florist",
            "type":"Retail Goods"
        }
    ],
    "sg:phone":"+1 817 732 8891",
    "sg:postcode":"76116",
    "sg:province":"TX",
    "wof:name":"Poncho's Flower Villa",
    "wof:placetype":"venue"
},
  "geometry": {"coordinates":[-97.425033,32.738318],"type":"Point"}
}