{
  "type": "Feature",
  "properties": {
    "iso:country":"US",
    "sg:address":"8140 Walnut Hill Ln",
    "sg:city":"Dallas",
    "sg:classifiers":[
        {
            "category":"Professional",
            "type":"Services"
        }
    ],
    "sg:phone":"+1 214 348 7758",
    "sg:postcode":"75231",
    "sg:province":"TX",
    "sg:tags":[
        "establishment"
    ],
    "wof:name":"Access By Design",
    "wof:placetype":"venue"
},
  "geometry": {"coordinates":[-96.768214,32.880136],"type":"Point"}
}