{
  "type": "Feature",
  "properties": {
    "iso:country":"US",
    "sg:address":"2004 Arthur Dr",
    "sg:city":"Fort Worth",
    "sg:classifiers":[
        {
            "category":"Parking",
            "type":"Transportation"
        }
    ],
    "sg:phone":"+1 817 293 2731",
    "sg:postcode":"76134",
    "sg:province":"TX",
    "sg:tags":[
        "attendant"
    ],
    "wof:name":"Billy Ray Pinyan",
    "wof:placetype":"venue"
},
  "geometry": {"coordinates":[-97.35186299999999,32.655907],"type":"Point"}
}