{
  "type": "Feature",
  "properties": {
    "iso:country":"US",
    "sg:address":"1305 S Key Ave",
    "sg:city":"Lampasas",
    "sg:classifiers":[
        {
            "category":"Organizations",
            "subcategory":"Membership Organization",
            "type":"Services"
        }
    ],
    "sg:phone":"+1 512 556 6962",
    "sg:postcode":"76550",
    "sg:province":"TX",
    "sg:tags":[
        "meditation",
        "instruction"
    ],
    "wof:name":"Central Counties Mhmr",
    "wof:placetype":"venue"
},
  "geometry": {"coordinates":[-98.17917,31.057114],"type":"Point"}
}