{
  "type": "Feature",
  "properties": {
    "iso:country":"US",
    "sg:address":"2100 Ironside Dr",
    "sg:city":"Plano",
    "sg:classifiers":[
        {
            "category":"Building & Trades",
            "subcategory":"Construction",
            "type":"Services"
        }
    ],
    "sg:phone":"+1 972 599 9943",
    "sg:postcode":"75075",
    "sg:province":"TX",
    "sg:tags":[
        "house"
    ],
    "wof:name":"A J B Investments & Cnstr",
    "wof:placetype":"venue"
},
  "geometry": {"coordinates":[-96.73365699999999,33.030878],"type":"Point"}
}