{
  "type": "Feature",
  "properties": {
    "iso:country":"US",
    "sg:address":"1501 Stephenson St",
    "sg:city":"Fort Worth",
    "sg:classifiers":[
        {
            "category":"Social Services",
            "subcategory":"Child Care",
            "type":"Services"
        }
    ],
    "sg:phone":"+1 817 332 4434",
    "sg:postcode":"76102",
    "sg:province":"TX",
    "wof:name":"Amaka Learning Ctr",
    "wof:placetype":"venue"
},
  "geometry": {"coordinates":[-97.318198,32.751027],"type":"Point"}
}