{
  "type": "Feature",
  "properties": {
    "iso:country":"US",
    "sg:address":"1301 E Lake St",
    "sg:city":"Sherman",
    "sg:classifiers":[
        {
            "category":"Building & Trades",
            "subcategory":"Landscaping Services",
            "type":"Services"
        }
    ],
    "sg:phone":"+1 903 892 9387",
    "sg:postcode":"75090",
    "sg:province":"TX",
    "sg:tags":[
        "lawn",
        "maintenance"
    ],
    "wof:name":"North Texoma Tree Service",
    "wof:placetype":"venue"
},
  "geometry": {"coordinates":[-96.587655,33.618546],"type":"Point"}
}