{
  "type": "Feature",
  "properties": {
    "iso:country":"US",
    "sg:address":"2408 NE 28th St",
    "sg:city":"Fort Worth",
    "sg:classifiers":[
        {
            "category":"Restaurant",
            "type":"Food & Drink"
        }
    ],
    "sg:phone":"+1 817 624 3399",
    "sg:postcode":"76106",
    "sg:province":"TX",
    "sg:tags":[
        "eating"
    ],
    "wof:name":"Alicia's Mexican Grill",
    "wof:placetype":"venue"
},
  "geometry": {"coordinates":[-97.325884,32.795113],"type":"Point"}
}