{
  "type": "Feature",
  "properties": {
    "iso:country":"US",
    "sg:address":"9522 Telephone Rd",
    "sg:city":"Houston",
    "sg:classifiers":[
        {
            "category":"Shopping",
            "subcategory":"Catalog Store",
            "type":"Retail Goods"
        }
    ],
    "sg:phone":"+1 713 987 9353",
    "sg:postcode":"77075",
    "sg:province":"TX",
    "sg:tags":[
        "e"
    ],
    "wof:name":"Billy Boy Enterprise",
    "wof:placetype":"venue"
},
  "geometry": {"coordinates":[-95.285445,29.629363],"type":"Point"}
}