{
  "type": "Feature",
  "properties": {
    "iso:country":"US",
    "sg:address":"8 E Barton Ave",
    "sg:city":"Temple",
    "sg:classifiers":[
        {
            "category":"Utilities",
            "subcategory":"Cable",
            "type":"Services"
        }
    ],
    "sg:phone":"+1 254 773 1163",
    "sg:postcode":"76501",
    "sg:province":"TX",
    "sg:tags":[
        "television"
    ],
    "wof:name":"Centro Vision Inc",
    "wof:placetype":"venue"
},
  "geometry": {"coordinates":[-97.33949699999999,31.098459],"type":"Point"}
}