{
  "type": "Feature",
  "properties": {
    "iso:country":"US",
    "sg:address":"2727 56th St",
    "sg:city":"Dallas",
    "sg:classifiers":[
        {
            "category":"Personal",
            "subcategory":"Beauty Salon",
            "type":"Services"
        }
    ],
    "sg:phone":"+1 214 375 6518",
    "sg:postcode":"75241",
    "sg:province":"TX",
    "sg:tags":[
        "shop"
    ],
    "wof:name":"Thrown of Grace Beauty & Bar",
    "wof:placetype":"venue"
},
  "geometry": {"coordinates":[-96.77727400000001,32.689317],"type":"Point"}
}