{
  "type": "Feature",
  "properties": {
    "iso:country":"US",
    "sg:address":"9275 Manion Dr",
    "sg:city":"Beaumont",
    "sg:classifiers":[
        {
            "category":"Education",
            "subcategory":"School",
            "type":"Public Place"
        }
    ],
    "sg:phone":"+1 409 866 1021",
    "sg:postcode":"77706",
    "sg:province":"TX",
    "sg:tags":[
        "elementary"
    ],
    "wof:name":"Oaks Education Center",
    "wof:placetype":"venue"
},
  "geometry": {"coordinates":[-94.19720700000001,30.084608],"type":"Point"}
}