{
  "type": "Feature",
  "properties": {
    "iso:country":"US",
    "sg:address":"3250 W Pleasant Run Rd",
    "sg:city":"Dallas",
    "sg:classifiers":[
        {
            "category":"Restaurant",
            "type":"Food & Drink"
        }
    ],
    "sg:phone":"+1 972 223 5601",
    "sg:postcode":"75227",
    "sg:province":"TX",
    "sg:tags":[
        "chinese"
    ],
    "wof:name":"Ton's Palace Chinese Restaurant",
    "wof:placetype":"venue"
},
  "geometry": {"coordinates":[-96.68270099999999,32.766399],"type":"Point"}
}