{
  "type": "Feature",
  "properties": {
    "iso:country":"US",
    "sg:address":"715 Discovery Blvd Ste 212",
    "sg:city":"Cedar Park",
    "sg:classifiers":[
        {
            "category":"Real Estate",
            "subcategory":"Real Estate Services",
            "type":"Services"
        },
        {
            "category":"Banks & Credit Unions",
            "subcategory":"Financial Services",
            "type":"Services"
        }
    ],
    "sg:phone":"+1 512 782 8202",
    "sg:postcode":"78613",
    "sg:province":"TX",
    "sg:tags":[
        "broker",
        "mortgage"
    ],
    "sg:website":"www.austin.benchmark.us",
    "wof:name":"Benchmark Mortgage",
    "wof:placetype":"venue"
},
  "geometry": {"coordinates":[-97.820077,30.520864],"type":"Point"}
}