{
  "type": "Feature",
  "properties": {
    "iso:country":"US",
    "sg:address":"911 Stone Lake Dr",
    "sg:city":"Cleburne",
    "sg:classifiers":[
        {
            "category":"Building & Trades",
            "subcategory":"Construction",
            "type":"Services"
        }
    ],
    "sg:phone":"+1 817 558 8177",
    "sg:postcode":"76033",
    "sg:province":"TX",
    "sg:tags":[
        "contractor"
    ],
    "wof:name":"Hudson Property",
    "wof:placetype":"venue"
},
  "geometry": {"coordinates":[-97.409584,32.326636],"type":"Point"}
}