{
  "type": "Feature",
  "properties": {
    "iso:country":"US",
    "sg:address":"8027 Exchange Dr",
    "sg:city":"Austin",
    "sg:classifiers":[
        {
            "category":"Government",
            "subcategory":"Office",
            "type":"Public Place"
        }
    ],
    "sg:phone":"+1 512 927 3500",
    "sg:postcode":"78754",
    "sg:province":"TX",
    "sg:tags":[
        "federal"
    ],
    "wof:name":"US Geological Survey",
    "wof:placetype":"venue"
},
  "geometry": {"coordinates":[-97.663658,30.335084],"type":"Point"}
}