{
  "type": "Feature",
  "properties": {
    "iso:country":"US",
    "sg:address":"220 Hyde Park Blvd",
    "sg:city":"Houston",
    "sg:classifiers":[
        {
            "category":"Communications",
            "type":"Services"
        }
    ],
    "sg:phone":"+1 713 524 7344",
    "sg:postcode":"77006",
    "sg:province":"TX",
    "sg:tags":[
        "web",
        "design"
    ],
    "sg:website":"www.ringworld.com",
    "wof:name":"Ringworld Web Design",
    "wof:placetype":"venue"
},
  "geometry": {"coordinates":[-95.384985,29.747675],"type":"Point"}
}