{
  "type": "Feature",
  "properties": {
    "iso:country":"US",
    "sg:address":"104 Brooks Ave",
    "sg:city":"Corsicana",
    "sg:classifiers":[
        {
            "category":"Building & Trades",
            "subcategory":"Plumbing",
            "type":"Services"
        }
    ],
    "sg:phone":"+1 903 879 5150",
    "sg:postcode":"75110",
    "sg:province":"TX",
    "sg:tags":[
        "conditioning",
        "air",
        "system",
        "contractor"
    ],
    "wof:name":"Chaney Svc Co",
    "wof:placetype":"venue"
},
  "geometry": {"coordinates":[-96.47541200000001,32.104824],"type":"Point"}
}