{
  "type": "Feature",
  "properties": {
    "iso:country":"US",
    "sg:address":"3616 Flagstone Dr",
    "sg:city":"Carrollton",
    "sg:classifiers":[
        {
            "category":"Banks & Credit Unions",
            "subcategory":"Financial Services",
            "type":"Services"
        }
    ],
    "sg:phone":"+1 972 466 4466",
    "sg:postcode":"75007",
    "sg:province":"TX",
    "sg:tags":[
        "patent"
    ],
    "wof:name":"UPS Stores",
    "wof:placetype":"venue"
},
  "geometry": {"coordinates":[-96.911824,33.008832],"type":"Point"}
}