{
  "type": "Feature",
  "properties": {
    "iso:country":"US",
    "sg:address":"535 Christopher Dr",
    "sg:city":"Eddy",
    "sg:classifiers":[
        {
            "category":"Building & Trades",
            "subcategory":"Plumbing",
            "type":"Services"
        }
    ],
    "sg:phone":"+1 254 717 6676",
    "sg:postcode":"76524",
    "sg:province":"TX",
    "sg:tags":[
        "conditioning",
        "air",
        "system",
        "contractor"
    ],
    "wof:name":"J & R Svc",
    "wof:placetype":"venue"
},
  "geometry": {"coordinates":[-97.244015,31.322339],"type":"Point"}
}