{
  "type": "Feature",
  "properties": {
    "iso:country":"US",
    "sg:address":"26593 E River Rd",
    "sg:city":"Splendora",
    "sg:classifiers":[
        {
            "category":"Manufacturing",
            "subcategory":"Tools & Machinery",
            "type":"Manufacturing & Wholesale Goods"
        }
    ],
    "sg:phone":"+1 281 689 2103",
    "sg:postcode":"77372",
    "sg:province":"TX",
    "sg:tags":[
        "mfg"
    ],
    "wof:name":"Texas Filter Service Inc",
    "wof:placetype":"venue"
},
  "geometry": {"coordinates":[-95.146441,30.250276],"type":"Point"}
}