{
  "type": "Feature",
  "properties": {
    "iso:country":"US",
    "sg:address":"1616 Moore Ave",
    "sg:city":"Tyler",
    "sg:classifiers":[
        {
            "category":"Shopping",
            "type":"Retail Goods"
        }
    ],
    "sg:phone":"+1 903 592 7511",
    "sg:postcode":"75702",
    "sg:province":"TX",
    "sg:tags":[
        "merchandise"
    ],
    "wof:name":"Wrights Boutique",
    "wof:placetype":"venue"
},
  "geometry": {"coordinates":[-95.31237900000001,32.367174],"type":"Point"}
}