{
  "type": "Feature",
  "properties": {
    "iso:country":"US",
    "sg:address":"1515 Lakeside Dr",
    "sg:city":"Abilene",
    "sg:classifiers":[
        {
            "category":"Organizations",
            "subcategory":"Religious Organization",
            "type":"Services"
        }
    ],
    "sg:phone":"+1 325 673 2339",
    "sg:postcode":"79602",
    "sg:province":"TX",
    "sg:tags":[
        "church"
    ],
    "wof:name":"Berry Lane Baptist Church",
    "wof:placetype":"venue"
},
  "geometry": {"coordinates":[-99.716562,32.430573],"type":"Point"}
}