{
  "type": "Feature",
  "properties": {
    "iso:country":"US",
    "sg:address":"4223 Meadowbank Dr",
    "sg:city":"Seabrook",
    "sg:classifiers":[
        {
            "category":"Professional",
            "type":"Services"
        },
        {
            "category":"Freight",
            "type":"Transportation"
        }
    ],
    "sg:phone":"+1 281 474 5044",
    "sg:postcode":"77586",
    "sg:province":"TX",
    "sg:tags":[
        "trucking"
    ],
    "wof:name":"Hopkins Transportation",
    "wof:placetype":"venue"
},
  "geometry": {"coordinates":[-95.062229,29.583291],"type":"Point"}
}