{
  "type": "Feature",
  "properties": {
    "iso:country":"US",
    "sg:address":"1106 W Main St",
    "sg:city":"Gatesville",
    "sg:classifiers":[
        {
            "category":"Retail",
            "subcategory":"Animal Services",
            "type":"Services"
        }
    ],
    "sg:phone":"+1 254 865 7957",
    "sg:postcode":"76528",
    "sg:province":"TX",
    "wof:name":"All Breed Grooming Services",
    "wof:placetype":"venue"
},
  "geometry": {"coordinates":[-97.768405,31.434826],"type":"Point"}
}