{
  "type": "Feature",
  "properties": {
    "iso:country":"US",
    "sg:address":"607 Gulf Bank Rd",
    "sg:city":"Houston",
    "sg:classifiers":[
        {
            "category":"Retail",
            "subcategory":"Auto Repair",
            "type":"Services"
        }
    ],
    "sg:phone":"+1 281 405 0054",
    "sg:postcode":"77037",
    "sg:province":"TX",
    "sg:tags":[
        "automotive"
    ],
    "wof:name":"Joses Auto Sales Inspections",
    "wof:placetype":"venue"
},
  "geometry": {"coordinates":[-95.383912,29.889554],"type":"Point"}
}