{
  "type": "Feature",
  "properties": {
    "iso:country":"US",
    "sg:address":"7933 Viterbo Rd",
    "sg:city":"Beaumont",
    "sg:classifiers":[
        {
            "category":"Government",
            "subcategory":"Office",
            "type":"Public Place"
        }
    ],
    "sg:phone":"+1 409 722 0292",
    "sg:postcode":"77705",
    "sg:province":"TX",
    "sg:tags":[
        "county",
        "program"
    ],
    "wof:name":"Jefferson County Environmental",
    "wof:placetype":"venue"
},
  "geometry": {"coordinates":[-94.020628,29.964088],"type":"Point"}
}