{
  "type": "Feature",
  "properties": {
    "iso:country":"US",
    "sg:address":"1633 N 10th St",
    "sg:city":"Mcallen",
    "sg:classifiers":[
        {
            "category":"Real Estate",
            "subcategory":"Real Estate Agent",
            "type":"Services"
        }
    ],
    "sg:phone":"+1 956 686 1821",
    "sg:postcode":"78501",
    "sg:province":"TX",
    "wof:name":"Moschel Realty Co",
    "wof:placetype":"venue"
},
  "geometry": {"coordinates":[-98.22748,26.218637],"type":"Point"}
}