{
  "type": "Feature",
  "properties": {
    "iso:country":"US",
    "sg:address":"213 Calhoun St",
    "sg:city":"Port Lavaca",
    "sg:classifiers":[
        {
            "category":"Shopping",
            "subcategory":"Discount & Variety Stores",
            "type":"Retail Goods"
        },
        {
            "category":"Shopping",
            "subcategory":"Department Store",
            "type":"Retail Goods"
        }
    ],
    "sg:phone":"+1 361 552 6462",
    "sg:postcode":"77979",
    "sg:province":"TX",
    "sg:tags":[
        "shop"
    ],
    "wof:name":"Family Dollar Stores",
    "wof:placetype":"venue"
},
  "geometry": {"coordinates":[-96.630354,28.625817],"type":"Point"}
}