{
  "type": "Feature",
  "properties": {
    "iso:country":"US",
    "sg:address":"700 E Randol Mill Rd",
    "sg:city":"Arlington",
    "sg:classifiers":[
        {
            "category":"Real Estate",
            "subcategory":"Real Estate Operator",
            "type":"Services"
        }
    ],
    "sg:phone":"+1 817 261 0442",
    "sg:postcode":"76011",
    "sg:province":"TX",
    "sg:tags":[
        "building",
        "apartment"
    ],
    "wof:name":"P H K Inc",
    "wof:placetype":"venue"
},
  "geometry": {"coordinates":[-97.09732200000001,32.749817],"type":"Point"}
}