{
  "type": "Feature",
  "properties": {
    "iso:country":"US",
    "sg:address":"2606 Cornell St",
    "sg:city":"Lubbock",
    "sg:classifiers":[
        {
            "category":"Personal",
            "subcategory":"Beauty Salon",
            "type":"Services"
        }
    ],
    "sg:phone":"+1 806 763 0803",
    "sg:postcode":"79415",
    "sg:province":"TX",
    "wof:name":"Doris Legers Beauty Salon",
    "wof:placetype":"venue"
},
  "geometry": {"coordinates":[-101.87333700000001,33.60321],"type":"Point"}
}