{
  "type": "Feature",
  "properties": {
    "iso:country":"US",
    "sg:address":"220 Vivian Ln",
    "sg:city":"Shepherd",
    "sg:classifiers":[
        {
            "category":"Wholesale",
            "subcategory":"Machinery & Supplies",
            "type":"Manufacturing & Wholesale Goods"
        }
    ],
    "sg:phone":"+1 281 593 5434",
    "sg:postcode":"77371",
    "sg:province":"TX",
    "sg:tags":[
        "equipment",
        "industrial"
    ],
    "sg:website":"http://jmmachine.com",
    "wof:name":"J&M Machine",
    "wof:placetype":"venue"
},
  "geometry": {"coordinates":[-94.98214900000001,30.498205],"type":"Point"}
}