{
  "type": "Feature",
  "properties": {
    "iso:country":"US",
    "sg:address":"701 14th St",
    "sg:city":"Lubbock",
    "sg:classifiers":[
        {
            "category":"Manufacturing",
            "subcategory":"Tools & Machinery",
            "type":"Manufacturing & Wholesale Goods"
        }
    ],
    "sg:phone":"+1 806 747 4747",
    "sg:postcode":"79401",
    "sg:province":"TX",
    "sg:tags":[
        "food",
        "product"
    ],
    "wof:name":"Hobart Corp",
    "wof:placetype":"venue"
},
  "geometry": {"coordinates":[-101.8432,33.582623],"type":"Point"}
}