{
  "type": "Feature",
  "properties": {
    "iso:country":"US",
    "sg:address":"1102 Almeda Genoa Rd",
    "sg:city":"Houston",
    "sg:classifiers":[
        {
            "category":"Food & Beverages",
            "subcategory":"Groceries & Convenience Stores",
            "type":"Retail Goods"
        }
    ],
    "sg:phone":"+1 713 433 5500",
    "sg:postcode":"77047",
    "sg:province":"TX",
    "wof:name":"Shell Express Mart Inc",
    "wof:placetype":"venue"
},
  "geometry": {"coordinates":[-95.405129,29.613603],"type":"Point"}
}