{
  "type": "Feature",
  "properties": {
    "iso:country":"US",
    "sg:address":"720 Eubanks St",
    "sg:city":"Houston",
    "sg:classifiers":[
        {
            "category":"Building & Trades",
            "subcategory":"Construction",
            "type":"Services"
        }
    ],
    "sg:phone":"+1 713 692 1396",
    "sg:postcode":"77022",
    "sg:province":"TX",
    "sg:tags":[
        "house"
    ],
    "wof:name":"Alex Lucio Construction",
    "wof:placetype":"venue"
},
  "geometry": {"coordinates":[-95.363743,29.832396],"type":"Point"}
}