{
  "type": "Feature",
  "properties": {
    "iso:country":"US",
    "sg:address":"7889 State Hwy 6",
    "sg:city":"Houston",
    "sg:classifiers":[
        {
            "category":"Personal",
            "subcategory":"Barber",
            "type":"Services"
        }
    ],
    "sg:phone":"+1 281 561 8812",
    "sg:postcode":"77083",
    "sg:province":"TX",
    "sg:tags":[
        "shop"
    ],
    "wof:name":"Roots Barber Shop",
    "wof:placetype":"venue"
},
  "geometry": {"coordinates":[-95.643659,29.693236],"type":"Point"}
}