{
  "type": "Feature",
  "properties": {
    "iso:country":"US",
    "sg:address":"6729 Meadowcrest Dr",
    "sg:city":"Arlington",
    "sg:classifiers":[
        {
            "category":"Professional",
            "subcategory":"Research",
            "type":"Services"
        }
    ],
    "sg:phone":"+1 817 417 7476",
    "sg:postcode":"76002",
    "sg:province":"TX",
    "wof:name":"Raymond Turco & Assoc",
    "wof:placetype":"venue"
},
  "geometry": {"coordinates":[-97.088769,32.630191],"type":"Point"}
}