{
  "type": "Feature",
  "properties": {
    "iso:country":"US",
    "sg:address":"117 Briarglen Dr",
    "sg:city":"League City",
    "sg:classifiers":[
        {
            "category":"Real Estate",
            "subcategory":"Real Estate Agent",
            "type":"Services"
        }
    ],
    "sg:phone":"+1 281 338 8088",
    "sg:postcode":"77573",
    "sg:province":"TX",
    "wof:name":"Real Estate Connection",
    "wof:placetype":"venue"
},
  "geometry": {"coordinates":[-95.082615,29.514364],"type":"Point"}
}