{
  "type": "Feature",
  "properties": {
    "iso:country":"US",
    "sg:address":"840 FM 1960 W",
    "sg:city":"Houston",
    "sg:classifiers":[
        {
            "category":"Shopping",
            "subcategory":"Clothing, Apparel, & Fashions",
            "type":"Retail Goods"
        }
    ],
    "sg:phone":"+1 281 444 5572",
    "sg:postcode":"77090",
    "sg:province":"TX",
    "sg:tags":[
        "ready"
    ],
    "wof:name":"Opals Boutique",
    "wof:placetype":"venue"
},
  "geometry": {"coordinates":[-95.441704,30.017396],"type":"Point"}
}