{
  "type": "Feature",
  "properties": {
    "iso:country":"US",
    "sg:address":"2208 Oxford Blvd",
    "sg:city":"Round Rock",
    "sg:classifiers":[
        {
            "category":"Retail",
            "subcategory":"Portrait Studio",
            "type":"Services"
        }
    ],
    "sg:phone":"+1 512 238 8768",
    "sg:postcode":"78664",
    "sg:province":"TX",
    "sg:tags":[
        "photo"
    ],
    "wof:name":"Real Life Photography",
    "wof:placetype":"venue"
},
  "geometry": {"coordinates":[-97.665237,30.489739],"type":"Point"}
}