{
  "type": "Feature",
  "properties": {
    "iso:country":"US",
    "sg:address":"2047 Common St",
    "sg:city":"New Braunfels",
    "sg:classifiers":[
        {
            "category":"Professional",
            "subcategory":"Business Services",
            "type":"Services"
        }
    ],
    "sg:phone":"+1 830 620 1948",
    "sg:postcode":"78130",
    "sg:province":"TX",
    "wof:name":"Riata Group",
    "wof:placetype":"venue"
},
  "geometry": {"coordinates":[-98.098727,29.734148],"type":"Point"}
}