{
  "type": "Feature",
  "properties": {
    "iso:country":"US",
    "sg:address":"4838 Kostoryz Rd",
    "sg:city":"Corpus Christi",
    "sg:classifiers":[
        {
            "category":"Insurance",
            "subcategory":"Insurance Agent",
            "type":"Services"
        }
    ],
    "sg:phone":"+1 361 225 2117",
    "sg:postcode":"78415",
    "sg:province":"TX",
    "sg:tags":[
        "a",
        "is",
        "agency"
    ],
    "wof:name":"Texas Low Cost Insurance Agcy",
    "wof:placetype":"venue"
},
  "geometry": {"coordinates":[-97.410454,27.732461],"type":"Point"}
}