{
  "type": "Feature",
  "properties": {
    "iso:country":"US",
    "sg:address":"1504 E Elm St",
    "sg:city":"Breckenridge",
    "sg:classifiers":[
        {
            "category":"Mining & Drilling",
            "type":"Manufacturing & Wholesale Goods"
        }
    ],
    "sg:phone":"+1 254 559 2888",
    "sg:postcode":"76424",
    "sg:province":"TX",
    "sg:tags":[
        "operator",
        "oil"
    ],
    "wof:name":"Kimble Oil Co",
    "wof:placetype":"venue"
},
  "geometry": {"coordinates":[-98.883971,32.756433],"type":"Point"}
}