{
  "type": "Feature",
  "properties": {
    "iso:country":"US",
    "sg:address":"6832 Coit Rd",
    "sg:city":"Plano",
    "sg:classifiers":[
        {
            "category":"Shopping",
            "subcategory":"Tobacco",
            "type":"Retail Goods"
        }
    ],
    "sg:phone":"+1 972 208 1676",
    "sg:postcode":"75023",
    "sg:province":"TX",
    "sg:tags":[
        "cigarette",
        "cigar",
        "tobacconist",
        "dealer"
    ],
    "wof:name":"Tobacco Town",
    "wof:placetype":"venue"
},
  "geometry": {"coordinates":[-96.770957,33.069491],"type":"Point"}
}