{
  "type": "Feature",
  "properties": {
    "iso:country":"US",
    "sg:address":"1660 S Stemmons Fwy",
    "sg:city":"Lewisville",
    "sg:classifiers":[
        {
            "category":"Real Estate",
            "subcategory":"Real Estate Services",
            "type":"Services"
        }
    ],
    "sg:phone":"+1 972 434 3650",
    "sg:postcode":"75067",
    "sg:province":"TX",
    "sg:tags":[
        "company",
        "title"
    ],
    "wof:name":"Empire Title Co",
    "wof:placetype":"venue"
},
  "geometry": {"coordinates":[-96.98839,33.026259],"type":"Point"}
}