{
  "type": "Feature",
  "properties": {
    "iso:country":"US",
    "sg:address":"4805 Lakeaire Cir",
    "sg:city":"Temple",
    "sg:classifiers":[
        {
            "category":"Travel",
            "subcategory":"Travel Agent",
            "type":"Entertainment"
        }
    ],
    "sg:phone":"+1 254 986 8145",
    "sg:postcode":"76502",
    "sg:province":"TX",
    "sg:tags":[
        "agency"
    ],
    "wof:name":"Voyages of Discovery",
    "wof:placetype":"venue"
},
  "geometry": {"coordinates":[-97.462864,31.169378],"type":"Point"}
}