{
  "type": "Feature",
  "properties": {
    "iso:country":"US",
    "sg:address":"5051 Forest Bend Rd",
    "sg:city":"Dallas",
    "sg:classifiers":[
        {
            "category":"Professional",
            "subcategory":"Advertising",
            "type":"Services"
        }
    ],
    "sg:phone":"+1 972 239 5002",
    "sg:postcode":"75244",
    "sg:province":"TX",
    "sg:tags":[
        "demonstration"
    ],
    "sg:website":"www.americandemonstration.com",
    "wof:name":"American Demonstration Product",
    "wof:placetype":"venue"
},
  "geometry": {"coordinates":[-96.82135599999999,32.922106],"type":"Point"}
}