{
  "type": "Feature",
  "properties": {
    "iso:country":"US",
    "sg:address":"2507 Plumgrove Cir",
    "sg:city":"Arlington",
    "sg:classifiers":[
        {
            "category":"Wholesale",
            "subcategory":"Apparel",
            "type":"Manufacturing & Wholesale Goods"
        }
    ],
    "sg:phone":"+1 817 994 9394",
    "sg:postcode":"76006",
    "sg:province":"TX",
    "sg:tags":[
        "clothing"
    ],
    "wof:name":"McF Designs",
    "wof:placetype":"venue"
},
  "geometry": {"coordinates":[-97.06655499999999,32.774413],"type":"Point"}
}