{
  "type": "Feature",
  "properties": {
    "iso:country":"US",
    "sg:address":"700 Lavaca Street Ste 110",
    "sg:city":"Austin",
    "sg:classifiers":[
        {
            "category":"Deli",
            "type":"Food & Drink"
        }
    ],
    "sg:phone":"+1 512 480 8881",
    "sg:postcode":"78701",
    "sg:province":"TX",
    "sg:website":"austinmurphysdeli.com",
    "wof:name":"Murphy's Deli",
    "wof:placetype":"venue"
},
  "geometry": {"coordinates":[-97.745212,30.270339],"type":"Point"}
}