{
  "type": "Feature",
  "properties": {
    "iso:country":"US",
    "sg:address":"9009 Forest Ln",
    "sg:city":"Dallas",
    "sg:classifiers":[
        {
            "category":"Health Services",
            "subcategory":"Health Practitioner",
            "type":"Services"
        }
    ],
    "sg:phone":"+1 469 330 8862",
    "sg:postcode":"75243",
    "sg:province":"TX",
    "sg:tags":[
        "gambling",
        "addiction-information",
        "treatment"
    ],
    "wof:name":"Rehabworks;",
    "wof:placetype":"venue"
},
  "geometry": {"coordinates":[-96.748452,32.909241],"type":"Point"}
}