{
  "type": "Feature",
  "properties": {
    "iso:country":"US",
    "sg:address":"5507 Bryanhurst Ln",
    "sg:city":"Spring",
    "sg:classifiers":[
        {
            "category":"Wholesale",
            "subcategory":"Electrical",
            "type":"Manufacturing & Wholesale Goods"
        }
    ],
    "sg:phone":"+1 281 376 9425",
    "sg:postcode":"77379",
    "sg:province":"TX",
    "sg:tags":[
        "equipment",
        "electronic",
        "supplies-wholesale",
        "manufacturer"
    ],
    "sg:website":"http://www.mcgheegroup.com",
    "wof:name":"The Mcghee Group Inc",
    "wof:placetype":"venue"
},
  "geometry": {"coordinates":[-95.497784,30.032302],"type":"Point"}
}