{
  "type": "Feature",
  "properties": {
    "iso:country":"US",
    "sg:address":"2024 Old Orchard Dr",
    "sg:city":"Dallas",
    "sg:classifiers":[
        {
            "category":"Professional",
            "subcategory":"Business Services",
            "type":"Services"
        }
    ],
    "sg:phone":"+1 214 943 6492",
    "sg:postcode":"75208",
    "sg:province":"TX",
    "wof:name":"RB Group LLC",
    "wof:placetype":"venue"
},
  "geometry": {"coordinates":[-96.856207,32.759106],"type":"Point"}
}