{
  "type": "Feature",
  "properties": {
    "iso:country":"US",
    "sg:address":"215 W Paisano Dr",
    "sg:city":"El Paso",
    "sg:classifiers":[
        {
            "category":"Education",
            "subcategory":"Library",
            "type":"Public Place"
        }
    ],
    "sg:phone":"+1 915 838 8967",
    "sg:postcode":"79901",
    "sg:province":"TX",
    "wof:name":"Club Televideo Christiano",
    "wof:placetype":"venue"
},
  "geometry": {"coordinates":[-106.490188,31.754811],"type":"Point"}
}