{
  "type": "Feature",
  "properties": {
    "iso:country":"US",
    "sg:address":"911 Genova Ct",
    "sg:city":"Sugar Land",
    "sg:classifiers":[
        {
            "category":"Real Estate",
            "subcategory":"Real Estate Agent",
            "type":"Services"
        }
    ],
    "sg:phone":"+1 713 582 5941",
    "sg:postcode":"77478",
    "sg:province":"TX",
    "wof:name":"Stanley Properties",
    "wof:placetype":"venue"
},
  "geometry": {"coordinates":[-95.619224,29.617819],"type":"Point"}
}