{
  "type": "Feature",
  "properties": {
    "iso:country":"US",
    "sg:address":"1113 Dayton Rd",
    "sg:city":"Midland",
    "sg:classifiers":[
        {
            "category":"Mining & Drilling",
            "type":"Manufacturing & Wholesale Goods"
        }
    ],
    "sg:phone":"+1 432 682 3030",
    "sg:postcode":"79706",
    "sg:province":"TX",
    "sg:tags":[
        "oil",
        "well"
    ],
    "sg:website":"www.eaglerockdrilling.com",
    "wof:name":"Eagle Rock Drilling LLC",
    "wof:placetype":"venue"
},
  "geometry": {"coordinates":[-102.073764,31.968712],"type":"Point"}
}