{
  "type": "Feature",
  "properties": {
    "iso:country":"US",
    "sg:address":"4002 Belgrade Dr",
    "sg:city":"Houston",
    "sg:classifiers":[
        {
            "category":"Manufacturing",
            "subcategory":"Chemicals & Compounds",
            "type":"Manufacturing & Wholesale Goods"
        }
    ],
    "sg:phone":"+1 713 721 5834",
    "sg:postcode":"77045",
    "sg:province":"TX",
    "sg:tags":[
        "technology",
        "consulting",
        "computer",
        "design"
    ],
    "wof:name":"H P Systems & Assoc",
    "wof:placetype":"venue"
},
  "geometry": {"coordinates":[-95.436573,29.640356],"type":"Point"}
}