{
  "type": "Feature",
  "properties": {
    "iso:country":"US",
    "sg:address":"609 Sheffield Dr",
    "sg:city":"Longview",
    "sg:classifiers":[
        {
            "category":"Banks & Credit Unions",
            "subcategory":"Investment Brokerage",
            "type":"Services"
        }
    ],
    "sg:phone":"+1 903 757 2077",
    "sg:postcode":"75605",
    "sg:province":"TX",
    "sg:tags":[
        "security"
    ],
    "wof:name":"First Southwest Co",
    "wof:placetype":"venue"
},
  "geometry": {"coordinates":[-94.75955399999999,32.531059],"type":"Point"}
}