{
  "type": "Feature",
  "properties": {
    "iso:country":"US",
    "sg:address":"3000 Grapevine Mills Pkwy # 338",
    "sg:city":"Grapevine",
    "sg:classifiers":[
        {
            "category":"Shopping",
            "subcategory":"Gifts & Souvenirs",
            "type":"Retail Goods"
        },
        {
            "category":"Manufacturing",
            "subcategory":"Jewelry",
            "type":"Manufacturing & Wholesale Goods"
        }
    ],
    "sg:phone":"+1 972 724 6836",
    "sg:postcode":"76051",
    "sg:province":"TX",
    "sg:tags":[
        "shop",
        "novelty"
    ],
    "sg:website":"http://www.spencersonline.com",
    "wof:name":"Spencer Gifts 189",
    "wof:placetype":"venue"
},
  "geometry": {"coordinates":[-97.037026,32.968779],"type":"Point"}
}