{
  "type": "Feature",
  "properties": {
    "iso:country":"US",
    "sg:address":"2108 Taylor St",
    "sg:city":"Texarkana",
    "sg:classifiers":[
        {
            "category":"Retail",
            "subcategory":"Auto Repair",
            "type":"Services"
        }
    ],
    "sg:phone":"+1 903 792 4358",
    "sg:postcode":"75501",
    "sg:province":"TX",
    "sg:tags":[
        "body",
        "painting",
        "repairing",
        "automobile"
    ],
    "wof:name":"Sledge Paint & Body",
    "wof:placetype":"venue"
},
  "geometry": {"coordinates":[-94.060869,33.436896],"type":"Point"}
}