{
  "type": "Feature",
  "properties": {
    "iso:country":"US",
    "sg:address":"Highland Mall 6001 Airport Blvd",
    "sg:city":"Austin",
    "sg:classifiers":[
        {
            "category":"Shopping",
            "subcategory":"Clothing, Apparel, & Fashions",
            "type":"Retail Goods"
        }
    ],
    "sg:phone":"+1 512 454 7770",
    "sg:postcode":"78752",
    "sg:province":"TX",
    "wof:name":"Papaya",
    "wof:placetype":"venue"
},
  "geometry": {"coordinates":[-97.71578,30.324252],"type":"Point"}
}