{
  "type": "Feature",
  "properties": {
    "iso:country":"US",
    "sg:address":"328 Gloria St",
    "sg:city":"Keller",
    "sg:classifiers":[
        {
            "category":"Shopping",
            "subcategory":"Computers & Home Electronics",
            "type":"Retail Goods"
        }
    ],
    "sg:phone":"+1 817 431 1672",
    "sg:postcode":"76248",
    "sg:province":"TX",
    "sg:tags":[
        "software"
    ],
    "wof:name":"Vanel",
    "wof:placetype":"venue"
},
  "geometry": {"coordinates":[-97.238437,32.928822],"type":"Point"}
}