{
  "type": "Feature",
  "properties": {
    "iso:country":"US",
    "sg:address":"1727 Keller Pkwy",
    "sg:city":"Keller",
    "sg:classifiers":[
        {
            "category":"Real Estate",
            "subcategory":"Real Estate Agent",
            "type":"Services"
        }
    ],
    "sg:phone":"+1 817 379 3111",
    "sg:postcode":"76248",
    "sg:province":"TX",
    "wof:name":"Century 21",
    "wof:placetype":"venue"
},
  "geometry": {"coordinates":[-97.212248,32.934563],"type":"Point"}
}