{
  "type": "Feature",
  "properties": {
    "iso:country":"US",
    "sg:address":"374 Shawnee Dr",
    "sg:city":"Gordonville",
    "sg:classifiers":[
        {
            "category":"Shopping",
            "subcategory":"Used Merchandise",
            "type":"Retail Goods"
        }
    ],
    "sg:phone":"+1 903 523 4857",
    "sg:postcode":"76245",
    "sg:province":"TX",
    "wof:name":"Quartersaw Antiques",
    "wof:placetype":"venue"
},
  "geometry": {"coordinates":[-96.81514799999999,33.846581],"type":"Point"}
}