{
  "type": "Feature",
  "properties": {
    "iso:country":"US",
    "sg:address":"2201 Civic Cir",
    "sg:city":"Amarillo",
    "sg:classifiers":[
        {
            "category":"Real Estate",
            "subcategory":"Real Estate Agent",
            "type":"Services"
        }
    ],
    "sg:phone":"+1 806 352 1328",
    "sg:postcode":"79109",
    "sg:province":"TX",
    "sg:tags":[
        "appraiser"
    ],
    "wof:name":"Tom Gergens",
    "wof:placetype":"venue"
},
  "geometry": {"coordinates":[-101.866151,35.190566],"type":"Point"}
}