{
  "type": "Feature",
  "properties": {
    "iso:country":"US",
    "sg:address":"406 S Sandra St",
    "sg:city":"Conroe",
    "sg:classifiers":[
        {
            "category":"Building & Trades",
            "subcategory":"Landscaping Services",
            "type":"Services"
        }
    ],
    "sg:phone":"+1 936 788 1837",
    "sg:postcode":"77301",
    "sg:province":"TX",
    "sg:tags":[
        "landscape"
    ],
    "wof:name":"Aguilar Bros Landscaping Lawn",
    "wof:placetype":"venue"
},
  "geometry": {"coordinates":[-95.46341700000001,30.302968],"type":"Point"}
}