{
  "type": "Feature",
  "properties": {
    "iso:country":"US",
    "sg:address":"2131 E Cesar Chavez St",
    "sg:city":"Austin",
    "sg:classifiers":[
        {
            "category":"Banks & Credit Unions",
            "subcategory":"Financial Services",
            "type":"Services"
        }
    ],
    "sg:phone":"+1 512 391 0133",
    "sg:postcode":"78702",
    "sg:province":"TX",
    "wof:name":"New Life Outreach Payee Servic",
    "wof:placetype":"venue"
},
  "geometry": {"coordinates":[-97.721453,30.256003],"type":"Point"}
}