{
  "type": "Feature",
  "properties": {
    "iso:country":"US",
    "sg:address":"9125 E R L Thornton Fwy",
    "sg:city":"Dallas",
    "sg:classifiers":[
        {
            "category":"Organizations",
            "subcategory":"Community Association",
            "type":"Services"
        },
        {
            "category":"Shopping",
            "subcategory":"Clothing, Apparel, & Fashions",
            "type":"Retail Goods"
        }
    ],
    "sg:phone":"+1 214 660 9912",
    "sg:postcode":"75228",
    "sg:province":"TX",
    "sg:tags":[
        "club"
    ],
    "wof:name":"Palace Men's Club",
    "wof:placetype":"venue"
},
  "geometry": {"coordinates":[-96.683376,32.797789],"type":"Point"}
}