{
  "type": "Feature",
  "properties": {
    "iso:country":"US",
    "sg:address":"2922 Pat Booker Rd",
    "sg:city":"Universal City",
    "sg:classifiers":[
        {
            "category":"Shopping",
            "subcategory":"Used Merchandise",
            "type":"Retail Goods"
        }
    ],
    "sg:phone":"+1 210 658 0104",
    "sg:postcode":"78148",
    "sg:province":"TX",
    "wof:name":"Top Dollar Pawn Shop",
    "wof:placetype":"venue"
},
  "geometry": {"coordinates":[-98.32295999999999,29.558771],"type":"Point"}
}