{
  "type": "Feature",
  "properties": {
    "iso:country":"US",
    "sg:address":"9300 S I H 35",
    "sg:city":"Austin",
    "sg:classifiers":[
        {
            "category":"Banks & Credit Unions",
            "subcategory":"Bank",
            "type":"Services"
        }
    ],
    "sg:phone":"+1 512 292 8978",
    "sg:postcode":"78748",
    "sg:province":"TX",
    "wof:name":"Woodforest National Bank Inside Wal-Mart",
    "wof:placetype":"venue"
},
  "geometry": {"coordinates":[-97.78812499999999,30.164744],"type":"Point"}
}