{
  "type": "Feature",
  "properties": {
    "iso:country":"US",
    "sg:address":"8118 Ravenswood Rd",
    "sg:city":"Granbury",
    "sg:classifiers":[
        {
            "category":"Freight",
            "type":"Transportation"
        }
    ],
    "sg:phone":"+1 817 279 9897",
    "sg:postcode":"76049",
    "sg:province":"TX",
    "sg:tags":[
        "local",
        "storage",
        "trucking"
    ],
    "wof:name":"Texas Truck & Rail Transfer",
    "wof:placetype":"venue"
},
  "geometry": {"coordinates":[-97.643699,32.372755],"type":"Point"}
}