{
  "type": "Feature",
  "properties": {
    "iso:country":"US",
    "sg:address":"9050 Cook Rd",
    "sg:city":"Houston",
    "sg:classifiers":[
        {
            "category":"Professional",
            "subcategory":"Business Services",
            "type":"Services"
        }
    ],
    "sg:phone":"+1 281 564 7099",
    "sg:postcode":"77099",
    "sg:province":"TX",
    "sg:tags":[
        "broker",
        "merchandise"
    ],
    "wof:name":"Araya Brokers",
    "wof:placetype":"venue"
},
  "geometry": {"coordinates":[-95.595806,29.680484],"type":"Point"}
}