{
  "type": "Feature",
  "properties": {
    "iso:country":"US",
    "sg:address":"215 S Fannin St",
    "sg:city":"Amarillo",
    "sg:classifiers":[
        {
            "category":"Professional",
            "subcategory":"Testing Lab",
            "type":"Services"
        }
    ],
    "sg:phone":"+1 806 374 8378",
    "sg:postcode":"79106",
    "sg:province":"TX",
    "sg:tags":[
        "laboratory"
    ],
    "wof:name":"Cornerstone Testing & Engnrng",
    "wof:placetype":"venue"
},
  "geometry": {"coordinates":[-101.858305,35.213743],"type":"Point"}
}