{
  "type": "Feature",
  "properties": {
    "iso:country":"US",
    "sg:address":"503 S Marienfeld St",
    "sg:city":"Midland",
    "sg:classifiers":[
        {
            "category":"Autos & Motor Vehicles",
            "subcategory":"Fuel & Gas Station",
            "type":"Retail Goods"
        }
    ],
    "sg:phone":"+1 432 686 7349",
    "sg:postcode":"79701",
    "sg:province":"TX",
    "sg:tags":[
        "oil"
    ],
    "wof:name":"Exxon Mobil Corp",
    "wof:placetype":"venue"
},
  "geometry": {"coordinates":[-102.07907299999999,31.992704],"type":"Point"}
}