{
  "type": "Feature",
  "properties": {
    "iso:country":"US",
    "sg:address":"7045 Allen Place Dr",
    "sg:city":"Fort Worth",
    "sg:classifiers":[
        {
            "category":"Professional",
            "subcategory":"Management & Consulting",
            "type":"Services"
        }
    ],
    "sg:phone":"+1 817 737 8489",
    "sg:postcode":"76116",
    "sg:province":"TX",
    "wof:name":"Allen Place Marketing Inc",
    "wof:placetype":"venue"
},
  "geometry": {"coordinates":[-97.42939800000001,32.697164],"type":"Point"}
}