{
  "type": "Feature",
  "properties": {
    "iso:country":"US",
    "sg:address":"1927 E Belt Line Rd # 166",
    "sg:city":"Dallas",
    "sg:classifiers":[
        {
            "category":"Professional",
            "subcategory":"Employment Agencies",
            "type":"Services"
        }
    ],
    "sg:phone":"+1 469 568 7100",
    "sg:postcode":"75201",
    "sg:province":"TX",
    "wof:name":"One Staffing Solution",
    "wof:placetype":"venue"
},
  "geometry": {"coordinates":[-96.603554,32.675477],"type":"Point"}
}