{
  "type": "Feature",
  "properties": {
    "iso:country":"US",
    "sg:address":"6420 Verm Rd",
    "sg:city":"Matagorda",
    "sg:classifiers":[
        {
            "category":"Recreation",
            "type":"Entertainment"
        }
    ],
    "sg:phone":"+1 979 863 2603",
    "sg:postcode":"77474",
    "sg:province":"TX",
    "sg:tags":[
        "parks"
    ],
    "wof:name":"Matagorda Bay Nature Park",
    "wof:placetype":"venue"
},
  "geometry": {"coordinates":[-96.074037,29.71234],"type":"Point"}
}