{
  "type": "Feature",
  "properties": {
    "iso:country":"US",
    "sg:address":"38 Torreys Post",
    "sg:city":"San Antonio",
    "sg:classifiers":[
        {
            "category":"Professional",
            "subcategory":"Lawyer & Legal Services",
            "type":"Services"
        }
    ],
    "sg:phone":"+1 210 979 9998",
    "sg:postcode":"78240",
    "sg:province":"TX",
    "sg:tags":[
        "naturalization",
        "immigration"
    ],
    "wof:name":"Immigration Bonding Svc",
    "wof:placetype":"venue"
},
  "geometry": {"coordinates":[-98.594398,29.521061],"type":"Point"}
}