{
  "type": "Feature",
  "properties": {
    "iso:country":"US",
    "sg:address":"204 E US Hwy 80",
    "sg:city":"White Oak",
    "sg:classifiers":[
        {
            "category":"Health Services",
            "subcategory":"Doctor",
            "type":"Services"
        },
        {
            "category":"Health Services",
            "subcategory":"Medical Lab",
            "type":"Services"
        }
    ],
    "sg:phone":"+1 903 295 4325",
    "sg:postcode":"75693",
    "sg:province":"TX",
    "sg:tags":[
        "laboratory",
        "surgeon",
        "physician"
    ],
    "wof:name":"Family First Medical Clinic",
    "wof:placetype":"venue"
},
  "geometry": {"coordinates":[-94.85709199999999,32.519147],"type":"Point"}
}