{
  "type": "Feature",
  "properties": {
    "iso:country":"US",
    "sg:address":"18823 Tomato St",
    "sg:city":"Spring",
    "sg:classifiers":[
        {
            "category":"Building & Trades",
            "subcategory":"Construction",
            "type":"Services"
        }
    ],
    "sg:phone":"+1 281 257 1039",
    "sg:postcode":"77379",
    "sg:province":"TX",
    "sg:tags":[
        "house",
        "general",
        "contractor"
    ],
    "wof:name":"C & C Constructors",
    "wof:placetype":"venue"
},
  "geometry": {"coordinates":[-95.49570799999999,30.046187],"type":"Point"}
}