{
  "type": "Feature",
  "properties": {
    "iso:country":"US",
    "sg:address":"3905 Liberty Rd",
    "sg:city":"Houston",
    "sg:classifiers":[
        {
            "category":"Retail",
            "subcategory":"Self-service Laundry",
            "type":"Services"
        },
        {
            "category":"Retail",
            "subcategory":"Laundry & Dry Cleaning",
            "type":"Services"
        }
    ],
    "sg:phone":"+1 713 673 4303",
    "sg:postcode":"77026",
    "sg:province":"TX",
    "sg:tags":[
        "coin"
    ],
    "wof:name":"Braden's Washateria",
    "wof:placetype":"venue"
},
  "geometry": {"coordinates":[-95.33105999999999,29.78499],"type":"Point"}
}