{
  "type": "Feature",
  "properties": {
    "iso:country":"US",
    "sg:address":"4455 Mill Run Rd",
    "sg:city":"Dallas",
    "sg:classifiers":[
        {
            "category":"Real Estate",
            "subcategory":"Real Estate Operator",
            "type":"Services"
        }
    ],
    "sg:phone":"+1 972 661 3722",
    "sg:postcode":"75244",
    "sg:province":"TX",
    "sg:tags":[
        "building",
        "nonresidential"
    ],
    "wof:name":"Oslin Energy Properties",
    "wof:placetype":"venue"
},
  "geometry": {"coordinates":[-96.82976499999999,32.924154],"type":"Point"}
}