{
  "type": "Feature",
  "properties": {
    "iso:country":"US",
    "sg:address":"1419 Chesterton Dr",
    "sg:city":"Richardson",
    "sg:classifiers":[
        {
            "category":"Professional",
            "subcategory":"Management & Consulting",
            "type":"Services"
        }
    ],
    "sg:phone":"+1 972 234 1370",
    "sg:postcode":"75080",
    "sg:province":"TX",
    "sg:tags":[
        "communications",
        "consultant"
    ],
    "wof:name":"Consulting PH",
    "wof:placetype":"venue"
},
  "geometry": {"coordinates":[-96.76575200000001,32.974685],"type":"Point"}
}