{
  "type": "Feature",
  "properties": {
    "iso:country":"US",
    "sg:address":"9805 Monroe Rd",
    "sg:city":"Houston",
    "sg:classifiers":[
        {
            "category":"Wholesale",
            "subcategory":"Machinery & Supplies",
            "type":"Manufacturing & Wholesale Goods"
        }
    ],
    "sg:phone":"+1 713 910 6540",
    "sg:postcode":"77075",
    "sg:province":"TX",
    "sg:tags":[
        "valve"
    ],
    "wof:name":"Mainland Valve & Fittings",
    "wof:placetype":"venue"
},
  "geometry": {"coordinates":[-95.266712,29.623254],"type":"Point"}
}