{
  "type": "Feature",
  "properties": {
    "iso:country":"US",
    "sg:address":"615 Louisiana St., Ste. 100",
    "sg:city":"Houston",
    "sg:classifiers":[
        {
            "category":"Arts & Performance",
            "subcategory":"Arts Center",
            "type":"Entertainment"
        }
    ],
    "sg:phone":"+1 713 227 4772",
    "sg:postcode":"77002",
    "sg:province":"TX",
    "sg:tags":[
        "performing"
    ],
    "sg:website":"www.spahouston.org",
    "wof:name":"Society For the Performing Arts Administrative",
    "wof:placetype":"venue"
},
  "geometry": {"coordinates":[-95.365019,29.760866],"type":"Point"}
}