{
  "type": "Feature",
  "properties": {
    "iso:country":"US",
    "sg:address":"815 Commerce Rd",
    "sg:city":"Alice",
    "sg:classifiers":[
        {
            "category":"Mining & Drilling",
            "type":"Manufacturing & Wholesale Goods"
        }
    ],
    "sg:phone":"+1 361 668 3382",
    "sg:postcode":"78332",
    "sg:province":"TX",
    "sg:tags":[
        "field",
        "oil"
    ],
    "wof:name":"Pro-Technics Intl Inc",
    "wof:placetype":"venue"
},
  "geometry": {"coordinates":[-98.07946200000001,27.775833],"type":"Point"}
}