{
  "type": "Feature",
  "properties": {
    "iso:country":"US",
    "sg:address":"111 Old Campbell Rd",
    "sg:city":"Seguin",
    "sg:classifiers":[
        {
            "category":"Shopping",
            "subcategory":"Hobbies, Toys, & Games",
            "type":"Retail Goods"
        }
    ],
    "sg:phone":"+1 830 303 5236",
    "sg:postcode":"78155",
    "sg:province":"TX",
    "wof:name":"Daves Hobby Shop",
    "wof:placetype":"venue"
},
  "geometry": {"coordinates":[-98.008582,29.526414],"type":"Point"}
}