{
  "type": "Feature",
  "properties": {
    "iso:country":"US",
    "sg:address":"8525 Ferndale Rd",
    "sg:city":"Dallas",
    "sg:classifiers":[
        {
            "category":"Professional",
            "subcategory":"Lawyer & Legal Services",
            "type":"Services"
        }
    ],
    "sg:phone":"+1 214 343 9119",
    "sg:postcode":"75238",
    "sg:province":"TX",
    "wof:name":"Kinney Craig Atty",
    "wof:placetype":"venue"
},
  "geometry": {"coordinates":[-96.710899,32.864799],"type":"Point"}
}