{
  "type": "Feature",
  "properties": {
    "iso:country":"US",
    "sg:address":"110 Rimrock Ln",
    "sg:city":"San Marcos",
    "sg:classifiers":[
        {
            "category":"Farming",
            "subcategory":"Livestock Farm",
            "type":"Manufacturing & Wholesale Goods"
        }
    ],
    "sg:phone":"+1 512 392 3422",
    "sg:postcode":"78666",
    "sg:province":"TX",
    "sg:tags":[
        "beef",
        "feedlot",
        "cattle"
    ],
    "wof:name":"K Bar T",
    "wof:placetype":"venue"
},
  "geometry": {"coordinates":[-98.01709200000001,29.895467],"type":"Point"}
}