{
  "type": "Feature",
  "properties": {
    "iso:country":"US",
    "sg:address":"2304 Midwestern Pkwy",
    "sg:city":"Wichita Falls",
    "sg:classifiers":[
        {
            "category":"Insurance",
            "subcategory":"Insurance Agent",
            "type":"Services"
        }
    ],
    "sg:phone":"+1 940 691 2601",
    "sg:postcode":"76308",
    "sg:province":"TX",
    "wof:name":"Jerri Thomas Insurance",
    "wof:placetype":"venue"
},
  "geometry": {"coordinates":[-98.51845899999999,33.870544],"type":"Point"}
}