{
  "type": "Feature",
  "properties": {
    "iso:country":"US",
    "sg:address":"10202 FM 1935",
    "sg:city":"Brenham",
    "sg:classifiers":[
        {
            "category":"Organizations",
            "subcategory":"Religious Organization",
            "type":"Services"
        }
    ],
    "sg:phone":"+1 979 836 7303",
    "sg:postcode":"77833",
    "sg:province":"TX",
    "wof:name":"Bethlehem Lutheran Church",
    "wof:placetype":"venue"
},
  "geometry": {"coordinates":[-96.27843300000001,30.319694],"type":"Point"}
}