{
  "type": "Feature",
  "properties": {
    "iso:country":"US",
    "sg:address":"5317 Schumacher Ln",
    "sg:city":"Houston",
    "sg:classifiers":[
        {
            "category":"Professional",
            "subcategory":"Engineering",
            "type":"Services"
        }
    ],
    "sg:phone":"+1 713 622 8279",
    "sg:postcode":"77056",
    "sg:province":"TX",
    "wof:name":"Insight Friends and Family",
    "wof:placetype":"venue"
},
  "geometry": {"coordinates":[-95.470707,29.729033],"type":"Point"}
}