{
  "type": "Feature",
  "properties": {
    "iso:country":"US",
    "sg:address":"3892 Happy Canyon Dr",
    "sg:city":"Dallas",
    "sg:classifiers":[
        {
            "category":"Retail",
            "subcategory":"Repair Shop",
            "type":"Services"
        }
    ],
    "sg:phone":"+1 972 225 6022",
    "sg:postcode":"75241",
    "sg:province":"TX",
    "wof:name":"Willis TV and Radio Service",
    "wof:placetype":"venue"
},
  "geometry": {"coordinates":[-96.75500599999999,32.674685],"type":"Point"}
}