{
  "type": "Feature",
  "properties": {
    "iso:country":"US",
    "sg:address":"8116 Westglen Dr",
    "sg:city":"Houston",
    "sg:classifiers":[
        {
            "category":"Communications",
            "subcategory":"Radio Station",
            "type":"Services"
        }
    ],
    "sg:phone":"+1 713 974 1433",
    "sg:postcode":"77063",
    "sg:province":"TX",
    "wof:name":"Radio Luz",
    "wof:placetype":"venue"
},
  "geometry": {"coordinates":[-95.507887,29.725137],"type":"Point"}
}