{
  "type": "Feature",
  "properties": {
    "iso:country":"US",
    "sg:address":"4904 Firestone Dr",
    "sg:city":"College Station",
    "sg:classifiers":[
        {
            "category":"Professional",
            "subcategory":"Management & Consulting",
            "type":"Services"
        }
    ],
    "sg:phone":"+1 979 690 9301",
    "sg:postcode":"77845",
    "sg:province":"TX",
    "wof:name":"Bracket & Associates",
    "wof:placetype":"venue"
},
  "geometry": {"coordinates":[-96.23936,30.561912],"type":"Point"}
}