{
  "type": "Feature",
  "properties": {
    "iso:country":"US",
    "sg:address":"2330 Apollo Cir",
    "sg:city":"Carrollton",
    "sg:classifiers":[
        {
            "category":"Shopping",
            "subcategory":"Bicycles & Sporting Goods",
            "type":"Retail Goods"
        }
    ],
    "sg:phone":"+1 972 390 8447",
    "sg:postcode":"75006",
    "sg:province":"TX",
    "sg:tags":[
        "equipment",
        "exercise",
        "fitness"
    ],
    "wof:name":"Bikes And Fitness Com",
    "wof:placetype":"venue"
},
  "geometry": {"coordinates":[-96.876124,32.960811],"type":"Point"}
}