{
  "type": "Feature",
  "properties": {
    "iso:country":"US",
    "sg:address":"354 E Elizabeth St",
    "sg:city":"Brownsville",
    "sg:classifiers":[
        {
            "category":"Social Services",
            "subcategory":"Adult Care",
            "type":"Services"
        }
    ],
    "sg:phone":"+1 956 986 6292",
    "sg:postcode":"78520",
    "sg:province":"TX",
    "sg:tags":[
        "residential"
    ],
    "wof:name":"La Placita",
    "wof:placetype":"venue"
},
  "geometry": {"coordinates":[-97.50426,25.906736],"type":"Point"}
}