{
  "type": "Feature",
  "properties": {
    "iso:country":"US",
    "sg:address":"4717 Osborne Dr",
    "sg:city":"El Paso",
    "sg:classifiers":[
        {
            "category":"Restaurant",
            "type":"Food & Drink"
        }
    ],
    "sg:phone":"+1 915 590 7767",
    "sg:postcode":"79922",
    "sg:province":"TX",
    "wof:name":"Pizza Pros",
    "wof:placetype":"venue"
},
  "geometry": {"coordinates":[-106.57208799999999,31.836783],"type":"Point"}
}