{
  "type": "Feature",
  "properties": {
    "iso:country":"US",
    "sg:address":"1446 Halsey Way",
    "sg:city":"Carrollton",
    "sg:classifiers":[
        {
            "category":"Banks & Credit Unions",
            "subcategory":"Bank",
            "type":"Services"
        }
    ],
    "sg:phone":"+1 972 242 1398",
    "sg:postcode":"75007",
    "sg:province":"TX",
    "sg:tags":[
        "other",
        "plan",
        "card"
    ],
    "wof:name":"Southwest Credit Systems",
    "wof:placetype":"venue"
},
  "geometry": {"coordinates":[-96.922256,32.987836],"type":"Point"}
}