{
  "type": "Feature",
  "properties": {
    "iso:country":"US",
    "sg:address":"4826 Aldine Mail Rd",
    "sg:city":"Houston",
    "sg:classifiers":[
        {
            "category":"Professional",
            "type":"Services"
        }
    ],
    "sg:phone":"+1 281 614 8323",
    "sg:postcode":"77039",
    "sg:province":"TX",
    "wof:name":"Emilio Perez Steel",
    "wof:placetype":"venue"
},
  "geometry": {"coordinates":[-95.318777,29.90288],"type":"Point"}
}