{
  "type": "Feature",
  "properties": {
    "iso:country":"US",
    "sg:address":"6930 Spanky Branch Dr",
    "sg:city":"Dallas",
    "sg:classifiers":[
        {
            "category":"Personal",
            "subcategory":"Beauty Salon",
            "type":"Services"
        }
    ],
    "sg:phone":"+1 972 931 8715",
    "sg:postcode":"75248",
    "sg:province":"TX",
    "wof:name":"Brenda's Beautique Lines-Finds",
    "wof:placetype":"venue"
},
  "geometry": {"coordinates":[-96.78751099999999,32.982415],"type":"Point"}
}