{
  "type": "Feature",
  "properties": {
    "iso:country":"US",
    "sg:address":"7575 College St",
    "sg:city":"Beaumont",
    "sg:classifiers":[
        {
            "category":"Shopping",
            "type":"Retail Goods"
        }
    ],
    "sg:phone":"+1 409 860 1664",
    "sg:postcode":"77707",
    "sg:province":"TX",
    "sg:tags":[
        "item",
        "boutique"
    ],
    "wof:name":"Bargain Closet Boutique & Gifts",
    "wof:placetype":"venue"
},
  "geometry": {"coordinates":[-94.18052299999999,30.067416],"type":"Point"}
}