{
  "type": "Feature",
  "properties": {
    "iso:country":"US",
    "sg:address":"4292 Old Hwy 105 W",
    "sg:city":"Conroe",
    "sg:classifiers":[
        {
            "category":"Retail",
            "subcategory":"Repair Shop",
            "type":"Services"
        }
    ],
    "sg:phone":"+1 936 588 6868",
    "sg:postcode":"77304",
    "sg:province":"TX",
    "sg:tags":[
        "upholsterer"
    ],
    "wof:name":"Bryan's Upholstery",
    "wof:placetype":"venue"
},
  "geometry": {"coordinates":[-95.55940099999999,30.334763],"type":"Point"}
}