{
  "type": "Feature",
  "properties": {
    "iso:country":"US",
    "sg:address":"3135 Weatherford St",
    "sg:city":"La Porte",
    "sg:classifiers":[
        {
            "category":"Wholesale",
            "subcategory":"Non-durable Goods",
            "type":"Manufacturing & Wholesale Goods"
        }
    ],
    "sg:phone":"+1 281 701 4273",
    "sg:postcode":"77571",
    "sg:province":"TX",
    "wof:name":"Makobal Inc",
    "wof:placetype":"venue"
},
  "geometry": {"coordinates":[-95.012912,29.626783],"type":"Point"}
}