{
  "type": "Feature",
  "properties": {
    "iso:country":"US",
    "sg:address":"7054 Pipestone",
    "sg:city":"Schertz",
    "sg:classifiers":[
        {
            "category":"Building & Trades",
            "subcategory":"Construction",
            "type":"Services"
        }
    ],
    "sg:phone":"+1 210 651 4452",
    "sg:postcode":"78154",
    "sg:province":"TX",
    "sg:tags":[
        "water",
        "sewer",
        "utility",
        "contractor"
    ],
    "wof:name":"Pesado Construction Company",
    "wof:placetype":"venue"
},
  "geometry": {"coordinates":[-98.280469,29.614152],"type":"Point"}
}