{
  "type": "Feature",
  "properties": {
    "iso:country":"US",
    "sg:address":"511 Johnson St",
    "sg:city":"Pasadena",
    "sg:classifiers":[
        {
            "category":"Retail",
            "subcategory":"Repair Shop",
            "type":"Services"
        }
    ],
    "sg:phone":"+1 713 477 8285",
    "sg:postcode":"77506",
    "sg:province":"TX",
    "wof:name":"Loves Cleaning",
    "wof:placetype":"venue"
},
  "geometry": {"coordinates":[-95.206254,29.703725],"type":"Point"}
}