{
  "type": "Feature",
  "properties": {
    "iso:country":"US",
    "sg:address":"5505 Exeter Dr",
    "sg:city":"Austin",
    "sg:classifiers":[
        {
            "category":"Shopping",
            "subcategory":"Bicycles & Sporting Goods",
            "type":"Retail Goods"
        }
    ],
    "sg:phone":"+1 512 926 0318",
    "sg:postcode":"78723",
    "sg:province":"TX",
    "wof:name":"Anew Technologies",
    "wof:placetype":"venue"
},
  "geometry": {"coordinates":[-97.682834,30.305202],"type":"Point"}
}