{
  "type": "Feature",
  "properties": {
    "iso:country":"US",
    "sg:address":"700 Park St",
    "sg:city":"Baytown",
    "sg:classifiers":[
        {
            "category":"Autos & Motor Vehicles",
            "subcategory":"Automobile Sales",
            "type":"Retail Goods"
        }
    ],
    "sg:phone":"+1 281 422 3399",
    "sg:postcode":"77520",
    "sg:province":"TX",
    "sg:tags":[
        "car",
        "used",
        "dealer"
    ],
    "wof:name":"Granny's Used Cars",
    "wof:placetype":"venue"
},
  "geometry": {"coordinates":[-94.97480899999999,29.746558],"type":"Point"}
}