{
  "type": "Feature",
  "properties": {
    "iso:country":"US",
    "sg:address":"2317 Roosevelt Dr",
    "sg:city":"Arlington",
    "sg:classifiers":[
        {
            "category":"Professional",
            "subcategory":"Management & Consulting",
            "type":"Services"
        }
    ],
    "sg:phone":"+1 817 274 1666",
    "sg:postcode":"76016",
    "sg:province":"TX",
    "wof:name":"Medical Centre Owners Assn Inc",
    "wof:placetype":"venue"
},
  "geometry": {"coordinates":[-97.15555000000001,32.703422],"type":"Point"}
}