{
  "type": "Feature",
  "properties": {
    "iso:country":"US",
    "sg:address":"105 Rocky Rd",
    "sg:city":"Marble Falls",
    "sg:classifiers":[
        {
            "category":"Building & Trades",
            "subcategory":"Equipment Rental",
            "type":"Services"
        }
    ],
    "sg:phone":"+1 830 798 8450",
    "sg:postcode":"78654",
    "sg:province":"TX",
    "wof:name":"Outback Party Rentals",
    "wof:placetype":"venue"
},
  "geometry": {"coordinates":[-98.28068399999999,30.540408],"type":"Point"}
}