{
  "type": "Feature",
  "properties": {
    "iso:country":"US",
    "sg:address":"3300 Reeder Dr",
    "sg:city":"Amarillo",
    "sg:classifiers":[
        {
            "category":"Professional",
            "type":"Services"
        }
    ],
    "sg:phone":"+1 806 354 8373",
    "sg:postcode":"79121",
    "sg:province":"TX",
    "wof:name":"Melody A Willis",
    "wof:placetype":"venue"
},
  "geometry": {"coordinates":[-101.93513299999999,35.176598],"type":"Point"}
}