{
  "type": "Feature",
  "properties": {
    "iso:country":"US",
    "sg:address":"3346 Galaway Bay Dr",
    "sg:city":"Grand Prairie",
    "sg:classifiers":[
        {
            "category":"Professional",
            "subcategory":"Management & Consulting",
            "type":"Services"
        }
    ],
    "sg:phone":"+1 972 602 9140",
    "sg:postcode":"75052",
    "sg:province":"TX",
    "wof:name":"Kemblelewen Management Group",
    "wof:placetype":"venue"
},
  "geometry": {"coordinates":[-97.056879,32.688431],"type":"Point"}
}