{
  "type": "Feature",
  "properties": {
    "iso:country":"US",
    "sg:address":"11322 North Fwy",
    "sg:city":"Houston",
    "sg:classifiers":[
        {
            "category":"Retail",
            "subcategory":"Auto Rental",
            "type":"Services"
        }
    ],
    "sg:phone":"+1 281 760 3243",
    "sg:postcode":"77037",
    "sg:province":"TX",
    "sg:tags":[
        "car"
    ],
    "wof:name":"Enterprise Rent-A Car",
    "wof:placetype":"venue"
},
  "geometry": {"coordinates":[-95.41120100000001,29.930099],"type":"Point"}
}