{
  "type": "Feature",
  "properties": {
    "iso:country":"US",
    "sg:address":"2210 S Hughes St",
    "sg:city":"Amarillo",
    "sg:classifiers":[
        {
            "category":"Retail",
            "subcategory":"Veterinary Services",
            "type":"Services"
        }
    ],
    "sg:phone":"+1 806 373 7711",
    "sg:postcode":"79109",
    "sg:province":"TX",
    "sg:tags":[
        "veterinarian"
    ],
    "wof:name":"William P Swann DVM",
    "wof:placetype":"venue"
},
  "geometry": {"coordinates":[-101.849797,35.187472],"type":"Point"}
}