{
  "type": "Feature",
  "properties": {
    "iso:country":"US",
    "sg:address":"1917 Maxwell Dr",
    "sg:city":"Lewisville",
    "sg:classifiers":[
        {
            "category":"Shopping",
            "subcategory":"Musical Instruments",
            "type":"Retail Goods"
        }
    ],
    "sg:phone":"+1 972 317 6877",
    "sg:postcode":"75077",
    "sg:province":"TX",
    "wof:name":"Minneapolis Piano Company",
    "wof:placetype":"venue"
},
  "geometry": {"coordinates":[-97.042205,33.073324],"type":"Point"}
}