{
  "type": "Feature",
  "properties": {
    "iso:country":"US",
    "sg:address":"210 S Main St",
    "sg:city":"Donna",
    "sg:classifiers":[
        {
            "category":"Professional",
            "subcategory":"Accounting & Tax Preparation",
            "type":"Services"
        }
    ],
    "sg:phone":"+1 956 464 5991",
    "sg:postcode":"78537",
    "sg:province":"TX",
    "wof:name":"Garza Adalberto",
    "wof:placetype":"venue"
},
  "geometry": {"coordinates":[-98.054464,26.169152],"type":"Point"}
}