{
  "type": "Feature",
  "properties": {
    "iso:country":"US",
    "sg:address":"16639 Kuykendahl Rd",
    "sg:city":"Houston",
    "sg:classifiers":[
        {
            "category":"Retail",
            "subcategory":"Car Wash",
            "type":"Services"
        }
    ],
    "sg:phone":"+1 281 631 0036",
    "sg:postcode":"77068",
    "sg:province":"TX",
    "sg:tags":[
        "carwash"
    ],
    "wof:name":"Klein Hand Car Wash",
    "wof:placetype":"venue"
},
  "geometry": {"coordinates":[-95.472273,30.018738],"type":"Point"}
}