{
  "type": "Feature",
  "properties": {
    "iso:country":"US",
    "sg:address":"2525 Wallingwood Drive",
    "sg:city":"Austin",
    "sg:classifiers":[
        {
            "category":"Professional",
            "subcategory":"Lawyer & Legal Services",
            "type":"Services"
        }
    ],
    "sg:phone":"+1 512 328 0048",
    "sg:postcode":"78746",
    "sg:province":"TX",
    "wof:name":"Dwight Marianne Atty",
    "wof:placetype":"venue"
},
  "geometry": {"coordinates":[-97.784913,30.264222],"type":"Point"}
}