{
  "type": "Feature",
  "properties": {
    "iso:country":"US",
    "sg:address":"217 Co Rd 403",
    "sg:city":"Mc Kinney",
    "sg:classifiers":[
        {
            "category":"Professional",
            "subcategory":"Computer Services",
            "type":"Services"
        }
    ],
    "sg:phone":"+1 972 562 5997",
    "sg:postcode":"75069",
    "sg:province":"TX",
    "sg:tags":[
        "internet"
    ],
    "sg:website":"www.fishingsports.com",
    "wof:name":"Fishingsports Comm",
    "wof:placetype":"venue"
},
  "geometry": {"coordinates":[-96.54806499999999,33.182367],"type":"Point"}
}