{
  "type": "Feature",
  "properties": {
    "iso:country":"US",
    "sg:address":"393 Knollwood Rd",
    "sg:city":"Sherman",
    "sg:classifiers":[
        {
            "category":"Professional",
            "subcategory":"Accounting & Tax Preparation",
            "type":"Services"
        }
    ],
    "sg:phone":"+1 903 893 2842",
    "sg:postcode":"75092",
    "sg:province":"TX",
    "wof:name":"Ernst Bkkpng & Tax Serv",
    "wof:placetype":"venue"
},
  "geometry": {"coordinates":[-96.619812,33.68373],"type":"Point"}
}