{
  "type": "Feature",
  "properties": {
    "iso:country":"US",
    "sg:address":"5811 Pinewood Springs Dr",
    "sg:city":"Houston",
    "sg:classifiers":[
        {
            "category":"Local Transit",
            "type":"Transportation"
        }
    ],
    "sg:phone":"+1 281 489 0033",
    "sg:postcode":"77066",
    "sg:province":"TX",
    "sg:tags":[
        "airport"
    ],
    "wof:name":"All Around Airport Transport",
    "wof:placetype":"venue"
},
  "geometry": {"coordinates":[-95.508523,29.967964],"type":"Point"}
}