{
  "type": "Feature",
  "properties": {
    "iso:country":"US",
    "sg:address":"1301 Lavaca St",
    "sg:city":"Austin",
    "sg:classifiers":[
        {
            "category":"Bars & Pubs",
            "type":"Food & Drink"
        }
    ],
    "sg:phone":"+1 512 474 6481",
    "sg:postcode":"78701",
    "sg:province":"TX",
    "sg:tags":[
        "club",
        "night"
    ],
    "sg:website":"www.charliesaustin.com",
    "wof:name":"Charlie's Austin",
    "wof:placetype":"venue"
},
  "geometry": {"coordinates":[-97.742272,30.276663],"type":"Point"}
}