{
  "type": "Feature",
  "properties": {
    "iso:country":"US",
    "sg:address":"422 Harmon Dr",
    "sg:city":"San Antonio",
    "sg:classifiers":[
        {
            "category":"Shopping",
            "type":"Retail Goods"
        }
    ],
    "sg:phone":"+1 210 828 6807",
    "sg:postcode":"78209",
    "sg:province":"TX",
    "sg:tags":[
        "merchandise"
    ],
    "wof:name":"Nora D Simmons",
    "wof:placetype":"venue"
},
  "geometry": {"coordinates":[-98.44266,29.491351],"type":"Point"}
}