{
  "type": "Feature",
  "properties": {
    "iso:country":"US",
    "sg:address":"4514 Cole Ave Ste 903",
    "sg:city":"Dallas",
    "sg:classifiers":[
        {
            "category":"Health Services",
            "subcategory":"Doctor",
            "type":"Services"
        }
    ],
    "sg:phone":"+1 214 559 4671",
    "sg:postcode":"75205",
    "sg:province":"TX",
    "sg:tags":[
        "surgeon",
        "oral"
    ],
    "wof:name":"Bohmfalk Chris F DDS",
    "wof:placetype":"venue"
},
  "geometry": {"coordinates":[-96.789597,32.8218],"type":"Point"}
}