{
  "type": "Feature",
  "properties": {
    "iso:country":"US",
    "sg:address":"340 N Sam Houston Pkwy E Ste 269",
    "sg:city":"Houston",
    "sg:classifiers":[
        {
            "category":"Professional",
            "subcategory":"Employment Agencies",
            "type":"Services"
        }
    ],
    "sg:phone":"+1 281 893 4401",
    "sg:postcode":"77060",
    "sg:province":"TX",
    "sg:website":"e-proact.com/",
    "wof:name":"Proaction Careers",
    "wof:placetype":"venue"
},
  "geometry": {"coordinates":[-95.359739,29.595346],"type":"Point"}
}