{
  "type": "Feature",
  "properties": {
    "iso:country":"US",
    "sg:address":"4613 Starlight Dr",
    "sg:city":"Fort Worth",
    "sg:classifiers":[
        {
            "category":"Mining & Drilling",
            "type":"Manufacturing & Wholesale Goods"
        }
    ],
    "sg:phone":"+1 817 281 3036",
    "sg:postcode":"76117",
    "sg:province":"TX",
    "sg:tags":[
        "nonmetallic",
        "mineral"
    ],
    "wof:name":"Continental Minerals Inc",
    "wof:placetype":"venue"
},
  "geometry": {"coordinates":[-97.257757,32.831454],"type":"Point"}
}