{
  "type": "Feature",
  "properties": {
    "iso:country":"US",
    "sg:address":"9805 Warwana Rd",
    "sg:city":"Houston",
    "sg:classifiers":[
        {
            "category":"Professional",
            "type":"Services"
        }
    ],
    "sg:phone":"+1 713 468 4278",
    "sg:postcode":"77080",
    "sg:province":"TX",
    "wof:name":"Lane E Horstman - Personal",
    "wof:placetype":"venue"
},
  "geometry": {"coordinates":[-95.53532,29.80089],"type":"Point"}
}