{
  "type": "Feature",
  "properties": {
    "iso:country":"US",
    "sg:address":"218 E Walker St",
    "sg:city":"Breckenridge",
    "sg:classifiers":[
        {
            "category":"Retail",
            "subcategory":"Repair Shop",
            "type":"Services"
        }
    ],
    "sg:phone":"+1 254 559 5339",
    "sg:postcode":"76424",
    "sg:province":"TX",
    "sg:tags":[
        "leather",
        "riding",
        "good",
        "tack",
        "saddle"
    ],
    "wof:name":"McIntire Saddle Shop",
    "wof:placetype":"venue"
},
  "geometry": {"coordinates":[-98.901134,32.75547],"type":"Point"}
}