{
  "type": "Feature",
  "properties": {
    "iso:country":"US",
    "sg:address":"311 S Saint Marys St",
    "sg:city":"San Antonio",
    "sg:classifiers":[
        {
            "category":"Social Services",
            "subcategory":"Job Training",
            "type":"Services"
        }
    ],
    "sg:phone":"+1 210 212 6922",
    "sg:postcode":"78205",
    "sg:province":"TX",
    "sg:tags":[
        "apprenticeship",
        "program"
    ],
    "wof:name":"National Elevator Industry",
    "wof:placetype":"venue"
},
  "geometry": {"coordinates":[-98.491901,29.423439],"type":"Point"}
}