{
  "type": "Feature",
  "properties": {
    "iso:country":"US",
    "sg:address":"11907 Warfield St",
    "sg:city":"San Antonio",
    "sg:classifiers":[
        {
            "category":"Professional",
            "subcategory":"Computer Services",
            "type":"Services"
        }
    ],
    "sg:phone":"+1 210 541 8000",
    "sg:postcode":"78216",
    "sg:province":"TX",
    "sg:tags":[
        "consultant",
        "designer",
        "design",
        "system"
    ],
    "wof:name":"Connect Concepts Inc",
    "wof:placetype":"venue"
},
  "geometry": {"coordinates":[-98.49280299999999,29.550985],"type":"Point"}
}