{
  "type": "Feature",
  "properties": {
    "iso:country":"US",
    "sg:address":"37 E Wandering Oak Dr",
    "sg:city":"Spring",
    "sg:classifiers":[
        {
            "category":"Shopping",
            "subcategory":"Hobbies, Toys, & Games",
            "type":"Retail Goods"
        }
    ],
    "sg:phone":"+1 281 292 8815",
    "sg:postcode":"77381",
    "sg:province":"TX",
    "wof:name":"Forever Country",
    "wof:placetype":"venue"
},
  "geometry": {"coordinates":[-95.507865,30.154402],"type":"Point"}
}