{
  "type": "Feature",
  "properties": {
    "iso:country":"US",
    "sg:address":"21123 W Hardy Rd",
    "sg:city":"Houston",
    "sg:classifiers":[
        {
            "category":"Manufacturing",
            "subcategory":"Petroleum Products",
            "type":"Manufacturing & Wholesale Goods"
        }
    ],
    "sg:phone":"+1 281 443 4241",
    "sg:postcode":"77073",
    "sg:province":"TX",
    "sg:tags":[
        "refiner"
    ],
    "wof:name":"American Siding & Remodel",
    "wof:placetype":"venue"
},
  "geometry": {"coordinates":[-95.40246999999999,30.01993],"type":"Point"}
}