{
  "type": "Feature",
  "properties": {
    "iso:country":"US",
    "sg:address":"3901 W Arkansas Ln",
    "sg:city":"Arlington",
    "sg:classifiers":[
        {
            "category":"Food & Beverages",
            "subcategory":"Groceries & Convenience Stores",
            "type":"Retail Goods"
        }
    ],
    "sg:phone":"+1 817 303 3499",
    "sg:postcode":"76016",
    "sg:province":"TX",
    "wof:name":"One Stop Food Store 121",
    "wof:placetype":"venue"
},
  "geometry": {"coordinates":[-97.165442,32.706863],"type":"Point"}
}