{
  "type": "Feature",
  "properties": {
    "iso:country":"US",
    "sg:address":"5303 E Lancaster Ave",
    "sg:city":"Fort Worth",
    "sg:classifiers":[
        {
            "category":"Restaurant",
            "type":"Food & Drink"
        }
    ],
    "sg:phone":"+1 817 457 1965",
    "sg:postcode":"76112",
    "sg:province":"TX",
    "sg:tags":[
        "eating"
    ],
    "wof:name":"Long John Silver's",
    "wof:placetype":"venue"
},
  "geometry": {"coordinates":[-97.240342,32.74032],"type":"Point"}
}