{
  "type": "Feature",
  "properties": {
    "iso:country":"US",
    "sg:address":"1201 Rio Grande St",
    "sg:city":"Austin",
    "sg:classifiers":[
        {
            "category":"Organizations",
            "subcategory":"Political Organization",
            "type":"Services"
        }
    ],
    "sg:phone":"+1 512 243 6443",
    "sg:postcode":"78701",
    "sg:province":"TX",
    "wof:name":"Texans For Elizabeth Ames Jones",
    "wof:placetype":"venue"
},
  "geometry": {"coordinates":[-97.74730700000001,30.27582],"type":"Point"}
}