{
  "type": "Feature",
  "properties": {
    "iso:country":"US",
    "sg:address":"10998 North Fwy",
    "sg:city":"Houston",
    "sg:classifiers":[
        {
            "category":"Insurance",
            "subcategory":"Insurance Agent",
            "type":"Services"
        }
    ],
    "sg:phone":"+1 281 447 0499",
    "sg:postcode":"77037",
    "sg:province":"TX",
    "wof:name":"Farm Bureau Insurance",
    "wof:placetype":"venue"
},
  "geometry": {"coordinates":[-95.41233800000001,29.923579],"type":"Point"}
}