{
  "type": "Feature",
  "properties": {
    "iso:country":"US",
    "sg:address":"5353 W Alabama",
    "sg:city":"Houston",
    "sg:classifiers":[
        {
            "category":"Insurance",
            "subcategory":"Insurance Agent",
            "type":"Services"
        }
    ],
    "sg:phone":"+1 281 286 9244",
    "sg:postcode":"77056",
    "sg:province":"TX",
    "wof:name":"Ai Network",
    "wof:placetype":"venue"
},
  "geometry": {"coordinates":[-95.46959099999999,29.737923],"type":"Point"}
}