{
  "type": "Feature",
  "properties": {
    "iso:country":"US",
    "sg:address":"949 S Mason Rd",
    "sg:city":"Katy",
    "sg:classifiers":[
        {
            "category":"Professional",
            "subcategory":"Business Services",
            "type":"Services"
        }
    ],
    "sg:phone":"+1 281 578 5812",
    "sg:postcode":"77450",
    "sg:province":"TX",
    "sg:tags":[
        "merchandise"
    ],
    "wof:name":"Bombay & Bazaar",
    "wof:placetype":"venue"
},
  "geometry": {"coordinates":[-95.751591,29.767645],"type":"Point"}
}