{
  "type": "Feature",
  "properties": {
    "iso:country":"US",
    "sg:address":"400 Market St Ste 302",
    "sg:city":"Baird",
    "sg:classifiers":[
        {
            "category":"Social Services",
            "type":"Services"
        }
    ],
    "sg:phone":"+1 325 854 1277",
    "sg:postcode":"79504",
    "sg:province":"TX",
    "wof:name":"Callahan County Nutrition Project",
    "wof:placetype":"venue"
},
  "geometry": {"coordinates":[-99.393738,32.394279],"type":"Point"}
}