{
  "type": "Feature",
  "properties": {
    "iso:country":"US",
    "sg:address":"719 Smith St",
    "sg:city":"Gainesville",
    "sg:classifiers":[
        {
            "category":"Manufacturing",
            "subcategory":"Metals",
            "type":"Manufacturing & Wholesale Goods"
        }
    ],
    "sg:phone":"+1 940 665 2030",
    "sg:postcode":"76240",
    "sg:province":"TX",
    "sg:tags":[
        "coating",
        "powder"
    ],
    "wof:name":"Enhanced Powder Coating",
    "wof:placetype":"venue"
},
  "geometry": {"coordinates":[-97.13845000000001,33.632122],"type":"Point"}
}