{
  "type": "Feature",
  "properties": {
    "iso:country":"US",
    "sg:address":"207 Carriage Trl",
    "sg:city":"Wylie",
    "sg:classifiers":[
        {
            "category":"Real Estate",
            "subcategory":"Real Estate Services",
            "type":"Services"
        },
        {
            "category":"Real Estate",
            "subcategory":"Real Estate Agent",
            "type":"Services"
        }
    ],
    "sg:phone":"+1 972 369 9799",
    "sg:postcode":"75098",
    "sg:province":"TX",
    "sg:tags":[
        "buyer",
        "broker"
    ],
    "wof:name":"Exemplary Real Estate",
    "wof:placetype":"venue"
},
  "geometry": {"coordinates":[-96.565392,33.073662],"type":"Point"}
}