{
  "type": "Feature",
  "properties": {
    "iso:country":"US",
    "sg:address":"5420 Grissom Rd",
    "sg:city":"San Antonio",
    "sg:classifiers":[
        {
            "category":"Retail",
            "subcategory":"Auto Rental",
            "type":"Services"
        }
    ],
    "sg:phone":"+1 210 680 9232",
    "sg:postcode":"78238",
    "sg:province":"TX",
    "sg:tags":[
        "renting",
        "truck",
        "leasing"
    ],
    "wof:name":"U-Haul Co",
    "wof:placetype":"venue"
},
  "geometry": {"coordinates":[-98.629042,29.483845],"type":"Point"}
}