{
  "type": "Feature",
  "properties": {
    "iso:country":"US",
    "sg:address":"7606 Bayswater Rd",
    "sg:city":"Amarillo",
    "sg:classifiers":[
        {
            "category":"Professional",
            "subcategory":"Computer Services",
            "type":"Services"
        }
    ],
    "sg:phone":"+1 806 331 2671",
    "sg:postcode":"79119",
    "sg:province":"TX",
    "sg:tags":[
        "programing",
        "related",
        "custom"
    ],
    "wof:name":"Micro Computer Solutions",
    "wof:placetype":"venue"
},
  "geometry": {"coordinates":[-101.92032,35.139193],"type":"Point"}
}