{
  "type": "Feature",
  "properties": {
    "iso:country":"US",
    "sg:address":"913 Regency Dr",
    "sg:city":"Longview",
    "sg:classifiers":[
        {
            "category":"Personal",
            "type":"Services"
        }
    ],
    "sg:phone":"+1 903 759 4756",
    "sg:postcode":"75604",
    "sg:province":"TX",
    "wof:name":"Cuellar Right Way & Project",
    "wof:placetype":"venue"
},
  "geometry": {"coordinates":[-94.785005,32.515194],"type":"Point"}
}