{
  "type": "Feature",
  "properties": {
    "iso:country":"US",
    "sg:address":"4402 19th St",
    "sg:city":"Lubbock",
    "sg:classifiers":[
        {
            "category":"Cinema",
            "subcategory":"Movie Rental",
            "type":"Entertainment"
        }
    ],
    "sg:phone":"+1 806 785 6600",
    "sg:postcode":"79407",
    "sg:province":"TX",
    "sg:tags":[
        "leasing",
        "video",
        "disc",
        "tape"
    ],
    "wof:name":"Hollywood Video",
    "wof:placetype":"venue"
},
  "geometry": {"coordinates":[-101.90723699999999,33.577858],"type":"Point"}
}