{
  "type": "Feature",
  "properties": {
    "iso:country":"US",
    "sg:address":"240 SE 58th Ave",
    "sg:city":"Amarillo",
    "sg:classifiers":[
        {
            "category":"Wholesale",
            "subcategory":"Auto Parts",
            "type":"Manufacturing & Wholesale Goods"
        }
    ],
    "sg:phone":"+1 806 622 3161",
    "sg:postcode":"79118",
    "sg:province":"TX",
    "sg:tags":[
        "automobile",
        "rebuilt"
    ],
    "wof:name":"Complete Auto Recyclers",
    "wof:placetype":"venue"
},
  "geometry": {"coordinates":[-101.83077,35.149421],"type":"Point"}
}