{
  "type": "Feature",
  "properties": {
    "iso:country":"US",
    "sg:address":"910 Louisiana St",
    "sg:city":"Houston",
    "sg:classifiers":[
        {
            "category":"Professional",
            "subcategory":"Lawyer & Legal Services",
            "type":"Services"
        }
    ],
    "sg:phone":"+1 713 229 1487",
    "sg:postcode":"77002",
    "sg:province":"TX",
    "sg:tags":[
        "attorney"
    ],
    "wof:name":"James P Lee",
    "wof:placetype":"venue"
},
  "geometry": {"coordinates":[-95.36752,29.75864],"type":"Point"}
}