{
  "type": "Feature",
  "properties": {
    "iso:country":"US",
    "sg:address":"4975 Preston Park Blvd Ste 80",
    "sg:city":"Plano",
    "sg:classifiers":[
        {
            "category":"Restaurant",
            "type":"Food & Drink"
        }
    ],
    "sg:phone":"+1 972 964 3315",
    "sg:postcode":"75093",
    "sg:province":"TX",
    "wof:name":"Song's Deli",
    "wof:placetype":"venue"
},
  "geometry": {"coordinates":[-96.7938,33.022999],"type":"Point"}
}