{
  "type": "Feature",
  "properties": {
    "iso:country":"US",
    "sg:address":"105 Southland St",
    "sg:city":"College Station",
    "sg:classifiers":[
        {
            "category":"Restaurant",
            "type":"Food & Drink"
        }
    ],
    "sg:phone":"+1 979 693 6140",
    "sg:postcode":"77840",
    "sg:province":"TX",
    "sg:tags":[
        "eating"
    ],
    "wof:name":"Moble Catering Svc",
    "wof:placetype":"venue"
},
  "geometry": {"coordinates":[-96.33005300000001,30.594745],"type":"Point"}
}