{
  "type": "Feature",
  "properties": {
    "iso:country":"US",
    "sg:address":"1388 Lime Tree Rd",
    "sg:city":"Gilmer",
    "sg:classifiers":[
        {
            "category":"Building & Trades",
            "subcategory":"Construction",
            "type":"Services"
        }
    ],
    "sg:phone":"+1 903 725 5133",
    "sg:postcode":"75644",
    "sg:province":"TX",
    "sg:tags":[
        "roofing",
        "contractor"
    ],
    "wof:name":"Danny G Langford Roofing",
    "wof:placetype":"venue"
},
  "geometry": {"coordinates":[-95.068839,32.708667],"type":"Point"}
}