{
  "type": "Feature",
  "properties": {
    "iso:country":"US",
    "sg:address":"4801 Baldwin Blvd",
    "sg:city":"Corpus Christi",
    "sg:classifiers":[
        {
            "category":"Manufacturing",
            "subcategory":"Metals",
            "type":"Manufacturing & Wholesale Goods"
        }
    ],
    "sg:phone":"+1 281 441 9015",
    "sg:postcode":"78408",
    "sg:province":"TX",
    "sg:tags":[
        "barrels",
        "drum"
    ],
    "wof:name":"Sooner Container Inc",
    "wof:placetype":"venue"
},
  "geometry": {"coordinates":[-97.45160799999999,27.797264],"type":"Point"}
}