{
  "type": "Feature",
  "properties": {
    "iso:country":"US",
    "sg:address":"12655 N Central Expy",
    "sg:city":"Dallas",
    "sg:classifiers":[
        {
            "category":"Banks & Credit Unions",
            "subcategory":"Bank",
            "type":"Services"
        }
    ],
    "sg:phone":"+1 214 343 0089",
    "sg:postcode":"75243",
    "sg:province":"TX",
    "sg:tags":[
        "leasing",
        "industrial",
        "commercial",
        "finance",
        "equipment"
    ],
    "wof:name":"Fleet",
    "wof:placetype":"venue"
},
  "geometry": {"coordinates":[-96.767929,32.912489],"type":"Point"}
}