{
  "type": "Feature",
  "properties": {
    "iso:country":"US",
    "sg:address":"1190 Fm 78",
    "sg:city":"Schertz",
    "sg:classifiers":[
        {
            "category":"Food & Beverages",
            "subcategory":"Groceries & Convenience Stores",
            "type":"Retail Goods"
        }
    ],
    "sg:phone":"+1 210 659 6502",
    "sg:postcode":"78154",
    "sg:province":"TX",
    "sg:website":"http://www.wuestec.com",
    "wof:name":"Pic & Pac Drive In",
    "wof:placetype":"venue"
},
  "geometry": {"coordinates":[-98.25002000000001,29.559491],"type":"Point"}
}