{
  "type": "Feature",
  "properties": {
    "iso:country":"US",
    "sg:address":"310 N Mesa St",
    "sg:city":"El Paso",
    "sg:classifiers":[
        {
            "category":"Manufacturing",
            "subcategory":"Printing",
            "type":"Manufacturing & Wholesale Goods"
        }
    ],
    "sg:phone":"+1 915 532 4408",
    "sg:postcode":"79901",
    "sg:province":"TX",
    "sg:tags":[
        "newspaper"
    ],
    "wof:name":"Dallas Mrning News W Texas Bur",
    "wof:placetype":"venue"
},
  "geometry": {"coordinates":[-106.488347,31.760245],"type":"Point"}
}