{
  "type": "Feature",
  "properties": {
    "iso:country":"US",
    "sg:address":"7308 Yaupon Dr",
    "sg:city":"Austin",
    "sg:classifiers":[
        {
            "category":"Building & Trades",
            "subcategory":"Construction",
            "type":"Services"
        }
    ],
    "sg:phone":"+1 512 249 5508",
    "sg:postcode":"78759",
    "sg:province":"TX",
    "sg:tags":[
        "home",
        "builder"
    ],
    "wof:name":"Fedrick Harris Estate Homes",
    "wof:placetype":"venue"
},
  "geometry": {"coordinates":[-97.777163,30.410991],"type":"Point"}
}