{
  "type": "Feature",
  "properties": {
    "iso:country":"US",
    "sg:address":"1117 Hampshire Ln",
    "sg:city":"Richardson",
    "sg:classifiers":[
        {
            "category":"Professional",
            "subcategory":"Secretarial Services",
            "type":"Services"
        }
    ],
    "sg:phone":"+1 972 231 2373",
    "sg:postcode":"75080",
    "sg:province":"TX",
    "sg:tags":[
        "convention",
        "reporting",
        "court",
        "reporter"
    ],
    "wof:name":"All Star Reporting",
    "wof:placetype":"venue"
},
  "geometry": {"coordinates":[-96.738551,32.964891],"type":"Point"}
}