{
  "type": "Feature",
  "properties": {
    "iso:country":"US",
    "sg:address":"5600 Chenevert St",
    "sg:city":"Houston",
    "sg:classifiers":[
        {
            "category":"Social Services",
            "subcategory":"Retirement Home",
            "type":"Services"
        }
    ],
    "sg:phone":"+1 713 523 6831",
    "sg:postcode":"77004",
    "sg:province":"TX",
    "wof:name":"Hermann Park Manor",
    "wof:placetype":"venue"
},
  "geometry": {"coordinates":[-95.38310199999999,29.7215],"type":"Point"}
}