{
  "type": "Feature",
  "properties": {
    "iso:country":"US",
    "sg:address":"5003 Harmon Rd",
    "sg:city":"Baytown",
    "sg:classifiers":[
        {
            "category":"Building & Trades",
            "subcategory":"Construction",
            "type":"Services"
        }
    ],
    "sg:phone":"+1 281 383 2848",
    "sg:postcode":"77520",
    "sg:province":"TX",
    "sg:tags":[
        "house"
    ],
    "wof:name":"Williams Construction",
    "wof:placetype":"venue"
},
  "geometry": {"coordinates":[-94.843403,29.805699],"type":"Point"}
}