{
  "type": "Feature",
  "properties": {
    "iso:country":"US",
    "sg:address":"1516 Goldcrest Ave",
    "sg:city":"Mcallen",
    "sg:classifiers":[
        {
            "category":"Organizations",
            "subcategory":"Religious Organization",
            "type":"Services"
        }
    ],
    "sg:phone":"+1 956 631 7606",
    "sg:postcode":"78504",
    "sg:province":"TX",
    "wof:name":"Joe Stewart Ministries",
    "wof:placetype":"venue"
},
  "geometry": {"coordinates":[-98.22658300000001,26.257792],"type":"Point"}
}