{
  "type": "Feature",
  "properties": {
    "iso:country":"US",
    "sg:address":"245 Chrestman Ln",
    "sg:city":"Seagoville",
    "sg:classifiers":[
        {
            "category":"Place Of Worship",
            "subcategory":"Church",
            "type":"Public Place"
        },
        {
            "category":"Place Of Worship",
            "type":"Public Place"
        }
    ],
    "sg:phone":"+1 972 476 6797",
    "sg:postcode":"75159",
    "sg:province":"TX",
    "sg:tags":[
        "churches-baptist-general",
        "churches-baptist"
    ],
    "wof:name":"Liberty Baptist Church",
    "wof:placetype":"venue"
},
  "geometry": {"coordinates":[-96.49089600000001,32.579494],"type":"Point"}
}