{
  "type": "Feature",
  "properties": {
    "iso:country":"US",
    "sg:address":"566 FM 1960 W",
    "sg:city":"Houston",
    "sg:classifiers":[
        {
            "category":"Home & Garden",
            "subcategory":"Furniture",
            "type":"Retail Goods"
        }
    ],
    "sg:phone":"+1 281 631 9040",
    "sg:postcode":"77090",
    "sg:province":"TX",
    "wof:name":"Mattress Giant Corporation",
    "wof:placetype":"venue"
},
  "geometry": {"coordinates":[-95.437378,30.018723],"type":"Point"}
}