{
  "type": "Feature",
  "properties": {
    "iso:country":"US",
    "sg:address":"15303 Huebner Rd",
    "sg:city":"San Antonio",
    "sg:classifiers":[
        {
            "category":"Banks & Credit Unions",
            "subcategory":"Bank",
            "type":"Services"
        }
    ],
    "sg:phone":"+1 210 479 0188",
    "sg:postcode":"78248",
    "sg:province":"TX",
    "sg:tags":[
        "loan",
        "real estate"
    ],
    "wof:name":"American Homefront Mortgage",
    "wof:placetype":"venue"
},
  "geometry": {"coordinates":[-98.53796699999999,29.582499],"type":"Point"}
}