{
  "type": "Feature",
  "properties": {
    "iso:country":"US",
    "sg:address":"1900 Cypress Creek Rd # 100",
    "sg:city":"Cedar Park",
    "sg:classifiers":[
        {
            "category":"Health Services",
            "subcategory":"Doctor",
            "type":"Services"
        },
        {
            "category":"Community Center",
            "type":"Public Place"
        }
    ],
    "sg:phone":"+1 512 535 5554",
    "sg:postcode":"78613",
    "sg:province":"TX",
    "sg:tags":[
        "medical",
        "surgeon",
        "cosmetic"
    ],
    "sg:website":"www.cedarparksurgery.com",
    "wof:name":"Surgical Renewal & Aesthetics",
    "wof:placetype":"venue"
},
  "geometry": {"coordinates":[-97.84074099999999,30.474919],"type":"Point"}
}