{
  "type": "Feature",
  "properties": {
    "iso:country":"US",
    "sg:address":"2900 S Lamar Blvd",
    "sg:city":"Austin",
    "sg:classifiers":[
        {
            "category":"Restaurant",
            "type":"Food & Drink"
        }
    ],
    "sg:phone":"+1 512 442 7033",
    "sg:postcode":"78704",
    "sg:province":"TX",
    "sg:tags":[
        "pizza"
    ],
    "wof:name":"Giovannis Pizza Stand",
    "wof:placetype":"venue"
},
  "geometry": {"coordinates":[-97.782831,30.243405],"type":"Point"}
}