{
  "type": "Feature",
  "properties": {
    "iso:country":"US",
    "sg:address":"400 S Columbia St",
    "sg:city":"Plainview",
    "sg:classifiers":[
        {
            "category":"Utilities",
            "subcategory":"Telephone",
            "type":"Services"
        }
    ],
    "sg:phone":"+1 806 293 0687",
    "sg:postcode":"79072",
    "sg:province":"TX",
    "sg:tags":[
        "distance",
        "long"
    ],
    "wof:name":"Nts Communications Inc",
    "wof:placetype":"venue"
},
  "geometry": {"coordinates":[-101.70698299999999,34.175132],"type":"Point"}
}