{
  "type": "Feature",
  "properties": {
    "iso:country":"US",
    "sg:address":"18523 Bridoon Dr",
    "sg:city":"Cypress",
    "sg:classifiers":[
        {
            "category":"Professional",
            "subcategory":"Computer Services",
            "type":"Services"
        }
    ],
    "sg:phone":"+1 281 856 6564",
    "sg:postcode":"77433",
    "sg:province":"TX",
    "wof:name":"Computer Hospital",
    "wof:placetype":"venue"
},
  "geometry": {"coordinates":[-95.691602,29.881121],"type":"Point"}
}