{
  "type": "Feature",
  "properties": {
    "iso:country":"US",
    "sg:address":"1 Stonebriar Way",
    "sg:city":"Frisco",
    "sg:classifiers":[
        {
            "category":"Professional",
            "type":"Services"
        }
    ],
    "sg:phone":"+1 214 528 1134",
    "sg:postcode":"75034",
    "sg:province":"TX",
    "wof:name":"Rocky A Freeman",
    "wof:placetype":"venue"
},
  "geometry": {"coordinates":[-96.827264,33.09466],"type":"Point"}
}