{
  "type": "Feature",
  "properties": {
    "iso:country":"US",
    "sg:address":"1106 Main St",
    "sg:city":"Bastrop",
    "sg:classifiers":[
        {
            "category":"Government",
            "subcategory":"Post Office",
            "type":"Public Place"
        }
    ],
    "sg:phone":"+1 512 303 1014",
    "sg:postcode":"78602",
    "sg:province":"TX",
    "sg:tags":[
        "postal",
        "us"
    ],
    "wof:name":"US Post Office",
    "wof:placetype":"venue"
},
  "geometry": {"coordinates":[-97.320121,30.112629],"type":"Point"}
}