{
  "type": "Feature",
  "properties": {
    "iso:country":"US",
    "sg:address":"5201 S 7th St",
    "sg:city":"Abilene",
    "sg:classifiers":[
        {
            "category":"Organizations",
            "subcategory":"Membership Organization",
            "type":"Services"
        }
    ],
    "sg:phone":"+1 325 695 0240",
    "sg:postcode":"79605",
    "sg:province":"TX",
    "wof:name":"Texas Assoc of Nonsmokers",
    "wof:placetype":"venue"
},
  "geometry": {"coordinates":[-99.79174999999999,32.444027],"type":"Point"}
}