{
  "type": "Feature",
  "properties": {
    "iso:country":"US",
    "sg:address":"4890 Lodgepole Ln",
    "sg:city":"Fort Worth",
    "sg:classifiers":[
        {
            "category":"Organizations",
            "subcategory":"Membership Organization",
            "type":"Services"
        }
    ],
    "sg:phone":"+1 817 294 7571",
    "sg:postcode":"76137",
    "sg:province":"TX",
    "sg:tags":[
        "protection",
        "animal"
    ],
    "wof:name":"Critter Control",
    "wof:placetype":"venue"
},
  "geometry": {"coordinates":[-97.275183,32.864696],"type":"Point"}
}