{
  "type": "Feature",
  "properties": {
    "iso:country":"US",
    "sg:address":"1010 N Belt Line Rd",
    "sg:city":"Mesquite",
    "sg:classifiers":[
        {
            "category":"Health Services",
            "subcategory":"Doctor",
            "type":"Services"
        }
    ],
    "sg:phone":"+1 972 288 4544",
    "sg:postcode":"75149",
    "sg:province":"TX",
    "wof:name":"Sutbblefield L K DO",
    "wof:placetype":"venue"
},
  "geometry": {"coordinates":[-96.597857,32.777446],"type":"Point"}
}