{
  "type": "Feature",
  "properties": {
    "iso:country":"US",
    "sg:address":"1350 E Seminary Dr",
    "sg:city":"Fort Worth",
    "sg:classifiers":[
        {
            "category":"Real Estate",
            "subcategory":"Real Estate Operator",
            "type":"Services"
        }
    ],
    "sg:phone":"+1 817 924 3449",
    "sg:postcode":"76115",
    "sg:province":"TX",
    "sg:tags":[
        "apartment"
    ],
    "wof:name":"Spanish Gate Apartments",
    "wof:placetype":"venue"
},
  "geometry": {"coordinates":[-97.310147,32.684366],"type":"Point"}
}