{
  "type": "Feature",
  "properties": {
    "iso:country":"US",
    "sg:address":"3225 NE Loop 286",
    "sg:city":"Paris",
    "sg:classifiers":[
        {
            "category":"Professional",
            "type":"Services"
        }
    ],
    "sg:phone":"+1 903 783 9464",
    "sg:postcode":"75460",
    "sg:province":"TX",
    "wof:name":"Screenworks & Embroidery",
    "wof:placetype":"venue"
},
  "geometry": {"coordinates":[-95.515191,33.671302],"type":"Point"}
}