{
  "type": "Feature",
  "properties": {
    "iso:country":"US",
    "sg:address":"11402 Hornsby St",
    "sg:city":"Austin",
    "sg:classifiers":[
        {
            "category":"Professional",
            "subcategory":"Management & Consulting",
            "type":"Services"
        }
    ],
    "sg:phone":"+1 512 873 7931",
    "sg:postcode":"78753",
    "sg:province":"TX",
    "sg:tags":[
        "consultant",
        "business"
    ],
    "wof:name":"Bannon & Associates",
    "wof:placetype":"venue"
},
  "geometry": {"coordinates":[-97.682948,30.381446],"type":"Point"}
}