{
  "type": "Feature",
  "properties": {
    "iso:country":"US",
    "sg:address":"1205 Sturgeon Ct",
    "sg:city":"Arlington",
    "sg:classifiers":[
        {
            "category":"Autos & Motor Vehicles",
            "subcategory":"Automobile Sales",
            "type":"Retail Goods"
        }
    ],
    "sg:phone":"+1 817 466 2222",
    "sg:postcode":"76001",
    "sg:province":"TX",
    "sg:tags":[
        "car",
        "used"
    ],
    "wof:name":"Auto Paradise of Texas",
    "wof:placetype":"venue"
},
  "geometry": {"coordinates":[-97.137395,32.618704],"type":"Point"}
}