{
  "type": "Feature",
  "properties": {
    "iso:country":"US",
    "sg:address":"9601 Katy Fwy",
    "sg:city":"Houston",
    "sg:classifiers":[
        {
            "category":"Professional",
            "type":"Services"
        }
    ],
    "sg:phone":"+1 713 468 4162",
    "sg:postcode":"77024",
    "sg:province":"TX",
    "wof:name":"Panorama By Bayou Inc",
    "wof:placetype":"venue"
},
  "geometry": {"coordinates":[-95.531632,29.783738],"type":"Point"}
}