{
  "type": "Feature",
  "properties": {
    "iso:country":"US",
    "sg:address":"2211 W North Loop Blvd",
    "sg:city":"Austin",
    "sg:classifiers":[
        {
            "category":"Real Estate",
            "subcategory":"Real Estate Operator",
            "type":"Services"
        }
    ],
    "sg:phone":"+1 512 452 9984",
    "sg:postcode":"78756",
    "sg:province":"TX",
    "sg:tags":[
        "building",
        "apartment"
    ],
    "wof:name":"French Quarter Apartments",
    "wof:placetype":"venue"
},
  "geometry": {"coordinates":[-97.742521,30.325382],"type":"Point"}
}