{
  "type": "Feature",
  "properties": {
    "iso:country":"US",
    "sg:address":"1226 County Road 150",
    "sg:city":"Tuscola",
    "sg:classifiers":[
        {
            "category":"Farming",
            "subcategory":"Farm",
            "type":"Manufacturing & Wholesale Goods"
        }
    ],
    "sg:phone":"+1 325 572 3041",
    "sg:postcode":"79562",
    "sg:province":"TX",
    "wof:name":"Dwight C Albus",
    "wof:placetype":"venue"
},
  "geometry": {"coordinates":[-99.78793400000001,32.255482],"type":"Point"}
}