{
  "type": "Feature",
  "properties": {
    "iso:country":"US",
    "sg:address":"549 W Wheatland Rd",
    "sg:city":"Duncanville",
    "sg:classifiers":[
        {
            "category":"Professional",
            "subcategory":"Lawyer & Legal Services",
            "type":"Services"
        }
    ],
    "sg:phone":"+1 972 296 6148",
    "sg:postcode":"75116",
    "sg:province":"TX",
    "wof:name":"Neilon William J PC",
    "wof:placetype":"venue"
},
  "geometry": {"coordinates":[-96.920303,32.647301],"type":"Point"}
}