{
  "type": "Feature",
  "properties": {
    "iso:country":"US",
    "sg:address":"4708 Burnet Rd",
    "sg:city":"Austin",
    "sg:classifiers":[
        {
            "category":"Restaurant",
            "type":"Food & Drink"
        }
    ],
    "sg:phone":"+1 512 454 0747",
    "sg:postcode":"78756",
    "sg:province":"TX",
    "sg:tags":[
        "eating"
    ],
    "wof:name":"Elsis Resturant",
    "wof:placetype":"venue"
},
  "geometry": {"coordinates":[-97.73991100000001,30.318019],"type":"Point"}
}