{
  "type": "Feature",
  "properties": {
    "iso:country":"US",
    "sg:address":"5333 Old Beaumont Hwy",
    "sg:city":"Silsbee",
    "sg:classifiers":[
        {
            "category":"Personal",
            "subcategory":"Beauty Salon",
            "type":"Services"
        }
    ],
    "sg:phone":"+1 409 385 0185",
    "sg:postcode":"77656",
    "sg:province":"TX",
    "sg:tags":[
        "shop"
    ],
    "wof:name":"Joy's Style Shop",
    "wof:placetype":"venue"
},
  "geometry": {"coordinates":[-94.183054,30.293738],"type":"Point"}
}