{
  "type": "Feature",
  "properties": {
    "iso:country":"US",
    "sg:address":"103 W Madison St",
    "sg:city":"Gilmer",
    "sg:classifiers":[
        {
            "category":"Social Services",
            "type":"Services"
        }
    ],
    "sg:phone":"+1 903 843 5518",
    "sg:postcode":"75644",
    "sg:province":"TX",
    "wof:name":"Sabine Valley Center",
    "wof:placetype":"venue"
},
  "geometry": {"coordinates":[-94.94565299999999,32.733684],"type":"Point"}
}