{
  "type": "Feature",
  "properties": {
    "iso:country":"US",
    "sg:address":"1558 Cardigan Ln",
    "sg:city":"Lancaster",
    "sg:classifiers":[
        {
            "category":"Professional",
            "subcategory":"Art Services",
            "type":"Services"
        }
    ],
    "sg:phone":"+1 866 434 5771",
    "sg:postcode":"75134",
    "sg:province":"TX",
    "sg:tags":[
        "interior",
        "designer",
        "decorator"
    ],
    "wof:name":"Gemini Home Interiors",
    "wof:placetype":"venue"
},
  "geometry": {"coordinates":[-96.79608399999999,32.610511],"type":"Point"}
}