{
  "type": "Feature",
  "properties": {
    "iso:country":"US",
    "sg:address":"200 N Texas Ave",
    "sg:city":"Bryan",
    "sg:classifiers":[
        {
            "category":"Food & Beverages",
            "subcategory":"Groceries & Convenience Stores",
            "type":"Retail Goods"
        }
    ],
    "sg:phone":"+1 979 822 4168",
    "sg:postcode":"77803",
    "sg:province":"TX",
    "wof:name":"Zip' N Food Store",
    "wof:placetype":"venue"
},
  "geometry": {"coordinates":[-96.369815,30.675252],"type":"Point"}
}