{
  "type": "Feature",
  "properties": {
    "iso:country":"US",
    "sg:address":"1120 Lindberg Ave",
    "sg:city":"Mcallen",
    "sg:classifiers":[
        {
            "category":"Wholesale",
            "subcategory":"Machinery & Supplies",
            "type":"Manufacturing & Wholesale Goods"
        }
    ],
    "sg:phone":"+1 956 631 5456",
    "sg:postcode":"78501",
    "sg:province":"TX",
    "sg:tags":[
        "equipment",
        "motel",
        "hotel"
    ],
    "wof:name":"Mattress Warehouse",
    "wof:placetype":"venue"
},
  "geometry": {"coordinates":[-98.23293200000001,26.192757],"type":"Point"}
}