{
  "type": "Feature",
  "properties": {
    "iso:country":"US",
    "sg:address":"25 Cedar Ln",
    "sg:city":"Orange",
    "sg:classifiers":[
        {
            "category":"Recreation",
            "subcategory":"Marina",
            "type":"Entertainment"
        }
    ],
    "sg:phone":"+1 409 746 3258",
    "sg:postcode":"77632",
    "sg:province":"TX",
    "sg:tags":[
        "repairing",
        "boat"
    ],
    "wof:name":"D M Mechanic Svc",
    "wof:placetype":"venue"
},
  "geometry": {"coordinates":[-93.80073,30.130112],"type":"Point"}
}