{
  "type": "Feature",
  "properties": {
    "iso:country":"US",
    "sg:address":"5815 Seymour Hwy",
    "sg:city":"Wichita Falls",
    "sg:classifiers":[
        {
            "category":"Wholesale",
            "subcategory":"Construction Materials",
            "type":"Manufacturing & Wholesale Goods"
        }
    ],
    "sg:phone":"+1 940 692 3290",
    "sg:postcode":"76310",
    "sg:province":"TX",
    "sg:tags":[
        "sand",
        "gravel"
    ],
    "wof:name":"Pitts Sand & Gravel Inc",
    "wof:placetype":"venue"
},
  "geometry": {"coordinates":[-98.578513,33.879879],"type":"Point"}
}