{
  "type": "Feature",
  "properties": {
    "iso:country":"US",
    "sg:address":"5111 Caden Dr",
    "sg:city":"San Antonio",
    "sg:classifiers":[
        {
            "category":"Retail",
            "subcategory":"Repair Shop",
            "type":"Services"
        }
    ],
    "sg:phone":"+1 210 924 1555",
    "sg:postcode":"78214",
    "sg:province":"TX",
    "sg:tags":[
        "armature",
        "rewinding"
    ],
    "wof:name":"Ernies Electric Motor",
    "wof:placetype":"venue"
},
  "geometry": {"coordinates":[-98.509671,29.37473],"type":"Point"}
}