{
  "type": "Feature",
  "properties": {
    "iso:country":"US",
    "sg:address":"11322 Cedar Creek Dr",
    "sg:city":"Houston",
    "sg:classifiers":[
        {
            "category":"Professional",
            "subcategory":"Management & Consulting",
            "type":"Services"
        }
    ],
    "sg:phone":"+1 281 291 0149",
    "sg:postcode":"77077",
    "sg:province":"TX",
    "wof:name":"Syloran Corp",
    "wof:placetype":"venue"
},
  "geometry": {"coordinates":[-95.580749,29.748111],"type":"Point"}
}