{
  "type": "Feature",
  "properties": {
    "iso:country":"US",
    "sg:address":"806 S 7th St",
    "sg:city":"Lamesa",
    "sg:classifiers":[
        {
            "category":"Professional",
            "type":"Services"
        }
    ],
    "sg:phone":"+1 806 872 8534",
    "sg:postcode":"79331",
    "sg:province":"TX",
    "wof:name":"Benjamin E Beaty",
    "wof:placetype":"venue"
},
  "geometry": {"coordinates":[-101.95470299999999,32.725142],"type":"Point"}
}