{
  "type": "Feature",
  "properties": {
    "iso:country":"US",
    "sg:address":"9562 Millers Ridge",
    "sg:city":"San Antonio",
    "sg:classifiers":[
        {
            "category":"Restaurant",
            "type":"Food & Drink"
        }
    ],
    "sg:phone":"+1 210 654 6573",
    "sg:postcode":"78239",
    "sg:province":"TX",
    "sg:tags":[
        "oriental"
    ],
    "wof:name":"Seoul House Korean Restaurant",
    "wof:placetype":"venue"
},
  "geometry": {"coordinates":[-98.349632,29.523438],"type":"Point"}
}