{
  "type": "Feature",
  "properties": {
    "iso:country":"US",
    "sg:address":"1428 Sheffield Ct",
    "sg:city":"Mesquite",
    "sg:classifiers":[
        {
            "category":"Manufacturing",
            "subcategory":"Retail Goods",
            "type":"Manufacturing & Wholesale Goods"
        }
    ],
    "sg:phone":"+1 972 289 5021",
    "sg:postcode":"75149",
    "sg:province":"TX",
    "sg:tags":[
        "product",
        "mfg"
    ],
    "wof:name":"Sierra Thermal Industries Inc",
    "wof:placetype":"venue"
},
  "geometry": {"coordinates":[-96.64979,32.787563],"type":"Point"}
}