{
  "type": "Feature",
  "properties": {
    "iso:country":"US",
    "sg:address":"301 E Mims St",
    "sg:city":"Tyler",
    "sg:classifiers":[
        {
            "category":"Organizations",
            "subcategory":"Religious Organization",
            "type":"Services"
        }
    ],
    "sg:phone":"+1 903 592 2001",
    "sg:postcode":"75702",
    "sg:province":"TX",
    "wof:name":"Fellowship Missionary Baptist",
    "wof:placetype":"venue"
},
  "geometry": {"coordinates":[-95.29709200000001,32.372051],"type":"Point"}
}