{
  "type": "Feature",
  "properties": {
    "iso:country":"US",
    "sg:address":"10311 North Fwy",
    "sg:city":"Houston",
    "sg:classifiers":[
        {
            "category":"Shopping",
            "subcategory":"Stationery & Office Supplies",
            "type":"Retail Goods"
        }
    ],
    "sg:phone":"+1 281 447 7800",
    "sg:postcode":"77037",
    "sg:province":"TX",
    "sg:tags":[
        "equipment"
    ],
    "sg:website":"www.officedepot.com",
    "wof:name":"Office Depot",
    "wof:placetype":"venue"
},
  "geometry": {"coordinates":[-95.413101,29.916401],"type":"Point"}
}