{
  "type": "Feature",
  "properties": {
    "iso:country":"US",
    "sg:address":"3700 W Wall St",
    "sg:city":"Midland",
    "sg:classifiers":[
        {
            "category":"Retail",
            "subcategory":"Auto Repair",
            "type":"Services"
        }
    ],
    "sg:phone":"+1 432 689 9853",
    "sg:postcode":"79703",
    "sg:province":"TX",
    "sg:tags":[
        "muffler",
        "exhaust",
        "system"
    ],
    "wof:name":"Life Time Muffler",
    "wof:placetype":"venue"
},
  "geometry": {"coordinates":[-102.114074,31.978372],"type":"Point"}
}