{
  "type": "Feature",
  "properties": {
    "iso:country":"US",
    "sg:address":"2405 Buttercup Dr",
    "sg:city":"Richardson",
    "sg:classifiers":[
        {
            "category":"Professional",
            "subcategory":"Management & Consulting",
            "type":"Services"
        }
    ],
    "sg:phone":"+1 972 234 6410",
    "sg:postcode":"75082",
    "sg:province":"TX",
    "sg:tags":[
        "business"
    ],
    "wof:name":"Akr Consulting LLC",
    "wof:placetype":"venue"
},
  "geometry": {"coordinates":[-96.678799,32.994506],"type":"Point"}
}