{
  "type": "Feature",
  "properties": {
    "iso:country":"US",
    "sg:address":"828 S Georgia St",
    "sg:city":"Amarillo",
    "sg:classifiers":[
        {
            "category":"Autos & Motor Vehicles",
            "subcategory":"Automobile Sales",
            "type":"Retail Goods"
        }
    ],
    "sg:phone":"+1 806 374 2833",
    "sg:postcode":"79106",
    "sg:province":"TX",
    "sg:tags":[
        "car",
        "dealer"
    ],
    "wof:name":"Calvin's Cars",
    "wof:placetype":"venue"
},
  "geometry": {"coordinates":[-101.866347,35.206447],"type":"Point"}
}