{
  "type": "Feature",
  "properties": {
    "iso:country":"US",
    "sg:address":"106 Lanark Dr",
    "sg:city":"San Antonio",
    "sg:classifiers":[
        {
            "category":"Organizations",
            "subcategory":"Community Association",
            "type":"Services"
        }
    ],
    "sg:phone":"+1 210 590 1863",
    "sg:postcode":"78218",
    "sg:province":"TX",
    "wof:name":"American Legion Post 592",
    "wof:placetype":"venue"
},
  "geometry": {"coordinates":[-98.415756,29.503236],"type":"Point"}
}