{
  "type": "Feature",
  "properties": {
    "iso:country":"US",
    "sg:address":"1004 Seago Dr",
    "sg:city":"Seagoville",
    "sg:classifiers":[
        {
            "category":"Banks & Credit Unions",
            "subcategory":"Investment Brokerage",
            "type":"Services"
        }
    ],
    "sg:phone":"+1 469 364 1986",
    "sg:postcode":"75159",
    "sg:province":"TX",
    "sg:tags":[
        "advisory"
    ],
    "wof:name":"Kreative Investments",
    "wof:placetype":"venue"
},
  "geometry": {"coordinates":[-96.556375,32.643826],"type":"Point"}
}