{
  "type": "Feature",
  "properties": {
    "iso:country":"US",
    "sg:address":"1070 Enterprise Dr",
    "sg:city":"Midlothian",
    "sg:classifiers":[
        {
            "category":"Building & Trades",
            "subcategory":"Construction",
            "type":"Services"
        }
    ],
    "sg:phone":"+1 972 723 8610",
    "sg:postcode":"76065",
    "sg:province":"TX",
    "sg:tags":[
        "concrete",
        "cutting",
        "breaking",
        "sawing"
    ],
    "wof:name":"Diamond C Concrete Cutting",
    "wof:placetype":"venue"
},
  "geometry": {"coordinates":[-96.95708,32.470997],"type":"Point"}
}