{
  "type": "Feature",
  "properties": {
    "iso:country":"US",
    "sg:address":"1332 S Plano Rd",
    "sg:city":"Richardson",
    "sg:classifiers":[
        {
            "category":"Retail",
            "subcategory":"Veterinary Services",
            "type":"Services"
        }
    ],
    "sg:phone":"+1 214 699 7387",
    "sg:postcode":"75081",
    "sg:province":"TX",
    "sg:tags":[
        "veterinarian"
    ],
    "wof:name":"Buckingham Plano Road Veterinary Clinic",
    "wof:placetype":"venue"
},
  "geometry": {"coordinates":[-96.70029700000001,32.932168],"type":"Point"}
}