{
  "type": "Feature",
  "properties": {
    "iso:country":"US",
    "sg:address":"9325 Ponderosa Trl",
    "sg:city":"Irving",
    "sg:classifiers":[
        {
            "category":"Shopping",
            "subcategory":"Used Merchandise",
            "type":"Retail Goods"
        }
    ],
    "sg:phone":"+1 972 556 0765",
    "sg:postcode":"75063",
    "sg:province":"TX",
    "sg:tags":[
        "antique"
    ],
    "wof:name":"Bruno A Salazar Retailer",
    "wof:placetype":"venue"
},
  "geometry": {"coordinates":[-96.963075,32.93367],"type":"Point"}
}