{
  "type": "Feature",
  "properties": {
    "iso:country":"US",
    "sg:address":"10008 Audrey Ridge",
    "sg:city":"San Antonio",
    "sg:classifiers":[
        {
            "category":"Building & Trades",
            "subcategory":"Construction",
            "type":"Services"
        }
    ],
    "sg:phone":"+1 210 651 1709",
    "sg:postcode":"78266",
    "sg:province":"TX",
    "sg:tags":[
        "home",
        "builder"
    ],
    "wof:name":"Highland Homes",
    "wof:placetype":"venue"
},
  "geometry": {"coordinates":[-98.288799,29.62603],"type":"Point"}
}