{
  "type": "Feature",
  "properties": {
    "iso:country":"US",
    "sg:address":"2121 E Oltorf St Ste 103",
    "sg:city":"Austin",
    "sg:classifiers":[
        {
            "category":"Health Services",
            "subcategory":"Dentist",
            "type":"Services"
        }
    ],
    "sg:phone":"+1 512 462 9800",
    "sg:postcode":"78741",
    "sg:province":"TX",
    "wof:name":"Smile Center The",
    "wof:placetype":"venue"
},
  "geometry": {"coordinates":[-97.73247499999999,30.230288],"type":"Point"}
}