{
  "type": "Feature",
  "properties": {
    "iso:country":"US",
    "sg:address":"6714 Northwinds Dr",
    "sg:city":"Houston",
    "sg:classifiers":[
        {
            "category":"Food & Beverages",
            "subcategory":"Specialty",
            "type":"Retail Goods"
        }
    ],
    "sg:phone":"+1 713 937 8630",
    "sg:postcode":"77041",
    "sg:province":"TX",
    "sg:tags":[
        "water",
        "bulk",
        "company"
    ],
    "sg:website":"www.amacwater.com",
    "wof:name":"Mountain Valley Water Co",
    "wof:placetype":"venue"
},
  "geometry": {"coordinates":[-95.580962,29.876492],"type":"Point"}
}