{
  "type": "Feature",
  "properties": {
    "iso:country":"US",
    "sg:address":"2150 Paredes Line Rd",
    "sg:city":"Brownsville",
    "sg:classifiers":[
        {
            "category":"Restaurant",
            "type":"Food & Drink"
        }
    ],
    "sg:phone":"+1 956 550 8994",
    "sg:postcode":"78521",
    "sg:province":"TX",
    "sg:tags":[
        "eating"
    ],
    "wof:name":"Jack In The Box",
    "wof:placetype":"venue"
},
  "geometry": {"coordinates":[-97.48320200000001,25.995096],"type":"Point"}
}