{
  "type": "Feature",
  "properties": {
    "iso:country":"US",
    "sg:address":"4901 Alpha Rd Ste 100",
    "sg:city":"Dallas",
    "sg:classifiers":[
        {
            "category":"Home & Garden",
            "subcategory":"Household Appliances",
            "type":"Retail Goods"
        }
    ],
    "sg:phone":"+1 214 306 6900",
    "sg:postcode":"75244",
    "sg:province":"TX",
    "sg:website":"www.eliteappliance.com",
    "wof:name":"Elite Appliance",
    "wof:placetype":"venue"
},
  "geometry": {"coordinates":[-96.824684,32.933831],"type":"Point"}
}