{
  "type": "Feature",
  "properties": {
    "iso:country":"US",
    "sg:address":"2416 Heather Hill Ln",
    "sg:city":"Plano",
    "sg:classifiers":[
        {
            "category":"Wholesale",
            "subcategory":"Electrical",
            "type":"Manufacturing & Wholesale Goods"
        }
    ],
    "sg:phone":"+1 972 596 3850",
    "sg:postcode":"75075",
    "sg:province":"TX",
    "sg:tags":[
        "electronic",
        "shoes"
    ],
    "wof:name":"Thats Showbiz",
    "wof:placetype":"venue"
},
  "geometry": {"coordinates":[-96.741225,33.034061],"type":"Point"}
}