{
  "type": "Feature",
  "properties": {
    "iso:country":"US",
    "sg:address":"5000 Ashlock Dr",
    "sg:city":"Lewisville",
    "sg:classifiers":[
        {
            "category":"Professional",
            "type":"Services"
        }
    ],
    "sg:phone":"+1 972 624 8744",
    "sg:postcode":"75056",
    "sg:province":"TX",
    "wof:name":"Brian P Walker",
    "wof:placetype":"venue"
},
  "geometry": {"coordinates":[-96.88702000000001,33.09568],"type":"Point"}
}