{
  "type": "Feature",
  "properties": {
    "iso:country":"US",
    "sg:address":"9486 Somerset Rd",
    "sg:city":"San Antonio",
    "sg:classifiers":[
        {
            "category":"Real Estate",
            "subcategory":"Real Estate Operator",
            "type":"Services"
        }
    ],
    "sg:phone":"+1 210 623 4000",
    "sg:postcode":"78211",
    "sg:province":"TX",
    "sg:tags":[
        "mobile",
        "home",
        "site"
    ],
    "wof:name":"Brookdale Mobile Home Park",
    "wof:placetype":"venue"
},
  "geometry": {"coordinates":[-98.58466799999999,29.328809],"type":"Point"}
}