{
  "type": "Feature",
  "properties": {
    "iso:country":"US",
    "sg:address":"1400 Moberly Dr",
    "sg:city":"Amarillo",
    "sg:classifiers":[
        {
            "category":"Shopping",
            "subcategory":"Used Merchandise",
            "type":"Retail Goods"
        }
    ],
    "sg:phone":"+1 806 335 2866",
    "sg:postcode":"79111",
    "sg:province":"TX",
    "sg:tags":[
        "second",
        "store",
        "hand"
    ],
    "wof:name":"Wampum Enterprises",
    "wof:placetype":"venue"
},
  "geometry": {"coordinates":[-101.664727,35.229391],"type":"Point"}
}