{
  "type": "Feature",
  "properties": {
    "iso:country":"US",
    "sg:address":"10295 Eastex Fwy",
    "sg:city":"Beaumont",
    "sg:classifiers":[
        {
            "category":"Health Services",
            "subcategory":"Clinic",
            "type":"Services"
        }
    ],
    "sg:phone":"+1 409 899 9053",
    "sg:postcode":"77708",
    "sg:province":"TX",
    "sg:tags":[
        "home"
    ],
    "wof:name":"Jordan Health Svc",
    "wof:placetype":"venue"
},
  "geometry": {"coordinates":[-94.182016,30.15632],"type":"Point"}
}