{
  "type": "Feature",
  "properties": {
    "iso:country":"US",
    "sg:address":"17706 Cypress Spring Dr",
    "sg:city":"Spring",
    "sg:classifiers":[
        {
            "category":"Real Estate",
            "subcategory":"Real Estate Operator",
            "type":"Services"
        }
    ],
    "sg:phone":"+1 281 350 8698",
    "sg:postcode":"77388",
    "sg:province":"TX",
    "sg:tags":[
        "building",
        "nonresidential"
    ],
    "wof:name":"AAA Properties",
    "wof:placetype":"venue"
},
  "geometry": {"coordinates":[-95.4746,30.034967],"type":"Point"}
}