{
  "type": "Feature",
  "properties": {
    "iso:country":"US",
    "sg:address":"2486 Times Blvd",
    "sg:city":"Houston",
    "sg:classifiers":[
        {
            "category":"Shopping",
            "subcategory":"Jewelry",
            "type":"Retail Goods"
        }
    ],
    "sg:phone":"+1 713 528 2135",
    "sg:postcode":"77005",
    "sg:province":"TX",
    "sg:website":"www.hnex.com",
    "wof:name":"HNE INC",
    "wof:placetype":"venue"
},
  "geometry": {"coordinates":[-95.416449,29.716798],"type":"Point"}
}