{
  "type": "Feature",
  "properties": {
    "iso:country":"US",
    "sg:address":"1909 Woodall Rodgers Fwy",
    "sg:city":"Dallas",
    "sg:classifiers":[
        {
            "category":"Professional",
            "subcategory":"Lawyer & Legal Services",
            "type":"Services"
        }
    ],
    "sg:phone":"+1 214 522 3343",
    "sg:postcode":"75201",
    "sg:province":"TX",
    "wof:name":"Hall Stephanie Atty",
    "wof:placetype":"venue"
},
  "geometry": {"coordinates":[-96.80308599999999,32.789113],"type":"Point"}
}