{
  "type": "Feature",
  "properties": {
    "iso:country":"US",
    "sg:address":"1606 W Pine Branch Dr",
    "sg:city":"Pearland",
    "sg:classifiers":[
        {
            "category":"Professional",
            "subcategory":"Business Services",
            "type":"Services"
        }
    ],
    "sg:phone":"+1 281 992 7654",
    "sg:postcode":"77581",
    "sg:province":"TX",
    "wof:name":"Document Technology Services",
    "wof:placetype":"venue"
},
  "geometry": {"coordinates":[-95.23383800000001,29.537637],"type":"Point"}
}