{
  "type": "Feature",
  "properties": {
    "iso:country":"US",
    "sg:address":"2223 Palmer Hwy",
    "sg:city":"Texas City",
    "sg:classifiers":[
        {
            "category":"Restaurant",
            "type":"Food & Drink"
        }
    ],
    "sg:phone":"+1 409 948 6501",
    "sg:postcode":"77590",
    "sg:province":"TX",
    "sg:tags":[
        "eating"
    ],
    "wof:name":"Grand Prize Catering",
    "wof:placetype":"venue"
},
  "geometry": {"coordinates":[-94.927485,29.393641],"type":"Point"}
}