{
  "type": "Feature",
  "properties": {
    "iso:country":"US",
    "sg:address":"208 Old Bayou Dr",
    "sg:city":"Dickinson",
    "sg:classifiers":[
        {
            "category":"Shopping",
            "subcategory":"Gifts & Souvenirs",
            "type":"Retail Goods"
        }
    ],
    "sg:phone":"+1 281 337 2964",
    "sg:postcode":"77539",
    "sg:province":"TX",
    "wof:name":"Bamis Flowers & Gifts",
    "wof:placetype":"venue"
},
  "geometry": {"coordinates":[-95.07243800000001,29.445721],"type":"Point"}
}