{
  "type": "Feature",
  "properties": {
    "iso:country":"US",
    "sg:address":"4818 W Hwy 31",
    "sg:city":"Corsicana",
    "sg:classifiers":[
        {
            "category":"Shopping",
            "subcategory":"Pharmacy",
            "type":"Retail Goods"
        }
    ],
    "sg:phone":"+1 903 874 7972",
    "sg:postcode":"75110",
    "sg:province":"TX",
    "wof:name":"Today Quilts By Miz Willi",
    "wof:placetype":"venue"
},
  "geometry": {"coordinates":[-96.522317,32.059065],"type":"Point"}
}