{
  "type": "Feature",
  "properties": {
    "iso:country":"US",
    "sg:address":"3301 Broadway Blvd",
    "sg:city":"Garland",
    "sg:classifiers":[
        {
            "category":"Food & Beverages",
            "subcategory":"Groceries & Convenience Stores",
            "type":"Retail Goods"
        }
    ],
    "sg:phone":"+1 972 926 7774",
    "sg:postcode":"75043",
    "sg:province":"TX",
    "wof:name":"Super Qwik",
    "wof:placetype":"venue"
},
  "geometry": {"coordinates":[-96.618337,32.875867],"type":"Point"}
}