{
  "type": "Feature",
  "properties": {
    "iso:country":"US",
    "sg:address":"700 W Main St",
    "sg:city":"Atlanta",
    "sg:classifiers":[
        {
            "category":"Shopping",
            "subcategory":"Computers & Home Electronics",
            "type":"Retail Goods"
        }
    ],
    "sg:phone":"+1 903 796 7419",
    "sg:postcode":"75551",
    "sg:province":"TX",
    "sg:tags":[
        "equipment",
        "dealer"
    ],
    "wof:name":"Computer King",
    "wof:placetype":"venue"
},
  "geometry": {"coordinates":[-94.17585,33.113656],"type":"Point"}
}