{
  "type": "Feature",
  "properties": {
    "iso:country":"US",
    "sg:address":"2127 E Highway 190",
    "sg:city":"Copperas Cove",
    "sg:classifiers":[
        {
            "category":"Restaurant",
            "type":"Food & Drink"
        }
    ],
    "sg:menulink":"http://www.allmenus.com/tx/copperas-cove/94441-dominos-pizza/menu/",
    "sg:phone":"+1 254 547 7566",
    "sg:postcode":"76522",
    "sg:province":"TX",
    "sg:tags":[
        "american",
        "wing",
        "pizza"
    ],
    "wof:name":"Domino's Pizza",
    "wof:placetype":"venue"
},
  "geometry": {"coordinates":[-97.88193099999999,31.120347],"type":"Point"}
}