{
  "type": "Feature",
  "properties": {
    "iso:country":"US",
    "sg:address":"2700 7th St",
    "sg:city":"Bay City",
    "sg:classifiers":[
        {
            "category":"Food & Beverages",
            "subcategory":"Groceries & Convenience Stores",
            "type":"Retail Goods"
        }
    ],
    "sg:phone":"+1 979 245 2990",
    "sg:postcode":"77414",
    "sg:province":"TX",
    "sg:tags":[
        "grocer"
    ],
    "sg:website":"www.heb.com",
    "wof:name":"H E B Foods",
    "wof:placetype":"venue"
},
  "geometry": {"coordinates":[-95.956987,28.983373],"type":"Point"}
}