{
  "type": "Feature",
  "properties": {
    "iso:country":"US",
    "sg:address":"619 S Denton St",
    "sg:city":"Gainesville",
    "sg:classifiers":[
        {
            "category":"Home & Garden",
            "subcategory":"Furniture",
            "type":"Retail Goods"
        }
    ],
    "sg:phone":"+1 940 612 2688",
    "sg:postcode":"76240",
    "sg:province":"TX",
    "wof:name":"Aimee D Fogle",
    "wof:placetype":"venue"
},
  "geometry": {"coordinates":[-97.142482,33.619676],"type":"Point"}
}