{
  "type": "Feature",
  "properties": {
    "iso:country":"US",
    "sg:address":"15599 Montana Ave",
    "sg:city":"El Paso",
    "sg:classifiers":[
        {
            "category":"Professional",
            "type":"Services"
        }
    ],
    "sg:phone":"+1 915 921 7956",
    "sg:postcode":"79938",
    "sg:province":"TX",
    "sg:tags":[
        "establishment"
    ],
    "wof:name":"Valfran Auto Collision",
    "wof:placetype":"venue"
},
  "geometry": {"coordinates":[-106.12600999999999,31.826008],"type":"Point"}
}