{
  "type": "Feature",
  "properties": {
    "iso:country":"US",
    "sg:address":"2008 Teri Rd",
    "sg:city":"Austin",
    "sg:classifiers":[
        {
            "category":"Restaurant",
            "type":"Food & Drink"
        },
        {
            "category":"Food Court",
            "type":"Food & Drink"
        }
    ],
    "sg:phone":"+1 512 619 3798",
    "sg:postcode":"78744",
    "sg:province":"TX",
    "sg:tags":[
        "mexican",
        "stand"
    ],
    "wof:name":"Taqueria Lopez",
    "wof:placetype":"venue"
},
  "geometry": {"coordinates":[-97.75241,30.202204],"type":"Point"}
}