{
  "type": "Feature",
  "properties": {
    "iso:country":"US",
    "sg:address":"303 Capewood Dr",
    "sg:city":"League City",
    "sg:classifiers":[
        {
            "category":"Shopping",
            "type":"Retail Goods"
        }
    ],
    "sg:phone":"+1 281 728 1733",
    "sg:postcode":"77573",
    "sg:province":"TX",
    "sg:tags":[
        "pet",
        "consulting",
        "supply"
    ],
    "wof:name":"Catbird & Co",
    "wof:placetype":"venue"
},
  "geometry": {"coordinates":[-95.08458,29.492288],"type":"Point"}
}