{
  "type": "Feature",
  "properties": {
    "iso:country":"US",
    "sg:address":"1820 Allen St",
    "sg:city":"Rosenberg",
    "sg:classifiers":[
        {
            "category":"Wholesale",
            "subcategory":"Farm Supplies",
            "type":"Manufacturing & Wholesale Goods"
        }
    ],
    "sg:phone":"+1 281 342 8747",
    "sg:postcode":"77471",
    "sg:province":"TX",
    "sg:tags":[
        "livestock"
    ],
    "wof:name":"Joe Gurecky",
    "wof:placetype":"venue"
},
  "geometry": {"coordinates":[-95.81849099999999,29.54919],"type":"Point"}
}