{
  "type": "Feature",
  "properties": {
    "iso:country":"US",
    "sg:address":"201 S Main St",
    "sg:city":"Bryan",
    "sg:classifiers":[
        {
            "category":"Restaurant",
            "type":"Food & Drink"
        }
    ],
    "sg:phone":"+1 979 775 7272",
    "sg:postcode":"77803",
    "sg:province":"TX",
    "sg:tags":[
        "mexican"
    ],
    "wof:name":"Papa Perez Mexican Cuisine",
    "wof:placetype":"venue"
},
  "geometry": {"coordinates":[-96.373543,30.672779],"type":"Point"}
}