{
  "type": "Feature",
  "properties": {
    "iso:country":"US",
    "sg:address":"210 D Lynne St",
    "sg:city":"Aubrey",
    "sg:classifiers":[
        {
            "category":"Professional",
            "subcategory":"Business Services",
            "type":"Services"
        }
    ],
    "sg:phone":"+1 940 365 3116",
    "sg:postcode":"76227",
    "sg:province":"TX",
    "wof:name":"Bill L Wright",
    "wof:placetype":"venue"
},
  "geometry": {"coordinates":[-96.99037800000001,33.305714],"type":"Point"}
}