{
  "type": "Feature",
  "properties": {
    "iso:country":"US",
    "sg:address":"1308 N Hwy 146",
    "sg:city":"Baytown",
    "sg:classifiers":[
        {
            "category":"Retail",
            "subcategory":"Funeral Services",
            "type":"Services"
        }
    ],
    "sg:phone":"+1 281 837 1509",
    "sg:postcode":"77521",
    "sg:province":"TX",
    "wof:name":"Guillen Baytown Funeral Home",
    "wof:placetype":"venue"
},
  "geometry": {"coordinates":[-94.91663200000001,29.770356],"type":"Point"}
}