{
  "type": "Feature",
  "properties": {
    "iso:country":"US",
    "sg:address":"3804 Elysian St",
    "sg:city":"Houston",
    "sg:classifiers":[
        {
            "category":"Shopping",
            "subcategory":"Music",
            "type":"Retail Goods"
        }
    ],
    "sg:phone":"+1 713 742 9294",
    "sg:postcode":"77009",
    "sg:province":"TX",
    "wof:name":"Redman Records",
    "wof:placetype":"venue"
},
  "geometry": {"coordinates":[-95.35119299999999,29.795761],"type":"Point"}
}