{
  "type": "Feature",
  "properties": {
    "iso:country":"US",
    "sg:address":"316 Little St",
    "sg:city":"Wilmer",
    "sg:classifiers":[
        {
            "category":"Professional",
            "subcategory":"Engineering",
            "type":"Services"
        }
    ],
    "sg:phone":"+1 214 923 0658",
    "sg:postcode":"75172",
    "sg:province":"TX",
    "sg:tags":[
        "consulting",
        "engineer"
    ],
    "wof:name":"Endeavor",
    "wof:placetype":"venue"
},
  "geometry": {"coordinates":[-96.688152,32.59135],"type":"Point"}
}