{
  "type": "Feature",
  "properties": {
    "iso:country":"US",
    "sg:address":"705 8th St",
    "sg:city":"Wichita Falls",
    "sg:classifiers":[
        {
            "category":"Communications",
            "subcategory":"Film & Video Production",
            "type":"Services"
        }
    ],
    "sg:phone":"+1 940 763 2326",
    "sg:postcode":"76301",
    "sg:province":"TX",
    "sg:tags":[
        "taping"
    ],
    "wof:name":"Adco",
    "wof:placetype":"venue"
},
  "geometry": {"coordinates":[-98.492001,33.911873],"type":"Point"}
}