{
  "type": "Feature",
  "properties": {
    "iso:country":"US",
    "sg:address":"206 E Main Ave",
    "sg:city":"Round Rock",
    "sg:classifiers":[
        {
            "category":"Real Estate",
            "subcategory":"Real Estate Agent",
            "type":"Services"
        }
    ],
    "sg:phone":"+1 512 255 1116",
    "sg:postcode":"78664",
    "sg:province":"TX",
    "wof:name":"Overland Property Group Inc",
    "wof:placetype":"venue"
},
  "geometry": {"coordinates":[-97.67677999999999,30.509224],"type":"Point"}
}