{
  "type": "Feature",
  "properties": {
    "iso:country":"US",
    "sg:address":"12502 Taylor Rd",
    "sg:city":"Houston",
    "sg:classifiers":[
        {
            "category":"Wholesale",
            "subcategory":"Electrical",
            "type":"Manufacturing & Wholesale Goods"
        }
    ],
    "sg:phone":"+1 713 466 3956",
    "sg:postcode":"77041",
    "sg:province":"TX",
    "sg:tags":[
        "lighting",
        "fixture"
    ],
    "wof:name":"Buck Lighting Co",
    "wof:placetype":"venue"
},
  "geometry": {"coordinates":[-95.598468,29.893501],"type":"Point"}
}