{
  "type": "Feature",
  "properties": {
    "iso:country":"US",
    "sg:address":"8230 Co Rd 392",
    "sg:city":"Princeton",
    "sg:classifiers":[
        {
            "category":"Building & Trades",
            "subcategory":"Landscaping Services",
            "type":"Services"
        }
    ],
    "sg:phone":"+1 972 734 6782",
    "sg:postcode":"75407",
    "sg:province":"TX",
    "wof:name":"Motivated Maintenance",
    "wof:placetype":"venue"
},
  "geometry": {"coordinates":[-96.515945,33.130937],"type":"Point"}
}