{
  "type": "Feature",
  "properties": {
    "iso:country":"US",
    "sg:address":"5095 Estes Pkwy",
    "sg:city":"Longview",
    "sg:classifiers":[
        {
            "category":"Professional",
            "subcategory":"Accounting & Tax Preparation",
            "type":"Services"
        }
    ],
    "sg:phone":"+1 903 643 9973",
    "sg:postcode":"75603",
    "sg:province":"TX",
    "sg:tags":[
        "reporting",
        "return",
        "preparation-business"
    ],
    "wof:name":"Community Tax Service",
    "wof:placetype":"venue"
},
  "geometry": {"coordinates":[-94.67568,32.392816],"type":"Point"}
}