{
  "type": "Feature",
  "properties": {
    "iso:country":"US",
    "sg:address":"1601 S Grand St",
    "sg:city":"Amarillo",
    "sg:classifiers":[
        {
            "category":"Restaurant",
            "type":"Food & Drink"
        }
    ],
    "sg:phone":"+1 806 374 4335",
    "sg:postcode":"79104",
    "sg:province":"TX",
    "sg:tags":[
        "eating"
    ],
    "wof:name":"Chicho's Cafe",
    "wof:placetype":"venue"
},
  "geometry": {"coordinates":[-101.79534099999999,35.194348],"type":"Point"}
}