{
  "type": "Feature",
  "properties": {
    "iso:country":"US",
    "sg:address":"3097 Kings Crown Pl",
    "sg:city":"El Paso",
    "sg:classifiers":[
        {
            "category":"Freight",
            "type":"Transportation"
        }
    ],
    "sg:phone":"+1 915 849 0246",
    "sg:postcode":"79936",
    "sg:province":"TX",
    "sg:tags":[
        "operator",
        "local",
        "trucking"
    ],
    "wof:name":"Three of A Kind Trucking",
    "wof:placetype":"venue"
},
  "geometry": {"coordinates":[-106.271764,31.785127],"type":"Point"}
}