{
  "type": "Feature",
  "properties": {
    "iso:country":"US",
    "sg:address":"2838 Anita Ln",
    "sg:city":"Tyler",
    "sg:classifiers":[
        {
            "category":"Professional",
            "subcategory":"Accounting & Tax Preparation",
            "type":"Services"
        }
    ],
    "sg:phone":"+1 903 566 8016",
    "sg:postcode":"75701",
    "sg:province":"TX",
    "sg:tags":[
        "return",
        "filing"
    ],
    "wof:name":"Jule Campbell",
    "wof:placetype":"venue"
},
  "geometry": {"coordinates":[-95.261392,32.315581],"type":"Point"}
}