{
  "type": "Feature",
  "properties": {
    "iso:country":"US",
    "sg:address":"6101 N 23rd St",
    "sg:city":"Mcallen",
    "sg:classifiers":[
        {
            "category":"Personal",
            "subcategory":"Nail Salon",
            "type":"Services"
        }
    ],
    "sg:phone":"+1 956 661 9770",
    "sg:postcode":"78504",
    "sg:province":"TX",
    "wof:name":"Mcallen Nails",
    "wof:placetype":"venue"
},
  "geometry": {"coordinates":[-98.23584700000001,26.261681],"type":"Point"}
}