{
  "type": "Feature",
  "properties": {
    "iso:country":"US",
    "sg:address":"1011 S Walton Walker Blvd",
    "sg:city":"Dallas",
    "sg:classifiers":[
        {
            "category":"Recreation",
            "type":"Entertainment"
        }
    ],
    "sg:phone":"+1 214 467 7674",
    "sg:postcode":"75211",
    "sg:province":"TX",
    "sg:tags":[
        "club",
        "membership"
    ],
    "wof:name":"My Club",
    "wof:placetype":"venue"
},
  "geometry": {"coordinates":[-96.920449,32.736277],"type":"Point"}
}