{
  "type": "Feature",
  "properties": {
    "iso:country":"US",
    "sg:address":"2914 Serrano Trl",
    "sg:city":"Katy",
    "sg:classifiers":[
        {
            "category":"Professional",
            "subcategory":"Business Services",
            "type":"Services"
        }
    ],
    "sg:phone":"+1 281 578 0904",
    "sg:postcode":"77450",
    "sg:province":"TX",
    "wof:name":"Jigu Enterprises Inc",
    "wof:placetype":"venue"
},
  "geometry": {"coordinates":[-95.73662400000001,29.741365],"type":"Point"}
}