{
  "type": "Feature",
  "properties": {
    "iso:country":"US",
    "sg:address":"1201 Caroline St",
    "sg:city":"Houston",
    "sg:classifiers":[
        {
            "category":"Restaurant",
            "type":"Food & Drink"
        }
    ],
    "sg:phone":"+1 713 651 3030",
    "sg:postcode":"77002",
    "sg:province":"TX",
    "wof:name":"Daiji's Izakaya",
    "wof:placetype":"venue"
},
  "geometry": {"coordinates":[-95.364098,29.753145],"type":"Point"}
}