{
  "type": "Feature",
  "properties": {
    "iso:country":"US",
    "sg:address":"11501 Town Lake Ln",
    "sg:city":"El Paso",
    "sg:classifiers":[
        {
            "category":"Shopping",
            "subcategory":"Clothing, Apparel, & Fashions",
            "type":"Retail Goods"
        }
    ],
    "sg:phone":"+1 915 855 9777",
    "sg:postcode":"79936",
    "sg:province":"TX",
    "sg:tags":[
        "art"
    ],
    "wof:name":"Beyond",
    "wof:placetype":"venue"
},
  "geometry": {"coordinates":[-106.292146,31.773248],"type":"Point"}
}