{
  "type": "Feature",
  "properties": {
    "iso:country":"US",
    "sg:address":"251 Carpers Trl",
    "sg:city":"Fischer",
    "sg:classifiers":[
        {
            "category":"Farming",
            "subcategory":"Farm",
            "type":"Manufacturing & Wholesale Goods"
        }
    ],
    "sg:phone":"+1 830 935 2826",
    "sg:postcode":"78623",
    "sg:province":"TX",
    "wof:name":"Stonehollow Farms",
    "wof:placetype":"venue"
},
  "geometry": {"coordinates":[-98.233002,29.968421],"type":"Point"}
}