{
  "type": "Feature",
  "properties": {
    "iso:country":"US",
    "sg:address":"6617 Ridgeview Cir",
    "sg:city":"Dallas",
    "sg:classifiers":[
        {
            "category":"Banks & Credit Unions",
            "subcategory":"Financial Services",
            "type":"Services"
        }
    ],
    "sg:phone":"+1 972 387 2737",
    "sg:postcode":"75240",
    "sg:province":"TX",
    "sg:tags":[
        "trust",
        "investment",
        "real estate"
    ],
    "wof:name":"Acorn Capital Company",
    "wof:placetype":"venue"
},
  "geometry": {"coordinates":[-96.790426,32.928721],"type":"Point"}
}