{
  "type": "Feature",
  "properties": {
    "iso:country":"US",
    "sg:address":"1207 Glouchester Ln",
    "sg:city":"Houston",
    "sg:classifiers":[
        {
            "category":"Real Estate",
            "subcategory":"Real Estate Agent",
            "type":"Services"
        }
    ],
    "sg:phone":"+1 281 443 8000",
    "sg:postcode":"77073",
    "sg:province":"TX",
    "wof:name":"Marie Taravella Inc",
    "wof:placetype":"venue"
},
  "geometry": {"coordinates":[-95.40970299999999,30.033411],"type":"Point"}
}