{
  "type": "Feature",
  "properties": {
    "iso:country":"US",
    "sg:address":"1111 Mulberry Dr",
    "sg:city":"Marble Falls",
    "sg:classifiers":[
        {
            "category":"Professional",
            "subcategory":"Computer Services",
            "type":"Services"
        }
    ],
    "sg:phone":"+1 830 798 8998",
    "sg:postcode":"78654",
    "sg:province":"TX",
    "sg:tags":[
        "related"
    ],
    "wof:name":"RLC Data Management",
    "wof:placetype":"venue"
},
  "geometry": {"coordinates":[-98.29245,30.557827],"type":"Point"}
}