{
  "type": "Feature",
  "properties": {
    "iso:country":"US",
    "sg:address":"1900 I- 35 S",
    "sg:city":"San Marcos",
    "sg:classifiers":[
        {
            "category":"Professional",
            "subcategory":"Business Services",
            "type":"Services"
        }
    ],
    "sg:phone":"+1 512 473 8208",
    "sg:postcode":"78666",
    "sg:province":"TX",
    "sg:tags":[
        "bail",
        "bond"
    ],
    "wof:name":"AAA Bail Bond",
    "wof:placetype":"venue"
},
  "geometry": {"coordinates":[-97.950547,29.859689],"type":"Point"}
}