{
  "type": "Feature",
  "properties": {
    "iso:country":"US",
    "sg:address":"2602 W 11th St",
    "sg:city":"Plainview",
    "sg:classifiers":[
        {
            "category":"Food & Beverages",
            "subcategory":"Fruits & Vegetables",
            "type":"Retail Goods"
        }
    ],
    "sg:phone":"+1 806 291 0851",
    "sg:postcode":"79072",
    "sg:province":"TX",
    "sg:tags":[
        "produce"
    ],
    "wof:name":"Rivera Produce Inc",
    "wof:placetype":"venue"
},
  "geometry": {"coordinates":[-101.73566599999999,34.191669],"type":"Point"}
}