{
  "type": "Feature",
  "properties": {
    "iso:country":"US",
    "sg:address":"9720 Data Point Dr",
    "sg:city":"San Antonio",
    "sg:classifiers":[
        {
            "category":"Retail",
            "subcategory":"Laundry & Dry Cleaning",
            "type":"Services"
        }
    ],
    "sg:phone":"+1 210 415 6300",
    "sg:postcode":"78229",
    "sg:province":"TX",
    "sg:tags":[
        "cleaners",
        "rug",
        "carpet"
    ],
    "wof:name":"Clean Like New",
    "wof:placetype":"venue"
},
  "geometry": {"coordinates":[-98.56347,29.527249],"type":"Point"}
}