{
  "type": "Feature",
  "properties": {
    "iso:country":"US",
    "sg:address":"514 W Commerce St",
    "sg:city":"Dallas",
    "sg:classifiers":[
        {
            "category":"Travel",
            "subcategory":"Hotels & Motels",
            "type":"Entertainment"
        }
    ],
    "sg:phone":"+1 214 744 9279",
    "sg:postcode":"75208",
    "sg:province":"TX",
    "sg:tags":[
        "operation"
    ],
    "wof:name":"Mission Motel",
    "wof:placetype":"venue"
},
  "geometry": {"coordinates":[-96.8335,32.772987],"type":"Point"}
}