{
  "type": "Feature",
  "properties": {
    "iso:country":"US",
    "sg:address":"3388 Sage Rd",
    "sg:city":"Houston",
    "sg:classifiers":[
        {
            "category":"Real Estate",
            "subcategory":"Real Estate Agent",
            "type":"Services"
        },
        {
            "category":"Real Estate",
            "subcategory":"Real Estate Operator",
            "type":"Services"
        }
    ],
    "sg:phone":"+1 713 623 2733",
    "sg:postcode":"77056",
    "sg:province":"TX",
    "sg:tags":[
        "condominium"
    ],
    "wof:name":"Mercer Condominiums Inc",
    "wof:placetype":"venue"
},
  "geometry": {"coordinates":[-95.466685,29.73088],"type":"Point"}
}