{
  "type": "Feature",
  "properties": {
    "iso:country":"US",
    "sg:address":"24420 Trumbo Rd",
    "sg:city":"San Antonio",
    "sg:classifiers":[
        {
            "category":"Retail",
            "subcategory":"Auto Repair",
            "type":"Services"
        }
    ],
    "sg:phone":"+1 210 626 2742",
    "sg:postcode":"78264",
    "sg:province":"TX",
    "sg:tags":[
        "transmission"
    ],
    "wof:name":"Ricks Transmissin",
    "wof:placetype":"venue"
},
  "geometry": {"coordinates":[-98.524694,29.152],"type":"Point"}
}