{
  "type": "Feature",
  "properties": {
    "iso:country":"US",
    "sg:address":"14302 Westheimer Rd",
    "sg:city":"Houston",
    "sg:classifiers":[
        {
            "category":"Restaurant",
            "type":"Food & Drink"
        }
    ],
    "sg:phone":"+1 281 497 2575",
    "sg:postcode":"77077",
    "sg:province":"TX",
    "sg:tags":[
        "eating"
    ],
    "wof:name":"Hartz Chicken Buffet",
    "wof:placetype":"venue"
},
  "geometry": {"coordinates":[-95.64403,29.735718],"type":"Point"}
}