{
  "type": "Feature",
  "properties": {
    "iso:country":"US",
    "sg:address":"4028 Daley Ave",
    "sg:city":"Fort Worth",
    "sg:classifiers":[
        {
            "category":"Professional",
            "subcategory":"Computer Services",
            "type":"Services"
        }
    ],
    "sg:phone":"+1 817 595 4700",
    "sg:postcode":"76180",
    "sg:province":"TX",
    "sg:tags":[
        "prepackaged",
        "software"
    ],
    "wof:name":"Ntex Technologies",
    "wof:placetype":"venue"
},
  "geometry": {"coordinates":[-97.22968299999999,32.822916],"type":"Point"}
}