{
  "type": "Feature",
  "properties": {
    "iso:country":"US",
    "sg:address":"770 Saint Andrew Dr",
    "sg:city":"Lewisville",
    "sg:classifiers":[
        {
            "category":"Shopping",
            "subcategory":"Gifts & Souvenirs",
            "type":"Retail Goods"
        }
    ],
    "sg:phone":"+1 972 317 0789",
    "sg:postcode":"75077",
    "sg:province":"TX",
    "wof:name":"Nancy J Rodgers",
    "wof:placetype":"venue"
},
  "geometry": {"coordinates":[-97.068653,33.079182],"type":"Point"}
}