{
  "type": "Feature",
  "properties": {
    "iso:country":"US",
    "sg:address":"411 Lakeview St",
    "sg:city":"Whitehouse",
    "sg:classifiers":[
        {
            "category":"Communications",
            "subcategory":"Television Station",
            "type":"Services"
        }
    ],
    "sg:phone":"+1 903 839 6422",
    "sg:postcode":"75791",
    "sg:province":"TX",
    "sg:tags":[
        "satellite",
        "cable"
    ],
    "wof:name":"Crawford Global Cable",
    "wof:placetype":"venue"
},
  "geometry": {"coordinates":[-95.21065,32.231461],"type":"Point"}
}