{
  "type": "Feature",
  "properties": {
    "iso:country":"US",
    "sg:address":"1302 Dayton Rd",
    "sg:city":"Midland",
    "sg:classifiers":[
        {
            "category":"Mining & Drilling",
            "type":"Manufacturing & Wholesale Goods"
        }
    ],
    "sg:phone":"+1 432 682 5406",
    "sg:postcode":"79706",
    "sg:province":"TX",
    "sg:tags":[
        "field"
    ],
    "wof:name":"Dean Energy Inc",
    "wof:placetype":"venue"
},
  "geometry": {"coordinates":[-102.075658,31.968437],"type":"Point"}
}