{
  "type": "Feature",
  "properties": {
    "iso:country":"US",
    "sg:address":"6300 Bridge Point Pkwy",
    "sg:city":"Austin",
    "sg:classifiers":[
        {
            "category":"Communications",
            "subcategory":"Television Station",
            "type":"Services"
        }
    ],
    "sg:phone":"+1 512 795 6865",
    "sg:postcode":"78730",
    "sg:province":"TX",
    "sg:tags":[
        "network"
    ],
    "wof:name":"Zenoss",
    "wof:placetype":"venue"
},
  "geometry": {"coordinates":[-97.80076200000001,30.354081],"type":"Point"}
}