{
  "type": "Feature",
  "properties": {
    "iso:country":"US",
    "sg:address":"1250 State Hwy 16",
    "sg:city":"Fredericksburg",
    "sg:classifiers":[
        {
            "category":"Mining & Drilling",
            "type":"Manufacturing & Wholesale Goods"
        }
    ],
    "sg:phone":"+1 830 997 7700",
    "sg:postcode":"78624",
    "sg:province":"TX",
    "sg:tags":[
        "development",
        "gas",
        "oil",
        "exploration"
    ],
    "wof:name":"Impact Exploration",
    "wof:placetype":"venue"
},
  "geometry": {"coordinates":[-98.89063400000001,30.255613],"type":"Point"}
}