{
  "type": "Feature",
  "properties": {
    "iso:country":"US",
    "sg:address":"708 E Pipeline Rd",
    "sg:city":"Hurst",
    "sg:classifiers":[
        {
            "category":"Food & Beverages",
            "subcategory":"Groceries & Convenience Stores",
            "type":"Retail Goods"
        }
    ],
    "sg:phone":"+1 817 285 9515",
    "sg:postcode":"76053",
    "sg:province":"TX",
    "wof:name":"Kroger-Texas LP",
    "wof:placetype":"venue"
},
  "geometry": {"coordinates":[-97.15942099999999,32.823441],"type":"Point"}
}