{
  "type": "Feature",
  "properties": {
    "iso:country":"US",
    "sg:address":"138 Scott Ln",
    "sg:city":"Weatherford",
    "sg:classifiers":[
        {
            "category":"Building & Trades",
            "subcategory":"Pest Control",
            "type":"Services"
        }
    ],
    "sg:phone":"+1 817 306 4389",
    "sg:postcode":"76085",
    "sg:province":"TX",
    "sg:tags":[
        "mothproofing"
    ],
    "wof:name":"Boyer Pest Control Svc.",
    "wof:placetype":"venue"
},
  "geometry": {"coordinates":[-97.601783,32.897734],"type":"Point"}
}