{
  "type": "Feature",
  "properties": {
    "iso:country":"US",
    "sg:address":"303 N Jackson St",
    "sg:city":"Jacksonville",
    "sg:classifiers":[
        {
            "category":"Shopping",
            "subcategory":"Gifts & Souvenirs",
            "type":"Retail Goods"
        }
    ],
    "sg:phone":"+1 903 586 4123",
    "sg:postcode":"75766",
    "sg:province":"TX",
    "sg:tags":[
        "shop"
    ],
    "wof:name":"Morgans Gifts",
    "wof:placetype":"venue"
},
  "geometry": {"coordinates":[-95.280922,32.022144],"type":"Point"}
}