{
  "type": "Feature",
  "properties": {
    "iso:country":"US",
    "sg:address":"7215 Bellaire Blvd",
    "sg:city":"Houston",
    "sg:classifiers":[
        {
            "category":"Personal",
            "type":"Services"
        }
    ],
    "sg:phone":"+1 713 973 0469",
    "sg:postcode":"77074",
    "sg:province":"TX",
    "sg:tags":[
        "therapist",
        "massage"
    ],
    "wof:name":"Secret Health Touch",
    "wof:placetype":"venue"
},
  "geometry": {"coordinates":[-95.51257699999999,29.704114],"type":"Point"}
}