{
  "type": "Feature",
  "properties": {
    "iso:country":"US",
    "sg:address":"515 Campbell St",
    "sg:city":"Denton",
    "sg:classifiers":[
        {
            "category":"Retail",
            "subcategory":"Repair Shop",
            "type":"Services"
        }
    ],
    "sg:phone":"+1 940 380 1163",
    "sg:postcode":"79553",
    "sg:province":"TX",
    "wof:name":"Aqua Clean Pool Service",
    "wof:placetype":"venue"
},
  "geometry": {"coordinates":[-99.809743,32.948734],"type":"Point"}
}