{
  "type": "Feature",
  "properties": {
    "iso:country":"US",
    "sg:address":"4800 N 23rd St",
    "sg:city":"Mcallen",
    "sg:classifiers":[
        {
            "category":"Banks & Credit Unions",
            "subcategory":"Investment Brokerage",
            "type":"Services"
        }
    ],
    "sg:phone":"+1 956 631 2334",
    "sg:postcode":"78504",
    "sg:province":"TX",
    "wof:name":"O E Investments",
    "wof:placetype":"venue"
},
  "geometry": {"coordinates":[-98.237848,26.249651],"type":"Point"}
}