{
  "type": "Feature",
  "properties": {
    "iso:country":"US",
    "sg:address":"5920 W 34th St",
    "sg:city":"Houston",
    "sg:classifiers":[
        {
            "category":"Wholesale",
            "subcategory":"Vending Machines",
            "type":"Manufacturing & Wholesale Goods"
        }
    ],
    "sg:phone":"+1 713 681 9492",
    "sg:postcode":"77092",
    "sg:province":"TX",
    "sg:tags":[
        "operator"
    ],
    "wof:name":"J P Vending",
    "wof:placetype":"venue"
},
  "geometry": {"coordinates":[-95.47599200000001,29.819381],"type":"Point"}
}