{
  "type": "Feature",
  "properties": {
    "iso:country":"US",
    "sg:address":"1314 Roy St",
    "sg:city":"Houston",
    "sg:classifiers":[
        {
            "category":"Food & Beverages",
            "subcategory":"Bakery",
            "type":"Retail Goods"
        }
    ],
    "sg:phone":"+1 713 426 1300",
    "sg:postcode":"77007",
    "sg:province":"TX",
    "wof:name":"Kraftsmen Baking",
    "wof:placetype":"venue"
},
  "geometry": {"coordinates":[-95.41247199999999,29.773166],"type":"Point"}
}