{
  "type": "Feature",
  "properties": {
    "iso:country":"US",
    "sg:address":"1813 Crockett Cir",
    "sg:city":"Irving",
    "sg:classifiers":[
        {
            "category":"Education",
            "subcategory":"Special Training",
            "type":"Public Place"
        }
    ],
    "sg:phone":"+1 214 728 1661",
    "sg:postcode":"75038",
    "sg:province":"TX",
    "wof:name":"Inst Salamanca",
    "wof:placetype":"venue"
},
  "geometry": {"coordinates":[-96.969278,32.857011],"type":"Point"}
}