{
  "type": "Feature",
  "properties": {
    "iso:country":"US",
    "sg:address":"5334 Rufe Snow Dr",
    "sg:city":"Fort Worth",
    "sg:classifiers":[
        {
            "category":"Banks & Credit Unions",
            "subcategory":"Bank",
            "type":"Services"
        }
    ],
    "sg:phone":"+1 817 485 6703",
    "sg:postcode":"76180",
    "sg:province":"TX",
    "sg:tags":[
        "cashing",
        "check"
    ],
    "wof:name":"Check 'n Go",
    "wof:placetype":"venue"
},
  "geometry": {"coordinates":[-97.23855399999999,32.846546],"type":"Point"}
}