{
  "type": "Feature",
  "properties": {
    "iso:country":"US",
    "sg:address":"602 E Polk Ave",
    "sg:city":"Harlingen",
    "sg:classifiers":[
        {
            "category":"Organizations",
            "subcategory":"Religious Organization",
            "type":"Services"
        }
    ],
    "sg:phone":"+1 956 421 2747",
    "sg:postcode":"78550",
    "sg:province":"TX",
    "wof:name":"Templo El Buen Samaritano",
    "wof:placetype":"venue"
},
  "geometry": {"coordinates":[-97.688987,26.188514],"type":"Point"}
}