{
  "type": "Feature",
  "properties": {
    "iso:country":"US",
    "sg:address":"108 NW 9th St",
    "sg:city":"Big Spring",
    "sg:classifiers":[
        {
            "category":"Education",
            "subcategory":"School",
            "type":"Public Place"
        }
    ],
    "sg:phone":"+1 432 264 4121",
    "sg:postcode":"79720",
    "sg:province":"TX",
    "wof:name":"Bauer Elementary",
    "wof:placetype":"venue"
},
  "geometry": {"coordinates":[-101.481466,32.261926],"type":"Point"}
}