{
  "type": "Feature",
  "properties": {
    "iso:country":"US",
    "sg:address":"3109 Uvalde Ave",
    "sg:city":"Nederland",
    "sg:classifiers":[
        {
            "category":"Shopping",
            "type":"Retail Goods"
        }
    ],
    "sg:phone":"+1 409 729 7569",
    "sg:postcode":"77627",
    "sg:province":"TX",
    "sg:tags":[
        "merchandising"
    ],
    "wof:name":"Landry's Sales",
    "wof:placetype":"venue"
},
  "geometry": {"coordinates":[-94.020089,29.972893],"type":"Point"}
}