{
  "type": "Feature",
  "properties": {
    "iso:country":"US",
    "sg:address":"405 Smith Dr",
    "sg:city":"Anna",
    "sg:classifiers":[
        {
            "category":"Building & Trades",
            "subcategory":"Construction",
            "type":"Services"
        }
    ],
    "sg:phone":"+1 972 924 3387",
    "sg:postcode":"75409",
    "sg:province":"TX",
    "sg:tags":[
        "road",
        "contractor"
    ],
    "wof:name":"Reed Barton & Son Excavating",
    "wof:placetype":"venue"
},
  "geometry": {"coordinates":[-96.54444700000001,33.346089],"type":"Point"}
}