{
  "type": "Feature",
  "properties": {
    "iso:country":"US",
    "sg:address":"202 Chevy Chase Dr",
    "sg:city":"San Antonio",
    "sg:classifiers":[
        {
            "category":"Professional",
            "type":"Services"
        }
    ],
    "sg:phone":"+1 210 824 1865",
    "sg:postcode":"78209",
    "sg:province":"TX",
    "wof:name":"Guy L Watts Pc",
    "wof:placetype":"venue"
},
  "geometry": {"coordinates":[-98.450183,29.490395],"type":"Point"}
}