{
  "type": "Feature",
  "properties": {
    "iso:country":"US",
    "sg:address":"385 Ravenaux Dr",
    "sg:city":"Southlake",
    "sg:classifiers":[
        {
            "category":"Organizations",
            "subcategory":"Community Association",
            "type":"Services"
        }
    ],
    "sg:phone":"+1 817 424 1214",
    "sg:postcode":"76092",
    "sg:province":"TX",
    "wof:name":"Ravenaux Place Homeowners",
    "wof:placetype":"venue"
},
  "geometry": {"coordinates":[-97.156158,32.96043],"type":"Point"}
}