{
  "type": "Feature",
  "properties": {
    "iso:country":"US",
    "sg:address":"311 W Mount Houston Rd",
    "sg:city":"Houston",
    "sg:classifiers":[
        {
            "category":"Retail",
            "subcategory":"Auto Repair",
            "type":"Services"
        }
    ],
    "sg:phone":"+1 281 272 5700",
    "sg:postcode":"77037",
    "sg:province":"TX",
    "wof:name":"Aki Auto Care",
    "wof:placetype":"venue"
},
  "geometry": {"coordinates":[-95.405265,29.896602],"type":"Point"}
}