{
  "type": "Feature",
  "properties": {
    "iso:country":"US",
    "sg:address":"1811 Fort Worth Hwy",
    "sg:city":"Weatherford",
    "sg:classifiers":[
        {
            "category":"Retail",
            "subcategory":"Repair Shop",
            "type":"Services"
        }
    ],
    "sg:phone":"+1 817 596 3244",
    "sg:postcode":"76086",
    "sg:province":"TX",
    "sg:tags":[
        "scooter",
        "motorcycle",
        "motor"
    ],
    "sg:website":"www.longhornpowersports.com",
    "wof:name":"Longhorn Power Sports",
    "wof:placetype":"venue"
},
  "geometry": {"coordinates":[-97.757868,32.75698],"type":"Point"}
}