{
  "type": "Feature",
  "properties": {
    "iso:country":"US",
    "sg:address":"1540 Telephone Rd",
    "sg:city":"Houston",
    "sg:classifiers":[
        {
            "category":"Organizations",
            "subcategory":"Religious Organization",
            "type":"Services"
        }
    ],
    "sg:phone":"+1 713 928 2779",
    "sg:postcode":"77023",
    "sg:province":"TX",
    "wof:name":"Sister Mary",
    "wof:placetype":"venue"
},
  "geometry": {"coordinates":[-95.32553799999999,29.727531],"type":"Point"}
}