{
  "type": "Feature",
  "properties": {
    "iso:country":"US",
    "sg:address":"202 S Ridge St",
    "sg:city":"Hallettsville",
    "sg:classifiers":[
        {
            "category":"Social Services",
            "subcategory":"Child Care",
            "type":"Services"
        }
    ],
    "sg:phone":"+1 361 798 1131",
    "sg:postcode":"77964",
    "sg:province":"TX",
    "sg:tags":[
        "day"
    ],
    "wof:name":"Cradle & Crayons",
    "wof:placetype":"venue"
},
  "geometry": {"coordinates":[-96.935323,29.445025],"type":"Point"}
}