{
  "type": "Feature",
  "properties": {
    "iso:country":"US",
    "sg:address":"10611 Hat St",
    "sg:city":"Houston",
    "sg:classifiers":[
        {
            "category":"Wholesale",
            "subcategory":"Durable Goods & Equipment",
            "type":"Manufacturing & Wholesale Goods"
        }
    ],
    "sg:phone":"+1 281 933 0121",
    "sg:postcode":"77099",
    "sg:province":"TX",
    "wof:name":"Fred Wuensche",
    "wof:placetype":"venue"
},
  "geometry": {"coordinates":[-95.60397500000001,29.662776],"type":"Point"}
}