{
  "type": "Feature",
  "properties": {
    "iso:country":"US",
    "sg:address":"10215 Gardner Rd",
    "sg:city":"Dallas",
    "sg:classifiers":[
        {
            "category":"Professional",
            "subcategory":"Research",
            "type":"Services"
        },
        {
            "category":"Banks & Credit Unions",
            "subcategory":"Financial Services",
            "type":"Services"
        }
    ],
    "sg:phone":"+1 972 910 0441",
    "sg:postcode":"75220",
    "sg:province":"TX",
    "sg:tags":[
        "control",
        "hazardous",
        "material",
        "removal",
        "environmental",
        "ecological",
        "investor"
    ],
    "sg:website":"http://www.setenv.com",
    "wof:name":"Set Environmental",
    "wof:placetype":"venue"
},
  "geometry": {"coordinates":[-96.902959,32.863718],"type":"Point"}
}