{
  "type": "Feature",
  "properties": {
    "iso:country":"US",
    "sg:address":"4511 86th St",
    "sg:city":"Lubbock",
    "sg:classifiers":[
        {
            "category":"Professional",
            "subcategory":"Management & Consulting",
            "type":"Services"
        }
    ],
    "sg:phone":"+1 806 798 1152",
    "sg:postcode":"79424",
    "sg:province":"TX",
    "wof:name":"Dgs Educational Consulting",
    "wof:placetype":"venue"
},
  "geometry": {"coordinates":[-101.90994999999999,33.515534],"type":"Point"}
}