{
  "type": "Feature",
  "properties": {
    "iso:country":"US",
    "sg:address":"4036 S Lamar Blvd",
    "sg:city":"Austin",
    "sg:classifiers":[
        {
            "category":"Shopping",
            "subcategory":"Gifts & Souvenirs",
            "type":"Retail Goods"
        }
    ],
    "sg:phone":"+1 512 912 8919",
    "sg:postcode":"78704",
    "sg:province":"TX",
    "wof:name":"Card Mart of Austin Inc",
    "wof:placetype":"venue"
},
  "geometry": {"coordinates":[-97.790865,30.237367],"type":"Point"}
}