{
  "type": "Feature",
  "properties": {
    "iso:country":"US",
    "sg:address":"1251 W Northwest Hwy",
    "sg:city":"Grapevine",
    "sg:classifiers":[
        {
            "category":"Retail",
            "subcategory":"Auto Repair",
            "type":"Services"
        }
    ],
    "sg:phone":"+1 817 488 5520",
    "sg:postcode":"76051",
    "sg:province":"TX",
    "sg:tags":[
        "repairing",
        "automobile"
    ],
    "wof:name":"Family Tire & Svc",
    "wof:placetype":"venue"
},
  "geometry": {"coordinates":[-97.087739,32.941007],"type":"Point"}
}