{
  "type": "Feature",
  "properties": {
    "iso:country":"US",
    "sg:address":"1000 E Cesar Chavez St",
    "sg:city":"Austin",
    "sg:classifiers":[
        {
            "category":"Organizations",
            "subcategory":"Non-profit Organization",
            "type":"Services"
        }
    ],
    "sg:phone":"+1 512 385 3660",
    "sg:postcode":"78702",
    "sg:province":"TX",
    "wof:name":"Believe In Me Project Inc",
    "wof:placetype":"venue"
},
  "geometry": {"coordinates":[-97.73361199999999,30.260241],"type":"Point"}
}