{
  "type": "Feature",
  "properties": {
    "iso:country":"US",
    "sg:address":"510 W Railroad St",
    "sg:city":"El Campo",
    "sg:classifiers":[
        {
            "category":"Mining & Drilling",
            "type":"Manufacturing & Wholesale Goods"
        }
    ],
    "sg:phone":"+1 979 543 8281",
    "sg:postcode":"77437",
    "sg:province":"TX",
    "sg:tags":[
        "field",
        "oil"
    ],
    "wof:name":"Wildcat Oilfield Svc Inc",
    "wof:placetype":"venue"
},
  "geometry": {"coordinates":[-96.276172,29.19058],"type":"Point"}
}