{
  "type": "Feature",
  "properties": {
    "iso:country":"US",
    "sg:address":"7918 Audubon Forest Dr",
    "sg:city":"Humble",
    "sg:classifiers":[
        {
            "category":"Freight",
            "type":"Transportation"
        }
    ],
    "sg:phone":"+1 281 441 8244",
    "sg:postcode":"77396",
    "sg:province":"TX",
    "sg:tags":[
        "operator",
        "local",
        "trucking"
    ],
    "wof:name":"R Garcia & Sons Trucking",
    "wof:placetype":"venue"
},
  "geometry": {"coordinates":[-95.268455,29.941937],"type":"Point"}
}