{
  "type": "Feature",
  "properties": {
    "iso:country":"US",
    "sg:address":"14410 Telge Rd",
    "sg:city":"Cypress",
    "sg:classifiers":[
        {
            "category":"Retail",
            "subcategory":"Auto Repair",
            "type":"Services"
        }
    ],
    "sg:phone":"+1 281 256 0486",
    "sg:postcode":"77429",
    "sg:province":"TX",
    "sg:tags":[
        "general"
    ],
    "wof:name":"Cypress Automotive Services",
    "wof:placetype":"venue"
},
  "geometry": {"coordinates":[-95.654417,29.985687],"type":"Point"}
}