{
  "type": "Feature",
  "properties": {
    "iso:country":"US",
    "sg:address":"4600 N Josey Ln",
    "sg:city":"Carrollton",
    "sg:classifiers":[
        {
            "category":"Professional",
            "type":"Services"
        }
    ],
    "sg:phone":"+1 972 939 3440",
    "sg:postcode":"75010",
    "sg:province":"TX",
    "sg:tags":[
        "establishment"
    ],
    "wof:name":"Jones & Jones",
    "wof:placetype":"venue"
},
  "geometry": {"coordinates":[-96.88392399999999,33.036758],"type":"Point"}
}