{
  "type": "Feature",
  "properties": {
    "iso:country":"US",
    "sg:address":"2809 S 38th St",
    "sg:city":"Abilene",
    "sg:classifiers":[
        {
            "category":"Building & Trades",
            "subcategory":"Electrical",
            "type":"Services"
        }
    ],
    "sg:phone":"+1 325 672 1073",
    "sg:postcode":"79605",
    "sg:province":"TX",
    "sg:tags":[
        "electric",
        "contractor"
    ],
    "wof:name":"Aztec Electric",
    "wof:placetype":"venue"
},
  "geometry": {"coordinates":[-99.756011,32.406144],"type":"Point"}
}