{
  "type": "Feature",
  "properties": {
    "iso:country":"US",
    "sg:address":"3316 de Soto St",
    "sg:city":"Houston",
    "sg:classifiers":[
        {
            "category":"Recreation",
            "type":"Entertainment"
        }
    ],
    "sg:phone":"+1 713 956 9137",
    "sg:postcode":"77091",
    "sg:province":"TX",
    "sg:tags":[
        "hall",
        "auditorium"
    ],
    "wof:name":"Highland Community Ctr",
    "wof:placetype":"venue"
},
  "geometry": {"coordinates":[-95.45658400000001,29.85454],"type":"Point"}
}