{
  "type": "Feature",
  "properties": {
    "iso:country":"US",
    "sg:address":"3419 Edgecreek Dr",
    "sg:city":"Houston",
    "sg:classifiers":[
        {
            "category":"Retail",
            "subcategory":"Repair Shop",
            "type":"Services"
        }
    ],
    "sg:phone":"+1 281 440 7978",
    "sg:postcode":"77066",
    "sg:province":"TX",
    "wof:name":"Taylor Precision Services Inc",
    "wof:placetype":"venue"
},
  "geometry": {"coordinates":[-95.47134800000001,29.943656],"type":"Point"}
}