{
  "type": "Feature",
  "properties": {
    "iso:country":"US",
    "sg:address":"1600 Promenade Center",
    "sg:city":"Richardson",
    "sg:classifiers":[
        {
            "category":"Building & Trades",
            "subcategory":"Electrical",
            "type":"Services"
        }
    ],
    "sg:phone":"+1 972 994 9291",
    "sg:postcode":"75080",
    "sg:province":"TX",
    "sg:tags":[
        "electrical",
        "contractor"
    ],
    "wof:name":"Winer Electric",
    "wof:placetype":"venue"
},
  "geometry": {"coordinates":[-96.76829499999999,32.959547],"type":"Point"}
}