{
  "type": "Feature",
  "properties": {
    "iso:country":"US",
    "sg:address":"1021 N Texas Blvd",
    "sg:city":"Weslaco",
    "sg:classifiers":[
        {
            "category":"Shopping",
            "subcategory":"Department Store",
            "type":"Retail Goods"
        }
    ],
    "sg:phone":"+1 956 968 0556",
    "sg:postcode":"78596",
    "sg:province":"TX",
    "sg:tags":[
        "shop"
    ],
    "wof:name":"Revco Discount Drug Ctr",
    "wof:placetype":"venue"
},
  "geometry": {"coordinates":[-97.991044,26.172451],"type":"Point"}
}