{
  "type": "Feature",
  "properties": {
    "iso:country":"US",
    "sg:address":"1011 Silver Knoll",
    "sg:city":"San Antonio",
    "sg:classifiers":[
        {
            "category":"Real Estate",
            "subcategory":"Real Estate Agent",
            "type":"Services"
        }
    ],
    "sg:phone":"+1 210 496 5776",
    "sg:postcode":"78258",
    "sg:province":"TX",
    "sg:tags":[
        "appraiser"
    ],
    "wof:name":"Services Appraisal",
    "wof:placetype":"venue"
},
  "geometry": {"coordinates":[-98.486903,29.629506],"type":"Point"}
}