{
  "type": "Feature",
  "properties": {
    "iso:country":"US",
    "sg:address":"409 E State Road 114",
    "sg:city":"Levelland",
    "sg:classifiers":[
        {
            "category":"Restaurant",
            "type":"Food & Drink"
        }
    ],
    "sg:phone":"+1 806 894 1762",
    "sg:postcode":"79336",
    "sg:province":"TX",
    "sg:tags":[
        "house",
        "japanese",
        "asian",
        "steak",
        "pan"
    ],
    "wof:name":"Ohana Japanese Steak House",
    "wof:placetype":"venue"
},
  "geometry": {"coordinates":[-102.36065600000001,33.593882],"type":"Point"}
}