{
  "type": "Feature",
  "properties": {
    "iso:country":"US",
    "sg:address":"1016 W Primrose Dr",
    "sg:city":"Pharr",
    "sg:classifiers":[
        {
            "category":"Farming",
            "subcategory":"Livestock Farm",
            "type":"Manufacturing & Wholesale Goods"
        }
    ],
    "sg:phone":"+1 956 782 4123",
    "sg:postcode":"78577",
    "sg:province":"TX",
    "sg:tags":[
        "specialty",
        "animal"
    ],
    "wof:name":"Amelia Johnson",
    "wof:placetype":"venue"
},
  "geometry": {"coordinates":[-98.19530899999999,26.220573],"type":"Point"}
}