{
  "type": "Feature",
  "properties": {
    "iso:country":"US",
    "sg:address":"1723 N I-35",
    "sg:city":"Round Rock",
    "sg:classifiers":[
        {
            "category":"Bakery",
            "type":"Food & Drink"
        }
    ],
    "sg:menulink":"http://www.allmenus.com/tx/georgetown-round-rock/147272-sirloin-stockade/menu/",
    "sg:phone":"+1 512 218 8600",
    "sg:postcode":"78664",
    "sg:province":"TX",
    "sg:tags":[
        "american",
        "steakhouse",
        "pastry"
    ],
    "wof:name":"Sirloin Stockade",
    "wof:placetype":"venue"
},
  "geometry": {"coordinates":[-97.67813599999999,30.494633],"type":"Point"}
}