{
  "type": "Feature",
  "properties": {
    "iso:country":"US",
    "sg:address":"4213 Benbrook Hwy",
    "sg:city":"Benbrook",
    "sg:classifiers":[
        {
            "category":"Wholesale",
            "subcategory":"Apparel",
            "type":"Manufacturing & Wholesale Goods"
        }
    ],
    "sg:phone":"+1 817 569 8230",
    "sg:postcode":"76116",
    "sg:province":"TX",
    "wof:name":"Brush Strokes",
    "wof:placetype":"venue"
},
  "geometry": {"coordinates":[-97.447788,32.708771],"type":"Point"}
}