{
  "type": "Feature",
  "properties": {
    "iso:country":"US",
    "sg:address":"401 Simonton St",
    "sg:city":"Conroe",
    "sg:classifiers":[
        {
            "category":"Government",
            "subcategory":"Police Station",
            "type":"Public Place"
        }
    ],
    "sg:phone":"+1 936 760 4667",
    "sg:postcode":"77301",
    "sg:province":"TX",
    "sg:tags":[
        "department"
    ],
    "wof:name":"City Criminal Investigations",
    "wof:placetype":"venue"
},
  "geometry": {"coordinates":[-95.45919000000001,30.311297],"type":"Point"}
}