{
  "type": "Feature",
  "properties": {
    "iso:country":"US",
    "sg:address":"1113 N Natchez Dr",
    "sg:city":"Texas City",
    "sg:classifiers":[
        {
            "category":"Social Services",
            "subcategory":"Child Care",
            "type":"Services"
        }
    ],
    "sg:phone":"+1 409 938 8803",
    "sg:postcode":"77591",
    "sg:province":"TX",
    "wof:name":"Trudys Child Care",
    "wof:placetype":"venue"
},
  "geometry": {"coordinates":[-95.006152,29.395672],"type":"Point"}
}