{
  "type": "Feature",
  "properties": {
    "iso:country":"US",
    "sg:address":"1925 N Grand Ave",
    "sg:city":"Gainesville",
    "sg:classifiers":[
        {
            "category":"Health Services",
            "subcategory":"Doctor",
            "type":"Services"
        }
    ],
    "sg:phone":"+1 940 665 0741",
    "sg:postcode":"76240",
    "sg:province":"TX",
    "sg:tags":[
        "physician",
        "surgeon"
    ],
    "wof:name":"Medical & Surgical Eye Assoc",
    "wof:placetype":"venue"
},
  "geometry": {"coordinates":[-97.13341,33.642922],"type":"Point"}
}