{
  "type": "Feature",
  "properties": {
    "iso:country":"US",
    "sg:address":"1710 Strawberry Rd",
    "sg:city":"Pasadena",
    "sg:classifiers":[
        {
            "category":"Professional",
            "subcategory":"Business Services",
            "type":"Services"
        }
    ],
    "sg:phone":"+1 713 473 2814",
    "sg:postcode":"77502",
    "sg:province":"TX",
    "sg:tags":[
        "recording",
        "studio"
    ],
    "wof:name":"Believers Recording Studio",
    "wof:placetype":"venue"
},
  "geometry": {"coordinates":[-95.19326599999999,29.686231],"type":"Point"}
}