{
  "type": "Feature",
  "properties": {
    "iso:country":"US",
    "sg:address":"9300 United Dr",
    "sg:city":"Austin",
    "sg:classifiers":[
        {
            "category":"Manufacturing",
            "subcategory":"Petroleum Products",
            "type":"Manufacturing & Wholesale Goods"
        }
    ],
    "sg:phone":"+1 512 637 3000",
    "sg:postcode":"78758",
    "sg:province":"TX",
    "sg:tags":[
        "oils-fuel-wholesale",
        "manufacturer"
    ],
    "wof:name":"Profitfuel Inc",
    "wof:placetype":"venue"
},
  "geometry": {"coordinates":[-97.730142,30.378365],"type":"Point"}
}