{
  "type": "Feature",
  "properties": {
    "iso:country":"US",
    "sg:address":"27350 Blueberry Hill Dr",
    "sg:city":"Conroe",
    "sg:classifiers":[
        {
            "category":"Shopping",
            "subcategory":"Computers & Home Electronics",
            "type":"Retail Goods"
        }
    ],
    "sg:phone":"+1 281 292 1737",
    "sg:postcode":"77385",
    "sg:province":"TX",
    "sg:tags":[
        "equipment",
        "electronic",
        "supply"
    ],
    "wof:name":"Best Buy",
    "wof:placetype":"venue"
},
  "geometry": {"coordinates":[-95.44022,30.164295],"type":"Point"}
}