{
  "type": "Feature",
  "properties": {
    "iso:country":"US",
    "sg:address":"4655 W Cardinal Dr",
    "sg:city":"Beaumont",
    "sg:classifiers":[
        {
            "category":"Food & Beverages",
            "subcategory":"Groceries & Convenience Stores",
            "type":"Retail Goods"
        }
    ],
    "sg:phone":"+1 409 842 2225",
    "sg:postcode":"77705",
    "sg:province":"TX",
    "wof:name":"Gators",
    "wof:placetype":"venue"
},
  "geometry": {"coordinates":[-94.13368,30.04256],"type":"Point"}
}