{
  "type": "Feature",
  "properties": {
    "iso:country":"US",
    "sg:address":"2400 S 4th St",
    "sg:city":"Austin",
    "sg:classifiers":[
        {
            "category":"Communications",
            "type":"Services"
        }
    ],
    "sg:phone":"+1 512 804 0033",
    "sg:postcode":"78704",
    "sg:province":"TX",
    "wof:name":"Aldrete Communications",
    "wof:placetype":"venue"
},
  "geometry": {"coordinates":[-97.76343799999999,30.242592],"type":"Point"}
}