{
  "type": "Feature",
  "properties": {
    "iso:country":"US",
    "sg:address":"2281 Heatherdale Dr",
    "sg:city":"Mesquite",
    "sg:classifiers":[
        {
            "category":"Shopping",
            "subcategory":"Hobbies, Toys, & Games",
            "type":"Retail Goods"
        }
    ],
    "sg:phone":"+1 972 682 5050",
    "sg:postcode":"75150",
    "sg:province":"TX",
    "sg:tags":[
        "craft"
    ],
    "wof:name":"Ceramic Fun",
    "wof:placetype":"venue"
},
  "geometry": {"coordinates":[-96.60304499999999,32.795313],"type":"Point"}
}