{
  "type": "Feature",
  "properties": {
    "iso:country":"US",
    "sg:address":"5314 el Tejano St",
    "sg:city":"San Antonio",
    "sg:classifiers":[
        {
            "category":"Restaurant",
            "type":"Food & Drink"
        }
    ],
    "sg:phone":"+1 210 656 1782",
    "sg:postcode":"78233",
    "sg:province":"TX",
    "sg:tags":[
        "eating"
    ],
    "wof:name":"Reigning Cats & Dogs",
    "wof:placetype":"venue"
},
  "geometry": {"coordinates":[-98.38458199999999,29.552102],"type":"Point"}
}