{
  "type": "Feature",
  "properties": {
    "iso:country":"US",
    "sg:address":"135 Lagos Ave",
    "sg:city":"Laredo",
    "sg:classifiers":[
        {
            "category":"Shopping",
            "subcategory":"Jewelry",
            "type":"Retail Goods"
        }
    ],
    "sg:phone":"+1 956 717 3212",
    "sg:postcode":"78045",
    "sg:province":"TX",
    "sg:tags":[
        "platinum",
        "silver",
        "gold"
    ],
    "wof:name":"Mayra's Silver",
    "wof:placetype":"venue"
},
  "geometry": {"coordinates":[-99.483092,27.578036],"type":"Point"}
}