{
  "type": "Feature",
  "properties": {
    "iso:country":"US",
    "sg:address":"104 N Memorial Fwy",
    "sg:city":"Nederland",
    "sg:classifiers":[
        {
            "category":"Food & Beverages",
            "subcategory":"Groceries & Convenience Stores",
            "type":"Retail Goods"
        }
    ],
    "sg:phone":"+1 409 721 5188",
    "sg:postcode":"77627",
    "sg:province":"TX",
    "wof:name":"Fastlane 12",
    "wof:placetype":"venue"
},
  "geometry": {"coordinates":[-94.00917800000001,29.956431],"type":"Point"}
}