{
  "type": "Feature",
  "properties": {
    "iso:country":"US",
    "sg:address":"119 Commerce St",
    "sg:city":"Mineola",
    "sg:classifiers":[
        {
            "category":"Shopping",
            "subcategory":"Gifts & Souvenirs",
            "type":"Retail Goods"
        }
    ],
    "sg:phone":"+1 903 569 3566",
    "sg:postcode":"75773",
    "sg:province":"TX",
    "sg:tags":[
        "shop"
    ],
    "wof:name":"Tis The Seasons",
    "wof:placetype":"venue"
},
  "geometry": {"coordinates":[-95.490409,32.662926],"type":"Point"}
}