{
  "type": "Feature",
  "properties": {
    "iso:country":"US",
    "sg:address":"13466 N Highway 183",
    "sg:city":"Austin",
    "sg:classifiers":[
        {
            "category":"Autos & Motor Vehicles",
            "subcategory":"Fuel & Gas Station",
            "type":"Retail Goods"
        }
    ],
    "sg:phone":"+1 512 258 9722",
    "sg:postcode":"78750",
    "sg:province":"TX",
    "wof:name":"Chevron Stations Inc",
    "wof:placetype":"venue"
},
  "geometry": {"coordinates":[-97.790497,30.4485],"type":"Point"}
}