{
  "type": "Feature",
  "properties": {
    "iso:country":"US",
    "sg:address":"41 Tidwell Rd",
    "sg:city":"Houston",
    "sg:classifiers":[
        {
            "category":"Building & Trades",
            "subcategory":"Electrical",
            "type":"Services"
        }
    ],
    "sg:phone":"+1 281 642 8169",
    "sg:postcode":"77022",
    "sg:province":"TX",
    "sg:tags":[
        "energy",
        "electrical",
        "solar"
    ],
    "wof:name":"Solar One Electrical Cnstr",
    "wof:placetype":"venue"
},
  "geometry": {"coordinates":[-95.380154,29.84564],"type":"Point"}
}