{
  "type": "Feature",
  "properties": {
    "iso:country":"US",
    "sg:address":"1012 W Hebron Pkwy Ste 126",
    "sg:city":"Carrollton",
    "sg:classifiers":[
        {
            "category":"Personal",
            "subcategory":"Nail Salon",
            "type":"Services"
        }
    ],
    "sg:phone":"+1 972 394 4424",
    "sg:postcode":"75010",
    "sg:province":"TX",
    "wof:name":"Nails Nails",
    "wof:placetype":"venue"
},
  "geometry": {"coordinates":[-96.916496,33.020699],"type":"Point"}
}