{
  "type": "Feature",
  "properties": {
    "iso:country":"US",
    "sg:address":"540 Annapolis Dr",
    "sg:city":"White Settlement",
    "sg:classifiers":[
        {
            "category":"Professional",
            "type":"Services"
        }
    ],
    "sg:phone":"+1 817 246 1724",
    "sg:postcode":"76108",
    "sg:province":"TX",
    "sg:tags":[
        "editorial"
    ],
    "wof:name":"Patterson Editorial Svc",
    "wof:placetype":"venue"
},
  "geometry": {"coordinates":[-97.492833,32.75118],"type":"Point"}
}