{
  "type": "Feature",
  "properties": {
    "iso:country":"US",
    "sg:address":"1625 Sawdust Rd",
    "sg:city":"Spring",
    "sg:classifiers":[
        {
            "category":"Social Services",
            "subcategory":"Child Care",
            "type":"Services"
        }
    ],
    "sg:phone":"+1 281 367 3553",
    "sg:postcode":"77380",
    "sg:province":"TX",
    "sg:tags":[
        "day"
    ],
    "wof:name":"Dogs Day Out",
    "wof:placetype":"venue"
},
  "geometry": {"coordinates":[-95.47031699999999,30.126168],"type":"Point"}
}