{
  "type": "Feature",
  "properties": {
    "iso:country":"US",
    "sg:address":"202 N Judkins Dr",
    "sg:city":"Odessa",
    "sg:classifiers":[
        {
            "category":"Building & Trades",
            "subcategory":"Landscaping Services",
            "type":"Services"
        }
    ],
    "sg:phone":"+1 432 332 4906",
    "sg:postcode":"79764",
    "sg:province":"TX",
    "sg:tags":[
        "tree"
    ],
    "wof:name":"Tommy's Liqui-Feed System",
    "wof:placetype":"venue"
},
  "geometry": {"coordinates":[-102.38418799999999,31.869615],"type":"Point"}
}