{
  "type": "Feature",
  "properties": {
    "iso:country":"US",
    "sg:address":"440 N Watson Rd",
    "sg:city":"Arlington",
    "sg:classifiers":[
        {
            "category":"Home & Garden",
            "subcategory":"Building Materials",
            "type":"Retail Goods"
        },
        {
            "category":"Wholesale",
            "subcategory":"Hardware",
            "type":"Manufacturing & Wholesale Goods"
        }
    ],
    "sg:phone":"+1 817 640 4343",
    "sg:postcode":"76011",
    "sg:province":"TX",
    "sg:tags":[
        "plumbing",
        "industrial",
        "fixture",
        "supply"
    ],
    "wof:name":"Apex Supply Company",
    "wof:placetype":"venue"
},
  "geometry": {"coordinates":[-97.062094,32.746901],"type":"Point"}
}