{
  "type": "Feature",
  "properties": {
    "iso:country":"US",
    "sg:address":"7210 River Garden Dr",
    "sg:city":"Houston",
    "sg:classifiers":[
        {
            "category":"Banks & Credit Unions",
            "subcategory":"Bank",
            "type":"Services"
        }
    ],
    "sg:phone":"+1 281 855 2103",
    "sg:postcode":"77095",
    "sg:province":"TX",
    "sg:tags":[
        "personal",
        "institution"
    ],
    "wof:name":"Parker Misty",
    "wof:placetype":"venue"
},
  "geometry": {"coordinates":[-95.64718999999999,29.882917],"type":"Point"}
}