{
  "type": "Feature",
  "properties": {
    "iso:country":"US",
    "sg:address":"1921 Cedar Bend Dr",
    "sg:city":"Austin",
    "sg:classifiers":[
        {
            "category":"Government",
            "subcategory":"Office",
            "type":"Public Place"
        }
    ],
    "sg:phone":"+1 512 458 7111",
    "sg:postcode":"78758",
    "sg:province":"TX",
    "sg:tags":[
        "state",
        "program",
        "health"
    ],
    "wof:name":"Health Dept",
    "wof:placetype":"venue"
},
  "geometry": {"coordinates":[-97.698273,30.408496],"type":"Point"}
}