{
  "type": "Feature",
  "properties": {
    "iso:country":"US",
    "sg:address":"7708 San Felipe Blvd # 39",
    "sg:city":"Austin",
    "sg:classifiers":[
        {
            "category":"Professional",
            "type":"Services"
        }
    ],
    "sg:phone":"+1 512 330 4737",
    "sg:postcode":"78729",
    "sg:province":"TX",
    "sg:tags":[
        "motion",
        "technician",
        "picture"
    ],
    "wof:name":"Curveball Films",
    "wof:placetype":"venue"
},
  "geometry": {"coordinates":[-97.767504,30.43644],"type":"Point"}
}