{
  "type": "Feature",
  "properties": {
    "iso:country":"US",
    "sg:address":"1102 Briarbrook Dr",
    "sg:city":"Houston",
    "sg:classifiers":[
        {
            "category":"Wholesale",
            "subcategory":"Apparel",
            "type":"Manufacturing & Wholesale Goods"
        }
    ],
    "sg:phone":"+1 713 782 1154",
    "sg:postcode":"77042",
    "sg:province":"TX",
    "sg:tags":[
        "shoes-wholesale",
        "manufacturer"
    ],
    "wof:name":"Bitsis Enterprises Incorporated",
    "wof:placetype":"venue"
},
  "geometry": {"coordinates":[-95.551689,29.750883],"type":"Point"}
}