{
  "type": "Feature",
  "properties": {
    "iso:country":"US",
    "sg:address":"7328 Williamswood Dr",
    "sg:city":"Dallas",
    "sg:classifiers":[
        {
            "category":"Professional",
            "subcategory":"Business Services",
            "type":"Services"
        }
    ],
    "sg:phone":"+1 972 248 0423",
    "sg:postcode":"75252",
    "sg:province":"TX",
    "wof:name":"Cherished Creat By Lucy Bellew",
    "wof:placetype":"venue"
},
  "geometry": {"coordinates":[-96.778396,32.995787],"type":"Point"}
}