{
  "type": "Feature",
  "properties": {
    "iso:country":"US",
    "sg:address":"3355 Bee Caves Rd",
    "sg:city":"West Lake Hills",
    "sg:classifiers":[
        {
            "category":"Community Center",
            "type":"Public Place"
        }
    ],
    "sg:phone":"+1 512 306 1300",
    "sg:postcode":"78746",
    "sg:province":"TX",
    "sg:tags":[
        "medical"
    ],
    "sg:website":"www.sourcewellnesscenter.com",
    "wof:name":"New Beginnings Wellness Center",
    "wof:placetype":"venue"
},
  "geometry": {"coordinates":[-97.80191000000001,30.275421],"type":"Point"}
}