{
  "type": "Feature",
  "properties": {
    "iso:country":"US",
    "sg:address":"250 S Expressway 83",
    "sg:city":"Brownsville",
    "sg:classifiers":[
        {
            "category":"Wholesale",
            "subcategory":"Machinery & Supplies",
            "type":"Manufacturing & Wholesale Goods"
        }
    ],
    "sg:phone":"+1 956 541 9449",
    "sg:postcode":"78520",
    "sg:province":"TX",
    "sg:tags":[
        "industrial",
        "equipment",
        "used",
        "machinery-new",
        "supplies-wholesale"
    ],
    "wof:name":"Mexico Industrial Supply",
    "wof:placetype":"venue"
},
  "geometry": {"coordinates":[-97.49105,25.921752],"type":"Point"}
}