{
  "type": "Feature",
  "properties": {
    "iso:country":"US",
    "sg:address":"6436 Ridglea Dr",
    "sg:city":"Fort Worth",
    "sg:classifiers":[
        {
            "category":"Professional",
            "subcategory":"Computer Services",
            "type":"Services"
        }
    ],
    "sg:phone":"+1 817 428 8322",
    "sg:postcode":"76148",
    "sg:province":"TX",
    "sg:tags":[
        "prepackaged",
        "software"
    ],
    "wof:name":"Software Services",
    "wof:placetype":"venue"
},
  "geometry": {"coordinates":[-97.246346,32.882877],"type":"Point"}
}