{
  "type": "Feature",
  "properties": {
    "iso:country":"US",
    "sg:address":"10135 Metropolitan Dr",
    "sg:city":"Austin",
    "sg:classifiers":[
        {
            "category":"Manufacturing",
            "subcategory":"Glass & Minerals",
            "type":"Manufacturing & Wholesale Goods"
        }
    ],
    "sg:phone":"+1 512 928 8000",
    "sg:postcode":"78758",
    "sg:province":"TX",
    "sg:tags":[
        "concrete",
        "brick",
        "prod",
        "block"
    ],
    "wof:name":"Sundek Of Austin",
    "wof:placetype":"venue"
},
  "geometry": {"coordinates":[-97.71728400000001,30.384176],"type":"Point"}
}