{
  "type": "Feature",
  "properties": {
    "iso:country":"US",
    "sg:address":"11410 Spring Cypress Rd",
    "sg:city":"Tomball",
    "sg:classifiers":[
        {
            "category":"Manufacturing",
            "subcategory":"Tools & Machinery",
            "type":"Manufacturing & Wholesale Goods"
        }
    ],
    "sg:phone":"+1 281 376 5494",
    "sg:postcode":"77377",
    "sg:province":"TX",
    "sg:tags":[
        "field",
        "mfg"
    ],
    "wof:name":"Drilling & Oil Technology",
    "wof:placetype":"venue"
},
  "geometry": {"coordinates":[-95.603461,30.012878],"type":"Point"}
}