{
  "type": "Feature",
  "properties": {
    "iso:country":"US",
    "sg:address":"15210 FM 529",
    "sg:city":"Houston",
    "sg:classifiers":[
        {
            "category":"Building & Trades",
            "subcategory":"Equipment Rental",
            "type":"Services"
        }
    ],
    "sg:phone":"+1 281 859 9766",
    "sg:postcode":"77095",
    "sg:province":"TX",
    "sg:tags":[
        "heavy",
        "construction"
    ],
    "wof:name":"RSC 751",
    "wof:placetype":"venue"
},
  "geometry": {"coordinates":[-95.63896,29.879335],"type":"Point"}
}