{
  "type": "Feature",
  "properties": {
    "iso:country":"US",
    "sg:address":"4701 San Dario Ave",
    "sg:city":"Laredo",
    "sg:classifiers":[
        {
            "category":"Shopping",
            "subcategory":"Department Store",
            "type":"Retail Goods"
        }
    ],
    "sg:phone":"+1 956 725 0752",
    "sg:postcode":"78041",
    "sg:province":"TX",
    "wof:name":"Factory 2 U",
    "wof:placetype":"venue"
},
  "geometry": {"coordinates":[-99.502487,27.53193],"type":"Point"}
}