{
  "type": "Feature",
  "properties": {
    "iso:country":"US",
    "sg:address":"5909 Co Rd 440",
    "sg:city":"Bellaire",
    "sg:classifiers":[
        {
            "category":"Real Estate",
            "subcategory":"Architect",
            "type":"Services"
        }
    ],
    "sg:phone":"+1 713 669 8005",
    "sg:postcode":"77480",
    "sg:province":"TX",
    "wof:name":"CEH Architect",
    "wof:placetype":"venue"
},
  "geometry": {"coordinates":[-95.719223,29.122212],"type":"Point"}
}