{
  "type": "Feature",
  "properties": {
    "iso:country":"US",
    "sg:address":"2725 Keystone Dr",
    "sg:city":"Odessa",
    "sg:classifiers":[
        {
            "category":"Shopping",
            "subcategory":"Gifts & Souvenirs",
            "type":"Retail Goods"
        }
    ],
    "sg:phone":"+1 432 363 3597",
    "sg:postcode":"79762",
    "sg:province":"TX",
    "wof:name":"Armidas Ceramics",
    "wof:placetype":"venue"
},
  "geometry": {"coordinates":[-102.36738099999999,31.871398],"type":"Point"}
}