{
  "type": "Feature",
  "properties": {
    "iso:country":"US",
    "sg:address":"421 W Pioneer Pkwy",
    "sg:city":"Grand Prairie",
    "sg:classifiers":[
        {
            "category":"Restaurant",
            "type":"Food & Drink"
        }
    ],
    "sg:menulink":"http://www.allmenus.com/tx/southwest/157190-whataburger/menu/",
    "sg:phone":"+1 972 642 8427",
    "sg:postcode":"75051",
    "sg:province":"TX",
    "sg:tags":[
        "burger",
        "american"
    ],
    "wof:name":"Whataburger",
    "wof:placetype":"venue"
},
  "geometry": {"coordinates":[-97.00745000000001,32.709399],"type":"Point"}
}