{
  "type": "Feature",
  "properties": {
    "iso:country":"US",
    "sg:address":"231 W Commerce St",
    "sg:city":"San Antonio",
    "sg:classifiers":[
        {
            "category":"Organizations",
            "subcategory":"Religious Organization",
            "type":"Services"
        }
    ],
    "sg:phone":"+1 210 223 6192",
    "sg:postcode":"78205",
    "sg:province":"TX",
    "sg:tags":[
        "church"
    ],
    "sg:website":"www.sfcathedral.org",
    "wof:name":"San Fernando Cathedral",
    "wof:placetype":"venue"
},
  "geometry": {"coordinates":[-98.496013,29.42522],"type":"Point"}
}