{
  "type": "Feature",
  "properties": {
    "iso:country":"US",
    "sg:address":"3735 Westheimer Rd",
    "sg:city":"Houston",
    "sg:classifiers":[
        {
            "category":"Building & Trades",
            "subcategory":"Cleaning & Sanitation",
            "type":"Services"
        }
    ],
    "sg:phone":"+1 713 850 0555",
    "sg:postcode":"77027",
    "sg:province":"TX",
    "sg:tags":[
        "carpet"
    ],
    "wof:name":"Craig's Biohazard Solutions",
    "wof:placetype":"venue"
},
  "geometry": {"coordinates":[-95.44000200000001,29.7416],"type":"Point"}
}