{
  "type": "Feature",
  "properties": {
    "iso:country":"US",
    "sg:address":"1001 Douglas Rd",
    "sg:city":"Athens",
    "sg:classifiers":[
        {
            "category":"Home & Garden",
            "subcategory":"Garden Supply",
            "type":"Retail Goods"
        }
    ],
    "sg:phone":"+1 903 675 1578",
    "sg:postcode":"75751",
    "sg:province":"TX",
    "wof:name":"Howdy Acres Christmas Trees",
    "wof:placetype":"venue"
},
  "geometry": {"coordinates":[-95.87420899999999,32.179229],"type":"Point"}
}