{
  "type": "Feature",
  "properties": {
    "iso:country":"US",
    "sg:address":"2121 E Van Buren Ave",
    "sg:city":"Harlingen",
    "sg:classifiers":[
        {
            "category":"Building & Trades",
            "subcategory":"Landscaping Services",
            "type":"Services"
        }
    ],
    "sg:phone":"+1 956 421 1091",
    "sg:postcode":"78550",
    "sg:province":"TX",
    "wof:name":"Tonys Lawn Service",
    "wof:placetype":"venue"
},
  "geometry": {"coordinates":[-97.670198,26.191724],"type":"Point"}
}