{
  "type": "Feature",
  "properties": {
    "iso:country":"US",
    "sg:address":"104 N 3rd St",
    "sg:city":"Lufkin",
    "sg:classifiers":[
        {
            "category":"Manufacturing",
            "subcategory":"Tools & Machinery",
            "type":"Manufacturing & Wholesale Goods"
        }
    ],
    "sg:phone":"+1 936 632 6112",
    "sg:postcode":"75901",
    "sg:province":"TX",
    "sg:tags":[
        "building",
        "equipment",
        "construction"
    ],
    "wof:name":"Ww Contractors Inc",
    "wof:placetype":"venue"
},
  "geometry": {"coordinates":[-94.726613,31.338454],"type":"Point"}
}