{
  "type": "Feature",
  "properties": {
    "iso:country":"US",
    "sg:address":"1934 Chandler Pl",
    "sg:city":"Ingleside",
    "sg:classifiers":[
        {
            "category":"Shopping",
            "subcategory":"Used Merchandise",
            "type":"Retail Goods"
        }
    ],
    "sg:phone":"+1 361 775 2043",
    "sg:postcode":"78362",
    "sg:province":"TX",
    "wof:name":"Julie Anns Persians & More",
    "wof:placetype":"venue"
},
  "geometry": {"coordinates":[-97.19865900000001,27.869264],"type":"Point"}
}