{
  "type": "Feature",
  "properties": {
    "iso:country":"US",
    "sg:address":"245 S Mahon Ave",
    "sg:city":"Tyler",
    "sg:classifiers":[
        {
            "category":"Food & Beverages",
            "subcategory":"Meat & Fish",
            "type":"Retail Goods"
        }
    ],
    "sg:phone":"+1 903 597 2071",
    "sg:postcode":"75702",
    "sg:province":"TX",
    "wof:name":"A & B Food Store",
    "wof:placetype":"venue"
},
  "geometry": {"coordinates":[-95.282285,32.348566],"type":"Point"}
}