{
  "type": "Feature",
  "properties": {
    "iso:country":"US",
    "sg:address":"901 24th St",
    "sg:city":"Hondo",
    "sg:classifiers":[
        {
            "category":"Building & Trades",
            "subcategory":"Construction",
            "type":"Services"
        }
    ],
    "sg:phone":"+1 830 741 7070",
    "sg:postcode":"78861",
    "sg:province":"TX",
    "sg:tags":[
        "painter"
    ],
    "wof:name":"Concept Painting & Home Repair",
    "wof:placetype":"venue"
},
  "geometry": {"coordinates":[-99.137896,29.343166],"type":"Point"}
}