{
  "type": "Feature",
  "properties": {
    "iso:country":"US",
    "sg:address":"4145 N 1st St",
    "sg:city":"Abilene",
    "sg:classifiers":[
        {
            "category":"Organizations",
            "subcategory":"Professional Association",
            "type":"Services"
        }
    ],
    "sg:phone":"+1 325 672 7950",
    "sg:postcode":"79603",
    "sg:province":"TX",
    "sg:tags":[
        "chambers",
        "commerce"
    ],
    "wof:name":"Abilene Black Chamber",
    "wof:placetype":"venue"
},
  "geometry": {"coordinates":[-99.777619,32.452735],"type":"Point"}
}