{
  "type": "Feature",
  "properties": {
    "iso:country":"US",
    "sg:address":"215 N 1st Ave",
    "sg:city":"Crystal City",
    "sg:classifiers":[
        {
            "category":"Professional",
            "type":"Services"
        }
    ],
    "sg:phone":"+1 830 374 3218",
    "sg:postcode":"78839",
    "sg:province":"TX",
    "sg:tags":[
        "establishment"
    ],
    "wof:name":"Border Abstract & Title Co Inc",
    "wof:placetype":"venue"
},
  "geometry": {"coordinates":[-99.827719,28.679659],"type":"Point"}
}