{
  "type": "Feature",
  "properties": {
    "iso:country":"US",
    "sg:address":"2520 Hazard St",
    "sg:city":"Houston",
    "sg:classifiers":[
        {
            "category":"Real Estate",
            "subcategory":"Real Estate Agent",
            "type":"Services"
        }
    ],
    "sg:phone":"+1 713 526 5932",
    "sg:postcode":"77019",
    "sg:province":"TX",
    "wof:name":"D & C Properties",
    "wof:placetype":"venue"
},
  "geometry": {"coordinates":[-95.407144,29.743935],"type":"Point"}
}