{
  "type": "Feature",
  "properties": {
    "iso:country":"US",
    "sg:address":"6313 N 23rd St",
    "sg:city":"Mcallen",
    "sg:classifiers":[
        {
            "category":"Food & Beverages",
            "subcategory":"Groceries & Convenience Stores",
            "type":"Retail Goods"
        }
    ],
    "sg:phone":"+1 956 668 1824",
    "sg:postcode":"78504",
    "sg:province":"TX",
    "wof:name":"Tiger Mart Exxon",
    "wof:placetype":"venue"
},
  "geometry": {"coordinates":[-98.23633100000001,26.258961],"type":"Point"}
}