{
  "type": "Feature",
  "properties": {
    "iso:country":"US",
    "sg:address":"3275 Martin Luther King Rd",
    "sg:city":"Beaumont",
    "sg:classifiers":[
        {
            "category":"Home & Garden",
            "subcategory":"Hardware",
            "type":"Retail Goods"
        }
    ],
    "sg:phone":"+1 409 832 1414",
    "sg:postcode":"77713",
    "sg:province":"TX",
    "sg:tags":[
        "tool",
        "used"
    ],
    "wof:name":"Value Warehouse",
    "wof:placetype":"venue"
},
  "geometry": {"coordinates":[-94.24665299999999,29.988249],"type":"Point"}
}