{
  "type": "Feature",
  "properties": {
    "iso:country":"US",
    "sg:address":"3417 Lynette Dr",
    "sg:city":"Amarillo",
    "sg:classifiers":[
        {
            "category":"Professional",
            "type":"Services"
        }
    ],
    "sg:phone":"+1 806 355 8473",
    "sg:postcode":"79109",
    "sg:province":"TX",
    "sg:tags":[
        "establishment"
    ],
    "wof:name":"Weiglerichard C",
    "wof:placetype":"venue"
},
  "geometry": {"coordinates":[-101.876166,35.176838],"type":"Point"}
}