{
  "type": "Feature",
  "properties": {
    "iso:country":"US",
    "sg:address":"4070 N Belt Line Rd",
    "sg:city":"Irving",
    "sg:classifiers":[
        {
            "category":"Manufacturing",
            "subcategory":"Signs",
            "type":"Manufacturing & Wholesale Goods"
        }
    ],
    "sg:phone":"+1 972 255 2022",
    "sg:postcode":"75038",
    "sg:province":"TX",
    "sg:website":"www.fastsigns.com",
    "wof:name":"Fastsigns",
    "wof:placetype":"venue"
},
  "geometry": {"coordinates":[-96.991625,32.864372],"type":"Point"}
}