{
  "type": "Feature",
  "properties": {
    "iso:country":"US",
    "sg:address":"204 Valleyglen Dr",
    "sg:city":"Desoto",
    "sg:classifiers":[
        {
            "category":"Social Services",
            "subcategory":"Child Care",
            "type":"Services"
        }
    ],
    "sg:phone":"+1 972 223 4167",
    "sg:postcode":"75115",
    "sg:province":"TX",
    "sg:tags":[
        "day"
    ],
    "wof:name":"Nana's Playland",
    "wof:placetype":"venue"
},
  "geometry": {"coordinates":[-96.852204,32.584259],"type":"Point"}
}