{
  "type": "Feature",
  "properties": {
    "iso:country":"US",
    "sg:address":"2704 Rio Grande St",
    "sg:city":"Austin",
    "sg:classifiers":[
        {
            "category":"Professional",
            "subcategory":"Business Services",
            "type":"Services"
        }
    ],
    "sg:phone":"+1 512 236 1903",
    "sg:postcode":"78705",
    "sg:province":"TX",
    "sg:tags":[
        "organizing",
        "services-household"
    ],
    "wof:name":"Dmc Management",
    "wof:placetype":"venue"
},
  "geometry": {"coordinates":[-97.74425599999999,30.292089],"type":"Point"}
}