{
  "type": "Feature",
  "properties": {
    "iso:country":"US",
    "sg:address":"301 N 15th St",
    "sg:city":"Canyon",
    "sg:classifiers":[
        {
            "category":"Personal",
            "subcategory":"Beauty Salon",
            "type":"Services"
        }
    ],
    "sg:phone":"+1 806 655 8477",
    "sg:postcode":"79015",
    "sg:province":"TX",
    "sg:tags":[
        "shop"
    ],
    "wof:name":"Tip To Toe",
    "wof:placetype":"venue"
},
  "geometry": {"coordinates":[-101.928738,34.987037],"type":"Point"}
}