{
  "type": "Feature",
  "properties": {
    "iso:country":"US",
    "sg:address":"121 W South St",
    "sg:city":"Uvalde",
    "sg:classifiers":[
        {
            "category":"Health Services",
            "subcategory":"Doctor",
            "type":"Services"
        }
    ],
    "sg:phone":"+1 830 278 6681",
    "sg:postcode":"78801",
    "sg:province":"TX",
    "sg:tags":[
        "physician",
        "surgeon"
    ],
    "wof:name":"Internal Medicine Clinic",
    "wof:placetype":"venue"
},
  "geometry": {"coordinates":[-99.786501,29.208648],"type":"Point"}
}