{
  "type": "Feature",
  "properties": {
    "iso:country":"US",
    "sg:address":"736 Teresa Dr",
    "sg:city":"De Soto",
    "sg:classifiers":[
        {
            "category":"Recreation",
            "type":"Entertainment"
        }
    ],
    "sg:phone":"+1 972 223 0837",
    "sg:postcode":"75115",
    "sg:province":"TX",
    "sg:tags":[
        "club",
        "membership"
    ],
    "wof:name":"Jjs Hunting Club Inc",
    "wof:placetype":"venue"
},
  "geometry": {"coordinates":[-96.840423,32.594837],"type":"Point"}
}