{
  "type": "Feature",
  "properties": {
    "iso:country":"US",
    "sg:address":"9303 Ponderosa Ln",
    "sg:city":"Houston",
    "sg:classifiers":[
        {
            "category":"Wholesale",
            "subcategory":"Machinery & Supplies",
            "type":"Manufacturing & Wholesale Goods"
        }
    ],
    "sg:phone":"+1 713 776 1212",
    "sg:postcode":"77074",
    "sg:province":"TX",
    "sg:tags":[
        "contractor"
    ],
    "wof:name":"Texas Contractors Equipment",
    "wof:placetype":"venue"
},
  "geometry": {"coordinates":[-95.539948,29.674917],"type":"Point"}
}