{
  "type": "Feature",
  "properties": {
    "iso:country":"US",
    "sg:address":"426 N Gilmer St",
    "sg:city":"Killeen",
    "sg:classifiers":[
        {
            "category":"Communications",
            "type":"Services"
        }
    ],
    "sg:phone":"+1 254 634 4525",
    "sg:postcode":"76541",
    "sg:province":"TX",
    "wof:name":"C & W Communications",
    "wof:placetype":"venue"
},
  "geometry": {"coordinates":[-97.736895,31.124501],"type":"Point"}
}