{
  "type": "Feature",
  "properties": {
    "iso:country":"US",
    "sg:address":"233 Linda Dr",
    "sg:city":"Sulphur Springs",
    "sg:classifiers":[
        {
            "category":"Building & Trades",
            "subcategory":"Construction",
            "type":"Services"
        }
    ],
    "sg:phone":"+1 903 439 0958",
    "sg:postcode":"75482",
    "sg:province":"TX",
    "sg:tags":[
        "television",
        "telephone",
        "cable",
        "contractor"
    ],
    "wof:name":"Housley Communications Inc",
    "wof:placetype":"venue"
},
  "geometry": {"coordinates":[-95.598758,33.122047],"type":"Point"}
}