{
  "type": "Feature",
  "properties": {
    "iso:country":"US",
    "sg:address":"3615 Willowbend Blvd Ste 428",
    "sg:city":"Houston",
    "sg:classifiers":[
        {
            "category":"Health Services",
            "subcategory":"Doctor",
            "type":"Services"
        }
    ],
    "sg:phone":"+1 713 218 7585",
    "sg:postcode":"77054",
    "sg:province":"TX",
    "sg:tags":[
        "orthopedist"
    ],
    "wof:name":"Pure Play Orthopedics",
    "wof:placetype":"venue"
},
  "geometry": {"coordinates":[-95.436031,29.663848],"type":"Point"}
}