{
  "type": "Feature",
  "properties": {
    "iso:country":"US",
    "sg:address":"3903 Kingsferry Dr",
    "sg:city":"Arlington",
    "sg:classifiers":[
        {
            "category":"Landmark",
            "subcategory":"Tourist Information",
            "type":"Public Place"
        },
        {
            "category":"Travel",
            "subcategory":"Travel Agent",
            "type":"Entertainment"
        },
        {
            "category":"Landmark",
            "subcategory":"Tourist Attraction",
            "type":"Public Place"
        }
    ],
    "sg:phone":"+1 817 563 7742",
    "sg:postcode":"76016",
    "sg:province":"TX",
    "sg:tags":[
        "agency",
        "services-commercial",
        "promoter",
        "tour",
        "tours-operators",
        "sightseeing"
    ],
    "wof:name":"Camelot Group Tours & Travel",
    "wof:placetype":"venue"
},
  "geometry": {"coordinates":[-97.21154,32.686192],"type":"Point"}
}