{
  "type": "Feature",
  "properties": {
    "iso:country":"US",
    "sg:address":"1927 Shadow Ln",
    "sg:city":"Richmond",
    "sg:classifiers":[
        {
            "category":"Banks & Credit Unions",
            "subcategory":"Financial Services",
            "type":"Services"
        }
    ],
    "sg:phone":"+1 281 342 2696",
    "sg:postcode":"77469",
    "sg:province":"TX",
    "sg:tags":[
        "company",
        "holding"
    ],
    "wof:name":"Powell Properties Holdings",
    "wof:placetype":"venue"
},
  "geometry": {"coordinates":[-95.773757,29.622077],"type":"Point"}
}