{
  "type": "Feature",
  "properties": {
    "iso:country":"US",
    "sg:address":"1 Blalock Cir",
    "sg:city":"Houston",
    "sg:classifiers":[
        {
            "category":"Wholesale",
            "subcategory":"Non-durable Goods",
            "type":"Manufacturing & Wholesale Goods"
        }
    ],
    "sg:phone":"+1 713 935 0700",
    "sg:postcode":"77024",
    "sg:province":"TX",
    "sg:tags":[
        "merchandise",
        "general"
    ],
    "wof:name":"J & R Traders",
    "wof:placetype":"venue"
},
  "geometry": {"coordinates":[-95.52224699999999,29.763119],"type":"Point"}
}