{
  "type": "Feature",
  "properties": {
    "iso:country":"US",
    "sg:address":"7603 Tussendo Dr",
    "sg:city":"Houston",
    "sg:classifiers":[
        {
            "category":"Professional",
            "subcategory":"Business Services",
            "type":"Services"
        }
    ],
    "sg:phone":"+1 281 530 5976",
    "sg:postcode":"77083",
    "sg:province":"TX",
    "wof:name":"Sam Ilampour",
    "wof:placetype":"venue"
},
  "geometry": {"coordinates":[-95.62734500000001,29.695519],"type":"Point"}
}