{
  "type": "Feature",
  "properties": {
    "iso:country":"US",
    "sg:address":"28145 State Highway 249",
    "sg:city":"Tomball",
    "sg:classifiers":[
        {
            "category":"Retail",
            "subcategory":"Laundry & Dry Cleaning",
            "type":"Services"
        }
    ],
    "sg:phone":"+1 281 357 8600",
    "sg:postcode":"77375",
    "sg:province":"TX",
    "sg:tags":[
        "cleaner",
        "commercial"
    ],
    "wof:name":"Tomball Cleaners",
    "wof:placetype":"venue"
},
  "geometry": {"coordinates":[-95.63076100000001,30.082815],"type":"Point"}
}