{
  "type": "Feature",
  "properties": {
    "iso:country":"US",
    "sg:address":"500 State Hwy 35",
    "sg:city":"Port Lavaca",
    "sg:classifiers":[
        {
            "category":"Real Estate",
            "subcategory":"Real Estate Agent",
            "type":"Services"
        }
    ],
    "sg:phone":"+1 361 552 6313",
    "sg:postcode":"77979",
    "sg:province":"TX",
    "wof:name":"Russell Cain Real Estate",
    "wof:placetype":"venue"
},
  "geometry": {"coordinates":[-96.632301,28.630624],"type":"Point"}
}