{
  "type": "Feature",
  "properties": {
    "iso:country":"US",
    "sg:address":"1404 Forest Ln",
    "sg:city":"Garland",
    "sg:classifiers":[
        {
            "category":"Insurance",
            "subcategory":"Hazard Insurance",
            "type":"Services"
        }
    ],
    "sg:phone":"+1 972 272 6200",
    "sg:postcode":"75042",
    "sg:province":"TX",
    "sg:tags":[
        "bond"
    ],
    "wof:name":"Ensearch Bail Bonds",
    "wof:placetype":"venue"
},
  "geometry": {"coordinates":[-96.64966699999999,32.909649],"type":"Point"}
}