{
  "type": "Feature",
  "properties": {
    "iso:country":"US",
    "sg:address":"10939 Scarsdale Blvd",
    "sg:city":"Houston",
    "sg:classifiers":[
        {
            "category":"Personal",
            "subcategory":"Beauty Salon",
            "type":"Services"
        }
    ],
    "sg:phone":"+1 281 484 1001",
    "sg:postcode":"77089",
    "sg:province":"TX",
    "sg:tags":[
        "shop"
    ],
    "wof:name":"Julienas Hair Salon",
    "wof:placetype":"venue"
},
  "geometry": {"coordinates":[-95.21326999999999,29.585054],"type":"Point"}
}