{
  "type": "Feature",
  "properties": {
    "iso:country":"US",
    "sg:address":"7823 Capri Cir",
    "sg:city":"Houston",
    "sg:classifiers":[
        {
            "category":"Food & Beverages",
            "subcategory":"Groceries & Convenience Stores",
            "type":"Retail Goods"
        }
    ],
    "sg:phone":"+1 713 733 2434",
    "sg:postcode":"77095",
    "sg:province":"TX",
    "sg:tags":[
        "eating"
    ],
    "wof:name":"Cullen Supermarket",
    "wof:placetype":"venue"
},
  "geometry": {"coordinates":[-95.625531,29.89094],"type":"Point"}
}