{
  "type": "Feature",
  "properties": {
    "iso:country":"US",
    "sg:address":"1856 Royal Ln",
    "sg:city":"Dallas",
    "sg:classifiers":[
        {
            "category":"Building & Trades",
            "subcategory":"Landscaping Services",
            "type":"Services"
        }
    ],
    "sg:phone":"+1 972 831 9393",
    "sg:postcode":"75229",
    "sg:province":"TX",
    "sg:tags":[
        "landscape"
    ],
    "wof:name":"Four Leaf Landscape Services L",
    "wof:placetype":"venue"
},
  "geometry": {"coordinates":[-96.91787100000001,32.895565],"type":"Point"}
}