{
  "type": "Feature",
  "properties": {
    "iso:country":"US",
    "sg:address":"2945 E Meadows Blvd",
    "sg:city":"Mesquite",
    "sg:classifiers":[
        {
            "category":"Professional",
            "subcategory":"Management & Consulting",
            "type":"Services"
        },
        {
            "category":"Home & Garden",
            "subcategory":"Garden Supply",
            "type":"Retail Goods"
        }
    ],
    "sg:phone":"+1 972 681 5511",
    "sg:postcode":"75150",
    "sg:province":"TX",
    "sg:tags":[
        "sprinkler",
        "business"
    ],
    "sg:website":"www.johndeerelandscapes.com",
    "wof:name":"John Deere Landscapes Inc",
    "wof:placetype":"venue"
},
  "geometry": {"coordinates":[-96.660703,32.803099],"type":"Point"}
}