{
  "type": "Feature",
  "properties": {
    "iso:country":"US",
    "sg:address":"1627 Spur St",
    "sg:city":"New Braunfels",
    "sg:classifiers":[
        {
            "category":"Personal",
            "subcategory":"Beauty Salon",
            "type":"Services"
        }
    ],
    "sg:phone":"+1 830 608 9257",
    "sg:postcode":"78130",
    "sg:province":"TX",
    "wof:name":"April Marie's Cut 'n Curls",
    "wof:placetype":"venue"
},
  "geometry": {"coordinates":[-98.137733,29.689409],"type":"Point"}
}