{
  "type": "Feature",
  "properties": {
    "iso:country":"US",
    "sg:address":"400 S Conway Ave",
    "sg:city":"Mission",
    "sg:classifiers":[
        {
            "category":"Insurance",
            "subcategory":"Insurance Agent",
            "type":"Services"
        }
    ],
    "sg:phone":"+1 956 583 3000",
    "sg:postcode":"78572",
    "sg:province":"TX",
    "sg:website":"www.fredloya.com",
    "wof:name":"Loya Fred Insurance",
    "wof:placetype":"venue"
},
  "geometry": {"coordinates":[-98.32801600000001,26.203061],"type":"Point"}
}