{
  "type": "Feature",
  "properties": {
    "iso:country":"US",
    "sg:address":"534 S Elm St",
    "sg:city":"Denton",
    "sg:classifiers":[
        {
            "category":"Professional",
            "subcategory":"Lawyer & Legal Services",
            "type":"Services"
        }
    ],
    "sg:phone":"+1 940 382 7297",
    "sg:postcode":"76201",
    "sg:province":"TX",
    "sg:tags":[
        "attorney",
        "law",
        "estate",
        "family",
        "planning",
        "criminal"
    ],
    "sg:website":"http://www.sharonlwilsonlaw.com",
    "wof:name":"Wilson Sharon L",
    "wof:placetype":"venue"
},
  "geometry": {"coordinates":[-97.133764,33.210165],"type":"Point"}
}