{
  "type": "Feature",
  "properties": {
    "iso:country":"US",
    "sg:address":"2718 N Hill Ter",
    "sg:city":"Cleburne",
    "sg:classifiers":[
        {
            "category":"Building & Trades",
            "subcategory":"Construction",
            "type":"Services"
        }
    ],
    "sg:phone":"+1 817 641 7438",
    "sg:postcode":"76031",
    "sg:province":"TX",
    "sg:tags":[
        "concrete",
        "contractor"
    ],
    "wof:name":"Marcus Lane Construction",
    "wof:placetype":"venue"
},
  "geometry": {"coordinates":[-97.323553,32.418829],"type":"Point"}
}