{
  "type": "Feature",
  "properties": {
    "iso:country":"US",
    "sg:address":"112 E Davis St",
    "sg:city":"Mesquite",
    "sg:classifiers":[
        {
            "category":"Retail",
            "subcategory":"Auto Repair",
            "type":"Services"
        }
    ],
    "sg:phone":"+1 972 557 3565",
    "sg:postcode":"75149",
    "sg:province":"TX",
    "wof:name":"Ferry's Aluminum Repair",
    "wof:placetype":"venue"
},
  "geometry": {"coordinates":[-96.598508,32.765973],"type":"Point"}
}