{
  "type": "Feature",
  "properties": {
    "iso:country":"US",
    "sg:address":"3012 S Flores St",
    "sg:city":"San Antonio",
    "sg:classifiers":[
        {
            "category":"Wholesale",
            "subcategory":"Groceries",
            "type":"Manufacturing & Wholesale Goods"
        }
    ],
    "sg:phone":"+1 210 532 0332",
    "sg:postcode":"78204",
    "sg:province":"TX",
    "sg:tags":[
        "tortilla"
    ],
    "wof:name":"California Molino Tortillas",
    "wof:placetype":"venue"
},
  "geometry": {"coordinates":[-98.50407800000001,29.393855],"type":"Point"}
}