{
  "type": "Feature",
  "properties": {
    "iso:country":"US",
    "sg:address":"207 Jackson Ave",
    "sg:city":"Hereford",
    "sg:classifiers":[
        {
            "category":"Professional",
            "subcategory":"Business Services",
            "type":"Services"
        }
    ],
    "sg:phone":"+1 806 364 4473",
    "sg:postcode":"79045",
    "sg:province":"TX",
    "wof:name":"Esters Crafts",
    "wof:placetype":"venue"
},
  "geometry": {"coordinates":[-102.40256599999999,34.815051],"type":"Point"}
}