{
  "type": "Feature",
  "properties": {
    "iso:country":"US",
    "sg:address":"29801 I- 45 N",
    "sg:city":"Spring",
    "sg:classifiers":[
        {
            "category":"Insurance",
            "subcategory":"Insurance Agent",
            "type":"Services"
        }
    ],
    "sg:phone":"+1 281 367 6481",
    "sg:postcode":"77381",
    "sg:province":"TX",
    "sg:tags":[
        "processing"
    ],
    "wof:name":"American Claims Expeditors",
    "wof:placetype":"venue"
},
  "geometry": {"coordinates":[-95.45272199999999,30.181395],"type":"Point"}
}