{
  "type": "Feature",
  "properties": {
    "iso:country":"US",
    "sg:address":"1405 Gruene Rd",
    "sg:city":"New Braunfels",
    "sg:classifiers":[
        {
            "category":"Recreation",
            "type":"Entertainment"
        }
    ],
    "sg:phone":"+1 830 629 6315",
    "sg:postcode":"78130",
    "sg:province":"TX",
    "sg:tags":[
        "tours",
        "rental",
        "rafting",
        "related",
        "equipment"
    ],
    "wof:name":"Rockin R River Rides",
    "wof:placetype":"venue"
},
  "geometry": {"coordinates":[-98.114492,29.73281],"type":"Point"}
}