{
  "type": "Feature",
  "properties": {
    "iso:country":"US",
    "sg:address":"1800 Columbian Club Dr",
    "sg:city":"Carrollton",
    "sg:classifiers":[
        {
            "category":"Shopping",
            "subcategory":"Music",
            "type":"Retail Goods"
        }
    ],
    "sg:phone":"+1 972 820 5919",
    "sg:postcode":"75006",
    "sg:province":"TX",
    "sg:tags":[
        "dvd's"
    ],
    "wof:name":"Iron Mountain",
    "wof:placetype":"venue"
},
  "geometry": {"coordinates":[-96.868342,32.956105],"type":"Point"}
}