{
  "type": "Feature",
  "properties": {
    "iso:country":"US",
    "sg:address":"125 M & M Ranch Rd",
    "sg:city":"Granbury",
    "sg:classifiers":[
        {
            "category":"Professional",
            "subcategory":"Engineering",
            "type":"Services"
        }
    ],
    "sg:phone":"+1 817 578 8601",
    "sg:postcode":"76049",
    "sg:province":"TX",
    "wof:name":"Garnet Technologies Ltd",
    "wof:placetype":"venue"
},
  "geometry": {"coordinates":[-97.69846200000001,32.472853],"type":"Point"}
}