{
  "type": "Feature",
  "properties": {
    "iso:country":"US",
    "sg:address":"2627 Seagoville Rd",
    "sg:city":"Seagoville",
    "sg:classifiers":[
        {
            "category":"Building & Trades",
            "subcategory":"Electrical",
            "type":"Services"
        }
    ],
    "sg:phone":"+1 972 287 5246",
    "sg:postcode":"75159",
    "sg:province":"TX",
    "sg:tags":[
        "electric",
        "contractor"
    ],
    "wof:name":"Exousia Electrical",
    "wof:placetype":"venue"
},
  "geometry": {"coordinates":[-96.572239,32.671709],"type":"Point"}
}