{
  "type": "Feature",
  "properties": {
    "iso:country":"US",
    "sg:address":"1117 W 6th St",
    "sg:city":"Irving",
    "sg:classifiers":[
        {
            "category":"Shopping",
            "subcategory":"Mobile Phones",
            "type":"Retail Goods"
        }
    ],
    "sg:phone":"+1 972 253 2800",
    "sg:postcode":"75060",
    "sg:province":"TX",
    "wof:name":"Sun Telecom DBA Metro Pcs",
    "wof:placetype":"venue"
},
  "geometry": {"coordinates":[-96.959481,32.808817],"type":"Point"}
}