{
  "type": "Feature",
  "properties": {
    "iso:country":"US",
    "sg:address":"8106 Ashley Circle Dr N",
    "sg:city":"Houston",
    "sg:classifiers":[
        {
            "category":"Home & Garden",
            "subcategory":"Building Materials",
            "type":"Retail Goods"
        }
    ],
    "sg:phone":"+1 713 779 2217",
    "sg:postcode":"77071",
    "sg:province":"TX",
    "wof:name":"Homer Paints",
    "wof:placetype":"venue"
},
  "geometry": {"coordinates":[-95.520354,29.645931],"type":"Point"}
}