{
  "type": "Feature",
  "properties": {
    "iso:country":"US",
    "sg:address":"5811 East Dr",
    "sg:city":"Laredo",
    "sg:classifiers":[
        {
            "category":"Freight",
            "type":"Transportation"
        }
    ],
    "sg:phone":"+1 956 725 2010",
    "sg:postcode":"78041",
    "sg:province":"TX",
    "wof:name":"M G Forwarding Agency",
    "wof:placetype":"venue"
},
  "geometry": {"coordinates":[-99.474873,27.551442],"type":"Point"}
}