{
  "type": "Feature",
  "properties": {
    "iso:country":"US",
    "sg:address":"6816 Oak Crest Dr E",
    "sg:city":"Fort Worth",
    "sg:classifiers":[
        {
            "category":"Building & Trades",
            "subcategory":"Construction",
            "type":"Services"
        }
    ],
    "sg:phone":"+1 817 478 2203",
    "sg:postcode":"76140",
    "sg:province":"TX",
    "sg:tags":[
        "contractor"
    ],
    "wof:name":"Eagle Drywall",
    "wof:placetype":"venue"
},
  "geometry": {"coordinates":[-97.239118,32.662368],"type":"Point"}
}