{
  "type": "Feature",
  "properties": {
    "iso:country":"US",
    "sg:address":"1106 Callahan Ave",
    "sg:city":"Conroe",
    "sg:classifiers":[
        {
            "category":"Arts & Performance",
            "subcategory":"Theater",
            "type":"Entertainment"
        }
    ],
    "sg:phone":"+1 936 441 4235",
    "sg:postcode":"77301",
    "sg:province":"TX",
    "sg:tags":[
        "group"
    ],
    "wof:name":"Discount Djz",
    "wof:placetype":"venue"
},
  "geometry": {"coordinates":[-95.467707,30.320699],"type":"Point"}
}