{
  "type": "Feature",
  "properties": {
    "iso:country":"US",
    "sg:address":"6720 Bracknell St",
    "sg:city":"Houston",
    "sg:classifiers":[
        {
            "category":"Mining & Drilling",
            "type":"Manufacturing & Wholesale Goods"
        }
    ],
    "sg:phone":"+1 713 947 2200",
    "sg:postcode":"77017",
    "sg:province":"TX",
    "sg:tags":[
        "inspector",
        "oil"
    ],
    "wof:name":"Aivepet USA",
    "wof:placetype":"venue"
},
  "geometry": {"coordinates":[-95.25151099999999,29.669942],"type":"Point"}
}