{
  "type": "Feature",
  "properties": {
    "iso:country":"US",
    "sg:address":"1135 Gunter St",
    "sg:city":"Austin",
    "sg:classifiers":[
        {
            "category":"Local Transit",
            "type":"Transportation"
        }
    ],
    "sg:phone":"+1 512 928 8893",
    "sg:postcode":"78702",
    "sg:province":"TX",
    "sg:tags":[
        "passenger"
    ],
    "wof:name":"Star Shuttle Inc",
    "wof:placetype":"venue"
},
  "geometry": {"coordinates":[-97.697564,30.267767],"type":"Point"}
}