{
  "type": "Feature",
  "properties": {
    "iso:country":"US",
    "sg:address":"3030 Greenridge Dr",
    "sg:city":"Houston",
    "sg:classifiers":[
        {
            "category":"Building & Trades",
            "subcategory":"Construction",
            "type":"Services"
        }
    ],
    "sg:phone":"+1 281 723 9898",
    "sg:postcode":"77057",
    "sg:province":"TX",
    "sg:tags":[
        "ready",
        "apartment",
        "get"
    ],
    "wof:name":"Asaka Services",
    "wof:placetype":"venue"
},
  "geometry": {"coordinates":[-95.489887,29.733429],"type":"Point"}
}