{
  "type": "Feature",
  "properties": {
    "iso:country":"US",
    "sg:address":"2705 N Dallas Ave",
    "sg:city":"Lancaster",
    "sg:classifiers":[
        {
            "category":"Food & Beverages",
            "subcategory":"Groceries & Convenience Stores",
            "type":"Retail Goods"
        }
    ],
    "sg:phone":"+1 972 227 1332",
    "sg:postcode":"75134",
    "sg:province":"TX",
    "wof:name":"Lancaster Express",
    "wof:placetype":"venue"
},
  "geometry": {"coordinates":[-96.768525,32.620255],"type":"Point"}
}