{
  "type": "Feature",
  "properties": {
    "iso:country":"US",
    "sg:address":"2825 Colquitt St",
    "sg:city":"Houston",
    "sg:classifiers":[
        {
            "category":"Arts & Performance",
            "subcategory":"Art Gallery",
            "type":"Entertainment"
        }
    ],
    "sg:phone":"+1 713 526 4146",
    "sg:postcode":"77098",
    "sg:province":"TX",
    "sg:website":"www.mkgart.com",
    "wof:name":"M K G Art Management",
    "wof:placetype":"venue"
},
  "geometry": {"coordinates":[-95.42130299999999,29.734699],"type":"Point"}
}