{
  "type": "Feature",
  "properties": {
    "iso:country":"US",
    "sg:address":"530 Chimney Rock Rd",
    "sg:city":"Houston",
    "sg:classifiers":[
        {
            "category":"Personal",
            "subcategory":"Beauty Salon",
            "type":"Services"
        }
    ],
    "sg:phone":"+1 713 785 4450",
    "sg:postcode":"77056",
    "sg:province":"TX",
    "sg:tags":[
        "unisex",
        "hair"
    ],
    "wof:name":"J Christopher Hair Studio",
    "wof:placetype":"venue"
},
  "geometry": {"coordinates":[-95.47827700000001,29.766111],"type":"Point"}
}