{
  "type": "Feature",
  "properties": {
    "iso:country":"US",
    "sg:address":"7500 Pinemont Dr",
    "sg:city":"Houston",
    "sg:classifiers":[
        {
            "category":"Retail",
            "subcategory":"Repair Shop",
            "type":"Services"
        }
    ],
    "sg:phone":"+1 832 338 5381",
    "sg:postcode":"77040",
    "sg:province":"TX",
    "sg:tags":[
        "janitorial",
        "cleaning"
    ],
    "wof:name":"Vector Cleaning Services",
    "wof:placetype":"venue"
},
  "geometry": {"coordinates":[-95.504411,29.841413],"type":"Point"}
}