{
  "type": "Feature",
  "properties": {
    "iso:country":"US",
    "sg:address":"4575 Claire Chennault St",
    "sg:city":"Addison",
    "sg:classifiers":[
        {
            "category":"Building & Trades",
            "subcategory":"Equipment Rental",
            "type":"Services"
        }
    ],
    "sg:phone":"+1 972 931 8890",
    "sg:postcode":"75001",
    "sg:province":"TX",
    "wof:name":"Aquila Leasing Co Inc",
    "wof:placetype":"venue"
},
  "geometry": {"coordinates":[-96.83490999999999,32.973079],"type":"Point"}
}