{
  "type": "Feature",
  "properties": {
    "iso:country":"US",
    "sg:address":"5709 Village Way Dr",
    "sg:city":"Katy",
    "sg:classifiers":[
        {
            "category":"Building & Trades",
            "subcategory":"Construction",
            "type":"Services"
        }
    ],
    "sg:phone":"+1 281 850 8194",
    "sg:postcode":"77493",
    "sg:province":"TX",
    "sg:tags":[
        "house"
    ],
    "wof:name":"Classic Homes",
    "wof:placetype":"venue"
},
  "geometry": {"coordinates":[-95.823027,29.81048],"type":"Point"}
}