{
  "type": "Feature",
  "properties": {
    "iso:country":"US",
    "sg:address":"5616 Boca Raton Blvd",
    "sg:city":"Fort Worth",
    "sg:classifiers":[
        {
            "category":"Restaurant",
            "type":"Food & Drink"
        }
    ],
    "sg:phone":"+1 817 496 3286",
    "sg:postcode":"76112",
    "sg:province":"TX",
    "sg:tags":[
        "eating"
    ],
    "wof:name":"Catering 4u",
    "wof:placetype":"venue"
},
  "geometry": {"coordinates":[-97.235275,32.764155],"type":"Point"}
}