{
  "type": "Feature",
  "properties": {
    "iso:country":"US",
    "sg:address":"17024 S Ridge Ln",
    "sg:city":"Austin",
    "sg:classifiers":[
        {
            "category":"Building & Trades",
            "subcategory":"Equipment Rental",
            "type":"Services"
        }
    ],
    "sg:phone":"+1 512 266 7672",
    "sg:postcode":"78734",
    "sg:province":"TX",
    "sg:tags":[
        "crane"
    ],
    "wof:name":"Lift Me Up",
    "wof:placetype":"venue"
},
  "geometry": {"coordinates":[-97.944681,30.419124],"type":"Point"}
}