{
  "type": "Feature",
  "properties": {
    "iso:country":"US",
    "sg:address":"15008 Cordero Dr",
    "sg:city":"Austin",
    "sg:classifiers":[
        {
            "category":"Wholesale",
            "subcategory":"Computers",
            "type":"Manufacturing & Wholesale Goods"
        }
    ],
    "sg:phone":"+1 512 733 1720",
    "sg:postcode":"78717",
    "sg:province":"TX",
    "wof:name":"Tripp Lite",
    "wof:placetype":"venue"
},
  "geometry": {"coordinates":[-97.76737900000001,30.491354],"type":"Point"}
}