{
  "type": "Feature",
  "properties": {
    "iso:country":"US",
    "sg:address":"2105 W Davis St",
    "sg:city":"Dallas",
    "sg:classifiers":[
        {
            "category":"Real Estate",
            "subcategory":"Real Estate Operator",
            "type":"Services"
        }
    ],
    "sg:phone":"+1 214 942 3833",
    "sg:postcode":"75208",
    "sg:province":"TX",
    "sg:tags":[
        "building",
        "apartment"
    ],
    "wof:name":"Acorn Tree Apartments",
    "wof:placetype":"venue"
},
  "geometry": {"coordinates":[-96.853737,32.749674],"type":"Point"}
}