{
  "type": "Feature",
  "properties": {
    "iso:country":"US",
    "sg:address":"11035 Northwest Fwy",
    "sg:city":"Houston",
    "sg:classifiers":[
        {
            "category":"Home & Garden",
            "subcategory":"Home Furnishings",
            "type":"Retail Goods"
        }
    ],
    "sg:phone":"+1 713 690 3489",
    "sg:postcode":"77092",
    "sg:province":"TX",
    "sg:tags":[
        "bedspread"
    ],
    "wof:name":"Mattress Firm",
    "wof:placetype":"venue"
},
  "geometry": {"coordinates":[-95.467997,29.818193],"type":"Point"}
}