{
  "type": "Feature",
  "properties": {
    "iso:country":"US",
    "sg:address":"270 N Timberlane St",
    "sg:city":"Vidor",
    "sg:classifiers":[
        {
            "category":"Manufacturing",
            "subcategory":"Tools & Machinery",
            "type":"Manufacturing & Wholesale Goods"
        }
    ],
    "sg:phone":"+1 409 769 2718",
    "sg:postcode":"77662",
    "sg:province":"TX",
    "sg:tags":[
        "mfg",
        "industrial",
        "supply"
    ],
    "wof:name":"Xtreme Machines",
    "wof:placetype":"venue"
},
  "geometry": {"coordinates":[-93.98063,30.137068],"type":"Point"}
}