{
  "type": "Feature",
  "properties": {
    "iso:country":"US",
    "sg:address":"7427 Northallerton",
    "sg:city":"Converse",
    "sg:classifiers":[
        {
            "category":"Utilities",
            "subcategory":"Telephone",
            "type":"Services"
        }
    ],
    "sg:phone":"+1 210 659 6750",
    "sg:postcode":"78109",
    "sg:province":"TX",
    "sg:tags":[
        "telecommunication"
    ],
    "wof:name":"Telcordia Technologies",
    "wof:placetype":"venue"
},
  "geometry": {"coordinates":[-98.317256,29.50527],"type":"Point"}
}