{
  "type": "Feature",
  "properties": {
    "iso:country":"US",
    "sg:address":"811 S Lamar Blvd",
    "sg:city":"Austin",
    "sg:classifiers":[
        {
            "category":"Autos & Motor Vehicles",
            "subcategory":"Automobile Sales",
            "type":"Retail Goods"
        }
    ],
    "sg:phone":"+1 512 441 3536",
    "sg:postcode":"78704",
    "sg:province":"TX",
    "sg:tags":[
        "used"
    ],
    "wof:name":"Rice Auto Sales",
    "wof:placetype":"venue"
},
  "geometry": {"coordinates":[-97.76138,30.256107],"type":"Point"}
}