{
  "type": "Feature",
  "properties": {
    "iso:country":"US",
    "sg:address":"802 Fisher Rd",
    "sg:city":"Longview",
    "sg:classifiers":[
        {
            "category":"Real Estate",
            "subcategory":"Real Estate Agent",
            "type":"Services"
        }
    ],
    "sg:phone":"+1 903 759 6813",
    "sg:postcode":"75604",
    "sg:province":"TX",
    "wof:name":"Perritt Enterprises",
    "wof:placetype":"venue"
},
  "geometry": {"coordinates":[-94.81871700000001,32.501247],"type":"Point"}
}