{
  "type": "Feature",
  "properties": {
    "iso:country":"US",
    "sg:address":"1712 New Boston Rd",
    "sg:city":"Texarkana",
    "sg:classifiers":[
        {
            "category":"Shopping",
            "subcategory":"Clothing, Apparel, & Fashions",
            "type":"Retail Goods"
        }
    ],
    "sg:phone":"+1 903 792 8424",
    "sg:postcode":"75501",
    "sg:province":"TX",
    "wof:name":"Fashion Cents",
    "wof:placetype":"venue"
},
  "geometry": {"coordinates":[-94.06173699999999,33.435014],"type":"Point"}
}