{
  "type": "Feature",
  "properties": {
    "iso:country":"US",
    "sg:address":"11528 Henderson Dr",
    "sg:city":"Frisco",
    "sg:classifiers":[
        {
            "category":"Shopping",
            "subcategory":"Florist",
            "type":"Retail Goods"
        }
    ],
    "sg:phone":"+1 214 783 3081",
    "sg:postcode":"75035",
    "sg:province":"TX",
    "wof:name":"Rountree & Benson Designs",
    "wof:placetype":"venue"
},
  "geometry": {"coordinates":[-96.77904100000001,33.178497],"type":"Point"}
}