{
  "type": "Feature",
  "properties": {
    "iso:country":"US",
    "sg:address":"1826 County Road 393",
    "sg:city":"Stephenville",
    "sg:classifiers":[
        {
            "category":"Farming",
            "subcategory":"Livestock Farm",
            "type":"Manufacturing & Wholesale Goods"
        }
    ],
    "sg:phone":"+1 254 968 3516",
    "sg:postcode":"76401",
    "sg:province":"TX",
    "sg:tags":[
        "ranch"
    ],
    "wof:name":"Great Southern Dairy",
    "wof:placetype":"venue"
},
  "geometry": {"coordinates":[-98.26109599999999,32.245163],"type":"Point"}
}