{
  "type": "Feature",
  "properties": {
    "iso:country":"US",
    "sg:address":"187 Shale Run Pl",
    "sg:city":"Spring",
    "sg:classifiers":[
        {
            "category":"Professional",
            "subcategory":"Advertising",
            "type":"Services"
        }
    ],
    "sg:phone":"+1 281 298 9657",
    "sg:postcode":"77382",
    "sg:province":"TX",
    "sg:tags":[
        "mail",
        "direct"
    ],
    "wof:name":"Proforma Innovative Solutions",
    "wof:placetype":"venue"
},
  "geometry": {"coordinates":[-95.54813,30.215107],"type":"Point"}
}