{
  "type": "Feature",
  "properties": {
    "iso:country":"US",
    "sg:address":"300 E Sunset Rd",
    "sg:city":"El Paso",
    "sg:classifiers":[
        {
            "category":"Shopping",
            "type":"Retail Goods"
        }
    ],
    "sg:phone":"+1 915 584 6646",
    "sg:postcode":"79922",
    "sg:province":"TX",
    "sg:tags":[
        "repair",
        "maintenance"
    ],
    "wof:name":"Radio Tech & Communications",
    "wof:placetype":"venue"
},
  "geometry": {"coordinates":[-106.570525,31.83757],"type":"Point"}
}