{
  "type": "Feature",
  "properties": {
    "iso:country":"US",
    "sg:address":"7804 Scott St",
    "sg:city":"Houston",
    "sg:classifiers":[
        {
            "category":"Professional",
            "subcategory":"Lawyer & Legal Services",
            "type":"Services"
        }
    ],
    "sg:phone":"+1 713 669 1066",
    "sg:postcode":"77051",
    "sg:province":"TX",
    "wof:name":"Jules Johnson Law Firm PLLC",
    "wof:placetype":"venue"
},
  "geometry": {"coordinates":[-95.367396,29.678114],"type":"Point"}
}